Classfile /Users/mw/Projects/slang-braindump/.jar/jar11/assemble/slang-braindump/assemble/content/org/sireum/package$$Double2F64.class
  Last modified May 29, 2022; size 4695 bytes
  SHA-256 checksum ce6e9efd6a6733547458e5055ccf2df4704ff9db93aac3db3d4a2c8309b352ff
  Compiled from "package.scala"
public final class org.sireum.package$$Double2F64
  minor version: 0
  major version: 52
  flags: (0x0031) ACC_PUBLIC, ACC_FINAL, ACC_SUPER
  this_class: #2                          // org/sireum/package$$Double2F64
  super_class: #4                         // java/lang/Object
  interfaces: 0, fields: 1, methods: 25, attributes: 4
Constant pool:
    #1 = Utf8               org/sireum/package$$Double2F64
    #2 = Class              #1            // org/sireum/package$$Double2F64
    #3 = Utf8               java/lang/Object
    #4 = Class              #3            // java/lang/Object
    #5 = Utf8               package.scala
    #6 = Utf8               org/sireum/package
    #7 = Class              #6            // org/sireum/package
    #8 = Utf8               $Double2F64
    #9 = Utf8               org/sireum/package$$Double2F64$
   #10 = Class              #9            // org/sireum/package$$Double2F64$
   #11 = Utf8               $Double2F64$
   #12 = Utf8               _value
   #13 = Utf8               D
   #14 = Utf8               ()D
   #15 = NameAndType        #12:#13       // _value:D
   #16 = Fieldref           #2.#15        // org/sireum/package$$Double2F64._value:D
   #17 = Utf8               this
   #18 = Utf8               Lorg/sireum/package$$Double2F64;
   #19 = Utf8               hash
   #20 = Utf8               ()Lorg/sireum/Z;
   #21 = Utf8               MODULE$
   #22 = Utf8               Lorg/sireum/package$$Double2F64$;
   #23 = NameAndType        #21:#22       // MODULE$:Lorg/sireum/package$$Double2F64$;
   #24 = Fieldref           #10.#23       // org/sireum/package$$Double2F64$.MODULE$:Lorg/sireum/package$$Double2F64$;
   #25 = NameAndType        #12:#14       // _value:()D
   #26 = Methodref          #2.#25        // org/sireum/package$$Double2F64._value:()D
   #27 = Utf8               hash$extension
   #28 = Utf8               (D)Lorg/sireum/Z;
   #29 = NameAndType        #27:#28       // hash$extension:(D)Lorg/sireum/Z;
   #30 = Methodref          #10.#29       // org/sireum/package$$Double2F64$.hash$extension:(D)Lorg/sireum/Z;
   #31 = Utf8               string
   #32 = Utf8               ()Ljava/lang/String;
   #33 = Utf8               string$extension
   #34 = Utf8               (D)Ljava/lang/String;
   #35 = NameAndType        #33:#34       // string$extension:(D)Ljava/lang/String;
   #36 = Methodref          #10.#35       // org/sireum/package$$Double2F64$.string$extension:(D)Ljava/lang/String;
   #37 = Utf8               $less
   #38 = Utf8               (D)Z
   #39 = Utf8               other
   #40 = Utf8               $less$extension
   #41 = Utf8               (DD)Z
   #42 = NameAndType        #40:#41       // $less$extension:(DD)Z
   #43 = Methodref          #10.#42       // org/sireum/package$$Double2F64$.$less$extension:(DD)Z
   #44 = Utf8               $less$eq
   #45 = Utf8               $less$eq$extension
   #46 = NameAndType        #45:#41       // $less$eq$extension:(DD)Z
   #47 = Methodref          #10.#46       // org/sireum/package$$Double2F64$.$less$eq$extension:(DD)Z
   #48 = Utf8               $greater
   #49 = Utf8               $greater$extension
   #50 = NameAndType        #49:#41       // $greater$extension:(DD)Z
   #51 = Methodref          #10.#50       // org/sireum/package$$Double2F64$.$greater$extension:(DD)Z
   #52 = Utf8               $greater$eq
   #53 = Utf8               $greater$eq$extension
   #54 = NameAndType        #53:#41       // $greater$eq$extension:(DD)Z
   #55 = Methodref          #10.#54       // org/sireum/package$$Double2F64$.$greater$eq$extension:(DD)Z
   #56 = Utf8               $eq$eq$eq
   #57 = Utf8               $eq$eq$eq$extension
   #58 = NameAndType        #57:#41       // $eq$eq$eq$extension:(DD)Z
   #59 = Methodref          #10.#58       // org/sireum/package$$Double2F64$.$eq$eq$eq$extension:(DD)Z
   #60 = Utf8               $eq$bang$eq
   #61 = Utf8               $eq$bang$eq$extension
   #62 = NameAndType        #61:#41       // $eq$bang$eq$extension:(DD)Z
   #63 = Methodref          #10.#62       // org/sireum/package$$Double2F64$.$eq$bang$eq$extension:(DD)Z
   #64 = Utf8               $plus
   #65 = Utf8               (D)D
   #66 = Utf8               $plus$extension
   #67 = Utf8               (DD)D
   #68 = NameAndType        #66:#67       // $plus$extension:(DD)D
   #69 = Methodref          #10.#68       // org/sireum/package$$Double2F64$.$plus$extension:(DD)D
   #70 = Utf8               $minus
   #71 = Utf8               $minus$extension
   #72 = NameAndType        #71:#67       // $minus$extension:(DD)D
   #73 = Methodref          #10.#72       // org/sireum/package$$Double2F64$.$minus$extension:(DD)D
   #74 = Utf8               $times
   #75 = Utf8               $times$extension
   #76 = NameAndType        #75:#67       // $times$extension:(DD)D
   #77 = Methodref          #10.#76       // org/sireum/package$$Double2F64$.$times$extension:(DD)D
   #78 = Utf8               $div
   #79 = Utf8               $div$extension
   #80 = NameAndType        #79:#67       // $div$extension:(DD)D
   #81 = Methodref          #10.#80       // org/sireum/package$$Double2F64$.$div$extension:(DD)D
   #82 = Utf8               $percent
   #83 = Utf8               $percent$extension
   #84 = NameAndType        #83:#67       // $percent$extension:(DD)D
   #85 = Methodref          #10.#84       // org/sireum/package$$Double2F64$.$percent$extension:(DD)D
   #86 = Utf8               $tilde$greater
   #87 = Utf8               (Z)Lscala/Tuple2;
   #88 = Utf8               (Z)Lscala/Tuple2<Lorg/sireum/F64;Lorg/sireum/B;>;
   #89 = Utf8               o
   #90 = Utf8               $tilde$greater$extension
   #91 = Utf8               (DZ)Lscala/Tuple2;
   #92 = NameAndType        #90:#91       // $tilde$greater$extension:(DZ)Lscala/Tuple2;
   #93 = Methodref          #10.#92       // org/sireum/package$$Double2F64$.$tilde$greater$extension:(DZ)Lscala/Tuple2;
   #94 = Utf8               Z
   #95 = Utf8               (C)Lscala/Tuple2;
   #96 = Utf8               (C)Lscala/Tuple2<Lorg/sireum/F64;Lorg/sireum/C;>;
   #97 = Utf8               (DC)Lscala/Tuple2;
   #98 = NameAndType        #90:#97       // $tilde$greater$extension:(DC)Lscala/Tuple2;
   #99 = Methodref          #10.#98       // org/sireum/package$$Double2F64$.$tilde$greater$extension:(DC)Lscala/Tuple2;
  #100 = Utf8               C
  #101 = Utf8               (I)Lscala/Tuple2;
  #102 = Utf8               (I)Lscala/Tuple2<Lorg/sireum/F64;Lorg/sireum/Z;>;
  #103 = Utf8               (DI)Lscala/Tuple2;
  #104 = NameAndType        #90:#103      // $tilde$greater$extension:(DI)Lscala/Tuple2;
  #105 = Methodref          #10.#104      // org/sireum/package$$Double2F64$.$tilde$greater$extension:(DI)Lscala/Tuple2;
  #106 = Utf8               I
  #107 = Utf8               (J)Lscala/Tuple2;
  #108 = Utf8               (J)Lscala/Tuple2<Lorg/sireum/F64;Lorg/sireum/Z;>;
  #109 = Utf8               (DJ)Lscala/Tuple2;
  #110 = NameAndType        #90:#109      // $tilde$greater$extension:(DJ)Lscala/Tuple2;
  #111 = Methodref          #10.#110      // org/sireum/package$$Double2F64$.$tilde$greater$extension:(DJ)Lscala/Tuple2;
  #112 = Utf8               J
  #113 = Utf8               (F)Lscala/Tuple2;
  #114 = Utf8               (F)Lscala/Tuple2<Lorg/sireum/F64;Lorg/sireum/F32;>;
  #115 = Utf8               (DF)Lscala/Tuple2;
  #116 = NameAndType        #90:#115      // $tilde$greater$extension:(DF)Lscala/Tuple2;
  #117 = Methodref          #10.#116      // org/sireum/package$$Double2F64$.$tilde$greater$extension:(DF)Lscala/Tuple2;
  #118 = Utf8               F
  #119 = Utf8               (D)Lscala/Tuple2;
  #120 = Utf8               (D)Lscala/Tuple2<Lorg/sireum/F64;Lorg/sireum/F64;>;
  #121 = Utf8               (DD)Lscala/Tuple2;
  #122 = NameAndType        #90:#121      // $tilde$greater$extension:(DD)Lscala/Tuple2;
  #123 = Methodref          #10.#122      // org/sireum/package$$Double2F64$.$tilde$greater$extension:(DD)Lscala/Tuple2;
  #124 = Utf8               (Ljava/lang/String;)Lscala/Tuple2;
  #125 = Utf8               (Ljava/lang/String;)Lscala/Tuple2<Lorg/sireum/F64;Lorg/sireum/String;>;
  #126 = Utf8               (DLjava/lang/String;)Lscala/Tuple2;
  #127 = NameAndType        #90:#126      // $tilde$greater$extension:(DLjava/lang/String;)Lscala/Tuple2;
  #128 = Methodref          #10.#127      // org/sireum/package$$Double2F64$.$tilde$greater$extension:(DLjava/lang/String;)Lscala/Tuple2;
  #129 = Utf8               Ljava/lang/String;
  #130 = Utf8               (Ljava/lang/Object;)Lscala/Tuple2;
  #131 = Utf8               <T:Ljava/lang/Object;>(TT;)Lscala/Tuple2<Lorg/sireum/F64;TT;>;
  #132 = Utf8               (DLjava/lang/Object;)Lscala/Tuple2;
  #133 = NameAndType        #90:#132      // $tilde$greater$extension:(DLjava/lang/Object;)Lscala/Tuple2;
  #134 = Methodref          #10.#133      // org/sireum/package$$Double2F64$.$tilde$greater$extension:(DLjava/lang/Object;)Lscala/Tuple2;
  #135 = Utf8               Ljava/lang/Object;
  #136 = Utf8               hashCode
  #137 = Utf8               ()I
  #138 = Utf8               hashCode$extension
  #139 = Utf8               (D)I
  #140 = NameAndType        #138:#139     // hashCode$extension:(D)I
  #141 = Methodref          #10.#140      // org/sireum/package$$Double2F64$.hashCode$extension:(D)I
  #142 = Utf8               equals
  #143 = Utf8               (Ljava/lang/Object;)Z
  #144 = Utf8               x$1
  #145 = Utf8               equals$extension
  #146 = Utf8               (DLjava/lang/Object;)Z
  #147 = NameAndType        #145:#146     // equals$extension:(DLjava/lang/Object;)Z
  #148 = Methodref          #10.#147      // org/sireum/package$$Double2F64$.equals$extension:(DLjava/lang/Object;)Z
  #149 = Utf8               <init>
  #150 = Utf8               (D)V
  #151 = Utf8               ()V
  #152 = NameAndType        #149:#151     // "<init>":()V
  #153 = Methodref          #4.#152       // java/lang/Object."<init>":()V
  #154 = Utf8               Code
  #155 = Utf8               LineNumberTable
  #156 = Utf8               LocalVariableTable
  #157 = Utf8               MethodParameters
  #158 = Utf8               Signature
  #159 = Utf8               InnerClasses
  #160 = Utf8               SourceFile
  #161 = Utf8               ScalaInlineInfo
  #162 = Utf8               Scala
{
  private final double _value;
    descriptor: D
    flags: (0x0012) ACC_PRIVATE, ACC_FINAL

  public double _value();
    descriptor: ()D
    flags: (0x0001) ACC_PUBLIC
    Code:
      stack=2, locals=1, args_size=1
         0: aload_0
         1: getfield      #16                 // Field _value:D
         4: dreturn
      LineNumberTable:
        line 360: 0
      LocalVariableTable:
        Start  Length  Slot  Name   Signature
            0       5     0  this   Lorg/sireum/package$$Double2F64;

  public org.sireum.Z hash();
    descriptor: ()Lorg/sireum/Z;
    flags: (0x0001) ACC_PUBLIC
    Code:
      stack=3, locals=1, args_size=1
         0: getstatic     #24                 // Field org/sireum/package$$Double2F64$.MODULE$:Lorg/sireum/package$$Double2F64$;
         3: aload_0
         4: invokevirtual #26                 // Method _value:()D
         7: invokevirtual #30                 // Method org/sireum/package$$Double2F64$.hash$extension:(D)Lorg/sireum/Z;
        10: areturn
      LineNumberTable:
        line 362: 0
      LocalVariableTable:
        Start  Length  Slot  Name   Signature
            0      11     0  this   Lorg/sireum/package$$Double2F64;

  public java.lang.String string();
    descriptor: ()Ljava/lang/String;
    flags: (0x0001) ACC_PUBLIC
    Code:
      stack=3, locals=1, args_size=1
         0: getstatic     #24                 // Field org/sireum/package$$Double2F64$.MODULE$:Lorg/sireum/package$$Double2F64$;
         3: aload_0
         4: invokevirtual #26                 // Method _value:()D
         7: invokevirtual #36                 // Method org/sireum/package$$Double2F64$.string$extension:(D)Ljava/lang/String;
        10: areturn
      LineNumberTable:
        line 364: 0
      LocalVariableTable:
        Start  Length  Slot  Name   Signature
            0      11     0  this   Lorg/sireum/package$$Double2F64;

  public boolean $less(double);
    descriptor: (D)Z
    flags: (0x0001) ACC_PUBLIC
    Code:
      stack=5, locals=3, args_size=2
         0: getstatic     #24                 // Field org/sireum/package$$Double2F64$.MODULE$:Lorg/sireum/package$$Double2F64$;
         3: aload_0
         4: invokevirtual #26                 // Method _value:()D
         7: dload_1
         8: invokevirtual #43                 // Method org/sireum/package$$Double2F64$.$less$extension:(DD)Z
        11: ireturn
      LineNumberTable:
        line 366: 0
      LocalVariableTable:
        Start  Length  Slot  Name   Signature
            0      12     0  this   Lorg/sireum/package$$Double2F64;
            0      12     1 other   D
    MethodParameters:
      Name                           Flags
      other                          final

  public boolean $less$eq(double);
    descriptor: (D)Z
    flags: (0x0001) ACC_PUBLIC
    Code:
      stack=5, locals=3, args_size=2
         0: getstatic     #24                 // Field org/sireum/package$$Double2F64$.MODULE$:Lorg/sireum/package$$Double2F64$;
         3: aload_0
         4: invokevirtual #26                 // Method _value:()D
         7: dload_1
         8: invokevirtual #47                 // Method org/sireum/package$$Double2F64$.$less$eq$extension:(DD)Z
        11: ireturn
      LineNumberTable:
        line 368: 0
      LocalVariableTable:
        Start  Length  Slot  Name   Signature
            0      12     0  this   Lorg/sireum/package$$Double2F64;
            0      12     1 other   D
    MethodParameters:
      Name                           Flags
      other                          final

  public boolean $greater(double);
    descriptor: (D)Z
    flags: (0x0001) ACC_PUBLIC
    Code:
      stack=5, locals=3, args_size=2
         0: getstatic     #24                 // Field org/sireum/package$$Double2F64$.MODULE$:Lorg/sireum/package$$Double2F64$;
         3: aload_0
         4: invokevirtual #26                 // Method _value:()D
         7: dload_1
         8: invokevirtual #51                 // Method org/sireum/package$$Double2F64$.$greater$extension:(DD)Z
        11: ireturn
      LineNumberTable:
        line 370: 0
      LocalVariableTable:
        Start  Length  Slot  Name   Signature
            0      12     0  this   Lorg/sireum/package$$Double2F64;
            0      12     1 other   D
    MethodParameters:
      Name                           Flags
      other                          final

  public boolean $greater$eq(double);
    descriptor: (D)Z
    flags: (0x0001) ACC_PUBLIC
    Code:
      stack=5, locals=3, args_size=2
         0: getstatic     #24                 // Field org/sireum/package$$Double2F64$.MODULE$:Lorg/sireum/package$$Double2F64$;
         3: aload_0
         4: invokevirtual #26                 // Method _value:()D
         7: dload_1
         8: invokevirtual #55                 // Method org/sireum/package$$Double2F64$.$greater$eq$extension:(DD)Z
        11: ireturn
      LineNumberTable:
        line 372: 0
      LocalVariableTable:
        Start  Length  Slot  Name   Signature
            0      12     0  this   Lorg/sireum/package$$Double2F64;
            0      12     1 other   D
    MethodParameters:
      Name                           Flags
      other                          final

  public boolean $eq$eq$eq(double);
    descriptor: (D)Z
    flags: (0x0001) ACC_PUBLIC
    Code:
      stack=5, locals=3, args_size=2
         0: getstatic     #24                 // Field org/sireum/package$$Double2F64$.MODULE$:Lorg/sireum/package$$Double2F64$;
         3: aload_0
         4: invokevirtual #26                 // Method _value:()D
         7: dload_1
         8: invokevirtual #59                 // Method org/sireum/package$$Double2F64$.$eq$eq$eq$extension:(DD)Z
        11: ireturn
      LineNumberTable:
        line 374: 0
      LocalVariableTable:
        Start  Length  Slot  Name   Signature
            0      12     0  this   Lorg/sireum/package$$Double2F64;
            0      12     1 other   D
    MethodParameters:
      Name                           Flags
      other                          final

  public boolean $eq$bang$eq(double);
    descriptor: (D)Z
    flags: (0x0001) ACC_PUBLIC
    Code:
      stack=5, locals=3, args_size=2
         0: getstatic     #24                 // Field org/sireum/package$$Double2F64$.MODULE$:Lorg/sireum/package$$Double2F64$;
         3: aload_0
         4: invokevirtual #26                 // Method _value:()D
         7: dload_1
         8: invokevirtual #63                 // Method org/sireum/package$$Double2F64$.$eq$bang$eq$extension:(DD)Z
        11: ireturn
      LineNumberTable:
        line 376: 0
      LocalVariableTable:
        Start  Length  Slot  Name   Signature
            0      12     0  this   Lorg/sireum/package$$Double2F64;
            0      12     1 other   D
    MethodParameters:
      Name                           Flags
      other                          final

  public double $plus(double);
    descriptor: (D)D
    flags: (0x0001) ACC_PUBLIC
    Code:
      stack=5, locals=3, args_size=2
         0: getstatic     #24                 // Field org/sireum/package$$Double2F64$.MODULE$:Lorg/sireum/package$$Double2F64$;
         3: aload_0
         4: invokevirtual #26                 // Method _value:()D
         7: dload_1
         8: invokevirtual #69                 // Method org/sireum/package$$Double2F64$.$plus$extension:(DD)D
        11: dreturn
      LineNumberTable:
        line 378: 0
      LocalVariableTable:
        Start  Length  Slot  Name   Signature
            0      12     0  this   Lorg/sireum/package$$Double2F64;
            0      12     1 other   D
    MethodParameters:
      Name                           Flags
      other                          final

  public double $minus(double);
    descriptor: (D)D
    flags: (0x0001) ACC_PUBLIC
    Code:
      stack=5, locals=3, args_size=2
         0: getstatic     #24                 // Field org/sireum/package$$Double2F64$.MODULE$:Lorg/sireum/package$$Double2F64$;
         3: aload_0
         4: invokevirtual #26                 // Method _value:()D
         7: dload_1
         8: invokevirtual #73                 // Method org/sireum/package$$Double2F64$.$minus$extension:(DD)D
        11: dreturn
      LineNumberTable:
        line 380: 0
      LocalVariableTable:
        Start  Length  Slot  Name   Signature
            0      12     0  this   Lorg/sireum/package$$Double2F64;
            0      12     1 other   D
    MethodParameters:
      Name                           Flags
      other                          final

  public double $times(double);
    descriptor: (D)D
    flags: (0x0001) ACC_PUBLIC
    Code:
      stack=5, locals=3, args_size=2
         0: getstatic     #24                 // Field org/sireum/package$$Double2F64$.MODULE$:Lorg/sireum/package$$Double2F64$;
         3: aload_0
         4: invokevirtual #26                 // Method _value:()D
         7: dload_1
         8: invokevirtual #77                 // Method org/sireum/package$$Double2F64$.$times$extension:(DD)D
        11: dreturn
      LineNumberTable:
        line 382: 0
      LocalVariableTable:
        Start  Length  Slot  Name   Signature
            0      12     0  this   Lorg/sireum/package$$Double2F64;
            0      12     1 other   D
    MethodParameters:
      Name                           Flags
      other                          final

  public double $div(double);
    descriptor: (D)D
    flags: (0x0001) ACC_PUBLIC
    Code:
      stack=5, locals=3, args_size=2
         0: getstatic     #24                 // Field org/sireum/package$$Double2F64$.MODULE$:Lorg/sireum/package$$Double2F64$;
         3: aload_0
         4: invokevirtual #26                 // Method _value:()D
         7: dload_1
         8: invokevirtual #81                 // Method org/sireum/package$$Double2F64$.$div$extension:(DD)D
        11: dreturn
      LineNumberTable:
        line 384: 0
      LocalVariableTable:
        Start  Length  Slot  Name   Signature
            0      12     0  this   Lorg/sireum/package$$Double2F64;
            0      12     1 other   D
    MethodParameters:
      Name                           Flags
      other                          final

  public double $percent(double);
    descriptor: (D)D
    flags: (0x0001) ACC_PUBLIC
    Code:
      stack=5, locals=3, args_size=2
         0: getstatic     #24                 // Field org/sireum/package$$Double2F64$.MODULE$:Lorg/sireum/package$$Double2F64$;
         3: aload_0
         4: invokevirtual #26                 // Method _value:()D
         7: dload_1
         8: invokevirtual #85                 // Method org/sireum/package$$Double2F64$.$percent$extension:(DD)D
        11: dreturn
      LineNumberTable:
        line 386: 0
      LocalVariableTable:
        Start  Length  Slot  Name   Signature
            0      12     0  this   Lorg/sireum/package$$Double2F64;
            0      12     1 other   D
    MethodParameters:
      Name                           Flags
      other                          final

  public scala.Tuple2<org.sireum.F64, org.sireum.B> $tilde$greater(boolean);
    descriptor: (Z)Lscala/Tuple2;
    flags: (0x0001) ACC_PUBLIC
    Code:
      stack=4, locals=2, args_size=2
         0: getstatic     #24                 // Field org/sireum/package$$Double2F64$.MODULE$:Lorg/sireum/package$$Double2F64$;
         3: aload_0
         4: invokevirtual #26                 // Method _value:()D
         7: iload_1
         8: invokevirtual #93                 // Method org/sireum/package$$Double2F64$.$tilde$greater$extension:(DZ)Lscala/Tuple2;
        11: areturn
      LineNumberTable:
        line 388: 0
      LocalVariableTable:
        Start  Length  Slot  Name   Signature
            0      12     0  this   Lorg/sireum/package$$Double2F64;
            0      12     1     o   Z
    Signature: #88                          // (Z)Lscala/Tuple2<Lorg/sireum/F64;Lorg/sireum/B;>;
    MethodParameters:
      Name                           Flags
      o                              final

  public scala.Tuple2<org.sireum.F64, org.sireum.C> $tilde$greater(char);
    descriptor: (C)Lscala/Tuple2;
    flags: (0x0001) ACC_PUBLIC
    Code:
      stack=4, locals=2, args_size=2
         0: getstatic     #24                 // Field org/sireum/package$$Double2F64$.MODULE$:Lorg/sireum/package$$Double2F64$;
         3: aload_0
         4: invokevirtual #26                 // Method _value:()D
         7: iload_1
         8: invokevirtual #99                 // Method org/sireum/package$$Double2F64$.$tilde$greater$extension:(DC)Lscala/Tuple2;
        11: areturn
      LineNumberTable:
        line 390: 0
      LocalVariableTable:
        Start  Length  Slot  Name   Signature
            0      12     0  this   Lorg/sireum/package$$Double2F64;
            0      12     1     o   C
    Signature: #96                          // (C)Lscala/Tuple2<Lorg/sireum/F64;Lorg/sireum/C;>;
    MethodParameters:
      Name                           Flags
      o                              final

  public scala.Tuple2<org.sireum.F64, org.sireum.Z> $tilde$greater(int);
    descriptor: (I)Lscala/Tuple2;
    flags: (0x0001) ACC_PUBLIC
    Code:
      stack=4, locals=2, args_size=2
         0: getstatic     #24                 // Field org/sireum/package$$Double2F64$.MODULE$:Lorg/sireum/package$$Double2F64$;
         3: aload_0
         4: invokevirtual #26                 // Method _value:()D
         7: iload_1
         8: invokevirtual #105                // Method org/sireum/package$$Double2F64$.$tilde$greater$extension:(DI)Lscala/Tuple2;
        11: areturn
      LineNumberTable:
        line 392: 0
      LocalVariableTable:
        Start  Length  Slot  Name   Signature
            0      12     0  this   Lorg/sireum/package$$Double2F64;
            0      12     1     o   I
    Signature: #102                         // (I)Lscala/Tuple2<Lorg/sireum/F64;Lorg/sireum/Z;>;
    MethodParameters:
      Name                           Flags
      o                              final

  public scala.Tuple2<org.sireum.F64, org.sireum.Z> $tilde$greater(long);
    descriptor: (J)Lscala/Tuple2;
    flags: (0x0001) ACC_PUBLIC
    Code:
      stack=5, locals=3, args_size=2
         0: getstatic     #24                 // Field org/sireum/package$$Double2F64$.MODULE$:Lorg/sireum/package$$Double2F64$;
         3: aload_0
         4: invokevirtual #26                 // Method _value:()D
         7: lload_1
         8: invokevirtual #111                // Method org/sireum/package$$Double2F64$.$tilde$greater$extension:(DJ)Lscala/Tuple2;
        11: areturn
      LineNumberTable:
        line 394: 0
      LocalVariableTable:
        Start  Length  Slot  Name   Signature
            0      12     0  this   Lorg/sireum/package$$Double2F64;
            0      12     1     o   J
    Signature: #108                         // (J)Lscala/Tuple2<Lorg/sireum/F64;Lorg/sireum/Z;>;
    MethodParameters:
      Name                           Flags
      o                              final

  public scala.Tuple2<org.sireum.F64, org.sireum.F32> $tilde$greater(float);
    descriptor: (F)Lscala/Tuple2;
    flags: (0x0001) ACC_PUBLIC
    Code:
      stack=4, locals=2, args_size=2
         0: getstatic     #24                 // Field org/sireum/package$$Double2F64$.MODULE$:Lorg/sireum/package$$Double2F64$;
         3: aload_0
         4: invokevirtual #26                 // Method _value:()D
         7: fload_1
         8: invokevirtual #117                // Method org/sireum/package$$Double2F64$.$tilde$greater$extension:(DF)Lscala/Tuple2;
        11: areturn
      LineNumberTable:
        line 396: 0
      LocalVariableTable:
        Start  Length  Slot  Name   Signature
            0      12     0  this   Lorg/sireum/package$$Double2F64;
            0      12     1     o   F
    Signature: #114                         // (F)Lscala/Tuple2<Lorg/sireum/F64;Lorg/sireum/F32;>;
    MethodParameters:
      Name                           Flags
      o                              final

  public scala.Tuple2<org.sireum.F64, org.sireum.F64> $tilde$greater(double);
    descriptor: (D)Lscala/Tuple2;
    flags: (0x0001) ACC_PUBLIC
    Code:
      stack=5, locals=3, args_size=2
         0: getstatic     #24                 // Field org/sireum/package$$Double2F64$.MODULE$:Lorg/sireum/package$$Double2F64$;
         3: aload_0
         4: invokevirtual #26                 // Method _value:()D
         7: dload_1
         8: invokevirtual #123                // Method org/sireum/package$$Double2F64$.$tilde$greater$extension:(DD)Lscala/Tuple2;
        11: areturn
      LineNumberTable:
        line 398: 0
      LocalVariableTable:
        Start  Length  Slot  Name   Signature
            0      12     0  this   Lorg/sireum/package$$Double2F64;
            0      12     1     o   D
    Signature: #120                         // (D)Lscala/Tuple2<Lorg/sireum/F64;Lorg/sireum/F64;>;
    MethodParameters:
      Name                           Flags
      o                              final

  public scala.Tuple2<org.sireum.F64, org.sireum.String> $tilde$greater(java.lang.String);
    descriptor: (Ljava/lang/String;)Lscala/Tuple2;
    flags: (0x0001) ACC_PUBLIC
    Code:
      stack=4, locals=2, args_size=2
         0: getstatic     #24                 // Field org/sireum/package$$Double2F64$.MODULE$:Lorg/sireum/package$$Double2F64$;
         3: aload_0
         4: invokevirtual #26                 // Method _value:()D
         7: aload_1
         8: invokevirtual #128                // Method org/sireum/package$$Double2F64$.$tilde$greater$extension:(DLjava/lang/String;)Lscala/Tuple2;
        11: areturn
      LineNumberTable:
        line 400: 0
      LocalVariableTable:
        Start  Length  Slot  Name   Signature
            0      12     0  this   Lorg/sireum/package$$Double2F64;
            0      12     1     o   Ljava/lang/String;
    Signature: #125                         // (Ljava/lang/String;)Lscala/Tuple2<Lorg/sireum/F64;Lorg/sireum/String;>;
    MethodParameters:
      Name                           Flags
      o                              final

  public <T extends java.lang.Object> scala.Tuple2<org.sireum.F64, T> $tilde$greater(T);
    descriptor: (Ljava/lang/Object;)Lscala/Tuple2;
    flags: (0x0001) ACC_PUBLIC
    Code:
      stack=4, locals=2, args_size=2
         0: getstatic     #24                 // Field org/sireum/package$$Double2F64$.MODULE$:Lorg/sireum/package$$Double2F64$;
         3: aload_0
         4: invokevirtual #26                 // Method _value:()D
         7: aload_1
         8: invokevirtual #134                // Method org/sireum/package$$Double2F64$.$tilde$greater$extension:(DLjava/lang/Object;)Lscala/Tuple2;
        11: areturn
      LineNumberTable:
        line 402: 0
      LocalVariableTable:
        Start  Length  Slot  Name   Signature
            0      12     0  this   Lorg/sireum/package$$Double2F64;
            0      12     1     o   Ljava/lang/Object;
    Signature: #131                         // <T:Ljava/lang/Object;>(TT;)Lscala/Tuple2<Lorg/sireum/F64;TT;>;
    MethodParameters:
      Name                           Flags
      o                              final

  public int hashCode();
    descriptor: ()I
    flags: (0x0001) ACC_PUBLIC
    Code:
      stack=3, locals=1, args_size=1
         0: getstatic     #24                 // Field org/sireum/package$$Double2F64$.MODULE$:Lorg/sireum/package$$Double2F64$;
         3: aload_0
         4: invokevirtual #26                 // Method _value:()D
         7: invokevirtual #141                // Method org/sireum/package$$Double2F64$.hashCode$extension:(D)I
        10: ireturn
      LineNumberTable:
        line 360: 0
      LocalVariableTable:
        Start  Length  Slot  Name   Signature
            0      11     0  this   Lorg/sireum/package$$Double2F64;

  public boolean equals(java.lang.Object);
    descriptor: (Ljava/lang/Object;)Z
    flags: (0x0001) ACC_PUBLIC
    Code:
      stack=4, locals=2, args_size=2
         0: getstatic     #24                 // Field org/sireum/package$$Double2F64$.MODULE$:Lorg/sireum/package$$Double2F64$;
         3: aload_0
         4: invokevirtual #26                 // Method _value:()D
         7: aload_1
         8: invokevirtual #148                // Method org/sireum/package$$Double2F64$.equals$extension:(DLjava/lang/Object;)Z
        11: ireturn
      LineNumberTable:
        line 360: 0
      LocalVariableTable:
        Start  Length  Slot  Name   Signature
            0      12     0  this   Lorg/sireum/package$$Double2F64;
            0      12     1   x$1   Ljava/lang/Object;
    MethodParameters:
      Name                           Flags
      x$1                            final

  public org.sireum.package$$Double2F64(double);
    descriptor: (D)V
    flags: (0x0001) ACC_PUBLIC
    Code:
      stack=3, locals=3, args_size=2
         0: aload_0
         1: dload_1
         2: putfield      #16                 // Field _value:D
         5: aload_0
         6: invokespecial #153                // Method java/lang/Object."<init>":()V
         9: return
      LineNumberTable:
        line 360: 0
      LocalVariableTable:
        Start  Length  Slot  Name   Signature
            0      10     0  this   Lorg/sireum/package$$Double2F64;
            0      10     1 _value   D
    MethodParameters:
      Name                           Flags
      _value                         final
}
InnerClasses:
  public static final #8= #2 of #7;       // $Double2F64=class org/sireum/package$$Double2F64 of class org/sireum/package
  public static #11= #10 of #7;           // $Double2F64$=class org/sireum/package$$Double2F64$ of class org/sireum/package
SourceFile: "package.scala"
  ScalaInlineInfo: length = 0x81 (unknown attribute)
   01 01 00 19 00 4E 00 41 05 00 3C 00 26 05 00 38
   00 26 05 00 30 00 26 05 00 34 00 26 05 00 25 00
   26 05 00 2C 00 26 05 00 46 00 41 05 00 52 00 41
   05 00 40 00 41 05 00 56 00 5F 05 00 56 00 77 05
   00 56 00 71 05 00 56 00 65 05 00 56 00 6B 05 00
   56 00 82 05 00 56 00 7C 05 00 56 00 57 05 00 4A
   00 41 05 00 95 00 96 01 00 0C 00 0E 01 00 8E 00
   8F 01 00 13 00 14 05 00 88 00 89 01 00 1F 00 20
   05
  Scala: length = 0x0 (unknown attribute)

