Classfile /Users/mw/Projects/slang-braindump/.jar/jar11/assemble/slang-braindump/assemble/content/org/sireum/package$$Int2Z$.class
  Last modified May 29, 2022; size 6863 bytes
  SHA-256 checksum 801847f918d690f1ea97fab30c569ab89bde59b5d79484db633d0ce4d84340ea
  Compiled from "package.scala"
public class org.sireum.package$$Int2Z$
  minor version: 0
  major version: 52
  flags: (0x0021) ACC_PUBLIC, ACC_SUPER
  this_class: #2                          // org/sireum/package$$Int2Z$
  super_class: #4                         // java/lang/Object
  interfaces: 0, fields: 1, methods: 29, attributes: 4
Constant pool:
    #1 = Utf8               org/sireum/package$$Int2Z$
    #2 = Class              #1            // org/sireum/package$$Int2Z$
    #3 = Utf8               java/lang/Object
    #4 = Class              #3            // java/lang/Object
    #5 = Utf8               package.scala
    #6 = Utf8               org/sireum/package$$Int2Z
    #7 = Class              #6            // org/sireum/package$$Int2Z
    #8 = Utf8               org/sireum/package
    #9 = Class              #8            // org/sireum/package
   #10 = Utf8               $Int2Z
   #11 = Utf8               $Int2Z$
   #12 = Utf8               org/sireum/package$Any2HashString$
   #13 = Class              #12           // org/sireum/package$Any2HashString$
   #14 = Utf8               Any2HashString$
   #15 = Utf8               MODULE$
   #16 = Utf8               Lorg/sireum/package$$Int2Z$;
   #17 = Utf8               <clinit>
   #18 = Utf8               ()V
   #19 = Utf8               <init>
   #20 = NameAndType        #19:#18       // "<init>":()V
   #21 = Methodref          #2.#20        // org/sireum/package$$Int2Z$."<init>":()V
   #22 = NameAndType        #15:#16       // MODULE$:Lorg/sireum/package$$Int2Z$;
   #23 = Fieldref           #2.#22        // org/sireum/package$$Int2Z$.MODULE$:Lorg/sireum/package$$Int2Z$;
   #24 = Utf8               hash$extension
   #25 = Utf8               (I)Lorg/sireum/Z;
   #26 = Utf8               $this
   #27 = Utf8               Lorg/sireum/package$Any2HashString$;
   #28 = NameAndType        #15:#27       // MODULE$:Lorg/sireum/package$Any2HashString$;
   #29 = Fieldref           #13.#28       // org/sireum/package$Any2HashString$.MODULE$:Lorg/sireum/package$Any2HashString$;
   #30 = Utf8               org/sireum/package$
   #31 = Class              #30           // org/sireum/package$
   #32 = Utf8               Lorg/sireum/package$;
   #33 = NameAndType        #15:#32       // MODULE$:Lorg/sireum/package$;
   #34 = Fieldref           #31.#33       // org/sireum/package$.MODULE$:Lorg/sireum/package$;
   #35 = Utf8               org/sireum/Z$
   #36 = Class              #35           // org/sireum/Z$
   #37 = Utf8               Lorg/sireum/Z$;
   #38 = NameAndType        #15:#37       // MODULE$:Lorg/sireum/Z$;
   #39 = Fieldref           #36.#38       // org/sireum/Z$.MODULE$:Lorg/sireum/Z$;
   #40 = Utf8               apply
   #41 = NameAndType        #40:#25       // apply:(I)Lorg/sireum/Z;
   #42 = Methodref          #36.#41       // org/sireum/Z$.apply:(I)Lorg/sireum/Z;
   #43 = Utf8               Any2HashString
   #44 = Utf8               (Ljava/lang/Object;)Ljava/lang/Object;
   #45 = NameAndType        #43:#44       // Any2HashString:(Ljava/lang/Object;)Ljava/lang/Object;
   #46 = Methodref          #31.#45       // org/sireum/package$.Any2HashString:(Ljava/lang/Object;)Ljava/lang/Object;
   #47 = Utf8               (Ljava/lang/Object;)Lorg/sireum/Z;
   #48 = NameAndType        #24:#47       // hash$extension:(Ljava/lang/Object;)Lorg/sireum/Z;
   #49 = Methodref          #13.#48       // org/sireum/package$Any2HashString$.hash$extension:(Ljava/lang/Object;)Lorg/sireum/Z;
   #50 = Utf8               this
   #51 = Utf8               I
   #52 = Utf8               string$extension
   #53 = Utf8               (I)Ljava/lang/String;
   #54 = Utf8               org/sireum/Z
   #55 = Class              #54           // org/sireum/Z
   #56 = Utf8               string
   #57 = Utf8               ()Ljava/lang/String;
   #58 = NameAndType        #56:#57       // string:()Ljava/lang/String;
   #59 = InterfaceMethodref #55.#58       // org/sireum/Z.string:()Ljava/lang/String;
   #60 = Utf8               $less$extension
   #61 = Utf8               (ILorg/sireum/Z;)Z
   #62 = Utf8               other
   #63 = Utf8               $less
   #64 = Utf8               (Lorg/sireum/Z;)Z
   #65 = NameAndType        #63:#64       // $less:(Lorg/sireum/Z;)Z
   #66 = InterfaceMethodref #55.#65       // org/sireum/Z.$less:(Lorg/sireum/Z;)Z
   #67 = Utf8               Lorg/sireum/Z;
   #68 = Utf8               $less$eq$extension
   #69 = Utf8               $less$eq
   #70 = NameAndType        #69:#64       // $less$eq:(Lorg/sireum/Z;)Z
   #71 = InterfaceMethodref #55.#70       // org/sireum/Z.$less$eq:(Lorg/sireum/Z;)Z
   #72 = Utf8               $greater$extension
   #73 = Utf8               $greater
   #74 = NameAndType        #73:#64       // $greater:(Lorg/sireum/Z;)Z
   #75 = InterfaceMethodref #55.#74       // org/sireum/Z.$greater:(Lorg/sireum/Z;)Z
   #76 = Utf8               $greater$eq$extension
   #77 = Utf8               $greater$eq
   #78 = NameAndType        #77:#64       // $greater$eq:(Lorg/sireum/Z;)Z
   #79 = InterfaceMethodref #55.#78       // org/sireum/Z.$greater$eq:(Lorg/sireum/Z;)Z
   #80 = Utf8               $eq$eq$eq$extension
   #81 = Utf8               org/sireum/B$
   #82 = Class              #81           // org/sireum/B$
   #83 = Utf8               Lorg/sireum/B$;
   #84 = NameAndType        #15:#83       // MODULE$:Lorg/sireum/B$;
   #85 = Fieldref           #82.#84       // org/sireum/B$.MODULE$:Lorg/sireum/B$;
   #86 = Utf8               equals
   #87 = Utf8               (Ljava/lang/Object;)Z
   #88 = NameAndType        #86:#87       // equals:(Ljava/lang/Object;)Z
   #89 = Methodref          #4.#88        // java/lang/Object.equals:(Ljava/lang/Object;)Z
   #90 = Utf8               (Z)Z
   #91 = NameAndType        #40:#90       // apply:(Z)Z
   #92 = Methodref          #82.#91       // org/sireum/B$.apply:(Z)Z
   #93 = Utf8               $eq$bang$eq$extension
   #94 = Utf8               $plus$extension
   #95 = Utf8               (ILorg/sireum/Z;)Lorg/sireum/Z;
   #96 = Utf8               $plus
   #97 = Utf8               (Lorg/sireum/Z;)Lorg/sireum/Z;
   #98 = NameAndType        #96:#97       // $plus:(Lorg/sireum/Z;)Lorg/sireum/Z;
   #99 = InterfaceMethodref #55.#98       // org/sireum/Z.$plus:(Lorg/sireum/Z;)Lorg/sireum/Z;
  #100 = Utf8               $minus$extension
  #101 = Utf8               $minus
  #102 = NameAndType        #101:#97      // $minus:(Lorg/sireum/Z;)Lorg/sireum/Z;
  #103 = InterfaceMethodref #55.#102      // org/sireum/Z.$minus:(Lorg/sireum/Z;)Lorg/sireum/Z;
  #104 = Utf8               $times$extension
  #105 = Utf8               $times
  #106 = NameAndType        #105:#97      // $times:(Lorg/sireum/Z;)Lorg/sireum/Z;
  #107 = InterfaceMethodref #55.#106      // org/sireum/Z.$times:(Lorg/sireum/Z;)Lorg/sireum/Z;
  #108 = Utf8               $div$extension
  #109 = Utf8               $div
  #110 = NameAndType        #109:#97      // $div:(Lorg/sireum/Z;)Lorg/sireum/Z;
  #111 = InterfaceMethodref #55.#110      // org/sireum/Z.$div:(Lorg/sireum/Z;)Lorg/sireum/Z;
  #112 = Utf8               $percent$extension
  #113 = Utf8               $percent
  #114 = NameAndType        #113:#97      // $percent:(Lorg/sireum/Z;)Lorg/sireum/Z;
  #115 = InterfaceMethodref #55.#114      // org/sireum/Z.$percent:(Lorg/sireum/Z;)Lorg/sireum/Z;
  #116 = Utf8               increase$extension
  #117 = Utf8               increase
  #118 = Utf8               ()Lorg/sireum/Z;
  #119 = NameAndType        #117:#118     // increase:()Lorg/sireum/Z;
  #120 = InterfaceMethodref #55.#119      // org/sireum/Z.increase:()Lorg/sireum/Z;
  #121 = Utf8               decrease$extension
  #122 = Utf8               decrease
  #123 = NameAndType        #122:#118     // decrease:()Lorg/sireum/Z;
  #124 = InterfaceMethodref #55.#123      // org/sireum/Z.decrease:()Lorg/sireum/Z;
  #125 = Utf8               to$extension
  #126 = Utf8               (ILorg/sireum/Z;)Lorg/sireum/ZRange;
  #127 = Utf8               (ILorg/sireum/Z;)Lorg/sireum/ZRange<Lorg/sireum/Z;>;
  #128 = Utf8               to
  #129 = Utf8               (Lorg/sireum/ZLike;)Lorg/sireum/ZRange;
  #130 = NameAndType        #128:#129     // to:(Lorg/sireum/ZLike;)Lorg/sireum/ZRange;
  #131 = InterfaceMethodref #55.#130      // org/sireum/Z.to:(Lorg/sireum/ZLike;)Lorg/sireum/ZRange;
  #132 = Utf8               until$extension
  #133 = Utf8               until
  #134 = NameAndType        #133:#129     // until:(Lorg/sireum/ZLike;)Lorg/sireum/ZRange;
  #135 = InterfaceMethodref #55.#134      // org/sireum/Z.until:(Lorg/sireum/ZLike;)Lorg/sireum/ZRange;
  #136 = Utf8               $tilde$greater$extension
  #137 = Utf8               (IZ)Lscala/Tuple2;
  #138 = Utf8               (IZ)Lscala/Tuple2<Lorg/sireum/Z;Lorg/sireum/B;>;
  #139 = Utf8               o
  #140 = Utf8               scala/Tuple2
  #141 = Class              #140          // scala/Tuple2
  #142 = Utf8               org/sireum/B
  #143 = Class              #142          // org/sireum/B
  #144 = Utf8               (Z)V
  #145 = NameAndType        #19:#144      // "<init>":(Z)V
  #146 = Methodref          #143.#145     // org/sireum/B."<init>":(Z)V
  #147 = Utf8               (Ljava/lang/Object;Ljava/lang/Object;)V
  #148 = NameAndType        #19:#147      // "<init>":(Ljava/lang/Object;Ljava/lang/Object;)V
  #149 = Methodref          #141.#148     // scala/Tuple2."<init>":(Ljava/lang/Object;Ljava/lang/Object;)V
  #150 = Utf8               Z
  #151 = Utf8               (IC)Lscala/Tuple2;
  #152 = Utf8               (IC)Lscala/Tuple2<Lorg/sireum/Z;Lorg/sireum/C;>;
  #153 = Utf8               org/sireum/C
  #154 = Class              #153          // org/sireum/C
  #155 = Utf8               org/sireum/C$
  #156 = Class              #155          // org/sireum/C$
  #157 = Utf8               Lorg/sireum/C$;
  #158 = NameAndType        #15:#157      // MODULE$:Lorg/sireum/C$;
  #159 = Fieldref           #156.#158     // org/sireum/C$.MODULE$:Lorg/sireum/C$;
  #160 = Utf8               (C)I
  #161 = NameAndType        #40:#160      // apply:(C)I
  #162 = Methodref          #156.#161     // org/sireum/C$.apply:(C)I
  #163 = Utf8               (I)V
  #164 = NameAndType        #19:#163      // "<init>":(I)V
  #165 = Methodref          #154.#164     // org/sireum/C."<init>":(I)V
  #166 = Utf8               C
  #167 = Utf8               (II)Lscala/Tuple2;
  #168 = Utf8               (II)Lscala/Tuple2<Lorg/sireum/Z;Lorg/sireum/Z;>;
  #169 = Utf8               (IJ)Lscala/Tuple2;
  #170 = Utf8               (IJ)Lscala/Tuple2<Lorg/sireum/Z;Lorg/sireum/Z;>;
  #171 = Utf8               (J)Lorg/sireum/Z;
  #172 = NameAndType        #40:#171      // apply:(J)Lorg/sireum/Z;
  #173 = Methodref          #36.#172      // org/sireum/Z$.apply:(J)Lorg/sireum/Z;
  #174 = Utf8               J
  #175 = Utf8               (IF)Lscala/Tuple2;
  #176 = Utf8               (IF)Lscala/Tuple2<Lorg/sireum/Z;Lorg/sireum/F32;>;
  #177 = Utf8               org/sireum/F32
  #178 = Class              #177          // org/sireum/F32
  #179 = Utf8               org/sireum/F32$
  #180 = Class              #179          // org/sireum/F32$
  #181 = Utf8               Lorg/sireum/F32$;
  #182 = NameAndType        #15:#181      // MODULE$:Lorg/sireum/F32$;
  #183 = Fieldref           #180.#182     // org/sireum/F32$.MODULE$:Lorg/sireum/F32$;
  #184 = Utf8               (F)F
  #185 = NameAndType        #40:#184      // apply:(F)F
  #186 = Methodref          #180.#185     // org/sireum/F32$.apply:(F)F
  #187 = Utf8               (F)V
  #188 = NameAndType        #19:#187      // "<init>":(F)V
  #189 = Methodref          #178.#188     // org/sireum/F32."<init>":(F)V
  #190 = Utf8               F
  #191 = Utf8               (ID)Lscala/Tuple2;
  #192 = Utf8               (ID)Lscala/Tuple2<Lorg/sireum/Z;Lorg/sireum/F64;>;
  #193 = Utf8               org/sireum/F64
  #194 = Class              #193          // org/sireum/F64
  #195 = Utf8               org/sireum/F64$
  #196 = Class              #195          // org/sireum/F64$
  #197 = Utf8               Lorg/sireum/F64$;
  #198 = NameAndType        #15:#197      // MODULE$:Lorg/sireum/F64$;
  #199 = Fieldref           #196.#198     // org/sireum/F64$.MODULE$:Lorg/sireum/F64$;
  #200 = Utf8               (D)D
  #201 = NameAndType        #40:#200      // apply:(D)D
  #202 = Methodref          #196.#201     // org/sireum/F64$.apply:(D)D
  #203 = Utf8               (D)V
  #204 = NameAndType        #19:#203      // "<init>":(D)V
  #205 = Methodref          #194.#204     // org/sireum/F64."<init>":(D)V
  #206 = Utf8               D
  #207 = Utf8               (ILjava/lang/String;)Lscala/Tuple2;
  #208 = Utf8               (ILjava/lang/String;)Lscala/Tuple2<Lorg/sireum/Z;Lorg/sireum/String;>;
  #209 = Utf8               org/sireum/String
  #210 = Class              #209          // org/sireum/String
  #211 = Utf8               org/sireum/String$
  #212 = Class              #211          // org/sireum/String$
  #213 = Utf8               Lorg/sireum/String$;
  #214 = NameAndType        #15:#213      // MODULE$:Lorg/sireum/String$;
  #215 = Fieldref           #212.#214     // org/sireum/String$.MODULE$:Lorg/sireum/String$;
  #216 = Utf8               (Ljava/lang/String;)Ljava/lang/String;
  #217 = NameAndType        #40:#216      // apply:(Ljava/lang/String;)Ljava/lang/String;
  #218 = Methodref          #212.#217     // org/sireum/String$.apply:(Ljava/lang/String;)Ljava/lang/String;
  #219 = Utf8               (Ljava/lang/String;)V
  #220 = NameAndType        #19:#219      // "<init>":(Ljava/lang/String;)V
  #221 = Methodref          #210.#220     // org/sireum/String."<init>":(Ljava/lang/String;)V
  #222 = Utf8               Ljava/lang/String;
  #223 = Utf8               (ILjava/lang/Object;)Lscala/Tuple2;
  #224 = Utf8               <T:Ljava/lang/Object;>(ITT;)Lscala/Tuple2<Lorg/sireum/Z;TT;>;
  #225 = Utf8               Ljava/lang/Object;
  #226 = Utf8               hashCode$extension
  #227 = Utf8               (I)I
  #228 = Utf8               java/lang/Integer
  #229 = Class              #228          // java/lang/Integer
  #230 = Utf8               hashCode
  #231 = NameAndType        #230:#227     // hashCode:(I)I
  #232 = Methodref          #229.#231     // java/lang/Integer.hashCode:(I)I
  #233 = Utf8               equals$extension
  #234 = Utf8               (ILjava/lang/Object;)Z
  #235 = Utf8               x$1
  #236 = Utf8               _value
  #237 = Utf8               ()I
  #238 = NameAndType        #236:#237     // _value:()I
  #239 = Methodref          #7.#238       // org/sireum/package$$Int2Z._value:()I
  #240 = Methodref          #4.#20        // java/lang/Object."<init>":()V
  #241 = Utf8               Code
  #242 = Utf8               LineNumberTable
  #243 = Utf8               LocalVariableTable
  #244 = Utf8               MethodParameters
  #245 = Utf8               StackMapTable
  #246 = Utf8               Signature
  #247 = Utf8               InnerClasses
  #248 = Utf8               SourceFile
  #249 = Utf8               ScalaInlineInfo
  #250 = Utf8               Scala
{
  public static final org.sireum.package$$Int2Z$ MODULE$;
    descriptor: Lorg/sireum/package$$Int2Z$;
    flags: (0x0019) ACC_PUBLIC, ACC_STATIC, ACC_FINAL

  public static {};
    descriptor: ()V
    flags: (0x0009) ACC_PUBLIC, ACC_STATIC
    Code:
      stack=2, locals=0, args_size=0
         0: new           #2                  // class org/sireum/package$$Int2Z$
         3: dup
         4: invokespecial #21                 // Method "<init>":()V
         7: putstatic     #23                 // Field MODULE$:Lorg/sireum/package$$Int2Z$;
        10: return
      LineNumberTable:
        line 209: 0

  public final org.sireum.Z hash$extension(int);
    descriptor: (I)Lorg/sireum/Z;
    flags: (0x0011) ACC_PUBLIC, ACC_FINAL
    Code:
      stack=4, locals=2, args_size=2
         0: getstatic     #29                 // Field org/sireum/package$Any2HashString$.MODULE$:Lorg/sireum/package$Any2HashString$;
         3: getstatic     #34                 // Field org/sireum/package$.MODULE$:Lorg/sireum/package$;
         6: getstatic     #39                 // Field org/sireum/Z$.MODULE$:Lorg/sireum/Z$;
         9: iload_1
        10: invokevirtual #42                 // Method org/sireum/Z$.apply:(I)Lorg/sireum/Z;
        13: invokevirtual #46                 // Method org/sireum/package$.Any2HashString:(Ljava/lang/Object;)Ljava/lang/Object;
        16: invokevirtual #49                 // Method org/sireum/package$Any2HashString$.hash$extension:(Ljava/lang/Object;)Lorg/sireum/Z;
        19: areturn
      LineNumberTable:
        line 211: 3
      LocalVariableTable:
        Start  Length  Slot  Name   Signature
            0      20     0  this   Lorg/sireum/package$$Int2Z$;
            0      20     1 $this   I
    MethodParameters:
      Name                           Flags
      $this                          final

  public final java.lang.String string$extension(int);
    descriptor: (I)Ljava/lang/String;
    flags: (0x0011) ACC_PUBLIC, ACC_FINAL
    Code:
      stack=2, locals=2, args_size=2
         0: getstatic     #39                 // Field org/sireum/Z$.MODULE$:Lorg/sireum/Z$;
         3: iload_1
         4: invokevirtual #42                 // Method org/sireum/Z$.apply:(I)Lorg/sireum/Z;
         7: invokeinterface #59,  1           // InterfaceMethod org/sireum/Z.string:()Ljava/lang/String;
        12: areturn
      LineNumberTable:
        line 213: 0
      LocalVariableTable:
        Start  Length  Slot  Name   Signature
            0      13     0  this   Lorg/sireum/package$$Int2Z$;
            0      13     1 $this   I
    MethodParameters:
      Name                           Flags
      $this                          final

  public final boolean $less$extension(int, org.sireum.Z);
    descriptor: (ILorg/sireum/Z;)Z
    flags: (0x0011) ACC_PUBLIC, ACC_FINAL
    Code:
      stack=2, locals=3, args_size=3
         0: getstatic     #39                 // Field org/sireum/Z$.MODULE$:Lorg/sireum/Z$;
         3: iload_1
         4: invokevirtual #42                 // Method org/sireum/Z$.apply:(I)Lorg/sireum/Z;
         7: aload_2
         8: invokeinterface #66,  2           // InterfaceMethod org/sireum/Z.$less:(Lorg/sireum/Z;)Z
        13: ireturn
      LineNumberTable:
        line 215: 0
      LocalVariableTable:
        Start  Length  Slot  Name   Signature
            0      14     0  this   Lorg/sireum/package$$Int2Z$;
            0      14     1 $this   I
            0      14     2 other   Lorg/sireum/Z;
    MethodParameters:
      Name                           Flags
      $this                          final
      other                          final

  public final boolean $less$eq$extension(int, org.sireum.Z);
    descriptor: (ILorg/sireum/Z;)Z
    flags: (0x0011) ACC_PUBLIC, ACC_FINAL
    Code:
      stack=2, locals=3, args_size=3
         0: getstatic     #39                 // Field org/sireum/Z$.MODULE$:Lorg/sireum/Z$;
         3: iload_1
         4: invokevirtual #42                 // Method org/sireum/Z$.apply:(I)Lorg/sireum/Z;
         7: aload_2
         8: invokeinterface #71,  2           // InterfaceMethod org/sireum/Z.$less$eq:(Lorg/sireum/Z;)Z
        13: ireturn
      LineNumberTable:
        line 217: 0
      LocalVariableTable:
        Start  Length  Slot  Name   Signature
            0      14     0  this   Lorg/sireum/package$$Int2Z$;
            0      14     1 $this   I
            0      14     2 other   Lorg/sireum/Z;
    MethodParameters:
      Name                           Flags
      $this                          final
      other                          final

  public final boolean $greater$extension(int, org.sireum.Z);
    descriptor: (ILorg/sireum/Z;)Z
    flags: (0x0011) ACC_PUBLIC, ACC_FINAL
    Code:
      stack=2, locals=3, args_size=3
         0: getstatic     #39                 // Field org/sireum/Z$.MODULE$:Lorg/sireum/Z$;
         3: iload_1
         4: invokevirtual #42                 // Method org/sireum/Z$.apply:(I)Lorg/sireum/Z;
         7: aload_2
         8: invokeinterface #75,  2           // InterfaceMethod org/sireum/Z.$greater:(Lorg/sireum/Z;)Z
        13: ireturn
      LineNumberTable:
        line 219: 0
      LocalVariableTable:
        Start  Length  Slot  Name   Signature
            0      14     0  this   Lorg/sireum/package$$Int2Z$;
            0      14     1 $this   I
            0      14     2 other   Lorg/sireum/Z;
    MethodParameters:
      Name                           Flags
      $this                          final
      other                          final

  public final boolean $greater$eq$extension(int, org.sireum.Z);
    descriptor: (ILorg/sireum/Z;)Z
    flags: (0x0011) ACC_PUBLIC, ACC_FINAL
    Code:
      stack=2, locals=3, args_size=3
         0: getstatic     #39                 // Field org/sireum/Z$.MODULE$:Lorg/sireum/Z$;
         3: iload_1
         4: invokevirtual #42                 // Method org/sireum/Z$.apply:(I)Lorg/sireum/Z;
         7: aload_2
         8: invokeinterface #79,  2           // InterfaceMethod org/sireum/Z.$greater$eq:(Lorg/sireum/Z;)Z
        13: ireturn
      LineNumberTable:
        line 221: 0
      LocalVariableTable:
        Start  Length  Slot  Name   Signature
            0      14     0  this   Lorg/sireum/package$$Int2Z$;
            0      14     1 $this   I
            0      14     2 other   Lorg/sireum/Z;
    MethodParameters:
      Name                           Flags
      $this                          final
      other                          final

  public final boolean $eq$eq$eq$extension(int, org.sireum.Z);
    descriptor: (ILorg/sireum/Z;)Z
    flags: (0x0011) ACC_PUBLIC, ACC_FINAL
    Code:
      stack=3, locals=4, args_size=3
         0: getstatic     #85                 // Field org/sireum/B$.MODULE$:Lorg/sireum/B$;
         3: getstatic     #39                 // Field org/sireum/Z$.MODULE$:Lorg/sireum/Z$;
         6: iload_1
         7: invokevirtual #42                 // Method org/sireum/Z$.apply:(I)Lorg/sireum/Z;
        10: aload_2
        11: astore_3
        12: dup
        13: ifnonnull     24
        16: pop
        17: aload_3
        18: ifnull        31
        21: goto          35
        24: aload_3
        25: invokevirtual #89                 // Method java/lang/Object.equals:(Ljava/lang/Object;)Z
        28: ifeq          35
        31: iconst_1
        32: goto          36
        35: iconst_0
        36: invokevirtual #92                 // Method org/sireum/B$.apply:(Z)Z
        39: ireturn
      StackMapTable: number_of_entries = 4
        frame_type = 255 /* full_frame */
          offset_delta = 24
          locals = [ class org/sireum/package$$Int2Z$, int, class org/sireum/Z, class org/sireum/Z ]
          stack = [ class org/sireum/B$, class org/sireum/Z ]
        frame_type = 70 /* same_locals_1_stack_item */
          stack = [ class org/sireum/B$ ]
        frame_type = 67 /* same_locals_1_stack_item */
          stack = [ class org/sireum/B$ ]
        frame_type = 255 /* full_frame */
          offset_delta = 0
          locals = [ class org/sireum/package$$Int2Z$, int, class org/sireum/Z, class org/sireum/Z ]
          stack = [ class org/sireum/B$, int ]
      LineNumberTable:
        line 223: 0
      LocalVariableTable:
        Start  Length  Slot  Name   Signature
            0      40     0  this   Lorg/sireum/package$$Int2Z$;
            0      40     1 $this   I
            0      40     2 other   Lorg/sireum/Z;
    MethodParameters:
      Name                           Flags
      $this                          final
      other                          final

  public final boolean $eq$bang$eq$extension(int, org.sireum.Z);
    descriptor: (ILorg/sireum/Z;)Z
    flags: (0x0011) ACC_PUBLIC, ACC_FINAL
    Code:
      stack=3, locals=4, args_size=3
         0: getstatic     #85                 // Field org/sireum/B$.MODULE$:Lorg/sireum/B$;
         3: getstatic     #39                 // Field org/sireum/Z$.MODULE$:Lorg/sireum/Z$;
         6: iload_1
         7: invokevirtual #42                 // Method org/sireum/Z$.apply:(I)Lorg/sireum/Z;
        10: aload_2
        11: astore_3
        12: dup
        13: ifnonnull     24
        16: pop
        17: aload_3
        18: ifnull        35
        21: goto          31
        24: aload_3
        25: invokevirtual #89                 // Method java/lang/Object.equals:(Ljava/lang/Object;)Z
        28: ifne          35
        31: iconst_1
        32: goto          36
        35: iconst_0
        36: invokevirtual #92                 // Method org/sireum/B$.apply:(Z)Z
        39: ireturn
      StackMapTable: number_of_entries = 4
        frame_type = 255 /* full_frame */
          offset_delta = 24
          locals = [ class org/sireum/package$$Int2Z$, int, class org/sireum/Z, class org/sireum/Z ]
          stack = [ class org/sireum/B$, class org/sireum/Z ]
        frame_type = 70 /* same_locals_1_stack_item */
          stack = [ class org/sireum/B$ ]
        frame_type = 67 /* same_locals_1_stack_item */
          stack = [ class org/sireum/B$ ]
        frame_type = 255 /* full_frame */
          offset_delta = 0
          locals = [ class org/sireum/package$$Int2Z$, int, class org/sireum/Z, class org/sireum/Z ]
          stack = [ class org/sireum/B$, int ]
      LineNumberTable:
        line 225: 0
      LocalVariableTable:
        Start  Length  Slot  Name   Signature
            0      40     0  this   Lorg/sireum/package$$Int2Z$;
            0      40     1 $this   I
            0      40     2 other   Lorg/sireum/Z;
    MethodParameters:
      Name                           Flags
      $this                          final
      other                          final

  public final org.sireum.Z $plus$extension(int, org.sireum.Z);
    descriptor: (ILorg/sireum/Z;)Lorg/sireum/Z;
    flags: (0x0011) ACC_PUBLIC, ACC_FINAL
    Code:
      stack=2, locals=3, args_size=3
         0: getstatic     #39                 // Field org/sireum/Z$.MODULE$:Lorg/sireum/Z$;
         3: iload_1
         4: invokevirtual #42                 // Method org/sireum/Z$.apply:(I)Lorg/sireum/Z;
         7: aload_2
         8: invokeinterface #99,  2           // InterfaceMethod org/sireum/Z.$plus:(Lorg/sireum/Z;)Lorg/sireum/Z;
        13: areturn
      LineNumberTable:
        line 227: 0
      LocalVariableTable:
        Start  Length  Slot  Name   Signature
            0      14     0  this   Lorg/sireum/package$$Int2Z$;
            0      14     1 $this   I
            0      14     2 other   Lorg/sireum/Z;
    MethodParameters:
      Name                           Flags
      $this                          final
      other                          final

  public final org.sireum.Z $minus$extension(int, org.sireum.Z);
    descriptor: (ILorg/sireum/Z;)Lorg/sireum/Z;
    flags: (0x0011) ACC_PUBLIC, ACC_FINAL
    Code:
      stack=2, locals=3, args_size=3
         0: getstatic     #39                 // Field org/sireum/Z$.MODULE$:Lorg/sireum/Z$;
         3: iload_1
         4: invokevirtual #42                 // Method org/sireum/Z$.apply:(I)Lorg/sireum/Z;
         7: aload_2
         8: invokeinterface #103,  2          // InterfaceMethod org/sireum/Z.$minus:(Lorg/sireum/Z;)Lorg/sireum/Z;
        13: areturn
      LineNumberTable:
        line 229: 0
      LocalVariableTable:
        Start  Length  Slot  Name   Signature
            0      14     0  this   Lorg/sireum/package$$Int2Z$;
            0      14     1 $this   I
            0      14     2 other   Lorg/sireum/Z;
    MethodParameters:
      Name                           Flags
      $this                          final
      other                          final

  public final org.sireum.Z $times$extension(int, org.sireum.Z);
    descriptor: (ILorg/sireum/Z;)Lorg/sireum/Z;
    flags: (0x0011) ACC_PUBLIC, ACC_FINAL
    Code:
      stack=2, locals=3, args_size=3
         0: getstatic     #39                 // Field org/sireum/Z$.MODULE$:Lorg/sireum/Z$;
         3: iload_1
         4: invokevirtual #42                 // Method org/sireum/Z$.apply:(I)Lorg/sireum/Z;
         7: aload_2
         8: invokeinterface #107,  2          // InterfaceMethod org/sireum/Z.$times:(Lorg/sireum/Z;)Lorg/sireum/Z;
        13: areturn
      LineNumberTable:
        line 231: 0
      LocalVariableTable:
        Start  Length  Slot  Name   Signature
            0      14     0  this   Lorg/sireum/package$$Int2Z$;
            0      14     1 $this   I
            0      14     2 other   Lorg/sireum/Z;
    MethodParameters:
      Name                           Flags
      $this                          final
      other                          final

  public final org.sireum.Z $div$extension(int, org.sireum.Z);
    descriptor: (ILorg/sireum/Z;)Lorg/sireum/Z;
    flags: (0x0011) ACC_PUBLIC, ACC_FINAL
    Code:
      stack=2, locals=3, args_size=3
         0: getstatic     #39                 // Field org/sireum/Z$.MODULE$:Lorg/sireum/Z$;
         3: iload_1
         4: invokevirtual #42                 // Method org/sireum/Z$.apply:(I)Lorg/sireum/Z;
         7: aload_2
         8: invokeinterface #111,  2          // InterfaceMethod org/sireum/Z.$div:(Lorg/sireum/Z;)Lorg/sireum/Z;
        13: areturn
      LineNumberTable:
        line 233: 0
      LocalVariableTable:
        Start  Length  Slot  Name   Signature
            0      14     0  this   Lorg/sireum/package$$Int2Z$;
            0      14     1 $this   I
            0      14     2 other   Lorg/sireum/Z;
    MethodParameters:
      Name                           Flags
      $this                          final
      other                          final

  public final org.sireum.Z $percent$extension(int, org.sireum.Z);
    descriptor: (ILorg/sireum/Z;)Lorg/sireum/Z;
    flags: (0x0011) ACC_PUBLIC, ACC_FINAL
    Code:
      stack=2, locals=3, args_size=3
         0: getstatic     #39                 // Field org/sireum/Z$.MODULE$:Lorg/sireum/Z$;
         3: iload_1
         4: invokevirtual #42                 // Method org/sireum/Z$.apply:(I)Lorg/sireum/Z;
         7: aload_2
         8: invokeinterface #115,  2          // InterfaceMethod org/sireum/Z.$percent:(Lorg/sireum/Z;)Lorg/sireum/Z;
        13: areturn
      LineNumberTable:
        line 235: 0
      LocalVariableTable:
        Start  Length  Slot  Name   Signature
            0      14     0  this   Lorg/sireum/package$$Int2Z$;
            0      14     1 $this   I
            0      14     2 other   Lorg/sireum/Z;
    MethodParameters:
      Name                           Flags
      $this                          final
      other                          final

  public final org.sireum.Z increase$extension(int);
    descriptor: (I)Lorg/sireum/Z;
    flags: (0x0011) ACC_PUBLIC, ACC_FINAL
    Code:
      stack=2, locals=2, args_size=2
         0: getstatic     #39                 // Field org/sireum/Z$.MODULE$:Lorg/sireum/Z$;
         3: iload_1
         4: invokevirtual #42                 // Method org/sireum/Z$.apply:(I)Lorg/sireum/Z;
         7: invokeinterface #120,  1          // InterfaceMethod org/sireum/Z.increase:()Lorg/sireum/Z;
        12: areturn
      LineNumberTable:
        line 237: 0
      LocalVariableTable:
        Start  Length  Slot  Name   Signature
            0      13     0  this   Lorg/sireum/package$$Int2Z$;
            0      13     1 $this   I
    MethodParameters:
      Name                           Flags
      $this                          final

  public final org.sireum.Z decrease$extension(int);
    descriptor: (I)Lorg/sireum/Z;
    flags: (0x0011) ACC_PUBLIC, ACC_FINAL
    Code:
      stack=2, locals=2, args_size=2
         0: getstatic     #39                 // Field org/sireum/Z$.MODULE$:Lorg/sireum/Z$;
         3: iload_1
         4: invokevirtual #42                 // Method org/sireum/Z$.apply:(I)Lorg/sireum/Z;
         7: invokeinterface #124,  1          // InterfaceMethod org/sireum/Z.decrease:()Lorg/sireum/Z;
        12: areturn
      LineNumberTable:
        line 239: 0
      LocalVariableTable:
        Start  Length  Slot  Name   Signature
            0      13     0  this   Lorg/sireum/package$$Int2Z$;
            0      13     1 $this   I
    MethodParameters:
      Name                           Flags
      $this                          final

  public final org.sireum.ZRange<org.sireum.Z> to$extension(int, org.sireum.Z);
    descriptor: (ILorg/sireum/Z;)Lorg/sireum/ZRange;
    flags: (0x0011) ACC_PUBLIC, ACC_FINAL
    Code:
      stack=2, locals=3, args_size=3
         0: getstatic     #39                 // Field org/sireum/Z$.MODULE$:Lorg/sireum/Z$;
         3: iload_1
         4: invokevirtual #42                 // Method org/sireum/Z$.apply:(I)Lorg/sireum/Z;
         7: aload_2
         8: invokeinterface #131,  2          // InterfaceMethod org/sireum/Z.to:(Lorg/sireum/ZLike;)Lorg/sireum/ZRange;
        13: areturn
      LineNumberTable:
        line 241: 0
      LocalVariableTable:
        Start  Length  Slot  Name   Signature
            0      14     0  this   Lorg/sireum/package$$Int2Z$;
            0      14     1 $this   I
            0      14     2 other   Lorg/sireum/Z;
    Signature: #127                         // (ILorg/sireum/Z;)Lorg/sireum/ZRange<Lorg/sireum/Z;>;
    MethodParameters:
      Name                           Flags
      $this                          final
      other                          final

  public final org.sireum.ZRange<org.sireum.Z> until$extension(int, org.sireum.Z);
    descriptor: (ILorg/sireum/Z;)Lorg/sireum/ZRange;
    flags: (0x0011) ACC_PUBLIC, ACC_FINAL
    Code:
      stack=2, locals=3, args_size=3
         0: getstatic     #39                 // Field org/sireum/Z$.MODULE$:Lorg/sireum/Z$;
         3: iload_1
         4: invokevirtual #42                 // Method org/sireum/Z$.apply:(I)Lorg/sireum/Z;
         7: aload_2
         8: invokeinterface #135,  2          // InterfaceMethod org/sireum/Z.until:(Lorg/sireum/ZLike;)Lorg/sireum/ZRange;
        13: areturn
      LineNumberTable:
        line 243: 0
      LocalVariableTable:
        Start  Length  Slot  Name   Signature
            0      14     0  this   Lorg/sireum/package$$Int2Z$;
            0      14     1 $this   I
            0      14     2 other   Lorg/sireum/Z;
    Signature: #127                         // (ILorg/sireum/Z;)Lorg/sireum/ZRange<Lorg/sireum/Z;>;
    MethodParameters:
      Name                           Flags
      $this                          final
      other                          final

  public final scala.Tuple2<org.sireum.Z, org.sireum.B> $tilde$greater$extension(int, boolean);
    descriptor: (IZ)Lscala/Tuple2;
    flags: (0x0011) ACC_PUBLIC, ACC_FINAL
    Code:
      stack=7, locals=3, args_size=3
         0: new           #141                // class scala/Tuple2
         3: dup
         4: getstatic     #39                 // Field org/sireum/Z$.MODULE$:Lorg/sireum/Z$;
         7: iload_1
         8: invokevirtual #42                 // Method org/sireum/Z$.apply:(I)Lorg/sireum/Z;
        11: new           #143                // class org/sireum/B
        14: dup
        15: getstatic     #85                 // Field org/sireum/B$.MODULE$:Lorg/sireum/B$;
        18: iload_2
        19: invokevirtual #92                 // Method org/sireum/B$.apply:(Z)Z
        22: invokespecial #146                // Method org/sireum/B."<init>":(Z)V
        25: invokespecial #149                // Method scala/Tuple2."<init>":(Ljava/lang/Object;Ljava/lang/Object;)V
        28: areturn
      LineNumberTable:
        line 245: 0
      LocalVariableTable:
        Start  Length  Slot  Name   Signature
            0      29     0  this   Lorg/sireum/package$$Int2Z$;
            0      29     1 $this   I
            0      29     2     o   Z
    Signature: #138                         // (IZ)Lscala/Tuple2<Lorg/sireum/Z;Lorg/sireum/B;>;
    MethodParameters:
      Name                           Flags
      $this                          final
      o                              final

  public final scala.Tuple2<org.sireum.Z, org.sireum.C> $tilde$greater$extension(int, char);
    descriptor: (IC)Lscala/Tuple2;
    flags: (0x0011) ACC_PUBLIC, ACC_FINAL
    Code:
      stack=7, locals=3, args_size=3
         0: new           #141                // class scala/Tuple2
         3: dup
         4: getstatic     #39                 // Field org/sireum/Z$.MODULE$:Lorg/sireum/Z$;
         7: iload_1
         8: invokevirtual #42                 // Method org/sireum/Z$.apply:(I)Lorg/sireum/Z;
        11: new           #154                // class org/sireum/C
        14: dup
        15: getstatic     #159                // Field org/sireum/C$.MODULE$:Lorg/sireum/C$;
        18: iload_2
        19: invokevirtual #162                // Method org/sireum/C$.apply:(C)I
        22: invokespecial #165                // Method org/sireum/C."<init>":(I)V
        25: invokespecial #149                // Method scala/Tuple2."<init>":(Ljava/lang/Object;Ljava/lang/Object;)V
        28: areturn
      LineNumberTable:
        line 247: 0
      LocalVariableTable:
        Start  Length  Slot  Name   Signature
            0      29     0  this   Lorg/sireum/package$$Int2Z$;
            0      29     1 $this   I
            0      29     2     o   C
    Signature: #152                         // (IC)Lscala/Tuple2<Lorg/sireum/Z;Lorg/sireum/C;>;
    MethodParameters:
      Name                           Flags
      $this                          final
      o                              final

  public final scala.Tuple2<org.sireum.Z, org.sireum.Z> $tilde$greater$extension(int, int);
    descriptor: (II)Lscala/Tuple2;
    flags: (0x0011) ACC_PUBLIC, ACC_FINAL
    Code:
      stack=5, locals=3, args_size=3
         0: new           #141                // class scala/Tuple2
         3: dup
         4: getstatic     #39                 // Field org/sireum/Z$.MODULE$:Lorg/sireum/Z$;
         7: iload_1
         8: invokevirtual #42                 // Method org/sireum/Z$.apply:(I)Lorg/sireum/Z;
        11: getstatic     #39                 // Field org/sireum/Z$.MODULE$:Lorg/sireum/Z$;
        14: iload_2
        15: invokevirtual #42                 // Method org/sireum/Z$.apply:(I)Lorg/sireum/Z;
        18: invokespecial #149                // Method scala/Tuple2."<init>":(Ljava/lang/Object;Ljava/lang/Object;)V
        21: areturn
      LineNumberTable:
        line 249: 0
      LocalVariableTable:
        Start  Length  Slot  Name   Signature
            0      22     0  this   Lorg/sireum/package$$Int2Z$;
            0      22     1 $this   I
            0      22     2     o   I
    Signature: #168                         // (II)Lscala/Tuple2<Lorg/sireum/Z;Lorg/sireum/Z;>;
    MethodParameters:
      Name                           Flags
      $this                          final
      o                              final

  public final scala.Tuple2<org.sireum.Z, org.sireum.Z> $tilde$greater$extension(int, long);
    descriptor: (IJ)Lscala/Tuple2;
    flags: (0x0011) ACC_PUBLIC, ACC_FINAL
    Code:
      stack=6, locals=4, args_size=3
         0: new           #141                // class scala/Tuple2
         3: dup
         4: getstatic     #39                 // Field org/sireum/Z$.MODULE$:Lorg/sireum/Z$;
         7: iload_1
         8: invokevirtual #42                 // Method org/sireum/Z$.apply:(I)Lorg/sireum/Z;
        11: getstatic     #39                 // Field org/sireum/Z$.MODULE$:Lorg/sireum/Z$;
        14: lload_2
        15: invokevirtual #173                // Method org/sireum/Z$.apply:(J)Lorg/sireum/Z;
        18: invokespecial #149                // Method scala/Tuple2."<init>":(Ljava/lang/Object;Ljava/lang/Object;)V
        21: areturn
      LineNumberTable:
        line 251: 0
      LocalVariableTable:
        Start  Length  Slot  Name   Signature
            0      22     0  this   Lorg/sireum/package$$Int2Z$;
            0      22     1 $this   I
            0      22     2     o   J
    Signature: #170                         // (IJ)Lscala/Tuple2<Lorg/sireum/Z;Lorg/sireum/Z;>;
    MethodParameters:
      Name                           Flags
      $this                          final
      o                              final

  public final scala.Tuple2<org.sireum.Z, org.sireum.F32> $tilde$greater$extension(int, float);
    descriptor: (IF)Lscala/Tuple2;
    flags: (0x0011) ACC_PUBLIC, ACC_FINAL
    Code:
      stack=7, locals=3, args_size=3
         0: new           #141                // class scala/Tuple2
         3: dup
         4: getstatic     #39                 // Field org/sireum/Z$.MODULE$:Lorg/sireum/Z$;
         7: iload_1
         8: invokevirtual #42                 // Method org/sireum/Z$.apply:(I)Lorg/sireum/Z;
        11: new           #178                // class org/sireum/F32
        14: dup
        15: getstatic     #183                // Field org/sireum/F32$.MODULE$:Lorg/sireum/F32$;
        18: fload_2
        19: invokevirtual #186                // Method org/sireum/F32$.apply:(F)F
        22: invokespecial #189                // Method org/sireum/F32."<init>":(F)V
        25: invokespecial #149                // Method scala/Tuple2."<init>":(Ljava/lang/Object;Ljava/lang/Object;)V
        28: areturn
      LineNumberTable:
        line 253: 0
      LocalVariableTable:
        Start  Length  Slot  Name   Signature
            0      29     0  this   Lorg/sireum/package$$Int2Z$;
            0      29     1 $this   I
            0      29     2     o   F
    Signature: #176                         // (IF)Lscala/Tuple2<Lorg/sireum/Z;Lorg/sireum/F32;>;
    MethodParameters:
      Name                           Flags
      $this                          final
      o                              final

  public final scala.Tuple2<org.sireum.Z, org.sireum.F64> $tilde$greater$extension(int, double);
    descriptor: (ID)Lscala/Tuple2;
    flags: (0x0011) ACC_PUBLIC, ACC_FINAL
    Code:
      stack=8, locals=4, args_size=3
         0: new           #141                // class scala/Tuple2
         3: dup
         4: getstatic     #39                 // Field org/sireum/Z$.MODULE$:Lorg/sireum/Z$;
         7: iload_1
         8: invokevirtual #42                 // Method org/sireum/Z$.apply:(I)Lorg/sireum/Z;
        11: new           #194                // class org/sireum/F64
        14: dup
        15: getstatic     #199                // Field org/sireum/F64$.MODULE$:Lorg/sireum/F64$;
        18: dload_2
        19: invokevirtual #202                // Method org/sireum/F64$.apply:(D)D
        22: invokespecial #205                // Method org/sireum/F64."<init>":(D)V
        25: invokespecial #149                // Method scala/Tuple2."<init>":(Ljava/lang/Object;Ljava/lang/Object;)V
        28: areturn
      LineNumberTable:
        line 255: 0
      LocalVariableTable:
        Start  Length  Slot  Name   Signature
            0      29     0  this   Lorg/sireum/package$$Int2Z$;
            0      29     1 $this   I
            0      29     2     o   D
    Signature: #192                         // (ID)Lscala/Tuple2<Lorg/sireum/Z;Lorg/sireum/F64;>;
    MethodParameters:
      Name                           Flags
      $this                          final
      o                              final

  public final scala.Tuple2<org.sireum.Z, org.sireum.String> $tilde$greater$extension(int, java.lang.String);
    descriptor: (ILjava/lang/String;)Lscala/Tuple2;
    flags: (0x0011) ACC_PUBLIC, ACC_FINAL
    Code:
      stack=7, locals=3, args_size=3
         0: new           #141                // class scala/Tuple2
         3: dup
         4: getstatic     #39                 // Field org/sireum/Z$.MODULE$:Lorg/sireum/Z$;
         7: iload_1
         8: invokevirtual #42                 // Method org/sireum/Z$.apply:(I)Lorg/sireum/Z;
        11: new           #210                // class org/sireum/String
        14: dup
        15: getstatic     #215                // Field org/sireum/String$.MODULE$:Lorg/sireum/String$;
        18: aload_2
        19: invokevirtual #218                // Method org/sireum/String$.apply:(Ljava/lang/String;)Ljava/lang/String;
        22: invokespecial #221                // Method org/sireum/String."<init>":(Ljava/lang/String;)V
        25: invokespecial #149                // Method scala/Tuple2."<init>":(Ljava/lang/Object;Ljava/lang/Object;)V
        28: areturn
      LineNumberTable:
        line 257: 0
      LocalVariableTable:
        Start  Length  Slot  Name   Signature
            0      29     0  this   Lorg/sireum/package$$Int2Z$;
            0      29     1 $this   I
            0      29     2     o   Ljava/lang/String;
    Signature: #208                         // (ILjava/lang/String;)Lscala/Tuple2<Lorg/sireum/Z;Lorg/sireum/String;>;
    MethodParameters:
      Name                           Flags
      $this                          final
      o                              final

  public final <T extends java.lang.Object> scala.Tuple2<org.sireum.Z, T> $tilde$greater$extension(int, T);
    descriptor: (ILjava/lang/Object;)Lscala/Tuple2;
    flags: (0x0011) ACC_PUBLIC, ACC_FINAL
    Code:
      stack=4, locals=3, args_size=3
         0: new           #141                // class scala/Tuple2
         3: dup
         4: getstatic     #39                 // Field org/sireum/Z$.MODULE$:Lorg/sireum/Z$;
         7: iload_1
         8: invokevirtual #42                 // Method org/sireum/Z$.apply:(I)Lorg/sireum/Z;
        11: aload_2
        12: invokespecial #149                // Method scala/Tuple2."<init>":(Ljava/lang/Object;Ljava/lang/Object;)V
        15: areturn
      LineNumberTable:
        line 259: 0
      LocalVariableTable:
        Start  Length  Slot  Name   Signature
            0      16     0  this   Lorg/sireum/package$$Int2Z$;
            0      16     1 $this   I
            0      16     2     o   Ljava/lang/Object;
    Signature: #224                         // <T:Ljava/lang/Object;>(ITT;)Lscala/Tuple2<Lorg/sireum/Z;TT;>;
    MethodParameters:
      Name                           Flags
      $this                          final
      o                              final

  public final int hashCode$extension(int);
    descriptor: (I)I
    flags: (0x0011) ACC_PUBLIC, ACC_FINAL
    Code:
      stack=1, locals=2, args_size=2
         0: iload_1
         1: invokestatic  #232                // Method java/lang/Integer.hashCode:(I)I
         4: ireturn
      LineNumberTable:
        line 209: 0
      LocalVariableTable:
        Start  Length  Slot  Name   Signature
            0       5     0  this   Lorg/sireum/package$$Int2Z$;
            0       5     1 $this   I
    MethodParameters:
      Name                           Flags
      $this                          final

  public final boolean equals$extension(int, java.lang.Object);
    descriptor: (ILjava/lang/Object;)Z
    flags: (0x0011) ACC_PUBLIC, ACC_FINAL
    Code:
      stack=2, locals=6, args_size=3
         0: aload_2
         1: astore        4
         3: aload         4
         5: instanceof    #7                  // class org/sireum/package$$Int2Z
         8: ifeq          16
        11: iconst_1
        12: istore_3
        13: goto          24
        16: goto          19
        19: iconst_0
        20: istore_3
        21: goto          24
        24: iload_3
        25: ifeq          55
        28: aload_2
        29: checkcast     #7                  // class org/sireum/package$$Int2Z
        32: invokevirtual #239                // Method org/sireum/package$$Int2Z._value:()I
        35: istore        5
        37: iload_1
        38: iload         5
        40: if_icmpne     47
        43: iconst_1
        44: goto          48
        47: iconst_0
        48: ifeq          55
        51: iconst_1
        52: goto          56
        55: iconst_0
        56: ireturn
      StackMapTable: number_of_entries = 7
        frame_type = 253 /* append */
          offset_delta = 16
          locals = [ top, class java/lang/Object ]
        frame_type = 2 /* same */
        frame_type = 255 /* full_frame */
          offset_delta = 4
          locals = [ class org/sireum/package$$Int2Z$, int, class java/lang/Object, int, class java/lang/Object ]
          stack = []
        frame_type = 252 /* append */
          offset_delta = 22
          locals = [ int ]
        frame_type = 64 /* same_locals_1_stack_item */
          stack = [ int ]
        frame_type = 250 /* chop */
          offset_delta = 6
        frame_type = 64 /* same_locals_1_stack_item */
          stack = [ int ]
      LineNumberTable:
        line 209: 0
      LocalVariableTable:
        Start  Length  Slot  Name   Signature
            0      57     0  this   Lorg/sireum/package$$Int2Z$;
            0      57     1 $this   I
            0      57     2   x$1   Ljava/lang/Object;
    MethodParameters:
      Name                           Flags
      $this                          final
      x$1                            final

  public org.sireum.package$$Int2Z$();
    descriptor: ()V
    flags: (0x0001) ACC_PUBLIC
    Code:
      stack=1, locals=1, args_size=1
         0: aload_0
         1: invokespecial #240                // Method java/lang/Object."<init>":()V
         4: return
      LineNumberTable:
        line 209: 0
      LocalVariableTable:
        Start  Length  Slot  Name   Signature
            0       5     0  this   Lorg/sireum/package$$Int2Z$;
}
InnerClasses:
  public static final #10= #7 of #9;      // $Int2Z=class org/sireum/package$$Int2Z of class org/sireum/package
  public static #11= #2 of #9;            // $Int2Z$=class org/sireum/package$$Int2Z$ of class org/sireum/package
  public static #14= #13 of #9;           // Any2HashString$=class org/sireum/package$Any2HashString$ of class org/sireum/package
SourceFile: "package.scala"
  ScalaInlineInfo: length = 0x90 (unknown attribute)
   01 01 00 1C 00 6C 00 5F 05 00 5D 00 3D 05 00 50
   00 3D 05 00 4C 00 3D 05 00 48 00 3D 05 00 44 00
   3D 05 00 3C 00 3D 05 00 64 00 5F 05 00 70 00 5F
   05 00 5E 00 5F 05 00 88 00 97 05 00 88 00 BF 05
   00 88 00 AF 05 00 88 00 A7 05 00 88 00 A9 05 00
   88 00 DF 05 00 88 00 CF 05 00 88 00 89 05 00 68
   00 5F 05 00 13 00 12 01 00 79 00 19 05 00 E9 00
   EA 01 00 18 00 19 05 00 E2 00 E3 01 00 74 00 19
   05 00 34 00 35 05 00 7D 00 7E 05 00 84 00 7E 05

  Scala: length = 0x0 (unknown attribute)

