Classfile /Users/mw/Projects/slang-braindump/.jar/jar11/assemble/slang-braindump/assemble/content/org/sireum/R$$String$.class
  Last modified May 29, 2022; size 913 bytes
  SHA-256 checksum 2eab69bffbc76509324c1f3ac85a0a53a31f0710fcbaafbfc55161606df388a6
  Compiled from "R.scala"
public class org.sireum.R$$String$
  minor version: 0
  major version: 52
  flags: (0x0021) ACC_PUBLIC, ACC_SUPER
  this_class: #2                          // org/sireum/R$$String$
  super_class: #4                         // java/lang/Object
  interfaces: 0, fields: 1, methods: 3, attributes: 4
Constant pool:
   #1 = Utf8               org/sireum/R$$String$
   #2 = Class              #1             // org/sireum/R$$String$
   #3 = Utf8               java/lang/Object
   #4 = Class              #3             // java/lang/Object
   #5 = Utf8               R.scala
   #6 = Utf8               org/sireum/R
   #7 = Class              #6             // org/sireum/R
   #8 = Utf8               $String$
   #9 = Utf8               MODULE$
  #10 = Utf8               Lorg/sireum/R$$String$;
  #11 = Utf8               <clinit>
  #12 = Utf8               ()V
  #13 = Utf8               <init>
  #14 = NameAndType        #13:#12        // "<init>":()V
  #15 = Methodref          #2.#14         // org/sireum/R$$String$."<init>":()V
  #16 = NameAndType        #9:#10         // MODULE$:Lorg/sireum/R$$String$;
  #17 = Fieldref           #2.#16         // org/sireum/R$$String$.MODULE$:Lorg/sireum/R$$String$;
  #18 = Utf8               apply
  #19 = Utf8               (Ljava/lang/String;)Lscala/math/BigDecimal;
  #20 = Utf8               s
  #21 = Utf8               org/sireum/R$
  #22 = Class              #21            // org/sireum/R$
  #23 = Utf8               Lorg/sireum/R$;
  #24 = NameAndType        #9:#23         // MODULE$:Lorg/sireum/R$;
  #25 = Fieldref           #22.#24        // org/sireum/R$.MODULE$:Lorg/sireum/R$;
  #26 = Utf8               scala/package$
  #27 = Class              #26            // scala/package$
  #28 = Utf8               Lscala/package$;
  #29 = NameAndType        #9:#28         // MODULE$:Lscala/package$;
  #30 = Fieldref           #27.#29        // scala/package$.MODULE$:Lscala/package$;
  #31 = Utf8               BigDecimal
  #32 = Utf8               ()Lscala/math/BigDecimal$;
  #33 = NameAndType        #31:#32        // BigDecimal:()Lscala/math/BigDecimal$;
  #34 = Methodref          #27.#33        // scala/package$.BigDecimal:()Lscala/math/BigDecimal$;
  #35 = Utf8               scala/math/BigDecimal$
  #36 = Class              #35            // scala/math/BigDecimal$
  #37 = NameAndType        #18:#19        // apply:(Ljava/lang/String;)Lscala/math/BigDecimal;
  #38 = Methodref          #36.#37        // scala/math/BigDecimal$.apply:(Ljava/lang/String;)Lscala/math/BigDecimal;
  #39 = Utf8               (Lscala/math/BigDecimal;)Lscala/math/BigDecimal;
  #40 = NameAndType        #18:#39        // apply:(Lscala/math/BigDecimal;)Lscala/math/BigDecimal;
  #41 = Methodref          #22.#40        // org/sireum/R$.apply:(Lscala/math/BigDecimal;)Lscala/math/BigDecimal;
  #42 = Utf8               this
  #43 = Utf8               Ljava/lang/String;
  #44 = Methodref          #4.#14         // java/lang/Object."<init>":()V
  #45 = Utf8               Code
  #46 = Utf8               LineNumberTable
  #47 = Utf8               LocalVariableTable
  #48 = Utf8               MethodParameters
  #49 = Utf8               InnerClasses
  #50 = Utf8               SourceFile
  #51 = Utf8               ScalaInlineInfo
  #52 = Utf8               Scala
{
  public static final org.sireum.R$$String$ MODULE$;
    descriptor: Lorg/sireum/R$$String$;
    flags: (0x0019) ACC_PUBLIC, ACC_STATIC, ACC_FINAL

  public static {};
    descriptor: ()V
    flags: (0x0009) ACC_PUBLIC, ACC_STATIC
    Code:
      stack=2, locals=0, args_size=0
         0: new           #2                  // class org/sireum/R$$String$
         3: dup
         4: invokespecial #15                 // Method "<init>":()V
         7: putstatic     #17                 // Field MODULE$:Lorg/sireum/R$$String$;
        10: return
      LineNumberTable:
        line 55: 0

  public scala.math.BigDecimal apply(java.lang.String);
    descriptor: (Ljava/lang/String;)Lscala/math/BigDecimal;
    flags: (0x0001) ACC_PUBLIC
    Code:
      stack=3, locals=2, args_size=2
         0: getstatic     #25                 // Field org/sireum/R$.MODULE$:Lorg/sireum/R$;
         3: getstatic     #30                 // Field scala/package$.MODULE$:Lscala/package$;
         6: invokevirtual #34                 // Method scala/package$.BigDecimal:()Lscala/math/BigDecimal$;
         9: aload_1
        10: invokevirtual #38                 // Method scala/math/BigDecimal$.apply:(Ljava/lang/String;)Lscala/math/BigDecimal;
        13: invokevirtual #41                 // Method org/sireum/R$.apply:(Lscala/math/BigDecimal;)Lscala/math/BigDecimal;
        16: areturn
      LineNumberTable:
        line 56: 0
      LocalVariableTable:
        Start  Length  Slot  Name   Signature
            0      17     0  this   Lorg/sireum/R$$String$;
            0      17     1     s   Ljava/lang/String;
    MethodParameters:
      Name                           Flags
      s                              final

  public org.sireum.R$$String$();
    descriptor: ()V
    flags: (0x0001) ACC_PUBLIC
    Code:
      stack=1, locals=1, args_size=1
         0: aload_0
         1: invokespecial #44                 // Method java/lang/Object."<init>":()V
         4: return
      LineNumberTable:
        line 55: 0
      LocalVariableTable:
        Start  Length  Slot  Name   Signature
            0       5     0  this   Lorg/sireum/R$$String$;
}
InnerClasses:
  public static #8= #2 of #7;             // $String$=class org/sireum/R$$String$ of class org/sireum/R
SourceFile: "R.scala"
  ScalaInlineInfo: length = 0xE (unknown attribute)
   01 01 00 02 00 0D 00 0C 01 00 12 00 13 01
  Scala: length = 0x0 (unknown attribute)

