Classfile /Users/mw/Projects/slang-braindump/.jar/jar11/assemble/slang-braindump/assemble/content/org/sireum/range.class
  Last modified May 29, 2022; size 1356 bytes
  SHA-256 checksum 116dfae0c83fdaaf86fc638377d67c0414c41e4b6594741c7deada1a5d5055c4
  Compiled from "Annotations.scala"
public class org.sireum.range
  minor version: 0
  major version: 52
  flags: (0x0021) ACC_PUBLIC, ACC_SUPER
  this_class: #2                          // org/sireum/range
  super_class: #4                         // java/lang/Object
  interfaces: 0, fields: 0, methods: 4, attributes: 4
Constant pool:
   #1 = Utf8               org/sireum/range
   #2 = Class              #1             // org/sireum/range
   #3 = Utf8               java/lang/Object
   #4 = Class              #3             // java/lang/Object
   #5 = Utf8               Annotations.scala
   #6 = Utf8               Lscala/reflect/ScalaSignature;
   #7 = Utf8               bytes
   #8 = Utf8               \u0006\u0005q2Aa\u0003\u0007\u0001#!A\u0001\u0004\u0001B\u0001B\u0003%\u0011\u0004\u0003\u0005\u001e\u0001\t\u0005\t\u0015!\u0003\u001a\u0011!q\u0002A!A!\u0002\u0013y\u0002\"\u0002\u0012\u0001\t\u0003\u0019sa\u0002\u0015\r\u0003\u0003E\t!\u000b\u0004\b\u00171\t\t\u0011#\u0001+\u0011\u0015\u0011c\u0001\"\u0001,\u0011\u001dac!%A\u0005\u00025Bq\u0001\u000f\u0004\u0012\u0002\u0013\u0005Q\u0006C\u0004:\rE\u0005I\u0011\u0001\u001e\u0003\u000bI\fgnZ3\u000b\u00055q\u0011AB:je\u0016,XNC\u0001\u0010\u0003\ry\'oZ\u0002\u0001\'\t\u0001!\u0003\u0005\u0002\u0014-5\tACC\u0001\u0016\u0003\u0015\u00198-\u00197b\u0013\t9BC\u0001\u0004B]f\u0014VMZ\u0001\u0004[&t\u0007C\u0001\u000e\u001c\u001b\u0005a\u0011B\u0001\u000f\r\u0005\u0005Q\u0016aA7bq\u0006)\u0011N\u001c3fqB\u0011!\u0004I\u0005\u0003C1\u0011\u0011AQ\u0001\u0007y%t\u0017\u000e\u001e \u0015\t\u0011*ce\n\t\u00035\u0001Aq\u0001\u0007\u0003\u0011\u0002\u0003\u0007\u0011\u0004C\u0004\u001e\tA\u0005\t\u0019A\r\t\u000fy!\u0001\u0013!a\u0001?\u0005)!/\u00198hKB\u0011!DB\n\u0003\rI!\u0012!K\u0001\u001cI1,7o]5oSR$sM]3bi\u0016\u0014H\u0005Z3gCVdG\u000fJ\u0019\u0016\u00039R#!G\u0018,\u0003A\u0002\"!\r\u001c\u000e\u0003IR!a\r\u001b\u0002\u0013Ut7\r[3dW\u0016$\'BA\u001b\u0015\u0003)\tgN\\8uCRLwN\\\u0005\u0003oI\u0012\u0011#\u001e8dQ\u0016\u001c7.\u001a3WCJL\u0017M\\2f\u0003m!C.Z:tS:LG\u000fJ4sK\u0006$XM\u001d\u0013eK\u001a\fW\u000f\u001c;%e\u0005YB\u0005\\3tg&t\u0017\u000e\u001e\u0013he\u0016\fG/\u001a:%I\u00164\u0017-\u001e7uIM*\u0012a\u000f\u0016\u0003?=\u0002
   #9 = Utf8               $lessinit$greater$default$3
  #10 = Utf8               ()Z
  #11 = Utf8               org/sireum/range$
  #12 = Class              #11            // org/sireum/range$
  #13 = Utf8               MODULE$
  #14 = Utf8               Lorg/sireum/range$;
  #15 = NameAndType        #13:#14        // MODULE$:Lorg/sireum/range$;
  #16 = Fieldref           #12.#15        // org/sireum/range$.MODULE$:Lorg/sireum/range$;
  #17 = NameAndType        #9:#10         // $lessinit$greater$default$3:()Z
  #18 = Methodref          #12.#17        // org/sireum/range$.$lessinit$greater$default$3:()Z
  #19 = Utf8               $lessinit$greater$default$2
  #20 = Utf8               ()Lorg/sireum/Z;
  #21 = NameAndType        #19:#20        // $lessinit$greater$default$2:()Lorg/sireum/Z;
  #22 = Methodref          #12.#21        // org/sireum/range$.$lessinit$greater$default$2:()Lorg/sireum/Z;
  #23 = Utf8               $lessinit$greater$default$1
  #24 = NameAndType        #23:#20        // $lessinit$greater$default$1:()Lorg/sireum/Z;
  #25 = Methodref          #12.#24        // org/sireum/range$.$lessinit$greater$default$1:()Lorg/sireum/Z;
  #26 = Utf8               <init>
  #27 = Utf8               (Lorg/sireum/Z;Lorg/sireum/Z;Z)V
  #28 = Utf8               min
  #29 = Utf8               max
  #30 = Utf8               index
  #31 = Utf8               ()V
  #32 = NameAndType        #26:#31        // "<init>":()V
  #33 = Methodref          #4.#32         // java/lang/Object."<init>":()V
  #34 = Utf8               this
  #35 = Utf8               Lorg/sireum/range;
  #36 = Utf8               Lorg/sireum/Z;
  #37 = Utf8               Z
  #38 = Utf8               Code
  #39 = Utf8               LineNumberTable
  #40 = Utf8               LocalVariableTable
  #41 = Utf8               MethodParameters
  #42 = Utf8               SourceFile
  #43 = Utf8               RuntimeVisibleAnnotations
  #44 = Utf8               ScalaInlineInfo
  #45 = Utf8               ScalaSig
{
  public static boolean $lessinit$greater$default$3();
    descriptor: ()Z
    flags: (0x0009) ACC_PUBLIC, ACC_STATIC
    Code:
      stack=1, locals=0, args_size=0
         0: getstatic     #16                 // Field org/sireum/range$.MODULE$:Lorg/sireum/range$;
         3: invokevirtual #18                 // Method org/sireum/range$.$lessinit$greater$default$3:()Z
         6: ireturn

  public static org.sireum.Z $lessinit$greater$default$2();
    descriptor: ()Lorg/sireum/Z;
    flags: (0x0009) ACC_PUBLIC, ACC_STATIC
    Code:
      stack=1, locals=0, args_size=0
         0: getstatic     #16                 // Field org/sireum/range$.MODULE$:Lorg/sireum/range$;
         3: invokevirtual #22                 // Method org/sireum/range$.$lessinit$greater$default$2:()Lorg/sireum/Z;
         6: areturn

  public static org.sireum.Z $lessinit$greater$default$1();
    descriptor: ()Lorg/sireum/Z;
    flags: (0x0009) ACC_PUBLIC, ACC_STATIC
    Code:
      stack=1, locals=0, args_size=0
         0: getstatic     #16                 // Field org/sireum/range$.MODULE$:Lorg/sireum/range$;
         3: invokevirtual #25                 // Method org/sireum/range$.$lessinit$greater$default$1:()Lorg/sireum/Z;
         6: areturn

  public org.sireum.range(org.sireum.Z, org.sireum.Z, boolean);
    descriptor: (Lorg/sireum/Z;Lorg/sireum/Z;Z)V
    flags: (0x0001) ACC_PUBLIC
    Code:
      stack=1, locals=4, args_size=4
         0: aload_0
         1: invokespecial #33                 // Method java/lang/Object."<init>":()V
         4: return
      LineNumberTable:
        line 54: 0
      LocalVariableTable:
        Start  Length  Slot  Name   Signature
            0       5     0  this   Lorg/sireum/range;
            0       5     1   min   Lorg/sireum/Z;
            0       5     2   max   Lorg/sireum/Z;
            0       5     3 index   Z
    MethodParameters:
      Name                           Flags
      min                            final
      max                            final
      index                          final
}
SourceFile: "Annotations.scala"
RuntimeVisibleAnnotations:
  0: #6(#7=s#8)
    scala.reflect.ScalaSignature(
      bytes="\u0006\u0005q2Aa\u0003\u0007\u0001#!A\u0001\u0004\u0001B\u0001B\u0003%\u0011\u0004\u0003\u0005\u001e\u0001\t\u0005\t\u0015!\u0003\u001a\u0011!q\u0002A!A!\u0002\u0013y\u0002\"\u0002\u0012\u0001\t\u0003\u0019sa\u0002\u0015\r\u0003\u0003E\t!\u000b\u0004\b\u00171\t\t\u0011#\u0001+\u0011\u0015\u0011c\u0001\"\u0001,\u0011\u001dac!%A\u0005\u00025Bq\u0001\u000f\u0004\u0012\u0002\u0013\u0005Q\u0006C\u0004:\rE\u0005I\u0011\u0001\u001e\u0003\u000bI\fgnZ3\u000b\u00055q\u0011AB:je\u0016,XNC\u0001\u0010\u0003\ry\'oZ\u0002\u0001\'\t\u0001!\u0003\u0005\u0002\u0014-5\tACC\u0001\u0016\u0003\u0015\u00198-\u00197b\u0013\t9BC\u0001\u0004B]f\u0014VMZ\u0001\u0004[&t\u0007C\u0001\u000e\u001c\u001b\u0005a\u0011B\u0001\u000f\r\u0005\u0005Q\u0016aA7bq\u0006)\u0011N\u001c3fqB\u0011!\u0004I\u0005\u0003C1\u0011\u0011AQ\u0001\u0007y%t\u0017\u000e\u001e \u0015\t\u0011*ce\n\t\u00035\u0001Aq\u0001\u0007\u0003\u0011\u0002\u0003\u0007\u0011\u0004C\u0004\u001e\tA\u0005\t\u0019A\r\t\u000fy!\u0001\u0013!a\u0001?\u0005)!/\u00198hKB\u0011!DB\n\u0003\rI!\u0012!K\u0001\u001cI1,7o]5oSR$sM]3bi\u0016\u0014H\u0005Z3gCVdG\u000fJ\u0019\u0016\u00039R#!G\u0018,\u0003A\u0002\"!\r\u001c\u000e\u0003IR!a\r\u001b\u0002\u0013Ut7\r[3dW\u0016$\'BA\u001b\u0015\u0003)\tgN\\8uCRLwN\\\u0005\u0003oI\u0012\u0011#\u001e8dQ\u0016\u001c7.\u001a3WCJL\u0017M\\2f\u0003m!C.Z:tS:LG\u000fJ4sK\u0006$XM\u001d\u0013eK\u001a\fW\u000f\u001c;%e\u0005YB\u0005\\3tg&t\u0017\u000e\u001e\u0013he\u0016\fG/\u001a:%I\u00164\u0017-\u001e7uIM*\u0012a\u000f\u0016\u0003?=\u0002"
    )
  ScalaInlineInfo: length = 0x9 (unknown attribute)
   01 00 00 01 00 1A 00 1B 00
  ScalaSig: length = 0x3 (unknown attribute)
   05 02 00
