Classfile /Users/mw/Projects/slang-braindump/.jar/jar11/assemble/slang-braindump/assemble/content/org/sireum/ST$Any$.class
  Last modified May 29, 2022; size 3270 bytes
  SHA-256 checksum 01ed8cb7b7c10a29110b041a5af72a68941ff64da507347542821f78a73c71db
  Compiled from "ST.scala"
public class org.sireum.ST$Any$
  minor version: 0
  major version: 52
  flags: (0x0021) ACC_PUBLIC, ACC_SUPER
  this_class: #2                          // org/sireum/ST$Any$
  super_class: #4                         // java/lang/Object
  interfaces: 0, fields: 1, methods: 7, attributes: 5
Constant pool:
    #1 = Utf8               org/sireum/ST$Any$
    #2 = Class              #1            // org/sireum/ST$Any$
    #3 = Utf8               java/lang/Object
    #4 = Class              #3            // java/lang/Object
    #5 = Utf8               ST.scala
    #6 = Utf8               java/lang/invoke/MethodHandles$Lookup
    #7 = Class              #6            // java/lang/invoke/MethodHandles$Lookup
    #8 = Utf8               java/lang/invoke/MethodHandles
    #9 = Class              #8            // java/lang/invoke/MethodHandles
   #10 = Utf8               Lookup
   #11 = Utf8               org/sireum/ST$Any
   #12 = Class              #11           // org/sireum/ST$Any
   #13 = Utf8               org/sireum/ST
   #14 = Class              #13           // org/sireum/ST
   #15 = Utf8               Any
   #16 = Utf8               Any$
   #17 = Utf8               MODULE$
   #18 = Utf8               Lorg/sireum/ST$Any$;
   #19 = Utf8               <clinit>
   #20 = Utf8               ()V
   #21 = Utf8               <init>
   #22 = NameAndType        #21:#20       // "<init>":()V
   #23 = Methodref          #2.#22        // org/sireum/ST$Any$."<init>":()V
   #24 = NameAndType        #17:#18       // MODULE$:Lorg/sireum/ST$Any$;
   #25 = Fieldref           #2.#24        // org/sireum/ST$Any$.MODULE$:Lorg/sireum/ST$Any$;
   #26 = Utf8               apply
   #27 = Utf8               (Lscala/collection/immutable/Seq;Ljava/lang/String;)Lorg/sireum/ST$Any;
   #28 = Utf8               (Lscala/collection/immutable/Seq<Ljava/lang/Object;>;Ljava/lang/String;)Lorg/sireum/ST$Any;
   #29 = Utf8               args
   #30 = Utf8               sep
   #31 = Utf8               scala/collection/ArrayOps$
   #32 = Class              #31           // scala/collection/ArrayOps$
   #33 = Utf8               Lscala/collection/ArrayOps$;
   #34 = NameAndType        #17:#33       // MODULE$:Lscala/collection/ArrayOps$;
   #35 = Fieldref           #32.#34       // scala/collection/ArrayOps$.MODULE$:Lscala/collection/ArrayOps$;
   #36 = Utf8               scala/Predef$
   #37 = Class              #36           // scala/Predef$
   #38 = Utf8               Lscala/Predef$;
   #39 = NameAndType        #17:#38       // MODULE$:Lscala/Predef$;
   #40 = Fieldref           #37.#39       // scala/Predef$.MODULE$:Lscala/Predef$;
   #41 = Utf8               scala/reflect/ClassTag$
   #42 = Class              #41           // scala/reflect/ClassTag$
   #43 = Utf8               Lscala/reflect/ClassTag$;
   #44 = NameAndType        #17:#43       // MODULE$:Lscala/reflect/ClassTag$;
   #45 = Fieldref           #42.#44       // scala/reflect/ClassTag$.MODULE$:Lscala/reflect/ClassTag$;
   #46 = Utf8               ()Lscala/reflect/ClassTag;
   #47 = NameAndType        #15:#46       // Any:()Lscala/reflect/ClassTag;
   #48 = Methodref          #42.#47       // scala/reflect/ClassTag$.Any:()Lscala/reflect/ClassTag;
   #49 = Utf8               scala/collection/immutable/Seq
   #50 = Class              #49           // scala/collection/immutable/Seq
   #51 = Utf8               toArray
   #52 = Utf8               (Lscala/reflect/ClassTag;)Ljava/lang/Object;
   #53 = NameAndType        #51:#52       // toArray:(Lscala/reflect/ClassTag;)Ljava/lang/Object;
   #54 = InterfaceMethodref #50.#53       // scala/collection/immutable/Seq.toArray:(Lscala/reflect/ClassTag;)Ljava/lang/Object;
   #55 = Utf8               genericArrayOps
   #56 = Utf8               (Ljava/lang/Object;)Ljava/lang/Object;
   #57 = NameAndType        #55:#56       // genericArrayOps:(Ljava/lang/Object;)Ljava/lang/Object;
   #58 = Methodref          #37.#57       // scala/Predef$.genericArrayOps:(Ljava/lang/Object;)Ljava/lang/Object;
   #59 = MethodType         #56           //  (Ljava/lang/Object;)Ljava/lang/Object;
   #60 = Utf8               $anonfun$apply$1
   #61 = NameAndType        #60:#56       // $anonfun$apply$1:(Ljava/lang/Object;)Ljava/lang/Object;
   #62 = Methodref          #2.#61        // org/sireum/ST$Any$.$anonfun$apply$1:(Ljava/lang/Object;)Ljava/lang/Object;
   #63 = MethodHandle       6:#62         // REF_invokeStatic org/sireum/ST$Any$.$anonfun$apply$1:(Ljava/lang/Object;)Ljava/lang/Object;
   #64 = Integer            1
   #65 = Utf8               java/lang/invoke/LambdaMetafactory
   #66 = Class              #65           // java/lang/invoke/LambdaMetafactory
   #67 = Utf8               altMetafactory
   #68 = Utf8               (Ljava/lang/invoke/MethodHandles$Lookup;Ljava/lang/String;Ljava/lang/invoke/MethodType;[Ljava/lang/Object;)Ljava/lang/invoke/CallSite;
   #69 = NameAndType        #67:#68       // altMetafactory:(Ljava/lang/invoke/MethodHandles$Lookup;Ljava/lang/String;Ljava/lang/invoke/MethodType;[Ljava/lang/Object;)Ljava/lang/invoke/CallSite;
   #70 = Methodref          #66.#69       // java/lang/invoke/LambdaMetafactory.altMetafactory:(Ljava/lang/invoke/MethodHandles$Lookup;Ljava/lang/String;Ljava/lang/invoke/MethodType;[Ljava/lang/Object;)Ljava/lang/invoke/CallSite;
   #71 = MethodHandle       6:#70         // REF_invokeStatic java/lang/invoke/LambdaMetafactory.altMetafactory:(Ljava/lang/invoke/MethodHandles$Lookup;Ljava/lang/String;Ljava/lang/invoke/MethodType;[Ljava/lang/Object;)Ljava/lang/invoke/CallSite;
   #72 = Utf8               ()Lscala/Function1;
   #73 = NameAndType        #26:#72       // apply:()Lscala/Function1;
   #74 = InvokeDynamic      #0:#73        // #0:apply:()Lscala/Function1;
   #75 = Utf8               map$extension
   #76 = Utf8               (Ljava/lang/Object;Lscala/Function1;Lscala/reflect/ClassTag;)Ljava/lang/Object;
   #77 = NameAndType        #75:#76       // map$extension:(Ljava/lang/Object;Lscala/Function1;Lscala/reflect/ClassTag;)Ljava/lang/Object;
   #78 = Methodref          #32.#77       // scala/collection/ArrayOps$.map$extension:(Ljava/lang/Object;Lscala/Function1;Lscala/reflect/ClassTag;)Ljava/lang/Object;
   #79 = Utf8               [Ljava/lang/Object;
   #80 = Class              #79           // "[Ljava/lang/Object;"
   #81 = Utf8               ([Ljava/lang/Object;Ljava/lang/String;)V
   #82 = NameAndType        #21:#81       // "<init>":([Ljava/lang/Object;Ljava/lang/String;)V
   #83 = Methodref          #12.#82       // org/sireum/ST$Any."<init>":([Ljava/lang/Object;Ljava/lang/String;)V
   #84 = Utf8               this
   #85 = Utf8               Lscala/collection/immutable/Seq;
   #86 = Utf8               Ljava/lang/String;
   #87 = Utf8               apply$default$2
   #88 = Utf8               ()Ljava/lang/String;
   #89 = Utf8
   #90 = String             #89           //
   #91 = Utf8               unapply
   #92 = Utf8               (Lorg/sireum/ST$Any;)Lscala/Some;
   #93 = Utf8               (Lorg/sireum/ST$Any;)Lscala/Some<Lscala/Tuple2<Lscala/collection/immutable/Seq<Ljava/lang/Object;>;Ljava/lang/String;>;>;
   #94 = Utf8               o
   #95 = Utf8               scala/Some
   #96 = Class              #95           // scala/Some
   #97 = Utf8               scala/Tuple2
   #98 = Class              #97           // scala/Tuple2
   #99 = Utf8               ()[Ljava/lang/Object;
  #100 = NameAndType        #29:#99       // args:()[Ljava/lang/Object;
  #101 = Methodref          #12.#100      // org/sireum/ST$Any.args:()[Ljava/lang/Object;
  #102 = Utf8               toSeq$extension
  #103 = Utf8               (Ljava/lang/Object;)Lscala/collection/immutable/Seq;
  #104 = NameAndType        #102:#103     // toSeq$extension:(Ljava/lang/Object;)Lscala/collection/immutable/Seq;
  #105 = Methodref          #32.#104      // scala/collection/ArrayOps$.toSeq$extension:(Ljava/lang/Object;)Lscala/collection/immutable/Seq;
  #106 = NameAndType        #30:#88       // sep:()Ljava/lang/String;
  #107 = Methodref          #12.#106      // org/sireum/ST$Any.sep:()Ljava/lang/String;
  #108 = Utf8               (Ljava/lang/Object;Ljava/lang/Object;)V
  #109 = NameAndType        #21:#108      // "<init>":(Ljava/lang/Object;Ljava/lang/Object;)V
  #110 = Methodref          #98.#109      // scala/Tuple2."<init>":(Ljava/lang/Object;Ljava/lang/Object;)V
  #111 = Utf8               (Ljava/lang/Object;)V
  #112 = NameAndType        #21:#111      // "<init>":(Ljava/lang/Object;)V
  #113 = Methodref          #96.#112      // scala/Some."<init>":(Ljava/lang/Object;)V
  #114 = Utf8               Lorg/sireum/ST$Any;
  #115 = Utf8               x0$1
  #116 = Utf8               org/sireum/Mutable
  #117 = Class              #116          // org/sireum/Mutable
  #118 = Utf8               org/sireum/helper$
  #119 = Class              #118          // org/sireum/helper$
  #120 = Utf8               Lorg/sireum/helper$;
  #121 = NameAndType        #17:#120      // MODULE$:Lorg/sireum/helper$;
  #122 = Fieldref           #119.#121     // org/sireum/helper$.MODULE$:Lorg/sireum/helper$;
  #123 = Utf8               cloneAssign
  #124 = NameAndType        #123:#56      // cloneAssign:(Ljava/lang/Object;)Ljava/lang/Object;
  #125 = Methodref          #119.#124     // org/sireum/helper$.cloneAssign:(Ljava/lang/Object;)Ljava/lang/Object;
  #126 = Utf8               Ljava/lang/Object;
  #127 = Methodref          #4.#22        // java/lang/Object."<init>":()V
  #128 = Utf8               $deserializeLambda$
  #129 = Utf8               (Ljava/lang/invoke/SerializedLambda;)Ljava/lang/Object;
  #130 = Utf8               scala/runtime/LambdaDeserialize
  #131 = Class              #130          // scala/runtime/LambdaDeserialize
  #132 = Utf8               bootstrap
  #133 = Utf8               (Ljava/lang/invoke/MethodHandles$Lookup;Ljava/lang/String;Ljava/lang/invoke/MethodType;[Ljava/lang/invoke/MethodHandle;)Ljava/lang/invoke/CallSite;
  #134 = NameAndType        #132:#133     // bootstrap:(Ljava/lang/invoke/MethodHandles$Lookup;Ljava/lang/String;Ljava/lang/invoke/MethodType;[Ljava/lang/invoke/MethodHandle;)Ljava/lang/invoke/CallSite;
  #135 = Methodref          #131.#134     // scala/runtime/LambdaDeserialize.bootstrap:(Ljava/lang/invoke/MethodHandles$Lookup;Ljava/lang/String;Ljava/lang/invoke/MethodType;[Ljava/lang/invoke/MethodHandle;)Ljava/lang/invoke/CallSite;
  #136 = MethodHandle       6:#135        // REF_invokeStatic scala/runtime/LambdaDeserialize.bootstrap:(Ljava/lang/invoke/MethodHandles$Lookup;Ljava/lang/String;Ljava/lang/invoke/MethodType;[Ljava/lang/invoke/MethodHandle;)Ljava/lang/invoke/CallSite;
  #137 = Utf8               lambdaDeserialize
  #138 = NameAndType        #137:#129     // lambdaDeserialize:(Ljava/lang/invoke/SerializedLambda;)Ljava/lang/Object;
  #139 = InvokeDynamic      #1:#138       // #1:lambdaDeserialize:(Ljava/lang/invoke/SerializedLambda;)Ljava/lang/Object;
  #140 = Utf8               Code
  #141 = Utf8               LineNumberTable
  #142 = Utf8               LocalVariableTable
  #143 = Utf8               Signature
  #144 = Utf8               MethodParameters
  #145 = Utf8               StackMapTable
  #146 = Utf8               InnerClasses
  #147 = Utf8               SourceFile
  #148 = Utf8               BootstrapMethods
  #149 = Utf8               ScalaInlineInfo
  #150 = Utf8               Scala
{
  public static final org.sireum.ST$Any$ MODULE$;
    descriptor: Lorg/sireum/ST$Any$;
    flags: (0x0019) ACC_PUBLIC, ACC_STATIC, ACC_FINAL

  public static {};
    descriptor: ()V
    flags: (0x0009) ACC_PUBLIC, ACC_STATIC
    Code:
      stack=2, locals=0, args_size=0
         0: new           #2                  // class org/sireum/ST$Any$
         3: dup
         4: invokespecial #23                 // Method "<init>":()V
         7: putstatic     #25                 // Field MODULE$:Lorg/sireum/ST$Any$;
        10: return
      LineNumberTable:
        line 34: 0

  public org.sireum.ST$Any apply(scala.collection.immutable.Seq<java.lang.Object>, java.lang.String);
    descriptor: (Lscala/collection/immutable/Seq;Ljava/lang/String;)Lorg/sireum/ST$Any;
    flags: (0x0001) ACC_PUBLIC
    Code:
      stack=6, locals=3, args_size=3
         0: new           #12                 // class org/sireum/ST$Any
         3: dup
         4: getstatic     #35                 // Field scala/collection/ArrayOps$.MODULE$:Lscala/collection/ArrayOps$;
         7: getstatic     #40                 // Field scala/Predef$.MODULE$:Lscala/Predef$;
        10: aload_1
        11: getstatic     #45                 // Field scala/reflect/ClassTag$.MODULE$:Lscala/reflect/ClassTag$;
        14: invokevirtual #48                 // Method scala/reflect/ClassTag$.Any:()Lscala/reflect/ClassTag;
        17: invokeinterface #54,  2           // InterfaceMethod scala/collection/immutable/Seq.toArray:(Lscala/reflect/ClassTag;)Ljava/lang/Object;
        22: invokevirtual #58                 // Method scala/Predef$.genericArrayOps:(Ljava/lang/Object;)Ljava/lang/Object;
        25: invokedynamic #74,  0             // InvokeDynamic #0:apply:()Lscala/Function1;
        30: getstatic     #45                 // Field scala/reflect/ClassTag$.MODULE$:Lscala/reflect/ClassTag$;
        33: invokevirtual #48                 // Method scala/reflect/ClassTag$.Any:()Lscala/reflect/ClassTag;
        36: invokevirtual #78                 // Method scala/collection/ArrayOps$.map$extension:(Ljava/lang/Object;Lscala/Function1;Lscala/reflect/ClassTag;)Ljava/lang/Object;
        39: checkcast     #80                 // class "[Ljava/lang/Object;"
        42: aload_2
        43: invokespecial #83                 // Method org/sireum/ST$Any."<init>":([Ljava/lang/Object;Ljava/lang/String;)V
        46: areturn
      LineNumberTable:
        line 36: 0
        line 39: 42
      LocalVariableTable:
        Start  Length  Slot  Name   Signature
            0      47     0  this   Lorg/sireum/ST$Any$;
            0      47     1  args   Lscala/collection/immutable/Seq;
            0      47     2   sep   Ljava/lang/String;
    Signature: #28                          // (Lscala/collection/immutable/Seq<Ljava/lang/Object;>;Ljava/lang/String;)Lorg/sireum/ST$Any;
    MethodParameters:
      Name                           Flags
      args                           final
      sep                            final

  public java.lang.String apply$default$2();
    descriptor: ()Ljava/lang/String;
    flags: (0x0001) ACC_PUBLIC
    Code:
      stack=1, locals=1, args_size=1
         0: ldc           #90                 // String
         2: areturn
      LineNumberTable:
        line 35: 0
      LocalVariableTable:
        Start  Length  Slot  Name   Signature
            0       3     0  this   Lorg/sireum/ST$Any$;

  public scala.Some<scala.Tuple2<scala.collection.immutable.Seq<java.lang.Object>, java.lang.String>> unapply(org.sireum.ST$Any);
    descriptor: (Lorg/sireum/ST$Any;)Lscala/Some;
    flags: (0x0001) ACC_PUBLIC
    Code:
      stack=7, locals=2, args_size=2
         0: new           #96                 // class scala/Some
         3: dup
         4: new           #98                 // class scala/Tuple2
         7: dup
         8: getstatic     #35                 // Field scala/collection/ArrayOps$.MODULE$:Lscala/collection/ArrayOps$;
        11: getstatic     #40                 // Field scala/Predef$.MODULE$:Lscala/Predef$;
        14: aload_1
        15: invokevirtual #101                // Method org/sireum/ST$Any.args:()[Ljava/lang/Object;
        18: invokevirtual #58                 // Method scala/Predef$.genericArrayOps:(Ljava/lang/Object;)Ljava/lang/Object;
        21: invokevirtual #105                // Method scala/collection/ArrayOps$.toSeq$extension:(Ljava/lang/Object;)Lscala/collection/immutable/Seq;
        24: aload_1
        25: invokevirtual #107                // Method org/sireum/ST$Any.sep:()Ljava/lang/String;
        28: invokespecial #110                // Method scala/Tuple2."<init>":(Ljava/lang/Object;Ljava/lang/Object;)V
        31: invokespecial #113                // Method scala/Some."<init>":(Ljava/lang/Object;)V
        34: areturn
      LineNumberTable:
        line 41: 0
      LocalVariableTable:
        Start  Length  Slot  Name   Signature
            0      35     0  this   Lorg/sireum/ST$Any$;
            0      35     1     o   Lorg/sireum/ST$Any;
    Signature: #93                          // (Lorg/sireum/ST$Any;)Lscala/Some<Lscala/Tuple2<Lscala/collection/immutable/Seq<Ljava/lang/Object;>;Ljava/lang/String;>;>;
    MethodParameters:
      Name                           Flags
      o                              final

  public static final java.lang.Object $anonfun$apply$1(java.lang.Object);
    descriptor: (Ljava/lang/Object;)Ljava/lang/Object;
    flags: (0x1019) ACC_PUBLIC, ACC_STATIC, ACC_FINAL, ACC_SYNTHETIC
    Code:
      stack=2, locals=4, args_size=1
         0: aload_0
         1: astore_2
         2: aload_2
         3: instanceof    #117                // class org/sireum/Mutable
         6: ifeq          25
         9: aload_2
        10: checkcast     #117                // class org/sireum/Mutable
        13: astore_3
        14: getstatic     #122                // Field org/sireum/helper$.MODULE$:Lorg/sireum/helper$;
        17: aload_3
        18: invokevirtual #125                // Method org/sireum/helper$.cloneAssign:(Ljava/lang/Object;)Ljava/lang/Object;
        21: astore_1
        22: goto          33
        25: goto          28
        28: aload_2
        29: astore_1
        30: goto          33
        33: aload_1
        34: areturn
      StackMapTable: number_of_entries = 3
        frame_type = 253 /* append */
          offset_delta = 25
          locals = [ top, class java/lang/Object ]
        frame_type = 2 /* same */
        frame_type = 255 /* full_frame */
          offset_delta = 4
          locals = [ class java/lang/Object, class java/lang/Object, class java/lang/Object ]
          stack = []
      LineNumberTable:
        line 36: 0
        line 37: 2
        line 38: 28
        line 36: 33
      LocalVariableTable:
        Start  Length  Slot  Name   Signature
            0      35     0  x0$1   Ljava/lang/Object;
    MethodParameters:
      Name                           Flags
      x0$1                           final

  public org.sireum.ST$Any$();
    descriptor: ()V
    flags: (0x0001) ACC_PUBLIC
    Code:
      stack=1, locals=1, args_size=1
         0: aload_0
         1: invokespecial #127                // Method java/lang/Object."<init>":()V
         4: return
      LineNumberTable:
        line 34: 0
      LocalVariableTable:
        Start  Length  Slot  Name   Signature
            0       5     0  this   Lorg/sireum/ST$Any$;

  private static java.lang.Object $deserializeLambda$(java.lang.invoke.SerializedLambda);
    descriptor: (Ljava/lang/invoke/SerializedLambda;)Ljava/lang/Object;
    flags: (0x100a) ACC_PRIVATE, ACC_STATIC, ACC_SYNTHETIC
    Code:
      stack=1, locals=1, args_size=1
         0: aload_0
         1: invokedynamic #139,  0            // InvokeDynamic #1:lambdaDeserialize:(Ljava/lang/invoke/SerializedLambda;)Ljava/lang/Object;
         6: areturn
}
InnerClasses:
  public static final #10= #7 of #9;      // Lookup=class java/lang/invoke/MethodHandles$Lookup of class java/lang/invoke/MethodHandles
  public static final #15= #12 of #14;    // Any=class org/sireum/ST$Any of class org/sireum/ST
  public static #16= #2 of #14;           // Any$=class org/sireum/ST$Any$ of class org/sireum/ST
SourceFile: "ST.scala"
BootstrapMethods:
  0: #71 REF_invokeStatic java/lang/invoke/LambdaMetafactory.altMetafactory:(Ljava/lang/invoke/MethodHandles$Lookup;Ljava/lang/String;Ljava/lang/invoke/MethodType;[Ljava/lang/Object;)Ljava/lang/invoke/CallSite;
    Method arguments:
      #59 (Ljava/lang/Object;)Ljava/lang/Object;
      #63 REF_invokeStatic org/sireum/ST$Any$.$anonfun$apply$1:(Ljava/lang/Object;)Ljava/lang/Object;
      #59 (Ljava/lang/Object;)Ljava/lang/Object;
      #64 1
  1: #136 REF_invokeStatic scala/runtime/LambdaDeserialize.bootstrap:(Ljava/lang/invoke/MethodHandles$Lookup;Ljava/lang/String;Ljava/lang/invoke/MethodType;[Ljava/lang/invoke/MethodHandle;)Ljava/lang/invoke/CallSite;
    Method arguments:
      #63 REF_invokeStatic org/sireum/ST$Any$.$anonfun$apply$1:(Ljava/lang/Object;)Ljava/lang/Object;
  ScalaInlineInfo: length = 0x1D (unknown attribute)
   01 01 00 05 00 3C 00 38 01 00 15 00 14 01 00 1A
   00 1B 01 00 57 00 58 01 00 5B 00 5C 01
  Scala: length = 0x0 (unknown attribute)

