Classfile /Users/mw/Projects/slang-braindump/.jar/jar11/assemble/slang-braindump/assemble/content/org/sireum/String.class
  Last modified May 29, 2022; size 8690 bytes
  SHA-256 checksum 925c81dfc7f09a178f5b1425202cdaeda8ce896dbb98dd9c8c491b4bb21fcd97
  Compiled from "String.scala"
public final class org.sireum.String implements org.sireum.Immutable,org.sireum.$internal.HasBoxer
  minor version: 0
  major version: 52
  flags: (0x0031) ACC_PUBLIC, ACC_FINAL, ACC_SUPER
  this_class: #2                          // org/sireum/String
  super_class: #4                         // java/lang/Object
  interfaces: 2, fields: 1, methods: 40, attributes: 5
Constant pool:
    #1 = Utf8               org/sireum/String
    #2 = Class              #1            // org/sireum/String
    #3 = Utf8               java/lang/Object
    #4 = Class              #3            // java/lang/Object
    #5 = Utf8               org/sireum/Immutable
    #6 = Class              #5            // org/sireum/Immutable
    #7 = Utf8               org/sireum/$internal/HasBoxer
    #8 = Class              #7            // org/sireum/$internal/HasBoxer
    #9 = Utf8               String.scala
   #10 = Utf8               Lscala/reflect/ScalaSignature;
   #11 = Utf8               bytes
   #12 = Utf8               \u0006\u0005\t}s!B\u00181\u0011\u0003)d!B\u001c1\u0011\u0003A\u0004\"B \u0002\t\u0003\u0001u!B!\u0002\u0011\u0003\u0011e!\u0002#\u0002\u0011\u0003)\u0005\"B \u0005\t\u0003Y\u0005\"\u0002\'\u0005\t\u0003i\u0005\"\u0002/\u0005\t\u0003i\u0006\"B3\u0005\t\u00032\u0007\"B<\u0002\t\u0003A\b\"\u0002>\u0002\t\u0003Y\bbBA\\\u0003\u0011\u0005\u0011\u0011\u0018\u0005\b\u00033\tA1AAc\u0011\u001d\tI-\u0001C\u0003\u0003\u0017Dq!!6\u0002\t\u000b\t9\u000eC\u0004\u0002^\u0006!)!a8\t\u000f\u0005\u0015\u0018\u0001\"\u0002\u0002h\"9\u0011Q^\u0001\u0005\u0006\u0005=\bbBA|\u0003\u0011\u0015\u0011\u0011 \u0005\b\u0003\u007f\fAQ\u0001B\u0001\u0011\u001d\u00119!\u0001C\u0003\u0005\u0013AqAa\u0005\u0002\t\u000b\u0011)\u0002C\u0004\u0003 \u0005!)A!\t\t\u000f\t-\u0012\u0001\"\u0002\u0003.!9!qG\u0001\u0005\u0006\te\u0002b\u0002B\"\u0003\u0011\u0015!Q\t\u0005\n\u0005\u001f\n\u0011\u0011!C\u0003\u0005#B\u0011B!\u0016\u0002\u0003\u0003%)Aa\u0016\u0007\t]\u0002$! \u0005\u000b\u0003\u001fa\"Q1A\u0005\u0002\u0005E\u0001\"CA\n9\t\u0005\t\u0015!\u0003_\u0011\u0019yD\u0004\"\u0001\u0002\u0016!9\u0011\u0011\u0004\u000f\u0005\u0002\u0005m\u0001bBA 9\u0011\u0005\u0011\u0011\u0003\u0005\u0007\u0003\u0013bB\u0011A>\t\u000f\u00055C\u0004\"\u0011\u0002P!9\u00111\u000b\u000f\u0005\u0002\u0005U\u0003bBA.9\u0011\u0005\u0011Q\f\u0005\b\u0003CbB\u0011AA2\u0011\u001d\t9\u0007\bC\u0001\u0003SBq!a\u001e\u001d\t\u0003\tI\bC\u0004\u0002\u0000q!\t!!!\t\u000f\u0005\u001dE\u0004\"\u0001\u0002\n\"9\u0011q\u0012\u000f\u0005\u0002\u0005E\u0005bBAL9\u0011\u0005\u0011\u0011\u0014\u0005\n\u0003?c\u0012\u0011!C!\u0003CC\u0011\"!+\u001d\u0003\u0003%\t%a+\u0002\rM#(/\u001b8h\u0015\t\t$\'\u0001\u0004tSJ,W/\u001c\u0006\u0002g\u0005\u0019qN]4\u0004\u0001A\u0011a\'A\u0007\u0002a\t11\u000b\u001e:j]\u001e\u001c\"!A\u001d\u0011\u0005ijT\"A\u001e\u000b\u0003q\nQa]2bY\u0006L!AP\u001e\u0003\r\u0005s\u0017PU3g\u0003\u0019a\u0014N\\5u}Q\tQ\'A\u0003C_b,\'\u000f\u0005\u0002D\t5\t\u0011AA\u0003C_b,\'oE\u0002\u0005s\u0019\u0003\"a\u0012&\u000e\u0003!S!!\u0013\u0019\u0002\u0013\u0011Jg\u000e^3s]\u0006d\u0017B\u0001#I)\u0005\u0011\u0015a\u00012pqV\u0011a*\u0015\u000b\u0003\u001fj\u0003\"\u0001U)\r\u0001\u0011)!K\u0002b\u0001\'\n\tA+\u0005\u0002U/B\u0011!(V\u0005\u0003-n\u0012qAT8uQ&tw\r\u0005\u0002;1&\u0011\u0011l\u000f\u0002\u0004\u0003:L\b\"B.\u0007\u0001\u00049\u0016!A8\u0002\u000bUt\'m\u001c=\u0015\u0005y#\u0007CA0c\u001d\tQ\u0004-\u0003\u0002bw\u00051\u0001K]3eK\u001aL!aN2\u000b\u0005\u0005\\\u0004\"B.\b\u0001\u00049\u0016aB2paflU\u000f\u001e\u000b\u0007O*d\u0017o];\u0011\u0005iB\u0017BA5<\u0005\u0011)f.\u001b;\t\u000b-D\u0001\u0019A\u001d\u0002\u0007M\u00148\rC\u0003n\u0011\u0001\u0007a.\u0001\u0004te\u000e\u0004vn\u001d\t\u0003m=L!\u0001\u001d\u0019\u0003\u0003iCQA\u001d\u0005A\u0002e\nA\u0001Z3ti\")A\u000f\u0003a\u0001]\u00069A-Z:u!>\u001c\b\"\u0002<\t\u0001\u0004q\u0017A\u00027f]\u001e$\b.\u0001\u0004fg\u000e\f\u0007/\u001a\u000b\u0003=fDQaW\u0005A\u0002]\u000baA]1oI>lW#\u0001?\u0011\u0005Yb2C\u0002\u000f\u007f\u0003\u0007\tI\u0001\u0005\u0002;\u007f&\u0019\u0011\u0011A\u001e\u0003\r\u0005s\u0017PV1m!\r1\u0014QA\u0005\u0004\u0003\u000f\u0001$!C%n[V$\u0018M\u00197f!\r9\u00151B\u0005\u0004\u0003\u001bA%\u0001\u0003%bg\n{\u00070\u001a:\u0002\u000bY\fG.^3\u0016\u0003y\u000baA^1mk\u0016\u0004Cc\u0001?\u0002\u0018!1\u0011qB\u0010A\u0002y\u000bQ!\u00199qYf$B!!\b\u00026A!\u0011qDA\u0018\u001d\u0011\t\t#a\n\u000f\u0007Y\n\u0019#C\u0002\u0002&A\nq\u0001]1dW\u0006<W-\u0003\u0003\u0002*\u0005-\u0012\u0001C\"p]R\u0014\u0018m\u0019;\n\u0007\u00055\u0002G\u0001\u0005d_:$(/Y2u\u0013\u0011\t\t$a\r\u0003\u001b)+8\u000f^5gS\u000e\fG/[8o\u0015\u0011\tI#a\u000b\t\u000f\u0005]\u0002\u00051\u0001\u0002:\u0005!\u0011M]4t!\u0011Q\u00141H,\n\u0007\u0005u2H\u0001\u0006=e\u0016\u0004X-\u0019;fIz\naA\\1uSZ,\u0007fA\u0011\u0002DA\u0019!(!\u0012\n\u0007\u0005\u001d3H\u0001\u0004j]2Lg.Z\u0001\u0007gR\u0014\u0018N\\4)\u0007\t\n\u0019%\u0001\u0005u_N#(/\u001b8h)\u0005q\u0006fA\u0012\u0002D\u0005Y1\u000f\u001e:jaB\u0013XMZ5y)\rq\u0016q\u000b\u0005\u0007\u00033\"\u0003\u0019\u00010\u0002\rA\u0014XMZ5y\u0003\u0015\u0011w\u000e_3s+\u00051\u0005fA\u0013\u0002D\u0005!1/\u001b>f+\u0005q\u0007f\u0001\u0014\u0002D\u0005)A\u0005\\3tgR!\u00111NA9!\r1\u0014QN\u0005\u0004\u0003_\u0002$!\u0001\"\t\r\u0005Mt\u00051\u0001}\u0003\u0015yG\u000f[3sQ\r9\u00131I\u0001\tI1,7o\u001d\u0013fcR!\u00111NA>\u0011\u0019\t\u0019\b\u000ba\u0001y\"\u001a\u0001&a\u0011\u0002\u0011\u0011:\'/Z1uKJ$B!a\u001b\u0002\u0004\"1\u00111O\u0015A\u0002qD3!KA\"\u0003-!sM]3bi\u0016\u0014H%Z9\u0015\t\u0005-\u00141\u0012\u0005\u0007\u0003gR\u0003\u0019\u0001?)\u0007)\n\u0019%A\u0005%KF$S-\u001d\u0013fcR!\u00111NAJ\u0011\u0019\t\u0019h\u000ba\u0001y\"\u001a1&a\u0011\u0002\u0017\u0011*\u0017\u000f\n2b]\u001e$S-\u001d\u000b\u0005\u0003W\nY\n\u0003\u0004\u0002t1\u0002\r\u0001 \u0015\u0004Y\u0005\r\u0013\u0001\u00035bg\"\u001cu\u000eZ3\u0015\u0005\u0005\r\u0006c\u0001\u001e\u0002&&\u0019\u0011qU\u001e\u0003\u0007%sG/\u0001\u0004fcV\fGn\u001d\u000b\u0005\u0003[\u000b\u0019\fE\u0002;\u0003_K1!!-<\u0005\u001d\u0011un\u001c7fC:D\u0001\"!./\u0003\u0003\u0005\raV\u0001\u0004q\u0012\n\u0014aB;oCB\u0004H.\u001f\u000b\u0005\u0003w\u000b\t\r\u0005\u0003;\u0003{s\u0016bAA`w\t1q\n\u001d;j_:Da!a1\f\u0001\u0004a\u0018!A:\u0015\u0007q\f9\r\u0003\u0004\u0002D2\u0001\rAX\u0001\u0010CB\u0004H.\u001f\u0013fqR,gn]5p]R!\u0011QZAi)\u0011\ti\"a4\t\u000f\u0005]R\u00021\u0001\u0002:!1\u00111[\u0007A\u0002q\fQ\u0001\n;iSN\f\u0001C\\1uSZ,G%\u001a=uK:\u001c\u0018n\u001c8\u0015\u0007y\u000bI\u000e\u0003\u0004\u0002T:\u0001\r\u0001 \u0015\u0004\u001d\u0005\r\u0013\u0001E:ue&tw\rJ3yi\u0016t7/[8o)\ra\u0018\u0011\u001d\u0005\u0007\u0003\'|\u0001\u0019\u0001?)\u0007=\t\u0019%\u0001\nu_N#(/\u001b8hI\u0015DH/\u001a8tS>tG\u0003BA(\u0003SDa!a5\u0011\u0001\u0004a\bf\u0001\t\u0002D\u0005)2\u000f\u001e:jaB\u0013XMZ5yI\u0015DH/\u001a8tS>tG\u0003BAy\u0003k$2AXAz\u0011\u0019\tI&\u0005a\u0001=\"1\u00111[\tA\u0002q\fqBY8yKJ$S\r\u001f;f]NLwN\u001c\u000b\u0004\r\u0006m\bBBAj%\u0001\u0007A\u0010K\u0002\u0013\u0003\u0007\nab]5{K\u0012*\u0007\u0010^3og&|g\u000eF\u0002o\u0005\u0007Aa!a5\u0014\u0001\u0004a\bfA\n\u0002D\u0005yA\u0005\\3tg\u0012*\u0007\u0010^3og&|g\u000e\u0006\u0003\u0003\f\t=A\u0003BA6\u0005\u001bAa!a\u001d\u0015\u0001\u0004a\bBBAj)\u0001\u0007A\u0010K\u0002\u0015\u0003\u0007\n!\u0003\n7fgN$S-\u001d\u0013fqR,gn]5p]R!!q\u0003B\u000e)\u0011\tYG!\u0007\t\r\u0005MT\u00031\u0001}\u0011\u0019\t\u0019.\u0006a\u0001y\"\u001aQ#a\u0011\u0002%\u0011:\'/Z1uKJ$S\r\u001f;f]NLwN\u001c\u000b\u0005\u0005G\u00119\u0003\u0006\u0003\u0002l\t\u0015\u0002BBA:-\u0001\u0007A\u0010\u0003\u0004\u0002TZ\u0001\r\u0001 \u0015\u0004-\u0005\r\u0013!\u0006\u0013he\u0016\fG/\u001a:%KF$S\r\u001f;f]NLwN\u001c\u000b\u0005\u0005_\u0011\u0019\u0004\u0006\u0003\u0002l\tE\u0002BBA:/\u0001\u0007A\u0010\u0003\u0004\u0002T^\u0001\r\u0001 \u0015\u0004/\u0005\r\u0013a\u0005\u0013fc\u0012*\u0017\u000fJ3rI\u0015DH/\u001a8tS>tG\u0003\u0002B\u001e\u0005\u007f!B!a\u001b\u0003>!1\u00111\u000f\rA\u0002qDa!a5\u0019\u0001\u0004a\bf\u0001\r\u0002D\u0005)B%Z9%E\u0006tw\rJ3rI\u0015DH/\u001a8tS>tG\u0003\u0002B$\u0005\u0017\"B!a\u001b\u0003J!1\u00111O\rA\u0002qDa!a5\u001a\u0001\u0004a\bfA\r\u0002D\u0005\u0011\u0002.Y:i\u0007>$W\rJ3yi\u0016t7/[8o)\u0011\t\tKa\u0015\t\r\u0005M\'\u00041\u0001}\u0003A)\u0017/^1mg\u0012*\u0007\u0010^3og&|g\u000e\u0006\u0003\u0003Z\tuC\u0003BAW\u00057B\u0001\"!.\u001c\u0003\u0003\u0005\ra\u0016\u0005\u0007\u0003\'\\\u0002\u0019\u0001?
   #13 = Utf8               org/sireum/String$Boxer$
   #14 = Class              #13           // org/sireum/String$Boxer$
   #15 = Utf8               Boxer$
   #16 = Utf8               org/sireum/contract$Contract$
   #17 = Class              #16           // org/sireum/contract$Contract$
   #18 = Utf8               org/sireum/contract
   #19 = Class              #18           // org/sireum/contract
   #20 = Utf8               Contract$
   #21 = Utf8               org/sireum/contract$Contract$Justification
   #22 = Class              #21           // org/sireum/contract$Contract$Justification
   #23 = Utf8               Justification
   #24 = Utf8               value
   #25 = Utf8               Ljava/lang/String;
   #26 = Utf8               equals$extension
   #27 = Utf8               (Ljava/lang/String;Ljava/lang/Object;)Z
   #28 = Utf8               $this
   #29 = Utf8               x$1
   #30 = Utf8               org/sireum/String$
   #31 = Class              #30           // org/sireum/String$
   #32 = Utf8               MODULE$
   #33 = Utf8               Lorg/sireum/String$;
   #34 = NameAndType        #32:#33       // MODULE$:Lorg/sireum/String$;
   #35 = Fieldref           #31.#34       // org/sireum/String$.MODULE$:Lorg/sireum/String$;
   #36 = NameAndType        #26:#27       // equals$extension:(Ljava/lang/String;Ljava/lang/Object;)Z
   #37 = Methodref          #31.#36       // org/sireum/String$.equals$extension:(Ljava/lang/String;Ljava/lang/Object;)Z
   #38 = Utf8               Ljava/lang/Object;
   #39 = Utf8               hashCode$extension
   #40 = Utf8               (Ljava/lang/String;)I
   #41 = NameAndType        #39:#40       // hashCode$extension:(Ljava/lang/String;)I
   #42 = Methodref          #31.#41       // org/sireum/String$.hashCode$extension:(Ljava/lang/String;)I
   #43 = Utf8               $eq$bang$eq$extension
   #44 = Utf8               (Ljava/lang/String;Ljava/lang/String;)Z
   #45 = Utf8               other
   #46 = NameAndType        #43:#44       // $eq$bang$eq$extension:(Ljava/lang/String;Ljava/lang/String;)Z
   #47 = Methodref          #31.#46       // org/sireum/String$.$eq$bang$eq$extension:(Ljava/lang/String;Ljava/lang/String;)Z
   #48 = Utf8               $eq$eq$eq$extension
   #49 = NameAndType        #48:#44       // $eq$eq$eq$extension:(Ljava/lang/String;Ljava/lang/String;)Z
   #50 = Methodref          #31.#49       // org/sireum/String$.$eq$eq$eq$extension:(Ljava/lang/String;Ljava/lang/String;)Z
   #51 = Utf8               $greater$eq$extension
   #52 = NameAndType        #51:#44       // $greater$eq$extension:(Ljava/lang/String;Ljava/lang/String;)Z
   #53 = Methodref          #31.#52       // org/sireum/String$.$greater$eq$extension:(Ljava/lang/String;Ljava/lang/String;)Z
   #54 = Utf8               $greater$extension
   #55 = NameAndType        #54:#44       // $greater$extension:(Ljava/lang/String;Ljava/lang/String;)Z
   #56 = Methodref          #31.#55       // org/sireum/String$.$greater$extension:(Ljava/lang/String;Ljava/lang/String;)Z
   #57 = Utf8               $less$eq$extension
   #58 = NameAndType        #57:#44       // $less$eq$extension:(Ljava/lang/String;Ljava/lang/String;)Z
   #59 = Methodref          #31.#58       // org/sireum/String$.$less$eq$extension:(Ljava/lang/String;Ljava/lang/String;)Z
   #60 = Utf8               $less$extension
   #61 = NameAndType        #60:#44       // $less$extension:(Ljava/lang/String;Ljava/lang/String;)Z
   #62 = Methodref          #31.#61       // org/sireum/String$.$less$extension:(Ljava/lang/String;Ljava/lang/String;)Z
   #63 = Utf8               size$extension
   #64 = Utf8               (Ljava/lang/String;)Lorg/sireum/Z;
   #65 = NameAndType        #63:#64       // size$extension:(Ljava/lang/String;)Lorg/sireum/Z;
   #66 = Methodref          #31.#65       // org/sireum/String$.size$extension:(Ljava/lang/String;)Lorg/sireum/Z;
   #67 = Utf8               boxer$extension
   #68 = Utf8               (Ljava/lang/String;)Lorg/sireum/$internal/Boxer;
   #69 = NameAndType        #67:#68       // boxer$extension:(Ljava/lang/String;)Lorg/sireum/$internal/Boxer;
   #70 = Methodref          #31.#69       // org/sireum/String$.boxer$extension:(Ljava/lang/String;)Lorg/sireum/$internal/Boxer;
   #71 = Utf8               stripPrefix$extension
   #72 = Utf8               (Ljava/lang/String;Ljava/lang/String;)Ljava/lang/String;
   #73 = Utf8               prefix
   #74 = NameAndType        #71:#72       // stripPrefix$extension:(Ljava/lang/String;Ljava/lang/String;)Ljava/lang/String;
   #75 = Methodref          #31.#74       // org/sireum/String$.stripPrefix$extension:(Ljava/lang/String;Ljava/lang/String;)Ljava/lang/String;
   #76 = Utf8               toString$extension
   #77 = Utf8               (Ljava/lang/String;)Ljava/lang/String;
   #78 = NameAndType        #76:#77       // toString$extension:(Ljava/lang/String;)Ljava/lang/String;
   #79 = Methodref          #31.#78       // org/sireum/String$.toString$extension:(Ljava/lang/String;)Ljava/lang/String;
   #80 = Utf8               string$extension
   #81 = NameAndType        #80:#77       // string$extension:(Ljava/lang/String;)Ljava/lang/String;
   #82 = Methodref          #31.#81       // org/sireum/String$.string$extension:(Ljava/lang/String;)Ljava/lang/String;
   #83 = Utf8               native$extension
   #84 = NameAndType        #83:#77       // native$extension:(Ljava/lang/String;)Ljava/lang/String;
   #85 = Methodref          #31.#84       // org/sireum/String$.native$extension:(Ljava/lang/String;)Ljava/lang/String;
   #86 = Utf8               apply$extension
   #87 = Utf8               (Ljava/lang/String;Lscala/collection/immutable/Seq;)Lorg/sireum/contract$Contract$Justification;
   #88 = Utf8               (Ljava/lang/String;Lscala/collection/immutable/Seq<Ljava/lang/Object;>;)Lorg/sireum/contract$Contract$Justification;
   #89 = Utf8               args
   #90 = NameAndType        #86:#87       // apply$extension:(Ljava/lang/String;Lscala/collection/immutable/Seq;)Lorg/sireum/contract$Contract$Justification;
   #91 = Methodref          #31.#90       // org/sireum/String$.apply$extension:(Ljava/lang/String;Lscala/collection/immutable/Seq;)Lorg/sireum/contract$Contract$Justification;
   #92 = Utf8               Lscala/collection/immutable/Seq;
   #93 = Utf8               unapply
   #94 = Utf8               (Ljava/lang/String;)Lscala/Option;
   #95 = Utf8               (Ljava/lang/String;)Lscala/Option<Ljava/lang/String;>;
   #96 = Utf8               s
   #97 = NameAndType        #93:#94       // unapply:(Ljava/lang/String;)Lscala/Option;
   #98 = Methodref          #31.#97       // org/sireum/String$.unapply:(Ljava/lang/String;)Lscala/Option;
   #99 = Utf8               random
  #100 = Utf8               ()Ljava/lang/String;
  #101 = NameAndType        #99:#100      // random:()Ljava/lang/String;
  #102 = Methodref          #31.#101      // org/sireum/String$.random:()Ljava/lang/String;
  #103 = Utf8               escape
  #104 = Utf8               (Ljava/lang/Object;)Ljava/lang/String;
  #105 = Utf8               o
  #106 = NameAndType        #103:#104     // escape:(Ljava/lang/Object;)Ljava/lang/String;
  #107 = Methodref          #31.#106      // org/sireum/String$.escape:(Ljava/lang/Object;)Ljava/lang/String;
  #108 = Utf8               $cannotMixImmutableAndMutable
  #109 = Utf8               ()Lscala/runtime/Nothing$;
  #110 = Utf8               $cannotMixImmutableAndMutable$
  #111 = Utf8               (Lorg/sireum/Immutable;)Lscala/runtime/Nothing$;
  #112 = NameAndType        #110:#111     // $cannotMixImmutableAndMutable$:(Lorg/sireum/Immutable;)Lscala/runtime/Nothing$;
  #113 = InterfaceMethodref #6.#112       // org/sireum/Immutable.$cannotMixImmutableAndMutable$:(Lorg/sireum/Immutable;)Lscala/runtime/Nothing$;
  #114 = Utf8               this
  #115 = Utf8               Lorg/sireum/String;
  #116 = Utf8               $hasEquals
  #117 = Utf8               ()Z
  #118 = Utf8               $hasEquals$
  #119 = Utf8               (Lorg/sireum/Immutable;)Z
  #120 = NameAndType        #118:#119     // $hasEquals$:(Lorg/sireum/Immutable;)Z
  #121 = InterfaceMethodref #6.#120       // org/sireum/Immutable.$hasEquals$:(Lorg/sireum/Immutable;)Z
  #122 = Utf8               $hasString
  #123 = Utf8               $hasString$
  #124 = NameAndType        #123:#119     // $hasString$:(Lorg/sireum/Immutable;)Z
  #125 = InterfaceMethodref #6.#124       // org/sireum/Immutable.$hasString$:(Lorg/sireum/Immutable;)Z
  #126 = Utf8               $clone
  #127 = Utf8               ()Lorg/sireum/$internal/ImmutableMarker;
  #128 = Utf8               org/sireum/$internal/ImmutableMarker
  #129 = Class              #128          // org/sireum/$internal/ImmutableMarker
  #130 = Utf8               $clone$
  #131 = Utf8               (Lorg/sireum/$internal/ImmutableMarker;)Lorg/sireum/$internal/ImmutableMarker;
  #132 = NameAndType        #130:#131     // $clone$:(Lorg/sireum/$internal/ImmutableMarker;)Lorg/sireum/$internal/ImmutableMarker;
  #133 = InterfaceMethodref #129.#132     // org/sireum/$internal/ImmutableMarker.$clone$:(Lorg/sireum/$internal/ImmutableMarker;)Lorg/sireum/$internal/ImmutableMarker;
  #134 = NameAndType        #24:#25       // value:Ljava/lang/String;
  #135 = Fieldref           #2.#134       // org/sireum/String.value:Ljava/lang/String;
  #136 = Utf8               apply
  #137 = Utf8               (Lscala/collection/immutable/Seq;)Lorg/sireum/contract$Contract$Justification;
  #138 = Utf8               (Lscala/collection/immutable/Seq<Ljava/lang/Object;>;)Lorg/sireum/contract$Contract$Justification;
  #139 = NameAndType        #24:#100      // value:()Ljava/lang/String;
  #140 = Methodref          #2.#139       // org/sireum/String.value:()Ljava/lang/String;
  #141 = Utf8               native
  #142 = Utf8               string
  #143 = Utf8               toString
  #144 = Utf8               stripPrefix
  #145 = Utf8               boxer
  #146 = Utf8               ()Lorg/sireum/$internal/Boxer;
  #147 = Utf8               size
  #148 = Utf8               ()Lorg/sireum/Z;
  #149 = Utf8               $less
  #150 = Utf8               (Ljava/lang/String;)Z
  #151 = Utf8               $less$eq
  #152 = Utf8               $greater
  #153 = Utf8               $greater$eq
  #154 = Utf8               $eq$eq$eq
  #155 = Utf8               $eq$bang$eq
  #156 = Utf8               hashCode
  #157 = Utf8               ()I
  #158 = Utf8               equals
  #159 = Utf8               (Ljava/lang/Object;)Z
  #160 = Utf8               ()Ljava/lang/Object;
  #161 = NameAndType        #126:#127     // $clone:()Lorg/sireum/$internal/ImmutableMarker;
  #162 = Methodref          #2.#161       // org/sireum/String.$clone:()Lorg/sireum/$internal/ImmutableMarker;
  #163 = Utf8               <init>
  #164 = Utf8               (Ljava/lang/String;)V
  #165 = Utf8               ()V
  #166 = NameAndType        #163:#165     // "<init>":()V
  #167 = Methodref          #4.#166       // java/lang/Object."<init>":()V
  #168 = Utf8               $init$
  #169 = Utf8               (Lorg/sireum/$internal/ImmutableMarker;)V
  #170 = NameAndType        #168:#169     // $init$:(Lorg/sireum/$internal/ImmutableMarker;)V
  #171 = InterfaceMethodref #129.#170     // org/sireum/$internal/ImmutableMarker.$init$:(Lorg/sireum/$internal/ImmutableMarker;)V
  #172 = Utf8               (Lorg/sireum/Immutable;)V
  #173 = NameAndType        #168:#172     // $init$:(Lorg/sireum/Immutable;)V
  #174 = InterfaceMethodref #6.#173       // org/sireum/Immutable.$init$:(Lorg/sireum/Immutable;)V
  #175 = Utf8               Code
  #176 = Utf8               LocalVariableTable
  #177 = Utf8               MethodParameters
  #178 = Utf8               Signature
  #179 = Utf8               LineNumberTable
  #180 = Utf8               InnerClasses
  #181 = Utf8               SourceFile
  #182 = Utf8               RuntimeVisibleAnnotations
  #183 = Utf8               ScalaInlineInfo
  #184 = Utf8               ScalaSig
{
  private final java.lang.String value;
    descriptor: Ljava/lang/String;
    flags: (0x0012) ACC_PRIVATE, ACC_FINAL

  public static boolean equals$extension(java.lang.String, java.lang.Object);
    descriptor: (Ljava/lang/String;Ljava/lang/Object;)Z
    flags: (0x0009) ACC_PUBLIC, ACC_STATIC
    Code:
      stack=3, locals=2, args_size=2
         0: getstatic     #35                 // Field org/sireum/String$.MODULE$:Lorg/sireum/String$;
         3: aload_0
         4: aload_1
         5: invokevirtual #37                 // Method org/sireum/String$.equals$extension:(Ljava/lang/String;Ljava/lang/Object;)Z
         8: ireturn
      LocalVariableTable:
        Start  Length  Slot  Name   Signature
            0       9     0 $this   Ljava/lang/String;
            0       9     1   x$1   Ljava/lang/Object;
    MethodParameters:
      Name                           Flags
      $this                          final
      x$1                            final

  public static int hashCode$extension(java.lang.String);
    descriptor: (Ljava/lang/String;)I
    flags: (0x0009) ACC_PUBLIC, ACC_STATIC
    Code:
      stack=2, locals=1, args_size=1
         0: getstatic     #35                 // Field org/sireum/String$.MODULE$:Lorg/sireum/String$;
         3: aload_0
         4: invokevirtual #42                 // Method org/sireum/String$.hashCode$extension:(Ljava/lang/String;)I
         7: ireturn
      LocalVariableTable:
        Start  Length  Slot  Name   Signature
            0       8     0 $this   Ljava/lang/String;
    MethodParameters:
      Name                           Flags
      $this                          final

  public static boolean $eq$bang$eq$extension(java.lang.String, java.lang.String);
    descriptor: (Ljava/lang/String;Ljava/lang/String;)Z
    flags: (0x0009) ACC_PUBLIC, ACC_STATIC
    Code:
      stack=3, locals=2, args_size=2
         0: getstatic     #35                 // Field org/sireum/String$.MODULE$:Lorg/sireum/String$;
         3: aload_0
         4: aload_1
         5: invokevirtual #47                 // Method org/sireum/String$.$eq$bang$eq$extension:(Ljava/lang/String;Ljava/lang/String;)Z
         8: ireturn
      LocalVariableTable:
        Start  Length  Slot  Name   Signature
            0       9     0 $this   Ljava/lang/String;
            0       9     1 other   Ljava/lang/String;
    MethodParameters:
      Name                           Flags
      $this                          final
      other                          final

  public static boolean $eq$eq$eq$extension(java.lang.String, java.lang.String);
    descriptor: (Ljava/lang/String;Ljava/lang/String;)Z
    flags: (0x0009) ACC_PUBLIC, ACC_STATIC
    Code:
      stack=3, locals=2, args_size=2
         0: getstatic     #35                 // Field org/sireum/String$.MODULE$:Lorg/sireum/String$;
         3: aload_0
         4: aload_1
         5: invokevirtual #50                 // Method org/sireum/String$.$eq$eq$eq$extension:(Ljava/lang/String;Ljava/lang/String;)Z
         8: ireturn
      LocalVariableTable:
        Start  Length  Slot  Name   Signature
            0       9     0 $this   Ljava/lang/String;
            0       9     1 other   Ljava/lang/String;
    MethodParameters:
      Name                           Flags
      $this                          final
      other                          final

  public static boolean $greater$eq$extension(java.lang.String, java.lang.String);
    descriptor: (Ljava/lang/String;Ljava/lang/String;)Z
    flags: (0x0009) ACC_PUBLIC, ACC_STATIC
    Code:
      stack=3, locals=2, args_size=2
         0: getstatic     #35                 // Field org/sireum/String$.MODULE$:Lorg/sireum/String$;
         3: aload_0
         4: aload_1
         5: invokevirtual #53                 // Method org/sireum/String$.$greater$eq$extension:(Ljava/lang/String;Ljava/lang/String;)Z
         8: ireturn
      LocalVariableTable:
        Start  Length  Slot  Name   Signature
            0       9     0 $this   Ljava/lang/String;
            0       9     1 other   Ljava/lang/String;
    MethodParameters:
      Name                           Flags
      $this                          final
      other                          final

  public static boolean $greater$extension(java.lang.String, java.lang.String);
    descriptor: (Ljava/lang/String;Ljava/lang/String;)Z
    flags: (0x0009) ACC_PUBLIC, ACC_STATIC
    Code:
      stack=3, locals=2, args_size=2
         0: getstatic     #35                 // Field org/sireum/String$.MODULE$:Lorg/sireum/String$;
         3: aload_0
         4: aload_1
         5: invokevirtual #56                 // Method org/sireum/String$.$greater$extension:(Ljava/lang/String;Ljava/lang/String;)Z
         8: ireturn
      LocalVariableTable:
        Start  Length  Slot  Name   Signature
            0       9     0 $this   Ljava/lang/String;
            0       9     1 other   Ljava/lang/String;
    MethodParameters:
      Name                           Flags
      $this                          final
      other                          final

  public static boolean $less$eq$extension(java.lang.String, java.lang.String);
    descriptor: (Ljava/lang/String;Ljava/lang/String;)Z
    flags: (0x0009) ACC_PUBLIC, ACC_STATIC
    Code:
      stack=3, locals=2, args_size=2
         0: getstatic     #35                 // Field org/sireum/String$.MODULE$:Lorg/sireum/String$;
         3: aload_0
         4: aload_1
         5: invokevirtual #59                 // Method org/sireum/String$.$less$eq$extension:(Ljava/lang/String;Ljava/lang/String;)Z
         8: ireturn
      LocalVariableTable:
        Start  Length  Slot  Name   Signature
            0       9     0 $this   Ljava/lang/String;
            0       9     1 other   Ljava/lang/String;
    MethodParameters:
      Name                           Flags
      $this                          final
      other                          final

  public static boolean $less$extension(java.lang.String, java.lang.String);
    descriptor: (Ljava/lang/String;Ljava/lang/String;)Z
    flags: (0x0009) ACC_PUBLIC, ACC_STATIC
    Code:
      stack=3, locals=2, args_size=2
         0: getstatic     #35                 // Field org/sireum/String$.MODULE$:Lorg/sireum/String$;
         3: aload_0
         4: aload_1
         5: invokevirtual #62                 // Method org/sireum/String$.$less$extension:(Ljava/lang/String;Ljava/lang/String;)Z
         8: ireturn
      LocalVariableTable:
        Start  Length  Slot  Name   Signature
            0       9     0 $this   Ljava/lang/String;
            0       9     1 other   Ljava/lang/String;
    MethodParameters:
      Name                           Flags
      $this                          final
      other                          final

  public static org.sireum.Z size$extension(java.lang.String);
    descriptor: (Ljava/lang/String;)Lorg/sireum/Z;
    flags: (0x0009) ACC_PUBLIC, ACC_STATIC
    Code:
      stack=2, locals=1, args_size=1
         0: getstatic     #35                 // Field org/sireum/String$.MODULE$:Lorg/sireum/String$;
         3: aload_0
         4: invokevirtual #66                 // Method org/sireum/String$.size$extension:(Ljava/lang/String;)Lorg/sireum/Z;
         7: areturn
      LocalVariableTable:
        Start  Length  Slot  Name   Signature
            0       8     0 $this   Ljava/lang/String;
    MethodParameters:
      Name                           Flags
      $this                          final

  public static org.sireum.$internal.Boxer boxer$extension(java.lang.String);
    descriptor: (Ljava/lang/String;)Lorg/sireum/$internal/Boxer;
    flags: (0x0009) ACC_PUBLIC, ACC_STATIC
    Code:
      stack=2, locals=1, args_size=1
         0: getstatic     #35                 // Field org/sireum/String$.MODULE$:Lorg/sireum/String$;
         3: aload_0
         4: invokevirtual #70                 // Method org/sireum/String$.boxer$extension:(Ljava/lang/String;)Lorg/sireum/$internal/Boxer;
         7: areturn
      LocalVariableTable:
        Start  Length  Slot  Name   Signature
            0       8     0 $this   Ljava/lang/String;
    MethodParameters:
      Name                           Flags
      $this                          final

  public static java.lang.String stripPrefix$extension(java.lang.String, java.lang.String);
    descriptor: (Ljava/lang/String;Ljava/lang/String;)Ljava/lang/String;
    flags: (0x0009) ACC_PUBLIC, ACC_STATIC
    Code:
      stack=3, locals=2, args_size=2
         0: getstatic     #35                 // Field org/sireum/String$.MODULE$:Lorg/sireum/String$;
         3: aload_0
         4: aload_1
         5: invokevirtual #75                 // Method org/sireum/String$.stripPrefix$extension:(Ljava/lang/String;Ljava/lang/String;)Ljava/lang/String;
         8: areturn
      LocalVariableTable:
        Start  Length  Slot  Name   Signature
            0       9     0 $this   Ljava/lang/String;
            0       9     1 prefix   Ljava/lang/String;
    MethodParameters:
      Name                           Flags
      $this                          final
      prefix                         final

  public static java.lang.String toString$extension(java.lang.String);
    descriptor: (Ljava/lang/String;)Ljava/lang/String;
    flags: (0x0009) ACC_PUBLIC, ACC_STATIC
    Code:
      stack=2, locals=1, args_size=1
         0: getstatic     #35                 // Field org/sireum/String$.MODULE$:Lorg/sireum/String$;
         3: aload_0
         4: invokevirtual #79                 // Method org/sireum/String$.toString$extension:(Ljava/lang/String;)Ljava/lang/String;
         7: areturn
      LocalVariableTable:
        Start  Length  Slot  Name   Signature
            0       8     0 $this   Ljava/lang/String;
    MethodParameters:
      Name                           Flags
      $this                          final

  public static java.lang.String string$extension(java.lang.String);
    descriptor: (Ljava/lang/String;)Ljava/lang/String;
    flags: (0x0009) ACC_PUBLIC, ACC_STATIC
    Code:
      stack=2, locals=1, args_size=1
         0: getstatic     #35                 // Field org/sireum/String$.MODULE$:Lorg/sireum/String$;
         3: aload_0
         4: invokevirtual #82                 // Method org/sireum/String$.string$extension:(Ljava/lang/String;)Ljava/lang/String;
         7: areturn
      LocalVariableTable:
        Start  Length  Slot  Name   Signature
            0       8     0 $this   Ljava/lang/String;
    MethodParameters:
      Name                           Flags
      $this                          final

  public static java.lang.String native$extension(java.lang.String);
    descriptor: (Ljava/lang/String;)Ljava/lang/String;
    flags: (0x0009) ACC_PUBLIC, ACC_STATIC
    Code:
      stack=2, locals=1, args_size=1
         0: getstatic     #35                 // Field org/sireum/String$.MODULE$:Lorg/sireum/String$;
         3: aload_0
         4: invokevirtual #85                 // Method org/sireum/String$.native$extension:(Ljava/lang/String;)Ljava/lang/String;
         7: areturn
      LocalVariableTable:
        Start  Length  Slot  Name   Signature
            0       8     0 $this   Ljava/lang/String;
    MethodParameters:
      Name                           Flags
      $this                          final

  public static org.sireum.contract$Contract$Justification apply$extension(java.lang.String, scala.collection.immutable.Seq<java.lang.Object>);
    descriptor: (Ljava/lang/String;Lscala/collection/immutable/Seq;)Lorg/sireum/contract$Contract$Justification;
    flags: (0x0009) ACC_PUBLIC, ACC_STATIC
    Code:
      stack=3, locals=2, args_size=2
         0: getstatic     #35                 // Field org/sireum/String$.MODULE$:Lorg/sireum/String$;
         3: aload_0
         4: aload_1
         5: invokevirtual #91                 // Method org/sireum/String$.apply$extension:(Ljava/lang/String;Lscala/collection/immutable/Seq;)Lorg/sireum/contract$Contract$Justification;
         8: areturn
      LocalVariableTable:
        Start  Length  Slot  Name   Signature
            0       9     0 $this   Ljava/lang/String;
            0       9     1  args   Lscala/collection/immutable/Seq;
    Signature: #88                          // (Ljava/lang/String;Lscala/collection/immutable/Seq<Ljava/lang/Object;>;)Lorg/sireum/contract$Contract$Justification;
    MethodParameters:
      Name                           Flags
      $this                          final
      args                           final

  public static scala.Option<java.lang.String> unapply(java.lang.String);
    descriptor: (Ljava/lang/String;)Lscala/Option;
    flags: (0x0009) ACC_PUBLIC, ACC_STATIC
    Code:
      stack=2, locals=1, args_size=1
         0: getstatic     #35                 // Field org/sireum/String$.MODULE$:Lorg/sireum/String$;
         3: aload_0
         4: invokevirtual #98                 // Method org/sireum/String$.unapply:(Ljava/lang/String;)Lscala/Option;
         7: areturn
      LocalVariableTable:
        Start  Length  Slot  Name   Signature
            0       8     0     s   Ljava/lang/String;
    Signature: #95                          // (Ljava/lang/String;)Lscala/Option<Ljava/lang/String;>;
    MethodParameters:
      Name                           Flags
      s                              final

  public static java.lang.String random();
    descriptor: ()Ljava/lang/String;
    flags: (0x0009) ACC_PUBLIC, ACC_STATIC
    Code:
      stack=1, locals=0, args_size=0
         0: getstatic     #35                 // Field org/sireum/String$.MODULE$:Lorg/sireum/String$;
         3: invokevirtual #102                // Method org/sireum/String$.random:()Ljava/lang/String;
         6: areturn

  public static java.lang.String escape(java.lang.Object);
    descriptor: (Ljava/lang/Object;)Ljava/lang/String;
    flags: (0x0009) ACC_PUBLIC, ACC_STATIC
    Code:
      stack=2, locals=1, args_size=1
         0: getstatic     #35                 // Field org/sireum/String$.MODULE$:Lorg/sireum/String$;
         3: aload_0
         4: invokevirtual #107                // Method org/sireum/String$.escape:(Ljava/lang/Object;)Ljava/lang/String;
         7: areturn
      LocalVariableTable:
        Start  Length  Slot  Name   Signature
            0       8     0     o   Ljava/lang/Object;
    MethodParameters:
      Name                           Flags
      o                              final

  public final scala.runtime.Nothing$ $cannotMixImmutableAndMutable();
    descriptor: ()Lscala/runtime/Nothing$;
    flags: (0x0011) ACC_PUBLIC, ACC_FINAL
    Code:
      stack=1, locals=1, args_size=1
         0: aload_0
         1: invokestatic  #113                // InterfaceMethod org/sireum/Immutable.$cannotMixImmutableAndMutable$:(Lorg/sireum/Immutable;)Lscala/runtime/Nothing$;
         4: areturn
      LineNumberTable:
        line 72: 0
      LocalVariableTable:
        Start  Length  Slot  Name   Signature
            0       5     0  this   Lorg/sireum/String;

  public boolean $hasEquals();
    descriptor: ()Z
    flags: (0x0001) ACC_PUBLIC
    Code:
      stack=1, locals=1, args_size=1
         0: aload_0
         1: invokestatic  #121                // InterfaceMethod org/sireum/Immutable.$hasEquals$:(Lorg/sireum/Immutable;)Z
         4: ireturn
      LineNumberTable:
        line 72: 0
      LocalVariableTable:
        Start  Length  Slot  Name   Signature
            0       5     0  this   Lorg/sireum/String;

  public boolean $hasString();
    descriptor: ()Z
    flags: (0x0001) ACC_PUBLIC
    Code:
      stack=1, locals=1, args_size=1
         0: aload_0
         1: invokestatic  #125                // InterfaceMethod org/sireum/Immutable.$hasString$:(Lorg/sireum/Immutable;)Z
         4: ireturn
      LineNumberTable:
        line 72: 0
      LocalVariableTable:
        Start  Length  Slot  Name   Signature
            0       5     0  this   Lorg/sireum/String;

  public org.sireum.$internal.ImmutableMarker $clone();
    descriptor: ()Lorg/sireum/$internal/ImmutableMarker;
    flags: (0x0001) ACC_PUBLIC
    Code:
      stack=1, locals=1, args_size=1
         0: aload_0
         1: invokestatic  #133                // InterfaceMethod org/sireum/$internal/ImmutableMarker.$clone$:(Lorg/sireum/$internal/ImmutableMarker;)Lorg/sireum/$internal/ImmutableMarker;
         4: areturn
      LineNumberTable:
        line 72: 0
      LocalVariableTable:
        Start  Length  Slot  Name   Signature
            0       5     0  this   Lorg/sireum/String;

  public java.lang.String value();
    descriptor: ()Ljava/lang/String;
    flags: (0x0001) ACC_PUBLIC
    Code:
      stack=1, locals=1, args_size=1
         0: aload_0
         1: getfield      #135                // Field value:Ljava/lang/String;
         4: areturn
      LineNumberTable:
        line 72: 0
      LocalVariableTable:
        Start  Length  Slot  Name   Signature
            0       5     0  this   Lorg/sireum/String;

  public org.sireum.contract$Contract$Justification apply(scala.collection.immutable.Seq<java.lang.Object>);
    descriptor: (Lscala/collection/immutable/Seq;)Lorg/sireum/contract$Contract$Justification;
    flags: (0x0001) ACC_PUBLIC
    Code:
      stack=3, locals=2, args_size=2
         0: getstatic     #35                 // Field org/sireum/String$.MODULE$:Lorg/sireum/String$;
         3: aload_0
         4: invokevirtual #140                // Method value:()Ljava/lang/String;
         7: aload_1
         8: invokevirtual #91                 // Method org/sireum/String$.apply$extension:(Ljava/lang/String;Lscala/collection/immutable/Seq;)Lorg/sireum/contract$Contract$Justification;
        11: areturn
      LineNumberTable:
        line 74: 0
      LocalVariableTable:
        Start  Length  Slot  Name   Signature
            0      12     0  this   Lorg/sireum/String;
            0      12     1  args   Lscala/collection/immutable/Seq;
    Signature: #138                         // (Lscala/collection/immutable/Seq<Ljava/lang/Object;>;)Lorg/sireum/contract$Contract$Justification;
    MethodParameters:
      Name                           Flags
      args                           final

  public java.lang.String native();
    descriptor: ()Ljava/lang/String;
    flags: (0x0001) ACC_PUBLIC
    Code:
      stack=2, locals=1, args_size=1
         0: getstatic     #35                 // Field org/sireum/String$.MODULE$:Lorg/sireum/String$;
         3: aload_0
         4: invokevirtual #140                // Method value:()Ljava/lang/String;
         7: invokevirtual #85                 // Method org/sireum/String$.native$extension:(Ljava/lang/String;)Ljava/lang/String;
        10: areturn
      LineNumberTable:
        line 76: 0
      LocalVariableTable:
        Start  Length  Slot  Name   Signature
            0      11     0  this   Lorg/sireum/String;

  public java.lang.String string();
    descriptor: ()Ljava/lang/String;
    flags: (0x0001) ACC_PUBLIC
    Code:
      stack=2, locals=1, args_size=1
         0: getstatic     #35                 // Field org/sireum/String$.MODULE$:Lorg/sireum/String$;
         3: aload_0
         4: invokevirtual #140                // Method value:()Ljava/lang/String;
         7: invokevirtual #82                 // Method org/sireum/String$.string$extension:(Ljava/lang/String;)Ljava/lang/String;
        10: areturn
      LineNumberTable:
        line 78: 0
      LocalVariableTable:
        Start  Length  Slot  Name   Signature
            0      11     0  this   Lorg/sireum/String;

  public java.lang.String toString();
    descriptor: ()Ljava/lang/String;
    flags: (0x0001) ACC_PUBLIC
    Code:
      stack=2, locals=1, args_size=1
         0: getstatic     #35                 // Field org/sireum/String$.MODULE$:Lorg/sireum/String$;
         3: aload_0
         4: invokevirtual #140                // Method value:()Ljava/lang/String;
         7: invokevirtual #79                 // Method org/sireum/String$.toString$extension:(Ljava/lang/String;)Ljava/lang/String;
        10: areturn
      LineNumberTable:
        line 80: 0
      LocalVariableTable:
        Start  Length  Slot  Name   Signature
            0      11     0  this   Lorg/sireum/String;

  public java.lang.String stripPrefix(java.lang.String);
    descriptor: (Ljava/lang/String;)Ljava/lang/String;
    flags: (0x0001) ACC_PUBLIC
    Code:
      stack=3, locals=2, args_size=2
         0: getstatic     #35                 // Field org/sireum/String$.MODULE$:Lorg/sireum/String$;
         3: aload_0
         4: invokevirtual #140                // Method value:()Ljava/lang/String;
         7: aload_1
         8: invokevirtual #75                 // Method org/sireum/String$.stripPrefix$extension:(Ljava/lang/String;Ljava/lang/String;)Ljava/lang/String;
        11: areturn
      LineNumberTable:
        line 82: 0
      LocalVariableTable:
        Start  Length  Slot  Name   Signature
            0      12     0  this   Lorg/sireum/String;
            0      12     1 prefix   Ljava/lang/String;
    MethodParameters:
      Name                           Flags
      prefix                         final

  public org.sireum.$internal.Boxer boxer();
    descriptor: ()Lorg/sireum/$internal/Boxer;
    flags: (0x0001) ACC_PUBLIC
    Code:
      stack=2, locals=1, args_size=1
         0: getstatic     #35                 // Field org/sireum/String$.MODULE$:Lorg/sireum/String$;
         3: aload_0
         4: invokevirtual #140                // Method value:()Ljava/lang/String;
         7: invokevirtual #70                 // Method org/sireum/String$.boxer$extension:(Ljava/lang/String;)Lorg/sireum/$internal/Boxer;
        10: areturn
      LineNumberTable:
        line 84: 0
      LocalVariableTable:
        Start  Length  Slot  Name   Signature
            0      11     0  this   Lorg/sireum/String;

  public org.sireum.Z size();
    descriptor: ()Lorg/sireum/Z;
    flags: (0x0001) ACC_PUBLIC
    Code:
      stack=2, locals=1, args_size=1
         0: getstatic     #35                 // Field org/sireum/String$.MODULE$:Lorg/sireum/String$;
         3: aload_0
         4: invokevirtual #140                // Method value:()Ljava/lang/String;
         7: invokevirtual #66                 // Method org/sireum/String$.size$extension:(Ljava/lang/String;)Lorg/sireum/Z;
        10: areturn
      LineNumberTable:
        line 86: 0
      LocalVariableTable:
        Start  Length  Slot  Name   Signature
            0      11     0  this   Lorg/sireum/String;

  public boolean $less(java.lang.String);
    descriptor: (Ljava/lang/String;)Z
    flags: (0x0001) ACC_PUBLIC
    Code:
      stack=3, locals=2, args_size=2
         0: getstatic     #35                 // Field org/sireum/String$.MODULE$:Lorg/sireum/String$;
         3: aload_0
         4: invokevirtual #140                // Method value:()Ljava/lang/String;
         7: aload_1
         8: invokevirtual #62                 // Method org/sireum/String$.$less$extension:(Ljava/lang/String;Ljava/lang/String;)Z
        11: ireturn
      LineNumberTable:
        line 88: 0
      LocalVariableTable:
        Start  Length  Slot  Name   Signature
            0      12     0  this   Lorg/sireum/String;
            0      12     1 other   Ljava/lang/String;
    MethodParameters:
      Name                           Flags
      other                          final

  public boolean $less$eq(java.lang.String);
    descriptor: (Ljava/lang/String;)Z
    flags: (0x0001) ACC_PUBLIC
    Code:
      stack=3, locals=2, args_size=2
         0: getstatic     #35                 // Field org/sireum/String$.MODULE$:Lorg/sireum/String$;
         3: aload_0
         4: invokevirtual #140                // Method value:()Ljava/lang/String;
         7: aload_1
         8: invokevirtual #59                 // Method org/sireum/String$.$less$eq$extension:(Ljava/lang/String;Ljava/lang/String;)Z
        11: ireturn
      LineNumberTable:
        line 90: 0
      LocalVariableTable:
        Start  Length  Slot  Name   Signature
            0      12     0  this   Lorg/sireum/String;
            0      12     1 other   Ljava/lang/String;
    MethodParameters:
      Name                           Flags
      other                          final

  public boolean $greater(java.lang.String);
    descriptor: (Ljava/lang/String;)Z
    flags: (0x0001) ACC_PUBLIC
    Code:
      stack=3, locals=2, args_size=2
         0: getstatic     #35                 // Field org/sireum/String$.MODULE$:Lorg/sireum/String$;
         3: aload_0
         4: invokevirtual #140                // Method value:()Ljava/lang/String;
         7: aload_1
         8: invokevirtual #56                 // Method org/sireum/String$.$greater$extension:(Ljava/lang/String;Ljava/lang/String;)Z
        11: ireturn
      LineNumberTable:
        line 92: 0
      LocalVariableTable:
        Start  Length  Slot  Name   Signature
            0      12     0  this   Lorg/sireum/String;
            0      12     1 other   Ljava/lang/String;
    MethodParameters:
      Name                           Flags
      other                          final

  public boolean $greater$eq(java.lang.String);
    descriptor: (Ljava/lang/String;)Z
    flags: (0x0001) ACC_PUBLIC
    Code:
      stack=3, locals=2, args_size=2
         0: getstatic     #35                 // Field org/sireum/String$.MODULE$:Lorg/sireum/String$;
         3: aload_0
         4: invokevirtual #140                // Method value:()Ljava/lang/String;
         7: aload_1
         8: invokevirtual #53                 // Method org/sireum/String$.$greater$eq$extension:(Ljava/lang/String;Ljava/lang/String;)Z
        11: ireturn
      LineNumberTable:
        line 94: 0
      LocalVariableTable:
        Start  Length  Slot  Name   Signature
            0      12     0  this   Lorg/sireum/String;
            0      12     1 other   Ljava/lang/String;
    MethodParameters:
      Name                           Flags
      other                          final

  public boolean $eq$eq$eq(java.lang.String);
    descriptor: (Ljava/lang/String;)Z
    flags: (0x0001) ACC_PUBLIC
    Code:
      stack=3, locals=2, args_size=2
         0: getstatic     #35                 // Field org/sireum/String$.MODULE$:Lorg/sireum/String$;
         3: aload_0
         4: invokevirtual #140                // Method value:()Ljava/lang/String;
         7: aload_1
         8: invokevirtual #50                 // Method org/sireum/String$.$eq$eq$eq$extension:(Ljava/lang/String;Ljava/lang/String;)Z
        11: ireturn
      LineNumberTable:
        line 96: 0
      LocalVariableTable:
        Start  Length  Slot  Name   Signature
            0      12     0  this   Lorg/sireum/String;
            0      12     1 other   Ljava/lang/String;
    MethodParameters:
      Name                           Flags
      other                          final

  public boolean $eq$bang$eq(java.lang.String);
    descriptor: (Ljava/lang/String;)Z
    flags: (0x0001) ACC_PUBLIC
    Code:
      stack=3, locals=2, args_size=2
         0: getstatic     #35                 // Field org/sireum/String$.MODULE$:Lorg/sireum/String$;
         3: aload_0
         4: invokevirtual #140                // Method value:()Ljava/lang/String;
         7: aload_1
         8: invokevirtual #47                 // Method org/sireum/String$.$eq$bang$eq$extension:(Ljava/lang/String;Ljava/lang/String;)Z
        11: ireturn
      LineNumberTable:
        line 98: 0
      LocalVariableTable:
        Start  Length  Slot  Name   Signature
            0      12     0  this   Lorg/sireum/String;
            0      12     1 other   Ljava/lang/String;
    MethodParameters:
      Name                           Flags
      other                          final

  public int hashCode();
    descriptor: ()I
    flags: (0x0001) ACC_PUBLIC
    Code:
      stack=2, locals=1, args_size=1
         0: getstatic     #35                 // Field org/sireum/String$.MODULE$:Lorg/sireum/String$;
         3: aload_0
         4: invokevirtual #140                // Method value:()Ljava/lang/String;
         7: invokevirtual #42                 // Method org/sireum/String$.hashCode$extension:(Ljava/lang/String;)I
        10: ireturn
      LineNumberTable:
        line 72: 0
      LocalVariableTable:
        Start  Length  Slot  Name   Signature
            0      11     0  this   Lorg/sireum/String;

  public boolean equals(java.lang.Object);
    descriptor: (Ljava/lang/Object;)Z
    flags: (0x0001) ACC_PUBLIC
    Code:
      stack=3, locals=2, args_size=2
         0: getstatic     #35                 // Field org/sireum/String$.MODULE$:Lorg/sireum/String$;
         3: aload_0
         4: invokevirtual #140                // Method value:()Ljava/lang/String;
         7: aload_1
         8: invokevirtual #37                 // Method org/sireum/String$.equals$extension:(Ljava/lang/String;Ljava/lang/Object;)Z
        11: ireturn
      LineNumberTable:
        line 72: 0
      LocalVariableTable:
        Start  Length  Slot  Name   Signature
            0      12     0  this   Lorg/sireum/String;
            0      12     1   x$1   Ljava/lang/Object;
    MethodParameters:
      Name                           Flags
      x$1                            final

  public java.lang.Object $clone();
    descriptor: ()Ljava/lang/Object;
    flags: (0x1041) ACC_PUBLIC, ACC_BRIDGE, ACC_SYNTHETIC
    Code:
      stack=1, locals=1, args_size=1
         0: aload_0
         1: invokevirtual #162                // Method $clone:()Lorg/sireum/$internal/ImmutableMarker;
         4: areturn
      LineNumberTable:
        line 72: 0
      LocalVariableTable:
        Start  Length  Slot  Name   Signature
            0       5     0  this   Lorg/sireum/String;

  public org.sireum.String(java.lang.String);
    descriptor: (Ljava/lang/String;)V
    flags: (0x0001) ACC_PUBLIC
    Code:
      stack=2, locals=2, args_size=2
         0: aload_0
         1: aload_1
         2: putfield      #135                // Field value:Ljava/lang/String;
         5: aload_0
         6: invokespecial #167                // Method java/lang/Object."<init>":()V
         9: aload_0
        10: invokestatic  #171                // InterfaceMethod org/sireum/$internal/ImmutableMarker.$init$:(Lorg/sireum/$internal/ImmutableMarker;)V
        13: aload_0
        14: invokestatic  #174                // InterfaceMethod org/sireum/Immutable.$init$:(Lorg/sireum/Immutable;)V
        17: return
      LineNumberTable:
        line 72: 0
      LocalVariableTable:
        Start  Length  Slot  Name   Signature
            0      18     0  this   Lorg/sireum/String;
            0      18     1 value   Ljava/lang/String;
    MethodParameters:
      Name                           Flags
      value                          final
}
InnerClasses:
  public static #15= #14 of #2;           // Boxer$=class org/sireum/String$Boxer$ of class org/sireum/String
  public #20= #17 of #19;                 // Contract$=class org/sireum/contract$Contract$ of class org/sireum/contract
  public #23= #22 of #17;                 // Justification=class org/sireum/contract$Contract$Justification of class org/sireum/contract$Contract$
SourceFile: "String.scala"
RuntimeVisibleAnnotations:
  0: #10(#11=s#12)
    scala.reflect.ScalaSignature(
      bytes="\u0006\u0005\t}s!B\u00181\u0011\u0003)d!B\u001c1\u0011\u0003A\u0004\"B \u0002\t\u0003\u0001u!B!\u0002\u0011\u0003\u0011e!\u0002#\u0002\u0011\u0003)\u0005\"B \u0005\t\u0003Y\u0005\"\u0002\'\u0005\t\u0003i\u0005\"\u0002/\u0005\t\u0003i\u0006\"B3\u0005\t\u00032\u0007\"B<\u0002\t\u0003A\b\"\u0002>\u0002\t\u0003Y\bbBA\\\u0003\u0011\u0005\u0011\u0011\u0018\u0005\b\u00033\tA1AAc\u0011\u001d\tI-\u0001C\u0003\u0003\u0017Dq!!6\u0002\t\u000b\t9\u000eC\u0004\u0002^\u0006!)!a8\t\u000f\u0005\u0015\u0018\u0001\"\u0002\u0002h\"9\u0011Q^\u0001\u0005\u0006\u0005=\bbBA|\u0003\u0011\u0015\u0011\u0011 \u0005\b\u0003\u007f\fAQ\u0001B\u0001\u0011\u001d\u00119!\u0001C\u0003\u0005\u0013AqAa\u0005\u0002\t\u000b\u0011)\u0002C\u0004\u0003 \u0005!)A!\t\t\u000f\t-\u0012\u0001\"\u0002\u0003.!9!qG\u0001\u0005\u0006\te\u0002b\u0002B\"\u0003\u0011\u0015!Q\t\u0005\n\u0005\u001f\n\u0011\u0011!C\u0003\u0005#B\u0011B!\u0016\u0002\u0003\u0003%)Aa\u0016\u0007\t]\u0002$! \u0005\u000b\u0003\u001fa\"Q1A\u0005\u0002\u0005E\u0001\"CA\n9\t\u0005\t\u0015!\u0003_\u0011\u0019yD\u0004\"\u0001\u0002\u0016!9\u0011\u0011\u0004\u000f\u0005\u0002\u0005m\u0001bBA 9\u0011\u0005\u0011\u0011\u0003\u0005\u0007\u0003\u0013bB\u0011A>\t\u000f\u00055C\u0004\"\u0011\u0002P!9\u00111\u000b\u000f\u0005\u0002\u0005U\u0003bBA.9\u0011\u0005\u0011Q\f\u0005\b\u0003CbB\u0011AA2\u0011\u001d\t9\u0007\bC\u0001\u0003SBq!a\u001e\u001d\t\u0003\tI\bC\u0004\u0002\u0000q!\t!!!\t\u000f\u0005\u001dE\u0004\"\u0001\u0002\n\"9\u0011q\u0012\u000f\u0005\u0002\u0005E\u0005bBAL9\u0011\u0005\u0011\u0011\u0014\u0005\n\u0003?c\u0012\u0011!C!\u0003CC\u0011\"!+\u001d\u0003\u0003%\t%a+\u0002\rM#(/\u001b8h\u0015\t\t$\'\u0001\u0004tSJ,W/\u001c\u0006\u0002g\u0005\u0019qN]4\u0004\u0001A\u0011a\'A\u0007\u0002a\t11\u000b\u001e:j]\u001e\u001c\"!A\u001d\u0011\u0005ijT\"A\u001e\u000b\u0003q\nQa]2bY\u0006L!AP\u001e\u0003\r\u0005s\u0017PU3g\u0003\u0019a\u0014N\\5u}Q\tQ\'A\u0003C_b,\'\u000f\u0005\u0002D\t5\t\u0011AA\u0003C_b,\'oE\u0002\u0005s\u0019\u0003\"a\u0012&\u000e\u0003!S!!\u0013\u0019\u0002\u0013\u0011Jg\u000e^3s]\u0006d\u0017B\u0001#I)\u0005\u0011\u0015a\u00012pqV\u0011a*\u0015\u000b\u0003\u001fj\u0003\"\u0001U)\r\u0001\u0011)!K\u0002b\u0001\'\n\tA+\u0005\u0002U/B\u0011!(V\u0005\u0003-n\u0012qAT8uQ&tw\r\u0005\u0002;1&\u0011\u0011l\u000f\u0002\u0004\u0003:L\b\"B.\u0007\u0001\u00049\u0016!A8\u0002\u000bUt\'m\u001c=\u0015\u0005y#\u0007CA0c\u001d\tQ\u0004-\u0003\u0002bw\u00051\u0001K]3eK\u001aL!aN2\u000b\u0005\u0005\\\u0004\"B.\b\u0001\u00049\u0016aB2paflU\u000f\u001e\u000b\u0007O*d\u0017o];\u0011\u0005iB\u0017BA5<\u0005\u0011)f.\u001b;\t\u000b-D\u0001\u0019A\u001d\u0002\u0007M\u00148\rC\u0003n\u0011\u0001\u0007a.\u0001\u0004te\u000e\u0004vn\u001d\t\u0003m=L!\u0001\u001d\u0019\u0003\u0003iCQA\u001d\u0005A\u0002e\nA\u0001Z3ti\")A\u000f\u0003a\u0001]\u00069A-Z:u!>\u001c\b\"\u0002<\t\u0001\u0004q\u0017A\u00027f]\u001e$\b.\u0001\u0004fg\u000e\f\u0007/\u001a\u000b\u0003=fDQaW\u0005A\u0002]\u000baA]1oI>lW#\u0001?\u0011\u0005Yb2C\u0002\u000f\u007f\u0003\u0007\tI\u0001\u0005\u0002;\u007f&\u0019\u0011\u0011A\u001e\u0003\r\u0005s\u0017PV1m!\r1\u0014QA\u0005\u0004\u0003\u000f\u0001$!C%n[V$\u0018M\u00197f!\r9\u00151B\u0005\u0004\u0003\u001bA%\u0001\u0003%bg\n{\u00070\u001a:\u0002\u000bY\fG.^3\u0016\u0003y\u000baA^1mk\u0016\u0004Cc\u0001?\u0002\u0018!1\u0011qB\u0010A\u0002y\u000bQ!\u00199qYf$B!!\b\u00026A!\u0011qDA\u0018\u001d\u0011\t\t#a\n\u000f\u0007Y\n\u0019#C\u0002\u0002&A\nq\u0001]1dW\u0006<W-\u0003\u0003\u0002*\u0005-\u0012\u0001C\"p]R\u0014\u0018m\u0019;\n\u0007\u00055\u0002G\u0001\u0005d_:$(/Y2u\u0013\u0011\t\t$a\r\u0003\u001b)+8\u000f^5gS\u000e\fG/[8o\u0015\u0011\tI#a\u000b\t\u000f\u0005]\u0002\u00051\u0001\u0002:\u0005!\u0011M]4t!\u0011Q\u00141H,\n\u0007\u0005u2H\u0001\u0006=e\u0016\u0004X-\u0019;fIz\naA\\1uSZ,\u0007fA\u0011\u0002DA\u0019!(!\u0012\n\u0007\u0005\u001d3H\u0001\u0004j]2Lg.Z\u0001\u0007gR\u0014\u0018N\\4)\u0007\t\n\u0019%\u0001\u0005u_N#(/\u001b8h)\u0005q\u0006fA\u0012\u0002D\u0005Y1\u000f\u001e:jaB\u0013XMZ5y)\rq\u0016q\u000b\u0005\u0007\u00033\"\u0003\u0019\u00010\u0002\rA\u0014XMZ5y\u0003\u0015\u0011w\u000e_3s+\u00051\u0005fA\u0013\u0002D\u0005!1/\u001b>f+\u0005q\u0007f\u0001\u0014\u0002D\u0005)A\u0005\\3tgR!\u00111NA9!\r1\u0014QN\u0005\u0004\u0003_\u0002$!\u0001\"\t\r\u0005Mt\u00051\u0001}\u0003\u0015yG\u000f[3sQ\r9\u00131I\u0001\tI1,7o\u001d\u0013fcR!\u00111NA>\u0011\u0019\t\u0019\b\u000ba\u0001y\"\u001a\u0001&a\u0011\u0002\u0011\u0011:\'/Z1uKJ$B!a\u001b\u0002\u0004\"1\u00111O\u0015A\u0002qD3!KA\"\u0003-!sM]3bi\u0016\u0014H%Z9\u0015\t\u0005-\u00141\u0012\u0005\u0007\u0003gR\u0003\u0019\u0001?)\u0007)\n\u0019%A\u0005%KF$S-\u001d\u0013fcR!\u00111NAJ\u0011\u0019\t\u0019h\u000ba\u0001y\"\u001a1&a\u0011\u0002\u0017\u0011*\u0017\u000f\n2b]\u001e$S-\u001d\u000b\u0005\u0003W\nY\n\u0003\u0004\u0002t1\u0002\r\u0001 \u0015\u0004Y\u0005\r\u0013\u0001\u00035bg\"\u001cu\u000eZ3\u0015\u0005\u0005\r\u0006c\u0001\u001e\u0002&&\u0019\u0011qU\u001e\u0003\u0007%sG/\u0001\u0004fcV\fGn\u001d\u000b\u0005\u0003[\u000b\u0019\fE\u0002;\u0003_K1!!-<\u0005\u001d\u0011un\u001c7fC:D\u0001\"!./\u0003\u0003\u0005\raV\u0001\u0004q\u0012\n\u0014aB;oCB\u0004H.\u001f\u000b\u0005\u0003w\u000b\t\r\u0005\u0003;\u0003{s\u0016bAA`w\t1q\n\u001d;j_:Da!a1\f\u0001\u0004a\u0018!A:\u0015\u0007q\f9\r\u0003\u0004\u0002D2\u0001\rAX\u0001\u0010CB\u0004H.\u001f\u0013fqR,gn]5p]R!\u0011QZAi)\u0011\ti\"a4\t\u000f\u0005]R\u00021\u0001\u0002:!1\u00111[\u0007A\u0002q\fQ\u0001\n;iSN\f\u0001C\\1uSZ,G%\u001a=uK:\u001c\u0018n\u001c8\u0015\u0007y\u000bI\u000e\u0003\u0004\u0002T:\u0001\r\u0001 \u0015\u0004\u001d\u0005\r\u0013\u0001E:ue&tw\rJ3yi\u0016t7/[8o)\ra\u0018\u0011\u001d\u0005\u0007\u0003\'|\u0001\u0019\u0001?)\u0007=\t\u0019%\u0001\nu_N#(/\u001b8hI\u0015DH/\u001a8tS>tG\u0003BA(\u0003SDa!a5\u0011\u0001\u0004a\bf\u0001\t\u0002D\u0005)2\u000f\u001e:jaB\u0013XMZ5yI\u0015DH/\u001a8tS>tG\u0003BAy\u0003k$2AXAz\u0011\u0019\tI&\u0005a\u0001=\"1\u00111[\tA\u0002q\fqBY8yKJ$S\r\u001f;f]NLwN\u001c\u000b\u0004\r\u0006m\bBBAj%\u0001\u0007A\u0010K\u0002\u0013\u0003\u0007\nab]5{K\u0012*\u0007\u0010^3og&|g\u000eF\u0002o\u0005\u0007Aa!a5\u0014\u0001\u0004a\bfA\n\u0002D\u0005yA\u0005\\3tg\u0012*\u0007\u0010^3og&|g\u000e\u0006\u0003\u0003\f\t=A\u0003BA6\u0005\u001bAa!a\u001d\u0015\u0001\u0004a\bBBAj)\u0001\u0007A\u0010K\u0002\u0015\u0003\u0007\n!\u0003\n7fgN$S-\u001d\u0013fqR,gn]5p]R!!q\u0003B\u000e)\u0011\tYG!\u0007\t\r\u0005MT\u00031\u0001}\u0011\u0019\t\u0019.\u0006a\u0001y\"\u001aQ#a\u0011\u0002%\u0011:\'/Z1uKJ$S\r\u001f;f]NLwN\u001c\u000b\u0005\u0005G\u00119\u0003\u0006\u0003\u0002l\t\u0015\u0002BBA:-\u0001\u0007A\u0010\u0003\u0004\u0002TZ\u0001\r\u0001 \u0015\u0004-\u0005\r\u0013!\u0006\u0013he\u0016\fG/\u001a:%KF$S\r\u001f;f]NLwN\u001c\u000b\u0005\u0005_\u0011\u0019\u0004\u0006\u0003\u0002l\tE\u0002BBA:/\u0001\u0007A\u0010\u0003\u0004\u0002T^\u0001\r\u0001 \u0015\u0004/\u0005\r\u0013a\u0005\u0013fc\u0012*\u0017\u000fJ3rI\u0015DH/\u001a8tS>tG\u0003\u0002B\u001e\u0005\u007f!B!a\u001b\u0003>!1\u00111\u000f\rA\u0002qDa!a5\u0019\u0001\u0004a\bf\u0001\r\u0002D\u0005)B%Z9%E\u0006tw\rJ3rI\u0015DH/\u001a8tS>tG\u0003\u0002B$\u0005\u0017\"B!a\u001b\u0003J!1\u00111O\rA\u0002qDa!a5\u001a\u0001\u0004a\bfA\r\u0002D\u0005\u0011\u0002.Y:i\u0007>$W\rJ3yi\u0016t7/[8o)\u0011\t\tKa\u0015\t\r\u0005M\'\u00041\u0001}\u0003A)\u0017/^1mg\u0012*\u0007\u0010^3og&|g\u000e\u0006\u0003\u0003Z\tuC\u0003BAW\u00057B\u0001\"!.\u001c\u0003\u0003\u0005\ra\u0016\u0005\u0007\u0003\'\\\u0002\u0019\u0001?"
    )
  ScalaInlineInfo: length = 0x72 (unknown attribute)
   01 01 00 16 00 6C 00 6D 01 00 7E 00 A0 01 00 7E
   00 7F 01 00 9B 00 96 05 00 9A 00 96 05 00 98 00
   96 05 00 99 00 96 05 00 74 00 75 01 00 7A 00 75
   01 00 95 00 96 05 00 97 00 96 05 00 A3 00 A4 01
   00 88 00 89 01 00 91 00 92 05 00 9E 00 9F 01 00
   9C 00 9D 01 00 8D 00 64 05 00 93 00 94 05 00 8E
   00 64 05 00 90 00 4D 01 00 8F 00 64 05 00 18 00
   64 01
  ScalaSig: length = 0x3 (unknown attribute)
   05 02 00
