Classfile /Users/mw/Projects/slang-braindump/.jar/jar11/assemble/slang-braindump/assemble/content/org/sireum/Z$Boxer$Long.class
  Last modified May 29, 2022; size 3948 bytes
  SHA-256 checksum 54b41eab85f7ee66fb8d6cf9af3bd265439cfcb4e7e644fbe24dcc2b2655eca5
  Compiled from "Z.scala"
public interface org.sireum.Z$Boxer$Long extends org.sireum.$internal.Boxer
  minor version: 0
  major version: 52
  flags: (0x0601) ACC_PUBLIC, ACC_INTERFACE, ACC_ABSTRACT
  this_class: #2                          // org/sireum/Z$Boxer$Long
  super_class: #4                         // java/lang/Object
  interfaces: 1, fields: 0, methods: 14, attributes: 4
Constant pool:
    #1 = Utf8               org/sireum/Z$Boxer$Long
    #2 = Class              #1            // org/sireum/Z$Boxer$Long
    #3 = Utf8               java/lang/Object
    #4 = Class              #3            // java/lang/Object
    #5 = Utf8               org/sireum/$internal/Boxer
    #6 = Class              #5            // org/sireum/$internal/Boxer
    #7 = Utf8               Z.scala
    #8 = Utf8               org/sireum/Z$BV$
    #9 = Class              #8            // org/sireum/Z$BV$
   #10 = Utf8               org/sireum/Z
   #11 = Class              #10           // org/sireum/Z
   #12 = Utf8               BV$
   #13 = Utf8               org/sireum/Z$BV$Long
   #14 = Class              #13           // org/sireum/Z$BV$Long
   #15 = Utf8               Long
   #16 = Utf8               org/sireum/Z$Boxer$
   #17 = Class              #16           // org/sireum/Z$Boxer$
   #18 = Utf8               Boxer$
   #19 = Utf8               org/sireum/Z$Range
   #20 = Class              #19           // org/sireum/Z$Range
   #21 = Utf8               Range
   #22 = Utf8               box$
   #23 = Utf8               (Lorg/sireum/Z$Boxer$Long;Ljava/lang/Object;)Ljava/lang/Object;
   #24 = Utf8               $this
   #25 = Utf8               o
   #26 = Utf8               box
   #27 = Utf8               (Ljava/lang/Object;)Ljava/lang/Object;
   #28 = NameAndType        #26:#27       // box:(Ljava/lang/Object;)Ljava/lang/Object;
   #29 = InterfaceMethodref #2.#28        // org/sireum/Z$Boxer$Long.box:(Ljava/lang/Object;)Ljava/lang/Object;
   #30 = Utf8               Lorg/sireum/Z$Boxer$Long;
   #31 = Utf8               Ljava/lang/Object;
   #32 = Utf8               <T:Ljava/lang/Object;>(Ljava/lang/Object;)TT;
   #33 = Utf8               java/lang/Long
   #34 = Class              #33           // java/lang/Long
   #35 = Utf8               scala/runtime/BoxesRunTime
   #36 = Class              #35           // scala/runtime/BoxesRunTime
   #37 = Utf8               unboxToLong
   #38 = Utf8               (Ljava/lang/Object;)J
   #39 = NameAndType        #37:#38       // unboxToLong:(Ljava/lang/Object;)J
   #40 = Methodref          #36.#39       // scala/runtime/BoxesRunTime.unboxToLong:(Ljava/lang/Object;)J
   #41 = Utf8               make
   #42 = Utf8               (J)Ljava/lang/Object;
   #43 = NameAndType        #41:#42       // make:(J)Ljava/lang/Object;
   #44 = InterfaceMethodref #2.#43        // org/sireum/Z$Boxer$Long.make:(J)Ljava/lang/Object;
   #45 = Utf8               scala/MatchError
   #46 = Class              #45           // scala/MatchError
   #47 = Utf8               <init>
   #48 = Utf8               (Ljava/lang/Object;)V
   #49 = NameAndType        #47:#48       // "<init>":(Ljava/lang/Object;)V
   #50 = Methodref          #46.#49       // scala/MatchError."<init>":(Ljava/lang/Object;)V
   #51 = Utf8               this
   #52 = Utf8               unbox$
   #53 = Utf8               (Lorg/sireum/Z$Boxer$Long;Ljava/lang/Object;)J
   #54 = Utf8               unbox
   #55 = NameAndType        #54:#38       // unbox:(Ljava/lang/Object;)J
   #56 = InterfaceMethodref #2.#55        // org/sireum/Z$Boxer$Long.unbox:(Ljava/lang/Object;)J
   #57 = Utf8               value
   #58 = Utf8               ()J
   #59 = NameAndType        #57:#58       // value:()J
   #60 = InterfaceMethodref #14.#59       // org/sireum/Z$BV$Long.value:()J
   #61 = Utf8               ()Lorg/sireum/Z;
   #62 = NameAndType        #57:#61       // value:()Lorg/sireum/Z;
   #63 = InterfaceMethodref #20.#62       // org/sireum/Z$Range.value:()Lorg/sireum/Z;
   #64 = Utf8               toLong
   #65 = Utf8               (Lorg/sireum/Z;)J
   #66 = NameAndType        #64:#65       // toLong:(Lorg/sireum/Z;)J
   #67 = InterfaceMethodref #2.#66        // org/sireum/Z$Boxer$Long.toLong:(Lorg/sireum/Z;)J
   #68 = Utf8               copyMut$
   #69 = Utf8               (Lorg/sireum/Z$Boxer$Long;Ljava/lang/Object;Lorg/sireum/Z;Ljava/lang/Object;Lorg/sireum/Z;Lorg/sireum/Z;)V
   #70 = Utf8               src
   #71 = Utf8               srcPos
   #72 = Utf8               dest
   #73 = Utf8               destPos
   #74 = Utf8               length
   #75 = Utf8               copyMut
   #76 = Utf8               (Ljava/lang/Object;Lorg/sireum/Z;Ljava/lang/Object;Lorg/sireum/Z;Lorg/sireum/Z;)V
   #77 = NameAndType        #75:#76       // copyMut:(Ljava/lang/Object;Lorg/sireum/Z;Ljava/lang/Object;Lorg/sireum/Z;Lorg/sireum/Z;)V
   #78 = InterfaceMethodref #2.#77        // org/sireum/Z$Boxer$Long.copyMut:(Ljava/lang/Object;Lorg/sireum/Z;Ljava/lang/Object;Lorg/sireum/Z;Lorg/sireum/Z;)V
   #79 = Utf8               Lorg/sireum/Z;
   #80 = Utf8               copy
   #81 = NameAndType        #80:#76       // copy:(Ljava/lang/Object;Lorg/sireum/Z;Ljava/lang/Object;Lorg/sireum/Z;Lorg/sireum/Z;)V
   #82 = InterfaceMethodref #2.#81        // org/sireum/Z$Boxer$Long.copy:(Ljava/lang/Object;Lorg/sireum/Z;Ljava/lang/Object;Lorg/sireum/Z;Lorg/sireum/Z;)V
   #83 = Utf8               create$
   #84 = Utf8               (Lorg/sireum/Z$Boxer$Long;Lorg/sireum/Z;)Ljava/lang/Object;
   #85 = Utf8               create
   #86 = Utf8               (Lorg/sireum/Z;)Ljava/lang/Object;
   #87 = NameAndType        #85:#86       // create:(Lorg/sireum/Z;)Ljava/lang/Object;
   #88 = InterfaceMethodref #2.#87        // org/sireum/Z$Boxer$Long.create:(Lorg/sireum/Z;)Ljava/lang/Object;
   #89 = Utf8               toInt
   #90 = Utf8               (Lorg/sireum/Z;)I
   #91 = NameAndType        #89:#90       // toInt:(Lorg/sireum/Z;)I
   #92 = InterfaceMethodref #2.#91        // org/sireum/Z$Boxer$Long.toInt:(Lorg/sireum/Z;)I
   #93 = Utf8               lookup$
   #94 = Utf8               (Lorg/sireum/Z$Boxer$Long;Ljava/lang/Object;Lorg/sireum/Z;)Ljava/lang/Object;
   #95 = Utf8               a
   #96 = Utf8               i
   #97 = Utf8               lookup
   #98 = Utf8               (Ljava/lang/Object;Lorg/sireum/Z;)Ljava/lang/Object;
   #99 = NameAndType        #97:#98       // lookup:(Ljava/lang/Object;Lorg/sireum/Z;)Ljava/lang/Object;
  #100 = InterfaceMethodref #2.#99        // org/sireum/Z$Boxer$Long.lookup:(Ljava/lang/Object;Lorg/sireum/Z;)Ljava/lang/Object;
  #101 = Utf8               <T:Ljava/lang/Object;>(Ljava/lang/Object;Lorg/sireum/Z;)TT;
  #102 = Utf8               [J
  #103 = Class              #102          // "[J"
  #104 = Utf8               boxToLong
  #105 = Utf8               (J)Ljava/lang/Long;
  #106 = NameAndType        #104:#105     // boxToLong:(J)Ljava/lang/Long;
  #107 = Methodref          #36.#106      // scala/runtime/BoxesRunTime.boxToLong:(J)Ljava/lang/Long;
  #108 = Utf8               store$
  #109 = Utf8               (Lorg/sireum/Z$Boxer$Long;Ljava/lang/Object;Lorg/sireum/Z;Ljava/lang/Object;)V
  #110 = Utf8               v
  #111 = Utf8               store
  #112 = Utf8               (Ljava/lang/Object;Lorg/sireum/Z;Ljava/lang/Object;)V
  #113 = NameAndType        #111:#112     // store:(Ljava/lang/Object;Lorg/sireum/Z;Ljava/lang/Object;)V
  #114 = InterfaceMethodref #2.#113       // org/sireum/Z$Boxer$Long.store:(Ljava/lang/Object;Lorg/sireum/Z;Ljava/lang/Object;)V
  #115 = Utf8               scala/runtime/BoxedUnit
  #116 = Class              #115          // scala/runtime/BoxedUnit
  #117 = Utf8               UNIT
  #118 = Utf8               Lscala/runtime/BoxedUnit;
  #119 = NameAndType        #117:#118     // UNIT:Lscala/runtime/BoxedUnit;
  #120 = Fieldref           #116.#119     // scala/runtime/BoxedUnit.UNIT:Lscala/runtime/BoxedUnit;
  #121 = Utf8               $init$
  #122 = Utf8               (Lorg/sireum/Z$Boxer$Long;)V
  #123 = Utf8               Code
  #124 = Utf8               LineNumberTable
  #125 = Utf8               LocalVariableTable
  #126 = Utf8               MethodParameters
  #127 = Utf8               StackMapTable
  #128 = Utf8               Signature
  #129 = Utf8               InnerClasses
  #130 = Utf8               SourceFile
  #131 = Utf8               ScalaInlineInfo
  #132 = Utf8               Scala
{
  public static java.lang.Object box$(org.sireum.Z$Boxer$Long, java.lang.Object);
    descriptor: (Lorg/sireum/Z$Boxer$Long;Ljava/lang/Object;)Ljava/lang/Object;
    flags: (0x1009) ACC_PUBLIC, ACC_STATIC, ACC_SYNTHETIC
    Code:
      stack=2, locals=2, args_size=2
         0: aload_0
         1: aload_1
         2: invokespecial #29                 // InterfaceMethod box:(Ljava/lang/Object;)Ljava/lang/Object;
         5: areturn
      LineNumberTable:
        line 281: 0
      LocalVariableTable:
        Start  Length  Slot  Name   Signature
            0       6     0 $this   Lorg/sireum/Z$Boxer$Long;
            0       6     1     o   Ljava/lang/Object;
    MethodParameters:
      Name                           Flags
      $this                          final synthetic
      o                              final

  public default <T extends java.lang.Object> T box(java.lang.Object);
    descriptor: (Ljava/lang/Object;)Ljava/lang/Object;
    flags: (0x0001) ACC_PUBLIC
    Code:
      stack=3, locals=6, args_size=2
         0: aload_1
         1: astore_3
         2: aload_3
         3: instanceof    #34                 // class java/lang/Long
         6: ifeq          27
         9: aload_3
        10: invokestatic  #40                 // Method scala/runtime/BoxesRunTime.unboxToLong:(Ljava/lang/Object;)J
        13: lstore        4
        15: aload_0
        16: lload         4
        18: invokeinterface #44,  3           // InterfaceMethod make:(J)Ljava/lang/Object;
        23: astore_2
        24: goto          39
        27: goto          30
        30: new           #46                 // class scala/MatchError
        33: dup
        34: aload_3
        35: invokespecial #50                 // Method scala/MatchError."<init>":(Ljava/lang/Object;)V
        38: athrow
        39: aload_2
        40: areturn
      StackMapTable: number_of_entries = 3
        frame_type = 253 /* append */
          offset_delta = 27
          locals = [ top, class java/lang/Object ]
        frame_type = 2 /* same */
        frame_type = 255 /* full_frame */
          offset_delta = 8
          locals = [ class org/sireum/Z$Boxer$Long, class java/lang/Object, class java/lang/Object, class java/lang/Object, long ]
          stack = []
      LineNumberTable:
        line 281: 0
        line 282: 2
        line 281: 30
      LocalVariableTable:
        Start  Length  Slot  Name   Signature
            0      41     0  this   Lorg/sireum/Z$Boxer$Long;
            0      41     1     o   Ljava/lang/Object;
    Signature: #32                          // <T:Ljava/lang/Object;>(Ljava/lang/Object;)TT;
    MethodParameters:
      Name                           Flags
      o                              final

  public static long unbox$(org.sireum.Z$Boxer$Long, java.lang.Object);
    descriptor: (Lorg/sireum/Z$Boxer$Long;Ljava/lang/Object;)J
    flags: (0x1009) ACC_PUBLIC, ACC_STATIC, ACC_SYNTHETIC
    Code:
      stack=2, locals=2, args_size=2
         0: aload_0
         1: aload_1
         2: invokespecial #56                 // InterfaceMethod unbox:(Ljava/lang/Object;)J
         5: lreturn
      LineNumberTable:
        line 285: 0
      LocalVariableTable:
        Start  Length  Slot  Name   Signature
            0       6     0 $this   Lorg/sireum/Z$Boxer$Long;
            0       6     1     o   Ljava/lang/Object;
    MethodParameters:
      Name                           Flags
      $this                          final synthetic
      o                              final

  public default long unbox(java.lang.Object);
    descriptor: (Ljava/lang/Object;)J
    flags: (0x0001) ACC_PUBLIC
    Code:
      stack=3, locals=7, args_size=2
         0: aload_1
         1: astore        4
         3: aload         4
         5: instanceof    #14                 // class org/sireum/Z$BV$Long
         8: ifeq          29
        11: aload         4
        13: checkcast     #14                 // class org/sireum/Z$BV$Long
        16: astore        5
        18: aload         5
        20: invokeinterface #60,  1           // InterfaceMethod org/sireum/Z$BV$Long.value:()J
        25: lstore_2
        26: goto          77
        29: goto          32
        32: aload         4
        34: instanceof    #20                 // class org/sireum/Z$Range
        37: ifeq          64
        40: aload         4
        42: checkcast     #20                 // class org/sireum/Z$Range
        45: astore        6
        47: aload_0
        48: aload         6
        50: invokeinterface #63,  1           // InterfaceMethod org/sireum/Z$Range.value:()Lorg/sireum/Z;
        55: invokeinterface #67,  2           // InterfaceMethod toLong:(Lorg/sireum/Z;)J
        60: lstore_2
        61: goto          77
        64: goto          67
        67: new           #46                 // class scala/MatchError
        70: dup
        71: aload         4
        73: invokespecial #50                 // Method scala/MatchError."<init>":(Ljava/lang/Object;)V
        76: athrow
        77: lload_2
        78: lreturn
      StackMapTable: number_of_entries = 5
        frame_type = 254 /* append */
          offset_delta = 29
          locals = [ top, top, class java/lang/Object ]
        frame_type = 2 /* same */
        frame_type = 31 /* same */
        frame_type = 2 /* same */
        frame_type = 255 /* full_frame */
          offset_delta = 9
          locals = [ class org/sireum/Z$Boxer$Long, class java/lang/Object, long, class java/lang/Object ]
          stack = []
      LineNumberTable:
        line 285: 0
        line 286: 3
        line 287: 32
        line 285: 67
      LocalVariableTable:
        Start  Length  Slot  Name   Signature
            0      79     0  this   Lorg/sireum/Z$Boxer$Long;
            0      79     1     o   Ljava/lang/Object;
    MethodParameters:
      Name                           Flags
      o                              final

  public static void copyMut$(org.sireum.Z$Boxer$Long, java.lang.Object, org.sireum.Z, java.lang.Object, org.sireum.Z, org.sireum.Z);
    descriptor: (Lorg/sireum/Z$Boxer$Long;Ljava/lang/Object;Lorg/sireum/Z;Ljava/lang/Object;Lorg/sireum/Z;Lorg/sireum/Z;)V
    flags: (0x1009) ACC_PUBLIC, ACC_STATIC, ACC_SYNTHETIC
    Code:
      stack=6, locals=6, args_size=6
         0: aload_0
         1: aload_1
         2: aload_2
         3: aload_3
         4: aload         4
         6: aload         5
         8: invokespecial #78                 // InterfaceMethod copyMut:(Ljava/lang/Object;Lorg/sireum/Z;Ljava/lang/Object;Lorg/sireum/Z;Lorg/sireum/Z;)V
        11: return
      LineNumberTable:
        line 290: 0
      LocalVariableTable:
        Start  Length  Slot  Name   Signature
            0      12     0 $this   Lorg/sireum/Z$Boxer$Long;
            0      12     1   src   Ljava/lang/Object;
            0      12     2 srcPos   Lorg/sireum/Z;
            0      12     3  dest   Ljava/lang/Object;
            0      12     4 destPos   Lorg/sireum/Z;
            0      12     5 length   Lorg/sireum/Z;
    MethodParameters:
      Name                           Flags
      $this                          final synthetic
      src                            final
      srcPos                         final
      dest                           final
      destPos                        final
      length                         final

  public default void copyMut(java.lang.Object, org.sireum.Z, java.lang.Object, org.sireum.Z, org.sireum.Z);
    descriptor: (Ljava/lang/Object;Lorg/sireum/Z;Ljava/lang/Object;Lorg/sireum/Z;Lorg/sireum/Z;)V
    flags: (0x0001) ACC_PUBLIC
    Code:
      stack=6, locals=6, args_size=6
         0: aload_0
         1: aload_1
         2: aload_2
         3: aload_3
         4: aload         4
         6: aload         5
         8: invokeinterface #82,  6           // InterfaceMethod copy:(Ljava/lang/Object;Lorg/sireum/Z;Ljava/lang/Object;Lorg/sireum/Z;Lorg/sireum/Z;)V
        13: return
      LineNumberTable:
        line 291: 0
      LocalVariableTable:
        Start  Length  Slot  Name   Signature
            0      14     0  this   Lorg/sireum/Z$Boxer$Long;
            0      14     1   src   Ljava/lang/Object;
            0      14     2 srcPos   Lorg/sireum/Z;
            0      14     3  dest   Ljava/lang/Object;
            0      14     4 destPos   Lorg/sireum/Z;
            0      14     5 length   Lorg/sireum/Z;
    MethodParameters:
      Name                           Flags
      src                            final
      srcPos                         final
      dest                           final
      destPos                        final
      length                         final

  public static java.lang.Object create$(org.sireum.Z$Boxer$Long, org.sireum.Z);
    descriptor: (Lorg/sireum/Z$Boxer$Long;Lorg/sireum/Z;)Ljava/lang/Object;
    flags: (0x1009) ACC_PUBLIC, ACC_STATIC, ACC_SYNTHETIC
    Code:
      stack=2, locals=2, args_size=2
         0: aload_0
         1: aload_1
         2: invokespecial #88                 // InterfaceMethod create:(Lorg/sireum/Z;)Ljava/lang/Object;
         5: areturn
      LineNumberTable:
        line 293: 0
      LocalVariableTable:
        Start  Length  Slot  Name   Signature
            0       6     0 $this   Lorg/sireum/Z$Boxer$Long;
            0       6     1 length   Lorg/sireum/Z;
    MethodParameters:
      Name                           Flags
      $this                          final synthetic
      length                         final

  public default java.lang.Object create(org.sireum.Z);
    descriptor: (Lorg/sireum/Z;)Ljava/lang/Object;
    flags: (0x0001) ACC_PUBLIC
    Code:
      stack=2, locals=2, args_size=2
         0: aload_0
         1: aload_1
         2: invokeinterface #92,  2           // InterfaceMethod toInt:(Lorg/sireum/Z;)I
         7: newarray       long
         9: areturn
      LineNumberTable:
        line 293: 0
      LocalVariableTable:
        Start  Length  Slot  Name   Signature
            0      10     0  this   Lorg/sireum/Z$Boxer$Long;
            0      10     1 length   Lorg/sireum/Z;
    MethodParameters:
      Name                           Flags
      length                         final

  public static java.lang.Object lookup$(org.sireum.Z$Boxer$Long, java.lang.Object, org.sireum.Z);
    descriptor: (Lorg/sireum/Z$Boxer$Long;Ljava/lang/Object;Lorg/sireum/Z;)Ljava/lang/Object;
    flags: (0x1009) ACC_PUBLIC, ACC_STATIC, ACC_SYNTHETIC
    Code:
      stack=3, locals=3, args_size=3
         0: aload_0
         1: aload_1
         2: aload_2
         3: invokespecial #100                // InterfaceMethod lookup:(Ljava/lang/Object;Lorg/sireum/Z;)Ljava/lang/Object;
         6: areturn
      LineNumberTable:
        line 295: 0
      LocalVariableTable:
        Start  Length  Slot  Name   Signature
            0       7     0 $this   Lorg/sireum/Z$Boxer$Long;
            0       7     1     a   Ljava/lang/Object;
            0       7     2     i   Lorg/sireum/Z;
    MethodParameters:
      Name                           Flags
      $this                          final synthetic
      a                              final
      i                              final

  public default <T extends java.lang.Object> T lookup(java.lang.Object, org.sireum.Z);
    descriptor: (Ljava/lang/Object;Lorg/sireum/Z;)Ljava/lang/Object;
    flags: (0x0001) ACC_PUBLIC
    Code:
      stack=4, locals=6, args_size=3
         0: aload_1
         1: astore        4
         3: aload         4
         5: instanceof    #103                // class "[J"
         8: ifeq          41
        11: aload         4
        13: checkcast     #103                // class "[J"
        16: astore        5
        18: aload_0
        19: aload         5
        21: aload_0
        22: aload_2
        23: invokeinterface #92,  2           // InterfaceMethod toInt:(Lorg/sireum/Z;)I
        28: laload
        29: invokestatic  #107                // Method scala/runtime/BoxesRunTime.boxToLong:(J)Ljava/lang/Long;
        32: invokeinterface #29,  2           // InterfaceMethod box:(Ljava/lang/Object;)Ljava/lang/Object;
        37: astore_3
        38: goto          54
        41: goto          44
        44: new           #46                 // class scala/MatchError
        47: dup
        48: aload         4
        50: invokespecial #50                 // Method scala/MatchError."<init>":(Ljava/lang/Object;)V
        53: athrow
        54: aload_3
        55: areturn
      StackMapTable: number_of_entries = 3
        frame_type = 253 /* append */
          offset_delta = 41
          locals = [ top, class java/lang/Object ]
        frame_type = 2 /* same */
        frame_type = 255 /* full_frame */
          offset_delta = 9
          locals = [ class org/sireum/Z$Boxer$Long, class java/lang/Object, class org/sireum/Z, class java/lang/Object, class java/lang/Object, class "[J" ]
          stack = []
      LineNumberTable:
        line 295: 0
        line 296: 3
        line 295: 44
      LocalVariableTable:
        Start  Length  Slot  Name   Signature
            0      56     0  this   Lorg/sireum/Z$Boxer$Long;
            0      56     1     a   Ljava/lang/Object;
            0      56     2     i   Lorg/sireum/Z;
    Signature: #101                         // <T:Ljava/lang/Object;>(Ljava/lang/Object;Lorg/sireum/Z;)TT;
    MethodParameters:
      Name                           Flags
      a                              final
      i                              final

  public static void store$(org.sireum.Z$Boxer$Long, java.lang.Object, org.sireum.Z, java.lang.Object);
    descriptor: (Lorg/sireum/Z$Boxer$Long;Ljava/lang/Object;Lorg/sireum/Z;Ljava/lang/Object;)V
    flags: (0x1009) ACC_PUBLIC, ACC_STATIC, ACC_SYNTHETIC
    Code:
      stack=4, locals=4, args_size=4
         0: aload_0
         1: aload_1
         2: aload_2
         3: aload_3
         4: invokespecial #114                // InterfaceMethod store:(Ljava/lang/Object;Lorg/sireum/Z;Ljava/lang/Object;)V
         7: return
      LineNumberTable:
        line 299: 0
      LocalVariableTable:
        Start  Length  Slot  Name   Signature
            0       8     0 $this   Lorg/sireum/Z$Boxer$Long;
            0       8     1     a   Ljava/lang/Object;
            0       8     2     i   Lorg/sireum/Z;
            0       8     3     v   Ljava/lang/Object;
    MethodParameters:
      Name                           Flags
      $this                          final synthetic
      a                              final
      i                              final
      v                              final

  public default void store(java.lang.Object, org.sireum.Z, java.lang.Object);
    descriptor: (Ljava/lang/Object;Lorg/sireum/Z;Ljava/lang/Object;)V
    flags: (0x0001) ACC_PUBLIC
    Code:
      stack=4, locals=7, args_size=4
         0: aload_1
         1: astore        5
         3: aload         5
         5: instanceof    #103                // class "[J"
         8: ifeq          43
        11: aload         5
        13: checkcast     #103                // class "[J"
        16: astore        6
        18: aload         6
        20: aload_0
        21: aload_2
        22: invokeinterface #92,  2           // InterfaceMethod toInt:(Lorg/sireum/Z;)I
        27: aload_0
        28: aload_3
        29: invokeinterface #56,  2           // InterfaceMethod unbox:(Ljava/lang/Object;)J
        34: lastore
        35: getstatic     #120                // Field scala/runtime/BoxedUnit.UNIT:Lscala/runtime/BoxedUnit;
        38: astore        4
        40: goto          56
        43: goto          46
        46: new           #46                 // class scala/MatchError
        49: dup
        50: aload         5
        52: invokespecial #50                 // Method scala/MatchError."<init>":(Ljava/lang/Object;)V
        55: athrow
        56: return
      StackMapTable: number_of_entries = 3
        frame_type = 253 /* append */
          offset_delta = 43
          locals = [ top, class java/lang/Object ]
        frame_type = 2 /* same */
        frame_type = 255 /* full_frame */
          offset_delta = 9
          locals = [ class org/sireum/Z$Boxer$Long, class java/lang/Object, class org/sireum/Z, class java/lang/Object, class scala/runtime/BoxedUnit, class java/lang/Object, class "[J" ]
          stack = []
      LineNumberTable:
        line 299: 0
        line 300: 3
        line 299: 46
      LocalVariableTable:
        Start  Length  Slot  Name   Signature
            0      57     0  this   Lorg/sireum/Z$Boxer$Long;
            0      57     1     a   Ljava/lang/Object;
            0      57     2     i   Lorg/sireum/Z;
            0      57     3     v   Ljava/lang/Object;
    MethodParameters:
      Name                           Flags
      a                              final
      i                              final
      v                              final

  public abstract java.lang.Object make(long);
    descriptor: (J)Ljava/lang/Object;
    flags: (0x0401) ACC_PUBLIC, ACC_ABSTRACT
    MethodParameters:
      Name                           Flags
      o                              final

  public static void $init$(org.sireum.Z$Boxer$Long);
    descriptor: (Lorg/sireum/Z$Boxer$Long;)V
    flags: (0x0009) ACC_PUBLIC, ACC_STATIC
    Code:
      stack=0, locals=1, args_size=1
         0: return
      LineNumberTable:
        line 279: 0
      LocalVariableTable:
        Start  Length  Slot  Name   Signature
            0       1     0 $this   Lorg/sireum/Z$Boxer$Long;
    MethodParameters:
      Name                           Flags
      $this                          final synthetic
}
InnerClasses:
  public static #12= #9 of #11;           // BV$=class org/sireum/Z$BV$ of class org/sireum/Z
  public static #15= #14 of #9;           // Long=class org/sireum/Z$BV$Long of class org/sireum/Z$BV$
  public static #18= #17 of #11;          // Boxer$=class org/sireum/Z$Boxer$ of class org/sireum/Z
  public static #15= #2 of #17;           // Long=class org/sireum/Z$Boxer$Long of class org/sireum/Z$Boxer$
  public static #21= #20 of #11;          // Range=class org/sireum/Z$Range of class org/sireum/Z
SourceFile: "Z.scala"
  ScalaInlineInfo: length = 0x4A (unknown attribute)
   01 00 00 0E 00 79 00 7A 01 00 1A 00 1B 00 00 16
   00 17 01 00 4B 00 4C 00 00 44 00 45 01 00 55 00
   56 00 00 53 00 54 01 00 61 00 62 00 00 5D 00 5E
   01 00 29 00 2A 00 00 6F 00 70 00 00 6C 00 6D 01
   00 36 00 26 00 00 34 00 35 01
  Scala: length = 0x0 (unknown attribute)

