Classfile /Users/mw/Projects/slang-braindump/.jar/jar11/assemble/slang-braindump/assemble/content/org/sireum/Z$Boxer$.class
  Last modified May 29, 2022; size 679 bytes
  SHA-256 checksum e26eab350c8929f00b703bb08aca7130df022e2878a80736a2ef5561e97dcff5
  Compiled from "Z.scala"
public class org.sireum.Z$Boxer$
  minor version: 0
  major version: 52
  flags: (0x0021) ACC_PUBLIC, ACC_SUPER
  this_class: #2                          // org/sireum/Z$Boxer$
  super_class: #4                         // java/lang/Object
  interfaces: 0, fields: 1, methods: 2, attributes: 4
Constant pool:
   #1 = Utf8               org/sireum/Z$Boxer$
   #2 = Class              #1             // org/sireum/Z$Boxer$
   #3 = Utf8               java/lang/Object
   #4 = Class              #3             // java/lang/Object
   #5 = Utf8               Z.scala
   #6 = Utf8               org/sireum/Z
   #7 = Class              #6             // org/sireum/Z
   #8 = Utf8               Boxer$
   #9 = Utf8               org/sireum/Z$Boxer$Byte
  #10 = Class              #9             // org/sireum/Z$Boxer$Byte
  #11 = Utf8               Byte
  #12 = Utf8               org/sireum/Z$Boxer$Int
  #13 = Class              #12            // org/sireum/Z$Boxer$Int
  #14 = Utf8               Int
  #15 = Utf8               org/sireum/Z$Boxer$Long
  #16 = Class              #15            // org/sireum/Z$Boxer$Long
  #17 = Utf8               Long
  #18 = Utf8               org/sireum/Z$Boxer$Short
  #19 = Class              #18            // org/sireum/Z$Boxer$Short
  #20 = Utf8               Short
  #21 = Utf8               org/sireum/Z$Boxer$Z$
  #22 = Class              #21            // org/sireum/Z$Boxer$Z$
  #23 = Utf8               Z$
  #24 = Utf8               MODULE$
  #25 = Utf8               Lorg/sireum/Z$Boxer$;
  #26 = Utf8               <clinit>
  #27 = Utf8               ()V
  #28 = Utf8               <init>
  #29 = NameAndType        #28:#27        // "<init>":()V
  #30 = Methodref          #2.#29         // org/sireum/Z$Boxer$."<init>":()V
  #31 = NameAndType        #24:#25        // MODULE$:Lorg/sireum/Z$Boxer$;
  #32 = Fieldref           #2.#31         // org/sireum/Z$Boxer$.MODULE$:Lorg/sireum/Z$Boxer$;
  #33 = Methodref          #4.#29         // java/lang/Object."<init>":()V
  #34 = Utf8               this
  #35 = Utf8               Code
  #36 = Utf8               LineNumberTable
  #37 = Utf8               LocalVariableTable
  #38 = Utf8               InnerClasses
  #39 = Utf8               SourceFile
  #40 = Utf8               ScalaInlineInfo
  #41 = Utf8               Scala
{
  public static final org.sireum.Z$Boxer$ MODULE$;
    descriptor: Lorg/sireum/Z$Boxer$;
    flags: (0x0019) ACC_PUBLIC, ACC_STATIC, ACC_FINAL

  public static {};
    descriptor: ()V
    flags: (0x0009) ACC_PUBLIC, ACC_STATIC
    Code:
      stack=2, locals=0, args_size=0
         0: new           #2                  // class org/sireum/Z$Boxer$
         3: dup
         4: invokespecial #30                 // Method "<init>":()V
         7: putstatic     #32                 // Field MODULE$:Lorg/sireum/Z$Boxer$;
        10: return
      LineNumberTable:
        line 192: 0

  public org.sireum.Z$Boxer$();
    descriptor: ()V
    flags: (0x0001) ACC_PUBLIC
    Code:
      stack=1, locals=1, args_size=1
         0: aload_0
         1: invokespecial #33                 // Method java/lang/Object."<init>":()V
         4: return
      LineNumberTable:
        line 192: 0
      LocalVariableTable:
        Start  Length  Slot  Name   Signature
            0       5     0  this   Lorg/sireum/Z$Boxer$;
}
InnerClasses:
  public static #8= #2 of #7;             // Boxer$=class org/sireum/Z$Boxer$ of class org/sireum/Z
  public static #11= #10 of #2;           // Byte=class org/sireum/Z$Boxer$Byte of class org/sireum/Z$Boxer$
  public static #14= #13 of #2;           // Int=class org/sireum/Z$Boxer$Int of class org/sireum/Z$Boxer$
  public static #17= #16 of #2;           // Long=class org/sireum/Z$Boxer$Long of class org/sireum/Z$Boxer$
  public static #20= #19 of #2;           // Short=class org/sireum/Z$Boxer$Short of class org/sireum/Z$Boxer$
  public static #23= #22 of #2;           // Z$=class org/sireum/Z$Boxer$Z$ of class org/sireum/Z$Boxer$
SourceFile: "Z.scala"
  ScalaInlineInfo: length = 0x9 (unknown attribute)
   01 01 00 01 00 1C 00 1B 01
  Scala: length = 0x0 (unknown attribute)

