Classfile /Users/mw/Projects/slang-braindump/.jar/jar11/assemble/slang-braindump/assemble/content/org/sireum/Z$BV$Short.class
  Last modified May 29, 2022; size 12730 bytes
  SHA-256 checksum 78dcb07a4d82f932db6c6b405943f474427b47a3a4056733b415a5b905bdf560
  Compiled from "Z.scala"
public interface org.sireum.Z$BV$Short<T extends org.sireum.Z$BV$Short<T>> extends org.sireum.ZLike<T>, org.sireum.$internal.HasBoxer
  minor version: 0
  major version: 52
  flags: (0x0601) ACC_PUBLIC, ACC_INTERFACE, ACC_ABSTRACT
  this_class: #2                          // org/sireum/Z$BV$Short
  super_class: #5                         // java/lang/Object
  interfaces: 2, fields: 0, methods: 69, attributes: 6
Constant pool:
    #1 = Utf8               org/sireum/Z$BV$Short
    #2 = Class              #1            // org/sireum/Z$BV$Short
    #3 = Utf8               <T::Lorg/sireum/Z$BV$Short<TT;>;>Ljava/lang/Object;Lorg/sireum/ZLike<TT;>;Lorg/sireum/$internal/HasBoxer;
    #4 = Utf8               java/lang/Object
    #5 = Class              #4            // java/lang/Object
    #6 = Utf8               org/sireum/ZLike
    #7 = Class              #6            // org/sireum/ZLike
    #8 = Utf8               org/sireum/$internal/HasBoxer
    #9 = Class              #8            // org/sireum/$internal/HasBoxer
   #10 = Utf8               Z.scala
   #11 = Utf8               java/lang/invoke/MethodHandles$Lookup
   #12 = Class              #11           // java/lang/invoke/MethodHandles$Lookup
   #13 = Utf8               java/lang/invoke/MethodHandles
   #14 = Class              #13           // java/lang/invoke/MethodHandles
   #15 = Utf8               Lookup
   #16 = Utf8               org/sireum/Z$BV$
   #17 = Class              #16           // org/sireum/Z$BV$
   #18 = Utf8               org/sireum/Z
   #19 = Class              #18           // org/sireum/Z
   #20 = Utf8               BV$
   #21 = Utf8               Short
   #22 = Utf8               org/sireum/Z$MP$
   #23 = Class              #22           // org/sireum/Z$MP$
   #24 = Utf8               MP$
   #25 = Utf8               org/sireum/Z$MP$BigInt
   #26 = Class              #25           // org/sireum/Z$MP$BigInt
   #27 = Utf8               BigInt
   #28 = Utf8               org/sireum/Z$MP$Long
   #29 = Class              #28           // org/sireum/Z$MP$Long
   #30 = Utf8               Long
   #31 = Utf8               org/sireum/Z$U$
   #32 = Class              #31           // org/sireum/Z$U$
   #33 = Utf8               U$
   #34 = Utf8               org/sireum/Z$U$_16$
   #35 = Class              #34           // org/sireum/Z$U$_16$
   #36 = Utf8               _16$
   #37 = Utf8               isBitVector$
   #38 = Utf8               (Lorg/sireum/Z$BV$Short;)Z
   #39 = Utf8               $this
   #40 = Utf8               isBitVector
   #41 = Utf8               ()Z
   #42 = NameAndType        #40:#41       // isBitVector:()Z
   #43 = InterfaceMethodref #2.#42        // org/sireum/Z$BV$Short.isBitVector:()Z
   #44 = Utf8               Lorg/sireum/Z$BV$Short;
   #45 = Utf8               this
   #46 = Utf8               hasMin$
   #47 = Utf8               hasMin
   #48 = NameAndType        #47:#41       // hasMin:()Z
   #49 = InterfaceMethodref #2.#48        // org/sireum/Z$BV$Short.hasMin:()Z
   #50 = Utf8               hasMax$
   #51 = Utf8               hasMax
   #52 = NameAndType        #51:#41       // hasMax:()Z
   #53 = InterfaceMethodref #2.#52        // org/sireum/Z$BV$Short.hasMax:()Z
   #54 = Utf8               value
   #55 = Utf8               ()S
   #56 = Utf8               make
   #57 = Utf8               (S)Lorg/sireum/Z$BV$Short;
   #58 = Utf8               (S)TT;
   #59 = Utf8               Min
   #60 = Utf8               ()Lorg/sireum/Z$BV$Short;
   #61 = Utf8               ()TT;
   #62 = Utf8               Max
   #63 = Utf8               Index
   #64 = Utf8               isZeroIndex
   #65 = Utf8               isWrapped
   #66 = Utf8               org$sireum$Z$BV$Short$$toShort$
   #67 = Utf8               (Lorg/sireum/Z$BV$Short;)S
   #68 = Utf8               org$sireum$Z$BV$Short$$toShort
   #69 = NameAndType        #68:#55       // org$sireum$Z$BV$Short$$toShort:()S
   #70 = InterfaceMethodref #2.#69        // org/sireum/Z$BV$Short.org$sireum$Z$BV$Short$$toShort:()S
   #71 = NameAndType        #54:#55       // value:()S
   #72 = InterfaceMethodref #2.#71        // org/sireum/Z$BV$Short.value:()S
   #73 = Utf8               toU16
   #74 = Utf8               MODULE$
   #75 = Utf8               Lorg/sireum/Z$U$_16$;
   #76 = NameAndType        #74:#75       // MODULE$:Lorg/sireum/Z$U$_16$;
   #77 = Fieldref           #35.#76       // org/sireum/Z$U$_16$.MODULE$:Lorg/sireum/Z$U$_16$;
   #78 = Utf8               apply
   #79 = Utf8               (S)S
   #80 = NameAndType        #78:#79       // apply:(S)S
   #81 = Methodref          #35.#80       // org/sireum/Z$U$_16$.apply:(S)S
   #82 = Utf8               (Lorg/sireum/Z;)Lorg/sireum/Z$BV$Short;
   #83 = Utf8               (Lorg/sireum/Z;)TT;
   #84 = Utf8               scala/Predef$
   #85 = Class              #84           // scala/Predef$
   #86 = Utf8               Lscala/Predef$;
   #87 = NameAndType        #74:#86       // MODULE$:Lscala/Predef$;
   #88 = Fieldref           #85.#87       // scala/Predef$.MODULE$:Lscala/Predef$;
   #89 = Utf8               org/sireum/B$
   #90 = Class              #89           // org/sireum/B$
   #91 = Utf8               Lorg/sireum/B$;
   #92 = NameAndType        #74:#91       // MODULE$:Lorg/sireum/B$;
   #93 = Fieldref           #90.#92       // org/sireum/B$.MODULE$:Lorg/sireum/B$;
   #94 = NameAndType        #59:#60       // Min:()Lorg/sireum/Z$BV$Short;
   #95 = InterfaceMethodref #2.#94        // org/sireum/Z$BV$Short.Min:()Lorg/sireum/Z$BV$Short;
   #96 = Utf8               toMP
   #97 = Utf8               ()Lorg/sireum/Z;
   #98 = NameAndType        #96:#97       // toMP:()Lorg/sireum/Z;
   #99 = InterfaceMethodref #2.#98        // org/sireum/Z$BV$Short.toMP:()Lorg/sireum/Z;
  #100 = Utf8               $less$eq
  #101 = Utf8               (Lorg/sireum/Z;)Z
  #102 = NameAndType        #100:#101     // $less$eq:(Lorg/sireum/Z;)Z
  #103 = InterfaceMethodref #19.#102      // org/sireum/Z.$less$eq:(Lorg/sireum/Z;)Z
  #104 = Utf8               $4B
  #105 = Utf8               (Z)Z
  #106 = NameAndType        #104:#105     // $4B:(Z)Z
  #107 = Methodref          #90.#106      // org/sireum/B$.$4B:(Z)Z
  #108 = Utf8               ()Ljava/lang/Object;
  #109 = MethodType         #108          //  ()Ljava/lang/Object;
  #110 = Utf8               $anonfun$make$3
  #111 = Utf8               (Lorg/sireum/Z$BV$Short;Lorg/sireum/Z;)Ljava/lang/String;
  #112 = NameAndType        #110:#111     // $anonfun$make$3:(Lorg/sireum/Z$BV$Short;Lorg/sireum/Z;)Ljava/lang/String;
  #113 = InterfaceMethodref #2.#112       // org/sireum/Z$BV$Short.$anonfun$make$3:(Lorg/sireum/Z$BV$Short;Lorg/sireum/Z;)Ljava/lang/String;
  #114 = MethodHandle       6:#113        // REF_invokeStatic org/sireum/Z$BV$Short.$anonfun$make$3:(Lorg/sireum/Z$BV$Short;Lorg/sireum/Z;)Ljava/lang/String;
  #115 = Utf8               ()Ljava/lang/String;
  #116 = MethodType         #115          //  ()Ljava/lang/String;
  #117 = Integer            5
  #118 = Integer            1
  #119 = Utf8               java/lang/invoke/LambdaMetafactory
  #120 = Class              #119          // java/lang/invoke/LambdaMetafactory
  #121 = Utf8               altMetafactory
  #122 = Utf8               (Ljava/lang/invoke/MethodHandles$Lookup;Ljava/lang/String;Ljava/lang/invoke/MethodType;[Ljava/lang/Object;)Ljava/lang/invoke/CallSite;
  #123 = NameAndType        #121:#122     // altMetafactory:(Ljava/lang/invoke/MethodHandles$Lookup;Ljava/lang/String;Ljava/lang/invoke/MethodType;[Ljava/lang/Object;)Ljava/lang/invoke/CallSite;
  #124 = Methodref          #120.#123     // java/lang/invoke/LambdaMetafactory.altMetafactory:(Ljava/lang/invoke/MethodHandles$Lookup;Ljava/lang/String;Ljava/lang/invoke/MethodType;[Ljava/lang/Object;)Ljava/lang/invoke/CallSite;
  #125 = MethodHandle       6:#124        // REF_invokeStatic java/lang/invoke/LambdaMetafactory.altMetafactory:(Ljava/lang/invoke/MethodHandles$Lookup;Ljava/lang/String;Ljava/lang/invoke/MethodType;[Ljava/lang/Object;)Ljava/lang/invoke/CallSite;
  #126 = Utf8               (Lorg/sireum/Z$BV$Short;Lorg/sireum/Z;)Lscala/Function0;
  #127 = NameAndType        #78:#126      // apply:(Lorg/sireum/Z$BV$Short;Lorg/sireum/Z;)Lscala/Function0;
  #128 = InvokeDynamic      #0:#127       // #0:apply:(Lorg/sireum/Z$BV$Short;Lorg/sireum/Z;)Lscala/Function0;
  #129 = Utf8               assert
  #130 = Utf8               (ZLscala/Function0;)V
  #131 = NameAndType        #129:#130     // assert:(ZLscala/Function0;)V
  #132 = Methodref          #85.#131      // scala/Predef$.assert:(ZLscala/Function0;)V
  #133 = NameAndType        #62:#60       // Max:()Lorg/sireum/Z$BV$Short;
  #134 = InterfaceMethodref #2.#133       // org/sireum/Z$BV$Short.Max:()Lorg/sireum/Z$BV$Short;
  #135 = Utf8               $anonfun$make$4
  #136 = NameAndType        #135:#111     // $anonfun$make$4:(Lorg/sireum/Z$BV$Short;Lorg/sireum/Z;)Ljava/lang/String;
  #137 = InterfaceMethodref #2.#136       // org/sireum/Z$BV$Short.$anonfun$make$4:(Lorg/sireum/Z$BV$Short;Lorg/sireum/Z;)Ljava/lang/String;
  #138 = MethodHandle       6:#137        // REF_invokeStatic org/sireum/Z$BV$Short.$anonfun$make$4:(Lorg/sireum/Z$BV$Short;Lorg/sireum/Z;)Ljava/lang/String;
  #139 = InvokeDynamic      #1:#127       // #1:apply:(Lorg/sireum/Z$BV$Short;Lorg/sireum/Z;)Lscala/Function0;
  #140 = Utf8               ()J
  #141 = NameAndType        #54:#140      // value:()J
  #142 = Methodref          #29.#141      // org/sireum/Z$MP$Long.value:()J
  #143 = Utf8               ()Lscala/math/BigInt;
  #144 = NameAndType        #54:#143      // value:()Lscala/math/BigInt;
  #145 = Methodref          #26.#144      // org/sireum/Z$MP$BigInt.value:()Lscala/math/BigInt;
  #146 = Utf8               scala/math/BigInt
  #147 = Class              #146          // scala/math/BigInt
  #148 = Utf8               toShort
  #149 = NameAndType        #148:#55      // toShort:()S
  #150 = Methodref          #147.#149     // scala/math/BigInt.toShort:()S
  #151 = Utf8               scala/MatchError
  #152 = Class              #151          // scala/MatchError
  #153 = Utf8               <init>
  #154 = Utf8               (Ljava/lang/Object;)V
  #155 = NameAndType        #153:#154     // "<init>":(Ljava/lang/Object;)V
  #156 = Methodref          #152.#155     // scala/MatchError."<init>":(Ljava/lang/Object;)V
  #157 = NameAndType        #56:#57       // make:(S)Lorg/sireum/Z$BV$Short;
  #158 = InterfaceMethodref #2.#157       // org/sireum/Z$BV$Short.make:(S)Lorg/sireum/Z$BV$Short;
  #159 = Utf8               n
  #160 = Utf8               J
  #161 = Utf8               Lscala/math/BigInt;
  #162 = Utf8               Lorg/sireum/Z;
  #163 = Utf8               umake
  #164 = Utf8               S
  #165 = Utf8               makeShort
  #166 = Utf8               (I)Lorg/sireum/Z$BV$Short;
  #167 = Utf8               (I)TT;
  #168 = Utf8               isSigned
  #169 = NameAndType        #168:#41      // isSigned:()Z
  #170 = InterfaceMethodref #2.#169       // org/sireum/Z$BV$Short.isSigned:()Z
  #171 = Utf8               (I)S
  #172 = NameAndType        #78:#171      // apply:(I)S
  #173 = Methodref          #35.#172      // org/sireum/Z$U$_16$.apply:(I)S
  #174 = Utf8               I
  #175 = Utf8               unary_$minus$
  #176 = Utf8               (Lorg/sireum/Z$BV$Short;)Lorg/sireum/Z$BV$Short;
  #177 = Utf8               unary_$minus
  #178 = NameAndType        #177:#60      // unary_$minus:()Lorg/sireum/Z$BV$Short;
  #179 = InterfaceMethodref #2.#178       // org/sireum/Z$BV$Short.unary_$minus:()Lorg/sireum/Z$BV$Short;
  #180 = NameAndType        #65:#41       // isWrapped:()Z
  #181 = InterfaceMethodref #2.#180       // org/sireum/Z$BV$Short.isWrapped:()Z
  #182 = NameAndType        #177:#97      // unary_$minus:()Lorg/sireum/Z;
  #183 = InterfaceMethodref #19.#182      // org/sireum/Z.unary_$minus:()Lorg/sireum/Z;
  #184 = NameAndType        #56:#82       // make:(Lorg/sireum/Z;)Lorg/sireum/Z$BV$Short;
  #185 = InterfaceMethodref #2.#184       // org/sireum/Z$BV$Short.make:(Lorg/sireum/Z;)Lorg/sireum/Z$BV$Short;
  #186 = NameAndType        #165:#166     // makeShort:(I)Lorg/sireum/Z$BV$Short;
  #187 = InterfaceMethodref #2.#186       // org/sireum/Z$BV$Short.makeShort:(I)Lorg/sireum/Z$BV$Short;
  #188 = NameAndType        #73:#55       // toU16:()S
  #189 = InterfaceMethodref #2.#188       // org/sireum/Z$BV$Short.toU16:()S
  #190 = Utf8               unary_$minus$extension
  #191 = NameAndType        #190:#79      // unary_$minus$extension:(S)S
  #192 = Methodref          #35.#191      // org/sireum/Z$U$_16$.unary_$minus$extension:(S)S
  #193 = NameAndType        #163:#57      // umake:(S)Lorg/sireum/Z$BV$Short;
  #194 = InterfaceMethodref #2.#193       // org/sireum/Z$BV$Short.umake:(S)Lorg/sireum/Z$BV$Short;
  #195 = Utf8               $plus$
  #196 = Utf8               (Lorg/sireum/Z$BV$Short;Lorg/sireum/Z$BV$Short;)Lorg/sireum/Z$BV$Short;
  #197 = Utf8               other
  #198 = Utf8               $plus
  #199 = NameAndType        #198:#176     // $plus:(Lorg/sireum/Z$BV$Short;)Lorg/sireum/Z$BV$Short;
  #200 = InterfaceMethodref #2.#199       // org/sireum/Z$BV$Short.$plus:(Lorg/sireum/Z$BV$Short;)Lorg/sireum/Z$BV$Short;
  #201 = Utf8               (TT;)TT;
  #202 = Utf8               (Lorg/sireum/Z;)Lorg/sireum/Z;
  #203 = NameAndType        #198:#202     // $plus:(Lorg/sireum/Z;)Lorg/sireum/Z;
  #204 = InterfaceMethodref #19.#203      // org/sireum/Z.$plus:(Lorg/sireum/Z;)Lorg/sireum/Z;
  #205 = Utf8               $plus$extension
  #206 = Utf8               (SS)S
  #207 = NameAndType        #205:#206     // $plus$extension:(SS)S
  #208 = Methodref          #35.#207      // org/sireum/Z$U$_16$.$plus$extension:(SS)S
  #209 = Utf8               $minus$
  #210 = Utf8               $minus
  #211 = NameAndType        #210:#176     // $minus:(Lorg/sireum/Z$BV$Short;)Lorg/sireum/Z$BV$Short;
  #212 = InterfaceMethodref #2.#211       // org/sireum/Z$BV$Short.$minus:(Lorg/sireum/Z$BV$Short;)Lorg/sireum/Z$BV$Short;
  #213 = NameAndType        #210:#202     // $minus:(Lorg/sireum/Z;)Lorg/sireum/Z;
  #214 = InterfaceMethodref #19.#213      // org/sireum/Z.$minus:(Lorg/sireum/Z;)Lorg/sireum/Z;
  #215 = Utf8               $minus$extension
  #216 = NameAndType        #215:#206     // $minus$extension:(SS)S
  #217 = Methodref          #35.#216      // org/sireum/Z$U$_16$.$minus$extension:(SS)S
  #218 = Utf8               $times$
  #219 = Utf8               $times
  #220 = NameAndType        #219:#176     // $times:(Lorg/sireum/Z$BV$Short;)Lorg/sireum/Z$BV$Short;
  #221 = InterfaceMethodref #2.#220       // org/sireum/Z$BV$Short.$times:(Lorg/sireum/Z$BV$Short;)Lorg/sireum/Z$BV$Short;
  #222 = NameAndType        #219:#202     // $times:(Lorg/sireum/Z;)Lorg/sireum/Z;
  #223 = InterfaceMethodref #19.#222      // org/sireum/Z.$times:(Lorg/sireum/Z;)Lorg/sireum/Z;
  #224 = Utf8               $times$extension
  #225 = NameAndType        #224:#206     // $times$extension:(SS)S
  #226 = Methodref          #35.#225      // org/sireum/Z$U$_16$.$times$extension:(SS)S
  #227 = Utf8               $div$
  #228 = Utf8               $div
  #229 = NameAndType        #228:#176     // $div:(Lorg/sireum/Z$BV$Short;)Lorg/sireum/Z$BV$Short;
  #230 = InterfaceMethodref #2.#229       // org/sireum/Z$BV$Short.$div:(Lorg/sireum/Z$BV$Short;)Lorg/sireum/Z$BV$Short;
  #231 = NameAndType        #228:#202     // $div:(Lorg/sireum/Z;)Lorg/sireum/Z;
  #232 = InterfaceMethodref #19.#231      // org/sireum/Z.$div:(Lorg/sireum/Z;)Lorg/sireum/Z;
  #233 = Utf8               $div$extension
  #234 = NameAndType        #233:#206     // $div$extension:(SS)S
  #235 = Methodref          #35.#234      // org/sireum/Z$U$_16$.$div$extension:(SS)S
  #236 = Utf8               $percent$
  #237 = Utf8               $percent
  #238 = NameAndType        #237:#176     // $percent:(Lorg/sireum/Z$BV$Short;)Lorg/sireum/Z$BV$Short;
  #239 = InterfaceMethodref #2.#238       // org/sireum/Z$BV$Short.$percent:(Lorg/sireum/Z$BV$Short;)Lorg/sireum/Z$BV$Short;
  #240 = NameAndType        #237:#202     // $percent:(Lorg/sireum/Z;)Lorg/sireum/Z;
  #241 = InterfaceMethodref #19.#240      // org/sireum/Z.$percent:(Lorg/sireum/Z;)Lorg/sireum/Z;
  #242 = Utf8               $percent$extension
  #243 = NameAndType        #242:#206     // $percent$extension:(SS)S
  #244 = Methodref          #35.#243      // org/sireum/Z$U$_16$.$percent$extension:(SS)S
  #245 = Utf8               $greater$
  #246 = Utf8               (Lorg/sireum/Z$BV$Short;Lorg/sireum/Z$BV$Short;)Z
  #247 = Utf8               $greater
  #248 = NameAndType        #247:#38      // $greater:(Lorg/sireum/Z$BV$Short;)Z
  #249 = InterfaceMethodref #2.#248       // org/sireum/Z$BV$Short.$greater:(Lorg/sireum/Z$BV$Short;)Z
  #250 = Utf8               (TT;)Z
  #251 = NameAndType        #78:#105      // apply:(Z)Z
  #252 = Methodref          #90.#251      // org/sireum/B$.apply:(Z)Z
  #253 = Utf8               $greater$extension
  #254 = Utf8               (SS)Z
  #255 = NameAndType        #253:#254     // $greater$extension:(SS)Z
  #256 = Methodref          #35.#255      // org/sireum/Z$U$_16$.$greater$extension:(SS)Z
  #257 = Utf8               $greater$eq$
  #258 = Utf8               $greater$eq
  #259 = NameAndType        #258:#38      // $greater$eq:(Lorg/sireum/Z$BV$Short;)Z
  #260 = InterfaceMethodref #2.#259       // org/sireum/Z$BV$Short.$greater$eq:(Lorg/sireum/Z$BV$Short;)Z
  #261 = Utf8               $greater$eq$extension
  #262 = NameAndType        #261:#254     // $greater$eq$extension:(SS)Z
  #263 = Methodref          #35.#262      // org/sireum/Z$U$_16$.$greater$eq$extension:(SS)Z
  #264 = Utf8               $less$
  #265 = Utf8               $less
  #266 = NameAndType        #265:#38      // $less:(Lorg/sireum/Z$BV$Short;)Z
  #267 = InterfaceMethodref #2.#266       // org/sireum/Z$BV$Short.$less:(Lorg/sireum/Z$BV$Short;)Z
  #268 = Utf8               $less$extension
  #269 = NameAndType        #268:#254     // $less$extension:(SS)Z
  #270 = Methodref          #35.#269      // org/sireum/Z$U$_16$.$less$extension:(SS)Z
  #271 = Utf8               $less$eq$
  #272 = NameAndType        #100:#38      // $less$eq:(Lorg/sireum/Z$BV$Short;)Z
  #273 = InterfaceMethodref #2.#272       // org/sireum/Z$BV$Short.$less$eq:(Lorg/sireum/Z$BV$Short;)Z
  #274 = Utf8               $less$eq$extension
  #275 = NameAndType        #274:#254     // $less$eq$extension:(SS)Z
  #276 = Methodref          #35.#275      // org/sireum/Z$U$_16$.$less$eq$extension:(SS)Z
  #277 = Utf8               $greater$greater$
  #278 = Utf8               $greater$greater
  #279 = NameAndType        #278:#176     // $greater$greater:(Lorg/sireum/Z$BV$Short;)Lorg/sireum/Z$BV$Short;
  #280 = InterfaceMethodref #2.#279       // org/sireum/Z$BV$Short.$greater$greater:(Lorg/sireum/Z$BV$Short;)Lorg/sireum/Z$BV$Short;
  #281 = Utf8               $greater$greater$greater
  #282 = NameAndType        #281:#176     // $greater$greater$greater:(Lorg/sireum/Z$BV$Short;)Lorg/sireum/Z$BV$Short;
  #283 = InterfaceMethodref #2.#282       // org/sireum/Z$BV$Short.$greater$greater$greater:(Lorg/sireum/Z$BV$Short;)Lorg/sireum/Z$BV$Short;
  #284 = Utf8               $greater$greater$greater$
  #285 = Utf8               toInt$extension
  #286 = Utf8               (S)I
  #287 = NameAndType        #285:#286     // toInt$extension:(S)I
  #288 = Methodref          #35.#287      // org/sireum/Z$U$_16$.toInt$extension:(S)I
  #289 = Utf8               $greater$greater$greater$extension
  #290 = Utf8               (SI)S
  #291 = NameAndType        #289:#290     // $greater$greater$greater$extension:(SI)S
  #292 = Methodref          #35.#291      // org/sireum/Z$U$_16$.$greater$greater$greater$extension:(SI)S
  #293 = Utf8               $less$less$
  #294 = Utf8               $less$less
  #295 = NameAndType        #294:#176     // $less$less:(Lorg/sireum/Z$BV$Short;)Lorg/sireum/Z$BV$Short;
  #296 = InterfaceMethodref #2.#295       // org/sireum/Z$BV$Short.$less$less:(Lorg/sireum/Z$BV$Short;)Lorg/sireum/Z$BV$Short;
  #297 = Utf8               $less$less$extension
  #298 = NameAndType        #297:#290     // $less$less$extension:(SI)S
  #299 = Methodref          #35.#298      // org/sireum/Z$U$_16$.$less$less$extension:(SI)S
  #300 = Utf8               $amp$
  #301 = Utf8               $amp
  #302 = NameAndType        #301:#176     // $amp:(Lorg/sireum/Z$BV$Short;)Lorg/sireum/Z$BV$Short;
  #303 = InterfaceMethodref #2.#302       // org/sireum/Z$BV$Short.$amp:(Lorg/sireum/Z$BV$Short;)Lorg/sireum/Z$BV$Short;
  #304 = Utf8               $amp$extension
  #305 = NameAndType        #304:#206     // $amp$extension:(SS)S
  #306 = Methodref          #35.#305      // org/sireum/Z$U$_16$.$amp$extension:(SS)S
  #307 = Utf8               $bar$
  #308 = Utf8               $bar
  #309 = NameAndType        #308:#176     // $bar:(Lorg/sireum/Z$BV$Short;)Lorg/sireum/Z$BV$Short;
  #310 = InterfaceMethodref #2.#309       // org/sireum/Z$BV$Short.$bar:(Lorg/sireum/Z$BV$Short;)Lorg/sireum/Z$BV$Short;
  #311 = Utf8               $bar$extension
  #312 = NameAndType        #311:#206     // $bar$extension:(SS)S
  #313 = Methodref          #35.#312      // org/sireum/Z$U$_16$.$bar$extension:(SS)S
  #314 = Utf8               $bar$up$
  #315 = Utf8               $bar$up
  #316 = NameAndType        #315:#176     // $bar$up:(Lorg/sireum/Z$BV$Short;)Lorg/sireum/Z$BV$Short;
  #317 = InterfaceMethodref #2.#316       // org/sireum/Z$BV$Short.$bar$up:(Lorg/sireum/Z$BV$Short;)Lorg/sireum/Z$BV$Short;
  #318 = Utf8               $up$extension
  #319 = NameAndType        #318:#206     // $up$extension:(SS)S
  #320 = Methodref          #35.#319      // org/sireum/Z$U$_16$.$up$extension:(SS)S
  #321 = Utf8               unary_$tilde$
  #322 = Utf8               unary_$tilde
  #323 = NameAndType        #322:#60      // unary_$tilde:()Lorg/sireum/Z$BV$Short;
  #324 = InterfaceMethodref #2.#323       // org/sireum/Z$BV$Short.unary_$tilde:()Lorg/sireum/Z$BV$Short;
  #325 = Utf8               unary_$tilde$extension
  #326 = NameAndType        #325:#79      // unary_$tilde$extension:(S)S
  #327 = Methodref          #35.#326      // org/sireum/Z$U$_16$.unary_$tilde$extension:(S)S
  #328 = Utf8               increase$
  #329 = Utf8               increase
  #330 = NameAndType        #329:#60      // increase:()Lorg/sireum/Z$BV$Short;
  #331 = InterfaceMethodref #2.#330       // org/sireum/Z$BV$Short.increase:()Lorg/sireum/Z$BV$Short;
  #332 = Utf8               decrease$
  #333 = Utf8               decrease
  #334 = NameAndType        #333:#60      // decrease:()Lorg/sireum/Z$BV$Short;
  #335 = InterfaceMethodref #2.#334       // org/sireum/Z$BV$Short.decrease:()Lorg/sireum/Z$BV$Short;
  #336 = Utf8               toString$
  #337 = Utf8               (Lorg/sireum/Z$BV$Short;)Ljava/lang/String;
  #338 = Utf8               toString
  #339 = NameAndType        #338:#115     // toString:()Ljava/lang/String;
  #340 = InterfaceMethodref #2.#339       // org/sireum/Z$BV$Short.toString:()Ljava/lang/String;
  #341 = Utf8               java/lang/Short
  #342 = Class              #341          // java/lang/Short
  #343 = Utf8               (S)Ljava/lang/String;
  #344 = NameAndType        #338:#343     // toString:(S)Ljava/lang/String;
  #345 = Methodref          #342.#344     // java/lang/Short.toString:(S)Ljava/lang/String;
  #346 = Utf8               toString$extension
  #347 = NameAndType        #346:#343     // toString$extension:(S)Ljava/lang/String;
  #348 = Methodref          #35.#347      // org/sireum/Z$U$_16$.toString$extension:(S)Ljava/lang/String;
  #349 = Utf8               java/lang/String
  #350 = Class              #349          // java/lang/String
  #351 = Utf8               toBigInt$
  #352 = Utf8               (Lorg/sireum/Z$BV$Short;)Lscala/math/BigInt;
  #353 = Utf8               toBigInt
  #354 = NameAndType        #353:#143     // toBigInt:()Lscala/math/BigInt;
  #355 = InterfaceMethodref #2.#354       // org/sireum/Z$BV$Short.toBigInt:()Lscala/math/BigInt;
  #356 = Utf8               scala/package$
  #357 = Class              #356          // scala/package$
  #358 = Utf8               Lscala/package$;
  #359 = NameAndType        #74:#358      // MODULE$:Lscala/package$;
  #360 = Fieldref           #357.#359     // scala/package$.MODULE$:Lscala/package$;
  #361 = Utf8               ()Lscala/math/BigInt$;
  #362 = NameAndType        #27:#361      // BigInt:()Lscala/math/BigInt$;
  #363 = Methodref          #357.#362     // scala/package$.BigInt:()Lscala/math/BigInt$;
  #364 = Utf8               scala/math/BigInt$
  #365 = Class              #364          // scala/math/BigInt$
  #366 = Utf8               (I)Lscala/math/BigInt;
  #367 = NameAndType        #78:#366      // apply:(I)Lscala/math/BigInt;
  #368 = Methodref          #365.#367     // scala/math/BigInt$.apply:(I)Lscala/math/BigInt;
  #369 = Utf8               org/sireum/Z$
  #370 = Class              #369          // org/sireum/Z$
  #371 = Utf8               Lorg/sireum/Z$;
  #372 = NameAndType        #74:#371      // MODULE$:Lorg/sireum/Z$;
  #373 = Fieldref           #370.#372     // org/sireum/Z$.MODULE$:Lorg/sireum/Z$;
  #374 = Utf8               (I)Lorg/sireum/Z;
  #375 = NameAndType        #78:#374      // apply:(I)Lorg/sireum/Z;
  #376 = Methodref          #370.#375     // org/sireum/Z$.apply:(I)Lorg/sireum/Z;
  #377 = InterfaceMethodref #19.#354      // org/sireum/Z.toBigInt:()Lscala/math/BigInt;
  #378 = Utf8               toMP$
  #379 = Utf8               (Lorg/sireum/Z$BV$Short;)Lorg/sireum/Z;
  #380 = Utf8               Lorg/sireum/Z$MP$;
  #381 = NameAndType        #74:#380      // MODULE$:Lorg/sireum/Z$MP$;
  #382 = Fieldref           #23.#381      // org/sireum/Z$MP$.MODULE$:Lorg/sireum/Z$MP$;
  #383 = Methodref          #23.#375      // org/sireum/Z$MP$.apply:(I)Lorg/sireum/Z;
  #384 = Utf8               toIndex$
  #385 = Utf8               toIndex
  #386 = NameAndType        #385:#97      // toIndex:()Lorg/sireum/Z;
  #387 = InterfaceMethodref #2.#386       // org/sireum/Z$BV$Short.toIndex:()Lorg/sireum/Z;
  #388 = NameAndType        #64:#41       // isZeroIndex:()Z
  #389 = InterfaceMethodref #2.#388       // org/sireum/Z$BV$Short.isZeroIndex:()Z
  #390 = NameAndType        #63:#60       // Index:()Lorg/sireum/Z$BV$Short;
  #391 = InterfaceMethodref #2.#390       // org/sireum/Z$BV$Short.Index:()Lorg/sireum/Z$BV$Short;
  #392 = Utf8               value$2
  #393 = Utf8               java/lang/StringBuilder
  #394 = Class              #393          // java/lang/StringBuilder
  #395 = Integer            32
  #396 = Utf8               (I)V
  #397 = NameAndType        #153:#396     // "<init>":(I)V
  #398 = Methodref          #394.#397     // java/lang/StringBuilder."<init>":(I)V
  #399 = Utf8               append
  #400 = Utf8               (Ljava/lang/Object;)Ljava/lang/StringBuilder;
  #401 = NameAndType        #399:#400     // append:(Ljava/lang/Object;)Ljava/lang/StringBuilder;
  #402 = Methodref          #394.#401     // java/lang/StringBuilder.append:(Ljava/lang/Object;)Ljava/lang/StringBuilder;
  #403 = Utf8                should not be less than
  #404 = String             #403          //  should not be less than
  #405 = Utf8               (Ljava/lang/String;)Ljava/lang/StringBuilder;
  #406 = NameAndType        #399:#405     // append:(Ljava/lang/String;)Ljava/lang/StringBuilder;
  #407 = Methodref          #394.#406     // java/lang/StringBuilder.append:(Ljava/lang/String;)Ljava/lang/StringBuilder;
  #408 = Utf8               Name
  #409 = NameAndType        #408:#115     // Name:()Ljava/lang/String;
  #410 = InterfaceMethodref #2.#409       // org/sireum/Z$BV$Short.Name:()Ljava/lang/String;
  #411 = Utf8               .Min (
  #412 = String             #411          // .Min (
  #413 = Utf8               )
  #414 = String             #413          // )
  #415 = Methodref          #394.#339     // java/lang/StringBuilder.toString:()Ljava/lang/String;
  #416 = Integer            35
  #417 = Utf8                should not be greater than
  #418 = String             #417          //  should not be greater than
  #419 = Utf8               .Max (
  #420 = String             #419          // .Max (
  #421 = Utf8               $init$
  #422 = Utf8               (Lorg/sireum/Z$BV$Short;)V
  #423 = Utf8               $deserializeLambda$
  #424 = Utf8               (Ljava/lang/invoke/SerializedLambda;)Ljava/lang/Object;
  #425 = Utf8               scala/runtime/LambdaDeserialize
  #426 = Class              #425          // scala/runtime/LambdaDeserialize
  #427 = Utf8               bootstrap
  #428 = Utf8               (Ljava/lang/invoke/MethodHandles$Lookup;Ljava/lang/String;Ljava/lang/invoke/MethodType;[Ljava/lang/invoke/MethodHandle;)Ljava/lang/invoke/CallSite;
  #429 = NameAndType        #427:#428     // bootstrap:(Ljava/lang/invoke/MethodHandles$Lookup;Ljava/lang/String;Ljava/lang/invoke/MethodType;[Ljava/lang/invoke/MethodHandle;)Ljava/lang/invoke/CallSite;
  #430 = Methodref          #426.#429     // scala/runtime/LambdaDeserialize.bootstrap:(Ljava/lang/invoke/MethodHandles$Lookup;Ljava/lang/String;Ljava/lang/invoke/MethodType;[Ljava/lang/invoke/MethodHandle;)Ljava/lang/invoke/CallSite;
  #431 = MethodHandle       6:#430        // REF_invokeStatic scala/runtime/LambdaDeserialize.bootstrap:(Ljava/lang/invoke/MethodHandles$Lookup;Ljava/lang/String;Ljava/lang/invoke/MethodType;[Ljava/lang/invoke/MethodHandle;)Ljava/lang/invoke/CallSite;
  #432 = Utf8               lambdaDeserialize
  #433 = NameAndType        #432:#424     // lambdaDeserialize:(Ljava/lang/invoke/SerializedLambda;)Ljava/lang/Object;
  #434 = InvokeDynamic      #2:#433       // #2:lambdaDeserialize:(Ljava/lang/invoke/SerializedLambda;)Ljava/lang/Object;
  #435 = Utf8               Code
  #436 = Utf8               LineNumberTable
  #437 = Utf8               LocalVariableTable
  #438 = Utf8               MethodParameters
  #439 = Utf8               Signature
  #440 = Utf8               StackMapTable
  #441 = Utf8               InnerClasses
  #442 = Utf8               SourceFile
  #443 = Utf8               BootstrapMethods
  #444 = Utf8               ScalaInlineInfo
  #445 = Utf8               Scala
{
  public static boolean isBitVector$(org.sireum.Z$BV$Short);
    descriptor: (Lorg/sireum/Z$BV$Short;)Z
    flags: (0x1009) ACC_PUBLIC, ACC_STATIC, ACC_SYNTHETIC
    Code:
      stack=1, locals=1, args_size=1
         0: aload_0
         1: invokespecial #43                 // InterfaceMethod isBitVector:()Z
         4: ireturn
      LineNumberTable:
        line 611: 0
      LocalVariableTable:
        Start  Length  Slot  Name   Signature
            0       5     0 $this   Lorg/sireum/Z$BV$Short;
    MethodParameters:
      Name                           Flags
      $this                          final synthetic

  public default boolean isBitVector();
    descriptor: ()Z
    flags: (0x0001) ACC_PUBLIC
    Code:
      stack=1, locals=1, args_size=1
         0: iconst_1
         1: ireturn
      LineNumberTable:
        line 611: 0
      LocalVariableTable:
        Start  Length  Slot  Name   Signature
            0       2     0  this   Lorg/sireum/Z$BV$Short;

  public static boolean hasMin$(org.sireum.Z$BV$Short);
    descriptor: (Lorg/sireum/Z$BV$Short;)Z
    flags: (0x1009) ACC_PUBLIC, ACC_STATIC, ACC_SYNTHETIC
    Code:
      stack=1, locals=1, args_size=1
         0: aload_0
         1: invokespecial #49                 // InterfaceMethod hasMin:()Z
         4: ireturn
      LineNumberTable:
        line 613: 0
      LocalVariableTable:
        Start  Length  Slot  Name   Signature
            0       5     0 $this   Lorg/sireum/Z$BV$Short;
    MethodParameters:
      Name                           Flags
      $this                          final synthetic

  public default boolean hasMin();
    descriptor: ()Z
    flags: (0x0001) ACC_PUBLIC
    Code:
      stack=1, locals=1, args_size=1
         0: iconst_1
         1: ireturn
      LineNumberTable:
        line 613: 0
      LocalVariableTable:
        Start  Length  Slot  Name   Signature
            0       2     0  this   Lorg/sireum/Z$BV$Short;

  public static boolean hasMax$(org.sireum.Z$BV$Short);
    descriptor: (Lorg/sireum/Z$BV$Short;)Z
    flags: (0x1009) ACC_PUBLIC, ACC_STATIC, ACC_SYNTHETIC
    Code:
      stack=1, locals=1, args_size=1
         0: aload_0
         1: invokespecial #53                 // InterfaceMethod hasMax:()Z
         4: ireturn
      LineNumberTable:
        line 615: 0
      LocalVariableTable:
        Start  Length  Slot  Name   Signature
            0       5     0 $this   Lorg/sireum/Z$BV$Short;
    MethodParameters:
      Name                           Flags
      $this                          final synthetic

  public default boolean hasMax();
    descriptor: ()Z
    flags: (0x0001) ACC_PUBLIC
    Code:
      stack=1, locals=1, args_size=1
         0: iconst_1
         1: ireturn
      LineNumberTable:
        line 615: 0
      LocalVariableTable:
        Start  Length  Slot  Name   Signature
            0       2     0  this   Lorg/sireum/Z$BV$Short;

  public abstract short value();
    descriptor: ()S
    flags: (0x0401) ACC_PUBLIC, ACC_ABSTRACT

  public abstract T make(short);
    descriptor: (S)Lorg/sireum/Z$BV$Short;
    flags: (0x0401) ACC_PUBLIC, ACC_ABSTRACT
    Signature: #58                          // (S)TT;
    MethodParameters:
      Name                           Flags
      value                          final

  public abstract T Min();
    descriptor: ()Lorg/sireum/Z$BV$Short;
    flags: (0x0401) ACC_PUBLIC, ACC_ABSTRACT
    Signature: #61                          // ()TT;

  public abstract T Max();
    descriptor: ()Lorg/sireum/Z$BV$Short;
    flags: (0x0401) ACC_PUBLIC, ACC_ABSTRACT
    Signature: #61                          // ()TT;

  public abstract T Index();
    descriptor: ()Lorg/sireum/Z$BV$Short;
    flags: (0x0401) ACC_PUBLIC, ACC_ABSTRACT
    Signature: #61                          // ()TT;

  public abstract boolean isZeroIndex();
    descriptor: ()Z
    flags: (0x0401) ACC_PUBLIC, ACC_ABSTRACT

  public abstract boolean isWrapped();
    descriptor: ()Z
    flags: (0x0401) ACC_PUBLIC, ACC_ABSTRACT

  public static short org$sireum$Z$BV$Short$$toShort$(org.sireum.Z$BV$Short);
    descriptor: (Lorg/sireum/Z$BV$Short;)S
    flags: (0x1009) ACC_PUBLIC, ACC_STATIC, ACC_SYNTHETIC
    Code:
      stack=1, locals=1, args_size=1
         0: aload_0
         1: invokespecial #70                 // InterfaceMethod org$sireum$Z$BV$Short$$toShort:()S
         4: ireturn
      LineNumberTable:
        line 631: 0
      LocalVariableTable:
        Start  Length  Slot  Name   Signature
            0       5     0 $this   Lorg/sireum/Z$BV$Short;
    MethodParameters:
      Name                           Flags
      $this                          final synthetic

  public default short org$sireum$Z$BV$Short$$toShort();
    descriptor: ()S
    flags: (0x0001) ACC_PUBLIC
    Code:
      stack=1, locals=1, args_size=1
         0: aload_0
         1: invokeinterface #72,  1           // InterfaceMethod value:()S
         6: ireturn
      LineNumberTable:
        line 631: 0
      LocalVariableTable:
        Start  Length  Slot  Name   Signature
            0       7     0  this   Lorg/sireum/Z$BV$Short;

  private short toU16();
    descriptor: ()S
    flags: (0x0002) ACC_PRIVATE
    Code:
      stack=2, locals=1, args_size=1
         0: getstatic     #77                 // Field org/sireum/Z$U$_16$.MODULE$:Lorg/sireum/Z$U$_16$;
         3: aload_0
         4: invokeinterface #70,  1           // InterfaceMethod org$sireum$Z$BV$Short$$toShort:()S
         9: invokevirtual #81                 // Method org/sireum/Z$U$_16$.apply:(S)S
        12: ireturn
      LineNumberTable:
        line 633: 0
      LocalVariableTable:
        Start  Length  Slot  Name   Signature
            0      13     0  this   Lorg/sireum/Z$BV$Short;

  private T make(org.sireum.Z);
    descriptor: (Lorg/sireum/Z;)Lorg/sireum/Z$BV$Short;
    flags: (0x0002) ACC_PRIVATE
    Code:
      stack=4, locals=9, args_size=2
         0: getstatic     #88                 // Field scala/Predef$.MODULE$:Lscala/Predef$;
         3: getstatic     #93                 // Field org/sireum/B$.MODULE$:Lorg/sireum/B$;
         6: aload_0
         7: invokeinterface #95,  1           // InterfaceMethod Min:()Lorg/sireum/Z$BV$Short;
        12: invokeinterface #99,  1           // InterfaceMethod toMP:()Lorg/sireum/Z;
        17: aload_1
        18: invokeinterface #103,  2          // InterfaceMethod org/sireum/Z.$less$eq:(Lorg/sireum/Z;)Z
        23: invokevirtual #107                // Method org/sireum/B$.$4B:(Z)Z
        26: aload_0
        27: aload_1
        28: invokedynamic #128,  0            // InvokeDynamic #0:apply:(Lorg/sireum/Z$BV$Short;Lorg/sireum/Z;)Lscala/Function0;
        33: invokevirtual #132                // Method scala/Predef$.assert:(ZLscala/Function0;)V
        36: getstatic     #88                 // Field scala/Predef$.MODULE$:Lscala/Predef$;
        39: getstatic     #93                 // Field org/sireum/B$.MODULE$:Lorg/sireum/B$;
        42: aload_1
        43: aload_0
        44: invokeinterface #134,  1          // InterfaceMethod Max:()Lorg/sireum/Z$BV$Short;
        49: invokeinterface #99,  1           // InterfaceMethod toMP:()Lorg/sireum/Z;
        54: invokeinterface #103,  2          // InterfaceMethod org/sireum/Z.$less$eq:(Lorg/sireum/Z;)Z
        59: invokevirtual #107                // Method org/sireum/B$.$4B:(Z)Z
        62: aload_0
        63: aload_1
        64: invokedynamic #139,  0            // InvokeDynamic #1:apply:(Lorg/sireum/Z$BV$Short;Lorg/sireum/Z;)Lscala/Function0;
        69: invokevirtual #132                // Method scala/Predef$.assert:(ZLscala/Function0;)V
        72: aload_0
        73: aload_1
        74: astore_3
        75: aload_3
        76: instanceof    #29                 // class org/sireum/Z$MP$Long
        79: ifeq          103
        82: aload_3
        83: checkcast     #29                 // class org/sireum/Z$MP$Long
        86: astore        4
        88: aload         4
        90: invokevirtual #142                // Method org/sireum/Z$MP$Long.value:()J
        93: lstore        5
        95: lload         5
        97: l2i
        98: i2s
        99: istore_2
       100: goto          147
       103: goto          106
       106: aload_3
       107: instanceof    #26                 // class org/sireum/Z$MP$BigInt
       110: ifeq          135
       113: aload_3
       114: checkcast     #26                 // class org/sireum/Z$MP$BigInt
       117: astore        7
       119: aload         7
       121: invokevirtual #145                // Method org/sireum/Z$MP$BigInt.value:()Lscala/math/BigInt;
       124: astore        8
       126: aload         8
       128: invokevirtual #150                // Method scala/math/BigInt.toShort:()S
       131: istore_2
       132: goto          147
       135: goto          138
       138: new           #152                // class scala/MatchError
       141: dup
       142: aload_3
       143: invokespecial #156                // Method scala/MatchError."<init>":(Ljava/lang/Object;)V
       146: athrow
       147: iload_2
       148: invokeinterface #158,  2          // InterfaceMethod make:(S)Lorg/sireum/Z$BV$Short;
       153: areturn
      StackMapTable: number_of_entries = 5
        frame_type = 255 /* full_frame */
          offset_delta = 103
          locals = [ class org/sireum/Z$BV$Short, class org/sireum/Z, top, class org/sireum/Z ]
          stack = [ class org/sireum/Z$BV$Short ]
        frame_type = 66 /* same_locals_1_stack_item */
          stack = [ class org/sireum/Z$BV$Short ]
        frame_type = 92 /* same_locals_1_stack_item */
          stack = [ class org/sireum/Z$BV$Short ]
        frame_type = 66 /* same_locals_1_stack_item */
          stack = [ class org/sireum/Z$BV$Short ]
        frame_type = 255 /* full_frame */
          offset_delta = 8
          locals = [ class org/sireum/Z$BV$Short, class org/sireum/Z, int, class org/sireum/Z ]
          stack = [ class org/sireum/Z$BV$Short ]
      LineNumberTable:
        line 636: 0
        line 637: 36
        line 638: 72
        line 639: 75
        line 640: 106
        line 638: 138
      LocalVariableTable:
        Start  Length  Slot  Name   Signature
           95       8     5     n   J
          126       9     8     n   Lscala/math/BigInt;
            0     154     0  this   Lorg/sireum/Z$BV$Short;
            0     154     1 value   Lorg/sireum/Z;
    Signature: #83                          // (Lorg/sireum/Z;)TT;
    MethodParameters:
      Name                           Flags
      value                          final

  private T umake(short);
    descriptor: (S)Lorg/sireum/Z$BV$Short;
    flags: (0x0002) ACC_PRIVATE
    Code:
      stack=2, locals=2, args_size=2
         0: aload_0
         1: iload_1
         2: invokeinterface #158,  2          // InterfaceMethod make:(S)Lorg/sireum/Z$BV$Short;
         7: areturn
      LineNumberTable:
        line 644: 0
      LocalVariableTable:
        Start  Length  Slot  Name   Signature
            0       8     0  this   Lorg/sireum/Z$BV$Short;
            0       8     1 value   S
    Signature: #58                          // (S)TT;
    MethodParameters:
      Name                           Flags
      value                          final

  private T makeShort(int);
    descriptor: (I)Lorg/sireum/Z$BV$Short;
    flags: (0x0002) ACC_PRIVATE
    Code:
      stack=3, locals=2, args_size=2
         0: aload_0
         1: invokeinterface #170,  1          // InterfaceMethod isSigned:()Z
         6: ifeq          20
         9: aload_0
        10: iload_1
        11: i2s
        12: invokeinterface #158,  2          // InterfaceMethod make:(S)Lorg/sireum/Z$BV$Short;
        17: goto          33
        20: aload_0
        21: getstatic     #77                 // Field org/sireum/Z$U$_16$.MODULE$:Lorg/sireum/Z$U$_16$;
        24: iload_1
        25: invokevirtual #173                // Method org/sireum/Z$U$_16$.apply:(I)S
        28: invokeinterface #158,  2          // InterfaceMethod make:(S)Lorg/sireum/Z$BV$Short;
        33: areturn
      StackMapTable: number_of_entries = 2
        frame_type = 20 /* same */
        frame_type = 76 /* same_locals_1_stack_item */
          stack = [ class org/sireum/Z$BV$Short ]
      LineNumberTable:
        line 647: 0
      LocalVariableTable:
        Start  Length  Slot  Name   Signature
            0      34     0  this   Lorg/sireum/Z$BV$Short;
            0      34     1 value   I
    Signature: #167                         // (I)TT;
    MethodParameters:
      Name                           Flags
      value                          final

  public static org.sireum.Z$BV$Short unary_$minus$(org.sireum.Z$BV$Short);
    descriptor: (Lorg/sireum/Z$BV$Short;)Lorg/sireum/Z$BV$Short;
    flags: (0x1009) ACC_PUBLIC, ACC_STATIC, ACC_SYNTHETIC
    Code:
      stack=1, locals=1, args_size=1
         0: aload_0
         1: invokespecial #179                // InterfaceMethod unary_$minus:()Lorg/sireum/Z$BV$Short;
         4: areturn
      LineNumberTable:
        line 649: 0
      LocalVariableTable:
        Start  Length  Slot  Name   Signature
            0       5     0 $this   Lorg/sireum/Z$BV$Short;
    MethodParameters:
      Name                           Flags
      $this                          final synthetic

  public default T unary_$minus();
    descriptor: ()Lorg/sireum/Z$BV$Short;
    flags: (0x0001) ACC_PUBLIC
    Code:
      stack=3, locals=1, args_size=1
         0: aload_0
         1: invokeinterface #181,  1          // InterfaceMethod isWrapped:()Z
         6: ifne          27
         9: aload_0
        10: aload_0
        11: invokeinterface #99,  1           // InterfaceMethod toMP:()Lorg/sireum/Z;
        16: invokeinterface #183,  1          // InterfaceMethod org/sireum/Z.unary_$minus:()Lorg/sireum/Z;
        21: invokespecial #185                // InterfaceMethod make:(Lorg/sireum/Z;)Lorg/sireum/Z$BV$Short;
        24: goto          64
        27: aload_0
        28: invokeinterface #170,  1          // InterfaceMethod isSigned:()Z
        33: ifeq          50
        36: aload_0
        37: aload_0
        38: invokeinterface #70,  1           // InterfaceMethod org$sireum$Z$BV$Short$$toShort:()S
        43: ineg
        44: invokespecial #187                // InterfaceMethod makeShort:(I)Lorg/sireum/Z$BV$Short;
        47: goto          64
        50: aload_0
        51: getstatic     #77                 // Field org/sireum/Z$U$_16$.MODULE$:Lorg/sireum/Z$U$_16$;
        54: aload_0
        55: invokespecial #189                // InterfaceMethod toU16:()S
        58: invokevirtual #192                // Method org/sireum/Z$U$_16$.unary_$minus$extension:(S)S
        61: invokespecial #194                // InterfaceMethod umake:(S)Lorg/sireum/Z$BV$Short;
        64: areturn
      StackMapTable: number_of_entries = 3
        frame_type = 27 /* same */
        frame_type = 22 /* same */
        frame_type = 77 /* same_locals_1_stack_item */
          stack = [ class org/sireum/Z$BV$Short ]
      LineNumberTable:
        line 650: 0
        line 651: 27
        line 652: 50
      LocalVariableTable:
        Start  Length  Slot  Name   Signature
            0      65     0  this   Lorg/sireum/Z$BV$Short;
    Signature: #61                          // ()TT;

  public static org.sireum.Z$BV$Short $plus$(org.sireum.Z$BV$Short, org.sireum.Z$BV$Short);
    descriptor: (Lorg/sireum/Z$BV$Short;Lorg/sireum/Z$BV$Short;)Lorg/sireum/Z$BV$Short;
    flags: (0x1009) ACC_PUBLIC, ACC_STATIC, ACC_SYNTHETIC
    Code:
      stack=2, locals=2, args_size=2
         0: aload_0
         1: aload_1
         2: invokespecial #200                // InterfaceMethod $plus:(Lorg/sireum/Z$BV$Short;)Lorg/sireum/Z$BV$Short;
         5: areturn
      LineNumberTable:
        line 654: 0
      LocalVariableTable:
        Start  Length  Slot  Name   Signature
            0       6     0 $this   Lorg/sireum/Z$BV$Short;
            0       6     1 other   Lorg/sireum/Z$BV$Short;
    MethodParameters:
      Name                           Flags
      $this                          final synthetic
      other                          final

  public default T $plus(T);
    descriptor: (Lorg/sireum/Z$BV$Short;)Lorg/sireum/Z$BV$Short;
    flags: (0x0001) ACC_PUBLIC
    Code:
      stack=4, locals=2, args_size=2
         0: aload_0
         1: invokeinterface #181,  1          // InterfaceMethod isWrapped:()Z
         6: ifne          33
         9: aload_0
        10: aload_0
        11: invokeinterface #99,  1           // InterfaceMethod toMP:()Lorg/sireum/Z;
        16: aload_1
        17: invokeinterface #99,  1           // InterfaceMethod toMP:()Lorg/sireum/Z;
        22: invokeinterface #204,  2          // InterfaceMethod org/sireum/Z.$plus:(Lorg/sireum/Z;)Lorg/sireum/Z;
        27: invokespecial #185                // InterfaceMethod make:(Lorg/sireum/Z;)Lorg/sireum/Z$BV$Short;
        30: goto          80
        33: aload_0
        34: invokeinterface #170,  1          // InterfaceMethod isSigned:()Z
        39: ifeq          62
        42: aload_0
        43: aload_0
        44: invokeinterface #70,  1           // InterfaceMethod org$sireum$Z$BV$Short$$toShort:()S
        49: aload_1
        50: invokeinterface #70,  1           // InterfaceMethod org$sireum$Z$BV$Short$$toShort:()S
        55: iadd
        56: invokespecial #187                // InterfaceMethod makeShort:(I)Lorg/sireum/Z$BV$Short;
        59: goto          80
        62: aload_0
        63: getstatic     #77                 // Field org/sireum/Z$U$_16$.MODULE$:Lorg/sireum/Z$U$_16$;
        66: aload_0
        67: invokespecial #189                // InterfaceMethod toU16:()S
        70: aload_1
        71: invokespecial #189                // InterfaceMethod toU16:()S
        74: invokevirtual #208                // Method org/sireum/Z$U$_16$.$plus$extension:(SS)S
        77: invokespecial #194                // InterfaceMethod umake:(S)Lorg/sireum/Z$BV$Short;
        80: areturn
      StackMapTable: number_of_entries = 3
        frame_type = 33 /* same */
        frame_type = 28 /* same */
        frame_type = 81 /* same_locals_1_stack_item */
          stack = [ class org/sireum/Z$BV$Short ]
      LineNumberTable:
        line 655: 0
        line 656: 33
        line 657: 62
      LocalVariableTable:
        Start  Length  Slot  Name   Signature
            0      81     0  this   Lorg/sireum/Z$BV$Short;
            0      81     1 other   Lorg/sireum/Z$BV$Short;
    Signature: #201                         // (TT;)TT;
    MethodParameters:
      Name                           Flags
      other                          final

  public static org.sireum.Z$BV$Short $minus$(org.sireum.Z$BV$Short, org.sireum.Z$BV$Short);
    descriptor: (Lorg/sireum/Z$BV$Short;Lorg/sireum/Z$BV$Short;)Lorg/sireum/Z$BV$Short;
    flags: (0x1009) ACC_PUBLIC, ACC_STATIC, ACC_SYNTHETIC
    Code:
      stack=2, locals=2, args_size=2
         0: aload_0
         1: aload_1
         2: invokespecial #212                // InterfaceMethod $minus:(Lorg/sireum/Z$BV$Short;)Lorg/sireum/Z$BV$Short;
         5: areturn
      LineNumberTable:
        line 660: 0
      LocalVariableTable:
        Start  Length  Slot  Name   Signature
            0       6     0 $this   Lorg/sireum/Z$BV$Short;
            0       6     1 other   Lorg/sireum/Z$BV$Short;
    MethodParameters:
      Name                           Flags
      $this                          final synthetic
      other                          final

  public default T $minus(T);
    descriptor: (Lorg/sireum/Z$BV$Short;)Lorg/sireum/Z$BV$Short;
    flags: (0x0001) ACC_PUBLIC
    Code:
      stack=4, locals=2, args_size=2
         0: aload_0
         1: invokeinterface #181,  1          // InterfaceMethod isWrapped:()Z
         6: ifne          33
         9: aload_0
        10: aload_0
        11: invokeinterface #99,  1           // InterfaceMethod toMP:()Lorg/sireum/Z;
        16: aload_1
        17: invokeinterface #99,  1           // InterfaceMethod toMP:()Lorg/sireum/Z;
        22: invokeinterface #214,  2          // InterfaceMethod org/sireum/Z.$minus:(Lorg/sireum/Z;)Lorg/sireum/Z;
        27: invokespecial #185                // InterfaceMethod make:(Lorg/sireum/Z;)Lorg/sireum/Z$BV$Short;
        30: goto          80
        33: aload_0
        34: invokeinterface #170,  1          // InterfaceMethod isSigned:()Z
        39: ifeq          62
        42: aload_0
        43: aload_0
        44: invokeinterface #70,  1           // InterfaceMethod org$sireum$Z$BV$Short$$toShort:()S
        49: aload_1
        50: invokeinterface #70,  1           // InterfaceMethod org$sireum$Z$BV$Short$$toShort:()S
        55: isub
        56: invokespecial #187                // InterfaceMethod makeShort:(I)Lorg/sireum/Z$BV$Short;
        59: goto          80
        62: aload_0
        63: getstatic     #77                 // Field org/sireum/Z$U$_16$.MODULE$:Lorg/sireum/Z$U$_16$;
        66: aload_0
        67: invokespecial #189                // InterfaceMethod toU16:()S
        70: aload_1
        71: invokespecial #189                // InterfaceMethod toU16:()S
        74: invokevirtual #217                // Method org/sireum/Z$U$_16$.$minus$extension:(SS)S
        77: invokespecial #194                // InterfaceMethod umake:(S)Lorg/sireum/Z$BV$Short;
        80: areturn
      StackMapTable: number_of_entries = 3
        frame_type = 33 /* same */
        frame_type = 28 /* same */
        frame_type = 81 /* same_locals_1_stack_item */
          stack = [ class org/sireum/Z$BV$Short ]
      LineNumberTable:
        line 661: 0
        line 662: 33
        line 663: 62
      LocalVariableTable:
        Start  Length  Slot  Name   Signature
            0      81     0  this   Lorg/sireum/Z$BV$Short;
            0      81     1 other   Lorg/sireum/Z$BV$Short;
    Signature: #201                         // (TT;)TT;
    MethodParameters:
      Name                           Flags
      other                          final

  public static org.sireum.Z$BV$Short $times$(org.sireum.Z$BV$Short, org.sireum.Z$BV$Short);
    descriptor: (Lorg/sireum/Z$BV$Short;Lorg/sireum/Z$BV$Short;)Lorg/sireum/Z$BV$Short;
    flags: (0x1009) ACC_PUBLIC, ACC_STATIC, ACC_SYNTHETIC
    Code:
      stack=2, locals=2, args_size=2
         0: aload_0
         1: aload_1
         2: invokespecial #221                // InterfaceMethod $times:(Lorg/sireum/Z$BV$Short;)Lorg/sireum/Z$BV$Short;
         5: areturn
      LineNumberTable:
        line 666: 0
      LocalVariableTable:
        Start  Length  Slot  Name   Signature
            0       6     0 $this   Lorg/sireum/Z$BV$Short;
            0       6     1 other   Lorg/sireum/Z$BV$Short;
    MethodParameters:
      Name                           Flags
      $this                          final synthetic
      other                          final

  public default T $times(T);
    descriptor: (Lorg/sireum/Z$BV$Short;)Lorg/sireum/Z$BV$Short;
    flags: (0x0001) ACC_PUBLIC
    Code:
      stack=4, locals=2, args_size=2
         0: aload_0
         1: invokeinterface #181,  1          // InterfaceMethod isWrapped:()Z
         6: ifne          33
         9: aload_0
        10: aload_0
        11: invokeinterface #99,  1           // InterfaceMethod toMP:()Lorg/sireum/Z;
        16: aload_1
        17: invokeinterface #99,  1           // InterfaceMethod toMP:()Lorg/sireum/Z;
        22: invokeinterface #223,  2          // InterfaceMethod org/sireum/Z.$times:(Lorg/sireum/Z;)Lorg/sireum/Z;
        27: invokespecial #185                // InterfaceMethod make:(Lorg/sireum/Z;)Lorg/sireum/Z$BV$Short;
        30: goto          80
        33: aload_0
        34: invokeinterface #170,  1          // InterfaceMethod isSigned:()Z
        39: ifeq          62
        42: aload_0
        43: aload_0
        44: invokeinterface #70,  1           // InterfaceMethod org$sireum$Z$BV$Short$$toShort:()S
        49: aload_1
        50: invokeinterface #70,  1           // InterfaceMethod org$sireum$Z$BV$Short$$toShort:()S
        55: imul
        56: invokespecial #187                // InterfaceMethod makeShort:(I)Lorg/sireum/Z$BV$Short;
        59: goto          80
        62: aload_0
        63: getstatic     #77                 // Field org/sireum/Z$U$_16$.MODULE$:Lorg/sireum/Z$U$_16$;
        66: aload_0
        67: invokespecial #189                // InterfaceMethod toU16:()S
        70: aload_1
        71: invokespecial #189                // InterfaceMethod toU16:()S
        74: invokevirtual #226                // Method org/sireum/Z$U$_16$.$times$extension:(SS)S
        77: invokespecial #194                // InterfaceMethod umake:(S)Lorg/sireum/Z$BV$Short;
        80: areturn
      StackMapTable: number_of_entries = 3
        frame_type = 33 /* same */
        frame_type = 28 /* same */
        frame_type = 81 /* same_locals_1_stack_item */
          stack = [ class org/sireum/Z$BV$Short ]
      LineNumberTable:
        line 667: 0
        line 668: 33
        line 669: 62
      LocalVariableTable:
        Start  Length  Slot  Name   Signature
            0      81     0  this   Lorg/sireum/Z$BV$Short;
            0      81     1 other   Lorg/sireum/Z$BV$Short;
    Signature: #201                         // (TT;)TT;
    MethodParameters:
      Name                           Flags
      other                          final

  public static org.sireum.Z$BV$Short $div$(org.sireum.Z$BV$Short, org.sireum.Z$BV$Short);
    descriptor: (Lorg/sireum/Z$BV$Short;Lorg/sireum/Z$BV$Short;)Lorg/sireum/Z$BV$Short;
    flags: (0x1009) ACC_PUBLIC, ACC_STATIC, ACC_SYNTHETIC
    Code:
      stack=2, locals=2, args_size=2
         0: aload_0
         1: aload_1
         2: invokespecial #230                // InterfaceMethod $div:(Lorg/sireum/Z$BV$Short;)Lorg/sireum/Z$BV$Short;
         5: areturn
      LineNumberTable:
        line 672: 0
      LocalVariableTable:
        Start  Length  Slot  Name   Signature
            0       6     0 $this   Lorg/sireum/Z$BV$Short;
            0       6     1 other   Lorg/sireum/Z$BV$Short;
    MethodParameters:
      Name                           Flags
      $this                          final synthetic
      other                          final

  public default T $div(T);
    descriptor: (Lorg/sireum/Z$BV$Short;)Lorg/sireum/Z$BV$Short;
    flags: (0x0001) ACC_PUBLIC
    Code:
      stack=4, locals=2, args_size=2
         0: aload_0
         1: invokeinterface #181,  1          // InterfaceMethod isWrapped:()Z
         6: ifne          33
         9: aload_0
        10: aload_0
        11: invokeinterface #99,  1           // InterfaceMethod toMP:()Lorg/sireum/Z;
        16: aload_1
        17: invokeinterface #99,  1           // InterfaceMethod toMP:()Lorg/sireum/Z;
        22: invokeinterface #232,  2          // InterfaceMethod org/sireum/Z.$div:(Lorg/sireum/Z;)Lorg/sireum/Z;
        27: invokespecial #185                // InterfaceMethod make:(Lorg/sireum/Z;)Lorg/sireum/Z$BV$Short;
        30: goto          80
        33: aload_0
        34: invokeinterface #170,  1          // InterfaceMethod isSigned:()Z
        39: ifeq          62
        42: aload_0
        43: aload_0
        44: invokeinterface #70,  1           // InterfaceMethod org$sireum$Z$BV$Short$$toShort:()S
        49: aload_1
        50: invokeinterface #70,  1           // InterfaceMethod org$sireum$Z$BV$Short$$toShort:()S
        55: idiv
        56: invokespecial #187                // InterfaceMethod makeShort:(I)Lorg/sireum/Z$BV$Short;
        59: goto          80
        62: aload_0
        63: getstatic     #77                 // Field org/sireum/Z$U$_16$.MODULE$:Lorg/sireum/Z$U$_16$;
        66: aload_0
        67: invokespecial #189                // InterfaceMethod toU16:()S
        70: aload_1
        71: invokespecial #189                // InterfaceMethod toU16:()S
        74: invokevirtual #235                // Method org/sireum/Z$U$_16$.$div$extension:(SS)S
        77: invokespecial #194                // InterfaceMethod umake:(S)Lorg/sireum/Z$BV$Short;
        80: areturn
      StackMapTable: number_of_entries = 3
        frame_type = 33 /* same */
        frame_type = 28 /* same */
        frame_type = 81 /* same_locals_1_stack_item */
          stack = [ class org/sireum/Z$BV$Short ]
      LineNumberTable:
        line 673: 0
        line 674: 33
        line 675: 62
      LocalVariableTable:
        Start  Length  Slot  Name   Signature
            0      81     0  this   Lorg/sireum/Z$BV$Short;
            0      81     1 other   Lorg/sireum/Z$BV$Short;
    Signature: #201                         // (TT;)TT;
    MethodParameters:
      Name                           Flags
      other                          final

  public static org.sireum.Z$BV$Short $percent$(org.sireum.Z$BV$Short, org.sireum.Z$BV$Short);
    descriptor: (Lorg/sireum/Z$BV$Short;Lorg/sireum/Z$BV$Short;)Lorg/sireum/Z$BV$Short;
    flags: (0x1009) ACC_PUBLIC, ACC_STATIC, ACC_SYNTHETIC
    Code:
      stack=2, locals=2, args_size=2
         0: aload_0
         1: aload_1
         2: invokespecial #239                // InterfaceMethod $percent:(Lorg/sireum/Z$BV$Short;)Lorg/sireum/Z$BV$Short;
         5: areturn
      LineNumberTable:
        line 678: 0
      LocalVariableTable:
        Start  Length  Slot  Name   Signature
            0       6     0 $this   Lorg/sireum/Z$BV$Short;
            0       6     1 other   Lorg/sireum/Z$BV$Short;
    MethodParameters:
      Name                           Flags
      $this                          final synthetic
      other                          final

  public default T $percent(T);
    descriptor: (Lorg/sireum/Z$BV$Short;)Lorg/sireum/Z$BV$Short;
    flags: (0x0001) ACC_PUBLIC
    Code:
      stack=4, locals=2, args_size=2
         0: aload_0
         1: invokeinterface #181,  1          // InterfaceMethod isWrapped:()Z
         6: ifne          33
         9: aload_0
        10: aload_0
        11: invokeinterface #99,  1           // InterfaceMethod toMP:()Lorg/sireum/Z;
        16: aload_1
        17: invokeinterface #99,  1           // InterfaceMethod toMP:()Lorg/sireum/Z;
        22: invokeinterface #241,  2          // InterfaceMethod org/sireum/Z.$percent:(Lorg/sireum/Z;)Lorg/sireum/Z;
        27: invokespecial #185                // InterfaceMethod make:(Lorg/sireum/Z;)Lorg/sireum/Z$BV$Short;
        30: goto          80
        33: aload_0
        34: invokeinterface #170,  1          // InterfaceMethod isSigned:()Z
        39: ifeq          62
        42: aload_0
        43: aload_0
        44: invokeinterface #70,  1           // InterfaceMethod org$sireum$Z$BV$Short$$toShort:()S
        49: aload_1
        50: invokeinterface #70,  1           // InterfaceMethod org$sireum$Z$BV$Short$$toShort:()S
        55: irem
        56: invokespecial #187                // InterfaceMethod makeShort:(I)Lorg/sireum/Z$BV$Short;
        59: goto          80
        62: aload_0
        63: getstatic     #77                 // Field org/sireum/Z$U$_16$.MODULE$:Lorg/sireum/Z$U$_16$;
        66: aload_0
        67: invokespecial #189                // InterfaceMethod toU16:()S
        70: aload_1
        71: invokespecial #189                // InterfaceMethod toU16:()S
        74: invokevirtual #244                // Method org/sireum/Z$U$_16$.$percent$extension:(SS)S
        77: invokespecial #194                // InterfaceMethod umake:(S)Lorg/sireum/Z$BV$Short;
        80: areturn
      StackMapTable: number_of_entries = 3
        frame_type = 33 /* same */
        frame_type = 28 /* same */
        frame_type = 81 /* same_locals_1_stack_item */
          stack = [ class org/sireum/Z$BV$Short ]
      LineNumberTable:
        line 679: 0
        line 680: 33
        line 681: 62
      LocalVariableTable:
        Start  Length  Slot  Name   Signature
            0      81     0  this   Lorg/sireum/Z$BV$Short;
            0      81     1 other   Lorg/sireum/Z$BV$Short;
    Signature: #201                         // (TT;)TT;
    MethodParameters:
      Name                           Flags
      other                          final

  public static boolean $greater$(org.sireum.Z$BV$Short, org.sireum.Z$BV$Short);
    descriptor: (Lorg/sireum/Z$BV$Short;Lorg/sireum/Z$BV$Short;)Z
    flags: (0x1009) ACC_PUBLIC, ACC_STATIC, ACC_SYNTHETIC
    Code:
      stack=2, locals=2, args_size=2
         0: aload_0
         1: aload_1
         2: invokespecial #249                // InterfaceMethod $greater:(Lorg/sireum/Z$BV$Short;)Z
         5: ireturn
      LineNumberTable:
        line 684: 0
      LocalVariableTable:
        Start  Length  Slot  Name   Signature
            0       6     0 $this   Lorg/sireum/Z$BV$Short;
            0       6     1 other   Lorg/sireum/Z$BV$Short;
    MethodParameters:
      Name                           Flags
      $this                          final synthetic
      other                          final

  public default boolean $greater(T);
    descriptor: (Lorg/sireum/Z$BV$Short;)Z
    flags: (0x0001) ACC_PUBLIC
    Code:
      stack=4, locals=2, args_size=2
         0: aload_0
         1: invokeinterface #170,  1          // InterfaceMethod isSigned:()Z
         6: ifeq          38
         9: getstatic     #93                 // Field org/sireum/B$.MODULE$:Lorg/sireum/B$;
        12: aload_0
        13: invokeinterface #70,  1           // InterfaceMethod org$sireum$Z$BV$Short$$toShort:()S
        18: aload_1
        19: invokeinterface #70,  1           // InterfaceMethod org$sireum$Z$BV$Short$$toShort:()S
        24: if_icmple     31
        27: iconst_1
        28: goto          32
        31: iconst_0
        32: invokevirtual #252                // Method org/sireum/B$.apply:(Z)Z
        35: goto          58
        38: getstatic     #93                 // Field org/sireum/B$.MODULE$:Lorg/sireum/B$;
        41: getstatic     #77                 // Field org/sireum/Z$U$_16$.MODULE$:Lorg/sireum/Z$U$_16$;
        44: aload_0
        45: invokespecial #189                // InterfaceMethod toU16:()S
        48: aload_1
        49: invokespecial #189                // InterfaceMethod toU16:()S
        52: invokevirtual #256                // Method org/sireum/Z$U$_16$.$greater$extension:(SS)Z
        55: invokevirtual #252                // Method org/sireum/B$.apply:(Z)Z
        58: ireturn
      StackMapTable: number_of_entries = 4
        frame_type = 95 /* same_locals_1_stack_item */
          stack = [ class org/sireum/B$ ]
        frame_type = 255 /* full_frame */
          offset_delta = 0
          locals = [ class org/sireum/Z$BV$Short, class org/sireum/Z$BV$Short ]
          stack = [ class org/sireum/B$, int ]
        frame_type = 5 /* same */
        frame_type = 83 /* same_locals_1_stack_item */
          stack = [ int ]
      LineNumberTable:
        line 685: 0
        line 686: 38
      LocalVariableTable:
        Start  Length  Slot  Name   Signature
            0      59     0  this   Lorg/sireum/Z$BV$Short;
            0      59     1 other   Lorg/sireum/Z$BV$Short;
    Signature: #250                         // (TT;)Z
    MethodParameters:
      Name                           Flags
      other                          final

  public static boolean $greater$eq$(org.sireum.Z$BV$Short, org.sireum.Z$BV$Short);
    descriptor: (Lorg/sireum/Z$BV$Short;Lorg/sireum/Z$BV$Short;)Z
    flags: (0x1009) ACC_PUBLIC, ACC_STATIC, ACC_SYNTHETIC
    Code:
      stack=2, locals=2, args_size=2
         0: aload_0
         1: aload_1
         2: invokespecial #260                // InterfaceMethod $greater$eq:(Lorg/sireum/Z$BV$Short;)Z
         5: ireturn
      LineNumberTable:
        line 689: 0
      LocalVariableTable:
        Start  Length  Slot  Name   Signature
            0       6     0 $this   Lorg/sireum/Z$BV$Short;
            0       6     1 other   Lorg/sireum/Z$BV$Short;
    MethodParameters:
      Name                           Flags
      $this                          final synthetic
      other                          final

  public default boolean $greater$eq(T);
    descriptor: (Lorg/sireum/Z$BV$Short;)Z
    flags: (0x0001) ACC_PUBLIC
    Code:
      stack=4, locals=2, args_size=2
         0: aload_0
         1: invokeinterface #170,  1          // InterfaceMethod isSigned:()Z
         6: ifeq          38
         9: getstatic     #93                 // Field org/sireum/B$.MODULE$:Lorg/sireum/B$;
        12: aload_0
        13: invokeinterface #70,  1           // InterfaceMethod org$sireum$Z$BV$Short$$toShort:()S
        18: aload_1
        19: invokeinterface #70,  1           // InterfaceMethod org$sireum$Z$BV$Short$$toShort:()S
        24: if_icmplt     31
        27: iconst_1
        28: goto          32
        31: iconst_0
        32: invokevirtual #252                // Method org/sireum/B$.apply:(Z)Z
        35: goto          58
        38: getstatic     #93                 // Field org/sireum/B$.MODULE$:Lorg/sireum/B$;
        41: getstatic     #77                 // Field org/sireum/Z$U$_16$.MODULE$:Lorg/sireum/Z$U$_16$;
        44: aload_0
        45: invokespecial #189                // InterfaceMethod toU16:()S
        48: aload_1
        49: invokespecial #189                // InterfaceMethod toU16:()S
        52: invokevirtual #263                // Method org/sireum/Z$U$_16$.$greater$eq$extension:(SS)Z
        55: invokevirtual #252                // Method org/sireum/B$.apply:(Z)Z
        58: ireturn
      StackMapTable: number_of_entries = 4
        frame_type = 95 /* same_locals_1_stack_item */
          stack = [ class org/sireum/B$ ]
        frame_type = 255 /* full_frame */
          offset_delta = 0
          locals = [ class org/sireum/Z$BV$Short, class org/sireum/Z$BV$Short ]
          stack = [ class org/sireum/B$, int ]
        frame_type = 5 /* same */
        frame_type = 83 /* same_locals_1_stack_item */
          stack = [ int ]
      LineNumberTable:
        line 690: 0
        line 691: 38
      LocalVariableTable:
        Start  Length  Slot  Name   Signature
            0      59     0  this   Lorg/sireum/Z$BV$Short;
            0      59     1 other   Lorg/sireum/Z$BV$Short;
    Signature: #250                         // (TT;)Z
    MethodParameters:
      Name                           Flags
      other                          final

  public static boolean $less$(org.sireum.Z$BV$Short, org.sireum.Z$BV$Short);
    descriptor: (Lorg/sireum/Z$BV$Short;Lorg/sireum/Z$BV$Short;)Z
    flags: (0x1009) ACC_PUBLIC, ACC_STATIC, ACC_SYNTHETIC
    Code:
      stack=2, locals=2, args_size=2
         0: aload_0
         1: aload_1
         2: invokespecial #267                // InterfaceMethod $less:(Lorg/sireum/Z$BV$Short;)Z
         5: ireturn
      LineNumberTable:
        line 694: 0
      LocalVariableTable:
        Start  Length  Slot  Name   Signature
            0       6     0 $this   Lorg/sireum/Z$BV$Short;
            0       6     1 other   Lorg/sireum/Z$BV$Short;
    MethodParameters:
      Name                           Flags
      $this                          final synthetic
      other                          final

  public default boolean $less(T);
    descriptor: (Lorg/sireum/Z$BV$Short;)Z
    flags: (0x0001) ACC_PUBLIC
    Code:
      stack=4, locals=2, args_size=2
         0: aload_0
         1: invokeinterface #170,  1          // InterfaceMethod isSigned:()Z
         6: ifeq          38
         9: getstatic     #93                 // Field org/sireum/B$.MODULE$:Lorg/sireum/B$;
        12: aload_0
        13: invokeinterface #70,  1           // InterfaceMethod org$sireum$Z$BV$Short$$toShort:()S
        18: aload_1
        19: invokeinterface #70,  1           // InterfaceMethod org$sireum$Z$BV$Short$$toShort:()S
        24: if_icmpge     31
        27: iconst_1
        28: goto          32
        31: iconst_0
        32: invokevirtual #252                // Method org/sireum/B$.apply:(Z)Z
        35: goto          58
        38: getstatic     #93                 // Field org/sireum/B$.MODULE$:Lorg/sireum/B$;
        41: getstatic     #77                 // Field org/sireum/Z$U$_16$.MODULE$:Lorg/sireum/Z$U$_16$;
        44: aload_0
        45: invokespecial #189                // InterfaceMethod toU16:()S
        48: aload_1
        49: invokespecial #189                // InterfaceMethod toU16:()S
        52: invokevirtual #270                // Method org/sireum/Z$U$_16$.$less$extension:(SS)Z
        55: invokevirtual #252                // Method org/sireum/B$.apply:(Z)Z
        58: ireturn
      StackMapTable: number_of_entries = 4
        frame_type = 95 /* same_locals_1_stack_item */
          stack = [ class org/sireum/B$ ]
        frame_type = 255 /* full_frame */
          offset_delta = 0
          locals = [ class org/sireum/Z$BV$Short, class org/sireum/Z$BV$Short ]
          stack = [ class org/sireum/B$, int ]
        frame_type = 5 /* same */
        frame_type = 83 /* same_locals_1_stack_item */
          stack = [ int ]
      LineNumberTable:
        line 695: 0
        line 696: 38
      LocalVariableTable:
        Start  Length  Slot  Name   Signature
            0      59     0  this   Lorg/sireum/Z$BV$Short;
            0      59     1 other   Lorg/sireum/Z$BV$Short;
    Signature: #250                         // (TT;)Z
    MethodParameters:
      Name                           Flags
      other                          final

  public static boolean $less$eq$(org.sireum.Z$BV$Short, org.sireum.Z$BV$Short);
    descriptor: (Lorg/sireum/Z$BV$Short;Lorg/sireum/Z$BV$Short;)Z
    flags: (0x1009) ACC_PUBLIC, ACC_STATIC, ACC_SYNTHETIC
    Code:
      stack=2, locals=2, args_size=2
         0: aload_0
         1: aload_1
         2: invokespecial #273                // InterfaceMethod $less$eq:(Lorg/sireum/Z$BV$Short;)Z
         5: ireturn
      LineNumberTable:
        line 699: 0
      LocalVariableTable:
        Start  Length  Slot  Name   Signature
            0       6     0 $this   Lorg/sireum/Z$BV$Short;
            0       6     1 other   Lorg/sireum/Z$BV$Short;
    MethodParameters:
      Name                           Flags
      $this                          final synthetic
      other                          final

  public default boolean $less$eq(T);
    descriptor: (Lorg/sireum/Z$BV$Short;)Z
    flags: (0x0001) ACC_PUBLIC
    Code:
      stack=4, locals=2, args_size=2
         0: aload_0
         1: invokeinterface #170,  1          // InterfaceMethod isSigned:()Z
         6: ifeq          38
         9: getstatic     #93                 // Field org/sireum/B$.MODULE$:Lorg/sireum/B$;
        12: aload_0
        13: invokeinterface #70,  1           // InterfaceMethod org$sireum$Z$BV$Short$$toShort:()S
        18: aload_1
        19: invokeinterface #70,  1           // InterfaceMethod org$sireum$Z$BV$Short$$toShort:()S
        24: if_icmpgt     31
        27: iconst_1
        28: goto          32
        31: iconst_0
        32: invokevirtual #252                // Method org/sireum/B$.apply:(Z)Z
        35: goto          58
        38: getstatic     #93                 // Field org/sireum/B$.MODULE$:Lorg/sireum/B$;
        41: getstatic     #77                 // Field org/sireum/Z$U$_16$.MODULE$:Lorg/sireum/Z$U$_16$;
        44: aload_0
        45: invokespecial #189                // InterfaceMethod toU16:()S
        48: aload_1
        49: invokespecial #189                // InterfaceMethod toU16:()S
        52: invokevirtual #276                // Method org/sireum/Z$U$_16$.$less$eq$extension:(SS)Z
        55: invokevirtual #252                // Method org/sireum/B$.apply:(Z)Z
        58: ireturn
      StackMapTable: number_of_entries = 4
        frame_type = 95 /* same_locals_1_stack_item */
          stack = [ class org/sireum/B$ ]
        frame_type = 255 /* full_frame */
          offset_delta = 0
          locals = [ class org/sireum/Z$BV$Short, class org/sireum/Z$BV$Short ]
          stack = [ class org/sireum/B$, int ]
        frame_type = 5 /* same */
        frame_type = 83 /* same_locals_1_stack_item */
          stack = [ int ]
      LineNumberTable:
        line 700: 0
        line 701: 38
      LocalVariableTable:
        Start  Length  Slot  Name   Signature
            0      59     0  this   Lorg/sireum/Z$BV$Short;
            0      59     1 other   Lorg/sireum/Z$BV$Short;
    Signature: #250                         // (TT;)Z
    MethodParameters:
      Name                           Flags
      other                          final

  public static org.sireum.Z$BV$Short $greater$greater$(org.sireum.Z$BV$Short, org.sireum.Z$BV$Short);
    descriptor: (Lorg/sireum/Z$BV$Short;Lorg/sireum/Z$BV$Short;)Lorg/sireum/Z$BV$Short;
    flags: (0x1009) ACC_PUBLIC, ACC_STATIC, ACC_SYNTHETIC
    Code:
      stack=2, locals=2, args_size=2
         0: aload_0
         1: aload_1
         2: invokespecial #280                // InterfaceMethod $greater$greater:(Lorg/sireum/Z$BV$Short;)Lorg/sireum/Z$BV$Short;
         5: areturn
      LineNumberTable:
        line 704: 0
      LocalVariableTable:
        Start  Length  Slot  Name   Signature
            0       6     0 $this   Lorg/sireum/Z$BV$Short;
            0       6     1 other   Lorg/sireum/Z$BV$Short;
    MethodParameters:
      Name                           Flags
      $this                          final synthetic
      other                          final

  public default T $greater$greater(T);
    descriptor: (Lorg/sireum/Z$BV$Short;)Lorg/sireum/Z$BV$Short;
    flags: (0x0001) ACC_PUBLIC
    Code:
      stack=3, locals=2, args_size=2
         0: aload_0
         1: invokeinterface #170,  1          // InterfaceMethod isSigned:()Z
         6: ifeq          29
         9: aload_0
        10: aload_0
        11: invokeinterface #70,  1           // InterfaceMethod org$sireum$Z$BV$Short$$toShort:()S
        16: aload_1
        17: invokeinterface #70,  1           // InterfaceMethod org$sireum$Z$BV$Short$$toShort:()S
        22: ishr
        23: invokespecial #187                // InterfaceMethod makeShort:(I)Lorg/sireum/Z$BV$Short;
        26: goto          36
        29: aload_0
        30: aload_1
        31: invokeinterface #283,  2          // InterfaceMethod $greater$greater$greater:(Lorg/sireum/Z$BV$Short;)Lorg/sireum/Z$BV$Short;
        36: areturn
      StackMapTable: number_of_entries = 2
        frame_type = 29 /* same */
        frame_type = 70 /* same_locals_1_stack_item */
          stack = [ class org/sireum/Z$BV$Short ]
      LineNumberTable:
        line 705: 0
        line 706: 29
      LocalVariableTable:
        Start  Length  Slot  Name   Signature
            0      37     0  this   Lorg/sireum/Z$BV$Short;
            0      37     1 other   Lorg/sireum/Z$BV$Short;
    Signature: #201                         // (TT;)TT;
    MethodParameters:
      Name                           Flags
      other                          final

  public static org.sireum.Z$BV$Short $greater$greater$greater$(org.sireum.Z$BV$Short, org.sireum.Z$BV$Short);
    descriptor: (Lorg/sireum/Z$BV$Short;Lorg/sireum/Z$BV$Short;)Lorg/sireum/Z$BV$Short;
    flags: (0x1009) ACC_PUBLIC, ACC_STATIC, ACC_SYNTHETIC
    Code:
      stack=2, locals=2, args_size=2
         0: aload_0
         1: aload_1
         2: invokespecial #283                // InterfaceMethod $greater$greater$greater:(Lorg/sireum/Z$BV$Short;)Lorg/sireum/Z$BV$Short;
         5: areturn
      LineNumberTable:
        line 709: 0
      LocalVariableTable:
        Start  Length  Slot  Name   Signature
            0       6     0 $this   Lorg/sireum/Z$BV$Short;
            0       6     1 other   Lorg/sireum/Z$BV$Short;
    MethodParameters:
      Name                           Flags
      $this                          final synthetic
      other                          final

  public default T $greater$greater$greater(T);
    descriptor: (Lorg/sireum/Z$BV$Short;)Lorg/sireum/Z$BV$Short;
    flags: (0x0001) ACC_PUBLIC
    Code:
      stack=5, locals=2, args_size=2
         0: aload_0
         1: invokeinterface #170,  1          // InterfaceMethod isSigned:()Z
         6: ifeq          29
         9: aload_0
        10: aload_0
        11: invokeinterface #70,  1           // InterfaceMethod org$sireum$Z$BV$Short$$toShort:()S
        16: aload_1
        17: invokeinterface #70,  1           // InterfaceMethod org$sireum$Z$BV$Short$$toShort:()S
        22: iushr
        23: invokespecial #187                // InterfaceMethod makeShort:(I)Lorg/sireum/Z$BV$Short;
        26: goto          53
        29: aload_0
        30: getstatic     #77                 // Field org/sireum/Z$U$_16$.MODULE$:Lorg/sireum/Z$U$_16$;
        33: aload_0
        34: invokespecial #189                // InterfaceMethod toU16:()S
        37: getstatic     #77                 // Field org/sireum/Z$U$_16$.MODULE$:Lorg/sireum/Z$U$_16$;
        40: aload_1
        41: invokespecial #189                // InterfaceMethod toU16:()S
        44: invokevirtual #288                // Method org/sireum/Z$U$_16$.toInt$extension:(S)I
        47: invokevirtual #292                // Method org/sireum/Z$U$_16$.$greater$greater$greater$extension:(SI)S
        50: invokespecial #194                // InterfaceMethod umake:(S)Lorg/sireum/Z$BV$Short;
        53: areturn
      StackMapTable: number_of_entries = 2
        frame_type = 29 /* same */
        frame_type = 87 /* same_locals_1_stack_item */
          stack = [ class org/sireum/Z$BV$Short ]
      LineNumberTable:
        line 710: 0
        line 711: 29
      LocalVariableTable:
        Start  Length  Slot  Name   Signature
            0      54     0  this   Lorg/sireum/Z$BV$Short;
            0      54     1 other   Lorg/sireum/Z$BV$Short;
    Signature: #201                         // (TT;)TT;
    MethodParameters:
      Name                           Flags
      other                          final

  public static org.sireum.Z$BV$Short $less$less$(org.sireum.Z$BV$Short, org.sireum.Z$BV$Short);
    descriptor: (Lorg/sireum/Z$BV$Short;Lorg/sireum/Z$BV$Short;)Lorg/sireum/Z$BV$Short;
    flags: (0x1009) ACC_PUBLIC, ACC_STATIC, ACC_SYNTHETIC
    Code:
      stack=2, locals=2, args_size=2
         0: aload_0
         1: aload_1
         2: invokespecial #296                // InterfaceMethod $less$less:(Lorg/sireum/Z$BV$Short;)Lorg/sireum/Z$BV$Short;
         5: areturn
      LineNumberTable:
        line 714: 0
      LocalVariableTable:
        Start  Length  Slot  Name   Signature
            0       6     0 $this   Lorg/sireum/Z$BV$Short;
            0       6     1 other   Lorg/sireum/Z$BV$Short;
    MethodParameters:
      Name                           Flags
      $this                          final synthetic
      other                          final

  public default T $less$less(T);
    descriptor: (Lorg/sireum/Z$BV$Short;)Lorg/sireum/Z$BV$Short;
    flags: (0x0001) ACC_PUBLIC
    Code:
      stack=5, locals=2, args_size=2
         0: aload_0
         1: invokeinterface #170,  1          // InterfaceMethod isSigned:()Z
         6: ifeq          29
         9: aload_0
        10: aload_0
        11: invokeinterface #70,  1           // InterfaceMethod org$sireum$Z$BV$Short$$toShort:()S
        16: aload_1
        17: invokeinterface #70,  1           // InterfaceMethod org$sireum$Z$BV$Short$$toShort:()S
        22: ishl
        23: invokespecial #187                // InterfaceMethod makeShort:(I)Lorg/sireum/Z$BV$Short;
        26: goto          53
        29: aload_0
        30: getstatic     #77                 // Field org/sireum/Z$U$_16$.MODULE$:Lorg/sireum/Z$U$_16$;
        33: aload_0
        34: invokespecial #189                // InterfaceMethod toU16:()S
        37: getstatic     #77                 // Field org/sireum/Z$U$_16$.MODULE$:Lorg/sireum/Z$U$_16$;
        40: aload_1
        41: invokespecial #189                // InterfaceMethod toU16:()S
        44: invokevirtual #288                // Method org/sireum/Z$U$_16$.toInt$extension:(S)I
        47: invokevirtual #299                // Method org/sireum/Z$U$_16$.$less$less$extension:(SI)S
        50: invokespecial #194                // InterfaceMethod umake:(S)Lorg/sireum/Z$BV$Short;
        53: areturn
      StackMapTable: number_of_entries = 2
        frame_type = 29 /* same */
        frame_type = 87 /* same_locals_1_stack_item */
          stack = [ class org/sireum/Z$BV$Short ]
      LineNumberTable:
        line 715: 0
        line 716: 29
      LocalVariableTable:
        Start  Length  Slot  Name   Signature
            0      54     0  this   Lorg/sireum/Z$BV$Short;
            0      54     1 other   Lorg/sireum/Z$BV$Short;
    Signature: #201                         // (TT;)TT;
    MethodParameters:
      Name                           Flags
      other                          final

  public static org.sireum.Z$BV$Short $amp$(org.sireum.Z$BV$Short, org.sireum.Z$BV$Short);
    descriptor: (Lorg/sireum/Z$BV$Short;Lorg/sireum/Z$BV$Short;)Lorg/sireum/Z$BV$Short;
    flags: (0x1009) ACC_PUBLIC, ACC_STATIC, ACC_SYNTHETIC
    Code:
      stack=2, locals=2, args_size=2
         0: aload_0
         1: aload_1
         2: invokespecial #303                // InterfaceMethod $amp:(Lorg/sireum/Z$BV$Short;)Lorg/sireum/Z$BV$Short;
         5: areturn
      LineNumberTable:
        line 719: 0
      LocalVariableTable:
        Start  Length  Slot  Name   Signature
            0       6     0 $this   Lorg/sireum/Z$BV$Short;
            0       6     1 other   Lorg/sireum/Z$BV$Short;
    MethodParameters:
      Name                           Flags
      $this                          final synthetic
      other                          final

  public default T $amp(T);
    descriptor: (Lorg/sireum/Z$BV$Short;)Lorg/sireum/Z$BV$Short;
    flags: (0x0001) ACC_PUBLIC
    Code:
      stack=4, locals=2, args_size=2
         0: aload_0
         1: invokeinterface #170,  1          // InterfaceMethod isSigned:()Z
         6: ifeq          30
         9: aload_0
        10: aload_0
        11: invokeinterface #70,  1           // InterfaceMethod org$sireum$Z$BV$Short$$toShort:()S
        16: aload_1
        17: invokeinterface #70,  1           // InterfaceMethod org$sireum$Z$BV$Short$$toShort:()S
        22: iand
        23: i2s
        24: invokespecial #187                // InterfaceMethod makeShort:(I)Lorg/sireum/Z$BV$Short;
        27: goto          48
        30: aload_0
        31: getstatic     #77                 // Field org/sireum/Z$U$_16$.MODULE$:Lorg/sireum/Z$U$_16$;
        34: aload_0
        35: invokespecial #189                // InterfaceMethod toU16:()S
        38: aload_1
        39: invokespecial #189                // InterfaceMethod toU16:()S
        42: invokevirtual #306                // Method org/sireum/Z$U$_16$.$amp$extension:(SS)S
        45: invokespecial #194                // InterfaceMethod umake:(S)Lorg/sireum/Z$BV$Short;
        48: areturn
      StackMapTable: number_of_entries = 2
        frame_type = 30 /* same */
        frame_type = 81 /* same_locals_1_stack_item */
          stack = [ class org/sireum/Z$BV$Short ]
      LineNumberTable:
        line 720: 0
        line 721: 30
      LocalVariableTable:
        Start  Length  Slot  Name   Signature
            0      49     0  this   Lorg/sireum/Z$BV$Short;
            0      49     1 other   Lorg/sireum/Z$BV$Short;
    Signature: #201                         // (TT;)TT;
    MethodParameters:
      Name                           Flags
      other                          final

  public static org.sireum.Z$BV$Short $bar$(org.sireum.Z$BV$Short, org.sireum.Z$BV$Short);
    descriptor: (Lorg/sireum/Z$BV$Short;Lorg/sireum/Z$BV$Short;)Lorg/sireum/Z$BV$Short;
    flags: (0x1009) ACC_PUBLIC, ACC_STATIC, ACC_SYNTHETIC
    Code:
      stack=2, locals=2, args_size=2
         0: aload_0
         1: aload_1
         2: invokespecial #310                // InterfaceMethod $bar:(Lorg/sireum/Z$BV$Short;)Lorg/sireum/Z$BV$Short;
         5: areturn
      LineNumberTable:
        line 724: 0
      LocalVariableTable:
        Start  Length  Slot  Name   Signature
            0       6     0 $this   Lorg/sireum/Z$BV$Short;
            0       6     1 other   Lorg/sireum/Z$BV$Short;
    MethodParameters:
      Name                           Flags
      $this                          final synthetic
      other                          final

  public default T $bar(T);
    descriptor: (Lorg/sireum/Z$BV$Short;)Lorg/sireum/Z$BV$Short;
    flags: (0x0001) ACC_PUBLIC
    Code:
      stack=4, locals=2, args_size=2
         0: aload_0
         1: invokeinterface #170,  1          // InterfaceMethod isSigned:()Z
         6: ifeq          30
         9: aload_0
        10: aload_0
        11: invokeinterface #70,  1           // InterfaceMethod org$sireum$Z$BV$Short$$toShort:()S
        16: aload_1
        17: invokeinterface #70,  1           // InterfaceMethod org$sireum$Z$BV$Short$$toShort:()S
        22: ior
        23: i2s
        24: invokespecial #187                // InterfaceMethod makeShort:(I)Lorg/sireum/Z$BV$Short;
        27: goto          48
        30: aload_0
        31: getstatic     #77                 // Field org/sireum/Z$U$_16$.MODULE$:Lorg/sireum/Z$U$_16$;
        34: aload_0
        35: invokespecial #189                // InterfaceMethod toU16:()S
        38: aload_1
        39: invokespecial #189                // InterfaceMethod toU16:()S
        42: invokevirtual #313                // Method org/sireum/Z$U$_16$.$bar$extension:(SS)S
        45: invokespecial #194                // InterfaceMethod umake:(S)Lorg/sireum/Z$BV$Short;
        48: areturn
      StackMapTable: number_of_entries = 2
        frame_type = 30 /* same */
        frame_type = 81 /* same_locals_1_stack_item */
          stack = [ class org/sireum/Z$BV$Short ]
      LineNumberTable:
        line 725: 0
        line 726: 30
      LocalVariableTable:
        Start  Length  Slot  Name   Signature
            0      49     0  this   Lorg/sireum/Z$BV$Short;
            0      49     1 other   Lorg/sireum/Z$BV$Short;
    Signature: #201                         // (TT;)TT;
    MethodParameters:
      Name                           Flags
      other                          final

  public static org.sireum.Z$BV$Short $bar$up$(org.sireum.Z$BV$Short, org.sireum.Z$BV$Short);
    descriptor: (Lorg/sireum/Z$BV$Short;Lorg/sireum/Z$BV$Short;)Lorg/sireum/Z$BV$Short;
    flags: (0x1009) ACC_PUBLIC, ACC_STATIC, ACC_SYNTHETIC
    Code:
      stack=2, locals=2, args_size=2
         0: aload_0
         1: aload_1
         2: invokespecial #317                // InterfaceMethod $bar$up:(Lorg/sireum/Z$BV$Short;)Lorg/sireum/Z$BV$Short;
         5: areturn
      LineNumberTable:
        line 729: 0
      LocalVariableTable:
        Start  Length  Slot  Name   Signature
            0       6     0 $this   Lorg/sireum/Z$BV$Short;
            0       6     1 other   Lorg/sireum/Z$BV$Short;
    MethodParameters:
      Name                           Flags
      $this                          final synthetic
      other                          final

  public default T $bar$up(T);
    descriptor: (Lorg/sireum/Z$BV$Short;)Lorg/sireum/Z$BV$Short;
    flags: (0x0001) ACC_PUBLIC
    Code:
      stack=4, locals=2, args_size=2
         0: aload_0
         1: invokeinterface #170,  1          // InterfaceMethod isSigned:()Z
         6: ifeq          30
         9: aload_0
        10: aload_0
        11: invokeinterface #70,  1           // InterfaceMethod org$sireum$Z$BV$Short$$toShort:()S
        16: aload_1
        17: invokeinterface #70,  1           // InterfaceMethod org$sireum$Z$BV$Short$$toShort:()S
        22: ixor
        23: i2s
        24: invokespecial #187                // InterfaceMethod makeShort:(I)Lorg/sireum/Z$BV$Short;
        27: goto          48
        30: aload_0
        31: getstatic     #77                 // Field org/sireum/Z$U$_16$.MODULE$:Lorg/sireum/Z$U$_16$;
        34: aload_0
        35: invokespecial #189                // InterfaceMethod toU16:()S
        38: aload_1
        39: invokespecial #189                // InterfaceMethod toU16:()S
        42: invokevirtual #320                // Method org/sireum/Z$U$_16$.$up$extension:(SS)S
        45: invokespecial #194                // InterfaceMethod umake:(S)Lorg/sireum/Z$BV$Short;
        48: areturn
      StackMapTable: number_of_entries = 2
        frame_type = 30 /* same */
        frame_type = 81 /* same_locals_1_stack_item */
          stack = [ class org/sireum/Z$BV$Short ]
      LineNumberTable:
        line 730: 0
        line 731: 30
      LocalVariableTable:
        Start  Length  Slot  Name   Signature
            0      49     0  this   Lorg/sireum/Z$BV$Short;
            0      49     1 other   Lorg/sireum/Z$BV$Short;
    Signature: #201                         // (TT;)TT;
    MethodParameters:
      Name                           Flags
      other                          final

  public static org.sireum.Z$BV$Short unary_$tilde$(org.sireum.Z$BV$Short);
    descriptor: (Lorg/sireum/Z$BV$Short;)Lorg/sireum/Z$BV$Short;
    flags: (0x1009) ACC_PUBLIC, ACC_STATIC, ACC_SYNTHETIC
    Code:
      stack=1, locals=1, args_size=1
         0: aload_0
         1: invokespecial #324                // InterfaceMethod unary_$tilde:()Lorg/sireum/Z$BV$Short;
         4: areturn
      LineNumberTable:
        line 734: 0
      LocalVariableTable:
        Start  Length  Slot  Name   Signature
            0       5     0 $this   Lorg/sireum/Z$BV$Short;
    MethodParameters:
      Name                           Flags
      $this                          final synthetic

  public default T unary_$tilde();
    descriptor: ()Lorg/sireum/Z$BV$Short;
    flags: (0x0001) ACC_PUBLIC
    Code:
      stack=3, locals=1, args_size=1
         0: aload_0
         1: invokeinterface #170,  1          // InterfaceMethod isSigned:()Z
         6: ifeq          24
         9: aload_0
        10: aload_0
        11: invokeinterface #70,  1           // InterfaceMethod org$sireum$Z$BV$Short$$toShort:()S
        16: iconst_m1
        17: ixor
        18: invokespecial #187                // InterfaceMethod makeShort:(I)Lorg/sireum/Z$BV$Short;
        21: goto          38
        24: aload_0
        25: getstatic     #77                 // Field org/sireum/Z$U$_16$.MODULE$:Lorg/sireum/Z$U$_16$;
        28: aload_0
        29: invokespecial #189                // InterfaceMethod toU16:()S
        32: invokevirtual #327                // Method org/sireum/Z$U$_16$.unary_$tilde$extension:(S)S
        35: invokespecial #194                // InterfaceMethod umake:(S)Lorg/sireum/Z$BV$Short;
        38: areturn
      StackMapTable: number_of_entries = 2
        frame_type = 24 /* same */
        frame_type = 77 /* same_locals_1_stack_item */
          stack = [ class org/sireum/Z$BV$Short ]
      LineNumberTable:
        line 735: 0
        line 736: 24
      LocalVariableTable:
        Start  Length  Slot  Name   Signature
            0      39     0  this   Lorg/sireum/Z$BV$Short;
    Signature: #61                          // ()TT;

  public static org.sireum.Z$BV$Short increase$(org.sireum.Z$BV$Short);
    descriptor: (Lorg/sireum/Z$BV$Short;)Lorg/sireum/Z$BV$Short;
    flags: (0x1009) ACC_PUBLIC, ACC_STATIC, ACC_SYNTHETIC
    Code:
      stack=1, locals=1, args_size=1
         0: aload_0
         1: invokespecial #331                // InterfaceMethod increase:()Lorg/sireum/Z$BV$Short;
         4: areturn
      LineNumberTable:
        line 738: 0
      LocalVariableTable:
        Start  Length  Slot  Name   Signature
            0       5     0 $this   Lorg/sireum/Z$BV$Short;
    MethodParameters:
      Name                           Flags
      $this                          final synthetic

  public default T increase();
    descriptor: ()Lorg/sireum/Z$BV$Short;
    flags: (0x0001) ACC_PUBLIC
    Code:
      stack=5, locals=1, args_size=1
         0: aload_0
         1: invokeinterface #170,  1          // InterfaceMethod isSigned:()Z
         6: ifeq          24
         9: aload_0
        10: aload_0
        11: invokeinterface #70,  1           // InterfaceMethod org$sireum$Z$BV$Short$$toShort:()S
        16: iconst_1
        17: iadd
        18: invokespecial #187                // InterfaceMethod makeShort:(I)Lorg/sireum/Z$BV$Short;
        21: goto          45
        24: aload_0
        25: getstatic     #77                 // Field org/sireum/Z$U$_16$.MODULE$:Lorg/sireum/Z$U$_16$;
        28: aload_0
        29: invokespecial #189                // InterfaceMethod toU16:()S
        32: getstatic     #77                 // Field org/sireum/Z$U$_16$.MODULE$:Lorg/sireum/Z$U$_16$;
        35: iconst_1
        36: invokevirtual #173                // Method org/sireum/Z$U$_16$.apply:(I)S
        39: invokevirtual #208                // Method org/sireum/Z$U$_16$.$plus$extension:(SS)S
        42: invokespecial #194                // InterfaceMethod umake:(S)Lorg/sireum/Z$BV$Short;
        45: areturn
      StackMapTable: number_of_entries = 2
        frame_type = 24 /* same */
        frame_type = 84 /* same_locals_1_stack_item */
          stack = [ class org/sireum/Z$BV$Short ]
      LineNumberTable:
        line 739: 0
        line 740: 24
      LocalVariableTable:
        Start  Length  Slot  Name   Signature
            0      46     0  this   Lorg/sireum/Z$BV$Short;
    Signature: #61                          // ()TT;

  public static org.sireum.Z$BV$Short decrease$(org.sireum.Z$BV$Short);
    descriptor: (Lorg/sireum/Z$BV$Short;)Lorg/sireum/Z$BV$Short;
    flags: (0x1009) ACC_PUBLIC, ACC_STATIC, ACC_SYNTHETIC
    Code:
      stack=1, locals=1, args_size=1
         0: aload_0
         1: invokespecial #335                // InterfaceMethod decrease:()Lorg/sireum/Z$BV$Short;
         4: areturn
      LineNumberTable:
        line 742: 0
      LocalVariableTable:
        Start  Length  Slot  Name   Signature
            0       5     0 $this   Lorg/sireum/Z$BV$Short;
    MethodParameters:
      Name                           Flags
      $this                          final synthetic

  public default T decrease();
    descriptor: ()Lorg/sireum/Z$BV$Short;
    flags: (0x0001) ACC_PUBLIC
    Code:
      stack=5, locals=1, args_size=1
         0: aload_0
         1: invokeinterface #170,  1          // InterfaceMethod isSigned:()Z
         6: ifeq          24
         9: aload_0
        10: aload_0
        11: invokeinterface #70,  1           // InterfaceMethod org$sireum$Z$BV$Short$$toShort:()S
        16: iconst_1
        17: isub
        18: invokespecial #187                // InterfaceMethod makeShort:(I)Lorg/sireum/Z$BV$Short;
        21: goto          45
        24: aload_0
        25: getstatic     #77                 // Field org/sireum/Z$U$_16$.MODULE$:Lorg/sireum/Z$U$_16$;
        28: aload_0
        29: invokespecial #189                // InterfaceMethod toU16:()S
        32: getstatic     #77                 // Field org/sireum/Z$U$_16$.MODULE$:Lorg/sireum/Z$U$_16$;
        35: iconst_1
        36: invokevirtual #173                // Method org/sireum/Z$U$_16$.apply:(I)S
        39: invokevirtual #217                // Method org/sireum/Z$U$_16$.$minus$extension:(SS)S
        42: invokespecial #194                // InterfaceMethod umake:(S)Lorg/sireum/Z$BV$Short;
        45: areturn
      StackMapTable: number_of_entries = 2
        frame_type = 24 /* same */
        frame_type = 84 /* same_locals_1_stack_item */
          stack = [ class org/sireum/Z$BV$Short ]
      LineNumberTable:
        line 743: 0
        line 744: 24
      LocalVariableTable:
        Start  Length  Slot  Name   Signature
            0      46     0  this   Lorg/sireum/Z$BV$Short;
    Signature: #61                          // ()TT;

  public static java.lang.String toString$(org.sireum.Z$BV$Short);
    descriptor: (Lorg/sireum/Z$BV$Short;)Ljava/lang/String;
    flags: (0x1009) ACC_PUBLIC, ACC_STATIC, ACC_SYNTHETIC
    Code:
      stack=1, locals=1, args_size=1
         0: aload_0
         1: invokespecial #340                // InterfaceMethod toString:()Ljava/lang/String;
         4: areturn
      LineNumberTable:
        line 746: 0
      LocalVariableTable:
        Start  Length  Slot  Name   Signature
            0       5     0 $this   Lorg/sireum/Z$BV$Short;
    MethodParameters:
      Name                           Flags
      $this                          final synthetic

  public default java.lang.String toString();
    descriptor: ()Ljava/lang/String;
    flags: (0x0001) ACC_PUBLIC
    Code:
      stack=2, locals=1, args_size=1
         0: aload_0
         1: invokeinterface #170,  1          // InterfaceMethod isSigned:()Z
         6: ifeq          21
         9: aload_0
        10: invokeinterface #70,  1           // InterfaceMethod org$sireum$Z$BV$Short$$toShort:()S
        15: invokestatic  #345                // Method java/lang/Short.toString:(S)Ljava/lang/String;
        18: goto          31
        21: getstatic     #77                 // Field org/sireum/Z$U$_16$.MODULE$:Lorg/sireum/Z$U$_16$;
        24: aload_0
        25: invokespecial #189                // InterfaceMethod toU16:()S
        28: invokevirtual #348                // Method org/sireum/Z$U$_16$.toString$extension:(S)Ljava/lang/String;
        31: areturn
      StackMapTable: number_of_entries = 2
        frame_type = 21 /* same */
        frame_type = 73 /* same_locals_1_stack_item */
          stack = [ class java/lang/String ]
      LineNumberTable:
        line 747: 0
        line 748: 24
      LocalVariableTable:
        Start  Length  Slot  Name   Signature
            0      32     0  this   Lorg/sireum/Z$BV$Short;

  public static scala.math.BigInt toBigInt$(org.sireum.Z$BV$Short);
    descriptor: (Lorg/sireum/Z$BV$Short;)Lscala/math/BigInt;
    flags: (0x1009) ACC_PUBLIC, ACC_STATIC, ACC_SYNTHETIC
    Code:
      stack=1, locals=1, args_size=1
         0: aload_0
         1: invokespecial #355                // InterfaceMethod toBigInt:()Lscala/math/BigInt;
         4: areturn
      LineNumberTable:
        line 750: 0
      LocalVariableTable:
        Start  Length  Slot  Name   Signature
            0       5     0 $this   Lorg/sireum/Z$BV$Short;
    MethodParameters:
      Name                           Flags
      $this                          final synthetic

  public default scala.math.BigInt toBigInt();
    descriptor: ()Lscala/math/BigInt;
    flags: (0x0001) ACC_PUBLIC
    Code:
      stack=3, locals=1, args_size=1
         0: aload_0
         1: invokeinterface #170,  1          // InterfaceMethod isSigned:()Z
         6: ifeq          27
         9: getstatic     #360                // Field scala/package$.MODULE$:Lscala/package$;
        12: invokevirtual #363                // Method scala/package$.BigInt:()Lscala/math/BigInt$;
        15: aload_0
        16: invokeinterface #70,  1           // InterfaceMethod org$sireum$Z$BV$Short$$toShort:()S
        21: invokevirtual #368                // Method scala/math/BigInt$.apply:(I)Lscala/math/BigInt;
        24: goto          48
        27: getstatic     #373                // Field org/sireum/Z$.MODULE$:Lorg/sireum/Z$;
        30: getstatic     #77                 // Field org/sireum/Z$U$_16$.MODULE$:Lorg/sireum/Z$U$_16$;
        33: aload_0
        34: invokespecial #189                // InterfaceMethod toU16:()S
        37: invokevirtual #288                // Method org/sireum/Z$U$_16$.toInt$extension:(S)I
        40: invokevirtual #376                // Method org/sireum/Z$.apply:(I)Lorg/sireum/Z;
        43: invokeinterface #377,  1          // InterfaceMethod org/sireum/Z.toBigInt:()Lscala/math/BigInt;
        48: areturn
      StackMapTable: number_of_entries = 2
        frame_type = 27 /* same */
        frame_type = 84 /* same_locals_1_stack_item */
          stack = [ class scala/math/BigInt ]
      LineNumberTable:
        line 751: 0
        line 752: 27
      LocalVariableTable:
        Start  Length  Slot  Name   Signature
            0      49     0  this   Lorg/sireum/Z$BV$Short;

  public static org.sireum.Z toMP$(org.sireum.Z$BV$Short);
    descriptor: (Lorg/sireum/Z$BV$Short;)Lorg/sireum/Z;
    flags: (0x1009) ACC_PUBLIC, ACC_STATIC, ACC_SYNTHETIC
    Code:
      stack=1, locals=1, args_size=1
         0: aload_0
         1: invokespecial #99                 // InterfaceMethod toMP:()Lorg/sireum/Z;
         4: areturn
      LineNumberTable:
        line 754: 0
      LocalVariableTable:
        Start  Length  Slot  Name   Signature
            0       5     0 $this   Lorg/sireum/Z$BV$Short;
    MethodParameters:
      Name                           Flags
      $this                          final synthetic

  public default org.sireum.Z toMP();
    descriptor: ()Lorg/sireum/Z;
    flags: (0x0001) ACC_PUBLIC
    Code:
      stack=3, locals=1, args_size=1
         0: aload_0
         1: invokeinterface #170,  1          // InterfaceMethod isSigned:()Z
         6: ifeq          24
         9: getstatic     #382                // Field org/sireum/Z$MP$.MODULE$:Lorg/sireum/Z$MP$;
        12: aload_0
        13: invokeinterface #70,  1           // InterfaceMethod org$sireum$Z$BV$Short$$toShort:()S
        18: invokevirtual #383                // Method org/sireum/Z$MP$.apply:(I)Lorg/sireum/Z;
        21: goto          40
        24: getstatic     #382                // Field org/sireum/Z$MP$.MODULE$:Lorg/sireum/Z$MP$;
        27: getstatic     #77                 // Field org/sireum/Z$U$_16$.MODULE$:Lorg/sireum/Z$U$_16$;
        30: aload_0
        31: invokespecial #189                // InterfaceMethod toU16:()S
        34: invokevirtual #288                // Method org/sireum/Z$U$_16$.toInt$extension:(S)I
        37: invokevirtual #383                // Method org/sireum/Z$MP$.apply:(I)Lorg/sireum/Z;
        40: areturn
      StackMapTable: number_of_entries = 2
        frame_type = 24 /* same */
        frame_type = 79 /* same_locals_1_stack_item */
          stack = [ class org/sireum/Z ]
      LineNumberTable:
        line 755: 0
        line 756: 24
      LocalVariableTable:
        Start  Length  Slot  Name   Signature
            0      41     0  this   Lorg/sireum/Z$BV$Short;

  public static org.sireum.Z toIndex$(org.sireum.Z$BV$Short);
    descriptor: (Lorg/sireum/Z$BV$Short;)Lorg/sireum/Z;
    flags: (0x1009) ACC_PUBLIC, ACC_STATIC, ACC_SYNTHETIC
    Code:
      stack=1, locals=1, args_size=1
         0: aload_0
         1: invokespecial #387                // InterfaceMethod toIndex:()Lorg/sireum/Z;
         4: areturn
      LineNumberTable:
        line 758: 0
      LocalVariableTable:
        Start  Length  Slot  Name   Signature
            0       5     0 $this   Lorg/sireum/Z$BV$Short;
    MethodParameters:
      Name                           Flags
      $this                          final synthetic

  public default org.sireum.Z toIndex();
    descriptor: ()Lorg/sireum/Z;
    flags: (0x0001) ACC_PUBLIC
    Code:
      stack=2, locals=1, args_size=1
         0: aload_0
         1: invokeinterface #389,  1          // InterfaceMethod isZeroIndex:()Z
         6: ifeq          18
         9: aload_0
        10: invokeinterface #99,  1           // InterfaceMethod toMP:()Lorg/sireum/Z;
        15: goto          40
        18: aload_0
        19: invokeinterface #99,  1           // InterfaceMethod toMP:()Lorg/sireum/Z;
        24: aload_0
        25: invokeinterface #391,  1          // InterfaceMethod Index:()Lorg/sireum/Z$BV$Short;
        30: invokeinterface #99,  1           // InterfaceMethod toMP:()Lorg/sireum/Z;
        35: invokeinterface #214,  2          // InterfaceMethod org/sireum/Z.$minus:(Lorg/sireum/Z;)Lorg/sireum/Z;
        40: areturn
      StackMapTable: number_of_entries = 2
        frame_type = 18 /* same */
        frame_type = 85 /* same_locals_1_stack_item */
          stack = [ class org/sireum/Z ]
      LineNumberTable:
        line 759: 0
      LocalVariableTable:
        Start  Length  Slot  Name   Signature
            0      41     0  this   Lorg/sireum/Z$BV$Short;

  public static java.lang.String $anonfun$make$3(org.sireum.Z$BV$Short, org.sireum.Z);
    descriptor: (Lorg/sireum/Z$BV$Short;Lorg/sireum/Z;)Ljava/lang/String;
    flags: (0x1009) ACC_PUBLIC, ACC_STATIC, ACC_SYNTHETIC
    Code:
      stack=3, locals=2, args_size=2
         0: new           #394                // class java/lang/StringBuilder
         3: dup
         4: ldc_w         #395                // int 32
         7: invokespecial #398                // Method java/lang/StringBuilder."<init>":(I)V
        10: aload_1
        11: invokevirtual #402                // Method java/lang/StringBuilder.append:(Ljava/lang/Object;)Ljava/lang/StringBuilder;
        14: ldc_w         #404                // String  should not be less than
        17: invokevirtual #407                // Method java/lang/StringBuilder.append:(Ljava/lang/String;)Ljava/lang/StringBuilder;
        20: aload_0
        21: invokeinterface #410,  1          // InterfaceMethod Name:()Ljava/lang/String;
        26: invokevirtual #407                // Method java/lang/StringBuilder.append:(Ljava/lang/String;)Ljava/lang/StringBuilder;
        29: ldc_w         #412                // String .Min (
        32: invokevirtual #407                // Method java/lang/StringBuilder.append:(Ljava/lang/String;)Ljava/lang/StringBuilder;
        35: aload_0
        36: invokeinterface #95,  1           // InterfaceMethod Min:()Lorg/sireum/Z$BV$Short;
        41: invokevirtual #402                // Method java/lang/StringBuilder.append:(Ljava/lang/Object;)Ljava/lang/StringBuilder;
        44: ldc_w         #414                // String )
        47: invokevirtual #407                // Method java/lang/StringBuilder.append:(Ljava/lang/String;)Ljava/lang/StringBuilder;
        50: invokevirtual #415                // Method java/lang/StringBuilder.toString:()Ljava/lang/String;
        53: areturn
      LineNumberTable:
        line 636: 0
      LocalVariableTable:
        Start  Length  Slot  Name   Signature
            0      54     0 $this   Lorg/sireum/Z$BV$Short;
            0      54     1 value$2   Lorg/sireum/Z;
    MethodParameters:
      Name                           Flags
      $this                          final synthetic
      value$2                        final

  public static java.lang.String $anonfun$make$4(org.sireum.Z$BV$Short, org.sireum.Z);
    descriptor: (Lorg/sireum/Z$BV$Short;Lorg/sireum/Z;)Ljava/lang/String;
    flags: (0x1009) ACC_PUBLIC, ACC_STATIC, ACC_SYNTHETIC
    Code:
      stack=3, locals=2, args_size=2
         0: new           #394                // class java/lang/StringBuilder
         3: dup
         4: ldc_w         #416                // int 35
         7: invokespecial #398                // Method java/lang/StringBuilder."<init>":(I)V
        10: aload_1
        11: invokevirtual #402                // Method java/lang/StringBuilder.append:(Ljava/lang/Object;)Ljava/lang/StringBuilder;
        14: ldc_w         #418                // String  should not be greater than
        17: invokevirtual #407                // Method java/lang/StringBuilder.append:(Ljava/lang/String;)Ljava/lang/StringBuilder;
        20: aload_0
        21: invokeinterface #410,  1          // InterfaceMethod Name:()Ljava/lang/String;
        26: invokevirtual #407                // Method java/lang/StringBuilder.append:(Ljava/lang/String;)Ljava/lang/StringBuilder;
        29: ldc_w         #420                // String .Max (
        32: invokevirtual #407                // Method java/lang/StringBuilder.append:(Ljava/lang/String;)Ljava/lang/StringBuilder;
        35: aload_0
        36: invokeinterface #134,  1          // InterfaceMethod Max:()Lorg/sireum/Z$BV$Short;
        41: invokevirtual #402                // Method java/lang/StringBuilder.append:(Ljava/lang/Object;)Ljava/lang/StringBuilder;
        44: ldc_w         #414                // String )
        47: invokevirtual #407                // Method java/lang/StringBuilder.append:(Ljava/lang/String;)Ljava/lang/StringBuilder;
        50: invokevirtual #415                // Method java/lang/StringBuilder.toString:()Ljava/lang/String;
        53: areturn
      LineNumberTable:
        line 637: 0
      LocalVariableTable:
        Start  Length  Slot  Name   Signature
            0      54     0 $this   Lorg/sireum/Z$BV$Short;
            0      54     1 value$2   Lorg/sireum/Z;
    MethodParameters:
      Name                           Flags
      $this                          final synthetic
      value$2                        final

  public static void $init$(org.sireum.Z$BV$Short);
    descriptor: (Lorg/sireum/Z$BV$Short;)V
    flags: (0x0009) ACC_PUBLIC, ACC_STATIC
    Code:
      stack=0, locals=1, args_size=1
         0: return
      LineNumberTable:
        line 608: 0
      LocalVariableTable:
        Start  Length  Slot  Name   Signature
            0       1     0 $this   Lorg/sireum/Z$BV$Short;
    MethodParameters:
      Name                           Flags
      $this                          final synthetic

  private static java.lang.Object $deserializeLambda$(java.lang.invoke.SerializedLambda);
    descriptor: (Ljava/lang/invoke/SerializedLambda;)Ljava/lang/Object;
    flags: (0x100a) ACC_PRIVATE, ACC_STATIC, ACC_SYNTHETIC
    Code:
      stack=1, locals=1, args_size=1
         0: aload_0
         1: invokedynamic #434,  0            // InvokeDynamic #2:lambdaDeserialize:(Ljava/lang/invoke/SerializedLambda;)Ljava/lang/Object;
         6: areturn
}
InnerClasses:
  public static final #15= #12 of #14;    // Lookup=class java/lang/invoke/MethodHandles$Lookup of class java/lang/invoke/MethodHandles
  public static #20= #17 of #19;          // BV$=class org/sireum/Z$BV$ of class org/sireum/Z
  public static #21= #2 of #17;           // Short=class org/sireum/Z$BV$Short of class org/sireum/Z$BV$
  public static #24= #23 of #19;          // MP$=class org/sireum/Z$MP$ of class org/sireum/Z
  public static final #27= #26 of #23;    // BigInt=class org/sireum/Z$MP$BigInt of class org/sireum/Z$MP$
  public static final #30= #29 of #23;    // Long=class org/sireum/Z$MP$Long of class org/sireum/Z$MP$
  public static #33= #32 of #19;          // U$=class org/sireum/Z$U$ of class org/sireum/Z
  public static #36= #35 of #32;          // _16$=class org/sireum/Z$U$_16$ of class org/sireum/Z$U$
Signature: #3                           // <T::Lorg/sireum/Z$BV$Short<TT;>;>Ljava/lang/Object;Lorg/sireum/ZLike<TT;>;Lorg/sireum/$internal/HasBoxer;
SourceFile: "Z.scala"
BootstrapMethods:
  0: #125 REF_invokeStatic java/lang/invoke/LambdaMetafactory.altMetafactory:(Ljava/lang/invoke/MethodHandles$Lookup;Ljava/lang/String;Ljava/lang/invoke/MethodType;[Ljava/lang/Object;)Ljava/lang/invoke/CallSite;
    Method arguments:
      #109 ()Ljava/lang/Object;
      #114 REF_invokeStatic org/sireum/Z$BV$Short.$anonfun$make$3:(Lorg/sireum/Z$BV$Short;Lorg/sireum/Z;)Ljava/lang/String;
      #116 ()Ljava/lang/String;
      #117 5
      #118 1
      #116 ()Ljava/lang/String;
  1: #125 REF_invokeStatic java/lang/invoke/LambdaMetafactory.altMetafactory:(Ljava/lang/invoke/MethodHandles$Lookup;Ljava/lang/String;Ljava/lang/invoke/MethodType;[Ljava/lang/Object;)Ljava/lang/invoke/CallSite;
    Method arguments:
      #109 ()Ljava/lang/Object;
      #138 REF_invokeStatic org/sireum/Z$BV$Short.$anonfun$make$4:(Lorg/sireum/Z$BV$Short;Lorg/sireum/Z;)Ljava/lang/String;
      #116 ()Ljava/lang/String;
      #117 5
      #118 1
      #116 ()Ljava/lang/String;
  2: #431 REF_invokeStatic scala/runtime/LambdaDeserialize.bootstrap:(Ljava/lang/invoke/MethodHandles$Lookup;Ljava/lang/String;Ljava/lang/invoke/MethodType;[Ljava/lang/invoke/MethodHandle;)Ljava/lang/invoke/CallSite;
    Method arguments:
      #114 REF_invokeStatic org/sireum/Z$BV$Short.$anonfun$make$3:(Lorg/sireum/Z$BV$Short;Lorg/sireum/Z;)Ljava/lang/String;
      #138 REF_invokeStatic org/sireum/Z$BV$Short.$anonfun$make$4:(Lorg/sireum/Z$BV$Short;Lorg/sireum/Z;)Ljava/lang/String;
  ScalaInlineInfo: length = 0x158 (unknown attribute)
   01 00 00 44 01 2D 00 B0 01 01 2C 00 C4 01 00 6E
   00 6F 01 00 87 00 6F 01 01 34 00 B0 01 01 33 00
   C4 01 01 3B 00 B0 01 01 3A 00 C4 01 00 E4 00 B0
   01 00 E3 00 C4 01 00 F7 00 26 01 00 F5 00 F6 01
   01 02 00 26 01 01 01 00 F6 01 01 16 00 B0 01 01
   15 00 C4 01 01 19 00 B0 01 01 1C 00 C4 01 01 A5
   01 A6 01 01 09 00 26 01 01 08 00 F6 01 00 64 00
   26 01 01 0F 00 F6 01 01 26 00 B0 01 01 25 00 C4
   01 00 D2 00 B0 01 00 D1 00 C4 01 00 ED 00 B0 01
   00 EC 00 C4 01 00 C6 00 B0 01 00 C3 00 C4 01 00
   DB 00 B0 01 00 DA 00 C4 01 00 3F 00 3C 00 00 3E
   00 3C 00 00 3B 00 3C 00 01 4D 00 3C 01 01 4C 00
   B0 01 00 33 00 29 01 00 32 00 26 01 00 2F 00 29
   01 00 2E 00 26 01 01 49 00 3C 01 01 48 00 B0 01
   00 28 00 29 01 00 25 00 26 01 00 41 00 29 00 00
   40 00 29 00 00 38 00 52 05 00 38 00 39 00 00 A5
   00 A6 05 00 44 00 37 05 00 42 00 43 05 01 61 00
   8F 01 01 5F 01 60 01 01 81 00 61 01 01 80 01 7B
   01 00 60 00 61 01 01 7A 01 7B 01 01 52 00 73 01
   01 50 01 51 01 00 49 00 37 05 00 A3 00 39 05 00
   B1 00 3C 01 00 AF 00 B0 01 01 42 00 3C 01 01 41
   00 B0 01 00 36 00 37 00
  Scala: length = 0x0 (unknown attribute)

