Classfile /Users/mw/Projects/slang-braindump/.jar/jar11/assemble/slang-braindump/assemble/content/org/sireum/Z$MP$Long$.class
  Last modified May 29, 2022; size 1874 bytes
  SHA-256 checksum 242b85096d842b608e5361f77c392ff97e1c5cbfbefb1e875703e6223b53bfa5
  Compiled from "Z.scala"
public class org.sireum.Z$MP$Long$ extends scala.runtime.AbstractFunction1<java.lang.Object, org.sireum.Z$MP$Long> implements java.io.Serializable
  minor version: 0
  major version: 52
  flags: (0x0021) ACC_PUBLIC, ACC_SUPER
  this_class: #2                          // org/sireum/Z$MP$Long$
  super_class: #5                         // scala/runtime/AbstractFunction1
  interfaces: 1, fields: 1, methods: 7, attributes: 5
Constant pool:
   #1 = Utf8               org/sireum/Z$MP$Long$
   #2 = Class              #1             // org/sireum/Z$MP$Long$
   #3 = Utf8               Lscala/runtime/AbstractFunction1<Ljava/lang/Object;Lorg/sireum/Z$MP$Long;>;Ljava/io/Serializable;
   #4 = Utf8               scala/runtime/AbstractFunction1
   #5 = Class              #4             // scala/runtime/AbstractFunction1
   #6 = Utf8               java/io/Serializable
   #7 = Class              #6             // java/io/Serializable
   #8 = Utf8               Z.scala
   #9 = Utf8               org/sireum/Z$MP$
  #10 = Class              #9             // org/sireum/Z$MP$
  #11 = Utf8               org/sireum/Z
  #12 = Class              #11            // org/sireum/Z
  #13 = Utf8               MP$
  #14 = Utf8               org/sireum/Z$MP$Long
  #15 = Class              #14            // org/sireum/Z$MP$Long
  #16 = Utf8               Long
  #17 = Utf8               Long$
  #18 = Utf8               MODULE$
  #19 = Utf8               Lorg/sireum/Z$MP$Long$;
  #20 = Utf8               <clinit>
  #21 = Utf8               ()V
  #22 = Utf8               <init>
  #23 = NameAndType        #22:#21        // "<init>":()V
  #24 = Methodref          #2.#23         // org/sireum/Z$MP$Long$."<init>":()V
  #25 = NameAndType        #18:#19        // MODULE$:Lorg/sireum/Z$MP$Long$;
  #26 = Fieldref           #2.#25         // org/sireum/Z$MP$Long$.MODULE$:Lorg/sireum/Z$MP$Long$;
  #27 = Utf8               toString
  #28 = Utf8               ()Ljava/lang/String;
  #29 = String             #16            // Long
  #30 = Utf8               this
  #31 = Utf8               apply
  #32 = Utf8               (J)Lorg/sireum/Z$MP$Long;
  #33 = Utf8               value
  #34 = Utf8               (J)V
  #35 = NameAndType        #22:#34        // "<init>":(J)V
  #36 = Methodref          #15.#35        // org/sireum/Z$MP$Long."<init>":(J)V
  #37 = Utf8               J
  #38 = Utf8               unapply
  #39 = Utf8               (Lorg/sireum/Z$MP$Long;)Lscala/Option;
  #40 = Utf8               (Lorg/sireum/Z$MP$Long;)Lscala/Option<Ljava/lang/Object;>;
  #41 = Utf8               x$0
  #42 = Utf8               scala/None$
  #43 = Class              #42            // scala/None$
  #44 = Utf8               Lscala/None$;
  #45 = NameAndType        #18:#44        // MODULE$:Lscala/None$;
  #46 = Fieldref           #43.#45        // scala/None$.MODULE$:Lscala/None$;
  #47 = Utf8               scala/Some
  #48 = Class              #47            // scala/Some
  #49 = Utf8               ()J
  #50 = NameAndType        #33:#49        // value:()J
  #51 = Methodref          #15.#50        // org/sireum/Z$MP$Long.value:()J
  #52 = Utf8               scala/runtime/BoxesRunTime
  #53 = Class              #52            // scala/runtime/BoxesRunTime
  #54 = Utf8               boxToLong
  #55 = Utf8               (J)Ljava/lang/Long;
  #56 = NameAndType        #54:#55        // boxToLong:(J)Ljava/lang/Long;
  #57 = Methodref          #53.#56        // scala/runtime/BoxesRunTime.boxToLong:(J)Ljava/lang/Long;
  #58 = Utf8               (Ljava/lang/Object;)V
  #59 = NameAndType        #22:#58        // "<init>":(Ljava/lang/Object;)V
  #60 = Methodref          #48.#59        // scala/Some."<init>":(Ljava/lang/Object;)V
  #61 = Utf8               Lorg/sireum/Z$MP$Long;
  #62 = Utf8               scala/Option
  #63 = Class              #62            // scala/Option
  #64 = Utf8               writeReplace
  #65 = Utf8               ()Ljava/lang/Object;
  #66 = Utf8               scala/runtime/ModuleSerializationProxy
  #67 = Class              #66            // scala/runtime/ModuleSerializationProxy
  #68 = Utf8               (Ljava/lang/Class;)V
  #69 = NameAndType        #22:#68        // "<init>":(Ljava/lang/Class;)V
  #70 = Methodref          #67.#69        // scala/runtime/ModuleSerializationProxy."<init>":(Ljava/lang/Class;)V
  #71 = Utf8               (Ljava/lang/Object;)Ljava/lang/Object;
  #72 = Utf8               v1
  #73 = Utf8               unboxToLong
  #74 = Utf8               (Ljava/lang/Object;)J
  #75 = NameAndType        #73:#74        // unboxToLong:(Ljava/lang/Object;)J
  #76 = Methodref          #53.#75        // scala/runtime/BoxesRunTime.unboxToLong:(Ljava/lang/Object;)J
  #77 = NameAndType        #31:#32        // apply:(J)Lorg/sireum/Z$MP$Long;
  #78 = Methodref          #2.#77         // org/sireum/Z$MP$Long$.apply:(J)Lorg/sireum/Z$MP$Long;
  #79 = Utf8               Ljava/lang/Object;
  #80 = Methodref          #5.#23         // scala/runtime/AbstractFunction1."<init>":()V
  #81 = Utf8               Code
  #82 = Utf8               LineNumberTable
  #83 = Utf8               LocalVariableTable
  #84 = Utf8               MethodParameters
  #85 = Utf8               StackMapTable
  #86 = Utf8               Signature
  #87 = Utf8               InnerClasses
  #88 = Utf8               SourceFile
  #89 = Utf8               ScalaInlineInfo
  #90 = Utf8               Scala
{
  public static final org.sireum.Z$MP$Long$ MODULE$;
    descriptor: Lorg/sireum/Z$MP$Long$;
    flags: (0x0019) ACC_PUBLIC, ACC_STATIC, ACC_FINAL

  public static {};
    descriptor: ()V
    flags: (0x0009) ACC_PUBLIC, ACC_STATIC
    Code:
      stack=2, locals=0, args_size=0
         0: new           #2                  // class org/sireum/Z$MP$Long$
         3: dup
         4: invokespecial #24                 // Method "<init>":()V
         7: putstatic     #26                 // Field MODULE$:Lorg/sireum/Z$MP$Long$;
        10: return
      LineNumberTable:
        line 41: 0

  public final java.lang.String toString();
    descriptor: ()Ljava/lang/String;
    flags: (0x0011) ACC_PUBLIC, ACC_FINAL
    Code:
      stack=1, locals=1, args_size=1
         0: ldc           #29                 // String Long
         2: areturn
      LineNumberTable:
        line 41: 0
      LocalVariableTable:
        Start  Length  Slot  Name   Signature
            0       3     0  this   Lorg/sireum/Z$MP$Long$;

  public org.sireum.Z$MP$Long apply(long);
    descriptor: (J)Lorg/sireum/Z$MP$Long;
    flags: (0x0001) ACC_PUBLIC
    Code:
      stack=4, locals=3, args_size=2
         0: new           #15                 // class org/sireum/Z$MP$Long
         3: dup
         4: lload_1
         5: invokespecial #36                 // Method org/sireum/Z$MP$Long."<init>":(J)V
         8: areturn
      LineNumberTable:
        line 41: 0
      LocalVariableTable:
        Start  Length  Slot  Name   Signature
            0       9     0  this   Lorg/sireum/Z$MP$Long$;
            0       9     1 value   J
    MethodParameters:
      Name                           Flags
      value                          final

  public scala.Option<java.lang.Object> unapply(org.sireum.Z$MP$Long);
    descriptor: (Lorg/sireum/Z$MP$Long;)Lscala/Option;
    flags: (0x0001) ACC_PUBLIC
    Code:
      stack=4, locals=2, args_size=2
         0: aload_1
         1: ifnonnull     10
         4: getstatic     #46                 // Field scala/None$.MODULE$:Lscala/None$;
         7: goto          24
        10: new           #48                 // class scala/Some
        13: dup
        14: aload_1
        15: invokevirtual #51                 // Method org/sireum/Z$MP$Long.value:()J
        18: invokestatic  #57                 // Method scala/runtime/BoxesRunTime.boxToLong:(J)Ljava/lang/Long;
        21: invokespecial #60                 // Method scala/Some."<init>":(Ljava/lang/Object;)V
        24: areturn
      StackMapTable: number_of_entries = 2
        frame_type = 10 /* same */
        frame_type = 77 /* same_locals_1_stack_item */
          stack = [ class scala/Option ]
      LineNumberTable:
        line 41: 0
      LocalVariableTable:
        Start  Length  Slot  Name   Signature
            0      25     0  this   Lorg/sireum/Z$MP$Long$;
            0      25     1   x$0   Lorg/sireum/Z$MP$Long;
    Signature: #40                          // (Lorg/sireum/Z$MP$Long;)Lscala/Option<Ljava/lang/Object;>;
    MethodParameters:
      Name                           Flags
      x$0                            final

  private java.lang.Object writeReplace();
    descriptor: ()Ljava/lang/Object;
    flags: (0x0002) ACC_PRIVATE
    Code:
      stack=3, locals=1, args_size=1
         0: new           #67                 // class scala/runtime/ModuleSerializationProxy
         3: dup
         4: ldc           #2                  // class org/sireum/Z$MP$Long$
         6: invokespecial #70                 // Method scala/runtime/ModuleSerializationProxy."<init>":(Ljava/lang/Class;)V
         9: areturn
      LineNumberTable:
        line 41: 0
      LocalVariableTable:
        Start  Length  Slot  Name   Signature
            0      10     0  this   Lorg/sireum/Z$MP$Long$;

  public java.lang.Object apply(java.lang.Object);
    descriptor: (Ljava/lang/Object;)Ljava/lang/Object;
    flags: (0x1041) ACC_PUBLIC, ACC_BRIDGE, ACC_SYNTHETIC
    Code:
      stack=3, locals=2, args_size=2
         0: aload_0
         1: aload_1
         2: invokestatic  #76                 // Method scala/runtime/BoxesRunTime.unboxToLong:(Ljava/lang/Object;)J
         5: invokevirtual #78                 // Method apply:(J)Lorg/sireum/Z$MP$Long;
         8: areturn
      LineNumberTable:
        line 41: 0
      LocalVariableTable:
        Start  Length  Slot  Name   Signature
            0       9     0  this   Lorg/sireum/Z$MP$Long$;
            0       9     1    v1   Ljava/lang/Object;
    MethodParameters:
      Name                           Flags
      v1                             final

  public org.sireum.Z$MP$Long$();
    descriptor: ()V
    flags: (0x0001) ACC_PUBLIC
    Code:
      stack=1, locals=1, args_size=1
         0: aload_0
         1: invokespecial #80                 // Method scala/runtime/AbstractFunction1."<init>":()V
         4: return
      LineNumberTable:
        line 41: 0
      LocalVariableTable:
        Start  Length  Slot  Name   Signature
            0       5     0  this   Lorg/sireum/Z$MP$Long$;
}
InnerClasses:
  public static #13= #10 of #12;          // MP$=class org/sireum/Z$MP$ of class org/sireum/Z
  public static final #16= #15 of #10;    // Long=class org/sireum/Z$MP$Long of class org/sireum/Z$MP$
  public static #17= #2 of #10;           // Long$=class org/sireum/Z$MP$Long$ of class org/sireum/Z$MP$
Signature: #3                           // Lscala/runtime/AbstractFunction1<Ljava/lang/Object;Lorg/sireum/Z$MP$Long;>;Ljava/io/Serializable;
SourceFile: "Z.scala"
  ScalaInlineInfo: length = 0x22 (unknown attribute)
   01 01 00 06 00 16 00 15 01 00 1F 00 20 01 00 1F
   00 47 01 00 1B 00 1C 01 00 26 00 27 01 00 40 00
   41 01
  Scala: length = 0x0 (unknown attribute)

