Classfile /Users/mw/Projects/slang-braindump/.jar/jar11/assemble/slang-braindump/assemble/content/org/sireum/Z$U$_64.class
  Last modified May 29, 2022; size 3655 bytes
  SHA-256 checksum 612b26487d0501d3bbc4b4825fae320c0aff7541d6e4f2283a855d87f2ad8ce6
  Compiled from "Z.scala"
public final class org.sireum.Z$U$_64
  minor version: 0
  major version: 52
  flags: (0x0031) ACC_PUBLIC, ACC_FINAL, ACC_SUPER
  this_class: #2                          // org/sireum/Z$U$_64
  super_class: #4                         // java/lang/Object
  interfaces: 0, fields: 1, methods: 23, attributes: 4
Constant pool:
    #1 = Utf8               org/sireum/Z$U$_64
    #2 = Class              #1            // org/sireum/Z$U$_64
    #3 = Utf8               java/lang/Object
    #4 = Class              #3            // java/lang/Object
    #5 = Utf8               Z.scala
    #6 = Utf8               org/sireum/Z$U$
    #7 = Class              #6            // org/sireum/Z$U$
    #8 = Utf8               org/sireum/Z
    #9 = Class              #8            // org/sireum/Z
   #10 = Utf8               U$
   #11 = Utf8               _64
   #12 = Utf8               org/sireum/Z$U$_64$
   #13 = Class              #12           // org/sireum/Z$U$_64$
   #14 = Utf8               _64$
   #15 = Utf8               value
   #16 = Utf8               J
   #17 = Utf8               ()J
   #18 = NameAndType        #15:#16       // value:J
   #19 = Fieldref           #2.#18        // org/sireum/Z$U$_64.value:J
   #20 = Utf8               this
   #21 = Utf8               Lorg/sireum/Z$U$_64;
   #22 = Utf8               unary_$minus
   #23 = Utf8               MODULE$
   #24 = Utf8               Lorg/sireum/Z$U$_64$;
   #25 = NameAndType        #23:#24       // MODULE$:Lorg/sireum/Z$U$_64$;
   #26 = Fieldref           #13.#25       // org/sireum/Z$U$_64$.MODULE$:Lorg/sireum/Z$U$_64$;
   #27 = NameAndType        #15:#17       // value:()J
   #28 = Methodref          #2.#27        // org/sireum/Z$U$_64.value:()J
   #29 = Utf8               unary_$minus$extension
   #30 = Utf8               (J)J
   #31 = NameAndType        #29:#30       // unary_$minus$extension:(J)J
   #32 = Methodref          #13.#31       // org/sireum/Z$U$_64$.unary_$minus$extension:(J)J
   #33 = Utf8               unary_$tilde
   #34 = Utf8               unary_$tilde$extension
   #35 = NameAndType        #34:#30       // unary_$tilde$extension:(J)J
   #36 = Methodref          #13.#35       // org/sireum/Z$U$_64$.unary_$tilde$extension:(J)J
   #37 = Utf8               $plus
   #38 = Utf8               other
   #39 = Utf8               $plus$extension
   #40 = Utf8               (JJ)J
   #41 = NameAndType        #39:#40       // $plus$extension:(JJ)J
   #42 = Methodref          #13.#41       // org/sireum/Z$U$_64$.$plus$extension:(JJ)J
   #43 = Utf8               $minus
   #44 = Utf8               $minus$extension
   #45 = NameAndType        #44:#40       // $minus$extension:(JJ)J
   #46 = Methodref          #13.#45       // org/sireum/Z$U$_64$.$minus$extension:(JJ)J
   #47 = Utf8               $times
   #48 = Utf8               $times$extension
   #49 = NameAndType        #48:#40       // $times$extension:(JJ)J
   #50 = Methodref          #13.#49       // org/sireum/Z$U$_64$.$times$extension:(JJ)J
   #51 = Utf8               $div
   #52 = Utf8               $div$extension
   #53 = NameAndType        #52:#40       // $div$extension:(JJ)J
   #54 = Methodref          #13.#53       // org/sireum/Z$U$_64$.$div$extension:(JJ)J
   #55 = Utf8               $percent
   #56 = Utf8               $percent$extension
   #57 = NameAndType        #56:#40       // $percent$extension:(JJ)J
   #58 = Methodref          #13.#57       // org/sireum/Z$U$_64$.$percent$extension:(JJ)J
   #59 = Utf8               $less$less
   #60 = Utf8               (I)J
   #61 = Utf8               n
   #62 = Utf8               $less$less$extension
   #63 = Utf8               (JI)J
   #64 = NameAndType        #62:#63       // $less$less$extension:(JI)J
   #65 = Methodref          #13.#64       // org/sireum/Z$U$_64$.$less$less$extension:(JI)J
   #66 = Utf8               I
   #67 = Utf8               $greater$greater
   #68 = Utf8               $greater$greater$extension
   #69 = NameAndType        #68:#63       // $greater$greater$extension:(JI)J
   #70 = Methodref          #13.#69       // org/sireum/Z$U$_64$.$greater$greater$extension:(JI)J
   #71 = Utf8               $greater$greater$greater
   #72 = Utf8               $greater$greater$greater$extension
   #73 = NameAndType        #72:#63       // $greater$greater$greater$extension:(JI)J
   #74 = Methodref          #13.#73       // org/sireum/Z$U$_64$.$greater$greater$greater$extension:(JI)J
   #75 = Utf8               $amp
   #76 = Utf8               $amp$extension
   #77 = NameAndType        #76:#40       // $amp$extension:(JJ)J
   #78 = Methodref          #13.#77       // org/sireum/Z$U$_64$.$amp$extension:(JJ)J
   #79 = Utf8               $bar
   #80 = Utf8               $bar$extension
   #81 = NameAndType        #80:#40       // $bar$extension:(JJ)J
   #82 = Methodref          #13.#81       // org/sireum/Z$U$_64$.$bar$extension:(JJ)J
   #83 = Utf8               $up
   #84 = Utf8               $up$extension
   #85 = NameAndType        #84:#40       // $up$extension:(JJ)J
   #86 = Methodref          #13.#85       // org/sireum/Z$U$_64$.$up$extension:(JJ)J
   #87 = Utf8               $less
   #88 = Utf8               (J)Z
   #89 = Utf8               $less$extension
   #90 = Utf8               (JJ)Z
   #91 = NameAndType        #89:#90       // $less$extension:(JJ)Z
   #92 = Methodref          #13.#91       // org/sireum/Z$U$_64$.$less$extension:(JJ)Z
   #93 = Utf8               $less$eq
   #94 = Utf8               $less$eq$extension
   #95 = NameAndType        #94:#90       // $less$eq$extension:(JJ)Z
   #96 = Methodref          #13.#95       // org/sireum/Z$U$_64$.$less$eq$extension:(JJ)Z
   #97 = Utf8               $greater
   #98 = Utf8               $greater$extension
   #99 = NameAndType        #98:#90       // $greater$extension:(JJ)Z
  #100 = Methodref          #13.#99       // org/sireum/Z$U$_64$.$greater$extension:(JJ)Z
  #101 = Utf8               $greater$eq
  #102 = Utf8               $greater$eq$extension
  #103 = NameAndType        #102:#90      // $greater$eq$extension:(JJ)Z
  #104 = Methodref          #13.#103      // org/sireum/Z$U$_64$.$greater$eq$extension:(JJ)Z
  #105 = Utf8               toBigInt
  #106 = Utf8               ()Lscala/math/BigInt;
  #107 = Utf8               toBigInt$extension
  #108 = Utf8               (J)Lscala/math/BigInt;
  #109 = NameAndType        #107:#108     // toBigInt$extension:(J)Lscala/math/BigInt;
  #110 = Methodref          #13.#109      // org/sireum/Z$U$_64$.toBigInt$extension:(J)Lscala/math/BigInt;
  #111 = Utf8               toString
  #112 = Utf8               ()Ljava/lang/String;
  #113 = Utf8               toString$extension
  #114 = Utf8               (J)Ljava/lang/String;
  #115 = NameAndType        #113:#114     // toString$extension:(J)Ljava/lang/String;
  #116 = Methodref          #13.#115      // org/sireum/Z$U$_64$.toString$extension:(J)Ljava/lang/String;
  #117 = Utf8               hashCode
  #118 = Utf8               ()I
  #119 = Utf8               hashCode$extension
  #120 = Utf8               (J)I
  #121 = NameAndType        #119:#120     // hashCode$extension:(J)I
  #122 = Methodref          #13.#121      // org/sireum/Z$U$_64$.hashCode$extension:(J)I
  #123 = Utf8               equals
  #124 = Utf8               (Ljava/lang/Object;)Z
  #125 = Utf8               x$1
  #126 = Utf8               equals$extension
  #127 = Utf8               (JLjava/lang/Object;)Z
  #128 = NameAndType        #126:#127     // equals$extension:(JLjava/lang/Object;)Z
  #129 = Methodref          #13.#128      // org/sireum/Z$U$_64$.equals$extension:(JLjava/lang/Object;)Z
  #130 = Utf8               Ljava/lang/Object;
  #131 = Utf8               <init>
  #132 = Utf8               (J)V
  #133 = Utf8               ()V
  #134 = NameAndType        #131:#133     // "<init>":()V
  #135 = Methodref          #4.#134       // java/lang/Object."<init>":()V
  #136 = Utf8               Code
  #137 = Utf8               LineNumberTable
  #138 = Utf8               LocalVariableTable
  #139 = Utf8               MethodParameters
  #140 = Utf8               InnerClasses
  #141 = Utf8               SourceFile
  #142 = Utf8               ScalaInlineInfo
  #143 = Utf8               Scala
{
  private final long value;
    descriptor: J
    flags: (0x0012) ACC_PRIVATE, ACC_FINAL

  public long value();
    descriptor: ()J
    flags: (0x0001) ACC_PUBLIC
    Code:
      stack=2, locals=1, args_size=1
         0: aload_0
         1: getfield      #19                 // Field value:J
         4: lreturn
      LineNumberTable:
        line 424: 0
      LocalVariableTable:
        Start  Length  Slot  Name   Signature
            0       5     0  this   Lorg/sireum/Z$U$_64;

  public long unary_$minus();
    descriptor: ()J
    flags: (0x0001) ACC_PUBLIC
    Code:
      stack=3, locals=1, args_size=1
         0: getstatic     #26                 // Field org/sireum/Z$U$_64$.MODULE$:Lorg/sireum/Z$U$_64$;
         3: aload_0
         4: invokevirtual #28                 // Method value:()J
         7: invokevirtual #32                 // Method org/sireum/Z$U$_64$.unary_$minus$extension:(J)J
        10: lreturn
      LineNumberTable:
        line 425: 0
      LocalVariableTable:
        Start  Length  Slot  Name   Signature
            0      11     0  this   Lorg/sireum/Z$U$_64;

  public long unary_$tilde();
    descriptor: ()J
    flags: (0x0001) ACC_PUBLIC
    Code:
      stack=3, locals=1, args_size=1
         0: getstatic     #26                 // Field org/sireum/Z$U$_64$.MODULE$:Lorg/sireum/Z$U$_64$;
         3: aload_0
         4: invokevirtual #28                 // Method value:()J
         7: invokevirtual #36                 // Method org/sireum/Z$U$_64$.unary_$tilde$extension:(J)J
        10: lreturn
      LineNumberTable:
        line 426: 0
      LocalVariableTable:
        Start  Length  Slot  Name   Signature
            0      11     0  this   Lorg/sireum/Z$U$_64;

  public long $plus(long);
    descriptor: (J)J
    flags: (0x0001) ACC_PUBLIC
    Code:
      stack=5, locals=3, args_size=2
         0: getstatic     #26                 // Field org/sireum/Z$U$_64$.MODULE$:Lorg/sireum/Z$U$_64$;
         3: aload_0
         4: invokevirtual #28                 // Method value:()J
         7: lload_1
         8: invokevirtual #42                 // Method org/sireum/Z$U$_64$.$plus$extension:(JJ)J
        11: lreturn
      LineNumberTable:
        line 427: 0
      LocalVariableTable:
        Start  Length  Slot  Name   Signature
            0      12     0  this   Lorg/sireum/Z$U$_64;
            0      12     1 other   J
    MethodParameters:
      Name                           Flags
      other                          final

  public long $minus(long);
    descriptor: (J)J
    flags: (0x0001) ACC_PUBLIC
    Code:
      stack=5, locals=3, args_size=2
         0: getstatic     #26                 // Field org/sireum/Z$U$_64$.MODULE$:Lorg/sireum/Z$U$_64$;
         3: aload_0
         4: invokevirtual #28                 // Method value:()J
         7: lload_1
         8: invokevirtual #46                 // Method org/sireum/Z$U$_64$.$minus$extension:(JJ)J
        11: lreturn
      LineNumberTable:
        line 428: 0
      LocalVariableTable:
        Start  Length  Slot  Name   Signature
            0      12     0  this   Lorg/sireum/Z$U$_64;
            0      12     1 other   J
    MethodParameters:
      Name                           Flags
      other                          final

  public long $times(long);
    descriptor: (J)J
    flags: (0x0001) ACC_PUBLIC
    Code:
      stack=5, locals=3, args_size=2
         0: getstatic     #26                 // Field org/sireum/Z$U$_64$.MODULE$:Lorg/sireum/Z$U$_64$;
         3: aload_0
         4: invokevirtual #28                 // Method value:()J
         7: lload_1
         8: invokevirtual #50                 // Method org/sireum/Z$U$_64$.$times$extension:(JJ)J
        11: lreturn
      LineNumberTable:
        line 429: 0
      LocalVariableTable:
        Start  Length  Slot  Name   Signature
            0      12     0  this   Lorg/sireum/Z$U$_64;
            0      12     1 other   J
    MethodParameters:
      Name                           Flags
      other                          final

  public long $div(long);
    descriptor: (J)J
    flags: (0x0001) ACC_PUBLIC
    Code:
      stack=5, locals=3, args_size=2
         0: getstatic     #26                 // Field org/sireum/Z$U$_64$.MODULE$:Lorg/sireum/Z$U$_64$;
         3: aload_0
         4: invokevirtual #28                 // Method value:()J
         7: lload_1
         8: invokevirtual #54                 // Method org/sireum/Z$U$_64$.$div$extension:(JJ)J
        11: lreturn
      LineNumberTable:
        line 430: 0
      LocalVariableTable:
        Start  Length  Slot  Name   Signature
            0      12     0  this   Lorg/sireum/Z$U$_64;
            0      12     1 other   J
    MethodParameters:
      Name                           Flags
      other                          final

  public long $percent(long);
    descriptor: (J)J
    flags: (0x0001) ACC_PUBLIC
    Code:
      stack=5, locals=3, args_size=2
         0: getstatic     #26                 // Field org/sireum/Z$U$_64$.MODULE$:Lorg/sireum/Z$U$_64$;
         3: aload_0
         4: invokevirtual #28                 // Method value:()J
         7: lload_1
         8: invokevirtual #58                 // Method org/sireum/Z$U$_64$.$percent$extension:(JJ)J
        11: lreturn
      LineNumberTable:
        line 431: 0
      LocalVariableTable:
        Start  Length  Slot  Name   Signature
            0      12     0  this   Lorg/sireum/Z$U$_64;
            0      12     1 other   J
    MethodParameters:
      Name                           Flags
      other                          final

  public long $less$less(int);
    descriptor: (I)J
    flags: (0x0001) ACC_PUBLIC
    Code:
      stack=4, locals=2, args_size=2
         0: getstatic     #26                 // Field org/sireum/Z$U$_64$.MODULE$:Lorg/sireum/Z$U$_64$;
         3: aload_0
         4: invokevirtual #28                 // Method value:()J
         7: iload_1
         8: invokevirtual #65                 // Method org/sireum/Z$U$_64$.$less$less$extension:(JI)J
        11: lreturn
      LineNumberTable:
        line 432: 0
      LocalVariableTable:
        Start  Length  Slot  Name   Signature
            0      12     0  this   Lorg/sireum/Z$U$_64;
            0      12     1     n   I
    MethodParameters:
      Name                           Flags
      n                              final

  public long $greater$greater(int);
    descriptor: (I)J
    flags: (0x0001) ACC_PUBLIC
    Code:
      stack=4, locals=2, args_size=2
         0: getstatic     #26                 // Field org/sireum/Z$U$_64$.MODULE$:Lorg/sireum/Z$U$_64$;
         3: aload_0
         4: invokevirtual #28                 // Method value:()J
         7: iload_1
         8: invokevirtual #70                 // Method org/sireum/Z$U$_64$.$greater$greater$extension:(JI)J
        11: lreturn
      LineNumberTable:
        line 433: 0
      LocalVariableTable:
        Start  Length  Slot  Name   Signature
            0      12     0  this   Lorg/sireum/Z$U$_64;
            0      12     1     n   I
    MethodParameters:
      Name                           Flags
      n                              final

  public long $greater$greater$greater(int);
    descriptor: (I)J
    flags: (0x0001) ACC_PUBLIC
    Code:
      stack=4, locals=2, args_size=2
         0: getstatic     #26                 // Field org/sireum/Z$U$_64$.MODULE$:Lorg/sireum/Z$U$_64$;
         3: aload_0
         4: invokevirtual #28                 // Method value:()J
         7: iload_1
         8: invokevirtual #74                 // Method org/sireum/Z$U$_64$.$greater$greater$greater$extension:(JI)J
        11: lreturn
      LineNumberTable:
        line 434: 0
      LocalVariableTable:
        Start  Length  Slot  Name   Signature
            0      12     0  this   Lorg/sireum/Z$U$_64;
            0      12     1     n   I
    MethodParameters:
      Name                           Flags
      n                              final

  public long $amp(long);
    descriptor: (J)J
    flags: (0x0001) ACC_PUBLIC
    Code:
      stack=5, locals=3, args_size=2
         0: getstatic     #26                 // Field org/sireum/Z$U$_64$.MODULE$:Lorg/sireum/Z$U$_64$;
         3: aload_0
         4: invokevirtual #28                 // Method value:()J
         7: lload_1
         8: invokevirtual #78                 // Method org/sireum/Z$U$_64$.$amp$extension:(JJ)J
        11: lreturn
      LineNumberTable:
        line 435: 0
      LocalVariableTable:
        Start  Length  Slot  Name   Signature
            0      12     0  this   Lorg/sireum/Z$U$_64;
            0      12     1 other   J
    MethodParameters:
      Name                           Flags
      other                          final

  public long $bar(long);
    descriptor: (J)J
    flags: (0x0001) ACC_PUBLIC
    Code:
      stack=5, locals=3, args_size=2
         0: getstatic     #26                 // Field org/sireum/Z$U$_64$.MODULE$:Lorg/sireum/Z$U$_64$;
         3: aload_0
         4: invokevirtual #28                 // Method value:()J
         7: lload_1
         8: invokevirtual #82                 // Method org/sireum/Z$U$_64$.$bar$extension:(JJ)J
        11: lreturn
      LineNumberTable:
        line 436: 0
      LocalVariableTable:
        Start  Length  Slot  Name   Signature
            0      12     0  this   Lorg/sireum/Z$U$_64;
            0      12     1 other   J
    MethodParameters:
      Name                           Flags
      other                          final

  public long $up(long);
    descriptor: (J)J
    flags: (0x0001) ACC_PUBLIC
    Code:
      stack=5, locals=3, args_size=2
         0: getstatic     #26                 // Field org/sireum/Z$U$_64$.MODULE$:Lorg/sireum/Z$U$_64$;
         3: aload_0
         4: invokevirtual #28                 // Method value:()J
         7: lload_1
         8: invokevirtual #86                 // Method org/sireum/Z$U$_64$.$up$extension:(JJ)J
        11: lreturn
      LineNumberTable:
        line 437: 0
      LocalVariableTable:
        Start  Length  Slot  Name   Signature
            0      12     0  this   Lorg/sireum/Z$U$_64;
            0      12     1 other   J
    MethodParameters:
      Name                           Flags
      other                          final

  public boolean $less(long);
    descriptor: (J)Z
    flags: (0x0001) ACC_PUBLIC
    Code:
      stack=5, locals=3, args_size=2
         0: getstatic     #26                 // Field org/sireum/Z$U$_64$.MODULE$:Lorg/sireum/Z$U$_64$;
         3: aload_0
         4: invokevirtual #28                 // Method value:()J
         7: lload_1
         8: invokevirtual #92                 // Method org/sireum/Z$U$_64$.$less$extension:(JJ)Z
        11: ireturn
      LineNumberTable:
        line 438: 0
      LocalVariableTable:
        Start  Length  Slot  Name   Signature
            0      12     0  this   Lorg/sireum/Z$U$_64;
            0      12     1 other   J
    MethodParameters:
      Name                           Flags
      other                          final

  public boolean $less$eq(long);
    descriptor: (J)Z
    flags: (0x0001) ACC_PUBLIC
    Code:
      stack=5, locals=3, args_size=2
         0: getstatic     #26                 // Field org/sireum/Z$U$_64$.MODULE$:Lorg/sireum/Z$U$_64$;
         3: aload_0
         4: invokevirtual #28                 // Method value:()J
         7: lload_1
         8: invokevirtual #96                 // Method org/sireum/Z$U$_64$.$less$eq$extension:(JJ)Z
        11: ireturn
      LineNumberTable:
        line 439: 0
      LocalVariableTable:
        Start  Length  Slot  Name   Signature
            0      12     0  this   Lorg/sireum/Z$U$_64;
            0      12     1 other   J
    MethodParameters:
      Name                           Flags
      other                          final

  public boolean $greater(long);
    descriptor: (J)Z
    flags: (0x0001) ACC_PUBLIC
    Code:
      stack=5, locals=3, args_size=2
         0: getstatic     #26                 // Field org/sireum/Z$U$_64$.MODULE$:Lorg/sireum/Z$U$_64$;
         3: aload_0
         4: invokevirtual #28                 // Method value:()J
         7: lload_1
         8: invokevirtual #100                // Method org/sireum/Z$U$_64$.$greater$extension:(JJ)Z
        11: ireturn
      LineNumberTable:
        line 440: 0
      LocalVariableTable:
        Start  Length  Slot  Name   Signature
            0      12     0  this   Lorg/sireum/Z$U$_64;
            0      12     1 other   J
    MethodParameters:
      Name                           Flags
      other                          final

  public boolean $greater$eq(long);
    descriptor: (J)Z
    flags: (0x0001) ACC_PUBLIC
    Code:
      stack=5, locals=3, args_size=2
         0: getstatic     #26                 // Field org/sireum/Z$U$_64$.MODULE$:Lorg/sireum/Z$U$_64$;
         3: aload_0
         4: invokevirtual #28                 // Method value:()J
         7: lload_1
         8: invokevirtual #104                // Method org/sireum/Z$U$_64$.$greater$eq$extension:(JJ)Z
        11: ireturn
      LineNumberTable:
        line 441: 0
      LocalVariableTable:
        Start  Length  Slot  Name   Signature
            0      12     0  this   Lorg/sireum/Z$U$_64;
            0      12     1 other   J
    MethodParameters:
      Name                           Flags
      other                          final

  public scala.math.BigInt toBigInt();
    descriptor: ()Lscala/math/BigInt;
    flags: (0x0001) ACC_PUBLIC
    Code:
      stack=3, locals=1, args_size=1
         0: getstatic     #26                 // Field org/sireum/Z$U$_64$.MODULE$:Lorg/sireum/Z$U$_64$;
         3: aload_0
         4: invokevirtual #28                 // Method value:()J
         7: invokevirtual #110                // Method org/sireum/Z$U$_64$.toBigInt$extension:(J)Lscala/math/BigInt;
        10: areturn
      LineNumberTable:
        line 444: 0
      LocalVariableTable:
        Start  Length  Slot  Name   Signature
            0      11     0  this   Lorg/sireum/Z$U$_64;

  public java.lang.String toString();
    descriptor: ()Ljava/lang/String;
    flags: (0x0001) ACC_PUBLIC
    Code:
      stack=3, locals=1, args_size=1
         0: getstatic     #26                 // Field org/sireum/Z$U$_64$.MODULE$:Lorg/sireum/Z$U$_64$;
         3: aload_0
         4: invokevirtual #28                 // Method value:()J
         7: invokevirtual #116                // Method org/sireum/Z$U$_64$.toString$extension:(J)Ljava/lang/String;
        10: areturn
      LineNumberTable:
        line 445: 0
      LocalVariableTable:
        Start  Length  Slot  Name   Signature
            0      11     0  this   Lorg/sireum/Z$U$_64;

  public int hashCode();
    descriptor: ()I
    flags: (0x0001) ACC_PUBLIC
    Code:
      stack=3, locals=1, args_size=1
         0: getstatic     #26                 // Field org/sireum/Z$U$_64$.MODULE$:Lorg/sireum/Z$U$_64$;
         3: aload_0
         4: invokevirtual #28                 // Method value:()J
         7: invokevirtual #122                // Method org/sireum/Z$U$_64$.hashCode$extension:(J)I
        10: ireturn
      LineNumberTable:
        line 424: 0
      LocalVariableTable:
        Start  Length  Slot  Name   Signature
            0      11     0  this   Lorg/sireum/Z$U$_64;

  public boolean equals(java.lang.Object);
    descriptor: (Ljava/lang/Object;)Z
    flags: (0x0001) ACC_PUBLIC
    Code:
      stack=4, locals=2, args_size=2
         0: getstatic     #26                 // Field org/sireum/Z$U$_64$.MODULE$:Lorg/sireum/Z$U$_64$;
         3: aload_0
         4: invokevirtual #28                 // Method value:()J
         7: aload_1
         8: invokevirtual #129                // Method org/sireum/Z$U$_64$.equals$extension:(JLjava/lang/Object;)Z
        11: ireturn
      LineNumberTable:
        line 424: 0
      LocalVariableTable:
        Start  Length  Slot  Name   Signature
            0      12     0  this   Lorg/sireum/Z$U$_64;
            0      12     1   x$1   Ljava/lang/Object;
    MethodParameters:
      Name                           Flags
      x$1                            final

  public org.sireum.Z$U$_64(long);
    descriptor: (J)V
    flags: (0x0001) ACC_PUBLIC
    Code:
      stack=3, locals=3, args_size=2
         0: aload_0
         1: lload_1
         2: putfield      #19                 // Field value:J
         5: aload_0
         6: invokespecial #135                // Method java/lang/Object."<init>":()V
         9: return
      LineNumberTable:
        line 424: 0
      LocalVariableTable:
        Start  Length  Slot  Name   Signature
            0      10     0  this   Lorg/sireum/Z$U$_64;
            0      10     1 value   J
    MethodParameters:
      Name                           Flags
      value                          final
}
InnerClasses:
  public static #10= #7 of #9;            // U$=class org/sireum/Z$U$ of class org/sireum/Z
  public static final #11= #2 of #7;      // _64=class org/sireum/Z$U$_64 of class org/sireum/Z$U$
  public static #14= #13 of #7;           // _64$=class org/sireum/Z$U$_64$ of class org/sireum/Z$U$
SourceFile: "Z.scala"
  ScalaInlineInfo: length = 0x77 (unknown attribute)
   01 01 00 17 00 4B 00 1E 01 00 4F 00 1E 01 00 33
   00 1E 01 00 61 00 58 01 00 65 00 58 01 00 43 00
   3C 01 00 47 00 3C 01 00 57 00 58 01 00 5D 00 58
   01 00 3B 00 3C 01 00 2B 00 1E 01 00 37 00 1E 01
   00 25 00 1E 01 00 2F 00 1E 01 00 53 00 1E 01 00
   83 00 84 01 00 7B 00 7C 01 00 75 00 76 01 00 69
   00 6A 01 00 6F 00 70 01 00 16 00 11 01 00 21 00
   11 01 00 0F 00 11 01
  Scala: length = 0x0 (unknown attribute)

