Classfile /Users/mw/Projects/slang-braindump/.jar/jar11/assemble/slang-braindump/assemble/content/org/sireum/Z$U$_16.class
  Last modified May 29, 2022; size 3600 bytes
  SHA-256 checksum dbc3f1348dd4fe21d98bdd2671ae89bf7d8ea258909eda91d78f22ac3e31663e
  Compiled from "Z.scala"
public final class org.sireum.Z$U$_16
  minor version: 0
  major version: 52
  flags: (0x0031) ACC_PUBLIC, ACC_FINAL, ACC_SUPER
  this_class: #2                          // org/sireum/Z$U$_16
  super_class: #4                         // java/lang/Object
  interfaces: 0, fields: 1, methods: 23, attributes: 4
Constant pool:
    #1 = Utf8               org/sireum/Z$U$_16
    #2 = Class              #1            // org/sireum/Z$U$_16
    #3 = Utf8               java/lang/Object
    #4 = Class              #3            // java/lang/Object
    #5 = Utf8               Z.scala
    #6 = Utf8               org/sireum/Z$U$
    #7 = Class              #6            // org/sireum/Z$U$
    #8 = Utf8               org/sireum/Z
    #9 = Class              #8            // org/sireum/Z
   #10 = Utf8               U$
   #11 = Utf8               _16
   #12 = Utf8               org/sireum/Z$U$_16$
   #13 = Class              #12           // org/sireum/Z$U$_16$
   #14 = Utf8               _16$
   #15 = Utf8               value
   #16 = Utf8               S
   #17 = Utf8               ()S
   #18 = NameAndType        #15:#16       // value:S
   #19 = Fieldref           #2.#18        // org/sireum/Z$U$_16.value:S
   #20 = Utf8               this
   #21 = Utf8               Lorg/sireum/Z$U$_16;
   #22 = Utf8               unary_$minus
   #23 = Utf8               MODULE$
   #24 = Utf8               Lorg/sireum/Z$U$_16$;
   #25 = NameAndType        #23:#24       // MODULE$:Lorg/sireum/Z$U$_16$;
   #26 = Fieldref           #13.#25       // org/sireum/Z$U$_16$.MODULE$:Lorg/sireum/Z$U$_16$;
   #27 = NameAndType        #15:#17       // value:()S
   #28 = Methodref          #2.#27        // org/sireum/Z$U$_16.value:()S
   #29 = Utf8               unary_$minus$extension
   #30 = Utf8               (S)S
   #31 = NameAndType        #29:#30       // unary_$minus$extension:(S)S
   #32 = Methodref          #13.#31       // org/sireum/Z$U$_16$.unary_$minus$extension:(S)S
   #33 = Utf8               unary_$tilde
   #34 = Utf8               unary_$tilde$extension
   #35 = NameAndType        #34:#30       // unary_$tilde$extension:(S)S
   #36 = Methodref          #13.#35       // org/sireum/Z$U$_16$.unary_$tilde$extension:(S)S
   #37 = Utf8               $plus
   #38 = Utf8               other
   #39 = Utf8               $plus$extension
   #40 = Utf8               (SS)S
   #41 = NameAndType        #39:#40       // $plus$extension:(SS)S
   #42 = Methodref          #13.#41       // org/sireum/Z$U$_16$.$plus$extension:(SS)S
   #43 = Utf8               $minus
   #44 = Utf8               $minus$extension
   #45 = NameAndType        #44:#40       // $minus$extension:(SS)S
   #46 = Methodref          #13.#45       // org/sireum/Z$U$_16$.$minus$extension:(SS)S
   #47 = Utf8               $times
   #48 = Utf8               $times$extension
   #49 = NameAndType        #48:#40       // $times$extension:(SS)S
   #50 = Methodref          #13.#49       // org/sireum/Z$U$_16$.$times$extension:(SS)S
   #51 = Utf8               $div
   #52 = Utf8               $div$extension
   #53 = NameAndType        #52:#40       // $div$extension:(SS)S
   #54 = Methodref          #13.#53       // org/sireum/Z$U$_16$.$div$extension:(SS)S
   #55 = Utf8               $percent
   #56 = Utf8               $percent$extension
   #57 = NameAndType        #56:#40       // $percent$extension:(SS)S
   #58 = Methodref          #13.#57       // org/sireum/Z$U$_16$.$percent$extension:(SS)S
   #59 = Utf8               $less$less
   #60 = Utf8               (I)S
   #61 = Utf8               n
   #62 = Utf8               $less$less$extension
   #63 = Utf8               (SI)S
   #64 = NameAndType        #62:#63       // $less$less$extension:(SI)S
   #65 = Methodref          #13.#64       // org/sireum/Z$U$_16$.$less$less$extension:(SI)S
   #66 = Utf8               I
   #67 = Utf8               $greater$greater
   #68 = Utf8               $greater$greater$extension
   #69 = NameAndType        #68:#63       // $greater$greater$extension:(SI)S
   #70 = Methodref          #13.#69       // org/sireum/Z$U$_16$.$greater$greater$extension:(SI)S
   #71 = Utf8               $greater$greater$greater
   #72 = Utf8               $greater$greater$greater$extension
   #73 = NameAndType        #72:#63       // $greater$greater$greater$extension:(SI)S
   #74 = Methodref          #13.#73       // org/sireum/Z$U$_16$.$greater$greater$greater$extension:(SI)S
   #75 = Utf8               $amp
   #76 = Utf8               $amp$extension
   #77 = NameAndType        #76:#40       // $amp$extension:(SS)S
   #78 = Methodref          #13.#77       // org/sireum/Z$U$_16$.$amp$extension:(SS)S
   #79 = Utf8               $bar
   #80 = Utf8               $bar$extension
   #81 = NameAndType        #80:#40       // $bar$extension:(SS)S
   #82 = Methodref          #13.#81       // org/sireum/Z$U$_16$.$bar$extension:(SS)S
   #83 = Utf8               $up
   #84 = Utf8               $up$extension
   #85 = NameAndType        #84:#40       // $up$extension:(SS)S
   #86 = Methodref          #13.#85       // org/sireum/Z$U$_16$.$up$extension:(SS)S
   #87 = Utf8               $less
   #88 = Utf8               (S)Z
   #89 = Utf8               $less$extension
   #90 = Utf8               (SS)Z
   #91 = NameAndType        #89:#90       // $less$extension:(SS)Z
   #92 = Methodref          #13.#91       // org/sireum/Z$U$_16$.$less$extension:(SS)Z
   #93 = Utf8               $less$eq
   #94 = Utf8               $less$eq$extension
   #95 = NameAndType        #94:#90       // $less$eq$extension:(SS)Z
   #96 = Methodref          #13.#95       // org/sireum/Z$U$_16$.$less$eq$extension:(SS)Z
   #97 = Utf8               $greater
   #98 = Utf8               $greater$extension
   #99 = NameAndType        #98:#90       // $greater$extension:(SS)Z
  #100 = Methodref          #13.#99       // org/sireum/Z$U$_16$.$greater$extension:(SS)Z
  #101 = Utf8               $greater$eq
  #102 = Utf8               $greater$eq$extension
  #103 = NameAndType        #102:#90      // $greater$eq$extension:(SS)Z
  #104 = Methodref          #13.#103      // org/sireum/Z$U$_16$.$greater$eq$extension:(SS)Z
  #105 = Utf8               toInt
  #106 = Utf8               ()I
  #107 = Utf8               toInt$extension
  #108 = Utf8               (S)I
  #109 = NameAndType        #107:#108     // toInt$extension:(S)I
  #110 = Methodref          #13.#109      // org/sireum/Z$U$_16$.toInt$extension:(S)I
  #111 = Utf8               toString
  #112 = Utf8               ()Ljava/lang/String;
  #113 = Utf8               toString$extension
  #114 = Utf8               (S)Ljava/lang/String;
  #115 = NameAndType        #113:#114     // toString$extension:(S)Ljava/lang/String;
  #116 = Methodref          #13.#115      // org/sireum/Z$U$_16$.toString$extension:(S)Ljava/lang/String;
  #117 = Utf8               hashCode
  #118 = Utf8               hashCode$extension
  #119 = NameAndType        #118:#108     // hashCode$extension:(S)I
  #120 = Methodref          #13.#119      // org/sireum/Z$U$_16$.hashCode$extension:(S)I
  #121 = Utf8               equals
  #122 = Utf8               (Ljava/lang/Object;)Z
  #123 = Utf8               x$1
  #124 = Utf8               equals$extension
  #125 = Utf8               (SLjava/lang/Object;)Z
  #126 = NameAndType        #124:#125     // equals$extension:(SLjava/lang/Object;)Z
  #127 = Methodref          #13.#126      // org/sireum/Z$U$_16$.equals$extension:(SLjava/lang/Object;)Z
  #128 = Utf8               Ljava/lang/Object;
  #129 = Utf8               <init>
  #130 = Utf8               (S)V
  #131 = Utf8               ()V
  #132 = NameAndType        #129:#131     // "<init>":()V
  #133 = Methodref          #4.#132       // java/lang/Object."<init>":()V
  #134 = Utf8               Code
  #135 = Utf8               LineNumberTable
  #136 = Utf8               LocalVariableTable
  #137 = Utf8               MethodParameters
  #138 = Utf8               InnerClasses
  #139 = Utf8               SourceFile
  #140 = Utf8               ScalaInlineInfo
  #141 = Utf8               Scala
{
  private final short value;
    descriptor: S
    flags: (0x0012) ACC_PRIVATE, ACC_FINAL

  public short value();
    descriptor: ()S
    flags: (0x0001) ACC_PUBLIC
    Code:
      stack=1, locals=1, args_size=1
         0: aload_0
         1: getfield      #19                 // Field value:S
         4: ireturn
      LineNumberTable:
        line 364: 0
      LocalVariableTable:
        Start  Length  Slot  Name   Signature
            0       5     0  this   Lorg/sireum/Z$U$_16;

  public short unary_$minus();
    descriptor: ()S
    flags: (0x0001) ACC_PUBLIC
    Code:
      stack=2, locals=1, args_size=1
         0: getstatic     #26                 // Field org/sireum/Z$U$_16$.MODULE$:Lorg/sireum/Z$U$_16$;
         3: aload_0
         4: invokevirtual #28                 // Method value:()S
         7: invokevirtual #32                 // Method org/sireum/Z$U$_16$.unary_$minus$extension:(S)S
        10: ireturn
      LineNumberTable:
        line 365: 0
      LocalVariableTable:
        Start  Length  Slot  Name   Signature
            0      11     0  this   Lorg/sireum/Z$U$_16;

  public short unary_$tilde();
    descriptor: ()S
    flags: (0x0001) ACC_PUBLIC
    Code:
      stack=2, locals=1, args_size=1
         0: getstatic     #26                 // Field org/sireum/Z$U$_16$.MODULE$:Lorg/sireum/Z$U$_16$;
         3: aload_0
         4: invokevirtual #28                 // Method value:()S
         7: invokevirtual #36                 // Method org/sireum/Z$U$_16$.unary_$tilde$extension:(S)S
        10: ireturn
      LineNumberTable:
        line 366: 0
      LocalVariableTable:
        Start  Length  Slot  Name   Signature
            0      11     0  this   Lorg/sireum/Z$U$_16;

  public short $plus(short);
    descriptor: (S)S
    flags: (0x0001) ACC_PUBLIC
    Code:
      stack=3, locals=2, args_size=2
         0: getstatic     #26                 // Field org/sireum/Z$U$_16$.MODULE$:Lorg/sireum/Z$U$_16$;
         3: aload_0
         4: invokevirtual #28                 // Method value:()S
         7: iload_1
         8: invokevirtual #42                 // Method org/sireum/Z$U$_16$.$plus$extension:(SS)S
        11: ireturn
      LineNumberTable:
        line 367: 0
      LocalVariableTable:
        Start  Length  Slot  Name   Signature
            0      12     0  this   Lorg/sireum/Z$U$_16;
            0      12     1 other   S
    MethodParameters:
      Name                           Flags
      other                          final

  public short $minus(short);
    descriptor: (S)S
    flags: (0x0001) ACC_PUBLIC
    Code:
      stack=3, locals=2, args_size=2
         0: getstatic     #26                 // Field org/sireum/Z$U$_16$.MODULE$:Lorg/sireum/Z$U$_16$;
         3: aload_0
         4: invokevirtual #28                 // Method value:()S
         7: iload_1
         8: invokevirtual #46                 // Method org/sireum/Z$U$_16$.$minus$extension:(SS)S
        11: ireturn
      LineNumberTable:
        line 368: 0
      LocalVariableTable:
        Start  Length  Slot  Name   Signature
            0      12     0  this   Lorg/sireum/Z$U$_16;
            0      12     1 other   S
    MethodParameters:
      Name                           Flags
      other                          final

  public short $times(short);
    descriptor: (S)S
    flags: (0x0001) ACC_PUBLIC
    Code:
      stack=3, locals=2, args_size=2
         0: getstatic     #26                 // Field org/sireum/Z$U$_16$.MODULE$:Lorg/sireum/Z$U$_16$;
         3: aload_0
         4: invokevirtual #28                 // Method value:()S
         7: iload_1
         8: invokevirtual #50                 // Method org/sireum/Z$U$_16$.$times$extension:(SS)S
        11: ireturn
      LineNumberTable:
        line 369: 0
      LocalVariableTable:
        Start  Length  Slot  Name   Signature
            0      12     0  this   Lorg/sireum/Z$U$_16;
            0      12     1 other   S
    MethodParameters:
      Name                           Flags
      other                          final

  public short $div(short);
    descriptor: (S)S
    flags: (0x0001) ACC_PUBLIC
    Code:
      stack=3, locals=2, args_size=2
         0: getstatic     #26                 // Field org/sireum/Z$U$_16$.MODULE$:Lorg/sireum/Z$U$_16$;
         3: aload_0
         4: invokevirtual #28                 // Method value:()S
         7: iload_1
         8: invokevirtual #54                 // Method org/sireum/Z$U$_16$.$div$extension:(SS)S
        11: ireturn
      LineNumberTable:
        line 370: 0
      LocalVariableTable:
        Start  Length  Slot  Name   Signature
            0      12     0  this   Lorg/sireum/Z$U$_16;
            0      12     1 other   S
    MethodParameters:
      Name                           Flags
      other                          final

  public short $percent(short);
    descriptor: (S)S
    flags: (0x0001) ACC_PUBLIC
    Code:
      stack=3, locals=2, args_size=2
         0: getstatic     #26                 // Field org/sireum/Z$U$_16$.MODULE$:Lorg/sireum/Z$U$_16$;
         3: aload_0
         4: invokevirtual #28                 // Method value:()S
         7: iload_1
         8: invokevirtual #58                 // Method org/sireum/Z$U$_16$.$percent$extension:(SS)S
        11: ireturn
      LineNumberTable:
        line 371: 0
      LocalVariableTable:
        Start  Length  Slot  Name   Signature
            0      12     0  this   Lorg/sireum/Z$U$_16;
            0      12     1 other   S
    MethodParameters:
      Name                           Flags
      other                          final

  public short $less$less(int);
    descriptor: (I)S
    flags: (0x0001) ACC_PUBLIC
    Code:
      stack=3, locals=2, args_size=2
         0: getstatic     #26                 // Field org/sireum/Z$U$_16$.MODULE$:Lorg/sireum/Z$U$_16$;
         3: aload_0
         4: invokevirtual #28                 // Method value:()S
         7: iload_1
         8: invokevirtual #65                 // Method org/sireum/Z$U$_16$.$less$less$extension:(SI)S
        11: ireturn
      LineNumberTable:
        line 372: 0
      LocalVariableTable:
        Start  Length  Slot  Name   Signature
            0      12     0  this   Lorg/sireum/Z$U$_16;
            0      12     1     n   I
    MethodParameters:
      Name                           Flags
      n                              final

  public short $greater$greater(int);
    descriptor: (I)S
    flags: (0x0001) ACC_PUBLIC
    Code:
      stack=3, locals=2, args_size=2
         0: getstatic     #26                 // Field org/sireum/Z$U$_16$.MODULE$:Lorg/sireum/Z$U$_16$;
         3: aload_0
         4: invokevirtual #28                 // Method value:()S
         7: iload_1
         8: invokevirtual #70                 // Method org/sireum/Z$U$_16$.$greater$greater$extension:(SI)S
        11: ireturn
      LineNumberTable:
        line 373: 0
      LocalVariableTable:
        Start  Length  Slot  Name   Signature
            0      12     0  this   Lorg/sireum/Z$U$_16;
            0      12     1     n   I
    MethodParameters:
      Name                           Flags
      n                              final

  public short $greater$greater$greater(int);
    descriptor: (I)S
    flags: (0x0001) ACC_PUBLIC
    Code:
      stack=3, locals=2, args_size=2
         0: getstatic     #26                 // Field org/sireum/Z$U$_16$.MODULE$:Lorg/sireum/Z$U$_16$;
         3: aload_0
         4: invokevirtual #28                 // Method value:()S
         7: iload_1
         8: invokevirtual #74                 // Method org/sireum/Z$U$_16$.$greater$greater$greater$extension:(SI)S
        11: ireturn
      LineNumberTable:
        line 374: 0
      LocalVariableTable:
        Start  Length  Slot  Name   Signature
            0      12     0  this   Lorg/sireum/Z$U$_16;
            0      12     1     n   I
    MethodParameters:
      Name                           Flags
      n                              final

  public short $amp(short);
    descriptor: (S)S
    flags: (0x0001) ACC_PUBLIC
    Code:
      stack=3, locals=2, args_size=2
         0: getstatic     #26                 // Field org/sireum/Z$U$_16$.MODULE$:Lorg/sireum/Z$U$_16$;
         3: aload_0
         4: invokevirtual #28                 // Method value:()S
         7: iload_1
         8: invokevirtual #78                 // Method org/sireum/Z$U$_16$.$amp$extension:(SS)S
        11: ireturn
      LineNumberTable:
        line 375: 0
      LocalVariableTable:
        Start  Length  Slot  Name   Signature
            0      12     0  this   Lorg/sireum/Z$U$_16;
            0      12     1 other   S
    MethodParameters:
      Name                           Flags
      other                          final

  public short $bar(short);
    descriptor: (S)S
    flags: (0x0001) ACC_PUBLIC
    Code:
      stack=3, locals=2, args_size=2
         0: getstatic     #26                 // Field org/sireum/Z$U$_16$.MODULE$:Lorg/sireum/Z$U$_16$;
         3: aload_0
         4: invokevirtual #28                 // Method value:()S
         7: iload_1
         8: invokevirtual #82                 // Method org/sireum/Z$U$_16$.$bar$extension:(SS)S
        11: ireturn
      LineNumberTable:
        line 376: 0
      LocalVariableTable:
        Start  Length  Slot  Name   Signature
            0      12     0  this   Lorg/sireum/Z$U$_16;
            0      12     1 other   S
    MethodParameters:
      Name                           Flags
      other                          final

  public short $up(short);
    descriptor: (S)S
    flags: (0x0001) ACC_PUBLIC
    Code:
      stack=3, locals=2, args_size=2
         0: getstatic     #26                 // Field org/sireum/Z$U$_16$.MODULE$:Lorg/sireum/Z$U$_16$;
         3: aload_0
         4: invokevirtual #28                 // Method value:()S
         7: iload_1
         8: invokevirtual #86                 // Method org/sireum/Z$U$_16$.$up$extension:(SS)S
        11: ireturn
      LineNumberTable:
        line 377: 0
      LocalVariableTable:
        Start  Length  Slot  Name   Signature
            0      12     0  this   Lorg/sireum/Z$U$_16;
            0      12     1 other   S
    MethodParameters:
      Name                           Flags
      other                          final

  public boolean $less(short);
    descriptor: (S)Z
    flags: (0x0001) ACC_PUBLIC
    Code:
      stack=3, locals=2, args_size=2
         0: getstatic     #26                 // Field org/sireum/Z$U$_16$.MODULE$:Lorg/sireum/Z$U$_16$;
         3: aload_0
         4: invokevirtual #28                 // Method value:()S
         7: iload_1
         8: invokevirtual #92                 // Method org/sireum/Z$U$_16$.$less$extension:(SS)Z
        11: ireturn
      LineNumberTable:
        line 378: 0
      LocalVariableTable:
        Start  Length  Slot  Name   Signature
            0      12     0  this   Lorg/sireum/Z$U$_16;
            0      12     1 other   S
    MethodParameters:
      Name                           Flags
      other                          final

  public boolean $less$eq(short);
    descriptor: (S)Z
    flags: (0x0001) ACC_PUBLIC
    Code:
      stack=3, locals=2, args_size=2
         0: getstatic     #26                 // Field org/sireum/Z$U$_16$.MODULE$:Lorg/sireum/Z$U$_16$;
         3: aload_0
         4: invokevirtual #28                 // Method value:()S
         7: iload_1
         8: invokevirtual #96                 // Method org/sireum/Z$U$_16$.$less$eq$extension:(SS)Z
        11: ireturn
      LineNumberTable:
        line 379: 0
      LocalVariableTable:
        Start  Length  Slot  Name   Signature
            0      12     0  this   Lorg/sireum/Z$U$_16;
            0      12     1 other   S
    MethodParameters:
      Name                           Flags
      other                          final

  public boolean $greater(short);
    descriptor: (S)Z
    flags: (0x0001) ACC_PUBLIC
    Code:
      stack=3, locals=2, args_size=2
         0: getstatic     #26                 // Field org/sireum/Z$U$_16$.MODULE$:Lorg/sireum/Z$U$_16$;
         3: aload_0
         4: invokevirtual #28                 // Method value:()S
         7: iload_1
         8: invokevirtual #100                // Method org/sireum/Z$U$_16$.$greater$extension:(SS)Z
        11: ireturn
      LineNumberTable:
        line 380: 0
      LocalVariableTable:
        Start  Length  Slot  Name   Signature
            0      12     0  this   Lorg/sireum/Z$U$_16;
            0      12     1 other   S
    MethodParameters:
      Name                           Flags
      other                          final

  public boolean $greater$eq(short);
    descriptor: (S)Z
    flags: (0x0001) ACC_PUBLIC
    Code:
      stack=3, locals=2, args_size=2
         0: getstatic     #26                 // Field org/sireum/Z$U$_16$.MODULE$:Lorg/sireum/Z$U$_16$;
         3: aload_0
         4: invokevirtual #28                 // Method value:()S
         7: iload_1
         8: invokevirtual #104                // Method org/sireum/Z$U$_16$.$greater$eq$extension:(SS)Z
        11: ireturn
      LineNumberTable:
        line 381: 0
      LocalVariableTable:
        Start  Length  Slot  Name   Signature
            0      12     0  this   Lorg/sireum/Z$U$_16;
            0      12     1 other   S
    MethodParameters:
      Name                           Flags
      other                          final

  public int toInt();
    descriptor: ()I
    flags: (0x0001) ACC_PUBLIC
    Code:
      stack=2, locals=1, args_size=1
         0: getstatic     #26                 // Field org/sireum/Z$U$_16$.MODULE$:Lorg/sireum/Z$U$_16$;
         3: aload_0
         4: invokevirtual #28                 // Method value:()S
         7: invokevirtual #110                // Method org/sireum/Z$U$_16$.toInt$extension:(S)I
        10: ireturn
      LineNumberTable:
        line 382: 0
      LocalVariableTable:
        Start  Length  Slot  Name   Signature
            0      11     0  this   Lorg/sireum/Z$U$_16;

  public java.lang.String toString();
    descriptor: ()Ljava/lang/String;
    flags: (0x0001) ACC_PUBLIC
    Code:
      stack=2, locals=1, args_size=1
         0: getstatic     #26                 // Field org/sireum/Z$U$_16$.MODULE$:Lorg/sireum/Z$U$_16$;
         3: aload_0
         4: invokevirtual #28                 // Method value:()S
         7: invokevirtual #116                // Method org/sireum/Z$U$_16$.toString$extension:(S)Ljava/lang/String;
        10: areturn
      LineNumberTable:
        line 383: 0
      LocalVariableTable:
        Start  Length  Slot  Name   Signature
            0      11     0  this   Lorg/sireum/Z$U$_16;

  public int hashCode();
    descriptor: ()I
    flags: (0x0001) ACC_PUBLIC
    Code:
      stack=2, locals=1, args_size=1
         0: getstatic     #26                 // Field org/sireum/Z$U$_16$.MODULE$:Lorg/sireum/Z$U$_16$;
         3: aload_0
         4: invokevirtual #28                 // Method value:()S
         7: invokevirtual #120                // Method org/sireum/Z$U$_16$.hashCode$extension:(S)I
        10: ireturn
      LineNumberTable:
        line 364: 0
      LocalVariableTable:
        Start  Length  Slot  Name   Signature
            0      11     0  this   Lorg/sireum/Z$U$_16;

  public boolean equals(java.lang.Object);
    descriptor: (Ljava/lang/Object;)Z
    flags: (0x0001) ACC_PUBLIC
    Code:
      stack=3, locals=2, args_size=2
         0: getstatic     #26                 // Field org/sireum/Z$U$_16$.MODULE$:Lorg/sireum/Z$U$_16$;
         3: aload_0
         4: invokevirtual #28                 // Method value:()S
         7: aload_1
         8: invokevirtual #127                // Method org/sireum/Z$U$_16$.equals$extension:(SLjava/lang/Object;)Z
        11: ireturn
      LineNumberTable:
        line 364: 0
      LocalVariableTable:
        Start  Length  Slot  Name   Signature
            0      12     0  this   Lorg/sireum/Z$U$_16;
            0      12     1   x$1   Ljava/lang/Object;
    MethodParameters:
      Name                           Flags
      x$1                            final

  public org.sireum.Z$U$_16(short);
    descriptor: (S)V
    flags: (0x0001) ACC_PUBLIC
    Code:
      stack=2, locals=2, args_size=2
         0: aload_0
         1: iload_1
         2: putfield      #19                 // Field value:S
         5: aload_0
         6: invokespecial #133                // Method java/lang/Object."<init>":()V
         9: return
      LineNumberTable:
        line 364: 0
      LocalVariableTable:
        Start  Length  Slot  Name   Signature
            0      10     0  this   Lorg/sireum/Z$U$_16;
            0      10     1 value   S
    MethodParameters:
      Name                           Flags
      value                          final
}
InnerClasses:
  public static #10= #7 of #9;            // U$=class org/sireum/Z$U$ of class org/sireum/Z
  public static final #11= #2 of #7;      // _16=class org/sireum/Z$U$_16 of class org/sireum/Z$U$
  public static #14= #13 of #7;           // _16$=class org/sireum/Z$U$_16$ of class org/sireum/Z$U$
SourceFile: "Z.scala"
  ScalaInlineInfo: length = 0x77 (unknown attribute)
   01 01 00 17 00 4B 00 1E 01 00 4F 00 1E 01 00 33
   00 1E 01 00 61 00 58 01 00 65 00 58 01 00 43 00
   3C 01 00 47 00 3C 01 00 57 00 58 01 00 5D 00 58
   01 00 3B 00 3C 01 00 2B 00 1E 01 00 37 00 1E 01
   00 25 00 1E 01 00 2F 00 1E 01 00 53 00 1E 01 00
   81 00 82 01 00 79 00 7A 01 00 75 00 6A 01 00 69
   00 6A 01 00 6F 00 70 01 00 16 00 11 01 00 21 00
   11 01 00 0F 00 11 01
  Scala: length = 0x0 (unknown attribute)

