Classfile /Users/mw/Projects/slang-braindump/.jar/jar11/assemble/slang-braindump/assemble/content/argonaut/derive/HListProductEncodeJson.class
  Last modified May 29, 2022; size 2836 bytes
  SHA-256 checksum ae26236eb71a10028f11eb5b67340fb13c686653f363f58b82a50ed5fa436356
  Compiled from "MkEncodeJson.scala"
public interface argonaut.derive.HListProductEncodeJson<L extends shapeless.HList, D extends shapeless.HList>
  minor version: 0
  major version: 52
  flags: (0x0601) ACC_PUBLIC, ACC_INTERFACE, ACC_ABSTRACT
  this_class: #2                          // argonaut/derive/HListProductEncodeJson
  super_class: #5                         // java/lang/Object
  interfaces: 0, fields: 0, methods: 4, attributes: 5
Constant pool:
   #1 = Utf8               argonaut/derive/HListProductEncodeJson
   #2 = Class              #1             // argonaut/derive/HListProductEncodeJson
   #3 = Utf8               <L::Lshapeless/HList;D::Lshapeless/HList;>Ljava/lang/Object;
   #4 = Utf8               java/lang/Object
   #5 = Class              #4             // java/lang/Object
   #6 = Utf8               MkEncodeJson.scala
   #7 = Utf8               Lscala/reflect/ScalaSignature;
   #8 = Utf8               bytes
   #9 = Utf8               \u0006\u0005\u0005=ba\u0002\u0006\f!\u0003\r\n\u0001\u0005\u0005\u00061\u00011\t!G\u0004\u0006o-A\t\u0001\u000f\u0004\u0006\u0015-A\t!\u000f\u0005\u0006u\r!\ta\u000f\u0005\u00061\r!\t\u0001\u0010\u0005\u0006\u000b\u000e!\tA\u0012\u0005\b\'\u000e\u0011\r\u0011b\u0001U\u0011\u0019I6\u0001)A\u0005+\")!l\u0001C\u00027\n1\u0002\nT5tiB\u0013x\u000eZ;di\u0016s7m\u001c3f\u0015N|gN\u0003\u0002\r\u001b\u00051A-\u001a:jm\u0016T\u0011AD\u0001\tCJ<wN\\1vi\u000e\u0001QcA\t!kM\u0011\u0001A\u0005\t\u0003\'Yi\u0011\u0001\u0006\u0006\u0002+\u0005)1oY1mC&\u0011q\u0003\u0006\u0002\u0007\u0003:L(+\u001a4\u0002\u000b\u0005\u0004\b\u000f\\=\u0015\u0007ia#\u0007E\u0002\u001c9yi\u0011!D\u0005\u0003;5\u0011!\"\u00128d_\u0012,\'j]8o!\ty\u0002\u0005\u0004\u0001\u0005\u000b\u0005\u0002!\u0019\u0001\u0012\u0003\u00031\u000b\"a\t\u0014\u0011\u0005M!\u0013BA\u0013\u0015\u0005\u001dqu\u000e\u001e5j]\u001e\u0004\"a\n\u0016\u000e\u0003!R\u0011!K\u0001\ng\"\f\u0007/\u001a7fgNL!a\u000b\u0015\u0003\u000b!c\u0015n\u001d;\t\u000b5\n\u0001\u0019\u0001\u0018\u0002\u0019A\u0014x\u000eZ;di\u000e{G-Z2\u0011\u0005=\u0002T\"A\u0006\n\u0005EZ!\u0001\u0005&t_:\u0004&o\u001c3vGR\u001cu\u000eZ3d\u0011\u0015\u0019\u0014\u00011\u00015\u0003!!WMZ1vYR\u001c\bCA\u00106\t\u00151\u0004A1\u0001#\u0005\u0005!\u0015A\u0006%MSN$\bK]8ek\u000e$XI\\2pI\u0016T5o\u001c8\u0011\u0005=\u001a1CA\u0002\u0013\u0003\u0019a\u0014N\\5u}Q\t\u0001(F\u0002>\u0001\n#\"AP\"\u0011\t=\u0002q(\u0011\t\u0003?\u0001#Q!I\u0003C\u0002\t\u0002\"a\b\"\u0005\u000bY*!\u0019\u0001\u0012\t\u000b\u0011+\u00019\u0001 \u0002\u0015\u0015t7m\u001c3f\u0015N|g.\u0001\u0005j]N$\u0018M\\2f+\r9%\n\u0014\u000b\u0003\u00116\u0003Ba\f\u0001J\u0017B\u0011qD\u0013\u0003\u0006C\u0019\u0011\rA\t\t\u0003?1#QA\u000e\u0004C\u0002\tBQA\u0014\u0004A\u0002=\u000b\u0011A\u001a\t\u0006\'As3JU\u0005\u0003#R\u0011\u0011BR;oGRLwN\u001c\u001a\u0011\u0007ma\u0012*\u0001\u0003i]&dW#A+\u0011\t=\u0002aK\u0016\t\u0003O]K!\u0001\u0017\u0015\u0003\t!s\u0015\u000e\\\u0001\u0006Q:LG\u000eI\u0001\u0006Q\u000e|gn]\u000b\u00079:,H0a\u0002\u0015\u000fu\u000bY!!\b\u0002*A!q\u0006\u00010\u007f!\u00119s,Y>\n\u0005\u0001D#\u0001\u0004\u0013d_2|g\u000eJ2pY>t\u0007\u0003\u00022k[Rt!a\u00195\u000f\u0005\u0011<W\"A3\u000b\u0005\u0019|\u0011A\u0002\u001fs_>$h(C\u0001*\u0013\tI\u0007&\u0001\u0005mC\n,G\u000e\\3e\u0013\tYGNA\u0005GS\u0016dG\rV=qK*\u0011\u0011\u000e\u000b\t\u0003?9$Qa\\\u0005C\u0002A\u0014\u0011aS\t\u0003GE\u0004\"a\u0005:\n\u0005M$\"AB*z[\n|G\u000e\u0005\u0002 k\u0012)a/\u0003b\u0001o\n\t\u0001*\u0005\u0002$qB\u00111#_\u0005\u0003uR\u00111!\u00118z!\tyB\u0010B\u0003~\u0013\t\u0007!EA\u0001U!\u00159sl`A\u0003!\u0011\u0019\u0012\u0011\u0001;\n\u0007\u0005\rAC\u0001\u0004PaRLwN\u001c\t\u0004?\u0005\u001dAABA\u0005\u0013\t\u0007!E\u0001\u0002U\t\"9\u0011QB\u0005A\u0004\u0005=\u0011aA6fsB)\u0011\u0011CA\f[:\u0019q%a\u0005\n\u0007\u0005U\u0001&A\u0004XSRtWm]:\n\t\u0005e\u00111\u0004\u0002\u0004\u0003VD(bAA\u000bQ!9\u0011qD\u0005A\u0004\u0005\u0005\u0012A\u00035fC\u0012,enY8eKB)q%a\t\u0002(%\u0019\u0011Q\u0005\u0015\u0003\rM#(/[2u!\rYB\u0004\u001e\u0005\b\u0003WI\u00019AA\u0017\u0003)!\u0018-\u001b7F]\u000e|G-\u001a\t\u0006_\u0001Y\u0018Q\u0001
  #10 = Utf8               hcons
  #11 = Utf8               (Lshapeless/Witness;Lshapeless/Strict;Largonaut/derive/HListProductEncodeJson;)Largonaut/derive/HListProductEncodeJson;
  #12 = Utf8               <K:Lscala/Symbol;H:Ljava/lang/Object;T::Lshapeless/HList;TD::Lshapeless/HList;>(Lshapeless/Witness;Lshapeless/Strict<Largonaut/EncodeJson<TH;>;>;Largonaut/derive/HListProductEncodeJson<TT;TTD;>;)Largonaut/derive/HListProductEncodeJson<Lshapeless/$colon$colon<TH;TT;>;Lshapeless/$colon$colon<Lscala/Option<TH;>;TTD;>;>;
  #13 = Utf8               key
  #14 = Utf8               headEncode
  #15 = Utf8               tailEncode
  #16 = Utf8               argonaut/derive/HListProductEncodeJson$
  #17 = Class              #16            // argonaut/derive/HListProductEncodeJson$
  #18 = Utf8               MODULE$
  #19 = Utf8               Largonaut/derive/HListProductEncodeJson$;
  #20 = NameAndType        #18:#19        // MODULE$:Largonaut/derive/HListProductEncodeJson$;
  #21 = Fieldref           #17.#20        // argonaut/derive/HListProductEncodeJson$.MODULE$:Largonaut/derive/HListProductEncodeJson$;
  #22 = NameAndType        #10:#11        // hcons:(Lshapeless/Witness;Lshapeless/Strict;Largonaut/derive/HListProductEncodeJson;)Largonaut/derive/HListProductEncodeJson;
  #23 = Methodref          #17.#22        // argonaut/derive/HListProductEncodeJson$.hcons:(Lshapeless/Witness;Lshapeless/Strict;Largonaut/derive/HListProductEncodeJson;)Largonaut/derive/HListProductEncodeJson;
  #24 = Utf8               hnil
  #25 = Utf8               ()Largonaut/derive/HListProductEncodeJson;
  #26 = Utf8               ()Largonaut/derive/HListProductEncodeJson<Lshapeless/HNil;Lshapeless/HNil;>;
  #27 = NameAndType        #24:#25        // hnil:()Largonaut/derive/HListProductEncodeJson;
  #28 = Methodref          #17.#27        // argonaut/derive/HListProductEncodeJson$.hnil:()Largonaut/derive/HListProductEncodeJson;
  #29 = Utf8               instance
  #30 = Utf8               (Lscala/Function2;)Largonaut/derive/HListProductEncodeJson;
  #31 = Utf8               <L::Lshapeless/HList;D::Lshapeless/HList;>(Lscala/Function2<Largonaut/derive/JsonProductCodec;TD;Largonaut/EncodeJson<TL;>;>;)Largonaut/derive/HListProductEncodeJson<TL;TD;>;
  #32 = Utf8               f
  #33 = NameAndType        #29:#30        // instance:(Lscala/Function2;)Largonaut/derive/HListProductEncodeJson;
  #34 = Methodref          #17.#33        // argonaut/derive/HListProductEncodeJson$.instance:(Lscala/Function2;)Largonaut/derive/HListProductEncodeJson;
  #35 = Utf8               apply
  #36 = Utf8               (Largonaut/derive/JsonProductCodec;Lshapeless/HList;)Largonaut/EncodeJson;
  #37 = Utf8               (Largonaut/derive/JsonProductCodec;TD;)Largonaut/EncodeJson<TL;>;
  #38 = Utf8               productCodec
  #39 = Utf8               defaults
  #40 = Utf8               Code
  #41 = Utf8               Signature
  #42 = Utf8               MethodParameters
  #43 = Utf8               SourceFile
  #44 = Utf8               RuntimeVisibleAnnotations
  #45 = Utf8               ScalaInlineInfo
  #46 = Utf8               ScalaSig
{
  public static <K extends scala.Symbol, H extends java.lang.Object, T extends shapeless.HList, TD extends shapeless.HList> argonaut.derive.HListProductEncodeJson<shapeless.$colon$colon<H, T>, shapeless.$colon$colon<scala.Option<H>, TD>> hcons(shapeless.Witness, shapeless.Strict<argonaut.EncodeJson<H>>, argonaut.derive.HListProductEncodeJson<T, TD>);
    descriptor: (Lshapeless/Witness;Lshapeless/Strict;Largonaut/derive/HListProductEncodeJson;)Largonaut/derive/HListProductEncodeJson;
    flags: (0x0009) ACC_PUBLIC, ACC_STATIC
    Code:
      stack=4, locals=3, args_size=3
         0: getstatic     #21                 // Field argonaut/derive/HListProductEncodeJson$.MODULE$:Largonaut/derive/HListProductEncodeJson$;
         3: aload_0
         4: aload_1
         5: aload_2
         6: invokevirtual #23                 // Method argonaut/derive/HListProductEncodeJson$.hcons:(Lshapeless/Witness;Lshapeless/Strict;Largonaut/derive/HListProductEncodeJson;)Largonaut/derive/HListProductEncodeJson;
         9: areturn
    Signature: #12                          // <K:Lscala/Symbol;H:Ljava/lang/Object;T::Lshapeless/HList;TD::Lshapeless/HList;>(Lshapeless/Witness;Lshapeless/Strict<Largonaut/EncodeJson<TH;>;>;Largonaut/derive/HListProductEncodeJson<TT;TTD;>;)Largonaut/derive/HListProductEncodeJson<Lshapeless/$colon$colon<TH;TT;>;Lshapeless/$colon$colon<Lscala/Option<TH;>;TTD;>;>;
    MethodParameters:
      Name                           Flags
      key                            final
      headEncode                     final
      tailEncode                     final

  public static argonaut.derive.HListProductEncodeJson<shapeless.HNil, shapeless.HNil> hnil();
    descriptor: ()Largonaut/derive/HListProductEncodeJson;
    flags: (0x0009) ACC_PUBLIC, ACC_STATIC
    Code:
      stack=1, locals=0, args_size=0
         0: getstatic     #21                 // Field argonaut/derive/HListProductEncodeJson$.MODULE$:Largonaut/derive/HListProductEncodeJson$;
         3: invokevirtual #28                 // Method argonaut/derive/HListProductEncodeJson$.hnil:()Largonaut/derive/HListProductEncodeJson;
         6: areturn
    Signature: #26                          // ()Largonaut/derive/HListProductEncodeJson<Lshapeless/HNil;Lshapeless/HNil;>;

  public static <L extends shapeless.HList, D extends shapeless.HList> argonaut.derive.HListProductEncodeJson<L, D> instance(scala.Function2<argonaut.derive.JsonProductCodec, D, argonaut.EncodeJson<L>>);
    descriptor: (Lscala/Function2;)Largonaut/derive/HListProductEncodeJson;
    flags: (0x0009) ACC_PUBLIC, ACC_STATIC
    Code:
      stack=2, locals=1, args_size=1
         0: getstatic     #21                 // Field argonaut/derive/HListProductEncodeJson$.MODULE$:Largonaut/derive/HListProductEncodeJson$;
         3: aload_0
         4: invokevirtual #34                 // Method argonaut/derive/HListProductEncodeJson$.instance:(Lscala/Function2;)Largonaut/derive/HListProductEncodeJson;
         7: areturn
    Signature: #31                          // <L::Lshapeless/HList;D::Lshapeless/HList;>(Lscala/Function2<Largonaut/derive/JsonProductCodec;TD;Largonaut/EncodeJson<TL;>;>;)Largonaut/derive/HListProductEncodeJson<TL;TD;>;
    MethodParameters:
      Name                           Flags
      f                              final

  public abstract argonaut.EncodeJson<L> apply(argonaut.derive.JsonProductCodec, D);
    descriptor: (Largonaut/derive/JsonProductCodec;Lshapeless/HList;)Largonaut/EncodeJson;
    flags: (0x0401) ACC_PUBLIC, ACC_ABSTRACT
    Signature: #37                          // (Largonaut/derive/JsonProductCodec;TD;)Largonaut/EncodeJson<TL;>;
    MethodParameters:
      Name                           Flags
      productCodec                   final
      defaults                       final
}
Signature: #3                           // <L::Lshapeless/HList;D::Lshapeless/HList;>Ljava/lang/Object;
SourceFile: "MkEncodeJson.scala"
RuntimeVisibleAnnotations:
  0: #7(#8=s#9)
    scala.reflect.ScalaSignature(
      bytes="\u0006\u0005\u0005=ba\u0002\u0006\f!\u0003\r\n\u0001\u0005\u0005\u00061\u00011\t!G\u0004\u0006o-A\t\u0001\u000f\u0004\u0006\u0015-A\t!\u000f\u0005\u0006u\r!\ta\u000f\u0005\u00061\r!\t\u0001\u0010\u0005\u0006\u000b\u000e!\tA\u0012\u0005\b\'\u000e\u0011\r\u0011b\u0001U\u0011\u0019I6\u0001)A\u0005+\")!l\u0001C\u00027\n1\u0002\nT5tiB\u0013x\u000eZ;di\u0016s7m\u001c3f\u0015N|gN\u0003\u0002\r\u001b\u00051A-\u001a:jm\u0016T\u0011AD\u0001\tCJ<wN\\1vi\u000e\u0001QcA\t!kM\u0011\u0001A\u0005\t\u0003\'Yi\u0011\u0001\u0006\u0006\u0002+\u0005)1oY1mC&\u0011q\u0003\u0006\u0002\u0007\u0003:L(+\u001a4\u0002\u000b\u0005\u0004\b\u000f\\=\u0015\u0007ia#\u0007E\u0002\u001c9yi\u0011!D\u0005\u0003;5\u0011!\"\u00128d_\u0012,\'j]8o!\ty\u0002\u0005\u0004\u0001\u0005\u000b\u0005\u0002!\u0019\u0001\u0012\u0003\u00031\u000b\"a\t\u0014\u0011\u0005M!\u0013BA\u0013\u0015\u0005\u001dqu\u000e\u001e5j]\u001e\u0004\"a\n\u0016\u000e\u0003!R\u0011!K\u0001\ng\"\f\u0007/\u001a7fgNL!a\u000b\u0015\u0003\u000b!c\u0015n\u001d;\t\u000b5\n\u0001\u0019\u0001\u0018\u0002\u0019A\u0014x\u000eZ;di\u000e{G-Z2\u0011\u0005=\u0002T\"A\u0006\n\u0005EZ!\u0001\u0005&t_:\u0004&o\u001c3vGR\u001cu\u000eZ3d\u0011\u0015\u0019\u0014\u00011\u00015\u0003!!WMZ1vYR\u001c\bCA\u00106\t\u00151\u0004A1\u0001#\u0005\u0005!\u0015A\u0006%MSN$\bK]8ek\u000e$XI\\2pI\u0016T5o\u001c8\u0011\u0005=\u001a1CA\u0002\u0013\u0003\u0019a\u0014N\\5u}Q\t\u0001(F\u0002>\u0001\n#\"AP\"\u0011\t=\u0002q(\u0011\t\u0003?\u0001#Q!I\u0003C\u0002\t\u0002\"a\b\"\u0005\u000bY*!\u0019\u0001\u0012\t\u000b\u0011+\u00019\u0001 \u0002\u0015\u0015t7m\u001c3f\u0015N|g.\u0001\u0005j]N$\u0018M\\2f+\r9%\n\u0014\u000b\u0003\u00116\u0003Ba\f\u0001J\u0017B\u0011qD\u0013\u0003\u0006C\u0019\u0011\rA\t\t\u0003?1#QA\u000e\u0004C\u0002\tBQA\u0014\u0004A\u0002=\u000b\u0011A\u001a\t\u0006\'As3JU\u0005\u0003#R\u0011\u0011BR;oGRLwN\u001c\u001a\u0011\u0007ma\u0012*\u0001\u0003i]&dW#A+\u0011\t=\u0002aK\u0016\t\u0003O]K!\u0001\u0017\u0015\u0003\t!s\u0015\u000e\\\u0001\u0006Q:LG\u000eI\u0001\u0006Q\u000e|gn]\u000b\u00079:,H0a\u0002\u0015\u000fu\u000bY!!\b\u0002*A!q\u0006\u00010\u007f!\u00119s,Y>\n\u0005\u0001D#\u0001\u0004\u0013d_2|g\u000eJ2pY>t\u0007\u0003\u00022k[Rt!a\u00195\u000f\u0005\u0011<W\"A3\u000b\u0005\u0019|\u0011A\u0002\u001fs_>$h(C\u0001*\u0013\tI\u0007&\u0001\u0005mC\n,G\u000e\\3e\u0013\tYGNA\u0005GS\u0016dG\rV=qK*\u0011\u0011\u000e\u000b\t\u0003?9$Qa\\\u0005C\u0002A\u0014\u0011aS\t\u0003GE\u0004\"a\u0005:\n\u0005M$\"AB*z[\n|G\u000e\u0005\u0002 k\u0012)a/\u0003b\u0001o\n\t\u0001*\u0005\u0002$qB\u00111#_\u0005\u0003uR\u00111!\u00118z!\tyB\u0010B\u0003~\u0013\t\u0007!EA\u0001U!\u00159sl`A\u0003!\u0011\u0019\u0012\u0011\u0001;\n\u0007\u0005\rAC\u0001\u0004PaRLwN\u001c\t\u0004?\u0005\u001dAABA\u0005\u0013\t\u0007!E\u0001\u0002U\t\"9\u0011QB\u0005A\u0004\u0005=\u0011aA6fsB)\u0011\u0011CA\f[:\u0019q%a\u0005\n\u0007\u0005U\u0001&A\u0004XSRtWm]:\n\t\u0005e\u00111\u0004\u0002\u0004\u0003VD(bAA\u000bQ!9\u0011qD\u0005A\u0004\u0005\u0005\u0012A\u00035fC\u0012,enY8eKB)q%a\t\u0002(%\u0019\u0011Q\u0005\u0015\u0003\rM#(/[2u!\rYB\u0004\u001e\u0005\b\u0003WI\u00019AA\u0017\u0003)!\u0018-\u001b7F]\u000e|G-\u001a\t\u0006_\u0001Y\u0018Q\u0001"
    )
  ScalaInlineInfo: length = 0x9 (unknown attribute)
   01 00 00 01 00 23 00 24 00
  ScalaSig: length = 0x3 (unknown attribute)
   05 02 00
