Classfile /Users/mw/Projects/slang-braindump/.jar/jar11/assemble/slang-braindump/assemble/content/argonaut/derive/JsonSumCodec.class
  Last modified May 29, 2022; size 2026 bytes
  SHA-256 checksum ab782d980ea6cfe497af6bcfbe1f53b4c77ef4c75684349c52ed8fe53ad2b1cf
  Compiled from "JsonSumCodec.scala"
public interface argonaut.derive.JsonSumCodec
  minor version: 0
  major version: 52
  flags: (0x0601) ACC_PUBLIC, ACC_INTERFACE, ACC_ABSTRACT
  this_class: #2                          // argonaut/derive/JsonSumCodec
  super_class: #4                         // java/lang/Object
  interfaces: 0, fields: 0, methods: 6, attributes: 4
Constant pool:
   #1 = Utf8               argonaut/derive/JsonSumCodec
   #2 = Class              #1             // argonaut/derive/JsonSumCodec
   #3 = Utf8               java/lang/Object
   #4 = Class              #3             // java/lang/Object
   #5 = Utf8               JsonSumCodec.scala
   #6 = Utf8               Lscala/reflect/ScalaSignature;
   #7 = Utf8               bytes
   #8 = Utf8               \u0006\u0005-4q\u0001D\u0007\u0011\u0002G\u0005!\u0003C\u0003\u001a\u0001\u0019\u0005!\u0004C\u0003\u001f\u0001\u0019\u0005q\u0004C\u0003>\u0001\u0019\u0005a\bC\u0003H\u0001\u0019\u0005\u0001jB\u0003`\u001b!\u0005\u0001MB\u0003\r\u001b!\u0005!\rC\u0003d\r\u0011\u0005A\rC\u0004f\r\t\u0007I\u0011\u00014\t\r!4\u0001\u0015!\u0003h\u0011\u001dIgA1A\u0005\u0002\u0019DaA\u001b\u0004!\u0002\u00139\'\u0001\u0004&t_:\u001cV/\\\"pI\u0016\u001c\'B\u0001\b\u0010\u0003\u0019!WM]5wK*\t\u0001#\u0001\u0005be\u001e|g.Y;u\u0007\u0001\u0019\"\u0001A\n\u0011\u0005Q9R\"A\u000b\u000b\u0003Y\tQa]2bY\u0006L!\u0001G\u000b\u0003\r\u0005s\u0017PU3g\u0003-)gnY8eK\u0016k\u0007\u000f^=\u0016\u0003m\u0001\"\u0001\u0006\u000f\n\u0005u)\"a\u0002(pi\"LgnZ\u0001\fK:\u001cw\u000eZ3GS\u0016dG\r\u0006\u0002!IA\u0011\u0011EI\u0007\u0002\u001f%\u00111e\u0004\u0002\u0005\u0015N|g\u000eC\u0003&\u0005\u0001\u0007a%\u0001\u0006gS\u0016dGm\u0014:PE*\u0004BaJ\u0018!e9\u0011\u0001&\f\b\u0003S1j\u0011A\u000b\u0006\u0003WE\ta\u0001\u0010:p_Rt\u0014\"\u0001\f\n\u00059*\u0012a\u00029bG.\fw-Z\u0005\u0003aE\u0012a!R5uQ\u0016\u0014(B\u0001\u0018\u0016!\u0011!2\'\u000e\u0011\n\u0005Q*\"A\u0002+va2,\'\u0007\u0005\u00027u9\u0011q\u0007\u000f\t\u0003SUI!!O\u000b\u0002\rA\u0013X\rZ3g\u0013\tYDH\u0001\u0004TiJLgn\u001a\u0006\u0003sU\t1\u0002Z3d_\u0012,W)\u001c9usR\u0011qH\u0011\t\u0004C\u0001[\u0012BA!\u0010\u00051!UmY8eKJ+7/\u001e7u\u0011\u0015\u00195\u00011\u0001E\u0003\u0019\u0019WO]:peB\u0011\u0011%R\u0005\u0003\r>\u0011q\u0001S\"veN|\'/A\u0006eK\u000e|G-\u001a$jK2$WCA%R)\u0011Qu+\u0017.\u0011\u0007\u0005\u00025\n\u0005\u0003(_1{\u0005CA\u0011N\u0013\tquBA\u0004B\u0007V\u00148o\u001c:\u0011\u0005A\u000bF\u0002\u0001\u0003\u0006%\u0012\u0011\ra\u0015\u0002\u0002\u0003F\u00111\u0004\u0016\t\u0003)UK!AV\u000b\u0003\u0007\u0005s\u0017\u0010C\u0003Y\t\u0001\u0007Q\'\u0001\u0003oC6,\u0007\"B\"\u0005\u0001\u0004!\u0005\"B.\u0005\u0001\u0004a\u0016A\u00023fG>$W\rE\u0002\";>K!AX\b\u0003\u0015\u0011+7m\u001c3f\u0015N|g.\u0001\u0007Kg>t7+^7D_\u0012,7\r\u0005\u0002b\r5\tQb\u0005\u0002\u0007\'\u00051A(\u001b8jiz\"\u0012\u0001Y\u0001\u0004_\nTW#A4\u0011\u0005\u0005\u0004\u0011\u0001B8cU\u0002\n\u0011\u0002^=qK\u001aKW\r\u001c3\u0002\u0015QL\b/\u001a$jK2$\u0007\u0005
   #9 = Utf8               typeField
  #10 = Utf8               ()Largonaut/derive/JsonSumCodec;
  #11 = Utf8               argonaut/derive/JsonSumCodec$
  #12 = Class              #11            // argonaut/derive/JsonSumCodec$
  #13 = Utf8               MODULE$
  #14 = Utf8               Largonaut/derive/JsonSumCodec$;
  #15 = NameAndType        #13:#14        // MODULE$:Largonaut/derive/JsonSumCodec$;
  #16 = Fieldref           #12.#15        // argonaut/derive/JsonSumCodec$.MODULE$:Largonaut/derive/JsonSumCodec$;
  #17 = NameAndType        #9:#10         // typeField:()Largonaut/derive/JsonSumCodec;
  #18 = Methodref          #12.#17        // argonaut/derive/JsonSumCodec$.typeField:()Largonaut/derive/JsonSumCodec;
  #19 = Utf8               obj
  #20 = NameAndType        #19:#10        // obj:()Largonaut/derive/JsonSumCodec;
  #21 = Methodref          #12.#20        // argonaut/derive/JsonSumCodec$.obj:()Largonaut/derive/JsonSumCodec;
  #22 = Utf8               encodeEmpty
  #23 = Utf8               ()Lscala/runtime/Nothing$;
  #24 = Utf8               encodeField
  #25 = Utf8               (Lscala/util/Either;)Largonaut/Json;
  #26 = Utf8               (Lscala/util/Either<Largonaut/Json;Lscala/Tuple2<Ljava/lang/String;Largonaut/Json;>;>;)Largonaut/Json;
  #27 = Utf8               fieldOrObj
  #28 = Utf8               decodeEmpty
  #29 = Utf8               (Largonaut/HCursor;)Largonaut/DecodeResult;
  #30 = Utf8               (Largonaut/HCursor;)Largonaut/DecodeResult<Lscala/runtime/Nothing$;>;
  #31 = Utf8               cursor
  #32 = Utf8               decodeField
  #33 = Utf8               (Ljava/lang/String;Largonaut/HCursor;Largonaut/DecodeJson;)Largonaut/DecodeResult;
  #34 = Utf8               <A:Ljava/lang/Object;>(Ljava/lang/String;Largonaut/HCursor;Largonaut/DecodeJson<TA;>;)Largonaut/DecodeResult<Lscala/util/Either<Largonaut/ACursor;TA;>;>;
  #35 = Utf8               name
  #36 = Utf8               decode
  #37 = Utf8               Code
  #38 = Utf8               Signature
  #39 = Utf8               MethodParameters
  #40 = Utf8               SourceFile
  #41 = Utf8               RuntimeVisibleAnnotations
  #42 = Utf8               ScalaInlineInfo
  #43 = Utf8               ScalaSig
{
  public static argonaut.derive.JsonSumCodec typeField();
    descriptor: ()Largonaut/derive/JsonSumCodec;
    flags: (0x0009) ACC_PUBLIC, ACC_STATIC
    Code:
      stack=1, locals=0, args_size=0
         0: getstatic     #16                 // Field argonaut/derive/JsonSumCodec$.MODULE$:Largonaut/derive/JsonSumCodec$;
         3: invokevirtual #18                 // Method argonaut/derive/JsonSumCodec$.typeField:()Largonaut/derive/JsonSumCodec;
         6: areturn

  public static argonaut.derive.JsonSumCodec obj();
    descriptor: ()Largonaut/derive/JsonSumCodec;
    flags: (0x0009) ACC_PUBLIC, ACC_STATIC
    Code:
      stack=1, locals=0, args_size=0
         0: getstatic     #16                 // Field argonaut/derive/JsonSumCodec$.MODULE$:Largonaut/derive/JsonSumCodec$;
         3: invokevirtual #21                 // Method argonaut/derive/JsonSumCodec$.obj:()Largonaut/derive/JsonSumCodec;
         6: areturn

  public abstract scala.runtime.Nothing$ encodeEmpty();
    descriptor: ()Lscala/runtime/Nothing$;
    flags: (0x0401) ACC_PUBLIC, ACC_ABSTRACT

  public abstract argonaut.Json encodeField(scala.util.Either<argonaut.Json, scala.Tuple2<java.lang.String, argonaut.Json>>);
    descriptor: (Lscala/util/Either;)Largonaut/Json;
    flags: (0x0401) ACC_PUBLIC, ACC_ABSTRACT
    Signature: #26                          // (Lscala/util/Either<Largonaut/Json;Lscala/Tuple2<Ljava/lang/String;Largonaut/Json;>;>;)Largonaut/Json;
    MethodParameters:
      Name                           Flags
      fieldOrObj                     final

  public abstract argonaut.DecodeResult<scala.runtime.Nothing$> decodeEmpty(argonaut.HCursor);
    descriptor: (Largonaut/HCursor;)Largonaut/DecodeResult;
    flags: (0x0401) ACC_PUBLIC, ACC_ABSTRACT
    Signature: #30                          // (Largonaut/HCursor;)Largonaut/DecodeResult<Lscala/runtime/Nothing$;>;
    MethodParameters:
      Name                           Flags
      cursor                         final

  public abstract <A extends java.lang.Object> argonaut.DecodeResult<scala.util.Either<argonaut.ACursor, A>> decodeField(java.lang.String, argonaut.HCursor, argonaut.DecodeJson<A>);
    descriptor: (Ljava/lang/String;Largonaut/HCursor;Largonaut/DecodeJson;)Largonaut/DecodeResult;
    flags: (0x0401) ACC_PUBLIC, ACC_ABSTRACT
    Signature: #34                          // <A:Ljava/lang/Object;>(Ljava/lang/String;Largonaut/HCursor;Largonaut/DecodeJson<TA;>;)Largonaut/DecodeResult<Lscala/util/Either<Largonaut/ACursor;TA;>;>;
    MethodParameters:
      Name                           Flags
      name                           final
      cursor                         final
      decode                         final
}
SourceFile: "JsonSumCodec.scala"
RuntimeVisibleAnnotations:
  0: #6(#7=s#8)
    scala.reflect.ScalaSignature(
      bytes="\u0006\u0005-4q\u0001D\u0007\u0011\u0002G\u0005!\u0003C\u0003\u001a\u0001\u0019\u0005!\u0004C\u0003\u001f\u0001\u0019\u0005q\u0004C\u0003>\u0001\u0019\u0005a\bC\u0003H\u0001\u0019\u0005\u0001jB\u0003`\u001b!\u0005\u0001MB\u0003\r\u001b!\u0005!\rC\u0003d\r\u0011\u0005A\rC\u0004f\r\t\u0007I\u0011\u00014\t\r!4\u0001\u0015!\u0003h\u0011\u001dIgA1A\u0005\u0002\u0019DaA\u001b\u0004!\u0002\u00139\'\u0001\u0004&t_:\u001cV/\\\"pI\u0016\u001c\'B\u0001\b\u0010\u0003\u0019!WM]5wK*\t\u0001#\u0001\u0005be\u001e|g.Y;u\u0007\u0001\u0019\"\u0001A\n\u0011\u0005Q9R\"A\u000b\u000b\u0003Y\tQa]2bY\u0006L!\u0001G\u000b\u0003\r\u0005s\u0017PU3g\u0003-)gnY8eK\u0016k\u0007\u000f^=\u0016\u0003m\u0001\"\u0001\u0006\u000f\n\u0005u)\"a\u0002(pi\"LgnZ\u0001\fK:\u001cw\u000eZ3GS\u0016dG\r\u0006\u0002!IA\u0011\u0011EI\u0007\u0002\u001f%\u00111e\u0004\u0002\u0005\u0015N|g\u000eC\u0003&\u0005\u0001\u0007a%\u0001\u0006gS\u0016dGm\u0014:PE*\u0004BaJ\u0018!e9\u0011\u0001&\f\b\u0003S1j\u0011A\u000b\u0006\u0003WE\ta\u0001\u0010:p_Rt\u0014\"\u0001\f\n\u00059*\u0012a\u00029bG.\fw-Z\u0005\u0003aE\u0012a!R5uQ\u0016\u0014(B\u0001\u0018\u0016!\u0011!2\'\u000e\u0011\n\u0005Q*\"A\u0002+va2,\'\u0007\u0005\u00027u9\u0011q\u0007\u000f\t\u0003SUI!!O\u000b\u0002\rA\u0013X\rZ3g\u0013\tYDH\u0001\u0004TiJLgn\u001a\u0006\u0003sU\t1\u0002Z3d_\u0012,W)\u001c9usR\u0011qH\u0011\t\u0004C\u0001[\u0012BA!\u0010\u00051!UmY8eKJ+7/\u001e7u\u0011\u0015\u00195\u00011\u0001E\u0003\u0019\u0019WO]:peB\u0011\u0011%R\u0005\u0003\r>\u0011q\u0001S\"veN|\'/A\u0006eK\u000e|G-\u001a$jK2$WCA%R)\u0011Qu+\u0017.\u0011\u0007\u0005\u00025\n\u0005\u0003(_1{\u0005CA\u0011N\u0013\tquBA\u0004B\u0007V\u00148o\u001c:\u0011\u0005A\u000bF\u0002\u0001\u0003\u0006%\u0012\u0011\ra\u0015\u0002\u0002\u0003F\u00111\u0004\u0016\t\u0003)UK!AV\u000b\u0003\u0007\u0005s\u0017\u0010C\u0003Y\t\u0001\u0007Q\'\u0001\u0003oC6,\u0007\"B\"\u0005\u0001\u0004!\u0005\"B.\u0005\u0001\u0004a\u0016A\u00023fG>$W\rE\u0002\";>K!AX\b\u0003\u0015\u0011+7m\u001c3f\u0015N|g.\u0001\u0007Kg>t7+^7D_\u0012,7\r\u0005\u0002b\r5\tQb\u0005\u0002\u0007\'\u00051A(\u001b8jiz\"\u0012\u0001Y\u0001\u0004_\nTW#A4\u0011\u0005\u0005\u0004\u0011\u0001B8cU\u0002\n\u0011\u0002^=qK\u001aKW\r\u001c3\u0002\u0015QL\b/\u001a$jK2$\u0007\u0005"
    )
  ScalaInlineInfo: length = 0x18 (unknown attribute)
   01 00 00 04 00 1C 00 1D 00 00 20 00 21 00 00 16
   00 17 00 00 18 00 19 00
  ScalaSig: length = 0x3 (unknown attribute)
   05 02 00
