Classfile /Users/mw/Projects/slang-braindump/.jar/jar11/assemble/slang-braindump/assemble/content/argonaut/derive/JsonProductCodecFor$$anon$3.class
  Last modified May 29, 2022; size 959 bytes
  SHA-256 checksum fe915be3a879c1b456339edcd037cd7ba498476053a0adea564c172f20f1da5e
  Compiled from "JsonProductCodec.scala"
public final class argonaut.derive.JsonProductCodecFor$$anon$3 extends java.lang.Object implements argonaut.derive.JsonProductCodecFor<S>
  minor version: 0
  major version: 52
  flags: (0x0031) ACC_PUBLIC, ACC_FINAL, ACC_SUPER
  this_class: #2                          // argonaut/derive/JsonProductCodecFor$$anon$3
  super_class: #5                         // java/lang/Object
  interfaces: 1, fields: 1, methods: 2, attributes: 6
Constant pool:
   #1 = Utf8               argonaut/derive/JsonProductCodecFor$$anon$3
   #2 = Class              #1             // argonaut/derive/JsonProductCodecFor$$anon$3
   #3 = Utf8               Ljava/lang/Object;Largonaut/derive/JsonProductCodecFor<TS;>;
   #4 = Utf8               java/lang/Object
   #5 = Class              #4             // java/lang/Object
   #6 = Utf8               argonaut/derive/JsonProductCodecFor
   #7 = Class              #6             // argonaut/derive/JsonProductCodecFor
   #8 = Utf8               JsonProductCodec.scala
   #9 = Utf8               argonaut/derive/JsonProductCodecFor$
  #10 = Class              #9             // argonaut/derive/JsonProductCodecFor$
  #11 = Utf8               apply
  #12 = Utf8               (Largonaut/derive/JsonProductCodec;)Largonaut/derive/JsonProductCodecFor;
  #13 = NameAndType        #11:#12        // apply:(Largonaut/derive/JsonProductCodec;)Largonaut/derive/JsonProductCodecFor;
  #14 = Utf8               codec0$1
  #15 = Utf8               Largonaut/derive/JsonProductCodec;
  #16 = Utf8               codec
  #17 = Utf8               ()Largonaut/derive/JsonProductCodec;
  #18 = NameAndType        #14:#15        // codec0$1:Largonaut/derive/JsonProductCodec;
  #19 = Fieldref           #2.#18         // argonaut/derive/JsonProductCodecFor$$anon$3.codec0$1:Largonaut/derive/JsonProductCodec;
  #20 = Utf8               this
  #21 = Utf8               Largonaut/derive/JsonProductCodecFor$$anon$3;
  #22 = Utf8               <init>
  #23 = Utf8               (Largonaut/derive/JsonProductCodec;)V
  #24 = Utf8               ()V
  #25 = NameAndType        #22:#24        // "<init>":()V
  #26 = Methodref          #5.#25         // java/lang/Object."<init>":()V
  #27 = Utf8               Code
  #28 = Utf8               LineNumberTable
  #29 = Utf8               LocalVariableTable
  #30 = Utf8               MethodParameters
  #31 = Utf8               InnerClasses
  #32 = Utf8               EnclosingMethod
  #33 = Utf8               Signature
  #34 = Utf8               SourceFile
  #35 = Utf8               ScalaInlineInfo
  #36 = Utf8               Scala
{
  private final argonaut.derive.JsonProductCodec codec0$1;
    descriptor: Largonaut/derive/JsonProductCodec;
    flags: (0x0012) ACC_PRIVATE, ACC_FINAL

  public argonaut.derive.JsonProductCodec codec();
    descriptor: ()Largonaut/derive/JsonProductCodec;
    flags: (0x0001) ACC_PUBLIC
    Code:
      stack=1, locals=1, args_size=1
         0: aload_0
         1: getfield      #19                 // Field codec0$1:Largonaut/derive/JsonProductCodec;
         4: areturn
      LineNumberTable:
        line 32: 0
      LocalVariableTable:
        Start  Length  Slot  Name   Signature
            0       5     0  this   Largonaut/derive/JsonProductCodecFor$$anon$3;

  public argonaut.derive.JsonProductCodecFor$$anon$3(argonaut.derive.JsonProductCodec);
    descriptor: (Largonaut/derive/JsonProductCodec;)V
    flags: (0x0001) ACC_PUBLIC
    Code:
      stack=2, locals=2, args_size=2
         0: aload_0
         1: aload_1
         2: putfield      #19                 // Field codec0$1:Largonaut/derive/JsonProductCodec;
         5: aload_0
         6: invokespecial #26                 // Method java/lang/Object."<init>":()V
         9: return
      LineNumberTable:
        line 30: 0
        line 31: 5
      LocalVariableTable:
        Start  Length  Slot  Name   Signature
            0      10     0  this   Largonaut/derive/JsonProductCodecFor$$anon$3;
            0      10     1 codec0$1   Largonaut/derive/JsonProductCodec;
    MethodParameters:
      Name                           Flags
      codec0$1                       final
}
InnerClasses:
  public final #2;                        // class argonaut/derive/JsonProductCodecFor$$anon$3
EnclosingMethod: #10.#13                // argonaut.derive.JsonProductCodecFor$.apply
Signature: #3                           // Ljava/lang/Object;Largonaut/derive/JsonProductCodecFor<TS;>;
SourceFile: "JsonProductCodec.scala"
  ScalaInlineInfo: length = 0xE (unknown attribute)
   01 01 00 02 00 16 00 17 01 00 10 00 11 01
  Scala: length = 0x0 (unknown attribute)

