Classfile /Users/mw/Projects/slang-braindump/.jar/jar11/assemble/slang-braindump/assemble/content/argonaut/derive/JsonCodecMacros.class
  Last modified May 29, 2022; size 19987 bytes
  SHA-256 checksum 19329ed985a8d5dfad8c931fa908b8398e57b806d6142f808b3e29837f9c2845
  Compiled from "JsonCodecMacros.scala"
public class argonaut.derive.JsonCodecMacros
  minor version: 0
  major version: 52
  flags: (0x0021) ACC_PUBLIC, ACC_SUPER
  this_class: #2                          // argonaut/derive/JsonCodecMacros
  super_class: #4                         // java/lang/Object
  interfaces: 0, fields: 5, methods: 10, attributes: 6
Constant pool:
    #1 = Utf8               argonaut/derive/JsonCodecMacros
    #2 = Class              #1            // argonaut/derive/JsonCodecMacros
    #3 = Utf8               java/lang/Object
    #4 = Class              #3            // java/lang/Object
    #5 = Utf8               JsonCodecMacros.scala
    #6 = Utf8               Lscala/reflect/ScalaSignature;
    #7 = Utf8               bytes
    #8 = Utf8               \u0006\u0005\t4Qa\u0003\u0007\u0001\u0019AA\u0001b\u0006\u0001\u0003\u0006\u0004%\t!\u0007\u0005\tI\u0001\u0011\t\u0011)A\u00055!)Q\u0005\u0001C\u0001M!1!\u0006\u0001Q\u0005\n-BQ!\u0010\u0001\u0005\u0002yBaa\u0012\u0001!\u0002\u0013A\u0005BB\'\u0001A\u0003%\u0001\n\u0003\u0004O\u0001\u0001\u0006Ia\u0014\u0005\u0007%\u0002\u0001\u000b\u0011B(\t\rM\u0003\u0001\u0015\"\u0003U\u0005=Q5o\u001c8D_\u0012,7-T1de>\u001c(BA\u0007\u000f\u0003\u0019!WM]5wK*\tq\"\u0001\u0005be\u001e|g.Y;u\'\t\u0001\u0011\u0003\u0005\u0002\u0013+5\t1CC\u0001\u0015\u0003\u0015\u00198-\u00197b\u0013\t12C\u0001\u0004B]f\u0014VMZ\u0001\u0002G\u000e\u0001Q#\u0001\u000e\u0011\u0005m\u0011S\"\u0001\u000f\u000b\u0005uq\u0012\u0001\u00032mC\u000e\\\'m\u001c=\u000b\u0005}\u0001\u0013AB7bGJ|7O\u0003\u0002\"\'\u00059!/\u001a4mK\u000e$\u0018BA\u0012\u001d\u0005\u001d\u0019uN\u001c;fqR\f!a\u0019\u0011\u0002\rqJg.\u001b;?)\t9\u0013\u0006\u0005\u0002)\u00015\tA\u0002C\u0003\u0018\u0007\u0001\u0007!$A\njg\u000e\u000b7/Z\"mCN\u001cxJ]*fC2,G\r\u0006\u0002-_A\u0011!#L\u0005\u0003]M\u0011qAQ8pY\u0016\fg\u000eC\u00031\t\u0001\u0007\u0011\'\u0001\u0004dYN$UM\u001a\t\u0003e]r!aM\u001b\u000f\u0005Q\nQ\"\u0001\u0001\n\u0005Y\u0012\u0013\u0001C;oSZ,\'o]3\n\u0005aJ$\u0001C\"mCN\u001cH)\u001a4\n\u0005iZ$!\u0002+sK\u0016\u001c(B\u0001\u001f!\u0003\r\t\u0007/[\u0001\u0019UN|gnQ8eK\u000e\feN\\8uCRLwN\\\'bGJ|GCA C!\t\u0011\u0004)\u0003\u0002Bs\t!AK]3f\u0011\u0015\u0019U\u00011\u0001E\u0003%\tgN\\8ui\u0016,7\u000fE\u0002\u0013\u000b~J!AR\n\u0003\u0015q\u0012X\r]3bi\u0016$g(\u0001\u0007EK\u000e|G-\u001a:DY\u0006\u001c8\u000f\u0005\u00023\u0013&\u0011!j\u0013\u0002\u000b)f\u0004XmU=nE>d\u0017B\u0001\'<\u0005\u001d\u0019\u00160\u001c2pYN\fA\"\u00128d_\u0012,\'o\u00117bgN\fA\"\\6EK\u000e|G-\u001a&t_:\u0004\"A\r)\n\u0005E[%AB*z[\n|G.\u0001\u0007nW\u0016s7m\u001c3f\u0015N|g.A\u0003d_\u0012,7\r\u0006\u0002VCB\u0019aKX \u000f\u0005]cfB\u0001-\\\u001b\u0005I&B\u0001.\u0019\u0003\u0019a$o\\8u}%\tA#\u0003\u0002^\'\u00059\u0001/Y2lC\u001e,\u0017BA0a\u0005\u0011a\u0015n\u001d;\u000b\u0005u\u001b\u0002\"\u0002\u0019\u000b\u0001\u0004\t\u0004
    #9 = Utf8               argonaut/derive/JsonCodecMacros$$anon$1
   #10 = Class              #9            // argonaut/derive/JsonCodecMacros$$anon$1
   #11 = Utf8               argonaut/derive/JsonCodecMacros$$typecreator1$1
   #12 = Class              #11           // argonaut/derive/JsonCodecMacros$$typecreator1$1
   #13 = Utf8               $typecreator1$1
   #14 = Utf8               argonaut/derive/JsonCodecMacros$$typecreator2$1
   #15 = Class              #14           // argonaut/derive/JsonCodecMacros$$typecreator2$1
   #16 = Utf8               $typecreator2$1
   #17 = Utf8               argonaut/derive/JsonCodecMacros$$typecreator3$1
   #18 = Class              #17           // argonaut/derive/JsonCodecMacros$$typecreator3$1
   #19 = Utf8               $typecreator3$1
   #20 = Utf8               argonaut/derive/JsonCodecMacros$$typecreator4$1
   #21 = Class              #20           // argonaut/derive/JsonCodecMacros$$typecreator4$1
   #22 = Utf8               $typecreator4$1
   #23 = Utf8               java/lang/invoke/MethodHandles$Lookup
   #24 = Class              #23           // java/lang/invoke/MethodHandles$Lookup
   #25 = Utf8               java/lang/invoke/MethodHandles
   #26 = Class              #25           // java/lang/invoke/MethodHandles
   #27 = Utf8               Lookup
   #28 = Utf8               scala/collection/SeqFactory$UnapplySeqWrapper
   #29 = Class              #28           // scala/collection/SeqFactory$UnapplySeqWrapper
   #30 = Utf8               scala/collection/SeqFactory
   #31 = Class              #30           // scala/collection/SeqFactory
   #32 = Utf8               UnapplySeqWrapper
   #33 = Utf8               scala/collection/SeqFactory$UnapplySeqWrapper$
   #34 = Class              #33           // scala/collection/SeqFactory$UnapplySeqWrapper$
   #35 = Utf8               UnapplySeqWrapper$
   #36 = Utf8               scala/reflect/api/FlagSets$FlagValues
   #37 = Class              #36           // scala/reflect/api/FlagSets$FlagValues
   #38 = Utf8               scala/reflect/api/FlagSets
   #39 = Class              #38           // scala/reflect/api/FlagSets
   #40 = Utf8               FlagValues
   #41 = Utf8               scala/reflect/api/Internals$InternalApi
   #42 = Class              #41           // scala/reflect/api/Internals$InternalApi
   #43 = Utf8               scala/reflect/api/Internals
   #44 = Class              #43           // scala/reflect/api/Internals
   #45 = Utf8               InternalApi
   #46 = Utf8               scala/reflect/api/Internals$ReificationSupportApi
   #47 = Class              #46           // scala/reflect/api/Internals$ReificationSupportApi
   #48 = Utf8               ReificationSupportApi
   #49 = Utf8               scala/reflect/api/Internals$ReificationSupportApi$FlagsReprExtractor
   #50 = Class              #49           // scala/reflect/api/Internals$ReificationSupportApi$FlagsReprExtractor
   #51 = Utf8               FlagsReprExtractor
   #52 = Utf8               scala/reflect/api/Internals$ReificationSupportApi$ImplicitParamsExtractor
   #53 = Class              #52           // scala/reflect/api/Internals$ReificationSupportApi$ImplicitParamsExtractor
   #54 = Utf8               ImplicitParamsExtractor
   #55 = Utf8               scala/reflect/api/Internals$ReificationSupportApi$ScalaDotExtractor
   #56 = Class              #55           // scala/reflect/api/Internals$ReificationSupportApi$ScalaDotExtractor
   #57 = Utf8               ScalaDotExtractor
   #58 = Utf8               scala/reflect/api/Internals$ReificationSupportApi$SyntacticBlockExtractor
   #59 = Class              #58           // scala/reflect/api/Internals$ReificationSupportApi$SyntacticBlockExtractor
   #60 = Utf8               SyntacticBlockExtractor
   #61 = Utf8               scala/reflect/api/Internals$ReificationSupportApi$SyntacticDefDefExtractor
   #62 = Class              #61           // scala/reflect/api/Internals$ReificationSupportApi$SyntacticDefDefExtractor
   #63 = Utf8               SyntacticDefDefExtractor
   #64 = Utf8               scala/reflect/api/Internals$ReificationSupportApi$SyntacticObjectDefExtractor
   #65 = Class              #64           // scala/reflect/api/Internals$ReificationSupportApi$SyntacticObjectDefExtractor
   #66 = Utf8               SyntacticObjectDefExtractor
   #67 = Utf8               scala/reflect/api/Internals$ReificationSupportApi$SyntacticSelectTermExtractor
   #68 = Class              #67           // scala/reflect/api/Internals$ReificationSupportApi$SyntacticSelectTermExtractor
   #69 = Utf8               SyntacticSelectTermExtractor
   #70 = Utf8               scala/reflect/api/Internals$ReificationSupportApi$SyntacticTermIdentExtractor
   #71 = Class              #70           // scala/reflect/api/Internals$ReificationSupportApi$SyntacticTermIdentExtractor
   #72 = Utf8               SyntacticTermIdentExtractor
   #73 = Utf8               scala/reflect/api/Internals$ReificationSupportApi$SyntacticTypeAppliedExtractor
   #74 = Class              #73           // scala/reflect/api/Internals$ReificationSupportApi$SyntacticTypeAppliedExtractor
   #75 = Utf8               SyntacticTypeAppliedExtractor
   #76 = Utf8               scala/reflect/api/Internals$ReificationSupportApi$SyntacticTypeIdentExtractor
   #77 = Class              #76           // scala/reflect/api/Internals$ReificationSupportApi$SyntacticTypeIdentExtractor
   #78 = Utf8               SyntacticTypeIdentExtractor
   #79 = Utf8               scala/reflect/api/Internals$ReificationSupportApi$SyntacticValDefExtractor
   #80 = Class              #79           // scala/reflect/api/Internals$ReificationSupportApi$SyntacticValDefExtractor
   #81 = Utf8               SyntacticValDefExtractor
   #82 = Utf8               scala/reflect/api/Liftables$Liftable
   #83 = Class              #82           // scala/reflect/api/Liftables$Liftable
   #84 = Utf8               scala/reflect/api/Liftables
   #85 = Class              #84           // scala/reflect/api/Liftables
   #86 = Utf8               Liftable
   #87 = Utf8               scala/reflect/api/Liftables$Liftable$
   #88 = Class              #87           // scala/reflect/api/Liftables$Liftable$
   #89 = Utf8               Liftable$
   #90 = Utf8               scala/reflect/api/Names$NameApi
   #91 = Class              #90           // scala/reflect/api/Names$NameApi
   #92 = Utf8               scala/reflect/api/Names
   #93 = Class              #92           // scala/reflect/api/Names
   #94 = Utf8               NameApi
   #95 = Utf8               scala/reflect/api/Names$TermNameApi
   #96 = Class              #95           // scala/reflect/api/Names$TermNameApi
   #97 = Utf8               TermNameApi
   #98 = Utf8               scala/reflect/api/Names$TermNameExtractor
   #99 = Class              #98           // scala/reflect/api/Names$TermNameExtractor
  #100 = Utf8               TermNameExtractor
  #101 = Utf8               scala/reflect/api/Names$TypeNameApi
  #102 = Class              #101          // scala/reflect/api/Names$TypeNameApi
  #103 = Utf8               TypeNameApi
  #104 = Utf8               scala/reflect/api/Names$TypeNameExtractor
  #105 = Class              #104          // scala/reflect/api/Names$TypeNameExtractor
  #106 = Utf8               TypeNameExtractor
  #107 = Utf8               scala/reflect/api/Symbols$ClassSymbolApi
  #108 = Class              #107          // scala/reflect/api/Symbols$ClassSymbolApi
  #109 = Utf8               scala/reflect/api/Symbols
  #110 = Class              #109          // scala/reflect/api/Symbols
  #111 = Utf8               ClassSymbolApi
  #112 = Utf8               scala/reflect/api/Symbols$SymbolApi
  #113 = Class              #112          // scala/reflect/api/Symbols$SymbolApi
  #114 = Utf8               SymbolApi
  #115 = Utf8               scala/reflect/api/Symbols$TypeSymbolApi
  #116 = Class              #115          // scala/reflect/api/Symbols$TypeSymbolApi
  #117 = Utf8               TypeSymbolApi
  #118 = Utf8               scala/reflect/api/Trees$ClassDefApi
  #119 = Class              #118          // scala/reflect/api/Trees$ClassDefApi
  #120 = Utf8               scala/reflect/api/Trees
  #121 = Class              #120          // scala/reflect/api/Trees
  #122 = Utf8               ClassDefApi
  #123 = Utf8               scala/reflect/api/Trees$DefDefApi
  #124 = Class              #123          // scala/reflect/api/Trees$DefDefApi
  #125 = Utf8               DefDefApi
  #126 = Utf8               scala/reflect/api/Trees$IdentApi
  #127 = Class              #126          // scala/reflect/api/Trees$IdentApi
  #128 = Utf8               IdentApi
  #129 = Utf8               scala/reflect/api/Trees$ImplDefApi
  #130 = Class              #129          // scala/reflect/api/Trees$ImplDefApi
  #131 = Utf8               ImplDefApi
  #132 = Utf8               scala/reflect/api/Trees$ModifiersApi
  #133 = Class              #132          // scala/reflect/api/Trees$ModifiersApi
  #134 = Utf8               ModifiersApi
  #135 = Utf8               scala/reflect/api/Trees$ModifiersExtractor
  #136 = Class              #135          // scala/reflect/api/Trees$ModifiersExtractor
  #137 = Utf8               ModifiersExtractor
  #138 = Utf8               scala/reflect/api/Trees$ModuleDefApi
  #139 = Class              #138          // scala/reflect/api/Trees$ModuleDefApi
  #140 = Utf8               ModuleDefApi
  #141 = Utf8               scala/reflect/api/Trees$SelectApi
  #142 = Class              #141          // scala/reflect/api/Trees$SelectApi
  #143 = Utf8               SelectApi
  #144 = Utf8               scala/reflect/api/Trees$TreeApi
  #145 = Class              #144          // scala/reflect/api/Trees$TreeApi
  #146 = Utf8               TreeApi
  #147 = Utf8               scala/reflect/api/Trees$TypeDefApi
  #148 = Class              #147          // scala/reflect/api/Trees$TypeDefApi
  #149 = Utf8               TypeDefApi
  #150 = Utf8               scala/reflect/api/Trees$TypedApi
  #151 = Class              #150          // scala/reflect/api/Trees$TypedApi
  #152 = Utf8               TypedApi
  #153 = Utf8               scala/reflect/api/Trees$TypedExtractor
  #154 = Class              #153          // scala/reflect/api/Trees$TypedExtractor
  #155 = Utf8               TypedExtractor
  #156 = Utf8               scala/reflect/api/Trees$ValDefApi
  #157 = Class              #156          // scala/reflect/api/Trees$ValDefApi
  #158 = Utf8               ValDefApi
  #159 = Utf8               scala/reflect/api/TypeTags$TypeTag
  #160 = Class              #159          // scala/reflect/api/TypeTags$TypeTag
  #161 = Utf8               scala/reflect/api/TypeTags
  #162 = Class              #161          // scala/reflect/api/TypeTags
  #163 = Utf8               TypeTag
  #164 = Utf8               scala/reflect/api/TypeTags$TypeTag$
  #165 = Class              #164          // scala/reflect/api/TypeTags$TypeTag$
  #166 = Utf8               TypeTag$
  #167 = Utf8               scala/reflect/api/TypeTags$WeakTypeTag
  #168 = Class              #167          // scala/reflect/api/TypeTags$WeakTypeTag
  #169 = Utf8               WeakTypeTag
  #170 = Utf8               c
  #171 = Utf8               Lscala/reflect/macros/blackbox/Context;
  #172 = Utf8               DecoderClass
  #173 = Utf8               Lscala/reflect/api/Symbols$TypeSymbolApi;
  #174 = Utf8               EncoderClass
  #175 = Utf8               mkDecodeJson
  #176 = Utf8               Lscala/reflect/api/Symbols$SymbolApi;
  #177 = Utf8               mkEncodeJson
  #178 = Utf8               ()Lscala/reflect/macros/blackbox/Context;
  #179 = NameAndType        #170:#171     // c:Lscala/reflect/macros/blackbox/Context;
  #180 = Fieldref           #2.#179       // argonaut/derive/JsonCodecMacros.c:Lscala/reflect/macros/blackbox/Context;
  #181 = Utf8               this
  #182 = Utf8               Largonaut/derive/JsonCodecMacros;
  #183 = Utf8               isCaseClassOrSealed
  #184 = Utf8               (Lscala/reflect/api/Trees$ClassDefApi;)Z
  #185 = Utf8               clsDef
  #186 = Utf8               mods
  #187 = Utf8               ()Lscala/reflect/api/Trees$ModifiersApi;
  #188 = NameAndType        #186:#187     // mods:()Lscala/reflect/api/Trees$ModifiersApi;
  #189 = InterfaceMethodref #119.#188     // scala/reflect/api/Trees$ClassDefApi.mods:()Lscala/reflect/api/Trees$ModifiersApi;
  #190 = NameAndType        #170:#178     // c:()Lscala/reflect/macros/blackbox/Context;
  #191 = Methodref          #2.#190       // argonaut/derive/JsonCodecMacros.c:()Lscala/reflect/macros/blackbox/Context;
  #192 = Utf8               scala/reflect/macros/blackbox/Context
  #193 = Class              #192          // scala/reflect/macros/blackbox/Context
  #194 = Utf8               universe
  #195 = Utf8               ()Lscala/reflect/macros/Universe;
  #196 = NameAndType        #194:#195     // universe:()Lscala/reflect/macros/Universe;
  #197 = InterfaceMethodref #193.#196     // scala/reflect/macros/blackbox/Context.universe:()Lscala/reflect/macros/Universe;
  #198 = Utf8               scala/reflect/macros/Universe
  #199 = Class              #198          // scala/reflect/macros/Universe
  #200 = Utf8               Flag
  #201 = Utf8               ()Lscala/reflect/api/FlagSets$FlagValues;
  #202 = NameAndType        #200:#201     // Flag:()Lscala/reflect/api/FlagSets$FlagValues;
  #203 = Methodref          #199.#202     // scala/reflect/macros/Universe.Flag:()Lscala/reflect/api/FlagSets$FlagValues;
  #204 = Utf8               CASE
  #205 = Utf8               ()Ljava/lang/Object;
  #206 = NameAndType        #204:#205     // CASE:()Ljava/lang/Object;
  #207 = InterfaceMethodref #37.#206      // scala/reflect/api/FlagSets$FlagValues.CASE:()Ljava/lang/Object;
  #208 = Utf8               hasFlag
  #209 = Utf8               (Ljava/lang/Object;)Z
  #210 = NameAndType        #208:#209     // hasFlag:(Ljava/lang/Object;)Z
  #211 = Methodref          #133.#210     // scala/reflect/api/Trees$ModifiersApi.hasFlag:(Ljava/lang/Object;)Z
  #212 = Utf8               SEALED
  #213 = NameAndType        #212:#205     // SEALED:()Ljava/lang/Object;
  #214 = InterfaceMethodref #37.#213      // scala/reflect/api/FlagSets$FlagValues.SEALED:()Ljava/lang/Object;
  #215 = Utf8               Lscala/reflect/api/Trees$ClassDefApi;
  #216 = Utf8               jsonCodecAnnotationMacro
  #217 = Utf8               (Lscala/collection/immutable/Seq;)Lscala/reflect/api/Trees$TreeApi;
  #218 = Utf8               (Lscala/collection/immutable/Seq<Lscala/reflect/api/Trees$TreeApi;>;)Lscala/reflect/api/Trees$TreeApi;
  #219 = Utf8               annottees
  #220 = Utf8               scala/collection/immutable/List
  #221 = Class              #220          // scala/collection/immutable/List
  #222 = Utf8               scala/collection/immutable/List$
  #223 = Class              #222          // scala/collection/immutable/List$
  #224 = Utf8               MODULE$
  #225 = Utf8               Lscala/collection/immutable/List$;
  #226 = NameAndType        #224:#225     // MODULE$:Lscala/collection/immutable/List$;
  #227 = Fieldref           #223.#226     // scala/collection/immutable/List$.MODULE$:Lscala/collection/immutable/List$;
  #228 = Utf8               unapplySeq
  #229 = Utf8               (Lscala/collection/SeqOps;)Lscala/collection/SeqOps;
  #230 = NameAndType        #228:#229     // unapplySeq:(Lscala/collection/SeqOps;)Lscala/collection/SeqOps;
  #231 = Methodref          #223.#230     // scala/collection/immutable/List$.unapplySeq:(Lscala/collection/SeqOps;)Lscala/collection/SeqOps;
  #232 = Utf8               Lscala/collection/SeqFactory$UnapplySeqWrapper$;
  #233 = NameAndType        #224:#232     // MODULE$:Lscala/collection/SeqFactory$UnapplySeqWrapper$;
  #234 = Fieldref           #34.#233      // scala/collection/SeqFactory$UnapplySeqWrapper$.MODULE$:Lscala/collection/SeqFactory$UnapplySeqWrapper$;
  #235 = Utf8               isEmpty$extension
  #236 = Utf8               (Lscala/collection/SeqOps;)Z
  #237 = NameAndType        #235:#236     // isEmpty$extension:(Lscala/collection/SeqOps;)Z
  #238 = Methodref          #34.#237      // scala/collection/SeqFactory$UnapplySeqWrapper$.isEmpty$extension:(Lscala/collection/SeqOps;)Z
  #239 = Utf8               get$extension
  #240 = NameAndType        #239:#229     // get$extension:(Lscala/collection/SeqOps;)Lscala/collection/SeqOps;
  #241 = Methodref          #34.#240      // scala/collection/SeqFactory$UnapplySeqWrapper$.get$extension:(Lscala/collection/SeqOps;)Lscala/collection/SeqOps;
  #242 = Utf8               <init>
  #243 = Utf8               (Lscala/collection/SeqOps;)V
  #244 = NameAndType        #242:#243     // "<init>":(Lscala/collection/SeqOps;)V
  #245 = Methodref          #29.#244      // scala/collection/SeqFactory$UnapplySeqWrapper."<init>":(Lscala/collection/SeqOps;)V
  #246 = Utf8               lengthCompare$extension
  #247 = Utf8               (Lscala/collection/SeqOps;I)I
  #248 = NameAndType        #246:#247     // lengthCompare$extension:(Lscala/collection/SeqOps;I)I
  #249 = Methodref          #34.#248      // scala/collection/SeqFactory$UnapplySeqWrapper$.lengthCompare$extension:(Lscala/collection/SeqOps;I)I
  #250 = Utf8               apply$extension
  #251 = Utf8               (Lscala/collection/SeqOps;I)Ljava/lang/Object;
  #252 = NameAndType        #250:#251     // apply$extension:(Lscala/collection/SeqOps;I)Ljava/lang/Object;
  #253 = Methodref          #34.#252      // scala/collection/SeqFactory$UnapplySeqWrapper$.apply$extension:(Lscala/collection/SeqOps;I)Ljava/lang/Object;
  #254 = Utf8               ClassDefTag
  #255 = Utf8               ()Lscala/reflect/ClassTag;
  #256 = NameAndType        #254:#255     // ClassDefTag:()Lscala/reflect/ClassTag;
  #257 = Methodref          #199.#256     // scala/reflect/macros/Universe.ClassDefTag:()Lscala/reflect/ClassTag;
  #258 = Utf8               scala/reflect/ClassTag
  #259 = Class              #258          // scala/reflect/ClassTag
  #260 = Utf8               unapply
  #261 = Utf8               (Ljava/lang/Object;)Lscala/Option;
  #262 = NameAndType        #260:#261     // unapply:(Ljava/lang/Object;)Lscala/Option;
  #263 = InterfaceMethodref #259.#262     // scala/reflect/ClassTag.unapply:(Ljava/lang/Object;)Lscala/Option;
  #264 = Utf8               scala/Option
  #265 = Class              #264          // scala/Option
  #266 = Utf8               isEmpty
  #267 = Utf8               ()Z
  #268 = NameAndType        #266:#267     // isEmpty:()Z
  #269 = Methodref          #265.#268     // scala/Option.isEmpty:()Z
  #270 = Utf8               get
  #271 = NameAndType        #270:#205     // get:()Ljava/lang/Object;
  #272 = Methodref          #265.#271     // scala/Option.get:()Ljava/lang/Object;
  #273 = NameAndType        #183:#184     // isCaseClassOrSealed:(Lscala/reflect/api/Trees$ClassDefApi;)Z
  #274 = Methodref          #2.#273       // argonaut/derive/JsonCodecMacros.isCaseClassOrSealed:(Lscala/reflect/api/Trees$ClassDefApi;)Z
  #275 = Utf8               internal
  #276 = Utf8               ()Lscala/reflect/api/Internals$InternalApi;
  #277 = NameAndType        #275:#276     // internal:()Lscala/reflect/api/Internals$InternalApi;
  #278 = Methodref          #199.#277     // scala/reflect/macros/Universe.internal:()Lscala/reflect/api/Internals$InternalApi;
  #279 = Utf8               reificationSupport
  #280 = Utf8               ()Lscala/reflect/api/Internals$ReificationSupportApi;
  #281 = NameAndType        #279:#280     // reificationSupport:()Lscala/reflect/api/Internals$ReificationSupportApi;
  #282 = InterfaceMethodref #42.#281      // scala/reflect/api/Internals$InternalApi.reificationSupport:()Lscala/reflect/api/Internals$ReificationSupportApi;
  #283 = Utf8               SyntacticBlock
  #284 = Utf8               ()Lscala/reflect/api/Internals$ReificationSupportApi$SyntacticBlockExtractor;
  #285 = NameAndType        #283:#284     // SyntacticBlock:()Lscala/reflect/api/Internals$ReificationSupportApi$SyntacticBlockExtractor;
  #286 = InterfaceMethodref #47.#285      // scala/reflect/api/Internals$ReificationSupportApi.SyntacticBlock:()Lscala/reflect/api/Internals$ReificationSupportApi$SyntacticBlockExtractor;
  #287 = Utf8               scala/collection/immutable/$colon$colon
  #288 = Class              #287          // scala/collection/immutable/$colon$colon
  #289 = Utf8               SyntacticObjectDef
  #290 = Utf8               ()Lscala/reflect/api/Internals$ReificationSupportApi$SyntacticObjectDefExtractor;
  #291 = NameAndType        #289:#290     // SyntacticObjectDef:()Lscala/reflect/api/Internals$ReificationSupportApi$SyntacticObjectDefExtractor;
  #292 = InterfaceMethodref #47.#291      // scala/reflect/api/Internals$ReificationSupportApi.SyntacticObjectDef:()Lscala/reflect/api/Internals$ReificationSupportApi$SyntacticObjectDefExtractor;
  #293 = Utf8               NoMods
  #294 = NameAndType        #293:#187     // NoMods:()Lscala/reflect/api/Trees$ModifiersApi;
  #295 = Methodref          #199.#294     // scala/reflect/macros/Universe.NoMods:()Lscala/reflect/api/Trees$ModifiersApi;
  #296 = Utf8               name
  #297 = Utf8               ()Lscala/reflect/api/Names$TypeNameApi;
  #298 = NameAndType        #296:#297     // name:()Lscala/reflect/api/Names$TypeNameApi;
  #299 = InterfaceMethodref #119.#298     // scala/reflect/api/Trees$ClassDefApi.name:()Lscala/reflect/api/Names$TypeNameApi;
  #300 = Utf8               toTermName
  #301 = Utf8               ()Lscala/reflect/api/Names$TermNameApi;
  #302 = NameAndType        #300:#301     // toTermName:()Lscala/reflect/api/Names$TermNameApi;
  #303 = Methodref          #91.#302      // scala/reflect/api/Names$NameApi.toTermName:()Lscala/reflect/api/Names$TermNameApi;
  #304 = Utf8               scala/collection/immutable/Nil$
  #305 = Class              #304          // scala/collection/immutable/Nil$
  #306 = Utf8               Lscala/collection/immutable/Nil$;
  #307 = NameAndType        #224:#306     // MODULE$:Lscala/collection/immutable/Nil$;
  #308 = Fieldref           #305.#307     // scala/collection/immutable/Nil$.MODULE$:Lscala/collection/immutable/Nil$;
  #309 = Utf8               ScalaDot
  #310 = Utf8               ()Lscala/reflect/api/Internals$ReificationSupportApi$ScalaDotExtractor;
  #311 = NameAndType        #309:#310     // ScalaDot:()Lscala/reflect/api/Internals$ReificationSupportApi$ScalaDotExtractor;
  #312 = InterfaceMethodref #47.#311      // scala/reflect/api/Internals$ReificationSupportApi.ScalaDot:()Lscala/reflect/api/Internals$ReificationSupportApi$ScalaDotExtractor;
  #313 = Utf8               TypeName
  #314 = Utf8               ()Lscala/reflect/api/Names$TypeNameExtractor;
  #315 = NameAndType        #313:#314     // TypeName:()Lscala/reflect/api/Names$TypeNameExtractor;
  #316 = Methodref          #199.#315     // scala/reflect/macros/Universe.TypeName:()Lscala/reflect/api/Names$TypeNameExtractor;
  #317 = Utf8               AnyRef
  #318 = String             #317          // AnyRef
  #319 = Utf8               apply
  #320 = Utf8               (Ljava/lang/String;)Lscala/reflect/api/Names$TypeNameApi;
  #321 = NameAndType        #319:#320     // apply:(Ljava/lang/String;)Lscala/reflect/api/Names$TypeNameApi;
  #322 = Methodref          #105.#321     // scala/reflect/api/Names$TypeNameExtractor.apply:(Ljava/lang/String;)Lscala/reflect/api/Names$TypeNameApi;
  #323 = Utf8               (Lscala/reflect/api/Names$NameApi;)Lscala/reflect/api/Trees$TreeApi;
  #324 = NameAndType        #319:#323     // apply:(Lscala/reflect/api/Names$NameApi;)Lscala/reflect/api/Trees$TreeApi;
  #325 = InterfaceMethodref #56.#324      // scala/reflect/api/Internals$ReificationSupportApi$ScalaDotExtractor.apply:(Lscala/reflect/api/Names$NameApi;)Lscala/reflect/api/Trees$TreeApi;
  #326 = Utf8               (Ljava/lang/Object;Lscala/collection/immutable/List;)V
  #327 = NameAndType        #242:#326     // "<init>":(Ljava/lang/Object;Lscala/collection/immutable/List;)V
  #328 = Methodref          #288.#327     // scala/collection/immutable/$colon$colon."<init>":(Ljava/lang/Object;Lscala/collection/immutable/List;)V
  #329 = Utf8               noSelfType
  #330 = Utf8               ()Lscala/reflect/api/Trees$ValDefApi;
  #331 = NameAndType        #329:#330     // noSelfType:()Lscala/reflect/api/Trees$ValDefApi;
  #332 = Methodref          #199.#331     // scala/reflect/macros/Universe.noSelfType:()Lscala/reflect/api/Trees$ValDefApi;
  #333 = Utf8               codec
  #334 = Utf8               (Lscala/reflect/api/Trees$ClassDefApi;)Lscala/collection/immutable/List;
  #335 = NameAndType        #333:#334     // codec:(Lscala/reflect/api/Trees$ClassDefApi;)Lscala/collection/immutable/List;
  #336 = Methodref          #2.#335       // argonaut/derive/JsonCodecMacros.codec:(Lscala/reflect/api/Trees$ClassDefApi;)Lscala/collection/immutable/List;
  #337 = Utf8               (Lscala/reflect/api/Trees$ModifiersApi;Lscala/reflect/api/Names$TermNameApi;Lscala/collection/immutable/List;Lscala/collection/immutable/List;Lscala/reflect/api/Trees$TreeApi;Lscala/collection/immutable/List;)Lscala/reflect/api/Trees$ModuleDefApi;
  #338 = NameAndType        #319:#337     // apply:(Lscala/reflect/api/Trees$ModifiersApi;Lscala/reflect/api/Names$TermNameApi;Lscala/collection/immutable/List;Lscala/collection/immutable/List;Lscala/reflect/api/Trees$TreeApi;Lscala/collection/immutable/List;)Lscala/reflect/api/Trees$ModuleDefApi;
  #339 = InterfaceMethodref #65.#338      // scala/reflect/api/Internals$ReificationSupportApi$SyntacticObjectDefExtractor.apply:(Lscala/reflect/api/Trees$ModifiersApi;Lscala/reflect/api/Names$TermNameApi;Lscala/collection/immutable/List;Lscala/collection/immutable/List;Lscala/reflect/api/Trees$TreeApi;Lscala/collection/immutable/List;)Lscala/reflect/api/Trees$ModuleDefApi;
  #340 = Utf8               (Lscala/collection/immutable/List;)Lscala/reflect/api/Trees$TreeApi;
  #341 = NameAndType        #319:#340     // apply:(Lscala/collection/immutable/List;)Lscala/reflect/api/Trees$TreeApi;
  #342 = InterfaceMethodref #59.#341      // scala/reflect/api/Internals$ReificationSupportApi$SyntacticBlockExtractor.apply:(Lscala/collection/immutable/List;)Lscala/reflect/api/Trees$TreeApi;
  #343 = Utf8               (Largonaut/derive/JsonCodecMacros;)V
  #344 = NameAndType        #242:#343     // "<init>":(Largonaut/derive/JsonCodecMacros;)V
  #345 = Methodref          #10.#344      // argonaut/derive/JsonCodecMacros$$anon$1."<init>":(Largonaut/derive/JsonCodecMacros;)V
  #346 = Methodref          #10.#262      // argonaut/derive/JsonCodecMacros$$anon$1.unapply:(Ljava/lang/Object;)Lscala/Option;
  #347 = Utf8               scala/Tuple5
  #348 = Class              #347          // scala/Tuple5
  #349 = Utf8               _1
  #350 = NameAndType        #349:#205     // _1:()Ljava/lang/Object;
  #351 = Methodref          #348.#350     // scala/Tuple5._1:()Ljava/lang/Object;
  #352 = Utf8               _2
  #353 = NameAndType        #352:#205     // _2:()Ljava/lang/Object;
  #354 = Methodref          #348.#353     // scala/Tuple5._2:()Ljava/lang/Object;
  #355 = Utf8               _3
  #356 = NameAndType        #355:#205     // _3:()Ljava/lang/Object;
  #357 = Methodref          #348.#356     // scala/Tuple5._3:()Ljava/lang/Object;
  #358 = Utf8               _4
  #359 = NameAndType        #358:#205     // _4:()Ljava/lang/Object;
  #360 = Methodref          #348.#359     // scala/Tuple5._4:()Ljava/lang/Object;
  #361 = Utf8               _5
  #362 = NameAndType        #361:#205     // _5:()Ljava/lang/Object;
  #363 = Methodref          #348.#362     // scala/Tuple5._5:()Ljava/lang/Object;
  #364 = Utf8               mkEarlyDef
  #365 = Utf8               (Lscala/collection/immutable/List;)Lscala/collection/immutable/List;
  #366 = NameAndType        #364:#365     // mkEarlyDef:(Lscala/collection/immutable/List;)Lscala/collection/immutable/List;
  #367 = InterfaceMethodref #47.#366      // scala/reflect/api/Internals$ReificationSupportApi.mkEarlyDef:(Lscala/collection/immutable/List;)Lscala/collection/immutable/List;
  #368 = Utf8               $plus$plus
  #369 = Utf8               (Lscala/collection/IterableOnce;)Ljava/lang/Object;
  #370 = NameAndType        #368:#369     // $plus$plus:(Lscala/collection/IterableOnce;)Ljava/lang/Object;
  #371 = Methodref          #221.#370     // scala/collection/immutable/List.$plus$plus:(Lscala/collection/IterableOnce;)Ljava/lang/Object;
  #372 = Utf8               enclosingPosition
  #373 = Utf8               ()Lscala/reflect/api/Position;
  #374 = NameAndType        #372:#373     // enclosingPosition:()Lscala/reflect/api/Position;
  #375 = InterfaceMethodref #193.#374     // scala/reflect/macros/blackbox/Context.enclosingPosition:()Lscala/reflect/api/Position;
  #376 = Utf8               Invalid annotation target: must be a case class or a sealed trait/class
  #377 = String             #376          // Invalid annotation target: must be a case class or a sealed trait/class
  #378 = Utf8               abort
  #379 = Utf8               (Lscala/reflect/api/Position;Ljava/lang/String;)Lscala/runtime/Nothing$;
  #380 = NameAndType        #378:#379     // abort:(Lscala/reflect/api/Position;Ljava/lang/String;)Lscala/runtime/Nothing$;
  #381 = InterfaceMethodref #193.#380     // scala/reflect/macros/blackbox/Context.abort:(Lscala/reflect/api/Position;Ljava/lang/String;)Lscala/runtime/Nothing$;
  #382 = Utf8               Lscala/reflect/api/Trees$TreeApi;
  #383 = Utf8               objName
  #384 = Utf8               Lscala/reflect/api/Names$TermNameApi;
  #385 = Utf8               objEarlyDefs
  #386 = Utf8               Lscala/collection/immutable/List;
  #387 = Utf8               objParents
  #388 = Utf8               objSelf
  #389 = Utf8               Lscala/reflect/api/Trees$ValDefApi;
  #390 = Utf8               objDefs
  #391 = Utf8               Lscala/collection/immutable/Seq;
  #392 = Utf8               scala/collection/immutable/Seq
  #393 = Class              #392          // scala/collection/immutable/Seq
  #394 = Utf8               scala/collection/SeqOps
  #395 = Class              #394          // scala/collection/SeqOps
  #396 = Utf8               (Lscala/reflect/api/Trees$ClassDefApi;)Lscala/collection/immutable/List<Lscala/reflect/api/Trees$TreeApi;>;
  #397 = Utf8               tparams
  #398 = Utf8               ()Lscala/collection/immutable/List;
  #399 = NameAndType        #397:#398     // tparams:()Lscala/collection/immutable/List;
  #400 = InterfaceMethodref #119.#399     // scala/reflect/api/Trees$ClassDefApi.tparams:()Lscala/collection/immutable/List;
  #401 = Utf8               TermName
  #402 = Utf8               ()Lscala/reflect/api/Names$TermNameExtractor;
  #403 = NameAndType        #401:#402     // TermName:()Lscala/reflect/api/Names$TermNameExtractor;
  #404 = Methodref          #199.#403     // scala/reflect/macros/Universe.TermName:()Lscala/reflect/api/Names$TermNameExtractor;
  #405 = Utf8               java/lang/StringBuilder
  #406 = Class              #405          // java/lang/StringBuilder
  #407 = Integer            6
  #408 = Utf8               (I)V
  #409 = NameAndType        #242:#408     // "<init>":(I)V
  #410 = Methodref          #406.#409     // java/lang/StringBuilder."<init>":(I)V
  #411 = Utf8               decode
  #412 = String             #411          // decode
  #413 = Utf8               append
  #414 = Utf8               (Ljava/lang/String;)Ljava/lang/StringBuilder;
  #415 = NameAndType        #413:#414     // append:(Ljava/lang/String;)Ljava/lang/StringBuilder;
  #416 = Methodref          #406.#415     // java/lang/StringBuilder.append:(Ljava/lang/String;)Ljava/lang/StringBuilder;
  #417 = Utf8               decodedName
  #418 = Utf8               ()Lscala/reflect/api/Names$NameApi;
  #419 = NameAndType        #417:#418     // decodedName:()Lscala/reflect/api/Names$NameApi;
  #420 = Methodref          #91.#419      // scala/reflect/api/Names$NameApi.decodedName:()Lscala/reflect/api/Names$NameApi;
  #421 = Utf8               (Ljava/lang/Object;)Ljava/lang/StringBuilder;
  #422 = NameAndType        #413:#421     // append:(Ljava/lang/Object;)Ljava/lang/StringBuilder;
  #423 = Methodref          #406.#422     // java/lang/StringBuilder.append:(Ljava/lang/Object;)Ljava/lang/StringBuilder;
  #424 = Utf8               toString
  #425 = Utf8               ()Ljava/lang/String;
  #426 = NameAndType        #424:#425     // toString:()Ljava/lang/String;
  #427 = Methodref          #406.#426     // java/lang/StringBuilder.toString:()Ljava/lang/String;
  #428 = Utf8               (Ljava/lang/String;)Lscala/reflect/api/Names$TermNameApi;
  #429 = NameAndType        #319:#428     // apply:(Ljava/lang/String;)Lscala/reflect/api/Names$TermNameApi;
  #430 = Methodref          #99.#429      // scala/reflect/api/Names$TermNameExtractor.apply:(Ljava/lang/String;)Lscala/reflect/api/Names$TermNameApi;
  #431 = Utf8               encode
  #432 = String             #431          // encode
  #433 = Methodref          #221.#268     // scala/collection/immutable/List.isEmpty:()Z
  #434 = Utf8               SyntacticValDef
  #435 = Utf8               ()Lscala/reflect/api/Internals$ReificationSupportApi$SyntacticValDefExtractor;
  #436 = NameAndType        #434:#435     // SyntacticValDef:()Lscala/reflect/api/Internals$ReificationSupportApi$SyntacticValDefExtractor;
  #437 = InterfaceMethodref #47.#436      // scala/reflect/api/Internals$ReificationSupportApi.SyntacticValDef:()Lscala/reflect/api/Internals$ReificationSupportApi$SyntacticValDefExtractor;
  #438 = Utf8               Modifiers
  #439 = Utf8               ()Lscala/reflect/api/Trees$ModifiersExtractor;
  #440 = NameAndType        #438:#439     // Modifiers:()Lscala/reflect/api/Trees$ModifiersExtractor;
  #441 = Methodref          #199.#440     // scala/reflect/macros/Universe.Modifiers:()Lscala/reflect/api/Trees$ModifiersExtractor;
  #442 = Utf8               FlagsRepr
  #443 = Utf8               ()Lscala/reflect/api/Internals$ReificationSupportApi$FlagsReprExtractor;
  #444 = NameAndType        #442:#443     // FlagsRepr:()Lscala/reflect/api/Internals$ReificationSupportApi$FlagsReprExtractor;
  #445 = InterfaceMethodref #47.#444      // scala/reflect/api/Internals$ReificationSupportApi.FlagsRepr:()Lscala/reflect/api/Internals$ReificationSupportApi$FlagsReprExtractor;
  #446 = Long               512l
  #448 = Utf8               (J)Ljava/lang/Object;
  #449 = NameAndType        #319:#448     // apply:(J)Ljava/lang/Object;
  #450 = InterfaceMethodref #50.#449      // scala/reflect/api/Internals$ReificationSupportApi$FlagsReprExtractor.apply:(J)Ljava/lang/Object;
  #451 = Utf8
  #452 = String             #451          //
  #453 = Utf8               (Ljava/lang/Object;Lscala/reflect/api/Names$NameApi;Lscala/collection/immutable/List;)Lscala/reflect/api/Trees$ModifiersApi;
  #454 = NameAndType        #319:#453     // apply:(Ljava/lang/Object;Lscala/reflect/api/Names$NameApi;Lscala/collection/immutable/List;)Lscala/reflect/api/Trees$ModifiersApi;
  #455 = Methodref          #136.#454     // scala/reflect/api/Trees$ModifiersExtractor.apply:(Ljava/lang/Object;Lscala/reflect/api/Names$NameApi;Lscala/collection/immutable/List;)Lscala/reflect/api/Trees$ModifiersApi;
  #456 = Utf8               SyntacticAppliedType
  #457 = Utf8               ()Lscala/reflect/api/Internals$ReificationSupportApi$SyntacticTypeAppliedExtractor;
  #458 = NameAndType        #456:#457     // SyntacticAppliedType:()Lscala/reflect/api/Internals$ReificationSupportApi$SyntacticTypeAppliedExtractor;
  #459 = InterfaceMethodref #47.#458      // scala/reflect/api/Internals$ReificationSupportApi.SyntacticAppliedType:()Lscala/reflect/api/Internals$ReificationSupportApi$SyntacticTypeAppliedExtractor;
  #460 = Utf8               EmptyTree
  #461 = Utf8               ()Lscala/reflect/api/Trees$TreeApi;
  #462 = NameAndType        #460:#461     // EmptyTree:()Lscala/reflect/api/Trees$TreeApi;
  #463 = Methodref          #199.#462     // scala/reflect/macros/Universe.EmptyTree:()Lscala/reflect/api/Trees$TreeApi;
  #464 = NameAndType        #172:#173     // DecoderClass:Lscala/reflect/api/Symbols$TypeSymbolApi;
  #465 = Fieldref           #2.#464       // argonaut/derive/JsonCodecMacros.DecoderClass:Lscala/reflect/api/Symbols$TypeSymbolApi;
  #466 = Utf8               mkRefTree
  #467 = Utf8               (Lscala/reflect/api/Trees$TreeApi;Lscala/reflect/api/Symbols$SymbolApi;)Lscala/reflect/api/Trees$TreeApi;
  #468 = NameAndType        #466:#467     // mkRefTree:(Lscala/reflect/api/Trees$TreeApi;Lscala/reflect/api/Symbols$SymbolApi;)Lscala/reflect/api/Trees$TreeApi;
  #469 = InterfaceMethodref #47.#468      // scala/reflect/api/Internals$ReificationSupportApi.mkRefTree:(Lscala/reflect/api/Trees$TreeApi;Lscala/reflect/api/Symbols$SymbolApi;)Lscala/reflect/api/Trees$TreeApi;
  #470 = Utf8               SyntacticTypeIdent
  #471 = Utf8               ()Lscala/reflect/api/Internals$ReificationSupportApi$SyntacticTypeIdentExtractor;
  #472 = NameAndType        #470:#471     // SyntacticTypeIdent:()Lscala/reflect/api/Internals$ReificationSupportApi$SyntacticTypeIdentExtractor;
  #473 = InterfaceMethodref #47.#472      // scala/reflect/api/Internals$ReificationSupportApi.SyntacticTypeIdent:()Lscala/reflect/api/Internals$ReificationSupportApi$SyntacticTypeIdentExtractor;
  #474 = Utf8               (Lscala/reflect/api/Names$TypeNameApi;)Lscala/reflect/api/Trees$IdentApi;
  #475 = NameAndType        #319:#474     // apply:(Lscala/reflect/api/Names$TypeNameApi;)Lscala/reflect/api/Trees$IdentApi;
  #476 = InterfaceMethodref #77.#475      // scala/reflect/api/Internals$ReificationSupportApi$SyntacticTypeIdentExtractor.apply:(Lscala/reflect/api/Names$TypeNameApi;)Lscala/reflect/api/Trees$IdentApi;
  #477 = Utf8               (Lscala/reflect/api/Trees$TreeApi;Lscala/collection/immutable/List;)Lscala/reflect/api/Trees$TreeApi;
  #478 = NameAndType        #319:#477     // apply:(Lscala/reflect/api/Trees$TreeApi;Lscala/collection/immutable/List;)Lscala/reflect/api/Trees$TreeApi;
  #479 = InterfaceMethodref #74.#478      // scala/reflect/api/Internals$ReificationSupportApi$SyntacticTypeAppliedExtractor.apply:(Lscala/reflect/api/Trees$TreeApi;Lscala/collection/immutable/List;)Lscala/reflect/api/Trees$TreeApi;
  #480 = Utf8               SyntacticSelectTerm
  #481 = Utf8               ()Lscala/reflect/api/Internals$ReificationSupportApi$SyntacticSelectTermExtractor;
  #482 = NameAndType        #480:#481     // SyntacticSelectTerm:()Lscala/reflect/api/Internals$ReificationSupportApi$SyntacticSelectTermExtractor;
  #483 = InterfaceMethodref #47.#482      // scala/reflect/api/Internals$ReificationSupportApi.SyntacticSelectTerm:()Lscala/reflect/api/Internals$ReificationSupportApi$SyntacticSelectTermExtractor;
  #484 = Utf8               SyntacticTypeApplied
  #485 = NameAndType        #484:#457     // SyntacticTypeApplied:()Lscala/reflect/api/Internals$ReificationSupportApi$SyntacticTypeAppliedExtractor;
  #486 = InterfaceMethodref #47.#485      // scala/reflect/api/Internals$ReificationSupportApi.SyntacticTypeApplied:()Lscala/reflect/api/Internals$ReificationSupportApi$SyntacticTypeAppliedExtractor;
  #487 = NameAndType        #175:#176     // mkDecodeJson:Lscala/reflect/api/Symbols$SymbolApi;
  #488 = Fieldref           #2.#487       // argonaut/derive/JsonCodecMacros.mkDecodeJson:Lscala/reflect/api/Symbols$SymbolApi;
  #489 = Utf8               decodeJson
  #490 = String             #489          // decodeJson
  #491 = Utf8               (Lscala/reflect/api/Trees$TreeApi;Lscala/reflect/api/Names$TermNameApi;)Lscala/reflect/api/Trees$SelectApi;
  #492 = NameAndType        #319:#491     // apply:(Lscala/reflect/api/Trees$TreeApi;Lscala/reflect/api/Names$TermNameApi;)Lscala/reflect/api/Trees$SelectApi;
  #493 = InterfaceMethodref #68.#492      // scala/reflect/api/Internals$ReificationSupportApi$SyntacticSelectTermExtractor.apply:(Lscala/reflect/api/Trees$TreeApi;Lscala/reflect/api/Names$TermNameApi;)Lscala/reflect/api/Trees$SelectApi;
  #494 = Utf8               (Lscala/reflect/api/Trees$ModifiersApi;Lscala/reflect/api/Names$TermNameApi;Lscala/reflect/api/Trees$TreeApi;Lscala/reflect/api/Trees$TreeApi;)Lscala/reflect/api/Trees$ValDefApi;
  #495 = NameAndType        #319:#494     // apply:(Lscala/reflect/api/Trees$ModifiersApi;Lscala/reflect/api/Names$TermNameApi;Lscala/reflect/api/Trees$TreeApi;Lscala/reflect/api/Trees$TreeApi;)Lscala/reflect/api/Trees$ValDefApi;
  #496 = InterfaceMethodref #80.#495      // scala/reflect/api/Internals$ReificationSupportApi$SyntacticValDefExtractor.apply:(Lscala/reflect/api/Trees$ModifiersApi;Lscala/reflect/api/Names$TermNameApi;Lscala/reflect/api/Trees$TreeApi;Lscala/reflect/api/Trees$TreeApi;)Lscala/reflect/api/Trees$ValDefApi;
  #497 = NameAndType        #174:#173     // EncoderClass:Lscala/reflect/api/Symbols$TypeSymbolApi;
  #498 = Fieldref           #2.#497       // argonaut/derive/JsonCodecMacros.EncoderClass:Lscala/reflect/api/Symbols$TypeSymbolApi;
  #499 = NameAndType        #177:#176     // mkEncodeJson:Lscala/reflect/api/Symbols$SymbolApi;
  #500 = Fieldref           #2.#499       // argonaut/derive/JsonCodecMacros.mkEncodeJson:Lscala/reflect/api/Symbols$SymbolApi;
  #501 = Utf8               encodeJson
  #502 = String             #501          // encodeJson
  #503 = Utf8               (Ljava/lang/Object;)Ljava/lang/Object;
  #504 = MethodType         #503          //  (Ljava/lang/Object;)Ljava/lang/Object;
  #505 = Utf8               $anonfun$codec$1
  #506 = Utf8               (Lscala/reflect/api/Trees$TypeDefApi;)Lscala/reflect/api/Names$TypeNameApi;
  #507 = NameAndType        #505:#506     // $anonfun$codec$1:(Lscala/reflect/api/Trees$TypeDefApi;)Lscala/reflect/api/Names$TypeNameApi;
  #508 = Methodref          #2.#507       // argonaut/derive/JsonCodecMacros.$anonfun$codec$1:(Lscala/reflect/api/Trees$TypeDefApi;)Lscala/reflect/api/Names$TypeNameApi;
  #509 = MethodHandle       6:#508        // REF_invokeStatic argonaut/derive/JsonCodecMacros.$anonfun$codec$1:(Lscala/reflect/api/Trees$TypeDefApi;)Lscala/reflect/api/Names$TypeNameApi;
  #510 = MethodType         #506          //  (Lscala/reflect/api/Trees$TypeDefApi;)Lscala/reflect/api/Names$TypeNameApi;
  #511 = Integer            5
  #512 = Integer            1
  #513 = Utf8               java/lang/invoke/LambdaMetafactory
  #514 = Class              #513          // java/lang/invoke/LambdaMetafactory
  #515 = Utf8               altMetafactory
  #516 = Utf8               (Ljava/lang/invoke/MethodHandles$Lookup;Ljava/lang/String;Ljava/lang/invoke/MethodType;[Ljava/lang/Object;)Ljava/lang/invoke/CallSite;
  #517 = NameAndType        #515:#516     // altMetafactory:(Ljava/lang/invoke/MethodHandles$Lookup;Ljava/lang/String;Ljava/lang/invoke/MethodType;[Ljava/lang/Object;)Ljava/lang/invoke/CallSite;
  #518 = Methodref          #514.#517     // java/lang/invoke/LambdaMetafactory.altMetafactory:(Ljava/lang/invoke/MethodHandles$Lookup;Ljava/lang/String;Ljava/lang/invoke/MethodType;[Ljava/lang/Object;)Ljava/lang/invoke/CallSite;
  #519 = MethodHandle       6:#518        // REF_invokeStatic java/lang/invoke/LambdaMetafactory.altMetafactory:(Ljava/lang/invoke/MethodHandles$Lookup;Ljava/lang/String;Ljava/lang/invoke/MethodType;[Ljava/lang/Object;)Ljava/lang/invoke/CallSite;
  #520 = Utf8               ()Lscala/Function1;
  #521 = NameAndType        #319:#520     // apply:()Lscala/Function1;
  #522 = InvokeDynamic      #0:#521       // #0:apply:()Lscala/Function1;
  #523 = Utf8               map
  #524 = Utf8               (Lscala/Function1;)Lscala/collection/immutable/List;
  #525 = NameAndType        #523:#524     // map:(Lscala/Function1;)Lscala/collection/immutable/List;
  #526 = Methodref          #221.#525     // scala/collection/immutable/List.map:(Lscala/Function1;)Lscala/collection/immutable/List;
  #527 = Utf8               mkImplicitParams$1
  #528 = Utf8               (Lscala/reflect/api/Symbols$TypeSymbolApi;Lscala/collection/immutable/List;)Lscala/collection/immutable/List;
  #529 = NameAndType        #527:#528     // mkImplicitParams$1:(Lscala/reflect/api/Symbols$TypeSymbolApi;Lscala/collection/immutable/List;)Lscala/collection/immutable/List;
  #530 = Methodref          #2.#529       // argonaut/derive/JsonCodecMacros.mkImplicitParams$1:(Lscala/reflect/api/Symbols$TypeSymbolApi;Lscala/collection/immutable/List;)Lscala/collection/immutable/List;
  #531 = Utf8               $anonfun$codec$3
  #532 = Utf8               (Largonaut/derive/JsonCodecMacros;Lscala/reflect/api/Names$TypeNameApi;)Lscala/reflect/api/Trees$TreeApi;
  #533 = NameAndType        #531:#532     // $anonfun$codec$3:(Largonaut/derive/JsonCodecMacros;Lscala/reflect/api/Names$TypeNameApi;)Lscala/reflect/api/Trees$TreeApi;
  #534 = Methodref          #2.#533       // argonaut/derive/JsonCodecMacros.$anonfun$codec$3:(Largonaut/derive/JsonCodecMacros;Lscala/reflect/api/Names$TypeNameApi;)Lscala/reflect/api/Trees$TreeApi;
  #535 = MethodHandle       6:#534        // REF_invokeStatic argonaut/derive/JsonCodecMacros.$anonfun$codec$3:(Largonaut/derive/JsonCodecMacros;Lscala/reflect/api/Names$TypeNameApi;)Lscala/reflect/api/Trees$TreeApi;
  #536 = Utf8               (Lscala/reflect/api/Names$TypeNameApi;)Lscala/reflect/api/Trees$TreeApi;
  #537 = MethodType         #536          //  (Lscala/reflect/api/Names$TypeNameApi;)Lscala/reflect/api/Trees$TreeApi;
  #538 = Utf8               (Largonaut/derive/JsonCodecMacros;)Lscala/Function1;
  #539 = NameAndType        #319:#538     // apply:(Largonaut/derive/JsonCodecMacros;)Lscala/Function1;
  #540 = InvokeDynamic      #1:#539       // #1:apply:(Largonaut/derive/JsonCodecMacros;)Lscala/Function1;
  #541 = Utf8               SyntacticDefDef
  #542 = Utf8               ()Lscala/reflect/api/Internals$ReificationSupportApi$SyntacticDefDefExtractor;
  #543 = NameAndType        #541:#542     // SyntacticDefDef:()Lscala/reflect/api/Internals$ReificationSupportApi$SyntacticDefDefExtractor;
  #544 = InterfaceMethodref #47.#543      // scala/reflect/api/Internals$ReificationSupportApi.SyntacticDefDef:()Lscala/reflect/api/Internals$ReificationSupportApi$SyntacticDefDefExtractor;
  #545 = Utf8               ImplicitParams
  #546 = Utf8               ()Lscala/reflect/api/Internals$ReificationSupportApi$ImplicitParamsExtractor;
  #547 = NameAndType        #545:#546     // ImplicitParams:()Lscala/reflect/api/Internals$ReificationSupportApi$ImplicitParamsExtractor;
  #548 = InterfaceMethodref #47.#547      // scala/reflect/api/Internals$ReificationSupportApi.ImplicitParams:()Lscala/reflect/api/Internals$ReificationSupportApi$ImplicitParamsExtractor;
  #549 = Utf8               (Lscala/collection/immutable/List;Lscala/collection/immutable/List;)Lscala/collection/immutable/List;
  #550 = NameAndType        #319:#549     // apply:(Lscala/collection/immutable/List;Lscala/collection/immutable/List;)Lscala/collection/immutable/List;
  #551 = InterfaceMethodref #53.#550      // scala/reflect/api/Internals$ReificationSupportApi$ImplicitParamsExtractor.apply:(Lscala/collection/immutable/List;Lscala/collection/immutable/List;)Lscala/collection/immutable/List;
  #552 = Utf8               (Lscala/reflect/api/Trees$ModifiersApi;Lscala/reflect/api/Names$TermNameApi;Lscala/collection/immutable/List;Lscala/collection/immutable/List;Lscala/reflect/api/Trees$TreeApi;Lscala/reflect/api/Trees$TreeApi;)Lscala/reflect/api/Trees$DefDefApi;
  #553 = NameAndType        #319:#552     // apply:(Lscala/reflect/api/Trees$ModifiersApi;Lscala/reflect/api/Names$TermNameApi;Lscala/collection/immutable/List;Lscala/collection/immutable/List;Lscala/reflect/api/Trees$TreeApi;Lscala/reflect/api/Trees$TreeApi;)Lscala/reflect/api/Trees$DefDefApi;
  #554 = InterfaceMethodref #62.#553      // scala/reflect/api/Internals$ReificationSupportApi$SyntacticDefDefExtractor.apply:(Lscala/reflect/api/Trees$ModifiersApi;Lscala/reflect/api/Names$TermNameApi;Lscala/collection/immutable/List;Lscala/collection/immutable/List;Lscala/reflect/api/Trees$TreeApi;Lscala/reflect/api/Trees$TreeApi;)Lscala/reflect/api/Trees$DefDefApi;
  #555 = Utf8               Type
  #556 = Utf8               Lscala/reflect/api/Names$TypeNameApi;
  #557 = Utf8               tparamNames
  #558 = Utf8               decodeParams
  #559 = Utf8               encodeParams
  #560 = Utf8               tpname
  #561 = Utf8               decodeNme
  #562 = Utf8               encodeNme
  #563 = Utf8               x$1
  #564 = InterfaceMethodref #148.#298     // scala/reflect/api/Trees$TypeDefApi.name:()Lscala/reflect/api/Names$TypeNameApi;
  #565 = Utf8               Lscala/reflect/api/Trees$TypeDefApi;
  #566 = Utf8               $anonfun$codec$2
  #567 = Utf8               (Largonaut/derive/JsonCodecMacros;Lscala/reflect/api/Symbols$TypeSymbolApi;Lscala/reflect/api/Names$TypeNameApi;)Lscala/reflect/api/Trees$TypedApi;
  #568 = Utf8               $this
  #569 = Utf8               typeSymbol$1
  #570 = Utf8               tparamName
  #571 = Utf8               freshName
  #572 = Utf8               (Lscala/reflect/api/Names$NameApi;)Lscala/reflect/api/Names$NameApi;
  #573 = NameAndType        #571:#572     // freshName:(Lscala/reflect/api/Names$NameApi;)Lscala/reflect/api/Names$NameApi;
  #574 = InterfaceMethodref #193.#573     // scala/reflect/macros/blackbox/Context.freshName:(Lscala/reflect/api/Names$NameApi;)Lscala/reflect/api/Names$NameApi;
  #575 = Utf8               Typed
  #576 = Utf8               ()Lscala/reflect/api/Trees$TypedExtractor;
  #577 = NameAndType        #575:#576     // Typed:()Lscala/reflect/api/Trees$TypedExtractor;
  #578 = Methodref          #199.#577     // scala/reflect/macros/Universe.Typed:()Lscala/reflect/api/Trees$TypedExtractor;
  #579 = Utf8               SyntacticTermIdent
  #580 = Utf8               ()Lscala/reflect/api/Internals$ReificationSupportApi$SyntacticTermIdentExtractor;
  #581 = NameAndType        #579:#580     // SyntacticTermIdent:()Lscala/reflect/api/Internals$ReificationSupportApi$SyntacticTermIdentExtractor;
  #582 = InterfaceMethodref #47.#581      // scala/reflect/api/Internals$ReificationSupportApi.SyntacticTermIdent:()Lscala/reflect/api/Internals$ReificationSupportApi$SyntacticTermIdentExtractor;
  #583 = Utf8               (Lscala/reflect/api/Names$TermNameApi;Z)Lscala/reflect/api/Trees$IdentApi;
  #584 = NameAndType        #319:#583     // apply:(Lscala/reflect/api/Names$TermNameApi;Z)Lscala/reflect/api/Trees$IdentApi;
  #585 = InterfaceMethodref #71.#584      // scala/reflect/api/Internals$ReificationSupportApi$SyntacticTermIdentExtractor.apply:(Lscala/reflect/api/Names$TermNameApi;Z)Lscala/reflect/api/Trees$IdentApi;
  #586 = Utf8               (Lscala/reflect/api/Trees$TreeApi;Lscala/reflect/api/Trees$TreeApi;)Lscala/reflect/api/Trees$TypedApi;
  #587 = NameAndType        #319:#586     // apply:(Lscala/reflect/api/Trees$TreeApi;Lscala/reflect/api/Trees$TreeApi;)Lscala/reflect/api/Trees$TypedApi;
  #588 = Methodref          #154.#587     // scala/reflect/api/Trees$TypedExtractor.apply:(Lscala/reflect/api/Trees$TreeApi;Lscala/reflect/api/Trees$TreeApi;)Lscala/reflect/api/Trees$TypedApi;
  #589 = Utf8               paramName
  #590 = Utf8               paramType
  #591 = Utf8               typeSymbol
  #592 = Utf8               tparamNames$1
  #593 = NameAndType        #566:#567     // $anonfun$codec$2:(Largonaut/derive/JsonCodecMacros;Lscala/reflect/api/Symbols$TypeSymbolApi;Lscala/reflect/api/Names$TypeNameApi;)Lscala/reflect/api/Trees$TypedApi;
  #594 = Methodref          #2.#593       // argonaut/derive/JsonCodecMacros.$anonfun$codec$2:(Largonaut/derive/JsonCodecMacros;Lscala/reflect/api/Symbols$TypeSymbolApi;Lscala/reflect/api/Names$TypeNameApi;)Lscala/reflect/api/Trees$TypedApi;
  #595 = MethodHandle       6:#594        // REF_invokeStatic argonaut/derive/JsonCodecMacros.$anonfun$codec$2:(Largonaut/derive/JsonCodecMacros;Lscala/reflect/api/Symbols$TypeSymbolApi;Lscala/reflect/api/Names$TypeNameApi;)Lscala/reflect/api/Trees$TypedApi;
  #596 = Utf8               (Lscala/reflect/api/Names$TypeNameApi;)Lscala/reflect/api/Trees$TypedApi;
  #597 = MethodType         #596          //  (Lscala/reflect/api/Names$TypeNameApi;)Lscala/reflect/api/Trees$TypedApi;
  #598 = Utf8               (Largonaut/derive/JsonCodecMacros;Lscala/reflect/api/Symbols$TypeSymbolApi;)Lscala/Function1;
  #599 = NameAndType        #319:#598     // apply:(Largonaut/derive/JsonCodecMacros;Lscala/reflect/api/Symbols$TypeSymbolApi;)Lscala/Function1;
  #600 = InvokeDynamic      #2:#599       // #2:apply:(Largonaut/derive/JsonCodecMacros;Lscala/reflect/api/Symbols$TypeSymbolApi;)Lscala/Function1;
  #601 = Utf8               fresh$macro$13
  #602 = Utf8               ()Lscala/reflect/api/Liftables$Liftable$;
  #603 = NameAndType        #86:#602      // Liftable:()Lscala/reflect/api/Liftables$Liftable$;
  #604 = Methodref          #199.#603     // scala/reflect/macros/Universe.Liftable:()Lscala/reflect/api/Liftables$Liftable$;
  #605 = Utf8               liftName
  #606 = Utf8               ()Lscala/reflect/api/Liftables$Liftable;
  #607 = NameAndType        #605:#606     // liftName:()Lscala/reflect/api/Liftables$Liftable;
  #608 = Methodref          #88.#607      // scala/reflect/api/Liftables$Liftable$.liftName:()Lscala/reflect/api/Liftables$Liftable;
  #609 = Utf8               (Ljava/lang/Object;)Lscala/reflect/api/Trees$TreeApi;
  #610 = NameAndType        #319:#609     // apply:(Ljava/lang/Object;)Lscala/reflect/api/Trees$TreeApi;
  #611 = InterfaceMethodref #83.#610      // scala/reflect/api/Liftables$Liftable.apply:(Ljava/lang/Object;)Lscala/reflect/api/Trees$TreeApi;
  #612 = Utf8               (Lscala/reflect/macros/blackbox/Context;)V
  #613 = Utf8               ()V
  #614 = NameAndType        #242:#613     // "<init>":()V
  #615 = Methodref          #4.#614       // java/lang/Object."<init>":()V
  #616 = Utf8               rootMirror
  #617 = Utf8               ()Lscala/reflect/api/Mirror;
  #618 = NameAndType        #616:#617     // rootMirror:()Lscala/reflect/api/Mirror;
  #619 = Methodref          #199.#618     // scala/reflect/macros/Universe.rootMirror:()Lscala/reflect/api/Mirror;
  #620 = Utf8               ()Lscala/reflect/api/TypeTags$TypeTag$;
  #621 = NameAndType        #163:#620     // TypeTag:()Lscala/reflect/api/TypeTags$TypeTag$;
  #622 = Methodref          #199.#621     // scala/reflect/macros/Universe.TypeTag:()Lscala/reflect/api/TypeTags$TypeTag$;
  #623 = Methodref          #12.#344      // argonaut/derive/JsonCodecMacros$$typecreator1$1."<init>":(Largonaut/derive/JsonCodecMacros;)V
  #624 = Utf8               (Lscala/reflect/api/Mirror;Lscala/reflect/api/TypeCreator;)Lscala/reflect/api/TypeTags$TypeTag;
  #625 = NameAndType        #319:#624     // apply:(Lscala/reflect/api/Mirror;Lscala/reflect/api/TypeCreator;)Lscala/reflect/api/TypeTags$TypeTag;
  #626 = Methodref          #165.#625     // scala/reflect/api/TypeTags$TypeTag$.apply:(Lscala/reflect/api/Mirror;Lscala/reflect/api/TypeCreator;)Lscala/reflect/api/TypeTags$TypeTag;
  #627 = Utf8               symbolOf
  #628 = Utf8               (Lscala/reflect/api/TypeTags$WeakTypeTag;)Lscala/reflect/api/Symbols$TypeSymbolApi;
  #629 = NameAndType        #627:#628     // symbolOf:(Lscala/reflect/api/TypeTags$WeakTypeTag;)Lscala/reflect/api/Symbols$TypeSymbolApi;
  #630 = Methodref          #199.#629     // scala/reflect/macros/Universe.symbolOf:(Lscala/reflect/api/TypeTags$WeakTypeTag;)Lscala/reflect/api/Symbols$TypeSymbolApi;
  #631 = Methodref          #15.#344      // argonaut/derive/JsonCodecMacros$$typecreator2$1."<init>":(Largonaut/derive/JsonCodecMacros;)V
  #632 = Methodref          #18.#344      // argonaut/derive/JsonCodecMacros$$typecreator3$1."<init>":(Largonaut/derive/JsonCodecMacros;)V
  #633 = Utf8               asClass
  #634 = Utf8               ()Lscala/reflect/api/Symbols$ClassSymbolApi;
  #635 = NameAndType        #633:#634     // asClass:()Lscala/reflect/api/Symbols$ClassSymbolApi;
  #636 = InterfaceMethodref #116.#635     // scala/reflect/api/Symbols$TypeSymbolApi.asClass:()Lscala/reflect/api/Symbols$ClassSymbolApi;
  #637 = Utf8               module
  #638 = Utf8               ()Lscala/reflect/api/Symbols$SymbolApi;
  #639 = NameAndType        #637:#638     // module:()Lscala/reflect/api/Symbols$SymbolApi;
  #640 = InterfaceMethodref #108.#639     // scala/reflect/api/Symbols$ClassSymbolApi.module:()Lscala/reflect/api/Symbols$SymbolApi;
  #641 = Methodref          #21.#344      // argonaut/derive/JsonCodecMacros$$typecreator4$1."<init>":(Largonaut/derive/JsonCodecMacros;)V
  #642 = Utf8               $u
  #643 = Utf8               Lscala/reflect/macros/Universe;
  #644 = Utf8               $m
  #645 = Utf8               Lscala/reflect/api/Mirror;
  #646 = Utf8               $deserializeLambda$
  #647 = Utf8               (Ljava/lang/invoke/SerializedLambda;)Ljava/lang/Object;
  #648 = Utf8               scala/runtime/LambdaDeserialize
  #649 = Class              #648          // scala/runtime/LambdaDeserialize
  #650 = Utf8               bootstrap
  #651 = Utf8               (Ljava/lang/invoke/MethodHandles$Lookup;Ljava/lang/String;Ljava/lang/invoke/MethodType;[Ljava/lang/invoke/MethodHandle;)Ljava/lang/invoke/CallSite;
  #652 = NameAndType        #650:#651     // bootstrap:(Ljava/lang/invoke/MethodHandles$Lookup;Ljava/lang/String;Ljava/lang/invoke/MethodType;[Ljava/lang/invoke/MethodHandle;)Ljava/lang/invoke/CallSite;
  #653 = Methodref          #649.#652     // scala/runtime/LambdaDeserialize.bootstrap:(Ljava/lang/invoke/MethodHandles$Lookup;Ljava/lang/String;Ljava/lang/invoke/MethodType;[Ljava/lang/invoke/MethodHandle;)Ljava/lang/invoke/CallSite;
  #654 = MethodHandle       6:#653        // REF_invokeStatic scala/runtime/LambdaDeserialize.bootstrap:(Ljava/lang/invoke/MethodHandles$Lookup;Ljava/lang/String;Ljava/lang/invoke/MethodType;[Ljava/lang/invoke/MethodHandle;)Ljava/lang/invoke/CallSite;
  #655 = Utf8               lambdaDeserialize
  #656 = NameAndType        #655:#647     // lambdaDeserialize:(Ljava/lang/invoke/SerializedLambda;)Ljava/lang/Object;
  #657 = InvokeDynamic      #3:#656       // #3:lambdaDeserialize:(Ljava/lang/invoke/SerializedLambda;)Ljava/lang/Object;
  #658 = Utf8               Code
  #659 = Utf8               LineNumberTable
  #660 = Utf8               LocalVariableTable
  #661 = Utf8               StackMapTable
  #662 = Utf8               MethodParameters
  #663 = Utf8               Signature
  #664 = Utf8               InnerClasses
  #665 = Utf8               SourceFile
  #666 = Utf8               RuntimeVisibleAnnotations
  #667 = Utf8               BootstrapMethods
  #668 = Utf8               ScalaInlineInfo
  #669 = Utf8               ScalaSig
{
  private final scala.reflect.macros.blackbox.Context c;
    descriptor: Lscala/reflect/macros/blackbox/Context;
    flags: (0x0012) ACC_PRIVATE, ACC_FINAL

  private final scala.reflect.api.Symbols$TypeSymbolApi DecoderClass;
    descriptor: Lscala/reflect/api/Symbols$TypeSymbolApi;
    flags: (0x0012) ACC_PRIVATE, ACC_FINAL

  private final scala.reflect.api.Symbols$TypeSymbolApi EncoderClass;
    descriptor: Lscala/reflect/api/Symbols$TypeSymbolApi;
    flags: (0x0012) ACC_PRIVATE, ACC_FINAL

  private final scala.reflect.api.Symbols$SymbolApi mkDecodeJson;
    descriptor: Lscala/reflect/api/Symbols$SymbolApi;
    flags: (0x0012) ACC_PRIVATE, ACC_FINAL

  private final scala.reflect.api.Symbols$SymbolApi mkEncodeJson;
    descriptor: Lscala/reflect/api/Symbols$SymbolApi;
    flags: (0x0012) ACC_PRIVATE, ACC_FINAL

  public scala.reflect.macros.blackbox.Context c();
    descriptor: ()Lscala/reflect/macros/blackbox/Context;
    flags: (0x0001) ACC_PUBLIC
    Code:
      stack=1, locals=1, args_size=1
         0: aload_0
         1: getfield      #180                // Field c:Lscala/reflect/macros/blackbox/Context;
         4: areturn
      LineNumberTable:
        line 13: 0
      LocalVariableTable:
        Start  Length  Slot  Name   Signature
            0       5     0  this   Largonaut/derive/JsonCodecMacros;

  private boolean isCaseClassOrSealed(scala.reflect.api.Trees$ClassDefApi);
    descriptor: (Lscala/reflect/api/Trees$ClassDefApi;)Z
    flags: (0x0002) ACC_PRIVATE
    Code:
      stack=2, locals=2, args_size=2
         0: aload_1
         1: invokeinterface #189,  1          // InterfaceMethod scala/reflect/api/Trees$ClassDefApi.mods:()Lscala/reflect/api/Trees$ModifiersApi;
         6: aload_0
         7: invokevirtual #191                // Method c:()Lscala/reflect/macros/blackbox/Context;
        10: invokeinterface #197,  1          // InterfaceMethod scala/reflect/macros/blackbox/Context.universe:()Lscala/reflect/macros/Universe;
        15: invokevirtual #203                // Method scala/reflect/macros/Universe.Flag:()Lscala/reflect/api/FlagSets$FlagValues;
        18: invokeinterface #207,  1          // InterfaceMethod scala/reflect/api/FlagSets$FlagValues.CASE:()Ljava/lang/Object;
        23: invokevirtual #211                // Method scala/reflect/api/Trees$ModifiersApi.hasFlag:(Ljava/lang/Object;)Z
        26: ifne          58
        29: aload_1
        30: invokeinterface #189,  1          // InterfaceMethod scala/reflect/api/Trees$ClassDefApi.mods:()Lscala/reflect/api/Trees$ModifiersApi;
        35: aload_0
        36: invokevirtual #191                // Method c:()Lscala/reflect/macros/blackbox/Context;
        39: invokeinterface #197,  1          // InterfaceMethod scala/reflect/macros/blackbox/Context.universe:()Lscala/reflect/macros/Universe;
        44: invokevirtual #203                // Method scala/reflect/macros/Universe.Flag:()Lscala/reflect/api/FlagSets$FlagValues;
        47: invokeinterface #214,  1          // InterfaceMethod scala/reflect/api/FlagSets$FlagValues.SEALED:()Ljava/lang/Object;
        52: invokevirtual #211                // Method scala/reflect/api/Trees$ModifiersApi.hasFlag:(Ljava/lang/Object;)Z
        55: ifeq          62
        58: iconst_1
        59: goto          63
        62: iconst_0
        63: ireturn
      StackMapTable: number_of_entries = 3
        frame_type = 58 /* same */
        frame_type = 3 /* same */
        frame_type = 64 /* same_locals_1_stack_item */
          stack = [ int ]
      LineNumberTable:
        line 17: 0
      LocalVariableTable:
        Start  Length  Slot  Name   Signature
            0      64     0  this   Largonaut/derive/JsonCodecMacros;
            0      64     1 clsDef   Lscala/reflect/api/Trees$ClassDefApi;
    MethodParameters:
      Name                           Flags
      clsDef                         final

  public scala.reflect.api.Trees$TreeApi jsonCodecAnnotationMacro(scala.collection.immutable.Seq<scala.reflect.api.Trees$TreeApi>);
    descriptor: (Lscala/collection/immutable/Seq;)Lscala/reflect/api/Trees$TreeApi;
    flags: (0x0001) ACC_PUBLIC
    Code:
      stack=15, locals=19, args_size=2
         0: iconst_0
         1: istore_3
         2: aconst_null
         3: astore        4
         5: aload_1
         6: astore        5
         8: aload         5
        10: instanceof    #221                // class scala/collection/immutable/List
        13: ifeq          362
        16: iconst_1
        17: istore_3
        18: aload         5
        20: checkcast     #221                // class scala/collection/immutable/List
        23: astore        4
        25: getstatic     #227                // Field scala/collection/immutable/List$.MODULE$:Lscala/collection/immutable/List$;
        28: aload         4
        30: invokevirtual #231                // Method scala/collection/immutable/List$.unapplySeq:(Lscala/collection/SeqOps;)Lscala/collection/SeqOps;
        33: astore        6
        35: getstatic     #234                // Field scala/collection/SeqFactory$UnapplySeqWrapper$.MODULE$:Lscala/collection/SeqFactory$UnapplySeqWrapper$;
        38: aload         6
        40: invokevirtual #238                // Method scala/collection/SeqFactory$UnapplySeqWrapper$.isEmpty$extension:(Lscala/collection/SeqOps;)Z
        43: ifne          359
        46: new           #29                 // class scala/collection/SeqFactory$UnapplySeqWrapper
        49: dup
        50: getstatic     #234                // Field scala/collection/SeqFactory$UnapplySeqWrapper$.MODULE$:Lscala/collection/SeqFactory$UnapplySeqWrapper$;
        53: aload         6
        55: invokevirtual #241                // Method scala/collection/SeqFactory$UnapplySeqWrapper$.get$extension:(Lscala/collection/SeqOps;)Lscala/collection/SeqOps;
        58: invokespecial #245                // Method scala/collection/SeqFactory$UnapplySeqWrapper."<init>":(Lscala/collection/SeqOps;)V
        61: ifnull        359
        64: getstatic     #234                // Field scala/collection/SeqFactory$UnapplySeqWrapper$.MODULE$:Lscala/collection/SeqFactory$UnapplySeqWrapper$;
        67: getstatic     #234                // Field scala/collection/SeqFactory$UnapplySeqWrapper$.MODULE$:Lscala/collection/SeqFactory$UnapplySeqWrapper$;
        70: aload         6
        72: invokevirtual #241                // Method scala/collection/SeqFactory$UnapplySeqWrapper$.get$extension:(Lscala/collection/SeqOps;)Lscala/collection/SeqOps;
        75: iconst_1
        76: invokevirtual #249                // Method scala/collection/SeqFactory$UnapplySeqWrapper$.lengthCompare$extension:(Lscala/collection/SeqOps;I)I
        79: iconst_0
        80: if_icmpne     359
        83: getstatic     #234                // Field scala/collection/SeqFactory$UnapplySeqWrapper$.MODULE$:Lscala/collection/SeqFactory$UnapplySeqWrapper$;
        86: getstatic     #234                // Field scala/collection/SeqFactory$UnapplySeqWrapper$.MODULE$:Lscala/collection/SeqFactory$UnapplySeqWrapper$;
        89: aload         6
        91: invokevirtual #241                // Method scala/collection/SeqFactory$UnapplySeqWrapper$.get$extension:(Lscala/collection/SeqOps;)Lscala/collection/SeqOps;
        94: iconst_0
        95: invokevirtual #253                // Method scala/collection/SeqFactory$UnapplySeqWrapper$.apply$extension:(Lscala/collection/SeqOps;I)Ljava/lang/Object;
        98: checkcast     #145                // class scala/reflect/api/Trees$TreeApi
       101: astore        7
       103: aload         7
       105: ifnull        356
       108: aload_0
       109: invokevirtual #191                // Method c:()Lscala/reflect/macros/blackbox/Context;
       112: invokeinterface #197,  1          // InterfaceMethod scala/reflect/macros/blackbox/Context.universe:()Lscala/reflect/macros/Universe;
       117: invokevirtual #257                // Method scala/reflect/macros/Universe.ClassDefTag:()Lscala/reflect/ClassTag;
       120: aload         7
       122: invokeinterface #263,  2          // InterfaceMethod scala/reflect/ClassTag.unapply:(Ljava/lang/Object;)Lscala/Option;
       127: astore        8
       129: aload         8
       131: invokevirtual #269                // Method scala/Option.isEmpty:()Z
       134: ifne          353
       137: aload         8
       139: invokevirtual #272                // Method scala/Option.get:()Ljava/lang/Object;
       142: ifnull        353
       145: aload_0
       146: aload         7
       148: checkcast     #119                // class scala/reflect/api/Trees$ClassDefApi
       151: invokespecial #274                // Method isCaseClassOrSealed:(Lscala/reflect/api/Trees$ClassDefApi;)Z
       154: ifeq          353
       157: aload_0
       158: invokevirtual #191                // Method c:()Lscala/reflect/macros/blackbox/Context;
       161: invokeinterface #197,  1          // InterfaceMethod scala/reflect/macros/blackbox/Context.universe:()Lscala/reflect/macros/Universe;
       166: invokevirtual #278                // Method scala/reflect/macros/Universe.internal:()Lscala/reflect/api/Internals$InternalApi;
       169: invokeinterface #282,  1          // InterfaceMethod scala/reflect/api/Internals$InternalApi.reificationSupport:()Lscala/reflect/api/Internals$ReificationSupportApi;
       174: invokeinterface #286,  1          // InterfaceMethod scala/reflect/api/Internals$ReificationSupportApi.SyntacticBlock:()Lscala/reflect/api/Internals$ReificationSupportApi$SyntacticBlockExtractor;
       179: new           #288                // class scala/collection/immutable/$colon$colon
       182: dup
       183: aload         7
       185: checkcast     #130                // class scala/reflect/api/Trees$ImplDefApi
       188: new           #288                // class scala/collection/immutable/$colon$colon
       191: dup
       192: aload_0
       193: invokevirtual #191                // Method c:()Lscala/reflect/macros/blackbox/Context;
       196: invokeinterface #197,  1          // InterfaceMethod scala/reflect/macros/blackbox/Context.universe:()Lscala/reflect/macros/Universe;
       201: invokevirtual #278                // Method scala/reflect/macros/Universe.internal:()Lscala/reflect/api/Internals$InternalApi;
       204: invokeinterface #282,  1          // InterfaceMethod scala/reflect/api/Internals$InternalApi.reificationSupport:()Lscala/reflect/api/Internals$ReificationSupportApi;
       209: invokeinterface #292,  1          // InterfaceMethod scala/reflect/api/Internals$ReificationSupportApi.SyntacticObjectDef:()Lscala/reflect/api/Internals$ReificationSupportApi$SyntacticObjectDefExtractor;
       214: aload_0
       215: invokevirtual #191                // Method c:()Lscala/reflect/macros/blackbox/Context;
       218: invokeinterface #197,  1          // InterfaceMethod scala/reflect/macros/blackbox/Context.universe:()Lscala/reflect/macros/Universe;
       223: invokevirtual #295                // Method scala/reflect/macros/Universe.NoMods:()Lscala/reflect/api/Trees$ModifiersApi;
       226: aload         7
       228: checkcast     #119                // class scala/reflect/api/Trees$ClassDefApi
       231: invokeinterface #299,  1          // InterfaceMethod scala/reflect/api/Trees$ClassDefApi.name:()Lscala/reflect/api/Names$TypeNameApi;
       236: checkcast     #91                 // class scala/reflect/api/Names$NameApi
       239: invokevirtual #303                // Method scala/reflect/api/Names$NameApi.toTermName:()Lscala/reflect/api/Names$TermNameApi;
       242: getstatic     #308                // Field scala/collection/immutable/Nil$.MODULE$:Lscala/collection/immutable/Nil$;
       245: new           #288                // class scala/collection/immutable/$colon$colon
       248: dup
       249: aload_0
       250: invokevirtual #191                // Method c:()Lscala/reflect/macros/blackbox/Context;
       253: invokeinterface #197,  1          // InterfaceMethod scala/reflect/macros/blackbox/Context.universe:()Lscala/reflect/macros/Universe;
       258: invokevirtual #278                // Method scala/reflect/macros/Universe.internal:()Lscala/reflect/api/Internals$InternalApi;
       261: invokeinterface #282,  1          // InterfaceMethod scala/reflect/api/Internals$InternalApi.reificationSupport:()Lscala/reflect/api/Internals$ReificationSupportApi;
       266: invokeinterface #312,  1          // InterfaceMethod scala/reflect/api/Internals$ReificationSupportApi.ScalaDot:()Lscala/reflect/api/Internals$ReificationSupportApi$ScalaDotExtractor;
       271: aload_0
       272: invokevirtual #191                // Method c:()Lscala/reflect/macros/blackbox/Context;
       275: invokeinterface #197,  1          // InterfaceMethod scala/reflect/macros/blackbox/Context.universe:()Lscala/reflect/macros/Universe;
       280: invokevirtual #316                // Method scala/reflect/macros/Universe.TypeName:()Lscala/reflect/api/Names$TypeNameExtractor;
       283: ldc_w         #318                // String AnyRef
       286: invokevirtual #322                // Method scala/reflect/api/Names$TypeNameExtractor.apply:(Ljava/lang/String;)Lscala/reflect/api/Names$TypeNameApi;
       289: checkcast     #91                 // class scala/reflect/api/Names$NameApi
       292: invokeinterface #325,  2          // InterfaceMethod scala/reflect/api/Internals$ReificationSupportApi$ScalaDotExtractor.apply:(Lscala/reflect/api/Names$NameApi;)Lscala/reflect/api/Trees$TreeApi;
       297: getstatic     #308                // Field scala/collection/immutable/Nil$.MODULE$:Lscala/collection/immutable/Nil$;
       300: invokespecial #328                // Method scala/collection/immutable/$colon$colon."<init>":(Ljava/lang/Object;Lscala/collection/immutable/List;)V
       303: checkcast     #221                // class scala/collection/immutable/List
       306: aload_0
       307: invokevirtual #191                // Method c:()Lscala/reflect/macros/blackbox/Context;
       310: invokeinterface #197,  1          // InterfaceMethod scala/reflect/macros/blackbox/Context.universe:()Lscala/reflect/macros/Universe;
       315: invokevirtual #332                // Method scala/reflect/macros/Universe.noSelfType:()Lscala/reflect/api/Trees$ValDefApi;
       318: aload_0
       319: aload         7
       321: checkcast     #119                // class scala/reflect/api/Trees$ClassDefApi
       324: invokespecial #336                // Method codec:(Lscala/reflect/api/Trees$ClassDefApi;)Lscala/collection/immutable/List;
       327: invokeinterface #339,  7          // InterfaceMethod scala/reflect/api/Internals$ReificationSupportApi$SyntacticObjectDefExtractor.apply:(Lscala/reflect/api/Trees$ModifiersApi;Lscala/reflect/api/Names$TermNameApi;Lscala/collection/immutable/List;Lscala/collection/immutable/List;Lscala/reflect/api/Trees$TreeApi;Lscala/collection/immutable/List;)Lscala/reflect/api/Trees$ModuleDefApi;
       332: getstatic     #308                // Field scala/collection/immutable/Nil$.MODULE$:Lscala/collection/immutable/Nil$;
       335: invokespecial #328                // Method scala/collection/immutable/$colon$colon."<init>":(Ljava/lang/Object;Lscala/collection/immutable/List;)V
       338: invokespecial #328                // Method scala/collection/immutable/$colon$colon."<init>":(Ljava/lang/Object;Lscala/collection/immutable/List;)V
       341: checkcast     #221                // class scala/collection/immutable/List
       344: invokeinterface #342,  2          // InterfaceMethod scala/reflect/api/Internals$ReificationSupportApi$SyntacticBlockExtractor.apply:(Lscala/collection/immutable/List;)Lscala/reflect/api/Trees$TreeApi;
       349: astore_2
       350: goto          811
       353: goto          365
       356: goto          365
       359: goto          365
       362: goto          365
       365: iload_3
       366: ifeq          786
       369: getstatic     #227                // Field scala/collection/immutable/List$.MODULE$:Lscala/collection/immutable/List$;
       372: aload         4
       374: invokevirtual #231                // Method scala/collection/immutable/List$.unapplySeq:(Lscala/collection/SeqOps;)Lscala/collection/SeqOps;
       377: astore        9
       379: getstatic     #234                // Field scala/collection/SeqFactory$UnapplySeqWrapper$.MODULE$:Lscala/collection/SeqFactory$UnapplySeqWrapper$;
       382: aload         9
       384: invokevirtual #238                // Method scala/collection/SeqFactory$UnapplySeqWrapper$.isEmpty$extension:(Lscala/collection/SeqOps;)Z
       387: ifne          783
       390: new           #29                 // class scala/collection/SeqFactory$UnapplySeqWrapper
       393: dup
       394: getstatic     #234                // Field scala/collection/SeqFactory$UnapplySeqWrapper$.MODULE$:Lscala/collection/SeqFactory$UnapplySeqWrapper$;
       397: aload         9
       399: invokevirtual #241                // Method scala/collection/SeqFactory$UnapplySeqWrapper$.get$extension:(Lscala/collection/SeqOps;)Lscala/collection/SeqOps;
       402: invokespecial #245                // Method scala/collection/SeqFactory$UnapplySeqWrapper."<init>":(Lscala/collection/SeqOps;)V
       405: ifnull        783
       408: getstatic     #234                // Field scala/collection/SeqFactory$UnapplySeqWrapper$.MODULE$:Lscala/collection/SeqFactory$UnapplySeqWrapper$;
       411: getstatic     #234                // Field scala/collection/SeqFactory$UnapplySeqWrapper$.MODULE$:Lscala/collection/SeqFactory$UnapplySeqWrapper$;
       414: aload         9
       416: invokevirtual #241                // Method scala/collection/SeqFactory$UnapplySeqWrapper$.get$extension:(Lscala/collection/SeqOps;)Lscala/collection/SeqOps;
       419: iconst_2
       420: invokevirtual #249                // Method scala/collection/SeqFactory$UnapplySeqWrapper$.lengthCompare$extension:(Lscala/collection/SeqOps;I)I
       423: iconst_0
       424: if_icmpne     783
       427: getstatic     #234                // Field scala/collection/SeqFactory$UnapplySeqWrapper$.MODULE$:Lscala/collection/SeqFactory$UnapplySeqWrapper$;
       430: getstatic     #234                // Field scala/collection/SeqFactory$UnapplySeqWrapper$.MODULE$:Lscala/collection/SeqFactory$UnapplySeqWrapper$;
       433: aload         9
       435: invokevirtual #241                // Method scala/collection/SeqFactory$UnapplySeqWrapper$.get$extension:(Lscala/collection/SeqOps;)Lscala/collection/SeqOps;
       438: iconst_0
       439: invokevirtual #253                // Method scala/collection/SeqFactory$UnapplySeqWrapper$.apply$extension:(Lscala/collection/SeqOps;I)Ljava/lang/Object;
       442: checkcast     #145                // class scala/reflect/api/Trees$TreeApi
       445: astore        10
       447: getstatic     #234                // Field scala/collection/SeqFactory$UnapplySeqWrapper$.MODULE$:Lscala/collection/SeqFactory$UnapplySeqWrapper$;
       450: getstatic     #234                // Field scala/collection/SeqFactory$UnapplySeqWrapper$.MODULE$:Lscala/collection/SeqFactory$UnapplySeqWrapper$;
       453: aload         9
       455: invokevirtual #241                // Method scala/collection/SeqFactory$UnapplySeqWrapper$.get$extension:(Lscala/collection/SeqOps;)Lscala/collection/SeqOps;
       458: iconst_1
       459: invokevirtual #253                // Method scala/collection/SeqFactory$UnapplySeqWrapper$.apply$extension:(Lscala/collection/SeqOps;I)Ljava/lang/Object;
       462: checkcast     #145                // class scala/reflect/api/Trees$TreeApi
       465: astore        11
       467: aload         10
       469: ifnull        780
       472: aload_0
       473: invokevirtual #191                // Method c:()Lscala/reflect/macros/blackbox/Context;
       476: invokeinterface #197,  1          // InterfaceMethod scala/reflect/macros/blackbox/Context.universe:()Lscala/reflect/macros/Universe;
       481: invokevirtual #257                // Method scala/reflect/macros/Universe.ClassDefTag:()Lscala/reflect/ClassTag;
       484: aload         10
       486: invokeinterface #263,  2          // InterfaceMethod scala/reflect/ClassTag.unapply:(Ljava/lang/Object;)Lscala/Option;
       491: astore        12
       493: aload         12
       495: invokevirtual #269                // Method scala/Option.isEmpty:()Z
       498: ifne          777
       501: aload         12
       503: invokevirtual #272                // Method scala/Option.get:()Ljava/lang/Object;
       506: ifnull        777
       509: aload         11
       511: ifnull        777
       514: new           #10                 // class argonaut/derive/JsonCodecMacros$$anon$1
       517: dup
       518: aload_0
       519: invokespecial #345                // Method argonaut/derive/JsonCodecMacros$$anon$1."<init>":(Largonaut/derive/JsonCodecMacros;)V
       522: aload         11
       524: invokevirtual #346                // Method argonaut/derive/JsonCodecMacros$$anon$1.unapply:(Ljava/lang/Object;)Lscala/Option;
       527: astore        13
       529: aload         13
       531: invokevirtual #269                // Method scala/Option.isEmpty:()Z
       534: ifne          774
       537: aload         13
       539: invokevirtual #272                // Method scala/Option.get:()Ljava/lang/Object;
       542: checkcast     #348                // class scala/Tuple5
       545: invokevirtual #351                // Method scala/Tuple5._1:()Ljava/lang/Object;
       548: checkcast     #96                 // class scala/reflect/api/Names$TermNameApi
       551: astore        14
       553: aload         13
       555: invokevirtual #272                // Method scala/Option.get:()Ljava/lang/Object;
       558: checkcast     #348                // class scala/Tuple5
       561: invokevirtual #354                // Method scala/Tuple5._2:()Ljava/lang/Object;
       564: checkcast     #221                // class scala/collection/immutable/List
       567: astore        15
       569: aload         13
       571: invokevirtual #272                // Method scala/Option.get:()Ljava/lang/Object;
       574: checkcast     #348                // class scala/Tuple5
       577: invokevirtual #357                // Method scala/Tuple5._3:()Ljava/lang/Object;
       580: checkcast     #221                // class scala/collection/immutable/List
       583: astore        16
       585: aload         13
       587: invokevirtual #272                // Method scala/Option.get:()Ljava/lang/Object;
       590: checkcast     #348                // class scala/Tuple5
       593: invokevirtual #360                // Method scala/Tuple5._4:()Ljava/lang/Object;
       596: checkcast     #157                // class scala/reflect/api/Trees$ValDefApi
       599: astore        17
       601: aload         13
       603: invokevirtual #272                // Method scala/Option.get:()Ljava/lang/Object;
       606: checkcast     #348                // class scala/Tuple5
       609: invokevirtual #363                // Method scala/Tuple5._5:()Ljava/lang/Object;
       612: checkcast     #221                // class scala/collection/immutable/List
       615: astore        18
       617: aload_0
       618: aload         10
       620: checkcast     #119                // class scala/reflect/api/Trees$ClassDefApi
       623: invokespecial #274                // Method isCaseClassOrSealed:(Lscala/reflect/api/Trees$ClassDefApi;)Z
       626: ifeq          771
       629: aload_0
       630: invokevirtual #191                // Method c:()Lscala/reflect/macros/blackbox/Context;
       633: invokeinterface #197,  1          // InterfaceMethod scala/reflect/macros/blackbox/Context.universe:()Lscala/reflect/macros/Universe;
       638: invokevirtual #278                // Method scala/reflect/macros/Universe.internal:()Lscala/reflect/api/Internals$InternalApi;
       641: invokeinterface #282,  1          // InterfaceMethod scala/reflect/api/Internals$InternalApi.reificationSupport:()Lscala/reflect/api/Internals$ReificationSupportApi;
       646: invokeinterface #286,  1          // InterfaceMethod scala/reflect/api/Internals$ReificationSupportApi.SyntacticBlock:()Lscala/reflect/api/Internals$ReificationSupportApi$SyntacticBlockExtractor;
       651: new           #288                // class scala/collection/immutable/$colon$colon
       654: dup
       655: aload         10
       657: checkcast     #130                // class scala/reflect/api/Trees$ImplDefApi
       660: new           #288                // class scala/collection/immutable/$colon$colon
       663: dup
       664: aload_0
       665: invokevirtual #191                // Method c:()Lscala/reflect/macros/blackbox/Context;
       668: invokeinterface #197,  1          // InterfaceMethod scala/reflect/macros/blackbox/Context.universe:()Lscala/reflect/macros/Universe;
       673: invokevirtual #278                // Method scala/reflect/macros/Universe.internal:()Lscala/reflect/api/Internals$InternalApi;
       676: invokeinterface #282,  1          // InterfaceMethod scala/reflect/api/Internals$InternalApi.reificationSupport:()Lscala/reflect/api/Internals$ReificationSupportApi;
       681: invokeinterface #292,  1          // InterfaceMethod scala/reflect/api/Internals$ReificationSupportApi.SyntacticObjectDef:()Lscala/reflect/api/Internals$ReificationSupportApi$SyntacticObjectDefExtractor;
       686: aload_0
       687: invokevirtual #191                // Method c:()Lscala/reflect/macros/blackbox/Context;
       690: invokeinterface #197,  1          // InterfaceMethod scala/reflect/macros/blackbox/Context.universe:()Lscala/reflect/macros/Universe;
       695: invokevirtual #295                // Method scala/reflect/macros/Universe.NoMods:()Lscala/reflect/api/Trees$ModifiersApi;
       698: aload         14
       700: aload_0
       701: invokevirtual #191                // Method c:()Lscala/reflect/macros/blackbox/Context;
       704: invokeinterface #197,  1          // InterfaceMethod scala/reflect/macros/blackbox/Context.universe:()Lscala/reflect/macros/Universe;
       709: invokevirtual #278                // Method scala/reflect/macros/Universe.internal:()Lscala/reflect/api/Internals$InternalApi;
       712: invokeinterface #282,  1          // InterfaceMethod scala/reflect/api/Internals$InternalApi.reificationSupport:()Lscala/reflect/api/Internals$ReificationSupportApi;
       717: aload         15
       719: invokeinterface #367,  2          // InterfaceMethod scala/reflect/api/Internals$ReificationSupportApi.mkEarlyDef:(Lscala/collection/immutable/List;)Lscala/collection/immutable/List;
       724: aload         16
       726: aload         17
       728: aload         18
       730: aload_0
       731: aload         10
       733: checkcast     #119                // class scala/reflect/api/Trees$ClassDefApi
       736: invokespecial #336                // Method codec:(Lscala/reflect/api/Trees$ClassDefApi;)Lscala/collection/immutable/List;
       739: invokevirtual #371                // Method scala/collection/immutable/List.$plus$plus:(Lscala/collection/IterableOnce;)Ljava/lang/Object;
       742: checkcast     #221                // class scala/collection/immutable/List
       745: invokeinterface #339,  7          // InterfaceMethod scala/reflect/api/Internals$ReificationSupportApi$SyntacticObjectDefExtractor.apply:(Lscala/reflect/api/Trees$ModifiersApi;Lscala/reflect/api/Names$TermNameApi;Lscala/collection/immutable/List;Lscala/collection/immutable/List;Lscala/reflect/api/Trees$TreeApi;Lscala/collection/immutable/List;)Lscala/reflect/api/Trees$ModuleDefApi;
       750: getstatic     #308                // Field scala/collection/immutable/Nil$.MODULE$:Lscala/collection/immutable/Nil$;
       753: invokespecial #328                // Method scala/collection/immutable/$colon$colon."<init>":(Ljava/lang/Object;Lscala/collection/immutable/List;)V
       756: invokespecial #328                // Method scala/collection/immutable/$colon$colon."<init>":(Ljava/lang/Object;Lscala/collection/immutable/List;)V
       759: checkcast     #221                // class scala/collection/immutable/List
       762: invokeinterface #342,  2          // InterfaceMethod scala/reflect/api/Internals$ReificationSupportApi$SyntacticBlockExtractor.apply:(Lscala/collection/immutable/List;)Lscala/reflect/api/Trees$TreeApi;
       767: astore_2
       768: goto          811
       771: goto          789
       774: goto          789
       777: goto          789
       780: goto          789
       783: goto          789
       786: goto          789
       789: aload_0
       790: invokevirtual #191                // Method c:()Lscala/reflect/macros/blackbox/Context;
       793: aload_0
       794: invokevirtual #191                // Method c:()Lscala/reflect/macros/blackbox/Context;
       797: invokeinterface #375,  1          // InterfaceMethod scala/reflect/macros/blackbox/Context.enclosingPosition:()Lscala/reflect/api/Position;
       802: ldc_w         #377                // String Invalid annotation target: must be a case class or a sealed trait/class
       805: invokeinterface #381,  3          // InterfaceMethod scala/reflect/macros/blackbox/Context.abort:(Lscala/reflect/api/Position;Ljava/lang/String;)Lscala/runtime/Nothing$;
       810: athrow
       811: aload_2
       812: areturn
      StackMapTable: number_of_entries = 13
        frame_type = 255 /* full_frame */
          offset_delta = 353
          locals = [ class argonaut/derive/JsonCodecMacros, class scala/collection/immutable/Seq, top, int, class scala/collection/immutable/List, class scala/collection/immutable/Seq, class scala/collection/SeqOps, class scala/reflect/api/Trees$TreeApi, class scala/Option ]
          stack = []
        frame_type = 250 /* chop */
          offset_delta = 2
        frame_type = 250 /* chop */
          offset_delta = 2
        frame_type = 255 /* full_frame */
          offset_delta = 2
          locals = [ class argonaut/derive/JsonCodecMacros, class scala/collection/immutable/Seq, top, int, null, class scala/collection/immutable/Seq ]
          stack = []
        frame_type = 255 /* full_frame */
          offset_delta = 2
          locals = [ class argonaut/derive/JsonCodecMacros, class scala/collection/immutable/Seq, top, int, class scala/collection/immutable/List, class scala/collection/immutable/Seq ]
          stack = []
        frame_type = 255 /* full_frame */
          offset_delta = 405
          locals = [ class argonaut/derive/JsonCodecMacros, class scala/collection/immutable/Seq, top, int, class scala/collection/immutable/List, class scala/collection/immutable/Seq, top, top, top, class scala/collection/SeqOps, class scala/reflect/api/Trees$TreeApi, class scala/reflect/api/Trees$TreeApi, class scala/Option, class scala/Option, class scala/reflect/api/Names$TermNameApi, class scala/collection/immutable/List, class scala/collection/immutable/List, class scala/reflect/api/Trees$ValDefApi, class scala/collection/immutable/List ]
          stack = []
        frame_type = 255 /* full_frame */
          offset_delta = 2
          locals = [ class argonaut/derive/JsonCodecMacros, class scala/collection/immutable/Seq, top, int, class scala/collection/immutable/List, class scala/collection/immutable/Seq, top, top, top, class scala/collection/SeqOps, class scala/reflect/api/Trees$TreeApi, class scala/reflect/api/Trees$TreeApi, class scala/Option, class scala/Option ]
          stack = []
        frame_type = 250 /* chop */
          offset_delta = 2
        frame_type = 250 /* chop */
          offset_delta = 2
        frame_type = 249 /* chop */
          offset_delta = 2
        frame_type = 255 /* full_frame */
          offset_delta = 2
          locals = [ class argonaut/derive/JsonCodecMacros, class scala/collection/immutable/Seq, top, int, class scala/collection/immutable/List, class scala/collection/immutable/Seq ]
          stack = []
        frame_type = 2 /* same */
        frame_type = 255 /* full_frame */
          offset_delta = 21
          locals = [ class argonaut/derive/JsonCodecMacros, class scala/collection/immutable/Seq, class scala/reflect/api/Trees$TreeApi, int, class scala/collection/immutable/List, class scala/collection/immutable/Seq ]
          stack = []
      LineNumberTable:
        line 19: 0
        line 20: 8
        line 19: 137
        line 20: 145
        line 21: 157
        line 22: 183
        line 21: 188
        line 23: 226
        line 21: 242
        line 24: 318
        line 21: 332
        line 20: 353
        line 27: 365
        line 28: 427
        line 27: 433
        line 28: 438
        line 29: 447
        line 27: 453
        line 29: 458
        line 28: 467
        line 19: 501
        line 29: 509
        line 19: 537
        line 19: 553
        line 19: 569
        line 19: 585
        line 19: 601
        line 30: 617
        line 31: 629
        line 32: 655
        line 31: 660
        line 33: 698
        line 31: 700
        line 33: 717
        line 34: 728
        line 35: 730
        line 31: 750
        line 29: 771
        line 28: 780
        line 27: 783
        line 38: 789
        line 39: 802
        line 19: 811
      LocalVariableTable:
        Start  Length  Slot  Name   Signature
          101     258     7 clsDef   Lscala/reflect/api/Trees$TreeApi;
          551     223    14 objName   Lscala/reflect/api/Names$TermNameApi;
          567     207    15 objEarlyDefs   Lscala/collection/immutable/List;
          583     191    16 objParents   Lscala/collection/immutable/List;
          599     175    17 objSelf   Lscala/reflect/api/Trees$ValDefApi;
          615     159    18 objDefs   Lscala/collection/immutable/List;
          445     338    10 clsDef   Lscala/reflect/api/Trees$TreeApi;
            0     813     0  this   Largonaut/derive/JsonCodecMacros;
            0     813     1 annottees   Lscala/collection/immutable/Seq;
    Signature: #218                         // (Lscala/collection/immutable/Seq<Lscala/reflect/api/Trees$TreeApi;>;)Lscala/reflect/api/Trees$TreeApi;
    MethodParameters:
      Name                           Flags
      annottees                      final

  private scala.collection.immutable.List<scala.reflect.api.Trees$TreeApi> codec(scala.reflect.api.Trees$ClassDefApi);
    descriptor: (Lscala/reflect/api/Trees$ClassDefApi;)Lscala/collection/immutable/List;
    flags: (0x0002) ACC_PRIVATE
    Code:
      stack=18, locals=11, args_size=2
         0: aload_1
         1: invokeinterface #299,  1          // InterfaceMethod scala/reflect/api/Trees$ClassDefApi.name:()Lscala/reflect/api/Names$TypeNameApi;
         6: astore_2
         7: aload_1
         8: invokeinterface #400,  1          // InterfaceMethod scala/reflect/api/Trees$ClassDefApi.tparams:()Lscala/collection/immutable/List;
        13: astore_3
        14: aload_0
        15: invokevirtual #191                // Method c:()Lscala/reflect/macros/blackbox/Context;
        18: invokeinterface #197,  1          // InterfaceMethod scala/reflect/macros/blackbox/Context.universe:()Lscala/reflect/macros/Universe;
        23: invokevirtual #404                // Method scala/reflect/macros/Universe.TermName:()Lscala/reflect/api/Names$TermNameExtractor;
        26: new           #406                // class java/lang/StringBuilder
        29: dup
        30: ldc_w         #407                // int 6
        33: invokespecial #410                // Method java/lang/StringBuilder."<init>":(I)V
        36: ldc_w         #412                // String decode
        39: invokevirtual #416                // Method java/lang/StringBuilder.append:(Ljava/lang/String;)Ljava/lang/StringBuilder;
        42: aload_2
        43: checkcast     #91                 // class scala/reflect/api/Names$NameApi
        46: invokevirtual #420                // Method scala/reflect/api/Names$NameApi.decodedName:()Lscala/reflect/api/Names$NameApi;
        49: invokevirtual #423                // Method java/lang/StringBuilder.append:(Ljava/lang/Object;)Ljava/lang/StringBuilder;
        52: invokevirtual #427                // Method java/lang/StringBuilder.toString:()Ljava/lang/String;
        55: invokevirtual #430                // Method scala/reflect/api/Names$TermNameExtractor.apply:(Ljava/lang/String;)Lscala/reflect/api/Names$TermNameApi;
        58: astore        4
        60: aload_0
        61: invokevirtual #191                // Method c:()Lscala/reflect/macros/blackbox/Context;
        64: invokeinterface #197,  1          // InterfaceMethod scala/reflect/macros/blackbox/Context.universe:()Lscala/reflect/macros/Universe;
        69: invokevirtual #404                // Method scala/reflect/macros/Universe.TermName:()Lscala/reflect/api/Names$TermNameExtractor;
        72: new           #406                // class java/lang/StringBuilder
        75: dup
        76: ldc_w         #407                // int 6
        79: invokespecial #410                // Method java/lang/StringBuilder."<init>":(I)V
        82: ldc_w         #432                // String encode
        85: invokevirtual #416                // Method java/lang/StringBuilder.append:(Ljava/lang/String;)Ljava/lang/StringBuilder;
        88: aload_2
        89: checkcast     #91                 // class scala/reflect/api/Names$NameApi
        92: invokevirtual #420                // Method scala/reflect/api/Names$NameApi.decodedName:()Lscala/reflect/api/Names$NameApi;
        95: invokevirtual #423                // Method java/lang/StringBuilder.append:(Ljava/lang/Object;)Ljava/lang/StringBuilder;
        98: invokevirtual #427                // Method java/lang/StringBuilder.toString:()Ljava/lang/String;
       101: invokevirtual #430                // Method scala/reflect/api/Names$TermNameExtractor.apply:(Ljava/lang/String;)Lscala/reflect/api/Names$TermNameApi;
       104: astore        5
       106: aload_3
       107: invokevirtual #433                // Method scala/collection/immutable/List.isEmpty:()Z
       110: ifeq          853
       113: aload_2
       114: astore        6
       116: new           #288                // class scala/collection/immutable/$colon$colon
       119: dup
       120: aload_0
       121: invokevirtual #191                // Method c:()Lscala/reflect/macros/blackbox/Context;
       124: invokeinterface #197,  1          // InterfaceMethod scala/reflect/macros/blackbox/Context.universe:()Lscala/reflect/macros/Universe;
       129: invokevirtual #278                // Method scala/reflect/macros/Universe.internal:()Lscala/reflect/api/Internals$InternalApi;
       132: invokeinterface #282,  1          // InterfaceMethod scala/reflect/api/Internals$InternalApi.reificationSupport:()Lscala/reflect/api/Internals$ReificationSupportApi;
       137: invokeinterface #437,  1          // InterfaceMethod scala/reflect/api/Internals$ReificationSupportApi.SyntacticValDef:()Lscala/reflect/api/Internals$ReificationSupportApi$SyntacticValDefExtractor;
       142: aload_0
       143: invokevirtual #191                // Method c:()Lscala/reflect/macros/blackbox/Context;
       146: invokeinterface #197,  1          // InterfaceMethod scala/reflect/macros/blackbox/Context.universe:()Lscala/reflect/macros/Universe;
       151: invokevirtual #441                // Method scala/reflect/macros/Universe.Modifiers:()Lscala/reflect/api/Trees$ModifiersExtractor;
       154: aload_0
       155: invokevirtual #191                // Method c:()Lscala/reflect/macros/blackbox/Context;
       158: invokeinterface #197,  1          // InterfaceMethod scala/reflect/macros/blackbox/Context.universe:()Lscala/reflect/macros/Universe;
       163: invokevirtual #278                // Method scala/reflect/macros/Universe.internal:()Lscala/reflect/api/Internals$InternalApi;
       166: invokeinterface #282,  1          // InterfaceMethod scala/reflect/api/Internals$InternalApi.reificationSupport:()Lscala/reflect/api/Internals$ReificationSupportApi;
       171: invokeinterface #445,  1          // InterfaceMethod scala/reflect/api/Internals$ReificationSupportApi.FlagsRepr:()Lscala/reflect/api/Internals$ReificationSupportApi$FlagsReprExtractor;
       176: ldc2_w        #446                // long 512l
       179: invokeinterface #450,  3          // InterfaceMethod scala/reflect/api/Internals$ReificationSupportApi$FlagsReprExtractor.apply:(J)Ljava/lang/Object;
       184: aload_0
       185: invokevirtual #191                // Method c:()Lscala/reflect/macros/blackbox/Context;
       188: invokeinterface #197,  1          // InterfaceMethod scala/reflect/macros/blackbox/Context.universe:()Lscala/reflect/macros/Universe;
       193: invokevirtual #316                // Method scala/reflect/macros/Universe.TypeName:()Lscala/reflect/api/Names$TypeNameExtractor;
       196: ldc_w         #452                // String
       199: invokevirtual #322                // Method scala/reflect/api/Names$TypeNameExtractor.apply:(Ljava/lang/String;)Lscala/reflect/api/Names$TypeNameApi;
       202: checkcast     #91                 // class scala/reflect/api/Names$NameApi
       205: getstatic     #308                // Field scala/collection/immutable/Nil$.MODULE$:Lscala/collection/immutable/Nil$;
       208: invokevirtual #455                // Method scala/reflect/api/Trees$ModifiersExtractor.apply:(Ljava/lang/Object;Lscala/reflect/api/Names$NameApi;Lscala/collection/immutable/List;)Lscala/reflect/api/Trees$ModifiersApi;
       211: aload         4
       213: aload_0
       214: invokevirtual #191                // Method c:()Lscala/reflect/macros/blackbox/Context;
       217: invokeinterface #197,  1          // InterfaceMethod scala/reflect/macros/blackbox/Context.universe:()Lscala/reflect/macros/Universe;
       222: invokevirtual #278                // Method scala/reflect/macros/Universe.internal:()Lscala/reflect/api/Internals$InternalApi;
       225: invokeinterface #282,  1          // InterfaceMethod scala/reflect/api/Internals$InternalApi.reificationSupport:()Lscala/reflect/api/Internals$ReificationSupportApi;
       230: invokeinterface #459,  1          // InterfaceMethod scala/reflect/api/Internals$ReificationSupportApi.SyntacticAppliedType:()Lscala/reflect/api/Internals$ReificationSupportApi$SyntacticTypeAppliedExtractor;
       235: aload_0
       236: invokevirtual #191                // Method c:()Lscala/reflect/macros/blackbox/Context;
       239: invokeinterface #197,  1          // InterfaceMethod scala/reflect/macros/blackbox/Context.universe:()Lscala/reflect/macros/Universe;
       244: invokevirtual #278                // Method scala/reflect/macros/Universe.internal:()Lscala/reflect/api/Internals$InternalApi;
       247: invokeinterface #282,  1          // InterfaceMethod scala/reflect/api/Internals$InternalApi.reificationSupport:()Lscala/reflect/api/Internals$ReificationSupportApi;
       252: aload_0
       253: invokevirtual #191                // Method c:()Lscala/reflect/macros/blackbox/Context;
       256: invokeinterface #197,  1          // InterfaceMethod scala/reflect/macros/blackbox/Context.universe:()Lscala/reflect/macros/Universe;
       261: invokevirtual #463                // Method scala/reflect/macros/Universe.EmptyTree:()Lscala/reflect/api/Trees$TreeApi;
       264: aload_0
       265: getfield      #465                // Field DecoderClass:Lscala/reflect/api/Symbols$TypeSymbolApi;
       268: invokeinterface #469,  3          // InterfaceMethod scala/reflect/api/Internals$ReificationSupportApi.mkRefTree:(Lscala/reflect/api/Trees$TreeApi;Lscala/reflect/api/Symbols$SymbolApi;)Lscala/reflect/api/Trees$TreeApi;
       273: new           #288                // class scala/collection/immutable/$colon$colon
       276: dup
       277: aload_0
       278: invokevirtual #191                // Method c:()Lscala/reflect/macros/blackbox/Context;
       281: invokeinterface #197,  1          // InterfaceMethod scala/reflect/macros/blackbox/Context.universe:()Lscala/reflect/macros/Universe;
       286: invokevirtual #278                // Method scala/reflect/macros/Universe.internal:()Lscala/reflect/api/Internals$InternalApi;
       289: invokeinterface #282,  1          // InterfaceMethod scala/reflect/api/Internals$InternalApi.reificationSupport:()Lscala/reflect/api/Internals$ReificationSupportApi;
       294: invokeinterface #473,  1          // InterfaceMethod scala/reflect/api/Internals$ReificationSupportApi.SyntacticTypeIdent:()Lscala/reflect/api/Internals$ReificationSupportApi$SyntacticTypeIdentExtractor;
       299: aload         6
       301: invokeinterface #476,  2          // InterfaceMethod scala/reflect/api/Internals$ReificationSupportApi$SyntacticTypeIdentExtractor.apply:(Lscala/reflect/api/Names$TypeNameApi;)Lscala/reflect/api/Trees$IdentApi;
       306: getstatic     #308                // Field scala/collection/immutable/Nil$.MODULE$:Lscala/collection/immutable/Nil$;
       309: invokespecial #328                // Method scala/collection/immutable/$colon$colon."<init>":(Ljava/lang/Object;Lscala/collection/immutable/List;)V
       312: checkcast     #221                // class scala/collection/immutable/List
       315: invokeinterface #479,  3          // InterfaceMethod scala/reflect/api/Internals$ReificationSupportApi$SyntacticTypeAppliedExtractor.apply:(Lscala/reflect/api/Trees$TreeApi;Lscala/collection/immutable/List;)Lscala/reflect/api/Trees$TreeApi;
       320: aload_0
       321: invokevirtual #191                // Method c:()Lscala/reflect/macros/blackbox/Context;
       324: invokeinterface #197,  1          // InterfaceMethod scala/reflect/macros/blackbox/Context.universe:()Lscala/reflect/macros/Universe;
       329: invokevirtual #278                // Method scala/reflect/macros/Universe.internal:()Lscala/reflect/api/Internals$InternalApi;
       332: invokeinterface #282,  1          // InterfaceMethod scala/reflect/api/Internals$InternalApi.reificationSupport:()Lscala/reflect/api/Internals$ReificationSupportApi;
       337: invokeinterface #483,  1          // InterfaceMethod scala/reflect/api/Internals$ReificationSupportApi.SyntacticSelectTerm:()Lscala/reflect/api/Internals$ReificationSupportApi$SyntacticSelectTermExtractor;
       342: aload_0
       343: invokevirtual #191                // Method c:()Lscala/reflect/macros/blackbox/Context;
       346: invokeinterface #197,  1          // InterfaceMethod scala/reflect/macros/blackbox/Context.universe:()Lscala/reflect/macros/Universe;
       351: invokevirtual #278                // Method scala/reflect/macros/Universe.internal:()Lscala/reflect/api/Internals$InternalApi;
       354: invokeinterface #282,  1          // InterfaceMethod scala/reflect/api/Internals$InternalApi.reificationSupport:()Lscala/reflect/api/Internals$ReificationSupportApi;
       359: invokeinterface #486,  1          // InterfaceMethod scala/reflect/api/Internals$ReificationSupportApi.SyntacticTypeApplied:()Lscala/reflect/api/Internals$ReificationSupportApi$SyntacticTypeAppliedExtractor;
       364: aload_0
       365: invokevirtual #191                // Method c:()Lscala/reflect/macros/blackbox/Context;
       368: invokeinterface #197,  1          // InterfaceMethod scala/reflect/macros/blackbox/Context.universe:()Lscala/reflect/macros/Universe;
       373: invokevirtual #278                // Method scala/reflect/macros/Universe.internal:()Lscala/reflect/api/Internals$InternalApi;
       376: invokeinterface #282,  1          // InterfaceMethod scala/reflect/api/Internals$InternalApi.reificationSupport:()Lscala/reflect/api/Internals$ReificationSupportApi;
       381: aload_0
       382: invokevirtual #191                // Method c:()Lscala/reflect/macros/blackbox/Context;
       385: invokeinterface #197,  1          // InterfaceMethod scala/reflect/macros/blackbox/Context.universe:()Lscala/reflect/macros/Universe;
       390: invokevirtual #463                // Method scala/reflect/macros/Universe.EmptyTree:()Lscala/reflect/api/Trees$TreeApi;
       393: aload_0
       394: getfield      #488                // Field mkDecodeJson:Lscala/reflect/api/Symbols$SymbolApi;
       397: invokeinterface #469,  3          // InterfaceMethod scala/reflect/api/Internals$ReificationSupportApi.mkRefTree:(Lscala/reflect/api/Trees$TreeApi;Lscala/reflect/api/Symbols$SymbolApi;)Lscala/reflect/api/Trees$TreeApi;
       402: new           #288                // class scala/collection/immutable/$colon$colon
       405: dup
       406: aload_0
       407: invokevirtual #191                // Method c:()Lscala/reflect/macros/blackbox/Context;
       410: invokeinterface #197,  1          // InterfaceMethod scala/reflect/macros/blackbox/Context.universe:()Lscala/reflect/macros/Universe;
       415: invokevirtual #278                // Method scala/reflect/macros/Universe.internal:()Lscala/reflect/api/Internals$InternalApi;
       418: invokeinterface #282,  1          // InterfaceMethod scala/reflect/api/Internals$InternalApi.reificationSupport:()Lscala/reflect/api/Internals$ReificationSupportApi;
       423: invokeinterface #473,  1          // InterfaceMethod scala/reflect/api/Internals$ReificationSupportApi.SyntacticTypeIdent:()Lscala/reflect/api/Internals$ReificationSupportApi$SyntacticTypeIdentExtractor;
       428: aload         6
       430: invokeinterface #476,  2          // InterfaceMethod scala/reflect/api/Internals$ReificationSupportApi$SyntacticTypeIdentExtractor.apply:(Lscala/reflect/api/Names$TypeNameApi;)Lscala/reflect/api/Trees$IdentApi;
       435: getstatic     #308                // Field scala/collection/immutable/Nil$.MODULE$:Lscala/collection/immutable/Nil$;
       438: invokespecial #328                // Method scala/collection/immutable/$colon$colon."<init>":(Ljava/lang/Object;Lscala/collection/immutable/List;)V
       441: checkcast     #221                // class scala/collection/immutable/List
       444: invokeinterface #479,  3          // InterfaceMethod scala/reflect/api/Internals$ReificationSupportApi$SyntacticTypeAppliedExtractor.apply:(Lscala/reflect/api/Trees$TreeApi;Lscala/collection/immutable/List;)Lscala/reflect/api/Trees$TreeApi;
       449: aload_0
       450: invokevirtual #191                // Method c:()Lscala/reflect/macros/blackbox/Context;
       453: invokeinterface #197,  1          // InterfaceMethod scala/reflect/macros/blackbox/Context.universe:()Lscala/reflect/macros/Universe;
       458: invokevirtual #404                // Method scala/reflect/macros/Universe.TermName:()Lscala/reflect/api/Names$TermNameExtractor;
       461: ldc_w         #490                // String decodeJson
       464: invokevirtual #430                // Method scala/reflect/api/Names$TermNameExtractor.apply:(Ljava/lang/String;)Lscala/reflect/api/Names$TermNameApi;
       467: invokeinterface #493,  3          // InterfaceMethod scala/reflect/api/Internals$ReificationSupportApi$SyntacticSelectTermExtractor.apply:(Lscala/reflect/api/Trees$TreeApi;Lscala/reflect/api/Names$TermNameApi;)Lscala/reflect/api/Trees$SelectApi;
       472: invokeinterface #496,  5          // InterfaceMethod scala/reflect/api/Internals$ReificationSupportApi$SyntacticValDefExtractor.apply:(Lscala/reflect/api/Trees$ModifiersApi;Lscala/reflect/api/Names$TermNameApi;Lscala/reflect/api/Trees$TreeApi;Lscala/reflect/api/Trees$TreeApi;)Lscala/reflect/api/Trees$ValDefApi;
       477: new           #288                // class scala/collection/immutable/$colon$colon
       480: dup
       481: aload_0
       482: invokevirtual #191                // Method c:()Lscala/reflect/macros/blackbox/Context;
       485: invokeinterface #197,  1          // InterfaceMethod scala/reflect/macros/blackbox/Context.universe:()Lscala/reflect/macros/Universe;
       490: invokevirtual #278                // Method scala/reflect/macros/Universe.internal:()Lscala/reflect/api/Internals$InternalApi;
       493: invokeinterface #282,  1          // InterfaceMethod scala/reflect/api/Internals$InternalApi.reificationSupport:()Lscala/reflect/api/Internals$ReificationSupportApi;
       498: invokeinterface #437,  1          // InterfaceMethod scala/reflect/api/Internals$ReificationSupportApi.SyntacticValDef:()Lscala/reflect/api/Internals$ReificationSupportApi$SyntacticValDefExtractor;
       503: aload_0
       504: invokevirtual #191                // Method c:()Lscala/reflect/macros/blackbox/Context;
       507: invokeinterface #197,  1          // InterfaceMethod scala/reflect/macros/blackbox/Context.universe:()Lscala/reflect/macros/Universe;
       512: invokevirtual #441                // Method scala/reflect/macros/Universe.Modifiers:()Lscala/reflect/api/Trees$ModifiersExtractor;
       515: aload_0
       516: invokevirtual #191                // Method c:()Lscala/reflect/macros/blackbox/Context;
       519: invokeinterface #197,  1          // InterfaceMethod scala/reflect/macros/blackbox/Context.universe:()Lscala/reflect/macros/Universe;
       524: invokevirtual #278                // Method scala/reflect/macros/Universe.internal:()Lscala/reflect/api/Internals$InternalApi;
       527: invokeinterface #282,  1          // InterfaceMethod scala/reflect/api/Internals$InternalApi.reificationSupport:()Lscala/reflect/api/Internals$ReificationSupportApi;
       532: invokeinterface #445,  1          // InterfaceMethod scala/reflect/api/Internals$ReificationSupportApi.FlagsRepr:()Lscala/reflect/api/Internals$ReificationSupportApi$FlagsReprExtractor;
       537: ldc2_w        #446                // long 512l
       540: invokeinterface #450,  3          // InterfaceMethod scala/reflect/api/Internals$ReificationSupportApi$FlagsReprExtractor.apply:(J)Ljava/lang/Object;
       545: aload_0
       546: invokevirtual #191                // Method c:()Lscala/reflect/macros/blackbox/Context;
       549: invokeinterface #197,  1          // InterfaceMethod scala/reflect/macros/blackbox/Context.universe:()Lscala/reflect/macros/Universe;
       554: invokevirtual #316                // Method scala/reflect/macros/Universe.TypeName:()Lscala/reflect/api/Names$TypeNameExtractor;
       557: ldc_w         #452                // String
       560: invokevirtual #322                // Method scala/reflect/api/Names$TypeNameExtractor.apply:(Ljava/lang/String;)Lscala/reflect/api/Names$TypeNameApi;
       563: checkcast     #91                 // class scala/reflect/api/Names$NameApi
       566: getstatic     #308                // Field scala/collection/immutable/Nil$.MODULE$:Lscala/collection/immutable/Nil$;
       569: invokevirtual #455                // Method scala/reflect/api/Trees$ModifiersExtractor.apply:(Ljava/lang/Object;Lscala/reflect/api/Names$NameApi;Lscala/collection/immutable/List;)Lscala/reflect/api/Trees$ModifiersApi;
       572: aload         5
       574: aload_0
       575: invokevirtual #191                // Method c:()Lscala/reflect/macros/blackbox/Context;
       578: invokeinterface #197,  1          // InterfaceMethod scala/reflect/macros/blackbox/Context.universe:()Lscala/reflect/macros/Universe;
       583: invokevirtual #278                // Method scala/reflect/macros/Universe.internal:()Lscala/reflect/api/Internals$InternalApi;
       586: invokeinterface #282,  1          // InterfaceMethod scala/reflect/api/Internals$InternalApi.reificationSupport:()Lscala/reflect/api/Internals$ReificationSupportApi;
       591: invokeinterface #459,  1          // InterfaceMethod scala/reflect/api/Internals$ReificationSupportApi.SyntacticAppliedType:()Lscala/reflect/api/Internals$ReificationSupportApi$SyntacticTypeAppliedExtractor;
       596: aload_0
       597: invokevirtual #191                // Method c:()Lscala/reflect/macros/blackbox/Context;
       600: invokeinterface #197,  1          // InterfaceMethod scala/reflect/macros/blackbox/Context.universe:()Lscala/reflect/macros/Universe;
       605: invokevirtual #278                // Method scala/reflect/macros/Universe.internal:()Lscala/reflect/api/Internals$InternalApi;
       608: invokeinterface #282,  1          // InterfaceMethod scala/reflect/api/Internals$InternalApi.reificationSupport:()Lscala/reflect/api/Internals$ReificationSupportApi;
       613: aload_0
       614: invokevirtual #191                // Method c:()Lscala/reflect/macros/blackbox/Context;
       617: invokeinterface #197,  1          // InterfaceMethod scala/reflect/macros/blackbox/Context.universe:()Lscala/reflect/macros/Universe;
       622: invokevirtual #463                // Method scala/reflect/macros/Universe.EmptyTree:()Lscala/reflect/api/Trees$TreeApi;
       625: aload_0
       626: getfield      #498                // Field EncoderClass:Lscala/reflect/api/Symbols$TypeSymbolApi;
       629: invokeinterface #469,  3          // InterfaceMethod scala/reflect/api/Internals$ReificationSupportApi.mkRefTree:(Lscala/reflect/api/Trees$TreeApi;Lscala/reflect/api/Symbols$SymbolApi;)Lscala/reflect/api/Trees$TreeApi;
       634: new           #288                // class scala/collection/immutable/$colon$colon
       637: dup
       638: aload_0
       639: invokevirtual #191                // Method c:()Lscala/reflect/macros/blackbox/Context;
       642: invokeinterface #197,  1          // InterfaceMethod scala/reflect/macros/blackbox/Context.universe:()Lscala/reflect/macros/Universe;
       647: invokevirtual #278                // Method scala/reflect/macros/Universe.internal:()Lscala/reflect/api/Internals$InternalApi;
       650: invokeinterface #282,  1          // InterfaceMethod scala/reflect/api/Internals$InternalApi.reificationSupport:()Lscala/reflect/api/Internals$ReificationSupportApi;
       655: invokeinterface #473,  1          // InterfaceMethod scala/reflect/api/Internals$ReificationSupportApi.SyntacticTypeIdent:()Lscala/reflect/api/Internals$ReificationSupportApi$SyntacticTypeIdentExtractor;
       660: aload         6
       662: invokeinterface #476,  2          // InterfaceMethod scala/reflect/api/Internals$ReificationSupportApi$SyntacticTypeIdentExtractor.apply:(Lscala/reflect/api/Names$TypeNameApi;)Lscala/reflect/api/Trees$IdentApi;
       667: getstatic     #308                // Field scala/collection/immutable/Nil$.MODULE$:Lscala/collection/immutable/Nil$;
       670: invokespecial #328                // Method scala/collection/immutable/$colon$colon."<init>":(Ljava/lang/Object;Lscala/collection/immutable/List;)V
       673: checkcast     #221                // class scala/collection/immutable/List
       676: invokeinterface #479,  3          // InterfaceMethod scala/reflect/api/Internals$ReificationSupportApi$SyntacticTypeAppliedExtractor.apply:(Lscala/reflect/api/Trees$TreeApi;Lscala/collection/immutable/List;)Lscala/reflect/api/Trees$TreeApi;
       681: aload_0
       682: invokevirtual #191                // Method c:()Lscala/reflect/macros/blackbox/Context;
       685: invokeinterface #197,  1          // InterfaceMethod scala/reflect/macros/blackbox/Context.universe:()Lscala/reflect/macros/Universe;
       690: invokevirtual #278                // Method scala/reflect/macros/Universe.internal:()Lscala/reflect/api/Internals$InternalApi;
       693: invokeinterface #282,  1          // InterfaceMethod scala/reflect/api/Internals$InternalApi.reificationSupport:()Lscala/reflect/api/Internals$ReificationSupportApi;
       698: invokeinterface #483,  1          // InterfaceMethod scala/reflect/api/Internals$ReificationSupportApi.SyntacticSelectTerm:()Lscala/reflect/api/Internals$ReificationSupportApi$SyntacticSelectTermExtractor;
       703: aload_0
       704: invokevirtual #191                // Method c:()Lscala/reflect/macros/blackbox/Context;
       707: invokeinterface #197,  1          // InterfaceMethod scala/reflect/macros/blackbox/Context.universe:()Lscala/reflect/macros/Universe;
       712: invokevirtual #278                // Method scala/reflect/macros/Universe.internal:()Lscala/reflect/api/Internals$InternalApi;
       715: invokeinterface #282,  1          // InterfaceMethod scala/reflect/api/Internals$InternalApi.reificationSupport:()Lscala/reflect/api/Internals$ReificationSupportApi;
       720: invokeinterface #486,  1          // InterfaceMethod scala/reflect/api/Internals$ReificationSupportApi.SyntacticTypeApplied:()Lscala/reflect/api/Internals$ReificationSupportApi$SyntacticTypeAppliedExtractor;
       725: aload_0
       726: invokevirtual #191                // Method c:()Lscala/reflect/macros/blackbox/Context;
       729: invokeinterface #197,  1          // InterfaceMethod scala/reflect/macros/blackbox/Context.universe:()Lscala/reflect/macros/Universe;
       734: invokevirtual #278                // Method scala/reflect/macros/Universe.internal:()Lscala/reflect/api/Internals$InternalApi;
       737: invokeinterface #282,  1          // InterfaceMethod scala/reflect/api/Internals$InternalApi.reificationSupport:()Lscala/reflect/api/Internals$ReificationSupportApi;
       742: aload_0
       743: invokevirtual #191                // Method c:()Lscala/reflect/macros/blackbox/Context;
       746: invokeinterface #197,  1          // InterfaceMethod scala/reflect/macros/blackbox/Context.universe:()Lscala/reflect/macros/Universe;
       751: invokevirtual #463                // Method scala/reflect/macros/Universe.EmptyTree:()Lscala/reflect/api/Trees$TreeApi;
       754: aload_0
       755: getfield      #500                // Field mkEncodeJson:Lscala/reflect/api/Symbols$SymbolApi;
       758: invokeinterface #469,  3          // InterfaceMethod scala/reflect/api/Internals$ReificationSupportApi.mkRefTree:(Lscala/reflect/api/Trees$TreeApi;Lscala/reflect/api/Symbols$SymbolApi;)Lscala/reflect/api/Trees$TreeApi;
       763: new           #288                // class scala/collection/immutable/$colon$colon
       766: dup
       767: aload_0
       768: invokevirtual #191                // Method c:()Lscala/reflect/macros/blackbox/Context;
       771: invokeinterface #197,  1          // InterfaceMethod scala/reflect/macros/blackbox/Context.universe:()Lscala/reflect/macros/Universe;
       776: invokevirtual #278                // Method scala/reflect/macros/Universe.internal:()Lscala/reflect/api/Internals$InternalApi;
       779: invokeinterface #282,  1          // InterfaceMethod scala/reflect/api/Internals$InternalApi.reificationSupport:()Lscala/reflect/api/Internals$ReificationSupportApi;
       784: invokeinterface #473,  1          // InterfaceMethod scala/reflect/api/Internals$ReificationSupportApi.SyntacticTypeIdent:()Lscala/reflect/api/Internals$ReificationSupportApi$SyntacticTypeIdentExtractor;
       789: aload         6
       791: invokeinterface #476,  2          // InterfaceMethod scala/reflect/api/Internals$ReificationSupportApi$SyntacticTypeIdentExtractor.apply:(Lscala/reflect/api/Names$TypeNameApi;)Lscala/reflect/api/Trees$IdentApi;
       796: getstatic     #308                // Field scala/collection/immutable/Nil$.MODULE$:Lscala/collection/immutable/Nil$;
       799: invokespecial #328                // Method scala/collection/immutable/$colon$colon."<init>":(Ljava/lang/Object;Lscala/collection/immutable/List;)V
       802: checkcast     #221                // class scala/collection/immutable/List
       805: invokeinterface #479,  3          // InterfaceMethod scala/reflect/api/Internals$ReificationSupportApi$SyntacticTypeAppliedExtractor.apply:(Lscala/reflect/api/Trees$TreeApi;Lscala/collection/immutable/List;)Lscala/reflect/api/Trees$TreeApi;
       810: aload_0
       811: invokevirtual #191                // Method c:()Lscala/reflect/macros/blackbox/Context;
       814: invokeinterface #197,  1          // InterfaceMethod scala/reflect/macros/blackbox/Context.universe:()Lscala/reflect/macros/Universe;
       819: invokevirtual #404                // Method scala/reflect/macros/Universe.TermName:()Lscala/reflect/api/Names$TermNameExtractor;
       822: ldc_w         #502                // String encodeJson
       825: invokevirtual #430                // Method scala/reflect/api/Names$TermNameExtractor.apply:(Ljava/lang/String;)Lscala/reflect/api/Names$TermNameApi;
       828: invokeinterface #493,  3          // InterfaceMethod scala/reflect/api/Internals$ReificationSupportApi$SyntacticSelectTermExtractor.apply:(Lscala/reflect/api/Trees$TreeApi;Lscala/reflect/api/Names$TermNameApi;)Lscala/reflect/api/Trees$SelectApi;
       833: invokeinterface #496,  5          // InterfaceMethod scala/reflect/api/Internals$ReificationSupportApi$SyntacticValDefExtractor.apply:(Lscala/reflect/api/Trees$ModifiersApi;Lscala/reflect/api/Names$TermNameApi;Lscala/reflect/api/Trees$TreeApi;Lscala/reflect/api/Trees$TreeApi;)Lscala/reflect/api/Trees$ValDefApi;
       838: getstatic     #308                // Field scala/collection/immutable/Nil$.MODULE$:Lscala/collection/immutable/Nil$;
       841: invokespecial #328                // Method scala/collection/immutable/$colon$colon."<init>":(Ljava/lang/Object;Lscala/collection/immutable/List;)V
       844: invokespecial #328                // Method scala/collection/immutable/$colon$colon."<init>":(Ljava/lang/Object;Lscala/collection/immutable/List;)V
       847: checkcast     #221                // class scala/collection/immutable/List
       850: goto          1648
       853: aload_3
       854: invokedynamic #522,  0            // InvokeDynamic #0:apply:()Lscala/Function1;
       859: invokevirtual #526                // Method scala/collection/immutable/List.map:(Lscala/Function1;)Lscala/collection/immutable/List;
       862: astore        7
       864: aload_0
       865: aload_0
       866: getfield      #465                // Field DecoderClass:Lscala/reflect/api/Symbols$TypeSymbolApi;
       869: aload         7
       871: invokespecial #530                // Method mkImplicitParams$1:(Lscala/reflect/api/Symbols$TypeSymbolApi;Lscala/collection/immutable/List;)Lscala/collection/immutable/List;
       874: astore        8
       876: aload_0
       877: aload_0
       878: getfield      #498                // Field EncoderClass:Lscala/reflect/api/Symbols$TypeSymbolApi;
       881: aload         7
       883: invokespecial #530                // Method mkImplicitParams$1:(Lscala/reflect/api/Symbols$TypeSymbolApi;Lscala/collection/immutable/List;)Lscala/collection/immutable/List;
       886: astore        9
       888: aload_0
       889: invokevirtual #191                // Method c:()Lscala/reflect/macros/blackbox/Context;
       892: invokeinterface #197,  1          // InterfaceMethod scala/reflect/macros/blackbox/Context.universe:()Lscala/reflect/macros/Universe;
       897: invokevirtual #278                // Method scala/reflect/macros/Universe.internal:()Lscala/reflect/api/Internals$InternalApi;
       900: invokeinterface #282,  1          // InterfaceMethod scala/reflect/api/Internals$InternalApi.reificationSupport:()Lscala/reflect/api/Internals$ReificationSupportApi;
       905: invokeinterface #459,  1          // InterfaceMethod scala/reflect/api/Internals$ReificationSupportApi.SyntacticAppliedType:()Lscala/reflect/api/Internals$ReificationSupportApi$SyntacticTypeAppliedExtractor;
       910: aload_0
       911: invokevirtual #191                // Method c:()Lscala/reflect/macros/blackbox/Context;
       914: invokeinterface #197,  1          // InterfaceMethod scala/reflect/macros/blackbox/Context.universe:()Lscala/reflect/macros/Universe;
       919: invokevirtual #278                // Method scala/reflect/macros/Universe.internal:()Lscala/reflect/api/Internals$InternalApi;
       922: invokeinterface #282,  1          // InterfaceMethod scala/reflect/api/Internals$InternalApi.reificationSupport:()Lscala/reflect/api/Internals$ReificationSupportApi;
       927: invokeinterface #473,  1          // InterfaceMethod scala/reflect/api/Internals$ReificationSupportApi.SyntacticTypeIdent:()Lscala/reflect/api/Internals$ReificationSupportApi$SyntacticTypeIdentExtractor;
       932: aload_2
       933: invokeinterface #476,  2          // InterfaceMethod scala/reflect/api/Internals$ReificationSupportApi$SyntacticTypeIdentExtractor.apply:(Lscala/reflect/api/Names$TypeNameApi;)Lscala/reflect/api/Trees$IdentApi;
       938: aload         7
       940: aload_0
       941: invokedynamic #540,  0            // InvokeDynamic #1:apply:(Largonaut/derive/JsonCodecMacros;)Lscala/Function1;
       946: invokevirtual #526                // Method scala/collection/immutable/List.map:(Lscala/Function1;)Lscala/collection/immutable/List;
       949: invokeinterface #479,  3          // InterfaceMethod scala/reflect/api/Internals$ReificationSupportApi$SyntacticTypeAppliedExtractor.apply:(Lscala/reflect/api/Trees$TreeApi;Lscala/collection/immutable/List;)Lscala/reflect/api/Trees$TreeApi;
       954: astore        10
       956: new           #288                // class scala/collection/immutable/$colon$colon
       959: dup
       960: aload_0
       961: invokevirtual #191                // Method c:()Lscala/reflect/macros/blackbox/Context;
       964: invokeinterface #197,  1          // InterfaceMethod scala/reflect/macros/blackbox/Context.universe:()Lscala/reflect/macros/Universe;
       969: invokevirtual #278                // Method scala/reflect/macros/Universe.internal:()Lscala/reflect/api/Internals$InternalApi;
       972: invokeinterface #282,  1          // InterfaceMethod scala/reflect/api/Internals$InternalApi.reificationSupport:()Lscala/reflect/api/Internals$ReificationSupportApi;
       977: invokeinterface #544,  1          // InterfaceMethod scala/reflect/api/Internals$ReificationSupportApi.SyntacticDefDef:()Lscala/reflect/api/Internals$ReificationSupportApi$SyntacticDefDefExtractor;
       982: aload_0
       983: invokevirtual #191                // Method c:()Lscala/reflect/macros/blackbox/Context;
       986: invokeinterface #197,  1          // InterfaceMethod scala/reflect/macros/blackbox/Context.universe:()Lscala/reflect/macros/Universe;
       991: invokevirtual #441                // Method scala/reflect/macros/Universe.Modifiers:()Lscala/reflect/api/Trees$ModifiersExtractor;
       994: aload_0
       995: invokevirtual #191                // Method c:()Lscala/reflect/macros/blackbox/Context;
       998: invokeinterface #197,  1          // InterfaceMethod scala/reflect/macros/blackbox/Context.universe:()Lscala/reflect/macros/Universe;
      1003: invokevirtual #278                // Method scala/reflect/macros/Universe.internal:()Lscala/reflect/api/Internals$InternalApi;
      1006: invokeinterface #282,  1          // InterfaceMethod scala/reflect/api/Internals$InternalApi.reificationSupport:()Lscala/reflect/api/Internals$ReificationSupportApi;
      1011: invokeinterface #445,  1          // InterfaceMethod scala/reflect/api/Internals$ReificationSupportApi.FlagsRepr:()Lscala/reflect/api/Internals$ReificationSupportApi$FlagsReprExtractor;
      1016: ldc2_w        #446                // long 512l
      1019: invokeinterface #450,  3          // InterfaceMethod scala/reflect/api/Internals$ReificationSupportApi$FlagsReprExtractor.apply:(J)Ljava/lang/Object;
      1024: aload_0
      1025: invokevirtual #191                // Method c:()Lscala/reflect/macros/blackbox/Context;
      1028: invokeinterface #197,  1          // InterfaceMethod scala/reflect/macros/blackbox/Context.universe:()Lscala/reflect/macros/Universe;
      1033: invokevirtual #316                // Method scala/reflect/macros/Universe.TypeName:()Lscala/reflect/api/Names$TypeNameExtractor;
      1036: ldc_w         #452                // String
      1039: invokevirtual #322                // Method scala/reflect/api/Names$TypeNameExtractor.apply:(Ljava/lang/String;)Lscala/reflect/api/Names$TypeNameApi;
      1042: checkcast     #91                 // class scala/reflect/api/Names$NameApi
      1045: getstatic     #308                // Field scala/collection/immutable/Nil$.MODULE$:Lscala/collection/immutable/Nil$;
      1048: invokevirtual #455                // Method scala/reflect/api/Trees$ModifiersExtractor.apply:(Ljava/lang/Object;Lscala/reflect/api/Names$NameApi;Lscala/collection/immutable/List;)Lscala/reflect/api/Trees$ModifiersApi;
      1051: aload         4
      1053: aload_3
      1054: aload_0
      1055: invokevirtual #191                // Method c:()Lscala/reflect/macros/blackbox/Context;
      1058: invokeinterface #197,  1          // InterfaceMethod scala/reflect/macros/blackbox/Context.universe:()Lscala/reflect/macros/Universe;
      1063: invokevirtual #278                // Method scala/reflect/macros/Universe.internal:()Lscala/reflect/api/Internals$InternalApi;
      1066: invokeinterface #282,  1          // InterfaceMethod scala/reflect/api/Internals$InternalApi.reificationSupport:()Lscala/reflect/api/Internals$ReificationSupportApi;
      1071: invokeinterface #548,  1          // InterfaceMethod scala/reflect/api/Internals$ReificationSupportApi.ImplicitParams:()Lscala/reflect/api/Internals$ReificationSupportApi$ImplicitParamsExtractor;
      1076: getstatic     #308                // Field scala/collection/immutable/Nil$.MODULE$:Lscala/collection/immutable/Nil$;
      1079: aload         8
      1081: invokeinterface #551,  3          // InterfaceMethod scala/reflect/api/Internals$ReificationSupportApi$ImplicitParamsExtractor.apply:(Lscala/collection/immutable/List;Lscala/collection/immutable/List;)Lscala/collection/immutable/List;
      1086: aload_0
      1087: invokevirtual #191                // Method c:()Lscala/reflect/macros/blackbox/Context;
      1090: invokeinterface #197,  1          // InterfaceMethod scala/reflect/macros/blackbox/Context.universe:()Lscala/reflect/macros/Universe;
      1095: invokevirtual #278                // Method scala/reflect/macros/Universe.internal:()Lscala/reflect/api/Internals$InternalApi;
      1098: invokeinterface #282,  1          // InterfaceMethod scala/reflect/api/Internals$InternalApi.reificationSupport:()Lscala/reflect/api/Internals$ReificationSupportApi;
      1103: invokeinterface #459,  1          // InterfaceMethod scala/reflect/api/Internals$ReificationSupportApi.SyntacticAppliedType:()Lscala/reflect/api/Internals$ReificationSupportApi$SyntacticTypeAppliedExtractor;
      1108: aload_0
      1109: invokevirtual #191                // Method c:()Lscala/reflect/macros/blackbox/Context;
      1112: invokeinterface #197,  1          // InterfaceMethod scala/reflect/macros/blackbox/Context.universe:()Lscala/reflect/macros/Universe;
      1117: invokevirtual #278                // Method scala/reflect/macros/Universe.internal:()Lscala/reflect/api/Internals$InternalApi;
      1120: invokeinterface #282,  1          // InterfaceMethod scala/reflect/api/Internals$InternalApi.reificationSupport:()Lscala/reflect/api/Internals$ReificationSupportApi;
      1125: aload_0
      1126: invokevirtual #191                // Method c:()Lscala/reflect/macros/blackbox/Context;
      1129: invokeinterface #197,  1          // InterfaceMethod scala/reflect/macros/blackbox/Context.universe:()Lscala/reflect/macros/Universe;
      1134: invokevirtual #463                // Method scala/reflect/macros/Universe.EmptyTree:()Lscala/reflect/api/Trees$TreeApi;
      1137: aload_0
      1138: getfield      #465                // Field DecoderClass:Lscala/reflect/api/Symbols$TypeSymbolApi;
      1141: invokeinterface #469,  3          // InterfaceMethod scala/reflect/api/Internals$ReificationSupportApi.mkRefTree:(Lscala/reflect/api/Trees$TreeApi;Lscala/reflect/api/Symbols$SymbolApi;)Lscala/reflect/api/Trees$TreeApi;
      1146: new           #288                // class scala/collection/immutable/$colon$colon
      1149: dup
      1150: aload         10
      1152: getstatic     #308                // Field scala/collection/immutable/Nil$.MODULE$:Lscala/collection/immutable/Nil$;
      1155: invokespecial #328                // Method scala/collection/immutable/$colon$colon."<init>":(Ljava/lang/Object;Lscala/collection/immutable/List;)V
      1158: checkcast     #221                // class scala/collection/immutable/List
      1161: invokeinterface #479,  3          // InterfaceMethod scala/reflect/api/Internals$ReificationSupportApi$SyntacticTypeAppliedExtractor.apply:(Lscala/reflect/api/Trees$TreeApi;Lscala/collection/immutable/List;)Lscala/reflect/api/Trees$TreeApi;
      1166: aload_0
      1167: invokevirtual #191                // Method c:()Lscala/reflect/macros/blackbox/Context;
      1170: invokeinterface #197,  1          // InterfaceMethod scala/reflect/macros/blackbox/Context.universe:()Lscala/reflect/macros/Universe;
      1175: invokevirtual #278                // Method scala/reflect/macros/Universe.internal:()Lscala/reflect/api/Internals$InternalApi;
      1178: invokeinterface #282,  1          // InterfaceMethod scala/reflect/api/Internals$InternalApi.reificationSupport:()Lscala/reflect/api/Internals$ReificationSupportApi;
      1183: invokeinterface #483,  1          // InterfaceMethod scala/reflect/api/Internals$ReificationSupportApi.SyntacticSelectTerm:()Lscala/reflect/api/Internals$ReificationSupportApi$SyntacticSelectTermExtractor;
      1188: aload_0
      1189: invokevirtual #191                // Method c:()Lscala/reflect/macros/blackbox/Context;
      1192: invokeinterface #197,  1          // InterfaceMethod scala/reflect/macros/blackbox/Context.universe:()Lscala/reflect/macros/Universe;
      1197: invokevirtual #278                // Method scala/reflect/macros/Universe.internal:()Lscala/reflect/api/Internals$InternalApi;
      1200: invokeinterface #282,  1          // InterfaceMethod scala/reflect/api/Internals$InternalApi.reificationSupport:()Lscala/reflect/api/Internals$ReificationSupportApi;
      1205: invokeinterface #486,  1          // InterfaceMethod scala/reflect/api/Internals$ReificationSupportApi.SyntacticTypeApplied:()Lscala/reflect/api/Internals$ReificationSupportApi$SyntacticTypeAppliedExtractor;
      1210: aload_0
      1211: invokevirtual #191                // Method c:()Lscala/reflect/macros/blackbox/Context;
      1214: invokeinterface #197,  1          // InterfaceMethod scala/reflect/macros/blackbox/Context.universe:()Lscala/reflect/macros/Universe;
      1219: invokevirtual #278                // Method scala/reflect/macros/Universe.internal:()Lscala/reflect/api/Internals$InternalApi;
      1222: invokeinterface #282,  1          // InterfaceMethod scala/reflect/api/Internals$InternalApi.reificationSupport:()Lscala/reflect/api/Internals$ReificationSupportApi;
      1227: aload_0
      1228: invokevirtual #191                // Method c:()Lscala/reflect/macros/blackbox/Context;
      1231: invokeinterface #197,  1          // InterfaceMethod scala/reflect/macros/blackbox/Context.universe:()Lscala/reflect/macros/Universe;
      1236: invokevirtual #463                // Method scala/reflect/macros/Universe.EmptyTree:()Lscala/reflect/api/Trees$TreeApi;
      1239: aload_0
      1240: getfield      #488                // Field mkDecodeJson:Lscala/reflect/api/Symbols$SymbolApi;
      1243: invokeinterface #469,  3          // InterfaceMethod scala/reflect/api/Internals$ReificationSupportApi.mkRefTree:(Lscala/reflect/api/Trees$TreeApi;Lscala/reflect/api/Symbols$SymbolApi;)Lscala/reflect/api/Trees$TreeApi;
      1248: new           #288                // class scala/collection/immutable/$colon$colon
      1251: dup
      1252: aload         10
      1254: getstatic     #308                // Field scala/collection/immutable/Nil$.MODULE$:Lscala/collection/immutable/Nil$;
      1257: invokespecial #328                // Method scala/collection/immutable/$colon$colon."<init>":(Ljava/lang/Object;Lscala/collection/immutable/List;)V
      1260: checkcast     #221                // class scala/collection/immutable/List
      1263: invokeinterface #479,  3          // InterfaceMethod scala/reflect/api/Internals$ReificationSupportApi$SyntacticTypeAppliedExtractor.apply:(Lscala/reflect/api/Trees$TreeApi;Lscala/collection/immutable/List;)Lscala/reflect/api/Trees$TreeApi;
      1268: aload_0
      1269: invokevirtual #191                // Method c:()Lscala/reflect/macros/blackbox/Context;
      1272: invokeinterface #197,  1          // InterfaceMethod scala/reflect/macros/blackbox/Context.universe:()Lscala/reflect/macros/Universe;
      1277: invokevirtual #404                // Method scala/reflect/macros/Universe.TermName:()Lscala/reflect/api/Names$TermNameExtractor;
      1280: ldc_w         #490                // String decodeJson
      1283: invokevirtual #430                // Method scala/reflect/api/Names$TermNameExtractor.apply:(Ljava/lang/String;)Lscala/reflect/api/Names$TermNameApi;
      1286: invokeinterface #493,  3          // InterfaceMethod scala/reflect/api/Internals$ReificationSupportApi$SyntacticSelectTermExtractor.apply:(Lscala/reflect/api/Trees$TreeApi;Lscala/reflect/api/Names$TermNameApi;)Lscala/reflect/api/Trees$SelectApi;
      1291: invokeinterface #554,  7          // InterfaceMethod scala/reflect/api/Internals$ReificationSupportApi$SyntacticDefDefExtractor.apply:(Lscala/reflect/api/Trees$ModifiersApi;Lscala/reflect/api/Names$TermNameApi;Lscala/collection/immutable/List;Lscala/collection/immutable/List;Lscala/reflect/api/Trees$TreeApi;Lscala/reflect/api/Trees$TreeApi;)Lscala/reflect/api/Trees$DefDefApi;
      1296: new           #288                // class scala/collection/immutable/$colon$colon
      1299: dup
      1300: aload_0
      1301: invokevirtual #191                // Method c:()Lscala/reflect/macros/blackbox/Context;
      1304: invokeinterface #197,  1          // InterfaceMethod scala/reflect/macros/blackbox/Context.universe:()Lscala/reflect/macros/Universe;
      1309: invokevirtual #278                // Method scala/reflect/macros/Universe.internal:()Lscala/reflect/api/Internals$InternalApi;
      1312: invokeinterface #282,  1          // InterfaceMethod scala/reflect/api/Internals$InternalApi.reificationSupport:()Lscala/reflect/api/Internals$ReificationSupportApi;
      1317: invokeinterface #544,  1          // InterfaceMethod scala/reflect/api/Internals$ReificationSupportApi.SyntacticDefDef:()Lscala/reflect/api/Internals$ReificationSupportApi$SyntacticDefDefExtractor;
      1322: aload_0
      1323: invokevirtual #191                // Method c:()Lscala/reflect/macros/blackbox/Context;
      1326: invokeinterface #197,  1          // InterfaceMethod scala/reflect/macros/blackbox/Context.universe:()Lscala/reflect/macros/Universe;
      1331: invokevirtual #441                // Method scala/reflect/macros/Universe.Modifiers:()Lscala/reflect/api/Trees$ModifiersExtractor;
      1334: aload_0
      1335: invokevirtual #191                // Method c:()Lscala/reflect/macros/blackbox/Context;
      1338: invokeinterface #197,  1          // InterfaceMethod scala/reflect/macros/blackbox/Context.universe:()Lscala/reflect/macros/Universe;
      1343: invokevirtual #278                // Method scala/reflect/macros/Universe.internal:()Lscala/reflect/api/Internals$InternalApi;
      1346: invokeinterface #282,  1          // InterfaceMethod scala/reflect/api/Internals$InternalApi.reificationSupport:()Lscala/reflect/api/Internals$ReificationSupportApi;
      1351: invokeinterface #445,  1          // InterfaceMethod scala/reflect/api/Internals$ReificationSupportApi.FlagsRepr:()Lscala/reflect/api/Internals$ReificationSupportApi$FlagsReprExtractor;
      1356: ldc2_w        #446                // long 512l
      1359: invokeinterface #450,  3          // InterfaceMethod scala/reflect/api/Internals$ReificationSupportApi$FlagsReprExtractor.apply:(J)Ljava/lang/Object;
      1364: aload_0
      1365: invokevirtual #191                // Method c:()Lscala/reflect/macros/blackbox/Context;
      1368: invokeinterface #197,  1          // InterfaceMethod scala/reflect/macros/blackbox/Context.universe:()Lscala/reflect/macros/Universe;
      1373: invokevirtual #316                // Method scala/reflect/macros/Universe.TypeName:()Lscala/reflect/api/Names$TypeNameExtractor;
      1376: ldc_w         #452                // String
      1379: invokevirtual #322                // Method scala/reflect/api/Names$TypeNameExtractor.apply:(Ljava/lang/String;)Lscala/reflect/api/Names$TypeNameApi;
      1382: checkcast     #91                 // class scala/reflect/api/Names$NameApi
      1385: getstatic     #308                // Field scala/collection/immutable/Nil$.MODULE$:Lscala/collection/immutable/Nil$;
      1388: invokevirtual #455                // Method scala/reflect/api/Trees$ModifiersExtractor.apply:(Ljava/lang/Object;Lscala/reflect/api/Names$NameApi;Lscala/collection/immutable/List;)Lscala/reflect/api/Trees$ModifiersApi;
      1391: aload         5
      1393: aload_3
      1394: aload_0
      1395: invokevirtual #191                // Method c:()Lscala/reflect/macros/blackbox/Context;
      1398: invokeinterface #197,  1          // InterfaceMethod scala/reflect/macros/blackbox/Context.universe:()Lscala/reflect/macros/Universe;
      1403: invokevirtual #278                // Method scala/reflect/macros/Universe.internal:()Lscala/reflect/api/Internals$InternalApi;
      1406: invokeinterface #282,  1          // InterfaceMethod scala/reflect/api/Internals$InternalApi.reificationSupport:()Lscala/reflect/api/Internals$ReificationSupportApi;
      1411: invokeinterface #548,  1          // InterfaceMethod scala/reflect/api/Internals$ReificationSupportApi.ImplicitParams:()Lscala/reflect/api/Internals$ReificationSupportApi$ImplicitParamsExtractor;
      1416: getstatic     #308                // Field scala/collection/immutable/Nil$.MODULE$:Lscala/collection/immutable/Nil$;
      1419: aload         9
      1421: invokeinterface #551,  3          // InterfaceMethod scala/reflect/api/Internals$ReificationSupportApi$ImplicitParamsExtractor.apply:(Lscala/collection/immutable/List;Lscala/collection/immutable/List;)Lscala/collection/immutable/List;
      1426: aload_0
      1427: invokevirtual #191                // Method c:()Lscala/reflect/macros/blackbox/Context;
      1430: invokeinterface #197,  1          // InterfaceMethod scala/reflect/macros/blackbox/Context.universe:()Lscala/reflect/macros/Universe;
      1435: invokevirtual #278                // Method scala/reflect/macros/Universe.internal:()Lscala/reflect/api/Internals$InternalApi;
      1438: invokeinterface #282,  1          // InterfaceMethod scala/reflect/api/Internals$InternalApi.reificationSupport:()Lscala/reflect/api/Internals$ReificationSupportApi;
      1443: invokeinterface #459,  1          // InterfaceMethod scala/reflect/api/Internals$ReificationSupportApi.SyntacticAppliedType:()Lscala/reflect/api/Internals$ReificationSupportApi$SyntacticTypeAppliedExtractor;
      1448: aload_0
      1449: invokevirtual #191                // Method c:()Lscala/reflect/macros/blackbox/Context;
      1452: invokeinterface #197,  1          // InterfaceMethod scala/reflect/macros/blackbox/Context.universe:()Lscala/reflect/macros/Universe;
      1457: invokevirtual #278                // Method scala/reflect/macros/Universe.internal:()Lscala/reflect/api/Internals$InternalApi;
      1460: invokeinterface #282,  1          // InterfaceMethod scala/reflect/api/Internals$InternalApi.reificationSupport:()Lscala/reflect/api/Internals$ReificationSupportApi;
      1465: aload_0
      1466: invokevirtual #191                // Method c:()Lscala/reflect/macros/blackbox/Context;
      1469: invokeinterface #197,  1          // InterfaceMethod scala/reflect/macros/blackbox/Context.universe:()Lscala/reflect/macros/Universe;
      1474: invokevirtual #463                // Method scala/reflect/macros/Universe.EmptyTree:()Lscala/reflect/api/Trees$TreeApi;
      1477: aload_0
      1478: getfield      #498                // Field EncoderClass:Lscala/reflect/api/Symbols$TypeSymbolApi;
      1481: invokeinterface #469,  3          // InterfaceMethod scala/reflect/api/Internals$ReificationSupportApi.mkRefTree:(Lscala/reflect/api/Trees$TreeApi;Lscala/reflect/api/Symbols$SymbolApi;)Lscala/reflect/api/Trees$TreeApi;
      1486: new           #288                // class scala/collection/immutable/$colon$colon
      1489: dup
      1490: aload         10
      1492: getstatic     #308                // Field scala/collection/immutable/Nil$.MODULE$:Lscala/collection/immutable/Nil$;
      1495: invokespecial #328                // Method scala/collection/immutable/$colon$colon."<init>":(Ljava/lang/Object;Lscala/collection/immutable/List;)V
      1498: checkcast     #221                // class scala/collection/immutable/List
      1501: invokeinterface #479,  3          // InterfaceMethod scala/reflect/api/Internals$ReificationSupportApi$SyntacticTypeAppliedExtractor.apply:(Lscala/reflect/api/Trees$TreeApi;Lscala/collection/immutable/List;)Lscala/reflect/api/Trees$TreeApi;
      1506: aload_0
      1507: invokevirtual #191                // Method c:()Lscala/reflect/macros/blackbox/Context;
      1510: invokeinterface #197,  1          // InterfaceMethod scala/reflect/macros/blackbox/Context.universe:()Lscala/reflect/macros/Universe;
      1515: invokevirtual #278                // Method scala/reflect/macros/Universe.internal:()Lscala/reflect/api/Internals$InternalApi;
      1518: invokeinterface #282,  1          // InterfaceMethod scala/reflect/api/Internals$InternalApi.reificationSupport:()Lscala/reflect/api/Internals$ReificationSupportApi;
      1523: invokeinterface #483,  1          // InterfaceMethod scala/reflect/api/Internals$ReificationSupportApi.SyntacticSelectTerm:()Lscala/reflect/api/Internals$ReificationSupportApi$SyntacticSelectTermExtractor;
      1528: aload_0
      1529: invokevirtual #191                // Method c:()Lscala/reflect/macros/blackbox/Context;
      1532: invokeinterface #197,  1          // InterfaceMethod scala/reflect/macros/blackbox/Context.universe:()Lscala/reflect/macros/Universe;
      1537: invokevirtual #278                // Method scala/reflect/macros/Universe.internal:()Lscala/reflect/api/Internals$InternalApi;
      1540: invokeinterface #282,  1          // InterfaceMethod scala/reflect/api/Internals$InternalApi.reificationSupport:()Lscala/reflect/api/Internals$ReificationSupportApi;
      1545: invokeinterface #486,  1          // InterfaceMethod scala/reflect/api/Internals$ReificationSupportApi.SyntacticTypeApplied:()Lscala/reflect/api/Internals$ReificationSupportApi$SyntacticTypeAppliedExtractor;
      1550: aload_0
      1551: invokevirtual #191                // Method c:()Lscala/reflect/macros/blackbox/Context;
      1554: invokeinterface #197,  1          // InterfaceMethod scala/reflect/macros/blackbox/Context.universe:()Lscala/reflect/macros/Universe;
      1559: invokevirtual #278                // Method scala/reflect/macros/Universe.internal:()Lscala/reflect/api/Internals$InternalApi;
      1562: invokeinterface #282,  1          // InterfaceMethod scala/reflect/api/Internals$InternalApi.reificationSupport:()Lscala/reflect/api/Internals$ReificationSupportApi;
      1567: aload_0
      1568: invokevirtual #191                // Method c:()Lscala/reflect/macros/blackbox/Context;
      1571: invokeinterface #197,  1          // InterfaceMethod scala/reflect/macros/blackbox/Context.universe:()Lscala/reflect/macros/Universe;
      1576: invokevirtual #463                // Method scala/reflect/macros/Universe.EmptyTree:()Lscala/reflect/api/Trees$TreeApi;
      1579: aload_0
      1580: getfield      #500                // Field mkEncodeJson:Lscala/reflect/api/Symbols$SymbolApi;
      1583: invokeinterface #469,  3          // InterfaceMethod scala/reflect/api/Internals$ReificationSupportApi.mkRefTree:(Lscala/reflect/api/Trees$TreeApi;Lscala/reflect/api/Symbols$SymbolApi;)Lscala/reflect/api/Trees$TreeApi;
      1588: new           #288                // class scala/collection/immutable/$colon$colon
      1591: dup
      1592: aload         10
      1594: getstatic     #308                // Field scala/collection/immutable/Nil$.MODULE$:Lscala/collection/immutable/Nil$;
      1597: invokespecial #328                // Method scala/collection/immutable/$colon$colon."<init>":(Ljava/lang/Object;Lscala/collection/immutable/List;)V
      1600: checkcast     #221                // class scala/collection/immutable/List
      1603: invokeinterface #479,  3          // InterfaceMethod scala/reflect/api/Internals$ReificationSupportApi$SyntacticTypeAppliedExtractor.apply:(Lscala/reflect/api/Trees$TreeApi;Lscala/collection/immutable/List;)Lscala/reflect/api/Trees$TreeApi;
      1608: aload_0
      1609: invokevirtual #191                // Method c:()Lscala/reflect/macros/blackbox/Context;
      1612: invokeinterface #197,  1          // InterfaceMethod scala/reflect/macros/blackbox/Context.universe:()Lscala/reflect/macros/Universe;
      1617: invokevirtual #404                // Method scala/reflect/macros/Universe.TermName:()Lscala/reflect/api/Names$TermNameExtractor;
      1620: ldc_w         #502                // String encodeJson
      1623: invokevirtual #430                // Method scala/reflect/api/Names$TermNameExtractor.apply:(Ljava/lang/String;)Lscala/reflect/api/Names$TermNameApi;
      1626: invokeinterface #493,  3          // InterfaceMethod scala/reflect/api/Internals$ReificationSupportApi$SyntacticSelectTermExtractor.apply:(Lscala/reflect/api/Trees$TreeApi;Lscala/reflect/api/Names$TermNameApi;)Lscala/reflect/api/Trees$SelectApi;
      1631: invokeinterface #554,  7          // InterfaceMethod scala/reflect/api/Internals$ReificationSupportApi$SyntacticDefDefExtractor.apply:(Lscala/reflect/api/Trees$ModifiersApi;Lscala/reflect/api/Names$TermNameApi;Lscala/collection/immutable/List;Lscala/collection/immutable/List;Lscala/reflect/api/Trees$TreeApi;Lscala/reflect/api/Trees$TreeApi;)Lscala/reflect/api/Trees$DefDefApi;
      1636: getstatic     #308                // Field scala/collection/immutable/Nil$.MODULE$:Lscala/collection/immutable/Nil$;
      1639: invokespecial #328                // Method scala/collection/immutable/$colon$colon."<init>":(Ljava/lang/Object;Lscala/collection/immutable/List;)V
      1642: invokespecial #328                // Method scala/collection/immutable/$colon$colon."<init>":(Ljava/lang/Object;Lscala/collection/immutable/List;)V
      1645: checkcast     #221                // class scala/collection/immutable/List
      1648: areturn
      StackMapTable: number_of_entries = 2
        frame_type = 255 /* full_frame */
          offset_delta = 853
          locals = [ class argonaut/derive/JsonCodecMacros, class scala/reflect/api/Trees$ClassDefApi, class scala/reflect/api/Names$TypeNameApi, class scala/collection/immutable/List, class scala/reflect/api/Names$TermNameApi, class scala/reflect/api/Names$TermNameApi ]
          stack = []
        frame_type = 247 /* same_locals_1_stack_item_frame_extended */
          offset_delta = 794
          stack = [ class scala/collection/immutable/List ]
      LineNumberTable:
        line 48: 0
        line 49: 7
        line 50: 14
        line 51: 60
        line 52: 106
        line 53: 113
        line 54: 116
        line 55: 120
        line 54: 477
        line 56: 481
        line 54: 838
        line 59: 853
        line 66: 864
        line 67: 876
        line 68: 888
        line 69: 956
        line 70: 960
        line 71: 1239
        line 70: 1248
        line 71: 1252
        line 70: 1254
        line 69: 1296
        line 72: 1300
        line 73: 1579
        line 72: 1588
        line 73: 1592
        line 72: 1594
        line 69: 1636
      LocalVariableTable:
        Start  Length  Slot  Name   Signature
          114     736     6  Type   Lscala/reflect/api/Names$TypeNameApi;
          862     786     7 tparamNames   Lscala/collection/immutable/List;
          874     774     8 decodeParams   Lscala/collection/immutable/List;
          886     762     9 encodeParams   Lscala/collection/immutable/List;
          954     694    10  Type   Lscala/reflect/api/Trees$TreeApi;
            6    1642     2 tpname   Lscala/reflect/api/Names$TypeNameApi;
           13    1635     3 tparams   Lscala/collection/immutable/List;
           58    1590     4 decodeNme   Lscala/reflect/api/Names$TermNameApi;
          104    1544     5 encodeNme   Lscala/reflect/api/Names$TermNameApi;
            0    1649     0  this   Largonaut/derive/JsonCodecMacros;
            0    1649     1 clsDef   Lscala/reflect/api/Trees$ClassDefApi;
    Signature: #396                         // (Lscala/reflect/api/Trees$ClassDefApi;)Lscala/collection/immutable/List<Lscala/reflect/api/Trees$TreeApi;>;
    MethodParameters:
      Name                           Flags
      clsDef                         final

  public static final scala.reflect.api.Names$TypeNameApi $anonfun$codec$1(scala.reflect.api.Trees$TypeDefApi);
    descriptor: (Lscala/reflect/api/Trees$TypeDefApi;)Lscala/reflect/api/Names$TypeNameApi;
    flags: (0x1019) ACC_PUBLIC, ACC_STATIC, ACC_FINAL, ACC_SYNTHETIC
    Code:
      stack=1, locals=1, args_size=1
         0: aload_0
         1: invokeinterface #564,  1          // InterfaceMethod scala/reflect/api/Trees$TypeDefApi.name:()Lscala/reflect/api/Names$TypeNameApi;
         6: areturn
      LineNumberTable:
        line 59: 0
      LocalVariableTable:
        Start  Length  Slot  Name   Signature
            0       7     0   x$1   Lscala/reflect/api/Trees$TypeDefApi;
    MethodParameters:
      Name                           Flags
      x$1                            final

  public static final scala.reflect.api.Trees$TypedApi $anonfun$codec$2(argonaut.derive.JsonCodecMacros, scala.reflect.api.Symbols$TypeSymbolApi, scala.reflect.api.Names$TypeNameApi);
    descriptor: (Largonaut/derive/JsonCodecMacros;Lscala/reflect/api/Symbols$TypeSymbolApi;Lscala/reflect/api/Names$TypeNameApi;)Lscala/reflect/api/Trees$TypedApi;
    flags: (0x1019) ACC_PUBLIC, ACC_STATIC, ACC_FINAL, ACC_SYNTHETIC
    Code:
      stack=6, locals=5, args_size=3
         0: aload_0
         1: invokevirtual #191                // Method c:()Lscala/reflect/macros/blackbox/Context;
         4: aload_2
         5: checkcast     #91                 // class scala/reflect/api/Names$NameApi
         8: invokevirtual #303                // Method scala/reflect/api/Names$NameApi.toTermName:()Lscala/reflect/api/Names$TermNameApi;
        11: checkcast     #91                 // class scala/reflect/api/Names$NameApi
        14: invokeinterface #574,  2          // InterfaceMethod scala/reflect/macros/blackbox/Context.freshName:(Lscala/reflect/api/Names$NameApi;)Lscala/reflect/api/Names$NameApi;
        19: checkcast     #96                 // class scala/reflect/api/Names$TermNameApi
        22: astore_3
        23: aload_0
        24: invokevirtual #191                // Method c:()Lscala/reflect/macros/blackbox/Context;
        27: invokeinterface #197,  1          // InterfaceMethod scala/reflect/macros/blackbox/Context.universe:()Lscala/reflect/macros/Universe;
        32: invokevirtual #278                // Method scala/reflect/macros/Universe.internal:()Lscala/reflect/api/Internals$InternalApi;
        35: invokeinterface #282,  1          // InterfaceMethod scala/reflect/api/Internals$InternalApi.reificationSupport:()Lscala/reflect/api/Internals$ReificationSupportApi;
        40: invokeinterface #459,  1          // InterfaceMethod scala/reflect/api/Internals$ReificationSupportApi.SyntacticAppliedType:()Lscala/reflect/api/Internals$ReificationSupportApi$SyntacticTypeAppliedExtractor;
        45: aload_0
        46: invokevirtual #191                // Method c:()Lscala/reflect/macros/blackbox/Context;
        49: invokeinterface #197,  1          // InterfaceMethod scala/reflect/macros/blackbox/Context.universe:()Lscala/reflect/macros/Universe;
        54: invokevirtual #278                // Method scala/reflect/macros/Universe.internal:()Lscala/reflect/api/Internals$InternalApi;
        57: invokeinterface #282,  1          // InterfaceMethod scala/reflect/api/Internals$InternalApi.reificationSupport:()Lscala/reflect/api/Internals$ReificationSupportApi;
        62: aload_0
        63: invokevirtual #191                // Method c:()Lscala/reflect/macros/blackbox/Context;
        66: invokeinterface #197,  1          // InterfaceMethod scala/reflect/macros/blackbox/Context.universe:()Lscala/reflect/macros/Universe;
        71: invokevirtual #463                // Method scala/reflect/macros/Universe.EmptyTree:()Lscala/reflect/api/Trees$TreeApi;
        74: aload_1
        75: invokeinterface #469,  3          // InterfaceMethod scala/reflect/api/Internals$ReificationSupportApi.mkRefTree:(Lscala/reflect/api/Trees$TreeApi;Lscala/reflect/api/Symbols$SymbolApi;)Lscala/reflect/api/Trees$TreeApi;
        80: new           #288                // class scala/collection/immutable/$colon$colon
        83: dup
        84: aload_0
        85: invokevirtual #191                // Method c:()Lscala/reflect/macros/blackbox/Context;
        88: invokeinterface #197,  1          // InterfaceMethod scala/reflect/macros/blackbox/Context.universe:()Lscala/reflect/macros/Universe;
        93: invokevirtual #278                // Method scala/reflect/macros/Universe.internal:()Lscala/reflect/api/Internals$InternalApi;
        96: invokeinterface #282,  1          // InterfaceMethod scala/reflect/api/Internals$InternalApi.reificationSupport:()Lscala/reflect/api/Internals$ReificationSupportApi;
       101: invokeinterface #473,  1          // InterfaceMethod scala/reflect/api/Internals$ReificationSupportApi.SyntacticTypeIdent:()Lscala/reflect/api/Internals$ReificationSupportApi$SyntacticTypeIdentExtractor;
       106: aload_2
       107: invokeinterface #476,  2          // InterfaceMethod scala/reflect/api/Internals$ReificationSupportApi$SyntacticTypeIdentExtractor.apply:(Lscala/reflect/api/Names$TypeNameApi;)Lscala/reflect/api/Trees$IdentApi;
       112: getstatic     #308                // Field scala/collection/immutable/Nil$.MODULE$:Lscala/collection/immutable/Nil$;
       115: invokespecial #328                // Method scala/collection/immutable/$colon$colon."<init>":(Ljava/lang/Object;Lscala/collection/immutable/List;)V
       118: checkcast     #221                // class scala/collection/immutable/List
       121: invokeinterface #479,  3          // InterfaceMethod scala/reflect/api/Internals$ReificationSupportApi$SyntacticTypeAppliedExtractor.apply:(Lscala/reflect/api/Trees$TreeApi;Lscala/collection/immutable/List;)Lscala/reflect/api/Trees$TreeApi;
       126: astore        4
       128: aload_0
       129: invokevirtual #191                // Method c:()Lscala/reflect/macros/blackbox/Context;
       132: invokeinterface #197,  1          // InterfaceMethod scala/reflect/macros/blackbox/Context.universe:()Lscala/reflect/macros/Universe;
       137: invokevirtual #578                // Method scala/reflect/macros/Universe.Typed:()Lscala/reflect/api/Trees$TypedExtractor;
       140: aload_0
       141: invokevirtual #191                // Method c:()Lscala/reflect/macros/blackbox/Context;
       144: invokeinterface #197,  1          // InterfaceMethod scala/reflect/macros/blackbox/Context.universe:()Lscala/reflect/macros/Universe;
       149: invokevirtual #278                // Method scala/reflect/macros/Universe.internal:()Lscala/reflect/api/Internals$InternalApi;
       152: invokeinterface #282,  1          // InterfaceMethod scala/reflect/api/Internals$InternalApi.reificationSupport:()Lscala/reflect/api/Internals$ReificationSupportApi;
       157: invokeinterface #582,  1          // InterfaceMethod scala/reflect/api/Internals$ReificationSupportApi.SyntacticTermIdent:()Lscala/reflect/api/Internals$ReificationSupportApi$SyntacticTermIdentExtractor;
       162: aload_3
       163: iconst_0
       164: invokeinterface #585,  3          // InterfaceMethod scala/reflect/api/Internals$ReificationSupportApi$SyntacticTermIdentExtractor.apply:(Lscala/reflect/api/Names$TermNameApi;Z)Lscala/reflect/api/Trees$IdentApi;
       169: aload         4
       171: invokevirtual #588                // Method scala/reflect/api/Trees$TypedExtractor.apply:(Lscala/reflect/api/Trees$TreeApi;Lscala/reflect/api/Trees$TreeApi;)Lscala/reflect/api/Trees$TypedApi;
       174: areturn
      LineNumberTable:
        line 62: 0
        line 63: 23
        line 64: 128
      LocalVariableTable:
        Start  Length  Slot  Name   Signature
           22     152     3 paramName   Lscala/reflect/api/Names$TermNameApi;
          126      48     4 paramType   Lscala/reflect/api/Trees$TreeApi;
            0     175     0 $this   Largonaut/derive/JsonCodecMacros;
            0     175     1 typeSymbol$1   Lscala/reflect/api/Symbols$TypeSymbolApi;
            0     175     2 tparamName   Lscala/reflect/api/Names$TypeNameApi;
    MethodParameters:
      Name                           Flags
      $this                          final synthetic
      typeSymbol$1                   final
      tparamName                     final

  private final scala.collection.immutable.List mkImplicitParams$1(scala.reflect.api.Symbols$TypeSymbolApi, scala.collection.immutable.List);
    descriptor: (Lscala/reflect/api/Symbols$TypeSymbolApi;Lscala/collection/immutable/List;)Lscala/collection/immutable/List;
    flags: (0x0012) ACC_PRIVATE, ACC_FINAL
    Code:
      stack=3, locals=3, args_size=3
         0: aload_2
         1: aload_0
         2: aload_1
         3: invokedynamic #600,  0            // InvokeDynamic #2:apply:(Largonaut/derive/JsonCodecMacros;Lscala/reflect/api/Symbols$TypeSymbolApi;)Lscala/Function1;
         8: invokevirtual #526                // Method scala/collection/immutable/List.map:(Lscala/Function1;)Lscala/collection/immutable/List;
        11: areturn
      LineNumberTable:
        line 61: 0
      LocalVariableTable:
        Start  Length  Slot  Name   Signature
            0      12     0  this   Largonaut/derive/JsonCodecMacros;
            0      12     1 typeSymbol   Lscala/reflect/api/Symbols$TypeSymbolApi;
            0      12     2 tparamNames$1   Lscala/collection/immutable/List;
    MethodParameters:
      Name                           Flags
      typeSymbol                     final
      tparamNames$1                  final

  public static final scala.reflect.api.Trees$TreeApi $anonfun$codec$3(argonaut.derive.JsonCodecMacros, scala.reflect.api.Names$TypeNameApi);
    descriptor: (Largonaut/derive/JsonCodecMacros;Lscala/reflect/api/Names$TypeNameApi;)Lscala/reflect/api/Trees$TreeApi;
    flags: (0x1019) ACC_PUBLIC, ACC_STATIC, ACC_FINAL, ACC_SYNTHETIC
    Code:
      stack=2, locals=2, args_size=2
         0: aload_0
         1: invokevirtual #191                // Method c:()Lscala/reflect/macros/blackbox/Context;
         4: invokeinterface #197,  1          // InterfaceMethod scala/reflect/macros/blackbox/Context.universe:()Lscala/reflect/macros/Universe;
         9: invokevirtual #604                // Method scala/reflect/macros/Universe.Liftable:()Lscala/reflect/api/Liftables$Liftable$;
        12: invokevirtual #608                // Method scala/reflect/api/Liftables$Liftable$.liftName:()Lscala/reflect/api/Liftables$Liftable;
        15: aload_1
        16: invokeinterface #611,  2          // InterfaceMethod scala/reflect/api/Liftables$Liftable.apply:(Ljava/lang/Object;)Lscala/reflect/api/Trees$TreeApi;
        21: areturn
      LineNumberTable:
        line 68: 0
      LocalVariableTable:
        Start  Length  Slot  Name   Signature
            0      22     0 $this   Largonaut/derive/JsonCodecMacros;
            0      22     1 fresh$macro$13   Lscala/reflect/api/Names$TypeNameApi;
    MethodParameters:
      Name                           Flags
      $this                          final synthetic
      fresh$macro$13                 final

  public argonaut.derive.JsonCodecMacros(scala.reflect.macros.blackbox.Context);
    descriptor: (Lscala/reflect/macros/blackbox/Context;)V
    flags: (0x0001) ACC_PUBLIC
    Code:
      stack=7, locals=10, args_size=2
         0: aload_0
         1: aload_1
         2: putfield      #180                // Field c:Lscala/reflect/macros/blackbox/Context;
         5: aload_0
         6: invokespecial #615                // Method java/lang/Object."<init>":()V
         9: aload_0
        10: aload_1
        11: invokeinterface #197,  1          // InterfaceMethod scala/reflect/macros/blackbox/Context.universe:()Lscala/reflect/macros/Universe;
        16: aload_1
        17: invokeinterface #197,  1          // InterfaceMethod scala/reflect/macros/blackbox/Context.universe:()Lscala/reflect/macros/Universe;
        22: astore_2
        23: aload_1
        24: invokeinterface #197,  1          // InterfaceMethod scala/reflect/macros/blackbox/Context.universe:()Lscala/reflect/macros/Universe;
        29: invokevirtual #619                // Method scala/reflect/macros/Universe.rootMirror:()Lscala/reflect/api/Mirror;
        32: astore_3
        33: aload_2
        34: invokevirtual #622                // Method scala/reflect/macros/Universe.TypeTag:()Lscala/reflect/api/TypeTags$TypeTag$;
        37: aload_3
        38: new           #12                 // class argonaut/derive/JsonCodecMacros$$typecreator1$1
        41: dup
        42: aconst_null
        43: invokespecial #623                // Method argonaut/derive/JsonCodecMacros$$typecreator1$1."<init>":(Largonaut/derive/JsonCodecMacros;)V
        46: invokevirtual #626                // Method scala/reflect/api/TypeTags$TypeTag$.apply:(Lscala/reflect/api/Mirror;Lscala/reflect/api/TypeCreator;)Lscala/reflect/api/TypeTags$TypeTag;
        49: invokevirtual #630                // Method scala/reflect/macros/Universe.symbolOf:(Lscala/reflect/api/TypeTags$WeakTypeTag;)Lscala/reflect/api/Symbols$TypeSymbolApi;
        52: putfield      #465                // Field DecoderClass:Lscala/reflect/api/Symbols$TypeSymbolApi;
        55: aload_0
        56: aload_1
        57: invokeinterface #197,  1          // InterfaceMethod scala/reflect/macros/blackbox/Context.universe:()Lscala/reflect/macros/Universe;
        62: aload_1
        63: invokeinterface #197,  1          // InterfaceMethod scala/reflect/macros/blackbox/Context.universe:()Lscala/reflect/macros/Universe;
        68: astore        4
        70: aload_1
        71: invokeinterface #197,  1          // InterfaceMethod scala/reflect/macros/blackbox/Context.universe:()Lscala/reflect/macros/Universe;
        76: invokevirtual #619                // Method scala/reflect/macros/Universe.rootMirror:()Lscala/reflect/api/Mirror;
        79: astore        5
        81: aload         4
        83: invokevirtual #622                // Method scala/reflect/macros/Universe.TypeTag:()Lscala/reflect/api/TypeTags$TypeTag$;
        86: aload         5
        88: new           #15                 // class argonaut/derive/JsonCodecMacros$$typecreator2$1
        91: dup
        92: aconst_null
        93: invokespecial #631                // Method argonaut/derive/JsonCodecMacros$$typecreator2$1."<init>":(Largonaut/derive/JsonCodecMacros;)V
        96: invokevirtual #626                // Method scala/reflect/api/TypeTags$TypeTag$.apply:(Lscala/reflect/api/Mirror;Lscala/reflect/api/TypeCreator;)Lscala/reflect/api/TypeTags$TypeTag;
        99: invokevirtual #630                // Method scala/reflect/macros/Universe.symbolOf:(Lscala/reflect/api/TypeTags$WeakTypeTag;)Lscala/reflect/api/Symbols$TypeSymbolApi;
       102: putfield      #498                // Field EncoderClass:Lscala/reflect/api/Symbols$TypeSymbolApi;
       105: aload_0
       106: aload_1
       107: invokeinterface #197,  1          // InterfaceMethod scala/reflect/macros/blackbox/Context.universe:()Lscala/reflect/macros/Universe;
       112: aload_1
       113: invokeinterface #197,  1          // InterfaceMethod scala/reflect/macros/blackbox/Context.universe:()Lscala/reflect/macros/Universe;
       118: astore        6
       120: aload_1
       121: invokeinterface #197,  1          // InterfaceMethod scala/reflect/macros/blackbox/Context.universe:()Lscala/reflect/macros/Universe;
       126: invokevirtual #619                // Method scala/reflect/macros/Universe.rootMirror:()Lscala/reflect/api/Mirror;
       129: astore        7
       131: aload         6
       133: invokevirtual #622                // Method scala/reflect/macros/Universe.TypeTag:()Lscala/reflect/api/TypeTags$TypeTag$;
       136: aload         7
       138: new           #18                 // class argonaut/derive/JsonCodecMacros$$typecreator3$1
       141: dup
       142: aconst_null
       143: invokespecial #632                // Method argonaut/derive/JsonCodecMacros$$typecreator3$1."<init>":(Largonaut/derive/JsonCodecMacros;)V
       146: invokevirtual #626                // Method scala/reflect/api/TypeTags$TypeTag$.apply:(Lscala/reflect/api/Mirror;Lscala/reflect/api/TypeCreator;)Lscala/reflect/api/TypeTags$TypeTag;
       149: invokevirtual #630                // Method scala/reflect/macros/Universe.symbolOf:(Lscala/reflect/api/TypeTags$WeakTypeTag;)Lscala/reflect/api/Symbols$TypeSymbolApi;
       152: invokeinterface #636,  1          // InterfaceMethod scala/reflect/api/Symbols$TypeSymbolApi.asClass:()Lscala/reflect/api/Symbols$ClassSymbolApi;
       157: invokeinterface #640,  1          // InterfaceMethod scala/reflect/api/Symbols$ClassSymbolApi.module:()Lscala/reflect/api/Symbols$SymbolApi;
       162: putfield      #488                // Field mkDecodeJson:Lscala/reflect/api/Symbols$SymbolApi;
       165: aload_0
       166: aload_1
       167: invokeinterface #197,  1          // InterfaceMethod scala/reflect/macros/blackbox/Context.universe:()Lscala/reflect/macros/Universe;
       172: aload_1
       173: invokeinterface #197,  1          // InterfaceMethod scala/reflect/macros/blackbox/Context.universe:()Lscala/reflect/macros/Universe;
       178: astore        8
       180: aload_1
       181: invokeinterface #197,  1          // InterfaceMethod scala/reflect/macros/blackbox/Context.universe:()Lscala/reflect/macros/Universe;
       186: invokevirtual #619                // Method scala/reflect/macros/Universe.rootMirror:()Lscala/reflect/api/Mirror;
       189: astore        9
       191: aload         8
       193: invokevirtual #622                // Method scala/reflect/macros/Universe.TypeTag:()Lscala/reflect/api/TypeTags$TypeTag$;
       196: aload         9
       198: new           #21                 // class argonaut/derive/JsonCodecMacros$$typecreator4$1
       201: dup
       202: aconst_null
       203: invokespecial #641                // Method argonaut/derive/JsonCodecMacros$$typecreator4$1."<init>":(Largonaut/derive/JsonCodecMacros;)V
       206: invokevirtual #626                // Method scala/reflect/api/TypeTags$TypeTag$.apply:(Lscala/reflect/api/Mirror;Lscala/reflect/api/TypeCreator;)Lscala/reflect/api/TypeTags$TypeTag;
       209: invokevirtual #630                // Method scala/reflect/macros/Universe.symbolOf:(Lscala/reflect/api/TypeTags$WeakTypeTag;)Lscala/reflect/api/Symbols$TypeSymbolApi;
       212: invokeinterface #636,  1          // InterfaceMethod scala/reflect/api/Symbols$TypeSymbolApi.asClass:()Lscala/reflect/api/Symbols$ClassSymbolApi;
       217: invokeinterface #640,  1          // InterfaceMethod scala/reflect/api/Symbols$ClassSymbolApi.module:()Lscala/reflect/api/Symbols$SymbolApi;
       222: putfield      #500                // Field mkEncodeJson:Lscala/reflect/api/Symbols$SymbolApi;
       225: return
      LineNumberTable:
        line 13: 0
        line 77: 5
        line 42: 9
        line 43: 55
        line 44: 105
        line 45: 165
        line 13: 225
      LocalVariableTable:
        Start  Length  Slot  Name   Signature
           22      27     2    $u   Lscala/reflect/macros/Universe;
           32      17     3    $m   Lscala/reflect/api/Mirror;
           68      31     4    $u   Lscala/reflect/macros/Universe;
           79      20     5    $m   Lscala/reflect/api/Mirror;
          118      31     6    $u   Lscala/reflect/macros/Universe;
          129      20     7    $m   Lscala/reflect/api/Mirror;
          178      31     8    $u   Lscala/reflect/macros/Universe;
          189      20     9    $m   Lscala/reflect/api/Mirror;
            0     226     0  this   Largonaut/derive/JsonCodecMacros;
            0     226     1     c   Lscala/reflect/macros/blackbox/Context;
    MethodParameters:
      Name                           Flags
      c                              final

  private static java.lang.Object $deserializeLambda$(java.lang.invoke.SerializedLambda);
    descriptor: (Ljava/lang/invoke/SerializedLambda;)Ljava/lang/Object;
    flags: (0x100a) ACC_PRIVATE, ACC_STATIC, ACC_SYNTHETIC
    Code:
      stack=1, locals=1, args_size=1
         0: aload_0
         1: invokedynamic #657,  0            // InvokeDynamic #3:lambdaDeserialize:(Ljava/lang/invoke/SerializedLambda;)Ljava/lang/Object;
         6: areturn
}
InnerClasses:
  public final #10;                       // class argonaut/derive/JsonCodecMacros$$anon$1
  public final #13= #12;                  // $typecreator1$1=class argonaut/derive/JsonCodecMacros$$typecreator1$1
  public final #16= #15;                  // $typecreator2$1=class argonaut/derive/JsonCodecMacros$$typecreator2$1
  public final #19= #18;                  // $typecreator3$1=class argonaut/derive/JsonCodecMacros$$typecreator3$1
  public final #22= #21;                  // $typecreator4$1=class argonaut/derive/JsonCodecMacros$$typecreator4$1
  public static final #27= #24 of #26;    // Lookup=class java/lang/invoke/MethodHandles$Lookup of class java/lang/invoke/MethodHandles
  public static final #32= #29 of #31;    // UnapplySeqWrapper=class scala/collection/SeqFactory$UnapplySeqWrapper of class scala/collection/SeqFactory
  public static #35= #34 of #31;          // UnapplySeqWrapper$=class scala/collection/SeqFactory$UnapplySeqWrapper$ of class scala/collection/SeqFactory
  public #40= #37 of #39;                 // FlagValues=class scala/reflect/api/FlagSets$FlagValues of class scala/reflect/api/FlagSets
  public #45= #42 of #44;                 // InternalApi=class scala/reflect/api/Internals$InternalApi of class scala/reflect/api/Internals
  public #48= #47 of #44;                 // ReificationSupportApi=class scala/reflect/api/Internals$ReificationSupportApi of class scala/reflect/api/Internals
  public #51= #50 of #47;                 // FlagsReprExtractor=class scala/reflect/api/Internals$ReificationSupportApi$FlagsReprExtractor of class scala/reflect/api/Internals$ReificationSupportApi
  public #54= #53 of #47;                 // ImplicitParamsExtractor=class scala/reflect/api/Internals$ReificationSupportApi$ImplicitParamsExtractor of class scala/reflect/api/Internals$ReificationSupportApi
  public #57= #56 of #47;                 // ScalaDotExtractor=class scala/reflect/api/Internals$ReificationSupportApi$ScalaDotExtractor of class scala/reflect/api/Internals$ReificationSupportApi
  public #60= #59 of #47;                 // SyntacticBlockExtractor=class scala/reflect/api/Internals$ReificationSupportApi$SyntacticBlockExtractor of class scala/reflect/api/Internals$ReificationSupportApi
  public #63= #62 of #47;                 // SyntacticDefDefExtractor=class scala/reflect/api/Internals$ReificationSupportApi$SyntacticDefDefExtractor of class scala/reflect/api/Internals$ReificationSupportApi
  public #66= #65 of #47;                 // SyntacticObjectDefExtractor=class scala/reflect/api/Internals$ReificationSupportApi$SyntacticObjectDefExtractor of class scala/reflect/api/Internals$ReificationSupportApi
  public #69= #68 of #47;                 // SyntacticSelectTermExtractor=class scala/reflect/api/Internals$ReificationSupportApi$SyntacticSelectTermExtractor of class scala/reflect/api/Internals$ReificationSupportApi
  public #72= #71 of #47;                 // SyntacticTermIdentExtractor=class scala/reflect/api/Internals$ReificationSupportApi$SyntacticTermIdentExtractor of class scala/reflect/api/Internals$ReificationSupportApi
  public #75= #74 of #47;                 // SyntacticTypeAppliedExtractor=class scala/reflect/api/Internals$ReificationSupportApi$SyntacticTypeAppliedExtractor of class scala/reflect/api/Internals$ReificationSupportApi
  public #78= #77 of #47;                 // SyntacticTypeIdentExtractor=class scala/reflect/api/Internals$ReificationSupportApi$SyntacticTypeIdentExtractor of class scala/reflect/api/Internals$ReificationSupportApi
  public #81= #80 of #47;                 // SyntacticValDefExtractor=class scala/reflect/api/Internals$ReificationSupportApi$SyntacticValDefExtractor of class scala/reflect/api/Internals$ReificationSupportApi
  public #86= #83 of #85;                 // Liftable=class scala/reflect/api/Liftables$Liftable of class scala/reflect/api/Liftables
  public #89= #88 of #85;                 // Liftable$=class scala/reflect/api/Liftables$Liftable$ of class scala/reflect/api/Liftables
  public abstract #94= #91 of #93;        // NameApi=class scala/reflect/api/Names$NameApi of class scala/reflect/api/Names
  public #97= #96 of #93;                 // TermNameApi=class scala/reflect/api/Names$TermNameApi of class scala/reflect/api/Names
  public abstract #100= #99 of #93;       // TermNameExtractor=class scala/reflect/api/Names$TermNameExtractor of class scala/reflect/api/Names
  public #103= #102 of #93;               // TypeNameApi=class scala/reflect/api/Names$TypeNameApi of class scala/reflect/api/Names
  public abstract #106= #105 of #93;      // TypeNameExtractor=class scala/reflect/api/Names$TypeNameExtractor of class scala/reflect/api/Names
  public #111= #108 of #110;              // ClassSymbolApi=class scala/reflect/api/Symbols$ClassSymbolApi of class scala/reflect/api/Symbols
  public #114= #113 of #110;              // SymbolApi=class scala/reflect/api/Symbols$SymbolApi of class scala/reflect/api/Symbols
  public #117= #116 of #110;              // TypeSymbolApi=class scala/reflect/api/Symbols$TypeSymbolApi of class scala/reflect/api/Symbols
  public #122= #119 of #121;              // ClassDefApi=class scala/reflect/api/Trees$ClassDefApi of class scala/reflect/api/Trees
  public #125= #124 of #121;              // DefDefApi=class scala/reflect/api/Trees$DefDefApi of class scala/reflect/api/Trees
  public #128= #127 of #121;              // IdentApi=class scala/reflect/api/Trees$IdentApi of class scala/reflect/api/Trees
  public #131= #130 of #121;              // ImplDefApi=class scala/reflect/api/Trees$ImplDefApi of class scala/reflect/api/Trees
  public abstract #134= #133 of #121;     // ModifiersApi=class scala/reflect/api/Trees$ModifiersApi of class scala/reflect/api/Trees
  public abstract #137= #136 of #121;     // ModifiersExtractor=class scala/reflect/api/Trees$ModifiersExtractor of class scala/reflect/api/Trees
  public #140= #139 of #121;              // ModuleDefApi=class scala/reflect/api/Trees$ModuleDefApi of class scala/reflect/api/Trees
  public #143= #142 of #121;              // SelectApi=class scala/reflect/api/Trees$SelectApi of class scala/reflect/api/Trees
  public #146= #145 of #121;              // TreeApi=class scala/reflect/api/Trees$TreeApi of class scala/reflect/api/Trees
  public #149= #148 of #121;              // TypeDefApi=class scala/reflect/api/Trees$TypeDefApi of class scala/reflect/api/Trees
  public #152= #151 of #121;              // TypedApi=class scala/reflect/api/Trees$TypedApi of class scala/reflect/api/Trees
  public abstract #155= #154 of #121;     // TypedExtractor=class scala/reflect/api/Trees$TypedExtractor of class scala/reflect/api/Trees
  public #158= #157 of #121;              // ValDefApi=class scala/reflect/api/Trees$ValDefApi of class scala/reflect/api/Trees
  public #163= #160 of #162;              // TypeTag=class scala/reflect/api/TypeTags$TypeTag of class scala/reflect/api/TypeTags
  public #166= #165 of #162;              // TypeTag$=class scala/reflect/api/TypeTags$TypeTag$ of class scala/reflect/api/TypeTags
  public #169= #168 of #162;              // WeakTypeTag=class scala/reflect/api/TypeTags$WeakTypeTag of class scala/reflect/api/TypeTags
SourceFile: "JsonCodecMacros.scala"
RuntimeVisibleAnnotations:
  0: #6(#7=s#8)
    scala.reflect.ScalaSignature(
      bytes="\u0006\u0005\t4Qa\u0003\u0007\u0001\u0019AA\u0001b\u0006\u0001\u0003\u0006\u0004%\t!\u0007\u0005\tI\u0001\u0011\t\u0011)A\u00055!)Q\u0005\u0001C\u0001M!1!\u0006\u0001Q\u0005\n-BQ!\u0010\u0001\u0005\u0002yBaa\u0012\u0001!\u0002\u0013A\u0005BB\'\u0001A\u0003%\u0001\n\u0003\u0004O\u0001\u0001\u0006Ia\u0014\u0005\u0007%\u0002\u0001\u000b\u0011B(\t\rM\u0003\u0001\u0015\"\u0003U\u0005=Q5o\u001c8D_\u0012,7-T1de>\u001c(BA\u0007\u000f\u0003\u0019!WM]5wK*\tq\"\u0001\u0005be\u001e|g.Y;u\'\t\u0001\u0011\u0003\u0005\u0002\u0013+5\t1CC\u0001\u0015\u0003\u0015\u00198-\u00197b\u0013\t12C\u0001\u0004B]f\u0014VMZ\u0001\u0002G\u000e\u0001Q#\u0001\u000e\u0011\u0005m\u0011S\"\u0001\u000f\u000b\u0005uq\u0012\u0001\u00032mC\u000e\\\'m\u001c=\u000b\u0005}\u0001\u0013AB7bGJ|7O\u0003\u0002\"\'\u00059!/\u001a4mK\u000e$\u0018BA\u0012\u001d\u0005\u001d\u0019uN\u001c;fqR\f!a\u0019\u0011\u0002\rqJg.\u001b;?)\t9\u0013\u0006\u0005\u0002)\u00015\tA\u0002C\u0003\u0018\u0007\u0001\u0007!$A\njg\u000e\u000b7/Z\"mCN\u001cxJ]*fC2,G\r\u0006\u0002-_A\u0011!#L\u0005\u0003]M\u0011qAQ8pY\u0016\fg\u000eC\u00031\t\u0001\u0007\u0011\'\u0001\u0004dYN$UM\u001a\t\u0003e]r!aM\u001b\u000f\u0005Q\nQ\"\u0001\u0001\n\u0005Y\u0012\u0013\u0001C;oSZ,\'o]3\n\u0005aJ$\u0001C\"mCN\u001cH)\u001a4\n\u0005iZ$!\u0002+sK\u0016\u001c(B\u0001\u001f!\u0003\r\t\u0007/[\u0001\u0019UN|gnQ8eK\u000e\feN\\8uCRLwN\\\'bGJ|GCA C!\t\u0011\u0004)\u0003\u0002Bs\t!AK]3f\u0011\u0015\u0019U\u00011\u0001E\u0003%\tgN\\8ui\u0016,7\u000fE\u0002\u0013\u000b~J!AR\n\u0003\u0015q\u0012X\r]3bi\u0016$g(\u0001\u0007EK\u000e|G-\u001a:DY\u0006\u001c8\u000f\u0005\u00023\u0013&\u0011!j\u0013\u0002\u000b)f\u0004XmU=nE>d\u0017B\u0001\'<\u0005\u001d\u0019\u00160\u001c2pYN\fA\"\u00128d_\u0012,\'o\u00117bgN\fA\"\\6EK\u000e|G-\u001a&t_:\u0004\"A\r)\n\u0005E[%AB*z[\n|G.\u0001\u0007nW\u0016s7m\u001c3f\u0015N|g.A\u0003d_\u0012,7\r\u0006\u0002VCB\u0019aKX \u000f\u0005]cfB\u0001-\\\u001b\u0005I&B\u0001.\u0019\u0003\u0019a$o\\8u}%\tA#\u0003\u0002^\'\u00059\u0001/Y2lC\u001e,\u0017BA0a\u0005\u0011a\u0015n\u001d;\u000b\u0005u\u001b\u0002\"\u0002\u0019\u000b\u0001\u0004\t\u0004"
    )
BootstrapMethods:
  0: #519 REF_invokeStatic java/lang/invoke/LambdaMetafactory.altMetafactory:(Ljava/lang/invoke/MethodHandles$Lookup;Ljava/lang/String;Ljava/lang/invoke/MethodType;[Ljava/lang/Object;)Ljava/lang/invoke/CallSite;
    Method arguments:
      #504 (Ljava/lang/Object;)Ljava/lang/Object;
      #509 REF_invokeStatic argonaut/derive/JsonCodecMacros.$anonfun$codec$1:(Lscala/reflect/api/Trees$TypeDefApi;)Lscala/reflect/api/Names$TypeNameApi;
      #510 (Lscala/reflect/api/Trees$TypeDefApi;)Lscala/reflect/api/Names$TypeNameApi;
      #511 5
      #512 1
      #510 (Lscala/reflect/api/Trees$TypeDefApi;)Lscala/reflect/api/Names$TypeNameApi;
  1: #519 REF_invokeStatic java/lang/invoke/LambdaMetafactory.altMetafactory:(Ljava/lang/invoke/MethodHandles$Lookup;Ljava/lang/String;Ljava/lang/invoke/MethodType;[Ljava/lang/Object;)Ljava/lang/invoke/CallSite;
    Method arguments:
      #504 (Ljava/lang/Object;)Ljava/lang/Object;
      #535 REF_invokeStatic argonaut/derive/JsonCodecMacros.$anonfun$codec$3:(Largonaut/derive/JsonCodecMacros;Lscala/reflect/api/Names$TypeNameApi;)Lscala/reflect/api/Trees$TreeApi;
      #537 (Lscala/reflect/api/Names$TypeNameApi;)Lscala/reflect/api/Trees$TreeApi;
      #511 5
      #512 1
      #537 (Lscala/reflect/api/Names$TypeNameApi;)Lscala/reflect/api/Trees$TreeApi;
  2: #519 REF_invokeStatic java/lang/invoke/LambdaMetafactory.altMetafactory:(Ljava/lang/invoke/MethodHandles$Lookup;Ljava/lang/String;Ljava/lang/invoke/MethodType;[Ljava/lang/Object;)Ljava/lang/invoke/CallSite;
    Method arguments:
      #504 (Ljava/lang/Object;)Ljava/lang/Object;
      #595 REF_invokeStatic argonaut/derive/JsonCodecMacros.$anonfun$codec$2:(Largonaut/derive/JsonCodecMacros;Lscala/reflect/api/Symbols$TypeSymbolApi;Lscala/reflect/api/Names$TypeNameApi;)Lscala/reflect/api/Trees$TypedApi;
      #597 (Lscala/reflect/api/Names$TypeNameApi;)Lscala/reflect/api/Trees$TypedApi;
      #511 5
      #512 1
      #597 (Lscala/reflect/api/Names$TypeNameApi;)Lscala/reflect/api/Trees$TypedApi;
  3: #654 REF_invokeStatic scala/runtime/LambdaDeserialize.bootstrap:(Ljava/lang/invoke/MethodHandles$Lookup;Ljava/lang/String;Ljava/lang/invoke/MethodType;[Ljava/lang/invoke/MethodHandle;)Ljava/lang/invoke/CallSite;
    Method arguments:
      #509 REF_invokeStatic argonaut/derive/JsonCodecMacros.$anonfun$codec$1:(Lscala/reflect/api/Trees$TypeDefApi;)Lscala/reflect/api/Names$TypeNameApi;
      #595 REF_invokeStatic argonaut/derive/JsonCodecMacros.$anonfun$codec$2:(Largonaut/derive/JsonCodecMacros;Lscala/reflect/api/Symbols$TypeSymbolApi;Lscala/reflect/api/Names$TypeNameApi;)Lscala/reflect/api/Trees$TypedApi;
      #535 REF_invokeStatic argonaut/derive/JsonCodecMacros.$anonfun$codec$3:(Largonaut/derive/JsonCodecMacros;Lscala/reflect/api/Names$TypeNameApi;)Lscala/reflect/api/Trees$TreeApi;
  ScalaInlineInfo: length = 0x31 (unknown attribute)
   01 00 00 09 01 F9 01 FA 01 02 36 02 37 01 02 13
   02 14 01 00 F2 02 64 00 00 AA 00 B2 00 01 4D 01
   4E 01 00 B7 00 B8 01 00 D8 00 D9 00 02 0F 02 10
   01
  ScalaSig: length = 0x3 (unknown attribute)
   05 02 00
