Classfile /Users/mw/Projects/slang-braindump/.jar/jar11/assemble/slang-braindump/assemble/content/argonaut/derive/ProductEncodeJson$.class
  Last modified May 29, 2022; size 3993 bytes
  SHA-256 checksum f20cbb1738295957a8a9c9988e3999abc7cfddaa61a55c7a5160fd28459b8a3d
  Compiled from "MkEncodeJson.scala"
public final class argonaut.derive.ProductEncodeJson$
  minor version: 0
  major version: 52
  flags: (0x0031) ACC_PUBLIC, ACC_FINAL, ACC_SUPER
  this_class: #2                          // argonaut/derive/ProductEncodeJson$
  super_class: #4                         // java/lang/Object
  interfaces: 0, fields: 1, methods: 8, attributes: 5
Constant pool:
    #1 = Utf8               argonaut/derive/ProductEncodeJson$
    #2 = Class              #1            // argonaut/derive/ProductEncodeJson$
    #3 = Utf8               java/lang/Object
    #4 = Class              #3            // java/lang/Object
    #5 = Utf8               MkEncodeJson.scala
    #6 = Utf8               argonaut/derive/ProductEncodeJson$$anon$3
    #7 = Class              #6            // argonaut/derive/ProductEncodeJson$$anon$3
    #8 = Utf8               java/lang/invoke/MethodHandles$Lookup
    #9 = Class              #8            // java/lang/invoke/MethodHandles$Lookup
   #10 = Utf8               java/lang/invoke/MethodHandles
   #11 = Class              #10           // java/lang/invoke/MethodHandles
   #12 = Utf8               Lookup
   #13 = Utf8               shapeless/Default$AsOptions
   #14 = Class              #13           // shapeless/Default$AsOptions
   #15 = Utf8               shapeless/Default
   #16 = Class              #15           // shapeless/Default
   #17 = Utf8               AsOptions
   #18 = Utf8               MODULE$
   #19 = Utf8               Largonaut/derive/ProductEncodeJson$;
   #20 = Utf8               <clinit>
   #21 = Utf8               ()V
   #22 = Utf8               <init>
   #23 = NameAndType        #22:#21       // "<init>":()V
   #24 = Methodref          #2.#23        // argonaut/derive/ProductEncodeJson$."<init>":()V
   #25 = NameAndType        #18:#19       // MODULE$:Largonaut/derive/ProductEncodeJson$;
   #26 = Fieldref           #2.#25        // argonaut/derive/ProductEncodeJson$.MODULE$:Largonaut/derive/ProductEncodeJson$;
   #27 = Utf8               apply
   #28 = Utf8               (Largonaut/derive/ProductEncodeJson;)Largonaut/derive/ProductEncodeJson;
   #29 = Utf8               <P:Ljava/lang/Object;>(Largonaut/derive/ProductEncodeJson<TP;>;)Largonaut/derive/ProductEncodeJson<TP;>;
   #30 = Utf8               encodeJson
   #31 = Utf8               this
   #32 = Utf8               Largonaut/derive/ProductEncodeJson;
   #33 = Utf8               instance
   #34 = Utf8               (Lscala/Function1;)Largonaut/derive/ProductEncodeJson;
   #35 = Utf8               <P:Ljava/lang/Object;>(Lscala/Function1<Largonaut/derive/JsonProductCodec;Largonaut/EncodeJson<TP;>;>;)Largonaut/derive/ProductEncodeJson<TP;>;
   #36 = Utf8               f
   #37 = Utf8               (Lscala/Function1;)V
   #38 = NameAndType        #22:#37       // "<init>":(Lscala/Function1;)V
   #39 = Methodref          #7.#38        // argonaut/derive/ProductEncodeJson$$anon$3."<init>":(Lscala/Function1;)V
   #40 = Utf8               Lscala/Function1;
   #41 = Utf8               generic
   #42 = Utf8               (Lshapeless/LabelledGeneric;Lshapeless/Default$AsOptions;Lshapeless/Lazy;)Largonaut/derive/ProductEncodeJson;
   #43 = Utf8               <P:Ljava/lang/Object;L::Lshapeless/HList;D::Lshapeless/HList;>(Lshapeless/LabelledGeneric<TP;>;Lshapeless/Default$AsOptions<TP;>;Lshapeless/Lazy<Largonaut/derive/HListProductEncodeJson<TL;TD;>;>;)Largonaut/derive/ProductEncodeJson<TP;>;
   #44 = Utf8               gen
   #45 = Utf8               defaults
   #46 = Utf8               underlying
   #47 = Utf8               (Ljava/lang/Object;)Ljava/lang/Object;
   #48 = MethodType         #47           //  (Ljava/lang/Object;)Ljava/lang/Object;
   #49 = Utf8               $anonfun$generic$1
   #50 = Utf8               (Lshapeless/Lazy;Lshapeless/Default$AsOptions;Lshapeless/LabelledGeneric;Largonaut/derive/JsonProductCodec;)Largonaut/EncodeJson;
   #51 = NameAndType        #49:#50       // $anonfun$generic$1:(Lshapeless/Lazy;Lshapeless/Default$AsOptions;Lshapeless/LabelledGeneric;Largonaut/derive/JsonProductCodec;)Largonaut/EncodeJson;
   #52 = Methodref          #2.#51        // argonaut/derive/ProductEncodeJson$.$anonfun$generic$1:(Lshapeless/Lazy;Lshapeless/Default$AsOptions;Lshapeless/LabelledGeneric;Largonaut/derive/JsonProductCodec;)Largonaut/EncodeJson;
   #53 = MethodHandle       6:#52         // REF_invokeStatic argonaut/derive/ProductEncodeJson$.$anonfun$generic$1:(Lshapeless/Lazy;Lshapeless/Default$AsOptions;Lshapeless/LabelledGeneric;Largonaut/derive/JsonProductCodec;)Largonaut/EncodeJson;
   #54 = Utf8               (Largonaut/derive/JsonProductCodec;)Largonaut/EncodeJson;
   #55 = MethodType         #54           //  (Largonaut/derive/JsonProductCodec;)Largonaut/EncodeJson;
   #56 = Integer            5
   #57 = Integer            1
   #58 = Utf8               java/lang/invoke/LambdaMetafactory
   #59 = Class              #58           // java/lang/invoke/LambdaMetafactory
   #60 = Utf8               altMetafactory
   #61 = Utf8               (Ljava/lang/invoke/MethodHandles$Lookup;Ljava/lang/String;Ljava/lang/invoke/MethodType;[Ljava/lang/Object;)Ljava/lang/invoke/CallSite;
   #62 = NameAndType        #60:#61       // altMetafactory:(Ljava/lang/invoke/MethodHandles$Lookup;Ljava/lang/String;Ljava/lang/invoke/MethodType;[Ljava/lang/Object;)Ljava/lang/invoke/CallSite;
   #63 = Methodref          #59.#62       // java/lang/invoke/LambdaMetafactory.altMetafactory:(Ljava/lang/invoke/MethodHandles$Lookup;Ljava/lang/String;Ljava/lang/invoke/MethodType;[Ljava/lang/Object;)Ljava/lang/invoke/CallSite;
   #64 = MethodHandle       6:#63         // REF_invokeStatic java/lang/invoke/LambdaMetafactory.altMetafactory:(Ljava/lang/invoke/MethodHandles$Lookup;Ljava/lang/String;Ljava/lang/invoke/MethodType;[Ljava/lang/Object;)Ljava/lang/invoke/CallSite;
   #65 = Utf8               (Lshapeless/Lazy;Lshapeless/Default$AsOptions;Lshapeless/LabelledGeneric;)Lscala/Function1;
   #66 = NameAndType        #27:#65       // apply:(Lshapeless/Lazy;Lshapeless/Default$AsOptions;Lshapeless/LabelledGeneric;)Lscala/Function1;
   #67 = InvokeDynamic      #0:#66        // #0:apply:(Lshapeless/Lazy;Lshapeless/Default$AsOptions;Lshapeless/LabelledGeneric;)Lscala/Function1;
   #68 = NameAndType        #33:#34       // instance:(Lscala/Function1;)Largonaut/derive/ProductEncodeJson;
   #69 = Methodref          #2.#68        // argonaut/derive/ProductEncodeJson$.instance:(Lscala/Function1;)Largonaut/derive/ProductEncodeJson;
   #70 = Utf8               Lshapeless/LabelledGeneric;
   #71 = Utf8               Lshapeless/Default$AsOptions;
   #72 = Utf8               Lshapeless/Lazy;
   #73 = Utf8               $anonfun$generic$2
   #74 = Utf8               (Lshapeless/LabelledGeneric;Ljava/lang/Object;)Lshapeless/HList;
   #75 = Utf8               gen$1
   #76 = Utf8               t
   #77 = Utf8               shapeless/LabelledGeneric
   #78 = Class              #77           // shapeless/LabelledGeneric
   #79 = Utf8               to
   #80 = NameAndType        #79:#47       // to:(Ljava/lang/Object;)Ljava/lang/Object;
   #81 = InterfaceMethodref #78.#80       // shapeless/LabelledGeneric.to:(Ljava/lang/Object;)Ljava/lang/Object;
   #82 = Utf8               shapeless/HList
   #83 = Class              #82           // shapeless/HList
   #84 = Utf8               Ljava/lang/Object;
   #85 = Utf8               underlying$3
   #86 = Utf8               defaults$1
   #87 = Utf8               productCodec
   #88 = Utf8               shapeless/Lazy
   #89 = Class              #88           // shapeless/Lazy
   #90 = Utf8               value
   #91 = Utf8               ()Ljava/lang/Object;
   #92 = NameAndType        #90:#91       // value:()Ljava/lang/Object;
   #93 = InterfaceMethodref #89.#92       // shapeless/Lazy.value:()Ljava/lang/Object;
   #94 = Utf8               argonaut/derive/HListProductEncodeJson
   #95 = Class              #94           // argonaut/derive/HListProductEncodeJson
   #96 = NameAndType        #27:#91       // apply:()Ljava/lang/Object;
   #97 = InterfaceMethodref #14.#96       // shapeless/Default$AsOptions.apply:()Ljava/lang/Object;
   #98 = Utf8               (Largonaut/derive/JsonProductCodec;Lshapeless/HList;)Largonaut/EncodeJson;
   #99 = NameAndType        #27:#98       // apply:(Largonaut/derive/JsonProductCodec;Lshapeless/HList;)Largonaut/EncodeJson;
  #100 = InterfaceMethodref #95.#99       // argonaut/derive/HListProductEncodeJson.apply:(Largonaut/derive/JsonProductCodec;Lshapeless/HList;)Largonaut/EncodeJson;
  #101 = NameAndType        #73:#74       // $anonfun$generic$2:(Lshapeless/LabelledGeneric;Ljava/lang/Object;)Lshapeless/HList;
  #102 = Methodref          #2.#101       // argonaut/derive/ProductEncodeJson$.$anonfun$generic$2:(Lshapeless/LabelledGeneric;Ljava/lang/Object;)Lshapeless/HList;
  #103 = MethodHandle       6:#102        // REF_invokeStatic argonaut/derive/ProductEncodeJson$.$anonfun$generic$2:(Lshapeless/LabelledGeneric;Ljava/lang/Object;)Lshapeless/HList;
  #104 = Utf8               (Ljava/lang/Object;)Lshapeless/HList;
  #105 = MethodType         #104          //  (Ljava/lang/Object;)Lshapeless/HList;
  #106 = Utf8               (Lshapeless/LabelledGeneric;)Lscala/Function1;
  #107 = NameAndType        #27:#106      // apply:(Lshapeless/LabelledGeneric;)Lscala/Function1;
  #108 = InvokeDynamic      #1:#107       // #1:apply:(Lshapeless/LabelledGeneric;)Lscala/Function1;
  #109 = Utf8               argonaut/EncodeJson
  #110 = Class              #109          // argonaut/EncodeJson
  #111 = Utf8               contramap
  #112 = Utf8               (Lscala/Function1;)Largonaut/EncodeJson;
  #113 = NameAndType        #111:#112     // contramap:(Lscala/Function1;)Largonaut/EncodeJson;
  #114 = InterfaceMethodref #110.#113     // argonaut/EncodeJson.contramap:(Lscala/Function1;)Largonaut/EncodeJson;
  #115 = Utf8               Largonaut/derive/JsonProductCodec;
  #116 = Methodref          #4.#23        // java/lang/Object."<init>":()V
  #117 = Utf8               $deserializeLambda$
  #118 = Utf8               (Ljava/lang/invoke/SerializedLambda;)Ljava/lang/Object;
  #119 = Utf8               scala/runtime/LambdaDeserialize
  #120 = Class              #119          // scala/runtime/LambdaDeserialize
  #121 = Utf8               bootstrap
  #122 = Utf8               (Ljava/lang/invoke/MethodHandles$Lookup;Ljava/lang/String;Ljava/lang/invoke/MethodType;[Ljava/lang/invoke/MethodHandle;)Ljava/lang/invoke/CallSite;
  #123 = NameAndType        #121:#122     // bootstrap:(Ljava/lang/invoke/MethodHandles$Lookup;Ljava/lang/String;Ljava/lang/invoke/MethodType;[Ljava/lang/invoke/MethodHandle;)Ljava/lang/invoke/CallSite;
  #124 = Methodref          #120.#123     // scala/runtime/LambdaDeserialize.bootstrap:(Ljava/lang/invoke/MethodHandles$Lookup;Ljava/lang/String;Ljava/lang/invoke/MethodType;[Ljava/lang/invoke/MethodHandle;)Ljava/lang/invoke/CallSite;
  #125 = MethodHandle       6:#124        // REF_invokeStatic scala/runtime/LambdaDeserialize.bootstrap:(Ljava/lang/invoke/MethodHandles$Lookup;Ljava/lang/String;Ljava/lang/invoke/MethodType;[Ljava/lang/invoke/MethodHandle;)Ljava/lang/invoke/CallSite;
  #126 = Utf8               lambdaDeserialize
  #127 = NameAndType        #126:#118     // lambdaDeserialize:(Ljava/lang/invoke/SerializedLambda;)Ljava/lang/Object;
  #128 = InvokeDynamic      #2:#127       // #2:lambdaDeserialize:(Ljava/lang/invoke/SerializedLambda;)Ljava/lang/Object;
  #129 = Utf8               Code
  #130 = Utf8               LineNumberTable
  #131 = Utf8               LocalVariableTable
  #132 = Utf8               Signature
  #133 = Utf8               MethodParameters
  #134 = Utf8               InnerClasses
  #135 = Utf8               SourceFile
  #136 = Utf8               BootstrapMethods
  #137 = Utf8               ScalaInlineInfo
  #138 = Utf8               Scala
{
  public static final argonaut.derive.ProductEncodeJson$ MODULE$;
    descriptor: Largonaut/derive/ProductEncodeJson$;
    flags: (0x0019) ACC_PUBLIC, ACC_STATIC, ACC_FINAL

  public static {};
    descriptor: ()V
    flags: (0x0009) ACC_PUBLIC, ACC_STATIC
    Code:
      stack=2, locals=0, args_size=0
         0: new           #2                  // class argonaut/derive/ProductEncodeJson$
         3: dup
         4: invokespecial #24                 // Method "<init>":()V
         7: putstatic     #26                 // Field MODULE$:Largonaut/derive/ProductEncodeJson$;
        10: return
      LineNumberTable:
        line 37: 0

  public <P extends java.lang.Object> argonaut.derive.ProductEncodeJson<P> apply(argonaut.derive.ProductEncodeJson<P>);
    descriptor: (Largonaut/derive/ProductEncodeJson;)Largonaut/derive/ProductEncodeJson;
    flags: (0x0001) ACC_PUBLIC
    Code:
      stack=1, locals=2, args_size=2
         0: aload_1
         1: areturn
      LineNumberTable:
        line 38: 0
      LocalVariableTable:
        Start  Length  Slot  Name   Signature
            0       2     0  this   Largonaut/derive/ProductEncodeJson$;
            0       2     1 encodeJson   Largonaut/derive/ProductEncodeJson;
    Signature: #29                          // <P:Ljava/lang/Object;>(Largonaut/derive/ProductEncodeJson<TP;>;)Largonaut/derive/ProductEncodeJson<TP;>;
    MethodParameters:
      Name                           Flags
      encodeJson                     final

  public <P extends java.lang.Object> argonaut.derive.ProductEncodeJson<P> instance(scala.Function1<argonaut.derive.JsonProductCodec, argonaut.EncodeJson<P>>);
    descriptor: (Lscala/Function1;)Largonaut/derive/ProductEncodeJson;
    flags: (0x0001) ACC_PUBLIC
    Code:
      stack=3, locals=2, args_size=2
         0: new           #7                  // class argonaut/derive/ProductEncodeJson$$anon$3
         3: dup
         4: aload_1
         5: invokespecial #39                 // Method argonaut/derive/ProductEncodeJson$$anon$3."<init>":(Lscala/Function1;)V
         8: areturn
      LineNumberTable:
        line 41: 0
      LocalVariableTable:
        Start  Length  Slot  Name   Signature
            0       9     0  this   Largonaut/derive/ProductEncodeJson$;
            0       9     1     f   Lscala/Function1;
    Signature: #35                          // <P:Ljava/lang/Object;>(Lscala/Function1<Largonaut/derive/JsonProductCodec;Largonaut/EncodeJson<TP;>;>;)Largonaut/derive/ProductEncodeJson<TP;>;
    MethodParameters:
      Name                           Flags
      f                              final

  public <P extends java.lang.Object, L extends shapeless.HList, D extends shapeless.HList> argonaut.derive.ProductEncodeJson<P> generic(shapeless.LabelledGeneric<P>, shapeless.Default$AsOptions<P>, shapeless.Lazy<argonaut.derive.HListProductEncodeJson<L, D>>);
    descriptor: (Lshapeless/LabelledGeneric;Lshapeless/Default$AsOptions;Lshapeless/Lazy;)Largonaut/derive/ProductEncodeJson;
    flags: (0x0001) ACC_PUBLIC
    Code:
      stack=4, locals=4, args_size=4
         0: aload_0
         1: aload_3
         2: aload_2
         3: aload_1
         4: invokedynamic #67,  0             // InvokeDynamic #0:apply:(Lshapeless/Lazy;Lshapeless/Default$AsOptions;Lshapeless/LabelledGeneric;)Lscala/Function1;
         9: invokevirtual #69                 // Method instance:(Lscala/Function1;)Largonaut/derive/ProductEncodeJson;
        12: areturn
      LineNumberTable:
        line 61: 0
      LocalVariableTable:
        Start  Length  Slot  Name   Signature
            0      13     0  this   Largonaut/derive/ProductEncodeJson$;
            0      13     1   gen   Lshapeless/LabelledGeneric;
            0      13     2 defaults   Lshapeless/Default$AsOptions;
            0      13     3 underlying   Lshapeless/Lazy;
    Signature: #43                          // <P:Ljava/lang/Object;L::Lshapeless/HList;D::Lshapeless/HList;>(Lshapeless/LabelledGeneric<TP;>;Lshapeless/Default$AsOptions<TP;>;Lshapeless/Lazy<Largonaut/derive/HListProductEncodeJson<TL;TD;>;>;)Largonaut/derive/ProductEncodeJson<TP;>;
    MethodParameters:
      Name                           Flags
      gen                            final
      defaults                       final
      underlying                     final

  public static final shapeless.HList $anonfun$generic$2(shapeless.LabelledGeneric, java.lang.Object);
    descriptor: (Lshapeless/LabelledGeneric;Ljava/lang/Object;)Lshapeless/HList;
    flags: (0x1019) ACC_PUBLIC, ACC_STATIC, ACC_FINAL, ACC_SYNTHETIC
    Code:
      stack=2, locals=2, args_size=2
         0: aload_0
         1: aload_1
         2: invokeinterface #81,  2           // InterfaceMethod shapeless/LabelledGeneric.to:(Ljava/lang/Object;)Ljava/lang/Object;
         7: checkcast     #83                 // class shapeless/HList
        10: areturn
      LineNumberTable:
        line 63: 0
      LocalVariableTable:
        Start  Length  Slot  Name   Signature
            0      11     0 gen$1   Lshapeless/LabelledGeneric;
            0      11     1     t   Ljava/lang/Object;
    MethodParameters:
      Name                           Flags
      gen$1                          final
      t                              final

  public static final argonaut.EncodeJson $anonfun$generic$1(shapeless.Lazy, shapeless.Default$AsOptions, shapeless.LabelledGeneric, argonaut.derive.JsonProductCodec);
    descriptor: (Lshapeless/Lazy;Lshapeless/Default$AsOptions;Lshapeless/LabelledGeneric;Largonaut/derive/JsonProductCodec;)Largonaut/EncodeJson;
    flags: (0x1019) ACC_PUBLIC, ACC_STATIC, ACC_FINAL, ACC_SYNTHETIC
    Code:
      stack=3, locals=4, args_size=4
         0: aload_0
         1: invokeinterface #93,  1           // InterfaceMethod shapeless/Lazy.value:()Ljava/lang/Object;
         6: checkcast     #95                 // class argonaut/derive/HListProductEncodeJson
         9: aload_3
        10: aload_1
        11: invokeinterface #97,  1           // InterfaceMethod shapeless/Default$AsOptions.apply:()Ljava/lang/Object;
        16: checkcast     #83                 // class shapeless/HList
        19: invokeinterface #100,  3          // InterfaceMethod argonaut/derive/HListProductEncodeJson.apply:(Largonaut/derive/JsonProductCodec;Lshapeless/HList;)Largonaut/EncodeJson;
        24: aload_2
        25: invokedynamic #108,  0            // InvokeDynamic #1:apply:(Lshapeless/LabelledGeneric;)Lscala/Function1;
        30: invokeinterface #114,  2          // InterfaceMethod argonaut/EncodeJson.contramap:(Lscala/Function1;)Largonaut/EncodeJson;
        35: areturn
      LineNumberTable:
        line 62: 0
        line 63: 24
      LocalVariableTable:
        Start  Length  Slot  Name   Signature
            0      36     0 underlying$3   Lshapeless/Lazy;
            0      36     1 defaults$1   Lshapeless/Default$AsOptions;
            0      36     2 gen$1   Lshapeless/LabelledGeneric;
            0      36     3 productCodec   Largonaut/derive/JsonProductCodec;
    MethodParameters:
      Name                           Flags
      underlying$3                   final
      defaults$1                     final
      gen$1                          final
      productCodec                   final

  private argonaut.derive.ProductEncodeJson$();
    descriptor: ()V
    flags: (0x0002) ACC_PRIVATE
    Code:
      stack=1, locals=1, args_size=1
         0: aload_0
         1: invokespecial #116                // Method java/lang/Object."<init>":()V
         4: return
      LineNumberTable:
        line 67: 0
        line 37: 4
      LocalVariableTable:
        Start  Length  Slot  Name   Signature
            0       5     0  this   Largonaut/derive/ProductEncodeJson$;

  private static java.lang.Object $deserializeLambda$(java.lang.invoke.SerializedLambda);
    descriptor: (Ljava/lang/invoke/SerializedLambda;)Ljava/lang/Object;
    flags: (0x100a) ACC_PRIVATE, ACC_STATIC, ACC_SYNTHETIC
    Code:
      stack=1, locals=1, args_size=1
         0: aload_0
         1: invokedynamic #128,  0            // InvokeDynamic #2:lambdaDeserialize:(Ljava/lang/invoke/SerializedLambda;)Ljava/lang/Object;
         6: areturn
}
InnerClasses:
  public final #7;                        // class argonaut/derive/ProductEncodeJson$$anon$3
  public static final #12= #9 of #11;     // Lookup=class java/lang/invoke/MethodHandles$Lookup of class java/lang/invoke/MethodHandles
  public static #17= #14 of #16;          // AsOptions=class shapeless/Default$AsOptions of class shapeless/Default
SourceFile: "MkEncodeJson.scala"
BootstrapMethods:
  0: #64 REF_invokeStatic java/lang/invoke/LambdaMetafactory.altMetafactory:(Ljava/lang/invoke/MethodHandles$Lookup;Ljava/lang/String;Ljava/lang/invoke/MethodType;[Ljava/lang/Object;)Ljava/lang/invoke/CallSite;
    Method arguments:
      #48 (Ljava/lang/Object;)Ljava/lang/Object;
      #53 REF_invokeStatic argonaut/derive/ProductEncodeJson$.$anonfun$generic$1:(Lshapeless/Lazy;Lshapeless/Default$AsOptions;Lshapeless/LabelledGeneric;Largonaut/derive/JsonProductCodec;)Largonaut/EncodeJson;
      #55 (Largonaut/derive/JsonProductCodec;)Largonaut/EncodeJson;
      #56 5
      #57 1
      #55 (Largonaut/derive/JsonProductCodec;)Largonaut/EncodeJson;
  1: #64 REF_invokeStatic java/lang/invoke/LambdaMetafactory.altMetafactory:(Ljava/lang/invoke/MethodHandles$Lookup;Ljava/lang/String;Ljava/lang/invoke/MethodType;[Ljava/lang/Object;)Ljava/lang/invoke/CallSite;
    Method arguments:
      #48 (Ljava/lang/Object;)Ljava/lang/Object;
      #103 REF_invokeStatic argonaut/derive/ProductEncodeJson$.$anonfun$generic$2:(Lshapeless/LabelledGeneric;Ljava/lang/Object;)Lshapeless/HList;
      #105 (Ljava/lang/Object;)Lshapeless/HList;
      #56 5
      #57 1
      #105 (Ljava/lang/Object;)Lshapeless/HList;
  2: #125 REF_invokeStatic scala/runtime/LambdaDeserialize.bootstrap:(Ljava/lang/invoke/MethodHandles$Lookup;Ljava/lang/String;Ljava/lang/invoke/MethodType;[Ljava/lang/invoke/MethodHandle;)Ljava/lang/invoke/CallSite;
    Method arguments:
      #53 REF_invokeStatic argonaut/derive/ProductEncodeJson$.$anonfun$generic$1:(Lshapeless/Lazy;Lshapeless/Default$AsOptions;Lshapeless/LabelledGeneric;Largonaut/derive/JsonProductCodec;)Largonaut/EncodeJson;
      #103 REF_invokeStatic argonaut/derive/ProductEncodeJson$.$anonfun$generic$2:(Lshapeless/LabelledGeneric;Ljava/lang/Object;)Lshapeless/HList;
  ScalaInlineInfo: length = 0x22 (unknown attribute)
   01 01 00 06 00 31 00 32 01 00 49 00 4A 01 00 16
   00 15 01 00 1B 00 1C 01 00 29 00 2A 01 00 21 00
   22 01
  Scala: length = 0x0 (unknown attribute)

