Classfile /Users/mw/Projects/slang-braindump/.jar/jar11/assemble/slang-braindump/assemble/content/argonaut/derive/SingletonInstances.class
  Last modified May 29, 2022; size 5579 bytes
  SHA-256 checksum d69b76227915742d0a63fcdda6c58fe769c1e6d54c86127e3b57e5cde4e21f16
  Compiled from "Instances.scala"
public interface argonaut.derive.SingletonInstances
  minor version: 0
  major version: 52
  flags: (0x0601) ACC_PUBLIC, ACC_INTERFACE, ACC_ABSTRACT
  this_class: #2                          // argonaut/derive/SingletonInstances
  super_class: #4                         // java/lang/Object
  interfaces: 0, fields: 0, methods: 9, attributes: 6
Constant pool:
    #1 = Utf8               argonaut/derive/SingletonInstances
    #2 = Class              #1            // argonaut/derive/SingletonInstances
    #3 = Utf8               java/lang/Object
    #4 = Class              #3            // java/lang/Object
    #5 = Utf8               Instances.scala
    #6 = Utf8               Lscala/reflect/ScalaSignature;
    #7 = Utf8               bytes
    #8 = Utf8               \u0006\u0005Q3q\u0001B\u0003\u0011\u0002\u0007\u0005!\u0002C\u0003\u0012\u0001\u0011\u0005!\u0003C\u0003\u0017\u0001\u0011\rq\u0003C\u0003D\u0001\u0011\rAI\u0001\nTS:<G.\u001a;p]&s7\u000f^1oG\u0016\u001c(B\u0001\u0004\b\u0003\u0019!WM]5wK*\t\u0001\"\u0001\u0005be\u001e|g.Y;u\u0007\u0001\u0019\"\u0001A\u0006\u0011\u00051yQ\"A\u0007\u000b\u00039\tQa]2bY\u0006L!\u0001E\u0007\u0003\r\u0005s\u0017PU3g\u0003\u0019!\u0013N\\5uIQ\t1\u0003\u0005\u0002\r)%\u0011Q#\u0004\u0002\u0005+:LG/A\ftS:<G.\u001a;p]RK\b/Z#oG>$WMS:p]V\u0019\u0001dH\u001f\u0015\teAC\u0007\u0011\t\u00045miR\"A\u0004\n\u0005q9!AC#oG>$WMS:p]B\u0011ad\b\u0007\u0001\t\u0015\u0001#A1\u0001\"\u0005\u0005\u0019\u0016C\u0001\u0012&!\ta1%\u0003\u0002%\u001b\t9aj\u001c;iS:<\u0007C\u0001\u0007\'\u0013\t9SBA\u0002B]fDQ!\u000b\u0002A\u0004)\n\u0011a\u001e\t\u0004WEjbB\u0001\u00170\u001b\u0005i#\"\u0001\u0018\u0002\u0013MD\u0017\r]3mKN\u001c\u0018B\u0001\u0019.\u0003\u001d9\u0016\u000e\u001e8fgNL!AM\u001a\u0003\u0007\u0005+\bP\u0003\u00021[!)QG\u0001a\u0002m\u0005)q/\u001b3f]B!qGO\u000f=\u001d\ta\u0003(\u0003\u0002:[\u0005)q+\u001b3f]&\u0011!g\u000f\u0006\u0003s5\u0002\"AH\u001f\u0005\u000by\u0012!\u0019A \u0003\u0003]\u000b\"!H\u0013\t\u000b\u0005\u0013\u00019\u0001\"\u0002\u0015UtG-\u001a:ms&tw\rE\u0002\u001b7q\nqc]5oO2,Go\u001c8UsB,G)Z2pI\u0016T5o\u001c8\u0016\u0007\u0015S\u0005\u000b\u0006\u0003G\u00176\u0013\u0006c\u0001\u000eH\u0013&\u0011\u0001j\u0002\u0002\u000b\t\u0016\u001cw\u000eZ3Kg>t\u0007C\u0001\u0010K\t\u0015\u00013A1\u0001\"\u0011\u0015I3\u0001q\u0001M!\rY\u0013\'\u0013\u0005\u0006k\r\u0001\u001dA\u0014\t\u0005oiJu\n\u0005\u0002\u001f!\u0012)ah\u0001b\u0001#F\u0011\u0011*\n\u0005\u0006\u0003\u000e\u0001\u001da\u0015\t\u00045\u001d{\u0005
    #9 = Utf8               java/lang/invoke/MethodHandles$Lookup
   #10 = Class              #9            // java/lang/invoke/MethodHandles$Lookup
   #11 = Utf8               java/lang/invoke/MethodHandles
   #12 = Class              #11           // java/lang/invoke/MethodHandles
   #13 = Utf8               Lookup
   #14 = Utf8               singletonTypeEncodeJson$
   #15 = Utf8               (Largonaut/derive/SingletonInstances;Lshapeless/Witness;Lshapeless/Widen;Largonaut/EncodeJson;)Largonaut/EncodeJson;
   #16 = Utf8               $this
   #17 = Utf8               w
   #18 = Utf8               widen
   #19 = Utf8               underlying
   #20 = Utf8               singletonTypeEncodeJson
   #21 = Utf8               (Lshapeless/Witness;Lshapeless/Widen;Largonaut/EncodeJson;)Largonaut/EncodeJson;
   #22 = NameAndType        #20:#21       // singletonTypeEncodeJson:(Lshapeless/Witness;Lshapeless/Widen;Largonaut/EncodeJson;)Largonaut/EncodeJson;
   #23 = InterfaceMethodref #2.#22        // argonaut/derive/SingletonInstances.singletonTypeEncodeJson:(Lshapeless/Witness;Lshapeless/Widen;Largonaut/EncodeJson;)Largonaut/EncodeJson;
   #24 = Utf8               Largonaut/derive/SingletonInstances;
   #25 = Utf8               Lshapeless/Witness;
   #26 = Utf8               Lshapeless/Widen;
   #27 = Utf8               Largonaut/EncodeJson;
   #28 = Utf8               <S:Ljava/lang/Object;W:Ljava/lang/Object;>(Lshapeless/Witness;Lshapeless/Widen<TS;>;Largonaut/EncodeJson<TW;>;)Largonaut/EncodeJson<TS;>;
   #29 = Utf8               (Ljava/lang/Object;)Ljava/lang/Object;
   #30 = MethodType         #29           //  (Ljava/lang/Object;)Ljava/lang/Object;
   #31 = Utf8               $anonfun$singletonTypeEncodeJson$1
   #32 = Utf8               (Lshapeless/Widen;Ljava/lang/Object;)Ljava/lang/Object;
   #33 = NameAndType        #31:#32       // $anonfun$singletonTypeEncodeJson$1:(Lshapeless/Widen;Ljava/lang/Object;)Ljava/lang/Object;
   #34 = InterfaceMethodref #2.#33        // argonaut/derive/SingletonInstances.$anonfun$singletonTypeEncodeJson$1:(Lshapeless/Widen;Ljava/lang/Object;)Ljava/lang/Object;
   #35 = MethodHandle       6:#34         // REF_invokeStatic argonaut/derive/SingletonInstances.$anonfun$singletonTypeEncodeJson$1:(Lshapeless/Widen;Ljava/lang/Object;)Ljava/lang/Object;
   #36 = Integer            1
   #37 = Utf8               java/lang/invoke/LambdaMetafactory
   #38 = Class              #37           // java/lang/invoke/LambdaMetafactory
   #39 = Utf8               altMetafactory
   #40 = Utf8               (Ljava/lang/invoke/MethodHandles$Lookup;Ljava/lang/String;Ljava/lang/invoke/MethodType;[Ljava/lang/Object;)Ljava/lang/invoke/CallSite;
   #41 = NameAndType        #39:#40       // altMetafactory:(Ljava/lang/invoke/MethodHandles$Lookup;Ljava/lang/String;Ljava/lang/invoke/MethodType;[Ljava/lang/Object;)Ljava/lang/invoke/CallSite;
   #42 = Methodref          #38.#41       // java/lang/invoke/LambdaMetafactory.altMetafactory:(Ljava/lang/invoke/MethodHandles$Lookup;Ljava/lang/String;Ljava/lang/invoke/MethodType;[Ljava/lang/Object;)Ljava/lang/invoke/CallSite;
   #43 = MethodHandle       6:#42         // REF_invokeStatic java/lang/invoke/LambdaMetafactory.altMetafactory:(Ljava/lang/invoke/MethodHandles$Lookup;Ljava/lang/String;Ljava/lang/invoke/MethodType;[Ljava/lang/Object;)Ljava/lang/invoke/CallSite;
   #44 = Utf8               apply
   #45 = Utf8               (Lshapeless/Widen;)Lscala/Function1;
   #46 = NameAndType        #44:#45       // apply:(Lshapeless/Widen;)Lscala/Function1;
   #47 = InvokeDynamic      #0:#46        // #0:apply:(Lshapeless/Widen;)Lscala/Function1;
   #48 = Utf8               argonaut/EncodeJson
   #49 = Class              #48           // argonaut/EncodeJson
   #50 = Utf8               contramap
   #51 = Utf8               (Lscala/Function1;)Largonaut/EncodeJson;
   #52 = NameAndType        #50:#51       // contramap:(Lscala/Function1;)Largonaut/EncodeJson;
   #53 = InterfaceMethodref #49.#52       // argonaut/EncodeJson.contramap:(Lscala/Function1;)Largonaut/EncodeJson;
   #54 = Utf8               this
   #55 = Utf8               singletonTypeDecodeJson$
   #56 = Utf8               (Largonaut/derive/SingletonInstances;Lshapeless/Witness;Lshapeless/Widen;Largonaut/DecodeJson;)Largonaut/DecodeJson;
   #57 = Utf8               singletonTypeDecodeJson
   #58 = Utf8               (Lshapeless/Witness;Lshapeless/Widen;Largonaut/DecodeJson;)Largonaut/DecodeJson;
   #59 = NameAndType        #57:#58       // singletonTypeDecodeJson:(Lshapeless/Witness;Lshapeless/Widen;Largonaut/DecodeJson;)Largonaut/DecodeJson;
   #60 = InterfaceMethodref #2.#59        // argonaut/derive/SingletonInstances.singletonTypeDecodeJson:(Lshapeless/Witness;Lshapeless/Widen;Largonaut/DecodeJson;)Largonaut/DecodeJson;
   #61 = Utf8               Largonaut/DecodeJson;
   #62 = Utf8               <S:Ljava/lang/Object;W:Ljava/lang/Object;>(Lshapeless/Witness;Lshapeless/Widen<TS;>;Largonaut/DecodeJson<TW;>;)Largonaut/DecodeJson<TS;>;
   #63 = Utf8               argonaut/DecodeJson$
   #64 = Class              #63           // argonaut/DecodeJson$
   #65 = Utf8               MODULE$
   #66 = Utf8               Largonaut/DecodeJson$;
   #67 = NameAndType        #65:#66       // MODULE$:Largonaut/DecodeJson$;
   #68 = Fieldref           #64.#67       // argonaut/DecodeJson$.MODULE$:Largonaut/DecodeJson$;
   #69 = Utf8               $anonfun$singletonTypeDecodeJson$1
   #70 = Utf8               (Largonaut/DecodeJson;Lshapeless/Witness;Largonaut/HCursor;)Largonaut/DecodeResult;
   #71 = NameAndType        #69:#70       // $anonfun$singletonTypeDecodeJson$1:(Largonaut/DecodeJson;Lshapeless/Witness;Largonaut/HCursor;)Largonaut/DecodeResult;
   #72 = InterfaceMethodref #2.#71        // argonaut/derive/SingletonInstances.$anonfun$singletonTypeDecodeJson$1:(Largonaut/DecodeJson;Lshapeless/Witness;Largonaut/HCursor;)Largonaut/DecodeResult;
   #73 = MethodHandle       6:#72         // REF_invokeStatic argonaut/derive/SingletonInstances.$anonfun$singletonTypeDecodeJson$1:(Largonaut/DecodeJson;Lshapeless/Witness;Largonaut/HCursor;)Largonaut/DecodeResult;
   #74 = Utf8               (Largonaut/HCursor;)Largonaut/DecodeResult;
   #75 = MethodType         #74           //  (Largonaut/HCursor;)Largonaut/DecodeResult;
   #76 = Integer            5
   #77 = Utf8               (Largonaut/DecodeJson;Lshapeless/Witness;)Lscala/Function1;
   #78 = NameAndType        #44:#77       // apply:(Largonaut/DecodeJson;Lshapeless/Witness;)Lscala/Function1;
   #79 = InvokeDynamic      #1:#78        // #1:apply:(Largonaut/DecodeJson;Lshapeless/Witness;)Lscala/Function1;
   #80 = Utf8               (Lscala/Function1;)Largonaut/DecodeJson;
   #81 = NameAndType        #44:#80       // apply:(Lscala/Function1;)Largonaut/DecodeJson;
   #82 = Methodref          #64.#81       // argonaut/DecodeJson$.apply:(Lscala/Function1;)Largonaut/DecodeJson;
   #83 = Utf8               widen$1
   #84 = Utf8               t
   #85 = Utf8               shapeless/Widen
   #86 = Class              #85           // shapeless/Widen
   #87 = NameAndType        #44:#29       // apply:(Ljava/lang/Object;)Ljava/lang/Object;
   #88 = InterfaceMethodref #86.#87       // shapeless/Widen.apply:(Ljava/lang/Object;)Ljava/lang/Object;
   #89 = Utf8               Ljava/lang/Object;
   #90 = Utf8               $anonfun$singletonTypeDecodeJson$2
   #91 = Utf8               (Lshapeless/Witness;Largonaut/HCursor;Ljava/lang/Object;)Largonaut/DecodeResult;
   #92 = Utf8               w$1
   #93 = Utf8               c$1
   #94 = Utf8               w0
   #95 = Utf8               shapeless/Witness
   #96 = Class              #95           // shapeless/Witness
   #97 = Utf8               value
   #98 = Utf8               ()Ljava/lang/Object;
   #99 = NameAndType        #97:#98       // value:()Ljava/lang/Object;
  #100 = InterfaceMethodref #96.#99       // shapeless/Witness.value:()Ljava/lang/Object;
  #101 = Utf8               scala/runtime/BoxesRunTime
  #102 = Class              #101          // scala/runtime/BoxesRunTime
  #103 = Utf8               equals
  #104 = Utf8               (Ljava/lang/Object;Ljava/lang/Object;)Z
  #105 = NameAndType        #103:#104     // equals:(Ljava/lang/Object;Ljava/lang/Object;)Z
  #106 = Methodref          #102.#105     // scala/runtime/BoxesRunTime.equals:(Ljava/lang/Object;Ljava/lang/Object;)Z
  #107 = Utf8               argonaut/DecodeResult$
  #108 = Class              #107          // argonaut/DecodeResult$
  #109 = Utf8               Largonaut/DecodeResult$;
  #110 = NameAndType        #65:#109      // MODULE$:Largonaut/DecodeResult$;
  #111 = Fieldref           #108.#110     // argonaut/DecodeResult$.MODULE$:Largonaut/DecodeResult$;
  #112 = Utf8               ok
  #113 = Utf8               (Ljava/lang/Object;)Largonaut/DecodeResult;
  #114 = NameAndType        #112:#113     // ok:(Ljava/lang/Object;)Largonaut/DecodeResult;
  #115 = Methodref          #108.#114     // argonaut/DecodeResult$.ok:(Ljava/lang/Object;)Largonaut/DecodeResult;
  #116 = Utf8               java/lang/StringBuilder
  #117 = Class              #116          // java/lang/StringBuilder
  #118 = Integer            15
  #119 = Utf8               <init>
  #120 = Utf8               (I)V
  #121 = NameAndType        #119:#120     // "<init>":(I)V
  #122 = Methodref          #117.#121     // java/lang/StringBuilder."<init>":(I)V
  #123 = Utf8               Expected
  #124 = String             #123          // Expected
  #125 = Utf8               append
  #126 = Utf8               (Ljava/lang/String;)Ljava/lang/StringBuilder;
  #127 = NameAndType        #125:#126     // append:(Ljava/lang/String;)Ljava/lang/StringBuilder;
  #128 = Methodref          #117.#127     // java/lang/StringBuilder.append:(Ljava/lang/String;)Ljava/lang/StringBuilder;
  #129 = Utf8               (Ljava/lang/Object;)Ljava/lang/StringBuilder;
  #130 = NameAndType        #125:#129     // append:(Ljava/lang/Object;)Ljava/lang/StringBuilder;
  #131 = Methodref          #117.#130     // java/lang/StringBuilder.append:(Ljava/lang/Object;)Ljava/lang/StringBuilder;
  #132 = Utf8               , got
  #133 = String             #132          // , got
  #134 = Utf8               toString
  #135 = Utf8               ()Ljava/lang/String;
  #136 = NameAndType        #134:#135     // toString:()Ljava/lang/String;
  #137 = Methodref          #117.#136     // java/lang/StringBuilder.toString:()Ljava/lang/String;
  #138 = Utf8               argonaut/HCursor
  #139 = Class              #138          // argonaut/HCursor
  #140 = Utf8               history
  #141 = Utf8               ()Largonaut/CursorHistory;
  #142 = NameAndType        #140:#141     // history:()Largonaut/CursorHistory;
  #143 = Methodref          #139.#142     // argonaut/HCursor.history:()Largonaut/CursorHistory;
  #144 = Utf8               fail
  #145 = Utf8               (Ljava/lang/String;Largonaut/CursorHistory;)Largonaut/DecodeResult;
  #146 = NameAndType        #144:#145     // fail:(Ljava/lang/String;Largonaut/CursorHistory;)Largonaut/DecodeResult;
  #147 = Methodref          #108.#146     // argonaut/DecodeResult$.fail:(Ljava/lang/String;Largonaut/CursorHistory;)Largonaut/DecodeResult;
  #148 = Utf8               Largonaut/HCursor;
  #149 = Utf8               argonaut/DecodeResult
  #150 = Class              #149          // argonaut/DecodeResult
  #151 = Utf8               underlying$1
  #152 = Utf8               c
  #153 = Utf8               argonaut/DecodeJson
  #154 = Class              #153          // argonaut/DecodeJson
  #155 = Utf8               decode
  #156 = NameAndType        #155:#74      // decode:(Largonaut/HCursor;)Largonaut/DecodeResult;
  #157 = InterfaceMethodref #154.#156     // argonaut/DecodeJson.decode:(Largonaut/HCursor;)Largonaut/DecodeResult;
  #158 = NameAndType        #90:#91       // $anonfun$singletonTypeDecodeJson$2:(Lshapeless/Witness;Largonaut/HCursor;Ljava/lang/Object;)Largonaut/DecodeResult;
  #159 = InterfaceMethodref #2.#158       // argonaut/derive/SingletonInstances.$anonfun$singletonTypeDecodeJson$2:(Lshapeless/Witness;Largonaut/HCursor;Ljava/lang/Object;)Largonaut/DecodeResult;
  #160 = MethodHandle       6:#159        // REF_invokeStatic argonaut/derive/SingletonInstances.$anonfun$singletonTypeDecodeJson$2:(Lshapeless/Witness;Largonaut/HCursor;Ljava/lang/Object;)Largonaut/DecodeResult;
  #161 = MethodType         #113          //  (Ljava/lang/Object;)Largonaut/DecodeResult;
  #162 = Utf8               (Lshapeless/Witness;Largonaut/HCursor;)Lscala/Function1;
  #163 = NameAndType        #44:#162      // apply:(Lshapeless/Witness;Largonaut/HCursor;)Lscala/Function1;
  #164 = InvokeDynamic      #2:#163       // #2:apply:(Lshapeless/Witness;Largonaut/HCursor;)Lscala/Function1;
  #165 = Utf8               flatMap
  #166 = Utf8               (Lscala/Function1;)Largonaut/DecodeResult;
  #167 = NameAndType        #165:#166     // flatMap:(Lscala/Function1;)Largonaut/DecodeResult;
  #168 = Methodref          #150.#167     // argonaut/DecodeResult.flatMap:(Lscala/Function1;)Largonaut/DecodeResult;
  #169 = Utf8               $init$
  #170 = Utf8               (Largonaut/derive/SingletonInstances;)V
  #171 = Utf8               $deserializeLambda$
  #172 = Utf8               (Ljava/lang/invoke/SerializedLambda;)Ljava/lang/Object;
  #173 = Utf8               scala/runtime/LambdaDeserialize
  #174 = Class              #173          // scala/runtime/LambdaDeserialize
  #175 = Utf8               bootstrap
  #176 = Utf8               (Ljava/lang/invoke/MethodHandles$Lookup;Ljava/lang/String;Ljava/lang/invoke/MethodType;[Ljava/lang/invoke/MethodHandle;)Ljava/lang/invoke/CallSite;
  #177 = NameAndType        #175:#176     // bootstrap:(Ljava/lang/invoke/MethodHandles$Lookup;Ljava/lang/String;Ljava/lang/invoke/MethodType;[Ljava/lang/invoke/MethodHandle;)Ljava/lang/invoke/CallSite;
  #178 = Methodref          #174.#177     // scala/runtime/LambdaDeserialize.bootstrap:(Ljava/lang/invoke/MethodHandles$Lookup;Ljava/lang/String;Ljava/lang/invoke/MethodType;[Ljava/lang/invoke/MethodHandle;)Ljava/lang/invoke/CallSite;
  #179 = MethodHandle       6:#178        // REF_invokeStatic scala/runtime/LambdaDeserialize.bootstrap:(Ljava/lang/invoke/MethodHandles$Lookup;Ljava/lang/String;Ljava/lang/invoke/MethodType;[Ljava/lang/invoke/MethodHandle;)Ljava/lang/invoke/CallSite;
  #180 = Utf8               lambdaDeserialize
  #181 = NameAndType        #180:#172     // lambdaDeserialize:(Ljava/lang/invoke/SerializedLambda;)Ljava/lang/Object;
  #182 = InvokeDynamic      #3:#181       // #3:lambdaDeserialize:(Ljava/lang/invoke/SerializedLambda;)Ljava/lang/Object;
  #183 = Utf8               Code
  #184 = Utf8               LineNumberTable
  #185 = Utf8               LocalVariableTable
  #186 = Utf8               MethodParameters
  #187 = Utf8               Signature
  #188 = Utf8               StackMapTable
  #189 = Utf8               InnerClasses
  #190 = Utf8               SourceFile
  #191 = Utf8               RuntimeVisibleAnnotations
  #192 = Utf8               BootstrapMethods
  #193 = Utf8               ScalaInlineInfo
  #194 = Utf8               ScalaSig
{
  public static argonaut.EncodeJson singletonTypeEncodeJson$(argonaut.derive.SingletonInstances, shapeless.Witness, shapeless.Widen, argonaut.EncodeJson);
    descriptor: (Largonaut/derive/SingletonInstances;Lshapeless/Witness;Lshapeless/Widen;Largonaut/EncodeJson;)Largonaut/EncodeJson;
    flags: (0x1009) ACC_PUBLIC, ACC_STATIC, ACC_SYNTHETIC
    Code:
      stack=4, locals=4, args_size=4
         0: aload_0
         1: aload_1
         2: aload_2
         3: aload_3
         4: invokespecial #23                 // InterfaceMethod singletonTypeEncodeJson:(Lshapeless/Witness;Lshapeless/Widen;Largonaut/EncodeJson;)Largonaut/EncodeJson;
         7: areturn
      LineNumberTable:
        line 9: 0
      LocalVariableTable:
        Start  Length  Slot  Name   Signature
            0       8     0 $this   Largonaut/derive/SingletonInstances;
            0       8     1     w   Lshapeless/Witness;
            0       8     2 widen   Lshapeless/Widen;
            0       8     3 underlying   Largonaut/EncodeJson;
    MethodParameters:
      Name                           Flags
      $this                          final synthetic
      w                              final
      widen                          final
      underlying                     final

  public default <S extends java.lang.Object, W extends java.lang.Object> argonaut.EncodeJson<S> singletonTypeEncodeJson(shapeless.Witness, shapeless.Widen<S>, argonaut.EncodeJson<W>);
    descriptor: (Lshapeless/Witness;Lshapeless/Widen;Largonaut/EncodeJson;)Largonaut/EncodeJson;
    flags: (0x0001) ACC_PUBLIC
    Code:
      stack=2, locals=4, args_size=4
         0: aload_3
         1: aload_2
         2: invokedynamic #47,  0             // InvokeDynamic #0:apply:(Lshapeless/Widen;)Lscala/Function1;
         7: invokeinterface #53,  2           // InterfaceMethod argonaut/EncodeJson.contramap:(Lscala/Function1;)Largonaut/EncodeJson;
        12: areturn
      LineNumberTable:
        line 15: 0
      LocalVariableTable:
        Start  Length  Slot  Name   Signature
            0      13     0  this   Largonaut/derive/SingletonInstances;
            0      13     1     w   Lshapeless/Witness;
            0      13     2 widen   Lshapeless/Widen;
            0      13     3 underlying   Largonaut/EncodeJson;
    Signature: #28                          // <S:Ljava/lang/Object;W:Ljava/lang/Object;>(Lshapeless/Witness;Lshapeless/Widen<TS;>;Largonaut/EncodeJson<TW;>;)Largonaut/EncodeJson<TS;>;
    MethodParameters:
      Name                           Flags
      w                              final
      widen                          final
      underlying                     final

  public static argonaut.DecodeJson singletonTypeDecodeJson$(argonaut.derive.SingletonInstances, shapeless.Witness, shapeless.Widen, argonaut.DecodeJson);
    descriptor: (Largonaut/derive/SingletonInstances;Lshapeless/Witness;Lshapeless/Widen;Largonaut/DecodeJson;)Largonaut/DecodeJson;
    flags: (0x1009) ACC_PUBLIC, ACC_STATIC, ACC_SYNTHETIC
    Code:
      stack=4, locals=4, args_size=4
         0: aload_0
         1: aload_1
         2: aload_2
         3: aload_3
         4: invokespecial #60                 // InterfaceMethod singletonTypeDecodeJson:(Lshapeless/Witness;Lshapeless/Widen;Largonaut/DecodeJson;)Largonaut/DecodeJson;
         7: areturn
      LineNumberTable:
        line 17: 0
      LocalVariableTable:
        Start  Length  Slot  Name   Signature
            0       8     0 $this   Largonaut/derive/SingletonInstances;
            0       8     1     w   Lshapeless/Witness;
            0       8     2 widen   Lshapeless/Widen;
            0       8     3 underlying   Largonaut/DecodeJson;
    MethodParameters:
      Name                           Flags
      $this                          final synthetic
      w                              final
      widen                          final
      underlying                     final

  public default <S extends java.lang.Object, W extends java.lang.Object> argonaut.DecodeJson<S> singletonTypeDecodeJson(shapeless.Witness, shapeless.Widen<S>, argonaut.DecodeJson<W>);
    descriptor: (Lshapeless/Witness;Lshapeless/Widen;Largonaut/DecodeJson;)Largonaut/DecodeJson;
    flags: (0x0001) ACC_PUBLIC
    Code:
      stack=3, locals=4, args_size=4
         0: getstatic     #68                 // Field argonaut/DecodeJson$.MODULE$:Largonaut/DecodeJson$;
         3: aload_3
         4: aload_1
         5: invokedynamic #79,  0             // InvokeDynamic #1:apply:(Largonaut/DecodeJson;Lshapeless/Witness;)Lscala/Function1;
        10: invokevirtual #82                 // Method argonaut/DecodeJson$.apply:(Lscala/Function1;)Largonaut/DecodeJson;
        13: areturn
      LineNumberTable:
        line 23: 0
      LocalVariableTable:
        Start  Length  Slot  Name   Signature
            0      14     0  this   Largonaut/derive/SingletonInstances;
            0      14     1     w   Lshapeless/Witness;
            0      14     2 widen   Lshapeless/Widen;
            0      14     3 underlying   Largonaut/DecodeJson;
    Signature: #62                          // <S:Ljava/lang/Object;W:Ljava/lang/Object;>(Lshapeless/Witness;Lshapeless/Widen<TS;>;Largonaut/DecodeJson<TW;>;)Largonaut/DecodeJson<TS;>;
    MethodParameters:
      Name                           Flags
      w                              final
      widen                          final
      underlying                     final

  public static java.lang.Object $anonfun$singletonTypeEncodeJson$1(shapeless.Widen, java.lang.Object);
    descriptor: (Lshapeless/Widen;Ljava/lang/Object;)Ljava/lang/Object;
    flags: (0x1009) ACC_PUBLIC, ACC_STATIC, ACC_SYNTHETIC
    Code:
      stack=2, locals=2, args_size=2
         0: aload_0
         1: aload_1
         2: invokeinterface #88,  2           // InterfaceMethod shapeless/Widen.apply:(Ljava/lang/Object;)Ljava/lang/Object;
         7: areturn
      LineNumberTable:
        line 15: 0
      LocalVariableTable:
        Start  Length  Slot  Name   Signature
            0       8     0 widen$1   Lshapeless/Widen;
            0       8     1     t   Ljava/lang/Object;
    MethodParameters:
      Name                           Flags
      widen$1                        final
      t                              final

  public static argonaut.DecodeResult $anonfun$singletonTypeDecodeJson$2(shapeless.Witness, argonaut.HCursor, java.lang.Object);
    descriptor: (Lshapeless/Witness;Largonaut/HCursor;Ljava/lang/Object;)Largonaut/DecodeResult;
    flags: (0x1009) ACC_PUBLIC, ACC_STATIC, ACC_SYNTHETIC
    Code:
      stack=4, locals=3, args_size=3
         0: aload_2
         1: aload_0
         2: invokeinterface #100,  1          // InterfaceMethod shapeless/Witness.value:()Ljava/lang/Object;
         7: invokestatic  #106                // Method scala/runtime/BoxesRunTime.equals:(Ljava/lang/Object;Ljava/lang/Object;)Z
        10: ifeq          28
        13: getstatic     #111                // Field argonaut/DecodeResult$.MODULE$:Largonaut/DecodeResult$;
        16: aload_0
        17: invokeinterface #100,  1          // InterfaceMethod shapeless/Witness.value:()Ljava/lang/Object;
        22: invokevirtual #115                // Method argonaut/DecodeResult$.ok:(Ljava/lang/Object;)Largonaut/DecodeResult;
        25: goto          73
        28: getstatic     #111                // Field argonaut/DecodeResult$.MODULE$:Largonaut/DecodeResult$;
        31: new           #117                // class java/lang/StringBuilder
        34: dup
        35: ldc           #118                // int 15
        37: invokespecial #122                // Method java/lang/StringBuilder."<init>":(I)V
        40: ldc           #124                // String Expected
        42: invokevirtual #128                // Method java/lang/StringBuilder.append:(Ljava/lang/String;)Ljava/lang/StringBuilder;
        45: aload_0
        46: invokeinterface #100,  1          // InterfaceMethod shapeless/Witness.value:()Ljava/lang/Object;
        51: invokevirtual #131                // Method java/lang/StringBuilder.append:(Ljava/lang/Object;)Ljava/lang/StringBuilder;
        54: ldc           #133                // String , got
        56: invokevirtual #128                // Method java/lang/StringBuilder.append:(Ljava/lang/String;)Ljava/lang/StringBuilder;
        59: aload_2
        60: invokevirtual #131                // Method java/lang/StringBuilder.append:(Ljava/lang/Object;)Ljava/lang/StringBuilder;
        63: invokevirtual #137                // Method java/lang/StringBuilder.toString:()Ljava/lang/String;
        66: aload_1
        67: invokevirtual #143                // Method argonaut/HCursor.history:()Largonaut/CursorHistory;
        70: invokevirtual #147                // Method argonaut/DecodeResult$.fail:(Ljava/lang/String;Largonaut/CursorHistory;)Largonaut/DecodeResult;
        73: areturn
      StackMapTable: number_of_entries = 2
        frame_type = 28 /* same */
        frame_type = 108 /* same_locals_1_stack_item */
          stack = [ class argonaut/DecodeResult ]
      LineNumberTable:
        line 25: 0
        line 26: 13
        line 28: 28
      LocalVariableTable:
        Start  Length  Slot  Name   Signature
            0      74     0   w$1   Lshapeless/Witness;
            0      74     1   c$1   Largonaut/HCursor;
            0      74     2    w0   Ljava/lang/Object;
    MethodParameters:
      Name                           Flags
      w$1                            final
      c$1                            final
      w0                             final

  public static argonaut.DecodeResult $anonfun$singletonTypeDecodeJson$1(argonaut.DecodeJson, shapeless.Witness, argonaut.HCursor);
    descriptor: (Largonaut/DecodeJson;Lshapeless/Witness;Largonaut/HCursor;)Largonaut/DecodeResult;
    flags: (0x1009) ACC_PUBLIC, ACC_STATIC, ACC_SYNTHETIC
    Code:
      stack=3, locals=3, args_size=3
         0: aload_0
         1: aload_2
         2: invokeinterface #157,  2          // InterfaceMethod argonaut/DecodeJson.decode:(Largonaut/HCursor;)Largonaut/DecodeResult;
         7: aload_1
         8: aload_2
         9: invokedynamic #164,  0            // InvokeDynamic #2:apply:(Lshapeless/Witness;Largonaut/HCursor;)Lscala/Function1;
        14: invokevirtual #168                // Method argonaut/DecodeResult.flatMap:(Lscala/Function1;)Largonaut/DecodeResult;
        17: areturn
      LineNumberTable:
        line 24: 0
      LocalVariableTable:
        Start  Length  Slot  Name   Signature
            0      18     0 underlying$1   Largonaut/DecodeJson;
            0      18     1   w$1   Lshapeless/Witness;
            0      18     2     c   Largonaut/HCursor;
    MethodParameters:
      Name                           Flags
      underlying$1                   final
      w$1                            final
      c                              final

  public static void $init$(argonaut.derive.SingletonInstances);
    descriptor: (Largonaut/derive/SingletonInstances;)V
    flags: (0x0009) ACC_PUBLIC, ACC_STATIC
    Code:
      stack=0, locals=1, args_size=1
         0: return
      LineNumberTable:
        line 7: 0
      LocalVariableTable:
        Start  Length  Slot  Name   Signature
            0       1     0 $this   Largonaut/derive/SingletonInstances;
    MethodParameters:
      Name                           Flags
      $this                          final synthetic

  private static java.lang.Object $deserializeLambda$(java.lang.invoke.SerializedLambda);
    descriptor: (Ljava/lang/invoke/SerializedLambda;)Ljava/lang/Object;
    flags: (0x100a) ACC_PRIVATE, ACC_STATIC, ACC_SYNTHETIC
    Code:
      stack=1, locals=1, args_size=1
         0: aload_0
         1: invokedynamic #182,  0            // InvokeDynamic #3:lambdaDeserialize:(Ljava/lang/invoke/SerializedLambda;)Ljava/lang/Object;
         6: areturn
}
InnerClasses:
  public static final #13= #10 of #12;    // Lookup=class java/lang/invoke/MethodHandles$Lookup of class java/lang/invoke/MethodHandles
SourceFile: "Instances.scala"
RuntimeVisibleAnnotations:
  0: #6(#7=s#8)
    scala.reflect.ScalaSignature(
      bytes="\u0006\u0005Q3q\u0001B\u0003\u0011\u0002\u0007\u0005!\u0002C\u0003\u0012\u0001\u0011\u0005!\u0003C\u0003\u0017\u0001\u0011\rq\u0003C\u0003D\u0001\u0011\rAI\u0001\nTS:<G.\u001a;p]&s7\u000f^1oG\u0016\u001c(B\u0001\u0004\b\u0003\u0019!WM]5wK*\t\u0001\"\u0001\u0005be\u001e|g.Y;u\u0007\u0001\u0019\"\u0001A\u0006\u0011\u00051yQ\"A\u0007\u000b\u00039\tQa]2bY\u0006L!\u0001E\u0007\u0003\r\u0005s\u0017PU3g\u0003\u0019!\u0013N\\5uIQ\t1\u0003\u0005\u0002\r)%\u0011Q#\u0004\u0002\u0005+:LG/A\ftS:<G.\u001a;p]RK\b/Z#oG>$WMS:p]V\u0019\u0001dH\u001f\u0015\teAC\u0007\u0011\t\u00045miR\"A\u0004\n\u0005q9!AC#oG>$WMS:p]B\u0011ad\b\u0007\u0001\t\u0015\u0001#A1\u0001\"\u0005\u0005\u0019\u0016C\u0001\u0012&!\ta1%\u0003\u0002%\u001b\t9aj\u001c;iS:<\u0007C\u0001\u0007\'\u0013\t9SBA\u0002B]fDQ!\u000b\u0002A\u0004)\n\u0011a\u001e\t\u0004WEjbB\u0001\u00170\u001b\u0005i#\"\u0001\u0018\u0002\u0013MD\u0017\r]3mKN\u001c\u0018B\u0001\u0019.\u0003\u001d9\u0016\u000e\u001e8fgNL!AM\u001a\u0003\u0007\u0005+\bP\u0003\u00021[!)QG\u0001a\u0002m\u0005)q/\u001b3f]B!qGO\u000f=\u001d\ta\u0003(\u0003\u0002:[\u0005)q+\u001b3f]&\u0011!g\u000f\u0006\u0003s5\u0002\"AH\u001f\u0005\u000by\u0012!\u0019A \u0003\u0003]\u000b\"!H\u0013\t\u000b\u0005\u0013\u00019\u0001\"\u0002\u0015UtG-\u001a:ms&tw\rE\u0002\u001b7q\nqc]5oO2,Go\u001c8UsB,G)Z2pI\u0016T5o\u001c8\u0016\u0007\u0015S\u0005\u000b\u0006\u0003G\u00176\u0013\u0006c\u0001\u000eH\u0013&\u0011\u0001j\u0002\u0002\u000b\t\u0016\u001cw\u000eZ3Kg>t\u0007C\u0001\u0010K\t\u0015\u00013A1\u0001\"\u0011\u0015I3\u0001q\u0001M!\rY\u0013\'\u0013\u0005\u0006k\r\u0001\u001dA\u0014\t\u0005oiJu\n\u0005\u0002\u001f!\u0012)ah\u0001b\u0001#F\u0011\u0011*\n\u0005\u0006\u0003\u000e\u0001\u001da\u0015\t\u00045\u001d{\u0005"
    )
BootstrapMethods:
  0: #43 REF_invokeStatic java/lang/invoke/LambdaMetafactory.altMetafactory:(Ljava/lang/invoke/MethodHandles$Lookup;Ljava/lang/String;Ljava/lang/invoke/MethodType;[Ljava/lang/Object;)Ljava/lang/invoke/CallSite;
    Method arguments:
      #30 (Ljava/lang/Object;)Ljava/lang/Object;
      #35 REF_invokeStatic argonaut/derive/SingletonInstances.$anonfun$singletonTypeEncodeJson$1:(Lshapeless/Widen;Ljava/lang/Object;)Ljava/lang/Object;
      #30 (Ljava/lang/Object;)Ljava/lang/Object;
      #36 1
  1: #43 REF_invokeStatic java/lang/invoke/LambdaMetafactory.altMetafactory:(Ljava/lang/invoke/MethodHandles$Lookup;Ljava/lang/String;Ljava/lang/invoke/MethodType;[Ljava/lang/Object;)Ljava/lang/invoke/CallSite;
    Method arguments:
      #30 (Ljava/lang/Object;)Ljava/lang/Object;
      #73 REF_invokeStatic argonaut/derive/SingletonInstances.$anonfun$singletonTypeDecodeJson$1:(Largonaut/DecodeJson;Lshapeless/Witness;Largonaut/HCursor;)Largonaut/DecodeResult;
      #75 (Largonaut/HCursor;)Largonaut/DecodeResult;
      #76 5
      #36 1
      #75 (Largonaut/HCursor;)Largonaut/DecodeResult;
  2: #43 REF_invokeStatic java/lang/invoke/LambdaMetafactory.altMetafactory:(Ljava/lang/invoke/MethodHandles$Lookup;Ljava/lang/String;Ljava/lang/invoke/MethodType;[Ljava/lang/Object;)Ljava/lang/invoke/CallSite;
    Method arguments:
      #30 (Ljava/lang/Object;)Ljava/lang/Object;
      #160 REF_invokeStatic argonaut/derive/SingletonInstances.$anonfun$singletonTypeDecodeJson$2:(Lshapeless/Witness;Largonaut/HCursor;Ljava/lang/Object;)Largonaut/DecodeResult;
      #161 (Ljava/lang/Object;)Largonaut/DecodeResult;
      #76 5
      #36 1
      #161 (Ljava/lang/Object;)Largonaut/DecodeResult;
  3: #179 REF_invokeStatic scala/runtime/LambdaDeserialize.bootstrap:(Ljava/lang/invoke/MethodHandles$Lookup;Ljava/lang/String;Ljava/lang/invoke/MethodType;[Ljava/lang/invoke/MethodHandle;)Ljava/lang/invoke/CallSite;
    Method arguments:
      #73 REF_invokeStatic argonaut/derive/SingletonInstances.$anonfun$singletonTypeDecodeJson$1:(Largonaut/DecodeJson;Lshapeless/Witness;Largonaut/HCursor;)Largonaut/DecodeResult;
      #160 REF_invokeStatic argonaut/derive/SingletonInstances.$anonfun$singletonTypeDecodeJson$2:(Lshapeless/Witness;Largonaut/HCursor;Ljava/lang/Object;)Largonaut/DecodeResult;
      #35 REF_invokeStatic argonaut/derive/SingletonInstances.$anonfun$singletonTypeEncodeJson$1:(Lshapeless/Widen;Ljava/lang/Object;)Ljava/lang/Object;
  ScalaInlineInfo: length = 0x2C (unknown attribute)
   01 00 00 08 00 45 00 46 01 00 5A 00 5B 01 00 1F
   00 20 01 00 A9 00 AA 01 00 39 00 3A 00 00 37 00
   38 01 00 14 00 15 00 00 0E 00 0F 01
  ScalaSig: length = 0x3 (unknown attribute)
   05 02 00
