Classfile /Users/mw/Projects/slang-braindump/.jar/jar11/assemble/slang-braindump/assemble/content/com/fasterxml/jackson/databind/util/Converter$None.class
  Last modified May 29, 2022; size 551 bytes
  SHA-256 checksum a7987f38b1d7a84656c009e9b3b46a40ab57f7df1ed502f8a947d2cad10bb54f
  Compiled from "Converter.java"
public abstract class com.fasterxml.jackson.databind.util.Converter$None extends java.lang.Object implements com.fasterxml.jackson.databind.util.Converter<java.lang.Object, java.lang.Object>
  minor version: 0
  major version: 52
  flags: (0x0421) ACC_PUBLIC, ACC_SUPER, ACC_ABSTRACT
  this_class: #2                          // com/fasterxml/jackson/databind/util/Converter$None
  super_class: #3                         // java/lang/Object
  interfaces: 1, fields: 0, methods: 1, attributes: 3
Constant pool:
   #1 = Methodref          #3.#18         // java/lang/Object."<init>":()V
   #2 = Class              #19            // com/fasterxml/jackson/databind/util/Converter$None
   #3 = Class              #20            // java/lang/Object
   #4 = Class              #21            // com/fasterxml/jackson/databind/util/Converter
   #5 = Utf8               <init>
   #6 = Utf8               ()V
   #7 = Utf8               Code
   #8 = Utf8               LineNumberTable
   #9 = Utf8               LocalVariableTable
  #10 = Utf8               this
  #11 = Utf8               None
  #12 = Utf8               InnerClasses
  #13 = Utf8               Lcom/fasterxml/jackson/databind/util/Converter$None;
  #14 = Utf8               Signature
  #15 = Utf8               Ljava/lang/Object;Lcom/fasterxml/jackson/databind/util/Converter<Ljava/lang/Object;Ljava/lang/Object;>;
  #16 = Utf8               SourceFile
  #17 = Utf8               Converter.java
  #18 = NameAndType        #5:#6          // "<init>":()V
  #19 = Utf8               com/fasterxml/jackson/databind/util/Converter$None
  #20 = Utf8               java/lang/Object
  #21 = Utf8               com/fasterxml/jackson/databind/util/Converter
{
  public com.fasterxml.jackson.databind.util.Converter$None();
    descriptor: ()V
    flags: (0x0001) ACC_PUBLIC
    Code:
      stack=1, locals=1, args_size=1
         0: aload_0
         1: invokespecial #1                  // Method java/lang/Object."<init>":()V
         4: return
      LineNumberTable:
        line 65: 0
      LocalVariableTable:
        Start  Length  Slot  Name   Signature
            0       5     0  this   Lcom/fasterxml/jackson/databind/util/Converter$None;
}
Signature: #15                          // Ljava/lang/Object;Lcom/fasterxml/jackson/databind/util/Converter<Ljava/lang/Object;Ljava/lang/Object;>;
SourceFile: "Converter.java"
InnerClasses:
  public static abstract #11= #2 of #4;   // None=class com/fasterxml/jackson/databind/util/Converter$None of class com/fasterxml/jackson/databind/util/Converter
