Classfile /Users/mw/Projects/slang-braindump/.jar/jar11/assemble/slang-braindump/assemble/content/com/fasterxml/jackson/databind/util/NameTransformer$1.class
  Last modified May 29, 2022; size 1537 bytes
  SHA-256 checksum 93b84fbf8f6d5796892ecc8793239cbe1fc68414aacdf3769bb9bc164249f6f0
  Compiled from "NameTransformer.java"
final class com.fasterxml.jackson.databind.util.NameTransformer$1 extends com.fasterxml.jackson.databind.util.NameTransformer
  minor version: 0
  major version: 52
  flags: (0x0030) ACC_FINAL, ACC_SUPER
  this_class: #16                         // com/fasterxml/jackson/databind/util/NameTransformer$1
  super_class: #17                        // com/fasterxml/jackson/databind/util/NameTransformer
  interfaces: 0, fields: 2, methods: 4, attributes: 3
Constant pool:
   #1 = Fieldref           #16.#42        // com/fasterxml/jackson/databind/util/NameTransformer$1.val$prefix:Ljava/lang/String;
   #2 = Fieldref           #16.#43        // com/fasterxml/jackson/databind/util/NameTransformer$1.val$suffix:Ljava/lang/String;
   #3 = Methodref          #17.#44        // com/fasterxml/jackson/databind/util/NameTransformer."<init>":()V
   #4 = Class              #45            // java/lang/StringBuilder
   #5 = Methodref          #4.#44         // java/lang/StringBuilder."<init>":()V
   #6 = Methodref          #4.#46         // java/lang/StringBuilder.append:(Ljava/lang/String;)Ljava/lang/StringBuilder;
   #7 = Methodref          #4.#47         // java/lang/StringBuilder.toString:()Ljava/lang/String;
   #8 = Methodref          #48.#49        // java/lang/String.startsWith:(Ljava/lang/String;)Z
   #9 = Methodref          #48.#50        // java/lang/String.length:()I
  #10 = Methodref          #48.#51        // java/lang/String.substring:(I)Ljava/lang/String;
  #11 = Methodref          #48.#52        // java/lang/String.endsWith:(Ljava/lang/String;)Z
  #12 = Methodref          #48.#53        // java/lang/String.substring:(II)Ljava/lang/String;
  #13 = String             #54            // [PreAndSuffixTransformer(\'
  #14 = String             #55            // \',\'
  #15 = String             #56            // \')]
  #16 = Class              #57            // com/fasterxml/jackson/databind/util/NameTransformer$1
  #17 = Class              #58            // com/fasterxml/jackson/databind/util/NameTransformer
  #18 = Utf8               val$prefix
  #19 = Utf8               Ljava/lang/String;
  #20 = Utf8               val$suffix
  #21 = Utf8               <init>
  #22 = Utf8               (Ljava/lang/String;Ljava/lang/String;)V
  #23 = Utf8               Code
  #24 = Utf8               LineNumberTable
  #25 = Utf8               LocalVariableTable
  #26 = Utf8               this
  #27 = Utf8               InnerClasses
  #28 = Utf8               Lcom/fasterxml/jackson/databind/util/NameTransformer$1;
  #29 = Utf8               transform
  #30 = Utf8               (Ljava/lang/String;)Ljava/lang/String;
  #31 = Utf8               name
  #32 = Utf8               reverse
  #33 = Utf8               str
  #34 = Utf8               transformed
  #35 = Utf8               StackMapTable
  #36 = Utf8               toString
  #37 = Utf8               ()Ljava/lang/String;
  #38 = Utf8               SourceFile
  #39 = Utf8               NameTransformer.java
  #40 = Utf8               EnclosingMethod
  #41 = NameAndType        #59:#60        // simpleTransformer:(Ljava/lang/String;Ljava/lang/String;)Lcom/fasterxml/jackson/databind/util/NameTransformer;
  #42 = NameAndType        #18:#19        // val$prefix:Ljava/lang/String;
  #43 = NameAndType        #20:#19        // val$suffix:Ljava/lang/String;
  #44 = NameAndType        #21:#61        // "<init>":()V
  #45 = Utf8               java/lang/StringBuilder
  #46 = NameAndType        #62:#63        // append:(Ljava/lang/String;)Ljava/lang/StringBuilder;
  #47 = NameAndType        #36:#37        // toString:()Ljava/lang/String;
  #48 = Class              #64            // java/lang/String
  #49 = NameAndType        #65:#66        // startsWith:(Ljava/lang/String;)Z
  #50 = NameAndType        #67:#68        // length:()I
  #51 = NameAndType        #69:#70        // substring:(I)Ljava/lang/String;
  #52 = NameAndType        #71:#66        // endsWith:(Ljava/lang/String;)Z
  #53 = NameAndType        #69:#72        // substring:(II)Ljava/lang/String;
  #54 = Utf8               [PreAndSuffixTransformer(\'
  #55 = Utf8               \',\'
  #56 = Utf8               \')]
  #57 = Utf8               com/fasterxml/jackson/databind/util/NameTransformer$1
  #58 = Utf8               com/fasterxml/jackson/databind/util/NameTransformer
  #59 = Utf8               simpleTransformer
  #60 = Utf8               (Ljava/lang/String;Ljava/lang/String;)Lcom/fasterxml/jackson/databind/util/NameTransformer;
  #61 = Utf8               ()V
  #62 = Utf8               append
  #63 = Utf8               (Ljava/lang/String;)Ljava/lang/StringBuilder;
  #64 = Utf8               java/lang/String
  #65 = Utf8               startsWith
  #66 = Utf8               (Ljava/lang/String;)Z
  #67 = Utf8               length
  #68 = Utf8               ()I
  #69 = Utf8               substring
  #70 = Utf8               (I)Ljava/lang/String;
  #71 = Utf8               endsWith
  #72 = Utf8               (II)Ljava/lang/String;
{
  final java.lang.String val$prefix;
    descriptor: Ljava/lang/String;
    flags: (0x1010) ACC_FINAL, ACC_SYNTHETIC

  final java.lang.String val$suffix;
    descriptor: Ljava/lang/String;
    flags: (0x1010) ACC_FINAL, ACC_SYNTHETIC

  com.fasterxml.jackson.databind.util.NameTransformer$1(java.lang.String, java.lang.String);
    descriptor: (Ljava/lang/String;Ljava/lang/String;)V
    flags: (0x0000)
    Code:
      stack=2, locals=3, args_size=3
         0: aload_0
         1: aload_1
         2: putfield      #1                  // Field val$prefix:Ljava/lang/String;
         5: aload_0
         6: aload_2
         7: putfield      #2                  // Field val$suffix:Ljava/lang/String;
        10: aload_0
        11: invokespecial #3                  // Method com/fasterxml/jackson/databind/util/NameTransformer."<init>":()V
        14: return
      LineNumberTable:
        line 46: 0
      LocalVariableTable:
        Start  Length  Slot  Name   Signature
            0      15     0  this   Lcom/fasterxml/jackson/databind/util/NameTransformer$1;

  public java.lang.String transform(java.lang.String);
    descriptor: (Ljava/lang/String;)Ljava/lang/String;
    flags: (0x0001) ACC_PUBLIC
    Code:
      stack=2, locals=2, args_size=2
         0: new           #4                  // class java/lang/StringBuilder
         3: dup
         4: invokespecial #5                  // Method java/lang/StringBuilder."<init>":()V
         7: aload_0
         8: getfield      #1                  // Field val$prefix:Ljava/lang/String;
        11: invokevirtual #6                  // Method java/lang/StringBuilder.append:(Ljava/lang/String;)Ljava/lang/StringBuilder;
        14: aload_1
        15: invokevirtual #6                  // Method java/lang/StringBuilder.append:(Ljava/lang/String;)Ljava/lang/StringBuilder;
        18: aload_0
        19: getfield      #2                  // Field val$suffix:Ljava/lang/String;
        22: invokevirtual #6                  // Method java/lang/StringBuilder.append:(Ljava/lang/String;)Ljava/lang/StringBuilder;
        25: invokevirtual #7                  // Method java/lang/StringBuilder.toString:()Ljava/lang/String;
        28: areturn
      LineNumberTable:
        line 48: 0
      LocalVariableTable:
        Start  Length  Slot  Name   Signature
            0      29     0  this   Lcom/fasterxml/jackson/databind/util/NameTransformer$1;
            0      29     1  name   Ljava/lang/String;

  public java.lang.String reverse(java.lang.String);
    descriptor: (Ljava/lang/String;)Ljava/lang/String;
    flags: (0x0001) ACC_PUBLIC
    Code:
      stack=4, locals=3, args_size=2
         0: aload_1
         1: aload_0
         2: getfield      #1                  // Field val$prefix:Ljava/lang/String;
         5: invokevirtual #8                  // Method java/lang/String.startsWith:(Ljava/lang/String;)Z
         8: ifeq          52
        11: aload_1
        12: aload_0
        13: getfield      #1                  // Field val$prefix:Ljava/lang/String;
        16: invokevirtual #9                  // Method java/lang/String.length:()I
        19: invokevirtual #10                 // Method java/lang/String.substring:(I)Ljava/lang/String;
        22: astore_2
        23: aload_2
        24: aload_0
        25: getfield      #2                  // Field val$suffix:Ljava/lang/String;
        28: invokevirtual #11                 // Method java/lang/String.endsWith:(Ljava/lang/String;)Z
        31: ifeq          52
        34: aload_2
        35: iconst_0
        36: aload_2
        37: invokevirtual #9                  // Method java/lang/String.length:()I
        40: aload_0
        41: getfield      #2                  // Field val$suffix:Ljava/lang/String;
        44: invokevirtual #9                  // Method java/lang/String.length:()I
        47: isub
        48: invokevirtual #12                 // Method java/lang/String.substring:(II)Ljava/lang/String;
        51: areturn
        52: aconst_null
        53: areturn
      LineNumberTable:
        line 51: 0
        line 52: 11
        line 53: 23
        line 54: 34
        line 57: 52
      LocalVariableTable:
        Start  Length  Slot  Name   Signature
           23      29     2   str   Ljava/lang/String;
            0      54     0  this   Lcom/fasterxml/jackson/databind/util/NameTransformer$1;
            0      54     1 transformed   Ljava/lang/String;
      StackMapTable: number_of_entries = 1
        frame_type = 52 /* same */

  public java.lang.String toString();
    descriptor: ()Ljava/lang/String;
    flags: (0x0001) ACC_PUBLIC
    Code:
      stack=2, locals=1, args_size=1
         0: new           #4                  // class java/lang/StringBuilder
         3: dup
         4: invokespecial #5                  // Method java/lang/StringBuilder."<init>":()V
         7: ldc           #13                 // String [PreAndSuffixTransformer(\'
         9: invokevirtual #6                  // Method java/lang/StringBuilder.append:(Ljava/lang/String;)Ljava/lang/StringBuilder;
        12: aload_0
        13: getfield      #1                  // Field val$prefix:Ljava/lang/String;
        16: invokevirtual #6                  // Method java/lang/StringBuilder.append:(Ljava/lang/String;)Ljava/lang/StringBuilder;
        19: ldc           #14                 // String \',\'
        21: invokevirtual #6                  // Method java/lang/StringBuilder.append:(Ljava/lang/String;)Ljava/lang/StringBuilder;
        24: aload_0
        25: getfield      #2                  // Field val$suffix:Ljava/lang/String;
        28: invokevirtual #6                  // Method java/lang/StringBuilder.append:(Ljava/lang/String;)Ljava/lang/StringBuilder;
        31: ldc           #15                 // String \')]
        33: invokevirtual #6                  // Method java/lang/StringBuilder.append:(Ljava/lang/String;)Ljava/lang/StringBuilder;
        36: invokevirtual #7                  // Method java/lang/StringBuilder.toString:()Ljava/lang/String;
        39: areturn
      LineNumberTable:
        line 60: 0
      LocalVariableTable:
        Start  Length  Slot  Name   Signature
            0      40     0  this   Lcom/fasterxml/jackson/databind/util/NameTransformer$1;
}
SourceFile: "NameTransformer.java"
EnclosingMethod: #17.#41                // com.fasterxml.jackson.databind.util.NameTransformer.simpleTransformer
InnerClasses:
  static #16;                             // class com/fasterxml/jackson/databind/util/NameTransformer$1
