Classfile /Users/mw/Projects/slang-braindump/.jar/jar11/assemble/slang-braindump/assemble/content/com/fasterxml/jackson/databind/util/TokenBuffer$Segment.class
  Last modified May 29, 2022; size 5163 bytes
  SHA-256 checksum 1fe0e72a679e52b55bffffa6a012960555aaae7cee3f61b01ac9dd2bfbe807f0
  Compiled from "TokenBuffer.java"
public final class com.fasterxml.jackson.databind.util.TokenBuffer$Segment
  minor version: 0
  major version: 52
  flags: (0x0031) ACC_PUBLIC, ACC_FINAL, ACC_SUPER
  this_class: #2                          // com/fasterxml/jackson/databind/util/TokenBuffer$Segment
  super_class: #3                         // java/lang/Object
  interfaces: 0, fields: 6, methods: 20, attributes: 2
Constant pool:
    #1 = Methodref          #3.#94        // java/lang/Object."<init>":()V
    #2 = Class              #96           // com/fasterxml/jackson/databind/util/TokenBuffer$Segment
    #3 = Class              #97           // java/lang/Object
    #4 = Fieldref           #2.#98        // com/fasterxml/jackson/databind/util/TokenBuffer$Segment._tokens:[Ljava/lang/Object;
    #5 = Fieldref           #2.#99        // com/fasterxml/jackson/databind/util/TokenBuffer$Segment._tokenTypes:J
    #6 = Fieldref           #2.#100       // com/fasterxml/jackson/databind/util/TokenBuffer$Segment.TOKEN_TYPES_BY_INDEX:[Lcom/fasterxml/jackson/core/JsonToken;
    #7 = Fieldref           #2.#101       // com/fasterxml/jackson/databind/util/TokenBuffer$Segment._next:Lcom/fasterxml/jackson/databind/util/TokenBuffer$Segment;
    #8 = Fieldref           #2.#102       // com/fasterxml/jackson/databind/util/TokenBuffer$Segment._nativeIds:Ljava/util/TreeMap;
    #9 = Methodref          #2.#103       // com/fasterxml/jackson/databind/util/TokenBuffer$Segment.set:(ILcom/fasterxml/jackson/core/JsonToken;)V
   #10 = Methodref          #2.#94        // com/fasterxml/jackson/databind/util/TokenBuffer$Segment."<init>":()V
   #11 = Methodref          #2.#104       // com/fasterxml/jackson/databind/util/TokenBuffer$Segment.set:(ILcom/fasterxml/jackson/core/JsonToken;Ljava/lang/Object;Ljava/lang/Object;)V
   #12 = Methodref          #2.#105       // com/fasterxml/jackson/databind/util/TokenBuffer$Segment.set:(ILcom/fasterxml/jackson/core/JsonToken;Ljava/lang/Object;)V
   #13 = Methodref          #2.#106       // com/fasterxml/jackson/databind/util/TokenBuffer$Segment.set:(ILcom/fasterxml/jackson/core/JsonToken;Ljava/lang/Object;Ljava/lang/Object;Ljava/lang/Object;)V
   #14 = Methodref          #23.#107      // com/fasterxml/jackson/core/JsonToken.ordinal:()I
   #15 = Methodref          #2.#108       // com/fasterxml/jackson/databind/util/TokenBuffer$Segment.assignNativeIds:(ILjava/lang/Object;Ljava/lang/Object;)V
   #16 = Class              #109          // java/util/TreeMap
   #17 = Methodref          #16.#94       // java/util/TreeMap."<init>":()V
   #18 = Methodref          #2.#110       // com/fasterxml/jackson/databind/util/TokenBuffer$Segment._objectIdIndex:(I)I
   #19 = Methodref          #111.#112     // java/lang/Integer.valueOf:(I)Ljava/lang/Integer;
   #20 = Methodref          #16.#113      // java/util/TreeMap.put:(Ljava/lang/Object;Ljava/lang/Object;)Ljava/lang/Object;
   #21 = Methodref          #2.#114       // com/fasterxml/jackson/databind/util/TokenBuffer$Segment._typeIdIndex:(I)I
   #22 = Methodref          #16.#115      // java/util/TreeMap.get:(Ljava/lang/Object;)Ljava/lang/Object;
   #23 = Class              #116          // com/fasterxml/jackson/core/JsonToken
   #24 = Methodref          #23.#117      // com/fasterxml/jackson/core/JsonToken.values:()[Lcom/fasterxml/jackson/core/JsonToken;
   #25 = Methodref          #118.#119     // java/lang/Math.min:(II)I
   #26 = Methodref          #120.#121     // java/lang/System.arraycopy:(Ljava/lang/Object;ILjava/lang/Object;II)V
   #27 = Utf8               TOKENS_PER_SEGMENT
   #28 = Utf8               I
   #29 = Utf8               ConstantValue
   #30 = Integer            16
   #31 = Utf8               TOKEN_TYPES_BY_INDEX
   #32 = Utf8               [Lcom/fasterxml/jackson/core/JsonToken;
   #33 = Utf8               _next
   #34 = Utf8               Segment
   #35 = Utf8               InnerClasses
   #36 = Utf8               Lcom/fasterxml/jackson/databind/util/TokenBuffer$Segment;
   #37 = Utf8               _tokenTypes
   #38 = Utf8               J
   #39 = Utf8               _tokens
   #40 = Utf8               [Ljava/lang/Object;
   #41 = Utf8               _nativeIds
   #42 = Utf8               Ljava/util/TreeMap;
   #43 = Utf8               Signature
   #44 = Utf8               Ljava/util/TreeMap<Ljava/lang/Integer;Ljava/lang/Object;>;
   #45 = Utf8               <init>
   #46 = Utf8               ()V
   #47 = Utf8               Code
   #48 = Utf8               LineNumberTable
   #49 = Utf8               LocalVariableTable
   #50 = Utf8               this
   #51 = Utf8               type
   #52 = Utf8               (I)Lcom/fasterxml/jackson/core/JsonToken;
   #53 = Utf8               index
   #54 = Utf8               l
   #55 = Utf8               ix
   #56 = Utf8               StackMapTable
   #57 = Utf8               rawType
   #58 = Utf8               (I)I
   #59 = Utf8               get
   #60 = Utf8               (I)Ljava/lang/Object;
   #61 = Utf8               next
   #62 = Utf8               ()Lcom/fasterxml/jackson/databind/util/TokenBuffer$Segment;
   #63 = Utf8               hasIds
   #64 = Utf8               ()Z
   #65 = Utf8               append
   #66 = Utf8               (ILcom/fasterxml/jackson/core/JsonToken;)Lcom/fasterxml/jackson/databind/util/TokenBuffer$Segment;
   #67 = Utf8               tokenType
   #68 = Utf8               Lcom/fasterxml/jackson/core/JsonToken;
   #69 = Utf8               (ILcom/fasterxml/jackson/core/JsonToken;Ljava/lang/Object;Ljava/lang/Object;)Lcom/fasterxml/jackson/databind/util/TokenBuffer$Segment;
   #70 = Utf8               objectId
   #71 = Utf8               Ljava/lang/Object;
   #72 = Utf8               typeId
   #73 = Utf8               (ILcom/fasterxml/jackson/core/JsonToken;Ljava/lang/Object;)Lcom/fasterxml/jackson/databind/util/TokenBuffer$Segment;
   #74 = Utf8               value
   #75 = Utf8               (ILcom/fasterxml/jackson/core/JsonToken;Ljava/lang/Object;Ljava/lang/Object;Ljava/lang/Object;)Lcom/fasterxml/jackson/databind/util/TokenBuffer$Segment;
   #76 = Utf8               set
   #77 = Utf8               (ILcom/fasterxml/jackson/core/JsonToken;)V
   #78 = Utf8               typeCode
   #79 = Utf8               (ILcom/fasterxml/jackson/core/JsonToken;Ljava/lang/Object;Ljava/lang/Object;)V
   #80 = Utf8               (ILcom/fasterxml/jackson/core/JsonToken;Ljava/lang/Object;)V
   #81 = Utf8               (ILcom/fasterxml/jackson/core/JsonToken;Ljava/lang/Object;Ljava/lang/Object;Ljava/lang/Object;)V
   #82 = Utf8               assignNativeIds
   #83 = Utf8               (ILjava/lang/Object;Ljava/lang/Object;)V
   #84 = Utf8               findObjectId
   #85 = Class              #97           // java/lang/Object
   #86 = Utf8               findTypeId
   #87 = Utf8               _typeIdIndex
   #88 = Utf8               i
   #89 = Utf8               _objectIdIndex
   #90 = Utf8               <clinit>
   #91 = Utf8               t
   #92 = Utf8               SourceFile
   #93 = Utf8               TokenBuffer.java
   #94 = NameAndType        #45:#46       // "<init>":()V
   #95 = Class              #122          // com/fasterxml/jackson/databind/util/TokenBuffer
   #96 = Utf8               com/fasterxml/jackson/databind/util/TokenBuffer$Segment
   #97 = Utf8               java/lang/Object
   #98 = NameAndType        #39:#40       // _tokens:[Ljava/lang/Object;
   #99 = NameAndType        #37:#38       // _tokenTypes:J
  #100 = NameAndType        #31:#32       // TOKEN_TYPES_BY_INDEX:[Lcom/fasterxml/jackson/core/JsonToken;
  #101 = NameAndType        #33:#36       // _next:Lcom/fasterxml/jackson/databind/util/TokenBuffer$Segment;
  #102 = NameAndType        #41:#42       // _nativeIds:Ljava/util/TreeMap;
  #103 = NameAndType        #76:#77       // set:(ILcom/fasterxml/jackson/core/JsonToken;)V
  #104 = NameAndType        #76:#79       // set:(ILcom/fasterxml/jackson/core/JsonToken;Ljava/lang/Object;Ljava/lang/Object;)V
  #105 = NameAndType        #76:#80       // set:(ILcom/fasterxml/jackson/core/JsonToken;Ljava/lang/Object;)V
  #106 = NameAndType        #76:#81       // set:(ILcom/fasterxml/jackson/core/JsonToken;Ljava/lang/Object;Ljava/lang/Object;Ljava/lang/Object;)V
  #107 = NameAndType        #123:#124     // ordinal:()I
  #108 = NameAndType        #82:#83       // assignNativeIds:(ILjava/lang/Object;Ljava/lang/Object;)V
  #109 = Utf8               java/util/TreeMap
  #110 = NameAndType        #89:#58       // _objectIdIndex:(I)I
  #111 = Class              #125          // java/lang/Integer
  #112 = NameAndType        #126:#127     // valueOf:(I)Ljava/lang/Integer;
  #113 = NameAndType        #128:#129     // put:(Ljava/lang/Object;Ljava/lang/Object;)Ljava/lang/Object;
  #114 = NameAndType        #87:#58       // _typeIdIndex:(I)I
  #115 = NameAndType        #59:#130      // get:(Ljava/lang/Object;)Ljava/lang/Object;
  #116 = Utf8               com/fasterxml/jackson/core/JsonToken
  #117 = NameAndType        #131:#132     // values:()[Lcom/fasterxml/jackson/core/JsonToken;
  #118 = Class              #133          // java/lang/Math
  #119 = NameAndType        #134:#135     // min:(II)I
  #120 = Class              #136          // java/lang/System
  #121 = NameAndType        #137:#138     // arraycopy:(Ljava/lang/Object;ILjava/lang/Object;II)V
  #122 = Utf8               com/fasterxml/jackson/databind/util/TokenBuffer
  #123 = Utf8               ordinal
  #124 = Utf8               ()I
  #125 = Utf8               java/lang/Integer
  #126 = Utf8               valueOf
  #127 = Utf8               (I)Ljava/lang/Integer;
  #128 = Utf8               put
  #129 = Utf8               (Ljava/lang/Object;Ljava/lang/Object;)Ljava/lang/Object;
  #130 = Utf8               (Ljava/lang/Object;)Ljava/lang/Object;
  #131 = Utf8               values
  #132 = Utf8               ()[Lcom/fasterxml/jackson/core/JsonToken;
  #133 = Utf8               java/lang/Math
  #134 = Utf8               min
  #135 = Utf8               (II)I
  #136 = Utf8               java/lang/System
  #137 = Utf8               arraycopy
  #138 = Utf8               (Ljava/lang/Object;ILjava/lang/Object;II)V
{
  public static final int TOKENS_PER_SEGMENT;
    descriptor: I
    flags: (0x0019) ACC_PUBLIC, ACC_STATIC, ACC_FINAL
    ConstantValue: int 16

  private static final com.fasterxml.jackson.core.JsonToken[] TOKEN_TYPES_BY_INDEX;
    descriptor: [Lcom/fasterxml/jackson/core/JsonToken;
    flags: (0x001a) ACC_PRIVATE, ACC_STATIC, ACC_FINAL

  protected com.fasterxml.jackson.databind.util.TokenBuffer$Segment _next;
    descriptor: Lcom/fasterxml/jackson/databind/util/TokenBuffer$Segment;
    flags: (0x0004) ACC_PROTECTED

  protected long _tokenTypes;
    descriptor: J
    flags: (0x0004) ACC_PROTECTED

  protected final java.lang.Object[] _tokens;
    descriptor: [Ljava/lang/Object;
    flags: (0x0014) ACC_PROTECTED, ACC_FINAL

  protected java.util.TreeMap<java.lang.Integer, java.lang.Object> _nativeIds;
    descriptor: Ljava/util/TreeMap;
    flags: (0x0004) ACC_PROTECTED
    Signature: #44                          // Ljava/util/TreeMap<Ljava/lang/Integer;Ljava/lang/Object;>;

  public com.fasterxml.jackson.databind.util.TokenBuffer$Segment();
    descriptor: ()V
    flags: (0x0001) ACC_PUBLIC
    Code:
      stack=2, locals=1, args_size=1
         0: aload_0
         1: invokespecial #1                  // Method java/lang/Object."<init>":()V
         4: aload_0
         5: bipush        16
         7: anewarray     #3                  // class java/lang/Object
        10: putfield      #4                  // Field _tokens:[Ljava/lang/Object;
        13: return
      LineNumberTable:
        line 2081: 0
        line 2074: 4
        line 2081: 13
      LocalVariableTable:
        Start  Length  Slot  Name   Signature
            0      14     0  this   Lcom/fasterxml/jackson/databind/util/TokenBuffer$Segment;

  public com.fasterxml.jackson.core.JsonToken type(int);
    descriptor: (I)Lcom/fasterxml/jackson/core/JsonToken;
    flags: (0x0001) ACC_PUBLIC
    Code:
      stack=4, locals=5, args_size=2
         0: aload_0
         1: getfield      #5                  // Field _tokenTypes:J
         4: lstore_2
         5: iload_1
         6: ifle          15
         9: lload_2
        10: iload_1
        11: iconst_2
        12: ishl
        13: lshr
        14: lstore_2
        15: lload_2
        16: l2i
        17: bipush        15
        19: iand
        20: istore        4
        22: getstatic     #6                  // Field TOKEN_TYPES_BY_INDEX:[Lcom/fasterxml/jackson/core/JsonToken;
        25: iload         4
        27: aaload
        28: areturn
      LineNumberTable:
        line 2087: 0
        line 2088: 5
        line 2089: 9
        line 2091: 15
        line 2092: 22
      LocalVariableTable:
        Start  Length  Slot  Name   Signature
            0      29     0  this   Lcom/fasterxml/jackson/databind/util/TokenBuffer$Segment;
            0      29     1 index   I
            5      24     2     l   J
           22       7     4    ix   I
      StackMapTable: number_of_entries = 1
        frame_type = 252 /* append */
          offset_delta = 15
          locals = [ long ]

  public int rawType(int);
    descriptor: (I)I
    flags: (0x0001) ACC_PUBLIC
    Code:
      stack=4, locals=5, args_size=2
         0: aload_0
         1: getfield      #5                  // Field _tokenTypes:J
         4: lstore_2
         5: iload_1
         6: ifle          15
         9: lload_2
        10: iload_1
        11: iconst_2
        12: ishl
        13: lshr
        14: lstore_2
        15: lload_2
        16: l2i
        17: bipush        15
        19: iand
        20: istore        4
        22: iload         4
        24: ireturn
      LineNumberTable:
        line 2097: 0
        line 2098: 5
        line 2099: 9
        line 2101: 15
        line 2102: 22
      LocalVariableTable:
        Start  Length  Slot  Name   Signature
            0      25     0  this   Lcom/fasterxml/jackson/databind/util/TokenBuffer$Segment;
            0      25     1 index   I
            5      20     2     l   J
           22       3     4    ix   I
      StackMapTable: number_of_entries = 1
        frame_type = 252 /* append */
          offset_delta = 15
          locals = [ long ]

  public java.lang.Object get(int);
    descriptor: (I)Ljava/lang/Object;
    flags: (0x0001) ACC_PUBLIC
    Code:
      stack=2, locals=2, args_size=2
         0: aload_0
         1: getfield      #4                  // Field _tokens:[Ljava/lang/Object;
         4: iload_1
         5: aaload
         6: areturn
      LineNumberTable:
        line 2106: 0
      LocalVariableTable:
        Start  Length  Slot  Name   Signature
            0       7     0  this   Lcom/fasterxml/jackson/databind/util/TokenBuffer$Segment;
            0       7     1 index   I

  public com.fasterxml.jackson.databind.util.TokenBuffer$Segment next();
    descriptor: ()Lcom/fasterxml/jackson/databind/util/TokenBuffer$Segment;
    flags: (0x0001) ACC_PUBLIC
    Code:
      stack=1, locals=1, args_size=1
         0: aload_0
         1: getfield      #7                  // Field _next:Lcom/fasterxml/jackson/databind/util/TokenBuffer$Segment;
         4: areturn
      LineNumberTable:
        line 2109: 0
      LocalVariableTable:
        Start  Length  Slot  Name   Signature
            0       5     0  this   Lcom/fasterxml/jackson/databind/util/TokenBuffer$Segment;

  public boolean hasIds();
    descriptor: ()Z
    flags: (0x0001) ACC_PUBLIC
    Code:
      stack=1, locals=1, args_size=1
         0: aload_0
         1: getfield      #8                  // Field _nativeIds:Ljava/util/TreeMap;
         4: ifnull        11
         7: iconst_1
         8: goto          12
        11: iconst_0
        12: ireturn
      LineNumberTable:
        line 2116: 0
      LocalVariableTable:
        Start  Length  Slot  Name   Signature
            0      13     0  this   Lcom/fasterxml/jackson/databind/util/TokenBuffer$Segment;
      StackMapTable: number_of_entries = 2
        frame_type = 11 /* same */
        frame_type = 64 /* same_locals_1_stack_item */
          stack = [ int ]

  public com.fasterxml.jackson.databind.util.TokenBuffer$Segment append(int, com.fasterxml.jackson.core.JsonToken);
    descriptor: (ILcom/fasterxml/jackson/core/JsonToken;)Lcom/fasterxml/jackson/databind/util/TokenBuffer$Segment;
    flags: (0x0001) ACC_PUBLIC
    Code:
      stack=3, locals=3, args_size=3
         0: iload_1
         1: bipush        16
         3: if_icmpge     14
         6: aload_0
         7: iload_1
         8: aload_2
         9: invokespecial #9                  // Method set:(ILcom/fasterxml/jackson/core/JsonToken;)V
        12: aconst_null
        13: areturn
        14: aload_0
        15: new           #2                  // class com/fasterxml/jackson/databind/util/TokenBuffer$Segment
        18: dup
        19: invokespecial #10                 // Method "<init>":()V
        22: putfield      #7                  // Field _next:Lcom/fasterxml/jackson/databind/util/TokenBuffer$Segment;
        25: aload_0
        26: getfield      #7                  // Field _next:Lcom/fasterxml/jackson/databind/util/TokenBuffer$Segment;
        29: iconst_0
        30: aload_2
        31: invokespecial #9                  // Method set:(ILcom/fasterxml/jackson/core/JsonToken;)V
        34: aload_0
        35: getfield      #7                  // Field _next:Lcom/fasterxml/jackson/databind/util/TokenBuffer$Segment;
        38: areturn
      LineNumberTable:
        line 2123: 0
        line 2124: 6
        line 2125: 12
        line 2127: 14
        line 2128: 25
        line 2129: 34
      LocalVariableTable:
        Start  Length  Slot  Name   Signature
            0      39     0  this   Lcom/fasterxml/jackson/databind/util/TokenBuffer$Segment;
            0      39     1 index   I
            0      39     2 tokenType   Lcom/fasterxml/jackson/core/JsonToken;
      StackMapTable: number_of_entries = 1
        frame_type = 14 /* same */

  public com.fasterxml.jackson.databind.util.TokenBuffer$Segment append(int, com.fasterxml.jackson.core.JsonToken, java.lang.Object, java.lang.Object);
    descriptor: (ILcom/fasterxml/jackson/core/JsonToken;Ljava/lang/Object;Ljava/lang/Object;)Lcom/fasterxml/jackson/databind/util/TokenBuffer$Segment;
    flags: (0x0001) ACC_PUBLIC
    Code:
      stack=5, locals=5, args_size=5
         0: iload_1
         1: bipush        16
         3: if_icmpge     17
         6: aload_0
         7: iload_1
         8: aload_2
         9: aload_3
        10: aload         4
        12: invokespecial #11                 // Method set:(ILcom/fasterxml/jackson/core/JsonToken;Ljava/lang/Object;Ljava/lang/Object;)V
        15: aconst_null
        16: areturn
        17: aload_0
        18: new           #2                  // class com/fasterxml/jackson/databind/util/TokenBuffer$Segment
        21: dup
        22: invokespecial #10                 // Method "<init>":()V
        25: putfield      #7                  // Field _next:Lcom/fasterxml/jackson/databind/util/TokenBuffer$Segment;
        28: aload_0
        29: getfield      #7                  // Field _next:Lcom/fasterxml/jackson/databind/util/TokenBuffer$Segment;
        32: iconst_0
        33: aload_2
        34: aload_3
        35: aload         4
        37: invokespecial #11                 // Method set:(ILcom/fasterxml/jackson/core/JsonToken;Ljava/lang/Object;Ljava/lang/Object;)V
        40: aload_0
        41: getfield      #7                  // Field _next:Lcom/fasterxml/jackson/databind/util/TokenBuffer$Segment;
        44: areturn
      LineNumberTable:
        line 2135: 0
        line 2136: 6
        line 2137: 15
        line 2139: 17
        line 2140: 28
        line 2141: 40
      LocalVariableTable:
        Start  Length  Slot  Name   Signature
            0      45     0  this   Lcom/fasterxml/jackson/databind/util/TokenBuffer$Segment;
            0      45     1 index   I
            0      45     2 tokenType   Lcom/fasterxml/jackson/core/JsonToken;
            0      45     3 objectId   Ljava/lang/Object;
            0      45     4 typeId   Ljava/lang/Object;
      StackMapTable: number_of_entries = 1
        frame_type = 17 /* same */

  public com.fasterxml.jackson.databind.util.TokenBuffer$Segment append(int, com.fasterxml.jackson.core.JsonToken, java.lang.Object);
    descriptor: (ILcom/fasterxml/jackson/core/JsonToken;Ljava/lang/Object;)Lcom/fasterxml/jackson/databind/util/TokenBuffer$Segment;
    flags: (0x0001) ACC_PUBLIC
    Code:
      stack=4, locals=4, args_size=4
         0: iload_1
         1: bipush        16
         3: if_icmpge     15
         6: aload_0
         7: iload_1
         8: aload_2
         9: aload_3
        10: invokespecial #12                 // Method set:(ILcom/fasterxml/jackson/core/JsonToken;Ljava/lang/Object;)V
        13: aconst_null
        14: areturn
        15: aload_0
        16: new           #2                  // class com/fasterxml/jackson/databind/util/TokenBuffer$Segment
        19: dup
        20: invokespecial #10                 // Method "<init>":()V
        23: putfield      #7                  // Field _next:Lcom/fasterxml/jackson/databind/util/TokenBuffer$Segment;
        26: aload_0
        27: getfield      #7                  // Field _next:Lcom/fasterxml/jackson/databind/util/TokenBuffer$Segment;
        30: iconst_0
        31: aload_2
        32: aload_3
        33: invokespecial #12                 // Method set:(ILcom/fasterxml/jackson/core/JsonToken;Ljava/lang/Object;)V
        36: aload_0
        37: getfield      #7                  // Field _next:Lcom/fasterxml/jackson/databind/util/TokenBuffer$Segment;
        40: areturn
      LineNumberTable:
        line 2146: 0
        line 2147: 6
        line 2148: 13
        line 2150: 15
        line 2151: 26
        line 2152: 36
      LocalVariableTable:
        Start  Length  Slot  Name   Signature
            0      41     0  this   Lcom/fasterxml/jackson/databind/util/TokenBuffer$Segment;
            0      41     1 index   I
            0      41     2 tokenType   Lcom/fasterxml/jackson/core/JsonToken;
            0      41     3 value   Ljava/lang/Object;
      StackMapTable: number_of_entries = 1
        frame_type = 15 /* same */

  public com.fasterxml.jackson.databind.util.TokenBuffer$Segment append(int, com.fasterxml.jackson.core.JsonToken, java.lang.Object, java.lang.Object, java.lang.Object);
    descriptor: (ILcom/fasterxml/jackson/core/JsonToken;Ljava/lang/Object;Ljava/lang/Object;Ljava/lang/Object;)Lcom/fasterxml/jackson/databind/util/TokenBuffer$Segment;
    flags: (0x0001) ACC_PUBLIC
    Code:
      stack=6, locals=6, args_size=6
         0: iload_1
         1: bipush        16
         3: if_icmpge     19
         6: aload_0
         7: iload_1
         8: aload_2
         9: aload_3
        10: aload         4
        12: aload         5
        14: invokespecial #13                 // Method set:(ILcom/fasterxml/jackson/core/JsonToken;Ljava/lang/Object;Ljava/lang/Object;Ljava/lang/Object;)V
        17: aconst_null
        18: areturn
        19: aload_0
        20: new           #2                  // class com/fasterxml/jackson/databind/util/TokenBuffer$Segment
        23: dup
        24: invokespecial #10                 // Method "<init>":()V
        27: putfield      #7                  // Field _next:Lcom/fasterxml/jackson/databind/util/TokenBuffer$Segment;
        30: aload_0
        31: getfield      #7                  // Field _next:Lcom/fasterxml/jackson/databind/util/TokenBuffer$Segment;
        34: iconst_0
        35: aload_2
        36: aload_3
        37: aload         4
        39: aload         5
        41: invokespecial #13                 // Method set:(ILcom/fasterxml/jackson/core/JsonToken;Ljava/lang/Object;Ljava/lang/Object;Ljava/lang/Object;)V
        44: aload_0
        45: getfield      #7                  // Field _next:Lcom/fasterxml/jackson/databind/util/TokenBuffer$Segment;
        48: areturn
      LineNumberTable:
        line 2158: 0
        line 2159: 6
        line 2160: 17
        line 2162: 19
        line 2163: 30
        line 2164: 44
      LocalVariableTable:
        Start  Length  Slot  Name   Signature
            0      49     0  this   Lcom/fasterxml/jackson/databind/util/TokenBuffer$Segment;
            0      49     1 index   I
            0      49     2 tokenType   Lcom/fasterxml/jackson/core/JsonToken;
            0      49     3 value   Ljava/lang/Object;
            0      49     4 objectId   Ljava/lang/Object;
            0      49     5 typeId   Ljava/lang/Object;
      StackMapTable: number_of_entries = 1
        frame_type = 19 /* same */

  private void set(int, com.fasterxml.jackson.core.JsonToken);
    descriptor: (ILcom/fasterxml/jackson/core/JsonToken;)V
    flags: (0x0002) ACC_PRIVATE
    Code:
      stack=5, locals=5, args_size=3
         0: aload_2
         1: invokevirtual #14                 // Method com/fasterxml/jackson/core/JsonToken.ordinal:()I
         4: i2l
         5: lstore_3
         6: iload_1
         7: ifle          16
        10: lload_3
        11: iload_1
        12: iconst_2
        13: ishl
        14: lshl
        15: lstore_3
        16: aload_0
        17: dup
        18: getfield      #5                  // Field _tokenTypes:J
        21: lload_3
        22: lor
        23: putfield      #5                  // Field _tokenTypes:J
        26: return
      LineNumberTable:
        line 2218: 0
        line 2219: 6
        line 2220: 10
        line 2222: 16
        line 2223: 26
      LocalVariableTable:
        Start  Length  Slot  Name   Signature
            0      27     0  this   Lcom/fasterxml/jackson/databind/util/TokenBuffer$Segment;
            0      27     1 index   I
            0      27     2 tokenType   Lcom/fasterxml/jackson/core/JsonToken;
            6      21     3 typeCode   J
      StackMapTable: number_of_entries = 1
        frame_type = 252 /* append */
          offset_delta = 16
          locals = [ long ]

  private void set(int, com.fasterxml.jackson.core.JsonToken, java.lang.Object, java.lang.Object);
    descriptor: (ILcom/fasterxml/jackson/core/JsonToken;Ljava/lang/Object;Ljava/lang/Object;)V
    flags: (0x0002) ACC_PRIVATE
    Code:
      stack=5, locals=7, args_size=5
         0: aload_2
         1: invokevirtual #14                 // Method com/fasterxml/jackson/core/JsonToken.ordinal:()I
         4: i2l
         5: lstore        5
         7: iload_1
         8: ifle          19
        11: lload         5
        13: iload_1
        14: iconst_2
        15: ishl
        16: lshl
        17: lstore        5
        19: aload_0
        20: dup
        21: getfield      #5                  // Field _tokenTypes:J
        24: lload         5
        26: lor
        27: putfield      #5                  // Field _tokenTypes:J
        30: aload_0
        31: iload_1
        32: aload_3
        33: aload         4
        35: invokespecial #15                 // Method assignNativeIds:(ILjava/lang/Object;Ljava/lang/Object;)V
        38: return
      LineNumberTable:
        line 2228: 0
        line 2229: 7
        line 2230: 11
        line 2232: 19
        line 2233: 30
        line 2234: 38
      LocalVariableTable:
        Start  Length  Slot  Name   Signature
            0      39     0  this   Lcom/fasterxml/jackson/databind/util/TokenBuffer$Segment;
            0      39     1 index   I
            0      39     2 tokenType   Lcom/fasterxml/jackson/core/JsonToken;
            0      39     3 objectId   Ljava/lang/Object;
            0      39     4 typeId   Ljava/lang/Object;
            7      32     5 typeCode   J
      StackMapTable: number_of_entries = 1
        frame_type = 252 /* append */
          offset_delta = 19
          locals = [ long ]

  private void set(int, com.fasterxml.jackson.core.JsonToken, java.lang.Object);
    descriptor: (ILcom/fasterxml/jackson/core/JsonToken;Ljava/lang/Object;)V
    flags: (0x0002) ACC_PRIVATE
    Code:
      stack=5, locals=6, args_size=4
         0: aload_0
         1: getfield      #4                  // Field _tokens:[Ljava/lang/Object;
         4: iload_1
         5: aload_3
         6: aastore
         7: aload_2
         8: invokevirtual #14                 // Method com/fasterxml/jackson/core/JsonToken.ordinal:()I
        11: i2l
        12: lstore        4
        14: iload_1
        15: ifle          26
        18: lload         4
        20: iload_1
        21: iconst_2
        22: ishl
        23: lshl
        24: lstore        4
        26: aload_0
        27: dup
        28: getfield      #5                  // Field _tokenTypes:J
        31: lload         4
        33: lor
        34: putfield      #5                  // Field _tokenTypes:J
        37: return
      LineNumberTable:
        line 2238: 0
        line 2239: 7
        line 2240: 14
        line 2241: 18
        line 2243: 26
        line 2244: 37
      LocalVariableTable:
        Start  Length  Slot  Name   Signature
            0      38     0  this   Lcom/fasterxml/jackson/databind/util/TokenBuffer$Segment;
            0      38     1 index   I
            0      38     2 tokenType   Lcom/fasterxml/jackson/core/JsonToken;
            0      38     3 value   Ljava/lang/Object;
           14      24     4 typeCode   J
      StackMapTable: number_of_entries = 1
        frame_type = 252 /* append */
          offset_delta = 26
          locals = [ long ]

  private void set(int, com.fasterxml.jackson.core.JsonToken, java.lang.Object, java.lang.Object, java.lang.Object);
    descriptor: (ILcom/fasterxml/jackson/core/JsonToken;Ljava/lang/Object;Ljava/lang/Object;Ljava/lang/Object;)V
    flags: (0x0002) ACC_PRIVATE
    Code:
      stack=5, locals=8, args_size=6
         0: aload_0
         1: getfield      #4                  // Field _tokens:[Ljava/lang/Object;
         4: iload_1
         5: aload_3
         6: aastore
         7: aload_2
         8: invokevirtual #14                 // Method com/fasterxml/jackson/core/JsonToken.ordinal:()I
        11: i2l
        12: lstore        6
        14: iload_1
        15: ifle          26
        18: lload         6
        20: iload_1
        21: iconst_2
        22: ishl
        23: lshl
        24: lstore        6
        26: aload_0
        27: dup
        28: getfield      #5                  // Field _tokenTypes:J
        31: lload         6
        33: lor
        34: putfield      #5                  // Field _tokenTypes:J
        37: aload_0
        38: iload_1
        39: aload         4
        41: aload         5
        43: invokespecial #15                 // Method assignNativeIds:(ILjava/lang/Object;Ljava/lang/Object;)V
        46: return
      LineNumberTable:
        line 2249: 0
        line 2250: 7
        line 2251: 14
        line 2252: 18
        line 2254: 26
        line 2255: 37
        line 2256: 46
      LocalVariableTable:
        Start  Length  Slot  Name   Signature
            0      47     0  this   Lcom/fasterxml/jackson/databind/util/TokenBuffer$Segment;
            0      47     1 index   I
            0      47     2 tokenType   Lcom/fasterxml/jackson/core/JsonToken;
            0      47     3 value   Ljava/lang/Object;
            0      47     4 objectId   Ljava/lang/Object;
            0      47     5 typeId   Ljava/lang/Object;
           14      33     6 typeCode   J
      StackMapTable: number_of_entries = 1
        frame_type = 252 /* append */
          offset_delta = 26
          locals = [ long ]

  private final void assignNativeIds(int, java.lang.Object, java.lang.Object);
    descriptor: (ILjava/lang/Object;Ljava/lang/Object;)V
    flags: (0x0012) ACC_PRIVATE, ACC_FINAL
    Code:
      stack=3, locals=4, args_size=4
         0: aload_0
         1: getfield      #8                  // Field _nativeIds:Ljava/util/TreeMap;
         4: ifnonnull     18
         7: aload_0
         8: new           #16                 // class java/util/TreeMap
        11: dup
        12: invokespecial #17                 // Method java/util/TreeMap."<init>":()V
        15: putfield      #8                  // Field _nativeIds:Ljava/util/TreeMap;
        18: aload_2
        19: ifnull        39
        22: aload_0
        23: getfield      #8                  // Field _nativeIds:Ljava/util/TreeMap;
        26: aload_0
        27: iload_1
        28: invokespecial #18                 // Method _objectIdIndex:(I)I
        31: invokestatic  #19                 // Method java/lang/Integer.valueOf:(I)Ljava/lang/Integer;
        34: aload_2
        35: invokevirtual #20                 // Method java/util/TreeMap.put:(Ljava/lang/Object;Ljava/lang/Object;)Ljava/lang/Object;
        38: pop
        39: aload_3
        40: ifnull        60
        43: aload_0
        44: getfield      #8                  // Field _nativeIds:Ljava/util/TreeMap;
        47: aload_0
        48: iload_1
        49: invokespecial #21                 // Method _typeIdIndex:(I)I
        52: invokestatic  #19                 // Method java/lang/Integer.valueOf:(I)Ljava/lang/Integer;
        55: aload_3
        56: invokevirtual #20                 // Method java/util/TreeMap.put:(Ljava/lang/Object;Ljava/lang/Object;)Ljava/lang/Object;
        59: pop
        60: return
      LineNumberTable:
        line 2260: 0
        line 2261: 7
        line 2263: 18
        line 2264: 22
        line 2266: 39
        line 2267: 43
        line 2269: 60
      LocalVariableTable:
        Start  Length  Slot  Name   Signature
            0      61     0  this   Lcom/fasterxml/jackson/databind/util/TokenBuffer$Segment;
            0      61     1 index   I
            0      61     2 objectId   Ljava/lang/Object;
            0      61     3 typeId   Ljava/lang/Object;
      StackMapTable: number_of_entries = 3
        frame_type = 18 /* same */
        frame_type = 20 /* same */
        frame_type = 20 /* same */

  java.lang.Object findObjectId(int);
    descriptor: (I)Ljava/lang/Object;
    flags: (0x0000)
    Code:
      stack=3, locals=2, args_size=2
         0: aload_0
         1: getfield      #8                  // Field _nativeIds:Ljava/util/TreeMap;
         4: ifnonnull     11
         7: aconst_null
         8: goto          26
        11: aload_0
        12: getfield      #8                  // Field _nativeIds:Ljava/util/TreeMap;
        15: aload_0
        16: iload_1
        17: invokespecial #18                 // Method _objectIdIndex:(I)I
        20: invokestatic  #19                 // Method java/lang/Integer.valueOf:(I)Ljava/lang/Integer;
        23: invokevirtual #22                 // Method java/util/TreeMap.get:(Ljava/lang/Object;)Ljava/lang/Object;
        26: areturn
      LineNumberTable:
        line 2275: 0
      LocalVariableTable:
        Start  Length  Slot  Name   Signature
            0      27     0  this   Lcom/fasterxml/jackson/databind/util/TokenBuffer$Segment;
            0      27     1 index   I
      StackMapTable: number_of_entries = 2
        frame_type = 11 /* same */
        frame_type = 78 /* same_locals_1_stack_item */
          stack = [ class java/lang/Object ]

  java.lang.Object findTypeId(int);
    descriptor: (I)Ljava/lang/Object;
    flags: (0x0000)
    Code:
      stack=3, locals=2, args_size=2
         0: aload_0
         1: getfield      #8                  // Field _nativeIds:Ljava/util/TreeMap;
         4: ifnonnull     11
         7: aconst_null
         8: goto          26
        11: aload_0
        12: getfield      #8                  // Field _nativeIds:Ljava/util/TreeMap;
        15: aload_0
        16: iload_1
        17: invokespecial #21                 // Method _typeIdIndex:(I)I
        20: invokestatic  #19                 // Method java/lang/Integer.valueOf:(I)Ljava/lang/Integer;
        23: invokevirtual #22                 // Method java/util/TreeMap.get:(Ljava/lang/Object;)Ljava/lang/Object;
        26: areturn
      LineNumberTable:
        line 2282: 0
      LocalVariableTable:
        Start  Length  Slot  Name   Signature
            0      27     0  this   Lcom/fasterxml/jackson/databind/util/TokenBuffer$Segment;
            0      27     1 index   I
      StackMapTable: number_of_entries = 2
        frame_type = 11 /* same */
        frame_type = 78 /* same_locals_1_stack_item */
          stack = [ class java/lang/Object ]

  private final int _typeIdIndex(int);
    descriptor: (I)I
    flags: (0x0012) ACC_PRIVATE, ACC_FINAL
    Code:
      stack=2, locals=2, args_size=2
         0: iload_1
         1: iload_1
         2: iadd
         3: ireturn
      LineNumberTable:
        line 2285: 0
      LocalVariableTable:
        Start  Length  Slot  Name   Signature
            0       4     0  this   Lcom/fasterxml/jackson/databind/util/TokenBuffer$Segment;
            0       4     1     i   I

  private final int _objectIdIndex(int);
    descriptor: (I)I
    flags: (0x0012) ACC_PRIVATE, ACC_FINAL
    Code:
      stack=2, locals=2, args_size=2
         0: iload_1
         1: iload_1
         2: iadd
         3: iconst_1
         4: iadd
         5: ireturn
      LineNumberTable:
        line 2286: 0
      LocalVariableTable:
        Start  Length  Slot  Name   Signature
            0       6     0  this   Lcom/fasterxml/jackson/databind/util/TokenBuffer$Segment;
            0       6     1     i   I

  static {};
    descriptor: ()V
    flags: (0x0008) ACC_STATIC
    Code:
      stack=7, locals=1, args_size=0
         0: bipush        16
         2: anewarray     #23                 // class com/fasterxml/jackson/core/JsonToken
         5: putstatic     #6                  // Field TOKEN_TYPES_BY_INDEX:[Lcom/fasterxml/jackson/core/JsonToken;
         8: invokestatic  #24                 // Method com/fasterxml/jackson/core/JsonToken.values:()[Lcom/fasterxml/jackson/core/JsonToken;
        11: astore_0
        12: aload_0
        13: iconst_1
        14: getstatic     #6                  // Field TOKEN_TYPES_BY_INDEX:[Lcom/fasterxml/jackson/core/JsonToken;
        17: iconst_1
        18: bipush        15
        20: aload_0
        21: arraylength
        22: iconst_1
        23: isub
        24: invokestatic  #25                 // Method java/lang/Math.min:(II)I
        27: invokestatic  #26                 // Method java/lang/System.arraycopy:(Ljava/lang/Object;ILjava/lang/Object;II)V
        30: return
      LineNumberTable:
        line 2053: 0
        line 2054: 8
        line 2056: 12
        line 2057: 30
      LocalVariableTable:
        Start  Length  Slot  Name   Signature
           12      18     0     t   [Lcom/fasterxml/jackson/core/JsonToken;
}
SourceFile: "TokenBuffer.java"
InnerClasses:
  protected static final #34= #2 of #95;  // Segment=class com/fasterxml/jackson/databind/util/TokenBuffer$Segment of class com/fasterxml/jackson/databind/util/TokenBuffer
