Classfile /Users/mw/Projects/slang-braindump/.jar/jar11/assemble/slang-braindump/assemble/content/com/fasterxml/jackson/databind/util/TokenBuffer.class
  Last modified May 29, 2022; size 25293 bytes
  SHA-256 checksum 38add28b9a4453252177fd1599970a761404a8c2be351dec97d911ddbf9a19f8
  Compiled from "TokenBuffer.java"
public class com.fasterxml.jackson.databind.util.TokenBuffer extends com.fasterxml.jackson.core.JsonGenerator
  minor version: 0
  major version: 52
  flags: (0x0021) ACC_PUBLIC, ACC_SUPER
  this_class: #25                         // com/fasterxml/jackson/databind/util/TokenBuffer
  super_class: #215                       // com/fasterxml/jackson/core/JsonGenerator
  interfaces: 0, fields: 16, methods: 88, attributes: 2
Constant pool:
    #1 = Methodref          #215.#462     // com/fasterxml/jackson/core/JsonGenerator."<init>":()V
    #2 = Fieldref           #25.#463      // com/fasterxml/jackson/databind/util/TokenBuffer._hasNativeId:Z
    #3 = Fieldref           #25.#464      // com/fasterxml/jackson/databind/util/TokenBuffer._objectCodec:Lcom/fasterxml/jackson/core/ObjectCodec;
    #4 = Fieldref           #25.#465      // com/fasterxml/jackson/databind/util/TokenBuffer.DEFAULT_GENERATOR_FEATURES:I
    #5 = Fieldref           #25.#466      // com/fasterxml/jackson/databind/util/TokenBuffer._generatorFeatures:I
    #6 = Methodref          #467.#468     // com/fasterxml/jackson/core/json/JsonWriteContext.createRootContext:(Lcom/fasterxml/jackson/core/json/DupDetector;)Lcom/fasterxml/jackson/core/json/JsonWriteContext;
    #7 = Fieldref           #25.#469      // com/fasterxml/jackson/databind/util/TokenBuffer._writeContext:Lcom/fasterxml/jackson/core/json/JsonWriteContext;
    #8 = Class              #470          // com/fasterxml/jackson/databind/util/TokenBuffer$Segment
    #9 = Methodref          #8.#462       // com/fasterxml/jackson/databind/util/TokenBuffer$Segment."<init>":()V
   #10 = Fieldref           #25.#471      // com/fasterxml/jackson/databind/util/TokenBuffer._last:Lcom/fasterxml/jackson/databind/util/TokenBuffer$Segment;
   #11 = Fieldref           #25.#472      // com/fasterxml/jackson/databind/util/TokenBuffer._first:Lcom/fasterxml/jackson/databind/util/TokenBuffer$Segment;
   #12 = Fieldref           #25.#473      // com/fasterxml/jackson/databind/util/TokenBuffer._appendAt:I
   #13 = Fieldref           #25.#474      // com/fasterxml/jackson/databind/util/TokenBuffer._hasNativeTypeIds:Z
   #14 = Fieldref           #25.#475      // com/fasterxml/jackson/databind/util/TokenBuffer._hasNativeObjectIds:Z
   #15 = Fieldref           #25.#476      // com/fasterxml/jackson/databind/util/TokenBuffer._mayHaveNativeIds:Z
   #16 = Methodref          #25.#477      // com/fasterxml/jackson/databind/util/TokenBuffer."<init>":(Lcom/fasterxml/jackson/core/JsonParser;Lcom/fasterxml/jackson/databind/DeserializationContext;)V
   #17 = Methodref          #478.#479     // com/fasterxml/jackson/core/JsonParser.getCodec:()Lcom/fasterxml/jackson/core/ObjectCodec;
   #18 = Methodref          #478.#480     // com/fasterxml/jackson/core/JsonParser.getParsingContext:()Lcom/fasterxml/jackson/core/JsonStreamContext;
   #19 = Fieldref           #25.#481      // com/fasterxml/jackson/databind/util/TokenBuffer._parentContext:Lcom/fasterxml/jackson/core/JsonStreamContext;
   #20 = Methodref          #478.#482     // com/fasterxml/jackson/core/JsonParser.canReadTypeId:()Z
   #21 = Methodref          #478.#483     // com/fasterxml/jackson/core/JsonParser.canReadObjectId:()Z
   #22 = Fieldref           #484.#485     // com/fasterxml/jackson/databind/DeserializationFeature.USE_BIG_DECIMAL_FOR_FLOATS:Lcom/fasterxml/jackson/databind/DeserializationFeature;
   #23 = Methodref          #486.#487     // com/fasterxml/jackson/databind/DeserializationContext.isEnabled:(Lcom/fasterxml/jackson/databind/DeserializationFeature;)Z
   #24 = Fieldref           #25.#488      // com/fasterxml/jackson/databind/util/TokenBuffer._forceBigDecimal:Z
   #25 = Class              #489          // com/fasterxml/jackson/databind/util/TokenBuffer
   #26 = Methodref          #25.#490      // com/fasterxml/jackson/databind/util/TokenBuffer."<init>":(Lcom/fasterxml/jackson/core/JsonParser;)V
   #27 = Methodref          #25.#491      // com/fasterxml/jackson/databind/util/TokenBuffer.copyCurrentStructure:(Lcom/fasterxml/jackson/core/JsonParser;)V
   #28 = Fieldref           #492.#493     // com/fasterxml/jackson/databind/cfg/PackageVersion.VERSION:Lcom/fasterxml/jackson/core/Version;
   #29 = Methodref          #25.#494      // com/fasterxml/jackson/databind/util/TokenBuffer.asParser:(Lcom/fasterxml/jackson/core/ObjectCodec;)Lcom/fasterxml/jackson/core/JsonParser;
   #30 = Methodref          #478.#495     // com/fasterxml/jackson/core/JsonParser.nextToken:()Lcom/fasterxml/jackson/core/JsonToken;
   #31 = Class              #496          // com/fasterxml/jackson/databind/util/TokenBuffer$Parser
   #32 = Methodref          #31.#497      // com/fasterxml/jackson/databind/util/TokenBuffer$Parser."<init>":(Lcom/fasterxml/jackson/databind/util/TokenBuffer$Segment;Lcom/fasterxml/jackson/core/ObjectCodec;ZZLcom/fasterxml/jackson/core/JsonStreamContext;)V
   #33 = Methodref          #478.#498     // com/fasterxml/jackson/core/JsonParser.getTokenLocation:()Lcom/fasterxml/jackson/core/JsonLocation;
   #34 = Methodref          #31.#499      // com/fasterxml/jackson/databind/util/TokenBuffer$Parser.setLocation:(Lcom/fasterxml/jackson/core/JsonLocation;)V
   #35 = Methodref          #8.#500       // com/fasterxml/jackson/databind/util/TokenBuffer$Segment.type:(I)Lcom/fasterxml/jackson/core/JsonToken;
   #36 = Methodref          #25.#501      // com/fasterxml/jackson/databind/util/TokenBuffer.canWriteTypeId:()Z
   #37 = Methodref          #25.#502      // com/fasterxml/jackson/databind/util/TokenBuffer.canWriteObjectId:()Z
   #38 = Methodref          #25.#503      // com/fasterxml/jackson/databind/util/TokenBuffer.asParser:()Lcom/fasterxml/jackson/core/JsonParser;
   #39 = Methodref          #8.#504       // com/fasterxml/jackson/databind/util/TokenBuffer$Segment.hasIds:()Z
   #40 = Methodref          #8.#505       // com/fasterxml/jackson/databind/util/TokenBuffer$Segment.next:()Lcom/fasterxml/jackson/databind/util/TokenBuffer$Segment;
   #41 = Methodref          #8.#506       // com/fasterxml/jackson/databind/util/TokenBuffer$Segment.findObjectId:(I)Ljava/lang/Object;
   #42 = Methodref          #215.#507     // com/fasterxml/jackson/core/JsonGenerator.writeObjectId:(Ljava/lang/Object;)V
   #43 = Methodref          #8.#508       // com/fasterxml/jackson/databind/util/TokenBuffer$Segment.findTypeId:(I)Ljava/lang/Object;
   #44 = Methodref          #215.#509     // com/fasterxml/jackson/core/JsonGenerator.writeTypeId:(Ljava/lang/Object;)V
   #45 = Fieldref           #216.#510     // com/fasterxml/jackson/databind/util/TokenBuffer$1.$SwitchMap$com$fasterxml$jackson$core$JsonToken:[I
   #46 = Methodref          #511.#512     // com/fasterxml/jackson/core/JsonToken.ordinal:()I
   #47 = Methodref          #215.#513     // com/fasterxml/jackson/core/JsonGenerator.writeStartObject:()V
   #48 = Methodref          #215.#514     // com/fasterxml/jackson/core/JsonGenerator.writeEndObject:()V
   #49 = Methodref          #215.#515     // com/fasterxml/jackson/core/JsonGenerator.writeStartArray:()V
   #50 = Methodref          #215.#516     // com/fasterxml/jackson/core/JsonGenerator.writeEndArray:()V
   #51 = Methodref          #8.#517       // com/fasterxml/jackson/databind/util/TokenBuffer$Segment.get:(I)Ljava/lang/Object;
   #52 = Class              #518          // com/fasterxml/jackson/core/SerializableString
   #53 = Methodref          #215.#519     // com/fasterxml/jackson/core/JsonGenerator.writeFieldName:(Lcom/fasterxml/jackson/core/SerializableString;)V
   #54 = Class              #520          // java/lang/String
   #55 = Methodref          #215.#521     // com/fasterxml/jackson/core/JsonGenerator.writeFieldName:(Ljava/lang/String;)V
   #56 = Methodref          #215.#522     // com/fasterxml/jackson/core/JsonGenerator.writeString:(Lcom/fasterxml/jackson/core/SerializableString;)V
   #57 = Methodref          #215.#523     // com/fasterxml/jackson/core/JsonGenerator.writeString:(Ljava/lang/String;)V
   #58 = Class              #524          // java/lang/Integer
   #59 = Methodref          #58.#525      // java/lang/Integer.intValue:()I
   #60 = Methodref          #215.#526     // com/fasterxml/jackson/core/JsonGenerator.writeNumber:(I)V
   #61 = Class              #527          // java/math/BigInteger
   #62 = Methodref          #215.#528     // com/fasterxml/jackson/core/JsonGenerator.writeNumber:(Ljava/math/BigInteger;)V
   #63 = Class              #529          // java/lang/Long
   #64 = Methodref          #63.#530      // java/lang/Long.longValue:()J
   #65 = Methodref          #215.#531     // com/fasterxml/jackson/core/JsonGenerator.writeNumber:(J)V
   #66 = Class              #532          // java/lang/Short
   #67 = Methodref          #66.#533      // java/lang/Short.shortValue:()S
   #68 = Methodref          #215.#534     // com/fasterxml/jackson/core/JsonGenerator.writeNumber:(S)V
   #69 = Class              #535          // java/lang/Number
   #70 = Methodref          #69.#525      // java/lang/Number.intValue:()I
   #71 = Class              #536          // java/lang/Double
   #72 = Methodref          #71.#537      // java/lang/Double.doubleValue:()D
   #73 = Methodref          #215.#538     // com/fasterxml/jackson/core/JsonGenerator.writeNumber:(D)V
   #74 = Class              #539          // java/math/BigDecimal
   #75 = Methodref          #215.#540     // com/fasterxml/jackson/core/JsonGenerator.writeNumber:(Ljava/math/BigDecimal;)V
   #76 = Class              #541          // java/lang/Float
   #77 = Methodref          #76.#542      // java/lang/Float.floatValue:()F
   #78 = Methodref          #215.#543     // com/fasterxml/jackson/core/JsonGenerator.writeNumber:(F)V
   #79 = Methodref          #215.#544     // com/fasterxml/jackson/core/JsonGenerator.writeNull:()V
   #80 = Methodref          #215.#545     // com/fasterxml/jackson/core/JsonGenerator.writeNumber:(Ljava/lang/String;)V
   #81 = String             #546          // Unrecognized value type for VALUE_NUMBER_FLOAT: %s, cannot serialize
   #82 = Class              #547          // java/lang/Object
   #83 = Methodref          #82.#548      // java/lang/Object.getClass:()Ljava/lang/Class;
   #84 = Methodref          #549.#550     // java/lang/Class.getName:()Ljava/lang/String;
   #85 = Methodref          #54.#551      // java/lang/String.format:(Ljava/lang/String;[Ljava/lang/Object;)Ljava/lang/String;
   #86 = Methodref          #25.#552      // com/fasterxml/jackson/databind/util/TokenBuffer._reportError:(Ljava/lang/String;)V
   #87 = Methodref          #215.#553     // com/fasterxml/jackson/core/JsonGenerator.writeBoolean:(Z)V
   #88 = Class              #554          // com/fasterxml/jackson/databind/util/RawValue
   #89 = Methodref          #88.#555      // com/fasterxml/jackson/databind/util/RawValue.serialize:(Lcom/fasterxml/jackson/core/JsonGenerator;)V
   #90 = Class              #556          // com/fasterxml/jackson/databind/JsonSerializable
   #91 = Methodref          #215.#557     // com/fasterxml/jackson/core/JsonGenerator.writeObject:(Ljava/lang/Object;)V
   #92 = Methodref          #215.#558     // com/fasterxml/jackson/core/JsonGenerator.writeEmbeddedObject:(Ljava/lang/Object;)V
   #93 = Class              #559          // java/lang/RuntimeException
   #94 = String             #560          // Internal error: should never end up through this code path
   #95 = Methodref          #93.#561      // java/lang/RuntimeException."<init>":(Ljava/lang/String;)V
   #96 = Fieldref           #511.#562     // com/fasterxml/jackson/core/JsonToken.FIELD_NAME:Lcom/fasterxml/jackson/core/JsonToken;
   #97 = Methodref          #478.#563     // com/fasterxml/jackson/core/JsonParser.hasToken:(Lcom/fasterxml/jackson/core/JsonToken;)Z
   #98 = Methodref          #25.#513      // com/fasterxml/jackson/databind/util/TokenBuffer.writeStartObject:()V
   #99 = Fieldref           #511.#564     // com/fasterxml/jackson/core/JsonToken.END_OBJECT:Lcom/fasterxml/jackson/core/JsonToken;
  #100 = Class              #565          // java/lang/StringBuilder
  #101 = Methodref          #100.#462     // java/lang/StringBuilder."<init>":()V
  #102 = String             #566          // Expected END_OBJECT after copying contents of a JsonParser into TokenBuffer, got
  #103 = Methodref          #100.#567     // java/lang/StringBuilder.append:(Ljava/lang/String;)Ljava/lang/StringBuilder;
  #104 = Methodref          #100.#568     // java/lang/StringBuilder.append:(Ljava/lang/Object;)Ljava/lang/StringBuilder;
  #105 = Methodref          #100.#569     // java/lang/StringBuilder.toString:()Ljava/lang/String;
  #106 = Methodref          #486.#570     // com/fasterxml/jackson/databind/DeserializationContext.reportWrongTokenException:(Ljava/lang/Class;Lcom/fasterxml/jackson/core/JsonToken;Ljava/lang/String;[Ljava/lang/Object;)V
  #107 = Methodref          #25.#514      // com/fasterxml/jackson/databind/util/TokenBuffer.writeEndObject:()V
  #108 = String             #571          // [TokenBuffer:
  #109 = Methodref          #25.#572      // com/fasterxml/jackson/databind/util/TokenBuffer._appendNativeIds:(Ljava/lang/StringBuilder;)V
  #110 = String             #573          // ,
  #111 = Methodref          #511.#569     // com/fasterxml/jackson/core/JsonToken.toString:()Ljava/lang/String;
  #112 = Methodref          #100.#574     // java/lang/StringBuilder.append:(C)Ljava/lang/StringBuilder;
  #113 = Methodref          #478.#575     // com/fasterxml/jackson/core/JsonParser.currentName:()Ljava/lang/String;
  #114 = Class              #576          // java/io/IOException
  #115 = Class              #577          // java/lang/IllegalStateException
  #116 = Methodref          #115.#578     // java/lang/IllegalStateException."<init>":(Ljava/lang/Throwable;)V
  #117 = String             #579          //  ... (truncated
  #118 = Methodref          #100.#580     // java/lang/StringBuilder.append:(I)Ljava/lang/StringBuilder;
  #119 = String             #581          //  entries)
  #120 = String             #582          // [objectId=
  #121 = Methodref          #54.#583      // java/lang/String.valueOf:(Ljava/lang/Object;)Ljava/lang/String;
  #122 = String             #584          // [typeId=
  #123 = Methodref          #325.#585     // com/fasterxml/jackson/core/JsonGenerator$Feature.getMask:()I
  #124 = Methodref          #25.#586      // com/fasterxml/jackson/databind/util/TokenBuffer.getFeatureMask:()I
  #125 = Fieldref           #25.#587      // com/fasterxml/jackson/databind/util/TokenBuffer.DEFAULT_WRITE_CAPABILITIES:Lcom/fasterxml/jackson/core/util/JacksonFeatureSet;
  #126 = Fieldref           #25.#588      // com/fasterxml/jackson/databind/util/TokenBuffer._closed:Z
  #127 = Methodref          #467.#589     // com/fasterxml/jackson/core/json/JsonWriteContext.writeValue:()I
  #128 = Fieldref           #511.#590     // com/fasterxml/jackson/core/JsonToken.START_ARRAY:Lcom/fasterxml/jackson/core/JsonToken;
  #129 = Methodref          #25.#591      // com/fasterxml/jackson/databind/util/TokenBuffer._appendStartMarker:(Lcom/fasterxml/jackson/core/JsonToken;)V
  #130 = Methodref          #467.#592     // com/fasterxml/jackson/core/json/JsonWriteContext.createChildArrayContext:()Lcom/fasterxml/jackson/core/json/JsonWriteContext;
  #131 = Methodref          #467.#593     // com/fasterxml/jackson/core/json/JsonWriteContext.createChildArrayContext:(Ljava/lang/Object;)Lcom/fasterxml/jackson/core/json/JsonWriteContext;
  #132 = Fieldref           #511.#594     // com/fasterxml/jackson/core/JsonToken.END_ARRAY:Lcom/fasterxml/jackson/core/JsonToken;
  #133 = Methodref          #25.#595      // com/fasterxml/jackson/databind/util/TokenBuffer._appendEndMarker:(Lcom/fasterxml/jackson/core/JsonToken;)V
  #134 = Methodref          #467.#596     // com/fasterxml/jackson/core/json/JsonWriteContext.getParent:()Lcom/fasterxml/jackson/core/json/JsonWriteContext;
  #135 = Fieldref           #511.#597     // com/fasterxml/jackson/core/JsonToken.START_OBJECT:Lcom/fasterxml/jackson/core/JsonToken;
  #136 = Methodref          #467.#598     // com/fasterxml/jackson/core/json/JsonWriteContext.createChildObjectContext:()Lcom/fasterxml/jackson/core/json/JsonWriteContext;
  #137 = Methodref          #467.#599     // com/fasterxml/jackson/core/json/JsonWriteContext.createChildObjectContext:(Ljava/lang/Object;)Lcom/fasterxml/jackson/core/json/JsonWriteContext;
  #138 = Methodref          #467.#600     // com/fasterxml/jackson/core/json/JsonWriteContext.writeFieldName:(Ljava/lang/String;)I
  #139 = Methodref          #25.#601      // com/fasterxml/jackson/databind/util/TokenBuffer._appendFieldName:(Ljava/lang/Object;)V
  #140 = InterfaceMethodref #52.#602      // com/fasterxml/jackson/core/SerializableString.getValue:()Ljava/lang/String;
  #141 = Methodref          #25.#544      // com/fasterxml/jackson/databind/util/TokenBuffer.writeNull:()V
  #142 = Fieldref           #511.#603     // com/fasterxml/jackson/core/JsonToken.VALUE_STRING:Lcom/fasterxml/jackson/core/JsonToken;
  #143 = Methodref          #25.#604      // com/fasterxml/jackson/databind/util/TokenBuffer._appendValue:(Lcom/fasterxml/jackson/core/JsonToken;Ljava/lang/Object;)V
  #144 = Methodref          #54.#605      // java/lang/String."<init>":([CII)V
  #145 = Methodref          #25.#523      // com/fasterxml/jackson/databind/util/TokenBuffer.writeString:(Ljava/lang/String;)V
  #146 = Methodref          #25.#606      // com/fasterxml/jackson/databind/util/TokenBuffer._reportUnsupportedOperation:()V
  #147 = Fieldref           #511.#607     // com/fasterxml/jackson/core/JsonToken.VALUE_EMBEDDED_OBJECT:Lcom/fasterxml/jackson/core/JsonToken;
  #148 = Methodref          #88.#561      // com/fasterxml/jackson/databind/util/RawValue."<init>":(Ljava/lang/String;)V
  #149 = Methodref          #54.#608      // java/lang/String.length:()I
  #150 = Methodref          #54.#609      // java/lang/String.substring:(II)Ljava/lang/String;
  #151 = Fieldref           #511.#610     // com/fasterxml/jackson/core/JsonToken.VALUE_NUMBER_INT:Lcom/fasterxml/jackson/core/JsonToken;
  #152 = Methodref          #66.#611      // java/lang/Short.valueOf:(S)Ljava/lang/Short;
  #153 = Methodref          #58.#612      // java/lang/Integer.valueOf:(I)Ljava/lang/Integer;
  #154 = Methodref          #63.#613      // java/lang/Long.valueOf:(J)Ljava/lang/Long;
  #155 = Fieldref           #511.#614     // com/fasterxml/jackson/core/JsonToken.VALUE_NUMBER_FLOAT:Lcom/fasterxml/jackson/core/JsonToken;
  #156 = Methodref          #71.#615      // java/lang/Double.valueOf:(D)Ljava/lang/Double;
  #157 = Methodref          #76.#616      // java/lang/Float.valueOf:(F)Ljava/lang/Float;
  #158 = Fieldref           #511.#617     // com/fasterxml/jackson/core/JsonToken.VALUE_TRUE:Lcom/fasterxml/jackson/core/JsonToken;
  #159 = Fieldref           #511.#618     // com/fasterxml/jackson/core/JsonToken.VALUE_FALSE:Lcom/fasterxml/jackson/core/JsonToken;
  #160 = Methodref          #25.#619      // com/fasterxml/jackson/databind/util/TokenBuffer._appendValue:(Lcom/fasterxml/jackson/core/JsonToken;)V
  #161 = Fieldref           #511.#620     // com/fasterxml/jackson/core/JsonToken.VALUE_NULL:Lcom/fasterxml/jackson/core/JsonToken;
  #162 = Class              #384          // "[B"
  #163 = Methodref          #621.#622     // com/fasterxml/jackson/core/ObjectCodec.writeValue:(Lcom/fasterxml/jackson/core/JsonGenerator;Ljava/lang/Object;)V
  #164 = Methodref          #621.#623     // com/fasterxml/jackson/core/ObjectCodec.writeTree:(Lcom/fasterxml/jackson/core/JsonGenerator;Lcom/fasterxml/jackson/core/TreeNode;)V
  #165 = Methodref          #624.#625     // java/lang/System.arraycopy:(Ljava/lang/Object;ILjava/lang/Object;II)V
  #166 = Methodref          #25.#557      // com/fasterxml/jackson/databind/util/TokenBuffer.writeObject:(Ljava/lang/Object;)V
  #167 = Class              #626          // java/lang/UnsupportedOperationException
  #168 = Methodref          #167.#462     // java/lang/UnsupportedOperationException."<init>":()V
  #169 = Fieldref           #25.#627      // com/fasterxml/jackson/databind/util/TokenBuffer._typeId:Ljava/lang/Object;
  #170 = Fieldref           #25.#628      // com/fasterxml/jackson/databind/util/TokenBuffer._objectId:Ljava/lang/Object;
  #171 = Methodref          #25.#629      // com/fasterxml/jackson/databind/util/TokenBuffer._checkNativeIds:(Lcom/fasterxml/jackson/core/JsonParser;)V
  #172 = Methodref          #478.#630     // com/fasterxml/jackson/core/JsonParser.currentToken:()Lcom/fasterxml/jackson/core/JsonToken;
  #173 = Methodref          #25.#515      // com/fasterxml/jackson/databind/util/TokenBuffer.writeStartArray:()V
  #174 = Methodref          #25.#516      // com/fasterxml/jackson/databind/util/TokenBuffer.writeEndArray:()V
  #175 = Methodref          #25.#521      // com/fasterxml/jackson/databind/util/TokenBuffer.writeFieldName:(Ljava/lang/String;)V
  #176 = Methodref          #478.#631     // com/fasterxml/jackson/core/JsonParser.hasTextCharacters:()Z
  #177 = Methodref          #478.#632     // com/fasterxml/jackson/core/JsonParser.getTextCharacters:()[C
  #178 = Methodref          #478.#633     // com/fasterxml/jackson/core/JsonParser.getTextOffset:()I
  #179 = Methodref          #478.#634     // com/fasterxml/jackson/core/JsonParser.getTextLength:()I
  #180 = Methodref          #25.#635      // com/fasterxml/jackson/databind/util/TokenBuffer.writeString:([CII)V
  #181 = Methodref          #478.#636     // com/fasterxml/jackson/core/JsonParser.getText:()Ljava/lang/String;
  #182 = Fieldref           #216.#637     // com/fasterxml/jackson/databind/util/TokenBuffer$1.$SwitchMap$com$fasterxml$jackson$core$JsonParser$NumberType:[I
  #183 = Methodref          #478.#638     // com/fasterxml/jackson/core/JsonParser.getNumberType:()Lcom/fasterxml/jackson/core/JsonParser$NumberType;
  #184 = Methodref          #639.#512     // com/fasterxml/jackson/core/JsonParser$NumberType.ordinal:()I
  #185 = Methodref          #478.#640     // com/fasterxml/jackson/core/JsonParser.getIntValue:()I
  #186 = Methodref          #25.#526      // com/fasterxml/jackson/databind/util/TokenBuffer.writeNumber:(I)V
  #187 = Methodref          #478.#641     // com/fasterxml/jackson/core/JsonParser.getBigIntegerValue:()Ljava/math/BigInteger;
  #188 = Methodref          #25.#528      // com/fasterxml/jackson/databind/util/TokenBuffer.writeNumber:(Ljava/math/BigInteger;)V
  #189 = Methodref          #478.#642     // com/fasterxml/jackson/core/JsonParser.getLongValue:()J
  #190 = Methodref          #25.#531      // com/fasterxml/jackson/databind/util/TokenBuffer.writeNumber:(J)V
  #191 = Methodref          #478.#643     // com/fasterxml/jackson/core/JsonParser.getDecimalValue:()Ljava/math/BigDecimal;
  #192 = Methodref          #25.#540      // com/fasterxml/jackson/databind/util/TokenBuffer.writeNumber:(Ljava/math/BigDecimal;)V
  #193 = Methodref          #478.#644     // com/fasterxml/jackson/core/JsonParser.getFloatValue:()F
  #194 = Methodref          #25.#543      // com/fasterxml/jackson/databind/util/TokenBuffer.writeNumber:(F)V
  #195 = Methodref          #478.#645     // com/fasterxml/jackson/core/JsonParser.getDoubleValue:()D
  #196 = Methodref          #25.#538      // com/fasterxml/jackson/databind/util/TokenBuffer.writeNumber:(D)V
  #197 = Methodref          #25.#553      // com/fasterxml/jackson/databind/util/TokenBuffer.writeBoolean:(Z)V
  #198 = Methodref          #478.#646     // com/fasterxml/jackson/core/JsonParser.getEmbeddedObject:()Ljava/lang/Object;
  #199 = String             #647          // Internal error: unexpected token:
  #200 = String             #648          // No token available from argument `JsonParser`
  #201 = Methodref          #115.#561     // java/lang/IllegalStateException."<init>":(Ljava/lang/String;)V
  #202 = Methodref          #25.#649      // com/fasterxml/jackson/databind/util/TokenBuffer._copyBufferContents:(Lcom/fasterxml/jackson/core/JsonParser;)V
  #203 = Methodref          #25.#650      // com/fasterxml/jackson/databind/util/TokenBuffer._copyBufferValue:(Lcom/fasterxml/jackson/core/JsonParser;Lcom/fasterxml/jackson/core/JsonToken;)V
  #204 = Methodref          #478.#651     // com/fasterxml/jackson/core/JsonParser.getNumberValueExact:()Ljava/lang/Number;
  #205 = Methodref          #478.#652     // com/fasterxml/jackson/core/JsonParser.getTypeId:()Ljava/lang/Object;
  #206 = Methodref          #478.#653     // com/fasterxml/jackson/core/JsonParser.getObjectId:()Ljava/lang/Object;
  #207 = Methodref          #8.#654       // com/fasterxml/jackson/databind/util/TokenBuffer$Segment.append:(ILcom/fasterxml/jackson/core/JsonToken;Ljava/lang/Object;Ljava/lang/Object;)Lcom/fasterxml/jackson/databind/util/TokenBuffer$Segment;
  #208 = Methodref          #8.#655       // com/fasterxml/jackson/databind/util/TokenBuffer$Segment.append:(ILcom/fasterxml/jackson/core/JsonToken;)Lcom/fasterxml/jackson/databind/util/TokenBuffer$Segment;
  #209 = Methodref          #8.#656       // com/fasterxml/jackson/databind/util/TokenBuffer$Segment.append:(ILcom/fasterxml/jackson/core/JsonToken;Ljava/lang/Object;Ljava/lang/Object;Ljava/lang/Object;)Lcom/fasterxml/jackson/databind/util/TokenBuffer$Segment;
  #210 = Methodref          #8.#657       // com/fasterxml/jackson/databind/util/TokenBuffer$Segment.append:(ILcom/fasterxml/jackson/core/JsonToken;Ljava/lang/Object;)Lcom/fasterxml/jackson/databind/util/TokenBuffer$Segment;
  #211 = String             #658          // Called operation not supported for TokenBuffer
  #212 = Methodref          #167.#561     // java/lang/UnsupportedOperationException."<init>":(Ljava/lang/String;)V
  #213 = Methodref          #25.#659      // com/fasterxml/jackson/databind/util/TokenBuffer.getOutputContext:()Lcom/fasterxml/jackson/core/json/JsonWriteContext;
  #214 = Methodref          #325.#660     // com/fasterxml/jackson/core/JsonGenerator$Feature.collectDefaults:()I
  #215 = Class              #661          // com/fasterxml/jackson/core/JsonGenerator
  #216 = Class              #662          // com/fasterxml/jackson/databind/util/TokenBuffer$1
  #217 = Utf8               InnerClasses
  #218 = Utf8               Segment
  #219 = Utf8               Parser
  #220 = Utf8               DEFAULT_GENERATOR_FEATURES
  #221 = Utf8               I
  #222 = Utf8               _objectCodec
  #223 = Utf8               Lcom/fasterxml/jackson/core/ObjectCodec;
  #224 = Utf8               _parentContext
  #225 = Utf8               Lcom/fasterxml/jackson/core/JsonStreamContext;
  #226 = Utf8               _generatorFeatures
  #227 = Utf8               _closed
  #228 = Utf8               Z
  #229 = Utf8               _hasNativeTypeIds
  #230 = Utf8               _hasNativeObjectIds
  #231 = Utf8               _mayHaveNativeIds
  #232 = Utf8               _forceBigDecimal
  #233 = Utf8               _first
  #234 = Utf8               Lcom/fasterxml/jackson/databind/util/TokenBuffer$Segment;
  #235 = Utf8               _last
  #236 = Utf8               _appendAt
  #237 = Utf8               _typeId
  #238 = Utf8               Ljava/lang/Object;
  #239 = Utf8               _objectId
  #240 = Utf8               _hasNativeId
  #241 = Utf8               _writeContext
  #242 = Utf8               Lcom/fasterxml/jackson/core/json/JsonWriteContext;
  #243 = Utf8               <init>
  #244 = Utf8               (Lcom/fasterxml/jackson/core/ObjectCodec;Z)V
  #245 = Utf8               Code
  #246 = Utf8               LineNumberTable
  #247 = Utf8               LocalVariableTable
  #248 = Utf8               this
  #249 = Utf8               Lcom/fasterxml/jackson/databind/util/TokenBuffer;
  #250 = Utf8               codec
  #251 = Utf8               hasNativeIds
  #252 = Utf8               StackMapTable
  #253 = Class              #489          // com/fasterxml/jackson/databind/util/TokenBuffer
  #254 = Class              #663          // com/fasterxml/jackson/core/ObjectCodec
  #255 = Utf8               (Lcom/fasterxml/jackson/core/JsonParser;)V
  #256 = Utf8               p
  #257 = Utf8               Lcom/fasterxml/jackson/core/JsonParser;
  #258 = Utf8               (Lcom/fasterxml/jackson/core/JsonParser;Lcom/fasterxml/jackson/databind/DeserializationContext;)V
  #259 = Utf8               ctxt
  #260 = Utf8               Lcom/fasterxml/jackson/databind/DeserializationContext;
  #261 = Class              #664          // com/fasterxml/jackson/core/JsonParser
  #262 = Class              #665          // com/fasterxml/jackson/databind/DeserializationContext
  #263 = Utf8               asCopyOfValue
  #264 = Utf8               (Lcom/fasterxml/jackson/core/JsonParser;)Lcom/fasterxml/jackson/databind/util/TokenBuffer;
  #265 = Utf8               b
  #266 = Utf8               Exceptions
  #267 = Utf8               Deprecated
  #268 = Utf8               RuntimeVisibleAnnotations
  #269 = Utf8               Ljava/lang/Deprecated;
  #270 = Utf8               overrideParentContext
  #271 = Utf8               (Lcom/fasterxml/jackson/core/JsonStreamContext;)Lcom/fasterxml/jackson/databind/util/TokenBuffer;
  #272 = Utf8               forceUseOfBigDecimal
  #273 = Utf8               (Z)Lcom/fasterxml/jackson/databind/util/TokenBuffer;
  #274 = Utf8               version
  #275 = Utf8               ()Lcom/fasterxml/jackson/core/Version;
  #276 = Utf8               asParser
  #277 = Utf8               ()Lcom/fasterxml/jackson/core/JsonParser;
  #278 = Utf8               asParserOnFirstToken
  #279 = Utf8               (Lcom/fasterxml/jackson/core/ObjectCodec;)Lcom/fasterxml/jackson/core/JsonParser;
  #280 = Utf8               (Lcom/fasterxml/jackson/core/JsonParser;)Lcom/fasterxml/jackson/core/JsonParser;
  #281 = Utf8               src
  #282 = Utf8               Lcom/fasterxml/jackson/databind/util/TokenBuffer$Parser;
  #283 = Utf8               firstToken
  #284 = Utf8               ()Lcom/fasterxml/jackson/core/JsonToken;
  #285 = Utf8               isEmpty
  #286 = Utf8               ()Z
  #287 = Utf8               append
  #288 = Utf8               (Lcom/fasterxml/jackson/databind/util/TokenBuffer;)Lcom/fasterxml/jackson/databind/util/TokenBuffer;
  #289 = Utf8               other
  #290 = Utf8               serialize
  #291 = Utf8               (Lcom/fasterxml/jackson/core/JsonGenerator;)V
  #292 = Utf8               id
  #293 = Utf8               ob
  #294 = Utf8               n
  #295 = Utf8               value
  #296 = Utf8               t
  #297 = Utf8               Lcom/fasterxml/jackson/core/JsonToken;
  #298 = Utf8               gen
  #299 = Utf8               Lcom/fasterxml/jackson/core/JsonGenerator;
  #300 = Utf8               segment
  #301 = Utf8               ptr
  #302 = Utf8               checkIds
  #303 = Utf8               hasIds
  #304 = Class              #470          // com/fasterxml/jackson/databind/util/TokenBuffer$Segment
  #305 = Class              #666          // com/fasterxml/jackson/core/JsonToken
  #306 = Class              #547          // java/lang/Object
  #307 = Utf8               deserialize
  #308 = Utf8               (Lcom/fasterxml/jackson/core/JsonParser;Lcom/fasterxml/jackson/databind/DeserializationContext;)Lcom/fasterxml/jackson/databind/util/TokenBuffer;
  #309 = Utf8               toString
  #310 = Utf8               ()Ljava/lang/String;
  #311 = Utf8               ioe
  #312 = Utf8               Ljava/io/IOException;
  #313 = Utf8               MAX_COUNT
  #314 = Utf8               sb
  #315 = Utf8               Ljava/lang/StringBuilder;
  #316 = Utf8               jp
  #317 = Utf8               count
  #318 = Class              #565          // java/lang/StringBuilder
  #319 = Class              #576          // java/io/IOException
  #320 = Utf8               _appendNativeIds
  #321 = Utf8               (Ljava/lang/StringBuilder;)V
  #322 = Utf8               objectId
  #323 = Utf8               typeId
  #324 = Utf8               enable
  #325 = Class              #667          // com/fasterxml/jackson/core/JsonGenerator$Feature
  #326 = Utf8               Feature
  #327 = Utf8               (Lcom/fasterxml/jackson/core/JsonGenerator$Feature;)Lcom/fasterxml/jackson/core/JsonGenerator;
  #328 = Utf8               f
  #329 = Utf8               Lcom/fasterxml/jackson/core/JsonGenerator$Feature;
  #330 = Utf8               disable
  #331 = Utf8               isEnabled
  #332 = Utf8               (Lcom/fasterxml/jackson/core/JsonGenerator$Feature;)Z
  #333 = Utf8               getFeatureMask
  #334 = Utf8               ()I
  #335 = Utf8               setFeatureMask
  #336 = Utf8               (I)Lcom/fasterxml/jackson/core/JsonGenerator;
  #337 = Utf8               mask
  #338 = Utf8               overrideStdFeatures
  #339 = Utf8               (II)Lcom/fasterxml/jackson/core/JsonGenerator;
  #340 = Utf8               values
  #341 = Utf8               oldState
  #342 = Utf8               useDefaultPrettyPrinter
  #343 = Utf8               ()Lcom/fasterxml/jackson/core/JsonGenerator;
  #344 = Utf8               setCodec
  #345 = Utf8               (Lcom/fasterxml/jackson/core/ObjectCodec;)Lcom/fasterxml/jackson/core/JsonGenerator;
  #346 = Utf8               oc
  #347 = Utf8               getCodec
  #348 = Utf8               ()Lcom/fasterxml/jackson/core/ObjectCodec;
  #349 = Utf8               getOutputContext
  #350 = Utf8               ()Lcom/fasterxml/jackson/core/json/JsonWriteContext;
  #351 = Utf8               canWriteBinaryNatively
  #352 = Utf8               getWriteCapabilities
  #353 = Utf8               ()Lcom/fasterxml/jackson/core/util/JacksonFeatureSet;
  #354 = Utf8               Signature
  #355 = Utf8               ()Lcom/fasterxml/jackson/core/util/JacksonFeatureSet<Lcom/fasterxml/jackson/core/StreamWriteCapability;>;
  #356 = Utf8               flush
  #357 = Utf8               ()V
  #358 = Utf8               close
  #359 = Utf8               isClosed
  #360 = Utf8               writeStartArray
  #361 = Utf8               (Ljava/lang/Object;)V
  #362 = Utf8               forValue
  #363 = Utf8               (Ljava/lang/Object;I)V
  #364 = Utf8               size
  #365 = Utf8               writeEndArray
  #366 = Utf8               c
  #367 = Class              #668          // com/fasterxml/jackson/core/json/JsonWriteContext
  #368 = Utf8               writeStartObject
  #369 = Utf8               writeEndObject
  #370 = Utf8               writeFieldName
  #371 = Utf8               (Ljava/lang/String;)V
  #372 = Utf8               name
  #373 = Utf8               Ljava/lang/String;
  #374 = Utf8               (Lcom/fasterxml/jackson/core/SerializableString;)V
  #375 = Utf8               Lcom/fasterxml/jackson/core/SerializableString;
  #376 = Utf8               writeString
  #377 = Utf8               text
  #378 = Utf8               ([CII)V
  #379 = Utf8               [C
  #380 = Utf8               offset
  #381 = Utf8               len
  #382 = Utf8               writeRawUTF8String
  #383 = Utf8               ([BII)V
  #384 = Utf8               [B
  #385 = Utf8               length
  #386 = Utf8               writeUTF8String
  #387 = Utf8               writeRaw
  #388 = Utf8               (Ljava/lang/String;II)V
  #389 = Utf8               (C)V
  #390 = Utf8               C
  #391 = Utf8               writeRawValue
  #392 = Utf8               writeNumber
  #393 = Utf8               (S)V
  #394 = Utf8               i
  #395 = Utf8               S
  #396 = Utf8               (I)V
  #397 = Utf8               (J)V
  #398 = Utf8               l
  #399 = Utf8               J
  #400 = Utf8               (D)V
  #401 = Utf8               d
  #402 = Utf8               D
  #403 = Utf8               (F)V
  #404 = Utf8               F
  #405 = Utf8               (Ljava/math/BigDecimal;)V
  #406 = Utf8               dec
  #407 = Utf8               Ljava/math/BigDecimal;
  #408 = Utf8               (Ljava/math/BigInteger;)V
  #409 = Utf8               v
  #410 = Utf8               Ljava/math/BigInteger;
  #411 = Utf8               encodedValue
  #412 = Utf8               writeBoolean
  #413 = Utf8               (Z)V
  #414 = Utf8               state
  #415 = Utf8               writeNull
  #416 = Utf8               writeObject
  #417 = Utf8               raw
  #418 = Utf8               Ljava/lang/Class;
  #419 = Utf8               LocalVariableTypeTable
  #420 = Utf8               Ljava/lang/Class<*>;
  #421 = Class              #669          // java/lang/Class
  #422 = Utf8               writeTree
  #423 = Utf8               (Lcom/fasterxml/jackson/core/TreeNode;)V
  #424 = Utf8               node
  #425 = Utf8               Lcom/fasterxml/jackson/core/TreeNode;
  #426 = Utf8               writeBinary
  #427 = Utf8               (Lcom/fasterxml/jackson/core/Base64Variant;[BII)V
  #428 = Utf8               b64variant
  #429 = Utf8               Lcom/fasterxml/jackson/core/Base64Variant;
  #430 = Utf8               data
  #431 = Utf8               copy
  #432 = Utf8               (Lcom/fasterxml/jackson/core/Base64Variant;Ljava/io/InputStream;I)I
  #433 = Utf8               Ljava/io/InputStream;
  #434 = Utf8               dataLength
  #435 = Utf8               canWriteTypeId
  #436 = Utf8               canWriteObjectId
  #437 = Utf8               writeTypeId
  #438 = Utf8               writeObjectId
  #439 = Utf8               writeEmbeddedObject
  #440 = Utf8               object
  #441 = Utf8               copyCurrentEvent
  #442 = Utf8               copyCurrentStructure
  #443 = Utf8               _copyBufferContents
  #444 = Utf8               depth
  #445 = Utf8               _copyBufferValue
  #446 = Utf8               (Lcom/fasterxml/jackson/core/JsonParser;Lcom/fasterxml/jackson/core/JsonToken;)V
  #447 = Utf8               Ljava/lang/Number;
  #448 = Utf8               _checkNativeIds
  #449 = Utf8               _appendValue
  #450 = Utf8               (Lcom/fasterxml/jackson/core/JsonToken;)V
  #451 = Utf8               next
  #452 = Utf8               type
  #453 = Utf8               (Lcom/fasterxml/jackson/core/JsonToken;Ljava/lang/Object;)V
  #454 = Utf8               _appendFieldName
  #455 = Utf8               _appendStartMarker
  #456 = Utf8               _appendEndMarker
  #457 = Utf8               _reportUnsupportedOperation
  #458 = Utf8               ()Lcom/fasterxml/jackson/core/JsonStreamContext;
  #459 = Utf8               <clinit>
  #460 = Utf8               SourceFile
  #461 = Utf8               TokenBuffer.java
  #462 = NameAndType        #243:#357     // "<init>":()V
  #463 = NameAndType        #240:#228     // _hasNativeId:Z
  #464 = NameAndType        #222:#223     // _objectCodec:Lcom/fasterxml/jackson/core/ObjectCodec;
  #465 = NameAndType        #220:#221     // DEFAULT_GENERATOR_FEATURES:I
  #466 = NameAndType        #226:#221     // _generatorFeatures:I
  #467 = Class              #668          // com/fasterxml/jackson/core/json/JsonWriteContext
  #468 = NameAndType        #670:#671     // createRootContext:(Lcom/fasterxml/jackson/core/json/DupDetector;)Lcom/fasterxml/jackson/core/json/JsonWriteContext;
  #469 = NameAndType        #241:#242     // _writeContext:Lcom/fasterxml/jackson/core/json/JsonWriteContext;
  #470 = Utf8               com/fasterxml/jackson/databind/util/TokenBuffer$Segment
  #471 = NameAndType        #235:#234     // _last:Lcom/fasterxml/jackson/databind/util/TokenBuffer$Segment;
  #472 = NameAndType        #233:#234     // _first:Lcom/fasterxml/jackson/databind/util/TokenBuffer$Segment;
  #473 = NameAndType        #236:#221     // _appendAt:I
  #474 = NameAndType        #229:#228     // _hasNativeTypeIds:Z
  #475 = NameAndType        #230:#228     // _hasNativeObjectIds:Z
  #476 = NameAndType        #231:#228     // _mayHaveNativeIds:Z
  #477 = NameAndType        #243:#258     // "<init>":(Lcom/fasterxml/jackson/core/JsonParser;Lcom/fasterxml/jackson/databind/DeserializationContext;)V
  #478 = Class              #664          // com/fasterxml/jackson/core/JsonParser
  #479 = NameAndType        #347:#348     // getCodec:()Lcom/fasterxml/jackson/core/ObjectCodec;
  #480 = NameAndType        #672:#458     // getParsingContext:()Lcom/fasterxml/jackson/core/JsonStreamContext;
  #481 = NameAndType        #224:#225     // _parentContext:Lcom/fasterxml/jackson/core/JsonStreamContext;
  #482 = NameAndType        #673:#286     // canReadTypeId:()Z
  #483 = NameAndType        #674:#286     // canReadObjectId:()Z
  #484 = Class              #675          // com/fasterxml/jackson/databind/DeserializationFeature
  #485 = NameAndType        #676:#677     // USE_BIG_DECIMAL_FOR_FLOATS:Lcom/fasterxml/jackson/databind/DeserializationFeature;
  #486 = Class              #665          // com/fasterxml/jackson/databind/DeserializationContext
  #487 = NameAndType        #331:#678     // isEnabled:(Lcom/fasterxml/jackson/databind/DeserializationFeature;)Z
  #488 = NameAndType        #232:#228     // _forceBigDecimal:Z
  #489 = Utf8               com/fasterxml/jackson/databind/util/TokenBuffer
  #490 = NameAndType        #243:#255     // "<init>":(Lcom/fasterxml/jackson/core/JsonParser;)V
  #491 = NameAndType        #442:#255     // copyCurrentStructure:(Lcom/fasterxml/jackson/core/JsonParser;)V
  #492 = Class              #679          // com/fasterxml/jackson/databind/cfg/PackageVersion
  #493 = NameAndType        #680:#681     // VERSION:Lcom/fasterxml/jackson/core/Version;
  #494 = NameAndType        #276:#279     // asParser:(Lcom/fasterxml/jackson/core/ObjectCodec;)Lcom/fasterxml/jackson/core/JsonParser;
  #495 = NameAndType        #682:#284     // nextToken:()Lcom/fasterxml/jackson/core/JsonToken;
  #496 = Utf8               com/fasterxml/jackson/databind/util/TokenBuffer$Parser
  #497 = NameAndType        #243:#683     // "<init>":(Lcom/fasterxml/jackson/databind/util/TokenBuffer$Segment;Lcom/fasterxml/jackson/core/ObjectCodec;ZZLcom/fasterxml/jackson/core/JsonStreamContext;)V
  #498 = NameAndType        #684:#685     // getTokenLocation:()Lcom/fasterxml/jackson/core/JsonLocation;
  #499 = NameAndType        #686:#687     // setLocation:(Lcom/fasterxml/jackson/core/JsonLocation;)V
  #500 = NameAndType        #452:#688     // type:(I)Lcom/fasterxml/jackson/core/JsonToken;
  #501 = NameAndType        #435:#286     // canWriteTypeId:()Z
  #502 = NameAndType        #436:#286     // canWriteObjectId:()Z
  #503 = NameAndType        #276:#277     // asParser:()Lcom/fasterxml/jackson/core/JsonParser;
  #504 = NameAndType        #303:#286     // hasIds:()Z
  #505 = NameAndType        #451:#689     // next:()Lcom/fasterxml/jackson/databind/util/TokenBuffer$Segment;
  #506 = NameAndType        #690:#691     // findObjectId:(I)Ljava/lang/Object;
  #507 = NameAndType        #438:#361     // writeObjectId:(Ljava/lang/Object;)V
  #508 = NameAndType        #692:#691     // findTypeId:(I)Ljava/lang/Object;
  #509 = NameAndType        #437:#361     // writeTypeId:(Ljava/lang/Object;)V
  #510 = NameAndType        #693:#694     // $SwitchMap$com$fasterxml$jackson$core$JsonToken:[I
  #511 = Class              #666          // com/fasterxml/jackson/core/JsonToken
  #512 = NameAndType        #695:#334     // ordinal:()I
  #513 = NameAndType        #368:#357     // writeStartObject:()V
  #514 = NameAndType        #369:#357     // writeEndObject:()V
  #515 = NameAndType        #360:#357     // writeStartArray:()V
  #516 = NameAndType        #365:#357     // writeEndArray:()V
  #517 = NameAndType        #696:#691     // get:(I)Ljava/lang/Object;
  #518 = Utf8               com/fasterxml/jackson/core/SerializableString
  #519 = NameAndType        #370:#374     // writeFieldName:(Lcom/fasterxml/jackson/core/SerializableString;)V
  #520 = Utf8               java/lang/String
  #521 = NameAndType        #370:#371     // writeFieldName:(Ljava/lang/String;)V
  #522 = NameAndType        #376:#374     // writeString:(Lcom/fasterxml/jackson/core/SerializableString;)V
  #523 = NameAndType        #376:#371     // writeString:(Ljava/lang/String;)V
  #524 = Utf8               java/lang/Integer
  #525 = NameAndType        #697:#334     // intValue:()I
  #526 = NameAndType        #392:#396     // writeNumber:(I)V
  #527 = Utf8               java/math/BigInteger
  #528 = NameAndType        #392:#408     // writeNumber:(Ljava/math/BigInteger;)V
  #529 = Utf8               java/lang/Long
  #530 = NameAndType        #698:#699     // longValue:()J
  #531 = NameAndType        #392:#397     // writeNumber:(J)V
  #532 = Utf8               java/lang/Short
  #533 = NameAndType        #700:#701     // shortValue:()S
  #534 = NameAndType        #392:#393     // writeNumber:(S)V
  #535 = Utf8               java/lang/Number
  #536 = Utf8               java/lang/Double
  #537 = NameAndType        #702:#703     // doubleValue:()D
  #538 = NameAndType        #392:#400     // writeNumber:(D)V
  #539 = Utf8               java/math/BigDecimal
  #540 = NameAndType        #392:#405     // writeNumber:(Ljava/math/BigDecimal;)V
  #541 = Utf8               java/lang/Float
  #542 = NameAndType        #704:#705     // floatValue:()F
  #543 = NameAndType        #392:#403     // writeNumber:(F)V
  #544 = NameAndType        #415:#357     // writeNull:()V
  #545 = NameAndType        #392:#371     // writeNumber:(Ljava/lang/String;)V
  #546 = Utf8               Unrecognized value type for VALUE_NUMBER_FLOAT: %s, cannot serialize
  #547 = Utf8               java/lang/Object
  #548 = NameAndType        #706:#707     // getClass:()Ljava/lang/Class;
  #549 = Class              #669          // java/lang/Class
  #550 = NameAndType        #708:#310     // getName:()Ljava/lang/String;
  #551 = NameAndType        #709:#710     // format:(Ljava/lang/String;[Ljava/lang/Object;)Ljava/lang/String;
  #552 = NameAndType        #711:#371     // _reportError:(Ljava/lang/String;)V
  #553 = NameAndType        #412:#413     // writeBoolean:(Z)V
  #554 = Utf8               com/fasterxml/jackson/databind/util/RawValue
  #555 = NameAndType        #290:#291     // serialize:(Lcom/fasterxml/jackson/core/JsonGenerator;)V
  #556 = Utf8               com/fasterxml/jackson/databind/JsonSerializable
  #557 = NameAndType        #416:#361     // writeObject:(Ljava/lang/Object;)V
  #558 = NameAndType        #439:#361     // writeEmbeddedObject:(Ljava/lang/Object;)V
  #559 = Utf8               java/lang/RuntimeException
  #560 = Utf8               Internal error: should never end up through this code path
  #561 = NameAndType        #243:#371     // "<init>":(Ljava/lang/String;)V
  #562 = NameAndType        #712:#297     // FIELD_NAME:Lcom/fasterxml/jackson/core/JsonToken;
  #563 = NameAndType        #713:#714     // hasToken:(Lcom/fasterxml/jackson/core/JsonToken;)Z
  #564 = NameAndType        #715:#297     // END_OBJECT:Lcom/fasterxml/jackson/core/JsonToken;
  #565 = Utf8               java/lang/StringBuilder
  #566 = Utf8               Expected END_OBJECT after copying contents of a JsonParser into TokenBuffer, got
  #567 = NameAndType        #287:#716     // append:(Ljava/lang/String;)Ljava/lang/StringBuilder;
  #568 = NameAndType        #287:#717     // append:(Ljava/lang/Object;)Ljava/lang/StringBuilder;
  #569 = NameAndType        #309:#310     // toString:()Ljava/lang/String;
  #570 = NameAndType        #718:#719     // reportWrongTokenException:(Ljava/lang/Class;Lcom/fasterxml/jackson/core/JsonToken;Ljava/lang/String;[Ljava/lang/Object;)V
  #571 = Utf8               [TokenBuffer:
  #572 = NameAndType        #320:#321     // _appendNativeIds:(Ljava/lang/StringBuilder;)V
  #573 = Utf8               ,
  #574 = NameAndType        #287:#720     // append:(C)Ljava/lang/StringBuilder;
  #575 = NameAndType        #721:#310     // currentName:()Ljava/lang/String;
  #576 = Utf8               java/io/IOException
  #577 = Utf8               java/lang/IllegalStateException
  #578 = NameAndType        #243:#722     // "<init>":(Ljava/lang/Throwable;)V
  #579 = Utf8                ... (truncated
  #580 = NameAndType        #287:#723     // append:(I)Ljava/lang/StringBuilder;
  #581 = Utf8                entries)
  #582 = Utf8               [objectId=
  #583 = NameAndType        #724:#725     // valueOf:(Ljava/lang/Object;)Ljava/lang/String;
  #584 = Utf8               [typeId=
  #585 = NameAndType        #726:#334     // getMask:()I
  #586 = NameAndType        #333:#334     // getFeatureMask:()I
  #587 = NameAndType        #727:#728     // DEFAULT_WRITE_CAPABILITIES:Lcom/fasterxml/jackson/core/util/JacksonFeatureSet;
  #588 = NameAndType        #227:#228     // _closed:Z
  #589 = NameAndType        #729:#334     // writeValue:()I
  #590 = NameAndType        #730:#297     // START_ARRAY:Lcom/fasterxml/jackson/core/JsonToken;
  #591 = NameAndType        #455:#450     // _appendStartMarker:(Lcom/fasterxml/jackson/core/JsonToken;)V
  #592 = NameAndType        #731:#350     // createChildArrayContext:()Lcom/fasterxml/jackson/core/json/JsonWriteContext;
  #593 = NameAndType        #731:#732     // createChildArrayContext:(Ljava/lang/Object;)Lcom/fasterxml/jackson/core/json/JsonWriteContext;
  #594 = NameAndType        #733:#297     // END_ARRAY:Lcom/fasterxml/jackson/core/JsonToken;
  #595 = NameAndType        #456:#450     // _appendEndMarker:(Lcom/fasterxml/jackson/core/JsonToken;)V
  #596 = NameAndType        #734:#350     // getParent:()Lcom/fasterxml/jackson/core/json/JsonWriteContext;
  #597 = NameAndType        #735:#297     // START_OBJECT:Lcom/fasterxml/jackson/core/JsonToken;
  #598 = NameAndType        #736:#350     // createChildObjectContext:()Lcom/fasterxml/jackson/core/json/JsonWriteContext;
  #599 = NameAndType        #736:#732     // createChildObjectContext:(Ljava/lang/Object;)Lcom/fasterxml/jackson/core/json/JsonWriteContext;
  #600 = NameAndType        #370:#737     // writeFieldName:(Ljava/lang/String;)I
  #601 = NameAndType        #454:#361     // _appendFieldName:(Ljava/lang/Object;)V
  #602 = NameAndType        #738:#310     // getValue:()Ljava/lang/String;
  #603 = NameAndType        #739:#297     // VALUE_STRING:Lcom/fasterxml/jackson/core/JsonToken;
  #604 = NameAndType        #449:#453     // _appendValue:(Lcom/fasterxml/jackson/core/JsonToken;Ljava/lang/Object;)V
  #605 = NameAndType        #243:#378     // "<init>":([CII)V
  #606 = NameAndType        #457:#357     // _reportUnsupportedOperation:()V
  #607 = NameAndType        #740:#297     // VALUE_EMBEDDED_OBJECT:Lcom/fasterxml/jackson/core/JsonToken;
  #608 = NameAndType        #385:#334     // length:()I
  #609 = NameAndType        #741:#742     // substring:(II)Ljava/lang/String;
  #610 = NameAndType        #743:#297     // VALUE_NUMBER_INT:Lcom/fasterxml/jackson/core/JsonToken;
  #611 = NameAndType        #724:#744     // valueOf:(S)Ljava/lang/Short;
  #612 = NameAndType        #724:#745     // valueOf:(I)Ljava/lang/Integer;
  #613 = NameAndType        #724:#746     // valueOf:(J)Ljava/lang/Long;
  #614 = NameAndType        #747:#297     // VALUE_NUMBER_FLOAT:Lcom/fasterxml/jackson/core/JsonToken;
  #615 = NameAndType        #724:#748     // valueOf:(D)Ljava/lang/Double;
  #616 = NameAndType        #724:#749     // valueOf:(F)Ljava/lang/Float;
  #617 = NameAndType        #750:#297     // VALUE_TRUE:Lcom/fasterxml/jackson/core/JsonToken;
  #618 = NameAndType        #751:#297     // VALUE_FALSE:Lcom/fasterxml/jackson/core/JsonToken;
  #619 = NameAndType        #449:#450     // _appendValue:(Lcom/fasterxml/jackson/core/JsonToken;)V
  #620 = NameAndType        #752:#297     // VALUE_NULL:Lcom/fasterxml/jackson/core/JsonToken;
  #621 = Class              #663          // com/fasterxml/jackson/core/ObjectCodec
  #622 = NameAndType        #729:#753     // writeValue:(Lcom/fasterxml/jackson/core/JsonGenerator;Ljava/lang/Object;)V
  #623 = NameAndType        #422:#754     // writeTree:(Lcom/fasterxml/jackson/core/JsonGenerator;Lcom/fasterxml/jackson/core/TreeNode;)V
  #624 = Class              #755          // java/lang/System
  #625 = NameAndType        #756:#757     // arraycopy:(Ljava/lang/Object;ILjava/lang/Object;II)V
  #626 = Utf8               java/lang/UnsupportedOperationException
  #627 = NameAndType        #237:#238     // _typeId:Ljava/lang/Object;
  #628 = NameAndType        #239:#238     // _objectId:Ljava/lang/Object;
  #629 = NameAndType        #448:#255     // _checkNativeIds:(Lcom/fasterxml/jackson/core/JsonParser;)V
  #630 = NameAndType        #758:#284     // currentToken:()Lcom/fasterxml/jackson/core/JsonToken;
  #631 = NameAndType        #759:#286     // hasTextCharacters:()Z
  #632 = NameAndType        #760:#761     // getTextCharacters:()[C
  #633 = NameAndType        #762:#334     // getTextOffset:()I
  #634 = NameAndType        #763:#334     // getTextLength:()I
  #635 = NameAndType        #376:#378     // writeString:([CII)V
  #636 = NameAndType        #764:#310     // getText:()Ljava/lang/String;
  #637 = NameAndType        #765:#694     // $SwitchMap$com$fasterxml$jackson$core$JsonParser$NumberType:[I
  #638 = NameAndType        #766:#768     // getNumberType:()Lcom/fasterxml/jackson/core/JsonParser$NumberType;
  #639 = Class              #769          // com/fasterxml/jackson/core/JsonParser$NumberType
  #640 = NameAndType        #770:#334     // getIntValue:()I
  #641 = NameAndType        #771:#772     // getBigIntegerValue:()Ljava/math/BigInteger;
  #642 = NameAndType        #773:#699     // getLongValue:()J
  #643 = NameAndType        #774:#775     // getDecimalValue:()Ljava/math/BigDecimal;
  #644 = NameAndType        #776:#705     // getFloatValue:()F
  #645 = NameAndType        #777:#703     // getDoubleValue:()D
  #646 = NameAndType        #778:#779     // getEmbeddedObject:()Ljava/lang/Object;
  #647 = Utf8               Internal error: unexpected token:
  #648 = Utf8               No token available from argument `JsonParser`
  #649 = NameAndType        #443:#255     // _copyBufferContents:(Lcom/fasterxml/jackson/core/JsonParser;)V
  #650 = NameAndType        #445:#446     // _copyBufferValue:(Lcom/fasterxml/jackson/core/JsonParser;Lcom/fasterxml/jackson/core/JsonToken;)V
  #651 = NameAndType        #780:#781     // getNumberValueExact:()Ljava/lang/Number;
  #652 = NameAndType        #782:#779     // getTypeId:()Ljava/lang/Object;
  #653 = NameAndType        #783:#779     // getObjectId:()Ljava/lang/Object;
  #654 = NameAndType        #287:#784     // append:(ILcom/fasterxml/jackson/core/JsonToken;Ljava/lang/Object;Ljava/lang/Object;)Lcom/fasterxml/jackson/databind/util/TokenBuffer$Segment;
  #655 = NameAndType        #287:#785     // append:(ILcom/fasterxml/jackson/core/JsonToken;)Lcom/fasterxml/jackson/databind/util/TokenBuffer$Segment;
  #656 = NameAndType        #287:#786     // append:(ILcom/fasterxml/jackson/core/JsonToken;Ljava/lang/Object;Ljava/lang/Object;Ljava/lang/Object;)Lcom/fasterxml/jackson/databind/util/TokenBuffer$Segment;
  #657 = NameAndType        #287:#787     // append:(ILcom/fasterxml/jackson/core/JsonToken;Ljava/lang/Object;)Lcom/fasterxml/jackson/databind/util/TokenBuffer$Segment;
  #658 = Utf8               Called operation not supported for TokenBuffer
  #659 = NameAndType        #349:#350     // getOutputContext:()Lcom/fasterxml/jackson/core/json/JsonWriteContext;
  #660 = NameAndType        #788:#334     // collectDefaults:()I
  #661 = Utf8               com/fasterxml/jackson/core/JsonGenerator
  #662 = Utf8               com/fasterxml/jackson/databind/util/TokenBuffer$1
  #663 = Utf8               com/fasterxml/jackson/core/ObjectCodec
  #664 = Utf8               com/fasterxml/jackson/core/JsonParser
  #665 = Utf8               com/fasterxml/jackson/databind/DeserializationContext
  #666 = Utf8               com/fasterxml/jackson/core/JsonToken
  #667 = Utf8               com/fasterxml/jackson/core/JsonGenerator$Feature
  #668 = Utf8               com/fasterxml/jackson/core/json/JsonWriteContext
  #669 = Utf8               java/lang/Class
  #670 = Utf8               createRootContext
  #671 = Utf8               (Lcom/fasterxml/jackson/core/json/DupDetector;)Lcom/fasterxml/jackson/core/json/JsonWriteContext;
  #672 = Utf8               getParsingContext
  #673 = Utf8               canReadTypeId
  #674 = Utf8               canReadObjectId
  #675 = Utf8               com/fasterxml/jackson/databind/DeserializationFeature
  #676 = Utf8               USE_BIG_DECIMAL_FOR_FLOATS
  #677 = Utf8               Lcom/fasterxml/jackson/databind/DeserializationFeature;
  #678 = Utf8               (Lcom/fasterxml/jackson/databind/DeserializationFeature;)Z
  #679 = Utf8               com/fasterxml/jackson/databind/cfg/PackageVersion
  #680 = Utf8               VERSION
  #681 = Utf8               Lcom/fasterxml/jackson/core/Version;
  #682 = Utf8               nextToken
  #683 = Utf8               (Lcom/fasterxml/jackson/databind/util/TokenBuffer$Segment;Lcom/fasterxml/jackson/core/ObjectCodec;ZZLcom/fasterxml/jackson/core/JsonStreamContext;)V
  #684 = Utf8               getTokenLocation
  #685 = Utf8               ()Lcom/fasterxml/jackson/core/JsonLocation;
  #686 = Utf8               setLocation
  #687 = Utf8               (Lcom/fasterxml/jackson/core/JsonLocation;)V
  #688 = Utf8               (I)Lcom/fasterxml/jackson/core/JsonToken;
  #689 = Utf8               ()Lcom/fasterxml/jackson/databind/util/TokenBuffer$Segment;
  #690 = Utf8               findObjectId
  #691 = Utf8               (I)Ljava/lang/Object;
  #692 = Utf8               findTypeId
  #693 = Utf8               $SwitchMap$com$fasterxml$jackson$core$JsonToken
  #694 = Utf8               [I
  #695 = Utf8               ordinal
  #696 = Utf8               get
  #697 = Utf8               intValue
  #698 = Utf8               longValue
  #699 = Utf8               ()J
  #700 = Utf8               shortValue
  #701 = Utf8               ()S
  #702 = Utf8               doubleValue
  #703 = Utf8               ()D
  #704 = Utf8               floatValue
  #705 = Utf8               ()F
  #706 = Utf8               getClass
  #707 = Utf8               ()Ljava/lang/Class;
  #708 = Utf8               getName
  #709 = Utf8               format
  #710 = Utf8               (Ljava/lang/String;[Ljava/lang/Object;)Ljava/lang/String;
  #711 = Utf8               _reportError
  #712 = Utf8               FIELD_NAME
  #713 = Utf8               hasToken
  #714 = Utf8               (Lcom/fasterxml/jackson/core/JsonToken;)Z
  #715 = Utf8               END_OBJECT
  #716 = Utf8               (Ljava/lang/String;)Ljava/lang/StringBuilder;
  #717 = Utf8               (Ljava/lang/Object;)Ljava/lang/StringBuilder;
  #718 = Utf8               reportWrongTokenException
  #719 = Utf8               (Ljava/lang/Class;Lcom/fasterxml/jackson/core/JsonToken;Ljava/lang/String;[Ljava/lang/Object;)V
  #720 = Utf8               (C)Ljava/lang/StringBuilder;
  #721 = Utf8               currentName
  #722 = Utf8               (Ljava/lang/Throwable;)V
  #723 = Utf8               (I)Ljava/lang/StringBuilder;
  #724 = Utf8               valueOf
  #725 = Utf8               (Ljava/lang/Object;)Ljava/lang/String;
  #726 = Utf8               getMask
  #727 = Utf8               DEFAULT_WRITE_CAPABILITIES
  #728 = Utf8               Lcom/fasterxml/jackson/core/util/JacksonFeatureSet;
  #729 = Utf8               writeValue
  #730 = Utf8               START_ARRAY
  #731 = Utf8               createChildArrayContext
  #732 = Utf8               (Ljava/lang/Object;)Lcom/fasterxml/jackson/core/json/JsonWriteContext;
  #733 = Utf8               END_ARRAY
  #734 = Utf8               getParent
  #735 = Utf8               START_OBJECT
  #736 = Utf8               createChildObjectContext
  #737 = Utf8               (Ljava/lang/String;)I
  #738 = Utf8               getValue
  #739 = Utf8               VALUE_STRING
  #740 = Utf8               VALUE_EMBEDDED_OBJECT
  #741 = Utf8               substring
  #742 = Utf8               (II)Ljava/lang/String;
  #743 = Utf8               VALUE_NUMBER_INT
  #744 = Utf8               (S)Ljava/lang/Short;
  #745 = Utf8               (I)Ljava/lang/Integer;
  #746 = Utf8               (J)Ljava/lang/Long;
  #747 = Utf8               VALUE_NUMBER_FLOAT
  #748 = Utf8               (D)Ljava/lang/Double;
  #749 = Utf8               (F)Ljava/lang/Float;
  #750 = Utf8               VALUE_TRUE
  #751 = Utf8               VALUE_FALSE
  #752 = Utf8               VALUE_NULL
  #753 = Utf8               (Lcom/fasterxml/jackson/core/JsonGenerator;Ljava/lang/Object;)V
  #754 = Utf8               (Lcom/fasterxml/jackson/core/JsonGenerator;Lcom/fasterxml/jackson/core/TreeNode;)V
  #755 = Utf8               java/lang/System
  #756 = Utf8               arraycopy
  #757 = Utf8               (Ljava/lang/Object;ILjava/lang/Object;II)V
  #758 = Utf8               currentToken
  #759 = Utf8               hasTextCharacters
  #760 = Utf8               getTextCharacters
  #761 = Utf8               ()[C
  #762 = Utf8               getTextOffset
  #763 = Utf8               getTextLength
  #764 = Utf8               getText
  #765 = Utf8               $SwitchMap$com$fasterxml$jackson$core$JsonParser$NumberType
  #766 = Utf8               getNumberType
  #767 = Utf8               NumberType
  #768 = Utf8               ()Lcom/fasterxml/jackson/core/JsonParser$NumberType;
  #769 = Utf8               com/fasterxml/jackson/core/JsonParser$NumberType
  #770 = Utf8               getIntValue
  #771 = Utf8               getBigIntegerValue
  #772 = Utf8               ()Ljava/math/BigInteger;
  #773 = Utf8               getLongValue
  #774 = Utf8               getDecimalValue
  #775 = Utf8               ()Ljava/math/BigDecimal;
  #776 = Utf8               getFloatValue
  #777 = Utf8               getDoubleValue
  #778 = Utf8               getEmbeddedObject
  #779 = Utf8               ()Ljava/lang/Object;
  #780 = Utf8               getNumberValueExact
  #781 = Utf8               ()Ljava/lang/Number;
  #782 = Utf8               getTypeId
  #783 = Utf8               getObjectId
  #784 = Utf8               (ILcom/fasterxml/jackson/core/JsonToken;Ljava/lang/Object;Ljava/lang/Object;)Lcom/fasterxml/jackson/databind/util/TokenBuffer$Segment;
  #785 = Utf8               (ILcom/fasterxml/jackson/core/JsonToken;)Lcom/fasterxml/jackson/databind/util/TokenBuffer$Segment;
  #786 = Utf8               (ILcom/fasterxml/jackson/core/JsonToken;Ljava/lang/Object;Ljava/lang/Object;Ljava/lang/Object;)Lcom/fasterxml/jackson/databind/util/TokenBuffer$Segment;
  #787 = Utf8               (ILcom/fasterxml/jackson/core/JsonToken;Ljava/lang/Object;)Lcom/fasterxml/jackson/databind/util/TokenBuffer$Segment;
  #788 = Utf8               collectDefaults
{
  protected static final int DEFAULT_GENERATOR_FEATURES;
    descriptor: I
    flags: (0x001c) ACC_PROTECTED, ACC_STATIC, ACC_FINAL

  protected com.fasterxml.jackson.core.ObjectCodec _objectCodec;
    descriptor: Lcom/fasterxml/jackson/core/ObjectCodec;
    flags: (0x0004) ACC_PROTECTED

  protected com.fasterxml.jackson.core.JsonStreamContext _parentContext;
    descriptor: Lcom/fasterxml/jackson/core/JsonStreamContext;
    flags: (0x0004) ACC_PROTECTED

  protected int _generatorFeatures;
    descriptor: I
    flags: (0x0004) ACC_PROTECTED

  protected boolean _closed;
    descriptor: Z
    flags: (0x0004) ACC_PROTECTED

  protected boolean _hasNativeTypeIds;
    descriptor: Z
    flags: (0x0004) ACC_PROTECTED

  protected boolean _hasNativeObjectIds;
    descriptor: Z
    flags: (0x0004) ACC_PROTECTED

  protected boolean _mayHaveNativeIds;
    descriptor: Z
    flags: (0x0004) ACC_PROTECTED

  protected boolean _forceBigDecimal;
    descriptor: Z
    flags: (0x0004) ACC_PROTECTED

  protected com.fasterxml.jackson.databind.util.TokenBuffer$Segment _first;
    descriptor: Lcom/fasterxml/jackson/databind/util/TokenBuffer$Segment;
    flags: (0x0004) ACC_PROTECTED

  protected com.fasterxml.jackson.databind.util.TokenBuffer$Segment _last;
    descriptor: Lcom/fasterxml/jackson/databind/util/TokenBuffer$Segment;
    flags: (0x0004) ACC_PROTECTED

  protected int _appendAt;
    descriptor: I
    flags: (0x0004) ACC_PROTECTED

  protected java.lang.Object _typeId;
    descriptor: Ljava/lang/Object;
    flags: (0x0004) ACC_PROTECTED

  protected java.lang.Object _objectId;
    descriptor: Ljava/lang/Object;
    flags: (0x0004) ACC_PROTECTED

  protected boolean _hasNativeId;
    descriptor: Z
    flags: (0x0004) ACC_PROTECTED

  protected com.fasterxml.jackson.core.json.JsonWriteContext _writeContext;
    descriptor: Lcom/fasterxml/jackson/core/json/JsonWriteContext;
    flags: (0x0004) ACC_PROTECTED

  public com.fasterxml.jackson.databind.util.TokenBuffer(com.fasterxml.jackson.core.ObjectCodec, boolean);
    descriptor: (Lcom/fasterxml/jackson/core/ObjectCodec;Z)V
    flags: (0x0001) ACC_PUBLIC
    Code:
      stack=4, locals=3, args_size=3
         0: aload_0
         1: invokespecial #1                  // Method com/fasterxml/jackson/core/JsonGenerator."<init>":()V
         4: aload_0
         5: iconst_0
         6: putfield      #2                  // Field _hasNativeId:Z
         9: aload_0
        10: aload_1
        11: putfield      #3                  // Field _objectCodec:Lcom/fasterxml/jackson/core/ObjectCodec;
        14: aload_0
        15: getstatic     #4                  // Field DEFAULT_GENERATOR_FEATURES:I
        18: putfield      #5                  // Field _generatorFeatures:I
        21: aload_0
        22: aconst_null
        23: invokestatic  #6                  // Method com/fasterxml/jackson/core/json/JsonWriteContext.createRootContext:(Lcom/fasterxml/jackson/core/json/DupDetector;)Lcom/fasterxml/jackson/core/json/JsonWriteContext;
        26: putfield      #7                  // Field _writeContext:Lcom/fasterxml/jackson/core/json/JsonWriteContext;
        29: aload_0
        30: aload_0
        31: new           #8                  // class com/fasterxml/jackson/databind/util/TokenBuffer$Segment
        34: dup
        35: invokespecial #9                  // Method com/fasterxml/jackson/databind/util/TokenBuffer$Segment."<init>":()V
        38: dup_x1
        39: putfield      #10                 // Field _last:Lcom/fasterxml/jackson/databind/util/TokenBuffer$Segment;
        42: putfield      #11                 // Field _first:Lcom/fasterxml/jackson/databind/util/TokenBuffer$Segment;
        45: aload_0
        46: iconst_0
        47: putfield      #12                 // Field _appendAt:I
        50: aload_0
        51: iload_2
        52: putfield      #13                 // Field _hasNativeTypeIds:Z
        55: aload_0
        56: iload_2
        57: putfield      #14                 // Field _hasNativeObjectIds:Z
        60: aload_0
        61: aload_0
        62: getfield      #13                 // Field _hasNativeTypeIds:Z
        65: ifne          75
        68: aload_0
        69: getfield      #14                 // Field _hasNativeObjectIds:Z
        72: ifeq          79
        75: iconst_1
        76: goto          80
        79: iconst_0
        80: putfield      #15                 // Field _mayHaveNativeIds:Z
        83: return
      LineNumberTable:
        line 146: 0
        line 122: 4
        line 147: 9
        line 148: 14
        line 149: 21
        line 151: 29
        line 152: 45
        line 153: 50
        line 154: 55
        line 156: 60
        line 157: 83
      LocalVariableTable:
        Start  Length  Slot  Name   Signature
            0      84     0  this   Lcom/fasterxml/jackson/databind/util/TokenBuffer;
            0      84     1 codec   Lcom/fasterxml/jackson/core/ObjectCodec;
            0      84     2 hasNativeIds   Z
      StackMapTable: number_of_entries = 3
        frame_type = 255 /* full_frame */
          offset_delta = 75
          locals = [ class com/fasterxml/jackson/databind/util/TokenBuffer, class com/fasterxml/jackson/core/ObjectCodec, int ]
          stack = [ class com/fasterxml/jackson/databind/util/TokenBuffer ]
        frame_type = 67 /* same_locals_1_stack_item */
          stack = [ class com/fasterxml/jackson/databind/util/TokenBuffer ]
        frame_type = 255 /* full_frame */
          offset_delta = 0
          locals = [ class com/fasterxml/jackson/databind/util/TokenBuffer, class com/fasterxml/jackson/core/ObjectCodec, int ]
          stack = [ class com/fasterxml/jackson/databind/util/TokenBuffer, int ]

  public com.fasterxml.jackson.databind.util.TokenBuffer(com.fasterxml.jackson.core.JsonParser);
    descriptor: (Lcom/fasterxml/jackson/core/JsonParser;)V
    flags: (0x0001) ACC_PUBLIC
    Code:
      stack=3, locals=2, args_size=2
         0: aload_0
         1: aload_1
         2: aconst_null
         3: invokespecial #16                 // Method "<init>":(Lcom/fasterxml/jackson/core/JsonParser;Lcom/fasterxml/jackson/databind/DeserializationContext;)V
         6: return
      LineNumberTable:
        line 163: 0
        line 164: 6
      LocalVariableTable:
        Start  Length  Slot  Name   Signature
            0       7     0  this   Lcom/fasterxml/jackson/databind/util/TokenBuffer;
            0       7     1     p   Lcom/fasterxml/jackson/core/JsonParser;

  public com.fasterxml.jackson.databind.util.TokenBuffer(com.fasterxml.jackson.core.JsonParser, com.fasterxml.jackson.databind.DeserializationContext);
    descriptor: (Lcom/fasterxml/jackson/core/JsonParser;Lcom/fasterxml/jackson/databind/DeserializationContext;)V
    flags: (0x0001) ACC_PUBLIC
    Code:
      stack=4, locals=3, args_size=3
         0: aload_0
         1: invokespecial #1                  // Method com/fasterxml/jackson/core/JsonGenerator."<init>":()V
         4: aload_0
         5: iconst_0
         6: putfield      #2                  // Field _hasNativeId:Z
         9: aload_0
        10: aload_1
        11: invokevirtual #17                 // Method com/fasterxml/jackson/core/JsonParser.getCodec:()Lcom/fasterxml/jackson/core/ObjectCodec;
        14: putfield      #3                  // Field _objectCodec:Lcom/fasterxml/jackson/core/ObjectCodec;
        17: aload_0
        18: aload_1
        19: invokevirtual #18                 // Method com/fasterxml/jackson/core/JsonParser.getParsingContext:()Lcom/fasterxml/jackson/core/JsonStreamContext;
        22: putfield      #19                 // Field _parentContext:Lcom/fasterxml/jackson/core/JsonStreamContext;
        25: aload_0
        26: getstatic     #4                  // Field DEFAULT_GENERATOR_FEATURES:I
        29: putfield      #5                  // Field _generatorFeatures:I
        32: aload_0
        33: aconst_null
        34: invokestatic  #6                  // Method com/fasterxml/jackson/core/json/JsonWriteContext.createRootContext:(Lcom/fasterxml/jackson/core/json/DupDetector;)Lcom/fasterxml/jackson/core/json/JsonWriteContext;
        37: putfield      #7                  // Field _writeContext:Lcom/fasterxml/jackson/core/json/JsonWriteContext;
        40: aload_0
        41: aload_0
        42: new           #8                  // class com/fasterxml/jackson/databind/util/TokenBuffer$Segment
        45: dup
        46: invokespecial #9                  // Method com/fasterxml/jackson/databind/util/TokenBuffer$Segment."<init>":()V
        49: dup_x1
        50: putfield      #10                 // Field _last:Lcom/fasterxml/jackson/databind/util/TokenBuffer$Segment;
        53: putfield      #11                 // Field _first:Lcom/fasterxml/jackson/databind/util/TokenBuffer$Segment;
        56: aload_0
        57: iconst_0
        58: putfield      #12                 // Field _appendAt:I
        61: aload_0
        62: aload_1
        63: invokevirtual #20                 // Method com/fasterxml/jackson/core/JsonParser.canReadTypeId:()Z
        66: putfield      #13                 // Field _hasNativeTypeIds:Z
        69: aload_0
        70: aload_1
        71: invokevirtual #21                 // Method com/fasterxml/jackson/core/JsonParser.canReadObjectId:()Z
        74: putfield      #14                 // Field _hasNativeObjectIds:Z
        77: aload_0
        78: aload_0
        79: getfield      #13                 // Field _hasNativeTypeIds:Z
        82: ifne          92
        85: aload_0
        86: getfield      #14                 // Field _hasNativeObjectIds:Z
        89: ifeq          96
        92: iconst_1
        93: goto          97
        96: iconst_0
        97: putfield      #15                 // Field _mayHaveNativeIds:Z
       100: aload_0
       101: aload_2
       102: ifnonnull     109
       105: iconst_0
       106: goto          116
       109: aload_2
       110: getstatic     #22                 // Field com/fasterxml/jackson/databind/DeserializationFeature.USE_BIG_DECIMAL_FOR_FLOATS:Lcom/fasterxml/jackson/databind/DeserializationFeature;
       113: invokevirtual #23                 // Method com/fasterxml/jackson/databind/DeserializationContext.isEnabled:(Lcom/fasterxml/jackson/databind/DeserializationFeature;)Z
       116: putfield      #24                 // Field _forceBigDecimal:Z
       119: return
      LineNumberTable:
        line 170: 0
        line 122: 4
        line 171: 9
        line 172: 17
        line 173: 25
        line 174: 32
        line 176: 40
        line 177: 56
        line 178: 61
        line 179: 69
        line 180: 77
        line 181: 100
        line 182: 113
        line 183: 119
      LocalVariableTable:
        Start  Length  Slot  Name   Signature
            0     120     0  this   Lcom/fasterxml/jackson/databind/util/TokenBuffer;
            0     120     1     p   Lcom/fasterxml/jackson/core/JsonParser;
            0     120     2  ctxt   Lcom/fasterxml/jackson/databind/DeserializationContext;
      StackMapTable: number_of_entries = 5
        frame_type = 255 /* full_frame */
          offset_delta = 92
          locals = [ class com/fasterxml/jackson/databind/util/TokenBuffer, class com/fasterxml/jackson/core/JsonParser, class com/fasterxml/jackson/databind/DeserializationContext ]
          stack = [ class com/fasterxml/jackson/databind/util/TokenBuffer ]
        frame_type = 67 /* same_locals_1_stack_item */
          stack = [ class com/fasterxml/jackson/databind/util/TokenBuffer ]
        frame_type = 255 /* full_frame */
          offset_delta = 0
          locals = [ class com/fasterxml/jackson/databind/util/TokenBuffer, class com/fasterxml/jackson/core/JsonParser, class com/fasterxml/jackson/databind/DeserializationContext ]
          stack = [ class com/fasterxml/jackson/databind/util/TokenBuffer, int ]
        frame_type = 75 /* same_locals_1_stack_item */
          stack = [ class com/fasterxml/jackson/databind/util/TokenBuffer ]
        frame_type = 255 /* full_frame */
          offset_delta = 6
          locals = [ class com/fasterxml/jackson/databind/util/TokenBuffer, class com/fasterxml/jackson/core/JsonParser, class com/fasterxml/jackson/databind/DeserializationContext ]
          stack = [ class com/fasterxml/jackson/databind/util/TokenBuffer, int ]

  public static com.fasterxml.jackson.databind.util.TokenBuffer asCopyOfValue(com.fasterxml.jackson.core.JsonParser) throws java.io.IOException;
    descriptor: (Lcom/fasterxml/jackson/core/JsonParser;)Lcom/fasterxml/jackson/databind/util/TokenBuffer;
    flags: (0x0009) ACC_PUBLIC, ACC_STATIC
    Code:
      stack=3, locals=2, args_size=1
         0: new           #25                 // class com/fasterxml/jackson/databind/util/TokenBuffer
         3: dup
         4: aload_0
         5: invokespecial #26                 // Method "<init>":(Lcom/fasterxml/jackson/core/JsonParser;)V
         8: astore_1
         9: aload_1
        10: aload_0
        11: invokevirtual #27                 // Method copyCurrentStructure:(Lcom/fasterxml/jackson/core/JsonParser;)V
        14: aload_1
        15: areturn
      LineNumberTable:
        line 199: 0
        line 200: 9
        line 201: 14
      LocalVariableTable:
        Start  Length  Slot  Name   Signature
            0      16     0     p   Lcom/fasterxml/jackson/core/JsonParser;
            9       7     1     b   Lcom/fasterxml/jackson/databind/util/TokenBuffer;
    Exceptions:
      throws java.io.IOException
    Deprecated: true
    RuntimeVisibleAnnotations:
      0: #269()
        java.lang.Deprecated

  public com.fasterxml.jackson.databind.util.TokenBuffer overrideParentContext(com.fasterxml.jackson.core.JsonStreamContext);
    descriptor: (Lcom/fasterxml/jackson/core/JsonStreamContext;)Lcom/fasterxml/jackson/databind/util/TokenBuffer;
    flags: (0x0001) ACC_PUBLIC
    Code:
      stack=2, locals=2, args_size=2
         0: aload_0
         1: aload_1
         2: putfield      #19                 // Field _parentContext:Lcom/fasterxml/jackson/core/JsonStreamContext;
         5: aload_0
         6: areturn
      LineNumberTable:
        line 213: 0
        line 214: 5
      LocalVariableTable:
        Start  Length  Slot  Name   Signature
            0       7     0  this   Lcom/fasterxml/jackson/databind/util/TokenBuffer;
            0       7     1  ctxt   Lcom/fasterxml/jackson/core/JsonStreamContext;

  public com.fasterxml.jackson.databind.util.TokenBuffer forceUseOfBigDecimal(boolean);
    descriptor: (Z)Lcom/fasterxml/jackson/databind/util/TokenBuffer;
    flags: (0x0001) ACC_PUBLIC
    Code:
      stack=2, locals=2, args_size=2
         0: aload_0
         1: iload_1
         2: putfield      #24                 // Field _forceBigDecimal:Z
         5: aload_0
         6: areturn
      LineNumberTable:
        line 221: 0
        line 222: 5
      LocalVariableTable:
        Start  Length  Slot  Name   Signature
            0       7     0  this   Lcom/fasterxml/jackson/databind/util/TokenBuffer;
            0       7     1     b   Z

  public com.fasterxml.jackson.core.Version version();
    descriptor: ()Lcom/fasterxml/jackson/core/Version;
    flags: (0x0001) ACC_PUBLIC
    Code:
      stack=1, locals=1, args_size=1
         0: getstatic     #28                 // Field com/fasterxml/jackson/databind/cfg/PackageVersion.VERSION:Lcom/fasterxml/jackson/core/Version;
         3: areturn
      LineNumberTable:
        line 227: 0
      LocalVariableTable:
        Start  Length  Slot  Name   Signature
            0       4     0  this   Lcom/fasterxml/jackson/databind/util/TokenBuffer;

  public com.fasterxml.jackson.core.JsonParser asParser();
    descriptor: ()Lcom/fasterxml/jackson/core/JsonParser;
    flags: (0x0001) ACC_PUBLIC
    Code:
      stack=2, locals=1, args_size=1
         0: aload_0
         1: aload_0
         2: getfield      #3                  // Field _objectCodec:Lcom/fasterxml/jackson/core/ObjectCodec;
         5: invokevirtual #29                 // Method asParser:(Lcom/fasterxml/jackson/core/ObjectCodec;)Lcom/fasterxml/jackson/core/JsonParser;
         8: areturn
      LineNumberTable:
        line 241: 0
      LocalVariableTable:
        Start  Length  Slot  Name   Signature
            0       9     0  this   Lcom/fasterxml/jackson/databind/util/TokenBuffer;

  public com.fasterxml.jackson.core.JsonParser asParserOnFirstToken() throws java.io.IOException;
    descriptor: ()Lcom/fasterxml/jackson/core/JsonParser;
    flags: (0x0001) ACC_PUBLIC
    Code:
      stack=2, locals=2, args_size=1
         0: aload_0
         1: aload_0
         2: getfield      #3                  // Field _objectCodec:Lcom/fasterxml/jackson/core/ObjectCodec;
         5: invokevirtual #29                 // Method asParser:(Lcom/fasterxml/jackson/core/ObjectCodec;)Lcom/fasterxml/jackson/core/JsonParser;
         8: astore_1
         9: aload_1
        10: invokevirtual #30                 // Method com/fasterxml/jackson/core/JsonParser.nextToken:()Lcom/fasterxml/jackson/core/JsonToken;
        13: pop
        14: aload_1
        15: areturn
      LineNumberTable:
        line 255: 0
        line 256: 9
        line 257: 14
      LocalVariableTable:
        Start  Length  Slot  Name   Signature
            0      16     0  this   Lcom/fasterxml/jackson/databind/util/TokenBuffer;
            9       7     1     p   Lcom/fasterxml/jackson/core/JsonParser;
    Exceptions:
      throws java.io.IOException

  public com.fasterxml.jackson.core.JsonParser asParser(com.fasterxml.jackson.core.ObjectCodec);
    descriptor: (Lcom/fasterxml/jackson/core/ObjectCodec;)Lcom/fasterxml/jackson/core/JsonParser;
    flags: (0x0001) ACC_PUBLIC
    Code:
      stack=7, locals=2, args_size=2
         0: new           #31                 // class com/fasterxml/jackson/databind/util/TokenBuffer$Parser
         3: dup
         4: aload_0
         5: getfield      #11                 // Field _first:Lcom/fasterxml/jackson/databind/util/TokenBuffer$Segment;
         8: aload_1
         9: aload_0
        10: getfield      #13                 // Field _hasNativeTypeIds:Z
        13: aload_0
        14: getfield      #14                 // Field _hasNativeObjectIds:Z
        17: aload_0
        18: getfield      #19                 // Field _parentContext:Lcom/fasterxml/jackson/core/JsonStreamContext;
        21: invokespecial #32                 // Method com/fasterxml/jackson/databind/util/TokenBuffer$Parser."<init>":(Lcom/fasterxml/jackson/databind/util/TokenBuffer$Segment;Lcom/fasterxml/jackson/core/ObjectCodec;ZZLcom/fasterxml/jackson/core/JsonStreamContext;)V
        24: areturn
      LineNumberTable:
        line 275: 0
      LocalVariableTable:
        Start  Length  Slot  Name   Signature
            0      25     0  this   Lcom/fasterxml/jackson/databind/util/TokenBuffer;
            0      25     1 codec   Lcom/fasterxml/jackson/core/ObjectCodec;

  public com.fasterxml.jackson.core.JsonParser asParser(com.fasterxml.jackson.core.JsonParser);
    descriptor: (Lcom/fasterxml/jackson/core/JsonParser;)Lcom/fasterxml/jackson/core/JsonParser;
    flags: (0x0001) ACC_PUBLIC
    Code:
      stack=7, locals=3, args_size=2
         0: new           #31                 // class com/fasterxml/jackson/databind/util/TokenBuffer$Parser
         3: dup
         4: aload_0
         5: getfield      #11                 // Field _first:Lcom/fasterxml/jackson/databind/util/TokenBuffer$Segment;
         8: aload_1
         9: invokevirtual #17                 // Method com/fasterxml/jackson/core/JsonParser.getCodec:()Lcom/fasterxml/jackson/core/ObjectCodec;
        12: aload_0
        13: getfield      #13                 // Field _hasNativeTypeIds:Z
        16: aload_0
        17: getfield      #14                 // Field _hasNativeObjectIds:Z
        20: aload_0
        21: getfield      #19                 // Field _parentContext:Lcom/fasterxml/jackson/core/JsonStreamContext;
        24: invokespecial #32                 // Method com/fasterxml/jackson/databind/util/TokenBuffer$Parser."<init>":(Lcom/fasterxml/jackson/databind/util/TokenBuffer$Segment;Lcom/fasterxml/jackson/core/ObjectCodec;ZZLcom/fasterxml/jackson/core/JsonStreamContext;)V
        27: astore_2
        28: aload_2
        29: aload_1
        30: invokevirtual #33                 // Method com/fasterxml/jackson/core/JsonParser.getTokenLocation:()Lcom/fasterxml/jackson/core/JsonLocation;
        33: invokevirtual #34                 // Method com/fasterxml/jackson/databind/util/TokenBuffer$Parser.setLocation:(Lcom/fasterxml/jackson/core/JsonLocation;)V
        36: aload_2
        37: areturn
      LineNumberTable:
        line 284: 0
        line 285: 28
        line 286: 36
      LocalVariableTable:
        Start  Length  Slot  Name   Signature
            0      38     0  this   Lcom/fasterxml/jackson/databind/util/TokenBuffer;
            0      38     1   src   Lcom/fasterxml/jackson/core/JsonParser;
           28      10     2     p   Lcom/fasterxml/jackson/databind/util/TokenBuffer$Parser;

  public com.fasterxml.jackson.core.JsonToken firstToken();
    descriptor: ()Lcom/fasterxml/jackson/core/JsonToken;
    flags: (0x0001) ACC_PUBLIC
    Code:
      stack=2, locals=1, args_size=1
         0: aload_0
         1: getfield      #11                 // Field _first:Lcom/fasterxml/jackson/databind/util/TokenBuffer$Segment;
         4: iconst_0
         5: invokevirtual #35                 // Method com/fasterxml/jackson/databind/util/TokenBuffer$Segment.type:(I)Lcom/fasterxml/jackson/core/JsonToken;
         8: areturn
      LineNumberTable:
        line 297: 0
      LocalVariableTable:
        Start  Length  Slot  Name   Signature
            0       9     0  this   Lcom/fasterxml/jackson/databind/util/TokenBuffer;

  public boolean isEmpty();
    descriptor: ()Z
    flags: (0x0001) ACC_PUBLIC
    Code:
      stack=2, locals=1, args_size=1
         0: aload_0
         1: getfield      #12                 // Field _appendAt:I
         4: ifne          22
         7: aload_0
         8: getfield      #11                 // Field _first:Lcom/fasterxml/jackson/databind/util/TokenBuffer$Segment;
        11: aload_0
        12: getfield      #10                 // Field _last:Lcom/fasterxml/jackson/databind/util/TokenBuffer$Segment;
        15: if_acmpne     22
        18: iconst_1
        19: goto          23
        22: iconst_0
        23: ireturn
      LineNumberTable:
        line 309: 0
      LocalVariableTable:
        Start  Length  Slot  Name   Signature
            0      24     0  this   Lcom/fasterxml/jackson/databind/util/TokenBuffer;
      StackMapTable: number_of_entries = 2
        frame_type = 22 /* same */
        frame_type = 64 /* same_locals_1_stack_item */
          stack = [ int ]

  public com.fasterxml.jackson.databind.util.TokenBuffer append(com.fasterxml.jackson.databind.util.TokenBuffer) throws java.io.IOException;
    descriptor: (Lcom/fasterxml/jackson/databind/util/TokenBuffer;)Lcom/fasterxml/jackson/databind/util/TokenBuffer;
    flags: (0x0001) ACC_PUBLIC
    Code:
      stack=2, locals=3, args_size=2
         0: aload_0
         1: getfield      #13                 // Field _hasNativeTypeIds:Z
         4: ifne          15
         7: aload_0
         8: aload_1
         9: invokevirtual #36                 // Method canWriteTypeId:()Z
        12: putfield      #13                 // Field _hasNativeTypeIds:Z
        15: aload_0
        16: getfield      #14                 // Field _hasNativeObjectIds:Z
        19: ifne          30
        22: aload_0
        23: aload_1
        24: invokevirtual #37                 // Method canWriteObjectId:()Z
        27: putfield      #14                 // Field _hasNativeObjectIds:Z
        30: aload_0
        31: aload_0
        32: getfield      #13                 // Field _hasNativeTypeIds:Z
        35: ifne          45
        38: aload_0
        39: getfield      #14                 // Field _hasNativeObjectIds:Z
        42: ifeq          49
        45: iconst_1
        46: goto          50
        49: iconst_0
        50: putfield      #15                 // Field _mayHaveNativeIds:Z
        53: aload_1
        54: invokevirtual #38                 // Method asParser:()Lcom/fasterxml/jackson/core/JsonParser;
        57: astore_2
        58: aload_2
        59: invokevirtual #30                 // Method com/fasterxml/jackson/core/JsonParser.nextToken:()Lcom/fasterxml/jackson/core/JsonToken;
        62: ifnull        73
        65: aload_0
        66: aload_2
        67: invokevirtual #27                 // Method copyCurrentStructure:(Lcom/fasterxml/jackson/core/JsonParser;)V
        70: goto          58
        73: aload_0
        74: areturn
      LineNumberTable:
        line 328: 0
        line 329: 7
        line 331: 15
        line 332: 22
        line 334: 30
        line 336: 53
        line 337: 58
        line 338: 65
        line 340: 73
      LocalVariableTable:
        Start  Length  Slot  Name   Signature
            0      75     0  this   Lcom/fasterxml/jackson/databind/util/TokenBuffer;
            0      75     1 other   Lcom/fasterxml/jackson/databind/util/TokenBuffer;
           58      17     2     p   Lcom/fasterxml/jackson/core/JsonParser;
      StackMapTable: number_of_entries = 7
        frame_type = 15 /* same */
        frame_type = 14 /* same */
        frame_type = 78 /* same_locals_1_stack_item */
          stack = [ class com/fasterxml/jackson/databind/util/TokenBuffer ]
        frame_type = 67 /* same_locals_1_stack_item */
          stack = [ class com/fasterxml/jackson/databind/util/TokenBuffer ]
        frame_type = 255 /* full_frame */
          offset_delta = 0
          locals = [ class com/fasterxml/jackson/databind/util/TokenBuffer, class com/fasterxml/jackson/databind/util/TokenBuffer ]
          stack = [ class com/fasterxml/jackson/databind/util/TokenBuffer, int ]
        frame_type = 252 /* append */
          offset_delta = 7
          locals = [ class com/fasterxml/jackson/core/JsonParser ]
        frame_type = 14 /* same */
    Exceptions:
      throws java.io.IOException

  public void serialize(com.fasterxml.jackson.core.JsonGenerator) throws java.io.IOException;
    descriptor: (Lcom/fasterxml/jackson/core/JsonGenerator;)V
    flags: (0x0001) ACC_PUBLIC
    Code:
      stack=6, locals=8, args_size=2
         0: aload_0
         1: getfield      #11                 // Field _first:Lcom/fasterxml/jackson/databind/util/TokenBuffer$Segment;
         4: astore_2
         5: iconst_m1
         6: istore_3
         7: aload_0
         8: getfield      #15                 // Field _mayHaveNativeIds:Z
        11: istore        4
        13: iload         4
        15: ifeq          29
        18: aload_2
        19: invokevirtual #39                 // Method com/fasterxml/jackson/databind/util/TokenBuffer$Segment.hasIds:()Z
        22: ifeq          29
        25: iconst_1
        26: goto          30
        29: iconst_0
        30: istore        5
        32: iinc          3, 1
        35: iload_3
        36: bipush        16
        38: if_icmplt     74
        41: iconst_0
        42: istore_3
        43: aload_2
        44: invokevirtual #40                 // Method com/fasterxml/jackson/databind/util/TokenBuffer$Segment.next:()Lcom/fasterxml/jackson/databind/util/TokenBuffer$Segment;
        47: astore_2
        48: aload_2
        49: ifnonnull     55
        52: goto          638
        55: iload         4
        57: ifeq          71
        60: aload_2
        61: invokevirtual #39                 // Method com/fasterxml/jackson/databind/util/TokenBuffer$Segment.hasIds:()Z
        64: ifeq          71
        67: iconst_1
        68: goto          72
        71: iconst_0
        72: istore        5
        74: aload_2
        75: iload_3
        76: invokevirtual #35                 // Method com/fasterxml/jackson/databind/util/TokenBuffer$Segment.type:(I)Lcom/fasterxml/jackson/core/JsonToken;
        79: astore        6
        81: aload         6
        83: ifnonnull     89
        86: goto          638
        89: iload         5
        91: ifeq          130
        94: aload_2
        95: iload_3
        96: invokevirtual #41                 // Method com/fasterxml/jackson/databind/util/TokenBuffer$Segment.findObjectId:(I)Ljava/lang/Object;
        99: astore        7
       101: aload         7
       103: ifnull        112
       106: aload_1
       107: aload         7
       109: invokevirtual #42                 // Method com/fasterxml/jackson/core/JsonGenerator.writeObjectId:(Ljava/lang/Object;)V
       112: aload_2
       113: iload_3
       114: invokevirtual #43                 // Method com/fasterxml/jackson/databind/util/TokenBuffer$Segment.findTypeId:(I)Ljava/lang/Object;
       117: astore        7
       119: aload         7
       121: ifnull        130
       124: aload_1
       125: aload         7
       127: invokevirtual #44                 // Method com/fasterxml/jackson/core/JsonGenerator.writeTypeId:(Ljava/lang/Object;)V
       130: getstatic     #45                 // Field com/fasterxml/jackson/databind/util/TokenBuffer$1.$SwitchMap$com$fasterxml$jackson$core$JsonToken:[I
       133: aload         6
       135: invokevirtual #46                 // Method com/fasterxml/jackson/core/JsonToken.ordinal:()I
       138: iaload
       139: tableswitch   { // 1 to 12
                       1: 200
                       2: 207
                       3: 214
                       4: 221
                       5: 228
                       6: 267
                       7: 306
                       8: 417
                       9: 549
                      10: 557
                      11: 565
                      12: 572
                 default: 625
            }
       200: aload_1
       201: invokevirtual #47                 // Method com/fasterxml/jackson/core/JsonGenerator.writeStartObject:()V
       204: goto          635
       207: aload_1
       208: invokevirtual #48                 // Method com/fasterxml/jackson/core/JsonGenerator.writeEndObject:()V
       211: goto          635
       214: aload_1
       215: invokevirtual #49                 // Method com/fasterxml/jackson/core/JsonGenerator.writeStartArray:()V
       218: goto          635
       221: aload_1
       222: invokevirtual #50                 // Method com/fasterxml/jackson/core/JsonGenerator.writeEndArray:()V
       225: goto          635
       228: aload_2
       229: iload_3
       230: invokevirtual #51                 // Method com/fasterxml/jackson/databind/util/TokenBuffer$Segment.get:(I)Ljava/lang/Object;
       233: astore        7
       235: aload         7
       237: instanceof    #52                 // class com/fasterxml/jackson/core/SerializableString
       240: ifeq          255
       243: aload_1
       244: aload         7
       246: checkcast     #52                 // class com/fasterxml/jackson/core/SerializableString
       249: invokevirtual #53                 // Method com/fasterxml/jackson/core/JsonGenerator.writeFieldName:(Lcom/fasterxml/jackson/core/SerializableString;)V
       252: goto          264
       255: aload_1
       256: aload         7
       258: checkcast     #54                 // class java/lang/String
       261: invokevirtual #55                 // Method com/fasterxml/jackson/core/JsonGenerator.writeFieldName:(Ljava/lang/String;)V
       264: goto          635
       267: aload_2
       268: iload_3
       269: invokevirtual #51                 // Method com/fasterxml/jackson/databind/util/TokenBuffer$Segment.get:(I)Ljava/lang/Object;
       272: astore        7
       274: aload         7
       276: instanceof    #52                 // class com/fasterxml/jackson/core/SerializableString
       279: ifeq          294
       282: aload_1
       283: aload         7
       285: checkcast     #52                 // class com/fasterxml/jackson/core/SerializableString
       288: invokevirtual #56                 // Method com/fasterxml/jackson/core/JsonGenerator.writeString:(Lcom/fasterxml/jackson/core/SerializableString;)V
       291: goto          303
       294: aload_1
       295: aload         7
       297: checkcast     #54                 // class java/lang/String
       300: invokevirtual #57                 // Method com/fasterxml/jackson/core/JsonGenerator.writeString:(Ljava/lang/String;)V
       303: goto          635
       306: aload_2
       307: iload_3
       308: invokevirtual #51                 // Method com/fasterxml/jackson/databind/util/TokenBuffer$Segment.get:(I)Ljava/lang/Object;
       311: astore        7
       313: aload         7
       315: instanceof    #58                 // class java/lang/Integer
       318: ifeq          336
       321: aload_1
       322: aload         7
       324: checkcast     #58                 // class java/lang/Integer
       327: invokevirtual #59                 // Method java/lang/Integer.intValue:()I
       330: invokevirtual #60                 // Method com/fasterxml/jackson/core/JsonGenerator.writeNumber:(I)V
       333: goto          414
       336: aload         7
       338: instanceof    #61                 // class java/math/BigInteger
       341: ifeq          356
       344: aload_1
       345: aload         7
       347: checkcast     #61                 // class java/math/BigInteger
       350: invokevirtual #62                 // Method com/fasterxml/jackson/core/JsonGenerator.writeNumber:(Ljava/math/BigInteger;)V
       353: goto          414
       356: aload         7
       358: instanceof    #63                 // class java/lang/Long
       361: ifeq          379
       364: aload_1
       365: aload         7
       367: checkcast     #63                 // class java/lang/Long
       370: invokevirtual #64                 // Method java/lang/Long.longValue:()J
       373: invokevirtual #65                 // Method com/fasterxml/jackson/core/JsonGenerator.writeNumber:(J)V
       376: goto          414
       379: aload         7
       381: instanceof    #66                 // class java/lang/Short
       384: ifeq          402
       387: aload_1
       388: aload         7
       390: checkcast     #66                 // class java/lang/Short
       393: invokevirtual #67                 // Method java/lang/Short.shortValue:()S
       396: invokevirtual #68                 // Method com/fasterxml/jackson/core/JsonGenerator.writeNumber:(S)V
       399: goto          414
       402: aload_1
       403: aload         7
       405: checkcast     #69                 // class java/lang/Number
       408: invokevirtual #70                 // Method java/lang/Number.intValue:()I
       411: invokevirtual #60                 // Method com/fasterxml/jackson/core/JsonGenerator.writeNumber:(I)V
       414: goto          635
       417: aload_2
       418: iload_3
       419: invokevirtual #51                 // Method com/fasterxml/jackson/databind/util/TokenBuffer$Segment.get:(I)Ljava/lang/Object;
       422: astore        7
       424: aload         7
       426: instanceof    #71                 // class java/lang/Double
       429: ifeq          447
       432: aload_1
       433: aload         7
       435: checkcast     #71                 // class java/lang/Double
       438: invokevirtual #72                 // Method java/lang/Double.doubleValue:()D
       441: invokevirtual #73                 // Method com/fasterxml/jackson/core/JsonGenerator.writeNumber:(D)V
       444: goto          546
       447: aload         7
       449: instanceof    #74                 // class java/math/BigDecimal
       452: ifeq          467
       455: aload_1
       456: aload         7
       458: checkcast     #74                 // class java/math/BigDecimal
       461: invokevirtual #75                 // Method com/fasterxml/jackson/core/JsonGenerator.writeNumber:(Ljava/math/BigDecimal;)V
       464: goto          546
       467: aload         7
       469: instanceof    #76                 // class java/lang/Float
       472: ifeq          490
       475: aload_1
       476: aload         7
       478: checkcast     #76                 // class java/lang/Float
       481: invokevirtual #77                 // Method java/lang/Float.floatValue:()F
       484: invokevirtual #78                 // Method com/fasterxml/jackson/core/JsonGenerator.writeNumber:(F)V
       487: goto          546
       490: aload         7
       492: ifnonnull     502
       495: aload_1
       496: invokevirtual #79                 // Method com/fasterxml/jackson/core/JsonGenerator.writeNull:()V
       499: goto          546
       502: aload         7
       504: instanceof    #54                 // class java/lang/String
       507: ifeq          522
       510: aload_1
       511: aload         7
       513: checkcast     #54                 // class java/lang/String
       516: invokevirtual #80                 // Method com/fasterxml/jackson/core/JsonGenerator.writeNumber:(Ljava/lang/String;)V
       519: goto          546
       522: aload_0
       523: ldc           #81                 // String Unrecognized value type for VALUE_NUMBER_FLOAT: %s, cannot serialize
       525: iconst_1
       526: anewarray     #82                 // class java/lang/Object
       529: dup
       530: iconst_0
       531: aload         7
       533: invokevirtual #83                 // Method java/lang/Object.getClass:()Ljava/lang/Class;
       536: invokevirtual #84                 // Method java/lang/Class.getName:()Ljava/lang/String;
       539: aastore
       540: invokestatic  #85                 // Method java/lang/String.format:(Ljava/lang/String;[Ljava/lang/Object;)Ljava/lang/String;
       543: invokevirtual #86                 // Method _reportError:(Ljava/lang/String;)V
       546: goto          635
       549: aload_1
       550: iconst_1
       551: invokevirtual #87                 // Method com/fasterxml/jackson/core/JsonGenerator.writeBoolean:(Z)V
       554: goto          635
       557: aload_1
       558: iconst_0
       559: invokevirtual #87                 // Method com/fasterxml/jackson/core/JsonGenerator.writeBoolean:(Z)V
       562: goto          635
       565: aload_1
       566: invokevirtual #79                 // Method com/fasterxml/jackson/core/JsonGenerator.writeNull:()V
       569: goto          635
       572: aload_2
       573: iload_3
       574: invokevirtual #51                 // Method com/fasterxml/jackson/databind/util/TokenBuffer$Segment.get:(I)Ljava/lang/Object;
       577: astore        7
       579: aload         7
       581: instanceof    #88                 // class com/fasterxml/jackson/databind/util/RawValue
       584: ifeq          599
       587: aload         7
       589: checkcast     #88                 // class com/fasterxml/jackson/databind/util/RawValue
       592: aload_1
       593: invokevirtual #89                 // Method com/fasterxml/jackson/databind/util/RawValue.serialize:(Lcom/fasterxml/jackson/core/JsonGenerator;)V
       596: goto          622
       599: aload         7
       601: instanceof    #90                 // class com/fasterxml/jackson/databind/JsonSerializable
       604: ifeq          616
       607: aload_1
       608: aload         7
       610: invokevirtual #91                 // Method com/fasterxml/jackson/core/JsonGenerator.writeObject:(Ljava/lang/Object;)V
       613: goto          622
       616: aload_1
       617: aload         7
       619: invokevirtual #92                 // Method com/fasterxml/jackson/core/JsonGenerator.writeEmbeddedObject:(Ljava/lang/Object;)V
       622: goto          635
       625: new           #93                 // class java/lang/RuntimeException
       628: dup
       629: ldc           #94                 // String Internal error: should never end up through this code path
       631: invokespecial #95                 // Method java/lang/RuntimeException."<init>":(Ljava/lang/String;)V
       634: athrow
       635: goto          32
       638: return
      LineNumberTable:
        line 355: 0
        line 356: 5
        line 358: 7
        line 359: 13
        line 362: 32
        line 363: 41
        line 364: 43
        line 365: 48
        line 366: 55
        line 368: 74
        line 369: 81
        line 371: 89
        line 372: 94
        line 373: 101
        line 374: 106
        line 376: 112
        line 377: 119
        line 378: 124
        line 383: 130
        line 385: 200
        line 386: 204
        line 388: 207
        line 389: 211
        line 391: 214
        line 392: 218
        line 394: 221
        line 395: 225
        line 399: 228
        line 400: 235
        line 401: 243
        line 403: 255
        line 406: 264
        line 409: 267
        line 410: 274
        line 411: 282
        line 413: 294
        line 416: 303
        line 419: 306
        line 420: 313
        line 421: 321
        line 422: 336
        line 423: 344
        line 424: 356
        line 425: 364
        line 426: 379
        line 427: 387
        line 429: 402
        line 432: 414
        line 435: 417
        line 436: 424
        line 437: 432
        line 438: 447
        line 439: 455
        line 440: 467
        line 441: 475
        line 442: 490
        line 443: 495
        line 444: 502
        line 445: 510
        line 447: 522
        line 449: 533
        line 447: 540
        line 452: 546
        line 454: 549
        line 455: 554
        line 457: 557
        line 458: 562
        line 460: 565
        line 461: 569
        line 464: 572
        line 468: 579
        line 469: 587
        line 470: 599
        line 471: 607
        line 473: 616
        line 476: 622
        line 478: 625
        line 480: 635
        line 481: 638
      LocalVariableTable:
        Start  Length  Slot  Name   Signature
          101      29     7    id   Ljava/lang/Object;
          235      29     7    ob   Ljava/lang/Object;
          274      29     7    ob   Ljava/lang/Object;
          313     101     7     n   Ljava/lang/Object;
          424     122     7     n   Ljava/lang/Object;
          579      43     7 value   Ljava/lang/Object;
           81     554     6     t   Lcom/fasterxml/jackson/core/JsonToken;
            0     639     0  this   Lcom/fasterxml/jackson/databind/util/TokenBuffer;
            0     639     1   gen   Lcom/fasterxml/jackson/core/JsonGenerator;
            5     634     2 segment   Lcom/fasterxml/jackson/databind/util/TokenBuffer$Segment;
            7     632     3   ptr   I
           13     626     4 checkIds   Z
           32     607     5 hasIds   Z
      StackMapTable: number_of_entries = 43
        frame_type = 254 /* append */
          offset_delta = 29
          locals = [ class com/fasterxml/jackson/databind/util/TokenBuffer$Segment, int, int ]
        frame_type = 64 /* same_locals_1_stack_item */
          stack = [ int ]
        frame_type = 252 /* append */
          offset_delta = 1
          locals = [ int ]
        frame_type = 22 /* same */
        frame_type = 15 /* same */
        frame_type = 64 /* same_locals_1_stack_item */
          stack = [ int ]
        frame_type = 1 /* same */
        frame_type = 252 /* append */
          offset_delta = 14
          locals = [ class com/fasterxml/jackson/core/JsonToken ]
        frame_type = 252 /* append */
          offset_delta = 22
          locals = [ class java/lang/Object ]
        frame_type = 250 /* chop */
          offset_delta = 17
        frame_type = 251 /* same_frame_extended */
          offset_delta = 69
        frame_type = 6 /* same */
        frame_type = 6 /* same */
        frame_type = 6 /* same */
        frame_type = 6 /* same */
        frame_type = 252 /* append */
          offset_delta = 26
          locals = [ class java/lang/Object ]
        frame_type = 250 /* chop */
          offset_delta = 8
        frame_type = 2 /* same */
        frame_type = 252 /* append */
          offset_delta = 26
          locals = [ class java/lang/Object ]
        frame_type = 250 /* chop */
          offset_delta = 8
        frame_type = 2 /* same */
        frame_type = 252 /* append */
          offset_delta = 29
          locals = [ class java/lang/Object ]
        frame_type = 19 /* same */
        frame_type = 22 /* same */
        frame_type = 22 /* same */
        frame_type = 250 /* chop */
          offset_delta = 11
        frame_type = 2 /* same */
        frame_type = 252 /* append */
          offset_delta = 29
          locals = [ class java/lang/Object ]
        frame_type = 19 /* same */
        frame_type = 22 /* same */
        frame_type = 11 /* same */
        frame_type = 19 /* same */
        frame_type = 250 /* chop */
          offset_delta = 23
        frame_type = 2 /* same */
        frame_type = 7 /* same */
        frame_type = 7 /* same */
        frame_type = 6 /* same */
        frame_type = 252 /* append */
          offset_delta = 26
          locals = [ class java/lang/Object ]
        frame_type = 16 /* same */
        frame_type = 250 /* chop */
          offset_delta = 5
        frame_type = 2 /* same */
        frame_type = 250 /* chop */
          offset_delta = 9
        frame_type = 2 /* same */
    Exceptions:
      throws java.io.IOException

  public com.fasterxml.jackson.databind.util.TokenBuffer deserialize(com.fasterxml.jackson.core.JsonParser, com.fasterxml.jackson.databind.DeserializationContext) throws java.io.IOException;
    descriptor: (Lcom/fasterxml/jackson/core/JsonParser;Lcom/fasterxml/jackson/databind/DeserializationContext;)Lcom/fasterxml/jackson/databind/util/TokenBuffer;
    flags: (0x0001) ACC_PUBLIC
    Code:
      stack=5, locals=4, args_size=3
         0: aload_1
         1: getstatic     #96                 // Field com/fasterxml/jackson/core/JsonToken.FIELD_NAME:Lcom/fasterxml/jackson/core/JsonToken;
         4: invokevirtual #97                 // Method com/fasterxml/jackson/core/JsonParser.hasToken:(Lcom/fasterxml/jackson/core/JsonToken;)Z
         7: ifne          17
        10: aload_0
        11: aload_1
        12: invokevirtual #27                 // Method copyCurrentStructure:(Lcom/fasterxml/jackson/core/JsonParser;)V
        15: aload_0
        16: areturn
        17: aload_0
        18: invokevirtual #98                 // Method writeStartObject:()V
        21: aload_0
        22: aload_1
        23: invokevirtual #27                 // Method copyCurrentStructure:(Lcom/fasterxml/jackson/core/JsonParser;)V
        26: aload_1
        27: invokevirtual #30                 // Method com/fasterxml/jackson/core/JsonParser.nextToken:()Lcom/fasterxml/jackson/core/JsonToken;
        30: dup
        31: astore_3
        32: getstatic     #96                 // Field com/fasterxml/jackson/core/JsonToken.FIELD_NAME:Lcom/fasterxml/jackson/core/JsonToken;
        35: if_acmpeq     21
        38: aload_3
        39: getstatic     #99                 // Field com/fasterxml/jackson/core/JsonToken.END_OBJECT:Lcom/fasterxml/jackson/core/JsonToken;
        42: if_acmpeq     77
        45: aload_2
        46: ldc           #25                 // class com/fasterxml/jackson/databind/util/TokenBuffer
        48: getstatic     #99                 // Field com/fasterxml/jackson/core/JsonToken.END_OBJECT:Lcom/fasterxml/jackson/core/JsonToken;
        51: new           #100                // class java/lang/StringBuilder
        54: dup
        55: invokespecial #101                // Method java/lang/StringBuilder."<init>":()V
        58: ldc           #102                // String Expected END_OBJECT after copying contents of a JsonParser into TokenBuffer, got
        60: invokevirtual #103                // Method java/lang/StringBuilder.append:(Ljava/lang/String;)Ljava/lang/StringBuilder;
        63: aload_3
        64: invokevirtual #104                // Method java/lang/StringBuilder.append:(Ljava/lang/Object;)Ljava/lang/StringBuilder;
        67: invokevirtual #105                // Method java/lang/StringBuilder.toString:()Ljava/lang/String;
        70: iconst_0
        71: anewarray     #82                 // class java/lang/Object
        74: invokevirtual #106                // Method com/fasterxml/jackson/databind/DeserializationContext.reportWrongTokenException:(Ljava/lang/Class;Lcom/fasterxml/jackson/core/JsonToken;Ljava/lang/String;[Ljava/lang/Object;)V
        77: aload_0
        78: invokevirtual #107                // Method writeEndObject:()V
        81: aload_0
        82: areturn
      LineNumberTable:
        line 490: 0
        line 491: 10
        line 492: 15
        line 498: 17
        line 500: 21
        line 501: 26
        line 502: 38
        line 503: 45
        line 507: 77
        line 508: 81
      LocalVariableTable:
        Start  Length  Slot  Name   Signature
            0      83     0  this   Lcom/fasterxml/jackson/databind/util/TokenBuffer;
            0      83     1     p   Lcom/fasterxml/jackson/core/JsonParser;
            0      83     2  ctxt   Lcom/fasterxml/jackson/databind/DeserializationContext;
           32      51     3     t   Lcom/fasterxml/jackson/core/JsonToken;
      StackMapTable: number_of_entries = 3
        frame_type = 17 /* same */
        frame_type = 3 /* same */
        frame_type = 252 /* append */
          offset_delta = 55
          locals = [ class com/fasterxml/jackson/core/JsonToken ]
    Exceptions:
      throws java.io.IOException

  public java.lang.String toString();
    descriptor: ()Ljava/lang/String;
    flags: (0x0001) ACC_PUBLIC
    Code:
      stack=3, locals=8, args_size=1
         0: bipush        100
         2: istore_1
         3: new           #100                // class java/lang/StringBuilder
         6: dup
         7: invokespecial #101                // Method java/lang/StringBuilder."<init>":()V
        10: astore_2
        11: aload_2
        12: ldc           #108                // String [TokenBuffer:
        14: invokevirtual #103                // Method java/lang/StringBuilder.append:(Ljava/lang/String;)Ljava/lang/StringBuilder;
        17: pop
        18: aload_0
        19: invokevirtual #38                 // Method asParser:()Lcom/fasterxml/jackson/core/JsonParser;
        22: astore_3
        23: iconst_0
        24: istore        4
        26: aload_0
        27: getfield      #13                 // Field _hasNativeTypeIds:Z
        30: ifne          40
        33: aload_0
        34: getfield      #14                 // Field _hasNativeObjectIds:Z
        37: ifeq          44
        40: iconst_1
        41: goto          45
        44: iconst_0
        45: istore        5
        47: aload_3
        48: invokevirtual #30                 // Method com/fasterxml/jackson/core/JsonParser.nextToken:()Lcom/fasterxml/jackson/core/JsonToken;
        51: astore        6
        53: aload         6
        55: ifnonnull     61
        58: goto          152
        61: iload         5
        63: ifeq          71
        66: aload_0
        67: aload_2
        68: invokespecial #109                // Method _appendNativeIds:(Ljava/lang/StringBuilder;)V
        71: iload         4
        73: bipush        100
        75: if_icmpge     131
        78: iload         4
        80: ifle          90
        83: aload_2
        84: ldc           #110                // String ,
        86: invokevirtual #103                // Method java/lang/StringBuilder.append:(Ljava/lang/String;)Ljava/lang/StringBuilder;
        89: pop
        90: aload_2
        91: aload         6
        93: invokevirtual #111                // Method com/fasterxml/jackson/core/JsonToken.toString:()Ljava/lang/String;
        96: invokevirtual #103                // Method java/lang/StringBuilder.append:(Ljava/lang/String;)Ljava/lang/StringBuilder;
        99: pop
       100: aload         6
       102: getstatic     #96                 // Field com/fasterxml/jackson/core/JsonToken.FIELD_NAME:Lcom/fasterxml/jackson/core/JsonToken;
       105: if_acmpne     131
       108: aload_2
       109: bipush        40
       111: invokevirtual #112                // Method java/lang/StringBuilder.append:(C)Ljava/lang/StringBuilder;
       114: pop
       115: aload_2
       116: aload_3
       117: invokevirtual #113                // Method com/fasterxml/jackson/core/JsonParser.currentName:()Ljava/lang/String;
       120: invokevirtual #103                // Method java/lang/StringBuilder.append:(Ljava/lang/String;)Ljava/lang/StringBuilder;
       123: pop
       124: aload_2
       125: bipush        41
       127: invokevirtual #112                // Method java/lang/StringBuilder.append:(C)Ljava/lang/StringBuilder;
       130: pop
       131: goto          146
       134: astore        7
       136: new           #115                // class java/lang/IllegalStateException
       139: dup
       140: aload         7
       142: invokespecial #116                // Method java/lang/IllegalStateException."<init>":(Ljava/lang/Throwable;)V
       145: athrow
       146: iinc          4, 1
       149: goto          47
       152: iload         4
       154: bipush        100
       156: if_icmplt     179
       159: aload_2
       160: ldc           #117                // String  ... (truncated
       162: invokevirtual #103                // Method java/lang/StringBuilder.append:(Ljava/lang/String;)Ljava/lang/StringBuilder;
       165: iload         4
       167: bipush        100
       169: isub
       170: invokevirtual #118                // Method java/lang/StringBuilder.append:(I)Ljava/lang/StringBuilder;
       173: ldc           #119                // String  entries)
       175: invokevirtual #103                // Method java/lang/StringBuilder.append:(Ljava/lang/String;)Ljava/lang/StringBuilder;
       178: pop
       179: aload_2
       180: bipush        93
       182: invokevirtual #112                // Method java/lang/StringBuilder.append:(C)Ljava/lang/StringBuilder;
       185: pop
       186: aload_2
       187: invokevirtual #105                // Method java/lang/StringBuilder.toString:()Ljava/lang/String;
       190: areturn
      Exception table:
         from    to  target type
            47    58   134   Class java/io/IOException
            61   131   134   Class java/io/IOException
      LineNumberTable:
        line 516: 0
        line 518: 3
        line 519: 11
        line 526: 18
        line 527: 23
        line 528: 26
        line 533: 47
        line 534: 53
        line 536: 61
        line 537: 66
        line 540: 71
        line 541: 78
        line 542: 83
        line 544: 90
        line 545: 100
        line 546: 108
        line 547: 115
        line 548: 124
        line 553: 131
        line 551: 134
        line 552: 136
        line 554: 146
        line 555: 149
        line 557: 152
        line 558: 159
        line 560: 179
        line 561: 186
      LocalVariableTable:
        Start  Length  Slot  Name   Signature
           53      81     6     t   Lcom/fasterxml/jackson/core/JsonToken;
          136      10     7   ioe   Ljava/io/IOException;
          146       3     6     t   Lcom/fasterxml/jackson/core/JsonToken;
            0     191     0  this   Lcom/fasterxml/jackson/databind/util/TokenBuffer;
            3     188     1 MAX_COUNT   I
           11     180     2    sb   Ljava/lang/StringBuilder;
           23     168     3    jp   Lcom/fasterxml/jackson/core/JsonParser;
           26     165     4 count   I
           47     144     5 hasNativeIds   Z
      StackMapTable: number_of_entries = 12
        frame_type = 255 /* full_frame */
          offset_delta = 40
          locals = [ class com/fasterxml/jackson/databind/util/TokenBuffer, int, class java/lang/StringBuilder, class com/fasterxml/jackson/core/JsonParser, int ]
          stack = []
        frame_type = 3 /* same */
        frame_type = 64 /* same_locals_1_stack_item */
          stack = [ int ]
        frame_type = 252 /* append */
          offset_delta = 1
          locals = [ int ]
        frame_type = 252 /* append */
          offset_delta = 13
          locals = [ class com/fasterxml/jackson/core/JsonToken ]
        frame_type = 9 /* same */
        frame_type = 18 /* same */
        frame_type = 40 /* same */
        frame_type = 255 /* full_frame */
          offset_delta = 2
          locals = [ class com/fasterxml/jackson/databind/util/TokenBuffer, int, class java/lang/StringBuilder, class com/fasterxml/jackson/core/JsonParser, int, int ]
          stack = [ class java/io/IOException ]
        frame_type = 252 /* append */
          offset_delta = 11
          locals = [ class com/fasterxml/jackson/core/JsonToken ]
        frame_type = 250 /* chop */
          offset_delta = 5
        frame_type = 26 /* same */

  private final void _appendNativeIds(java.lang.StringBuilder);
    descriptor: (Ljava/lang/StringBuilder;)V
    flags: (0x0012) ACC_PRIVATE, ACC_FINAL
    Code:
      stack=3, locals=4, args_size=2
         0: aload_0
         1: getfield      #10                 // Field _last:Lcom/fasterxml/jackson/databind/util/TokenBuffer$Segment;
         4: aload_0
         5: getfield      #12                 // Field _appendAt:I
         8: iconst_1
         9: isub
        10: invokevirtual #41                 // Method com/fasterxml/jackson/databind/util/TokenBuffer$Segment.findObjectId:(I)Ljava/lang/Object;
        13: astore_2
        14: aload_2
        15: ifnull        37
        18: aload_1
        19: ldc           #120                // String [objectId=
        21: invokevirtual #103                // Method java/lang/StringBuilder.append:(Ljava/lang/String;)Ljava/lang/StringBuilder;
        24: aload_2
        25: invokestatic  #121                // Method java/lang/String.valueOf:(Ljava/lang/Object;)Ljava/lang/String;
        28: invokevirtual #103                // Method java/lang/StringBuilder.append:(Ljava/lang/String;)Ljava/lang/StringBuilder;
        31: bipush        93
        33: invokevirtual #112                // Method java/lang/StringBuilder.append:(C)Ljava/lang/StringBuilder;
        36: pop
        37: aload_0
        38: getfield      #10                 // Field _last:Lcom/fasterxml/jackson/databind/util/TokenBuffer$Segment;
        41: aload_0
        42: getfield      #12                 // Field _appendAt:I
        45: iconst_1
        46: isub
        47: invokevirtual #43                 // Method com/fasterxml/jackson/databind/util/TokenBuffer$Segment.findTypeId:(I)Ljava/lang/Object;
        50: astore_3
        51: aload_3
        52: ifnull        74
        55: aload_1
        56: ldc           #122                // String [typeId=
        58: invokevirtual #103                // Method java/lang/StringBuilder.append:(Ljava/lang/String;)Ljava/lang/StringBuilder;
        61: aload_3
        62: invokestatic  #121                // Method java/lang/String.valueOf:(Ljava/lang/Object;)Ljava/lang/String;
        65: invokevirtual #103                // Method java/lang/StringBuilder.append:(Ljava/lang/String;)Ljava/lang/StringBuilder;
        68: bipush        93
        70: invokevirtual #112                // Method java/lang/StringBuilder.append:(C)Ljava/lang/StringBuilder;
        73: pop
        74: return
      LineNumberTable:
        line 566: 0
        line 567: 14
        line 568: 18
        line 570: 37
        line 571: 51
        line 572: 55
        line 574: 74
      LocalVariableTable:
        Start  Length  Slot  Name   Signature
            0      75     0  this   Lcom/fasterxml/jackson/databind/util/TokenBuffer;
            0      75     1    sb   Ljava/lang/StringBuilder;
           14      61     2 objectId   Ljava/lang/Object;
           51      24     3 typeId   Ljava/lang/Object;
      StackMapTable: number_of_entries = 2
        frame_type = 252 /* append */
          offset_delta = 37
          locals = [ class java/lang/Object ]
        frame_type = 252 /* append */
          offset_delta = 36
          locals = [ class java/lang/Object ]

  public com.fasterxml.jackson.core.JsonGenerator enable(com.fasterxml.jackson.core.JsonGenerator$Feature);
    descriptor: (Lcom/fasterxml/jackson/core/JsonGenerator$Feature;)Lcom/fasterxml/jackson/core/JsonGenerator;
    flags: (0x0001) ACC_PUBLIC
    Code:
      stack=3, locals=2, args_size=2
         0: aload_0
         1: dup
         2: getfield      #5                  // Field _generatorFeatures:I
         5: aload_1
         6: invokevirtual #123                // Method com/fasterxml/jackson/core/JsonGenerator$Feature.getMask:()I
         9: ior
        10: putfield      #5                  // Field _generatorFeatures:I
        13: aload_0
        14: areturn
      LineNumberTable:
        line 584: 0
        line 585: 13
      LocalVariableTable:
        Start  Length  Slot  Name   Signature
            0      15     0  this   Lcom/fasterxml/jackson/databind/util/TokenBuffer;
            0      15     1     f   Lcom/fasterxml/jackson/core/JsonGenerator$Feature;

  public com.fasterxml.jackson.core.JsonGenerator disable(com.fasterxml.jackson.core.JsonGenerator$Feature);
    descriptor: (Lcom/fasterxml/jackson/core/JsonGenerator$Feature;)Lcom/fasterxml/jackson/core/JsonGenerator;
    flags: (0x0001) ACC_PUBLIC
    Code:
      stack=4, locals=2, args_size=2
         0: aload_0
         1: dup
         2: getfield      #5                  // Field _generatorFeatures:I
         5: aload_1
         6: invokevirtual #123                // Method com/fasterxml/jackson/core/JsonGenerator$Feature.getMask:()I
         9: iconst_m1
        10: ixor
        11: iand
        12: putfield      #5                  // Field _generatorFeatures:I
        15: aload_0
        16: areturn
      LineNumberTable:
        line 590: 0
        line 591: 15
      LocalVariableTable:
        Start  Length  Slot  Name   Signature
            0      17     0  this   Lcom/fasterxml/jackson/databind/util/TokenBuffer;
            0      17     1     f   Lcom/fasterxml/jackson/core/JsonGenerator$Feature;

  public boolean isEnabled(com.fasterxml.jackson.core.JsonGenerator$Feature);
    descriptor: (Lcom/fasterxml/jackson/core/JsonGenerator$Feature;)Z
    flags: (0x0001) ACC_PUBLIC
    Code:
      stack=2, locals=2, args_size=2
         0: aload_0
         1: getfield      #5                  // Field _generatorFeatures:I
         4: aload_1
         5: invokevirtual #123                // Method com/fasterxml/jackson/core/JsonGenerator$Feature.getMask:()I
         8: iand
         9: ifeq          16
        12: iconst_1
        13: goto          17
        16: iconst_0
        17: ireturn
      LineNumberTable:
        line 598: 0
      LocalVariableTable:
        Start  Length  Slot  Name   Signature
            0      18     0  this   Lcom/fasterxml/jackson/databind/util/TokenBuffer;
            0      18     1     f   Lcom/fasterxml/jackson/core/JsonGenerator$Feature;
      StackMapTable: number_of_entries = 2
        frame_type = 16 /* same */
        frame_type = 64 /* same_locals_1_stack_item */
          stack = [ int ]

  public int getFeatureMask();
    descriptor: ()I
    flags: (0x0001) ACC_PUBLIC
    Code:
      stack=1, locals=1, args_size=1
         0: aload_0
         1: getfield      #5                  // Field _generatorFeatures:I
         4: ireturn
      LineNumberTable:
        line 603: 0
      LocalVariableTable:
        Start  Length  Slot  Name   Signature
            0       5     0  this   Lcom/fasterxml/jackson/databind/util/TokenBuffer;

  public com.fasterxml.jackson.core.JsonGenerator setFeatureMask(int);
    descriptor: (I)Lcom/fasterxml/jackson/core/JsonGenerator;
    flags: (0x0001) ACC_PUBLIC
    Code:
      stack=2, locals=2, args_size=2
         0: aload_0
         1: iload_1
         2: putfield      #5                  // Field _generatorFeatures:I
         5: aload_0
         6: areturn
      LineNumberTable:
        line 610: 0
        line 611: 5
      LocalVariableTable:
        Start  Length  Slot  Name   Signature
            0       7     0  this   Lcom/fasterxml/jackson/databind/util/TokenBuffer;
            0       7     1  mask   I
    Deprecated: true
    RuntimeVisibleAnnotations:
      0: #269()
        java.lang.Deprecated

  public com.fasterxml.jackson.core.JsonGenerator overrideStdFeatures(int, int);
    descriptor: (II)Lcom/fasterxml/jackson/core/JsonGenerator;
    flags: (0x0001) ACC_PUBLIC
    Code:
      stack=4, locals=4, args_size=3
         0: aload_0
         1: invokevirtual #124                // Method getFeatureMask:()I
         4: istore_3
         5: aload_0
         6: iload_3
         7: iload_2
         8: iconst_m1
         9: ixor
        10: iand
        11: iload_1
        12: iload_2
        13: iand
        14: ior
        15: putfield      #5                  // Field _generatorFeatures:I
        18: aload_0
        19: areturn
      LineNumberTable:
        line 616: 0
        line 617: 5
        line 618: 18
      LocalVariableTable:
        Start  Length  Slot  Name   Signature
            0      20     0  this   Lcom/fasterxml/jackson/databind/util/TokenBuffer;
            0      20     1 values   I
            0      20     2  mask   I
            5      15     3 oldState   I

  public com.fasterxml.jackson.core.JsonGenerator useDefaultPrettyPrinter();
    descriptor: ()Lcom/fasterxml/jackson/core/JsonGenerator;
    flags: (0x0001) ACC_PUBLIC
    Code:
      stack=1, locals=1, args_size=1
         0: aload_0
         1: areturn
      LineNumberTable:
        line 624: 0
      LocalVariableTable:
        Start  Length  Slot  Name   Signature
            0       2     0  this   Lcom/fasterxml/jackson/databind/util/TokenBuffer;

  public com.fasterxml.jackson.core.JsonGenerator setCodec(com.fasterxml.jackson.core.ObjectCodec);
    descriptor: (Lcom/fasterxml/jackson/core/ObjectCodec;)Lcom/fasterxml/jackson/core/JsonGenerator;
    flags: (0x0001) ACC_PUBLIC
    Code:
      stack=2, locals=2, args_size=2
         0: aload_0
         1: aload_1
         2: putfield      #3                  // Field _objectCodec:Lcom/fasterxml/jackson/core/ObjectCodec;
         5: aload_0
         6: areturn
      LineNumberTable:
        line 629: 0
        line 630: 5
      LocalVariableTable:
        Start  Length  Slot  Name   Signature
            0       7     0  this   Lcom/fasterxml/jackson/databind/util/TokenBuffer;
            0       7     1    oc   Lcom/fasterxml/jackson/core/ObjectCodec;

  public com.fasterxml.jackson.core.ObjectCodec getCodec();
    descriptor: ()Lcom/fasterxml/jackson/core/ObjectCodec;
    flags: (0x0001) ACC_PUBLIC
    Code:
      stack=1, locals=1, args_size=1
         0: aload_0
         1: getfield      #3                  // Field _objectCodec:Lcom/fasterxml/jackson/core/ObjectCodec;
         4: areturn
      LineNumberTable:
        line 634: 0
      LocalVariableTable:
        Start  Length  Slot  Name   Signature
            0       5     0  this   Lcom/fasterxml/jackson/databind/util/TokenBuffer;

  public final com.fasterxml.jackson.core.json.JsonWriteContext getOutputContext();
    descriptor: ()Lcom/fasterxml/jackson/core/json/JsonWriteContext;
    flags: (0x0011) ACC_PUBLIC, ACC_FINAL
    Code:
      stack=1, locals=1, args_size=1
         0: aload_0
         1: getfield      #7                  // Field _writeContext:Lcom/fasterxml/jackson/core/json/JsonWriteContext;
         4: areturn
      LineNumberTable:
        line 637: 0
      LocalVariableTable:
        Start  Length  Slot  Name   Signature
            0       5     0  this   Lcom/fasterxml/jackson/databind/util/TokenBuffer;

  public boolean canWriteBinaryNatively();
    descriptor: ()Z
    flags: (0x0001) ACC_PUBLIC
    Code:
      stack=1, locals=1, args_size=1
         0: iconst_1
         1: ireturn
      LineNumberTable:
        line 650: 0
      LocalVariableTable:
        Start  Length  Slot  Name   Signature
            0       2     0  this   Lcom/fasterxml/jackson/databind/util/TokenBuffer;

  public com.fasterxml.jackson.core.util.JacksonFeatureSet<com.fasterxml.jackson.core.StreamWriteCapability> getWriteCapabilities();
    descriptor: ()Lcom/fasterxml/jackson/core/util/JacksonFeatureSet;
    flags: (0x0001) ACC_PUBLIC
    Code:
      stack=1, locals=1, args_size=1
         0: getstatic     #125                // Field DEFAULT_WRITE_CAPABILITIES:Lcom/fasterxml/jackson/core/util/JacksonFeatureSet;
         3: areturn
      LineNumberTable:
        line 659: 0
      LocalVariableTable:
        Start  Length  Slot  Name   Signature
            0       4     0  this   Lcom/fasterxml/jackson/databind/util/TokenBuffer;
    Signature: #355                         // ()Lcom/fasterxml/jackson/core/util/JacksonFeatureSet<Lcom/fasterxml/jackson/core/StreamWriteCapability;>;

  public void flush() throws java.io.IOException;
    descriptor: ()V
    flags: (0x0001) ACC_PUBLIC
    Code:
      stack=0, locals=1, args_size=1
         0: return
      LineNumberTable:
        line 669: 0
      LocalVariableTable:
        Start  Length  Slot  Name   Signature
            0       1     0  this   Lcom/fasterxml/jackson/databind/util/TokenBuffer;
    Exceptions:
      throws java.io.IOException

  public void close() throws java.io.IOException;
    descriptor: ()V
    flags: (0x0001) ACC_PUBLIC
    Code:
      stack=2, locals=1, args_size=1
         0: aload_0
         1: iconst_1
         2: putfield      #126                // Field _closed:Z
         5: return
      LineNumberTable:
        line 673: 0
        line 674: 5
      LocalVariableTable:
        Start  Length  Slot  Name   Signature
            0       6     0  this   Lcom/fasterxml/jackson/databind/util/TokenBuffer;
    Exceptions:
      throws java.io.IOException

  public boolean isClosed();
    descriptor: ()Z
    flags: (0x0001) ACC_PUBLIC
    Code:
      stack=1, locals=1, args_size=1
         0: aload_0
         1: getfield      #126                // Field _closed:Z
         4: ireturn
      LineNumberTable:
        line 677: 0
      LocalVariableTable:
        Start  Length  Slot  Name   Signature
            0       5     0  this   Lcom/fasterxml/jackson/databind/util/TokenBuffer;

  public final void writeStartArray() throws java.io.IOException;
    descriptor: ()V
    flags: (0x0011) ACC_PUBLIC, ACC_FINAL
    Code:
      stack=2, locals=1, args_size=1
         0: aload_0
         1: getfield      #7                  // Field _writeContext:Lcom/fasterxml/jackson/core/json/JsonWriteContext;
         4: invokevirtual #127                // Method com/fasterxml/jackson/core/json/JsonWriteContext.writeValue:()I
         7: pop
         8: aload_0
         9: getstatic     #128                // Field com/fasterxml/jackson/core/JsonToken.START_ARRAY:Lcom/fasterxml/jackson/core/JsonToken;
        12: invokevirtual #129                // Method _appendStartMarker:(Lcom/fasterxml/jackson/core/JsonToken;)V
        15: aload_0
        16: aload_0
        17: getfield      #7                  // Field _writeContext:Lcom/fasterxml/jackson/core/json/JsonWriteContext;
        20: invokevirtual #130                // Method com/fasterxml/jackson/core/json/JsonWriteContext.createChildArrayContext:()Lcom/fasterxml/jackson/core/json/JsonWriteContext;
        23: putfield      #7                  // Field _writeContext:Lcom/fasterxml/jackson/core/json/JsonWriteContext;
        26: return
      LineNumberTable:
        line 688: 0
        line 689: 8
        line 690: 15
        line 691: 26
      LocalVariableTable:
        Start  Length  Slot  Name   Signature
            0      27     0  this   Lcom/fasterxml/jackson/databind/util/TokenBuffer;
    Exceptions:
      throws java.io.IOException

  public void writeStartArray(java.lang.Object) throws java.io.IOException;
    descriptor: (Ljava/lang/Object;)V
    flags: (0x0001) ACC_PUBLIC
    Code:
      stack=3, locals=2, args_size=2
         0: aload_0
         1: getfield      #7                  // Field _writeContext:Lcom/fasterxml/jackson/core/json/JsonWriteContext;
         4: invokevirtual #127                // Method com/fasterxml/jackson/core/json/JsonWriteContext.writeValue:()I
         7: pop
         8: aload_0
         9: getstatic     #128                // Field com/fasterxml/jackson/core/JsonToken.START_ARRAY:Lcom/fasterxml/jackson/core/JsonToken;
        12: invokevirtual #129                // Method _appendStartMarker:(Lcom/fasterxml/jackson/core/JsonToken;)V
        15: aload_0
        16: aload_0
        17: getfield      #7                  // Field _writeContext:Lcom/fasterxml/jackson/core/json/JsonWriteContext;
        20: aload_1
        21: invokevirtual #131                // Method com/fasterxml/jackson/core/json/JsonWriteContext.createChildArrayContext:(Ljava/lang/Object;)Lcom/fasterxml/jackson/core/json/JsonWriteContext;
        24: putfield      #7                  // Field _writeContext:Lcom/fasterxml/jackson/core/json/JsonWriteContext;
        27: return
      LineNumberTable:
        line 695: 0
        line 696: 8
        line 697: 15
        line 698: 27
      LocalVariableTable:
        Start  Length  Slot  Name   Signature
            0      28     0  this   Lcom/fasterxml/jackson/databind/util/TokenBuffer;
            0      28     1 forValue   Ljava/lang/Object;
    Exceptions:
      throws java.io.IOException

  public void writeStartArray(java.lang.Object, int) throws java.io.IOException;
    descriptor: (Ljava/lang/Object;I)V
    flags: (0x0001) ACC_PUBLIC
    Code:
      stack=3, locals=3, args_size=3
         0: aload_0
         1: getfield      #7                  // Field _writeContext:Lcom/fasterxml/jackson/core/json/JsonWriteContext;
         4: invokevirtual #127                // Method com/fasterxml/jackson/core/json/JsonWriteContext.writeValue:()I
         7: pop
         8: aload_0
         9: getstatic     #128                // Field com/fasterxml/jackson/core/JsonToken.START_ARRAY:Lcom/fasterxml/jackson/core/JsonToken;
        12: invokevirtual #129                // Method _appendStartMarker:(Lcom/fasterxml/jackson/core/JsonToken;)V
        15: aload_0
        16: aload_0
        17: getfield      #7                  // Field _writeContext:Lcom/fasterxml/jackson/core/json/JsonWriteContext;
        20: aload_1
        21: invokevirtual #131                // Method com/fasterxml/jackson/core/json/JsonWriteContext.createChildArrayContext:(Ljava/lang/Object;)Lcom/fasterxml/jackson/core/json/JsonWriteContext;
        24: putfield      #7                  // Field _writeContext:Lcom/fasterxml/jackson/core/json/JsonWriteContext;
        27: return
      LineNumberTable:
        line 702: 0
        line 703: 8
        line 704: 15
        line 705: 27
      LocalVariableTable:
        Start  Length  Slot  Name   Signature
            0      28     0  this   Lcom/fasterxml/jackson/databind/util/TokenBuffer;
            0      28     1 forValue   Ljava/lang/Object;
            0      28     2  size   I
    Exceptions:
      throws java.io.IOException

  public final void writeEndArray() throws java.io.IOException;
    descriptor: ()V
    flags: (0x0011) ACC_PUBLIC, ACC_FINAL
    Code:
      stack=2, locals=2, args_size=1
         0: aload_0
         1: getstatic     #132                // Field com/fasterxml/jackson/core/JsonToken.END_ARRAY:Lcom/fasterxml/jackson/core/JsonToken;
         4: invokevirtual #133                // Method _appendEndMarker:(Lcom/fasterxml/jackson/core/JsonToken;)V
         7: aload_0
         8: getfield      #7                  // Field _writeContext:Lcom/fasterxml/jackson/core/json/JsonWriteContext;
        11: invokevirtual #134                // Method com/fasterxml/jackson/core/json/JsonWriteContext.getParent:()Lcom/fasterxml/jackson/core/json/JsonWriteContext;
        14: astore_1
        15: aload_1
        16: ifnull        24
        19: aload_0
        20: aload_1
        21: putfield      #7                  // Field _writeContext:Lcom/fasterxml/jackson/core/json/JsonWriteContext;
        24: return
      LineNumberTable:
        line 710: 0
        line 712: 7
        line 713: 15
        line 714: 19
        line 716: 24
      LocalVariableTable:
        Start  Length  Slot  Name   Signature
            0      25     0  this   Lcom/fasterxml/jackson/databind/util/TokenBuffer;
           15      10     1     c   Lcom/fasterxml/jackson/core/json/JsonWriteContext;
      StackMapTable: number_of_entries = 1
        frame_type = 252 /* append */
          offset_delta = 24
          locals = [ class com/fasterxml/jackson/core/json/JsonWriteContext ]
    Exceptions:
      throws java.io.IOException

  public final void writeStartObject() throws java.io.IOException;
    descriptor: ()V
    flags: (0x0011) ACC_PUBLIC, ACC_FINAL
    Code:
      stack=2, locals=1, args_size=1
         0: aload_0
         1: getfield      #7                  // Field _writeContext:Lcom/fasterxml/jackson/core/json/JsonWriteContext;
         4: invokevirtual #127                // Method com/fasterxml/jackson/core/json/JsonWriteContext.writeValue:()I
         7: pop
         8: aload_0
         9: getstatic     #135                // Field com/fasterxml/jackson/core/JsonToken.START_OBJECT:Lcom/fasterxml/jackson/core/JsonToken;
        12: invokevirtual #129                // Method _appendStartMarker:(Lcom/fasterxml/jackson/core/JsonToken;)V
        15: aload_0
        16: aload_0
        17: getfield      #7                  // Field _writeContext:Lcom/fasterxml/jackson/core/json/JsonWriteContext;
        20: invokevirtual #136                // Method com/fasterxml/jackson/core/json/JsonWriteContext.createChildObjectContext:()Lcom/fasterxml/jackson/core/json/JsonWriteContext;
        23: putfield      #7                  // Field _writeContext:Lcom/fasterxml/jackson/core/json/JsonWriteContext;
        26: return
      LineNumberTable:
        line 721: 0
        line 722: 8
        line 723: 15
        line 724: 26
      LocalVariableTable:
        Start  Length  Slot  Name   Signature
            0      27     0  this   Lcom/fasterxml/jackson/databind/util/TokenBuffer;
    Exceptions:
      throws java.io.IOException

  public void writeStartObject(java.lang.Object) throws java.io.IOException;
    descriptor: (Ljava/lang/Object;)V
    flags: (0x0001) ACC_PUBLIC
    Code:
      stack=2, locals=3, args_size=2
         0: aload_0
         1: getfield      #7                  // Field _writeContext:Lcom/fasterxml/jackson/core/json/JsonWriteContext;
         4: invokevirtual #127                // Method com/fasterxml/jackson/core/json/JsonWriteContext.writeValue:()I
         7: pop
         8: aload_0
         9: getstatic     #135                // Field com/fasterxml/jackson/core/JsonToken.START_OBJECT:Lcom/fasterxml/jackson/core/JsonToken;
        12: invokevirtual #129                // Method _appendStartMarker:(Lcom/fasterxml/jackson/core/JsonToken;)V
        15: aload_0
        16: getfield      #7                  // Field _writeContext:Lcom/fasterxml/jackson/core/json/JsonWriteContext;
        19: aload_1
        20: invokevirtual #137                // Method com/fasterxml/jackson/core/json/JsonWriteContext.createChildObjectContext:(Ljava/lang/Object;)Lcom/fasterxml/jackson/core/json/JsonWriteContext;
        23: astore_2
        24: aload_0
        25: aload_2
        26: putfield      #7                  // Field _writeContext:Lcom/fasterxml/jackson/core/json/JsonWriteContext;
        29: return
      LineNumberTable:
        line 729: 0
        line 730: 8
        line 731: 15
        line 732: 24
        line 733: 29
      LocalVariableTable:
        Start  Length  Slot  Name   Signature
            0      30     0  this   Lcom/fasterxml/jackson/databind/util/TokenBuffer;
            0      30     1 forValue   Ljava/lang/Object;
           24       6     2  ctxt   Lcom/fasterxml/jackson/core/json/JsonWriteContext;
    Exceptions:
      throws java.io.IOException

  public void writeStartObject(java.lang.Object, int) throws java.io.IOException;
    descriptor: (Ljava/lang/Object;I)V
    flags: (0x0001) ACC_PUBLIC
    Code:
      stack=2, locals=4, args_size=3
         0: aload_0
         1: getfield      #7                  // Field _writeContext:Lcom/fasterxml/jackson/core/json/JsonWriteContext;
         4: invokevirtual #127                // Method com/fasterxml/jackson/core/json/JsonWriteContext.writeValue:()I
         7: pop
         8: aload_0
         9: getstatic     #135                // Field com/fasterxml/jackson/core/JsonToken.START_OBJECT:Lcom/fasterxml/jackson/core/JsonToken;
        12: invokevirtual #129                // Method _appendStartMarker:(Lcom/fasterxml/jackson/core/JsonToken;)V
        15: aload_0
        16: getfield      #7                  // Field _writeContext:Lcom/fasterxml/jackson/core/json/JsonWriteContext;
        19: aload_1
        20: invokevirtual #137                // Method com/fasterxml/jackson/core/json/JsonWriteContext.createChildObjectContext:(Ljava/lang/Object;)Lcom/fasterxml/jackson/core/json/JsonWriteContext;
        23: astore_3
        24: aload_0
        25: aload_3
        26: putfield      #7                  // Field _writeContext:Lcom/fasterxml/jackson/core/json/JsonWriteContext;
        29: return
      LineNumberTable:
        line 738: 0
        line 739: 8
        line 740: 15
        line 741: 24
        line 742: 29
      LocalVariableTable:
        Start  Length  Slot  Name   Signature
            0      30     0  this   Lcom/fasterxml/jackson/databind/util/TokenBuffer;
            0      30     1 forValue   Ljava/lang/Object;
            0      30     2  size   I
           24       6     3  ctxt   Lcom/fasterxml/jackson/core/json/JsonWriteContext;
    Exceptions:
      throws java.io.IOException

  public final void writeEndObject() throws java.io.IOException;
    descriptor: ()V
    flags: (0x0011) ACC_PUBLIC, ACC_FINAL
    Code:
      stack=2, locals=2, args_size=1
         0: aload_0
         1: getstatic     #99                 // Field com/fasterxml/jackson/core/JsonToken.END_OBJECT:Lcom/fasterxml/jackson/core/JsonToken;
         4: invokevirtual #133                // Method _appendEndMarker:(Lcom/fasterxml/jackson/core/JsonToken;)V
         7: aload_0
         8: getfield      #7                  // Field _writeContext:Lcom/fasterxml/jackson/core/json/JsonWriteContext;
        11: invokevirtual #134                // Method com/fasterxml/jackson/core/json/JsonWriteContext.getParent:()Lcom/fasterxml/jackson/core/json/JsonWriteContext;
        14: astore_1
        15: aload_1
        16: ifnull        24
        19: aload_0
        20: aload_1
        21: putfield      #7                  // Field _writeContext:Lcom/fasterxml/jackson/core/json/JsonWriteContext;
        24: return
      LineNumberTable:
        line 747: 0
        line 749: 7
        line 750: 15
        line 751: 19
        line 753: 24
      LocalVariableTable:
        Start  Length  Slot  Name   Signature
            0      25     0  this   Lcom/fasterxml/jackson/databind/util/TokenBuffer;
           15      10     1     c   Lcom/fasterxml/jackson/core/json/JsonWriteContext;
      StackMapTable: number_of_entries = 1
        frame_type = 252 /* append */
          offset_delta = 24
          locals = [ class com/fasterxml/jackson/core/json/JsonWriteContext ]
    Exceptions:
      throws java.io.IOException

  public final void writeFieldName(java.lang.String) throws java.io.IOException;
    descriptor: (Ljava/lang/String;)V
    flags: (0x0011) ACC_PUBLIC, ACC_FINAL
    Code:
      stack=2, locals=2, args_size=2
         0: aload_0
         1: getfield      #7                  // Field _writeContext:Lcom/fasterxml/jackson/core/json/JsonWriteContext;
         4: aload_1
         5: invokevirtual #138                // Method com/fasterxml/jackson/core/json/JsonWriteContext.writeFieldName:(Ljava/lang/String;)I
         8: pop
         9: aload_0
        10: aload_1
        11: invokevirtual #139                // Method _appendFieldName:(Ljava/lang/Object;)V
        14: return
      LineNumberTable:
        line 758: 0
        line 759: 9
        line 760: 14
      LocalVariableTable:
        Start  Length  Slot  Name   Signature
            0      15     0  this   Lcom/fasterxml/jackson/databind/util/TokenBuffer;
            0      15     1  name   Ljava/lang/String;
    Exceptions:
      throws java.io.IOException

  public void writeFieldName(com.fasterxml.jackson.core.SerializableString) throws java.io.IOException;
    descriptor: (Lcom/fasterxml/jackson/core/SerializableString;)V
    flags: (0x0001) ACC_PUBLIC
    Code:
      stack=2, locals=2, args_size=2
         0: aload_0
         1: getfield      #7                  // Field _writeContext:Lcom/fasterxml/jackson/core/json/JsonWriteContext;
         4: aload_1
         5: invokeinterface #140,  1          // InterfaceMethod com/fasterxml/jackson/core/SerializableString.getValue:()Ljava/lang/String;
        10: invokevirtual #138                // Method com/fasterxml/jackson/core/json/JsonWriteContext.writeFieldName:(Ljava/lang/String;)I
        13: pop
        14: aload_0
        15: aload_1
        16: invokevirtual #139                // Method _appendFieldName:(Ljava/lang/Object;)V
        19: return
      LineNumberTable:
        line 765: 0
        line 766: 14
        line 767: 19
      LocalVariableTable:
        Start  Length  Slot  Name   Signature
            0      20     0  this   Lcom/fasterxml/jackson/databind/util/TokenBuffer;
            0      20     1  name   Lcom/fasterxml/jackson/core/SerializableString;
    Exceptions:
      throws java.io.IOException

  public void writeString(java.lang.String) throws java.io.IOException;
    descriptor: (Ljava/lang/String;)V
    flags: (0x0001) ACC_PUBLIC
    Code:
      stack=3, locals=2, args_size=2
         0: aload_1
         1: ifnonnull     11
         4: aload_0
         5: invokevirtual #141                // Method writeNull:()V
         8: goto          19
        11: aload_0
        12: getstatic     #142                // Field com/fasterxml/jackson/core/JsonToken.VALUE_STRING:Lcom/fasterxml/jackson/core/JsonToken;
        15: aload_1
        16: invokevirtual #143                // Method _appendValue:(Lcom/fasterxml/jackson/core/JsonToken;Ljava/lang/Object;)V
        19: return
      LineNumberTable:
        line 777: 0
        line 778: 4
        line 780: 11
        line 782: 19
      LocalVariableTable:
        Start  Length  Slot  Name   Signature
            0      20     0  this   Lcom/fasterxml/jackson/databind/util/TokenBuffer;
            0      20     1  text   Ljava/lang/String;
      StackMapTable: number_of_entries = 2
        frame_type = 11 /* same */
        frame_type = 7 /* same */
    Exceptions:
      throws java.io.IOException

  public void writeString(char[], int, int) throws java.io.IOException;
    descriptor: ([CII)V
    flags: (0x0001) ACC_PUBLIC
    Code:
      stack=6, locals=4, args_size=4
         0: aload_0
         1: new           #54                 // class java/lang/String
         4: dup
         5: aload_1
         6: iload_2
         7: iload_3
         8: invokespecial #144                // Method java/lang/String."<init>":([CII)V
        11: invokevirtual #145                // Method writeString:(Ljava/lang/String;)V
        14: return
      LineNumberTable:
        line 786: 0
        line 787: 14
      LocalVariableTable:
        Start  Length  Slot  Name   Signature
            0      15     0  this   Lcom/fasterxml/jackson/databind/util/TokenBuffer;
            0      15     1  text   [C
            0      15     2 offset   I
            0      15     3   len   I
    Exceptions:
      throws java.io.IOException

  public void writeString(com.fasterxml.jackson.core.SerializableString) throws java.io.IOException;
    descriptor: (Lcom/fasterxml/jackson/core/SerializableString;)V
    flags: (0x0001) ACC_PUBLIC
    Code:
      stack=3, locals=2, args_size=2
         0: aload_1
         1: ifnonnull     11
         4: aload_0
         5: invokevirtual #141                // Method writeNull:()V
         8: goto          19
        11: aload_0
        12: getstatic     #142                // Field com/fasterxml/jackson/core/JsonToken.VALUE_STRING:Lcom/fasterxml/jackson/core/JsonToken;
        15: aload_1
        16: invokevirtual #143                // Method _appendValue:(Lcom/fasterxml/jackson/core/JsonToken;Ljava/lang/Object;)V
        19: return
      LineNumberTable:
        line 791: 0
        line 792: 4
        line 794: 11
        line 796: 19
      LocalVariableTable:
        Start  Length  Slot  Name   Signature
            0      20     0  this   Lcom/fasterxml/jackson/databind/util/TokenBuffer;
            0      20     1  text   Lcom/fasterxml/jackson/core/SerializableString;
      StackMapTable: number_of_entries = 2
        frame_type = 11 /* same */
        frame_type = 7 /* same */
    Exceptions:
      throws java.io.IOException

  public void writeRawUTF8String(byte[], int, int) throws java.io.IOException;
    descriptor: ([BII)V
    flags: (0x0001) ACC_PUBLIC
    Code:
      stack=1, locals=4, args_size=4
         0: aload_0
         1: invokevirtual #146                // Method _reportUnsupportedOperation:()V
         4: return
      LineNumberTable:
        line 802: 0
        line 803: 4
      LocalVariableTable:
        Start  Length  Slot  Name   Signature
            0       5     0  this   Lcom/fasterxml/jackson/databind/util/TokenBuffer;
            0       5     1  text   [B
            0       5     2 offset   I
            0       5     3 length   I
    Exceptions:
      throws java.io.IOException

  public void writeUTF8String(byte[], int, int) throws java.io.IOException;
    descriptor: ([BII)V
    flags: (0x0001) ACC_PUBLIC
    Code:
      stack=1, locals=4, args_size=4
         0: aload_0
         1: invokevirtual #146                // Method _reportUnsupportedOperation:()V
         4: return
      LineNumberTable:
        line 809: 0
        line 810: 4
      LocalVariableTable:
        Start  Length  Slot  Name   Signature
            0       5     0  this   Lcom/fasterxml/jackson/databind/util/TokenBuffer;
            0       5     1  text   [B
            0       5     2 offset   I
            0       5     3 length   I
    Exceptions:
      throws java.io.IOException

  public void writeRaw(java.lang.String) throws java.io.IOException;
    descriptor: (Ljava/lang/String;)V
    flags: (0x0001) ACC_PUBLIC
    Code:
      stack=1, locals=2, args_size=2
         0: aload_0
         1: invokevirtual #146                // Method _reportUnsupportedOperation:()V
         4: return
      LineNumberTable:
        line 814: 0
        line 815: 4
      LocalVariableTable:
        Start  Length  Slot  Name   Signature
            0       5     0  this   Lcom/fasterxml/jackson/databind/util/TokenBuffer;
            0       5     1  text   Ljava/lang/String;
    Exceptions:
      throws java.io.IOException

  public void writeRaw(java.lang.String, int, int) throws java.io.IOException;
    descriptor: (Ljava/lang/String;II)V
    flags: (0x0001) ACC_PUBLIC
    Code:
      stack=1, locals=4, args_size=4
         0: aload_0
         1: invokevirtual #146                // Method _reportUnsupportedOperation:()V
         4: return
      LineNumberTable:
        line 819: 0
        line 820: 4
      LocalVariableTable:
        Start  Length  Slot  Name   Signature
            0       5     0  this   Lcom/fasterxml/jackson/databind/util/TokenBuffer;
            0       5     1  text   Ljava/lang/String;
            0       5     2 offset   I
            0       5     3   len   I
    Exceptions:
      throws java.io.IOException

  public void writeRaw(com.fasterxml.jackson.core.SerializableString) throws java.io.IOException;
    descriptor: (Lcom/fasterxml/jackson/core/SerializableString;)V
    flags: (0x0001) ACC_PUBLIC
    Code:
      stack=1, locals=2, args_size=2
         0: aload_0
         1: invokevirtual #146                // Method _reportUnsupportedOperation:()V
         4: return
      LineNumberTable:
        line 824: 0
        line 825: 4
      LocalVariableTable:
        Start  Length  Slot  Name   Signature
            0       5     0  this   Lcom/fasterxml/jackson/databind/util/TokenBuffer;
            0       5     1  text   Lcom/fasterxml/jackson/core/SerializableString;
    Exceptions:
      throws java.io.IOException

  public void writeRaw(char[], int, int) throws java.io.IOException;
    descriptor: ([CII)V
    flags: (0x0001) ACC_PUBLIC
    Code:
      stack=1, locals=4, args_size=4
         0: aload_0
         1: invokevirtual #146                // Method _reportUnsupportedOperation:()V
         4: return
      LineNumberTable:
        line 829: 0
        line 830: 4
      LocalVariableTable:
        Start  Length  Slot  Name   Signature
            0       5     0  this   Lcom/fasterxml/jackson/databind/util/TokenBuffer;
            0       5     1  text   [C
            0       5     2 offset   I
            0       5     3   len   I
    Exceptions:
      throws java.io.IOException

  public void writeRaw(char) throws java.io.IOException;
    descriptor: (C)V
    flags: (0x0001) ACC_PUBLIC
    Code:
      stack=1, locals=2, args_size=2
         0: aload_0
         1: invokevirtual #146                // Method _reportUnsupportedOperation:()V
         4: return
      LineNumberTable:
        line 834: 0
        line 835: 4
      LocalVariableTable:
        Start  Length  Slot  Name   Signature
            0       5     0  this   Lcom/fasterxml/jackson/databind/util/TokenBuffer;
            0       5     1     c   C
    Exceptions:
      throws java.io.IOException

  public void writeRawValue(java.lang.String) throws java.io.IOException;
    descriptor: (Ljava/lang/String;)V
    flags: (0x0001) ACC_PUBLIC
    Code:
      stack=5, locals=2, args_size=2
         0: aload_0
         1: getstatic     #147                // Field com/fasterxml/jackson/core/JsonToken.VALUE_EMBEDDED_OBJECT:Lcom/fasterxml/jackson/core/JsonToken;
         4: new           #88                 // class com/fasterxml/jackson/databind/util/RawValue
         7: dup
         8: aload_1
         9: invokespecial #148                // Method com/fasterxml/jackson/databind/util/RawValue."<init>":(Ljava/lang/String;)V
        12: invokevirtual #143                // Method _appendValue:(Lcom/fasterxml/jackson/core/JsonToken;Ljava/lang/Object;)V
        15: return
      LineNumberTable:
        line 839: 0
        line 840: 15
      LocalVariableTable:
        Start  Length  Slot  Name   Signature
            0      16     0  this   Lcom/fasterxml/jackson/databind/util/TokenBuffer;
            0      16     1  text   Ljava/lang/String;
    Exceptions:
      throws java.io.IOException

  public void writeRawValue(java.lang.String, int, int) throws java.io.IOException;
    descriptor: (Ljava/lang/String;II)V
    flags: (0x0001) ACC_PUBLIC
    Code:
      stack=5, locals=4, args_size=4
         0: iload_2
         1: ifgt          12
         4: iload_3
         5: aload_1
         6: invokevirtual #149                // Method java/lang/String.length:()I
         9: if_icmpeq     21
        12: aload_1
        13: iload_2
        14: iload_2
        15: iload_3
        16: iadd
        17: invokevirtual #150                // Method java/lang/String.substring:(II)Ljava/lang/String;
        20: astore_1
        21: aload_0
        22: getstatic     #147                // Field com/fasterxml/jackson/core/JsonToken.VALUE_EMBEDDED_OBJECT:Lcom/fasterxml/jackson/core/JsonToken;
        25: new           #88                 // class com/fasterxml/jackson/databind/util/RawValue
        28: dup
        29: aload_1
        30: invokespecial #148                // Method com/fasterxml/jackson/databind/util/RawValue."<init>":(Ljava/lang/String;)V
        33: invokevirtual #143                // Method _appendValue:(Lcom/fasterxml/jackson/core/JsonToken;Ljava/lang/Object;)V
        36: return
      LineNumberTable:
        line 844: 0
        line 845: 12
        line 847: 21
        line 848: 36
      LocalVariableTable:
        Start  Length  Slot  Name   Signature
            0      37     0  this   Lcom/fasterxml/jackson/databind/util/TokenBuffer;
            0      37     1  text   Ljava/lang/String;
            0      37     2 offset   I
            0      37     3   len   I
      StackMapTable: number_of_entries = 2
        frame_type = 12 /* same */
        frame_type = 8 /* same */
    Exceptions:
      throws java.io.IOException

  public void writeRawValue(char[], int, int) throws java.io.IOException;
    descriptor: ([CII)V
    flags: (0x0001) ACC_PUBLIC
    Code:
      stack=7, locals=4, args_size=4
         0: aload_0
         1: getstatic     #147                // Field com/fasterxml/jackson/core/JsonToken.VALUE_EMBEDDED_OBJECT:Lcom/fasterxml/jackson/core/JsonToken;
         4: new           #54                 // class java/lang/String
         7: dup
         8: aload_1
         9: iload_2
        10: iload_3
        11: invokespecial #144                // Method java/lang/String."<init>":([CII)V
        14: invokevirtual #143                // Method _appendValue:(Lcom/fasterxml/jackson/core/JsonToken;Ljava/lang/Object;)V
        17: return
      LineNumberTable:
        line 852: 0
        line 853: 17
      LocalVariableTable:
        Start  Length  Slot  Name   Signature
            0      18     0  this   Lcom/fasterxml/jackson/databind/util/TokenBuffer;
            0      18     1  text   [C
            0      18     2 offset   I
            0      18     3   len   I
    Exceptions:
      throws java.io.IOException

  public void writeNumber(short) throws java.io.IOException;
    descriptor: (S)V
    flags: (0x0001) ACC_PUBLIC
    Code:
      stack=3, locals=2, args_size=2
         0: aload_0
         1: getstatic     #151                // Field com/fasterxml/jackson/core/JsonToken.VALUE_NUMBER_INT:Lcom/fasterxml/jackson/core/JsonToken;
         4: iload_1
         5: invokestatic  #152                // Method java/lang/Short.valueOf:(S)Ljava/lang/Short;
         8: invokevirtual #143                // Method _appendValue:(Lcom/fasterxml/jackson/core/JsonToken;Ljava/lang/Object;)V
        11: return
      LineNumberTable:
        line 863: 0
        line 864: 11
      LocalVariableTable:
        Start  Length  Slot  Name   Signature
            0      12     0  this   Lcom/fasterxml/jackson/databind/util/TokenBuffer;
            0      12     1     i   S
    Exceptions:
      throws java.io.IOException

  public void writeNumber(int) throws java.io.IOException;
    descriptor: (I)V
    flags: (0x0001) ACC_PUBLIC
    Code:
      stack=3, locals=2, args_size=2
         0: aload_0
         1: getstatic     #151                // Field com/fasterxml/jackson/core/JsonToken.VALUE_NUMBER_INT:Lcom/fasterxml/jackson/core/JsonToken;
         4: iload_1
         5: invokestatic  #153                // Method java/lang/Integer.valueOf:(I)Ljava/lang/Integer;
         8: invokevirtual #143                // Method _appendValue:(Lcom/fasterxml/jackson/core/JsonToken;Ljava/lang/Object;)V
        11: return
      LineNumberTable:
        line 868: 0
        line 869: 11
      LocalVariableTable:
        Start  Length  Slot  Name   Signature
            0      12     0  this   Lcom/fasterxml/jackson/databind/util/TokenBuffer;
            0      12     1     i   I
    Exceptions:
      throws java.io.IOException

  public void writeNumber(long) throws java.io.IOException;
    descriptor: (J)V
    flags: (0x0001) ACC_PUBLIC
    Code:
      stack=4, locals=3, args_size=2
         0: aload_0
         1: getstatic     #151                // Field com/fasterxml/jackson/core/JsonToken.VALUE_NUMBER_INT:Lcom/fasterxml/jackson/core/JsonToken;
         4: lload_1
         5: invokestatic  #154                // Method java/lang/Long.valueOf:(J)Ljava/lang/Long;
         8: invokevirtual #143                // Method _appendValue:(Lcom/fasterxml/jackson/core/JsonToken;Ljava/lang/Object;)V
        11: return
      LineNumberTable:
        line 873: 0
        line 874: 11
      LocalVariableTable:
        Start  Length  Slot  Name   Signature
            0      12     0  this   Lcom/fasterxml/jackson/databind/util/TokenBuffer;
            0      12     1     l   J
    Exceptions:
      throws java.io.IOException

  public void writeNumber(double) throws java.io.IOException;
    descriptor: (D)V
    flags: (0x0001) ACC_PUBLIC
    Code:
      stack=4, locals=3, args_size=2
         0: aload_0
         1: getstatic     #155                // Field com/fasterxml/jackson/core/JsonToken.VALUE_NUMBER_FLOAT:Lcom/fasterxml/jackson/core/JsonToken;
         4: dload_1
         5: invokestatic  #156                // Method java/lang/Double.valueOf:(D)Ljava/lang/Double;
         8: invokevirtual #143                // Method _appendValue:(Lcom/fasterxml/jackson/core/JsonToken;Ljava/lang/Object;)V
        11: return
      LineNumberTable:
        line 878: 0
        line 879: 11
      LocalVariableTable:
        Start  Length  Slot  Name   Signature
            0      12     0  this   Lcom/fasterxml/jackson/databind/util/TokenBuffer;
            0      12     1     d   D
    Exceptions:
      throws java.io.IOException

  public void writeNumber(float) throws java.io.IOException;
    descriptor: (F)V
    flags: (0x0001) ACC_PUBLIC
    Code:
      stack=3, locals=2, args_size=2
         0: aload_0
         1: getstatic     #155                // Field com/fasterxml/jackson/core/JsonToken.VALUE_NUMBER_FLOAT:Lcom/fasterxml/jackson/core/JsonToken;
         4: fload_1
         5: invokestatic  #157                // Method java/lang/Float.valueOf:(F)Ljava/lang/Float;
         8: invokevirtual #143                // Method _appendValue:(Lcom/fasterxml/jackson/core/JsonToken;Ljava/lang/Object;)V
        11: return
      LineNumberTable:
        line 883: 0
        line 884: 11
      LocalVariableTable:
        Start  Length  Slot  Name   Signature
            0      12     0  this   Lcom/fasterxml/jackson/databind/util/TokenBuffer;
            0      12     1     f   F
    Exceptions:
      throws java.io.IOException

  public void writeNumber(java.math.BigDecimal) throws java.io.IOException;
    descriptor: (Ljava/math/BigDecimal;)V
    flags: (0x0001) ACC_PUBLIC
    Code:
      stack=3, locals=2, args_size=2
         0: aload_1
         1: ifnonnull     11
         4: aload_0
         5: invokevirtual #141                // Method writeNull:()V
         8: goto          19
        11: aload_0
        12: getstatic     #155                // Field com/fasterxml/jackson/core/JsonToken.VALUE_NUMBER_FLOAT:Lcom/fasterxml/jackson/core/JsonToken;
        15: aload_1
        16: invokevirtual #143                // Method _appendValue:(Lcom/fasterxml/jackson/core/JsonToken;Ljava/lang/Object;)V
        19: return
      LineNumberTable:
        line 888: 0
        line 889: 4
        line 891: 11
        line 893: 19
      LocalVariableTable:
        Start  Length  Slot  Name   Signature
            0      20     0  this   Lcom/fasterxml/jackson/databind/util/TokenBuffer;
            0      20     1   dec   Ljava/math/BigDecimal;
      StackMapTable: number_of_entries = 2
        frame_type = 11 /* same */
        frame_type = 7 /* same */
    Exceptions:
      throws java.io.IOException

  public void writeNumber(java.math.BigInteger) throws java.io.IOException;
    descriptor: (Ljava/math/BigInteger;)V
    flags: (0x0001) ACC_PUBLIC
    Code:
      stack=3, locals=2, args_size=2
         0: aload_1
         1: ifnonnull     11
         4: aload_0
         5: invokevirtual #141                // Method writeNull:()V
         8: goto          19
        11: aload_0
        12: getstatic     #151                // Field com/fasterxml/jackson/core/JsonToken.VALUE_NUMBER_INT:Lcom/fasterxml/jackson/core/JsonToken;
        15: aload_1
        16: invokevirtual #143                // Method _appendValue:(Lcom/fasterxml/jackson/core/JsonToken;Ljava/lang/Object;)V
        19: return
      LineNumberTable:
        line 897: 0
        line 898: 4
        line 900: 11
        line 902: 19
      LocalVariableTable:
        Start  Length  Slot  Name   Signature
            0      20     0  this   Lcom/fasterxml/jackson/databind/util/TokenBuffer;
            0      20     1     v   Ljava/math/BigInteger;
      StackMapTable: number_of_entries = 2
        frame_type = 11 /* same */
        frame_type = 7 /* same */
    Exceptions:
      throws java.io.IOException

  public void writeNumber(java.lang.String) throws java.io.IOException;
    descriptor: (Ljava/lang/String;)V
    flags: (0x0001) ACC_PUBLIC
    Code:
      stack=3, locals=2, args_size=2
         0: aload_0
         1: getstatic     #155                // Field com/fasterxml/jackson/core/JsonToken.VALUE_NUMBER_FLOAT:Lcom/fasterxml/jackson/core/JsonToken;
         4: aload_1
         5: invokevirtual #143                // Method _appendValue:(Lcom/fasterxml/jackson/core/JsonToken;Ljava/lang/Object;)V
         8: return
      LineNumberTable:
        line 909: 0
        line 910: 8
      LocalVariableTable:
        Start  Length  Slot  Name   Signature
            0       9     0  this   Lcom/fasterxml/jackson/databind/util/TokenBuffer;
            0       9     1 encodedValue   Ljava/lang/String;
    Exceptions:
      throws java.io.IOException

  public void writeBoolean(boolean) throws java.io.IOException;
    descriptor: (Z)V
    flags: (0x0001) ACC_PUBLIC
    Code:
      stack=2, locals=2, args_size=2
         0: aload_0
         1: iload_1
         2: ifeq          11
         5: getstatic     #158                // Field com/fasterxml/jackson/core/JsonToken.VALUE_TRUE:Lcom/fasterxml/jackson/core/JsonToken;
         8: goto          14
        11: getstatic     #159                // Field com/fasterxml/jackson/core/JsonToken.VALUE_FALSE:Lcom/fasterxml/jackson/core/JsonToken;
        14: invokevirtual #160                // Method _appendValue:(Lcom/fasterxml/jackson/core/JsonToken;)V
        17: return
      LineNumberTable:
        line 914: 0
        line 915: 17
      LocalVariableTable:
        Start  Length  Slot  Name   Signature
            0      18     0  this   Lcom/fasterxml/jackson/databind/util/TokenBuffer;
            0      18     1 state   Z
      StackMapTable: number_of_entries = 2
        frame_type = 75 /* same_locals_1_stack_item */
          stack = [ class com/fasterxml/jackson/databind/util/TokenBuffer ]
        frame_type = 255 /* full_frame */
          offset_delta = 2
          locals = [ class com/fasterxml/jackson/databind/util/TokenBuffer, int ]
          stack = [ class com/fasterxml/jackson/databind/util/TokenBuffer, class com/fasterxml/jackson/core/JsonToken ]
    Exceptions:
      throws java.io.IOException

  public void writeNull() throws java.io.IOException;
    descriptor: ()V
    flags: (0x0001) ACC_PUBLIC
    Code:
      stack=2, locals=1, args_size=1
         0: aload_0
         1: getstatic     #161                // Field com/fasterxml/jackson/core/JsonToken.VALUE_NULL:Lcom/fasterxml/jackson/core/JsonToken;
         4: invokevirtual #160                // Method _appendValue:(Lcom/fasterxml/jackson/core/JsonToken;)V
         7: return
      LineNumberTable:
        line 919: 0
        line 920: 7
      LocalVariableTable:
        Start  Length  Slot  Name   Signature
            0       8     0  this   Lcom/fasterxml/jackson/databind/util/TokenBuffer;
    Exceptions:
      throws java.io.IOException

  public void writeObject(java.lang.Object) throws java.io.IOException;
    descriptor: (Ljava/lang/Object;)V
    flags: (0x0001) ACC_PUBLIC
    Code:
      stack=3, locals=3, args_size=2
         0: aload_1
         1: ifnonnull     9
         4: aload_0
         5: invokevirtual #141                // Method writeNull:()V
         8: return
         9: aload_1
        10: invokevirtual #83                 // Method java/lang/Object.getClass:()Ljava/lang/Class;
        13: astore_2
        14: aload_2
        15: ldc           #162                // class "[B"
        17: if_acmpeq     27
        20: aload_1
        21: instanceof    #88                 // class com/fasterxml/jackson/databind/util/RawValue
        24: ifeq          36
        27: aload_0
        28: getstatic     #147                // Field com/fasterxml/jackson/core/JsonToken.VALUE_EMBEDDED_OBJECT:Lcom/fasterxml/jackson/core/JsonToken;
        31: aload_1
        32: invokevirtual #143                // Method _appendValue:(Lcom/fasterxml/jackson/core/JsonToken;Ljava/lang/Object;)V
        35: return
        36: aload_0
        37: getfield      #3                  // Field _objectCodec:Lcom/fasterxml/jackson/core/ObjectCodec;
        40: ifnonnull     54
        43: aload_0
        44: getstatic     #147                // Field com/fasterxml/jackson/core/JsonToken.VALUE_EMBEDDED_OBJECT:Lcom/fasterxml/jackson/core/JsonToken;
        47: aload_1
        48: invokevirtual #143                // Method _appendValue:(Lcom/fasterxml/jackson/core/JsonToken;Ljava/lang/Object;)V
        51: goto          63
        54: aload_0
        55: getfield      #3                  // Field _objectCodec:Lcom/fasterxml/jackson/core/ObjectCodec;
        58: aload_0
        59: aload_1
        60: invokevirtual #163                // Method com/fasterxml/jackson/core/ObjectCodec.writeValue:(Lcom/fasterxml/jackson/core/JsonGenerator;Ljava/lang/Object;)V
        63: return
      LineNumberTable:
        line 931: 0
        line 932: 4
        line 933: 8
        line 935: 9
        line 936: 14
        line 937: 27
        line 938: 35
        line 940: 36
        line 945: 43
        line 947: 54
        line 949: 63
      LocalVariableTable:
        Start  Length  Slot  Name   Signature
            0      64     0  this   Lcom/fasterxml/jackson/databind/util/TokenBuffer;
            0      64     1 value   Ljava/lang/Object;
           14      50     2   raw   Ljava/lang/Class;
      LocalVariableTypeTable:
        Start  Length  Slot  Name   Signature
           14      50     2   raw   Ljava/lang/Class<*>;
      StackMapTable: number_of_entries = 5
        frame_type = 9 /* same */
        frame_type = 252 /* append */
          offset_delta = 17
          locals = [ class java/lang/Class ]
        frame_type = 8 /* same */
        frame_type = 17 /* same */
        frame_type = 8 /* same */
    Exceptions:
      throws java.io.IOException

  public void writeTree(com.fasterxml.jackson.core.TreeNode) throws java.io.IOException;
    descriptor: (Lcom/fasterxml/jackson/core/TreeNode;)V
    flags: (0x0001) ACC_PUBLIC
    Code:
      stack=3, locals=2, args_size=2
         0: aload_1
         1: ifnonnull     9
         4: aload_0
         5: invokevirtual #141                // Method writeNull:()V
         8: return
         9: aload_0
        10: getfield      #3                  // Field _objectCodec:Lcom/fasterxml/jackson/core/ObjectCodec;
        13: ifnonnull     27
        16: aload_0
        17: getstatic     #147                // Field com/fasterxml/jackson/core/JsonToken.VALUE_EMBEDDED_OBJECT:Lcom/fasterxml/jackson/core/JsonToken;
        20: aload_1
        21: invokevirtual #143                // Method _appendValue:(Lcom/fasterxml/jackson/core/JsonToken;Ljava/lang/Object;)V
        24: goto          36
        27: aload_0
        28: getfield      #3                  // Field _objectCodec:Lcom/fasterxml/jackson/core/ObjectCodec;
        31: aload_0
        32: aload_1
        33: invokevirtual #164                // Method com/fasterxml/jackson/core/ObjectCodec.writeTree:(Lcom/fasterxml/jackson/core/JsonGenerator;Lcom/fasterxml/jackson/core/TreeNode;)V
        36: return
      LineNumberTable:
        line 954: 0
        line 955: 4
        line 956: 8
        line 959: 9
        line 961: 16
        line 963: 27
        line 965: 36
      LocalVariableTable:
        Start  Length  Slot  Name   Signature
            0      37     0  this   Lcom/fasterxml/jackson/databind/util/TokenBuffer;
            0      37     1  node   Lcom/fasterxml/jackson/core/TreeNode;
      StackMapTable: number_of_entries = 3
        frame_type = 9 /* same */
        frame_type = 17 /* same */
        frame_type = 8 /* same */
    Exceptions:
      throws java.io.IOException

  public void writeBinary(com.fasterxml.jackson.core.Base64Variant, byte[], int, int) throws java.io.IOException;
    descriptor: (Lcom/fasterxml/jackson/core/Base64Variant;[BII)V
    flags: (0x0001) ACC_PUBLIC
    Code:
      stack=5, locals=6, args_size=5
         0: iload         4
         2: newarray       byte
         4: astore        5
         6: aload_2
         7: iload_3
         8: aload         5
        10: iconst_0
        11: iload         4
        13: invokestatic  #165                // Method java/lang/System.arraycopy:(Ljava/lang/Object;ILjava/lang/Object;II)V
        16: aload_0
        17: aload         5
        19: invokevirtual #166                // Method writeObject:(Ljava/lang/Object;)V
        22: return
      LineNumberTable:
        line 982: 0
        line 983: 6
        line 984: 16
        line 985: 22
      LocalVariableTable:
        Start  Length  Slot  Name   Signature
            0      23     0  this   Lcom/fasterxml/jackson/databind/util/TokenBuffer;
            0      23     1 b64variant   Lcom/fasterxml/jackson/core/Base64Variant;
            0      23     2  data   [B
            0      23     3 offset   I
            0      23     4   len   I
            6      17     5  copy   [B
    Exceptions:
      throws java.io.IOException

  public int writeBinary(com.fasterxml.jackson.core.Base64Variant, java.io.InputStream, int);
    descriptor: (Lcom/fasterxml/jackson/core/Base64Variant;Ljava/io/InputStream;I)I
    flags: (0x0001) ACC_PUBLIC
    Code:
      stack=2, locals=4, args_size=4
         0: new           #167                // class java/lang/UnsupportedOperationException
         3: dup
         4: invokespecial #168                // Method java/lang/UnsupportedOperationException."<init>":()V
         7: athrow
      LineNumberTable:
        line 995: 0
      LocalVariableTable:
        Start  Length  Slot  Name   Signature
            0       8     0  this   Lcom/fasterxml/jackson/databind/util/TokenBuffer;
            0       8     1 b64variant   Lcom/fasterxml/jackson/core/Base64Variant;
            0       8     2  data   Ljava/io/InputStream;
            0       8     3 dataLength   I

  public boolean canWriteTypeId();
    descriptor: ()Z
    flags: (0x0001) ACC_PUBLIC
    Code:
      stack=1, locals=1, args_size=1
         0: aload_0
         1: getfield      #13                 // Field _hasNativeTypeIds:Z
         4: ireturn
      LineNumberTable:
        line 1006: 0
      LocalVariableTable:
        Start  Length  Slot  Name   Signature
            0       5     0  this   Lcom/fasterxml/jackson/databind/util/TokenBuffer;

  public boolean canWriteObjectId();
    descriptor: ()Z
    flags: (0x0001) ACC_PUBLIC
    Code:
      stack=1, locals=1, args_size=1
         0: aload_0
         1: getfield      #14                 // Field _hasNativeObjectIds:Z
         4: ireturn
      LineNumberTable:
        line 1011: 0
      LocalVariableTable:
        Start  Length  Slot  Name   Signature
            0       5     0  this   Lcom/fasterxml/jackson/databind/util/TokenBuffer;

  public void writeTypeId(java.lang.Object);
    descriptor: (Ljava/lang/Object;)V
    flags: (0x0001) ACC_PUBLIC
    Code:
      stack=2, locals=2, args_size=2
         0: aload_0
         1: aload_1
         2: putfield      #169                // Field _typeId:Ljava/lang/Object;
         5: aload_0
         6: iconst_1
         7: putfield      #2                  // Field _hasNativeId:Z
        10: return
      LineNumberTable:
        line 1016: 0
        line 1017: 5
        line 1018: 10
      LocalVariableTable:
        Start  Length  Slot  Name   Signature
            0      11     0  this   Lcom/fasterxml/jackson/databind/util/TokenBuffer;
            0      11     1    id   Ljava/lang/Object;

  public void writeObjectId(java.lang.Object);
    descriptor: (Ljava/lang/Object;)V
    flags: (0x0001) ACC_PUBLIC
    Code:
      stack=2, locals=2, args_size=2
         0: aload_0
         1: aload_1
         2: putfield      #170                // Field _objectId:Ljava/lang/Object;
         5: aload_0
         6: iconst_1
         7: putfield      #2                  // Field _hasNativeId:Z
        10: return
      LineNumberTable:
        line 1022: 0
        line 1023: 5
        line 1024: 10
      LocalVariableTable:
        Start  Length  Slot  Name   Signature
            0      11     0  this   Lcom/fasterxml/jackson/databind/util/TokenBuffer;
            0      11     1    id   Ljava/lang/Object;

  public void writeEmbeddedObject(java.lang.Object) throws java.io.IOException;
    descriptor: (Ljava/lang/Object;)V
    flags: (0x0001) ACC_PUBLIC
    Code:
      stack=3, locals=2, args_size=2
         0: aload_0
         1: getstatic     #147                // Field com/fasterxml/jackson/core/JsonToken.VALUE_EMBEDDED_OBJECT:Lcom/fasterxml/jackson/core/JsonToken;
         4: aload_1
         5: invokevirtual #143                // Method _appendValue:(Lcom/fasterxml/jackson/core/JsonToken;Ljava/lang/Object;)V
         8: return
      LineNumberTable:
        line 1028: 0
        line 1029: 8
      LocalVariableTable:
        Start  Length  Slot  Name   Signature
            0       9     0  this   Lcom/fasterxml/jackson/databind/util/TokenBuffer;
            0       9     1 object   Ljava/lang/Object;
    Exceptions:
      throws java.io.IOException

  public void copyCurrentEvent(com.fasterxml.jackson.core.JsonParser) throws java.io.IOException;
    descriptor: (Lcom/fasterxml/jackson/core/JsonParser;)V
    flags: (0x0001) ACC_PUBLIC
    Code:
      stack=4, locals=2, args_size=2
         0: aload_0
         1: getfield      #15                 // Field _mayHaveNativeIds:Z
         4: ifeq          12
         7: aload_0
         8: aload_1
         9: invokespecial #171                // Method _checkNativeIds:(Lcom/fasterxml/jackson/core/JsonParser;)V
        12: getstatic     #45                 // Field com/fasterxml/jackson/databind/util/TokenBuffer$1.$SwitchMap$com$fasterxml$jackson$core$JsonToken:[I
        15: aload_1
        16: invokevirtual #172                // Method com/fasterxml/jackson/core/JsonParser.currentToken:()Lcom/fasterxml/jackson/core/JsonToken;
        19: invokevirtual #46                 // Method com/fasterxml/jackson/core/JsonToken.ordinal:()I
        22: iaload
        23: tableswitch   { // 1 to 12
                       1: 84
                       2: 91
                       3: 98
                       4: 105
                       5: 112
                       6: 123
                       7: 160
                       8: 229
                       9: 317
                      10: 325
                      11: 333
                      12: 340
                 default: 351
            }
        84: aload_0
        85: invokevirtual #98                 // Method writeStartObject:()V
        88: goto          381
        91: aload_0
        92: invokevirtual #107                // Method writeEndObject:()V
        95: goto          381
        98: aload_0
        99: invokevirtual #173                // Method writeStartArray:()V
       102: goto          381
       105: aload_0
       106: invokevirtual #174                // Method writeEndArray:()V
       109: goto          381
       112: aload_0
       113: aload_1
       114: invokevirtual #113                // Method com/fasterxml/jackson/core/JsonParser.currentName:()Ljava/lang/String;
       117: invokevirtual #175                // Method writeFieldName:(Ljava/lang/String;)V
       120: goto          381
       123: aload_1
       124: invokevirtual #176                // Method com/fasterxml/jackson/core/JsonParser.hasTextCharacters:()Z
       127: ifeq          149
       130: aload_0
       131: aload_1
       132: invokevirtual #177                // Method com/fasterxml/jackson/core/JsonParser.getTextCharacters:()[C
       135: aload_1
       136: invokevirtual #178                // Method com/fasterxml/jackson/core/JsonParser.getTextOffset:()I
       139: aload_1
       140: invokevirtual #179                // Method com/fasterxml/jackson/core/JsonParser.getTextLength:()I
       143: invokevirtual #180                // Method writeString:([CII)V
       146: goto          381
       149: aload_0
       150: aload_1
       151: invokevirtual #181                // Method com/fasterxml/jackson/core/JsonParser.getText:()Ljava/lang/String;
       154: invokevirtual #145                // Method writeString:(Ljava/lang/String;)V
       157: goto          381
       160: getstatic     #182                // Field com/fasterxml/jackson/databind/util/TokenBuffer$1.$SwitchMap$com$fasterxml$jackson$core$JsonParser$NumberType:[I
       163: aload_1
       164: invokevirtual #183                // Method com/fasterxml/jackson/core/JsonParser.getNumberType:()Lcom/fasterxml/jackson/core/JsonParser$NumberType;
       167: invokevirtual #184                // Method com/fasterxml/jackson/core/JsonParser$NumberType.ordinal:()I
       170: iaload
       171: lookupswitch  { // 2
                       1: 196
                       2: 207
                 default: 218
            }
       196: aload_0
       197: aload_1
       198: invokevirtual #185                // Method com/fasterxml/jackson/core/JsonParser.getIntValue:()I
       201: invokevirtual #186                // Method writeNumber:(I)V
       204: goto          381
       207: aload_0
       208: aload_1
       209: invokevirtual #187                // Method com/fasterxml/jackson/core/JsonParser.getBigIntegerValue:()Ljava/math/BigInteger;
       212: invokevirtual #188                // Method writeNumber:(Ljava/math/BigInteger;)V
       215: goto          381
       218: aload_0
       219: aload_1
       220: invokevirtual #189                // Method com/fasterxml/jackson/core/JsonParser.getLongValue:()J
       223: invokevirtual #190                // Method writeNumber:(J)V
       226: goto          381
       229: aload_0
       230: getfield      #24                 // Field _forceBigDecimal:Z
       233: ifeq          247
       236: aload_0
       237: aload_1
       238: invokevirtual #191                // Method com/fasterxml/jackson/core/JsonParser.getDecimalValue:()Ljava/math/BigDecimal;
       241: invokevirtual #192                // Method writeNumber:(Ljava/math/BigDecimal;)V
       244: goto          381
       247: getstatic     #182                // Field com/fasterxml/jackson/databind/util/TokenBuffer$1.$SwitchMap$com$fasterxml$jackson$core$JsonParser$NumberType:[I
       250: aload_1
       251: invokevirtual #183                // Method com/fasterxml/jackson/core/JsonParser.getNumberType:()Lcom/fasterxml/jackson/core/JsonParser$NumberType;
       254: invokevirtual #184                // Method com/fasterxml/jackson/core/JsonParser$NumberType.ordinal:()I
       257: iaload
       258: lookupswitch  { // 2
                       3: 284
                       4: 295
                 default: 306
            }
       284: aload_0
       285: aload_1
       286: invokevirtual #191                // Method com/fasterxml/jackson/core/JsonParser.getDecimalValue:()Ljava/math/BigDecimal;
       289: invokevirtual #192                // Method writeNumber:(Ljava/math/BigDecimal;)V
       292: goto          381
       295: aload_0
       296: aload_1
       297: invokevirtual #193                // Method com/fasterxml/jackson/core/JsonParser.getFloatValue:()F
       300: invokevirtual #194                // Method writeNumber:(F)V
       303: goto          381
       306: aload_0
       307: aload_1
       308: invokevirtual #195                // Method com/fasterxml/jackson/core/JsonParser.getDoubleValue:()D
       311: invokevirtual #196                // Method writeNumber:(D)V
       314: goto          381
       317: aload_0
       318: iconst_1
       319: invokevirtual #197                // Method writeBoolean:(Z)V
       322: goto          381
       325: aload_0
       326: iconst_0
       327: invokevirtual #197                // Method writeBoolean:(Z)V
       330: goto          381
       333: aload_0
       334: invokevirtual #141                // Method writeNull:()V
       337: goto          381
       340: aload_0
       341: aload_1
       342: invokevirtual #198                // Method com/fasterxml/jackson/core/JsonParser.getEmbeddedObject:()Ljava/lang/Object;
       345: invokevirtual #166                // Method writeObject:(Ljava/lang/Object;)V
       348: goto          381
       351: new           #93                 // class java/lang/RuntimeException
       354: dup
       355: new           #100                // class java/lang/StringBuilder
       358: dup
       359: invokespecial #101                // Method java/lang/StringBuilder."<init>":()V
       362: ldc           #199                // String Internal error: unexpected token:
       364: invokevirtual #103                // Method java/lang/StringBuilder.append:(Ljava/lang/String;)Ljava/lang/StringBuilder;
       367: aload_1
       368: invokevirtual #172                // Method com/fasterxml/jackson/core/JsonParser.currentToken:()Lcom/fasterxml/jackson/core/JsonToken;
       371: invokevirtual #104                // Method java/lang/StringBuilder.append:(Ljava/lang/Object;)Ljava/lang/StringBuilder;
       374: invokevirtual #105                // Method java/lang/StringBuilder.toString:()Ljava/lang/String;
       377: invokespecial #95                 // Method java/lang/RuntimeException."<init>":(Ljava/lang/String;)V
       380: athrow
       381: return
      LineNumberTable:
        line 1040: 0
        line 1041: 7
        line 1043: 12
        line 1045: 84
        line 1046: 88
        line 1048: 91
        line 1049: 95
        line 1051: 98
        line 1052: 102
        line 1054: 105
        line 1055: 109
        line 1057: 112
        line 1058: 120
        line 1060: 123
        line 1061: 130
        line 1063: 149
        line 1065: 157
        line 1067: 160
        line 1069: 196
        line 1070: 204
        line 1072: 207
        line 1073: 215
        line 1075: 218
        line 1077: 226
        line 1079: 229
        line 1084: 236
        line 1086: 247
        line 1088: 284
        line 1089: 292
        line 1091: 295
        line 1092: 303
        line 1094: 306
        line 1097: 314
        line 1099: 317
        line 1100: 322
        line 1102: 325
        line 1103: 330
        line 1105: 333
        line 1106: 337
        line 1108: 340
        line 1109: 348
        line 1111: 351
        line 1113: 381
      LocalVariableTable:
        Start  Length  Slot  Name   Signature
            0     382     0  this   Lcom/fasterxml/jackson/databind/util/TokenBuffer;
            0     382     1     p   Lcom/fasterxml/jackson/core/JsonParser;
      StackMapTable: number_of_entries = 23
        frame_type = 12 /* same */
        frame_type = 251 /* same_frame_extended */
          offset_delta = 71
        frame_type = 6 /* same */
        frame_type = 6 /* same */
        frame_type = 6 /* same */
        frame_type = 6 /* same */
        frame_type = 10 /* same */
        frame_type = 25 /* same */
        frame_type = 10 /* same */
        frame_type = 35 /* same */
        frame_type = 10 /* same */
        frame_type = 10 /* same */
        frame_type = 10 /* same */
        frame_type = 17 /* same */
        frame_type = 36 /* same */
        frame_type = 10 /* same */
        frame_type = 10 /* same */
        frame_type = 10 /* same */
        frame_type = 7 /* same */
        frame_type = 7 /* same */
        frame_type = 6 /* same */
        frame_type = 10 /* same */
        frame_type = 29 /* same */
    Exceptions:
      throws java.io.IOException

  public void copyCurrentStructure(com.fasterxml.jackson.core.JsonParser) throws java.io.IOException;
    descriptor: (Lcom/fasterxml/jackson/core/JsonParser;)V
    flags: (0x0001) ACC_PUBLIC
    Code:
      stack=3, locals=3, args_size=2
         0: aload_1
         1: invokevirtual #172                // Method com/fasterxml/jackson/core/JsonParser.currentToken:()Lcom/fasterxml/jackson/core/JsonToken;
         4: astore_2
         5: aload_2
         6: getstatic     #96                 // Field com/fasterxml/jackson/core/JsonToken.FIELD_NAME:Lcom/fasterxml/jackson/core/JsonToken;
         9: if_acmpne     40
        12: aload_0
        13: getfield      #15                 // Field _mayHaveNativeIds:Z
        16: ifeq          24
        19: aload_0
        20: aload_1
        21: invokespecial #171                // Method _checkNativeIds:(Lcom/fasterxml/jackson/core/JsonParser;)V
        24: aload_0
        25: aload_1
        26: invokevirtual #113                // Method com/fasterxml/jackson/core/JsonParser.currentName:()Ljava/lang/String;
        29: invokevirtual #175                // Method writeFieldName:(Ljava/lang/String;)V
        32: aload_1
        33: invokevirtual #30                 // Method com/fasterxml/jackson/core/JsonParser.nextToken:()Lcom/fasterxml/jackson/core/JsonToken;
        36: astore_2
        37: goto          54
        40: aload_2
        41: ifnonnull     54
        44: new           #115                // class java/lang/IllegalStateException
        47: dup
        48: ldc           #200                // String No token available from argument `JsonParser`
        50: invokespecial #201                // Method java/lang/IllegalStateException."<init>":(Ljava/lang/String;)V
        53: athrow
        54: getstatic     #45                 // Field com/fasterxml/jackson/databind/util/TokenBuffer$1.$SwitchMap$com$fasterxml$jackson$core$JsonToken:[I
        57: aload_2
        58: invokevirtual #46                 // Method com/fasterxml/jackson/core/JsonToken.ordinal:()I
        61: iaload
        62: tableswitch   { // 1 to 4
                       1: 116
                       2: 147
                       3: 92
                       4: 140
                 default: 154
            }
        92: aload_0
        93: getfield      #15                 // Field _mayHaveNativeIds:Z
        96: ifeq          104
        99: aload_0
       100: aload_1
       101: invokespecial #171                // Method _checkNativeIds:(Lcom/fasterxml/jackson/core/JsonParser;)V
       104: aload_0
       105: invokevirtual #173                // Method writeStartArray:()V
       108: aload_0
       109: aload_1
       110: invokevirtual #202                // Method _copyBufferContents:(Lcom/fasterxml/jackson/core/JsonParser;)V
       113: goto          160
       116: aload_0
       117: getfield      #15                 // Field _mayHaveNativeIds:Z
       120: ifeq          128
       123: aload_0
       124: aload_1
       125: invokespecial #171                // Method _checkNativeIds:(Lcom/fasterxml/jackson/core/JsonParser;)V
       128: aload_0
       129: invokevirtual #98                 // Method writeStartObject:()V
       132: aload_0
       133: aload_1
       134: invokevirtual #202                // Method _copyBufferContents:(Lcom/fasterxml/jackson/core/JsonParser;)V
       137: goto          160
       140: aload_0
       141: invokevirtual #174                // Method writeEndArray:()V
       144: goto          160
       147: aload_0
       148: invokevirtual #107                // Method writeEndObject:()V
       151: goto          160
       154: aload_0
       155: aload_1
       156: aload_2
       157: invokespecial #203                // Method _copyBufferValue:(Lcom/fasterxml/jackson/core/JsonParser;Lcom/fasterxml/jackson/core/JsonToken;)V
       160: return
      LineNumberTable:
        line 1118: 0
        line 1121: 5
        line 1122: 12
        line 1123: 19
        line 1125: 24
        line 1126: 32
        line 1128: 40
        line 1129: 44
        line 1135: 54
        line 1137: 92
        line 1138: 99
        line 1140: 104
        line 1141: 108
        line 1142: 113
        line 1144: 116
        line 1145: 123
        line 1147: 128
        line 1148: 132
        line 1149: 137
        line 1151: 140
        line 1152: 144
        line 1154: 147
        line 1155: 151
        line 1157: 154
        line 1159: 160
      LocalVariableTable:
        Start  Length  Slot  Name   Signature
            0     161     0  this   Lcom/fasterxml/jackson/databind/util/TokenBuffer;
            0     161     1     p   Lcom/fasterxml/jackson/core/JsonParser;
            5     156     2     t   Lcom/fasterxml/jackson/core/JsonToken;
      StackMapTable: number_of_entries = 11
        frame_type = 252 /* append */
          offset_delta = 24
          locals = [ class com/fasterxml/jackson/core/JsonToken ]
        frame_type = 15 /* same */
        frame_type = 13 /* same */
        frame_type = 37 /* same */
        frame_type = 11 /* same */
        frame_type = 11 /* same */
        frame_type = 11 /* same */
        frame_type = 11 /* same */
        frame_type = 6 /* same */
        frame_type = 6 /* same */
        frame_type = 5 /* same */
    Exceptions:
      throws java.io.IOException

  protected void _copyBufferContents(com.fasterxml.jackson.core.JsonParser) throws java.io.IOException;
    descriptor: (Lcom/fasterxml/jackson/core/JsonParser;)V
    flags: (0x0004) ACC_PROTECTED
    Code:
      stack=3, locals=4, args_size=2
         0: iconst_1
         1: istore_2
         2: aload_1
         3: invokevirtual #30                 // Method com/fasterxml/jackson/core/JsonParser.nextToken:()Lcom/fasterxml/jackson/core/JsonToken;
         6: dup
         7: astore_3
         8: ifnull        152
        11: getstatic     #45                 // Field com/fasterxml/jackson/databind/util/TokenBuffer$1.$SwitchMap$com$fasterxml$jackson$core$JsonToken:[I
        14: aload_3
        15: invokevirtual #46                 // Method com/fasterxml/jackson/core/JsonToken.ordinal:()I
        18: iaload
        19: tableswitch   { // 1 to 5
                       1: 97
                       2: 131
                       3: 75
                       4: 119
                       5: 52
                 default: 143
            }
        52: aload_0
        53: getfield      #15                 // Field _mayHaveNativeIds:Z
        56: ifeq          64
        59: aload_0
        60: aload_1
        61: invokespecial #171                // Method _checkNativeIds:(Lcom/fasterxml/jackson/core/JsonParser;)V
        64: aload_0
        65: aload_1
        66: invokevirtual #113                // Method com/fasterxml/jackson/core/JsonParser.currentName:()Ljava/lang/String;
        69: invokevirtual #175                // Method writeFieldName:(Ljava/lang/String;)V
        72: goto          2
        75: aload_0
        76: getfield      #15                 // Field _mayHaveNativeIds:Z
        79: ifeq          87
        82: aload_0
        83: aload_1
        84: invokespecial #171                // Method _checkNativeIds:(Lcom/fasterxml/jackson/core/JsonParser;)V
        87: aload_0
        88: invokevirtual #173                // Method writeStartArray:()V
        91: iinc          2, 1
        94: goto          2
        97: aload_0
        98: getfield      #15                 // Field _mayHaveNativeIds:Z
       101: ifeq          109
       104: aload_0
       105: aload_1
       106: invokespecial #171                // Method _checkNativeIds:(Lcom/fasterxml/jackson/core/JsonParser;)V
       109: aload_0
       110: invokevirtual #98                 // Method writeStartObject:()V
       113: iinc          2, 1
       116: goto          2
       119: aload_0
       120: invokevirtual #174                // Method writeEndArray:()V
       123: iinc          2, -1
       126: iload_2
       127: ifne          2
       130: return
       131: aload_0
       132: invokevirtual #107                // Method writeEndObject:()V
       135: iinc          2, -1
       138: iload_2
       139: ifne          2
       142: return
       143: aload_0
       144: aload_1
       145: aload_3
       146: invokespecial #203                // Method _copyBufferValue:(Lcom/fasterxml/jackson/core/JsonParser;Lcom/fasterxml/jackson/core/JsonToken;)V
       149: goto          2
       152: return
      LineNumberTable:
        line 1163: 0
        line 1166: 2
        line 1167: 11
        line 1169: 52
        line 1170: 59
        line 1172: 64
        line 1173: 72
        line 1176: 75
        line 1177: 82
        line 1179: 87
        line 1180: 91
        line 1181: 94
        line 1184: 97
        line 1185: 104
        line 1187: 109
        line 1188: 113
        line 1189: 116
        line 1192: 119
        line 1193: 123
        line 1194: 130
        line 1198: 131
        line 1199: 135
        line 1200: 142
        line 1205: 143
        line 1208: 152
      LocalVariableTable:
        Start  Length  Slot  Name   Signature
            0     153     0  this   Lcom/fasterxml/jackson/databind/util/TokenBuffer;
            0     153     1     p   Lcom/fasterxml/jackson/core/JsonParser;
            2     151     2 depth   I
            8     145     3     t   Lcom/fasterxml/jackson/core/JsonToken;
      StackMapTable: number_of_entries = 11
        frame_type = 252 /* append */
          offset_delta = 2
          locals = [ int ]
        frame_type = 252 /* append */
          offset_delta = 49
          locals = [ class com/fasterxml/jackson/core/JsonToken ]
        frame_type = 11 /* same */
        frame_type = 10 /* same */
        frame_type = 11 /* same */
        frame_type = 9 /* same */
        frame_type = 11 /* same */
        frame_type = 9 /* same */
        frame_type = 11 /* same */
        frame_type = 11 /* same */
        frame_type = 8 /* same */
    Exceptions:
      throws java.io.IOException

  private void _copyBufferValue(com.fasterxml.jackson.core.JsonParser, com.fasterxml.jackson.core.JsonToken) throws java.io.IOException;
    descriptor: (Lcom/fasterxml/jackson/core/JsonParser;Lcom/fasterxml/jackson/core/JsonToken;)V
    flags: (0x0002) ACC_PRIVATE
    Code:
      stack=4, locals=4, args_size=3
         0: aload_0
         1: getfield      #15                 // Field _mayHaveNativeIds:Z
         4: ifeq          12
         7: aload_0
         8: aload_1
         9: invokespecial #171                // Method _checkNativeIds:(Lcom/fasterxml/jackson/core/JsonParser;)V
        12: getstatic     #45                 // Field com/fasterxml/jackson/databind/util/TokenBuffer$1.$SwitchMap$com$fasterxml$jackson$core$JsonToken:[I
        15: aload_2
        16: invokevirtual #46                 // Method com/fasterxml/jackson/core/JsonToken.ordinal:()I
        19: iaload
        20: tableswitch   { // 6 to 12
                       6: 64
                       7: 101
                       8: 173
                       9: 207
                      10: 215
                      11: 223
                      12: 230
                 default: 241
            }
        64: aload_1
        65: invokevirtual #176                // Method com/fasterxml/jackson/core/JsonParser.hasTextCharacters:()Z
        68: ifeq          90
        71: aload_0
        72: aload_1
        73: invokevirtual #177                // Method com/fasterxml/jackson/core/JsonParser.getTextCharacters:()[C
        76: aload_1
        77: invokevirtual #178                // Method com/fasterxml/jackson/core/JsonParser.getTextOffset:()I
        80: aload_1
        81: invokevirtual #179                // Method com/fasterxml/jackson/core/JsonParser.getTextLength:()I
        84: invokevirtual #180                // Method writeString:([CII)V
        87: goto          268
        90: aload_0
        91: aload_1
        92: invokevirtual #181                // Method com/fasterxml/jackson/core/JsonParser.getText:()Ljava/lang/String;
        95: invokevirtual #145                // Method writeString:(Ljava/lang/String;)V
        98: goto          268
       101: getstatic     #182                // Field com/fasterxml/jackson/databind/util/TokenBuffer$1.$SwitchMap$com$fasterxml$jackson$core$JsonParser$NumberType:[I
       104: aload_1
       105: invokevirtual #183                // Method com/fasterxml/jackson/core/JsonParser.getNumberType:()Lcom/fasterxml/jackson/core/JsonParser$NumberType;
       108: invokevirtual #184                // Method com/fasterxml/jackson/core/JsonParser$NumberType.ordinal:()I
       111: iaload
       112: lookupswitch  { // 2
                       1: 140
                       2: 151
                 default: 162
            }
       140: aload_0
       141: aload_1
       142: invokevirtual #185                // Method com/fasterxml/jackson/core/JsonParser.getIntValue:()I
       145: invokevirtual #186                // Method writeNumber:(I)V
       148: goto          268
       151: aload_0
       152: aload_1
       153: invokevirtual #187                // Method com/fasterxml/jackson/core/JsonParser.getBigIntegerValue:()Ljava/math/BigInteger;
       156: invokevirtual #188                // Method writeNumber:(Ljava/math/BigInteger;)V
       159: goto          268
       162: aload_0
       163: aload_1
       164: invokevirtual #189                // Method com/fasterxml/jackson/core/JsonParser.getLongValue:()J
       167: invokevirtual #190                // Method writeNumber:(J)V
       170: goto          268
       173: aload_0
       174: getfield      #24                 // Field _forceBigDecimal:Z
       177: ifeq          191
       180: aload_0
       181: aload_1
       182: invokevirtual #191                // Method com/fasterxml/jackson/core/JsonParser.getDecimalValue:()Ljava/math/BigDecimal;
       185: invokevirtual #192                // Method writeNumber:(Ljava/math/BigDecimal;)V
       188: goto          268
       191: aload_1
       192: invokevirtual #204                // Method com/fasterxml/jackson/core/JsonParser.getNumberValueExact:()Ljava/lang/Number;
       195: astore_3
       196: aload_0
       197: getstatic     #155                // Field com/fasterxml/jackson/core/JsonToken.VALUE_NUMBER_FLOAT:Lcom/fasterxml/jackson/core/JsonToken;
       200: aload_3
       201: invokevirtual #143                // Method _appendValue:(Lcom/fasterxml/jackson/core/JsonToken;Ljava/lang/Object;)V
       204: goto          268
       207: aload_0
       208: iconst_1
       209: invokevirtual #197                // Method writeBoolean:(Z)V
       212: goto          268
       215: aload_0
       216: iconst_0
       217: invokevirtual #197                // Method writeBoolean:(Z)V
       220: goto          268
       223: aload_0
       224: invokevirtual #141                // Method writeNull:()V
       227: goto          268
       230: aload_0
       231: aload_1
       232: invokevirtual #198                // Method com/fasterxml/jackson/core/JsonParser.getEmbeddedObject:()Ljava/lang/Object;
       235: invokevirtual #166                // Method writeObject:(Ljava/lang/Object;)V
       238: goto          268
       241: new           #93                 // class java/lang/RuntimeException
       244: dup
       245: new           #100                // class java/lang/StringBuilder
       248: dup
       249: invokespecial #101                // Method java/lang/StringBuilder."<init>":()V
       252: ldc           #199                // String Internal error: unexpected token:
       254: invokevirtual #103                // Method java/lang/StringBuilder.append:(Ljava/lang/String;)Ljava/lang/StringBuilder;
       257: aload_2
       258: invokevirtual #104                // Method java/lang/StringBuilder.append:(Ljava/lang/Object;)Ljava/lang/StringBuilder;
       261: invokevirtual #105                // Method java/lang/StringBuilder.toString:()Ljava/lang/String;
       264: invokespecial #95                 // Method java/lang/RuntimeException."<init>":(Ljava/lang/String;)V
       267: athrow
       268: return
      LineNumberTable:
        line 1213: 0
        line 1214: 7
        line 1216: 12
        line 1218: 64
        line 1219: 71
        line 1221: 90
        line 1223: 98
        line 1225: 101
        line 1227: 140
        line 1228: 148
        line 1230: 151
        line 1231: 159
        line 1233: 162
        line 1235: 170
        line 1237: 173
        line 1238: 180
        line 1242: 191
        line 1243: 196
        line 1245: 204
        line 1247: 207
        line 1248: 212
        line 1250: 215
        line 1251: 220
        line 1253: 223
        line 1254: 227
        line 1256: 230
        line 1257: 238
        line 1259: 241
        line 1261: 268
      LocalVariableTable:
        Start  Length  Slot  Name   Signature
          196       8     3     n   Ljava/lang/Number;
            0     269     0  this   Lcom/fasterxml/jackson/databind/util/TokenBuffer;
            0     269     1     p   Lcom/fasterxml/jackson/core/JsonParser;
            0     269     2     t   Lcom/fasterxml/jackson/core/JsonToken;
      StackMapTable: number_of_entries = 15
        frame_type = 12 /* same */
        frame_type = 51 /* same */
        frame_type = 25 /* same */
        frame_type = 10 /* same */
        frame_type = 38 /* same */
        frame_type = 10 /* same */
        frame_type = 10 /* same */
        frame_type = 10 /* same */
        frame_type = 17 /* same */
        frame_type = 15 /* same */
        frame_type = 7 /* same */
        frame_type = 7 /* same */
        frame_type = 6 /* same */
        frame_type = 10 /* same */
        frame_type = 26 /* same */
    Exceptions:
      throws java.io.IOException

  private final void _checkNativeIds(com.fasterxml.jackson.core.JsonParser) throws java.io.IOException;
    descriptor: (Lcom/fasterxml/jackson/core/JsonParser;)V
    flags: (0x0012) ACC_PRIVATE, ACC_FINAL
    Code:
      stack=3, locals=2, args_size=2
         0: aload_0
         1: aload_1
         2: invokevirtual #205                // Method com/fasterxml/jackson/core/JsonParser.getTypeId:()Ljava/lang/Object;
         5: dup_x1
         6: putfield      #169                // Field _typeId:Ljava/lang/Object;
         9: ifnull        17
        12: aload_0
        13: iconst_1
        14: putfield      #2                  // Field _hasNativeId:Z
        17: aload_0
        18: aload_1
        19: invokevirtual #206                // Method com/fasterxml/jackson/core/JsonParser.getObjectId:()Ljava/lang/Object;
        22: dup_x1
        23: putfield      #170                // Field _objectId:Ljava/lang/Object;
        26: ifnull        34
        29: aload_0
        30: iconst_1
        31: putfield      #2                  // Field _hasNativeId:Z
        34: return
      LineNumberTable:
        line 1265: 0
        line 1266: 12
        line 1268: 17
        line 1269: 29
        line 1271: 34
      LocalVariableTable:
        Start  Length  Slot  Name   Signature
            0      35     0  this   Lcom/fasterxml/jackson/databind/util/TokenBuffer;
            0      35     1     p   Lcom/fasterxml/jackson/core/JsonParser;
      StackMapTable: number_of_entries = 2
        frame_type = 17 /* same */
        frame_type = 16 /* same */
    Exceptions:
      throws java.io.IOException

  protected final void _appendValue(com.fasterxml.jackson.core.JsonToken);
    descriptor: (Lcom/fasterxml/jackson/core/JsonToken;)V
    flags: (0x0014) ACC_PROTECTED, ACC_FINAL
    Code:
      stack=5, locals=3, args_size=2
         0: aload_0
         1: getfield      #7                  // Field _writeContext:Lcom/fasterxml/jackson/core/json/JsonWriteContext;
         4: invokevirtual #127                // Method com/fasterxml/jackson/core/json/JsonWriteContext.writeValue:()I
         7: pop
         8: aload_0
         9: getfield      #2                  // Field _hasNativeId:Z
        12: ifeq          39
        15: aload_0
        16: getfield      #10                 // Field _last:Lcom/fasterxml/jackson/databind/util/TokenBuffer$Segment;
        19: aload_0
        20: getfield      #12                 // Field _appendAt:I
        23: aload_1
        24: aload_0
        25: getfield      #170                // Field _objectId:Ljava/lang/Object;
        28: aload_0
        29: getfield      #169                // Field _typeId:Ljava/lang/Object;
        32: invokevirtual #207                // Method com/fasterxml/jackson/databind/util/TokenBuffer$Segment.append:(ILcom/fasterxml/jackson/core/JsonToken;Ljava/lang/Object;Ljava/lang/Object;)Lcom/fasterxml/jackson/databind/util/TokenBuffer$Segment;
        35: astore_2
        36: goto          52
        39: aload_0
        40: getfield      #10                 // Field _last:Lcom/fasterxml/jackson/databind/util/TokenBuffer$Segment;
        43: aload_0
        44: getfield      #12                 // Field _appendAt:I
        47: aload_1
        48: invokevirtual #208                // Method com/fasterxml/jackson/databind/util/TokenBuffer$Segment.append:(ILcom/fasterxml/jackson/core/JsonToken;)Lcom/fasterxml/jackson/databind/util/TokenBuffer$Segment;
        51: astore_2
        52: aload_2
        53: ifnonnull     69
        56: aload_0
        57: dup
        58: getfield      #12                 // Field _appendAt:I
        61: iconst_1
        62: iadd
        63: putfield      #12                 // Field _appendAt:I
        66: goto          79
        69: aload_0
        70: aload_2
        71: putfield      #10                 // Field _last:Lcom/fasterxml/jackson/databind/util/TokenBuffer$Segment;
        74: aload_0
        75: iconst_1
        76: putfield      #12                 // Field _appendAt:I
        79: return
      LineNumberTable:
        line 1322: 0
        line 1324: 8
        line 1325: 15
        line 1327: 39
        line 1329: 52
        line 1330: 56
        line 1332: 69
        line 1333: 74
        line 1335: 79
      LocalVariableTable:
        Start  Length  Slot  Name   Signature
           36       3     2  next   Lcom/fasterxml/jackson/databind/util/TokenBuffer$Segment;
            0      80     0  this   Lcom/fasterxml/jackson/databind/util/TokenBuffer;
            0      80     1  type   Lcom/fasterxml/jackson/core/JsonToken;
           52      28     2  next   Lcom/fasterxml/jackson/databind/util/TokenBuffer$Segment;
      StackMapTable: number_of_entries = 4
        frame_type = 39 /* same */
        frame_type = 252 /* append */
          offset_delta = 12
          locals = [ class com/fasterxml/jackson/databind/util/TokenBuffer$Segment ]
        frame_type = 16 /* same */
        frame_type = 9 /* same */

  protected final void _appendValue(com.fasterxml.jackson.core.JsonToken, java.lang.Object);
    descriptor: (Lcom/fasterxml/jackson/core/JsonToken;Ljava/lang/Object;)V
    flags: (0x0014) ACC_PROTECTED, ACC_FINAL
    Code:
      stack=6, locals=4, args_size=3
         0: aload_0
         1: getfield      #7                  // Field _writeContext:Lcom/fasterxml/jackson/core/json/JsonWriteContext;
         4: invokevirtual #127                // Method com/fasterxml/jackson/core/json/JsonWriteContext.writeValue:()I
         7: pop
         8: aload_0
         9: getfield      #2                  // Field _hasNativeId:Z
        12: ifeq          40
        15: aload_0
        16: getfield      #10                 // Field _last:Lcom/fasterxml/jackson/databind/util/TokenBuffer$Segment;
        19: aload_0
        20: getfield      #12                 // Field _appendAt:I
        23: aload_1
        24: aload_2
        25: aload_0
        26: getfield      #170                // Field _objectId:Ljava/lang/Object;
        29: aload_0
        30: getfield      #169                // Field _typeId:Ljava/lang/Object;
        33: invokevirtual #209                // Method com/fasterxml/jackson/databind/util/TokenBuffer$Segment.append:(ILcom/fasterxml/jackson/core/JsonToken;Ljava/lang/Object;Ljava/lang/Object;Ljava/lang/Object;)Lcom/fasterxml/jackson/databind/util/TokenBuffer$Segment;
        36: astore_3
        37: goto          54
        40: aload_0
        41: getfield      #10                 // Field _last:Lcom/fasterxml/jackson/databind/util/TokenBuffer$Segment;
        44: aload_0
        45: getfield      #12                 // Field _appendAt:I
        48: aload_1
        49: aload_2
        50: invokevirtual #210                // Method com/fasterxml/jackson/databind/util/TokenBuffer$Segment.append:(ILcom/fasterxml/jackson/core/JsonToken;Ljava/lang/Object;)Lcom/fasterxml/jackson/databind/util/TokenBuffer$Segment;
        53: astore_3
        54: aload_3
        55: ifnonnull     71
        58: aload_0
        59: dup
        60: getfield      #12                 // Field _appendAt:I
        63: iconst_1
        64: iadd
        65: putfield      #12                 // Field _appendAt:I
        68: goto          81
        71: aload_0
        72: aload_3
        73: putfield      #10                 // Field _last:Lcom/fasterxml/jackson/databind/util/TokenBuffer$Segment;
        76: aload_0
        77: iconst_1
        78: putfield      #12                 // Field _appendAt:I
        81: return
      LineNumberTable:
        line 1345: 0
        line 1347: 8
        line 1348: 15
        line 1350: 40
        line 1352: 54
        line 1353: 58
        line 1355: 71
        line 1356: 76
        line 1358: 81
      LocalVariableTable:
        Start  Length  Slot  Name   Signature
           37       3     3  next   Lcom/fasterxml/jackson/databind/util/TokenBuffer$Segment;
            0      82     0  this   Lcom/fasterxml/jackson/databind/util/TokenBuffer;
            0      82     1  type   Lcom/fasterxml/jackson/core/JsonToken;
            0      82     2 value   Ljava/lang/Object;
           54      28     3  next   Lcom/fasterxml/jackson/databind/util/TokenBuffer$Segment;
      StackMapTable: number_of_entries = 4
        frame_type = 40 /* same */
        frame_type = 252 /* append */
          offset_delta = 13
          locals = [ class com/fasterxml/jackson/databind/util/TokenBuffer$Segment ]
        frame_type = 16 /* same */
        frame_type = 9 /* same */

  protected final void _appendFieldName(java.lang.Object);
    descriptor: (Ljava/lang/Object;)V
    flags: (0x0014) ACC_PROTECTED, ACC_FINAL
    Code:
      stack=6, locals=3, args_size=2
         0: aload_0
         1: getfield      #2                  // Field _hasNativeId:Z
         4: ifeq          34
         7: aload_0
         8: getfield      #10                 // Field _last:Lcom/fasterxml/jackson/databind/util/TokenBuffer$Segment;
        11: aload_0
        12: getfield      #12                 // Field _appendAt:I
        15: getstatic     #96                 // Field com/fasterxml/jackson/core/JsonToken.FIELD_NAME:Lcom/fasterxml/jackson/core/JsonToken;
        18: aload_1
        19: aload_0
        20: getfield      #170                // Field _objectId:Ljava/lang/Object;
        23: aload_0
        24: getfield      #169                // Field _typeId:Ljava/lang/Object;
        27: invokevirtual #209                // Method com/fasterxml/jackson/databind/util/TokenBuffer$Segment.append:(ILcom/fasterxml/jackson/core/JsonToken;Ljava/lang/Object;Ljava/lang/Object;Ljava/lang/Object;)Lcom/fasterxml/jackson/databind/util/TokenBuffer$Segment;
        30: astore_2
        31: goto          50
        34: aload_0
        35: getfield      #10                 // Field _last:Lcom/fasterxml/jackson/databind/util/TokenBuffer$Segment;
        38: aload_0
        39: getfield      #12                 // Field _appendAt:I
        42: getstatic     #96                 // Field com/fasterxml/jackson/core/JsonToken.FIELD_NAME:Lcom/fasterxml/jackson/core/JsonToken;
        45: aload_1
        46: invokevirtual #210                // Method com/fasterxml/jackson/databind/util/TokenBuffer$Segment.append:(ILcom/fasterxml/jackson/core/JsonToken;Ljava/lang/Object;)Lcom/fasterxml/jackson/databind/util/TokenBuffer$Segment;
        49: astore_2
        50: aload_2
        51: ifnonnull     67
        54: aload_0
        55: dup
        56: getfield      #12                 // Field _appendAt:I
        59: iconst_1
        60: iadd
        61: putfield      #12                 // Field _appendAt:I
        64: goto          77
        67: aload_0
        68: aload_2
        69: putfield      #10                 // Field _last:Lcom/fasterxml/jackson/databind/util/TokenBuffer$Segment;
        72: aload_0
        73: iconst_1
        74: putfield      #12                 // Field _appendAt:I
        77: return
      LineNumberTable:
        line 1370: 0
        line 1371: 7
        line 1373: 34
        line 1375: 50
        line 1376: 54
        line 1378: 67
        line 1379: 72
        line 1381: 77
      LocalVariableTable:
        Start  Length  Slot  Name   Signature
           31       3     2  next   Lcom/fasterxml/jackson/databind/util/TokenBuffer$Segment;
            0      78     0  this   Lcom/fasterxml/jackson/databind/util/TokenBuffer;
            0      78     1 value   Ljava/lang/Object;
           50      28     2  next   Lcom/fasterxml/jackson/databind/util/TokenBuffer$Segment;
      StackMapTable: number_of_entries = 4
        frame_type = 34 /* same */
        frame_type = 252 /* append */
          offset_delta = 15
          locals = [ class com/fasterxml/jackson/databind/util/TokenBuffer$Segment ]
        frame_type = 16 /* same */
        frame_type = 9 /* same */

  protected final void _appendStartMarker(com.fasterxml.jackson.core.JsonToken);
    descriptor: (Lcom/fasterxml/jackson/core/JsonToken;)V
    flags: (0x0014) ACC_PROTECTED, ACC_FINAL
    Code:
      stack=5, locals=3, args_size=2
         0: aload_0
         1: getfield      #2                  // Field _hasNativeId:Z
         4: ifeq          31
         7: aload_0
         8: getfield      #10                 // Field _last:Lcom/fasterxml/jackson/databind/util/TokenBuffer$Segment;
        11: aload_0
        12: getfield      #12                 // Field _appendAt:I
        15: aload_1
        16: aload_0
        17: getfield      #170                // Field _objectId:Ljava/lang/Object;
        20: aload_0
        21: getfield      #169                // Field _typeId:Ljava/lang/Object;
        24: invokevirtual #207                // Method com/fasterxml/jackson/databind/util/TokenBuffer$Segment.append:(ILcom/fasterxml/jackson/core/JsonToken;Ljava/lang/Object;Ljava/lang/Object;)Lcom/fasterxml/jackson/databind/util/TokenBuffer$Segment;
        27: astore_2
        28: goto          44
        31: aload_0
        32: getfield      #10                 // Field _last:Lcom/fasterxml/jackson/databind/util/TokenBuffer$Segment;
        35: aload_0
        36: getfield      #12                 // Field _appendAt:I
        39: aload_1
        40: invokevirtual #208                // Method com/fasterxml/jackson/databind/util/TokenBuffer$Segment.append:(ILcom/fasterxml/jackson/core/JsonToken;)Lcom/fasterxml/jackson/databind/util/TokenBuffer$Segment;
        43: astore_2
        44: aload_2
        45: ifnonnull     61
        48: aload_0
        49: dup
        50: getfield      #12                 // Field _appendAt:I
        53: iconst_1
        54: iadd
        55: putfield      #12                 // Field _appendAt:I
        58: goto          71
        61: aload_0
        62: aload_2
        63: putfield      #10                 // Field _last:Lcom/fasterxml/jackson/databind/util/TokenBuffer$Segment;
        66: aload_0
        67: iconst_1
        68: putfield      #12                 // Field _appendAt:I
        71: return
      LineNumberTable:
        line 1391: 0
        line 1392: 7
        line 1394: 31
        line 1396: 44
        line 1397: 48
        line 1399: 61
        line 1400: 66
        line 1402: 71
      LocalVariableTable:
        Start  Length  Slot  Name   Signature
           28       3     2  next   Lcom/fasterxml/jackson/databind/util/TokenBuffer$Segment;
            0      72     0  this   Lcom/fasterxml/jackson/databind/util/TokenBuffer;
            0      72     1  type   Lcom/fasterxml/jackson/core/JsonToken;
           44      28     2  next   Lcom/fasterxml/jackson/databind/util/TokenBuffer$Segment;
      StackMapTable: number_of_entries = 4
        frame_type = 31 /* same */
        frame_type = 252 /* append */
          offset_delta = 12
          locals = [ class com/fasterxml/jackson/databind/util/TokenBuffer$Segment ]
        frame_type = 16 /* same */
        frame_type = 9 /* same */

  protected final void _appendEndMarker(com.fasterxml.jackson.core.JsonToken);
    descriptor: (Lcom/fasterxml/jackson/core/JsonToken;)V
    flags: (0x0014) ACC_PROTECTED, ACC_FINAL
    Code:
      stack=3, locals=3, args_size=2
         0: aload_0
         1: getfield      #10                 // Field _last:Lcom/fasterxml/jackson/databind/util/TokenBuffer$Segment;
         4: aload_0
         5: getfield      #12                 // Field _appendAt:I
         8: aload_1
         9: invokevirtual #208                // Method com/fasterxml/jackson/databind/util/TokenBuffer$Segment.append:(ILcom/fasterxml/jackson/core/JsonToken;)Lcom/fasterxml/jackson/databind/util/TokenBuffer$Segment;
        12: astore_2
        13: aload_2
        14: ifnonnull     30
        17: aload_0
        18: dup
        19: getfield      #12                 // Field _appendAt:I
        22: iconst_1
        23: iadd
        24: putfield      #12                 // Field _appendAt:I
        27: goto          40
        30: aload_0
        31: aload_2
        32: putfield      #10                 // Field _last:Lcom/fasterxml/jackson/databind/util/TokenBuffer$Segment;
        35: aload_0
        36: iconst_1
        37: putfield      #12                 // Field _appendAt:I
        40: return
      LineNumberTable:
        line 1412: 0
        line 1413: 13
        line 1414: 17
        line 1416: 30
        line 1417: 35
        line 1419: 40
      LocalVariableTable:
        Start  Length  Slot  Name   Signature
            0      41     0  this   Lcom/fasterxml/jackson/databind/util/TokenBuffer;
            0      41     1  type   Lcom/fasterxml/jackson/core/JsonToken;
           13      28     2  next   Lcom/fasterxml/jackson/databind/util/TokenBuffer$Segment;
      StackMapTable: number_of_entries = 2
        frame_type = 252 /* append */
          offset_delta = 30
          locals = [ class com/fasterxml/jackson/databind/util/TokenBuffer$Segment ]
        frame_type = 9 /* same */

  protected void _reportUnsupportedOperation();
    descriptor: ()V
    flags: (0x0004) ACC_PROTECTED
    Code:
      stack=3, locals=1, args_size=1
         0: new           #167                // class java/lang/UnsupportedOperationException
         3: dup
         4: ldc           #211                // String Called operation not supported for TokenBuffer
         6: invokespecial #212                // Method java/lang/UnsupportedOperationException."<init>":(Ljava/lang/String;)V
         9: athrow
      LineNumberTable:
        line 1423: 0
      LocalVariableTable:
        Start  Length  Slot  Name   Signature
            0      10     0  this   Lcom/fasterxml/jackson/databind/util/TokenBuffer;

  public com.fasterxml.jackson.core.JsonStreamContext getOutputContext();
    descriptor: ()Lcom/fasterxml/jackson/core/JsonStreamContext;
    flags: (0x1041) ACC_PUBLIC, ACC_BRIDGE, ACC_SYNTHETIC
    Code:
      stack=1, locals=1, args_size=1
         0: aload_0
         1: invokevirtual #213                // Method getOutputContext:()Lcom/fasterxml/jackson/core/json/JsonWriteContext;
         4: areturn
      LineNumberTable:
        line 23: 0
      LocalVariableTable:
        Start  Length  Slot  Name   Signature
            0       5     0  this   Lcom/fasterxml/jackson/databind/util/TokenBuffer;

  static {};
    descriptor: ()V
    flags: (0x0008) ACC_STATIC
    Code:
      stack=1, locals=0, args_size=0
         0: invokestatic  #214                // Method com/fasterxml/jackson/core/JsonGenerator$Feature.collectDefaults:()I
         3: putstatic     #4                  // Field DEFAULT_GENERATOR_FEATURES:I
         6: return
      LineNumberTable:
        line 28: 0
}
SourceFile: "TokenBuffer.java"
InnerClasses:
  static #216;                            // class com/fasterxml/jackson/databind/util/TokenBuffer$1
  protected static final #218= #8 of #25; // Segment=class com/fasterxml/jackson/databind/util/TokenBuffer$Segment of class com/fasterxml/jackson/databind/util/TokenBuffer
  protected static final #219= #31 of #25; // Parser=class com/fasterxml/jackson/databind/util/TokenBuffer$Parser of class com/fasterxml/jackson/databind/util/TokenBuffer
  public static final #326= #325 of #215; // Feature=class com/fasterxml/jackson/core/JsonGenerator$Feature of class com/fasterxml/jackson/core/JsonGenerator
  public static final #767= #639 of #478; // NumberType=class com/fasterxml/jackson/core/JsonParser$NumberType of class com/fasterxml/jackson/core/JsonParser
