Classfile /Users/mw/Projects/slang-braindump/.jar/jar8/assemble/slang-braindump/assemble/content/scala/reflect/macros/internal/macroImpl.class
  Last modified May 29, 2022; size 1023 bytes
  SHA-256 checksum 04c8a9d19aace4a2d44544202eec324a7043c24e1dc9bad63a4c8724dab8f19b
  Compiled from "macroImpl.scala"
public final class scala.reflect.macros.internal.macroImpl extends scala.annotation.Annotation implements scala.annotation.StaticAnnotation
  minor version: 0
  major version: 52
  flags: (0x0031) ACC_PUBLIC, ACC_FINAL, ACC_SUPER
  this_class: #2                          // scala/reflect/macros/internal/macroImpl
  super_class: #4                         // scala/annotation/Annotation
  interfaces: 1, fields: 1, methods: 2, attributes: 4
Constant pool:
   #1 = Utf8               scala/reflect/macros/internal/macroImpl
   #2 = Class              #1             // scala/reflect/macros/internal/macroImpl
   #3 = Utf8               scala/annotation/Annotation
   #4 = Class              #3             // scala/annotation/Annotation
   #5 = Utf8               scala/annotation/StaticAnnotation
   #6 = Class              #5             // scala/annotation/StaticAnnotation
   #7 = Utf8               macroImpl.scala
   #8 = Utf8               Lscala/reflect/ScalaSignature;
   #9 = Utf8               bytes
  #10 = Utf8               \u0006\u0005\u00112Q\u0001B\u0003\u0003\u00175A\u0001b\u0006\u0001\u0003\u0006\u0004%\t!\u0007\u0005\t=\u0001\u0011\t\u0011)A\u00055!)q\u0004\u0001C\u0001A\tIQ.Y2s_&k\u0007\u000f\u001c\u0006\u0003\r\u001d\t\u0001\"\u001b8uKJt\u0017\r\u001c\u0006\u0003\u0011%\ta!\\1de>\u001c(B\u0001\u0006\f\u0003\u001d\u0011XM\u001a7fGRT\u0011\u0001D\u0001\u0006g\u000e\fG.Y\n\u0004\u00019!\u0002CA\b\u0013\u001b\u0005\u0001\"BA\t\f\u0003)\tgN\\8uCRLwN\\\u0005\u0003\'A\u0011!\"\u00118o_R\fG/[8o!\tyQ#\u0003\u0002\u0017!\t\u00012\u000b^1uS\u000e\feN\\8uCRLwN\\\u0001\u0015e\u00164WM]3oG\u0016$v.T1de>LU\u000e\u001d7\u0004\u0001U\t!\u0004\u0005\u0002\u001c95\t1\"\u0003\u0002\u001e\u0017\t\u0019\u0011I\\=\u0002+I,g-\u001a:f]\u000e,Gk\\\'bGJ|\u0017*\u001c9mA\u00051A(\u001b8jiz\"\"!I\u0012\u0011\u0005\t\u0002Q\"A\u0003\t\u000b]\u0019\u0001\u0019\u0001\u000e
  #11 = Utf8               referenceToMacroImpl
  #12 = Utf8               Ljava/lang/Object;
  #13 = Utf8               ()Ljava/lang/Object;
  #14 = NameAndType        #11:#12        // referenceToMacroImpl:Ljava/lang/Object;
  #15 = Fieldref           #2.#14         // scala/reflect/macros/internal/macroImpl.referenceToMacroImpl:Ljava/lang/Object;
  #16 = Utf8               this
  #17 = Utf8               Lscala/reflect/macros/internal/macroImpl;
  #18 = Utf8               <init>
  #19 = Utf8               (Ljava/lang/Object;)V
  #20 = Utf8               ()V
  #21 = NameAndType        #18:#20        // "<init>":()V
  #22 = Methodref          #4.#21         // scala/annotation/Annotation."<init>":()V
  #23 = Utf8               Code
  #24 = Utf8               LineNumberTable
  #25 = Utf8               LocalVariableTable
  #26 = Utf8               MethodParameters
  #27 = Utf8               SourceFile
  #28 = Utf8               RuntimeVisibleAnnotations
  #29 = Utf8               ScalaInlineInfo
  #30 = Utf8               ScalaSig
{
  private final java.lang.Object referenceToMacroImpl;
    descriptor: Ljava/lang/Object;
    flags: (0x0012) ACC_PRIVATE, ACC_FINAL

  public java.lang.Object referenceToMacroImpl();
    descriptor: ()Ljava/lang/Object;
    flags: (0x0001) ACC_PUBLIC
    Code:
      stack=1, locals=1, args_size=1
         0: aload_0
         1: getfield      #15                 // Field referenceToMacroImpl:Ljava/lang/Object;
         4: areturn
      LineNumberTable:
        line 30: 0
      LocalVariableTable:
        Start  Length  Slot  Name   Signature
            0       5     0  this   Lscala/reflect/macros/internal/macroImpl;

  public scala.reflect.macros.internal.macroImpl(java.lang.Object);
    descriptor: (Ljava/lang/Object;)V
    flags: (0x0001) ACC_PUBLIC
    Code:
      stack=2, locals=2, args_size=2
         0: aload_0
         1: aload_1
         2: putfield      #15                 // Field referenceToMacroImpl:Ljava/lang/Object;
         5: aload_0
         6: invokespecial #22                 // Method scala/annotation/Annotation."<init>":()V
         9: return
      LineNumberTable:
        line 30: 0
      LocalVariableTable:
        Start  Length  Slot  Name   Signature
            0      10     0  this   Lscala/reflect/macros/internal/macroImpl;
            0      10     1 referenceToMacroImpl   Ljava/lang/Object;
    MethodParameters:
      Name                           Flags
      referenceToMacroImpl           final
}
SourceFile: "macroImpl.scala"
RuntimeVisibleAnnotations:
  0: #8(#9=s#10)
    scala.reflect.ScalaSignature(
      bytes="\u0006\u0005\u00112Q\u0001B\u0003\u0003\u00175A\u0001b\u0006\u0001\u0003\u0006\u0004%\t!\u0007\u0005\t=\u0001\u0011\t\u0011)A\u00055!)q\u0004\u0001C\u0001A\tIQ.Y2s_&k\u0007\u000f\u001c\u0006\u0003\r\u001d\t\u0001\"\u001b8uKJt\u0017\r\u001c\u0006\u0003\u0011%\ta!\\1de>\u001c(B\u0001\u0006\f\u0003\u001d\u0011XM\u001a7fGRT\u0011\u0001D\u0001\u0006g\u000e\fG.Y\n\u0004\u00019!\u0002CA\b\u0013\u001b\u0005\u0001\"BA\t\f\u0003)\tgN\\8uCRLwN\\\u0005\u0003\'A\u0011!\"\u00118o_R\fG/[8o!\tyQ#\u0003\u0002\u0017!\t\u00012\u000b^1uS\u000e\feN\\8uCRLwN\\\u0001\u0015e\u00164WM]3oG\u0016$v.T1de>LU\u000e\u001d7\u0004\u0001U\t!\u0004\u0005\u0002\u001c95\t1\"\u0003\u0002\u001e\u0017\t\u0019\u0011I\\=\u0002+I,g-\u001a:f]\u000e,Gk\\\'bGJ|\u0017*\u001c9mA\u00051A(\u001b8jiz\"\"!I\u0012\u0011\u0005\t\u0002Q\"A\u0003\t\u000b]\u0019\u0001\u0019\u0001\u000e"
    )
  ScalaInlineInfo: length = 0xE (unknown attribute)
   01 01 00 02 00 12 00 13 01 00 0B 00 0D 01
  ScalaSig: length = 0x3 (unknown attribute)
   05 02 00
