Classfile /Users/mw/Projects/slang-braindump/.jar/jar8/assemble/slang-braindump/assemble/content/scala/compat/java8/collectionImpl/package.class
  Last modified May 29, 2022; size 2485 bytes
  SHA-256 checksum 70a873ba7c279bef049a60a655cf22dab954ee98d42a788b8c711daa0f487d4d
  Compiled from "package.scala"
public final class scala.compat.java8.collectionImpl.package
  minor version: 0
  major version: 52
  flags: (0x0031) ACC_PUBLIC, ACC_FINAL, ACC_SUPER
  this_class: #2                          // scala/compat/java8/collectionImpl/package
  super_class: #4                         // java/lang/Object
  interfaces: 0, fields: 0, methods: 9, attributes: 3
Constant pool:
   #1 = Utf8               scala/compat/java8/collectionImpl/package
   #2 = Class              #1             // scala/compat/java8/collectionImpl/package
   #3 = Utf8               java/lang/Object
   #4 = Class              #3             // java/lang/Object
   #5 = Utf8               package.scala
   #6 = Utf8               Lscala/reflect/ScalaSignature;
   #7 = Utf8               bytes
   #8 = Utf8               \u0006\u0005\u0005mr!\u0002\u0010 \u0011\u0003Ac!\u0002\u0016 \u0011\u0003Y\u0003\"\u0002\u0019\u0002\t\u0003\tT\u0001\u0002\u001a\u0002\u0001MBq!R\u0001C\u0002\u0013\u0005a\t\u0003\u0004R\u0003\u0001\u0006IaR\u0003\u0005%\u0006\u00011\u000bC\u0004V\u0003\t\u0007I\u0011\u0001,\t\re\u000b\u0001\u0015!\u0003X\u000b\u0011Q\u0016\u0001A.\t\u000fu\u000b!\u0019!C\u0001=\"1\u0011-\u0001Q\u0001\n}+AAY\u0001\u0001G\"9Q-\u0001b\u0001\n\u00031\u0007BB5\u0002A\u0003%q-\u0002\u0003k\u0003\u0001Y\u0007bB:\u0002\u0005\u0004%\t\u0001\u001e\u0005\u0007s\u0006\u0001\u000b\u0011B;\u0006\ti\f\u0001a\u001f\u0005\n\u0003\u0003\t!\u0019!C\u0001\u0003\u0007A\u0001\"!\u0003\u0002A\u0003%\u0011QA\u0003\u0007\u0003\u0017\t\u0001!!\u0004\t\u0013\u0005E\u0011A1A\u0005\u0002\u0005M\u0001\u0002CA\r\u0003\u0001\u0006I!!\u0006\u0006\r\u0005m\u0011\u0001AA\u000f\u0011%\t\t#\u0001b\u0001\n\u0003\t\u0019\u0003\u0003\u0005\u0002*\u0005\u0001\u000b\u0011BA\u0013\u000b\u0019\tY#\u0001\u0001\u0002.!I\u0011\u0011G\u0001C\u0002\u0013\u0005\u00111\u0007\u0005\t\u0003s\t\u0001\u0015!\u0003\u00026\u00059\u0001/Y2lC\u001e,\'B\u0001\u0011\"\u00039\u0019w\u000e\u001c7fGRLwN\\%na2T!AI\u0012\u0002\u000b)\fg/\u0019\u001d\u000b\u0005\u0011*\u0013AB2p[B\fGOC\u0001\'\u0003\u0015\u00198-\u00197b\u0007\u0001\u0001\"!K\u0001\u000e\u0003}\u0011q\u0001]1dW\u0006<Wm\u0005\u0002\u0002YA\u0011QFL\u0007\u0002K%\u0011q&\n\u0002\u0007\u0003:L(+\u001a4\u0002\rqJg.\u001b;?)\u0005A#aC!dGVlW\u000f\\1u_J,\"\u0001\u000e\u001f\u0011\u0007UB$(D\u00017\u0015\t9T%A\u0002kI.L!!\u000f\u001c\u0003\u001d\u0005s\u00170Q2dk6,H.\u0019;peB\u00111\b\u0010\u0007\u0001\t\u0015i4A1\u0001?\u0005\u0005\t\u0015CA C!\ti\u0003)\u0003\u0002BK\t9aj\u001c;iS:<\u0007CA\u0017D\u0013\t!UEA\u0002B]f\f1\"Q2dk6,H.\u0019;peV\tqI\u0004\u0002I\u001f:\u0011\u0011J\u0014\b\u0003\u00156k\u0011a\u0013\u0006\u0003\u0019\u001e\na\u0001\u0010:p_Rt\u0014\"\u0001\u0014\n\u0005]*\u0013B\u0001)7\u00039\te._!dGVlW\u000f\\1u_J\fA\"Q2dk6,H.\u0019;pe\u0002\u0012a\"\u00138u\u0003\u000e\u001cW/\\;mCR|\'\u000f\u0005\u00026)&\u0011!KN\u0001\u000f\u0013:$\u0018iY2v[Vd\u0017\r^8s+\u00059fB\u0001%Y\u0013\t)f\'A\bJ]R\f5mY;nk2\fGo\u001c:!\u0005=auN\\4BG\u000e,X.\u001e7bi>\u0014\bCA\u001b]\u0013\tQf\'A\bM_:<\u0017iY2v[Vd\u0017\r^8s+\u0005yfB\u0001%a\u0013\tif\'\u0001\tM_:<\u0017iY2v[Vd\u0017\r^8sA\t\tBi\\;cY\u0016\f5mY;nk2\fGo\u001c:\u0011\u0005U\"\u0017B\u000127\u0003E!u.\u001e2mK\u0006\u001b7-^7vY\u0006$xN]\u000b\u0002O:\u0011\u0001\n[\u0005\u0003KZ\n!\u0003R8vE2,\u0017iY2v[Vd\u0017\r^8sA\t91\u000b^3qa\u0016\u0014XC\u00017s!\ri\u0007/]\u0007\u0002]*\u0011q.J\u0001\u000bG>dG.Z2uS>t\u0017B\u00016o!\tY$\u000fB\u0003>\u001f\t\u0007a(A\u0004Ti\u0016\u0004\b/\u001a:\u0016\u0003Ut!A\u001e=\u000f\u0005%;\u0018BA8&\u0013\t\u0019h.\u0001\u0005Ti\u0016\u0004\b/\u001a:!\u0005)\te._*uKB\u0004XM]\u000b\u0003y~\u00042!\\?\u007f\u0013\tQh\u000e\u0005\u0002<\u007f\u0012)QH\u0005b\u0001}\u0005Q\u0011I\\=Ti\u0016\u0004\b/\u001a:\u0016\u0005\u0005\u0015ab\u0001<\u0002\b%\u0019\u0011\u0011\u00018\u0002\u0017\u0005s\u0017p\u0015;faB,\'\u000f\t\u0002\u000b\u0013:$8\u000b^3qa\u0016\u0014\bcA7\u0002\u0010%\u0019\u00111\u00028\u0002\u0015%sGo\u0015;faB,\'/\u0006\u0002\u0002\u00169\u0019a/a\u0006\n\u0007\u0005Ea.A\u0006J]R\u001cF/\u001a9qKJ\u0004#a\u0003\'p]\u001e\u001cF/\u001a9qKJ\u00042!\\A\u0010\u0013\r\tYB\\\u0001\f\u0019>twm\u0015;faB,\'/\u0006\u0002\u0002&9\u0019a/a\n\n\u0007\u0005\u0005b.\u0001\u0007M_:<7\u000b^3qa\u0016\u0014\bEA\u0007E_V\u0014G.Z*uKB\u0004XM\u001d\t\u0004[\u0006=\u0012bAA\u0016]\u0006iAi\\;cY\u0016\u001cF/\u001a9qKJ,\"!!\u000e\u000f\u0007Y\f9$C\u0002\u000229\fa\u0002R8vE2,7\u000b^3qa\u0016\u0014\b\u0005
   #9 = Utf8               DoubleStepper
  #10 = Utf8               ()Lscala/collection/DoubleStepper$;
  #11 = Utf8               scala/compat/java8/collectionImpl/package$
  #12 = Class              #11            // scala/compat/java8/collectionImpl/package$
  #13 = Utf8               MODULE$
  #14 = Utf8               Lscala/compat/java8/collectionImpl/package$;
  #15 = NameAndType        #13:#14        // MODULE$:Lscala/compat/java8/collectionImpl/package$;
  #16 = Fieldref           #12.#15        // scala/compat/java8/collectionImpl/package$.MODULE$:Lscala/compat/java8/collectionImpl/package$;
  #17 = NameAndType        #9:#10         // DoubleStepper:()Lscala/collection/DoubleStepper$;
  #18 = Methodref          #12.#17        // scala/compat/java8/collectionImpl/package$.DoubleStepper:()Lscala/collection/DoubleStepper$;
  #19 = Utf8               LongStepper
  #20 = Utf8               ()Lscala/collection/LongStepper$;
  #21 = NameAndType        #19:#20        // LongStepper:()Lscala/collection/LongStepper$;
  #22 = Methodref          #12.#21        // scala/compat/java8/collectionImpl/package$.LongStepper:()Lscala/collection/LongStepper$;
  #23 = Utf8               IntStepper
  #24 = Utf8               ()Lscala/collection/IntStepper$;
  #25 = NameAndType        #23:#24        // IntStepper:()Lscala/collection/IntStepper$;
  #26 = Methodref          #12.#25        // scala/compat/java8/collectionImpl/package$.IntStepper:()Lscala/collection/IntStepper$;
  #27 = Utf8               AnyStepper
  #28 = Utf8               ()Lscala/collection/AnyStepper$;
  #29 = NameAndType        #27:#28        // AnyStepper:()Lscala/collection/AnyStepper$;
  #30 = Methodref          #12.#29        // scala/compat/java8/collectionImpl/package$.AnyStepper:()Lscala/collection/AnyStepper$;
  #31 = Utf8               Stepper
  #32 = Utf8               ()Lscala/collection/Stepper$;
  #33 = NameAndType        #31:#32        // Stepper:()Lscala/collection/Stepper$;
  #34 = Methodref          #12.#33        // scala/compat/java8/collectionImpl/package$.Stepper:()Lscala/collection/Stepper$;
  #35 = Utf8               DoubleAccumulator
  #36 = Utf8               ()Lscala/jdk/DoubleAccumulator$;
  #37 = NameAndType        #35:#36        // DoubleAccumulator:()Lscala/jdk/DoubleAccumulator$;
  #38 = Methodref          #12.#37        // scala/compat/java8/collectionImpl/package$.DoubleAccumulator:()Lscala/jdk/DoubleAccumulator$;
  #39 = Utf8               LongAccumulator
  #40 = Utf8               ()Lscala/jdk/LongAccumulator$;
  #41 = NameAndType        #39:#40        // LongAccumulator:()Lscala/jdk/LongAccumulator$;
  #42 = Methodref          #12.#41        // scala/compat/java8/collectionImpl/package$.LongAccumulator:()Lscala/jdk/LongAccumulator$;
  #43 = Utf8               IntAccumulator
  #44 = Utf8               ()Lscala/jdk/IntAccumulator$;
  #45 = NameAndType        #43:#44        // IntAccumulator:()Lscala/jdk/IntAccumulator$;
  #46 = Methodref          #12.#45        // scala/compat/java8/collectionImpl/package$.IntAccumulator:()Lscala/jdk/IntAccumulator$;
  #47 = Utf8               Accumulator
  #48 = Utf8               ()Lscala/jdk/AnyAccumulator$;
  #49 = NameAndType        #47:#48        // Accumulator:()Lscala/jdk/AnyAccumulator$;
  #50 = Methodref          #12.#49        // scala/compat/java8/collectionImpl/package$.Accumulator:()Lscala/jdk/AnyAccumulator$;
  #51 = Utf8               Code
  #52 = Utf8               SourceFile
  #53 = Utf8               RuntimeVisibleAnnotations
  #54 = Utf8               ScalaSig
{
  public static scala.collection.DoubleStepper$ DoubleStepper();
    descriptor: ()Lscala/collection/DoubleStepper$;
    flags: (0x0009) ACC_PUBLIC, ACC_STATIC
    Code:
      stack=1, locals=0, args_size=0
         0: getstatic     #16                 // Field scala/compat/java8/collectionImpl/package$.MODULE$:Lscala/compat/java8/collectionImpl/package$;
         3: invokevirtual #18                 // Method scala/compat/java8/collectionImpl/package$.DoubleStepper:()Lscala/collection/DoubleStepper$;
         6: areturn

  public static scala.collection.LongStepper$ LongStepper();
    descriptor: ()Lscala/collection/LongStepper$;
    flags: (0x0009) ACC_PUBLIC, ACC_STATIC
    Code:
      stack=1, locals=0, args_size=0
         0: getstatic     #16                 // Field scala/compat/java8/collectionImpl/package$.MODULE$:Lscala/compat/java8/collectionImpl/package$;
         3: invokevirtual #22                 // Method scala/compat/java8/collectionImpl/package$.LongStepper:()Lscala/collection/LongStepper$;
         6: areturn

  public static scala.collection.IntStepper$ IntStepper();
    descriptor: ()Lscala/collection/IntStepper$;
    flags: (0x0009) ACC_PUBLIC, ACC_STATIC
    Code:
      stack=1, locals=0, args_size=0
         0: getstatic     #16                 // Field scala/compat/java8/collectionImpl/package$.MODULE$:Lscala/compat/java8/collectionImpl/package$;
         3: invokevirtual #26                 // Method scala/compat/java8/collectionImpl/package$.IntStepper:()Lscala/collection/IntStepper$;
         6: areturn

  public static scala.collection.AnyStepper$ AnyStepper();
    descriptor: ()Lscala/collection/AnyStepper$;
    flags: (0x0009) ACC_PUBLIC, ACC_STATIC
    Code:
      stack=1, locals=0, args_size=0
         0: getstatic     #16                 // Field scala/compat/java8/collectionImpl/package$.MODULE$:Lscala/compat/java8/collectionImpl/package$;
         3: invokevirtual #30                 // Method scala/compat/java8/collectionImpl/package$.AnyStepper:()Lscala/collection/AnyStepper$;
         6: areturn

  public static scala.collection.Stepper$ Stepper();
    descriptor: ()Lscala/collection/Stepper$;
    flags: (0x0009) ACC_PUBLIC, ACC_STATIC
    Code:
      stack=1, locals=0, args_size=0
         0: getstatic     #16                 // Field scala/compat/java8/collectionImpl/package$.MODULE$:Lscala/compat/java8/collectionImpl/package$;
         3: invokevirtual #34                 // Method scala/compat/java8/collectionImpl/package$.Stepper:()Lscala/collection/Stepper$;
         6: areturn

  public static scala.jdk.DoubleAccumulator$ DoubleAccumulator();
    descriptor: ()Lscala/jdk/DoubleAccumulator$;
    flags: (0x0009) ACC_PUBLIC, ACC_STATIC
    Code:
      stack=1, locals=0, args_size=0
         0: getstatic     #16                 // Field scala/compat/java8/collectionImpl/package$.MODULE$:Lscala/compat/java8/collectionImpl/package$;
         3: invokevirtual #38                 // Method scala/compat/java8/collectionImpl/package$.DoubleAccumulator:()Lscala/jdk/DoubleAccumulator$;
         6: areturn

  public static scala.jdk.LongAccumulator$ LongAccumulator();
    descriptor: ()Lscala/jdk/LongAccumulator$;
    flags: (0x0009) ACC_PUBLIC, ACC_STATIC
    Code:
      stack=1, locals=0, args_size=0
         0: getstatic     #16                 // Field scala/compat/java8/collectionImpl/package$.MODULE$:Lscala/compat/java8/collectionImpl/package$;
         3: invokevirtual #42                 // Method scala/compat/java8/collectionImpl/package$.LongAccumulator:()Lscala/jdk/LongAccumulator$;
         6: areturn

  public static scala.jdk.IntAccumulator$ IntAccumulator();
    descriptor: ()Lscala/jdk/IntAccumulator$;
    flags: (0x0009) ACC_PUBLIC, ACC_STATIC
    Code:
      stack=1, locals=0, args_size=0
         0: getstatic     #16                 // Field scala/compat/java8/collectionImpl/package$.MODULE$:Lscala/compat/java8/collectionImpl/package$;
         3: invokevirtual #46                 // Method scala/compat/java8/collectionImpl/package$.IntAccumulator:()Lscala/jdk/IntAccumulator$;
         6: areturn

  public static scala.jdk.AnyAccumulator$ Accumulator();
    descriptor: ()Lscala/jdk/AnyAccumulator$;
    flags: (0x0009) ACC_PUBLIC, ACC_STATIC
    Code:
      stack=1, locals=0, args_size=0
         0: getstatic     #16                 // Field scala/compat/java8/collectionImpl/package$.MODULE$:Lscala/compat/java8/collectionImpl/package$;
         3: invokevirtual #50                 // Method scala/compat/java8/collectionImpl/package$.Accumulator:()Lscala/jdk/AnyAccumulator$;
         6: areturn
}
SourceFile: "package.scala"
RuntimeVisibleAnnotations:
  0: #6(#7=s#8)
    scala.reflect.ScalaSignature(
      bytes="\u0006\u0005\u0005mr!\u0002\u0010 \u0011\u0003Ac!\u0002\u0016 \u0011\u0003Y\u0003\"\u0002\u0019\u0002\t\u0003\tT\u0001\u0002\u001a\u0002\u0001MBq!R\u0001C\u0002\u0013\u0005a\t\u0003\u0004R\u0003\u0001\u0006IaR\u0003\u0005%\u0006\u00011\u000bC\u0004V\u0003\t\u0007I\u0011\u0001,\t\re\u000b\u0001\u0015!\u0003X\u000b\u0011Q\u0016\u0001A.\t\u000fu\u000b!\u0019!C\u0001=\"1\u0011-\u0001Q\u0001\n}+AAY\u0001\u0001G\"9Q-\u0001b\u0001\n\u00031\u0007BB5\u0002A\u0003%q-\u0002\u0003k\u0003\u0001Y\u0007bB:\u0002\u0005\u0004%\t\u0001\u001e\u0005\u0007s\u0006\u0001\u000b\u0011B;\u0006\ti\f\u0001a\u001f\u0005\n\u0003\u0003\t!\u0019!C\u0001\u0003\u0007A\u0001\"!\u0003\u0002A\u0003%\u0011QA\u0003\u0007\u0003\u0017\t\u0001!!\u0004\t\u0013\u0005E\u0011A1A\u0005\u0002\u0005M\u0001\u0002CA\r\u0003\u0001\u0006I!!\u0006\u0006\r\u0005m\u0011\u0001AA\u000f\u0011%\t\t#\u0001b\u0001\n\u0003\t\u0019\u0003\u0003\u0005\u0002*\u0005\u0001\u000b\u0011BA\u0013\u000b\u0019\tY#\u0001\u0001\u0002.!I\u0011\u0011G\u0001C\u0002\u0013\u0005\u00111\u0007\u0005\t\u0003s\t\u0001\u0015!\u0003\u00026\u00059\u0001/Y2lC\u001e,\'B\u0001\u0011\"\u00039\u0019w\u000e\u001c7fGRLwN\\%na2T!AI\u0012\u0002\u000b)\fg/\u0019\u001d\u000b\u0005\u0011*\u0013AB2p[B\fGOC\u0001\'\u0003\u0015\u00198-\u00197b\u0007\u0001\u0001\"!K\u0001\u000e\u0003}\u0011q\u0001]1dW\u0006<Wm\u0005\u0002\u0002YA\u0011QFL\u0007\u0002K%\u0011q&\n\u0002\u0007\u0003:L(+\u001a4\u0002\rqJg.\u001b;?)\u0005A#aC!dGVlW\u000f\\1u_J,\"\u0001\u000e\u001f\u0011\u0007UB$(D\u00017\u0015\t9T%A\u0002kI.L!!\u000f\u001c\u0003\u001d\u0005s\u00170Q2dk6,H.\u0019;peB\u00111\b\u0010\u0007\u0001\t\u0015i4A1\u0001?\u0005\u0005\t\u0015CA C!\ti\u0003)\u0003\u0002BK\t9aj\u001c;iS:<\u0007CA\u0017D\u0013\t!UEA\u0002B]f\f1\"Q2dk6,H.\u0019;peV\tqI\u0004\u0002I\u001f:\u0011\u0011J\u0014\b\u0003\u00156k\u0011a\u0013\u0006\u0003\u0019\u001e\na\u0001\u0010:p_Rt\u0014\"\u0001\u0014\n\u0005]*\u0013B\u0001)7\u00039\te._!dGVlW\u000f\\1u_J\fA\"Q2dk6,H.\u0019;pe\u0002\u0012a\"\u00138u\u0003\u000e\u001cW/\\;mCR|\'\u000f\u0005\u00026)&\u0011!KN\u0001\u000f\u0013:$\u0018iY2v[Vd\u0017\r^8s+\u00059fB\u0001%Y\u0013\t)f\'A\bJ]R\f5mY;nk2\fGo\u001c:!\u0005=auN\\4BG\u000e,X.\u001e7bi>\u0014\bCA\u001b]\u0013\tQf\'A\bM_:<\u0017iY2v[Vd\u0017\r^8s+\u0005yfB\u0001%a\u0013\tif\'\u0001\tM_:<\u0017iY2v[Vd\u0017\r^8sA\t\tBi\\;cY\u0016\f5mY;nk2\fGo\u001c:\u0011\u0005U\"\u0017B\u000127\u0003E!u.\u001e2mK\u0006\u001b7-^7vY\u0006$xN]\u000b\u0002O:\u0011\u0001\n[\u0005\u0003KZ\n!\u0003R8vE2,\u0017iY2v[Vd\u0017\r^8sA\t91\u000b^3qa\u0016\u0014XC\u00017s!\ri\u0007/]\u0007\u0002]*\u0011q.J\u0001\u000bG>dG.Z2uS>t\u0017B\u00016o!\tY$\u000fB\u0003>\u001f\t\u0007a(A\u0004Ti\u0016\u0004\b/\u001a:\u0016\u0003Ut!A\u001e=\u000f\u0005%;\u0018BA8&\u0013\t\u0019h.\u0001\u0005Ti\u0016\u0004\b/\u001a:!\u0005)\te._*uKB\u0004XM]\u000b\u0003y~\u00042!\\?\u007f\u0013\tQh\u000e\u0005\u0002<\u007f\u0012)QH\u0005b\u0001}\u0005Q\u0011I\\=Ti\u0016\u0004\b/\u001a:\u0016\u0005\u0005\u0015ab\u0001<\u0002\b%\u0019\u0011\u0011\u00018\u0002\u0017\u0005s\u0017p\u0015;faB,\'\u000f\t\u0002\u000b\u0013:$8\u000b^3qa\u0016\u0014\bcA7\u0002\u0010%\u0019\u00111\u00028\u0002\u0015%sGo\u0015;faB,\'/\u0006\u0002\u0002\u00169\u0019a/a\u0006\n\u0007\u0005Ea.A\u0006J]R\u001cF/\u001a9qKJ\u0004#a\u0003\'p]\u001e\u001cF/\u001a9qKJ\u00042!\\A\u0010\u0013\r\tYB\\\u0001\f\u0019>twm\u0015;faB,\'/\u0006\u0002\u0002&9\u0019a/a\n\n\u0007\u0005\u0005b.\u0001\u0007M_:<7\u000b^3qa\u0016\u0014\bEA\u0007E_V\u0014G.Z*uKB\u0004XM\u001d\t\u0004[\u0006=\u0012bAA\u0016]\u0006iAi\\;cY\u0016\u001cF/\u001a9qKJ,\"!!\u000e\u000f\u0007Y\f9$C\u0002\u000229\fa\u0002R8vE2,7\u000b^3qa\u0016\u0014\b\u0005"
    )
  ScalaSig: length = 0x3 (unknown attribute)
   05 02 00
