Classfile /Users/mw/Projects/slang-braindump/.jar/jar8/assemble/slang-braindump/assemble/content/org/antlr/runtime/tree/BufferedTreeNodeStream.class
  Last modified May 29, 2022; size 8282 bytes
  SHA-256 checksum ab81d33b825a533539b1c8ae23e4987e45fd034fe00ddabe4926e9538a3a2e09
  Compiled from "BufferedTreeNodeStream.java"
public class org.antlr.runtime.tree.BufferedTreeNodeStream implements org.antlr.runtime.tree.TreeNodeStream
  minor version: 0
  major version: 49
  flags: (0x0021) ACC_PUBLIC, ACC_SUPER
  this_class: #71                         // org/antlr/runtime/tree/BufferedTreeNodeStream
  super_class: #72                        // java/lang/Object
  interfaces: 1, fields: 13, methods: 36, attributes: 2
Constant pool:
    #1 = Class              #187          // org/antlr/runtime/tree/CommonTreeAdaptor
    #2 = Methodref          #1.#188       // org/antlr/runtime/tree/CommonTreeAdaptor."<init>":()V
    #3 = Methodref          #71.#189      // org/antlr/runtime/tree/BufferedTreeNodeStream."<init>":(Lorg/antlr/runtime/tree/TreeAdaptor;Ljava/lang/Object;)V
    #4 = Methodref          #71.#190      // org/antlr/runtime/tree/BufferedTreeNodeStream."<init>":(Lorg/antlr/runtime/tree/TreeAdaptor;Ljava/lang/Object;I)V
    #5 = Methodref          #72.#188      // java/lang/Object."<init>":()V
    #6 = Fieldref           #71.#191      // org/antlr/runtime/tree/BufferedTreeNodeStream.uniqueNavigationNodes:Z
    #7 = Fieldref           #71.#192      // org/antlr/runtime/tree/BufferedTreeNodeStream.p:I
    #8 = Fieldref           #71.#193      // org/antlr/runtime/tree/BufferedTreeNodeStream.root:Ljava/lang/Object;
    #9 = Fieldref           #71.#194      // org/antlr/runtime/tree/BufferedTreeNodeStream.adaptor:Lorg/antlr/runtime/tree/TreeAdaptor;
   #10 = Class              #195          // java/util/ArrayList
   #11 = Methodref          #10.#196      // java/util/ArrayList."<init>":(I)V
   #12 = Fieldref           #71.#197      // org/antlr/runtime/tree/BufferedTreeNodeStream.nodes:Ljava/util/List;
   #13 = String             #198          // DOWN
   #14 = InterfaceMethodref #199.#200     // org/antlr/runtime/tree/TreeAdaptor.create:(ILjava/lang/String;)Ljava/lang/Object;
   #15 = Fieldref           #71.#201      // org/antlr/runtime/tree/BufferedTreeNodeStream.down:Ljava/lang/Object;
   #16 = String             #202          // UP
   #17 = Fieldref           #71.#203      // org/antlr/runtime/tree/BufferedTreeNodeStream.up:Ljava/lang/Object;
   #18 = String             #204          // EOF
   #19 = Fieldref           #71.#205      // org/antlr/runtime/tree/BufferedTreeNodeStream.eof:Ljava/lang/Object;
   #20 = Methodref          #71.#206      // org/antlr/runtime/tree/BufferedTreeNodeStream.fillBuffer:(Ljava/lang/Object;)V
   #21 = InterfaceMethodref #199.#207     // org/antlr/runtime/tree/TreeAdaptor.isNil:(Ljava/lang/Object;)Z
   #22 = InterfaceMethodref #208.#209     // java/util/List.add:(Ljava/lang/Object;)Z
   #23 = InterfaceMethodref #199.#210     // org/antlr/runtime/tree/TreeAdaptor.getChildCount:(Ljava/lang/Object;)I
   #24 = Methodref          #71.#211      // org/antlr/runtime/tree/BufferedTreeNodeStream.addNavigationNode:(I)V
   #25 = InterfaceMethodref #199.#212     // org/antlr/runtime/tree/TreeAdaptor.getChild:(Ljava/lang/Object;I)Ljava/lang/Object;
   #26 = Methodref          #71.#213      // org/antlr/runtime/tree/BufferedTreeNodeStream.fillBuffer:()V
   #27 = InterfaceMethodref #208.#214     // java/util/List.size:()I
   #28 = InterfaceMethodref #208.#215     // java/util/List.get:(I)Ljava/lang/Object;
   #29 = Methodref          #71.#216      // org/antlr/runtime/tree/BufferedTreeNodeStream.hasUniqueNavigationNodes:()Z
   #30 = Methodref          #71.#217      // org/antlr/runtime/tree/BufferedTreeNodeStream.LB:(I)Ljava/lang/Object;
   #31 = Methodref          #71.#218      // org/antlr/runtime/tree/BufferedTreeNodeStream.LT:(I)Ljava/lang/Object;
   #32 = Methodref          #71.#219      // org/antlr/runtime/tree/BufferedTreeNodeStream.getTokenStream:()Lorg/antlr/runtime/TokenStream;
   #33 = InterfaceMethodref #220.#221     // org/antlr/runtime/TokenStream.getSourceName:()Ljava/lang/String;
   #34 = Fieldref           #71.#222      // org/antlr/runtime/tree/BufferedTreeNodeStream.tokens:Lorg/antlr/runtime/TokenStream;
   #35 = InterfaceMethodref #199.#223     // org/antlr/runtime/tree/TreeAdaptor.getType:(Ljava/lang/Object;)I
   #36 = Methodref          #71.#224      // org/antlr/runtime/tree/BufferedTreeNodeStream.index:()I
   #37 = Fieldref           #71.#225      // org/antlr/runtime/tree/BufferedTreeNodeStream.lastMarker:I
   #38 = Methodref          #71.#226      // org/antlr/runtime/tree/BufferedTreeNodeStream.seek:(I)V
   #39 = Fieldref           #71.#227      // org/antlr/runtime/tree/BufferedTreeNodeStream.calls:Lorg/antlr/runtime/misc/IntArray;
   #40 = Class              #228          // org/antlr/runtime/misc/IntArray
   #41 = Methodref          #40.#188      // org/antlr/runtime/misc/IntArray."<init>":()V
   #42 = Methodref          #40.#229      // org/antlr/runtime/misc/IntArray.push:(I)V
   #43 = Methodref          #40.#230      // org/antlr/runtime/misc/IntArray.pop:()I
   #44 = Methodref          #40.#231      // org/antlr/runtime/misc/IntArray.clear:()V
   #45 = Class              #232          // org/antlr/runtime/tree/BufferedTreeNodeStream$StreamIterator
   #46 = Methodref          #45.#233      // org/antlr/runtime/tree/BufferedTreeNodeStream$StreamIterator."<init>":(Lorg/antlr/runtime/tree/BufferedTreeNodeStream;)V
   #47 = InterfaceMethodref #199.#234     // org/antlr/runtime/tree/TreeAdaptor.replaceChildren:(Ljava/lang/Object;IILjava/lang/Object;)V
   #48 = Class              #235          // java/lang/StringBuilder
   #49 = Methodref          #48.#188      // java/lang/StringBuilder."<init>":()V
   #50 = String             #236          //
   #51 = Methodref          #48.#237      // java/lang/StringBuilder.append:(Ljava/lang/String;)Ljava/lang/StringBuilder;
   #52 = Methodref          #48.#238      // java/lang/StringBuilder.append:(I)Ljava/lang/StringBuilder;
   #53 = Methodref          #48.#239      // java/lang/StringBuilder.toString:()Ljava/lang/String;
   #54 = InterfaceMethodref #199.#240     // org/antlr/runtime/tree/TreeAdaptor.getToken:(Ljava/lang/Object;)Lorg/antlr/runtime/Token;
   #55 = Methodref          #48.#241      // java/lang/StringBuilder.append:(Ljava/lang/Object;)Ljava/lang/StringBuilder;
   #56 = Fieldref           #242.#243     // java/lang/System.out:Ljava/io/PrintStream;
   #57 = String             #179          // toString
   #58 = Methodref          #244.#245     // java/io/PrintStream.println:(Ljava/lang/String;)V
   #59 = Class              #246          // org/antlr/runtime/tree/CommonTree
   #60 = String             #247          // toString:
   #61 = Methodref          #59.#248      // org/antlr/runtime/tree/CommonTree.getToken:()Lorg/antlr/runtime/Token;
   #62 = String             #249          // ,
   #63 = Methodref          #244.#250     // java/io/PrintStream.print:(Ljava/lang/String;)V
   #64 = Methodref          #244.#251     // java/io/PrintStream.println:(Ljava/lang/Object;)V
   #65 = InterfaceMethodref #199.#252     // org/antlr/runtime/tree/TreeAdaptor.getTokenStartIndex:(Ljava/lang/Object;)I
   #66 = InterfaceMethodref #199.#253     // org/antlr/runtime/tree/TreeAdaptor.getTokenStopIndex:(Ljava/lang/Object;)I
   #67 = Methodref          #71.#214      // org/antlr/runtime/tree/BufferedTreeNodeStream.size:()I
   #68 = InterfaceMethodref #220.#254     // org/antlr/runtime/TokenStream.toString:(II)Ljava/lang/String;
   #69 = InterfaceMethodref #199.#255     // org/antlr/runtime/tree/TreeAdaptor.getText:(Ljava/lang/Object;)Ljava/lang/String;
   #70 = Methodref          #256.#257     // java/lang/String.valueOf:(I)Ljava/lang/String;
   #71 = Class              #258          // org/antlr/runtime/tree/BufferedTreeNodeStream
   #72 = Class              #259          // java/lang/Object
   #73 = Class              #260          // org/antlr/runtime/tree/TreeNodeStream
   #74 = Utf8               StreamIterator
   #75 = Utf8               InnerClasses
   #76 = Utf8               DEFAULT_INITIAL_BUFFER_SIZE
   #77 = Utf8               I
   #78 = Utf8               ConstantValue
   #79 = Integer            100
   #80 = Utf8               INITIAL_CALL_STACK_SIZE
   #81 = Integer            10
   #82 = Utf8               down
   #83 = Utf8               Ljava/lang/Object;
   #84 = Utf8               up
   #85 = Utf8               eof
   #86 = Utf8               nodes
   #87 = Utf8               Ljava/util/List;
   #88 = Utf8               Signature
   #89 = Utf8               Ljava/util/List<Ljava/lang/Object;>;
   #90 = Utf8               root
   #91 = Utf8               tokens
   #92 = Utf8               Lorg/antlr/runtime/TokenStream;
   #93 = Utf8               adaptor
   #94 = Utf8               Lorg/antlr/runtime/tree/TreeAdaptor;
   #95 = Utf8               uniqueNavigationNodes
   #96 = Utf8               Z
   #97 = Utf8               p
   #98 = Utf8               lastMarker
   #99 = Utf8               calls
  #100 = Utf8               Lorg/antlr/runtime/misc/IntArray;
  #101 = Utf8               <init>
  #102 = Utf8               (Ljava/lang/Object;)V
  #103 = Utf8               Code
  #104 = Utf8               LineNumberTable
  #105 = Utf8               LocalVariableTable
  #106 = Utf8               this
  #107 = Utf8               Lorg/antlr/runtime/tree/BufferedTreeNodeStream;
  #108 = Utf8               tree
  #109 = Utf8               (Lorg/antlr/runtime/tree/TreeAdaptor;Ljava/lang/Object;)V
  #110 = Utf8               (Lorg/antlr/runtime/tree/TreeAdaptor;Ljava/lang/Object;I)V
  #111 = Utf8               initialBufferSize
  #112 = Utf8               fillBuffer
  #113 = Utf8               ()V
  #114 = Utf8               child
  #115 = Utf8               c
  #116 = Utf8               t
  #117 = Utf8               nil
  #118 = Utf8               n
  #119 = Utf8               getNodeIndex
  #120 = Utf8               (Ljava/lang/Object;)I
  #121 = Utf8               i
  #122 = Utf8               node
  #123 = Utf8               addNavigationNode
  #124 = Utf8               (I)V
  #125 = Utf8               navNode
  #126 = Utf8               ttype
  #127 = Utf8               get
  #128 = Utf8               (I)Ljava/lang/Object;
  #129 = Utf8               LT
  #130 = Utf8               k
  #131 = Utf8               getCurrentSymbol
  #132 = Utf8               ()Ljava/lang/Object;
  #133 = Utf8               LB
  #134 = Utf8               getTreeSource
  #135 = Utf8               getSourceName
  #136 = Utf8               ()Ljava/lang/String;
  #137 = Utf8               getTokenStream
  #138 = Utf8               ()Lorg/antlr/runtime/TokenStream;
  #139 = Utf8               setTokenStream
  #140 = Utf8               (Lorg/antlr/runtime/TokenStream;)V
  #141 = Utf8               getTreeAdaptor
  #142 = Utf8               ()Lorg/antlr/runtime/tree/TreeAdaptor;
  #143 = Utf8               setTreeAdaptor
  #144 = Utf8               (Lorg/antlr/runtime/tree/TreeAdaptor;)V
  #145 = Utf8               hasUniqueNavigationNodes
  #146 = Utf8               ()Z
  #147 = Utf8               setUniqueNavigationNodes
  #148 = Utf8               (Z)V
  #149 = Utf8               consume
  #150 = Utf8               LA
  #151 = Utf8               (I)I
  #152 = Utf8               mark
  #153 = Utf8               ()I
  #154 = Utf8               release
  #155 = Utf8               marker
  #156 = Utf8               index
  #157 = Utf8               rewind
  #158 = Utf8               seek
  #159 = Utf8               push
  #160 = Utf8               pop
  #161 = Utf8               ret
  #162 = Utf8               reset
  #163 = Utf8               size
  #164 = Utf8               iterator
  #165 = Utf8               ()Ljava/util/Iterator;
  #166 = Utf8               ()Ljava/util/Iterator<Ljava/lang/Object;>;
  #167 = Utf8               replaceChildren
  #168 = Utf8               (Ljava/lang/Object;IILjava/lang/Object;)V
  #169 = Utf8               parent
  #170 = Utf8               startChildIndex
  #171 = Utf8               stopChildIndex
  #172 = Utf8               toTokenTypeString
  #173 = Utf8               buf
  #174 = Utf8               Ljava/lang/StringBuilder;
  #175 = Utf8               toTokenString
  #176 = Utf8               (II)Ljava/lang/String;
  #177 = Utf8               start
  #178 = Utf8               stop
  #179 = Utf8               toString
  #180 = Utf8               (Ljava/lang/Object;Ljava/lang/Object;)Ljava/lang/String;
  #181 = Utf8               beginTokenIndex
  #182 = Utf8               endTokenIndex
  #183 = Utf8               text
  #184 = Utf8               Ljava/lang/String;
  #185 = Utf8               SourceFile
  #186 = Utf8               BufferedTreeNodeStream.java
  #187 = Utf8               org/antlr/runtime/tree/CommonTreeAdaptor
  #188 = NameAndType        #101:#113     // "<init>":()V
  #189 = NameAndType        #101:#109     // "<init>":(Lorg/antlr/runtime/tree/TreeAdaptor;Ljava/lang/Object;)V
  #190 = NameAndType        #101:#110     // "<init>":(Lorg/antlr/runtime/tree/TreeAdaptor;Ljava/lang/Object;I)V
  #191 = NameAndType        #95:#96       // uniqueNavigationNodes:Z
  #192 = NameAndType        #97:#77       // p:I
  #193 = NameAndType        #90:#83       // root:Ljava/lang/Object;
  #194 = NameAndType        #93:#94       // adaptor:Lorg/antlr/runtime/tree/TreeAdaptor;
  #195 = Utf8               java/util/ArrayList
  #196 = NameAndType        #101:#124     // "<init>":(I)V
  #197 = NameAndType        #86:#87       // nodes:Ljava/util/List;
  #198 = Utf8               DOWN
  #199 = Class              #261          // org/antlr/runtime/tree/TreeAdaptor
  #200 = NameAndType        #262:#263     // create:(ILjava/lang/String;)Ljava/lang/Object;
  #201 = NameAndType        #82:#83       // down:Ljava/lang/Object;
  #202 = Utf8               UP
  #203 = NameAndType        #84:#83       // up:Ljava/lang/Object;
  #204 = Utf8               EOF
  #205 = NameAndType        #85:#83       // eof:Ljava/lang/Object;
  #206 = NameAndType        #112:#102     // fillBuffer:(Ljava/lang/Object;)V
  #207 = NameAndType        #264:#265     // isNil:(Ljava/lang/Object;)Z
  #208 = Class              #266          // java/util/List
  #209 = NameAndType        #267:#265     // add:(Ljava/lang/Object;)Z
  #210 = NameAndType        #268:#120     // getChildCount:(Ljava/lang/Object;)I
  #211 = NameAndType        #123:#124     // addNavigationNode:(I)V
  #212 = NameAndType        #269:#270     // getChild:(Ljava/lang/Object;I)Ljava/lang/Object;
  #213 = NameAndType        #112:#113     // fillBuffer:()V
  #214 = NameAndType        #163:#153     // size:()I
  #215 = NameAndType        #127:#128     // get:(I)Ljava/lang/Object;
  #216 = NameAndType        #145:#146     // hasUniqueNavigationNodes:()Z
  #217 = NameAndType        #133:#128     // LB:(I)Ljava/lang/Object;
  #218 = NameAndType        #129:#128     // LT:(I)Ljava/lang/Object;
  #219 = NameAndType        #137:#138     // getTokenStream:()Lorg/antlr/runtime/TokenStream;
  #220 = Class              #271          // org/antlr/runtime/TokenStream
  #221 = NameAndType        #135:#136     // getSourceName:()Ljava/lang/String;
  #222 = NameAndType        #91:#92       // tokens:Lorg/antlr/runtime/TokenStream;
  #223 = NameAndType        #272:#120     // getType:(Ljava/lang/Object;)I
  #224 = NameAndType        #156:#153     // index:()I
  #225 = NameAndType        #98:#77       // lastMarker:I
  #226 = NameAndType        #158:#124     // seek:(I)V
  #227 = NameAndType        #99:#100      // calls:Lorg/antlr/runtime/misc/IntArray;
  #228 = Utf8               org/antlr/runtime/misc/IntArray
  #229 = NameAndType        #159:#124     // push:(I)V
  #230 = NameAndType        #160:#153     // pop:()I
  #231 = NameAndType        #273:#113     // clear:()V
  #232 = Utf8               org/antlr/runtime/tree/BufferedTreeNodeStream$StreamIterator
  #233 = NameAndType        #101:#274     // "<init>":(Lorg/antlr/runtime/tree/BufferedTreeNodeStream;)V
  #234 = NameAndType        #167:#168     // replaceChildren:(Ljava/lang/Object;IILjava/lang/Object;)V
  #235 = Utf8               java/lang/StringBuilder
  #236 = Utf8
  #237 = NameAndType        #275:#276     // append:(Ljava/lang/String;)Ljava/lang/StringBuilder;
  #238 = NameAndType        #275:#277     // append:(I)Ljava/lang/StringBuilder;
  #239 = NameAndType        #179:#136     // toString:()Ljava/lang/String;
  #240 = NameAndType        #278:#279     // getToken:(Ljava/lang/Object;)Lorg/antlr/runtime/Token;
  #241 = NameAndType        #275:#280     // append:(Ljava/lang/Object;)Ljava/lang/StringBuilder;
  #242 = Class              #281          // java/lang/System
  #243 = NameAndType        #282:#283     // out:Ljava/io/PrintStream;
  #244 = Class              #284          // java/io/PrintStream
  #245 = NameAndType        #285:#286     // println:(Ljava/lang/String;)V
  #246 = Utf8               org/antlr/runtime/tree/CommonTree
  #247 = Utf8               toString:
  #248 = NameAndType        #278:#287     // getToken:()Lorg/antlr/runtime/Token;
  #249 = Utf8               ,
  #250 = NameAndType        #288:#286     // print:(Ljava/lang/String;)V
  #251 = NameAndType        #285:#102     // println:(Ljava/lang/Object;)V
  #252 = NameAndType        #289:#120     // getTokenStartIndex:(Ljava/lang/Object;)I
  #253 = NameAndType        #290:#120     // getTokenStopIndex:(Ljava/lang/Object;)I
  #254 = NameAndType        #179:#176     // toString:(II)Ljava/lang/String;
  #255 = NameAndType        #291:#292     // getText:(Ljava/lang/Object;)Ljava/lang/String;
  #256 = Class              #293          // java/lang/String
  #257 = NameAndType        #294:#295     // valueOf:(I)Ljava/lang/String;
  #258 = Utf8               org/antlr/runtime/tree/BufferedTreeNodeStream
  #259 = Utf8               java/lang/Object
  #260 = Utf8               org/antlr/runtime/tree/TreeNodeStream
  #261 = Utf8               org/antlr/runtime/tree/TreeAdaptor
  #262 = Utf8               create
  #263 = Utf8               (ILjava/lang/String;)Ljava/lang/Object;
  #264 = Utf8               isNil
  #265 = Utf8               (Ljava/lang/Object;)Z
  #266 = Utf8               java/util/List
  #267 = Utf8               add
  #268 = Utf8               getChildCount
  #269 = Utf8               getChild
  #270 = Utf8               (Ljava/lang/Object;I)Ljava/lang/Object;
  #271 = Utf8               org/antlr/runtime/TokenStream
  #272 = Utf8               getType
  #273 = Utf8               clear
  #274 = Utf8               (Lorg/antlr/runtime/tree/BufferedTreeNodeStream;)V
  #275 = Utf8               append
  #276 = Utf8               (Ljava/lang/String;)Ljava/lang/StringBuilder;
  #277 = Utf8               (I)Ljava/lang/StringBuilder;
  #278 = Utf8               getToken
  #279 = Utf8               (Ljava/lang/Object;)Lorg/antlr/runtime/Token;
  #280 = Utf8               (Ljava/lang/Object;)Ljava/lang/StringBuilder;
  #281 = Utf8               java/lang/System
  #282 = Utf8               out
  #283 = Utf8               Ljava/io/PrintStream;
  #284 = Utf8               java/io/PrintStream
  #285 = Utf8               println
  #286 = Utf8               (Ljava/lang/String;)V
  #287 = Utf8               ()Lorg/antlr/runtime/Token;
  #288 = Utf8               print
  #289 = Utf8               getTokenStartIndex
  #290 = Utf8               getTokenStopIndex
  #291 = Utf8               getText
  #292 = Utf8               (Ljava/lang/Object;)Ljava/lang/String;
  #293 = Utf8               java/lang/String
  #294 = Utf8               valueOf
  #295 = Utf8               (I)Ljava/lang/String;
{
  public static final int DEFAULT_INITIAL_BUFFER_SIZE;
    descriptor: I
    flags: (0x0019) ACC_PUBLIC, ACC_STATIC, ACC_FINAL
    ConstantValue: int 100

  public static final int INITIAL_CALL_STACK_SIZE;
    descriptor: I
    flags: (0x0019) ACC_PUBLIC, ACC_STATIC, ACC_FINAL
    ConstantValue: int 10

  protected java.lang.Object down;
    descriptor: Ljava/lang/Object;
    flags: (0x0004) ACC_PROTECTED

  protected java.lang.Object up;
    descriptor: Ljava/lang/Object;
    flags: (0x0004) ACC_PROTECTED

  protected java.lang.Object eof;
    descriptor: Ljava/lang/Object;
    flags: (0x0004) ACC_PROTECTED

  protected java.util.List<java.lang.Object> nodes;
    descriptor: Ljava/util/List;
    flags: (0x0004) ACC_PROTECTED
    Signature: #89                          // Ljava/util/List<Ljava/lang/Object;>;

  protected java.lang.Object root;
    descriptor: Ljava/lang/Object;
    flags: (0x0004) ACC_PROTECTED

  protected org.antlr.runtime.TokenStream tokens;
    descriptor: Lorg/antlr/runtime/TokenStream;
    flags: (0x0004) ACC_PROTECTED

  org.antlr.runtime.tree.TreeAdaptor adaptor;
    descriptor: Lorg/antlr/runtime/tree/TreeAdaptor;
    flags: (0x0000)

  protected boolean uniqueNavigationNodes;
    descriptor: Z
    flags: (0x0004) ACC_PROTECTED

  protected int p;
    descriptor: I
    flags: (0x0004) ACC_PROTECTED

  protected int lastMarker;
    descriptor: I
    flags: (0x0004) ACC_PROTECTED

  protected org.antlr.runtime.misc.IntArray calls;
    descriptor: Lorg/antlr/runtime/misc/IntArray;
    flags: (0x0004) ACC_PROTECTED

  public org.antlr.runtime.tree.BufferedTreeNodeStream(java.lang.Object);
    descriptor: (Ljava/lang/Object;)V
    flags: (0x0001) ACC_PUBLIC
    Code:
      stack=3, locals=2, args_size=2
         0: aload_0
         1: new           #1                  // class org/antlr/runtime/tree/CommonTreeAdaptor
         4: dup
         5: invokespecial #2                  // Method org/antlr/runtime/tree/CommonTreeAdaptor."<init>":()V
         8: aload_1
         9: invokespecial #3                  // Method "<init>":(Lorg/antlr/runtime/tree/TreeAdaptor;Ljava/lang/Object;)V
        12: return
      LineNumberTable:
        line 126: 0
        line 127: 12
      LocalVariableTable:
        Start  Length  Slot  Name   Signature
            0      13     0  this   Lorg/antlr/runtime/tree/BufferedTreeNodeStream;
            0      13     1  tree   Ljava/lang/Object;

  public org.antlr.runtime.tree.BufferedTreeNodeStream(org.antlr.runtime.tree.TreeAdaptor, java.lang.Object);
    descriptor: (Lorg/antlr/runtime/tree/TreeAdaptor;Ljava/lang/Object;)V
    flags: (0x0001) ACC_PUBLIC
    Code:
      stack=4, locals=3, args_size=3
         0: aload_0
         1: aload_1
         2: aload_2
         3: bipush        100
         5: invokespecial #4                  // Method "<init>":(Lorg/antlr/runtime/tree/TreeAdaptor;Ljava/lang/Object;I)V
         8: return
      LineNumberTable:
        line 130: 0
        line 131: 8
      LocalVariableTable:
        Start  Length  Slot  Name   Signature
            0       9     0  this   Lorg/antlr/runtime/tree/BufferedTreeNodeStream;
            0       9     1 adaptor   Lorg/antlr/runtime/tree/TreeAdaptor;
            0       9     2  tree   Ljava/lang/Object;

  public org.antlr.runtime.tree.BufferedTreeNodeStream(org.antlr.runtime.tree.TreeAdaptor, java.lang.Object, int);
    descriptor: (Lorg/antlr/runtime/tree/TreeAdaptor;Ljava/lang/Object;I)V
    flags: (0x0001) ACC_PUBLIC
    Code:
      stack=4, locals=4, args_size=4
         0: aload_0
         1: invokespecial #5                  // Method java/lang/Object."<init>":()V
         4: aload_0
         5: iconst_0
         6: putfield      #6                  // Field uniqueNavigationNodes:Z
         9: aload_0
        10: iconst_m1
        11: putfield      #7                  // Field p:I
        14: aload_0
        15: aload_2
        16: putfield      #8                  // Field root:Ljava/lang/Object;
        19: aload_0
        20: aload_1
        21: putfield      #9                  // Field adaptor:Lorg/antlr/runtime/tree/TreeAdaptor;
        24: aload_0
        25: new           #10                 // class java/util/ArrayList
        28: dup
        29: iload_3
        30: invokespecial #11                 // Method java/util/ArrayList."<init>":(I)V
        33: putfield      #12                 // Field nodes:Ljava/util/List;
        36: aload_0
        37: aload_1
        38: iconst_2
        39: ldc           #13                 // String DOWN
        41: invokeinterface #14,  3           // InterfaceMethod org/antlr/runtime/tree/TreeAdaptor.create:(ILjava/lang/String;)Ljava/lang/Object;
        46: putfield      #15                 // Field down:Ljava/lang/Object;
        49: aload_0
        50: aload_1
        51: iconst_3
        52: ldc           #16                 // String UP
        54: invokeinterface #14,  3           // InterfaceMethod org/antlr/runtime/tree/TreeAdaptor.create:(ILjava/lang/String;)Ljava/lang/Object;
        59: putfield      #17                 // Field up:Ljava/lang/Object;
        62: aload_0
        63: aload_1
        64: iconst_m1
        65: ldc           #18                 // String EOF
        67: invokeinterface #14,  3           // InterfaceMethod org/antlr/runtime/tree/TreeAdaptor.create:(ILjava/lang/String;)Ljava/lang/Object;
        72: putfield      #19                 // Field eof:Ljava/lang/Object;
        75: return
      LineNumberTable:
        line 133: 0
        line 112: 4
        line 117: 9
        line 134: 14
        line 135: 19
        line 136: 24
        line 137: 36
        line 138: 49
        line 139: 62
        line 140: 75
      LocalVariableTable:
        Start  Length  Slot  Name   Signature
            0      76     0  this   Lorg/antlr/runtime/tree/BufferedTreeNodeStream;
            0      76     1 adaptor   Lorg/antlr/runtime/tree/TreeAdaptor;
            0      76     2  tree   Ljava/lang/Object;
            0      76     3 initialBufferSize   I

  protected void fillBuffer();
    descriptor: ()V
    flags: (0x0004) ACC_PROTECTED
    Code:
      stack=2, locals=1, args_size=1
         0: aload_0
         1: aload_0
         2: getfield      #8                  // Field root:Ljava/lang/Object;
         5: invokevirtual #20                 // Method fillBuffer:(Ljava/lang/Object;)V
         8: aload_0
         9: iconst_0
        10: putfield      #7                  // Field p:I
        13: return
      LineNumberTable:
        line 146: 0
        line 148: 8
        line 149: 13
      LocalVariableTable:
        Start  Length  Slot  Name   Signature
            0      14     0  this   Lorg/antlr/runtime/tree/BufferedTreeNodeStream;

  public void fillBuffer(java.lang.Object);
    descriptor: (Ljava/lang/Object;)V
    flags: (0x0001) ACC_PUBLIC
    Code:
      stack=3, locals=6, args_size=2
         0: aload_0
         1: getfield      #9                  // Field adaptor:Lorg/antlr/runtime/tree/TreeAdaptor;
         4: aload_1
         5: invokeinterface #21,  2           // InterfaceMethod org/antlr/runtime/tree/TreeAdaptor.isNil:(Ljava/lang/Object;)Z
        10: istore_2
        11: iload_2
        12: ifne          26
        15: aload_0
        16: getfield      #12                 // Field nodes:Ljava/util/List;
        19: aload_1
        20: invokeinterface #22,  2           // InterfaceMethod java/util/List.add:(Ljava/lang/Object;)Z
        25: pop
        26: aload_0
        27: getfield      #9                  // Field adaptor:Lorg/antlr/runtime/tree/TreeAdaptor;
        30: aload_1
        31: invokeinterface #23,  2           // InterfaceMethod org/antlr/runtime/tree/TreeAdaptor.getChildCount:(Ljava/lang/Object;)I
        36: istore_3
        37: iload_2
        38: ifne          50
        41: iload_3
        42: ifle          50
        45: aload_0
        46: iconst_2
        47: invokevirtual #24                 // Method addNavigationNode:(I)V
        50: iconst_0
        51: istore        4
        53: iload         4
        55: iload_3
        56: if_icmpge     85
        59: aload_0
        60: getfield      #9                  // Field adaptor:Lorg/antlr/runtime/tree/TreeAdaptor;
        63: aload_1
        64: iload         4
        66: invokeinterface #25,  3           // InterfaceMethod org/antlr/runtime/tree/TreeAdaptor.getChild:(Ljava/lang/Object;I)Ljava/lang/Object;
        71: astore        5
        73: aload_0
        74: aload         5
        76: invokevirtual #20                 // Method fillBuffer:(Ljava/lang/Object;)V
        79: iinc          4, 1
        82: goto          53
        85: iload_2
        86: ifne          98
        89: iload_3
        90: ifle          98
        93: aload_0
        94: iconst_3
        95: invokevirtual #24                 // Method addNavigationNode:(I)V
        98: return
      LineNumberTable:
        line 152: 0
        line 153: 11
        line 154: 15
        line 157: 26
        line 158: 37
        line 159: 45
        line 162: 50
        line 163: 59
        line 164: 73
        line 162: 79
        line 167: 85
        line 168: 93
        line 170: 98
      LocalVariableTable:
        Start  Length  Slot  Name   Signature
           73       6     5 child   Ljava/lang/Object;
           53      32     4     c   I
            0      99     0  this   Lorg/antlr/runtime/tree/BufferedTreeNodeStream;
            0      99     1     t   Ljava/lang/Object;
           11      88     2   nil   Z
           37      62     3     n   I

  protected int getNodeIndex(java.lang.Object);
    descriptor: (Ljava/lang/Object;)I
    flags: (0x0004) ACC_PROTECTED
    Code:
      stack=2, locals=4, args_size=2
         0: aload_0
         1: getfield      #7                  // Field p:I
         4: iconst_m1
         5: if_icmpne     12
         8: aload_0
         9: invokevirtual #26                 // Method fillBuffer:()V
        12: iconst_0
        13: istore_2
        14: iload_2
        15: aload_0
        16: getfield      #12                 // Field nodes:Ljava/util/List;
        19: invokeinterface #27,  1           // InterfaceMethod java/util/List.size:()I
        24: if_icmpge     51
        27: aload_0
        28: getfield      #12                 // Field nodes:Ljava/util/List;
        31: iload_2
        32: invokeinterface #28,  2           // InterfaceMethod java/util/List.get:(I)Ljava/lang/Object;
        37: astore_3
        38: aload_3
        39: aload_1
        40: if_acmpne     45
        43: iload_2
        44: ireturn
        45: iinc          2, 1
        48: goto          14
        51: iconst_m1
        52: ireturn
      LineNumberTable:
        line 176: 0
        line 177: 8
        line 179: 12
        line 180: 27
        line 181: 38
        line 182: 43
        line 179: 45
        line 185: 51
      LocalVariableTable:
        Start  Length  Slot  Name   Signature
           38       7     3     t   Ljava/lang/Object;
           14      37     2     i   I
            0      53     0  this   Lorg/antlr/runtime/tree/BufferedTreeNodeStream;
            0      53     1  node   Ljava/lang/Object;

  protected void addNavigationNode(int);
    descriptor: (I)V
    flags: (0x0004) ACC_PROTECTED
    Code:
      stack=3, locals=3, args_size=2
         0: iload_1
         1: iconst_2
         2: if_icmpne     36
         5: aload_0
         6: invokevirtual #29                 // Method hasUniqueNavigationNodes:()Z
         9: ifeq          28
        12: aload_0
        13: getfield      #9                  // Field adaptor:Lorg/antlr/runtime/tree/TreeAdaptor;
        16: iconst_2
        17: ldc           #13                 // String DOWN
        19: invokeinterface #14,  3           // InterfaceMethod org/antlr/runtime/tree/TreeAdaptor.create:(ILjava/lang/String;)Ljava/lang/Object;
        24: astore_2
        25: goto          64
        28: aload_0
        29: getfield      #15                 // Field down:Ljava/lang/Object;
        32: astore_2
        33: goto          64
        36: aload_0
        37: invokevirtual #29                 // Method hasUniqueNavigationNodes:()Z
        40: ifeq          59
        43: aload_0
        44: getfield      #9                  // Field adaptor:Lorg/antlr/runtime/tree/TreeAdaptor;
        47: iconst_3
        48: ldc           #16                 // String UP
        50: invokeinterface #14,  3           // InterfaceMethod org/antlr/runtime/tree/TreeAdaptor.create:(ILjava/lang/String;)Ljava/lang/Object;
        55: astore_2
        56: goto          64
        59: aload_0
        60: getfield      #17                 // Field up:Ljava/lang/Object;
        63: astore_2
        64: aload_0
        65: getfield      #12                 // Field nodes:Ljava/util/List;
        68: aload_2
        69: invokeinterface #22,  2           // InterfaceMethod java/util/List.add:(Ljava/lang/Object;)Z
        74: pop
        75: return
      LineNumberTable:
        line 194: 0
        line 195: 5
        line 196: 12
        line 199: 28
        line 203: 36
        line 204: 43
        line 207: 59
        line 210: 64
        line 211: 75
      LocalVariableTable:
        Start  Length  Slot  Name   Signature
           25       3     2 navNode   Ljava/lang/Object;
           33       3     2 navNode   Ljava/lang/Object;
           56       3     2 navNode   Ljava/lang/Object;
            0      76     0  this   Lorg/antlr/runtime/tree/BufferedTreeNodeStream;
            0      76     1 ttype   I
           64      12     2 navNode   Ljava/lang/Object;

  public java.lang.Object get(int);
    descriptor: (I)Ljava/lang/Object;
    flags: (0x0001) ACC_PUBLIC
    Code:
      stack=2, locals=2, args_size=2
         0: aload_0
         1: getfield      #7                  // Field p:I
         4: iconst_m1
         5: if_icmpne     12
         8: aload_0
         9: invokevirtual #26                 // Method fillBuffer:()V
        12: aload_0
        13: getfield      #12                 // Field nodes:Ljava/util/List;
        16: iload_1
        17: invokeinterface #28,  2           // InterfaceMethod java/util/List.get:(I)Ljava/lang/Object;
        22: areturn
      LineNumberTable:
        line 215: 0
        line 216: 8
        line 218: 12
      LocalVariableTable:
        Start  Length  Slot  Name   Signature
            0      23     0  this   Lorg/antlr/runtime/tree/BufferedTreeNodeStream;
            0      23     1     i   I

  public java.lang.Object LT(int);
    descriptor: (I)Ljava/lang/Object;
    flags: (0x0001) ACC_PUBLIC
    Code:
      stack=3, locals=2, args_size=2
         0: aload_0
         1: getfield      #7                  // Field p:I
         4: iconst_m1
         5: if_icmpne     12
         8: aload_0
         9: invokevirtual #26                 // Method fillBuffer:()V
        12: iload_1
        13: ifne          18
        16: aconst_null
        17: areturn
        18: iload_1
        19: ifge          29
        22: aload_0
        23: iload_1
        24: ineg
        25: invokevirtual #30                 // Method LB:(I)Ljava/lang/Object;
        28: areturn
        29: aload_0
        30: getfield      #7                  // Field p:I
        33: iload_1
        34: iadd
        35: iconst_1
        36: isub
        37: aload_0
        38: getfield      #12                 // Field nodes:Ljava/util/List;
        41: invokeinterface #27,  1           // InterfaceMethod java/util/List.size:()I
        46: if_icmplt     54
        49: aload_0
        50: getfield      #19                 // Field eof:Ljava/lang/Object;
        53: areturn
        54: aload_0
        55: getfield      #12                 // Field nodes:Ljava/util/List;
        58: aload_0
        59: getfield      #7                  // Field p:I
        62: iload_1
        63: iadd
        64: iconst_1
        65: isub
        66: invokeinterface #28,  2           // InterfaceMethod java/util/List.get:(I)Ljava/lang/Object;
        71: areturn
      LineNumberTable:
        line 223: 0
        line 224: 8
        line 226: 12
        line 227: 16
        line 229: 18
        line 230: 22
        line 233: 29
        line 234: 49
        line 236: 54
      LocalVariableTable:
        Start  Length  Slot  Name   Signature
            0      72     0  this   Lorg/antlr/runtime/tree/BufferedTreeNodeStream;
            0      72     1     k   I

  public java.lang.Object getCurrentSymbol();
    descriptor: ()Ljava/lang/Object;
    flags: (0x0001) ACC_PUBLIC
    Code:
      stack=2, locals=1, args_size=1
         0: aload_0
         1: iconst_1
         2: invokevirtual #31                 // Method LT:(I)Ljava/lang/Object;
         5: areturn
      LineNumberTable:
        line 239: 0
      LocalVariableTable:
        Start  Length  Slot  Name   Signature
            0       6     0  this   Lorg/antlr/runtime/tree/BufferedTreeNodeStream;

  protected java.lang.Object LB(int);
    descriptor: (I)Ljava/lang/Object;
    flags: (0x0004) ACC_PROTECTED
    Code:
      stack=3, locals=2, args_size=2
         0: iload_1
         1: ifne          6
         4: aconst_null
         5: areturn
         6: aload_0
         7: getfield      #7                  // Field p:I
        10: iload_1
        11: isub
        12: ifge          17
        15: aconst_null
        16: areturn
        17: aload_0
        18: getfield      #12                 // Field nodes:Ljava/util/List;
        21: aload_0
        22: getfield      #7                  // Field p:I
        25: iload_1
        26: isub
        27: invokeinterface #28,  2           // InterfaceMethod java/util/List.get:(I)Ljava/lang/Object;
        32: areturn
      LineNumberTable:
        line 262: 0
        line 263: 4
        line 265: 6
        line 266: 15
        line 268: 17
      LocalVariableTable:
        Start  Length  Slot  Name   Signature
            0      33     0  this   Lorg/antlr/runtime/tree/BufferedTreeNodeStream;
            0      33     1     k   I

  public java.lang.Object getTreeSource();
    descriptor: ()Ljava/lang/Object;
    flags: (0x0001) ACC_PUBLIC
    Code:
      stack=1, locals=1, args_size=1
         0: aload_0
         1: getfield      #8                  // Field root:Ljava/lang/Object;
         4: areturn
      LineNumberTable:
        line 273: 0
      LocalVariableTable:
        Start  Length  Slot  Name   Signature
            0       5     0  this   Lorg/antlr/runtime/tree/BufferedTreeNodeStream;

  public java.lang.String getSourceName();
    descriptor: ()Ljava/lang/String;
    flags: (0x0001) ACC_PUBLIC
    Code:
      stack=1, locals=1, args_size=1
         0: aload_0
         1: invokevirtual #32                 // Method getTokenStream:()Lorg/antlr/runtime/TokenStream;
         4: invokeinterface #33,  1           // InterfaceMethod org/antlr/runtime/TokenStream.getSourceName:()Ljava/lang/String;
         9: areturn
      LineNumberTable:
        line 278: 0
      LocalVariableTable:
        Start  Length  Slot  Name   Signature
            0      10     0  this   Lorg/antlr/runtime/tree/BufferedTreeNodeStream;

  public org.antlr.runtime.TokenStream getTokenStream();
    descriptor: ()Lorg/antlr/runtime/TokenStream;
    flags: (0x0001) ACC_PUBLIC
    Code:
      stack=1, locals=1, args_size=1
         0: aload_0
         1: getfield      #34                 // Field tokens:Lorg/antlr/runtime/TokenStream;
         4: areturn
      LineNumberTable:
        line 283: 0
      LocalVariableTable:
        Start  Length  Slot  Name   Signature
            0       5     0  this   Lorg/antlr/runtime/tree/BufferedTreeNodeStream;

  public void setTokenStream(org.antlr.runtime.TokenStream);
    descriptor: (Lorg/antlr/runtime/TokenStream;)V
    flags: (0x0001) ACC_PUBLIC
    Code:
      stack=2, locals=2, args_size=2
         0: aload_0
         1: aload_1
         2: putfield      #34                 // Field tokens:Lorg/antlr/runtime/TokenStream;
         5: return
      LineNumberTable:
        line 287: 0
        line 288: 5
      LocalVariableTable:
        Start  Length  Slot  Name   Signature
            0       6     0  this   Lorg/antlr/runtime/tree/BufferedTreeNodeStream;
            0       6     1 tokens   Lorg/antlr/runtime/TokenStream;

  public org.antlr.runtime.tree.TreeAdaptor getTreeAdaptor();
    descriptor: ()Lorg/antlr/runtime/tree/TreeAdaptor;
    flags: (0x0001) ACC_PUBLIC
    Code:
      stack=1, locals=1, args_size=1
         0: aload_0
         1: getfield      #9                  // Field adaptor:Lorg/antlr/runtime/tree/TreeAdaptor;
         4: areturn
      LineNumberTable:
        line 292: 0
      LocalVariableTable:
        Start  Length  Slot  Name   Signature
            0       5     0  this   Lorg/antlr/runtime/tree/BufferedTreeNodeStream;

  public void setTreeAdaptor(org.antlr.runtime.tree.TreeAdaptor);
    descriptor: (Lorg/antlr/runtime/tree/TreeAdaptor;)V
    flags: (0x0001) ACC_PUBLIC
    Code:
      stack=2, locals=2, args_size=2
         0: aload_0
         1: aload_1
         2: putfield      #9                  // Field adaptor:Lorg/antlr/runtime/tree/TreeAdaptor;
         5: return
      LineNumberTable:
        line 296: 0
        line 297: 5
      LocalVariableTable:
        Start  Length  Slot  Name   Signature
            0       6     0  this   Lorg/antlr/runtime/tree/BufferedTreeNodeStream;
            0       6     1 adaptor   Lorg/antlr/runtime/tree/TreeAdaptor;

  public boolean hasUniqueNavigationNodes();
    descriptor: ()Z
    flags: (0x0001) ACC_PUBLIC
    Code:
      stack=1, locals=1, args_size=1
         0: aload_0
         1: getfield      #6                  // Field uniqueNavigationNodes:Z
         4: ireturn
      LineNumberTable:
        line 300: 0
      LocalVariableTable:
        Start  Length  Slot  Name   Signature
            0       5     0  this   Lorg/antlr/runtime/tree/BufferedTreeNodeStream;

  public void setUniqueNavigationNodes(boolean);
    descriptor: (Z)V
    flags: (0x0001) ACC_PUBLIC
    Code:
      stack=2, locals=2, args_size=2
         0: aload_0
         1: iload_1
         2: putfield      #6                  // Field uniqueNavigationNodes:Z
         5: return
      LineNumberTable:
        line 305: 0
        line 306: 5
      LocalVariableTable:
        Start  Length  Slot  Name   Signature
            0       6     0  this   Lorg/antlr/runtime/tree/BufferedTreeNodeStream;
            0       6     1 uniqueNavigationNodes   Z

  public void consume();
    descriptor: ()V
    flags: (0x0001) ACC_PUBLIC
    Code:
      stack=3, locals=1, args_size=1
         0: aload_0
         1: getfield      #7                  // Field p:I
         4: iconst_m1
         5: if_icmpne     12
         8: aload_0
         9: invokevirtual #26                 // Method fillBuffer:()V
        12: aload_0
        13: dup
        14: getfield      #7                  // Field p:I
        17: iconst_1
        18: iadd
        19: putfield      #7                  // Field p:I
        22: return
      LineNumberTable:
        line 310: 0
        line 311: 8
        line 313: 12
        line 314: 22
      LocalVariableTable:
        Start  Length  Slot  Name   Signature
            0      23     0  this   Lorg/antlr/runtime/tree/BufferedTreeNodeStream;

  public int LA(int);
    descriptor: (I)I
    flags: (0x0001) ACC_PUBLIC
    Code:
      stack=3, locals=2, args_size=2
         0: aload_0
         1: getfield      #9                  // Field adaptor:Lorg/antlr/runtime/tree/TreeAdaptor;
         4: aload_0
         5: iload_1
         6: invokevirtual #31                 // Method LT:(I)Ljava/lang/Object;
         9: invokeinterface #35,  2           // InterfaceMethod org/antlr/runtime/tree/TreeAdaptor.getType:(Ljava/lang/Object;)I
        14: ireturn
      LineNumberTable:
        line 318: 0
      LocalVariableTable:
        Start  Length  Slot  Name   Signature
            0      15     0  this   Lorg/antlr/runtime/tree/BufferedTreeNodeStream;
            0      15     1     i   I

  public int mark();
    descriptor: ()I
    flags: (0x0001) ACC_PUBLIC
    Code:
      stack=2, locals=1, args_size=1
         0: aload_0
         1: getfield      #7                  // Field p:I
         4: iconst_m1
         5: if_icmpne     12
         8: aload_0
         9: invokevirtual #26                 // Method fillBuffer:()V
        12: aload_0
        13: aload_0
        14: invokevirtual #36                 // Method index:()I
        17: putfield      #37                 // Field lastMarker:I
        20: aload_0
        21: getfield      #37                 // Field lastMarker:I
        24: ireturn
      LineNumberTable:
        line 323: 0
        line 324: 8
        line 326: 12
        line 327: 20
      LocalVariableTable:
        Start  Length  Slot  Name   Signature
            0      25     0  this   Lorg/antlr/runtime/tree/BufferedTreeNodeStream;

  public void release(int);
    descriptor: (I)V
    flags: (0x0001) ACC_PUBLIC
    Code:
      stack=0, locals=2, args_size=2
         0: return
      LineNumberTable:
        line 333: 0
      LocalVariableTable:
        Start  Length  Slot  Name   Signature
            0       1     0  this   Lorg/antlr/runtime/tree/BufferedTreeNodeStream;
            0       1     1 marker   I

  public int index();
    descriptor: ()I
    flags: (0x0001) ACC_PUBLIC
    Code:
      stack=1, locals=1, args_size=1
         0: aload_0
         1: getfield      #7                  // Field p:I
         4: ireturn
      LineNumberTable:
        line 337: 0
      LocalVariableTable:
        Start  Length  Slot  Name   Signature
            0       5     0  this   Lorg/antlr/runtime/tree/BufferedTreeNodeStream;

  public void rewind(int);
    descriptor: (I)V
    flags: (0x0001) ACC_PUBLIC
    Code:
      stack=2, locals=2, args_size=2
         0: aload_0
         1: iload_1
         2: invokevirtual #38                 // Method seek:(I)V
         5: return
      LineNumberTable:
        line 342: 0
        line 343: 5
      LocalVariableTable:
        Start  Length  Slot  Name   Signature
            0       6     0  this   Lorg/antlr/runtime/tree/BufferedTreeNodeStream;
            0       6     1 marker   I

  public void rewind();
    descriptor: ()V
    flags: (0x0001) ACC_PUBLIC
    Code:
      stack=2, locals=1, args_size=1
         0: aload_0
         1: aload_0
         2: getfield      #37                 // Field lastMarker:I
         5: invokevirtual #38                 // Method seek:(I)V
         8: return
      LineNumberTable:
        line 347: 0
        line 348: 8
      LocalVariableTable:
        Start  Length  Slot  Name   Signature
            0       9     0  this   Lorg/antlr/runtime/tree/BufferedTreeNodeStream;

  public void seek(int);
    descriptor: (I)V
    flags: (0x0001) ACC_PUBLIC
    Code:
      stack=2, locals=2, args_size=2
         0: aload_0
         1: getfield      #7                  // Field p:I
         4: iconst_m1
         5: if_icmpne     12
         8: aload_0
         9: invokevirtual #26                 // Method fillBuffer:()V
        12: aload_0
        13: iload_1
        14: putfield      #7                  // Field p:I
        17: return
      LineNumberTable:
        line 352: 0
        line 353: 8
        line 355: 12
        line 356: 17
      LocalVariableTable:
        Start  Length  Slot  Name   Signature
            0      18     0  this   Lorg/antlr/runtime/tree/BufferedTreeNodeStream;
            0      18     1 index   I

  public void push(int);
    descriptor: (I)V
    flags: (0x0001) ACC_PUBLIC
    Code:
      stack=3, locals=2, args_size=2
         0: aload_0
         1: getfield      #39                 // Field calls:Lorg/antlr/runtime/misc/IntArray;
         4: ifnonnull     18
         7: aload_0
         8: new           #40                 // class org/antlr/runtime/misc/IntArray
        11: dup
        12: invokespecial #41                 // Method org/antlr/runtime/misc/IntArray."<init>":()V
        15: putfield      #39                 // Field calls:Lorg/antlr/runtime/misc/IntArray;
        18: aload_0
        19: getfield      #39                 // Field calls:Lorg/antlr/runtime/misc/IntArray;
        22: aload_0
        23: getfield      #7                  // Field p:I
        26: invokevirtual #42                 // Method org/antlr/runtime/misc/IntArray.push:(I)V
        29: aload_0
        30: iload_1
        31: invokevirtual #38                 // Method seek:(I)V
        34: return
      LineNumberTable:
        line 362: 0
        line 363: 7
        line 365: 18
        line 366: 29
        line 367: 34
      LocalVariableTable:
        Start  Length  Slot  Name   Signature
            0      35     0  this   Lorg/antlr/runtime/tree/BufferedTreeNodeStream;
            0      35     1 index   I

  public int pop();
    descriptor: ()I
    flags: (0x0001) ACC_PUBLIC
    Code:
      stack=2, locals=2, args_size=1
         0: aload_0
         1: getfield      #39                 // Field calls:Lorg/antlr/runtime/misc/IntArray;
         4: invokevirtual #43                 // Method org/antlr/runtime/misc/IntArray.pop:()I
         7: istore_1
         8: aload_0
         9: iload_1
        10: invokevirtual #38                 // Method seek:(I)V
        13: iload_1
        14: ireturn
      LineNumberTable:
        line 373: 0
        line 374: 8
        line 375: 13
      LocalVariableTable:
        Start  Length  Slot  Name   Signature
            0      15     0  this   Lorg/antlr/runtime/tree/BufferedTreeNodeStream;
            8       7     1   ret   I

  public void reset();
    descriptor: ()V
    flags: (0x0001) ACC_PUBLIC
    Code:
      stack=2, locals=1, args_size=1
         0: aload_0
         1: iconst_0
         2: putfield      #7                  // Field p:I
         5: aload_0
         6: iconst_0
         7: putfield      #37                 // Field lastMarker:I
        10: aload_0
        11: getfield      #39                 // Field calls:Lorg/antlr/runtime/misc/IntArray;
        14: ifnull        24
        17: aload_0
        18: getfield      #39                 // Field calls:Lorg/antlr/runtime/misc/IntArray;
        21: invokevirtual #44                 // Method org/antlr/runtime/misc/IntArray.clear:()V
        24: return
      LineNumberTable:
        line 380: 0
        line 381: 5
        line 382: 10
        line 383: 17
        line 385: 24
      LocalVariableTable:
        Start  Length  Slot  Name   Signature
            0      25     0  this   Lorg/antlr/runtime/tree/BufferedTreeNodeStream;

  public int size();
    descriptor: ()I
    flags: (0x0001) ACC_PUBLIC
    Code:
      stack=2, locals=1, args_size=1
         0: aload_0
         1: getfield      #7                  // Field p:I
         4: iconst_m1
         5: if_icmpne     12
         8: aload_0
         9: invokevirtual #26                 // Method fillBuffer:()V
        12: aload_0
        13: getfield      #12                 // Field nodes:Ljava/util/List;
        16: invokeinterface #27,  1           // InterfaceMethod java/util/List.size:()I
        21: ireturn
      LineNumberTable:
        line 389: 0
        line 390: 8
        line 392: 12
      LocalVariableTable:
        Start  Length  Slot  Name   Signature
            0      22     0  this   Lorg/antlr/runtime/tree/BufferedTreeNodeStream;

  public java.util.Iterator<java.lang.Object> iterator();
    descriptor: ()Ljava/util/Iterator;
    flags: (0x0001) ACC_PUBLIC
    Code:
      stack=3, locals=1, args_size=1
         0: aload_0
         1: getfield      #7                  // Field p:I
         4: iconst_m1
         5: if_icmpne     12
         8: aload_0
         9: invokevirtual #26                 // Method fillBuffer:()V
        12: new           #45                 // class org/antlr/runtime/tree/BufferedTreeNodeStream$StreamIterator
        15: dup
        16: aload_0
        17: invokespecial #46                 // Method org/antlr/runtime/tree/BufferedTreeNodeStream$StreamIterator."<init>":(Lorg/antlr/runtime/tree/BufferedTreeNodeStream;)V
        20: areturn
      LineNumberTable:
        line 396: 0
        line 397: 8
        line 399: 12
      LocalVariableTable:
        Start  Length  Slot  Name   Signature
            0      21     0  this   Lorg/antlr/runtime/tree/BufferedTreeNodeStream;
    Signature: #166                         // ()Ljava/util/Iterator<Ljava/lang/Object;>;

  public void replaceChildren(java.lang.Object, int, int, java.lang.Object);
    descriptor: (Ljava/lang/Object;IILjava/lang/Object;)V
    flags: (0x0001) ACC_PUBLIC
    Code:
      stack=5, locals=5, args_size=5
         0: aload_1
         1: ifnull        18
         4: aload_0
         5: getfield      #9                  // Field adaptor:Lorg/antlr/runtime/tree/TreeAdaptor;
         8: aload_1
         9: iload_2
        10: iload_3
        11: aload         4
        13: invokeinterface #47,  5           // InterfaceMethod org/antlr/runtime/tree/TreeAdaptor.replaceChildren:(Ljava/lang/Object;IILjava/lang/Object;)V
        18: return
      LineNumberTable:
        line 406: 0
        line 407: 4
        line 409: 18
      LocalVariableTable:
        Start  Length  Slot  Name   Signature
            0      19     0  this   Lorg/antlr/runtime/tree/BufferedTreeNodeStream;
            0      19     1 parent   Ljava/lang/Object;
            0      19     2 startChildIndex   I
            0      19     3 stopChildIndex   I
            0      19     4     t   Ljava/lang/Object;

  public java.lang.String toTokenTypeString();
    descriptor: ()Ljava/lang/String;
    flags: (0x0001) ACC_PUBLIC
    Code:
      stack=3, locals=4, args_size=1
         0: aload_0
         1: getfield      #7                  // Field p:I
         4: iconst_m1
         5: if_icmpne     12
         8: aload_0
         9: invokevirtual #26                 // Method fillBuffer:()V
        12: new           #48                 // class java/lang/StringBuilder
        15: dup
        16: invokespecial #49                 // Method java/lang/StringBuilder."<init>":()V
        19: astore_1
        20: iconst_0
        21: istore_2
        22: iload_2
        23: aload_0
        24: getfield      #12                 // Field nodes:Ljava/util/List;
        27: invokeinterface #27,  1           // InterfaceMethod java/util/List.size:()I
        32: if_icmpge     74
        35: aload_0
        36: getfield      #12                 // Field nodes:Ljava/util/List;
        39: iload_2
        40: invokeinterface #28,  2           // InterfaceMethod java/util/List.get:(I)Ljava/lang/Object;
        45: astore_3
        46: aload_1
        47: ldc           #50                 // String
        49: invokevirtual #51                 // Method java/lang/StringBuilder.append:(Ljava/lang/String;)Ljava/lang/StringBuilder;
        52: pop
        53: aload_1
        54: aload_0
        55: getfield      #9                  // Field adaptor:Lorg/antlr/runtime/tree/TreeAdaptor;
        58: aload_3
        59: invokeinterface #35,  2           // InterfaceMethod org/antlr/runtime/tree/TreeAdaptor.getType:(Ljava/lang/Object;)I
        64: invokevirtual #52                 // Method java/lang/StringBuilder.append:(I)Ljava/lang/StringBuilder;
        67: pop
        68: iinc          2, 1
        71: goto          22
        74: aload_1
        75: invokevirtual #53                 // Method java/lang/StringBuilder.toString:()Ljava/lang/String;
        78: areturn
      LineNumberTable:
        line 413: 0
        line 414: 8
        line 416: 12
        line 417: 20
        line 418: 35
        line 419: 46
        line 420: 53
        line 417: 68
        line 422: 74
      LocalVariableTable:
        Start  Length  Slot  Name   Signature
           46      22     3     t   Ljava/lang/Object;
           22      52     2     i   I
            0      79     0  this   Lorg/antlr/runtime/tree/BufferedTreeNodeStream;
           20      59     1   buf   Ljava/lang/StringBuilder;

  public java.lang.String toTokenString(int, int);
    descriptor: (II)Ljava/lang/String;
    flags: (0x0001) ACC_PUBLIC
    Code:
      stack=3, locals=6, args_size=3
         0: aload_0
         1: getfield      #7                  // Field p:I
         4: iconst_m1
         5: if_icmpne     12
         8: aload_0
         9: invokevirtual #26                 // Method fillBuffer:()V
        12: new           #48                 // class java/lang/StringBuilder
        15: dup
        16: invokespecial #49                 // Method java/lang/StringBuilder."<init>":()V
        19: astore_3
        20: iload_1
        21: istore        4
        23: iload         4
        25: aload_0
        26: getfield      #12                 // Field nodes:Ljava/util/List;
        29: invokeinterface #27,  1           // InterfaceMethod java/util/List.size:()I
        34: if_icmpge     85
        37: iload         4
        39: iload_2
        40: if_icmpgt     85
        43: aload_0
        44: getfield      #12                 // Field nodes:Ljava/util/List;
        47: iload         4
        49: invokeinterface #28,  2           // InterfaceMethod java/util/List.get:(I)Ljava/lang/Object;
        54: astore        5
        56: aload_3
        57: ldc           #50                 // String
        59: invokevirtual #51                 // Method java/lang/StringBuilder.append:(Ljava/lang/String;)Ljava/lang/StringBuilder;
        62: pop
        63: aload_3
        64: aload_0
        65: getfield      #9                  // Field adaptor:Lorg/antlr/runtime/tree/TreeAdaptor;
        68: aload         5
        70: invokeinterface #54,  2           // InterfaceMethod org/antlr/runtime/tree/TreeAdaptor.getToken:(Ljava/lang/Object;)Lorg/antlr/runtime/Token;
        75: invokevirtual #55                 // Method java/lang/StringBuilder.append:(Ljava/lang/Object;)Ljava/lang/StringBuilder;
        78: pop
        79: iinc          4, 1
        82: goto          23
        85: aload_3
        86: invokevirtual #53                 // Method java/lang/StringBuilder.toString:()Ljava/lang/String;
        89: areturn
      LineNumberTable:
        line 427: 0
        line 428: 8
        line 430: 12
        line 431: 20
        line 432: 43
        line 433: 56
        line 434: 63
        line 431: 79
        line 436: 85
      LocalVariableTable:
        Start  Length  Slot  Name   Signature
           56      23     5     t   Ljava/lang/Object;
           23      62     4     i   I
            0      90     0  this   Lorg/antlr/runtime/tree/BufferedTreeNodeStream;
            0      90     1 start   I
            0      90     2  stop   I
           20      70     3   buf   Ljava/lang/StringBuilder;

  public java.lang.String toString(java.lang.Object, java.lang.Object);
    descriptor: (Ljava/lang/Object;Ljava/lang/Object;)Ljava/lang/String;
    flags: (0x0001) ACC_PUBLIC
    Code:
      stack=3, locals=7, args_size=3
         0: getstatic     #56                 // Field java/lang/System.out:Ljava/io/PrintStream;
         3: ldc           #57                 // String toString
         5: invokevirtual #58                 // Method java/io/PrintStream.println:(Ljava/lang/String;)V
         8: aload_1
         9: ifnull        16
        12: aload_2
        13: ifnonnull     18
        16: aconst_null
        17: areturn
        18: aload_0
        19: getfield      #7                  // Field p:I
        22: iconst_m1
        23: if_icmpne     30
        26: aload_0
        27: invokevirtual #26                 // Method fillBuffer:()V
        30: aload_1
        31: instanceof    #59                 // class org/antlr/runtime/tree/CommonTree
        34: ifeq          76
        37: getstatic     #56                 // Field java/lang/System.out:Ljava/io/PrintStream;
        40: new           #48                 // class java/lang/StringBuilder
        43: dup
        44: invokespecial #49                 // Method java/lang/StringBuilder."<init>":()V
        47: ldc           #60                 // String toString:
        49: invokevirtual #51                 // Method java/lang/StringBuilder.append:(Ljava/lang/String;)Ljava/lang/StringBuilder;
        52: aload_1
        53: checkcast     #59                 // class org/antlr/runtime/tree/CommonTree
        56: invokevirtual #61                 // Method org/antlr/runtime/tree/CommonTree.getToken:()Lorg/antlr/runtime/Token;
        59: invokevirtual #55                 // Method java/lang/StringBuilder.append:(Ljava/lang/Object;)Ljava/lang/StringBuilder;
        62: ldc           #62                 // String ,
        64: invokevirtual #51                 // Method java/lang/StringBuilder.append:(Ljava/lang/String;)Ljava/lang/StringBuilder;
        67: invokevirtual #53                 // Method java/lang/StringBuilder.toString:()Ljava/lang/String;
        70: invokevirtual #63                 // Method java/io/PrintStream.print:(Ljava/lang/String;)V
        73: goto          83
        76: getstatic     #56                 // Field java/lang/System.out:Ljava/io/PrintStream;
        79: aload_1
        80: invokevirtual #64                 // Method java/io/PrintStream.println:(Ljava/lang/Object;)V
        83: aload_2
        84: instanceof    #59                 // class org/antlr/runtime/tree/CommonTree
        87: ifeq          106
        90: getstatic     #56                 // Field java/lang/System.out:Ljava/io/PrintStream;
        93: aload_2
        94: checkcast     #59                 // class org/antlr/runtime/tree/CommonTree
        97: invokevirtual #61                 // Method org/antlr/runtime/tree/CommonTree.getToken:()Lorg/antlr/runtime/Token;
       100: invokevirtual #64                 // Method java/io/PrintStream.println:(Ljava/lang/Object;)V
       103: goto          113
       106: getstatic     #56                 // Field java/lang/System.out:Ljava/io/PrintStream;
       109: aload_2
       110: invokevirtual #64                 // Method java/io/PrintStream.println:(Ljava/lang/Object;)V
       113: aload_0
       114: getfield      #34                 // Field tokens:Lorg/antlr/runtime/TokenStream;
       117: ifnull        207
       120: aload_0
       121: getfield      #9                  // Field adaptor:Lorg/antlr/runtime/tree/TreeAdaptor;
       124: aload_1
       125: invokeinterface #65,  2           // InterfaceMethod org/antlr/runtime/tree/TreeAdaptor.getTokenStartIndex:(Ljava/lang/Object;)I
       130: istore_3
       131: aload_0
       132: getfield      #9                  // Field adaptor:Lorg/antlr/runtime/tree/TreeAdaptor;
       135: aload_2
       136: invokeinterface #66,  2           // InterfaceMethod org/antlr/runtime/tree/TreeAdaptor.getTokenStopIndex:(Ljava/lang/Object;)I
       141: istore        4
       143: aload_0
       144: getfield      #9                  // Field adaptor:Lorg/antlr/runtime/tree/TreeAdaptor;
       147: aload_2
       148: invokeinterface #35,  2           // InterfaceMethod org/antlr/runtime/tree/TreeAdaptor.getType:(Ljava/lang/Object;)I
       153: iconst_3
       154: if_icmpne     172
       157: aload_0
       158: getfield      #9                  // Field adaptor:Lorg/antlr/runtime/tree/TreeAdaptor;
       161: aload_1
       162: invokeinterface #66,  2           // InterfaceMethod org/antlr/runtime/tree/TreeAdaptor.getTokenStopIndex:(Ljava/lang/Object;)I
       167: istore        4
       169: goto          194
       172: aload_0
       173: getfield      #9                  // Field adaptor:Lorg/antlr/runtime/tree/TreeAdaptor;
       176: aload_2
       177: invokeinterface #35,  2           // InterfaceMethod org/antlr/runtime/tree/TreeAdaptor.getType:(Ljava/lang/Object;)I
       182: iconst_m1
       183: if_icmpne     194
       186: aload_0
       187: invokevirtual #67                 // Method size:()I
       190: iconst_2
       191: isub
       192: istore        4
       194: aload_0
       195: getfield      #34                 // Field tokens:Lorg/antlr/runtime/TokenStream;
       198: iload_3
       199: iload         4
       201: invokeinterface #68,  3           // InterfaceMethod org/antlr/runtime/TokenStream.toString:(II)Ljava/lang/String;
       206: areturn
       207: iconst_0
       208: istore        4
       210: iload         4
       212: aload_0
       213: getfield      #12                 // Field nodes:Ljava/util/List;
       216: invokeinterface #27,  1           // InterfaceMethod java/util/List.size:()I
       221: if_icmpge     250
       224: aload_0
       225: getfield      #12                 // Field nodes:Ljava/util/List;
       228: iload         4
       230: invokeinterface #28,  2           // InterfaceMethod java/util/List.get:(I)Ljava/lang/Object;
       235: astore_3
       236: aload_3
       237: aload_1
       238: if_acmpne     244
       241: goto          250
       244: iinc          4, 1
       247: goto          210
       250: new           #48                 // class java/lang/StringBuilder
       253: dup
       254: invokespecial #49                 // Method java/lang/StringBuilder."<init>":()V
       257: astore        5
       259: aload_0
       260: getfield      #12                 // Field nodes:Ljava/util/List;
       263: iload         4
       265: invokeinterface #28,  2           // InterfaceMethod java/util/List.get:(I)Ljava/lang/Object;
       270: astore_3
       271: aload_3
       272: aload_2
       273: if_acmpeq     352
       276: aload_0
       277: getfield      #9                  // Field adaptor:Lorg/antlr/runtime/tree/TreeAdaptor;
       280: aload_3
       281: invokeinterface #69,  2           // InterfaceMethod org/antlr/runtime/tree/TreeAdaptor.getText:(Ljava/lang/Object;)Ljava/lang/String;
       286: astore        6
       288: aload         6
       290: ifnonnull     326
       293: new           #48                 // class java/lang/StringBuilder
       296: dup
       297: invokespecial #49                 // Method java/lang/StringBuilder."<init>":()V
       300: ldc           #50                 // String
       302: invokevirtual #51                 // Method java/lang/StringBuilder.append:(Ljava/lang/String;)Ljava/lang/StringBuilder;
       305: aload_0
       306: getfield      #9                  // Field adaptor:Lorg/antlr/runtime/tree/TreeAdaptor;
       309: aload_3
       310: invokeinterface #35,  2           // InterfaceMethod org/antlr/runtime/tree/TreeAdaptor.getType:(Ljava/lang/Object;)I
       315: invokestatic  #70                 // Method java/lang/String.valueOf:(I)Ljava/lang/String;
       318: invokevirtual #51                 // Method java/lang/StringBuilder.append:(Ljava/lang/String;)Ljava/lang/StringBuilder;
       321: invokevirtual #53                 // Method java/lang/StringBuilder.toString:()Ljava/lang/String;
       324: astore        6
       326: aload         5
       328: aload         6
       330: invokevirtual #51                 // Method java/lang/StringBuilder.append:(Ljava/lang/String;)Ljava/lang/StringBuilder;
       333: pop
       334: iinc          4, 1
       337: aload_0
       338: getfield      #12                 // Field nodes:Ljava/util/List;
       341: iload         4
       343: invokeinterface #28,  2           // InterfaceMethod java/util/List.get:(I)Ljava/lang/Object;
       348: astore_3
       349: goto          271
       352: aload_0
       353: getfield      #9                  // Field adaptor:Lorg/antlr/runtime/tree/TreeAdaptor;
       356: aload_2
       357: invokeinterface #69,  2           // InterfaceMethod org/antlr/runtime/tree/TreeAdaptor.getText:(Ljava/lang/Object;)Ljava/lang/String;
       362: astore        6
       364: aload         6
       366: ifnonnull     402
       369: new           #48                 // class java/lang/StringBuilder
       372: dup
       373: invokespecial #49                 // Method java/lang/StringBuilder."<init>":()V
       376: ldc           #50                 // String
       378: invokevirtual #51                 // Method java/lang/StringBuilder.append:(Ljava/lang/String;)Ljava/lang/StringBuilder;
       381: aload_0
       382: getfield      #9                  // Field adaptor:Lorg/antlr/runtime/tree/TreeAdaptor;
       385: aload_2
       386: invokeinterface #35,  2           // InterfaceMethod org/antlr/runtime/tree/TreeAdaptor.getType:(Ljava/lang/Object;)I
       391: invokestatic  #70                 // Method java/lang/String.valueOf:(I)Ljava/lang/String;
       394: invokevirtual #51                 // Method java/lang/StringBuilder.append:(Ljava/lang/String;)Ljava/lang/StringBuilder;
       397: invokevirtual #53                 // Method java/lang/StringBuilder.toString:()Ljava/lang/String;
       400: astore        6
       402: aload         5
       404: aload         6
       406: invokevirtual #51                 // Method java/lang/StringBuilder.append:(Ljava/lang/String;)Ljava/lang/StringBuilder;
       409: pop
       410: aload         5
       412: invokevirtual #53                 // Method java/lang/StringBuilder.toString:()Ljava/lang/String;
       415: areturn
      LineNumberTable:
        line 441: 0
        line 442: 8
        line 443: 16
        line 445: 18
        line 446: 26
        line 449: 30
        line 450: 37
        line 452: 76
        line 453: 83
        line 454: 90
        line 456: 106
        line 458: 113
        line 459: 120
        line 460: 131
        line 463: 143
        line 464: 157
        line 466: 172
        line 467: 186
        line 469: 194
        line 473: 207
        line 474: 210
        line 475: 224
        line 476: 236
        line 477: 241
        line 474: 244
        line 481: 250
        line 482: 259
        line 483: 271
        line 484: 276
        line 485: 288
        line 486: 293
        line 488: 326
        line 489: 334
        line 490: 337
        line 491: 349
        line 493: 352
        line 494: 364
        line 495: 369
        line 497: 402
        line 498: 410
      LocalVariableTable:
        Start  Length  Slot  Name   Signature
          131      76     3 beginTokenIndex   I
          143      64     4 endTokenIndex   I
          236      14     3     t   Ljava/lang/Object;
          288      61     6  text   Ljava/lang/String;
            0     416     0  this   Lorg/antlr/runtime/tree/BufferedTreeNodeStream;
            0     416     1 start   Ljava/lang/Object;
            0     416     2  stop   Ljava/lang/Object;
          271     145     3     t   Ljava/lang/Object;
          210     206     4     i   I
          259     157     5   buf   Ljava/lang/StringBuilder;
          364      52     6  text   Ljava/lang/String;
}
SourceFile: "BufferedTreeNodeStream.java"
InnerClasses:
  protected #74= #45 of #71;              // StreamIterator=class org/antlr/runtime/tree/BufferedTreeNodeStream$StreamIterator of class org/antlr/runtime/tree/BufferedTreeNodeStream
