Classfile /Users/mw/Projects/slang-braindump/.jar/jar8/assemble/slang-braindump/assemble/content/org/antlr/runtime/tree/TreeWizard$3.class
  Last modified May 29, 2022; size 1765 bytes
  SHA-256 checksum 497ea1045aebf8d749d989fb13d8aba213a899fb62125b0dde049c1d8ca0f066
  Compiled from "TreeWizard.java"
class org.antlr.runtime.tree.TreeWizard$3 implements org.antlr.runtime.tree.TreeWizard$ContextVisitor
  minor version: 0
  major version: 49
  flags: (0x0020) ACC_SUPER
  this_class: #9                          // org/antlr/runtime/tree/TreeWizard$3
  super_class: #10                        // java/lang/Object
  interfaces: 1, fields: 4, methods: 2, attributes: 3
Constant pool:
   #1 = Fieldref           #9.#49         // org/antlr/runtime/tree/TreeWizard$3.this$0:Lorg/antlr/runtime/tree/TreeWizard;
   #2 = Fieldref           #9.#50         // org/antlr/runtime/tree/TreeWizard$3.val$labels:Ljava/util/Map;
   #3 = Fieldref           #9.#51         // org/antlr/runtime/tree/TreeWizard$3.val$tpattern:Lorg/antlr/runtime/tree/TreeWizard$TreePattern;
   #4 = Fieldref           #9.#52         // org/antlr/runtime/tree/TreeWizard$3.val$visitor:Lorg/antlr/runtime/tree/TreeWizard$ContextVisitor;
   #5 = Methodref          #10.#53        // java/lang/Object."<init>":()V
   #6 = InterfaceMethodref #54.#55        // java/util/Map.clear:()V
   #7 = Methodref          #47.#56        // org/antlr/runtime/tree/TreeWizard._parse:(Ljava/lang/Object;Lorg/antlr/runtime/tree/TreeWizard$TreePattern;Ljava/util/Map;)Z
   #8 = InterfaceMethodref #11.#57        // org/antlr/runtime/tree/TreeWizard$ContextVisitor.visit:(Ljava/lang/Object;Ljava/lang/Object;ILjava/util/Map;)V
   #9 = Class              #58            // org/antlr/runtime/tree/TreeWizard$3
  #10 = Class              #59            // java/lang/Object
  #11 = Class              #60            // org/antlr/runtime/tree/TreeWizard$ContextVisitor
  #12 = Utf8               val$labels
  #13 = Utf8               Ljava/util/Map;
  #14 = Utf8               val$tpattern
  #15 = Class              #61            // org/antlr/runtime/tree/TreeWizard$TreePattern
  #16 = Utf8               TreePattern
  #17 = Utf8               InnerClasses
  #18 = Utf8               Lorg/antlr/runtime/tree/TreeWizard$TreePattern;
  #19 = Utf8               val$visitor
  #20 = Utf8               ContextVisitor
  #21 = Utf8               Lorg/antlr/runtime/tree/TreeWizard$ContextVisitor;
  #22 = Utf8               this$0
  #23 = Utf8               Lorg/antlr/runtime/tree/TreeWizard;
  #24 = Utf8               <init>
  #25 = Utf8               (Lorg/antlr/runtime/tree/TreeWizard;Ljava/util/Map;Lorg/antlr/runtime/tree/TreeWizard$TreePattern;Lorg/antlr/runtime/tree/TreeWizard$ContextVisitor;)V
  #26 = Utf8               Code
  #27 = Utf8               LineNumberTable
  #28 = Utf8               LocalVariableTable
  #29 = Utf8               this
  #30 = Utf8
  #31 = Utf8               Lorg/antlr/runtime/tree/TreeWizard$3;
  #32 = Utf8               visit
  #33 = Utf8               (Ljava/lang/Object;Ljava/lang/Object;ILjava/util/Map;)V
  #34 = Utf8               t
  #35 = Utf8               Ljava/lang/Object;
  #36 = Utf8               parent
  #37 = Utf8               childIndex
  #38 = Utf8               I
  #39 = Utf8               unusedlabels
  #40 = Utf8               LocalVariableTypeTable
  #41 = Utf8               Ljava/util/Map<Ljava/lang/String;Ljava/lang/Object;>;
  #42 = Utf8               Signature
  #43 = Utf8               (Ljava/lang/Object;Ljava/lang/Object;ILjava/util/Map<Ljava/lang/String;Ljava/lang/Object;>;)V
  #44 = Utf8               SourceFile
  #45 = Utf8               TreeWizard.java
  #46 = Utf8               EnclosingMethod
  #47 = Class              #62            // org/antlr/runtime/tree/TreeWizard
  #48 = NameAndType        #32:#63        // visit:(Ljava/lang/Object;Ljava/lang/String;Lorg/antlr/runtime/tree/TreeWizard$ContextVisitor;)V
  #49 = NameAndType        #22:#23        // this$0:Lorg/antlr/runtime/tree/TreeWizard;
  #50 = NameAndType        #12:#13        // val$labels:Ljava/util/Map;
  #51 = NameAndType        #14:#18        // val$tpattern:Lorg/antlr/runtime/tree/TreeWizard$TreePattern;
  #52 = NameAndType        #19:#21        // val$visitor:Lorg/antlr/runtime/tree/TreeWizard$ContextVisitor;
  #53 = NameAndType        #24:#64        // "<init>":()V
  #54 = Class              #65            // java/util/Map
  #55 = NameAndType        #66:#64        // clear:()V
  #56 = NameAndType        #67:#68        // _parse:(Ljava/lang/Object;Lorg/antlr/runtime/tree/TreeWizard$TreePattern;Ljava/util/Map;)Z
  #57 = NameAndType        #32:#33        // visit:(Ljava/lang/Object;Ljava/lang/Object;ILjava/util/Map;)V
  #58 = Utf8               org/antlr/runtime/tree/TreeWizard$3
  #59 = Utf8               java/lang/Object
  #60 = Utf8               org/antlr/runtime/tree/TreeWizard$ContextVisitor
  #61 = Utf8               org/antlr/runtime/tree/TreeWizard$TreePattern
  #62 = Utf8               org/antlr/runtime/tree/TreeWizard
  #63 = Utf8               (Ljava/lang/Object;Ljava/lang/String;Lorg/antlr/runtime/tree/TreeWizard$ContextVisitor;)V
  #64 = Utf8               ()V
  #65 = Utf8               java/util/Map
  #66 = Utf8               clear
  #67 = Utf8               _parse
  #68 = Utf8               (Ljava/lang/Object;Lorg/antlr/runtime/tree/TreeWizard$TreePattern;Ljava/util/Map;)Z
{
  final java.util.Map val$labels;
    descriptor: Ljava/util/Map;
    flags: (0x1010) ACC_FINAL, ACC_SYNTHETIC

  final org.antlr.runtime.tree.TreeWizard$TreePattern val$tpattern;
    descriptor: Lorg/antlr/runtime/tree/TreeWizard$TreePattern;
    flags: (0x1010) ACC_FINAL, ACC_SYNTHETIC

  final org.antlr.runtime.tree.TreeWizard$ContextVisitor val$visitor;
    descriptor: Lorg/antlr/runtime/tree/TreeWizard$ContextVisitor;
    flags: (0x1010) ACC_FINAL, ACC_SYNTHETIC

  final org.antlr.runtime.tree.TreeWizard this$0;
    descriptor: Lorg/antlr/runtime/tree/TreeWizard;
    flags: (0x1010) ACC_FINAL, ACC_SYNTHETIC

  org.antlr.runtime.tree.TreeWizard$3(org.antlr.runtime.tree.TreeWizard, java.util.Map, org.antlr.runtime.tree.TreeWizard$TreePattern, org.antlr.runtime.tree.TreeWizard$ContextVisitor);
    descriptor: (Lorg/antlr/runtime/tree/TreeWizard;Ljava/util/Map;Lorg/antlr/runtime/tree/TreeWizard$TreePattern;Lorg/antlr/runtime/tree/TreeWizard$ContextVisitor;)V
    flags: (0x0000)
    Code:
      stack=2, locals=5, args_size=5
         0: aload_0
         1: aload_1
         2: putfield      #1                  // Field this$0:Lorg/antlr/runtime/tree/TreeWizard;
         5: aload_0
         6: aload_2
         7: putfield      #2                  // Field val$labels:Ljava/util/Map;
        10: aload_0
        11: aload_3
        12: putfield      #3                  // Field val$tpattern:Lorg/antlr/runtime/tree/TreeWizard$TreePattern;
        15: aload_0
        16: aload         4
        18: putfield      #4                  // Field val$visitor:Lorg/antlr/runtime/tree/TreeWizard$ContextVisitor;
        21: aload_0
        22: invokespecial #5                  // Method java/lang/Object."<init>":()V
        25: return
      LineNumberTable:
        line 293: 0
      LocalVariableTable:
        Start  Length  Slot  Name   Signature
            0      26     0  this   Lorg/antlr/runtime/tree/TreeWizard$3;

  public void visit(java.lang.Object, java.lang.Object, int, java.util.Map<java.lang.String, java.lang.Object>);
    descriptor: (Ljava/lang/Object;Ljava/lang/Object;ILjava/util/Map;)V
    flags: (0x0001) ACC_PUBLIC
    Code:
      stack=5, locals=5, args_size=5
         0: aload_0
         1: getfield      #2                  // Field val$labels:Ljava/util/Map;
         4: invokeinterface #6,  1            // InterfaceMethod java/util/Map.clear:()V
         9: aload_0
        10: getfield      #1                  // Field this$0:Lorg/antlr/runtime/tree/TreeWizard;
        13: aload_1
        14: aload_0
        15: getfield      #3                  // Field val$tpattern:Lorg/antlr/runtime/tree/TreeWizard$TreePattern;
        18: aload_0
        19: getfield      #2                  // Field val$labels:Ljava/util/Map;
        22: invokevirtual #7                  // Method org/antlr/runtime/tree/TreeWizard._parse:(Ljava/lang/Object;Lorg/antlr/runtime/tree/TreeWizard$TreePattern;Ljava/util/Map;)Z
        25: ifeq          44
        28: aload_0
        29: getfield      #4                  // Field val$visitor:Lorg/antlr/runtime/tree/TreeWizard$ContextVisitor;
        32: aload_1
        33: aload_2
        34: iload_3
        35: aload_0
        36: getfield      #2                  // Field val$labels:Ljava/util/Map;
        39: invokeinterface #8,  5            // InterfaceMethod org/antlr/runtime/tree/TreeWizard$ContextVisitor.visit:(Ljava/lang/Object;Ljava/lang/Object;ILjava/util/Map;)V
        44: return
      LineNumberTable:
        line 297: 0
        line 298: 9
        line 299: 28
        line 301: 44
      LocalVariableTable:
        Start  Length  Slot  Name   Signature
            0      45     0  this   Lorg/antlr/runtime/tree/TreeWizard$3;
            0      45     1     t   Ljava/lang/Object;
            0      45     2 parent   Ljava/lang/Object;
            0      45     3 childIndex   I
            0      45     4 unusedlabels   Ljava/util/Map;
      LocalVariableTypeTable:
        Start  Length  Slot  Name   Signature
            0      45     4 unusedlabels   Ljava/util/Map<Ljava/lang/String;Ljava/lang/Object;>;
    Signature: #43                          // (Ljava/lang/Object;Ljava/lang/Object;ILjava/util/Map<Ljava/lang/String;Ljava/lang/Object;>;)V
}
SourceFile: "TreeWizard.java"
EnclosingMethod: #47.#48                // org.antlr.runtime.tree.TreeWizard.visit
InnerClasses:
  public static #16= #15 of #47;          // TreePattern=class org/antlr/runtime/tree/TreeWizard$TreePattern of class org/antlr/runtime/tree/TreeWizard
  public static #20= #11 of #47;          // ContextVisitor=class org/antlr/runtime/tree/TreeWizard$ContextVisitor of class org/antlr/runtime/tree/TreeWizard
  #9;                                     // class org/antlr/runtime/tree/TreeWizard$3
