Classfile /Users/mw/Projects/slang-braindump/.jar/jar8/assemble/slang-braindump/assemble/content/org/antlr/runtime/tree/TreeWizard$1.class
  Last modified May 29, 2022; size 881 bytes
  SHA-256 checksum 075c2c809bd7d68916632d4ba67b9345979ec7b9f6ce37db6506aea2a54bcf5a
  Compiled from "TreeWizard.java"
class org.antlr.runtime.tree.TreeWizard$1 extends org.antlr.runtime.tree.TreeWizard$Visitor
  minor version: 0
  major version: 49
  flags: (0x0020) ACC_SUPER
  this_class: #5                          // org/antlr/runtime/tree/TreeWizard$1
  super_class: #6                         // org/antlr/runtime/tree/TreeWizard$Visitor
  interfaces: 0, fields: 2, methods: 2, attributes: 3
Constant pool:
   #1 = Fieldref           #5.#29         // org/antlr/runtime/tree/TreeWizard$1.this$0:Lorg/antlr/runtime/tree/TreeWizard;
   #2 = Fieldref           #5.#30         // org/antlr/runtime/tree/TreeWizard$1.val$nodes:Ljava/util/List;
   #3 = Methodref          #6.#31         // org/antlr/runtime/tree/TreeWizard$Visitor."<init>":()V
   #4 = InterfaceMethodref #32.#33        // java/util/List.add:(Ljava/lang/Object;)Z
   #5 = Class              #34            // org/antlr/runtime/tree/TreeWizard$1
   #6 = Class              #35            // org/antlr/runtime/tree/TreeWizard$Visitor
   #7 = Utf8               val$nodes
   #8 = Utf8               Ljava/util/List;
   #9 = Utf8               this$0
  #10 = Utf8               Lorg/antlr/runtime/tree/TreeWizard;
  #11 = Utf8               <init>
  #12 = Utf8               (Lorg/antlr/runtime/tree/TreeWizard;Ljava/util/List;)V
  #13 = Utf8               Code
  #14 = Utf8               LineNumberTable
  #15 = Utf8               LocalVariableTable
  #16 = Utf8               this
  #17 = Utf8
  #18 = Utf8               InnerClasses
  #19 = Utf8               Lorg/antlr/runtime/tree/TreeWizard$1;
  #20 = Utf8               visit
  #21 = Utf8               (Ljava/lang/Object;)V
  #22 = Utf8               t
  #23 = Utf8               Ljava/lang/Object;
  #24 = Utf8               SourceFile
  #25 = Utf8               TreeWizard.java
  #26 = Utf8               EnclosingMethod
  #27 = Class              #37            // org/antlr/runtime/tree/TreeWizard
  #28 = NameAndType        #38:#39        // find:(Ljava/lang/Object;I)Ljava/util/List;
  #29 = NameAndType        #9:#10         // this$0:Lorg/antlr/runtime/tree/TreeWizard;
  #30 = NameAndType        #7:#8          // val$nodes:Ljava/util/List;
  #31 = NameAndType        #11:#40        // "<init>":()V
  #32 = Class              #41            // java/util/List
  #33 = NameAndType        #42:#43        // add:(Ljava/lang/Object;)Z
  #34 = Utf8               org/antlr/runtime/tree/TreeWizard$1
  #35 = Utf8               org/antlr/runtime/tree/TreeWizard$Visitor
  #36 = Utf8               Visitor
  #37 = Utf8               org/antlr/runtime/tree/TreeWizard
  #38 = Utf8               find
  #39 = Utf8               (Ljava/lang/Object;I)Ljava/util/List;
  #40 = Utf8               ()V
  #41 = Utf8               java/util/List
  #42 = Utf8               add
  #43 = Utf8               (Ljava/lang/Object;)Z
{
  final java.util.List val$nodes;
    descriptor: Ljava/util/List;
    flags: (0x1010) ACC_FINAL, ACC_SYNTHETIC

  final org.antlr.runtime.tree.TreeWizard this$0;
    descriptor: Lorg/antlr/runtime/tree/TreeWizard;
    flags: (0x1010) ACC_FINAL, ACC_SYNTHETIC

  org.antlr.runtime.tree.TreeWizard$1(org.antlr.runtime.tree.TreeWizard, java.util.List);
    descriptor: (Lorg/antlr/runtime/tree/TreeWizard;Ljava/util/List;)V
    flags: (0x0000)
    Code:
      stack=2, locals=3, args_size=3
         0: aload_0
         1: aload_1
         2: putfield      #1                  // Field this$0:Lorg/antlr/runtime/tree/TreeWizard;
         5: aload_0
         6: aload_2
         7: putfield      #2                  // Field val$nodes:Ljava/util/List;
        10: aload_0
        11: invokespecial #3                  // Method org/antlr/runtime/tree/TreeWizard$Visitor."<init>":()V
        14: return
      LineNumberTable:
        line 205: 0
      LocalVariableTable:
        Start  Length  Slot  Name   Signature
            0      15     0  this   Lorg/antlr/runtime/tree/TreeWizard$1;

  public void visit(java.lang.Object);
    descriptor: (Ljava/lang/Object;)V
    flags: (0x0001) ACC_PUBLIC
    Code:
      stack=2, locals=2, args_size=2
         0: aload_0
         1: getfield      #2                  // Field val$nodes:Ljava/util/List;
         4: aload_1
         5: invokeinterface #4,  2            // InterfaceMethod java/util/List.add:(Ljava/lang/Object;)Z
        10: pop
        11: return
      LineNumberTable:
        line 208: 0
        line 209: 11
      LocalVariableTable:
        Start  Length  Slot  Name   Signature
            0      12     0  this   Lorg/antlr/runtime/tree/TreeWizard$1;
            0      12     1     t   Ljava/lang/Object;
}
SourceFile: "TreeWizard.java"
EnclosingMethod: #27.#28                // org.antlr.runtime.tree.TreeWizard.find
InnerClasses:
  #5;                                     // class org/antlr/runtime/tree/TreeWizard$1
  public static abstract #36= #6 of #27;  // Visitor=class org/antlr/runtime/tree/TreeWizard$Visitor of class org/antlr/runtime/tree/TreeWizard
