Classfile /Users/mw/Projects/slang-braindump/.jar/jar8/assemble/slang-braindump/assemble/content/scala/xml/Document.class
  Last modified May 29, 2022; size 5080 bytes
  SHA-256 checksum 333f5dc712ab29ef2f004f85f64da728b743116100ca146dbf18976527641a99
  Compiled from "Document.scala"
public class scala.xml.Document extends scala.xml.NodeSeq
  minor version: 0
  major version: 52
  flags: (0x0021) ACC_PUBLIC, ACC_SUPER
  this_class: #2                          // scala/xml/Document
  super_class: #4                         // scala/xml/NodeSeq
  interfaces: 0, fields: 9, methods: 21, attributes: 4
Constant pool:
    #1 = Utf8               scala/xml/Document
    #2 = Class              #1            // scala/xml/Document
    #3 = Utf8               scala/xml/NodeSeq
    #4 = Class              #3            // scala/xml/NodeSeq
    #5 = Utf8               Document.scala
    #6 = Utf8               Lscala/reflect/ScalaSignature;
    #7 = Utf8               bytes
    #8 = Utf8               \u0006\u0005\u0005\rc\u0001\u0002\u0010 \u0001\u0011BQ!\r\u0001\u0005\u0002IB\u0011\u0002\u000e\u0001A\u0002\u0003\u0007I\u0011A\u001b\t\u0013}\u0002\u0001\u0019!a\u0001\n\u0003\u0001\u0005\"\u0003$\u0001\u0001\u0004\u0005\t\u0015)\u00037\u0011%9\u0005\u00011AA\u0002\u0013\u0005\u0001\nC\u0005J\u0001\u0001\u0007\t\u0019!C\u0001\u0015\"IA\n\u0001a\u0001\u0002\u0003\u0006K\u0001\u0010\u0005\n\u001b\u0002\u0001\r\u00111A\u0005\u00029C\u0011\u0002\u0016\u0001A\u0002\u0003\u0007I\u0011A+\t\u0013]\u0003\u0001\u0019!A!B\u0013y\u0005\"\u0002-\u0001\t\u0003I\u0006\"\u00020\u0001\t\u0003y\u0006\"\u00033\u0001\u0001\u0004\u0005\r\u0011\"\u0001f\u0011%\t\b\u00011AA\u0002\u0013\u0005!\u000fC\u0005u\u0001\u0001\u0007\t\u0011)Q\u0005M\"IQ\u000f\u0001a\u0001\u0002\u0004%\tA\u001e\u0005\nu\u0002\u0001\r\u00111A\u0005\u0002mD\u0011\" \u0001A\u0002\u0003\u0005\u000b\u0015B<\t\u0013y\u0004\u0001\u0019!a\u0001\n\u0003y\bbCA\u0005\u0001\u0001\u0007\t\u0019!C\u0001\u0003\u0017A1\"a\u0004\u0001\u0001\u0004\u0005\t\u0015)\u0003\u0002\u0002!Q\u0011\u0011\u0003\u0001A\u0002\u0003\u0007I\u0011\u0001<\t\u0017\u0005M\u0001\u00011AA\u0002\u0013\u0005\u0011Q\u0003\u0005\u000b\u00033\u0001\u0001\u0019!A!B\u00139\b\"CA\u000e\u0001\u0001\u0007I\u0011AA\u000f\u0011%\ty\u0002\u0001a\u0001\n\u0003\t\t\u0003\u0003\u0005\u0002&\u0001\u0001\u000b\u0015BA\u0002\u0011\u0019\t9\u0003\u0001C\u0001k!9\u0011\u0011\u0006\u0001\u0005B\u0005-\"\u0001\u0003#pGVlWM\u001c;\u000b\u0005\u0001\n\u0013a\u0001=nY*\t!%A\u0003tG\u0006d\u0017m\u0001\u0001\u0014\u0007\u0001)\u0013\u0006\u0005\u0002\'O5\tq$\u0003\u0002)?\t9aj\u001c3f\'\u0016\f\bC\u0001\u0016/\u001d\tYC&D\u0001\"\u0013\ti\u0013%A\u0004qC\u000e\\\u0017mZ3\n\u0005=\u0002$\u0001D*fe&\fG.\u001b>bE2,\'BA\u0017\"\u0003\u0019a\u0014N\\5u}Q\t1\u0007\u0005\u0002\'\u0001\u0005A1\r[5mIJ,g.F\u00017!\r9$\bP\u0007\u0002q)\u0011\u0011(I\u0001\u000bG>dG.Z2uS>t\u0017BA\u001e9\u0005\r\u0019V-\u001d\t\u0003MuJ!AP\u0010\u0003\t9{G-Z\u0001\rG\"LG\u000e\u001a:f]~#S-\u001d\u000b\u0003\u0003\u0012\u0003\"a\u000b\"\n\u0005\r\u000b#\u0001B+oSRDq!R\u0002\u0002\u0002\u0003\u0007a\'A\u0002yIE\n\u0011b\u00195jY\u0012\u0014XM\u001c\u0011\u0002\u000f\u0011|7-\u00127f[V\tA(A\u0006e_\u000e,E.Z7`I\u0015\fHCA!L\u0011\u001d)e!!AA\u0002q\n\u0001\u0002Z8d\u000b2,W\u000eI\u0001\u0004IR$W#A(\u0011\u0005A\u0013V\"A)\u000b\u00055{\u0012BA*R\u0005\r!E\u000bR\u0001\bIR$w\fJ3r)\t\te\u000bC\u0004F\u0013\u0005\u0005\t\u0019A(\u0002\t\u0011$H\rI\u0001\n]>$\u0018\r^5p]N,\u0012A\u0017\t\u0004oiZ\u0006C\u0001)]\u0013\ti\u0016K\u0001\u0007O_R\fG/[8o\t\u0016\u001cG.\u0001\tv]B\f\'o]3e\u000b:$\u0018\u000e^5fgV\t\u0001\rE\u00028u\u0005\u0004\"\u0001\u00152\n\u0005\r\f&AC#oi&$\u0018\u0010R3dY\u00069!-Y:f+JKU#\u00014\u0011\u0005\u001dtgB\u00015m!\tI\u0017%D\u0001k\u0015\tY7%\u0001\u0004=e>|GOP\u0005\u0003[\u0006\na\u0001\u0015:fI\u00164\u0017BA8q\u0005\u0019\u0019FO]5oO*\u0011Q.I\u0001\fE\u0006\u001cX-\u0016*J?\u0012*\u0017\u000f\u0006\u0002Bg\"9QIDA\u0001\u0002\u00041\u0017\u0001\u00032bg\u0016,&+\u0013\u0011\u0002\u0011\u0015t7m\u001c3j]\u001e,\u0012a\u001e\t\u0004Wa4\u0017BA=\"\u0005\u0019y\u0005\u000f^5p]\u0006aQM\\2pI&twm\u0018\u0013fcR\u0011\u0011\t \u0005\b\u000bF\t\t\u00111\u0001x\u0003%)gnY8eS:<\u0007%\u0001\u0006ti\u0006tG-\u00117p]\u0016,\"!!\u0001\u0011\t-B\u00181\u0001\t\u0004W\u0005\u0015\u0011bAA\u0004C\t9!i\\8mK\u0006t\u0017AD:uC:$\u0017\t\\8oK~#S-\u001d\u000b\u0004\u0003\u00065\u0001\u0002C#\u0015\u0003\u0003\u0005\r!!\u0001\u0002\u0017M$\u0018M\u001c3BY>tW\rI\u0001\bm\u0016\u00148/[8o\u0003-1XM]:j_:|F%Z9\u0015\u0007\u0005\u000b9\u0002C\u0004F/\u0005\u0005\t\u0019A<\u0002\u0011Y,\'o]5p]\u0002\n\u0001$\u00197m\t\u0016\u001cG.\u0019:bi&|gn\u001d)s_\u000e,7o]3e+\t\t\u0019!\u0001\u000fbY2$Um\u00197be\u0006$\u0018n\u001c8t!J|7-Z:tK\u0012|F%Z9\u0015\u0007\u0005\u000b\u0019\u0003\u0003\u0005F5\u0005\u0005\t\u0019AA\u0002\u0003e\tG\u000e\u001c#fG2\f\'/\u0019;j_:\u001c\bK]8dKN\u001cX\r\u001a\u0011\u0002\rQDWmU3r\u0003!\u0019\u0017M\\#rk\u0006dG\u0003BA\u0002\u0003[Aq!a\f\u001e\u0001\u0004\t\t$A\u0003pi\",\'\u000fE\u0002,\u0003gI1!!\u000e\"\u0005\r\te.\u001f\u0015\b\u0001\u0005e\u0012qHA!!\rY\u00131H\u0005\u0004\u0003{\t#\u0001E*fe&\fGNV3sg&|g.V%E\u0003\u00151\u0018\r\\;f=!\u0001/hm\n7l5Y\u000e
    #9 = Utf8               serialVersionUID
   #10 = Utf8               J
   #11 = Long               -2289320563321795109l
   #13 = Utf8               children
   #14 = Utf8               Lscala/collection/Seq;
   #15 = Utf8               Lscala/collection/Seq<Lscala/xml/Node;>;
   #16 = Utf8               docElem
   #17 = Utf8               Lscala/xml/Node;
   #18 = Utf8               dtd
   #19 = Utf8               Lscala/xml/dtd/DTD;
   #20 = Utf8               baseURI
   #21 = Utf8               Ljava/lang/String;
   #22 = Utf8               encoding
   #23 = Utf8               Lscala/Option;
   #24 = Utf8               Lscala/Option<Ljava/lang/String;>;
   #25 = Utf8               standAlone
   #26 = Utf8               Lscala/Option<Ljava/lang/Object;>;
   #27 = Utf8               version
   #28 = Utf8               allDeclarationsProcessed
   #29 = Utf8               Z
   #30 = Utf8               ()Lscala/collection/Seq;
   #31 = Utf8               ()Lscala/collection/Seq<Lscala/xml/Node;>;
   #32 = NameAndType        #13:#14       // children:Lscala/collection/Seq;
   #33 = Fieldref           #2.#32        // scala/xml/Document.children:Lscala/collection/Seq;
   #34 = Utf8               this
   #35 = Utf8               Lscala/xml/Document;
   #36 = Utf8               children_$eq
   #37 = Utf8               (Lscala/collection/Seq;)V
   #38 = Utf8               (Lscala/collection/Seq<Lscala/xml/Node;>;)V
   #39 = Utf8               x$1
   #40 = Utf8               ()Lscala/xml/Node;
   #41 = NameAndType        #16:#17       // docElem:Lscala/xml/Node;
   #42 = Fieldref           #2.#41        // scala/xml/Document.docElem:Lscala/xml/Node;
   #43 = Utf8               docElem_$eq
   #44 = Utf8               (Lscala/xml/Node;)V
   #45 = Utf8               ()Lscala/xml/dtd/DTD;
   #46 = NameAndType        #18:#19       // dtd:Lscala/xml/dtd/DTD;
   #47 = Fieldref           #2.#46        // scala/xml/Document.dtd:Lscala/xml/dtd/DTD;
   #48 = Utf8               dtd_$eq
   #49 = Utf8               (Lscala/xml/dtd/DTD;)V
   #50 = Utf8               notations
   #51 = Utf8               ()Lscala/collection/Seq<Lscala/xml/dtd/NotationDecl;>;
   #52 = NameAndType        #18:#45       // dtd:()Lscala/xml/dtd/DTD;
   #53 = Methodref          #2.#52        // scala/xml/Document.dtd:()Lscala/xml/dtd/DTD;
   #54 = Utf8               scala/xml/dtd/DTD
   #55 = Class              #54           // scala/xml/dtd/DTD
   #56 = NameAndType        #50:#30       // notations:()Lscala/collection/Seq;
   #57 = Methodref          #55.#56       // scala/xml/dtd/DTD.notations:()Lscala/collection/Seq;
   #58 = Utf8               unparsedEntities
   #59 = Utf8               ()Lscala/collection/Seq<Lscala/xml/dtd/EntityDecl;>;
   #60 = NameAndType        #58:#30       // unparsedEntities:()Lscala/collection/Seq;
   #61 = Methodref          #55.#60       // scala/xml/dtd/DTD.unparsedEntities:()Lscala/collection/Seq;
   #62 = Utf8               ()Ljava/lang/String;
   #63 = NameAndType        #20:#21       // baseURI:Ljava/lang/String;
   #64 = Fieldref           #2.#63        // scala/xml/Document.baseURI:Ljava/lang/String;
   #65 = Utf8               baseURI_$eq
   #66 = Utf8               (Ljava/lang/String;)V
   #67 = Utf8               ()Lscala/Option;
   #68 = Utf8               ()Lscala/Option<Ljava/lang/String;>;
   #69 = NameAndType        #22:#23       // encoding:Lscala/Option;
   #70 = Fieldref           #2.#69        // scala/xml/Document.encoding:Lscala/Option;
   #71 = Utf8               encoding_$eq
   #72 = Utf8               (Lscala/Option;)V
   #73 = Utf8               (Lscala/Option<Ljava/lang/String;>;)V
   #74 = Utf8               ()Lscala/Option<Ljava/lang/Object;>;
   #75 = NameAndType        #25:#23       // standAlone:Lscala/Option;
   #76 = Fieldref           #2.#75        // scala/xml/Document.standAlone:Lscala/Option;
   #77 = Utf8               standAlone_$eq
   #78 = Utf8               (Lscala/Option<Ljava/lang/Object;>;)V
   #79 = NameAndType        #27:#23       // version:Lscala/Option;
   #80 = Fieldref           #2.#79        // scala/xml/Document.version:Lscala/Option;
   #81 = Utf8               version_$eq
   #82 = Utf8               ()Z
   #83 = NameAndType        #28:#29       // allDeclarationsProcessed:Z
   #84 = Fieldref           #2.#83        // scala/xml/Document.allDeclarationsProcessed:Z
   #85 = Utf8               allDeclarationsProcessed_$eq
   #86 = Utf8               (Z)V
   #87 = Utf8               theSeq
   #88 = NameAndType        #16:#40       // docElem:()Lscala/xml/Node;
   #89 = Methodref          #2.#88        // scala/xml/Document.docElem:()Lscala/xml/Node;
   #90 = Utf8               canEqual
   #91 = Utf8               (Ljava/lang/Object;)Z
   #92 = Utf8               other
   #93 = Utf8               Ljava/lang/Object;
   #94 = Utf8               java/lang/Object
   #95 = Class              #94           // java/lang/Object
   #96 = Utf8               <init>
   #97 = Utf8               ()V
   #98 = NameAndType        #96:#97       // "<init>":()V
   #99 = Methodref          #4.#98        // scala/xml/NodeSeq."<init>":()V
  #100 = Utf8               ConstantValue
  #101 = Utf8               Signature
  #102 = Utf8               Code
  #103 = Utf8               LineNumberTable
  #104 = Utf8               LocalVariableTable
  #105 = Utf8               MethodParameters
  #106 = Utf8               StackMapTable
  #107 = Utf8               SourceFile
  #108 = Utf8               RuntimeVisibleAnnotations
  #109 = Utf8               ScalaInlineInfo
  #110 = Utf8               ScalaSig
{
  private static final long serialVersionUID;
    descriptor: J
    flags: (0x001a) ACC_PRIVATE, ACC_STATIC, ACC_FINAL
    ConstantValue: long -2289320563321795109l

  private scala.collection.Seq<scala.xml.Node> children;
    descriptor: Lscala/collection/Seq;
    flags: (0x0002) ACC_PRIVATE
    Signature: #15                          // Lscala/collection/Seq<Lscala/xml/Node;>;

  private scala.xml.Node docElem;
    descriptor: Lscala/xml/Node;
    flags: (0x0002) ACC_PRIVATE

  private scala.xml.dtd.DTD dtd;
    descriptor: Lscala/xml/dtd/DTD;
    flags: (0x0002) ACC_PRIVATE

  private java.lang.String baseURI;
    descriptor: Ljava/lang/String;
    flags: (0x0002) ACC_PRIVATE

  private scala.Option<java.lang.String> encoding;
    descriptor: Lscala/Option;
    flags: (0x0002) ACC_PRIVATE
    Signature: #24                          // Lscala/Option<Ljava/lang/String;>;

  private scala.Option<java.lang.Object> standAlone;
    descriptor: Lscala/Option;
    flags: (0x0002) ACC_PRIVATE
    Signature: #26                          // Lscala/Option<Ljava/lang/Object;>;

  private scala.Option<java.lang.String> version;
    descriptor: Lscala/Option;
    flags: (0x0002) ACC_PRIVATE
    Signature: #24                          // Lscala/Option<Ljava/lang/String;>;

  private boolean allDeclarationsProcessed;
    descriptor: Z
    flags: (0x0002) ACC_PRIVATE

  public scala.collection.Seq<scala.xml.Node> children();
    descriptor: ()Lscala/collection/Seq;
    flags: (0x0001) ACC_PUBLIC
    Code:
      stack=1, locals=1, args_size=1
         0: aload_0
         1: getfield      #33                 // Field children:Lscala/collection/Seq;
         4: areturn
      LineNumberTable:
        line 39: 0
      LocalVariableTable:
        Start  Length  Slot  Name   Signature
            0       5     0  this   Lscala/xml/Document;
    Signature: #31                          // ()Lscala/collection/Seq<Lscala/xml/Node;>;

  public void children_$eq(scala.collection.Seq<scala.xml.Node>);
    descriptor: (Lscala/collection/Seq;)V
    flags: (0x0001) ACC_PUBLIC
    Code:
      stack=2, locals=2, args_size=2
         0: aload_0
         1: aload_1
         2: putfield      #33                 // Field children:Lscala/collection/Seq;
         5: return
      LineNumberTable:
        line 39: 0
      LocalVariableTable:
        Start  Length  Slot  Name   Signature
            0       6     0  this   Lscala/xml/Document;
            0       6     1   x$1   Lscala/collection/Seq;
    Signature: #38                          // (Lscala/collection/Seq<Lscala/xml/Node;>;)V
    MethodParameters:
      Name                           Flags
      x$1                            final

  public scala.xml.Node docElem();
    descriptor: ()Lscala/xml/Node;
    flags: (0x0001) ACC_PUBLIC
    Code:
      stack=1, locals=1, args_size=1
         0: aload_0
         1: getfield      #42                 // Field docElem:Lscala/xml/Node;
         4: areturn
      LineNumberTable:
        line 42: 0
      LocalVariableTable:
        Start  Length  Slot  Name   Signature
            0       5     0  this   Lscala/xml/Document;

  public void docElem_$eq(scala.xml.Node);
    descriptor: (Lscala/xml/Node;)V
    flags: (0x0001) ACC_PUBLIC
    Code:
      stack=2, locals=2, args_size=2
         0: aload_0
         1: aload_1
         2: putfield      #42                 // Field docElem:Lscala/xml/Node;
         5: return
      LineNumberTable:
        line 42: 0
      LocalVariableTable:
        Start  Length  Slot  Name   Signature
            0       6     0  this   Lscala/xml/Document;
            0       6     1   x$1   Lscala/xml/Node;
    MethodParameters:
      Name                           Flags
      x$1                            final

  public scala.xml.dtd.DTD dtd();
    descriptor: ()Lscala/xml/dtd/DTD;
    flags: (0x0001) ACC_PUBLIC
    Code:
      stack=1, locals=1, args_size=1
         0: aload_0
         1: getfield      #47                 // Field dtd:Lscala/xml/dtd/DTD;
         4: areturn
      LineNumberTable:
        line 45: 0
      LocalVariableTable:
        Start  Length  Slot  Name   Signature
            0       5     0  this   Lscala/xml/Document;

  public void dtd_$eq(scala.xml.dtd.DTD);
    descriptor: (Lscala/xml/dtd/DTD;)V
    flags: (0x0001) ACC_PUBLIC
    Code:
      stack=2, locals=2, args_size=2
         0: aload_0
         1: aload_1
         2: putfield      #47                 // Field dtd:Lscala/xml/dtd/DTD;
         5: return
      LineNumberTable:
        line 45: 0
      LocalVariableTable:
        Start  Length  Slot  Name   Signature
            0       6     0  this   Lscala/xml/Document;
            0       6     1   x$1   Lscala/xml/dtd/DTD;
    MethodParameters:
      Name                           Flags
      x$1                            final

  public scala.collection.Seq<scala.xml.dtd.NotationDecl> notations();
    descriptor: ()Lscala/collection/Seq;
    flags: (0x0001) ACC_PUBLIC
    Code:
      stack=1, locals=1, args_size=1
         0: aload_0
         1: invokevirtual #53                 // Method dtd:()Lscala/xml/dtd/DTD;
         4: invokevirtual #57                 // Method scala/xml/dtd/DTD.notations:()Lscala/collection/Seq;
         7: areturn
      LineNumberTable:
        line 53: 0
      LocalVariableTable:
        Start  Length  Slot  Name   Signature
            0       8     0  this   Lscala/xml/Document;
    Signature: #51                          // ()Lscala/collection/Seq<Lscala/xml/dtd/NotationDecl;>;

  public scala.collection.Seq<scala.xml.dtd.EntityDecl> unparsedEntities();
    descriptor: ()Lscala/collection/Seq;
    flags: (0x0001) ACC_PUBLIC
    Code:
      stack=1, locals=1, args_size=1
         0: aload_0
         1: invokevirtual #53                 // Method dtd:()Lscala/xml/dtd/DTD;
         4: invokevirtual #61                 // Method scala/xml/dtd/DTD.unparsedEntities:()Lscala/collection/Seq;
         7: areturn
      LineNumberTable:
        line 60: 0
      LocalVariableTable:
        Start  Length  Slot  Name   Signature
            0       8     0  this   Lscala/xml/Document;
    Signature: #59                          // ()Lscala/collection/Seq<Lscala/xml/dtd/EntityDecl;>;

  public java.lang.String baseURI();
    descriptor: ()Ljava/lang/String;
    flags: (0x0001) ACC_PUBLIC
    Code:
      stack=1, locals=1, args_size=1
         0: aload_0
         1: getfield      #64                 // Field baseURI:Ljava/lang/String;
         4: areturn
      LineNumberTable:
        line 63: 0
      LocalVariableTable:
        Start  Length  Slot  Name   Signature
            0       5     0  this   Lscala/xml/Document;

  public void baseURI_$eq(java.lang.String);
    descriptor: (Ljava/lang/String;)V
    flags: (0x0001) ACC_PUBLIC
    Code:
      stack=2, locals=2, args_size=2
         0: aload_0
         1: aload_1
         2: putfield      #64                 // Field baseURI:Ljava/lang/String;
         5: return
      LineNumberTable:
        line 63: 0
      LocalVariableTable:
        Start  Length  Slot  Name   Signature
            0       6     0  this   Lscala/xml/Document;
            0       6     1   x$1   Ljava/lang/String;
    MethodParameters:
      Name                           Flags
      x$1                            final

  public scala.Option<java.lang.String> encoding();
    descriptor: ()Lscala/Option;
    flags: (0x0001) ACC_PUBLIC
    Code:
      stack=1, locals=1, args_size=1
         0: aload_0
         1: getfield      #70                 // Field encoding:Lscala/Option;
         4: areturn
      LineNumberTable:
        line 69: 0
      LocalVariableTable:
        Start  Length  Slot  Name   Signature
            0       5     0  this   Lscala/xml/Document;
    Signature: #68                          // ()Lscala/Option<Ljava/lang/String;>;

  public void encoding_$eq(scala.Option<java.lang.String>);
    descriptor: (Lscala/Option;)V
    flags: (0x0001) ACC_PUBLIC
    Code:
      stack=2, locals=2, args_size=2
         0: aload_0
         1: aload_1
         2: putfield      #70                 // Field encoding:Lscala/Option;
         5: return
      LineNumberTable:
        line 69: 0
      LocalVariableTable:
        Start  Length  Slot  Name   Signature
            0       6     0  this   Lscala/xml/Document;
            0       6     1   x$1   Lscala/Option;
    Signature: #73                          // (Lscala/Option<Ljava/lang/String;>;)V
    MethodParameters:
      Name                           Flags
      x$1                            final

  public scala.Option<java.lang.Object> standAlone();
    descriptor: ()Lscala/Option;
    flags: (0x0001) ACC_PUBLIC
    Code:
      stack=1, locals=1, args_size=1
         0: aload_0
         1: getfield      #76                 // Field standAlone:Lscala/Option;
         4: areturn
      LineNumberTable:
        line 78: 0
      LocalVariableTable:
        Start  Length  Slot  Name   Signature
            0       5     0  this   Lscala/xml/Document;
    Signature: #74                          // ()Lscala/Option<Ljava/lang/Object;>;

  public void standAlone_$eq(scala.Option<java.lang.Object>);
    descriptor: (Lscala/Option;)V
    flags: (0x0001) ACC_PUBLIC
    Code:
      stack=2, locals=2, args_size=2
         0: aload_0
         1: aload_1
         2: putfield      #76                 // Field standAlone:Lscala/Option;
         5: return
      LineNumberTable:
        line 78: 0
      LocalVariableTable:
        Start  Length  Slot  Name   Signature
            0       6     0  this   Lscala/xml/Document;
            0       6     1   x$1   Lscala/Option;
    Signature: #78                          // (Lscala/Option<Ljava/lang/Object;>;)V
    MethodParameters:
      Name                           Flags
      x$1                            final

  public scala.Option<java.lang.String> version();
    descriptor: ()Lscala/Option;
    flags: (0x0001) ACC_PUBLIC
    Code:
      stack=1, locals=1, args_size=1
         0: aload_0
         1: getfield      #80                 // Field version:Lscala/Option;
         4: areturn
      LineNumberTable:
        line 86: 0
      LocalVariableTable:
        Start  Length  Slot  Name   Signature
            0       5     0  this   Lscala/xml/Document;
    Signature: #68                          // ()Lscala/Option<Ljava/lang/String;>;

  public void version_$eq(scala.Option<java.lang.String>);
    descriptor: (Lscala/Option;)V
    flags: (0x0001) ACC_PUBLIC
    Code:
      stack=2, locals=2, args_size=2
         0: aload_0
         1: aload_1
         2: putfield      #80                 // Field version:Lscala/Option;
         5: return
      LineNumberTable:
        line 86: 0
      LocalVariableTable:
        Start  Length  Slot  Name   Signature
            0       6     0  this   Lscala/xml/Document;
            0       6     1   x$1   Lscala/Option;
    Signature: #73                          // (Lscala/Option<Ljava/lang/String;>;)V
    MethodParameters:
      Name                           Flags
      x$1                            final

  public boolean allDeclarationsProcessed();
    descriptor: ()Z
    flags: (0x0001) ACC_PUBLIC
    Code:
      stack=1, locals=1, args_size=1
         0: aload_0
         1: getfield      #84                 // Field allDeclarationsProcessed:Z
         4: ireturn
      LineNumberTable:
        line 95: 0
      LocalVariableTable:
        Start  Length  Slot  Name   Signature
            0       5     0  this   Lscala/xml/Document;

  public void allDeclarationsProcessed_$eq(boolean);
    descriptor: (Z)V
    flags: (0x0001) ACC_PUBLIC
    Code:
      stack=2, locals=2, args_size=2
         0: aload_0
         1: iload_1
         2: putfield      #84                 // Field allDeclarationsProcessed:Z
         5: return
      LineNumberTable:
        line 95: 0
      LocalVariableTable:
        Start  Length  Slot  Name   Signature
            0       6     0  this   Lscala/xml/Document;
            0       6     1   x$1   Z
    MethodParameters:
      Name                           Flags
      x$1                            final

  public scala.collection.Seq<scala.xml.Node> theSeq();
    descriptor: ()Lscala/collection/Seq;
    flags: (0x0001) ACC_PUBLIC
    Code:
      stack=1, locals=1, args_size=1
         0: aload_0
         1: invokevirtual #89                 // Method docElem:()Lscala/xml/Node;
         4: areturn
      LineNumberTable:
        line 99: 0
      LocalVariableTable:
        Start  Length  Slot  Name   Signature
            0       5     0  this   Lscala/xml/Document;
    Signature: #31                          // ()Lscala/collection/Seq<Lscala/xml/Node;>;

  public boolean canEqual(java.lang.Object);
    descriptor: (Ljava/lang/Object;)Z
    flags: (0x0001) ACC_PUBLIC
    Code:
      stack=1, locals=4, args_size=2
         0: aload_1
         1: astore_3
         2: aload_3
         3: instanceof    #2                  // class scala/xml/Document
         6: ifeq          14
         9: iconst_1
        10: istore_2
        11: goto          22
        14: goto          17
        17: iconst_0
        18: istore_2
        19: goto          22
        22: iload_2
        23: ireturn
      StackMapTable: number_of_entries = 3
        frame_type = 253 /* append */
          offset_delta = 14
          locals = [ top, class java/lang/Object ]
        frame_type = 2 /* same */
        frame_type = 255 /* full_frame */
          offset_delta = 4
          locals = [ class scala/xml/Document, class java/lang/Object, int, class java/lang/Object ]
          stack = []
      LineNumberTable:
        line 101: 0
        line 102: 2
        line 103: 17
        line 101: 22
      LocalVariableTable:
        Start  Length  Slot  Name   Signature
            0      24     0  this   Lscala/xml/Document;
            0      24     1 other   Ljava/lang/Object;
    MethodParameters:
      Name                           Flags
      other                          final

  public scala.xml.Document();
    descriptor: ()V
    flags: (0x0001) ACC_PUBLIC
    Code:
      stack=2, locals=1, args_size=1
         0: aload_0
         1: invokespecial #99                 // Method scala/xml/NodeSeq."<init>":()V
         4: aload_0
         5: iconst_0
         6: putfield      #84                 // Field allDeclarationsProcessed:Z
         9: return
      LineNumberTable:
        line 27: 0
        line 95: 4
        line 27: 9
      LocalVariableTable:
        Start  Length  Slot  Name   Signature
            0      10     0  this   Lscala/xml/Document;
}
SourceFile: "Document.scala"
RuntimeVisibleAnnotations:
  0: #6(#7=s#8)
    scala.reflect.ScalaSignature(
      bytes="\u0006\u0005\u0005\rc\u0001\u0002\u0010 \u0001\u0011BQ!\r\u0001\u0005\u0002IB\u0011\u0002\u000e\u0001A\u0002\u0003\u0007I\u0011A\u001b\t\u0013}\u0002\u0001\u0019!a\u0001\n\u0003\u0001\u0005\"\u0003$\u0001\u0001\u0004\u0005\t\u0015)\u00037\u0011%9\u0005\u00011AA\u0002\u0013\u0005\u0001\nC\u0005J\u0001\u0001\u0007\t\u0019!C\u0001\u0015\"IA\n\u0001a\u0001\u0002\u0003\u0006K\u0001\u0010\u0005\n\u001b\u0002\u0001\r\u00111A\u0005\u00029C\u0011\u0002\u0016\u0001A\u0002\u0003\u0007I\u0011A+\t\u0013]\u0003\u0001\u0019!A!B\u0013y\u0005\"\u0002-\u0001\t\u0003I\u0006\"\u00020\u0001\t\u0003y\u0006\"\u00033\u0001\u0001\u0004\u0005\r\u0011\"\u0001f\u0011%\t\b\u00011AA\u0002\u0013\u0005!\u000fC\u0005u\u0001\u0001\u0007\t\u0011)Q\u0005M\"IQ\u000f\u0001a\u0001\u0002\u0004%\tA\u001e\u0005\nu\u0002\u0001\r\u00111A\u0005\u0002mD\u0011\" \u0001A\u0002\u0003\u0005\u000b\u0015B<\t\u0013y\u0004\u0001\u0019!a\u0001\n\u0003y\bbCA\u0005\u0001\u0001\u0007\t\u0019!C\u0001\u0003\u0017A1\"a\u0004\u0001\u0001\u0004\u0005\t\u0015)\u0003\u0002\u0002!Q\u0011\u0011\u0003\u0001A\u0002\u0003\u0007I\u0011\u0001<\t\u0017\u0005M\u0001\u00011AA\u0002\u0013\u0005\u0011Q\u0003\u0005\u000b\u00033\u0001\u0001\u0019!A!B\u00139\b\"CA\u000e\u0001\u0001\u0007I\u0011AA\u000f\u0011%\ty\u0002\u0001a\u0001\n\u0003\t\t\u0003\u0003\u0005\u0002&\u0001\u0001\u000b\u0015BA\u0002\u0011\u0019\t9\u0003\u0001C\u0001k!9\u0011\u0011\u0006\u0001\u0005B\u0005-\"\u0001\u0003#pGVlWM\u001c;\u000b\u0005\u0001\n\u0013a\u0001=nY*\t!%A\u0003tG\u0006d\u0017m\u0001\u0001\u0014\u0007\u0001)\u0013\u0006\u0005\u0002\'O5\tq$\u0003\u0002)?\t9aj\u001c3f\'\u0016\f\bC\u0001\u0016/\u001d\tYC&D\u0001\"\u0013\ti\u0013%A\u0004qC\u000e\\\u0017mZ3\n\u0005=\u0002$\u0001D*fe&\fG.\u001b>bE2,\'BA\u0017\"\u0003\u0019a\u0014N\\5u}Q\t1\u0007\u0005\u0002\'\u0001\u0005A1\r[5mIJ,g.F\u00017!\r9$\bP\u0007\u0002q)\u0011\u0011(I\u0001\u000bG>dG.Z2uS>t\u0017BA\u001e9\u0005\r\u0019V-\u001d\t\u0003MuJ!AP\u0010\u0003\t9{G-Z\u0001\rG\"LG\u000e\u001a:f]~#S-\u001d\u000b\u0003\u0003\u0012\u0003\"a\u000b\"\n\u0005\r\u000b#\u0001B+oSRDq!R\u0002\u0002\u0002\u0003\u0007a\'A\u0002yIE\n\u0011b\u00195jY\u0012\u0014XM\u001c\u0011\u0002\u000f\u0011|7-\u00127f[V\tA(A\u0006e_\u000e,E.Z7`I\u0015\fHCA!L\u0011\u001d)e!!AA\u0002q\n\u0001\u0002Z8d\u000b2,W\u000eI\u0001\u0004IR$W#A(\u0011\u0005A\u0013V\"A)\u000b\u00055{\u0012BA*R\u0005\r!E\u000bR\u0001\bIR$w\fJ3r)\t\te\u000bC\u0004F\u0013\u0005\u0005\t\u0019A(\u0002\t\u0011$H\rI\u0001\n]>$\u0018\r^5p]N,\u0012A\u0017\t\u0004oiZ\u0006C\u0001)]\u0013\ti\u0016K\u0001\u0007O_R\fG/[8o\t\u0016\u001cG.\u0001\tv]B\f\'o]3e\u000b:$\u0018\u000e^5fgV\t\u0001\rE\u00028u\u0005\u0004\"\u0001\u00152\n\u0005\r\f&AC#oi&$\u0018\u0010R3dY\u00069!-Y:f+JKU#\u00014\u0011\u0005\u001dtgB\u00015m!\tI\u0017%D\u0001k\u0015\tY7%\u0001\u0004=e>|GOP\u0005\u0003[\u0006\na\u0001\u0015:fI\u00164\u0017BA8q\u0005\u0019\u0019FO]5oO*\u0011Q.I\u0001\fE\u0006\u001cX-\u0016*J?\u0012*\u0017\u000f\u0006\u0002Bg\"9QIDA\u0001\u0002\u00041\u0017\u0001\u00032bg\u0016,&+\u0013\u0011\u0002\u0011\u0015t7m\u001c3j]\u001e,\u0012a\u001e\t\u0004Wa4\u0017BA=\"\u0005\u0019y\u0005\u000f^5p]\u0006aQM\\2pI&twm\u0018\u0013fcR\u0011\u0011\t \u0005\b\u000bF\t\t\u00111\u0001x\u0003%)gnY8eS:<\u0007%\u0001\u0006ti\u0006tG-\u00117p]\u0016,\"!!\u0001\u0011\t-B\u00181\u0001\t\u0004W\u0005\u0015\u0011bAA\u0004C\t9!i\\8mK\u0006t\u0017AD:uC:$\u0017\t\\8oK~#S-\u001d\u000b\u0004\u0003\u00065\u0001\u0002C#\u0015\u0003\u0003\u0005\r!!\u0001\u0002\u0017M$\u0018M\u001c3BY>tW\rI\u0001\bm\u0016\u00148/[8o\u0003-1XM]:j_:|F%Z9\u0015\u0007\u0005\u000b9\u0002C\u0004F/\u0005\u0005\t\u0019A<\u0002\u0011Y,\'o]5p]\u0002\n\u0001$\u00197m\t\u0016\u001cG.\u0019:bi&|gn\u001d)s_\u000e,7o]3e+\t\t\u0019!\u0001\u000fbY2$Um\u00197be\u0006$\u0018n\u001c8t!J|7-Z:tK\u0012|F%Z9\u0015\u0007\u0005\u000b\u0019\u0003\u0003\u0005F5\u0005\u0005\t\u0019AA\u0002\u0003e\tG\u000e\u001c#fG2\f\'/\u0019;j_:\u001c\bK]8dKN\u001cX\r\u001a\u0011\u0002\rQDWmU3r\u0003!\u0019\u0017M\\#rk\u0006dG\u0003BA\u0002\u0003[Aq!a\f\u001e\u0001\u0004\t\t$A\u0003pi\",\'\u000fE\u0002,\u0003gI1!!\u000e\"\u0005\r\te.\u001f\u0015\b\u0001\u0005e\u0012qHA!!\rY\u00131H\u0005\u0004\u0003{\t#\u0001E*fe&\fGNV3sg&|g.V%E\u0003\u00151\u0018\r\\;f=!\u0001/hm\n7l5Y\u000e"
    )
  ScalaInlineInfo: length = 0x6D (unknown attribute)
   01 00 00 15 00 60 00 61 00 00 1C 00 52 00 00 55
   00 56 00 00 14 00 3E 00 00 41 00 42 00 00 5A 00
   5B 00 00 0D 00 1E 00 00 24 00 25 00 00 10 00 28
   00 00 2B 00 2C 00 00 12 00 2D 00 00 30 00 31 00
   00 16 00 43 00 00 47 00 48 00 00 32 00 1E 00 00
   19 00 43 00 00 4D 00 48 00 00 57 00 1E 00 00 3A
   00 1E 00 00 1B 00 43 00 00 51 00 48 00
  ScalaSig: length = 0x3 (unknown attribute)
   05 02 00
