Classfile /Users/mw/Projects/slang-braindump/.jar/jar8/assemble/slang-braindump/assemble/content/scala/xml/Null$.class
  Last modified May 29, 2022; size 7473 bytes
  SHA-256 checksum 5a3ece4793ae0fdd998492118fa540ee7998393a76a3be40ac07cb3e922547fd
  Compiled from "Null.scala"
public final class scala.xml.Null$ extends scala.xml.MetaData implements scala.Product
  minor version: 0
  major version: 52
  flags: (0x0031) ACC_PUBLIC, ACC_FINAL, ACC_SUPER
  this_class: #2                          // scala/xml/Null$
  super_class: #4                         // scala/xml/MetaData
  interfaces: 1, fields: 1, methods: 42, attributes: 3
Constant pool:
    #1 = Utf8               scala/xml/Null$
    #2 = Class              #1            // scala/xml/Null$
    #3 = Utf8               scala/xml/MetaData
    #4 = Class              #3            // scala/xml/MetaData
    #5 = Utf8               scala/Product
    #6 = Class              #5            // scala/Product
    #7 = Utf8               Null.scala
    #8 = Utf8               MODULE$
    #9 = Utf8               Lscala/xml/Null$;
   #10 = Utf8               <clinit>
   #11 = Utf8               ()V
   #12 = Utf8               <init>
   #13 = NameAndType        #12:#11       // "<init>":()V
   #14 = Methodref          #2.#13        // scala/xml/Null$."<init>":()V
   #15 = NameAndType        #8:#9         // MODULE$:Lscala/xml/Null$;
   #16 = Fieldref           #2.#15        // scala/xml/Null$.MODULE$:Lscala/xml/Null$;
   #17 = Utf8               $init$
   #18 = Utf8               (Lscala/Product;)V
   #19 = NameAndType        #17:#18       // $init$:(Lscala/Product;)V
   #20 = InterfaceMethodref #6.#19        // scala/Product.$init$:(Lscala/Product;)V
   #21 = Utf8               productElementName
   #22 = Utf8               (I)Ljava/lang/String;
   #23 = Utf8               n
   #24 = Utf8               productElementName$
   #25 = Utf8               (Lscala/Product;I)Ljava/lang/String;
   #26 = NameAndType        #24:#25       // productElementName$:(Lscala/Product;I)Ljava/lang/String;
   #27 = InterfaceMethodref #6.#26        // scala/Product.productElementName$:(Lscala/Product;I)Ljava/lang/String;
   #28 = Utf8               this
   #29 = Utf8               I
   #30 = Utf8               productElementNames
   #31 = Utf8               ()Lscala/collection/Iterator;
   #32 = Utf8               ()Lscala/collection/Iterator<Ljava/lang/String;>;
   #33 = Utf8               productElementNames$
   #34 = Utf8               (Lscala/Product;)Lscala/collection/Iterator;
   #35 = NameAndType        #33:#34       // productElementNames$:(Lscala/Product;)Lscala/collection/Iterator;
   #36 = InterfaceMethodref #6.#35        // scala/Product.productElementNames$:(Lscala/Product;)Lscala/collection/Iterator;
   #37 = Utf8               iterator
   #38 = Utf8               ()Lscala/collection/Iterator<Lscala/runtime/Nothing$;>;
   #39 = Utf8               scala/collection/Iterator$
   #40 = Class              #39           // scala/collection/Iterator$
   #41 = Utf8               Lscala/collection/Iterator$;
   #42 = NameAndType        #8:#41        // MODULE$:Lscala/collection/Iterator$;
   #43 = Fieldref           #40.#42       // scala/collection/Iterator$.MODULE$:Lscala/collection/Iterator$;
   #44 = Utf8               empty
   #45 = NameAndType        #44:#31       // empty:()Lscala/collection/Iterator;
   #46 = Methodref          #40.#45       // scala/collection/Iterator$.empty:()Lscala/collection/Iterator;
   #47 = Utf8               size
   #48 = Utf8               ()I
   #49 = Utf8               append
   #50 = Utf8               (Lscala/xml/MetaData;Lscala/xml/NamespaceBinding;)Lscala/xml/MetaData;
   #51 = Utf8               m
   #52 = Utf8               scope
   #53 = Utf8               Lscala/xml/MetaData;
   #54 = Utf8               Lscala/xml/NamespaceBinding;
   #55 = Utf8               append$default$2
   #56 = Utf8               ()Lscala/xml/NamespaceBinding;
   #57 = Utf8               scala/xml/TopScope$
   #58 = Class              #57           // scala/xml/TopScope$
   #59 = Utf8               Lscala/xml/TopScope$;
   #60 = NameAndType        #8:#59        // MODULE$:Lscala/xml/TopScope$;
   #61 = Fieldref           #58.#60       // scala/xml/TopScope$.MODULE$:Lscala/xml/TopScope$;
   #62 = Utf8               filter
   #63 = Utf8               (Lscala/Function1;)Lscala/xml/MetaData;
   #64 = Utf8               (Lscala/Function1<Lscala/xml/MetaData;Ljava/lang/Object;>;)Lscala/xml/MetaData;
   #65 = Utf8               f
   #66 = Utf8               Lscala/Function1;
   #67 = Utf8               copy
   #68 = Utf8               (Lscala/xml/MetaData;)Lscala/xml/MetaData;
   #69 = Utf8               next
   #70 = Utf8               getNamespace
   #71 = Utf8               (Lscala/xml/Node;)Lscala/runtime/Null$;
   #72 = Utf8               owner
   #73 = Utf8               Lscala/xml/Node;
   #74 = Utf8               hasNext
   #75 = Utf8               ()Z
   #76 = Utf8               ()Lscala/runtime/Null$;
   #77 = Utf8               key
   #78 = Utf8               value
   #79 = Utf8               isPrefixed
   #80 = Utf8               length
   #81 = Utf8               (I)I
   #82 = Utf8               i
   #83 = Utf8               strict_$eq$eq
   #84 = Utf8               (Lscala/xml/Equality;)Z
   #85 = Utf8               other
   #86 = NameAndType        #80:#48       // length:()I
   #87 = Methodref          #4.#86        // scala/xml/MetaData.length:()I
   #88 = Utf8               Lscala/xml/Equality;
   #89 = Utf8               scala/xml/Equality
   #90 = Class              #89           // scala/xml/Equality
   #91 = Utf8               basisForHashCode
   #92 = Utf8               ()Lscala/collection/Seq;
   #93 = Utf8               ()Lscala/collection/Seq<Ljava/lang/Object;>;
   #94 = Utf8               scala/package$
   #95 = Class              #94           // scala/package$
   #96 = Utf8               Lscala/package$;
   #97 = NameAndType        #8:#96        // MODULE$:Lscala/package$;
   #98 = Fieldref           #95.#97       // scala/package$.MODULE$:Lscala/package$;
   #99 = Utf8               Nil
  #100 = Utf8               ()Lscala/collection/immutable/Nil$;
  #101 = NameAndType        #99:#100      // Nil:()Lscala/collection/immutable/Nil$;
  #102 = Methodref          #95.#101      // scala/package$.Nil:()Lscala/collection/immutable/Nil$;
  #103 = Utf8               apply
  #104 = Utf8               (Ljava/lang/String;Lscala/xml/NamespaceBinding;Ljava/lang/String;)Lscala/runtime/Null$;
  #105 = Utf8               namespace
  #106 = Utf8               Ljava/lang/String;
  #107 = Utf8               (Ljava/lang/String;)Lscala/collection/Seq;
  #108 = Utf8               (Ljava/lang/String;)Lscala/collection/Seq<Lscala/xml/Node;>;
  #109 = Utf8               scala/xml/Utility$
  #110 = Class              #109          // scala/xml/Utility$
  #111 = Utf8               Lscala/xml/Utility$;
  #112 = NameAndType        #8:#111       // MODULE$:Lscala/xml/Utility$;
  #113 = Fieldref           #110.#112     // scala/xml/Utility$.MODULE$:Lscala/xml/Utility$;
  #114 = Utf8               scala/collection/StringOps$
  #115 = Class              #114          // scala/collection/StringOps$
  #116 = Utf8               Lscala/collection/StringOps$;
  #117 = NameAndType        #8:#116       // MODULE$:Lscala/collection/StringOps$;
  #118 = Fieldref           #115.#117     // scala/collection/StringOps$.MODULE$:Lscala/collection/StringOps$;
  #119 = Utf8               scala/Predef$
  #120 = Class              #119          // scala/Predef$
  #121 = Utf8               Lscala/Predef$;
  #122 = NameAndType        #8:#121       // MODULE$:Lscala/Predef$;
  #123 = Fieldref           #120.#122     // scala/Predef$.MODULE$:Lscala/Predef$;
  #124 = Utf8               augmentString
  #125 = Utf8               (Ljava/lang/String;)Ljava/lang/String;
  #126 = NameAndType        #124:#125     // augmentString:(Ljava/lang/String;)Ljava/lang/String;
  #127 = Methodref          #120.#126     // scala/Predef$.augmentString:(Ljava/lang/String;)Ljava/lang/String;
  #128 = Utf8               head$extension
  #129 = Utf8               (Ljava/lang/String;)C
  #130 = NameAndType        #128:#129     // head$extension:(Ljava/lang/String;)C
  #131 = Methodref          #115.#130     // scala/collection/StringOps$.head$extension:(Ljava/lang/String;)C
  #132 = Utf8               isNameStart
  #133 = Utf8               (C)Z
  #134 = NameAndType        #132:#133     // isNameStart:(C)Z
  #135 = Methodref          #110.#134     // scala/xml/Utility$.isNameStart:(C)Z
  #136 = Utf8               java/lang/IllegalArgumentException
  #137 = Class              #136          // java/lang/IllegalArgumentException
  #138 = Utf8               java/lang/StringBuilder
  #139 = Class              #138          // java/lang/StringBuilder
  #140 = Integer            51
  #141 = Utf8               (I)V
  #142 = NameAndType        #12:#141      // "<init>":(I)V
  #143 = Methodref          #139.#142     // java/lang/StringBuilder."<init>":(I)V
  #144 = Utf8               not a valid attribute name \'
  #145 = String             #144          // not a valid attribute name \'
  #146 = Utf8               (Ljava/lang/String;)Ljava/lang/StringBuilder;
  #147 = NameAndType        #49:#146      // append:(Ljava/lang/String;)Ljava/lang/StringBuilder;
  #148 = Methodref          #139.#147     // java/lang/StringBuilder.append:(Ljava/lang/String;)Ljava/lang/StringBuilder;
  #149 = Utf8               \', so can never match !
  #150 = String             #149          // \', so can never match !
  #151 = Utf8               toString
  #152 = Utf8               ()Ljava/lang/String;
  #153 = NameAndType        #151:#152     // toString:()Ljava/lang/String;
  #154 = Methodref          #139.#153     // java/lang/StringBuilder.toString:()Ljava/lang/String;
  #155 = Utf8               (Ljava/lang/String;)V
  #156 = NameAndType        #12:#155      // "<init>":(Ljava/lang/String;)V
  #157 = Methodref          #137.#156     // java/lang/IllegalArgumentException."<init>":(Ljava/lang/String;)V
  #158 = Utf8               toString1
  #159 = Utf8               (Lscala/collection/mutable/StringBuilder;)V
  #160 = Utf8               sb
  #161 = Utf8               Lscala/collection/mutable/StringBuilder;
  #162 = Utf8
  #163 = String             #162          //
  #164 = Utf8               buildString
  #165 = Utf8               (Lscala/collection/mutable/StringBuilder;)Lscala/collection/mutable/StringBuilder;
  #166 = Utf8               wellformed
  #167 = Utf8               (Lscala/xml/NamespaceBinding;)Z
  #168 = Utf8               remove
  #169 = Utf8               (Ljava/lang/String;)Lscala/xml/Null$;
  #170 = Utf8               (Ljava/lang/String;Lscala/xml/NamespaceBinding;Ljava/lang/String;)Lscala/xml/Null$;
  #171 = Utf8               productPrefix
  #172 = Utf8               Null
  #173 = String             #172          // Null
  #174 = Utf8               productArity
  #175 = Utf8               productElement
  #176 = Utf8               (I)Ljava/lang/Object;
  #177 = Utf8               x$1
  #178 = Utf8               scala/runtime/Statics
  #179 = Class              #178          // scala/runtime/Statics
  #180 = Utf8               ioobe
  #181 = NameAndType        #180:#176     // ioobe:(I)Ljava/lang/Object;
  #182 = Methodref          #179.#181     // scala/runtime/Statics.ioobe:(I)Ljava/lang/Object;
  #183 = Utf8               java/lang/Object
  #184 = Class              #183          // java/lang/Object
  #185 = Utf8               productIterator
  #186 = Utf8               ()Lscala/collection/Iterator<Ljava/lang/Object;>;
  #187 = Utf8               scala/runtime/ScalaRunTime$
  #188 = Class              #187          // scala/runtime/ScalaRunTime$
  #189 = Utf8               Lscala/runtime/ScalaRunTime$;
  #190 = NameAndType        #8:#189       // MODULE$:Lscala/runtime/ScalaRunTime$;
  #191 = Fieldref           #188.#190     // scala/runtime/ScalaRunTime$.MODULE$:Lscala/runtime/ScalaRunTime$;
  #192 = Utf8               typedProductIterator
  #193 = NameAndType        #192:#34      // typedProductIterator:(Lscala/Product;)Lscala/collection/Iterator;
  #194 = Methodref          #188.#193     // scala/runtime/ScalaRunTime$.typedProductIterator:(Lscala/Product;)Lscala/collection/Iterator;
  #195 = Utf8               writeReplace
  #196 = Utf8               ()Ljava/lang/Object;
  #197 = Utf8               scala/runtime/ModuleSerializationProxy
  #198 = Class              #197          // scala/runtime/ModuleSerializationProxy
  #199 = Utf8               (Ljava/lang/Class;)V
  #200 = NameAndType        #12:#199      // "<init>":(Ljava/lang/Class;)V
  #201 = Methodref          #198.#200     // scala/runtime/ModuleSerializationProxy."<init>":(Ljava/lang/Class;)V
  #202 = Utf8               (Ljava/lang/String;Lscala/xml/NamespaceBinding;Ljava/lang/String;)Lscala/xml/MetaData;
  #203 = NameAndType        #168:#170     // remove:(Ljava/lang/String;Lscala/xml/NamespaceBinding;Ljava/lang/String;)Lscala/xml/Null$;
  #204 = Methodref          #2.#203       // scala/xml/Null$.remove:(Ljava/lang/String;Lscala/xml/NamespaceBinding;Ljava/lang/String;)Lscala/xml/Null$;
  #205 = Utf8               (Ljava/lang/String;)Lscala/xml/MetaData;
  #206 = NameAndType        #168:#169     // remove:(Ljava/lang/String;)Lscala/xml/Null$;
  #207 = Methodref          #2.#206       // scala/xml/Null$.remove:(Ljava/lang/String;)Lscala/xml/Null$;
  #208 = Utf8               (Ljava/lang/String;Lscala/xml/NamespaceBinding;Ljava/lang/String;)Lscala/collection/Seq;
  #209 = Utf8               namespace_uri
  #210 = Utf8               scp
  #211 = Utf8               k
  #212 = NameAndType        #103:#104     // apply:(Ljava/lang/String;Lscala/xml/NamespaceBinding;Ljava/lang/String;)Lscala/runtime/Null$;
  #213 = Methodref          #2.#212       // scala/xml/Null$.apply:(Ljava/lang/String;Lscala/xml/NamespaceBinding;Ljava/lang/String;)Lscala/runtime/Null$;
  #214 = NameAndType        #78:#76       // value:()Lscala/runtime/Null$;
  #215 = Methodref          #2.#214       // scala/xml/Null$.value:()Lscala/runtime/Null$;
  #216 = NameAndType        #77:#76       // key:()Lscala/runtime/Null$;
  #217 = Methodref          #2.#216       // scala/xml/Null$.key:()Lscala/runtime/Null$;
  #218 = Utf8               ()Lscala/xml/MetaData;
  #219 = NameAndType        #69:#76       // next:()Lscala/runtime/Null$;
  #220 = Methodref          #2.#219       // scala/xml/Null$.next:()Lscala/runtime/Null$;
  #221 = Utf8               (Lscala/xml/Node;)Ljava/lang/String;
  #222 = NameAndType        #70:#71       // getNamespace:(Lscala/xml/Node;)Lscala/runtime/Null$;
  #223 = Methodref          #2.#222       // scala/xml/Null$.getNamespace:(Lscala/xml/Node;)Lscala/runtime/Null$;
  #224 = Utf8               (Lscala/Function1;)Ljava/lang/Object;
  #225 = Utf8               pred
  #226 = NameAndType        #62:#63       // filter:(Lscala/Function1;)Lscala/xml/MetaData;
  #227 = Methodref          #2.#226       // scala/xml/Null$.filter:(Lscala/Function1;)Lscala/xml/MetaData;
  #228 = Methodref          #4.#13        // scala/xml/MetaData."<init>":()V
  #229 = Utf8               Code
  #230 = Utf8               LineNumberTable
  #231 = Utf8               LocalVariableTable
  #232 = Utf8               MethodParameters
  #233 = Utf8               Signature
  #234 = Utf8               StackMapTable
  #235 = Utf8               SourceFile
  #236 = Utf8               ScalaInlineInfo
  #237 = Utf8               Scala
{
  public static final scala.xml.Null$ MODULE$;
    descriptor: Lscala/xml/Null$;
    flags: (0x0019) ACC_PUBLIC, ACC_STATIC, ACC_FINAL

  public static {};
    descriptor: ()V
    flags: (0x0009) ACC_PUBLIC, ACC_STATIC
    Code:
      stack=2, locals=0, args_size=0
         0: new           #2                  // class scala/xml/Null$
         3: dup
         4: invokespecial #14                 // Method "<init>":()V
         7: putstatic     #16                 // Field MODULE$:Lscala/xml/Null$;
        10: getstatic     #16                 // Field MODULE$:Lscala/xml/Null$;
        13: invokestatic  #20                 // InterfaceMethod scala/Product.$init$:(Lscala/Product;)V
        16: return
      LineNumberTable:
        line 27: 0

  public java.lang.String productElementName(int);
    descriptor: (I)Ljava/lang/String;
    flags: (0x0001) ACC_PUBLIC
    Code:
      stack=2, locals=2, args_size=2
         0: aload_0
         1: iload_1
         2: invokestatic  #27                 // InterfaceMethod scala/Product.productElementName$:(Lscala/Product;I)Ljava/lang/String;
         5: areturn
      LineNumberTable:
        line 27: 0
      LocalVariableTable:
        Start  Length  Slot  Name   Signature
            0       6     0  this   Lscala/xml/Null$;
            0       6     1     n   I
    MethodParameters:
      Name                           Flags
      n                              final

  public scala.collection.Iterator<java.lang.String> productElementNames();
    descriptor: ()Lscala/collection/Iterator;
    flags: (0x0001) ACC_PUBLIC
    Code:
      stack=1, locals=1, args_size=1
         0: aload_0
         1: invokestatic  #36                 // InterfaceMethod scala/Product.productElementNames$:(Lscala/Product;)Lscala/collection/Iterator;
         4: areturn
      LineNumberTable:
        line 27: 0
      LocalVariableTable:
        Start  Length  Slot  Name   Signature
            0       5     0  this   Lscala/xml/Null$;
    Signature: #32                          // ()Lscala/collection/Iterator<Ljava/lang/String;>;

  public scala.collection.Iterator<scala.runtime.Nothing$> iterator();
    descriptor: ()Lscala/collection/Iterator;
    flags: (0x0001) ACC_PUBLIC
    Code:
      stack=1, locals=1, args_size=1
         0: getstatic     #43                 // Field scala/collection/Iterator$.MODULE$:Lscala/collection/Iterator$;
         3: invokevirtual #46                 // Method scala/collection/Iterator$.empty:()Lscala/collection/Iterator;
         6: areturn
      LineNumberTable:
        line 28: 0
      LocalVariableTable:
        Start  Length  Slot  Name   Signature
            0       7     0  this   Lscala/xml/Null$;
    Signature: #38                          // ()Lscala/collection/Iterator<Lscala/runtime/Nothing$;>;

  public int size();
    descriptor: ()I
    flags: (0x0001) ACC_PUBLIC
    Code:
      stack=1, locals=1, args_size=1
         0: iconst_0
         1: ireturn
      LineNumberTable:
        line 29: 0
      LocalVariableTable:
        Start  Length  Slot  Name   Signature
            0       2     0  this   Lscala/xml/Null$;

  public scala.xml.MetaData append(scala.xml.MetaData, scala.xml.NamespaceBinding);
    descriptor: (Lscala/xml/MetaData;Lscala/xml/NamespaceBinding;)Lscala/xml/MetaData;
    flags: (0x0001) ACC_PUBLIC
    Code:
      stack=1, locals=3, args_size=3
         0: aload_1
         1: areturn
      LineNumberTable:
        line 30: 0
      LocalVariableTable:
        Start  Length  Slot  Name   Signature
            0       2     0  this   Lscala/xml/Null$;
            0       2     1     m   Lscala/xml/MetaData;
            0       2     2 scope   Lscala/xml/NamespaceBinding;
    MethodParameters:
      Name                           Flags
      m                              final
      scope                          final

  public scala.xml.NamespaceBinding append$default$2();
    descriptor: ()Lscala/xml/NamespaceBinding;
    flags: (0x0001) ACC_PUBLIC
    Code:
      stack=1, locals=1, args_size=1
         0: getstatic     #61                 // Field scala/xml/TopScope$.MODULE$:Lscala/xml/TopScope$;
         3: areturn
      LineNumberTable:
        line 30: 0
      LocalVariableTable:
        Start  Length  Slot  Name   Signature
            0       4     0  this   Lscala/xml/Null$;

  public scala.xml.MetaData filter(scala.Function1<scala.xml.MetaData, java.lang.Object>);
    descriptor: (Lscala/Function1;)Lscala/xml/MetaData;
    flags: (0x0001) ACC_PUBLIC
    Code:
      stack=1, locals=2, args_size=2
         0: aload_0
         1: areturn
      LineNumberTable:
        line 31: 0
      LocalVariableTable:
        Start  Length  Slot  Name   Signature
            0       2     0  this   Lscala/xml/Null$;
            0       2     1     f   Lscala/Function1;
    Signature: #64                          // (Lscala/Function1<Lscala/xml/MetaData;Ljava/lang/Object;>;)Lscala/xml/MetaData;
    MethodParameters:
      Name                           Flags
      f                              final

  public scala.xml.MetaData copy(scala.xml.MetaData);
    descriptor: (Lscala/xml/MetaData;)Lscala/xml/MetaData;
    flags: (0x0001) ACC_PUBLIC
    Code:
      stack=1, locals=2, args_size=2
         0: aload_1
         1: areturn
      LineNumberTable:
        line 33: 0
      LocalVariableTable:
        Start  Length  Slot  Name   Signature
            0       2     0  this   Lscala/xml/Null$;
            0       2     1  next   Lscala/xml/MetaData;
    MethodParameters:
      Name                           Flags
      next                           final

  public scala.runtime.Null$ getNamespace(scala.xml.Node);
    descriptor: (Lscala/xml/Node;)Lscala/runtime/Null$;
    flags: (0x0001) ACC_PUBLIC
    Code:
      stack=1, locals=2, args_size=2
         0: aconst_null
         1: areturn
      LineNumberTable:
        line 34: 0
      LocalVariableTable:
        Start  Length  Slot  Name   Signature
            0       2     0  this   Lscala/xml/Null$;
            0       2     1 owner   Lscala/xml/Node;
    MethodParameters:
      Name                           Flags
      owner                          final

  public boolean hasNext();
    descriptor: ()Z
    flags: (0x0001) ACC_PUBLIC
    Code:
      stack=1, locals=1, args_size=1
         0: iconst_0
         1: ireturn
      LineNumberTable:
        line 36: 0
      LocalVariableTable:
        Start  Length  Slot  Name   Signature
            0       2     0  this   Lscala/xml/Null$;

  public scala.runtime.Null$ next();
    descriptor: ()Lscala/runtime/Null$;
    flags: (0x0001) ACC_PUBLIC
    Code:
      stack=1, locals=1, args_size=1
         0: aconst_null
         1: areturn
      LineNumberTable:
        line 37: 0
      LocalVariableTable:
        Start  Length  Slot  Name   Signature
            0       2     0  this   Lscala/xml/Null$;

  public scala.runtime.Null$ key();
    descriptor: ()Lscala/runtime/Null$;
    flags: (0x0001) ACC_PUBLIC
    Code:
      stack=1, locals=1, args_size=1
         0: aconst_null
         1: areturn
      LineNumberTable:
        line 38: 0
      LocalVariableTable:
        Start  Length  Slot  Name   Signature
            0       2     0  this   Lscala/xml/Null$;

  public scala.runtime.Null$ value();
    descriptor: ()Lscala/runtime/Null$;
    flags: (0x0001) ACC_PUBLIC
    Code:
      stack=1, locals=1, args_size=1
         0: aconst_null
         1: areturn
      LineNumberTable:
        line 39: 0
      LocalVariableTable:
        Start  Length  Slot  Name   Signature
            0       2     0  this   Lscala/xml/Null$;

  public boolean isPrefixed();
    descriptor: ()Z
    flags: (0x0001) ACC_PUBLIC
    Code:
      stack=1, locals=1, args_size=1
         0: iconst_0
         1: ireturn
      LineNumberTable:
        line 40: 0
      LocalVariableTable:
        Start  Length  Slot  Name   Signature
            0       2     0  this   Lscala/xml/Null$;

  public int length();
    descriptor: ()I
    flags: (0x0001) ACC_PUBLIC
    Code:
      stack=1, locals=1, args_size=1
         0: iconst_0
         1: ireturn
      LineNumberTable:
        line 42: 0
      LocalVariableTable:
        Start  Length  Slot  Name   Signature
            0       2     0  this   Lscala/xml/Null$;

  public int length(int);
    descriptor: (I)I
    flags: (0x0001) ACC_PUBLIC
    Code:
      stack=1, locals=2, args_size=2
         0: iload_1
         1: ireturn
      LineNumberTable:
        line 43: 0
      LocalVariableTable:
        Start  Length  Slot  Name   Signature
            0       2     0  this   Lscala/xml/Null$;
            0       2     1     i   I
    MethodParameters:
      Name                           Flags
      i                              final

  public boolean strict_$eq$eq(scala.xml.Equality);
    descriptor: (Lscala/xml/Equality;)Z
    flags: (0x0001) ACC_PUBLIC
    Code:
      stack=2, locals=5, args_size=2
         0: aload_1
         1: astore_3
         2: aload_3
         3: instanceof    #4                  // class scala/xml/MetaData
         6: ifeq          33
         9: aload_3
        10: checkcast     #4                  // class scala/xml/MetaData
        13: astore        4
        15: aload         4
        17: invokevirtual #87                 // Method scala/xml/MetaData.length:()I
        20: iconst_0
        21: if_icmpne     28
        24: iconst_1
        25: goto          29
        28: iconst_0
        29: istore_2
        30: goto          41
        33: goto          36
        36: iconst_0
        37: istore_2
        38: goto          41
        41: iload_2
        42: ireturn
      StackMapTable: number_of_entries = 5
        frame_type = 254 /* append */
          offset_delta = 28
          locals = [ top, class scala/xml/Equality, class scala/xml/MetaData ]
        frame_type = 64 /* same_locals_1_stack_item */
          stack = [ int ]
        frame_type = 250 /* chop */
          offset_delta = 3
        frame_type = 2 /* same */
        frame_type = 255 /* full_frame */
          offset_delta = 4
          locals = [ class scala/xml/Null$, class scala/xml/Equality, int, class scala/xml/Equality ]
          stack = []
      LineNumberTable:
        line 45: 0
        line 46: 2
        line 47: 36
        line 45: 41
      LocalVariableTable:
        Start  Length  Slot  Name   Signature
            0      43     0  this   Lscala/xml/Null$;
            0      43     1 other   Lscala/xml/Equality;
    MethodParameters:
      Name                           Flags
      other                          final

  public scala.collection.Seq<java.lang.Object> basisForHashCode();
    descriptor: ()Lscala/collection/Seq;
    flags: (0x0001) ACC_PUBLIC
    Code:
      stack=1, locals=1, args_size=1
         0: getstatic     #98                 // Field scala/package$.MODULE$:Lscala/package$;
         3: invokevirtual #102                // Method scala/package$.Nil:()Lscala/collection/immutable/Nil$;
         6: areturn
      LineNumberTable:
        line 49: 0
      LocalVariableTable:
        Start  Length  Slot  Name   Signature
            0       7     0  this   Lscala/xml/Null$;
    Signature: #93                          // ()Lscala/collection/Seq<Ljava/lang/Object;>;

  public scala.runtime.Null$ apply(java.lang.String, scala.xml.NamespaceBinding, java.lang.String);
    descriptor: (Ljava/lang/String;Lscala/xml/NamespaceBinding;Ljava/lang/String;)Lscala/runtime/Null$;
    flags: (0x0001) ACC_PUBLIC
    Code:
      stack=1, locals=4, args_size=4
         0: aconst_null
         1: areturn
      LineNumberTable:
        line 51: 0
      LocalVariableTable:
        Start  Length  Slot  Name   Signature
            0       2     0  this   Lscala/xml/Null$;
            0       2     1 namespace   Ljava/lang/String;
            0       2     2 scope   Lscala/xml/NamespaceBinding;
            0       2     3   key   Ljava/lang/String;
    MethodParameters:
      Name                           Flags
      namespace                      final
      scope                          final
      key                            final

  public scala.collection.Seq<scala.xml.Node> apply(java.lang.String);
    descriptor: (Ljava/lang/String;)Lscala/collection/Seq;
    flags: (0x0001) ACC_PUBLIC
    Code:
      stack=5, locals=2, args_size=2
         0: getstatic     #113                // Field scala/xml/Utility$.MODULE$:Lscala/xml/Utility$;
         3: getstatic     #118                // Field scala/collection/StringOps$.MODULE$:Lscala/collection/StringOps$;
         6: getstatic     #123                // Field scala/Predef$.MODULE$:Lscala/Predef$;
         9: aload_1
        10: invokevirtual #127                // Method scala/Predef$.augmentString:(Ljava/lang/String;)Ljava/lang/String;
        13: invokevirtual #131                // Method scala/collection/StringOps$.head$extension:(Ljava/lang/String;)C
        16: invokevirtual #135                // Method scala/xml/Utility$.isNameStart:(C)Z
        19: ifeq          26
        22: aconst_null
        23: goto          60
        26: new           #137                // class java/lang/IllegalArgumentException
        29: dup
        30: new           #139                // class java/lang/StringBuilder
        33: dup
        34: ldc           #140                // int 51
        36: invokespecial #143                // Method java/lang/StringBuilder."<init>":(I)V
        39: ldc           #145                // String not a valid attribute name \'
        41: invokevirtual #148                // Method java/lang/StringBuilder.append:(Ljava/lang/String;)Ljava/lang/StringBuilder;
        44: aload_1
        45: invokevirtual #148                // Method java/lang/StringBuilder.append:(Ljava/lang/String;)Ljava/lang/StringBuilder;
        48: ldc           #150                // String \', so can never match !
        50: invokevirtual #148                // Method java/lang/StringBuilder.append:(Ljava/lang/String;)Ljava/lang/StringBuilder;
        53: invokevirtual #154                // Method java/lang/StringBuilder.toString:()Ljava/lang/String;
        56: invokespecial #157                // Method java/lang/IllegalArgumentException."<init>":(Ljava/lang/String;)V
        59: athrow
        60: areturn
      StackMapTable: number_of_entries = 2
        frame_type = 26 /* same */
        frame_type = 97 /* same_locals_1_stack_item */
          stack = [ null ]
      LineNumberTable:
        line 53: 0
        line 54: 26
      LocalVariableTable:
        Start  Length  Slot  Name   Signature
            0      61     0  this   Lscala/xml/Null$;
            0      61     1   key   Ljava/lang/String;
    Signature: #108                         // (Ljava/lang/String;)Lscala/collection/Seq<Lscala/xml/Node;>;
    MethodParameters:
      Name                           Flags
      key                            final

  public void toString1(scala.collection.mutable.StringBuilder);
    descriptor: (Lscala/collection/mutable/StringBuilder;)V
    flags: (0x0001) ACC_PUBLIC
    Code:
      stack=0, locals=2, args_size=2
         0: return
      LineNumberTable:
        line 56: 0
      LocalVariableTable:
        Start  Length  Slot  Name   Signature
            0       1     0  this   Lscala/xml/Null$;
            0       1     1    sb   Lscala/collection/mutable/StringBuilder;
    MethodParameters:
      Name                           Flags
      sb                             final

  public java.lang.String toString1();
    descriptor: ()Ljava/lang/String;
    flags: (0x0001) ACC_PUBLIC
    Code:
      stack=1, locals=1, args_size=1
         0: ldc           #163                // String
         2: areturn
      LineNumberTable:
        line 57: 0
      LocalVariableTable:
        Start  Length  Slot  Name   Signature
            0       3     0  this   Lscala/xml/Null$;

  public java.lang.String toString();
    descriptor: ()Ljava/lang/String;
    flags: (0x0001) ACC_PUBLIC
    Code:
      stack=1, locals=1, args_size=1
         0: ldc           #163                // String
         2: areturn
      LineNumberTable:
        line 59: 0
      LocalVariableTable:
        Start  Length  Slot  Name   Signature
            0       3     0  this   Lscala/xml/Null$;

  public scala.collection.mutable.StringBuilder buildString(scala.collection.mutable.StringBuilder);
    descriptor: (Lscala/collection/mutable/StringBuilder;)Lscala/collection/mutable/StringBuilder;
    flags: (0x0001) ACC_PUBLIC
    Code:
      stack=1, locals=2, args_size=2
         0: aload_1
         1: areturn
      LineNumberTable:
        line 61: 0
      LocalVariableTable:
        Start  Length  Slot  Name   Signature
            0       2     0  this   Lscala/xml/Null$;
            0       2     1    sb   Lscala/collection/mutable/StringBuilder;
    MethodParameters:
      Name                           Flags
      sb                             final

  public boolean wellformed(scala.xml.NamespaceBinding);
    descriptor: (Lscala/xml/NamespaceBinding;)Z
    flags: (0x0001) ACC_PUBLIC
    Code:
      stack=1, locals=2, args_size=2
         0: iconst_1
         1: ireturn
      LineNumberTable:
        line 63: 0
      LocalVariableTable:
        Start  Length  Slot  Name   Signature
            0       2     0  this   Lscala/xml/Null$;
            0       2     1 scope   Lscala/xml/NamespaceBinding;
    MethodParameters:
      Name                           Flags
      scope                          final

  public scala.xml.Null$ remove(java.lang.String);
    descriptor: (Ljava/lang/String;)Lscala/xml/Null$;
    flags: (0x0001) ACC_PUBLIC
    Code:
      stack=1, locals=2, args_size=2
         0: aload_0
         1: areturn
      LineNumberTable:
        line 65: 0
      LocalVariableTable:
        Start  Length  Slot  Name   Signature
            0       2     0  this   Lscala/xml/Null$;
            0       2     1   key   Ljava/lang/String;
    MethodParameters:
      Name                           Flags
      key                            final

  public scala.xml.Null$ remove(java.lang.String, scala.xml.NamespaceBinding, java.lang.String);
    descriptor: (Ljava/lang/String;Lscala/xml/NamespaceBinding;Ljava/lang/String;)Lscala/xml/Null$;
    flags: (0x0001) ACC_PUBLIC
    Code:
      stack=1, locals=4, args_size=4
         0: aload_0
         1: areturn
      LineNumberTable:
        line 66: 0
      LocalVariableTable:
        Start  Length  Slot  Name   Signature
            0       2     0  this   Lscala/xml/Null$;
            0       2     1 namespace   Ljava/lang/String;
            0       2     2 scope   Lscala/xml/NamespaceBinding;
            0       2     3   key   Ljava/lang/String;
    MethodParameters:
      Name                           Flags
      namespace                      final
      scope                          final
      key                            final

  public java.lang.String productPrefix();
    descriptor: ()Ljava/lang/String;
    flags: (0x0001) ACC_PUBLIC
    Code:
      stack=1, locals=1, args_size=1
         0: ldc           #173                // String Null
         2: areturn
      LineNumberTable:
        line 27: 0
      LocalVariableTable:
        Start  Length  Slot  Name   Signature
            0       3     0  this   Lscala/xml/Null$;

  public int productArity();
    descriptor: ()I
    flags: (0x0001) ACC_PUBLIC
    Code:
      stack=1, locals=1, args_size=1
         0: iconst_0
         1: ireturn
      LineNumberTable:
        line 27: 0
      LocalVariableTable:
        Start  Length  Slot  Name   Signature
            0       2     0  this   Lscala/xml/Null$;

  public java.lang.Object productElement(int);
    descriptor: (I)Ljava/lang/Object;
    flags: (0x0001) ACC_PUBLIC
    Code:
      stack=1, locals=4, args_size=2
         0: iload_1
         1: istore_3
         2: iload_1
         3: invokestatic  #182                // Method scala/runtime/Statics.ioobe:(I)Ljava/lang/Object;
         6: astore_2
         7: goto          10
        10: aload_2
        11: areturn
      StackMapTable: number_of_entries = 1
        frame_type = 253 /* append */
          offset_delta = 10
          locals = [ class java/lang/Object, int ]
      LineNumberTable:
        line 27: 0
      LocalVariableTable:
        Start  Length  Slot  Name   Signature
            0      12     0  this   Lscala/xml/Null$;
            0      12     1   x$1   I
    MethodParameters:
      Name                           Flags
      x$1                            final

  public scala.collection.Iterator<java.lang.Object> productIterator();
    descriptor: ()Lscala/collection/Iterator;
    flags: (0x0001) ACC_PUBLIC
    Code:
      stack=2, locals=1, args_size=1
         0: getstatic     #191                // Field scala/runtime/ScalaRunTime$.MODULE$:Lscala/runtime/ScalaRunTime$;
         3: aload_0
         4: invokevirtual #194                // Method scala/runtime/ScalaRunTime$.typedProductIterator:(Lscala/Product;)Lscala/collection/Iterator;
         7: areturn
      LineNumberTable:
        line 27: 0
      LocalVariableTable:
        Start  Length  Slot  Name   Signature
            0       8     0  this   Lscala/xml/Null$;
    Signature: #186                         // ()Lscala/collection/Iterator<Ljava/lang/Object;>;

  private java.lang.Object writeReplace();
    descriptor: ()Ljava/lang/Object;
    flags: (0x0002) ACC_PRIVATE
    Code:
      stack=3, locals=1, args_size=1
         0: new           #198                // class scala/runtime/ModuleSerializationProxy
         3: dup
         4: ldc           #2                  // class scala/xml/Null$
         6: invokespecial #201                // Method scala/runtime/ModuleSerializationProxy."<init>":(Ljava/lang/Class;)V
         9: areturn
      LineNumberTable:
        line 27: 0
      LocalVariableTable:
        Start  Length  Slot  Name   Signature
            0      10     0  this   Lscala/xml/Null$;

  public scala.xml.MetaData remove(java.lang.String, scala.xml.NamespaceBinding, java.lang.String);
    descriptor: (Ljava/lang/String;Lscala/xml/NamespaceBinding;Ljava/lang/String;)Lscala/xml/MetaData;
    flags: (0x1041) ACC_PUBLIC, ACC_BRIDGE, ACC_SYNTHETIC
    Code:
      stack=4, locals=4, args_size=4
         0: aload_0
         1: aload_1
         2: aload_2
         3: aload_3
         4: invokevirtual #204                // Method remove:(Ljava/lang/String;Lscala/xml/NamespaceBinding;Ljava/lang/String;)Lscala/xml/Null$;
         7: areturn
      LineNumberTable:
        line 27: 0
      LocalVariableTable:
        Start  Length  Slot  Name   Signature
            0       8     0  this   Lscala/xml/Null$;
            0       8     1 namespace   Ljava/lang/String;
            0       8     2 scope   Lscala/xml/NamespaceBinding;
            0       8     3   key   Ljava/lang/String;
    MethodParameters:
      Name                           Flags
      namespace                      final
      scope                          final
      key                            final

  public scala.xml.MetaData remove(java.lang.String);
    descriptor: (Ljava/lang/String;)Lscala/xml/MetaData;
    flags: (0x1041) ACC_PUBLIC, ACC_BRIDGE, ACC_SYNTHETIC
    Code:
      stack=2, locals=2, args_size=2
         0: aload_0
         1: aload_1
         2: invokevirtual #207                // Method remove:(Ljava/lang/String;)Lscala/xml/Null$;
         5: areturn
      LineNumberTable:
        line 27: 0
      LocalVariableTable:
        Start  Length  Slot  Name   Signature
            0       6     0  this   Lscala/xml/Null$;
            0       6     1   key   Ljava/lang/String;
    MethodParameters:
      Name                           Flags
      key                            final

  public scala.collection.Seq apply(java.lang.String, scala.xml.NamespaceBinding, java.lang.String);
    descriptor: (Ljava/lang/String;Lscala/xml/NamespaceBinding;Ljava/lang/String;)Lscala/collection/Seq;
    flags: (0x1041) ACC_PUBLIC, ACC_BRIDGE, ACC_SYNTHETIC
    Code:
      stack=4, locals=4, args_size=4
         0: aload_0
         1: aload_1
         2: aload_2
         3: aload_3
         4: invokevirtual #213                // Method apply:(Ljava/lang/String;Lscala/xml/NamespaceBinding;Ljava/lang/String;)Lscala/runtime/Null$;
         7: pop
         8: aconst_null
         9: areturn
      LineNumberTable:
        line 27: 0
      LocalVariableTable:
        Start  Length  Slot  Name   Signature
            0      10     0  this   Lscala/xml/Null$;
            0      10     1 namespace_uri   Ljava/lang/String;
            0      10     2   scp   Lscala/xml/NamespaceBinding;
            0      10     3     k   Ljava/lang/String;
    MethodParameters:
      Name                           Flags
      namespace_uri                  final
      scp                            final
      k                              final

  public scala.collection.Seq value();
    descriptor: ()Lscala/collection/Seq;
    flags: (0x1041) ACC_PUBLIC, ACC_BRIDGE, ACC_SYNTHETIC
    Code:
      stack=1, locals=1, args_size=1
         0: aload_0
         1: invokevirtual #215                // Method value:()Lscala/runtime/Null$;
         4: pop
         5: aconst_null
         6: areturn
      LineNumberTable:
        line 27: 0
      LocalVariableTable:
        Start  Length  Slot  Name   Signature
            0       7     0  this   Lscala/xml/Null$;

  public java.lang.String key();
    descriptor: ()Ljava/lang/String;
    flags: (0x1041) ACC_PUBLIC, ACC_BRIDGE, ACC_SYNTHETIC
    Code:
      stack=1, locals=1, args_size=1
         0: aload_0
         1: invokevirtual #217                // Method key:()Lscala/runtime/Null$;
         4: pop
         5: aconst_null
         6: areturn
      LineNumberTable:
        line 27: 0
      LocalVariableTable:
        Start  Length  Slot  Name   Signature
            0       7     0  this   Lscala/xml/Null$;

  public scala.xml.MetaData next();
    descriptor: ()Lscala/xml/MetaData;
    flags: (0x1041) ACC_PUBLIC, ACC_BRIDGE, ACC_SYNTHETIC
    Code:
      stack=1, locals=1, args_size=1
         0: aload_0
         1: invokevirtual #220                // Method next:()Lscala/runtime/Null$;
         4: pop
         5: aconst_null
         6: areturn
      LineNumberTable:
        line 27: 0
      LocalVariableTable:
        Start  Length  Slot  Name   Signature
            0       7     0  this   Lscala/xml/Null$;

  public java.lang.String getNamespace(scala.xml.Node);
    descriptor: (Lscala/xml/Node;)Ljava/lang/String;
    flags: (0x1041) ACC_PUBLIC, ACC_BRIDGE, ACC_SYNTHETIC
    Code:
      stack=2, locals=2, args_size=2
         0: aload_0
         1: aload_1
         2: invokevirtual #223                // Method getNamespace:(Lscala/xml/Node;)Lscala/runtime/Null$;
         5: pop
         6: aconst_null
         7: areturn
      LineNumberTable:
        line 27: 0
      LocalVariableTable:
        Start  Length  Slot  Name   Signature
            0       8     0  this   Lscala/xml/Null$;
            0       8     1 owner   Lscala/xml/Node;
    MethodParameters:
      Name                           Flags
      owner                          final

  public java.lang.Object filter(scala.Function1);
    descriptor: (Lscala/Function1;)Ljava/lang/Object;
    flags: (0x1041) ACC_PUBLIC, ACC_BRIDGE, ACC_SYNTHETIC
    Code:
      stack=2, locals=2, args_size=2
         0: aload_0
         1: aload_1
         2: invokevirtual #227                // Method filter:(Lscala/Function1;)Lscala/xml/MetaData;
         5: areturn
      LineNumberTable:
        line 27: 0
      LocalVariableTable:
        Start  Length  Slot  Name   Signature
            0       6     0  this   Lscala/xml/Null$;
            0       6     1  pred   Lscala/Function1;
    MethodParameters:
      Name                           Flags
      pred                           final

  private scala.xml.Null$();
    descriptor: ()V
    flags: (0x0002) ACC_PRIVATE
    Code:
      stack=1, locals=1, args_size=1
         0: aload_0
         1: invokespecial #228                // Method scala/xml/MetaData."<init>":()V
         4: return
      LineNumberTable:
        line 27: 0
      LocalVariableTable:
        Start  Length  Slot  Name   Signature
            0       5     0  this   Lscala/xml/Null$;
}
SourceFile: "Null.scala"
  ScalaInlineInfo: length = 0xD1 (unknown attribute)
   01 01 00 29 00 0C 00 0B 01 00 31 00 32 01 00 37
   00 38 01 00 67 00 6B 01 00 67 00 D0 01 00 67 00
   68 01 00 5B 00 5C 01 00 A4 00 A5 01 00 43 00 44
   01 00 3E 00 E0 01 00 3E 00 3F 01 00 46 00 DD 01
   00 46 00 47 01 00 4A 00 4B 01 00 4F 00 4B 01 00
   25 00 1F 01 00 4D 00 98 01 00 4D 00 4C 01 00 50
   00 30 01 00 50 00 51 01 00 45 00 4C 01 00 45 00
   DA 01 00 AE 00 30 01 00 AF 00 B0 01 00 15 00 16
   01 00 1E 00 1F 01 00 B9 00 1F 01 00 AB 00 98 01
   00 A8 00 CD 01 00 A8 00 A9 01 00 A8 00 CA 01 00
   A8 00 AA 01 00 2F 00 30 01 00 53 00 54 01 00 97
   00 98 01 00 9E 00 98 01 00 9E 00 9F 01 00 4E 00
   5C 01 00 4E 00 4C 01 00 A6 00 A7 01 00 C3 00 C4
   01
  Scala: length = 0x0 (unknown attribute)

