Classfile /Users/mw/Projects/slang-braindump/.jar/jar8/assemble/slang-braindump/assemble/content/scala/xml/Null.class
  Last modified May 29, 2022; size 25189 bytes
  SHA-256 checksum 8c22a1380d8dbb2be80df2762c34176ce277310cc4891e380df4a0368e0e21e5
  Compiled from "Null.scala"
public final class scala.xml.Null
  minor version: 0
  major version: 52
  flags: (0x0031) ACC_PUBLIC, ACC_FINAL, ACC_SUPER
  this_class: #2                          // scala/xml/Null
  super_class: #4                         // java/lang/Object
  interfaces: 0, fields: 0, methods: 155, attributes: 3
Constant pool:
    #1 = Utf8               scala/xml/Null
    #2 = Class              #1            // scala/xml/Null
    #3 = Utf8               java/lang/Object
    #4 = Class              #3            // java/lang/Object
    #5 = Utf8               Null.scala
    #6 = Utf8               Lscala/reflect/ScalaSignature;
    #7 = Utf8               bytes
    #8 = Utf8               \u0006\u0005\u00055v!B\u0011#\u0011\u0003;c!B\u0015#\u0011\u0003S\u0003\"\u0002 \u0002\t\u0003y\u0004\"\u0002!\u0002\t\u0003\n\u0005\"B&\u0002\t\u0003b\u0005\"\u0002)\u0002\t\u0003\n\u0006bB-\u0002#\u0003%\tA\u0017\u0005\u0006K\u0006!\tE\u001a\u0005\u0006_\u0006!\t\u0001\u001d\u0005\u0006g\u0006!\t\u0001\u001e\u0005\u0006y\u0006!\t% \u0005\u0006e\u0006!\tA \u0005\u0006\u007f\u0006!\tA \u0005\u0007\u0003\u0003\tA\u0011\u0001@\t\r\u0005\r\u0011\u0001\"\u0001~\u0011\u0019\t)!\u0001C!\u0019\"9\u0011QA\u0001\u0005B\u0005\u001d\u0001bBA\u0007\u0003\u0011\u0005\u0013q\u0002\u0005\b\u00037\tA\u0011KA\u000f\u0011\u001d\tY#\u0001C\u0001\u0003[Aq!a\u000b\u0002\t\u0003\t9\u0005C\u0004\u0002N\u0005!\t\"a\u0014\t\u000f\u00055\u0013\u0001\"\u0015\u0002d!9\u0011QM\u0001\u0005B\u0005\r\u0004bBA4\u0003\u0011\u0005\u0013\u0011\u000e\u0005\b\u0003[\nA\u0011IA8\u0011\u001d\t\u0019(\u0001C\u0001\u0003kBq!a\u001d\u0002\t\u0003\tI\bC\u0005\u0002\u0002\u0006\t\t\u0011\"\u0011\u0002\u0004\"A\u00111S\u0001\u0002\u0002\u0013\u0005A\nC\u0005\u0002\u0016\u0006\t\t\u0011\"\u0001\u0002\u0018\"I\u0011QT\u0001\u0002\u0002\u0013\u0005\u0013q\u0014\u0005\n\u0003G\u000b\u0011\u0011!C\u0005\u0003K\u000bAAT;mY*\u00111\u0005J\u0001\u0004q6d\'\"A\u0013\u0002\u000bM\u001c\u0017\r\\1\u0004\u0001A\u0011\u0001&A\u0007\u0002E\t!a*\u001e7m\'\u0011\t1F\f\u001a\u0011\u0005!b\u0013BA\u0017#\u0005!iU\r^1ECR\f\u0007CA\u00181\u001b\u0005!\u0013BA\u0019%\u0005\u001d\u0001&o\u001c3vGR\u0004\"aM\u001e\u000f\u0005QJdBA\u001b9\u001b\u00051$BA\u001c\'\u0003\u0019a$o\\8u}%\tQ%\u0003\u0002;I\u00059\u0001/Y2lC\u001e,\u0017B\u0001\u001f>\u00051\u0019VM]5bY&T\u0018M\u00197f\u0015\tQD%\u0001\u0004=S:LGO\u0010\u000b\u0002O\u0005A\u0011\u000e^3sCR|\'/F\u0001C!\r\u0019e\tS\u0007\u0002\t*\u0011Q\tJ\u0001\u000bG>dG.Z2uS>t\u0017BA$E\u0005!IE/\u001a:bi>\u0014\bCA\u0018J\u0013\tQEEA\u0004O_RD\u0017N\\4\u0002\tML\'0Z\u000b\u0002\u001bB\u0011qFT\u0005\u0003\u001f\u0012\u00121!\u00138u\u0003\u0019\t\u0007\u000f]3oIR\u00191F\u0015+\t\u000bM+\u0001\u0019A\u0016\u0002\u00035Dq!V\u0003\u0011\u0002\u0003\u0007a+A\u0003tG>\u0004X\r\u0005\u0002)/&\u0011\u0001L\t\u0002\u0011\u001d\u0006lWm\u001d9bG\u0016\u0014\u0015N\u001c3j]\u001e\f\u0001#\u00199qK:$G\u0005Z3gCVdG\u000f\n\u001a\u0016\u0003mS#A\u0016/,\u0003u\u0003\"AX2\u000e\u0003}S!\u0001Y1\u0002\u0013Ut7\r[3dW\u0016$\'B\u00012%\u0003)\tgN\\8uCRLwN\\\u0005\u0003I~\u0013\u0011#\u001e8dQ\u0016\u001c7.\u001a3WCJL\u0017M\\2f\u0003\u00191\u0017\u000e\u001c;feR\u00111f\u001a\u0005\u0006Q\u001e\u0001\r![\u0001\u0002MB!qF[\u0016m\u0013\tYGEA\u0005Gk:\u001cG/[8ocA\u0011q&\\\u0005\u0003]\u0012\u0012qAQ8pY\u0016\fg.\u0001\u0003d_BLHCA\u0016r\u0011\u0015\u0011\b\u00021\u0001,\u0003\u0011qW\r\u001f;\u0002\u0019\u001d,GOT1nKN\u0004\u0018mY3\u0015\u0005U<\bCA\u0018w\u0013\tIC\u0005C\u0003y\u0013\u0001\u0007\u00110A\u0003po:,\'\u000f\u0005\u0002)u&\u00111P\t\u0002\u0005\u001d>$W-A\u0004iCNtU\r\u001f;\u0016\u00031,\u0012!^\u0001\u0004W\u0016L\u0018!\u0002<bYV,\u0017AC5t!J,g-\u001b=fI\u00061A.\u001a8hi\"$2!TA\u0005\u0011\u0019\tY\u0001\u0005a\u0001\u001b\u0006\t\u0011.A\u0007tiJL7\r^0%KF$S-\u001d\u000b\u0004Y\u0006E\u0001bBA\n#\u0001\u0007\u0011QC\u0001\u0006_RDWM\u001d\t\u0004Q\u0005]\u0011bAA\rE\tAQ)];bY&$\u00180\u0001\tcCNL7OR8s\u0011\u0006\u001c\bnQ8eKV\u0011\u0011q\u0004\t\u0006\u0007\u0006\u0005\u0012QE\u0005\u0004\u0003G!%aA*fcB\u0019q&a\n\n\u0007\u0005%BEA\u0002B]f\fQ!\u00199qYf$r!^A\u0018\u0003\u0007\n)\u0005C\u0004\u00022M\u0001\r!a\r\u0002\u00139\fW.Z:qC\u000e,\u0007\u0003BA\u001b\u0003{qA!a\u000e\u0002:A\u0011Q\u0007J\u0005\u0004\u0003w!\u0013A\u0002)sK\u0012,g-\u0003\u0003\u0002@\u0005\u0005#AB*ue&twMC\u0002\u0002<\u0011BQ!V\nA\u0002YCaa`\nA\u0002\u0005MB\u0003BA%\u0003\u0017\u0002BaQA\u0011s\"1q\u0010\u0006a\u0001\u0003g\t\u0011\u0002^8TiJLgnZ\u0019\u0015\t\u0005E\u0013q\u000b\t\u0004_\u0005M\u0013bAA+I\t!QK\\5u\u0011\u001d\tI&\u0006a\u0001\u00037\n!a\u001d2\u0011\t\u0005u\u0013q\f\b\u0003_eJ1!!\u0019>\u00055\u0019FO]5oO\n+\u0018\u000e\u001c3feR\u0011\u00111G\u0001\ti>\u001cFO]5oO\u0006Y!-^5mIN#(/\u001b8h)\u0011\tY&a\u001b\t\u000f\u0005e\u0003\u00041\u0001\u0002\\\u0005Qq/\u001a7mM>\u0014X.\u001a3\u0015\u00071\f\t\bC\u0003V3\u0001\u0007a+\u0001\u0004sK6|g/\u001a\u000b\u0004O\u0005]\u0004BB@\u001b\u0001\u0004\t\u0019\u0004F\u0004(\u0003w\ni(a \t\u000f\u0005E2\u00041\u0001\u00024!)Qk\u0007a\u0001-\"1qp\u0007a\u0001\u0003g\tQ\u0002\u001d:pIV\u001cG\u000f\u0015:fM&DXCAAC!\u0011\t9)!%\u000e\u0005\u0005%%\u0002BAF\u0003\u001b\u000bA\u0001\\1oO*\u0011\u0011qR\u0001\u0005U\u00064\u0018-\u0003\u0003\u0002@\u0005%\u0015\u0001\u00049s_\u0012,8\r^!sSRL\u0018A\u00049s_\u0012,8\r^#mK6,g\u000e\u001e\u000b\u0005\u0003K\tI\n\u0003\u0005\u0002\u001cz\t\t\u00111\u0001N\u0003\rAH%M\u0001\u0010aJ|G-^2u\u0013R,\'/\u0019;peV\u0011\u0011\u0011\u0015\t\u0005\u0007\u001a\u000b)#\u0001\u0007xe&$XMU3qY\u0006\u001cW\r\u0006\u0002\u0002(B!\u0011qQAU\u0013\u0011\tY+!#\u0003\r=\u0013\'.Z2u\u0001
    #9 = Utf8               productIterator
   #10 = Utf8               ()Lscala/collection/Iterator;
   #11 = Utf8               ()Lscala/collection/Iterator<Ljava/lang/Object;>;
   #12 = Utf8               scala/xml/Null$
   #13 = Class              #12           // scala/xml/Null$
   #14 = Utf8               MODULE$
   #15 = Utf8               Lscala/xml/Null$;
   #16 = NameAndType        #14:#15       // MODULE$:Lscala/xml/Null$;
   #17 = Fieldref           #13.#16       // scala/xml/Null$.MODULE$:Lscala/xml/Null$;
   #18 = NameAndType        #9:#10        // productIterator:()Lscala/collection/Iterator;
   #19 = Methodref          #13.#18       // scala/xml/Null$.productIterator:()Lscala/collection/Iterator;
   #20 = Utf8               productElement
   #21 = Utf8               (I)Ljava/lang/Object;
   #22 = Utf8               x$1
   #23 = NameAndType        #20:#21       // productElement:(I)Ljava/lang/Object;
   #24 = Methodref          #13.#23       // scala/xml/Null$.productElement:(I)Ljava/lang/Object;
   #25 = Utf8               I
   #26 = Utf8               productArity
   #27 = Utf8               ()I
   #28 = NameAndType        #26:#27       // productArity:()I
   #29 = Methodref          #13.#28       // scala/xml/Null$.productArity:()I
   #30 = Utf8               productPrefix
   #31 = Utf8               ()Ljava/lang/String;
   #32 = NameAndType        #30:#31       // productPrefix:()Ljava/lang/String;
   #33 = Methodref          #13.#32       // scala/xml/Null$.productPrefix:()Ljava/lang/String;
   #34 = Utf8               remove
   #35 = Utf8               (Ljava/lang/String;Lscala/xml/NamespaceBinding;Ljava/lang/String;)Lscala/xml/Null$;
   #36 = Utf8               namespace
   #37 = Utf8               scope
   #38 = Utf8               key
   #39 = NameAndType        #34:#35       // remove:(Ljava/lang/String;Lscala/xml/NamespaceBinding;Ljava/lang/String;)Lscala/xml/Null$;
   #40 = Methodref          #13.#39       // scala/xml/Null$.remove:(Ljava/lang/String;Lscala/xml/NamespaceBinding;Ljava/lang/String;)Lscala/xml/Null$;
   #41 = Utf8               Ljava/lang/String;
   #42 = Utf8               Lscala/xml/NamespaceBinding;
   #43 = Utf8               (Ljava/lang/String;)Lscala/xml/Null$;
   #44 = NameAndType        #34:#43       // remove:(Ljava/lang/String;)Lscala/xml/Null$;
   #45 = Methodref          #13.#44       // scala/xml/Null$.remove:(Ljava/lang/String;)Lscala/xml/Null$;
   #46 = Utf8               wellformed
   #47 = Utf8               (Lscala/xml/NamespaceBinding;)Z
   #48 = NameAndType        #46:#47       // wellformed:(Lscala/xml/NamespaceBinding;)Z
   #49 = Methodref          #13.#48       // scala/xml/Null$.wellformed:(Lscala/xml/NamespaceBinding;)Z
   #50 = Utf8               buildString
   #51 = Utf8               (Lscala/collection/mutable/StringBuilder;)Lscala/collection/mutable/StringBuilder;
   #52 = Utf8               sb
   #53 = NameAndType        #50:#51       // buildString:(Lscala/collection/mutable/StringBuilder;)Lscala/collection/mutable/StringBuilder;
   #54 = Methodref          #13.#53       // scala/xml/Null$.buildString:(Lscala/collection/mutable/StringBuilder;)Lscala/collection/mutable/StringBuilder;
   #55 = Utf8               Lscala/collection/mutable/StringBuilder;
   #56 = Utf8               toString
   #57 = NameAndType        #56:#31       // toString:()Ljava/lang/String;
   #58 = Methodref          #13.#57       // scala/xml/Null$.toString:()Ljava/lang/String;
   #59 = Utf8               apply
   #60 = Utf8               (Ljava/lang/String;)Lscala/collection/Seq;
   #61 = Utf8               (Ljava/lang/String;)Lscala/collection/Seq<Lscala/xml/Node;>;
   #62 = NameAndType        #59:#60       // apply:(Ljava/lang/String;)Lscala/collection/Seq;
   #63 = Methodref          #13.#62       // scala/xml/Null$.apply:(Ljava/lang/String;)Lscala/collection/Seq;
   #64 = Utf8               (Ljava/lang/String;Lscala/xml/NamespaceBinding;Ljava/lang/String;)Lscala/runtime/Null$;
   #65 = NameAndType        #59:#64       // apply:(Ljava/lang/String;Lscala/xml/NamespaceBinding;Ljava/lang/String;)Lscala/runtime/Null$;
   #66 = Methodref          #13.#65       // scala/xml/Null$.apply:(Ljava/lang/String;Lscala/xml/NamespaceBinding;Ljava/lang/String;)Lscala/runtime/Null$;
   #67 = Utf8               strict_$eq$eq
   #68 = Utf8               (Lscala/xml/Equality;)Z
   #69 = Utf8               other
   #70 = NameAndType        #67:#68       // strict_$eq$eq:(Lscala/xml/Equality;)Z
   #71 = Methodref          #13.#70       // scala/xml/Null$.strict_$eq$eq:(Lscala/xml/Equality;)Z
   #72 = Utf8               Lscala/xml/Equality;
   #73 = Utf8               length
   #74 = Utf8               (I)I
   #75 = Utf8               i
   #76 = NameAndType        #73:#74       // length:(I)I
   #77 = Methodref          #13.#76       // scala/xml/Null$.length:(I)I
   #78 = NameAndType        #73:#27       // length:()I
   #79 = Methodref          #13.#78       // scala/xml/Null$.length:()I
   #80 = Utf8               isPrefixed
   #81 = Utf8               ()Z
   #82 = NameAndType        #80:#81       // isPrefixed:()Z
   #83 = Methodref          #13.#82       // scala/xml/Null$.isPrefixed:()Z
   #84 = Utf8               value
   #85 = Utf8               ()Lscala/runtime/Null$;
   #86 = NameAndType        #84:#85       // value:()Lscala/runtime/Null$;
   #87 = Methodref          #13.#86       // scala/xml/Null$.value:()Lscala/runtime/Null$;
   #88 = NameAndType        #38:#85       // key:()Lscala/runtime/Null$;
   #89 = Methodref          #13.#88       // scala/xml/Null$.key:()Lscala/runtime/Null$;
   #90 = Utf8               next
   #91 = NameAndType        #90:#85       // next:()Lscala/runtime/Null$;
   #92 = Methodref          #13.#91       // scala/xml/Null$.next:()Lscala/runtime/Null$;
   #93 = Utf8               hasNext
   #94 = NameAndType        #93:#81       // hasNext:()Z
   #95 = Methodref          #13.#94       // scala/xml/Null$.hasNext:()Z
   #96 = Utf8               getNamespace
   #97 = Utf8               (Lscala/xml/Node;)Lscala/runtime/Null$;
   #98 = Utf8               owner
   #99 = NameAndType        #96:#97       // getNamespace:(Lscala/xml/Node;)Lscala/runtime/Null$;
  #100 = Methodref          #13.#99       // scala/xml/Null$.getNamespace:(Lscala/xml/Node;)Lscala/runtime/Null$;
  #101 = Utf8               Lscala/xml/Node;
  #102 = Utf8               copy
  #103 = Utf8               (Lscala/xml/MetaData;)Lscala/xml/MetaData;
  #104 = NameAndType        #102:#103     // copy:(Lscala/xml/MetaData;)Lscala/xml/MetaData;
  #105 = Methodref          #13.#104      // scala/xml/Null$.copy:(Lscala/xml/MetaData;)Lscala/xml/MetaData;
  #106 = Utf8               Lscala/xml/MetaData;
  #107 = Utf8               filter
  #108 = Utf8               (Lscala/Function1;)Lscala/xml/MetaData;
  #109 = Utf8               (Lscala/Function1<Lscala/xml/MetaData;Ljava/lang/Object;>;)Lscala/xml/MetaData;
  #110 = Utf8               f
  #111 = NameAndType        #107:#108     // filter:(Lscala/Function1;)Lscala/xml/MetaData;
  #112 = Methodref          #13.#111      // scala/xml/Null$.filter:(Lscala/Function1;)Lscala/xml/MetaData;
  #113 = Utf8               Lscala/Function1;
  #114 = Utf8               append$default$2
  #115 = Utf8               ()Lscala/xml/NamespaceBinding;
  #116 = NameAndType        #114:#115     // append$default$2:()Lscala/xml/NamespaceBinding;
  #117 = Methodref          #13.#116      // scala/xml/Null$.append$default$2:()Lscala/xml/NamespaceBinding;
  #118 = Utf8               append
  #119 = Utf8               (Lscala/xml/MetaData;Lscala/xml/NamespaceBinding;)Lscala/xml/MetaData;
  #120 = Utf8               m
  #121 = NameAndType        #118:#119     // append:(Lscala/xml/MetaData;Lscala/xml/NamespaceBinding;)Lscala/xml/MetaData;
  #122 = Methodref          #13.#121      // scala/xml/Null$.append:(Lscala/xml/MetaData;Lscala/xml/NamespaceBinding;)Lscala/xml/MetaData;
  #123 = Utf8               size
  #124 = NameAndType        #123:#27      // size:()I
  #125 = Methodref          #13.#124      // scala/xml/Null$.size:()I
  #126 = Utf8               iterator
  #127 = Utf8               ()Lscala/collection/Iterator<Lscala/runtime/Nothing$;>;
  #128 = NameAndType        #126:#10      // iterator:()Lscala/collection/Iterator;
  #129 = Methodref          #13.#128      // scala/xml/Null$.iterator:()Lscala/collection/Iterator;
  #130 = Utf8               productElementNames
  #131 = Utf8               ()Lscala/collection/Iterator<Ljava/lang/String;>;
  #132 = NameAndType        #130:#10      // productElementNames:()Lscala/collection/Iterator;
  #133 = Methodref          #13.#132      // scala/xml/Null$.productElementNames:()Lscala/collection/Iterator;
  #134 = Utf8               productElementName
  #135 = Utf8               (I)Ljava/lang/String;
  #136 = Utf8               n
  #137 = NameAndType        #134:#135     // productElementName:(I)Ljava/lang/String;
  #138 = Methodref          #13.#137      // scala/xml/Null$.productElementName:(I)Ljava/lang/String;
  #139 = Utf8               (Ljava/lang/String;Lscala/xml/Node;Ljava/lang/String;)Lscala/xml/MetaData;
  #140 = NameAndType        #34:#139      // remove:(Ljava/lang/String;Lscala/xml/Node;Ljava/lang/String;)Lscala/xml/MetaData;
  #141 = Methodref          #13.#140      // scala/xml/Null$.remove:(Ljava/lang/String;Lscala/xml/Node;Ljava/lang/String;)Lscala/xml/MetaData;
  #142 = Utf8               get
  #143 = Utf8               (Ljava/lang/String;Lscala/xml/NamespaceBinding;Ljava/lang/String;)Lscala/Option;
  #144 = Utf8               (Ljava/lang/String;Lscala/xml/NamespaceBinding;Ljava/lang/String;)Lscala/Option<Lscala/collection/Seq<Lscala/xml/Node;>;>;
  #145 = Utf8               uri
  #146 = NameAndType        #142:#143     // get:(Ljava/lang/String;Lscala/xml/NamespaceBinding;Ljava/lang/String;)Lscala/Option;
  #147 = Methodref          #13.#146      // scala/xml/Null$.get:(Ljava/lang/String;Lscala/xml/NamespaceBinding;Ljava/lang/String;)Lscala/Option;
  #148 = Utf8               (Ljava/lang/String;Lscala/xml/Node;Ljava/lang/String;)Lscala/Option;
  #149 = Utf8               (Ljava/lang/String;Lscala/xml/Node;Ljava/lang/String;)Lscala/Option<Lscala/collection/Seq<Lscala/xml/Node;>;>;
  #150 = NameAndType        #142:#148     // get:(Ljava/lang/String;Lscala/xml/Node;Ljava/lang/String;)Lscala/Option;
  #151 = Methodref          #13.#150      // scala/xml/Null$.get:(Ljava/lang/String;Lscala/xml/Node;Ljava/lang/String;)Lscala/Option;
  #152 = Utf8               (Ljava/lang/String;)Lscala/Option;
  #153 = Utf8               (Ljava/lang/String;)Lscala/Option<Lscala/collection/Seq<Lscala/xml/Node;>;>;
  #154 = NameAndType        #142:#152     // get:(Ljava/lang/String;)Lscala/Option;
  #155 = Methodref          #13.#154      // scala/xml/Null$.get:(Ljava/lang/String;)Lscala/Option;
  #156 = Utf8               asAttrMap
  #157 = Utf8               ()Lscala/collection/immutable/Map;
  #158 = Utf8               ()Lscala/collection/immutable/Map<Ljava/lang/String;Ljava/lang/String;>;
  #159 = NameAndType        #156:#157     // asAttrMap:()Lscala/collection/immutable/Map;
  #160 = Methodref          #13.#159      // scala/xml/Null$.asAttrMap:()Lscala/collection/immutable/Map;
  #161 = Utf8               prefixedKey
  #162 = NameAndType        #161:#31      // prefixedKey:()Ljava/lang/String;
  #163 = Methodref          #13.#162      // scala/xml/Null$.prefixedKey:()Ljava/lang/String;
  #164 = Utf8               reverse
  #165 = Utf8               ()Lscala/xml/MetaData;
  #166 = NameAndType        #164:#165     // reverse:()Lscala/xml/MetaData;
  #167 = Methodref          #13.#166      // scala/xml/Null$.reverse:()Lscala/xml/MetaData;
  #168 = Utf8               canEqual
  #169 = Utf8               (Ljava/lang/Object;)Z
  #170 = NameAndType        #168:#169     // canEqual:(Ljava/lang/Object;)Z
  #171 = Methodref          #13.#170      // scala/xml/Null$.canEqual:(Ljava/lang/Object;)Z
  #172 = Utf8               Ljava/lang/Object;
  #173 = Utf8               (Ljava/lang/String;Lscala/xml/Node;Ljava/lang/String;)Lscala/collection/Seq;
  #174 = Utf8               (Ljava/lang/String;Lscala/xml/Node;Ljava/lang/String;)Lscala/collection/Seq<Lscala/xml/Node;>;
  #175 = Utf8               namespace_uri
  #176 = NameAndType        #59:#173      // apply:(Ljava/lang/String;Lscala/xml/Node;Ljava/lang/String;)Lscala/collection/Seq;
  #177 = Methodref          #13.#176      // scala/xml/Null$.apply:(Ljava/lang/String;Lscala/xml/Node;Ljava/lang/String;)Lscala/collection/Seq;
  #178 = Utf8               xml_$bang$eq
  #179 = NameAndType        #178:#169     // xml_$bang$eq:(Ljava/lang/Object;)Z
  #180 = Methodref          #13.#179      // scala/xml/Null$.xml_$bang$eq:(Ljava/lang/Object;)Z
  #181 = Utf8               xml_$eq$eq
  #182 = NameAndType        #181:#169     // xml_$eq$eq:(Ljava/lang/Object;)Z
  #183 = Methodref          #13.#182      // scala/xml/Null$.xml_$eq$eq:(Ljava/lang/Object;)Z
  #184 = Utf8               equals
  #185 = NameAndType        #184:#169     // equals:(Ljava/lang/Object;)Z
  #186 = Methodref          #13.#185      // scala/xml/Null$.equals:(Ljava/lang/Object;)Z
  #187 = Utf8               hashCode
  #188 = NameAndType        #187:#27      // hashCode:()I
  #189 = Methodref          #13.#188      // scala/xml/Null$.hashCode:()I
  #190 = Utf8               strict_$bang$eq
  #191 = NameAndType        #190:#68      // strict_$bang$eq:(Lscala/xml/Equality;)Z
  #192 = Methodref          #13.#191      // scala/xml/Null$.strict_$bang$eq:(Lscala/xml/Equality;)Z
  #193 = Utf8               lazyZip
  #194 = Utf8               (Lscala/collection/Iterable;)Lscala/collection/LazyZip2;
  #195 = Utf8               <B:Ljava/lang/Object;>(Lscala/collection/Iterable<TB;>;)Lscala/collection/LazyZip2<Lscala/xml/MetaData;TB;Lscala/xml/Null$;>;
  #196 = Utf8               that
  #197 = NameAndType        #193:#194     // lazyZip:(Lscala/collection/Iterable;)Lscala/collection/LazyZip2;
  #198 = Methodref          #13.#197      // scala/xml/Null$.lazyZip:(Lscala/collection/Iterable;)Lscala/collection/LazyZip2;
  #199 = Utf8               Lscala/collection/Iterable;
  #200 = Utf8               seq
  #201 = Utf8               ()Lscala/collection/Iterable;
  #202 = NameAndType        #200:#201     // seq:()Lscala/collection/Iterable;
  #203 = Methodref          #13.#202      // scala/xml/Null$.seq:()Lscala/collection/Iterable;
  #204 = Utf8               iterableFactory
  #205 = Utf8               ()Lscala/collection/IterableFactory;
  #206 = Utf8               ()Lscala/collection/IterableFactory<Lscala/collection/Iterable;>;
  #207 = NameAndType        #204:#205     // iterableFactory:()Lscala/collection/IterableFactory;
  #208 = Methodref          #13.#207      // scala/xml/Null$.iterableFactory:()Lscala/collection/IterableFactory;
  #209 = Utf8               toIterable
  #210 = NameAndType        #209:#201     // toIterable:()Lscala/collection/Iterable;
  #211 = Methodref          #13.#210      // scala/xml/Null$.toIterable:()Lscala/collection/Iterable;
  #212 = Utf8               empty
  #213 = Utf8               ()Lscala/collection/IterableOps;
  #214 = NameAndType        #212:#213     // empty:()Lscala/collection/IterableOps;
  #215 = Methodref          #13.#214      // scala/xml/Null$.empty:()Lscala/collection/IterableOps;
  #216 = Utf8               $plus$plus$colon
  #217 = Utf8               (Lscala/collection/IterableOnce;)Ljava/lang/Object;
  #218 = NameAndType        #216:#217     // $plus$plus$colon:(Lscala/collection/IterableOnce;)Ljava/lang/Object;
  #219 = Methodref          #13.#218      // scala/xml/Null$.$plus$plus$colon:(Lscala/collection/IterableOnce;)Ljava/lang/Object;
  #220 = Utf8               Lscala/collection/IterableOnce;
  #221 = Utf8               tapEach
  #222 = Utf8               (Lscala/Function1;)Ljava/lang/Object;
  #223 = NameAndType        #221:#222     // tapEach:(Lscala/Function1;)Ljava/lang/Object;
  #224 = Methodref          #13.#223      // scala/xml/Null$.tapEach:(Lscala/Function1;)Ljava/lang/Object;
  #225 = Utf8               inits
  #226 = Utf8               ()Lscala/collection/Iterator<Lscala/collection/Iterable<Lscala/xml/MetaData;>;>;
  #227 = NameAndType        #225:#10      // inits:()Lscala/collection/Iterator;
  #228 = Methodref          #13.#227      // scala/xml/Null$.inits:()Lscala/collection/Iterator;
  #229 = Utf8               tails
  #230 = NameAndType        #229:#10      // tails:()Lscala/collection/Iterator;
  #231 = Methodref          #13.#230      // scala/xml/Null$.tails:()Lscala/collection/Iterator;
  #232 = Utf8               unzip3
  #233 = Utf8               (Lscala/Function1;)Lscala/Tuple3;
  #234 = Utf8               <A1:Ljava/lang/Object;A2:Ljava/lang/Object;A3:Ljava/lang/Object;>(Lscala/Function1<Lscala/xml/MetaData;Lscala/Tuple3<TA1;TA2;TA3;>;>;)Lscala/Tuple3<Lscala/collection/Iterable<TA1;>;Lscala/collection/Iterable<TA2;>;Lscala/collection/Iterable<TA3;>;>;
  #235 = Utf8               asTriple
  #236 = NameAndType        #232:#233     // unzip3:(Lscala/Function1;)Lscala/Tuple3;
  #237 = Methodref          #13.#236      // scala/xml/Null$.unzip3:(Lscala/Function1;)Lscala/Tuple3;
  #238 = Utf8               unzip
  #239 = Utf8               (Lscala/Function1;)Lscala/Tuple2;
  #240 = Utf8               <A1:Ljava/lang/Object;A2:Ljava/lang/Object;>(Lscala/Function1<Lscala/xml/MetaData;Lscala/Tuple2<TA1;TA2;>;>;)Lscala/Tuple2<Lscala/collection/Iterable<TA1;>;Lscala/collection/Iterable<TA2;>;>;
  #241 = Utf8               asPair
  #242 = NameAndType        #238:#239     // unzip:(Lscala/Function1;)Lscala/Tuple2;
  #243 = Methodref          #13.#242      // scala/xml/Null$.unzip:(Lscala/Function1;)Lscala/Tuple2;
  #244 = Utf8               zipAll
  #245 = Utf8               (Lscala/collection/Iterable;Ljava/lang/Object;Ljava/lang/Object;)Ljava/lang/Object;
  #246 = Utf8               thisElem
  #247 = Utf8               thatElem
  #248 = NameAndType        #244:#245     // zipAll:(Lscala/collection/Iterable;Ljava/lang/Object;Ljava/lang/Object;)Ljava/lang/Object;
  #249 = Methodref          #13.#248      // scala/xml/Null$.zipAll:(Lscala/collection/Iterable;Ljava/lang/Object;Ljava/lang/Object;)Ljava/lang/Object;
  #250 = Utf8               zipWithIndex
  #251 = Utf8               ()Ljava/lang/Object;
  #252 = NameAndType        #250:#251     // zipWithIndex:()Ljava/lang/Object;
  #253 = Methodref          #13.#252      // scala/xml/Null$.zipWithIndex:()Ljava/lang/Object;
  #254 = Utf8               zip
  #255 = NameAndType        #254:#217     // zip:(Lscala/collection/IterableOnce;)Ljava/lang/Object;
  #256 = Methodref          #13.#255      // scala/xml/Null$.zip:(Lscala/collection/IterableOnce;)Ljava/lang/Object;
  #257 = Utf8               $plus$plus
  #258 = Utf8               suffix
  #259 = NameAndType        #257:#217     // $plus$plus:(Lscala/collection/IterableOnce;)Ljava/lang/Object;
  #260 = Methodref          #13.#259      // scala/xml/Null$.$plus$plus:(Lscala/collection/IterableOnce;)Ljava/lang/Object;
  #261 = Utf8               concat
  #262 = NameAndType        #261:#217     // concat:(Lscala/collection/IterableOnce;)Ljava/lang/Object;
  #263 = Methodref          #13.#262      // scala/xml/Null$.concat:(Lscala/collection/IterableOnce;)Ljava/lang/Object;
  #264 = Utf8               partitionMap
  #265 = Utf8               <A1:Ljava/lang/Object;A2:Ljava/lang/Object;>(Lscala/Function1<Lscala/xml/MetaData;Lscala/util/Either<TA1;TA2;>;>;)Lscala/Tuple2<Lscala/collection/Iterable<TA1;>;Lscala/collection/Iterable<TA2;>;>;
  #266 = NameAndType        #264:#239     // partitionMap:(Lscala/Function1;)Lscala/Tuple2;
  #267 = Methodref          #13.#266      // scala/xml/Null$.partitionMap:(Lscala/Function1;)Lscala/Tuple2;
  #268 = Utf8               collect
  #269 = Utf8               (Lscala/PartialFunction;)Ljava/lang/Object;
  #270 = Utf8               pf
  #271 = NameAndType        #268:#269     // collect:(Lscala/PartialFunction;)Ljava/lang/Object;
  #272 = Methodref          #13.#271      // scala/xml/Null$.collect:(Lscala/PartialFunction;)Ljava/lang/Object;
  #273 = Utf8               Lscala/PartialFunction;
  #274 = Utf8               flatten
  #275 = Utf8               asIterable
  #276 = NameAndType        #274:#222     // flatten:(Lscala/Function1;)Ljava/lang/Object;
  #277 = Methodref          #13.#276      // scala/xml/Null$.flatten:(Lscala/Function1;)Ljava/lang/Object;
  #278 = Utf8               flatMap
  #279 = NameAndType        #278:#222     // flatMap:(Lscala/Function1;)Ljava/lang/Object;
  #280 = Methodref          #13.#279      // scala/xml/Null$.flatMap:(Lscala/Function1;)Ljava/lang/Object;
  #281 = Utf8               map
  #282 = NameAndType        #281:#222     // map:(Lscala/Function1;)Ljava/lang/Object;
  #283 = Methodref          #13.#282      // scala/xml/Null$.map:(Lscala/Function1;)Ljava/lang/Object;
  #284 = Utf8               scanRight
  #285 = Utf8               (Ljava/lang/Object;Lscala/Function2;)Ljava/lang/Object;
  #286 = Utf8               z
  #287 = Utf8               op
  #288 = NameAndType        #284:#285     // scanRight:(Ljava/lang/Object;Lscala/Function2;)Ljava/lang/Object;
  #289 = Methodref          #13.#288      // scala/xml/Null$.scanRight:(Ljava/lang/Object;Lscala/Function2;)Ljava/lang/Object;
  #290 = Utf8               Lscala/Function2;
  #291 = Utf8               scanLeft
  #292 = NameAndType        #291:#285     // scanLeft:(Ljava/lang/Object;Lscala/Function2;)Ljava/lang/Object;
  #293 = Methodref          #13.#292      // scala/xml/Null$.scanLeft:(Ljava/lang/Object;Lscala/Function2;)Ljava/lang/Object;
  #294 = Utf8               scan
  #295 = NameAndType        #294:#285     // scan:(Ljava/lang/Object;Lscala/Function2;)Ljava/lang/Object;
  #296 = Methodref          #13.#295      // scala/xml/Null$.scan:(Ljava/lang/Object;Lscala/Function2;)Ljava/lang/Object;
  #297 = Utf8               groupMapReduce
  #298 = Utf8               (Lscala/Function1;Lscala/Function1;Lscala/Function2;)Lscala/collection/immutable/Map;
  #299 = Utf8               <K:Ljava/lang/Object;B:Ljava/lang/Object;>(Lscala/Function1<Lscala/xml/MetaData;TK;>;Lscala/Function1<Lscala/xml/MetaData;TB;>;Lscala/Function2<TB;TB;TB;>;)Lscala/collection/immutable/Map<TK;TB;>;
  #300 = Utf8               reduce
  #301 = NameAndType        #297:#298     // groupMapReduce:(Lscala/Function1;Lscala/Function1;Lscala/Function2;)Lscala/collection/immutable/Map;
  #302 = Methodref          #13.#301      // scala/xml/Null$.groupMapReduce:(Lscala/Function1;Lscala/Function1;Lscala/Function2;)Lscala/collection/immutable/Map;
  #303 = Utf8               groupMap
  #304 = Utf8               (Lscala/Function1;Lscala/Function1;)Lscala/collection/immutable/Map;
  #305 = Utf8               <K:Ljava/lang/Object;B:Ljava/lang/Object;>(Lscala/Function1<Lscala/xml/MetaData;TK;>;Lscala/Function1<Lscala/xml/MetaData;TB;>;)Lscala/collection/immutable/Map<TK;Lscala/collection/Iterable<TB;>;>;
  #306 = NameAndType        #303:#304     // groupMap:(Lscala/Function1;Lscala/Function1;)Lscala/collection/immutable/Map;
  #307 = Methodref          #13.#306      // scala/xml/Null$.groupMap:(Lscala/Function1;Lscala/Function1;)Lscala/collection/immutable/Map;
  #308 = Utf8               groupBy
  #309 = Utf8               (Lscala/Function1;)Lscala/collection/immutable/Map;
  #310 = Utf8               <K:Ljava/lang/Object;>(Lscala/Function1<Lscala/xml/MetaData;TK;>;)Lscala/collection/immutable/Map<TK;Lscala/collection/Iterable<Lscala/xml/MetaData;>;>;
  #311 = NameAndType        #308:#309     // groupBy:(Lscala/Function1;)Lscala/collection/immutable/Map;
  #312 = Methodref          #13.#311      // scala/xml/Null$.groupBy:(Lscala/Function1;)Lscala/collection/immutable/Map;
  #313 = Utf8               slice
  #314 = Utf8               (II)Ljava/lang/Object;
  #315 = Utf8               from
  #316 = Utf8               until
  #317 = NameAndType        #313:#314     // slice:(II)Ljava/lang/Object;
  #318 = Methodref          #13.#317      // scala/xml/Null$.slice:(II)Ljava/lang/Object;
  #319 = Utf8               init
  #320 = NameAndType        #319:#251     // init:()Ljava/lang/Object;
  #321 = Methodref          #13.#320      // scala/xml/Null$.init:()Ljava/lang/Object;
  #322 = Utf8               tail
  #323 = NameAndType        #322:#251     // tail:()Ljava/lang/Object;
  #324 = Methodref          #13.#323      // scala/xml/Null$.tail:()Ljava/lang/Object;
  #325 = Utf8               sliding
  #326 = Utf8               (II)Lscala/collection/Iterator;
  #327 = Utf8               (II)Lscala/collection/Iterator<Lscala/collection/Iterable<Lscala/xml/MetaData;>;>;
  #328 = Utf8               step
  #329 = NameAndType        #325:#326     // sliding:(II)Lscala/collection/Iterator;
  #330 = Methodref          #13.#329      // scala/xml/Null$.sliding:(II)Lscala/collection/Iterator;
  #331 = Utf8               (I)Lscala/collection/Iterator;
  #332 = Utf8               (I)Lscala/collection/Iterator<Lscala/collection/Iterable<Lscala/xml/MetaData;>;>;
  #333 = NameAndType        #325:#331     // sliding:(I)Lscala/collection/Iterator;
  #334 = Methodref          #13.#333      // scala/xml/Null$.sliding:(I)Lscala/collection/Iterator;
  #335 = Utf8               grouped
  #336 = NameAndType        #335:#331     // grouped:(I)Lscala/collection/Iterator;
  #337 = Methodref          #13.#336      // scala/xml/Null$.grouped:(I)Lscala/collection/Iterator;
  #338 = Utf8               dropWhile
  #339 = Utf8               p
  #340 = NameAndType        #338:#222     // dropWhile:(Lscala/Function1;)Ljava/lang/Object;
  #341 = Methodref          #13.#340      // scala/xml/Null$.dropWhile:(Lscala/Function1;)Ljava/lang/Object;
  #342 = Utf8               dropRight
  #343 = NameAndType        #342:#21      // dropRight:(I)Ljava/lang/Object;
  #344 = Methodref          #13.#343      // scala/xml/Null$.dropRight:(I)Ljava/lang/Object;
  #345 = Utf8               drop
  #346 = NameAndType        #345:#21      // drop:(I)Ljava/lang/Object;
  #347 = Methodref          #13.#346      // scala/xml/Null$.drop:(I)Ljava/lang/Object;
  #348 = Utf8               span
  #349 = Utf8               (Lscala/Function1<Lscala/xml/MetaData;Ljava/lang/Object;>;)Lscala/Tuple2<Lscala/collection/Iterable<Lscala/xml/MetaData;>;Lscala/collection/Iterable<Lscala/xml/MetaData;>;>;
  #350 = NameAndType        #348:#239     // span:(Lscala/Function1;)Lscala/Tuple2;
  #351 = Methodref          #13.#350      // scala/xml/Null$.span:(Lscala/Function1;)Lscala/Tuple2;
  #352 = Utf8               takeWhile
  #353 = NameAndType        #352:#222     // takeWhile:(Lscala/Function1;)Ljava/lang/Object;
  #354 = Methodref          #13.#353      // scala/xml/Null$.takeWhile:(Lscala/Function1;)Ljava/lang/Object;
  #355 = Utf8               takeRight
  #356 = NameAndType        #355:#21      // takeRight:(I)Ljava/lang/Object;
  #357 = Methodref          #13.#356      // scala/xml/Null$.takeRight:(I)Ljava/lang/Object;
  #358 = Utf8               take
  #359 = NameAndType        #358:#21      // take:(I)Ljava/lang/Object;
  #360 = Methodref          #13.#359      // scala/xml/Null$.take:(I)Ljava/lang/Object;
  #361 = Utf8               splitAt
  #362 = Utf8               (I)Lscala/Tuple2;
  #363 = Utf8               (I)Lscala/Tuple2<Lscala/collection/Iterable<Lscala/xml/MetaData;>;Lscala/collection/Iterable<Lscala/xml/MetaData;>;>;
  #364 = NameAndType        #361:#362     // splitAt:(I)Lscala/Tuple2;
  #365 = Methodref          #13.#364      // scala/xml/Null$.splitAt:(I)Lscala/Tuple2;
  #366 = Utf8               partition
  #367 = NameAndType        #366:#239     // partition:(Lscala/Function1;)Lscala/Tuple2;
  #368 = Methodref          #13.#367      // scala/xml/Null$.partition:(Lscala/Function1;)Lscala/Tuple2;
  #369 = Utf8               withFilter
  #370 = Utf8               (Lscala/Function1;)Lscala/collection/WithFilter;
  #371 = Utf8               (Lscala/Function1<Lscala/xml/MetaData;Ljava/lang/Object;>;)Lscala/collection/WithFilter<Lscala/xml/MetaData;Lscala/collection/Iterable;>;
  #372 = NameAndType        #369:#370     // withFilter:(Lscala/Function1;)Lscala/collection/WithFilter;
  #373 = Methodref          #13.#372      // scala/xml/Null$.withFilter:(Lscala/Function1;)Lscala/collection/WithFilter;
  #374 = Utf8               filterNot
  #375 = Utf8               pred
  #376 = NameAndType        #374:#222     // filterNot:(Lscala/Function1;)Ljava/lang/Object;
  #377 = Methodref          #13.#376      // scala/xml/Null$.filterNot:(Lscala/Function1;)Ljava/lang/Object;
  #378 = Utf8               transpose
  #379 = NameAndType        #378:#222     // transpose:(Lscala/Function1;)Ljava/lang/Object;
  #380 = Methodref          #13.#379      // scala/xml/Null$.transpose:(Lscala/Function1;)Ljava/lang/Object;
  #381 = Utf8               view
  #382 = Utf8               (II)Lscala/collection/View;
  #383 = Utf8               (II)Lscala/collection/View<Lscala/xml/MetaData;>;
  #384 = NameAndType        #381:#382     // view:(II)Lscala/collection/View;
  #385 = Methodref          #13.#384      // scala/xml/Null$.view:(II)Lscala/collection/View;
  #386 = Utf8               sizeCompare
  #387 = Utf8               (Lscala/collection/Iterable;)I
  #388 = Utf8               (Lscala/collection/Iterable<*>;)I
  #389 = NameAndType        #386:#387     // sizeCompare:(Lscala/collection/Iterable;)I
  #390 = Methodref          #13.#389      // scala/xml/Null$.sizeCompare:(Lscala/collection/Iterable;)I
  #391 = Utf8               sizeIs
  #392 = NameAndType        #391:#213     // sizeIs:()Lscala/collection/IterableOps;
  #393 = Methodref          #13.#392      // scala/xml/Null$.sizeIs:()Lscala/collection/IterableOps;
  #394 = Utf8               otherSize
  #395 = NameAndType        #386:#74      // sizeCompare:(I)I
  #396 = Methodref          #13.#395      // scala/xml/Null$.sizeCompare:(I)I
  #397 = Utf8               ()Lscala/collection/View;
  #398 = Utf8               ()Lscala/collection/View<Lscala/xml/MetaData;>;
  #399 = NameAndType        #381:#397     // view:()Lscala/collection/View;
  #400 = Methodref          #13.#399      // scala/xml/Null$.view:()Lscala/collection/View;
  #401 = Utf8               lastOption
  #402 = Utf8               ()Lscala/Option;
  #403 = Utf8               ()Lscala/Option<Lscala/xml/MetaData;>;
  #404 = NameAndType        #401:#402     // lastOption:()Lscala/Option;
  #405 = Methodref          #13.#404      // scala/xml/Null$.lastOption:()Lscala/Option;
  #406 = Utf8               last
  #407 = NameAndType        #406:#251     // last:()Ljava/lang/Object;
  #408 = Methodref          #13.#407      // scala/xml/Null$.last:()Ljava/lang/Object;
  #409 = Utf8               headOption
  #410 = NameAndType        #409:#402     // headOption:()Lscala/Option;
  #411 = Methodref          #13.#410      // scala/xml/Null$.headOption:()Lscala/Option;
  #412 = Utf8               head
  #413 = NameAndType        #412:#251     // head:()Ljava/lang/Object;
  #414 = Methodref          #13.#413      // scala/xml/Null$.head:()Ljava/lang/Object;
  #415 = Utf8               companion
  #416 = NameAndType        #415:#205     // companion:()Lscala/collection/IterableFactory;
  #417 = Methodref          #13.#416      // scala/xml/Null$.companion:()Lscala/collection/IterableFactory;
  #418 = Utf8               repr
  #419 = NameAndType        #418:#251     // repr:()Ljava/lang/Object;
  #420 = Methodref          #13.#419      // scala/xml/Null$.repr:()Ljava/lang/Object;
  #421 = Utf8               isTraversableAgain
  #422 = NameAndType        #421:#81      // isTraversableAgain:()Z
  #423 = Methodref          #13.#422      // scala/xml/Null$.isTraversableAgain:()Z
  #424 = Utf8               toTraversable
  #425 = Utf8               ()Lscala/collection/Iterable<Lscala/xml/MetaData;>;
  #426 = NameAndType        #424:#201     // toTraversable:()Lscala/collection/Iterable;
  #427 = Methodref          #13.#426      // scala/xml/Null$.toTraversable:()Lscala/collection/Iterable;
  #428 = Utf8               toArray
  #429 = Utf8               (Lscala/reflect/ClassTag;)Ljava/lang/Object;
  #430 = Utf8               evidence$2
  #431 = NameAndType        #428:#429     // toArray:(Lscala/reflect/ClassTag;)Ljava/lang/Object;
  #432 = Methodref          #13.#431      // scala/xml/Null$.toArray:(Lscala/reflect/ClassTag;)Ljava/lang/Object;
  #433 = Utf8               Lscala/reflect/ClassTag;
  #434 = Utf8               toBuffer
  #435 = Utf8               ()Lscala/collection/mutable/Buffer;
  #436 = Utf8               <B:Ljava/lang/Object;>()Lscala/collection/mutable/Buffer<TB;>;
  #437 = NameAndType        #434:#435     // toBuffer:()Lscala/collection/mutable/Buffer;
  #438 = Methodref          #13.#437      // scala/xml/Null$.toBuffer:()Lscala/collection/mutable/Buffer;
  #439 = Utf8               toStream
  #440 = Utf8               ()Lscala/collection/immutable/Stream;
  #441 = Utf8               ()Lscala/collection/immutable/Stream<Lscala/xml/MetaData;>;
  #442 = NameAndType        #439:#440     // toStream:()Lscala/collection/immutable/Stream;
  #443 = Methodref          #13.#442      // scala/xml/Null$.toStream:()Lscala/collection/immutable/Stream;
  #444 = Utf8               toIndexedSeq
  #445 = Utf8               ()Lscala/collection/immutable/IndexedSeq;
  #446 = Utf8               ()Lscala/collection/immutable/IndexedSeq<Lscala/xml/MetaData;>;
  #447 = NameAndType        #444:#445     // toIndexedSeq:()Lscala/collection/immutable/IndexedSeq;
  #448 = Methodref          #13.#447      // scala/xml/Null$.toIndexedSeq:()Lscala/collection/immutable/IndexedSeq;
  #449 = Utf8               toSeq
  #450 = Utf8               ()Lscala/collection/immutable/Seq;
  #451 = Utf8               ()Lscala/collection/immutable/Seq<Lscala/xml/MetaData;>;
  #452 = NameAndType        #449:#450     // toSeq:()Lscala/collection/immutable/Seq;
  #453 = Methodref          #13.#452      // scala/xml/Null$.toSeq:()Lscala/collection/immutable/Seq;
  #454 = Utf8               toSet
  #455 = Utf8               ()Lscala/collection/immutable/Set;
  #456 = Utf8               <B:Ljava/lang/Object;>()Lscala/collection/immutable/Set<TB;>;
  #457 = NameAndType        #454:#455     // toSet:()Lscala/collection/immutable/Set;
  #458 = Methodref          #13.#457      // scala/xml/Null$.toSet:()Lscala/collection/immutable/Set;
  #459 = Utf8               toMap
  #460 = Utf8               (Lscala/$less$colon$less;)Lscala/collection/immutable/Map;
  #461 = Utf8               <K:Ljava/lang/Object;V:Ljava/lang/Object;>(Lscala/$less$colon$less<Lscala/xml/MetaData;Lscala/Tuple2<TK;TV;>;>;)Lscala/collection/immutable/Map<TK;TV;>;
  #462 = Utf8               ev
  #463 = NameAndType        #459:#460     // toMap:(Lscala/$less$colon$less;)Lscala/collection/immutable/Map;
  #464 = Methodref          #13.#463      // scala/xml/Null$.toMap:(Lscala/$less$colon$less;)Lscala/collection/immutable/Map;
  #465 = Utf8               Lscala/$less$colon$less;
  #466 = Utf8               toVector
  #467 = Utf8               ()Lscala/collection/immutable/Vector;
  #468 = Utf8               ()Lscala/collection/immutable/Vector<Lscala/xml/MetaData;>;
  #469 = NameAndType        #466:#467     // toVector:()Lscala/collection/immutable/Vector;
  #470 = Methodref          #13.#469      // scala/xml/Null$.toVector:()Lscala/collection/immutable/Vector;
  #471 = Utf8               toList
  #472 = Utf8               ()Lscala/collection/immutable/List;
  #473 = Utf8               ()Lscala/collection/immutable/List<Lscala/xml/MetaData;>;
  #474 = NameAndType        #471:#472     // toList:()Lscala/collection/immutable/List;
  #475 = Methodref          #13.#474      // scala/xml/Null$.toList:()Lscala/collection/immutable/List;
  #476 = Utf8               toIterator
  #477 = Utf8               ()Lscala/collection/Iterator<Lscala/xml/MetaData;>;
  #478 = NameAndType        #476:#10      // toIterator:()Lscala/collection/Iterator;
  #479 = Methodref          #13.#478      // scala/xml/Null$.toIterator:()Lscala/collection/Iterator;
  #480 = Utf8               to
  #481 = Utf8               (Lscala/collection/Factory;)Ljava/lang/Object;
  #482 = Utf8               <C1:Ljava/lang/Object;>(Lscala/collection/Factory<Lscala/xml/MetaData;TC1;>;)TC1;
  #483 = Utf8               factory
  #484 = NameAndType        #480:#481     // to:(Lscala/collection/Factory;)Ljava/lang/Object;
  #485 = Methodref          #13.#484      // scala/xml/Null$.to:(Lscala/collection/Factory;)Ljava/lang/Object;
  #486 = Utf8               Lscala/collection/Factory;
  #487 = Utf8               addString
  #488 = Utf8               b
  #489 = NameAndType        #487:#51      // addString:(Lscala/collection/mutable/StringBuilder;)Lscala/collection/mutable/StringBuilder;
  #490 = Methodref          #13.#489      // scala/xml/Null$.addString:(Lscala/collection/mutable/StringBuilder;)Lscala/collection/mutable/StringBuilder;
  #491 = Utf8               (Lscala/collection/mutable/StringBuilder;Ljava/lang/String;)Lscala/collection/mutable/StringBuilder;
  #492 = Utf8               sep
  #493 = NameAndType        #487:#491     // addString:(Lscala/collection/mutable/StringBuilder;Ljava/lang/String;)Lscala/collection/mutable/StringBuilder;
  #494 = Methodref          #13.#493      // scala/xml/Null$.addString:(Lscala/collection/mutable/StringBuilder;Ljava/lang/String;)Lscala/collection/mutable/StringBuilder;
  #495 = Utf8               (Lscala/collection/mutable/StringBuilder;Ljava/lang/String;Ljava/lang/String;Ljava/lang/String;)Lscala/collection/mutable/StringBuilder;
  #496 = Utf8               start
  #497 = Utf8               end
  #498 = NameAndType        #487:#495     // addString:(Lscala/collection/mutable/StringBuilder;Ljava/lang/String;Ljava/lang/String;Ljava/lang/String;)Lscala/collection/mutable/StringBuilder;
  #499 = Methodref          #13.#498      // scala/xml/Null$.addString:(Lscala/collection/mutable/StringBuilder;Ljava/lang/String;Ljava/lang/String;Ljava/lang/String;)Lscala/collection/mutable/StringBuilder;
  #500 = Utf8               mkString
  #501 = NameAndType        #500:#31      // mkString:()Ljava/lang/String;
  #502 = Methodref          #13.#501      // scala/xml/Null$.mkString:()Ljava/lang/String;
  #503 = Utf8               (Ljava/lang/String;)Ljava/lang/String;
  #504 = NameAndType        #500:#503     // mkString:(Ljava/lang/String;)Ljava/lang/String;
  #505 = Methodref          #13.#504      // scala/xml/Null$.mkString:(Ljava/lang/String;)Ljava/lang/String;
  #506 = Utf8               (Ljava/lang/String;Ljava/lang/String;Ljava/lang/String;)Ljava/lang/String;
  #507 = NameAndType        #500:#506     // mkString:(Ljava/lang/String;Ljava/lang/String;Ljava/lang/String;)Ljava/lang/String;
  #508 = Methodref          #13.#507      // scala/xml/Null$.mkString:(Ljava/lang/String;Ljava/lang/String;Ljava/lang/String;)Ljava/lang/String;
  #509 = Utf8               corresponds
  #510 = Utf8               (Lscala/collection/IterableOnce;Lscala/Function2;)Z
  #511 = Utf8               <B:Ljava/lang/Object;>(Lscala/collection/IterableOnce<TB;>;Lscala/Function2<Lscala/xml/MetaData;TB;Ljava/lang/Object;>;)Z
  #512 = NameAndType        #509:#510     // corresponds:(Lscala/collection/IterableOnce;Lscala/Function2;)Z
  #513 = Methodref          #13.#512      // scala/xml/Null$.corresponds:(Lscala/collection/IterableOnce;Lscala/Function2;)Z
  #514 = Utf8               aggregate
  #515 = Utf8               (Lscala/Function0;Lscala/Function2;Lscala/Function2;)Ljava/lang/Object;
  #516 = Utf8               <B:Ljava/lang/Object;>(Lscala/Function0<TB;>;Lscala/Function2<TB;Lscala/xml/MetaData;TB;>;Lscala/Function2<TB;TB;TB;>;)TB;
  #517 = Utf8               seqop
  #518 = Utf8               combop
  #519 = NameAndType        #514:#515     // aggregate:(Lscala/Function0;Lscala/Function2;Lscala/Function2;)Ljava/lang/Object;
  #520 = Methodref          #13.#519      // scala/xml/Null$.aggregate:(Lscala/Function0;Lscala/Function2;Lscala/Function2;)Ljava/lang/Object;
  #521 = Utf8               Lscala/Function0;
  #522 = Utf8               collectFirst
  #523 = Utf8               (Lscala/PartialFunction;)Lscala/Option;
  #524 = Utf8               <B:Ljava/lang/Object;>(Lscala/PartialFunction<Lscala/xml/MetaData;TB;>;)Lscala/Option<TB;>;
  #525 = NameAndType        #522:#523     // collectFirst:(Lscala/PartialFunction;)Lscala/Option;
  #526 = Methodref          #13.#525      // scala/xml/Null$.collectFirst:(Lscala/PartialFunction;)Lscala/Option;
  #527 = Utf8               minByOption
  #528 = Utf8               (Lscala/Function1;Lscala/math/Ordering;)Lscala/Option;
  #529 = Utf8               <B:Ljava/lang/Object;>(Lscala/Function1<Lscala/xml/MetaData;TB;>;Lscala/math/Ordering<TB;>;)Lscala/Option<Lscala/xml/MetaData;>;
  #530 = Utf8               cmp
  #531 = NameAndType        #527:#528     // minByOption:(Lscala/Function1;Lscala/math/Ordering;)Lscala/Option;
  #532 = Methodref          #13.#531      // scala/xml/Null$.minByOption:(Lscala/Function1;Lscala/math/Ordering;)Lscala/Option;
  #533 = Utf8               Lscala/math/Ordering;
  #534 = Utf8               minBy
  #535 = Utf8               (Lscala/Function1;Lscala/math/Ordering;)Ljava/lang/Object;
  #536 = NameAndType        #534:#535     // minBy:(Lscala/Function1;Lscala/math/Ordering;)Ljava/lang/Object;
  #537 = Methodref          #13.#536      // scala/xml/Null$.minBy:(Lscala/Function1;Lscala/math/Ordering;)Ljava/lang/Object;
  #538 = Utf8               maxByOption
  #539 = NameAndType        #538:#528     // maxByOption:(Lscala/Function1;Lscala/math/Ordering;)Lscala/Option;
  #540 = Methodref          #13.#539      // scala/xml/Null$.maxByOption:(Lscala/Function1;Lscala/math/Ordering;)Lscala/Option;
  #541 = Utf8               maxBy
  #542 = NameAndType        #541:#535     // maxBy:(Lscala/Function1;Lscala/math/Ordering;)Ljava/lang/Object;
  #543 = Methodref          #13.#542      // scala/xml/Null$.maxBy:(Lscala/Function1;Lscala/math/Ordering;)Ljava/lang/Object;
  #544 = Utf8               maxOption
  #545 = Utf8               (Lscala/math/Ordering;)Lscala/Option;
  #546 = Utf8               <B:Ljava/lang/Object;>(Lscala/math/Ordering<TB;>;)Lscala/Option<Lscala/xml/MetaData;>;
  #547 = Utf8               ord
  #548 = NameAndType        #544:#545     // maxOption:(Lscala/math/Ordering;)Lscala/Option;
  #549 = Methodref          #13.#548      // scala/xml/Null$.maxOption:(Lscala/math/Ordering;)Lscala/Option;
  #550 = Utf8               max
  #551 = Utf8               (Lscala/math/Ordering;)Ljava/lang/Object;
  #552 = NameAndType        #550:#551     // max:(Lscala/math/Ordering;)Ljava/lang/Object;
  #553 = Methodref          #13.#552      // scala/xml/Null$.max:(Lscala/math/Ordering;)Ljava/lang/Object;
  #554 = Utf8               minOption
  #555 = NameAndType        #554:#545     // minOption:(Lscala/math/Ordering;)Lscala/Option;
  #556 = Methodref          #13.#555      // scala/xml/Null$.minOption:(Lscala/math/Ordering;)Lscala/Option;
  #557 = Utf8               min
  #558 = NameAndType        #557:#551     // min:(Lscala/math/Ordering;)Ljava/lang/Object;
  #559 = Methodref          #13.#558      // scala/xml/Null$.min:(Lscala/math/Ordering;)Ljava/lang/Object;
  #560 = Utf8               product
  #561 = Utf8               (Lscala/math/Numeric;)Ljava/lang/Object;
  #562 = Utf8               <B:Ljava/lang/Object;>(Lscala/math/Numeric<TB;>;)TB;
  #563 = Utf8               num
  #564 = NameAndType        #560:#561     // product:(Lscala/math/Numeric;)Ljava/lang/Object;
  #565 = Methodref          #13.#564      // scala/xml/Null$.product:(Lscala/math/Numeric;)Ljava/lang/Object;
  #566 = Utf8               Lscala/math/Numeric;
  #567 = Utf8               sum
  #568 = NameAndType        #567:#561     // sum:(Lscala/math/Numeric;)Ljava/lang/Object;
  #569 = Methodref          #13.#568      // scala/xml/Null$.sum:(Lscala/math/Numeric;)Ljava/lang/Object;
  #570 = Utf8               copyToArray
  #571 = Utf8               (Ljava/lang/Object;II)I
  #572 = Utf8               <B:Ljava/lang/Object;>(Ljava/lang/Object;II)I
  #573 = Utf8               xs
  #574 = Utf8               len
  #575 = NameAndType        #570:#571     // copyToArray:(Ljava/lang/Object;II)I
  #576 = Methodref          #13.#575      // scala/xml/Null$.copyToArray:(Ljava/lang/Object;II)I
  #577 = Utf8               (Ljava/lang/Object;I)I
  #578 = Utf8               <B:Ljava/lang/Object;>(Ljava/lang/Object;I)I
  #579 = NameAndType        #570:#577     // copyToArray:(Ljava/lang/Object;I)I
  #580 = Methodref          #13.#579      // scala/xml/Null$.copyToArray:(Ljava/lang/Object;I)I
  #581 = Utf8               (Ljava/lang/Object;)I
  #582 = Utf8               <B:Ljava/lang/Object;>(Ljava/lang/Object;)I
  #583 = NameAndType        #570:#581     // copyToArray:(Ljava/lang/Object;)I
  #584 = Methodref          #13.#583      // scala/xml/Null$.copyToArray:(Ljava/lang/Object;)I
  #585 = Utf8               copyToBuffer
  #586 = Utf8               (Lscala/collection/mutable/Buffer;)V
  #587 = Utf8               <B:Ljava/lang/Object;>(Lscala/collection/mutable/Buffer<TB;>;)V
  #588 = Utf8               dest
  #589 = NameAndType        #585:#586     // copyToBuffer:(Lscala/collection/mutable/Buffer;)V
  #590 = Methodref          #13.#589      // scala/xml/Null$.copyToBuffer:(Lscala/collection/mutable/Buffer;)V
  #591 = Utf8               Lscala/collection/mutable/Buffer;
  #592 = Utf8               nonEmpty
  #593 = NameAndType        #592:#81      // nonEmpty:()Z
  #594 = Methodref          #13.#593      // scala/xml/Null$.nonEmpty:()Z
  #595 = Utf8               isEmpty
  #596 = NameAndType        #595:#81      // isEmpty:()Z
  #597 = Methodref          #13.#596      // scala/xml/Null$.isEmpty:()Z
  #598 = Utf8               reduceRightOption
  #599 = Utf8               (Lscala/Function2;)Lscala/Option;
  #600 = Utf8               <B:Ljava/lang/Object;>(Lscala/Function2<Lscala/xml/MetaData;TB;TB;>;)Lscala/Option<TB;>;
  #601 = NameAndType        #598:#599     // reduceRightOption:(Lscala/Function2;)Lscala/Option;
  #602 = Methodref          #13.#601      // scala/xml/Null$.reduceRightOption:(Lscala/Function2;)Lscala/Option;
  #603 = Utf8               reduceLeftOption
  #604 = Utf8               <B:Ljava/lang/Object;>(Lscala/Function2<TB;Lscala/xml/MetaData;TB;>;)Lscala/Option<TB;>;
  #605 = NameAndType        #603:#599     // reduceLeftOption:(Lscala/Function2;)Lscala/Option;
  #606 = Methodref          #13.#605      // scala/xml/Null$.reduceLeftOption:(Lscala/Function2;)Lscala/Option;
  #607 = Utf8               reduceRight
  #608 = Utf8               (Lscala/Function2;)Ljava/lang/Object;
  #609 = Utf8               <B:Ljava/lang/Object;>(Lscala/Function2<Lscala/xml/MetaData;TB;TB;>;)TB;
  #610 = NameAndType        #607:#608     // reduceRight:(Lscala/Function2;)Ljava/lang/Object;
  #611 = Methodref          #13.#610      // scala/xml/Null$.reduceRight:(Lscala/Function2;)Ljava/lang/Object;
  #612 = Utf8               reduceLeft
  #613 = Utf8               <B:Ljava/lang/Object;>(Lscala/Function2<TB;Lscala/xml/MetaData;TB;>;)TB;
  #614 = NameAndType        #612:#608     // reduceLeft:(Lscala/Function2;)Ljava/lang/Object;
  #615 = Methodref          #13.#614      // scala/xml/Null$.reduceLeft:(Lscala/Function2;)Ljava/lang/Object;
  #616 = Utf8               reduceOption
  #617 = Utf8               <B:Ljava/lang/Object;>(Lscala/Function2<TB;TB;TB;>;)Lscala/Option<TB;>;
  #618 = NameAndType        #616:#599     // reduceOption:(Lscala/Function2;)Lscala/Option;
  #619 = Methodref          #13.#618      // scala/xml/Null$.reduceOption:(Lscala/Function2;)Lscala/Option;
  #620 = Utf8               <B:Ljava/lang/Object;>(Lscala/Function2<TB;TB;TB;>;)TB;
  #621 = NameAndType        #300:#608     // reduce:(Lscala/Function2;)Ljava/lang/Object;
  #622 = Methodref          #13.#621      // scala/xml/Null$.reduce:(Lscala/Function2;)Ljava/lang/Object;
  #623 = Utf8               fold
  #624 = Utf8               <A1:Ljava/lang/Object;>(TA1;Lscala/Function2<TA1;TA1;TA1;>;)TA1;
  #625 = NameAndType        #623:#285     // fold:(Ljava/lang/Object;Lscala/Function2;)Ljava/lang/Object;
  #626 = Methodref          #13.#625      // scala/xml/Null$.fold:(Ljava/lang/Object;Lscala/Function2;)Ljava/lang/Object;
  #627 = Utf8               $colon$bslash
  #628 = Utf8               <B:Ljava/lang/Object;>(TB;Lscala/Function2<Lscala/xml/MetaData;TB;TB;>;)TB;
  #629 = NameAndType        #627:#285     // $colon$bslash:(Ljava/lang/Object;Lscala/Function2;)Ljava/lang/Object;
  #630 = Methodref          #13.#629      // scala/xml/Null$.$colon$bslash:(Ljava/lang/Object;Lscala/Function2;)Ljava/lang/Object;
  #631 = Utf8               $div$colon
  #632 = Utf8               <B:Ljava/lang/Object;>(TB;Lscala/Function2<TB;Lscala/xml/MetaData;TB;>;)TB;
  #633 = NameAndType        #631:#285     // $div$colon:(Ljava/lang/Object;Lscala/Function2;)Ljava/lang/Object;
  #634 = Methodref          #13.#633      // scala/xml/Null$.$div$colon:(Ljava/lang/Object;Lscala/Function2;)Ljava/lang/Object;
  #635 = Utf8               foldRight
  #636 = NameAndType        #635:#285     // foldRight:(Ljava/lang/Object;Lscala/Function2;)Ljava/lang/Object;
  #637 = Methodref          #13.#636      // scala/xml/Null$.foldRight:(Ljava/lang/Object;Lscala/Function2;)Ljava/lang/Object;
  #638 = Utf8               foldLeft
  #639 = NameAndType        #638:#285     // foldLeft:(Ljava/lang/Object;Lscala/Function2;)Ljava/lang/Object;
  #640 = Methodref          #13.#639      // scala/xml/Null$.foldLeft:(Ljava/lang/Object;Lscala/Function2;)Ljava/lang/Object;
  #641 = Utf8               find
  #642 = Utf8               (Lscala/Function1;)Lscala/Option;
  #643 = Utf8               (Lscala/Function1<Lscala/xml/MetaData;Ljava/lang/Object;>;)Lscala/Option<Lscala/xml/MetaData;>;
  #644 = NameAndType        #641:#642     // find:(Lscala/Function1;)Lscala/Option;
  #645 = Methodref          #13.#644      // scala/xml/Null$.find:(Lscala/Function1;)Lscala/Option;
  #646 = Utf8               count
  #647 = Utf8               (Lscala/Function1;)I
  #648 = Utf8               (Lscala/Function1<Lscala/xml/MetaData;Ljava/lang/Object;>;)I
  #649 = NameAndType        #646:#647     // count:(Lscala/Function1;)I
  #650 = Methodref          #13.#649      // scala/xml/Null$.count:(Lscala/Function1;)I
  #651 = Utf8               exists
  #652 = Utf8               (Lscala/Function1;)Z
  #653 = Utf8               (Lscala/Function1<Lscala/xml/MetaData;Ljava/lang/Object;>;)Z
  #654 = NameAndType        #651:#652     // exists:(Lscala/Function1;)Z
  #655 = Methodref          #13.#654      // scala/xml/Null$.exists:(Lscala/Function1;)Z
  #656 = Utf8               forall
  #657 = NameAndType        #656:#652     // forall:(Lscala/Function1;)Z
  #658 = Methodref          #13.#657      // scala/xml/Null$.forall:(Lscala/Function1;)Z
  #659 = Utf8               foreach
  #660 = Utf8               (Lscala/Function1;)V
  #661 = Utf8               <U:Ljava/lang/Object;>(Lscala/Function1<Lscala/xml/MetaData;TU;>;)V
  #662 = NameAndType        #659:#660     // foreach:(Lscala/Function1;)V
  #663 = Methodref          #13.#662      // scala/xml/Null$.foreach:(Lscala/Function1;)V
  #664 = Utf8               hasDefiniteSize
  #665 = NameAndType        #664:#81      // hasDefiniteSize:()Z
  #666 = Methodref          #13.#665      // scala/xml/Null$.hasDefiniteSize:()Z
  #667 = Utf8               knownSize
  #668 = NameAndType        #667:#27      // knownSize:()I
  #669 = Methodref          #13.#668      // scala/xml/Null$.knownSize:()I
  #670 = Utf8               stepper
  #671 = Utf8               (Lscala/collection/StepperShape;)Lscala/collection/Stepper;
  #672 = Utf8               <S::Lscala/collection/Stepper<*>;>(Lscala/collection/StepperShape<Lscala/xml/MetaData;TS;>;)TS;
  #673 = Utf8               shape
  #674 = NameAndType        #670:#671     // stepper:(Lscala/collection/StepperShape;)Lscala/collection/Stepper;
  #675 = Methodref          #13.#674      // scala/xml/Null$.stepper:(Lscala/collection/StepperShape;)Lscala/collection/Stepper;
  #676 = Utf8               Lscala/collection/StepperShape;
  #677 = Utf8               Code
  #678 = Utf8               Signature
  #679 = Utf8               LocalVariableTable
  #680 = Utf8               MethodParameters
  #681 = Utf8               Deprecated
  #682 = Utf8               SourceFile
  #683 = Utf8               RuntimeVisibleAnnotations
  #684 = Utf8               ScalaSig
{
  public static scala.collection.Iterator<java.lang.Object> productIterator();
    descriptor: ()Lscala/collection/Iterator;
    flags: (0x0009) ACC_PUBLIC, ACC_STATIC
    Code:
      stack=1, locals=0, args_size=0
         0: getstatic     #17                 // Field scala/xml/Null$.MODULE$:Lscala/xml/Null$;
         3: invokevirtual #19                 // Method scala/xml/Null$.productIterator:()Lscala/collection/Iterator;
         6: areturn
    Signature: #11                          // ()Lscala/collection/Iterator<Ljava/lang/Object;>;

  public static java.lang.Object productElement(int);
    descriptor: (I)Ljava/lang/Object;
    flags: (0x0009) ACC_PUBLIC, ACC_STATIC
    Code:
      stack=2, locals=1, args_size=1
         0: getstatic     #17                 // Field scala/xml/Null$.MODULE$:Lscala/xml/Null$;
         3: iload_0
         4: invokevirtual #24                 // Method scala/xml/Null$.productElement:(I)Ljava/lang/Object;
         7: areturn
      LocalVariableTable:
        Start  Length  Slot  Name   Signature
            0       8     0   x$1   I
    MethodParameters:
      Name                           Flags
      x$1                            final

  public static int productArity();
    descriptor: ()I
    flags: (0x0009) ACC_PUBLIC, ACC_STATIC
    Code:
      stack=1, locals=0, args_size=0
         0: getstatic     #17                 // Field scala/xml/Null$.MODULE$:Lscala/xml/Null$;
         3: invokevirtual #29                 // Method scala/xml/Null$.productArity:()I
         6: ireturn

  public static java.lang.String productPrefix();
    descriptor: ()Ljava/lang/String;
    flags: (0x0009) ACC_PUBLIC, ACC_STATIC
    Code:
      stack=1, locals=0, args_size=0
         0: getstatic     #17                 // Field scala/xml/Null$.MODULE$:Lscala/xml/Null$;
         3: invokevirtual #33                 // Method scala/xml/Null$.productPrefix:()Ljava/lang/String;
         6: areturn

  public static scala.xml.Null$ remove(java.lang.String, scala.xml.NamespaceBinding, java.lang.String);
    descriptor: (Ljava/lang/String;Lscala/xml/NamespaceBinding;Ljava/lang/String;)Lscala/xml/Null$;
    flags: (0x0009) ACC_PUBLIC, ACC_STATIC
    Code:
      stack=4, locals=3, args_size=3
         0: getstatic     #17                 // Field scala/xml/Null$.MODULE$:Lscala/xml/Null$;
         3: aload_0
         4: aload_1
         5: aload_2
         6: invokevirtual #40                 // Method scala/xml/Null$.remove:(Ljava/lang/String;Lscala/xml/NamespaceBinding;Ljava/lang/String;)Lscala/xml/Null$;
         9: areturn
      LocalVariableTable:
        Start  Length  Slot  Name   Signature
            0      10     0 namespace   Ljava/lang/String;
            0      10     1 scope   Lscala/xml/NamespaceBinding;
            0      10     2   key   Ljava/lang/String;
    MethodParameters:
      Name                           Flags
      namespace                      final
      scope                          final
      key                            final

  public static scala.xml.Null$ remove(java.lang.String);
    descriptor: (Ljava/lang/String;)Lscala/xml/Null$;
    flags: (0x0009) ACC_PUBLIC, ACC_STATIC
    Code:
      stack=2, locals=1, args_size=1
         0: getstatic     #17                 // Field scala/xml/Null$.MODULE$:Lscala/xml/Null$;
         3: aload_0
         4: invokevirtual #45                 // Method scala/xml/Null$.remove:(Ljava/lang/String;)Lscala/xml/Null$;
         7: areturn
      LocalVariableTable:
        Start  Length  Slot  Name   Signature
            0       8     0   key   Ljava/lang/String;
    MethodParameters:
      Name                           Flags
      key                            final

  public static boolean wellformed(scala.xml.NamespaceBinding);
    descriptor: (Lscala/xml/NamespaceBinding;)Z
    flags: (0x0009) ACC_PUBLIC, ACC_STATIC
    Code:
      stack=2, locals=1, args_size=1
         0: getstatic     #17                 // Field scala/xml/Null$.MODULE$:Lscala/xml/Null$;
         3: aload_0
         4: invokevirtual #49                 // Method scala/xml/Null$.wellformed:(Lscala/xml/NamespaceBinding;)Z
         7: ireturn
      LocalVariableTable:
        Start  Length  Slot  Name   Signature
            0       8     0 scope   Lscala/xml/NamespaceBinding;
    MethodParameters:
      Name                           Flags
      scope                          final

  public static scala.collection.mutable.StringBuilder buildString(scala.collection.mutable.StringBuilder);
    descriptor: (Lscala/collection/mutable/StringBuilder;)Lscala/collection/mutable/StringBuilder;
    flags: (0x0009) ACC_PUBLIC, ACC_STATIC
    Code:
      stack=2, locals=1, args_size=1
         0: getstatic     #17                 // Field scala/xml/Null$.MODULE$:Lscala/xml/Null$;
         3: aload_0
         4: invokevirtual #54                 // Method scala/xml/Null$.buildString:(Lscala/collection/mutable/StringBuilder;)Lscala/collection/mutable/StringBuilder;
         7: areturn
      LocalVariableTable:
        Start  Length  Slot  Name   Signature
            0       8     0    sb   Lscala/collection/mutable/StringBuilder;
    MethodParameters:
      Name                           Flags
      sb                             final

  public static java.lang.String toString();
    descriptor: ()Ljava/lang/String;
    flags: (0x0009) ACC_PUBLIC, ACC_STATIC
    Code:
      stack=1, locals=0, args_size=0
         0: getstatic     #17                 // Field scala/xml/Null$.MODULE$:Lscala/xml/Null$;
         3: invokevirtual #58                 // Method scala/xml/Null$.toString:()Ljava/lang/String;
         6: areturn

  public static scala.collection.Seq<scala.xml.Node> apply(java.lang.String);
    descriptor: (Ljava/lang/String;)Lscala/collection/Seq;
    flags: (0x0009) ACC_PUBLIC, ACC_STATIC
    Code:
      stack=2, locals=1, args_size=1
         0: getstatic     #17                 // Field scala/xml/Null$.MODULE$:Lscala/xml/Null$;
         3: aload_0
         4: invokevirtual #63                 // Method scala/xml/Null$.apply:(Ljava/lang/String;)Lscala/collection/Seq;
         7: areturn
      LocalVariableTable:
        Start  Length  Slot  Name   Signature
            0       8     0   key   Ljava/lang/String;
    Signature: #61                          // (Ljava/lang/String;)Lscala/collection/Seq<Lscala/xml/Node;>;
    MethodParameters:
      Name                           Flags
      key                            final

  public static scala.runtime.Null$ apply(java.lang.String, scala.xml.NamespaceBinding, java.lang.String);
    descriptor: (Ljava/lang/String;Lscala/xml/NamespaceBinding;Ljava/lang/String;)Lscala/runtime/Null$;
    flags: (0x0009) ACC_PUBLIC, ACC_STATIC
    Code:
      stack=4, locals=3, args_size=3
         0: getstatic     #17                 // Field scala/xml/Null$.MODULE$:Lscala/xml/Null$;
         3: aload_0
         4: aload_1
         5: aload_2
         6: invokevirtual #66                 // Method scala/xml/Null$.apply:(Ljava/lang/String;Lscala/xml/NamespaceBinding;Ljava/lang/String;)Lscala/runtime/Null$;
         9: areturn
      LocalVariableTable:
        Start  Length  Slot  Name   Signature
            0      10     0 namespace   Ljava/lang/String;
            0      10     1 scope   Lscala/xml/NamespaceBinding;
            0      10     2   key   Ljava/lang/String;
    MethodParameters:
      Name                           Flags
      namespace                      final
      scope                          final
      key                            final

  public static boolean strict_$eq$eq(scala.xml.Equality);
    descriptor: (Lscala/xml/Equality;)Z
    flags: (0x0009) ACC_PUBLIC, ACC_STATIC
    Code:
      stack=2, locals=1, args_size=1
         0: getstatic     #17                 // Field scala/xml/Null$.MODULE$:Lscala/xml/Null$;
         3: aload_0
         4: invokevirtual #71                 // Method scala/xml/Null$.strict_$eq$eq:(Lscala/xml/Equality;)Z
         7: ireturn
      LocalVariableTable:
        Start  Length  Slot  Name   Signature
            0       8     0 other   Lscala/xml/Equality;
    MethodParameters:
      Name                           Flags
      other                          final

  public static int length(int);
    descriptor: (I)I
    flags: (0x0009) ACC_PUBLIC, ACC_STATIC
    Code:
      stack=2, locals=1, args_size=1
         0: getstatic     #17                 // Field scala/xml/Null$.MODULE$:Lscala/xml/Null$;
         3: iload_0
         4: invokevirtual #77                 // Method scala/xml/Null$.length:(I)I
         7: ireturn
      LocalVariableTable:
        Start  Length  Slot  Name   Signature
            0       8     0     i   I
    MethodParameters:
      Name                           Flags
      i                              final

  public static int length();
    descriptor: ()I
    flags: (0x0009) ACC_PUBLIC, ACC_STATIC
    Code:
      stack=1, locals=0, args_size=0
         0: getstatic     #17                 // Field scala/xml/Null$.MODULE$:Lscala/xml/Null$;
         3: invokevirtual #79                 // Method scala/xml/Null$.length:()I
         6: ireturn

  public static boolean isPrefixed();
    descriptor: ()Z
    flags: (0x0009) ACC_PUBLIC, ACC_STATIC
    Code:
      stack=1, locals=0, args_size=0
         0: getstatic     #17                 // Field scala/xml/Null$.MODULE$:Lscala/xml/Null$;
         3: invokevirtual #83                 // Method scala/xml/Null$.isPrefixed:()Z
         6: ireturn

  public static scala.runtime.Null$ value();
    descriptor: ()Lscala/runtime/Null$;
    flags: (0x0009) ACC_PUBLIC, ACC_STATIC
    Code:
      stack=1, locals=0, args_size=0
         0: getstatic     #17                 // Field scala/xml/Null$.MODULE$:Lscala/xml/Null$;
         3: invokevirtual #87                 // Method scala/xml/Null$.value:()Lscala/runtime/Null$;
         6: areturn

  public static scala.runtime.Null$ key();
    descriptor: ()Lscala/runtime/Null$;
    flags: (0x0009) ACC_PUBLIC, ACC_STATIC
    Code:
      stack=1, locals=0, args_size=0
         0: getstatic     #17                 // Field scala/xml/Null$.MODULE$:Lscala/xml/Null$;
         3: invokevirtual #89                 // Method scala/xml/Null$.key:()Lscala/runtime/Null$;
         6: areturn

  public static scala.runtime.Null$ next();
    descriptor: ()Lscala/runtime/Null$;
    flags: (0x0009) ACC_PUBLIC, ACC_STATIC
    Code:
      stack=1, locals=0, args_size=0
         0: getstatic     #17                 // Field scala/xml/Null$.MODULE$:Lscala/xml/Null$;
         3: invokevirtual #92                 // Method scala/xml/Null$.next:()Lscala/runtime/Null$;
         6: areturn

  public static boolean hasNext();
    descriptor: ()Z
    flags: (0x0009) ACC_PUBLIC, ACC_STATIC
    Code:
      stack=1, locals=0, args_size=0
         0: getstatic     #17                 // Field scala/xml/Null$.MODULE$:Lscala/xml/Null$;
         3: invokevirtual #95                 // Method scala/xml/Null$.hasNext:()Z
         6: ireturn

  public static scala.runtime.Null$ getNamespace(scala.xml.Node);
    descriptor: (Lscala/xml/Node;)Lscala/runtime/Null$;
    flags: (0x0009) ACC_PUBLIC, ACC_STATIC
    Code:
      stack=2, locals=1, args_size=1
         0: getstatic     #17                 // Field scala/xml/Null$.MODULE$:Lscala/xml/Null$;
         3: aload_0
         4: invokevirtual #100                // Method scala/xml/Null$.getNamespace:(Lscala/xml/Node;)Lscala/runtime/Null$;
         7: areturn
      LocalVariableTable:
        Start  Length  Slot  Name   Signature
            0       8     0 owner   Lscala/xml/Node;
    MethodParameters:
      Name                           Flags
      owner                          final

  public static scala.xml.MetaData copy(scala.xml.MetaData);
    descriptor: (Lscala/xml/MetaData;)Lscala/xml/MetaData;
    flags: (0x0009) ACC_PUBLIC, ACC_STATIC
    Code:
      stack=2, locals=1, args_size=1
         0: getstatic     #17                 // Field scala/xml/Null$.MODULE$:Lscala/xml/Null$;
         3: aload_0
         4: invokevirtual #105                // Method scala/xml/Null$.copy:(Lscala/xml/MetaData;)Lscala/xml/MetaData;
         7: areturn
      LocalVariableTable:
        Start  Length  Slot  Name   Signature
            0       8     0  next   Lscala/xml/MetaData;
    MethodParameters:
      Name                           Flags
      next                           final

  public static scala.xml.MetaData filter(scala.Function1<scala.xml.MetaData, java.lang.Object>);
    descriptor: (Lscala/Function1;)Lscala/xml/MetaData;
    flags: (0x0009) ACC_PUBLIC, ACC_STATIC
    Code:
      stack=2, locals=1, args_size=1
         0: getstatic     #17                 // Field scala/xml/Null$.MODULE$:Lscala/xml/Null$;
         3: aload_0
         4: invokevirtual #112                // Method scala/xml/Null$.filter:(Lscala/Function1;)Lscala/xml/MetaData;
         7: areturn
      LocalVariableTable:
        Start  Length  Slot  Name   Signature
            0       8     0     f   Lscala/Function1;
    Signature: #109                         // (Lscala/Function1<Lscala/xml/MetaData;Ljava/lang/Object;>;)Lscala/xml/MetaData;
    MethodParameters:
      Name                           Flags
      f                              final

  public static scala.xml.NamespaceBinding append$default$2();
    descriptor: ()Lscala/xml/NamespaceBinding;
    flags: (0x0009) ACC_PUBLIC, ACC_STATIC
    Code:
      stack=1, locals=0, args_size=0
         0: getstatic     #17                 // Field scala/xml/Null$.MODULE$:Lscala/xml/Null$;
         3: invokevirtual #117                // Method scala/xml/Null$.append$default$2:()Lscala/xml/NamespaceBinding;
         6: areturn

  public static scala.xml.MetaData append(scala.xml.MetaData, scala.xml.NamespaceBinding);
    descriptor: (Lscala/xml/MetaData;Lscala/xml/NamespaceBinding;)Lscala/xml/MetaData;
    flags: (0x0009) ACC_PUBLIC, ACC_STATIC
    Code:
      stack=3, locals=2, args_size=2
         0: getstatic     #17                 // Field scala/xml/Null$.MODULE$:Lscala/xml/Null$;
         3: aload_0
         4: aload_1
         5: invokevirtual #122                // Method scala/xml/Null$.append:(Lscala/xml/MetaData;Lscala/xml/NamespaceBinding;)Lscala/xml/MetaData;
         8: areturn
      LocalVariableTable:
        Start  Length  Slot  Name   Signature
            0       9     0     m   Lscala/xml/MetaData;
            0       9     1 scope   Lscala/xml/NamespaceBinding;
    MethodParameters:
      Name                           Flags
      m                              final
      scope                          final

  public static int size();
    descriptor: ()I
    flags: (0x0009) ACC_PUBLIC, ACC_STATIC
    Code:
      stack=1, locals=0, args_size=0
         0: getstatic     #17                 // Field scala/xml/Null$.MODULE$:Lscala/xml/Null$;
         3: invokevirtual #125                // Method scala/xml/Null$.size:()I
         6: ireturn

  public static scala.collection.Iterator<scala.runtime.Nothing$> iterator();
    descriptor: ()Lscala/collection/Iterator;
    flags: (0x0009) ACC_PUBLIC, ACC_STATIC
    Code:
      stack=1, locals=0, args_size=0
         0: getstatic     #17                 // Field scala/xml/Null$.MODULE$:Lscala/xml/Null$;
         3: invokevirtual #129                // Method scala/xml/Null$.iterator:()Lscala/collection/Iterator;
         6: areturn
    Signature: #127                         // ()Lscala/collection/Iterator<Lscala/runtime/Nothing$;>;

  public static scala.collection.Iterator<java.lang.String> productElementNames();
    descriptor: ()Lscala/collection/Iterator;
    flags: (0x0009) ACC_PUBLIC, ACC_STATIC
    Code:
      stack=1, locals=0, args_size=0
         0: getstatic     #17                 // Field scala/xml/Null$.MODULE$:Lscala/xml/Null$;
         3: invokevirtual #133                // Method scala/xml/Null$.productElementNames:()Lscala/collection/Iterator;
         6: areturn
    Signature: #131                         // ()Lscala/collection/Iterator<Ljava/lang/String;>;

  public static java.lang.String productElementName(int);
    descriptor: (I)Ljava/lang/String;
    flags: (0x0009) ACC_PUBLIC, ACC_STATIC
    Code:
      stack=2, locals=1, args_size=1
         0: getstatic     #17                 // Field scala/xml/Null$.MODULE$:Lscala/xml/Null$;
         3: iload_0
         4: invokevirtual #138                // Method scala/xml/Null$.productElementName:(I)Ljava/lang/String;
         7: areturn
      LocalVariableTable:
        Start  Length  Slot  Name   Signature
            0       8     0     n   I
    MethodParameters:
      Name                           Flags
      n                              final

  public static scala.xml.MetaData remove(java.lang.String, scala.xml.Node, java.lang.String);
    descriptor: (Ljava/lang/String;Lscala/xml/Node;Ljava/lang/String;)Lscala/xml/MetaData;
    flags: (0x0009) ACC_PUBLIC, ACC_STATIC
    Code:
      stack=4, locals=3, args_size=3
         0: getstatic     #17                 // Field scala/xml/Null$.MODULE$:Lscala/xml/Null$;
         3: aload_0
         4: aload_1
         5: aload_2
         6: invokevirtual #141                // Method scala/xml/Null$.remove:(Ljava/lang/String;Lscala/xml/Node;Ljava/lang/String;)Lscala/xml/MetaData;
         9: areturn
      LocalVariableTable:
        Start  Length  Slot  Name   Signature
            0      10     0 namespace   Ljava/lang/String;
            0      10     1 owner   Lscala/xml/Node;
            0      10     2   key   Ljava/lang/String;
    MethodParameters:
      Name                           Flags
      namespace                      final
      owner                          final
      key                            final

  public static scala.Option<scala.collection.Seq<scala.xml.Node>> get(java.lang.String, scala.xml.NamespaceBinding, java.lang.String);
    descriptor: (Ljava/lang/String;Lscala/xml/NamespaceBinding;Ljava/lang/String;)Lscala/Option;
    flags: (0x0009) ACC_PUBLIC, ACC_STATIC
    Code:
      stack=4, locals=3, args_size=3
         0: getstatic     #17                 // Field scala/xml/Null$.MODULE$:Lscala/xml/Null$;
         3: aload_0
         4: aload_1
         5: aload_2
         6: invokevirtual #147                // Method scala/xml/Null$.get:(Ljava/lang/String;Lscala/xml/NamespaceBinding;Ljava/lang/String;)Lscala/Option;
         9: areturn
      LocalVariableTable:
        Start  Length  Slot  Name   Signature
            0      10     0   uri   Ljava/lang/String;
            0      10     1 scope   Lscala/xml/NamespaceBinding;
            0      10     2   key   Ljava/lang/String;
    Signature: #144                         // (Ljava/lang/String;Lscala/xml/NamespaceBinding;Ljava/lang/String;)Lscala/Option<Lscala/collection/Seq<Lscala/xml/Node;>;>;
    MethodParameters:
      Name                           Flags
      uri                            final
      scope                          final
      key                            final

  public static scala.Option<scala.collection.Seq<scala.xml.Node>> get(java.lang.String, scala.xml.Node, java.lang.String);
    descriptor: (Ljava/lang/String;Lscala/xml/Node;Ljava/lang/String;)Lscala/Option;
    flags: (0x0009) ACC_PUBLIC, ACC_STATIC
    Code:
      stack=4, locals=3, args_size=3
         0: getstatic     #17                 // Field scala/xml/Null$.MODULE$:Lscala/xml/Null$;
         3: aload_0
         4: aload_1
         5: aload_2
         6: invokevirtual #151                // Method scala/xml/Null$.get:(Ljava/lang/String;Lscala/xml/Node;Ljava/lang/String;)Lscala/Option;
         9: areturn
      LocalVariableTable:
        Start  Length  Slot  Name   Signature
            0      10     0   uri   Ljava/lang/String;
            0      10     1 owner   Lscala/xml/Node;
            0      10     2   key   Ljava/lang/String;
    Signature: #149                         // (Ljava/lang/String;Lscala/xml/Node;Ljava/lang/String;)Lscala/Option<Lscala/collection/Seq<Lscala/xml/Node;>;>;
    MethodParameters:
      Name                           Flags
      uri                            final
      owner                          final
      key                            final

  public static scala.Option<scala.collection.Seq<scala.xml.Node>> get(java.lang.String);
    descriptor: (Ljava/lang/String;)Lscala/Option;
    flags: (0x0009) ACC_PUBLIC, ACC_STATIC
    Code:
      stack=2, locals=1, args_size=1
         0: getstatic     #17                 // Field scala/xml/Null$.MODULE$:Lscala/xml/Null$;
         3: aload_0
         4: invokevirtual #155                // Method scala/xml/Null$.get:(Ljava/lang/String;)Lscala/Option;
         7: areturn
      LocalVariableTable:
        Start  Length  Slot  Name   Signature
            0       8     0   key   Ljava/lang/String;
    Signature: #153                         // (Ljava/lang/String;)Lscala/Option<Lscala/collection/Seq<Lscala/xml/Node;>;>;
    MethodParameters:
      Name                           Flags
      key                            final

  public static scala.collection.immutable.Map<java.lang.String, java.lang.String> asAttrMap();
    descriptor: ()Lscala/collection/immutable/Map;
    flags: (0x0009) ACC_PUBLIC, ACC_STATIC
    Code:
      stack=1, locals=0, args_size=0
         0: getstatic     #17                 // Field scala/xml/Null$.MODULE$:Lscala/xml/Null$;
         3: invokevirtual #160                // Method scala/xml/Null$.asAttrMap:()Lscala/collection/immutable/Map;
         6: areturn
    Signature: #158                         // ()Lscala/collection/immutable/Map<Ljava/lang/String;Ljava/lang/String;>;

  public static java.lang.String prefixedKey();
    descriptor: ()Ljava/lang/String;
    flags: (0x0009) ACC_PUBLIC, ACC_STATIC
    Code:
      stack=1, locals=0, args_size=0
         0: getstatic     #17                 // Field scala/xml/Null$.MODULE$:Lscala/xml/Null$;
         3: invokevirtual #163                // Method scala/xml/Null$.prefixedKey:()Ljava/lang/String;
         6: areturn

  public static scala.xml.MetaData reverse();
    descriptor: ()Lscala/xml/MetaData;
    flags: (0x0009) ACC_PUBLIC, ACC_STATIC
    Code:
      stack=1, locals=0, args_size=0
         0: getstatic     #17                 // Field scala/xml/Null$.MODULE$:Lscala/xml/Null$;
         3: invokevirtual #167                // Method scala/xml/Null$.reverse:()Lscala/xml/MetaData;
         6: areturn

  public static boolean canEqual(java.lang.Object);
    descriptor: (Ljava/lang/Object;)Z
    flags: (0x0009) ACC_PUBLIC, ACC_STATIC
    Code:
      stack=2, locals=1, args_size=1
         0: getstatic     #17                 // Field scala/xml/Null$.MODULE$:Lscala/xml/Null$;
         3: aload_0
         4: invokevirtual #171                // Method scala/xml/Null$.canEqual:(Ljava/lang/Object;)Z
         7: ireturn
      LocalVariableTable:
        Start  Length  Slot  Name   Signature
            0       8     0 other   Ljava/lang/Object;
    MethodParameters:
      Name                           Flags
      other                          final

  public static scala.collection.Seq<scala.xml.Node> apply(java.lang.String, scala.xml.Node, java.lang.String);
    descriptor: (Ljava/lang/String;Lscala/xml/Node;Ljava/lang/String;)Lscala/collection/Seq;
    flags: (0x0009) ACC_PUBLIC, ACC_STATIC
    Code:
      stack=4, locals=3, args_size=3
         0: getstatic     #17                 // Field scala/xml/Null$.MODULE$:Lscala/xml/Null$;
         3: aload_0
         4: aload_1
         5: aload_2
         6: invokevirtual #177                // Method scala/xml/Null$.apply:(Ljava/lang/String;Lscala/xml/Node;Ljava/lang/String;)Lscala/collection/Seq;
         9: areturn
      LocalVariableTable:
        Start  Length  Slot  Name   Signature
            0      10     0 namespace_uri   Ljava/lang/String;
            0      10     1 owner   Lscala/xml/Node;
            0      10     2   key   Ljava/lang/String;
    Signature: #174                         // (Ljava/lang/String;Lscala/xml/Node;Ljava/lang/String;)Lscala/collection/Seq<Lscala/xml/Node;>;
    MethodParameters:
      Name                           Flags
      namespace_uri                  final
      owner                          final
      key                            final

  public static boolean xml_$bang$eq(java.lang.Object);
    descriptor: (Ljava/lang/Object;)Z
    flags: (0x0009) ACC_PUBLIC, ACC_STATIC
    Code:
      stack=2, locals=1, args_size=1
         0: getstatic     #17                 // Field scala/xml/Null$.MODULE$:Lscala/xml/Null$;
         3: aload_0
         4: invokevirtual #180                // Method scala/xml/Null$.xml_$bang$eq:(Ljava/lang/Object;)Z
         7: ireturn
      LocalVariableTable:
        Start  Length  Slot  Name   Signature
            0       8     0 other   Ljava/lang/Object;
    MethodParameters:
      Name                           Flags
      other                          final

  public static boolean xml_$eq$eq(java.lang.Object);
    descriptor: (Ljava/lang/Object;)Z
    flags: (0x0009) ACC_PUBLIC, ACC_STATIC
    Code:
      stack=2, locals=1, args_size=1
         0: getstatic     #17                 // Field scala/xml/Null$.MODULE$:Lscala/xml/Null$;
         3: aload_0
         4: invokevirtual #183                // Method scala/xml/Null$.xml_$eq$eq:(Ljava/lang/Object;)Z
         7: ireturn
      LocalVariableTable:
        Start  Length  Slot  Name   Signature
            0       8     0 other   Ljava/lang/Object;
    MethodParameters:
      Name                           Flags
      other                          final

  public static boolean equals(java.lang.Object);
    descriptor: (Ljava/lang/Object;)Z
    flags: (0x0009) ACC_PUBLIC, ACC_STATIC
    Code:
      stack=2, locals=1, args_size=1
         0: getstatic     #17                 // Field scala/xml/Null$.MODULE$:Lscala/xml/Null$;
         3: aload_0
         4: invokevirtual #186                // Method scala/xml/Null$.equals:(Ljava/lang/Object;)Z
         7: ireturn
      LocalVariableTable:
        Start  Length  Slot  Name   Signature
            0       8     0 other   Ljava/lang/Object;
    MethodParameters:
      Name                           Flags
      other                          final

  public static int hashCode();
    descriptor: ()I
    flags: (0x0009) ACC_PUBLIC, ACC_STATIC
    Code:
      stack=1, locals=0, args_size=0
         0: getstatic     #17                 // Field scala/xml/Null$.MODULE$:Lscala/xml/Null$;
         3: invokevirtual #189                // Method scala/xml/Null$.hashCode:()I
         6: ireturn

  public static boolean strict_$bang$eq(scala.xml.Equality);
    descriptor: (Lscala/xml/Equality;)Z
    flags: (0x0009) ACC_PUBLIC, ACC_STATIC
    Code:
      stack=2, locals=1, args_size=1
         0: getstatic     #17                 // Field scala/xml/Null$.MODULE$:Lscala/xml/Null$;
         3: aload_0
         4: invokevirtual #192                // Method scala/xml/Null$.strict_$bang$eq:(Lscala/xml/Equality;)Z
         7: ireturn
      LocalVariableTable:
        Start  Length  Slot  Name   Signature
            0       8     0 other   Lscala/xml/Equality;
    MethodParameters:
      Name                           Flags
      other                          final

  public static <B extends java.lang.Object> scala.collection.LazyZip2<scala.xml.MetaData, B, scala.xml.Null$> lazyZip(scala.collection.Iterable<B>);
    descriptor: (Lscala/collection/Iterable;)Lscala/collection/LazyZip2;
    flags: (0x0009) ACC_PUBLIC, ACC_STATIC
    Code:
      stack=2, locals=1, args_size=1
         0: getstatic     #17                 // Field scala/xml/Null$.MODULE$:Lscala/xml/Null$;
         3: aload_0
         4: invokevirtual #198                // Method scala/xml/Null$.lazyZip:(Lscala/collection/Iterable;)Lscala/collection/LazyZip2;
         7: areturn
      LocalVariableTable:
        Start  Length  Slot  Name   Signature
            0       8     0  that   Lscala/collection/Iterable;
    Signature: #195                         // <B:Ljava/lang/Object;>(Lscala/collection/Iterable<TB;>;)Lscala/collection/LazyZip2<Lscala/xml/MetaData;TB;Lscala/xml/Null$;>;
    MethodParameters:
      Name                           Flags
      that                           final

  public static scala.collection.Iterable seq();
    descriptor: ()Lscala/collection/Iterable;
    flags: (0x0009) ACC_PUBLIC, ACC_STATIC
    Code:
      stack=1, locals=0, args_size=0
         0: getstatic     #17                 // Field scala/xml/Null$.MODULE$:Lscala/xml/Null$;
         3: invokevirtual #203                // Method scala/xml/Null$.seq:()Lscala/collection/Iterable;
         6: areturn
    Deprecated: true

  public static scala.collection.IterableFactory<scala.collection.Iterable> iterableFactory();
    descriptor: ()Lscala/collection/IterableFactory;
    flags: (0x0009) ACC_PUBLIC, ACC_STATIC
    Code:
      stack=1, locals=0, args_size=0
         0: getstatic     #17                 // Field scala/xml/Null$.MODULE$:Lscala/xml/Null$;
         3: invokevirtual #208                // Method scala/xml/Null$.iterableFactory:()Lscala/collection/IterableFactory;
         6: areturn
    Signature: #206                         // ()Lscala/collection/IterableFactory<Lscala/collection/Iterable;>;

  public static scala.collection.Iterable toIterable();
    descriptor: ()Lscala/collection/Iterable;
    flags: (0x0009) ACC_PUBLIC, ACC_STATIC
    Code:
      stack=1, locals=0, args_size=0
         0: getstatic     #17                 // Field scala/xml/Null$.MODULE$:Lscala/xml/Null$;
         3: invokevirtual #211                // Method scala/xml/Null$.toIterable:()Lscala/collection/Iterable;
         6: areturn

  public static scala.collection.IterableOps empty();
    descriptor: ()Lscala/collection/IterableOps;
    flags: (0x0009) ACC_PUBLIC, ACC_STATIC
    Code:
      stack=1, locals=0, args_size=0
         0: getstatic     #17                 // Field scala/xml/Null$.MODULE$:Lscala/xml/Null$;
         3: invokevirtual #215                // Method scala/xml/Null$.empty:()Lscala/collection/IterableOps;
         6: areturn

  public static java.lang.Object $plus$plus$colon(scala.collection.IterableOnce);
    descriptor: (Lscala/collection/IterableOnce;)Ljava/lang/Object;
    flags: (0x0009) ACC_PUBLIC, ACC_STATIC
    Code:
      stack=2, locals=1, args_size=1
         0: getstatic     #17                 // Field scala/xml/Null$.MODULE$:Lscala/xml/Null$;
         3: aload_0
         4: invokevirtual #219                // Method scala/xml/Null$.$plus$plus$colon:(Lscala/collection/IterableOnce;)Ljava/lang/Object;
         7: areturn
      LocalVariableTable:
        Start  Length  Slot  Name   Signature
            0       8     0  that   Lscala/collection/IterableOnce;
    Deprecated: true
    MethodParameters:
      Name                           Flags
      that                           final

  public static java.lang.Object tapEach(scala.Function1);
    descriptor: (Lscala/Function1;)Ljava/lang/Object;
    flags: (0x0009) ACC_PUBLIC, ACC_STATIC
    Code:
      stack=2, locals=1, args_size=1
         0: getstatic     #17                 // Field scala/xml/Null$.MODULE$:Lscala/xml/Null$;
         3: aload_0
         4: invokevirtual #224                // Method scala/xml/Null$.tapEach:(Lscala/Function1;)Ljava/lang/Object;
         7: areturn
      LocalVariableTable:
        Start  Length  Slot  Name   Signature
            0       8     0     f   Lscala/Function1;
    MethodParameters:
      Name                           Flags
      f                              final

  public static scala.collection.Iterator<scala.collection.Iterable<scala.xml.MetaData>> inits();
    descriptor: ()Lscala/collection/Iterator;
    flags: (0x0009) ACC_PUBLIC, ACC_STATIC
    Code:
      stack=1, locals=0, args_size=0
         0: getstatic     #17                 // Field scala/xml/Null$.MODULE$:Lscala/xml/Null$;
         3: invokevirtual #228                // Method scala/xml/Null$.inits:()Lscala/collection/Iterator;
         6: areturn
    Signature: #226                         // ()Lscala/collection/Iterator<Lscala/collection/Iterable<Lscala/xml/MetaData;>;>;

  public static scala.collection.Iterator<scala.collection.Iterable<scala.xml.MetaData>> tails();
    descriptor: ()Lscala/collection/Iterator;
    flags: (0x0009) ACC_PUBLIC, ACC_STATIC
    Code:
      stack=1, locals=0, args_size=0
         0: getstatic     #17                 // Field scala/xml/Null$.MODULE$:Lscala/xml/Null$;
         3: invokevirtual #231                // Method scala/xml/Null$.tails:()Lscala/collection/Iterator;
         6: areturn
    Signature: #226                         // ()Lscala/collection/Iterator<Lscala/collection/Iterable<Lscala/xml/MetaData;>;>;

  public static <A1 extends java.lang.Object, A2 extends java.lang.Object, A3 extends java.lang.Object> scala.Tuple3<scala.collection.Iterable<A1>, scala.collection.Iterable<A2>, scala.collection.Iterable<A3>> unzip3(scala.Function1<scala.xml.MetaData, scala.Tuple3<A1, A2, A3>>);
    descriptor: (Lscala/Function1;)Lscala/Tuple3;
    flags: (0x0009) ACC_PUBLIC, ACC_STATIC
    Code:
      stack=2, locals=1, args_size=1
         0: getstatic     #17                 // Field scala/xml/Null$.MODULE$:Lscala/xml/Null$;
         3: aload_0
         4: invokevirtual #237                // Method scala/xml/Null$.unzip3:(Lscala/Function1;)Lscala/Tuple3;
         7: areturn
      LocalVariableTable:
        Start  Length  Slot  Name   Signature
            0       8     0 asTriple   Lscala/Function1;
    Signature: #234                         // <A1:Ljava/lang/Object;A2:Ljava/lang/Object;A3:Ljava/lang/Object;>(Lscala/Function1<Lscala/xml/MetaData;Lscala/Tuple3<TA1;TA2;TA3;>;>;)Lscala/Tuple3<Lscala/collection/Iterable<TA1;>;Lscala/collection/Iterable<TA2;>;Lscala/collection/Iterable<TA3;>;>;
    MethodParameters:
      Name                           Flags
      asTriple                       final

  public static <A1 extends java.lang.Object, A2 extends java.lang.Object> scala.Tuple2<scala.collection.Iterable<A1>, scala.collection.Iterable<A2>> unzip(scala.Function1<scala.xml.MetaData, scala.Tuple2<A1, A2>>);
    descriptor: (Lscala/Function1;)Lscala/Tuple2;
    flags: (0x0009) ACC_PUBLIC, ACC_STATIC
    Code:
      stack=2, locals=1, args_size=1
         0: getstatic     #17                 // Field scala/xml/Null$.MODULE$:Lscala/xml/Null$;
         3: aload_0
         4: invokevirtual #243                // Method scala/xml/Null$.unzip:(Lscala/Function1;)Lscala/Tuple2;
         7: areturn
      LocalVariableTable:
        Start  Length  Slot  Name   Signature
            0       8     0 asPair   Lscala/Function1;
    Signature: #240                         // <A1:Ljava/lang/Object;A2:Ljava/lang/Object;>(Lscala/Function1<Lscala/xml/MetaData;Lscala/Tuple2<TA1;TA2;>;>;)Lscala/Tuple2<Lscala/collection/Iterable<TA1;>;Lscala/collection/Iterable<TA2;>;>;
    MethodParameters:
      Name                           Flags
      asPair                         final

  public static java.lang.Object zipAll(scala.collection.Iterable, java.lang.Object, java.lang.Object);
    descriptor: (Lscala/collection/Iterable;Ljava/lang/Object;Ljava/lang/Object;)Ljava/lang/Object;
    flags: (0x0009) ACC_PUBLIC, ACC_STATIC
    Code:
      stack=4, locals=3, args_size=3
         0: getstatic     #17                 // Field scala/xml/Null$.MODULE$:Lscala/xml/Null$;
         3: aload_0
         4: aload_1
         5: aload_2
         6: invokevirtual #249                // Method scala/xml/Null$.zipAll:(Lscala/collection/Iterable;Ljava/lang/Object;Ljava/lang/Object;)Ljava/lang/Object;
         9: areturn
      LocalVariableTable:
        Start  Length  Slot  Name   Signature
            0      10     0  that   Lscala/collection/Iterable;
            0      10     1 thisElem   Ljava/lang/Object;
            0      10     2 thatElem   Ljava/lang/Object;
    MethodParameters:
      Name                           Flags
      that                           final
      thisElem                       final
      thatElem                       final

  public static java.lang.Object zipWithIndex();
    descriptor: ()Ljava/lang/Object;
    flags: (0x0009) ACC_PUBLIC, ACC_STATIC
    Code:
      stack=1, locals=0, args_size=0
         0: getstatic     #17                 // Field scala/xml/Null$.MODULE$:Lscala/xml/Null$;
         3: invokevirtual #253                // Method scala/xml/Null$.zipWithIndex:()Ljava/lang/Object;
         6: areturn

  public static java.lang.Object zip(scala.collection.IterableOnce);
    descriptor: (Lscala/collection/IterableOnce;)Ljava/lang/Object;
    flags: (0x0009) ACC_PUBLIC, ACC_STATIC
    Code:
      stack=2, locals=1, args_size=1
         0: getstatic     #17                 // Field scala/xml/Null$.MODULE$:Lscala/xml/Null$;
         3: aload_0
         4: invokevirtual #256                // Method scala/xml/Null$.zip:(Lscala/collection/IterableOnce;)Ljava/lang/Object;
         7: areturn
      LocalVariableTable:
        Start  Length  Slot  Name   Signature
            0       8     0  that   Lscala/collection/IterableOnce;
    MethodParameters:
      Name                           Flags
      that                           final

  public static java.lang.Object $plus$plus(scala.collection.IterableOnce);
    descriptor: (Lscala/collection/IterableOnce;)Ljava/lang/Object;
    flags: (0x0009) ACC_PUBLIC, ACC_STATIC
    Code:
      stack=2, locals=1, args_size=1
         0: getstatic     #17                 // Field scala/xml/Null$.MODULE$:Lscala/xml/Null$;
         3: aload_0
         4: invokevirtual #260                // Method scala/xml/Null$.$plus$plus:(Lscala/collection/IterableOnce;)Ljava/lang/Object;
         7: areturn
      LocalVariableTable:
        Start  Length  Slot  Name   Signature
            0       8     0 suffix   Lscala/collection/IterableOnce;
    MethodParameters:
      Name                           Flags
      suffix                         final

  public static java.lang.Object concat(scala.collection.IterableOnce);
    descriptor: (Lscala/collection/IterableOnce;)Ljava/lang/Object;
    flags: (0x0009) ACC_PUBLIC, ACC_STATIC
    Code:
      stack=2, locals=1, args_size=1
         0: getstatic     #17                 // Field scala/xml/Null$.MODULE$:Lscala/xml/Null$;
         3: aload_0
         4: invokevirtual #263                // Method scala/xml/Null$.concat:(Lscala/collection/IterableOnce;)Ljava/lang/Object;
         7: areturn
      LocalVariableTable:
        Start  Length  Slot  Name   Signature
            0       8     0 suffix   Lscala/collection/IterableOnce;
    MethodParameters:
      Name                           Flags
      suffix                         final

  public static <A1 extends java.lang.Object, A2 extends java.lang.Object> scala.Tuple2<scala.collection.Iterable<A1>, scala.collection.Iterable<A2>> partitionMap(scala.Function1<scala.xml.MetaData, scala.util.Either<A1, A2>>);
    descriptor: (Lscala/Function1;)Lscala/Tuple2;
    flags: (0x0009) ACC_PUBLIC, ACC_STATIC
    Code:
      stack=2, locals=1, args_size=1
         0: getstatic     #17                 // Field scala/xml/Null$.MODULE$:Lscala/xml/Null$;
         3: aload_0
         4: invokevirtual #267                // Method scala/xml/Null$.partitionMap:(Lscala/Function1;)Lscala/Tuple2;
         7: areturn
      LocalVariableTable:
        Start  Length  Slot  Name   Signature
            0       8     0     f   Lscala/Function1;
    Signature: #265                         // <A1:Ljava/lang/Object;A2:Ljava/lang/Object;>(Lscala/Function1<Lscala/xml/MetaData;Lscala/util/Either<TA1;TA2;>;>;)Lscala/Tuple2<Lscala/collection/Iterable<TA1;>;Lscala/collection/Iterable<TA2;>;>;
    MethodParameters:
      Name                           Flags
      f                              final

  public static java.lang.Object collect(scala.PartialFunction);
    descriptor: (Lscala/PartialFunction;)Ljava/lang/Object;
    flags: (0x0009) ACC_PUBLIC, ACC_STATIC
    Code:
      stack=2, locals=1, args_size=1
         0: getstatic     #17                 // Field scala/xml/Null$.MODULE$:Lscala/xml/Null$;
         3: aload_0
         4: invokevirtual #272                // Method scala/xml/Null$.collect:(Lscala/PartialFunction;)Ljava/lang/Object;
         7: areturn
      LocalVariableTable:
        Start  Length  Slot  Name   Signature
            0       8     0    pf   Lscala/PartialFunction;
    MethodParameters:
      Name                           Flags
      pf                             final

  public static java.lang.Object flatten(scala.Function1);
    descriptor: (Lscala/Function1;)Ljava/lang/Object;
    flags: (0x0009) ACC_PUBLIC, ACC_STATIC
    Code:
      stack=2, locals=1, args_size=1
         0: getstatic     #17                 // Field scala/xml/Null$.MODULE$:Lscala/xml/Null$;
         3: aload_0
         4: invokevirtual #277                // Method scala/xml/Null$.flatten:(Lscala/Function1;)Ljava/lang/Object;
         7: areturn
      LocalVariableTable:
        Start  Length  Slot  Name   Signature
            0       8     0 asIterable   Lscala/Function1;
    MethodParameters:
      Name                           Flags
      asIterable                     final

  public static java.lang.Object flatMap(scala.Function1);
    descriptor: (Lscala/Function1;)Ljava/lang/Object;
    flags: (0x0009) ACC_PUBLIC, ACC_STATIC
    Code:
      stack=2, locals=1, args_size=1
         0: getstatic     #17                 // Field scala/xml/Null$.MODULE$:Lscala/xml/Null$;
         3: aload_0
         4: invokevirtual #280                // Method scala/xml/Null$.flatMap:(Lscala/Function1;)Ljava/lang/Object;
         7: areturn
      LocalVariableTable:
        Start  Length  Slot  Name   Signature
            0       8     0     f   Lscala/Function1;
    MethodParameters:
      Name                           Flags
      f                              final

  public static java.lang.Object map(scala.Function1);
    descriptor: (Lscala/Function1;)Ljava/lang/Object;
    flags: (0x0009) ACC_PUBLIC, ACC_STATIC
    Code:
      stack=2, locals=1, args_size=1
         0: getstatic     #17                 // Field scala/xml/Null$.MODULE$:Lscala/xml/Null$;
         3: aload_0
         4: invokevirtual #283                // Method scala/xml/Null$.map:(Lscala/Function1;)Ljava/lang/Object;
         7: areturn
      LocalVariableTable:
        Start  Length  Slot  Name   Signature
            0       8     0     f   Lscala/Function1;
    MethodParameters:
      Name                           Flags
      f                              final

  public static java.lang.Object scanRight(java.lang.Object, scala.Function2);
    descriptor: (Ljava/lang/Object;Lscala/Function2;)Ljava/lang/Object;
    flags: (0x0009) ACC_PUBLIC, ACC_STATIC
    Code:
      stack=3, locals=2, args_size=2
         0: getstatic     #17                 // Field scala/xml/Null$.MODULE$:Lscala/xml/Null$;
         3: aload_0
         4: aload_1
         5: invokevirtual #289                // Method scala/xml/Null$.scanRight:(Ljava/lang/Object;Lscala/Function2;)Ljava/lang/Object;
         8: areturn
      LocalVariableTable:
        Start  Length  Slot  Name   Signature
            0       9     0     z   Ljava/lang/Object;
            0       9     1    op   Lscala/Function2;
    MethodParameters:
      Name                           Flags
      z                              final
      op                             final

  public static java.lang.Object scanLeft(java.lang.Object, scala.Function2);
    descriptor: (Ljava/lang/Object;Lscala/Function2;)Ljava/lang/Object;
    flags: (0x0009) ACC_PUBLIC, ACC_STATIC
    Code:
      stack=3, locals=2, args_size=2
         0: getstatic     #17                 // Field scala/xml/Null$.MODULE$:Lscala/xml/Null$;
         3: aload_0
         4: aload_1
         5: invokevirtual #293                // Method scala/xml/Null$.scanLeft:(Ljava/lang/Object;Lscala/Function2;)Ljava/lang/Object;
         8: areturn
      LocalVariableTable:
        Start  Length  Slot  Name   Signature
            0       9     0     z   Ljava/lang/Object;
            0       9     1    op   Lscala/Function2;
    MethodParameters:
      Name                           Flags
      z                              final
      op                             final

  public static java.lang.Object scan(java.lang.Object, scala.Function2);
    descriptor: (Ljava/lang/Object;Lscala/Function2;)Ljava/lang/Object;
    flags: (0x0009) ACC_PUBLIC, ACC_STATIC
    Code:
      stack=3, locals=2, args_size=2
         0: getstatic     #17                 // Field scala/xml/Null$.MODULE$:Lscala/xml/Null$;
         3: aload_0
         4: aload_1
         5: invokevirtual #296                // Method scala/xml/Null$.scan:(Ljava/lang/Object;Lscala/Function2;)Ljava/lang/Object;
         8: areturn
      LocalVariableTable:
        Start  Length  Slot  Name   Signature
            0       9     0     z   Ljava/lang/Object;
            0       9     1    op   Lscala/Function2;
    MethodParameters:
      Name                           Flags
      z                              final
      op                             final

  public static <K extends java.lang.Object, B extends java.lang.Object> scala.collection.immutable.Map<K, B> groupMapReduce(scala.Function1<scala.xml.MetaData, K>, scala.Function1<scala.xml.MetaData, B>, scala.Function2<B, B, B>);
    descriptor: (Lscala/Function1;Lscala/Function1;Lscala/Function2;)Lscala/collection/immutable/Map;
    flags: (0x0009) ACC_PUBLIC, ACC_STATIC
    Code:
      stack=4, locals=3, args_size=3
         0: getstatic     #17                 // Field scala/xml/Null$.MODULE$:Lscala/xml/Null$;
         3: aload_0
         4: aload_1
         5: aload_2
         6: invokevirtual #302                // Method scala/xml/Null$.groupMapReduce:(Lscala/Function1;Lscala/Function1;Lscala/Function2;)Lscala/collection/immutable/Map;
         9: areturn
      LocalVariableTable:
        Start  Length  Slot  Name   Signature
            0      10     0   key   Lscala/Function1;
            0      10     1     f   Lscala/Function1;
            0      10     2 reduce   Lscala/Function2;
    Signature: #299                         // <K:Ljava/lang/Object;B:Ljava/lang/Object;>(Lscala/Function1<Lscala/xml/MetaData;TK;>;Lscala/Function1<Lscala/xml/MetaData;TB;>;Lscala/Function2<TB;TB;TB;>;)Lscala/collection/immutable/Map<TK;TB;>;
    MethodParameters:
      Name                           Flags
      key                            final
      f                              final
      reduce                         final

  public static <K extends java.lang.Object, B extends java.lang.Object> scala.collection.immutable.Map<K, scala.collection.Iterable<B>> groupMap(scala.Function1<scala.xml.MetaData, K>, scala.Function1<scala.xml.MetaData, B>);
    descriptor: (Lscala/Function1;Lscala/Function1;)Lscala/collection/immutable/Map;
    flags: (0x0009) ACC_PUBLIC, ACC_STATIC
    Code:
      stack=3, locals=2, args_size=2
         0: getstatic     #17                 // Field scala/xml/Null$.MODULE$:Lscala/xml/Null$;
         3: aload_0
         4: aload_1
         5: invokevirtual #307                // Method scala/xml/Null$.groupMap:(Lscala/Function1;Lscala/Function1;)Lscala/collection/immutable/Map;
         8: areturn
      LocalVariableTable:
        Start  Length  Slot  Name   Signature
            0       9     0   key   Lscala/Function1;
            0       9     1     f   Lscala/Function1;
    Signature: #305                         // <K:Ljava/lang/Object;B:Ljava/lang/Object;>(Lscala/Function1<Lscala/xml/MetaData;TK;>;Lscala/Function1<Lscala/xml/MetaData;TB;>;)Lscala/collection/immutable/Map<TK;Lscala/collection/Iterable<TB;>;>;
    MethodParameters:
      Name                           Flags
      key                            final
      f                              final

  public static <K extends java.lang.Object> scala.collection.immutable.Map<K, scala.collection.Iterable<scala.xml.MetaData>> groupBy(scala.Function1<scala.xml.MetaData, K>);
    descriptor: (Lscala/Function1;)Lscala/collection/immutable/Map;
    flags: (0x0009) ACC_PUBLIC, ACC_STATIC
    Code:
      stack=2, locals=1, args_size=1
         0: getstatic     #17                 // Field scala/xml/Null$.MODULE$:Lscala/xml/Null$;
         3: aload_0
         4: invokevirtual #312                // Method scala/xml/Null$.groupBy:(Lscala/Function1;)Lscala/collection/immutable/Map;
         7: areturn
      LocalVariableTable:
        Start  Length  Slot  Name   Signature
            0       8     0     f   Lscala/Function1;
    Signature: #310                         // <K:Ljava/lang/Object;>(Lscala/Function1<Lscala/xml/MetaData;TK;>;)Lscala/collection/immutable/Map<TK;Lscala/collection/Iterable<Lscala/xml/MetaData;>;>;
    MethodParameters:
      Name                           Flags
      f                              final

  public static java.lang.Object slice(int, int);
    descriptor: (II)Ljava/lang/Object;
    flags: (0x0009) ACC_PUBLIC, ACC_STATIC
    Code:
      stack=3, locals=2, args_size=2
         0: getstatic     #17                 // Field scala/xml/Null$.MODULE$:Lscala/xml/Null$;
         3: iload_0
         4: iload_1
         5: invokevirtual #318                // Method scala/xml/Null$.slice:(II)Ljava/lang/Object;
         8: areturn
      LocalVariableTable:
        Start  Length  Slot  Name   Signature
            0       9     0  from   I
            0       9     1 until   I
    MethodParameters:
      Name                           Flags
      from                           final
      until                          final

  public static java.lang.Object init();
    descriptor: ()Ljava/lang/Object;
    flags: (0x0009) ACC_PUBLIC, ACC_STATIC
    Code:
      stack=1, locals=0, args_size=0
         0: getstatic     #17                 // Field scala/xml/Null$.MODULE$:Lscala/xml/Null$;
         3: invokevirtual #321                // Method scala/xml/Null$.init:()Ljava/lang/Object;
         6: areturn

  public static java.lang.Object tail();
    descriptor: ()Ljava/lang/Object;
    flags: (0x0009) ACC_PUBLIC, ACC_STATIC
    Code:
      stack=1, locals=0, args_size=0
         0: getstatic     #17                 // Field scala/xml/Null$.MODULE$:Lscala/xml/Null$;
         3: invokevirtual #324                // Method scala/xml/Null$.tail:()Ljava/lang/Object;
         6: areturn

  public static scala.collection.Iterator<scala.collection.Iterable<scala.xml.MetaData>> sliding(int, int);
    descriptor: (II)Lscala/collection/Iterator;
    flags: (0x0009) ACC_PUBLIC, ACC_STATIC
    Code:
      stack=3, locals=2, args_size=2
         0: getstatic     #17                 // Field scala/xml/Null$.MODULE$:Lscala/xml/Null$;
         3: iload_0
         4: iload_1
         5: invokevirtual #330                // Method scala/xml/Null$.sliding:(II)Lscala/collection/Iterator;
         8: areturn
      LocalVariableTable:
        Start  Length  Slot  Name   Signature
            0       9     0  size   I
            0       9     1  step   I
    Signature: #327                         // (II)Lscala/collection/Iterator<Lscala/collection/Iterable<Lscala/xml/MetaData;>;>;
    MethodParameters:
      Name                           Flags
      size                           final
      step                           final

  public static scala.collection.Iterator<scala.collection.Iterable<scala.xml.MetaData>> sliding(int);
    descriptor: (I)Lscala/collection/Iterator;
    flags: (0x0009) ACC_PUBLIC, ACC_STATIC
    Code:
      stack=2, locals=1, args_size=1
         0: getstatic     #17                 // Field scala/xml/Null$.MODULE$:Lscala/xml/Null$;
         3: iload_0
         4: invokevirtual #334                // Method scala/xml/Null$.sliding:(I)Lscala/collection/Iterator;
         7: areturn
      LocalVariableTable:
        Start  Length  Slot  Name   Signature
            0       8     0  size   I
    Signature: #332                         // (I)Lscala/collection/Iterator<Lscala/collection/Iterable<Lscala/xml/MetaData;>;>;
    MethodParameters:
      Name                           Flags
      size                           final

  public static scala.collection.Iterator<scala.collection.Iterable<scala.xml.MetaData>> grouped(int);
    descriptor: (I)Lscala/collection/Iterator;
    flags: (0x0009) ACC_PUBLIC, ACC_STATIC
    Code:
      stack=2, locals=1, args_size=1
         0: getstatic     #17                 // Field scala/xml/Null$.MODULE$:Lscala/xml/Null$;
         3: iload_0
         4: invokevirtual #337                // Method scala/xml/Null$.grouped:(I)Lscala/collection/Iterator;
         7: areturn
      LocalVariableTable:
        Start  Length  Slot  Name   Signature
            0       8     0  size   I
    Signature: #332                         // (I)Lscala/collection/Iterator<Lscala/collection/Iterable<Lscala/xml/MetaData;>;>;
    MethodParameters:
      Name                           Flags
      size                           final

  public static java.lang.Object dropWhile(scala.Function1);
    descriptor: (Lscala/Function1;)Ljava/lang/Object;
    flags: (0x0009) ACC_PUBLIC, ACC_STATIC
    Code:
      stack=2, locals=1, args_size=1
         0: getstatic     #17                 // Field scala/xml/Null$.MODULE$:Lscala/xml/Null$;
         3: aload_0
         4: invokevirtual #341                // Method scala/xml/Null$.dropWhile:(Lscala/Function1;)Ljava/lang/Object;
         7: areturn
      LocalVariableTable:
        Start  Length  Slot  Name   Signature
            0       8     0     p   Lscala/Function1;
    MethodParameters:
      Name                           Flags
      p                              final

  public static java.lang.Object dropRight(int);
    descriptor: (I)Ljava/lang/Object;
    flags: (0x0009) ACC_PUBLIC, ACC_STATIC
    Code:
      stack=2, locals=1, args_size=1
         0: getstatic     #17                 // Field scala/xml/Null$.MODULE$:Lscala/xml/Null$;
         3: iload_0
         4: invokevirtual #344                // Method scala/xml/Null$.dropRight:(I)Ljava/lang/Object;
         7: areturn
      LocalVariableTable:
        Start  Length  Slot  Name   Signature
            0       8     0     n   I
    MethodParameters:
      Name                           Flags
      n                              final

  public static java.lang.Object drop(int);
    descriptor: (I)Ljava/lang/Object;
    flags: (0x0009) ACC_PUBLIC, ACC_STATIC
    Code:
      stack=2, locals=1, args_size=1
         0: getstatic     #17                 // Field scala/xml/Null$.MODULE$:Lscala/xml/Null$;
         3: iload_0
         4: invokevirtual #347                // Method scala/xml/Null$.drop:(I)Ljava/lang/Object;
         7: areturn
      LocalVariableTable:
        Start  Length  Slot  Name   Signature
            0       8     0     n   I
    MethodParameters:
      Name                           Flags
      n                              final

  public static scala.Tuple2<scala.collection.Iterable<scala.xml.MetaData>, scala.collection.Iterable<scala.xml.MetaData>> span(scala.Function1<scala.xml.MetaData, java.lang.Object>);
    descriptor: (Lscala/Function1;)Lscala/Tuple2;
    flags: (0x0009) ACC_PUBLIC, ACC_STATIC
    Code:
      stack=2, locals=1, args_size=1
         0: getstatic     #17                 // Field scala/xml/Null$.MODULE$:Lscala/xml/Null$;
         3: aload_0
         4: invokevirtual #351                // Method scala/xml/Null$.span:(Lscala/Function1;)Lscala/Tuple2;
         7: areturn
      LocalVariableTable:
        Start  Length  Slot  Name   Signature
            0       8     0     p   Lscala/Function1;
    Signature: #349                         // (Lscala/Function1<Lscala/xml/MetaData;Ljava/lang/Object;>;)Lscala/Tuple2<Lscala/collection/Iterable<Lscala/xml/MetaData;>;Lscala/collection/Iterable<Lscala/xml/MetaData;>;>;
    MethodParameters:
      Name                           Flags
      p                              final

  public static java.lang.Object takeWhile(scala.Function1);
    descriptor: (Lscala/Function1;)Ljava/lang/Object;
    flags: (0x0009) ACC_PUBLIC, ACC_STATIC
    Code:
      stack=2, locals=1, args_size=1
         0: getstatic     #17                 // Field scala/xml/Null$.MODULE$:Lscala/xml/Null$;
         3: aload_0
         4: invokevirtual #354                // Method scala/xml/Null$.takeWhile:(Lscala/Function1;)Ljava/lang/Object;
         7: areturn
      LocalVariableTable:
        Start  Length  Slot  Name   Signature
            0       8     0     p   Lscala/Function1;
    MethodParameters:
      Name                           Flags
      p                              final

  public static java.lang.Object takeRight(int);
    descriptor: (I)Ljava/lang/Object;
    flags: (0x0009) ACC_PUBLIC, ACC_STATIC
    Code:
      stack=2, locals=1, args_size=1
         0: getstatic     #17                 // Field scala/xml/Null$.MODULE$:Lscala/xml/Null$;
         3: iload_0
         4: invokevirtual #357                // Method scala/xml/Null$.takeRight:(I)Ljava/lang/Object;
         7: areturn
      LocalVariableTable:
        Start  Length  Slot  Name   Signature
            0       8     0     n   I
    MethodParameters:
      Name                           Flags
      n                              final

  public static java.lang.Object take(int);
    descriptor: (I)Ljava/lang/Object;
    flags: (0x0009) ACC_PUBLIC, ACC_STATIC
    Code:
      stack=2, locals=1, args_size=1
         0: getstatic     #17                 // Field scala/xml/Null$.MODULE$:Lscala/xml/Null$;
         3: iload_0
         4: invokevirtual #360                // Method scala/xml/Null$.take:(I)Ljava/lang/Object;
         7: areturn
      LocalVariableTable:
        Start  Length  Slot  Name   Signature
            0       8     0     n   I
    MethodParameters:
      Name                           Flags
      n                              final

  public static scala.Tuple2<scala.collection.Iterable<scala.xml.MetaData>, scala.collection.Iterable<scala.xml.MetaData>> splitAt(int);
    descriptor: (I)Lscala/Tuple2;
    flags: (0x0009) ACC_PUBLIC, ACC_STATIC
    Code:
      stack=2, locals=1, args_size=1
         0: getstatic     #17                 // Field scala/xml/Null$.MODULE$:Lscala/xml/Null$;
         3: iload_0
         4: invokevirtual #365                // Method scala/xml/Null$.splitAt:(I)Lscala/Tuple2;
         7: areturn
      LocalVariableTable:
        Start  Length  Slot  Name   Signature
            0       8     0     n   I
    Signature: #363                         // (I)Lscala/Tuple2<Lscala/collection/Iterable<Lscala/xml/MetaData;>;Lscala/collection/Iterable<Lscala/xml/MetaData;>;>;
    MethodParameters:
      Name                           Flags
      n                              final

  public static scala.Tuple2<scala.collection.Iterable<scala.xml.MetaData>, scala.collection.Iterable<scala.xml.MetaData>> partition(scala.Function1<scala.xml.MetaData, java.lang.Object>);
    descriptor: (Lscala/Function1;)Lscala/Tuple2;
    flags: (0x0009) ACC_PUBLIC, ACC_STATIC
    Code:
      stack=2, locals=1, args_size=1
         0: getstatic     #17                 // Field scala/xml/Null$.MODULE$:Lscala/xml/Null$;
         3: aload_0
         4: invokevirtual #368                // Method scala/xml/Null$.partition:(Lscala/Function1;)Lscala/Tuple2;
         7: areturn
      LocalVariableTable:
        Start  Length  Slot  Name   Signature
            0       8     0     p   Lscala/Function1;
    Signature: #349                         // (Lscala/Function1<Lscala/xml/MetaData;Ljava/lang/Object;>;)Lscala/Tuple2<Lscala/collection/Iterable<Lscala/xml/MetaData;>;Lscala/collection/Iterable<Lscala/xml/MetaData;>;>;
    MethodParameters:
      Name                           Flags
      p                              final

  public static scala.collection.WithFilter<scala.xml.MetaData, scala.collection.Iterable> withFilter(scala.Function1<scala.xml.MetaData, java.lang.Object>);
    descriptor: (Lscala/Function1;)Lscala/collection/WithFilter;
    flags: (0x0009) ACC_PUBLIC, ACC_STATIC
    Code:
      stack=2, locals=1, args_size=1
         0: getstatic     #17                 // Field scala/xml/Null$.MODULE$:Lscala/xml/Null$;
         3: aload_0
         4: invokevirtual #373                // Method scala/xml/Null$.withFilter:(Lscala/Function1;)Lscala/collection/WithFilter;
         7: areturn
      LocalVariableTable:
        Start  Length  Slot  Name   Signature
            0       8     0     p   Lscala/Function1;
    Signature: #371                         // (Lscala/Function1<Lscala/xml/MetaData;Ljava/lang/Object;>;)Lscala/collection/WithFilter<Lscala/xml/MetaData;Lscala/collection/Iterable;>;
    MethodParameters:
      Name                           Flags
      p                              final

  public static java.lang.Object filterNot(scala.Function1);
    descriptor: (Lscala/Function1;)Ljava/lang/Object;
    flags: (0x0009) ACC_PUBLIC, ACC_STATIC
    Code:
      stack=2, locals=1, args_size=1
         0: getstatic     #17                 // Field scala/xml/Null$.MODULE$:Lscala/xml/Null$;
         3: aload_0
         4: invokevirtual #377                // Method scala/xml/Null$.filterNot:(Lscala/Function1;)Ljava/lang/Object;
         7: areturn
      LocalVariableTable:
        Start  Length  Slot  Name   Signature
            0       8     0  pred   Lscala/Function1;
    MethodParameters:
      Name                           Flags
      pred                           final

  public static java.lang.Object transpose(scala.Function1);
    descriptor: (Lscala/Function1;)Ljava/lang/Object;
    flags: (0x0009) ACC_PUBLIC, ACC_STATIC
    Code:
      stack=2, locals=1, args_size=1
         0: getstatic     #17                 // Field scala/xml/Null$.MODULE$:Lscala/xml/Null$;
         3: aload_0
         4: invokevirtual #380                // Method scala/xml/Null$.transpose:(Lscala/Function1;)Ljava/lang/Object;
         7: areturn
      LocalVariableTable:
        Start  Length  Slot  Name   Signature
            0       8     0 asIterable   Lscala/Function1;
    MethodParameters:
      Name                           Flags
      asIterable                     final

  public static scala.collection.View<scala.xml.MetaData> view(int, int);
    descriptor: (II)Lscala/collection/View;
    flags: (0x0009) ACC_PUBLIC, ACC_STATIC
    Code:
      stack=3, locals=2, args_size=2
         0: getstatic     #17                 // Field scala/xml/Null$.MODULE$:Lscala/xml/Null$;
         3: iload_0
         4: iload_1
         5: invokevirtual #385                // Method scala/xml/Null$.view:(II)Lscala/collection/View;
         8: areturn
      LocalVariableTable:
        Start  Length  Slot  Name   Signature
            0       9     0  from   I
            0       9     1 until   I
    Signature: #383                         // (II)Lscala/collection/View<Lscala/xml/MetaData;>;
    Deprecated: true
    MethodParameters:
      Name                           Flags
      from                           final
      until                          final

  public static int sizeCompare(scala.collection.Iterable<?>);
    descriptor: (Lscala/collection/Iterable;)I
    flags: (0x0009) ACC_PUBLIC, ACC_STATIC
    Code:
      stack=2, locals=1, args_size=1
         0: getstatic     #17                 // Field scala/xml/Null$.MODULE$:Lscala/xml/Null$;
         3: aload_0
         4: invokevirtual #390                // Method scala/xml/Null$.sizeCompare:(Lscala/collection/Iterable;)I
         7: ireturn
      LocalVariableTable:
        Start  Length  Slot  Name   Signature
            0       8     0  that   Lscala/collection/Iterable;
    Signature: #388                         // (Lscala/collection/Iterable<*>;)I
    MethodParameters:
      Name                           Flags
      that                           final

  public static scala.collection.IterableOps sizeIs();
    descriptor: ()Lscala/collection/IterableOps;
    flags: (0x0009) ACC_PUBLIC, ACC_STATIC
    Code:
      stack=1, locals=0, args_size=0
         0: getstatic     #17                 // Field scala/xml/Null$.MODULE$:Lscala/xml/Null$;
         3: invokevirtual #393                // Method scala/xml/Null$.sizeIs:()Lscala/collection/IterableOps;
         6: areturn

  public static int sizeCompare(int);
    descriptor: (I)I
    flags: (0x0009) ACC_PUBLIC, ACC_STATIC
    Code:
      stack=2, locals=1, args_size=1
         0: getstatic     #17                 // Field scala/xml/Null$.MODULE$:Lscala/xml/Null$;
         3: iload_0
         4: invokevirtual #396                // Method scala/xml/Null$.sizeCompare:(I)I
         7: ireturn
      LocalVariableTable:
        Start  Length  Slot  Name   Signature
            0       8     0 otherSize   I
    MethodParameters:
      Name                           Flags
      otherSize                      final

  public static scala.collection.View<scala.xml.MetaData> view();
    descriptor: ()Lscala/collection/View;
    flags: (0x0009) ACC_PUBLIC, ACC_STATIC
    Code:
      stack=1, locals=0, args_size=0
         0: getstatic     #17                 // Field scala/xml/Null$.MODULE$:Lscala/xml/Null$;
         3: invokevirtual #400                // Method scala/xml/Null$.view:()Lscala/collection/View;
         6: areturn
    Signature: #398                         // ()Lscala/collection/View<Lscala/xml/MetaData;>;

  public static scala.Option<scala.xml.MetaData> lastOption();
    descriptor: ()Lscala/Option;
    flags: (0x0009) ACC_PUBLIC, ACC_STATIC
    Code:
      stack=1, locals=0, args_size=0
         0: getstatic     #17                 // Field scala/xml/Null$.MODULE$:Lscala/xml/Null$;
         3: invokevirtual #405                // Method scala/xml/Null$.lastOption:()Lscala/Option;
         6: areturn
    Signature: #403                         // ()Lscala/Option<Lscala/xml/MetaData;>;

  public static java.lang.Object last();
    descriptor: ()Ljava/lang/Object;
    flags: (0x0009) ACC_PUBLIC, ACC_STATIC
    Code:
      stack=1, locals=0, args_size=0
         0: getstatic     #17                 // Field scala/xml/Null$.MODULE$:Lscala/xml/Null$;
         3: invokevirtual #408                // Method scala/xml/Null$.last:()Ljava/lang/Object;
         6: areturn

  public static scala.Option<scala.xml.MetaData> headOption();
    descriptor: ()Lscala/Option;
    flags: (0x0009) ACC_PUBLIC, ACC_STATIC
    Code:
      stack=1, locals=0, args_size=0
         0: getstatic     #17                 // Field scala/xml/Null$.MODULE$:Lscala/xml/Null$;
         3: invokevirtual #411                // Method scala/xml/Null$.headOption:()Lscala/Option;
         6: areturn
    Signature: #403                         // ()Lscala/Option<Lscala/xml/MetaData;>;

  public static java.lang.Object head();
    descriptor: ()Ljava/lang/Object;
    flags: (0x0009) ACC_PUBLIC, ACC_STATIC
    Code:
      stack=1, locals=0, args_size=0
         0: getstatic     #17                 // Field scala/xml/Null$.MODULE$:Lscala/xml/Null$;
         3: invokevirtual #414                // Method scala/xml/Null$.head:()Ljava/lang/Object;
         6: areturn

  public static scala.collection.IterableFactory<scala.collection.Iterable> companion();
    descriptor: ()Lscala/collection/IterableFactory;
    flags: (0x0009) ACC_PUBLIC, ACC_STATIC
    Code:
      stack=1, locals=0, args_size=0
         0: getstatic     #17                 // Field scala/xml/Null$.MODULE$:Lscala/xml/Null$;
         3: invokevirtual #417                // Method scala/xml/Null$.companion:()Lscala/collection/IterableFactory;
         6: areturn
    Signature: #206                         // ()Lscala/collection/IterableFactory<Lscala/collection/Iterable;>;
    Deprecated: true

  public static java.lang.Object repr();
    descriptor: ()Ljava/lang/Object;
    flags: (0x0009) ACC_PUBLIC, ACC_STATIC
    Code:
      stack=1, locals=0, args_size=0
         0: getstatic     #17                 // Field scala/xml/Null$.MODULE$:Lscala/xml/Null$;
         3: invokevirtual #420                // Method scala/xml/Null$.repr:()Ljava/lang/Object;
         6: areturn
    Deprecated: true

  public static boolean isTraversableAgain();
    descriptor: ()Z
    flags: (0x0009) ACC_PUBLIC, ACC_STATIC
    Code:
      stack=1, locals=0, args_size=0
         0: getstatic     #17                 // Field scala/xml/Null$.MODULE$:Lscala/xml/Null$;
         3: invokevirtual #423                // Method scala/xml/Null$.isTraversableAgain:()Z
         6: ireturn

  public static scala.collection.Iterable<scala.xml.MetaData> toTraversable();
    descriptor: ()Lscala/collection/Iterable;
    flags: (0x0009) ACC_PUBLIC, ACC_STATIC
    Code:
      stack=1, locals=0, args_size=0
         0: getstatic     #17                 // Field scala/xml/Null$.MODULE$:Lscala/xml/Null$;
         3: invokevirtual #427                // Method scala/xml/Null$.toTraversable:()Lscala/collection/Iterable;
         6: areturn
    Signature: #425                         // ()Lscala/collection/Iterable<Lscala/xml/MetaData;>;
    Deprecated: true

  public static java.lang.Object toArray(scala.reflect.ClassTag);
    descriptor: (Lscala/reflect/ClassTag;)Ljava/lang/Object;
    flags: (0x0009) ACC_PUBLIC, ACC_STATIC
    Code:
      stack=2, locals=1, args_size=1
         0: getstatic     #17                 // Field scala/xml/Null$.MODULE$:Lscala/xml/Null$;
         3: aload_0
         4: invokevirtual #432                // Method scala/xml/Null$.toArray:(Lscala/reflect/ClassTag;)Ljava/lang/Object;
         7: areturn
      LocalVariableTable:
        Start  Length  Slot  Name   Signature
            0       8     0 evidence$2   Lscala/reflect/ClassTag;
    MethodParameters:
      Name                           Flags
      evidence$2                     final

  public static <B extends java.lang.Object> scala.collection.mutable.Buffer<B> toBuffer();
    descriptor: ()Lscala/collection/mutable/Buffer;
    flags: (0x0009) ACC_PUBLIC, ACC_STATIC
    Code:
      stack=1, locals=0, args_size=0
         0: getstatic     #17                 // Field scala/xml/Null$.MODULE$:Lscala/xml/Null$;
         3: invokevirtual #438                // Method scala/xml/Null$.toBuffer:()Lscala/collection/mutable/Buffer;
         6: areturn
    Signature: #436                         // <B:Ljava/lang/Object;>()Lscala/collection/mutable/Buffer<TB;>;

  public static scala.collection.immutable.Stream<scala.xml.MetaData> toStream();
    descriptor: ()Lscala/collection/immutable/Stream;
    flags: (0x0009) ACC_PUBLIC, ACC_STATIC
    Code:
      stack=1, locals=0, args_size=0
         0: getstatic     #17                 // Field scala/xml/Null$.MODULE$:Lscala/xml/Null$;
         3: invokevirtual #443                // Method scala/xml/Null$.toStream:()Lscala/collection/immutable/Stream;
         6: areturn
    Signature: #441                         // ()Lscala/collection/immutable/Stream<Lscala/xml/MetaData;>;
    Deprecated: true

  public static scala.collection.immutable.IndexedSeq<scala.xml.MetaData> toIndexedSeq();
    descriptor: ()Lscala/collection/immutable/IndexedSeq;
    flags: (0x0009) ACC_PUBLIC, ACC_STATIC
    Code:
      stack=1, locals=0, args_size=0
         0: getstatic     #17                 // Field scala/xml/Null$.MODULE$:Lscala/xml/Null$;
         3: invokevirtual #448                // Method scala/xml/Null$.toIndexedSeq:()Lscala/collection/immutable/IndexedSeq;
         6: areturn
    Signature: #446                         // ()Lscala/collection/immutable/IndexedSeq<Lscala/xml/MetaData;>;

  public static scala.collection.immutable.Seq<scala.xml.MetaData> toSeq();
    descriptor: ()Lscala/collection/immutable/Seq;
    flags: (0x0009) ACC_PUBLIC, ACC_STATIC
    Code:
      stack=1, locals=0, args_size=0
         0: getstatic     #17                 // Field scala/xml/Null$.MODULE$:Lscala/xml/Null$;
         3: invokevirtual #453                // Method scala/xml/Null$.toSeq:()Lscala/collection/immutable/Seq;
         6: areturn
    Signature: #451                         // ()Lscala/collection/immutable/Seq<Lscala/xml/MetaData;>;

  public static <B extends java.lang.Object> scala.collection.immutable.Set<B> toSet();
    descriptor: ()Lscala/collection/immutable/Set;
    flags: (0x0009) ACC_PUBLIC, ACC_STATIC
    Code:
      stack=1, locals=0, args_size=0
         0: getstatic     #17                 // Field scala/xml/Null$.MODULE$:Lscala/xml/Null$;
         3: invokevirtual #458                // Method scala/xml/Null$.toSet:()Lscala/collection/immutable/Set;
         6: areturn
    Signature: #456                         // <B:Ljava/lang/Object;>()Lscala/collection/immutable/Set<TB;>;

  public static <K extends java.lang.Object, V extends java.lang.Object> scala.collection.immutable.Map<K, V> toMap(scala.$less$colon$less<scala.xml.MetaData, scala.Tuple2<K, V>>);
    descriptor: (Lscala/$less$colon$less;)Lscala/collection/immutable/Map;
    flags: (0x0009) ACC_PUBLIC, ACC_STATIC
    Code:
      stack=2, locals=1, args_size=1
         0: getstatic     #17                 // Field scala/xml/Null$.MODULE$:Lscala/xml/Null$;
         3: aload_0
         4: invokevirtual #464                // Method scala/xml/Null$.toMap:(Lscala/$less$colon$less;)Lscala/collection/immutable/Map;
         7: areturn
      LocalVariableTable:
        Start  Length  Slot  Name   Signature
            0       8     0    ev   Lscala/$less$colon$less;
    Signature: #461                         // <K:Ljava/lang/Object;V:Ljava/lang/Object;>(Lscala/$less$colon$less<Lscala/xml/MetaData;Lscala/Tuple2<TK;TV;>;>;)Lscala/collection/immutable/Map<TK;TV;>;
    MethodParameters:
      Name                           Flags
      ev                             final

  public static scala.collection.immutable.Vector<scala.xml.MetaData> toVector();
    descriptor: ()Lscala/collection/immutable/Vector;
    flags: (0x0009) ACC_PUBLIC, ACC_STATIC
    Code:
      stack=1, locals=0, args_size=0
         0: getstatic     #17                 // Field scala/xml/Null$.MODULE$:Lscala/xml/Null$;
         3: invokevirtual #470                // Method scala/xml/Null$.toVector:()Lscala/collection/immutable/Vector;
         6: areturn
    Signature: #468                         // ()Lscala/collection/immutable/Vector<Lscala/xml/MetaData;>;

  public static scala.collection.immutable.List<scala.xml.MetaData> toList();
    descriptor: ()Lscala/collection/immutable/List;
    flags: (0x0009) ACC_PUBLIC, ACC_STATIC
    Code:
      stack=1, locals=0, args_size=0
         0: getstatic     #17                 // Field scala/xml/Null$.MODULE$:Lscala/xml/Null$;
         3: invokevirtual #475                // Method scala/xml/Null$.toList:()Lscala/collection/immutable/List;
         6: areturn
    Signature: #473                         // ()Lscala/collection/immutable/List<Lscala/xml/MetaData;>;

  public static scala.collection.Iterator<scala.xml.MetaData> toIterator();
    descriptor: ()Lscala/collection/Iterator;
    flags: (0x0009) ACC_PUBLIC, ACC_STATIC
    Code:
      stack=1, locals=0, args_size=0
         0: getstatic     #17                 // Field scala/xml/Null$.MODULE$:Lscala/xml/Null$;
         3: invokevirtual #479                // Method scala/xml/Null$.toIterator:()Lscala/collection/Iterator;
         6: areturn
    Signature: #477                         // ()Lscala/collection/Iterator<Lscala/xml/MetaData;>;
    Deprecated: true

  public static <C1 extends java.lang.Object> C1 to(scala.collection.Factory<scala.xml.MetaData, C1>);
    descriptor: (Lscala/collection/Factory;)Ljava/lang/Object;
    flags: (0x0009) ACC_PUBLIC, ACC_STATIC
    Code:
      stack=2, locals=1, args_size=1
         0: getstatic     #17                 // Field scala/xml/Null$.MODULE$:Lscala/xml/Null$;
         3: aload_0
         4: invokevirtual #485                // Method scala/xml/Null$.to:(Lscala/collection/Factory;)Ljava/lang/Object;
         7: areturn
      LocalVariableTable:
        Start  Length  Slot  Name   Signature
            0       8     0 factory   Lscala/collection/Factory;
    Signature: #482                         // <C1:Ljava/lang/Object;>(Lscala/collection/Factory<Lscala/xml/MetaData;TC1;>;)TC1;
    MethodParameters:
      Name                           Flags
      factory                        final

  public static scala.collection.mutable.StringBuilder addString(scala.collection.mutable.StringBuilder);
    descriptor: (Lscala/collection/mutable/StringBuilder;)Lscala/collection/mutable/StringBuilder;
    flags: (0x0009) ACC_PUBLIC, ACC_STATIC
    Code:
      stack=2, locals=1, args_size=1
         0: getstatic     #17                 // Field scala/xml/Null$.MODULE$:Lscala/xml/Null$;
         3: aload_0
         4: invokevirtual #490                // Method scala/xml/Null$.addString:(Lscala/collection/mutable/StringBuilder;)Lscala/collection/mutable/StringBuilder;
         7: areturn
      LocalVariableTable:
        Start  Length  Slot  Name   Signature
            0       8     0     b   Lscala/collection/mutable/StringBuilder;
    MethodParameters:
      Name                           Flags
      b                              final

  public static scala.collection.mutable.StringBuilder addString(scala.collection.mutable.StringBuilder, java.lang.String);
    descriptor: (Lscala/collection/mutable/StringBuilder;Ljava/lang/String;)Lscala/collection/mutable/StringBuilder;
    flags: (0x0009) ACC_PUBLIC, ACC_STATIC
    Code:
      stack=3, locals=2, args_size=2
         0: getstatic     #17                 // Field scala/xml/Null$.MODULE$:Lscala/xml/Null$;
         3: aload_0
         4: aload_1
         5: invokevirtual #494                // Method scala/xml/Null$.addString:(Lscala/collection/mutable/StringBuilder;Ljava/lang/String;)Lscala/collection/mutable/StringBuilder;
         8: areturn
      LocalVariableTable:
        Start  Length  Slot  Name   Signature
            0       9     0     b   Lscala/collection/mutable/StringBuilder;
            0       9     1   sep   Ljava/lang/String;
    MethodParameters:
      Name                           Flags
      b                              final
      sep                            final

  public static scala.collection.mutable.StringBuilder addString(scala.collection.mutable.StringBuilder, java.lang.String, java.lang.String, java.lang.String);
    descriptor: (Lscala/collection/mutable/StringBuilder;Ljava/lang/String;Ljava/lang/String;Ljava/lang/String;)Lscala/collection/mutable/StringBuilder;
    flags: (0x0009) ACC_PUBLIC, ACC_STATIC
    Code:
      stack=5, locals=4, args_size=4
         0: getstatic     #17                 // Field scala/xml/Null$.MODULE$:Lscala/xml/Null$;
         3: aload_0
         4: aload_1
         5: aload_2
         6: aload_3
         7: invokevirtual #499                // Method scala/xml/Null$.addString:(Lscala/collection/mutable/StringBuilder;Ljava/lang/String;Ljava/lang/String;Ljava/lang/String;)Lscala/collection/mutable/StringBuilder;
        10: areturn
      LocalVariableTable:
        Start  Length  Slot  Name   Signature
            0      11     0     b   Lscala/collection/mutable/StringBuilder;
            0      11     1 start   Ljava/lang/String;
            0      11     2   sep   Ljava/lang/String;
            0      11     3   end   Ljava/lang/String;
    MethodParameters:
      Name                           Flags
      b                              final
      start                          final
      sep                            final
      end                            final

  public static java.lang.String mkString();
    descriptor: ()Ljava/lang/String;
    flags: (0x0009) ACC_PUBLIC, ACC_STATIC
    Code:
      stack=1, locals=0, args_size=0
         0: getstatic     #17                 // Field scala/xml/Null$.MODULE$:Lscala/xml/Null$;
         3: invokevirtual #502                // Method scala/xml/Null$.mkString:()Ljava/lang/String;
         6: areturn

  public static java.lang.String mkString(java.lang.String);
    descriptor: (Ljava/lang/String;)Ljava/lang/String;
    flags: (0x0009) ACC_PUBLIC, ACC_STATIC
    Code:
      stack=2, locals=1, args_size=1
         0: getstatic     #17                 // Field scala/xml/Null$.MODULE$:Lscala/xml/Null$;
         3: aload_0
         4: invokevirtual #505                // Method scala/xml/Null$.mkString:(Ljava/lang/String;)Ljava/lang/String;
         7: areturn
      LocalVariableTable:
        Start  Length  Slot  Name   Signature
            0       8     0   sep   Ljava/lang/String;
    MethodParameters:
      Name                           Flags
      sep                            final

  public static java.lang.String mkString(java.lang.String, java.lang.String, java.lang.String);
    descriptor: (Ljava/lang/String;Ljava/lang/String;Ljava/lang/String;)Ljava/lang/String;
    flags: (0x0009) ACC_PUBLIC, ACC_STATIC
    Code:
      stack=4, locals=3, args_size=3
         0: getstatic     #17                 // Field scala/xml/Null$.MODULE$:Lscala/xml/Null$;
         3: aload_0
         4: aload_1
         5: aload_2
         6: invokevirtual #508                // Method scala/xml/Null$.mkString:(Ljava/lang/String;Ljava/lang/String;Ljava/lang/String;)Ljava/lang/String;
         9: areturn
      LocalVariableTable:
        Start  Length  Slot  Name   Signature
            0      10     0 start   Ljava/lang/String;
            0      10     1   sep   Ljava/lang/String;
            0      10     2   end   Ljava/lang/String;
    MethodParameters:
      Name                           Flags
      start                          final
      sep                            final
      end                            final

  public static <B extends java.lang.Object> boolean corresponds(scala.collection.IterableOnce<B>, scala.Function2<scala.xml.MetaData, B, java.lang.Object>);
    descriptor: (Lscala/collection/IterableOnce;Lscala/Function2;)Z
    flags: (0x0009) ACC_PUBLIC, ACC_STATIC
    Code:
      stack=3, locals=2, args_size=2
         0: getstatic     #17                 // Field scala/xml/Null$.MODULE$:Lscala/xml/Null$;
         3: aload_0
         4: aload_1
         5: invokevirtual #513                // Method scala/xml/Null$.corresponds:(Lscala/collection/IterableOnce;Lscala/Function2;)Z
         8: ireturn
      LocalVariableTable:
        Start  Length  Slot  Name   Signature
            0       9     0  that   Lscala/collection/IterableOnce;
            0       9     1     p   Lscala/Function2;
    Signature: #511                         // <B:Ljava/lang/Object;>(Lscala/collection/IterableOnce<TB;>;Lscala/Function2<Lscala/xml/MetaData;TB;Ljava/lang/Object;>;)Z
    MethodParameters:
      Name                           Flags
      that                           final
      p                              final

  public static <B extends java.lang.Object> B aggregate(scala.Function0<B>, scala.Function2<B, scala.xml.MetaData, B>, scala.Function2<B, B, B>);
    descriptor: (Lscala/Function0;Lscala/Function2;Lscala/Function2;)Ljava/lang/Object;
    flags: (0x0009) ACC_PUBLIC, ACC_STATIC
    Code:
      stack=4, locals=3, args_size=3
         0: getstatic     #17                 // Field scala/xml/Null$.MODULE$:Lscala/xml/Null$;
         3: aload_0
         4: aload_1
         5: aload_2
         6: invokevirtual #520                // Method scala/xml/Null$.aggregate:(Lscala/Function0;Lscala/Function2;Lscala/Function2;)Ljava/lang/Object;
         9: areturn
      LocalVariableTable:
        Start  Length  Slot  Name   Signature
            0      10     0     z   Lscala/Function0;
            0      10     1 seqop   Lscala/Function2;
            0      10     2 combop   Lscala/Function2;
    Signature: #516                         // <B:Ljava/lang/Object;>(Lscala/Function0<TB;>;Lscala/Function2<TB;Lscala/xml/MetaData;TB;>;Lscala/Function2<TB;TB;TB;>;)TB;
    Deprecated: true
    MethodParameters:
      Name                           Flags
      z                              final
      seqop                          final
      combop                         final

  public static <B extends java.lang.Object> scala.Option<B> collectFirst(scala.PartialFunction<scala.xml.MetaData, B>);
    descriptor: (Lscala/PartialFunction;)Lscala/Option;
    flags: (0x0009) ACC_PUBLIC, ACC_STATIC
    Code:
      stack=2, locals=1, args_size=1
         0: getstatic     #17                 // Field scala/xml/Null$.MODULE$:Lscala/xml/Null$;
         3: aload_0
         4: invokevirtual #526                // Method scala/xml/Null$.collectFirst:(Lscala/PartialFunction;)Lscala/Option;
         7: areturn
      LocalVariableTable:
        Start  Length  Slot  Name   Signature
            0       8     0    pf   Lscala/PartialFunction;
    Signature: #524                         // <B:Ljava/lang/Object;>(Lscala/PartialFunction<Lscala/xml/MetaData;TB;>;)Lscala/Option<TB;>;
    MethodParameters:
      Name                           Flags
      pf                             final

  public static <B extends java.lang.Object> scala.Option<scala.xml.MetaData> minByOption(scala.Function1<scala.xml.MetaData, B>, scala.math.Ordering<B>);
    descriptor: (Lscala/Function1;Lscala/math/Ordering;)Lscala/Option;
    flags: (0x0009) ACC_PUBLIC, ACC_STATIC
    Code:
      stack=3, locals=2, args_size=2
         0: getstatic     #17                 // Field scala/xml/Null$.MODULE$:Lscala/xml/Null$;
         3: aload_0
         4: aload_1
         5: invokevirtual #532                // Method scala/xml/Null$.minByOption:(Lscala/Function1;Lscala/math/Ordering;)Lscala/Option;
         8: areturn
      LocalVariableTable:
        Start  Length  Slot  Name   Signature
            0       9     0     f   Lscala/Function1;
            0       9     1   cmp   Lscala/math/Ordering;
    Signature: #529                         // <B:Ljava/lang/Object;>(Lscala/Function1<Lscala/xml/MetaData;TB;>;Lscala/math/Ordering<TB;>;)Lscala/Option<Lscala/xml/MetaData;>;
    MethodParameters:
      Name                           Flags
      f                              final
      cmp                            final

  public static java.lang.Object minBy(scala.Function1, scala.math.Ordering);
    descriptor: (Lscala/Function1;Lscala/math/Ordering;)Ljava/lang/Object;
    flags: (0x0009) ACC_PUBLIC, ACC_STATIC
    Code:
      stack=3, locals=2, args_size=2
         0: getstatic     #17                 // Field scala/xml/Null$.MODULE$:Lscala/xml/Null$;
         3: aload_0
         4: aload_1
         5: invokevirtual #537                // Method scala/xml/Null$.minBy:(Lscala/Function1;Lscala/math/Ordering;)Ljava/lang/Object;
         8: areturn
      LocalVariableTable:
        Start  Length  Slot  Name   Signature
            0       9     0     f   Lscala/Function1;
            0       9     1   cmp   Lscala/math/Ordering;
    MethodParameters:
      Name                           Flags
      f                              final
      cmp                            final

  public static <B extends java.lang.Object> scala.Option<scala.xml.MetaData> maxByOption(scala.Function1<scala.xml.MetaData, B>, scala.math.Ordering<B>);
    descriptor: (Lscala/Function1;Lscala/math/Ordering;)Lscala/Option;
    flags: (0x0009) ACC_PUBLIC, ACC_STATIC
    Code:
      stack=3, locals=2, args_size=2
         0: getstatic     #17                 // Field scala/xml/Null$.MODULE$:Lscala/xml/Null$;
         3: aload_0
         4: aload_1
         5: invokevirtual #540                // Method scala/xml/Null$.maxByOption:(Lscala/Function1;Lscala/math/Ordering;)Lscala/Option;
         8: areturn
      LocalVariableTable:
        Start  Length  Slot  Name   Signature
            0       9     0     f   Lscala/Function1;
            0       9     1   cmp   Lscala/math/Ordering;
    Signature: #529                         // <B:Ljava/lang/Object;>(Lscala/Function1<Lscala/xml/MetaData;TB;>;Lscala/math/Ordering<TB;>;)Lscala/Option<Lscala/xml/MetaData;>;
    MethodParameters:
      Name                           Flags
      f                              final
      cmp                            final

  public static java.lang.Object maxBy(scala.Function1, scala.math.Ordering);
    descriptor: (Lscala/Function1;Lscala/math/Ordering;)Ljava/lang/Object;
    flags: (0x0009) ACC_PUBLIC, ACC_STATIC
    Code:
      stack=3, locals=2, args_size=2
         0: getstatic     #17                 // Field scala/xml/Null$.MODULE$:Lscala/xml/Null$;
         3: aload_0
         4: aload_1
         5: invokevirtual #543                // Method scala/xml/Null$.maxBy:(Lscala/Function1;Lscala/math/Ordering;)Ljava/lang/Object;
         8: areturn
      LocalVariableTable:
        Start  Length  Slot  Name   Signature
            0       9     0     f   Lscala/Function1;
            0       9     1   cmp   Lscala/math/Ordering;
    MethodParameters:
      Name                           Flags
      f                              final
      cmp                            final

  public static <B extends java.lang.Object> scala.Option<scala.xml.MetaData> maxOption(scala.math.Ordering<B>);
    descriptor: (Lscala/math/Ordering;)Lscala/Option;
    flags: (0x0009) ACC_PUBLIC, ACC_STATIC
    Code:
      stack=2, locals=1, args_size=1
         0: getstatic     #17                 // Field scala/xml/Null$.MODULE$:Lscala/xml/Null$;
         3: aload_0
         4: invokevirtual #549                // Method scala/xml/Null$.maxOption:(Lscala/math/Ordering;)Lscala/Option;
         7: areturn
      LocalVariableTable:
        Start  Length  Slot  Name   Signature
            0       8     0   ord   Lscala/math/Ordering;
    Signature: #546                         // <B:Ljava/lang/Object;>(Lscala/math/Ordering<TB;>;)Lscala/Option<Lscala/xml/MetaData;>;
    MethodParameters:
      Name                           Flags
      ord                            final

  public static java.lang.Object max(scala.math.Ordering);
    descriptor: (Lscala/math/Ordering;)Ljava/lang/Object;
    flags: (0x0009) ACC_PUBLIC, ACC_STATIC
    Code:
      stack=2, locals=1, args_size=1
         0: getstatic     #17                 // Field scala/xml/Null$.MODULE$:Lscala/xml/Null$;
         3: aload_0
         4: invokevirtual #553                // Method scala/xml/Null$.max:(Lscala/math/Ordering;)Ljava/lang/Object;
         7: areturn
      LocalVariableTable:
        Start  Length  Slot  Name   Signature
            0       8     0   ord   Lscala/math/Ordering;
    MethodParameters:
      Name                           Flags
      ord                            final

  public static <B extends java.lang.Object> scala.Option<scala.xml.MetaData> minOption(scala.math.Ordering<B>);
    descriptor: (Lscala/math/Ordering;)Lscala/Option;
    flags: (0x0009) ACC_PUBLIC, ACC_STATIC
    Code:
      stack=2, locals=1, args_size=1
         0: getstatic     #17                 // Field scala/xml/Null$.MODULE$:Lscala/xml/Null$;
         3: aload_0
         4: invokevirtual #556                // Method scala/xml/Null$.minOption:(Lscala/math/Ordering;)Lscala/Option;
         7: areturn
      LocalVariableTable:
        Start  Length  Slot  Name   Signature
            0       8     0   ord   Lscala/math/Ordering;
    Signature: #546                         // <B:Ljava/lang/Object;>(Lscala/math/Ordering<TB;>;)Lscala/Option<Lscala/xml/MetaData;>;
    MethodParameters:
      Name                           Flags
      ord                            final

  public static java.lang.Object min(scala.math.Ordering);
    descriptor: (Lscala/math/Ordering;)Ljava/lang/Object;
    flags: (0x0009) ACC_PUBLIC, ACC_STATIC
    Code:
      stack=2, locals=1, args_size=1
         0: getstatic     #17                 // Field scala/xml/Null$.MODULE$:Lscala/xml/Null$;
         3: aload_0
         4: invokevirtual #559                // Method scala/xml/Null$.min:(Lscala/math/Ordering;)Ljava/lang/Object;
         7: areturn
      LocalVariableTable:
        Start  Length  Slot  Name   Signature
            0       8     0   ord   Lscala/math/Ordering;
    MethodParameters:
      Name                           Flags
      ord                            final

  public static <B extends java.lang.Object> B product(scala.math.Numeric<B>);
    descriptor: (Lscala/math/Numeric;)Ljava/lang/Object;
    flags: (0x0009) ACC_PUBLIC, ACC_STATIC
    Code:
      stack=2, locals=1, args_size=1
         0: getstatic     #17                 // Field scala/xml/Null$.MODULE$:Lscala/xml/Null$;
         3: aload_0
         4: invokevirtual #565                // Method scala/xml/Null$.product:(Lscala/math/Numeric;)Ljava/lang/Object;
         7: areturn
      LocalVariableTable:
        Start  Length  Slot  Name   Signature
            0       8     0   num   Lscala/math/Numeric;
    Signature: #562                         // <B:Ljava/lang/Object;>(Lscala/math/Numeric<TB;>;)TB;
    MethodParameters:
      Name                           Flags
      num                            final

  public static <B extends java.lang.Object> B sum(scala.math.Numeric<B>);
    descriptor: (Lscala/math/Numeric;)Ljava/lang/Object;
    flags: (0x0009) ACC_PUBLIC, ACC_STATIC
    Code:
      stack=2, locals=1, args_size=1
         0: getstatic     #17                 // Field scala/xml/Null$.MODULE$:Lscala/xml/Null$;
         3: aload_0
         4: invokevirtual #569                // Method scala/xml/Null$.sum:(Lscala/math/Numeric;)Ljava/lang/Object;
         7: areturn
      LocalVariableTable:
        Start  Length  Slot  Name   Signature
            0       8     0   num   Lscala/math/Numeric;
    Signature: #562                         // <B:Ljava/lang/Object;>(Lscala/math/Numeric<TB;>;)TB;
    MethodParameters:
      Name                           Flags
      num                            final

  public static <B extends java.lang.Object> int copyToArray(java.lang.Object, int, int);
    descriptor: (Ljava/lang/Object;II)I
    flags: (0x0009) ACC_PUBLIC, ACC_STATIC
    Code:
      stack=4, locals=3, args_size=3
         0: getstatic     #17                 // Field scala/xml/Null$.MODULE$:Lscala/xml/Null$;
         3: aload_0
         4: iload_1
         5: iload_2
         6: invokevirtual #576                // Method scala/xml/Null$.copyToArray:(Ljava/lang/Object;II)I
         9: ireturn
      LocalVariableTable:
        Start  Length  Slot  Name   Signature
            0      10     0    xs   Ljava/lang/Object;
            0      10     1 start   I
            0      10     2   len   I
    Signature: #572                         // <B:Ljava/lang/Object;>(Ljava/lang/Object;II)I
    MethodParameters:
      Name                           Flags
      xs                             final
      start                          final
      len                            final

  public static <B extends java.lang.Object> int copyToArray(java.lang.Object, int);
    descriptor: (Ljava/lang/Object;I)I
    flags: (0x0009) ACC_PUBLIC, ACC_STATIC
    Code:
      stack=3, locals=2, args_size=2
         0: getstatic     #17                 // Field scala/xml/Null$.MODULE$:Lscala/xml/Null$;
         3: aload_0
         4: iload_1
         5: invokevirtual #580                // Method scala/xml/Null$.copyToArray:(Ljava/lang/Object;I)I
         8: ireturn
      LocalVariableTable:
        Start  Length  Slot  Name   Signature
            0       9     0    xs   Ljava/lang/Object;
            0       9     1 start   I
    Signature: #578                         // <B:Ljava/lang/Object;>(Ljava/lang/Object;I)I
    MethodParameters:
      Name                           Flags
      xs                             final
      start                          final

  public static <B extends java.lang.Object> int copyToArray(java.lang.Object);
    descriptor: (Ljava/lang/Object;)I
    flags: (0x0009) ACC_PUBLIC, ACC_STATIC
    Code:
      stack=2, locals=1, args_size=1
         0: getstatic     #17                 // Field scala/xml/Null$.MODULE$:Lscala/xml/Null$;
         3: aload_0
         4: invokevirtual #584                // Method scala/xml/Null$.copyToArray:(Ljava/lang/Object;)I
         7: ireturn
      LocalVariableTable:
        Start  Length  Slot  Name   Signature
            0       8     0    xs   Ljava/lang/Object;
    Signature: #582                         // <B:Ljava/lang/Object;>(Ljava/lang/Object;)I
    MethodParameters:
      Name                           Flags
      xs                             final

  public static <B extends java.lang.Object> void copyToBuffer(scala.collection.mutable.Buffer<B>);
    descriptor: (Lscala/collection/mutable/Buffer;)V
    flags: (0x0009) ACC_PUBLIC, ACC_STATIC
    Code:
      stack=2, locals=1, args_size=1
         0: getstatic     #17                 // Field scala/xml/Null$.MODULE$:Lscala/xml/Null$;
         3: aload_0
         4: invokevirtual #590                // Method scala/xml/Null$.copyToBuffer:(Lscala/collection/mutable/Buffer;)V
         7: return
      LocalVariableTable:
        Start  Length  Slot  Name   Signature
            0       8     0  dest   Lscala/collection/mutable/Buffer;
    Signature: #587                         // <B:Ljava/lang/Object;>(Lscala/collection/mutable/Buffer<TB;>;)V
    Deprecated: true
    MethodParameters:
      Name                           Flags
      dest                           final

  public static boolean nonEmpty();
    descriptor: ()Z
    flags: (0x0009) ACC_PUBLIC, ACC_STATIC
    Code:
      stack=1, locals=0, args_size=0
         0: getstatic     #17                 // Field scala/xml/Null$.MODULE$:Lscala/xml/Null$;
         3: invokevirtual #594                // Method scala/xml/Null$.nonEmpty:()Z
         6: ireturn

  public static boolean isEmpty();
    descriptor: ()Z
    flags: (0x0009) ACC_PUBLIC, ACC_STATIC
    Code:
      stack=1, locals=0, args_size=0
         0: getstatic     #17                 // Field scala/xml/Null$.MODULE$:Lscala/xml/Null$;
         3: invokevirtual #597                // Method scala/xml/Null$.isEmpty:()Z
         6: ireturn

  public static <B extends java.lang.Object> scala.Option<B> reduceRightOption(scala.Function2<scala.xml.MetaData, B, B>);
    descriptor: (Lscala/Function2;)Lscala/Option;
    flags: (0x0009) ACC_PUBLIC, ACC_STATIC
    Code:
      stack=2, locals=1, args_size=1
         0: getstatic     #17                 // Field scala/xml/Null$.MODULE$:Lscala/xml/Null$;
         3: aload_0
         4: invokevirtual #602                // Method scala/xml/Null$.reduceRightOption:(Lscala/Function2;)Lscala/Option;
         7: areturn
      LocalVariableTable:
        Start  Length  Slot  Name   Signature
            0       8     0    op   Lscala/Function2;
    Signature: #600                         // <B:Ljava/lang/Object;>(Lscala/Function2<Lscala/xml/MetaData;TB;TB;>;)Lscala/Option<TB;>;
    MethodParameters:
      Name                           Flags
      op                             final

  public static <B extends java.lang.Object> scala.Option<B> reduceLeftOption(scala.Function2<B, scala.xml.MetaData, B>);
    descriptor: (Lscala/Function2;)Lscala/Option;
    flags: (0x0009) ACC_PUBLIC, ACC_STATIC
    Code:
      stack=2, locals=1, args_size=1
         0: getstatic     #17                 // Field scala/xml/Null$.MODULE$:Lscala/xml/Null$;
         3: aload_0
         4: invokevirtual #606                // Method scala/xml/Null$.reduceLeftOption:(Lscala/Function2;)Lscala/Option;
         7: areturn
      LocalVariableTable:
        Start  Length  Slot  Name   Signature
            0       8     0    op   Lscala/Function2;
    Signature: #604                         // <B:Ljava/lang/Object;>(Lscala/Function2<TB;Lscala/xml/MetaData;TB;>;)Lscala/Option<TB;>;
    MethodParameters:
      Name                           Flags
      op                             final

  public static <B extends java.lang.Object> B reduceRight(scala.Function2<scala.xml.MetaData, B, B>);
    descriptor: (Lscala/Function2;)Ljava/lang/Object;
    flags: (0x0009) ACC_PUBLIC, ACC_STATIC
    Code:
      stack=2, locals=1, args_size=1
         0: getstatic     #17                 // Field scala/xml/Null$.MODULE$:Lscala/xml/Null$;
         3: aload_0
         4: invokevirtual #611                // Method scala/xml/Null$.reduceRight:(Lscala/Function2;)Ljava/lang/Object;
         7: areturn
      LocalVariableTable:
        Start  Length  Slot  Name   Signature
            0       8     0    op   Lscala/Function2;
    Signature: #609                         // <B:Ljava/lang/Object;>(Lscala/Function2<Lscala/xml/MetaData;TB;TB;>;)TB;
    MethodParameters:
      Name                           Flags
      op                             final

  public static <B extends java.lang.Object> B reduceLeft(scala.Function2<B, scala.xml.MetaData, B>);
    descriptor: (Lscala/Function2;)Ljava/lang/Object;
    flags: (0x0009) ACC_PUBLIC, ACC_STATIC
    Code:
      stack=2, locals=1, args_size=1
         0: getstatic     #17                 // Field scala/xml/Null$.MODULE$:Lscala/xml/Null$;
         3: aload_0
         4: invokevirtual #615                // Method scala/xml/Null$.reduceLeft:(Lscala/Function2;)Ljava/lang/Object;
         7: areturn
      LocalVariableTable:
        Start  Length  Slot  Name   Signature
            0       8     0    op   Lscala/Function2;
    Signature: #613                         // <B:Ljava/lang/Object;>(Lscala/Function2<TB;Lscala/xml/MetaData;TB;>;)TB;
    MethodParameters:
      Name                           Flags
      op                             final

  public static <B extends java.lang.Object> scala.Option<B> reduceOption(scala.Function2<B, B, B>);
    descriptor: (Lscala/Function2;)Lscala/Option;
    flags: (0x0009) ACC_PUBLIC, ACC_STATIC
    Code:
      stack=2, locals=1, args_size=1
         0: getstatic     #17                 // Field scala/xml/Null$.MODULE$:Lscala/xml/Null$;
         3: aload_0
         4: invokevirtual #619                // Method scala/xml/Null$.reduceOption:(Lscala/Function2;)Lscala/Option;
         7: areturn
      LocalVariableTable:
        Start  Length  Slot  Name   Signature
            0       8     0    op   Lscala/Function2;
    Signature: #617                         // <B:Ljava/lang/Object;>(Lscala/Function2<TB;TB;TB;>;)Lscala/Option<TB;>;
    MethodParameters:
      Name                           Flags
      op                             final

  public static <B extends java.lang.Object> B reduce(scala.Function2<B, B, B>);
    descriptor: (Lscala/Function2;)Ljava/lang/Object;
    flags: (0x0009) ACC_PUBLIC, ACC_STATIC
    Code:
      stack=2, locals=1, args_size=1
         0: getstatic     #17                 // Field scala/xml/Null$.MODULE$:Lscala/xml/Null$;
         3: aload_0
         4: invokevirtual #622                // Method scala/xml/Null$.reduce:(Lscala/Function2;)Ljava/lang/Object;
         7: areturn
      LocalVariableTable:
        Start  Length  Slot  Name   Signature
            0       8     0    op   Lscala/Function2;
    Signature: #620                         // <B:Ljava/lang/Object;>(Lscala/Function2<TB;TB;TB;>;)TB;
    MethodParameters:
      Name                           Flags
      op                             final

  public static <A1 extends java.lang.Object> A1 fold(A1, scala.Function2<A1, A1, A1>);
    descriptor: (Ljava/lang/Object;Lscala/Function2;)Ljava/lang/Object;
    flags: (0x0009) ACC_PUBLIC, ACC_STATIC
    Code:
      stack=3, locals=2, args_size=2
         0: getstatic     #17                 // Field scala/xml/Null$.MODULE$:Lscala/xml/Null$;
         3: aload_0
         4: aload_1
         5: invokevirtual #626                // Method scala/xml/Null$.fold:(Ljava/lang/Object;Lscala/Function2;)Ljava/lang/Object;
         8: areturn
      LocalVariableTable:
        Start  Length  Slot  Name   Signature
            0       9     0     z   Ljava/lang/Object;
            0       9     1    op   Lscala/Function2;
    Signature: #624                         // <A1:Ljava/lang/Object;>(TA1;Lscala/Function2<TA1;TA1;TA1;>;)TA1;
    MethodParameters:
      Name                           Flags
      z                              final
      op                             final

  public static <B extends java.lang.Object> B $colon$bslash(B, scala.Function2<scala.xml.MetaData, B, B>);
    descriptor: (Ljava/lang/Object;Lscala/Function2;)Ljava/lang/Object;
    flags: (0x0009) ACC_PUBLIC, ACC_STATIC
    Code:
      stack=3, locals=2, args_size=2
         0: getstatic     #17                 // Field scala/xml/Null$.MODULE$:Lscala/xml/Null$;
         3: aload_0
         4: aload_1
         5: invokevirtual #630                // Method scala/xml/Null$.$colon$bslash:(Ljava/lang/Object;Lscala/Function2;)Ljava/lang/Object;
         8: areturn
      LocalVariableTable:
        Start  Length  Slot  Name   Signature
            0       9     0     z   Ljava/lang/Object;
            0       9     1    op   Lscala/Function2;
    Signature: #628                         // <B:Ljava/lang/Object;>(TB;Lscala/Function2<Lscala/xml/MetaData;TB;TB;>;)TB;
    Deprecated: true
    MethodParameters:
      Name                           Flags
      z                              final
      op                             final

  public static <B extends java.lang.Object> B $div$colon(B, scala.Function2<B, scala.xml.MetaData, B>);
    descriptor: (Ljava/lang/Object;Lscala/Function2;)Ljava/lang/Object;
    flags: (0x0009) ACC_PUBLIC, ACC_STATIC
    Code:
      stack=3, locals=2, args_size=2
         0: getstatic     #17                 // Field scala/xml/Null$.MODULE$:Lscala/xml/Null$;
         3: aload_0
         4: aload_1
         5: invokevirtual #634                // Method scala/xml/Null$.$div$colon:(Ljava/lang/Object;Lscala/Function2;)Ljava/lang/Object;
         8: areturn
      LocalVariableTable:
        Start  Length  Slot  Name   Signature
            0       9     0     z   Ljava/lang/Object;
            0       9     1    op   Lscala/Function2;
    Signature: #632                         // <B:Ljava/lang/Object;>(TB;Lscala/Function2<TB;Lscala/xml/MetaData;TB;>;)TB;
    Deprecated: true
    MethodParameters:
      Name                           Flags
      z                              final
      op                             final

  public static <B extends java.lang.Object> B foldRight(B, scala.Function2<scala.xml.MetaData, B, B>);
    descriptor: (Ljava/lang/Object;Lscala/Function2;)Ljava/lang/Object;
    flags: (0x0009) ACC_PUBLIC, ACC_STATIC
    Code:
      stack=3, locals=2, args_size=2
         0: getstatic     #17                 // Field scala/xml/Null$.MODULE$:Lscala/xml/Null$;
         3: aload_0
         4: aload_1
         5: invokevirtual #637                // Method scala/xml/Null$.foldRight:(Ljava/lang/Object;Lscala/Function2;)Ljava/lang/Object;
         8: areturn
      LocalVariableTable:
        Start  Length  Slot  Name   Signature
            0       9     0     z   Ljava/lang/Object;
            0       9     1    op   Lscala/Function2;
    Signature: #628                         // <B:Ljava/lang/Object;>(TB;Lscala/Function2<Lscala/xml/MetaData;TB;TB;>;)TB;
    MethodParameters:
      Name                           Flags
      z                              final
      op                             final

  public static <B extends java.lang.Object> B foldLeft(B, scala.Function2<B, scala.xml.MetaData, B>);
    descriptor: (Ljava/lang/Object;Lscala/Function2;)Ljava/lang/Object;
    flags: (0x0009) ACC_PUBLIC, ACC_STATIC
    Code:
      stack=3, locals=2, args_size=2
         0: getstatic     #17                 // Field scala/xml/Null$.MODULE$:Lscala/xml/Null$;
         3: aload_0
         4: aload_1
         5: invokevirtual #640                // Method scala/xml/Null$.foldLeft:(Ljava/lang/Object;Lscala/Function2;)Ljava/lang/Object;
         8: areturn
      LocalVariableTable:
        Start  Length  Slot  Name   Signature
            0       9     0     z   Ljava/lang/Object;
            0       9     1    op   Lscala/Function2;
    Signature: #632                         // <B:Ljava/lang/Object;>(TB;Lscala/Function2<TB;Lscala/xml/MetaData;TB;>;)TB;
    MethodParameters:
      Name                           Flags
      z                              final
      op                             final

  public static scala.Option<scala.xml.MetaData> find(scala.Function1<scala.xml.MetaData, java.lang.Object>);
    descriptor: (Lscala/Function1;)Lscala/Option;
    flags: (0x0009) ACC_PUBLIC, ACC_STATIC
    Code:
      stack=2, locals=1, args_size=1
         0: getstatic     #17                 // Field scala/xml/Null$.MODULE$:Lscala/xml/Null$;
         3: aload_0
         4: invokevirtual #645                // Method scala/xml/Null$.find:(Lscala/Function1;)Lscala/Option;
         7: areturn
      LocalVariableTable:
        Start  Length  Slot  Name   Signature
            0       8     0     p   Lscala/Function1;
    Signature: #643                         // (Lscala/Function1<Lscala/xml/MetaData;Ljava/lang/Object;>;)Lscala/Option<Lscala/xml/MetaData;>;
    MethodParameters:
      Name                           Flags
      p                              final

  public static int count(scala.Function1<scala.xml.MetaData, java.lang.Object>);
    descriptor: (Lscala/Function1;)I
    flags: (0x0009) ACC_PUBLIC, ACC_STATIC
    Code:
      stack=2, locals=1, args_size=1
         0: getstatic     #17                 // Field scala/xml/Null$.MODULE$:Lscala/xml/Null$;
         3: aload_0
         4: invokevirtual #650                // Method scala/xml/Null$.count:(Lscala/Function1;)I
         7: ireturn
      LocalVariableTable:
        Start  Length  Slot  Name   Signature
            0       8     0     p   Lscala/Function1;
    Signature: #648                         // (Lscala/Function1<Lscala/xml/MetaData;Ljava/lang/Object;>;)I
    MethodParameters:
      Name                           Flags
      p                              final

  public static boolean exists(scala.Function1<scala.xml.MetaData, java.lang.Object>);
    descriptor: (Lscala/Function1;)Z
    flags: (0x0009) ACC_PUBLIC, ACC_STATIC
    Code:
      stack=2, locals=1, args_size=1
         0: getstatic     #17                 // Field scala/xml/Null$.MODULE$:Lscala/xml/Null$;
         3: aload_0
         4: invokevirtual #655                // Method scala/xml/Null$.exists:(Lscala/Function1;)Z
         7: ireturn
      LocalVariableTable:
        Start  Length  Slot  Name   Signature
            0       8     0     p   Lscala/Function1;
    Signature: #653                         // (Lscala/Function1<Lscala/xml/MetaData;Ljava/lang/Object;>;)Z
    MethodParameters:
      Name                           Flags
      p                              final

  public static boolean forall(scala.Function1<scala.xml.MetaData, java.lang.Object>);
    descriptor: (Lscala/Function1;)Z
    flags: (0x0009) ACC_PUBLIC, ACC_STATIC
    Code:
      stack=2, locals=1, args_size=1
         0: getstatic     #17                 // Field scala/xml/Null$.MODULE$:Lscala/xml/Null$;
         3: aload_0
         4: invokevirtual #658                // Method scala/xml/Null$.forall:(Lscala/Function1;)Z
         7: ireturn
      LocalVariableTable:
        Start  Length  Slot  Name   Signature
            0       8     0     p   Lscala/Function1;
    Signature: #653                         // (Lscala/Function1<Lscala/xml/MetaData;Ljava/lang/Object;>;)Z
    MethodParameters:
      Name                           Flags
      p                              final

  public static <U extends java.lang.Object> void foreach(scala.Function1<scala.xml.MetaData, U>);
    descriptor: (Lscala/Function1;)V
    flags: (0x0009) ACC_PUBLIC, ACC_STATIC
    Code:
      stack=2, locals=1, args_size=1
         0: getstatic     #17                 // Field scala/xml/Null$.MODULE$:Lscala/xml/Null$;
         3: aload_0
         4: invokevirtual #663                // Method scala/xml/Null$.foreach:(Lscala/Function1;)V
         7: return
      LocalVariableTable:
        Start  Length  Slot  Name   Signature
            0       8     0     f   Lscala/Function1;
    Signature: #661                         // <U:Ljava/lang/Object;>(Lscala/Function1<Lscala/xml/MetaData;TU;>;)V
    MethodParameters:
      Name                           Flags
      f                              final

  public static boolean hasDefiniteSize();
    descriptor: ()Z
    flags: (0x0009) ACC_PUBLIC, ACC_STATIC
    Code:
      stack=1, locals=0, args_size=0
         0: getstatic     #17                 // Field scala/xml/Null$.MODULE$:Lscala/xml/Null$;
         3: invokevirtual #666                // Method scala/xml/Null$.hasDefiniteSize:()Z
         6: ireturn
    Deprecated: true

  public static int knownSize();
    descriptor: ()I
    flags: (0x0009) ACC_PUBLIC, ACC_STATIC
    Code:
      stack=1, locals=0, args_size=0
         0: getstatic     #17                 // Field scala/xml/Null$.MODULE$:Lscala/xml/Null$;
         3: invokevirtual #669                // Method scala/xml/Null$.knownSize:()I
         6: ireturn

  public static <S extends scala.collection.Stepper<?>> S stepper(scala.collection.StepperShape<scala.xml.MetaData, S>);
    descriptor: (Lscala/collection/StepperShape;)Lscala/collection/Stepper;
    flags: (0x0009) ACC_PUBLIC, ACC_STATIC
    Code:
      stack=2, locals=1, args_size=1
         0: getstatic     #17                 // Field scala/xml/Null$.MODULE$:Lscala/xml/Null$;
         3: aload_0
         4: invokevirtual #675                // Method scala/xml/Null$.stepper:(Lscala/collection/StepperShape;)Lscala/collection/Stepper;
         7: areturn
      LocalVariableTable:
        Start  Length  Slot  Name   Signature
            0       8     0 shape   Lscala/collection/StepperShape;
    Signature: #672                         // <S::Lscala/collection/Stepper<*>;>(Lscala/collection/StepperShape<Lscala/xml/MetaData;TS;>;)TS;
    MethodParameters:
      Name                           Flags
      shape                          final
}
SourceFile: "Null.scala"
RuntimeVisibleAnnotations:
  0: #6(#7=s#8)
    scala.reflect.ScalaSignature(
      bytes="\u0006\u0005\u00055v!B\u0011#\u0011\u0003;c!B\u0015#\u0011\u0003S\u0003\"\u0002 \u0002\t\u0003y\u0004\"\u0002!\u0002\t\u0003\n\u0005\"B&\u0002\t\u0003b\u0005\"\u0002)\u0002\t\u0003\n\u0006bB-\u0002#\u0003%\tA\u0017\u0005\u0006K\u0006!\tE\u001a\u0005\u0006_\u0006!\t\u0001\u001d\u0005\u0006g\u0006!\t\u0001\u001e\u0005\u0006y\u0006!\t% \u0005\u0006e\u0006!\tA \u0005\u0006\u007f\u0006!\tA \u0005\u0007\u0003\u0003\tA\u0011\u0001@\t\r\u0005\r\u0011\u0001\"\u0001~\u0011\u0019\t)!\u0001C!\u0019\"9\u0011QA\u0001\u0005B\u0005\u001d\u0001bBA\u0007\u0003\u0011\u0005\u0013q\u0002\u0005\b\u00037\tA\u0011KA\u000f\u0011\u001d\tY#\u0001C\u0001\u0003[Aq!a\u000b\u0002\t\u0003\t9\u0005C\u0004\u0002N\u0005!\t\"a\u0014\t\u000f\u00055\u0013\u0001\"\u0015\u0002d!9\u0011QM\u0001\u0005B\u0005\r\u0004bBA4\u0003\u0011\u0005\u0013\u0011\u000e\u0005\b\u0003[\nA\u0011IA8\u0011\u001d\t\u0019(\u0001C\u0001\u0003kBq!a\u001d\u0002\t\u0003\tI\bC\u0005\u0002\u0002\u0006\t\t\u0011\"\u0011\u0002\u0004\"A\u00111S\u0001\u0002\u0002\u0013\u0005A\nC\u0005\u0002\u0016\u0006\t\t\u0011\"\u0001\u0002\u0018\"I\u0011QT\u0001\u0002\u0002\u0013\u0005\u0013q\u0014\u0005\n\u0003G\u000b\u0011\u0011!C\u0005\u0003K\u000bAAT;mY*\u00111\u0005J\u0001\u0004q6d\'\"A\u0013\u0002\u000bM\u001c\u0017\r\\1\u0004\u0001A\u0011\u0001&A\u0007\u0002E\t!a*\u001e7m\'\u0011\t1F\f\u001a\u0011\u0005!b\u0013BA\u0017#\u0005!iU\r^1ECR\f\u0007CA\u00181\u001b\u0005!\u0013BA\u0019%\u0005\u001d\u0001&o\u001c3vGR\u0004\"aM\u001e\u000f\u0005QJdBA\u001b9\u001b\u00051$BA\u001c\'\u0003\u0019a$o\\8u}%\tQ%\u0003\u0002;I\u00059\u0001/Y2lC\u001e,\u0017B\u0001\u001f>\u00051\u0019VM]5bY&T\u0018M\u00197f\u0015\tQD%\u0001\u0004=S:LGO\u0010\u000b\u0002O\u0005A\u0011\u000e^3sCR|\'/F\u0001C!\r\u0019e\tS\u0007\u0002\t*\u0011Q\tJ\u0001\u000bG>dG.Z2uS>t\u0017BA$E\u0005!IE/\u001a:bi>\u0014\bCA\u0018J\u0013\tQEEA\u0004O_RD\u0017N\\4\u0002\tML\'0Z\u000b\u0002\u001bB\u0011qFT\u0005\u0003\u001f\u0012\u00121!\u00138u\u0003\u0019\t\u0007\u000f]3oIR\u00191F\u0015+\t\u000bM+\u0001\u0019A\u0016\u0002\u00035Dq!V\u0003\u0011\u0002\u0003\u0007a+A\u0003tG>\u0004X\r\u0005\u0002)/&\u0011\u0001L\t\u0002\u0011\u001d\u0006lWm\u001d9bG\u0016\u0014\u0015N\u001c3j]\u001e\f\u0001#\u00199qK:$G\u0005Z3gCVdG\u000f\n\u001a\u0016\u0003mS#A\u0016/,\u0003u\u0003\"AX2\u000e\u0003}S!\u0001Y1\u0002\u0013Ut7\r[3dW\u0016$\'B\u00012%\u0003)\tgN\\8uCRLwN\\\u0005\u0003I~\u0013\u0011#\u001e8dQ\u0016\u001c7.\u001a3WCJL\u0017M\\2f\u0003\u00191\u0017\u000e\u001c;feR\u00111f\u001a\u0005\u0006Q\u001e\u0001\r![\u0001\u0002MB!qF[\u0016m\u0013\tYGEA\u0005Gk:\u001cG/[8ocA\u0011q&\\\u0005\u0003]\u0012\u0012qAQ8pY\u0016\fg.\u0001\u0003d_BLHCA\u0016r\u0011\u0015\u0011\b\u00021\u0001,\u0003\u0011qW\r\u001f;\u0002\u0019\u001d,GOT1nKN\u0004\u0018mY3\u0015\u0005U<\bCA\u0018w\u0013\tIC\u0005C\u0003y\u0013\u0001\u0007\u00110A\u0003po:,\'\u000f\u0005\u0002)u&\u00111P\t\u0002\u0005\u001d>$W-A\u0004iCNtU\r\u001f;\u0016\u00031,\u0012!^\u0001\u0004W\u0016L\u0018!\u0002<bYV,\u0017AC5t!J,g-\u001b=fI\u00061A.\u001a8hi\"$2!TA\u0005\u0011\u0019\tY\u0001\u0005a\u0001\u001b\u0006\t\u0011.A\u0007tiJL7\r^0%KF$S-\u001d\u000b\u0004Y\u0006E\u0001bBA\n#\u0001\u0007\u0011QC\u0001\u0006_RDWM\u001d\t\u0004Q\u0005]\u0011bAA\rE\tAQ)];bY&$\u00180\u0001\tcCNL7OR8s\u0011\u0006\u001c\bnQ8eKV\u0011\u0011q\u0004\t\u0006\u0007\u0006\u0005\u0012QE\u0005\u0004\u0003G!%aA*fcB\u0019q&a\n\n\u0007\u0005%BEA\u0002B]f\fQ!\u00199qYf$r!^A\u0018\u0003\u0007\n)\u0005C\u0004\u00022M\u0001\r!a\r\u0002\u00139\fW.Z:qC\u000e,\u0007\u0003BA\u001b\u0003{qA!a\u000e\u0002:A\u0011Q\u0007J\u0005\u0004\u0003w!\u0013A\u0002)sK\u0012,g-\u0003\u0003\u0002@\u0005\u0005#AB*ue&twMC\u0002\u0002<\u0011BQ!V\nA\u0002YCaa`\nA\u0002\u0005MB\u0003BA%\u0003\u0017\u0002BaQA\u0011s\"1q\u0010\u0006a\u0001\u0003g\t\u0011\u0002^8TiJLgnZ\u0019\u0015\t\u0005E\u0013q\u000b\t\u0004_\u0005M\u0013bAA+I\t!QK\\5u\u0011\u001d\tI&\u0006a\u0001\u00037\n!a\u001d2\u0011\t\u0005u\u0013q\f\b\u0003_eJ1!!\u0019>\u00055\u0019FO]5oO\n+\u0018\u000e\u001c3feR\u0011\u00111G\u0001\ti>\u001cFO]5oO\u0006Y!-^5mIN#(/\u001b8h)\u0011\tY&a\u001b\t\u000f\u0005e\u0003\u00041\u0001\u0002\\\u0005Qq/\u001a7mM>\u0014X.\u001a3\u0015\u00071\f\t\bC\u0003V3\u0001\u0007a+\u0001\u0004sK6|g/\u001a\u000b\u0004O\u0005]\u0004BB@\u001b\u0001\u0004\t\u0019\u0004F\u0004(\u0003w\ni(a \t\u000f\u0005E2\u00041\u0001\u00024!)Qk\u0007a\u0001-\"1qp\u0007a\u0001\u0003g\tQ\u0002\u001d:pIV\u001cG\u000f\u0015:fM&DXCAAC!\u0011\t9)!%\u000e\u0005\u0005%%\u0002BAF\u0003\u001b\u000bA\u0001\\1oO*\u0011\u0011qR\u0001\u0005U\u00064\u0018-\u0003\u0003\u0002@\u0005%\u0015\u0001\u00049s_\u0012,8\r^!sSRL\u0018A\u00049s_\u0012,8\r^#mK6,g\u000e\u001e\u000b\u0005\u0003K\tI\n\u0003\u0005\u0002\u001cz\t\t\u00111\u0001N\u0003\rAH%M\u0001\u0010aJ|G-^2u\u0013R,\'/\u0019;peV\u0011\u0011\u0011\u0015\t\u0005\u0007\u001a\u000b)#\u0001\u0007xe&$XMU3qY\u0006\u001cW\r\u0006\u0002\u0002(B!\u0011qQAU\u0013\u0011\tY+!#\u0003\r=\u0013\'.Z2u\u0001"
    )
  ScalaSig: length = 0x3 (unknown attribute)
   05 02 00
