Classfile /Users/mw/Projects/slang-braindump/.jar/jar8/assemble/slang-braindump/assemble/content/scala/xml/Source$.class
  Last modified May 29, 2022; size 1833 bytes
  SHA-256 checksum e0de567a3d1cbf14e177fca33e322255128008ecb170fe14c14f0fc4c547781c
  Compiled from "XML.scala"
public final class scala.xml.Source$
  minor version: 0
  major version: 52
  flags: (0x0031) ACC_PUBLIC, ACC_FINAL, ACC_SUPER
  this_class: #2                          // scala/xml/Source$
  super_class: #4                         // java/lang/Object
  interfaces: 0, fields: 1, methods: 9, attributes: 3
Constant pool:
   #1 = Utf8               scala/xml/Source$
   #2 = Class              #1             // scala/xml/Source$
   #3 = Utf8               java/lang/Object
   #4 = Class              #3             // java/lang/Object
   #5 = Utf8               XML.scala
   #6 = Utf8               MODULE$
   #7 = Utf8               Lscala/xml/Source$;
   #8 = Utf8               <clinit>
   #9 = Utf8               ()V
  #10 = Utf8               <init>
  #11 = NameAndType        #10:#9         // "<init>":()V
  #12 = Methodref          #2.#11         // scala/xml/Source$."<init>":()V
  #13 = NameAndType        #6:#7          // MODULE$:Lscala/xml/Source$;
  #14 = Fieldref           #2.#13         // scala/xml/Source$.MODULE$:Lscala/xml/Source$;
  #15 = Utf8               fromFile
  #16 = Utf8               (Ljava/io/File;)Lorg/xml/sax/InputSource;
  #17 = Utf8               file
  #18 = Utf8               org/xml/sax/InputSource
  #19 = Class              #18            // org/xml/sax/InputSource
  #20 = Utf8               java/io/FileInputStream
  #21 = Class              #20            // java/io/FileInputStream
  #22 = Utf8               (Ljava/io/File;)V
  #23 = NameAndType        #10:#22        // "<init>":(Ljava/io/File;)V
  #24 = Methodref          #21.#23        // java/io/FileInputStream."<init>":(Ljava/io/File;)V
  #25 = Utf8               (Ljava/io/InputStream;)V
  #26 = NameAndType        #10:#25        // "<init>":(Ljava/io/InputStream;)V
  #27 = Methodref          #19.#26        // org/xml/sax/InputSource."<init>":(Ljava/io/InputStream;)V
  #28 = Utf8               this
  #29 = Utf8               Ljava/io/File;
  #30 = Utf8               (Ljava/io/FileDescriptor;)Lorg/xml/sax/InputSource;
  #31 = Utf8               fd
  #32 = Utf8               (Ljava/io/FileDescriptor;)V
  #33 = NameAndType        #10:#32        // "<init>":(Ljava/io/FileDescriptor;)V
  #34 = Methodref          #21.#33        // java/io/FileInputStream."<init>":(Ljava/io/FileDescriptor;)V
  #35 = Utf8               Ljava/io/FileDescriptor;
  #36 = Utf8               (Ljava/lang/String;)Lorg/xml/sax/InputSource;
  #37 = Utf8               name
  #38 = Utf8               (Ljava/lang/String;)V
  #39 = NameAndType        #10:#38        // "<init>":(Ljava/lang/String;)V
  #40 = Methodref          #21.#39        // java/io/FileInputStream."<init>":(Ljava/lang/String;)V
  #41 = Utf8               Ljava/lang/String;
  #42 = Utf8               fromInputStream
  #43 = Utf8               (Ljava/io/InputStream;)Lorg/xml/sax/InputSource;
  #44 = Utf8               is
  #45 = Utf8               Ljava/io/InputStream;
  #46 = Utf8               fromReader
  #47 = Utf8               (Ljava/io/Reader;)Lorg/xml/sax/InputSource;
  #48 = Utf8               reader
  #49 = Utf8               (Ljava/io/Reader;)V
  #50 = NameAndType        #10:#49        // "<init>":(Ljava/io/Reader;)V
  #51 = Methodref          #19.#50        // org/xml/sax/InputSource."<init>":(Ljava/io/Reader;)V
  #52 = Utf8               Ljava/io/Reader;
  #53 = Utf8               fromSysId
  #54 = Utf8               sysID
  #55 = Methodref          #19.#39        // org/xml/sax/InputSource."<init>":(Ljava/lang/String;)V
  #56 = Utf8               fromString
  #57 = Utf8               string
  #58 = Utf8               java/io/StringReader
  #59 = Class              #58            // java/io/StringReader
  #60 = Methodref          #59.#39        // java/io/StringReader."<init>":(Ljava/lang/String;)V
  #61 = NameAndType        #46:#47        // fromReader:(Ljava/io/Reader;)Lorg/xml/sax/InputSource;
  #62 = Methodref          #2.#61         // scala/xml/Source$.fromReader:(Ljava/io/Reader;)Lorg/xml/sax/InputSource;
  #63 = Methodref          #4.#11         // java/lang/Object."<init>":()V
  #64 = Utf8               Code
  #65 = Utf8               LineNumberTable
  #66 = Utf8               LocalVariableTable
  #67 = Utf8               MethodParameters
  #68 = Utf8               SourceFile
  #69 = Utf8               ScalaInlineInfo
  #70 = Utf8               Scala
{
  public static final scala.xml.Source$ MODULE$;
    descriptor: Lscala/xml/Source$;
    flags: (0x0019) ACC_PUBLIC, ACC_STATIC, ACC_FINAL

  public static {};
    descriptor: ()V
    flags: (0x0009) ACC_PUBLIC, ACC_STATIC
    Code:
      stack=2, locals=0, args_size=0
         0: new           #2                  // class scala/xml/Source$
         3: dup
         4: invokespecial #12                 // Method "<init>":()V
         7: putstatic     #14                 // Field MODULE$:Lscala/xml/Source$;
        10: return
      LineNumberTable:
        line 22: 0

  public org.xml.sax.InputSource fromFile(java.io.File);
    descriptor: (Ljava/io/File;)Lorg/xml/sax/InputSource;
    flags: (0x0001) ACC_PUBLIC
    Code:
      stack=5, locals=2, args_size=2
         0: new           #19                 // class org/xml/sax/InputSource
         3: dup
         4: new           #21                 // class java/io/FileInputStream
         7: dup
         8: aload_1
         9: invokespecial #24                 // Method java/io/FileInputStream."<init>":(Ljava/io/File;)V
        12: invokespecial #27                 // Method org/xml/sax/InputSource."<init>":(Ljava/io/InputStream;)V
        15: areturn
      LineNumberTable:
        line 23: 0
      LocalVariableTable:
        Start  Length  Slot  Name   Signature
            0      16     0  this   Lscala/xml/Source$;
            0      16     1  file   Ljava/io/File;
    MethodParameters:
      Name                           Flags
      file                           final

  public org.xml.sax.InputSource fromFile(java.io.FileDescriptor);
    descriptor: (Ljava/io/FileDescriptor;)Lorg/xml/sax/InputSource;
    flags: (0x0001) ACC_PUBLIC
    Code:
      stack=5, locals=2, args_size=2
         0: new           #19                 // class org/xml/sax/InputSource
         3: dup
         4: new           #21                 // class java/io/FileInputStream
         7: dup
         8: aload_1
         9: invokespecial #34                 // Method java/io/FileInputStream."<init>":(Ljava/io/FileDescriptor;)V
        12: invokespecial #27                 // Method org/xml/sax/InputSource."<init>":(Ljava/io/InputStream;)V
        15: areturn
      LineNumberTable:
        line 24: 0
      LocalVariableTable:
        Start  Length  Slot  Name   Signature
            0      16     0  this   Lscala/xml/Source$;
            0      16     1    fd   Ljava/io/FileDescriptor;
    MethodParameters:
      Name                           Flags
      fd                             final

  public org.xml.sax.InputSource fromFile(java.lang.String);
    descriptor: (Ljava/lang/String;)Lorg/xml/sax/InputSource;
    flags: (0x0001) ACC_PUBLIC
    Code:
      stack=5, locals=2, args_size=2
         0: new           #19                 // class org/xml/sax/InputSource
         3: dup
         4: new           #21                 // class java/io/FileInputStream
         7: dup
         8: aload_1
         9: invokespecial #40                 // Method java/io/FileInputStream."<init>":(Ljava/lang/String;)V
        12: invokespecial #27                 // Method org/xml/sax/InputSource."<init>":(Ljava/io/InputStream;)V
        15: areturn
      LineNumberTable:
        line 25: 0
      LocalVariableTable:
        Start  Length  Slot  Name   Signature
            0      16     0  this   Lscala/xml/Source$;
            0      16     1  name   Ljava/lang/String;
    MethodParameters:
      Name                           Flags
      name                           final

  public org.xml.sax.InputSource fromInputStream(java.io.InputStream);
    descriptor: (Ljava/io/InputStream;)Lorg/xml/sax/InputSource;
    flags: (0x0001) ACC_PUBLIC
    Code:
      stack=3, locals=2, args_size=2
         0: new           #19                 // class org/xml/sax/InputSource
         3: dup
         4: aload_1
         5: invokespecial #27                 // Method org/xml/sax/InputSource."<init>":(Ljava/io/InputStream;)V
         8: areturn
      LineNumberTable:
        line 27: 0
      LocalVariableTable:
        Start  Length  Slot  Name   Signature
            0       9     0  this   Lscala/xml/Source$;
            0       9     1    is   Ljava/io/InputStream;
    MethodParameters:
      Name                           Flags
      is                             final

  public org.xml.sax.InputSource fromReader(java.io.Reader);
    descriptor: (Ljava/io/Reader;)Lorg/xml/sax/InputSource;
    flags: (0x0001) ACC_PUBLIC
    Code:
      stack=3, locals=2, args_size=2
         0: new           #19                 // class org/xml/sax/InputSource
         3: dup
         4: aload_1
         5: invokespecial #51                 // Method org/xml/sax/InputSource."<init>":(Ljava/io/Reader;)V
         8: areturn
      LineNumberTable:
        line 28: 0
      LocalVariableTable:
        Start  Length  Slot  Name   Signature
            0       9     0  this   Lscala/xml/Source$;
            0       9     1 reader   Ljava/io/Reader;
    MethodParameters:
      Name                           Flags
      reader                         final

  public org.xml.sax.InputSource fromSysId(java.lang.String);
    descriptor: (Ljava/lang/String;)Lorg/xml/sax/InputSource;
    flags: (0x0001) ACC_PUBLIC
    Code:
      stack=3, locals=2, args_size=2
         0: new           #19                 // class org/xml/sax/InputSource
         3: dup
         4: aload_1
         5: invokespecial #55                 // Method org/xml/sax/InputSource."<init>":(Ljava/lang/String;)V
         8: areturn
      LineNumberTable:
        line 29: 0
      LocalVariableTable:
        Start  Length  Slot  Name   Signature
            0       9     0  this   Lscala/xml/Source$;
            0       9     1 sysID   Ljava/lang/String;
    MethodParameters:
      Name                           Flags
      sysID                          final

  public org.xml.sax.InputSource fromString(java.lang.String);
    descriptor: (Ljava/lang/String;)Lorg/xml/sax/InputSource;
    flags: (0x0001) ACC_PUBLIC
    Code:
      stack=4, locals=2, args_size=2
         0: aload_0
         1: new           #59                 // class java/io/StringReader
         4: dup
         5: aload_1
         6: invokespecial #60                 // Method java/io/StringReader."<init>":(Ljava/lang/String;)V
         9: invokevirtual #62                 // Method fromReader:(Ljava/io/Reader;)Lorg/xml/sax/InputSource;
        12: areturn
      LineNumberTable:
        line 30: 0
      LocalVariableTable:
        Start  Length  Slot  Name   Signature
            0      13     0  this   Lscala/xml/Source$;
            0      13     1 string   Ljava/lang/String;
    MethodParameters:
      Name                           Flags
      string                         final

  private scala.xml.Source$();
    descriptor: ()V
    flags: (0x0002) ACC_PRIVATE
    Code:
      stack=1, locals=1, args_size=1
         0: aload_0
         1: invokespecial #63                 // Method java/lang/Object."<init>":()V
         4: return
      LineNumberTable:
        line 36: 0
        line 22: 4
      LocalVariableTable:
        Start  Length  Slot  Name   Signature
            0       5     0  this   Lscala/xml/Source$;
}
SourceFile: "XML.scala"
  ScalaInlineInfo: length = 0x2C (unknown attribute)
   01 01 00 08 00 0A 00 09 01 00 0F 00 10 01 00 0F
   00 1E 01 00 0F 00 24 01 00 2A 00 2B 01 00 2E 00
   2F 01 00 38 00 24 01 00 35 00 24 01
  Scala: length = 0x0 (unknown attribute)

