Classfile /Users/mw/Projects/slang-braindump/.jar/jar8/assemble/slang-braindump/assemble/content/scala/xml/Unparsed$.class
  Last modified May 29, 2022; size 1182 bytes
  SHA-256 checksum 5abfab74098985f265edf75751f4266edeeb8a7b9bc0d871d6f80174d906c50d
  Compiled from "Unparsed.scala"
public final class scala.xml.Unparsed$ implements java.io.Serializable
  minor version: 0
  major version: 52
  flags: (0x0031) ACC_PUBLIC, ACC_FINAL, ACC_SUPER
  this_class: #2                          // scala/xml/Unparsed$
  super_class: #4                         // java/lang/Object
  interfaces: 1, fields: 1, methods: 5, attributes: 3
Constant pool:
   #1 = Utf8               scala/xml/Unparsed$
   #2 = Class              #1             // scala/xml/Unparsed$
   #3 = Utf8               java/lang/Object
   #4 = Class              #3             // java/lang/Object
   #5 = Utf8               java/io/Serializable
   #6 = Class              #5             // java/io/Serializable
   #7 = Utf8               Unparsed.scala
   #8 = Utf8               MODULE$
   #9 = Utf8               Lscala/xml/Unparsed$;
  #10 = Utf8               <clinit>
  #11 = Utf8               ()V
  #12 = Utf8               <init>
  #13 = NameAndType        #12:#11        // "<init>":()V
  #14 = Methodref          #2.#13         // scala/xml/Unparsed$."<init>":()V
  #15 = NameAndType        #8:#9          // MODULE$:Lscala/xml/Unparsed$;
  #16 = Fieldref           #2.#15         // scala/xml/Unparsed$.MODULE$:Lscala/xml/Unparsed$;
  #17 = Utf8               apply
  #18 = Utf8               (Ljava/lang/String;)Lscala/xml/Unparsed;
  #19 = Utf8               data
  #20 = Utf8               scala/xml/Unparsed
  #21 = Class              #20            // scala/xml/Unparsed
  #22 = Utf8               (Ljava/lang/String;)V
  #23 = NameAndType        #12:#22        // "<init>":(Ljava/lang/String;)V
  #24 = Methodref          #21.#23        // scala/xml/Unparsed."<init>":(Ljava/lang/String;)V
  #25 = Utf8               this
  #26 = Utf8               Ljava/lang/String;
  #27 = Utf8               unapply
  #28 = Utf8               (Lscala/xml/Unparsed;)Lscala/Some;
  #29 = Utf8               (Lscala/xml/Unparsed;)Lscala/Some<Ljava/lang/String;>;
  #30 = Utf8               x
  #31 = Utf8               scala/Some
  #32 = Class              #31            // scala/Some
  #33 = Utf8               ()Ljava/lang/Object;
  #34 = NameAndType        #19:#33        // data:()Ljava/lang/Object;
  #35 = Methodref          #21.#34        // scala/xml/Unparsed.data:()Ljava/lang/Object;
  #36 = Utf8               (Ljava/lang/Object;)V
  #37 = NameAndType        #12:#36        // "<init>":(Ljava/lang/Object;)V
  #38 = Methodref          #32.#37        // scala/Some."<init>":(Ljava/lang/Object;)V
  #39 = Utf8               Lscala/xml/Unparsed;
  #40 = Utf8               writeReplace
  #41 = Utf8               scala/runtime/ModuleSerializationProxy
  #42 = Class              #41            // scala/runtime/ModuleSerializationProxy
  #43 = Utf8               (Ljava/lang/Class;)V
  #44 = NameAndType        #12:#43        // "<init>":(Ljava/lang/Class;)V
  #45 = Methodref          #42.#44        // scala/runtime/ModuleSerializationProxy."<init>":(Ljava/lang/Class;)V
  #46 = Methodref          #4.#13         // java/lang/Object."<init>":()V
  #47 = Utf8               Code
  #48 = Utf8               LineNumberTable
  #49 = Utf8               LocalVariableTable
  #50 = Utf8               MethodParameters
  #51 = Utf8               Signature
  #52 = Utf8               SourceFile
  #53 = Utf8               ScalaInlineInfo
  #54 = Utf8               Scala
{
  public static final scala.xml.Unparsed$ MODULE$;
    descriptor: Lscala/xml/Unparsed$;
    flags: (0x0019) ACC_PUBLIC, ACC_STATIC, ACC_FINAL

  public static {};
    descriptor: ()V
    flags: (0x0009) ACC_PUBLIC, ACC_STATIC
    Code:
      stack=2, locals=0, args_size=0
         0: new           #2                  // class scala/xml/Unparsed$
         3: dup
         4: invokespecial #14                 // Method "<init>":()V
         7: putstatic     #16                 // Field MODULE$:Lscala/xml/Unparsed$;
        10: return
      LineNumberTable:
        line 39: 0

  public scala.xml.Unparsed apply(java.lang.String);
    descriptor: (Ljava/lang/String;)Lscala/xml/Unparsed;
    flags: (0x0001) ACC_PUBLIC
    Code:
      stack=3, locals=2, args_size=2
         0: new           #21                 // class scala/xml/Unparsed
         3: dup
         4: aload_1
         5: invokespecial #24                 // Method scala/xml/Unparsed."<init>":(Ljava/lang/String;)V
         8: areturn
      LineNumberTable:
        line 40: 0
      LocalVariableTable:
        Start  Length  Slot  Name   Signature
            0       9     0  this   Lscala/xml/Unparsed$;
            0       9     1  data   Ljava/lang/String;
    MethodParameters:
      Name                           Flags
      data                           final

  public scala.Some<java.lang.String> unapply(scala.xml.Unparsed);
    descriptor: (Lscala/xml/Unparsed;)Lscala/Some;
    flags: (0x0001) ACC_PUBLIC
    Code:
      stack=3, locals=2, args_size=2
         0: new           #32                 // class scala/Some
         3: dup
         4: aload_1
         5: invokevirtual #35                 // Method scala/xml/Unparsed.data:()Ljava/lang/Object;
         8: invokespecial #38                 // Method scala/Some."<init>":(Ljava/lang/Object;)V
        11: areturn
      LineNumberTable:
        line 41: 0
      LocalVariableTable:
        Start  Length  Slot  Name   Signature
            0      12     0  this   Lscala/xml/Unparsed$;
            0      12     1     x   Lscala/xml/Unparsed;
    Signature: #29                          // (Lscala/xml/Unparsed;)Lscala/Some<Ljava/lang/String;>;
    MethodParameters:
      Name                           Flags
      x                              final

  private java.lang.Object writeReplace();
    descriptor: ()Ljava/lang/Object;
    flags: (0x0002) ACC_PRIVATE
    Code:
      stack=3, locals=1, args_size=1
         0: new           #42                 // class scala/runtime/ModuleSerializationProxy
         3: dup
         4: ldc           #2                  // class scala/xml/Unparsed$
         6: invokespecial #45                 // Method scala/runtime/ModuleSerializationProxy."<init>":(Ljava/lang/Class;)V
         9: areturn
      LineNumberTable:
        line 39: 0
      LocalVariableTable:
        Start  Length  Slot  Name   Signature
            0      10     0  this   Lscala/xml/Unparsed$;

  private scala.xml.Unparsed$();
    descriptor: ()V
    flags: (0x0002) ACC_PRIVATE
    Code:
      stack=1, locals=1, args_size=1
         0: aload_0
         1: invokespecial #46                 // Method java/lang/Object."<init>":()V
         4: return
      LineNumberTable:
        line 42: 0
        line 39: 4
      LocalVariableTable:
        Start  Length  Slot  Name   Signature
            0       5     0  this   Lscala/xml/Unparsed$;
}
SourceFile: "Unparsed.scala"
  ScalaInlineInfo: length = 0x18 (unknown attribute)
   01 01 00 04 00 0C 00 0B 01 00 11 00 12 01 00 1B
   00 1C 01 00 28 00 21 01
  Scala: length = 0x0 (unknown attribute)

