Classfile /Users/mw/Projects/slang-braindump/.jar/jar8/assemble/slang-braindump/assemble/content/scala/xml/XML$$anon$1.class
  Last modified May 29, 2022; size 4108 bytes
  SHA-256 checksum 46d1f678c7df41858a7119613570cbd6d5088b4ae81b70704f3ead630242d41e
  Compiled from "XML.scala"
public final class scala.xml.XML$$anon$1 extends java.lang.Object implements scala.xml.factory.XMLLoader<scala.xml.Elem>
  minor version: 0
  major version: 52
  flags: (0x0031) ACC_PUBLIC, ACC_FINAL, ACC_SUPER
  this_class: #2                          // scala/xml/XML$$anon$1
  super_class: #5                         // java/lang/Object
  interfaces: 1, fields: 3, methods: 15, attributes: 6
Constant pool:
    #1 = Utf8               scala/xml/XML$$anon$1
    #2 = Class              #1            // scala/xml/XML$$anon$1
    #3 = Utf8               Ljava/lang/Object;Lscala/xml/factory/XMLLoader<Lscala/xml/Elem;>;
    #4 = Utf8               java/lang/Object
    #5 = Class              #4            // java/lang/Object
    #6 = Utf8               scala/xml/factory/XMLLoader
    #7 = Class              #6            // scala/xml/factory/XMLLoader
    #8 = Utf8               XML.scala
    #9 = Utf8               scala/xml/XML$
   #10 = Class              #9            // scala/xml/XML$
   #11 = Utf8               withSAXParser
   #12 = Utf8               (Ljavax/xml/parsers/SAXParser;)Lscala/xml/factory/XMLLoader;
   #13 = NameAndType        #11:#12       // withSAXParser:(Ljavax/xml/parsers/SAXParser;)Lscala/xml/factory/XMLLoader;
   #14 = Utf8               parser
   #15 = Utf8               Ljavax/xml/parsers/SAXParser;
   #16 = Utf8               scala$xml$factory$XMLLoader$$parserInstance
   #17 = Utf8               Ljava/lang/ThreadLocal;
   #18 = Utf8               Ljava/lang/ThreadLocal<Ljavax/xml/parsers/SAXParser;>;
   #19 = Utf8               bitmap$0
   #20 = Utf8               Z
   #21 = Utf8               adapter
   #22 = Utf8               ()Lscala/xml/parsing/FactoryAdapter;
   #23 = Utf8               adapter$
   #24 = Utf8               (Lscala/xml/factory/XMLLoader;)Lscala/xml/parsing/FactoryAdapter;
   #25 = NameAndType        #23:#24       // adapter$:(Lscala/xml/factory/XMLLoader;)Lscala/xml/parsing/FactoryAdapter;
   #26 = InterfaceMethodref #7.#25        // scala/xml/factory/XMLLoader.adapter$:(Lscala/xml/factory/XMLLoader;)Lscala/xml/parsing/FactoryAdapter;
   #27 = Utf8               this
   #28 = Utf8               Lscala/xml/XML$$anon$1;
   #29 = Utf8               loadXML
   #30 = Utf8               (Lorg/xml/sax/InputSource;Ljavax/xml/parsers/SAXParser;)Lscala/xml/Node;
   #31 = Utf8               source
   #32 = Utf8               loadXML$
   #33 = Utf8               (Lscala/xml/factory/XMLLoader;Lorg/xml/sax/InputSource;Ljavax/xml/parsers/SAXParser;)Lscala/xml/Node;
   #34 = NameAndType        #32:#33       // loadXML$:(Lscala/xml/factory/XMLLoader;Lorg/xml/sax/InputSource;Ljavax/xml/parsers/SAXParser;)Lscala/xml/Node;
   #35 = InterfaceMethodref #7.#34        // scala/xml/factory/XMLLoader.loadXML$:(Lscala/xml/factory/XMLLoader;Lorg/xml/sax/InputSource;Ljavax/xml/parsers/SAXParser;)Lscala/xml/Node;
   #36 = Utf8               Lorg/xml/sax/InputSource;
   #37 = Utf8               loadFile
   #38 = Utf8               (Ljava/io/File;)Lscala/xml/Node;
   #39 = Utf8               file
   #40 = Utf8               loadFile$
   #41 = Utf8               (Lscala/xml/factory/XMLLoader;Ljava/io/File;)Lscala/xml/Node;
   #42 = NameAndType        #40:#41       // loadFile$:(Lscala/xml/factory/XMLLoader;Ljava/io/File;)Lscala/xml/Node;
   #43 = InterfaceMethodref #7.#42        // scala/xml/factory/XMLLoader.loadFile$:(Lscala/xml/factory/XMLLoader;Ljava/io/File;)Lscala/xml/Node;
   #44 = Utf8               Ljava/io/File;
   #45 = Utf8               (Ljava/io/FileDescriptor;)Lscala/xml/Node;
   #46 = Utf8               fd
   #47 = Utf8               (Lscala/xml/factory/XMLLoader;Ljava/io/FileDescriptor;)Lscala/xml/Node;
   #48 = NameAndType        #40:#47       // loadFile$:(Lscala/xml/factory/XMLLoader;Ljava/io/FileDescriptor;)Lscala/xml/Node;
   #49 = InterfaceMethodref #7.#48        // scala/xml/factory/XMLLoader.loadFile$:(Lscala/xml/factory/XMLLoader;Ljava/io/FileDescriptor;)Lscala/xml/Node;
   #50 = Utf8               Ljava/io/FileDescriptor;
   #51 = Utf8               (Ljava/lang/String;)Lscala/xml/Node;
   #52 = Utf8               name
   #53 = Utf8               (Lscala/xml/factory/XMLLoader;Ljava/lang/String;)Lscala/xml/Node;
   #54 = NameAndType        #40:#53       // loadFile$:(Lscala/xml/factory/XMLLoader;Ljava/lang/String;)Lscala/xml/Node;
   #55 = InterfaceMethodref #7.#54        // scala/xml/factory/XMLLoader.loadFile$:(Lscala/xml/factory/XMLLoader;Ljava/lang/String;)Lscala/xml/Node;
   #56 = Utf8               Ljava/lang/String;
   #57 = Utf8               load
   #58 = Utf8               (Ljava/io/InputStream;)Lscala/xml/Node;
   #59 = Utf8               is
   #60 = Utf8               load$
   #61 = Utf8               (Lscala/xml/factory/XMLLoader;Ljava/io/InputStream;)Lscala/xml/Node;
   #62 = NameAndType        #60:#61       // load$:(Lscala/xml/factory/XMLLoader;Ljava/io/InputStream;)Lscala/xml/Node;
   #63 = InterfaceMethodref #7.#62        // scala/xml/factory/XMLLoader.load$:(Lscala/xml/factory/XMLLoader;Ljava/io/InputStream;)Lscala/xml/Node;
   #64 = Utf8               Ljava/io/InputStream;
   #65 = Utf8               (Ljava/io/Reader;)Lscala/xml/Node;
   #66 = Utf8               reader
   #67 = Utf8               (Lscala/xml/factory/XMLLoader;Ljava/io/Reader;)Lscala/xml/Node;
   #68 = NameAndType        #60:#67       // load$:(Lscala/xml/factory/XMLLoader;Ljava/io/Reader;)Lscala/xml/Node;
   #69 = InterfaceMethodref #7.#68        // scala/xml/factory/XMLLoader.load$:(Lscala/xml/factory/XMLLoader;Ljava/io/Reader;)Lscala/xml/Node;
   #70 = Utf8               Ljava/io/Reader;
   #71 = Utf8               sysID
   #72 = NameAndType        #60:#53       // load$:(Lscala/xml/factory/XMLLoader;Ljava/lang/String;)Lscala/xml/Node;
   #73 = InterfaceMethodref #7.#72        // scala/xml/factory/XMLLoader.load$:(Lscala/xml/factory/XMLLoader;Ljava/lang/String;)Lscala/xml/Node;
   #74 = Utf8               (Lorg/xml/sax/InputSource;)Lscala/xml/Node;
   #75 = Utf8               (Lscala/xml/factory/XMLLoader;Lorg/xml/sax/InputSource;)Lscala/xml/Node;
   #76 = NameAndType        #60:#75       // load$:(Lscala/xml/factory/XMLLoader;Lorg/xml/sax/InputSource;)Lscala/xml/Node;
   #77 = InterfaceMethodref #7.#76        // scala/xml/factory/XMLLoader.load$:(Lscala/xml/factory/XMLLoader;Lorg/xml/sax/InputSource;)Lscala/xml/Node;
   #78 = Utf8               (Ljava/net/URL;)Lscala/xml/Node;
   #79 = Utf8               url
   #80 = Utf8               (Lscala/xml/factory/XMLLoader;Ljava/net/URL;)Lscala/xml/Node;
   #81 = NameAndType        #60:#80       // load$:(Lscala/xml/factory/XMLLoader;Ljava/net/URL;)Lscala/xml/Node;
   #82 = InterfaceMethodref #7.#81        // scala/xml/factory/XMLLoader.load$:(Lscala/xml/factory/XMLLoader;Ljava/net/URL;)Lscala/xml/Node;
   #83 = Utf8               Ljava/net/URL;
   #84 = Utf8               loadString
   #85 = Utf8               string
   #86 = Utf8               loadString$
   #87 = NameAndType        #86:#53       // loadString$:(Lscala/xml/factory/XMLLoader;Ljava/lang/String;)Lscala/xml/Node;
   #88 = InterfaceMethodref #7.#87        // scala/xml/factory/XMLLoader.loadString$:(Lscala/xml/factory/XMLLoader;Ljava/lang/String;)Lscala/xml/Node;
   #89 = Utf8               scala$xml$factory$XMLLoader$$parserInstance$lzycompute
   #90 = Utf8               ()Ljava/lang/ThreadLocal;
   #91 = Utf8               ()Ljava/lang/ThreadLocal<Ljavax/xml/parsers/SAXParser;>;
   #92 = NameAndType        #19:#20       // bitmap$0:Z
   #93 = Fieldref           #2.#92        // scala/xml/XML$$anon$1.bitmap$0:Z
   #94 = Utf8               scala$xml$factory$XMLLoader$$parserInstance$
   #95 = Utf8               (Lscala/xml/factory/XMLLoader;)Ljava/lang/ThreadLocal;
   #96 = NameAndType        #94:#95       // scala$xml$factory$XMLLoader$$parserInstance$:(Lscala/xml/factory/XMLLoader;)Ljava/lang/ThreadLocal;
   #97 = InterfaceMethodref #7.#96        // scala/xml/factory/XMLLoader.scala$xml$factory$XMLLoader$$parserInstance$:(Lscala/xml/factory/XMLLoader;)Ljava/lang/ThreadLocal;
   #98 = NameAndType        #16:#17       // scala$xml$factory$XMLLoader$$parserInstance:Ljava/lang/ThreadLocal;
   #99 = Fieldref           #2.#98        // scala/xml/XML$$anon$1.scala$xml$factory$XMLLoader$$parserInstance:Ljava/lang/ThreadLocal;
  #100 = Utf8               java/lang/Throwable
  #101 = Class              #100          // java/lang/Throwable
  #102 = NameAndType        #89:#90       // scala$xml$factory$XMLLoader$$parserInstance$lzycompute:()Ljava/lang/ThreadLocal;
  #103 = Methodref          #2.#102       // scala/xml/XML$$anon$1.scala$xml$factory$XMLLoader$$parserInstance$lzycompute:()Ljava/lang/ThreadLocal;
  #104 = Utf8               java/lang/ThreadLocal
  #105 = Class              #104          // java/lang/ThreadLocal
  #106 = Utf8               ()Ljavax/xml/parsers/SAXParser;
  #107 = NameAndType        #14:#15       // parser:Ljavax/xml/parsers/SAXParser;
  #108 = Fieldref           #2.#107       // scala/xml/XML$$anon$1.parser:Ljavax/xml/parsers/SAXParser;
  #109 = Utf8               <init>
  #110 = Utf8               (Ljavax/xml/parsers/SAXParser;)V
  #111 = Utf8               p$1
  #112 = Utf8               ()V
  #113 = NameAndType        #109:#112     // "<init>":()V
  #114 = Methodref          #5.#113       // java/lang/Object."<init>":()V
  #115 = Utf8               $init$
  #116 = Utf8               (Lscala/xml/factory/XMLLoader;)V
  #117 = NameAndType        #115:#116     // $init$:(Lscala/xml/factory/XMLLoader;)V
  #118 = InterfaceMethodref #7.#117       // scala/xml/factory/XMLLoader.$init$:(Lscala/xml/factory/XMLLoader;)V
  #119 = Utf8               Signature
  #120 = Utf8               Code
  #121 = Utf8               LineNumberTable
  #122 = Utf8               LocalVariableTable
  #123 = Utf8               MethodParameters
  #124 = Utf8               StackMapTable
  #125 = Utf8               InnerClasses
  #126 = Utf8               EnclosingMethod
  #127 = Utf8               SourceFile
  #128 = Utf8               ScalaInlineInfo
  #129 = Utf8               Scala
{
  private final javax.xml.parsers.SAXParser parser;
    descriptor: Ljavax/xml/parsers/SAXParser;
    flags: (0x0012) ACC_PRIVATE, ACC_FINAL

  private java.lang.ThreadLocal<javax.xml.parsers.SAXParser> scala$xml$factory$XMLLoader$$parserInstance;
    descriptor: Ljava/lang/ThreadLocal;
    flags: (0x0002) ACC_PRIVATE
    Signature: #18                          // Ljava/lang/ThreadLocal<Ljavax/xml/parsers/SAXParser;>;

  private volatile boolean bitmap$0;
    descriptor: Z
    flags: (0x0042) ACC_PRIVATE, ACC_VOLATILE

  public scala.xml.parsing.FactoryAdapter adapter();
    descriptor: ()Lscala/xml/parsing/FactoryAdapter;
    flags: (0x0001) ACC_PUBLIC
    Code:
      stack=1, locals=1, args_size=1
         0: aload_0
         1: invokestatic  #26                 // InterfaceMethod scala/xml/factory/XMLLoader.adapter$:(Lscala/xml/factory/XMLLoader;)Lscala/xml/parsing/FactoryAdapter;
         4: areturn
      LineNumberTable:
        line 73: 0
      LocalVariableTable:
        Start  Length  Slot  Name   Signature
            0       5     0  this   Lscala/xml/XML$$anon$1;

  public scala.xml.Node loadXML(org.xml.sax.InputSource, javax.xml.parsers.SAXParser);
    descriptor: (Lorg/xml/sax/InputSource;Ljavax/xml/parsers/SAXParser;)Lscala/xml/Node;
    flags: (0x0001) ACC_PUBLIC
    Code:
      stack=3, locals=3, args_size=3
         0: aload_0
         1: aload_1
         2: aload_2
         3: invokestatic  #35                 // InterfaceMethod scala/xml/factory/XMLLoader.loadXML$:(Lscala/xml/factory/XMLLoader;Lorg/xml/sax/InputSource;Ljavax/xml/parsers/SAXParser;)Lscala/xml/Node;
         6: areturn
      LineNumberTable:
        line 73: 0
      LocalVariableTable:
        Start  Length  Slot  Name   Signature
            0       7     0  this   Lscala/xml/XML$$anon$1;
            0       7     1 source   Lorg/xml/sax/InputSource;
            0       7     2 parser   Ljavax/xml/parsers/SAXParser;
    MethodParameters:
      Name                           Flags
      source                         final
      parser                         final

  public scala.xml.Node loadFile(java.io.File);
    descriptor: (Ljava/io/File;)Lscala/xml/Node;
    flags: (0x0001) ACC_PUBLIC
    Code:
      stack=2, locals=2, args_size=2
         0: aload_0
         1: aload_1
         2: invokestatic  #43                 // InterfaceMethod scala/xml/factory/XMLLoader.loadFile$:(Lscala/xml/factory/XMLLoader;Ljava/io/File;)Lscala/xml/Node;
         5: areturn
      LineNumberTable:
        line 73: 0
      LocalVariableTable:
        Start  Length  Slot  Name   Signature
            0       6     0  this   Lscala/xml/XML$$anon$1;
            0       6     1  file   Ljava/io/File;
    MethodParameters:
      Name                           Flags
      file                           final

  public scala.xml.Node loadFile(java.io.FileDescriptor);
    descriptor: (Ljava/io/FileDescriptor;)Lscala/xml/Node;
    flags: (0x0001) ACC_PUBLIC
    Code:
      stack=2, locals=2, args_size=2
         0: aload_0
         1: aload_1
         2: invokestatic  #49                 // InterfaceMethod scala/xml/factory/XMLLoader.loadFile$:(Lscala/xml/factory/XMLLoader;Ljava/io/FileDescriptor;)Lscala/xml/Node;
         5: areturn
      LineNumberTable:
        line 73: 0
      LocalVariableTable:
        Start  Length  Slot  Name   Signature
            0       6     0  this   Lscala/xml/XML$$anon$1;
            0       6     1    fd   Ljava/io/FileDescriptor;
    MethodParameters:
      Name                           Flags
      fd                             final

  public scala.xml.Node loadFile(java.lang.String);
    descriptor: (Ljava/lang/String;)Lscala/xml/Node;
    flags: (0x0001) ACC_PUBLIC
    Code:
      stack=2, locals=2, args_size=2
         0: aload_0
         1: aload_1
         2: invokestatic  #55                 // InterfaceMethod scala/xml/factory/XMLLoader.loadFile$:(Lscala/xml/factory/XMLLoader;Ljava/lang/String;)Lscala/xml/Node;
         5: areturn
      LineNumberTable:
        line 73: 0
      LocalVariableTable:
        Start  Length  Slot  Name   Signature
            0       6     0  this   Lscala/xml/XML$$anon$1;
            0       6     1  name   Ljava/lang/String;
    MethodParameters:
      Name                           Flags
      name                           final

  public scala.xml.Node load(java.io.InputStream);
    descriptor: (Ljava/io/InputStream;)Lscala/xml/Node;
    flags: (0x0001) ACC_PUBLIC
    Code:
      stack=2, locals=2, args_size=2
         0: aload_0
         1: aload_1
         2: invokestatic  #63                 // InterfaceMethod scala/xml/factory/XMLLoader.load$:(Lscala/xml/factory/XMLLoader;Ljava/io/InputStream;)Lscala/xml/Node;
         5: areturn
      LineNumberTable:
        line 73: 0
      LocalVariableTable:
        Start  Length  Slot  Name   Signature
            0       6     0  this   Lscala/xml/XML$$anon$1;
            0       6     1    is   Ljava/io/InputStream;
    MethodParameters:
      Name                           Flags
      is                             final

  public scala.xml.Node load(java.io.Reader);
    descriptor: (Ljava/io/Reader;)Lscala/xml/Node;
    flags: (0x0001) ACC_PUBLIC
    Code:
      stack=2, locals=2, args_size=2
         0: aload_0
         1: aload_1
         2: invokestatic  #69                 // InterfaceMethod scala/xml/factory/XMLLoader.load$:(Lscala/xml/factory/XMLLoader;Ljava/io/Reader;)Lscala/xml/Node;
         5: areturn
      LineNumberTable:
        line 73: 0
      LocalVariableTable:
        Start  Length  Slot  Name   Signature
            0       6     0  this   Lscala/xml/XML$$anon$1;
            0       6     1 reader   Ljava/io/Reader;
    MethodParameters:
      Name                           Flags
      reader                         final

  public scala.xml.Node load(java.lang.String);
    descriptor: (Ljava/lang/String;)Lscala/xml/Node;
    flags: (0x0001) ACC_PUBLIC
    Code:
      stack=2, locals=2, args_size=2
         0: aload_0
         1: aload_1
         2: invokestatic  #73                 // InterfaceMethod scala/xml/factory/XMLLoader.load$:(Lscala/xml/factory/XMLLoader;Ljava/lang/String;)Lscala/xml/Node;
         5: areturn
      LineNumberTable:
        line 73: 0
      LocalVariableTable:
        Start  Length  Slot  Name   Signature
            0       6     0  this   Lscala/xml/XML$$anon$1;
            0       6     1 sysID   Ljava/lang/String;
    MethodParameters:
      Name                           Flags
      sysID                          final

  public scala.xml.Node load(org.xml.sax.InputSource);
    descriptor: (Lorg/xml/sax/InputSource;)Lscala/xml/Node;
    flags: (0x0001) ACC_PUBLIC
    Code:
      stack=2, locals=2, args_size=2
         0: aload_0
         1: aload_1
         2: invokestatic  #77                 // InterfaceMethod scala/xml/factory/XMLLoader.load$:(Lscala/xml/factory/XMLLoader;Lorg/xml/sax/InputSource;)Lscala/xml/Node;
         5: areturn
      LineNumberTable:
        line 73: 0
      LocalVariableTable:
        Start  Length  Slot  Name   Signature
            0       6     0  this   Lscala/xml/XML$$anon$1;
            0       6     1 source   Lorg/xml/sax/InputSource;
    MethodParameters:
      Name                           Flags
      source                         final

  public scala.xml.Node load(java.net.URL);
    descriptor: (Ljava/net/URL;)Lscala/xml/Node;
    flags: (0x0001) ACC_PUBLIC
    Code:
      stack=2, locals=2, args_size=2
         0: aload_0
         1: aload_1
         2: invokestatic  #82                 // InterfaceMethod scala/xml/factory/XMLLoader.load$:(Lscala/xml/factory/XMLLoader;Ljava/net/URL;)Lscala/xml/Node;
         5: areturn
      LineNumberTable:
        line 73: 0
      LocalVariableTable:
        Start  Length  Slot  Name   Signature
            0       6     0  this   Lscala/xml/XML$$anon$1;
            0       6     1   url   Ljava/net/URL;
    MethodParameters:
      Name                           Flags
      url                            final

  public scala.xml.Node loadString(java.lang.String);
    descriptor: (Ljava/lang/String;)Lscala/xml/Node;
    flags: (0x0001) ACC_PUBLIC
    Code:
      stack=2, locals=2, args_size=2
         0: aload_0
         1: aload_1
         2: invokestatic  #88                 // InterfaceMethod scala/xml/factory/XMLLoader.loadString$:(Lscala/xml/factory/XMLLoader;Ljava/lang/String;)Lscala/xml/Node;
         5: areturn
      LineNumberTable:
        line 73: 0
      LocalVariableTable:
        Start  Length  Slot  Name   Signature
            0       6     0  this   Lscala/xml/XML$$anon$1;
            0       6     1 string   Ljava/lang/String;
    MethodParameters:
      Name                           Flags
      string                         final

  private java.lang.ThreadLocal<javax.xml.parsers.SAXParser> scala$xml$factory$XMLLoader$$parserInstance$lzycompute();
    descriptor: ()Ljava/lang/ThreadLocal;
    flags: (0x0002) ACC_PRIVATE
    Code:
      stack=2, locals=2, args_size=1
         0: aload_0
         1: dup
         2: astore_1
         3: monitorenter
         4: aload_0
         5: getfield      #93                 // Field bitmap$0:Z
         8: ifne          24
        11: aload_0
        12: aload_0
        13: invokestatic  #97                 // InterfaceMethod scala/xml/factory/XMLLoader.scala$xml$factory$XMLLoader$$parserInstance$:(Lscala/xml/factory/XMLLoader;)Ljava/lang/ThreadLocal;
        16: putfield      #99                 // Field scala$xml$factory$XMLLoader$$parserInstance:Ljava/lang/ThreadLocal;
        19: aload_0
        20: iconst_1
        21: putfield      #93                 // Field bitmap$0:Z
        24: aload_1
        25: monitorexit
        26: goto          32
        29: aload_1
        30: monitorexit
        31: athrow
        32: aload_0
        33: getfield      #99                 // Field scala$xml$factory$XMLLoader$$parserInstance:Ljava/lang/ThreadLocal;
        36: areturn
      Exception table:
         from    to  target type
             4    24    29   any
      StackMapTable: number_of_entries = 3
        frame_type = 252 /* append */
          offset_delta = 24
          locals = [ class scala/xml/XML$$anon$1 ]
        frame_type = 68 /* same_locals_1_stack_item */
          stack = [ class java/lang/Throwable ]
        frame_type = 2 /* same */
      LineNumberTable:
        line 73: 0
      LocalVariableTable:
        Start  Length  Slot  Name   Signature
            0      37     0  this   Lscala/xml/XML$$anon$1;
    Signature: #91                          // ()Ljava/lang/ThreadLocal<Ljavax/xml/parsers/SAXParser;>;

  public java.lang.ThreadLocal<javax.xml.parsers.SAXParser> scala$xml$factory$XMLLoader$$parserInstance();
    descriptor: ()Ljava/lang/ThreadLocal;
    flags: (0x0001) ACC_PUBLIC
    Code:
      stack=1, locals=1, args_size=1
         0: aload_0
         1: getfield      #93                 // Field bitmap$0:Z
         4: ifne          14
         7: aload_0
         8: invokespecial #103                // Method scala$xml$factory$XMLLoader$$parserInstance$lzycompute:()Ljava/lang/ThreadLocal;
        11: goto          18
        14: aload_0
        15: getfield      #99                 // Field scala$xml$factory$XMLLoader$$parserInstance:Ljava/lang/ThreadLocal;
        18: areturn
      StackMapTable: number_of_entries = 2
        frame_type = 14 /* same */
        frame_type = 67 /* same_locals_1_stack_item */
          stack = [ class java/lang/ThreadLocal ]
      LineNumberTable:
        line 73: 0
      LocalVariableTable:
        Start  Length  Slot  Name   Signature
            0      19     0  this   Lscala/xml/XML$$anon$1;
    Signature: #91                          // ()Ljava/lang/ThreadLocal<Ljavax/xml/parsers/SAXParser;>;

  public javax.xml.parsers.SAXParser parser();
    descriptor: ()Ljavax/xml/parsers/SAXParser;
    flags: (0x0001) ACC_PUBLIC
    Code:
      stack=1, locals=1, args_size=1
         0: aload_0
         1: getfield      #108                // Field parser:Ljavax/xml/parsers/SAXParser;
         4: areturn
      LineNumberTable:
        line 73: 0
      LocalVariableTable:
        Start  Length  Slot  Name   Signature
            0       5     0  this   Lscala/xml/XML$$anon$1;

  public scala.xml.XML$$anon$1(javax.xml.parsers.SAXParser);
    descriptor: (Ljavax/xml/parsers/SAXParser;)V
    flags: (0x0001) ACC_PUBLIC
    Code:
      stack=2, locals=2, args_size=2
         0: aload_0
         1: invokespecial #114                // Method java/lang/Object."<init>":()V
         4: aload_0
         5: invokestatic  #118                // InterfaceMethod scala/xml/factory/XMLLoader.$init$:(Lscala/xml/factory/XMLLoader;)V
         8: aload_0
         9: aload_1
        10: putfield      #108                // Field parser:Ljavax/xml/parsers/SAXParser;
        13: return
      LineNumberTable:
        line 73: 0
      LocalVariableTable:
        Start  Length  Slot  Name   Signature
            0      14     0  this   Lscala/xml/XML$$anon$1;
            0      14     1   p$1   Ljavax/xml/parsers/SAXParser;
    MethodParameters:
      Name                           Flags
      p$1                            final
}
InnerClasses:
  public final #2;                        // class scala/xml/XML$$anon$1
EnclosingMethod: #10.#13                // scala.xml.XML$.withSAXParser
Signature: #3                           // Ljava/lang/Object;Lscala/xml/factory/XMLLoader<Lscala/xml/Elem;>;
SourceFile: "XML.scala"
  ScalaInlineInfo: length = 0x4F (unknown attribute)
   01 01 00 0F 00 6D 00 6E 01 00 15 00 16 01 00 39
   00 3A 01 00 39 00 41 01 00 39 00 33 01 00 39 00
   4E 01 00 39 00 4A 01 00 25 00 26 01 00 25 00 2D
   01 00 25 00 33 01 00 54 00 33 01 00 1D 00 1E 01
   00 0E 00 6A 01 00 10 00 5A 01 00 59 00 5A 01
  Scala: length = 0x0 (unknown attribute)

