Classfile /Users/mw/Projects/slang-braindump/.jar/jar11/assemble/slang-braindump/assemble/content/org/sireum/message/Level.class
  Last modified May 29, 2022; size 3677 bytes
  SHA-256 checksum 924fe749c8ce123d63bfb2cb8662f077707d3bd248f67be24786b2506575aef6
  Compiled from "Message.scala"
public final class org.sireum.message.Level
  minor version: 0
  major version: 52
  flags: (0x0031) ACC_PUBLIC, ACC_FINAL, ACC_SUPER
  this_class: #2                          // org/sireum/message/Level
  super_class: #4                         // java/lang/Object
  interfaces: 0, fields: 0, methods: 6, attributes: 4
Constant pool:
   #1 = Utf8               org/sireum/message/Level
   #2 = Class              #1             // org/sireum/message/Level
   #3 = Utf8               java/lang/Object
   #4 = Class              #3             // java/lang/Object
   #5 = Utf8               Message.scala
   #6 = Utf8               Lscala/reflect/ScalaSignature;
   #7 = Utf8               bytes
   #8 = Utf8               \u0006\u0005\t\u0005q!B#G\u0011\u0003ie!B(G\u0011\u0003\u0001\u0006\"B.\u0002\t\u0003afaB/\u0002!\u0003\r\tC\u0018\u0005\u0006a\u000e!\t!\u001d\u0005\u0006k\u000e1\tA\u001e\u0005\u0006u\u000e1\ta\u001f\u0005\u0006\u007f\u000e!)A\u001e\u0005\b\u0003\u0003\u0019AQAA\u0002\u0011\u001d\tya\u0001C\u0003\u0003#Aa!!\b\u0004\t\u000bY\bbBA\\\u0003\u0011\u0015\u0011\u0011\u0018\u0005\b\u0003\u0007\fAQAAc\u000f\u001d\tY-\u0001EC\u0003;3q!a&\u0002\u0011\u000b\u000bI\n\u0003\u0004\\\u001d\u0011\u0005\u00111\u0014\u0005\u0006k:!\tA\u001e\u0005\u0006u:!\ta\u001f\u0005\n\u0003kq\u0011\u0011!C!\u0003oA\u0011\"a\u0012\u000f\u0003\u0003%\t!!\u0013\t\u0013\u0005-c\"!A\u0005\u0002\u0005}\u0005\"CA-\u001d\u0005\u0005I\u0011IA.\u0011%\tIGDA\u0001\n\u0003\t\u0019\u000bC\u0005\u0002v9\t\t\u0011\"\u0011\u0002x!I\u0011\u0011\u0010\b\u0002\u0002\u0013\u0005\u00131\u0010\u0005\n\u0003{r\u0011\u0011!C\u0005\u0003\u007f:q!!4\u0002\u0011\u000b\u000b\u0019DB\u0004\u0002\"\u0005A))a\t\t\rm[B\u0011AA\u0019\u0011\u0015)8\u0004\"\u0001w\u0011\u0015Q8\u0004\"\u0001|\u0011%\t)dGA\u0001\n\u0003\n9\u0004C\u0005\u0002Hm\t\t\u0011\"\u0001\u0002J!I\u00111J\u000e\u0002\u0002\u0013\u0005\u0011Q\n\u0005\n\u00033Z\u0012\u0011!C!\u00037B\u0011\"!\u001b\u001c\u0003\u0003%\t!a\u001b\t\u0013\u0005U4$!A\u0005B\u0005]\u0004\"CA=7\u0005\u0005I\u0011IA>\u0011%\tihGA\u0001\n\u0013\tyhB\u0004\u0002P\u0006A))!,\u0007\u000f\u0005\u001d\u0016\u0001#\"\u0002*\"11\f\u000bC\u0001\u0003WCQ!\u001e\u0015\u0005\u0002YDQA\u001f\u0015\u0005\u0002mD\u0011\"!\u000e)\u0003\u0003%\t%a\u000e\t\u0013\u0005\u001d\u0003&!A\u0005\u0002\u0005%\u0003\"CA&Q\u0005\u0005I\u0011AAX\u0011%\tI\u0006KA\u0001\n\u0003\nY\u0006C\u0005\u0002j!\n\t\u0011\"\u0001\u00024\"I\u0011Q\u000f\u0015\u0002\u0002\u0013\u0005\u0013q\u000f\u0005\n\u0003sB\u0013\u0011!C!\u0003wB\u0011\"! )\u0003\u0003%I!a \b\u000f\u0005E\u0017\u0001#\"\u0002\u000e\u001a9\u0011qQ\u0001\t\u0006\u0006%\u0005BB.6\t\u0003\tY\tC\u0003vk\u0011\u0005a\u000fC\u0003{k\u0011\u00051\u0010C\u0005\u00026U\n\t\u0011\"\u0011\u00028!I\u0011qI\u001b\u0002\u0002\u0013\u0005\u0011\u0011\n\u0005\n\u0003\u0017*\u0014\u0011!C\u0001\u0003\u001fC\u0011\"!\u00176\u0003\u0003%\t%a\u0017\t\u0013\u0005%T\'!A\u0005\u0002\u0005M\u0005\"CA;k\u0005\u0005I\u0011IA<\u0011%\tI(NA\u0001\n\u0003\nY\bC\u0005\u0002~U\n\t\u0011\"\u0003\u0002\u0000!A\u00111[\u0001C\u0002\u0013\u0005a\u000fC\u0004\u0002V\u0006\u0001\u000b\u0011B<\t\u0013\u0005]\u0017A1A\u0005\u0002\u0005e\u0007\u0002CA{\u0003\u0001\u0006I!a7\u0002\u000b1+g/\u001a7\u000b\u0005\u001dC\u0015aB7fgN\fw-\u001a\u0006\u0003\u0013*\u000baa]5sKVl\'\"A&\u0002\u0007=\u0014xm\u0001\u0001\u0011\u00059\u000bQ\"\u0001$\u0003\u000b1+g/\u001a7\u0014\u0007\u0005\tv\u000b\u0005\u0002S+6\t1KC\u0001U\u0003\u0015\u00198-\u00197b\u0013\t16K\u0001\u0004B]f\u0014VM\u001a\t\u00031fk\u0011\u0001S\u0005\u00035\"\u0013q!\u00128v[NKw-\u0001\u0004=S:LGO\u0010\u000b\u0002\u001b\n!A+\u001f9f\'\u0011\u0019\u0011k\u00182\u0011\u0005a\u0003\u0017BA1I\u0005%IU.\\;uC\ndW\rE\u0002dW:t!\u0001Z5\u000f\u0005\u0015DW\"\u00014\u000b\u0005\u001dd\u0015A\u0002\u001fs_>$h(C\u0001U\u0013\tQ7+A\u0004qC\u000e\\\u0017mZ3\n\u00051l\'aB(sI\u0016\u0014X\r\u001a\u0006\u0003UN\u0003\"a\\\u0002\u000e\u0003\u0005\ta\u0001J5oSR$C#\u0001:\u0011\u0005I\u001b\u0018B\u0001;T\u0005\u0011)f.\u001b;\u0002\u000f=\u0014H-\u001b8bYV\tq\u000f\u0005\u0002Yq&\u0011\u0011\u0010\u0013\u0002\u00025\u0006!a.Y7f+\u0005a\bC\u0001-~\u0013\tq\bJ\u0001\u0004TiJLgnZ\u0001\u0005Q\u0006\u001c\b.A\u0004jg\u0016\u000bX/\u00197\u0015\t\u0005\u0015\u00111\u0002\t\u00041\u0006\u001d\u0011bAA\u0005\u0011\n\t!\t\u0003\u0004\u0002\u000e!\u0001\rA\\\u0001\u0006_RDWM]\u0001\bG>l\u0007/\u0019:f)\u0011\t\u0019\"!\u0007\u0011\u0007I\u000b)\"C\u0002\u0002\u0018M\u00131!\u00138u\u0011\u0019\tY\"\u0003a\u0001]\u0006!A\u000f[1u\u0003\u0019\u0019HO]5oO&*1aG\u001b\u000fQ\t)QI\u001d:peN91$\u00158\u0002&\u0005-\u0002c\u0001*\u0002(%\u0019\u0011\u0011F*\u0003\u000fA\u0013x\u000eZ;diB\u00191-!\f\n\u0007\u0005=RN\u0001\u0007TKJL\u0017\r\\5{C\ndW\r\u0006\u0002\u00024A\u0011qnG\u0001\u000eaJ|G-^2u!J,g-\u001b=\u0016\u0005\u0005e\u0002\u0003BA\u001e\u0003\u000bj!!!\u0010\u000b\t\u0005}\u0012\u0011I\u0001\u0005Y\u0006twM\u0003\u0002\u0002D\u0005!!.\u0019<b\u0013\rq\u0018QH\u0001\raJ|G-^2u\u0003JLG/_\u000b\u0003\u0003\'\ta\u0002\u001d:pIV\u001cG/\u00127f[\u0016tG\u000f\u0006\u0003\u0002P\u0005U\u0003c\u0001*\u0002R%\u0019\u00111K*\u0003\u0007\u0005s\u0017\u0010C\u0005\u0002X\u0005\n\t\u00111\u0001\u0002\u0014\u0005\u0019\u0001\u0010J\u0019\u0002\u001fA\u0014x\u000eZ;di&#XM]1u_J,\"!!\u0018\u0011\r\u0005}\u0013QMA(\u001b\t\t\tGC\u0002\u0002dM\u000b!bY8mY\u0016\u001cG/[8o\u0013\u0011\t9\'!\u0019\u0003\u0011%#XM]1u_J\f\u0001bY1o\u000bF,\u0018\r\u001c\u000b\u0005\u0003[\n\u0019\bE\u0002S\u0003_J1!!\u001dT\u0005\u001d\u0011un\u001c7fC:D\u0011\"a\u0016$\u0003\u0003\u0005\r!a\u0014\u0002\u0011!\f7\u000f[\"pI\u0016$\"!a\u0005\u0002\u0011Q|7\u000b\u001e:j]\u001e$\"!!\u000f\u0002\u0019]\u0014\u0018\u000e^3SKBd\u0017mY3\u0015\u0005\u0005\u0005\u0005\u0003BA\u001e\u0003\u0007KA!!\"\u0002>\t1qJ\u00196fGR\u0014A!\u00138g_N9Q\'\u00158\u0002&\u0005-BCAAG!\tyW\u0007\u0006\u0003\u0002P\u0005E\u0005\"CA,w\u0005\u0005\t\u0019AA\n)\u0011\ti\'!&\t\u0013\u0005]S(!AA\u0002\u0005=#!D%oi\u0016\u0014h.\u00197FeJ|\'oE\u0004\u000f#:\f)#a\u000b\u0015\u0005\u0005u\u0005CA8\u000f)\u0011\ty%!)\t\u0013\u0005]C#!AA\u0002\u0005MA\u0003BA7\u0003KC\u0011\"a\u0016\u0017\u0003\u0003\u0005\r!a\u0014\u0003\u000f]\u000b\'O\\5oON9\u0001&\u00158\u0002&\u0005-BCAAW!\ty\u0007\u0006\u0006\u0003\u0002P\u0005E\u0006\"CA,]\u0005\u0005\t\u0019AA\n)\u0011\ti\'!.\t\u0013\u0005]\u0003\'!AA\u0002\u0005=\u0013A\u00022z\u001d\u0006lW\r\u0006\u0003\u0002<\u0006\u0005\u0007\u0003\u0002-\u0002>:L1!a0I\u0005\u0019y\u0005\u000f^5p]\")!p\u0003a\u0001y\u0006I!-_(sI&t\u0017\r\u001c\u000b\u0005\u0003w\u000b9\r\u0003\u0004\u0002J2\u0001\ra^\u0001\u0002]\u0006i\u0011J\u001c;fe:\fG.\u0012:s_J\fQ!\u0012:s_J\fqaV1s]&tw-\u0001\u0003J]\u001a|\u0017!\u00048v[>3W\t\\3nK:$8/\u0001\bok6|e-\u00127f[\u0016tGo\u001d\u0011\u0002\u0011\u0015dW-\\3oiN,\"!a7\u0011\u000b\u0005u\u0017\u0011\u001e8\u000f\t\u0005}\u0017q\u001d\b\u0005\u0003C\f)OD\u0002f\u0003GL\u0011aS\u0005\u0003\u0013*K!A\u001b%\n\t\u0005-\u0018Q\u001e\u0002\u0004\u0013NS\u0016\u0002BAx\u0003c\u0014A\u0002U1dW\u0006<W\r\u0016:bSRT1!a=I\u0003%!\u0013N\u001c;fe:\fG.A\u0005fY\u0016lWM\u001c;tA!\u001a\u0011!!?\u0011\u0007a\u000bY0C\u0002\u0002~\"\u0013A!\u001a8v[\"\u001a\u0001!!?
   #9 = Utf8               org/sireum/message/Level$Error$
  #10 = Class              #9             // org/sireum/message/Level$Error$
  #11 = Utf8               Error$
  #12 = Utf8               org/sireum/message/Level$Info$
  #13 = Class              #12            // org/sireum/message/Level$Info$
  #14 = Utf8               Info$
  #15 = Utf8               org/sireum/message/Level$InternalError$
  #16 = Class              #15            // org/sireum/message/Level$InternalError$
  #17 = Utf8               InternalError$
  #18 = Utf8               org/sireum/message/Level$Type
  #19 = Class              #18            // org/sireum/message/Level$Type
  #20 = Utf8               Type
  #21 = Utf8               org/sireum/message/Level$Warning$
  #22 = Class              #21            // org/sireum/message/Level$Warning$
  #23 = Utf8               Warning$
  #24 = Utf8               elements
  #25 = Utf8               ()Lorg/sireum/IS;
  #26 = Utf8               ()Lorg/sireum/IS<Lorg/sireum/Z;Lorg/sireum/message/Level$Type;>;
  #27 = Utf8               org/sireum/message/Level$
  #28 = Class              #27            // org/sireum/message/Level$
  #29 = Utf8               MODULE$
  #30 = Utf8               Lorg/sireum/message/Level$;
  #31 = NameAndType        #29:#30        // MODULE$:Lorg/sireum/message/Level$;
  #32 = Fieldref           #28.#31        // org/sireum/message/Level$.MODULE$:Lorg/sireum/message/Level$;
  #33 = NameAndType        #24:#25        // elements:()Lorg/sireum/IS;
  #34 = Methodref          #28.#33        // org/sireum/message/Level$.elements:()Lorg/sireum/IS;
  #35 = Utf8               numOfElements
  #36 = Utf8               ()Lorg/sireum/Z;
  #37 = NameAndType        #35:#36        // numOfElements:()Lorg/sireum/Z;
  #38 = Methodref          #28.#37        // org/sireum/message/Level$.numOfElements:()Lorg/sireum/Z;
  #39 = Utf8               byOrdinal
  #40 = Utf8               (Lorg/sireum/Z;)Lorg/sireum/Option;
  #41 = Utf8               (Lorg/sireum/Z;)Lorg/sireum/Option<Lorg/sireum/message/Level$Type;>;
  #42 = Utf8               n
  #43 = NameAndType        #39:#40        // byOrdinal:(Lorg/sireum/Z;)Lorg/sireum/Option;
  #44 = Methodref          #28.#43        // org/sireum/message/Level$.byOrdinal:(Lorg/sireum/Z;)Lorg/sireum/Option;
  #45 = Utf8               Lorg/sireum/Z;
  #46 = Utf8               byName
  #47 = Utf8               (Ljava/lang/String;)Lorg/sireum/Option;
  #48 = Utf8               (Ljava/lang/String;)Lorg/sireum/Option<Lorg/sireum/message/Level$Type;>;
  #49 = Utf8               name
  #50 = NameAndType        #46:#47        // byName:(Ljava/lang/String;)Lorg/sireum/Option;
  #51 = Methodref          #28.#50        // org/sireum/message/Level$.byName:(Ljava/lang/String;)Lorg/sireum/Option;
  #52 = Utf8               Ljava/lang/String;
  #53 = Utf8               string
  #54 = Utf8               ()Ljava/lang/String;
  #55 = NameAndType        #53:#54        // string:()Ljava/lang/String;
  #56 = Methodref          #28.#55        // org/sireum/message/Level$.string:()Ljava/lang/String;
  #57 = Utf8               $clone
  #58 = Utf8               ()Lorg/sireum/$internal/ImmutableMarker;
  #59 = NameAndType        #57:#58        // $clone:()Lorg/sireum/$internal/ImmutableMarker;
  #60 = Methodref          #28.#59        // org/sireum/message/Level$.$clone:()Lorg/sireum/$internal/ImmutableMarker;
  #61 = Utf8               Code
  #62 = Utf8               Signature
  #63 = Utf8               LocalVariableTable
  #64 = Utf8               MethodParameters
  #65 = Utf8               InnerClasses
  #66 = Utf8               SourceFile
  #67 = Utf8               RuntimeVisibleAnnotations
  #68 = Utf8               ScalaSig
{
  public static org.sireum.IS<org.sireum.Z, org.sireum.message.Level$Type> elements();
    descriptor: ()Lorg/sireum/IS;
    flags: (0x0009) ACC_PUBLIC, ACC_STATIC
    Code:
      stack=1, locals=0, args_size=0
         0: getstatic     #32                 // Field org/sireum/message/Level$.MODULE$:Lorg/sireum/message/Level$;
         3: invokevirtual #34                 // Method org/sireum/message/Level$.elements:()Lorg/sireum/IS;
         6: areturn
    Signature: #26                          // ()Lorg/sireum/IS<Lorg/sireum/Z;Lorg/sireum/message/Level$Type;>;

  public static org.sireum.Z numOfElements();
    descriptor: ()Lorg/sireum/Z;
    flags: (0x0009) ACC_PUBLIC, ACC_STATIC
    Code:
      stack=1, locals=0, args_size=0
         0: getstatic     #32                 // Field org/sireum/message/Level$.MODULE$:Lorg/sireum/message/Level$;
         3: invokevirtual #38                 // Method org/sireum/message/Level$.numOfElements:()Lorg/sireum/Z;
         6: areturn

  public static org.sireum.Option<org.sireum.message.Level$Type> byOrdinal(org.sireum.Z);
    descriptor: (Lorg/sireum/Z;)Lorg/sireum/Option;
    flags: (0x0009) ACC_PUBLIC, ACC_STATIC
    Code:
      stack=2, locals=1, args_size=1
         0: getstatic     #32                 // Field org/sireum/message/Level$.MODULE$:Lorg/sireum/message/Level$;
         3: aload_0
         4: invokevirtual #44                 // Method org/sireum/message/Level$.byOrdinal:(Lorg/sireum/Z;)Lorg/sireum/Option;
         7: areturn
      LocalVariableTable:
        Start  Length  Slot  Name   Signature
            0       8     0     n   Lorg/sireum/Z;
    Signature: #41                          // (Lorg/sireum/Z;)Lorg/sireum/Option<Lorg/sireum/message/Level$Type;>;
    MethodParameters:
      Name                           Flags
      n                              final

  public static org.sireum.Option<org.sireum.message.Level$Type> byName(java.lang.String);
    descriptor: (Ljava/lang/String;)Lorg/sireum/Option;
    flags: (0x0009) ACC_PUBLIC, ACC_STATIC
    Code:
      stack=2, locals=1, args_size=1
         0: getstatic     #32                 // Field org/sireum/message/Level$.MODULE$:Lorg/sireum/message/Level$;
         3: aload_0
         4: invokevirtual #51                 // Method org/sireum/message/Level$.byName:(Ljava/lang/String;)Lorg/sireum/Option;
         7: areturn
      LocalVariableTable:
        Start  Length  Slot  Name   Signature
            0       8     0  name   Ljava/lang/String;
    Signature: #48                          // (Ljava/lang/String;)Lorg/sireum/Option<Lorg/sireum/message/Level$Type;>;
    MethodParameters:
      Name                           Flags
      name                           final

  public static java.lang.String string();
    descriptor: ()Ljava/lang/String;
    flags: (0x0009) ACC_PUBLIC, ACC_STATIC
    Code:
      stack=1, locals=0, args_size=0
         0: getstatic     #32                 // Field org/sireum/message/Level$.MODULE$:Lorg/sireum/message/Level$;
         3: invokevirtual #56                 // Method org/sireum/message/Level$.string:()Ljava/lang/String;
         6: areturn

  public static org.sireum.$internal.ImmutableMarker $clone();
    descriptor: ()Lorg/sireum/$internal/ImmutableMarker;
    flags: (0x0009) ACC_PUBLIC, ACC_STATIC
    Code:
      stack=1, locals=0, args_size=0
         0: getstatic     #32                 // Field org/sireum/message/Level$.MODULE$:Lorg/sireum/message/Level$;
         3: invokevirtual #60                 // Method org/sireum/message/Level$.$clone:()Lorg/sireum/$internal/ImmutableMarker;
         6: areturn
}
InnerClasses:
  public static final #11= #10 of #2;     // Error$=class org/sireum/message/Level$Error$ of class org/sireum/message/Level
  public static final #14= #13 of #2;     // Info$=class org/sireum/message/Level$Info$ of class org/sireum/message/Level
  public static final #17= #16 of #2;     // InternalError$=class org/sireum/message/Level$InternalError$ of class org/sireum/message/Level
  public static #20= #19 of #2;           // Type=class org/sireum/message/Level$Type of class org/sireum/message/Level
  public static final #23= #22 of #2;     // Warning$=class org/sireum/message/Level$Warning$ of class org/sireum/message/Level
SourceFile: "Message.scala"
RuntimeVisibleAnnotations:
  0: #6(#7=s#8)
    scala.reflect.ScalaSignature(
      bytes="\u0006\u0005\t\u0005q!B#G\u0011\u0003ie!B(G\u0011\u0003\u0001\u0006\"B.\u0002\t\u0003afaB/\u0002!\u0003\r\tC\u0018\u0005\u0006a\u000e!\t!\u001d\u0005\u0006k\u000e1\tA\u001e\u0005\u0006u\u000e1\ta\u001f\u0005\u0006\u007f\u000e!)A\u001e\u0005\b\u0003\u0003\u0019AQAA\u0002\u0011\u001d\tya\u0001C\u0003\u0003#Aa!!\b\u0004\t\u000bY\bbBA\\\u0003\u0011\u0015\u0011\u0011\u0018\u0005\b\u0003\u0007\fAQAAc\u000f\u001d\tY-\u0001EC\u0003;3q!a&\u0002\u0011\u000b\u000bI\n\u0003\u0004\\\u001d\u0011\u0005\u00111\u0014\u0005\u0006k:!\tA\u001e\u0005\u0006u:!\ta\u001f\u0005\n\u0003kq\u0011\u0011!C!\u0003oA\u0011\"a\u0012\u000f\u0003\u0003%\t!!\u0013\t\u0013\u0005-c\"!A\u0005\u0002\u0005}\u0005\"CA-\u001d\u0005\u0005I\u0011IA.\u0011%\tIGDA\u0001\n\u0003\t\u0019\u000bC\u0005\u0002v9\t\t\u0011\"\u0011\u0002x!I\u0011\u0011\u0010\b\u0002\u0002\u0013\u0005\u00131\u0010\u0005\n\u0003{r\u0011\u0011!C\u0005\u0003\u007f:q!!4\u0002\u0011\u000b\u000b\u0019DB\u0004\u0002\"\u0005A))a\t\t\rm[B\u0011AA\u0019\u0011\u0015)8\u0004\"\u0001w\u0011\u0015Q8\u0004\"\u0001|\u0011%\t)dGA\u0001\n\u0003\n9\u0004C\u0005\u0002Hm\t\t\u0011\"\u0001\u0002J!I\u00111J\u000e\u0002\u0002\u0013\u0005\u0011Q\n\u0005\n\u00033Z\u0012\u0011!C!\u00037B\u0011\"!\u001b\u001c\u0003\u0003%\t!a\u001b\t\u0013\u0005U4$!A\u0005B\u0005]\u0004\"CA=7\u0005\u0005I\u0011IA>\u0011%\tihGA\u0001\n\u0013\tyhB\u0004\u0002P\u0006A))!,\u0007\u000f\u0005\u001d\u0016\u0001#\"\u0002*\"11\f\u000bC\u0001\u0003WCQ!\u001e\u0015\u0005\u0002YDQA\u001f\u0015\u0005\u0002mD\u0011\"!\u000e)\u0003\u0003%\t%a\u000e\t\u0013\u0005\u001d\u0003&!A\u0005\u0002\u0005%\u0003\"CA&Q\u0005\u0005I\u0011AAX\u0011%\tI\u0006KA\u0001\n\u0003\nY\u0006C\u0005\u0002j!\n\t\u0011\"\u0001\u00024\"I\u0011Q\u000f\u0015\u0002\u0002\u0013\u0005\u0013q\u000f\u0005\n\u0003sB\u0013\u0011!C!\u0003wB\u0011\"! )\u0003\u0003%I!a \b\u000f\u0005E\u0017\u0001#\"\u0002\u000e\u001a9\u0011qQ\u0001\t\u0006\u0006%\u0005BB.6\t\u0003\tY\tC\u0003vk\u0011\u0005a\u000fC\u0003{k\u0011\u00051\u0010C\u0005\u00026U\n\t\u0011\"\u0011\u00028!I\u0011qI\u001b\u0002\u0002\u0013\u0005\u0011\u0011\n\u0005\n\u0003\u0017*\u0014\u0011!C\u0001\u0003\u001fC\u0011\"!\u00176\u0003\u0003%\t%a\u0017\t\u0013\u0005%T\'!A\u0005\u0002\u0005M\u0005\"CA;k\u0005\u0005I\u0011IA<\u0011%\tI(NA\u0001\n\u0003\nY\bC\u0005\u0002~U\n\t\u0011\"\u0003\u0002\u0000!A\u00111[\u0001C\u0002\u0013\u0005a\u000fC\u0004\u0002V\u0006\u0001\u000b\u0011B<\t\u0013\u0005]\u0017A1A\u0005\u0002\u0005e\u0007\u0002CA{\u0003\u0001\u0006I!a7\u0002\u000b1+g/\u001a7\u000b\u0005\u001dC\u0015aB7fgN\fw-\u001a\u0006\u0003\u0013*\u000baa]5sKVl\'\"A&\u0002\u0007=\u0014xm\u0001\u0001\u0011\u00059\u000bQ\"\u0001$\u0003\u000b1+g/\u001a7\u0014\u0007\u0005\tv\u000b\u0005\u0002S+6\t1KC\u0001U\u0003\u0015\u00198-\u00197b\u0013\t16K\u0001\u0004B]f\u0014VM\u001a\t\u00031fk\u0011\u0001S\u0005\u00035\"\u0013q!\u00128v[NKw-\u0001\u0004=S:LGO\u0010\u000b\u0002\u001b\n!A+\u001f9f\'\u0011\u0019\u0011k\u00182\u0011\u0005a\u0003\u0017BA1I\u0005%IU.\\;uC\ndW\rE\u0002dW:t!\u0001Z5\u000f\u0005\u0015DW\"\u00014\u000b\u0005\u001dd\u0015A\u0002\u001fs_>$h(C\u0001U\u0013\tQ7+A\u0004qC\u000e\\\u0017mZ3\n\u00051l\'aB(sI\u0016\u0014X\r\u001a\u0006\u0003UN\u0003\"a\\\u0002\u000e\u0003\u0005\ta\u0001J5oSR$C#\u0001:\u0011\u0005I\u001b\u0018B\u0001;T\u0005\u0011)f.\u001b;\u0002\u000f=\u0014H-\u001b8bYV\tq\u000f\u0005\u0002Yq&\u0011\u0011\u0010\u0013\u0002\u00025\u0006!a.Y7f+\u0005a\bC\u0001-~\u0013\tq\bJ\u0001\u0004TiJLgnZ\u0001\u0005Q\u0006\u001c\b.A\u0004jg\u0016\u000bX/\u00197\u0015\t\u0005\u0015\u00111\u0002\t\u00041\u0006\u001d\u0011bAA\u0005\u0011\n\t!\t\u0003\u0004\u0002\u000e!\u0001\rA\\\u0001\u0006_RDWM]\u0001\bG>l\u0007/\u0019:f)\u0011\t\u0019\"!\u0007\u0011\u0007I\u000b)\"C\u0002\u0002\u0018M\u00131!\u00138u\u0011\u0019\tY\"\u0003a\u0001]\u0006!A\u000f[1u\u0003\u0019\u0019HO]5oO&*1aG\u001b\u000fQ\t)QI\u001d:peN91$\u00158\u0002&\u0005-\u0002c\u0001*\u0002(%\u0019\u0011\u0011F*\u0003\u000fA\u0013x\u000eZ;diB\u00191-!\f\n\u0007\u0005=RN\u0001\u0007TKJL\u0017\r\\5{C\ndW\r\u0006\u0002\u00024A\u0011qnG\u0001\u000eaJ|G-^2u!J,g-\u001b=\u0016\u0005\u0005e\u0002\u0003BA\u001e\u0003\u000bj!!!\u0010\u000b\t\u0005}\u0012\u0011I\u0001\u0005Y\u0006twM\u0003\u0002\u0002D\u0005!!.\u0019<b\u0013\rq\u0018QH\u0001\raJ|G-^2u\u0003JLG/_\u000b\u0003\u0003\'\ta\u0002\u001d:pIV\u001cG/\u00127f[\u0016tG\u000f\u0006\u0003\u0002P\u0005U\u0003c\u0001*\u0002R%\u0019\u00111K*\u0003\u0007\u0005s\u0017\u0010C\u0005\u0002X\u0005\n\t\u00111\u0001\u0002\u0014\u0005\u0019\u0001\u0010J\u0019\u0002\u001fA\u0014x\u000eZ;di&#XM]1u_J,\"!!\u0018\u0011\r\u0005}\u0013QMA(\u001b\t\t\tGC\u0002\u0002dM\u000b!bY8mY\u0016\u001cG/[8o\u0013\u0011\t9\'!\u0019\u0003\u0011%#XM]1u_J\f\u0001bY1o\u000bF,\u0018\r\u001c\u000b\u0005\u0003[\n\u0019\bE\u0002S\u0003_J1!!\u001dT\u0005\u001d\u0011un\u001c7fC:D\u0011\"a\u0016$\u0003\u0003\u0005\r!a\u0014\u0002\u0011!\f7\u000f[\"pI\u0016$\"!a\u0005\u0002\u0011Q|7\u000b\u001e:j]\u001e$\"!!\u000f\u0002\u0019]\u0014\u0018\u000e^3SKBd\u0017mY3\u0015\u0005\u0005\u0005\u0005\u0003BA\u001e\u0003\u0007KA!!\"\u0002>\t1qJ\u00196fGR\u0014A!\u00138g_N9Q\'\u00158\u0002&\u0005-BCAAG!\tyW\u0007\u0006\u0003\u0002P\u0005E\u0005\"CA,w\u0005\u0005\t\u0019AA\n)\u0011\ti\'!&\t\u0013\u0005]S(!AA\u0002\u0005=#!D%oi\u0016\u0014h.\u00197FeJ|\'oE\u0004\u000f#:\f)#a\u000b\u0015\u0005\u0005u\u0005CA8\u000f)\u0011\ty%!)\t\u0013\u0005]C#!AA\u0002\u0005MA\u0003BA7\u0003KC\u0011\"a\u0016\u0017\u0003\u0003\u0005\r!a\u0014\u0003\u000f]\u000b\'O\\5oON9\u0001&\u00158\u0002&\u0005-BCAAW!\ty\u0007\u0006\u0006\u0003\u0002P\u0005E\u0006\"CA,]\u0005\u0005\t\u0019AA\n)\u0011\ti\'!.\t\u0013\u0005]\u0003\'!AA\u0002\u0005=\u0013A\u00022z\u001d\u0006lW\r\u0006\u0003\u0002<\u0006\u0005\u0007\u0003\u0002-\u0002>:L1!a0I\u0005\u0019y\u0005\u000f^5p]\")!p\u0003a\u0001y\u0006I!-_(sI&t\u0017\r\u001c\u000b\u0005\u0003w\u000b9\r\u0003\u0004\u0002J2\u0001\ra^\u0001\u0002]\u0006i\u0011J\u001c;fe:\fG.\u0012:s_J\fQ!\u0012:s_J\fqaV1s]&tw-\u0001\u0003J]\u001a|\u0017!\u00048v[>3W\t\\3nK:$8/\u0001\bok6|e-\u00127f[\u0016tGo\u001d\u0011\u0002\u0011\u0015dW-\\3oiN,\"!a7\u0011\u000b\u0005u\u0017\u0011\u001e8\u000f\t\u0005}\u0017q\u001d\b\u0005\u0003C\f)OD\u0002f\u0003GL\u0011aS\u0005\u0003\u0013*K!A\u001b%\n\t\u0005-\u0018Q\u001e\u0002\u0004\u0013NS\u0016\u0002BAx\u0003c\u0014A\u0002U1dW\u0006<W\r\u0016:bSRT1!a=I\u0003%!\u0013N\u001c;fe:\fG.A\u0005fY\u0016lWM\u001c;tA!\u001a\u0011!!?\u0011\u0007a\u000bY0C\u0002\u0002~\"\u0013A!\u001a8v[\"\u001a\u0001!!?"
    )
  ScalaSig: length = 0x3 (unknown attribute)
   05 02 00
