Classfile /Users/mw/Projects/slang-braindump/.jar/jar11/assemble/slang-braindump/assemble/content/org/sireum/message/Message$.class
  Last modified May 29, 2022; size 1968 bytes
  SHA-256 checksum 95a22c92ea4d156223ccff36c33c3b8fcf49675186583db624292169f2665143
  Compiled from "Message.scala"
public final class org.sireum.message.Message$
  minor version: 0
  major version: 52
  flags: (0x0031) ACC_PUBLIC, ACC_FINAL, ACC_SUPER
  this_class: #2                          // org/sireum/message/Message$
  super_class: #4                         // java/lang/Object
  interfaces: 0, fields: 1, methods: 4, attributes: 4
Constant pool:
   #1 = Utf8               org/sireum/message/Message$
   #2 = Class              #1             // org/sireum/message/Message$
   #3 = Utf8               java/lang/Object
   #4 = Class              #3             // java/lang/Object
   #5 = Utf8               Message.scala
   #6 = Utf8               org/sireum/message/Level$Type
   #7 = Class              #6             // org/sireum/message/Level$Type
   #8 = Utf8               org/sireum/message/Level
   #9 = Class              #8             // org/sireum/message/Level
  #10 = Utf8               Type
  #11 = Utf8               MODULE$
  #12 = Utf8               Lorg/sireum/message/Message$;
  #13 = Utf8               <clinit>
  #14 = Utf8               ()V
  #15 = Utf8               <init>
  #16 = NameAndType        #15:#14        // "<init>":()V
  #17 = Methodref          #2.#16         // org/sireum/message/Message$."<init>":()V
  #18 = NameAndType        #11:#12        // MODULE$:Lorg/sireum/message/Message$;
  #19 = Fieldref           #2.#18         // org/sireum/message/Message$.MODULE$:Lorg/sireum/message/Message$;
  #20 = Utf8               apply
  #21 = Utf8               (Lorg/sireum/message/Level$Type;Lorg/sireum/Option;Ljava/lang/String;Ljava/lang/String;)Lorg/sireum/message/Message;
  #22 = Utf8               (Lorg/sireum/message/Level$Type;Lorg/sireum/Option<Lorg/sireum/message/Position;>;Ljava/lang/String;Ljava/lang/String;)Lorg/sireum/message/Message;
  #23 = Utf8               level
  #24 = Utf8               posOpt
  #25 = Utf8               kind
  #26 = Utf8               text
  #27 = Utf8               org/sireum/message/Message
  #28 = Class              #27            // org/sireum/message/Message
  #29 = Utf8               (Lorg/sireum/message/Level$Type;Lorg/sireum/Option;Ljava/lang/String;Ljava/lang/String;)V
  #30 = NameAndType        #15:#29        // "<init>":(Lorg/sireum/message/Level$Type;Lorg/sireum/Option;Ljava/lang/String;Ljava/lang/String;)V
  #31 = Methodref          #28.#30        // org/sireum/message/Message."<init>":(Lorg/sireum/message/Level$Type;Lorg/sireum/Option;Ljava/lang/String;Ljava/lang/String;)V
  #32 = Utf8               this
  #33 = Utf8               Lorg/sireum/message/Level$Type;
  #34 = Utf8               Lorg/sireum/Option;
  #35 = Utf8               Ljava/lang/String;
  #36 = Utf8               unapply
  #37 = Utf8               (Lorg/sireum/message/Message;)Lscala/Some;
  #38 = Utf8               (Lorg/sireum/message/Message;)Lscala/Some<Lscala/Tuple4<Lorg/sireum/message/Level$Type;Lorg/sireum/Option<Lorg/sireum/message/Position;>;Lorg/sireum/String;Lorg/sireum/String;>;>;
  #39 = Utf8               o
  #40 = Utf8               scala/Some
  #41 = Class              #40            // scala/Some
  #42 = Utf8               scala/Tuple4
  #43 = Class              #42            // scala/Tuple4
  #44 = Utf8               ()Lorg/sireum/message/Level$Type;
  #45 = NameAndType        #23:#44        // level:()Lorg/sireum/message/Level$Type;
  #46 = Methodref          #28.#45        // org/sireum/message/Message.level:()Lorg/sireum/message/Level$Type;
  #47 = Utf8               ()Lorg/sireum/Option;
  #48 = NameAndType        #24:#47        // posOpt:()Lorg/sireum/Option;
  #49 = Methodref          #28.#48        // org/sireum/message/Message.posOpt:()Lorg/sireum/Option;
  #50 = Utf8               org/sireum/String
  #51 = Class              #50            // org/sireum/String
  #52 = Utf8               ()Ljava/lang/String;
  #53 = NameAndType        #25:#52        // kind:()Ljava/lang/String;
  #54 = Methodref          #28.#53        // org/sireum/message/Message.kind:()Ljava/lang/String;
  #55 = Utf8               (Ljava/lang/String;)V
  #56 = NameAndType        #15:#55        // "<init>":(Ljava/lang/String;)V
  #57 = Methodref          #51.#56        // org/sireum/String."<init>":(Ljava/lang/String;)V
  #58 = NameAndType        #26:#52        // text:()Ljava/lang/String;
  #59 = Methodref          #28.#58        // org/sireum/message/Message.text:()Ljava/lang/String;
  #60 = Utf8               (Ljava/lang/Object;Ljava/lang/Object;Ljava/lang/Object;Ljava/lang/Object;)V
  #61 = NameAndType        #15:#60        // "<init>":(Ljava/lang/Object;Ljava/lang/Object;Ljava/lang/Object;Ljava/lang/Object;)V
  #62 = Methodref          #43.#61        // scala/Tuple4."<init>":(Ljava/lang/Object;Ljava/lang/Object;Ljava/lang/Object;Ljava/lang/Object;)V
  #63 = Utf8               (Ljava/lang/Object;)V
  #64 = NameAndType        #15:#63        // "<init>":(Ljava/lang/Object;)V
  #65 = Methodref          #41.#64        // scala/Some."<init>":(Ljava/lang/Object;)V
  #66 = Utf8               Lorg/sireum/message/Message;
  #67 = Methodref          #4.#16         // java/lang/Object."<init>":()V
  #68 = Utf8               Code
  #69 = Utf8               LineNumberTable
  #70 = Utf8               LocalVariableTable
  #71 = Utf8               Signature
  #72 = Utf8               MethodParameters
  #73 = Utf8               InnerClasses
  #74 = Utf8               SourceFile
  #75 = Utf8               ScalaInlineInfo
  #76 = Utf8               Scala
{
  public static final org.sireum.message.Message$ MODULE$;
    descriptor: Lorg/sireum/message/Message$;
    flags: (0x0019) ACC_PUBLIC, ACC_STATIC, ACC_FINAL

  public static {};
    descriptor: ()V
    flags: (0x0009) ACC_PUBLIC, ACC_STATIC
    Code:
      stack=2, locals=0, args_size=0
         0: new           #2                  // class org/sireum/message/Message$
         3: dup
         4: invokespecial #17                 // Method "<init>":()V
         7: putstatic     #19                 // Field MODULE$:Lorg/sireum/message/Message$;
        10: return
      LineNumberTable:
        line 39: 0

  public org.sireum.message.Message apply(org.sireum.message.Level$Type, org.sireum.Option<org.sireum.message.Position>, java.lang.String, java.lang.String);
    descriptor: (Lorg/sireum/message/Level$Type;Lorg/sireum/Option;Ljava/lang/String;Ljava/lang/String;)Lorg/sireum/message/Message;
    flags: (0x0001) ACC_PUBLIC
    Code:
      stack=6, locals=5, args_size=5
         0: new           #28                 // class org/sireum/message/Message
         3: dup
         4: aload_1
         5: aload_2
         6: aload_3
         7: aload         4
         9: invokespecial #31                 // Method org/sireum/message/Message."<init>":(Lorg/sireum/message/Level$Type;Lorg/sireum/Option;Ljava/lang/String;Ljava/lang/String;)V
        12: areturn
      LineNumberTable:
        line 39: 0
      LocalVariableTable:
        Start  Length  Slot  Name   Signature
            0      13     0  this   Lorg/sireum/message/Message$;
            0      13     1 level   Lorg/sireum/message/Level$Type;
            0      13     2 posOpt   Lorg/sireum/Option;
            0      13     3  kind   Ljava/lang/String;
            0      13     4  text   Ljava/lang/String;
    Signature: #22                          // (Lorg/sireum/message/Level$Type;Lorg/sireum/Option<Lorg/sireum/message/Position;>;Ljava/lang/String;Ljava/lang/String;)Lorg/sireum/message/Message;
    MethodParameters:
      Name                           Flags
      level                          final
      posOpt                         final
      kind                           final
      text                           final

  public scala.Some<scala.Tuple4<org.sireum.message.Level$Type, org.sireum.Option<org.sireum.message.Position>, org.sireum.String, org.sireum.String>> unapply(org.sireum.message.Message);
    descriptor: (Lorg/sireum/message/Message;)Lscala/Some;
    flags: (0x0001) ACC_PUBLIC
    Code:
      stack=10, locals=2, args_size=2
         0: new           #41                 // class scala/Some
         3: dup
         4: new           #43                 // class scala/Tuple4
         7: dup
         8: aload_1
         9: invokevirtual #46                 // Method org/sireum/message/Message.level:()Lorg/sireum/message/Level$Type;
        12: aload_1
        13: invokevirtual #49                 // Method org/sireum/message/Message.posOpt:()Lorg/sireum/Option;
        16: new           #51                 // class org/sireum/String
        19: dup
        20: aload_1
        21: invokevirtual #54                 // Method org/sireum/message/Message.kind:()Ljava/lang/String;
        24: invokespecial #57                 // Method org/sireum/String."<init>":(Ljava/lang/String;)V
        27: new           #51                 // class org/sireum/String
        30: dup
        31: aload_1
        32: invokevirtual #59                 // Method org/sireum/message/Message.text:()Ljava/lang/String;
        35: invokespecial #57                 // Method org/sireum/String."<init>":(Ljava/lang/String;)V
        38: invokespecial #62                 // Method scala/Tuple4."<init>":(Ljava/lang/Object;Ljava/lang/Object;Ljava/lang/Object;Ljava/lang/Object;)V
        41: invokespecial #65                 // Method scala/Some."<init>":(Ljava/lang/Object;)V
        44: areturn
      LineNumberTable:
        line 39: 0
      LocalVariableTable:
        Start  Length  Slot  Name   Signature
            0      45     0  this   Lorg/sireum/message/Message$;
            0      45     1     o   Lorg/sireum/message/Message;
    Signature: #38                          // (Lorg/sireum/message/Message;)Lscala/Some<Lscala/Tuple4<Lorg/sireum/message/Level$Type;Lorg/sireum/Option<Lorg/sireum/message/Position;>;Lorg/sireum/String;Lorg/sireum/String;>;>;
    MethodParameters:
      Name                           Flags
      o                              final

  private org.sireum.message.Message$();
    descriptor: ()V
    flags: (0x0002) ACC_PRIVATE
    Code:
      stack=1, locals=1, args_size=1
         0: aload_0
         1: invokespecial #67                 // Method java/lang/Object."<init>":()V
         4: return
      LineNumberTable:
        line 39: 0
      LocalVariableTable:
        Start  Length  Slot  Name   Signature
            0       5     0  this   Lorg/sireum/message/Message$;
}
InnerClasses:
  public static #10= #7 of #9;            // Type=class org/sireum/message/Level$Type of class org/sireum/message/Level
SourceFile: "Message.scala"
  ScalaInlineInfo: length = 0x13 (unknown attribute)
   01 01 00 03 00 0F 00 0E 01 00 14 00 15 01 00 24
   00 25 01
  Scala: length = 0x0 (unknown attribute)

