Classfile /Users/mw/Projects/slang-braindump/.jar/jar11/assemble/slang-braindump/assemble/content/org/sireum/message/Position$.class
  Last modified May 29, 2022; size 1818 bytes
  SHA-256 checksum 9c140ad86bb290320b555fbca6e102bc4547d09b8c8da58399a6df2ec9038d11
  Compiled from "Message.scala"
public final class org.sireum.message.Position$
  minor version: 0
  major version: 52
  flags: (0x0031) ACC_PUBLIC, ACC_FINAL, ACC_SUPER
  this_class: #2                          // org/sireum/message/Position$
  super_class: #4                         // java/lang/Object
  interfaces: 0, fields: 2, methods: 3, attributes: 4
Constant pool:
   #1 = Utf8               org/sireum/message/Position$
   #2 = Class              #1             // org/sireum/message/Position$
   #3 = Utf8               java/lang/Object
   #4 = Class              #3             // java/lang/Object
   #5 = Utf8               Message.scala
   #6 = Utf8               org/sireum/U32$U32$Slang
   #7 = Class              #6             // org/sireum/U32$U32$Slang
   #8 = Utf8               org/sireum/U32
   #9 = Class              #8             // org/sireum/U32
  #10 = Utf8               U32$Slang
  #11 = Utf8               org/sireum/U32$U32$Slang$u32$
  #12 = Class              #11            // org/sireum/U32$U32$Slang$u32$
  #13 = Utf8               u32$
  #14 = Utf8               MODULE$
  #15 = Utf8               Lorg/sireum/message/Position$;
  #16 = Utf8               none
  #17 = Utf8               Lorg/sireum/message/Position;
  #18 = Utf8               <clinit>
  #19 = Utf8               ()V
  #20 = Utf8               <init>
  #21 = NameAndType        #20:#19        // "<init>":()V
  #22 = Methodref          #2.#21         // org/sireum/message/Position$."<init>":()V
  #23 = NameAndType        #14:#15        // MODULE$:Lorg/sireum/message/Position$;
  #24 = Fieldref           #2.#23         // org/sireum/message/Position$.MODULE$:Lorg/sireum/message/Position$;
  #25 = Utf8               org/sireum/message/FlatPos$
  #26 = Class              #25            // org/sireum/message/FlatPos$
  #27 = Utf8               Lorg/sireum/message/FlatPos$;
  #28 = NameAndType        #14:#27        // MODULE$:Lorg/sireum/message/FlatPos$;
  #29 = Fieldref           #26.#28        // org/sireum/message/FlatPos$.MODULE$:Lorg/sireum/message/FlatPos$;
  #30 = Utf8               org/sireum/None$
  #31 = Class              #30            // org/sireum/None$
  #32 = Utf8               Lorg/sireum/None$;
  #33 = NameAndType        #14:#32        // MODULE$:Lorg/sireum/None$;
  #34 = Fieldref           #31.#33        // org/sireum/None$.MODULE$:Lorg/sireum/None$;
  #35 = Utf8               apply
  #36 = Utf8               ()Lorg/sireum/None;
  #37 = NameAndType        #35:#36        // apply:()Lorg/sireum/None;
  #38 = Methodref          #31.#37        // org/sireum/None$.apply:()Lorg/sireum/None;
  #39 = Utf8               org/sireum/U32$
  #40 = Class              #39            // org/sireum/U32$
  #41 = Utf8               Lorg/sireum/U32$;
  #42 = NameAndType        #14:#41        // MODULE$:Lorg/sireum/U32$;
  #43 = Fieldref           #40.#42        // org/sireum/U32$.MODULE$:Lorg/sireum/U32$;
  #44 = Utf8               scala/StringContext
  #45 = Class              #44            // scala/StringContext
  #46 = Utf8               scala/runtime/ScalaRunTime$
  #47 = Class              #46            // scala/runtime/ScalaRunTime$
  #48 = Utf8               Lscala/runtime/ScalaRunTime$;
  #49 = NameAndType        #14:#48        // MODULE$:Lscala/runtime/ScalaRunTime$;
  #50 = Fieldref           #47.#49        // scala/runtime/ScalaRunTime$.MODULE$:Lscala/runtime/ScalaRunTime$;
  #51 = Utf8               java/lang/String
  #52 = Class              #51            // java/lang/String
  #53 = Utf8               1
  #54 = String             #53            // 1
  #55 = Utf8               [Ljava/lang/Object;
  #56 = Class              #55            // "[Ljava/lang/Object;"
  #57 = Utf8               wrapRefArray
  #58 = Utf8               ([Ljava/lang/Object;)Lscala/collection/immutable/ArraySeq;
  #59 = NameAndType        #57:#58        // wrapRefArray:([Ljava/lang/Object;)Lscala/collection/immutable/ArraySeq;
  #60 = Methodref          #47.#59        // scala/runtime/ScalaRunTime$.wrapRefArray:([Ljava/lang/Object;)Lscala/collection/immutable/ArraySeq;
  #61 = Utf8               (Lscala/collection/immutable/Seq;)V
  #62 = NameAndType        #20:#61        // "<init>":(Lscala/collection/immutable/Seq;)V
  #63 = Methodref          #45.#62        // scala/StringContext."<init>":(Lscala/collection/immutable/Seq;)V
  #64 = Utf8               (Lscala/StringContext;)Lorg/sireum/U32$U32$Slang;
  #65 = NameAndType        #10:#64        // U32$Slang:(Lscala/StringContext;)Lorg/sireum/U32$U32$Slang;
  #66 = Methodref          #40.#65        // org/sireum/U32$.U32$Slang:(Lscala/StringContext;)Lorg/sireum/U32$U32$Slang;
  #67 = Utf8               u32
  #68 = Utf8               ()Lorg/sireum/U32$U32$Slang$u32$;
  #69 = NameAndType        #67:#68        // u32:()Lorg/sireum/U32$U32$Slang$u32$;
  #70 = Methodref          #7.#69         // org/sireum/U32$U32$Slang.u32:()Lorg/sireum/U32$U32$Slang$u32$;
  #71 = Utf8               scala/collection/immutable/Nil$
  #72 = Class              #71            // scala/collection/immutable/Nil$
  #73 = Utf8               Lscala/collection/immutable/Nil$;
  #74 = NameAndType        #14:#73        // MODULE$:Lscala/collection/immutable/Nil$;
  #75 = Fieldref           #72.#74        // scala/collection/immutable/Nil$.MODULE$:Lscala/collection/immutable/Nil$;
  #76 = Utf8               (Lscala/collection/immutable/Seq;)I
  #77 = NameAndType        #35:#76        // apply:(Lscala/collection/immutable/Seq;)I
  #78 = Methodref          #12.#77        // org/sireum/U32$U32$Slang$u32$.apply:(Lscala/collection/immutable/Seq;)I
  #79 = Utf8               0
  #80 = String             #79            // 0
  #81 = Utf8               (Lorg/sireum/Option;IIIIII)Lorg/sireum/message/FlatPos;
  #82 = NameAndType        #35:#81        // apply:(Lorg/sireum/Option;IIIIII)Lorg/sireum/message/FlatPos;
  #83 = Methodref          #26.#82        // org/sireum/message/FlatPos$.apply:(Lorg/sireum/Option;IIIIII)Lorg/sireum/message/FlatPos;
  #84 = NameAndType        #16:#17        // none:Lorg/sireum/message/Position;
  #85 = Fieldref           #2.#84         // org/sireum/message/Position$.none:Lorg/sireum/message/Position;
  #86 = Utf8               ()Lorg/sireum/message/Position;
  #87 = Utf8               this
  #88 = Methodref          #4.#21         // java/lang/Object."<init>":()V
  #89 = Utf8               Code
  #90 = Utf8               LineNumberTable
  #91 = Utf8               LocalVariableTable
  #92 = Utf8               InnerClasses
  #93 = Utf8               SourceFile
  #94 = Utf8               ScalaInlineInfo
  #95 = Utf8               Scala
{
  public static final org.sireum.message.Position$ MODULE$;
    descriptor: Lorg/sireum/message/Position$;
    flags: (0x0019) ACC_PUBLIC, ACC_STATIC, ACC_FINAL

  private static final org.sireum.message.Position none;
    descriptor: Lorg/sireum/message/Position;
    flags: (0x001a) ACC_PRIVATE, ACC_STATIC, ACC_FINAL

  public static {};
    descriptor: ()V
    flags: (0x0009) ACC_PUBLIC, ACC_STATIC
    Code:
      stack=15, locals=0, args_size=0
         0: new           #2                  // class org/sireum/message/Position$
         3: dup
         4: invokespecial #22                 // Method "<init>":()V
         7: putstatic     #24                 // Field MODULE$:Lorg/sireum/message/Position$;
        10: getstatic     #29                 // Field org/sireum/message/FlatPos$.MODULE$:Lorg/sireum/message/FlatPos$;
        13: getstatic     #34                 // Field org/sireum/None$.MODULE$:Lorg/sireum/None$;
        16: invokevirtual #38                 // Method org/sireum/None$.apply:()Lorg/sireum/None;
        19: getstatic     #43                 // Field org/sireum/U32$.MODULE$:Lorg/sireum/U32$;
        22: new           #45                 // class scala/StringContext
        25: dup
        26: getstatic     #50                 // Field scala/runtime/ScalaRunTime$.MODULE$:Lscala/runtime/ScalaRunTime$;
        29: iconst_1
        30: anewarray     #52                 // class java/lang/String
        33: dup
        34: iconst_0
        35: ldc           #54                 // String 1
        37: aastore
        38: checkcast     #56                 // class "[Ljava/lang/Object;"
        41: invokevirtual #60                 // Method scala/runtime/ScalaRunTime$.wrapRefArray:([Ljava/lang/Object;)Lscala/collection/immutable/ArraySeq;
        44: invokespecial #63                 // Method scala/StringContext."<init>":(Lscala/collection/immutable/Seq;)V
        47: invokevirtual #66                 // Method org/sireum/U32$.U32$Slang:(Lscala/StringContext;)Lorg/sireum/U32$U32$Slang;
        50: invokevirtual #70                 // Method org/sireum/U32$U32$Slang.u32:()Lorg/sireum/U32$U32$Slang$u32$;
        53: getstatic     #75                 // Field scala/collection/immutable/Nil$.MODULE$:Lscala/collection/immutable/Nil$;
        56: invokevirtual #78                 // Method org/sireum/U32$U32$Slang$u32$.apply:(Lscala/collection/immutable/Seq;)I
        59: getstatic     #43                 // Field org/sireum/U32$.MODULE$:Lorg/sireum/U32$;
        62: new           #45                 // class scala/StringContext
        65: dup
        66: getstatic     #50                 // Field scala/runtime/ScalaRunTime$.MODULE$:Lscala/runtime/ScalaRunTime$;
        69: iconst_1
        70: anewarray     #52                 // class java/lang/String
        73: dup
        74: iconst_0
        75: ldc           #54                 // String 1
        77: aastore
        78: checkcast     #56                 // class "[Ljava/lang/Object;"
        81: invokevirtual #60                 // Method scala/runtime/ScalaRunTime$.wrapRefArray:([Ljava/lang/Object;)Lscala/collection/immutable/ArraySeq;
        84: invokespecial #63                 // Method scala/StringContext."<init>":(Lscala/collection/immutable/Seq;)V
        87: invokevirtual #66                 // Method org/sireum/U32$.U32$Slang:(Lscala/StringContext;)Lorg/sireum/U32$U32$Slang;
        90: invokevirtual #70                 // Method org/sireum/U32$U32$Slang.u32:()Lorg/sireum/U32$U32$Slang$u32$;
        93: getstatic     #75                 // Field scala/collection/immutable/Nil$.MODULE$:Lscala/collection/immutable/Nil$;
        96: invokevirtual #78                 // Method org/sireum/U32$U32$Slang$u32$.apply:(Lscala/collection/immutable/Seq;)I
        99: getstatic     #43                 // Field org/sireum/U32$.MODULE$:Lorg/sireum/U32$;
       102: new           #45                 // class scala/StringContext
       105: dup
       106: getstatic     #50                 // Field scala/runtime/ScalaRunTime$.MODULE$:Lscala/runtime/ScalaRunTime$;
       109: iconst_1
       110: anewarray     #52                 // class java/lang/String
       113: dup
       114: iconst_0
       115: ldc           #54                 // String 1
       117: aastore
       118: checkcast     #56                 // class "[Ljava/lang/Object;"
       121: invokevirtual #60                 // Method scala/runtime/ScalaRunTime$.wrapRefArray:([Ljava/lang/Object;)Lscala/collection/immutable/ArraySeq;
       124: invokespecial #63                 // Method scala/StringContext."<init>":(Lscala/collection/immutable/Seq;)V
       127: invokevirtual #66                 // Method org/sireum/U32$.U32$Slang:(Lscala/StringContext;)Lorg/sireum/U32$U32$Slang;
       130: invokevirtual #70                 // Method org/sireum/U32$U32$Slang.u32:()Lorg/sireum/U32$U32$Slang$u32$;
       133: getstatic     #75                 // Field scala/collection/immutable/Nil$.MODULE$:Lscala/collection/immutable/Nil$;
       136: invokevirtual #78                 // Method org/sireum/U32$U32$Slang$u32$.apply:(Lscala/collection/immutable/Seq;)I
       139: getstatic     #43                 // Field org/sireum/U32$.MODULE$:Lorg/sireum/U32$;
       142: new           #45                 // class scala/StringContext
       145: dup
       146: getstatic     #50                 // Field scala/runtime/ScalaRunTime$.MODULE$:Lscala/runtime/ScalaRunTime$;
       149: iconst_1
       150: anewarray     #52                 // class java/lang/String
       153: dup
       154: iconst_0
       155: ldc           #54                 // String 1
       157: aastore
       158: checkcast     #56                 // class "[Ljava/lang/Object;"
       161: invokevirtual #60                 // Method scala/runtime/ScalaRunTime$.wrapRefArray:([Ljava/lang/Object;)Lscala/collection/immutable/ArraySeq;
       164: invokespecial #63                 // Method scala/StringContext."<init>":(Lscala/collection/immutable/Seq;)V
       167: invokevirtual #66                 // Method org/sireum/U32$.U32$Slang:(Lscala/StringContext;)Lorg/sireum/U32$U32$Slang;
       170: invokevirtual #70                 // Method org/sireum/U32$U32$Slang.u32:()Lorg/sireum/U32$U32$Slang$u32$;
       173: getstatic     #75                 // Field scala/collection/immutable/Nil$.MODULE$:Lscala/collection/immutable/Nil$;
       176: invokevirtual #78                 // Method org/sireum/U32$U32$Slang$u32$.apply:(Lscala/collection/immutable/Seq;)I
       179: getstatic     #43                 // Field org/sireum/U32$.MODULE$:Lorg/sireum/U32$;
       182: new           #45                 // class scala/StringContext
       185: dup
       186: getstatic     #50                 // Field scala/runtime/ScalaRunTime$.MODULE$:Lscala/runtime/ScalaRunTime$;
       189: iconst_1
       190: anewarray     #52                 // class java/lang/String
       193: dup
       194: iconst_0
       195: ldc           #80                 // String 0
       197: aastore
       198: checkcast     #56                 // class "[Ljava/lang/Object;"
       201: invokevirtual #60                 // Method scala/runtime/ScalaRunTime$.wrapRefArray:([Ljava/lang/Object;)Lscala/collection/immutable/ArraySeq;
       204: invokespecial #63                 // Method scala/StringContext."<init>":(Lscala/collection/immutable/Seq;)V
       207: invokevirtual #66                 // Method org/sireum/U32$.U32$Slang:(Lscala/StringContext;)Lorg/sireum/U32$U32$Slang;
       210: invokevirtual #70                 // Method org/sireum/U32$U32$Slang.u32:()Lorg/sireum/U32$U32$Slang$u32$;
       213: getstatic     #75                 // Field scala/collection/immutable/Nil$.MODULE$:Lscala/collection/immutable/Nil$;
       216: invokevirtual #78                 // Method org/sireum/U32$U32$Slang$u32$.apply:(Lscala/collection/immutable/Seq;)I
       219: getstatic     #43                 // Field org/sireum/U32$.MODULE$:Lorg/sireum/U32$;
       222: new           #45                 // class scala/StringContext
       225: dup
       226: getstatic     #50                 // Field scala/runtime/ScalaRunTime$.MODULE$:Lscala/runtime/ScalaRunTime$;
       229: iconst_1
       230: anewarray     #52                 // class java/lang/String
       233: dup
       234: iconst_0
       235: ldc           #80                 // String 0
       237: aastore
       238: checkcast     #56                 // class "[Ljava/lang/Object;"
       241: invokevirtual #60                 // Method scala/runtime/ScalaRunTime$.wrapRefArray:([Ljava/lang/Object;)Lscala/collection/immutable/ArraySeq;
       244: invokespecial #63                 // Method scala/StringContext."<init>":(Lscala/collection/immutable/Seq;)V
       247: invokevirtual #66                 // Method org/sireum/U32$.U32$Slang:(Lscala/StringContext;)Lorg/sireum/U32$U32$Slang;
       250: invokevirtual #70                 // Method org/sireum/U32$U32$Slang.u32:()Lorg/sireum/U32$U32$Slang$u32$;
       253: getstatic     #75                 // Field scala/collection/immutable/Nil$.MODULE$:Lscala/collection/immutable/Nil$;
       256: invokevirtual #78                 // Method org/sireum/U32$U32$Slang$u32$.apply:(Lscala/collection/immutable/Seq;)I
       259: invokevirtual #83                 // Method org/sireum/message/FlatPos$.apply:(Lorg/sireum/Option;IIIIII)Lorg/sireum/message/FlatPos;
       262: putstatic     #85                 // Field none:Lorg/sireum/message/Position;
       265: return
      LineNumberTable:
        line 67: 0
        line 68: 10
        line 67: 265

  public org.sireum.message.Position none();
    descriptor: ()Lorg/sireum/message/Position;
    flags: (0x0001) ACC_PUBLIC
    Code:
      stack=1, locals=1, args_size=1
         0: getstatic     #85                 // Field none:Lorg/sireum/message/Position;
         3: areturn
      LineNumberTable:
        line 68: 0
      LocalVariableTable:
        Start  Length  Slot  Name   Signature
            0       4     0  this   Lorg/sireum/message/Position$;

  private org.sireum.message.Position$();
    descriptor: ()V
    flags: (0x0002) ACC_PRIVATE
    Code:
      stack=1, locals=1, args_size=1
         0: aload_0
         1: invokespecial #88                 // Method java/lang/Object."<init>":()V
         4: return
      LineNumberTable:
        line 67: 0
      LocalVariableTable:
        Start  Length  Slot  Name   Signature
            0       5     0  this   Lorg/sireum/message/Position$;
}
InnerClasses:
  public static #10= #7 of #9;            // U32$Slang=class org/sireum/U32$U32$Slang of class org/sireum/U32
  public #13= #12 of #7;                  // u32$=class org/sireum/U32$U32$Slang$u32$ of class org/sireum/U32$U32$Slang
SourceFile: "Message.scala"
  ScalaInlineInfo: length = 0xE (unknown attribute)
   01 01 00 02 00 14 00 13 01 00 10 00 56 01
  Scala: length = 0x0 (unknown attribute)

