Classfile /Users/mw/Projects/slang-braindump/.jar/jar11/assemble/slang-braindump/assemble/content/org/sireum/message/Position.class
  Last modified May 29, 2022; size 9192 bytes
  SHA-256 checksum 53c0109a5cc79c5732e405dd8f80ced87d25a33b44ef02550aa722fdfad66ecd
  Compiled from "Message.scala"
public interface org.sireum.message.Position extends org.sireum.DatatypeSig
  minor version: 0
  major version: 52
  flags: (0x0601) ACC_PUBLIC, ACC_INTERFACE, ACC_ABSTRACT
  this_class: #2                          // org/sireum/message/Position
  super_class: #4                         // java/lang/Object
  interfaces: 1, fields: 0, methods: 27, attributes: 5
Constant pool:
    #1 = Utf8               org/sireum/message/Position
    #2 = Class              #1            // org/sireum/message/Position
    #3 = Utf8               java/lang/Object
    #4 = Class              #3            // java/lang/Object
    #5 = Utf8               org/sireum/DatatypeSig
    #6 = Class              #5            // org/sireum/DatatypeSig
    #7 = Utf8               Message.scala
    #8 = Utf8               Lscala/reflect/ScalaSignature;
    #9 = Utf8               bytes
   #10 = Utf8               \u0006\u0005\u0005eq!B\f\u0019\u0011\u0003yb!B\u0011\u0019\u0011\u0003\u0011\u0003\"B\u0015\u0002\t\u0003Q\u0003bB\u0016\u0002\u0005\u0004%\t\u0001\f\u0005\b\u0003/\t\u0001\u0015!\u0003.\r\u001d\t\u0003\u0004%A\u0002\"9BQaM\u0003\u0005\u0002QBQ\u0001O\u0003\u0005BeBq!P\u0003C\u0002\u0013Uc\bC\u0003B\u000b\u0011\u0005#\tC\u0004L\u000b\t\u0007IQ\u000b \t\u000b1+A\u0011I\'\t\u000bY+a\u0011A,\t\u000b\u0005,a\u0011\u00012\t\u000b\u001d,a\u0011\u00012\t\u000b%,a\u0011\u00012\t\u000b-,a\u0011\u00012\t\u000b5,a\u0011\u00012\t\u000b=,a\u0011\u00012\t\u000bE,A\u0011\t2\t\u000bM,A\u0011\u0001;\t\u000bm,A\u0011\t?\t\u000by,A\u0011A@\u0002\u0011A{7/\u001b;j_:T!!\u0007\u000e\u0002\u000f5,7o]1hK*\u00111\u0004H\u0001\u0007g&\u0014X-^7\u000b\u0003u\t1a\u001c:h\u0007\u0001\u0001\"\u0001I\u0001\u000e\u0003a\u0011\u0001\u0002U8tSRLwN\\\n\u0003\u0003\r\u0002\"\u0001J\u0014\u000e\u0003\u0015R\u0011AJ\u0001\u0006g\u000e\fG.Y\u0005\u0003Q\u0015\u0012a!\u00118z%\u00164\u0017A\u0002\u001fj]&$h\bF\u0001 \u0003\u0011qwN\\3\u0016\u00035\u0002\"\u0001I\u0003\u0014\u0007\u0015\u0019s\u0006\u0005\u00021c5\t!$\u0003\u000235\tYA)\u0019;bif\u0004XmU5h\u0003\u0019!\u0013N\\5uIQ\tQ\u0007\u0005\u0002%m%\u0011q\'\n\u0002\u0005+:LG/\u0001\u0005iCND7i\u001c3f)\u0005Q\u0004C\u0001\u0013<\u0013\taTEA\u0002J]R\f!\u0002\n5bg\u0016\u000bX/\u00197t+\u0005yt\"\u0001!\u001a\u0003\u0005\ta!Z9vC2\u001cHCA\"G!\t!C)\u0003\u0002FK\t9!i\\8mK\u0006t\u0007\"B$\n\u0001\u0004A\u0015!A8\u0011\u0005\u0011J\u0015B\u0001&&\u0005\r\te._\u0001\u000bI!\f7o\u0015;sS:<\u0017\u0001\u0003;p\'R\u0014\u0018N\\4\u0015\u00039\u0003\"a\u0014+\u000e\u0003AS!!\u0015*\u0002\t1\fgn\u001a\u0006\u0002\'\u0006!!.\u0019<b\u0013\t)\u0006K\u0001\u0004TiJLgnZ\u0001\u0007kJLw\n\u001d;\u0016\u0003a\u00032\u0001M-\\\u0013\tQ&D\u0001\u0004PaRLwN\u001c\t\u0003aqK!!\u0016\u000e)\u00051q\u0006C\u0001\u0019`\u0013\t\u0001\'D\u0001\u0003qkJ,\u0017!\u00032fO&tG*\u001b8f+\u0005\u0019\u0007C\u0001\u0019e\u0013\t)\'DA\u0001[Q\tia,A\u0006cK\u001eLgnQ8mk6t\u0007F\u0001\b_\u0003\u001d)g\u000e\u001a\'j]\u0016D#a\u00040\u0002\u0013\u0015tGmQ8mk6t\u0007F\u0001\t_\u0003\u0019ygMZ:fi\"\u0012\u0011CX\u0001\u0007Y\u0016tw\r\u001e5)\u0005Iq\u0016\u0001\u00025bg\"D#a\u00050\u0002\u000f%\u001cX)];bYR\u0011Q\u000f\u001f\t\u0003aYL!a\u001e\u000e\u0003\u0003\tCQ!\u001f\u000bA\u00025\nQa\u001c;iKJD#\u0001\u00060\u0002\rM$(/\u001b8h+\u0005Y\u0006FA\u000b_\u0003\t!x\u000eF\u0002.\u0003\u0003AQ!\u001f\fA\u00025B#A\u00060*\u000b\u0015\t9!a\u0003\n\u0007\u0005%\u0001DA\u0004GY\u0006$\bk\\:\n\u0007\u00055\u0001DA\u0004Q_NLeNZ8)\u0007\u0015\t\t\u0002E\u00021\u0003\'I1!!\u0006\u001b\u0005!!\u0017\r^1usB,\u0017!\u00028p]\u0016\u0004\u0003
   #11 = Utf8               org/sireum/U64$U64$Slang
   #12 = Class              #11           // org/sireum/U64$U64$Slang
   #13 = Utf8               org/sireum/U64
   #14 = Class              #13           // org/sireum/U64
   #15 = Utf8               U64$Slang
   #16 = Utf8               org/sireum/U64$U64$Slang$u64$
   #17 = Class              #16           // org/sireum/U64$U64$Slang$u64$
   #18 = Utf8               u64$
   #19 = Utf8               org/sireum/Z$BV$
   #20 = Class              #19           // org/sireum/Z$BV$
   #21 = Utf8               org/sireum/Z
   #22 = Class              #21           // org/sireum/Z
   #23 = Utf8               BV$
   #24 = Utf8               org/sireum/Z$BV$Long
   #25 = Class              #24           // org/sireum/Z$BV$Long
   #26 = Utf8               Long
   #27 = Utf8               none
   #28 = Utf8               ()Lorg/sireum/message/Position;
   #29 = Utf8               org/sireum/message/Position$
   #30 = Class              #29           // org/sireum/message/Position$
   #31 = Utf8               MODULE$
   #32 = Utf8               Lorg/sireum/message/Position$;
   #33 = NameAndType        #31:#32       // MODULE$:Lorg/sireum/message/Position$;
   #34 = Fieldref           #30.#33       // org/sireum/message/Position$.MODULE$:Lorg/sireum/message/Position$;
   #35 = NameAndType        #27:#28       // none:()Lorg/sireum/message/Position;
   #36 = Methodref          #30.#35       // org/sireum/message/Position$.none:()Lorg/sireum/message/Position;
   #37 = Utf8               hashCode$
   #38 = Utf8               (Lorg/sireum/message/Position;)I
   #39 = Utf8               $this
   #40 = Utf8               hashCode
   #41 = Utf8               ()I
   #42 = NameAndType        #40:#41       // hashCode:()I
   #43 = InterfaceMethodref #2.#42        // org/sireum/message/Position.hashCode:()I
   #44 = Utf8               Lorg/sireum/message/Position;
   #45 = Utf8               hash
   #46 = Utf8               ()Lorg/sireum/Z;
   #47 = NameAndType        #45:#46       // hash:()Lorg/sireum/Z;
   #48 = InterfaceMethodref #2.#47        // org/sireum/message/Position.hash:()Lorg/sireum/Z;
   #49 = Methodref          #4.#42        // java/lang/Object.hashCode:()I
   #50 = Utf8               this
   #51 = Utf8               $hasEquals$
   #52 = Utf8               (Lorg/sireum/message/Position;)Z
   #53 = Utf8               $hasEquals
   #54 = Utf8               ()Z
   #55 = NameAndType        #53:#54       // $hasEquals:()Z
   #56 = InterfaceMethodref #2.#55        // org/sireum/message/Position.$hasEquals:()Z
   #57 = Utf8               equals$
   #58 = Utf8               (Lorg/sireum/message/Position;Ljava/lang/Object;)Z
   #59 = Utf8               o
   #60 = Utf8               equals
   #61 = Utf8               (Ljava/lang/Object;)Z
   #62 = NameAndType        #60:#61       // equals:(Ljava/lang/Object;)Z
   #63 = InterfaceMethodref #2.#62        // org/sireum/message/Position.equals:(Ljava/lang/Object;)Z
   #64 = Utf8               Ljava/lang/Object;
   #65 = Utf8               org/sireum/B$
   #66 = Class              #65           // org/sireum/B$
   #67 = Utf8               Lorg/sireum/B$;
   #68 = NameAndType        #31:#67       // MODULE$:Lorg/sireum/B$;
   #69 = Fieldref           #66.#68       // org/sireum/B$.MODULE$:Lorg/sireum/B$;
   #70 = Utf8               isEqual
   #71 = NameAndType        #70:#52       // isEqual:(Lorg/sireum/message/Position;)Z
   #72 = InterfaceMethodref #2.#71        // org/sireum/message/Position.isEqual:(Lorg/sireum/message/Position;)Z
   #73 = Utf8               $4B
   #74 = Utf8               (Z)Z
   #75 = NameAndType        #73:#74       // $4B:(Z)Z
   #76 = Methodref          #66.#75       // org/sireum/B$.$4B:(Z)Z
   #77 = Utf8               $hasString$
   #78 = Utf8               $hasString
   #79 = NameAndType        #78:#54       // $hasString:()Z
   #80 = InterfaceMethodref #2.#79        // org/sireum/message/Position.$hasString:()Z
   #81 = Utf8               toString$
   #82 = Utf8               (Lorg/sireum/message/Position;)Ljava/lang/String;
   #83 = Utf8               toString
   #84 = Utf8               ()Ljava/lang/String;
   #85 = NameAndType        #83:#84       // toString:()Ljava/lang/String;
   #86 = InterfaceMethodref #2.#85        // org/sireum/message/Position.toString:()Ljava/lang/String;
   #87 = Utf8               string
   #88 = NameAndType        #87:#84       // string:()Ljava/lang/String;
   #89 = InterfaceMethodref #2.#88        // org/sireum/message/Position.string:()Ljava/lang/String;
   #90 = Utf8               uriOpt
   #91 = Utf8               ()Lorg/sireum/Option;
   #92 = Utf8               ()Lorg/sireum/Option<Lorg/sireum/String;>;
   #93 = Utf8               beginLine
   #94 = Utf8               beginColumn
   #95 = Utf8               endLine
   #96 = Utf8               endColumn
   #97 = Utf8               offset
   #98 = Utf8               length
   #99 = Utf8               hash$
  #100 = Utf8               (Lorg/sireum/message/Position;)Lorg/sireum/Z;
  #101 = Utf8               org/sireum/Z$
  #102 = Class              #101          // org/sireum/Z$
  #103 = Utf8               Lorg/sireum/Z$;
  #104 = NameAndType        #31:#103      // MODULE$:Lorg/sireum/Z$;
  #105 = Fieldref           #102.#104     // org/sireum/Z$.MODULE$:Lorg/sireum/Z$;
  #106 = Utf8               scala/Tuple6
  #107 = Class              #106          // scala/Tuple6
  #108 = NameAndType        #90:#91       // uriOpt:()Lorg/sireum/Option;
  #109 = InterfaceMethodref #2.#108       // org/sireum/message/Position.uriOpt:()Lorg/sireum/Option;
  #110 = NameAndType        #93:#46       // beginLine:()Lorg/sireum/Z;
  #111 = InterfaceMethodref #2.#110       // org/sireum/message/Position.beginLine:()Lorg/sireum/Z;
  #112 = NameAndType        #95:#46       // endLine:()Lorg/sireum/Z;
  #113 = InterfaceMethodref #2.#112       // org/sireum/message/Position.endLine:()Lorg/sireum/Z;
  #114 = NameAndType        #96:#46       // endColumn:()Lorg/sireum/Z;
  #115 = InterfaceMethodref #2.#114       // org/sireum/message/Position.endColumn:()Lorg/sireum/Z;
  #116 = NameAndType        #97:#46       // offset:()Lorg/sireum/Z;
  #117 = InterfaceMethodref #2.#116       // org/sireum/message/Position.offset:()Lorg/sireum/Z;
  #118 = NameAndType        #98:#46       // length:()Lorg/sireum/Z;
  #119 = InterfaceMethodref #2.#118       // org/sireum/message/Position.length:()Lorg/sireum/Z;
  #120 = Utf8               <init>
  #121 = Utf8               (Ljava/lang/Object;Ljava/lang/Object;Ljava/lang/Object;Ljava/lang/Object;Ljava/lang/Object;Ljava/lang/Object;)V
  #122 = NameAndType        #120:#121     // "<init>":(Ljava/lang/Object;Ljava/lang/Object;Ljava/lang/Object;Ljava/lang/Object;Ljava/lang/Object;Ljava/lang/Object;)V
  #123 = Methodref          #107.#122     // scala/Tuple6."<init>":(Ljava/lang/Object;Ljava/lang/Object;Ljava/lang/Object;Ljava/lang/Object;Ljava/lang/Object;Ljava/lang/Object;)V
  #124 = Methodref          #107.#42      // scala/Tuple6.hashCode:()I
  #125 = Utf8               apply
  #126 = Utf8               (I)Lorg/sireum/Z;
  #127 = NameAndType        #125:#126     // apply:(I)Lorg/sireum/Z;
  #128 = Methodref          #102.#127     // org/sireum/Z$.apply:(I)Lorg/sireum/Z;
  #129 = Utf8               isEqual$
  #130 = Utf8               (Lorg/sireum/message/Position;Lorg/sireum/message/Position;)Z
  #131 = Utf8               other
  #132 = Methodref          #4.#62        // java/lang/Object.equals:(Ljava/lang/Object;)Z
  #133 = NameAndType        #94:#46       // beginColumn:()Lorg/sireum/Z;
  #134 = InterfaceMethodref #2.#133       // org/sireum/message/Position.beginColumn:()Lorg/sireum/Z;
  #135 = NameAndType        #125:#74      // apply:(Z)Z
  #136 = Methodref          #66.#135      // org/sireum/B$.apply:(Z)Z
  #137 = Utf8               org/sireum/Option
  #138 = Class              #137          // org/sireum/Option
  #139 = Utf8               string$
  #140 = Utf8               org/sireum/Some
  #141 = Class              #140          // org/sireum/Some
  #142 = Utf8               org/sireum/Some$
  #143 = Class              #142          // org/sireum/Some$
  #144 = Utf8               Lorg/sireum/Some$;
  #145 = NameAndType        #31:#144      // MODULE$:Lorg/sireum/Some$;
  #146 = Fieldref           #143.#145     // org/sireum/Some$.MODULE$:Lorg/sireum/Some$;
  #147 = Utf8               unapply
  #148 = Utf8               (Lorg/sireum/Some;)Lscala/Some;
  #149 = NameAndType        #147:#148     // unapply:(Lorg/sireum/Some;)Lscala/Some;
  #150 = Methodref          #143.#149     // org/sireum/Some$.unapply:(Lorg/sireum/Some;)Lscala/Some;
  #151 = Utf8               scala/Some
  #152 = Class              #151          // scala/Some
  #153 = Utf8               isEmpty
  #154 = NameAndType        #153:#54      // isEmpty:()Z
  #155 = Methodref          #152.#154     // scala/Some.isEmpty:()Z
  #156 = Utf8               get
  #157 = Utf8               ()Ljava/lang/Object;
  #158 = NameAndType        #156:#157     // get:()Ljava/lang/Object;
  #159 = Methodref          #152.#158     // scala/Some.get:()Ljava/lang/Object;
  #160 = Utf8               org/sireum/String
  #161 = Class              #160          // org/sireum/String
  #162 = Utf8               value
  #163 = NameAndType        #162:#84      // value:()Ljava/lang/String;
  #164 = Methodref          #161.#163     // org/sireum/String.value:()Ljava/lang/String;
  #165 = Utf8               org/sireum/ops/StringOps$
  #166 = Class              #165          // org/sireum/ops/StringOps$
  #167 = Utf8               Lorg/sireum/ops/StringOps$;
  #168 = NameAndType        #31:#167      // MODULE$:Lorg/sireum/ops/StringOps$;
  #169 = Fieldref           #166.#168     // org/sireum/ops/StringOps$.MODULE$:Lorg/sireum/ops/StringOps$;
  #170 = Utf8               (Ljava/lang/String;)Lorg/sireum/ops/StringOps;
  #171 = NameAndType        #125:#170     // apply:(Ljava/lang/String;)Lorg/sireum/ops/StringOps;
  #172 = Methodref          #166.#171     // org/sireum/ops/StringOps$.apply:(Ljava/lang/String;)Lorg/sireum/ops/StringOps;
  #173 = Utf8               org/sireum/C$
  #174 = Class              #173          // org/sireum/C$
  #175 = Utf8               Lorg/sireum/C$;
  #176 = NameAndType        #31:#175      // MODULE$:Lorg/sireum/C$;
  #177 = Fieldref           #174.#176     // org/sireum/C$.MODULE$:Lorg/sireum/C$;
  #178 = Utf8               (C)I
  #179 = NameAndType        #125:#178     // apply:(C)I
  #180 = Methodref          #174.#179     // org/sireum/C$.apply:(C)I
  #181 = Utf8               org/sireum/ops/StringOps
  #182 = Class              #181          // org/sireum/ops/StringOps
  #183 = Utf8               lastIndexOf
  #184 = NameAndType        #183:#126     // lastIndexOf:(I)Lorg/sireum/Z;
  #185 = Methodref          #182.#184     // org/sireum/ops/StringOps.lastIndexOf:(I)Lorg/sireum/Z;
  #186 = Utf8               $less
  #187 = Utf8               (Lorg/sireum/Z;)Z
  #188 = NameAndType        #186:#187     // $less:(Lorg/sireum/Z;)Z
  #189 = InterfaceMethodref #22.#188      // org/sireum/Z.$less:(Lorg/sireum/Z;)Z
  #190 = Utf8               org/sireum/String$
  #191 = Class              #190          // org/sireum/String$
  #192 = Utf8               Lorg/sireum/String$;
  #193 = NameAndType        #31:#192      // MODULE$:Lorg/sireum/String$;
  #194 = Fieldref           #191.#193     // org/sireum/String$.MODULE$:Lorg/sireum/String$;
  #195 = Utf8               java/lang/StringBuilder
  #196 = Class              #195          // java/lang/StringBuilder
  #197 = Integer            6
  #198 = Utf8               (I)V
  #199 = NameAndType        #120:#198     // "<init>":(I)V
  #200 = Methodref          #196.#199     // java/lang/StringBuilder."<init>":(I)V
  #201 = Utf8               [
  #202 = String             #201          // [
  #203 = Utf8               append
  #204 = Utf8               (Ljava/lang/String;)Ljava/lang/StringBuilder;
  #205 = NameAndType        #203:#204     // append:(Ljava/lang/String;)Ljava/lang/StringBuilder;
  #206 = Methodref          #196.#205     // java/lang/StringBuilder.append:(Ljava/lang/String;)Ljava/lang/StringBuilder;
  #207 = Utf8               size$extension
  #208 = Utf8               (Ljava/lang/String;)Lorg/sireum/Z;
  #209 = NameAndType        #207:#208     // size$extension:(Ljava/lang/String;)Lorg/sireum/Z;
  #210 = Methodref          #191.#209     // org/sireum/String$.size$extension:(Ljava/lang/String;)Lorg/sireum/Z;
  #211 = Utf8               substring
  #212 = Utf8               (Lorg/sireum/Z;Lorg/sireum/Z;)Ljava/lang/String;
  #213 = NameAndType        #211:#212     // substring:(Lorg/sireum/Z;Lorg/sireum/Z;)Ljava/lang/String;
  #214 = Methodref          #182.#213     // org/sireum/ops/StringOps.substring:(Lorg/sireum/Z;Lorg/sireum/Z;)Ljava/lang/String;
  #215 = Utf8               (Ljava/lang/String;)V
  #216 = NameAndType        #120:#215     // "<init>":(Ljava/lang/String;)V
  #217 = Methodref          #161.#216     // org/sireum/String."<init>":(Ljava/lang/String;)V
  #218 = Utf8               (Ljava/lang/Object;)Ljava/lang/StringBuilder;
  #219 = NameAndType        #203:#218     // append:(Ljava/lang/Object;)Ljava/lang/StringBuilder;
  #220 = Methodref          #196.#219     // java/lang/StringBuilder.append:(Ljava/lang/Object;)Ljava/lang/StringBuilder;
  #221 = Utf8               ,
  #222 = String             #221          // ,
  #223 = Utf8               ]
  #224 = String             #223          // ]
  #225 = Methodref          #196.#85      // java/lang/StringBuilder.toString:()Ljava/lang/String;
  #226 = Utf8               (Ljava/lang/String;)Ljava/lang/String;
  #227 = NameAndType        #125:#226     // apply:(Ljava/lang/String;)Ljava/lang/String;
  #228 = Methodref          #191.#227     // org/sireum/String$.apply:(Ljava/lang/String;)Ljava/lang/String;
  #229 = Integer            4
  #230 = Utf8               i
  #231 = Utf8               Lorg/sireum/Z;
  #232 = Utf8               fileUri
  #233 = Utf8               Ljava/lang/String;
  #234 = Utf8               java/lang/String
  #235 = Class              #234          // java/lang/String
  #236 = Utf8               to$
  #237 = Utf8               (Lorg/sireum/message/Position;Lorg/sireum/message/Position;)Lorg/sireum/message/Position;
  #238 = Utf8               to
  #239 = Utf8               (Lorg/sireum/message/Position;)Lorg/sireum/message/Position;
  #240 = NameAndType        #238:#239     // to:(Lorg/sireum/message/Position;)Lorg/sireum/message/Position;
  #241 = InterfaceMethodref #2.#240       // org/sireum/message/Position.to:(Lorg/sireum/message/Position;)Lorg/sireum/message/Position;
  #242 = Utf8               org/sireum/None$
  #243 = Class              #242          // org/sireum/None$
  #244 = Utf8               Lorg/sireum/None$;
  #245 = NameAndType        #31:#244      // MODULE$:Lorg/sireum/None$;
  #246 = Fieldref           #243.#245     // org/sireum/None$.MODULE$:Lorg/sireum/None$;
  #247 = Utf8               ()Lorg/sireum/None;
  #248 = NameAndType        #125:#247     // apply:()Lorg/sireum/None;
  #249 = Methodref          #243.#248     // org/sireum/None$.apply:()Lorg/sireum/None;
  #250 = Utf8               org/sireum/message/PosInfo
  #251 = Class              #250          // org/sireum/message/PosInfo
  #252 = Utf8               info
  #253 = Utf8               ()Lorg/sireum/message/DocInfo;
  #254 = NameAndType        #252:#253     // info:()Lorg/sireum/message/DocInfo;
  #255 = Methodref          #251.#254     // org/sireum/message/PosInfo.info:()Lorg/sireum/message/DocInfo;
  #256 = Utf8               (Ljava/lang/Object;)Lorg/sireum/Some;
  #257 = NameAndType        #125:#256     // apply:(Ljava/lang/Object;)Lorg/sireum/Some;
  #258 = Methodref          #143.#257     // org/sireum/Some$.apply:(Ljava/lang/Object;)Lorg/sireum/Some;
  #259 = Utf8               scala/runtime/BoxedUnit
  #260 = Class              #259          // scala/runtime/BoxedUnit
  #261 = Utf8               UNIT
  #262 = Utf8               Lscala/runtime/BoxedUnit;
  #263 = NameAndType        #261:#262     // UNIT:Lscala/runtime/BoxedUnit;
  #264 = Fieldref           #260.#263     // scala/runtime/BoxedUnit.UNIT:Lscala/runtime/BoxedUnit;
  #265 = Utf8               org/sireum/message/DocInfo
  #266 = Class              #265          // org/sireum/message/DocInfo
  #267 = Utf8               org/sireum/message/PosInfo$
  #268 = Class              #267          // org/sireum/message/PosInfo$
  #269 = Utf8               Lorg/sireum/message/PosInfo$;
  #270 = NameAndType        #31:#269      // MODULE$:Lorg/sireum/message/PosInfo$;
  #271 = Fieldref           #268.#270     // org/sireum/message/PosInfo$.MODULE$:Lorg/sireum/message/PosInfo$;
  #272 = Utf8               org/sireum/conversions/Z$
  #273 = Class              #272          // org/sireum/conversions/Z$
  #274 = Utf8               Lorg/sireum/conversions/Z$;
  #275 = NameAndType        #31:#274      // MODULE$:Lorg/sireum/conversions/Z$;
  #276 = Fieldref           #273.#275     // org/sireum/conversions/Z$.MODULE$:Lorg/sireum/conversions/Z$;
  #277 = Utf8               toU64
  #278 = Utf8               (Lorg/sireum/Z;)J
  #279 = NameAndType        #277:#278     // toU64:(Lorg/sireum/Z;)J
  #280 = Methodref          #273.#279     // org/sireum/conversions/Z$.toU64:(Lorg/sireum/Z;)J
  #281 = Utf8               (J)V
  #282 = NameAndType        #120:#281     // "<init>":(J)V
  #283 = Methodref          #14.#282      // org/sireum/U64."<init>":(J)V
  #284 = Utf8               org/sireum/U64$
  #285 = Class              #284          // org/sireum/U64$
  #286 = Utf8               Lorg/sireum/U64$;
  #287 = NameAndType        #31:#286      // MODULE$:Lorg/sireum/U64$;
  #288 = Fieldref           #285.#287     // org/sireum/U64$.MODULE$:Lorg/sireum/U64$;
  #289 = Utf8               scala/StringContext
  #290 = Class              #289          // scala/StringContext
  #291 = Utf8               scala/runtime/ScalaRunTime$
  #292 = Class              #291          // scala/runtime/ScalaRunTime$
  #293 = Utf8               Lscala/runtime/ScalaRunTime$;
  #294 = NameAndType        #31:#293      // MODULE$:Lscala/runtime/ScalaRunTime$;
  #295 = Fieldref           #292.#294     // scala/runtime/ScalaRunTime$.MODULE$:Lscala/runtime/ScalaRunTime$;
  #296 = Utf8               32
  #297 = String             #296          // 32
  #298 = Utf8               [Ljava/lang/Object;
  #299 = Class              #298          // "[Ljava/lang/Object;"
  #300 = Utf8               wrapRefArray
  #301 = Utf8               ([Ljava/lang/Object;)Lscala/collection/immutable/ArraySeq;
  #302 = NameAndType        #300:#301     // wrapRefArray:([Ljava/lang/Object;)Lscala/collection/immutable/ArraySeq;
  #303 = Methodref          #292.#302     // scala/runtime/ScalaRunTime$.wrapRefArray:([Ljava/lang/Object;)Lscala/collection/immutable/ArraySeq;
  #304 = Utf8               (Lscala/collection/immutable/Seq;)V
  #305 = NameAndType        #120:#304     // "<init>":(Lscala/collection/immutable/Seq;)V
  #306 = Methodref          #290.#305     // scala/StringContext."<init>":(Lscala/collection/immutable/Seq;)V
  #307 = Utf8               (Lscala/StringContext;)Lorg/sireum/U64$U64$Slang;
  #308 = NameAndType        #15:#307      // U64$Slang:(Lscala/StringContext;)Lorg/sireum/U64$U64$Slang;
  #309 = Methodref          #285.#308     // org/sireum/U64$.U64$Slang:(Lscala/StringContext;)Lorg/sireum/U64$U64$Slang;
  #310 = Utf8               u64
  #311 = Utf8               ()Lorg/sireum/U64$U64$Slang$u64$;
  #312 = NameAndType        #310:#311     // u64:()Lorg/sireum/U64$U64$Slang$u64$;
  #313 = Methodref          #12.#312      // org/sireum/U64$U64$Slang.u64:()Lorg/sireum/U64$U64$Slang$u64$;
  #314 = Utf8               scala/collection/immutable/Nil$
  #315 = Class              #314          // scala/collection/immutable/Nil$
  #316 = Utf8               Lscala/collection/immutable/Nil$;
  #317 = NameAndType        #31:#316      // MODULE$:Lscala/collection/immutable/Nil$;
  #318 = Fieldref           #315.#317     // scala/collection/immutable/Nil$.MODULE$:Lscala/collection/immutable/Nil$;
  #319 = Utf8               (Lscala/collection/immutable/Seq;)J
  #320 = NameAndType        #125:#319     // apply:(Lscala/collection/immutable/Seq;)J
  #321 = Methodref          #17.#320      // org/sireum/U64$U64$Slang$u64$.apply:(Lscala/collection/immutable/Seq;)J
  #322 = Utf8               $less$less
  #323 = Utf8               (Lorg/sireum/Z$BV$Long;)Lorg/sireum/Z$BV$Long;
  #324 = NameAndType        #322:#323     // $less$less:(Lorg/sireum/Z$BV$Long;)Lorg/sireum/Z$BV$Long;
  #325 = Methodref          #14.#324      // org/sireum/U64.$less$less:(Lorg/sireum/Z$BV$Long;)Lorg/sireum/Z$BV$Long;
  #326 = Utf8               $plus
  #327 = Utf8               (Lorg/sireum/Z;)Lorg/sireum/Z;
  #328 = NameAndType        #326:#327     // $plus:(Lorg/sireum/Z;)Lorg/sireum/Z;
  #329 = InterfaceMethodref #22.#328      // org/sireum/Z.$plus:(Lorg/sireum/Z;)Lorg/sireum/Z;
  #330 = Utf8               $minus
  #331 = NameAndType        #330:#327     // $minus:(Lorg/sireum/Z;)Lorg/sireum/Z;
  #332 = InterfaceMethodref #22.#331      // org/sireum/Z.$minus:(Lorg/sireum/Z;)Lorg/sireum/Z;
  #333 = Utf8               $bar
  #334 = NameAndType        #333:#323     // $bar:(Lorg/sireum/Z$BV$Long;)Lorg/sireum/Z$BV$Long;
  #335 = InterfaceMethodref #25.#334      // org/sireum/Z$BV$Long.$bar:(Lorg/sireum/Z$BV$Long;)Lorg/sireum/Z$BV$Long;
  #336 = Utf8               ()J
  #337 = NameAndType        #162:#336     // value:()J
  #338 = Methodref          #14.#337      // org/sireum/U64.value:()J
  #339 = Utf8               (Lorg/sireum/message/DocInfo;J)Lorg/sireum/message/PosInfo;
  #340 = NameAndType        #125:#339     // apply:(Lorg/sireum/message/DocInfo;J)Lorg/sireum/message/PosInfo;
  #341 = Methodref          #268.#340     // org/sireum/message/PosInfo$.apply:(Lorg/sireum/message/DocInfo;J)Lorg/sireum/message/PosInfo;
  #342 = Utf8               org/sireum/message/FlatPos$
  #343 = Class              #342          // org/sireum/message/FlatPos$
  #344 = Utf8               Lorg/sireum/message/FlatPos$;
  #345 = NameAndType        #31:#344      // MODULE$:Lorg/sireum/message/FlatPos$;
  #346 = Fieldref           #343.#345     // org/sireum/message/FlatPos$.MODULE$:Lorg/sireum/message/FlatPos$;
  #347 = Utf8               toU32
  #348 = Utf8               (Lorg/sireum/Z;)I
  #349 = NameAndType        #347:#348     // toU32:(Lorg/sireum/Z;)I
  #350 = Methodref          #273.#349     // org/sireum/conversions/Z$.toU32:(Lorg/sireum/Z;)I
  #351 = Utf8               (Lorg/sireum/Option;IIIIII)Lorg/sireum/message/FlatPos;
  #352 = NameAndType        #125:#351     // apply:(Lorg/sireum/Option;IIIIII)Lorg/sireum/message/FlatPos;
  #353 = Methodref          #343.#352     // org/sireum/message/FlatPos$.apply:(Lorg/sireum/Option;IIIIII)Lorg/sireum/message/FlatPos;
  #354 = Utf8               Lorg/sireum/message/DocInfo;
  #355 = Utf8               pos1
  #356 = Utf8               pos2
  #357 = Utf8               docInfoOpt
  #358 = Utf8               Lorg/sireum/Option;
  #359 = Utf8               org/sireum/None
  #360 = Class              #359          // org/sireum/None
  #361 = Utf8               $init$
  #362 = Utf8               (Lorg/sireum/message/Position;)V
  #363 = Utf8               Code
  #364 = Utf8               LineNumberTable
  #365 = Utf8               LocalVariableTable
  #366 = Utf8               MethodParameters
  #367 = Utf8               StackMapTable
  #368 = Utf8               Signature
  #369 = Utf8               InnerClasses
  #370 = Utf8               SourceFile
  #371 = Utf8               RuntimeVisibleAnnotations
  #372 = Utf8               ScalaInlineInfo
  #373 = Utf8               ScalaSig
{
  public static org.sireum.message.Position none();
    descriptor: ()Lorg/sireum/message/Position;
    flags: (0x0009) ACC_PUBLIC, ACC_STATIC
    Code:
      stack=1, locals=0, args_size=0
         0: getstatic     #34                 // Field org/sireum/message/Position$.MODULE$:Lorg/sireum/message/Position$;
         3: invokevirtual #36                 // Method org/sireum/message/Position$.none:()Lorg/sireum/message/Position;
         6: areturn

  public static int hashCode$(org.sireum.message.Position);
    descriptor: (Lorg/sireum/message/Position;)I
    flags: (0x1009) ACC_PUBLIC, ACC_STATIC, ACC_SYNTHETIC
    Code:
      stack=1, locals=1, args_size=1
         0: aload_0
         1: invokespecial #43                 // InterfaceMethod hashCode:()I
         4: ireturn
      LineNumberTable:
        line 71: 0
      LocalVariableTable:
        Start  Length  Slot  Name   Signature
            0       5     0 $this   Lorg/sireum/message/Position;
    MethodParameters:
      Name                           Flags
      $this                          final synthetic

  public default int hashCode();
    descriptor: ()I
    flags: (0x0001) ACC_PUBLIC
    Code:
      stack=1, locals=1, args_size=1
         0: aload_0
         1: invokeinterface #48,  1           // InterfaceMethod hash:()Lorg/sireum/Z;
         6: invokevirtual #49                 // Method java/lang/Object.hashCode:()I
         9: ireturn
      LineNumberTable:
        line 71: 0
      LocalVariableTable:
        Start  Length  Slot  Name   Signature
            0      10     0  this   Lorg/sireum/message/Position;

  public static boolean $hasEquals$(org.sireum.message.Position);
    descriptor: (Lorg/sireum/message/Position;)Z
    flags: (0x1009) ACC_PUBLIC, ACC_STATIC, ACC_SYNTHETIC
    Code:
      stack=1, locals=1, args_size=1
         0: aload_0
         1: invokespecial #56                 // InterfaceMethod $hasEquals:()Z
         4: ireturn
      LineNumberTable:
        line 71: 0
      LocalVariableTable:
        Start  Length  Slot  Name   Signature
            0       5     0 $this   Lorg/sireum/message/Position;
    MethodParameters:
      Name                           Flags
      $this                          final synthetic

  public default boolean $hasEquals();
    descriptor: ()Z
    flags: (0x0001) ACC_PUBLIC
    Code:
      stack=1, locals=1, args_size=1
         0: iconst_1
         1: ireturn
      LineNumberTable:
        line 71: 0
      LocalVariableTable:
        Start  Length  Slot  Name   Signature
            0       2     0  this   Lorg/sireum/message/Position;

  public static boolean equals$(org.sireum.message.Position, java.lang.Object);
    descriptor: (Lorg/sireum/message/Position;Ljava/lang/Object;)Z
    flags: (0x1009) ACC_PUBLIC, ACC_STATIC, ACC_SYNTHETIC
    Code:
      stack=2, locals=2, args_size=2
         0: aload_0
         1: aload_1
         2: invokespecial #63                 // InterfaceMethod equals:(Ljava/lang/Object;)Z
         5: ireturn
      LineNumberTable:
        line 71: 0
      LocalVariableTable:
        Start  Length  Slot  Name   Signature
            0       6     0 $this   Lorg/sireum/message/Position;
            0       6     1     o   Ljava/lang/Object;
    MethodParameters:
      Name                           Flags
      $this                          final synthetic
      o                              final

  public default boolean equals(java.lang.Object);
    descriptor: (Ljava/lang/Object;)Z
    flags: (0x0001) ACC_PUBLIC
    Code:
      stack=3, locals=5, args_size=2
         0: aload_1
         1: astore_3
         2: aload_3
         3: instanceof    #2                  // class org/sireum/message/Position
         6: ifeq          33
         9: aload_3
        10: checkcast     #2                  // class org/sireum/message/Position
        13: astore        4
        15: getstatic     #69                 // Field org/sireum/B$.MODULE$:Lorg/sireum/B$;
        18: aload_0
        19: aload         4
        21: invokeinterface #72,  2           // InterfaceMethod isEqual:(Lorg/sireum/message/Position;)Z
        26: invokevirtual #76                 // Method org/sireum/B$.$4B:(Z)Z
        29: istore_2
        30: goto          38
        33: goto          36
        36: iconst_0
        37: ireturn
        38: iload_2
        39: ireturn
      StackMapTable: number_of_entries = 3
        frame_type = 253 /* append */
          offset_delta = 33
          locals = [ top, class java/lang/Object ]
        frame_type = 2 /* same */
        frame_type = 255 /* full_frame */
          offset_delta = 1
          locals = [ class org/sireum/message/Position, class java/lang/Object, int, class java/lang/Object, class org/sireum/message/Position ]
          stack = []
      LineNumberTable:
        line 71: 0
      LocalVariableTable:
        Start  Length  Slot  Name   Signature
            0      40     0  this   Lorg/sireum/message/Position;
            0      40     1     o   Ljava/lang/Object;
    MethodParameters:
      Name                           Flags
      o                              final

  public static boolean $hasString$(org.sireum.message.Position);
    descriptor: (Lorg/sireum/message/Position;)Z
    flags: (0x1009) ACC_PUBLIC, ACC_STATIC, ACC_SYNTHETIC
    Code:
      stack=1, locals=1, args_size=1
         0: aload_0
         1: invokespecial #80                 // InterfaceMethod $hasString:()Z
         4: ireturn
      LineNumberTable:
        line 71: 0
      LocalVariableTable:
        Start  Length  Slot  Name   Signature
            0       5     0 $this   Lorg/sireum/message/Position;
    MethodParameters:
      Name                           Flags
      $this                          final synthetic

  public default boolean $hasString();
    descriptor: ()Z
    flags: (0x0001) ACC_PUBLIC
    Code:
      stack=1, locals=1, args_size=1
         0: iconst_1
         1: ireturn
      LineNumberTable:
        line 71: 0
      LocalVariableTable:
        Start  Length  Slot  Name   Signature
            0       2     0  this   Lorg/sireum/message/Position;

  public static java.lang.String toString$(org.sireum.message.Position);
    descriptor: (Lorg/sireum/message/Position;)Ljava/lang/String;
    flags: (0x1009) ACC_PUBLIC, ACC_STATIC, ACC_SYNTHETIC
    Code:
      stack=1, locals=1, args_size=1
         0: aload_0
         1: invokespecial #86                 // InterfaceMethod toString:()Ljava/lang/String;
         4: areturn
      LineNumberTable:
        line 71: 0
      LocalVariableTable:
        Start  Length  Slot  Name   Signature
            0       5     0 $this   Lorg/sireum/message/Position;
    MethodParameters:
      Name                           Flags
      $this                          final synthetic

  public default java.lang.String toString();
    descriptor: ()Ljava/lang/String;
    flags: (0x0001) ACC_PUBLIC
    Code:
      stack=1, locals=1, args_size=1
         0: aload_0
         1: invokeinterface #89,  1           // InterfaceMethod string:()Ljava/lang/String;
         6: areturn
      LineNumberTable:
        line 71: 0
      LocalVariableTable:
        Start  Length  Slot  Name   Signature
            0       7     0  this   Lorg/sireum/message/Position;

  public abstract org.sireum.Option<org.sireum.String> uriOpt();
    descriptor: ()Lorg/sireum/Option;
    flags: (0x0401) ACC_PUBLIC, ACC_ABSTRACT
    Signature: #92                          // ()Lorg/sireum/Option<Lorg/sireum/String;>;

  public abstract org.sireum.Z beginLine();
    descriptor: ()Lorg/sireum/Z;
    flags: (0x0401) ACC_PUBLIC, ACC_ABSTRACT

  public abstract org.sireum.Z beginColumn();
    descriptor: ()Lorg/sireum/Z;
    flags: (0x0401) ACC_PUBLIC, ACC_ABSTRACT

  public abstract org.sireum.Z endLine();
    descriptor: ()Lorg/sireum/Z;
    flags: (0x0401) ACC_PUBLIC, ACC_ABSTRACT

  public abstract org.sireum.Z endColumn();
    descriptor: ()Lorg/sireum/Z;
    flags: (0x0401) ACC_PUBLIC, ACC_ABSTRACT

  public abstract org.sireum.Z offset();
    descriptor: ()Lorg/sireum/Z;
    flags: (0x0401) ACC_PUBLIC, ACC_ABSTRACT

  public abstract org.sireum.Z length();
    descriptor: ()Lorg/sireum/Z;
    flags: (0x0401) ACC_PUBLIC, ACC_ABSTRACT

  public static org.sireum.Z hash$(org.sireum.message.Position);
    descriptor: (Lorg/sireum/message/Position;)Lorg/sireum/Z;
    flags: (0x1009) ACC_PUBLIC, ACC_STATIC, ACC_SYNTHETIC
    Code:
      stack=1, locals=1, args_size=1
         0: aload_0
         1: invokespecial #48                 // InterfaceMethod hash:()Lorg/sireum/Z;
         4: areturn
      LineNumberTable:
        line 94: 0
      LocalVariableTable:
        Start  Length  Slot  Name   Signature
            0       5     0 $this   Lorg/sireum/message/Position;
    MethodParameters:
      Name                           Flags
      $this                          final synthetic

  public default org.sireum.Z hash();
    descriptor: ()Lorg/sireum/Z;
    flags: (0x0001) ACC_PUBLIC
    Code:
      stack=9, locals=1, args_size=1
         0: getstatic     #105                // Field org/sireum/Z$.MODULE$:Lorg/sireum/Z$;
         3: new           #107                // class scala/Tuple6
         6: dup
         7: aload_0
         8: invokeinterface #109,  1          // InterfaceMethod uriOpt:()Lorg/sireum/Option;
        13: aload_0
        14: invokeinterface #111,  1          // InterfaceMethod beginLine:()Lorg/sireum/Z;
        19: aload_0
        20: invokeinterface #113,  1          // InterfaceMethod endLine:()Lorg/sireum/Z;
        25: aload_0
        26: invokeinterface #115,  1          // InterfaceMethod endColumn:()Lorg/sireum/Z;
        31: aload_0
        32: invokeinterface #117,  1          // InterfaceMethod offset:()Lorg/sireum/Z;
        37: aload_0
        38: invokeinterface #119,  1          // InterfaceMethod length:()Lorg/sireum/Z;
        43: invokespecial #123                // Method scala/Tuple6."<init>":(Ljava/lang/Object;Ljava/lang/Object;Ljava/lang/Object;Ljava/lang/Object;Ljava/lang/Object;Ljava/lang/Object;)V
        46: invokevirtual #124                // Method scala/Tuple6.hashCode:()I
        49: invokevirtual #128                // Method org/sireum/Z$.apply:(I)Lorg/sireum/Z;
        52: areturn
      LineNumberTable:
        line 95: 0
      LocalVariableTable:
        Start  Length  Slot  Name   Signature
            0      53     0  this   Lorg/sireum/message/Position;

  public static boolean isEqual$(org.sireum.message.Position, org.sireum.message.Position);
    descriptor: (Lorg/sireum/message/Position;Lorg/sireum/message/Position;)Z
    flags: (0x1009) ACC_PUBLIC, ACC_STATIC, ACC_SYNTHETIC
    Code:
      stack=2, locals=2, args_size=2
         0: aload_0
         1: aload_1
         2: invokespecial #72                 // InterfaceMethod isEqual:(Lorg/sireum/message/Position;)Z
         5: ireturn
      LineNumberTable:
        line 98: 0
      LocalVariableTable:
        Start  Length  Slot  Name   Signature
            0       6     0 $this   Lorg/sireum/message/Position;
            0       6     1 other   Lorg/sireum/message/Position;
    MethodParameters:
      Name                           Flags
      $this                          final synthetic
      other                          final

  public default boolean isEqual(org.sireum.message.Position);
    descriptor: (Lorg/sireum/message/Position;)Z
    flags: (0x0001) ACC_PUBLIC
    Code:
      stack=3, locals=9, args_size=2
         0: getstatic     #69                 // Field org/sireum/B$.MODULE$:Lorg/sireum/B$;
         3: aload_0
         4: invokeinterface #109,  1          // InterfaceMethod uriOpt:()Lorg/sireum/Option;
         9: aload_1
        10: invokeinterface #109,  1          // InterfaceMethod uriOpt:()Lorg/sireum/Option;
        15: astore_2
        16: dup
        17: ifnonnull     28
        20: pop
        21: aload_2
        22: ifnull        35
        25: goto          246
        28: aload_2
        29: invokevirtual #132                // Method java/lang/Object.equals:(Ljava/lang/Object;)Z
        32: ifeq          246
        35: aload_0
        36: invokeinterface #111,  1          // InterfaceMethod beginLine:()Lorg/sireum/Z;
        41: aload_1
        42: invokeinterface #111,  1          // InterfaceMethod beginLine:()Lorg/sireum/Z;
        47: astore_3
        48: dup
        49: ifnonnull     60
        52: pop
        53: aload_3
        54: ifnull        67
        57: goto          246
        60: aload_3
        61: invokevirtual #132                // Method java/lang/Object.equals:(Ljava/lang/Object;)Z
        64: ifeq          246
        67: aload_0
        68: invokeinterface #134,  1          // InterfaceMethod beginColumn:()Lorg/sireum/Z;
        73: aload_1
        74: invokeinterface #134,  1          // InterfaceMethod beginColumn:()Lorg/sireum/Z;
        79: astore        4
        81: dup
        82: ifnonnull     94
        85: pop
        86: aload         4
        88: ifnull        102
        91: goto          246
        94: aload         4
        96: invokevirtual #132                // Method java/lang/Object.equals:(Ljava/lang/Object;)Z
        99: ifeq          246
       102: aload_0
       103: invokeinterface #113,  1          // InterfaceMethod endLine:()Lorg/sireum/Z;
       108: aload_1
       109: invokeinterface #113,  1          // InterfaceMethod endLine:()Lorg/sireum/Z;
       114: astore        5
       116: dup
       117: ifnonnull     129
       120: pop
       121: aload         5
       123: ifnull        137
       126: goto          246
       129: aload         5
       131: invokevirtual #132                // Method java/lang/Object.equals:(Ljava/lang/Object;)Z
       134: ifeq          246
       137: aload_0
       138: invokeinterface #115,  1          // InterfaceMethod endColumn:()Lorg/sireum/Z;
       143: aload_1
       144: invokeinterface #115,  1          // InterfaceMethod endColumn:()Lorg/sireum/Z;
       149: astore        6
       151: dup
       152: ifnonnull     164
       155: pop
       156: aload         6
       158: ifnull        172
       161: goto          246
       164: aload         6
       166: invokevirtual #132                // Method java/lang/Object.equals:(Ljava/lang/Object;)Z
       169: ifeq          246
       172: aload_0
       173: invokeinterface #117,  1          // InterfaceMethod offset:()Lorg/sireum/Z;
       178: aload_1
       179: invokeinterface #117,  1          // InterfaceMethod offset:()Lorg/sireum/Z;
       184: astore        7
       186: dup
       187: ifnonnull     199
       190: pop
       191: aload         7
       193: ifnull        207
       196: goto          246
       199: aload         7
       201: invokevirtual #132                // Method java/lang/Object.equals:(Ljava/lang/Object;)Z
       204: ifeq          246
       207: aload_0
       208: invokeinterface #119,  1          // InterfaceMethod length:()Lorg/sireum/Z;
       213: aload_1
       214: invokeinterface #119,  1          // InterfaceMethod length:()Lorg/sireum/Z;
       219: astore        8
       221: dup
       222: ifnonnull     234
       225: pop
       226: aload         8
       228: ifnull        242
       231: goto          246
       234: aload         8
       236: invokevirtual #132                // Method java/lang/Object.equals:(Ljava/lang/Object;)Z
       239: ifeq          246
       242: iconst_1
       243: goto          247
       246: iconst_0
       247: invokevirtual #136                // Method org/sireum/B$.apply:(Z)Z
       250: ireturn
      StackMapTable: number_of_entries = 16
        frame_type = 255 /* full_frame */
          offset_delta = 28
          locals = [ class org/sireum/message/Position, class org/sireum/message/Position, class org/sireum/Option ]
          stack = [ class org/sireum/B$, class org/sireum/Option ]
        frame_type = 70 /* same_locals_1_stack_item */
          stack = [ class org/sireum/B$ ]
        frame_type = 255 /* full_frame */
          offset_delta = 24
          locals = [ class org/sireum/message/Position, class org/sireum/message/Position, class org/sireum/Option, class org/sireum/Z ]
          stack = [ class org/sireum/B$, class org/sireum/Z ]
        frame_type = 70 /* same_locals_1_stack_item */
          stack = [ class org/sireum/B$ ]
        frame_type = 255 /* full_frame */
          offset_delta = 26
          locals = [ class org/sireum/message/Position, class org/sireum/message/Position, class org/sireum/Option, class org/sireum/Z, class org/sireum/Z ]
          stack = [ class org/sireum/B$, class org/sireum/Z ]
        frame_type = 71 /* same_locals_1_stack_item */
          stack = [ class org/sireum/B$ ]
        frame_type = 255 /* full_frame */
          offset_delta = 26
          locals = [ class org/sireum/message/Position, class org/sireum/message/Position, class org/sireum/Option, class org/sireum/Z, class org/sireum/Z, class org/sireum/Z ]
          stack = [ class org/sireum/B$, class org/sireum/Z ]
        frame_type = 71 /* same_locals_1_stack_item */
          stack = [ class org/sireum/B$ ]
        frame_type = 255 /* full_frame */
          offset_delta = 26
          locals = [ class org/sireum/message/Position, class org/sireum/message/Position, class org/sireum/Option, class org/sireum/Z, class org/sireum/Z, class org/sireum/Z, class org/sireum/Z ]
          stack = [ class org/sireum/B$, class org/sireum/Z ]
        frame_type = 71 /* same_locals_1_stack_item */
          stack = [ class org/sireum/B$ ]
        frame_type = 255 /* full_frame */
          offset_delta = 26
          locals = [ class org/sireum/message/Position, class org/sireum/message/Position, class org/sireum/Option, class org/sireum/Z, class org/sireum/Z, class org/sireum/Z, class org/sireum/Z, class org/sireum/Z ]
          stack = [ class org/sireum/B$, class org/sireum/Z ]
        frame_type = 71 /* same_locals_1_stack_item */
          stack = [ class org/sireum/B$ ]
        frame_type = 255 /* full_frame */
          offset_delta = 26
          locals = [ class org/sireum/message/Position, class org/sireum/message/Position, class org/sireum/Option, class org/sireum/Z, class org/sireum/Z, class org/sireum/Z, class org/sireum/Z, class org/sireum/Z, class org/sireum/Z ]
          stack = [ class org/sireum/B$, class org/sireum/Z ]
        frame_type = 71 /* same_locals_1_stack_item */
          stack = [ class org/sireum/B$ ]
        frame_type = 255 /* full_frame */
          offset_delta = 3
          locals = [ class org/sireum/message/Position, class org/sireum/message/Position, class org/sireum/Option ]
          stack = [ class org/sireum/B$ ]
        frame_type = 255 /* full_frame */
          offset_delta = 0
          locals = [ class org/sireum/message/Position, class org/sireum/message/Position, class org/sireum/Option ]
          stack = [ class org/sireum/B$, int ]
      LineNumberTable:
        line 100: 0
        line 99: 3
        line 100: 102
        line 99: 250
      LocalVariableTable:
        Start  Length  Slot  Name   Signature
            0     251     0  this   Lorg/sireum/message/Position;
            0     251     1 other   Lorg/sireum/message/Position;
    MethodParameters:
      Name                           Flags
      other                          final

  public static java.lang.String string$(org.sireum.message.Position);
    descriptor: (Lorg/sireum/message/Position;)Ljava/lang/String;
    flags: (0x1009) ACC_PUBLIC, ACC_STATIC, ACC_SYNTHETIC
    Code:
      stack=1, locals=1, args_size=1
         0: aload_0
         1: invokespecial #89                 // InterfaceMethod string:()Ljava/lang/String;
         4: areturn
      LineNumberTable:
        line 103: 0
      LocalVariableTable:
        Start  Length  Slot  Name   Signature
            0       5     0 $this   Lorg/sireum/message/Position;
    MethodParameters:
      Name                           Flags
      $this                          final synthetic

  public default java.lang.String string();
    descriptor: ()Ljava/lang/String;
    flags: (0x0001) ACC_PUBLIC
    Code:
      stack=8, locals=7, args_size=1
         0: aload_0
         1: invokeinterface #109,  1          // InterfaceMethod uriOpt:()Lorg/sireum/Option;
         6: astore_2
         7: aload_2
         8: instanceof    #141                // class org/sireum/Some
        11: ifeq          196
        14: aload_2
        15: checkcast     #141                // class org/sireum/Some
        18: astore_3
        19: getstatic     #146                // Field org/sireum/Some$.MODULE$:Lorg/sireum/Some$;
        22: aload_3
        23: invokevirtual #150                // Method org/sireum/Some$.unapply:(Lorg/sireum/Some;)Lscala/Some;
        26: astore        4
        28: aload         4
        30: invokevirtual #155                // Method scala/Some.isEmpty:()Z
        33: ifne          193
        36: aload         4
        38: invokevirtual #159                // Method scala/Some.get:()Ljava/lang/Object;
        41: checkcast     #161                // class org/sireum/String
        44: invokevirtual #164                // Method org/sireum/String.value:()Ljava/lang/String;
        47: astore        5
        49: getstatic     #169                // Field org/sireum/ops/StringOps$.MODULE$:Lorg/sireum/ops/StringOps$;
        52: aload         5
        54: invokevirtual #172                // Method org/sireum/ops/StringOps$.apply:(Ljava/lang/String;)Lorg/sireum/ops/StringOps;
        57: getstatic     #177                // Field org/sireum/C$.MODULE$:Lorg/sireum/C$;
        60: bipush        47
        62: invokevirtual #180                // Method org/sireum/C$.apply:(C)I
        65: invokevirtual #185                // Method org/sireum/ops/StringOps.lastIndexOf:(I)Lorg/sireum/Z;
        68: astore        6
        70: getstatic     #69                 // Field org/sireum/B$.MODULE$:Lorg/sireum/B$;
        73: aload         6
        75: getstatic     #105                // Field org/sireum/Z$.MODULE$:Lorg/sireum/Z$;
        78: iconst_0
        79: invokevirtual #128                // Method org/sireum/Z$.apply:(I)Lorg/sireum/Z;
        82: invokeinterface #189,  2          // InterfaceMethod org/sireum/Z.$less:(Lorg/sireum/Z;)Z
        87: invokevirtual #76                 // Method org/sireum/B$.$4B:(Z)Z
        90: ifeq          105
        93: getstatic     #105                // Field org/sireum/Z$.MODULE$:Lorg/sireum/Z$;
        96: iconst_0
        97: invokevirtual #128                // Method org/sireum/Z$.apply:(I)Lorg/sireum/Z;
       100: astore        6
       102: goto          105
       105: getstatic     #194                // Field org/sireum/String$.MODULE$:Lorg/sireum/String$;
       108: new           #196                // class java/lang/StringBuilder
       111: dup
       112: ldc           #197                // int 6
       114: invokespecial #200                // Method java/lang/StringBuilder."<init>":(I)V
       117: ldc           #202                // String [
       119: invokevirtual #206                // Method java/lang/StringBuilder.append:(Ljava/lang/String;)Ljava/lang/StringBuilder;
       122: new           #161                // class org/sireum/String
       125: dup
       126: getstatic     #169                // Field org/sireum/ops/StringOps$.MODULE$:Lorg/sireum/ops/StringOps$;
       129: aload         5
       131: invokevirtual #172                // Method org/sireum/ops/StringOps$.apply:(Ljava/lang/String;)Lorg/sireum/ops/StringOps;
       134: aload         6
       136: getstatic     #194                // Field org/sireum/String$.MODULE$:Lorg/sireum/String$;
       139: aload         5
       141: invokevirtual #210                // Method org/sireum/String$.size$extension:(Ljava/lang/String;)Lorg/sireum/Z;
       144: invokevirtual #214                // Method org/sireum/ops/StringOps.substring:(Lorg/sireum/Z;Lorg/sireum/Z;)Ljava/lang/String;
       147: invokespecial #217                // Method org/sireum/String."<init>":(Ljava/lang/String;)V
       150: invokevirtual #220                // Method java/lang/StringBuilder.append:(Ljava/lang/Object;)Ljava/lang/StringBuilder;
       153: ldc           #222                // String ,
       155: invokevirtual #206                // Method java/lang/StringBuilder.append:(Ljava/lang/String;)Ljava/lang/StringBuilder;
       158: aload_0
       159: invokeinterface #111,  1          // InterfaceMethod beginLine:()Lorg/sireum/Z;
       164: invokevirtual #220                // Method java/lang/StringBuilder.append:(Ljava/lang/Object;)Ljava/lang/StringBuilder;
       167: ldc           #222                // String ,
       169: invokevirtual #206                // Method java/lang/StringBuilder.append:(Ljava/lang/String;)Ljava/lang/StringBuilder;
       172: aload_0
       173: invokeinterface #134,  1          // InterfaceMethod beginColumn:()Lorg/sireum/Z;
       178: invokevirtual #220                // Method java/lang/StringBuilder.append:(Ljava/lang/Object;)Ljava/lang/StringBuilder;
       181: ldc           #224                // String ]
       183: invokevirtual #206                // Method java/lang/StringBuilder.append:(Ljava/lang/String;)Ljava/lang/StringBuilder;
       186: invokevirtual #225                // Method java/lang/StringBuilder.toString:()Ljava/lang/String;
       189: invokevirtual #228                // Method org/sireum/String$.apply:(Ljava/lang/String;)Ljava/lang/String;
       192: areturn
       193: goto          199
       196: goto          199
       199: getstatic     #194                // Field org/sireum/String$.MODULE$:Lorg/sireum/String$;
       202: new           #196                // class java/lang/StringBuilder
       205: dup
       206: ldc           #229                // int 4
       208: invokespecial #200                // Method java/lang/StringBuilder."<init>":(I)V
       211: ldc           #202                // String [
       213: invokevirtual #206                // Method java/lang/StringBuilder.append:(Ljava/lang/String;)Ljava/lang/StringBuilder;
       216: aload_0
       217: invokeinterface #111,  1          // InterfaceMethod beginLine:()Lorg/sireum/Z;
       222: invokevirtual #220                // Method java/lang/StringBuilder.append:(Ljava/lang/Object;)Ljava/lang/StringBuilder;
       225: ldc           #222                // String ,
       227: invokevirtual #206                // Method java/lang/StringBuilder.append:(Ljava/lang/String;)Ljava/lang/StringBuilder;
       230: aload_0
       231: invokeinterface #134,  1          // InterfaceMethod beginColumn:()Lorg/sireum/Z;
       236: invokevirtual #220                // Method java/lang/StringBuilder.append:(Ljava/lang/Object;)Ljava/lang/StringBuilder;
       239: ldc           #224                // String ]
       241: invokevirtual #206                // Method java/lang/StringBuilder.append:(Ljava/lang/String;)Ljava/lang/StringBuilder;
       244: invokevirtual #225                // Method java/lang/StringBuilder.toString:()Ljava/lang/String;
       247: invokevirtual #228                // Method org/sireum/String$.apply:(Ljava/lang/String;)Ljava/lang/String;
       250: areturn
      StackMapTable: number_of_entries = 4
        frame_type = 255 /* full_frame */
          offset_delta = 105
          locals = [ class org/sireum/message/Position, top, class org/sireum/Option, class org/sireum/Some, class scala/Some, class java/lang/String, class org/sireum/Z ]
          stack = []
        frame_type = 249 /* chop */
          offset_delta = 87
        frame_type = 249 /* chop */
          offset_delta = 2
        frame_type = 2 /* same */
      LineNumberTable:
        line 104: 0
        line 105: 7
        line 104: 36
        line 106: 49
        line 107: 70
        line 108: 93
        line 110: 105
        line 105: 193
        line 111: 199
      LocalVariableTable:
        Start  Length  Slot  Name   Signature
           70     123     6     i   Lorg/sireum/Z;
           49     144     5 fileUri   Ljava/lang/String;
            0     251     0  this   Lorg/sireum/message/Position;

  public static org.sireum.message.Position to$(org.sireum.message.Position, org.sireum.message.Position);
    descriptor: (Lorg/sireum/message/Position;Lorg/sireum/message/Position;)Lorg/sireum/message/Position;
    flags: (0x1009) ACC_PUBLIC, ACC_STATIC, ACC_SYNTHETIC
    Code:
      stack=2, locals=2, args_size=2
         0: aload_0
         1: aload_1
         2: invokespecial #241                // InterfaceMethod to:(Lorg/sireum/message/Position;)Lorg/sireum/message/Position;
         5: areturn
      LineNumberTable:
        line 116: 0
      LocalVariableTable:
        Start  Length  Slot  Name   Signature
            0       6     0 $this   Lorg/sireum/message/Position;
            0       6     1 other   Lorg/sireum/message/Position;
    MethodParameters:
      Name                           Flags
      $this                          final synthetic
      other                          final

  public default org.sireum.message.Position to(org.sireum.message.Position);
    descriptor: (Lorg/sireum/message/Position;)Lorg/sireum/message/Position;
    flags: (0x0001) ACC_PUBLIC
    Code:
      stack=13, locals=16, args_size=2
         0: aload_0
         1: astore        5
         3: aload_1
         4: astore        6
         6: getstatic     #246                // Field org/sireum/None$.MODULE$:Lorg/sireum/None$;
         9: invokevirtual #249                // Method org/sireum/None$.apply:()Lorg/sireum/None;
        12: astore        7
        14: aload         5
        16: astore        8
        18: aload         8
        20: instanceof    #251                // class org/sireum/message/PosInfo
        23: ifeq          53
        26: aload         8
        28: checkcast     #251                // class org/sireum/message/PosInfo
        31: astore        9
        33: getstatic     #146                // Field org/sireum/Some$.MODULE$:Lorg/sireum/Some$;
        36: aload         9
        38: invokevirtual #255                // Method org/sireum/message/PosInfo.info:()Lorg/sireum/message/DocInfo;
        41: invokevirtual #258                // Method org/sireum/Some$.apply:(Ljava/lang/Object;)Lorg/sireum/Some;
        44: astore        7
        46: getstatic     #264                // Field scala/runtime/BoxedUnit.UNIT:Lscala/runtime/BoxedUnit;
        49: astore_3
        50: goto          114
        53: goto          56
        56: aload         6
        58: astore        10
        60: aload         10
        62: instanceof    #251                // class org/sireum/message/PosInfo
        65: ifeq          96
        68: aload         10
        70: checkcast     #251                // class org/sireum/message/PosInfo
        73: astore        11
        75: getstatic     #146                // Field org/sireum/Some$.MODULE$:Lorg/sireum/Some$;
        78: aload         11
        80: invokevirtual #255                // Method org/sireum/message/PosInfo.info:()Lorg/sireum/message/DocInfo;
        83: invokevirtual #258                // Method org/sireum/Some$.apply:(Ljava/lang/Object;)Lorg/sireum/Some;
        86: astore        7
        88: getstatic     #264                // Field scala/runtime/BoxedUnit.UNIT:Lscala/runtime/BoxedUnit;
        91: astore        4
        93: goto          107
        96: goto          99
        99: getstatic     #264                // Field scala/runtime/BoxedUnit.UNIT:Lscala/runtime/BoxedUnit;
       102: astore        4
       104: goto          107
       107: getstatic     #264                // Field scala/runtime/BoxedUnit.UNIT:Lscala/runtime/BoxedUnit;
       110: astore_3
       111: goto          114
       114: aload         7
       116: astore        12
       118: aload         12
       120: instanceof    #141                // class org/sireum/Some
       123: ifeq          299
       126: aload         12
       128: checkcast     #141                // class org/sireum/Some
       131: astore        13
       133: getstatic     #146                // Field org/sireum/Some$.MODULE$:Lorg/sireum/Some$;
       136: aload         13
       138: invokevirtual #150                // Method org/sireum/Some$.unapply:(Lorg/sireum/Some;)Lscala/Some;
       141: astore        14
       143: aload         14
       145: invokevirtual #155                // Method scala/Some.isEmpty:()Z
       148: ifne          296
       151: aload         14
       153: invokevirtual #159                // Method scala/Some.get:()Ljava/lang/Object;
       156: checkcast     #266                // class org/sireum/message/DocInfo
       159: astore        15
       161: getstatic     #271                // Field org/sireum/message/PosInfo$.MODULE$:Lorg/sireum/message/PosInfo$;
       164: aload         15
       166: new           #14                 // class org/sireum/U64
       169: dup
       170: getstatic     #276                // Field org/sireum/conversions/Z$.MODULE$:Lorg/sireum/conversions/Z$;
       173: aload         5
       175: invokeinterface #117,  1          // InterfaceMethod offset:()Lorg/sireum/Z;
       180: invokevirtual #280                // Method org/sireum/conversions/Z$.toU64:(Lorg/sireum/Z;)J
       183: invokespecial #283                // Method org/sireum/U64."<init>":(J)V
       186: new           #14                 // class org/sireum/U64
       189: dup
       190: getstatic     #288                // Field org/sireum/U64$.MODULE$:Lorg/sireum/U64$;
       193: new           #290                // class scala/StringContext
       196: dup
       197: getstatic     #295                // Field scala/runtime/ScalaRunTime$.MODULE$:Lscala/runtime/ScalaRunTime$;
       200: iconst_1
       201: anewarray     #235                // class java/lang/String
       204: dup
       205: iconst_0
       206: ldc_w         #297                // String 32
       209: aastore
       210: checkcast     #299                // class "[Ljava/lang/Object;"
       213: invokevirtual #303                // Method scala/runtime/ScalaRunTime$.wrapRefArray:([Ljava/lang/Object;)Lscala/collection/immutable/ArraySeq;
       216: invokespecial #306                // Method scala/StringContext."<init>":(Lscala/collection/immutable/Seq;)V
       219: invokevirtual #309                // Method org/sireum/U64$.U64$Slang:(Lscala/StringContext;)Lorg/sireum/U64$U64$Slang;
       222: invokevirtual #313                // Method org/sireum/U64$U64$Slang.u64:()Lorg/sireum/U64$U64$Slang$u64$;
       225: getstatic     #318                // Field scala/collection/immutable/Nil$.MODULE$:Lscala/collection/immutable/Nil$;
       228: invokevirtual #321                // Method org/sireum/U64$U64$Slang$u64$.apply:(Lscala/collection/immutable/Seq;)J
       231: invokespecial #283                // Method org/sireum/U64."<init>":(J)V
       234: invokevirtual #325                // Method org/sireum/U64.$less$less:(Lorg/sireum/Z$BV$Long;)Lorg/sireum/Z$BV$Long;
       237: new           #14                 // class org/sireum/U64
       240: dup
       241: getstatic     #276                // Field org/sireum/conversions/Z$.MODULE$:Lorg/sireum/conversions/Z$;
       244: aload         6
       246: invokeinterface #117,  1          // InterfaceMethod offset:()Lorg/sireum/Z;
       251: aload         6
       253: invokeinterface #119,  1          // InterfaceMethod length:()Lorg/sireum/Z;
       258: invokeinterface #329,  2          // InterfaceMethod org/sireum/Z.$plus:(Lorg/sireum/Z;)Lorg/sireum/Z;
       263: aload         5
       265: invokeinterface #117,  1          // InterfaceMethod offset:()Lorg/sireum/Z;
       270: invokeinterface #332,  2          // InterfaceMethod org/sireum/Z.$minus:(Lorg/sireum/Z;)Lorg/sireum/Z;
       275: invokevirtual #280                // Method org/sireum/conversions/Z$.toU64:(Lorg/sireum/Z;)J
       278: invokespecial #283                // Method org/sireum/U64."<init>":(J)V
       281: invokeinterface #335,  2          // InterfaceMethod org/sireum/Z$BV$Long.$bar:(Lorg/sireum/Z$BV$Long;)Lorg/sireum/Z$BV$Long;
       286: checkcast     #14                 // class org/sireum/U64
       289: invokevirtual #338                // Method org/sireum/U64.value:()J
       292: invokevirtual #341                // Method org/sireum/message/PosInfo$.apply:(Lorg/sireum/message/DocInfo;J)Lorg/sireum/message/PosInfo;
       295: areturn
       296: goto          302
       299: goto          302
       302: getstatic     #346                // Field org/sireum/message/FlatPos$.MODULE$:Lorg/sireum/message/FlatPos$;
       305: aload         5
       307: invokeinterface #109,  1          // InterfaceMethod uriOpt:()Lorg/sireum/Option;
       312: getstatic     #276                // Field org/sireum/conversions/Z$.MODULE$:Lorg/sireum/conversions/Z$;
       315: aload         5
       317: invokeinterface #111,  1          // InterfaceMethod beginLine:()Lorg/sireum/Z;
       322: invokevirtual #350                // Method org/sireum/conversions/Z$.toU32:(Lorg/sireum/Z;)I
       325: getstatic     #276                // Field org/sireum/conversions/Z$.MODULE$:Lorg/sireum/conversions/Z$;
       328: aload         5
       330: invokeinterface #134,  1          // InterfaceMethod beginColumn:()Lorg/sireum/Z;
       335: invokevirtual #350                // Method org/sireum/conversions/Z$.toU32:(Lorg/sireum/Z;)I
       338: getstatic     #276                // Field org/sireum/conversions/Z$.MODULE$:Lorg/sireum/conversions/Z$;
       341: aload         6
       343: invokeinterface #113,  1          // InterfaceMethod endLine:()Lorg/sireum/Z;
       348: invokevirtual #350                // Method org/sireum/conversions/Z$.toU32:(Lorg/sireum/Z;)I
       351: getstatic     #276                // Field org/sireum/conversions/Z$.MODULE$:Lorg/sireum/conversions/Z$;
       354: aload         6
       356: invokeinterface #115,  1          // InterfaceMethod endColumn:()Lorg/sireum/Z;
       361: invokevirtual #350                // Method org/sireum/conversions/Z$.toU32:(Lorg/sireum/Z;)I
       364: getstatic     #276                // Field org/sireum/conversions/Z$.MODULE$:Lorg/sireum/conversions/Z$;
       367: aload         5
       369: invokeinterface #117,  1          // InterfaceMethod offset:()Lorg/sireum/Z;
       374: invokevirtual #350                // Method org/sireum/conversions/Z$.toU32:(Lorg/sireum/Z;)I
       377: getstatic     #276                // Field org/sireum/conversions/Z$.MODULE$:Lorg/sireum/conversions/Z$;
       380: aload         6
       382: invokeinterface #117,  1          // InterfaceMethod offset:()Lorg/sireum/Z;
       387: aload         6
       389: invokeinterface #119,  1          // InterfaceMethod length:()Lorg/sireum/Z;
       394: invokeinterface #329,  2          // InterfaceMethod org/sireum/Z.$plus:(Lorg/sireum/Z;)Lorg/sireum/Z;
       399: aload         5
       401: invokeinterface #117,  1          // InterfaceMethod offset:()Lorg/sireum/Z;
       406: invokeinterface #332,  2          // InterfaceMethod org/sireum/Z.$minus:(Lorg/sireum/Z;)Lorg/sireum/Z;
       411: invokevirtual #350                // Method org/sireum/conversions/Z$.toU32:(Lorg/sireum/Z;)I
       414: invokevirtual #353                // Method org/sireum/message/FlatPos$.apply:(Lorg/sireum/Option;IIIIII)Lorg/sireum/message/FlatPos;
       417: areturn
      StackMapTable: number_of_entries = 9
        frame_type = 255 /* full_frame */
          offset_delta = 53
          locals = [ class org/sireum/message/Position, class org/sireum/message/Position, top, top, top, class org/sireum/message/Position, class org/sireum/message/Position, class org/sireum/None, class org/sireum/message/Position ]
          stack = []
        frame_type = 2 /* same */
        frame_type = 253 /* append */
          offset_delta = 39
          locals = [ top, class org/sireum/message/Position ]
        frame_type = 2 /* same */
        frame_type = 255 /* full_frame */
          offset_delta = 7
          locals = [ class org/sireum/message/Position, class org/sireum/message/Position, top, top, class scala/runtime/BoxedUnit, class org/sireum/message/Position, class org/sireum/message/Position, class java/lang/Object, class org/sireum/message/Position, top, class org/sireum/message/Position ]
          stack = []
        frame_type = 255 /* full_frame */
          offset_delta = 6
          locals = [ class org/sireum/message/Position, class org/sireum/message/Position, top, class scala/runtime/BoxedUnit, top, class org/sireum/message/Position, class org/sireum/message/Position, class java/lang/Object, class org/sireum/message/Position ]
          stack = []
        frame_type = 255 /* full_frame */
          offset_delta = 181
          locals = [ class org/sireum/message/Position, class org/sireum/message/Position, top, class scala/runtime/BoxedUnit, top, class org/sireum/message/Position, class org/sireum/message/Position, class java/lang/Object, class org/sireum/message/Position, top, top, top, class java/lang/Object, class org/sireum/Some, class scala/Some ]
          stack = []
        frame_type = 249 /* chop */
          offset_delta = 2
        frame_type = 2 /* same */
      LineNumberTable:
        line 117: 0
        line 118: 3
        line 119: 6
        line 120: 14
        line 121: 18
        line 123: 56
        line 124: 60
        line 125: 99
        line 123: 107
        line 128: 114
        line 129: 118
        line 128: 151
        line 130: 161
        line 131: 237
        line 130: 295
        line 129: 296
        line 133: 302
        line 134: 305
        line 135: 312
        line 136: 325
        line 137: 338
        line 138: 351
        line 139: 364
        line 140: 377
        line 133: 417
      LocalVariableTable:
        Start  Length  Slot  Name   Signature
          161     135    15  info   Lorg/sireum/message/DocInfo;
            3     415     5  pos1   Lorg/sireum/message/Position;
            6     412     6  pos2   Lorg/sireum/message/Position;
           14     404     7 docInfoOpt   Lorg/sireum/Option;
            0     418     0  this   Lorg/sireum/message/Position;
            0     418     1 other   Lorg/sireum/message/Position;
    MethodParameters:
      Name                           Flags
      other                          final

  public static void $init$(org.sireum.message.Position);
    descriptor: (Lorg/sireum/message/Position;)V
    flags: (0x0009) ACC_PUBLIC, ACC_STATIC
    Code:
      stack=0, locals=1, args_size=1
         0: return
      LineNumberTable:
        line 71: 0
      LocalVariableTable:
        Start  Length  Slot  Name   Signature
            0       1     0 $this   Lorg/sireum/message/Position;
    MethodParameters:
      Name                           Flags
      $this                          final synthetic
}
InnerClasses:
  public static #15= #12 of #14;          // U64$Slang=class org/sireum/U64$U64$Slang of class org/sireum/U64
  public #18= #17 of #12;                 // u64$=class org/sireum/U64$U64$Slang$u64$ of class org/sireum/U64$U64$Slang
  public static #23= #20 of #22;          // BV$=class org/sireum/Z$BV$ of class org/sireum/Z
  public static #26= #25 of #20;          // Long=class org/sireum/Z$BV$Long of class org/sireum/Z$BV$
SourceFile: "Message.scala"
RuntimeVisibleAnnotations:
  0: #8(#9=s#10)
    scala.reflect.ScalaSignature(
      bytes="\u0006\u0005\u0005eq!B\f\u0019\u0011\u0003yb!B\u0011\u0019\u0011\u0003\u0011\u0003\"B\u0015\u0002\t\u0003Q\u0003bB\u0016\u0002\u0005\u0004%\t\u0001\f\u0005\b\u0003/\t\u0001\u0015!\u0003.\r\u001d\t\u0003\u0004%A\u0002\"9BQaM\u0003\u0005\u0002QBQ\u0001O\u0003\u0005BeBq!P\u0003C\u0002\u0013Uc\bC\u0003B\u000b\u0011\u0005#\tC\u0004L\u000b\t\u0007IQ\u000b \t\u000b1+A\u0011I\'\t\u000bY+a\u0011A,\t\u000b\u0005,a\u0011\u00012\t\u000b\u001d,a\u0011\u00012\t\u000b%,a\u0011\u00012\t\u000b-,a\u0011\u00012\t\u000b5,a\u0011\u00012\t\u000b=,a\u0011\u00012\t\u000bE,A\u0011\t2\t\u000bM,A\u0011\u0001;\t\u000bm,A\u0011\t?\t\u000by,A\u0011A@\u0002\u0011A{7/\u001b;j_:T!!\u0007\u000e\u0002\u000f5,7o]1hK*\u00111\u0004H\u0001\u0007g&\u0014X-^7\u000b\u0003u\t1a\u001c:h\u0007\u0001\u0001\"\u0001I\u0001\u000e\u0003a\u0011\u0001\u0002U8tSRLwN\\\n\u0003\u0003\r\u0002\"\u0001J\u0014\u000e\u0003\u0015R\u0011AJ\u0001\u0006g\u000e\fG.Y\u0005\u0003Q\u0015\u0012a!\u00118z%\u00164\u0017A\u0002\u001fj]&$h\bF\u0001 \u0003\u0011qwN\\3\u0016\u00035\u0002\"\u0001I\u0003\u0014\u0007\u0015\u0019s\u0006\u0005\u00021c5\t!$\u0003\u000235\tYA)\u0019;bif\u0004XmU5h\u0003\u0019!\u0013N\\5uIQ\tQ\u0007\u0005\u0002%m%\u0011q\'\n\u0002\u0005+:LG/\u0001\u0005iCND7i\u001c3f)\u0005Q\u0004C\u0001\u0013<\u0013\taTEA\u0002J]R\f!\u0002\n5bg\u0016\u000bX/\u00197t+\u0005yt\"\u0001!\u001a\u0003\u0005\ta!Z9vC2\u001cHCA\"G!\t!C)\u0003\u0002FK\t9!i\\8mK\u0006t\u0007\"B$\n\u0001\u0004A\u0015!A8\u0011\u0005\u0011J\u0015B\u0001&&\u0005\r\te._\u0001\u000bI!\f7o\u0015;sS:<\u0017\u0001\u0003;p\'R\u0014\u0018N\\4\u0015\u00039\u0003\"a\u0014+\u000e\u0003AS!!\u0015*\u0002\t1\fgn\u001a\u0006\u0002\'\u0006!!.\u0019<b\u0013\t)\u0006K\u0001\u0004TiJLgnZ\u0001\u0007kJLw\n\u001d;\u0016\u0003a\u00032\u0001M-\\\u0013\tQ&D\u0001\u0004PaRLwN\u001c\t\u0003aqK!!\u0016\u000e)\u00051q\u0006C\u0001\u0019`\u0013\t\u0001\'D\u0001\u0003qkJ,\u0017!\u00032fO&tG*\u001b8f+\u0005\u0019\u0007C\u0001\u0019e\u0013\t)\'DA\u0001[Q\tia,A\u0006cK\u001eLgnQ8mk6t\u0007F\u0001\b_\u0003\u001d)g\u000e\u001a\'j]\u0016D#a\u00040\u0002\u0013\u0015tGmQ8mk6t\u0007F\u0001\t_\u0003\u0019ygMZ:fi\"\u0012\u0011CX\u0001\u0007Y\u0016tw\r\u001e5)\u0005Iq\u0016\u0001\u00025bg\"D#a\u00050\u0002\u000f%\u001cX)];bYR\u0011Q\u000f\u001f\t\u0003aYL!a\u001e\u000e\u0003\u0003\tCQ!\u001f\u000bA\u00025\nQa\u001c;iKJD#\u0001\u00060\u0002\rM$(/\u001b8h+\u0005Y\u0006FA\u000b_\u0003\t!x\u000eF\u0002.\u0003\u0003AQ!\u001f\fA\u00025B#A\u00060*\u000b\u0015\t9!a\u0003\n\u0007\u0005%\u0001DA\u0004GY\u0006$\bk\\:\n\u0007\u00055\u0001DA\u0004Q_NLeNZ8)\u0007\u0015\t\t\u0002E\u00021\u0003\'I1!!\u0006\u001b\u0005!!\u0017\r^1usB,\u0017!\u00028p]\u0016\u0004\u0003"
    )
  ScalaInlineInfo: length = 0x86 (unknown attribute)
   01 00 00 1A 00 35 00 36 01 00 33 00 34 01 00 4E
   00 36 01 00 4D 00 34 01 01 69 01 6A 01 00 5E 00
   2E 00 00 5D 00 2E 00 00 60 00 2E 00 00 5F 00 2E
   00 00 3C 00 3D 00 00 39 00 3A 01 00 2D 00 2E 00
   00 63 00 64 01 00 28 00 29 00 00 25 00 26 01 00
   46 00 34 00 00 81 00 82 01 00 62 00 2E 00 00 61
   00 2E 00 00 57 00 54 00 00 8B 00 52 01 00 EE 00
   EF 00 00 EC 00 ED 01 00 53 00 54 00 00 51 00 52
   01 00 5A 00 5B 00
  ScalaSig: length = 0x3 (unknown attribute)
   05 02 00
