Classfile /Users/mw/Projects/slang-braindump/.jar/jar8/assemble/slang-braindump/assemble/content/org/apache/commons/lang3/reflect/TypeUtils$WildcardTypeImpl.class
  Last modified May 29, 2022; size 2141 bytes
  SHA-256 checksum 8b0112c39b5645dc7faddbe10cae01c780bc2b317f537457810c8392654bca45
  Compiled from "TypeUtils.java"
final class org.apache.commons.lang3.reflect.TypeUtils$WildcardTypeImpl implements java.lang.reflect.WildcardType
  minor version: 0
  major version: 52
  flags: (0x0030) ACC_FINAL, ACC_SUPER
  this_class: #15                         // org/apache/commons/lang3/reflect/TypeUtils$WildcardTypeImpl
  super_class: #16                        // java/lang/Object
  interfaces: 1, fields: 3, methods: 8, attributes: 2
Constant pool:
   #1 = Methodref          #15.#54        // org/apache/commons/lang3/reflect/TypeUtils$WildcardTypeImpl."<init>":([Ljava/lang/reflect/Type;[Ljava/lang/reflect/Type;)V
   #2 = Methodref          #16.#55        // java/lang/Object."<init>":()V
   #3 = Fieldref           #15.#56        // org/apache/commons/lang3/reflect/TypeUtils$WildcardTypeImpl.EMPTY_BOUNDS:[Ljava/lang/reflect/Type;
   #4 = Methodref          #57.#58        // org/apache/commons/lang3/ObjectUtils.defaultIfNull:(Ljava/lang/Object;Ljava/lang/Object;)Ljava/lang/Object;
   #5 = Class              #18            // "[Ljava/lang/reflect/Type;"
   #6 = Fieldref           #15.#59        // org/apache/commons/lang3/reflect/TypeUtils$WildcardTypeImpl.upperBounds:[Ljava/lang/reflect/Type;
   #7 = Fieldref           #15.#60        // org/apache/commons/lang3/reflect/TypeUtils$WildcardTypeImpl.lowerBounds:[Ljava/lang/reflect/Type;
   #8 = Methodref          #61.#62        // "[Ljava/lang/reflect/Type;".clone:()Ljava/lang/Object;
   #9 = Methodref          #63.#62        // "[Ljava/lang/reflect/Type;".clone:()Ljava/lang/Object;
  #10 = Methodref          #64.#65        // org/apache/commons/lang3/reflect/TypeUtils.toString:(Ljava/lang/reflect/Type;)Ljava/lang/String;
  #11 = Class              #66            // java/lang/reflect/WildcardType
  #12 = Methodref          #64.#67        // org/apache/commons/lang3/reflect/TypeUtils.access$300:(Ljava/lang/reflect/WildcardType;Ljava/lang/reflect/Type;)Z
  #13 = Methodref          #68.#69        // java/util/Arrays.hashCode:([Ljava/lang/Object;)I
  #14 = Class              #70            // java/lang/reflect/Type
  #15 = Class              #71            // org/apache/commons/lang3/reflect/TypeUtils$WildcardTypeImpl
  #16 = Class              #72            // java/lang/Object
  #17 = Utf8               EMPTY_BOUNDS
  #18 = Utf8               [Ljava/lang/reflect/Type;
  #19 = Utf8               upperBounds
  #20 = Utf8               lowerBounds
  #21 = Utf8               <init>
  #22 = Utf8               ([Ljava/lang/reflect/Type;[Ljava/lang/reflect/Type;)V
  #23 = Utf8               Code
  #24 = Utf8               LineNumberTable
  #25 = Utf8               LocalVariableTable
  #26 = Utf8               this
  #27 = Utf8               WildcardTypeImpl
  #28 = Utf8               InnerClasses
  #29 = Utf8               Lorg/apache/commons/lang3/reflect/TypeUtils$WildcardTypeImpl;
  #30 = Utf8               getUpperBounds
  #31 = Utf8               ()[Ljava/lang/reflect/Type;
  #32 = Utf8               getLowerBounds
  #33 = Utf8               toString
  #34 = Utf8               ()Ljava/lang/String;
  #35 = Utf8               equals
  #36 = Utf8               (Ljava/lang/Object;)Z
  #37 = Utf8               obj
  #38 = Utf8               Ljava/lang/Object;
  #39 = Utf8               StackMapTable
  #40 = Utf8               hashCode
  #41 = Utf8               ()I
  #42 = Utf8               result
  #43 = Utf8               I
  #44 = Class              #73            // org/apache/commons/lang3/reflect/TypeUtils$1
  #45 = Utf8               ([Ljava/lang/reflect/Type;[Ljava/lang/reflect/Type;Lorg/apache/commons/lang3/reflect/TypeUtils$1;)V
  #46 = Utf8               x0
  #47 = Utf8               x1
  #48 = Utf8               x2
  #49 = Utf8               Lorg/apache/commons/lang3/reflect/TypeUtils$1;
  #50 = Utf8               <clinit>
  #51 = Utf8               ()V
  #52 = Utf8               SourceFile
  #53 = Utf8               TypeUtils.java
  #54 = NameAndType        #21:#22        // "<init>":([Ljava/lang/reflect/Type;[Ljava/lang/reflect/Type;)V
  #55 = NameAndType        #21:#51        // "<init>":()V
  #56 = NameAndType        #17:#18        // EMPTY_BOUNDS:[Ljava/lang/reflect/Type;
  #57 = Class              #74            // org/apache/commons/lang3/ObjectUtils
  #58 = NameAndType        #75:#76        // defaultIfNull:(Ljava/lang/Object;Ljava/lang/Object;)Ljava/lang/Object;
  #59 = NameAndType        #19:#18        // upperBounds:[Ljava/lang/reflect/Type;
  #60 = NameAndType        #20:#18        // lowerBounds:[Ljava/lang/reflect/Type;
  #61 = Class              #18            // "[Ljava/lang/reflect/Type;"
  #62 = NameAndType        #77:#78        // clone:()Ljava/lang/Object;
  #63 = Class              #18            // "[Ljava/lang/reflect/Type;"
  #64 = Class              #79            // org/apache/commons/lang3/reflect/TypeUtils
  #65 = NameAndType        #33:#80        // toString:(Ljava/lang/reflect/Type;)Ljava/lang/String;
  #66 = Utf8               java/lang/reflect/WildcardType
  #67 = NameAndType        #81:#82        // access$300:(Ljava/lang/reflect/WildcardType;Ljava/lang/reflect/Type;)Z
  #68 = Class              #83            // java/util/Arrays
  #69 = NameAndType        #40:#84        // hashCode:([Ljava/lang/Object;)I
  #70 = Utf8               java/lang/reflect/Type
  #71 = Utf8               org/apache/commons/lang3/reflect/TypeUtils$WildcardTypeImpl
  #72 = Utf8               java/lang/Object
  #73 = Utf8               org/apache/commons/lang3/reflect/TypeUtils$1
  #74 = Utf8               org/apache/commons/lang3/ObjectUtils
  #75 = Utf8               defaultIfNull
  #76 = Utf8               (Ljava/lang/Object;Ljava/lang/Object;)Ljava/lang/Object;
  #77 = Utf8               clone
  #78 = Utf8               ()Ljava/lang/Object;
  #79 = Utf8               org/apache/commons/lang3/reflect/TypeUtils
  #80 = Utf8               (Ljava/lang/reflect/Type;)Ljava/lang/String;
  #81 = Utf8               access$300
  #82 = Utf8               (Ljava/lang/reflect/WildcardType;Ljava/lang/reflect/Type;)Z
  #83 = Utf8               java/util/Arrays
  #84 = Utf8               ([Ljava/lang/Object;)I
{
  private static final java.lang.reflect.Type[] EMPTY_BOUNDS;
    descriptor: [Ljava/lang/reflect/Type;
    flags: (0x001a) ACC_PRIVATE, ACC_STATIC, ACC_FINAL

  private final java.lang.reflect.Type[] upperBounds;
    descriptor: [Ljava/lang/reflect/Type;
    flags: (0x0012) ACC_PRIVATE, ACC_FINAL

  private final java.lang.reflect.Type[] lowerBounds;
    descriptor: [Ljava/lang/reflect/Type;
    flags: (0x0012) ACC_PRIVATE, ACC_FINAL

  private org.apache.commons.lang3.reflect.TypeUtils$WildcardTypeImpl(java.lang.reflect.Type[], java.lang.reflect.Type[]);
    descriptor: ([Ljava/lang/reflect/Type;[Ljava/lang/reflect/Type;)V
    flags: (0x0002) ACC_PRIVATE
    Code:
      stack=3, locals=3, args_size=3
         0: aload_0
         1: invokespecial #2                  // Method java/lang/Object."<init>":()V
         4: aload_0
         5: aload_1
         6: getstatic     #3                  // Field EMPTY_BOUNDS:[Ljava/lang/reflect/Type;
         9: invokestatic  #4                  // Method org/apache/commons/lang3/ObjectUtils.defaultIfNull:(Ljava/lang/Object;Ljava/lang/Object;)Ljava/lang/Object;
        12: checkcast     #5                  // class "[Ljava/lang/reflect/Type;"
        15: putfield      #6                  // Field upperBounds:[Ljava/lang/reflect/Type;
        18: aload_0
        19: aload_2
        20: getstatic     #3                  // Field EMPTY_BOUNDS:[Ljava/lang/reflect/Type;
        23: invokestatic  #4                  // Method org/apache/commons/lang3/ObjectUtils.defaultIfNull:(Ljava/lang/Object;Ljava/lang/Object;)Ljava/lang/Object;
        26: checkcast     #5                  // class "[Ljava/lang/reflect/Type;"
        29: putfield      #7                  // Field lowerBounds:[Ljava/lang/reflect/Type;
        32: return
      LineNumberTable:
        line 233: 0
        line 234: 4
        line 235: 18
        line 236: 32
      LocalVariableTable:
        Start  Length  Slot  Name   Signature
            0      33     0  this   Lorg/apache/commons/lang3/reflect/TypeUtils$WildcardTypeImpl;
            0      33     1 upperBounds   [Ljava/lang/reflect/Type;
            0      33     2 lowerBounds   [Ljava/lang/reflect/Type;

  public java.lang.reflect.Type[] getUpperBounds();
    descriptor: ()[Ljava/lang/reflect/Type;
    flags: (0x0001) ACC_PUBLIC
    Code:
      stack=1, locals=1, args_size=1
         0: aload_0
         1: getfield      #6                  // Field upperBounds:[Ljava/lang/reflect/Type;
         4: invokevirtual #8                  // Method "[Ljava/lang/reflect/Type;".clone:()Ljava/lang/Object;
         7: checkcast     #5                  // class "[Ljava/lang/reflect/Type;"
        10: areturn
      LineNumberTable:
        line 243: 0
      LocalVariableTable:
        Start  Length  Slot  Name   Signature
            0      11     0  this   Lorg/apache/commons/lang3/reflect/TypeUtils$WildcardTypeImpl;

  public java.lang.reflect.Type[] getLowerBounds();
    descriptor: ()[Ljava/lang/reflect/Type;
    flags: (0x0001) ACC_PUBLIC
    Code:
      stack=1, locals=1, args_size=1
         0: aload_0
         1: getfield      #7                  // Field lowerBounds:[Ljava/lang/reflect/Type;
         4: invokevirtual #9                  // Method "[Ljava/lang/reflect/Type;".clone:()Ljava/lang/Object;
         7: checkcast     #5                  // class "[Ljava/lang/reflect/Type;"
        10: areturn
      LineNumberTable:
        line 251: 0
      LocalVariableTable:
        Start  Length  Slot  Name   Signature
            0      11     0  this   Lorg/apache/commons/lang3/reflect/TypeUtils$WildcardTypeImpl;

  public java.lang.String toString();
    descriptor: ()Ljava/lang/String;
    flags: (0x0001) ACC_PUBLIC
    Code:
      stack=1, locals=1, args_size=1
         0: aload_0
         1: invokestatic  #10                 // Method org/apache/commons/lang3/reflect/TypeUtils.toString:(Ljava/lang/reflect/Type;)Ljava/lang/String;
         4: areturn
      LineNumberTable:
        line 259: 0
      LocalVariableTable:
        Start  Length  Slot  Name   Signature
            0       5     0  this   Lorg/apache/commons/lang3/reflect/TypeUtils$WildcardTypeImpl;

  public boolean equals(java.lang.Object);
    descriptor: (Ljava/lang/Object;)Z
    flags: (0x0001) ACC_PUBLIC
    Code:
      stack=2, locals=2, args_size=2
         0: aload_1
         1: aload_0
         2: if_acmpeq     23
         5: aload_1
         6: instanceof    #11                 // class java/lang/reflect/WildcardType
         9: ifeq          27
        12: aload_0
        13: aload_1
        14: checkcast     #11                 // class java/lang/reflect/WildcardType
        17: invokestatic  #12                 // Method org/apache/commons/lang3/reflect/TypeUtils.access$300:(Ljava/lang/reflect/WildcardType;Ljava/lang/reflect/Type;)Z
        20: ifeq          27
        23: iconst_1
        24: goto          28
        27: iconst_0
        28: ireturn
      LineNumberTable:
        line 267: 0
      LocalVariableTable:
        Start  Length  Slot  Name   Signature
            0      29     0  this   Lorg/apache/commons/lang3/reflect/TypeUtils$WildcardTypeImpl;
            0      29     1   obj   Ljava/lang/Object;
      StackMapTable: number_of_entries = 3
        frame_type = 23 /* same */
        frame_type = 3 /* same */
        frame_type = 64 /* same_locals_1_stack_item */
          stack = [ int ]

  public int hashCode();
    descriptor: ()I
    flags: (0x0001) ACC_PUBLIC
    Code:
      stack=2, locals=2, args_size=1
         0: sipush        18688
         3: istore_1
         4: iload_1
         5: aload_0
         6: getfield      #6                  // Field upperBounds:[Ljava/lang/reflect/Type;
         9: invokestatic  #13                 // Method java/util/Arrays.hashCode:([Ljava/lang/Object;)I
        12: ior
        13: istore_1
        14: iload_1
        15: bipush        8
        17: ishl
        18: istore_1
        19: iload_1
        20: aload_0
        21: getfield      #7                  // Field lowerBounds:[Ljava/lang/reflect/Type;
        24: invokestatic  #13                 // Method java/util/Arrays.hashCode:([Ljava/lang/Object;)I
        27: ior
        28: istore_1
        29: iload_1
        30: ireturn
      LineNumberTable:
        line 275: 0
        line 276: 4
        line 277: 14
        line 278: 19
        line 279: 29
      LocalVariableTable:
        Start  Length  Slot  Name   Signature
            0      31     0  this   Lorg/apache/commons/lang3/reflect/TypeUtils$WildcardTypeImpl;
            4      27     1 result   I

  org.apache.commons.lang3.reflect.TypeUtils$WildcardTypeImpl(java.lang.reflect.Type[], java.lang.reflect.Type[], org.apache.commons.lang3.reflect.TypeUtils$1);
    descriptor: ([Ljava/lang/reflect/Type;[Ljava/lang/reflect/Type;Lorg/apache/commons/lang3/reflect/TypeUtils$1;)V
    flags: (0x1000) ACC_SYNTHETIC
    Code:
      stack=3, locals=4, args_size=4
         0: aload_0
         1: aload_1
         2: aload_2
         3: invokespecial #1                  // Method "<init>":([Ljava/lang/reflect/Type;[Ljava/lang/reflect/Type;)V
         6: return
      LineNumberTable:
        line 222: 0
      LocalVariableTable:
        Start  Length  Slot  Name   Signature
            0       7     0  this   Lorg/apache/commons/lang3/reflect/TypeUtils$WildcardTypeImpl;
            0       7     1    x0   [Ljava/lang/reflect/Type;
            0       7     2    x1   [Ljava/lang/reflect/Type;
            0       7     3    x2   Lorg/apache/commons/lang3/reflect/TypeUtils$1;

  static {};
    descriptor: ()V
    flags: (0x0008) ACC_STATIC
    Code:
      stack=1, locals=0, args_size=0
         0: iconst_0
         1: anewarray     #14                 // class java/lang/reflect/Type
         4: putstatic     #3                  // Field EMPTY_BOUNDS:[Ljava/lang/reflect/Type;
         7: return
      LineNumberTable:
        line 223: 0
}
SourceFile: "TypeUtils.java"
InnerClasses:
  private static final #27= #15 of #64;   // WildcardTypeImpl=class org/apache/commons/lang3/reflect/TypeUtils$WildcardTypeImpl of class org/apache/commons/lang3/reflect/TypeUtils
  #44;                                    // class org/apache/commons/lang3/reflect/TypeUtils$1
