Classfile /Users/mw/Projects/slang-braindump/.jar/jar11/assemble/slang-braindump/assemble/content/scala/xml/factory/XMLLoader$$anon$1.class
  Last modified May 29, 2022; size 1607 bytes
  SHA-256 checksum 763b0445ef5cc89ea8076006bc8c08146432ba0e6de6227dc4248c0c9a67d2d8
  Compiled from "XMLLoader.scala"
public final class scala.xml.factory.XMLLoader$$anon$1 extends java.lang.ThreadLocal<javax.xml.parsers.SAXParser>
  minor version: 0
  major version: 52
  flags: (0x0031) ACC_PUBLIC, ACC_FINAL, ACC_SUPER
  this_class: #2                          // scala/xml/factory/XMLLoader$$anon$1
  super_class: #5                         // java/lang/ThreadLocal
  interfaces: 0, fields: 0, methods: 3, attributes: 6
Constant pool:
   #1 = Utf8               scala/xml/factory/XMLLoader$$anon$1
   #2 = Class              #1             // scala/xml/factory/XMLLoader$$anon$1
   #3 = Utf8               Ljava/lang/ThreadLocal<Ljavax/xml/parsers/SAXParser;>;
   #4 = Utf8               java/lang/ThreadLocal
   #5 = Class              #4             // java/lang/ThreadLocal
   #6 = Utf8               XMLLoader.scala
   #7 = Utf8               scala/xml/factory/XMLLoader
   #8 = Class              #7             // scala/xml/factory/XMLLoader
   #9 = Utf8               initialValue
  #10 = Utf8               ()Ljavax/xml/parsers/SAXParser;
  #11 = Utf8               javax/xml/parsers/SAXParserFactory
  #12 = Class              #11            // javax/xml/parsers/SAXParserFactory
  #13 = Utf8               newInstance
  #14 = Utf8               ()Ljavax/xml/parsers/SAXParserFactory;
  #15 = NameAndType        #13:#14        // newInstance:()Ljavax/xml/parsers/SAXParserFactory;
  #16 = Methodref          #12.#15        // javax/xml/parsers/SAXParserFactory.newInstance:()Ljavax/xml/parsers/SAXParserFactory;
  #17 = Utf8               http://javax.xml.XMLConstants/feature/secure-processing
  #18 = String             #17            // http://javax.xml.XMLConstants/feature/secure-processing
  #19 = Utf8               setFeature
  #20 = Utf8               (Ljava/lang/String;Z)V
  #21 = NameAndType        #19:#20        // setFeature:(Ljava/lang/String;Z)V
  #22 = Methodref          #12.#21        // javax/xml/parsers/SAXParserFactory.setFeature:(Ljava/lang/String;Z)V
  #23 = Utf8               http://apache.org/xml/features/nonvalidating/load-external-dtd
  #24 = String             #23            // http://apache.org/xml/features/nonvalidating/load-external-dtd
  #25 = Utf8               http://apache.org/xml/features/disallow-doctype-decl
  #26 = String             #25            // http://apache.org/xml/features/disallow-doctype-decl
  #27 = Utf8               http://xml.org/sax/features/external-parameter-entities
  #28 = String             #27            // http://xml.org/sax/features/external-parameter-entities
  #29 = Utf8               http://xml.org/sax/features/external-general-entities
  #30 = String             #29            // http://xml.org/sax/features/external-general-entities
  #31 = Utf8               http://xml.org/sax/features/resolve-dtd-uris
  #32 = String             #31            // http://xml.org/sax/features/resolve-dtd-uris
  #33 = Utf8               setXIncludeAware
  #34 = Utf8               (Z)V
  #35 = NameAndType        #33:#34        // setXIncludeAware:(Z)V
  #36 = Methodref          #12.#35        // javax/xml/parsers/SAXParserFactory.setXIncludeAware:(Z)V
  #37 = Utf8               setNamespaceAware
  #38 = NameAndType        #37:#34        // setNamespaceAware:(Z)V
  #39 = Methodref          #12.#38        // javax/xml/parsers/SAXParserFactory.setNamespaceAware:(Z)V
  #40 = Utf8               newSAXParser
  #41 = NameAndType        #40:#10        // newSAXParser:()Ljavax/xml/parsers/SAXParser;
  #42 = Methodref          #12.#41        // javax/xml/parsers/SAXParserFactory.newSAXParser:()Ljavax/xml/parsers/SAXParser;
  #43 = Utf8               parser
  #44 = Utf8               Ljavax/xml/parsers/SAXParserFactory;
  #45 = Utf8               this
  #46 = Utf8               Lscala/xml/factory/XMLLoader$$anon$1;
  #47 = Utf8               ()Ljava/lang/Object;
  #48 = NameAndType        #9:#10         // initialValue:()Ljavax/xml/parsers/SAXParser;
  #49 = Methodref          #2.#48         // scala/xml/factory/XMLLoader$$anon$1.initialValue:()Ljavax/xml/parsers/SAXParser;
  #50 = Utf8               <init>
  #51 = Utf8               (Lscala/xml/factory/XMLLoader;)V
  #52 = Utf8               $outer
  #53 = Utf8               ()V
  #54 = NameAndType        #50:#53        // "<init>":()V
  #55 = Methodref          #5.#54         // java/lang/ThreadLocal."<init>":()V
  #56 = Utf8               Lscala/xml/factory/XMLLoader;
  #57 = Utf8               Code
  #58 = Utf8               LineNumberTable
  #59 = Utf8               LocalVariableTable
  #60 = Utf8               MethodParameters
  #61 = Utf8               InnerClasses
  #62 = Utf8               EnclosingMethod
  #63 = Utf8               Signature
  #64 = Utf8               SourceFile
  #65 = Utf8               ScalaInlineInfo
  #66 = Utf8               Scala
{
  public javax.xml.parsers.SAXParser initialValue();
    descriptor: ()Ljavax/xml/parsers/SAXParser;
    flags: (0x0001) ACC_PUBLIC
    Code:
      stack=3, locals=2, args_size=1
         0: invokestatic  #16                 // Method javax/xml/parsers/SAXParserFactory.newInstance:()Ljavax/xml/parsers/SAXParserFactory;
         3: astore_1
         4: aload_1
         5: ldc           #18                 // String http://javax.xml.XMLConstants/feature/secure-processing
         7: iconst_1
         8: invokevirtual #22                 // Method javax/xml/parsers/SAXParserFactory.setFeature:(Ljava/lang/String;Z)V
        11: aload_1
        12: ldc           #24                 // String http://apache.org/xml/features/nonvalidating/load-external-dtd
        14: iconst_0
        15: invokevirtual #22                 // Method javax/xml/parsers/SAXParserFactory.setFeature:(Ljava/lang/String;Z)V
        18: aload_1
        19: ldc           #26                 // String http://apache.org/xml/features/disallow-doctype-decl
        21: iconst_1
        22: invokevirtual #22                 // Method javax/xml/parsers/SAXParserFactory.setFeature:(Ljava/lang/String;Z)V
        25: aload_1
        26: ldc           #28                 // String http://xml.org/sax/features/external-parameter-entities
        28: iconst_0
        29: invokevirtual #22                 // Method javax/xml/parsers/SAXParserFactory.setFeature:(Ljava/lang/String;Z)V
        32: aload_1
        33: ldc           #30                 // String http://xml.org/sax/features/external-general-entities
        35: iconst_0
        36: invokevirtual #22                 // Method javax/xml/parsers/SAXParserFactory.setFeature:(Ljava/lang/String;Z)V
        39: aload_1
        40: ldc           #32                 // String http://xml.org/sax/features/resolve-dtd-uris
        42: iconst_0
        43: invokevirtual #22                 // Method javax/xml/parsers/SAXParserFactory.setFeature:(Ljava/lang/String;Z)V
        46: aload_1
        47: iconst_0
        48: invokevirtual #36                 // Method javax/xml/parsers/SAXParserFactory.setXIncludeAware:(Z)V
        51: aload_1
        52: iconst_0
        53: invokevirtual #39                 // Method javax/xml/parsers/SAXParserFactory.setNamespaceAware:(Z)V
        56: aload_1
        57: invokevirtual #42                 // Method javax/xml/parsers/SAXParserFactory.newSAXParser:()Ljavax/xml/parsers/SAXParser;
        60: areturn
      LineNumberTable:
        line 32: 0
        line 33: 4
        line 34: 11
        line 35: 18
        line 36: 25
        line 37: 32
        line 38: 39
        line 39: 46
        line 40: 51
        line 41: 56
      LocalVariableTable:
        Start  Length  Slot  Name   Signature
            4      56     1 parser   Ljavax/xml/parsers/SAXParserFactory;
            0      61     0  this   Lscala/xml/factory/XMLLoader$$anon$1;

  public java.lang.Object initialValue();
    descriptor: ()Ljava/lang/Object;
    flags: (0x1041) ACC_PUBLIC, ACC_BRIDGE, ACC_SYNTHETIC
    Code:
      stack=1, locals=1, args_size=1
         0: aload_0
         1: invokevirtual #49                 // Method initialValue:()Ljavax/xml/parsers/SAXParser;
         4: areturn
      LineNumberTable:
        line 30: 0
      LocalVariableTable:
        Start  Length  Slot  Name   Signature
            0       5     0  this   Lscala/xml/factory/XMLLoader$$anon$1;

  public scala.xml.factory.XMLLoader$$anon$1(scala.xml.factory.XMLLoader);
    descriptor: (Lscala/xml/factory/XMLLoader;)V
    flags: (0x0001) ACC_PUBLIC
    Code:
      stack=1, locals=2, args_size=2
         0: aload_0
         1: invokespecial #55                 // Method java/lang/ThreadLocal."<init>":()V
         4: return
      LineNumberTable:
        line 30: 0
      LocalVariableTable:
        Start  Length  Slot  Name   Signature
            0       5     0  this   Lscala/xml/factory/XMLLoader$$anon$1;
            0       5     1 $outer   Lscala/xml/factory/XMLLoader;
    MethodParameters:
      Name                           Flags
      $outer                         final synthetic
}
InnerClasses:
  public final #2;                        // class scala/xml/factory/XMLLoader$$anon$1
EnclosingMethod: #8.#0                  // scala.xml.factory.XMLLoader
Signature: #3                           // Ljava/lang/ThreadLocal<Ljavax/xml/parsers/SAXParser;>;
SourceFile: "XMLLoader.scala"
  ScalaInlineInfo: length = 0x13 (unknown attribute)
   01 01 00 03 00 32 00 33 01 00 09 00 2F 01 00 09
   00 0A 01
  Scala: length = 0x0 (unknown attribute)

