Classfile /Users/mw/Projects/slang-braindump/.jar/jar8/assemble/slang-braindump/assemble/content/shapeless/syntax/DynamicRecordOps.class
  Last modified May 29, 2022; size 5638 bytes
  SHA-256 checksum cf551618b40dc512a3d75d96a1dd71f93dc24747c364012f84ec9f152754df75
  Compiled from "records.scala"
public final class shapeless.syntax.DynamicRecordOps<L extends shapeless.HList> extends java.lang.Object implements scala.Dynamic, scala.Product, java.io.Serializable
  minor version: 0
  major version: 52
  flags: (0x0031) ACC_PUBLIC, ACC_FINAL, ACC_SUPER
  this_class: #2                          // shapeless/syntax/DynamicRecordOps
  super_class: #5                         // java/lang/Object
  interfaces: 3, fields: 1, methods: 17, attributes: 5
Constant pool:
    #1 = Utf8               shapeless/syntax/DynamicRecordOps
    #2 = Class              #1            // shapeless/syntax/DynamicRecordOps
    #3 = Utf8               <L::Lshapeless/HList;>Ljava/lang/Object;Lscala/Dynamic;Lscala/Product;Ljava/io/Serializable;
    #4 = Utf8               java/lang/Object
    #5 = Class              #4            // java/lang/Object
    #6 = Utf8               scala/Dynamic
    #7 = Class              #6            // scala/Dynamic
    #8 = Utf8               scala/Product
    #9 = Class              #8            // scala/Product
   #10 = Utf8               java/io/Serializable
   #11 = Class              #10           // java/io/Serializable
   #12 = Utf8               records.scala
   #13 = Utf8               Lscala/reflect/ScalaSignature;
   #14 = Utf8               bytes
   #15 = Utf8               \u0006\u0005\u0005\u001df\u0001B\f\u0019\u0005vA\u0001b\u000e\u0001\u0003\u0016\u0004%\t\u0001\u000f\u0005\t\u000b\u0002\u0011\t\u0012)A\u0005s!)a\t\u0001C\u0001\u000f\")1\n\u0001C\u0001\u0019\"9\u0011\u000fAA\u0001\n\u0003\u0011\bb\u0002=\u0001#\u0003%\t!\u001f\u0005\n\u0003\u001b\u0001\u0011\u0011!C!\u0003\u001fA\u0011\"a\b\u0001\u0003\u0003%\t!!\t\t\u0013\u0005%\u0002!!A\u0005\u0002\u0005-\u0002\"CA\u001c\u0001\u0005\u0005I\u0011IA\u001d\u0011%\t9\u0005AA\u0001\n\u0003\tI\u0005C\u0005\u0002T\u0001\t\t\u0011\"\u0011\u0002V!I\u0011\u0011\f\u0001\u0002\u0002\u0013\u0005\u00131\f\u0005\n\u0003;\u0002\u0011\u0011!C!\u0003?B\u0011\"!\u0019\u0001\u0003\u0003%\t%a\u0019\b\u0013\u0005\u001d\u0004$!A\t\u0002\u0005%d\u0001C\f\u0019\u0003\u0003E\t!a\u001b\t\r\u0019\u000bB\u0011AA<\u0011%\ti&EA\u0001\n\u000b\ny\u0006C\u0005\u0002zE\t\t\u0011\"!\u0002|!I\u0011qQ\t\u0002\u0002\u0013\u0005\u0015\u0011\u0012\u0005\n\u0003;\u000b\u0012\u0011!C\u0005\u0003?\u0013\u0001\u0003R=oC6L7MU3d_J$w\n]:\u000b\u0005eQ\u0012AB:z]R\f\u0007PC\u0001\u001c\u0003%\u0019\b.\u00199fY\u0016\u001c8o\u0001\u0001\u0016\u0005yY4#\u0002\u0001 K!Z\u0003C\u0001\u0011$\u001b\u0005\t#\"\u0001\u0012\u0002\u000bM\u001c\u0017\r\\1\n\u0005\u0011\n#AB!osJ+g\r\u0005\u0002!M%\u0011q%\t\u0002\b\tft\u0017-\\5d!\t\u0001\u0013&\u0003\u0002+C\t9\u0001K]8ek\u000e$\bC\u0001\u00175\u001d\ti#G\u0004\u0002/c5\tqF\u0003\u000219\u00051AH]8pizJ\u0011AI\u0005\u0003g\u0005\nq\u0001]1dW\u0006<W-\u0003\u00026m\ta1+\u001a:jC2L\'0\u00192mK*\u00111\'I\u0001\u0002YV\t\u0011\b\u0005\u0002;w1\u0001A!\u0002\u001f\u0001\u0005\u0004i$!\u0001\'\u0012\u0005y\n\u0005C\u0001\u0011@\u0013\t\u0001\u0015EA\u0004O_RD\u0017N\\4\u0011\u0005\t\u001bU\"\u0001\u000e\n\u0005\u0011S\"!\u0002%MSN$\u0018A\u00017!\u0003\u0019a\u0014N\\5u}Q\u0011\u0001J\u0013\t\u0004\u0013\u0002IT\"\u0001\r\t\u000b]\u001a\u0001\u0019A\u001d\u0002\u001bM,G.Z2u\tft\u0017-\\5d)\tiU\r\u0006\u0002O!B\u0011qj\u001c\b\u0003uACQ!\u0015\u0003A\u0004I\u000b\u0001b]3mK\u000e$xN\u001d\t\u0005\'bK$,D\u0001U\u0015\t)f+\u0001\u0004sK\u000e|\'\u000f\u001a\u0006\u0003/j\t1a\u001c9t\u0013\tIFK\u0001\u0005TK2,7\r^8s!\u0011Yf,\u00193\u000f\u0005\tc\u0016BA/\u001b\u0003\r!\u0018mZ\u0005\u0003?\u0002\u0014a\u0001J1uI\u0005$(BA/\u001b!\t\u0001#-\u0003\u0002dC\t11+_7c_2t!AO3\t\u000b\u0019$\u0001\u0019A4\u0002\u0007-,\u0017\u0010\u0005\u0002iY:\u0011\u0011N\u001b\t\u0003]\u0005J!a[\u0011\u0002\rA\u0013X\rZ3g\u0013\tigN\u0001\u0004TiJLgn\u001a\u0006\u0003W\u0006J!\u0001\u001d-\u0003\u0007=+H/\u0001\u0003d_BLXCA:w)\t!x\u000fE\u0002J\u0001U\u0004\"A\u000f<\u0005\u000bq*!\u0019A\u001f\t\u000f]*\u0001\u0013!a\u0001k\u0006q1m\u001c9zI\u0011,g-Y;mi\u0012\nTc\u0001>\u0002\fU\t1P\u000b\u0002:y.\nQ\u0010E\u0002\u007f\u0003\u000fi\u0011a \u0006\u0005\u0003\u0003\t\u0019!A\u0005v]\u000eDWmY6fI*\u0019\u0011QA\u0011\u0002\u0015\u0005tgn\u001c;bi&|g.C\u0002\u0002\n}\u0014\u0011#\u001e8dQ\u0016\u001c7.\u001a3WCJL\u0017M\\2f\t\u0015adA1\u0001>\u00035\u0001(o\u001c3vGR\u0004&/\u001a4jqV\u0011\u0011\u0011\u0003\t\u0005\u0003\'\ti\"\u0004\u0002\u0002\u0016)!\u0011qCA\r\u0003\u0011a\u0017M\\4\u000b\u0005\u0005m\u0011\u0001\u00026bm\u0006L1!\\A\u000b\u00031\u0001(o\u001c3vGR\f%/\u001b;z+\t\t\u0019\u0003E\u0002!\u0003KI1!a\n\"\u0005\rIe\u000e^\u0001\u000faJ|G-^2u\u000b2,W.\u001a8u)\u0011\ti#a\r\u0011\u0007\u0001\ny#C\u0002\u00022\u0005\u00121!\u00118z\u0011%\t)$CA\u0001\u0002\u0004\t\u0019#A\u0002yIE\nq\u0002\u001d:pIV\u001cG/\u0013;fe\u0006$xN]\u000b\u0003\u0003w\u0001b!!\u0010\u0002D\u00055RBAA \u0015\r\t\t%I\u0001\u000bG>dG.Z2uS>t\u0017\u0002BA#\u0003\u007f\u0011\u0001\"\u0013;fe\u0006$xN]\u0001\tG\u0006tW)];bYR!\u00111JA)!\r\u0001\u0013QJ\u0005\u0004\u0003\u001f\n#a\u0002\"p_2,\u0017M\u001c\u0005\n\u0003kY\u0011\u0011!a\u0001\u0003[\t!\u0003\u001d:pIV\u001cG/\u00127f[\u0016tGOT1nKR!\u0011\u0011CA,\u0011%\t)\u0004DA\u0001\u0002\u0004\t\u0019#\u0001\u0005iCND7i\u001c3f)\t\t\u0019#\u0001\u0005u_N#(/\u001b8h)\t\t\t\"\u0001\u0004fcV\fGn\u001d\u000b\u0005\u0003\u0017\n)\u0007C\u0005\u00026=\t\t\u00111\u0001\u0002.\u0005\u0001B)\u001f8b[&\u001c\'+Z2pe\u0012|\u0005o\u001d\t\u0003\u0013F\u0019B!E\u0010\u0002nA!\u0011qNA;\u001b\t\t\tH\u0003\u0003\u0002t\u0005e\u0011AA5p\u0013\r)\u0014\u0011\u000f\u000b\u0003\u0003S\nQ!\u00199qYf,B!! \u0002\u0004R!\u0011qPAC!\u0011I\u0005!!!\u0011\u0007i\n\u0019\tB\u0003=)\t\u0007Q\b\u0003\u00048)\u0001\u0007\u0011\u0011Q\u0001\bk:\f\u0007\u000f\u001d7z+\u0011\tY)!&\u0015\t\u00055\u0015q\u0013\t\u0006A\u0005=\u00151S\u0005\u0004\u0003#\u000b#AB(qi&|g\u000eE\u0002;\u0003+#Q\u0001P\u000bC\u0002uB\u0011\"!\'\u0016\u0003\u0003\u0005\r!a\'\u0002\u0007a$\u0003\u0007\u0005\u0003J\u0001\u0005M\u0015\u0001D<sSR,\'+\u001a9mC\u000e,GCAAQ!\u0011\t\u0019\"a)\n\t\u0005\u0015\u0016Q\u0003\u0002\u0007\u001f\nTWm\u0019;
   #16 = Utf8               l
   #17 = Utf8               Lshapeless/HList;
   #18 = Utf8               TL;
   #19 = Utf8               unapply
   #20 = Utf8               (Lshapeless/syntax/DynamicRecordOps;)Lscala/Option;
   #21 = Utf8               <L::Lshapeless/HList;>(Lshapeless/syntax/DynamicRecordOps<TL;>;)Lscala/Option<TL;>;
   #22 = Utf8               x$0
   #23 = Utf8               shapeless/syntax/DynamicRecordOps$
   #24 = Class              #23           // shapeless/syntax/DynamicRecordOps$
   #25 = Utf8               MODULE$
   #26 = Utf8               Lshapeless/syntax/DynamicRecordOps$;
   #27 = NameAndType        #25:#26       // MODULE$:Lshapeless/syntax/DynamicRecordOps$;
   #28 = Fieldref           #24.#27       // shapeless/syntax/DynamicRecordOps$.MODULE$:Lshapeless/syntax/DynamicRecordOps$;
   #29 = NameAndType        #19:#20       // unapply:(Lshapeless/syntax/DynamicRecordOps;)Lscala/Option;
   #30 = Methodref          #24.#29       // shapeless/syntax/DynamicRecordOps$.unapply:(Lshapeless/syntax/DynamicRecordOps;)Lscala/Option;
   #31 = Utf8               apply
   #32 = Utf8               (Lshapeless/HList;)Lshapeless/syntax/DynamicRecordOps;
   #33 = Utf8               <L::Lshapeless/HList;>(TL;)Lshapeless/syntax/DynamicRecordOps<TL;>;
   #34 = NameAndType        #31:#32       // apply:(Lshapeless/HList;)Lshapeless/syntax/DynamicRecordOps;
   #35 = Methodref          #24.#34       // shapeless/syntax/DynamicRecordOps$.apply:(Lshapeless/HList;)Lshapeless/syntax/DynamicRecordOps;
   #36 = Utf8               productElementNames
   #37 = Utf8               ()Lscala/collection/Iterator;
   #38 = Utf8               ()Lscala/collection/Iterator<Ljava/lang/String;>;
   #39 = Utf8               productElementNames$
   #40 = Utf8               (Lscala/Product;)Lscala/collection/Iterator;
   #41 = NameAndType        #39:#40       // productElementNames$:(Lscala/Product;)Lscala/collection/Iterator;
   #42 = InterfaceMethodref #9.#41        // scala/Product.productElementNames$:(Lscala/Product;)Lscala/collection/Iterator;
   #43 = Utf8               this
   #44 = Utf8               Lshapeless/syntax/DynamicRecordOps;
   #45 = Utf8               ()Lshapeless/HList;
   #46 = Utf8               ()TL;
   #47 = NameAndType        #16:#17       // l:Lshapeless/HList;
   #48 = Fieldref           #2.#47        // shapeless/syntax/DynamicRecordOps.l:Lshapeless/HList;
   #49 = Utf8               selectDynamic
   #50 = Utf8               (Ljava/lang/String;Lshapeless/ops/record/Selector;)Ljava/lang/Object;
   #51 = Utf8               (Ljava/lang/String;Lshapeless/ops/record/Selector<TL;Lscala/Symbol;>;)Ljava/lang/Object;
   #52 = Utf8               key
   #53 = Utf8               selector
   #54 = NameAndType        #16:#45       // l:()Lshapeless/HList;
   #55 = Methodref          #2.#54        // shapeless/syntax/DynamicRecordOps.l:()Lshapeless/HList;
   #56 = Utf8               shapeless/ops/record/Selector
   #57 = Class              #56           // shapeless/ops/record/Selector
   #58 = Utf8               (Lshapeless/HList;)Ljava/lang/Object;
   #59 = NameAndType        #31:#58       // apply:(Lshapeless/HList;)Ljava/lang/Object;
   #60 = InterfaceMethodref #57.#59       // shapeless/ops/record/Selector.apply:(Lshapeless/HList;)Ljava/lang/Object;
   #61 = Utf8               Ljava/lang/String;
   #62 = Utf8               Lshapeless/ops/record/Selector;
   #63 = Utf8               copy
   #64 = Utf8               <init>
   #65 = Utf8               (Lshapeless/HList;)V
   #66 = NameAndType        #64:#65       // "<init>":(Lshapeless/HList;)V
   #67 = Methodref          #2.#66        // shapeless/syntax/DynamicRecordOps."<init>":(Lshapeless/HList;)V
   #68 = Utf8               copy$default$1
   #69 = Utf8               <L::Lshapeless/HList;>()TL;
   #70 = Utf8               productPrefix
   #71 = Utf8               ()Ljava/lang/String;
   #72 = Utf8               DynamicRecordOps
   #73 = String             #72           // DynamicRecordOps
   #74 = Utf8               productArity
   #75 = Utf8               ()I
   #76 = Utf8               productElement
   #77 = Utf8               (I)Ljava/lang/Object;
   #78 = Utf8               x$1
   #79 = Utf8               scala/runtime/Statics
   #80 = Class              #79           // scala/runtime/Statics
   #81 = Utf8               ioobe
   #82 = NameAndType        #81:#77       // ioobe:(I)Ljava/lang/Object;
   #83 = Methodref          #80.#82       // scala/runtime/Statics.ioobe:(I)Ljava/lang/Object;
   #84 = Utf8               I
   #85 = Utf8               productIterator
   #86 = Utf8               ()Lscala/collection/Iterator<Ljava/lang/Object;>;
   #87 = Utf8               scala/runtime/ScalaRunTime$
   #88 = Class              #87           // scala/runtime/ScalaRunTime$
   #89 = Utf8               Lscala/runtime/ScalaRunTime$;
   #90 = NameAndType        #25:#89       // MODULE$:Lscala/runtime/ScalaRunTime$;
   #91 = Fieldref           #88.#90       // scala/runtime/ScalaRunTime$.MODULE$:Lscala/runtime/ScalaRunTime$;
   #92 = Utf8               typedProductIterator
   #93 = NameAndType        #92:#40       // typedProductIterator:(Lscala/Product;)Lscala/collection/Iterator;
   #94 = Methodref          #88.#93       // scala/runtime/ScalaRunTime$.typedProductIterator:(Lscala/Product;)Lscala/collection/Iterator;
   #95 = Utf8               canEqual
   #96 = Utf8               (Ljava/lang/Object;)Z
   #97 = Utf8               Ljava/lang/Object;
   #98 = Utf8               productElementName
   #99 = Utf8               (I)Ljava/lang/String;
  #100 = String             #16           // l
  #101 = Utf8               java/lang/String
  #102 = Class              #101          // java/lang/String
  #103 = Utf8               hashCode
  #104 = Utf8               _hashCode
  #105 = Utf8               (Lscala/Product;)I
  #106 = NameAndType        #104:#105     // _hashCode:(Lscala/Product;)I
  #107 = Methodref          #88.#106      // scala/runtime/ScalaRunTime$._hashCode:(Lscala/Product;)I
  #108 = Utf8               toString
  #109 = Utf8               _toString
  #110 = Utf8               (Lscala/Product;)Ljava/lang/String;
  #111 = NameAndType        #109:#110     // _toString:(Lscala/Product;)Ljava/lang/String;
  #112 = Methodref          #88.#111      // scala/runtime/ScalaRunTime$._toString:(Lscala/Product;)Ljava/lang/String;
  #113 = Utf8               equals
  #114 = NameAndType        #113:#96      // equals:(Ljava/lang/Object;)Z
  #115 = Methodref          #5.#114       // java/lang/Object.equals:(Ljava/lang/Object;)Z
  #116 = Utf8               shapeless/HList
  #117 = Class              #116          // shapeless/HList
  #118 = Utf8               (TL;)V
  #119 = Utf8               ()V
  #120 = NameAndType        #64:#119      // "<init>":()V
  #121 = Methodref          #5.#120       // java/lang/Object."<init>":()V
  #122 = Utf8               $init$
  #123 = Utf8               (Lscala/Product;)V
  #124 = NameAndType        #122:#123     // $init$:(Lscala/Product;)V
  #125 = InterfaceMethodref #9.#124       // scala/Product.$init$:(Lscala/Product;)V
  #126 = Utf8               Signature
  #127 = Utf8               Code
  #128 = Utf8               MethodParameters
  #129 = Utf8               LineNumberTable
  #130 = Utf8               LocalVariableTable
  #131 = Utf8               StackMapTable
  #132 = Utf8               SourceFile
  #133 = Utf8               RuntimeVisibleAnnotations
  #134 = Utf8               ScalaInlineInfo
  #135 = Utf8               ScalaSig
{
  private final L l;
    descriptor: Lshapeless/HList;
    flags: (0x0012) ACC_PRIVATE, ACC_FINAL
    Signature: #18                          // TL;

  public static <L extends shapeless.HList> scala.Option<L> unapply(shapeless.syntax.DynamicRecordOps<L>);
    descriptor: (Lshapeless/syntax/DynamicRecordOps;)Lscala/Option;
    flags: (0x0009) ACC_PUBLIC, ACC_STATIC
    Code:
      stack=2, locals=1, args_size=1
         0: getstatic     #28                 // Field shapeless/syntax/DynamicRecordOps$.MODULE$:Lshapeless/syntax/DynamicRecordOps$;
         3: aload_0
         4: invokevirtual #30                 // Method shapeless/syntax/DynamicRecordOps$.unapply:(Lshapeless/syntax/DynamicRecordOps;)Lscala/Option;
         7: areturn
    Signature: #21                          // <L::Lshapeless/HList;>(Lshapeless/syntax/DynamicRecordOps<TL;>;)Lscala/Option<TL;>;
    MethodParameters:
      Name                           Flags
      x$0                            final

  public static <L extends shapeless.HList> shapeless.syntax.DynamicRecordOps<L> apply(L);
    descriptor: (Lshapeless/HList;)Lshapeless/syntax/DynamicRecordOps;
    flags: (0x0009) ACC_PUBLIC, ACC_STATIC
    Code:
      stack=2, locals=1, args_size=1
         0: getstatic     #28                 // Field shapeless/syntax/DynamicRecordOps$.MODULE$:Lshapeless/syntax/DynamicRecordOps$;
         3: aload_0
         4: invokevirtual #35                 // Method shapeless/syntax/DynamicRecordOps$.apply:(Lshapeless/HList;)Lshapeless/syntax/DynamicRecordOps;
         7: areturn
    Signature: #33                          // <L::Lshapeless/HList;>(TL;)Lshapeless/syntax/DynamicRecordOps<TL;>;
    MethodParameters:
      Name                           Flags
      l                              final

  public scala.collection.Iterator<java.lang.String> productElementNames();
    descriptor: ()Lscala/collection/Iterator;
    flags: (0x0001) ACC_PUBLIC
    Code:
      stack=1, locals=1, args_size=1
         0: aload_0
         1: invokestatic  #42                 // InterfaceMethod scala/Product.productElementNames$:(Lscala/Product;)Lscala/collection/Iterator;
         4: areturn
      LineNumberTable:
        line 161: 0
      LocalVariableTable:
        Start  Length  Slot  Name   Signature
            0       5     0  this   Lshapeless/syntax/DynamicRecordOps;
    Signature: #38                          // ()Lscala/collection/Iterator<Ljava/lang/String;>;

  public L l();
    descriptor: ()Lshapeless/HList;
    flags: (0x0001) ACC_PUBLIC
    Code:
      stack=1, locals=1, args_size=1
         0: aload_0
         1: getfield      #48                 // Field l:Lshapeless/HList;
         4: areturn
      LineNumberTable:
        line 161: 0
      LocalVariableTable:
        Start  Length  Slot  Name   Signature
            0       5     0  this   Lshapeless/syntax/DynamicRecordOps;
    Signature: #46                          // ()TL;

  public java.lang.Object selectDynamic(java.lang.String, shapeless.ops.record.Selector<L, scala.Symbol>);
    descriptor: (Ljava/lang/String;Lshapeless/ops/record/Selector;)Ljava/lang/Object;
    flags: (0x0001) ACC_PUBLIC
    Code:
      stack=2, locals=4, args_size=3
         0: aload_2
         1: astore_3
         2: aload_3
         3: aload_0
         4: invokevirtual #55                 // Method l:()Lshapeless/HList;
         7: invokeinterface #60,  2           // InterfaceMethod shapeless/ops/record/Selector.apply:(Lshapeless/HList;)Ljava/lang/Object;
        12: areturn
      LineNumberTable:
        line 167: 0
      LocalVariableTable:
        Start  Length  Slot  Name   Signature
            0      13     0  this   Lshapeless/syntax/DynamicRecordOps;
            0      13     1   key   Ljava/lang/String;
            0      13     2 selector   Lshapeless/ops/record/Selector;
    Signature: #51                          // (Ljava/lang/String;Lshapeless/ops/record/Selector<TL;Lscala/Symbol;>;)Ljava/lang/Object;
    MethodParameters:
      Name                           Flags
      key                            final
      selector                       final

  public <L extends shapeless.HList> shapeless.syntax.DynamicRecordOps<L> copy(L);
    descriptor: (Lshapeless/HList;)Lshapeless/syntax/DynamicRecordOps;
    flags: (0x0001) ACC_PUBLIC
    Code:
      stack=3, locals=2, args_size=2
         0: new           #2                  // class shapeless/syntax/DynamicRecordOps
         3: dup
         4: aload_1
         5: invokespecial #67                 // Method "<init>":(Lshapeless/HList;)V
         8: areturn
      LineNumberTable:
        line 161: 0
      LocalVariableTable:
        Start  Length  Slot  Name   Signature
            0       9     0  this   Lshapeless/syntax/DynamicRecordOps;
            0       9     1     l   Lshapeless/HList;
    Signature: #33                          // <L::Lshapeless/HList;>(TL;)Lshapeless/syntax/DynamicRecordOps<TL;>;
    MethodParameters:
      Name                           Flags
      l                              final

  public <L extends shapeless.HList> L copy$default$1();
    descriptor: ()Lshapeless/HList;
    flags: (0x0001) ACC_PUBLIC
    Code:
      stack=1, locals=1, args_size=1
         0: aload_0
         1: invokevirtual #55                 // Method l:()Lshapeless/HList;
         4: areturn
      LineNumberTable:
        line 161: 0
      LocalVariableTable:
        Start  Length  Slot  Name   Signature
            0       5     0  this   Lshapeless/syntax/DynamicRecordOps;
    Signature: #69                          // <L::Lshapeless/HList;>()TL;

  public java.lang.String productPrefix();
    descriptor: ()Ljava/lang/String;
    flags: (0x0001) ACC_PUBLIC
    Code:
      stack=1, locals=1, args_size=1
         0: ldc           #73                 // String DynamicRecordOps
         2: areturn
      LineNumberTable:
        line 161: 0
      LocalVariableTable:
        Start  Length  Slot  Name   Signature
            0       3     0  this   Lshapeless/syntax/DynamicRecordOps;

  public int productArity();
    descriptor: ()I
    flags: (0x0001) ACC_PUBLIC
    Code:
      stack=1, locals=1, args_size=1
         0: iconst_1
         1: ireturn
      LineNumberTable:
        line 161: 0
      LocalVariableTable:
        Start  Length  Slot  Name   Signature
            0       2     0  this   Lshapeless/syntax/DynamicRecordOps;

  public java.lang.Object productElement(int);
    descriptor: (I)Ljava/lang/Object;
    flags: (0x0001) ACC_PUBLIC
    Code:
      stack=1, locals=3, args_size=2
         0: iload_1
         1: istore_2
         2: iload_2
         3: tableswitch   { // 0 to 0
                       0: 20
                 default: 27
            }
        20: aload_0
        21: invokevirtual #55                 // Method l:()Lshapeless/HList;
        24: goto          34
        27: iload_1
        28: invokestatic  #83                 // Method scala/runtime/Statics.ioobe:(I)Ljava/lang/Object;
        31: goto          34
        34: areturn
      StackMapTable: number_of_entries = 3
        frame_type = 252 /* append */
          offset_delta = 20
          locals = [ int ]
        frame_type = 6 /* same */
        frame_type = 70 /* same_locals_1_stack_item */
          stack = [ class java/lang/Object ]
      LineNumberTable:
        line 161: 0
      LocalVariableTable:
        Start  Length  Slot  Name   Signature
            0      35     0  this   Lshapeless/syntax/DynamicRecordOps;
            0      35     1   x$1   I
    MethodParameters:
      Name                           Flags
      x$1                            final

  public scala.collection.Iterator<java.lang.Object> productIterator();
    descriptor: ()Lscala/collection/Iterator;
    flags: (0x0001) ACC_PUBLIC
    Code:
      stack=2, locals=1, args_size=1
         0: getstatic     #91                 // Field scala/runtime/ScalaRunTime$.MODULE$:Lscala/runtime/ScalaRunTime$;
         3: aload_0
         4: invokevirtual #94                 // Method scala/runtime/ScalaRunTime$.typedProductIterator:(Lscala/Product;)Lscala/collection/Iterator;
         7: areturn
      LineNumberTable:
        line 161: 0
      LocalVariableTable:
        Start  Length  Slot  Name   Signature
            0       8     0  this   Lshapeless/syntax/DynamicRecordOps;
    Signature: #86                          // ()Lscala/collection/Iterator<Ljava/lang/Object;>;

  public boolean canEqual(java.lang.Object);
    descriptor: (Ljava/lang/Object;)Z
    flags: (0x0001) ACC_PUBLIC
    Code:
      stack=1, locals=2, args_size=2
         0: aload_1
         1: instanceof    #2                  // class shapeless/syntax/DynamicRecordOps
         4: ireturn
      LineNumberTable:
        line 161: 0
      LocalVariableTable:
        Start  Length  Slot  Name   Signature
            0       5     0  this   Lshapeless/syntax/DynamicRecordOps;
            0       5     1   x$1   Ljava/lang/Object;
    MethodParameters:
      Name                           Flags
      x$1                            final

  public java.lang.String productElementName(int);
    descriptor: (I)Ljava/lang/String;
    flags: (0x0001) ACC_PUBLIC
    Code:
      stack=1, locals=3, args_size=2
         0: iload_1
         1: istore_2
         2: iload_2
         3: tableswitch   { // 0 to 0
                       0: 20
                 default: 25
            }
        20: ldc           #100                // String l
        22: goto          35
        25: iload_1
        26: invokestatic  #83                 // Method scala/runtime/Statics.ioobe:(I)Ljava/lang/Object;
        29: checkcast     #102                // class java/lang/String
        32: goto          35
        35: areturn
      StackMapTable: number_of_entries = 3
        frame_type = 252 /* append */
          offset_delta = 20
          locals = [ int ]
        frame_type = 4 /* same */
        frame_type = 73 /* same_locals_1_stack_item */
          stack = [ class java/lang/String ]
      LineNumberTable:
        line 161: 0
      LocalVariableTable:
        Start  Length  Slot  Name   Signature
            0      36     0  this   Lshapeless/syntax/DynamicRecordOps;
            0      36     1   x$1   I
    MethodParameters:
      Name                           Flags
      x$1                            final

  public int hashCode();
    descriptor: ()I
    flags: (0x0001) ACC_PUBLIC
    Code:
      stack=2, locals=1, args_size=1
         0: getstatic     #91                 // Field scala/runtime/ScalaRunTime$.MODULE$:Lscala/runtime/ScalaRunTime$;
         3: aload_0
         4: invokevirtual #107                // Method scala/runtime/ScalaRunTime$._hashCode:(Lscala/Product;)I
         7: ireturn
      LineNumberTable:
        line 161: 0
      LocalVariableTable:
        Start  Length  Slot  Name   Signature
            0       8     0  this   Lshapeless/syntax/DynamicRecordOps;

  public java.lang.String toString();
    descriptor: ()Ljava/lang/String;
    flags: (0x0001) ACC_PUBLIC
    Code:
      stack=2, locals=1, args_size=1
         0: getstatic     #91                 // Field scala/runtime/ScalaRunTime$.MODULE$:Lscala/runtime/ScalaRunTime$;
         3: aload_0
         4: invokevirtual #112                // Method scala/runtime/ScalaRunTime$._toString:(Lscala/Product;)Ljava/lang/String;
         7: areturn
      LineNumberTable:
        line 161: 0
      LocalVariableTable:
        Start  Length  Slot  Name   Signature
            0       8     0  this   Lshapeless/syntax/DynamicRecordOps;

  public boolean equals(java.lang.Object);
    descriptor: (Ljava/lang/Object;)Z
    flags: (0x0001) ACC_PUBLIC
    Code:
      stack=2, locals=6, args_size=2
         0: aload_0
         1: aload_1
         2: if_acmpeq     77
         5: aload_1
         6: astore_3
         7: aload_3
         8: instanceof    #2                  // class shapeless/syntax/DynamicRecordOps
        11: ifeq          19
        14: iconst_1
        15: istore_2
        16: goto          27
        19: goto          22
        22: iconst_0
        23: istore_2
        24: goto          27
        27: iload_2
        28: ifeq          81
        31: aload_1
        32: checkcast     #2                  // class shapeless/syntax/DynamicRecordOps
        35: astore        4
        37: aload_0
        38: invokevirtual #55                 // Method l:()Lshapeless/HList;
        41: aload         4
        43: invokevirtual #55                 // Method l:()Lshapeless/HList;
        46: astore        5
        48: dup
        49: ifnonnull     61
        52: pop
        53: aload         5
        55: ifnull        69
        58: goto          73
        61: aload         5
        63: invokevirtual #115                // Method java/lang/Object.equals:(Ljava/lang/Object;)Z
        66: ifeq          73
        69: iconst_1
        70: goto          74
        73: iconst_0
        74: ifeq          81
        77: iconst_1
        78: goto          82
        81: iconst_0
        82: ireturn
      StackMapTable: number_of_entries = 10
        frame_type = 253 /* append */
          offset_delta = 19
          locals = [ top, class java/lang/Object ]
        frame_type = 2 /* same */
        frame_type = 255 /* full_frame */
          offset_delta = 4
          locals = [ class shapeless/syntax/DynamicRecordOps, class java/lang/Object, int, class java/lang/Object ]
          stack = []
        frame_type = 255 /* full_frame */
          offset_delta = 33
          locals = [ class shapeless/syntax/DynamicRecordOps, class java/lang/Object, int, class java/lang/Object, class shapeless/syntax/DynamicRecordOps, class shapeless/HList ]
          stack = [ class shapeless/HList ]
        frame_type = 7 /* same */
        frame_type = 3 /* same */
        frame_type = 64 /* same_locals_1_stack_item */
          stack = [ int ]
        frame_type = 255 /* full_frame */
          offset_delta = 2
          locals = [ class shapeless/syntax/DynamicRecordOps, class java/lang/Object ]
          stack = []
        frame_type = 253 /* append */
          offset_delta = 3
          locals = [ int, class java/lang/Object ]
        frame_type = 255 /* full_frame */
          offset_delta = 0
          locals = [ class shapeless/syntax/DynamicRecordOps, class java/lang/Object ]
          stack = [ int ]
      LineNumberTable:
        line 161: 0
      LocalVariableTable:
        Start  Length  Slot  Name   Signature
            0      83     0  this   Lshapeless/syntax/DynamicRecordOps;
            0      83     1   x$1   Ljava/lang/Object;
    MethodParameters:
      Name                           Flags
      x$1                            final

  public shapeless.syntax.DynamicRecordOps(L);
    descriptor: (Lshapeless/HList;)V
    flags: (0x0001) ACC_PUBLIC
    Code:
      stack=2, locals=2, args_size=2
         0: aload_0
         1: aload_1
         2: putfield      #48                 // Field l:Lshapeless/HList;
         5: aload_0
         6: invokespecial #121                // Method java/lang/Object."<init>":()V
         9: aload_0
        10: invokestatic  #125                // InterfaceMethod scala/Product.$init$:(Lscala/Product;)V
        13: return
      LineNumberTable:
        line 161: 0
      LocalVariableTable:
        Start  Length  Slot  Name   Signature
            0      14     0  this   Lshapeless/syntax/DynamicRecordOps;
            0      14     1     l   Lshapeless/HList;
    Signature: #118                         // (TL;)V
    MethodParameters:
      Name                           Flags
      l                              final
}
Signature: #3                           // <L::Lshapeless/HList;>Ljava/lang/Object;Lscala/Dynamic;Lscala/Product;Ljava/io/Serializable;
SourceFile: "records.scala"
RuntimeVisibleAnnotations:
  0: #13(#14=s#15)
    scala.reflect.ScalaSignature(
      bytes="\u0006\u0005\u0005\u001df\u0001B\f\u0019\u0005vA\u0001b\u000e\u0001\u0003\u0016\u0004%\t\u0001\u000f\u0005\t\u000b\u0002\u0011\t\u0012)A\u0005s!)a\t\u0001C\u0001\u000f\")1\n\u0001C\u0001\u0019\"9\u0011\u000fAA\u0001\n\u0003\u0011\bb\u0002=\u0001#\u0003%\t!\u001f\u0005\n\u0003\u001b\u0001\u0011\u0011!C!\u0003\u001fA\u0011\"a\b\u0001\u0003\u0003%\t!!\t\t\u0013\u0005%\u0002!!A\u0005\u0002\u0005-\u0002\"CA\u001c\u0001\u0005\u0005I\u0011IA\u001d\u0011%\t9\u0005AA\u0001\n\u0003\tI\u0005C\u0005\u0002T\u0001\t\t\u0011\"\u0011\u0002V!I\u0011\u0011\f\u0001\u0002\u0002\u0013\u0005\u00131\f\u0005\n\u0003;\u0002\u0011\u0011!C!\u0003?B\u0011\"!\u0019\u0001\u0003\u0003%\t%a\u0019\b\u0013\u0005\u001d\u0004$!A\t\u0002\u0005%d\u0001C\f\u0019\u0003\u0003E\t!a\u001b\t\r\u0019\u000bB\u0011AA<\u0011%\ti&EA\u0001\n\u000b\ny\u0006C\u0005\u0002zE\t\t\u0011\"!\u0002|!I\u0011qQ\t\u0002\u0002\u0013\u0005\u0015\u0011\u0012\u0005\n\u0003;\u000b\u0012\u0011!C\u0005\u0003?\u0013\u0001\u0003R=oC6L7MU3d_J$w\n]:\u000b\u0005eQ\u0012AB:z]R\f\u0007PC\u0001\u001c\u0003%\u0019\b.\u00199fY\u0016\u001c8o\u0001\u0001\u0016\u0005yY4#\u0002\u0001 K!Z\u0003C\u0001\u0011$\u001b\u0005\t#\"\u0001\u0012\u0002\u000bM\u001c\u0017\r\\1\n\u0005\u0011\n#AB!osJ+g\r\u0005\u0002!M%\u0011q%\t\u0002\b\tft\u0017-\\5d!\t\u0001\u0013&\u0003\u0002+C\t9\u0001K]8ek\u000e$\bC\u0001\u00175\u001d\ti#G\u0004\u0002/c5\tqF\u0003\u000219\u00051AH]8pizJ\u0011AI\u0005\u0003g\u0005\nq\u0001]1dW\u0006<W-\u0003\u00026m\ta1+\u001a:jC2L\'0\u00192mK*\u00111\'I\u0001\u0002YV\t\u0011\b\u0005\u0002;w1\u0001A!\u0002\u001f\u0001\u0005\u0004i$!\u0001\'\u0012\u0005y\n\u0005C\u0001\u0011@\u0013\t\u0001\u0015EA\u0004O_RD\u0017N\\4\u0011\u0005\t\u001bU\"\u0001\u000e\n\u0005\u0011S\"!\u0002%MSN$\u0018A\u00017!\u0003\u0019a\u0014N\\5u}Q\u0011\u0001J\u0013\t\u0004\u0013\u0002IT\"\u0001\r\t\u000b]\u001a\u0001\u0019A\u001d\u0002\u001bM,G.Z2u\tft\u0017-\\5d)\tiU\r\u0006\u0002O!B\u0011qj\u001c\b\u0003uACQ!\u0015\u0003A\u0004I\u000b\u0001b]3mK\u000e$xN\u001d\t\u0005\'bK$,D\u0001U\u0015\t)f+\u0001\u0004sK\u000e|\'\u000f\u001a\u0006\u0003/j\t1a\u001c9t\u0013\tIFK\u0001\u0005TK2,7\r^8s!\u0011Yf,\u00193\u000f\u0005\tc\u0016BA/\u001b\u0003\r!\u0018mZ\u0005\u0003?\u0002\u0014a\u0001J1uI\u0005$(BA/\u001b!\t\u0001#-\u0003\u0002dC\t11+_7c_2t!AO3\t\u000b\u0019$\u0001\u0019A4\u0002\u0007-,\u0017\u0010\u0005\u0002iY:\u0011\u0011N\u001b\t\u0003]\u0005J!a[\u0011\u0002\rA\u0013X\rZ3g\u0013\tigN\u0001\u0004TiJLgn\u001a\u0006\u0003W\u0006J!\u0001\u001d-\u0003\u0007=+H/\u0001\u0003d_BLXCA:w)\t!x\u000fE\u0002J\u0001U\u0004\"A\u000f<\u0005\u000bq*!\u0019A\u001f\t\u000f]*\u0001\u0013!a\u0001k\u0006q1m\u001c9zI\u0011,g-Y;mi\u0012\nTc\u0001>\u0002\fU\t1P\u000b\u0002:y.\nQ\u0010E\u0002\u007f\u0003\u000fi\u0011a \u0006\u0005\u0003\u0003\t\u0019!A\u0005v]\u000eDWmY6fI*\u0019\u0011QA\u0011\u0002\u0015\u0005tgn\u001c;bi&|g.C\u0002\u0002\n}\u0014\u0011#\u001e8dQ\u0016\u001c7.\u001a3WCJL\u0017M\\2f\t\u0015adA1\u0001>\u00035\u0001(o\u001c3vGR\u0004&/\u001a4jqV\u0011\u0011\u0011\u0003\t\u0005\u0003\'\ti\"\u0004\u0002\u0002\u0016)!\u0011qCA\r\u0003\u0011a\u0017M\\4\u000b\u0005\u0005m\u0011\u0001\u00026bm\u0006L1!\\A\u000b\u00031\u0001(o\u001c3vGR\f%/\u001b;z+\t\t\u0019\u0003E\u0002!\u0003KI1!a\n\"\u0005\rIe\u000e^\u0001\u000faJ|G-^2u\u000b2,W.\u001a8u)\u0011\ti#a\r\u0011\u0007\u0001\ny#C\u0002\u00022\u0005\u00121!\u00118z\u0011%\t)$CA\u0001\u0002\u0004\t\u0019#A\u0002yIE\nq\u0002\u001d:pIV\u001cG/\u0013;fe\u0006$xN]\u000b\u0003\u0003w\u0001b!!\u0010\u0002D\u00055RBAA \u0015\r\t\t%I\u0001\u000bG>dG.Z2uS>t\u0017\u0002BA#\u0003\u007f\u0011\u0001\"\u0013;fe\u0006$xN]\u0001\tG\u0006tW)];bYR!\u00111JA)!\r\u0001\u0013QJ\u0005\u0004\u0003\u001f\n#a\u0002\"p_2,\u0017M\u001c\u0005\n\u0003kY\u0011\u0011!a\u0001\u0003[\t!\u0003\u001d:pIV\u001cG/\u00127f[\u0016tGOT1nKR!\u0011\u0011CA,\u0011%\t)\u0004DA\u0001\u0002\u0004\t\u0019#\u0001\u0005iCND7i\u001c3f)\t\t\u0019#\u0001\u0005u_N#(/\u001b8h)\t\t\t\"\u0001\u0004fcV\fGn\u001d\u000b\u0005\u0003\u0017\n)\u0007C\u0005\u00026=\t\t\u00111\u0001\u0002.\u0005\u0001B)\u001f8b[&\u001c\'+Z2pe\u0012|\u0005o\u001d\t\u0003\u0013F\u0019B!E\u0010\u0002nA!\u0011qNA;\u001b\t\t\tH\u0003\u0003\u0002t\u0005e\u0011AA5p\u0013\r)\u0014\u0011\u000f\u000b\u0003\u0003S\nQ!\u00199qYf,B!! \u0002\u0004R!\u0011qPAC!\u0011I\u0005!!!\u0011\u0007i\n\u0019\tB\u0003=)\t\u0007Q\b\u0003\u00048)\u0001\u0007\u0011\u0011Q\u0001\bk:\f\u0007\u000f\u001d7z+\u0011\tY)!&\u0015\t\u00055\u0015q\u0013\t\u0006A\u0005=\u00151S\u0005\u0004\u0003#\u000b#AB(qi&|g\u000eE\u0002;\u0003+#Q\u0001P\u000bC\u0002uB\u0011\"!\'\u0016\u0003\u0003\u0005\r!a\'\u0002\u0007a$\u0003\u0007\u0005\u0003J\u0001\u0005M\u0015\u0001D<sSR,\'+\u001a9mC\u000e,GCAAQ!\u0011\t\u0019\"a)\n\t\u0005\u0015\u0016Q\u0003\u0002\u0007\u001f\nTWm\u0019;"
    )
  ScalaInlineInfo: length = 0x4F (unknown attribute)
   01 01 00 0F 00 40 00 41 01 00 5F 00 60 01 00 44
   00 2D 01 00 3F 00 20 01 00 71 00 60 01 00 67 00
   4B 01 00 10 00 2D 01 00 4A 00 4B 01 00 4C 00 4D
   01 00 62 00 63 01 00 24 00 25 01 00 55 00 25 01
   00 46 00 47 01 00 31 00 32 01 00 6C 00 47 01
  ScalaSig: length = 0x3 (unknown attribute)
   05 02 00
