Classfile /Users/mw/Projects/slang-braindump/.jar/jar8/assemble/slang-braindump/assemble/content/shapeless/syntax/DynamicUnionOps$.class
  Last modified May 29, 2022; size 1628 bytes
  SHA-256 checksum a6b4d00b7577c1dc519a4599979b43f8e0f1c5fd8f68f3be1a0083387f54ea20
  Compiled from "unions.scala"
public final class shapeless.syntax.DynamicUnionOps$ implements java.io.Serializable
  minor version: 0
  major version: 52
  flags: (0x0031) ACC_PUBLIC, ACC_FINAL, ACC_SUPER
  this_class: #2                          // shapeless/syntax/DynamicUnionOps$
  super_class: #4                         // java/lang/Object
  interfaces: 1, fields: 1, methods: 6, attributes: 3
Constant pool:
   #1 = Utf8               shapeless/syntax/DynamicUnionOps$
   #2 = Class              #1             // shapeless/syntax/DynamicUnionOps$
   #3 = Utf8               java/lang/Object
   #4 = Class              #3             // java/lang/Object
   #5 = Utf8               java/io/Serializable
   #6 = Class              #5             // java/io/Serializable
   #7 = Utf8               unions.scala
   #8 = Utf8               MODULE$
   #9 = Utf8               Lshapeless/syntax/DynamicUnionOps$;
  #10 = Utf8               <clinit>
  #11 = Utf8               ()V
  #12 = Utf8               <init>
  #13 = NameAndType        #12:#11        // "<init>":()V
  #14 = Methodref          #2.#13         // shapeless/syntax/DynamicUnionOps$."<init>":()V
  #15 = NameAndType        #8:#9          // MODULE$:Lshapeless/syntax/DynamicUnionOps$;
  #16 = Fieldref           #2.#15         // shapeless/syntax/DynamicUnionOps$.MODULE$:Lshapeless/syntax/DynamicUnionOps$;
  #17 = Utf8               toString
  #18 = Utf8               ()Ljava/lang/String;
  #19 = Utf8               DynamicUnionOps
  #20 = String             #19            // DynamicUnionOps
  #21 = Utf8               this
  #22 = Utf8               apply
  #23 = Utf8               (Lshapeless/Coproduct;)Lshapeless/syntax/DynamicUnionOps;
  #24 = Utf8               <C::Lshapeless/Coproduct;>(TC;)Lshapeless/syntax/DynamicUnionOps<TC;>;
  #25 = Utf8               c
  #26 = Utf8               shapeless/syntax/DynamicUnionOps
  #27 = Class              #26            // shapeless/syntax/DynamicUnionOps
  #28 = Utf8               (Lshapeless/Coproduct;)V
  #29 = NameAndType        #12:#28        // "<init>":(Lshapeless/Coproduct;)V
  #30 = Methodref          #27.#29        // shapeless/syntax/DynamicUnionOps."<init>":(Lshapeless/Coproduct;)V
  #31 = Utf8               Lshapeless/Coproduct;
  #32 = Utf8               unapply
  #33 = Utf8               (Lshapeless/syntax/DynamicUnionOps;)Lscala/Option;
  #34 = Utf8               <C::Lshapeless/Coproduct;>(Lshapeless/syntax/DynamicUnionOps<TC;>;)Lscala/Option<TC;>;
  #35 = Utf8               x$0
  #36 = Utf8               scala/None$
  #37 = Class              #36            // scala/None$
  #38 = Utf8               Lscala/None$;
  #39 = NameAndType        #8:#38         // MODULE$:Lscala/None$;
  #40 = Fieldref           #37.#39        // scala/None$.MODULE$:Lscala/None$;
  #41 = Utf8               scala/Some
  #42 = Class              #41            // scala/Some
  #43 = Utf8               ()Lshapeless/Coproduct;
  #44 = NameAndType        #25:#43        // c:()Lshapeless/Coproduct;
  #45 = Methodref          #27.#44        // shapeless/syntax/DynamicUnionOps.c:()Lshapeless/Coproduct;
  #46 = Utf8               (Ljava/lang/Object;)V
  #47 = NameAndType        #12:#46        // "<init>":(Ljava/lang/Object;)V
  #48 = Methodref          #42.#47        // scala/Some."<init>":(Ljava/lang/Object;)V
  #49 = Utf8               Lshapeless/syntax/DynamicUnionOps;
  #50 = Utf8               scala/Option
  #51 = Class              #50            // scala/Option
  #52 = Utf8               writeReplace
  #53 = Utf8               ()Ljava/lang/Object;
  #54 = Utf8               scala/runtime/ModuleSerializationProxy
  #55 = Class              #54            // scala/runtime/ModuleSerializationProxy
  #56 = Utf8               (Ljava/lang/Class;)V
  #57 = NameAndType        #12:#56        // "<init>":(Ljava/lang/Class;)V
  #58 = Methodref          #55.#57        // scala/runtime/ModuleSerializationProxy."<init>":(Ljava/lang/Class;)V
  #59 = Methodref          #4.#13         // java/lang/Object."<init>":()V
  #60 = Utf8               Code
  #61 = Utf8               LineNumberTable
  #62 = Utf8               LocalVariableTable
  #63 = Utf8               Signature
  #64 = Utf8               MethodParameters
  #65 = Utf8               StackMapTable
  #66 = Utf8               SourceFile
  #67 = Utf8               ScalaInlineInfo
  #68 = Utf8               Scala
{
  public static final shapeless.syntax.DynamicUnionOps$ MODULE$;
    descriptor: Lshapeless/syntax/DynamicUnionOps$;
    flags: (0x0019) ACC_PUBLIC, ACC_STATIC, ACC_FINAL

  public static {};
    descriptor: ()V
    flags: (0x0009) ACC_PUBLIC, ACC_STATIC
    Code:
      stack=2, locals=0, args_size=0
         0: new           #2                  // class shapeless/syntax/DynamicUnionOps$
         3: dup
         4: invokespecial #14                 // Method "<init>":()V
         7: putstatic     #16                 // Field MODULE$:Lshapeless/syntax/DynamicUnionOps$;
        10: return
      LineNumberTable:
        line 84: 0

  public final java.lang.String toString();
    descriptor: ()Ljava/lang/String;
    flags: (0x0011) ACC_PUBLIC, ACC_FINAL
    Code:
      stack=1, locals=1, args_size=1
         0: ldc           #20                 // String DynamicUnionOps
         2: areturn
      LineNumberTable:
        line 84: 0
      LocalVariableTable:
        Start  Length  Slot  Name   Signature
            0       3     0  this   Lshapeless/syntax/DynamicUnionOps$;

  public <C extends shapeless.Coproduct> shapeless.syntax.DynamicUnionOps<C> apply(C);
    descriptor: (Lshapeless/Coproduct;)Lshapeless/syntax/DynamicUnionOps;
    flags: (0x0001) ACC_PUBLIC
    Code:
      stack=3, locals=2, args_size=2
         0: new           #27                 // class shapeless/syntax/DynamicUnionOps
         3: dup
         4: aload_1
         5: invokespecial #30                 // Method shapeless/syntax/DynamicUnionOps."<init>":(Lshapeless/Coproduct;)V
         8: areturn
      LineNumberTable:
        line 84: 0
      LocalVariableTable:
        Start  Length  Slot  Name   Signature
            0       9     0  this   Lshapeless/syntax/DynamicUnionOps$;
            0       9     1     c   Lshapeless/Coproduct;
    Signature: #24                          // <C::Lshapeless/Coproduct;>(TC;)Lshapeless/syntax/DynamicUnionOps<TC;>;
    MethodParameters:
      Name                           Flags
      c                              final

  public <C extends shapeless.Coproduct> scala.Option<C> unapply(shapeless.syntax.DynamicUnionOps<C>);
    descriptor: (Lshapeless/syntax/DynamicUnionOps;)Lscala/Option;
    flags: (0x0001) ACC_PUBLIC
    Code:
      stack=3, locals=2, args_size=2
         0: aload_1
         1: ifnonnull     10
         4: getstatic     #40                 // Field scala/None$.MODULE$:Lscala/None$;
         7: goto          21
        10: new           #42                 // class scala/Some
        13: dup
        14: aload_1
        15: invokevirtual #45                 // Method shapeless/syntax/DynamicUnionOps.c:()Lshapeless/Coproduct;
        18: invokespecial #48                 // Method scala/Some."<init>":(Ljava/lang/Object;)V
        21: areturn
      StackMapTable: number_of_entries = 2
        frame_type = 10 /* same */
        frame_type = 74 /* same_locals_1_stack_item */
          stack = [ class scala/Option ]
      LineNumberTable:
        line 84: 0
      LocalVariableTable:
        Start  Length  Slot  Name   Signature
            0      22     0  this   Lshapeless/syntax/DynamicUnionOps$;
            0      22     1   x$0   Lshapeless/syntax/DynamicUnionOps;
    Signature: #34                          // <C::Lshapeless/Coproduct;>(Lshapeless/syntax/DynamicUnionOps<TC;>;)Lscala/Option<TC;>;
    MethodParameters:
      Name                           Flags
      x$0                            final

  private java.lang.Object writeReplace();
    descriptor: ()Ljava/lang/Object;
    flags: (0x0002) ACC_PRIVATE
    Code:
      stack=3, locals=1, args_size=1
         0: new           #55                 // class scala/runtime/ModuleSerializationProxy
         3: dup
         4: ldc           #2                  // class shapeless/syntax/DynamicUnionOps$
         6: invokespecial #58                 // Method scala/runtime/ModuleSerializationProxy."<init>":(Ljava/lang/Class;)V
         9: areturn
      LineNumberTable:
        line 84: 0
      LocalVariableTable:
        Start  Length  Slot  Name   Signature
            0      10     0  this   Lshapeless/syntax/DynamicUnionOps$;

  private shapeless.syntax.DynamicUnionOps$();
    descriptor: ()V
    flags: (0x0002) ACC_PRIVATE
    Code:
      stack=1, locals=1, args_size=1
         0: aload_0
         1: invokespecial #59                 // Method java/lang/Object."<init>":()V
         4: return
      LineNumberTable:
        line 84: 0
      LocalVariableTable:
        Start  Length  Slot  Name   Signature
            0       5     0  this   Lshapeless/syntax/DynamicUnionOps$;
}
SourceFile: "unions.scala"
  ScalaInlineInfo: length = 0x1D (unknown attribute)
   01 01 00 05 00 0C 00 0B 01 00 16 00 17 01 00 11
   00 12 01 00 20 00 21 01 00 34 00 35 01
  Scala: length = 0x0 (unknown attribute)

