Classfile /Users/mw/Projects/slang-braindump/.jar/jar8/assemble/slang-braindump/assemble/content/shapeless/syntax/inject.class
  Last modified May 29, 2022; size 1755 bytes
  SHA-256 checksum 390eab0f9c42670a0f723bb3e53600da9aba9a9c9df049e832c77f15ecd6d87e
  Compiled from "inject.scala"
public final class shapeless.syntax.inject
  minor version: 0
  major version: 52
  flags: (0x0031) ACC_PUBLIC, ACC_FINAL, ACC_SUPER
  this_class: #2                          // shapeless/syntax/inject
  super_class: #4                         // java/lang/Object
  interfaces: 0, fields: 0, methods: 1, attributes: 4
Constant pool:
   #1 = Utf8               shapeless/syntax/inject
   #2 = Class              #1             // shapeless/syntax/inject
   #3 = Utf8               java/lang/Object
   #4 = Class              #3             // java/lang/Object
   #5 = Utf8               inject.scala
   #6 = Utf8               Lscala/reflect/ScalaSignature;
   #7 = Utf8               bytes
   #8 = Utf8               \u0006\u0005\u0005\rs!B\n\u0015\u0011\u0003Ib!B\u000e\u0015\u0011\u0003a\u0002\"B\u0012\u0002\t\u0003!c\u0001B\u0013\u0002\u0007\u0019B\u0001bK\u0002\u0003\u0006\u0004%\t\u0001\f\u0005\tq\r\u0011\t\u0011)A\u0005[!)1e\u0001C\u0001s!)1c\u0001C\u0001{!)Ak\u0001C\u0001+\"9\u0011mAA\u0001\n\u0003\u0012\u0007b\u00024\u0004\u0003\u0003%\te\u001a\u0005\b[\u0006\t\t\u0011b\u0001o\u000f\u001di\u0017!!A\t\u0002Q4q!J\u0001\u0002\u0002#\u0005Q\u000fC\u0003$\u001b\u0011\u0005a\u000fC\u0003x\u001b\u0011\u0015\u0001\u0010C\u0004\u0002\n5!)!a\u0003\t\u0013\u0005\rR\"!A\u0005\u0006\u0005\u0015\u0002\"CA\u0019\u001b\u0005\u0005IQAA\u001a\u0003\u0019IgN[3di*\u0011QCF\u0001\u0007gftG/\u0019=\u000b\u0003]\t\u0011b\u001d5ba\u0016dWm]:\u0004\u0001A\u0011!$A\u0007\u0002)\t1\u0011N\u001c6fGR\u001c\"!A\u000f\u0011\u0005y\tS\"A\u0010\u000b\u0003\u0001\nQa]2bY\u0006L!AI\u0010\u0003\r\u0005s\u0017PU3g\u0003\u0019a\u0014N\\5u}Q\t\u0011D\u0001\u0007J]*,7\r^*z]R\f\u00070\u0006\u0002(_M\u00111\u0001\u000b\t\u0003=%J!AK\u0010\u0003\r\u0005s\u0017PV1m\u0003\u0005!X#A\u0017\u0011\u00059zC\u0002\u0001\u0003\u0006a\r\u0011\r!\r\u0002\u0002)F\u0011!\'\u000e\t\u0003=MJ!\u0001N\u0010\u0003\u000f9{G\u000f[5oOB\u0011aDN\u0005\u0003o}\u00111!\u00118z\u0003\t!\b\u0005\u0006\u0002;yA\u00191hA\u0017\u000e\u0003\u0005AQa\u000b\u0004A\u00025*\"A\u0010!\u0015\u0005}:\u0005C\u0001\u0018A\t\u0015\tuA1\u0001C\u0005\u0005\u0019\u0015C\u0001\u001aD!\t!U)D\u0001\u0017\u0013\t1eCA\u0005D_B\u0014x\u000eZ;di\")\u0001j\u0002a\u0002\u0013\u0006\u0019\u0011N\u001c6\u0011\t)\u000bv(\f\b\u0003\u0017:s!\u0001\u0012\'\n\u000553\u0012aA8qg&\u0011q\nU\u0001\nG>\u0004(o\u001c3vGRT!!\u0014\f\n\u0005I\u001b&AB%oU\u0016\u001cGO\u0003\u0002P!\u0006i!/\u001e8uS6,\u0017J\u001c6fGR,\"AV.\u0015\u0005]c\u0006c\u0001\u0010Y5&\u0011\u0011l\b\u0002\u0007\u001fB$\u0018n\u001c8\u0011\u00059ZF!B!\t\u0005\u0004\u0011\u0005\"B/\t\u0001\bq\u0016\u0001\u0002:J]*\u00042AS0[\u0013\t\u00017KA\u0007Sk:$\u0018.\\3J]*,7\r^\u0001\tQ\u0006\u001c\bnQ8eKR\t1\r\u0005\u0002\u001fI&\u0011Qm\b\u0002\u0004\u0013:$\u0018AB3rk\u0006d7\u000f\u0006\u0002iWB\u0011a$[\u0005\u0003U~\u0011qAQ8pY\u0016\fg\u000eC\u0004m\u0015\u0005\u0005\t\u0019A\u001b\u0002\u0007a$\u0013\'\u0001\u0007J]*,7\r^*z]R\f\u00070\u0006\u0002peR\u0011\u0001o\u001d\t\u0004w\r\t\bC\u0001\u0018s\t\u0015\u00014B1\u00012\u0011\u0015Y3\u00021\u0001r!\tYTb\u0005\u0002\u000e;Q\tA/\u0001\tj]*,7\r\u001e\u0013fqR,gn]5p]V!\u0011\u0010`A\u0001)\rQ\u00181\u0001\u000b\u0003wv\u0004\"A\f?\u0005\u000b\u0005{!\u0019\u0001\"\t\u000b!{\u00019\u0001@\u0011\t)\u000b6p \t\u0004]\u0005\u0005A!\u0002\u0019\u0010\u0005\u0004\t\u0004bBA\u0003\u001f\u0001\u0007\u0011qA\u0001\u0006IQD\u0017n\u001d\t\u0004w\ry\u0018a\u0006:v]RLW.Z%oU\u0016\u001cG\u000fJ3yi\u0016t7/[8o+\u0019\ti!!\u0006\u0002\"Q!\u0011qBA\u000e)\u0011\t\t\"a\u0006\u0011\tyA\u00161\u0003\t\u0004]\u0005UA!B!\u0011\u0005\u0004\u0011\u0005BB/\u0011\u0001\b\tI\u0002\u0005\u0003K?\u0006M\u0001bBA\u0003!\u0001\u0007\u0011Q\u0004\t\u0005w\r\ty\u0002E\u0002/\u0003C!Q\u0001\r\tC\u0002E\n!\u0003[1tQ\u000e{G-\u001a\u0013fqR,gn]5p]V!\u0011qEA\u0018)\r\u0011\u0017\u0011\u0006\u0005\b\u0003\u000b\t\u0002\u0019AA\u0016!\u0011Y4!!\f\u0011\u00079\ny\u0003B\u00031#\t\u0007\u0011\'\u0001\tfcV\fGn\u001d\u0013fqR,gn]5p]V!\u0011QGA!)\u0011\t9$a\u000f\u0015\u0007!\fI\u0004C\u0004m%\u0005\u0005\t\u0019A\u001b\t\u000f\u0005\u0015!\u00031\u0001\u0002>A!1hAA !\rq\u0013\u0011\t\u0003\u0006aI\u0011\r!\r
   #9 = Utf8               shapeless/syntax/inject$InjectSyntax
  #10 = Class              #9             // shapeless/syntax/inject$InjectSyntax
  #11 = Utf8               InjectSyntax
  #12 = Utf8               shapeless/syntax/inject$InjectSyntax$
  #13 = Class              #12            // shapeless/syntax/inject$InjectSyntax$
  #14 = Utf8               InjectSyntax$
  #15 = Utf8               (Ljava/lang/Object;)Ljava/lang/Object;
  #16 = Utf8               t
  #17 = Utf8               shapeless/syntax/inject$
  #18 = Class              #17            // shapeless/syntax/inject$
  #19 = Utf8               MODULE$
  #20 = Utf8               Lshapeless/syntax/inject$;
  #21 = NameAndType        #19:#20        // MODULE$:Lshapeless/syntax/inject$;
  #22 = Fieldref           #18.#21        // shapeless/syntax/inject$.MODULE$:Lshapeless/syntax/inject$;
  #23 = NameAndType        #11:#15        // InjectSyntax:(Ljava/lang/Object;)Ljava/lang/Object;
  #24 = Methodref          #18.#23        // shapeless/syntax/inject$.InjectSyntax:(Ljava/lang/Object;)Ljava/lang/Object;
  #25 = Utf8               Code
  #26 = Utf8               MethodParameters
  #27 = Utf8               InnerClasses
  #28 = Utf8               SourceFile
  #29 = Utf8               RuntimeVisibleAnnotations
  #30 = Utf8               ScalaSig
{
  public static java.lang.Object InjectSyntax(java.lang.Object);
    descriptor: (Ljava/lang/Object;)Ljava/lang/Object;
    flags: (0x0009) ACC_PUBLIC, ACC_STATIC
    Code:
      stack=2, locals=1, args_size=1
         0: getstatic     #22                 // Field shapeless/syntax/inject$.MODULE$:Lshapeless/syntax/inject$;
         3: aload_0
         4: invokevirtual #24                 // Method shapeless/syntax/inject$.InjectSyntax:(Ljava/lang/Object;)Ljava/lang/Object;
         7: areturn
    MethodParameters:
      Name                           Flags
      t                              final
}
InnerClasses:
  public static final #11= #10 of #2;     // InjectSyntax=class shapeless/syntax/inject$InjectSyntax of class shapeless/syntax/inject
  public static #14= #13 of #2;           // InjectSyntax$=class shapeless/syntax/inject$InjectSyntax$ of class shapeless/syntax/inject
SourceFile: "inject.scala"
RuntimeVisibleAnnotations:
  0: #6(#7=s#8)
    scala.reflect.ScalaSignature(
      bytes="\u0006\u0005\u0005\rs!B\n\u0015\u0011\u0003Ib!B\u000e\u0015\u0011\u0003a\u0002\"B\u0012\u0002\t\u0003!c\u0001B\u0013\u0002\u0007\u0019B\u0001bK\u0002\u0003\u0006\u0004%\t\u0001\f\u0005\tq\r\u0011\t\u0011)A\u0005[!)1e\u0001C\u0001s!)1c\u0001C\u0001{!)Ak\u0001C\u0001+\"9\u0011mAA\u0001\n\u0003\u0012\u0007b\u00024\u0004\u0003\u0003%\te\u001a\u0005\b[\u0006\t\t\u0011b\u0001o\u000f\u001di\u0017!!A\t\u0002Q4q!J\u0001\u0002\u0002#\u0005Q\u000fC\u0003$\u001b\u0011\u0005a\u000fC\u0003x\u001b\u0011\u0015\u0001\u0010C\u0004\u0002\n5!)!a\u0003\t\u0013\u0005\rR\"!A\u0005\u0006\u0005\u0015\u0002\"CA\u0019\u001b\u0005\u0005IQAA\u001a\u0003\u0019IgN[3di*\u0011QCF\u0001\u0007gftG/\u0019=\u000b\u0003]\t\u0011b\u001d5ba\u0016dWm]:\u0004\u0001A\u0011!$A\u0007\u0002)\t1\u0011N\u001c6fGR\u001c\"!A\u000f\u0011\u0005y\tS\"A\u0010\u000b\u0003\u0001\nQa]2bY\u0006L!AI\u0010\u0003\r\u0005s\u0017PU3g\u0003\u0019a\u0014N\\5u}Q\t\u0011D\u0001\u0007J]*,7\r^*z]R\f\u00070\u0006\u0002(_M\u00111\u0001\u000b\t\u0003=%J!AK\u0010\u0003\r\u0005s\u0017PV1m\u0003\u0005!X#A\u0017\u0011\u00059zC\u0002\u0001\u0003\u0006a\r\u0011\r!\r\u0002\u0002)F\u0011!\'\u000e\t\u0003=MJ!\u0001N\u0010\u0003\u000f9{G\u000f[5oOB\u0011aDN\u0005\u0003o}\u00111!\u00118z\u0003\t!\b\u0005\u0006\u0002;yA\u00191hA\u0017\u000e\u0003\u0005AQa\u000b\u0004A\u00025*\"A\u0010!\u0015\u0005}:\u0005C\u0001\u0018A\t\u0015\tuA1\u0001C\u0005\u0005\u0019\u0015C\u0001\u001aD!\t!U)D\u0001\u0017\u0013\t1eCA\u0005D_B\u0014x\u000eZ;di\")\u0001j\u0002a\u0002\u0013\u0006\u0019\u0011N\u001c6\u0011\t)\u000bv(\f\b\u0003\u0017:s!\u0001\u0012\'\n\u000553\u0012aA8qg&\u0011q\nU\u0001\nG>\u0004(o\u001c3vGRT!!\u0014\f\n\u0005I\u001b&AB%oU\u0016\u001cGO\u0003\u0002P!\u0006i!/\u001e8uS6,\u0017J\u001c6fGR,\"AV.\u0015\u0005]c\u0006c\u0001\u0010Y5&\u0011\u0011l\b\u0002\u0007\u001fB$\u0018n\u001c8\u0011\u00059ZF!B!\t\u0005\u0004\u0011\u0005\"B/\t\u0001\bq\u0016\u0001\u0002:J]*\u00042AS0[\u0013\t\u00017KA\u0007Sk:$\u0018.\\3J]*,7\r^\u0001\tQ\u0006\u001c\bnQ8eKR\t1\r\u0005\u0002\u001fI&\u0011Qm\b\u0002\u0004\u0013:$\u0018AB3rk\u0006d7\u000f\u0006\u0002iWB\u0011a$[\u0005\u0003U~\u0011qAQ8pY\u0016\fg\u000eC\u0004m\u0015\u0005\u0005\t\u0019A\u001b\u0002\u0007a$\u0013\'\u0001\u0007J]*,7\r^*z]R\f\u00070\u0006\u0002peR\u0011\u0001o\u001d\t\u0004w\r\t\bC\u0001\u0018s\t\u0015\u00014B1\u00012\u0011\u0015Y3\u00021\u0001r!\tYTb\u0005\u0002\u000e;Q\tA/\u0001\tj]*,7\r\u001e\u0013fqR,gn]5p]V!\u0011\u0010`A\u0001)\rQ\u00181\u0001\u000b\u0003wv\u0004\"A\f?\u0005\u000b\u0005{!\u0019\u0001\"\t\u000b!{\u00019\u0001@\u0011\t)\u000b6p \t\u0004]\u0005\u0005A!\u0002\u0019\u0010\u0005\u0004\t\u0004bBA\u0003\u001f\u0001\u0007\u0011qA\u0001\u0006IQD\u0017n\u001d\t\u0004w\ry\u0018a\u0006:v]RLW.Z%oU\u0016\u001cG\u000fJ3yi\u0016t7/[8o+\u0019\ti!!\u0006\u0002\"Q!\u0011qBA\u000e)\u0011\t\t\"a\u0006\u0011\tyA\u00161\u0003\t\u0004]\u0005UA!B!\u0011\u0005\u0004\u0011\u0005BB/\u0011\u0001\b\tI\u0002\u0005\u0003K?\u0006M\u0001bBA\u0003!\u0001\u0007\u0011Q\u0004\t\u0005w\r\ty\u0002E\u0002/\u0003C!Q\u0001\r\tC\u0002E\n!\u0003[1tQ\u000e{G-\u001a\u0013fqR,gn]5p]V!\u0011qEA\u0018)\r\u0011\u0017\u0011\u0006\u0005\b\u0003\u000b\t\u0002\u0019AA\u0016!\u0011Y4!!\f\u0011\u00079\ny\u0003B\u00031#\t\u0007\u0011\'\u0001\tfcV\fGn\u001d\u0013fqR,gn]5p]V!\u0011QGA!)\u0011\t9$a\u000f\u0015\u0007!\fI\u0004C\u0004m%\u0005\u0005\t\u0019A\u001b\t\u000f\u0005\u0015!\u00031\u0001\u0002>A!1hAA !\rq\u0013\u0011\t\u0003\u0006aI\u0011\r!\r"
    )
  ScalaSig: length = 0x3 (unknown attribute)
   05 02 00
