Classfile /Users/mw/Projects/slang-braindump/.jar/jar8/assemble/slang-braindump/assemble/content/shapeless/syntax/inject$InjectSyntax$.class
  Last modified May 29, 2022; size 2274 bytes
  SHA-256 checksum 0bc260ec274bc92cc3521ad3ffa50d20f80add02c9288b05712716754cd16d15
  Compiled from "inject.scala"
public class shapeless.syntax.inject$InjectSyntax$
  minor version: 0
  major version: 52
  flags: (0x0021) ACC_PUBLIC, ACC_SUPER
  this_class: #2                          // shapeless/syntax/inject$InjectSyntax$
  super_class: #4                         // java/lang/Object
  interfaces: 0, fields: 1, methods: 6, attributes: 4
Constant pool:
   #1 = Utf8               shapeless/syntax/inject$InjectSyntax$
   #2 = Class              #1             // shapeless/syntax/inject$InjectSyntax$
   #3 = Utf8               java/lang/Object
   #4 = Class              #3             // java/lang/Object
   #5 = Utf8               inject.scala
   #6 = Utf8               shapeless/ops/coproduct$Inject
   #7 = Class              #6             // shapeless/ops/coproduct$Inject
   #8 = Utf8               shapeless/ops/coproduct
   #9 = Class              #8             // shapeless/ops/coproduct
  #10 = Utf8               Inject
  #11 = Utf8               shapeless/ops/coproduct$RuntimeInject
  #12 = Class              #11            // shapeless/ops/coproduct$RuntimeInject
  #13 = Utf8               RuntimeInject
  #14 = Utf8               shapeless/syntax/inject$InjectSyntax
  #15 = Class              #14            // shapeless/syntax/inject$InjectSyntax
  #16 = Utf8               shapeless/syntax/inject
  #17 = Class              #16            // shapeless/syntax/inject
  #18 = Utf8               InjectSyntax
  #19 = Utf8               InjectSyntax$
  #20 = Utf8               MODULE$
  #21 = Utf8               Lshapeless/syntax/inject$InjectSyntax$;
  #22 = Utf8               <clinit>
  #23 = Utf8               ()V
  #24 = Utf8               <init>
  #25 = NameAndType        #24:#23        // "<init>":()V
  #26 = Methodref          #2.#25         // shapeless/syntax/inject$InjectSyntax$."<init>":()V
  #27 = NameAndType        #20:#21        // MODULE$:Lshapeless/syntax/inject$InjectSyntax$;
  #28 = Fieldref           #2.#27         // shapeless/syntax/inject$InjectSyntax$.MODULE$:Lshapeless/syntax/inject$InjectSyntax$;
  #29 = Utf8               inject$extension
  #30 = Utf8               (Ljava/lang/Object;Lshapeless/ops/coproduct$Inject;)Lshapeless/Coproduct;
  #31 = Utf8               <C::Lshapeless/Coproduct;T:Ljava/lang/Object;>(TT;Lshapeless/ops/coproduct$Inject<TC;TT;>;)TC;
  #32 = Utf8               $this
  #33 = Utf8               inj
  #34 = Utf8               apply
  #35 = Utf8               (Ljava/lang/Object;)Lshapeless/Coproduct;
  #36 = NameAndType        #34:#35        // apply:(Ljava/lang/Object;)Lshapeless/Coproduct;
  #37 = InterfaceMethodref #7.#36         // shapeless/ops/coproduct$Inject.apply:(Ljava/lang/Object;)Lshapeless/Coproduct;
  #38 = Utf8               this
  #39 = Utf8               Ljava/lang/Object;
  #40 = Utf8               Lshapeless/ops/coproduct$Inject;
  #41 = Utf8               runtimeInject$extension
  #42 = Utf8               (Ljava/lang/Object;Lshapeless/ops/coproduct$RuntimeInject;)Lscala/Option;
  #43 = Utf8               <C::Lshapeless/Coproduct;T:Ljava/lang/Object;>(TT;Lshapeless/ops/coproduct$RuntimeInject<TC;>;)Lscala/Option<TC;>;
  #44 = Utf8               rInj
  #45 = Utf8               (Ljava/lang/Object;)Lscala/Option;
  #46 = NameAndType        #34:#45        // apply:(Ljava/lang/Object;)Lscala/Option;
  #47 = InterfaceMethodref #12.#46        // shapeless/ops/coproduct$RuntimeInject.apply:(Ljava/lang/Object;)Lscala/Option;
  #48 = Utf8               Lshapeless/ops/coproduct$RuntimeInject;
  #49 = Utf8               hashCode$extension
  #50 = Utf8               (Ljava/lang/Object;)I
  #51 = Utf8               <T:Ljava/lang/Object;>(TT;)I
  #52 = Utf8               hashCode
  #53 = Utf8               ()I
  #54 = NameAndType        #52:#53        // hashCode:()I
  #55 = Methodref          #4.#54         // java/lang/Object.hashCode:()I
  #56 = Utf8               equals$extension
  #57 = Utf8               (Ljava/lang/Object;Ljava/lang/Object;)Z
  #58 = Utf8               <T:Ljava/lang/Object;>(TT;Ljava/lang/Object;)Z
  #59 = Utf8               x$1
  #60 = Utf8               t
  #61 = Utf8               ()Ljava/lang/Object;
  #62 = NameAndType        #60:#61        // t:()Ljava/lang/Object;
  #63 = Methodref          #15.#62        // shapeless/syntax/inject$InjectSyntax.t:()Ljava/lang/Object;
  #64 = Utf8               scala/runtime/BoxesRunTime
  #65 = Class              #64            // scala/runtime/BoxesRunTime
  #66 = Utf8               equals
  #67 = NameAndType        #66:#57        // equals:(Ljava/lang/Object;Ljava/lang/Object;)Z
  #68 = Methodref          #65.#67        // scala/runtime/BoxesRunTime.equals:(Ljava/lang/Object;Ljava/lang/Object;)Z
  #69 = Methodref          #4.#25         // java/lang/Object."<init>":()V
  #70 = Utf8               Code
  #71 = Utf8               LineNumberTable
  #72 = Utf8               LocalVariableTable
  #73 = Utf8               Signature
  #74 = Utf8               MethodParameters
  #75 = Utf8               StackMapTable
  #76 = Utf8               InnerClasses
  #77 = Utf8               SourceFile
  #78 = Utf8               ScalaInlineInfo
  #79 = Utf8               Scala
{
  public static final shapeless.syntax.inject$InjectSyntax$ MODULE$;
    descriptor: Lshapeless/syntax/inject$InjectSyntax$;
    flags: (0x0019) ACC_PUBLIC, ACC_STATIC, ACC_FINAL

  public static {};
    descriptor: ()V
    flags: (0x0009) ACC_PUBLIC, ACC_STATIC
    Code:
      stack=2, locals=0, args_size=0
         0: new           #2                  // class shapeless/syntax/inject$InjectSyntax$
         3: dup
         4: invokespecial #26                 // Method "<init>":()V
         7: putstatic     #28                 // Field MODULE$:Lshapeless/syntax/inject$InjectSyntax$;
        10: return
      LineNumberTable:
        line 26: 0

  public final <C extends shapeless.Coproduct, T extends java.lang.Object> C inject$extension(T, shapeless.ops.coproduct$Inject<C, T>);
    descriptor: (Ljava/lang/Object;Lshapeless/ops/coproduct$Inject;)Lshapeless/Coproduct;
    flags: (0x0011) ACC_PUBLIC, ACC_FINAL
    Code:
      stack=2, locals=3, args_size=3
         0: aload_2
         1: aload_1
         2: invokeinterface #37,  2           // InterfaceMethod shapeless/ops/coproduct$Inject.apply:(Ljava/lang/Object;)Lshapeless/Coproduct;
         7: areturn
      LineNumberTable:
        line 31: 0
      LocalVariableTable:
        Start  Length  Slot  Name   Signature
            0       8     0  this   Lshapeless/syntax/inject$InjectSyntax$;
            0       8     1 $this   Ljava/lang/Object;
            0       8     2   inj   Lshapeless/ops/coproduct$Inject;
    Signature: #31                          // <C::Lshapeless/Coproduct;T:Ljava/lang/Object;>(TT;Lshapeless/ops/coproduct$Inject<TC;TT;>;)TC;
    MethodParameters:
      Name                           Flags
      $this                          final
      inj                            final

  public final <C extends shapeless.Coproduct, T extends java.lang.Object> scala.Option<C> runtimeInject$extension(T, shapeless.ops.coproduct$RuntimeInject<C>);
    descriptor: (Ljava/lang/Object;Lshapeless/ops/coproduct$RuntimeInject;)Lscala/Option;
    flags: (0x0011) ACC_PUBLIC, ACC_FINAL
    Code:
      stack=2, locals=3, args_size=3
         0: aload_2
         1: aload_1
         2: invokeinterface #47,  2           // InterfaceMethod shapeless/ops/coproduct$RuntimeInject.apply:(Ljava/lang/Object;)Lscala/Option;
         7: areturn
      LineNumberTable:
        line 39: 0
      LocalVariableTable:
        Start  Length  Slot  Name   Signature
            0       8     0  this   Lshapeless/syntax/inject$InjectSyntax$;
            0       8     1 $this   Ljava/lang/Object;
            0       8     2  rInj   Lshapeless/ops/coproduct$RuntimeInject;
    Signature: #43                          // <C::Lshapeless/Coproduct;T:Ljava/lang/Object;>(TT;Lshapeless/ops/coproduct$RuntimeInject<TC;>;)Lscala/Option<TC;>;
    MethodParameters:
      Name                           Flags
      $this                          final
      rInj                           final

  public final <T extends java.lang.Object> int hashCode$extension(T);
    descriptor: (Ljava/lang/Object;)I
    flags: (0x0011) ACC_PUBLIC, ACC_FINAL
    Code:
      stack=1, locals=2, args_size=2
         0: aload_1
         1: invokevirtual #55                 // Method java/lang/Object.hashCode:()I
         4: ireturn
      LineNumberTable:
        line 26: 0
      LocalVariableTable:
        Start  Length  Slot  Name   Signature
            0       5     0  this   Lshapeless/syntax/inject$InjectSyntax$;
            0       5     1 $this   Ljava/lang/Object;
    Signature: #51                          // <T:Ljava/lang/Object;>(TT;)I
    MethodParameters:
      Name                           Flags
      $this                          final

  public final <T extends java.lang.Object> boolean equals$extension(T, java.lang.Object);
    descriptor: (Ljava/lang/Object;Ljava/lang/Object;)Z
    flags: (0x0011) ACC_PUBLIC, ACC_FINAL
    Code:
      stack=2, locals=6, args_size=3
         0: aload_2
         1: astore        4
         3: aload         4
         5: instanceof    #15                 // class shapeless/syntax/inject$InjectSyntax
         8: ifeq          16
        11: iconst_1
        12: istore_3
        13: goto          24
        16: goto          19
        19: iconst_0
        20: istore_3
        21: goto          24
        24: iload_3
        25: ifeq          66
        28: aload_2
        29: ifnonnull     36
        32: aconst_null
        33: goto          43
        36: aload_2
        37: checkcast     #15                 // class shapeless/syntax/inject$InjectSyntax
        40: invokevirtual #63                 // Method shapeless/syntax/inject$InjectSyntax.t:()Ljava/lang/Object;
        43: astore        5
        45: aload_1
        46: aload         5
        48: invokestatic  #68                 // Method scala/runtime/BoxesRunTime.equals:(Ljava/lang/Object;Ljava/lang/Object;)Z
        51: ifeq          58
        54: iconst_1
        55: goto          59
        58: iconst_0
        59: ifeq          66
        62: iconst_1
        63: goto          67
        66: iconst_0
        67: ireturn
      StackMapTable: number_of_entries = 9
        frame_type = 253 /* append */
          offset_delta = 16
          locals = [ top, class java/lang/Object ]
        frame_type = 2 /* same */
        frame_type = 255 /* full_frame */
          offset_delta = 4
          locals = [ class shapeless/syntax/inject$InjectSyntax$, class java/lang/Object, class java/lang/Object, int, class java/lang/Object ]
          stack = []
        frame_type = 11 /* same */
        frame_type = 70 /* same_locals_1_stack_item */
          stack = [ class java/lang/Object ]
        frame_type = 252 /* append */
          offset_delta = 14
          locals = [ class java/lang/Object ]
        frame_type = 64 /* same_locals_1_stack_item */
          stack = [ int ]
        frame_type = 250 /* chop */
          offset_delta = 6
        frame_type = 64 /* same_locals_1_stack_item */
          stack = [ int ]
      LineNumberTable:
        line 26: 0
      LocalVariableTable:
        Start  Length  Slot  Name   Signature
            0      68     0  this   Lshapeless/syntax/inject$InjectSyntax$;
            0      68     1 $this   Ljava/lang/Object;
            0      68     2   x$1   Ljava/lang/Object;
    Signature: #58                          // <T:Ljava/lang/Object;>(TT;Ljava/lang/Object;)Z
    MethodParameters:
      Name                           Flags
      $this                          final
      x$1                            final

  public shapeless.syntax.inject$InjectSyntax$();
    descriptor: ()V
    flags: (0x0001) ACC_PUBLIC
    Code:
      stack=1, locals=1, args_size=1
         0: aload_0
         1: invokespecial #69                 // Method java/lang/Object."<init>":()V
         4: return
      LineNumberTable:
        line 26: 0
      LocalVariableTable:
        Start  Length  Slot  Name   Signature
            0       5     0  this   Lshapeless/syntax/inject$InjectSyntax$;
}
InnerClasses:
  public static #10= #7 of #9;            // Inject=class shapeless/ops/coproduct$Inject of class shapeless/ops/coproduct
  public static #13= #12 of #9;           // RuntimeInject=class shapeless/ops/coproduct$RuntimeInject of class shapeless/ops/coproduct
  public static final #18= #15 of #17;    // InjectSyntax=class shapeless/syntax/inject$InjectSyntax of class shapeless/syntax/inject
  public static #19= #2 of #17;           // InjectSyntax$=class shapeless/syntax/inject$InjectSyntax$ of class shapeless/syntax/inject
SourceFile: "inject.scala"
  ScalaInlineInfo: length = 0x1D (unknown attribute)
   01 01 00 05 00 18 00 17 01 00 38 00 39 01 00 31
   00 32 01 00 1D 00 1E 01 00 29 00 2A 01
  Scala: length = 0x0 (unknown attribute)

