Classfile /Users/mw/Projects/slang-braindump/.jar/jar8/assemble/slang-braindump/assemble/content/shapeless/syntax/inject$InjectSyntax.class
  Last modified May 29, 2022; size 2193 bytes
  SHA-256 checksum 24ddeaad3c5b2f4098bd685c3a9b7ffd22b3fe95360ad89999c6e3cfafa727da
  Compiled from "inject.scala"
public final class shapeless.syntax.inject$InjectSyntax<T extends java.lang.Object> extends java.lang.Object
  minor version: 0
  major version: 52
  flags: (0x0031) ACC_PUBLIC, ACC_FINAL, ACC_SUPER
  this_class: #2                          // shapeless/syntax/inject$InjectSyntax
  super_class: #5                         // java/lang/Object
  interfaces: 0, fields: 1, methods: 6, attributes: 5
Constant pool:
   #1 = Utf8               shapeless/syntax/inject$InjectSyntax
   #2 = Class              #1             // shapeless/syntax/inject$InjectSyntax
   #3 = Utf8               <T:Ljava/lang/Object;>Ljava/lang/Object;
   #4 = Utf8               java/lang/Object
   #5 = Class              #4             // java/lang/Object
   #6 = Utf8               inject.scala
   #7 = Utf8               shapeless/ops/coproduct$Inject
   #8 = Class              #7             // shapeless/ops/coproduct$Inject
   #9 = Utf8               shapeless/ops/coproduct
  #10 = Class              #9             // shapeless/ops/coproduct
  #11 = Utf8               Inject
  #12 = Utf8               shapeless/ops/coproduct$RuntimeInject
  #13 = Class              #12            // shapeless/ops/coproduct$RuntimeInject
  #14 = Utf8               RuntimeInject
  #15 = Utf8               shapeless/syntax/inject
  #16 = Class              #15            // shapeless/syntax/inject
  #17 = Utf8               InjectSyntax
  #18 = Utf8               shapeless/syntax/inject$InjectSyntax$
  #19 = Class              #18            // shapeless/syntax/inject$InjectSyntax$
  #20 = Utf8               InjectSyntax$
  #21 = Utf8               t
  #22 = Utf8               Ljava/lang/Object;
  #23 = Utf8               TT;
  #24 = Utf8               ()Ljava/lang/Object;
  #25 = Utf8               ()TT;
  #26 = NameAndType        #21:#22        // t:Ljava/lang/Object;
  #27 = Fieldref           #2.#26         // shapeless/syntax/inject$InjectSyntax.t:Ljava/lang/Object;
  #28 = Utf8               this
  #29 = Utf8               Lshapeless/syntax/inject$InjectSyntax;
  #30 = Utf8               inject
  #31 = Utf8               (Lshapeless/ops/coproduct$Inject;)Lshapeless/Coproduct;
  #32 = Utf8               <C::Lshapeless/Coproduct;>(Lshapeless/ops/coproduct$Inject<TC;TT;>;)TC;
  #33 = Utf8               inj
  #34 = Utf8               MODULE$
  #35 = Utf8               Lshapeless/syntax/inject$InjectSyntax$;
  #36 = NameAndType        #34:#35        // MODULE$:Lshapeless/syntax/inject$InjectSyntax$;
  #37 = Fieldref           #19.#36        // shapeless/syntax/inject$InjectSyntax$.MODULE$:Lshapeless/syntax/inject$InjectSyntax$;
  #38 = NameAndType        #21:#24        // t:()Ljava/lang/Object;
  #39 = Methodref          #2.#38         // shapeless/syntax/inject$InjectSyntax.t:()Ljava/lang/Object;
  #40 = Utf8               inject$extension
  #41 = Utf8               (Ljava/lang/Object;Lshapeless/ops/coproduct$Inject;)Lshapeless/Coproduct;
  #42 = NameAndType        #40:#41        // inject$extension:(Ljava/lang/Object;Lshapeless/ops/coproduct$Inject;)Lshapeless/Coproduct;
  #43 = Methodref          #19.#42        // shapeless/syntax/inject$InjectSyntax$.inject$extension:(Ljava/lang/Object;Lshapeless/ops/coproduct$Inject;)Lshapeless/Coproduct;
  #44 = Utf8               Lshapeless/ops/coproduct$Inject;
  #45 = Utf8               runtimeInject
  #46 = Utf8               (Lshapeless/ops/coproduct$RuntimeInject;)Lscala/Option;
  #47 = Utf8               <C::Lshapeless/Coproduct;>(Lshapeless/ops/coproduct$RuntimeInject<TC;>;)Lscala/Option<TC;>;
  #48 = Utf8               rInj
  #49 = Utf8               runtimeInject$extension
  #50 = Utf8               (Ljava/lang/Object;Lshapeless/ops/coproduct$RuntimeInject;)Lscala/Option;
  #51 = NameAndType        #49:#50        // runtimeInject$extension:(Ljava/lang/Object;Lshapeless/ops/coproduct$RuntimeInject;)Lscala/Option;
  #52 = Methodref          #19.#51        // shapeless/syntax/inject$InjectSyntax$.runtimeInject$extension:(Ljava/lang/Object;Lshapeless/ops/coproduct$RuntimeInject;)Lscala/Option;
  #53 = Utf8               Lshapeless/ops/coproduct$RuntimeInject;
  #54 = Utf8               hashCode
  #55 = Utf8               ()I
  #56 = Utf8               hashCode$extension
  #57 = Utf8               (Ljava/lang/Object;)I
  #58 = NameAndType        #56:#57        // hashCode$extension:(Ljava/lang/Object;)I
  #59 = Methodref          #19.#58        // shapeless/syntax/inject$InjectSyntax$.hashCode$extension:(Ljava/lang/Object;)I
  #60 = Utf8               equals
  #61 = Utf8               (Ljava/lang/Object;)Z
  #62 = Utf8               x$1
  #63 = Utf8               equals$extension
  #64 = Utf8               (Ljava/lang/Object;Ljava/lang/Object;)Z
  #65 = NameAndType        #63:#64        // equals$extension:(Ljava/lang/Object;Ljava/lang/Object;)Z
  #66 = Methodref          #19.#65        // shapeless/syntax/inject$InjectSyntax$.equals$extension:(Ljava/lang/Object;Ljava/lang/Object;)Z
  #67 = Utf8               <init>
  #68 = Utf8               (Ljava/lang/Object;)V
  #69 = Utf8               (TT;)V
  #70 = Utf8               ()V
  #71 = NameAndType        #67:#70        // "<init>":()V
  #72 = Methodref          #5.#71         // java/lang/Object."<init>":()V
  #73 = Utf8               Signature
  #74 = Utf8               Code
  #75 = Utf8               LineNumberTable
  #76 = Utf8               LocalVariableTable
  #77 = Utf8               MethodParameters
  #78 = Utf8               InnerClasses
  #79 = Utf8               SourceFile
  #80 = Utf8               ScalaInlineInfo
  #81 = Utf8               Scala
{
  private final T t;
    descriptor: Ljava/lang/Object;
    flags: (0x0012) ACC_PRIVATE, ACC_FINAL
    Signature: #23                          // TT;

  public T t();
    descriptor: ()Ljava/lang/Object;
    flags: (0x0001) ACC_PUBLIC
    Code:
      stack=1, locals=1, args_size=1
         0: aload_0
         1: getfield      #27                 // Field t:Ljava/lang/Object;
         4: areturn
      LineNumberTable:
        line 26: 0
      LocalVariableTable:
        Start  Length  Slot  Name   Signature
            0       5     0  this   Lshapeless/syntax/inject$InjectSyntax;
    Signature: #25                          // ()TT;

  public <C extends shapeless.Coproduct> C inject(shapeless.ops.coproduct$Inject<C, T>);
    descriptor: (Lshapeless/ops/coproduct$Inject;)Lshapeless/Coproduct;
    flags: (0x0001) ACC_PUBLIC
    Code:
      stack=3, locals=2, args_size=2
         0: getstatic     #37                 // Field shapeless/syntax/inject$InjectSyntax$.MODULE$:Lshapeless/syntax/inject$InjectSyntax$;
         3: aload_0
         4: invokevirtual #39                 // Method t:()Ljava/lang/Object;
         7: aload_1
         8: invokevirtual #43                 // Method shapeless/syntax/inject$InjectSyntax$.inject$extension:(Ljava/lang/Object;Lshapeless/ops/coproduct$Inject;)Lshapeless/Coproduct;
        11: areturn
      LineNumberTable:
        line 31: 0
      LocalVariableTable:
        Start  Length  Slot  Name   Signature
            0      12     0  this   Lshapeless/syntax/inject$InjectSyntax;
            0      12     1   inj   Lshapeless/ops/coproduct$Inject;
    Signature: #32                          // <C::Lshapeless/Coproduct;>(Lshapeless/ops/coproduct$Inject<TC;TT;>;)TC;
    MethodParameters:
      Name                           Flags
      inj                            final

  public <C extends shapeless.Coproduct> scala.Option<C> runtimeInject(shapeless.ops.coproduct$RuntimeInject<C>);
    descriptor: (Lshapeless/ops/coproduct$RuntimeInject;)Lscala/Option;
    flags: (0x0001) ACC_PUBLIC
    Code:
      stack=3, locals=2, args_size=2
         0: getstatic     #37                 // Field shapeless/syntax/inject$InjectSyntax$.MODULE$:Lshapeless/syntax/inject$InjectSyntax$;
         3: aload_0
         4: invokevirtual #39                 // Method t:()Ljava/lang/Object;
         7: aload_1
         8: invokevirtual #52                 // Method shapeless/syntax/inject$InjectSyntax$.runtimeInject$extension:(Ljava/lang/Object;Lshapeless/ops/coproduct$RuntimeInject;)Lscala/Option;
        11: areturn
      LineNumberTable:
        line 39: 0
      LocalVariableTable:
        Start  Length  Slot  Name   Signature
            0      12     0  this   Lshapeless/syntax/inject$InjectSyntax;
            0      12     1  rInj   Lshapeless/ops/coproduct$RuntimeInject;
    Signature: #47                          // <C::Lshapeless/Coproduct;>(Lshapeless/ops/coproduct$RuntimeInject<TC;>;)Lscala/Option<TC;>;
    MethodParameters:
      Name                           Flags
      rInj                           final

  public int hashCode();
    descriptor: ()I
    flags: (0x0001) ACC_PUBLIC
    Code:
      stack=2, locals=1, args_size=1
         0: getstatic     #37                 // Field shapeless/syntax/inject$InjectSyntax$.MODULE$:Lshapeless/syntax/inject$InjectSyntax$;
         3: aload_0
         4: invokevirtual #39                 // Method t:()Ljava/lang/Object;
         7: invokevirtual #59                 // Method shapeless/syntax/inject$InjectSyntax$.hashCode$extension:(Ljava/lang/Object;)I
        10: ireturn
      LineNumberTable:
        line 26: 0
      LocalVariableTable:
        Start  Length  Slot  Name   Signature
            0      11     0  this   Lshapeless/syntax/inject$InjectSyntax;

  public boolean equals(java.lang.Object);
    descriptor: (Ljava/lang/Object;)Z
    flags: (0x0001) ACC_PUBLIC
    Code:
      stack=3, locals=2, args_size=2
         0: getstatic     #37                 // Field shapeless/syntax/inject$InjectSyntax$.MODULE$:Lshapeless/syntax/inject$InjectSyntax$;
         3: aload_0
         4: invokevirtual #39                 // Method t:()Ljava/lang/Object;
         7: aload_1
         8: invokevirtual #66                 // Method shapeless/syntax/inject$InjectSyntax$.equals$extension:(Ljava/lang/Object;Ljava/lang/Object;)Z
        11: ireturn
      LineNumberTable:
        line 26: 0
      LocalVariableTable:
        Start  Length  Slot  Name   Signature
            0      12     0  this   Lshapeless/syntax/inject$InjectSyntax;
            0      12     1   x$1   Ljava/lang/Object;
    MethodParameters:
      Name                           Flags
      x$1                            final

  public shapeless.syntax.inject$InjectSyntax(T);
    descriptor: (Ljava/lang/Object;)V
    flags: (0x0001) ACC_PUBLIC
    Code:
      stack=2, locals=2, args_size=2
         0: aload_0
         1: aload_1
         2: putfield      #27                 // Field t:Ljava/lang/Object;
         5: aload_0
         6: invokespecial #72                 // Method java/lang/Object."<init>":()V
         9: return
      LineNumberTable:
        line 26: 0
      LocalVariableTable:
        Start  Length  Slot  Name   Signature
            0      10     0  this   Lshapeless/syntax/inject$InjectSyntax;
            0      10     1     t   Ljava/lang/Object;
    Signature: #69                          // (TT;)V
    MethodParameters:
      Name                           Flags
      t                              final
}
InnerClasses:
  public static #11= #8 of #10;           // Inject=class shapeless/ops/coproduct$Inject of class shapeless/ops/coproduct
  public static #14= #13 of #10;          // RuntimeInject=class shapeless/ops/coproduct$RuntimeInject of class shapeless/ops/coproduct
  public static final #17= #2 of #16;     // InjectSyntax=class shapeless/syntax/inject$InjectSyntax of class shapeless/syntax/inject
  public static #20= #19 of #16;          // InjectSyntax$=class shapeless/syntax/inject$InjectSyntax$ of class shapeless/syntax/inject
Signature: #3                           // <T:Ljava/lang/Object;>Ljava/lang/Object;
SourceFile: "inject.scala"
  ScalaInlineInfo: length = 0x22 (unknown attribute)
   01 01 00 06 00 43 00 44 01 00 3C 00 3D 01 00 36
   00 37 01 00 1E 00 1F 01 00 2D 00 2E 01 00 15 00
   18 01
  Scala: length = 0x0 (unknown attribute)

