Classfile /Users/mw/Projects/slang-braindump/.jar/jar8/assemble/slang-braindump/assemble/content/shapeless/syntax/NatOps.class
  Last modified May 29, 2022; size 2906 bytes
  SHA-256 checksum ce7a48601fa3f42530db38cf999cf0ecacb69fa74e04d06115e80c2c39008663
  Compiled from "nat.scala"
public final class shapeless.syntax.NatOps<N extends shapeless.Nat> extends java.lang.Object implements java.io.Serializable
  minor version: 0
  major version: 52
  flags: (0x0031) ACC_PUBLIC, ACC_FINAL, ACC_SUPER
  this_class: #2                          // shapeless/syntax/NatOps
  super_class: #5                         // java/lang/Object
  interfaces: 1, fields: 1, methods: 8, attributes: 6
Constant pool:
   #1 = Utf8               shapeless/syntax/NatOps
   #2 = Class              #1             // shapeless/syntax/NatOps
   #3 = Utf8               <N::Lshapeless/Nat;>Ljava/lang/Object;Ljava/io/Serializable;
   #4 = Utf8               java/lang/Object
   #5 = Class              #4             // java/lang/Object
   #6 = Utf8               java/io/Serializable
   #7 = Class              #6             // java/io/Serializable
   #8 = Utf8               nat.scala
   #9 = Utf8               Lscala/reflect/ScalaSignature;
  #10 = Utf8               bytes
  #11 = Utf8               \u0006\u0005\u0005\u0015b\u0001\u0002\b\u0010\u0005QA\u0001\u0002\u000b\u0001\u0003\u0006\u0004%\t!\u000b\u0005\tm\u0001\u0011\t\u0011)A\u0005U!)q\u0007\u0001C\u0001q!)A\b\u0001C\u0001{!9!\u000bAA\u0001\n\u0003\u001a\u0006b\u0002+\u0001\u0003\u0003%\t%V\u0004\b=>\t\t\u0011#\u0001`\r\u001dqq\"!A\t\u0002\u0001DQa\u000e\u0005\u0005\u0002-Dq\u0001\u001c\u0005\u0002\u0002\u0013%Q\u000eC\u0003u\u0011\u0011\u0015Q\u000fC\u0005\u0002\u0006!\t\t\u0011\"\u0002\u0002\b!I\u00111\u0003\u0005\u0002\u0002\u0013\u0015\u0011Q\u0003\u0002\u0007\u001d\u0006$x\n]:\u000b\u0005A\t\u0012AB:z]R\f\u0007PC\u0001\u0013\u0003%\u0019\b.\u00199fY\u0016\u001c8o\u0001\u0001\u0016\u0005Ua3c\u0001\u0001\u00179A\u0011qCG\u0007\u00021)\t\u0011$A\u0003tG\u0006d\u0017-\u0003\u0002\u001c1\t1\u0011I\\=WC2\u0004\"!H\u0013\u000f\u0005y\u0019cBA\u0010#\u001b\u0005\u0001#BA\u0011\u0014\u0003\u0019a$o\\8u}%\t\u0011$\u0003\u0002%1\u00059\u0001/Y2lC\u001e,\u0017B\u0001\u0014(\u00051\u0019VM]5bY&T\u0018M\u00197f\u0015\t!\u0003$A\u0001o+\u0005Q\u0003CA\u0016-\u0019\u0001!Q!\f\u0001C\u00029\u0012\u0011AT\t\u0003_I\u0002\"a\u0006\u0019\n\u0005EB\"a\u0002(pi\"Lgn\u001a\t\u0003gQj\u0011!E\u0005\u0003kE\u00111AT1u\u0003\tq\u0007%\u0001\u0004=S:LGO\u0010\u000b\u0003sm\u00022A\u000f\u0001+\u001b\u0005y\u0001\"\u0002\u0015\u0004\u0001\u0004Q\u0013!\u0002;p\u0013:$HC\u0001 B!\t9r(\u0003\u0002A1\t\u0019\u0011J\u001c;\t\u000b\t#\u00019A\"\u0002\rQ|\u0017J\u001c;O!\r!5J\u0014\b\u0003\u000b\"s!a\r$\n\u0005\u001d\u000b\u0012aA8qg&\u0011\u0011JS\u0001\u0004]\u0006$(BA$\u0012\u0013\taUJA\u0003U_&sGO\u0003\u0002J\u0015B\u0011q*\u0015\b\u0003!\u0006i\u0011\u0001A\u0005\u0003[Q\n\u0001\u0002[1tQ\u000e{G-\u001a\u000b\u0002}\u00051Q-];bYN$\"AV-\u0011\u0005]9\u0016B\u0001-\u0019\u0005\u001d\u0011un\u001c7fC:DqA\u0017\u0004\u0002\u0002\u0003\u00071,A\u0002yIE\u0002\"a\u0006/\n\u0005uC\"aA!os\u00061a*\u0019;PaN\u0004\"A\u000f\u0005\u0014\u0007!\tG\r\u0005\u0002\u0018E&\u00111\r\u0007\u0002\u0007\u0003:L(+\u001a4\u0011\u0005\u0015TW\"\u00014\u000b\u0005\u001dD\u0017AA5p\u0015\u0005I\u0017\u0001\u00026bm\u0006L!A\n4\u0015\u0003}\u000bAb\u001e:ji\u0016\u0014V\r\u001d7bG\u0016$\u0012A\u001c\t\u0003_Jl\u0011\u0001\u001d\u0006\u0003c\"\fA\u0001\\1oO&\u00111\u000f\u001d\u0002\u0007\u001f\nTWm\u0019;\u0002\u001fQ|\u0017J\u001c;%Kb$XM\\:j_:,2A^A\u0002)\t9X\u0010\u0006\u0002?q\")!i\u0003a\u0002sB\u0019Ai\u0013>\u0011\u0005m\ffB\u0001?\u0002\u001d\tYS\u0010C\u0003\u007f\u0017\u0001\u0007q0A\u0003%i\"L7\u000f\u0005\u0003;\u0001\u0005\u0005\u0001cA\u0016\u0002\u0004\u0011)Qf\u0003b\u0001]\u0005\u0011\u0002.Y:i\u0007>$W\rJ3yi\u0016t7/[8o+\u0011\tI!!\u0005\u0015\u0007M\u000bY\u0001\u0003\u0004\u007f\u0019\u0001\u0007\u0011Q\u0002\t\u0005u\u0001\ty\u0001E\u0002,\u0003#!Q!\f\u0007C\u00029\n\u0001#Z9vC2\u001cH%\u001a=uK:\u001c\u0018n\u001c8\u0016\t\u0005]\u00111\u0005\u000b\u0005\u00033\ti\u0002F\u0002W\u00037AqAW\u0007\u0002\u0002\u0003\u00071\f\u0003\u0004\u007f\u001b\u0001\u0007\u0011q\u0004\t\u0005u\u0001\t\t\u0003E\u0002,\u0003G!Q!L\u0007C\u00029\u0002
  #12 = Utf8               shapeless/ops/nat$ToInt
  #13 = Class              #12            // shapeless/ops/nat$ToInt
  #14 = Utf8               shapeless/ops/nat
  #15 = Class              #14            // shapeless/ops/nat
  #16 = Utf8               ToInt
  #17 = Utf8               n
  #18 = Utf8               Lshapeless/Nat;
  #19 = Utf8               TN;
  #20 = Utf8               equals$extension
  #21 = Utf8               (Lshapeless/Nat;Ljava/lang/Object;)Z
  #22 = Utf8               <N::Lshapeless/Nat;>(TN;Ljava/lang/Object;)Z
  #23 = Utf8               $this
  #24 = Utf8               x$1
  #25 = Utf8               shapeless/syntax/NatOps$
  #26 = Class              #25            // shapeless/syntax/NatOps$
  #27 = Utf8               MODULE$
  #28 = Utf8               Lshapeless/syntax/NatOps$;
  #29 = NameAndType        #27:#28        // MODULE$:Lshapeless/syntax/NatOps$;
  #30 = Fieldref           #26.#29        // shapeless/syntax/NatOps$.MODULE$:Lshapeless/syntax/NatOps$;
  #31 = NameAndType        #20:#21        // equals$extension:(Lshapeless/Nat;Ljava/lang/Object;)Z
  #32 = Methodref          #26.#31        // shapeless/syntax/NatOps$.equals$extension:(Lshapeless/Nat;Ljava/lang/Object;)Z
  #33 = Utf8               hashCode$extension
  #34 = Utf8               (Lshapeless/Nat;)I
  #35 = Utf8               <N::Lshapeless/Nat;>(TN;)I
  #36 = NameAndType        #33:#34        // hashCode$extension:(Lshapeless/Nat;)I
  #37 = Methodref          #26.#36        // shapeless/syntax/NatOps$.hashCode$extension:(Lshapeless/Nat;)I
  #38 = Utf8               toInt$extension
  #39 = Utf8               (Lshapeless/Nat;Lshapeless/ops/nat$ToInt;)I
  #40 = Utf8               <N::Lshapeless/Nat;>(TN;Lshapeless/ops/nat$ToInt<Lshapeless/Nat;>;)I
  #41 = Utf8               toIntN
  #42 = NameAndType        #38:#39        // toInt$extension:(Lshapeless/Nat;Lshapeless/ops/nat$ToInt;)I
  #43 = Methodref          #26.#42        // shapeless/syntax/NatOps$.toInt$extension:(Lshapeless/Nat;Lshapeless/ops/nat$ToInt;)I
  #44 = Utf8               ()Lshapeless/Nat;
  #45 = Utf8               ()TN;
  #46 = NameAndType        #17:#18        // n:Lshapeless/Nat;
  #47 = Fieldref           #2.#46         // shapeless/syntax/NatOps.n:Lshapeless/Nat;
  #48 = Utf8               this
  #49 = Utf8               Lshapeless/syntax/NatOps;
  #50 = Utf8               toInt
  #51 = Utf8               (Lshapeless/ops/nat$ToInt;)I
  #52 = Utf8               (Lshapeless/ops/nat$ToInt<Lshapeless/Nat;>;)I
  #53 = NameAndType        #17:#44        // n:()Lshapeless/Nat;
  #54 = Methodref          #2.#53         // shapeless/syntax/NatOps.n:()Lshapeless/Nat;
  #55 = Utf8               Lshapeless/ops/nat$ToInt;
  #56 = Utf8               hashCode
  #57 = Utf8               ()I
  #58 = Utf8               equals
  #59 = Utf8               (Ljava/lang/Object;)Z
  #60 = Utf8               Ljava/lang/Object;
  #61 = Utf8               <init>
  #62 = Utf8               (Lshapeless/Nat;)V
  #63 = Utf8               (TN;)V
  #64 = Utf8               ()V
  #65 = NameAndType        #61:#64        // "<init>":()V
  #66 = Methodref          #5.#65         // java/lang/Object."<init>":()V
  #67 = Utf8               Signature
  #68 = Utf8               Code
  #69 = Utf8               MethodParameters
  #70 = Utf8               LineNumberTable
  #71 = Utf8               LocalVariableTable
  #72 = Utf8               InnerClasses
  #73 = Utf8               SourceFile
  #74 = Utf8               RuntimeVisibleAnnotations
  #75 = Utf8               ScalaInlineInfo
  #76 = Utf8               ScalaSig
{
  private final N n;
    descriptor: Lshapeless/Nat;
    flags: (0x0012) ACC_PRIVATE, ACC_FINAL
    Signature: #19                          // TN;

  public static <N extends shapeless.Nat> boolean equals$extension(N, java.lang.Object);
    descriptor: (Lshapeless/Nat;Ljava/lang/Object;)Z
    flags: (0x0009) ACC_PUBLIC, ACC_STATIC
    Code:
      stack=3, locals=2, args_size=2
         0: getstatic     #30                 // Field shapeless/syntax/NatOps$.MODULE$:Lshapeless/syntax/NatOps$;
         3: aload_0
         4: aload_1
         5: invokevirtual #32                 // Method shapeless/syntax/NatOps$.equals$extension:(Lshapeless/Nat;Ljava/lang/Object;)Z
         8: ireturn
    Signature: #22                          // <N::Lshapeless/Nat;>(TN;Ljava/lang/Object;)Z
    MethodParameters:
      Name                           Flags
      $this                          final
      x$1                            final

  public static <N extends shapeless.Nat> int hashCode$extension(N);
    descriptor: (Lshapeless/Nat;)I
    flags: (0x0009) ACC_PUBLIC, ACC_STATIC
    Code:
      stack=2, locals=1, args_size=1
         0: getstatic     #30                 // Field shapeless/syntax/NatOps$.MODULE$:Lshapeless/syntax/NatOps$;
         3: aload_0
         4: invokevirtual #37                 // Method shapeless/syntax/NatOps$.hashCode$extension:(Lshapeless/Nat;)I
         7: ireturn
    Signature: #35                          // <N::Lshapeless/Nat;>(TN;)I
    MethodParameters:
      Name                           Flags
      $this                          final

  public static <N extends shapeless.Nat> int toInt$extension(N, shapeless.ops.nat$ToInt<shapeless.Nat>);
    descriptor: (Lshapeless/Nat;Lshapeless/ops/nat$ToInt;)I
    flags: (0x0009) ACC_PUBLIC, ACC_STATIC
    Code:
      stack=3, locals=2, args_size=2
         0: getstatic     #30                 // Field shapeless/syntax/NatOps$.MODULE$:Lshapeless/syntax/NatOps$;
         3: aload_0
         4: aload_1
         5: invokevirtual #43                 // Method shapeless/syntax/NatOps$.toInt$extension:(Lshapeless/Nat;Lshapeless/ops/nat$ToInt;)I
         8: ireturn
    Signature: #40                          // <N::Lshapeless/Nat;>(TN;Lshapeless/ops/nat$ToInt<Lshapeless/Nat;>;)I
    MethodParameters:
      Name                           Flags
      $this                          final
      toIntN                         final

  public N n();
    descriptor: ()Lshapeless/Nat;
    flags: (0x0001) ACC_PUBLIC
    Code:
      stack=1, locals=1, args_size=1
         0: aload_0
         1: getfield      #47                 // Field n:Lshapeless/Nat;
         4: areturn
      LineNumberTable:
        line 40: 0
      LocalVariableTable:
        Start  Length  Slot  Name   Signature
            0       5     0  this   Lshapeless/syntax/NatOps;
    Signature: #45                          // ()TN;

  public int toInt(shapeless.ops.nat$ToInt<shapeless.Nat>);
    descriptor: (Lshapeless/ops/nat$ToInt;)I
    flags: (0x0001) ACC_PUBLIC
    Code:
      stack=3, locals=2, args_size=2
         0: getstatic     #30                 // Field shapeless/syntax/NatOps$.MODULE$:Lshapeless/syntax/NatOps$;
         3: aload_0
         4: invokevirtual #54                 // Method n:()Lshapeless/Nat;
         7: aload_1
         8: invokevirtual #43                 // Method shapeless/syntax/NatOps$.toInt$extension:(Lshapeless/Nat;Lshapeless/ops/nat$ToInt;)I
        11: ireturn
      LineNumberTable:
        line 46: 0
      LocalVariableTable:
        Start  Length  Slot  Name   Signature
            0      12     0  this   Lshapeless/syntax/NatOps;
            0      12     1 toIntN   Lshapeless/ops/nat$ToInt;
    Signature: #52                          // (Lshapeless/ops/nat$ToInt<Lshapeless/Nat;>;)I
    MethodParameters:
      Name                           Flags
      toIntN                         final

  public int hashCode();
    descriptor: ()I
    flags: (0x0001) ACC_PUBLIC
    Code:
      stack=2, locals=1, args_size=1
         0: getstatic     #30                 // Field shapeless/syntax/NatOps$.MODULE$:Lshapeless/syntax/NatOps$;
         3: aload_0
         4: invokevirtual #54                 // Method n:()Lshapeless/Nat;
         7: invokevirtual #37                 // Method shapeless/syntax/NatOps$.hashCode$extension:(Lshapeless/Nat;)I
        10: ireturn
      LineNumberTable:
        line 40: 0
      LocalVariableTable:
        Start  Length  Slot  Name   Signature
            0      11     0  this   Lshapeless/syntax/NatOps;

  public boolean equals(java.lang.Object);
    descriptor: (Ljava/lang/Object;)Z
    flags: (0x0001) ACC_PUBLIC
    Code:
      stack=3, locals=2, args_size=2
         0: getstatic     #30                 // Field shapeless/syntax/NatOps$.MODULE$:Lshapeless/syntax/NatOps$;
         3: aload_0
         4: invokevirtual #54                 // Method n:()Lshapeless/Nat;
         7: aload_1
         8: invokevirtual #32                 // Method shapeless/syntax/NatOps$.equals$extension:(Lshapeless/Nat;Ljava/lang/Object;)Z
        11: ireturn
      LineNumberTable:
        line 40: 0
      LocalVariableTable:
        Start  Length  Slot  Name   Signature
            0      12     0  this   Lshapeless/syntax/NatOps;
            0      12     1   x$1   Ljava/lang/Object;
    MethodParameters:
      Name                           Flags
      x$1                            final

  public shapeless.syntax.NatOps(N);
    descriptor: (Lshapeless/Nat;)V
    flags: (0x0001) ACC_PUBLIC
    Code:
      stack=2, locals=2, args_size=2
         0: aload_0
         1: aload_1
         2: putfield      #47                 // Field n:Lshapeless/Nat;
         5: aload_0
         6: invokespecial #66                 // Method java/lang/Object."<init>":()V
         9: return
      LineNumberTable:
        line 40: 0
      LocalVariableTable:
        Start  Length  Slot  Name   Signature
            0      10     0  this   Lshapeless/syntax/NatOps;
            0      10     1     n   Lshapeless/Nat;
    Signature: #63                          // (TN;)V
    MethodParameters:
      Name                           Flags
      n                              final
}
InnerClasses:
  public static #16= #13 of #15;          // ToInt=class shapeless/ops/nat$ToInt of class shapeless/ops/nat
Signature: #3                           // <N::Lshapeless/Nat;>Ljava/lang/Object;Ljava/io/Serializable;
SourceFile: "nat.scala"
RuntimeVisibleAnnotations:
  0: #9(#10=s#11)
    scala.reflect.ScalaSignature(
      bytes="\u0006\u0005\u0005\u0015b\u0001\u0002\b\u0010\u0005QA\u0001\u0002\u000b\u0001\u0003\u0006\u0004%\t!\u000b\u0005\tm\u0001\u0011\t\u0011)A\u0005U!)q\u0007\u0001C\u0001q!)A\b\u0001C\u0001{!9!\u000bAA\u0001\n\u0003\u001a\u0006b\u0002+\u0001\u0003\u0003%\t%V\u0004\b=>\t\t\u0011#\u0001`\r\u001dqq\"!A\t\u0002\u0001DQa\u000e\u0005\u0005\u0002-Dq\u0001\u001c\u0005\u0002\u0002\u0013%Q\u000eC\u0003u\u0011\u0011\u0015Q\u000fC\u0005\u0002\u0006!\t\t\u0011\"\u0002\u0002\b!I\u00111\u0003\u0005\u0002\u0002\u0013\u0015\u0011Q\u0003\u0002\u0007\u001d\u0006$x\n]:\u000b\u0005A\t\u0012AB:z]R\f\u0007PC\u0001\u0013\u0003%\u0019\b.\u00199fY\u0016\u001c8o\u0001\u0001\u0016\u0005Ua3c\u0001\u0001\u00179A\u0011qCG\u0007\u00021)\t\u0011$A\u0003tG\u0006d\u0017-\u0003\u0002\u001c1\t1\u0011I\\=WC2\u0004\"!H\u0013\u000f\u0005y\u0019cBA\u0010#\u001b\u0005\u0001#BA\u0011\u0014\u0003\u0019a$o\\8u}%\t\u0011$\u0003\u0002%1\u00059\u0001/Y2lC\u001e,\u0017B\u0001\u0014(\u00051\u0019VM]5bY&T\u0018M\u00197f\u0015\t!\u0003$A\u0001o+\u0005Q\u0003CA\u0016-\u0019\u0001!Q!\f\u0001C\u00029\u0012\u0011AT\t\u0003_I\u0002\"a\u0006\u0019\n\u0005EB\"a\u0002(pi\"Lgn\u001a\t\u0003gQj\u0011!E\u0005\u0003kE\u00111AT1u\u0003\tq\u0007%\u0001\u0004=S:LGO\u0010\u000b\u0003sm\u00022A\u000f\u0001+\u001b\u0005y\u0001\"\u0002\u0015\u0004\u0001\u0004Q\u0013!\u0002;p\u0013:$HC\u0001 B!\t9r(\u0003\u0002A1\t\u0019\u0011J\u001c;\t\u000b\t#\u00019A\"\u0002\rQ|\u0017J\u001c;O!\r!5J\u0014\b\u0003\u000b\"s!a\r$\n\u0005\u001d\u000b\u0012aA8qg&\u0011\u0011JS\u0001\u0004]\u0006$(BA$\u0012\u0013\taUJA\u0003U_&sGO\u0003\u0002J\u0015B\u0011q*\u0015\b\u0003!\u0006i\u0011\u0001A\u0005\u0003[Q\n\u0001\u0002[1tQ\u000e{G-\u001a\u000b\u0002}\u00051Q-];bYN$\"AV-\u0011\u0005]9\u0016B\u0001-\u0019\u0005\u001d\u0011un\u001c7fC:DqA\u0017\u0004\u0002\u0002\u0003\u00071,A\u0002yIE\u0002\"a\u0006/\n\u0005uC\"aA!os\u00061a*\u0019;PaN\u0004\"A\u000f\u0005\u0014\u0007!\tG\r\u0005\u0002\u0018E&\u00111\r\u0007\u0002\u0007\u0003:L(+\u001a4\u0011\u0005\u0015TW\"\u00014\u000b\u0005\u001dD\u0017AA5p\u0015\u0005I\u0017\u0001\u00026bm\u0006L!A\n4\u0015\u0003}\u000bAb\u001e:ji\u0016\u0014V\r\u001d7bG\u0016$\u0012A\u001c\t\u0003_Jl\u0011\u0001\u001d\u0006\u0003c\"\fA\u0001\\1oO&\u00111\u000f\u001d\u0002\u0007\u001f\nTWm\u0019;\u0002\u001fQ|\u0017J\u001c;%Kb$XM\\:j_:,2A^A\u0002)\t9X\u0010\u0006\u0002?q\")!i\u0003a\u0002sB\u0019Ai\u0013>\u0011\u0005m\ffB\u0001?\u0002\u001d\tYS\u0010C\u0003\u007f\u0017\u0001\u0007q0A\u0003%i\"L7\u000f\u0005\u0003;\u0001\u0005\u0005\u0001cA\u0016\u0002\u0004\u0011)Qf\u0003b\u0001]\u0005\u0011\u0002.Y:i\u0007>$W\rJ3yi\u0016t7/[8o+\u0011\tI!!\u0005\u0015\u0007M\u000bY\u0001\u0003\u0004\u007f\u0019\u0001\u0007\u0011Q\u0002\t\u0005u\u0001\ty\u0001E\u0002,\u0003#!Q!\f\u0007C\u00029\n\u0001#Z9vC2\u001cH%\u001a=uK:\u001c\u0018n\u001c8\u0016\t\u0005]\u00111\u0005\u000b\u0005\u00033\ti\u0002F\u0002W\u00037AqAW\u0007\u0002\u0002\u0003\u00071\f\u0003\u0004\u007f\u001b\u0001\u0007\u0011q\u0004\t\u0005u\u0001\t\t\u0003E\u0002,\u0003G!Q!L\u0007C\u00029\u0002"
    )
  ScalaInlineInfo: length = 0x1D (unknown attribute)
   01 01 00 05 00 3D 00 3E 01 00 3A 00 3B 01 00 38
   00 39 01 00 11 00 2C 01 00 32 00 33 01
  ScalaSig: length = 0x3 (unknown attribute)
   05 02 00
