Classfile /Users/mw/Projects/slang-braindump/.jar/jar8/assemble/slang-braindump/assemble/content/shapeless/syntax/TypeableOps.class
  Last modified May 29, 2022; size 3421 bytes
  SHA-256 checksum a826da66eeaee4f86117f9768a2f6f5746897da58f9e16b2fb2aec0374cf4664
  Compiled from "typeable.scala"
public final class shapeless.syntax.TypeableOps<T extends java.lang.Object> extends java.lang.Object implements java.io.Serializable
  minor version: 0
  major version: 52
  flags: (0x0031) ACC_PUBLIC, ACC_FINAL, ACC_SUPER
  this_class: #2                          // shapeless/syntax/TypeableOps
  super_class: #5                         // java/lang/Object
  interfaces: 1, fields: 1, methods: 10, attributes: 5
Constant pool:
   #1 = Utf8               shapeless/syntax/TypeableOps
   #2 = Class              #1             // shapeless/syntax/TypeableOps
   #3 = Utf8               <T:Ljava/lang/Object;>Ljava/lang/Object;Ljava/io/Serializable;
   #4 = Utf8               java/lang/Object
   #5 = Class              #4             // java/lang/Object
   #6 = Utf8               java/io/Serializable
   #7 = Class              #6             // java/io/Serializable
   #8 = Utf8               typeable.scala
   #9 = Utf8               Lscala/reflect/ScalaSignature;
  #10 = Utf8               bytes
  #11 = Utf8               \u0006\u0005\u0005\u001dc\u0001\u0002\t\u0012\u0005YA\u0001B\u000b\u0001\u0003\u0006\u0004%\ta\u000b\u0005\to\u0001\u0011\t\u0011)A\u0005Y!)\u0001\b\u0001C\u0001s!)Q\b\u0001C\u0001}!)A\n\u0001C\u0001\u001b\"9Q\u000bAA\u0001\n\u00032\u0006b\u0002.\u0001\u0003\u0003%\teW\u0004\bCF\t\t\u0011#\u0001c\r\u001d\u0001\u0012#!A\t\u0002\rDQ\u0001O\u0005\u0005\u00029Dqa\\\u0005\u0002\u0002\u0013%\u0001\u000fC\u0003x\u0013\u0011\u0015\u0001\u0010C\u0004\u0002\f%!)!!\u0004\t\u0013\u0005\u001d\u0012\"!A\u0005\u0006\u0005%\u0002\"CA\u001b\u0013\u0005\u0005IQAA\u001c\u0005-!\u0016\u0010]3bE2,w\n]:\u000b\u0005I\u0019\u0012AB:z]R\f\u0007PC\u0001\u0015\u0003%\u0019\b.\u00199fY\u0016\u001c8o\u0001\u0001\u0016\u0005]q3c\u0001\u0001\u0019=A\u0011\u0011\u0004H\u0007\u00025)\t1$A\u0003tG\u0006d\u0017-\u0003\u0002\u001e5\t1\u0011I\\=WC2\u0004\"aH\u0014\u000f\u0005\u0001*cBA\u0011%\u001b\u0005\u0011#BA\u0012\u0016\u0003\u0019a$o\\8u}%\t1$\u0003\u0002\'5\u00059\u0001/Y2lC\u001e,\u0017B\u0001\u0015*\u00051\u0019VM]5bY&T\u0018M\u00197f\u0015\t1#$A\u0001u+\u0005a\u0003CA\u0017/\u0019\u0001!Qa\f\u0001C\u0002A\u0012\u0011\u0001V\t\u0003cQ\u0002\"!\u0007\u001a\n\u0005MR\"a\u0002(pi\"Lgn\u001a\t\u00033UJ!A\u000e\u000e\u0003\u0007\u0005s\u00170\u0001\u0002uA\u00051A(\u001b8jiz\"\"A\u000f\u001f\u0011\u0007m\u0002A&D\u0001\u0012\u0011\u0015Q3\u00011\u0001-\u0003\u0011\u0019\u0017m\u001d;\u0016\u0005}\"EC\u0001!G!\rI\u0012iQ\u0005\u0003\u0005j\u0011aa\u00149uS>t\u0007CA\u0017E\t\u0015)EA1\u00011\u0005\u0005)\u0006\"B$\u0005\u0001\bA\u0015!B2bgR,\u0006cA%K\u00076\t1#\u0003\u0002L\'\tAA+\u001f9fC\ndW-\u0001\u0005oCJ\u0014xn\u001e+p+\tq\u0015\u000b\u0006\u0002P\'B\u0019\u0011$\u0011)\u0011\u00055\nF!B#\u0006\u0005\u0004\u0011\u0016CA\u0019-\u0011\u00159U\u0001q\u0001U!\rI%\nU\u0001\tQ\u0006\u001c\bnQ8eKR\tq\u000b\u0005\u0002\u001a1&\u0011\u0011L\u0007\u0002\u0004\u0013:$\u0018AB3rk\u0006d7\u000f\u0006\u0002]?B\u0011\u0011$X\u0005\u0003=j\u0011qAQ8pY\u0016\fg\u000eC\u0004a\u000f\u0005\u0005\t\u0019\u0001\u001b\u0002\u0007a$\u0013\'A\u0006UsB,\u0017M\u00197f\u001fB\u001c\bCA\u001e\n\'\rIAm\u001a\t\u00033\u0015L!A\u001a\u000e\u0003\r\u0005s\u0017PU3g!\tAW.D\u0001j\u0015\tQ7.\u0001\u0002j_*\tA.\u0001\u0003kCZ\f\u0017B\u0001\u0015j)\u0005\u0011\u0017\u0001D<sSR,\'+\u001a9mC\u000e,G#A9\u0011\u0005I,X\"A:\u000b\u0005Q\\\u0017\u0001\u00027b]\u001eL!A^:\u0003\r=\u0013\'.Z2u\u00039\u0019\u0017m\u001d;%Kb$XM\\:j_:,B!_?\u0002\nQ\u0019!0!\u0001\u0015\u0005mt\bcA\rByB\u0011Q& \u0003\u0006\u000b2\u0011\r\u0001\r\u0005\u0006\u000f2\u0001\u001da \t\u0004\u0013*c\bbBA\u0002\u0019\u0001\u0007\u0011QA\u0001\u0006IQD\u0017n\u001d\t\u0005w\u0001\t9\u0001E\u0002.\u0003\u0013!Qa\f\u0007C\u0002A\n!C\\1se><Hk\u001c\u0013fqR,gn]5p]V1\u0011qBA\f\u0003;!B!!\u0005\u0002$Q!\u00111CA\u0010!\u0011I\u0012)!\u0006\u0011\u00075\n9\u0002\u0002\u0004F\u001b\t\u0007\u0011\u0011D\t\u0004c\u0005m\u0001cA\u0017\u0002\u001e\u0011)q&\u0004b\u0001a!1q)\u0004a\u0002\u0003C\u0001B!\u0013&\u0002\u0016!9\u00111A\u0007A\u0002\u0005\u0015\u0002\u0003B\u001e\u0001\u00037\t!\u0003[1tQ\u000e{G-\u001a\u0013fqR,gn]5p]V!\u00111FA\u001a)\r1\u0016Q\u0006\u0005\b\u0003\u0007q\u0001\u0019AA\u0018!\u0011Y\u0004!!\r\u0011\u00075\n\u0019\u0004B\u00030\u001d\t\u0007\u0001\'\u0001\tfcV\fGn\u001d\u0013fqR,gn]5p]V!\u0011\u0011HA#)\u0011\tY$a\u0010\u0015\u0007q\u000bi\u0004C\u0004a\u001f\u0005\u0005\t\u0019\u0001\u001b\t\u000f\u0005\rq\u00021\u0001\u0002BA!1\bAA\"!\ri\u0013Q\t\u0003\u0006_=\u0011\r\u0001\r
  #12 = Utf8               t
  #13 = Utf8               Ljava/lang/Object;
  #14 = Utf8               TT;
  #15 = Utf8               equals$extension
  #16 = Utf8               (Ljava/lang/Object;Ljava/lang/Object;)Z
  #17 = Utf8               <T:Ljava/lang/Object;>(TT;Ljava/lang/Object;)Z
  #18 = Utf8               $this
  #19 = Utf8               x$1
  #20 = Utf8               shapeless/syntax/TypeableOps$
  #21 = Class              #20            // shapeless/syntax/TypeableOps$
  #22 = Utf8               MODULE$
  #23 = Utf8               Lshapeless/syntax/TypeableOps$;
  #24 = NameAndType        #22:#23        // MODULE$:Lshapeless/syntax/TypeableOps$;
  #25 = Fieldref           #21.#24        // shapeless/syntax/TypeableOps$.MODULE$:Lshapeless/syntax/TypeableOps$;
  #26 = NameAndType        #15:#16        // equals$extension:(Ljava/lang/Object;Ljava/lang/Object;)Z
  #27 = Methodref          #21.#26        // shapeless/syntax/TypeableOps$.equals$extension:(Ljava/lang/Object;Ljava/lang/Object;)Z
  #28 = Utf8               hashCode$extension
  #29 = Utf8               (Ljava/lang/Object;)I
  #30 = Utf8               <T:Ljava/lang/Object;>(TT;)I
  #31 = NameAndType        #28:#29        // hashCode$extension:(Ljava/lang/Object;)I
  #32 = Methodref          #21.#31        // shapeless/syntax/TypeableOps$.hashCode$extension:(Ljava/lang/Object;)I
  #33 = Utf8               narrowTo$extension
  #34 = Utf8               (Ljava/lang/Object;Lshapeless/Typeable;)Lscala/Option;
  #35 = Utf8               <U:TT;T:Ljava/lang/Object;>(TT;Lshapeless/Typeable<TU;>;)Lscala/Option<TU;>;
  #36 = Utf8               castU
  #37 = NameAndType        #33:#34        // narrowTo$extension:(Ljava/lang/Object;Lshapeless/Typeable;)Lscala/Option;
  #38 = Methodref          #21.#37        // shapeless/syntax/TypeableOps$.narrowTo$extension:(Ljava/lang/Object;Lshapeless/Typeable;)Lscala/Option;
  #39 = Utf8               cast$extension
  #40 = Utf8               <U:Ljava/lang/Object;T:Ljava/lang/Object;>(TT;Lshapeless/Typeable<TU;>;)Lscala/Option<TU;>;
  #41 = NameAndType        #39:#34        // cast$extension:(Ljava/lang/Object;Lshapeless/Typeable;)Lscala/Option;
  #42 = Methodref          #21.#41        // shapeless/syntax/TypeableOps$.cast$extension:(Ljava/lang/Object;Lshapeless/Typeable;)Lscala/Option;
  #43 = Utf8               ()Ljava/lang/Object;
  #44 = Utf8               ()TT;
  #45 = NameAndType        #12:#13        // t:Ljava/lang/Object;
  #46 = Fieldref           #2.#45         // shapeless/syntax/TypeableOps.t:Ljava/lang/Object;
  #47 = Utf8               this
  #48 = Utf8               Lshapeless/syntax/TypeableOps;
  #49 = Utf8               cast
  #50 = Utf8               (Lshapeless/Typeable;)Lscala/Option;
  #51 = Utf8               <U:Ljava/lang/Object;>(Lshapeless/Typeable<TU;>;)Lscala/Option<TU;>;
  #52 = NameAndType        #12:#43        // t:()Ljava/lang/Object;
  #53 = Methodref          #2.#52         // shapeless/syntax/TypeableOps.t:()Ljava/lang/Object;
  #54 = Utf8               Lshapeless/Typeable;
  #55 = Utf8               narrowTo
  #56 = Utf8               <U:TT;>(Lshapeless/Typeable<TU;>;)Lscala/Option<TU;>;
  #57 = Utf8               hashCode
  #58 = Utf8               ()I
  #59 = Utf8               equals
  #60 = Utf8               (Ljava/lang/Object;)Z
  #61 = Utf8               <init>
  #62 = Utf8               (Ljava/lang/Object;)V
  #63 = Utf8               (TT;)V
  #64 = Utf8               ()V
  #65 = NameAndType        #61:#64        // "<init>":()V
  #66 = Methodref          #5.#65         // java/lang/Object."<init>":()V
  #67 = Utf8               Signature
  #68 = Utf8               Code
  #69 = Utf8               MethodParameters
  #70 = Utf8               LineNumberTable
  #71 = Utf8               LocalVariableTable
  #72 = Utf8               SourceFile
  #73 = Utf8               RuntimeVisibleAnnotations
  #74 = Utf8               ScalaInlineInfo
  #75 = Utf8               ScalaSig
{
  private final T t;
    descriptor: Ljava/lang/Object;
    flags: (0x0012) ACC_PRIVATE, ACC_FINAL
    Signature: #14                          // TT;

  public static <T extends java.lang.Object> boolean equals$extension(T, java.lang.Object);
    descriptor: (Ljava/lang/Object;Ljava/lang/Object;)Z
    flags: (0x0009) ACC_PUBLIC, ACC_STATIC
    Code:
      stack=3, locals=2, args_size=2
         0: getstatic     #25                 // Field shapeless/syntax/TypeableOps$.MODULE$:Lshapeless/syntax/TypeableOps$;
         3: aload_0
         4: aload_1
         5: invokevirtual #27                 // Method shapeless/syntax/TypeableOps$.equals$extension:(Ljava/lang/Object;Ljava/lang/Object;)Z
         8: ireturn
    Signature: #17                          // <T:Ljava/lang/Object;>(TT;Ljava/lang/Object;)Z
    MethodParameters:
      Name                           Flags
      $this                          final
      x$1                            final

  public static <T extends java.lang.Object> int hashCode$extension(T);
    descriptor: (Ljava/lang/Object;)I
    flags: (0x0009) ACC_PUBLIC, ACC_STATIC
    Code:
      stack=2, locals=1, args_size=1
         0: getstatic     #25                 // Field shapeless/syntax/TypeableOps$.MODULE$:Lshapeless/syntax/TypeableOps$;
         3: aload_0
         4: invokevirtual #32                 // Method shapeless/syntax/TypeableOps$.hashCode$extension:(Ljava/lang/Object;)I
         7: ireturn
    Signature: #30                          // <T:Ljava/lang/Object;>(TT;)I
    MethodParameters:
      Name                           Flags
      $this                          final

  public static <U extends T, T extends java.lang.Object> scala.Option<U> narrowTo$extension(T, shapeless.Typeable<U>);
    descriptor: (Ljava/lang/Object;Lshapeless/Typeable;)Lscala/Option;
    flags: (0x0009) ACC_PUBLIC, ACC_STATIC
    Code:
      stack=3, locals=2, args_size=2
         0: getstatic     #25                 // Field shapeless/syntax/TypeableOps$.MODULE$:Lshapeless/syntax/TypeableOps$;
         3: aload_0
         4: aload_1
         5: invokevirtual #38                 // Method shapeless/syntax/TypeableOps$.narrowTo$extension:(Ljava/lang/Object;Lshapeless/Typeable;)Lscala/Option;
         8: areturn
    Signature: #35                          // <U:TT;T:Ljava/lang/Object;>(TT;Lshapeless/Typeable<TU;>;)Lscala/Option<TU;>;
    MethodParameters:
      Name                           Flags
      $this                          final
      castU                          final

  public static <U extends java.lang.Object, T extends java.lang.Object> scala.Option<U> cast$extension(T, shapeless.Typeable<U>);
    descriptor: (Ljava/lang/Object;Lshapeless/Typeable;)Lscala/Option;
    flags: (0x0009) ACC_PUBLIC, ACC_STATIC
    Code:
      stack=3, locals=2, args_size=2
         0: getstatic     #25                 // Field shapeless/syntax/TypeableOps$.MODULE$:Lshapeless/syntax/TypeableOps$;
         3: aload_0
         4: aload_1
         5: invokevirtual #42                 // Method shapeless/syntax/TypeableOps$.cast$extension:(Ljava/lang/Object;Lshapeless/Typeable;)Lscala/Option;
         8: areturn
    Signature: #40                          // <U:Ljava/lang/Object;T:Ljava/lang/Object;>(TT;Lshapeless/Typeable<TU;>;)Lscala/Option<TU;>;
    MethodParameters:
      Name                           Flags
      $this                          final
      castU                          final

  public T t();
    descriptor: ()Ljava/lang/Object;
    flags: (0x0001) ACC_PUBLIC
    Code:
      stack=1, locals=1, args_size=1
         0: aload_0
         1: getfield      #46                 // Field t:Ljava/lang/Object;
         4: areturn
      LineNumberTable:
        line 24: 0
      LocalVariableTable:
        Start  Length  Slot  Name   Signature
            0       5     0  this   Lshapeless/syntax/TypeableOps;
    Signature: #44                          // ()TT;

  public <U extends java.lang.Object> scala.Option<U> cast(shapeless.Typeable<U>);
    descriptor: (Lshapeless/Typeable;)Lscala/Option;
    flags: (0x0001) ACC_PUBLIC
    Code:
      stack=3, locals=2, args_size=2
         0: getstatic     #25                 // Field shapeless/syntax/TypeableOps$.MODULE$:Lshapeless/syntax/TypeableOps$;
         3: aload_0
         4: invokevirtual #53                 // Method t:()Ljava/lang/Object;
         7: aload_1
         8: invokevirtual #42                 // Method shapeless/syntax/TypeableOps$.cast$extension:(Ljava/lang/Object;Lshapeless/Typeable;)Lscala/Option;
        11: areturn
      LineNumberTable:
        line 29: 0
      LocalVariableTable:
        Start  Length  Slot  Name   Signature
            0      12     0  this   Lshapeless/syntax/TypeableOps;
            0      12     1 castU   Lshapeless/Typeable;
    Signature: #51                          // <U:Ljava/lang/Object;>(Lshapeless/Typeable<TU;>;)Lscala/Option<TU;>;
    MethodParameters:
      Name                           Flags
      castU                          final

  public <U extends T> scala.Option<U> narrowTo(shapeless.Typeable<U>);
    descriptor: (Lshapeless/Typeable;)Lscala/Option;
    flags: (0x0001) ACC_PUBLIC
    Code:
      stack=3, locals=2, args_size=2
         0: getstatic     #25                 // Field shapeless/syntax/TypeableOps$.MODULE$:Lshapeless/syntax/TypeableOps$;
         3: aload_0
         4: invokevirtual #53                 // Method t:()Ljava/lang/Object;
         7: aload_1
         8: invokevirtual #38                 // Method shapeless/syntax/TypeableOps$.narrowTo$extension:(Ljava/lang/Object;Lshapeless/Typeable;)Lscala/Option;
        11: areturn
      LineNumberTable:
        line 35: 0
      LocalVariableTable:
        Start  Length  Slot  Name   Signature
            0      12     0  this   Lshapeless/syntax/TypeableOps;
            0      12     1 castU   Lshapeless/Typeable;
    Signature: #56                          // <U:TT;>(Lshapeless/Typeable<TU;>;)Lscala/Option<TU;>;
    MethodParameters:
      Name                           Flags
      castU                          final

  public int hashCode();
    descriptor: ()I
    flags: (0x0001) ACC_PUBLIC
    Code:
      stack=2, locals=1, args_size=1
         0: getstatic     #25                 // Field shapeless/syntax/TypeableOps$.MODULE$:Lshapeless/syntax/TypeableOps$;
         3: aload_0
         4: invokevirtual #53                 // Method t:()Ljava/lang/Object;
         7: invokevirtual #32                 // Method shapeless/syntax/TypeableOps$.hashCode$extension:(Ljava/lang/Object;)I
        10: ireturn
      LineNumberTable:
        line 24: 0
      LocalVariableTable:
        Start  Length  Slot  Name   Signature
            0      11     0  this   Lshapeless/syntax/TypeableOps;

  public boolean equals(java.lang.Object);
    descriptor: (Ljava/lang/Object;)Z
    flags: (0x0001) ACC_PUBLIC
    Code:
      stack=3, locals=2, args_size=2
         0: getstatic     #25                 // Field shapeless/syntax/TypeableOps$.MODULE$:Lshapeless/syntax/TypeableOps$;
         3: aload_0
         4: invokevirtual #53                 // Method t:()Ljava/lang/Object;
         7: aload_1
         8: invokevirtual #27                 // Method shapeless/syntax/TypeableOps$.equals$extension:(Ljava/lang/Object;Ljava/lang/Object;)Z
        11: ireturn
      LineNumberTable:
        line 24: 0
      LocalVariableTable:
        Start  Length  Slot  Name   Signature
            0      12     0  this   Lshapeless/syntax/TypeableOps;
            0      12     1   x$1   Ljava/lang/Object;
    MethodParameters:
      Name                           Flags
      x$1                            final

  public shapeless.syntax.TypeableOps(T);
    descriptor: (Ljava/lang/Object;)V
    flags: (0x0001) ACC_PUBLIC
    Code:
      stack=2, locals=2, args_size=2
         0: aload_0
         1: aload_1
         2: putfield      #46                 // Field t:Ljava/lang/Object;
         5: aload_0
         6: invokespecial #66                 // Method java/lang/Object."<init>":()V
         9: return
      LineNumberTable:
        line 24: 0
      LocalVariableTable:
        Start  Length  Slot  Name   Signature
            0      10     0  this   Lshapeless/syntax/TypeableOps;
            0      10     1     t   Ljava/lang/Object;
    Signature: #63                          // (TT;)V
    MethodParameters:
      Name                           Flags
      t                              final
}
Signature: #3                           // <T:Ljava/lang/Object;>Ljava/lang/Object;Ljava/io/Serializable;
SourceFile: "typeable.scala"
RuntimeVisibleAnnotations:
  0: #9(#10=s#11)
    scala.reflect.ScalaSignature(
      bytes="\u0006\u0005\u0005\u001dc\u0001\u0002\t\u0012\u0005YA\u0001B\u000b\u0001\u0003\u0006\u0004%\ta\u000b\u0005\to\u0001\u0011\t\u0011)A\u0005Y!)\u0001\b\u0001C\u0001s!)Q\b\u0001C\u0001}!)A\n\u0001C\u0001\u001b\"9Q\u000bAA\u0001\n\u00032\u0006b\u0002.\u0001\u0003\u0003%\teW\u0004\bCF\t\t\u0011#\u0001c\r\u001d\u0001\u0012#!A\t\u0002\rDQ\u0001O\u0005\u0005\u00029Dqa\\\u0005\u0002\u0002\u0013%\u0001\u000fC\u0003x\u0013\u0011\u0015\u0001\u0010C\u0004\u0002\f%!)!!\u0004\t\u0013\u0005\u001d\u0012\"!A\u0005\u0006\u0005%\u0002\"CA\u001b\u0013\u0005\u0005IQAA\u001c\u0005-!\u0016\u0010]3bE2,w\n]:\u000b\u0005I\u0019\u0012AB:z]R\f\u0007PC\u0001\u0015\u0003%\u0019\b.\u00199fY\u0016\u001c8o\u0001\u0001\u0016\u0005]q3c\u0001\u0001\u0019=A\u0011\u0011\u0004H\u0007\u00025)\t1$A\u0003tG\u0006d\u0017-\u0003\u0002\u001e5\t1\u0011I\\=WC2\u0004\"aH\u0014\u000f\u0005\u0001*cBA\u0011%\u001b\u0005\u0011#BA\u0012\u0016\u0003\u0019a$o\\8u}%\t1$\u0003\u0002\'5\u00059\u0001/Y2lC\u001e,\u0017B\u0001\u0015*\u00051\u0019VM]5bY&T\u0018M\u00197f\u0015\t1#$A\u0001u+\u0005a\u0003CA\u0017/\u0019\u0001!Qa\f\u0001C\u0002A\u0012\u0011\u0001V\t\u0003cQ\u0002\"!\u0007\u001a\n\u0005MR\"a\u0002(pi\"Lgn\u001a\t\u00033UJ!A\u000e\u000e\u0003\u0007\u0005s\u00170\u0001\u0002uA\u00051A(\u001b8jiz\"\"A\u000f\u001f\u0011\u0007m\u0002A&D\u0001\u0012\u0011\u0015Q3\u00011\u0001-\u0003\u0011\u0019\u0017m\u001d;\u0016\u0005}\"EC\u0001!G!\rI\u0012iQ\u0005\u0003\u0005j\u0011aa\u00149uS>t\u0007CA\u0017E\t\u0015)EA1\u00011\u0005\u0005)\u0006\"B$\u0005\u0001\bA\u0015!B2bgR,\u0006cA%K\u00076\t1#\u0003\u0002L\'\tAA+\u001f9fC\ndW-\u0001\u0005oCJ\u0014xn\u001e+p+\tq\u0015\u000b\u0006\u0002P\'B\u0019\u0011$\u0011)\u0011\u00055\nF!B#\u0006\u0005\u0004\u0011\u0016CA\u0019-\u0011\u00159U\u0001q\u0001U!\rI%\nU\u0001\tQ\u0006\u001c\bnQ8eKR\tq\u000b\u0005\u0002\u001a1&\u0011\u0011L\u0007\u0002\u0004\u0013:$\u0018AB3rk\u0006d7\u000f\u0006\u0002]?B\u0011\u0011$X\u0005\u0003=j\u0011qAQ8pY\u0016\fg\u000eC\u0004a\u000f\u0005\u0005\t\u0019\u0001\u001b\u0002\u0007a$\u0013\'A\u0006UsB,\u0017M\u00197f\u001fB\u001c\bCA\u001e\n\'\rIAm\u001a\t\u00033\u0015L!A\u001a\u000e\u0003\r\u0005s\u0017PU3g!\tAW.D\u0001j\u0015\tQ7.\u0001\u0002j_*\tA.\u0001\u0003kCZ\f\u0017B\u0001\u0015j)\u0005\u0011\u0017\u0001D<sSR,\'+\u001a9mC\u000e,G#A9\u0011\u0005I,X\"A:\u000b\u0005Q\\\u0017\u0001\u00027b]\u001eL!A^:\u0003\r=\u0013\'.Z2u\u00039\u0019\u0017m\u001d;%Kb$XM\\:j_:,B!_?\u0002\nQ\u0019!0!\u0001\u0015\u0005mt\bcA\rByB\u0011Q& \u0003\u0006\u000b2\u0011\r\u0001\r\u0005\u0006\u000f2\u0001\u001da \t\u0004\u0013*c\bbBA\u0002\u0019\u0001\u0007\u0011QA\u0001\u0006IQD\u0017n\u001d\t\u0005w\u0001\t9\u0001E\u0002.\u0003\u0013!Qa\f\u0007C\u0002A\n!C\\1se><Hk\u001c\u0013fqR,gn]5p]V1\u0011qBA\f\u0003;!B!!\u0005\u0002$Q!\u00111CA\u0010!\u0011I\u0012)!\u0006\u0011\u00075\n9\u0002\u0002\u0004F\u001b\t\u0007\u0011\u0011D\t\u0004c\u0005m\u0001cA\u0017\u0002\u001e\u0011)q&\u0004b\u0001a!1q)\u0004a\u0002\u0003C\u0001B!\u0013&\u0002\u0016!9\u00111A\u0007A\u0002\u0005\u0015\u0002\u0003B\u001e\u0001\u00037\t!\u0003[1tQ\u000e{G-\u001a\u0013fqR,gn]5p]V!\u00111FA\u001a)\r1\u0016Q\u0006\u0005\b\u0003\u0007q\u0001\u0019AA\u0018!\u0011Y\u0004!!\r\u0011\u00075\n\u0019\u0004B\u00030\u001d\t\u0007\u0001\'\u0001\tfcV\fGn\u001d\u0013fqR,gn]5p]V!\u0011\u0011HA#)\u0011\tY$a\u0010\u0015\u0007q\u000bi\u0004C\u0004a\u001f\u0005\u0005\t\u0019\u0001\u001b\t\u000f\u0005\rq\u00021\u0001\u0002BA!1\bAA\"!\ri\u0013Q\t\u0003\u0006_=\u0011\r\u0001\r"
    )
  ScalaInlineInfo: length = 0x22 (unknown attribute)
   01 01 00 06 00 3D 00 3E 01 00 31 00 32 01 00 3B
   00 3C 01 00 39 00 3A 01 00 37 00 32 01 00 0C 00
   2B 01
  ScalaSig: length = 0x3 (unknown attribute)
   05 02 00
