Classfile /Users/mw/Projects/slang-braindump/.jar/jar11/assemble/slang-braindump/assemble/content/org/kohsuke/github/extras/OkHttpConnector.class
  Last modified May 29, 2022; size 3478 bytes
  SHA-256 checksum fd3afe4c56a39011e4846e658dbc50fcc54bc107048fa2f7476021b4de0150f6
  Compiled from "OkHttpConnector.java"
public class org.kohsuke.github.extras.OkHttpConnector implements org.kohsuke.github.HttpConnector
  minor version: 0
  major version: 52
  flags: (0x0021) ACC_PUBLIC, ACC_SUPER
  this_class: #18                         // org/kohsuke/github/extras/OkHttpConnector
  super_class: #35                        // java/lang/Object
  interfaces: 1, fields: 3, methods: 5, attributes: 4
Constant pool:
    #1 = Methodref          #18.#81       // org/kohsuke/github/extras/OkHttpConnector."<init>":(Lcom/squareup/okhttp/OkUrlFactory;I)V
    #2 = Methodref          #35.#82       // java/lang/Object."<init>":()V
    #3 = Methodref          #54.#83       // com/squareup/okhttp/OkUrlFactory.client:()Lcom/squareup/okhttp/OkHttpClient;
    #4 = Methodref          #18.#84       // org/kohsuke/github/extras/OkHttpConnector.TlsSocketFactory:()Ljavax/net/ssl/SSLSocketFactory;
    #5 = Methodref          #85.#86       // com/squareup/okhttp/OkHttpClient.setSslSocketFactory:(Ljavax/net/ssl/SSLSocketFactory;)Lcom/squareup/okhttp/OkHttpClient;
    #6 = Methodref          #18.#87       // org/kohsuke/github/extras/OkHttpConnector.TlsConnectionSpecs:()Ljava/util/List;
    #7 = Methodref          #85.#88       // com/squareup/okhttp/OkHttpClient.setConnectionSpecs:(Ljava/util/List;)Lcom/squareup/okhttp/OkHttpClient;
    #8 = Fieldref           #18.#89       // org/kohsuke/github/extras/OkHttpConnector.urlFactory:Lcom/squareup/okhttp/OkUrlFactory;
    #9 = Methodref          #85.#90       // com/squareup/okhttp/OkHttpClient.getCache:()Lcom/squareup/okhttp/Cache;
   #10 = Class              #92           // com/squareup/okhttp/CacheControl$Builder
   #11 = Methodref          #10.#82       // com/squareup/okhttp/CacheControl$Builder."<init>":()V
   #12 = Fieldref           #95.#96       // java/util/concurrent/TimeUnit.SECONDS:Ljava/util/concurrent/TimeUnit;
   #13 = Methodref          #10.#97       // com/squareup/okhttp/CacheControl$Builder.maxAge:(ILjava/util/concurrent/TimeUnit;)Lcom/squareup/okhttp/CacheControl$Builder;
   #14 = Methodref          #10.#98       // com/squareup/okhttp/CacheControl$Builder.build:()Lcom/squareup/okhttp/CacheControl;
   #15 = Methodref          #91.#99       // com/squareup/okhttp/CacheControl.toString:()Ljava/lang/String;
   #16 = Fieldref           #18.#100      // org/kohsuke/github/extras/OkHttpConnector.maxAgeHeaderValue:Ljava/lang/String;
   #17 = Methodref          #54.#101      // com/squareup/okhttp/OkUrlFactory.open:(Ljava/net/URL;)Ljava/net/HttpURLConnection;
   #18 = Class              #102          // org/kohsuke/github/extras/OkHttpConnector
   #19 = String             #103          // Cache-Control
   #20 = Methodref          #61.#104      // java/net/HttpURLConnection.setRequestProperty:(Ljava/lang/String;Ljava/lang/String;)V
   #21 = String             #105          // TLSv1.2
   #22 = Methodref          #71.#106      // javax/net/ssl/SSLContext.getInstance:(Ljava/lang/String;)Ljavax/net/ssl/SSLContext;
   #23 = Class              #107          // java/security/NoSuchAlgorithmException
   #24 = Class              #108          // java/lang/RuntimeException
   #25 = Methodref          #23.#109      // java/security/NoSuchAlgorithmException.getMessage:()Ljava/lang/String;
   #26 = Methodref          #24.#110      // java/lang/RuntimeException."<init>":(Ljava/lang/String;Ljava/lang/Throwable;)V
   #27 = Methodref          #71.#111      // javax/net/ssl/SSLContext.init:([Ljavax/net/ssl/KeyManager;[Ljavax/net/ssl/TrustManager;Ljava/security/SecureRandom;)V
   #28 = Methodref          #71.#112      // javax/net/ssl/SSLContext.getSocketFactory:()Ljavax/net/ssl/SSLSocketFactory;
   #29 = Class              #113          // java/security/KeyManagementException
   #30 = Methodref          #29.#109      // java/security/KeyManagementException.getMessage:()Ljava/lang/String;
   #31 = Class              #114          // com/squareup/okhttp/ConnectionSpec
   #32 = Fieldref           #31.#115      // com/squareup/okhttp/ConnectionSpec.MODERN_TLS:Lcom/squareup/okhttp/ConnectionSpec;
   #33 = Fieldref           #31.#116      // com/squareup/okhttp/ConnectionSpec.CLEARTEXT:Lcom/squareup/okhttp/ConnectionSpec;
   #34 = Methodref          #117.#118     // java/util/Arrays.asList:([Ljava/lang/Object;)Ljava/util/List;
   #35 = Class              #119          // java/lang/Object
   #36 = Class              #120          // org/kohsuke/github/HttpConnector
   #37 = Utf8               HEADER_NAME
   #38 = Utf8               Ljava/lang/String;
   #39 = Utf8               ConstantValue
   #40 = Utf8               urlFactory
   #41 = Utf8               Lcom/squareup/okhttp/OkUrlFactory;
   #42 = Utf8               maxAgeHeaderValue
   #43 = Utf8               <init>
   #44 = Utf8               (Lcom/squareup/okhttp/OkUrlFactory;)V
   #45 = Utf8               Code
   #46 = Utf8               LineNumberTable
   #47 = Utf8               LocalVariableTable
   #48 = Utf8               this
   #49 = Utf8               Lorg/kohsuke/github/extras/OkHttpConnector;
   #50 = Utf8               (Lcom/squareup/okhttp/OkUrlFactory;I)V
   #51 = Utf8               cacheMaxAge
   #52 = Utf8               I
   #53 = Utf8               StackMapTable
   #54 = Class              #121          // com/squareup/okhttp/OkUrlFactory
   #55 = Utf8               connect
   #56 = Utf8               (Ljava/net/URL;)Ljava/net/HttpURLConnection;
   #57 = Utf8               url
   #58 = Utf8               Ljava/net/URL;
   #59 = Utf8               urlConnection
   #60 = Utf8               Ljava/net/HttpURLConnection;
   #61 = Class              #122          // java/net/HttpURLConnection
   #62 = Utf8               Exceptions
   #63 = Class              #123          // java/io/IOException
   #64 = Utf8               TlsSocketFactory
   #65 = Utf8               ()Ljavax/net/ssl/SSLSocketFactory;
   #66 = Utf8               sc
   #67 = Utf8               Ljavax/net/ssl/SSLContext;
   #68 = Utf8               e
   #69 = Utf8               Ljava/security/NoSuchAlgorithmException;
   #70 = Utf8               Ljava/security/KeyManagementException;
   #71 = Class              #124          // javax/net/ssl/SSLContext
   #72 = Utf8               TlsConnectionSpecs
   #73 = Utf8               ()Ljava/util/List;
   #74 = Utf8               Signature
   #75 = Utf8               ()Ljava/util/List<Lcom/squareup/okhttp/ConnectionSpec;>;
   #76 = Utf8               SourceFile
   #77 = Utf8               OkHttpConnector.java
   #78 = Utf8               Deprecated
   #79 = Utf8               RuntimeVisibleAnnotations
   #80 = Utf8               Ljava/lang/Deprecated;
   #81 = NameAndType        #43:#50       // "<init>":(Lcom/squareup/okhttp/OkUrlFactory;I)V
   #82 = NameAndType        #43:#125      // "<init>":()V
   #83 = NameAndType        #126:#127     // client:()Lcom/squareup/okhttp/OkHttpClient;
   #84 = NameAndType        #64:#65       // TlsSocketFactory:()Ljavax/net/ssl/SSLSocketFactory;
   #85 = Class              #128          // com/squareup/okhttp/OkHttpClient
   #86 = NameAndType        #129:#130     // setSslSocketFactory:(Ljavax/net/ssl/SSLSocketFactory;)Lcom/squareup/okhttp/OkHttpClient;
   #87 = NameAndType        #72:#73       // TlsConnectionSpecs:()Ljava/util/List;
   #88 = NameAndType        #131:#132     // setConnectionSpecs:(Ljava/util/List;)Lcom/squareup/okhttp/OkHttpClient;
   #89 = NameAndType        #40:#41       // urlFactory:Lcom/squareup/okhttp/OkUrlFactory;
   #90 = NameAndType        #133:#134     // getCache:()Lcom/squareup/okhttp/Cache;
   #91 = Class              #135          // com/squareup/okhttp/CacheControl
   #92 = Utf8               com/squareup/okhttp/CacheControl$Builder
   #93 = Utf8               Builder
   #94 = Utf8               InnerClasses
   #95 = Class              #136          // java/util/concurrent/TimeUnit
   #96 = NameAndType        #137:#138     // SECONDS:Ljava/util/concurrent/TimeUnit;
   #97 = NameAndType        #139:#140     // maxAge:(ILjava/util/concurrent/TimeUnit;)Lcom/squareup/okhttp/CacheControl$Builder;
   #98 = NameAndType        #141:#142     // build:()Lcom/squareup/okhttp/CacheControl;
   #99 = NameAndType        #143:#144     // toString:()Ljava/lang/String;
  #100 = NameAndType        #42:#38       // maxAgeHeaderValue:Ljava/lang/String;
  #101 = NameAndType        #145:#56      // open:(Ljava/net/URL;)Ljava/net/HttpURLConnection;
  #102 = Utf8               org/kohsuke/github/extras/OkHttpConnector
  #103 = Utf8               Cache-Control
  #104 = NameAndType        #146:#147     // setRequestProperty:(Ljava/lang/String;Ljava/lang/String;)V
  #105 = Utf8               TLSv1.2
  #106 = NameAndType        #148:#149     // getInstance:(Ljava/lang/String;)Ljavax/net/ssl/SSLContext;
  #107 = Utf8               java/security/NoSuchAlgorithmException
  #108 = Utf8               java/lang/RuntimeException
  #109 = NameAndType        #150:#144     // getMessage:()Ljava/lang/String;
  #110 = NameAndType        #43:#151      // "<init>":(Ljava/lang/String;Ljava/lang/Throwable;)V
  #111 = NameAndType        #152:#153     // init:([Ljavax/net/ssl/KeyManager;[Ljavax/net/ssl/TrustManager;Ljava/security/SecureRandom;)V
  #112 = NameAndType        #154:#65      // getSocketFactory:()Ljavax/net/ssl/SSLSocketFactory;
  #113 = Utf8               java/security/KeyManagementException
  #114 = Utf8               com/squareup/okhttp/ConnectionSpec
  #115 = NameAndType        #155:#156     // MODERN_TLS:Lcom/squareup/okhttp/ConnectionSpec;
  #116 = NameAndType        #157:#156     // CLEARTEXT:Lcom/squareup/okhttp/ConnectionSpec;
  #117 = Class              #158          // java/util/Arrays
  #118 = NameAndType        #159:#160     // asList:([Ljava/lang/Object;)Ljava/util/List;
  #119 = Utf8               java/lang/Object
  #120 = Utf8               org/kohsuke/github/HttpConnector
  #121 = Utf8               com/squareup/okhttp/OkUrlFactory
  #122 = Utf8               java/net/HttpURLConnection
  #123 = Utf8               java/io/IOException
  #124 = Utf8               javax/net/ssl/SSLContext
  #125 = Utf8               ()V
  #126 = Utf8               client
  #127 = Utf8               ()Lcom/squareup/okhttp/OkHttpClient;
  #128 = Utf8               com/squareup/okhttp/OkHttpClient
  #129 = Utf8               setSslSocketFactory
  #130 = Utf8               (Ljavax/net/ssl/SSLSocketFactory;)Lcom/squareup/okhttp/OkHttpClient;
  #131 = Utf8               setConnectionSpecs
  #132 = Utf8               (Ljava/util/List;)Lcom/squareup/okhttp/OkHttpClient;
  #133 = Utf8               getCache
  #134 = Utf8               ()Lcom/squareup/okhttp/Cache;
  #135 = Utf8               com/squareup/okhttp/CacheControl
  #136 = Utf8               java/util/concurrent/TimeUnit
  #137 = Utf8               SECONDS
  #138 = Utf8               Ljava/util/concurrent/TimeUnit;
  #139 = Utf8               maxAge
  #140 = Utf8               (ILjava/util/concurrent/TimeUnit;)Lcom/squareup/okhttp/CacheControl$Builder;
  #141 = Utf8               build
  #142 = Utf8               ()Lcom/squareup/okhttp/CacheControl;
  #143 = Utf8               toString
  #144 = Utf8               ()Ljava/lang/String;
  #145 = Utf8               open
  #146 = Utf8               setRequestProperty
  #147 = Utf8               (Ljava/lang/String;Ljava/lang/String;)V
  #148 = Utf8               getInstance
  #149 = Utf8               (Ljava/lang/String;)Ljavax/net/ssl/SSLContext;
  #150 = Utf8               getMessage
  #151 = Utf8               (Ljava/lang/String;Ljava/lang/Throwable;)V
  #152 = Utf8               init
  #153 = Utf8               ([Ljavax/net/ssl/KeyManager;[Ljavax/net/ssl/TrustManager;Ljava/security/SecureRandom;)V
  #154 = Utf8               getSocketFactory
  #155 = Utf8               MODERN_TLS
  #156 = Utf8               Lcom/squareup/okhttp/ConnectionSpec;
  #157 = Utf8               CLEARTEXT
  #158 = Utf8               java/util/Arrays
  #159 = Utf8               asList
  #160 = Utf8               ([Ljava/lang/Object;)Ljava/util/List;
{
  private static final java.lang.String HEADER_NAME;
    descriptor: Ljava/lang/String;
    flags: (0x001a) ACC_PRIVATE, ACC_STATIC, ACC_FINAL
    ConstantValue: String Cache-Control

  private final com.squareup.okhttp.OkUrlFactory urlFactory;
    descriptor: Lcom/squareup/okhttp/OkUrlFactory;
    flags: (0x0012) ACC_PRIVATE, ACC_FINAL

  private final java.lang.String maxAgeHeaderValue;
    descriptor: Ljava/lang/String;
    flags: (0x0012) ACC_PRIVATE, ACC_FINAL

  public org.kohsuke.github.extras.OkHttpConnector(com.squareup.okhttp.OkUrlFactory);
    descriptor: (Lcom/squareup/okhttp/OkUrlFactory;)V
    flags: (0x0001) ACC_PUBLIC
    Code:
      stack=3, locals=2, args_size=2
         0: aload_0
         1: aload_1
         2: iconst_0
         3: invokespecial #1                  // Method "<init>":(Lcom/squareup/okhttp/OkUrlFactory;I)V
         6: return
      LineNumberTable:
        line 47: 0
        line 48: 6
      LocalVariableTable:
        Start  Length  Slot  Name   Signature
            0       7     0  this   Lorg/kohsuke/github/extras/OkHttpConnector;
            0       7     1 urlFactory   Lcom/squareup/okhttp/OkUrlFactory;

  org.kohsuke.github.extras.OkHttpConnector(com.squareup.okhttp.OkUrlFactory, int);
    descriptor: (Lcom/squareup/okhttp/OkUrlFactory;I)V
    flags: (0x0000)
    Code:
      stack=4, locals=3, args_size=3
         0: aload_0
         1: invokespecial #2                  // Method java/lang/Object."<init>":()V
         4: aload_1
         5: invokevirtual #3                  // Method com/squareup/okhttp/OkUrlFactory.client:()Lcom/squareup/okhttp/OkHttpClient;
         8: aload_0
         9: invokespecial #4                  // Method TlsSocketFactory:()Ljavax/net/ssl/SSLSocketFactory;
        12: invokevirtual #5                  // Method com/squareup/okhttp/OkHttpClient.setSslSocketFactory:(Ljavax/net/ssl/SSLSocketFactory;)Lcom/squareup/okhttp/OkHttpClient;
        15: pop
        16: aload_1
        17: invokevirtual #3                  // Method com/squareup/okhttp/OkUrlFactory.client:()Lcom/squareup/okhttp/OkHttpClient;
        20: aload_0
        21: invokespecial #6                  // Method TlsConnectionSpecs:()Ljava/util/List;
        24: invokevirtual #7                  // Method com/squareup/okhttp/OkHttpClient.setConnectionSpecs:(Ljava/util/List;)Lcom/squareup/okhttp/OkHttpClient;
        27: pop
        28: aload_0
        29: aload_1
        30: putfield      #8                  // Field urlFactory:Lcom/squareup/okhttp/OkUrlFactory;
        33: iload_2
        34: iflt          81
        37: aload_1
        38: invokevirtual #3                  // Method com/squareup/okhttp/OkUrlFactory.client:()Lcom/squareup/okhttp/OkHttpClient;
        41: ifnull        81
        44: aload_1
        45: invokevirtual #3                  // Method com/squareup/okhttp/OkUrlFactory.client:()Lcom/squareup/okhttp/OkHttpClient;
        48: invokevirtual #9                  // Method com/squareup/okhttp/OkHttpClient.getCache:()Lcom/squareup/okhttp/Cache;
        51: ifnull        81
        54: aload_0
        55: new           #10                 // class com/squareup/okhttp/CacheControl$Builder
        58: dup
        59: invokespecial #11                 // Method com/squareup/okhttp/CacheControl$Builder."<init>":()V
        62: iload_2
        63: getstatic     #12                 // Field java/util/concurrent/TimeUnit.SECONDS:Ljava/util/concurrent/TimeUnit;
        66: invokevirtual #13                 // Method com/squareup/okhttp/CacheControl$Builder.maxAge:(ILjava/util/concurrent/TimeUnit;)Lcom/squareup/okhttp/CacheControl$Builder;
        69: invokevirtual #14                 // Method com/squareup/okhttp/CacheControl$Builder.build:()Lcom/squareup/okhttp/CacheControl;
        72: invokevirtual #15                 // Method com/squareup/okhttp/CacheControl.toString:()Ljava/lang/String;
        75: putfield      #16                 // Field maxAgeHeaderValue:Ljava/lang/String;
        78: goto          86
        81: aload_0
        82: aconst_null
        83: putfield      #16                 // Field maxAgeHeaderValue:Ljava/lang/String;
        86: return
      LineNumberTable:
        line 56: 0
        line 57: 4
        line 58: 16
        line 59: 28
        line 61: 33
        line 62: 54
        line 64: 81
        line 66: 86
      LocalVariableTable:
        Start  Length  Slot  Name   Signature
            0      87     0  this   Lorg/kohsuke/github/extras/OkHttpConnector;
            0      87     1 urlFactory   Lcom/squareup/okhttp/OkUrlFactory;
            0      87     2 cacheMaxAge   I
      StackMapTable: number_of_entries = 2
        frame_type = 255 /* full_frame */
          offset_delta = 81
          locals = [ class org/kohsuke/github/extras/OkHttpConnector, class com/squareup/okhttp/OkUrlFactory, int ]
          stack = []
        frame_type = 4 /* same */

  public java.net.HttpURLConnection connect(java.net.URL) throws java.io.IOException;
    descriptor: (Ljava/net/URL;)Ljava/net/HttpURLConnection;
    flags: (0x0001) ACC_PUBLIC
    Code:
      stack=3, locals=3, args_size=2
         0: aload_0
         1: getfield      #8                  // Field urlFactory:Lcom/squareup/okhttp/OkUrlFactory;
         4: aload_1
         5: invokevirtual #17                 // Method com/squareup/okhttp/OkUrlFactory.open:(Ljava/net/URL;)Ljava/net/HttpURLConnection;
         8: astore_2
         9: aload_0
        10: getfield      #16                 // Field maxAgeHeaderValue:Ljava/lang/String;
        13: ifnull        26
        16: aload_2
        17: ldc           #19                 // String Cache-Control
        19: aload_0
        20: getfield      #16                 // Field maxAgeHeaderValue:Ljava/lang/String;
        23: invokevirtual #20                 // Method java/net/HttpURLConnection.setRequestProperty:(Ljava/lang/String;Ljava/lang/String;)V
        26: aload_2
        27: areturn
      LineNumberTable:
        line 69: 0
        line 70: 9
        line 77: 16
        line 80: 26
      LocalVariableTable:
        Start  Length  Slot  Name   Signature
            0      28     0  this   Lorg/kohsuke/github/extras/OkHttpConnector;
            0      28     1   url   Ljava/net/URL;
            9      19     2 urlConnection   Ljava/net/HttpURLConnection;
      StackMapTable: number_of_entries = 1
        frame_type = 252 /* append */
          offset_delta = 26
          locals = [ class java/net/HttpURLConnection ]
    Exceptions:
      throws java.io.IOException

  private javax.net.ssl.SSLSocketFactory TlsSocketFactory();
    descriptor: ()Ljavax/net/ssl/SSLSocketFactory;
    flags: (0x0002) ACC_PRIVATE
    Code:
      stack=4, locals=3, args_size=1
         0: ldc           #21                 // String TLSv1.2
         2: invokestatic  #22                 // Method javax/net/ssl/SSLContext.getInstance:(Ljava/lang/String;)Ljavax/net/ssl/SSLContext;
         5: astore_1
         6: goto          23
         9: astore_2
        10: new           #24                 // class java/lang/RuntimeException
        13: dup
        14: aload_2
        15: invokevirtual #25                 // Method java/security/NoSuchAlgorithmException.getMessage:()Ljava/lang/String;
        18: aload_2
        19: invokespecial #26                 // Method java/lang/RuntimeException."<init>":(Ljava/lang/String;Ljava/lang/Throwable;)V
        22: athrow
        23: aload_1
        24: aconst_null
        25: aconst_null
        26: aconst_null
        27: invokevirtual #27                 // Method javax/net/ssl/SSLContext.init:([Ljavax/net/ssl/KeyManager;[Ljavax/net/ssl/TrustManager;Ljava/security/SecureRandom;)V
        30: aload_1
        31: invokevirtual #28                 // Method javax/net/ssl/SSLContext.getSocketFactory:()Ljavax/net/ssl/SSLSocketFactory;
        34: areturn
        35: astore_2
        36: new           #24                 // class java/lang/RuntimeException
        39: dup
        40: aload_2
        41: invokevirtual #30                 // Method java/security/KeyManagementException.getMessage:()Ljava/lang/String;
        44: aload_2
        45: invokespecial #26                 // Method java/lang/RuntimeException."<init>":(Ljava/lang/String;Ljava/lang/Throwable;)V
        48: athrow
      Exception table:
         from    to  target type
             0     6     9   Class java/security/NoSuchAlgorithmException
            23    34    35   Class java/security/KeyManagementException
      LineNumberTable:
        line 87: 0
        line 90: 6
        line 88: 9
        line 89: 10
        line 92: 23
        line 93: 30
        line 94: 35
        line 95: 36
      LocalVariableTable:
        Start  Length  Slot  Name   Signature
            6       3     1    sc   Ljavax/net/ssl/SSLContext;
           10      13     2     e   Ljava/security/NoSuchAlgorithmException;
           36      13     2     e   Ljava/security/KeyManagementException;
            0      49     0  this   Lorg/kohsuke/github/extras/OkHttpConnector;
           23      26     1    sc   Ljavax/net/ssl/SSLContext;
      StackMapTable: number_of_entries = 3
        frame_type = 73 /* same_locals_1_stack_item */
          stack = [ class java/security/NoSuchAlgorithmException ]
        frame_type = 252 /* append */
          offset_delta = 13
          locals = [ class javax/net/ssl/SSLContext ]
        frame_type = 75 /* same_locals_1_stack_item */
          stack = [ class java/security/KeyManagementException ]

  private java.util.List<com.squareup.okhttp.ConnectionSpec> TlsConnectionSpecs();
    descriptor: ()Ljava/util/List;
    flags: (0x0002) ACC_PRIVATE
    Code:
      stack=4, locals=1, args_size=1
         0: iconst_2
         1: anewarray     #31                 // class com/squareup/okhttp/ConnectionSpec
         4: dup
         5: iconst_0
         6: getstatic     #32                 // Field com/squareup/okhttp/ConnectionSpec.MODERN_TLS:Lcom/squareup/okhttp/ConnectionSpec;
         9: aastore
        10: dup
        11: iconst_1
        12: getstatic     #33                 // Field com/squareup/okhttp/ConnectionSpec.CLEARTEXT:Lcom/squareup/okhttp/ConnectionSpec;
        15: aastore
        16: invokestatic  #34                 // Method java/util/Arrays.asList:([Ljava/lang/Object;)Ljava/util/List;
        19: areturn
      LineNumberTable:
        line 101: 0
      LocalVariableTable:
        Start  Length  Slot  Name   Signature
            0      20     0  this   Lorg/kohsuke/github/extras/OkHttpConnector;
    Signature: #75                          // ()Ljava/util/List<Lcom/squareup/okhttp/ConnectionSpec;>;
}
SourceFile: "OkHttpConnector.java"
Deprecated: true
RuntimeVisibleAnnotations:
  0: #80()
    java.lang.Deprecated
InnerClasses:
  public static final #93= #10 of #91;    // Builder=class com/squareup/okhttp/CacheControl$Builder of class com/squareup/okhttp/CacheControl
