Classfile /Users/mw/Projects/slang-braindump/.jar/jar11/assemble/slang-braindump/assemble/content/org/sireum/bitcodec/Spec_Ext.class
  Last modified May 29, 2022; size 1271 bytes
  SHA-256 checksum 69d93511dee249a77c300cd07ae4505048f696059210b937a47331ef459d936b
  Compiled from "Spec_Ext.scala"
public final class org.sireum.bitcodec.Spec_Ext
  minor version: 0
  major version: 52
  flags: (0x0031) ACC_PUBLIC, ACC_FINAL, ACC_SUPER
  this_class: #2                          // org/sireum/bitcodec/Spec_Ext
  super_class: #4                         // java/lang/Object
  interfaces: 0, fields: 0, methods: 2, attributes: 4
Constant pool:
   #1 = Utf8               org/sireum/bitcodec/Spec_Ext
   #2 = Class              #1             // org/sireum/bitcodec/Spec_Ext
   #3 = Utf8               java/lang/Object
   #4 = Class              #3             // java/lang/Object
   #5 = Utf8               Spec_Ext.scala
   #6 = Utf8               Lscala/reflect/ScalaSignature;
   #7 = Utf8               bytes
   #8 = Utf8               \u0006\u0005]:Q!\u0002\u0004\t\u000251Qa\u0004\u0004\t\u0002AAQaF\u0001\u0005\u0002aAQ!G\u0001\u0005\u0002iAQ!K\u0001\u0005\u0002)\n\u0001b\u00159fG~+\u0005\u0010\u001e\u0006\u0003\u000f!\t\u0001BY5uG>$Wm\u0019\u0006\u0003\u0013)\taa]5sKVl\'\"A\u0006\u0002\u0007=\u0014xm\u0001\u0001\u0011\u00059\tQ\"\u0001\u0004\u0003\u0011M\u0003XmY0FqR\u001c\"!A\t\u0011\u0005I)R\"A\n\u000b\u0003Q\tQa]2bY\u0006L!AF\n\u0003\r\u0005s\u0017PU3g\u0003\u0019a\u0014N\\5u}Q\tQ\"\u0001\u0004u_*\u001bvJ\u0014\u000b\u00047}!\u0003C\u0001\u000f\u001e\u001b\u0005A\u0011B\u0001\u0010\t\u0005\u0019\u0019FO]5oO\")\u0001e\u0001a\u0001C\u0005\tq\u000e\u0005\u0002\u000fE%\u00111E\u0002\u0002\u0005\'B,7\rC\u0003&\u0007\u0001\u0007a%A\u0005jg\u000e{W\u000e]1diB\u0011AdJ\u0005\u0003Q!\u0011\u0011AQ\u0001\tMJ|WNS*P\u001dR\u00111&\u000e\t\u000591\nc&\u0003\u0002.\u0011\t1Q)\u001b;iKJ\u0004\"a\f\u001a\u000f\u0005q\u0001\u0014BA\u0019\t\u0003\u0011Q5o\u001c8\n\u0005M\"$\u0001C#se>\u0014Xj]4\u000b\u0005EB\u0001\"\u0002\u001c\u0005\u0001\u0004Y\u0012!A:
   #9 = Utf8               org/sireum/Json$ErrorMsg
  #10 = Class              #9             // org/sireum/Json$ErrorMsg
  #11 = Utf8               org/sireum/Json
  #12 = Class              #11            // org/sireum/Json
  #13 = Utf8               ErrorMsg
  #14 = Utf8               fromJSON
  #15 = Utf8               (Ljava/lang/String;)Lorg/sireum/Either;
  #16 = Utf8               (Ljava/lang/String;)Lorg/sireum/Either<Lorg/sireum/bitcodec/Spec;Lorg/sireum/Json$ErrorMsg;>;
  #17 = Utf8               s
  #18 = Utf8               org/sireum/bitcodec/Spec_Ext$
  #19 = Class              #18            // org/sireum/bitcodec/Spec_Ext$
  #20 = Utf8               MODULE$
  #21 = Utf8               Lorg/sireum/bitcodec/Spec_Ext$;
  #22 = NameAndType        #20:#21        // MODULE$:Lorg/sireum/bitcodec/Spec_Ext$;
  #23 = Fieldref           #19.#22        // org/sireum/bitcodec/Spec_Ext$.MODULE$:Lorg/sireum/bitcodec/Spec_Ext$;
  #24 = NameAndType        #14:#15        // fromJSON:(Ljava/lang/String;)Lorg/sireum/Either;
  #25 = Methodref          #19.#24        // org/sireum/bitcodec/Spec_Ext$.fromJSON:(Ljava/lang/String;)Lorg/sireum/Either;
  #26 = Utf8               Ljava/lang/String;
  #27 = Utf8               toJSON
  #28 = Utf8               (Lorg/sireum/bitcodec/Spec;Z)Ljava/lang/String;
  #29 = Utf8               o
  #30 = Utf8               isCompact
  #31 = NameAndType        #27:#28        // toJSON:(Lorg/sireum/bitcodec/Spec;Z)Ljava/lang/String;
  #32 = Methodref          #19.#31        // org/sireum/bitcodec/Spec_Ext$.toJSON:(Lorg/sireum/bitcodec/Spec;Z)Ljava/lang/String;
  #33 = Utf8               Lorg/sireum/bitcodec/Spec;
  #34 = Utf8               Z
  #35 = Utf8               Code
  #36 = Utf8               LocalVariableTable
  #37 = Utf8               Signature
  #38 = Utf8               MethodParameters
  #39 = Utf8               InnerClasses
  #40 = Utf8               SourceFile
  #41 = Utf8               RuntimeVisibleAnnotations
  #42 = Utf8               ScalaSig
{
  public static org.sireum.Either<org.sireum.bitcodec.Spec, org.sireum.Json$ErrorMsg> fromJSON(java.lang.String);
    descriptor: (Ljava/lang/String;)Lorg/sireum/Either;
    flags: (0x0009) ACC_PUBLIC, ACC_STATIC
    Code:
      stack=2, locals=1, args_size=1
         0: getstatic     #23                 // Field org/sireum/bitcodec/Spec_Ext$.MODULE$:Lorg/sireum/bitcodec/Spec_Ext$;
         3: aload_0
         4: invokevirtual #25                 // Method org/sireum/bitcodec/Spec_Ext$.fromJSON:(Ljava/lang/String;)Lorg/sireum/Either;
         7: areturn
      LocalVariableTable:
        Start  Length  Slot  Name   Signature
            0       8     0     s   Ljava/lang/String;
    Signature: #16                          // (Ljava/lang/String;)Lorg/sireum/Either<Lorg/sireum/bitcodec/Spec;Lorg/sireum/Json$ErrorMsg;>;
    MethodParameters:
      Name                           Flags
      s                              final

  public static java.lang.String toJSON(org.sireum.bitcodec.Spec, boolean);
    descriptor: (Lorg/sireum/bitcodec/Spec;Z)Ljava/lang/String;
    flags: (0x0009) ACC_PUBLIC, ACC_STATIC
    Code:
      stack=3, locals=2, args_size=2
         0: getstatic     #23                 // Field org/sireum/bitcodec/Spec_Ext$.MODULE$:Lorg/sireum/bitcodec/Spec_Ext$;
         3: aload_0
         4: iload_1
         5: invokevirtual #32                 // Method org/sireum/bitcodec/Spec_Ext$.toJSON:(Lorg/sireum/bitcodec/Spec;Z)Ljava/lang/String;
         8: areturn
      LocalVariableTable:
        Start  Length  Slot  Name   Signature
            0       9     0     o   Lorg/sireum/bitcodec/Spec;
            0       9     1 isCompact   Z
    MethodParameters:
      Name                           Flags
      o                              final
      isCompact                      final
}
InnerClasses:
  public static final #13= #10 of #12;    // ErrorMsg=class org/sireum/Json$ErrorMsg of class org/sireum/Json
SourceFile: "Spec_Ext.scala"
RuntimeVisibleAnnotations:
  0: #6(#7=s#8)
    scala.reflect.ScalaSignature(
      bytes="\u0006\u0005]:Q!\u0002\u0004\t\u000251Qa\u0004\u0004\t\u0002AAQaF\u0001\u0005\u0002aAQ!G\u0001\u0005\u0002iAQ!K\u0001\u0005\u0002)\n\u0001b\u00159fG~+\u0005\u0010\u001e\u0006\u0003\u000f!\t\u0001BY5uG>$Wm\u0019\u0006\u0003\u0013)\taa]5sKVl\'\"A\u0006\u0002\u0007=\u0014xm\u0001\u0001\u0011\u00059\tQ\"\u0001\u0004\u0003\u0011M\u0003XmY0FqR\u001c\"!A\t\u0011\u0005I)R\"A\n\u000b\u0003Q\tQa]2bY\u0006L!AF\n\u0003\r\u0005s\u0017PU3g\u0003\u0019a\u0014N\\5u}Q\tQ\"\u0001\u0004u_*\u001bvJ\u0014\u000b\u00047}!\u0003C\u0001\u000f\u001e\u001b\u0005A\u0011B\u0001\u0010\t\u0005\u0019\u0019FO]5oO\")\u0001e\u0001a\u0001C\u0005\tq\u000e\u0005\u0002\u000fE%\u00111E\u0002\u0002\u0005\'B,7\rC\u0003&\u0007\u0001\u0007a%A\u0005jg\u000e{W\u000e]1diB\u0011AdJ\u0005\u0003Q!\u0011\u0011AQ\u0001\tMJ|WNS*P\u001dR\u00111&\u000e\t\u000591\nc&\u0003\u0002.\u0011\t1Q)\u001b;iKJ\u0004\"a\f\u001a\u000f\u0005q\u0001\u0014BA\u0019\t\u0003\u0011Q5o\u001c8\n\u0005M\"$\u0001C#se>\u0014Xj]4\u000b\u0005EB\u0001\"\u0002\u001c\u0005\u0001\u0004Y\u0012!A:"
    )
  ScalaSig: length = 0x3 (unknown attribute)
   05 02 00
