Classfile /Users/mw/Projects/slang-braindump/.jar/jar8/assemble/slang-braindump/assemble/content/com/fasterxml/jackson/core/util/JsonParserDelegate.class
  Last modified May 29, 2022; size 10793 bytes
  SHA-256 checksum 4b80e0dcf1f9e7c8cdb4e798404fb3ae3788de0d2860a24f69576100c015ad4e
  Compiled from "JsonParserDelegate.java"
public class com.fasterxml.jackson.core.util.JsonParserDelegate extends com.fasterxml.jackson.core.JsonParser
  minor version: 0
  major version: 50
  flags: (0x0021) ACC_PUBLIC, ACC_SUPER
  this_class: #83                         // com/fasterxml/jackson/core/util/JsonParserDelegate
  super_class: #84                        // com/fasterxml/jackson/core/JsonParser
  interfaces: 0, fields: 1, methods: 84, attributes: 2
Constant pool:
    #1 = Methodref          #84.#254      // com/fasterxml/jackson/core/JsonParser."<init>":()V
    #2 = Fieldref           #83.#255      // com/fasterxml/jackson/core/util/JsonParserDelegate.delegate:Lcom/fasterxml/jackson/core/JsonParser;
    #3 = Methodref          #84.#256      // com/fasterxml/jackson/core/JsonParser.setCodec:(Lcom/fasterxml/jackson/core/ObjectCodec;)V
    #4 = Methodref          #84.#257      // com/fasterxml/jackson/core/JsonParser.getCodec:()Lcom/fasterxml/jackson/core/ObjectCodec;
    #5 = Methodref          #84.#258      // com/fasterxml/jackson/core/JsonParser.enable:(Lcom/fasterxml/jackson/core/JsonParser$Feature;)Lcom/fasterxml/jackson/core/JsonParser;
    #6 = Methodref          #84.#259      // com/fasterxml/jackson/core/JsonParser.disable:(Lcom/fasterxml/jackson/core/JsonParser$Feature;)Lcom/fasterxml/jackson/core/JsonParser;
    #7 = Methodref          #84.#260      // com/fasterxml/jackson/core/JsonParser.isEnabled:(Lcom/fasterxml/jackson/core/JsonParser$Feature;)Z
    #8 = Methodref          #84.#261      // com/fasterxml/jackson/core/JsonParser.getFeatureMask:()I
    #9 = Methodref          #84.#262      // com/fasterxml/jackson/core/JsonParser.setFeatureMask:(I)Lcom/fasterxml/jackson/core/JsonParser;
   #10 = Methodref          #84.#263      // com/fasterxml/jackson/core/JsonParser.overrideStdFeatures:(II)Lcom/fasterxml/jackson/core/JsonParser;
   #11 = Methodref          #84.#264      // com/fasterxml/jackson/core/JsonParser.overrideFormatFeatures:(II)Lcom/fasterxml/jackson/core/JsonParser;
   #12 = Methodref          #84.#265      // com/fasterxml/jackson/core/JsonParser.getSchema:()Lcom/fasterxml/jackson/core/FormatSchema;
   #13 = Methodref          #84.#266      // com/fasterxml/jackson/core/JsonParser.setSchema:(Lcom/fasterxml/jackson/core/FormatSchema;)V
   #14 = Methodref          #84.#267      // com/fasterxml/jackson/core/JsonParser.canUseSchema:(Lcom/fasterxml/jackson/core/FormatSchema;)Z
   #15 = Methodref          #84.#268      // com/fasterxml/jackson/core/JsonParser.version:()Lcom/fasterxml/jackson/core/Version;
   #16 = Methodref          #84.#269      // com/fasterxml/jackson/core/JsonParser.getInputSource:()Ljava/lang/Object;
   #17 = Methodref          #84.#270      // com/fasterxml/jackson/core/JsonParser.requiresCustomCodec:()Z
   #18 = Methodref          #84.#271      // com/fasterxml/jackson/core/JsonParser.getReadCapabilities:()Lcom/fasterxml/jackson/core/util/JacksonFeatureSet;
   #19 = Methodref          #84.#272      // com/fasterxml/jackson/core/JsonParser.close:()V
   #20 = Methodref          #84.#273      // com/fasterxml/jackson/core/JsonParser.isClosed:()Z
   #21 = Methodref          #84.#274      // com/fasterxml/jackson/core/JsonParser.clearCurrentToken:()V
   #22 = Methodref          #84.#275      // com/fasterxml/jackson/core/JsonParser.getLastClearedToken:()Lcom/fasterxml/jackson/core/JsonToken;
   #23 = Methodref          #84.#276      // com/fasterxml/jackson/core/JsonParser.overrideCurrentName:(Ljava/lang/String;)V
   #24 = Methodref          #84.#277      // com/fasterxml/jackson/core/JsonParser.assignCurrentValue:(Ljava/lang/Object;)V
   #25 = Methodref          #84.#278      // com/fasterxml/jackson/core/JsonParser.setCurrentValue:(Ljava/lang/Object;)V
   #26 = Methodref          #84.#279      // com/fasterxml/jackson/core/JsonParser.getParsingContext:()Lcom/fasterxml/jackson/core/JsonStreamContext;
   #27 = Methodref          #84.#280      // com/fasterxml/jackson/core/JsonParser.currentToken:()Lcom/fasterxml/jackson/core/JsonToken;
   #28 = Methodref          #84.#281      // com/fasterxml/jackson/core/JsonParser.currentTokenId:()I
   #29 = Methodref          #84.#282      // com/fasterxml/jackson/core/JsonParser.currentName:()Ljava/lang/String;
   #30 = Methodref          #84.#283      // com/fasterxml/jackson/core/JsonParser.currentValue:()Ljava/lang/Object;
   #31 = Methodref          #84.#284      // com/fasterxml/jackson/core/JsonParser.getCurrentLocation:()Lcom/fasterxml/jackson/core/JsonLocation;
   #32 = Methodref          #84.#285      // com/fasterxml/jackson/core/JsonParser.getTokenLocation:()Lcom/fasterxml/jackson/core/JsonLocation;
   #33 = Methodref          #84.#286      // com/fasterxml/jackson/core/JsonParser.getCurrentToken:()Lcom/fasterxml/jackson/core/JsonToken;
   #34 = Methodref          #84.#287      // com/fasterxml/jackson/core/JsonParser.getCurrentTokenId:()I
   #35 = Methodref          #84.#288      // com/fasterxml/jackson/core/JsonParser.getCurrentName:()Ljava/lang/String;
   #36 = Methodref          #84.#289      // com/fasterxml/jackson/core/JsonParser.getCurrentValue:()Ljava/lang/Object;
   #37 = Methodref          #84.#290      // com/fasterxml/jackson/core/JsonParser.hasCurrentToken:()Z
   #38 = Methodref          #84.#291      // com/fasterxml/jackson/core/JsonParser.hasTokenId:(I)Z
   #39 = Methodref          #84.#292      // com/fasterxml/jackson/core/JsonParser.hasToken:(Lcom/fasterxml/jackson/core/JsonToken;)Z
   #40 = Methodref          #84.#293      // com/fasterxml/jackson/core/JsonParser.isExpectedStartArrayToken:()Z
   #41 = Methodref          #84.#294      // com/fasterxml/jackson/core/JsonParser.isExpectedStartObjectToken:()Z
   #42 = Methodref          #84.#295      // com/fasterxml/jackson/core/JsonParser.isExpectedNumberIntToken:()Z
   #43 = Methodref          #84.#296      // com/fasterxml/jackson/core/JsonParser.isNaN:()Z
   #44 = Methodref          #84.#297      // com/fasterxml/jackson/core/JsonParser.getText:()Ljava/lang/String;
   #45 = Methodref          #84.#298      // com/fasterxml/jackson/core/JsonParser.hasTextCharacters:()Z
   #46 = Methodref          #84.#299      // com/fasterxml/jackson/core/JsonParser.getTextCharacters:()[C
   #47 = Methodref          #84.#300      // com/fasterxml/jackson/core/JsonParser.getTextLength:()I
   #48 = Methodref          #84.#301      // com/fasterxml/jackson/core/JsonParser.getTextOffset:()I
   #49 = Methodref          #84.#302      // com/fasterxml/jackson/core/JsonParser.getText:(Ljava/io/Writer;)I
   #50 = Methodref          #84.#303      // com/fasterxml/jackson/core/JsonParser.getBigIntegerValue:()Ljava/math/BigInteger;
   #51 = Methodref          #84.#304      // com/fasterxml/jackson/core/JsonParser.getBooleanValue:()Z
   #52 = Methodref          #84.#305      // com/fasterxml/jackson/core/JsonParser.getByteValue:()B
   #53 = Methodref          #84.#306      // com/fasterxml/jackson/core/JsonParser.getShortValue:()S
   #54 = Methodref          #84.#307      // com/fasterxml/jackson/core/JsonParser.getDecimalValue:()Ljava/math/BigDecimal;
   #55 = Methodref          #84.#308      // com/fasterxml/jackson/core/JsonParser.getDoubleValue:()D
   #56 = Methodref          #84.#309      // com/fasterxml/jackson/core/JsonParser.getFloatValue:()F
   #57 = Methodref          #84.#310      // com/fasterxml/jackson/core/JsonParser.getIntValue:()I
   #58 = Methodref          #84.#311      // com/fasterxml/jackson/core/JsonParser.getLongValue:()J
   #59 = Methodref          #84.#312      // com/fasterxml/jackson/core/JsonParser.getNumberType:()Lcom/fasterxml/jackson/core/JsonParser$NumberType;
   #60 = Methodref          #84.#313      // com/fasterxml/jackson/core/JsonParser.getNumberValue:()Ljava/lang/Number;
   #61 = Methodref          #84.#314      // com/fasterxml/jackson/core/JsonParser.getNumberValueExact:()Ljava/lang/Number;
   #62 = Methodref          #84.#315      // com/fasterxml/jackson/core/JsonParser.getValueAsInt:()I
   #63 = Methodref          #84.#316      // com/fasterxml/jackson/core/JsonParser.getValueAsInt:(I)I
   #64 = Methodref          #84.#317      // com/fasterxml/jackson/core/JsonParser.getValueAsLong:()J
   #65 = Methodref          #84.#318      // com/fasterxml/jackson/core/JsonParser.getValueAsLong:(J)J
   #66 = Methodref          #84.#319      // com/fasterxml/jackson/core/JsonParser.getValueAsDouble:()D
   #67 = Methodref          #84.#320      // com/fasterxml/jackson/core/JsonParser.getValueAsDouble:(D)D
   #68 = Methodref          #84.#321      // com/fasterxml/jackson/core/JsonParser.getValueAsBoolean:()Z
   #69 = Methodref          #84.#322      // com/fasterxml/jackson/core/JsonParser.getValueAsBoolean:(Z)Z
   #70 = Methodref          #84.#323      // com/fasterxml/jackson/core/JsonParser.getValueAsString:()Ljava/lang/String;
   #71 = Methodref          #84.#324      // com/fasterxml/jackson/core/JsonParser.getValueAsString:(Ljava/lang/String;)Ljava/lang/String;
   #72 = Methodref          #84.#325      // com/fasterxml/jackson/core/JsonParser.getEmbeddedObject:()Ljava/lang/Object;
   #73 = Methodref          #84.#326      // com/fasterxml/jackson/core/JsonParser.getBinaryValue:(Lcom/fasterxml/jackson/core/Base64Variant;)[B
   #74 = Methodref          #84.#327      // com/fasterxml/jackson/core/JsonParser.readBinaryValue:(Lcom/fasterxml/jackson/core/Base64Variant;Ljava/io/OutputStream;)I
   #75 = Methodref          #84.#328      // com/fasterxml/jackson/core/JsonParser.nextToken:()Lcom/fasterxml/jackson/core/JsonToken;
   #76 = Methodref          #84.#329      // com/fasterxml/jackson/core/JsonParser.nextValue:()Lcom/fasterxml/jackson/core/JsonToken;
   #77 = Methodref          #84.#330      // com/fasterxml/jackson/core/JsonParser.finishToken:()V
   #78 = Methodref          #84.#331      // com/fasterxml/jackson/core/JsonParser.skipChildren:()Lcom/fasterxml/jackson/core/JsonParser;
   #79 = Methodref          #84.#332      // com/fasterxml/jackson/core/JsonParser.canReadObjectId:()Z
   #80 = Methodref          #84.#333      // com/fasterxml/jackson/core/JsonParser.canReadTypeId:()Z
   #81 = Methodref          #84.#334      // com/fasterxml/jackson/core/JsonParser.getObjectId:()Ljava/lang/Object;
   #82 = Methodref          #84.#335      // com/fasterxml/jackson/core/JsonParser.getTypeId:()Ljava/lang/Object;
   #83 = Class              #336          // com/fasterxml/jackson/core/util/JsonParserDelegate
   #84 = Class              #337          // com/fasterxml/jackson/core/JsonParser
   #85 = Utf8               delegate
   #86 = Utf8               Lcom/fasterxml/jackson/core/JsonParser;
   #87 = Utf8               <init>
   #88 = Utf8               (Lcom/fasterxml/jackson/core/JsonParser;)V
   #89 = Utf8               Code
   #90 = Utf8               LineNumberTable
   #91 = Utf8               LocalVariableTable
   #92 = Utf8               this
   #93 = Utf8               Lcom/fasterxml/jackson/core/util/JsonParserDelegate;
   #94 = Utf8               d
   #95 = Utf8               setCodec
   #96 = Utf8               (Lcom/fasterxml/jackson/core/ObjectCodec;)V
   #97 = Utf8               c
   #98 = Utf8               Lcom/fasterxml/jackson/core/ObjectCodec;
   #99 = Utf8               getCodec
  #100 = Utf8               ()Lcom/fasterxml/jackson/core/ObjectCodec;
  #101 = Utf8               enable
  #102 = Class              #338          // com/fasterxml/jackson/core/JsonParser$Feature
  #103 = Utf8               Feature
  #104 = Utf8               InnerClasses
  #105 = Utf8               (Lcom/fasterxml/jackson/core/JsonParser$Feature;)Lcom/fasterxml/jackson/core/JsonParser;
  #106 = Utf8               f
  #107 = Utf8               Lcom/fasterxml/jackson/core/JsonParser$Feature;
  #108 = Utf8               disable
  #109 = Utf8               isEnabled
  #110 = Utf8               (Lcom/fasterxml/jackson/core/JsonParser$Feature;)Z
  #111 = Utf8               getFeatureMask
  #112 = Utf8               ()I
  #113 = Utf8               setFeatureMask
  #114 = Utf8               (I)Lcom/fasterxml/jackson/core/JsonParser;
  #115 = Utf8               mask
  #116 = Utf8               I
  #117 = Utf8               Deprecated
  #118 = Utf8               RuntimeVisibleAnnotations
  #119 = Utf8               Ljava/lang/Deprecated;
  #120 = Utf8               overrideStdFeatures
  #121 = Utf8               (II)Lcom/fasterxml/jackson/core/JsonParser;
  #122 = Utf8               values
  #123 = Utf8               overrideFormatFeatures
  #124 = Utf8               getSchema
  #125 = Utf8               ()Lcom/fasterxml/jackson/core/FormatSchema;
  #126 = Utf8               setSchema
  #127 = Utf8               (Lcom/fasterxml/jackson/core/FormatSchema;)V
  #128 = Utf8               schema
  #129 = Utf8               Lcom/fasterxml/jackson/core/FormatSchema;
  #130 = Utf8               canUseSchema
  #131 = Utf8               (Lcom/fasterxml/jackson/core/FormatSchema;)Z
  #132 = Utf8               version
  #133 = Utf8               ()Lcom/fasterxml/jackson/core/Version;
  #134 = Utf8               getInputSource
  #135 = Utf8               ()Ljava/lang/Object;
  #136 = Utf8               requiresCustomCodec
  #137 = Utf8               ()Z
  #138 = Utf8               getReadCapabilities
  #139 = Utf8               ()Lcom/fasterxml/jackson/core/util/JacksonFeatureSet;
  #140 = Utf8               Signature
  #141 = Utf8               ()Lcom/fasterxml/jackson/core/util/JacksonFeatureSet<Lcom/fasterxml/jackson/core/StreamReadCapability;>;
  #142 = Utf8               close
  #143 = Utf8               ()V
  #144 = Utf8               Exceptions
  #145 = Class              #339          // java/io/IOException
  #146 = Utf8               isClosed
  #147 = Utf8               clearCurrentToken
  #148 = Utf8               getLastClearedToken
  #149 = Utf8               ()Lcom/fasterxml/jackson/core/JsonToken;
  #150 = Utf8               overrideCurrentName
  #151 = Utf8               (Ljava/lang/String;)V
  #152 = Utf8               name
  #153 = Utf8               Ljava/lang/String;
  #154 = Utf8               assignCurrentValue
  #155 = Utf8               (Ljava/lang/Object;)V
  #156 = Utf8               v
  #157 = Utf8               Ljava/lang/Object;
  #158 = Utf8               setCurrentValue
  #159 = Utf8               getParsingContext
  #160 = Utf8               ()Lcom/fasterxml/jackson/core/JsonStreamContext;
  #161 = Utf8               currentToken
  #162 = Utf8               currentTokenId
  #163 = Utf8               currentName
  #164 = Utf8               ()Ljava/lang/String;
  #165 = Utf8               currentValue
  #166 = Utf8               currentLocation
  #167 = Utf8               ()Lcom/fasterxml/jackson/core/JsonLocation;
  #168 = Utf8               currentTokenLocation
  #169 = Utf8               getCurrentToken
  #170 = Utf8               getCurrentTokenId
  #171 = Utf8               getCurrentName
  #172 = Utf8               getCurrentValue
  #173 = Utf8               getCurrentLocation
  #174 = Utf8               getTokenLocation
  #175 = Utf8               hasCurrentToken
  #176 = Utf8               hasTokenId
  #177 = Utf8               (I)Z
  #178 = Utf8               id
  #179 = Utf8               hasToken
  #180 = Utf8               (Lcom/fasterxml/jackson/core/JsonToken;)Z
  #181 = Utf8               t
  #182 = Utf8               Lcom/fasterxml/jackson/core/JsonToken;
  #183 = Utf8               isExpectedStartArrayToken
  #184 = Utf8               isExpectedStartObjectToken
  #185 = Utf8               isExpectedNumberIntToken
  #186 = Utf8               isNaN
  #187 = Utf8               getText
  #188 = Utf8               hasTextCharacters
  #189 = Utf8               getTextCharacters
  #190 = Utf8               ()[C
  #191 = Utf8               getTextLength
  #192 = Utf8               getTextOffset
  #193 = Utf8               (Ljava/io/Writer;)I
  #194 = Utf8               writer
  #195 = Utf8               Ljava/io/Writer;
  #196 = Class              #340          // java/lang/UnsupportedOperationException
  #197 = Utf8               getBigIntegerValue
  #198 = Utf8               ()Ljava/math/BigInteger;
  #199 = Utf8               getBooleanValue
  #200 = Utf8               getByteValue
  #201 = Utf8               ()B
  #202 = Utf8               getShortValue
  #203 = Utf8               ()S
  #204 = Utf8               getDecimalValue
  #205 = Utf8               ()Ljava/math/BigDecimal;
  #206 = Utf8               getDoubleValue
  #207 = Utf8               ()D
  #208 = Utf8               getFloatValue
  #209 = Utf8               ()F
  #210 = Utf8               getIntValue
  #211 = Utf8               getLongValue
  #212 = Utf8               ()J
  #213 = Utf8               getNumberType
  #214 = Class              #341          // com/fasterxml/jackson/core/JsonParser$NumberType
  #215 = Utf8               NumberType
  #216 = Utf8               ()Lcom/fasterxml/jackson/core/JsonParser$NumberType;
  #217 = Utf8               getNumberValue
  #218 = Utf8               ()Ljava/lang/Number;
  #219 = Utf8               getNumberValueExact
  #220 = Utf8               getValueAsInt
  #221 = Utf8               (I)I
  #222 = Utf8               defaultValue
  #223 = Utf8               getValueAsLong
  #224 = Utf8               (J)J
  #225 = Utf8               J
  #226 = Utf8               getValueAsDouble
  #227 = Utf8               (D)D
  #228 = Utf8               D
  #229 = Utf8               getValueAsBoolean
  #230 = Utf8               (Z)Z
  #231 = Utf8               Z
  #232 = Utf8               getValueAsString
  #233 = Utf8               (Ljava/lang/String;)Ljava/lang/String;
  #234 = Utf8               getEmbeddedObject
  #235 = Utf8               getBinaryValue
  #236 = Utf8               (Lcom/fasterxml/jackson/core/Base64Variant;)[B
  #237 = Utf8               b64variant
  #238 = Utf8               Lcom/fasterxml/jackson/core/Base64Variant;
  #239 = Utf8               readBinaryValue
  #240 = Utf8               (Lcom/fasterxml/jackson/core/Base64Variant;Ljava/io/OutputStream;)I
  #241 = Utf8               out
  #242 = Utf8               Ljava/io/OutputStream;
  #243 = Utf8               nextToken
  #244 = Utf8               nextValue
  #245 = Utf8               finishToken
  #246 = Utf8               skipChildren
  #247 = Utf8               ()Lcom/fasterxml/jackson/core/JsonParser;
  #248 = Utf8               canReadObjectId
  #249 = Utf8               canReadTypeId
  #250 = Utf8               getObjectId
  #251 = Utf8               getTypeId
  #252 = Utf8               SourceFile
  #253 = Utf8               JsonParserDelegate.java
  #254 = NameAndType        #87:#143      // "<init>":()V
  #255 = NameAndType        #85:#86       // delegate:Lcom/fasterxml/jackson/core/JsonParser;
  #256 = NameAndType        #95:#96       // setCodec:(Lcom/fasterxml/jackson/core/ObjectCodec;)V
  #257 = NameAndType        #99:#100      // getCodec:()Lcom/fasterxml/jackson/core/ObjectCodec;
  #258 = NameAndType        #101:#105     // enable:(Lcom/fasterxml/jackson/core/JsonParser$Feature;)Lcom/fasterxml/jackson/core/JsonParser;
  #259 = NameAndType        #108:#105     // disable:(Lcom/fasterxml/jackson/core/JsonParser$Feature;)Lcom/fasterxml/jackson/core/JsonParser;
  #260 = NameAndType        #109:#110     // isEnabled:(Lcom/fasterxml/jackson/core/JsonParser$Feature;)Z
  #261 = NameAndType        #111:#112     // getFeatureMask:()I
  #262 = NameAndType        #113:#114     // setFeatureMask:(I)Lcom/fasterxml/jackson/core/JsonParser;
  #263 = NameAndType        #120:#121     // overrideStdFeatures:(II)Lcom/fasterxml/jackson/core/JsonParser;
  #264 = NameAndType        #123:#121     // overrideFormatFeatures:(II)Lcom/fasterxml/jackson/core/JsonParser;
  #265 = NameAndType        #124:#125     // getSchema:()Lcom/fasterxml/jackson/core/FormatSchema;
  #266 = NameAndType        #126:#127     // setSchema:(Lcom/fasterxml/jackson/core/FormatSchema;)V
  #267 = NameAndType        #130:#131     // canUseSchema:(Lcom/fasterxml/jackson/core/FormatSchema;)Z
  #268 = NameAndType        #132:#133     // version:()Lcom/fasterxml/jackson/core/Version;
  #269 = NameAndType        #134:#135     // getInputSource:()Ljava/lang/Object;
  #270 = NameAndType        #136:#137     // requiresCustomCodec:()Z
  #271 = NameAndType        #138:#139     // getReadCapabilities:()Lcom/fasterxml/jackson/core/util/JacksonFeatureSet;
  #272 = NameAndType        #142:#143     // close:()V
  #273 = NameAndType        #146:#137     // isClosed:()Z
  #274 = NameAndType        #147:#143     // clearCurrentToken:()V
  #275 = NameAndType        #148:#149     // getLastClearedToken:()Lcom/fasterxml/jackson/core/JsonToken;
  #276 = NameAndType        #150:#151     // overrideCurrentName:(Ljava/lang/String;)V
  #277 = NameAndType        #154:#155     // assignCurrentValue:(Ljava/lang/Object;)V
  #278 = NameAndType        #158:#155     // setCurrentValue:(Ljava/lang/Object;)V
  #279 = NameAndType        #159:#160     // getParsingContext:()Lcom/fasterxml/jackson/core/JsonStreamContext;
  #280 = NameAndType        #161:#149     // currentToken:()Lcom/fasterxml/jackson/core/JsonToken;
  #281 = NameAndType        #162:#112     // currentTokenId:()I
  #282 = NameAndType        #163:#164     // currentName:()Ljava/lang/String;
  #283 = NameAndType        #165:#135     // currentValue:()Ljava/lang/Object;
  #284 = NameAndType        #173:#167     // getCurrentLocation:()Lcom/fasterxml/jackson/core/JsonLocation;
  #285 = NameAndType        #174:#167     // getTokenLocation:()Lcom/fasterxml/jackson/core/JsonLocation;
  #286 = NameAndType        #169:#149     // getCurrentToken:()Lcom/fasterxml/jackson/core/JsonToken;
  #287 = NameAndType        #170:#112     // getCurrentTokenId:()I
  #288 = NameAndType        #171:#164     // getCurrentName:()Ljava/lang/String;
  #289 = NameAndType        #172:#135     // getCurrentValue:()Ljava/lang/Object;
  #290 = NameAndType        #175:#137     // hasCurrentToken:()Z
  #291 = NameAndType        #176:#177     // hasTokenId:(I)Z
  #292 = NameAndType        #179:#180     // hasToken:(Lcom/fasterxml/jackson/core/JsonToken;)Z
  #293 = NameAndType        #183:#137     // isExpectedStartArrayToken:()Z
  #294 = NameAndType        #184:#137     // isExpectedStartObjectToken:()Z
  #295 = NameAndType        #185:#137     // isExpectedNumberIntToken:()Z
  #296 = NameAndType        #186:#137     // isNaN:()Z
  #297 = NameAndType        #187:#164     // getText:()Ljava/lang/String;
  #298 = NameAndType        #188:#137     // hasTextCharacters:()Z
  #299 = NameAndType        #189:#190     // getTextCharacters:()[C
  #300 = NameAndType        #191:#112     // getTextLength:()I
  #301 = NameAndType        #192:#112     // getTextOffset:()I
  #302 = NameAndType        #187:#193     // getText:(Ljava/io/Writer;)I
  #303 = NameAndType        #197:#198     // getBigIntegerValue:()Ljava/math/BigInteger;
  #304 = NameAndType        #199:#137     // getBooleanValue:()Z
  #305 = NameAndType        #200:#201     // getByteValue:()B
  #306 = NameAndType        #202:#203     // getShortValue:()S
  #307 = NameAndType        #204:#205     // getDecimalValue:()Ljava/math/BigDecimal;
  #308 = NameAndType        #206:#207     // getDoubleValue:()D
  #309 = NameAndType        #208:#209     // getFloatValue:()F
  #310 = NameAndType        #210:#112     // getIntValue:()I
  #311 = NameAndType        #211:#212     // getLongValue:()J
  #312 = NameAndType        #213:#216     // getNumberType:()Lcom/fasterxml/jackson/core/JsonParser$NumberType;
  #313 = NameAndType        #217:#218     // getNumberValue:()Ljava/lang/Number;
  #314 = NameAndType        #219:#218     // getNumberValueExact:()Ljava/lang/Number;
  #315 = NameAndType        #220:#112     // getValueAsInt:()I
  #316 = NameAndType        #220:#221     // getValueAsInt:(I)I
  #317 = NameAndType        #223:#212     // getValueAsLong:()J
  #318 = NameAndType        #223:#224     // getValueAsLong:(J)J
  #319 = NameAndType        #226:#207     // getValueAsDouble:()D
  #320 = NameAndType        #226:#227     // getValueAsDouble:(D)D
  #321 = NameAndType        #229:#137     // getValueAsBoolean:()Z
  #322 = NameAndType        #229:#230     // getValueAsBoolean:(Z)Z
  #323 = NameAndType        #232:#164     // getValueAsString:()Ljava/lang/String;
  #324 = NameAndType        #232:#233     // getValueAsString:(Ljava/lang/String;)Ljava/lang/String;
  #325 = NameAndType        #234:#135     // getEmbeddedObject:()Ljava/lang/Object;
  #326 = NameAndType        #235:#236     // getBinaryValue:(Lcom/fasterxml/jackson/core/Base64Variant;)[B
  #327 = NameAndType        #239:#240     // readBinaryValue:(Lcom/fasterxml/jackson/core/Base64Variant;Ljava/io/OutputStream;)I
  #328 = NameAndType        #243:#149     // nextToken:()Lcom/fasterxml/jackson/core/JsonToken;
  #329 = NameAndType        #244:#149     // nextValue:()Lcom/fasterxml/jackson/core/JsonToken;
  #330 = NameAndType        #245:#143     // finishToken:()V
  #331 = NameAndType        #246:#247     // skipChildren:()Lcom/fasterxml/jackson/core/JsonParser;
  #332 = NameAndType        #248:#137     // canReadObjectId:()Z
  #333 = NameAndType        #249:#137     // canReadTypeId:()Z
  #334 = NameAndType        #250:#135     // getObjectId:()Ljava/lang/Object;
  #335 = NameAndType        #251:#135     // getTypeId:()Ljava/lang/Object;
  #336 = Utf8               com/fasterxml/jackson/core/util/JsonParserDelegate
  #337 = Utf8               com/fasterxml/jackson/core/JsonParser
  #338 = Utf8               com/fasterxml/jackson/core/JsonParser$Feature
  #339 = Utf8               java/io/IOException
  #340 = Utf8               java/lang/UnsupportedOperationException
  #341 = Utf8               com/fasterxml/jackson/core/JsonParser$NumberType
{
  protected com.fasterxml.jackson.core.JsonParser delegate;
    descriptor: Lcom/fasterxml/jackson/core/JsonParser;
    flags: (0x0004) ACC_PROTECTED

  public com.fasterxml.jackson.core.util.JsonParserDelegate(com.fasterxml.jackson.core.JsonParser);
    descriptor: (Lcom/fasterxml/jackson/core/JsonParser;)V
    flags: (0x0001) ACC_PUBLIC
    Code:
      stack=2, locals=2, args_size=2
         0: aload_0
         1: invokespecial #1                  // Method com/fasterxml/jackson/core/JsonParser."<init>":()V
         4: aload_0
         5: aload_1
         6: putfield      #2                  // Field delegate:Lcom/fasterxml/jackson/core/JsonParser;
         9: return
      LineNumberTable:
        line 25: 0
        line 26: 4
        line 27: 9
      LocalVariableTable:
        Start  Length  Slot  Name   Signature
            0      10     0  this   Lcom/fasterxml/jackson/core/util/JsonParserDelegate;
            0      10     1     d   Lcom/fasterxml/jackson/core/JsonParser;

  public void setCodec(com.fasterxml.jackson.core.ObjectCodec);
    descriptor: (Lcom/fasterxml/jackson/core/ObjectCodec;)V
    flags: (0x0001) ACC_PUBLIC
    Code:
      stack=2, locals=2, args_size=2
         0: aload_0
         1: getfield      #2                  // Field delegate:Lcom/fasterxml/jackson/core/JsonParser;
         4: aload_1
         5: invokevirtual #3                  // Method com/fasterxml/jackson/core/JsonParser.setCodec:(Lcom/fasterxml/jackson/core/ObjectCodec;)V
         8: return
      LineNumberTable:
        line 35: 0
      LocalVariableTable:
        Start  Length  Slot  Name   Signature
            0       9     0  this   Lcom/fasterxml/jackson/core/util/JsonParserDelegate;
            0       9     1     c   Lcom/fasterxml/jackson/core/ObjectCodec;

  public com.fasterxml.jackson.core.ObjectCodec getCodec();
    descriptor: ()Lcom/fasterxml/jackson/core/ObjectCodec;
    flags: (0x0001) ACC_PUBLIC
    Code:
      stack=1, locals=1, args_size=1
         0: aload_0
         1: getfield      #2                  // Field delegate:Lcom/fasterxml/jackson/core/JsonParser;
         4: invokevirtual #4                  // Method com/fasterxml/jackson/core/JsonParser.getCodec:()Lcom/fasterxml/jackson/core/ObjectCodec;
         7: areturn
      LineNumberTable:
        line 36: 0
      LocalVariableTable:
        Start  Length  Slot  Name   Signature
            0       8     0  this   Lcom/fasterxml/jackson/core/util/JsonParserDelegate;

  public com.fasterxml.jackson.core.JsonParser enable(com.fasterxml.jackson.core.JsonParser$Feature);
    descriptor: (Lcom/fasterxml/jackson/core/JsonParser$Feature;)Lcom/fasterxml/jackson/core/JsonParser;
    flags: (0x0001) ACC_PUBLIC
    Code:
      stack=2, locals=2, args_size=2
         0: aload_0
         1: getfield      #2                  // Field delegate:Lcom/fasterxml/jackson/core/JsonParser;
         4: aload_1
         5: invokevirtual #5                  // Method com/fasterxml/jackson/core/JsonParser.enable:(Lcom/fasterxml/jackson/core/JsonParser$Feature;)Lcom/fasterxml/jackson/core/JsonParser;
         8: pop
         9: aload_0
        10: areturn
      LineNumberTable:
        line 40: 0
        line 41: 9
      LocalVariableTable:
        Start  Length  Slot  Name   Signature
            0      11     0  this   Lcom/fasterxml/jackson/core/util/JsonParserDelegate;
            0      11     1     f   Lcom/fasterxml/jackson/core/JsonParser$Feature;

  public com.fasterxml.jackson.core.JsonParser disable(com.fasterxml.jackson.core.JsonParser$Feature);
    descriptor: (Lcom/fasterxml/jackson/core/JsonParser$Feature;)Lcom/fasterxml/jackson/core/JsonParser;
    flags: (0x0001) ACC_PUBLIC
    Code:
      stack=2, locals=2, args_size=2
         0: aload_0
         1: getfield      #2                  // Field delegate:Lcom/fasterxml/jackson/core/JsonParser;
         4: aload_1
         5: invokevirtual #6                  // Method com/fasterxml/jackson/core/JsonParser.disable:(Lcom/fasterxml/jackson/core/JsonParser$Feature;)Lcom/fasterxml/jackson/core/JsonParser;
         8: pop
         9: aload_0
        10: areturn
      LineNumberTable:
        line 46: 0
        line 47: 9
      LocalVariableTable:
        Start  Length  Slot  Name   Signature
            0      11     0  this   Lcom/fasterxml/jackson/core/util/JsonParserDelegate;
            0      11     1     f   Lcom/fasterxml/jackson/core/JsonParser$Feature;

  public boolean isEnabled(com.fasterxml.jackson.core.JsonParser$Feature);
    descriptor: (Lcom/fasterxml/jackson/core/JsonParser$Feature;)Z
    flags: (0x0001) ACC_PUBLIC
    Code:
      stack=2, locals=2, args_size=2
         0: aload_0
         1: getfield      #2                  // Field delegate:Lcom/fasterxml/jackson/core/JsonParser;
         4: aload_1
         5: invokevirtual #7                  // Method com/fasterxml/jackson/core/JsonParser.isEnabled:(Lcom/fasterxml/jackson/core/JsonParser$Feature;)Z
         8: ireturn
      LineNumberTable:
        line 50: 0
      LocalVariableTable:
        Start  Length  Slot  Name   Signature
            0       9     0  this   Lcom/fasterxml/jackson/core/util/JsonParserDelegate;
            0       9     1     f   Lcom/fasterxml/jackson/core/JsonParser$Feature;

  public int getFeatureMask();
    descriptor: ()I
    flags: (0x0001) ACC_PUBLIC
    Code:
      stack=1, locals=1, args_size=1
         0: aload_0
         1: getfield      #2                  // Field delegate:Lcom/fasterxml/jackson/core/JsonParser;
         4: invokevirtual #8                  // Method com/fasterxml/jackson/core/JsonParser.getFeatureMask:()I
         7: ireturn
      LineNumberTable:
        line 51: 0
      LocalVariableTable:
        Start  Length  Slot  Name   Signature
            0       8     0  this   Lcom/fasterxml/jackson/core/util/JsonParserDelegate;

  public com.fasterxml.jackson.core.JsonParser setFeatureMask(int);
    descriptor: (I)Lcom/fasterxml/jackson/core/JsonParser;
    flags: (0x0001) ACC_PUBLIC
    Code:
      stack=2, locals=2, args_size=2
         0: aload_0
         1: getfield      #2                  // Field delegate:Lcom/fasterxml/jackson/core/JsonParser;
         4: iload_1
         5: invokevirtual #9                  // Method com/fasterxml/jackson/core/JsonParser.setFeatureMask:(I)Lcom/fasterxml/jackson/core/JsonParser;
         8: pop
         9: aload_0
        10: areturn
      LineNumberTable:
        line 56: 0
        line 57: 9
      LocalVariableTable:
        Start  Length  Slot  Name   Signature
            0      11     0  this   Lcom/fasterxml/jackson/core/util/JsonParserDelegate;
            0      11     1  mask   I
    Deprecated: true
    RuntimeVisibleAnnotations:
      0: #119()
        java.lang.Deprecated

  public com.fasterxml.jackson.core.JsonParser overrideStdFeatures(int, int);
    descriptor: (II)Lcom/fasterxml/jackson/core/JsonParser;
    flags: (0x0001) ACC_PUBLIC
    Code:
      stack=3, locals=3, args_size=3
         0: aload_0
         1: getfield      #2                  // Field delegate:Lcom/fasterxml/jackson/core/JsonParser;
         4: iload_1
         5: iload_2
         6: invokevirtual #10                 // Method com/fasterxml/jackson/core/JsonParser.overrideStdFeatures:(II)Lcom/fasterxml/jackson/core/JsonParser;
         9: pop
        10: aload_0
        11: areturn
      LineNumberTable:
        line 62: 0
        line 63: 10
      LocalVariableTable:
        Start  Length  Slot  Name   Signature
            0      12     0  this   Lcom/fasterxml/jackson/core/util/JsonParserDelegate;
            0      12     1 values   I
            0      12     2  mask   I

  public com.fasterxml.jackson.core.JsonParser overrideFormatFeatures(int, int);
    descriptor: (II)Lcom/fasterxml/jackson/core/JsonParser;
    flags: (0x0001) ACC_PUBLIC
    Code:
      stack=3, locals=3, args_size=3
         0: aload_0
         1: getfield      #2                  // Field delegate:Lcom/fasterxml/jackson/core/JsonParser;
         4: iload_1
         5: iload_2
         6: invokevirtual #11                 // Method com/fasterxml/jackson/core/JsonParser.overrideFormatFeatures:(II)Lcom/fasterxml/jackson/core/JsonParser;
         9: pop
        10: aload_0
        11: areturn
      LineNumberTable:
        line 68: 0
        line 69: 10
      LocalVariableTable:
        Start  Length  Slot  Name   Signature
            0      12     0  this   Lcom/fasterxml/jackson/core/util/JsonParserDelegate;
            0      12     1 values   I
            0      12     2  mask   I

  public com.fasterxml.jackson.core.FormatSchema getSchema();
    descriptor: ()Lcom/fasterxml/jackson/core/FormatSchema;
    flags: (0x0001) ACC_PUBLIC
    Code:
      stack=1, locals=1, args_size=1
         0: aload_0
         1: getfield      #2                  // Field delegate:Lcom/fasterxml/jackson/core/JsonParser;
         4: invokevirtual #12                 // Method com/fasterxml/jackson/core/JsonParser.getSchema:()Lcom/fasterxml/jackson/core/FormatSchema;
         7: areturn
      LineNumberTable:
        line 72: 0
      LocalVariableTable:
        Start  Length  Slot  Name   Signature
            0       8     0  this   Lcom/fasterxml/jackson/core/util/JsonParserDelegate;

  public void setSchema(com.fasterxml.jackson.core.FormatSchema);
    descriptor: (Lcom/fasterxml/jackson/core/FormatSchema;)V
    flags: (0x0001) ACC_PUBLIC
    Code:
      stack=2, locals=2, args_size=2
         0: aload_0
         1: getfield      #2                  // Field delegate:Lcom/fasterxml/jackson/core/JsonParser;
         4: aload_1
         5: invokevirtual #13                 // Method com/fasterxml/jackson/core/JsonParser.setSchema:(Lcom/fasterxml/jackson/core/FormatSchema;)V
         8: return
      LineNumberTable:
        line 73: 0
      LocalVariableTable:
        Start  Length  Slot  Name   Signature
            0       9     0  this   Lcom/fasterxml/jackson/core/util/JsonParserDelegate;
            0       9     1 schema   Lcom/fasterxml/jackson/core/FormatSchema;

  public boolean canUseSchema(com.fasterxml.jackson.core.FormatSchema);
    descriptor: (Lcom/fasterxml/jackson/core/FormatSchema;)Z
    flags: (0x0001) ACC_PUBLIC
    Code:
      stack=2, locals=2, args_size=2
         0: aload_0
         1: getfield      #2                  // Field delegate:Lcom/fasterxml/jackson/core/JsonParser;
         4: aload_1
         5: invokevirtual #14                 // Method com/fasterxml/jackson/core/JsonParser.canUseSchema:(Lcom/fasterxml/jackson/core/FormatSchema;)Z
         8: ireturn
      LineNumberTable:
        line 74: 0
      LocalVariableTable:
        Start  Length  Slot  Name   Signature
            0       9     0  this   Lcom/fasterxml/jackson/core/util/JsonParserDelegate;
            0       9     1 schema   Lcom/fasterxml/jackson/core/FormatSchema;

  public com.fasterxml.jackson.core.Version version();
    descriptor: ()Lcom/fasterxml/jackson/core/Version;
    flags: (0x0001) ACC_PUBLIC
    Code:
      stack=1, locals=1, args_size=1
         0: aload_0
         1: getfield      #2                  // Field delegate:Lcom/fasterxml/jackson/core/JsonParser;
         4: invokevirtual #15                 // Method com/fasterxml/jackson/core/JsonParser.version:()Lcom/fasterxml/jackson/core/Version;
         7: areturn
      LineNumberTable:
        line 75: 0
      LocalVariableTable:
        Start  Length  Slot  Name   Signature
            0       8     0  this   Lcom/fasterxml/jackson/core/util/JsonParserDelegate;

  public java.lang.Object getInputSource();
    descriptor: ()Ljava/lang/Object;
    flags: (0x0001) ACC_PUBLIC
    Code:
      stack=1, locals=1, args_size=1
         0: aload_0
         1: getfield      #2                  // Field delegate:Lcom/fasterxml/jackson/core/JsonParser;
         4: invokevirtual #16                 // Method com/fasterxml/jackson/core/JsonParser.getInputSource:()Ljava/lang/Object;
         7: areturn
      LineNumberTable:
        line 76: 0
      LocalVariableTable:
        Start  Length  Slot  Name   Signature
            0       8     0  this   Lcom/fasterxml/jackson/core/util/JsonParserDelegate;

  public boolean requiresCustomCodec();
    descriptor: ()Z
    flags: (0x0001) ACC_PUBLIC
    Code:
      stack=1, locals=1, args_size=1
         0: aload_0
         1: getfield      #2                  // Field delegate:Lcom/fasterxml/jackson/core/JsonParser;
         4: invokevirtual #17                 // Method com/fasterxml/jackson/core/JsonParser.requiresCustomCodec:()Z
         7: ireturn
      LineNumberTable:
        line 84: 0
      LocalVariableTable:
        Start  Length  Slot  Name   Signature
            0       8     0  this   Lcom/fasterxml/jackson/core/util/JsonParserDelegate;

  public com.fasterxml.jackson.core.util.JacksonFeatureSet<com.fasterxml.jackson.core.StreamReadCapability> getReadCapabilities();
    descriptor: ()Lcom/fasterxml/jackson/core/util/JacksonFeatureSet;
    flags: (0x0001) ACC_PUBLIC
    Code:
      stack=1, locals=1, args_size=1
         0: aload_0
         1: getfield      #2                  // Field delegate:Lcom/fasterxml/jackson/core/JsonParser;
         4: invokevirtual #18                 // Method com/fasterxml/jackson/core/JsonParser.getReadCapabilities:()Lcom/fasterxml/jackson/core/util/JacksonFeatureSet;
         7: areturn
      LineNumberTable:
        line 86: 0
      LocalVariableTable:
        Start  Length  Slot  Name   Signature
            0       8     0  this   Lcom/fasterxml/jackson/core/util/JsonParserDelegate;
    Signature: #141                         // ()Lcom/fasterxml/jackson/core/util/JacksonFeatureSet<Lcom/fasterxml/jackson/core/StreamReadCapability;>;

  public void close() throws java.io.IOException;
    descriptor: ()V
    flags: (0x0001) ACC_PUBLIC
    Code:
      stack=1, locals=1, args_size=1
         0: aload_0
         1: getfield      #2                  // Field delegate:Lcom/fasterxml/jackson/core/JsonParser;
         4: invokevirtual #19                 // Method com/fasterxml/jackson/core/JsonParser.close:()V
         7: return
      LineNumberTable:
        line 94: 0
      LocalVariableTable:
        Start  Length  Slot  Name   Signature
            0       8     0  this   Lcom/fasterxml/jackson/core/util/JsonParserDelegate;
    Exceptions:
      throws java.io.IOException

  public boolean isClosed();
    descriptor: ()Z
    flags: (0x0001) ACC_PUBLIC
    Code:
      stack=1, locals=1, args_size=1
         0: aload_0
         1: getfield      #2                  // Field delegate:Lcom/fasterxml/jackson/core/JsonParser;
         4: invokevirtual #20                 // Method com/fasterxml/jackson/core/JsonParser.isClosed:()Z
         7: ireturn
      LineNumberTable:
        line 95: 0
      LocalVariableTable:
        Start  Length  Slot  Name   Signature
            0       8     0  this   Lcom/fasterxml/jackson/core/util/JsonParserDelegate;

  public void clearCurrentToken();
    descriptor: ()V
    flags: (0x0001) ACC_PUBLIC
    Code:
      stack=1, locals=1, args_size=1
         0: aload_0
         1: getfield      #2                  // Field delegate:Lcom/fasterxml/jackson/core/JsonParser;
         4: invokevirtual #21                 // Method com/fasterxml/jackson/core/JsonParser.clearCurrentToken:()V
         7: return
      LineNumberTable:
        line 103: 0
      LocalVariableTable:
        Start  Length  Slot  Name   Signature
            0       8     0  this   Lcom/fasterxml/jackson/core/util/JsonParserDelegate;

  public com.fasterxml.jackson.core.JsonToken getLastClearedToken();
    descriptor: ()Lcom/fasterxml/jackson/core/JsonToken;
    flags: (0x0001) ACC_PUBLIC
    Code:
      stack=1, locals=1, args_size=1
         0: aload_0
         1: getfield      #2                  // Field delegate:Lcom/fasterxml/jackson/core/JsonParser;
         4: invokevirtual #22                 // Method com/fasterxml/jackson/core/JsonParser.getLastClearedToken:()Lcom/fasterxml/jackson/core/JsonToken;
         7: areturn
      LineNumberTable:
        line 104: 0
      LocalVariableTable:
        Start  Length  Slot  Name   Signature
            0       8     0  this   Lcom/fasterxml/jackson/core/util/JsonParserDelegate;

  public void overrideCurrentName(java.lang.String);
    descriptor: (Ljava/lang/String;)V
    flags: (0x0001) ACC_PUBLIC
    Code:
      stack=2, locals=2, args_size=2
         0: aload_0
         1: getfield      #2                  // Field delegate:Lcom/fasterxml/jackson/core/JsonParser;
         4: aload_1
         5: invokevirtual #23                 // Method com/fasterxml/jackson/core/JsonParser.overrideCurrentName:(Ljava/lang/String;)V
         8: return
      LineNumberTable:
        line 105: 0
      LocalVariableTable:
        Start  Length  Slot  Name   Signature
            0       9     0  this   Lcom/fasterxml/jackson/core/util/JsonParserDelegate;
            0       9     1  name   Ljava/lang/String;

  public void assignCurrentValue(java.lang.Object);
    descriptor: (Ljava/lang/Object;)V
    flags: (0x0001) ACC_PUBLIC
    Code:
      stack=2, locals=2, args_size=2
         0: aload_0
         1: getfield      #2                  // Field delegate:Lcom/fasterxml/jackson/core/JsonParser;
         4: aload_1
         5: invokevirtual #24                 // Method com/fasterxml/jackson/core/JsonParser.assignCurrentValue:(Ljava/lang/Object;)V
         8: return
      LineNumberTable:
        line 108: 0
      LocalVariableTable:
        Start  Length  Slot  Name   Signature
            0       9     0  this   Lcom/fasterxml/jackson/core/util/JsonParserDelegate;
            0       9     1     v   Ljava/lang/Object;

  public void setCurrentValue(java.lang.Object);
    descriptor: (Ljava/lang/Object;)V
    flags: (0x0001) ACC_PUBLIC
    Code:
      stack=2, locals=2, args_size=2
         0: aload_0
         1: getfield      #2                  // Field delegate:Lcom/fasterxml/jackson/core/JsonParser;
         4: aload_1
         5: invokevirtual #25                 // Method com/fasterxml/jackson/core/JsonParser.setCurrentValue:(Ljava/lang/Object;)V
         8: return
      LineNumberTable:
        line 112: 0
      LocalVariableTable:
        Start  Length  Slot  Name   Signature
            0       9     0  this   Lcom/fasterxml/jackson/core/util/JsonParserDelegate;
            0       9     1     v   Ljava/lang/Object;

  public com.fasterxml.jackson.core.JsonStreamContext getParsingContext();
    descriptor: ()Lcom/fasterxml/jackson/core/JsonStreamContext;
    flags: (0x0001) ACC_PUBLIC
    Code:
      stack=1, locals=1, args_size=1
         0: aload_0
         1: getfield      #2                  // Field delegate:Lcom/fasterxml/jackson/core/JsonParser;
         4: invokevirtual #26                 // Method com/fasterxml/jackson/core/JsonParser.getParsingContext:()Lcom/fasterxml/jackson/core/JsonStreamContext;
         7: areturn
      LineNumberTable:
        line 120: 0
      LocalVariableTable:
        Start  Length  Slot  Name   Signature
            0       8     0  this   Lcom/fasterxml/jackson/core/util/JsonParserDelegate;

  public com.fasterxml.jackson.core.JsonToken currentToken();
    descriptor: ()Lcom/fasterxml/jackson/core/JsonToken;
    flags: (0x0001) ACC_PUBLIC
    Code:
      stack=1, locals=1, args_size=1
         0: aload_0
         1: getfield      #2                  // Field delegate:Lcom/fasterxml/jackson/core/JsonParser;
         4: invokevirtual #27                 // Method com/fasterxml/jackson/core/JsonParser.currentToken:()Lcom/fasterxml/jackson/core/JsonToken;
         7: areturn
      LineNumberTable:
        line 122: 0
      LocalVariableTable:
        Start  Length  Slot  Name   Signature
            0       8     0  this   Lcom/fasterxml/jackson/core/util/JsonParserDelegate;

  public int currentTokenId();
    descriptor: ()I
    flags: (0x0001) ACC_PUBLIC
    Code:
      stack=1, locals=1, args_size=1
         0: aload_0
         1: getfield      #2                  // Field delegate:Lcom/fasterxml/jackson/core/JsonParser;
         4: invokevirtual #28                 // Method com/fasterxml/jackson/core/JsonParser.currentTokenId:()I
         7: ireturn
      LineNumberTable:
        line 123: 0
      LocalVariableTable:
        Start  Length  Slot  Name   Signature
            0       8     0  this   Lcom/fasterxml/jackson/core/util/JsonParserDelegate;

  public java.lang.String currentName() throws java.io.IOException;
    descriptor: ()Ljava/lang/String;
    flags: (0x0001) ACC_PUBLIC
    Code:
      stack=1, locals=1, args_size=1
         0: aload_0
         1: getfield      #2                  // Field delegate:Lcom/fasterxml/jackson/core/JsonParser;
         4: invokevirtual #29                 // Method com/fasterxml/jackson/core/JsonParser.currentName:()Ljava/lang/String;
         7: areturn
      LineNumberTable:
        line 124: 0
      LocalVariableTable:
        Start  Length  Slot  Name   Signature
            0       8     0  this   Lcom/fasterxml/jackson/core/util/JsonParserDelegate;
    Exceptions:
      throws java.io.IOException

  public java.lang.Object currentValue();
    descriptor: ()Ljava/lang/Object;
    flags: (0x0001) ACC_PUBLIC
    Code:
      stack=1, locals=1, args_size=1
         0: aload_0
         1: getfield      #2                  // Field delegate:Lcom/fasterxml/jackson/core/JsonParser;
         4: invokevirtual #30                 // Method com/fasterxml/jackson/core/JsonParser.currentValue:()Ljava/lang/Object;
         7: areturn
      LineNumberTable:
        line 126: 0
      LocalVariableTable:
        Start  Length  Slot  Name   Signature
            0       8     0  this   Lcom/fasterxml/jackson/core/util/JsonParserDelegate;

  public com.fasterxml.jackson.core.JsonLocation currentLocation();
    descriptor: ()Lcom/fasterxml/jackson/core/JsonLocation;
    flags: (0x0001) ACC_PUBLIC
    Code:
      stack=1, locals=1, args_size=1
         0: aload_0
         1: getfield      #2                  // Field delegate:Lcom/fasterxml/jackson/core/JsonParser;
         4: invokevirtual #31                 // Method com/fasterxml/jackson/core/JsonParser.getCurrentLocation:()Lcom/fasterxml/jackson/core/JsonLocation;
         7: areturn
      LineNumberTable:
        line 129: 0
      LocalVariableTable:
        Start  Length  Slot  Name   Signature
            0       8     0  this   Lcom/fasterxml/jackson/core/util/JsonParserDelegate;

  public com.fasterxml.jackson.core.JsonLocation currentTokenLocation();
    descriptor: ()Lcom/fasterxml/jackson/core/JsonLocation;
    flags: (0x0001) ACC_PUBLIC
    Code:
      stack=1, locals=1, args_size=1
         0: aload_0
         1: getfield      #2                  // Field delegate:Lcom/fasterxml/jackson/core/JsonParser;
         4: invokevirtual #32                 // Method com/fasterxml/jackson/core/JsonParser.getTokenLocation:()Lcom/fasterxml/jackson/core/JsonLocation;
         7: areturn
      LineNumberTable:
        line 131: 0
      LocalVariableTable:
        Start  Length  Slot  Name   Signature
            0       8     0  this   Lcom/fasterxml/jackson/core/util/JsonParserDelegate;

  public com.fasterxml.jackson.core.JsonToken getCurrentToken();
    descriptor: ()Lcom/fasterxml/jackson/core/JsonToken;
    flags: (0x0001) ACC_PUBLIC
    Code:
      stack=1, locals=1, args_size=1
         0: aload_0
         1: getfield      #2                  // Field delegate:Lcom/fasterxml/jackson/core/JsonParser;
         4: invokevirtual #33                 // Method com/fasterxml/jackson/core/JsonParser.getCurrentToken:()Lcom/fasterxml/jackson/core/JsonToken;
         7: areturn
      LineNumberTable:
        line 134: 0
      LocalVariableTable:
        Start  Length  Slot  Name   Signature
            0       8     0  this   Lcom/fasterxml/jackson/core/util/JsonParserDelegate;

  public int getCurrentTokenId();
    descriptor: ()I
    flags: (0x0001) ACC_PUBLIC
    Code:
      stack=1, locals=1, args_size=1
         0: aload_0
         1: getfield      #2                  // Field delegate:Lcom/fasterxml/jackson/core/JsonParser;
         4: invokevirtual #34                 // Method com/fasterxml/jackson/core/JsonParser.getCurrentTokenId:()I
         7: ireturn
      LineNumberTable:
        line 136: 0
      LocalVariableTable:
        Start  Length  Slot  Name   Signature
            0       8     0  this   Lcom/fasterxml/jackson/core/util/JsonParserDelegate;
    Deprecated: true
    RuntimeVisibleAnnotations:
      0: #119()
        java.lang.Deprecated

  public java.lang.String getCurrentName() throws java.io.IOException;
    descriptor: ()Ljava/lang/String;
    flags: (0x0001) ACC_PUBLIC
    Code:
      stack=1, locals=1, args_size=1
         0: aload_0
         1: getfield      #2                  // Field delegate:Lcom/fasterxml/jackson/core/JsonParser;
         4: invokevirtual #35                 // Method com/fasterxml/jackson/core/JsonParser.getCurrentName:()Ljava/lang/String;
         7: areturn
      LineNumberTable:
        line 138: 0
      LocalVariableTable:
        Start  Length  Slot  Name   Signature
            0       8     0  this   Lcom/fasterxml/jackson/core/util/JsonParserDelegate;
    Exceptions:
      throws java.io.IOException

  public java.lang.Object getCurrentValue();
    descriptor: ()Ljava/lang/Object;
    flags: (0x0001) ACC_PUBLIC
    Code:
      stack=1, locals=1, args_size=1
         0: aload_0
         1: getfield      #2                  // Field delegate:Lcom/fasterxml/jackson/core/JsonParser;
         4: invokevirtual #36                 // Method com/fasterxml/jackson/core/JsonParser.getCurrentValue:()Ljava/lang/Object;
         7: areturn
      LineNumberTable:
        line 140: 0
      LocalVariableTable:
        Start  Length  Slot  Name   Signature
            0       8     0  this   Lcom/fasterxml/jackson/core/util/JsonParserDelegate;

  public com.fasterxml.jackson.core.JsonLocation getCurrentLocation();
    descriptor: ()Lcom/fasterxml/jackson/core/JsonLocation;
    flags: (0x0001) ACC_PUBLIC
    Code:
      stack=1, locals=1, args_size=1
         0: aload_0
         1: getfield      #2                  // Field delegate:Lcom/fasterxml/jackson/core/JsonParser;
         4: invokevirtual #31                 // Method com/fasterxml/jackson/core/JsonParser.getCurrentLocation:()Lcom/fasterxml/jackson/core/JsonLocation;
         7: areturn
      LineNumberTable:
        line 143: 0
      LocalVariableTable:
        Start  Length  Slot  Name   Signature
            0       8     0  this   Lcom/fasterxml/jackson/core/util/JsonParserDelegate;

  public com.fasterxml.jackson.core.JsonLocation getTokenLocation();
    descriptor: ()Lcom/fasterxml/jackson/core/JsonLocation;
    flags: (0x0001) ACC_PUBLIC
    Code:
      stack=1, locals=1, args_size=1
         0: aload_0
         1: getfield      #2                  // Field delegate:Lcom/fasterxml/jackson/core/JsonParser;
         4: invokevirtual #32                 // Method com/fasterxml/jackson/core/JsonParser.getTokenLocation:()Lcom/fasterxml/jackson/core/JsonLocation;
         7: areturn
      LineNumberTable:
        line 145: 0
      LocalVariableTable:
        Start  Length  Slot  Name   Signature
            0       8     0  this   Lcom/fasterxml/jackson/core/util/JsonParserDelegate;

  public boolean hasCurrentToken();
    descriptor: ()Z
    flags: (0x0001) ACC_PUBLIC
    Code:
      stack=1, locals=1, args_size=1
         0: aload_0
         1: getfield      #2                  // Field delegate:Lcom/fasterxml/jackson/core/JsonParser;
         4: invokevirtual #37                 // Method com/fasterxml/jackson/core/JsonParser.hasCurrentToken:()Z
         7: ireturn
      LineNumberTable:
        line 153: 0
      LocalVariableTable:
        Start  Length  Slot  Name   Signature
            0       8     0  this   Lcom/fasterxml/jackson/core/util/JsonParserDelegate;

  public boolean hasTokenId(int);
    descriptor: (I)Z
    flags: (0x0001) ACC_PUBLIC
    Code:
      stack=2, locals=2, args_size=2
         0: aload_0
         1: getfield      #2                  // Field delegate:Lcom/fasterxml/jackson/core/JsonParser;
         4: iload_1
         5: invokevirtual #38                 // Method com/fasterxml/jackson/core/JsonParser.hasTokenId:(I)Z
         8: ireturn
      LineNumberTable:
        line 154: 0
      LocalVariableTable:
        Start  Length  Slot  Name   Signature
            0       9     0  this   Lcom/fasterxml/jackson/core/util/JsonParserDelegate;
            0       9     1    id   I

  public boolean hasToken(com.fasterxml.jackson.core.JsonToken);
    descriptor: (Lcom/fasterxml/jackson/core/JsonToken;)Z
    flags: (0x0001) ACC_PUBLIC
    Code:
      stack=2, locals=2, args_size=2
         0: aload_0
         1: getfield      #2                  // Field delegate:Lcom/fasterxml/jackson/core/JsonParser;
         4: aload_1
         5: invokevirtual #39                 // Method com/fasterxml/jackson/core/JsonParser.hasToken:(Lcom/fasterxml/jackson/core/JsonToken;)Z
         8: ireturn
      LineNumberTable:
        line 155: 0
      LocalVariableTable:
        Start  Length  Slot  Name   Signature
            0       9     0  this   Lcom/fasterxml/jackson/core/util/JsonParserDelegate;
            0       9     1     t   Lcom/fasterxml/jackson/core/JsonToken;

  public boolean isExpectedStartArrayToken();
    descriptor: ()Z
    flags: (0x0001) ACC_PUBLIC
    Code:
      stack=1, locals=1, args_size=1
         0: aload_0
         1: getfield      #2                  // Field delegate:Lcom/fasterxml/jackson/core/JsonParser;
         4: invokevirtual #40                 // Method com/fasterxml/jackson/core/JsonParser.isExpectedStartArrayToken:()Z
         7: ireturn
      LineNumberTable:
        line 157: 0
      LocalVariableTable:
        Start  Length  Slot  Name   Signature
            0       8     0  this   Lcom/fasterxml/jackson/core/util/JsonParserDelegate;

  public boolean isExpectedStartObjectToken();
    descriptor: ()Z
    flags: (0x0001) ACC_PUBLIC
    Code:
      stack=1, locals=1, args_size=1
         0: aload_0
         1: getfield      #2                  // Field delegate:Lcom/fasterxml/jackson/core/JsonParser;
         4: invokevirtual #41                 // Method com/fasterxml/jackson/core/JsonParser.isExpectedStartObjectToken:()Z
         7: ireturn
      LineNumberTable:
        line 158: 0
      LocalVariableTable:
        Start  Length  Slot  Name   Signature
            0       8     0  this   Lcom/fasterxml/jackson/core/util/JsonParserDelegate;

  public boolean isExpectedNumberIntToken();
    descriptor: ()Z
    flags: (0x0001) ACC_PUBLIC
    Code:
      stack=1, locals=1, args_size=1
         0: aload_0
         1: getfield      #2                  // Field delegate:Lcom/fasterxml/jackson/core/JsonParser;
         4: invokevirtual #42                 // Method com/fasterxml/jackson/core/JsonParser.isExpectedNumberIntToken:()Z
         7: ireturn
      LineNumberTable:
        line 159: 0
      LocalVariableTable:
        Start  Length  Slot  Name   Signature
            0       8     0  this   Lcom/fasterxml/jackson/core/util/JsonParserDelegate;

  public boolean isNaN() throws java.io.IOException;
    descriptor: ()Z
    flags: (0x0001) ACC_PUBLIC
    Code:
      stack=1, locals=1, args_size=1
         0: aload_0
         1: getfield      #2                  // Field delegate:Lcom/fasterxml/jackson/core/JsonParser;
         4: invokevirtual #43                 // Method com/fasterxml/jackson/core/JsonParser.isNaN:()Z
         7: ireturn
      LineNumberTable:
        line 161: 0
      LocalVariableTable:
        Start  Length  Slot  Name   Signature
            0       8     0  this   Lcom/fasterxml/jackson/core/util/JsonParserDelegate;
    Exceptions:
      throws java.io.IOException

  public java.lang.String getText() throws java.io.IOException;
    descriptor: ()Ljava/lang/String;
    flags: (0x0001) ACC_PUBLIC
    Code:
      stack=1, locals=1, args_size=1
         0: aload_0
         1: getfield      #2                  // Field delegate:Lcom/fasterxml/jackson/core/JsonParser;
         4: invokevirtual #44                 // Method com/fasterxml/jackson/core/JsonParser.getText:()Ljava/lang/String;
         7: areturn
      LineNumberTable:
        line 169: 0
      LocalVariableTable:
        Start  Length  Slot  Name   Signature
            0       8     0  this   Lcom/fasterxml/jackson/core/util/JsonParserDelegate;
    Exceptions:
      throws java.io.IOException

  public boolean hasTextCharacters();
    descriptor: ()Z
    flags: (0x0001) ACC_PUBLIC
    Code:
      stack=1, locals=1, args_size=1
         0: aload_0
         1: getfield      #2                  // Field delegate:Lcom/fasterxml/jackson/core/JsonParser;
         4: invokevirtual #45                 // Method com/fasterxml/jackson/core/JsonParser.hasTextCharacters:()Z
         7: ireturn
      LineNumberTable:
        line 170: 0
      LocalVariableTable:
        Start  Length  Slot  Name   Signature
            0       8     0  this   Lcom/fasterxml/jackson/core/util/JsonParserDelegate;

  public char[] getTextCharacters() throws java.io.IOException;
    descriptor: ()[C
    flags: (0x0001) ACC_PUBLIC
    Code:
      stack=1, locals=1, args_size=1
         0: aload_0
         1: getfield      #2                  // Field delegate:Lcom/fasterxml/jackson/core/JsonParser;
         4: invokevirtual #46                 // Method com/fasterxml/jackson/core/JsonParser.getTextCharacters:()[C
         7: areturn
      LineNumberTable:
        line 171: 0
      LocalVariableTable:
        Start  Length  Slot  Name   Signature
            0       8     0  this   Lcom/fasterxml/jackson/core/util/JsonParserDelegate;
    Exceptions:
      throws java.io.IOException

  public int getTextLength() throws java.io.IOException;
    descriptor: ()I
    flags: (0x0001) ACC_PUBLIC
    Code:
      stack=1, locals=1, args_size=1
         0: aload_0
         1: getfield      #2                  // Field delegate:Lcom/fasterxml/jackson/core/JsonParser;
         4: invokevirtual #47                 // Method com/fasterxml/jackson/core/JsonParser.getTextLength:()I
         7: ireturn
      LineNumberTable:
        line 172: 0
      LocalVariableTable:
        Start  Length  Slot  Name   Signature
            0       8     0  this   Lcom/fasterxml/jackson/core/util/JsonParserDelegate;
    Exceptions:
      throws java.io.IOException

  public int getTextOffset() throws java.io.IOException;
    descriptor: ()I
    flags: (0x0001) ACC_PUBLIC
    Code:
      stack=1, locals=1, args_size=1
         0: aload_0
         1: getfield      #2                  // Field delegate:Lcom/fasterxml/jackson/core/JsonParser;
         4: invokevirtual #48                 // Method com/fasterxml/jackson/core/JsonParser.getTextOffset:()I
         7: ireturn
      LineNumberTable:
        line 173: 0
      LocalVariableTable:
        Start  Length  Slot  Name   Signature
            0       8     0  this   Lcom/fasterxml/jackson/core/util/JsonParserDelegate;
    Exceptions:
      throws java.io.IOException

  public int getText(java.io.Writer) throws java.io.IOException, java.lang.UnsupportedOperationException;
    descriptor: (Ljava/io/Writer;)I
    flags: (0x0001) ACC_PUBLIC
    Code:
      stack=2, locals=2, args_size=2
         0: aload_0
         1: getfield      #2                  // Field delegate:Lcom/fasterxml/jackson/core/JsonParser;
         4: aload_1
         5: invokevirtual #49                 // Method com/fasterxml/jackson/core/JsonParser.getText:(Ljava/io/Writer;)I
         8: ireturn
      LineNumberTable:
        line 174: 0
      LocalVariableTable:
        Start  Length  Slot  Name   Signature
            0       9     0  this   Lcom/fasterxml/jackson/core/util/JsonParserDelegate;
            0       9     1 writer   Ljava/io/Writer;
    Exceptions:
      throws java.io.IOException, java.lang.UnsupportedOperationException

  public java.math.BigInteger getBigIntegerValue() throws java.io.IOException;
    descriptor: ()Ljava/math/BigInteger;
    flags: (0x0001) ACC_PUBLIC
    Code:
      stack=1, locals=1, args_size=1
         0: aload_0
         1: getfield      #2                  // Field delegate:Lcom/fasterxml/jackson/core/JsonParser;
         4: invokevirtual #50                 // Method com/fasterxml/jackson/core/JsonParser.getBigIntegerValue:()Ljava/math/BigInteger;
         7: areturn
      LineNumberTable:
        line 183: 0
      LocalVariableTable:
        Start  Length  Slot  Name   Signature
            0       8     0  this   Lcom/fasterxml/jackson/core/util/JsonParserDelegate;
    Exceptions:
      throws java.io.IOException

  public boolean getBooleanValue() throws java.io.IOException;
    descriptor: ()Z
    flags: (0x0001) ACC_PUBLIC
    Code:
      stack=1, locals=1, args_size=1
         0: aload_0
         1: getfield      #2                  // Field delegate:Lcom/fasterxml/jackson/core/JsonParser;
         4: invokevirtual #51                 // Method com/fasterxml/jackson/core/JsonParser.getBooleanValue:()Z
         7: ireturn
      LineNumberTable:
        line 186: 0
      LocalVariableTable:
        Start  Length  Slot  Name   Signature
            0       8     0  this   Lcom/fasterxml/jackson/core/util/JsonParserDelegate;
    Exceptions:
      throws java.io.IOException

  public byte getByteValue() throws java.io.IOException;
    descriptor: ()B
    flags: (0x0001) ACC_PUBLIC
    Code:
      stack=1, locals=1, args_size=1
         0: aload_0
         1: getfield      #2                  // Field delegate:Lcom/fasterxml/jackson/core/JsonParser;
         4: invokevirtual #52                 // Method com/fasterxml/jackson/core/JsonParser.getByteValue:()B
         7: ireturn
      LineNumberTable:
        line 189: 0
      LocalVariableTable:
        Start  Length  Slot  Name   Signature
            0       8     0  this   Lcom/fasterxml/jackson/core/util/JsonParserDelegate;
    Exceptions:
      throws java.io.IOException

  public short getShortValue() throws java.io.IOException;
    descriptor: ()S
    flags: (0x0001) ACC_PUBLIC
    Code:
      stack=1, locals=1, args_size=1
         0: aload_0
         1: getfield      #2                  // Field delegate:Lcom/fasterxml/jackson/core/JsonParser;
         4: invokevirtual #53                 // Method com/fasterxml/jackson/core/JsonParser.getShortValue:()S
         7: ireturn
      LineNumberTable:
        line 192: 0
      LocalVariableTable:
        Start  Length  Slot  Name   Signature
            0       8     0  this   Lcom/fasterxml/jackson/core/util/JsonParserDelegate;
    Exceptions:
      throws java.io.IOException

  public java.math.BigDecimal getDecimalValue() throws java.io.IOException;
    descriptor: ()Ljava/math/BigDecimal;
    flags: (0x0001) ACC_PUBLIC
    Code:
      stack=1, locals=1, args_size=1
         0: aload_0
         1: getfield      #2                  // Field delegate:Lcom/fasterxml/jackson/core/JsonParser;
         4: invokevirtual #54                 // Method com/fasterxml/jackson/core/JsonParser.getDecimalValue:()Ljava/math/BigDecimal;
         7: areturn
      LineNumberTable:
        line 195: 0
      LocalVariableTable:
        Start  Length  Slot  Name   Signature
            0       8     0  this   Lcom/fasterxml/jackson/core/util/JsonParserDelegate;
    Exceptions:
      throws java.io.IOException

  public double getDoubleValue() throws java.io.IOException;
    descriptor: ()D
    flags: (0x0001) ACC_PUBLIC
    Code:
      stack=2, locals=1, args_size=1
         0: aload_0
         1: getfield      #2                  // Field delegate:Lcom/fasterxml/jackson/core/JsonParser;
         4: invokevirtual #55                 // Method com/fasterxml/jackson/core/JsonParser.getDoubleValue:()D
         7: dreturn
      LineNumberTable:
        line 198: 0
      LocalVariableTable:
        Start  Length  Slot  Name   Signature
            0       8     0  this   Lcom/fasterxml/jackson/core/util/JsonParserDelegate;
    Exceptions:
      throws java.io.IOException

  public float getFloatValue() throws java.io.IOException;
    descriptor: ()F
    flags: (0x0001) ACC_PUBLIC
    Code:
      stack=1, locals=1, args_size=1
         0: aload_0
         1: getfield      #2                  // Field delegate:Lcom/fasterxml/jackson/core/JsonParser;
         4: invokevirtual #56                 // Method com/fasterxml/jackson/core/JsonParser.getFloatValue:()F
         7: freturn
      LineNumberTable:
        line 201: 0
      LocalVariableTable:
        Start  Length  Slot  Name   Signature
            0       8     0  this   Lcom/fasterxml/jackson/core/util/JsonParserDelegate;
    Exceptions:
      throws java.io.IOException

  public int getIntValue() throws java.io.IOException;
    descriptor: ()I
    flags: (0x0001) ACC_PUBLIC
    Code:
      stack=1, locals=1, args_size=1
         0: aload_0
         1: getfield      #2                  // Field delegate:Lcom/fasterxml/jackson/core/JsonParser;
         4: invokevirtual #57                 // Method com/fasterxml/jackson/core/JsonParser.getIntValue:()I
         7: ireturn
      LineNumberTable:
        line 204: 0
      LocalVariableTable:
        Start  Length  Slot  Name   Signature
            0       8     0  this   Lcom/fasterxml/jackson/core/util/JsonParserDelegate;
    Exceptions:
      throws java.io.IOException

  public long getLongValue() throws java.io.IOException;
    descriptor: ()J
    flags: (0x0001) ACC_PUBLIC
    Code:
      stack=2, locals=1, args_size=1
         0: aload_0
         1: getfield      #2                  // Field delegate:Lcom/fasterxml/jackson/core/JsonParser;
         4: invokevirtual #58                 // Method com/fasterxml/jackson/core/JsonParser.getLongValue:()J
         7: lreturn
      LineNumberTable:
        line 207: 0
      LocalVariableTable:
        Start  Length  Slot  Name   Signature
            0       8     0  this   Lcom/fasterxml/jackson/core/util/JsonParserDelegate;
    Exceptions:
      throws java.io.IOException

  public com.fasterxml.jackson.core.JsonParser$NumberType getNumberType() throws java.io.IOException;
    descriptor: ()Lcom/fasterxml/jackson/core/JsonParser$NumberType;
    flags: (0x0001) ACC_PUBLIC
    Code:
      stack=1, locals=1, args_size=1
         0: aload_0
         1: getfield      #2                  // Field delegate:Lcom/fasterxml/jackson/core/JsonParser;
         4: invokevirtual #59                 // Method com/fasterxml/jackson/core/JsonParser.getNumberType:()Lcom/fasterxml/jackson/core/JsonParser$NumberType;
         7: areturn
      LineNumberTable:
        line 210: 0
      LocalVariableTable:
        Start  Length  Slot  Name   Signature
            0       8     0  this   Lcom/fasterxml/jackson/core/util/JsonParserDelegate;
    Exceptions:
      throws java.io.IOException

  public java.lang.Number getNumberValue() throws java.io.IOException;
    descriptor: ()Ljava/lang/Number;
    flags: (0x0001) ACC_PUBLIC
    Code:
      stack=1, locals=1, args_size=1
         0: aload_0
         1: getfield      #2                  // Field delegate:Lcom/fasterxml/jackson/core/JsonParser;
         4: invokevirtual #60                 // Method com/fasterxml/jackson/core/JsonParser.getNumberValue:()Ljava/lang/Number;
         7: areturn
      LineNumberTable:
        line 213: 0
      LocalVariableTable:
        Start  Length  Slot  Name   Signature
            0       8     0  this   Lcom/fasterxml/jackson/core/util/JsonParserDelegate;
    Exceptions:
      throws java.io.IOException

  public java.lang.Number getNumberValueExact() throws java.io.IOException;
    descriptor: ()Ljava/lang/Number;
    flags: (0x0001) ACC_PUBLIC
    Code:
      stack=1, locals=1, args_size=1
         0: aload_0
         1: getfield      #2                  // Field delegate:Lcom/fasterxml/jackson/core/JsonParser;
         4: invokevirtual #61                 // Method com/fasterxml/jackson/core/JsonParser.getNumberValueExact:()Ljava/lang/Number;
         7: areturn
      LineNumberTable:
        line 216: 0
      LocalVariableTable:
        Start  Length  Slot  Name   Signature
            0       8     0  this   Lcom/fasterxml/jackson/core/util/JsonParserDelegate;
    Exceptions:
      throws java.io.IOException

  public int getValueAsInt() throws java.io.IOException;
    descriptor: ()I
    flags: (0x0001) ACC_PUBLIC
    Code:
      stack=1, locals=1, args_size=1
         0: aload_0
         1: getfield      #2                  // Field delegate:Lcom/fasterxml/jackson/core/JsonParser;
         4: invokevirtual #62                 // Method com/fasterxml/jackson/core/JsonParser.getValueAsInt:()I
         7: ireturn
      LineNumberTable:
        line 224: 0
      LocalVariableTable:
        Start  Length  Slot  Name   Signature
            0       8     0  this   Lcom/fasterxml/jackson/core/util/JsonParserDelegate;
    Exceptions:
      throws java.io.IOException

  public int getValueAsInt(int) throws java.io.IOException;
    descriptor: (I)I
    flags: (0x0001) ACC_PUBLIC
    Code:
      stack=2, locals=2, args_size=2
         0: aload_0
         1: getfield      #2                  // Field delegate:Lcom/fasterxml/jackson/core/JsonParser;
         4: iload_1
         5: invokevirtual #63                 // Method com/fasterxml/jackson/core/JsonParser.getValueAsInt:(I)I
         8: ireturn
      LineNumberTable:
        line 225: 0
      LocalVariableTable:
        Start  Length  Slot  Name   Signature
            0       9     0  this   Lcom/fasterxml/jackson/core/util/JsonParserDelegate;
            0       9     1 defaultValue   I
    Exceptions:
      throws java.io.IOException

  public long getValueAsLong() throws java.io.IOException;
    descriptor: ()J
    flags: (0x0001) ACC_PUBLIC
    Code:
      stack=2, locals=1, args_size=1
         0: aload_0
         1: getfield      #2                  // Field delegate:Lcom/fasterxml/jackson/core/JsonParser;
         4: invokevirtual #64                 // Method com/fasterxml/jackson/core/JsonParser.getValueAsLong:()J
         7: lreturn
      LineNumberTable:
        line 226: 0
      LocalVariableTable:
        Start  Length  Slot  Name   Signature
            0       8     0  this   Lcom/fasterxml/jackson/core/util/JsonParserDelegate;
    Exceptions:
      throws java.io.IOException

  public long getValueAsLong(long) throws java.io.IOException;
    descriptor: (J)J
    flags: (0x0001) ACC_PUBLIC
    Code:
      stack=3, locals=3, args_size=2
         0: aload_0
         1: getfield      #2                  // Field delegate:Lcom/fasterxml/jackson/core/JsonParser;
         4: lload_1
         5: invokevirtual #65                 // Method com/fasterxml/jackson/core/JsonParser.getValueAsLong:(J)J
         8: lreturn
      LineNumberTable:
        line 227: 0
      LocalVariableTable:
        Start  Length  Slot  Name   Signature
            0       9     0  this   Lcom/fasterxml/jackson/core/util/JsonParserDelegate;
            0       9     1 defaultValue   J
    Exceptions:
      throws java.io.IOException

  public double getValueAsDouble() throws java.io.IOException;
    descriptor: ()D
    flags: (0x0001) ACC_PUBLIC
    Code:
      stack=2, locals=1, args_size=1
         0: aload_0
         1: getfield      #2                  // Field delegate:Lcom/fasterxml/jackson/core/JsonParser;
         4: invokevirtual #66                 // Method com/fasterxml/jackson/core/JsonParser.getValueAsDouble:()D
         7: dreturn
      LineNumberTable:
        line 228: 0
      LocalVariableTable:
        Start  Length  Slot  Name   Signature
            0       8     0  this   Lcom/fasterxml/jackson/core/util/JsonParserDelegate;
    Exceptions:
      throws java.io.IOException

  public double getValueAsDouble(double) throws java.io.IOException;
    descriptor: (D)D
    flags: (0x0001) ACC_PUBLIC
    Code:
      stack=3, locals=3, args_size=2
         0: aload_0
         1: getfield      #2                  // Field delegate:Lcom/fasterxml/jackson/core/JsonParser;
         4: dload_1
         5: invokevirtual #67                 // Method com/fasterxml/jackson/core/JsonParser.getValueAsDouble:(D)D
         8: dreturn
      LineNumberTable:
        line 229: 0
      LocalVariableTable:
        Start  Length  Slot  Name   Signature
            0       9     0  this   Lcom/fasterxml/jackson/core/util/JsonParserDelegate;
            0       9     1 defaultValue   D
    Exceptions:
      throws java.io.IOException

  public boolean getValueAsBoolean() throws java.io.IOException;
    descriptor: ()Z
    flags: (0x0001) ACC_PUBLIC
    Code:
      stack=1, locals=1, args_size=1
         0: aload_0
         1: getfield      #2                  // Field delegate:Lcom/fasterxml/jackson/core/JsonParser;
         4: invokevirtual #68                 // Method com/fasterxml/jackson/core/JsonParser.getValueAsBoolean:()Z
         7: ireturn
      LineNumberTable:
        line 230: 0
      LocalVariableTable:
        Start  Length  Slot  Name   Signature
            0       8     0  this   Lcom/fasterxml/jackson/core/util/JsonParserDelegate;
    Exceptions:
      throws java.io.IOException

  public boolean getValueAsBoolean(boolean) throws java.io.IOException;
    descriptor: (Z)Z
    flags: (0x0001) ACC_PUBLIC
    Code:
      stack=2, locals=2, args_size=2
         0: aload_0
         1: getfield      #2                  // Field delegate:Lcom/fasterxml/jackson/core/JsonParser;
         4: iload_1
         5: invokevirtual #69                 // Method com/fasterxml/jackson/core/JsonParser.getValueAsBoolean:(Z)Z
         8: ireturn
      LineNumberTable:
        line 231: 0
      LocalVariableTable:
        Start  Length  Slot  Name   Signature
            0       9     0  this   Lcom/fasterxml/jackson/core/util/JsonParserDelegate;
            0       9     1 defaultValue   Z
    Exceptions:
      throws java.io.IOException

  public java.lang.String getValueAsString() throws java.io.IOException;
    descriptor: ()Ljava/lang/String;
    flags: (0x0001) ACC_PUBLIC
    Code:
      stack=1, locals=1, args_size=1
         0: aload_0
         1: getfield      #2                  // Field delegate:Lcom/fasterxml/jackson/core/JsonParser;
         4: invokevirtual #70                 // Method com/fasterxml/jackson/core/JsonParser.getValueAsString:()Ljava/lang/String;
         7: areturn
      LineNumberTable:
        line 232: 0
      LocalVariableTable:
        Start  Length  Slot  Name   Signature
            0       8     0  this   Lcom/fasterxml/jackson/core/util/JsonParserDelegate;
    Exceptions:
      throws java.io.IOException

  public java.lang.String getValueAsString(java.lang.String) throws java.io.IOException;
    descriptor: (Ljava/lang/String;)Ljava/lang/String;
    flags: (0x0001) ACC_PUBLIC
    Code:
      stack=2, locals=2, args_size=2
         0: aload_0
         1: getfield      #2                  // Field delegate:Lcom/fasterxml/jackson/core/JsonParser;
         4: aload_1
         5: invokevirtual #71                 // Method com/fasterxml/jackson/core/JsonParser.getValueAsString:(Ljava/lang/String;)Ljava/lang/String;
         8: areturn
      LineNumberTable:
        line 233: 0
      LocalVariableTable:
        Start  Length  Slot  Name   Signature
            0       9     0  this   Lcom/fasterxml/jackson/core/util/JsonParserDelegate;
            0       9     1 defaultValue   Ljava/lang/String;
    Exceptions:
      throws java.io.IOException

  public java.lang.Object getEmbeddedObject() throws java.io.IOException;
    descriptor: ()Ljava/lang/Object;
    flags: (0x0001) ACC_PUBLIC
    Code:
      stack=1, locals=1, args_size=1
         0: aload_0
         1: getfield      #2                  // Field delegate:Lcom/fasterxml/jackson/core/JsonParser;
         4: invokevirtual #72                 // Method com/fasterxml/jackson/core/JsonParser.getEmbeddedObject:()Ljava/lang/Object;
         7: areturn
      LineNumberTable:
        line 241: 0
      LocalVariableTable:
        Start  Length  Slot  Name   Signature
            0       8     0  this   Lcom/fasterxml/jackson/core/util/JsonParserDelegate;
    Exceptions:
      throws java.io.IOException

  public byte[] getBinaryValue(com.fasterxml.jackson.core.Base64Variant) throws java.io.IOException;
    descriptor: (Lcom/fasterxml/jackson/core/Base64Variant;)[B
    flags: (0x0001) ACC_PUBLIC
    Code:
      stack=2, locals=2, args_size=2
         0: aload_0
         1: getfield      #2                  // Field delegate:Lcom/fasterxml/jackson/core/JsonParser;
         4: aload_1
         5: invokevirtual #73                 // Method com/fasterxml/jackson/core/JsonParser.getBinaryValue:(Lcom/fasterxml/jackson/core/Base64Variant;)[B
         8: areturn
      LineNumberTable:
        line 242: 0
      LocalVariableTable:
        Start  Length  Slot  Name   Signature
            0       9     0  this   Lcom/fasterxml/jackson/core/util/JsonParserDelegate;
            0       9     1 b64variant   Lcom/fasterxml/jackson/core/Base64Variant;
    Exceptions:
      throws java.io.IOException

  public int readBinaryValue(com.fasterxml.jackson.core.Base64Variant, java.io.OutputStream) throws java.io.IOException;
    descriptor: (Lcom/fasterxml/jackson/core/Base64Variant;Ljava/io/OutputStream;)I
    flags: (0x0001) ACC_PUBLIC
    Code:
      stack=3, locals=3, args_size=3
         0: aload_0
         1: getfield      #2                  // Field delegate:Lcom/fasterxml/jackson/core/JsonParser;
         4: aload_1
         5: aload_2
         6: invokevirtual #74                 // Method com/fasterxml/jackson/core/JsonParser.readBinaryValue:(Lcom/fasterxml/jackson/core/Base64Variant;Ljava/io/OutputStream;)I
         9: ireturn
      LineNumberTable:
        line 243: 0
      LocalVariableTable:
        Start  Length  Slot  Name   Signature
            0      10     0  this   Lcom/fasterxml/jackson/core/util/JsonParserDelegate;
            0      10     1 b64variant   Lcom/fasterxml/jackson/core/Base64Variant;
            0      10     2   out   Ljava/io/OutputStream;
    Exceptions:
      throws java.io.IOException

  public com.fasterxml.jackson.core.JsonToken nextToken() throws java.io.IOException;
    descriptor: ()Lcom/fasterxml/jackson/core/JsonToken;
    flags: (0x0001) ACC_PUBLIC
    Code:
      stack=1, locals=1, args_size=1
         0: aload_0
         1: getfield      #2                  // Field delegate:Lcom/fasterxml/jackson/core/JsonParser;
         4: invokevirtual #75                 // Method com/fasterxml/jackson/core/JsonParser.nextToken:()Lcom/fasterxml/jackson/core/JsonToken;
         7: areturn
      LineNumberTable:
        line 245: 0
      LocalVariableTable:
        Start  Length  Slot  Name   Signature
            0       8     0  this   Lcom/fasterxml/jackson/core/util/JsonParserDelegate;
    Exceptions:
      throws java.io.IOException

  public com.fasterxml.jackson.core.JsonToken nextValue() throws java.io.IOException;
    descriptor: ()Lcom/fasterxml/jackson/core/JsonToken;
    flags: (0x0001) ACC_PUBLIC
    Code:
      stack=1, locals=1, args_size=1
         0: aload_0
         1: getfield      #2                  // Field delegate:Lcom/fasterxml/jackson/core/JsonParser;
         4: invokevirtual #76                 // Method com/fasterxml/jackson/core/JsonParser.nextValue:()Lcom/fasterxml/jackson/core/JsonToken;
         7: areturn
      LineNumberTable:
        line 247: 0
      LocalVariableTable:
        Start  Length  Slot  Name   Signature
            0       8     0  this   Lcom/fasterxml/jackson/core/util/JsonParserDelegate;
    Exceptions:
      throws java.io.IOException

  public void finishToken() throws java.io.IOException;
    descriptor: ()V
    flags: (0x0001) ACC_PUBLIC
    Code:
      stack=1, locals=1, args_size=1
         0: aload_0
         1: getfield      #2                  // Field delegate:Lcom/fasterxml/jackson/core/JsonParser;
         4: invokevirtual #77                 // Method com/fasterxml/jackson/core/JsonParser.finishToken:()V
         7: return
      LineNumberTable:
        line 249: 0
      LocalVariableTable:
        Start  Length  Slot  Name   Signature
            0       8     0  this   Lcom/fasterxml/jackson/core/util/JsonParserDelegate;
    Exceptions:
      throws java.io.IOException

  public com.fasterxml.jackson.core.JsonParser skipChildren() throws java.io.IOException;
    descriptor: ()Lcom/fasterxml/jackson/core/JsonParser;
    flags: (0x0001) ACC_PUBLIC
    Code:
      stack=1, locals=1, args_size=1
         0: aload_0
         1: getfield      #2                  // Field delegate:Lcom/fasterxml/jackson/core/JsonParser;
         4: invokevirtual #78                 // Method com/fasterxml/jackson/core/JsonParser.skipChildren:()Lcom/fasterxml/jackson/core/JsonParser;
         7: pop
         8: aload_0
         9: areturn
      LineNumberTable:
        line 253: 0
        line 255: 8
      LocalVariableTable:
        Start  Length  Slot  Name   Signature
            0      10     0  this   Lcom/fasterxml/jackson/core/util/JsonParserDelegate;
    Exceptions:
      throws java.io.IOException

  public boolean canReadObjectId();
    descriptor: ()Z
    flags: (0x0001) ACC_PUBLIC
    Code:
      stack=1, locals=1, args_size=1
         0: aload_0
         1: getfield      #2                  // Field delegate:Lcom/fasterxml/jackson/core/JsonParser;
         4: invokevirtual #79                 // Method com/fasterxml/jackson/core/JsonParser.canReadObjectId:()Z
         7: ireturn
      LineNumberTable:
        line 264: 0
      LocalVariableTable:
        Start  Length  Slot  Name   Signature
            0       8     0  this   Lcom/fasterxml/jackson/core/util/JsonParserDelegate;

  public boolean canReadTypeId();
    descriptor: ()Z
    flags: (0x0001) ACC_PUBLIC
    Code:
      stack=1, locals=1, args_size=1
         0: aload_0
         1: getfield      #2                  // Field delegate:Lcom/fasterxml/jackson/core/JsonParser;
         4: invokevirtual #80                 // Method com/fasterxml/jackson/core/JsonParser.canReadTypeId:()Z
         7: ireturn
      LineNumberTable:
        line 265: 0
      LocalVariableTable:
        Start  Length  Slot  Name   Signature
            0       8     0  this   Lcom/fasterxml/jackson/core/util/JsonParserDelegate;

  public java.lang.Object getObjectId() throws java.io.IOException;
    descriptor: ()Ljava/lang/Object;
    flags: (0x0001) ACC_PUBLIC
    Code:
      stack=1, locals=1, args_size=1
         0: aload_0
         1: getfield      #2                  // Field delegate:Lcom/fasterxml/jackson/core/JsonParser;
         4: invokevirtual #81                 // Method com/fasterxml/jackson/core/JsonParser.getObjectId:()Ljava/lang/Object;
         7: areturn
      LineNumberTable:
        line 266: 0
      LocalVariableTable:
        Start  Length  Slot  Name   Signature
            0       8     0  this   Lcom/fasterxml/jackson/core/util/JsonParserDelegate;
    Exceptions:
      throws java.io.IOException

  public java.lang.Object getTypeId() throws java.io.IOException;
    descriptor: ()Ljava/lang/Object;
    flags: (0x0001) ACC_PUBLIC
    Code:
      stack=1, locals=1, args_size=1
         0: aload_0
         1: getfield      #2                  // Field delegate:Lcom/fasterxml/jackson/core/JsonParser;
         4: invokevirtual #82                 // Method com/fasterxml/jackson/core/JsonParser.getTypeId:()Ljava/lang/Object;
         7: areturn
      LineNumberTable:
        line 267: 0
      LocalVariableTable:
        Start  Length  Slot  Name   Signature
            0       8     0  this   Lcom/fasterxml/jackson/core/util/JsonParserDelegate;
    Exceptions:
      throws java.io.IOException

  public com.fasterxml.jackson.core.JsonParser delegate();
    descriptor: ()Lcom/fasterxml/jackson/core/JsonParser;
    flags: (0x0001) ACC_PUBLIC
    Code:
      stack=1, locals=1, args_size=1
         0: aload_0
         1: getfield      #2                  // Field delegate:Lcom/fasterxml/jackson/core/JsonParser;
         4: areturn
      LineNumberTable:
        line 282: 0
      LocalVariableTable:
        Start  Length  Slot  Name   Signature
            0       5     0  this   Lcom/fasterxml/jackson/core/util/JsonParserDelegate;
}
SourceFile: "JsonParserDelegate.java"
InnerClasses:
  public static final #103= #102 of #84;  // Feature=class com/fasterxml/jackson/core/JsonParser$Feature of class com/fasterxml/jackson/core/JsonParser
  public static final #215= #214 of #84;  // NumberType=class com/fasterxml/jackson/core/JsonParser$NumberType of class com/fasterxml/jackson/core/JsonParser
