Classfile /Users/mw/Projects/slang-braindump/.jar/jar11/assemble/slang-braindump/assemble/content/geny/ByteData.class
  Last modified May 29, 2022; size 5314 bytes
  SHA-256 checksum 29c276dd77d9fe59952b92628573f21dea1390960ade7b8118e3320ebc18ed68
  Compiled from "ByteData.scala"
public interface geny.ByteData
  minor version: 0
  major version: 52
  flags: (0x0601) ACC_PUBLIC, ACC_INTERFACE, ACC_ABSTRACT
  this_class: #2                          // geny/ByteData
  super_class: #4                         // java/lang/Object
  interfaces: 0, fields: 0, methods: 18, attributes: 5
Constant pool:
    #1 = Utf8               geny/ByteData
    #2 = Class              #1            // geny/ByteData
    #3 = Utf8               java/lang/Object
    #4 = Class              #3            // java/lang/Object
    #5 = Utf8               ByteData.scala
    #6 = Utf8               Lscala/reflect/ScalaSignature;
    #7 = Utf8               bytes
    #8 = Utf8               \u0006\u0005\u0005}gaB\u0013\'!\u0003\r\t!\u000b\u0005\u0006a\u0001!\t!\r\u0005\u0006k\u00011\tA\u000e\u0005\u0006{\u0001!\tA\u0010\u0005\u0006{\u0001!\tA\u0017\u0005\u0006O\u0002!\tA\u0010\u0005\u0006O\u0002!\t\u0001\u001b\u0005\u0006U\u0002!\tA\u0010\u0005\u0006U\u0002!\ta\u001b\u0005\u0006[\u0002!\tA\u001c\u0005\u0006[\u0002!\t\u0001_\u0004\u0006u\u001aB\ta\u001f\u0004\u0006K\u0019B\t! \u0005\u0006}2!\ta \u0004\u0007\u0003\u0003a\u0001)a\u0001\t\u0015\u0005MaB!f\u0001\n\u0003\t)\u0002\u0003\u0006\u0002$9\u0011\t\u0012)A\u0005\u0003/AaA \b\u0005\u0002\u0005\u0015\u0002\u0002C\u001b\u000f\u0011\u000b\u0007I\u0011\u0001\u001c\t\u0013\u00055b\"!A\u0005\u0002\u0005=\u0002\"CA\u001a\u001dE\u0005I\u0011AA\u001b\u0011%\tYEDA\u0001\n\u0003\ni\u0005C\u0005\u0002^9\t\t\u0011\"\u0001\u0002`!I\u0011q\r\b\u0002\u0002\u0013\u0005\u0011\u0011\u000e\u0005\n\u0003kr\u0011\u0011!C!\u0003oB\u0011\"!\"\u000f\u0003\u0003%\t!a\"\t\u0013\u0005Ee\"!A\u0005B\u0005M\u0005\"CAL\u001d\u0005\u0005I\u0011IAM\u0011%\tYJDA\u0001\n\u0003\ni\nC\u0005\u0002 :\t\t\u0011\"\u0011\u0002\"\u001eI\u0011Q\u0015\u0007\u0002\u0002#\u0005\u0011q\u0015\u0004\n\u0003\u0003a\u0011\u0011!E\u0001\u0003SCaA`\u0010\u0005\u0002\u0005}\u0006\"CAN?\u0005\u0005IQIAO\u0011%\t\tmHA\u0001\n\u0003\u000b\u0019\rC\u0005\u0002H~\t\t\u0011\"!\u0002J\"I\u0011Q[\u0010\u0002\u0002\u0013%\u0011q\u001b\u0002\t\u0005f$X\rR1uC*\tq%\u0001\u0003hK:L8\u0001A\n\u0003\u0001)\u0002\"a\u000b\u0018\u000e\u00031R\u0011!L\u0001\u0006g\u000e\fG.Y\u0005\u0003_1\u0012a!\u00118z%\u00164\u0017A\u0002\u0013j]&$H\u0005F\u00013!\tY3\'\u0003\u00025Y\t!QK\\5u\u0003\u0015\u0011\u0017\u0010^3t+\u00059\u0004cA\u00169u%\u0011\u0011\b\f\u0002\u0006\u0003J\u0014\u0018-\u001f\t\u0003WmJ!\u0001\u0010\u0017\u0003\t\tKH/Z\u0001\u0007gR\u0014\u0018N\\4\u0015\u0003}\u0002\"\u0001Q$\u000f\u0005\u0005+\u0005C\u0001\"-\u001b\u0005\u0019%B\u0001#)\u0003\u0019a$o\\8u}%\u0011a\tL\u0001\u0007!J,G-\u001a4\n\u0005!K%AB*ue&twM\u0003\u0002GY!\"1a\u0013(Q!\tYC*\u0003\u0002NY\tQA-\u001a9sK\u000e\fG/\u001a3\"\u0003=\u000b1\"V:fA9\"X\r\u001f;)SE*1eP)V%&\u0011!kU\u0001\u001cI1,7o]5oSR$sM]3bi\u0016\u0014H\u0005Z3gCVdG\u000f\n\u001a\u000b\u0005Qc\u0013A\u00033faJ,7-\u0019;fIF*1EV,Y):\u00111fV\u0005\u0003)2\nDAI\u0016-3\n)1oY1mCR\u0011qh\u0017\u0005\u00069\u0012\u0001\r!X\u0001\u0006G>$Wm\u0019\t\u0003=\u0006l\u0011a\u0018\u0006\u0003A2\n!![8\n\u0005\t|&!B\"pI\u0016\u001c\u0007\u0006\u0002\u0003L\u001d\u0012\fTaI RKJ\u000bTa\t,XMR\u000bDAI\u0016-3\u0006!A/\u001a=u)\ty\u0014\u000eC\u0003]\r\u0001\u0007Q,\u0001\u0003ue&lGCA m\u0011\u0015a\u0006\u00021\u0001^\u0003\u0015a\u0017N\\3t)\u0005y\u0007c\u00019v\u007f9\u0011\u0011o\u001d\b\u0003\u0005JL\u0011!L\u0005\u0003i2\nq\u0001]1dW\u0006<W-\u0003\u0002wo\n1a+Z2u_JT!\u0001\u001e\u0017\u0015\u0005=L\b\"\u0002/\u000b\u0001\u0004i\u0016\u0001\u0003\"zi\u0016$\u0015\r^1\u0011\u0005qdQ\"\u0001\u0014\u0014\u00051Q\u0013A\u0002\u001fj]&$h\bF\u0001|\u0005\u0019\u0019\u0005.\u001e8lgNAaBKA\u0003\u0003\u000f\ti\u0001\u0005\u0002}\u0001A\u00191&!\u0003\n\u0007\u0005-AFA\u0004Qe>$Wo\u0019;\u0011\u0007A\fy!C\u0002\u0002\u0012]\u0014AbU3sS\u0006d\u0017N_1cY\u0016\faa\u00195v].\u001cXCAA\f!\u0015\u0001\u0018\u0011DA\u000f\u0013\r\tYb\u001e\u0002\u0004\'\u0016\f\bc\u0001?\u0002 %\u0019\u0011\u0011\u0005\u0014\u0003\u000b\tKH/Z:\u0002\u000f\rDWO\\6tAQ!\u0011qEA\u0016!\r\tICD\u0007\u0002\u0019!9\u00111C\tA\u0002\u0005]\u0011\u0001B2paf$B!a\n\u00022!I\u00111C\n\u0011\u0002\u0003\u0007\u0011qC\u0001\u000fG>\u0004\u0018\u0010\n3fM\u0006,H\u000e\u001e\u00132+\t\t9D\u000b\u0003\u0002\u0018\u0005e2FAA\u001e!\u0011\ti$a\u0012\u000e\u0005\u0005}\"\u0002BA!\u0003\u0007\n\u0011\"\u001e8dQ\u0016\u001c7.\u001a3\u000b\u0007\u0005\u0015C&\u0001\u0006b]:|G/\u0019;j_:LA!!\u0013\u0002@\t\tRO\\2iK\u000e\\W\r\u001a,be&\fgnY3\u0002\u001bA\u0014x\u000eZ;diB\u0013XMZ5y+\t\ty\u0005\u0005\u0003\u0002R\u0005mSBAA*\u0015\u0011\t)&a\u0016\u0002\t1\fgn\u001a\u0006\u0003\u00033\nAA[1wC&\u0019\u0001*a\u0015\u0002\u0019A\u0014x\u000eZ;di\u0006\u0013\u0018\u000e^=\u0016\u0005\u0005\u0005\u0004cA\u0016\u0002d%\u0019\u0011Q\r\u0017\u0003\u0007%sG/\u0001\bqe>$Wo\u0019;FY\u0016lWM\u001c;\u0015\t\u0005-\u0014\u0011\u000f\t\u0004W\u00055\u0014bAA8Y\t\u0019\u0011I\\=\t\u0013\u0005Mt#!AA\u0002\u0005\u0005\u0014a\u0001=%c\u0005y\u0001O]8ek\u000e$\u0018\n^3sCR|\'/\u0006\u0002\u0002zA1\u00111PAA\u0003Wj!!! \u000b\u0007\u0005}D&\u0001\u0006d_2dWm\u0019;j_:LA!a!\u0002~\tA\u0011\n^3sCR|\'/\u0001\u0005dC:,\u0015/^1m)\u0011\tI)a$\u0011\u0007-\nY)C\u0002\u0002\u000e2\u0012qAQ8pY\u0016\fg\u000eC\u0005\u0002te\t\t\u00111\u0001\u0002l\u0005\u0011\u0002O]8ek\u000e$X\t\\3nK:$h*Y7f)\u0011\ty%!&\t\u0013\u0005M$$!AA\u0002\u0005\u0005\u0014\u0001\u00035bg\"\u001cu\u000eZ3\u0015\u0005\u0005\u0005\u0014\u0001\u0003;p\'R\u0014\u0018N\\4\u0015\u0005\u0005=\u0013AB3rk\u0006d7\u000f\u0006\u0003\u0002\n\u0006\r\u0006\"CA:;\u0005\u0005\t\u0019AA6\u0003\u0019\u0019\u0005.\u001e8lgB\u0019\u0011\u0011F\u0010\u0014\u000b}\tY+a.\u0011\u0011\u00055\u00161WA\f\u0003Oi!!a,\u000b\u0007\u0005EF&A\u0004sk:$\u0018.\\3\n\t\u0005U\u0016q\u0016\u0002\u0012\u0003\n\u001cHO]1di\u001a+hn\u0019;j_:\f\u0004\u0003BA]\u0003{k!!a/\u000b\u0007\u0001\f9&\u0003\u0003\u0002\u0012\u0005mFCAAT\u0003\u0015\t\u0007\u000f\u001d7z)\u0011\t9#!2\t\u000f\u0005M!\u00051\u0001\u0002\u0018\u00059QO\\1qa2LH\u0003BAf\u0003#\u0004RaKAg\u0003/I1!a4-\u0005\u0019y\u0005\u000f^5p]\"I\u00111[\u0012\u0002\u0002\u0003\u0007\u0011qE\u0001\u0004q\u0012\u0002\u0014\u0001D<sSR,\'+\u001a9mC\u000e,GCAAm!\u0011\t\t&a7\n\t\u0005u\u00171\u000b\u0002\u0007\u001f\nTWm\u0019;
    #9 = Utf8               geny/ByteData$Chunks
   #10 = Class              #9            // geny/ByteData$Chunks
   #11 = Utf8               Chunks
   #12 = Utf8               geny/ByteData$Chunks$
   #13 = Class              #12           // geny/ByteData$Chunks$
   #14 = Utf8               Chunks$
   #15 = Utf8               ()[B
   #16 = Utf8               string$
   #17 = Utf8               (Lgeny/ByteData;)Ljava/lang/String;
   #18 = Utf8               $this
   #19 = Utf8               string
   #20 = Utf8               ()Ljava/lang/String;
   #21 = NameAndType        #19:#20       // string:()Ljava/lang/String;
   #22 = InterfaceMethodref #2.#21        // geny/ByteData.string:()Ljava/lang/String;
   #23 = Utf8               Lgeny/ByteData;
   #24 = Utf8               scala/io/Codec$
   #25 = Class              #24           // scala/io/Codec$
   #26 = Utf8               MODULE$
   #27 = Utf8               Lscala/io/Codec$;
   #28 = NameAndType        #26:#27       // MODULE$:Lscala/io/Codec$;
   #29 = Fieldref           #25.#28       // scala/io/Codec$.MODULE$:Lscala/io/Codec$;
   #30 = Utf8               java/nio/charset/StandardCharsets
   #31 = Class              #30           // java/nio/charset/StandardCharsets
   #32 = Utf8               UTF_8
   #33 = Utf8               Ljava/nio/charset/Charset;
   #34 = NameAndType        #32:#33       // UTF_8:Ljava/nio/charset/Charset;
   #35 = Fieldref           #31.#34       // java/nio/charset/StandardCharsets.UTF_8:Ljava/nio/charset/Charset;
   #36 = Utf8               charset2codec
   #37 = Utf8               (Ljava/nio/charset/Charset;)Lscala/io/Codec;
   #38 = NameAndType        #36:#37       // charset2codec:(Ljava/nio/charset/Charset;)Lscala/io/Codec;
   #39 = Methodref          #25.#38       // scala/io/Codec$.charset2codec:(Ljava/nio/charset/Charset;)Lscala/io/Codec;
   #40 = Utf8               text
   #41 = Utf8               (Lscala/io/Codec;)Ljava/lang/String;
   #42 = NameAndType        #40:#41       // text:(Lscala/io/Codec;)Ljava/lang/String;
   #43 = InterfaceMethodref #2.#42        // geny/ByteData.text:(Lscala/io/Codec;)Ljava/lang/String;
   #44 = Utf8               this
   #45 = Utf8               (Lgeny/ByteData;Lscala/io/Codec;)Ljava/lang/String;
   #46 = Utf8               codec
   #47 = NameAndType        #19:#41       // string:(Lscala/io/Codec;)Ljava/lang/String;
   #48 = InterfaceMethodref #2.#47        // geny/ByteData.string:(Lscala/io/Codec;)Ljava/lang/String;
   #49 = Utf8               Lscala/io/Codec;
   #50 = Utf8               java/lang/String
   #51 = Class              #50           // java/lang/String
   #52 = NameAndType        #7:#15        // bytes:()[B
   #53 = InterfaceMethodref #2.#52        // geny/ByteData.bytes:()[B
   #54 = Utf8               scala/io/Codec
   #55 = Class              #54           // scala/io/Codec
   #56 = Utf8               charSet
   #57 = Utf8               ()Ljava/nio/charset/Charset;
   #58 = NameAndType        #56:#57       // charSet:()Ljava/nio/charset/Charset;
   #59 = Methodref          #55.#58       // scala/io/Codec.charSet:()Ljava/nio/charset/Charset;
   #60 = Utf8               <init>
   #61 = Utf8               ([BLjava/nio/charset/Charset;)V
   #62 = NameAndType        #60:#61       // "<init>":([BLjava/nio/charset/Charset;)V
   #63 = Methodref          #51.#62       // java/lang/String."<init>":([BLjava/nio/charset/Charset;)V
   #64 = Utf8               text$
   #65 = NameAndType        #40:#20       // text:()Ljava/lang/String;
   #66 = InterfaceMethodref #2.#65        // geny/ByteData.text:()Ljava/lang/String;
   #67 = Utf8               trim$
   #68 = Utf8               trim
   #69 = NameAndType        #68:#20       // trim:()Ljava/lang/String;
   #70 = InterfaceMethodref #2.#69        // geny/ByteData.trim:()Ljava/lang/String;
   #71 = NameAndType        #68:#41       // trim:(Lscala/io/Codec;)Ljava/lang/String;
   #72 = InterfaceMethodref #2.#71        // geny/ByteData.trim:(Lscala/io/Codec;)Ljava/lang/String;
   #73 = Methodref          #51.#69       // java/lang/String.trim:()Ljava/lang/String;
   #74 = Utf8               lines$
   #75 = Utf8               (Lgeny/ByteData;)Lscala/collection/immutable/Vector;
   #76 = Utf8               lines
   #77 = Utf8               ()Lscala/collection/immutable/Vector;
   #78 = NameAndType        #76:#77       // lines:()Lscala/collection/immutable/Vector;
   #79 = InterfaceMethodref #2.#78        // geny/ByteData.lines:()Lscala/collection/immutable/Vector;
   #80 = Utf8               ()Lscala/collection/immutable/Vector<Ljava/lang/String;>;
   #81 = Utf8               (Lscala/io/Codec;)Lscala/collection/immutable/Vector;
   #82 = NameAndType        #76:#81       // lines:(Lscala/io/Codec;)Lscala/collection/immutable/Vector;
   #83 = InterfaceMethodref #2.#82        // geny/ByteData.lines:(Lscala/io/Codec;)Lscala/collection/immutable/Vector;
   #84 = Utf8               (Lgeny/ByteData;Lscala/io/Codec;)Lscala/collection/immutable/Vector;
   #85 = Utf8               (Lscala/io/Codec;)Lscala/collection/immutable/Vector<Ljava/lang/String;>;
   #86 = Utf8               scala/collection/StringOps$
   #87 = Class              #86           // scala/collection/StringOps$
   #88 = Utf8               Lscala/collection/StringOps$;
   #89 = NameAndType        #26:#88       // MODULE$:Lscala/collection/StringOps$;
   #90 = Fieldref           #87.#89       // scala/collection/StringOps$.MODULE$:Lscala/collection/StringOps$;
   #91 = Utf8               scala/Predef$
   #92 = Class              #91           // scala/Predef$
   #93 = Utf8               Lscala/Predef$;
   #94 = NameAndType        #26:#93       // MODULE$:Lscala/Predef$;
   #95 = Fieldref           #92.#94       // scala/Predef$.MODULE$:Lscala/Predef$;
   #96 = Utf8               augmentString
   #97 = Utf8               (Ljava/lang/String;)Ljava/lang/String;
   #98 = NameAndType        #96:#97       // augmentString:(Ljava/lang/String;)Ljava/lang/String;
   #99 = Methodref          #92.#98       // scala/Predef$.augmentString:(Ljava/lang/String;)Ljava/lang/String;
  #100 = Utf8               lines$extension
  #101 = Utf8               (Ljava/lang/String;)Lscala/collection/Iterator;
  #102 = NameAndType        #100:#101     // lines$extension:(Ljava/lang/String;)Lscala/collection/Iterator;
  #103 = Methodref          #87.#102      // scala/collection/StringOps$.lines$extension:(Ljava/lang/String;)Lscala/collection/Iterator;
  #104 = Utf8               scala/collection/Iterator
  #105 = Class              #104          // scala/collection/Iterator
  #106 = Utf8               toVector
  #107 = NameAndType        #106:#77      // toVector:()Lscala/collection/immutable/Vector;
  #108 = InterfaceMethodref #105.#107     // scala/collection/Iterator.toVector:()Lscala/collection/immutable/Vector;
  #109 = Utf8               $init$
  #110 = Utf8               (Lgeny/ByteData;)V
  #111 = Utf8               Code
  #112 = Utf8               LineNumberTable
  #113 = Utf8               LocalVariableTable
  #114 = Utf8               MethodParameters
  #115 = Utf8               Deprecated
  #116 = Utf8               Signature
  #117 = Utf8               InnerClasses
  #118 = Utf8               SourceFile
  #119 = Utf8               RuntimeVisibleAnnotations
  #120 = Utf8               ScalaInlineInfo
  #121 = Utf8               ScalaSig
{
  public abstract byte[] bytes();
    descriptor: ()[B
    flags: (0x0401) ACC_PUBLIC, ACC_ABSTRACT

  public static java.lang.String string$(geny.ByteData);
    descriptor: (Lgeny/ByteData;)Ljava/lang/String;
    flags: (0x1009) ACC_PUBLIC, ACC_STATIC, ACC_SYNTHETIC
    Code:
      stack=1, locals=1, args_size=1
         0: aload_0
         1: invokespecial #22                 // InterfaceMethod string:()Ljava/lang/String;
         4: areturn
      LineNumberTable:
        line 16: 0
      LocalVariableTable:
        Start  Length  Slot  Name   Signature
            0       5     0 $this   Lgeny/ByteData;
    MethodParameters:
      Name                           Flags
      $this                          final synthetic

  public default java.lang.String string();
    descriptor: ()Ljava/lang/String;
    flags: (0x0001) ACC_PUBLIC
    Code:
      stack=3, locals=1, args_size=1
         0: aload_0
         1: getstatic     #29                 // Field scala/io/Codec$.MODULE$:Lscala/io/Codec$;
         4: getstatic     #35                 // Field java/nio/charset/StandardCharsets.UTF_8:Ljava/nio/charset/Charset;
         7: invokevirtual #39                 // Method scala/io/Codec$.charset2codec:(Ljava/nio/charset/Charset;)Lscala/io/Codec;
        10: invokeinterface #43,  2           // InterfaceMethod text:(Lscala/io/Codec;)Ljava/lang/String;
        15: areturn
      LineNumberTable:
        line 16: 0
      LocalVariableTable:
        Start  Length  Slot  Name   Signature
            0      16     0  this   Lgeny/ByteData;
    Deprecated: true

  public static java.lang.String string$(geny.ByteData, scala.io.Codec);
    descriptor: (Lgeny/ByteData;Lscala/io/Codec;)Ljava/lang/String;
    flags: (0x1009) ACC_PUBLIC, ACC_STATIC, ACC_SYNTHETIC
    Code:
      stack=2, locals=2, args_size=2
         0: aload_0
         1: aload_1
         2: invokespecial #48                 // InterfaceMethod string:(Lscala/io/Codec;)Ljava/lang/String;
         5: areturn
      LineNumberTable:
        line 19: 0
      LocalVariableTable:
        Start  Length  Slot  Name   Signature
            0       6     0 $this   Lgeny/ByteData;
            0       6     1 codec   Lscala/io/Codec;
    MethodParameters:
      Name                           Flags
      $this                          final synthetic
      codec                          final

  public default java.lang.String string(scala.io.Codec);
    descriptor: (Lscala/io/Codec;)Ljava/lang/String;
    flags: (0x0001) ACC_PUBLIC
    Code:
      stack=4, locals=2, args_size=2
         0: new           #51                 // class java/lang/String
         3: dup
         4: aload_0
         5: invokeinterface #53,  1           // InterfaceMethod bytes:()[B
        10: aload_1
        11: invokevirtual #59                 // Method scala/io/Codec.charSet:()Ljava/nio/charset/Charset;
        14: invokespecial #63                 // Method java/lang/String."<init>":([BLjava/nio/charset/Charset;)V
        17: areturn
      LineNumberTable:
        line 19: 0
      LocalVariableTable:
        Start  Length  Slot  Name   Signature
            0      18     0  this   Lgeny/ByteData;
            0      18     1 codec   Lscala/io/Codec;
    Deprecated: true
    MethodParameters:
      Name                           Flags
      codec                          final

  public static java.lang.String text$(geny.ByteData);
    descriptor: (Lgeny/ByteData;)Ljava/lang/String;
    flags: (0x1009) ACC_PUBLIC, ACC_STATIC, ACC_SYNTHETIC
    Code:
      stack=1, locals=1, args_size=1
         0: aload_0
         1: invokespecial #66                 // InterfaceMethod text:()Ljava/lang/String;
         4: areturn
      LineNumberTable:
        line 21: 0
      LocalVariableTable:
        Start  Length  Slot  Name   Signature
            0       5     0 $this   Lgeny/ByteData;
    MethodParameters:
      Name                           Flags
      $this                          final synthetic

  public default java.lang.String text();
    descriptor: ()Ljava/lang/String;
    flags: (0x0001) ACC_PUBLIC
    Code:
      stack=3, locals=1, args_size=1
         0: aload_0
         1: getstatic     #29                 // Field scala/io/Codec$.MODULE$:Lscala/io/Codec$;
         4: getstatic     #35                 // Field java/nio/charset/StandardCharsets.UTF_8:Ljava/nio/charset/Charset;
         7: invokevirtual #39                 // Method scala/io/Codec$.charset2codec:(Ljava/nio/charset/Charset;)Lscala/io/Codec;
        10: invokeinterface #43,  2           // InterfaceMethod text:(Lscala/io/Codec;)Ljava/lang/String;
        15: areturn
      LineNumberTable:
        line 21: 0
      LocalVariableTable:
        Start  Length  Slot  Name   Signature
            0      16     0  this   Lgeny/ByteData;

  public static java.lang.String text$(geny.ByteData, scala.io.Codec);
    descriptor: (Lgeny/ByteData;Lscala/io/Codec;)Ljava/lang/String;
    flags: (0x1009) ACC_PUBLIC, ACC_STATIC, ACC_SYNTHETIC
    Code:
      stack=2, locals=2, args_size=2
         0: aload_0
         1: aload_1
         2: invokespecial #43                 // InterfaceMethod text:(Lscala/io/Codec;)Ljava/lang/String;
         5: areturn
      LineNumberTable:
        line 22: 0
      LocalVariableTable:
        Start  Length  Slot  Name   Signature
            0       6     0 $this   Lgeny/ByteData;
            0       6     1 codec   Lscala/io/Codec;
    MethodParameters:
      Name                           Flags
      $this                          final synthetic
      codec                          final

  public default java.lang.String text(scala.io.Codec);
    descriptor: (Lscala/io/Codec;)Ljava/lang/String;
    flags: (0x0001) ACC_PUBLIC
    Code:
      stack=4, locals=2, args_size=2
         0: new           #51                 // class java/lang/String
         3: dup
         4: aload_0
         5: invokeinterface #53,  1           // InterfaceMethod bytes:()[B
        10: aload_1
        11: invokevirtual #59                 // Method scala/io/Codec.charSet:()Ljava/nio/charset/Charset;
        14: invokespecial #63                 // Method java/lang/String."<init>":([BLjava/nio/charset/Charset;)V
        17: areturn
      LineNumberTable:
        line 22: 0
      LocalVariableTable:
        Start  Length  Slot  Name   Signature
            0      18     0  this   Lgeny/ByteData;
            0      18     1 codec   Lscala/io/Codec;
    MethodParameters:
      Name                           Flags
      codec                          final

  public static java.lang.String trim$(geny.ByteData);
    descriptor: (Lgeny/ByteData;)Ljava/lang/String;
    flags: (0x1009) ACC_PUBLIC, ACC_STATIC, ACC_SYNTHETIC
    Code:
      stack=1, locals=1, args_size=1
         0: aload_0
         1: invokespecial #70                 // InterfaceMethod trim:()Ljava/lang/String;
         4: areturn
      LineNumberTable:
        line 24: 0
      LocalVariableTable:
        Start  Length  Slot  Name   Signature
            0       5     0 $this   Lgeny/ByteData;
    MethodParameters:
      Name                           Flags
      $this                          final synthetic

  public default java.lang.String trim();
    descriptor: ()Ljava/lang/String;
    flags: (0x0001) ACC_PUBLIC
    Code:
      stack=3, locals=1, args_size=1
         0: aload_0
         1: getstatic     #29                 // Field scala/io/Codec$.MODULE$:Lscala/io/Codec$;
         4: getstatic     #35                 // Field java/nio/charset/StandardCharsets.UTF_8:Ljava/nio/charset/Charset;
         7: invokevirtual #39                 // Method scala/io/Codec$.charset2codec:(Ljava/nio/charset/Charset;)Lscala/io/Codec;
        10: invokeinterface #72,  2           // InterfaceMethod trim:(Lscala/io/Codec;)Ljava/lang/String;
        15: areturn
      LineNumberTable:
        line 24: 0
      LocalVariableTable:
        Start  Length  Slot  Name   Signature
            0      16     0  this   Lgeny/ByteData;

  public static java.lang.String trim$(geny.ByteData, scala.io.Codec);
    descriptor: (Lgeny/ByteData;Lscala/io/Codec;)Ljava/lang/String;
    flags: (0x1009) ACC_PUBLIC, ACC_STATIC, ACC_SYNTHETIC
    Code:
      stack=2, locals=2, args_size=2
         0: aload_0
         1: aload_1
         2: invokespecial #72                 // InterfaceMethod trim:(Lscala/io/Codec;)Ljava/lang/String;
         5: areturn
      LineNumberTable:
        line 25: 0
      LocalVariableTable:
        Start  Length  Slot  Name   Signature
            0       6     0 $this   Lgeny/ByteData;
            0       6     1 codec   Lscala/io/Codec;
    MethodParameters:
      Name                           Flags
      $this                          final synthetic
      codec                          final

  public default java.lang.String trim(scala.io.Codec);
    descriptor: (Lscala/io/Codec;)Ljava/lang/String;
    flags: (0x0001) ACC_PUBLIC
    Code:
      stack=2, locals=2, args_size=2
         0: aload_0
         1: aload_1
         2: invokeinterface #43,  2           // InterfaceMethod text:(Lscala/io/Codec;)Ljava/lang/String;
         7: invokevirtual #73                 // Method java/lang/String.trim:()Ljava/lang/String;
        10: areturn
      LineNumberTable:
        line 25: 0
      LocalVariableTable:
        Start  Length  Slot  Name   Signature
            0      11     0  this   Lgeny/ByteData;
            0      11     1 codec   Lscala/io/Codec;
    MethodParameters:
      Name                           Flags
      codec                          final

  public static scala.collection.immutable.Vector lines$(geny.ByteData);
    descriptor: (Lgeny/ByteData;)Lscala/collection/immutable/Vector;
    flags: (0x1009) ACC_PUBLIC, ACC_STATIC, ACC_SYNTHETIC
    Code:
      stack=1, locals=1, args_size=1
         0: aload_0
         1: invokespecial #79                 // InterfaceMethod lines:()Lscala/collection/immutable/Vector;
         4: areturn
      LineNumberTable:
        line 27: 0
      LocalVariableTable:
        Start  Length  Slot  Name   Signature
            0       5     0 $this   Lgeny/ByteData;
    MethodParameters:
      Name                           Flags
      $this                          final synthetic

  public default scala.collection.immutable.Vector<java.lang.String> lines();
    descriptor: ()Lscala/collection/immutable/Vector;
    flags: (0x0001) ACC_PUBLIC
    Code:
      stack=3, locals=1, args_size=1
         0: aload_0
         1: getstatic     #29                 // Field scala/io/Codec$.MODULE$:Lscala/io/Codec$;
         4: getstatic     #35                 // Field java/nio/charset/StandardCharsets.UTF_8:Ljava/nio/charset/Charset;
         7: invokevirtual #39                 // Method scala/io/Codec$.charset2codec:(Ljava/nio/charset/Charset;)Lscala/io/Codec;
        10: invokeinterface #83,  2           // InterfaceMethod lines:(Lscala/io/Codec;)Lscala/collection/immutable/Vector;
        15: areturn
      LineNumberTable:
        line 27: 0
      LocalVariableTable:
        Start  Length  Slot  Name   Signature
            0      16     0  this   Lgeny/ByteData;
    Signature: #80                          // ()Lscala/collection/immutable/Vector<Ljava/lang/String;>;

  public static scala.collection.immutable.Vector lines$(geny.ByteData, scala.io.Codec);
    descriptor: (Lgeny/ByteData;Lscala/io/Codec;)Lscala/collection/immutable/Vector;
    flags: (0x1009) ACC_PUBLIC, ACC_STATIC, ACC_SYNTHETIC
    Code:
      stack=2, locals=2, args_size=2
         0: aload_0
         1: aload_1
         2: invokespecial #83                 // InterfaceMethod lines:(Lscala/io/Codec;)Lscala/collection/immutable/Vector;
         5: areturn
      LineNumberTable:
        line 28: 0
      LocalVariableTable:
        Start  Length  Slot  Name   Signature
            0       6     0 $this   Lgeny/ByteData;
            0       6     1 codec   Lscala/io/Codec;
    MethodParameters:
      Name                           Flags
      $this                          final synthetic
      codec                          final

  public default scala.collection.immutable.Vector<java.lang.String> lines(scala.io.Codec);
    descriptor: (Lscala/io/Codec;)Lscala/collection/immutable/Vector;
    flags: (0x0001) ACC_PUBLIC
    Code:
      stack=4, locals=2, args_size=2
         0: getstatic     #90                 // Field scala/collection/StringOps$.MODULE$:Lscala/collection/StringOps$;
         3: getstatic     #95                 // Field scala/Predef$.MODULE$:Lscala/Predef$;
         6: aload_0
         7: aload_1
         8: invokeinterface #43,  2           // InterfaceMethod text:(Lscala/io/Codec;)Ljava/lang/String;
        13: invokevirtual #99                 // Method scala/Predef$.augmentString:(Ljava/lang/String;)Ljava/lang/String;
        16: invokevirtual #103                // Method scala/collection/StringOps$.lines$extension:(Ljava/lang/String;)Lscala/collection/Iterator;
        19: invokeinterface #108,  1          // InterfaceMethod scala/collection/Iterator.toVector:()Lscala/collection/immutable/Vector;
        24: areturn
      LineNumberTable:
        line 28: 0
      LocalVariableTable:
        Start  Length  Slot  Name   Signature
            0      25     0  this   Lgeny/ByteData;
            0      25     1 codec   Lscala/io/Codec;
    Signature: #85                          // (Lscala/io/Codec;)Lscala/collection/immutable/Vector<Ljava/lang/String;>;
    MethodParameters:
      Name                           Flags
      codec                          final

  public static void $init$(geny.ByteData);
    descriptor: (Lgeny/ByteData;)V
    flags: (0x0009) ACC_PUBLIC, ACC_STATIC
    Code:
      stack=0, locals=1, args_size=1
         0: return
      LineNumberTable:
        line 11: 0
      LocalVariableTable:
        Start  Length  Slot  Name   Signature
            0       1     0 $this   Lgeny/ByteData;
    MethodParameters:
      Name                           Flags
      $this                          final synthetic
}
InnerClasses:
  public static #11= #10 of #2;           // Chunks=class geny/ByteData$Chunks of class geny/ByteData
  public static #14= #13 of #2;           // Chunks$=class geny/ByteData$Chunks$ of class geny/ByteData
SourceFile: "ByteData.scala"
RuntimeVisibleAnnotations:
  0: #6(#7=s#8)
    scala.reflect.ScalaSignature(
      bytes="\u0006\u0005\u0005}gaB\u0013\'!\u0003\r\t!\u000b\u0005\u0006a\u0001!\t!\r\u0005\u0006k\u00011\tA\u000e\u0005\u0006{\u0001!\tA\u0010\u0005\u0006{\u0001!\tA\u0017\u0005\u0006O\u0002!\tA\u0010\u0005\u0006O\u0002!\t\u0001\u001b\u0005\u0006U\u0002!\tA\u0010\u0005\u0006U\u0002!\ta\u001b\u0005\u0006[\u0002!\tA\u001c\u0005\u0006[\u0002!\t\u0001_\u0004\u0006u\u001aB\ta\u001f\u0004\u0006K\u0019B\t! \u0005\u0006}2!\ta \u0004\u0007\u0003\u0003a\u0001)a\u0001\t\u0015\u0005MaB!f\u0001\n\u0003\t)\u0002\u0003\u0006\u0002$9\u0011\t\u0012)A\u0005\u0003/AaA \b\u0005\u0002\u0005\u0015\u0002\u0002C\u001b\u000f\u0011\u000b\u0007I\u0011\u0001\u001c\t\u0013\u00055b\"!A\u0005\u0002\u0005=\u0002\"CA\u001a\u001dE\u0005I\u0011AA\u001b\u0011%\tYEDA\u0001\n\u0003\ni\u0005C\u0005\u0002^9\t\t\u0011\"\u0001\u0002`!I\u0011q\r\b\u0002\u0002\u0013\u0005\u0011\u0011\u000e\u0005\n\u0003kr\u0011\u0011!C!\u0003oB\u0011\"!\"\u000f\u0003\u0003%\t!a\"\t\u0013\u0005Ee\"!A\u0005B\u0005M\u0005\"CAL\u001d\u0005\u0005I\u0011IAM\u0011%\tYJDA\u0001\n\u0003\ni\nC\u0005\u0002 :\t\t\u0011\"\u0011\u0002\"\u001eI\u0011Q\u0015\u0007\u0002\u0002#\u0005\u0011q\u0015\u0004\n\u0003\u0003a\u0011\u0011!E\u0001\u0003SCaA`\u0010\u0005\u0002\u0005}\u0006\"CAN?\u0005\u0005IQIAO\u0011%\t\tmHA\u0001\n\u0003\u000b\u0019\rC\u0005\u0002H~\t\t\u0011\"!\u0002J\"I\u0011Q[\u0010\u0002\u0002\u0013%\u0011q\u001b\u0002\t\u0005f$X\rR1uC*\tq%\u0001\u0003hK:L8\u0001A\n\u0003\u0001)\u0002\"a\u000b\u0018\u000e\u00031R\u0011!L\u0001\u0006g\u000e\fG.Y\u0005\u0003_1\u0012a!\u00118z%\u00164\u0017A\u0002\u0013j]&$H\u0005F\u00013!\tY3\'\u0003\u00025Y\t!QK\\5u\u0003\u0015\u0011\u0017\u0010^3t+\u00059\u0004cA\u00169u%\u0011\u0011\b\f\u0002\u0006\u0003J\u0014\u0018-\u001f\t\u0003WmJ!\u0001\u0010\u0017\u0003\t\tKH/Z\u0001\u0007gR\u0014\u0018N\\4\u0015\u0003}\u0002\"\u0001Q$\u000f\u0005\u0005+\u0005C\u0001\"-\u001b\u0005\u0019%B\u0001#)\u0003\u0019a$o\\8u}%\u0011a\tL\u0001\u0007!J,G-\u001a4\n\u0005!K%AB*ue&twM\u0003\u0002GY!\"1a\u0013(Q!\tYC*\u0003\u0002NY\tQA-\u001a9sK\u000e\fG/\u001a3\"\u0003=\u000b1\"V:fA9\"X\r\u001f;)SE*1eP)V%&\u0011!kU\u0001\u001cI1,7o]5oSR$sM]3bi\u0016\u0014H\u0005Z3gCVdG\u000f\n\u001a\u000b\u0005Qc\u0013A\u00033faJ,7-\u0019;fIF*1EV,Y):\u00111fV\u0005\u0003)2\nDAI\u0016-3\n)1oY1mCR\u0011qh\u0017\u0005\u00069\u0012\u0001\r!X\u0001\u0006G>$Wm\u0019\t\u0003=\u0006l\u0011a\u0018\u0006\u0003A2\n!![8\n\u0005\t|&!B\"pI\u0016\u001c\u0007\u0006\u0002\u0003L\u001d\u0012\fTaI RKJ\u000bTa\t,XMR\u000bDAI\u0016-3\u0006!A/\u001a=u)\ty\u0014\u000eC\u0003]\r\u0001\u0007Q,\u0001\u0003ue&lGCA m\u0011\u0015a\u0006\u00021\u0001^\u0003\u0015a\u0017N\\3t)\u0005y\u0007c\u00019v\u007f9\u0011\u0011o\u001d\b\u0003\u0005JL\u0011!L\u0005\u0003i2\nq\u0001]1dW\u0006<W-\u0003\u0002wo\n1a+Z2u_JT!\u0001\u001e\u0017\u0015\u0005=L\b\"\u0002/\u000b\u0001\u0004i\u0016\u0001\u0003\"zi\u0016$\u0015\r^1\u0011\u0005qdQ\"\u0001\u0014\u0014\u00051Q\u0013A\u0002\u001fj]&$h\bF\u0001|\u0005\u0019\u0019\u0005.\u001e8lgNAaBKA\u0003\u0003\u000f\ti\u0001\u0005\u0002}\u0001A\u00191&!\u0003\n\u0007\u0005-AFA\u0004Qe>$Wo\u0019;\u0011\u0007A\fy!C\u0002\u0002\u0012]\u0014AbU3sS\u0006d\u0017N_1cY\u0016\faa\u00195v].\u001cXCAA\f!\u0015\u0001\u0018\u0011DA\u000f\u0013\r\tYb\u001e\u0002\u0004\'\u0016\f\bc\u0001?\u0002 %\u0019\u0011\u0011\u0005\u0014\u0003\u000b\tKH/Z:\u0002\u000f\rDWO\\6tAQ!\u0011qEA\u0016!\r\tICD\u0007\u0002\u0019!9\u00111C\tA\u0002\u0005]\u0011\u0001B2paf$B!a\n\u00022!I\u00111C\n\u0011\u0002\u0003\u0007\u0011qC\u0001\u000fG>\u0004\u0018\u0010\n3fM\u0006,H\u000e\u001e\u00132+\t\t9D\u000b\u0003\u0002\u0018\u0005e2FAA\u001e!\u0011\ti$a\u0012\u000e\u0005\u0005}\"\u0002BA!\u0003\u0007\n\u0011\"\u001e8dQ\u0016\u001c7.\u001a3\u000b\u0007\u0005\u0015C&\u0001\u0006b]:|G/\u0019;j_:LA!!\u0013\u0002@\t\tRO\\2iK\u000e\\W\r\u001a,be&\fgnY3\u0002\u001bA\u0014x\u000eZ;diB\u0013XMZ5y+\t\ty\u0005\u0005\u0003\u0002R\u0005mSBAA*\u0015\u0011\t)&a\u0016\u0002\t1\fgn\u001a\u0006\u0003\u00033\nAA[1wC&\u0019\u0001*a\u0015\u0002\u0019A\u0014x\u000eZ;di\u0006\u0013\u0018\u000e^=\u0016\u0005\u0005\u0005\u0004cA\u0016\u0002d%\u0019\u0011Q\r\u0017\u0003\u0007%sG/\u0001\bqe>$Wo\u0019;FY\u0016lWM\u001c;\u0015\t\u0005-\u0014\u0011\u000f\t\u0004W\u00055\u0014bAA8Y\t\u0019\u0011I\\=\t\u0013\u0005Mt#!AA\u0002\u0005\u0005\u0014a\u0001=%c\u0005y\u0001O]8ek\u000e$\u0018\n^3sCR|\'/\u0006\u0002\u0002zA1\u00111PAA\u0003Wj!!! \u000b\u0007\u0005}D&\u0001\u0006d_2dWm\u0019;j_:LA!a!\u0002~\tA\u0011\n^3sCR|\'/\u0001\u0005dC:,\u0015/^1m)\u0011\tI)a$\u0011\u0007-\nY)C\u0002\u0002\u000e2\u0012qAQ8pY\u0016\fg\u000eC\u0005\u0002te\t\t\u00111\u0001\u0002l\u0005\u0011\u0002O]8ek\u000e$X\t\\3nK:$h*Y7f)\u0011\ty%!&\t\u0013\u0005M$$!AA\u0002\u0005\u0005\u0014\u0001\u00035bg\"\u001cu\u000eZ3\u0015\u0005\u0005\u0005\u0014\u0001\u0003;p\'R\u0014\u0018N\\4\u0015\u0005\u0005=\u0013AB3rk\u0006d7\u000f\u0006\u0003\u0002\n\u0006\r\u0006\"CA:;\u0005\u0005\t\u0019AA6\u0003\u0019\u0019\u0005.\u001e8lgB\u0019\u0011\u0011F\u0010\u0014\u000b}\tY+a.\u0011\u0011\u00055\u00161WA\f\u0003Oi!!a,\u000b\u0007\u0005EF&A\u0004sk:$\u0018.\\3\n\t\u0005U\u0016q\u0016\u0002\u0012\u0003\n\u001cHO]1di\u001a+hn\u0019;j_:\f\u0004\u0003BA]\u0003{k!!a/\u000b\u0007\u0001\f9&\u0003\u0003\u0002\u0012\u0005mFCAAT\u0003\u0015\t\u0007\u000f\u001d7z)\u0011\t9#!2\t\u000f\u0005M!\u00051\u0001\u0002\u0018\u00059QO\\1qa2LH\u0003BAf\u0003#\u0004RaKAg\u0003/I1!a4-\u0005\u0019y\u0005\u000f^5p]\"I\u00111[\u0012\u0002\u0002\u0003\u0007\u0011qE\u0001\u0004q\u0012\u0002\u0014\u0001D<sSR,\'+\u001a9mC\u000e,GCAAm!\u0011\t\t&a7\n\t\u0005u\u00171\u000b\u0002\u0007\u001f\nTWm\u0019;"
    )
  ScalaInlineInfo: length = 0x5E (unknown attribute)
   01 00 00 12 00 6D 00 6E 01 00 07 00 0F 00 00 4C
   00 4D 00 00 4C 00 51 00 00 4A 00 4B 01 00 4A 00
   54 01 00 13 00 14 00 00 13 00 29 00 00 10 00 11
   01 00 10 00 2D 01 00 28 00 14 00 00 28 00 29 00
   00 40 00 11 01 00 40 00 2D 01 00 44 00 14 00 00
   44 00 29 00 00 43 00 11 01 00 43 00 2D 01
  ScalaSig: length = 0x3 (unknown attribute)
   05 02 00
