Classfile /Users/mw/Projects/slang-braindump/.jar/jar11/assemble/slang-braindump/assemble/content/geny/Generator.class
  Last modified May 29, 2022; size 33933 bytes
  SHA-256 checksum b8c11ad93ea8234397bb442979da6ba5b377a652f05c75187dc381c950ed14d8
  Compiled from "Generator.scala"
public interface geny.Generator<A extends java.lang.Object>
  minor version: 0
  major version: 52
  flags: (0x0601) ACC_PUBLIC, ACC_INTERFACE, ACC_ABSTRACT
  this_class: #2                          // geny/Generator
  super_class: #5                         // java/lang/Object
  interfaces: 0, fields: 0, methods: 123, attributes: 7
Constant pool:
    #1 = Utf8               geny/Generator
    #2 = Class              #1            // geny/Generator
    #3 = Utf8               <A:Ljava/lang/Object;>Ljava/lang/Object;
    #4 = Utf8               java/lang/Object
    #5 = Class              #4            // java/lang/Object
    #6 = Utf8               Generator.scala
    #7 = Utf8               Lscala/reflect/ScalaSignature;
    #8 = Utf8               bytes
    #9 = Utf8               \u0006\u0005\u00155da\u0002<x!\u0003\r\tA\u001f\u0005\b\u0003\u000b\u0001A\u0011AA\u0004\u0011\u001d\ty\u0001\u0001D\u0001\u0003#Aqa!\u0010\u0001\t\u0003\u0019y\u0004C\u0004\u0004F\u0001!\taa\u0012\t\u000f\rM\u0003\u0001\"\u0001\u0004V!91\u0011\f\u0001\u0005\u0002\rm\u0003bBB1\u0001\u0011\u000511\r\u0005\b\u0007O\u0002A\u0011AB5\u0011%\u0019i\u0007AI\u0001\n\u0003\u0019y\u0007C\u0004\u0004\u0006\u0002!\taa\"\t\u000f\ru\u0005\u0001\"\u0001\u0004 \"91q\u0016\u0001\u0005\u0002\rE\u0006bBB`\u0001\u0011\u00051\u0011\u0019\u0005\b\u0007\u001b\u0004A\u0011ABh\u0011\u001d\u0019)\u000e\u0001C\u0001\u0007/Dqaa7\u0001\t\u0003\u0019i\u000eC\u0004\u0004l\u0002!\ta!<\t\u000f\rm\b\u0001\"\u0001\u0004~\"9Aq\u0002\u0001\u0005\u0002\u0011E\u0001b\u0002C\u0010\u0001\u0011\u0005A\u0011\u0005\u0005\b\t_\u0001A\u0011\u0001C\u0019\u0011\u001d!9\u0004\u0001C\u0001\tsAq\u0001b\u0010\u0001\t\u0003!\t\u0005C\u0004\u0005F\u0001!\t\u0001b\u0012\t\u000f\u0011-\u0003\u0001\"\u0001\u0005N!9A\u0011\u000b\u0001\u0005\u0002\u0011M\u0003b\u0002C-\u0001\u0011\u0005A1\f\u0005\b\tW\u0002A\u0011\u0001C7\u0011\u001d!I\b\u0001C\u0001\twBq\u0001\" \u0001\t\u0003!y\bC\u0004\u0005\u0002\u0002!\t\u0001b!\t\u000f\u0011m\u0005\u0001\"\u0001\u0005\u001e\"9A1\u0018\u0001\u0005\u0002\u0011u\u0006b\u0002Cc\u0001\u0011\u0005Aq\u0019\u0005\b\t+\u0004A\u0011\u0001Cl\u0011\u001d!)\u000f\u0001C\u0001\tODq\u0001b<\u0001\t\u0003!\t\u0010C\u0004\u0005p\u0002!\t\u0001b?\t\u000f\u0011=\b\u0001\"\u0001\u0005\u0000\"9Q\u0011\u0001\u0001\u0005\u0002\u0015\r\u0001bBC\u000b\u0001\u0011\u0005Qq\u0003\u0005\b\u000bG\u0001A\u0011AC\u0013\u0011\u001d)9\u0004\u0001C\u0001\u000bsAq!\"\u0012\u0001\t\u0003)9\u0005C\u0004\u0006Z\u0001!\t!b\u0017\b\u000f\u0005eq\u000f#\u0001\u0002\u001c\u00191ao\u001eE\u0001\u0003;Aq!a\b0\t\u0003\t\tCB\u0005\u0002$=\u0002\n1%\t\u0002&\u001d9\u0011QH\u0018\t\u0002\u0005mbaBA\u001b_!\u0005\u0011q\u0007\u0005\b\u0003?\u0019D\u0011AA\u001d\u000f\u001d\tyd\fE\u0001\u0003g1q!!\u000b0\u0011\u0003\tY\u0003C\u0004\u0002 Y\"\t!!\r\t\u000f\u0005\u0005s\u0006\"\u0001\u0002D!9\u0011\u0011N\u0018\u0005\u0004\u0005-\u0004bBAU_\u0011\u0005\u00111\u0016\u0004\u0007\u0003#|C!a5\t\u0015\u0005]6H!A%\u0002\u0013\ti\u000eC\u0004\u0002 m\"\t!a9\t\u000f\u0005=1\b\"\u0001\u0002j\"9\u0011\u0011_\u001e\u0005B\u0005MhA\u0002B\u0003_\u0011\u00119\u0001\u0003\u0006\u0003\u0012\u0001\u0013\t\u0011)A\u0005\u0005\u0017A!Ba\u0005A\u0005\u0003\u0005\u000b\u0011\u0002B\u0006\u0011\u001d\ty\u0002\u0011C\u0001\u0005+Aq!a\u0004A\t\u0003\u0011i\u0002C\u0004\u0002r\u0002#\t%a=\u0007\r\t\rr\u0006\u0002B\u0013\u0011)\u0011\tB\u0012B\u0001B\u0003%!q\u0007\u0005\b\u0003?1E\u0011\u0001B\u001d\u0011\u001d\tyA\u0012C\u0001\u0005\u007fAq!!=G\t\u0003\n\u0019P\u0002\u0004\u0003F=\"!q\t\u0005\u000b\u0005#Y%\u0011!Q\u0001\n\te\u0003B\u0003B\n\u0017\n\u0005\t\u0015!\u0003\u0003\\!9\u0011qD&\u0005\u0002\t\u0005\u0004bBA\b\u0017\u0012\u0005!\u0011\u000e\u0005\b\u0003c\\E\u0011IAz\r\u0019\u0011yg\f\u0003\u0003r!Q!\u0011C)\u0003\u0002\u0003\u0006IA!\u001e\t\u0015\tm\u0014K!A!\u0002\u0013\u0011i\bC\u0004\u0002 E#\tA!\"\t\u000f\u0005=\u0011\u000b\"\u0001\u0003\u000e\"9\u0011\u0011_)\u0005B\u0005MhA\u0002BJ_\u0011\u0011)\n\u0003\u0006\u0003\u0012]\u0013\t\u0011)A\u0005\u0005?C!B!*X\u0005\u0003\u0005\u000b\u0011\u0002BT\u0011\u001d\tyb\u0016C\u0001\u0005SCq!a\u0004X\t\u0003\u0011\t\fC\u0004\u0002r^#\t%a=\u0007\r\t]v\u0006\u0002B]\u0011)\u0011\t\"\u0018B\u0001B\u0003%!1\u0019\u0005\u000b\u0005Kk&\u0011!Q\u0001\n\t%\u0007bBA\u0010;\u0012\u0005!1\u001a\u0005\b\u0003\u001fiF\u0011\u0001Bj\u0011\u001d\t\t0\u0018C!\u0003g4aA!70\t\tm\u0007B\u0003B\tG\n\u0005\t\u0015!\u0003\u0003`\"Q!Q]2\u0003\u0002\u0003\u0006IA!\r\t\u0015\t\u001d8M!A!\u0002\u0013\u0011\t\u0004C\u0004\u0002 \r$\tA!;\t\u000f\u0005=1\r\"\u0001\u0003t\"9\u0011\u0011_2\u0005B\u0005MhA\u0002B}_\u0011\u0011Y\u0010\u0003\u0006\u0003\u0012)\u0014\t\u0011)A\u0005\u0005\u007fD!Ba\u001fk\u0005\u0003\u0005\u000b\u0011BB\u0003\u0011\u001d\tyB\u001bC\u0001\u0007\u000fAq!a\u0004k\t\u0003\u0019y\u0001C\u0004\u0002r*$\t%a=\u0007\r\rUq\u0006BB\f\u0011)\u0011\t\u0002\u001dB\u0001B\u0003%11\u0004\u0005\u000b\u0005w\u0002(\u0011!Q\u0001\n\r\u0005\u0002bBA\u0010a\u0012\u000511\u0005\u0005\b\u0003\u001f\u0001H\u0011AB\u0016\u0011\u001d\t\t\u0010\u001dC!\u0003g\u0014\u0011bR3oKJ\fGo\u001c:\u000b\u0003a\fAaZ3os\u000e\u0001QcA>\u0004:M\u0011\u0001\u0001 \t\u0004{\u0006\u0005Q\"\u0001@\u000b\u0003}\fQa]2bY\u0006L1!a\u0001\u007f\u0005\u0019\te.\u001f*fM\u00061A%\u001b8ji\u0012\"\"!!\u0003\u0011\u0007u\fY!C\u0002\u0002\u000ey\u0014A!\u00168ji\u0006Aq-\u001a8fe\u0006$X\r\u0006\u0003\u0002\u0014\rE\u0002cAA\u000bc9\u0019\u0011q\u0003\u0018\u000e\u0003]\f\u0011bR3oKJ\fGo\u001c:\u0011\u0007\u0005]qf\u0005\u00020y\u00061A(\u001b8jiz\"\"!a\u0007\u0003\r\u0005\u001bG/[8o\'\t\tD0K\u00022mM\u0012\u0001bQ8oi&tW/Z\n\u0005mq\fi\u0003E\u0002\u00020Ej\u0011a\f\u000b\u0003\u0003g\u00012!a\f7\u0005\r)e\u000eZ\n\u0005gq\fi\u0003\u0006\u0002\u0002<A\u0019\u0011qF\u001a\u0002\u0007\u0015sG-\u0001\u0005D_:$\u0018N\\;f\u0003\u0015\t\u0007\u000f\u001d7z+\u0011\t)%!\u0014\u0015\t\u0005\u001d\u0013q\f\t\u0006\u0003/\u0001\u0011\u0011\n\t\u0005\u0003\u0017\ni\u0005\u0004\u0001\u0005\u000f\u0005=\u0003H1\u0001\u0002R\t\tA+\u0005\u0003\u0002T\u0005e\u0003cA?\u0002V%\u0019\u0011q\u000b@\u0003\u000f9{G\u000f[5oOB\u0019Q0a\u0017\n\u0007\u0005ucPA\u0002B]fDq!!\u00199\u0001\u0004\t\u0019\'\u0001\u0002ygB)Q0!\u001a\u0002J%\u0019\u0011q\r@\u0003\u0015q\u0012X\r]3bi\u0016$g(\u0001\u0003ge>lWCBA7\u0003\u0007\u000b)\b\u0006\u0003\u0002p\u0005\u0015F\u0003BA9\u0003o\u0002R!a\u0006\u0001\u0003g\u0002B!a\u0013\u0002v\u00119\u0011qJ\u001dC\u0002\u0005E\u0003bBA=s\u0001\u000f\u00111P\u0001\bG>tg/\u001a:u!\u001di\u0018QPAA\u0003\u001bK1!a \u007f\u0005%1UO\\2uS>t\u0017\u0007\u0005\u0004\u0002L\u0005\r\u00151\u000f\u0003\b\u0003\u000bK$\u0019AAD\u0005\u0005iU\u0003BA)\u0003\u0013#\u0001\"a#\u0002\u0004\n\u0007\u0011\u0011\u000b\u0002\u0002?B1\u0011qRAP\u0003grA!!%\u0002\u001c:!\u00111SAM\u001b\t\t)JC\u0002\u0002\u0018f\fa\u0001\u0010:p_Rt\u0014\"A@\n\u0007\u0005ue0A\u0004qC\u000e\\\u0017mZ3\n\t\u0005\u0005\u00161\u0015\u0002\u0010)J\fg/\u001a:tC\ndWm\u00148dK*\u0019\u0011Q\u0014@\t\u000f\u0005\u001d\u0016\b1\u0001\u0002\u0002\u0006\tA/A\u0006tK247\t\\8tS:<W\u0003BAW\u0003g#B!a,\u00026B)\u0011q\u0003\u0001\u00022B!\u00111JAZ\t\u001d\tyE\u000fb\u0001\u0003#B\u0001\"a.;\t\u0003\u0007\u0011\u0011X\u0001\r[\u0006\\W-\u0013;fe\u0006$xN\u001d\t\u0006{\u0006m\u0016qX\u0005\u0004\u0003{s(\u0001\u0003\u001fcs:\fW.\u001a \u0011\u000fu\f\t-!2\u0002L&\u0019\u00111\u0019@\u0003\rQ+\b\u000f\\33!\u0019\ty)a2\u00022&!\u0011\u0011ZAR\u0005!IE/\u001a:bi>\u0014\b#B?\u0002N\u0006%\u0011bAAh}\nIa)\u001e8di&|g\u000e\r\u0002\f\'\u0016dgm\u00117pg&tw-\u0006\u0003\u0002V\u0006m7\u0003B\u001e}\u0003/\u0004R!a\u0006\u0001\u00033\u0004B!a\u0013\u0002\\\u0012A\u0011qJ\u001e\u0005\u0006\u0004\t\t\u0006E\u0003~\u0003w\u000by\u000eE\u0004~\u0003\u0003\f\t/a3\u0011\r\u0005=\u0015qYAm)\u0011\t)/a:\u0011\u000b\u0005=2(!7\t\u0011\u0005]V\b\"a\u0001\u0003;$B!a\u0005\u0002l\"9\u0011Q\u001e A\u0002\u0005=\u0018!\u00014\u0011\u000fu\fi(!7\u0002\u0014\u0005AAo\\*ue&tw\r\u0006\u0002\u0002vB!\u0011q_A\u0000\u001d\u0011\tI0a?\u0011\u0007\u0005Me0C\u0002\u0002~z\fa\u0001\u0015:fI\u00164\u0017\u0002\u0002B\u0001\u0005\u0007\u0011aa\u0015;sS:<\'bAA\u007f}\n11i\u001c8dCR,BA!\u0003\u0003\u0010M!\u0001\t B\u0006!\u0015\t9\u0002\u0001B\u0007!\u0011\tYEa\u0004\u0005\u0011\u0005=\u0003\t\"b\u0001\u0003#\nQ!\u001b8oKJ\fQa\u001c;iKJ$bAa\u0006\u0003\u001a\tm\u0001#BA\u0018\u0001\n5\u0001b\u0002B\t\u0007\u0002\u0007!1\u0002\u0005\b\u0005\'\u0019\u0005\u0019\u0001B\u0006)\u0011\t\u0019Ba\b\t\u000f\u00055H\t1\u0001\u0003\"A9Q0! \u0003\u000e\u0005M!A\u0004.ja^KG\u000f[%oI\u0016DX\rZ\u000b\u0005\u0005O\u0011yc\u0005\u0003Gy\n%\u0002#BA\f\u0001\t-\u0002cB?\u0002B\n5\"\u0011\u0007\t\u0005\u0003\u0017\u0012y\u0003\u0002\u0005\u0002P\u0019#)\u0019AA)!\ri(1G\u0005\u0004\u0005kq(aA%oiB)\u0011q\u0003\u0001\u0003.Q!!1\bB\u001f!\u0015\tyC\u0012B\u0017\u0011\u001d\u0011\t\u0002\u0013a\u0001\u0005o!B!a\u0005\u0003B!9\u0011Q^%A\u0002\t\r\u0003cB?\u0002~\t-\u00121\u0003\u0002\u00075&\u0004\b/\u001a3\u0016\r\t%#\u0011\u000bB+\'\u0011YEPa\u0013\u0011\u000b\u0005]\u0001A!\u0014\u0011\u000fu\f\tMa\u0014\u0003TA!\u00111\nB)\t!\tye\u0013CC\u0002\u0005E\u0003\u0003BA&\u0005+\"qAa\u0016L\u0005\u0004\t\tFA\u0001W!\u0015\t9\u0002\u0001B(!\u0019\tyI!\u0018\u0003T%!!qLAR\u0005!IE/\u001a:bE2,GC\u0002B2\u0005K\u00129\u0007E\u0004\u00020-\u0013yEa\u0015\t\u000f\tEa\n1\u0001\u0003Z!9!1\u0003(A\u0002\tmC\u0003BA\n\u0005WBq!!<P\u0001\u0004\u0011i\u0007E\u0004~\u0003{\u0012i%a\u0005\u0003\u0011\u0019KG\u000e^3sK\u0012,BAa\u001d\u0003zM!\u0011\u000b B;!\u0015\t9\u0002\u0001B<!\u0011\tYE!\u001f\u0005\u0011\u0005=\u0013\u000b\"b\u0001\u0003#\nA\u0001\u001d:fIB9Q0! \u0003x\t}\u0004cA?\u0003\u0002&\u0019!1\u0011@\u0003\u000f\t{w\u000e\\3b]R1!q\u0011BE\u0005\u0017\u0003R!a\fR\u0005oBqA!\u0005U\u0001\u0004\u0011)\bC\u0004\u0003|Q\u0003\rA! \u0015\t\u0005M!q\u0012\u0005\b\u0003[,\u0006\u0019\u0001BI!\u001di\u0018Q\u0010B<\u0003\'\u0011a!T1qa\u0016$WC\u0002BL\u0005;\u0013\u0019k\u0005\u0003Xy\ne\u0005#BA\f\u0001\tm\u0005\u0003BA&\u0005;#\u0001\"a\u0014X\t\u000b\u0007\u0011\u0011\u000b\t\u0006\u0003/\u0001!\u0011\u0015\t\u0005\u0003\u0017\u0012\u0019\u000bB\u0004\u0003X]\u0013\r!!\u0015\u0002\t\u0019,hn\u0019\t\b{\u0006u$\u0011\u0015BN)\u0019\u0011YK!,\u00030B9\u0011qF,\u0003\u001c\n\u0005\u0006b\u0002B\t5\u0002\u0007!q\u0014\u0005\b\u0005KS\u0006\u0019\u0001BT)\u0011\t\u0019Ba-\t\u000f\u000558\f1\u0001\u00036B9Q0! \u0003\u001c\u0006M!A\u0003$mCRl\u0015\r\u001d9fIV1!1\u0018Ba\u0005\u000f\u001cB!\u0018?\u0003>B)\u0011q\u0003\u0001\u0003@B!\u00111\nBa\t!\ty%\u0018CC\u0002\u0005E\u0003#BA\f\u0001\t\u0015\u0007\u0003BA&\u0005\u000f$qAa\u0016^\u0005\u0004\t\t\u0006E\u0004~\u0003{\u0012)M!0\u0015\r\t5\'q\u001aBi!\u001d\ty#\u0018B`\u0005\u000bDqA!\u0005a\u0001\u0004\u0011\u0019\rC\u0004\u0003&\u0002\u0004\rA!3\u0015\t\u0005M!Q\u001b\u0005\b\u0003[\f\u0007\u0019\u0001Bl!\u001di\u0018Q\u0010B`\u0003\'\u0011aa\u00157jG\u0016$W\u0003\u0002Bo\u0005G\u001cBa\u0019?\u0003`B)\u0011q\u0003\u0001\u0003bB!\u00111\nBr\t!\tye\u0019CC\u0002\u0005E\u0013!B:uCJ$\u0018aA3oIRA!1\u001eBw\u0005_\u0014\t\u0010E\u0003\u00020\r\u0014\t\u000fC\u0004\u0003\u0012\u001d\u0004\rAa8\t\u000f\t\u0015x\r1\u0001\u00032!9!q]4A\u0002\tEB\u0003BA\n\u0005kDq!!<i\u0001\u0004\u00119\u0010E\u0004~\u0003{\u0012\t/a\u0005\u0003\u0013Q\u000b7.Z,iS2,W\u0003\u0002B\u007f\u0007\u0007\u0019BA\u001b?\u0003\u0000B)\u0011q\u0003\u0001\u0004\u0002A!\u00111JB\u0002\t!\tyE\u001bCC\u0002\u0005E\u0003cB?\u0002~\r\u0005!q\u0010\u000b\u0007\u0007\u0013\u0019Ya!\u0004\u0011\u000b\u0005=\"n!\u0001\t\u000f\tEQ\u000e1\u0001\u0003\u0000\"9!1P7A\u0002\r\u0015A\u0003BA\n\u0007#Aq!!<o\u0001\u0004\u0019\u0019\u0002E\u0004~\u0003{\u001a\t!a\u0005\u0003\u0013\u0011\u0013x\u000e],iS2,W\u0003BB\r\u0007?\u0019B\u0001\u001d?\u0004\u001cA)\u0011q\u0003\u0001\u0004\u001eA!\u00111JB\u0010\t!\ty\u0005\u001dCC\u0002\u0005E\u0003cB?\u0002~\ru!q\u0010\u000b\u0007\u0007K\u00199c!\u000b\u0011\u000b\u0005=\u0002o!\b\t\u000f\tE1\u000f1\u0001\u0004\u001c!9!1P:A\u0002\r\u0005B\u0003BA\n\u0007[Aq!!<u\u0001\u0004\u0019y\u0003E\u0004~\u0003{\u001ai\"a\u0005\t\u000f\rM\"\u00011\u0001\u00046\u0005Q\u0001.\u00198eY\u0016LE/Z7\u0011\u000fu\fiha\u000e\u0002\u0014A!\u00111JB\u001d\t!\u0019Y\u0004\u0001CC\u0002\u0005E#!A!\u0002\u000f\u0019|\'/Z1dQR!\u0011\u0011BB!\u0011\u001d\tio\u0001a\u0001\u0007\u0007\u0002r!`A?\u0007o\tI!\u0001\u0003gS:$G\u0003BB%\u0007\u001f\u0002R!`B&\u0007oI1a!\u0014\u007f\u0005\u0019y\u0005\u000f^5p]\"9\u0011Q\u001e\u0003A\u0002\rE\u0003cB?\u0002~\r]\"qP\u0001\u0007KbL7\u000f^:\u0015\t\t}4q\u000b\u0005\b\u0003[,\u0001\u0019AB)\u0003!\u0019wN\u001c;bS:\u001cH\u0003\u0002B@\u0007;Bqaa\u0018\u0007\u0001\u0004\tI&A\u0001b\u0003\u00191wN]1mYR!!qPB3\u0011\u001d\tio\u0002a\u0001\u0007#\nQaY8v]R$BA!\r\u0004l!I\u0011Q\u001e\u0005\u0011\u0002\u0003\u00071\u0011K\u0001\u0010G>,h\u000e\u001e\u0013eK\u001a\fW\u000f\u001c;%cU\u00111\u0011\u000f\u0016\u0005\u0007#\u001a\u0019h\u000b\u0002\u0004vA!1qOBA\u001b\t\u0019IH\u0003\u0003\u0004|\ru\u0014!C;oG\",7m[3e\u0015\r\u0019yH`\u0001\u000bC:tw\u000e^1uS>t\u0017\u0002BBB\u0007s\u0012\u0011#\u001e8dQ\u0016\u001c7.\u001a3WCJL\u0017M\\2f\u0003\u00111w\u000e\u001c3\u0016\t\r%5q\u0012\u000b\u0005\u0007\u0017\u001bY\n\u0006\u0003\u0004\u000e\u000eM\u0005\u0003BA&\u0007\u001f#qa!%\u000b\u0005\u0004\t\tFA\u0001C\u0011\u001d\tiO\u0003a\u0001\u0007+\u0003\u0012\"`BL\u0007\u001b\u001b9d!$\n\u0007\reePA\u0005Gk:\u001cG/[8oe!9!Q\u001d\u0006A\u0002\r5\u0015\u0001\u00034pY\u0012dUM\u001a;\u0016\t\r\u00056q\u0015\u000b\u0005\u0007G\u001bi\u000b\u0006\u0003\u0004&\u000e%\u0006\u0003BA&\u0007O#qa!%\f\u0005\u0004\t\t\u0006C\u0004\u0002n.\u0001\raa+\u0011\u0013u\u001c9j!*\u00048\r\u0015\u0006b\u0002Bs\u0017\u0001\u00071QU\u0001\u0007e\u0016$WoY3\u0016\t\rM6q\u0017\u000b\u0005\u0007k\u001bY\f\u0005\u0003\u0002L\r]FaBBI\u0019\t\u00071\u0011X\t\u0005\u0007o\tI\u0006C\u0004\u0002n2\u0001\ra!0\u0011\u0013u\u001c9j!.\u00048\rU\u0016A\u0003:fIV\u001cW\rT3giV!11YBd)\u0011\u0019)m!3\u0011\t\u0005-3q\u0019\u0003\b\u0007#k!\u0019AB]\u0011\u001d\ti/\u0004a\u0001\u0007\u0017\u0004\u0012\"`BL\u0007\u000b\u001c9d!2\u0002\r\u0019LG\u000e^3s)\u0011\u0019\tna5\u0011\u000b\u0005]\u0001aa\u000e\t\u000f\tmd\u00021\u0001\u0004R\u0005Qq/\u001b;i\r&dG/\u001a:\u0015\t\rE7\u0011\u001c\u0005\b\u0005wz\u0001\u0019AB)\u0003\ri\u0017\r]\u000b\u0005\u0007?\u001c)\u000f\u0006\u0003\u0004b\u000e\u001d\b#BA\f\u0001\r\r\b\u0003BA&\u0007K$qa!%\u0011\u0005\u0004\t\t\u0006C\u0004\u0003&B\u0001\ra!;\u0011\u000fu\fiha\u000e\u0004d\u00069a\r\\1u\u001b\u0006\u0004X\u0003BBx\u0007k$Ba!=\u0004xB)\u0011q\u0003\u0001\u0004tB!\u00111JB{\t\u001d\u0019\t*\u0005b\u0001\u0003#BqA!*\u0012\u0001\u0004\u0019I\u0010E\u0004~\u0003{\u001a9d!=\u0002\u000f\r|G\u000e\\3diV!1q C\u0003)\u0011!\t\u0001b\u0002\u0011\u000b\u0005]\u0001\u0001b\u0001\u0011\t\u0005-CQ\u0001\u0003\b\u0007#\u0013\"\u0019AA)\u0011\u001d\u0011)K\u0005a\u0001\t\u0013\u0001r! C\u0006\u0007o!\u0019!C\u0002\u0005\u000ey\u0014q\u0002U1si&\fGNR;oGRLwN\\\u0001\rG>dG.Z2u\r&\u00148\u000f^\u000b\u0005\t\'!I\u0002\u0006\u0003\u0005\u0016\u0011m\u0001#B?\u0004L\u0011]\u0001\u0003BA&\t3!qa!%\u0014\u0005\u0004\t\t\u0006C\u0004\u0003&N\u0001\r\u0001\"\b\u0011\u000fu$Yaa\u000e\u0005\u0018\u00059a\r\\1ui\u0016tW\u0003\u0002C\u0012\tS!B\u0001\"\n\u0005,A)\u0011q\u0003\u0001\u0005(A!\u00111\nC\u0015\t\u001d\u00119\u0006\u0006b\u0001\u0003#Bq!!<\u0015\u0001\b!i\u0003E\u0004~\u0003{\u001a9\u0004\"\n\u0002\u000bMd\u0017nY3\u0015\r\rEG1\u0007C\u001b\u0011\u001d\u0011)/\u0006a\u0001\u0005cAqAa:\u0016\u0001\u0004\u0011\t$\u0001\u0003uC.,G\u0003BBi\twAq\u0001\"\u0010\u0017\u0001\u0004\u0011\t$A\u0001o\u0003\u0011!\'o\u001c9\u0015\t\rEG1\t\u0005\b\t{9\u0002\u0019\u0001B\u0019\u0003%!\u0018m[3XQ&dW\r\u0006\u0003\u0004R\u0012%\u0003b\u0002B>1\u0001\u00071\u0011K\u0001\nIJ|\u0007o\u00165jY\u0016$Ba!5\u0005P!9!1P\rA\u0002\rE\u0013\u0001\u0004>ja^KG\u000f[%oI\u0016DXC\u0001C+!\u0015\t9\u0002\u0001C,!\u001di\u0018\u0011YB\u001c\u0005c\t1A_5q+\u0011!i\u0006\"\u001a\u0015\t\u0011}Cq\r\t\u0006\u0003/\u0001A\u0011\r\t\b{\u0006\u00057q\u0007C2!\u0011\tY\u0005\"\u001a\u0005\u000f\rE5D1\u0001\u0002R!9!1C\u000eA\u0002\u0011%\u0004CBAH\u0005;\"\u0019\'\u0001\u0006%a2,8\u000f\n9mkN,B\u0001b\u001c\u0005vQ!A\u0011\u000fC<!\u0015\t9\u0002\u0001C:!\u0011\tY\u0005\"\u001e\u0005\u000f\rEED1\u0001\u0004:\"9!1\u0003\u000fA\u0002\u0011E\u0014\u0001\u00025fC\u0012,\"aa\u000e\u0002\u0015!,\u0017\rZ(qi&|g.\u0006\u0002\u0004J\u0005AAo\u001c\"vM\u001a,\'/\u0006\u0003\u0005\u0006\u0012eUC\u0001CD!\u0019!I\tb%\u0005\u00186\u0011A1\u0012\u0006\u0005\t\u001b#y)A\u0004nkR\f\'\r\\3\u000b\u0007\u0011Ee0\u0001\u0006d_2dWm\u0019;j_:LA\u0001\"&\u0005\f\n1!)\u001e4gKJ\u0004B!a\u0013\u0005\u001a\u001291\u0011S\u0010C\u0002\re\u0016a\u0002;p\u0003J\u0014\u0018-_\u000b\u0005\t?#I\u000b\u0006\u0003\u0005\"\u0012-\u0006#B?\u0005$\u0012\u001d\u0016b\u0001CS}\n)\u0011I\u001d:bsB!\u00111\nCU\t\u001d\u0019\t\n\tb\u0001\u0007sC\u0011\u0002\",!\u0003\u0003\u0005\u001d\u0001b,\u0002\u0015\u00154\u0018\u000eZ3oG\u0016$\u0013\u0007\u0005\u0004\u00052\u0012]FqU\u0007\u0003\tgS1\u0001\".\u007f\u0003\u001d\u0011XM\u001a7fGRLA\u0001\"/\u00054\nA1\t\\1tgR\u000bw-A\u0003u_N+\u0017/\u0006\u0002\u0005@B1\u0011q\u0012Ca\u0007oIA\u0001b1\u0002$\n\u00191+Z9\u0002\rQ|G*[:u+\t!I\r\u0005\u0004\u0005L\u0012E7qG\u0007\u0003\t\u001bTA\u0001b4\u0005\u0010\u0006I\u0011.\\7vi\u0006\u0014G.Z\u0005\u0005\t\'$iM\u0001\u0003MSN$\u0018!\u0002;p\'\u0016$X\u0003\u0002Cm\tG,\"\u0001b7\u0011\r\u0011-GQ\u001cCq\u0013\u0011!y\u000e\"4\u0003\u0007M+G\u000f\u0005\u0003\u0002L\u0011\rHaBBIG\t\u00071\u0011X\u0001\ti>4Vm\u0019;peV\u0011A\u0011\u001e\t\u0007\t\u0017$Yoa\u000e\n\t\u00115HQ\u001a\u0002\u0007-\u0016\u001cGo\u001c:\u0002\u00115\\7\u000b\u001e:j]\u001e$\u0002\"!>\u0005t\u0012UH\u0011 \u0005\b\u0005K,\u0003\u0019AA{\u0011\u001d!90\na\u0001\u0003k\f1a]3q\u0011\u001d\u00119/\na\u0001\u0003k$B!!>\u0005~\"9Aq\u001f\u0014A\u0002\u0005UXCAA{\u0003\r\u0019X/\\\u000b\u0005\u000b\u000b)I\u0001\u0006\u0003\u0006\b\u0015-\u0001\u0003BA&\u000b\u0013!qa!%)\u0005\u0004\u0019I\fC\u0004\u0006\u000e!\u0002\u001d!b\u0004\u0002\u00079,X\u000e\u0005\u0004\u0002\u0010\u0016EQqA\u0005\u0005\u000b\'\t\u0019KA\u0004Ok6,\'/[2\u0002\u000fA\u0014x\u000eZ;diV!Q\u0011DC\u000f)\u0011)Y\"b\b\u0011\t\u0005-SQ\u0004\u0003\b\u0007#K#\u0019AB]\u0011\u001d)i!\u000ba\u0002\u000bC\u0001b!a$\u0006\u0012\u0015m\u0011aA7j]V!QqEC\u001b)\u0011\u00199$\"\u000b\t\u000f\u0015-\"\u0006q\u0001\u0006.\u0005\u00191-\u001c9\u0011\r\u0005=UqFC\u001a\u0013\u0011)\t$a)\u0003\u0011=\u0013H-\u001a:j]\u001e\u0004B!a\u0013\u00066\u001191\u0011\u0013\u0016C\u0002\re\u0016aA7bqV!Q1HC\")\u0011\u00199$\"\u0010\t\u000f\u0015-2\u0006q\u0001\u0006@A1\u0011qRC\u0018\u000b\u0003\u0002B!a\u0013\u0006D\u001191\u0011S\u0016C\u0002\re\u0016!B7bq\nKX\u0003BC%\u000b\'\"B!b\u0013\u0006VQ!1qGC\'\u0011\u001d)Y\u0003\fa\u0002\u000b\u001f\u0002b!a$\u00060\u0015E\u0003\u0003BA&\u000b\'\"qa!%-\u0005\u0004\t\t\u0006C\u0004\u0002n2\u0002\r!b\u0016\u0011\u000fu\fiha\u000e\u0006R\u0005)Q.\u001b8CsV!QQLC4)\u0011)y&\"\u001b\u0015\t\r]R\u0011\r\u0005\b\u000bWi\u00039AC2!\u0019\ty)b\f\u0006fA!\u00111JC4\t\u001d\u0019\t*\fb\u0001\u0003#Bq!!<.\u0001\u0004)Y\u0007E\u0004~\u0003{\u001a9$\"\u001a
   #10 = Utf8               geny/Generator$Action
   #11 = Class              #10           // geny/Generator$Action
   #12 = Utf8               Action
   #13 = Utf8               geny/Generator$Concat
   #14 = Class              #13           // geny/Generator$Concat
   #15 = Utf8               Concat
   #16 = Utf8               geny/Generator$Continue$
   #17 = Class              #16           // geny/Generator$Continue$
   #18 = Utf8               Continue$
   #19 = Utf8               geny/Generator$DropWhile
   #20 = Class              #19           // geny/Generator$DropWhile
   #21 = Utf8               DropWhile
   #22 = Utf8               geny/Generator$End$
   #23 = Class              #22           // geny/Generator$End$
   #24 = Utf8               End$
   #25 = Utf8               geny/Generator$Filtered
   #26 = Class              #25           // geny/Generator$Filtered
   #27 = Utf8               Filtered
   #28 = Utf8               geny/Generator$FlatMapped
   #29 = Class              #28           // geny/Generator$FlatMapped
   #30 = Utf8               FlatMapped
   #31 = Utf8               geny/Generator$Mapped
   #32 = Class              #31           // geny/Generator$Mapped
   #33 = Utf8               Mapped
   #34 = Utf8               geny/Generator$SelfClosing
   #35 = Class              #34           // geny/Generator$SelfClosing
   #36 = Utf8               SelfClosing
   #37 = Utf8               geny/Generator$Sliced
   #38 = Class              #37           // geny/Generator$Sliced
   #39 = Utf8               Sliced
   #40 = Utf8               geny/Generator$TakeWhile
   #41 = Class              #40           // geny/Generator$TakeWhile
   #42 = Utf8               TakeWhile
   #43 = Utf8               geny/Generator$ZipWithIndexed
   #44 = Class              #43           // geny/Generator$ZipWithIndexed
   #45 = Utf8               ZipWithIndexed
   #46 = Utf8               geny/Generator$Zipped
   #47 = Class              #46           // geny/Generator$Zipped
   #48 = Utf8               Zipped
   #49 = Utf8               java/lang/invoke/MethodHandles$Lookup
   #50 = Class              #49           // java/lang/invoke/MethodHandles$Lookup
   #51 = Utf8               java/lang/invoke/MethodHandles
   #52 = Class              #51           // java/lang/invoke/MethodHandles
   #53 = Utf8               Lookup
   #54 = Utf8               selfClosing
   #55 = Utf8               (Lscala/Function0;)Lgeny/Generator;
   #56 = Utf8               <T:Ljava/lang/Object;>(Lscala/Function0<Lscala/Tuple2<Lscala/collection/Iterator<TT;>;Lscala/Function0<Lscala/runtime/BoxedUnit;>;>;>;)Lgeny/Generator<TT;>;
   #57 = Utf8               makeIterator
   #58 = Utf8               geny/Generator$
   #59 = Class              #58           // geny/Generator$
   #60 = Utf8               MODULE$
   #61 = Utf8               Lgeny/Generator$;
   #62 = NameAndType        #60:#61       // MODULE$:Lgeny/Generator$;
   #63 = Fieldref           #59.#62       // geny/Generator$.MODULE$:Lgeny/Generator$;
   #64 = NameAndType        #54:#55       // selfClosing:(Lscala/Function0;)Lgeny/Generator;
   #65 = Methodref          #59.#64       // geny/Generator$.selfClosing:(Lscala/Function0;)Lgeny/Generator;
   #66 = Utf8               from
   #67 = Utf8               (Ljava/lang/Object;Lscala/Function1;)Lgeny/Generator;
   #68 = Utf8               <M:Ljava/lang/Object;T:Ljava/lang/Object;>(TM;Lscala/Function1<TM;Lscala/collection/IterableOnce<TT;>;>;)Lgeny/Generator<TT;>;
   #69 = Utf8               t
   #70 = Utf8               convert
   #71 = NameAndType        #66:#67       // from:(Ljava/lang/Object;Lscala/Function1;)Lgeny/Generator;
   #72 = Methodref          #59.#71       // geny/Generator$.from:(Ljava/lang/Object;Lscala/Function1;)Lgeny/Generator;
   #73 = Utf8               apply
   #74 = Utf8               (Lscala/collection/immutable/Seq;)Lgeny/Generator;
   #75 = Utf8               <T:Ljava/lang/Object;>(Lscala/collection/immutable/Seq<TT;>;)Lgeny/Generator<TT;>;
   #76 = Utf8               xs
   #77 = NameAndType        #73:#74       // apply:(Lscala/collection/immutable/Seq;)Lgeny/Generator;
   #78 = Methodref          #59.#77       // geny/Generator$.apply:(Lscala/collection/immutable/Seq;)Lgeny/Generator;
   #79 = Utf8               generate
   #80 = Utf8               (Lscala/Function1;)Lgeny/Generator$Action;
   #81 = Utf8               (Lscala/Function1<TA;Lgeny/Generator$Action;>;)Lgeny/Generator$Action;
   #82 = Utf8               handleItem
   #83 = Utf8               foreach$
   #84 = Utf8               (Lgeny/Generator;Lscala/Function1;)V
   #85 = Utf8               $this
   #86 = Utf8               f
   #87 = Utf8               foreach
   #88 = Utf8               (Lscala/Function1;)V
   #89 = NameAndType        #87:#88       // foreach:(Lscala/Function1;)V
   #90 = InterfaceMethodref #2.#89        // geny/Generator.foreach:(Lscala/Function1;)V
   #91 = Utf8               Lgeny/Generator;
   #92 = Utf8               Lscala/Function1;
   #93 = Utf8               (Lscala/Function1<TA;Lscala/runtime/BoxedUnit;>;)V
   #94 = Utf8               (Ljava/lang/Object;)Ljava/lang/Object;
   #95 = MethodType         #94           //  (Ljava/lang/Object;)Ljava/lang/Object;
   #96 = Utf8               $anonfun$foreach$1
   #97 = Utf8               (Lscala/Function1;Ljava/lang/Object;)Lgeny/Generator$Continue$;
   #98 = NameAndType        #96:#97       // $anonfun$foreach$1:(Lscala/Function1;Ljava/lang/Object;)Lgeny/Generator$Continue$;
   #99 = InterfaceMethodref #2.#98        // geny/Generator.$anonfun$foreach$1:(Lscala/Function1;Ljava/lang/Object;)Lgeny/Generator$Continue$;
  #100 = MethodHandle       6:#99         // REF_invokeStatic geny/Generator.$anonfun$foreach$1:(Lscala/Function1;Ljava/lang/Object;)Lgeny/Generator$Continue$;
  #101 = Utf8               (Ljava/lang/Object;)Lgeny/Generator$Continue$;
  #102 = MethodType         #101          //  (Ljava/lang/Object;)Lgeny/Generator$Continue$;
  #103 = Integer            5
  #104 = Integer            1
  #105 = Utf8               java/lang/invoke/LambdaMetafactory
  #106 = Class              #105          // java/lang/invoke/LambdaMetafactory
  #107 = Utf8               altMetafactory
  #108 = Utf8               (Ljava/lang/invoke/MethodHandles$Lookup;Ljava/lang/String;Ljava/lang/invoke/MethodType;[Ljava/lang/Object;)Ljava/lang/invoke/CallSite;
  #109 = NameAndType        #107:#108     // altMetafactory:(Ljava/lang/invoke/MethodHandles$Lookup;Ljava/lang/String;Ljava/lang/invoke/MethodType;[Ljava/lang/Object;)Ljava/lang/invoke/CallSite;
  #110 = Methodref          #106.#109     // java/lang/invoke/LambdaMetafactory.altMetafactory:(Ljava/lang/invoke/MethodHandles$Lookup;Ljava/lang/String;Ljava/lang/invoke/MethodType;[Ljava/lang/Object;)Ljava/lang/invoke/CallSite;
  #111 = MethodHandle       6:#110        // REF_invokeStatic java/lang/invoke/LambdaMetafactory.altMetafactory:(Ljava/lang/invoke/MethodHandles$Lookup;Ljava/lang/String;Ljava/lang/invoke/MethodType;[Ljava/lang/Object;)Ljava/lang/invoke/CallSite;
  #112 = Utf8               (Lscala/Function1;)Lscala/Function1;
  #113 = NameAndType        #73:#112      // apply:(Lscala/Function1;)Lscala/Function1;
  #114 = InvokeDynamic      #0:#113       // #0:apply:(Lscala/Function1;)Lscala/Function1;
  #115 = NameAndType        #79:#80       // generate:(Lscala/Function1;)Lgeny/Generator$Action;
  #116 = InterfaceMethodref #2.#115       // geny/Generator.generate:(Lscala/Function1;)Lgeny/Generator$Action;
  #117 = Utf8               this
  #118 = Utf8               find$
  #119 = Utf8               (Lgeny/Generator;Lscala/Function1;)Lscala/Option;
  #120 = Utf8               find
  #121 = Utf8               (Lscala/Function1;)Lscala/Option;
  #122 = NameAndType        #120:#121     // find:(Lscala/Function1;)Lscala/Option;
  #123 = InterfaceMethodref #2.#122       // geny/Generator.find:(Lscala/Function1;)Lscala/Option;
  #124 = Utf8               (Lscala/Function1<TA;Ljava/lang/Object;>;)Lscala/Option<TA;>;
  #125 = Utf8               scala/None$
  #126 = Class              #125          // scala/None$
  #127 = Utf8               Lscala/None$;
  #128 = NameAndType        #60:#127      // MODULE$:Lscala/None$;
  #129 = Fieldref           #126.#128     // scala/None$.MODULE$:Lscala/None$;
  #130 = Utf8               scala/runtime/ObjectRef
  #131 = Class              #130          // scala/runtime/ObjectRef
  #132 = Utf8               create
  #133 = Utf8               (Ljava/lang/Object;)Lscala/runtime/ObjectRef;
  #134 = NameAndType        #132:#133     // create:(Ljava/lang/Object;)Lscala/runtime/ObjectRef;
  #135 = Methodref          #131.#134     // scala/runtime/ObjectRef.create:(Ljava/lang/Object;)Lscala/runtime/ObjectRef;
  #136 = Utf8               $anonfun$find$1
  #137 = Utf8               (Lscala/Function1;Lscala/runtime/ObjectRef;Ljava/lang/Object;)Lgeny/Generator$Action;
  #138 = NameAndType        #136:#137     // $anonfun$find$1:(Lscala/Function1;Lscala/runtime/ObjectRef;Ljava/lang/Object;)Lgeny/Generator$Action;
  #139 = InterfaceMethodref #2.#138       // geny/Generator.$anonfun$find$1:(Lscala/Function1;Lscala/runtime/ObjectRef;Ljava/lang/Object;)Lgeny/Generator$Action;
  #140 = MethodHandle       6:#139        // REF_invokeStatic geny/Generator.$anonfun$find$1:(Lscala/Function1;Lscala/runtime/ObjectRef;Ljava/lang/Object;)Lgeny/Generator$Action;
  #141 = Utf8               (Ljava/lang/Object;)Lgeny/Generator$Action;
  #142 = MethodType         #141          //  (Ljava/lang/Object;)Lgeny/Generator$Action;
  #143 = Utf8               (Lscala/Function1;Lscala/runtime/ObjectRef;)Lscala/Function1;
  #144 = NameAndType        #73:#143      // apply:(Lscala/Function1;Lscala/runtime/ObjectRef;)Lscala/Function1;
  #145 = InvokeDynamic      #1:#144       // #1:apply:(Lscala/Function1;Lscala/runtime/ObjectRef;)Lscala/Function1;
  #146 = Utf8               elem
  #147 = Utf8               Ljava/lang/Object;
  #148 = NameAndType        #146:#147     // elem:Ljava/lang/Object;
  #149 = Fieldref           #131.#148     // scala/runtime/ObjectRef.elem:Ljava/lang/Object;
  #150 = Utf8               scala/Option
  #151 = Class              #150          // scala/Option
  #152 = Utf8               result
  #153 = Utf8               Lscala/runtime/ObjectRef;
  #154 = Utf8               exists$
  #155 = Utf8               (Lgeny/Generator;Lscala/Function1;)Z
  #156 = Utf8               exists
  #157 = Utf8               (Lscala/Function1;)Z
  #158 = NameAndType        #156:#157     // exists:(Lscala/Function1;)Z
  #159 = InterfaceMethodref #2.#158       // geny/Generator.exists:(Lscala/Function1;)Z
  #160 = Utf8               (Lscala/Function1<TA;Ljava/lang/Object;>;)Z
  #161 = Utf8               $anonfun$exists$1$adapted
  #162 = Utf8               (Lscala/Function1;Ljava/lang/Object;)Ljava/lang/Object;
  #163 = NameAndType        #161:#162     // $anonfun$exists$1$adapted:(Lscala/Function1;Ljava/lang/Object;)Ljava/lang/Object;
  #164 = InterfaceMethodref #2.#163       // geny/Generator.$anonfun$exists$1$adapted:(Lscala/Function1;Ljava/lang/Object;)Ljava/lang/Object;
  #165 = MethodHandle       6:#164        // REF_invokeStatic geny/Generator.$anonfun$exists$1$adapted:(Lscala/Function1;Ljava/lang/Object;)Ljava/lang/Object;
  #166 = InvokeDynamic      #2:#113       // #2:apply:(Lscala/Function1;)Lscala/Function1;
  #167 = Utf8               isDefined
  #168 = Utf8               ()Z
  #169 = NameAndType        #167:#168     // isDefined:()Z
  #170 = Methodref          #151.#169     // scala/Option.isDefined:()Z
  #171 = Utf8               contains$
  #172 = Utf8               (Lgeny/Generator;Ljava/lang/Object;)Z
  #173 = Utf8               a
  #174 = Utf8               contains
  #175 = Utf8               (Ljava/lang/Object;)Z
  #176 = NameAndType        #174:#175     // contains:(Ljava/lang/Object;)Z
  #177 = InterfaceMethodref #2.#176       // geny/Generator.contains:(Ljava/lang/Object;)Z
  #178 = Utf8               $anonfun$contains$1$adapted
  #179 = Utf8               (Ljava/lang/Object;Ljava/lang/Object;)Ljava/lang/Object;
  #180 = NameAndType        #178:#179     // $anonfun$contains$1$adapted:(Ljava/lang/Object;Ljava/lang/Object;)Ljava/lang/Object;
  #181 = InterfaceMethodref #2.#180       // geny/Generator.$anonfun$contains$1$adapted:(Ljava/lang/Object;Ljava/lang/Object;)Ljava/lang/Object;
  #182 = MethodHandle       6:#181        // REF_invokeStatic geny/Generator.$anonfun$contains$1$adapted:(Ljava/lang/Object;Ljava/lang/Object;)Ljava/lang/Object;
  #183 = Utf8               (Ljava/lang/Object;)Lscala/Function1;
  #184 = NameAndType        #73:#183      // apply:(Ljava/lang/Object;)Lscala/Function1;
  #185 = InvokeDynamic      #3:#184       // #3:apply:(Ljava/lang/Object;)Lscala/Function1;
  #186 = Utf8               forall$
  #187 = Utf8               forall
  #188 = NameAndType        #187:#157     // forall:(Lscala/Function1;)Z
  #189 = InterfaceMethodref #2.#188       // geny/Generator.forall:(Lscala/Function1;)Z
  #190 = Utf8               $anonfun$forall$1$adapted
  #191 = NameAndType        #190:#162     // $anonfun$forall$1$adapted:(Lscala/Function1;Ljava/lang/Object;)Ljava/lang/Object;
  #192 = InterfaceMethodref #2.#191       // geny/Generator.$anonfun$forall$1$adapted:(Lscala/Function1;Ljava/lang/Object;)Ljava/lang/Object;
  #193 = MethodHandle       6:#192        // REF_invokeStatic geny/Generator.$anonfun$forall$1$adapted:(Lscala/Function1;Ljava/lang/Object;)Ljava/lang/Object;
  #194 = InvokeDynamic      #4:#113       // #4:apply:(Lscala/Function1;)Lscala/Function1;
  #195 = Utf8               count$
  #196 = Utf8               (Lgeny/Generator;Lscala/Function1;)I
  #197 = Utf8               count
  #198 = Utf8               (Lscala/Function1;)I
  #199 = NameAndType        #197:#198     // count:(Lscala/Function1;)I
  #200 = InterfaceMethodref #2.#199       // geny/Generator.count:(Lscala/Function1;)I
  #201 = Utf8               (Lscala/Function1<TA;Ljava/lang/Object;>;)I
  #202 = Utf8               scala/runtime/IntRef
  #203 = Class              #202          // scala/runtime/IntRef
  #204 = Utf8               (I)Lscala/runtime/IntRef;
  #205 = NameAndType        #132:#204     // create:(I)Lscala/runtime/IntRef;
  #206 = Methodref          #203.#205     // scala/runtime/IntRef.create:(I)Lscala/runtime/IntRef;
  #207 = Utf8               $anonfun$count$1
  #208 = Utf8               (Lscala/Function1;Lscala/runtime/IntRef;Ljava/lang/Object;)Lgeny/Generator$Continue$;
  #209 = NameAndType        #207:#208     // $anonfun$count$1:(Lscala/Function1;Lscala/runtime/IntRef;Ljava/lang/Object;)Lgeny/Generator$Continue$;
  #210 = InterfaceMethodref #2.#209       // geny/Generator.$anonfun$count$1:(Lscala/Function1;Lscala/runtime/IntRef;Ljava/lang/Object;)Lgeny/Generator$Continue$;
  #211 = MethodHandle       6:#210        // REF_invokeStatic geny/Generator.$anonfun$count$1:(Lscala/Function1;Lscala/runtime/IntRef;Ljava/lang/Object;)Lgeny/Generator$Continue$;
  #212 = Utf8               (Lscala/Function1;Lscala/runtime/IntRef;)Lscala/Function1;
  #213 = NameAndType        #73:#212      // apply:(Lscala/Function1;Lscala/runtime/IntRef;)Lscala/Function1;
  #214 = InvokeDynamic      #5:#213       // #5:apply:(Lscala/Function1;Lscala/runtime/IntRef;)Lscala/Function1;
  #215 = Utf8               I
  #216 = NameAndType        #146:#215     // elem:I
  #217 = Fieldref           #203.#216     // scala/runtime/IntRef.elem:I
  #218 = Utf8               Lscala/runtime/IntRef;
  #219 = Utf8               count$default$1$
  #220 = Utf8               (Lgeny/Generator;)Lscala/Function1;
  #221 = Utf8               count$default$1
  #222 = Utf8               ()Lscala/Function1;
  #223 = NameAndType        #221:#222     // count$default$1:()Lscala/Function1;
  #224 = InterfaceMethodref #2.#223       // geny/Generator.count$default$1:()Lscala/Function1;
  #225 = Utf8               ()Lscala/Function1<TA;Ljava/lang/Object;>;
  #226 = Utf8               $anonfun$count$default$1$1$adapted
  #227 = NameAndType        #226:#94      // $anonfun$count$default$1$1$adapted:(Ljava/lang/Object;)Ljava/lang/Object;
  #228 = InterfaceMethodref #2.#227       // geny/Generator.$anonfun$count$default$1$1$adapted:(Ljava/lang/Object;)Ljava/lang/Object;
  #229 = MethodHandle       6:#228        // REF_invokeStatic geny/Generator.$anonfun$count$default$1$1$adapted:(Ljava/lang/Object;)Ljava/lang/Object;
  #230 = NameAndType        #73:#222      // apply:()Lscala/Function1;
  #231 = InvokeDynamic      #6:#230       // #6:apply:()Lscala/Function1;
  #232 = Utf8               fold$
  #233 = Utf8               (Lgeny/Generator;Ljava/lang/Object;Lscala/Function2;)Ljava/lang/Object;
  #234 = Utf8               start
  #235 = Utf8               fold
  #236 = Utf8               (Ljava/lang/Object;Lscala/Function2;)Ljava/lang/Object;
  #237 = NameAndType        #235:#236     // fold:(Ljava/lang/Object;Lscala/Function2;)Ljava/lang/Object;
  #238 = InterfaceMethodref #2.#237       // geny/Generator.fold:(Ljava/lang/Object;Lscala/Function2;)Ljava/lang/Object;
  #239 = Utf8               Lscala/Function2;
  #240 = Utf8               <B:Ljava/lang/Object;>(TB;Lscala/Function2<TB;TA;TB;>;)TB;
  #241 = Utf8               foldLeft
  #242 = NameAndType        #241:#236     // foldLeft:(Ljava/lang/Object;Lscala/Function2;)Ljava/lang/Object;
  #243 = InterfaceMethodref #2.#242       // geny/Generator.foldLeft:(Ljava/lang/Object;Lscala/Function2;)Ljava/lang/Object;
  #244 = Utf8               foldLeft$
  #245 = Utf8               $anonfun$foldLeft$1
  #246 = Utf8               (Lscala/runtime/ObjectRef;Lscala/Function2;Ljava/lang/Object;)Lgeny/Generator$Continue$;
  #247 = NameAndType        #245:#246     // $anonfun$foldLeft$1:(Lscala/runtime/ObjectRef;Lscala/Function2;Ljava/lang/Object;)Lgeny/Generator$Continue$;
  #248 = InterfaceMethodref #2.#247       // geny/Generator.$anonfun$foldLeft$1:(Lscala/runtime/ObjectRef;Lscala/Function2;Ljava/lang/Object;)Lgeny/Generator$Continue$;
  #249 = MethodHandle       6:#248        // REF_invokeStatic geny/Generator.$anonfun$foldLeft$1:(Lscala/runtime/ObjectRef;Lscala/Function2;Ljava/lang/Object;)Lgeny/Generator$Continue$;
  #250 = Utf8               (Lscala/runtime/ObjectRef;Lscala/Function2;)Lscala/Function1;
  #251 = NameAndType        #73:#250      // apply:(Lscala/runtime/ObjectRef;Lscala/Function2;)Lscala/Function1;
  #252 = InvokeDynamic      #7:#251       // #7:apply:(Lscala/runtime/ObjectRef;Lscala/Function2;)Lscala/Function1;
  #253 = Utf8               reduce$
  #254 = Utf8               (Lgeny/Generator;Lscala/Function2;)Ljava/lang/Object;
  #255 = Utf8               reduce
  #256 = Utf8               (Lscala/Function2;)Ljava/lang/Object;
  #257 = NameAndType        #255:#256     // reduce:(Lscala/Function2;)Ljava/lang/Object;
  #258 = InterfaceMethodref #2.#257       // geny/Generator.reduce:(Lscala/Function2;)Ljava/lang/Object;
  #259 = Utf8               <B:Ljava/lang/Object;>(Lscala/Function2<TB;TA;TB;>;)TB;
  #260 = Utf8               reduceLeft
  #261 = NameAndType        #260:#256     // reduceLeft:(Lscala/Function2;)Ljava/lang/Object;
  #262 = InterfaceMethodref #2.#261       // geny/Generator.reduceLeft:(Lscala/Function2;)Ljava/lang/Object;
  #263 = Utf8               reduceLeft$
  #264 = Utf8               $anonfun$reduceLeft$1
  #265 = NameAndType        #264:#246     // $anonfun$reduceLeft$1:(Lscala/runtime/ObjectRef;Lscala/Function2;Ljava/lang/Object;)Lgeny/Generator$Continue$;
  #266 = InterfaceMethodref #2.#265       // geny/Generator.$anonfun$reduceLeft$1:(Lscala/runtime/ObjectRef;Lscala/Function2;Ljava/lang/Object;)Lgeny/Generator$Continue$;
  #267 = MethodHandle       6:#266        // REF_invokeStatic geny/Generator.$anonfun$reduceLeft$1:(Lscala/runtime/ObjectRef;Lscala/Function2;Ljava/lang/Object;)Lgeny/Generator$Continue$;
  #268 = InvokeDynamic      #8:#251       // #8:apply:(Lscala/runtime/ObjectRef;Lscala/Function2;)Lscala/Function1;
  #269 = Utf8               ()Ljava/lang/Object;
  #270 = MethodType         #269          //  ()Ljava/lang/Object;
  #271 = Utf8               $anonfun$reduceLeft$2
  #272 = Utf8               ()Lscala/runtime/Nothing$;
  #273 = NameAndType        #271:#272     // $anonfun$reduceLeft$2:()Lscala/runtime/Nothing$;
  #274 = InterfaceMethodref #2.#273       // geny/Generator.$anonfun$reduceLeft$2:()Lscala/runtime/Nothing$;
  #275 = MethodHandle       6:#274        // REF_invokeStatic geny/Generator.$anonfun$reduceLeft$2:()Lscala/runtime/Nothing$;
  #276 = MethodType         #272          //  ()Lscala/runtime/Nothing$;
  #277 = Utf8               ()Lscala/Function0;
  #278 = NameAndType        #73:#277      // apply:()Lscala/Function0;
  #279 = InvokeDynamic      #9:#278       // #9:apply:()Lscala/Function0;
  #280 = Utf8               getOrElse
  #281 = Utf8               (Lscala/Function0;)Ljava/lang/Object;
  #282 = NameAndType        #280:#281     // getOrElse:(Lscala/Function0;)Ljava/lang/Object;
  #283 = Methodref          #151.#282     // scala/Option.getOrElse:(Lscala/Function0;)Ljava/lang/Object;
  #284 = Utf8               filter$
  #285 = Utf8               (Lgeny/Generator;Lscala/Function1;)Lgeny/Generator;
  #286 = Utf8               pred
  #287 = Utf8               filter
  #288 = Utf8               (Lscala/Function1;)Lgeny/Generator;
  #289 = NameAndType        #287:#288     // filter:(Lscala/Function1;)Lgeny/Generator;
  #290 = InterfaceMethodref #2.#289       // geny/Generator.filter:(Lscala/Function1;)Lgeny/Generator;
  #291 = Utf8               (Lscala/Function1<TA;Ljava/lang/Object;>;)Lgeny/Generator<TA;>;
  #292 = Utf8               <init>
  #293 = NameAndType        #292:#84      // "<init>":(Lgeny/Generator;Lscala/Function1;)V
  #294 = Methodref          #26.#293      // geny/Generator$Filtered."<init>":(Lgeny/Generator;Lscala/Function1;)V
  #295 = Utf8               withFilter$
  #296 = Utf8               withFilter
  #297 = NameAndType        #296:#288     // withFilter:(Lscala/Function1;)Lgeny/Generator;
  #298 = InterfaceMethodref #2.#297       // geny/Generator.withFilter:(Lscala/Function1;)Lgeny/Generator;
  #299 = Utf8               map$
  #300 = Utf8               func
  #301 = Utf8               map
  #302 = NameAndType        #301:#288     // map:(Lscala/Function1;)Lgeny/Generator;
  #303 = InterfaceMethodref #2.#302       // geny/Generator.map:(Lscala/Function1;)Lgeny/Generator;
  #304 = Utf8               <B:Ljava/lang/Object;>(Lscala/Function1<TA;TB;>;)Lgeny/Generator<TB;>;
  #305 = Methodref          #32.#293      // geny/Generator$Mapped."<init>":(Lgeny/Generator;Lscala/Function1;)V
  #306 = Utf8               flatMap$
  #307 = Utf8               flatMap
  #308 = NameAndType        #307:#288     // flatMap:(Lscala/Function1;)Lgeny/Generator;
  #309 = InterfaceMethodref #2.#308       // geny/Generator.flatMap:(Lscala/Function1;)Lgeny/Generator;
  #310 = Utf8               <B:Ljava/lang/Object;>(Lscala/Function1<TA;Lgeny/Generator<TB;>;>;)Lgeny/Generator<TB;>;
  #311 = Methodref          #29.#293      // geny/Generator$FlatMapped."<init>":(Lgeny/Generator;Lscala/Function1;)V
  #312 = Utf8               collect$
  #313 = Utf8               (Lgeny/Generator;Lscala/PartialFunction;)Lgeny/Generator;
  #314 = Utf8               collect
  #315 = Utf8               (Lscala/PartialFunction;)Lgeny/Generator;
  #316 = NameAndType        #314:#315     // collect:(Lscala/PartialFunction;)Lgeny/Generator;
  #317 = InterfaceMethodref #2.#316       // geny/Generator.collect:(Lscala/PartialFunction;)Lgeny/Generator;
  #318 = Utf8               Lscala/PartialFunction;
  #319 = Utf8               <B:Ljava/lang/Object;>(Lscala/PartialFunction<TA;TB;>;)Lgeny/Generator<TB;>;
  #320 = Utf8               $anonfun$collect$1$adapted
  #321 = Utf8               (Lscala/PartialFunction;Ljava/lang/Object;)Ljava/lang/Object;
  #322 = NameAndType        #320:#321     // $anonfun$collect$1$adapted:(Lscala/PartialFunction;Ljava/lang/Object;)Ljava/lang/Object;
  #323 = InterfaceMethodref #2.#322       // geny/Generator.$anonfun$collect$1$adapted:(Lscala/PartialFunction;Ljava/lang/Object;)Ljava/lang/Object;
  #324 = MethodHandle       6:#323        // REF_invokeStatic geny/Generator.$anonfun$collect$1$adapted:(Lscala/PartialFunction;Ljava/lang/Object;)Ljava/lang/Object;
  #325 = Utf8               (Lscala/PartialFunction;)Lscala/Function1;
  #326 = NameAndType        #73:#325      // apply:(Lscala/PartialFunction;)Lscala/Function1;
  #327 = InvokeDynamic      #10:#326      // #10:apply:(Lscala/PartialFunction;)Lscala/Function1;
  #328 = Utf8               collectFirst$
  #329 = Utf8               (Lgeny/Generator;Lscala/PartialFunction;)Lscala/Option;
  #330 = Utf8               collectFirst
  #331 = Utf8               (Lscala/PartialFunction;)Lscala/Option;
  #332 = NameAndType        #330:#331     // collectFirst:(Lscala/PartialFunction;)Lscala/Option;
  #333 = InterfaceMethodref #2.#332       // geny/Generator.collectFirst:(Lscala/PartialFunction;)Lscala/Option;
  #334 = Utf8               <B:Ljava/lang/Object;>(Lscala/PartialFunction<TA;TB;>;)Lscala/Option<TB;>;
  #335 = Utf8               $anonfun$collectFirst$1$adapted
  #336 = NameAndType        #335:#321     // $anonfun$collectFirst$1$adapted:(Lscala/PartialFunction;Ljava/lang/Object;)Ljava/lang/Object;
  #337 = InterfaceMethodref #2.#336       // geny/Generator.$anonfun$collectFirst$1$adapted:(Lscala/PartialFunction;Ljava/lang/Object;)Ljava/lang/Object;
  #338 = MethodHandle       6:#337        // REF_invokeStatic geny/Generator.$anonfun$collectFirst$1$adapted:(Lscala/PartialFunction;Ljava/lang/Object;)Ljava/lang/Object;
  #339 = InvokeDynamic      #11:#326      // #11:apply:(Lscala/PartialFunction;)Lscala/Function1;
  #340 = Utf8               headOption
  #341 = Utf8               ()Lscala/Option;
  #342 = NameAndType        #340:#341     // headOption:()Lscala/Option;
  #343 = InterfaceMethodref #2.#342       // geny/Generator.headOption:()Lscala/Option;
  #344 = Utf8               flatten$
  #345 = Utf8               flatten
  #346 = NameAndType        #345:#288     // flatten:(Lscala/Function1;)Lgeny/Generator;
  #347 = InterfaceMethodref #2.#346       // geny/Generator.flatten:(Lscala/Function1;)Lgeny/Generator;
  #348 = Utf8               <V$:Ljava/lang/Object;>(Lscala/Function1<TA;Lgeny/Generator<TV$;>;>;)Lgeny/Generator<TV$;>;
  #349 = Utf8               $anonfun$flatten$1
  #350 = Utf8               (Lscala/Function1;Ljava/lang/Object;)Lgeny/Generator;
  #351 = NameAndType        #349:#350     // $anonfun$flatten$1:(Lscala/Function1;Ljava/lang/Object;)Lgeny/Generator;
  #352 = InterfaceMethodref #2.#351       // geny/Generator.$anonfun$flatten$1:(Lscala/Function1;Ljava/lang/Object;)Lgeny/Generator;
  #353 = MethodHandle       6:#352        // REF_invokeStatic geny/Generator.$anonfun$flatten$1:(Lscala/Function1;Ljava/lang/Object;)Lgeny/Generator;
  #354 = Utf8               (Ljava/lang/Object;)Lgeny/Generator;
  #355 = MethodType         #354          //  (Ljava/lang/Object;)Lgeny/Generator;
  #356 = InvokeDynamic      #12:#113      // #12:apply:(Lscala/Function1;)Lscala/Function1;
  #357 = Utf8               slice$
  #358 = Utf8               (Lgeny/Generator;II)Lgeny/Generator;
  #359 = Utf8               end
  #360 = Utf8               slice
  #361 = Utf8               (II)Lgeny/Generator;
  #362 = NameAndType        #360:#361     // slice:(II)Lgeny/Generator;
  #363 = InterfaceMethodref #2.#362       // geny/Generator.slice:(II)Lgeny/Generator;
  #364 = Utf8               (II)Lgeny/Generator<TA;>;
  #365 = Utf8               (Lgeny/Generator;II)V
  #366 = NameAndType        #292:#365     // "<init>":(Lgeny/Generator;II)V
  #367 = Methodref          #38.#366      // geny/Generator$Sliced."<init>":(Lgeny/Generator;II)V
  #368 = Utf8               take$
  #369 = Utf8               (Lgeny/Generator;I)Lgeny/Generator;
  #370 = Utf8               n
  #371 = Utf8               take
  #372 = Utf8               (I)Lgeny/Generator;
  #373 = NameAndType        #371:#372     // take:(I)Lgeny/Generator;
  #374 = InterfaceMethodref #2.#373       // geny/Generator.take:(I)Lgeny/Generator;
  #375 = Utf8               (I)Lgeny/Generator<TA;>;
  #376 = Utf8               drop$
  #377 = Utf8               drop
  #378 = NameAndType        #377:#372     // drop:(I)Lgeny/Generator;
  #379 = InterfaceMethodref #2.#378       // geny/Generator.drop:(I)Lgeny/Generator;
  #380 = Integer            2147483647
  #381 = Utf8               takeWhile$
  #382 = Utf8               takeWhile
  #383 = NameAndType        #382:#288     // takeWhile:(Lscala/Function1;)Lgeny/Generator;
  #384 = InterfaceMethodref #2.#383       // geny/Generator.takeWhile:(Lscala/Function1;)Lgeny/Generator;
  #385 = Methodref          #41.#293      // geny/Generator$TakeWhile."<init>":(Lgeny/Generator;Lscala/Function1;)V
  #386 = Utf8               dropWhile$
  #387 = Utf8               dropWhile
  #388 = NameAndType        #387:#288     // dropWhile:(Lscala/Function1;)Lgeny/Generator;
  #389 = InterfaceMethodref #2.#388       // geny/Generator.dropWhile:(Lscala/Function1;)Lgeny/Generator;
  #390 = Methodref          #20.#293      // geny/Generator$DropWhile."<init>":(Lgeny/Generator;Lscala/Function1;)V
  #391 = Utf8               zipWithIndex$
  #392 = Utf8               (Lgeny/Generator;)Lgeny/Generator;
  #393 = Utf8               zipWithIndex
  #394 = Utf8               ()Lgeny/Generator;
  #395 = NameAndType        #393:#394     // zipWithIndex:()Lgeny/Generator;
  #396 = InterfaceMethodref #2.#395       // geny/Generator.zipWithIndex:()Lgeny/Generator;
  #397 = Utf8               ()Lgeny/Generator<Lscala/Tuple2<TA;Ljava/lang/Object;>;>;
  #398 = Utf8               (Lgeny/Generator;)V
  #399 = NameAndType        #292:#398     // "<init>":(Lgeny/Generator;)V
  #400 = Methodref          #44.#399      // geny/Generator$ZipWithIndexed."<init>":(Lgeny/Generator;)V
  #401 = Utf8               zip$
  #402 = Utf8               (Lgeny/Generator;Lscala/collection/Iterable;)Lgeny/Generator;
  #403 = Utf8               other
  #404 = Utf8               zip
  #405 = Utf8               (Lscala/collection/Iterable;)Lgeny/Generator;
  #406 = NameAndType        #404:#405     // zip:(Lscala/collection/Iterable;)Lgeny/Generator;
  #407 = InterfaceMethodref #2.#406       // geny/Generator.zip:(Lscala/collection/Iterable;)Lgeny/Generator;
  #408 = Utf8               Lscala/collection/Iterable;
  #409 = Utf8               <B:Ljava/lang/Object;>(Lscala/collection/Iterable<TB;>;)Lgeny/Generator<Lscala/Tuple2<TA;TB;>;>;
  #410 = Utf8               (Lgeny/Generator;Lscala/collection/Iterable;)V
  #411 = NameAndType        #292:#410     // "<init>":(Lgeny/Generator;Lscala/collection/Iterable;)V
  #412 = Methodref          #47.#411      // geny/Generator$Zipped."<init>":(Lgeny/Generator;Lscala/collection/Iterable;)V
  #413 = Utf8               $plus$plus$
  #414 = Utf8               (Lgeny/Generator;Lgeny/Generator;)Lgeny/Generator;
  #415 = Utf8               $plus$plus
  #416 = NameAndType        #415:#392     // $plus$plus:(Lgeny/Generator;)Lgeny/Generator;
  #417 = InterfaceMethodref #2.#416       // geny/Generator.$plus$plus:(Lgeny/Generator;)Lgeny/Generator;
  #418 = Utf8               <B:Ljava/lang/Object;>(Lgeny/Generator<TB;>;)Lgeny/Generator<TB;>;
  #419 = Utf8               (Lgeny/Generator;Lgeny/Generator;)V
  #420 = NameAndType        #292:#419     // "<init>":(Lgeny/Generator;Lgeny/Generator;)V
  #421 = Methodref          #14.#420      // geny/Generator$Concat."<init>":(Lgeny/Generator;Lgeny/Generator;)V
  #422 = Utf8               head$
  #423 = Utf8               (Lgeny/Generator;)Ljava/lang/Object;
  #424 = Utf8               head
  #425 = NameAndType        #424:#269     // head:()Ljava/lang/Object;
  #426 = InterfaceMethodref #2.#425       // geny/Generator.head:()Ljava/lang/Object;
  #427 = Utf8               ()TA;
  #428 = Utf8               toSeq
  #429 = Utf8               ()Lscala/collection/immutable/Seq;
  #430 = NameAndType        #428:#429     // toSeq:()Lscala/collection/immutable/Seq;
  #431 = InterfaceMethodref #2.#430       // geny/Generator.toSeq:()Lscala/collection/immutable/Seq;
  #432 = Utf8               scala/collection/immutable/Seq
  #433 = Class              #432          // scala/collection/immutable/Seq
  #434 = InterfaceMethodref #433.#425     // scala/collection/immutable/Seq.head:()Ljava/lang/Object;
  #435 = Utf8               headOption$
  #436 = Utf8               (Lgeny/Generator;)Lscala/Option;
  #437 = Utf8               ()Lscala/Option<TA;>;
  #438 = InterfaceMethodref #433.#342     // scala/collection/immutable/Seq.headOption:()Lscala/Option;
  #439 = Utf8               toBuffer$
  #440 = Utf8               (Lgeny/Generator;)Lscala/collection/mutable/Buffer;
  #441 = Utf8               toBuffer
  #442 = Utf8               ()Lscala/collection/mutable/Buffer;
  #443 = NameAndType        #441:#442     // toBuffer:()Lscala/collection/mutable/Buffer;
  #444 = InterfaceMethodref #2.#443       // geny/Generator.toBuffer:()Lscala/collection/mutable/Buffer;
  #445 = Utf8               <B:Ljava/lang/Object;>()Lscala/collection/mutable/Buffer<TB;>;
  #446 = Utf8               scala/collection/mutable/Buffer$
  #447 = Class              #446          // scala/collection/mutable/Buffer$
  #448 = Utf8               Lscala/collection/mutable/Buffer$;
  #449 = NameAndType        #60:#448      // MODULE$:Lscala/collection/mutable/Buffer$;
  #450 = Fieldref           #447.#449     // scala/collection/mutable/Buffer$.MODULE$:Lscala/collection/mutable/Buffer$;
  #451 = Utf8               empty
  #452 = Utf8               ()Lscala/collection/SeqOps;
  #453 = NameAndType        #451:#452     // empty:()Lscala/collection/SeqOps;
  #454 = Methodref          #447.#453     // scala/collection/mutable/Buffer$.empty:()Lscala/collection/SeqOps;
  #455 = Utf8               scala/collection/mutable/Buffer
  #456 = Class              #455          // scala/collection/mutable/Buffer
  #457 = Utf8               $anonfun$toBuffer$1$adapted
  #458 = Utf8               (Lscala/collection/mutable/Buffer;Ljava/lang/Object;)Ljava/lang/Object;
  #459 = NameAndType        #457:#458     // $anonfun$toBuffer$1$adapted:(Lscala/collection/mutable/Buffer;Ljava/lang/Object;)Ljava/lang/Object;
  #460 = InterfaceMethodref #2.#459       // geny/Generator.$anonfun$toBuffer$1$adapted:(Lscala/collection/mutable/Buffer;Ljava/lang/Object;)Ljava/lang/Object;
  #461 = MethodHandle       6:#460        // REF_invokeStatic geny/Generator.$anonfun$toBuffer$1$adapted:(Lscala/collection/mutable/Buffer;Ljava/lang/Object;)Ljava/lang/Object;
  #462 = Utf8               (Lscala/collection/mutable/Buffer;)Lscala/Function1;
  #463 = NameAndType        #73:#462      // apply:(Lscala/collection/mutable/Buffer;)Lscala/Function1;
  #464 = InvokeDynamic      #13:#463      // #13:apply:(Lscala/collection/mutable/Buffer;)Lscala/Function1;
  #465 = Utf8               arr
  #466 = Utf8               Lscala/collection/mutable/Buffer;
  #467 = Utf8               toArray$
  #468 = Utf8               (Lgeny/Generator;Lscala/reflect/ClassTag;)Ljava/lang/Object;
  #469 = Utf8               evidence$1
  #470 = Utf8               toArray
  #471 = Utf8               (Lscala/reflect/ClassTag;)Ljava/lang/Object;
  #472 = NameAndType        #470:#471     // toArray:(Lscala/reflect/ClassTag;)Ljava/lang/Object;
  #473 = InterfaceMethodref #2.#472       // geny/Generator.toArray:(Lscala/reflect/ClassTag;)Ljava/lang/Object;
  #474 = Utf8               Lscala/reflect/ClassTag;
  #475 = Utf8               <B:Ljava/lang/Object;>(Lscala/reflect/ClassTag<TB;>;)Ljava/lang/Object;
  #476 = InterfaceMethodref #456.#472     // scala/collection/mutable/Buffer.toArray:(Lscala/reflect/ClassTag;)Ljava/lang/Object;
  #477 = Utf8               toSeq$
  #478 = Utf8               (Lgeny/Generator;)Lscala/collection/immutable/Seq;
  #479 = Utf8               ()Lscala/collection/immutable/Seq<TA;>;
  #480 = Utf8               toVector
  #481 = Utf8               ()Lscala/collection/immutable/Vector;
  #482 = NameAndType        #480:#481     // toVector:()Lscala/collection/immutable/Vector;
  #483 = InterfaceMethodref #2.#482       // geny/Generator.toVector:()Lscala/collection/immutable/Vector;
  #484 = Utf8               toList$
  #485 = Utf8               (Lgeny/Generator;)Lscala/collection/immutable/List;
  #486 = Utf8               toList
  #487 = Utf8               ()Lscala/collection/immutable/List;
  #488 = NameAndType        #486:#487     // toList:()Lscala/collection/immutable/List;
  #489 = InterfaceMethodref #2.#488       // geny/Generator.toList:()Lscala/collection/immutable/List;
  #490 = Utf8               ()Lscala/collection/immutable/List<TA;>;
  #491 = InterfaceMethodref #456.#488     // scala/collection/mutable/Buffer.toList:()Lscala/collection/immutable/List;
  #492 = Utf8               toSet$
  #493 = Utf8               (Lgeny/Generator;)Lscala/collection/immutable/Set;
  #494 = Utf8               toSet
  #495 = Utf8               ()Lscala/collection/immutable/Set;
  #496 = NameAndType        #494:#495     // toSet:()Lscala/collection/immutable/Set;
  #497 = InterfaceMethodref #2.#496       // geny/Generator.toSet:()Lscala/collection/immutable/Set;
  #498 = Utf8               <B:Ljava/lang/Object;>()Lscala/collection/immutable/Set<TB;>;
  #499 = InterfaceMethodref #456.#496     // scala/collection/mutable/Buffer.toSet:()Lscala/collection/immutable/Set;
  #500 = Utf8               toVector$
  #501 = Utf8               (Lgeny/Generator;)Lscala/collection/immutable/Vector;
  #502 = Utf8               ()Lscala/collection/immutable/Vector<TA;>;
  #503 = InterfaceMethodref #456.#482     // scala/collection/mutable/Buffer.toVector:()Lscala/collection/immutable/Vector;
  #504 = Utf8               mkString$
  #505 = Utf8               (Lgeny/Generator;Ljava/lang/String;Ljava/lang/String;Ljava/lang/String;)Ljava/lang/String;
  #506 = Utf8               sep
  #507 = Utf8               mkString
  #508 = Utf8               (Ljava/lang/String;Ljava/lang/String;Ljava/lang/String;)Ljava/lang/String;
  #509 = NameAndType        #507:#508     // mkString:(Ljava/lang/String;Ljava/lang/String;Ljava/lang/String;)Ljava/lang/String;
  #510 = InterfaceMethodref #2.#509       // geny/Generator.mkString:(Ljava/lang/String;Ljava/lang/String;Ljava/lang/String;)Ljava/lang/String;
  #511 = Utf8               Ljava/lang/String;
  #512 = Utf8               scala/collection/mutable/StringBuilder
  #513 = Class              #512          // scala/collection/mutable/StringBuilder
  #514 = Utf8               ()V
  #515 = NameAndType        #292:#514     // "<init>":()V
  #516 = Methodref          #513.#515     // scala/collection/mutable/StringBuilder."<init>":()V
  #517 = Utf8               append
  #518 = Utf8               (Ljava/lang/String;)Lscala/collection/mutable/StringBuilder;
  #519 = NameAndType        #517:#518     // append:(Ljava/lang/String;)Lscala/collection/mutable/StringBuilder;
  #520 = Methodref          #513.#519     // scala/collection/mutable/StringBuilder.append:(Ljava/lang/String;)Lscala/collection/mutable/StringBuilder;
  #521 = Utf8               scala/runtime/BooleanRef
  #522 = Class              #521          // scala/runtime/BooleanRef
  #523 = Utf8               (Z)Lscala/runtime/BooleanRef;
  #524 = NameAndType        #132:#523     // create:(Z)Lscala/runtime/BooleanRef;
  #525 = Methodref          #522.#524     // scala/runtime/BooleanRef.create:(Z)Lscala/runtime/BooleanRef;
  #526 = Utf8               $anonfun$mkString$1$adapted
  #527 = Utf8               (Lscala/runtime/BooleanRef;Lscala/collection/mutable/StringBuilder;Ljava/lang/String;Ljava/lang/Object;)Ljava/lang/Object;
  #528 = NameAndType        #526:#527     // $anonfun$mkString$1$adapted:(Lscala/runtime/BooleanRef;Lscala/collection/mutable/StringBuilder;Ljava/lang/String;Ljava/lang/Object;)Ljava/lang/Object;
  #529 = InterfaceMethodref #2.#528       // geny/Generator.$anonfun$mkString$1$adapted:(Lscala/runtime/BooleanRef;Lscala/collection/mutable/StringBuilder;Ljava/lang/String;Ljava/lang/Object;)Ljava/lang/Object;
  #530 = MethodHandle       6:#529        // REF_invokeStatic geny/Generator.$anonfun$mkString$1$adapted:(Lscala/runtime/BooleanRef;Lscala/collection/mutable/StringBuilder;Ljava/lang/String;Ljava/lang/Object;)Ljava/lang/Object;
  #531 = Utf8               (Lscala/runtime/BooleanRef;Lscala/collection/mutable/StringBuilder;Ljava/lang/String;)Lscala/Function1;
  #532 = NameAndType        #73:#531      // apply:(Lscala/runtime/BooleanRef;Lscala/collection/mutable/StringBuilder;Ljava/lang/String;)Lscala/Function1;
  #533 = InvokeDynamic      #14:#532      // #14:apply:(Lscala/runtime/BooleanRef;Lscala/collection/mutable/StringBuilder;Ljava/lang/String;)Lscala/Function1;
  #534 = Utf8               toString
  #535 = Utf8               ()Ljava/lang/String;
  #536 = NameAndType        #534:#535     // toString:()Ljava/lang/String;
  #537 = Methodref          #513.#536     // scala/collection/mutable/StringBuilder.toString:()Ljava/lang/String;
  #538 = Utf8               sb
  #539 = Utf8               Lscala/collection/mutable/StringBuilder;
  #540 = Utf8               first
  #541 = Utf8               Lscala/runtime/BooleanRef;
  #542 = Utf8               (Lgeny/Generator;Ljava/lang/String;)Ljava/lang/String;
  #543 = Utf8               (Ljava/lang/String;)Ljava/lang/String;
  #544 = NameAndType        #507:#543     // mkString:(Ljava/lang/String;)Ljava/lang/String;
  #545 = InterfaceMethodref #2.#544       // geny/Generator.mkString:(Ljava/lang/String;)Ljava/lang/String;
  #546 = Utf8
  #547 = String             #546          //
  #548 = Utf8               (Lgeny/Generator;)Ljava/lang/String;
  #549 = NameAndType        #507:#535     // mkString:()Ljava/lang/String;
  #550 = InterfaceMethodref #2.#549       // geny/Generator.mkString:()Ljava/lang/String;
  #551 = Utf8               sum$
  #552 = Utf8               (Lgeny/Generator;Lscala/math/Numeric;)Ljava/lang/Object;
  #553 = Utf8               num
  #554 = Utf8               sum
  #555 = Utf8               (Lscala/math/Numeric;)Ljava/lang/Object;
  #556 = NameAndType        #554:#555     // sum:(Lscala/math/Numeric;)Ljava/lang/Object;
  #557 = InterfaceMethodref #2.#556       // geny/Generator.sum:(Lscala/math/Numeric;)Ljava/lang/Object;
  #558 = Utf8               Lscala/math/Numeric;
  #559 = Utf8               <B:Ljava/lang/Object;>(Lscala/math/Numeric<TB;>;)TB;
  #560 = Utf8               scala/math/Numeric
  #561 = Class              #560          // scala/math/Numeric
  #562 = Utf8               zero
  #563 = NameAndType        #562:#269     // zero:()Ljava/lang/Object;
  #564 = InterfaceMethodref #561.#563     // scala/math/Numeric.zero:()Ljava/lang/Object;
  #565 = MethodType         #179          //  (Ljava/lang/Object;Ljava/lang/Object;)Ljava/lang/Object;
  #566 = Utf8               $anonfun$sum$1
  #567 = Utf8               (Lscala/math/Numeric;Ljava/lang/Object;Ljava/lang/Object;)Ljava/lang/Object;
  #568 = NameAndType        #566:#567     // $anonfun$sum$1:(Lscala/math/Numeric;Ljava/lang/Object;Ljava/lang/Object;)Ljava/lang/Object;
  #569 = InterfaceMethodref #2.#568       // geny/Generator.$anonfun$sum$1:(Lscala/math/Numeric;Ljava/lang/Object;Ljava/lang/Object;)Ljava/lang/Object;
  #570 = MethodHandle       6:#569        // REF_invokeStatic geny/Generator.$anonfun$sum$1:(Lscala/math/Numeric;Ljava/lang/Object;Ljava/lang/Object;)Ljava/lang/Object;
  #571 = Utf8               (Lscala/math/Numeric;)Lscala/Function2;
  #572 = NameAndType        #73:#571      // apply:(Lscala/math/Numeric;)Lscala/Function2;
  #573 = InvokeDynamic      #15:#572      // #15:apply:(Lscala/math/Numeric;)Lscala/Function2;
  #574 = Utf8               product$
  #575 = Utf8               product
  #576 = NameAndType        #575:#555     // product:(Lscala/math/Numeric;)Ljava/lang/Object;
  #577 = InterfaceMethodref #2.#576       // geny/Generator.product:(Lscala/math/Numeric;)Ljava/lang/Object;
  #578 = Utf8               one
  #579 = NameAndType        #578:#269     // one:()Ljava/lang/Object;
  #580 = InterfaceMethodref #561.#579     // scala/math/Numeric.one:()Ljava/lang/Object;
  #581 = Utf8               $anonfun$product$1
  #582 = NameAndType        #581:#567     // $anonfun$product$1:(Lscala/math/Numeric;Ljava/lang/Object;Ljava/lang/Object;)Ljava/lang/Object;
  #583 = InterfaceMethodref #2.#582       // geny/Generator.$anonfun$product$1:(Lscala/math/Numeric;Ljava/lang/Object;Ljava/lang/Object;)Ljava/lang/Object;
  #584 = MethodHandle       6:#583        // REF_invokeStatic geny/Generator.$anonfun$product$1:(Lscala/math/Numeric;Ljava/lang/Object;Ljava/lang/Object;)Ljava/lang/Object;
  #585 = InvokeDynamic      #16:#572      // #16:apply:(Lscala/math/Numeric;)Lscala/Function2;
  #586 = Utf8               min$
  #587 = Utf8               (Lgeny/Generator;Lscala/math/Ordering;)Ljava/lang/Object;
  #588 = Utf8               cmp
  #589 = Utf8               min
  #590 = Utf8               (Lscala/math/Ordering;)Ljava/lang/Object;
  #591 = NameAndType        #589:#590     // min:(Lscala/math/Ordering;)Ljava/lang/Object;
  #592 = InterfaceMethodref #2.#591       // geny/Generator.min:(Lscala/math/Ordering;)Ljava/lang/Object;
  #593 = Utf8               Lscala/math/Ordering;
  #594 = Utf8               <B:Ljava/lang/Object;>(Lscala/math/Ordering<TB;>;)TA;
  #595 = Utf8               $anonfun$min$1
  #596 = Utf8               (Lscala/math/Ordering;Ljava/lang/Object;Ljava/lang/Object;)Ljava/lang/Object;
  #597 = NameAndType        #595:#596     // $anonfun$min$1:(Lscala/math/Ordering;Ljava/lang/Object;Ljava/lang/Object;)Ljava/lang/Object;
  #598 = InterfaceMethodref #2.#597       // geny/Generator.$anonfun$min$1:(Lscala/math/Ordering;Ljava/lang/Object;Ljava/lang/Object;)Ljava/lang/Object;
  #599 = MethodHandle       6:#598        // REF_invokeStatic geny/Generator.$anonfun$min$1:(Lscala/math/Ordering;Ljava/lang/Object;Ljava/lang/Object;)Ljava/lang/Object;
  #600 = Utf8               (Lscala/math/Ordering;)Lscala/Function2;
  #601 = NameAndType        #73:#600      // apply:(Lscala/math/Ordering;)Lscala/Function2;
  #602 = InvokeDynamic      #17:#601      // #17:apply:(Lscala/math/Ordering;)Lscala/Function2;
  #603 = Utf8               max$
  #604 = Utf8               max
  #605 = NameAndType        #604:#590     // max:(Lscala/math/Ordering;)Ljava/lang/Object;
  #606 = InterfaceMethodref #2.#605       // geny/Generator.max:(Lscala/math/Ordering;)Ljava/lang/Object;
  #607 = Utf8               $anonfun$max$1
  #608 = NameAndType        #607:#596     // $anonfun$max$1:(Lscala/math/Ordering;Ljava/lang/Object;Ljava/lang/Object;)Ljava/lang/Object;
  #609 = InterfaceMethodref #2.#608       // geny/Generator.$anonfun$max$1:(Lscala/math/Ordering;Ljava/lang/Object;Ljava/lang/Object;)Ljava/lang/Object;
  #610 = MethodHandle       6:#609        // REF_invokeStatic geny/Generator.$anonfun$max$1:(Lscala/math/Ordering;Ljava/lang/Object;Ljava/lang/Object;)Ljava/lang/Object;
  #611 = InvokeDynamic      #18:#601      // #18:apply:(Lscala/math/Ordering;)Lscala/Function2;
  #612 = Utf8               maxBy$
  #613 = Utf8               (Lgeny/Generator;Lscala/Function1;Lscala/math/Ordering;)Ljava/lang/Object;
  #614 = Utf8               maxBy
  #615 = Utf8               (Lscala/Function1;Lscala/math/Ordering;)Ljava/lang/Object;
  #616 = NameAndType        #614:#615     // maxBy:(Lscala/Function1;Lscala/math/Ordering;)Ljava/lang/Object;
  #617 = InterfaceMethodref #2.#616       // geny/Generator.maxBy:(Lscala/Function1;Lscala/math/Ordering;)Ljava/lang/Object;
  #618 = Utf8               <B:Ljava/lang/Object;>(Lscala/Function1<TA;TB;>;Lscala/math/Ordering<TB;>;)TA;
  #619 = Utf8               $anonfun$maxBy$1$adapted
  #620 = Utf8               (Lscala/Function1;Lscala/runtime/BooleanRef;Lscala/math/Ordering;Lscala/runtime/ObjectRef;Lscala/runtime/ObjectRef;Ljava/lang/Object;)Ljava/lang/Object;
  #621 = NameAndType        #619:#620     // $anonfun$maxBy$1$adapted:(Lscala/Function1;Lscala/runtime/BooleanRef;Lscala/math/Ordering;Lscala/runtime/ObjectRef;Lscala/runtime/ObjectRef;Ljava/lang/Object;)Ljava/lang/Object;
  #622 = InterfaceMethodref #2.#621       // geny/Generator.$anonfun$maxBy$1$adapted:(Lscala/Function1;Lscala/runtime/BooleanRef;Lscala/math/Ordering;Lscala/runtime/ObjectRef;Lscala/runtime/ObjectRef;Ljava/lang/Object;)Ljava/lang/Object;
  #623 = MethodHandle       6:#622        // REF_invokeStatic geny/Generator.$anonfun$maxBy$1$adapted:(Lscala/Function1;Lscala/runtime/BooleanRef;Lscala/math/Ordering;Lscala/runtime/ObjectRef;Lscala/runtime/ObjectRef;Ljava/lang/Object;)Ljava/lang/Object;
  #624 = Utf8               (Lscala/Function1;Lscala/runtime/BooleanRef;Lscala/math/Ordering;Lscala/runtime/ObjectRef;Lscala/runtime/ObjectRef;)Lscala/Function1;
  #625 = NameAndType        #73:#624      // apply:(Lscala/Function1;Lscala/runtime/BooleanRef;Lscala/math/Ordering;Lscala/runtime/ObjectRef;Lscala/runtime/ObjectRef;)Lscala/Function1;
  #626 = InvokeDynamic      #19:#625      // #19:apply:(Lscala/Function1;Lscala/runtime/BooleanRef;Lscala/math/Ordering;Lscala/runtime/ObjectRef;Lscala/runtime/ObjectRef;)Lscala/Function1;
  #627 = Utf8               maxF
  #628 = Utf8               maxElem
  #629 = Utf8               minBy$
  #630 = Utf8               minBy
  #631 = NameAndType        #630:#615     // minBy:(Lscala/Function1;Lscala/math/Ordering;)Ljava/lang/Object;
  #632 = InterfaceMethodref #2.#631       // geny/Generator.minBy:(Lscala/Function1;Lscala/math/Ordering;)Ljava/lang/Object;
  #633 = Utf8               $anonfun$minBy$1$adapted
  #634 = NameAndType        #633:#620     // $anonfun$minBy$1$adapted:(Lscala/Function1;Lscala/runtime/BooleanRef;Lscala/math/Ordering;Lscala/runtime/ObjectRef;Lscala/runtime/ObjectRef;Ljava/lang/Object;)Ljava/lang/Object;
  #635 = InterfaceMethodref #2.#634       // geny/Generator.$anonfun$minBy$1$adapted:(Lscala/Function1;Lscala/runtime/BooleanRef;Lscala/math/Ordering;Lscala/runtime/ObjectRef;Lscala/runtime/ObjectRef;Ljava/lang/Object;)Ljava/lang/Object;
  #636 = MethodHandle       6:#635        // REF_invokeStatic geny/Generator.$anonfun$minBy$1$adapted:(Lscala/Function1;Lscala/runtime/BooleanRef;Lscala/math/Ordering;Lscala/runtime/ObjectRef;Lscala/runtime/ObjectRef;Ljava/lang/Object;)Ljava/lang/Object;
  #637 = InvokeDynamic      #20:#625      // #20:apply:(Lscala/Function1;Lscala/runtime/BooleanRef;Lscala/math/Ordering;Lscala/runtime/ObjectRef;Lscala/runtime/ObjectRef;)Lscala/Function1;
  #638 = Utf8               minF
  #639 = Utf8               minElem
  #640 = Utf8               f$1
  #641 = Utf8               x
  #642 = Utf8               scala/Function1
  #643 = Class              #642          // scala/Function1
  #644 = NameAndType        #73:#94       // apply:(Ljava/lang/Object;)Ljava/lang/Object;
  #645 = InterfaceMethodref #643.#644     // scala/Function1.apply:(Ljava/lang/Object;)Ljava/lang/Object;
  #646 = Utf8               Lgeny/Generator$Continue$;
  #647 = NameAndType        #60:#646      // MODULE$:Lgeny/Generator$Continue$;
  #648 = Fieldref           #17.#647      // geny/Generator$Continue$.MODULE$:Lgeny/Generator$Continue$;
  #649 = Utf8               f$2
  #650 = Utf8               result$1
  #651 = Utf8               scala/runtime/BoxesRunTime
  #652 = Class              #651          // scala/runtime/BoxesRunTime
  #653 = Utf8               unboxToBoolean
  #654 = NameAndType        #653:#175     // unboxToBoolean:(Ljava/lang/Object;)Z
  #655 = Methodref          #652.#654     // scala/runtime/BoxesRunTime.unboxToBoolean:(Ljava/lang/Object;)Z
  #656 = Utf8               scala/Some
  #657 = Class              #656          // scala/Some
  #658 = Utf8               (Ljava/lang/Object;)V
  #659 = NameAndType        #292:#658     // "<init>":(Ljava/lang/Object;)V
  #660 = Methodref          #657.#659     // scala/Some."<init>":(Ljava/lang/Object;)V
  #661 = Utf8               Lgeny/Generator$End$;
  #662 = NameAndType        #60:#661      // MODULE$:Lgeny/Generator$End$;
  #663 = Fieldref           #23.#662      // geny/Generator$End$.MODULE$:Lgeny/Generator$End$;
  #664 = Utf8               $anonfun$exists$1
  #665 = Utf8               (Lscala/Function1;Ljava/lang/Object;)Z
  #666 = Utf8               f$3
  #667 = Utf8               x$1
  #668 = Utf8               $anonfun$contains$1
  #669 = Utf8               (Ljava/lang/Object;Ljava/lang/Object;)Z
  #670 = Utf8               a$1
  #671 = Utf8               x$2
  #672 = Utf8               equals
  #673 = NameAndType        #672:#669     // equals:(Ljava/lang/Object;Ljava/lang/Object;)Z
  #674 = Methodref          #652.#673     // scala/runtime/BoxesRunTime.equals:(Ljava/lang/Object;Ljava/lang/Object;)Z
  #675 = Utf8               $anonfun$forall$1
  #676 = Utf8               f$4
  #677 = Utf8               x$3
  #678 = Utf8               f$5
  #679 = Utf8               result$2
  #680 = Utf8               $anonfun$count$default$1$1
  #681 = Utf8               x$4
  #682 = Utf8               result$3
  #683 = Utf8               f$6
  #684 = Utf8               scala/Function2
  #685 = Class              #684          // scala/Function2
  #686 = NameAndType        #73:#179      // apply:(Ljava/lang/Object;Ljava/lang/Object;)Ljava/lang/Object;
  #687 = InterfaceMethodref #685.#686     // scala/Function2.apply:(Ljava/lang/Object;Ljava/lang/Object;)Ljava/lang/Object;
  #688 = Utf8               result$4
  #689 = Utf8               f$7
  #690 = NameAndType        #672:#175     // equals:(Ljava/lang/Object;)Z
  #691 = Methodref          #5.#690       // java/lang/Object.equals:(Ljava/lang/Object;)Z
  #692 = Utf8               value
  #693 = NameAndType        #692:#269     // value:()Ljava/lang/Object;
  #694 = Methodref          #657.#693     // scala/Some.value:()Ljava/lang/Object;
  #695 = Utf8               scala/MatchError
  #696 = Class              #695          // scala/MatchError
  #697 = Methodref          #696.#659     // scala/MatchError."<init>":(Ljava/lang/Object;)V
  #698 = Utf8               old
  #699 = Utf8               java/lang/UnsupportedOperationException
  #700 = Class              #699          // java/lang/UnsupportedOperationException
  #701 = Utf8               empty.reduceLeft
  #702 = String             #701          // empty.reduceLeft
  #703 = Utf8               (Ljava/lang/String;)V
  #704 = NameAndType        #292:#703     // "<init>":(Ljava/lang/String;)V
  #705 = Methodref          #700.#704     // java/lang/UnsupportedOperationException."<init>":(Ljava/lang/String;)V
  #706 = Utf8               $anonfun$collect$1
  #707 = Utf8               (Lscala/PartialFunction;Ljava/lang/Object;)Z
  #708 = Utf8               func$1
  #709 = Utf8               scala/PartialFunction
  #710 = Class              #709          // scala/PartialFunction
  #711 = Utf8               isDefinedAt
  #712 = NameAndType        #711:#175     // isDefinedAt:(Ljava/lang/Object;)Z
  #713 = InterfaceMethodref #710.#712     // scala/PartialFunction.isDefinedAt:(Ljava/lang/Object;)Z
  #714 = Utf8               $anonfun$collectFirst$1
  #715 = Utf8               func$2
  #716 = Utf8               f$8
  #717 = Utf8               $anonfun$toBuffer$1
  #718 = Utf8               (Lscala/collection/mutable/Buffer;Ljava/lang/Object;)V
  #719 = Utf8               arr$1
  #720 = Utf8               x$5
  #721 = Utf8               (Ljava/lang/Object;)Lscala/collection/mutable/Buffer;
  #722 = NameAndType        #517:#721     // append:(Ljava/lang/Object;)Lscala/collection/mutable/Buffer;
  #723 = InterfaceMethodref #456.#722     // scala/collection/mutable/Buffer.append:(Ljava/lang/Object;)Lscala/collection/mutable/Buffer;
  #724 = Utf8               $anonfun$mkString$1
  #725 = Utf8               (Lscala/runtime/BooleanRef;Lscala/collection/mutable/StringBuilder;Ljava/lang/String;Ljava/lang/Object;)V
  #726 = Utf8               first$1
  #727 = Utf8               sb$1
  #728 = Utf8               sep$1
  #729 = Utf8               Z
  #730 = NameAndType        #146:#729     // elem:Z
  #731 = Fieldref           #522.#730     // scala/runtime/BooleanRef.elem:Z
  #732 = Utf8               scala/runtime/BoxedUnit
  #733 = Class              #732          // scala/runtime/BoxedUnit
  #734 = Utf8               UNIT
  #735 = Utf8               Lscala/runtime/BoxedUnit;
  #736 = NameAndType        #734:#735     // UNIT:Lscala/runtime/BoxedUnit;
  #737 = Fieldref           #733.#736     // scala/runtime/BoxedUnit.UNIT:Lscala/runtime/BoxedUnit;
  #738 = Utf8               (Ljava/lang/Object;)Lscala/collection/mutable/StringBuilder;
  #739 = NameAndType        #517:#738     // append:(Ljava/lang/Object;)Lscala/collection/mutable/StringBuilder;
  #740 = Methodref          #513.#739     // scala/collection/mutable/StringBuilder.append:(Ljava/lang/Object;)Lscala/collection/mutable/StringBuilder;
  #741 = Utf8               num$1
  #742 = Utf8               y
  #743 = Utf8               plus
  #744 = NameAndType        #743:#179     // plus:(Ljava/lang/Object;Ljava/lang/Object;)Ljava/lang/Object;
  #745 = InterfaceMethodref #561.#744     // scala/math/Numeric.plus:(Ljava/lang/Object;Ljava/lang/Object;)Ljava/lang/Object;
  #746 = Utf8               num$2
  #747 = Utf8               times
  #748 = NameAndType        #747:#179     // times:(Ljava/lang/Object;Ljava/lang/Object;)Ljava/lang/Object;
  #749 = InterfaceMethodref #561.#748     // scala/math/Numeric.times:(Ljava/lang/Object;Ljava/lang/Object;)Ljava/lang/Object;
  #750 = Utf8               cmp$1
  #751 = Utf8               scala/math/Ordering
  #752 = Class              #751          // scala/math/Ordering
  #753 = Utf8               lteq
  #754 = NameAndType        #753:#669     // lteq:(Ljava/lang/Object;Ljava/lang/Object;)Z
  #755 = InterfaceMethodref #752.#754     // scala/math/Ordering.lteq:(Ljava/lang/Object;Ljava/lang/Object;)Z
  #756 = Utf8               cmp$2
  #757 = Utf8               gteq
  #758 = NameAndType        #757:#669     // gteq:(Ljava/lang/Object;Ljava/lang/Object;)Z
  #759 = InterfaceMethodref #752.#758     // scala/math/Ordering.gteq:(Ljava/lang/Object;Ljava/lang/Object;)Z
  #760 = Utf8               $anonfun$maxBy$1
  #761 = Utf8               (Lscala/Function1;Lscala/runtime/BooleanRef;Lscala/math/Ordering;Lscala/runtime/ObjectRef;Lscala/runtime/ObjectRef;Ljava/lang/Object;)V
  #762 = Utf8               f$9
  #763 = Utf8               first$2
  #764 = Utf8               cmp$3
  #765 = Utf8               maxF$1
  #766 = Utf8               maxElem$1
  #767 = Utf8               gt
  #768 = NameAndType        #767:#669     // gt:(Ljava/lang/Object;Ljava/lang/Object;)Z
  #769 = InterfaceMethodref #752.#768     // scala/math/Ordering.gt:(Ljava/lang/Object;Ljava/lang/Object;)Z
  #770 = Utf8               fx
  #771 = Utf8               $anonfun$minBy$1
  #772 = Utf8               f$10
  #773 = Utf8               first$3
  #774 = Utf8               cmp$4
  #775 = Utf8               minF$1
  #776 = Utf8               minElem$1
  #777 = Utf8               lt
  #778 = NameAndType        #777:#669     // lt:(Ljava/lang/Object;Ljava/lang/Object;)Z
  #779 = InterfaceMethodref #752.#778     // scala/math/Ordering.lt:(Ljava/lang/Object;Ljava/lang/Object;)Z
  #780 = Utf8               $init$
  #781 = NameAndType        #664:#665     // $anonfun$exists$1:(Lscala/Function1;Ljava/lang/Object;)Z
  #782 = InterfaceMethodref #2.#781       // geny/Generator.$anonfun$exists$1:(Lscala/Function1;Ljava/lang/Object;)Z
  #783 = Utf8               boxToBoolean
  #784 = Utf8               (Z)Ljava/lang/Boolean;
  #785 = NameAndType        #783:#784     // boxToBoolean:(Z)Ljava/lang/Boolean;
  #786 = Methodref          #652.#785     // scala/runtime/BoxesRunTime.boxToBoolean:(Z)Ljava/lang/Boolean;
  #787 = NameAndType        #668:#669     // $anonfun$contains$1:(Ljava/lang/Object;Ljava/lang/Object;)Z
  #788 = InterfaceMethodref #2.#787       // geny/Generator.$anonfun$contains$1:(Ljava/lang/Object;Ljava/lang/Object;)Z
  #789 = NameAndType        #675:#665     // $anonfun$forall$1:(Lscala/Function1;Ljava/lang/Object;)Z
  #790 = InterfaceMethodref #2.#789       // geny/Generator.$anonfun$forall$1:(Lscala/Function1;Ljava/lang/Object;)Z
  #791 = NameAndType        #680:#175     // $anonfun$count$default$1$1:(Ljava/lang/Object;)Z
  #792 = InterfaceMethodref #2.#791       // geny/Generator.$anonfun$count$default$1$1:(Ljava/lang/Object;)Z
  #793 = NameAndType        #706:#707     // $anonfun$collect$1:(Lscala/PartialFunction;Ljava/lang/Object;)Z
  #794 = InterfaceMethodref #2.#793       // geny/Generator.$anonfun$collect$1:(Lscala/PartialFunction;Ljava/lang/Object;)Z
  #795 = NameAndType        #714:#707     // $anonfun$collectFirst$1:(Lscala/PartialFunction;Ljava/lang/Object;)Z
  #796 = InterfaceMethodref #2.#795       // geny/Generator.$anonfun$collectFirst$1:(Lscala/PartialFunction;Ljava/lang/Object;)Z
  #797 = NameAndType        #717:#718     // $anonfun$toBuffer$1:(Lscala/collection/mutable/Buffer;Ljava/lang/Object;)V
  #798 = InterfaceMethodref #2.#797       // geny/Generator.$anonfun$toBuffer$1:(Lscala/collection/mutable/Buffer;Ljava/lang/Object;)V
  #799 = NameAndType        #724:#725     // $anonfun$mkString$1:(Lscala/runtime/BooleanRef;Lscala/collection/mutable/StringBuilder;Ljava/lang/String;Ljava/lang/Object;)V
  #800 = InterfaceMethodref #2.#799       // geny/Generator.$anonfun$mkString$1:(Lscala/runtime/BooleanRef;Lscala/collection/mutable/StringBuilder;Ljava/lang/String;Ljava/lang/Object;)V
  #801 = NameAndType        #760:#761     // $anonfun$maxBy$1:(Lscala/Function1;Lscala/runtime/BooleanRef;Lscala/math/Ordering;Lscala/runtime/ObjectRef;Lscala/runtime/ObjectRef;Ljava/lang/Object;)V
  #802 = InterfaceMethodref #2.#801       // geny/Generator.$anonfun$maxBy$1:(Lscala/Function1;Lscala/runtime/BooleanRef;Lscala/math/Ordering;Lscala/runtime/ObjectRef;Lscala/runtime/ObjectRef;Ljava/lang/Object;)V
  #803 = NameAndType        #771:#761     // $anonfun$minBy$1:(Lscala/Function1;Lscala/runtime/BooleanRef;Lscala/math/Ordering;Lscala/runtime/ObjectRef;Lscala/runtime/ObjectRef;Ljava/lang/Object;)V
  #804 = InterfaceMethodref #2.#803       // geny/Generator.$anonfun$minBy$1:(Lscala/Function1;Lscala/runtime/BooleanRef;Lscala/math/Ordering;Lscala/runtime/ObjectRef;Lscala/runtime/ObjectRef;Ljava/lang/Object;)V
  #805 = Utf8               $deserializeLambda$
  #806 = Utf8               (Ljava/lang/invoke/SerializedLambda;)Ljava/lang/Object;
  #807 = Utf8               scala/runtime/LambdaDeserialize
  #808 = Class              #807          // scala/runtime/LambdaDeserialize
  #809 = Utf8               bootstrap
  #810 = Utf8               (Ljava/lang/invoke/MethodHandles$Lookup;Ljava/lang/String;Ljava/lang/invoke/MethodType;[Ljava/lang/invoke/MethodHandle;)Ljava/lang/invoke/CallSite;
  #811 = NameAndType        #809:#810     // bootstrap:(Ljava/lang/invoke/MethodHandles$Lookup;Ljava/lang/String;Ljava/lang/invoke/MethodType;[Ljava/lang/invoke/MethodHandle;)Ljava/lang/invoke/CallSite;
  #812 = Methodref          #808.#811     // scala/runtime/LambdaDeserialize.bootstrap:(Ljava/lang/invoke/MethodHandles$Lookup;Ljava/lang/String;Ljava/lang/invoke/MethodType;[Ljava/lang/invoke/MethodHandle;)Ljava/lang/invoke/CallSite;
  #813 = MethodHandle       6:#812        // REF_invokeStatic scala/runtime/LambdaDeserialize.bootstrap:(Ljava/lang/invoke/MethodHandles$Lookup;Ljava/lang/String;Ljava/lang/invoke/MethodType;[Ljava/lang/invoke/MethodHandle;)Ljava/lang/invoke/CallSite;
  #814 = Utf8               lambdaDeserialize
  #815 = NameAndType        #814:#806     // lambdaDeserialize:(Ljava/lang/invoke/SerializedLambda;)Ljava/lang/Object;
  #816 = InvokeDynamic      #21:#815      // #21:lambdaDeserialize:(Ljava/lang/invoke/SerializedLambda;)Ljava/lang/Object;
  #817 = Utf8               Code
  #818 = Utf8               Signature
  #819 = Utf8               MethodParameters
  #820 = Utf8               LineNumberTable
  #821 = Utf8               LocalVariableTable
  #822 = Utf8               StackMapTable
  #823 = Utf8               InnerClasses
  #824 = Utf8               SourceFile
  #825 = Utf8               RuntimeVisibleAnnotations
  #826 = Utf8               BootstrapMethods
  #827 = Utf8               ScalaInlineInfo
  #828 = Utf8               ScalaSig
{
  public static <T extends java.lang.Object> geny.Generator<T> selfClosing(scala.Function0<scala.Tuple2<scala.collection.Iterator<T>, scala.Function0<scala.runtime.BoxedUnit>>>);
    descriptor: (Lscala/Function0;)Lgeny/Generator;
    flags: (0x0009) ACC_PUBLIC, ACC_STATIC
    Code:
      stack=2, locals=1, args_size=1
         0: getstatic     #63                 // Field geny/Generator$.MODULE$:Lgeny/Generator$;
         3: aload_0
         4: invokevirtual #65                 // Method geny/Generator$.selfClosing:(Lscala/Function0;)Lgeny/Generator;
         7: areturn
    Signature: #56                          // <T:Ljava/lang/Object;>(Lscala/Function0<Lscala/Tuple2<Lscala/collection/Iterator<TT;>;Lscala/Function0<Lscala/runtime/BoxedUnit;>;>;>;)Lgeny/Generator<TT;>;
    MethodParameters:
      Name                           Flags
      makeIterator                   final

  public static <M extends java.lang.Object, T extends java.lang.Object> geny.Generator<T> from(M, scala.Function1<M, scala.collection.IterableOnce<T>>);
    descriptor: (Ljava/lang/Object;Lscala/Function1;)Lgeny/Generator;
    flags: (0x0009) ACC_PUBLIC, ACC_STATIC
    Code:
      stack=3, locals=2, args_size=2
         0: getstatic     #63                 // Field geny/Generator$.MODULE$:Lgeny/Generator$;
         3: aload_0
         4: aload_1
         5: invokevirtual #72                 // Method geny/Generator$.from:(Ljava/lang/Object;Lscala/Function1;)Lgeny/Generator;
         8: areturn
    Signature: #68                          // <M:Ljava/lang/Object;T:Ljava/lang/Object;>(TM;Lscala/Function1<TM;Lscala/collection/IterableOnce<TT;>;>;)Lgeny/Generator<TT;>;
    MethodParameters:
      Name                           Flags
      t                              final
      convert                        final

  public static <T extends java.lang.Object> geny.Generator<T> apply(scala.collection.immutable.Seq<T>);
    descriptor: (Lscala/collection/immutable/Seq;)Lgeny/Generator;
    flags: (0x0009) ACC_PUBLIC, ACC_STATIC
    Code:
      stack=2, locals=1, args_size=1
         0: getstatic     #63                 // Field geny/Generator$.MODULE$:Lgeny/Generator$;
         3: aload_0
         4: invokevirtual #78                 // Method geny/Generator$.apply:(Lscala/collection/immutable/Seq;)Lgeny/Generator;
         7: areturn
    Signature: #75                          // <T:Ljava/lang/Object;>(Lscala/collection/immutable/Seq<TT;>;)Lgeny/Generator<TT;>;
    MethodParameters:
      Name                           Flags
      xs                             final

  public abstract geny.Generator$Action generate(scala.Function1<A, geny.Generator$Action>);
    descriptor: (Lscala/Function1;)Lgeny/Generator$Action;
    flags: (0x0401) ACC_PUBLIC, ACC_ABSTRACT
    Signature: #81                          // (Lscala/Function1<TA;Lgeny/Generator$Action;>;)Lgeny/Generator$Action;
    MethodParameters:
      Name                           Flags
      handleItem                     final

  public static void foreach$(geny.Generator, scala.Function1);
    descriptor: (Lgeny/Generator;Lscala/Function1;)V
    flags: (0x1009) ACC_PUBLIC, ACC_STATIC, ACC_SYNTHETIC
    Code:
      stack=2, locals=2, args_size=2
         0: aload_0
         1: aload_1
         2: invokespecial #90                 // InterfaceMethod foreach:(Lscala/Function1;)V
         5: return
      LineNumberTable:
        line 49: 0
      LocalVariableTable:
        Start  Length  Slot  Name   Signature
            0       6     0 $this   Lgeny/Generator;
            0       6     1     f   Lscala/Function1;
    MethodParameters:
      Name                           Flags
      $this                          final synthetic
      f                              final

  public default void foreach(scala.Function1<A, scala.runtime.BoxedUnit>);
    descriptor: (Lscala/Function1;)V
    flags: (0x0001) ACC_PUBLIC
    Code:
      stack=2, locals=2, args_size=2
         0: aload_0
         1: aload_1
         2: invokedynamic #114,  0            // InvokeDynamic #0:apply:(Lscala/Function1;)Lscala/Function1;
         7: invokeinterface #116,  2          // InterfaceMethod generate:(Lscala/Function1;)Lgeny/Generator$Action;
        12: pop
        13: return
      LineNumberTable:
        line 49: 0
      LocalVariableTable:
        Start  Length  Slot  Name   Signature
            0      14     0  this   Lgeny/Generator;
            0      14     1     f   Lscala/Function1;
    Signature: #93                          // (Lscala/Function1<TA;Lscala/runtime/BoxedUnit;>;)V
    MethodParameters:
      Name                           Flags
      f                              final

  public static scala.Option find$(geny.Generator, scala.Function1);
    descriptor: (Lgeny/Generator;Lscala/Function1;)Lscala/Option;
    flags: (0x1009) ACC_PUBLIC, ACC_STATIC, ACC_SYNTHETIC
    Code:
      stack=2, locals=2, args_size=2
         0: aload_0
         1: aload_1
         2: invokespecial #123                // InterfaceMethod find:(Lscala/Function1;)Lscala/Option;
         5: areturn
      LineNumberTable:
        line 54: 0
      LocalVariableTable:
        Start  Length  Slot  Name   Signature
            0       6     0 $this   Lgeny/Generator;
            0       6     1     f   Lscala/Function1;
    MethodParameters:
      Name                           Flags
      $this                          final synthetic
      f                              final

  public default scala.Option<A> find(scala.Function1<A, java.lang.Object>);
    descriptor: (Lscala/Function1;)Lscala/Option;
    flags: (0x0001) ACC_PUBLIC
    Code:
      stack=3, locals=3, args_size=2
         0: getstatic     #129                // Field scala/None$.MODULE$:Lscala/None$;
         3: invokestatic  #135                // Method scala/runtime/ObjectRef.create:(Ljava/lang/Object;)Lscala/runtime/ObjectRef;
         6: astore_2
         7: aload_0
         8: aload_1
         9: aload_2
        10: invokedynamic #145,  0            // InvokeDynamic #1:apply:(Lscala/Function1;Lscala/runtime/ObjectRef;)Lscala/Function1;
        15: invokeinterface #116,  2          // InterfaceMethod generate:(Lscala/Function1;)Lgeny/Generator$Action;
        20: pop
        21: aload_2
        22: getfield      #149                // Field scala/runtime/ObjectRef.elem:Ljava/lang/Object;
        25: checkcast     #151                // class scala/Option
        28: areturn
      LineNumberTable:
        line 55: 0
        line 56: 7
        line 63: 21
      LocalVariableTable:
        Start  Length  Slot  Name   Signature
            7      21     2 result   Lscala/runtime/ObjectRef;
            0      29     0  this   Lgeny/Generator;
            0      29     1     f   Lscala/Function1;
    Signature: #124                         // (Lscala/Function1<TA;Ljava/lang/Object;>;)Lscala/Option<TA;>;
    MethodParameters:
      Name                           Flags
      f                              final

  public static boolean exists$(geny.Generator, scala.Function1);
    descriptor: (Lgeny/Generator;Lscala/Function1;)Z
    flags: (0x1009) ACC_PUBLIC, ACC_STATIC, ACC_SYNTHETIC
    Code:
      stack=2, locals=2, args_size=2
         0: aload_0
         1: aload_1
         2: invokespecial #159                // InterfaceMethod exists:(Lscala/Function1;)Z
         5: ireturn
      LineNumberTable:
        line 65: 0
      LocalVariableTable:
        Start  Length  Slot  Name   Signature
            0       6     0 $this   Lgeny/Generator;
            0       6     1     f   Lscala/Function1;
    MethodParameters:
      Name                           Flags
      $this                          final synthetic
      f                              final

  public default boolean exists(scala.Function1<A, java.lang.Object>);
    descriptor: (Lscala/Function1;)Z
    flags: (0x0001) ACC_PUBLIC
    Code:
      stack=2, locals=2, args_size=2
         0: aload_0
         1: aload_1
         2: invokedynamic #166,  0            // InvokeDynamic #2:apply:(Lscala/Function1;)Lscala/Function1;
         7: invokeinterface #123,  2          // InterfaceMethod find:(Lscala/Function1;)Lscala/Option;
        12: invokevirtual #170                // Method scala/Option.isDefined:()Z
        15: ireturn
      LineNumberTable:
        line 65: 0
      LocalVariableTable:
        Start  Length  Slot  Name   Signature
            0      16     0  this   Lgeny/Generator;
            0      16     1     f   Lscala/Function1;
    Signature: #160                         // (Lscala/Function1<TA;Ljava/lang/Object;>;)Z
    MethodParameters:
      Name                           Flags
      f                              final

  public static boolean contains$(geny.Generator, java.lang.Object);
    descriptor: (Lgeny/Generator;Ljava/lang/Object;)Z
    flags: (0x1009) ACC_PUBLIC, ACC_STATIC, ACC_SYNTHETIC
    Code:
      stack=2, locals=2, args_size=2
         0: aload_0
         1: aload_1
         2: invokespecial #177                // InterfaceMethod contains:(Ljava/lang/Object;)Z
         5: ireturn
      LineNumberTable:
        line 66: 0
      LocalVariableTable:
        Start  Length  Slot  Name   Signature
            0       6     0 $this   Lgeny/Generator;
            0       6     1     a   Ljava/lang/Object;
    MethodParameters:
      Name                           Flags
      $this                          final synthetic
      a                              final

  public default boolean contains(java.lang.Object);
    descriptor: (Ljava/lang/Object;)Z
    flags: (0x0001) ACC_PUBLIC
    Code:
      stack=2, locals=2, args_size=2
         0: aload_0
         1: aload_1
         2: invokedynamic #185,  0            // InvokeDynamic #3:apply:(Ljava/lang/Object;)Lscala/Function1;
         7: invokeinterface #159,  2          // InterfaceMethod exists:(Lscala/Function1;)Z
        12: ireturn
      LineNumberTable:
        line 66: 0
      LocalVariableTable:
        Start  Length  Slot  Name   Signature
            0      13     0  this   Lgeny/Generator;
            0      13     1     a   Ljava/lang/Object;
    MethodParameters:
      Name                           Flags
      a                              final

  public static boolean forall$(geny.Generator, scala.Function1);
    descriptor: (Lgeny/Generator;Lscala/Function1;)Z
    flags: (0x1009) ACC_PUBLIC, ACC_STATIC, ACC_SYNTHETIC
    Code:
      stack=2, locals=2, args_size=2
         0: aload_0
         1: aload_1
         2: invokespecial #189                // InterfaceMethod forall:(Lscala/Function1;)Z
         5: ireturn
      LineNumberTable:
        line 67: 0
      LocalVariableTable:
        Start  Length  Slot  Name   Signature
            0       6     0 $this   Lgeny/Generator;
            0       6     1     f   Lscala/Function1;
    MethodParameters:
      Name                           Flags
      $this                          final synthetic
      f                              final

  public default boolean forall(scala.Function1<A, java.lang.Object>);
    descriptor: (Lscala/Function1;)Z
    flags: (0x0001) ACC_PUBLIC
    Code:
      stack=2, locals=2, args_size=2
         0: aload_0
         1: aload_1
         2: invokedynamic #194,  0            // InvokeDynamic #4:apply:(Lscala/Function1;)Lscala/Function1;
         7: invokeinterface #159,  2          // InterfaceMethod exists:(Lscala/Function1;)Z
        12: ifne          19
        15: iconst_1
        16: goto          20
        19: iconst_0
        20: ireturn
      StackMapTable: number_of_entries = 2
        frame_type = 19 /* same */
        frame_type = 64 /* same_locals_1_stack_item */
          stack = [ int ]
      LineNumberTable:
        line 67: 0
      LocalVariableTable:
        Start  Length  Slot  Name   Signature
            0      21     0  this   Lgeny/Generator;
            0      21     1     f   Lscala/Function1;
    Signature: #160                         // (Lscala/Function1<TA;Ljava/lang/Object;>;)Z
    MethodParameters:
      Name                           Flags
      f                              final

  public static int count$(geny.Generator, scala.Function1);
    descriptor: (Lgeny/Generator;Lscala/Function1;)I
    flags: (0x1009) ACC_PUBLIC, ACC_STATIC, ACC_SYNTHETIC
    Code:
      stack=2, locals=2, args_size=2
         0: aload_0
         1: aload_1
         2: invokespecial #200                // InterfaceMethod count:(Lscala/Function1;)I
         5: ireturn
      LineNumberTable:
        line 68: 0
      LocalVariableTable:
        Start  Length  Slot  Name   Signature
            0       6     0 $this   Lgeny/Generator;
            0       6     1     f   Lscala/Function1;
    MethodParameters:
      Name                           Flags
      $this                          final synthetic
      f                              final

  public default int count(scala.Function1<A, java.lang.Object>);
    descriptor: (Lscala/Function1;)I
    flags: (0x0001) ACC_PUBLIC
    Code:
      stack=3, locals=3, args_size=2
         0: iconst_0
         1: invokestatic  #206                // Method scala/runtime/IntRef.create:(I)Lscala/runtime/IntRef;
         4: astore_2
         5: aload_0
         6: aload_1
         7: aload_2
         8: invokedynamic #214,  0            // InvokeDynamic #5:apply:(Lscala/Function1;Lscala/runtime/IntRef;)Lscala/Function1;
        13: invokeinterface #116,  2          // InterfaceMethod generate:(Lscala/Function1;)Lgeny/Generator$Action;
        18: pop
        19: aload_2
        20: getfield      #217                // Field scala/runtime/IntRef.elem:I
        23: ireturn
      LineNumberTable:
        line 69: 0
        line 70: 5
        line 74: 19
      LocalVariableTable:
        Start  Length  Slot  Name   Signature
            5      18     2 result   Lscala/runtime/IntRef;
            0      24     0  this   Lgeny/Generator;
            0      24     1     f   Lscala/Function1;
    Signature: #201                         // (Lscala/Function1<TA;Ljava/lang/Object;>;)I
    MethodParameters:
      Name                           Flags
      f                              final

  public static scala.Function1 count$default$1$(geny.Generator);
    descriptor: (Lgeny/Generator;)Lscala/Function1;
    flags: (0x1009) ACC_PUBLIC, ACC_STATIC, ACC_SYNTHETIC
    Code:
      stack=1, locals=1, args_size=1
         0: aload_0
         1: invokespecial #224                // InterfaceMethod count$default$1:()Lscala/Function1;
         4: areturn
      LineNumberTable:
        line 68: 0
      LocalVariableTable:
        Start  Length  Slot  Name   Signature
            0       5     0 $this   Lgeny/Generator;
    MethodParameters:
      Name                           Flags
      $this                          final synthetic

  public default scala.Function1<A, java.lang.Object> count$default$1();
    descriptor: ()Lscala/Function1;
    flags: (0x0001) ACC_PUBLIC
    Code:
      stack=1, locals=1, args_size=1
         0: invokedynamic #231,  0            // InvokeDynamic #6:apply:()Lscala/Function1;
         5: areturn
      LineNumberTable:
        line 68: 0
      LocalVariableTable:
        Start  Length  Slot  Name   Signature
            0       6     0  this   Lgeny/Generator;
    Signature: #225                         // ()Lscala/Function1<TA;Ljava/lang/Object;>;

  public static java.lang.Object fold$(geny.Generator, java.lang.Object, scala.Function2);
    descriptor: (Lgeny/Generator;Ljava/lang/Object;Lscala/Function2;)Ljava/lang/Object;
    flags: (0x1009) ACC_PUBLIC, ACC_STATIC, ACC_SYNTHETIC
    Code:
      stack=3, locals=3, args_size=3
         0: aload_0
         1: aload_1
         2: aload_2
         3: invokespecial #238                // InterfaceMethod fold:(Ljava/lang/Object;Lscala/Function2;)Ljava/lang/Object;
         6: areturn
      LineNumberTable:
        line 76: 0
      LocalVariableTable:
        Start  Length  Slot  Name   Signature
            0       7     0 $this   Lgeny/Generator;
            0       7     1 start   Ljava/lang/Object;
            0       7     2     f   Lscala/Function2;
    MethodParameters:
      Name                           Flags
      $this                          final synthetic
      start                          final
      f                              final

  public default <B extends java.lang.Object> B fold(B, scala.Function2<B, A, B>);
    descriptor: (Ljava/lang/Object;Lscala/Function2;)Ljava/lang/Object;
    flags: (0x0001) ACC_PUBLIC
    Code:
      stack=3, locals=3, args_size=3
         0: aload_0
         1: aload_1
         2: aload_2
         3: invokeinterface #243,  3          // InterfaceMethod foldLeft:(Ljava/lang/Object;Lscala/Function2;)Ljava/lang/Object;
         8: areturn
      LineNumberTable:
        line 76: 0
      LocalVariableTable:
        Start  Length  Slot  Name   Signature
            0       9     0  this   Lgeny/Generator;
            0       9     1 start   Ljava/lang/Object;
            0       9     2     f   Lscala/Function2;
    Signature: #240                         // <B:Ljava/lang/Object;>(TB;Lscala/Function2<TB;TA;TB;>;)TB;
    MethodParameters:
      Name                           Flags
      start                          final
      f                              final

  public static java.lang.Object foldLeft$(geny.Generator, java.lang.Object, scala.Function2);
    descriptor: (Lgeny/Generator;Ljava/lang/Object;Lscala/Function2;)Ljava/lang/Object;
    flags: (0x1009) ACC_PUBLIC, ACC_STATIC, ACC_SYNTHETIC
    Code:
      stack=3, locals=3, args_size=3
         0: aload_0
         1: aload_1
         2: aload_2
         3: invokespecial #243                // InterfaceMethod foldLeft:(Ljava/lang/Object;Lscala/Function2;)Ljava/lang/Object;
         6: areturn
      LineNumberTable:
        line 77: 0
      LocalVariableTable:
        Start  Length  Slot  Name   Signature
            0       7     0 $this   Lgeny/Generator;
            0       7     1 start   Ljava/lang/Object;
            0       7     2     f   Lscala/Function2;
    MethodParameters:
      Name                           Flags
      $this                          final synthetic
      start                          final
      f                              final

  public default <B extends java.lang.Object> B foldLeft(B, scala.Function2<B, A, B>);
    descriptor: (Ljava/lang/Object;Lscala/Function2;)Ljava/lang/Object;
    flags: (0x0001) ACC_PUBLIC
    Code:
      stack=3, locals=4, args_size=3
         0: aload_1
         1: invokestatic  #135                // Method scala/runtime/ObjectRef.create:(Ljava/lang/Object;)Lscala/runtime/ObjectRef;
         4: astore_3
         5: aload_0
         6: aload_3
         7: aload_2
         8: invokedynamic #252,  0            // InvokeDynamic #7:apply:(Lscala/runtime/ObjectRef;Lscala/Function2;)Lscala/Function1;
        13: invokeinterface #116,  2          // InterfaceMethod generate:(Lscala/Function1;)Lgeny/Generator$Action;
        18: pop
        19: aload_3
        20: getfield      #149                // Field scala/runtime/ObjectRef.elem:Ljava/lang/Object;
        23: areturn
      LineNumberTable:
        line 78: 0
        line 79: 5
        line 83: 19
      LocalVariableTable:
        Start  Length  Slot  Name   Signature
            5      18     3 result   Lscala/runtime/ObjectRef;
            0      24     0  this   Lgeny/Generator;
            0      24     1 start   Ljava/lang/Object;
            0      24     2     f   Lscala/Function2;
    Signature: #240                         // <B:Ljava/lang/Object;>(TB;Lscala/Function2<TB;TA;TB;>;)TB;
    MethodParameters:
      Name                           Flags
      start                          final
      f                              final

  public static java.lang.Object reduce$(geny.Generator, scala.Function2);
    descriptor: (Lgeny/Generator;Lscala/Function2;)Ljava/lang/Object;
    flags: (0x1009) ACC_PUBLIC, ACC_STATIC, ACC_SYNTHETIC
    Code:
      stack=2, locals=2, args_size=2
         0: aload_0
         1: aload_1
         2: invokespecial #258                // InterfaceMethod reduce:(Lscala/Function2;)Ljava/lang/Object;
         5: areturn
      LineNumberTable:
        line 87: 0
      LocalVariableTable:
        Start  Length  Slot  Name   Signature
            0       6     0 $this   Lgeny/Generator;
            0       6     1     f   Lscala/Function2;
    MethodParameters:
      Name                           Flags
      $this                          final synthetic
      f                              final

  public default <B extends java.lang.Object> B reduce(scala.Function2<B, A, B>);
    descriptor: (Lscala/Function2;)Ljava/lang/Object;
    flags: (0x0001) ACC_PUBLIC
    Code:
      stack=2, locals=2, args_size=2
         0: aload_0
         1: aload_1
         2: invokeinterface #262,  2          // InterfaceMethod reduceLeft:(Lscala/Function2;)Ljava/lang/Object;
         7: areturn
      LineNumberTable:
        line 87: 0
      LocalVariableTable:
        Start  Length  Slot  Name   Signature
            0       8     0  this   Lgeny/Generator;
            0       8     1     f   Lscala/Function2;
    Signature: #259                         // <B:Ljava/lang/Object;>(Lscala/Function2<TB;TA;TB;>;)TB;
    MethodParameters:
      Name                           Flags
      f                              final

  public static java.lang.Object reduceLeft$(geny.Generator, scala.Function2);
    descriptor: (Lgeny/Generator;Lscala/Function2;)Ljava/lang/Object;
    flags: (0x1009) ACC_PUBLIC, ACC_STATIC, ACC_SYNTHETIC
    Code:
      stack=2, locals=2, args_size=2
         0: aload_0
         1: aload_1
         2: invokespecial #262                // InterfaceMethod reduceLeft:(Lscala/Function2;)Ljava/lang/Object;
         5: areturn
      LineNumberTable:
        line 88: 0
      LocalVariableTable:
        Start  Length  Slot  Name   Signature
            0       6     0 $this   Lgeny/Generator;
            0       6     1     f   Lscala/Function2;
    MethodParameters:
      Name                           Flags
      $this                          final synthetic
      f                              final

  public default <B extends java.lang.Object> B reduceLeft(scala.Function2<B, A, B>);
    descriptor: (Lscala/Function2;)Ljava/lang/Object;
    flags: (0x0001) ACC_PUBLIC
    Code:
      stack=3, locals=3, args_size=2
         0: getstatic     #129                // Field scala/None$.MODULE$:Lscala/None$;
         3: invokestatic  #135                // Method scala/runtime/ObjectRef.create:(Ljava/lang/Object;)Lscala/runtime/ObjectRef;
         6: astore_2
         7: aload_0
         8: aload_2
         9: aload_1
        10: invokedynamic #268,  0            // InvokeDynamic #8:apply:(Lscala/runtime/ObjectRef;Lscala/Function2;)Lscala/Function1;
        15: invokeinterface #116,  2          // InterfaceMethod generate:(Lscala/Function1;)Lgeny/Generator$Action;
        20: pop
        21: aload_2
        22: getfield      #149                // Field scala/runtime/ObjectRef.elem:Ljava/lang/Object;
        25: checkcast     #151                // class scala/Option
        28: invokedynamic #279,  0            // InvokeDynamic #9:apply:()Lscala/Function0;
        33: invokevirtual #283                // Method scala/Option.getOrElse:(Lscala/Function0;)Ljava/lang/Object;
        36: areturn
      LineNumberTable:
        line 89: 0
        line 90: 7
        line 97: 21
        line 98: 28
      LocalVariableTable:
        Start  Length  Slot  Name   Signature
            7      29     2 result   Lscala/runtime/ObjectRef;
            0      37     0  this   Lgeny/Generator;
            0      37     1     f   Lscala/Function2;
    Signature: #259                         // <B:Ljava/lang/Object;>(Lscala/Function2<TB;TA;TB;>;)TB;
    MethodParameters:
      Name                           Flags
      f                              final

  public static geny.Generator filter$(geny.Generator, scala.Function1);
    descriptor: (Lgeny/Generator;Lscala/Function1;)Lgeny/Generator;
    flags: (0x1009) ACC_PUBLIC, ACC_STATIC, ACC_SYNTHETIC
    Code:
      stack=2, locals=2, args_size=2
         0: aload_0
         1: aload_1
         2: invokespecial #290                // InterfaceMethod filter:(Lscala/Function1;)Lgeny/Generator;
         5: areturn
      LineNumberTable:
        line 103: 0
      LocalVariableTable:
        Start  Length  Slot  Name   Signature
            0       6     0 $this   Lgeny/Generator;
            0       6     1  pred   Lscala/Function1;
    MethodParameters:
      Name                           Flags
      $this                          final synthetic
      pred                           final

  public default geny.Generator<A> filter(scala.Function1<A, java.lang.Object>);
    descriptor: (Lscala/Function1;)Lgeny/Generator;
    flags: (0x0001) ACC_PUBLIC
    Code:
      stack=4, locals=2, args_size=2
         0: new           #26                 // class geny/Generator$Filtered
         3: dup
         4: aload_0
         5: aload_1
         6: invokespecial #294                // Method geny/Generator$Filtered."<init>":(Lgeny/Generator;Lscala/Function1;)V
         9: areturn
      LineNumberTable:
        line 103: 0
      LocalVariableTable:
        Start  Length  Slot  Name   Signature
            0      10     0  this   Lgeny/Generator;
            0      10     1  pred   Lscala/Function1;
    Signature: #291                         // (Lscala/Function1<TA;Ljava/lang/Object;>;)Lgeny/Generator<TA;>;
    MethodParameters:
      Name                           Flags
      pred                           final

  public static geny.Generator withFilter$(geny.Generator, scala.Function1);
    descriptor: (Lgeny/Generator;Lscala/Function1;)Lgeny/Generator;
    flags: (0x1009) ACC_PUBLIC, ACC_STATIC, ACC_SYNTHETIC
    Code:
      stack=2, locals=2, args_size=2
         0: aload_0
         1: aload_1
         2: invokespecial #298                // InterfaceMethod withFilter:(Lscala/Function1;)Lgeny/Generator;
         5: areturn
      LineNumberTable:
        line 104: 0
      LocalVariableTable:
        Start  Length  Slot  Name   Signature
            0       6     0 $this   Lgeny/Generator;
            0       6     1  pred   Lscala/Function1;
    MethodParameters:
      Name                           Flags
      $this                          final synthetic
      pred                           final

  public default geny.Generator<A> withFilter(scala.Function1<A, java.lang.Object>);
    descriptor: (Lscala/Function1;)Lgeny/Generator;
    flags: (0x0001) ACC_PUBLIC
    Code:
      stack=4, locals=2, args_size=2
         0: new           #26                 // class geny/Generator$Filtered
         3: dup
         4: aload_0
         5: aload_1
         6: invokespecial #294                // Method geny/Generator$Filtered."<init>":(Lgeny/Generator;Lscala/Function1;)V
         9: areturn
      LineNumberTable:
        line 104: 0
      LocalVariableTable:
        Start  Length  Slot  Name   Signature
            0      10     0  this   Lgeny/Generator;
            0      10     1  pred   Lscala/Function1;
    Signature: #291                         // (Lscala/Function1<TA;Ljava/lang/Object;>;)Lgeny/Generator<TA;>;
    MethodParameters:
      Name                           Flags
      pred                           final

  public static geny.Generator map$(geny.Generator, scala.Function1);
    descriptor: (Lgeny/Generator;Lscala/Function1;)Lgeny/Generator;
    flags: (0x1009) ACC_PUBLIC, ACC_STATIC, ACC_SYNTHETIC
    Code:
      stack=2, locals=2, args_size=2
         0: aload_0
         1: aload_1
         2: invokespecial #303                // InterfaceMethod map:(Lscala/Function1;)Lgeny/Generator;
         5: areturn
      LineNumberTable:
        line 105: 0
      LocalVariableTable:
        Start  Length  Slot  Name   Signature
            0       6     0 $this   Lgeny/Generator;
            0       6     1  func   Lscala/Function1;
    MethodParameters:
      Name                           Flags
      $this                          final synthetic
      func                           final

  public default <B extends java.lang.Object> geny.Generator<B> map(scala.Function1<A, B>);
    descriptor: (Lscala/Function1;)Lgeny/Generator;
    flags: (0x0001) ACC_PUBLIC
    Code:
      stack=4, locals=2, args_size=2
         0: new           #32                 // class geny/Generator$Mapped
         3: dup
         4: aload_0
         5: aload_1
         6: invokespecial #305                // Method geny/Generator$Mapped."<init>":(Lgeny/Generator;Lscala/Function1;)V
         9: areturn
      LineNumberTable:
        line 105: 0
      LocalVariableTable:
        Start  Length  Slot  Name   Signature
            0      10     0  this   Lgeny/Generator;
            0      10     1  func   Lscala/Function1;
    Signature: #304                         // <B:Ljava/lang/Object;>(Lscala/Function1<TA;TB;>;)Lgeny/Generator<TB;>;
    MethodParameters:
      Name                           Flags
      func                           final

  public static geny.Generator flatMap$(geny.Generator, scala.Function1);
    descriptor: (Lgeny/Generator;Lscala/Function1;)Lgeny/Generator;
    flags: (0x1009) ACC_PUBLIC, ACC_STATIC, ACC_SYNTHETIC
    Code:
      stack=2, locals=2, args_size=2
         0: aload_0
         1: aload_1
         2: invokespecial #309                // InterfaceMethod flatMap:(Lscala/Function1;)Lgeny/Generator;
         5: areturn
      LineNumberTable:
        line 106: 0
      LocalVariableTable:
        Start  Length  Slot  Name   Signature
            0       6     0 $this   Lgeny/Generator;
            0       6     1  func   Lscala/Function1;
    MethodParameters:
      Name                           Flags
      $this                          final synthetic
      func                           final

  public default <B extends java.lang.Object> geny.Generator<B> flatMap(scala.Function1<A, geny.Generator<B>>);
    descriptor: (Lscala/Function1;)Lgeny/Generator;
    flags: (0x0001) ACC_PUBLIC
    Code:
      stack=4, locals=2, args_size=2
         0: new           #29                 // class geny/Generator$FlatMapped
         3: dup
         4: aload_0
         5: aload_1
         6: invokespecial #311                // Method geny/Generator$FlatMapped."<init>":(Lgeny/Generator;Lscala/Function1;)V
         9: areturn
      LineNumberTable:
        line 106: 0
      LocalVariableTable:
        Start  Length  Slot  Name   Signature
            0      10     0  this   Lgeny/Generator;
            0      10     1  func   Lscala/Function1;
    Signature: #310                         // <B:Ljava/lang/Object;>(Lscala/Function1<TA;Lgeny/Generator<TB;>;>;)Lgeny/Generator<TB;>;
    MethodParameters:
      Name                           Flags
      func                           final

  public static geny.Generator collect$(geny.Generator, scala.PartialFunction);
    descriptor: (Lgeny/Generator;Lscala/PartialFunction;)Lgeny/Generator;
    flags: (0x1009) ACC_PUBLIC, ACC_STATIC, ACC_SYNTHETIC
    Code:
      stack=2, locals=2, args_size=2
         0: aload_0
         1: aload_1
         2: invokespecial #317                // InterfaceMethod collect:(Lscala/PartialFunction;)Lgeny/Generator;
         5: areturn
      LineNumberTable:
        line 107: 0
      LocalVariableTable:
        Start  Length  Slot  Name   Signature
            0       6     0 $this   Lgeny/Generator;
            0       6     1  func   Lscala/PartialFunction;
    MethodParameters:
      Name                           Flags
      $this                          final synthetic
      func                           final

  public default <B extends java.lang.Object> geny.Generator<B> collect(scala.PartialFunction<A, B>);
    descriptor: (Lscala/PartialFunction;)Lgeny/Generator;
    flags: (0x0001) ACC_PUBLIC
    Code:
      stack=2, locals=2, args_size=2
         0: aload_0
         1: aload_1
         2: invokedynamic #327,  0            // InvokeDynamic #10:apply:(Lscala/PartialFunction;)Lscala/Function1;
         7: invokeinterface #290,  2          // InterfaceMethod filter:(Lscala/Function1;)Lgeny/Generator;
        12: aload_1
        13: invokeinterface #303,  2          // InterfaceMethod map:(Lscala/Function1;)Lgeny/Generator;
        18: areturn
      LineNumberTable:
        line 108: 0
      LocalVariableTable:
        Start  Length  Slot  Name   Signature
            0      19     0  this   Lgeny/Generator;
            0      19     1  func   Lscala/PartialFunction;
    Signature: #319                         // <B:Ljava/lang/Object;>(Lscala/PartialFunction<TA;TB;>;)Lgeny/Generator<TB;>;
    MethodParameters:
      Name                           Flags
      func                           final

  public static scala.Option collectFirst$(geny.Generator, scala.PartialFunction);
    descriptor: (Lgeny/Generator;Lscala/PartialFunction;)Lscala/Option;
    flags: (0x1009) ACC_PUBLIC, ACC_STATIC, ACC_SYNTHETIC
    Code:
      stack=2, locals=2, args_size=2
         0: aload_0
         1: aload_1
         2: invokespecial #333                // InterfaceMethod collectFirst:(Lscala/PartialFunction;)Lscala/Option;
         5: areturn
      LineNumberTable:
        line 109: 0
      LocalVariableTable:
        Start  Length  Slot  Name   Signature
            0       6     0 $this   Lgeny/Generator;
            0       6     1  func   Lscala/PartialFunction;
    MethodParameters:
      Name                           Flags
      $this                          final synthetic
      func                           final

  public default <B extends java.lang.Object> scala.Option<B> collectFirst(scala.PartialFunction<A, B>);
    descriptor: (Lscala/PartialFunction;)Lscala/Option;
    flags: (0x0001) ACC_PUBLIC
    Code:
      stack=2, locals=2, args_size=2
         0: aload_0
         1: aload_1
         2: invokedynamic #339,  0            // InvokeDynamic #11:apply:(Lscala/PartialFunction;)Lscala/Function1;
         7: invokeinterface #290,  2          // InterfaceMethod filter:(Lscala/Function1;)Lgeny/Generator;
        12: aload_1
        13: invokeinterface #303,  2          // InterfaceMethod map:(Lscala/Function1;)Lgeny/Generator;
        18: invokeinterface #343,  1          // InterfaceMethod headOption:()Lscala/Option;
        23: areturn
      LineNumberTable:
        line 110: 0
      LocalVariableTable:
        Start  Length  Slot  Name   Signature
            0      24     0  this   Lgeny/Generator;
            0      24     1  func   Lscala/PartialFunction;
    Signature: #334                         // <B:Ljava/lang/Object;>(Lscala/PartialFunction<TA;TB;>;)Lscala/Option<TB;>;
    MethodParameters:
      Name                           Flags
      func                           final

  public static geny.Generator flatten$(geny.Generator, scala.Function1);
    descriptor: (Lgeny/Generator;Lscala/Function1;)Lgeny/Generator;
    flags: (0x1009) ACC_PUBLIC, ACC_STATIC, ACC_SYNTHETIC
    Code:
      stack=2, locals=2, args_size=2
         0: aload_0
         1: aload_1
         2: invokespecial #347                // InterfaceMethod flatten:(Lscala/Function1;)Lgeny/Generator;
         5: areturn
      LineNumberTable:
        line 112: 0
      LocalVariableTable:
        Start  Length  Slot  Name   Signature
            0       6     0 $this   Lgeny/Generator;
            0       6     1     f   Lscala/Function1;
    MethodParameters:
      Name                           Flags
      $this                          final synthetic
      f                              final

  public default <V$ extends java.lang.Object> geny.Generator<V$> flatten(scala.Function1<A, geny.Generator<V$>>);
    descriptor: (Lscala/Function1;)Lgeny/Generator;
    flags: (0x0001) ACC_PUBLIC
    Code:
      stack=2, locals=2, args_size=2
         0: aload_0
         1: aload_1
         2: invokedynamic #356,  0            // InvokeDynamic #12:apply:(Lscala/Function1;)Lscala/Function1;
         7: invokeinterface #309,  2          // InterfaceMethod flatMap:(Lscala/Function1;)Lgeny/Generator;
        12: areturn
      LineNumberTable:
        line 112: 0
      LocalVariableTable:
        Start  Length  Slot  Name   Signature
            0      13     0  this   Lgeny/Generator;
            0      13     1     f   Lscala/Function1;
    Signature: #348                         // <V$:Ljava/lang/Object;>(Lscala/Function1<TA;Lgeny/Generator<TV$;>;>;)Lgeny/Generator<TV$;>;
    MethodParameters:
      Name                           Flags
      f                              final

  public static geny.Generator slice$(geny.Generator, int, int);
    descriptor: (Lgeny/Generator;II)Lgeny/Generator;
    flags: (0x1009) ACC_PUBLIC, ACC_STATIC, ACC_SYNTHETIC
    Code:
      stack=3, locals=3, args_size=3
         0: aload_0
         1: iload_1
         2: iload_2
         3: invokespecial #363                // InterfaceMethod slice:(II)Lgeny/Generator;
         6: areturn
      LineNumberTable:
        line 113: 0
      LocalVariableTable:
        Start  Length  Slot  Name   Signature
            0       7     0 $this   Lgeny/Generator;
            0       7     1 start   I
            0       7     2   end   I
    MethodParameters:
      Name                           Flags
      $this                          final synthetic
      start                          final
      end                            final

  public default geny.Generator<A> slice(int, int);
    descriptor: (II)Lgeny/Generator;
    flags: (0x0001) ACC_PUBLIC
    Code:
      stack=5, locals=3, args_size=3
         0: new           #38                 // class geny/Generator$Sliced
         3: dup
         4: aload_0
         5: iload_1
         6: iload_2
         7: invokespecial #367                // Method geny/Generator$Sliced."<init>":(Lgeny/Generator;II)V
        10: areturn
      LineNumberTable:
        line 113: 0
      LocalVariableTable:
        Start  Length  Slot  Name   Signature
            0      11     0  this   Lgeny/Generator;
            0      11     1 start   I
            0      11     2   end   I
    Signature: #364                         // (II)Lgeny/Generator<TA;>;
    MethodParameters:
      Name                           Flags
      start                          final
      end                            final

  public static geny.Generator take$(geny.Generator, int);
    descriptor: (Lgeny/Generator;I)Lgeny/Generator;
    flags: (0x1009) ACC_PUBLIC, ACC_STATIC, ACC_SYNTHETIC
    Code:
      stack=2, locals=2, args_size=2
         0: aload_0
         1: iload_1
         2: invokespecial #374                // InterfaceMethod take:(I)Lgeny/Generator;
         5: areturn
      LineNumberTable:
        line 114: 0
      LocalVariableTable:
        Start  Length  Slot  Name   Signature
            0       6     0 $this   Lgeny/Generator;
            0       6     1     n   I
    MethodParameters:
      Name                           Flags
      $this                          final synthetic
      n                              final

  public default geny.Generator<A> take(int);
    descriptor: (I)Lgeny/Generator;
    flags: (0x0001) ACC_PUBLIC
    Code:
      stack=3, locals=2, args_size=2
         0: aload_0
         1: iconst_0
         2: iload_1
         3: invokeinterface #363,  3          // InterfaceMethod slice:(II)Lgeny/Generator;
         8: areturn
      LineNumberTable:
        line 114: 0
      LocalVariableTable:
        Start  Length  Slot  Name   Signature
            0       9     0  this   Lgeny/Generator;
            0       9     1     n   I
    Signature: #375                         // (I)Lgeny/Generator<TA;>;
    MethodParameters:
      Name                           Flags
      n                              final

  public static geny.Generator drop$(geny.Generator, int);
    descriptor: (Lgeny/Generator;I)Lgeny/Generator;
    flags: (0x1009) ACC_PUBLIC, ACC_STATIC, ACC_SYNTHETIC
    Code:
      stack=2, locals=2, args_size=2
         0: aload_0
         1: iload_1
         2: invokespecial #379                // InterfaceMethod drop:(I)Lgeny/Generator;
         5: areturn
      LineNumberTable:
        line 115: 0
      LocalVariableTable:
        Start  Length  Slot  Name   Signature
            0       6     0 $this   Lgeny/Generator;
            0       6     1     n   I
    MethodParameters:
      Name                           Flags
      $this                          final synthetic
      n                              final

  public default geny.Generator<A> drop(int);
    descriptor: (I)Lgeny/Generator;
    flags: (0x0001) ACC_PUBLIC
    Code:
      stack=3, locals=2, args_size=2
         0: aload_0
         1: iload_1
         2: ldc_w         #380                // int 2147483647
         5: invokeinterface #363,  3          // InterfaceMethod slice:(II)Lgeny/Generator;
        10: areturn
      LineNumberTable:
        line 115: 0
      LocalVariableTable:
        Start  Length  Slot  Name   Signature
            0      11     0  this   Lgeny/Generator;
            0      11     1     n   I
    Signature: #375                         // (I)Lgeny/Generator<TA;>;
    MethodParameters:
      Name                           Flags
      n                              final

  public static geny.Generator takeWhile$(geny.Generator, scala.Function1);
    descriptor: (Lgeny/Generator;Lscala/Function1;)Lgeny/Generator;
    flags: (0x1009) ACC_PUBLIC, ACC_STATIC, ACC_SYNTHETIC
    Code:
      stack=2, locals=2, args_size=2
         0: aload_0
         1: aload_1
         2: invokespecial #384                // InterfaceMethod takeWhile:(Lscala/Function1;)Lgeny/Generator;
         5: areturn
      LineNumberTable:
        line 116: 0
      LocalVariableTable:
        Start  Length  Slot  Name   Signature
            0       6     0 $this   Lgeny/Generator;
            0       6     1  pred   Lscala/Function1;
    MethodParameters:
      Name                           Flags
      $this                          final synthetic
      pred                           final

  public default geny.Generator<A> takeWhile(scala.Function1<A, java.lang.Object>);
    descriptor: (Lscala/Function1;)Lgeny/Generator;
    flags: (0x0001) ACC_PUBLIC
    Code:
      stack=4, locals=2, args_size=2
         0: new           #41                 // class geny/Generator$TakeWhile
         3: dup
         4: aload_0
         5: aload_1
         6: invokespecial #385                // Method geny/Generator$TakeWhile."<init>":(Lgeny/Generator;Lscala/Function1;)V
         9: areturn
      LineNumberTable:
        line 116: 0
      LocalVariableTable:
        Start  Length  Slot  Name   Signature
            0      10     0  this   Lgeny/Generator;
            0      10     1  pred   Lscala/Function1;
    Signature: #291                         // (Lscala/Function1<TA;Ljava/lang/Object;>;)Lgeny/Generator<TA;>;
    MethodParameters:
      Name                           Flags
      pred                           final

  public static geny.Generator dropWhile$(geny.Generator, scala.Function1);
    descriptor: (Lgeny/Generator;Lscala/Function1;)Lgeny/Generator;
    flags: (0x1009) ACC_PUBLIC, ACC_STATIC, ACC_SYNTHETIC
    Code:
      stack=2, locals=2, args_size=2
         0: aload_0
         1: aload_1
         2: invokespecial #389                // InterfaceMethod dropWhile:(Lscala/Function1;)Lgeny/Generator;
         5: areturn
      LineNumberTable:
        line 117: 0
      LocalVariableTable:
        Start  Length  Slot  Name   Signature
            0       6     0 $this   Lgeny/Generator;
            0       6     1  pred   Lscala/Function1;
    MethodParameters:
      Name                           Flags
      $this                          final synthetic
      pred                           final

  public default geny.Generator<A> dropWhile(scala.Function1<A, java.lang.Object>);
    descriptor: (Lscala/Function1;)Lgeny/Generator;
    flags: (0x0001) ACC_PUBLIC
    Code:
      stack=4, locals=2, args_size=2
         0: new           #20                 // class geny/Generator$DropWhile
         3: dup
         4: aload_0
         5: aload_1
         6: invokespecial #390                // Method geny/Generator$DropWhile."<init>":(Lgeny/Generator;Lscala/Function1;)V
         9: areturn
      LineNumberTable:
        line 117: 0
      LocalVariableTable:
        Start  Length  Slot  Name   Signature
            0      10     0  this   Lgeny/Generator;
            0      10     1  pred   Lscala/Function1;
    Signature: #291                         // (Lscala/Function1<TA;Ljava/lang/Object;>;)Lgeny/Generator<TA;>;
    MethodParameters:
      Name                           Flags
      pred                           final

  public static geny.Generator zipWithIndex$(geny.Generator);
    descriptor: (Lgeny/Generator;)Lgeny/Generator;
    flags: (0x1009) ACC_PUBLIC, ACC_STATIC, ACC_SYNTHETIC
    Code:
      stack=1, locals=1, args_size=1
         0: aload_0
         1: invokespecial #396                // InterfaceMethod zipWithIndex:()Lgeny/Generator;
         4: areturn
      LineNumberTable:
        line 118: 0
      LocalVariableTable:
        Start  Length  Slot  Name   Signature
            0       5     0 $this   Lgeny/Generator;
    MethodParameters:
      Name                           Flags
      $this                          final synthetic

  public default geny.Generator<scala.Tuple2<A, java.lang.Object>> zipWithIndex();
    descriptor: ()Lgeny/Generator;
    flags: (0x0001) ACC_PUBLIC
    Code:
      stack=3, locals=1, args_size=1
         0: new           #44                 // class geny/Generator$ZipWithIndexed
         3: dup
         4: aload_0
         5: invokespecial #400                // Method geny/Generator$ZipWithIndexed."<init>":(Lgeny/Generator;)V
         8: areturn
      LineNumberTable:
        line 118: 0
      LocalVariableTable:
        Start  Length  Slot  Name   Signature
            0       9     0  this   Lgeny/Generator;
    Signature: #397                         // ()Lgeny/Generator<Lscala/Tuple2<TA;Ljava/lang/Object;>;>;

  public static geny.Generator zip$(geny.Generator, scala.collection.Iterable);
    descriptor: (Lgeny/Generator;Lscala/collection/Iterable;)Lgeny/Generator;
    flags: (0x1009) ACC_PUBLIC, ACC_STATIC, ACC_SYNTHETIC
    Code:
      stack=2, locals=2, args_size=2
         0: aload_0
         1: aload_1
         2: invokespecial #407                // InterfaceMethod zip:(Lscala/collection/Iterable;)Lgeny/Generator;
         5: areturn
      LineNumberTable:
        line 119: 0
      LocalVariableTable:
        Start  Length  Slot  Name   Signature
            0       6     0 $this   Lgeny/Generator;
            0       6     1 other   Lscala/collection/Iterable;
    MethodParameters:
      Name                           Flags
      $this                          final synthetic
      other                          final

  public default <B extends java.lang.Object> geny.Generator<scala.Tuple2<A, B>> zip(scala.collection.Iterable<B>);
    descriptor: (Lscala/collection/Iterable;)Lgeny/Generator;
    flags: (0x0001) ACC_PUBLIC
    Code:
      stack=4, locals=2, args_size=2
         0: new           #47                 // class geny/Generator$Zipped
         3: dup
         4: aload_0
         5: aload_1
         6: invokespecial #412                // Method geny/Generator$Zipped."<init>":(Lgeny/Generator;Lscala/collection/Iterable;)V
         9: areturn
      LineNumberTable:
        line 119: 0
      LocalVariableTable:
        Start  Length  Slot  Name   Signature
            0      10     0  this   Lgeny/Generator;
            0      10     1 other   Lscala/collection/Iterable;
    Signature: #409                         // <B:Ljava/lang/Object;>(Lscala/collection/Iterable<TB;>;)Lgeny/Generator<Lscala/Tuple2<TA;TB;>;>;
    MethodParameters:
      Name                           Flags
      other                          final

  public static geny.Generator $plus$plus$(geny.Generator, geny.Generator);
    descriptor: (Lgeny/Generator;Lgeny/Generator;)Lgeny/Generator;
    flags: (0x1009) ACC_PUBLIC, ACC_STATIC, ACC_SYNTHETIC
    Code:
      stack=2, locals=2, args_size=2
         0: aload_0
         1: aload_1
         2: invokespecial #417                // InterfaceMethod $plus$plus:(Lgeny/Generator;)Lgeny/Generator;
         5: areturn
      LineNumberTable:
        line 120: 0
      LocalVariableTable:
        Start  Length  Slot  Name   Signature
            0       6     0 $this   Lgeny/Generator;
            0       6     1 other   Lgeny/Generator;
    MethodParameters:
      Name                           Flags
      $this                          final synthetic
      other                          final

  public default <B extends java.lang.Object> geny.Generator<B> $plus$plus(geny.Generator<B>);
    descriptor: (Lgeny/Generator;)Lgeny/Generator;
    flags: (0x0001) ACC_PUBLIC
    Code:
      stack=4, locals=2, args_size=2
         0: new           #14                 // class geny/Generator$Concat
         3: dup
         4: aload_0
         5: aload_1
         6: invokespecial #421                // Method geny/Generator$Concat."<init>":(Lgeny/Generator;Lgeny/Generator;)V
         9: areturn
      LineNumberTable:
        line 120: 0
      LocalVariableTable:
        Start  Length  Slot  Name   Signature
            0      10     0  this   Lgeny/Generator;
            0      10     1 other   Lgeny/Generator;
    Signature: #418                         // <B:Ljava/lang/Object;>(Lgeny/Generator<TB;>;)Lgeny/Generator<TB;>;
    MethodParameters:
      Name                           Flags
      other                          final

  public static java.lang.Object head$(geny.Generator);
    descriptor: (Lgeny/Generator;)Ljava/lang/Object;
    flags: (0x1009) ACC_PUBLIC, ACC_STATIC, ACC_SYNTHETIC
    Code:
      stack=1, locals=1, args_size=1
         0: aload_0
         1: invokespecial #426                // InterfaceMethod head:()Ljava/lang/Object;
         4: areturn
      LineNumberTable:
        line 123: 0
      LocalVariableTable:
        Start  Length  Slot  Name   Signature
            0       5     0 $this   Lgeny/Generator;
    MethodParameters:
      Name                           Flags
      $this                          final synthetic

  public default A head();
    descriptor: ()Ljava/lang/Object;
    flags: (0x0001) ACC_PUBLIC
    Code:
      stack=2, locals=1, args_size=1
         0: aload_0
         1: iconst_1
         2: invokeinterface #374,  2          // InterfaceMethod take:(I)Lgeny/Generator;
         7: invokeinterface #431,  1          // InterfaceMethod toSeq:()Lscala/collection/immutable/Seq;
        12: invokeinterface #434,  1          // InterfaceMethod scala/collection/immutable/Seq.head:()Ljava/lang/Object;
        17: areturn
      LineNumberTable:
        line 123: 0
      LocalVariableTable:
        Start  Length  Slot  Name   Signature
            0      18     0  this   Lgeny/Generator;
    Signature: #427                         // ()TA;

  public static scala.Option headOption$(geny.Generator);
    descriptor: (Lgeny/Generator;)Lscala/Option;
    flags: (0x1009) ACC_PUBLIC, ACC_STATIC, ACC_SYNTHETIC
    Code:
      stack=1, locals=1, args_size=1
         0: aload_0
         1: invokespecial #343                // InterfaceMethod headOption:()Lscala/Option;
         4: areturn
      LineNumberTable:
        line 124: 0
      LocalVariableTable:
        Start  Length  Slot  Name   Signature
            0       5     0 $this   Lgeny/Generator;
    MethodParameters:
      Name                           Flags
      $this                          final synthetic

  public default scala.Option<A> headOption();
    descriptor: ()Lscala/Option;
    flags: (0x0001) ACC_PUBLIC
    Code:
      stack=2, locals=1, args_size=1
         0: aload_0
         1: iconst_1
         2: invokeinterface #374,  2          // InterfaceMethod take:(I)Lgeny/Generator;
         7: invokeinterface #431,  1          // InterfaceMethod toSeq:()Lscala/collection/immutable/Seq;
        12: invokeinterface #438,  1          // InterfaceMethod scala/collection/immutable/Seq.headOption:()Lscala/Option;
        17: areturn
      LineNumberTable:
        line 124: 0
      LocalVariableTable:
        Start  Length  Slot  Name   Signature
            0      18     0  this   Lgeny/Generator;
    Signature: #437                         // ()Lscala/Option<TA;>;

  public static scala.collection.mutable.Buffer toBuffer$(geny.Generator);
    descriptor: (Lgeny/Generator;)Lscala/collection/mutable/Buffer;
    flags: (0x1009) ACC_PUBLIC, ACC_STATIC, ACC_SYNTHETIC
    Code:
      stack=1, locals=1, args_size=1
         0: aload_0
         1: invokespecial #444                // InterfaceMethod toBuffer:()Lscala/collection/mutable/Buffer;
         4: areturn
      LineNumberTable:
        line 125: 0
      LocalVariableTable:
        Start  Length  Slot  Name   Signature
            0       5     0 $this   Lgeny/Generator;
    MethodParameters:
      Name                           Flags
      $this                          final synthetic

  public default <B extends java.lang.Object> scala.collection.mutable.Buffer<B> toBuffer();
    descriptor: ()Lscala/collection/mutable/Buffer;
    flags: (0x0001) ACC_PUBLIC
    Code:
      stack=2, locals=2, args_size=1
         0: getstatic     #450                // Field scala/collection/mutable/Buffer$.MODULE$:Lscala/collection/mutable/Buffer$;
         3: invokevirtual #454                // Method scala/collection/mutable/Buffer$.empty:()Lscala/collection/SeqOps;
         6: checkcast     #456                // class scala/collection/mutable/Buffer
         9: astore_1
        10: aload_0
        11: aload_1
        12: invokedynamic #464,  0            // InvokeDynamic #13:apply:(Lscala/collection/mutable/Buffer;)Lscala/Function1;
        17: invokeinterface #90,  2           // InterfaceMethod foreach:(Lscala/Function1;)V
        22: aload_1
        23: areturn
      LineNumberTable:
        line 126: 0
        line 127: 10
        line 128: 22
      LocalVariableTable:
        Start  Length  Slot  Name   Signature
           10      13     1   arr   Lscala/collection/mutable/Buffer;
            0      24     0  this   Lgeny/Generator;
    Signature: #445                         // <B:Ljava/lang/Object;>()Lscala/collection/mutable/Buffer<TB;>;

  public static java.lang.Object toArray$(geny.Generator, scala.reflect.ClassTag);
    descriptor: (Lgeny/Generator;Lscala/reflect/ClassTag;)Ljava/lang/Object;
    flags: (0x1009) ACC_PUBLIC, ACC_STATIC, ACC_SYNTHETIC
    Code:
      stack=2, locals=2, args_size=2
         0: aload_0
         1: aload_1
         2: invokespecial #473                // InterfaceMethod toArray:(Lscala/reflect/ClassTag;)Ljava/lang/Object;
         5: areturn
      LineNumberTable:
        line 131: 0
      LocalVariableTable:
        Start  Length  Slot  Name   Signature
            0       6     0 $this   Lgeny/Generator;
            0       6     1 evidence$1   Lscala/reflect/ClassTag;
    MethodParameters:
      Name                           Flags
      $this                          final synthetic
      evidence$1                     final

  public default <B extends java.lang.Object> java.lang.Object toArray(scala.reflect.ClassTag<B>);
    descriptor: (Lscala/reflect/ClassTag;)Ljava/lang/Object;
    flags: (0x0001) ACC_PUBLIC
    Code:
      stack=2, locals=2, args_size=2
         0: aload_0
         1: invokeinterface #444,  1          // InterfaceMethod toBuffer:()Lscala/collection/mutable/Buffer;
         6: aload_1
         7: invokeinterface #476,  2          // InterfaceMethod scala/collection/mutable/Buffer.toArray:(Lscala/reflect/ClassTag;)Ljava/lang/Object;
        12: areturn
      LineNumberTable:
        line 131: 0
      LocalVariableTable:
        Start  Length  Slot  Name   Signature
            0      13     0  this   Lgeny/Generator;
            0      13     1 evidence$1   Lscala/reflect/ClassTag;
    Signature: #475                         // <B:Ljava/lang/Object;>(Lscala/reflect/ClassTag<TB;>;)Ljava/lang/Object;
    MethodParameters:
      Name                           Flags
      evidence$1                     final

  public static scala.collection.immutable.Seq toSeq$(geny.Generator);
    descriptor: (Lgeny/Generator;)Lscala/collection/immutable/Seq;
    flags: (0x1009) ACC_PUBLIC, ACC_STATIC, ACC_SYNTHETIC
    Code:
      stack=1, locals=1, args_size=1
         0: aload_0
         1: invokespecial #431                // InterfaceMethod toSeq:()Lscala/collection/immutable/Seq;
         4: areturn
      LineNumberTable:
        line 132: 0
      LocalVariableTable:
        Start  Length  Slot  Name   Signature
            0       5     0 $this   Lgeny/Generator;
    MethodParameters:
      Name                           Flags
      $this                          final synthetic

  public default scala.collection.immutable.Seq<A> toSeq();
    descriptor: ()Lscala/collection/immutable/Seq;
    flags: (0x0001) ACC_PUBLIC
    Code:
      stack=1, locals=1, args_size=1
         0: aload_0
         1: invokeinterface #483,  1          // InterfaceMethod toVector:()Lscala/collection/immutable/Vector;
         6: areturn
      LineNumberTable:
        line 132: 0
      LocalVariableTable:
        Start  Length  Slot  Name   Signature
            0       7     0  this   Lgeny/Generator;
    Signature: #479                         // ()Lscala/collection/immutable/Seq<TA;>;

  public static scala.collection.immutable.List toList$(geny.Generator);
    descriptor: (Lgeny/Generator;)Lscala/collection/immutable/List;
    flags: (0x1009) ACC_PUBLIC, ACC_STATIC, ACC_SYNTHETIC
    Code:
      stack=1, locals=1, args_size=1
         0: aload_0
         1: invokespecial #489                // InterfaceMethod toList:()Lscala/collection/immutable/List;
         4: areturn
      LineNumberTable:
        line 133: 0
      LocalVariableTable:
        Start  Length  Slot  Name   Signature
            0       5     0 $this   Lgeny/Generator;
    MethodParameters:
      Name                           Flags
      $this                          final synthetic

  public default scala.collection.immutable.List<A> toList();
    descriptor: ()Lscala/collection/immutable/List;
    flags: (0x0001) ACC_PUBLIC
    Code:
      stack=1, locals=1, args_size=1
         0: aload_0
         1: invokeinterface #444,  1          // InterfaceMethod toBuffer:()Lscala/collection/mutable/Buffer;
         6: invokeinterface #491,  1          // InterfaceMethod scala/collection/mutable/Buffer.toList:()Lscala/collection/immutable/List;
        11: areturn
      LineNumberTable:
        line 133: 0
      LocalVariableTable:
        Start  Length  Slot  Name   Signature
            0      12     0  this   Lgeny/Generator;
    Signature: #490                         // ()Lscala/collection/immutable/List<TA;>;

  public static scala.collection.immutable.Set toSet$(geny.Generator);
    descriptor: (Lgeny/Generator;)Lscala/collection/immutable/Set;
    flags: (0x1009) ACC_PUBLIC, ACC_STATIC, ACC_SYNTHETIC
    Code:
      stack=1, locals=1, args_size=1
         0: aload_0
         1: invokespecial #497                // InterfaceMethod toSet:()Lscala/collection/immutable/Set;
         4: areturn
      LineNumberTable:
        line 134: 0
      LocalVariableTable:
        Start  Length  Slot  Name   Signature
            0       5     0 $this   Lgeny/Generator;
    MethodParameters:
      Name                           Flags
      $this                          final synthetic

  public default <B extends java.lang.Object> scala.collection.immutable.Set<B> toSet();
    descriptor: ()Lscala/collection/immutable/Set;
    flags: (0x0001) ACC_PUBLIC
    Code:
      stack=1, locals=1, args_size=1
         0: aload_0
         1: invokeinterface #444,  1          // InterfaceMethod toBuffer:()Lscala/collection/mutable/Buffer;
         6: invokeinterface #499,  1          // InterfaceMethod scala/collection/mutable/Buffer.toSet:()Lscala/collection/immutable/Set;
        11: areturn
      LineNumberTable:
        line 134: 0
      LocalVariableTable:
        Start  Length  Slot  Name   Signature
            0      12     0  this   Lgeny/Generator;
    Signature: #498                         // <B:Ljava/lang/Object;>()Lscala/collection/immutable/Set<TB;>;

  public static scala.collection.immutable.Vector toVector$(geny.Generator);
    descriptor: (Lgeny/Generator;)Lscala/collection/immutable/Vector;
    flags: (0x1009) ACC_PUBLIC, ACC_STATIC, ACC_SYNTHETIC
    Code:
      stack=1, locals=1, args_size=1
         0: aload_0
         1: invokespecial #483                // InterfaceMethod toVector:()Lscala/collection/immutable/Vector;
         4: areturn
      LineNumberTable:
        line 135: 0
      LocalVariableTable:
        Start  Length  Slot  Name   Signature
            0       5     0 $this   Lgeny/Generator;
    MethodParameters:
      Name                           Flags
      $this                          final synthetic

  public default scala.collection.immutable.Vector<A> toVector();
    descriptor: ()Lscala/collection/immutable/Vector;
    flags: (0x0001) ACC_PUBLIC
    Code:
      stack=1, locals=1, args_size=1
         0: aload_0
         1: invokeinterface #444,  1          // InterfaceMethod toBuffer:()Lscala/collection/mutable/Buffer;
         6: invokeinterface #503,  1          // InterfaceMethod scala/collection/mutable/Buffer.toVector:()Lscala/collection/immutable/Vector;
        11: areturn
      LineNumberTable:
        line 135: 0
      LocalVariableTable:
        Start  Length  Slot  Name   Signature
            0      12     0  this   Lgeny/Generator;
    Signature: #502                         // ()Lscala/collection/immutable/Vector<TA;>;

  public static java.lang.String mkString$(geny.Generator, java.lang.String, java.lang.String, java.lang.String);
    descriptor: (Lgeny/Generator;Ljava/lang/String;Ljava/lang/String;Ljava/lang/String;)Ljava/lang/String;
    flags: (0x1009) ACC_PUBLIC, ACC_STATIC, ACC_SYNTHETIC
    Code:
      stack=4, locals=4, args_size=4
         0: aload_0
         1: aload_1
         2: aload_2
         3: aload_3
         4: invokespecial #510                // InterfaceMethod mkString:(Ljava/lang/String;Ljava/lang/String;Ljava/lang/String;)Ljava/lang/String;
         7: areturn
      LineNumberTable:
        line 136: 0
      LocalVariableTable:
        Start  Length  Slot  Name   Signature
            0       8     0 $this   Lgeny/Generator;
            0       8     1 start   Ljava/lang/String;
            0       8     2   sep   Ljava/lang/String;
            0       8     3   end   Ljava/lang/String;
    MethodParameters:
      Name                           Flags
      $this                          final synthetic
      start                          final
      sep                            final
      end                            final

  public default java.lang.String mkString(java.lang.String, java.lang.String, java.lang.String);
    descriptor: (Ljava/lang/String;Ljava/lang/String;Ljava/lang/String;)Ljava/lang/String;
    flags: (0x0001) ACC_PUBLIC
    Code:
      stack=4, locals=6, args_size=4
         0: new           #513                // class scala/collection/mutable/StringBuilder
         3: dup
         4: invokespecial #516                // Method scala/collection/mutable/StringBuilder."<init>":()V
         7: astore        4
         9: aload         4
        11: aload_1
        12: invokevirtual #520                // Method scala/collection/mutable/StringBuilder.append:(Ljava/lang/String;)Lscala/collection/mutable/StringBuilder;
        15: pop
        16: iconst_1
        17: invokestatic  #525                // Method scala/runtime/BooleanRef.create:(Z)Lscala/runtime/BooleanRef;
        20: astore        5
        22: aload_0
        23: aload         5
        25: aload         4
        27: aload_2
        28: invokedynamic #533,  0            // InvokeDynamic #14:apply:(Lscala/runtime/BooleanRef;Lscala/collection/mutable/StringBuilder;Ljava/lang/String;)Lscala/Function1;
        33: invokeinterface #90,  2           // InterfaceMethod foreach:(Lscala/Function1;)V
        38: aload         4
        40: aload_3
        41: invokevirtual #520                // Method scala/collection/mutable/StringBuilder.append:(Ljava/lang/String;)Lscala/collection/mutable/StringBuilder;
        44: pop
        45: aload         4
        47: invokevirtual #537                // Method scala/collection/mutable/StringBuilder.toString:()Ljava/lang/String;
        50: areturn
      LineNumberTable:
        line 137: 0
        line 138: 9
        line 139: 16
        line 140: 22
        line 147: 38
        line 148: 45
      LocalVariableTable:
        Start  Length  Slot  Name   Signature
            9      41     4    sb   Lscala/collection/mutable/StringBuilder;
           22      28     5 first   Lscala/runtime/BooleanRef;
            0      51     0  this   Lgeny/Generator;
            0      51     1 start   Ljava/lang/String;
            0      51     2   sep   Ljava/lang/String;
            0      51     3   end   Ljava/lang/String;
    MethodParameters:
      Name                           Flags
      start                          final
      sep                            final
      end                            final

  public static java.lang.String mkString$(geny.Generator, java.lang.String);
    descriptor: (Lgeny/Generator;Ljava/lang/String;)Ljava/lang/String;
    flags: (0x1009) ACC_PUBLIC, ACC_STATIC, ACC_SYNTHETIC
    Code:
      stack=2, locals=2, args_size=2
         0: aload_0
         1: aload_1
         2: invokespecial #545                // InterfaceMethod mkString:(Ljava/lang/String;)Ljava/lang/String;
         5: areturn
      LineNumberTable:
        line 150: 0
      LocalVariableTable:
        Start  Length  Slot  Name   Signature
            0       6     0 $this   Lgeny/Generator;
            0       6     1   sep   Ljava/lang/String;
    MethodParameters:
      Name                           Flags
      $this                          final synthetic
      sep                            final

  public default java.lang.String mkString(java.lang.String);
    descriptor: (Ljava/lang/String;)Ljava/lang/String;
    flags: (0x0001) ACC_PUBLIC
    Code:
      stack=4, locals=2, args_size=2
         0: aload_0
         1: ldc_w         #547                // String
         4: aload_1
         5: ldc_w         #547                // String
         8: invokeinterface #510,  4          // InterfaceMethod mkString:(Ljava/lang/String;Ljava/lang/String;Ljava/lang/String;)Ljava/lang/String;
        13: areturn
      LineNumberTable:
        line 150: 0
      LocalVariableTable:
        Start  Length  Slot  Name   Signature
            0      14     0  this   Lgeny/Generator;
            0      14     1   sep   Ljava/lang/String;
    MethodParameters:
      Name                           Flags
      sep                            final

  public static java.lang.String mkString$(geny.Generator);
    descriptor: (Lgeny/Generator;)Ljava/lang/String;
    flags: (0x1009) ACC_PUBLIC, ACC_STATIC, ACC_SYNTHETIC
    Code:
      stack=1, locals=1, args_size=1
         0: aload_0
         1: invokespecial #550                // InterfaceMethod mkString:()Ljava/lang/String;
         4: areturn
      LineNumberTable:
        line 151: 0
      LocalVariableTable:
        Start  Length  Slot  Name   Signature
            0       5     0 $this   Lgeny/Generator;
    MethodParameters:
      Name                           Flags
      $this                          final synthetic

  public default java.lang.String mkString();
    descriptor: ()Ljava/lang/String;
    flags: (0x0001) ACC_PUBLIC
    Code:
      stack=2, locals=1, args_size=1
         0: aload_0
         1: ldc_w         #547                // String
         4: invokeinterface #545,  2          // InterfaceMethod mkString:(Ljava/lang/String;)Ljava/lang/String;
         9: areturn
      LineNumberTable:
        line 151: 0
      LocalVariableTable:
        Start  Length  Slot  Name   Signature
            0      10     0  this   Lgeny/Generator;

  public static java.lang.Object sum$(geny.Generator, scala.math.Numeric);
    descriptor: (Lgeny/Generator;Lscala/math/Numeric;)Ljava/lang/Object;
    flags: (0x1009) ACC_PUBLIC, ACC_STATIC, ACC_SYNTHETIC
    Code:
      stack=2, locals=2, args_size=2
         0: aload_0
         1: aload_1
         2: invokespecial #557                // InterfaceMethod sum:(Lscala/math/Numeric;)Ljava/lang/Object;
         5: areturn
      LineNumberTable:
        line 154: 0
      LocalVariableTable:
        Start  Length  Slot  Name   Signature
            0       6     0 $this   Lgeny/Generator;
            0       6     1   num   Lscala/math/Numeric;
    MethodParameters:
      Name                           Flags
      $this                          final synthetic
      num                            final

  public default <B extends java.lang.Object> B sum(scala.math.Numeric<B>);
    descriptor: (Lscala/math/Numeric;)Ljava/lang/Object;
    flags: (0x0001) ACC_PUBLIC
    Code:
      stack=3, locals=2, args_size=2
         0: aload_0
         1: aload_1
         2: invokeinterface #564,  1          // InterfaceMethod scala/math/Numeric.zero:()Ljava/lang/Object;
         7: aload_1
         8: invokedynamic #573,  0            // InvokeDynamic #15:apply:(Lscala/math/Numeric;)Lscala/Function2;
        13: invokeinterface #243,  3          // InterfaceMethod foldLeft:(Ljava/lang/Object;Lscala/Function2;)Ljava/lang/Object;
        18: areturn
      LineNumberTable:
        line 154: 0
      LocalVariableTable:
        Start  Length  Slot  Name   Signature
            0      19     0  this   Lgeny/Generator;
            0      19     1   num   Lscala/math/Numeric;
    Signature: #559                         // <B:Ljava/lang/Object;>(Lscala/math/Numeric<TB;>;)TB;
    MethodParameters:
      Name                           Flags
      num                            final

  public static java.lang.Object product$(geny.Generator, scala.math.Numeric);
    descriptor: (Lgeny/Generator;Lscala/math/Numeric;)Ljava/lang/Object;
    flags: (0x1009) ACC_PUBLIC, ACC_STATIC, ACC_SYNTHETIC
    Code:
      stack=2, locals=2, args_size=2
         0: aload_0
         1: aload_1
         2: invokespecial #577                // InterfaceMethod product:(Lscala/math/Numeric;)Ljava/lang/Object;
         5: areturn
      LineNumberTable:
        line 156: 0
      LocalVariableTable:
        Start  Length  Slot  Name   Signature
            0       6     0 $this   Lgeny/Generator;
            0       6     1   num   Lscala/math/Numeric;
    MethodParameters:
      Name                           Flags
      $this                          final synthetic
      num                            final

  public default <B extends java.lang.Object> B product(scala.math.Numeric<B>);
    descriptor: (Lscala/math/Numeric;)Ljava/lang/Object;
    flags: (0x0001) ACC_PUBLIC
    Code:
      stack=3, locals=2, args_size=2
         0: aload_0
         1: aload_1
         2: invokeinterface #580,  1          // InterfaceMethod scala/math/Numeric.one:()Ljava/lang/Object;
         7: aload_1
         8: invokedynamic #585,  0            // InvokeDynamic #16:apply:(Lscala/math/Numeric;)Lscala/Function2;
        13: invokeinterface #243,  3          // InterfaceMethod foldLeft:(Ljava/lang/Object;Lscala/Function2;)Ljava/lang/Object;
        18: areturn
      LineNumberTable:
        line 156: 0
      LocalVariableTable:
        Start  Length  Slot  Name   Signature
            0      19     0  this   Lgeny/Generator;
            0      19     1   num   Lscala/math/Numeric;
    Signature: #559                         // <B:Ljava/lang/Object;>(Lscala/math/Numeric<TB;>;)TB;
    MethodParameters:
      Name                           Flags
      num                            final

  public static java.lang.Object min$(geny.Generator, scala.math.Ordering);
    descriptor: (Lgeny/Generator;Lscala/math/Ordering;)Ljava/lang/Object;
    flags: (0x1009) ACC_PUBLIC, ACC_STATIC, ACC_SYNTHETIC
    Code:
      stack=2, locals=2, args_size=2
         0: aload_0
         1: aload_1
         2: invokespecial #592                // InterfaceMethod min:(Lscala/math/Ordering;)Ljava/lang/Object;
         5: areturn
      LineNumberTable:
        line 158: 0
      LocalVariableTable:
        Start  Length  Slot  Name   Signature
            0       6     0 $this   Lgeny/Generator;
            0       6     1   cmp   Lscala/math/Ordering;
    MethodParameters:
      Name                           Flags
      $this                          final synthetic
      cmp                            final

  public default <B extends java.lang.Object> A min(scala.math.Ordering<B>);
    descriptor: (Lscala/math/Ordering;)Ljava/lang/Object;
    flags: (0x0001) ACC_PUBLIC
    Code:
      stack=2, locals=2, args_size=2
         0: aload_0
         1: aload_1
         2: invokedynamic #602,  0            // InvokeDynamic #17:apply:(Lscala/math/Ordering;)Lscala/Function2;
         7: invokeinterface #262,  2          // InterfaceMethod reduceLeft:(Lscala/Function2;)Ljava/lang/Object;
        12: areturn
      LineNumberTable:
        line 159: 0
      LocalVariableTable:
        Start  Length  Slot  Name   Signature
            0      13     0  this   Lgeny/Generator;
            0      13     1   cmp   Lscala/math/Ordering;
    Signature: #594                         // <B:Ljava/lang/Object;>(Lscala/math/Ordering<TB;>;)TA;
    MethodParameters:
      Name                           Flags
      cmp                            final

  public static java.lang.Object max$(geny.Generator, scala.math.Ordering);
    descriptor: (Lgeny/Generator;Lscala/math/Ordering;)Ljava/lang/Object;
    flags: (0x1009) ACC_PUBLIC, ACC_STATIC, ACC_SYNTHETIC
    Code:
      stack=2, locals=2, args_size=2
         0: aload_0
         1: aload_1
         2: invokespecial #606                // InterfaceMethod max:(Lscala/math/Ordering;)Ljava/lang/Object;
         5: areturn
      LineNumberTable:
        line 162: 0
      LocalVariableTable:
        Start  Length  Slot  Name   Signature
            0       6     0 $this   Lgeny/Generator;
            0       6     1   cmp   Lscala/math/Ordering;
    MethodParameters:
      Name                           Flags
      $this                          final synthetic
      cmp                            final

  public default <B extends java.lang.Object> A max(scala.math.Ordering<B>);
    descriptor: (Lscala/math/Ordering;)Ljava/lang/Object;
    flags: (0x0001) ACC_PUBLIC
    Code:
      stack=2, locals=2, args_size=2
         0: aload_0
         1: aload_1
         2: invokedynamic #611,  0            // InvokeDynamic #18:apply:(Lscala/math/Ordering;)Lscala/Function2;
         7: invokeinterface #262,  2          // InterfaceMethod reduceLeft:(Lscala/Function2;)Ljava/lang/Object;
        12: areturn
      LineNumberTable:
        line 163: 0
      LocalVariableTable:
        Start  Length  Slot  Name   Signature
            0      13     0  this   Lgeny/Generator;
            0      13     1   cmp   Lscala/math/Ordering;
    Signature: #594                         // <B:Ljava/lang/Object;>(Lscala/math/Ordering<TB;>;)TA;
    MethodParameters:
      Name                           Flags
      cmp                            final

  public static java.lang.Object maxBy$(geny.Generator, scala.Function1, scala.math.Ordering);
    descriptor: (Lgeny/Generator;Lscala/Function1;Lscala/math/Ordering;)Ljava/lang/Object;
    flags: (0x1009) ACC_PUBLIC, ACC_STATIC, ACC_SYNTHETIC
    Code:
      stack=3, locals=3, args_size=3
         0: aload_0
         1: aload_1
         2: aload_2
         3: invokespecial #617                // InterfaceMethod maxBy:(Lscala/Function1;Lscala/math/Ordering;)Ljava/lang/Object;
         6: areturn
      LineNumberTable:
        line 166: 0
      LocalVariableTable:
        Start  Length  Slot  Name   Signature
            0       7     0 $this   Lgeny/Generator;
            0       7     1     f   Lscala/Function1;
            0       7     2   cmp   Lscala/math/Ordering;
    MethodParameters:
      Name                           Flags
      $this                          final synthetic
      f                              final
      cmp                            final

  public default <B extends java.lang.Object> A maxBy(scala.Function1<A, B>, scala.math.Ordering<B>);
    descriptor: (Lscala/Function1;Lscala/math/Ordering;)Ljava/lang/Object;
    flags: (0x0001) ACC_PUBLIC
    Code:
      stack=6, locals=6, args_size=3
         0: aconst_null
         1: invokestatic  #135                // Method scala/runtime/ObjectRef.create:(Ljava/lang/Object;)Lscala/runtime/ObjectRef;
         4: astore_3
         5: aconst_null
         6: invokestatic  #135                // Method scala/runtime/ObjectRef.create:(Ljava/lang/Object;)Lscala/runtime/ObjectRef;
         9: astore        4
        11: iconst_1
        12: invokestatic  #525                // Method scala/runtime/BooleanRef.create:(Z)Lscala/runtime/BooleanRef;
        15: astore        5
        17: aload_0
        18: aload_1
        19: aload         5
        21: aload_2
        22: aload_3
        23: aload         4
        25: invokedynamic #626,  0            // InvokeDynamic #19:apply:(Lscala/Function1;Lscala/runtime/BooleanRef;Lscala/math/Ordering;Lscala/runtime/ObjectRef;Lscala/runtime/ObjectRef;)Lscala/Function1;
        30: invokeinterface #90,  2           // InterfaceMethod foreach:(Lscala/Function1;)V
        35: aload         4
        37: getfield      #149                // Field scala/runtime/ObjectRef.elem:Ljava/lang/Object;
        40: areturn
      LineNumberTable:
        line 167: 0
        line 168: 5
        line 169: 11
        line 171: 17
        line 179: 35
      LocalVariableTable:
        Start  Length  Slot  Name   Signature
            5      35     3  maxF   Lscala/runtime/ObjectRef;
           11      29     4 maxElem   Lscala/runtime/ObjectRef;
           17      23     5 first   Lscala/runtime/BooleanRef;
            0      41     0  this   Lgeny/Generator;
            0      41     1     f   Lscala/Function1;
            0      41     2   cmp   Lscala/math/Ordering;
    Signature: #618                         // <B:Ljava/lang/Object;>(Lscala/Function1<TA;TB;>;Lscala/math/Ordering<TB;>;)TA;
    MethodParameters:
      Name                           Flags
      f                              final
      cmp                            final

  public static java.lang.Object minBy$(geny.Generator, scala.Function1, scala.math.Ordering);
    descriptor: (Lgeny/Generator;Lscala/Function1;Lscala/math/Ordering;)Ljava/lang/Object;
    flags: (0x1009) ACC_PUBLIC, ACC_STATIC, ACC_SYNTHETIC
    Code:
      stack=3, locals=3, args_size=3
         0: aload_0
         1: aload_1
         2: aload_2
         3: invokespecial #632                // InterfaceMethod minBy:(Lscala/Function1;Lscala/math/Ordering;)Ljava/lang/Object;
         6: areturn
      LineNumberTable:
        line 181: 0
      LocalVariableTable:
        Start  Length  Slot  Name   Signature
            0       7     0 $this   Lgeny/Generator;
            0       7     1     f   Lscala/Function1;
            0       7     2   cmp   Lscala/math/Ordering;
    MethodParameters:
      Name                           Flags
      $this                          final synthetic
      f                              final
      cmp                            final

  public default <B extends java.lang.Object> A minBy(scala.Function1<A, B>, scala.math.Ordering<B>);
    descriptor: (Lscala/Function1;Lscala/math/Ordering;)Ljava/lang/Object;
    flags: (0x0001) ACC_PUBLIC
    Code:
      stack=6, locals=6, args_size=3
         0: aconst_null
         1: invokestatic  #135                // Method scala/runtime/ObjectRef.create:(Ljava/lang/Object;)Lscala/runtime/ObjectRef;
         4: astore_3
         5: aconst_null
         6: invokestatic  #135                // Method scala/runtime/ObjectRef.create:(Ljava/lang/Object;)Lscala/runtime/ObjectRef;
         9: astore        4
        11: iconst_1
        12: invokestatic  #525                // Method scala/runtime/BooleanRef.create:(Z)Lscala/runtime/BooleanRef;
        15: astore        5
        17: aload_0
        18: aload_1
        19: aload         5
        21: aload_2
        22: aload_3
        23: aload         4
        25: invokedynamic #637,  0            // InvokeDynamic #20:apply:(Lscala/Function1;Lscala/runtime/BooleanRef;Lscala/math/Ordering;Lscala/runtime/ObjectRef;Lscala/runtime/ObjectRef;)Lscala/Function1;
        30: invokeinterface #90,  2           // InterfaceMethod foreach:(Lscala/Function1;)V
        35: aload         4
        37: getfield      #149                // Field scala/runtime/ObjectRef.elem:Ljava/lang/Object;
        40: areturn
      LineNumberTable:
        line 182: 0
        line 183: 5
        line 184: 11
        line 186: 17
        line 194: 35
      LocalVariableTable:
        Start  Length  Slot  Name   Signature
            5      35     3  minF   Lscala/runtime/ObjectRef;
           11      29     4 minElem   Lscala/runtime/ObjectRef;
           17      23     5 first   Lscala/runtime/BooleanRef;
            0      41     0  this   Lgeny/Generator;
            0      41     1     f   Lscala/Function1;
            0      41     2   cmp   Lscala/math/Ordering;
    Signature: #618                         // <B:Ljava/lang/Object;>(Lscala/Function1<TA;TB;>;Lscala/math/Ordering<TB;>;)TA;
    MethodParameters:
      Name                           Flags
      f                              final
      cmp                            final

  public static geny.Generator$Continue$ $anonfun$foreach$1(scala.Function1, java.lang.Object);
    descriptor: (Lscala/Function1;Ljava/lang/Object;)Lgeny/Generator$Continue$;
    flags: (0x1009) ACC_PUBLIC, ACC_STATIC, ACC_SYNTHETIC
    Code:
      stack=2, locals=2, args_size=2
         0: aload_0
         1: aload_1
         2: invokeinterface #645,  2          // InterfaceMethod scala/Function1.apply:(Ljava/lang/Object;)Ljava/lang/Object;
         7: pop
         8: getstatic     #648                // Field geny/Generator$Continue$.MODULE$:Lgeny/Generator$Continue$;
        11: areturn
      LineNumberTable:
        line 50: 0
        line 51: 8
      LocalVariableTable:
        Start  Length  Slot  Name   Signature
            0      12     0   f$1   Lscala/Function1;
            0      12     1     x   Ljava/lang/Object;
    MethodParameters:
      Name                           Flags
      f$1                            final
      x                              final

  public static geny.Generator$Action $anonfun$find$1(scala.Function1, scala.runtime.ObjectRef, java.lang.Object);
    descriptor: (Lscala/Function1;Lscala/runtime/ObjectRef;Ljava/lang/Object;)Lgeny/Generator$Action;
    flags: (0x1009) ACC_PUBLIC, ACC_STATIC, ACC_SYNTHETIC
    Code:
      stack=4, locals=3, args_size=3
         0: aload_0
         1: aload_2
         2: invokeinterface #645,  2          // InterfaceMethod scala/Function1.apply:(Ljava/lang/Object;)Ljava/lang/Object;
         7: invokestatic  #655                // Method scala/runtime/BoxesRunTime.unboxToBoolean:(Ljava/lang/Object;)Z
        10: ifne          19
        13: getstatic     #648                // Field geny/Generator$Continue$.MODULE$:Lgeny/Generator$Continue$;
        16: goto          34
        19: aload_1
        20: new           #657                // class scala/Some
        23: dup
        24: aload_2
        25: invokespecial #660                // Method scala/Some."<init>":(Ljava/lang/Object;)V
        28: putfield      #149                // Field scala/runtime/ObjectRef.elem:Ljava/lang/Object;
        31: getstatic     #663                // Field geny/Generator$End$.MODULE$:Lgeny/Generator$End$;
        34: areturn
      StackMapTable: number_of_entries = 2
        frame_type = 19 /* same */
        frame_type = 78 /* same_locals_1_stack_item */
          stack = [ class java/lang/Object ]
      LineNumberTable:
        line 57: 0
        line 59: 19
        line 60: 31
      LocalVariableTable:
        Start  Length  Slot  Name   Signature
            0      35     0   f$2   Lscala/Function1;
            0      35     1 result$1   Lscala/runtime/ObjectRef;
            0      35     2     t   Ljava/lang/Object;
    MethodParameters:
      Name                           Flags
      f$2                            final
      result$1                       final
      t                              final

  public static boolean $anonfun$exists$1(scala.Function1, java.lang.Object);
    descriptor: (Lscala/Function1;Ljava/lang/Object;)Z
    flags: (0x1009) ACC_PUBLIC, ACC_STATIC, ACC_SYNTHETIC
    Code:
      stack=2, locals=2, args_size=2
         0: aload_0
         1: aload_1
         2: invokeinterface #645,  2          // InterfaceMethod scala/Function1.apply:(Ljava/lang/Object;)Ljava/lang/Object;
         7: invokestatic  #655                // Method scala/runtime/BoxesRunTime.unboxToBoolean:(Ljava/lang/Object;)Z
        10: ireturn
      LineNumberTable:
        line 65: 0
      LocalVariableTable:
        Start  Length  Slot  Name   Signature
            0      11     0   f$3   Lscala/Function1;
            0      11     1   x$1   Ljava/lang/Object;
    MethodParameters:
      Name                           Flags
      f$3                            final
      x$1                            final

  public static boolean $anonfun$contains$1(java.lang.Object, java.lang.Object);
    descriptor: (Ljava/lang/Object;Ljava/lang/Object;)Z
    flags: (0x1009) ACC_PUBLIC, ACC_STATIC, ACC_SYNTHETIC
    Code:
      stack=2, locals=2, args_size=2
         0: aload_1
         1: aload_0
         2: invokestatic  #674                // Method scala/runtime/BoxesRunTime.equals:(Ljava/lang/Object;Ljava/lang/Object;)Z
         5: ifeq          12
         8: iconst_1
         9: goto          13
        12: iconst_0
        13: ireturn
      StackMapTable: number_of_entries = 2
        frame_type = 12 /* same */
        frame_type = 64 /* same_locals_1_stack_item */
          stack = [ int ]
      LineNumberTable:
        line 66: 0
      LocalVariableTable:
        Start  Length  Slot  Name   Signature
            0      14     0   a$1   Ljava/lang/Object;
            0      14     1   x$2   Ljava/lang/Object;
    MethodParameters:
      Name                           Flags
      a$1                            final
      x$2                            final

  public static boolean $anonfun$forall$1(scala.Function1, java.lang.Object);
    descriptor: (Lscala/Function1;Ljava/lang/Object;)Z
    flags: (0x1009) ACC_PUBLIC, ACC_STATIC, ACC_SYNTHETIC
    Code:
      stack=2, locals=2, args_size=2
         0: aload_0
         1: aload_1
         2: invokeinterface #645,  2          // InterfaceMethod scala/Function1.apply:(Ljava/lang/Object;)Ljava/lang/Object;
         7: invokestatic  #655                // Method scala/runtime/BoxesRunTime.unboxToBoolean:(Ljava/lang/Object;)Z
        10: ifne          17
        13: iconst_1
        14: goto          18
        17: iconst_0
        18: ireturn
      StackMapTable: number_of_entries = 2
        frame_type = 17 /* same */
        frame_type = 64 /* same_locals_1_stack_item */
          stack = [ int ]
      LineNumberTable:
        line 67: 0
      LocalVariableTable:
        Start  Length  Slot  Name   Signature
            0      19     0   f$4   Lscala/Function1;
            0      19     1   x$3   Ljava/lang/Object;
    MethodParameters:
      Name                           Flags
      f$4                            final
      x$3                            final

  public static geny.Generator$Continue$ $anonfun$count$1(scala.Function1, scala.runtime.IntRef, java.lang.Object);
    descriptor: (Lscala/Function1;Lscala/runtime/IntRef;Ljava/lang/Object;)Lgeny/Generator$Continue$;
    flags: (0x1009) ACC_PUBLIC, ACC_STATIC, ACC_SYNTHETIC
    Code:
      stack=3, locals=3, args_size=3
         0: aload_0
         1: aload_2
         2: invokeinterface #645,  2          // InterfaceMethod scala/Function1.apply:(Ljava/lang/Object;)Ljava/lang/Object;
         7: invokestatic  #655                // Method scala/runtime/BoxesRunTime.unboxToBoolean:(Ljava/lang/Object;)Z
        10: ifeq          26
        13: aload_1
        14: aload_1
        15: getfield      #217                // Field scala/runtime/IntRef.elem:I
        18: iconst_1
        19: iadd
        20: putfield      #217                // Field scala/runtime/IntRef.elem:I
        23: goto          26
        26: getstatic     #648                // Field geny/Generator$Continue$.MODULE$:Lgeny/Generator$Continue$;
        29: areturn
      StackMapTable: number_of_entries = 1
        frame_type = 26 /* same */
      LineNumberTable:
        line 71: 0
        line 72: 26
      LocalVariableTable:
        Start  Length  Slot  Name   Signature
            0      30     0   f$5   Lscala/Function1;
            0      30     1 result$2   Lscala/runtime/IntRef;
            0      30     2     t   Ljava/lang/Object;
    MethodParameters:
      Name                           Flags
      f$5                            final
      result$2                       final
      t                              final

  public static boolean $anonfun$count$default$1$1(java.lang.Object);
    descriptor: (Ljava/lang/Object;)Z
    flags: (0x1009) ACC_PUBLIC, ACC_STATIC, ACC_SYNTHETIC
    Code:
      stack=1, locals=1, args_size=1
         0: iconst_1
         1: ireturn
      LineNumberTable:
        line 68: 0
      LocalVariableTable:
        Start  Length  Slot  Name   Signature
            0       2     0   x$4   Ljava/lang/Object;
    MethodParameters:
      Name                           Flags
      x$4                            final

  public static geny.Generator$Continue$ $anonfun$foldLeft$1(scala.runtime.ObjectRef, scala.Function2, java.lang.Object);
    descriptor: (Lscala/runtime/ObjectRef;Lscala/Function2;Ljava/lang/Object;)Lgeny/Generator$Continue$;
    flags: (0x1009) ACC_PUBLIC, ACC_STATIC, ACC_SYNTHETIC
    Code:
      stack=4, locals=3, args_size=3
         0: aload_0
         1: aload_1
         2: aload_0
         3: getfield      #149                // Field scala/runtime/ObjectRef.elem:Ljava/lang/Object;
         6: aload_2
         7: invokeinterface #687,  3          // InterfaceMethod scala/Function2.apply:(Ljava/lang/Object;Ljava/lang/Object;)Ljava/lang/Object;
        12: putfield      #149                // Field scala/runtime/ObjectRef.elem:Ljava/lang/Object;
        15: getstatic     #648                // Field geny/Generator$Continue$.MODULE$:Lgeny/Generator$Continue$;
        18: areturn
      LineNumberTable:
        line 80: 0
        line 81: 15
      LocalVariableTable:
        Start  Length  Slot  Name   Signature
            0      19     0 result$3   Lscala/runtime/ObjectRef;
            0      19     1   f$6   Lscala/Function2;
            0      19     2     t   Ljava/lang/Object;
    MethodParameters:
      Name                           Flags
      result$3                       final
      f$6                            final
      t                              final

  public static geny.Generator$Continue$ $anonfun$reduceLeft$1(scala.runtime.ObjectRef, scala.Function2, java.lang.Object);
    descriptor: (Lscala/runtime/ObjectRef;Lscala/Function2;Ljava/lang/Object;)Lgeny/Generator$Continue$;
    flags: (0x1009) ACC_PUBLIC, ACC_STATIC, ACC_SYNTHETIC
    Code:
      stack=6, locals=7, args_size=3
         0: aload_0
         1: aload_0
         2: getfield      #149                // Field scala/runtime/ObjectRef.elem:Ljava/lang/Object;
         5: checkcast     #151                // class scala/Option
         8: astore        4
        10: getstatic     #129                // Field scala/None$.MODULE$:Lscala/None$;
        13: aload         4
        15: invokevirtual #691                // Method java/lang/Object.equals:(Ljava/lang/Object;)Z
        18: ifeq          33
        21: new           #657                // class scala/Some
        24: dup
        25: aload_2
        26: invokespecial #660                // Method scala/Some."<init>":(Ljava/lang/Object;)V
        29: astore_3
        30: goto          91
        33: goto          36
        36: aload         4
        38: instanceof    #657                // class scala/Some
        41: ifeq          78
        44: aload         4
        46: checkcast     #657                // class scala/Some
        49: astore        5
        51: aload         5
        53: invokevirtual #694                // Method scala/Some.value:()Ljava/lang/Object;
        56: astore        6
        58: new           #657                // class scala/Some
        61: dup
        62: aload_1
        63: aload         6
        65: aload_2
        66: invokeinterface #687,  3          // InterfaceMethod scala/Function2.apply:(Ljava/lang/Object;Ljava/lang/Object;)Ljava/lang/Object;
        71: invokespecial #660                // Method scala/Some."<init>":(Ljava/lang/Object;)V
        74: astore_3
        75: goto          91
        78: goto          81
        81: new           #696                // class scala/MatchError
        84: dup
        85: aload         4
        87: invokespecial #697                // Method scala/MatchError."<init>":(Ljava/lang/Object;)V
        90: athrow
        91: aload_3
        92: putfield      #149                // Field scala/runtime/ObjectRef.elem:Ljava/lang/Object;
        95: getstatic     #648                // Field geny/Generator$Continue$.MODULE$:Lgeny/Generator$Continue$;
        98: areturn
      StackMapTable: number_of_entries = 5
        frame_type = 255 /* full_frame */
          offset_delta = 33
          locals = [ class scala/runtime/ObjectRef, class scala/Function2, class java/lang/Object, top, class scala/Option ]
          stack = [ class scala/runtime/ObjectRef ]
        frame_type = 66 /* same_locals_1_stack_item */
          stack = [ class scala/runtime/ObjectRef ]
        frame_type = 105 /* same_locals_1_stack_item */
          stack = [ class scala/runtime/ObjectRef ]
        frame_type = 66 /* same_locals_1_stack_item */
          stack = [ class scala/runtime/ObjectRef ]
        frame_type = 255 /* full_frame */
          offset_delta = 9
          locals = [ class scala/runtime/ObjectRef, class scala/Function2, class java/lang/Object, class scala/Some, class scala/Option ]
          stack = [ class scala/runtime/ObjectRef ]
      LineNumberTable:
        line 91: 0
        line 92: 10
        line 93: 36
        line 91: 81
        line 95: 95
      LocalVariableTable:
        Start  Length  Slot  Name   Signature
           58      20     6   old   Ljava/lang/Object;
            0      99     0 result$4   Lscala/runtime/ObjectRef;
            0      99     1   f$7   Lscala/Function2;
            0      99     2     t   Ljava/lang/Object;
    MethodParameters:
      Name                           Flags
      result$4                       final
      f$7                            final
      t                              final

  public static scala.runtime.Nothing$ $anonfun$reduceLeft$2();
    descriptor: ()Lscala/runtime/Nothing$;
    flags: (0x1009) ACC_PUBLIC, ACC_STATIC, ACC_SYNTHETIC
    Code:
      stack=3, locals=0, args_size=0
         0: new           #700                // class java/lang/UnsupportedOperationException
         3: dup
         4: ldc_w         #702                // String empty.reduceLeft
         7: invokespecial #705                // Method java/lang/UnsupportedOperationException."<init>":(Ljava/lang/String;)V
        10: athrow
      LineNumberTable:
        line 98: 0

  public static boolean $anonfun$collect$1(scala.PartialFunction, java.lang.Object);
    descriptor: (Lscala/PartialFunction;Ljava/lang/Object;)Z
    flags: (0x1009) ACC_PUBLIC, ACC_STATIC, ACC_SYNTHETIC
    Code:
      stack=2, locals=2, args_size=2
         0: aload_0
         1: aload_1
         2: invokeinterface #713,  2          // InterfaceMethod scala/PartialFunction.isDefinedAt:(Ljava/lang/Object;)Z
         7: ireturn
      LineNumberTable:
        line 108: 0
      LocalVariableTable:
        Start  Length  Slot  Name   Signature
            0       8     0 func$1   Lscala/PartialFunction;
            0       8     1     x   Ljava/lang/Object;
    MethodParameters:
      Name                           Flags
      func$1                         final
      x                              final

  public static boolean $anonfun$collectFirst$1(scala.PartialFunction, java.lang.Object);
    descriptor: (Lscala/PartialFunction;Ljava/lang/Object;)Z
    flags: (0x1009) ACC_PUBLIC, ACC_STATIC, ACC_SYNTHETIC
    Code:
      stack=2, locals=2, args_size=2
         0: aload_0
         1: aload_1
         2: invokeinterface #713,  2          // InterfaceMethod scala/PartialFunction.isDefinedAt:(Ljava/lang/Object;)Z
         7: ireturn
      LineNumberTable:
        line 110: 0
      LocalVariableTable:
        Start  Length  Slot  Name   Signature
            0       8     0 func$2   Lscala/PartialFunction;
            0       8     1     x   Ljava/lang/Object;
    MethodParameters:
      Name                           Flags
      func$2                         final
      x                              final

  public static geny.Generator $anonfun$flatten$1(scala.Function1, java.lang.Object);
    descriptor: (Lscala/Function1;Ljava/lang/Object;)Lgeny/Generator;
    flags: (0x1009) ACC_PUBLIC, ACC_STATIC, ACC_SYNTHETIC
    Code:
      stack=2, locals=2, args_size=2
         0: aload_0
         1: aload_1
         2: invokeinterface #645,  2          // InterfaceMethod scala/Function1.apply:(Ljava/lang/Object;)Ljava/lang/Object;
         7: checkcast     #2                  // class geny/Generator
        10: areturn
      LineNumberTable:
        line 112: 0
      LocalVariableTable:
        Start  Length  Slot  Name   Signature
            0      11     0   f$8   Lscala/Function1;
            0      11     1     x   Ljava/lang/Object;
    MethodParameters:
      Name                           Flags
      f$8                            final
      x                              final

  public static void $anonfun$toBuffer$1(scala.collection.mutable.Buffer, java.lang.Object);
    descriptor: (Lscala/collection/mutable/Buffer;Ljava/lang/Object;)V
    flags: (0x1009) ACC_PUBLIC, ACC_STATIC, ACC_SYNTHETIC
    Code:
      stack=2, locals=2, args_size=2
         0: aload_0
         1: aload_1
         2: invokeinterface #723,  2          // InterfaceMethod scala/collection/mutable/Buffer.append:(Ljava/lang/Object;)Lscala/collection/mutable/Buffer;
         7: pop
         8: return
      LineNumberTable:
        line 127: 0
      LocalVariableTable:
        Start  Length  Slot  Name   Signature
            0       9     0 arr$1   Lscala/collection/mutable/Buffer;
            0       9     1   x$5   Ljava/lang/Object;
    MethodParameters:
      Name                           Flags
      arr$1                          final
      x$5                            final

  public static void $anonfun$mkString$1(scala.runtime.BooleanRef, scala.collection.mutable.StringBuilder, java.lang.String, java.lang.Object);
    descriptor: (Lscala/runtime/BooleanRef;Lscala/collection/mutable/StringBuilder;Ljava/lang/String;Ljava/lang/Object;)V
    flags: (0x1009) ACC_PUBLIC, ACC_STATIC, ACC_SYNTHETIC
    Code:
      stack=2, locals=4, args_size=4
         0: aload_0
         1: getfield      #731                // Field scala/runtime/BooleanRef.elem:Z
         4: ifne          15
         7: aload_1
         8: aload_2
         9: invokevirtual #520                // Method scala/collection/mutable/StringBuilder.append:(Ljava/lang/String;)Lscala/collection/mutable/StringBuilder;
        12: goto          18
        15: getstatic     #737                // Field scala/runtime/BoxedUnit.UNIT:Lscala/runtime/BoxedUnit;
        18: pop
        19: aload_1
        20: aload_3
        21: invokevirtual #740                // Method scala/collection/mutable/StringBuilder.append:(Ljava/lang/Object;)Lscala/collection/mutable/StringBuilder;
        24: pop
        25: aload_0
        26: iconst_0
        27: putfield      #731                // Field scala/runtime/BooleanRef.elem:Z
        30: return
      StackMapTable: number_of_entries = 2
        frame_type = 15 /* same */
        frame_type = 66 /* same_locals_1_stack_item */
          stack = [ class java/lang/Object ]
      LineNumberTable:
        line 141: 0
        line 142: 7
        line 141: 15
        line 144: 19
        line 145: 25
      LocalVariableTable:
        Start  Length  Slot  Name   Signature
            0      31     0 first$1   Lscala/runtime/BooleanRef;
            0      31     1  sb$1   Lscala/collection/mutable/StringBuilder;
            0      31     2 sep$1   Ljava/lang/String;
            0      31     3     x   Ljava/lang/Object;
    MethodParameters:
      Name                           Flags
      first$1                        final
      sb$1                           final
      sep$1                          final
      x                              final

  public static java.lang.Object $anonfun$sum$1(scala.math.Numeric, java.lang.Object, java.lang.Object);
    descriptor: (Lscala/math/Numeric;Ljava/lang/Object;Ljava/lang/Object;)Ljava/lang/Object;
    flags: (0x1009) ACC_PUBLIC, ACC_STATIC, ACC_SYNTHETIC
    Code:
      stack=3, locals=3, args_size=3
         0: aload_0
         1: aload_1
         2: aload_2
         3: invokeinterface #745,  3          // InterfaceMethod scala/math/Numeric.plus:(Ljava/lang/Object;Ljava/lang/Object;)Ljava/lang/Object;
         8: areturn
      LineNumberTable:
        line 154: 0
      LocalVariableTable:
        Start  Length  Slot  Name   Signature
            0       9     0 num$1   Lscala/math/Numeric;
            0       9     1     x   Ljava/lang/Object;
            0       9     2     y   Ljava/lang/Object;
    MethodParameters:
      Name                           Flags
      num$1                          final
      x                              final
      y                              final

  public static java.lang.Object $anonfun$product$1(scala.math.Numeric, java.lang.Object, java.lang.Object);
    descriptor: (Lscala/math/Numeric;Ljava/lang/Object;Ljava/lang/Object;)Ljava/lang/Object;
    flags: (0x1009) ACC_PUBLIC, ACC_STATIC, ACC_SYNTHETIC
    Code:
      stack=3, locals=3, args_size=3
         0: aload_0
         1: aload_1
         2: aload_2
         3: invokeinterface #749,  3          // InterfaceMethod scala/math/Numeric.times:(Ljava/lang/Object;Ljava/lang/Object;)Ljava/lang/Object;
         8: areturn
      LineNumberTable:
        line 156: 0
      LocalVariableTable:
        Start  Length  Slot  Name   Signature
            0       9     0 num$2   Lscala/math/Numeric;
            0       9     1     x   Ljava/lang/Object;
            0       9     2     y   Ljava/lang/Object;
    MethodParameters:
      Name                           Flags
      num$2                          final
      x                              final
      y                              final

  public static java.lang.Object $anonfun$min$1(scala.math.Ordering, java.lang.Object, java.lang.Object);
    descriptor: (Lscala/math/Ordering;Ljava/lang/Object;Ljava/lang/Object;)Ljava/lang/Object;
    flags: (0x1009) ACC_PUBLIC, ACC_STATIC, ACC_SYNTHETIC
    Code:
      stack=3, locals=3, args_size=3
         0: aload_0
         1: aload_1
         2: aload_2
         3: invokeinterface #755,  3          // InterfaceMethod scala/math/Ordering.lteq:(Ljava/lang/Object;Ljava/lang/Object;)Z
         8: ifeq          15
        11: aload_1
        12: goto          16
        15: aload_2
        16: areturn
      StackMapTable: number_of_entries = 2
        frame_type = 15 /* same */
        frame_type = 64 /* same_locals_1_stack_item */
          stack = [ class java/lang/Object ]
      LineNumberTable:
        line 159: 0
      LocalVariableTable:
        Start  Length  Slot  Name   Signature
            0      17     0 cmp$1   Lscala/math/Ordering;
            0      17     1     x   Ljava/lang/Object;
            0      17     2     y   Ljava/lang/Object;
    MethodParameters:
      Name                           Flags
      cmp$1                          final
      x                              final
      y                              final

  public static java.lang.Object $anonfun$max$1(scala.math.Ordering, java.lang.Object, java.lang.Object);
    descriptor: (Lscala/math/Ordering;Ljava/lang/Object;Ljava/lang/Object;)Ljava/lang/Object;
    flags: (0x1009) ACC_PUBLIC, ACC_STATIC, ACC_SYNTHETIC
    Code:
      stack=3, locals=3, args_size=3
         0: aload_0
         1: aload_1
         2: aload_2
         3: invokeinterface #759,  3          // InterfaceMethod scala/math/Ordering.gteq:(Ljava/lang/Object;Ljava/lang/Object;)Z
         8: ifeq          15
        11: aload_1
        12: goto          16
        15: aload_2
        16: areturn
      StackMapTable: number_of_entries = 2
        frame_type = 15 /* same */
        frame_type = 64 /* same_locals_1_stack_item */
          stack = [ class java/lang/Object ]
      LineNumberTable:
        line 163: 0
      LocalVariableTable:
        Start  Length  Slot  Name   Signature
            0      17     0 cmp$2   Lscala/math/Ordering;
            0      17     1     x   Ljava/lang/Object;
            0      17     2     y   Ljava/lang/Object;
    MethodParameters:
      Name                           Flags
      cmp$2                          final
      x                              final
      y                              final

  public static void $anonfun$maxBy$1(scala.Function1, scala.runtime.BooleanRef, scala.math.Ordering, scala.runtime.ObjectRef, scala.runtime.ObjectRef, java.lang.Object);
    descriptor: (Lscala/Function1;Lscala/runtime/BooleanRef;Lscala/math/Ordering;Lscala/runtime/ObjectRef;Lscala/runtime/ObjectRef;Ljava/lang/Object;)V
    flags: (0x1009) ACC_PUBLIC, ACC_STATIC, ACC_SYNTHETIC
    Code:
      stack=3, locals=7, args_size=6
         0: aload_0
         1: aload         5
         3: invokeinterface #645,  2          // InterfaceMethod scala/Function1.apply:(Ljava/lang/Object;)Ljava/lang/Object;
         8: astore        6
        10: aload_1
        11: getfield      #731                // Field scala/runtime/BooleanRef.elem:Z
        14: ifne          32
        17: aload_2
        18: aload         6
        20: aload_3
        21: getfield      #149                // Field scala/runtime/ObjectRef.elem:Ljava/lang/Object;
        24: invokeinterface #769,  3          // InterfaceMethod scala/math/Ordering.gt:(Ljava/lang/Object;Ljava/lang/Object;)Z
        29: ifeq          53
        32: aload         4
        34: aload         5
        36: putfield      #149                // Field scala/runtime/ObjectRef.elem:Ljava/lang/Object;
        39: aload_3
        40: aload         6
        42: putfield      #149                // Field scala/runtime/ObjectRef.elem:Ljava/lang/Object;
        45: aload_1
        46: iconst_0
        47: putfield      #731                // Field scala/runtime/BooleanRef.elem:Z
        50: goto          53
        53: return
      StackMapTable: number_of_entries = 2
        frame_type = 252 /* append */
          offset_delta = 32
          locals = [ class java/lang/Object ]
        frame_type = 20 /* same */
      LineNumberTable:
        line 172: 0
        line 173: 10
        line 174: 32
        line 175: 39
        line 176: 45
        line 173: 53
      LocalVariableTable:
        Start  Length  Slot  Name   Signature
           10      43     6    fx   Ljava/lang/Object;
            0      54     0   f$9   Lscala/Function1;
            0      54     1 first$2   Lscala/runtime/BooleanRef;
            0      54     2 cmp$3   Lscala/math/Ordering;
            0      54     3 maxF$1   Lscala/runtime/ObjectRef;
            0      54     4 maxElem$1   Lscala/runtime/ObjectRef;
            0      54     5  elem   Ljava/lang/Object;
    MethodParameters:
      Name                           Flags
      f$9                            final
      first$2                        final
      cmp$3                          final
      maxF$1                         final
      maxElem$1                      final
      elem                           final

  public static void $anonfun$minBy$1(scala.Function1, scala.runtime.BooleanRef, scala.math.Ordering, scala.runtime.ObjectRef, scala.runtime.ObjectRef, java.lang.Object);
    descriptor: (Lscala/Function1;Lscala/runtime/BooleanRef;Lscala/math/Ordering;Lscala/runtime/ObjectRef;Lscala/runtime/ObjectRef;Ljava/lang/Object;)V
    flags: (0x1009) ACC_PUBLIC, ACC_STATIC, ACC_SYNTHETIC
    Code:
      stack=3, locals=7, args_size=6
         0: aload_0
         1: aload         5
         3: invokeinterface #645,  2          // InterfaceMethod scala/Function1.apply:(Ljava/lang/Object;)Ljava/lang/Object;
         8: astore        6
        10: aload_1
        11: getfield      #731                // Field scala/runtime/BooleanRef.elem:Z
        14: ifne          32
        17: aload_2
        18: aload         6
        20: aload_3
        21: getfield      #149                // Field scala/runtime/ObjectRef.elem:Ljava/lang/Object;
        24: invokeinterface #779,  3          // InterfaceMethod scala/math/Ordering.lt:(Ljava/lang/Object;Ljava/lang/Object;)Z
        29: ifeq          53
        32: aload         4
        34: aload         5
        36: putfield      #149                // Field scala/runtime/ObjectRef.elem:Ljava/lang/Object;
        39: aload_3
        40: aload         6
        42: putfield      #149                // Field scala/runtime/ObjectRef.elem:Ljava/lang/Object;
        45: aload_1
        46: iconst_0
        47: putfield      #731                // Field scala/runtime/BooleanRef.elem:Z
        50: goto          53
        53: return
      StackMapTable: number_of_entries = 2
        frame_type = 252 /* append */
          offset_delta = 32
          locals = [ class java/lang/Object ]
        frame_type = 20 /* same */
      LineNumberTable:
        line 187: 0
        line 188: 10
        line 189: 32
        line 190: 39
        line 191: 45
        line 188: 53
      LocalVariableTable:
        Start  Length  Slot  Name   Signature
           10      43     6    fx   Ljava/lang/Object;
            0      54     0  f$10   Lscala/Function1;
            0      54     1 first$3   Lscala/runtime/BooleanRef;
            0      54     2 cmp$4   Lscala/math/Ordering;
            0      54     3 minF$1   Lscala/runtime/ObjectRef;
            0      54     4 minElem$1   Lscala/runtime/ObjectRef;
            0      54     5  elem   Ljava/lang/Object;
    MethodParameters:
      Name                           Flags
      f$10                           final
      first$3                        final
      cmp$4                          final
      minF$1                         final
      minElem$1                      final
      elem                           final

  public static void $init$(geny.Generator);
    descriptor: (Lgeny/Generator;)V
    flags: (0x0009) ACC_PUBLIC, ACC_STATIC
    Code:
      stack=0, locals=1, args_size=1
         0: return
      LineNumberTable:
        line 33: 0
      LocalVariableTable:
        Start  Length  Slot  Name   Signature
            0       1     0 $this   Lgeny/Generator;
    MethodParameters:
      Name                           Flags
      $this                          final synthetic

  public static java.lang.Object $anonfun$exists$1$adapted(scala.Function1, java.lang.Object);
    descriptor: (Lscala/Function1;Ljava/lang/Object;)Ljava/lang/Object;
    flags: (0x1009) ACC_PUBLIC, ACC_STATIC, ACC_SYNTHETIC
    Code:
      stack=2, locals=2, args_size=2
         0: aload_0
         1: aload_1
         2: invokestatic  #782                // InterfaceMethod $anonfun$exists$1:(Lscala/Function1;Ljava/lang/Object;)Z
         5: invokestatic  #786                // Method scala/runtime/BoxesRunTime.boxToBoolean:(Z)Ljava/lang/Boolean;
         8: areturn
      LineNumberTable:
        line 65: 0
      LocalVariableTable:
        Start  Length  Slot  Name   Signature
            0       9     0   f$3   Lscala/Function1;
            0       9     1   x$1   Ljava/lang/Object;
    MethodParameters:
      Name                           Flags
      f$3                            final
      x$1                            final

  public static java.lang.Object $anonfun$contains$1$adapted(java.lang.Object, java.lang.Object);
    descriptor: (Ljava/lang/Object;Ljava/lang/Object;)Ljava/lang/Object;
    flags: (0x1009) ACC_PUBLIC, ACC_STATIC, ACC_SYNTHETIC
    Code:
      stack=2, locals=2, args_size=2
         0: aload_0
         1: aload_1
         2: invokestatic  #788                // InterfaceMethod $anonfun$contains$1:(Ljava/lang/Object;Ljava/lang/Object;)Z
         5: invokestatic  #786                // Method scala/runtime/BoxesRunTime.boxToBoolean:(Z)Ljava/lang/Boolean;
         8: areturn
      LineNumberTable:
        line 66: 0
      LocalVariableTable:
        Start  Length  Slot  Name   Signature
            0       9     0   a$1   Ljava/lang/Object;
            0       9     1   x$2   Ljava/lang/Object;
    MethodParameters:
      Name                           Flags
      a$1                            final
      x$2                            final

  public static java.lang.Object $anonfun$forall$1$adapted(scala.Function1, java.lang.Object);
    descriptor: (Lscala/Function1;Ljava/lang/Object;)Ljava/lang/Object;
    flags: (0x1009) ACC_PUBLIC, ACC_STATIC, ACC_SYNTHETIC
    Code:
      stack=2, locals=2, args_size=2
         0: aload_0
         1: aload_1
         2: invokestatic  #790                // InterfaceMethod $anonfun$forall$1:(Lscala/Function1;Ljava/lang/Object;)Z
         5: invokestatic  #786                // Method scala/runtime/BoxesRunTime.boxToBoolean:(Z)Ljava/lang/Boolean;
         8: areturn
      LineNumberTable:
        line 67: 0
      LocalVariableTable:
        Start  Length  Slot  Name   Signature
            0       9     0   f$4   Lscala/Function1;
            0       9     1   x$3   Ljava/lang/Object;
    MethodParameters:
      Name                           Flags
      f$4                            final
      x$3                            final

  public static java.lang.Object $anonfun$count$default$1$1$adapted(java.lang.Object);
    descriptor: (Ljava/lang/Object;)Ljava/lang/Object;
    flags: (0x1009) ACC_PUBLIC, ACC_STATIC, ACC_SYNTHETIC
    Code:
      stack=1, locals=1, args_size=1
         0: aload_0
         1: invokestatic  #792                // InterfaceMethod $anonfun$count$default$1$1:(Ljava/lang/Object;)Z
         4: invokestatic  #786                // Method scala/runtime/BoxesRunTime.boxToBoolean:(Z)Ljava/lang/Boolean;
         7: areturn
      LineNumberTable:
        line 68: 0
      LocalVariableTable:
        Start  Length  Slot  Name   Signature
            0       8     0   x$4   Ljava/lang/Object;
    MethodParameters:
      Name                           Flags
      x$4                            final

  public static java.lang.Object $anonfun$collect$1$adapted(scala.PartialFunction, java.lang.Object);
    descriptor: (Lscala/PartialFunction;Ljava/lang/Object;)Ljava/lang/Object;
    flags: (0x1009) ACC_PUBLIC, ACC_STATIC, ACC_SYNTHETIC
    Code:
      stack=2, locals=2, args_size=2
         0: aload_0
         1: aload_1
         2: invokestatic  #794                // InterfaceMethod $anonfun$collect$1:(Lscala/PartialFunction;Ljava/lang/Object;)Z
         5: invokestatic  #786                // Method scala/runtime/BoxesRunTime.boxToBoolean:(Z)Ljava/lang/Boolean;
         8: areturn
      LineNumberTable:
        line 108: 0
      LocalVariableTable:
        Start  Length  Slot  Name   Signature
            0       9     0 func$1   Lscala/PartialFunction;
            0       9     1     x   Ljava/lang/Object;
    MethodParameters:
      Name                           Flags
      func$1                         final
      x                              final

  public static java.lang.Object $anonfun$collectFirst$1$adapted(scala.PartialFunction, java.lang.Object);
    descriptor: (Lscala/PartialFunction;Ljava/lang/Object;)Ljava/lang/Object;
    flags: (0x1009) ACC_PUBLIC, ACC_STATIC, ACC_SYNTHETIC
    Code:
      stack=2, locals=2, args_size=2
         0: aload_0
         1: aload_1
         2: invokestatic  #796                // InterfaceMethod $anonfun$collectFirst$1:(Lscala/PartialFunction;Ljava/lang/Object;)Z
         5: invokestatic  #786                // Method scala/runtime/BoxesRunTime.boxToBoolean:(Z)Ljava/lang/Boolean;
         8: areturn
      LineNumberTable:
        line 110: 0
      LocalVariableTable:
        Start  Length  Slot  Name   Signature
            0       9     0 func$2   Lscala/PartialFunction;
            0       9     1     x   Ljava/lang/Object;
    MethodParameters:
      Name                           Flags
      func$2                         final
      x                              final

  public static java.lang.Object $anonfun$toBuffer$1$adapted(scala.collection.mutable.Buffer, java.lang.Object);
    descriptor: (Lscala/collection/mutable/Buffer;Ljava/lang/Object;)Ljava/lang/Object;
    flags: (0x1009) ACC_PUBLIC, ACC_STATIC, ACC_SYNTHETIC
    Code:
      stack=2, locals=2, args_size=2
         0: aload_0
         1: aload_1
         2: invokestatic  #798                // InterfaceMethod $anonfun$toBuffer$1:(Lscala/collection/mutable/Buffer;Ljava/lang/Object;)V
         5: getstatic     #737                // Field scala/runtime/BoxedUnit.UNIT:Lscala/runtime/BoxedUnit;
         8: areturn
      LineNumberTable:
        line 127: 0
      LocalVariableTable:
        Start  Length  Slot  Name   Signature
            0       9     0 arr$1   Lscala/collection/mutable/Buffer;
            0       9     1   x$5   Ljava/lang/Object;
    MethodParameters:
      Name                           Flags
      arr$1                          final
      x$5                            final

  public static java.lang.Object $anonfun$mkString$1$adapted(scala.runtime.BooleanRef, scala.collection.mutable.StringBuilder, java.lang.String, java.lang.Object);
    descriptor: (Lscala/runtime/BooleanRef;Lscala/collection/mutable/StringBuilder;Ljava/lang/String;Ljava/lang/Object;)Ljava/lang/Object;
    flags: (0x1009) ACC_PUBLIC, ACC_STATIC, ACC_SYNTHETIC
    Code:
      stack=4, locals=4, args_size=4
         0: aload_0
         1: aload_1
         2: aload_2
         3: aload_3
         4: invokestatic  #800                // InterfaceMethod $anonfun$mkString$1:(Lscala/runtime/BooleanRef;Lscala/collection/mutable/StringBuilder;Ljava/lang/String;Ljava/lang/Object;)V
         7: getstatic     #737                // Field scala/runtime/BoxedUnit.UNIT:Lscala/runtime/BoxedUnit;
        10: areturn
      LineNumberTable:
        line 140: 0
      LocalVariableTable:
        Start  Length  Slot  Name   Signature
            0      11     0 first$1   Lscala/runtime/BooleanRef;
            0      11     1  sb$1   Lscala/collection/mutable/StringBuilder;
            0      11     2 sep$1   Ljava/lang/String;
            0      11     3     x   Ljava/lang/Object;
    MethodParameters:
      Name                           Flags
      first$1                        final
      sb$1                           final
      sep$1                          final
      x                              final

  public static java.lang.Object $anonfun$maxBy$1$adapted(scala.Function1, scala.runtime.BooleanRef, scala.math.Ordering, scala.runtime.ObjectRef, scala.runtime.ObjectRef, java.lang.Object);
    descriptor: (Lscala/Function1;Lscala/runtime/BooleanRef;Lscala/math/Ordering;Lscala/runtime/ObjectRef;Lscala/runtime/ObjectRef;Ljava/lang/Object;)Ljava/lang/Object;
    flags: (0x1009) ACC_PUBLIC, ACC_STATIC, ACC_SYNTHETIC
    Code:
      stack=6, locals=6, args_size=6
         0: aload_0
         1: aload_1
         2: aload_2
         3: aload_3
         4: aload         4
         6: aload         5
         8: invokestatic  #802                // InterfaceMethod $anonfun$maxBy$1:(Lscala/Function1;Lscala/runtime/BooleanRef;Lscala/math/Ordering;Lscala/runtime/ObjectRef;Lscala/runtime/ObjectRef;Ljava/lang/Object;)V
        11: getstatic     #737                // Field scala/runtime/BoxedUnit.UNIT:Lscala/runtime/BoxedUnit;
        14: areturn
      LineNumberTable:
        line 171: 0
      LocalVariableTable:
        Start  Length  Slot  Name   Signature
            0      15     0   f$9   Lscala/Function1;
            0      15     1 first$2   Lscala/runtime/BooleanRef;
            0      15     2 cmp$3   Lscala/math/Ordering;
            0      15     3 maxF$1   Lscala/runtime/ObjectRef;
            0      15     4 maxElem$1   Lscala/runtime/ObjectRef;
            0      15     5  elem   Ljava/lang/Object;
    MethodParameters:
      Name                           Flags
      f$9                            final
      first$2                        final
      cmp$3                          final
      maxF$1                         final
      maxElem$1                      final
      elem                           final

  public static java.lang.Object $anonfun$minBy$1$adapted(scala.Function1, scala.runtime.BooleanRef, scala.math.Ordering, scala.runtime.ObjectRef, scala.runtime.ObjectRef, java.lang.Object);
    descriptor: (Lscala/Function1;Lscala/runtime/BooleanRef;Lscala/math/Ordering;Lscala/runtime/ObjectRef;Lscala/runtime/ObjectRef;Ljava/lang/Object;)Ljava/lang/Object;
    flags: (0x1009) ACC_PUBLIC, ACC_STATIC, ACC_SYNTHETIC
    Code:
      stack=6, locals=6, args_size=6
         0: aload_0
         1: aload_1
         2: aload_2
         3: aload_3
         4: aload         4
         6: aload         5
         8: invokestatic  #804                // InterfaceMethod $anonfun$minBy$1:(Lscala/Function1;Lscala/runtime/BooleanRef;Lscala/math/Ordering;Lscala/runtime/ObjectRef;Lscala/runtime/ObjectRef;Ljava/lang/Object;)V
        11: getstatic     #737                // Field scala/runtime/BoxedUnit.UNIT:Lscala/runtime/BoxedUnit;
        14: areturn
      LineNumberTable:
        line 186: 0
      LocalVariableTable:
        Start  Length  Slot  Name   Signature
            0      15     0  f$10   Lscala/Function1;
            0      15     1 first$3   Lscala/runtime/BooleanRef;
            0      15     2 cmp$4   Lscala/math/Ordering;
            0      15     3 minF$1   Lscala/runtime/ObjectRef;
            0      15     4 minElem$1   Lscala/runtime/ObjectRef;
            0      15     5  elem   Ljava/lang/Object;
    MethodParameters:
      Name                           Flags
      f$10                           final
      first$3                        final
      cmp$4                          final
      minF$1                         final
      minElem$1                      final
      elem                           final

  private static java.lang.Object $deserializeLambda$(java.lang.invoke.SerializedLambda);
    descriptor: (Ljava/lang/invoke/SerializedLambda;)Ljava/lang/Object;
    flags: (0x100a) ACC_PRIVATE, ACC_STATIC, ACC_SYNTHETIC
    Code:
      stack=1, locals=1, args_size=1
         0: aload_0
         1: invokedynamic #816,  0            // InvokeDynamic #21:lambdaDeserialize:(Ljava/lang/invoke/SerializedLambda;)Ljava/lang/Object;
         6: areturn
}
InnerClasses:
  public static #12= #11 of #2;           // Action=class geny/Generator$Action of class geny/Generator
  private static #15= #14 of #2;          // Concat=class geny/Generator$Concat of class geny/Generator
  public static #18= #17 of #2;           // Continue$=class geny/Generator$Continue$ of class geny/Generator
  private static #21= #20 of #2;          // DropWhile=class geny/Generator$DropWhile of class geny/Generator
  public static #24= #23 of #2;           // End$=class geny/Generator$End$ of class geny/Generator
  private static #27= #26 of #2;          // Filtered=class geny/Generator$Filtered of class geny/Generator
  private static #30= #29 of #2;          // FlatMapped=class geny/Generator$FlatMapped of class geny/Generator
  private static #33= #32 of #2;          // Mapped=class geny/Generator$Mapped of class geny/Generator
  private static #36= #35 of #2;          // SelfClosing=class geny/Generator$SelfClosing of class geny/Generator
  private static #39= #38 of #2;          // Sliced=class geny/Generator$Sliced of class geny/Generator
  private static #42= #41 of #2;          // TakeWhile=class geny/Generator$TakeWhile of class geny/Generator
  private static #45= #44 of #2;          // ZipWithIndexed=class geny/Generator$ZipWithIndexed of class geny/Generator
  private static #48= #47 of #2;          // Zipped=class geny/Generator$Zipped of class geny/Generator
  public static final #53= #50 of #52;    // Lookup=class java/lang/invoke/MethodHandles$Lookup of class java/lang/invoke/MethodHandles
Signature: #3                           // <A:Ljava/lang/Object;>Ljava/lang/Object;
SourceFile: "Generator.scala"
RuntimeVisibleAnnotations:
  0: #7(#8=s#9)
    scala.reflect.ScalaSignature(
      bytes="\u0006\u0005\u00155da\u0002<x!\u0003\r\tA\u001f\u0005\b\u0003\u000b\u0001A\u0011AA\u0004\u0011\u001d\ty\u0001\u0001D\u0001\u0003#Aqa!\u0010\u0001\t\u0003\u0019y\u0004C\u0004\u0004F\u0001!\taa\u0012\t\u000f\rM\u0003\u0001\"\u0001\u0004V!91\u0011\f\u0001\u0005\u0002\rm\u0003bBB1\u0001\u0011\u000511\r\u0005\b\u0007O\u0002A\u0011AB5\u0011%\u0019i\u0007AI\u0001\n\u0003\u0019y\u0007C\u0004\u0004\u0006\u0002!\taa\"\t\u000f\ru\u0005\u0001\"\u0001\u0004 \"91q\u0016\u0001\u0005\u0002\rE\u0006bBB`\u0001\u0011\u00051\u0011\u0019\u0005\b\u0007\u001b\u0004A\u0011ABh\u0011\u001d\u0019)\u000e\u0001C\u0001\u0007/Dqaa7\u0001\t\u0003\u0019i\u000eC\u0004\u0004l\u0002!\ta!<\t\u000f\rm\b\u0001\"\u0001\u0004~\"9Aq\u0002\u0001\u0005\u0002\u0011E\u0001b\u0002C\u0010\u0001\u0011\u0005A\u0011\u0005\u0005\b\t_\u0001A\u0011\u0001C\u0019\u0011\u001d!9\u0004\u0001C\u0001\tsAq\u0001b\u0010\u0001\t\u0003!\t\u0005C\u0004\u0005F\u0001!\t\u0001b\u0012\t\u000f\u0011-\u0003\u0001\"\u0001\u0005N!9A\u0011\u000b\u0001\u0005\u0002\u0011M\u0003b\u0002C-\u0001\u0011\u0005A1\f\u0005\b\tW\u0002A\u0011\u0001C7\u0011\u001d!I\b\u0001C\u0001\twBq\u0001\" \u0001\t\u0003!y\bC\u0004\u0005\u0002\u0002!\t\u0001b!\t\u000f\u0011m\u0005\u0001\"\u0001\u0005\u001e\"9A1\u0018\u0001\u0005\u0002\u0011u\u0006b\u0002Cc\u0001\u0011\u0005Aq\u0019\u0005\b\t+\u0004A\u0011\u0001Cl\u0011\u001d!)\u000f\u0001C\u0001\tODq\u0001b<\u0001\t\u0003!\t\u0010C\u0004\u0005p\u0002!\t\u0001b?\t\u000f\u0011=\b\u0001\"\u0001\u0005\u0000\"9Q\u0011\u0001\u0001\u0005\u0002\u0015\r\u0001bBC\u000b\u0001\u0011\u0005Qq\u0003\u0005\b\u000bG\u0001A\u0011AC\u0013\u0011\u001d)9\u0004\u0001C\u0001\u000bsAq!\"\u0012\u0001\t\u0003)9\u0005C\u0004\u0006Z\u0001!\t!b\u0017\b\u000f\u0005eq\u000f#\u0001\u0002\u001c\u00191ao\u001eE\u0001\u0003;Aq!a\b0\t\u0003\t\tCB\u0005\u0002$=\u0002\n1%\t\u0002&\u001d9\u0011QH\u0018\t\u0002\u0005mbaBA\u001b_!\u0005\u0011q\u0007\u0005\b\u0003?\u0019D\u0011AA\u001d\u000f\u001d\tyd\fE\u0001\u0003g1q!!\u000b0\u0011\u0003\tY\u0003C\u0004\u0002 Y\"\t!!\r\t\u000f\u0005\u0005s\u0006\"\u0001\u0002D!9\u0011\u0011N\u0018\u0005\u0004\u0005-\u0004bBAU_\u0011\u0005\u00111\u0016\u0004\u0007\u0003#|C!a5\t\u0015\u0005]6H!A%\u0002\u0013\ti\u000eC\u0004\u0002 m\"\t!a9\t\u000f\u0005=1\b\"\u0001\u0002j\"9\u0011\u0011_\u001e\u0005B\u0005MhA\u0002B\u0003_\u0011\u00119\u0001\u0003\u0006\u0003\u0012\u0001\u0013\t\u0011)A\u0005\u0005\u0017A!Ba\u0005A\u0005\u0003\u0005\u000b\u0011\u0002B\u0006\u0011\u001d\ty\u0002\u0011C\u0001\u0005+Aq!a\u0004A\t\u0003\u0011i\u0002C\u0004\u0002r\u0002#\t%a=\u0007\r\t\rr\u0006\u0002B\u0013\u0011)\u0011\tB\u0012B\u0001B\u0003%!q\u0007\u0005\b\u0003?1E\u0011\u0001B\u001d\u0011\u001d\tyA\u0012C\u0001\u0005\u007fAq!!=G\t\u0003\n\u0019P\u0002\u0004\u0003F=\"!q\t\u0005\u000b\u0005#Y%\u0011!Q\u0001\n\te\u0003B\u0003B\n\u0017\n\u0005\t\u0015!\u0003\u0003\\!9\u0011qD&\u0005\u0002\t\u0005\u0004bBA\b\u0017\u0012\u0005!\u0011\u000e\u0005\b\u0003c\\E\u0011IAz\r\u0019\u0011yg\f\u0003\u0003r!Q!\u0011C)\u0003\u0002\u0003\u0006IA!\u001e\t\u0015\tm\u0014K!A!\u0002\u0013\u0011i\bC\u0004\u0002 E#\tA!\"\t\u000f\u0005=\u0011\u000b\"\u0001\u0003\u000e\"9\u0011\u0011_)\u0005B\u0005MhA\u0002BJ_\u0011\u0011)\n\u0003\u0006\u0003\u0012]\u0013\t\u0011)A\u0005\u0005?C!B!*X\u0005\u0003\u0005\u000b\u0011\u0002BT\u0011\u001d\tyb\u0016C\u0001\u0005SCq!a\u0004X\t\u0003\u0011\t\fC\u0004\u0002r^#\t%a=\u0007\r\t]v\u0006\u0002B]\u0011)\u0011\t\"\u0018B\u0001B\u0003%!1\u0019\u0005\u000b\u0005Kk&\u0011!Q\u0001\n\t%\u0007bBA\u0010;\u0012\u0005!1\u001a\u0005\b\u0003\u001fiF\u0011\u0001Bj\u0011\u001d\t\t0\u0018C!\u0003g4aA!70\t\tm\u0007B\u0003B\tG\n\u0005\t\u0015!\u0003\u0003`\"Q!Q]2\u0003\u0002\u0003\u0006IA!\r\t\u0015\t\u001d8M!A!\u0002\u0013\u0011\t\u0004C\u0004\u0002 \r$\tA!;\t\u000f\u0005=1\r\"\u0001\u0003t\"9\u0011\u0011_2\u0005B\u0005MhA\u0002B}_\u0011\u0011Y\u0010\u0003\u0006\u0003\u0012)\u0014\t\u0011)A\u0005\u0005\u007fD!Ba\u001fk\u0005\u0003\u0005\u000b\u0011BB\u0003\u0011\u001d\tyB\u001bC\u0001\u0007\u000fAq!a\u0004k\t\u0003\u0019y\u0001C\u0004\u0002r*$\t%a=\u0007\r\rUq\u0006BB\f\u0011)\u0011\t\u0002\u001dB\u0001B\u0003%11\u0004\u0005\u000b\u0005w\u0002(\u0011!Q\u0001\n\r\u0005\u0002bBA\u0010a\u0012\u000511\u0005\u0005\b\u0003\u001f\u0001H\u0011AB\u0016\u0011\u001d\t\t\u0010\u001dC!\u0003g\u0014\u0011bR3oKJ\fGo\u001c:\u000b\u0003a\fAaZ3os\u000e\u0001QcA>\u0004:M\u0011\u0001\u0001 \t\u0004{\u0006\u0005Q\"\u0001@\u000b\u0003}\fQa]2bY\u0006L1!a\u0001\u007f\u0005\u0019\te.\u001f*fM\u00061A%\u001b8ji\u0012\"\"!!\u0003\u0011\u0007u\fY!C\u0002\u0002\u000ey\u0014A!\u00168ji\u0006Aq-\u001a8fe\u0006$X\r\u0006\u0003\u0002\u0014\rE\u0002cAA\u000bc9\u0019\u0011q\u0003\u0018\u000e\u0003]\f\u0011bR3oKJ\fGo\u001c:\u0011\u0007\u0005]qf\u0005\u00020y\u00061A(\u001b8jiz\"\"!a\u0007\u0003\r\u0005\u001bG/[8o\'\t\tD0K\u00022mM\u0012\u0001bQ8oi&tW/Z\n\u0005mq\fi\u0003E\u0002\u00020Ej\u0011a\f\u000b\u0003\u0003g\u00012!a\f7\u0005\r)e\u000eZ\n\u0005gq\fi\u0003\u0006\u0002\u0002<A\u0019\u0011qF\u001a\u0002\u0007\u0015sG-\u0001\u0005D_:$\u0018N\\;f\u0003\u0015\t\u0007\u000f\u001d7z+\u0011\t)%!\u0014\u0015\t\u0005\u001d\u0013q\f\t\u0006\u0003/\u0001\u0011\u0011\n\t\u0005\u0003\u0017\ni\u0005\u0004\u0001\u0005\u000f\u0005=\u0003H1\u0001\u0002R\t\tA+\u0005\u0003\u0002T\u0005e\u0003cA?\u0002V%\u0019\u0011q\u000b@\u0003\u000f9{G\u000f[5oOB\u0019Q0a\u0017\n\u0007\u0005ucPA\u0002B]fDq!!\u00199\u0001\u0004\t\u0019\'\u0001\u0002ygB)Q0!\u001a\u0002J%\u0019\u0011q\r@\u0003\u0015q\u0012X\r]3bi\u0016$g(\u0001\u0003ge>lWCBA7\u0003\u0007\u000b)\b\u0006\u0003\u0002p\u0005\u0015F\u0003BA9\u0003o\u0002R!a\u0006\u0001\u0003g\u0002B!a\u0013\u0002v\u00119\u0011qJ\u001dC\u0002\u0005E\u0003bBA=s\u0001\u000f\u00111P\u0001\bG>tg/\u001a:u!\u001di\u0018QPAA\u0003\u001bK1!a \u007f\u0005%1UO\\2uS>t\u0017\u0007\u0005\u0004\u0002L\u0005\r\u00151\u000f\u0003\b\u0003\u000bK$\u0019AAD\u0005\u0005iU\u0003BA)\u0003\u0013#\u0001\"a#\u0002\u0004\n\u0007\u0011\u0011\u000b\u0002\u0002?B1\u0011qRAP\u0003grA!!%\u0002\u001c:!\u00111SAM\u001b\t\t)JC\u0002\u0002\u0018f\fa\u0001\u0010:p_Rt\u0014\"A@\n\u0007\u0005ue0A\u0004qC\u000e\\\u0017mZ3\n\t\u0005\u0005\u00161\u0015\u0002\u0010)J\fg/\u001a:tC\ndWm\u00148dK*\u0019\u0011Q\u0014@\t\u000f\u0005\u001d\u0016\b1\u0001\u0002\u0002\u0006\tA/A\u0006tK247\t\\8tS:<W\u0003BAW\u0003g#B!a,\u00026B)\u0011q\u0003\u0001\u00022B!\u00111JAZ\t\u001d\tyE\u000fb\u0001\u0003#B\u0001\"a.;\t\u0003\u0007\u0011\u0011X\u0001\r[\u0006\\W-\u0013;fe\u0006$xN\u001d\t\u0006{\u0006m\u0016qX\u0005\u0004\u0003{s(\u0001\u0003\u001fcs:\fW.\u001a \u0011\u000fu\f\t-!2\u0002L&\u0019\u00111\u0019@\u0003\rQ+\b\u000f\\33!\u0019\ty)a2\u00022&!\u0011\u0011ZAR\u0005!IE/\u001a:bi>\u0014\b#B?\u0002N\u0006%\u0011bAAh}\nIa)\u001e8di&|g\u000e\r\u0002\f\'\u0016dgm\u00117pg&tw-\u0006\u0003\u0002V\u0006m7\u0003B\u001e}\u0003/\u0004R!a\u0006\u0001\u00033\u0004B!a\u0013\u0002\\\u0012A\u0011qJ\u001e\u0005\u0006\u0004\t\t\u0006E\u0003~\u0003w\u000by\u000eE\u0004~\u0003\u0003\f\t/a3\u0011\r\u0005=\u0015qYAm)\u0011\t)/a:\u0011\u000b\u0005=2(!7\t\u0011\u0005]V\b\"a\u0001\u0003;$B!a\u0005\u0002l\"9\u0011Q\u001e A\u0002\u0005=\u0018!\u00014\u0011\u000fu\fi(!7\u0002\u0014\u0005AAo\\*ue&tw\r\u0006\u0002\u0002vB!\u0011q_A\u0000\u001d\u0011\tI0a?\u0011\u0007\u0005Me0C\u0002\u0002~z\fa\u0001\u0015:fI\u00164\u0017\u0002\u0002B\u0001\u0005\u0007\u0011aa\u0015;sS:<\'bAA\u007f}\n11i\u001c8dCR,BA!\u0003\u0003\u0010M!\u0001\t B\u0006!\u0015\t9\u0002\u0001B\u0007!\u0011\tYEa\u0004\u0005\u0011\u0005=\u0003\t\"b\u0001\u0003#\nQ!\u001b8oKJ\fQa\u001c;iKJ$bAa\u0006\u0003\u001a\tm\u0001#BA\u0018\u0001\n5\u0001b\u0002B\t\u0007\u0002\u0007!1\u0002\u0005\b\u0005\'\u0019\u0005\u0019\u0001B\u0006)\u0011\t\u0019Ba\b\t\u000f\u00055H\t1\u0001\u0003\"A9Q0! \u0003\u000e\u0005M!A\u0004.ja^KG\u000f[%oI\u0016DX\rZ\u000b\u0005\u0005O\u0011yc\u0005\u0003Gy\n%\u0002#BA\f\u0001\t-\u0002cB?\u0002B\n5\"\u0011\u0007\t\u0005\u0003\u0017\u0012y\u0003\u0002\u0005\u0002P\u0019#)\u0019AA)!\ri(1G\u0005\u0004\u0005kq(aA%oiB)\u0011q\u0003\u0001\u0003.Q!!1\bB\u001f!\u0015\tyC\u0012B\u0017\u0011\u001d\u0011\t\u0002\u0013a\u0001\u0005o!B!a\u0005\u0003B!9\u0011Q^%A\u0002\t\r\u0003cB?\u0002~\t-\u00121\u0003\u0002\u00075&\u0004\b/\u001a3\u0016\r\t%#\u0011\u000bB+\'\u0011YEPa\u0013\u0011\u000b\u0005]\u0001A!\u0014\u0011\u000fu\f\tMa\u0014\u0003TA!\u00111\nB)\t!\tye\u0013CC\u0002\u0005E\u0003\u0003BA&\u0005+\"qAa\u0016L\u0005\u0004\t\tFA\u0001W!\u0015\t9\u0002\u0001B(!\u0019\tyI!\u0018\u0003T%!!qLAR\u0005!IE/\u001a:bE2,GC\u0002B2\u0005K\u00129\u0007E\u0004\u00020-\u0013yEa\u0015\t\u000f\tEa\n1\u0001\u0003Z!9!1\u0003(A\u0002\tmC\u0003BA\n\u0005WBq!!<P\u0001\u0004\u0011i\u0007E\u0004~\u0003{\u0012i%a\u0005\u0003\u0011\u0019KG\u000e^3sK\u0012,BAa\u001d\u0003zM!\u0011\u000b B;!\u0015\t9\u0002\u0001B<!\u0011\tYE!\u001f\u0005\u0011\u0005=\u0013\u000b\"b\u0001\u0003#\nA\u0001\u001d:fIB9Q0! \u0003x\t}\u0004cA?\u0003\u0002&\u0019!1\u0011@\u0003\u000f\t{w\u000e\\3b]R1!q\u0011BE\u0005\u0017\u0003R!a\fR\u0005oBqA!\u0005U\u0001\u0004\u0011)\bC\u0004\u0003|Q\u0003\rA! \u0015\t\u0005M!q\u0012\u0005\b\u0003[,\u0006\u0019\u0001BI!\u001di\u0018Q\u0010B<\u0003\'\u0011a!T1qa\u0016$WC\u0002BL\u0005;\u0013\u0019k\u0005\u0003Xy\ne\u0005#BA\f\u0001\tm\u0005\u0003BA&\u0005;#\u0001\"a\u0014X\t\u000b\u0007\u0011\u0011\u000b\t\u0006\u0003/\u0001!\u0011\u0015\t\u0005\u0003\u0017\u0012\u0019\u000bB\u0004\u0003X]\u0013\r!!\u0015\u0002\t\u0019,hn\u0019\t\b{\u0006u$\u0011\u0015BN)\u0019\u0011YK!,\u00030B9\u0011qF,\u0003\u001c\n\u0005\u0006b\u0002B\t5\u0002\u0007!q\u0014\u0005\b\u0005KS\u0006\u0019\u0001BT)\u0011\t\u0019Ba-\t\u000f\u000558\f1\u0001\u00036B9Q0! \u0003\u001c\u0006M!A\u0003$mCRl\u0015\r\u001d9fIV1!1\u0018Ba\u0005\u000f\u001cB!\u0018?\u0003>B)\u0011q\u0003\u0001\u0003@B!\u00111\nBa\t!\ty%\u0018CC\u0002\u0005E\u0003#BA\f\u0001\t\u0015\u0007\u0003BA&\u0005\u000f$qAa\u0016^\u0005\u0004\t\t\u0006E\u0004~\u0003{\u0012)M!0\u0015\r\t5\'q\u001aBi!\u001d\ty#\u0018B`\u0005\u000bDqA!\u0005a\u0001\u0004\u0011\u0019\rC\u0004\u0003&\u0002\u0004\rA!3\u0015\t\u0005M!Q\u001b\u0005\b\u0003[\f\u0007\u0019\u0001Bl!\u001di\u0018Q\u0010B`\u0003\'\u0011aa\u00157jG\u0016$W\u0003\u0002Bo\u0005G\u001cBa\u0019?\u0003`B)\u0011q\u0003\u0001\u0003bB!\u00111\nBr\t!\tye\u0019CC\u0002\u0005E\u0013!B:uCJ$\u0018aA3oIRA!1\u001eBw\u0005_\u0014\t\u0010E\u0003\u00020\r\u0014\t\u000fC\u0004\u0003\u0012\u001d\u0004\rAa8\t\u000f\t\u0015x\r1\u0001\u00032!9!q]4A\u0002\tEB\u0003BA\n\u0005kDq!!<i\u0001\u0004\u00119\u0010E\u0004~\u0003{\u0012\t/a\u0005\u0003\u0013Q\u000b7.Z,iS2,W\u0003\u0002B\u007f\u0007\u0007\u0019BA\u001b?\u0003\u0000B)\u0011q\u0003\u0001\u0004\u0002A!\u00111JB\u0002\t!\tyE\u001bCC\u0002\u0005E\u0003cB?\u0002~\r\u0005!q\u0010\u000b\u0007\u0007\u0013\u0019Ya!\u0004\u0011\u000b\u0005=\"n!\u0001\t\u000f\tEQ\u000e1\u0001\u0003\u0000\"9!1P7A\u0002\r\u0015A\u0003BA\n\u0007#Aq!!<o\u0001\u0004\u0019\u0019\u0002E\u0004~\u0003{\u001a\t!a\u0005\u0003\u0013\u0011\u0013x\u000e],iS2,W\u0003BB\r\u0007?\u0019B\u0001\u001d?\u0004\u001cA)\u0011q\u0003\u0001\u0004\u001eA!\u00111JB\u0010\t!\ty\u0005\u001dCC\u0002\u0005E\u0003cB?\u0002~\ru!q\u0010\u000b\u0007\u0007K\u00199c!\u000b\u0011\u000b\u0005=\u0002o!\b\t\u000f\tE1\u000f1\u0001\u0004\u001c!9!1P:A\u0002\r\u0005B\u0003BA\n\u0007[Aq!!<u\u0001\u0004\u0019y\u0003E\u0004~\u0003{\u001ai\"a\u0005\t\u000f\rM\"\u00011\u0001\u00046\u0005Q\u0001.\u00198eY\u0016LE/Z7\u0011\u000fu\fiha\u000e\u0002\u0014A!\u00111JB\u001d\t!\u0019Y\u0004\u0001CC\u0002\u0005E#!A!\u0002\u000f\u0019|\'/Z1dQR!\u0011\u0011BB!\u0011\u001d\tio\u0001a\u0001\u0007\u0007\u0002r!`A?\u0007o\tI!\u0001\u0003gS:$G\u0003BB%\u0007\u001f\u0002R!`B&\u0007oI1a!\u0014\u007f\u0005\u0019y\u0005\u000f^5p]\"9\u0011Q\u001e\u0003A\u0002\rE\u0003cB?\u0002~\r]\"qP\u0001\u0007KbL7\u000f^:\u0015\t\t}4q\u000b\u0005\b\u0003[,\u0001\u0019AB)\u0003!\u0019wN\u001c;bS:\u001cH\u0003\u0002B@\u0007;Bqaa\u0018\u0007\u0001\u0004\tI&A\u0001b\u0003\u00191wN]1mYR!!qPB3\u0011\u001d\tio\u0002a\u0001\u0007#\nQaY8v]R$BA!\r\u0004l!I\u0011Q\u001e\u0005\u0011\u0002\u0003\u00071\u0011K\u0001\u0010G>,h\u000e\u001e\u0013eK\u001a\fW\u000f\u001c;%cU\u00111\u0011\u000f\u0016\u0005\u0007#\u001a\u0019h\u000b\u0002\u0004vA!1qOBA\u001b\t\u0019IH\u0003\u0003\u0004|\ru\u0014!C;oG\",7m[3e\u0015\r\u0019yH`\u0001\u000bC:tw\u000e^1uS>t\u0017\u0002BBB\u0007s\u0012\u0011#\u001e8dQ\u0016\u001c7.\u001a3WCJL\u0017M\\2f\u0003\u00111w\u000e\u001c3\u0016\t\r%5q\u0012\u000b\u0005\u0007\u0017\u001bY\n\u0006\u0003\u0004\u000e\u000eM\u0005\u0003BA&\u0007\u001f#qa!%\u000b\u0005\u0004\t\tFA\u0001C\u0011\u001d\tiO\u0003a\u0001\u0007+\u0003\u0012\"`BL\u0007\u001b\u001b9d!$\n\u0007\reePA\u0005Gk:\u001cG/[8oe!9!Q\u001d\u0006A\u0002\r5\u0015\u0001\u00034pY\u0012dUM\u001a;\u0016\t\r\u00056q\u0015\u000b\u0005\u0007G\u001bi\u000b\u0006\u0003\u0004&\u000e%\u0006\u0003BA&\u0007O#qa!%\f\u0005\u0004\t\t\u0006C\u0004\u0002n.\u0001\raa+\u0011\u0013u\u001c9j!*\u00048\r\u0015\u0006b\u0002Bs\u0017\u0001\u00071QU\u0001\u0007e\u0016$WoY3\u0016\t\rM6q\u0017\u000b\u0005\u0007k\u001bY\f\u0005\u0003\u0002L\r]FaBBI\u0019\t\u00071\u0011X\t\u0005\u0007o\tI\u0006C\u0004\u0002n2\u0001\ra!0\u0011\u0013u\u001c9j!.\u00048\rU\u0016A\u0003:fIV\u001cW\rT3giV!11YBd)\u0011\u0019)m!3\u0011\t\u0005-3q\u0019\u0003\b\u0007#k!\u0019AB]\u0011\u001d\ti/\u0004a\u0001\u0007\u0017\u0004\u0012\"`BL\u0007\u000b\u001c9d!2\u0002\r\u0019LG\u000e^3s)\u0011\u0019\tna5\u0011\u000b\u0005]\u0001aa\u000e\t\u000f\tmd\u00021\u0001\u0004R\u0005Qq/\u001b;i\r&dG/\u001a:\u0015\t\rE7\u0011\u001c\u0005\b\u0005wz\u0001\u0019AB)\u0003\ri\u0017\r]\u000b\u0005\u0007?\u001c)\u000f\u0006\u0003\u0004b\u000e\u001d\b#BA\f\u0001\r\r\b\u0003BA&\u0007K$qa!%\u0011\u0005\u0004\t\t\u0006C\u0004\u0003&B\u0001\ra!;\u0011\u000fu\fiha\u000e\u0004d\u00069a\r\\1u\u001b\u0006\u0004X\u0003BBx\u0007k$Ba!=\u0004xB)\u0011q\u0003\u0001\u0004tB!\u00111JB{\t\u001d\u0019\t*\u0005b\u0001\u0003#BqA!*\u0012\u0001\u0004\u0019I\u0010E\u0004~\u0003{\u001a9d!=\u0002\u000f\r|G\u000e\\3diV!1q C\u0003)\u0011!\t\u0001b\u0002\u0011\u000b\u0005]\u0001\u0001b\u0001\u0011\t\u0005-CQ\u0001\u0003\b\u0007#\u0013\"\u0019AA)\u0011\u001d\u0011)K\u0005a\u0001\t\u0013\u0001r! C\u0006\u0007o!\u0019!C\u0002\u0005\u000ey\u0014q\u0002U1si&\fGNR;oGRLwN\\\u0001\rG>dG.Z2u\r&\u00148\u000f^\u000b\u0005\t\'!I\u0002\u0006\u0003\u0005\u0016\u0011m\u0001#B?\u0004L\u0011]\u0001\u0003BA&\t3!qa!%\u0014\u0005\u0004\t\t\u0006C\u0004\u0003&N\u0001\r\u0001\"\b\u0011\u000fu$Yaa\u000e\u0005\u0018\u00059a\r\\1ui\u0016tW\u0003\u0002C\u0012\tS!B\u0001\"\n\u0005,A)\u0011q\u0003\u0001\u0005(A!\u00111\nC\u0015\t\u001d\u00119\u0006\u0006b\u0001\u0003#Bq!!<\u0015\u0001\b!i\u0003E\u0004~\u0003{\u001a9\u0004\"\n\u0002\u000bMd\u0017nY3\u0015\r\rEG1\u0007C\u001b\u0011\u001d\u0011)/\u0006a\u0001\u0005cAqAa:\u0016\u0001\u0004\u0011\t$\u0001\u0003uC.,G\u0003BBi\twAq\u0001\"\u0010\u0017\u0001\u0004\u0011\t$A\u0001o\u0003\u0011!\'o\u001c9\u0015\t\rEG1\t\u0005\b\t{9\u0002\u0019\u0001B\u0019\u0003%!\u0018m[3XQ&dW\r\u0006\u0003\u0004R\u0012%\u0003b\u0002B>1\u0001\u00071\u0011K\u0001\nIJ|\u0007o\u00165jY\u0016$Ba!5\u0005P!9!1P\rA\u0002\rE\u0013\u0001\u0004>ja^KG\u000f[%oI\u0016DXC\u0001C+!\u0015\t9\u0002\u0001C,!\u001di\u0018\u0011YB\u001c\u0005c\t1A_5q+\u0011!i\u0006\"\u001a\u0015\t\u0011}Cq\r\t\u0006\u0003/\u0001A\u0011\r\t\b{\u0006\u00057q\u0007C2!\u0011\tY\u0005\"\u001a\u0005\u000f\rE5D1\u0001\u0002R!9!1C\u000eA\u0002\u0011%\u0004CBAH\u0005;\"\u0019\'\u0001\u0006%a2,8\u000f\n9mkN,B\u0001b\u001c\u0005vQ!A\u0011\u000fC<!\u0015\t9\u0002\u0001C:!\u0011\tY\u0005\"\u001e\u0005\u000f\rEED1\u0001\u0004:\"9!1\u0003\u000fA\u0002\u0011E\u0014\u0001\u00025fC\u0012,\"aa\u000e\u0002\u0015!,\u0017\rZ(qi&|g.\u0006\u0002\u0004J\u0005AAo\u001c\"vM\u001a,\'/\u0006\u0003\u0005\u0006\u0012eUC\u0001CD!\u0019!I\tb%\u0005\u00186\u0011A1\u0012\u0006\u0005\t\u001b#y)A\u0004nkR\f\'\r\\3\u000b\u0007\u0011Ee0\u0001\u0006d_2dWm\u0019;j_:LA\u0001\"&\u0005\f\n1!)\u001e4gKJ\u0004B!a\u0013\u0005\u001a\u001291\u0011S\u0010C\u0002\re\u0016a\u0002;p\u0003J\u0014\u0018-_\u000b\u0005\t?#I\u000b\u0006\u0003\u0005\"\u0012-\u0006#B?\u0005$\u0012\u001d\u0016b\u0001CS}\n)\u0011I\u001d:bsB!\u00111\nCU\t\u001d\u0019\t\n\tb\u0001\u0007sC\u0011\u0002\",!\u0003\u0003\u0005\u001d\u0001b,\u0002\u0015\u00154\u0018\u000eZ3oG\u0016$\u0013\u0007\u0005\u0004\u00052\u0012]FqU\u0007\u0003\tgS1\u0001\".\u007f\u0003\u001d\u0011XM\u001a7fGRLA\u0001\"/\u00054\nA1\t\\1tgR\u000bw-A\u0003u_N+\u0017/\u0006\u0002\u0005@B1\u0011q\u0012Ca\u0007oIA\u0001b1\u0002$\n\u00191+Z9\u0002\rQ|G*[:u+\t!I\r\u0005\u0004\u0005L\u0012E7qG\u0007\u0003\t\u001bTA\u0001b4\u0005\u0010\u0006I\u0011.\\7vi\u0006\u0014G.Z\u0005\u0005\t\'$iM\u0001\u0003MSN$\u0018!\u0002;p\'\u0016$X\u0003\u0002Cm\tG,\"\u0001b7\u0011\r\u0011-GQ\u001cCq\u0013\u0011!y\u000e\"4\u0003\u0007M+G\u000f\u0005\u0003\u0002L\u0011\rHaBBIG\t\u00071\u0011X\u0001\ti>4Vm\u0019;peV\u0011A\u0011\u001e\t\u0007\t\u0017$Yoa\u000e\n\t\u00115HQ\u001a\u0002\u0007-\u0016\u001cGo\u001c:\u0002\u00115\\7\u000b\u001e:j]\u001e$\u0002\"!>\u0005t\u0012UH\u0011 \u0005\b\u0005K,\u0003\u0019AA{\u0011\u001d!90\na\u0001\u0003k\f1a]3q\u0011\u001d\u00119/\na\u0001\u0003k$B!!>\u0005~\"9Aq\u001f\u0014A\u0002\u0005UXCAA{\u0003\r\u0019X/\\\u000b\u0005\u000b\u000b)I\u0001\u0006\u0003\u0006\b\u0015-\u0001\u0003BA&\u000b\u0013!qa!%)\u0005\u0004\u0019I\fC\u0004\u0006\u000e!\u0002\u001d!b\u0004\u0002\u00079,X\u000e\u0005\u0004\u0002\u0010\u0016EQqA\u0005\u0005\u000b\'\t\u0019KA\u0004Ok6,\'/[2\u0002\u000fA\u0014x\u000eZ;diV!Q\u0011DC\u000f)\u0011)Y\"b\b\u0011\t\u0005-SQ\u0004\u0003\b\u0007#K#\u0019AB]\u0011\u001d)i!\u000ba\u0002\u000bC\u0001b!a$\u0006\u0012\u0015m\u0011aA7j]V!QqEC\u001b)\u0011\u00199$\"\u000b\t\u000f\u0015-\"\u0006q\u0001\u0006.\u0005\u00191-\u001c9\u0011\r\u0005=UqFC\u001a\u0013\u0011)\t$a)\u0003\u0011=\u0013H-\u001a:j]\u001e\u0004B!a\u0013\u00066\u001191\u0011\u0013\u0016C\u0002\re\u0016aA7bqV!Q1HC\")\u0011\u00199$\"\u0010\t\u000f\u0015-2\u0006q\u0001\u0006@A1\u0011qRC\u0018\u000b\u0003\u0002B!a\u0013\u0006D\u001191\u0011S\u0016C\u0002\re\u0016!B7bq\nKX\u0003BC%\u000b\'\"B!b\u0013\u0006VQ!1qGC\'\u0011\u001d)Y\u0003\fa\u0002\u000b\u001f\u0002b!a$\u00060\u0015E\u0003\u0003BA&\u000b\'\"qa!%-\u0005\u0004\t\t\u0006C\u0004\u0002n2\u0002\r!b\u0016\u0011\u000fu\fiha\u000e\u0006R\u0005)Q.\u001b8CsV!QQLC4)\u0011)y&\"\u001b\u0015\t\r]R\u0011\r\u0005\b\u000bWi\u00039AC2!\u0019\ty)b\f\u0006fA!\u00111JC4\t\u001d\u0019\t*\fb\u0001\u0003#Bq!!<.\u0001\u0004)Y\u0007E\u0004~\u0003{\u001a9$\"\u001a"
    )
BootstrapMethods:
  0: #111 REF_invokeStatic java/lang/invoke/LambdaMetafactory.altMetafactory:(Ljava/lang/invoke/MethodHandles$Lookup;Ljava/lang/String;Ljava/lang/invoke/MethodType;[Ljava/lang/Object;)Ljava/lang/invoke/CallSite;
    Method arguments:
      #95 (Ljava/lang/Object;)Ljava/lang/Object;
      #100 REF_invokeStatic geny/Generator.$anonfun$foreach$1:(Lscala/Function1;Ljava/lang/Object;)Lgeny/Generator$Continue$;
      #102 (Ljava/lang/Object;)Lgeny/Generator$Continue$;
      #103 5
      #104 1
      #102 (Ljava/lang/Object;)Lgeny/Generator$Continue$;
  1: #111 REF_invokeStatic java/lang/invoke/LambdaMetafactory.altMetafactory:(Ljava/lang/invoke/MethodHandles$Lookup;Ljava/lang/String;Ljava/lang/invoke/MethodType;[Ljava/lang/Object;)Ljava/lang/invoke/CallSite;
    Method arguments:
      #95 (Ljava/lang/Object;)Ljava/lang/Object;
      #140 REF_invokeStatic geny/Generator.$anonfun$find$1:(Lscala/Function1;Lscala/runtime/ObjectRef;Ljava/lang/Object;)Lgeny/Generator$Action;
      #142 (Ljava/lang/Object;)Lgeny/Generator$Action;
      #103 5
      #104 1
      #142 (Ljava/lang/Object;)Lgeny/Generator$Action;
  2: #111 REF_invokeStatic java/lang/invoke/LambdaMetafactory.altMetafactory:(Ljava/lang/invoke/MethodHandles$Lookup;Ljava/lang/String;Ljava/lang/invoke/MethodType;[Ljava/lang/Object;)Ljava/lang/invoke/CallSite;
    Method arguments:
      #95 (Ljava/lang/Object;)Ljava/lang/Object;
      #165 REF_invokeStatic geny/Generator.$anonfun$exists$1$adapted:(Lscala/Function1;Ljava/lang/Object;)Ljava/lang/Object;
      #95 (Ljava/lang/Object;)Ljava/lang/Object;
      #104 1
  3: #111 REF_invokeStatic java/lang/invoke/LambdaMetafactory.altMetafactory:(Ljava/lang/invoke/MethodHandles$Lookup;Ljava/lang/String;Ljava/lang/invoke/MethodType;[Ljava/lang/Object;)Ljava/lang/invoke/CallSite;
    Method arguments:
      #95 (Ljava/lang/Object;)Ljava/lang/Object;
      #182 REF_invokeStatic geny/Generator.$anonfun$contains$1$adapted:(Ljava/lang/Object;Ljava/lang/Object;)Ljava/lang/Object;
      #95 (Ljava/lang/Object;)Ljava/lang/Object;
      #104 1
  4: #111 REF_invokeStatic java/lang/invoke/LambdaMetafactory.altMetafactory:(Ljava/lang/invoke/MethodHandles$Lookup;Ljava/lang/String;Ljava/lang/invoke/MethodType;[Ljava/lang/Object;)Ljava/lang/invoke/CallSite;
    Method arguments:
      #95 (Ljava/lang/Object;)Ljava/lang/Object;
      #193 REF_invokeStatic geny/Generator.$anonfun$forall$1$adapted:(Lscala/Function1;Ljava/lang/Object;)Ljava/lang/Object;
      #95 (Ljava/lang/Object;)Ljava/lang/Object;
      #104 1
  5: #111 REF_invokeStatic java/lang/invoke/LambdaMetafactory.altMetafactory:(Ljava/lang/invoke/MethodHandles$Lookup;Ljava/lang/String;Ljava/lang/invoke/MethodType;[Ljava/lang/Object;)Ljava/lang/invoke/CallSite;
    Method arguments:
      #95 (Ljava/lang/Object;)Ljava/lang/Object;
      #211 REF_invokeStatic geny/Generator.$anonfun$count$1:(Lscala/Function1;Lscala/runtime/IntRef;Ljava/lang/Object;)Lgeny/Generator$Continue$;
      #102 (Ljava/lang/Object;)Lgeny/Generator$Continue$;
      #103 5
      #104 1
      #102 (Ljava/lang/Object;)Lgeny/Generator$Continue$;
  6: #111 REF_invokeStatic java/lang/invoke/LambdaMetafactory.altMetafactory:(Ljava/lang/invoke/MethodHandles$Lookup;Ljava/lang/String;Ljava/lang/invoke/MethodType;[Ljava/lang/Object;)Ljava/lang/invoke/CallSite;
    Method arguments:
      #95 (Ljava/lang/Object;)Ljava/lang/Object;
      #229 REF_invokeStatic geny/Generator.$anonfun$count$default$1$1$adapted:(Ljava/lang/Object;)Ljava/lang/Object;
      #95 (Ljava/lang/Object;)Ljava/lang/Object;
      #104 1
  7: #111 REF_invokeStatic java/lang/invoke/LambdaMetafactory.altMetafactory:(Ljava/lang/invoke/MethodHandles$Lookup;Ljava/lang/String;Ljava/lang/invoke/MethodType;[Ljava/lang/Object;)Ljava/lang/invoke/CallSite;
    Method arguments:
      #95 (Ljava/lang/Object;)Ljava/lang/Object;
      #249 REF_invokeStatic geny/Generator.$anonfun$foldLeft$1:(Lscala/runtime/ObjectRef;Lscala/Function2;Ljava/lang/Object;)Lgeny/Generator$Continue$;
      #102 (Ljava/lang/Object;)Lgeny/Generator$Continue$;
      #103 5
      #104 1
      #102 (Ljava/lang/Object;)Lgeny/Generator$Continue$;
  8: #111 REF_invokeStatic java/lang/invoke/LambdaMetafactory.altMetafactory:(Ljava/lang/invoke/MethodHandles$Lookup;Ljava/lang/String;Ljava/lang/invoke/MethodType;[Ljava/lang/Object;)Ljava/lang/invoke/CallSite;
    Method arguments:
      #95 (Ljava/lang/Object;)Ljava/lang/Object;
      #267 REF_invokeStatic geny/Generator.$anonfun$reduceLeft$1:(Lscala/runtime/ObjectRef;Lscala/Function2;Ljava/lang/Object;)Lgeny/Generator$Continue$;
      #102 (Ljava/lang/Object;)Lgeny/Generator$Continue$;
      #103 5
      #104 1
      #102 (Ljava/lang/Object;)Lgeny/Generator$Continue$;
  9: #111 REF_invokeStatic java/lang/invoke/LambdaMetafactory.altMetafactory:(Ljava/lang/invoke/MethodHandles$Lookup;Ljava/lang/String;Ljava/lang/invoke/MethodType;[Ljava/lang/Object;)Ljava/lang/invoke/CallSite;
    Method arguments:
      #270 ()Ljava/lang/Object;
      #275 REF_invokeStatic geny/Generator.$anonfun$reduceLeft$2:()Lscala/runtime/Nothing$;
      #276 ()Lscala/runtime/Nothing$;
      #103 5
      #104 1
      #276 ()Lscala/runtime/Nothing$;
  10: #111 REF_invokeStatic java/lang/invoke/LambdaMetafactory.altMetafactory:(Ljava/lang/invoke/MethodHandles$Lookup;Ljava/lang/String;Ljava/lang/invoke/MethodType;[Ljava/lang/Object;)Ljava/lang/invoke/CallSite;
    Method arguments:
      #95 (Ljava/lang/Object;)Ljava/lang/Object;
      #324 REF_invokeStatic geny/Generator.$anonfun$collect$1$adapted:(Lscala/PartialFunction;Ljava/lang/Object;)Ljava/lang/Object;
      #95 (Ljava/lang/Object;)Ljava/lang/Object;
      #104 1
  11: #111 REF_invokeStatic java/lang/invoke/LambdaMetafactory.altMetafactory:(Ljava/lang/invoke/MethodHandles$Lookup;Ljava/lang/String;Ljava/lang/invoke/MethodType;[Ljava/lang/Object;)Ljava/lang/invoke/CallSite;
    Method arguments:
      #95 (Ljava/lang/Object;)Ljava/lang/Object;
      #338 REF_invokeStatic geny/Generator.$anonfun$collectFirst$1$adapted:(Lscala/PartialFunction;Ljava/lang/Object;)Ljava/lang/Object;
      #95 (Ljava/lang/Object;)Ljava/lang/Object;
      #104 1
  12: #111 REF_invokeStatic java/lang/invoke/LambdaMetafactory.altMetafactory:(Ljava/lang/invoke/MethodHandles$Lookup;Ljava/lang/String;Ljava/lang/invoke/MethodType;[Ljava/lang/Object;)Ljava/lang/invoke/CallSite;
    Method arguments:
      #95 (Ljava/lang/Object;)Ljava/lang/Object;
      #353 REF_invokeStatic geny/Generator.$anonfun$flatten$1:(Lscala/Function1;Ljava/lang/Object;)Lgeny/Generator;
      #355 (Ljava/lang/Object;)Lgeny/Generator;
      #103 5
      #104 1
      #355 (Ljava/lang/Object;)Lgeny/Generator;
  13: #111 REF_invokeStatic java/lang/invoke/LambdaMetafactory.altMetafactory:(Ljava/lang/invoke/MethodHandles$Lookup;Ljava/lang/String;Ljava/lang/invoke/MethodType;[Ljava/lang/Object;)Ljava/lang/invoke/CallSite;
    Method arguments:
      #95 (Ljava/lang/Object;)Ljava/lang/Object;
      #461 REF_invokeStatic geny/Generator.$anonfun$toBuffer$1$adapted:(Lscala/collection/mutable/Buffer;Ljava/lang/Object;)Ljava/lang/Object;
      #95 (Ljava/lang/Object;)Ljava/lang/Object;
      #104 1
  14: #111 REF_invokeStatic java/lang/invoke/LambdaMetafactory.altMetafactory:(Ljava/lang/invoke/MethodHandles$Lookup;Ljava/lang/String;Ljava/lang/invoke/MethodType;[Ljava/lang/Object;)Ljava/lang/invoke/CallSite;
    Method arguments:
      #95 (Ljava/lang/Object;)Ljava/lang/Object;
      #530 REF_invokeStatic geny/Generator.$anonfun$mkString$1$adapted:(Lscala/runtime/BooleanRef;Lscala/collection/mutable/StringBuilder;Ljava/lang/String;Ljava/lang/Object;)Ljava/lang/Object;
      #95 (Ljava/lang/Object;)Ljava/lang/Object;
      #104 1
  15: #111 REF_invokeStatic java/lang/invoke/LambdaMetafactory.altMetafactory:(Ljava/lang/invoke/MethodHandles$Lookup;Ljava/lang/String;Ljava/lang/invoke/MethodType;[Ljava/lang/Object;)Ljava/lang/invoke/CallSite;
    Method arguments:
      #565 (Ljava/lang/Object;Ljava/lang/Object;)Ljava/lang/Object;
      #570 REF_invokeStatic geny/Generator.$anonfun$sum$1:(Lscala/math/Numeric;Ljava/lang/Object;Ljava/lang/Object;)Ljava/lang/Object;
      #565 (Ljava/lang/Object;Ljava/lang/Object;)Ljava/lang/Object;
      #104 1
  16: #111 REF_invokeStatic java/lang/invoke/LambdaMetafactory.altMetafactory:(Ljava/lang/invoke/MethodHandles$Lookup;Ljava/lang/String;Ljava/lang/invoke/MethodType;[Ljava/lang/Object;)Ljava/lang/invoke/CallSite;
    Method arguments:
      #565 (Ljava/lang/Object;Ljava/lang/Object;)Ljava/lang/Object;
      #584 REF_invokeStatic geny/Generator.$anonfun$product$1:(Lscala/math/Numeric;Ljava/lang/Object;Ljava/lang/Object;)Ljava/lang/Object;
      #565 (Ljava/lang/Object;Ljava/lang/Object;)Ljava/lang/Object;
      #104 1
  17: #111 REF_invokeStatic java/lang/invoke/LambdaMetafactory.altMetafactory:(Ljava/lang/invoke/MethodHandles$Lookup;Ljava/lang/String;Ljava/lang/invoke/MethodType;[Ljava/lang/Object;)Ljava/lang/invoke/CallSite;
    Method arguments:
      #565 (Ljava/lang/Object;Ljava/lang/Object;)Ljava/lang/Object;
      #599 REF_invokeStatic geny/Generator.$anonfun$min$1:(Lscala/math/Ordering;Ljava/lang/Object;Ljava/lang/Object;)Ljava/lang/Object;
      #565 (Ljava/lang/Object;Ljava/lang/Object;)Ljava/lang/Object;
      #104 1
  18: #111 REF_invokeStatic java/lang/invoke/LambdaMetafactory.altMetafactory:(Ljava/lang/invoke/MethodHandles$Lookup;Ljava/lang/String;Ljava/lang/invoke/MethodType;[Ljava/lang/Object;)Ljava/lang/invoke/CallSite;
    Method arguments:
      #565 (Ljava/lang/Object;Ljava/lang/Object;)Ljava/lang/Object;
      #610 REF_invokeStatic geny/Generator.$anonfun$max$1:(Lscala/math/Ordering;Ljava/lang/Object;Ljava/lang/Object;)Ljava/lang/Object;
      #565 (Ljava/lang/Object;Ljava/lang/Object;)Ljava/lang/Object;
      #104 1
  19: #111 REF_invokeStatic java/lang/invoke/LambdaMetafactory.altMetafactory:(Ljava/lang/invoke/MethodHandles$Lookup;Ljava/lang/String;Ljava/lang/invoke/MethodType;[Ljava/lang/Object;)Ljava/lang/invoke/CallSite;
    Method arguments:
      #95 (Ljava/lang/Object;)Ljava/lang/Object;
      #623 REF_invokeStatic geny/Generator.$anonfun$maxBy$1$adapted:(Lscala/Function1;Lscala/runtime/BooleanRef;Lscala/math/Ordering;Lscala/runtime/ObjectRef;Lscala/runtime/ObjectRef;Ljava/lang/Object;)Ljava/lang/Object;
      #95 (Ljava/lang/Object;)Ljava/lang/Object;
      #104 1
  20: #111 REF_invokeStatic java/lang/invoke/LambdaMetafactory.altMetafactory:(Ljava/lang/invoke/MethodHandles$Lookup;Ljava/lang/String;Ljava/lang/invoke/MethodType;[Ljava/lang/Object;)Ljava/lang/invoke/CallSite;
    Method arguments:
      #95 (Ljava/lang/Object;)Ljava/lang/Object;
      #636 REF_invokeStatic geny/Generator.$anonfun$minBy$1$adapted:(Lscala/Function1;Lscala/runtime/BooleanRef;Lscala/math/Ordering;Lscala/runtime/ObjectRef;Lscala/runtime/ObjectRef;Ljava/lang/Object;)Ljava/lang/Object;
      #95 (Ljava/lang/Object;)Ljava/lang/Object;
      #104 1
  21: #813 REF_invokeStatic scala/runtime/LambdaDeserialize.bootstrap:(Ljava/lang/invoke/MethodHandles$Lookup;Ljava/lang/String;Ljava/lang/invoke/MethodType;[Ljava/lang/invoke/MethodHandle;)Ljava/lang/invoke/CallSite;
    Method arguments:
      #324 REF_invokeStatic geny/Generator.$anonfun$collect$1$adapted:(Lscala/PartialFunction;Ljava/lang/Object;)Ljava/lang/Object;
      #338 REF_invokeStatic geny/Generator.$anonfun$collectFirst$1$adapted:(Lscala/PartialFunction;Ljava/lang/Object;)Ljava/lang/Object;
      #182 REF_invokeStatic geny/Generator.$anonfun$contains$1$adapted:(Ljava/lang/Object;Ljava/lang/Object;)Ljava/lang/Object;
      #211 REF_invokeStatic geny/Generator.$anonfun$count$1:(Lscala/Function1;Lscala/runtime/IntRef;Ljava/lang/Object;)Lgeny/Generator$Continue$;
      #229 REF_invokeStatic geny/Generator.$anonfun$count$default$1$1$adapted:(Ljava/lang/Object;)Ljava/lang/Object;
      #165 REF_invokeStatic geny/Generator.$anonfun$exists$1$adapted:(Lscala/Function1;Ljava/lang/Object;)Ljava/lang/Object;
      #140 REF_invokeStatic geny/Generator.$anonfun$find$1:(Lscala/Function1;Lscala/runtime/ObjectRef;Ljava/lang/Object;)Lgeny/Generator$Action;
      #353 REF_invokeStatic geny/Generator.$anonfun$flatten$1:(Lscala/Function1;Ljava/lang/Object;)Lgeny/Generator;
      #249 REF_invokeStatic geny/Generator.$anonfun$foldLeft$1:(Lscala/runtime/ObjectRef;Lscala/Function2;Ljava/lang/Object;)Lgeny/Generator$Continue$;
      #193 REF_invokeStatic geny/Generator.$anonfun$forall$1$adapted:(Lscala/Function1;Ljava/lang/Object;)Ljava/lang/Object;
      #100 REF_invokeStatic geny/Generator.$anonfun$foreach$1:(Lscala/Function1;Ljava/lang/Object;)Lgeny/Generator$Continue$;
      #610 REF_invokeStatic geny/Generator.$anonfun$max$1:(Lscala/math/Ordering;Ljava/lang/Object;Ljava/lang/Object;)Ljava/lang/Object;
      #623 REF_invokeStatic geny/Generator.$anonfun$maxBy$1$adapted:(Lscala/Function1;Lscala/runtime/BooleanRef;Lscala/math/Ordering;Lscala/runtime/ObjectRef;Lscala/runtime/ObjectRef;Ljava/lang/Object;)Ljava/lang/Object;
      #599 REF_invokeStatic geny/Generator.$anonfun$min$1:(Lscala/math/Ordering;Ljava/lang/Object;Ljava/lang/Object;)Ljava/lang/Object;
      #636 REF_invokeStatic geny/Generator.$anonfun$minBy$1$adapted:(Lscala/Function1;Lscala/runtime/BooleanRef;Lscala/math/Ordering;Lscala/runtime/ObjectRef;Lscala/runtime/ObjectRef;Ljava/lang/Object;)Ljava/lang/Object;
      #530 REF_invokeStatic geny/Generator.$anonfun$mkString$1$adapted:(Lscala/runtime/BooleanRef;Lscala/collection/mutable/StringBuilder;Ljava/lang/String;Ljava/lang/Object;)Ljava/lang/Object;
      #584 REF_invokeStatic geny/Generator.$anonfun$product$1:(Lscala/math/Numeric;Ljava/lang/Object;Ljava/lang/Object;)Ljava/lang/Object;
      #267 REF_invokeStatic geny/Generator.$anonfun$reduceLeft$1:(Lscala/runtime/ObjectRef;Lscala/Function2;Ljava/lang/Object;)Lgeny/Generator$Continue$;
      #275 REF_invokeStatic geny/Generator.$anonfun$reduceLeft$2:()Lscala/runtime/Nothing$;
      #570 REF_invokeStatic geny/Generator.$anonfun$sum$1:(Lscala/math/Numeric;Ljava/lang/Object;Ljava/lang/Object;)Ljava/lang/Object;
      #461 REF_invokeStatic geny/Generator.$anonfun$toBuffer$1$adapted:(Lscala/collection/mutable/Buffer;Ljava/lang/Object;)Ljava/lang/Object;
  ScalaInlineInfo: length = 0x257 (unknown attribute)
   01 00 00 77 02 C2 02 C3 01 01 40 01 41 01 02 CA
   02 C3 01 01 4F 01 41 01 02 9C 02 9D 01 00 B2 00
   B3 01 00 CF 00 D0 01 02 A8 00 AF 01 00 E2 00 5E
   01 02 98 02 99 01 00 A1 00 A2 01 00 88 00 89 01
   01 5D 01 5E 01 00 F5 00 F6 01 02 A3 02 99 01 00
   BE 00 A2 01 00 60 00 61 01 02 5F 02 54 01 02 F8
   02 F9 01 02 6B 02 6C 01 02 53 02 54 01 03 03 02
   F9 01 02 79 02 6C 01 02 D4 02 D5 01 02 0E 02 0F
   01 02 45 02 37 01 01 08 00 F6 01 01 0F 01 10 01
   02 36 02 37 01 02 CD 02 CE 01 01 C9 01 CA 01 03
   0C 01 8E 01 01 9F 01 88 00 01 9D 01 9E 01 01 3A
   01 3B 00 01 38 01 39 01 01 4A 01 4B 00 01 48 01
   49 01 00 AE 00 AF 00 00 AB 00 AC 01 00 C5 00 C6
   00 00 C3 00 C4 01 00 DD 00 DE 00 00 DB 00 DC 01
   01 79 01 74 00 01 78 01 71 01 01 83 01 20 00 01
   82 01 1D 01 00 9C 00 9D 00 00 9A 00 9B 01 01 1F
   01 20 00 01 1C 01 1D 01 00 78 00 79 00 00 76 00
   77 01 01 33 01 20 00 01 32 01 1D 01 01 59 01 20
   00 01 58 01 1D 01 00 EB 00 EC 00 00 E8 00 E9 01
   00 F1 00 EC 00 00 F4 00 E9 01 00 BB 00 9D 00 00
   BA 00 9B 01 00 57 00 58 00 00 53 00 54 01 00 4F
   00 50 00 01 A8 01 0D 00 01 A6 01 A7 01 01 54 01
   55 00 01 B3 01 B4 01 01 2D 01 20 00 01 2B 01 1D
   01 02 5C 02 4E 00 02 5B 02 4B 01 02 66 02 67 00
   02 64 02 65 01 02 4D 02 4E 00 02 4A 02 4B 01 02
   76 02 67 00 02 75 02 65 01 01 FB 02 17 00 01 FB
   02 1F 00 01 FB 01 FC 00 01 F8 02 24 01 01 F8 02
   1E 01 01 F8 01 F9 01 02 3F 02 2B 00 02 3E 02 28
   01 00 FF 01 00 00 00 FD 00 FE 01 01 04 01 00 00
   01 07 00 FE 01 01 68 01 69 00 01 65 01 66 01 02
   2A 02 2B 00 02 27 02 28 01 01 73 01 74 00 01 70
   01 71 01 01 7E 01 20 00 01 7D 01 1D 01 01 D6 01
   D7 00 01 D3 01 D4 01 01 B9 01 BA 00 01 B7 01 B8
   01 01 E6 01 E7 00 01 E4 01 E5 01 01 AC 01 AD 00
   01 DD 01 DE 01 01 EE 01 EF 00 01 EC 01 ED 01 01
   E0 01 E1 00 01 F4 01 F5 01 01 28 01 20 00 01 27
   01 1D 01 01 94 01 95 00 01 91 01 92 01 01 89 01
   8A 00 01 87 01 88 01
  ScalaSig: length = 0x3 (unknown attribute)
   05 02 00
