Classfile /Users/mw/Projects/slang-braindump/.jar/jar11/assemble/slang-braindump/assemble/content/geny/Writable$StringWritable.class
  Last modified May 29, 2022; size 3393 bytes
  SHA-256 checksum 7685de52cd536261859ac5ff3e17740b713b0ee17c9a2d5d40787ab159cacb3b
  Compiled from "Writable.scala"
public class geny.Writable$StringWritable implements geny.Writable
  minor version: 0
  major version: 52
  flags: (0x0021) ACC_PUBLIC, ACC_SUPER
  this_class: #2                          // geny/Writable$StringWritable
  super_class: #4                         // java/lang/Object
  interfaces: 1, fields: 1, methods: 9, attributes: 5
Constant pool:
    #1 = Utf8               geny/Writable$StringWritable
    #2 = Class              #1            // geny/Writable$StringWritable
    #3 = Utf8               java/lang/Object
    #4 = Class              #3            // java/lang/Object
    #5 = Utf8               geny/Writable
    #6 = Class              #5            // geny/Writable
    #7 = Utf8               Writable.scala
    #8 = Utf8               StringWritable
    #9 = Utf8               java/lang/invoke/MethodHandles$Lookup
   #10 = Class              #9            // java/lang/invoke/MethodHandles$Lookup
   #11 = Utf8               java/lang/invoke/MethodHandles
   #12 = Class              #11           // java/lang/invoke/MethodHandles
   #13 = Utf8               Lookup
   #14 = Utf8               s
   #15 = Utf8               Ljava/lang/String;
   #16 = Utf8               writeBytesTo
   #17 = Utf8               (Ljava/io/OutputStream;)V
   #18 = Utf8               out
   #19 = Utf8               scala/collection/StringOps$
   #20 = Class              #19           // scala/collection/StringOps$
   #21 = Utf8               MODULE$
   #22 = Utf8               Lscala/collection/StringOps$;
   #23 = NameAndType        #21:#22       // MODULE$:Lscala/collection/StringOps$;
   #24 = Fieldref           #20.#23       // scala/collection/StringOps$.MODULE$:Lscala/collection/StringOps$;
   #25 = Utf8               scala/Predef$
   #26 = Class              #25           // scala/Predef$
   #27 = Utf8               Lscala/Predef$;
   #28 = NameAndType        #21:#27       // MODULE$:Lscala/Predef$;
   #29 = Fieldref           #26.#28       // scala/Predef$.MODULE$:Lscala/Predef$;
   #30 = NameAndType        #14:#15       // s:Ljava/lang/String;
   #31 = Fieldref           #2.#30        // geny/Writable$StringWritable.s:Ljava/lang/String;
   #32 = Utf8               augmentString
   #33 = Utf8               (Ljava/lang/String;)Ljava/lang/String;
   #34 = NameAndType        #32:#33       // augmentString:(Ljava/lang/String;)Ljava/lang/String;
   #35 = Methodref          #26.#34       // scala/Predef$.augmentString:(Ljava/lang/String;)Ljava/lang/String;
   #36 = Utf8               grouped$extension
   #37 = Utf8               (Ljava/lang/String;I)Lscala/collection/Iterator;
   #38 = NameAndType        #36:#37       // grouped$extension:(Ljava/lang/String;I)Lscala/collection/Iterator;
   #39 = Methodref          #20.#38       // scala/collection/StringOps$.grouped$extension:(Ljava/lang/String;I)Lscala/collection/Iterator;
   #40 = Utf8               (Ljava/lang/Object;)Ljava/lang/Object;
   #41 = MethodType         #40           //  (Ljava/lang/Object;)Ljava/lang/Object;
   #42 = Utf8               $anonfun$writeBytesTo$1$adapted
   #43 = Utf8               (Ljava/io/OutputStream;Ljava/lang/String;)Ljava/lang/Object;
   #44 = NameAndType        #42:#43       // $anonfun$writeBytesTo$1$adapted:(Ljava/io/OutputStream;Ljava/lang/String;)Ljava/lang/Object;
   #45 = Methodref          #2.#44        // geny/Writable$StringWritable.$anonfun$writeBytesTo$1$adapted:(Ljava/io/OutputStream;Ljava/lang/String;)Ljava/lang/Object;
   #46 = MethodHandle       6:#45         // REF_invokeStatic geny/Writable$StringWritable.$anonfun$writeBytesTo$1$adapted:(Ljava/io/OutputStream;Ljava/lang/String;)Ljava/lang/Object;
   #47 = Utf8               (Ljava/lang/String;)Ljava/lang/Object;
   #48 = MethodType         #47           //  (Ljava/lang/String;)Ljava/lang/Object;
   #49 = Integer            5
   #50 = Integer            1
   #51 = Utf8               java/lang/invoke/LambdaMetafactory
   #52 = Class              #51           // java/lang/invoke/LambdaMetafactory
   #53 = Utf8               altMetafactory
   #54 = Utf8               (Ljava/lang/invoke/MethodHandles$Lookup;Ljava/lang/String;Ljava/lang/invoke/MethodType;[Ljava/lang/Object;)Ljava/lang/invoke/CallSite;
   #55 = NameAndType        #53:#54       // altMetafactory:(Ljava/lang/invoke/MethodHandles$Lookup;Ljava/lang/String;Ljava/lang/invoke/MethodType;[Ljava/lang/Object;)Ljava/lang/invoke/CallSite;
   #56 = Methodref          #52.#55       // java/lang/invoke/LambdaMetafactory.altMetafactory:(Ljava/lang/invoke/MethodHandles$Lookup;Ljava/lang/String;Ljava/lang/invoke/MethodType;[Ljava/lang/Object;)Ljava/lang/invoke/CallSite;
   #57 = MethodHandle       6:#56         // REF_invokeStatic java/lang/invoke/LambdaMetafactory.altMetafactory:(Ljava/lang/invoke/MethodHandles$Lookup;Ljava/lang/String;Ljava/lang/invoke/MethodType;[Ljava/lang/Object;)Ljava/lang/invoke/CallSite;
   #58 = Utf8               apply
   #59 = Utf8               (Ljava/io/OutputStream;)Lscala/Function1;
   #60 = NameAndType        #58:#59       // apply:(Ljava/io/OutputStream;)Lscala/Function1;
   #61 = InvokeDynamic      #0:#60        // #0:apply:(Ljava/io/OutputStream;)Lscala/Function1;
   #62 = Utf8               scala/collection/Iterator
   #63 = Class              #62           // scala/collection/Iterator
   #64 = Utf8               foreach
   #65 = Utf8               (Lscala/Function1;)V
   #66 = NameAndType        #64:#65       // foreach:(Lscala/Function1;)V
   #67 = InterfaceMethodref #63.#66       // scala/collection/Iterator.foreach:(Lscala/Function1;)V
   #68 = Utf8               this
   #69 = Utf8               Lgeny/Writable$StringWritable;
   #70 = Utf8               Ljava/io/OutputStream;
   #71 = Utf8               httpContentType
   #72 = Utf8               ()Lscala/Some;
   #73 = Utf8               ()Lscala/Some<Ljava/lang/String;>;
   #74 = Utf8               scala/Some
   #75 = Class              #74           // scala/Some
   #76 = Utf8               text/plain; charset=utf-8
   #77 = String             #76           // text/plain; charset=utf-8
   #78 = Utf8               <init>
   #79 = Utf8               (Ljava/lang/Object;)V
   #80 = NameAndType        #78:#79       // "<init>":(Ljava/lang/Object;)V
   #81 = Methodref          #75.#80       // scala/Some."<init>":(Ljava/lang/Object;)V
   #82 = Utf8               contentLength
   #83 = Utf8               ()Lscala/Some<Ljava/lang/Object;>;
   #84 = Utf8               geny/Internal$
   #85 = Class              #84           // geny/Internal$
   #86 = Utf8               Lgeny/Internal$;
   #87 = NameAndType        #21:#86       // MODULE$:Lgeny/Internal$;
   #88 = Fieldref           #85.#87       // geny/Internal$.MODULE$:Lgeny/Internal$;
   #89 = Utf8               encodedLength
   #90 = Utf8               (Ljava/lang/String;)I
   #91 = NameAndType        #89:#90       // encodedLength:(Ljava/lang/String;)I
   #92 = Methodref          #85.#91       // geny/Internal$.encodedLength:(Ljava/lang/String;)I
   #93 = Utf8               scala/runtime/BoxesRunTime
   #94 = Class              #93           // scala/runtime/BoxesRunTime
   #95 = Utf8               boxToLong
   #96 = Utf8               (J)Ljava/lang/Long;
   #97 = NameAndType        #95:#96       // boxToLong:(J)Ljava/lang/Long;
   #98 = Methodref          #94.#97       // scala/runtime/BoxesRunTime.boxToLong:(J)Ljava/lang/Long;
   #99 = Utf8               ()Lscala/Option;
  #100 = NameAndType        #82:#72       // contentLength:()Lscala/Some;
  #101 = Methodref          #2.#100       // geny/Writable$StringWritable.contentLength:()Lscala/Some;
  #102 = NameAndType        #71:#72       // httpContentType:()Lscala/Some;
  #103 = Methodref          #2.#102       // geny/Writable$StringWritable.httpContentType:()Lscala/Some;
  #104 = Utf8               $anonfun$writeBytesTo$1
  #105 = Utf8               (Ljava/io/OutputStream;Ljava/lang/String;)V
  #106 = Utf8               out$1
  #107 = Utf8               ss
  #108 = Utf8               java/nio/charset/StandardCharsets
  #109 = Class              #108          // java/nio/charset/StandardCharsets
  #110 = Utf8               UTF_8
  #111 = Utf8               Ljava/nio/charset/Charset;
  #112 = NameAndType        #110:#111     // UTF_8:Ljava/nio/charset/Charset;
  #113 = Fieldref           #109.#112     // java/nio/charset/StandardCharsets.UTF_8:Ljava/nio/charset/Charset;
  #114 = Utf8               java/lang/String
  #115 = Class              #114          // java/lang/String
  #116 = Utf8               getBytes
  #117 = Utf8               (Ljava/nio/charset/Charset;)[B
  #118 = NameAndType        #116:#117     // getBytes:(Ljava/nio/charset/Charset;)[B
  #119 = Methodref          #115.#118     // java/lang/String.getBytes:(Ljava/nio/charset/Charset;)[B
  #120 = Utf8               java/io/OutputStream
  #121 = Class              #120          // java/io/OutputStream
  #122 = Utf8               write
  #123 = Utf8               ([B)V
  #124 = NameAndType        #122:#123     // write:([B)V
  #125 = Methodref          #121.#124     // java/io/OutputStream.write:([B)V
  #126 = Utf8               (Ljava/lang/String;)V
  #127 = Utf8               ()V
  #128 = NameAndType        #78:#127      // "<init>":()V
  #129 = Methodref          #4.#128       // java/lang/Object."<init>":()V
  #130 = Utf8               $init$
  #131 = Utf8               (Lgeny/Writable;)V
  #132 = NameAndType        #130:#131     // $init$:(Lgeny/Writable;)V
  #133 = InterfaceMethodref #6.#132       // geny/Writable.$init$:(Lgeny/Writable;)V
  #134 = NameAndType        #104:#105     // $anonfun$writeBytesTo$1:(Ljava/io/OutputStream;Ljava/lang/String;)V
  #135 = Methodref          #2.#134       // geny/Writable$StringWritable.$anonfun$writeBytesTo$1:(Ljava/io/OutputStream;Ljava/lang/String;)V
  #136 = Utf8               scala/runtime/BoxedUnit
  #137 = Class              #136          // scala/runtime/BoxedUnit
  #138 = Utf8               UNIT
  #139 = Utf8               Lscala/runtime/BoxedUnit;
  #140 = NameAndType        #138:#139     // UNIT:Lscala/runtime/BoxedUnit;
  #141 = Fieldref           #137.#140     // scala/runtime/BoxedUnit.UNIT:Lscala/runtime/BoxedUnit;
  #142 = Utf8               $deserializeLambda$
  #143 = Utf8               (Ljava/lang/invoke/SerializedLambda;)Ljava/lang/Object;
  #144 = Utf8               scala/runtime/LambdaDeserialize
  #145 = Class              #144          // scala/runtime/LambdaDeserialize
  #146 = Utf8               bootstrap
  #147 = Utf8               (Ljava/lang/invoke/MethodHandles$Lookup;Ljava/lang/String;Ljava/lang/invoke/MethodType;[Ljava/lang/invoke/MethodHandle;)Ljava/lang/invoke/CallSite;
  #148 = NameAndType        #146:#147     // bootstrap:(Ljava/lang/invoke/MethodHandles$Lookup;Ljava/lang/String;Ljava/lang/invoke/MethodType;[Ljava/lang/invoke/MethodHandle;)Ljava/lang/invoke/CallSite;
  #149 = Methodref          #145.#148     // scala/runtime/LambdaDeserialize.bootstrap:(Ljava/lang/invoke/MethodHandles$Lookup;Ljava/lang/String;Ljava/lang/invoke/MethodType;[Ljava/lang/invoke/MethodHandle;)Ljava/lang/invoke/CallSite;
  #150 = MethodHandle       6:#149        // REF_invokeStatic scala/runtime/LambdaDeserialize.bootstrap:(Ljava/lang/invoke/MethodHandles$Lookup;Ljava/lang/String;Ljava/lang/invoke/MethodType;[Ljava/lang/invoke/MethodHandle;)Ljava/lang/invoke/CallSite;
  #151 = Utf8               lambdaDeserialize
  #152 = NameAndType        #151:#143     // lambdaDeserialize:(Ljava/lang/invoke/SerializedLambda;)Ljava/lang/Object;
  #153 = InvokeDynamic      #1:#152       // #1:lambdaDeserialize:(Ljava/lang/invoke/SerializedLambda;)Ljava/lang/Object;
  #154 = Utf8               Code
  #155 = Utf8               LineNumberTable
  #156 = Utf8               LocalVariableTable
  #157 = Utf8               MethodParameters
  #158 = Utf8               Signature
  #159 = Utf8               InnerClasses
  #160 = Utf8               SourceFile
  #161 = Utf8               BootstrapMethods
  #162 = Utf8               ScalaInlineInfo
  #163 = Utf8               Scala
{
  private final java.lang.String s;
    descriptor: Ljava/lang/String;
    flags: (0x0012) ACC_PRIVATE, ACC_FINAL

  public void writeBytesTo(java.io.OutputStream);
    descriptor: (Ljava/io/OutputStream;)V
    flags: (0x0001) ACC_PUBLIC
    Code:
      stack=3, locals=2, args_size=2
         0: getstatic     #24                 // Field scala/collection/StringOps$.MODULE$:Lscala/collection/StringOps$;
         3: getstatic     #29                 // Field scala/Predef$.MODULE$:Lscala/Predef$;
         6: aload_0
         7: getfield      #31                 // Field s:Ljava/lang/String;
        10: invokevirtual #35                 // Method scala/Predef$.augmentString:(Ljava/lang/String;)Ljava/lang/String;
        13: sipush        8192
        16: invokevirtual #39                 // Method scala/collection/StringOps$.grouped$extension:(Ljava/lang/String;I)Lscala/collection/Iterator;
        19: aload_1
        20: invokedynamic #61,  0             // InvokeDynamic #0:apply:(Ljava/io/OutputStream;)Lscala/Function1;
        25: invokeinterface #67,  2           // InterfaceMethod scala/collection/Iterator.foreach:(Lscala/Function1;)V
        30: return
      LineNumberTable:
        line 34: 0
      LocalVariableTable:
        Start  Length  Slot  Name   Signature
            0      31     0  this   Lgeny/Writable$StringWritable;
            0      31     1   out   Ljava/io/OutputStream;
    MethodParameters:
      Name                           Flags
      out                            final

  public scala.Some<java.lang.String> httpContentType();
    descriptor: ()Lscala/Some;
    flags: (0x0001) ACC_PUBLIC
    Code:
      stack=3, locals=1, args_size=1
         0: new           #75                 // class scala/Some
         3: dup
         4: ldc           #77                 // String text/plain; charset=utf-8
         6: invokespecial #81                 // Method scala/Some."<init>":(Ljava/lang/Object;)V
         9: areturn
      LineNumberTable:
        line 36: 0
      LocalVariableTable:
        Start  Length  Slot  Name   Signature
            0      10     0  this   Lgeny/Writable$StringWritable;
    Signature: #73                          // ()Lscala/Some<Ljava/lang/String;>;

  public scala.Some<java.lang.Object> contentLength();
    descriptor: ()Lscala/Some;
    flags: (0x0001) ACC_PUBLIC
    Code:
      stack=4, locals=1, args_size=1
         0: new           #75                 // class scala/Some
         3: dup
         4: getstatic     #88                 // Field geny/Internal$.MODULE$:Lgeny/Internal$;
         7: aload_0
         8: getfield      #31                 // Field s:Ljava/lang/String;
        11: invokevirtual #92                 // Method geny/Internal$.encodedLength:(Ljava/lang/String;)I
        14: i2l
        15: invokestatic  #98                 // Method scala/runtime/BoxesRunTime.boxToLong:(J)Ljava/lang/Long;
        18: invokespecial #81                 // Method scala/Some."<init>":(Ljava/lang/Object;)V
        21: areturn
      LineNumberTable:
        line 37: 0
      LocalVariableTable:
        Start  Length  Slot  Name   Signature
            0      22     0  this   Lgeny/Writable$StringWritable;
    Signature: #83                          // ()Lscala/Some<Ljava/lang/Object;>;

  public scala.Option contentLength();
    descriptor: ()Lscala/Option;
    flags: (0x1041) ACC_PUBLIC, ACC_BRIDGE, ACC_SYNTHETIC
    Code:
      stack=1, locals=1, args_size=1
         0: aload_0
         1: invokevirtual #101                // Method contentLength:()Lscala/Some;
         4: areturn
      LineNumberTable:
        line 31: 0
      LocalVariableTable:
        Start  Length  Slot  Name   Signature
            0       5     0  this   Lgeny/Writable$StringWritable;

  public scala.Option httpContentType();
    descriptor: ()Lscala/Option;
    flags: (0x1041) ACC_PUBLIC, ACC_BRIDGE, ACC_SYNTHETIC
    Code:
      stack=1, locals=1, args_size=1
         0: aload_0
         1: invokevirtual #103                // Method httpContentType:()Lscala/Some;
         4: areturn
      LineNumberTable:
        line 31: 0
      LocalVariableTable:
        Start  Length  Slot  Name   Signature
            0       5     0  this   Lgeny/Writable$StringWritable;

  public static final void $anonfun$writeBytesTo$1(java.io.OutputStream, java.lang.String);
    descriptor: (Ljava/io/OutputStream;Ljava/lang/String;)V
    flags: (0x1019) ACC_PUBLIC, ACC_STATIC, ACC_FINAL, ACC_SYNTHETIC
    Code:
      stack=3, locals=2, args_size=2
         0: aload_0
         1: aload_1
         2: getstatic     #113                // Field java/nio/charset/StandardCharsets.UTF_8:Ljava/nio/charset/Charset;
         5: invokevirtual #119                // Method java/lang/String.getBytes:(Ljava/nio/charset/Charset;)[B
         8: invokevirtual #125                // Method java/io/OutputStream.write:([B)V
        11: return
      LineNumberTable:
        line 34: 0
      LocalVariableTable:
        Start  Length  Slot  Name   Signature
            0      12     0 out$1   Ljava/io/OutputStream;
            0      12     1    ss   Ljava/lang/String;
    MethodParameters:
      Name                           Flags
      out$1                          final
      ss                             final

  public geny.Writable$StringWritable(java.lang.String);
    descriptor: (Ljava/lang/String;)V
    flags: (0x0001) ACC_PUBLIC
    Code:
      stack=2, locals=2, args_size=2
         0: aload_0
         1: aload_1
         2: putfield      #31                 // Field s:Ljava/lang/String;
         5: aload_0
         6: invokespecial #129                // Method java/lang/Object."<init>":()V
         9: aload_0
        10: invokestatic  #133                // InterfaceMethod geny/Writable.$init$:(Lgeny/Writable;)V
        13: return
      LineNumberTable:
        line 31: 0
      LocalVariableTable:
        Start  Length  Slot  Name   Signature
            0      14     0  this   Lgeny/Writable$StringWritable;
            0      14     1     s   Ljava/lang/String;
    MethodParameters:
      Name                           Flags
      s                              final

  public static final java.lang.Object $anonfun$writeBytesTo$1$adapted(java.io.OutputStream, java.lang.String);
    descriptor: (Ljava/io/OutputStream;Ljava/lang/String;)Ljava/lang/Object;
    flags: (0x1019) ACC_PUBLIC, ACC_STATIC, ACC_FINAL, ACC_SYNTHETIC
    Code:
      stack=2, locals=2, args_size=2
         0: aload_0
         1: aload_1
         2: invokestatic  #135                // Method $anonfun$writeBytesTo$1:(Ljava/io/OutputStream;Ljava/lang/String;)V
         5: getstatic     #141                // Field scala/runtime/BoxedUnit.UNIT:Lscala/runtime/BoxedUnit;
         8: areturn
      LineNumberTable:
        line 34: 0
      LocalVariableTable:
        Start  Length  Slot  Name   Signature
            0       9     0 out$1   Ljava/io/OutputStream;
            0       9     1    ss   Ljava/lang/String;
    MethodParameters:
      Name                           Flags
      out$1                          final
      ss                             final

  private static java.lang.Object $deserializeLambda$(java.lang.invoke.SerializedLambda);
    descriptor: (Ljava/lang/invoke/SerializedLambda;)Ljava/lang/Object;
    flags: (0x100a) ACC_PRIVATE, ACC_STATIC, ACC_SYNTHETIC
    Code:
      stack=1, locals=1, args_size=1
         0: aload_0
         1: invokedynamic #153,  0            // InvokeDynamic #1:lambdaDeserialize:(Ljava/lang/invoke/SerializedLambda;)Ljava/lang/Object;
         6: areturn
}
InnerClasses:
  public static #8= #2 of #6;             // StringWritable=class geny/Writable$StringWritable of class geny/Writable
  public static final #13= #10 of #12;    // Lookup=class java/lang/invoke/MethodHandles$Lookup of class java/lang/invoke/MethodHandles
SourceFile: "Writable.scala"
BootstrapMethods:
  0: #57 REF_invokeStatic java/lang/invoke/LambdaMetafactory.altMetafactory:(Ljava/lang/invoke/MethodHandles$Lookup;Ljava/lang/String;Ljava/lang/invoke/MethodType;[Ljava/lang/Object;)Ljava/lang/invoke/CallSite;
    Method arguments:
      #41 (Ljava/lang/Object;)Ljava/lang/Object;
      #46 REF_invokeStatic geny/Writable$StringWritable.$anonfun$writeBytesTo$1$adapted:(Ljava/io/OutputStream;Ljava/lang/String;)Ljava/lang/Object;
      #48 (Ljava/lang/String;)Ljava/lang/Object;
      #49 5
      #50 1
      #48 (Ljava/lang/String;)Ljava/lang/Object;
  1: #150 REF_invokeStatic scala/runtime/LambdaDeserialize.bootstrap:(Ljava/lang/invoke/MethodHandles$Lookup;Ljava/lang/String;Ljava/lang/invoke/MethodType;[Ljava/lang/invoke/MethodHandle;)Ljava/lang/invoke/CallSite;
    Method arguments:
      #46 REF_invokeStatic geny/Writable$StringWritable.$anonfun$writeBytesTo$1$adapted:(Ljava/io/OutputStream;Ljava/lang/String;)Ljava/lang/Object;
  ScalaInlineInfo: length = 0x2C (unknown attribute)
   01 00 00 08 00 68 00 69 01 00 2A 00 2B 01 00 4E
   00 7E 00 00 52 00 63 00 00 52 00 48 00 00 47 00
   63 00 00 47 00 48 00 00 10 00 11 00
  Scala: length = 0x0 (unknown attribute)

