Classfile /Users/mw/Projects/slang-braindump/.jar/jar8/assemble/slang-braindump/assemble/content/org/apache/commons/io/output/BrokenWriter.class
  Last modified May 29, 2022; size 901 bytes
  SHA-256 checksum 1ec6aaa7191d7925e9983f9cec4d0b5b13d7e29a7ea237cd705e27e91e234e68
  Compiled from "BrokenWriter.java"
public class org.apache.commons.io.output.BrokenWriter extends java.io.Writer
  minor version: 0
  major version: 52
  flags: (0x0021) ACC_PUBLIC, ACC_SUPER
  this_class: #7                          // org/apache/commons/io/output/BrokenWriter
  super_class: #8                         // java/io/Writer
  interfaces: 0, fields: 1, methods: 5, attributes: 1
Constant pool:
   #1 = Methodref          #8.#31         // java/io/Writer."<init>":()V
   #2 = Fieldref           #7.#32         // org/apache/commons/io/output/BrokenWriter.exception:Ljava/io/IOException;
   #3 = Class              #33            // java/io/IOException
   #4 = String             #34            // Broken writer
   #5 = Methodref          #3.#35         // java/io/IOException."<init>":(Ljava/lang/String;)V
   #6 = Methodref          #7.#36         // org/apache/commons/io/output/BrokenWriter."<init>":(Ljava/io/IOException;)V
   #7 = Class              #37            // org/apache/commons/io/output/BrokenWriter
   #8 = Class              #38            // java/io/Writer
   #9 = Utf8               exception
  #10 = Utf8               Ljava/io/IOException;
  #11 = Utf8               <init>
  #12 = Utf8               (Ljava/io/IOException;)V
  #13 = Utf8               Code
  #14 = Utf8               LineNumberTable
  #15 = Utf8               LocalVariableTable
  #16 = Utf8               this
  #17 = Utf8               Lorg/apache/commons/io/output/BrokenWriter;
  #18 = Utf8               ()V
  #19 = Utf8               write
  #20 = Utf8               ([CII)V
  #21 = Utf8               cbuf
  #22 = Utf8               [C
  #23 = Utf8               off
  #24 = Utf8               I
  #25 = Utf8               len
  #26 = Utf8               Exceptions
  #27 = Utf8               flush
  #28 = Utf8               close
  #29 = Utf8               SourceFile
  #30 = Utf8               BrokenWriter.java
  #31 = NameAndType        #11:#18        // "<init>":()V
  #32 = NameAndType        #9:#10         // exception:Ljava/io/IOException;
  #33 = Utf8               java/io/IOException
  #34 = Utf8               Broken writer
  #35 = NameAndType        #11:#39        // "<init>":(Ljava/lang/String;)V
  #36 = NameAndType        #11:#12        // "<init>":(Ljava/io/IOException;)V
  #37 = Utf8               org/apache/commons/io/output/BrokenWriter
  #38 = Utf8               java/io/Writer
  #39 = Utf8               (Ljava/lang/String;)V
{
  private final java.io.IOException exception;
    descriptor: Ljava/io/IOException;
    flags: (0x0012) ACC_PRIVATE, ACC_FINAL

  public org.apache.commons.io.output.BrokenWriter(java.io.IOException);
    descriptor: (Ljava/io/IOException;)V
    flags: (0x0001) ACC_PUBLIC
    Code:
      stack=2, locals=2, args_size=2
         0: aload_0
         1: invokespecial #1                  // Method java/io/Writer."<init>":()V
         4: aload_0
         5: aload_1
         6: putfield      #2                  // Field exception:Ljava/io/IOException;
         9: return
      LineNumberTable:
        line 43: 0
        line 44: 4
        line 45: 9
      LocalVariableTable:
        Start  Length  Slot  Name   Signature
            0      10     0  this   Lorg/apache/commons/io/output/BrokenWriter;
            0      10     1 exception   Ljava/io/IOException;

  public org.apache.commons.io.output.BrokenWriter();
    descriptor: ()V
    flags: (0x0001) ACC_PUBLIC
    Code:
      stack=4, locals=1, args_size=1
         0: aload_0
         1: new           #3                  // class java/io/IOException
         4: dup
         5: ldc           #4                  // String Broken writer
         7: invokespecial #5                  // Method java/io/IOException."<init>":(Ljava/lang/String;)V
        10: invokespecial #6                  // Method "<init>":(Ljava/io/IOException;)V
        13: return
      LineNumberTable:
        line 51: 0
        line 52: 13
      LocalVariableTable:
        Start  Length  Slot  Name   Signature
            0      14     0  this   Lorg/apache/commons/io/output/BrokenWriter;

  public void write(char[], int, int) throws java.io.IOException;
    descriptor: ([CII)V
    flags: (0x0001) ACC_PUBLIC
    Code:
      stack=1, locals=4, args_size=4
         0: aload_0
         1: getfield      #2                  // Field exception:Ljava/io/IOException;
         4: athrow
      LineNumberTable:
        line 64: 0
      LocalVariableTable:
        Start  Length  Slot  Name   Signature
            0       5     0  this   Lorg/apache/commons/io/output/BrokenWriter;
            0       5     1  cbuf   [C
            0       5     2   off   I
            0       5     3   len   I
    Exceptions:
      throws java.io.IOException

  public void flush() throws java.io.IOException;
    descriptor: ()V
    flags: (0x0001) ACC_PUBLIC
    Code:
      stack=1, locals=1, args_size=1
         0: aload_0
         1: getfield      #2                  // Field exception:Ljava/io/IOException;
         4: athrow
      LineNumberTable:
        line 74: 0
      LocalVariableTable:
        Start  Length  Slot  Name   Signature
            0       5     0  this   Lorg/apache/commons/io/output/BrokenWriter;
    Exceptions:
      throws java.io.IOException

  public void close() throws java.io.IOException;
    descriptor: ()V
    flags: (0x0001) ACC_PUBLIC
    Code:
      stack=1, locals=1, args_size=1
         0: aload_0
         1: getfield      #2                  // Field exception:Ljava/io/IOException;
         4: athrow
      LineNumberTable:
        line 84: 0
      LocalVariableTable:
        Start  Length  Slot  Name   Signature
            0       5     0  this   Lorg/apache/commons/io/output/BrokenWriter;
    Exceptions:
      throws java.io.IOException
}
SourceFile: "BrokenWriter.java"
