Classfile /Users/mw/Projects/slang-braindump/.jar/jar8/assemble/slang-braindump/assemble/content/org/apache/commons/io/output/TeeOutputStream.class
  Last modified May 29, 2022; size 1318 bytes
  SHA-256 checksum 2ec1550c1cee8b72669eb94d3641d2d031449fcc86b30e166762a54dc239eb3b
  Compiled from "TeeOutputStream.java"
public class org.apache.commons.io.output.TeeOutputStream extends org.apache.commons.io.output.ProxyOutputStream
  minor version: 0
  major version: 52
  flags: (0x0021) ACC_PUBLIC, ACC_SUPER
  this_class: #13                         // org/apache/commons/io/output/TeeOutputStream
  super_class: #14                        // org/apache/commons/io/output/ProxyOutputStream
  interfaces: 0, fields: 1, methods: 6, attributes: 1
Constant pool:
   #1 = Methodref          #14.#43        // org/apache/commons/io/output/ProxyOutputStream."<init>":(Ljava/io/OutputStream;)V
   #2 = Fieldref           #13.#44        // org/apache/commons/io/output/TeeOutputStream.branch:Ljava/io/OutputStream;
   #3 = Methodref          #14.#45        // org/apache/commons/io/output/ProxyOutputStream.write:([B)V
   #4 = Methodref          #46.#45        // java/io/OutputStream.write:([B)V
   #5 = Methodref          #14.#47        // org/apache/commons/io/output/ProxyOutputStream.write:([BII)V
   #6 = Methodref          #46.#47        // java/io/OutputStream.write:([BII)V
   #7 = Methodref          #14.#48        // org/apache/commons/io/output/ProxyOutputStream.write:(I)V
   #8 = Methodref          #46.#48        // java/io/OutputStream.write:(I)V
   #9 = Methodref          #14.#49        // org/apache/commons/io/output/ProxyOutputStream.flush:()V
  #10 = Methodref          #46.#49        // java/io/OutputStream.flush:()V
  #11 = Methodref          #14.#50        // org/apache/commons/io/output/ProxyOutputStream.close:()V
  #12 = Methodref          #46.#50        // java/io/OutputStream.close:()V
  #13 = Class              #51            // org/apache/commons/io/output/TeeOutputStream
  #14 = Class              #52            // org/apache/commons/io/output/ProxyOutputStream
  #15 = Utf8               branch
  #16 = Utf8               Ljava/io/OutputStream;
  #17 = Utf8               <init>
  #18 = Utf8               (Ljava/io/OutputStream;Ljava/io/OutputStream;)V
  #19 = Utf8               Code
  #20 = Utf8               LineNumberTable
  #21 = Utf8               LocalVariableTable
  #22 = Utf8               this
  #23 = Utf8               Lorg/apache/commons/io/output/TeeOutputStream;
  #24 = Utf8               out
  #25 = Utf8               write
  #26 = Utf8               ([B)V
  #27 = Utf8               b
  #28 = Utf8               [B
  #29 = Utf8               Exceptions
  #30 = Class              #53            // java/io/IOException
  #31 = Utf8               ([BII)V
  #32 = Utf8               off
  #33 = Utf8               I
  #34 = Utf8               len
  #35 = Utf8               (I)V
  #36 = Utf8               flush
  #37 = Utf8               ()V
  #38 = Utf8               close
  #39 = Utf8               StackMapTable
  #40 = Class              #54            // java/lang/Throwable
  #41 = Utf8               SourceFile
  #42 = Utf8               TeeOutputStream.java
  #43 = NameAndType        #17:#55        // "<init>":(Ljava/io/OutputStream;)V
  #44 = NameAndType        #15:#16        // branch:Ljava/io/OutputStream;
  #45 = NameAndType        #25:#26        // write:([B)V
  #46 = Class              #56            // java/io/OutputStream
  #47 = NameAndType        #25:#31        // write:([BII)V
  #48 = NameAndType        #25:#35        // write:(I)V
  #49 = NameAndType        #36:#37        // flush:()V
  #50 = NameAndType        #38:#37        // close:()V
  #51 = Utf8               org/apache/commons/io/output/TeeOutputStream
  #52 = Utf8               org/apache/commons/io/output/ProxyOutputStream
  #53 = Utf8               java/io/IOException
  #54 = Utf8               java/lang/Throwable
  #55 = Utf8               (Ljava/io/OutputStream;)V
  #56 = Utf8               java/io/OutputStream
{
  protected java.io.OutputStream branch;
    descriptor: Ljava/io/OutputStream;
    flags: (0x0004) ACC_PROTECTED

  public org.apache.commons.io.output.TeeOutputStream(java.io.OutputStream, java.io.OutputStream);
    descriptor: (Ljava/io/OutputStream;Ljava/io/OutputStream;)V
    flags: (0x0001) ACC_PUBLIC
    Code:
      stack=2, locals=3, args_size=3
         0: aload_0
         1: aload_1
         2: invokespecial #1                  // Method org/apache/commons/io/output/ProxyOutputStream."<init>":(Ljava/io/OutputStream;)V
         5: aload_0
         6: aload_2
         7: putfield      #2                  // Field branch:Ljava/io/OutputStream;
        10: return
      LineNumberTable:
        line 37: 0
        line 38: 5
        line 39: 10
      LocalVariableTable:
        Start  Length  Slot  Name   Signature
            0      11     0  this   Lorg/apache/commons/io/output/TeeOutputStream;
            0      11     1   out   Ljava/io/OutputStream;
            0      11     2 branch   Ljava/io/OutputStream;

  public synchronized void write(byte[]) throws java.io.IOException;
    descriptor: ([B)V
    flags: (0x0021) ACC_PUBLIC, ACC_SYNCHRONIZED
    Code:
      stack=2, locals=2, args_size=2
         0: aload_0
         1: aload_1
         2: invokespecial #3                  // Method org/apache/commons/io/output/ProxyOutputStream.write:([B)V
         5: aload_0
         6: getfield      #2                  // Field branch:Ljava/io/OutputStream;
         9: aload_1
        10: invokevirtual #4                  // Method java/io/OutputStream.write:([B)V
        13: return
      LineNumberTable:
        line 48: 0
        line 49: 5
        line 50: 13
      LocalVariableTable:
        Start  Length  Slot  Name   Signature
            0      14     0  this   Lorg/apache/commons/io/output/TeeOutputStream;
            0      14     1     b   [B
    Exceptions:
      throws java.io.IOException

  public synchronized void write(byte[], int, int) throws java.io.IOException;
    descriptor: ([BII)V
    flags: (0x0021) ACC_PUBLIC, ACC_SYNCHRONIZED
    Code:
      stack=4, locals=4, args_size=4
         0: aload_0
         1: aload_1
         2: iload_2
         3: iload_3
         4: invokespecial #5                  // Method org/apache/commons/io/output/ProxyOutputStream.write:([BII)V
         7: aload_0
         8: getfield      #2                  // Field branch:Ljava/io/OutputStream;
        11: aload_1
        12: iload_2
        13: iload_3
        14: invokevirtual #6                  // Method java/io/OutputStream.write:([BII)V
        17: return
      LineNumberTable:
        line 61: 0
        line 62: 7
        line 63: 17
      LocalVariableTable:
        Start  Length  Slot  Name   Signature
            0      18     0  this   Lorg/apache/commons/io/output/TeeOutputStream;
            0      18     1     b   [B
            0      18     2   off   I
            0      18     3   len   I
    Exceptions:
      throws java.io.IOException

  public synchronized void write(int) throws java.io.IOException;
    descriptor: (I)V
    flags: (0x0021) ACC_PUBLIC, ACC_SYNCHRONIZED
    Code:
      stack=2, locals=2, args_size=2
         0: aload_0
         1: iload_1
         2: invokespecial #7                  // Method org/apache/commons/io/output/ProxyOutputStream.write:(I)V
         5: aload_0
         6: getfield      #2                  // Field branch:Ljava/io/OutputStream;
         9: iload_1
        10: invokevirtual #8                  // Method java/io/OutputStream.write:(I)V
        13: return
      LineNumberTable:
        line 72: 0
        line 73: 5
        line 74: 13
      LocalVariableTable:
        Start  Length  Slot  Name   Signature
            0      14     0  this   Lorg/apache/commons/io/output/TeeOutputStream;
            0      14     1     b   I
    Exceptions:
      throws java.io.IOException

  public void flush() throws java.io.IOException;
    descriptor: ()V
    flags: (0x0001) ACC_PUBLIC
    Code:
      stack=1, locals=1, args_size=1
         0: aload_0
         1: invokespecial #9                  // Method org/apache/commons/io/output/ProxyOutputStream.flush:()V
         4: aload_0
         5: getfield      #2                  // Field branch:Ljava/io/OutputStream;
         8: invokevirtual #10                 // Method java/io/OutputStream.flush:()V
        11: return
      LineNumberTable:
        line 82: 0
        line 83: 4
        line 84: 11
      LocalVariableTable:
        Start  Length  Slot  Name   Signature
            0      12     0  this   Lorg/apache/commons/io/output/TeeOutputStream;
    Exceptions:
      throws java.io.IOException

  public void close() throws java.io.IOException;
    descriptor: ()V
    flags: (0x0001) ACC_PUBLIC
    Code:
      stack=1, locals=2, args_size=1
         0: aload_0
         1: invokespecial #11                 // Method org/apache/commons/io/output/ProxyOutputStream.close:()V
         4: aload_0
         5: getfield      #2                  // Field branch:Ljava/io/OutputStream;
         8: invokevirtual #12                 // Method java/io/OutputStream.close:()V
        11: goto          24
        14: astore_1
        15: aload_0
        16: getfield      #2                  // Field branch:Ljava/io/OutputStream;
        19: invokevirtual #12                 // Method java/io/OutputStream.close:()V
        22: aload_1
        23: athrow
        24: return
      Exception table:
         from    to  target type
             0     4    14   any
      LineNumberTable:
        line 100: 0
        line 102: 4
        line 103: 11
        line 102: 14
        line 103: 22
        line 104: 24
      LocalVariableTable:
        Start  Length  Slot  Name   Signature
            0      25     0  this   Lorg/apache/commons/io/output/TeeOutputStream;
      StackMapTable: number_of_entries = 2
        frame_type = 78 /* same_locals_1_stack_item */
          stack = [ class java/lang/Throwable ]
        frame_type = 9 /* same */
    Exceptions:
      throws java.io.IOException
}
SourceFile: "TeeOutputStream.java"
