Classfile /Users/mw/Projects/slang-braindump/.jar/jar11/assemble/slang-braindump/assemble/content/scala/compat/java8/converterImpl/AccumulateLongCollection.class
  Last modified May 29, 2022; size 2940 bytes
  SHA-256 checksum 174aa18968a9c4bdba0164d1f95af14b7e536664885145dc1451357cde0e991c
  Compiled from "Accumulates.scala"
public final class scala.compat.java8.converterImpl.AccumulateLongCollection
  minor version: 0
  major version: 52
  flags: (0x0031) ACC_PUBLIC, ACC_FINAL, ACC_SUPER
  this_class: #2                          // scala/compat/java8/converterImpl/AccumulateLongCollection
  super_class: #4                         // java/lang/Object
  interfaces: 0, fields: 1, methods: 8, attributes: 4
Constant pool:
   #1 = Utf8               scala/compat/java8/converterImpl/AccumulateLongCollection
   #2 = Class              #1             // scala/compat/java8/converterImpl/AccumulateLongCollection
   #3 = Utf8               java/lang/Object
   #4 = Class              #3             // java/lang/Object
   #5 = Utf8               Accumulates.scala
   #6 = Utf8               Lscala/reflect/ScalaSignature;
   #7 = Utf8               bytes
   #8 = Utf8               \u0006\u0005\u00194A!\u0004\b\u0003/!aA\u0004\u0001C\u0001\u0002\u000b\u0015)\u0019!C\u0005;!IQ\u0006\u0001B\u0003\u0002\u0003\u0006IA\b\u0005\u0006]\u0001!\ta\f\u0005\u0006i\u0001!\t!\u000e\u0005\b\t\u0002\t\t\u0011\"\u0011F\u0011\u001dI\u0005!!A\u0005B);qa\u0015\b\u0002\u0002#\u0005AKB\u0004\u000e\u001d\u0005\u0005\t\u0012A+\t\u000b9BA\u0011A-\t\u000biCAQA.\t\u000fyC\u0011\u0011!C\u0003?\"9\u0011\rCA\u0001\n\u000b\u0011\'\u0001G!dGVlW\u000f\\1uK2{gnZ\"pY2,7\r^5p]*\u0011q\u0002E\u0001\u000eG>tg/\u001a:uKJLU\u000e\u001d7\u000b\u0005E\u0011\u0012!\u00026bm\u0006D$BA\n\u0015\u0003\u0019\u0019w.\u001c9bi*\tQ#A\u0003tG\u0006d\u0017m\u0001\u0001\u0014\u0005\u0001A\u0002CA\r\u001b\u001b\u0005!\u0012BA\u000e\u0015\u0005\u0019\te.\u001f,bY\u0006)5oY1mC\u0012\u001aw.\u001c9bi\u0012R\u0017M^19I\r|gN^3si\u0016\u0014\u0018*\u001c9mI\u0005\u001b7-^7vY\u0006$X\rT8oO\u000e{G\u000e\\3di&|g\u000e\n\u0013v]\u0012,\'\u000f\\=j]\u001e,\u0012A\b\t\u0004?\u001dRcB\u0001\u0011&\u001d\t\tC%D\u0001#\u0015\t\u0019c#\u0001\u0004=e>|GOP\u0005\u0002+%\u0011a\u0005F\u0001\ba\u0006\u001c7.Y4f\u0013\tA\u0013F\u0001\u0007Ji\u0016\u0014\u0018M\u00197f\u001f:\u001cWM\u0003\u0002\')A\u0011\u0011dK\u0005\u0003YQ\u0011A\u0001T8oO\u000615oY1mC\u0012\u001aw.\u001c9bi\u0012R\u0017M^19I\r|gN^3si\u0016\u0014\u0018*\u001c9mI\u0005\u001b7-^7vY\u0006$X\rT8oO\u000e{G\u000e\\3di&|g\u000e\n\u0013v]\u0012,\'\u000f\\=j]\u001e\u0004\u0013A\u0002\u001fj]&$h\b\u0006\u00021eA\u0011\u0011\u0007A\u0007\u0002\u001d!)1g\u0001a\u0001=\u0005QQO\u001c3fe2L\u0018N\\4\u0002\u0015\u0005\u001c7-^7vY\u0006$X-F\u00017!\t9\u0014I\u0004\u00029\u007f9\u0011\u0011(\u0010\b\u0003uqr!\u0001I\u001e\n\u0005M!\u0012BA\t\u0013\u0013\tq\u0004#\u0001\bd_2dWm\u0019;j_:LU\u000e\u001d7\n\u0005\u0019\u0002%B\u0001 \u0011\u0013\t\u00115IA\bM_:<\u0017iY2v[Vd\u0017\r^8s\u0015\t1\u0003)\u0001\u0005iCND7i\u001c3f)\u00051\u0005CA\rH\u0013\tAECA\u0002J]R\fa!Z9vC2\u001cHCA&O!\tIB*\u0003\u0002N)\t9!i\\8mK\u0006t\u0007bB(\u0007\u0003\u0003\u0005\r\u0001U\u0001\u0004q\u0012\n\u0004CA\rR\u0013\t\u0011FCA\u0002B]f\f\u0001$Q2dk6,H.\u0019;f\u0019>twmQ8mY\u0016\u001cG/[8o!\t\t\u0004b\u0005\u0002\t-B\u0011\u0011dV\u0005\u00031R\u0011a!\u00118z%\u00164G#\u0001+\u0002)\u0005\u001c7-^7vY\u0006$X\rJ3yi\u0016t7/[8o)\t1D\fC\u0003^\u0015\u0001\u0007\u0001\'A\u0003%i\"L7/\u0001\niCND7i\u001c3fI\u0015DH/\u001a8tS>tGCA#a\u0011\u0015i6\u00021\u00011\u0003A)\u0017/^1mg\u0012*\u0007\u0010^3og&|g\u000e\u0006\u0002dKR\u00111\n\u001a\u0005\b\u001f2\t\t\u00111\u0001Q\u0011\u0015iF\u00021\u00011\u0001
   #9 = Utf8               scala$compat$java8$converterImpl$AccumulateLongCollection$$underlying
  #10 = Utf8               Lscala/collection/IterableOnce;
  #11 = Utf8               Lscala/collection/IterableOnce<Ljava/lang/Object;>;
  #12 = Utf8               equals$extension
  #13 = Utf8               (Lscala/collection/IterableOnce;Ljava/lang/Object;)Z
  #14 = Utf8               $this
  #15 = Utf8               x$1
  #16 = Utf8               scala/compat/java8/converterImpl/AccumulateLongCollection$
  #17 = Class              #16            // scala/compat/java8/converterImpl/AccumulateLongCollection$
  #18 = Utf8               MODULE$
  #19 = Utf8               Lscala/compat/java8/converterImpl/AccumulateLongCollection$;
  #20 = NameAndType        #18:#19        // MODULE$:Lscala/compat/java8/converterImpl/AccumulateLongCollection$;
  #21 = Fieldref           #17.#20        // scala/compat/java8/converterImpl/AccumulateLongCollection$.MODULE$:Lscala/compat/java8/converterImpl/AccumulateLongCollection$;
  #22 = NameAndType        #12:#13        // equals$extension:(Lscala/collection/IterableOnce;Ljava/lang/Object;)Z
  #23 = Methodref          #17.#22        // scala/compat/java8/converterImpl/AccumulateLongCollection$.equals$extension:(Lscala/collection/IterableOnce;Ljava/lang/Object;)Z
  #24 = Utf8               Ljava/lang/Object;
  #25 = Utf8               hashCode$extension
  #26 = Utf8               (Lscala/collection/IterableOnce;)I
  #27 = NameAndType        #25:#26        // hashCode$extension:(Lscala/collection/IterableOnce;)I
  #28 = Methodref          #17.#27        // scala/compat/java8/converterImpl/AccumulateLongCollection$.hashCode$extension:(Lscala/collection/IterableOnce;)I
  #29 = Utf8               accumulate$extension
  #30 = Utf8               (Lscala/collection/IterableOnce;)Lscala/jdk/LongAccumulator;
  #31 = NameAndType        #29:#30        // accumulate$extension:(Lscala/collection/IterableOnce;)Lscala/jdk/LongAccumulator;
  #32 = Methodref          #17.#31        // scala/compat/java8/converterImpl/AccumulateLongCollection$.accumulate$extension:(Lscala/collection/IterableOnce;)Lscala/jdk/LongAccumulator;
  #33 = Utf8               ()Lscala/collection/IterableOnce;
  #34 = Utf8               ()Lscala/collection/IterableOnce<Ljava/lang/Object;>;
  #35 = NameAndType        #9:#10         // scala$compat$java8$converterImpl$AccumulateLongCollection$$underlying:Lscala/collection/IterableOnce;
  #36 = Fieldref           #2.#35         // scala/compat/java8/converterImpl/AccumulateLongCollection.scala$compat$java8$converterImpl$AccumulateLongCollection$$underlying:Lscala/collection/IterableOnce;
  #37 = Utf8               this
  #38 = Utf8               Lscala/compat/java8/converterImpl/AccumulateLongCollection;
  #39 = Utf8               accumulate
  #40 = Utf8               ()Lscala/jdk/LongAccumulator;
  #41 = NameAndType        #9:#33         // scala$compat$java8$converterImpl$AccumulateLongCollection$$underlying:()Lscala/collection/IterableOnce;
  #42 = Methodref          #2.#41         // scala/compat/java8/converterImpl/AccumulateLongCollection.scala$compat$java8$converterImpl$AccumulateLongCollection$$underlying:()Lscala/collection/IterableOnce;
  #43 = Utf8               hashCode
  #44 = Utf8               ()I
  #45 = Utf8               equals
  #46 = Utf8               (Ljava/lang/Object;)Z
  #47 = Utf8               <init>
  #48 = Utf8               (Lscala/collection/IterableOnce;)V
  #49 = Utf8               (Lscala/collection/IterableOnce<Ljava/lang/Object;>;)V
  #50 = Utf8               underlying
  #51 = Utf8               ()V
  #52 = NameAndType        #47:#51        // "<init>":()V
  #53 = Methodref          #4.#52         // java/lang/Object."<init>":()V
  #54 = Utf8               Signature
  #55 = Utf8               Code
  #56 = Utf8               LocalVariableTable
  #57 = Utf8               MethodParameters
  #58 = Utf8               LineNumberTable
  #59 = Utf8               SourceFile
  #60 = Utf8               RuntimeVisibleAnnotations
  #61 = Utf8               ScalaInlineInfo
  #62 = Utf8               ScalaSig
{
  private final scala.collection.IterableOnce<java.lang.Object> scala$compat$java8$converterImpl$AccumulateLongCollection$$underlying;
    descriptor: Lscala/collection/IterableOnce;
    flags: (0x0012) ACC_PRIVATE, ACC_FINAL
    Signature: #11                          // Lscala/collection/IterableOnce<Ljava/lang/Object;>;

  public static boolean equals$extension(scala.collection.IterableOnce, java.lang.Object);
    descriptor: (Lscala/collection/IterableOnce;Ljava/lang/Object;)Z
    flags: (0x0009) ACC_PUBLIC, ACC_STATIC
    Code:
      stack=3, locals=2, args_size=2
         0: getstatic     #21                 // Field scala/compat/java8/converterImpl/AccumulateLongCollection$.MODULE$:Lscala/compat/java8/converterImpl/AccumulateLongCollection$;
         3: aload_0
         4: aload_1
         5: invokevirtual #23                 // Method scala/compat/java8/converterImpl/AccumulateLongCollection$.equals$extension:(Lscala/collection/IterableOnce;Ljava/lang/Object;)Z
         8: ireturn
      LocalVariableTable:
        Start  Length  Slot  Name   Signature
            0       9     0 $this   Lscala/collection/IterableOnce;
            0       9     1   x$1   Ljava/lang/Object;
    MethodParameters:
      Name                           Flags
      $this                          final
      x$1                            final

  public static int hashCode$extension(scala.collection.IterableOnce);
    descriptor: (Lscala/collection/IterableOnce;)I
    flags: (0x0009) ACC_PUBLIC, ACC_STATIC
    Code:
      stack=2, locals=1, args_size=1
         0: getstatic     #21                 // Field scala/compat/java8/converterImpl/AccumulateLongCollection$.MODULE$:Lscala/compat/java8/converterImpl/AccumulateLongCollection$;
         3: aload_0
         4: invokevirtual #28                 // Method scala/compat/java8/converterImpl/AccumulateLongCollection$.hashCode$extension:(Lscala/collection/IterableOnce;)I
         7: ireturn
      LocalVariableTable:
        Start  Length  Slot  Name   Signature
            0       8     0 $this   Lscala/collection/IterableOnce;
    MethodParameters:
      Name                           Flags
      $this                          final

  public static scala.jdk.LongAccumulator accumulate$extension(scala.collection.IterableOnce);
    descriptor: (Lscala/collection/IterableOnce;)Lscala/jdk/LongAccumulator;
    flags: (0x0009) ACC_PUBLIC, ACC_STATIC
    Code:
      stack=2, locals=1, args_size=1
         0: getstatic     #21                 // Field scala/compat/java8/converterImpl/AccumulateLongCollection$.MODULE$:Lscala/compat/java8/converterImpl/AccumulateLongCollection$;
         3: aload_0
         4: invokevirtual #32                 // Method scala/compat/java8/converterImpl/AccumulateLongCollection$.accumulate$extension:(Lscala/collection/IterableOnce;)Lscala/jdk/LongAccumulator;
         7: areturn
      LocalVariableTable:
        Start  Length  Slot  Name   Signature
            0       8     0 $this   Lscala/collection/IterableOnce;
    MethodParameters:
      Name                           Flags
      $this                          final

  public scala.collection.IterableOnce<java.lang.Object> scala$compat$java8$converterImpl$AccumulateLongCollection$$underlying();
    descriptor: ()Lscala/collection/IterableOnce;
    flags: (0x0001) ACC_PUBLIC
    Code:
      stack=1, locals=1, args_size=1
         0: aload_0
         1: getfield      #36                 // Field scala$compat$java8$converterImpl$AccumulateLongCollection$$underlying:Lscala/collection/IterableOnce;
         4: areturn
      LineNumberTable:
        line 29: 0
      LocalVariableTable:
        Start  Length  Slot  Name   Signature
            0       5     0  this   Lscala/compat/java8/converterImpl/AccumulateLongCollection;
    Signature: #34                          // ()Lscala/collection/IterableOnce<Ljava/lang/Object;>;

  public scala.jdk.LongAccumulator accumulate();
    descriptor: ()Lscala/jdk/LongAccumulator;
    flags: (0x0001) ACC_PUBLIC
    Code:
      stack=2, locals=1, args_size=1
         0: getstatic     #21                 // Field scala/compat/java8/converterImpl/AccumulateLongCollection$.MODULE$:Lscala/compat/java8/converterImpl/AccumulateLongCollection$;
         3: aload_0
         4: invokevirtual #42                 // Method scala$compat$java8$converterImpl$AccumulateLongCollection$$underlying:()Lscala/collection/IterableOnce;
         7: invokevirtual #32                 // Method scala/compat/java8/converterImpl/AccumulateLongCollection$.accumulate$extension:(Lscala/collection/IterableOnce;)Lscala/jdk/LongAccumulator;
        10: areturn
      LineNumberTable:
        line 30: 0
      LocalVariableTable:
        Start  Length  Slot  Name   Signature
            0      11     0  this   Lscala/compat/java8/converterImpl/AccumulateLongCollection;

  public int hashCode();
    descriptor: ()I
    flags: (0x0001) ACC_PUBLIC
    Code:
      stack=2, locals=1, args_size=1
         0: getstatic     #21                 // Field scala/compat/java8/converterImpl/AccumulateLongCollection$.MODULE$:Lscala/compat/java8/converterImpl/AccumulateLongCollection$;
         3: aload_0
         4: invokevirtual #42                 // Method scala$compat$java8$converterImpl$AccumulateLongCollection$$underlying:()Lscala/collection/IterableOnce;
         7: invokevirtual #28                 // Method scala/compat/java8/converterImpl/AccumulateLongCollection$.hashCode$extension:(Lscala/collection/IterableOnce;)I
        10: ireturn
      LineNumberTable:
        line 29: 0
      LocalVariableTable:
        Start  Length  Slot  Name   Signature
            0      11     0  this   Lscala/compat/java8/converterImpl/AccumulateLongCollection;

  public boolean equals(java.lang.Object);
    descriptor: (Ljava/lang/Object;)Z
    flags: (0x0001) ACC_PUBLIC
    Code:
      stack=3, locals=2, args_size=2
         0: getstatic     #21                 // Field scala/compat/java8/converterImpl/AccumulateLongCollection$.MODULE$:Lscala/compat/java8/converterImpl/AccumulateLongCollection$;
         3: aload_0
         4: invokevirtual #42                 // Method scala$compat$java8$converterImpl$AccumulateLongCollection$$underlying:()Lscala/collection/IterableOnce;
         7: aload_1
         8: invokevirtual #23                 // Method scala/compat/java8/converterImpl/AccumulateLongCollection$.equals$extension:(Lscala/collection/IterableOnce;Ljava/lang/Object;)Z
        11: ireturn
      LineNumberTable:
        line 29: 0
      LocalVariableTable:
        Start  Length  Slot  Name   Signature
            0      12     0  this   Lscala/compat/java8/converterImpl/AccumulateLongCollection;
            0      12     1   x$1   Ljava/lang/Object;
    MethodParameters:
      Name                           Flags
      x$1                            final

  public scala.compat.java8.converterImpl.AccumulateLongCollection(scala.collection.IterableOnce<java.lang.Object>);
    descriptor: (Lscala/collection/IterableOnce;)V
    flags: (0x0001) ACC_PUBLIC
    Code:
      stack=2, locals=2, args_size=2
         0: aload_0
         1: aload_1
         2: putfield      #36                 // Field scala$compat$java8$converterImpl$AccumulateLongCollection$$underlying:Lscala/collection/IterableOnce;
         5: aload_0
         6: invokespecial #53                 // Method java/lang/Object."<init>":()V
         9: return
      LineNumberTable:
        line 29: 0
      LocalVariableTable:
        Start  Length  Slot  Name   Signature
            0      10     0  this   Lscala/compat/java8/converterImpl/AccumulateLongCollection;
            0      10     1 underlying   Lscala/collection/IterableOnce;
    Signature: #49                          // (Lscala/collection/IterableOnce<Ljava/lang/Object;>;)V
    MethodParameters:
      Name                           Flags
      underlying                     final
}
SourceFile: "Accumulates.scala"
RuntimeVisibleAnnotations:
  0: #6(#7=s#8)
    scala.reflect.ScalaSignature(
      bytes="\u0006\u0005\u00194A!\u0004\b\u0003/!aA\u0004\u0001C\u0001\u0002\u000b\u0015)\u0019!C\u0005;!IQ\u0006\u0001B\u0003\u0002\u0003\u0006IA\b\u0005\u0006]\u0001!\ta\f\u0005\u0006i\u0001!\t!\u000e\u0005\b\t\u0002\t\t\u0011\"\u0011F\u0011\u001dI\u0005!!A\u0005B);qa\u0015\b\u0002\u0002#\u0005AKB\u0004\u000e\u001d\u0005\u0005\t\u0012A+\t\u000b9BA\u0011A-\t\u000biCAQA.\t\u000fyC\u0011\u0011!C\u0003?\"9\u0011\rCA\u0001\n\u000b\u0011\'\u0001G!dGVlW\u000f\\1uK2{gnZ\"pY2,7\r^5p]*\u0011q\u0002E\u0001\u000eG>tg/\u001a:uKJLU\u000e\u001d7\u000b\u0005E\u0011\u0012!\u00026bm\u0006D$BA\n\u0015\u0003\u0019\u0019w.\u001c9bi*\tQ#A\u0003tG\u0006d\u0017m\u0001\u0001\u0014\u0005\u0001A\u0002CA\r\u001b\u001b\u0005!\u0012BA\u000e\u0015\u0005\u0019\te.\u001f,bY\u0006)5oY1mC\u0012\u001aw.\u001c9bi\u0012R\u0017M^19I\r|gN^3si\u0016\u0014\u0018*\u001c9mI\u0005\u001b7-^7vY\u0006$X\rT8oO\u000e{G\u000e\\3di&|g\u000e\n\u0013v]\u0012,\'\u000f\\=j]\u001e,\u0012A\b\t\u0004?\u001dRcB\u0001\u0011&\u001d\t\tC%D\u0001#\u0015\t\u0019c#\u0001\u0004=e>|GOP\u0005\u0002+%\u0011a\u0005F\u0001\ba\u0006\u001c7.Y4f\u0013\tA\u0013F\u0001\u0007Ji\u0016\u0014\u0018M\u00197f\u001f:\u001cWM\u0003\u0002\')A\u0011\u0011dK\u0005\u0003YQ\u0011A\u0001T8oO\u000615oY1mC\u0012\u001aw.\u001c9bi\u0012R\u0017M^19I\r|gN^3si\u0016\u0014\u0018*\u001c9mI\u0005\u001b7-^7vY\u0006$X\rT8oO\u000e{G\u000e\\3di&|g\u000e\n\u0013v]\u0012,\'\u000f\\=j]\u001e\u0004\u0013A\u0002\u001fj]&$h\b\u0006\u00021eA\u0011\u0011\u0007A\u0007\u0002\u001d!)1g\u0001a\u0001=\u0005QQO\u001c3fe2L\u0018N\\4\u0002\u0015\u0005\u001c7-^7vY\u0006$X-F\u00017!\t9\u0014I\u0004\u00029\u007f9\u0011\u0011(\u0010\b\u0003uqr!\u0001I\u001e\n\u0005M!\u0012BA\t\u0013\u0013\tq\u0004#\u0001\bd_2dWm\u0019;j_:LU\u000e\u001d7\n\u0005\u0019\u0002%B\u0001 \u0011\u0013\t\u00115IA\bM_:<\u0017iY2v[Vd\u0017\r^8s\u0015\t1\u0003)\u0001\u0005iCND7i\u001c3f)\u00051\u0005CA\rH\u0013\tAECA\u0002J]R\fa!Z9vC2\u001cHCA&O!\tIB*\u0003\u0002N)\t9!i\\8mK\u0006t\u0007bB(\u0007\u0003\u0003\u0005\r\u0001U\u0001\u0004q\u0012\n\u0004CA\rR\u0013\t\u0011FCA\u0002B]f\f\u0001$Q2dk6,H.\u0019;f\u0019>twmQ8mY\u0016\u001cG/[8o!\t\t\u0004b\u0005\u0002\t-B\u0011\u0011dV\u0005\u00031R\u0011a!\u00118z%\u00164G#\u0001+\u0002)\u0005\u001c7-^7vY\u0006$X\rJ3yi\u0016t7/[8o)\t1D\fC\u0003^\u0015\u0001\u0007\u0001\'A\u0003%i\"L7/\u0001\niCND7i\u001c3fI\u0015DH/\u001a8tS>tGCA#a\u0011\u0015i6\u00021\u00011\u0003A)\u0017/^1mg\u0012*\u0007\u0010^3og&|g\u000e\u0006\u0002dKR\u00111\n\u001a\u0005\b\u001f2\t\t\u00111\u0001Q\u0011\u0015iF\u00021\u00011\u0001"
    )
  ScalaInlineInfo: length = 0x1D (unknown attribute)
   01 01 00 05 00 2F 00 30 01 00 27 00 28 01 00 2D
   00 2E 01 00 2B 00 2C 01 00 09 00 21 01
  ScalaSig: length = 0x3 (unknown attribute)
   05 02 00
