Classfile /Users/mw/Projects/slang-braindump/.jar/jar11/assemble/slang-braindump/assemble/content/scala/compat/java8/converterImpl/AccumulateAnyArray.class
  Last modified May 29, 2022; size 3000 bytes
  SHA-256 checksum 95450057f878753357c1f4438da9c652cf8a3349e8752fb565f0bfa940b19c90
  Compiled from "Accumulates.scala"
public final class scala.compat.java8.converterImpl.AccumulateAnyArray<A extends java.lang.Object> extends java.lang.Object
  minor version: 0
  major version: 52
  flags: (0x0031) ACC_PUBLIC, ACC_FINAL, ACC_SUPER
  this_class: #2                          // scala/compat/java8/converterImpl/AccumulateAnyArray
  super_class: #5                         // java/lang/Object
  interfaces: 0, fields: 1, methods: 8, attributes: 5
Constant pool:
   #1 = Utf8               scala/compat/java8/converterImpl/AccumulateAnyArray
   #2 = Class              #1             // scala/compat/java8/converterImpl/AccumulateAnyArray
   #3 = Utf8               <A:Ljava/lang/Object;>Ljava/lang/Object;
   #4 = Utf8               java/lang/Object
   #5 = Class              #4             // java/lang/Object
   #6 = Utf8               Accumulates.scala
   #7 = Utf8               Lscala/reflect/ScalaSignature;
   #8 = Utf8               bytes
   #9 = Utf8               \u0006\u0005Y4A!\u0004\b\u0003/!aQ\u0004\u0001C\u0001\u0002\u000b\u0015)\u0019!C\u0005=!IQ\u0006\u0001B\u0003\u0002\u0003\u0006Ia\b\u0005\u0006]\u0001!\ta\f\u0005\u0006i\u0001!\t!\u000e\u0005\b\u0015\u0002\t\t\u0011\"\u0011L\u0011\u001dy\u0005!!A\u0005BA;qA\u0016\b\u0002\u0002#\u0005qKB\u0004\u000e\u001d\u0005\u0005\t\u0012\u0001-\t\u000b9BA\u0011\u0001/\t\u000buCAQ\u00010\t\u000f\u0019D\u0011\u0011!C\u0003O\"9Q\u000eCA\u0001\n\u000bq\'AE!dGVlW\u000f\\1uK\u0006s\u00170\u0011:sCfT!a\u0004\t\u0002\u001b\r|gN^3si\u0016\u0014\u0018*\u001c9m\u0015\t\t\"#A\u0003kCZ\f\u0007H\u0003\u0002\u0014)\u000511m\\7qCRT\u0011!F\u0001\u0006g\u000e\fG.Y\u0002\u0001+\tABe\u0005\u0002\u00013A\u0011!dG\u0007\u0002)%\u0011A\u0004\u0006\u0002\u0007\u0003:Lh+\u00197\u0002\u007fM\u001c\u0017\r\\1%G>l\u0007/\u0019;%U\u00064\u0018\r\u000f\u0013d_:4XM\u001d;fe&k\u0007\u000f\u001c\u0013BG\u000e,X.\u001e7bi\u0016\fe._!se\u0006LH\u0005J;oI\u0016\u0014H._5oOV\tq\u0004E\u0002\u001bA\tJ!!\t\u000b\u0003\u000b\u0005\u0013(/Y=\u0011\u0005\r\"C\u0002\u0001\u0003\u0006K\u0001\u0011\rA\n\u0002\u0002\u0003F\u0011qE\u000b\t\u00035!J!!\u000b\u000b\u0003\u000f9{G\u000f[5oOB\u0011!dK\u0005\u0003YQ\u00111!\u00118z\u0003\u0001\u001b8-\u00197bI\r|W\u000e]1uI)\fg/\u0019\u001d%G>tg/\u001a:uKJLU\u000e\u001d7%\u0003\u000e\u001cW/\\;mCR,\u0017I\\=BeJ\f\u0017\u0010\n\u0013v]\u0012,\'\u000f\\=j]\u001e\u0004\u0013A\u0002\u001fj]&$h\b\u0006\u00021eA\u0019\u0011\u0007\u0001\u0012\u000e\u00039AQaM\u0002A\u0002}\t!\"\u001e8eKJd\u00170\u001b8h\u0003)\t7mY;nk2\fG/Z\u000b\u0002mA\u0019qg\u0012\u0012\u000f\u0005a\"eBA\u001dC\u001d\tQ\u0014I\u0004\u0002<\u0001:\u0011AhP\u0007\u0002{)\u0011aHF\u0001\u0007yI|w\u000e\u001e \n\u0003UI!a\u0005\u000b\n\u0005E\u0011\u0012BA\"\u0011\u00039\u0019w\u000e\u001c7fGRLwN\\%na2L!!\u0012$\u0002\u000fA\f7m[1hK*\u00111\tE\u0005\u0003\u0011&\u00131\"Q2dk6,H.\u0019;pe*\u0011QIR\u0001\tQ\u0006\u001c\bnQ8eKR\tA\n\u0005\u0002\u001b\u001b&\u0011a\n\u0006\u0002\u0004\u0013:$\u0018AB3rk\u0006d7\u000f\u0006\u0002R)B\u0011!DU\u0005\u0003\'R\u0011qAQ8pY\u0016\fg\u000eC\u0004V\r\u0005\u0005\t\u0019\u0001\u0016\u0002\u0007a$\u0013\'\u0001\nBG\u000e,X.\u001e7bi\u0016\fe._!se\u0006L\bCA\u0019\t\'\tA\u0011\f\u0005\u0002\u001b5&\u00111\f\u0006\u0002\u0007\u0003:L(+\u001a4\u0015\u0003]\u000bA#Y2dk6,H.\u0019;fI\u0015DH/\u001a8tS>tWCA0c)\t\u00017\rE\u00028\u000f\u0006\u0004\"a\t2\u0005\u000b\u0015R!\u0019\u0001\u0014\t\u000b\u0011T\u0001\u0019A3\u0002\u000b\u0011\"\b.[:\u0011\u0007E\u0002\u0011-\u0001\niCND7i\u001c3fI\u0015DH/\u001a8tS>tWC\u00015m)\tY\u0015\u000eC\u0003e\u0017\u0001\u0007!\u000eE\u00022\u0001-\u0004\"a\t7\u0005\u000b\u0015Z!\u0019\u0001\u0014\u0002!\u0015\fX/\u00197tI\u0015DH/\u001a8tS>tWCA8v)\t\u0001(\u000f\u0006\u0002Rc\"9Q\u000bDA\u0001\u0002\u0004Q\u0003\"\u00023\r\u0001\u0004\u0019\bcA\u0019\u0001iB\u00111%\u001e\u0003\u0006K1\u0011\rA\n
  #10 = Utf8               scala$compat$java8$converterImpl$AccumulateAnyArray$$underlying
  #11 = Utf8               Ljava/lang/Object;
  #12 = Utf8               equals$extension
  #13 = Utf8               (Ljava/lang/Object;Ljava/lang/Object;)Z
  #14 = Utf8               <A:Ljava/lang/Object;>(Ljava/lang/Object;Ljava/lang/Object;)Z
  #15 = Utf8               $this
  #16 = Utf8               x$1
  #17 = Utf8               scala/compat/java8/converterImpl/AccumulateAnyArray$
  #18 = Class              #17            // scala/compat/java8/converterImpl/AccumulateAnyArray$
  #19 = Utf8               MODULE$
  #20 = Utf8               Lscala/compat/java8/converterImpl/AccumulateAnyArray$;
  #21 = NameAndType        #19:#20        // MODULE$:Lscala/compat/java8/converterImpl/AccumulateAnyArray$;
  #22 = Fieldref           #18.#21        // scala/compat/java8/converterImpl/AccumulateAnyArray$.MODULE$:Lscala/compat/java8/converterImpl/AccumulateAnyArray$;
  #23 = NameAndType        #12:#13        // equals$extension:(Ljava/lang/Object;Ljava/lang/Object;)Z
  #24 = Methodref          #18.#23        // scala/compat/java8/converterImpl/AccumulateAnyArray$.equals$extension:(Ljava/lang/Object;Ljava/lang/Object;)Z
  #25 = Utf8               hashCode$extension
  #26 = Utf8               (Ljava/lang/Object;)I
  #27 = Utf8               <A:Ljava/lang/Object;>(Ljava/lang/Object;)I
  #28 = NameAndType        #25:#26        // hashCode$extension:(Ljava/lang/Object;)I
  #29 = Methodref          #18.#28        // scala/compat/java8/converterImpl/AccumulateAnyArray$.hashCode$extension:(Ljava/lang/Object;)I
  #30 = Utf8               accumulate$extension
  #31 = Utf8               (Ljava/lang/Object;)Lscala/jdk/AnyAccumulator;
  #32 = Utf8               <A:Ljava/lang/Object;>(Ljava/lang/Object;)Lscala/jdk/AnyAccumulator<TA;>;
  #33 = NameAndType        #30:#31        // accumulate$extension:(Ljava/lang/Object;)Lscala/jdk/AnyAccumulator;
  #34 = Methodref          #18.#33        // scala/compat/java8/converterImpl/AccumulateAnyArray$.accumulate$extension:(Ljava/lang/Object;)Lscala/jdk/AnyAccumulator;
  #35 = Utf8               ()Ljava/lang/Object;
  #36 = NameAndType        #10:#11        // scala$compat$java8$converterImpl$AccumulateAnyArray$$underlying:Ljava/lang/Object;
  #37 = Fieldref           #2.#36         // scala/compat/java8/converterImpl/AccumulateAnyArray.scala$compat$java8$converterImpl$AccumulateAnyArray$$underlying:Ljava/lang/Object;
  #38 = Utf8               this
  #39 = Utf8               Lscala/compat/java8/converterImpl/AccumulateAnyArray;
  #40 = Utf8               accumulate
  #41 = Utf8               ()Lscala/jdk/AnyAccumulator;
  #42 = Utf8               ()Lscala/jdk/AnyAccumulator<TA;>;
  #43 = NameAndType        #10:#35        // scala$compat$java8$converterImpl$AccumulateAnyArray$$underlying:()Ljava/lang/Object;
  #44 = Methodref          #2.#43         // scala/compat/java8/converterImpl/AccumulateAnyArray.scala$compat$java8$converterImpl$AccumulateAnyArray$$underlying:()Ljava/lang/Object;
  #45 = Utf8               hashCode
  #46 = Utf8               ()I
  #47 = Utf8               equals
  #48 = Utf8               (Ljava/lang/Object;)Z
  #49 = Utf8               <init>
  #50 = Utf8               (Ljava/lang/Object;)V
  #51 = Utf8               underlying
  #52 = Utf8               ()V
  #53 = NameAndType        #49:#52        // "<init>":()V
  #54 = Methodref          #5.#53         // java/lang/Object."<init>":()V
  #55 = Utf8               Signature
  #56 = Utf8               Code
  #57 = Utf8               LocalVariableTable
  #58 = Utf8               MethodParameters
  #59 = Utf8               LineNumberTable
  #60 = Utf8               SourceFile
  #61 = Utf8               RuntimeVisibleAnnotations
  #62 = Utf8               ScalaInlineInfo
  #63 = Utf8               ScalaSig
{
  private final java.lang.Object scala$compat$java8$converterImpl$AccumulateAnyArray$$underlying;
    descriptor: Ljava/lang/Object;
    flags: (0x0012) ACC_PRIVATE, ACC_FINAL
    Signature: #11                          // Ljava/lang/Object;

  public static <A extends java.lang.Object> boolean equals$extension(java.lang.Object, java.lang.Object);
    descriptor: (Ljava/lang/Object;Ljava/lang/Object;)Z
    flags: (0x0009) ACC_PUBLIC, ACC_STATIC
    Code:
      stack=3, locals=2, args_size=2
         0: getstatic     #22                 // Field scala/compat/java8/converterImpl/AccumulateAnyArray$.MODULE$:Lscala/compat/java8/converterImpl/AccumulateAnyArray$;
         3: aload_0
         4: aload_1
         5: invokevirtual #24                 // Method scala/compat/java8/converterImpl/AccumulateAnyArray$.equals$extension:(Ljava/lang/Object;Ljava/lang/Object;)Z
         8: ireturn
      LocalVariableTable:
        Start  Length  Slot  Name   Signature
            0       9     0 $this   Ljava/lang/Object;
            0       9     1   x$1   Ljava/lang/Object;
    Signature: #14                          // <A:Ljava/lang/Object;>(Ljava/lang/Object;Ljava/lang/Object;)Z
    MethodParameters:
      Name                           Flags
      $this                          final
      x$1                            final

  public static <A extends java.lang.Object> int hashCode$extension(java.lang.Object);
    descriptor: (Ljava/lang/Object;)I
    flags: (0x0009) ACC_PUBLIC, ACC_STATIC
    Code:
      stack=2, locals=1, args_size=1
         0: getstatic     #22                 // Field scala/compat/java8/converterImpl/AccumulateAnyArray$.MODULE$:Lscala/compat/java8/converterImpl/AccumulateAnyArray$;
         3: aload_0
         4: invokevirtual #29                 // Method scala/compat/java8/converterImpl/AccumulateAnyArray$.hashCode$extension:(Ljava/lang/Object;)I
         7: ireturn
      LocalVariableTable:
        Start  Length  Slot  Name   Signature
            0       8     0 $this   Ljava/lang/Object;
    Signature: #27                          // <A:Ljava/lang/Object;>(Ljava/lang/Object;)I
    MethodParameters:
      Name                           Flags
      $this                          final

  public static <A extends java.lang.Object> scala.jdk.AnyAccumulator<A> accumulate$extension(java.lang.Object);
    descriptor: (Ljava/lang/Object;)Lscala/jdk/AnyAccumulator;
    flags: (0x0009) ACC_PUBLIC, ACC_STATIC
    Code:
      stack=2, locals=1, args_size=1
         0: getstatic     #22                 // Field scala/compat/java8/converterImpl/AccumulateAnyArray$.MODULE$:Lscala/compat/java8/converterImpl/AccumulateAnyArray$;
         3: aload_0
         4: invokevirtual #34                 // Method scala/compat/java8/converterImpl/AccumulateAnyArray$.accumulate$extension:(Ljava/lang/Object;)Lscala/jdk/AnyAccumulator;
         7: areturn
      LocalVariableTable:
        Start  Length  Slot  Name   Signature
            0       8     0 $this   Ljava/lang/Object;
    Signature: #32                          // <A:Ljava/lang/Object;>(Ljava/lang/Object;)Lscala/jdk/AnyAccumulator<TA;>;
    MethodParameters:
      Name                           Flags
      $this                          final

  public java.lang.Object scala$compat$java8$converterImpl$AccumulateAnyArray$$underlying();
    descriptor: ()Ljava/lang/Object;
    flags: (0x0001) ACC_PUBLIC
    Code:
      stack=1, locals=1, args_size=1
         0: aload_0
         1: getfield      #37                 // Field scala$compat$java8$converterImpl$AccumulateAnyArray$$underlying:Ljava/lang/Object;
         4: areturn
      LineNumberTable:
        line 33: 0
      LocalVariableTable:
        Start  Length  Slot  Name   Signature
            0       5     0  this   Lscala/compat/java8/converterImpl/AccumulateAnyArray;
    Signature: #35                          // ()Ljava/lang/Object;

  public scala.jdk.AnyAccumulator<A> accumulate();
    descriptor: ()Lscala/jdk/AnyAccumulator;
    flags: (0x0001) ACC_PUBLIC
    Code:
      stack=2, locals=1, args_size=1
         0: getstatic     #22                 // Field scala/compat/java8/converterImpl/AccumulateAnyArray$.MODULE$:Lscala/compat/java8/converterImpl/AccumulateAnyArray$;
         3: aload_0
         4: invokevirtual #44                 // Method scala$compat$java8$converterImpl$AccumulateAnyArray$$underlying:()Ljava/lang/Object;
         7: invokevirtual #34                 // Method scala/compat/java8/converterImpl/AccumulateAnyArray$.accumulate$extension:(Ljava/lang/Object;)Lscala/jdk/AnyAccumulator;
        10: areturn
      LineNumberTable:
        line 34: 0
      LocalVariableTable:
        Start  Length  Slot  Name   Signature
            0      11     0  this   Lscala/compat/java8/converterImpl/AccumulateAnyArray;
    Signature: #42                          // ()Lscala/jdk/AnyAccumulator<TA;>;

  public int hashCode();
    descriptor: ()I
    flags: (0x0001) ACC_PUBLIC
    Code:
      stack=2, locals=1, args_size=1
         0: getstatic     #22                 // Field scala/compat/java8/converterImpl/AccumulateAnyArray$.MODULE$:Lscala/compat/java8/converterImpl/AccumulateAnyArray$;
         3: aload_0
         4: invokevirtual #44                 // Method scala$compat$java8$converterImpl$AccumulateAnyArray$$underlying:()Ljava/lang/Object;
         7: invokevirtual #29                 // Method scala/compat/java8/converterImpl/AccumulateAnyArray$.hashCode$extension:(Ljava/lang/Object;)I
        10: ireturn
      LineNumberTable:
        line 33: 0
      LocalVariableTable:
        Start  Length  Slot  Name   Signature
            0      11     0  this   Lscala/compat/java8/converterImpl/AccumulateAnyArray;

  public boolean equals(java.lang.Object);
    descriptor: (Ljava/lang/Object;)Z
    flags: (0x0001) ACC_PUBLIC
    Code:
      stack=3, locals=2, args_size=2
         0: getstatic     #22                 // Field scala/compat/java8/converterImpl/AccumulateAnyArray$.MODULE$:Lscala/compat/java8/converterImpl/AccumulateAnyArray$;
         3: aload_0
         4: invokevirtual #44                 // Method scala$compat$java8$converterImpl$AccumulateAnyArray$$underlying:()Ljava/lang/Object;
         7: aload_1
         8: invokevirtual #24                 // Method scala/compat/java8/converterImpl/AccumulateAnyArray$.equals$extension:(Ljava/lang/Object;Ljava/lang/Object;)Z
        11: ireturn
      LineNumberTable:
        line 33: 0
      LocalVariableTable:
        Start  Length  Slot  Name   Signature
            0      12     0  this   Lscala/compat/java8/converterImpl/AccumulateAnyArray;
            0      12     1   x$1   Ljava/lang/Object;
    MethodParameters:
      Name                           Flags
      x$1                            final

  public scala.compat.java8.converterImpl.AccumulateAnyArray(java.lang.Object);
    descriptor: (Ljava/lang/Object;)V
    flags: (0x0001) ACC_PUBLIC
    Code:
      stack=2, locals=2, args_size=2
         0: aload_0
         1: aload_1
         2: putfield      #37                 // Field scala$compat$java8$converterImpl$AccumulateAnyArray$$underlying:Ljava/lang/Object;
         5: aload_0
         6: invokespecial #54                 // Method java/lang/Object."<init>":()V
         9: return
      LineNumberTable:
        line 33: 0
      LocalVariableTable:
        Start  Length  Slot  Name   Signature
            0      10     0  this   Lscala/compat/java8/converterImpl/AccumulateAnyArray;
            0      10     1 underlying   Ljava/lang/Object;
    Signature: #50                          // (Ljava/lang/Object;)V
    MethodParameters:
      Name                           Flags
      underlying                     final
}
Signature: #3                           // <A:Ljava/lang/Object;>Ljava/lang/Object;
SourceFile: "Accumulates.scala"
RuntimeVisibleAnnotations:
  0: #7(#8=s#9)
    scala.reflect.ScalaSignature(
      bytes="\u0006\u0005Y4A!\u0004\b\u0003/!aQ\u0004\u0001C\u0001\u0002\u000b\u0015)\u0019!C\u0005=!IQ\u0006\u0001B\u0003\u0002\u0003\u0006Ia\b\u0005\u0006]\u0001!\ta\f\u0005\u0006i\u0001!\t!\u000e\u0005\b\u0015\u0002\t\t\u0011\"\u0011L\u0011\u001dy\u0005!!A\u0005BA;qA\u0016\b\u0002\u0002#\u0005qKB\u0004\u000e\u001d\u0005\u0005\t\u0012\u0001-\t\u000b9BA\u0011\u0001/\t\u000buCAQ\u00010\t\u000f\u0019D\u0011\u0011!C\u0003O\"9Q\u000eCA\u0001\n\u000bq\'AE!dGVlW\u000f\\1uK\u0006s\u00170\u0011:sCfT!a\u0004\t\u0002\u001b\r|gN^3si\u0016\u0014\u0018*\u001c9m\u0015\t\t\"#A\u0003kCZ\f\u0007H\u0003\u0002\u0014)\u000511m\\7qCRT\u0011!F\u0001\u0006g\u000e\fG.Y\u0002\u0001+\tABe\u0005\u0002\u00013A\u0011!dG\u0007\u0002)%\u0011A\u0004\u0006\u0002\u0007\u0003:Lh+\u00197\u0002\u007fM\u001c\u0017\r\\1%G>l\u0007/\u0019;%U\u00064\u0018\r\u000f\u0013d_:4XM\u001d;fe&k\u0007\u000f\u001c\u0013BG\u000e,X.\u001e7bi\u0016\fe._!se\u0006LH\u0005J;oI\u0016\u0014H._5oOV\tq\u0004E\u0002\u001bA\tJ!!\t\u000b\u0003\u000b\u0005\u0013(/Y=\u0011\u0005\r\"C\u0002\u0001\u0003\u0006K\u0001\u0011\rA\n\u0002\u0002\u0003F\u0011qE\u000b\t\u00035!J!!\u000b\u000b\u0003\u000f9{G\u000f[5oOB\u0011!dK\u0005\u0003YQ\u00111!\u00118z\u0003\u0001\u001b8-\u00197bI\r|W\u000e]1uI)\fg/\u0019\u001d%G>tg/\u001a:uKJLU\u000e\u001d7%\u0003\u000e\u001cW/\\;mCR,\u0017I\\=BeJ\f\u0017\u0010\n\u0013v]\u0012,\'\u000f\\=j]\u001e\u0004\u0013A\u0002\u001fj]&$h\b\u0006\u00021eA\u0019\u0011\u0007\u0001\u0012\u000e\u00039AQaM\u0002A\u0002}\t!\"\u001e8eKJd\u00170\u001b8h\u0003)\t7mY;nk2\fG/Z\u000b\u0002mA\u0019qg\u0012\u0012\u000f\u0005a\"eBA\u001dC\u001d\tQ\u0014I\u0004\u0002<\u0001:\u0011AhP\u0007\u0002{)\u0011aHF\u0001\u0007yI|w\u000e\u001e \n\u0003UI!a\u0005\u000b\n\u0005E\u0011\u0012BA\"\u0011\u00039\u0019w\u000e\u001c7fGRLwN\\%na2L!!\u0012$\u0002\u000fA\f7m[1hK*\u00111\tE\u0005\u0003\u0011&\u00131\"Q2dk6,H.\u0019;pe*\u0011QIR\u0001\tQ\u0006\u001c\bnQ8eKR\tA\n\u0005\u0002\u001b\u001b&\u0011a\n\u0006\u0002\u0004\u0013:$\u0018AB3rk\u0006d7\u000f\u0006\u0002R)B\u0011!DU\u0005\u0003\'R\u0011qAQ8pY\u0016\fg\u000eC\u0004V\r\u0005\u0005\t\u0019\u0001\u0016\u0002\u0007a$\u0013\'\u0001\nBG\u000e,X.\u001e7bi\u0016\fe._!se\u0006L\bCA\u0019\t\'\tA\u0011\f\u0005\u0002\u001b5&\u00111\f\u0006\u0002\u0007\u0003:L(+\u001a4\u0015\u0003]\u000bA#Y2dk6,H.\u0019;fI\u0015DH/\u001a8tS>tWCA0c)\t\u00017\rE\u00028\u000f\u0006\u0004\"a\t2\u0005\u000b\u0015R!\u0019\u0001\u0014\t\u000b\u0011T\u0001\u0019A3\u0002\u000b\u0011\"\b.[:\u0011\u0007E\u0002\u0011-\u0001\niCND7i\u001c3fI\u0015DH/\u001a8tS>tWC\u00015m)\tY\u0015\u000eC\u0003e\u0017\u0001\u0007!\u000eE\u00022\u0001-\u0004\"a\t7\u0005\u000b\u0015Z!\u0019\u0001\u0014\u0002!\u0015\fX/\u00197tI\u0015DH/\u001a8tS>tWCA8v)\t\u0001(\u000f\u0006\u0002Rc\"9Q\u000bDA\u0001\u0002\u0004Q\u0003\"\u00023\r\u0001\u0004\u0019\bcA\u0019\u0001iB\u00111%\u001e\u0003\u0006K1\u0011\rA\n"
    )
  ScalaInlineInfo: length = 0x1D (unknown attribute)
   01 01 00 05 00 31 00 32 01 00 28 00 29 01 00 2F
   00 30 01 00 2D 00 2E 01 00 0A 00 23 01
  ScalaSig: length = 0x3 (unknown attribute)
   05 02 00
