Classfile /Users/mw/Projects/slang-braindump/.jar/jar11/assemble/slang-braindump/assemble/content/scala/compat/java8/converterImpl/AccumulateIntArray.class
  Last modified May 29, 2022; size 2464 bytes
  SHA-256 checksum 80a6735b4e2d9593dd952d29ef0c7c681e8f677d0d50c85e145b045762315048
  Compiled from "Accumulates.scala"
public final class scala.compat.java8.converterImpl.AccumulateIntArray
  minor version: 0
  major version: 52
  flags: (0x0031) ACC_PUBLIC, ACC_FINAL, ACC_SUPER
  this_class: #2                          // scala/compat/java8/converterImpl/AccumulateIntArray
  super_class: #4                         // java/lang/Object
  interfaces: 0, fields: 1, methods: 8, attributes: 4
Constant pool:
   #1 = Utf8               scala/compat/java8/converterImpl/AccumulateIntArray
   #2 = Class              #1             // scala/compat/java8/converterImpl/AccumulateIntArray
   #3 = Utf8               java/lang/Object
   #4 = Class              #3             // java/lang/Object
   #5 = Utf8               Accumulates.scala
   #6 = Utf8               Lscala/reflect/ScalaSignature;
   #7 = Utf8               bytes
   #8 = Utf8               \u0006\u0005\u00014A!\u0004\b\u0003/!aA\u0004\u0001C\u0001\u0002\u000b\u0015)\u0019!C\u0005;!IA\u0005\u0001B\u0003\u0002\u0003\u0006IA\b\u0005\u0006K\u0001!\tA\n\u0005\u0006W\u0001!\t\u0001\f\u0005\b\u0003\u0002\t\t\u0011\"\u0011C\u0011\u001d\u0019\u0005!!A\u0005B\u0011;q!\u0014\b\u0002\u0002#\u0005aJB\u0004\u000e\u001d\u0005\u0005\t\u0012A(\t\u000b\u0015BA\u0011A*\t\u000bQCAQA+\t\u000faC\u0011\u0011!C\u00033\"91\fCA\u0001\n\u000ba&AE!dGVlW\u000f\\1uK&sG/\u0011:sCfT!a\u0004\t\u0002\u001b\r|gN^3si\u0016\u0014\u0018*\u001c9m\u0015\t\t\"#A\u0003kCZ\f\u0007H\u0003\u0002\u0014)\u000511m\\7qCRT\u0011!F\u0001\u0006g\u000e\fG.Y\u0002\u0001\'\t\u0001\u0001\u0004\u0005\u0002\u001a55\tA#\u0003\u0002\u001c)\t1\u0011I\\=WC2\fqh]2bY\u0006$3m\\7qCR$#.\u0019<bq\u0011\u001awN\u001c<feR,\'/S7qY\u0012\n5mY;nk2\fG/Z%oi\u0006\u0013(/Y=%IUtG-\u001a:ms&tw-F\u0001\u001f!\rIr$I\u0005\u0003AQ\u0011Q!\u0011:sCf\u0004\"!\u0007\u0012\n\u0005\r\"\"aA%oi\u0006\u00015oY1mC\u0012\u001aw.\u001c9bi\u0012R\u0017M^19I\r|gN^3si\u0016\u0014\u0018*\u001c9mI\u0005\u001b7-^7vY\u0006$X-\u00138u\u0003J\u0014\u0018-\u001f\u0013%k:$WM\u001d7zS:<\u0007%\u0001\u0004=S:LGO\u0010\u000b\u0003O%\u0002\"\u0001\u000b\u0001\u000e\u00039AQAK\u0002A\u0002y\t!\"\u001e8eKJd\u00170\u001b8h\u0003)\t7mY;nk2\fG/Z\u000b\u0002[A\u0011aF\u0010\b\u0003_mr!\u0001M\u001d\u000f\u0005EBdB\u0001\u001a8\u001d\t\u0019d\'D\u00015\u0015\t)d#\u0001\u0004=e>|GOP\u0005\u0002+%\u00111\u0003F\u0005\u0003#II!A\u000f\t\u0002\u001d\r|G\u000e\\3di&|g.S7qY&\u0011A(P\u0001\ba\u0006\u001c7.Y4f\u0015\tQ\u0004#\u0003\u0002@\u0001\nq\u0011J\u001c;BG\u000e,X.\u001e7bi>\u0014(B\u0001\u001f>\u0003!A\u0017m\u001d5D_\u0012,G#A\u0011\u0002\r\u0015\fX/\u00197t)\t)\u0005\n\u0005\u0002\u001a\r&\u0011q\t\u0006\u0002\b\u0005>|G.Z1o\u0011\u001dIe!!AA\u0002)\u000b1\u0001\u001f\u00132!\tI2*\u0003\u0002M)\t\u0019\u0011I\\=\u0002%\u0005\u001b7-^7vY\u0006$X-\u00138u\u0003J\u0014\u0018-\u001f\t\u0003Q!\u0019\"\u0001\u0003)\u0011\u0005e\t\u0016B\u0001*\u0015\u0005\u0019\te.\u001f*fMR\ta*\u0001\u000bbG\u000e,X.\u001e7bi\u0016$S\r\u001f;f]NLwN\u001c\u000b\u0003[YCQa\u0016\u0006A\u0002\u001d\nQ\u0001\n;iSN\f!\u0003[1tQ\u000e{G-\u001a\u0013fqR,gn]5p]R\u0011!I\u0017\u0005\u0006/.\u0001\raJ\u0001\u0011KF,\u0018\r\\:%Kb$XM\\:j_:$\"!X0\u0015\u0005\u0015s\u0006bB%\r\u0003\u0003\u0005\rA\u0013\u0005\u0006/2\u0001\ra\n
   #9 = Utf8               scala$compat$java8$converterImpl$AccumulateIntArray$$underlying
  #10 = Utf8               [I
  #11 = Utf8               equals$extension
  #12 = Utf8               ([ILjava/lang/Object;)Z
  #13 = Utf8               $this
  #14 = Utf8               x$1
  #15 = Utf8               scala/compat/java8/converterImpl/AccumulateIntArray$
  #16 = Class              #15            // scala/compat/java8/converterImpl/AccumulateIntArray$
  #17 = Utf8               MODULE$
  #18 = Utf8               Lscala/compat/java8/converterImpl/AccumulateIntArray$;
  #19 = NameAndType        #17:#18        // MODULE$:Lscala/compat/java8/converterImpl/AccumulateIntArray$;
  #20 = Fieldref           #16.#19        // scala/compat/java8/converterImpl/AccumulateIntArray$.MODULE$:Lscala/compat/java8/converterImpl/AccumulateIntArray$;
  #21 = NameAndType        #11:#12        // equals$extension:([ILjava/lang/Object;)Z
  #22 = Methodref          #16.#21        // scala/compat/java8/converterImpl/AccumulateIntArray$.equals$extension:([ILjava/lang/Object;)Z
  #23 = Utf8               Ljava/lang/Object;
  #24 = Utf8               hashCode$extension
  #25 = Utf8               ([I)I
  #26 = NameAndType        #24:#25        // hashCode$extension:([I)I
  #27 = Methodref          #16.#26        // scala/compat/java8/converterImpl/AccumulateIntArray$.hashCode$extension:([I)I
  #28 = Utf8               accumulate$extension
  #29 = Utf8               ([I)Lscala/jdk/IntAccumulator;
  #30 = NameAndType        #28:#29        // accumulate$extension:([I)Lscala/jdk/IntAccumulator;
  #31 = Methodref          #16.#30        // scala/compat/java8/converterImpl/AccumulateIntArray$.accumulate$extension:([I)Lscala/jdk/IntAccumulator;
  #32 = Utf8               ()[I
  #33 = NameAndType        #9:#10         // scala$compat$java8$converterImpl$AccumulateIntArray$$underlying:[I
  #34 = Fieldref           #2.#33         // scala/compat/java8/converterImpl/AccumulateIntArray.scala$compat$java8$converterImpl$AccumulateIntArray$$underlying:[I
  #35 = Utf8               this
  #36 = Utf8               Lscala/compat/java8/converterImpl/AccumulateIntArray;
  #37 = Utf8               accumulate
  #38 = Utf8               ()Lscala/jdk/IntAccumulator;
  #39 = NameAndType        #9:#32         // scala$compat$java8$converterImpl$AccumulateIntArray$$underlying:()[I
  #40 = Methodref          #2.#39         // scala/compat/java8/converterImpl/AccumulateIntArray.scala$compat$java8$converterImpl$AccumulateIntArray$$underlying:()[I
  #41 = Utf8               hashCode
  #42 = Utf8               ()I
  #43 = Utf8               equals
  #44 = Utf8               (Ljava/lang/Object;)Z
  #45 = Utf8               <init>
  #46 = Utf8               ([I)V
  #47 = Utf8               underlying
  #48 = Utf8               ()V
  #49 = NameAndType        #45:#48        // "<init>":()V
  #50 = Methodref          #4.#49         // java/lang/Object."<init>":()V
  #51 = Utf8               Code
  #52 = Utf8               LocalVariableTable
  #53 = Utf8               MethodParameters
  #54 = Utf8               LineNumberTable
  #55 = Utf8               SourceFile
  #56 = Utf8               RuntimeVisibleAnnotations
  #57 = Utf8               ScalaInlineInfo
  #58 = Utf8               ScalaSig
{
  private final int[] scala$compat$java8$converterImpl$AccumulateIntArray$$underlying;
    descriptor: [I
    flags: (0x0012) ACC_PRIVATE, ACC_FINAL

  public static boolean equals$extension(int[], java.lang.Object);
    descriptor: ([ILjava/lang/Object;)Z
    flags: (0x0009) ACC_PUBLIC, ACC_STATIC
    Code:
      stack=3, locals=2, args_size=2
         0: getstatic     #20                 // Field scala/compat/java8/converterImpl/AccumulateIntArray$.MODULE$:Lscala/compat/java8/converterImpl/AccumulateIntArray$;
         3: aload_0
         4: aload_1
         5: invokevirtual #22                 // Method scala/compat/java8/converterImpl/AccumulateIntArray$.equals$extension:([ILjava/lang/Object;)Z
         8: ireturn
      LocalVariableTable:
        Start  Length  Slot  Name   Signature
            0       9     0 $this   [I
            0       9     1   x$1   Ljava/lang/Object;
    MethodParameters:
      Name                           Flags
      $this                          final
      x$1                            final

  public static int hashCode$extension(int[]);
    descriptor: ([I)I
    flags: (0x0009) ACC_PUBLIC, ACC_STATIC
    Code:
      stack=2, locals=1, args_size=1
         0: getstatic     #20                 // Field scala/compat/java8/converterImpl/AccumulateIntArray$.MODULE$:Lscala/compat/java8/converterImpl/AccumulateIntArray$;
         3: aload_0
         4: invokevirtual #27                 // Method scala/compat/java8/converterImpl/AccumulateIntArray$.hashCode$extension:([I)I
         7: ireturn
      LocalVariableTable:
        Start  Length  Slot  Name   Signature
            0       8     0 $this   [I
    MethodParameters:
      Name                           Flags
      $this                          final

  public static scala.jdk.IntAccumulator accumulate$extension(int[]);
    descriptor: ([I)Lscala/jdk/IntAccumulator;
    flags: (0x0009) ACC_PUBLIC, ACC_STATIC
    Code:
      stack=2, locals=1, args_size=1
         0: getstatic     #20                 // Field scala/compat/java8/converterImpl/AccumulateIntArray$.MODULE$:Lscala/compat/java8/converterImpl/AccumulateIntArray$;
         3: aload_0
         4: invokevirtual #31                 // Method scala/compat/java8/converterImpl/AccumulateIntArray$.accumulate$extension:([I)Lscala/jdk/IntAccumulator;
         7: areturn
      LocalVariableTable:
        Start  Length  Slot  Name   Signature
            0       8     0 $this   [I
    MethodParameters:
      Name                           Flags
      $this                          final

  public int[] scala$compat$java8$converterImpl$AccumulateIntArray$$underlying();
    descriptor: ()[I
    flags: (0x0001) ACC_PUBLIC
    Code:
      stack=1, locals=1, args_size=1
         0: aload_0
         1: getfield      #34                 // Field scala$compat$java8$converterImpl$AccumulateIntArray$$underlying:[I
         4: areturn
      LineNumberTable:
        line 41: 0
      LocalVariableTable:
        Start  Length  Slot  Name   Signature
            0       5     0  this   Lscala/compat/java8/converterImpl/AccumulateIntArray;

  public scala.jdk.IntAccumulator accumulate();
    descriptor: ()Lscala/jdk/IntAccumulator;
    flags: (0x0001) ACC_PUBLIC
    Code:
      stack=2, locals=1, args_size=1
         0: getstatic     #20                 // Field scala/compat/java8/converterImpl/AccumulateIntArray$.MODULE$:Lscala/compat/java8/converterImpl/AccumulateIntArray$;
         3: aload_0
         4: invokevirtual #40                 // Method scala$compat$java8$converterImpl$AccumulateIntArray$$underlying:()[I
         7: invokevirtual #31                 // Method scala/compat/java8/converterImpl/AccumulateIntArray$.accumulate$extension:([I)Lscala/jdk/IntAccumulator;
        10: areturn
      LineNumberTable:
        line 42: 0
      LocalVariableTable:
        Start  Length  Slot  Name   Signature
            0      11     0  this   Lscala/compat/java8/converterImpl/AccumulateIntArray;

  public int hashCode();
    descriptor: ()I
    flags: (0x0001) ACC_PUBLIC
    Code:
      stack=2, locals=1, args_size=1
         0: getstatic     #20                 // Field scala/compat/java8/converterImpl/AccumulateIntArray$.MODULE$:Lscala/compat/java8/converterImpl/AccumulateIntArray$;
         3: aload_0
         4: invokevirtual #40                 // Method scala$compat$java8$converterImpl$AccumulateIntArray$$underlying:()[I
         7: invokevirtual #27                 // Method scala/compat/java8/converterImpl/AccumulateIntArray$.hashCode$extension:([I)I
        10: ireturn
      LineNumberTable:
        line 41: 0
      LocalVariableTable:
        Start  Length  Slot  Name   Signature
            0      11     0  this   Lscala/compat/java8/converterImpl/AccumulateIntArray;

  public boolean equals(java.lang.Object);
    descriptor: (Ljava/lang/Object;)Z
    flags: (0x0001) ACC_PUBLIC
    Code:
      stack=3, locals=2, args_size=2
         0: getstatic     #20                 // Field scala/compat/java8/converterImpl/AccumulateIntArray$.MODULE$:Lscala/compat/java8/converterImpl/AccumulateIntArray$;
         3: aload_0
         4: invokevirtual #40                 // Method scala$compat$java8$converterImpl$AccumulateIntArray$$underlying:()[I
         7: aload_1
         8: invokevirtual #22                 // Method scala/compat/java8/converterImpl/AccumulateIntArray$.equals$extension:([ILjava/lang/Object;)Z
        11: ireturn
      LineNumberTable:
        line 41: 0
      LocalVariableTable:
        Start  Length  Slot  Name   Signature
            0      12     0  this   Lscala/compat/java8/converterImpl/AccumulateIntArray;
            0      12     1   x$1   Ljava/lang/Object;
    MethodParameters:
      Name                           Flags
      x$1                            final

  public scala.compat.java8.converterImpl.AccumulateIntArray(int[]);
    descriptor: ([I)V
    flags: (0x0001) ACC_PUBLIC
    Code:
      stack=2, locals=2, args_size=2
         0: aload_0
         1: aload_1
         2: putfield      #34                 // Field scala$compat$java8$converterImpl$AccumulateIntArray$$underlying:[I
         5: aload_0
         6: invokespecial #50                 // Method java/lang/Object."<init>":()V
         9: return
      LineNumberTable:
        line 41: 0
      LocalVariableTable:
        Start  Length  Slot  Name   Signature
            0      10     0  this   Lscala/compat/java8/converterImpl/AccumulateIntArray;
            0      10     1 underlying   [I
    MethodParameters:
      Name                           Flags
      underlying                     final
}
SourceFile: "Accumulates.scala"
RuntimeVisibleAnnotations:
  0: #6(#7=s#8)
    scala.reflect.ScalaSignature(
      bytes="\u0006\u0005\u00014A!\u0004\b\u0003/!aA\u0004\u0001C\u0001\u0002\u000b\u0015)\u0019!C\u0005;!IA\u0005\u0001B\u0003\u0002\u0003\u0006IA\b\u0005\u0006K\u0001!\tA\n\u0005\u0006W\u0001!\t\u0001\f\u0005\b\u0003\u0002\t\t\u0011\"\u0011C\u0011\u001d\u0019\u0005!!A\u0005B\u0011;q!\u0014\b\u0002\u0002#\u0005aJB\u0004\u000e\u001d\u0005\u0005\t\u0012A(\t\u000b\u0015BA\u0011A*\t\u000bQCAQA+\t\u000faC\u0011\u0011!C\u00033\"91\fCA\u0001\n\u000ba&AE!dGVlW\u000f\\1uK&sG/\u0011:sCfT!a\u0004\t\u0002\u001b\r|gN^3si\u0016\u0014\u0018*\u001c9m\u0015\t\t\"#A\u0003kCZ\f\u0007H\u0003\u0002\u0014)\u000511m\\7qCRT\u0011!F\u0001\u0006g\u000e\fG.Y\u0002\u0001\'\t\u0001\u0001\u0004\u0005\u0002\u001a55\tA#\u0003\u0002\u001c)\t1\u0011I\\=WC2\fqh]2bY\u0006$3m\\7qCR$#.\u0019<bq\u0011\u001awN\u001c<feR,\'/S7qY\u0012\n5mY;nk2\fG/Z%oi\u0006\u0013(/Y=%IUtG-\u001a:ms&tw-F\u0001\u001f!\rIr$I\u0005\u0003AQ\u0011Q!\u0011:sCf\u0004\"!\u0007\u0012\n\u0005\r\"\"aA%oi\u0006\u00015oY1mC\u0012\u001aw.\u001c9bi\u0012R\u0017M^19I\r|gN^3si\u0016\u0014\u0018*\u001c9mI\u0005\u001b7-^7vY\u0006$X-\u00138u\u0003J\u0014\u0018-\u001f\u0013%k:$WM\u001d7zS:<\u0007%\u0001\u0004=S:LGO\u0010\u000b\u0003O%\u0002\"\u0001\u000b\u0001\u000e\u00039AQAK\u0002A\u0002y\t!\"\u001e8eKJd\u00170\u001b8h\u0003)\t7mY;nk2\fG/Z\u000b\u0002[A\u0011aF\u0010\b\u0003_mr!\u0001M\u001d\u000f\u0005EBdB\u0001\u001a8\u001d\t\u0019d\'D\u00015\u0015\t)d#\u0001\u0004=e>|GOP\u0005\u0002+%\u00111\u0003F\u0005\u0003#II!A\u000f\t\u0002\u001d\r|G\u000e\\3di&|g.S7qY&\u0011A(P\u0001\ba\u0006\u001c7.Y4f\u0015\tQ\u0004#\u0003\u0002@\u0001\nq\u0011J\u001c;BG\u000e,X.\u001e7bi>\u0014(B\u0001\u001f>\u0003!A\u0017m\u001d5D_\u0012,G#A\u0011\u0002\r\u0015\fX/\u00197t)\t)\u0005\n\u0005\u0002\u001a\r&\u0011q\t\u0006\u0002\b\u0005>|G.Z1o\u0011\u001dIe!!AA\u0002)\u000b1\u0001\u001f\u00132!\tI2*\u0003\u0002M)\t\u0019\u0011I\\=\u0002%\u0005\u001b7-^7vY\u0006$X-\u00138u\u0003J\u0014\u0018-\u001f\t\u0003Q!\u0019\"\u0001\u0003)\u0011\u0005e\t\u0016B\u0001*\u0015\u0005\u0019\te.\u001f*fMR\ta*\u0001\u000bbG\u000e,X.\u001e7bi\u0016$S\r\u001f;f]NLwN\u001c\u000b\u0003[YCQa\u0016\u0006A\u0002\u001d\nQ\u0001\n;iSN\f!\u0003[1tQ\u000e{G-\u001a\u0013fqR,gn]5p]R\u0011!I\u0017\u0005\u0006/.\u0001\raJ\u0001\u0011KF,\u0018\r\\:%Kb$XM\\:j_:$\"!X0\u0015\u0005\u0015s\u0006bB%\r\u0003\u0003\u0005\rA\u0013\u0005\u0006/2\u0001\ra\n"
    )
  ScalaInlineInfo: length = 0x1D (unknown attribute)
   01 01 00 05 00 2D 00 2E 01 00 25 00 26 01 00 2B
   00 2C 01 00 29 00 2A 01 00 09 00 20 01
  ScalaSig: length = 0x3 (unknown attribute)
   05 02 00
