Classfile /Users/mw/Projects/slang-braindump/.jar/jar11/assemble/slang-braindump/assemble/content/scala/compat/java8/converterImpl/Priority2AccumulatorConverters.class
  Last modified May 29, 2022; size 3059 bytes
  SHA-256 checksum 9992076fad365045acc93144936f59f153e3f84d706fc1d7cf3c9a472ac8b1a5
  Compiled from "AccumulatorConverters.scala"
public interface scala.compat.java8.converterImpl.Priority2AccumulatorConverters extends scala.compat.java8.converterImpl.Priority3AccumulatorConverters
  minor version: 0
  major version: 52
  flags: (0x0601) ACC_PUBLIC, ACC_INTERFACE, ACC_ABSTRACT
  this_class: #2                          // scala/compat/java8/converterImpl/Priority2AccumulatorConverters
  super_class: #4                         // java/lang/Object
  interfaces: 1, fields: 0, methods: 9, attributes: 4
Constant pool:
   #1 = Utf8               scala/compat/java8/converterImpl/Priority2AccumulatorConverters
   #2 = Class              #1             // scala/compat/java8/converterImpl/Priority2AccumulatorConverters
   #3 = Utf8               java/lang/Object
   #4 = Class              #3             // java/lang/Object
   #5 = Utf8               scala/compat/java8/converterImpl/Priority3AccumulatorConverters
   #6 = Class              #5             // scala/compat/java8/converterImpl/Priority3AccumulatorConverters
   #7 = Utf8               AccumulatorConverters.scala
   #8 = Utf8               Lscala/reflect/ScalaSignature;
   #9 = Utf8               bytes
  #10 = Utf8               \u0006\u0005u3qAB\u0004\u0011\u0002\u0007\u0005\u0001\u0003C\u0003\u001a\u0001\u0011\u0005!\u0004C\u0003\u001f\u0001\u0011\rq\u0004C\u00035\u0001\u0011\rQ\u0007C\u0003?\u0001\u0011\rq\bC\u0003I\u0001\u0011\r\u0011J\u0001\u0010Qe&|\'/\u001b;ze\u0005\u001b7-^7vY\u0006$xN]\"p]Z,\'\u000f^3sg*\u0011\u0001\"C\u0001\u000eG>tg/\u001a:uKJLU\u000e\u001d7\u000b\u0005)Y\u0011!\u00026bm\u0006D$B\u0001\u0007\u000e\u0003\u0019\u0019w.\u001c9bi*\ta\"A\u0003tG\u0006d\u0017m\u0001\u0001\u0014\u0007\u0001\tR\u0003\u0005\u0002\u0013\'5\tQ\"\u0003\u0002\u0015\u001b\t1\u0011I\\=SK\u001a\u0004\"AF\f\u000e\u0003\u001dI!\u0001G\u0004\u0003=A\u0013\u0018n\u001c:jif\u001c\u0014iY2v[Vd\u0017\r^8s\u0007>tg/\u001a:uKJ\u001c\u0018A\u0002\u0013j]&$H\u0005F\u0001\u001c!\t\u0011B$\u0003\u0002\u001e\u001b\t!QK\\5u\u0003i\t7mY;nk2\fG/\u001a#pk\ndWmQ8mY\u0016\u001cG/[8o)\t\u00013\u0005\u0005\u0002\u0017C%\u0011!e\u0002\u0002\u001b\u0003\u000e\u001cW/\\;mCR,Gi\\;cY\u0016\u001cu\u000e\u001c7fGRLwN\u001c\u0005\u0006I\t\u0001\r!J\u0001\u000bk:$WM\u001d7zS:<\u0007c\u0001\u0014/c9\u0011q\u0005\f\b\u0003Q-j\u0011!\u000b\u0006\u0003U=\ta\u0001\u0010:p_Rt\u0014\"\u0001\b\n\u00055j\u0011a\u00029bG.\fw-Z\u0005\u0003_A\u0012A\"\u0013;fe\u0006\u0014G.Z(oG\u0016T!!L\u0007\u0011\u0005I\u0011\u0014BA\u001a\u000e\u0005\u0019!u.\u001e2mK\u00069\u0012mY2v[Vd\u0017\r^3J]R\u001cu\u000e\u001c7fGRLwN\u001c\u000b\u0003me\u0002\"AF\u001c\n\u0005a:!aF!dGVlW\u000f\\1uK&sGoQ8mY\u0016\u001cG/[8o\u0011\u0015!3\u00011\u0001;!\r1cf\u000f\t\u0003%qJ!!P\u0007\u0003\u0007%sG/\u0001\rbG\u000e,X.\u001e7bi\u0016duN\\4D_2dWm\u0019;j_:$\"\u0001Q\"\u0011\u0005Y\t\u0015B\u0001\"\b\u0005a\t5mY;nk2\fG/\u001a\'p]\u001e\u001cu\u000e\u001c7fGRLwN\u001c\u0005\u0006I\u0011\u0001\r\u0001\u0012\t\u0004M9*\u0005C\u0001\nG\u0013\t9UB\u0001\u0003M_:<\u0017AE1dGVlW\u000f\\1uK\u0006s\u00170\u0011:sCf,\"A\u0013)\u0015\u0005-K\u0006c\u0001\fM\u001d&\u0011Qj\u0002\u0002\u0013\u0003\u000e\u001cW/\\;mCR,\u0017I\\=BeJ\f\u0017\u0010\u0005\u0002P!2\u0001A!B)\u0006\u0005\u0004\u0011&!A!\u0012\u0005M3\u0006C\u0001\nU\u0013\t)VBA\u0004O_RD\u0017N\\4\u0011\u0005I9\u0016B\u0001-\u000e\u0005\r\te.\u001f\u0005\u0006I\u0015\u0001\rA\u0017\t\u0004%ms\u0015B\u0001/\u000e\u0005\u0015\t%O]1z\u0001
  #11 = Utf8               accumulateDoubleCollection$
  #12 = Utf8               (Lscala/compat/java8/converterImpl/Priority2AccumulatorConverters;Lscala/collection/IterableOnce;)Lscala/collection/IterableOnce;
  #13 = Utf8               $this
  #14 = Utf8               underlying
  #15 = Utf8               accumulateDoubleCollection
  #16 = Utf8               (Lscala/collection/IterableOnce;)Lscala/collection/IterableOnce;
  #17 = NameAndType        #15:#16        // accumulateDoubleCollection:(Lscala/collection/IterableOnce;)Lscala/collection/IterableOnce;
  #18 = InterfaceMethodref #2.#17         // scala/compat/java8/converterImpl/Priority2AccumulatorConverters.accumulateDoubleCollection:(Lscala/collection/IterableOnce;)Lscala/collection/IterableOnce;
  #19 = Utf8               Lscala/compat/java8/converterImpl/Priority2AccumulatorConverters;
  #20 = Utf8               Lscala/collection/IterableOnce;
  #21 = Utf8               (Lscala/collection/IterableOnce<Ljava/lang/Object;>;)Lscala/collection/IterableOnce<Ljava/lang/Object;>;
  #22 = Utf8               this
  #23 = Utf8               accumulateIntCollection$
  #24 = Utf8               accumulateIntCollection
  #25 = NameAndType        #24:#16        // accumulateIntCollection:(Lscala/collection/IterableOnce;)Lscala/collection/IterableOnce;
  #26 = InterfaceMethodref #2.#25         // scala/compat/java8/converterImpl/Priority2AccumulatorConverters.accumulateIntCollection:(Lscala/collection/IterableOnce;)Lscala/collection/IterableOnce;
  #27 = Utf8               accumulateLongCollection$
  #28 = Utf8               accumulateLongCollection
  #29 = NameAndType        #28:#16        // accumulateLongCollection:(Lscala/collection/IterableOnce;)Lscala/collection/IterableOnce;
  #30 = InterfaceMethodref #2.#29         // scala/compat/java8/converterImpl/Priority2AccumulatorConverters.accumulateLongCollection:(Lscala/collection/IterableOnce;)Lscala/collection/IterableOnce;
  #31 = Utf8               accumulateAnyArray$
  #32 = Utf8               (Lscala/compat/java8/converterImpl/Priority2AccumulatorConverters;Ljava/lang/Object;)Ljava/lang/Object;
  #33 = Utf8               accumulateAnyArray
  #34 = Utf8               (Ljava/lang/Object;)Ljava/lang/Object;
  #35 = NameAndType        #33:#34        // accumulateAnyArray:(Ljava/lang/Object;)Ljava/lang/Object;
  #36 = InterfaceMethodref #2.#35         // scala/compat/java8/converterImpl/Priority2AccumulatorConverters.accumulateAnyArray:(Ljava/lang/Object;)Ljava/lang/Object;
  #37 = Utf8               Ljava/lang/Object;
  #38 = Utf8               <A:Ljava/lang/Object;>(Ljava/lang/Object;)Ljava/lang/Object;
  #39 = Utf8               $init$
  #40 = Utf8               (Lscala/compat/java8/converterImpl/Priority2AccumulatorConverters;)V
  #41 = Utf8               Code
  #42 = Utf8               LineNumberTable
  #43 = Utf8               LocalVariableTable
  #44 = Utf8               MethodParameters
  #45 = Utf8               Signature
  #46 = Utf8               SourceFile
  #47 = Utf8               RuntimeVisibleAnnotations
  #48 = Utf8               ScalaInlineInfo
  #49 = Utf8               ScalaSig
{
  public static scala.collection.IterableOnce accumulateDoubleCollection$(scala.compat.java8.converterImpl.Priority2AccumulatorConverters, scala.collection.IterableOnce);
    descriptor: (Lscala/compat/java8/converterImpl/Priority2AccumulatorConverters;Lscala/collection/IterableOnce;)Lscala/collection/IterableOnce;
    flags: (0x1009) ACC_PUBLIC, ACC_STATIC, ACC_SYNTHETIC
    Code:
      stack=2, locals=2, args_size=2
         0: aload_0
         1: aload_1
         2: invokespecial #18                 // InterfaceMethod accumulateDoubleCollection:(Lscala/collection/IterableOnce;)Lscala/collection/IterableOnce;
         5: areturn
      LineNumberTable:
        line 23: 0
      LocalVariableTable:
        Start  Length  Slot  Name   Signature
            0       6     0 $this   Lscala/compat/java8/converterImpl/Priority2AccumulatorConverters;
            0       6     1 underlying   Lscala/collection/IterableOnce;
    MethodParameters:
      Name                           Flags
      $this                          final synthetic
      underlying                     final

  public default scala.collection.IterableOnce<java.lang.Object> accumulateDoubleCollection(scala.collection.IterableOnce<java.lang.Object>);
    descriptor: (Lscala/collection/IterableOnce;)Lscala/collection/IterableOnce;
    flags: (0x0001) ACC_PUBLIC
    Code:
      stack=1, locals=2, args_size=2
         0: aload_1
         1: areturn
      LineNumberTable:
        line 24: 0
      LocalVariableTable:
        Start  Length  Slot  Name   Signature
            0       2     0  this   Lscala/compat/java8/converterImpl/Priority2AccumulatorConverters;
            0       2     1 underlying   Lscala/collection/IterableOnce;
    Signature: #21                          // (Lscala/collection/IterableOnce<Ljava/lang/Object;>;)Lscala/collection/IterableOnce<Ljava/lang/Object;>;
    MethodParameters:
      Name                           Flags
      underlying                     final

  public static scala.collection.IterableOnce accumulateIntCollection$(scala.compat.java8.converterImpl.Priority2AccumulatorConverters, scala.collection.IterableOnce);
    descriptor: (Lscala/compat/java8/converterImpl/Priority2AccumulatorConverters;Lscala/collection/IterableOnce;)Lscala/collection/IterableOnce;
    flags: (0x1009) ACC_PUBLIC, ACC_STATIC, ACC_SYNTHETIC
    Code:
      stack=2, locals=2, args_size=2
         0: aload_0
         1: aload_1
         2: invokespecial #26                 // InterfaceMethod accumulateIntCollection:(Lscala/collection/IterableOnce;)Lscala/collection/IterableOnce;
         5: areturn
      LineNumberTable:
        line 25: 0
      LocalVariableTable:
        Start  Length  Slot  Name   Signature
            0       6     0 $this   Lscala/compat/java8/converterImpl/Priority2AccumulatorConverters;
            0       6     1 underlying   Lscala/collection/IterableOnce;
    MethodParameters:
      Name                           Flags
      $this                          final synthetic
      underlying                     final

  public default scala.collection.IterableOnce<java.lang.Object> accumulateIntCollection(scala.collection.IterableOnce<java.lang.Object>);
    descriptor: (Lscala/collection/IterableOnce;)Lscala/collection/IterableOnce;
    flags: (0x0001) ACC_PUBLIC
    Code:
      stack=1, locals=2, args_size=2
         0: aload_1
         1: areturn
      LineNumberTable:
        line 26: 0
      LocalVariableTable:
        Start  Length  Slot  Name   Signature
            0       2     0  this   Lscala/compat/java8/converterImpl/Priority2AccumulatorConverters;
            0       2     1 underlying   Lscala/collection/IterableOnce;
    Signature: #21                          // (Lscala/collection/IterableOnce<Ljava/lang/Object;>;)Lscala/collection/IterableOnce<Ljava/lang/Object;>;
    MethodParameters:
      Name                           Flags
      underlying                     final

  public static scala.collection.IterableOnce accumulateLongCollection$(scala.compat.java8.converterImpl.Priority2AccumulatorConverters, scala.collection.IterableOnce);
    descriptor: (Lscala/compat/java8/converterImpl/Priority2AccumulatorConverters;Lscala/collection/IterableOnce;)Lscala/collection/IterableOnce;
    flags: (0x1009) ACC_PUBLIC, ACC_STATIC, ACC_SYNTHETIC
    Code:
      stack=2, locals=2, args_size=2
         0: aload_0
         1: aload_1
         2: invokespecial #30                 // InterfaceMethod accumulateLongCollection:(Lscala/collection/IterableOnce;)Lscala/collection/IterableOnce;
         5: areturn
      LineNumberTable:
        line 27: 0
      LocalVariableTable:
        Start  Length  Slot  Name   Signature
            0       6     0 $this   Lscala/compat/java8/converterImpl/Priority2AccumulatorConverters;
            0       6     1 underlying   Lscala/collection/IterableOnce;
    MethodParameters:
      Name                           Flags
      $this                          final synthetic
      underlying                     final

  public default scala.collection.IterableOnce<java.lang.Object> accumulateLongCollection(scala.collection.IterableOnce<java.lang.Object>);
    descriptor: (Lscala/collection/IterableOnce;)Lscala/collection/IterableOnce;
    flags: (0x0001) ACC_PUBLIC
    Code:
      stack=1, locals=2, args_size=2
         0: aload_1
         1: areturn
      LineNumberTable:
        line 28: 0
      LocalVariableTable:
        Start  Length  Slot  Name   Signature
            0       2     0  this   Lscala/compat/java8/converterImpl/Priority2AccumulatorConverters;
            0       2     1 underlying   Lscala/collection/IterableOnce;
    Signature: #21                          // (Lscala/collection/IterableOnce<Ljava/lang/Object;>;)Lscala/collection/IterableOnce<Ljava/lang/Object;>;
    MethodParameters:
      Name                           Flags
      underlying                     final

  public static java.lang.Object accumulateAnyArray$(scala.compat.java8.converterImpl.Priority2AccumulatorConverters, java.lang.Object);
    descriptor: (Lscala/compat/java8/converterImpl/Priority2AccumulatorConverters;Ljava/lang/Object;)Ljava/lang/Object;
    flags: (0x1009) ACC_PUBLIC, ACC_STATIC, ACC_SYNTHETIC
    Code:
      stack=2, locals=2, args_size=2
         0: aload_0
         1: aload_1
         2: invokespecial #36                 // InterfaceMethod accumulateAnyArray:(Ljava/lang/Object;)Ljava/lang/Object;
         5: areturn
      LineNumberTable:
        line 29: 0
      LocalVariableTable:
        Start  Length  Slot  Name   Signature
            0       6     0 $this   Lscala/compat/java8/converterImpl/Priority2AccumulatorConverters;
            0       6     1 underlying   Ljava/lang/Object;
    MethodParameters:
      Name                           Flags
      $this                          final synthetic
      underlying                     final

  public default <A extends java.lang.Object> java.lang.Object accumulateAnyArray(java.lang.Object);
    descriptor: (Ljava/lang/Object;)Ljava/lang/Object;
    flags: (0x0001) ACC_PUBLIC
    Code:
      stack=1, locals=2, args_size=2
         0: aload_1
         1: areturn
      LineNumberTable:
        line 30: 0
      LocalVariableTable:
        Start  Length  Slot  Name   Signature
            0       2     0  this   Lscala/compat/java8/converterImpl/Priority2AccumulatorConverters;
            0       2     1 underlying   Ljava/lang/Object;
    Signature: #38                          // <A:Ljava/lang/Object;>(Ljava/lang/Object;)Ljava/lang/Object;
    MethodParameters:
      Name                           Flags
      underlying                     final

  public static void $init$(scala.compat.java8.converterImpl.Priority2AccumulatorConverters);
    descriptor: (Lscala/compat/java8/converterImpl/Priority2AccumulatorConverters;)V
    flags: (0x0009) ACC_PUBLIC, ACC_STATIC
    Code:
      stack=0, locals=1, args_size=1
         0: return
      LineNumberTable:
        line 22: 0
      LocalVariableTable:
        Start  Length  Slot  Name   Signature
            0       1     0 $this   Lscala/compat/java8/converterImpl/Priority2AccumulatorConverters;
    MethodParameters:
      Name                           Flags
      $this                          final synthetic
}
SourceFile: "AccumulatorConverters.scala"
RuntimeVisibleAnnotations:
  0: #8(#9=s#10)
    scala.reflect.ScalaSignature(
      bytes="\u0006\u0005u3qAB\u0004\u0011\u0002\u0007\u0005\u0001\u0003C\u0003\u001a\u0001\u0011\u0005!\u0004C\u0003\u001f\u0001\u0011\rq\u0004C\u00035\u0001\u0011\rQ\u0007C\u0003?\u0001\u0011\rq\bC\u0003I\u0001\u0011\r\u0011J\u0001\u0010Qe&|\'/\u001b;ze\u0005\u001b7-^7vY\u0006$xN]\"p]Z,\'\u000f^3sg*\u0011\u0001\"C\u0001\u000eG>tg/\u001a:uKJLU\u000e\u001d7\u000b\u0005)Y\u0011!\u00026bm\u0006D$B\u0001\u0007\u000e\u0003\u0019\u0019w.\u001c9bi*\ta\"A\u0003tG\u0006d\u0017m\u0001\u0001\u0014\u0007\u0001\tR\u0003\u0005\u0002\u0013\'5\tQ\"\u0003\u0002\u0015\u001b\t1\u0011I\\=SK\u001a\u0004\"AF\f\u000e\u0003\u001dI!\u0001G\u0004\u0003=A\u0013\u0018n\u001c:jif\u001c\u0014iY2v[Vd\u0017\r^8s\u0007>tg/\u001a:uKJ\u001c\u0018A\u0002\u0013j]&$H\u0005F\u0001\u001c!\t\u0011B$\u0003\u0002\u001e\u001b\t!QK\\5u\u0003i\t7mY;nk2\fG/\u001a#pk\ndWmQ8mY\u0016\u001cG/[8o)\t\u00013\u0005\u0005\u0002\u0017C%\u0011!e\u0002\u0002\u001b\u0003\u000e\u001cW/\\;mCR,Gi\\;cY\u0016\u001cu\u000e\u001c7fGRLwN\u001c\u0005\u0006I\t\u0001\r!J\u0001\u000bk:$WM\u001d7zS:<\u0007c\u0001\u0014/c9\u0011q\u0005\f\b\u0003Q-j\u0011!\u000b\u0006\u0003U=\ta\u0001\u0010:p_Rt\u0014\"\u0001\b\n\u00055j\u0011a\u00029bG.\fw-Z\u0005\u0003_A\u0012A\"\u0013;fe\u0006\u0014G.Z(oG\u0016T!!L\u0007\u0011\u0005I\u0011\u0014BA\u001a\u000e\u0005\u0019!u.\u001e2mK\u00069\u0012mY2v[Vd\u0017\r^3J]R\u001cu\u000e\u001c7fGRLwN\u001c\u000b\u0003me\u0002\"AF\u001c\n\u0005a:!aF!dGVlW\u000f\\1uK&sGoQ8mY\u0016\u001cG/[8o\u0011\u0015!3\u00011\u0001;!\r1cf\u000f\t\u0003%qJ!!P\u0007\u0003\u0007%sG/\u0001\rbG\u000e,X.\u001e7bi\u0016duN\\4D_2dWm\u0019;j_:$\"\u0001Q\"\u0011\u0005Y\t\u0015B\u0001\"\b\u0005a\t5mY;nk2\fG/\u001a\'p]\u001e\u001cu\u000e\u001c7fGRLwN\u001c\u0005\u0006I\u0011\u0001\r\u0001\u0012\t\u0004M9*\u0005C\u0001\nG\u0013\t9UB\u0001\u0003M_:<\u0017AE1dGVlW\u000f\\1uK\u0006s\u00170\u0011:sCf,\"A\u0013)\u0015\u0005-K\u0006c\u0001\fM\u001d&\u0011Qj\u0002\u0002\u0013\u0003\u000e\u001cW/\\;mCR,\u0017I\\=BeJ\f\u0017\u0010\u0005\u0002P!2\u0001A!B)\u0006\u0005\u0004\u0011&!A!\u0012\u0005M3\u0006C\u0001\nU\u0013\t)VBA\u0004O_RD\u0017N\\4\u0011\u0005I9\u0016B\u0001-\u000e\u0005\r\te.\u001f\u0005\u0006I\u0015\u0001\rA\u0017\t\u0004%ms\u0015B\u0001/\u000e\u0005\u0015\t%O]1z\u0001"
    )
  ScalaInlineInfo: length = 0x31 (unknown attribute)
   01 00 00 09 00 27 00 28 01 00 21 00 22 00 00 1F
   00 20 01 00 0F 00 10 00 00 0B 00 0C 01 00 18 00
   10 00 00 17 00 0C 01 00 1C 00 10 00 00 1B 00 0C
   01
  ScalaSig: length = 0x3 (unknown attribute)
   05 02 00
