Classfile /Users/mw/Projects/slang-braindump/.jar/jar11/assemble/slang-braindump/assemble/content/scala/compat/java8/converterImpl/StepperExtensions$mcJ$sp.class
  Last modified May 29, 2022; size 8093 bytes
  SHA-256 checksum 1c037a37c7aa606b999d6a69fbeed6ee7de6d2288d66b575e5d13e7a77b90e5e
  Compiled from "StepperExtensions.scala"
public class scala.compat.java8.converterImpl.StepperExtensions$mcJ$sp extends scala.compat.java8.converterImpl.StepperExtensions<java.lang.Object>
  minor version: 0
  major version: 52
  flags: (0x0021) ACC_PUBLIC, ACC_SUPER
  this_class: #2                          // scala/compat/java8/converterImpl/StepperExtensions$mcJ$sp
  super_class: #5                         // scala/compat/java8/converterImpl/StepperExtensions
  interfaces: 0, fields: 1, methods: 33, attributes: 4
Constant pool:
    #1 = Utf8               scala/compat/java8/converterImpl/StepperExtensions$mcJ$sp
    #2 = Class              #1            // scala/compat/java8/converterImpl/StepperExtensions$mcJ$sp
    #3 = Utf8               Lscala/compat/java8/converterImpl/StepperExtensions<Ljava/lang/Object;>;
    #4 = Utf8               scala/compat/java8/converterImpl/StepperExtensions
    #5 = Class              #4            // scala/compat/java8/converterImpl/StepperExtensions
    #6 = Utf8               StepperExtensions.scala
    #7 = Utf8               s$mcJ$sp
    #8 = Utf8               Lscala/collection/Stepper;
    #9 = Utf8               Lscala/collection/Stepper<Ljava/lang/Object;>;
   #10 = Utf8               ()Lscala/collection/Stepper;
   #11 = Utf8               ()Lscala/collection/Stepper<Ljava/lang/Object;>;
   #12 = NameAndType        #7:#8         // s$mcJ$sp:Lscala/collection/Stepper;
   #13 = Fieldref           #2.#12        // scala/compat/java8/converterImpl/StepperExtensions$mcJ$sp.s$mcJ$sp:Lscala/collection/Stepper;
   #14 = Utf8               this
   #15 = Utf8               Lscala/compat/java8/converterImpl/StepperExtensions$mcJ$sp;
   #16 = Utf8               s
   #17 = NameAndType        #7:#10        // s$mcJ$sp:()Lscala/collection/Stepper;
   #18 = Methodref          #2.#17        // scala/compat/java8/converterImpl/StepperExtensions$mcJ$sp.s$mcJ$sp:()Lscala/collection/Stepper;
   #19 = Utf8               substep
   #20 = Utf8               substep$mcJ$sp
   #21 = NameAndType        #20:#10       // substep$mcJ$sp:()Lscala/collection/Stepper;
   #22 = Methodref          #2.#21        // scala/compat/java8/converterImpl/StepperExtensions$mcJ$sp.substep$mcJ$sp:()Lscala/collection/Stepper;
   #23 = NameAndType        #16:#10       // s:()Lscala/collection/Stepper;
   #24 = Methodref          #2.#23        // scala/compat/java8/converterImpl/StepperExtensions$mcJ$sp.s:()Lscala/collection/Stepper;
   #25 = Utf8               scala/collection/Stepper
   #26 = Class              #25           // scala/collection/Stepper
   #27 = Utf8               trySplit$mcJ$sp
   #28 = NameAndType        #27:#10       // trySplit$mcJ$sp:()Lscala/collection/Stepper;
   #29 = InterfaceMethodref #26.#28       // scala/collection/Stepper.trySplit$mcJ$sp:()Lscala/collection/Stepper;
   #30 = Utf8               count
   #31 = Utf8               (Lscala/Function1;)J
   #32 = Utf8               (Lscala/Function1<Ljava/lang/Object;Ljava/lang/Object;>;)J
   #33 = Utf8               p
   #34 = Utf8               count$mcJ$sp
   #35 = NameAndType        #34:#31       // count$mcJ$sp:(Lscala/Function1;)J
   #36 = Methodref          #2.#35        // scala/compat/java8/converterImpl/StepperExtensions$mcJ$sp.count$mcJ$sp:(Lscala/Function1;)J
   #37 = Utf8               Lscala/Function1;
   #38 = Utf8               hasStep
   #39 = Utf8               ()Z
   #40 = NameAndType        #38:#39       // hasStep:()Z
   #41 = InterfaceMethodref #26.#40       // scala/collection/Stepper.hasStep:()Z
   #42 = Utf8               nextStep$mcJ$sp
   #43 = Utf8               ()J
   #44 = NameAndType        #42:#43       // nextStep$mcJ$sp:()J
   #45 = InterfaceMethodref #26.#44       // scala/collection/Stepper.nextStep$mcJ$sp:()J
   #46 = Utf8               scala/Function1
   #47 = Class              #46           // scala/Function1
   #48 = Utf8               apply$mcZJ$sp
   #49 = Utf8               (J)Z
   #50 = NameAndType        #48:#49       // apply$mcZJ$sp:(J)Z
   #51 = InterfaceMethodref #47.#50       // scala/Function1.apply$mcZJ$sp:(J)Z
   #52 = Utf8               n
   #53 = Utf8               J
   #54 = Utf8               exists
   #55 = Utf8               (Lscala/Function1;)Z
   #56 = Utf8               (Lscala/Function1<Ljava/lang/Object;Ljava/lang/Object;>;)Z
   #57 = Utf8               exists$mcJ$sp
   #58 = NameAndType        #57:#55       // exists$mcJ$sp:(Lscala/Function1;)Z
   #59 = Methodref          #2.#58        // scala/compat/java8/converterImpl/StepperExtensions$mcJ$sp.exists$mcJ$sp:(Lscala/Function1;)Z
   #60 = Utf8               find
   #61 = Utf8               (Lscala/Function1;)Lscala/Option;
   #62 = Utf8               (Lscala/Function1<Ljava/lang/Object;Ljava/lang/Object;>;)Lscala/Option<Ljava/lang/Object;>;
   #63 = Utf8               find$mcJ$sp
   #64 = NameAndType        #63:#61       // find$mcJ$sp:(Lscala/Function1;)Lscala/Option;
   #65 = Methodref          #2.#64        // scala/compat/java8/converterImpl/StepperExtensions$mcJ$sp.find$mcJ$sp:(Lscala/Function1;)Lscala/Option;
   #66 = Utf8               scala/Some
   #67 = Class              #66           // scala/Some
   #68 = Utf8               scala/runtime/BoxesRunTime
   #69 = Class              #68           // scala/runtime/BoxesRunTime
   #70 = Utf8               boxToLong
   #71 = Utf8               (J)Ljava/lang/Long;
   #72 = NameAndType        #70:#71       // boxToLong:(J)Ljava/lang/Long;
   #73 = Methodref          #69.#72       // scala/runtime/BoxesRunTime.boxToLong:(J)Ljava/lang/Long;
   #74 = Utf8               <init>
   #75 = Utf8               (Ljava/lang/Object;)V
   #76 = NameAndType        #74:#75       // "<init>":(Ljava/lang/Object;)V
   #77 = Methodref          #67.#76       // scala/Some."<init>":(Ljava/lang/Object;)V
   #78 = Utf8               scala/None$
   #79 = Class              #78           // scala/None$
   #80 = Utf8               MODULE$
   #81 = Utf8               Lscala/None$;
   #82 = NameAndType        #80:#81       // MODULE$:Lscala/None$;
   #83 = Fieldref           #79.#82       // scala/None$.MODULE$:Lscala/None$;
   #84 = Utf8               a
   #85 = Utf8               fold
   #86 = Utf8               (Ljava/lang/Object;Lscala/Function2;)Ljava/lang/Object;
   #87 = Utf8               <B:Ljava/lang/Object;>(TB;Lscala/Function2<TB;Ljava/lang/Object;TB;>;)TB;
   #88 = Utf8               zero
   #89 = Utf8               op
   #90 = Utf8               fold$mcJ$sp
   #91 = NameAndType        #90:#86       // fold$mcJ$sp:(Ljava/lang/Object;Lscala/Function2;)Ljava/lang/Object;
   #92 = Methodref          #2.#91        // scala/compat/java8/converterImpl/StepperExtensions$mcJ$sp.fold$mcJ$sp:(Ljava/lang/Object;Lscala/Function2;)Ljava/lang/Object;
   #93 = Utf8               Ljava/lang/Object;
   #94 = Utf8               Lscala/Function2;
   #95 = Utf8               scala/Function2
   #96 = Class              #95           // scala/Function2
   #97 = Utf8               apply
   #98 = Utf8               (Ljava/lang/Object;Ljava/lang/Object;)Ljava/lang/Object;
   #99 = NameAndType        #97:#98       // apply:(Ljava/lang/Object;Ljava/lang/Object;)Ljava/lang/Object;
  #100 = InterfaceMethodref #96.#99       // scala/Function2.apply:(Ljava/lang/Object;Ljava/lang/Object;)Ljava/lang/Object;
  #101 = Utf8               b
  #102 = Utf8               java/lang/Object
  #103 = Class              #102          // java/lang/Object
  #104 = Utf8               fold$mDc$sp
  #105 = Utf8               (DLscala/Function2;)D
  #106 = Utf8               (DLscala/Function2<Ljava/lang/Object;Ljava/lang/Object;Ljava/lang/Object;>;)D
  #107 = Utf8               fold$mDcJ$sp
  #108 = NameAndType        #107:#105     // fold$mDcJ$sp:(DLscala/Function2;)D
  #109 = Methodref          #2.#108       // scala/compat/java8/converterImpl/StepperExtensions$mcJ$sp.fold$mDcJ$sp:(DLscala/Function2;)D
  #110 = Utf8               D
  #111 = Utf8               apply$mcDDJ$sp
  #112 = Utf8               (DJ)D
  #113 = NameAndType        #111:#112     // apply$mcDDJ$sp:(DJ)D
  #114 = InterfaceMethodref #96.#113      // scala/Function2.apply$mcDDJ$sp:(DJ)D
  #115 = Utf8               fold$mIc$sp
  #116 = Utf8               (ILscala/Function2;)I
  #117 = Utf8               (ILscala/Function2<Ljava/lang/Object;Ljava/lang/Object;Ljava/lang/Object;>;)I
  #118 = Utf8               fold$mIcJ$sp
  #119 = NameAndType        #118:#116     // fold$mIcJ$sp:(ILscala/Function2;)I
  #120 = Methodref          #2.#119       // scala/compat/java8/converterImpl/StepperExtensions$mcJ$sp.fold$mIcJ$sp:(ILscala/Function2;)I
  #121 = Utf8               I
  #122 = Utf8               apply$mcIIJ$sp
  #123 = Utf8               (IJ)I
  #124 = NameAndType        #122:#123     // apply$mcIIJ$sp:(IJ)I
  #125 = InterfaceMethodref #96.#124      // scala/Function2.apply$mcIIJ$sp:(IJ)I
  #126 = Utf8               fold$mJc$sp
  #127 = Utf8               (JLscala/Function2;)J
  #128 = Utf8               (JLscala/Function2<Ljava/lang/Object;Ljava/lang/Object;Ljava/lang/Object;>;)J
  #129 = Utf8               fold$mJcJ$sp
  #130 = NameAndType        #129:#127     // fold$mJcJ$sp:(JLscala/Function2;)J
  #131 = Methodref          #2.#130       // scala/compat/java8/converterImpl/StepperExtensions$mcJ$sp.fold$mJcJ$sp:(JLscala/Function2;)J
  #132 = Utf8               apply$mcJJJ$sp
  #133 = Utf8               (JJ)J
  #134 = NameAndType        #132:#133     // apply$mcJJJ$sp:(JJ)J
  #135 = InterfaceMethodref #96.#134      // scala/Function2.apply$mcJJJ$sp:(JJ)J
  #136 = Utf8               foldTo
  #137 = Utf8               (Ljava/lang/Object;Lscala/Function2;Lscala/Function1;)Ljava/lang/Object;
  #138 = Utf8               <B:Ljava/lang/Object;>(TB;Lscala/Function2<TB;Ljava/lang/Object;TB;>;Lscala/Function1<TB;Ljava/lang/Object;>;)TB;
  #139 = Utf8               foldTo$mcJ$sp
  #140 = NameAndType        #139:#137     // foldTo$mcJ$sp:(Ljava/lang/Object;Lscala/Function2;Lscala/Function1;)Ljava/lang/Object;
  #141 = Methodref          #2.#140       // scala/compat/java8/converterImpl/StepperExtensions$mcJ$sp.foldTo$mcJ$sp:(Ljava/lang/Object;Lscala/Function2;Lscala/Function1;)Ljava/lang/Object;
  #142 = Utf8               (Ljava/lang/Object;)Ljava/lang/Object;
  #143 = NameAndType        #97:#142      // apply:(Ljava/lang/Object;)Ljava/lang/Object;
  #144 = InterfaceMethodref #47.#143      // scala/Function1.apply:(Ljava/lang/Object;)Ljava/lang/Object;
  #145 = Utf8               unboxToBoolean
  #146 = Utf8               (Ljava/lang/Object;)Z
  #147 = NameAndType        #145:#146     // unboxToBoolean:(Ljava/lang/Object;)Z
  #148 = Methodref          #69.#147      // scala/runtime/BoxesRunTime.unboxToBoolean:(Ljava/lang/Object;)Z
  #149 = Utf8               foldTo$mDc$sp
  #150 = Utf8               (DLscala/Function2;Lscala/Function1;)D
  #151 = Utf8               (DLscala/Function2<Ljava/lang/Object;Ljava/lang/Object;Ljava/lang/Object;>;Lscala/Function1<Ljava/lang/Object;Ljava/lang/Object;>;)D
  #152 = Utf8               foldTo$mDcJ$sp
  #153 = NameAndType        #152:#150     // foldTo$mDcJ$sp:(DLscala/Function2;Lscala/Function1;)D
  #154 = Methodref          #2.#153       // scala/compat/java8/converterImpl/StepperExtensions$mcJ$sp.foldTo$mDcJ$sp:(DLscala/Function2;Lscala/Function1;)D
  #155 = Utf8               apply$mcZD$sp
  #156 = Utf8               (D)Z
  #157 = NameAndType        #155:#156     // apply$mcZD$sp:(D)Z
  #158 = InterfaceMethodref #47.#157      // scala/Function1.apply$mcZD$sp:(D)Z
  #159 = Utf8               foldTo$mIc$sp
  #160 = Utf8               (ILscala/Function2;Lscala/Function1;)I
  #161 = Utf8               (ILscala/Function2<Ljava/lang/Object;Ljava/lang/Object;Ljava/lang/Object;>;Lscala/Function1<Ljava/lang/Object;Ljava/lang/Object;>;)I
  #162 = Utf8               foldTo$mIcJ$sp
  #163 = NameAndType        #162:#160     // foldTo$mIcJ$sp:(ILscala/Function2;Lscala/Function1;)I
  #164 = Methodref          #2.#163       // scala/compat/java8/converterImpl/StepperExtensions$mcJ$sp.foldTo$mIcJ$sp:(ILscala/Function2;Lscala/Function1;)I
  #165 = Utf8               apply$mcZI$sp
  #166 = Utf8               (I)Z
  #167 = NameAndType        #165:#166     // apply$mcZI$sp:(I)Z
  #168 = InterfaceMethodref #47.#167      // scala/Function1.apply$mcZI$sp:(I)Z
  #169 = Utf8               foldTo$mJc$sp
  #170 = Utf8               (JLscala/Function2;Lscala/Function1;)J
  #171 = Utf8               (JLscala/Function2<Ljava/lang/Object;Ljava/lang/Object;Ljava/lang/Object;>;Lscala/Function1<Ljava/lang/Object;Ljava/lang/Object;>;)J
  #172 = Utf8               foldTo$mJcJ$sp
  #173 = NameAndType        #172:#170     // foldTo$mJcJ$sp:(JLscala/Function2;Lscala/Function1;)J
  #174 = Methodref          #2.#173       // scala/compat/java8/converterImpl/StepperExtensions$mcJ$sp.foldTo$mJcJ$sp:(JLscala/Function2;Lscala/Function1;)J
  #175 = Utf8               foreach
  #176 = Utf8               (Lscala/Function1;)V
  #177 = Utf8               (Lscala/Function1<Ljava/lang/Object;Lscala/runtime/BoxedUnit;>;)V
  #178 = Utf8               f
  #179 = Utf8               foreach$mcJ$sp
  #180 = NameAndType        #179:#176     // foreach$mcJ$sp:(Lscala/Function1;)V
  #181 = Methodref          #2.#180       // scala/compat/java8/converterImpl/StepperExtensions$mcJ$sp.foreach$mcJ$sp:(Lscala/Function1;)V
  #182 = Utf8               apply$mcVJ$sp
  #183 = Utf8               (J)V
  #184 = NameAndType        #182:#183     // apply$mcVJ$sp:(J)V
  #185 = InterfaceMethodref #47.#184      // scala/Function1.apply$mcVJ$sp:(J)V
  #186 = Utf8               reduce
  #187 = Utf8               (Lscala/Function2;)J
  #188 = Utf8               (Lscala/Function2<Ljava/lang/Object;Ljava/lang/Object;Ljava/lang/Object;>;)J
  #189 = Utf8               reduce$mcJ$sp
  #190 = NameAndType        #189:#187     // reduce$mcJ$sp:(Lscala/Function2;)J
  #191 = Methodref          #2.#190       // scala/compat/java8/converterImpl/StepperExtensions$mcJ$sp.reduce$mcJ$sp:(Lscala/Function2;)J
  #192 = Utf8               specInstance$
  #193 = Utf8               (Lscala/Function2;)Ljava/lang/Object;
  #194 = NameAndType        #186:#187     // reduce:(Lscala/Function2;)J
  #195 = Methodref          #2.#194       // scala/compat/java8/converterImpl/StepperExtensions$mcJ$sp.reduce:(Lscala/Function2;)J
  #196 = Utf8               (Lscala/collection/Stepper;)V
  #197 = Utf8               (Lscala/collection/Stepper<Ljava/lang/Object;>;)V
  #198 = NameAndType        #74:#196      // "<init>":(Lscala/collection/Stepper;)V
  #199 = Methodref          #5.#198       // scala/compat/java8/converterImpl/StepperExtensions."<init>":(Lscala/collection/Stepper;)V
  #200 = Utf8               Signature
  #201 = Utf8               Code
  #202 = Utf8               LocalVariableTable
  #203 = Utf8               LineNumberTable
  #204 = Utf8               MethodParameters
  #205 = Utf8               StackMapTable
  #206 = Utf8               SourceFile
  #207 = Utf8               ScalaInlineInfo
  #208 = Utf8               Scala
{
  public final scala.collection.Stepper<java.lang.Object> s$mcJ$sp;
    descriptor: Lscala/collection/Stepper;
    flags: (0x0011) ACC_PUBLIC, ACC_FINAL
    Signature: #9                           // Lscala/collection/Stepper<Ljava/lang/Object;>;

  public scala.collection.Stepper<java.lang.Object> s$mcJ$sp();
    descriptor: ()Lscala/collection/Stepper;
    flags: (0x0001) ACC_PUBLIC
    Code:
      stack=1, locals=1, args_size=1
         0: aload_0
         1: getfield      #13                 // Field s$mcJ$sp:Lscala/collection/Stepper;
         4: areturn
      LocalVariableTable:
        Start  Length  Slot  Name   Signature
            0       5     0  this   Lscala/compat/java8/converterImpl/StepperExtensions$mcJ$sp;
    Signature: #11                          // ()Lscala/collection/Stepper<Ljava/lang/Object;>;

  public scala.collection.Stepper<java.lang.Object> s();
    descriptor: ()Lscala/collection/Stepper;
    flags: (0x0001) ACC_PUBLIC
    Code:
      stack=1, locals=1, args_size=1
         0: aload_0
         1: invokevirtual #18                 // Method s$mcJ$sp:()Lscala/collection/Stepper;
         4: areturn
      LineNumberTable:
        line 19: 0
      LocalVariableTable:
        Start  Length  Slot  Name   Signature
            0       5     0  this   Lscala/compat/java8/converterImpl/StepperExtensions$mcJ$sp;
    Signature: #11                          // ()Lscala/collection/Stepper<Ljava/lang/Object;>;

  public scala.collection.Stepper<java.lang.Object> substep();
    descriptor: ()Lscala/collection/Stepper;
    flags: (0x0001) ACC_PUBLIC
    Code:
      stack=1, locals=1, args_size=1
         0: aload_0
         1: invokevirtual #22                 // Method substep$mcJ$sp:()Lscala/collection/Stepper;
         4: areturn
      LineNumberTable:
        line 44: 0
      LocalVariableTable:
        Start  Length  Slot  Name   Signature
            0       5     0  this   Lscala/compat/java8/converterImpl/StepperExtensions$mcJ$sp;
    Signature: #11                          // ()Lscala/collection/Stepper<Ljava/lang/Object;>;

  public scala.collection.Stepper<java.lang.Object> substep$mcJ$sp();
    descriptor: ()Lscala/collection/Stepper;
    flags: (0x0001) ACC_PUBLIC
    Code:
      stack=1, locals=1, args_size=1
         0: aload_0
         1: invokevirtual #24                 // Method s:()Lscala/collection/Stepper;
         4: invokeinterface #29,  1           // InterfaceMethod scala/collection/Stepper.trySplit$mcJ$sp:()Lscala/collection/Stepper;
         9: areturn
      LineNumberTable:
        line 44: 0
      LocalVariableTable:
        Start  Length  Slot  Name   Signature
            0      10     0  this   Lscala/compat/java8/converterImpl/StepperExtensions$mcJ$sp;
    Signature: #11                          // ()Lscala/collection/Stepper<Ljava/lang/Object;>;

  public long count(scala.Function1<java.lang.Object, java.lang.Object>);
    descriptor: (Lscala/Function1;)J
    flags: (0x0001) ACC_PUBLIC
    Code:
      stack=2, locals=2, args_size=2
         0: aload_0
         1: aload_1
         2: invokevirtual #36                 // Method count$mcJ$sp:(Lscala/Function1;)J
         5: lreturn
      LineNumberTable:
        line 54: 0
      LocalVariableTable:
        Start  Length  Slot  Name   Signature
            0       6     0  this   Lscala/compat/java8/converterImpl/StepperExtensions$mcJ$sp;
            0       6     1     p   Lscala/Function1;
    Signature: #32                          // (Lscala/Function1<Ljava/lang/Object;Ljava/lang/Object;>;)J
    MethodParameters:
      Name                           Flags
      p                              final

  public long count$mcJ$sp(scala.Function1<java.lang.Object, java.lang.Object>);
    descriptor: (Lscala/Function1;)J
    flags: (0x0001) ACC_PUBLIC
    Code:
      stack=4, locals=4, args_size=2
         0: lconst_0
         1: lstore_2
         2: aload_0
         3: invokevirtual #24                 // Method s:()Lscala/collection/Stepper;
         6: invokeinterface #41,  1           // InterfaceMethod scala/collection/Stepper.hasStep:()Z
        11: ifeq          42
        14: aload_1
        15: aload_0
        16: invokevirtual #24                 // Method s:()Lscala/collection/Stepper;
        19: invokeinterface #45,  1           // InterfaceMethod scala/collection/Stepper.nextStep$mcJ$sp:()J
        24: invokeinterface #51,  3           // InterfaceMethod scala/Function1.apply$mcZJ$sp:(J)Z
        29: ifeq          39
        32: lload_2
        33: lconst_1
        34: ladd
        35: lstore_2
        36: goto          39
        39: goto          2
        42: lload_2
        43: lreturn
      StackMapTable: number_of_entries = 3
        frame_type = 252 /* append */
          offset_delta = 2
          locals = [ long ]
        frame_type = 36 /* same */
        frame_type = 2 /* same */
      LineNumberTable:
        line 54: 0
      LocalVariableTable:
        Start  Length  Slot  Name   Signature
            2      41     2     n   J
            0      44     0  this   Lscala/compat/java8/converterImpl/StepperExtensions$mcJ$sp;
            0      44     1     p   Lscala/Function1;
    Signature: #32                          // (Lscala/Function1<Ljava/lang/Object;Ljava/lang/Object;>;)J
    MethodParameters:
      Name                           Flags
      p                              final

  public boolean exists(scala.Function1<java.lang.Object, java.lang.Object>);
    descriptor: (Lscala/Function1;)Z
    flags: (0x0001) ACC_PUBLIC
    Code:
      stack=2, locals=2, args_size=2
         0: aload_0
         1: aload_1
         2: invokevirtual #59                 // Method exists$mcJ$sp:(Lscala/Function1;)Z
         5: ireturn
      LineNumberTable:
        line 59: 0
      LocalVariableTable:
        Start  Length  Slot  Name   Signature
            0       6     0  this   Lscala/compat/java8/converterImpl/StepperExtensions$mcJ$sp;
            0       6     1     p   Lscala/Function1;
    Signature: #56                          // (Lscala/Function1<Ljava/lang/Object;Ljava/lang/Object;>;)Z
    MethodParameters:
      Name                           Flags
      p                              final

  public boolean exists$mcJ$sp(scala.Function1<java.lang.Object, java.lang.Object>);
    descriptor: (Lscala/Function1;)Z
    flags: (0x0001) ACC_PUBLIC
    Code:
      stack=3, locals=2, args_size=2
         0: aload_0
         1: invokevirtual #24                 // Method s:()Lscala/collection/Stepper;
         4: invokeinterface #41,  1           // InterfaceMethod scala/collection/Stepper.hasStep:()Z
         9: ifeq          35
        12: aload_1
        13: aload_0
        14: invokevirtual #24                 // Method s:()Lscala/collection/Stepper;
        17: invokeinterface #45,  1           // InterfaceMethod scala/collection/Stepper.nextStep$mcJ$sp:()J
        22: invokeinterface #51,  3           // InterfaceMethod scala/Function1.apply$mcZJ$sp:(J)Z
        27: ifeq          32
        30: iconst_1
        31: ireturn
        32: goto          0
        35: iconst_0
        36: ireturn
      StackMapTable: number_of_entries = 3
        frame_type = 0 /* same */
        frame_type = 31 /* same */
        frame_type = 2 /* same */
      LineNumberTable:
        line 59: 0
      LocalVariableTable:
        Start  Length  Slot  Name   Signature
            0      37     0  this   Lscala/compat/java8/converterImpl/StepperExtensions$mcJ$sp;
            0      37     1     p   Lscala/Function1;
    Signature: #56                          // (Lscala/Function1<Ljava/lang/Object;Ljava/lang/Object;>;)Z
    MethodParameters:
      Name                           Flags
      p                              final

  public scala.Option<java.lang.Object> find(scala.Function1<java.lang.Object, java.lang.Object>);
    descriptor: (Lscala/Function1;)Lscala/Option;
    flags: (0x0001) ACC_PUBLIC
    Code:
      stack=2, locals=2, args_size=2
         0: aload_0
         1: aload_1
         2: invokevirtual #65                 // Method find$mcJ$sp:(Lscala/Function1;)Lscala/Option;
         5: areturn
      LineNumberTable:
        line 64: 0
      LocalVariableTable:
        Start  Length  Slot  Name   Signature
            0       6     0  this   Lscala/compat/java8/converterImpl/StepperExtensions$mcJ$sp;
            0       6     1     p   Lscala/Function1;
    Signature: #62                          // (Lscala/Function1<Ljava/lang/Object;Ljava/lang/Object;>;)Lscala/Option<Ljava/lang/Object;>;
    MethodParameters:
      Name                           Flags
      p                              final

  public scala.Option<java.lang.Object> find$mcJ$sp(scala.Function1<java.lang.Object, java.lang.Object>);
    descriptor: (Lscala/Function1;)Lscala/Option;
    flags: (0x0001) ACC_PUBLIC
    Code:
      stack=4, locals=4, args_size=2
         0: aload_0
         1: invokevirtual #24                 // Method s:()Lscala/collection/Stepper;
         4: invokeinterface #41,  1           // InterfaceMethod scala/collection/Stepper.hasStep:()Z
         9: ifeq          47
        12: aload_0
        13: invokevirtual #24                 // Method s:()Lscala/collection/Stepper;
        16: invokeinterface #45,  1           // InterfaceMethod scala/collection/Stepper.nextStep$mcJ$sp:()J
        21: lstore_2
        22: aload_1
        23: lload_2
        24: invokeinterface #51,  3           // InterfaceMethod scala/Function1.apply$mcZJ$sp:(J)Z
        29: ifeq          44
        32: new           #67                 // class scala/Some
        35: dup
        36: lload_2
        37: invokestatic  #73                 // Method scala/runtime/BoxesRunTime.boxToLong:(J)Ljava/lang/Long;
        40: invokespecial #77                 // Method scala/Some."<init>":(Ljava/lang/Object;)V
        43: areturn
        44: goto          0
        47: getstatic     #83                 // Field scala/None$.MODULE$:Lscala/None$;
        50: areturn
      StackMapTable: number_of_entries = 3
        frame_type = 0 /* same */
        frame_type = 252 /* append */
          offset_delta = 43
          locals = [ long ]
        frame_type = 250 /* chop */
          offset_delta = 2
      LineNumberTable:
        line 64: 0
      LocalVariableTable:
        Start  Length  Slot  Name   Signature
           22      22     2     a   J
            0      51     0  this   Lscala/compat/java8/converterImpl/StepperExtensions$mcJ$sp;
            0      51     1     p   Lscala/Function1;
    Signature: #62                          // (Lscala/Function1<Ljava/lang/Object;Ljava/lang/Object;>;)Lscala/Option<Ljava/lang/Object;>;
    MethodParameters:
      Name                           Flags
      p                              final

  public <B extends java.lang.Object> B fold(B, scala.Function2<B, java.lang.Object, B>);
    descriptor: (Ljava/lang/Object;Lscala/Function2;)Ljava/lang/Object;
    flags: (0x0001) ACC_PUBLIC
    Code:
      stack=3, locals=3, args_size=3
         0: aload_0
         1: aload_1
         2: aload_2
         3: invokevirtual #92                 // Method fold$mcJ$sp:(Ljava/lang/Object;Lscala/Function2;)Ljava/lang/Object;
         6: areturn
      LineNumberTable:
        line 70: 0
      LocalVariableTable:
        Start  Length  Slot  Name   Signature
            0       7     0  this   Lscala/compat/java8/converterImpl/StepperExtensions$mcJ$sp;
            0       7     1  zero   Ljava/lang/Object;
            0       7     2    op   Lscala/Function2;
    Signature: #87                          // <B:Ljava/lang/Object;>(TB;Lscala/Function2<TB;Ljava/lang/Object;TB;>;)TB;
    MethodParameters:
      Name                           Flags
      zero                           final
      op                             final

  public <B extends java.lang.Object> B fold$mcJ$sp(B, scala.Function2<B, java.lang.Object, B>);
    descriptor: (Ljava/lang/Object;Lscala/Function2;)Ljava/lang/Object;
    flags: (0x0001) ACC_PUBLIC
    Code:
      stack=4, locals=4, args_size=3
         0: aload_1
         1: astore_3
         2: aload_0
         3: invokevirtual #24                 // Method s:()Lscala/collection/Stepper;
         6: invokeinterface #41,  1           // InterfaceMethod scala/collection/Stepper.hasStep:()Z
        11: ifeq          37
        14: aload_2
        15: aload_3
        16: aload_0
        17: invokevirtual #24                 // Method s:()Lscala/collection/Stepper;
        20: invokeinterface #45,  1           // InterfaceMethod scala/collection/Stepper.nextStep$mcJ$sp:()J
        25: invokestatic  #73                 // Method scala/runtime/BoxesRunTime.boxToLong:(J)Ljava/lang/Long;
        28: invokeinterface #100,  3          // InterfaceMethod scala/Function2.apply:(Ljava/lang/Object;Ljava/lang/Object;)Ljava/lang/Object;
        33: astore_3
        34: goto          2
        37: aload_3
        38: areturn
      StackMapTable: number_of_entries = 2
        frame_type = 252 /* append */
          offset_delta = 2
          locals = [ class java/lang/Object ]
        frame_type = 34 /* same */
      LineNumberTable:
        line 70: 0
      LocalVariableTable:
        Start  Length  Slot  Name   Signature
            2      36     3     b   Ljava/lang/Object;
            0      39     0  this   Lscala/compat/java8/converterImpl/StepperExtensions$mcJ$sp;
            0      39     1  zero   Ljava/lang/Object;
            0      39     2    op   Lscala/Function2;
    Signature: #87                          // <B:Ljava/lang/Object;>(TB;Lscala/Function2<TB;Ljava/lang/Object;TB;>;)TB;
    MethodParameters:
      Name                           Flags
      zero                           final
      op                             final

  public double fold$mDc$sp(double, scala.Function2<java.lang.Object, java.lang.Object, java.lang.Object>);
    descriptor: (DLscala/Function2;)D
    flags: (0x0001) ACC_PUBLIC
    Code:
      stack=4, locals=4, args_size=3
         0: aload_0
         1: dload_1
         2: aload_3
         3: invokevirtual #109                // Method fold$mDcJ$sp:(DLscala/Function2;)D
         6: dreturn
      LineNumberTable:
        line 70: 0
      LocalVariableTable:
        Start  Length  Slot  Name   Signature
            0       7     0  this   Lscala/compat/java8/converterImpl/StepperExtensions$mcJ$sp;
            0       7     1  zero   D
            0       7     3    op   Lscala/Function2;
    Signature: #106                         // (DLscala/Function2<Ljava/lang/Object;Ljava/lang/Object;Ljava/lang/Object;>;)D
    MethodParameters:
      Name                           Flags
      zero                           final
      op                             final

  public double fold$mDcJ$sp(double, scala.Function2<java.lang.Object, java.lang.Object, java.lang.Object>);
    descriptor: (DLscala/Function2;)D
    flags: (0x0001) ACC_PUBLIC
    Code:
      stack=5, locals=6, args_size=3
         0: dload_1
         1: dstore        4
         3: aload_0
         4: invokevirtual #24                 // Method s:()Lscala/collection/Stepper;
         7: invokeinterface #41,  1           // InterfaceMethod scala/collection/Stepper.hasStep:()Z
        12: ifeq          37
        15: aload_3
        16: dload         4
        18: aload_0
        19: invokevirtual #24                 // Method s:()Lscala/collection/Stepper;
        22: invokeinterface #45,  1           // InterfaceMethod scala/collection/Stepper.nextStep$mcJ$sp:()J
        27: invokeinterface #114,  5          // InterfaceMethod scala/Function2.apply$mcDDJ$sp:(DJ)D
        32: dstore        4
        34: goto          3
        37: dload         4
        39: dreturn
      StackMapTable: number_of_entries = 2
        frame_type = 252 /* append */
          offset_delta = 3
          locals = [ double ]
        frame_type = 33 /* same */
      LineNumberTable:
        line 70: 0
      LocalVariableTable:
        Start  Length  Slot  Name   Signature
            3      36     4     b   D
            0      40     0  this   Lscala/compat/java8/converterImpl/StepperExtensions$mcJ$sp;
            0      40     1  zero   D
            0      40     3    op   Lscala/Function2;
    Signature: #106                         // (DLscala/Function2<Ljava/lang/Object;Ljava/lang/Object;Ljava/lang/Object;>;)D
    MethodParameters:
      Name                           Flags
      zero                           final
      op                             final

  public int fold$mIc$sp(int, scala.Function2<java.lang.Object, java.lang.Object, java.lang.Object>);
    descriptor: (ILscala/Function2;)I
    flags: (0x0001) ACC_PUBLIC
    Code:
      stack=3, locals=3, args_size=3
         0: aload_0
         1: iload_1
         2: aload_2
         3: invokevirtual #120                // Method fold$mIcJ$sp:(ILscala/Function2;)I
         6: ireturn
      LineNumberTable:
        line 70: 0
      LocalVariableTable:
        Start  Length  Slot  Name   Signature
            0       7     0  this   Lscala/compat/java8/converterImpl/StepperExtensions$mcJ$sp;
            0       7     1  zero   I
            0       7     2    op   Lscala/Function2;
    Signature: #117                         // (ILscala/Function2<Ljava/lang/Object;Ljava/lang/Object;Ljava/lang/Object;>;)I
    MethodParameters:
      Name                           Flags
      zero                           final
      op                             final

  public int fold$mIcJ$sp(int, scala.Function2<java.lang.Object, java.lang.Object, java.lang.Object>);
    descriptor: (ILscala/Function2;)I
    flags: (0x0001) ACC_PUBLIC
    Code:
      stack=4, locals=4, args_size=3
         0: iload_1
         1: istore_3
         2: aload_0
         3: invokevirtual #24                 // Method s:()Lscala/collection/Stepper;
         6: invokeinterface #41,  1           // InterfaceMethod scala/collection/Stepper.hasStep:()Z
        11: ifeq          34
        14: aload_2
        15: iload_3
        16: aload_0
        17: invokevirtual #24                 // Method s:()Lscala/collection/Stepper;
        20: invokeinterface #45,  1           // InterfaceMethod scala/collection/Stepper.nextStep$mcJ$sp:()J
        25: invokeinterface #125,  4          // InterfaceMethod scala/Function2.apply$mcIIJ$sp:(IJ)I
        30: istore_3
        31: goto          2
        34: iload_3
        35: ireturn
      StackMapTable: number_of_entries = 2
        frame_type = 252 /* append */
          offset_delta = 2
          locals = [ int ]
        frame_type = 31 /* same */
      LineNumberTable:
        line 70: 0
      LocalVariableTable:
        Start  Length  Slot  Name   Signature
            2      33     3     b   I
            0      36     0  this   Lscala/compat/java8/converterImpl/StepperExtensions$mcJ$sp;
            0      36     1  zero   I
            0      36     2    op   Lscala/Function2;
    Signature: #117                         // (ILscala/Function2<Ljava/lang/Object;Ljava/lang/Object;Ljava/lang/Object;>;)I
    MethodParameters:
      Name                           Flags
      zero                           final
      op                             final

  public long fold$mJc$sp(long, scala.Function2<java.lang.Object, java.lang.Object, java.lang.Object>);
    descriptor: (JLscala/Function2;)J
    flags: (0x0001) ACC_PUBLIC
    Code:
      stack=4, locals=4, args_size=3
         0: aload_0
         1: lload_1
         2: aload_3
         3: invokevirtual #131                // Method fold$mJcJ$sp:(JLscala/Function2;)J
         6: lreturn
      LineNumberTable:
        line 70: 0
      LocalVariableTable:
        Start  Length  Slot  Name   Signature
            0       7     0  this   Lscala/compat/java8/converterImpl/StepperExtensions$mcJ$sp;
            0       7     1  zero   J
            0       7     3    op   Lscala/Function2;
    Signature: #128                         // (JLscala/Function2<Ljava/lang/Object;Ljava/lang/Object;Ljava/lang/Object;>;)J
    MethodParameters:
      Name                           Flags
      zero                           final
      op                             final

  public long fold$mJcJ$sp(long, scala.Function2<java.lang.Object, java.lang.Object, java.lang.Object>);
    descriptor: (JLscala/Function2;)J
    flags: (0x0001) ACC_PUBLIC
    Code:
      stack=5, locals=6, args_size=3
         0: lload_1
         1: lstore        4
         3: aload_0
         4: invokevirtual #24                 // Method s:()Lscala/collection/Stepper;
         7: invokeinterface #41,  1           // InterfaceMethod scala/collection/Stepper.hasStep:()Z
        12: ifeq          37
        15: aload_3
        16: lload         4
        18: aload_0
        19: invokevirtual #24                 // Method s:()Lscala/collection/Stepper;
        22: invokeinterface #45,  1           // InterfaceMethod scala/collection/Stepper.nextStep$mcJ$sp:()J
        27: invokeinterface #135,  5          // InterfaceMethod scala/Function2.apply$mcJJJ$sp:(JJ)J
        32: lstore        4
        34: goto          3
        37: lload         4
        39: lreturn
      StackMapTable: number_of_entries = 2
        frame_type = 252 /* append */
          offset_delta = 3
          locals = [ long ]
        frame_type = 33 /* same */
      LineNumberTable:
        line 70: 0
      LocalVariableTable:
        Start  Length  Slot  Name   Signature
            3      36     4     b   J
            0      40     0  this   Lscala/compat/java8/converterImpl/StepperExtensions$mcJ$sp;
            0      40     1  zero   J
            0      40     3    op   Lscala/Function2;
    Signature: #128                         // (JLscala/Function2<Ljava/lang/Object;Ljava/lang/Object;Ljava/lang/Object;>;)J
    MethodParameters:
      Name                           Flags
      zero                           final
      op                             final

  public <B extends java.lang.Object> B foldTo(B, scala.Function2<B, java.lang.Object, B>, scala.Function1<B, java.lang.Object>);
    descriptor: (Ljava/lang/Object;Lscala/Function2;Lscala/Function1;)Ljava/lang/Object;
    flags: (0x0001) ACC_PUBLIC
    Code:
      stack=4, locals=4, args_size=4
         0: aload_0
         1: aload_1
         2: aload_2
         3: aload_3
         4: invokevirtual #141                // Method foldTo$mcJ$sp:(Ljava/lang/Object;Lscala/Function2;Lscala/Function1;)Ljava/lang/Object;
         7: areturn
      LineNumberTable:
        line 76: 0
      LocalVariableTable:
        Start  Length  Slot  Name   Signature
            0       8     0  this   Lscala/compat/java8/converterImpl/StepperExtensions$mcJ$sp;
            0       8     1  zero   Ljava/lang/Object;
            0       8     2    op   Lscala/Function2;
            0       8     3     p   Lscala/Function1;
    Signature: #138                         // <B:Ljava/lang/Object;>(TB;Lscala/Function2<TB;Ljava/lang/Object;TB;>;Lscala/Function1<TB;Ljava/lang/Object;>;)TB;
    MethodParameters:
      Name                           Flags
      zero                           final
      op                             final
      p                              final

  public <B extends java.lang.Object> B foldTo$mcJ$sp(B, scala.Function2<B, java.lang.Object, B>, scala.Function1<B, java.lang.Object>);
    descriptor: (Ljava/lang/Object;Lscala/Function2;Lscala/Function1;)Ljava/lang/Object;
    flags: (0x0001) ACC_PUBLIC
    Code:
      stack=4, locals=5, args_size=4
         0: aload_1
         1: astore        4
         3: aload_3
         4: aload         4
         6: invokeinterface #144,  2          // InterfaceMethod scala/Function1.apply:(Ljava/lang/Object;)Ljava/lang/Object;
        11: invokestatic  #148                // Method scala/runtime/BoxesRunTime.unboxToBoolean:(Ljava/lang/Object;)Z
        14: ifne          54
        17: aload_0
        18: invokevirtual #24                 // Method s:()Lscala/collection/Stepper;
        21: invokeinterface #41,  1           // InterfaceMethod scala/collection/Stepper.hasStep:()Z
        26: ifeq          54
        29: aload_2
        30: aload         4
        32: aload_0
        33: invokevirtual #24                 // Method s:()Lscala/collection/Stepper;
        36: invokeinterface #45,  1           // InterfaceMethod scala/collection/Stepper.nextStep$mcJ$sp:()J
        41: invokestatic  #73                 // Method scala/runtime/BoxesRunTime.boxToLong:(J)Ljava/lang/Long;
        44: invokeinterface #100,  3          // InterfaceMethod scala/Function2.apply:(Ljava/lang/Object;Ljava/lang/Object;)Ljava/lang/Object;
        49: astore        4
        51: goto          3
        54: aload         4
        56: areturn
      StackMapTable: number_of_entries = 2
        frame_type = 252 /* append */
          offset_delta = 3
          locals = [ class java/lang/Object ]
        frame_type = 50 /* same */
      LineNumberTable:
        line 76: 0
      LocalVariableTable:
        Start  Length  Slot  Name   Signature
            3      53     4     b   Ljava/lang/Object;
            0      57     0  this   Lscala/compat/java8/converterImpl/StepperExtensions$mcJ$sp;
            0      57     1  zero   Ljava/lang/Object;
            0      57     2    op   Lscala/Function2;
            0      57     3     p   Lscala/Function1;
    Signature: #138                         // <B:Ljava/lang/Object;>(TB;Lscala/Function2<TB;Ljava/lang/Object;TB;>;Lscala/Function1<TB;Ljava/lang/Object;>;)TB;
    MethodParameters:
      Name                           Flags
      zero                           final
      op                             final
      p                              final

  public double foldTo$mDc$sp(double, scala.Function2<java.lang.Object, java.lang.Object, java.lang.Object>, scala.Function1<java.lang.Object, java.lang.Object>);
    descriptor: (DLscala/Function2;Lscala/Function1;)D
    flags: (0x0001) ACC_PUBLIC
    Code:
      stack=5, locals=5, args_size=4
         0: aload_0
         1: dload_1
         2: aload_3
         3: aload         4
         5: invokevirtual #154                // Method foldTo$mDcJ$sp:(DLscala/Function2;Lscala/Function1;)D
         8: dreturn
      LineNumberTable:
        line 76: 0
      LocalVariableTable:
        Start  Length  Slot  Name   Signature
            0       9     0  this   Lscala/compat/java8/converterImpl/StepperExtensions$mcJ$sp;
            0       9     1  zero   D
            0       9     3    op   Lscala/Function2;
            0       9     4     p   Lscala/Function1;
    Signature: #151                         // (DLscala/Function2<Ljava/lang/Object;Ljava/lang/Object;Ljava/lang/Object;>;Lscala/Function1<Ljava/lang/Object;Ljava/lang/Object;>;)D
    MethodParameters:
      Name                           Flags
      zero                           final
      op                             final
      p                              final

  public double foldTo$mDcJ$sp(double, scala.Function2<java.lang.Object, java.lang.Object, java.lang.Object>, scala.Function1<java.lang.Object, java.lang.Object>);
    descriptor: (DLscala/Function2;Lscala/Function1;)D
    flags: (0x0001) ACC_PUBLIC
    Code:
      stack=5, locals=7, args_size=4
         0: dload_1
         1: dstore        5
         3: aload         4
         5: dload         5
         7: invokeinterface #158,  3          // InterfaceMethod scala/Function1.apply$mcZD$sp:(D)Z
        12: ifne          49
        15: aload_0
        16: invokevirtual #24                 // Method s:()Lscala/collection/Stepper;
        19: invokeinterface #41,  1           // InterfaceMethod scala/collection/Stepper.hasStep:()Z
        24: ifeq          49
        27: aload_3
        28: dload         5
        30: aload_0
        31: invokevirtual #24                 // Method s:()Lscala/collection/Stepper;
        34: invokeinterface #45,  1           // InterfaceMethod scala/collection/Stepper.nextStep$mcJ$sp:()J
        39: invokeinterface #114,  5          // InterfaceMethod scala/Function2.apply$mcDDJ$sp:(DJ)D
        44: dstore        5
        46: goto          3
        49: dload         5
        51: dreturn
      StackMapTable: number_of_entries = 2
        frame_type = 252 /* append */
          offset_delta = 3
          locals = [ double ]
        frame_type = 45 /* same */
      LineNumberTable:
        line 76: 0
      LocalVariableTable:
        Start  Length  Slot  Name   Signature
            3      48     5     b   D
            0      52     0  this   Lscala/compat/java8/converterImpl/StepperExtensions$mcJ$sp;
            0      52     1  zero   D
            0      52     3    op   Lscala/Function2;
            0      52     4     p   Lscala/Function1;
    Signature: #151                         // (DLscala/Function2<Ljava/lang/Object;Ljava/lang/Object;Ljava/lang/Object;>;Lscala/Function1<Ljava/lang/Object;Ljava/lang/Object;>;)D
    MethodParameters:
      Name                           Flags
      zero                           final
      op                             final
      p                              final

  public int foldTo$mIc$sp(int, scala.Function2<java.lang.Object, java.lang.Object, java.lang.Object>, scala.Function1<java.lang.Object, java.lang.Object>);
    descriptor: (ILscala/Function2;Lscala/Function1;)I
    flags: (0x0001) ACC_PUBLIC
    Code:
      stack=4, locals=4, args_size=4
         0: aload_0
         1: iload_1
         2: aload_2
         3: aload_3
         4: invokevirtual #164                // Method foldTo$mIcJ$sp:(ILscala/Function2;Lscala/Function1;)I
         7: ireturn
      LineNumberTable:
        line 76: 0
      LocalVariableTable:
        Start  Length  Slot  Name   Signature
            0       8     0  this   Lscala/compat/java8/converterImpl/StepperExtensions$mcJ$sp;
            0       8     1  zero   I
            0       8     2    op   Lscala/Function2;
            0       8     3     p   Lscala/Function1;
    Signature: #161                         // (ILscala/Function2<Ljava/lang/Object;Ljava/lang/Object;Ljava/lang/Object;>;Lscala/Function1<Ljava/lang/Object;Ljava/lang/Object;>;)I
    MethodParameters:
      Name                           Flags
      zero                           final
      op                             final
      p                              final

  public int foldTo$mIcJ$sp(int, scala.Function2<java.lang.Object, java.lang.Object, java.lang.Object>, scala.Function1<java.lang.Object, java.lang.Object>);
    descriptor: (ILscala/Function2;Lscala/Function1;)I
    flags: (0x0001) ACC_PUBLIC
    Code:
      stack=4, locals=5, args_size=4
         0: iload_1
         1: istore        4
         3: aload_3
         4: iload         4
         6: invokeinterface #168,  2          // InterfaceMethod scala/Function1.apply$mcZI$sp:(I)Z
        11: ifne          48
        14: aload_0
        15: invokevirtual #24                 // Method s:()Lscala/collection/Stepper;
        18: invokeinterface #41,  1           // InterfaceMethod scala/collection/Stepper.hasStep:()Z
        23: ifeq          48
        26: aload_2
        27: iload         4
        29: aload_0
        30: invokevirtual #24                 // Method s:()Lscala/collection/Stepper;
        33: invokeinterface #45,  1           // InterfaceMethod scala/collection/Stepper.nextStep$mcJ$sp:()J
        38: invokeinterface #125,  4          // InterfaceMethod scala/Function2.apply$mcIIJ$sp:(IJ)I
        43: istore        4
        45: goto          3
        48: iload         4
        50: ireturn
      StackMapTable: number_of_entries = 2
        frame_type = 252 /* append */
          offset_delta = 3
          locals = [ int ]
        frame_type = 44 /* same */
      LineNumberTable:
        line 76: 0
      LocalVariableTable:
        Start  Length  Slot  Name   Signature
            3      47     4     b   I
            0      51     0  this   Lscala/compat/java8/converterImpl/StepperExtensions$mcJ$sp;
            0      51     1  zero   I
            0      51     2    op   Lscala/Function2;
            0      51     3     p   Lscala/Function1;
    Signature: #161                         // (ILscala/Function2<Ljava/lang/Object;Ljava/lang/Object;Ljava/lang/Object;>;Lscala/Function1<Ljava/lang/Object;Ljava/lang/Object;>;)I
    MethodParameters:
      Name                           Flags
      zero                           final
      op                             final
      p                              final

  public long foldTo$mJc$sp(long, scala.Function2<java.lang.Object, java.lang.Object, java.lang.Object>, scala.Function1<java.lang.Object, java.lang.Object>);
    descriptor: (JLscala/Function2;Lscala/Function1;)J
    flags: (0x0001) ACC_PUBLIC
    Code:
      stack=5, locals=5, args_size=4
         0: aload_0
         1: lload_1
         2: aload_3
         3: aload         4
         5: invokevirtual #174                // Method foldTo$mJcJ$sp:(JLscala/Function2;Lscala/Function1;)J
         8: lreturn
      LineNumberTable:
        line 76: 0
      LocalVariableTable:
        Start  Length  Slot  Name   Signature
            0       9     0  this   Lscala/compat/java8/converterImpl/StepperExtensions$mcJ$sp;
            0       9     1  zero   J
            0       9     3    op   Lscala/Function2;
            0       9     4     p   Lscala/Function1;
    Signature: #171                         // (JLscala/Function2<Ljava/lang/Object;Ljava/lang/Object;Ljava/lang/Object;>;Lscala/Function1<Ljava/lang/Object;Ljava/lang/Object;>;)J
    MethodParameters:
      Name                           Flags
      zero                           final
      op                             final
      p                              final

  public long foldTo$mJcJ$sp(long, scala.Function2<java.lang.Object, java.lang.Object, java.lang.Object>, scala.Function1<java.lang.Object, java.lang.Object>);
    descriptor: (JLscala/Function2;Lscala/Function1;)J
    flags: (0x0001) ACC_PUBLIC
    Code:
      stack=5, locals=7, args_size=4
         0: lload_1
         1: lstore        5
         3: aload         4
         5: lload         5
         7: invokeinterface #51,  3           // InterfaceMethod scala/Function1.apply$mcZJ$sp:(J)Z
        12: ifne          49
        15: aload_0
        16: invokevirtual #24                 // Method s:()Lscala/collection/Stepper;
        19: invokeinterface #41,  1           // InterfaceMethod scala/collection/Stepper.hasStep:()Z
        24: ifeq          49
        27: aload_3
        28: lload         5
        30: aload_0
        31: invokevirtual #24                 // Method s:()Lscala/collection/Stepper;
        34: invokeinterface #45,  1           // InterfaceMethod scala/collection/Stepper.nextStep$mcJ$sp:()J
        39: invokeinterface #135,  5          // InterfaceMethod scala/Function2.apply$mcJJJ$sp:(JJ)J
        44: lstore        5
        46: goto          3
        49: lload         5
        51: lreturn
      StackMapTable: number_of_entries = 2
        frame_type = 252 /* append */
          offset_delta = 3
          locals = [ long ]
        frame_type = 45 /* same */
      LineNumberTable:
        line 76: 0
      LocalVariableTable:
        Start  Length  Slot  Name   Signature
            3      48     5     b   J
            0      52     0  this   Lscala/compat/java8/converterImpl/StepperExtensions$mcJ$sp;
            0      52     1  zero   J
            0      52     3    op   Lscala/Function2;
            0      52     4     p   Lscala/Function1;
    Signature: #171                         // (JLscala/Function2<Ljava/lang/Object;Ljava/lang/Object;Ljava/lang/Object;>;Lscala/Function1<Ljava/lang/Object;Ljava/lang/Object;>;)J
    MethodParameters:
      Name                           Flags
      zero                           final
      op                             final
      p                              final

  public void foreach(scala.Function1<java.lang.Object, scala.runtime.BoxedUnit>);
    descriptor: (Lscala/Function1;)V
    flags: (0x0001) ACC_PUBLIC
    Code:
      stack=2, locals=2, args_size=2
         0: aload_0
         1: aload_1
         2: invokevirtual #181                // Method foreach$mcJ$sp:(Lscala/Function1;)V
         5: return
      LineNumberTable:
        line 81: 0
      LocalVariableTable:
        Start  Length  Slot  Name   Signature
            0       6     0  this   Lscala/compat/java8/converterImpl/StepperExtensions$mcJ$sp;
            0       6     1     f   Lscala/Function1;
    Signature: #177                         // (Lscala/Function1<Ljava/lang/Object;Lscala/runtime/BoxedUnit;>;)V
    MethodParameters:
      Name                           Flags
      f                              final

  public void foreach$mcJ$sp(scala.Function1<java.lang.Object, scala.runtime.BoxedUnit>);
    descriptor: (Lscala/Function1;)V
    flags: (0x0001) ACC_PUBLIC
    Code:
      stack=3, locals=2, args_size=2
         0: aload_0
         1: invokevirtual #24                 // Method s:()Lscala/collection/Stepper;
         4: invokeinterface #41,  1           // InterfaceMethod scala/collection/Stepper.hasStep:()Z
         9: ifeq          30
        12: aload_1
        13: aload_0
        14: invokevirtual #24                 // Method s:()Lscala/collection/Stepper;
        17: invokeinterface #45,  1           // InterfaceMethod scala/collection/Stepper.nextStep$mcJ$sp:()J
        22: invokeinterface #185,  3          // InterfaceMethod scala/Function1.apply$mcVJ$sp:(J)V
        27: goto          0
        30: return
      StackMapTable: number_of_entries = 2
        frame_type = 0 /* same */
        frame_type = 29 /* same */
      LineNumberTable:
        line 81: 0
      LocalVariableTable:
        Start  Length  Slot  Name   Signature
            0      31     0  this   Lscala/compat/java8/converterImpl/StepperExtensions$mcJ$sp;
            0      31     1     f   Lscala/Function1;
    Signature: #177                         // (Lscala/Function1<Ljava/lang/Object;Lscala/runtime/BoxedUnit;>;)V
    MethodParameters:
      Name                           Flags
      f                              final

  public long reduce(scala.Function2<java.lang.Object, java.lang.Object, java.lang.Object>);
    descriptor: (Lscala/Function2;)J
    flags: (0x0001) ACC_PUBLIC
    Code:
      stack=2, locals=2, args_size=2
         0: aload_0
         1: aload_1
         2: invokevirtual #191                // Method reduce$mcJ$sp:(Lscala/Function2;)J
         5: lreturn
      LineNumberTable:
        line 88: 0
      LocalVariableTable:
        Start  Length  Slot  Name   Signature
            0       6     0  this   Lscala/compat/java8/converterImpl/StepperExtensions$mcJ$sp;
            0       6     1    op   Lscala/Function2;
    Signature: #188                         // (Lscala/Function2<Ljava/lang/Object;Ljava/lang/Object;Ljava/lang/Object;>;)J
    MethodParameters:
      Name                           Flags
      op                             final

  public long reduce$mcJ$sp(scala.Function2<java.lang.Object, java.lang.Object, java.lang.Object>);
    descriptor: (Lscala/Function2;)J
    flags: (0x0001) ACC_PUBLIC
    Code:
      stack=5, locals=4, args_size=2
         0: aload_0
         1: invokevirtual #24                 // Method s:()Lscala/collection/Stepper;
         4: invokeinterface #45,  1           // InterfaceMethod scala/collection/Stepper.nextStep$mcJ$sp:()J
         9: lstore_2
        10: aload_0
        11: invokevirtual #24                 // Method s:()Lscala/collection/Stepper;
        14: invokeinterface #41,  1           // InterfaceMethod scala/collection/Stepper.hasStep:()Z
        19: ifeq          42
        22: aload_1
        23: lload_2
        24: aload_0
        25: invokevirtual #24                 // Method s:()Lscala/collection/Stepper;
        28: invokeinterface #45,  1           // InterfaceMethod scala/collection/Stepper.nextStep$mcJ$sp:()J
        33: invokeinterface #135,  5          // InterfaceMethod scala/Function2.apply$mcJJJ$sp:(JJ)J
        38: lstore_2
        39: goto          10
        42: lload_2
        43: lreturn
      StackMapTable: number_of_entries = 2
        frame_type = 252 /* append */
          offset_delta = 10
          locals = [ long ]
        frame_type = 31 /* same */
      LineNumberTable:
        line 88: 0
      LocalVariableTable:
        Start  Length  Slot  Name   Signature
           10      33     2     a   J
            0      44     0  this   Lscala/compat/java8/converterImpl/StepperExtensions$mcJ$sp;
            0      44     1    op   Lscala/Function2;
    Signature: #188                         // (Lscala/Function2<Ljava/lang/Object;Ljava/lang/Object;Ljava/lang/Object;>;)J
    MethodParameters:
      Name                           Flags
      op                             final

  public boolean specInstance$();
    descriptor: ()Z
    flags: (0x0001) ACC_PUBLIC
    Code:
      stack=1, locals=1, args_size=1
         0: iconst_1
         1: ireturn
      LineNumberTable:
        line 19: 0
      LocalVariableTable:
        Start  Length  Slot  Name   Signature
            0       2     0  this   Lscala/compat/java8/converterImpl/StepperExtensions$mcJ$sp;

  public java.lang.Object reduce(scala.Function2);
    descriptor: (Lscala/Function2;)Ljava/lang/Object;
    flags: (0x1041) ACC_PUBLIC, ACC_BRIDGE, ACC_SYNTHETIC
    Code:
      stack=2, locals=2, args_size=2
         0: aload_0
         1: aload_1
         2: invokevirtual #195                // Method reduce:(Lscala/Function2;)J
         5: invokestatic  #73                 // Method scala/runtime/BoxesRunTime.boxToLong:(J)Ljava/lang/Long;
         8: areturn
      LineNumberTable:
        line 19: 0
      LocalVariableTable:
        Start  Length  Slot  Name   Signature
            0       9     0  this   Lscala/compat/java8/converterImpl/StepperExtensions$mcJ$sp;
            0       9     1    op   Lscala/Function2;
    MethodParameters:
      Name                           Flags
      op                             final

  public scala.compat.java8.converterImpl.StepperExtensions$mcJ$sp(scala.collection.Stepper<java.lang.Object>);
    descriptor: (Lscala/collection/Stepper;)V
    flags: (0x0001) ACC_PUBLIC
    Code:
      stack=2, locals=2, args_size=2
         0: aload_0
         1: aload_1
         2: putfield      #13                 // Field s$mcJ$sp:Lscala/collection/Stepper;
         5: aload_0
         6: aload_1
         7: invokespecial #199                // Method scala/compat/java8/converterImpl/StepperExtensions."<init>":(Lscala/collection/Stepper;)V
        10: return
      LineNumberTable:
        line 19: 0
      LocalVariableTable:
        Start  Length  Slot  Name   Signature
            0      11     0  this   Lscala/compat/java8/converterImpl/StepperExtensions$mcJ$sp;
            0      11     1 s$mcJ$sp   Lscala/collection/Stepper;
    Signature: #197                         // (Lscala/collection/Stepper<Ljava/lang/Object;>;)V
    MethodParameters:
      Name                           Flags
      s$mcJ$sp                       final
}
Signature: #3                           // Lscala/compat/java8/converterImpl/StepperExtensions<Ljava/lang/Object;>;
SourceFile: "StepperExtensions.scala"
  ScalaInlineInfo: length = 0xA9 (unknown attribute)
   01 00 00 21 00 4A 00 C4 00 00 1E 00 1F 00 00 22
   00 1F 00 00 36 00 37 00 00 39 00 37 00 00 3C 00
   3D 00 00 3F 00 3D 00 00 55 00 56 00 00 68 00 69
   00 00 6B 00 69 00 00 73 00 74 00 00 76 00 74 00
   00 7E 00 7F 00 00 81 00 7F 00 00 5A 00 56 00 00
   88 00 89 00 00 95 00 96 00 00 98 00 96 00 00 9F
   00 A0 00 00 A2 00 A0 00 00 A9 00 AA 00 00 AC 00
   AA 00 00 8B 00 89 00 00 AF 00 B0 00 00 B3 00 B0
   00 00 BA 00 BB 00 00 BA 00 C1 00 00 BD 00 BB 00
   00 10 00 0A 00 00 07 00 0A 00 00 C0 00 27 00 00
   13 00 0A 00 00 14 00 0A 00
  Scala: length = 0x0 (unknown attribute)

