Classfile /Users/mw/Projects/slang-braindump/.jar/jar11/assemble/slang-braindump/assemble/content/coursier/cache/CacheUrl$Args$.class
  Last modified May 29, 2022; size 5780 bytes
  SHA-256 checksum 9f269769b9716571783aec5f0e3ef708b87c10ee2d2f6311c55282519e7074cc
  Compiled from "CacheUrl.scala"
public class coursier.cache.CacheUrl$Args$ extends scala.runtime.AbstractFunction15<java.lang.String, java.lang.String, scala.Option<coursier.core.Authentication>, java.lang.Object, java.lang.Object, java.lang.Object, scala.collection.immutable.Seq<coursier.credentials.DirectCredentials>, scala.Option<javax.net.ssl.SSLSocketFactory>, scala.Option<javax.net.ssl.HostnameVerifier>, scala.Option<java.net.Proxy>, java.lang.String, scala.Option<java.lang.String>, java.lang.Object, scala.Option<java.lang.Object>, scala.collection.immutable.Seq<java.lang.ClassLoader>, coursier.cache.CacheUrl$Args> implements java.io.Serializable
  minor version: 0
  major version: 52
  flags: (0x0021) ACC_PUBLIC, ACC_SUPER
  this_class: #2                          // coursier/cache/CacheUrl$Args$
  super_class: #5                         // scala/runtime/AbstractFunction15
  interfaces: 1, fields: 1, methods: 7, attributes: 5
Constant pool:
    #1 = Utf8               coursier/cache/CacheUrl$Args$
    #2 = Class              #1            // coursier/cache/CacheUrl$Args$
    #3 = Utf8               Lscala/runtime/AbstractFunction15<Ljava/lang/String;Ljava/lang/String;Lscala/Option<Lcoursier/core/Authentication;>;Ljava/lang/Object;Ljava/lang/Object;Ljava/lang/Object;Lscala/collection/immutable/Seq<Lcoursier/credentials/DirectCredentials;>;Lscala/Option<Ljavax/net/ssl/SSLSocketFactory;>;Lscala/Option<Ljavax/net/ssl/HostnameVerifier;>;Lscala/Option<Ljava/net/Proxy;>;Ljava/lang/String;Lscala/Option<Ljava/lang/String;>;Ljava/lang/Object;Lscala/Option<Ljava/lang/Object;>;Lscala/collection/immutable/Seq<Ljava/lang/ClassLoader;>;Lcoursier/cache/CacheUrl$Args;>;Ljava/io/Serializable;
    #4 = Utf8               scala/runtime/AbstractFunction15
    #5 = Class              #4            // scala/runtime/AbstractFunction15
    #6 = Utf8               java/io/Serializable
    #7 = Class              #6            // java/io/Serializable
    #8 = Utf8               CacheUrl.scala
    #9 = Utf8               coursier/cache/CacheUrl$Args
   #10 = Class              #9            // coursier/cache/CacheUrl$Args
   #11 = Utf8               coursier/cache/CacheUrl
   #12 = Class              #11           // coursier/cache/CacheUrl
   #13 = Utf8               Args
   #14 = Utf8
   #15 = Utf8               MODULE$
   #16 = Utf8               Lcoursier/cache/CacheUrl$Args$;
   #17 = Utf8               <clinit>
   #18 = Utf8               ()V
   #19 = Utf8               <init>
   #20 = NameAndType        #19:#18       // "<init>":()V
   #21 = Methodref          #2.#20        // coursier/cache/CacheUrl$Args$."<init>":()V
   #22 = NameAndType        #15:#16       // MODULE$:Lcoursier/cache/CacheUrl$Args$;
   #23 = Fieldref           #2.#22        // coursier/cache/CacheUrl$Args$.MODULE$:Lcoursier/cache/CacheUrl$Args$;
   #24 = Utf8               toString
   #25 = Utf8               ()Ljava/lang/String;
   #26 = String             #13           // Args
   #27 = Utf8               this
   #28 = Utf8               apply
   #29 = Utf8               (Ljava/lang/String;Ljava/lang/String;Lscala/Option;JZZLscala/collection/immutable/Seq;Lscala/Option;Lscala/Option;Lscala/Option;Ljava/lang/String;Lscala/Option;ILscala/Option;Lscala/collection/immutable/Seq;)Lcoursier/cache/CacheUrl$Args;
   #30 = Utf8               (Ljava/lang/String;Ljava/lang/String;Lscala/Option<Lcoursier/core/Authentication;>;JZZLscala/collection/immutable/Seq<Lcoursier/credentials/DirectCredentials;>;Lscala/Option<Ljavax/net/ssl/SSLSocketFactory;>;Lscala/Option<Ljavax/net/ssl/HostnameVerifier;>;Lscala/Option<Ljava/net/Proxy;>;Ljava/lang/String;Lscala/Option<Ljava/lang/String;>;ILscala/Option<Ljava/lang/Object;>;Lscala/collection/immutable/Seq<Ljava/lang/ClassLoader;>;)Lcoursier/cache/CacheUrl$Args;
   #31 = Utf8               initialUrl
   #32 = Utf8               url0
   #33 = Utf8               authentication
   #34 = Utf8               alreadyDownloaded
   #35 = Utf8               followHttpToHttpsRedirections
   #36 = Utf8               followHttpsToHttpRedirections
   #37 = Utf8               autoCredentials
   #38 = Utf8               sslSocketFactoryOpt
   #39 = Utf8               hostnameVerifierOpt
   #40 = Utf8               proxyOpt
   #41 = Utf8               method
   #42 = Utf8               authRealm
   #43 = Utf8               redirectionCount
   #44 = Utf8               maxRedirectionsOpt
   #45 = Utf8               classLoaders
   #46 = Utf8               (Ljava/lang/String;Ljava/lang/String;Lscala/Option;JZZLscala/collection/immutable/Seq;Lscala/Option;Lscala/Option;Lscala/Option;Ljava/lang/String;Lscala/Option;ILscala/Option;Lscala/collection/immutable/Seq;)V
   #47 = NameAndType        #19:#46       // "<init>":(Ljava/lang/String;Ljava/lang/String;Lscala/Option;JZZLscala/collection/immutable/Seq;Lscala/Option;Lscala/Option;Lscala/Option;Ljava/lang/String;Lscala/Option;ILscala/Option;Lscala/collection/immutable/Seq;)V
   #48 = Methodref          #10.#47       // coursier/cache/CacheUrl$Args."<init>":(Ljava/lang/String;Ljava/lang/String;Lscala/Option;JZZLscala/collection/immutable/Seq;Lscala/Option;Lscala/Option;Lscala/Option;Ljava/lang/String;Lscala/Option;ILscala/Option;Lscala/collection/immutable/Seq;)V
   #49 = Utf8               Ljava/lang/String;
   #50 = Utf8               Lscala/Option;
   #51 = Utf8               J
   #52 = Utf8               Z
   #53 = Utf8               Lscala/collection/immutable/Seq;
   #54 = Utf8               I
   #55 = Utf8               unapply
   #56 = Utf8               (Lcoursier/cache/CacheUrl$Args;)Lscala/Option;
   #57 = Utf8               (Lcoursier/cache/CacheUrl$Args;)Lscala/Option<Lscala/Tuple15<Ljava/lang/String;Ljava/lang/String;Lscala/Option<Lcoursier/core/Authentication;>;Ljava/lang/Object;Ljava/lang/Object;Ljava/lang/Object;Lscala/collection/immutable/Seq<Lcoursier/credentials/DirectCredentials;>;Lscala/Option<Ljavax/net/ssl/SSLSocketFactory;>;Lscala/Option<Ljavax/net/ssl/HostnameVerifier;>;Lscala/Option<Ljava/net/Proxy;>;Ljava/lang/String;Lscala/Option<Ljava/lang/String;>;Ljava/lang/Object;Lscala/Option<Ljava/lang/Object;>;Lscala/collection/immutable/Seq<Ljava/lang/ClassLoader;>;>;>;
   #58 = Utf8               x$0
   #59 = Utf8               scala/None$
   #60 = Class              #59           // scala/None$
   #61 = Utf8               Lscala/None$;
   #62 = NameAndType        #15:#61       // MODULE$:Lscala/None$;
   #63 = Fieldref           #60.#62       // scala/None$.MODULE$:Lscala/None$;
   #64 = Utf8               scala/Some
   #65 = Class              #64           // scala/Some
   #66 = Utf8               scala/Tuple15
   #67 = Class              #66           // scala/Tuple15
   #68 = NameAndType        #31:#25       // initialUrl:()Ljava/lang/String;
   #69 = Methodref          #10.#68       // coursier/cache/CacheUrl$Args.initialUrl:()Ljava/lang/String;
   #70 = NameAndType        #32:#25       // url0:()Ljava/lang/String;
   #71 = Methodref          #10.#70       // coursier/cache/CacheUrl$Args.url0:()Ljava/lang/String;
   #72 = Utf8               ()Lscala/Option;
   #73 = NameAndType        #33:#72       // authentication:()Lscala/Option;
   #74 = Methodref          #10.#73       // coursier/cache/CacheUrl$Args.authentication:()Lscala/Option;
   #75 = Utf8               ()J
   #76 = NameAndType        #34:#75       // alreadyDownloaded:()J
   #77 = Methodref          #10.#76       // coursier/cache/CacheUrl$Args.alreadyDownloaded:()J
   #78 = Utf8               scala/runtime/BoxesRunTime
   #79 = Class              #78           // scala/runtime/BoxesRunTime
   #80 = Utf8               boxToLong
   #81 = Utf8               (J)Ljava/lang/Long;
   #82 = NameAndType        #80:#81       // boxToLong:(J)Ljava/lang/Long;
   #83 = Methodref          #79.#82       // scala/runtime/BoxesRunTime.boxToLong:(J)Ljava/lang/Long;
   #84 = Utf8               ()Z
   #85 = NameAndType        #35:#84       // followHttpToHttpsRedirections:()Z
   #86 = Methodref          #10.#85       // coursier/cache/CacheUrl$Args.followHttpToHttpsRedirections:()Z
   #87 = Utf8               boxToBoolean
   #88 = Utf8               (Z)Ljava/lang/Boolean;
   #89 = NameAndType        #87:#88       // boxToBoolean:(Z)Ljava/lang/Boolean;
   #90 = Methodref          #79.#89       // scala/runtime/BoxesRunTime.boxToBoolean:(Z)Ljava/lang/Boolean;
   #91 = NameAndType        #36:#84       // followHttpsToHttpRedirections:()Z
   #92 = Methodref          #10.#91       // coursier/cache/CacheUrl$Args.followHttpsToHttpRedirections:()Z
   #93 = Utf8               ()Lscala/collection/immutable/Seq;
   #94 = NameAndType        #37:#93       // autoCredentials:()Lscala/collection/immutable/Seq;
   #95 = Methodref          #10.#94       // coursier/cache/CacheUrl$Args.autoCredentials:()Lscala/collection/immutable/Seq;
   #96 = NameAndType        #38:#72       // sslSocketFactoryOpt:()Lscala/Option;
   #97 = Methodref          #10.#96       // coursier/cache/CacheUrl$Args.sslSocketFactoryOpt:()Lscala/Option;
   #98 = NameAndType        #39:#72       // hostnameVerifierOpt:()Lscala/Option;
   #99 = Methodref          #10.#98       // coursier/cache/CacheUrl$Args.hostnameVerifierOpt:()Lscala/Option;
  #100 = NameAndType        #40:#72       // proxyOpt:()Lscala/Option;
  #101 = Methodref          #10.#100      // coursier/cache/CacheUrl$Args.proxyOpt:()Lscala/Option;
  #102 = NameAndType        #41:#25       // method:()Ljava/lang/String;
  #103 = Methodref          #10.#102      // coursier/cache/CacheUrl$Args.method:()Ljava/lang/String;
  #104 = NameAndType        #42:#72       // authRealm:()Lscala/Option;
  #105 = Methodref          #10.#104      // coursier/cache/CacheUrl$Args.authRealm:()Lscala/Option;
  #106 = Utf8               ()I
  #107 = NameAndType        #43:#106      // redirectionCount:()I
  #108 = Methodref          #10.#107      // coursier/cache/CacheUrl$Args.redirectionCount:()I
  #109 = Utf8               boxToInteger
  #110 = Utf8               (I)Ljava/lang/Integer;
  #111 = NameAndType        #109:#110     // boxToInteger:(I)Ljava/lang/Integer;
  #112 = Methodref          #79.#111      // scala/runtime/BoxesRunTime.boxToInteger:(I)Ljava/lang/Integer;
  #113 = NameAndType        #44:#72       // maxRedirectionsOpt:()Lscala/Option;
  #114 = Methodref          #10.#113      // coursier/cache/CacheUrl$Args.maxRedirectionsOpt:()Lscala/Option;
  #115 = NameAndType        #45:#93       // classLoaders:()Lscala/collection/immutable/Seq;
  #116 = Methodref          #10.#115      // coursier/cache/CacheUrl$Args.classLoaders:()Lscala/collection/immutable/Seq;
  #117 = Utf8               (Ljava/lang/Object;Ljava/lang/Object;Ljava/lang/Object;Ljava/lang/Object;Ljava/lang/Object;Ljava/lang/Object;Ljava/lang/Object;Ljava/lang/Object;Ljava/lang/Object;Ljava/lang/Object;Ljava/lang/Object;Ljava/lang/Object;Ljava/lang/Object;Ljava/lang/Object;Ljava/lang/Object;)V
  #118 = NameAndType        #19:#117      // "<init>":(Ljava/lang/Object;Ljava/lang/Object;Ljava/lang/Object;Ljava/lang/Object;Ljava/lang/Object;Ljava/lang/Object;Ljava/lang/Object;Ljava/lang/Object;Ljava/lang/Object;Ljava/lang/Object;Ljava/lang/Object;Ljava/lang/Object;Ljava/lang/Object;Ljava/lang/Object;Ljava/lang/Object;)V
  #119 = Methodref          #67.#118      // scala/Tuple15."<init>":(Ljava/lang/Object;Ljava/lang/Object;Ljava/lang/Object;Ljava/lang/Object;Ljava/lang/Object;Ljava/lang/Object;Ljava/lang/Object;Ljava/lang/Object;Ljava/lang/Object;Ljava/lang/Object;Ljava/lang/Object;Ljava/lang/Object;Ljava/lang/Object;Ljava/lang/Object;Ljava/lang/Object;)V
  #120 = Utf8               (Ljava/lang/Object;)V
  #121 = NameAndType        #19:#120      // "<init>":(Ljava/lang/Object;)V
  #122 = Methodref          #65.#121      // scala/Some."<init>":(Ljava/lang/Object;)V
  #123 = Utf8               scala/Option
  #124 = Class              #123          // scala/Option
  #125 = Utf8               Lcoursier/cache/CacheUrl$Args;
  #126 = Utf8               writeReplace
  #127 = Utf8               ()Ljava/lang/Object;
  #128 = Utf8               scala/runtime/ModuleSerializationProxy
  #129 = Class              #128          // scala/runtime/ModuleSerializationProxy
  #130 = Utf8               (Ljava/lang/Class;)V
  #131 = NameAndType        #19:#130      // "<init>":(Ljava/lang/Class;)V
  #132 = Methodref          #129.#131     // scala/runtime/ModuleSerializationProxy."<init>":(Ljava/lang/Class;)V
  #133 = Utf8               (Ljava/lang/Object;Ljava/lang/Object;Ljava/lang/Object;Ljava/lang/Object;Ljava/lang/Object;Ljava/lang/Object;Ljava/lang/Object;Ljava/lang/Object;Ljava/lang/Object;Ljava/lang/Object;Ljava/lang/Object;Ljava/lang/Object;Ljava/lang/Object;Ljava/lang/Object;Ljava/lang/Object;)Ljava/lang/Object;
  #134 = Utf8               v1
  #135 = Utf8               v2
  #136 = Utf8               v3
  #137 = Utf8               v4
  #138 = Utf8               v5
  #139 = Utf8               v6
  #140 = Utf8               v7
  #141 = Utf8               v8
  #142 = Utf8               v9
  #143 = Utf8               v10
  #144 = Utf8               v11
  #145 = Utf8               v12
  #146 = Utf8               v13
  #147 = Utf8               v14
  #148 = Utf8               v15
  #149 = Utf8               java/lang/String
  #150 = Class              #149          // java/lang/String
  #151 = Utf8               unboxToLong
  #152 = Utf8               (Ljava/lang/Object;)J
  #153 = NameAndType        #151:#152     // unboxToLong:(Ljava/lang/Object;)J
  #154 = Methodref          #79.#153      // scala/runtime/BoxesRunTime.unboxToLong:(Ljava/lang/Object;)J
  #155 = Utf8               unboxToBoolean
  #156 = Utf8               (Ljava/lang/Object;)Z
  #157 = NameAndType        #155:#156     // unboxToBoolean:(Ljava/lang/Object;)Z
  #158 = Methodref          #79.#157      // scala/runtime/BoxesRunTime.unboxToBoolean:(Ljava/lang/Object;)Z
  #159 = Utf8               scala/collection/immutable/Seq
  #160 = Class              #159          // scala/collection/immutable/Seq
  #161 = Utf8               unboxToInt
  #162 = Utf8               (Ljava/lang/Object;)I
  #163 = NameAndType        #161:#162     // unboxToInt:(Ljava/lang/Object;)I
  #164 = Methodref          #79.#163      // scala/runtime/BoxesRunTime.unboxToInt:(Ljava/lang/Object;)I
  #165 = NameAndType        #28:#29       // apply:(Ljava/lang/String;Ljava/lang/String;Lscala/Option;JZZLscala/collection/immutable/Seq;Lscala/Option;Lscala/Option;Lscala/Option;Ljava/lang/String;Lscala/Option;ILscala/Option;Lscala/collection/immutable/Seq;)Lcoursier/cache/CacheUrl$Args;
  #166 = Methodref          #2.#165       // coursier/cache/CacheUrl$Args$.apply:(Ljava/lang/String;Ljava/lang/String;Lscala/Option;JZZLscala/collection/immutable/Seq;Lscala/Option;Lscala/Option;Lscala/Option;Ljava/lang/String;Lscala/Option;ILscala/Option;Lscala/collection/immutable/Seq;)Lcoursier/cache/CacheUrl$Args;
  #167 = Utf8               Ljava/lang/Object;
  #168 = Methodref          #5.#20        // scala/runtime/AbstractFunction15."<init>":()V
  #169 = Utf8               Code
  #170 = Utf8               LineNumberTable
  #171 = Utf8               LocalVariableTable
  #172 = Utf8               Signature
  #173 = Utf8               MethodParameters
  #174 = Utf8               StackMapTable
  #175 = Utf8               InnerClasses
  #176 = Utf8               SourceFile
  #177 = Utf8               ScalaInlineInfo
  #178 = Utf8               Scala
{
  public static final coursier.cache.CacheUrl$Args$ MODULE$;
    descriptor: Lcoursier/cache/CacheUrl$Args$;
    flags: (0x0019) ACC_PUBLIC, ACC_STATIC, ACC_FINAL

  public static {};
    descriptor: ()V
    flags: (0x0009) ACC_PUBLIC, ACC_STATIC
    Code:
      stack=2, locals=0, args_size=0
         0: new           #2                  // class coursier/cache/CacheUrl$Args$
         3: dup
         4: invokespecial #21                 // Method "<init>":()V
         7: putstatic     #23                 // Field MODULE$:Lcoursier/cache/CacheUrl$Args$;
        10: return
      LineNumberTable:
        line 252: 0

  public final java.lang.String toString();
    descriptor: ()Ljava/lang/String;
    flags: (0x0011) ACC_PUBLIC, ACC_FINAL
    Code:
      stack=1, locals=1, args_size=1
         0: ldc           #26                 // String Args
         2: areturn
      LineNumberTable:
        line 252: 0
      LocalVariableTable:
        Start  Length  Slot  Name   Signature
            0       3     0  this   Lcoursier/cache/CacheUrl$Args$;

  public coursier.cache.CacheUrl$Args apply(java.lang.String, java.lang.String, scala.Option<coursier.core.Authentication>, long, boolean, boolean, scala.collection.immutable.Seq<coursier.credentials.DirectCredentials>, scala.Option<javax.net.ssl.SSLSocketFactory>, scala.Option<javax.net.ssl.HostnameVerifier>, scala.Option<java.net.Proxy>, java.lang.String, scala.Option<java.lang.String>, int, scala.Option<java.lang.Object>, scala.collection.immutable.Seq<java.lang.ClassLoader>);
    descriptor: (Ljava/lang/String;Ljava/lang/String;Lscala/Option;JZZLscala/collection/immutable/Seq;Lscala/Option;Lscala/Option;Lscala/Option;Ljava/lang/String;Lscala/Option;ILscala/Option;Lscala/collection/immutable/Seq;)Lcoursier/cache/CacheUrl$Args;
    flags: (0x0001) ACC_PUBLIC
    Code:
      stack=18, locals=17, args_size=16
         0: new           #10                 // class coursier/cache/CacheUrl$Args
         3: dup
         4: aload_1
         5: aload_2
         6: aload_3
         7: lload         4
         9: iload         6
        11: iload         7
        13: aload         8
        15: aload         9
        17: aload         10
        19: aload         11
        21: aload         12
        23: aload         13
        25: iload         14
        27: aload         15
        29: aload         16
        31: invokespecial #48                 // Method coursier/cache/CacheUrl$Args."<init>":(Ljava/lang/String;Ljava/lang/String;Lscala/Option;JZZLscala/collection/immutable/Seq;Lscala/Option;Lscala/Option;Lscala/Option;Ljava/lang/String;Lscala/Option;ILscala/Option;Lscala/collection/immutable/Seq;)V
        34: areturn
      LineNumberTable:
        line 252: 0
      LocalVariableTable:
        Start  Length  Slot  Name   Signature
            0      35     0  this   Lcoursier/cache/CacheUrl$Args$;
            0      35     1 initialUrl   Ljava/lang/String;
            0      35     2  url0   Ljava/lang/String;
            0      35     3 authentication   Lscala/Option;
            0      35     4 alreadyDownloaded   J
            0      35     6 followHttpToHttpsRedirections   Z
            0      35     7 followHttpsToHttpRedirections   Z
            0      35     8 autoCredentials   Lscala/collection/immutable/Seq;
            0      35     9 sslSocketFactoryOpt   Lscala/Option;
            0      35    10 hostnameVerifierOpt   Lscala/Option;
            0      35    11 proxyOpt   Lscala/Option;
            0      35    12 method   Ljava/lang/String;
            0      35    13 authRealm   Lscala/Option;
            0      35    14 redirectionCount   I
            0      35    15 maxRedirectionsOpt   Lscala/Option;
            0      35    16 classLoaders   Lscala/collection/immutable/Seq;
    Signature: #30                          // (Ljava/lang/String;Ljava/lang/String;Lscala/Option<Lcoursier/core/Authentication;>;JZZLscala/collection/immutable/Seq<Lcoursier/credentials/DirectCredentials;>;Lscala/Option<Ljavax/net/ssl/SSLSocketFactory;>;Lscala/Option<Ljavax/net/ssl/HostnameVerifier;>;Lscala/Option<Ljava/net/Proxy;>;Ljava/lang/String;Lscala/Option<Ljava/lang/String;>;ILscala/Option<Ljava/lang/Object;>;Lscala/collection/immutable/Seq<Ljava/lang/ClassLoader;>;)Lcoursier/cache/CacheUrl$Args;
    MethodParameters:
      Name                           Flags
      initialUrl                     final
      url0                           final
      authentication                 final
      alreadyDownloaded              final
      followHttpToHttpsRedirections  final
      followHttpsToHttpRedirections  final
      autoCredentials                final
      sslSocketFactoryOpt            final
      hostnameVerifierOpt            final
      proxyOpt                       final
      method                         final
      authRealm                      final
      redirectionCount               final
      maxRedirectionsOpt             final
      classLoaders                   final

  public scala.Option<scala.Tuple15<java.lang.String, java.lang.String, scala.Option<coursier.core.Authentication>, java.lang.Object, java.lang.Object, java.lang.Object, scala.collection.immutable.Seq<coursier.credentials.DirectCredentials>, scala.Option<javax.net.ssl.SSLSocketFactory>, scala.Option<javax.net.ssl.HostnameVerifier>, scala.Option<java.net.Proxy>, java.lang.String, scala.Option<java.lang.String>, java.lang.Object, scala.Option<java.lang.Object>, scala.collection.immutable.Seq<java.lang.ClassLoader>>> unapply(coursier.cache.CacheUrl$Args);
    descriptor: (Lcoursier/cache/CacheUrl$Args;)Lscala/Option;
    flags: (0x0001) ACC_PUBLIC
    Code:
      stack=19, locals=2, args_size=2
         0: aload_1
         1: ifnonnull     10
         4: getstatic     #63                 // Field scala/None$.MODULE$:Lscala/None$;
         7: goto          96
        10: new           #65                 // class scala/Some
        13: dup
        14: new           #67                 // class scala/Tuple15
        17: dup
        18: aload_1
        19: invokevirtual #69                 // Method coursier/cache/CacheUrl$Args.initialUrl:()Ljava/lang/String;
        22: aload_1
        23: invokevirtual #71                 // Method coursier/cache/CacheUrl$Args.url0:()Ljava/lang/String;
        26: aload_1
        27: invokevirtual #74                 // Method coursier/cache/CacheUrl$Args.authentication:()Lscala/Option;
        30: aload_1
        31: invokevirtual #77                 // Method coursier/cache/CacheUrl$Args.alreadyDownloaded:()J
        34: invokestatic  #83                 // Method scala/runtime/BoxesRunTime.boxToLong:(J)Ljava/lang/Long;
        37: aload_1
        38: invokevirtual #86                 // Method coursier/cache/CacheUrl$Args.followHttpToHttpsRedirections:()Z
        41: invokestatic  #90                 // Method scala/runtime/BoxesRunTime.boxToBoolean:(Z)Ljava/lang/Boolean;
        44: aload_1
        45: invokevirtual #92                 // Method coursier/cache/CacheUrl$Args.followHttpsToHttpRedirections:()Z
        48: invokestatic  #90                 // Method scala/runtime/BoxesRunTime.boxToBoolean:(Z)Ljava/lang/Boolean;
        51: aload_1
        52: invokevirtual #95                 // Method coursier/cache/CacheUrl$Args.autoCredentials:()Lscala/collection/immutable/Seq;
        55: aload_1
        56: invokevirtual #97                 // Method coursier/cache/CacheUrl$Args.sslSocketFactoryOpt:()Lscala/Option;
        59: aload_1
        60: invokevirtual #99                 // Method coursier/cache/CacheUrl$Args.hostnameVerifierOpt:()Lscala/Option;
        63: aload_1
        64: invokevirtual #101                // Method coursier/cache/CacheUrl$Args.proxyOpt:()Lscala/Option;
        67: aload_1
        68: invokevirtual #103                // Method coursier/cache/CacheUrl$Args.method:()Ljava/lang/String;
        71: aload_1
        72: invokevirtual #105                // Method coursier/cache/CacheUrl$Args.authRealm:()Lscala/Option;
        75: aload_1
        76: invokevirtual #108                // Method coursier/cache/CacheUrl$Args.redirectionCount:()I
        79: invokestatic  #112                // Method scala/runtime/BoxesRunTime.boxToInteger:(I)Ljava/lang/Integer;
        82: aload_1
        83: invokevirtual #114                // Method coursier/cache/CacheUrl$Args.maxRedirectionsOpt:()Lscala/Option;
        86: aload_1
        87: invokevirtual #116                // Method coursier/cache/CacheUrl$Args.classLoaders:()Lscala/collection/immutable/Seq;
        90: invokespecial #119                // Method scala/Tuple15."<init>":(Ljava/lang/Object;Ljava/lang/Object;Ljava/lang/Object;Ljava/lang/Object;Ljava/lang/Object;Ljava/lang/Object;Ljava/lang/Object;Ljava/lang/Object;Ljava/lang/Object;Ljava/lang/Object;Ljava/lang/Object;Ljava/lang/Object;Ljava/lang/Object;Ljava/lang/Object;Ljava/lang/Object;)V
        93: invokespecial #122                // Method scala/Some."<init>":(Ljava/lang/Object;)V
        96: areturn
      StackMapTable: number_of_entries = 2
        frame_type = 10 /* same */
        frame_type = 247 /* same_locals_1_stack_item_frame_extended */
          offset_delta = 85
          stack = [ class scala/Option ]
      LineNumberTable:
        line 252: 0
      LocalVariableTable:
        Start  Length  Slot  Name   Signature
            0      97     0  this   Lcoursier/cache/CacheUrl$Args$;
            0      97     1   x$0   Lcoursier/cache/CacheUrl$Args;
    Signature: #57                          // (Lcoursier/cache/CacheUrl$Args;)Lscala/Option<Lscala/Tuple15<Ljava/lang/String;Ljava/lang/String;Lscala/Option<Lcoursier/core/Authentication;>;Ljava/lang/Object;Ljava/lang/Object;Ljava/lang/Object;Lscala/collection/immutable/Seq<Lcoursier/credentials/DirectCredentials;>;Lscala/Option<Ljavax/net/ssl/SSLSocketFactory;>;Lscala/Option<Ljavax/net/ssl/HostnameVerifier;>;Lscala/Option<Ljava/net/Proxy;>;Ljava/lang/String;Lscala/Option<Ljava/lang/String;>;Ljava/lang/Object;Lscala/Option<Ljava/lang/Object;>;Lscala/collection/immutable/Seq<Ljava/lang/ClassLoader;>;>;>;
    MethodParameters:
      Name                           Flags
      x$0                            final

  private java.lang.Object writeReplace();
    descriptor: ()Ljava/lang/Object;
    flags: (0x0002) ACC_PRIVATE
    Code:
      stack=3, locals=1, args_size=1
         0: new           #129                // class scala/runtime/ModuleSerializationProxy
         3: dup
         4: ldc           #2                  // class coursier/cache/CacheUrl$Args$
         6: invokespecial #132                // Method scala/runtime/ModuleSerializationProxy."<init>":(Ljava/lang/Class;)V
         9: areturn
      LineNumberTable:
        line 252: 0
      LocalVariableTable:
        Start  Length  Slot  Name   Signature
            0      10     0  this   Lcoursier/cache/CacheUrl$Args$;

  public java.lang.Object apply(java.lang.Object, java.lang.Object, java.lang.Object, java.lang.Object, java.lang.Object, java.lang.Object, java.lang.Object, java.lang.Object, java.lang.Object, java.lang.Object, java.lang.Object, java.lang.Object, java.lang.Object, java.lang.Object, java.lang.Object);
    descriptor: (Ljava/lang/Object;Ljava/lang/Object;Ljava/lang/Object;Ljava/lang/Object;Ljava/lang/Object;Ljava/lang/Object;Ljava/lang/Object;Ljava/lang/Object;Ljava/lang/Object;Ljava/lang/Object;Ljava/lang/Object;Ljava/lang/Object;Ljava/lang/Object;Ljava/lang/Object;Ljava/lang/Object;)Ljava/lang/Object;
    flags: (0x1041) ACC_PUBLIC, ACC_BRIDGE, ACC_SYNTHETIC
    Code:
      stack=17, locals=16, args_size=16
         0: aload_0
         1: aload_1
         2: checkcast     #150                // class java/lang/String
         5: aload_2
         6: checkcast     #150                // class java/lang/String
         9: aload_3
        10: checkcast     #124                // class scala/Option
        13: aload         4
        15: invokestatic  #154                // Method scala/runtime/BoxesRunTime.unboxToLong:(Ljava/lang/Object;)J
        18: aload         5
        20: invokestatic  #158                // Method scala/runtime/BoxesRunTime.unboxToBoolean:(Ljava/lang/Object;)Z
        23: aload         6
        25: invokestatic  #158                // Method scala/runtime/BoxesRunTime.unboxToBoolean:(Ljava/lang/Object;)Z
        28: aload         7
        30: checkcast     #160                // class scala/collection/immutable/Seq
        33: aload         8
        35: checkcast     #124                // class scala/Option
        38: aload         9
        40: checkcast     #124                // class scala/Option
        43: aload         10
        45: checkcast     #124                // class scala/Option
        48: aload         11
        50: checkcast     #150                // class java/lang/String
        53: aload         12
        55: checkcast     #124                // class scala/Option
        58: aload         13
        60: invokestatic  #164                // Method scala/runtime/BoxesRunTime.unboxToInt:(Ljava/lang/Object;)I
        63: aload         14
        65: checkcast     #124                // class scala/Option
        68: aload         15
        70: checkcast     #160                // class scala/collection/immutable/Seq
        73: invokevirtual #166                // Method apply:(Ljava/lang/String;Ljava/lang/String;Lscala/Option;JZZLscala/collection/immutable/Seq;Lscala/Option;Lscala/Option;Lscala/Option;Ljava/lang/String;Lscala/Option;ILscala/Option;Lscala/collection/immutable/Seq;)Lcoursier/cache/CacheUrl$Args;
        76: areturn
      LineNumberTable:
        line 252: 0
      LocalVariableTable:
        Start  Length  Slot  Name   Signature
            0      77     0  this   Lcoursier/cache/CacheUrl$Args$;
            0      77     1    v1   Ljava/lang/Object;
            0      77     2    v2   Ljava/lang/Object;
            0      77     3    v3   Ljava/lang/Object;
            0      77     4    v4   Ljava/lang/Object;
            0      77     5    v5   Ljava/lang/Object;
            0      77     6    v6   Ljava/lang/Object;
            0      77     7    v7   Ljava/lang/Object;
            0      77     8    v8   Ljava/lang/Object;
            0      77     9    v9   Ljava/lang/Object;
            0      77    10   v10   Ljava/lang/Object;
            0      77    11   v11   Ljava/lang/Object;
            0      77    12   v12   Ljava/lang/Object;
            0      77    13   v13   Ljava/lang/Object;
            0      77    14   v14   Ljava/lang/Object;
            0      77    15   v15   Ljava/lang/Object;
    MethodParameters:
      Name                           Flags
      v1                             final
      v2                             final
      v3                             final
      v4                             final
      v5                             final
      v6                             final
      v7                             final
      v8                             final
      v9                             final
      v10                            final
      v11                            final
      v12                            final
      v13                            final
      v14                            final
      v15                            final

  public coursier.cache.CacheUrl$Args$();
    descriptor: ()V
    flags: (0x0001) ACC_PUBLIC
    Code:
      stack=1, locals=1, args_size=1
         0: aload_0
         1: invokespecial #168                // Method scala/runtime/AbstractFunction15."<init>":()V
         4: return
      LineNumberTable:
        line 252: 0
      LocalVariableTable:
        Start  Length  Slot  Name   Signature
            0       5     0  this   Lcoursier/cache/CacheUrl$Args$;
}
InnerClasses:
  public static final #13= #10 of #12;    // Args=class coursier/cache/CacheUrl$Args of class coursier/cache/CacheUrl
  public static #14= #2 of #12;           // =class coursier/cache/CacheUrl$Args$ of class coursier/cache/CacheUrl
Signature: #3                           // Lscala/runtime/AbstractFunction15<Ljava/lang/String;Ljava/lang/String;Lscala/Option<Lcoursier/core/Authentication;>;Ljava/lang/Object;Ljava/lang/Object;Ljava/lang/Object;Lscala/collection/immutable/Seq<Lcoursier/credentials/DirectCredentials;>;Lscala/Option<Ljavax/net/ssl/SSLSocketFactory;>;Lscala/Option<Ljavax/net/ssl/HostnameVerifier;>;Lscala/Option<Ljava/net/Proxy;>;Ljava/lang/String;Lscala/Option<Ljava/lang/String;>;Ljava/lang/Object;Lscala/Option<Ljava/lang/Object;>;Lscala/collection/immutable/Seq<Ljava/lang/ClassLoader;>;Lcoursier/cache/CacheUrl$Args;>;Ljava/io/Serializable;
SourceFile: "CacheUrl.scala"
  ScalaInlineInfo: length = 0x22 (unknown attribute)
   01 01 00 06 00 13 00 12 01 00 1C 00 85 01 00 1C
   00 1D 01 00 18 00 19 01 00 37 00 38 01 00 7E 00
   7F 01
  Scala: length = 0x0 (unknown attribute)

