Classfile /Users/mw/Projects/slang-braindump/.jar/jar11/assemble/slang-braindump/assemble/content/coursier/cache/CacheUrl$BasicRealm$.class
  Last modified May 29, 2022; size 4222 bytes
  SHA-256 checksum cdf1844d40885a64deb73dd93c41b9ba29a2b1679f53f7e582a780a1e9ea2238
  Compiled from "CacheUrl.scala"
public class coursier.cache.CacheUrl$BasicRealm$
  minor version: 0
  major version: 52
  flags: (0x0021) ACC_PUBLIC, ACC_SUPER
  this_class: #2                          // coursier/cache/CacheUrl$BasicRealm$
  super_class: #4                         // java/lang/Object
  interfaces: 0, fields: 3, methods: 7, attributes: 5
Constant pool:
    #1 = Utf8               coursier/cache/CacheUrl$BasicRealm$
    #2 = Class              #1            // coursier/cache/CacheUrl$BasicRealm$
    #3 = Utf8               java/lang/Object
    #4 = Class              #3            // java/lang/Object
    #5 = Utf8               CacheUrl.scala
    #6 = Utf8               coursier/cache/CacheUrl
    #7 = Class              #6            // coursier/cache/CacheUrl
    #8 = Utf8
    #9 = Utf8               coursier/cache/CacheUrl$BasicRealm$$anonfun$unapply$2
   #10 = Class              #9            // coursier/cache/CacheUrl$BasicRealm$$anonfun$unapply$2
   #11 = Utf8               java/lang/invoke/MethodHandles$Lookup
   #12 = Class              #11           // java/lang/invoke/MethodHandles$Lookup
   #13 = Utf8               java/lang/invoke/MethodHandles
   #14 = Class              #13           // java/lang/invoke/MethodHandles
   #15 = Utf8               Lookup
   #16 = Utf8               scala/Predef$ArrowAssoc$
   #17 = Class              #16           // scala/Predef$ArrowAssoc$
   #18 = Utf8               scala/Predef
   #19 = Class              #18           // scala/Predef
   #20 = Utf8               scala/util/matching/Regex$Match
   #21 = Class              #20           // scala/util/matching/Regex$Match
   #22 = Utf8               scala/util/matching/Regex
   #23 = Class              #22           // scala/util/matching/Regex
   #24 = Utf8               Match
   #25 = Utf8               MODULE$
   #26 = Utf8               Lcoursier/cache/CacheUrl$BasicRealm$;
   #27 = Utf8               BasicAuthBase
   #28 = Utf8               Lscala/util/matching/Regex;
   #29 = Utf8               Param
   #30 = Utf8               <clinit>
   #31 = Utf8               ()V
   #32 = Utf8               <init>
   #33 = NameAndType        #32:#31       // "<init>":()V
   #34 = Methodref          #2.#33        // coursier/cache/CacheUrl$BasicRealm$."<init>":()V
   #35 = NameAndType        #25:#26       // MODULE$:Lcoursier/cache/CacheUrl$BasicRealm$;
   #36 = Fieldref           #2.#35        // coursier/cache/CacheUrl$BasicRealm$.MODULE$:Lcoursier/cache/CacheUrl$BasicRealm$;
   #37 = Utf8               scala/collection/StringOps$
   #38 = Class              #37           // scala/collection/StringOps$
   #39 = Utf8               Lscala/collection/StringOps$;
   #40 = NameAndType        #25:#39       // MODULE$:Lscala/collection/StringOps$;
   #41 = Fieldref           #38.#40       // scala/collection/StringOps$.MODULE$:Lscala/collection/StringOps$;
   #42 = Utf8               scala/Predef$
   #43 = Class              #42           // scala/Predef$
   #44 = Utf8               Lscala/Predef$;
   #45 = NameAndType        #25:#44       // MODULE$:Lscala/Predef$;
   #46 = Fieldref           #43.#45       // scala/Predef$.MODULE$:Lscala/Predef$;
   #47 = Utf8               java/lang/StringBuilder
   #48 = Class              #47           // java/lang/StringBuilder
   #49 = Integer            12
   #50 = Utf8               (I)V
   #51 = NameAndType        #32:#50       // "<init>":(I)V
   #52 = Methodref          #48.#51       // java/lang/StringBuilder."<init>":(I)V
   #53 = Utf8               (?i)^
   #54 = String             #53           // (?i)^
   #55 = Utf8               append
   #56 = Utf8               (Ljava/lang/String;)Ljava/lang/StringBuilder;
   #57 = NameAndType        #55:#56       // append:(Ljava/lang/String;)Ljava/lang/StringBuilder;
   #58 = Methodref          #48.#57       // java/lang/StringBuilder.append:(Ljava/lang/String;)Ljava/lang/StringBuilder;
   #59 = Utf8               Basic
   #60 = String             #59           // Basic
   #61 = Utf8               java/util/regex/Pattern
   #62 = Class              #61           // java/util/regex/Pattern
   #63 = Utf8               quote
   #64 = Utf8               (Ljava/lang/String;)Ljava/lang/String;
   #65 = NameAndType        #63:#64       // quote:(Ljava/lang/String;)Ljava/lang/String;
   #66 = Methodref          #62.#65       // java/util/regex/Pattern.quote:(Ljava/lang/String;)Ljava/lang/String;
   #67 = Utf8                +(.*)
   #68 = String             #67           //  +(.*)
   #69 = Utf8               $
   #70 = String             #69           // $
   #71 = Utf8               toString
   #72 = Utf8               ()Ljava/lang/String;
   #73 = NameAndType        #71:#72       // toString:()Ljava/lang/String;
   #74 = Methodref          #48.#73       // java/lang/StringBuilder.toString:()Ljava/lang/String;
   #75 = Utf8               augmentString
   #76 = NameAndType        #75:#64       // augmentString:(Ljava/lang/String;)Ljava/lang/String;
   #77 = Methodref          #43.#76       // scala/Predef$.augmentString:(Ljava/lang/String;)Ljava/lang/String;
   #78 = Utf8               r$extension
   #79 = Utf8               (Ljava/lang/String;)Lscala/util/matching/Regex;
   #80 = NameAndType        #78:#79       // r$extension:(Ljava/lang/String;)Lscala/util/matching/Regex;
   #81 = Methodref          #38.#80       // scala/collection/StringOps$.r$extension:(Ljava/lang/String;)Lscala/util/matching/Regex;
   #82 = NameAndType        #27:#28       // BasicAuthBase:Lscala/util/matching/Regex;
   #83 = Fieldref           #2.#82        // coursier/cache/CacheUrl$BasicRealm$.BasicAuthBase:Lscala/util/matching/Regex;
   #84 = Integer            25
   #85 = Utf8               \\s*(\\S+?)
   #86 = String             #85           // \\s*(\\S+?)
   #87 = Utf8               =\"
   #88 = String             #87           // =\"
   #89 = Utf8               ([^
   #90 = String             #89           // ([^
   #91 = Utf8               \"
   #92 = String             #91           // \"
   #93 = Utf8               ]*)
   #94 = String             #93           // ]*)
   #95 = Utf8               \\s*
   #96 = String             #95           // \\s*
   #97 = Utf8               (?:,|$)
   #98 = String             #97           // (?:,|$)
   #99 = NameAndType        #29:#28       // Param:Lscala/util/matching/Regex;
  #100 = Fieldref           #2.#99        // coursier/cache/CacheUrl$BasicRealm$.Param:Lscala/util/matching/Regex;
  #101 = Utf8               ()Lscala/util/matching/Regex;
  #102 = Utf8               this
  #103 = Utf8               unapply
  #104 = Utf8               (Ljava/lang/String;)Lscala/Option;
  #105 = Utf8               (Ljava/lang/String;)Lscala/Option<Ljava/lang/String;>;
  #106 = Utf8               wwwAuthenticate
  #107 = NameAndType        #27:#101      // BasicAuthBase:()Lscala/util/matching/Regex;
  #108 = Methodref          #2.#107       // coursier/cache/CacheUrl$BasicRealm$.BasicAuthBase:()Lscala/util/matching/Regex;
  #109 = Utf8               unapplySeq
  #110 = Utf8               (Ljava/lang/CharSequence;)Lscala/Option;
  #111 = NameAndType        #109:#110     // unapplySeq:(Ljava/lang/CharSequence;)Lscala/Option;
  #112 = Methodref          #23.#111      // scala/util/matching/Regex.unapplySeq:(Ljava/lang/CharSequence;)Lscala/Option;
  #113 = Utf8               scala/Option
  #114 = Class              #113          // scala/Option
  #115 = Utf8               isEmpty
  #116 = Utf8               ()Z
  #117 = NameAndType        #115:#116     // isEmpty:()Z
  #118 = Methodref          #114.#117     // scala/Option.isEmpty:()Z
  #119 = Utf8               get
  #120 = Utf8               ()Ljava/lang/Object;
  #121 = NameAndType        #119:#120     // get:()Ljava/lang/Object;
  #122 = Methodref          #114.#121     // scala/Option.get:()Ljava/lang/Object;
  #123 = Utf8               scala/collection/immutable/List
  #124 = Class              #123          // scala/collection/immutable/List
  #125 = Utf8               lengthCompare
  #126 = Utf8               (I)I
  #127 = NameAndType        #125:#126     // lengthCompare:(I)I
  #128 = Methodref          #124.#127     // scala/collection/immutable/List.lengthCompare:(I)I
  #129 = Utf8               scala/collection/LinearSeqOps
  #130 = Class              #129          // scala/collection/LinearSeqOps
  #131 = Utf8               apply
  #132 = Utf8               (I)Ljava/lang/Object;
  #133 = NameAndType        #131:#132     // apply:(I)Ljava/lang/Object;
  #134 = InterfaceMethodref #130.#133     // scala/collection/LinearSeqOps.apply:(I)Ljava/lang/Object;
  #135 = Utf8               java/lang/String
  #136 = Class              #135          // java/lang/String
  #137 = NameAndType        #29:#101      // Param:()Lscala/util/matching/Regex;
  #138 = Methodref          #2.#137       // coursier/cache/CacheUrl$BasicRealm$.Param:()Lscala/util/matching/Regex;
  #139 = Utf8               findAllMatchIn
  #140 = Utf8               (Ljava/lang/CharSequence;)Lscala/collection/Iterator;
  #141 = NameAndType        #139:#140     // findAllMatchIn:(Ljava/lang/CharSequence;)Lscala/collection/Iterator;
  #142 = Methodref          #23.#141      // scala/util/matching/Regex.findAllMatchIn:(Ljava/lang/CharSequence;)Lscala/collection/Iterator;
  #143 = Utf8               (Ljava/lang/Object;)Ljava/lang/Object;
  #144 = MethodType         #143          //  (Ljava/lang/Object;)Ljava/lang/Object;
  #145 = Utf8               $anonfun$unapply$1
  #146 = Utf8               (Lscala/util/matching/Regex$Match;)Lscala/Tuple2;
  #147 = NameAndType        #145:#146     // $anonfun$unapply$1:(Lscala/util/matching/Regex$Match;)Lscala/Tuple2;
  #148 = Methodref          #2.#147       // coursier/cache/CacheUrl$BasicRealm$.$anonfun$unapply$1:(Lscala/util/matching/Regex$Match;)Lscala/Tuple2;
  #149 = MethodHandle       6:#148        // REF_invokeStatic coursier/cache/CacheUrl$BasicRealm$.$anonfun$unapply$1:(Lscala/util/matching/Regex$Match;)Lscala/Tuple2;
  #150 = MethodType         #146          //  (Lscala/util/matching/Regex$Match;)Lscala/Tuple2;
  #151 = Integer            5
  #152 = Integer            1
  #153 = Utf8               java/lang/invoke/LambdaMetafactory
  #154 = Class              #153          // java/lang/invoke/LambdaMetafactory
  #155 = Utf8               altMetafactory
  #156 = Utf8               (Ljava/lang/invoke/MethodHandles$Lookup;Ljava/lang/String;Ljava/lang/invoke/MethodType;[Ljava/lang/Object;)Ljava/lang/invoke/CallSite;
  #157 = NameAndType        #155:#156     // altMetafactory:(Ljava/lang/invoke/MethodHandles$Lookup;Ljava/lang/String;Ljava/lang/invoke/MethodType;[Ljava/lang/Object;)Ljava/lang/invoke/CallSite;
  #158 = Methodref          #154.#157     // java/lang/invoke/LambdaMetafactory.altMetafactory:(Ljava/lang/invoke/MethodHandles$Lookup;Ljava/lang/String;Ljava/lang/invoke/MethodType;[Ljava/lang/Object;)Ljava/lang/invoke/CallSite;
  #159 = MethodHandle       6:#158        // REF_invokeStatic java/lang/invoke/LambdaMetafactory.altMetafactory:(Ljava/lang/invoke/MethodHandles$Lookup;Ljava/lang/String;Ljava/lang/invoke/MethodType;[Ljava/lang/Object;)Ljava/lang/invoke/CallSite;
  #160 = Utf8               ()Lscala/Function1;
  #161 = NameAndType        #131:#160     // apply:()Lscala/Function1;
  #162 = InvokeDynamic      #0:#161       // #0:apply:()Lscala/Function1;
  #163 = Utf8               scala/collection/Iterator
  #164 = Class              #163          // scala/collection/Iterator
  #165 = Utf8               map
  #166 = Utf8               (Lscala/Function1;)Lscala/collection/Iterator;
  #167 = NameAndType        #165:#166     // map:(Lscala/Function1;)Lscala/collection/Iterator;
  #168 = InterfaceMethodref #164.#167     // scala/collection/Iterator.map:(Lscala/Function1;)Lscala/collection/Iterator;
  #169 = Methodref          #10.#33       // coursier/cache/CacheUrl$BasicRealm$$anonfun$unapply$2."<init>":()V
  #170 = Utf8               collectFirst
  #171 = Utf8               (Lscala/PartialFunction;)Lscala/Option;
  #172 = NameAndType        #170:#171     // collectFirst:(Lscala/PartialFunction;)Lscala/Option;
  #173 = InterfaceMethodref #164.#172     // scala/collection/Iterator.collectFirst:(Lscala/PartialFunction;)Lscala/Option;
  #174 = Utf8               scala/None$
  #175 = Class              #174          // scala/None$
  #176 = Utf8               Lscala/None$;
  #177 = NameAndType        #25:#176      // MODULE$:Lscala/None$;
  #178 = Fieldref           #175.#177     // scala/None$.MODULE$:Lscala/None$;
  #179 = Utf8               basicAuthLine
  #180 = Utf8               Ljava/lang/String;
  #181 = Utf8               mobj
  #182 = Utf8               Lscala/Predef$ArrowAssoc$;
  #183 = NameAndType        #25:#182      // MODULE$:Lscala/Predef$ArrowAssoc$;
  #184 = Fieldref           #17.#183      // scala/Predef$ArrowAssoc$.MODULE$:Lscala/Predef$ArrowAssoc$;
  #185 = Utf8               group
  #186 = Utf8               (I)Ljava/lang/String;
  #187 = NameAndType        #185:#186     // group:(I)Ljava/lang/String;
  #188 = Methodref          #21.#187      // scala/util/matching/Regex$Match.group:(I)Ljava/lang/String;
  #189 = Utf8               java/util/Locale
  #190 = Class              #189          // java/util/Locale
  #191 = Utf8               ROOT
  #192 = Utf8               Ljava/util/Locale;
  #193 = NameAndType        #191:#192     // ROOT:Ljava/util/Locale;
  #194 = Fieldref           #190.#193     // java/util/Locale.ROOT:Ljava/util/Locale;
  #195 = Utf8               toLowerCase
  #196 = Utf8               (Ljava/util/Locale;)Ljava/lang/String;
  #197 = NameAndType        #195:#196     // toLowerCase:(Ljava/util/Locale;)Ljava/lang/String;
  #198 = Methodref          #136.#197     // java/lang/String.toLowerCase:(Ljava/util/Locale;)Ljava/lang/String;
  #199 = Utf8               ArrowAssoc
  #200 = NameAndType        #199:#143     // ArrowAssoc:(Ljava/lang/Object;)Ljava/lang/Object;
  #201 = Methodref          #43.#200      // scala/Predef$.ArrowAssoc:(Ljava/lang/Object;)Ljava/lang/Object;
  #202 = Utf8               $minus$greater$extension
  #203 = Utf8               (Ljava/lang/Object;Ljava/lang/Object;)Lscala/Tuple2;
  #204 = NameAndType        #202:#203     // $minus$greater$extension:(Ljava/lang/Object;Ljava/lang/Object;)Lscala/Tuple2;
  #205 = Methodref          #17.#204      // scala/Predef$ArrowAssoc$.$minus$greater$extension:(Ljava/lang/Object;Ljava/lang/Object;)Lscala/Tuple2;
  #206 = Utf8               Lscala/util/matching/Regex$Match;
  #207 = Methodref          #4.#33        // java/lang/Object."<init>":()V
  #208 = Utf8               $deserializeLambda$
  #209 = Utf8               (Ljava/lang/invoke/SerializedLambda;)Ljava/lang/Object;
  #210 = Utf8               scala/runtime/LambdaDeserialize
  #211 = Class              #210          // scala/runtime/LambdaDeserialize
  #212 = Utf8               bootstrap
  #213 = Utf8               (Ljava/lang/invoke/MethodHandles$Lookup;Ljava/lang/String;Ljava/lang/invoke/MethodType;[Ljava/lang/invoke/MethodHandle;)Ljava/lang/invoke/CallSite;
  #214 = NameAndType        #212:#213     // bootstrap:(Ljava/lang/invoke/MethodHandles$Lookup;Ljava/lang/String;Ljava/lang/invoke/MethodType;[Ljava/lang/invoke/MethodHandle;)Ljava/lang/invoke/CallSite;
  #215 = Methodref          #211.#214     // scala/runtime/LambdaDeserialize.bootstrap:(Ljava/lang/invoke/MethodHandles$Lookup;Ljava/lang/String;Ljava/lang/invoke/MethodType;[Ljava/lang/invoke/MethodHandle;)Ljava/lang/invoke/CallSite;
  #216 = MethodHandle       6:#215        // REF_invokeStatic scala/runtime/LambdaDeserialize.bootstrap:(Ljava/lang/invoke/MethodHandles$Lookup;Ljava/lang/String;Ljava/lang/invoke/MethodType;[Ljava/lang/invoke/MethodHandle;)Ljava/lang/invoke/CallSite;
  #217 = Utf8               lambdaDeserialize
  #218 = NameAndType        #217:#209     // lambdaDeserialize:(Ljava/lang/invoke/SerializedLambda;)Ljava/lang/Object;
  #219 = InvokeDynamic      #1:#218       // #1:lambdaDeserialize:(Ljava/lang/invoke/SerializedLambda;)Ljava/lang/Object;
  #220 = Utf8               Code
  #221 = Utf8               LineNumberTable
  #222 = Utf8               LocalVariableTable
  #223 = Utf8               StackMapTable
  #224 = Utf8               Signature
  #225 = Utf8               MethodParameters
  #226 = Utf8               InnerClasses
  #227 = Utf8               SourceFile
  #228 = Utf8               BootstrapMethods
  #229 = Utf8               ScalaInlineInfo
  #230 = Utf8               Scala
{
  public static final coursier.cache.CacheUrl$BasicRealm$ MODULE$;
    descriptor: Lcoursier/cache/CacheUrl$BasicRealm$;
    flags: (0x0019) ACC_PUBLIC, ACC_STATIC, ACC_FINAL

  private static final scala.util.matching.Regex BasicAuthBase;
    descriptor: Lscala/util/matching/Regex;
    flags: (0x001a) ACC_PRIVATE, ACC_STATIC, ACC_FINAL

  private static final scala.util.matching.Regex Param;
    descriptor: Lscala/util/matching/Regex;
    flags: (0x001a) ACC_PRIVATE, ACC_STATIC, ACC_FINAL

  public static {};
    descriptor: ()V
    flags: (0x0009) ACC_PUBLIC, ACC_STATIC
    Code:
      stack=5, locals=0, args_size=0
         0: new           #2                  // class coursier/cache/CacheUrl$BasicRealm$
         3: dup
         4: invokespecial #34                 // Method "<init>":()V
         7: putstatic     #36                 // Field MODULE$:Lcoursier/cache/CacheUrl$BasicRealm$;
        10: getstatic     #41                 // Field scala/collection/StringOps$.MODULE$:Lscala/collection/StringOps$;
        13: getstatic     #46                 // Field scala/Predef$.MODULE$:Lscala/Predef$;
        16: new           #48                 // class java/lang/StringBuilder
        19: dup
        20: ldc           #49                 // int 12
        22: invokespecial #52                 // Method java/lang/StringBuilder."<init>":(I)V
        25: ldc           #54                 // String (?i)^
        27: invokevirtual #58                 // Method java/lang/StringBuilder.append:(Ljava/lang/String;)Ljava/lang/StringBuilder;
        30: ldc           #60                 // String Basic
        32: invokestatic  #66                 // Method java/util/regex/Pattern.quote:(Ljava/lang/String;)Ljava/lang/String;
        35: invokevirtual #58                 // Method java/lang/StringBuilder.append:(Ljava/lang/String;)Ljava/lang/StringBuilder;
        38: ldc           #68                 // String  +(.*)
        40: invokevirtual #58                 // Method java/lang/StringBuilder.append:(Ljava/lang/String;)Ljava/lang/StringBuilder;
        43: ldc           #70                 // String $
        45: invokevirtual #58                 // Method java/lang/StringBuilder.append:(Ljava/lang/String;)Ljava/lang/StringBuilder;
        48: invokevirtual #74                 // Method java/lang/StringBuilder.toString:()Ljava/lang/String;
        51: invokevirtual #77                 // Method scala/Predef$.augmentString:(Ljava/lang/String;)Ljava/lang/String;
        54: invokevirtual #81                 // Method scala/collection/StringOps$.r$extension:(Ljava/lang/String;)Lscala/util/matching/Regex;
        57: putstatic     #83                 // Field BasicAuthBase:Lscala/util/matching/Regex;
        60: getstatic     #41                 // Field scala/collection/StringOps$.MODULE$:Lscala/collection/StringOps$;
        63: getstatic     #46                 // Field scala/Predef$.MODULE$:Lscala/Predef$;
        66: new           #48                 // class java/lang/StringBuilder
        69: dup
        70: ldc           #84                 // int 25
        72: invokespecial #52                 // Method java/lang/StringBuilder."<init>":(I)V
        75: ldc           #86                 // String \\s*(\\S+?)
        77: invokevirtual #58                 // Method java/lang/StringBuilder.append:(Ljava/lang/String;)Ljava/lang/StringBuilder;
        80: ldc           #88                 // String =\"
        82: invokestatic  #66                 // Method java/util/regex/Pattern.quote:(Ljava/lang/String;)Ljava/lang/String;
        85: invokevirtual #58                 // Method java/lang/StringBuilder.append:(Ljava/lang/String;)Ljava/lang/StringBuilder;
        88: ldc           #90                 // String ([^
        90: invokevirtual #58                 // Method java/lang/StringBuilder.append:(Ljava/lang/String;)Ljava/lang/StringBuilder;
        93: ldc           #92                 // String \"
        95: invokestatic  #66                 // Method java/util/regex/Pattern.quote:(Ljava/lang/String;)Ljava/lang/String;
        98: invokevirtual #58                 // Method java/lang/StringBuilder.append:(Ljava/lang/String;)Ljava/lang/StringBuilder;
       101: ldc           #94                 // String ]*)
       103: invokevirtual #58                 // Method java/lang/StringBuilder.append:(Ljava/lang/String;)Ljava/lang/StringBuilder;
       106: ldc           #92                 // String \"
       108: invokestatic  #66                 // Method java/util/regex/Pattern.quote:(Ljava/lang/String;)Ljava/lang/String;
       111: invokevirtual #58                 // Method java/lang/StringBuilder.append:(Ljava/lang/String;)Ljava/lang/StringBuilder;
       114: ldc           #96                 // String \\s*
       116: invokevirtual #58                 // Method java/lang/StringBuilder.append:(Ljava/lang/String;)Ljava/lang/StringBuilder;
       119: ldc           #98                 // String (?:,|$)
       121: invokevirtual #58                 // Method java/lang/StringBuilder.append:(Ljava/lang/String;)Ljava/lang/StringBuilder;
       124: invokevirtual #74                 // Method java/lang/StringBuilder.toString:()Ljava/lang/String;
       127: invokevirtual #77                 // Method scala/Predef$.augmentString:(Ljava/lang/String;)Ljava/lang/String;
       130: invokevirtual #81                 // Method scala/collection/StringOps$.r$extension:(Ljava/lang/String;)Lscala/util/matching/Regex;
       133: putstatic     #100                // Field Param:Lscala/util/matching/Regex;
       136: return
      LineNumberTable:
        line 408: 0
        line 409: 10
        line 413: 13
        line 410: 25
        line 412: 30
        line 413: 38
        line 414: 43
        line 409: 57
        line 417: 60
        line 421: 63
        line 418: 75
        line 419: 88
        line 420: 106
        line 421: 114
        line 422: 119
        line 417: 133
        line 408: 136

  private scala.util.matching.Regex BasicAuthBase();
    descriptor: ()Lscala/util/matching/Regex;
    flags: (0x0002) ACC_PRIVATE
    Code:
      stack=1, locals=1, args_size=1
         0: getstatic     #83                 // Field BasicAuthBase:Lscala/util/matching/Regex;
         3: areturn
      LineNumberTable:
        line 409: 0
      LocalVariableTable:
        Start  Length  Slot  Name   Signature
            0       4     0  this   Lcoursier/cache/CacheUrl$BasicRealm$;

  private scala.util.matching.Regex Param();
    descriptor: ()Lscala/util/matching/Regex;
    flags: (0x0002) ACC_PRIVATE
    Code:
      stack=1, locals=1, args_size=1
         0: getstatic     #100                // Field Param:Lscala/util/matching/Regex;
         3: areturn
      LineNumberTable:
        line 417: 0
      LocalVariableTable:
        Start  Length  Slot  Name   Signature
            0       4     0  this   Lcoursier/cache/CacheUrl$BasicRealm$;

  public scala.Option<java.lang.String> unapply(java.lang.String);
    descriptor: (Ljava/lang/String;)Lscala/Option;
    flags: (0x0001) ACC_PUBLIC
    Code:
      stack=3, locals=6, args_size=2
         0: aload_1
         1: astore_3
         2: aload_3
         3: ifnull        105
         6: aload_0
         7: invokespecial #108                // Method BasicAuthBase:()Lscala/util/matching/Regex;
        10: aload_3
        11: invokevirtual #112                // Method scala/util/matching/Regex.unapplySeq:(Ljava/lang/CharSequence;)Lscala/Option;
        14: astore        4
        16: aload         4
        18: invokevirtual #118                // Method scala/Option.isEmpty:()Z
        21: ifne          102
        24: aload         4
        26: invokevirtual #122                // Method scala/Option.get:()Ljava/lang/Object;
        29: ifnull        102
        32: aload         4
        34: invokevirtual #122                // Method scala/Option.get:()Ljava/lang/Object;
        37: checkcast     #124                // class scala/collection/immutable/List
        40: iconst_1
        41: invokevirtual #128                // Method scala/collection/immutable/List.lengthCompare:(I)I
        44: iconst_0
        45: if_icmpne     102
        48: aload         4
        50: invokevirtual #122                // Method scala/Option.get:()Ljava/lang/Object;
        53: checkcast     #130                // class scala/collection/LinearSeqOps
        56: iconst_0
        57: invokeinterface #134,  2          // InterfaceMethod scala/collection/LinearSeqOps.apply:(I)Ljava/lang/Object;
        62: checkcast     #136                // class java/lang/String
        65: astore        5
        67: aload_0
        68: invokespecial #138                // Method Param:()Lscala/util/matching/Regex;
        71: aload         5
        73: invokevirtual #142                // Method scala/util/matching/Regex.findAllMatchIn:(Ljava/lang/CharSequence;)Lscala/collection/Iterator;
        76: invokedynamic #162,  0            // InvokeDynamic #0:apply:()Lscala/Function1;
        81: invokeinterface #168,  2          // InterfaceMethod scala/collection/Iterator.map:(Lscala/Function1;)Lscala/collection/Iterator;
        86: new           #10                 // class coursier/cache/CacheUrl$BasicRealm$$anonfun$unapply$2
        89: dup
        90: invokespecial #169                // Method coursier/cache/CacheUrl$BasicRealm$$anonfun$unapply$2."<init>":()V
        93: invokeinterface #173,  2          // InterfaceMethod scala/collection/Iterator.collectFirst:(Lscala/PartialFunction;)Lscala/Option;
        98: astore_2
        99: goto          115
       102: goto          108
       105: goto          108
       108: getstatic     #178                // Field scala/None$.MODULE$:Lscala/None$;
       111: astore_2
       112: goto          115
       115: aload_2
       116: areturn
      StackMapTable: number_of_entries = 4
        frame_type = 254 /* append */
          offset_delta = 102
          locals = [ top, class java/lang/String, class scala/Option ]
        frame_type = 250 /* chop */
          offset_delta = 2
        frame_type = 2 /* same */
        frame_type = 255 /* full_frame */
          offset_delta = 6
          locals = [ class coursier/cache/CacheUrl$BasicRealm$, class java/lang/String, class scala/Option, class java/lang/String ]
          stack = []
      LineNumberTable:
        line 439: 0
        line 440: 2
        line 441: 67
        line 442: 76
        line 443: 86
        line 440: 102
        line 446: 108
        line 439: 115
      LocalVariableTable:
        Start  Length  Slot  Name   Signature
           67      35     5 basicAuthLine   Ljava/lang/String;
            0     117     0  this   Lcoursier/cache/CacheUrl$BasicRealm$;
            0     117     1 wwwAuthenticate   Ljava/lang/String;
    Signature: #105                         // (Ljava/lang/String;)Lscala/Option<Ljava/lang/String;>;
    MethodParameters:
      Name                           Flags
      wwwAuthenticate                final

  public static final scala.Tuple2 $anonfun$unapply$1(scala.util.matching.Regex$Match);
    descriptor: (Lscala/util/matching/Regex$Match;)Lscala/Tuple2;
    flags: (0x1019) ACC_PUBLIC, ACC_STATIC, ACC_FINAL, ACC_SYNTHETIC
    Code:
      stack=4, locals=1, args_size=1
         0: getstatic     #184                // Field scala/Predef$ArrowAssoc$.MODULE$:Lscala/Predef$ArrowAssoc$;
         3: getstatic     #46                 // Field scala/Predef$.MODULE$:Lscala/Predef$;
         6: aload_0
         7: iconst_1
         8: invokevirtual #188                // Method scala/util/matching/Regex$Match.group:(I)Ljava/lang/String;
        11: getstatic     #194                // Field java/util/Locale.ROOT:Ljava/util/Locale;
        14: invokevirtual #198                // Method java/lang/String.toLowerCase:(Ljava/util/Locale;)Ljava/lang/String;
        17: invokevirtual #201                // Method scala/Predef$.ArrowAssoc:(Ljava/lang/Object;)Ljava/lang/Object;
        20: aload_0
        21: iconst_2
        22: invokevirtual #188                // Method scala/util/matching/Regex$Match.group:(I)Ljava/lang/String;
        25: invokevirtual #205                // Method scala/Predef$ArrowAssoc$.$minus$greater$extension:(Ljava/lang/Object;Ljava/lang/Object;)Lscala/Tuple2;
        28: areturn
      LineNumberTable:
        line 442: 3
      LocalVariableTable:
        Start  Length  Slot  Name   Signature
            0      29     0  mobj   Lscala/util/matching/Regex$Match;
    MethodParameters:
      Name                           Flags
      mobj                           final

  public coursier.cache.CacheUrl$BasicRealm$();
    descriptor: ()V
    flags: (0x0001) ACC_PUBLIC
    Code:
      stack=1, locals=1, args_size=1
         0: aload_0
         1: invokespecial #207                // Method java/lang/Object."<init>":()V
         4: return
      LineNumberTable:
        line 451: 0
        line 408: 4
      LocalVariableTable:
        Start  Length  Slot  Name   Signature
            0       5     0  this   Lcoursier/cache/CacheUrl$BasicRealm$;

  private static java.lang.Object $deserializeLambda$(java.lang.invoke.SerializedLambda);
    descriptor: (Ljava/lang/invoke/SerializedLambda;)Ljava/lang/Object;
    flags: (0x100a) ACC_PRIVATE, ACC_STATIC, ACC_SYNTHETIC
    Code:
      stack=1, locals=1, args_size=1
         0: aload_0
         1: invokedynamic #219,  0            // InvokeDynamic #1:lambdaDeserialize:(Ljava/lang/invoke/SerializedLambda;)Ljava/lang/Object;
         6: areturn
}
InnerClasses:
  public static #8= #2 of #7;             // =class coursier/cache/CacheUrl$BasicRealm$ of class coursier/cache/CacheUrl
  public final #10;                       // class coursier/cache/CacheUrl$BasicRealm$$anonfun$unapply$2
  public static final #15= #12 of #14;    // Lookup=class java/lang/invoke/MethodHandles$Lookup of class java/lang/invoke/MethodHandles
  public static #8= #17 of #19;           // =class scala/Predef$ArrowAssoc$ of class scala/Predef
  public static #24= #21 of #23;          // Match=class scala/util/matching/Regex$Match of class scala/util/matching/Regex
SourceFile: "CacheUrl.scala"
BootstrapMethods:
  0: #159 REF_invokeStatic java/lang/invoke/LambdaMetafactory.altMetafactory:(Ljava/lang/invoke/MethodHandles$Lookup;Ljava/lang/String;Ljava/lang/invoke/MethodType;[Ljava/lang/Object;)Ljava/lang/invoke/CallSite;
    Method arguments:
      #144 (Ljava/lang/Object;)Ljava/lang/Object;
      #149 REF_invokeStatic coursier/cache/CacheUrl$BasicRealm$.$anonfun$unapply$1:(Lscala/util/matching/Regex$Match;)Lscala/Tuple2;
      #150 (Lscala/util/matching/Regex$Match;)Lscala/Tuple2;
      #151 5
      #152 1
      #150 (Lscala/util/matching/Regex$Match;)Lscala/Tuple2;
  1: #216 REF_invokeStatic scala/runtime/LambdaDeserialize.bootstrap:(Ljava/lang/invoke/MethodHandles$Lookup;Ljava/lang/String;Ljava/lang/invoke/MethodType;[Ljava/lang/invoke/MethodHandle;)Ljava/lang/invoke/CallSite;
    Method arguments:
      #149 REF_invokeStatic coursier/cache/CacheUrl$BasicRealm$.$anonfun$unapply$1:(Lscala/util/matching/Regex$Match;)Lscala/Tuple2;
  ScalaInlineInfo: length = 0x1D (unknown attribute)
   01 01 00 05 00 92 00 93 01 00 21 00 20 01 00 1C
   00 66 01 00 1E 00 66 01 00 68 00 69 01
  Scala: length = 0x0 (unknown attribute)

