Classfile /Users/mw/Projects/slang-braindump/.jar/jar11/assemble/slang-braindump/assemble/content/coursier/cache/FileCache$$anon$1.class
  Last modified May 29, 2022; size 887 bytes
  SHA-256 checksum 8f821ae6ff0e0e57b28ea67f39db2a786e04cbcdcdb4d3edd077e1cab8e347ef
  Compiled from "FileCache.scala"
public final class coursier.cache.FileCache$$anon$1 implements java.io.FilenameFilter
  minor version: 0
  major version: 52
  flags: (0x0031) ACC_PUBLIC, ACC_FINAL, ACC_SUPER
  this_class: #2                          // coursier/cache/FileCache$$anon$1
  super_class: #4                         // java/lang/Object
  interfaces: 1, fields: 1, methods: 2, attributes: 5
Constant pool:
   #1 = Utf8               coursier/cache/FileCache$$anon$1
   #2 = Class              #1             // coursier/cache/FileCache$$anon$1
   #3 = Utf8               java/lang/Object
   #4 = Class              #3             // java/lang/Object
   #5 = Utf8               java/io/FilenameFilter
   #6 = Class              #5             // java/io/FilenameFilter
   #7 = Utf8               FileCache.scala
   #8 = Utf8               coursier/cache/FileCache$
   #9 = Class              #8             // coursier/cache/FileCache$
  #10 = Utf8               clearAuxiliaryFiles
  #11 = Utf8               (Ljava/io/File;)V
  #12 = NameAndType        #10:#11        // clearAuxiliaryFiles:(Ljava/io/File;)V
  #13 = Utf8               prefix$1
  #14 = Utf8               Ljava/lang/String;
  #15 = Utf8               accept
  #16 = Utf8               (Ljava/io/File;Ljava/lang/String;)Z
  #17 = Utf8               dir
  #18 = Utf8               name
  #19 = NameAndType        #13:#14        // prefix$1:Ljava/lang/String;
  #20 = Fieldref           #2.#19         // coursier/cache/FileCache$$anon$1.prefix$1:Ljava/lang/String;
  #21 = Utf8               java/lang/String
  #22 = Class              #21            // java/lang/String
  #23 = Utf8               startsWith
  #24 = Utf8               (Ljava/lang/String;)Z
  #25 = NameAndType        #23:#24        // startsWith:(Ljava/lang/String;)Z
  #26 = Methodref          #22.#25        // java/lang/String.startsWith:(Ljava/lang/String;)Z
  #27 = Utf8               this
  #28 = Utf8               Lcoursier/cache/FileCache$$anon$1;
  #29 = Utf8               Ljava/io/File;
  #30 = Utf8               <init>
  #31 = Utf8               (Ljava/lang/String;)V
  #32 = Utf8               ()V
  #33 = NameAndType        #30:#32        // "<init>":()V
  #34 = Methodref          #4.#33         // java/lang/Object."<init>":()V
  #35 = Utf8               Code
  #36 = Utf8               LineNumberTable
  #37 = Utf8               LocalVariableTable
  #38 = Utf8               MethodParameters
  #39 = Utf8               InnerClasses
  #40 = Utf8               EnclosingMethod
  #41 = Utf8               SourceFile
  #42 = Utf8               ScalaInlineInfo
  #43 = Utf8               Scala
{
  private final java.lang.String prefix$1;
    descriptor: Ljava/lang/String;
    flags: (0x0012) ACC_PRIVATE, ACC_FINAL

  public boolean accept(java.io.File, java.lang.String);
    descriptor: (Ljava/io/File;Ljava/lang/String;)Z
    flags: (0x0001) ACC_PUBLIC
    Code:
      stack=2, locals=3, args_size=3
         0: aload_2
         1: aload_0
         2: getfield      #20                 // Field prefix$1:Ljava/lang/String;
         5: invokevirtual #26                 // Method java/lang/String.startsWith:(Ljava/lang/String;)Z
         8: ireturn
      LineNumberTable:
        line 379: 0
      LocalVariableTable:
        Start  Length  Slot  Name   Signature
            0       9     0  this   Lcoursier/cache/FileCache$$anon$1;
            0       9     1   dir   Ljava/io/File;
            0       9     2  name   Ljava/lang/String;
    MethodParameters:
      Name                           Flags
      dir                            final
      name                           final

  public coursier.cache.FileCache$$anon$1(java.lang.String);
    descriptor: (Ljava/lang/String;)V
    flags: (0x0001) ACC_PUBLIC
    Code:
      stack=2, locals=2, args_size=2
         0: aload_0
         1: aload_1
         2: putfield      #20                 // Field prefix$1:Ljava/lang/String;
         5: aload_0
         6: invokespecial #34                 // Method java/lang/Object."<init>":()V
         9: return
      LineNumberTable:
        line 376: 0
        line 377: 5
      LocalVariableTable:
        Start  Length  Slot  Name   Signature
            0      10     0  this   Lcoursier/cache/FileCache$$anon$1;
            0      10     1 prefix$1   Ljava/lang/String;
    MethodParameters:
      Name                           Flags
      prefix$1                       final
}
InnerClasses:
  public final #2;                        // class coursier/cache/FileCache$$anon$1
EnclosingMethod: #9.#12                 // coursier.cache.FileCache$.clearAuxiliaryFiles
SourceFile: "FileCache.scala"
  ScalaInlineInfo: length = 0xE (unknown attribute)
   01 01 00 02 00 1E 00 1F 01 00 0F 00 10 01
  Scala: length = 0x0 (unknown attribute)

