Classfile /Users/mw/Projects/slang-braindump/.jar/jar11/assemble/slang-braindump/assemble/content/shapeless/AdditiveCollection.class
  Last modified May 29, 2022; size 3000 bytes
  SHA-256 checksum 28cccd06c2594dfbc0059d7872c8a9bf2bc87ee64b75da78276e6afd830da175
  Compiled from "sized.scala"
public interface shapeless.AdditiveCollection<Repr extends java.lang.Object> extends java.io.Serializable
  minor version: 0
  major version: 52
  flags: (0x0601) ACC_PUBLIC, ACC_INTERFACE, ACC_ABSTRACT
  this_class: #2                          // shapeless/AdditiveCollection
  super_class: #5                         // java/lang/Object
  interfaces: 1, fields: 0, methods: 8, attributes: 5
Constant pool:
   #1 = Utf8               shapeless/AdditiveCollection
   #2 = Class              #1             // shapeless/AdditiveCollection
   #3 = Utf8               <Repr:Ljava/lang/Object;>Ljava/lang/Object;Ljava/io/Serializable;
   #4 = Utf8               java/lang/Object
   #5 = Class              #4             // java/lang/Object
   #6 = Utf8               java/io/Serializable
   #7 = Class              #6             // java/io/Serializable
   #8 = Utf8               sized.scala
   #9 = Utf8               Lscala/reflect/ScalaSignature;
  #10 = Utf8               bytes
  #11 = Utf8               \u0006\u0005\u0005-baB\u0007\u000f!\u0003\r\n!E\u0004\u0006]9A\ta\f\u0004\u0006\u001b9A\t!\r\u0005\u0006s\t!\tA\u000f\u0005\u0006w\t!\u0019\u0001\u0010\u0005\u0006\u0013\n!\u0019A\u0013\u0005\u0006%\n!\u0019a\u0015\u0005\u00067\n!\u0019\u0001\u0018\u0005\u0006M\n!\u0019a\u001a\u0005\u0006_\n!\u0019\u0001\u001d\u0005\u0006q\n!\u0019!\u001f\u0005\b\u0003\u0013\u0011A1AA\u0006\u0011%\tYBAA\u0001\n\u0013\tiB\u0001\nBI\u0012LG/\u001b<f\u0007>dG.Z2uS>t\'\"A\b\u0002\u0013MD\u0017\r]3mKN\u001c8\u0001A\u000b\u0003%\u0015\u001a2\u0001A\n\u001a!\t!r#D\u0001\u0016\u0015\u00051\u0012!B:dC2\f\u0017B\u0001\r\u0016\u0005\u0019\te.\u001f*fMB\u0011!D\t\b\u00037\u0001r!\u0001H\u0010\u000e\u0003uQ!A\b\t\u0002\rq\u0012xn\u001c;?\u0013\u00051\u0012BA\u0011\u0016\u0003\u001d\u0001\u0018mY6bO\u0016L!a\t\u0013\u0003\u0019M+\'/[1mSj\f\'\r\\3\u000b\u0005\u0005*B!\u0002\u0014\u0001\u0005\u00049#\u0001\u0002*faJ\f\"\u0001K\u0016\u0011\u0005QI\u0013B\u0001\u0016\u0016\u0005\u001dqu\u000e\u001e5j]\u001e\u0004\"\u0001\u0006\u0017\n\u00055*\"aA!os\u0006\u0011\u0012\t\u001a3ji&4XmQ8mY\u0016\u001cG/[8o!\t\u0001$!D\u0001\u000f\'\r\u00111C\r\t\u0003gaj\u0011\u0001\u000e\u0006\u0003kY\n!![8\u000b\u0003]\nAA[1wC&\u00111\u0005N\u0001\u0007y%t\u0017\u000e\u001e \u0015\u0003=\n1\u0004\\5oK\u0006\u00148+Z9BI\u0012LG/\u001b<f\u0007>dG.Z2uS>tWCA\u001fH+\u0005q\u0004c\u0001\u0019\u0001\u007fA\u0019\u0001iQ#\u000e\u0003\u0005S!AQ\u000b\u0002\u0015\r|G\u000e\\3di&|g.\u0003\u0002E\u0003\nIA*\u001b8fCJ\u001cV-\u001d\t\u0003\r\u001ec\u0001\u0001B\u0003I\t\t\u0007qEA\u0001U\u0003a1Xm\u0019;pe\u0006#G-\u001b;jm\u0016\u001cu\u000e\u001c7fGRLwN\\\u000b\u0003\u0017F+\u0012\u0001\u0014\t\u0004a\u0001i\u0005c\u0001\u000eO!&\u0011q\n\n\u0002\u0007-\u0016\u001cGo\u001c:\u0011\u0005\u0019\u000bF!\u0002%\u0006\u0005\u00049\u0013aF1se\u0006L\u0018\t\u001a3ji&4XmQ8mY\u0016\u001cG/[8o+\t!&,F\u0001V!\r\u0001\u0004A\u0016\t\u0004)]K\u0016B\u0001-\u0016\u0005\u0015\t%O]1z!\t1%\fB\u0003I\r\t\u0007q%\u0001\rtiJLgnZ!eI&$\u0018N^3D_2dWm\u0019;j_:,\u0012!\u0018\t\u0004a\u0001q\u0006CA0d\u001d\t\u0001\u0017\r\u0005\u0002\u001d+%\u0011!-F\u0001\u0007!J,G-\u001a4\n\u0005\u0011,\'AB*ue&twM\u0003\u0002c+\u00051B.[:u\u0003\u0012$\u0017\u000e^5wK\u000e{G\u000e\\3di&|g.\u0006\u0002i]V\t\u0011\u000eE\u00021\u0001)\u00042AG6n\u0013\taGE\u0001\u0003MSN$\bC\u0001$o\t\u0015A\u0005B1\u0001(\u0003a\u0019HO]3b[\u0006#G-\u001b;jm\u0016\u001cu\u000e\u001c7fGRLwN\\\u000b\u0003c^,\u0012A\u001d\t\u0004a\u0001\u0019\bc\u0001\u000eum&\u0011Q\u000f\n\u0002\t\u0019\u0006T\u0018\u0010T5tiB\u0011ai\u001e\u0003\u0006\u0011&\u0011\raJ\u0001\u0018cV,W/Z!eI&$\u0018N^3D_2dWm\u0019;j_:,2A_A\u0004+\u0005Y\bc\u0001\u0019\u0001yB)Q0!\u0001\u0002\u00065\taP\u0003\u0002\u0000\u0003\u0006I\u0011.\\7vi\u0006\u0014G.Z\u0005\u0004\u0003\u0007q(!B)vKV,\u0007c\u0001$\u0002\b\u0011)\u0001J\u0003b\u0001O\u0005IB-\u001a4bk2$\u0018\t\u001a3ji&4XmQ8mY\u0016\u001cG/[8o+\u0011\ti!!\u0007\u0016\u0005\u0005=\u0001\u0003\u0002\u0019\u0001\u0003#\u0001R!`A\n\u0003/I1!!\u0006\u007f\u0005)Ie\u000eZ3yK\u0012\u001cV-\u001d\t\u0004\r\u0006eA!\u0002%\f\u0005\u00049\u0013\u0001D<sSR,\'+\u001a9mC\u000e,GCAA\u0010!\u0011\t\t#a\n\u000e\u0005\u0005\r\"bAA\u0013m\u0005!A.\u00198h\u0013\u0011\tI#a\t\u0003\r=\u0013\'.Z2u\u0001
  #12 = Utf8               defaultAdditiveCollection
  #13 = Utf8               ()Lshapeless/AdditiveCollection;
  #14 = Utf8               <T:Ljava/lang/Object;>()Lshapeless/AdditiveCollection<Lscala/collection/immutable/IndexedSeq<TT;>;>;
  #15 = Utf8               shapeless/AdditiveCollection$
  #16 = Class              #15            // shapeless/AdditiveCollection$
  #17 = Utf8               MODULE$
  #18 = Utf8               Lshapeless/AdditiveCollection$;
  #19 = NameAndType        #17:#18        // MODULE$:Lshapeless/AdditiveCollection$;
  #20 = Fieldref           #16.#19        // shapeless/AdditiveCollection$.MODULE$:Lshapeless/AdditiveCollection$;
  #21 = NameAndType        #12:#13        // defaultAdditiveCollection:()Lshapeless/AdditiveCollection;
  #22 = Methodref          #16.#21        // shapeless/AdditiveCollection$.defaultAdditiveCollection:()Lshapeless/AdditiveCollection;
  #23 = Utf8               queueAdditiveCollection
  #24 = Utf8               <T:Ljava/lang/Object;>()Lshapeless/AdditiveCollection<Lscala/collection/immutable/Queue<TT;>;>;
  #25 = NameAndType        #23:#13        // queueAdditiveCollection:()Lshapeless/AdditiveCollection;
  #26 = Methodref          #16.#25        // shapeless/AdditiveCollection$.queueAdditiveCollection:()Lshapeless/AdditiveCollection;
  #27 = Utf8               streamAdditiveCollection
  #28 = Utf8               <T:Ljava/lang/Object;>()Lshapeless/AdditiveCollection<Lscala/collection/immutable/LazyList<TT;>;>;
  #29 = NameAndType        #27:#13        // streamAdditiveCollection:()Lshapeless/AdditiveCollection;
  #30 = Methodref          #16.#29        // shapeless/AdditiveCollection$.streamAdditiveCollection:()Lshapeless/AdditiveCollection;
  #31 = Utf8               listAdditiveCollection
  #32 = Utf8               <T:Ljava/lang/Object;>()Lshapeless/AdditiveCollection<Lscala/collection/immutable/List<TT;>;>;
  #33 = NameAndType        #31:#13        // listAdditiveCollection:()Lshapeless/AdditiveCollection;
  #34 = Methodref          #16.#33        // shapeless/AdditiveCollection$.listAdditiveCollection:()Lshapeless/AdditiveCollection;
  #35 = Utf8               stringAdditiveCollection
  #36 = Utf8               ()Lshapeless/AdditiveCollection<Ljava/lang/String;>;
  #37 = NameAndType        #35:#13        // stringAdditiveCollection:()Lshapeless/AdditiveCollection;
  #38 = Methodref          #16.#37        // shapeless/AdditiveCollection$.stringAdditiveCollection:()Lshapeless/AdditiveCollection;
  #39 = Utf8               arrayAdditiveCollection
  #40 = Utf8               <T:Ljava/lang/Object;>()Lshapeless/AdditiveCollection<Ljava/lang/Object;>;
  #41 = NameAndType        #39:#13        // arrayAdditiveCollection:()Lshapeless/AdditiveCollection;
  #42 = Methodref          #16.#41        // shapeless/AdditiveCollection$.arrayAdditiveCollection:()Lshapeless/AdditiveCollection;
  #43 = Utf8               vectorAdditiveCollection
  #44 = Utf8               <T:Ljava/lang/Object;>()Lshapeless/AdditiveCollection<Lscala/collection/immutable/Vector<TT;>;>;
  #45 = NameAndType        #43:#13        // vectorAdditiveCollection:()Lshapeless/AdditiveCollection;
  #46 = Methodref          #16.#45        // shapeless/AdditiveCollection$.vectorAdditiveCollection:()Lshapeless/AdditiveCollection;
  #47 = Utf8               linearSeqAdditiveCollection
  #48 = Utf8               <T:Ljava/lang/Object;>()Lshapeless/AdditiveCollection<Lscala/collection/LinearSeq<TT;>;>;
  #49 = NameAndType        #47:#13        // linearSeqAdditiveCollection:()Lshapeless/AdditiveCollection;
  #50 = Methodref          #16.#49        // shapeless/AdditiveCollection$.linearSeqAdditiveCollection:()Lshapeless/AdditiveCollection;
  #51 = Utf8               Code
  #52 = Utf8               Signature
  #53 = Utf8               SourceFile
  #54 = Utf8               RuntimeVisibleAnnotations
  #55 = Utf8               ScalaInlineInfo
  #56 = Utf8               ScalaSig
{
  public static <T extends java.lang.Object> shapeless.AdditiveCollection<scala.collection.immutable.IndexedSeq<T>> defaultAdditiveCollection();
    descriptor: ()Lshapeless/AdditiveCollection;
    flags: (0x0009) ACC_PUBLIC, ACC_STATIC
    Code:
      stack=1, locals=0, args_size=0
         0: getstatic     #20                 // Field shapeless/AdditiveCollection$.MODULE$:Lshapeless/AdditiveCollection$;
         3: invokevirtual #22                 // Method shapeless/AdditiveCollection$.defaultAdditiveCollection:()Lshapeless/AdditiveCollection;
         6: areturn
    Signature: #14                          // <T:Ljava/lang/Object;>()Lshapeless/AdditiveCollection<Lscala/collection/immutable/IndexedSeq<TT;>;>;

  public static <T extends java.lang.Object> shapeless.AdditiveCollection<scala.collection.immutable.Queue<T>> queueAdditiveCollection();
    descriptor: ()Lshapeless/AdditiveCollection;
    flags: (0x0009) ACC_PUBLIC, ACC_STATIC
    Code:
      stack=1, locals=0, args_size=0
         0: getstatic     #20                 // Field shapeless/AdditiveCollection$.MODULE$:Lshapeless/AdditiveCollection$;
         3: invokevirtual #26                 // Method shapeless/AdditiveCollection$.queueAdditiveCollection:()Lshapeless/AdditiveCollection;
         6: areturn
    Signature: #24                          // <T:Ljava/lang/Object;>()Lshapeless/AdditiveCollection<Lscala/collection/immutable/Queue<TT;>;>;

  public static <T extends java.lang.Object> shapeless.AdditiveCollection<scala.collection.immutable.LazyList<T>> streamAdditiveCollection();
    descriptor: ()Lshapeless/AdditiveCollection;
    flags: (0x0009) ACC_PUBLIC, ACC_STATIC
    Code:
      stack=1, locals=0, args_size=0
         0: getstatic     #20                 // Field shapeless/AdditiveCollection$.MODULE$:Lshapeless/AdditiveCollection$;
         3: invokevirtual #30                 // Method shapeless/AdditiveCollection$.streamAdditiveCollection:()Lshapeless/AdditiveCollection;
         6: areturn
    Signature: #28                          // <T:Ljava/lang/Object;>()Lshapeless/AdditiveCollection<Lscala/collection/immutable/LazyList<TT;>;>;

  public static <T extends java.lang.Object> shapeless.AdditiveCollection<scala.collection.immutable.List<T>> listAdditiveCollection();
    descriptor: ()Lshapeless/AdditiveCollection;
    flags: (0x0009) ACC_PUBLIC, ACC_STATIC
    Code:
      stack=1, locals=0, args_size=0
         0: getstatic     #20                 // Field shapeless/AdditiveCollection$.MODULE$:Lshapeless/AdditiveCollection$;
         3: invokevirtual #34                 // Method shapeless/AdditiveCollection$.listAdditiveCollection:()Lshapeless/AdditiveCollection;
         6: areturn
    Signature: #32                          // <T:Ljava/lang/Object;>()Lshapeless/AdditiveCollection<Lscala/collection/immutable/List<TT;>;>;

  public static shapeless.AdditiveCollection<java.lang.String> stringAdditiveCollection();
    descriptor: ()Lshapeless/AdditiveCollection;
    flags: (0x0009) ACC_PUBLIC, ACC_STATIC
    Code:
      stack=1, locals=0, args_size=0
         0: getstatic     #20                 // Field shapeless/AdditiveCollection$.MODULE$:Lshapeless/AdditiveCollection$;
         3: invokevirtual #38                 // Method shapeless/AdditiveCollection$.stringAdditiveCollection:()Lshapeless/AdditiveCollection;
         6: areturn
    Signature: #36                          // ()Lshapeless/AdditiveCollection<Ljava/lang/String;>;

  public static <T extends java.lang.Object> shapeless.AdditiveCollection<java.lang.Object> arrayAdditiveCollection();
    descriptor: ()Lshapeless/AdditiveCollection;
    flags: (0x0009) ACC_PUBLIC, ACC_STATIC
    Code:
      stack=1, locals=0, args_size=0
         0: getstatic     #20                 // Field shapeless/AdditiveCollection$.MODULE$:Lshapeless/AdditiveCollection$;
         3: invokevirtual #42                 // Method shapeless/AdditiveCollection$.arrayAdditiveCollection:()Lshapeless/AdditiveCollection;
         6: areturn
    Signature: #40                          // <T:Ljava/lang/Object;>()Lshapeless/AdditiveCollection<Ljava/lang/Object;>;

  public static <T extends java.lang.Object> shapeless.AdditiveCollection<scala.collection.immutable.Vector<T>> vectorAdditiveCollection();
    descriptor: ()Lshapeless/AdditiveCollection;
    flags: (0x0009) ACC_PUBLIC, ACC_STATIC
    Code:
      stack=1, locals=0, args_size=0
         0: getstatic     #20                 // Field shapeless/AdditiveCollection$.MODULE$:Lshapeless/AdditiveCollection$;
         3: invokevirtual #46                 // Method shapeless/AdditiveCollection$.vectorAdditiveCollection:()Lshapeless/AdditiveCollection;
         6: areturn
    Signature: #44                          // <T:Ljava/lang/Object;>()Lshapeless/AdditiveCollection<Lscala/collection/immutable/Vector<TT;>;>;

  public static <T extends java.lang.Object> shapeless.AdditiveCollection<scala.collection.LinearSeq<T>> linearSeqAdditiveCollection();
    descriptor: ()Lshapeless/AdditiveCollection;
    flags: (0x0009) ACC_PUBLIC, ACC_STATIC
    Code:
      stack=1, locals=0, args_size=0
         0: getstatic     #20                 // Field shapeless/AdditiveCollection$.MODULE$:Lshapeless/AdditiveCollection$;
         3: invokevirtual #50                 // Method shapeless/AdditiveCollection$.linearSeqAdditiveCollection:()Lshapeless/AdditiveCollection;
         6: areturn
    Signature: #48                          // <T:Ljava/lang/Object;>()Lshapeless/AdditiveCollection<Lscala/collection/LinearSeq<TT;>;>;
}
Signature: #3                           // <Repr:Ljava/lang/Object;>Ljava/lang/Object;Ljava/io/Serializable;
SourceFile: "sized.scala"
RuntimeVisibleAnnotations:
  0: #9(#10=s#11)
    scala.reflect.ScalaSignature(
      bytes="\u0006\u0005\u0005-baB\u0007\u000f!\u0003\r\n!E\u0004\u0006]9A\ta\f\u0004\u0006\u001b9A\t!\r\u0005\u0006s\t!\tA\u000f\u0005\u0006w\t!\u0019\u0001\u0010\u0005\u0006\u0013\n!\u0019A\u0013\u0005\u0006%\n!\u0019a\u0015\u0005\u00067\n!\u0019\u0001\u0018\u0005\u0006M\n!\u0019a\u001a\u0005\u0006_\n!\u0019\u0001\u001d\u0005\u0006q\n!\u0019!\u001f\u0005\b\u0003\u0013\u0011A1AA\u0006\u0011%\tYBAA\u0001\n\u0013\tiB\u0001\nBI\u0012LG/\u001b<f\u0007>dG.Z2uS>t\'\"A\b\u0002\u0013MD\u0017\r]3mKN\u001c8\u0001A\u000b\u0003%\u0015\u001a2\u0001A\n\u001a!\t!r#D\u0001\u0016\u0015\u00051\u0012!B:dC2\f\u0017B\u0001\r\u0016\u0005\u0019\te.\u001f*fMB\u0011!D\t\b\u00037\u0001r!\u0001H\u0010\u000e\u0003uQ!A\b\t\u0002\rq\u0012xn\u001c;?\u0013\u00051\u0012BA\u0011\u0016\u0003\u001d\u0001\u0018mY6bO\u0016L!a\t\u0013\u0003\u0019M+\'/[1mSj\f\'\r\\3\u000b\u0005\u0005*B!\u0002\u0014\u0001\u0005\u00049#\u0001\u0002*faJ\f\"\u0001K\u0016\u0011\u0005QI\u0013B\u0001\u0016\u0016\u0005\u001dqu\u000e\u001e5j]\u001e\u0004\"\u0001\u0006\u0017\n\u00055*\"aA!os\u0006\u0011\u0012\t\u001a3ji&4XmQ8mY\u0016\u001cG/[8o!\t\u0001$!D\u0001\u000f\'\r\u00111C\r\t\u0003gaj\u0011\u0001\u000e\u0006\u0003kY\n!![8\u000b\u0003]\nAA[1wC&\u00111\u0005N\u0001\u0007y%t\u0017\u000e\u001e \u0015\u0003=\n1\u0004\\5oK\u0006\u00148+Z9BI\u0012LG/\u001b<f\u0007>dG.Z2uS>tWCA\u001fH+\u0005q\u0004c\u0001\u0019\u0001\u007fA\u0019\u0001iQ#\u000e\u0003\u0005S!AQ\u000b\u0002\u0015\r|G\u000e\\3di&|g.\u0003\u0002E\u0003\nIA*\u001b8fCJ\u001cV-\u001d\t\u0003\r\u001ec\u0001\u0001B\u0003I\t\t\u0007qEA\u0001U\u0003a1Xm\u0019;pe\u0006#G-\u001b;jm\u0016\u001cu\u000e\u001c7fGRLwN\\\u000b\u0003\u0017F+\u0012\u0001\u0014\t\u0004a\u0001i\u0005c\u0001\u000eO!&\u0011q\n\n\u0002\u0007-\u0016\u001cGo\u001c:\u0011\u0005\u0019\u000bF!\u0002%\u0006\u0005\u00049\u0013aF1se\u0006L\u0018\t\u001a3ji&4XmQ8mY\u0016\u001cG/[8o+\t!&,F\u0001V!\r\u0001\u0004A\u0016\t\u0004)]K\u0016B\u0001-\u0016\u0005\u0015\t%O]1z!\t1%\fB\u0003I\r\t\u0007q%\u0001\rtiJLgnZ!eI&$\u0018N^3D_2dWm\u0019;j_:,\u0012!\u0018\t\u0004a\u0001q\u0006CA0d\u001d\t\u0001\u0017\r\u0005\u0002\u001d+%\u0011!-F\u0001\u0007!J,G-\u001a4\n\u0005\u0011,\'AB*ue&twM\u0003\u0002c+\u00051B.[:u\u0003\u0012$\u0017\u000e^5wK\u000e{G\u000e\\3di&|g.\u0006\u0002i]V\t\u0011\u000eE\u00021\u0001)\u00042AG6n\u0013\taGE\u0001\u0003MSN$\bC\u0001$o\t\u0015A\u0005B1\u0001(\u0003a\u0019HO]3b[\u0006#G-\u001b;jm\u0016\u001cu\u000e\u001c7fGRLwN\\\u000b\u0003c^,\u0012A\u001d\t\u0004a\u0001\u0019\bc\u0001\u000eum&\u0011Q\u000f\n\u0002\t\u0019\u0006T\u0018\u0010T5tiB\u0011ai\u001e\u0003\u0006\u0011&\u0011\raJ\u0001\u0018cV,W/Z!eI&$\u0018N^3D_2dWm\u0019;j_:,2A_A\u0004+\u0005Y\bc\u0001\u0019\u0001yB)Q0!\u0001\u0002\u00065\taP\u0003\u0002\u0000\u0003\u0006I\u0011.\\7vi\u0006\u0014G.Z\u0005\u0004\u0003\u0007q(!B)vKV,\u0007c\u0001$\u0002\b\u0011)\u0001J\u0003b\u0001O\u0005IB-\u001a4bk2$\u0018\t\u001a3ji&4XmQ8mY\u0016\u001cG/[8o+\u0011\ti!!\u0007\u0016\u0005\u0005=\u0001\u0003\u0002\u0019\u0001\u0003#\u0001R!`A\n\u0003/I1!!\u0006\u007f\u0005)Ie\u000eZ3yK\u0012\u001cV-\u001d\t\u0004\r\u0006eA!\u0002%\f\u0005\u00049\u0013\u0001D<sSR,\'+\u001a9mC\u000e,GCAA\u0010!\u0011\t\t#a\n\u000e\u0005\u0005\r\"bAA\u0013m\u0005!A.\u00198h\u0013\u0011\tI#a\t\u0003\r=\u0013\'.Z2u\u0001"
    )
  ScalaInlineInfo: length = 0x4 (unknown attribute)
   01 00 00 00
  ScalaSig: length = 0x3 (unknown attribute)
   05 02 00
