Classfile /Users/mw/Projects/slang-braindump/.jar/jar11/assemble/slang-braindump/assemble/content/shapeless/Annotation.class
  Last modified May 29, 2022; size 2091 bytes
  SHA-256 checksum 1844c835f774385938ca31f6d74d395732839ed2f703b5c71cf286597126f307
  Compiled from "annotation.scala"
public interface shapeless.Annotation<A extends java.lang.Object, T extends java.lang.Object> extends java.io.Serializable
  minor version: 0
  major version: 52
  flags: (0x0601) ACC_PUBLIC, ACC_INTERFACE, ACC_ABSTRACT
  this_class: #2                          // shapeless/Annotation
  super_class: #5                         // java/lang/Object
  interfaces: 1, fields: 0, methods: 2, attributes: 5
Constant pool:
   #1 = Utf8               shapeless/Annotation
   #2 = Class              #1             // shapeless/Annotation
   #3 = Utf8               <A:Ljava/lang/Object;T:Ljava/lang/Object;>Ljava/lang/Object;Ljava/io/Serializable;
   #4 = Utf8               java/lang/Object
   #5 = Class              #4             // java/lang/Object
   #6 = Utf8               java/io/Serializable
   #7 = Class              #6             // java/io/Serializable
   #8 = Utf8               annotation.scala
   #9 = Utf8               Lscala/reflect/ScalaSignature;
  #10 = Utf8               bytes
  #11 = Utf8               \u0006\u0005\u00055daB\u0005\u000b!\u0003\r\n!\u0004\u0005\u0006C\u00011\tAI\u0004\u0006a)A\t!\r\u0004\u0006\u0013)A\ta\r\u0005\u0006w\r!\t\u0001\u0010\u0005\u0006C\r!\t!\u0010\u0005\u0006\r\u000e!\ta\u0012\u0005\u0007%\u000e\u0011I1A*\t\u0013\u0005u3!!A\u0005\n\u0005}#AC!o]>$\u0018\r^5p]*\t1\"A\u0005tQ\u0006\u0004X\r\\3tg\u000e\u0001Qc\u0001\b&]M\u0019\u0001aD\u000b\u0011\u0005A\u0019R\"A\t\u000b\u0003I\tQa]2bY\u0006L!\u0001F\t\u0003\r\u0005s\u0017PU3g!\t1bD\u0004\u0002\u001899\u0011\u0001dG\u0007\u00023)\u0011!\u0004D\u0001\u0007yI|w\u000e\u001e \n\u0003II!!H\t\u0002\u000fA\f7m[1hK&\u0011q\u0004\t\u0002\r\'\u0016\u0014\u0018.\u00197ju\u0006\u0014G.\u001a\u0006\u0003;E\tQ!\u00199qYf$\u0012a\t\t\u0003I\u0015b\u0001\u0001B\u0003\'\u0001\t\u0007qEA\u0001B#\tA3\u0006\u0005\u0002\u0011S%\u0011!&\u0005\u0002\b\u001d>$\b.\u001b8h!\t\u0001B&\u0003\u0002.#\t\u0019\u0011I\\=\u0005\u000b=\u0002!\u0019A\u0014\u0003\u0003Q\u000b!\"\u00118o_R\fG/[8o!\t\u00114!D\u0001\u000b\'\r\u0019q\u0002\u000e\t\u0003kij\u0011A\u000e\u0006\u0003oa\n!![8\u000b\u0003e\nAA[1wC&\u0011qDN\u0001\u0007y%t\u0017\u000e\u001e \u0015\u0003E*2AP!D)\tyD\t\u0005\u00033\u0001\u0001\u0013\u0005C\u0001\u0013B\t\u00151SA1\u0001(!\t!3\tB\u00030\u000b\t\u0007q\u0005C\u0003F\u000b\u0001\u000fq(\u0001\u0006b]:|G/\u0019;j_:\fA\"\\6B]:|G/\u0019;j_:,2\u0001S&N)\tIe\n\u0005\u00033\u0001)c\u0005C\u0001\u0013L\t\u00151cA1\u0001(!\t!S\nB\u00030\r\t\u0007q\u0005\u0003\u0004F\r\u0011\u0005\ra\u0014\t\u0004!AS\u0015BA)\u0012\u0005!a$-\u001f8b[\u0016t\u0014aC7bi\u0016\u0014\u0018.\u00197ju\u0016,2\u0001V,Z+\u0005)\u0006\u0003\u0002\u001a\u0001-b\u0003\"\u0001J,\u0005\u000b\u0019:!\u0019A\u0014\u0011\u0005\u0011JF!B\u0018\b\u0005\u00049\u0003fA\u0004\\KB\u0011AlY\u0007\u0002;*\u0011alX\u0001\tS:$XM\u001d8bY*\u0011\u0001-Y\u0001\u0007[\u0006\u001c\'o\\:\u000b\u0005\t\f\u0012a\u0002:fM2,7\r^\u0005\u0003Iv\u0013\u0011\"\\1de>LU\u000e\u001d72\u000fy1w-!\u0016\u0002Z-\u0001\u0011\u0007D\u0010gQ*\u001c80a\u0002\u0002\u001a\u0005-\u0012\u0007\u0002\u0013g\u0019%\fQ!\\1de>\fDA\u00064l_F\u001aQ\u0005\\7\u0010\u00035\f\u0013A\\\u0001\f[\u0006\u001c\'o\\#oO&tW-M\u0002&aF|\u0011!]\u0011\u0002e\u0006)co\u000e\u00181A!JW\u000e\u001d7f[\u0016tG/\u001a3!S:\u00043kY1mC\u0002\u0012d&M\u0019/a5j\u0005(K\u0019\u0005-\u0019$\b0M\u0002&kZ|\u0011A^\u0011\u0002o\u0006A\u0011n\u001d\"v]\u0012dW-M\u0002&sj|\u0011A_\r\u0002\u0003E*aC\u001a?\u0002\u0002E\u001aQ% @\u0010\u0003y\f\u0013a`\u0001\u000bSN\u0014E.Y2lE>D\u0018\'B\u0013\u0002\u0004\u0005\u0015qBAA\u00033\u0005\u0001\u0011G\u0002\fg\u0003\u0013\t\t\"M\u0003&\u0003\u0017\tia\u0004\u0002\u0002\u000e\u0005\u0012\u0011qB\u0001\nG2\f7o\u001d(b[\u0016\fT!JA\n\u0003+y!!!\u0006\"\u0005\u0005]\u0011AG:iCB,G.Z:t]\u0005sgn\u001c;bi&|g.T1de>\u001c\u0018G\u0002\fg\u00037\t\u0019#M\u0003&\u0003;\tyb\u0004\u0002\u0002 \u0005\u0012\u0011\u0011E\u0001\u000b[\u0016$\bn\u001c3OC6,\u0017\'B\u0013\u0002&\u0005\u001drBAA\u0014C\t\tI#A\u000bnCR,\'/[1mSj,\u0017I\u001c8pi\u0006$\u0018n\u001c82\rY1\u0017QFA\u001bc\u0015)\u0013qFA\u0019\u001f\t\t\t$\t\u0002\u00024\u0005I1/[4oCR,(/Z\u0019\u0007?\u0019\f9$!\u00122\r\u00112\u0017\u0011HA\u001e\u0013\u0011\tY$!\u0010\u0002\t1K7\u000f\u001e\u0006\u0005\u0003\u007f\t\t%A\u0005j[6,H/\u00192mK*\u0019\u00111I\t\u0002\u0015\r|G\u000e\\3di&|g.\r\u0005 M\u0006\u001d\u0013\u0011JA(c\u0019!c-!\u000f\u0002<E*Q%a\u0013\u0002N=\u0011\u0011QJ\u000f\u0002\u0001E*Q%!\u0015\u0002T=\u0011\u00111K\u000f\u0002\u0003E\u001aa%a\u0016\u0011\u0005\u0011:\u0016g\u0001\u0014\u0002\\A\u0011A%W\u0001\roJLG/\u001a*fa2\f7-\u001a\u000b\u0003\u0003C\u0002B!a\u0019\u0002j5\u0011\u0011Q\r\u0006\u0004\u0003OB\u0014\u0001\u00027b]\u001eLA!a\u001b\u0002f\t1qJ\u00196fGR\u0004
  #12 = Utf8               mkAnnotation
  #13 = Utf8               (Lscala/Function0;)Lshapeless/Annotation;
  #14 = Utf8               <A:Ljava/lang/Object;T:Ljava/lang/Object;>(Lscala/Function0<TA;>;)Lshapeless/Annotation<TA;TT;>;
  #15 = Utf8               annotation
  #16 = Utf8               shapeless/Annotation$
  #17 = Class              #16            // shapeless/Annotation$
  #18 = Utf8               MODULE$
  #19 = Utf8               Lshapeless/Annotation$;
  #20 = NameAndType        #18:#19        // MODULE$:Lshapeless/Annotation$;
  #21 = Fieldref           #17.#20        // shapeless/Annotation$.MODULE$:Lshapeless/Annotation$;
  #22 = NameAndType        #12:#13        // mkAnnotation:(Lscala/Function0;)Lshapeless/Annotation;
  #23 = Methodref          #17.#22        // shapeless/Annotation$.mkAnnotation:(Lscala/Function0;)Lshapeless/Annotation;
  #24 = Utf8               apply
  #25 = Utf8               ()Ljava/lang/Object;
  #26 = Utf8               ()TA;
  #27 = Utf8               Code
  #28 = Utf8               Signature
  #29 = Utf8               MethodParameters
  #30 = Utf8               SourceFile
  #31 = Utf8               RuntimeVisibleAnnotations
  #32 = Utf8               ScalaInlineInfo
  #33 = Utf8               ScalaSig
{
  public static <A extends java.lang.Object, T extends java.lang.Object> shapeless.Annotation<A, T> mkAnnotation(scala.Function0<A>);
    descriptor: (Lscala/Function0;)Lshapeless/Annotation;
    flags: (0x0009) ACC_PUBLIC, ACC_STATIC
    Code:
      stack=2, locals=1, args_size=1
         0: getstatic     #21                 // Field shapeless/Annotation$.MODULE$:Lshapeless/Annotation$;
         3: aload_0
         4: invokevirtual #23                 // Method shapeless/Annotation$.mkAnnotation:(Lscala/Function0;)Lshapeless/Annotation;
         7: areturn
    Signature: #14                          // <A:Ljava/lang/Object;T:Ljava/lang/Object;>(Lscala/Function0<TA;>;)Lshapeless/Annotation<TA;TT;>;
    MethodParameters:
      Name                           Flags
      annotation                     final

  public abstract A apply();
    descriptor: ()Ljava/lang/Object;
    flags: (0x0401) ACC_PUBLIC, ACC_ABSTRACT
    Signature: #26                          // ()TA;
}
Signature: #3                           // <A:Ljava/lang/Object;T:Ljava/lang/Object;>Ljava/lang/Object;Ljava/io/Serializable;
SourceFile: "annotation.scala"
RuntimeVisibleAnnotations:
  0: #9(#10=s#11)
    scala.reflect.ScalaSignature(
      bytes="\u0006\u0005\u00055daB\u0005\u000b!\u0003\r\n!\u0004\u0005\u0006C\u00011\tAI\u0004\u0006a)A\t!\r\u0004\u0006\u0013)A\ta\r\u0005\u0006w\r!\t\u0001\u0010\u0005\u0006C\r!\t!\u0010\u0005\u0006\r\u000e!\ta\u0012\u0005\u0007%\u000e\u0011I1A*\t\u0013\u0005u3!!A\u0005\n\u0005}#AC!o]>$\u0018\r^5p]*\t1\"A\u0005tQ\u0006\u0004X\r\\3tg\u000e\u0001Qc\u0001\b&]M\u0019\u0001aD\u000b\u0011\u0005A\u0019R\"A\t\u000b\u0003I\tQa]2bY\u0006L!\u0001F\t\u0003\r\u0005s\u0017PU3g!\t1bD\u0004\u0002\u001899\u0011\u0001dG\u0007\u00023)\u0011!\u0004D\u0001\u0007yI|w\u000e\u001e \n\u0003II!!H\t\u0002\u000fA\f7m[1hK&\u0011q\u0004\t\u0002\r\'\u0016\u0014\u0018.\u00197ju\u0006\u0014G.\u001a\u0006\u0003;E\tQ!\u00199qYf$\u0012a\t\t\u0003I\u0015b\u0001\u0001B\u0003\'\u0001\t\u0007qEA\u0001B#\tA3\u0006\u0005\u0002\u0011S%\u0011!&\u0005\u0002\b\u001d>$\b.\u001b8h!\t\u0001B&\u0003\u0002.#\t\u0019\u0011I\\=\u0005\u000b=\u0002!\u0019A\u0014\u0003\u0003Q\u000b!\"\u00118o_R\fG/[8o!\t\u00114!D\u0001\u000b\'\r\u0019q\u0002\u000e\t\u0003kij\u0011A\u000e\u0006\u0003oa\n!![8\u000b\u0003e\nAA[1wC&\u0011qDN\u0001\u0007y%t\u0017\u000e\u001e \u0015\u0003E*2AP!D)\tyD\t\u0005\u00033\u0001\u0001\u0013\u0005C\u0001\u0013B\t\u00151SA1\u0001(!\t!3\tB\u00030\u000b\t\u0007q\u0005C\u0003F\u000b\u0001\u000fq(\u0001\u0006b]:|G/\u0019;j_:\fA\"\\6B]:|G/\u0019;j_:,2\u0001S&N)\tIe\n\u0005\u00033\u0001)c\u0005C\u0001\u0013L\t\u00151cA1\u0001(!\t!S\nB\u00030\r\t\u0007q\u0005\u0003\u0004F\r\u0011\u0005\ra\u0014\t\u0004!AS\u0015BA)\u0012\u0005!a$-\u001f8b[\u0016t\u0014aC7bi\u0016\u0014\u0018.\u00197ju\u0016,2\u0001V,Z+\u0005)\u0006\u0003\u0002\u001a\u0001-b\u0003\"\u0001J,\u0005\u000b\u0019:!\u0019A\u0014\u0011\u0005\u0011JF!B\u0018\b\u0005\u00049\u0003fA\u0004\\KB\u0011AlY\u0007\u0002;*\u0011alX\u0001\tS:$XM\u001d8bY*\u0011\u0001-Y\u0001\u0007[\u0006\u001c\'o\\:\u000b\u0005\t\f\u0012a\u0002:fM2,7\r^\u0005\u0003Iv\u0013\u0011\"\\1de>LU\u000e\u001d72\u000fy1w-!\u0016\u0002Z-\u0001\u0011\u0007D\u0010gQ*\u001c80a\u0002\u0002\u001a\u0005-\u0012\u0007\u0002\u0013g\u0019%\fQ!\\1de>\fDA\u00064l_F\u001aQ\u0005\\7\u0010\u00035\f\u0013A\\\u0001\f[\u0006\u001c\'o\\#oO&tW-M\u0002&aF|\u0011!]\u0011\u0002e\u0006)co\u000e\u00181A!JW\u000e\u001d7f[\u0016tG/\u001a3!S:\u00043kY1mC\u0002\u0012d&M\u0019/a5j\u0005(K\u0019\u0005-\u0019$\b0M\u0002&kZ|\u0011A^\u0011\u0002o\u0006A\u0011n\u001d\"v]\u0012dW-M\u0002&sj|\u0011A_\r\u0002\u0003E*aC\u001a?\u0002\u0002E\u001aQ% @\u0010\u0003y\f\u0013a`\u0001\u000bSN\u0014E.Y2lE>D\u0018\'B\u0013\u0002\u0004\u0005\u0015qBAA\u00033\u0005\u0001\u0011G\u0002\fg\u0003\u0013\t\t\"M\u0003&\u0003\u0017\tia\u0004\u0002\u0002\u000e\u0005\u0012\u0011qB\u0001\nG2\f7o\u001d(b[\u0016\fT!JA\n\u0003+y!!!\u0006\"\u0005\u0005]\u0011AG:iCB,G.Z:t]\u0005sgn\u001c;bi&|g.T1de>\u001c\u0018G\u0002\fg\u00037\t\u0019#M\u0003&\u0003;\tyb\u0004\u0002\u0002 \u0005\u0012\u0011\u0011E\u0001\u000b[\u0016$\bn\u001c3OC6,\u0017\'B\u0013\u0002&\u0005\u001drBAA\u0014C\t\tI#A\u000bnCR,\'/[1mSj,\u0017I\u001c8pi\u0006$\u0018n\u001c82\rY1\u0017QFA\u001bc\u0015)\u0013qFA\u0019\u001f\t\t\t$\t\u0002\u00024\u0005I1/[4oCR,(/Z\u0019\u0007?\u0019\f9$!\u00122\r\u00112\u0017\u0011HA\u001e\u0013\u0011\tY$!\u0010\u0002\t1K7\u000f\u001e\u0006\u0005\u0003\u007f\t\t%A\u0005j[6,H/\u00192mK*\u0019\u00111I\t\u0002\u0015\r|G\u000e\\3di&|g.\r\u0005 M\u0006\u001d\u0013\u0011JA(c\u0019!c-!\u000f\u0002<E*Q%a\u0013\u0002N=\u0011\u0011QJ\u000f\u0002\u0001E*Q%!\u0015\u0002T=\u0011\u00111K\u000f\u0002\u0003E\u001aa%a\u0016\u0011\u0005\u0011:\u0016g\u0001\u0014\u0002\\A\u0011A%W\u0001\roJLG/\u001a*fa2\f7-\u001a\u000b\u0003\u0003C\u0002B!a\u0019\u0002j5\u0011\u0011Q\r\u0006\u0004\u0003OB\u0014\u0001\u00027b]\u001eLA!a\u001b\u0002f\t1qJ\u00196fGR\u0004"
    )
  ScalaInlineInfo: length = 0x9 (unknown attribute)
   01 00 00 01 00 18 00 19 00
  ScalaSig: length = 0x3 (unknown attribute)
   05 02 00
