Classfile /Users/mw/Projects/slang-braindump/.jar/jar11/assemble/slang-braindump/assemble/content/shapeless/Annotations$$anon$2.class
  Last modified May 29, 2022; size 995 bytes
  SHA-256 checksum cb08fe6e62251e6a84439c3e6fd27f2181da6864871dcb6b46851b04bbf744f2
  Compiled from "annotation.scala"
public final class shapeless.Annotations$$anon$2 extends java.lang.Object implements shapeless.Annotations<A, T>
  minor version: 0
  major version: 52
  flags: (0x0031) ACC_PUBLIC, ACC_FINAL, ACC_SUPER
  this_class: #2                          // shapeless/Annotations$$anon$2
  super_class: #5                         // java/lang/Object
  interfaces: 1, fields: 1, methods: 3, attributes: 6
Constant pool:
   #1 = Utf8               shapeless/Annotations$$anon$2
   #2 = Class              #1             // shapeless/Annotations$$anon$2
   #3 = Utf8               Ljava/lang/Object;Lshapeless/Annotations<TA;TT;>;
   #4 = Utf8               java/lang/Object
   #5 = Class              #4             // java/lang/Object
   #6 = Utf8               shapeless/Annotations
   #7 = Class              #6             // shapeless/Annotations
   #8 = Utf8               annotation.scala
   #9 = Utf8               shapeless/Annotations$
  #10 = Class              #9             // shapeless/Annotations$
  #11 = Utf8               mkAnnotations
  #12 = Utf8               (Lscala/Function0;)Lshapeless/Annotations;
  #13 = NameAndType        #11:#12        // mkAnnotations:(Lscala/Function0;)Lshapeless/Annotations;
  #14 = Utf8               annotations$1
  #15 = Utf8               Lscala/Function0;
  #16 = Utf8               apply
  #17 = Utf8               ()Lshapeless/HList;
  #18 = Utf8               ()TOut0;
  #19 = NameAndType        #14:#15        // annotations$1:Lscala/Function0;
  #20 = Fieldref           #2.#19         // shapeless/Annotations$$anon$2.annotations$1:Lscala/Function0;
  #21 = Utf8               scala/Function0
  #22 = Class              #21            // scala/Function0
  #23 = Utf8               ()Ljava/lang/Object;
  #24 = NameAndType        #16:#23        // apply:()Ljava/lang/Object;
  #25 = InterfaceMethodref #22.#24        // scala/Function0.apply:()Ljava/lang/Object;
  #26 = Utf8               shapeless/HList
  #27 = Class              #26            // shapeless/HList
  #28 = Utf8               this
  #29 = Utf8               Lshapeless/Annotations$$anon$2;
  #30 = NameAndType        #16:#17        // apply:()Lshapeless/HList;
  #31 = Methodref          #2.#30         // shapeless/Annotations$$anon$2.apply:()Lshapeless/HList;
  #32 = Utf8               <init>
  #33 = Utf8               (Lscala/Function0;)V
  #34 = Utf8               ()V
  #35 = NameAndType        #32:#34        // "<init>":()V
  #36 = Methodref          #5.#35         // java/lang/Object."<init>":()V
  #37 = Utf8               Code
  #38 = Utf8               LineNumberTable
  #39 = Utf8               LocalVariableTable
  #40 = Utf8               Signature
  #41 = Utf8               MethodParameters
  #42 = Utf8               InnerClasses
  #43 = Utf8               EnclosingMethod
  #44 = Utf8               SourceFile
  #45 = Utf8               ScalaInlineInfo
  #46 = Utf8               Scala
{
  private final scala.Function0 annotations$1;
    descriptor: Lscala/Function0;
    flags: (0x0012) ACC_PRIVATE, ACC_FINAL

  public Out0 apply();
    descriptor: ()Lshapeless/HList;
    flags: (0x0001) ACC_PUBLIC
    Code:
      stack=1, locals=1, args_size=1
         0: aload_0
         1: getfield      #20                 // Field annotations$1:Lscala/Function0;
         4: invokeinterface #25,  1           // InterfaceMethod scala/Function0.apply:()Ljava/lang/Object;
         9: checkcast     #27                 // class shapeless/HList
        12: areturn
      LineNumberTable:
        line 114: 0
      LocalVariableTable:
        Start  Length  Slot  Name   Signature
            0      13     0  this   Lshapeless/Annotations$$anon$2;
    Signature: #18                          // ()TOut0;

  public java.lang.Object apply();
    descriptor: ()Ljava/lang/Object;
    flags: (0x1041) ACC_PUBLIC, ACC_BRIDGE, ACC_SYNTHETIC
    Code:
      stack=1, locals=1, args_size=1
         0: aload_0
         1: invokevirtual #31                 // Method apply:()Lshapeless/HList;
         4: areturn
      LineNumberTable:
        line 112: 0
      LocalVariableTable:
        Start  Length  Slot  Name   Signature
            0       5     0  this   Lshapeless/Annotations$$anon$2;

  public shapeless.Annotations$$anon$2(scala.Function0);
    descriptor: (Lscala/Function0;)V
    flags: (0x0001) ACC_PUBLIC
    Code:
      stack=2, locals=2, args_size=2
         0: aload_0
         1: aload_1
         2: putfield      #20                 // Field annotations$1:Lscala/Function0;
         5: aload_0
         6: invokespecial #36                 // Method java/lang/Object."<init>":()V
         9: return
      LineNumberTable:
        line 111: 0
        line 112: 5
      LocalVariableTable:
        Start  Length  Slot  Name   Signature
            0      10     0  this   Lshapeless/Annotations$$anon$2;
            0      10     1 annotations$1   Lscala/Function0;
    MethodParameters:
      Name                           Flags
      annotations$1                  final
}
InnerClasses:
  public final #2;                        // class shapeless/Annotations$$anon$2
EnclosingMethod: #10.#13                // shapeless.Annotations$.mkAnnotations
Signature: #3                           // Ljava/lang/Object;Lshapeless/Annotations<TA;TT;>;
SourceFile: "annotation.scala"
  ScalaInlineInfo: length = 0x13 (unknown attribute)
   01 01 00 03 00 20 00 21 01 00 10 00 17 01 00 10
   00 11 01
  Scala: length = 0x0 (unknown attribute)

