Classfile /Users/mw/Projects/slang-braindump/.jar/jar11/assemble/slang-braindump/assemble/content/shapeless/Cached.class
  Last modified May 29, 2022; size 7598 bytes
  SHA-256 checksum 66f54e0768fa060c4ca4ea671b766916f61216a6b144a1542b9ba55321e9a1ad
  Compiled from "cached.scala"
public final class shapeless.Cached<T extends java.lang.Object> extends java.lang.Object implements scala.Product, java.io.Serializable
  minor version: 0
  major version: 52
  flags: (0x0031) ACC_PUBLIC, ACC_FINAL, ACC_SUPER
  this_class: #2                          // shapeless/Cached
  super_class: #5                         // java/lang/Object
  interfaces: 2, fields: 1, methods: 28, attributes: 5
Constant pool:
    #1 = Utf8               shapeless/Cached
    #2 = Class              #1            // shapeless/Cached
    #3 = Utf8               <T:Ljava/lang/Object;>Ljava/lang/Object;Lscala/Product;Ljava/io/Serializable;
    #4 = Utf8               java/lang/Object
    #5 = Class              #4            // java/lang/Object
    #6 = Utf8               scala/Product
    #7 = Class              #6            // scala/Product
    #8 = Utf8               java/io/Serializable
    #9 = Class              #8            // java/io/Serializable
   #10 = Utf8               cached.scala
   #11 = Utf8               Lscala/reflect/ScalaSignature;
   #12 = Utf8               bytes
   #13 = Utf8               \u0006\u0005\teg\u0001\u0002\u0012$\u0005\u001aB\u0001\"\u0010\u0001\u0003\u0016\u0004%\tA\u0010\u0005\t\u0015\u0002\u0011\t\u0012)A\u0005\u007f!)1\n\u0001C\u0001\u0019\"9\u0001\u000bAA\u0001\n\u0003\t\u0006bB,\u0001#\u0003%\t\u0001\u0017\u0005\bK\u0002\t\t\u0011\"\u0011g\u0011\u001dy\u0007!!A\u0005\u0002ADq\u0001\u001e\u0001\u0002\u0002\u0013\u0005Q\u000fC\u0004y\u0001\u0005\u0005I\u0011I=\t\u0013\u0005\u0005\u0001!!A\u0005\u0002\u0005\r\u0001\"CA\u0007\u0001\u0005\u0005I\u0011IA\b\u0011%\t\u0019\u0002AA\u0001\n\u0003\n)\u0002C\u0005\u0002\u0018\u0001\t\t\u0011\"\u0011\u0002\u001a!I\u0011Q\u0004\u0001\u0002\u0002\u0013\u0005\u0013qD\u0004\b\u0003C\u0019\u0003\u0012AA\u0012\r\u0019\u00113\u0005#\u0001\u0002&!11\n\u0005C\u0001\u0003oA\u0001\"!\u000f\u0011\u0005\u0013\r\u00111\b\u0005\b\u0003C\u0004B\u0011AAr\u0011%\t\t\u0010EA\u0001\n\u0003\u000b\u0019\u0010C\u0005\u0002\u0000B\t\t\u0011\"!\u0003\u0002!I!Q\u0003\t\u0002\u0002\u0013%!q\u0003\u0005\n\u0005?\u0001\u0012\u0011!C\u0003\u0005CA\u0011B!\u000f\u0011#\u0003%)Aa\u000f\t\u0013\t-\u0003#!A\u0005\u0006\t5\u0003\"\u0003B-!\u0005\u0005IQ\u0001B.\u0011%\u00119\u0007EA\u0001\n\u000b\u0011I\u0007C\u0005\u0003zA\t\t\u0011\"\u0002\u0003|!I!q\u0011\t\u0002\u0002\u0013\u0015!\u0011\u0012\u0005\n\u00053\u0003\u0012\u0011!C\u0003\u00057C\u0011Ba+\u0011\u0003\u0003%)A!,\t\u0013\te\u0006#!A\u0005\u0006\tm\u0006\"\u0003Bf!\u0005\u0005IQ\u0001Bg\u0005\u0019\u0019\u0015m\u00195fI*\tA%A\u0005tQ\u0006\u0004X\r\\3tg\u000e\u0001QCA\u0014B\'\u0011\u0001\u0001FL\u0019\u0011\u0005%bS\"\u0001\u0016\u000b\u0003-\nQa]2bY\u0006L!!\f\u0016\u0003\r\u0005s\u0017PV1m!\tIs&\u0003\u00021U\t9\u0001K]8ek\u000e$\bC\u0001\u001a;\u001d\t\u0019\u0004H\u0004\u00025o5\tQG\u0003\u00027K\u00051AH]8pizJ\u0011aK\u0005\u0003s)\nq\u0001]1dW\u0006<W-\u0003\u0002<y\ta1+\u001a:jC2L\'0\u00192mK*\u0011\u0011HK\u0001\u0006m\u0006dW/Z\u000b\u0002\u007fA\u0011\u0001)\u0011\u0007\u0001\t\u0019\u0011\u0005\u0001\"b\u0001\u0007\n\tA+\u0005\u0002E\u000fB\u0011\u0011&R\u0005\u0003\r*\u0012qAT8uQ&tw\r\u0005\u0002*\u0011&\u0011\u0011J\u000b\u0002\u0004\u0003:L\u0018A\u0002<bYV,\u0007%\u0001\u0004=S:LGO\u0010\u000b\u0003\u001b>\u00032A\u0014\u0001@\u001b\u0005\u0019\u0003\"B\u001f\u0004\u0001\u0004y\u0014\u0001B2paf,\"AU+\u0015\u0005M3\u0006c\u0001(\u0001)B\u0011\u0001)\u0016\u0003\u0006\u0005\u0012\u0011\ra\u0011\u0005\b{\u0011\u0001\n\u00111\u0001U\u00039\u0019w\u000e]=%I\u00164\u0017-\u001e7uIE*\"!\u00173\u0016\u0003iS#aP.,\u0003q\u0003\"!\u00182\u000e\u0003yS!a\u00181\u0002\u0013Ut7\r[3dW\u0016$\'BA1+\u0003)\tgN\\8uCRLwN\\\u0005\u0003Gz\u0013\u0011#\u001e8dQ\u0016\u001c7.\u001a3WCJL\u0017M\\2f\t\u0015\u0011UA1\u0001D\u00035\u0001(o\u001c3vGR\u0004&/\u001a4jqV\tq\r\u0005\u0002i[6\t\u0011N\u0003\u0002kW\u0006!A.\u00198h\u0015\u0005a\u0017\u0001\u00026bm\u0006L!A\\5\u0003\rM#(/\u001b8h\u00031\u0001(o\u001c3vGR\f%/\u001b;z+\u0005\t\bCA\u0015s\u0013\t\u0019(FA\u0002J]R\fa\u0002\u001d:pIV\u001cG/\u00127f[\u0016tG\u000f\u0006\u0002Hm\"9q\u000fCA\u0001\u0002\u0004\t\u0018a\u0001=%c\u0005y\u0001O]8ek\u000e$\u0018\n^3sCR|\'/F\u0001{!\rYhpR\u0007\u0002y*\u0011QPK\u0001\u000bG>dG.Z2uS>t\u0017BA@}\u0005!IE/\u001a:bi>\u0014\u0018\u0001C2b]\u0016\u000bX/\u00197\u0015\t\u0005\u0015\u00111\u0002\t\u0004S\u0005\u001d\u0011bAA\u0005U\t9!i\\8mK\u0006t\u0007bB<\u000b\u0003\u0003\u0005\raR\u0001\u0013aJ|G-^2u\u000b2,W.\u001a8u\u001d\u0006lW\rF\u0002h\u0003#Aqa^\u0006\u0002\u0002\u0003\u0007\u0011/\u0001\u0005iCND7i\u001c3f)\u0005\t\u0018AB3rk\u0006d7\u000f\u0006\u0003\u0002\u0006\u0005m\u0001bB<\u000e\u0003\u0003\u0005\raR\u0001\ti>\u001cFO]5oOR\tq-\u0001\u0004DC\u000eDW\r\u001a\t\u0003\u001dB\u0019R\u0001EA\u0014\u0003[\u00012!KA\u0015\u0013\r\tYC\u000b\u0002\u0007\u0003:L(+\u001a4\u0011\t\u0005=\u0012QG\u0007\u0003\u0003cQ1!a\rl\u0003\tIw.C\u0002<\u0003c!\"!a\t\u0002\u00175\fG/\u001a:jC2L\'0Z\u000b\u0005\u0003{\t\u0019%\u0006\u0002\u0002@A!a\nAA!!\r\u0001\u00151\t\u0003\u0007\u0003\u000b\u0012\"\u0019A\"\u0003\u0003%CSAEA%\u0003;\u0002B!a\u0013\u0002Z5\u0011\u0011Q\n\u0006\u0005\u0003\u001f\n\t&\u0001\u0005j]R,\'O\\1m\u0015\u0011\t\u0019&!\u0016\u0002\r5\f7M]8t\u0015\r\t9FK\u0001\be\u00164G.Z2u\u0013\u0011\tY&!\u0014\u0003\u00135\f7M]8J[Bd\u0017g\u0002\u0010\u0002`\u0005\u0005\u0014Q\\\u0006\u0001cEy\u0012qLA2\u0003O\nI(!#\u0002\u001a\u0006-\u0016QX\u0019\u0007I\u0005}S%!\u001a\u0002\u000b5\f7M]82\u000fY\ty&!\u001b\u0002rE*Q%a\u001b\u0002n=\u0011\u0011QN\u0011\u0003\u0003_\n1\"\\1de>,enZ5oKF*Q%a\u001d\u0002v=\u0011\u0011QO\u0011\u0003\u0003o\nQE^\u001c/a\u0001B\u0013.\u001c9mK6,g\u000e^3eA%t\u0007eU2bY\u0006\u0004#GL\u00192]AjS\nO\u00152\u000fY\ty&a\u001f\u0002\u0004F*Q%! \u0002\u0000=\u0011\u0011qP\u0011\u0003\u0003\u0003\u000b\u0001\"[:Ck:$G.Z\u0019\u0006K\u0005\u0015\u0015qQ\b\u0003\u0003\u000fK\u0012!A\u0019\b-\u0005}\u00131RAJc\u0015)\u0013QRAH\u001f\t\ty)\t\u0002\u0002\u0012\u0006Q\u0011n\u001d\"mC\u000e\\\'m\u001c=2\u000b\u0015\n)*a&\u0010\u0005\u0005]\u0015$\u0001\u00012\u000fY\ty&a\'\u0002$F*Q%!(\u0002 >\u0011\u0011qT\u0011\u0003\u0003C\u000b\u0011b\u00197bgNt\u0015-\\32\u000b\u0015\n)+a*\u0010\u0005\u0005\u001d\u0016EAAU\u0003Y\u0019\b.\u00199fY\u0016\u001c8OL\"bG\",G-T1de>\u001c\u0018g\u0002\f\u0002`\u00055\u0016QW\u0019\u0006K\u0005=\u0016\u0011W\b\u0003\u0003c\u000b#!a-\u0002\u00155,G\u000f[8e\u001d\u0006lW-M\u0003&\u0003o\u000bIl\u0004\u0002\u0002:\u0006\u0012\u00111X\u0001\u0012[\u0006$XM]5bY&TXmQ1dQ\u0016$\u0017g\u0002\f\u0002`\u0005}\u0016qY\u0019\u0006K\u0005\u0005\u00171Y\b\u0003\u0003\u0007\f#!!2\u0002\u0013MLwM\\1ukJ,\u0017gB\u0010\u0002`\u0005%\u00171[\u0019\bI\u0005}\u00131ZAg\u0013\u0011\ti-a4\u0002\t1K7\u000f\u001e\u0006\u0004\u0003#d\u0018!C5n[V$\u0018M\u00197fc\u001dy\u0012qLAk\u0003/\ft\u0001JA0\u0003\u0017\fi-M\u0003&\u00033\fYn\u0004\u0002\u0002\\v\t\u0001!M\u0002\'\u0003?\u00042\u0001QA\"\u0003)IW\u000e\u001d7jG&$H._\u000b\u0005\u0003K\fI\u000f\u0006\u0003\u0002h\u0006-\bc\u0001!\u0002j\u0012)!i\u0005b\u0001\u0007\"9\u0011Q^\nA\u0004\u0005=\u0018AB2bG\",G\r\u0005\u0003O\u0001\u0005\u001d\u0018!B1qa2LX\u0003BA{\u0003w$B!a>\u0002~B!a\nAA}!\r\u0001\u00151 \u0003\u0006\u0005R\u0011\ra\u0011\u0005\u0007{Q\u0001\r!!?\u0002\u000fUt\u0017\r\u001d9msV!!1\u0001B\u0007)\u0011\u0011)Aa\u0004\u0011\u000b%\u00129Aa\u0003\n\u0007\t%!F\u0001\u0004PaRLwN\u001c\t\u0004\u0001\n5A!\u0002\"\u0016\u0005\u0004\u0019\u0005\"\u0003B\t+\u0005\u0005\t\u0019\u0001B\n\u0003\rAH\u0005\r\t\u0005\u001d\u0002\u0011Y!\u0001\u0007xe&$XMU3qY\u0006\u001cW\r\u0006\u0002\u0003\u001aA\u0019\u0001Na\u0007\n\u0007\tu\u0011N\u0001\u0004PE*,7\r^\u0001\u000fG>\u0004\u0018\u0010J3yi\u0016t7/[8o+\u0019\u0011\u0019Ca\u000b\u00038Q!!Q\u0005B\u0018)\u0011\u00119C!\f\u0011\t9\u0003!\u0011\u0006\t\u0004\u0001\n-B!\u0002\"\u0018\u0005\u0004\u0019\u0005\u0002C\u001f\u0018!\u0003\u0005\rA!\u000b\t\u000f\tEr\u00031\u0001\u00034\u0005)A\u0005\u001e5jgB!a\n\u0001B\u001b!\r\u0001%q\u0007\u0003\u0006\u0005^\u0011\raQ\u0001\u0019G>\u0004\u0018\u0010\n3fM\u0006,H\u000e\u001e\u00132I\u0015DH/\u001a8tS>tWC\u0002B\u001f\u0005\u0013\u0012\u0019\u0005\u0006\u0003\u0003@\t\u0015#f\u0001B!7B\u0019\u0001Ia\u0011\u0005\u000b\tC\"\u0019A\"\t\u000f\tE\u0002\u00041\u0001\u0003HA!a\n\u0001B!\t\u0015\u0011\u0005D1\u0001D\u0003]\u0001(o\u001c3vGR\u0004&/\u001a4jq\u0012*\u0007\u0010^3og&|g.\u0006\u0003\u0003P\t]CcA4\u0003R!9!\u0011G\rA\u0002\tM\u0003\u0003\u0002(\u0001\u0005+\u00022\u0001\u0011B,\t\u0015\u0011\u0015D1\u0001D\u0003Y\u0001(o\u001c3vGR\f%/\u001b;zI\u0015DH/\u001a8tS>tW\u0003\u0002B/\u0005K\"2!\u001dB0\u0011\u001d\u0011\tD\u0007a\u0001\u0005C\u0002BA\u0014\u0001\u0003dA\u0019\u0001I!\u001a\u0005\u000b\tS\"\u0019A\"\u00021A\u0014x\u000eZ;di\u0016cW-\\3oi\u0012*\u0007\u0010^3og&|g.\u0006\u0003\u0003l\t]D\u0003\u0002B7\u0005c\"2a\u0012B8\u0011\u001d98$!AA\u0002EDqA!\r\u001c\u0001\u0004\u0011\u0019\b\u0005\u0003O\u0001\tU\u0004c\u0001!\u0003x\u0011)!i\u0007b\u0001\u0007\u0006I\u0002O]8ek\u000e$\u0018\n^3sCR|\'\u000fJ3yi\u0016t7/[8o+\u0011\u0011iH!\"\u0015\u0007i\u0014y\bC\u0004\u00032q\u0001\rA!!\u0011\t9\u0003!1\u0011\t\u0004\u0001\n\u0015E!\u0002\"\u001d\u0005\u0004\u0019\u0015AE2b]\u0016\u000bX/\u00197%Kb$XM\\:j_:,BAa#\u0003\u0018R!!Q\u0012BI)\u0011\t)Aa$\t\u000f]l\u0012\u0011!a\u0001\u000f\"9!\u0011G\u000fA\u0002\tM\u0005\u0003\u0002(\u0001\u0005+\u00032\u0001\u0011BL\t\u0015\u0011UD1\u0001D\u0003q\u0001(o\u001c3vGR,E.Z7f]Rt\u0015-\\3%Kb$XM\\:j_:,BA!(\u0003*R!!q\u0014BR)\r9\'\u0011\u0015\u0005\boz\t\t\u00111\u0001r\u0011\u001d\u0011\tD\ba\u0001\u0005K\u0003BA\u0014\u0001\u0003(B\u0019\u0001I!+\u0005\u000b\ts\"\u0019A\"\u0002%!\f7\u000f[\"pI\u0016$S\r\u001f;f]NLwN\\\u000b\u0005\u0005_\u00139\f\u0006\u0003\u0002\u0016\tE\u0006b\u0002B\u0019?\u0001\u0007!1\u0017\t\u0005\u001d\u0002\u0011)\fE\u0002A\u0005o#QAQ\u0010C\u0002\r\u000b\u0001#Z9vC2\u001cH%\u001a=uK:\u001c\u0018n\u001c8\u0016\t\tu&\u0011\u001a\u000b\u0005\u0005\u007f\u0013\u0019\r\u0006\u0003\u0002\u0006\t\u0005\u0007bB<!\u0003\u0003\u0005\ra\u0012\u0005\b\u0005c\u0001\u0003\u0019\u0001Bc!\u0011q\u0005Aa2\u0011\u0007\u0001\u0013I\rB\u0003CA\t\u00071)\u0001\nu_N#(/\u001b8hI\u0015DH/\u001a8tS>tW\u0003\u0002Bh\u0005/$B!a\b\u0003R\"9!\u0011G\u0011A\u0002\tM\u0007\u0003\u0002(\u0001\u0005+\u00042\u0001\u0011Bl\t\u0015\u0011\u0015E1\u0001D\u0001
   #14 = Utf8               value
   #15 = Utf8               Ljava/lang/Object;
   #16 = Utf8               TT;
   #17 = Utf8               toString$extension
   #18 = Utf8               (Ljava/lang/Object;)Ljava/lang/String;
   #19 = Utf8               <T:Ljava/lang/Object;>(TT;)Ljava/lang/String;
   #20 = Utf8               $this
   #21 = Utf8               shapeless/Cached$
   #22 = Class              #21           // shapeless/Cached$
   #23 = Utf8               MODULE$
   #24 = Utf8               Lshapeless/Cached$;
   #25 = NameAndType        #23:#24       // MODULE$:Lshapeless/Cached$;
   #26 = Fieldref           #22.#25       // shapeless/Cached$.MODULE$:Lshapeless/Cached$;
   #27 = NameAndType        #17:#18       // toString$extension:(Ljava/lang/Object;)Ljava/lang/String;
   #28 = Methodref          #22.#27       // shapeless/Cached$.toString$extension:(Ljava/lang/Object;)Ljava/lang/String;
   #29 = Utf8               equals$extension
   #30 = Utf8               (Ljava/lang/Object;Ljava/lang/Object;)Z
   #31 = Utf8               <T:Ljava/lang/Object;>(TT;Ljava/lang/Object;)Z
   #32 = Utf8               x$1
   #33 = NameAndType        #29:#30       // equals$extension:(Ljava/lang/Object;Ljava/lang/Object;)Z
   #34 = Methodref          #22.#33       // shapeless/Cached$.equals$extension:(Ljava/lang/Object;Ljava/lang/Object;)Z
   #35 = Utf8               hashCode$extension
   #36 = Utf8               (Ljava/lang/Object;)I
   #37 = Utf8               <T:Ljava/lang/Object;>(TT;)I
   #38 = NameAndType        #35:#36       // hashCode$extension:(Ljava/lang/Object;)I
   #39 = Methodref          #22.#38       // shapeless/Cached$.hashCode$extension:(Ljava/lang/Object;)I
   #40 = Utf8               productElementName$extension
   #41 = Utf8               (Ljava/lang/Object;I)Ljava/lang/String;
   #42 = Utf8               <T:Ljava/lang/Object;>(TT;I)Ljava/lang/String;
   #43 = NameAndType        #40:#41       // productElementName$extension:(Ljava/lang/Object;I)Ljava/lang/String;
   #44 = Methodref          #22.#43       // shapeless/Cached$.productElementName$extension:(Ljava/lang/Object;I)Ljava/lang/String;
   #45 = Utf8               canEqual$extension
   #46 = NameAndType        #45:#30       // canEqual$extension:(Ljava/lang/Object;Ljava/lang/Object;)Z
   #47 = Methodref          #22.#46       // shapeless/Cached$.canEqual$extension:(Ljava/lang/Object;Ljava/lang/Object;)Z
   #48 = Utf8               productIterator$extension
   #49 = Utf8               (Ljava/lang/Object;)Lscala/collection/Iterator;
   #50 = Utf8               <T:Ljava/lang/Object;>(TT;)Lscala/collection/Iterator<Ljava/lang/Object;>;
   #51 = NameAndType        #48:#49       // productIterator$extension:(Ljava/lang/Object;)Lscala/collection/Iterator;
   #52 = Methodref          #22.#51       // shapeless/Cached$.productIterator$extension:(Ljava/lang/Object;)Lscala/collection/Iterator;
   #53 = Utf8               productElement$extension
   #54 = Utf8               (Ljava/lang/Object;I)Ljava/lang/Object;
   #55 = Utf8               <T:Ljava/lang/Object;>(TT;I)Ljava/lang/Object;
   #56 = NameAndType        #53:#54       // productElement$extension:(Ljava/lang/Object;I)Ljava/lang/Object;
   #57 = Methodref          #22.#56       // shapeless/Cached$.productElement$extension:(Ljava/lang/Object;I)Ljava/lang/Object;
   #58 = Utf8               productArity$extension
   #59 = NameAndType        #58:#36       // productArity$extension:(Ljava/lang/Object;)I
   #60 = Methodref          #22.#59       // shapeless/Cached$.productArity$extension:(Ljava/lang/Object;)I
   #61 = Utf8               productPrefix$extension
   #62 = NameAndType        #61:#18       // productPrefix$extension:(Ljava/lang/Object;)Ljava/lang/String;
   #63 = Methodref          #22.#62       // shapeless/Cached$.productPrefix$extension:(Ljava/lang/Object;)Ljava/lang/String;
   #64 = Utf8               copy$default$1$extension
   #65 = Utf8               (Ljava/lang/Object;)Ljava/lang/Object;
   #66 = Utf8               <T:Ljava/lang/Object;T:Ljava/lang/Object;>(TT;)TT;
   #67 = NameAndType        #64:#65       // copy$default$1$extension:(Ljava/lang/Object;)Ljava/lang/Object;
   #68 = Methodref          #22.#67       // shapeless/Cached$.copy$default$1$extension:(Ljava/lang/Object;)Ljava/lang/Object;
   #69 = Utf8               copy$extension
   #70 = Utf8               (Ljava/lang/Object;Ljava/lang/Object;)Ljava/lang/Object;
   #71 = NameAndType        #69:#70       // copy$extension:(Ljava/lang/Object;Ljava/lang/Object;)Ljava/lang/Object;
   #72 = Methodref          #22.#71       // shapeless/Cached$.copy$extension:(Ljava/lang/Object;Ljava/lang/Object;)Ljava/lang/Object;
   #73 = Utf8               unapply
   #74 = Utf8               (Ljava/lang/Object;)Lscala/Option;
   #75 = Utf8               <T:Ljava/lang/Object;>(TT;)Lscala/Option<TT;>;
   #76 = Utf8               x$0
   #77 = NameAndType        #73:#74       // unapply:(Ljava/lang/Object;)Lscala/Option;
   #78 = Methodref          #22.#77       // shapeless/Cached$.unapply:(Ljava/lang/Object;)Lscala/Option;
   #79 = Utf8               apply
   #80 = NameAndType        #79:#65       // apply:(Ljava/lang/Object;)Ljava/lang/Object;
   #81 = Methodref          #22.#80       // shapeless/Cached$.apply:(Ljava/lang/Object;)Ljava/lang/Object;
   #82 = Utf8               implicitly
   #83 = Utf8               <T:Ljava/lang/Object;>(TT;)TT;
   #84 = Utf8               cached
   #85 = NameAndType        #82:#65       // implicitly:(Ljava/lang/Object;)Ljava/lang/Object;
   #86 = Methodref          #22.#85       // shapeless/Cached$.implicitly:(Ljava/lang/Object;)Ljava/lang/Object;
   #87 = Utf8               productElementNames
   #88 = Utf8               ()Lscala/collection/Iterator;
   #89 = Utf8               ()Lscala/collection/Iterator<Ljava/lang/String;>;
   #90 = Utf8               productElementNames$
   #91 = Utf8               (Lscala/Product;)Lscala/collection/Iterator;
   #92 = NameAndType        #90:#91       // productElementNames$:(Lscala/Product;)Lscala/collection/Iterator;
   #93 = InterfaceMethodref #7.#92        // scala/Product.productElementNames$:(Lscala/Product;)Lscala/collection/Iterator;
   #94 = Utf8               this
   #95 = Utf8               Lshapeless/Cached;
   #96 = Utf8               ()Ljava/lang/Object;
   #97 = Utf8               ()TT;
   #98 = NameAndType        #14:#15       // value:Ljava/lang/Object;
   #99 = Fieldref           #2.#98        // shapeless/Cached.value:Ljava/lang/Object;
  #100 = Utf8               copy
  #101 = NameAndType        #14:#96       // value:()Ljava/lang/Object;
  #102 = Methodref          #2.#101       // shapeless/Cached.value:()Ljava/lang/Object;
  #103 = Utf8               copy$default$1
  #104 = Utf8               <T:Ljava/lang/Object;>()TT;
  #105 = Utf8               productPrefix
  #106 = Utf8               ()Ljava/lang/String;
  #107 = Utf8               productArity
  #108 = Utf8               ()I
  #109 = Utf8               productElement
  #110 = Utf8               (I)Ljava/lang/Object;
  #111 = Utf8               I
  #112 = Utf8               productIterator
  #113 = Utf8               ()Lscala/collection/Iterator<Ljava/lang/Object;>;
  #114 = Utf8               canEqual
  #115 = Utf8               (Ljava/lang/Object;)Z
  #116 = Utf8               productElementName
  #117 = Utf8               (I)Ljava/lang/String;
  #118 = Utf8               hashCode
  #119 = Utf8               equals
  #120 = Utf8               toString
  #121 = Utf8               <init>
  #122 = Utf8               (Ljava/lang/Object;)V
  #123 = Utf8               (TT;)V
  #124 = Utf8               ()V
  #125 = NameAndType        #121:#124     // "<init>":()V
  #126 = Methodref          #5.#125       // java/lang/Object."<init>":()V
  #127 = Utf8               $init$
  #128 = Utf8               (Lscala/Product;)V
  #129 = NameAndType        #127:#128     // $init$:(Lscala/Product;)V
  #130 = InterfaceMethodref #7.#129       // scala/Product.$init$:(Lscala/Product;)V
  #131 = Utf8               Signature
  #132 = Utf8               Code
  #133 = Utf8               MethodParameters
  #134 = Utf8               LineNumberTable
  #135 = Utf8               LocalVariableTable
  #136 = Utf8               SourceFile
  #137 = Utf8               RuntimeVisibleAnnotations
  #138 = Utf8               ScalaInlineInfo
  #139 = Utf8               ScalaSig
{
  private final T value;
    descriptor: Ljava/lang/Object;
    flags: (0x0012) ACC_PRIVATE, ACC_FINAL
    Signature: #16                          // TT;

  public static <T extends java.lang.Object> java.lang.String toString$extension(T);
    descriptor: (Ljava/lang/Object;)Ljava/lang/String;
    flags: (0x0009) ACC_PUBLIC, ACC_STATIC
    Code:
      stack=2, locals=1, args_size=1
         0: getstatic     #26                 // Field shapeless/Cached$.MODULE$:Lshapeless/Cached$;
         3: aload_0
         4: invokevirtual #28                 // Method shapeless/Cached$.toString$extension:(Ljava/lang/Object;)Ljava/lang/String;
         7: areturn
    Signature: #19                          // <T:Ljava/lang/Object;>(TT;)Ljava/lang/String;
    MethodParameters:
      Name                           Flags
      $this                          final

  public static <T extends java.lang.Object> boolean equals$extension(T, java.lang.Object);
    descriptor: (Ljava/lang/Object;Ljava/lang/Object;)Z
    flags: (0x0009) ACC_PUBLIC, ACC_STATIC
    Code:
      stack=3, locals=2, args_size=2
         0: getstatic     #26                 // Field shapeless/Cached$.MODULE$:Lshapeless/Cached$;
         3: aload_0
         4: aload_1
         5: invokevirtual #34                 // Method shapeless/Cached$.equals$extension:(Ljava/lang/Object;Ljava/lang/Object;)Z
         8: ireturn
    Signature: #31                          // <T:Ljava/lang/Object;>(TT;Ljava/lang/Object;)Z
    MethodParameters:
      Name                           Flags
      $this                          final
      x$1                            final

  public static <T extends java.lang.Object> int hashCode$extension(T);
    descriptor: (Ljava/lang/Object;)I
    flags: (0x0009) ACC_PUBLIC, ACC_STATIC
    Code:
      stack=2, locals=1, args_size=1
         0: getstatic     #26                 // Field shapeless/Cached$.MODULE$:Lshapeless/Cached$;
         3: aload_0
         4: invokevirtual #39                 // Method shapeless/Cached$.hashCode$extension:(Ljava/lang/Object;)I
         7: ireturn
    Signature: #37                          // <T:Ljava/lang/Object;>(TT;)I
    MethodParameters:
      Name                           Flags
      $this                          final

  public static <T extends java.lang.Object> java.lang.String productElementName$extension(T, int);
    descriptor: (Ljava/lang/Object;I)Ljava/lang/String;
    flags: (0x0009) ACC_PUBLIC, ACC_STATIC
    Code:
      stack=3, locals=2, args_size=2
         0: getstatic     #26                 // Field shapeless/Cached$.MODULE$:Lshapeless/Cached$;
         3: aload_0
         4: iload_1
         5: invokevirtual #44                 // Method shapeless/Cached$.productElementName$extension:(Ljava/lang/Object;I)Ljava/lang/String;
         8: areturn
    Signature: #42                          // <T:Ljava/lang/Object;>(TT;I)Ljava/lang/String;
    MethodParameters:
      Name                           Flags
      $this                          final
      x$1                            final

  public static <T extends java.lang.Object> boolean canEqual$extension(T, java.lang.Object);
    descriptor: (Ljava/lang/Object;Ljava/lang/Object;)Z
    flags: (0x0009) ACC_PUBLIC, ACC_STATIC
    Code:
      stack=3, locals=2, args_size=2
         0: getstatic     #26                 // Field shapeless/Cached$.MODULE$:Lshapeless/Cached$;
         3: aload_0
         4: aload_1
         5: invokevirtual #47                 // Method shapeless/Cached$.canEqual$extension:(Ljava/lang/Object;Ljava/lang/Object;)Z
         8: ireturn
    Signature: #31                          // <T:Ljava/lang/Object;>(TT;Ljava/lang/Object;)Z
    MethodParameters:
      Name                           Flags
      $this                          final
      x$1                            final

  public static <T extends java.lang.Object> scala.collection.Iterator<java.lang.Object> productIterator$extension(T);
    descriptor: (Ljava/lang/Object;)Lscala/collection/Iterator;
    flags: (0x0009) ACC_PUBLIC, ACC_STATIC
    Code:
      stack=2, locals=1, args_size=1
         0: getstatic     #26                 // Field shapeless/Cached$.MODULE$:Lshapeless/Cached$;
         3: aload_0
         4: invokevirtual #52                 // Method shapeless/Cached$.productIterator$extension:(Ljava/lang/Object;)Lscala/collection/Iterator;
         7: areturn
    Signature: #50                          // <T:Ljava/lang/Object;>(TT;)Lscala/collection/Iterator<Ljava/lang/Object;>;
    MethodParameters:
      Name                           Flags
      $this                          final

  public static <T extends java.lang.Object> java.lang.Object productElement$extension(T, int);
    descriptor: (Ljava/lang/Object;I)Ljava/lang/Object;
    flags: (0x0009) ACC_PUBLIC, ACC_STATIC
    Code:
      stack=3, locals=2, args_size=2
         0: getstatic     #26                 // Field shapeless/Cached$.MODULE$:Lshapeless/Cached$;
         3: aload_0
         4: iload_1
         5: invokevirtual #57                 // Method shapeless/Cached$.productElement$extension:(Ljava/lang/Object;I)Ljava/lang/Object;
         8: areturn
    Signature: #55                          // <T:Ljava/lang/Object;>(TT;I)Ljava/lang/Object;
    MethodParameters:
      Name                           Flags
      $this                          final
      x$1                            final

  public static <T extends java.lang.Object> int productArity$extension(T);
    descriptor: (Ljava/lang/Object;)I
    flags: (0x0009) ACC_PUBLIC, ACC_STATIC
    Code:
      stack=2, locals=1, args_size=1
         0: getstatic     #26                 // Field shapeless/Cached$.MODULE$:Lshapeless/Cached$;
         3: aload_0
         4: invokevirtual #60                 // Method shapeless/Cached$.productArity$extension:(Ljava/lang/Object;)I
         7: ireturn
    Signature: #37                          // <T:Ljava/lang/Object;>(TT;)I
    MethodParameters:
      Name                           Flags
      $this                          final

  public static <T extends java.lang.Object> java.lang.String productPrefix$extension(T);
    descriptor: (Ljava/lang/Object;)Ljava/lang/String;
    flags: (0x0009) ACC_PUBLIC, ACC_STATIC
    Code:
      stack=2, locals=1, args_size=1
         0: getstatic     #26                 // Field shapeless/Cached$.MODULE$:Lshapeless/Cached$;
         3: aload_0
         4: invokevirtual #63                 // Method shapeless/Cached$.productPrefix$extension:(Ljava/lang/Object;)Ljava/lang/String;
         7: areturn
    Signature: #19                          // <T:Ljava/lang/Object;>(TT;)Ljava/lang/String;
    MethodParameters:
      Name                           Flags
      $this                          final

  public static <T extends java.lang.Object, T extends java.lang.Object> T copy$default$1$extension(T);
    descriptor: (Ljava/lang/Object;)Ljava/lang/Object;
    flags: (0x0009) ACC_PUBLIC, ACC_STATIC
    Code:
      stack=2, locals=1, args_size=1
         0: getstatic     #26                 // Field shapeless/Cached$.MODULE$:Lshapeless/Cached$;
         3: aload_0
         4: invokevirtual #68                 // Method shapeless/Cached$.copy$default$1$extension:(Ljava/lang/Object;)Ljava/lang/Object;
         7: areturn
    Signature: #66                          // <T:Ljava/lang/Object;T:Ljava/lang/Object;>(TT;)TT;
    MethodParameters:
      Name                           Flags
      $this                          final

  public static java.lang.Object copy$extension(java.lang.Object, java.lang.Object);
    descriptor: (Ljava/lang/Object;Ljava/lang/Object;)Ljava/lang/Object;
    flags: (0x0009) ACC_PUBLIC, ACC_STATIC
    Code:
      stack=3, locals=2, args_size=2
         0: getstatic     #26                 // Field shapeless/Cached$.MODULE$:Lshapeless/Cached$;
         3: aload_0
         4: aload_1
         5: invokevirtual #72                 // Method shapeless/Cached$.copy$extension:(Ljava/lang/Object;Ljava/lang/Object;)Ljava/lang/Object;
         8: areturn
    MethodParameters:
      Name                           Flags
      $this                          final
      value                          final

  public static <T extends java.lang.Object> scala.Option<T> unapply(T);
    descriptor: (Ljava/lang/Object;)Lscala/Option;
    flags: (0x0009) ACC_PUBLIC, ACC_STATIC
    Code:
      stack=2, locals=1, args_size=1
         0: getstatic     #26                 // Field shapeless/Cached$.MODULE$:Lshapeless/Cached$;
         3: aload_0
         4: invokevirtual #78                 // Method shapeless/Cached$.unapply:(Ljava/lang/Object;)Lscala/Option;
         7: areturn
    Signature: #75                          // <T:Ljava/lang/Object;>(TT;)Lscala/Option<TT;>;
    MethodParameters:
      Name                           Flags
      x$0                            final

  public static java.lang.Object apply(java.lang.Object);
    descriptor: (Ljava/lang/Object;)Ljava/lang/Object;
    flags: (0x0009) ACC_PUBLIC, ACC_STATIC
    Code:
      stack=2, locals=1, args_size=1
         0: getstatic     #26                 // Field shapeless/Cached$.MODULE$:Lshapeless/Cached$;
         3: aload_0
         4: invokevirtual #81                 // Method shapeless/Cached$.apply:(Ljava/lang/Object;)Ljava/lang/Object;
         7: areturn
    MethodParameters:
      Name                           Flags
      value                          final

  public static <T extends java.lang.Object> T implicitly(T);
    descriptor: (Ljava/lang/Object;)Ljava/lang/Object;
    flags: (0x0009) ACC_PUBLIC, ACC_STATIC
    Code:
      stack=2, locals=1, args_size=1
         0: getstatic     #26                 // Field shapeless/Cached$.MODULE$:Lshapeless/Cached$;
         3: aload_0
         4: invokevirtual #86                 // Method shapeless/Cached$.implicitly:(Ljava/lang/Object;)Ljava/lang/Object;
         7: areturn
    Signature: #83                          // <T:Ljava/lang/Object;>(TT;)TT;
    MethodParameters:
      Name                           Flags
      cached                         final

  public scala.collection.Iterator<java.lang.String> productElementNames();
    descriptor: ()Lscala/collection/Iterator;
    flags: (0x0001) ACC_PUBLIC
    Code:
      stack=1, locals=1, args_size=1
         0: aload_0
         1: invokestatic  #93                 // InterfaceMethod scala/Product.productElementNames$:(Lscala/Product;)Lscala/collection/Iterator;
         4: areturn
      LineNumberTable:
        line 54: 0
      LocalVariableTable:
        Start  Length  Slot  Name   Signature
            0       5     0  this   Lshapeless/Cached;
    Signature: #89                          // ()Lscala/collection/Iterator<Ljava/lang/String;>;

  public T value();
    descriptor: ()Ljava/lang/Object;
    flags: (0x0001) ACC_PUBLIC
    Code:
      stack=1, locals=1, args_size=1
         0: aload_0
         1: getfield      #99                 // Field value:Ljava/lang/Object;
         4: areturn
      LineNumberTable:
        line 54: 0
      LocalVariableTable:
        Start  Length  Slot  Name   Signature
            0       5     0  this   Lshapeless/Cached;
    Signature: #97                          // ()TT;

  public <T extends java.lang.Object> T copy(T);
    descriptor: (Ljava/lang/Object;)Ljava/lang/Object;
    flags: (0x0001) ACC_PUBLIC
    Code:
      stack=3, locals=2, args_size=2
         0: getstatic     #26                 // Field shapeless/Cached$.MODULE$:Lshapeless/Cached$;
         3: aload_0
         4: invokevirtual #102                // Method value:()Ljava/lang/Object;
         7: aload_1
         8: invokevirtual #72                 // Method shapeless/Cached$.copy$extension:(Ljava/lang/Object;Ljava/lang/Object;)Ljava/lang/Object;
        11: areturn
      LineNumberTable:
        line 54: 0
      LocalVariableTable:
        Start  Length  Slot  Name   Signature
            0      12     0  this   Lshapeless/Cached;
            0      12     1 value   Ljava/lang/Object;
    Signature: #83                          // <T:Ljava/lang/Object;>(TT;)TT;
    MethodParameters:
      Name                           Flags
      value                          final

  public <T extends java.lang.Object> T copy$default$1();
    descriptor: ()Ljava/lang/Object;
    flags: (0x0001) ACC_PUBLIC
    Code:
      stack=2, locals=1, args_size=1
         0: getstatic     #26                 // Field shapeless/Cached$.MODULE$:Lshapeless/Cached$;
         3: aload_0
         4: invokevirtual #102                // Method value:()Ljava/lang/Object;
         7: invokevirtual #68                 // Method shapeless/Cached$.copy$default$1$extension:(Ljava/lang/Object;)Ljava/lang/Object;
        10: areturn
      LineNumberTable:
        line 54: 0
      LocalVariableTable:
        Start  Length  Slot  Name   Signature
            0      11     0  this   Lshapeless/Cached;
    Signature: #104                         // <T:Ljava/lang/Object;>()TT;

  public java.lang.String productPrefix();
    descriptor: ()Ljava/lang/String;
    flags: (0x0001) ACC_PUBLIC
    Code:
      stack=2, locals=1, args_size=1
         0: getstatic     #26                 // Field shapeless/Cached$.MODULE$:Lshapeless/Cached$;
         3: aload_0
         4: invokevirtual #102                // Method value:()Ljava/lang/Object;
         7: invokevirtual #63                 // Method shapeless/Cached$.productPrefix$extension:(Ljava/lang/Object;)Ljava/lang/String;
        10: areturn
      LineNumberTable:
        line 54: 0
      LocalVariableTable:
        Start  Length  Slot  Name   Signature
            0      11     0  this   Lshapeless/Cached;

  public int productArity();
    descriptor: ()I
    flags: (0x0001) ACC_PUBLIC
    Code:
      stack=2, locals=1, args_size=1
         0: getstatic     #26                 // Field shapeless/Cached$.MODULE$:Lshapeless/Cached$;
         3: aload_0
         4: invokevirtual #102                // Method value:()Ljava/lang/Object;
         7: invokevirtual #60                 // Method shapeless/Cached$.productArity$extension:(Ljava/lang/Object;)I
        10: ireturn
      LineNumberTable:
        line 54: 0
      LocalVariableTable:
        Start  Length  Slot  Name   Signature
            0      11     0  this   Lshapeless/Cached;

  public java.lang.Object productElement(int);
    descriptor: (I)Ljava/lang/Object;
    flags: (0x0001) ACC_PUBLIC
    Code:
      stack=3, locals=2, args_size=2
         0: getstatic     #26                 // Field shapeless/Cached$.MODULE$:Lshapeless/Cached$;
         3: aload_0
         4: invokevirtual #102                // Method value:()Ljava/lang/Object;
         7: iload_1
         8: invokevirtual #57                 // Method shapeless/Cached$.productElement$extension:(Ljava/lang/Object;I)Ljava/lang/Object;
        11: areturn
      LineNumberTable:
        line 54: 0
      LocalVariableTable:
        Start  Length  Slot  Name   Signature
            0      12     0  this   Lshapeless/Cached;
            0      12     1   x$1   I
    MethodParameters:
      Name                           Flags
      x$1                            final

  public scala.collection.Iterator<java.lang.Object> productIterator();
    descriptor: ()Lscala/collection/Iterator;
    flags: (0x0001) ACC_PUBLIC
    Code:
      stack=2, locals=1, args_size=1
         0: getstatic     #26                 // Field shapeless/Cached$.MODULE$:Lshapeless/Cached$;
         3: aload_0
         4: invokevirtual #102                // Method value:()Ljava/lang/Object;
         7: invokevirtual #52                 // Method shapeless/Cached$.productIterator$extension:(Ljava/lang/Object;)Lscala/collection/Iterator;
        10: areturn
      LineNumberTable:
        line 54: 0
      LocalVariableTable:
        Start  Length  Slot  Name   Signature
            0      11     0  this   Lshapeless/Cached;
    Signature: #113                         // ()Lscala/collection/Iterator<Ljava/lang/Object;>;

  public boolean canEqual(java.lang.Object);
    descriptor: (Ljava/lang/Object;)Z
    flags: (0x0001) ACC_PUBLIC
    Code:
      stack=3, locals=2, args_size=2
         0: getstatic     #26                 // Field shapeless/Cached$.MODULE$:Lshapeless/Cached$;
         3: aload_0
         4: invokevirtual #102                // Method value:()Ljava/lang/Object;
         7: aload_1
         8: invokevirtual #47                 // Method shapeless/Cached$.canEqual$extension:(Ljava/lang/Object;Ljava/lang/Object;)Z
        11: ireturn
      LineNumberTable:
        line 54: 0
      LocalVariableTable:
        Start  Length  Slot  Name   Signature
            0      12     0  this   Lshapeless/Cached;
            0      12     1   x$1   Ljava/lang/Object;
    MethodParameters:
      Name                           Flags
      x$1                            final

  public java.lang.String productElementName(int);
    descriptor: (I)Ljava/lang/String;
    flags: (0x0001) ACC_PUBLIC
    Code:
      stack=3, locals=2, args_size=2
         0: getstatic     #26                 // Field shapeless/Cached$.MODULE$:Lshapeless/Cached$;
         3: aload_0
         4: invokevirtual #102                // Method value:()Ljava/lang/Object;
         7: iload_1
         8: invokevirtual #44                 // Method shapeless/Cached$.productElementName$extension:(Ljava/lang/Object;I)Ljava/lang/String;
        11: areturn
      LineNumberTable:
        line 54: 0
      LocalVariableTable:
        Start  Length  Slot  Name   Signature
            0      12     0  this   Lshapeless/Cached;
            0      12     1   x$1   I
    MethodParameters:
      Name                           Flags
      x$1                            final

  public int hashCode();
    descriptor: ()I
    flags: (0x0001) ACC_PUBLIC
    Code:
      stack=2, locals=1, args_size=1
         0: getstatic     #26                 // Field shapeless/Cached$.MODULE$:Lshapeless/Cached$;
         3: aload_0
         4: invokevirtual #102                // Method value:()Ljava/lang/Object;
         7: invokevirtual #39                 // Method shapeless/Cached$.hashCode$extension:(Ljava/lang/Object;)I
        10: ireturn
      LineNumberTable:
        line 54: 0
      LocalVariableTable:
        Start  Length  Slot  Name   Signature
            0      11     0  this   Lshapeless/Cached;

  public boolean equals(java.lang.Object);
    descriptor: (Ljava/lang/Object;)Z
    flags: (0x0001) ACC_PUBLIC
    Code:
      stack=3, locals=2, args_size=2
         0: getstatic     #26                 // Field shapeless/Cached$.MODULE$:Lshapeless/Cached$;
         3: aload_0
         4: invokevirtual #102                // Method value:()Ljava/lang/Object;
         7: aload_1
         8: invokevirtual #34                 // Method shapeless/Cached$.equals$extension:(Ljava/lang/Object;Ljava/lang/Object;)Z
        11: ireturn
      LineNumberTable:
        line 54: 0
      LocalVariableTable:
        Start  Length  Slot  Name   Signature
            0      12     0  this   Lshapeless/Cached;
            0      12     1   x$1   Ljava/lang/Object;
    MethodParameters:
      Name                           Flags
      x$1                            final

  public java.lang.String toString();
    descriptor: ()Ljava/lang/String;
    flags: (0x0001) ACC_PUBLIC
    Code:
      stack=2, locals=1, args_size=1
         0: getstatic     #26                 // Field shapeless/Cached$.MODULE$:Lshapeless/Cached$;
         3: aload_0
         4: invokevirtual #102                // Method value:()Ljava/lang/Object;
         7: invokevirtual #28                 // Method shapeless/Cached$.toString$extension:(Ljava/lang/Object;)Ljava/lang/String;
        10: areturn
      LineNumberTable:
        line 54: 0
      LocalVariableTable:
        Start  Length  Slot  Name   Signature
            0      11     0  this   Lshapeless/Cached;

  public shapeless.Cached(T);
    descriptor: (Ljava/lang/Object;)V
    flags: (0x0001) ACC_PUBLIC
    Code:
      stack=2, locals=2, args_size=2
         0: aload_0
         1: aload_1
         2: putfield      #99                 // Field value:Ljava/lang/Object;
         5: aload_0
         6: invokespecial #126                // Method java/lang/Object."<init>":()V
         9: aload_0
        10: invokestatic  #130                // InterfaceMethod scala/Product.$init$:(Lscala/Product;)V
        13: return
      LineNumberTable:
        line 54: 0
      LocalVariableTable:
        Start  Length  Slot  Name   Signature
            0      14     0  this   Lshapeless/Cached;
            0      14     1 value   Ljava/lang/Object;
    Signature: #123                         // (TT;)V
    MethodParameters:
      Name                           Flags
      value                          final
}
Signature: #3                           // <T:Ljava/lang/Object;>Ljava/lang/Object;Lscala/Product;Ljava/io/Serializable;
SourceFile: "cached.scala"
RuntimeVisibleAnnotations:
  0: #11(#12=s#13)
    scala.reflect.ScalaSignature(
      bytes="\u0006\u0005\teg\u0001\u0002\u0012$\u0005\u001aB\u0001\"\u0010\u0001\u0003\u0016\u0004%\tA\u0010\u0005\t\u0015\u0002\u0011\t\u0012)A\u0005\u007f!)1\n\u0001C\u0001\u0019\"9\u0001\u000bAA\u0001\n\u0003\t\u0006bB,\u0001#\u0003%\t\u0001\u0017\u0005\bK\u0002\t\t\u0011\"\u0011g\u0011\u001dy\u0007!!A\u0005\u0002ADq\u0001\u001e\u0001\u0002\u0002\u0013\u0005Q\u000fC\u0004y\u0001\u0005\u0005I\u0011I=\t\u0013\u0005\u0005\u0001!!A\u0005\u0002\u0005\r\u0001\"CA\u0007\u0001\u0005\u0005I\u0011IA\b\u0011%\t\u0019\u0002AA\u0001\n\u0003\n)\u0002C\u0005\u0002\u0018\u0001\t\t\u0011\"\u0011\u0002\u001a!I\u0011Q\u0004\u0001\u0002\u0002\u0013\u0005\u0013qD\u0004\b\u0003C\u0019\u0003\u0012AA\u0012\r\u0019\u00113\u0005#\u0001\u0002&!11\n\u0005C\u0001\u0003oA\u0001\"!\u000f\u0011\u0005\u0013\r\u00111\b\u0005\b\u0003C\u0004B\u0011AAr\u0011%\t\t\u0010EA\u0001\n\u0003\u000b\u0019\u0010C\u0005\u0002\u0000B\t\t\u0011\"!\u0003\u0002!I!Q\u0003\t\u0002\u0002\u0013%!q\u0003\u0005\n\u0005?\u0001\u0012\u0011!C\u0003\u0005CA\u0011B!\u000f\u0011#\u0003%)Aa\u000f\t\u0013\t-\u0003#!A\u0005\u0006\t5\u0003\"\u0003B-!\u0005\u0005IQ\u0001B.\u0011%\u00119\u0007EA\u0001\n\u000b\u0011I\u0007C\u0005\u0003zA\t\t\u0011\"\u0002\u0003|!I!q\u0011\t\u0002\u0002\u0013\u0015!\u0011\u0012\u0005\n\u00053\u0003\u0012\u0011!C\u0003\u00057C\u0011Ba+\u0011\u0003\u0003%)A!,\t\u0013\te\u0006#!A\u0005\u0006\tm\u0006\"\u0003Bf!\u0005\u0005IQ\u0001Bg\u0005\u0019\u0019\u0015m\u00195fI*\tA%A\u0005tQ\u0006\u0004X\r\\3tg\u000e\u0001QCA\u0014B\'\u0011\u0001\u0001FL\u0019\u0011\u0005%bS\"\u0001\u0016\u000b\u0003-\nQa]2bY\u0006L!!\f\u0016\u0003\r\u0005s\u0017PV1m!\tIs&\u0003\u00021U\t9\u0001K]8ek\u000e$\bC\u0001\u001a;\u001d\t\u0019\u0004H\u0004\u00025o5\tQG\u0003\u00027K\u00051AH]8pizJ\u0011aK\u0005\u0003s)\nq\u0001]1dW\u0006<W-\u0003\u0002<y\ta1+\u001a:jC2L\'0\u00192mK*\u0011\u0011HK\u0001\u0006m\u0006dW/Z\u000b\u0002\u007fA\u0011\u0001)\u0011\u0007\u0001\t\u0019\u0011\u0005\u0001\"b\u0001\u0007\n\tA+\u0005\u0002E\u000fB\u0011\u0011&R\u0005\u0003\r*\u0012qAT8uQ&tw\r\u0005\u0002*\u0011&\u0011\u0011J\u000b\u0002\u0004\u0003:L\u0018A\u0002<bYV,\u0007%\u0001\u0004=S:LGO\u0010\u000b\u0003\u001b>\u00032A\u0014\u0001@\u001b\u0005\u0019\u0003\"B\u001f\u0004\u0001\u0004y\u0014\u0001B2paf,\"AU+\u0015\u0005M3\u0006c\u0001(\u0001)B\u0011\u0001)\u0016\u0003\u0006\u0005\u0012\u0011\ra\u0011\u0005\b{\u0011\u0001\n\u00111\u0001U\u00039\u0019w\u000e]=%I\u00164\u0017-\u001e7uIE*\"!\u00173\u0016\u0003iS#aP.,\u0003q\u0003\"!\u00182\u000e\u0003yS!a\u00181\u0002\u0013Ut7\r[3dW\u0016$\'BA1+\u0003)\tgN\\8uCRLwN\\\u0005\u0003Gz\u0013\u0011#\u001e8dQ\u0016\u001c7.\u001a3WCJL\u0017M\\2f\t\u0015\u0011UA1\u0001D\u00035\u0001(o\u001c3vGR\u0004&/\u001a4jqV\tq\r\u0005\u0002i[6\t\u0011N\u0003\u0002kW\u0006!A.\u00198h\u0015\u0005a\u0017\u0001\u00026bm\u0006L!A\\5\u0003\rM#(/\u001b8h\u00031\u0001(o\u001c3vGR\f%/\u001b;z+\u0005\t\bCA\u0015s\u0013\t\u0019(FA\u0002J]R\fa\u0002\u001d:pIV\u001cG/\u00127f[\u0016tG\u000f\u0006\u0002Hm\"9q\u000fCA\u0001\u0002\u0004\t\u0018a\u0001=%c\u0005y\u0001O]8ek\u000e$\u0018\n^3sCR|\'/F\u0001{!\rYhpR\u0007\u0002y*\u0011QPK\u0001\u000bG>dG.Z2uS>t\u0017BA@}\u0005!IE/\u001a:bi>\u0014\u0018\u0001C2b]\u0016\u000bX/\u00197\u0015\t\u0005\u0015\u00111\u0002\t\u0004S\u0005\u001d\u0011bAA\u0005U\t9!i\\8mK\u0006t\u0007bB<\u000b\u0003\u0003\u0005\raR\u0001\u0013aJ|G-^2u\u000b2,W.\u001a8u\u001d\u0006lW\rF\u0002h\u0003#Aqa^\u0006\u0002\u0002\u0003\u0007\u0011/\u0001\u0005iCND7i\u001c3f)\u0005\t\u0018AB3rk\u0006d7\u000f\u0006\u0003\u0002\u0006\u0005m\u0001bB<\u000e\u0003\u0003\u0005\raR\u0001\ti>\u001cFO]5oOR\tq-\u0001\u0004DC\u000eDW\r\u001a\t\u0003\u001dB\u0019R\u0001EA\u0014\u0003[\u00012!KA\u0015\u0013\r\tYC\u000b\u0002\u0007\u0003:L(+\u001a4\u0011\t\u0005=\u0012QG\u0007\u0003\u0003cQ1!a\rl\u0003\tIw.C\u0002<\u0003c!\"!a\t\u0002\u00175\fG/\u001a:jC2L\'0Z\u000b\u0005\u0003{\t\u0019%\u0006\u0002\u0002@A!a\nAA!!\r\u0001\u00151\t\u0003\u0007\u0003\u000b\u0012\"\u0019A\"\u0003\u0003%CSAEA%\u0003;\u0002B!a\u0013\u0002Z5\u0011\u0011Q\n\u0006\u0005\u0003\u001f\n\t&\u0001\u0005j]R,\'O\\1m\u0015\u0011\t\u0019&!\u0016\u0002\r5\f7M]8t\u0015\r\t9FK\u0001\be\u00164G.Z2u\u0013\u0011\tY&!\u0014\u0003\u00135\f7M]8J[Bd\u0017g\u0002\u0010\u0002`\u0005\u0005\u0014Q\\\u0006\u0001cEy\u0012qLA2\u0003O\nI(!#\u0002\u001a\u0006-\u0016QX\u0019\u0007I\u0005}S%!\u001a\u0002\u000b5\f7M]82\u000fY\ty&!\u001b\u0002rE*Q%a\u001b\u0002n=\u0011\u0011QN\u0011\u0003\u0003_\n1\"\\1de>,enZ5oKF*Q%a\u001d\u0002v=\u0011\u0011QO\u0011\u0003\u0003o\nQE^\u001c/a\u0001B\u0013.\u001c9mK6,g\u000e^3eA%t\u0007eU2bY\u0006\u0004#GL\u00192]AjS\nO\u00152\u000fY\ty&a\u001f\u0002\u0004F*Q%! \u0002\u0000=\u0011\u0011qP\u0011\u0003\u0003\u0003\u000b\u0001\"[:Ck:$G.Z\u0019\u0006K\u0005\u0015\u0015qQ\b\u0003\u0003\u000fK\u0012!A\u0019\b-\u0005}\u00131RAJc\u0015)\u0013QRAH\u001f\t\ty)\t\u0002\u0002\u0012\u0006Q\u0011n\u001d\"mC\u000e\\\'m\u001c=2\u000b\u0015\n)*a&\u0010\u0005\u0005]\u0015$\u0001\u00012\u000fY\ty&a\'\u0002$F*Q%!(\u0002 >\u0011\u0011qT\u0011\u0003\u0003C\u000b\u0011b\u00197bgNt\u0015-\\32\u000b\u0015\n)+a*\u0010\u0005\u0005\u001d\u0016EAAU\u0003Y\u0019\b.\u00199fY\u0016\u001c8OL\"bG\",G-T1de>\u001c\u0018g\u0002\f\u0002`\u00055\u0016QW\u0019\u0006K\u0005=\u0016\u0011W\b\u0003\u0003c\u000b#!a-\u0002\u00155,G\u000f[8e\u001d\u0006lW-M\u0003&\u0003o\u000bIl\u0004\u0002\u0002:\u0006\u0012\u00111X\u0001\u0012[\u0006$XM]5bY&TXmQ1dQ\u0016$\u0017g\u0002\f\u0002`\u0005}\u0016qY\u0019\u0006K\u0005\u0005\u00171Y\b\u0003\u0003\u0007\f#!!2\u0002\u0013MLwM\\1ukJ,\u0017gB\u0010\u0002`\u0005%\u00171[\u0019\bI\u0005}\u00131ZAg\u0013\u0011\ti-a4\u0002\t1K7\u000f\u001e\u0006\u0004\u0003#d\u0018!C5n[V$\u0018M\u00197fc\u001dy\u0012qLAk\u0003/\ft\u0001JA0\u0003\u0017\fi-M\u0003&\u00033\fYn\u0004\u0002\u0002\\v\t\u0001!M\u0002\'\u0003?\u00042\u0001QA\"\u0003)IW\u000e\u001d7jG&$H._\u000b\u0005\u0003K\fI\u000f\u0006\u0003\u0002h\u0006-\bc\u0001!\u0002j\u0012)!i\u0005b\u0001\u0007\"9\u0011Q^\nA\u0004\u0005=\u0018AB2bG\",G\r\u0005\u0003O\u0001\u0005\u001d\u0018!B1qa2LX\u0003BA{\u0003w$B!a>\u0002~B!a\nAA}!\r\u0001\u00151 \u0003\u0006\u0005R\u0011\ra\u0011\u0005\u0007{Q\u0001\r!!?\u0002\u000fUt\u0017\r\u001d9msV!!1\u0001B\u0007)\u0011\u0011)Aa\u0004\u0011\u000b%\u00129Aa\u0003\n\u0007\t%!F\u0001\u0004PaRLwN\u001c\t\u0004\u0001\n5A!\u0002\"\u0016\u0005\u0004\u0019\u0005\"\u0003B\t+\u0005\u0005\t\u0019\u0001B\n\u0003\rAH\u0005\r\t\u0005\u001d\u0002\u0011Y!\u0001\u0007xe&$XMU3qY\u0006\u001cW\r\u0006\u0002\u0003\u001aA\u0019\u0001Na\u0007\n\u0007\tu\u0011N\u0001\u0004PE*,7\r^\u0001\u000fG>\u0004\u0018\u0010J3yi\u0016t7/[8o+\u0019\u0011\u0019Ca\u000b\u00038Q!!Q\u0005B\u0018)\u0011\u00119C!\f\u0011\t9\u0003!\u0011\u0006\t\u0004\u0001\n-B!\u0002\"\u0018\u0005\u0004\u0019\u0005\u0002C\u001f\u0018!\u0003\u0005\rA!\u000b\t\u000f\tEr\u00031\u0001\u00034\u0005)A\u0005\u001e5jgB!a\n\u0001B\u001b!\r\u0001%q\u0007\u0003\u0006\u0005^\u0011\raQ\u0001\u0019G>\u0004\u0018\u0010\n3fM\u0006,H\u000e\u001e\u00132I\u0015DH/\u001a8tS>tWC\u0002B\u001f\u0005\u0013\u0012\u0019\u0005\u0006\u0003\u0003@\t\u0015#f\u0001B!7B\u0019\u0001Ia\u0011\u0005\u000b\tC\"\u0019A\"\t\u000f\tE\u0002\u00041\u0001\u0003HA!a\n\u0001B!\t\u0015\u0011\u0005D1\u0001D\u0003]\u0001(o\u001c3vGR\u0004&/\u001a4jq\u0012*\u0007\u0010^3og&|g.\u0006\u0003\u0003P\t]CcA4\u0003R!9!\u0011G\rA\u0002\tM\u0003\u0003\u0002(\u0001\u0005+\u00022\u0001\u0011B,\t\u0015\u0011\u0015D1\u0001D\u0003Y\u0001(o\u001c3vGR\f%/\u001b;zI\u0015DH/\u001a8tS>tW\u0003\u0002B/\u0005K\"2!\u001dB0\u0011\u001d\u0011\tD\u0007a\u0001\u0005C\u0002BA\u0014\u0001\u0003dA\u0019\u0001I!\u001a\u0005\u000b\tS\"\u0019A\"\u00021A\u0014x\u000eZ;di\u0016cW-\\3oi\u0012*\u0007\u0010^3og&|g.\u0006\u0003\u0003l\t]D\u0003\u0002B7\u0005c\"2a\u0012B8\u0011\u001d98$!AA\u0002EDqA!\r\u001c\u0001\u0004\u0011\u0019\b\u0005\u0003O\u0001\tU\u0004c\u0001!\u0003x\u0011)!i\u0007b\u0001\u0007\u0006I\u0002O]8ek\u000e$\u0018\n^3sCR|\'\u000fJ3yi\u0016t7/[8o+\u0011\u0011iH!\"\u0015\u0007i\u0014y\bC\u0004\u00032q\u0001\rA!!\u0011\t9\u0003!1\u0011\t\u0004\u0001\n\u0015E!\u0002\"\u001d\u0005\u0004\u0019\u0015AE2b]\u0016\u000bX/\u00197%Kb$XM\\:j_:,BAa#\u0003\u0018R!!Q\u0012BI)\u0011\t)Aa$\t\u000f]l\u0012\u0011!a\u0001\u000f\"9!\u0011G\u000fA\u0002\tM\u0005\u0003\u0002(\u0001\u0005+\u00032\u0001\u0011BL\t\u0015\u0011UD1\u0001D\u0003q\u0001(o\u001c3vGR,E.Z7f]Rt\u0015-\\3%Kb$XM\\:j_:,BA!(\u0003*R!!q\u0014BR)\r9\'\u0011\u0015\u0005\boz\t\t\u00111\u0001r\u0011\u001d\u0011\tD\ba\u0001\u0005K\u0003BA\u0014\u0001\u0003(B\u0019\u0001I!+\u0005\u000b\ts\"\u0019A\"\u0002%!\f7\u000f[\"pI\u0016$S\r\u001f;f]NLwN\\\u000b\u0005\u0005_\u00139\f\u0006\u0003\u0002\u0016\tE\u0006b\u0002B\u0019?\u0001\u0007!1\u0017\t\u0005\u001d\u0002\u0011)\fE\u0002A\u0005o#QAQ\u0010C\u0002\r\u000b\u0001#Z9vC2\u001cH%\u001a=uK:\u001c\u0018n\u001c8\u0016\t\tu&\u0011\u001a\u000b\u0005\u0005\u007f\u0013\u0019\r\u0006\u0003\u0002\u0006\t\u0005\u0007bB<!\u0003\u0003\u0005\ra\u0012\u0005\b\u0005c\u0001\u0003\u0019\u0001Bc!\u0011q\u0005Aa2\u0011\u0007\u0001\u0013I\rB\u0003CA\t\u00071)\u0001\nu_N#(/\u001b8hI\u0015DH/\u001a8tS>tW\u0003\u0002Bh\u0005/$B!a\b\u0003R\"9!\u0011G\u0011A\u0002\tM\u0007\u0003\u0002(\u0001\u0005+\u00042\u0001\u0011Bl\t\u0015\u0011\u0015E1\u0001D\u0001"
    )
  ScalaInlineInfo: length = 0x4A (unknown attribute)
   01 01 00 0E 00 79 00 7A 01 00 72 00 73 01 00 67
   00 60 01 00 64 00 41 01 00 77 00 73 01 00 76 00
   6C 01 00 6B 00 6C 01 00 6D 00 6E 01 00 74 00 75
   01 00 57 00 58 01 00 70 00 58 01 00 69 00 6A 01
   00 78 00 6A 01 00 0E 00 60 01
  ScalaSig: length = 0x3 (unknown attribute)
   05 02 00
