Classfile /Users/mw/Projects/slang-braindump/.jar/jar11/assemble/slang-braindump/assemble/content/shapeless/Cached$.class
  Last modified May 29, 2022; size 4099 bytes
  SHA-256 checksum 41942e35dfaea9dbde3c88a344d10cda39535783dab086495f627e347c76232e
  Compiled from "cached.scala"
public final class shapeless.Cached$ implements java.io.Serializable
  minor version: 0
  major version: 52
  flags: (0x0031) ACC_PUBLIC, ACC_FINAL, ACC_SUPER
  this_class: #2                          // shapeless/Cached$
  super_class: #4                         // java/lang/Object
  interfaces: 1, fields: 1, methods: 17, attributes: 3
Constant pool:
    #1 = Utf8               shapeless/Cached$
    #2 = Class              #1            // shapeless/Cached$
    #3 = Utf8               java/lang/Object
    #4 = Class              #3            // java/lang/Object
    #5 = Utf8               java/io/Serializable
    #6 = Class              #5            // java/io/Serializable
    #7 = Utf8               cached.scala
    #8 = Utf8               MODULE$
    #9 = Utf8               Lshapeless/Cached$;
   #10 = Utf8               <clinit>
   #11 = Utf8               ()V
   #12 = Utf8               <init>
   #13 = NameAndType        #12:#11       // "<init>":()V
   #14 = Methodref          #2.#13        // shapeless/Cached$."<init>":()V
   #15 = NameAndType        #8:#9         // MODULE$:Lshapeless/Cached$;
   #16 = Fieldref           #2.#15        // shapeless/Cached$.MODULE$:Lshapeless/Cached$;
   #17 = Utf8               implicitly
   #18 = Utf8               (Ljava/lang/Object;)Ljava/lang/Object;
   #19 = Utf8               <T:Ljava/lang/Object;>(TT;)TT;
   #20 = Utf8               cached
   #21 = Utf8               this
   #22 = Utf8               Ljava/lang/Object;
   #23 = Utf8               apply
   #24 = Utf8               value
   #25 = Utf8               unapply
   #26 = Utf8               (Ljava/lang/Object;)Lscala/Option;
   #27 = Utf8               <T:Ljava/lang/Object;>(TT;)Lscala/Option<TT;>;
   #28 = Utf8               x$0
   #29 = Utf8               shapeless/Cached
   #30 = Class              #29           // shapeless/Cached
   #31 = Utf8               (Ljava/lang/Object;)V
   #32 = NameAndType        #12:#31       // "<init>":(Ljava/lang/Object;)V
   #33 = Methodref          #30.#32       // shapeless/Cached."<init>":(Ljava/lang/Object;)V
   #34 = Utf8               scala/None$
   #35 = Class              #34           // scala/None$
   #36 = Utf8               Lscala/None$;
   #37 = NameAndType        #8:#36        // MODULE$:Lscala/None$;
   #38 = Fieldref           #35.#37       // scala/None$.MODULE$:Lscala/None$;
   #39 = Utf8               scala/Some
   #40 = Class              #39           // scala/Some
   #41 = Methodref          #40.#32       // scala/Some."<init>":(Ljava/lang/Object;)V
   #42 = Utf8               scala/Option
   #43 = Class              #42           // scala/Option
   #44 = Utf8               writeReplace
   #45 = Utf8               ()Ljava/lang/Object;
   #46 = Utf8               scala/runtime/ModuleSerializationProxy
   #47 = Class              #46           // scala/runtime/ModuleSerializationProxy
   #48 = Utf8               (Ljava/lang/Class;)V
   #49 = NameAndType        #12:#48       // "<init>":(Ljava/lang/Class;)V
   #50 = Methodref          #47.#49       // scala/runtime/ModuleSerializationProxy."<init>":(Ljava/lang/Class;)V
   #51 = Utf8               copy$extension
   #52 = Utf8               (Ljava/lang/Object;Ljava/lang/Object;)Ljava/lang/Object;
   #53 = Utf8               <T:Ljava/lang/Object;T:Ljava/lang/Object;>(TT;TT;)TT;
   #54 = Utf8               $this
   #55 = Utf8               copy$default$1$extension
   #56 = Utf8               <T:Ljava/lang/Object;T:Ljava/lang/Object;>(TT;)TT;
   #57 = Utf8               productPrefix$extension
   #58 = Utf8               (Ljava/lang/Object;)Ljava/lang/String;
   #59 = Utf8               <T:Ljava/lang/Object;>(TT;)Ljava/lang/String;
   #60 = Utf8               Cached
   #61 = String             #60           // Cached
   #62 = Utf8               productArity$extension
   #63 = Utf8               (Ljava/lang/Object;)I
   #64 = Utf8               <T:Ljava/lang/Object;>(TT;)I
   #65 = Utf8               productElement$extension
   #66 = Utf8               (Ljava/lang/Object;I)Ljava/lang/Object;
   #67 = Utf8               <T:Ljava/lang/Object;>(TT;I)Ljava/lang/Object;
   #68 = Utf8               x$1
   #69 = Utf8               scala/runtime/Statics
   #70 = Class              #69           // scala/runtime/Statics
   #71 = Utf8               ioobe
   #72 = Utf8               (I)Ljava/lang/Object;
   #73 = NameAndType        #71:#72       // ioobe:(I)Ljava/lang/Object;
   #74 = Methodref          #70.#73       // scala/runtime/Statics.ioobe:(I)Ljava/lang/Object;
   #75 = Utf8               I
   #76 = Utf8               productIterator$extension
   #77 = Utf8               (Ljava/lang/Object;)Lscala/collection/Iterator;
   #78 = Utf8               <T:Ljava/lang/Object;>(TT;)Lscala/collection/Iterator<Ljava/lang/Object;>;
   #79 = Utf8               scala/runtime/ScalaRunTime$
   #80 = Class              #79           // scala/runtime/ScalaRunTime$
   #81 = Utf8               Lscala/runtime/ScalaRunTime$;
   #82 = NameAndType        #8:#81        // MODULE$:Lscala/runtime/ScalaRunTime$;
   #83 = Fieldref           #80.#82       // scala/runtime/ScalaRunTime$.MODULE$:Lscala/runtime/ScalaRunTime$;
   #84 = Utf8               typedProductIterator
   #85 = Utf8               (Lscala/Product;)Lscala/collection/Iterator;
   #86 = NameAndType        #84:#85       // typedProductIterator:(Lscala/Product;)Lscala/collection/Iterator;
   #87 = Methodref          #80.#86       // scala/runtime/ScalaRunTime$.typedProductIterator:(Lscala/Product;)Lscala/collection/Iterator;
   #88 = Utf8               canEqual$extension
   #89 = Utf8               (Ljava/lang/Object;Ljava/lang/Object;)Z
   #90 = Utf8               <T:Ljava/lang/Object;>(TT;Ljava/lang/Object;)Z
   #91 = Utf8               productElementName$extension
   #92 = Utf8               (Ljava/lang/Object;I)Ljava/lang/String;
   #93 = Utf8               <T:Ljava/lang/Object;>(TT;I)Ljava/lang/String;
   #94 = String             #24           // value
   #95 = Utf8               java/lang/String
   #96 = Class              #95           // java/lang/String
   #97 = Utf8               hashCode$extension
   #98 = Utf8               hashCode
   #99 = Utf8               ()I
  #100 = NameAndType        #98:#99       // hashCode:()I
  #101 = Methodref          #4.#100       // java/lang/Object.hashCode:()I
  #102 = Utf8               equals$extension
  #103 = NameAndType        #24:#45       // value:()Ljava/lang/Object;
  #104 = Methodref          #30.#103      // shapeless/Cached.value:()Ljava/lang/Object;
  #105 = Utf8               scala/runtime/BoxesRunTime
  #106 = Class              #105          // scala/runtime/BoxesRunTime
  #107 = Utf8               equals
  #108 = NameAndType        #107:#89      // equals:(Ljava/lang/Object;Ljava/lang/Object;)Z
  #109 = Methodref          #106.#108     // scala/runtime/BoxesRunTime.equals:(Ljava/lang/Object;Ljava/lang/Object;)Z
  #110 = Utf8               toString$extension
  #111 = Utf8               _toString
  #112 = Utf8               (Lscala/Product;)Ljava/lang/String;
  #113 = NameAndType        #111:#112     // _toString:(Lscala/Product;)Ljava/lang/String;
  #114 = Methodref          #80.#113      // scala/runtime/ScalaRunTime$._toString:(Lscala/Product;)Ljava/lang/String;
  #115 = Methodref          #4.#13        // java/lang/Object."<init>":()V
  #116 = Utf8               Code
  #117 = Utf8               LineNumberTable
  #118 = Utf8               LocalVariableTable
  #119 = Utf8               Signature
  #120 = Utf8               MethodParameters
  #121 = Utf8               StackMapTable
  #122 = Utf8               SourceFile
  #123 = Utf8               ScalaInlineInfo
  #124 = Utf8               materialize
  #125 = Utf8               Scala
{
  public static final shapeless.Cached$ MODULE$;
    descriptor: Lshapeless/Cached$;
    flags: (0x0019) ACC_PUBLIC, ACC_STATIC, ACC_FINAL

  public static {};
    descriptor: ()V
    flags: (0x0009) ACC_PUBLIC, ACC_STATIC
    Code:
      stack=2, locals=0, args_size=0
         0: new           #2                  // class shapeless/Cached$
         3: dup
         4: invokespecial #14                 // Method "<init>":()V
         7: putstatic     #16                 // Field MODULE$:Lshapeless/Cached$;
        10: return
      LineNumberTable:
        line 56: 0

  public <T extends java.lang.Object> T implicitly(T);
    descriptor: (Ljava/lang/Object;)Ljava/lang/Object;
    flags: (0x0001) ACC_PUBLIC
    Code:
      stack=1, locals=2, args_size=2
         0: aload_1
         1: areturn
      LineNumberTable:
        line 59: 0
      LocalVariableTable:
        Start  Length  Slot  Name   Signature
            0       2     0  this   Lshapeless/Cached$;
            0       2     1 cached   Ljava/lang/Object;
    Signature: #19                          // <T:Ljava/lang/Object;>(TT;)TT;
    MethodParameters:
      Name                           Flags
      cached                         final

  public <T extends java.lang.Object> T apply(T);
    descriptor: (Ljava/lang/Object;)Ljava/lang/Object;
    flags: (0x0001) ACC_PUBLIC
    Code:
      stack=1, locals=2, args_size=2
         0: aload_1
         1: areturn
      LineNumberTable:
        line 54: 0
      LocalVariableTable:
        Start  Length  Slot  Name   Signature
            0       2     0  this   Lshapeless/Cached$;
            0       2     1 value   Ljava/lang/Object;
    Signature: #19                          // <T:Ljava/lang/Object;>(TT;)TT;
    MethodParameters:
      Name                           Flags
      value                          final

  public <T extends java.lang.Object> scala.Option<T> unapply(T);
    descriptor: (Ljava/lang/Object;)Lscala/Option;
    flags: (0x0001) ACC_PUBLIC
    Code:
      stack=3, locals=2, args_size=2
         0: new           #30                 // class shapeless/Cached
         3: dup
         4: aload_1
         5: invokespecial #33                 // Method shapeless/Cached."<init>":(Ljava/lang/Object;)V
         8: ifnonnull     17
        11: getstatic     #38                 // Field scala/None$.MODULE$:Lscala/None$;
        14: goto          25
        17: new           #40                 // class scala/Some
        20: dup
        21: aload_1
        22: invokespecial #41                 // Method scala/Some."<init>":(Ljava/lang/Object;)V
        25: areturn
      StackMapTable: number_of_entries = 2
        frame_type = 17 /* same */
        frame_type = 71 /* same_locals_1_stack_item */
          stack = [ class scala/Option ]
      LineNumberTable:
        line 54: 0
      LocalVariableTable:
        Start  Length  Slot  Name   Signature
            0      26     0  this   Lshapeless/Cached$;
            0      26     1   x$0   Ljava/lang/Object;
    Signature: #27                          // <T:Ljava/lang/Object;>(TT;)Lscala/Option<TT;>;
    MethodParameters:
      Name                           Flags
      x$0                            final

  private java.lang.Object writeReplace();
    descriptor: ()Ljava/lang/Object;
    flags: (0x0002) ACC_PRIVATE
    Code:
      stack=3, locals=1, args_size=1
         0: new           #47                 // class scala/runtime/ModuleSerializationProxy
         3: dup
         4: ldc           #2                  // class shapeless/Cached$
         6: invokespecial #50                 // Method scala/runtime/ModuleSerializationProxy."<init>":(Ljava/lang/Class;)V
         9: areturn
      LineNumberTable:
        line 56: 0
      LocalVariableTable:
        Start  Length  Slot  Name   Signature
            0      10     0  this   Lshapeless/Cached$;

  public final <T extends java.lang.Object, T extends java.lang.Object> T copy$extension(T, T);
    descriptor: (Ljava/lang/Object;Ljava/lang/Object;)Ljava/lang/Object;
    flags: (0x0011) ACC_PUBLIC, ACC_FINAL
    Code:
      stack=1, locals=3, args_size=3
         0: aload_2
         1: areturn
      LineNumberTable:
        line 54: 0
      LocalVariableTable:
        Start  Length  Slot  Name   Signature
            0       2     0  this   Lshapeless/Cached$;
            0       2     1 $this   Ljava/lang/Object;
            0       2     2 value   Ljava/lang/Object;
    Signature: #53                          // <T:Ljava/lang/Object;T:Ljava/lang/Object;>(TT;TT;)TT;
    MethodParameters:
      Name                           Flags
      $this                          final
      value                          final

  public final <T extends java.lang.Object, T extends java.lang.Object> T copy$default$1$extension(T);
    descriptor: (Ljava/lang/Object;)Ljava/lang/Object;
    flags: (0x0011) ACC_PUBLIC, ACC_FINAL
    Code:
      stack=1, locals=2, args_size=2
         0: aload_1
         1: areturn
      LocalVariableTable:
        Start  Length  Slot  Name   Signature
            0       2     0  this   Lshapeless/Cached$;
            0       2     1 $this   Ljava/lang/Object;
    Signature: #56                          // <T:Ljava/lang/Object;T:Ljava/lang/Object;>(TT;)TT;
    MethodParameters:
      Name                           Flags
      $this                          final

  public final <T extends java.lang.Object> java.lang.String productPrefix$extension(T);
    descriptor: (Ljava/lang/Object;)Ljava/lang/String;
    flags: (0x0011) ACC_PUBLIC, ACC_FINAL
    Code:
      stack=1, locals=2, args_size=2
         0: ldc           #61                 // String Cached
         2: areturn
      LineNumberTable:
        line 54: 0
      LocalVariableTable:
        Start  Length  Slot  Name   Signature
            0       3     0  this   Lshapeless/Cached$;
            0       3     1 $this   Ljava/lang/Object;
    Signature: #59                          // <T:Ljava/lang/Object;>(TT;)Ljava/lang/String;
    MethodParameters:
      Name                           Flags
      $this                          final

  public final <T extends java.lang.Object> int productArity$extension(T);
    descriptor: (Ljava/lang/Object;)I
    flags: (0x0011) ACC_PUBLIC, ACC_FINAL
    Code:
      stack=1, locals=2, args_size=2
         0: iconst_1
         1: ireturn
      LineNumberTable:
        line 54: 0
      LocalVariableTable:
        Start  Length  Slot  Name   Signature
            0       2     0  this   Lshapeless/Cached$;
            0       2     1 $this   Ljava/lang/Object;
    Signature: #64                          // <T:Ljava/lang/Object;>(TT;)I
    MethodParameters:
      Name                           Flags
      $this                          final

  public final <T extends java.lang.Object> java.lang.Object productElement$extension(T, int);
    descriptor: (Ljava/lang/Object;I)Ljava/lang/Object;
    flags: (0x0011) ACC_PUBLIC, ACC_FINAL
    Code:
      stack=1, locals=4, args_size=3
         0: iload_2
         1: istore_3
         2: iload_3
         3: tableswitch   { // 0 to 0
                       0: 20
                 default: 24
            }
        20: aload_1
        21: goto          31
        24: iload_2
        25: invokestatic  #74                 // Method scala/runtime/Statics.ioobe:(I)Ljava/lang/Object;
        28: goto          31
        31: areturn
      StackMapTable: number_of_entries = 3
        frame_type = 252 /* append */
          offset_delta = 20
          locals = [ int ]
        frame_type = 3 /* same */
        frame_type = 70 /* same_locals_1_stack_item */
          stack = [ class java/lang/Object ]
      LineNumberTable:
        line 54: 0
      LocalVariableTable:
        Start  Length  Slot  Name   Signature
            0      32     0  this   Lshapeless/Cached$;
            0      32     1 $this   Ljava/lang/Object;
            0      32     2   x$1   I
    Signature: #67                          // <T:Ljava/lang/Object;>(TT;I)Ljava/lang/Object;
    MethodParameters:
      Name                           Flags
      $this                          final
      x$1                            final

  public final <T extends java.lang.Object> scala.collection.Iterator<java.lang.Object> productIterator$extension(T);
    descriptor: (Ljava/lang/Object;)Lscala/collection/Iterator;
    flags: (0x0011) ACC_PUBLIC, ACC_FINAL
    Code:
      stack=4, locals=2, args_size=2
         0: getstatic     #83                 // Field scala/runtime/ScalaRunTime$.MODULE$:Lscala/runtime/ScalaRunTime$;
         3: new           #30                 // class shapeless/Cached
         6: dup
         7: aload_1
         8: invokespecial #33                 // Method shapeless/Cached."<init>":(Ljava/lang/Object;)V
        11: invokevirtual #87                 // Method scala/runtime/ScalaRunTime$.typedProductIterator:(Lscala/Product;)Lscala/collection/Iterator;
        14: areturn
      LineNumberTable:
        line 54: 0
      LocalVariableTable:
        Start  Length  Slot  Name   Signature
            0      15     0  this   Lshapeless/Cached$;
            0      15     1 $this   Ljava/lang/Object;
    Signature: #78                          // <T:Ljava/lang/Object;>(TT;)Lscala/collection/Iterator<Ljava/lang/Object;>;
    MethodParameters:
      Name                           Flags
      $this                          final

  public final <T extends java.lang.Object> boolean canEqual$extension(T, java.lang.Object);
    descriptor: (Ljava/lang/Object;Ljava/lang/Object;)Z
    flags: (0x0011) ACC_PUBLIC, ACC_FINAL
    Code:
      stack=1, locals=3, args_size=3
         0: aload_2
         1: instanceof    #4                  // class java/lang/Object
         4: ireturn
      LineNumberTable:
        line 54: 0
      LocalVariableTable:
        Start  Length  Slot  Name   Signature
            0       5     0  this   Lshapeless/Cached$;
            0       5     1 $this   Ljava/lang/Object;
            0       5     2   x$1   Ljava/lang/Object;
    Signature: #90                          // <T:Ljava/lang/Object;>(TT;Ljava/lang/Object;)Z
    MethodParameters:
      Name                           Flags
      $this                          final
      x$1                            final

  public final <T extends java.lang.Object> java.lang.String productElementName$extension(T, int);
    descriptor: (Ljava/lang/Object;I)Ljava/lang/String;
    flags: (0x0011) ACC_PUBLIC, ACC_FINAL
    Code:
      stack=1, locals=4, args_size=3
         0: iload_2
         1: istore_3
         2: iload_3
         3: tableswitch   { // 0 to 0
                       0: 20
                 default: 25
            }
        20: ldc           #94                 // String value
        22: goto          35
        25: iload_2
        26: invokestatic  #74                 // Method scala/runtime/Statics.ioobe:(I)Ljava/lang/Object;
        29: checkcast     #96                 // class java/lang/String
        32: goto          35
        35: areturn
      StackMapTable: number_of_entries = 3
        frame_type = 252 /* append */
          offset_delta = 20
          locals = [ int ]
        frame_type = 4 /* same */
        frame_type = 73 /* same_locals_1_stack_item */
          stack = [ class java/lang/String ]
      LineNumberTable:
        line 54: 0
      LocalVariableTable:
        Start  Length  Slot  Name   Signature
            0      36     0  this   Lshapeless/Cached$;
            0      36     1 $this   Ljava/lang/Object;
            0      36     2   x$1   I
    Signature: #93                          // <T:Ljava/lang/Object;>(TT;I)Ljava/lang/String;
    MethodParameters:
      Name                           Flags
      $this                          final
      x$1                            final

  public final <T extends java.lang.Object> int hashCode$extension(T);
    descriptor: (Ljava/lang/Object;)I
    flags: (0x0011) ACC_PUBLIC, ACC_FINAL
    Code:
      stack=1, locals=2, args_size=2
         0: aload_1
         1: invokevirtual #101                // Method java/lang/Object.hashCode:()I
         4: ireturn
      LineNumberTable:
        line 54: 0
      LocalVariableTable:
        Start  Length  Slot  Name   Signature
            0       5     0  this   Lshapeless/Cached$;
            0       5     1 $this   Ljava/lang/Object;
    Signature: #64                          // <T:Ljava/lang/Object;>(TT;)I
    MethodParameters:
      Name                           Flags
      $this                          final

  public final <T extends java.lang.Object> boolean equals$extension(T, java.lang.Object);
    descriptor: (Ljava/lang/Object;Ljava/lang/Object;)Z
    flags: (0x0011) ACC_PUBLIC, ACC_FINAL
    Code:
      stack=2, locals=6, args_size=3
         0: aload_2
         1: astore        4
         3: aload         4
         5: instanceof    #30                 // class shapeless/Cached
         8: ifeq          16
        11: iconst_1
        12: istore_3
        13: goto          24
        16: goto          19
        19: iconst_0
        20: istore_3
        21: goto          24
        24: iload_3
        25: ifeq          66
        28: aload_2
        29: ifnonnull     36
        32: aconst_null
        33: goto          43
        36: aload_2
        37: checkcast     #30                 // class shapeless/Cached
        40: invokevirtual #104                // Method shapeless/Cached.value:()Ljava/lang/Object;
        43: astore        5
        45: aload_1
        46: aload         5
        48: invokestatic  #109                // Method scala/runtime/BoxesRunTime.equals:(Ljava/lang/Object;Ljava/lang/Object;)Z
        51: ifeq          58
        54: iconst_1
        55: goto          59
        58: iconst_0
        59: ifeq          66
        62: iconst_1
        63: goto          67
        66: iconst_0
        67: ireturn
      StackMapTable: number_of_entries = 9
        frame_type = 253 /* append */
          offset_delta = 16
          locals = [ top, class java/lang/Object ]
        frame_type = 2 /* same */
        frame_type = 255 /* full_frame */
          offset_delta = 4
          locals = [ class shapeless/Cached$, class java/lang/Object, class java/lang/Object, int, class java/lang/Object ]
          stack = []
        frame_type = 11 /* same */
        frame_type = 70 /* same_locals_1_stack_item */
          stack = [ class java/lang/Object ]
        frame_type = 252 /* append */
          offset_delta = 14
          locals = [ class java/lang/Object ]
        frame_type = 64 /* same_locals_1_stack_item */
          stack = [ int ]
        frame_type = 250 /* chop */
          offset_delta = 6
        frame_type = 64 /* same_locals_1_stack_item */
          stack = [ int ]
      LineNumberTable:
        line 54: 0
      LocalVariableTable:
        Start  Length  Slot  Name   Signature
            0      68     0  this   Lshapeless/Cached$;
            0      68     1 $this   Ljava/lang/Object;
            0      68     2   x$1   Ljava/lang/Object;
    Signature: #90                          // <T:Ljava/lang/Object;>(TT;Ljava/lang/Object;)Z
    MethodParameters:
      Name                           Flags
      $this                          final
      x$1                            final

  public final <T extends java.lang.Object> java.lang.String toString$extension(T);
    descriptor: (Ljava/lang/Object;)Ljava/lang/String;
    flags: (0x0011) ACC_PUBLIC, ACC_FINAL
    Code:
      stack=4, locals=2, args_size=2
         0: getstatic     #83                 // Field scala/runtime/ScalaRunTime$.MODULE$:Lscala/runtime/ScalaRunTime$;
         3: new           #30                 // class shapeless/Cached
         6: dup
         7: aload_1
         8: invokespecial #33                 // Method shapeless/Cached."<init>":(Ljava/lang/Object;)V
        11: invokevirtual #114                // Method scala/runtime/ScalaRunTime$._toString:(Lscala/Product;)Ljava/lang/String;
        14: areturn
      LineNumberTable:
        line 54: 0
      LocalVariableTable:
        Start  Length  Slot  Name   Signature
            0      15     0  this   Lshapeless/Cached$;
            0      15     1 $this   Ljava/lang/Object;
    Signature: #59                          // <T:Ljava/lang/Object;>(TT;)Ljava/lang/String;
    MethodParameters:
      Name                           Flags
      $this                          final

  private shapeless.Cached$();
    descriptor: ()V
    flags: (0x0002) ACC_PRIVATE
    Code:
      stack=1, locals=1, args_size=1
         0: aload_0
         1: invokespecial #115                // Method java/lang/Object."<init>":()V
         4: return
      LineNumberTable:
        line 62: 0
        line 56: 4
      LocalVariableTable:
        Start  Length  Slot  Name   Signature
            0       5     0  this   Lshapeless/Cached$;
}
SourceFile: "cached.scala"
  ScalaInlineInfo: length = 0x59 (unknown attribute)
   01 01 00 11 00 0C 00 0B 01 00 17 00 12 01 00 58
   00 59 01 00 37 00 12 01 00 33 00 34 01 00 66 00
   59 01 00 61 00 3F 01 00 11 00 12 01 00 7C 00 2D
   01 00 3E 00 3F 01 00 41 00 42 01 00 5B 00 5C 01
   00 4C 00 4D 01 00 39 00 3A 01 00 6E 00 3A 01 00
   19 00 1A 01 00 2C 00 2D 01
  Scala: length = 0x0 (unknown attribute)

