Classfile /Users/mw/Projects/slang-braindump/.jar/jar11/assemble/slang-braindump/assemble/content/shapeless/Data$$anon$8.class
  Last modified May 29, 2022; size 1028 bytes
  SHA-256 checksum 10f416a9669df82fca5274177c58c1a8aa4b0500aeea6fb484accec53449a592
  Compiled from "sybclass.scala"
public final class shapeless.Data$$anon$8 extends java.lang.Object implements shapeless.Data<P, shapeless.CNil, R>
  minor version: 0
  major version: 52
  flags: (0x0031) ACC_PUBLIC, ACC_FINAL, ACC_SUPER
  this_class: #2                          // shapeless/Data$$anon$8
  super_class: #5                         // java/lang/Object
  interfaces: 1, fields: 0, methods: 3, attributes: 6
Constant pool:
   #1 = Utf8               shapeless/Data$$anon$8
   #2 = Class              #1             // shapeless/Data$$anon$8
   #3 = Utf8               Ljava/lang/Object;Lshapeless/Data<TP;Lshapeless/CNil;TR;>;
   #4 = Utf8               java/lang/Object
   #5 = Class              #4             // java/lang/Object
   #6 = Utf8               shapeless/Data
   #7 = Class              #6             // shapeless/Data
   #8 = Utf8               sybclass.scala
   #9 = Utf8               shapeless/Data$
  #10 = Class              #9             // shapeless/Data$
  #11 = Utf8               deriveCNil
  #12 = Utf8               ()Lshapeless/Data;
  #13 = NameAndType        #11:#12        // deriveCNil:()Lshapeless/Data;
  #14 = Utf8               gmapQ
  #15 = Utf8               (Lshapeless/CNil;)Lscala/collection/immutable/Nil$;
  #16 = Utf8               t
  #17 = Utf8               scala/collection/immutable/Nil$
  #18 = Class              #17            // scala/collection/immutable/Nil$
  #19 = Utf8               MODULE$
  #20 = Utf8               Lscala/collection/immutable/Nil$;
  #21 = NameAndType        #19:#20        // MODULE$:Lscala/collection/immutable/Nil$;
  #22 = Fieldref           #18.#21        // scala/collection/immutable/Nil$.MODULE$:Lscala/collection/immutable/Nil$;
  #23 = Utf8               this
  #24 = Utf8               Lshapeless/Data$$anon$8;
  #25 = Utf8               Lshapeless/CNil;
  #26 = Utf8               (Ljava/lang/Object;)Lscala/collection/immutable/List;
  #27 = Utf8               shapeless/CNil
  #28 = Class              #27            // shapeless/CNil
  #29 = NameAndType        #14:#15        // gmapQ:(Lshapeless/CNil;)Lscala/collection/immutable/Nil$;
  #30 = Methodref          #2.#29         // shapeless/Data$$anon$8.gmapQ:(Lshapeless/CNil;)Lscala/collection/immutable/Nil$;
  #31 = Utf8               Ljava/lang/Object;
  #32 = Utf8               <init>
  #33 = Utf8               ()V
  #34 = NameAndType        #32:#33        // "<init>":()V
  #35 = Methodref          #5.#34         // java/lang/Object."<init>":()V
  #36 = Utf8               Code
  #37 = Utf8               LineNumberTable
  #38 = Utf8               LocalVariableTable
  #39 = Utf8               MethodParameters
  #40 = Utf8               InnerClasses
  #41 = Utf8               EnclosingMethod
  #42 = Utf8               Signature
  #43 = Utf8               SourceFile
  #44 = Utf8               ScalaInlineInfo
  #45 = Utf8               Scala
{
  public scala.collection.immutable.Nil$ gmapQ(shapeless.CNil);
    descriptor: (Lshapeless/CNil;)Lscala/collection/immutable/Nil$;
    flags: (0x0001) ACC_PUBLIC
    Code:
      stack=1, locals=2, args_size=2
         0: getstatic     #22                 // Field scala/collection/immutable/Nil$.MODULE$:Lscala/collection/immutable/Nil$;
         3: areturn
      LineNumberTable:
        line 98: 0
      LocalVariableTable:
        Start  Length  Slot  Name   Signature
            0       4     0  this   Lshapeless/Data$$anon$8;
            0       4     1     t   Lshapeless/CNil;
    MethodParameters:
      Name                           Flags
      t                              final

  public scala.collection.immutable.List gmapQ(java.lang.Object);
    descriptor: (Ljava/lang/Object;)Lscala/collection/immutable/List;
    flags: (0x1041) ACC_PUBLIC, ACC_BRIDGE, ACC_SYNTHETIC
    Code:
      stack=2, locals=2, args_size=2
         0: aload_0
         1: aload_1
         2: checkcast     #28                 // class shapeless/CNil
         5: invokevirtual #30                 // Method gmapQ:(Lshapeless/CNil;)Lscala/collection/immutable/Nil$;
         8: areturn
      LineNumberTable:
        line 97: 0
      LocalVariableTable:
        Start  Length  Slot  Name   Signature
            0       9     0  this   Lshapeless/Data$$anon$8;
            0       9     1     t   Ljava/lang/Object;
    MethodParameters:
      Name                           Flags
      t                              final

  public shapeless.Data$$anon$8();
    descriptor: ()V
    flags: (0x0001) ACC_PUBLIC
    Code:
      stack=1, locals=1, args_size=1
         0: aload_0
         1: invokespecial #35                 // Method java/lang/Object."<init>":()V
         4: return
      LineNumberTable:
        line 97: 0
      LocalVariableTable:
        Start  Length  Slot  Name   Signature
            0       5     0  this   Lshapeless/Data$$anon$8;
}
InnerClasses:
  public final #2;                        // class shapeless/Data$$anon$8
EnclosingMethod: #10.#13                // shapeless.Data$.deriveCNil
Signature: #3                           // Ljava/lang/Object;Lshapeless/Data<TP;Lshapeless/CNil;TR;>;
SourceFile: "sybclass.scala"
  ScalaInlineInfo: length = 0x13 (unknown attribute)
   01 01 00 03 00 20 00 21 01 00 0E 00 1A 01 00 0E
   00 0F 01
  Scala: length = 0x0 (unknown attribute)

