Classfile /Users/mw/Projects/slang-braindump/.jar/jar11/assemble/slang-braindump/assemble/content/shapeless/DefaultCaseClassDefns$$anon$1.class
  Last modified May 29, 2022; size 8324 bytes
  SHA-256 checksum 1b2da45f89af4fe8db788a4fb80459d7b6fe54f0fbf18c31183db0e3816d2bb9
  Compiled from "alacarte.scala"
public final class shapeless.DefaultCaseClassDefns$$anon$1 implements shapeless.DefaultCaseClassDefns$CaseClassOps
  minor version: 0
  major version: 52
  flags: (0x0031) ACC_PUBLIC, ACC_FINAL, ACC_SUPER
  this_class: #2                          // shapeless/DefaultCaseClassDefns$$anon$1
  super_class: #4                         // java/lang/Object
  interfaces: 1, fields: 8, methods: 25, attributes: 5
Constant pool:
    #1 = Utf8               shapeless/DefaultCaseClassDefns$$anon$1
    #2 = Class              #1            // shapeless/DefaultCaseClassDefns$$anon$1
    #3 = Utf8               java/lang/Object
    #4 = Class              #3            // java/lang/Object
    #5 = Utf8               shapeless/DefaultCaseClassDefns$CaseClassOps
    #6 = Class              #5            // shapeless/DefaultCaseClassDefns$CaseClassOps
    #7 = Utf8               alacarte.scala
    #8 = Utf8               shapeless/DefaultCaseClassDefns
    #9 = Class              #8            // shapeless/DefaultCaseClassDefns
   #10 = Utf8               Ops
   #11 = Utf8               (Lshapeless/Generic;Lshapeless/LabelledGeneric;Lshapeless/ops/hlist$Length;Lshapeless/ops/nat$ToInt;Lshapeless/ops/hlist$Tupler;Lshapeless/Generic;Lshapeless/Typeable;Lscala/reflect/ClassTag;)Lshapeless/DefaultCaseClassDefns$CaseClassOps;
   #12 = NameAndType        #10:#11       // Ops:(Lshapeless/Generic;Lshapeless/LabelledGeneric;Lshapeless/ops/hlist$Length;Lshapeless/ops/nat$ToInt;Lshapeless/ops/hlist$Tupler;Lshapeless/Generic;Lshapeless/Typeable;Lscala/reflect/ClassTag;)Lshapeless/DefaultCaseClassDefns$CaseClassOps;
   #13 = Utf8               shapeless/ApplyUnapplyFacet$ApplyUnapplyOps
   #14 = Class              #13           // shapeless/ApplyUnapplyFacet$ApplyUnapplyOps
   #15 = Utf8               shapeless/ApplyUnapplyFacet
   #16 = Class              #15           // shapeless/ApplyUnapplyFacet
   #17 = Utf8               ApplyUnapplyOps
   #18 = Utf8               shapeless/CopyFacet$CopyOps
   #19 = Class              #18           // shapeless/CopyFacet$CopyOps
   #20 = Utf8               shapeless/CopyFacet
   #21 = Class              #20           // shapeless/CopyFacet
   #22 = Utf8               CopyOps
   #23 = Utf8               CaseClassOps
   #24 = Utf8               shapeless/PolymorphicEqualityFacet$PolymorphicEqualityOps
   #25 = Class              #24           // shapeless/PolymorphicEqualityFacet$PolymorphicEqualityOps
   #26 = Utf8               shapeless/PolymorphicEqualityFacet
   #27 = Class              #26           // shapeless/PolymorphicEqualityFacet
   #28 = Utf8               PolymorphicEqualityOps
   #29 = Utf8               shapeless/ProductFacet$ProductOps
   #30 = Class              #29           // shapeless/ProductFacet$ProductOps
   #31 = Utf8               shapeless/ProductFacet
   #32 = Class              #31           // shapeless/ProductFacet
   #33 = Utf8               ProductOps
   #34 = Utf8               shapeless/ProductISOFacet$ProductISOOps
   #35 = Class              #34           // shapeless/ProductISOFacet$ProductISOOps
   #36 = Utf8               shapeless/ProductISOFacet
   #37 = Class              #36           // shapeless/ProductISOFacet
   #38 = Utf8               ProductISOOps
   #39 = Utf8               shapeless/ToStringFacet$ToStringOps
   #40 = Class              #39           // shapeless/ToStringFacet$ToStringOps
   #41 = Utf8               shapeless/ToStringFacet
   #42 = Class              #41           // shapeless/ToStringFacet
   #43 = Utf8               ToStringOps
   #44 = Utf8               shapeless/ops/nat$ToInt
   #45 = Class              #44           // shapeless/ops/nat$ToInt
   #46 = Utf8               shapeless/ops/nat
   #47 = Class              #46           // shapeless/ops/nat
   #48 = Utf8               ToInt
   #49 = Utf8               gen
   #50 = Utf8               Lshapeless/Generic;
   #51 = Utf8               Lshapeless/Generic<Ljava/lang/Object;>;
   #52 = Utf8               lgen
   #53 = Utf8               Lshapeless/LabelledGeneric;
   #54 = Utf8               Lshapeless/LabelledGeneric<Ljava/lang/Object;>;
   #55 = Utf8               pgen
   #56 = Utf8               Lshapeless/Generic<TP0;>;
   #57 = Utf8               typ
   #58 = Utf8               Lshapeless/Typeable;
   #59 = Utf8               Lshapeless/Typeable<Ljava/lang/Object;>;
   #60 = Utf8               tag
   #61 = Utf8               Lscala/reflect/ClassTag;
   #62 = Utf8               Lscala/reflect/ClassTag<Ljava/lang/Object;>;
   #63 = Utf8               productPrefix
   #64 = Utf8               Ljava/lang/String;
   #65 = Utf8               productArity
   #66 = Utf8               I
   #67 = Utf8               $outer
   #68 = Utf8               Lshapeless/DefaultCaseClassDefns;
   #69 = Utf8               toString
   #70 = Utf8               (Ljava/lang/Object;)Ljava/lang/String;
   #71 = Utf8               c
   #72 = Utf8               toString$
   #73 = Utf8               (Lshapeless/ToStringFacet$ToStringOps;Ljava/lang/Object;)Ljava/lang/String;
   #74 = NameAndType        #72:#73       // toString$:(Lshapeless/ToStringFacet$ToStringOps;Ljava/lang/Object;)Ljava/lang/String;
   #75 = InterfaceMethodref #40.#74       // shapeless/ToStringFacet$ToStringOps.toString$:(Lshapeless/ToStringFacet$ToStringOps;Ljava/lang/Object;)Ljava/lang/String;
   #76 = Utf8               this
   #77 = Utf8               Lshapeless/DefaultCaseClassDefns$$anon$1;
   #78 = Utf8               Ljava/lang/Object;
   #79 = Utf8               copy
   #80 = Utf8               (Ljava/lang/Object;Lshapeless/HList;Lshapeless/ops/record/Merger;)Ljava/lang/Object;
   #81 = Utf8               <R::Lshapeless/HList;>(Ljava/lang/Object;TR;Lshapeless/ops/record/Merger<Lshapeless/HList;TR;>;)Ljava/lang/Object;
   #82 = Utf8               rec
   #83 = Utf8               merger
   #84 = Utf8               copy$
   #85 = Utf8               (Lshapeless/CopyFacet$CopyOps;Ljava/lang/Object;Lshapeless/HList;Lshapeless/ops/record/Merger;)Ljava/lang/Object;
   #86 = NameAndType        #84:#85       // copy$:(Lshapeless/CopyFacet$CopyOps;Ljava/lang/Object;Lshapeless/HList;Lshapeless/ops/record/Merger;)Ljava/lang/Object;
   #87 = InterfaceMethodref #19.#86       // shapeless/CopyFacet$CopyOps.copy$:(Lshapeless/CopyFacet$CopyOps;Ljava/lang/Object;Lshapeless/HList;Lshapeless/ops/record/Merger;)Ljava/lang/Object;
   #88 = Utf8               Lshapeless/HList;
   #89 = Utf8               Lshapeless/ops/record/Merger;
   #90 = Utf8               canEqual
   #91 = Utf8               (Ljava/lang/Object;Ljava/lang/Object;)Z
   #92 = Utf8               other
   #93 = Utf8               canEqual$
   #94 = Utf8               (Lshapeless/PolymorphicEqualityFacet$PolymorphicEqualityOps;Ljava/lang/Object;Ljava/lang/Object;)Z
   #95 = NameAndType        #93:#94       // canEqual$:(Lshapeless/PolymorphicEqualityFacet$PolymorphicEqualityOps;Ljava/lang/Object;Ljava/lang/Object;)Z
   #96 = InterfaceMethodref #25.#95       // shapeless/PolymorphicEqualityFacet$PolymorphicEqualityOps.canEqual$:(Lshapeless/PolymorphicEqualityFacet$PolymorphicEqualityOps;Ljava/lang/Object;Ljava/lang/Object;)Z
   #97 = Utf8               equals
   #98 = Utf8               equals$
   #99 = NameAndType        #98:#94       // equals$:(Lshapeless/PolymorphicEqualityFacet$PolymorphicEqualityOps;Ljava/lang/Object;Ljava/lang/Object;)Z
  #100 = InterfaceMethodref #25.#99       // shapeless/PolymorphicEqualityFacet$PolymorphicEqualityOps.equals$:(Lshapeless/PolymorphicEqualityFacet$PolymorphicEqualityOps;Ljava/lang/Object;Ljava/lang/Object;)Z
  #101 = Utf8               hashCode
  #102 = Utf8               (Ljava/lang/Object;)I
  #103 = Utf8               hashCode$
  #104 = Utf8               (Lshapeless/PolymorphicEqualityFacet$PolymorphicEqualityOps;Ljava/lang/Object;)I
  #105 = NameAndType        #103:#104     // hashCode$:(Lshapeless/PolymorphicEqualityFacet$PolymorphicEqualityOps;Ljava/lang/Object;)I
  #106 = InterfaceMethodref #25.#105      // shapeless/PolymorphicEqualityFacet$PolymorphicEqualityOps.hashCode$:(Lshapeless/PolymorphicEqualityFacet$PolymorphicEqualityOps;Ljava/lang/Object;)I
  #107 = Utf8               productElement
  #108 = Utf8               (Ljava/lang/Object;I)Ljava/lang/Object;
  #109 = Utf8               n
  #110 = Utf8               productElement$
  #111 = Utf8               (Lshapeless/ProductFacet$ProductOps;Ljava/lang/Object;I)Ljava/lang/Object;
  #112 = NameAndType        #110:#111     // productElement$:(Lshapeless/ProductFacet$ProductOps;Ljava/lang/Object;I)Ljava/lang/Object;
  #113 = InterfaceMethodref #30.#112      // shapeless/ProductFacet$ProductOps.productElement$:(Lshapeless/ProductFacet$ProductOps;Ljava/lang/Object;I)Ljava/lang/Object;
  #114 = Utf8               productIterator
  #115 = Utf8               (Ljava/lang/Object;)Lscala/collection/Iterator;
  #116 = Utf8               (Ljava/lang/Object;)Lscala/collection/Iterator<Ljava/lang/Object;>;
  #117 = Utf8               productIterator$
  #118 = Utf8               (Lshapeless/ProductFacet$ProductOps;Ljava/lang/Object;)Lscala/collection/Iterator;
  #119 = NameAndType        #117:#118     // productIterator$:(Lshapeless/ProductFacet$ProductOps;Ljava/lang/Object;)Lscala/collection/Iterator;
  #120 = InterfaceMethodref #30.#119      // shapeless/ProductFacet$ProductOps.productIterator$:(Lshapeless/ProductFacet$ProductOps;Ljava/lang/Object;)Lscala/collection/Iterator;
  #121 = Utf8               apply
  #122 = Utf8               (Lscala/Product;)Ljava/lang/Object;
  #123 = Utf8               p
  #124 = Utf8               apply$
  #125 = Utf8               (Lshapeless/ApplyUnapplyFacet$ApplyUnapplyOps;Lscala/Product;)Ljava/lang/Object;
  #126 = NameAndType        #124:#125     // apply$:(Lshapeless/ApplyUnapplyFacet$ApplyUnapplyOps;Lscala/Product;)Ljava/lang/Object;
  #127 = InterfaceMethodref #14.#126      // shapeless/ApplyUnapplyFacet$ApplyUnapplyOps.apply$:(Lshapeless/ApplyUnapplyFacet$ApplyUnapplyOps;Lscala/Product;)Ljava/lang/Object;
  #128 = Utf8               Lscala/Product;
  #129 = Utf8               unapply
  #130 = Utf8               (Ljava/lang/Object;)Lscala/Option;
  #131 = Utf8               (Ljava/lang/Object;)Lscala/Option<Lscala/Product;>;
  #132 = Utf8               unapply$
  #133 = Utf8               (Lshapeless/ApplyUnapplyFacet$ApplyUnapplyOps;Ljava/lang/Object;)Lscala/Option;
  #134 = NameAndType        #132:#133     // unapply$:(Lshapeless/ApplyUnapplyFacet$ApplyUnapplyOps;Ljava/lang/Object;)Lscala/Option;
  #135 = InterfaceMethodref #14.#134      // shapeless/ApplyUnapplyFacet$ApplyUnapplyOps.unapply$:(Lshapeless/ApplyUnapplyFacet$ApplyUnapplyOps;Ljava/lang/Object;)Lscala/Option;
  #136 = Utf8               toProduct
  #137 = Utf8               (Ljava/lang/Object;)Lscala/Product;
  #138 = Utf8               toProduct$
  #139 = Utf8               (Lshapeless/ProductISOFacet$ProductISOOps;Ljava/lang/Object;)Lscala/Product;
  #140 = NameAndType        #138:#139     // toProduct$:(Lshapeless/ProductISOFacet$ProductISOOps;Ljava/lang/Object;)Lscala/Product;
  #141 = InterfaceMethodref #35.#140      // shapeless/ProductISOFacet$ProductISOOps.toProduct$:(Lshapeless/ProductISOFacet$ProductISOOps;Ljava/lang/Object;)Lscala/Product;
  #142 = Utf8               fromProduct
  #143 = Utf8               fromProduct$
  #144 = Utf8               (Lshapeless/ProductISOFacet$ProductISOOps;Lscala/Product;)Ljava/lang/Object;
  #145 = NameAndType        #143:#144     // fromProduct$:(Lshapeless/ProductISOFacet$ProductISOOps;Lscala/Product;)Ljava/lang/Object;
  #146 = InterfaceMethodref #35.#145      // shapeless/ProductISOFacet$ProductISOOps.fromProduct$:(Lshapeless/ProductISOFacet$ProductISOOps;Lscala/Product;)Ljava/lang/Object;
  #147 = Utf8               ()Lshapeless/Generic;
  #148 = Utf8               ()Lshapeless/Generic<Ljava/lang/Object;>;
  #149 = NameAndType        #49:#50       // gen:Lshapeless/Generic;
  #150 = Fieldref           #2.#149       // shapeless/DefaultCaseClassDefns$$anon$1.gen:Lshapeless/Generic;
  #151 = Utf8               ()Lshapeless/LabelledGeneric;
  #152 = Utf8               ()Lshapeless/LabelledGeneric<Ljava/lang/Object;>;
  #153 = NameAndType        #52:#53       // lgen:Lshapeless/LabelledGeneric;
  #154 = Fieldref           #2.#153       // shapeless/DefaultCaseClassDefns$$anon$1.lgen:Lshapeless/LabelledGeneric;
  #155 = Utf8               ()Lshapeless/Generic<TP0;>;
  #156 = NameAndType        #55:#50       // pgen:Lshapeless/Generic;
  #157 = Fieldref           #2.#156       // shapeless/DefaultCaseClassDefns$$anon$1.pgen:Lshapeless/Generic;
  #158 = Utf8               ()Lshapeless/Typeable;
  #159 = Utf8               ()Lshapeless/Typeable<Ljava/lang/Object;>;
  #160 = NameAndType        #57:#58       // typ:Lshapeless/Typeable;
  #161 = Fieldref           #2.#160       // shapeless/DefaultCaseClassDefns$$anon$1.typ:Lshapeless/Typeable;
  #162 = Utf8               ()Lscala/reflect/ClassTag;
  #163 = Utf8               ()Lscala/reflect/ClassTag<Ljava/lang/Object;>;
  #164 = NameAndType        #60:#61       // tag:Lscala/reflect/ClassTag;
  #165 = Fieldref           #2.#164       // shapeless/DefaultCaseClassDefns$$anon$1.tag:Lscala/reflect/ClassTag;
  #166 = Utf8               ()Ljava/lang/String;
  #167 = NameAndType        #63:#64       // productPrefix:Ljava/lang/String;
  #168 = Fieldref           #2.#167       // shapeless/DefaultCaseClassDefns$$anon$1.productPrefix:Ljava/lang/String;
  #169 = Utf8               ()I
  #170 = NameAndType        #65:#66       // productArity:I
  #171 = Fieldref           #2.#170       // shapeless/DefaultCaseClassDefns$$anon$1.productArity:I
  #172 = Utf8               shapeless$ToStringFacet$ToStringOps$$$outer
  #173 = Utf8               ()Lshapeless/ToStringFacet;
  #174 = NameAndType        #67:#68       // $outer:Lshapeless/DefaultCaseClassDefns;
  #175 = Fieldref           #2.#174       // shapeless/DefaultCaseClassDefns$$anon$1.$outer:Lshapeless/DefaultCaseClassDefns;
  #176 = Utf8               shapeless$CopyFacet$CopyOps$$$outer
  #177 = Utf8               ()Lshapeless/CopyFacet;
  #178 = Utf8               shapeless$PolymorphicEqualityFacet$PolymorphicEqualityOps$$$outer
  #179 = Utf8               ()Lshapeless/PolymorphicEqualityFacet;
  #180 = Utf8               shapeless$ProductFacet$ProductOps$$$outer
  #181 = Utf8               ()Lshapeless/ProductFacet;
  #182 = Utf8               shapeless$ApplyUnapplyFacet$ApplyUnapplyOps$$$outer
  #183 = Utf8               ()Lshapeless/ApplyUnapplyFacet;
  #184 = Utf8               shapeless$ProductISOFacet$ProductISOOps$$$outer
  #185 = Utf8               ()Lshapeless/ProductISOFacet;
  #186 = Utf8               <init>
  #187 = Utf8               (Lshapeless/DefaultCaseClassDefns;Lshapeless/Generic;Lshapeless/LabelledGeneric;Lshapeless/Generic;Lshapeless/Typeable;Lscala/reflect/ClassTag;Lshapeless/ops/nat$ToInt;)V
  #188 = Utf8               gen0$1
  #189 = Utf8               lgen0$1
  #190 = Utf8               pgen0$1
  #191 = Utf8               typ0$1
  #192 = Utf8               tag0$1
  #193 = Utf8               toInt$1
  #194 = Utf8               ()V
  #195 = NameAndType        #186:#194     // "<init>":()V
  #196 = Methodref          #4.#195       // java/lang/Object."<init>":()V
  #197 = Utf8               $init$
  #198 = Utf8               (Lshapeless/ProductISOFacet$ProductISOOps;)V
  #199 = NameAndType        #197:#198     // $init$:(Lshapeless/ProductISOFacet$ProductISOOps;)V
  #200 = InterfaceMethodref #35.#199      // shapeless/ProductISOFacet$ProductISOOps.$init$:(Lshapeless/ProductISOFacet$ProductISOOps;)V
  #201 = Utf8               (Lshapeless/ApplyUnapplyFacet$ApplyUnapplyOps;)V
  #202 = NameAndType        #197:#201     // $init$:(Lshapeless/ApplyUnapplyFacet$ApplyUnapplyOps;)V
  #203 = InterfaceMethodref #14.#202      // shapeless/ApplyUnapplyFacet$ApplyUnapplyOps.$init$:(Lshapeless/ApplyUnapplyFacet$ApplyUnapplyOps;)V
  #204 = Utf8               (Lshapeless/ProductFacet$ProductOps;)V
  #205 = NameAndType        #197:#204     // $init$:(Lshapeless/ProductFacet$ProductOps;)V
  #206 = InterfaceMethodref #30.#205      // shapeless/ProductFacet$ProductOps.$init$:(Lshapeless/ProductFacet$ProductOps;)V
  #207 = Utf8               (Lshapeless/PolymorphicEqualityFacet$PolymorphicEqualityOps;)V
  #208 = NameAndType        #197:#207     // $init$:(Lshapeless/PolymorphicEqualityFacet$PolymorphicEqualityOps;)V
  #209 = InterfaceMethodref #25.#208      // shapeless/PolymorphicEqualityFacet$PolymorphicEqualityOps.$init$:(Lshapeless/PolymorphicEqualityFacet$PolymorphicEqualityOps;)V
  #210 = Utf8               (Lshapeless/CopyFacet$CopyOps;)V
  #211 = NameAndType        #197:#210     // $init$:(Lshapeless/CopyFacet$CopyOps;)V
  #212 = InterfaceMethodref #19.#211      // shapeless/CopyFacet$CopyOps.$init$:(Lshapeless/CopyFacet$CopyOps;)V
  #213 = Utf8               (Lshapeless/ToStringFacet$ToStringOps;)V
  #214 = NameAndType        #197:#213     // $init$:(Lshapeless/ToStringFacet$ToStringOps;)V
  #215 = InterfaceMethodref #40.#214      // shapeless/ToStringFacet$ToStringOps.$init$:(Lshapeless/ToStringFacet$ToStringOps;)V
  #216 = Utf8               scala/collection/ArrayOps$
  #217 = Class              #216          // scala/collection/ArrayOps$
  #218 = Utf8               MODULE$
  #219 = Utf8               Lscala/collection/ArrayOps$;
  #220 = NameAndType        #218:#219     // MODULE$:Lscala/collection/ArrayOps$;
  #221 = Fieldref           #217.#220     // scala/collection/ArrayOps$.MODULE$:Lscala/collection/ArrayOps$;
  #222 = Utf8               scala/Predef$
  #223 = Class              #222          // scala/Predef$
  #224 = Utf8               Lscala/Predef$;
  #225 = NameAndType        #218:#224     // MODULE$:Lscala/Predef$;
  #226 = Fieldref           #223.#225     // scala/Predef$.MODULE$:Lscala/Predef$;
  #227 = Utf8               scala/reflect/ClassTag
  #228 = Class              #227          // scala/reflect/ClassTag
  #229 = Utf8               runtimeClass
  #230 = Utf8               ()Ljava/lang/Class;
  #231 = NameAndType        #229:#230     // runtimeClass:()Ljava/lang/Class;
  #232 = InterfaceMethodref #228.#231     // scala/reflect/ClassTag.runtimeClass:()Ljava/lang/Class;
  #233 = Utf8               java/lang/Class
  #234 = Class              #233          // java/lang/Class
  #235 = Utf8               getName
  #236 = NameAndType        #235:#166     // getName:()Ljava/lang/String;
  #237 = Methodref          #234.#236     // java/lang/Class.getName:()Ljava/lang/String;
  #238 = Utf8               (\\.|\\$)
  #239 = String             #238          // (\\.|\\$)
  #240 = Utf8               java/lang/String
  #241 = Class              #240          // java/lang/String
  #242 = Utf8               split
  #243 = Utf8               (Ljava/lang/String;)[Ljava/lang/String;
  #244 = NameAndType        #242:#243     // split:(Ljava/lang/String;)[Ljava/lang/String;
  #245 = Methodref          #241.#244     // java/lang/String.split:(Ljava/lang/String;)[Ljava/lang/String;
  #246 = Utf8               [Ljava/lang/Object;
  #247 = Class              #246          // "[Ljava/lang/Object;"
  #248 = Utf8               refArrayOps
  #249 = Utf8               ([Ljava/lang/Object;)Ljava/lang/Object;
  #250 = NameAndType        #248:#249     // refArrayOps:([Ljava/lang/Object;)Ljava/lang/Object;
  #251 = Methodref          #223.#250     // scala/Predef$.refArrayOps:([Ljava/lang/Object;)Ljava/lang/Object;
  #252 = Utf8               last$extension
  #253 = Utf8               (Ljava/lang/Object;)Ljava/lang/Object;
  #254 = NameAndType        #252:#253     // last$extension:(Ljava/lang/Object;)Ljava/lang/Object;
  #255 = Methodref          #217.#254     // scala/collection/ArrayOps$.last$extension:(Ljava/lang/Object;)Ljava/lang/Object;
  #256 = NameAndType        #121:#169     // apply:()I
  #257 = InterfaceMethodref #45.#256      // shapeless/ops/nat$ToInt.apply:()I
  #258 = Utf8               Lshapeless/ops/nat$ToInt;
  #259 = Utf8               Signature
  #260 = Utf8               Code
  #261 = Utf8               LineNumberTable
  #262 = Utf8               LocalVariableTable
  #263 = Utf8               MethodParameters
  #264 = Utf8               StackMapTable
  #265 = Utf8               InnerClasses
  #266 = Utf8               EnclosingMethod
  #267 = Utf8               SourceFile
  #268 = Utf8               ScalaInlineInfo
  #269 = Utf8               Scala
{
  private final shapeless.Generic<java.lang.Object> gen;
    descriptor: Lshapeless/Generic;
    flags: (0x0012) ACC_PRIVATE, ACC_FINAL
    Signature: #51                          // Lshapeless/Generic<Ljava/lang/Object;>;

  private final shapeless.LabelledGeneric<java.lang.Object> lgen;
    descriptor: Lshapeless/LabelledGeneric;
    flags: (0x0012) ACC_PRIVATE, ACC_FINAL
    Signature: #54                          // Lshapeless/LabelledGeneric<Ljava/lang/Object;>;

  private final shapeless.Generic<P0> pgen;
    descriptor: Lshapeless/Generic;
    flags: (0x0012) ACC_PRIVATE, ACC_FINAL
    Signature: #56                          // Lshapeless/Generic<TP0;>;

  private final shapeless.Typeable<java.lang.Object> typ;
    descriptor: Lshapeless/Typeable;
    flags: (0x0012) ACC_PRIVATE, ACC_FINAL
    Signature: #59                          // Lshapeless/Typeable<Ljava/lang/Object;>;

  private final scala.reflect.ClassTag<java.lang.Object> tag;
    descriptor: Lscala/reflect/ClassTag;
    flags: (0x0012) ACC_PRIVATE, ACC_FINAL
    Signature: #62                          // Lscala/reflect/ClassTag<Ljava/lang/Object;>;

  private final java.lang.String productPrefix;
    descriptor: Ljava/lang/String;
    flags: (0x0012) ACC_PRIVATE, ACC_FINAL

  private final int productArity;
    descriptor: I
    flags: (0x0012) ACC_PRIVATE, ACC_FINAL

  private final shapeless.DefaultCaseClassDefns $outer;
    descriptor: Lshapeless/DefaultCaseClassDefns;
    flags: (0x1012) ACC_PRIVATE, ACC_FINAL, ACC_SYNTHETIC

  public java.lang.String toString(java.lang.Object);
    descriptor: (Ljava/lang/Object;)Ljava/lang/String;
    flags: (0x0001) ACC_PUBLIC
    Code:
      stack=2, locals=2, args_size=2
         0: aload_0
         1: aload_1
         2: invokestatic  #75                 // InterfaceMethod shapeless/ToStringFacet$ToStringOps.toString$:(Lshapeless/ToStringFacet$ToStringOps;Ljava/lang/Object;)Ljava/lang/String;
         5: areturn
      LineNumberTable:
        line 173: 0
      LocalVariableTable:
        Start  Length  Slot  Name   Signature
            0       6     0  this   Lshapeless/DefaultCaseClassDefns$$anon$1;
            0       6     1     c   Ljava/lang/Object;
    MethodParameters:
      Name                           Flags
      c                              final

  public <R extends shapeless.HList> java.lang.Object copy(java.lang.Object, R, shapeless.ops.record.Merger<shapeless.HList, R>);
    descriptor: (Ljava/lang/Object;Lshapeless/HList;Lshapeless/ops/record/Merger;)Ljava/lang/Object;
    flags: (0x0001) ACC_PUBLIC
    Code:
      stack=4, locals=4, args_size=4
         0: aload_0
         1: aload_1
         2: aload_2
         3: aload_3
         4: invokestatic  #87                 // InterfaceMethod shapeless/CopyFacet$CopyOps.copy$:(Lshapeless/CopyFacet$CopyOps;Ljava/lang/Object;Lshapeless/HList;Lshapeless/ops/record/Merger;)Ljava/lang/Object;
         7: areturn
      LineNumberTable:
        line 173: 0
      LocalVariableTable:
        Start  Length  Slot  Name   Signature
            0       8     0  this   Lshapeless/DefaultCaseClassDefns$$anon$1;
            0       8     1     c   Ljava/lang/Object;
            0       8     2   rec   Lshapeless/HList;
            0       8     3 merger   Lshapeless/ops/record/Merger;
    Signature: #81                          // <R::Lshapeless/HList;>(Ljava/lang/Object;TR;Lshapeless/ops/record/Merger<Lshapeless/HList;TR;>;)Ljava/lang/Object;
    MethodParameters:
      Name                           Flags
      c                              final
      rec                            final
      merger                         final

  public boolean canEqual(java.lang.Object, java.lang.Object);
    descriptor: (Ljava/lang/Object;Ljava/lang/Object;)Z
    flags: (0x0001) ACC_PUBLIC
    Code:
      stack=3, locals=3, args_size=3
         0: aload_0
         1: aload_1
         2: aload_2
         3: invokestatic  #96                 // InterfaceMethod shapeless/PolymorphicEqualityFacet$PolymorphicEqualityOps.canEqual$:(Lshapeless/PolymorphicEqualityFacet$PolymorphicEqualityOps;Ljava/lang/Object;Ljava/lang/Object;)Z
         6: ireturn
      LineNumberTable:
        line 173: 0
      LocalVariableTable:
        Start  Length  Slot  Name   Signature
            0       7     0  this   Lshapeless/DefaultCaseClassDefns$$anon$1;
            0       7     1     c   Ljava/lang/Object;
            0       7     2 other   Ljava/lang/Object;
    MethodParameters:
      Name                           Flags
      c                              final
      other                          final

  public boolean equals(java.lang.Object, java.lang.Object);
    descriptor: (Ljava/lang/Object;Ljava/lang/Object;)Z
    flags: (0x0001) ACC_PUBLIC
    Code:
      stack=3, locals=3, args_size=3
         0: aload_0
         1: aload_1
         2: aload_2
         3: invokestatic  #100                // InterfaceMethod shapeless/PolymorphicEqualityFacet$PolymorphicEqualityOps.equals$:(Lshapeless/PolymorphicEqualityFacet$PolymorphicEqualityOps;Ljava/lang/Object;Ljava/lang/Object;)Z
         6: ireturn
      LineNumberTable:
        line 173: 0
      LocalVariableTable:
        Start  Length  Slot  Name   Signature
            0       7     0  this   Lshapeless/DefaultCaseClassDefns$$anon$1;
            0       7     1     c   Ljava/lang/Object;
            0       7     2 other   Ljava/lang/Object;
    MethodParameters:
      Name                           Flags
      c                              final
      other                          final

  public int hashCode(java.lang.Object);
    descriptor: (Ljava/lang/Object;)I
    flags: (0x0001) ACC_PUBLIC
    Code:
      stack=2, locals=2, args_size=2
         0: aload_0
         1: aload_1
         2: invokestatic  #106                // InterfaceMethod shapeless/PolymorphicEqualityFacet$PolymorphicEqualityOps.hashCode$:(Lshapeless/PolymorphicEqualityFacet$PolymorphicEqualityOps;Ljava/lang/Object;)I
         5: ireturn
      LineNumberTable:
        line 173: 0
      LocalVariableTable:
        Start  Length  Slot  Name   Signature
            0       6     0  this   Lshapeless/DefaultCaseClassDefns$$anon$1;
            0       6     1     c   Ljava/lang/Object;
    MethodParameters:
      Name                           Flags
      c                              final

  public java.lang.Object productElement(java.lang.Object, int);
    descriptor: (Ljava/lang/Object;I)Ljava/lang/Object;
    flags: (0x0001) ACC_PUBLIC
    Code:
      stack=3, locals=3, args_size=3
         0: aload_0
         1: aload_1
         2: iload_2
         3: invokestatic  #113                // InterfaceMethod shapeless/ProductFacet$ProductOps.productElement$:(Lshapeless/ProductFacet$ProductOps;Ljava/lang/Object;I)Ljava/lang/Object;
         6: areturn
      LineNumberTable:
        line 173: 0
      LocalVariableTable:
        Start  Length  Slot  Name   Signature
            0       7     0  this   Lshapeless/DefaultCaseClassDefns$$anon$1;
            0       7     1     c   Ljava/lang/Object;
            0       7     2     n   I
    MethodParameters:
      Name                           Flags
      c                              final
      n                              final

  public scala.collection.Iterator<java.lang.Object> productIterator(java.lang.Object);
    descriptor: (Ljava/lang/Object;)Lscala/collection/Iterator;
    flags: (0x0001) ACC_PUBLIC
    Code:
      stack=2, locals=2, args_size=2
         0: aload_0
         1: aload_1
         2: invokestatic  #120                // InterfaceMethod shapeless/ProductFacet$ProductOps.productIterator$:(Lshapeless/ProductFacet$ProductOps;Ljava/lang/Object;)Lscala/collection/Iterator;
         5: areturn
      LineNumberTable:
        line 173: 0
      LocalVariableTable:
        Start  Length  Slot  Name   Signature
            0       6     0  this   Lshapeless/DefaultCaseClassDefns$$anon$1;
            0       6     1     c   Ljava/lang/Object;
    Signature: #116                         // (Ljava/lang/Object;)Lscala/collection/Iterator<Ljava/lang/Object;>;
    MethodParameters:
      Name                           Flags
      c                              final

  public java.lang.Object apply(scala.Product);
    descriptor: (Lscala/Product;)Ljava/lang/Object;
    flags: (0x0001) ACC_PUBLIC
    Code:
      stack=2, locals=2, args_size=2
         0: aload_0
         1: aload_1
         2: invokestatic  #127                // InterfaceMethod shapeless/ApplyUnapplyFacet$ApplyUnapplyOps.apply$:(Lshapeless/ApplyUnapplyFacet$ApplyUnapplyOps;Lscala/Product;)Ljava/lang/Object;
         5: areturn
      LineNumberTable:
        line 173: 0
      LocalVariableTable:
        Start  Length  Slot  Name   Signature
            0       6     0  this   Lshapeless/DefaultCaseClassDefns$$anon$1;
            0       6     1     p   Lscala/Product;
    MethodParameters:
      Name                           Flags
      p                              final

  public scala.Option<scala.Product> unapply(java.lang.Object);
    descriptor: (Ljava/lang/Object;)Lscala/Option;
    flags: (0x0001) ACC_PUBLIC
    Code:
      stack=2, locals=2, args_size=2
         0: aload_0
         1: aload_1
         2: invokestatic  #135                // InterfaceMethod shapeless/ApplyUnapplyFacet$ApplyUnapplyOps.unapply$:(Lshapeless/ApplyUnapplyFacet$ApplyUnapplyOps;Ljava/lang/Object;)Lscala/Option;
         5: areturn
      LineNumberTable:
        line 173: 0
      LocalVariableTable:
        Start  Length  Slot  Name   Signature
            0       6     0  this   Lshapeless/DefaultCaseClassDefns$$anon$1;
            0       6     1     c   Ljava/lang/Object;
    Signature: #131                         // (Ljava/lang/Object;)Lscala/Option<Lscala/Product;>;
    MethodParameters:
      Name                           Flags
      c                              final

  public scala.Product toProduct(java.lang.Object);
    descriptor: (Ljava/lang/Object;)Lscala/Product;
    flags: (0x0001) ACC_PUBLIC
    Code:
      stack=2, locals=2, args_size=2
         0: aload_0
         1: aload_1
         2: invokestatic  #141                // InterfaceMethod shapeless/ProductISOFacet$ProductISOOps.toProduct$:(Lshapeless/ProductISOFacet$ProductISOOps;Ljava/lang/Object;)Lscala/Product;
         5: areturn
      LineNumberTable:
        line 173: 0
      LocalVariableTable:
        Start  Length  Slot  Name   Signature
            0       6     0  this   Lshapeless/DefaultCaseClassDefns$$anon$1;
            0       6     1     c   Ljava/lang/Object;
    MethodParameters:
      Name                           Flags
      c                              final

  public java.lang.Object fromProduct(scala.Product);
    descriptor: (Lscala/Product;)Ljava/lang/Object;
    flags: (0x0001) ACC_PUBLIC
    Code:
      stack=2, locals=2, args_size=2
         0: aload_0
         1: aload_1
         2: invokestatic  #146                // InterfaceMethod shapeless/ProductISOFacet$ProductISOOps.fromProduct$:(Lshapeless/ProductISOFacet$ProductISOOps;Lscala/Product;)Ljava/lang/Object;
         5: areturn
      LineNumberTable:
        line 173: 0
      LocalVariableTable:
        Start  Length  Slot  Name   Signature
            0       6     0  this   Lshapeless/DefaultCaseClassDefns$$anon$1;
            0       6     1     p   Lscala/Product;
    MethodParameters:
      Name                           Flags
      p                              final

  public shapeless.Generic<java.lang.Object> gen();
    descriptor: ()Lshapeless/Generic;
    flags: (0x0001) ACC_PUBLIC
    Code:
      stack=1, locals=1, args_size=1
         0: aload_0
         1: getfield      #150                // Field gen:Lshapeless/Generic;
         4: areturn
      LineNumberTable:
        line 177: 0
      LocalVariableTable:
        Start  Length  Slot  Name   Signature
            0       5     0  this   Lshapeless/DefaultCaseClassDefns$$anon$1;
    Signature: #148                         // ()Lshapeless/Generic<Ljava/lang/Object;>;

  public shapeless.LabelledGeneric<java.lang.Object> lgen();
    descriptor: ()Lshapeless/LabelledGeneric;
    flags: (0x0001) ACC_PUBLIC
    Code:
      stack=1, locals=1, args_size=1
         0: aload_0
         1: getfield      #154                // Field lgen:Lshapeless/LabelledGeneric;
         4: areturn
      LineNumberTable:
        line 178: 0
      LocalVariableTable:
        Start  Length  Slot  Name   Signature
            0       5     0  this   Lshapeless/DefaultCaseClassDefns$$anon$1;
    Signature: #152                         // ()Lshapeless/LabelledGeneric<Ljava/lang/Object;>;

  public shapeless.Generic<P0> pgen();
    descriptor: ()Lshapeless/Generic;
    flags: (0x0001) ACC_PUBLIC
    Code:
      stack=1, locals=1, args_size=1
         0: aload_0
         1: getfield      #157                // Field pgen:Lshapeless/Generic;
         4: areturn
      LineNumberTable:
        line 179: 0
      LocalVariableTable:
        Start  Length  Slot  Name   Signature
            0       5     0  this   Lshapeless/DefaultCaseClassDefns$$anon$1;
    Signature: #155                         // ()Lshapeless/Generic<TP0;>;

  public shapeless.Typeable<java.lang.Object> typ();
    descriptor: ()Lshapeless/Typeable;
    flags: (0x0001) ACC_PUBLIC
    Code:
      stack=1, locals=1, args_size=1
         0: aload_0
         1: getfield      #161                // Field typ:Lshapeless/Typeable;
         4: areturn
      LineNumberTable:
        line 180: 0
      LocalVariableTable:
        Start  Length  Slot  Name   Signature
            0       5     0  this   Lshapeless/DefaultCaseClassDefns$$anon$1;
    Signature: #159                         // ()Lshapeless/Typeable<Ljava/lang/Object;>;

  public scala.reflect.ClassTag<java.lang.Object> tag();
    descriptor: ()Lscala/reflect/ClassTag;
    flags: (0x0001) ACC_PUBLIC
    Code:
      stack=1, locals=1, args_size=1
         0: aload_0
         1: getfield      #165                // Field tag:Lscala/reflect/ClassTag;
         4: areturn
      LineNumberTable:
        line 181: 0
      LocalVariableTable:
        Start  Length  Slot  Name   Signature
            0       5     0  this   Lshapeless/DefaultCaseClassDefns$$anon$1;
    Signature: #163                         // ()Lscala/reflect/ClassTag<Ljava/lang/Object;>;

  public java.lang.String productPrefix();
    descriptor: ()Ljava/lang/String;
    flags: (0x0001) ACC_PUBLIC
    Code:
      stack=1, locals=1, args_size=1
         0: aload_0
         1: getfield      #168                // Field productPrefix:Ljava/lang/String;
         4: areturn
      LineNumberTable:
        line 182: 0
      LocalVariableTable:
        Start  Length  Slot  Name   Signature
            0       5     0  this   Lshapeless/DefaultCaseClassDefns$$anon$1;

  public int productArity();
    descriptor: ()I
    flags: (0x0001) ACC_PUBLIC
    Code:
      stack=1, locals=1, args_size=1
         0: aload_0
         1: getfield      #171                // Field productArity:I
         4: ireturn
      LineNumberTable:
        line 183: 0
      LocalVariableTable:
        Start  Length  Slot  Name   Signature
            0       5     0  this   Lshapeless/DefaultCaseClassDefns$$anon$1;

  public shapeless.ToStringFacet shapeless$ToStringFacet$ToStringOps$$$outer();
    descriptor: ()Lshapeless/ToStringFacet;
    flags: (0x1001) ACC_PUBLIC, ACC_SYNTHETIC
    Code:
      stack=1, locals=1, args_size=1
         0: aload_0
         1: getfield      #175                // Field $outer:Lshapeless/DefaultCaseClassDefns;
         4: areturn
      LineNumberTable:
        line 173: 0
      LocalVariableTable:
        Start  Length  Slot  Name   Signature
            0       5     0  this   Lshapeless/DefaultCaseClassDefns$$anon$1;

  public shapeless.CopyFacet shapeless$CopyFacet$CopyOps$$$outer();
    descriptor: ()Lshapeless/CopyFacet;
    flags: (0x1001) ACC_PUBLIC, ACC_SYNTHETIC
    Code:
      stack=1, locals=1, args_size=1
         0: aload_0
         1: getfield      #175                // Field $outer:Lshapeless/DefaultCaseClassDefns;
         4: areturn
      LineNumberTable:
        line 173: 0
      LocalVariableTable:
        Start  Length  Slot  Name   Signature
            0       5     0  this   Lshapeless/DefaultCaseClassDefns$$anon$1;

  public shapeless.PolymorphicEqualityFacet shapeless$PolymorphicEqualityFacet$PolymorphicEqualityOps$$$outer();
    descriptor: ()Lshapeless/PolymorphicEqualityFacet;
    flags: (0x1001) ACC_PUBLIC, ACC_SYNTHETIC
    Code:
      stack=1, locals=1, args_size=1
         0: aload_0
         1: getfield      #175                // Field $outer:Lshapeless/DefaultCaseClassDefns;
         4: areturn
      LineNumberTable:
        line 173: 0
      LocalVariableTable:
        Start  Length  Slot  Name   Signature
            0       5     0  this   Lshapeless/DefaultCaseClassDefns$$anon$1;

  public shapeless.ProductFacet shapeless$ProductFacet$ProductOps$$$outer();
    descriptor: ()Lshapeless/ProductFacet;
    flags: (0x1001) ACC_PUBLIC, ACC_SYNTHETIC
    Code:
      stack=1, locals=1, args_size=1
         0: aload_0
         1: getfield      #175                // Field $outer:Lshapeless/DefaultCaseClassDefns;
         4: areturn
      LineNumberTable:
        line 173: 0
      LocalVariableTable:
        Start  Length  Slot  Name   Signature
            0       5     0  this   Lshapeless/DefaultCaseClassDefns$$anon$1;

  public shapeless.ApplyUnapplyFacet shapeless$ApplyUnapplyFacet$ApplyUnapplyOps$$$outer();
    descriptor: ()Lshapeless/ApplyUnapplyFacet;
    flags: (0x1001) ACC_PUBLIC, ACC_SYNTHETIC
    Code:
      stack=1, locals=1, args_size=1
         0: aload_0
         1: getfield      #175                // Field $outer:Lshapeless/DefaultCaseClassDefns;
         4: areturn
      LineNumberTable:
        line 173: 0
      LocalVariableTable:
        Start  Length  Slot  Name   Signature
            0       5     0  this   Lshapeless/DefaultCaseClassDefns$$anon$1;

  public shapeless.ProductISOFacet shapeless$ProductISOFacet$ProductISOOps$$$outer();
    descriptor: ()Lshapeless/ProductISOFacet;
    flags: (0x1001) ACC_PUBLIC, ACC_SYNTHETIC
    Code:
      stack=1, locals=1, args_size=1
         0: aload_0
         1: getfield      #175                // Field $outer:Lshapeless/DefaultCaseClassDefns;
         4: areturn
      LineNumberTable:
        line 173: 0
      LocalVariableTable:
        Start  Length  Slot  Name   Signature
            0       5     0  this   Lshapeless/DefaultCaseClassDefns$$anon$1;

  public shapeless.DefaultCaseClassDefns$$anon$1(shapeless.DefaultCaseClassDefns, shapeless.Generic, shapeless.LabelledGeneric, shapeless.Generic, shapeless.Typeable, scala.reflect.ClassTag, shapeless.ops.nat$ToInt);
    descriptor: (Lshapeless/DefaultCaseClassDefns;Lshapeless/Generic;Lshapeless/LabelledGeneric;Lshapeless/Generic;Lshapeless/Typeable;Lscala/reflect/ClassTag;Lshapeless/ops/nat$ToInt;)V
    flags: (0x0001) ACC_PUBLIC
    Code:
      stack=5, locals=8, args_size=8
         0: aload_1
         1: ifnonnull     6
         4: aconst_null
         5: athrow
         6: aload_0
         7: aload_1
         8: putfield      #175                // Field $outer:Lshapeless/DefaultCaseClassDefns;
        11: aload_0
        12: invokespecial #196                // Method java/lang/Object."<init>":()V
        15: aload_0
        16: invokestatic  #200                // InterfaceMethod shapeless/ProductISOFacet$ProductISOOps.$init$:(Lshapeless/ProductISOFacet$ProductISOOps;)V
        19: aload_0
        20: invokestatic  #203                // InterfaceMethod shapeless/ApplyUnapplyFacet$ApplyUnapplyOps.$init$:(Lshapeless/ApplyUnapplyFacet$ApplyUnapplyOps;)V
        23: aload_0
        24: invokestatic  #206                // InterfaceMethod shapeless/ProductFacet$ProductOps.$init$:(Lshapeless/ProductFacet$ProductOps;)V
        27: aload_0
        28: invokestatic  #209                // InterfaceMethod shapeless/PolymorphicEqualityFacet$PolymorphicEqualityOps.$init$:(Lshapeless/PolymorphicEqualityFacet$PolymorphicEqualityOps;)V
        31: aload_0
        32: invokestatic  #212                // InterfaceMethod shapeless/CopyFacet$CopyOps.$init$:(Lshapeless/CopyFacet$CopyOps;)V
        35: aload_0
        36: invokestatic  #215                // InterfaceMethod shapeless/ToStringFacet$ToStringOps.$init$:(Lshapeless/ToStringFacet$ToStringOps;)V
        39: aload_0
        40: aload_2
        41: putfield      #150                // Field gen:Lshapeless/Generic;
        44: aload_0
        45: aload_3
        46: putfield      #154                // Field lgen:Lshapeless/LabelledGeneric;
        49: aload_0
        50: aload         4
        52: putfield      #157                // Field pgen:Lshapeless/Generic;
        55: aload_0
        56: aload         5
        58: putfield      #161                // Field typ:Lshapeless/Typeable;
        61: aload_0
        62: aload         6
        64: putfield      #165                // Field tag:Lscala/reflect/ClassTag;
        67: aload_0
        68: getstatic     #221                // Field scala/collection/ArrayOps$.MODULE$:Lscala/collection/ArrayOps$;
        71: getstatic     #226                // Field scala/Predef$.MODULE$:Lscala/Predef$;
        74: aload         6
        76: invokeinterface #232,  1          // InterfaceMethod scala/reflect/ClassTag.runtimeClass:()Ljava/lang/Class;
        81: invokevirtual #237                // Method java/lang/Class.getName:()Ljava/lang/String;
        84: ldc           #239                // String (\\.|\\$)
        86: invokevirtual #245                // Method java/lang/String.split:(Ljava/lang/String;)[Ljava/lang/String;
        89: checkcast     #247                // class "[Ljava/lang/Object;"
        92: invokevirtual #251                // Method scala/Predef$.refArrayOps:([Ljava/lang/Object;)Ljava/lang/Object;
        95: invokevirtual #255                // Method scala/collection/ArrayOps$.last$extension:(Ljava/lang/Object;)Ljava/lang/Object;
        98: checkcast     #241                // class java/lang/String
       101: putfield      #168                // Field productPrefix:Ljava/lang/String;
       104: aload_0
       105: aload         7
       107: invokeinterface #257,  1          // InterfaceMethod shapeless/ops/nat$ToInt.apply:()I
       112: putfield      #171                // Field productArity:I
       115: return
      StackMapTable: number_of_entries = 1
        frame_type = 6 /* same */
      LineNumberTable:
        line 173: 0
        line 177: 39
        line 178: 44
        line 179: 49
        line 180: 55
        line 181: 61
        line 182: 67
        line 183: 104
        line 173: 115
      LocalVariableTable:
        Start  Length  Slot  Name   Signature
            0     116     0  this   Lshapeless/DefaultCaseClassDefns$$anon$1;
            0     116     1 $outer   Lshapeless/DefaultCaseClassDefns;
            0     116     2 gen0$1   Lshapeless/Generic;
            0     116     3 lgen0$1   Lshapeless/LabelledGeneric;
            0     116     4 pgen0$1   Lshapeless/Generic;
            0     116     5 typ0$1   Lshapeless/Typeable;
            0     116     6 tag0$1   Lscala/reflect/ClassTag;
            0     116     7 toInt$1   Lshapeless/ops/nat$ToInt;
    MethodParameters:
      Name                           Flags
      $outer                         final synthetic
      gen0$1                         final
      lgen0$1                        final
      pgen0$1                        final
      typ0$1                         final
      tag0$1                         final
      toInt$1                        final
}
InnerClasses:
  public #17= #14 of #16;                 // ApplyUnapplyOps=class shapeless/ApplyUnapplyFacet$ApplyUnapplyOps of class shapeless/ApplyUnapplyFacet
  public #22= #19 of #21;                 // CopyOps=class shapeless/CopyFacet$CopyOps of class shapeless/CopyFacet
  public final #2;                        // class shapeless/DefaultCaseClassDefns$$anon$1
  public #23= #6 of #9;                   // CaseClassOps=class shapeless/DefaultCaseClassDefns$CaseClassOps of class shapeless/DefaultCaseClassDefns
  public #28= #25 of #27;                 // PolymorphicEqualityOps=class shapeless/PolymorphicEqualityFacet$PolymorphicEqualityOps of class shapeless/PolymorphicEqualityFacet
  public #33= #30 of #32;                 // ProductOps=class shapeless/ProductFacet$ProductOps of class shapeless/ProductFacet
  public #38= #35 of #37;                 // ProductISOOps=class shapeless/ProductISOFacet$ProductISOOps of class shapeless/ProductISOFacet
  public #43= #40 of #42;                 // ToStringOps=class shapeless/ToStringFacet$ToStringOps of class shapeless/ToStringFacet
  public static #48= #45 of #47;          // ToInt=class shapeless/ops/nat$ToInt of class shapeless/ops/nat
EnclosingMethod: #9.#12                 // shapeless.DefaultCaseClassDefns.Ops
SourceFile: "alacarte.scala"
  ScalaInlineInfo: length = 0x81 (unknown attribute)
   01 01 00 19 00 BA 00 BB 01 00 79 00 7A 01 00 5A
   00 5B 01 00 4F 00 50 01 00 61 00 5B 01 00 8E 00
   7A 01 00 31 00 93 01 00 65 00 66 01 00 34 00 97
   01 00 37 00 93 01 00 41 00 A9 01 00 6B 00 6C 01
   00 72 00 73 01 00 3F 00 A6 01 00 B6 00 B7 01 00
   B0 00 B1 01 00 B2 00 B3 01 00 B4 00 B5 01 00 B8
   00 B9 01 00 AC 00 AD 01 00 3C 00 A2 01 00 88 00
   89 01 00 45 00 46 01 00 39 00 9E 01 00 81 00 82
   01
  Scala: length = 0x0 (unknown attribute)

