Classfile /Users/mw/Projects/slang-braindump/.jar/jar11/assemble/slang-braindump/assemble/content/shapeless/Default$AsOptions$.class
  Last modified May 29, 2022; size 1913 bytes
  SHA-256 checksum 728f1bf70e440a8a11745072b2e891fbafde805144c24f2bc3255cfcabbb7344
  Compiled from "default.scala"
public class shapeless.Default$AsOptions$ implements java.io.Serializable
  minor version: 0
  major version: 52
  flags: (0x0021) ACC_PUBLIC, ACC_SUPER
  this_class: #2                          // shapeless/Default$AsOptions$
  super_class: #4                         // java/lang/Object
  interfaces: 1, fields: 1, methods: 5, attributes: 4
Constant pool:
   #1 = Utf8               shapeless/Default$AsOptions$
   #2 = Class              #1             // shapeless/Default$AsOptions$
   #3 = Utf8               java/lang/Object
   #4 = Class              #3             // java/lang/Object
   #5 = Utf8               java/io/Serializable
   #6 = Class              #5             // java/io/Serializable
   #7 = Utf8               default.scala
   #8 = Utf8               shapeless/Default$AsOptions
   #9 = Class              #8             // shapeless/Default$AsOptions
  #10 = Utf8               shapeless/Default
  #11 = Class              #10            // shapeless/Default
  #12 = Utf8               AsOptions
  #13 = Utf8               AsOptions$
  #14 = Utf8               shapeless/Default$AsOptions$$anon$9
  #15 = Class              #14            // shapeless/Default$AsOptions$$anon$9
  #16 = Utf8               shapeless/Default$AsOptions$Helper
  #17 = Class              #16            // shapeless/Default$AsOptions$Helper
  #18 = Utf8               Helper
  #19 = Utf8               shapeless/Default$AsOptions$Helper$
  #20 = Class              #19            // shapeless/Default$AsOptions$Helper$
  #21 = Utf8               Helper$
  #22 = Utf8               MODULE$
  #23 = Utf8               Lshapeless/Default$AsOptions$;
  #24 = Utf8               <clinit>
  #25 = Utf8               ()V
  #26 = Utf8               <init>
  #27 = NameAndType        #26:#25        // "<init>":()V
  #28 = Methodref          #2.#27         // shapeless/Default$AsOptions$."<init>":()V
  #29 = NameAndType        #22:#23        // MODULE$:Lshapeless/Default$AsOptions$;
  #30 = Fieldref           #2.#29         // shapeless/Default$AsOptions$.MODULE$:Lshapeless/Default$AsOptions$;
  #31 = Utf8               apply
  #32 = Utf8               (Lshapeless/Default$AsOptions;)Lshapeless/Default$AsOptions;
  #33 = Utf8               <T:Ljava/lang/Object;>(Lshapeless/Default$AsOptions<TT;>;)Lshapeless/Default$AsOptions<TT;>;
  #34 = Utf8               default
  #35 = Utf8               this
  #36 = Utf8               Lshapeless/Default$AsOptions;
  #37 = Utf8               asOption
  #38 = Utf8               (Lshapeless/Default;Lshapeless/Generic;Lshapeless/Default$AsOptions$Helper;)Lshapeless/Default$AsOptions;
  #39 = Utf8               <T:Ljava/lang/Object;Repr::Lshapeless/HList;Options::Lshapeless/HList;Out0::Lshapeless/HList;>(Lshapeless/Default<TT;>;Lshapeless/Generic<TT;>;Lshapeless/Default$AsOptions$Helper<TOptions;TRepr;>;)Lshapeless/Default$AsOptions<TT;>;
  #40 = Utf8               gen
  #41 = Utf8               helper
  #42 = Utf8               (Lshapeless/Default$AsOptions$Helper;Lshapeless/Default;)V
  #43 = NameAndType        #26:#42        // "<init>":(Lshapeless/Default$AsOptions$Helper;Lshapeless/Default;)V
  #44 = Methodref          #15.#43        // shapeless/Default$AsOptions$$anon$9."<init>":(Lshapeless/Default$AsOptions$Helper;Lshapeless/Default;)V
  #45 = Utf8               Lshapeless/Default;
  #46 = Utf8               Lshapeless/Generic;
  #47 = Utf8               Lshapeless/Default$AsOptions$Helper;
  #48 = Utf8               writeReplace
  #49 = Utf8               ()Ljava/lang/Object;
  #50 = Utf8               scala/runtime/ModuleSerializationProxy
  #51 = Class              #50            // scala/runtime/ModuleSerializationProxy
  #52 = Utf8               (Ljava/lang/Class;)V
  #53 = NameAndType        #26:#52        // "<init>":(Ljava/lang/Class;)V
  #54 = Methodref          #51.#53        // scala/runtime/ModuleSerializationProxy."<init>":(Ljava/lang/Class;)V
  #55 = Methodref          #4.#27         // java/lang/Object."<init>":()V
  #56 = Utf8               Code
  #57 = Utf8               LineNumberTable
  #58 = Utf8               LocalVariableTable
  #59 = Utf8               Signature
  #60 = Utf8               MethodParameters
  #61 = Utf8               InnerClasses
  #62 = Utf8               SourceFile
  #63 = Utf8               ScalaInlineInfo
  #64 = Utf8               Scala
{
  public static final shapeless.Default$AsOptions$ MODULE$;
    descriptor: Lshapeless/Default$AsOptions$;
    flags: (0x0019) ACC_PUBLIC, ACC_STATIC, ACC_FINAL

  public static {};
    descriptor: ()V
    flags: (0x0009) ACC_PUBLIC, ACC_STATIC
    Code:
      stack=2, locals=0, args_size=0
         0: new           #2                  // class shapeless/Default$AsOptions$
         3: dup
         4: invokespecial #28                 // Method "<init>":()V
         7: putstatic     #30                 // Field MODULE$:Lshapeless/Default$AsOptions$;
        10: return
      LineNumberTable:
        line 159: 0

  public <T extends java.lang.Object> shapeless.Default$AsOptions<T> apply(shapeless.Default$AsOptions<T>);
    descriptor: (Lshapeless/Default$AsOptions;)Lshapeless/Default$AsOptions;
    flags: (0x0001) ACC_PUBLIC
    Code:
      stack=1, locals=2, args_size=2
         0: aload_1
         1: areturn
      LineNumberTable:
        line 160: 0
      LocalVariableTable:
        Start  Length  Slot  Name   Signature
            0       2     0  this   Lshapeless/Default$AsOptions$;
            0       2     1 default   Lshapeless/Default$AsOptions;
    Signature: #33                          // <T:Ljava/lang/Object;>(Lshapeless/Default$AsOptions<TT;>;)Lshapeless/Default$AsOptions<TT;>;
    MethodParameters:
      Name                           Flags
      default                        final

  public <T extends java.lang.Object, Repr extends shapeless.HList, Options extends shapeless.HList, Out0 extends shapeless.HList> shapeless.Default$AsOptions<T> asOption(shapeless.Default<T>, shapeless.Generic<T>, shapeless.Default$AsOptions$Helper<Options, Repr>);
    descriptor: (Lshapeless/Default;Lshapeless/Generic;Lshapeless/Default$AsOptions$Helper;)Lshapeless/Default$AsOptions;
    flags: (0x0001) ACC_PUBLIC
    Code:
      stack=4, locals=4, args_size=4
         0: new           #15                 // class shapeless/Default$AsOptions$$anon$9
         3: dup
         4: aload_3
         5: aload_1
         6: invokespecial #44                 // Method shapeless/Default$AsOptions$$anon$9."<init>":(Lshapeless/Default$AsOptions$Helper;Lshapeless/Default;)V
         9: areturn
      LineNumberTable:
        line 204: 0
      LocalVariableTable:
        Start  Length  Slot  Name   Signature
            0      10     0  this   Lshapeless/Default$AsOptions$;
            0      10     1 default   Lshapeless/Default;
            0      10     2   gen   Lshapeless/Generic;
            0      10     3 helper   Lshapeless/Default$AsOptions$Helper;
    Signature: #39                          // <T:Ljava/lang/Object;Repr::Lshapeless/HList;Options::Lshapeless/HList;Out0::Lshapeless/HList;>(Lshapeless/Default<TT;>;Lshapeless/Generic<TT;>;Lshapeless/Default$AsOptions$Helper<TOptions;TRepr;>;)Lshapeless/Default$AsOptions<TT;>;
    MethodParameters:
      Name                           Flags
      default                        final
      gen                            final
      helper                         final

  private java.lang.Object writeReplace();
    descriptor: ()Ljava/lang/Object;
    flags: (0x0002) ACC_PRIVATE
    Code:
      stack=3, locals=1, args_size=1
         0: new           #51                 // class scala/runtime/ModuleSerializationProxy
         3: dup
         4: ldc           #2                  // class shapeless/Default$AsOptions$
         6: invokespecial #54                 // Method scala/runtime/ModuleSerializationProxy."<init>":(Ljava/lang/Class;)V
         9: areturn
      LineNumberTable:
        line 159: 0
      LocalVariableTable:
        Start  Length  Slot  Name   Signature
            0      10     0  this   Lshapeless/Default$AsOptions$;

  public shapeless.Default$AsOptions$();
    descriptor: ()V
    flags: (0x0001) ACC_PUBLIC
    Code:
      stack=1, locals=1, args_size=1
         0: aload_0
         1: invokespecial #55                 // Method java/lang/Object."<init>":()V
         4: return
      LineNumberTable:
        line 209: 0
        line 159: 4
      LocalVariableTable:
        Start  Length  Slot  Name   Signature
            0       5     0  this   Lshapeless/Default$AsOptions$;
}
InnerClasses:
  public static #12= #9 of #11;           // AsOptions=class shapeless/Default$AsOptions of class shapeless/Default
  public static #13= #2 of #11;           // AsOptions$=class shapeless/Default$AsOptions$ of class shapeless/Default
  public final #15;                       // class shapeless/Default$AsOptions$$anon$9
  public static #18= #17 of #2;           // Helper=class shapeless/Default$AsOptions$Helper of class shapeless/Default$AsOptions$
  public static #21= #20 of #2;           // Helper$=class shapeless/Default$AsOptions$Helper$ of class shapeless/Default$AsOptions$
SourceFile: "default.scala"
  ScalaInlineInfo: length = 0x18 (unknown attribute)
   01 01 00 04 00 1A 00 19 01 00 1F 00 20 01 00 25
   00 26 01 00 30 00 31 01
  Scala: length = 0x0 (unknown attribute)

