Classfile /Users/mw/Projects/slang-braindump/.jar/jar11/assemble/slang-braindump/assemble/content/shapeless/LabelledProductTypeClassCompanion.class
  Last modified May 29, 2022; size 7208 bytes
  SHA-256 checksum 3bf2ad636c7dd76d55cb972c33948ea3f29410202885181399d8459aeae469af
  Compiled from "typeclass.scala"
public interface shapeless.LabelledProductTypeClassCompanion<C extends java.lang.Object> extends java.io.Serializable
  minor version: 0
  major version: 52
  flags: (0x0601) ACC_PUBLIC, ACC_INTERFACE, ACC_ABSTRACT
  this_class: #2                          // shapeless/LabelledProductTypeClassCompanion
  super_class: #5                         // java/lang/Object
  interfaces: 1, fields: 0, methods: 15, attributes: 7
Constant pool:
    #1 = Utf8               shapeless/LabelledProductTypeClassCompanion
    #2 = Class              #1            // shapeless/LabelledProductTypeClassCompanion
    #3 = Utf8               <C:Ljava/lang/Object;>Ljava/lang/Object;Ljava/io/Serializable;
    #4 = Utf8               java/lang/Object
    #5 = Class              #4            // java/lang/Object
    #6 = Utf8               java/io/Serializable
    #7 = Class              #6            // java/io/Serializable
    #8 = Utf8               typeclass.scala
    #9 = Utf8               Lscala/reflect/ScalaSignature;
   #10 = Utf8               bytes
   #11 = Utf8               \u0006\u0005\u0005mea\u0002\t\u0012!\u0003\r\t\u0001\u0006\u0005\u0006Q\u0001!\t!\u000b\u0005\u0006[\u0001!\tA\f\u0005\b\u000f\u0002\u0011\rQ\"\u0001I\r\u001di\u0005\u0001%A\u0012\u00029#Q\u0001\u0015\u0003\u0003\u0002UBq!\u0015\u0003C\u0002\u001b\u0005!\u000bC\u0003W\t\u0019\u0005q\u000bC\u0003^\t\u0019\u0005alB\u0003b\u0001!\u0005!MB\u0003N\u0001!\u0005A\rC\u0003m\u0015\u0011\u0005Q.\u0002\u0003o\u0015\u0001y\u0007\"\u0002>\u0001\t\u0007Y\bbBA\u0002\u0001\u0011\r\u0011Q\u0001\u0005\b\u0003c\u0002A1AA:\u0005\u0005b\u0015MY3mY\u0016$\u0007K]8ek\u000e$H+\u001f9f\u00072\f7o]\"p[B\fg.[8o\u0015\u0005\u0011\u0012!C:iCB,G.Z:t\u0007\u0001)\"!\u0006\u001a\u0014\u0007\u00011B\u0004\u0005\u0002\u001855\t\u0001DC\u0001\u001a\u0003\u0015\u00198-\u00197b\u0013\tY\u0002D\u0001\u0004B]f\u0014VM\u001a\t\u0003;\u0015r!AH\u0012\u000f\u0005}\u0011S\"\u0001\u0011\u000b\u0005\u0005\u001a\u0012A\u0002\u001fs_>$h(C\u0001\u001a\u0013\t!\u0003$A\u0004qC\u000e\\\u0017mZ3\n\u0005\u0019:#\u0001D*fe&\fG.\u001b>bE2,\'B\u0001\u0013\u0019\u0003\u0019!\u0013N\\5uIQ\t!\u0006\u0005\u0002\u0018W%\u0011A\u0006\u0007\u0002\u0005+:LG/A\u0003baBd\u00170\u0006\u00020\u007fQ\u0011\u0001\'\u0011\t\u0004cIrD\u0002\u0001\u0003\u0006g\u0001\u0011\r\u0001\u000e\u0002\u0002\u0007V\u0011Q\u0007P\t\u0003me\u0002\"aF\u001c\n\u0005aB\"a\u0002(pi\"Lgn\u001a\t\u0003/iJ!a\u000f\r\u0003\u0007\u0005s\u0017\u0010B\u0003>e\t\u0007QGA\u0001`!\t\tt\bB\u0003A\u0005\t\u0007QGA\u0001U\u0011\u0015\u0011%\u0001q\u0001D\u0003\t\u0019G\u000fE\u0002E\u000bBj\u0011!E\u0005\u0003\rF\u0011A\u0001T1{s\u0006IA/\u001f9f\u00072\f7o]\u000b\u0002\u0013B\u0019AI\u0013\'\n\u0005-\u000b\"\u0001\u0007\'bE\u0016dG.\u001a3Qe>$Wo\u0019;UsB,7\t\\1tgB\u0011\u0011G\r\u0002\u0005/J\f\u0007/\u0006\u0002P3N\u0019AA\u0006\u000f\u0003\u0003Y\u000ba!\u001e8xe\u0006\u0004X#A*\u0011\u0007E\u0012D\u000b\u0005\u0002V\u000b5\tA!A\u0003mC\n,G\u000e\u0006\u0002Y7B\u0011\u0011\'\u0017\u0003\u00065\u0012\u0011\r!\u000e\u0002\u0003\u0017ZCQ\u0001X\u0004A\u0002Q\u000b\u0011A^\u0001\bk:d\u0017MY3m)\t!v\fC\u0003a\u0011\u0001\u0007\u0001,A\u0002sK\u000e\fAa\u0016:baB\u00111MC\u0007\u0002\u0001M\u0019!BF3\u0011\u0005\u0019\\W\"A4\u000b\u0005!L\u0017AA5p\u0015\u0005Q\u0017\u0001\u00026bm\u0006L!AJ4\u0002\rqJg.\u001b;?)\u0005\u0011\'aA!vqV\u0019\u0001/\u001e=\u0013\u0005E\u001ch\u0001\u0002:\u000b\u0001A\u0014A\u0002\u0010:fM&tW-\\3oiz\u00022a\u0019\u0003u!\t\tT\u000fB\u0003[\u0019\t\u0007Q\'\u0002\u0003Qc\u0002:\bCA\u0019y\t\u0015IHB1\u00016\u0005\t1\u0006\'\u0001\u0006eKJLg/\u001a%OS2,\u0012\u0001 \t\u0005{2qhP\u0004\u0002d\u0013A\u0011Ai`\u0005\u0004\u0003\u0003\t\"\u0001\u0002%OS2\f1\u0002Z3sSZ,\u0007jQ8ogVA\u0011qAA\u0011\u0003_\t)\u0004\u0006\u0005\u0002\n\u0005e\u0013\u0011MA%!\u0019iH\"a\u0003\u0002BA9A)!\u0004\u0002\u0012\u0005M\u0012bAA\b#\taAeY8m_:$3m\u001c7p]BA\u00111CA\r\u0003?\tiCD\u0002E\u0003+I1!a\u0006\u0012\u0003!a\u0017MY3mY\u0016$\u0017\u0002BA\u000e\u0003;\u0011\u0011BR5fY\u0012$\u0016\u0010]3\u000b\u0007\u0005]\u0011\u0003E\u00022\u0003C!q!a\t\u000f\u0005\u0004\t)C\u0001\u0002I\u0017F\u0019a\'a\n\u0011\u0007]\tI#C\u0002\u0002,a\u0011aaU=nE>d\u0007cA\u0019\u00020\u00111\u0011\u0011\u0007\bC\u0002U\u0012!\u0001\u0013,\u0011\u0007E\n)\u0004B\u0004\u000289\u0011\r!!\u000f\u0003\u0007Q[e+E\u00027\u0003w\u00012\u0001RA\u001f\u0013\r\ty$\u0005\u0002\u0006\u00112K7\u000f\u001e\t\b\t\u00065\u0011QFA\"!\u0011\t)%a\u0015\u000f\t\u0005\u001d\u0013Q\u000b\b\u0004c\u0005%\u0003B\u0002\"\u000f\u0001\b\tY\u0005\u0005\u0003E\u000b\u00065#\u0003BA(\u0003#2QA\u001d\u0001\u0001\u0003\u001b\u0002Ba\u0019\u0003\u00024\u00119\u0001+a\u0014\u0003\u0002\u0005e\u0012bAA,\u000b\u0006)a/\u00197vK\"9\u00111\f\bA\u0004\u0005u\u0013AA2i!\u0011!U)a\u0018\u0011\tE\u0012\u0014Q\u0006\u0005\b\u0003Gr\u00019AA3\u0003\rYW-\u001f\t\u0007\u0003O\ni\'a\b\u000f\u0007\u0011\u000bI\'C\u0002\u0002lE\tqaV5u]\u0016\u001c8/C\u0002o\u0003_R1!a\u001b\u0012\u00039!WM]5wK&s7\u000f^1oG\u0016,b!!\u001e\u0002|\u0005=ECBA<\u0003{\n\u0019\n\u0005\u00032e\u0005e\u0004cA\u0019\u0002|\u0011)\u0001i\u0004b\u0001k!9\u0011qP\bA\u0004\u0005\u0005\u0015\u0001\u00027hK:\u0004\u0002\"a!\u0002\n\u0006e\u0014Q\u0012\b\u0004\t\u0006\u0015\u0015bAAD#\u0005yA*\u00192fY2,GmR3oKJL7-C\u0002o\u0003\u0017S1!a\"\u0012!\r\t\u0014q\u0012\u0003\u0007\u0003#{!\u0019A\u001b\u0003\u00071[e\u000bC\u0004\u0002\u0016>\u0001\u001d!a&\u0002\r1<8\r\\6w!\u0011!U)!\'\u0011\t\r$\u0011Q\u0012
   #12 = Utf8               java/lang/invoke/MethodHandles$Lookup
   #13 = Class              #12           // java/lang/invoke/MethodHandles$Lookup
   #14 = Utf8               java/lang/invoke/MethodHandles
   #15 = Class              #14           // java/lang/invoke/MethodHandles
   #16 = Utf8               Lookup
   #17 = Utf8               shapeless/LabelledProductTypeClassCompanion$$anon$1
   #18 = Class              #17           // shapeless/LabelledProductTypeClassCompanion$$anon$1
   #19 = Utf8               shapeless/LabelledProductTypeClassCompanion$$anon$2
   #20 = Class              #19           // shapeless/LabelledProductTypeClassCompanion$$anon$2
   #21 = Utf8               shapeless/LabelledProductTypeClassCompanion$Wrap
   #22 = Class              #21           // shapeless/LabelledProductTypeClassCompanion$Wrap
   #23 = Utf8               Wrap
   #24 = Utf8               shapeless/LabelledProductTypeClassCompanion$Wrap$
   #25 = Class              #24           // shapeless/LabelledProductTypeClassCompanion$Wrap$
   #26 = Utf8               Wrap$
   #27 = Utf8               ()Lshapeless/LabelledProductTypeClassCompanion$Wrap$;
   #28 = Utf8               ()Lshapeless/LabelledProductTypeClassCompanion<TC;>.Wrap$;
   #29 = Utf8               apply$
   #30 = Utf8               (Lshapeless/LabelledProductTypeClassCompanion;Lshapeless/Lazy;)Ljava/lang/Object;
   #31 = Utf8               $this
   #32 = Utf8               ct
   #33 = Utf8               apply
   #34 = Utf8               (Lshapeless/Lazy;)Ljava/lang/Object;
   #35 = NameAndType        #33:#34       // apply:(Lshapeless/Lazy;)Ljava/lang/Object;
   #36 = InterfaceMethodref #2.#35        // shapeless/LabelledProductTypeClassCompanion.apply:(Lshapeless/Lazy;)Ljava/lang/Object;
   #37 = Utf8               Lshapeless/LabelledProductTypeClassCompanion;
   #38 = Utf8               Lshapeless/Lazy;
   #39 = Utf8               <T:Ljava/lang/Object;>(Lshapeless/Lazy<TC;>;)TC;
   #40 = Utf8               shapeless/Lazy
   #41 = Class              #40           // shapeless/Lazy
   #42 = Utf8               value
   #43 = Utf8               ()Ljava/lang/Object;
   #44 = NameAndType        #42:#43       // value:()Ljava/lang/Object;
   #45 = InterfaceMethodref #41.#44       // shapeless/Lazy.value:()Ljava/lang/Object;
   #46 = Utf8               this
   #47 = Utf8               typeClass
   #48 = Utf8               ()Lshapeless/LabelledProductTypeClass;
   #49 = Utf8               ()Lshapeless/LabelledProductTypeClass<TC;>;
   #50 = Utf8               deriveHNil$
   #51 = Utf8               (Lshapeless/LabelledProductTypeClassCompanion;)Lshapeless/LabelledProductTypeClassCompanion$Wrap;
   #52 = Utf8               deriveHNil
   #53 = Utf8               ()Lshapeless/LabelledProductTypeClassCompanion$Wrap;
   #54 = NameAndType        #52:#53       // deriveHNil:()Lshapeless/LabelledProductTypeClassCompanion$Wrap;
   #55 = InterfaceMethodref #2.#54        // shapeless/LabelledProductTypeClassCompanion.deriveHNil:()Lshapeless/LabelledProductTypeClassCompanion$Wrap;
   #56 = Utf8               ()Lshapeless/LabelledProductTypeClassCompanion<TC;>.Wrap<Lshapeless/HNil;>;
   #57 = Utf8               <init>
   #58 = Utf8               (Lshapeless/LabelledProductTypeClassCompanion;)V
   #59 = NameAndType        #57:#58       // "<init>":(Lshapeless/LabelledProductTypeClassCompanion;)V
   #60 = Methodref          #18.#59       // shapeless/LabelledProductTypeClassCompanion$$anon$1."<init>":(Lshapeless/LabelledProductTypeClassCompanion;)V
   #61 = Utf8               deriveHCons$
   #62 = Utf8               (Lshapeless/LabelledProductTypeClassCompanion;Lshapeless/Lazy;Lshapeless/Witness;Lshapeless/Lazy;)Lshapeless/LabelledProductTypeClassCompanion$Wrap;
   #63 = Utf8               ch
   #64 = Utf8               key
   #65 = Utf8               deriveHCons
   #66 = Utf8               (Lshapeless/Lazy;Lshapeless/Witness;Lshapeless/Lazy;)Lshapeless/LabelledProductTypeClassCompanion$Wrap;
   #67 = NameAndType        #65:#66       // deriveHCons:(Lshapeless/Lazy;Lshapeless/Witness;Lshapeless/Lazy;)Lshapeless/LabelledProductTypeClassCompanion$Wrap;
   #68 = InterfaceMethodref #2.#67        // shapeless/LabelledProductTypeClassCompanion.deriveHCons:(Lshapeless/Lazy;Lshapeless/Witness;Lshapeless/Lazy;)Lshapeless/LabelledProductTypeClassCompanion$Wrap;
   #69 = Utf8               Lshapeless/Witness;
   #70 = Utf8               <HK:Lscala/Symbol;HV:Ljava/lang/Object;TKV::Lshapeless/HList;>(Lshapeless/Lazy<TC;>;Lshapeless/Witness;Lshapeless/Lazy<Lshapeless/LabelledProductTypeClassCompanion<TC;>.Wrap<TTKV;>;>;)Lshapeless/LabelledProductTypeClassCompanion<TC;>.Wrap<Lshapeless/$colon$colon<THV;TTKV;>;>;
   #71 = Utf8               (Lshapeless/LabelledProductTypeClassCompanion;Lshapeless/Witness;Lshapeless/Lazy;Lshapeless/Lazy;)V
   #72 = NameAndType        #57:#71       // "<init>":(Lshapeless/LabelledProductTypeClassCompanion;Lshapeless/Witness;Lshapeless/Lazy;Lshapeless/Lazy;)V
   #73 = Methodref          #20.#72       // shapeless/LabelledProductTypeClassCompanion$$anon$2."<init>":(Lshapeless/LabelledProductTypeClassCompanion;Lshapeless/Witness;Lshapeless/Lazy;Lshapeless/Lazy;)V
   #74 = Utf8               deriveInstance$
   #75 = Utf8               (Lshapeless/LabelledProductTypeClassCompanion;Lshapeless/LabelledGeneric;Lshapeless/Lazy;)Ljava/lang/Object;
   #76 = Utf8               lgen
   #77 = Utf8               lwclkv
   #78 = Utf8               deriveInstance
   #79 = Utf8               (Lshapeless/LabelledGeneric;Lshapeless/Lazy;)Ljava/lang/Object;
   #80 = NameAndType        #78:#79       // deriveInstance:(Lshapeless/LabelledGeneric;Lshapeless/Lazy;)Ljava/lang/Object;
   #81 = InterfaceMethodref #2.#80        // shapeless/LabelledProductTypeClassCompanion.deriveInstance:(Lshapeless/LabelledGeneric;Lshapeless/Lazy;)Ljava/lang/Object;
   #82 = Utf8               Lshapeless/LabelledGeneric;
   #83 = Utf8               <T:Ljava/lang/Object;LKV:Ljava/lang/Object;>(Lshapeless/LabelledGeneric<TT;>;Lshapeless/Lazy<Lshapeless/LabelledProductTypeClassCompanion<TC;>.Wrap<TLKV;>;>;)TC;
   #84 = Utf8               (Ljava/lang/Object;)Ljava/lang/Object;
   #85 = MethodType         #84           //  (Ljava/lang/Object;)Ljava/lang/Object;
   #86 = Utf8               $anonfun$deriveInstance$4
   #87 = Utf8               (Lshapeless/Lazy;Lshapeless/LabelledGeneric;Ljava/lang/Object;)Ljava/lang/Object;
   #88 = NameAndType        #86:#87       // $anonfun$deriveInstance$4:(Lshapeless/Lazy;Lshapeless/LabelledGeneric;Ljava/lang/Object;)Ljava/lang/Object;
   #89 = InterfaceMethodref #2.#88        // shapeless/LabelledProductTypeClassCompanion.$anonfun$deriveInstance$4:(Lshapeless/Lazy;Lshapeless/LabelledGeneric;Ljava/lang/Object;)Ljava/lang/Object;
   #90 = MethodHandle       6:#89         // REF_invokeStatic shapeless/LabelledProductTypeClassCompanion.$anonfun$deriveInstance$4:(Lshapeless/Lazy;Lshapeless/LabelledGeneric;Ljava/lang/Object;)Ljava/lang/Object;
   #91 = Integer            1
   #92 = Utf8               java/lang/invoke/LambdaMetafactory
   #93 = Class              #92           // java/lang/invoke/LambdaMetafactory
   #94 = Utf8               altMetafactory
   #95 = Utf8               (Ljava/lang/invoke/MethodHandles$Lookup;Ljava/lang/String;Ljava/lang/invoke/MethodType;[Ljava/lang/Object;)Ljava/lang/invoke/CallSite;
   #96 = NameAndType        #94:#95       // altMetafactory:(Ljava/lang/invoke/MethodHandles$Lookup;Ljava/lang/String;Ljava/lang/invoke/MethodType;[Ljava/lang/Object;)Ljava/lang/invoke/CallSite;
   #97 = Methodref          #93.#96       // java/lang/invoke/LambdaMetafactory.altMetafactory:(Ljava/lang/invoke/MethodHandles$Lookup;Ljava/lang/String;Ljava/lang/invoke/MethodType;[Ljava/lang/Object;)Ljava/lang/invoke/CallSite;
   #98 = MethodHandle       6:#97         // REF_invokeStatic java/lang/invoke/LambdaMetafactory.altMetafactory:(Ljava/lang/invoke/MethodHandles$Lookup;Ljava/lang/String;Ljava/lang/invoke/MethodType;[Ljava/lang/Object;)Ljava/lang/invoke/CallSite;
   #99 = Utf8               (Lshapeless/Lazy;Lshapeless/LabelledGeneric;)Lscala/Function1;
  #100 = NameAndType        #33:#99       // apply:(Lshapeless/Lazy;Lshapeless/LabelledGeneric;)Lscala/Function1;
  #101 = InvokeDynamic      #0:#100       // #0:apply:(Lshapeless/Lazy;Lshapeless/LabelledGeneric;)Lscala/Function1;
  #102 = Utf8               $anonfun$deriveInstance$5
  #103 = Utf8               (Lshapeless/LabelledGeneric;Lshapeless/Lazy;Ljava/lang/Object;)Ljava/lang/Object;
  #104 = NameAndType        #102:#103     // $anonfun$deriveInstance$5:(Lshapeless/LabelledGeneric;Lshapeless/Lazy;Ljava/lang/Object;)Ljava/lang/Object;
  #105 = InterfaceMethodref #2.#104       // shapeless/LabelledProductTypeClassCompanion.$anonfun$deriveInstance$5:(Lshapeless/LabelledGeneric;Lshapeless/Lazy;Ljava/lang/Object;)Ljava/lang/Object;
  #106 = MethodHandle       6:#105        // REF_invokeStatic shapeless/LabelledProductTypeClassCompanion.$anonfun$deriveInstance$5:(Lshapeless/LabelledGeneric;Lshapeless/Lazy;Ljava/lang/Object;)Ljava/lang/Object;
  #107 = Utf8               (Lshapeless/LabelledGeneric;Lshapeless/Lazy;)Lscala/Function1;
  #108 = NameAndType        #33:#107      // apply:(Lshapeless/LabelledGeneric;Lshapeless/Lazy;)Lscala/Function1;
  #109 = InvokeDynamic      #1:#108       // #1:apply:(Lshapeless/LabelledGeneric;Lshapeless/Lazy;)Lscala/Function1;
  #110 = NameAndType        #47:#48       // typeClass:()Lshapeless/LabelledProductTypeClass;
  #111 = InterfaceMethodref #2.#110       // shapeless/LabelledProductTypeClassCompanion.typeClass:()Lshapeless/LabelledProductTypeClass;
  #112 = MethodType         #43           //  ()Ljava/lang/Object;
  #113 = Utf8               $anonfun$deriveInstance$6
  #114 = NameAndType        #113:#34      // $anonfun$deriveInstance$6:(Lshapeless/Lazy;)Ljava/lang/Object;
  #115 = InterfaceMethodref #2.#114       // shapeless/LabelledProductTypeClassCompanion.$anonfun$deriveInstance$6:(Lshapeless/Lazy;)Ljava/lang/Object;
  #116 = MethodHandle       6:#115        // REF_invokeStatic shapeless/LabelledProductTypeClassCompanion.$anonfun$deriveInstance$6:(Lshapeless/Lazy;)Ljava/lang/Object;
  #117 = Utf8               (Lshapeless/Lazy;)Lscala/Function0;
  #118 = NameAndType        #33:#117      // apply:(Lshapeless/Lazy;)Lscala/Function0;
  #119 = InvokeDynamic      #2:#118       // #2:apply:(Lshapeless/Lazy;)Lscala/Function0;
  #120 = Utf8               shapeless/LabelledProductTypeClass
  #121 = Class              #120          // shapeless/LabelledProductTypeClass
  #122 = Utf8               project
  #123 = Utf8               (Lscala/Function0;Lscala/Function1;Lscala/Function1;)Ljava/lang/Object;
  #124 = NameAndType        #122:#123     // project:(Lscala/Function0;Lscala/Function1;Lscala/Function1;)Ljava/lang/Object;
  #125 = InterfaceMethodref #121.#124     // shapeless/LabelledProductTypeClass.project:(Lscala/Function0;Lscala/Function1;Lscala/Function1;)Ljava/lang/Object;
  #126 = Utf8               to
  #127 = Utf8               Lscala/Function1;
  #128 = Utf8               from
  #129 = Utf8               lwclkv$1
  #130 = Utf8               lgen$1
  #131 = Utf8               t
  #132 = Utf8               shapeless/LabelledGeneric
  #133 = Class              #132          // shapeless/LabelledGeneric
  #134 = NameAndType        #126:#84      // to:(Ljava/lang/Object;)Ljava/lang/Object;
  #135 = InterfaceMethodref #133.#134     // shapeless/LabelledGeneric.to:(Ljava/lang/Object;)Ljava/lang/Object;
  #136 = Utf8               unlabel
  #137 = NameAndType        #136:#84      // unlabel:(Ljava/lang/Object;)Ljava/lang/Object;
  #138 = InterfaceMethodref #22.#137      // shapeless/LabelledProductTypeClassCompanion$Wrap.unlabel:(Ljava/lang/Object;)Ljava/lang/Object;
  #139 = Utf8               Ljava/lang/Object;
  #140 = Utf8               v
  #141 = Utf8               label
  #142 = NameAndType        #141:#84      // label:(Ljava/lang/Object;)Ljava/lang/Object;
  #143 = InterfaceMethodref #22.#142      // shapeless/LabelledProductTypeClassCompanion$Wrap.label:(Ljava/lang/Object;)Ljava/lang/Object;
  #144 = NameAndType        #128:#84      // from:(Ljava/lang/Object;)Ljava/lang/Object;
  #145 = InterfaceMethodref #133.#144     // shapeless/LabelledGeneric.from:(Ljava/lang/Object;)Ljava/lang/Object;
  #146 = Utf8               unwrap
  #147 = NameAndType        #146:#43      // unwrap:()Ljava/lang/Object;
  #148 = InterfaceMethodref #22.#147      // shapeless/LabelledProductTypeClassCompanion$Wrap.unwrap:()Ljava/lang/Object;
  #149 = Utf8               $init$
  #150 = Utf8               $deserializeLambda$
  #151 = Utf8               (Ljava/lang/invoke/SerializedLambda;)Ljava/lang/Object;
  #152 = Utf8               scala/runtime/LambdaDeserialize
  #153 = Class              #152          // scala/runtime/LambdaDeserialize
  #154 = Utf8               bootstrap
  #155 = Utf8               (Ljava/lang/invoke/MethodHandles$Lookup;Ljava/lang/String;Ljava/lang/invoke/MethodType;[Ljava/lang/invoke/MethodHandle;)Ljava/lang/invoke/CallSite;
  #156 = NameAndType        #154:#155     // bootstrap:(Ljava/lang/invoke/MethodHandles$Lookup;Ljava/lang/String;Ljava/lang/invoke/MethodType;[Ljava/lang/invoke/MethodHandle;)Ljava/lang/invoke/CallSite;
  #157 = Methodref          #153.#156     // scala/runtime/LambdaDeserialize.bootstrap:(Ljava/lang/invoke/MethodHandles$Lookup;Ljava/lang/String;Ljava/lang/invoke/MethodType;[Ljava/lang/invoke/MethodHandle;)Ljava/lang/invoke/CallSite;
  #158 = MethodHandle       6:#157        // REF_invokeStatic scala/runtime/LambdaDeserialize.bootstrap:(Ljava/lang/invoke/MethodHandles$Lookup;Ljava/lang/String;Ljava/lang/invoke/MethodType;[Ljava/lang/invoke/MethodHandle;)Ljava/lang/invoke/CallSite;
  #159 = Utf8               lambdaDeserialize
  #160 = NameAndType        #159:#151     // lambdaDeserialize:(Ljava/lang/invoke/SerializedLambda;)Ljava/lang/Object;
  #161 = InvokeDynamic      #3:#160       // #3:lambdaDeserialize:(Ljava/lang/invoke/SerializedLambda;)Ljava/lang/Object;
  #162 = Utf8               Signature
  #163 = Utf8               Code
  #164 = Utf8               LineNumberTable
  #165 = Utf8               LocalVariableTable
  #166 = Utf8               MethodParameters
  #167 = Utf8               InnerClasses
  #168 = Utf8               SourceFile
  #169 = Utf8               RuntimeVisibleAnnotations
  #170 = Utf8               BootstrapMethods
  #171 = Utf8               ScalaInlineInfo
  #172 = Utf8               ScalaSig
{
  public abstract shapeless.LabelledProductTypeClassCompanion<C>.Wrap$ Wrap();
    descriptor: ()Lshapeless/LabelledProductTypeClassCompanion$Wrap$;
    flags: (0x0401) ACC_PUBLIC, ACC_ABSTRACT
    Signature: #28                          // ()Lshapeless/LabelledProductTypeClassCompanion<TC;>.Wrap$;

  public static java.lang.Object apply$(shapeless.LabelledProductTypeClassCompanion, shapeless.Lazy);
    descriptor: (Lshapeless/LabelledProductTypeClassCompanion;Lshapeless/Lazy;)Ljava/lang/Object;
    flags: (0x1009) ACC_PUBLIC, ACC_STATIC, ACC_SYNTHETIC
    Code:
      stack=2, locals=2, args_size=2
         0: aload_0
         1: aload_1
         2: invokespecial #36                 // InterfaceMethod apply:(Lshapeless/Lazy;)Ljava/lang/Object;
         5: areturn
      LineNumberTable:
        line 85: 0
      LocalVariableTable:
        Start  Length  Slot  Name   Signature
            0       6     0 $this   Lshapeless/LabelledProductTypeClassCompanion;
            0       6     1    ct   Lshapeless/Lazy;
    MethodParameters:
      Name                           Flags
      $this                          final synthetic
      ct                             final

  public default <T extends java.lang.Object> C apply(shapeless.Lazy<C>);
    descriptor: (Lshapeless/Lazy;)Ljava/lang/Object;
    flags: (0x0001) ACC_PUBLIC
    Code:
      stack=1, locals=2, args_size=2
         0: aload_1
         1: invokeinterface #45,  1           // InterfaceMethod shapeless/Lazy.value:()Ljava/lang/Object;
         6: areturn
      LineNumberTable:
        line 85: 0
      LocalVariableTable:
        Start  Length  Slot  Name   Signature
            0       7     0  this   Lshapeless/LabelledProductTypeClassCompanion;
            0       7     1    ct   Lshapeless/Lazy;
    Signature: #39                          // <T:Ljava/lang/Object;>(Lshapeless/Lazy<TC;>;)TC;
    MethodParameters:
      Name                           Flags
      ct                             final

  public abstract shapeless.LabelledProductTypeClass<C> typeClass();
    descriptor: ()Lshapeless/LabelledProductTypeClass;
    flags: (0x0401) ACC_PUBLIC, ACC_ABSTRACT
    Signature: #49                          // ()Lshapeless/LabelledProductTypeClass<TC;>;

  public static shapeless.LabelledProductTypeClassCompanion$Wrap deriveHNil$(shapeless.LabelledProductTypeClassCompanion);
    descriptor: (Lshapeless/LabelledProductTypeClassCompanion;)Lshapeless/LabelledProductTypeClassCompanion$Wrap;
    flags: (0x1009) ACC_PUBLIC, ACC_STATIC, ACC_SYNTHETIC
    Code:
      stack=1, locals=1, args_size=1
         0: aload_0
         1: invokespecial #55                 // InterfaceMethod deriveHNil:()Lshapeless/LabelledProductTypeClassCompanion$Wrap;
         4: areturn
      LineNumberTable:
        line 100: 0
      LocalVariableTable:
        Start  Length  Slot  Name   Signature
            0       5     0 $this   Lshapeless/LabelledProductTypeClassCompanion;
    MethodParameters:
      Name                           Flags
      $this                          final synthetic

  public default shapeless.LabelledProductTypeClassCompanion<C>.Wrap<shapeless.HNil> deriveHNil();
    descriptor: ()Lshapeless/LabelledProductTypeClassCompanion$Wrap;
    flags: (0x0001) ACC_PUBLIC
    Code:
      stack=3, locals=1, args_size=1
         0: new           #18                 // class shapeless/LabelledProductTypeClassCompanion$$anon$1
         3: dup
         4: aload_0
         5: invokespecial #60                 // Method shapeless/LabelledProductTypeClassCompanion$$anon$1."<init>":(Lshapeless/LabelledProductTypeClassCompanion;)V
         8: areturn
      LineNumberTable:
        line 101: 0
      LocalVariableTable:
        Start  Length  Slot  Name   Signature
            0       9     0  this   Lshapeless/LabelledProductTypeClassCompanion;
    Signature: #56                          // ()Lshapeless/LabelledProductTypeClassCompanion<TC;>.Wrap<Lshapeless/HNil;>;

  public static shapeless.LabelledProductTypeClassCompanion$Wrap deriveHCons$(shapeless.LabelledProductTypeClassCompanion, shapeless.Lazy, shapeless.Witness, shapeless.Lazy);
    descriptor: (Lshapeless/LabelledProductTypeClassCompanion;Lshapeless/Lazy;Lshapeless/Witness;Lshapeless/Lazy;)Lshapeless/LabelledProductTypeClassCompanion$Wrap;
    flags: (0x1009) ACC_PUBLIC, ACC_STATIC, ACC_SYNTHETIC
    Code:
      stack=4, locals=4, args_size=4
         0: aload_0
         1: aload_1
         2: aload_2
         3: aload_3
         4: invokespecial #68                 // InterfaceMethod deriveHCons:(Lshapeless/Lazy;Lshapeless/Witness;Lshapeless/Lazy;)Lshapeless/LabelledProductTypeClassCompanion$Wrap;
         7: areturn
      LineNumberTable:
        line 108: 0
      LocalVariableTable:
        Start  Length  Slot  Name   Signature
            0       8     0 $this   Lshapeless/LabelledProductTypeClassCompanion;
            0       8     1    ch   Lshapeless/Lazy;
            0       8     2   key   Lshapeless/Witness;
            0       8     3    ct   Lshapeless/Lazy;
    MethodParameters:
      Name                           Flags
      $this                          final synthetic
      ch                             final
      key                            final
      ct                             final

  public default <HK extends scala.Symbol, HV extends java.lang.Object, TKV extends shapeless.HList> shapeless.LabelledProductTypeClassCompanion<C>.Wrap<shapeless.$colon$colon<HV, TKV>> deriveHCons(shapeless.Lazy<C>, shapeless.Witness, shapeless.Lazy<shapeless.LabelledProductTypeClassCompanion<C>.Wrap<TKV>>);
    descriptor: (Lshapeless/Lazy;Lshapeless/Witness;Lshapeless/Lazy;)Lshapeless/LabelledProductTypeClassCompanion$Wrap;
    flags: (0x0001) ACC_PUBLIC
    Code:
      stack=6, locals=4, args_size=4
         0: new           #20                 // class shapeless/LabelledProductTypeClassCompanion$$anon$2
         3: dup
         4: aload_0
         5: aload_2
         6: aload_1
         7: aload_3
         8: invokespecial #73                 // Method shapeless/LabelledProductTypeClassCompanion$$anon$2."<init>":(Lshapeless/LabelledProductTypeClassCompanion;Lshapeless/Witness;Lshapeless/Lazy;Lshapeless/Lazy;)V
        11: areturn
      LineNumberTable:
        line 114: 0
      LocalVariableTable:
        Start  Length  Slot  Name   Signature
            0      12     0  this   Lshapeless/LabelledProductTypeClassCompanion;
            0      12     1    ch   Lshapeless/Lazy;
            0      12     2   key   Lshapeless/Witness;
            0      12     3    ct   Lshapeless/Lazy;
    Signature: #70                          // <HK:Lscala/Symbol;HV:Ljava/lang/Object;TKV::Lshapeless/HList;>(Lshapeless/Lazy<TC;>;Lshapeless/Witness;Lshapeless/Lazy<Lshapeless/LabelledProductTypeClassCompanion<TC;>.Wrap<TTKV;>;>;)Lshapeless/LabelledProductTypeClassCompanion<TC;>.Wrap<Lshapeless/$colon$colon<THV;TTKV;>;>;
    MethodParameters:
      Name                           Flags
      ch                             final
      key                            final
      ct                             final

  public static java.lang.Object deriveInstance$(shapeless.LabelledProductTypeClassCompanion, shapeless.LabelledGeneric, shapeless.Lazy);
    descriptor: (Lshapeless/LabelledProductTypeClassCompanion;Lshapeless/LabelledGeneric;Lshapeless/Lazy;)Ljava/lang/Object;
    flags: (0x1009) ACC_PUBLIC, ACC_STATIC, ACC_SYNTHETIC
    Code:
      stack=3, locals=3, args_size=3
         0: aload_0
         1: aload_1
         2: aload_2
         3: invokespecial #81                 // InterfaceMethod deriveInstance:(Lshapeless/LabelledGeneric;Lshapeless/Lazy;)Ljava/lang/Object;
         6: areturn
      LineNumberTable:
        line 121: 0
      LocalVariableTable:
        Start  Length  Slot  Name   Signature
            0       7     0 $this   Lshapeless/LabelledProductTypeClassCompanion;
            0       7     1  lgen   Lshapeless/LabelledGeneric;
            0       7     2 lwclkv   Lshapeless/Lazy;
    MethodParameters:
      Name                           Flags
      $this                          final synthetic
      lgen                           final
      lwclkv                         final

  public default <T extends java.lang.Object, LKV extends java.lang.Object> C deriveInstance(shapeless.LabelledGeneric<T>, shapeless.Lazy<shapeless.LabelledProductTypeClassCompanion<C>.Wrap<LKV>>);
    descriptor: (Lshapeless/LabelledGeneric;Lshapeless/Lazy;)Ljava/lang/Object;
    flags: (0x0001) ACC_PUBLIC
    Code:
      stack=4, locals=5, args_size=3
         0: aload_2
         1: aload_1
         2: invokedynamic #101,  0            // InvokeDynamic #0:apply:(Lshapeless/Lazy;Lshapeless/LabelledGeneric;)Lscala/Function1;
         7: astore_3
         8: aload_1
         9: aload_2
        10: invokedynamic #109,  0            // InvokeDynamic #1:apply:(Lshapeless/LabelledGeneric;Lshapeless/Lazy;)Lscala/Function1;
        15: astore        4
        17: aload_0
        18: invokeinterface #111,  1          // InterfaceMethod typeClass:()Lshapeless/LabelledProductTypeClass;
        23: aload_2
        24: invokedynamic #119,  0            // InvokeDynamic #2:apply:(Lshapeless/Lazy;)Lscala/Function0;
        29: aload_3
        30: aload         4
        32: invokeinterface #125,  4          // InterfaceMethod shapeless/LabelledProductTypeClass.project:(Lscala/Function0;Lscala/Function1;Lscala/Function1;)Ljava/lang/Object;
        37: areturn
      LineNumberTable:
        line 127: 0
        line 128: 8
        line 129: 17
      LocalVariableTable:
        Start  Length  Slot  Name   Signature
            7      30     3    to   Lscala/Function1;
           15      22     4  from   Lscala/Function1;
            0      38     0  this   Lshapeless/LabelledProductTypeClassCompanion;
            0      38     1  lgen   Lshapeless/LabelledGeneric;
            0      38     2 lwclkv   Lshapeless/Lazy;
    Signature: #83                          // <T:Ljava/lang/Object;LKV:Ljava/lang/Object;>(Lshapeless/LabelledGeneric<TT;>;Lshapeless/Lazy<Lshapeless/LabelledProductTypeClassCompanion<TC;>.Wrap<TLKV;>;>;)TC;
    MethodParameters:
      Name                           Flags
      lgen                           final
      lwclkv                         final

  public static java.lang.Object $anonfun$deriveInstance$4(shapeless.Lazy, shapeless.LabelledGeneric, java.lang.Object);
    descriptor: (Lshapeless/Lazy;Lshapeless/LabelledGeneric;Ljava/lang/Object;)Ljava/lang/Object;
    flags: (0x1009) ACC_PUBLIC, ACC_STATIC, ACC_SYNTHETIC
    Code:
      stack=3, locals=3, args_size=3
         0: aload_0
         1: invokeinterface #45,  1           // InterfaceMethod shapeless/Lazy.value:()Ljava/lang/Object;
         6: checkcast     #22                 // class shapeless/LabelledProductTypeClassCompanion$Wrap
         9: aload_1
        10: aload_2
        11: invokeinterface #135,  2          // InterfaceMethod shapeless/LabelledGeneric.to:(Ljava/lang/Object;)Ljava/lang/Object;
        16: invokeinterface #138,  2          // InterfaceMethod shapeless/LabelledProductTypeClassCompanion$Wrap.unlabel:(Ljava/lang/Object;)Ljava/lang/Object;
        21: areturn
      LineNumberTable:
        line 127: 0
      LocalVariableTable:
        Start  Length  Slot  Name   Signature
            0      22     0 lwclkv$1   Lshapeless/Lazy;
            0      22     1 lgen$1   Lshapeless/LabelledGeneric;
            0      22     2     t   Ljava/lang/Object;
    MethodParameters:
      Name                           Flags
      lwclkv$1                       final
      lgen$1                         final
      t                              final

  public static java.lang.Object $anonfun$deriveInstance$5(shapeless.LabelledGeneric, shapeless.Lazy, java.lang.Object);
    descriptor: (Lshapeless/LabelledGeneric;Lshapeless/Lazy;Ljava/lang/Object;)Ljava/lang/Object;
    flags: (0x1009) ACC_PUBLIC, ACC_STATIC, ACC_SYNTHETIC
    Code:
      stack=3, locals=3, args_size=3
         0: aload_0
         1: aload_1
         2: invokeinterface #45,  1           // InterfaceMethod shapeless/Lazy.value:()Ljava/lang/Object;
         7: checkcast     #22                 // class shapeless/LabelledProductTypeClassCompanion$Wrap
        10: aload_2
        11: invokeinterface #143,  2          // InterfaceMethod shapeless/LabelledProductTypeClassCompanion$Wrap.label:(Ljava/lang/Object;)Ljava/lang/Object;
        16: invokeinterface #145,  2          // InterfaceMethod shapeless/LabelledGeneric.from:(Ljava/lang/Object;)Ljava/lang/Object;
        21: areturn
      LineNumberTable:
        line 128: 0
      LocalVariableTable:
        Start  Length  Slot  Name   Signature
            0      22     0 lgen$1   Lshapeless/LabelledGeneric;
            0      22     1 lwclkv$1   Lshapeless/Lazy;
            0      22     2     v   Ljava/lang/Object;
    MethodParameters:
      Name                           Flags
      lgen$1                         final
      lwclkv$1                       final
      v                              final

  public static java.lang.Object $anonfun$deriveInstance$6(shapeless.Lazy);
    descriptor: (Lshapeless/Lazy;)Ljava/lang/Object;
    flags: (0x1009) ACC_PUBLIC, ACC_STATIC, ACC_SYNTHETIC
    Code:
      stack=1, locals=1, args_size=1
         0: aload_0
         1: invokeinterface #45,  1           // InterfaceMethod shapeless/Lazy.value:()Ljava/lang/Object;
         6: checkcast     #22                 // class shapeless/LabelledProductTypeClassCompanion$Wrap
         9: invokeinterface #148,  1          // InterfaceMethod shapeless/LabelledProductTypeClassCompanion$Wrap.unwrap:()Ljava/lang/Object;
        14: areturn
      LineNumberTable:
        line 129: 0
      LocalVariableTable:
        Start  Length  Slot  Name   Signature
            0      15     0 lwclkv$1   Lshapeless/Lazy;
    MethodParameters:
      Name                           Flags
      lwclkv$1                       final

  public static void $init$(shapeless.LabelledProductTypeClassCompanion);
    descriptor: (Lshapeless/LabelledProductTypeClassCompanion;)V
    flags: (0x0009) ACC_PUBLIC, ACC_STATIC
    Code:
      stack=0, locals=1, args_size=1
         0: return
      LineNumberTable:
        line 84: 0
      LocalVariableTable:
        Start  Length  Slot  Name   Signature
            0       1     0 $this   Lshapeless/LabelledProductTypeClassCompanion;
    MethodParameters:
      Name                           Flags
      $this                          final synthetic

  private static java.lang.Object $deserializeLambda$(java.lang.invoke.SerializedLambda);
    descriptor: (Ljava/lang/invoke/SerializedLambda;)Ljava/lang/Object;
    flags: (0x100a) ACC_PRIVATE, ACC_STATIC, ACC_SYNTHETIC
    Code:
      stack=1, locals=1, args_size=1
         0: aload_0
         1: invokedynamic #161,  0            // InvokeDynamic #3:lambdaDeserialize:(Ljava/lang/invoke/SerializedLambda;)Ljava/lang/Object;
         6: areturn
}
InnerClasses:
  public static final #16= #13 of #15;    // Lookup=class java/lang/invoke/MethodHandles$Lookup of class java/lang/invoke/MethodHandles
  public final #18;                       // class shapeless/LabelledProductTypeClassCompanion$$anon$1
  public final #20;                       // class shapeless/LabelledProductTypeClassCompanion$$anon$2
  public #23= #22 of #2;                  // Wrap=class shapeless/LabelledProductTypeClassCompanion$Wrap of class shapeless/LabelledProductTypeClassCompanion
  public #26= #25 of #2;                  // Wrap$=class shapeless/LabelledProductTypeClassCompanion$Wrap$ of class shapeless/LabelledProductTypeClassCompanion
Signature: #3                           // <C:Ljava/lang/Object;>Ljava/lang/Object;Ljava/io/Serializable;
SourceFile: "typeclass.scala"
RuntimeVisibleAnnotations:
  0: #9(#10=s#11)
    scala.reflect.ScalaSignature(
      bytes="\u0006\u0005\u0005mea\u0002\t\u0012!\u0003\r\t\u0001\u0006\u0005\u0006Q\u0001!\t!\u000b\u0005\u0006[\u0001!\tA\f\u0005\b\u000f\u0002\u0011\rQ\"\u0001I\r\u001di\u0005\u0001%A\u0012\u00029#Q\u0001\u0015\u0003\u0003\u0002UBq!\u0015\u0003C\u0002\u001b\u0005!\u000bC\u0003W\t\u0019\u0005q\u000bC\u0003^\t\u0019\u0005alB\u0003b\u0001!\u0005!MB\u0003N\u0001!\u0005A\rC\u0003m\u0015\u0011\u0005Q.\u0002\u0003o\u0015\u0001y\u0007\"\u0002>\u0001\t\u0007Y\bbBA\u0002\u0001\u0011\r\u0011Q\u0001\u0005\b\u0003c\u0002A1AA:\u0005\u0005b\u0015MY3mY\u0016$\u0007K]8ek\u000e$H+\u001f9f\u00072\f7o]\"p[B\fg.[8o\u0015\u0005\u0011\u0012!C:iCB,G.Z:t\u0007\u0001)\"!\u0006\u001a\u0014\u0007\u00011B\u0004\u0005\u0002\u001855\t\u0001DC\u0001\u001a\u0003\u0015\u00198-\u00197b\u0013\tY\u0002D\u0001\u0004B]f\u0014VM\u001a\t\u0003;\u0015r!AH\u0012\u000f\u0005}\u0011S\"\u0001\u0011\u000b\u0005\u0005\u001a\u0012A\u0002\u001fs_>$h(C\u0001\u001a\u0013\t!\u0003$A\u0004qC\u000e\\\u0017mZ3\n\u0005\u0019:#\u0001D*fe&\fG.\u001b>bE2,\'B\u0001\u0013\u0019\u0003\u0019!\u0013N\\5uIQ\t!\u0006\u0005\u0002\u0018W%\u0011A\u0006\u0007\u0002\u0005+:LG/A\u0003baBd\u00170\u0006\u00020\u007fQ\u0011\u0001\'\u0011\t\u0004cIrD\u0002\u0001\u0003\u0006g\u0001\u0011\r\u0001\u000e\u0002\u0002\u0007V\u0011Q\u0007P\t\u0003me\u0002\"aF\u001c\n\u0005aB\"a\u0002(pi\"Lgn\u001a\t\u0003/iJ!a\u000f\r\u0003\u0007\u0005s\u0017\u0010B\u0003>e\t\u0007QGA\u0001`!\t\tt\bB\u0003A\u0005\t\u0007QGA\u0001U\u0011\u0015\u0011%\u0001q\u0001D\u0003\t\u0019G\u000fE\u0002E\u000bBj\u0011!E\u0005\u0003\rF\u0011A\u0001T1{s\u0006IA/\u001f9f\u00072\f7o]\u000b\u0002\u0013B\u0019AI\u0013\'\n\u0005-\u000b\"\u0001\u0007\'bE\u0016dG.\u001a3Qe>$Wo\u0019;UsB,7\t\\1tgB\u0011\u0011G\r\u0002\u0005/J\f\u0007/\u0006\u0002P3N\u0019AA\u0006\u000f\u0003\u0003Y\u000ba!\u001e8xe\u0006\u0004X#A*\u0011\u0007E\u0012D\u000b\u0005\u0002V\u000b5\tA!A\u0003mC\n,G\u000e\u0006\u0002Y7B\u0011\u0011\'\u0017\u0003\u00065\u0012\u0011\r!\u000e\u0002\u0003\u0017ZCQ\u0001X\u0004A\u0002Q\u000b\u0011A^\u0001\bk:d\u0017MY3m)\t!v\fC\u0003a\u0011\u0001\u0007\u0001,A\u0002sK\u000e\fAa\u0016:baB\u00111MC\u0007\u0002\u0001M\u0019!BF3\u0011\u0005\u0019\\W\"A4\u000b\u0005!L\u0017AA5p\u0015\u0005Q\u0017\u0001\u00026bm\u0006L!AJ4\u0002\rqJg.\u001b;?)\u0005\u0011\'aA!vqV\u0019\u0001/\u001e=\u0013\u0005E\u001ch\u0001\u0002:\u000b\u0001A\u0014A\u0002\u0010:fM&tW-\\3oiz\u00022a\u0019\u0003u!\t\tT\u000fB\u0003[\u0019\t\u0007Q\'\u0002\u0003Qc\u0002:\bCA\u0019y\t\u0015IHB1\u00016\u0005\t1\u0006\'\u0001\u0006eKJLg/\u001a%OS2,\u0012\u0001 \t\u0005{2qhP\u0004\u0002d\u0013A\u0011Ai`\u0005\u0004\u0003\u0003\t\"\u0001\u0002%OS2\f1\u0002Z3sSZ,\u0007jQ8ogVA\u0011qAA\u0011\u0003_\t)\u0004\u0006\u0005\u0002\n\u0005e\u0013\u0011MA%!\u0019iH\"a\u0003\u0002BA9A)!\u0004\u0002\u0012\u0005M\u0012bAA\b#\taAeY8m_:$3m\u001c7p]BA\u00111CA\r\u0003?\tiCD\u0002E\u0003+I1!a\u0006\u0012\u0003!a\u0017MY3mY\u0016$\u0017\u0002BA\u000e\u0003;\u0011\u0011BR5fY\u0012$\u0016\u0010]3\u000b\u0007\u0005]\u0011\u0003E\u00022\u0003C!q!a\t\u000f\u0005\u0004\t)C\u0001\u0002I\u0017F\u0019a\'a\n\u0011\u0007]\tI#C\u0002\u0002,a\u0011aaU=nE>d\u0007cA\u0019\u00020\u00111\u0011\u0011\u0007\bC\u0002U\u0012!\u0001\u0013,\u0011\u0007E\n)\u0004B\u0004\u000289\u0011\r!!\u000f\u0003\u0007Q[e+E\u00027\u0003w\u00012\u0001RA\u001f\u0013\r\ty$\u0005\u0002\u0006\u00112K7\u000f\u001e\t\b\t\u00065\u0011QFA\"!\u0011\t)%a\u0015\u000f\t\u0005\u001d\u0013Q\u000b\b\u0004c\u0005%\u0003B\u0002\"\u000f\u0001\b\tY\u0005\u0005\u0003E\u000b\u00065#\u0003BA(\u0003#2QA\u001d\u0001\u0001\u0003\u001b\u0002Ba\u0019\u0003\u00024\u00119\u0001+a\u0014\u0003\u0002\u0005e\u0012bAA,\u000b\u0006)a/\u00197vK\"9\u00111\f\bA\u0004\u0005u\u0013AA2i!\u0011!U)a\u0018\u0011\tE\u0012\u0014Q\u0006\u0005\b\u0003Gr\u00019AA3\u0003\rYW-\u001f\t\u0007\u0003O\ni\'a\b\u000f\u0007\u0011\u000bI\'C\u0002\u0002lE\tqaV5u]\u0016\u001c8/C\u0002o\u0003_R1!a\u001b\u0012\u00039!WM]5wK&s7\u000f^1oG\u0016,b!!\u001e\u0002|\u0005=ECBA<\u0003{\n\u0019\n\u0005\u00032e\u0005e\u0004cA\u0019\u0002|\u0011)\u0001i\u0004b\u0001k!9\u0011qP\bA\u0004\u0005\u0005\u0015\u0001\u00027hK:\u0004\u0002\"a!\u0002\n\u0006e\u0014Q\u0012\b\u0004\t\u0006\u0015\u0015bAAD#\u0005yA*\u00192fY2,GmR3oKJL7-C\u0002o\u0003\u0017S1!a\"\u0012!\r\t\u0014q\u0012\u0003\u0007\u0003#{!\u0019A\u001b\u0003\u00071[e\u000bC\u0004\u0002\u0016>\u0001\u001d!a&\u0002\r1<8\r\\6w!\u0011!U)!\'\u0011\t\r$\u0011Q\u0012"
    )
BootstrapMethods:
  0: #98 REF_invokeStatic java/lang/invoke/LambdaMetafactory.altMetafactory:(Ljava/lang/invoke/MethodHandles$Lookup;Ljava/lang/String;Ljava/lang/invoke/MethodType;[Ljava/lang/Object;)Ljava/lang/invoke/CallSite;
    Method arguments:
      #85 (Ljava/lang/Object;)Ljava/lang/Object;
      #90 REF_invokeStatic shapeless/LabelledProductTypeClassCompanion.$anonfun$deriveInstance$4:(Lshapeless/Lazy;Lshapeless/LabelledGeneric;Ljava/lang/Object;)Ljava/lang/Object;
      #85 (Ljava/lang/Object;)Ljava/lang/Object;
      #91 1
  1: #98 REF_invokeStatic java/lang/invoke/LambdaMetafactory.altMetafactory:(Ljava/lang/invoke/MethodHandles$Lookup;Ljava/lang/String;Ljava/lang/invoke/MethodType;[Ljava/lang/Object;)Ljava/lang/invoke/CallSite;
    Method arguments:
      #85 (Ljava/lang/Object;)Ljava/lang/Object;
      #106 REF_invokeStatic shapeless/LabelledProductTypeClassCompanion.$anonfun$deriveInstance$5:(Lshapeless/LabelledGeneric;Lshapeless/Lazy;Ljava/lang/Object;)Ljava/lang/Object;
      #85 (Ljava/lang/Object;)Ljava/lang/Object;
      #91 1
  2: #98 REF_invokeStatic java/lang/invoke/LambdaMetafactory.altMetafactory:(Ljava/lang/invoke/MethodHandles$Lookup;Ljava/lang/String;Ljava/lang/invoke/MethodType;[Ljava/lang/Object;)Ljava/lang/invoke/CallSite;
    Method arguments:
      #112 ()Ljava/lang/Object;
      #116 REF_invokeStatic shapeless/LabelledProductTypeClassCompanion.$anonfun$deriveInstance$6:(Lshapeless/Lazy;)Ljava/lang/Object;
      #112 ()Ljava/lang/Object;
      #91 1
  3: #158 REF_invokeStatic scala/runtime/LambdaDeserialize.bootstrap:(Ljava/lang/invoke/MethodHandles$Lookup;Ljava/lang/String;Ljava/lang/invoke/MethodType;[Ljava/lang/invoke/MethodHandle;)Ljava/lang/invoke/CallSite;
    Method arguments:
      #90 REF_invokeStatic shapeless/LabelledProductTypeClassCompanion.$anonfun$deriveInstance$4:(Lshapeless/Lazy;Lshapeless/LabelledGeneric;Ljava/lang/Object;)Ljava/lang/Object;
      #106 REF_invokeStatic shapeless/LabelledProductTypeClassCompanion.$anonfun$deriveInstance$5:(Lshapeless/LabelledGeneric;Lshapeless/Lazy;Ljava/lang/Object;)Ljava/lang/Object;
      #116 REF_invokeStatic shapeless/LabelledProductTypeClassCompanion.$anonfun$deriveInstance$6:(Lshapeless/Lazy;)Ljava/lang/Object;
  ScalaInlineInfo: length = 0x4A (unknown attribute)
   01 00 00 0E 00 56 00 57 01 00 66 00 67 01 00 71
   00 22 01 00 95 00 3A 01 00 17 00 1B 00 00 1D 00
   1E 01 00 21 00 22 00 00 3D 00 3E 01 00 41 00 42
   00 00 32 00 33 01 00 34 00 35 00 00 4A 00 4B 01
   00 4E 00 4F 00 00 2F 00 30 00
  ScalaSig: length = 0x3 (unknown attribute)
   05 02 00
