Classfile /Users/mw/Projects/slang-braindump/.jar/jar11/assemble/slang-braindump/assemble/content/shapeless/LazyMacros$.class
  Last modified May 29, 2022; size 1872 bytes
  SHA-256 checksum 85ab29401108d7269e26166116e6c64968c48995f3026b998a1e5ce97baceb88
  Compiled from "lazy.scala"
public final class shapeless.LazyMacros$ implements shapeless.LazyMacrosCompat
  minor version: 0
  major version: 52
  flags: (0x0031) ACC_PUBLIC, ACC_FINAL, ACC_SUPER
  this_class: #2                          // shapeless/LazyMacros$
  super_class: #4                         // java/lang/Object
  interfaces: 1, fields: 1, methods: 4, attributes: 4
Constant pool:
   #1 = Utf8               shapeless/LazyMacros$
   #2 = Class              #1             // shapeless/LazyMacros$
   #3 = Utf8               java/lang/Object
   #4 = Class              #3             // java/lang/Object
   #5 = Utf8               shapeless/LazyMacrosCompat
   #6 = Class              #5             // shapeless/LazyMacrosCompat
   #7 = Utf8               lazy.scala
   #8 = Utf8               scala/reflect/api/Trees$TreeApi
   #9 = Class              #8             // scala/reflect/api/Trees$TreeApi
  #10 = Utf8               scala/reflect/api/Trees
  #11 = Class              #10            // scala/reflect/api/Trees
  #12 = Utf8               TreeApi
  #13 = Utf8               scala/reflect/api/Types$TypeApi
  #14 = Class              #13            // scala/reflect/api/Types$TypeApi
  #15 = Utf8               scala/reflect/api/Types
  #16 = Class              #15            // scala/reflect/api/Types
  #17 = Utf8               TypeApi
  #18 = Utf8               shapeless/LazyMacros$DerivationContext
  #19 = Class              #18            // shapeless/LazyMacros$DerivationContext
  #20 = Utf8               shapeless/LazyMacros
  #21 = Class              #20            // shapeless/LazyMacros
  #22 = Utf8               DerivationContext
  #23 = Utf8               MODULE$
  #24 = Utf8               Lshapeless/LazyMacros$;
  #25 = Utf8               <clinit>
  #26 = Utf8               ()V
  #27 = Utf8               <init>
  #28 = NameAndType        #27:#26        // "<init>":()V
  #29 = Methodref          #2.#28         // shapeless/LazyMacros$."<init>":()V
  #30 = NameAndType        #23:#24        // MODULE$:Lshapeless/LazyMacros$;
  #31 = Fieldref           #2.#30         // shapeless/LazyMacros$.MODULE$:Lshapeless/LazyMacros$;
  #32 = Utf8               $init$
  #33 = Utf8               (Lshapeless/LazyMacrosCompat;)V
  #34 = NameAndType        #32:#33        // $init$:(Lshapeless/LazyMacrosCompat;)V
  #35 = InterfaceMethodref #6.#34         // shapeless/LazyMacrosCompat.$init$:(Lshapeless/LazyMacrosCompat;)V
  #36 = Utf8               dcRef
  #37 = Utf8               (Lshapeless/LazyMacros;)Lscala/Option;
  #38 = Utf8               (Lshapeless/LazyMacros;)Lscala/Option<Lshapeless/LazyMacros$DerivationContext;>;
  #39 = Utf8               lm
  #40 = Utf8               dcRef$
  #41 = Utf8               (Lshapeless/LazyMacrosCompat;Lshapeless/LazyMacros;)Lscala/Option;
  #42 = NameAndType        #40:#41        // dcRef$:(Lshapeless/LazyMacrosCompat;Lshapeless/LazyMacros;)Lscala/Option;
  #43 = InterfaceMethodref #6.#42         // shapeless/LazyMacrosCompat.dcRef$:(Lshapeless/LazyMacrosCompat;Lshapeless/LazyMacros;)Lscala/Option;
  #44 = Utf8               this
  #45 = Utf8               Lshapeless/LazyMacros;
  #46 = Utf8               deriveInstance
  #47 = Utf8               (Lshapeless/LazyMacros;Lscala/reflect/api/Types$TypeApi;Lscala/Function2;)Lscala/reflect/api/Trees$TreeApi;
  #48 = Utf8               (Lshapeless/LazyMacros;Lscala/reflect/api/Types$TypeApi;Lscala/Function2<Lscala/reflect/api/Trees$TreeApi;Lscala/reflect/api/Types$TypeApi;Lscala/reflect/api/Trees$TreeApi;>;)Lscala/reflect/api/Trees$TreeApi;
  #49 = Utf8               tpe
  #50 = Utf8               mkInst
  #51 = Utf8               deriveInstance$
  #52 = Utf8               (Lshapeless/LazyMacrosCompat;Lshapeless/LazyMacros;Lscala/reflect/api/Types$TypeApi;Lscala/Function2;)Lscala/reflect/api/Trees$TreeApi;
  #53 = NameAndType        #51:#52        // deriveInstance$:(Lshapeless/LazyMacrosCompat;Lshapeless/LazyMacros;Lscala/reflect/api/Types$TypeApi;Lscala/Function2;)Lscala/reflect/api/Trees$TreeApi;
  #54 = InterfaceMethodref #6.#53         // shapeless/LazyMacrosCompat.deriveInstance$:(Lshapeless/LazyMacrosCompat;Lshapeless/LazyMacros;Lscala/reflect/api/Types$TypeApi;Lscala/Function2;)Lscala/reflect/api/Trees$TreeApi;
  #55 = Utf8               Lscala/reflect/api/Types$TypeApi;
  #56 = Utf8               Lscala/Function2;
  #57 = Methodref          #4.#28         // java/lang/Object."<init>":()V
  #58 = Utf8               Code
  #59 = Utf8               LineNumberTable
  #60 = Utf8               LocalVariableTable
  #61 = Utf8               Signature
  #62 = Utf8               MethodParameters
  #63 = Utf8               InnerClasses
  #64 = Utf8               SourceFile
  #65 = Utf8               ScalaInlineInfo
  #66 = Utf8               Scala
{
  public static final shapeless.LazyMacros$ MODULE$;
    descriptor: Lshapeless/LazyMacros$;
    flags: (0x0019) ACC_PUBLIC, ACC_STATIC, ACC_FINAL

  public static {};
    descriptor: ()V
    flags: (0x0009) ACC_PUBLIC, ACC_STATIC
    Code:
      stack=2, locals=0, args_size=0
         0: new           #2                  // class shapeless/LazyMacros$
         3: dup
         4: invokespecial #29                 // Method "<init>":()V
         7: putstatic     #31                 // Field MODULE$:Lshapeless/LazyMacros$;
        10: getstatic     #31                 // Field MODULE$:Lshapeless/LazyMacros$;
        13: invokestatic  #35                 // InterfaceMethod shapeless/LazyMacrosCompat.$init$:(Lshapeless/LazyMacrosCompat;)V
        16: return
      LineNumberTable:
        line 573: 0

  public scala.Option<shapeless.LazyMacros$DerivationContext> dcRef(shapeless.LazyMacros);
    descriptor: (Lshapeless/LazyMacros;)Lscala/Option;
    flags: (0x0001) ACC_PUBLIC
    Code:
      stack=2, locals=2, args_size=2
         0: aload_0
         1: aload_1
         2: invokestatic  #43                 // InterfaceMethod shapeless/LazyMacrosCompat.dcRef$:(Lshapeless/LazyMacrosCompat;Lshapeless/LazyMacros;)Lscala/Option;
         5: areturn
      LineNumberTable:
        line 573: 0
      LocalVariableTable:
        Start  Length  Slot  Name   Signature
            0       6     0  this   Lshapeless/LazyMacros$;
            0       6     1    lm   Lshapeless/LazyMacros;
    Signature: #38                          // (Lshapeless/LazyMacros;)Lscala/Option<Lshapeless/LazyMacros$DerivationContext;>;
    MethodParameters:
      Name                           Flags
      lm                             final

  public scala.reflect.api.Trees$TreeApi deriveInstance(shapeless.LazyMacros, scala.reflect.api.Types$TypeApi, scala.Function2<scala.reflect.api.Trees$TreeApi, scala.reflect.api.Types$TypeApi, scala.reflect.api.Trees$TreeApi>);
    descriptor: (Lshapeless/LazyMacros;Lscala/reflect/api/Types$TypeApi;Lscala/Function2;)Lscala/reflect/api/Trees$TreeApi;
    flags: (0x0001) ACC_PUBLIC
    Code:
      stack=4, locals=4, args_size=4
         0: aload_0
         1: aload_1
         2: aload_2
         3: aload_3
         4: invokestatic  #54                 // InterfaceMethod shapeless/LazyMacrosCompat.deriveInstance$:(Lshapeless/LazyMacrosCompat;Lshapeless/LazyMacros;Lscala/reflect/api/Types$TypeApi;Lscala/Function2;)Lscala/reflect/api/Trees$TreeApi;
         7: areturn
      LineNumberTable:
        line 573: 0
      LocalVariableTable:
        Start  Length  Slot  Name   Signature
            0       8     0  this   Lshapeless/LazyMacros$;
            0       8     1    lm   Lshapeless/LazyMacros;
            0       8     2   tpe   Lscala/reflect/api/Types$TypeApi;
            0       8     3 mkInst   Lscala/Function2;
    Signature: #48                          // (Lshapeless/LazyMacros;Lscala/reflect/api/Types$TypeApi;Lscala/Function2<Lscala/reflect/api/Trees$TreeApi;Lscala/reflect/api/Types$TypeApi;Lscala/reflect/api/Trees$TreeApi;>;)Lscala/reflect/api/Trees$TreeApi;
    MethodParameters:
      Name                           Flags
      lm                             final
      tpe                            final
      mkInst                         final

  private shapeless.LazyMacros$();
    descriptor: ()V
    flags: (0x0002) ACC_PRIVATE
    Code:
      stack=1, locals=1, args_size=1
         0: aload_0
         1: invokespecial #57                 // Method java/lang/Object."<init>":()V
         4: return
      LineNumberTable:
        line 573: 0
      LocalVariableTable:
        Start  Length  Slot  Name   Signature
            0       5     0  this   Lshapeless/LazyMacros$;
}
InnerClasses:
  public #12= #9 of #11;                  // TreeApi=class scala/reflect/api/Trees$TreeApi of class scala/reflect/api/Trees
  public abstract #17= #14 of #16;        // TypeApi=class scala/reflect/api/Types$TypeApi of class scala/reflect/api/Types
  public #22= #19 of #21;                 // DerivationContext=class shapeless/LazyMacros$DerivationContext of class shapeless/LazyMacros
SourceFile: "lazy.scala"
  ScalaInlineInfo: length = 0x13 (unknown attribute)
   01 01 00 03 00 1B 00 1A 01 00 24 00 25 01 00 2E
   00 2F 01
  Scala: length = 0x0 (unknown attribute)

