Classfile /Users/mw/Projects/slang-braindump/.jar/jar11/assemble/slang-braindump/assemble/content/shapeless/LazyMacros$LazyDefinitions$Instance$.class
  Last modified May 29, 2022; size 5304 bytes
  SHA-256 checksum 947fe5ee906b20a50abacf98e02aa8f8032b5a8a3fd7aaaf4a2db8d5b9a65ea7
  Compiled from "lazy.scala"
public class shapeless.LazyMacros$LazyDefinitions$Instance$ implements java.io.Serializable
  minor version: 0
  major version: 52
  flags: (0x0021) ACC_PUBLIC, ACC_SUPER
  this_class: #2                          // shapeless/LazyMacros$LazyDefinitions$Instance$
  super_class: #4                         // java/lang/Object
  interfaces: 1, fields: 1, methods: 4, attributes: 4
Constant pool:
    #1 = Utf8               shapeless/LazyMacros$LazyDefinitions$Instance$
    #2 = Class              #1            // shapeless/LazyMacros$LazyDefinitions$Instance$
    #3 = Utf8               java/lang/Object
    #4 = Class              #3            // java/lang/Object
    #5 = Utf8               java/io/Serializable
    #6 = Class              #5            // java/io/Serializable
    #7 = Utf8               lazy.scala
    #8 = Utf8               scala/reflect/api/Names$TermNameApi
    #9 = Class              #8            // scala/reflect/api/Names$TermNameApi
   #10 = Utf8               scala/reflect/api/Names
   #11 = Class              #10           // scala/reflect/api/Names
   #12 = Utf8               TermNameApi
   #13 = Utf8               scala/reflect/api/Names$TermNameExtractor
   #14 = Class              #13           // scala/reflect/api/Names$TermNameExtractor
   #15 = Utf8               TermNameExtractor
   #16 = Utf8               scala/reflect/api/Symbols$SymbolApi
   #17 = Class              #16           // scala/reflect/api/Symbols$SymbolApi
   #18 = Utf8               scala/reflect/api/Symbols
   #19 = Class              #18           // scala/reflect/api/Symbols
   #20 = Utf8               SymbolApi
   #21 = Utf8               scala/reflect/api/Symbols$TermSymbolApi
   #22 = Class              #21           // scala/reflect/api/Symbols$TermSymbolApi
   #23 = Utf8               TermSymbolApi
   #24 = Utf8               scala/reflect/api/Trees$TreeApi
   #25 = Class              #24           // scala/reflect/api/Trees$TreeApi
   #26 = Utf8               scala/reflect/api/Trees
   #27 = Class              #26           // scala/reflect/api/Trees
   #28 = Utf8               TreeApi
   #29 = Utf8               scala/reflect/api/Types$TypeApi
   #30 = Class              #29           // scala/reflect/api/Types$TypeApi
   #31 = Utf8               scala/reflect/api/Types
   #32 = Class              #31           // scala/reflect/api/Types
   #33 = Utf8               TypeApi
   #34 = Utf8               scala/reflect/macros/Internals$ContextInternalApi
   #35 = Class              #34           // scala/reflect/macros/Internals$ContextInternalApi
   #36 = Utf8               scala/reflect/macros/Internals
   #37 = Class              #36           // scala/reflect/macros/Internals
   #38 = Utf8               ContextInternalApi
   #39 = Utf8               shapeless/LazyMacros$LazyDefinitions
   #40 = Class              #39           // shapeless/LazyMacros$LazyDefinitions
   #41 = Utf8               shapeless/LazyMacros
   #42 = Class              #41           // shapeless/LazyMacros
   #43 = Utf8               LazyDefinitions
   #44 = Utf8               shapeless/LazyMacros$LazyDefinitions$Instance
   #45 = Class              #44           // shapeless/LazyMacros$LazyDefinitions$Instance
   #46 = Utf8               Instance
   #47 = Utf8               Instance$
   #48 = Utf8               $outer
   #49 = Utf8               Lshapeless/LazyMacros$LazyDefinitions;
   #50 = Utf8               apply
   #51 = Utf8               (Lscala/reflect/api/Types$TypeApi;)Lshapeless/LazyMacros$LazyDefinitions$Instance;
   #52 = Utf8               instTpe
   #53 = NameAndType        #48:#49       // $outer:Lshapeless/LazyMacros$LazyDefinitions;
   #54 = Fieldref           #2.#53        // shapeless/LazyMacros$LazyDefinitions$Instance$.$outer:Lshapeless/LazyMacros$LazyDefinitions;
   #55 = Utf8               shapeless$LazyMacros$LazyDefinitions$$$outer
   #56 = Utf8               ()Lshapeless/LazyMacros;
   #57 = NameAndType        #55:#56       // shapeless$LazyMacros$LazyDefinitions$$$outer:()Lshapeless/LazyMacros;
   #58 = InterfaceMethodref #40.#57       // shapeless/LazyMacros$LazyDefinitions.shapeless$LazyMacros$LazyDefinitions$$$outer:()Lshapeless/LazyMacros;
   #59 = Utf8               c
   #60 = Utf8               ()Lscala/reflect/macros/whitebox/Context;
   #61 = NameAndType        #59:#60       // c:()Lscala/reflect/macros/whitebox/Context;
   #62 = Methodref          #42.#61       // shapeless/LazyMacros.c:()Lscala/reflect/macros/whitebox/Context;
   #63 = Utf8               scala/reflect/macros/whitebox/Context
   #64 = Class              #63           // scala/reflect/macros/whitebox/Context
   #65 = Utf8               universe
   #66 = Utf8               ()Lscala/reflect/macros/Universe;
   #67 = NameAndType        #65:#66       // universe:()Lscala/reflect/macros/Universe;
   #68 = InterfaceMethodref #64.#67       // scala/reflect/macros/whitebox/Context.universe:()Lscala/reflect/macros/Universe;
   #69 = Utf8               scala/reflect/macros/Universe
   #70 = Class              #69           // scala/reflect/macros/Universe
   #71 = Utf8               TermName
   #72 = Utf8               ()Lscala/reflect/api/Names$TermNameExtractor;
   #73 = NameAndType        #71:#72       // TermName:()Lscala/reflect/api/Names$TermNameExtractor;
   #74 = Methodref          #70.#73       // scala/reflect/macros/Universe.TermName:()Lscala/reflect/api/Names$TermNameExtractor;
   #75 = Utf8               inst
   #76 = String             #75           // inst
   #77 = Utf8               freshName
   #78 = Utf8               (Ljava/lang/String;)Ljava/lang/String;
   #79 = NameAndType        #77:#78       // freshName:(Ljava/lang/String;)Ljava/lang/String;
   #80 = InterfaceMethodref #64.#79       // scala/reflect/macros/whitebox/Context.freshName:(Ljava/lang/String;)Ljava/lang/String;
   #81 = Utf8               (Ljava/lang/String;)Lscala/reflect/api/Names$TermNameApi;
   #82 = NameAndType        #50:#81       // apply:(Ljava/lang/String;)Lscala/reflect/api/Names$TermNameApi;
   #83 = Methodref          #14.#82       // scala/reflect/api/Names$TermNameExtractor.apply:(Ljava/lang/String;)Lscala/reflect/api/Names$TermNameApi;
   #84 = Utf8               internal
   #85 = Utf8               ()Lscala/reflect/macros/Internals$ContextInternalApi;
   #86 = NameAndType        #84:#85       // internal:()Lscala/reflect/macros/Internals$ContextInternalApi;
   #87 = InterfaceMethodref #64.#86       // scala/reflect/macros/whitebox/Context.internal:()Lscala/reflect/macros/Internals$ContextInternalApi;
   #88 = Utf8               NoSymbol
   #89 = Utf8               ()Lscala/reflect/api/Symbols$SymbolApi;
   #90 = NameAndType        #88:#89       // NoSymbol:()Lscala/reflect/api/Symbols$SymbolApi;
   #91 = Methodref          #70.#90       // scala/reflect/macros/Universe.NoSymbol:()Lscala/reflect/api/Symbols$SymbolApi;
   #92 = Utf8               newTermSymbol$default$3
   #93 = Utf8               ()Lscala/reflect/api/Position;
   #94 = NameAndType        #92:#93       // newTermSymbol$default$3:()Lscala/reflect/api/Position;
   #95 = InterfaceMethodref #35.#94       // scala/reflect/macros/Internals$ContextInternalApi.newTermSymbol$default$3:()Lscala/reflect/api/Position;
   #96 = Utf8               newTermSymbol$default$4
   #97 = Utf8               ()Ljava/lang/Object;
   #98 = NameAndType        #96:#97       // newTermSymbol$default$4:()Ljava/lang/Object;
   #99 = InterfaceMethodref #35.#98       // scala/reflect/macros/Internals$ContextInternalApi.newTermSymbol$default$4:()Ljava/lang/Object;
  #100 = Utf8               newTermSymbol
  #101 = Utf8               (Lscala/reflect/api/Symbols$SymbolApi;Lscala/reflect/api/Names$TermNameApi;Lscala/reflect/api/Position;Ljava/lang/Object;)Lscala/reflect/api/Symbols$TermSymbolApi;
  #102 = NameAndType        #100:#101     // newTermSymbol:(Lscala/reflect/api/Symbols$SymbolApi;Lscala/reflect/api/Names$TermNameApi;Lscala/reflect/api/Position;Ljava/lang/Object;)Lscala/reflect/api/Symbols$TermSymbolApi;
  #103 = InterfaceMethodref #35.#102      // scala/reflect/macros/Internals$ContextInternalApi.newTermSymbol:(Lscala/reflect/api/Symbols$SymbolApi;Lscala/reflect/api/Names$TermNameApi;Lscala/reflect/api/Position;Ljava/lang/Object;)Lscala/reflect/api/Symbols$TermSymbolApi;
  #104 = Utf8               setInfo
  #105 = Utf8               (Lscala/reflect/api/Symbols$SymbolApi;Lscala/reflect/api/Types$TypeApi;)Lscala/reflect/api/Symbols$SymbolApi;
  #106 = NameAndType        #104:#105     // setInfo:(Lscala/reflect/api/Symbols$SymbolApi;Lscala/reflect/api/Types$TypeApi;)Lscala/reflect/api/Symbols$SymbolApi;
  #107 = InterfaceMethodref #35.#106      // scala/reflect/macros/Internals$ContextInternalApi.setInfo:(Lscala/reflect/api/Symbols$SymbolApi;Lscala/reflect/api/Types$TypeApi;)Lscala/reflect/api/Symbols$SymbolApi;
  #108 = Utf8               scala/None$
  #109 = Class              #108          // scala/None$
  #110 = Utf8               MODULE$
  #111 = Utf8               Lscala/None$;
  #112 = NameAndType        #110:#111     // MODULE$:Lscala/None$;
  #113 = Fieldref           #109.#112     // scala/None$.MODULE$:Lscala/None$;
  #114 = Utf8               scala/collection/immutable/Nil$
  #115 = Class              #114          // scala/collection/immutable/Nil$
  #116 = Utf8               Lscala/collection/immutable/Nil$;
  #117 = NameAndType        #110:#116     // MODULE$:Lscala/collection/immutable/Nil$;
  #118 = Fieldref           #115.#117     // scala/collection/immutable/Nil$.MODULE$:Lscala/collection/immutable/Nil$;
  #119 = Utf8               <init>
  #120 = Utf8               (Lshapeless/LazyMacros$LazyDefinitions;Lscala/reflect/api/Types$TypeApi;Lscala/reflect/api/Names$TermNameApi;Lscala/reflect/api/Symbols$SymbolApi;Lscala/Option;Lscala/reflect/api/Types$TypeApi;Lscala/collection/immutable/List;)V
  #121 = NameAndType        #119:#120     // "<init>":(Lshapeless/LazyMacros$LazyDefinitions;Lscala/reflect/api/Types$TypeApi;Lscala/reflect/api/Names$TermNameApi;Lscala/reflect/api/Symbols$SymbolApi;Lscala/Option;Lscala/reflect/api/Types$TypeApi;Lscala/collection/immutable/List;)V
  #122 = Methodref          #45.#121      // shapeless/LazyMacros$LazyDefinitions$Instance."<init>":(Lshapeless/LazyMacros$LazyDefinitions;Lscala/reflect/api/Types$TypeApi;Lscala/reflect/api/Names$TermNameApi;Lscala/reflect/api/Symbols$SymbolApi;Lscala/Option;Lscala/reflect/api/Types$TypeApi;Lscala/collection/immutable/List;)V
  #123 = Utf8               nme
  #124 = Utf8               Lscala/reflect/api/Names$TermNameApi;
  #125 = Utf8               sym
  #126 = Utf8               Lscala/reflect/api/Symbols$TermSymbolApi;
  #127 = Utf8               this
  #128 = Utf8               Lshapeless/LazyMacros$LazyDefinitions$Instance$;
  #129 = Utf8               Lscala/reflect/api/Types$TypeApi;
  #130 = Utf8               (Lscala/reflect/api/Types$TypeApi;Lscala/reflect/api/Names$TermNameApi;Lscala/reflect/api/Symbols$SymbolApi;Lscala/Option;Lscala/reflect/api/Types$TypeApi;Lscala/collection/immutable/List;)Lshapeless/LazyMacros$LazyDefinitions$Instance;
  #131 = Utf8               (Lscala/reflect/api/Types$TypeApi;Lscala/reflect/api/Names$TermNameApi;Lscala/reflect/api/Symbols$SymbolApi;Lscala/Option<Lscala/reflect/api/Trees$TreeApi;>;Lscala/reflect/api/Types$TypeApi;Lscala/collection/immutable/List<Lscala/reflect/api/Types$TypeApi;>;)Lshapeless/LazyMacros$LazyDefinitions$Instance;
  #132 = Utf8               name
  #133 = Utf8               symbol
  #134 = Utf8               actualTpe
  #135 = Utf8               dependsOn
  #136 = Utf8               Lscala/reflect/api/Symbols$SymbolApi;
  #137 = Utf8               Lscala/Option;
  #138 = Utf8               Lscala/collection/immutable/List;
  #139 = Utf8               unapply
  #140 = Utf8               (Lshapeless/LazyMacros$LazyDefinitions$Instance;)Lscala/Option;
  #141 = Utf8               (Lshapeless/LazyMacros$LazyDefinitions$Instance;)Lscala/Option<Lscala/Tuple6<Lscala/reflect/api/Types$TypeApi;Lscala/reflect/api/Names$TermNameApi;Lscala/reflect/api/Symbols$SymbolApi;Lscala/Option<Lscala/reflect/api/Trees$TreeApi;>;Lscala/reflect/api/Types$TypeApi;Lscala/collection/immutable/List<Lscala/reflect/api/Types$TypeApi;>;>;>;
  #142 = Utf8               x$0
  #143 = Utf8               scala/Some
  #144 = Class              #143          // scala/Some
  #145 = Utf8               scala/Tuple6
  #146 = Class              #145          // scala/Tuple6
  #147 = Utf8               ()Lscala/reflect/api/Types$TypeApi;
  #148 = NameAndType        #52:#147      // instTpe:()Lscala/reflect/api/Types$TypeApi;
  #149 = Methodref          #45.#148      // shapeless/LazyMacros$LazyDefinitions$Instance.instTpe:()Lscala/reflect/api/Types$TypeApi;
  #150 = Utf8               ()Lscala/reflect/api/Names$TermNameApi;
  #151 = NameAndType        #132:#150     // name:()Lscala/reflect/api/Names$TermNameApi;
  #152 = Methodref          #45.#151      // shapeless/LazyMacros$LazyDefinitions$Instance.name:()Lscala/reflect/api/Names$TermNameApi;
  #153 = NameAndType        #133:#89      // symbol:()Lscala/reflect/api/Symbols$SymbolApi;
  #154 = Methodref          #45.#153      // shapeless/LazyMacros$LazyDefinitions$Instance.symbol:()Lscala/reflect/api/Symbols$SymbolApi;
  #155 = Utf8               ()Lscala/Option;
  #156 = NameAndType        #75:#155      // inst:()Lscala/Option;
  #157 = Methodref          #45.#156      // shapeless/LazyMacros$LazyDefinitions$Instance.inst:()Lscala/Option;
  #158 = NameAndType        #134:#147     // actualTpe:()Lscala/reflect/api/Types$TypeApi;
  #159 = Methodref          #45.#158      // shapeless/LazyMacros$LazyDefinitions$Instance.actualTpe:()Lscala/reflect/api/Types$TypeApi;
  #160 = Utf8               ()Lscala/collection/immutable/List;
  #161 = NameAndType        #135:#160     // dependsOn:()Lscala/collection/immutable/List;
  #162 = Methodref          #45.#161      // shapeless/LazyMacros$LazyDefinitions$Instance.dependsOn:()Lscala/collection/immutable/List;
  #163 = Utf8               (Ljava/lang/Object;Ljava/lang/Object;Ljava/lang/Object;Ljava/lang/Object;Ljava/lang/Object;Ljava/lang/Object;)V
  #164 = NameAndType        #119:#163     // "<init>":(Ljava/lang/Object;Ljava/lang/Object;Ljava/lang/Object;Ljava/lang/Object;Ljava/lang/Object;Ljava/lang/Object;)V
  #165 = Methodref          #146.#164     // scala/Tuple6."<init>":(Ljava/lang/Object;Ljava/lang/Object;Ljava/lang/Object;Ljava/lang/Object;Ljava/lang/Object;Ljava/lang/Object;)V
  #166 = Utf8               (Ljava/lang/Object;)V
  #167 = NameAndType        #119:#166     // "<init>":(Ljava/lang/Object;)V
  #168 = Methodref          #144.#167     // scala/Some."<init>":(Ljava/lang/Object;)V
  #169 = Utf8               Lshapeless/LazyMacros$LazyDefinitions$Instance;
  #170 = Utf8               scala/Option
  #171 = Class              #170          // scala/Option
  #172 = Utf8               (Lshapeless/LazyMacros$LazyDefinitions;)V
  #173 = Utf8               ()V
  #174 = NameAndType        #119:#173     // "<init>":()V
  #175 = Methodref          #4.#174       // java/lang/Object."<init>":()V
  #176 = Utf8               Code
  #177 = Utf8               LineNumberTable
  #178 = Utf8               LocalVariableTable
  #179 = Utf8               MethodParameters
  #180 = Utf8               Signature
  #181 = Utf8               StackMapTable
  #182 = Utf8               InnerClasses
  #183 = Utf8               SourceFile
  #184 = Utf8               ScalaInlineInfo
  #185 = Utf8               Scala
{
  private final shapeless.LazyMacros$LazyDefinitions $outer;
    descriptor: Lshapeless/LazyMacros$LazyDefinitions;
    flags: (0x1012) ACC_PRIVATE, ACC_FINAL, ACC_SYNTHETIC

  public shapeless.LazyMacros$LazyDefinitions$Instance apply(scala.reflect.api.Types$TypeApi);
    descriptor: (Lscala/reflect/api/Types$TypeApi;)Lshapeless/LazyMacros$LazyDefinitions$Instance;
    flags: (0x0001) ACC_PUBLIC
    Code:
      stack=9, locals=4, args_size=2
         0: aload_0
         1: getfield      #54                 // Field $outer:Lshapeless/LazyMacros$LazyDefinitions;
         4: invokeinterface #58,  1           // InterfaceMethod shapeless/LazyMacros$LazyDefinitions.shapeless$LazyMacros$LazyDefinitions$$$outer:()Lshapeless/LazyMacros;
         9: invokevirtual #62                 // Method shapeless/LazyMacros.c:()Lscala/reflect/macros/whitebox/Context;
        12: invokeinterface #68,  1           // InterfaceMethod scala/reflect/macros/whitebox/Context.universe:()Lscala/reflect/macros/Universe;
        17: invokevirtual #74                 // Method scala/reflect/macros/Universe.TermName:()Lscala/reflect/api/Names$TermNameExtractor;
        20: aload_0
        21: getfield      #54                 // Field $outer:Lshapeless/LazyMacros$LazyDefinitions;
        24: invokeinterface #58,  1           // InterfaceMethod shapeless/LazyMacros$LazyDefinitions.shapeless$LazyMacros$LazyDefinitions$$$outer:()Lshapeless/LazyMacros;
        29: invokevirtual #62                 // Method shapeless/LazyMacros.c:()Lscala/reflect/macros/whitebox/Context;
        32: ldc           #76                 // String inst
        34: invokeinterface #80,  2           // InterfaceMethod scala/reflect/macros/whitebox/Context.freshName:(Ljava/lang/String;)Ljava/lang/String;
        39: invokevirtual #83                 // Method scala/reflect/api/Names$TermNameExtractor.apply:(Ljava/lang/String;)Lscala/reflect/api/Names$TermNameApi;
        42: astore_2
        43: aload_0
        44: getfield      #54                 // Field $outer:Lshapeless/LazyMacros$LazyDefinitions;
        47: invokeinterface #58,  1           // InterfaceMethod shapeless/LazyMacros$LazyDefinitions.shapeless$LazyMacros$LazyDefinitions$$$outer:()Lshapeless/LazyMacros;
        52: invokevirtual #62                 // Method shapeless/LazyMacros.c:()Lscala/reflect/macros/whitebox/Context;
        55: invokeinterface #87,  1           // InterfaceMethod scala/reflect/macros/whitebox/Context.internal:()Lscala/reflect/macros/Internals$ContextInternalApi;
        60: aload_0
        61: getfield      #54                 // Field $outer:Lshapeless/LazyMacros$LazyDefinitions;
        64: invokeinterface #58,  1           // InterfaceMethod shapeless/LazyMacros$LazyDefinitions.shapeless$LazyMacros$LazyDefinitions$$$outer:()Lshapeless/LazyMacros;
        69: invokevirtual #62                 // Method shapeless/LazyMacros.c:()Lscala/reflect/macros/whitebox/Context;
        72: invokeinterface #87,  1           // InterfaceMethod scala/reflect/macros/whitebox/Context.internal:()Lscala/reflect/macros/Internals$ContextInternalApi;
        77: aload_0
        78: getfield      #54                 // Field $outer:Lshapeless/LazyMacros$LazyDefinitions;
        81: invokeinterface #58,  1           // InterfaceMethod shapeless/LazyMacros$LazyDefinitions.shapeless$LazyMacros$LazyDefinitions$$$outer:()Lshapeless/LazyMacros;
        86: invokevirtual #62                 // Method shapeless/LazyMacros.c:()Lscala/reflect/macros/whitebox/Context;
        89: invokeinterface #68,  1           // InterfaceMethod scala/reflect/macros/whitebox/Context.universe:()Lscala/reflect/macros/Universe;
        94: invokevirtual #91                 // Method scala/reflect/macros/Universe.NoSymbol:()Lscala/reflect/api/Symbols$SymbolApi;
        97: aload_2
        98: aload_0
        99: getfield      #54                 // Field $outer:Lshapeless/LazyMacros$LazyDefinitions;
       102: invokeinterface #58,  1           // InterfaceMethod shapeless/LazyMacros$LazyDefinitions.shapeless$LazyMacros$LazyDefinitions$$$outer:()Lshapeless/LazyMacros;
       107: invokevirtual #62                 // Method shapeless/LazyMacros.c:()Lscala/reflect/macros/whitebox/Context;
       110: invokeinterface #87,  1           // InterfaceMethod scala/reflect/macros/whitebox/Context.internal:()Lscala/reflect/macros/Internals$ContextInternalApi;
       115: invokeinterface #95,  1           // InterfaceMethod scala/reflect/macros/Internals$ContextInternalApi.newTermSymbol$default$3:()Lscala/reflect/api/Position;
       120: aload_0
       121: getfield      #54                 // Field $outer:Lshapeless/LazyMacros$LazyDefinitions;
       124: invokeinterface #58,  1           // InterfaceMethod shapeless/LazyMacros$LazyDefinitions.shapeless$LazyMacros$LazyDefinitions$$$outer:()Lshapeless/LazyMacros;
       129: invokevirtual #62                 // Method shapeless/LazyMacros.c:()Lscala/reflect/macros/whitebox/Context;
       132: invokeinterface #87,  1           // InterfaceMethod scala/reflect/macros/whitebox/Context.internal:()Lscala/reflect/macros/Internals$ContextInternalApi;
       137: invokeinterface #99,  1           // InterfaceMethod scala/reflect/macros/Internals$ContextInternalApi.newTermSymbol$default$4:()Ljava/lang/Object;
       142: invokeinterface #103,  5          // InterfaceMethod scala/reflect/macros/Internals$ContextInternalApi.newTermSymbol:(Lscala/reflect/api/Symbols$SymbolApi;Lscala/reflect/api/Names$TermNameApi;Lscala/reflect/api/Position;Ljava/lang/Object;)Lscala/reflect/api/Symbols$TermSymbolApi;
       147: aload_1
       148: invokeinterface #107,  3          // InterfaceMethod scala/reflect/macros/Internals$ContextInternalApi.setInfo:(Lscala/reflect/api/Symbols$SymbolApi;Lscala/reflect/api/Types$TypeApi;)Lscala/reflect/api/Symbols$SymbolApi;
       153: checkcast     #22                 // class scala/reflect/api/Symbols$TermSymbolApi
       156: astore_3
       157: new           #45                 // class shapeless/LazyMacros$LazyDefinitions$Instance
       160: dup
       161: aload_0
       162: getfield      #54                 // Field $outer:Lshapeless/LazyMacros$LazyDefinitions;
       165: aload_1
       166: aload_2
       167: aload_3
       168: getstatic     #113                // Field scala/None$.MODULE$:Lscala/None$;
       171: aload_1
       172: getstatic     #118                // Field scala/collection/immutable/Nil$.MODULE$:Lscala/collection/immutable/Nil$;
       175: invokespecial #122                // Method shapeless/LazyMacros$LazyDefinitions$Instance."<init>":(Lshapeless/LazyMacros$LazyDefinitions;Lscala/reflect/api/Types$TypeApi;Lscala/reflect/api/Names$TermNameApi;Lscala/reflect/api/Symbols$SymbolApi;Lscala/Option;Lscala/reflect/api/Types$TypeApi;Lscala/collection/immutable/List;)V
       178: areturn
      LineNumberTable:
        line 270: 0
        line 271: 43
        line 273: 157
      LocalVariableTable:
        Start  Length  Slot  Name   Signature
           42     136     2   nme   Lscala/reflect/api/Names$TermNameApi;
          156      22     3   sym   Lscala/reflect/api/Symbols$TermSymbolApi;
            0     179     0  this   Lshapeless/LazyMacros$LazyDefinitions$Instance$;
            0     179     1 instTpe   Lscala/reflect/api/Types$TypeApi;
    MethodParameters:
      Name                           Flags
      instTpe                        final

  public shapeless.LazyMacros$LazyDefinitions$Instance apply(scala.reflect.api.Types$TypeApi, scala.reflect.api.Names$TermNameApi, scala.reflect.api.Symbols$SymbolApi, scala.Option<scala.reflect.api.Trees$TreeApi>, scala.reflect.api.Types$TypeApi, scala.collection.immutable.List<scala.reflect.api.Types$TypeApi>);
    descriptor: (Lscala/reflect/api/Types$TypeApi;Lscala/reflect/api/Names$TermNameApi;Lscala/reflect/api/Symbols$SymbolApi;Lscala/Option;Lscala/reflect/api/Types$TypeApi;Lscala/collection/immutable/List;)Lshapeless/LazyMacros$LazyDefinitions$Instance;
    flags: (0x0001) ACC_PUBLIC
    Code:
      stack=9, locals=7, args_size=7
         0: new           #45                 // class shapeless/LazyMacros$LazyDefinitions$Instance
         3: dup
         4: aload_0
         5: getfield      #54                 // Field $outer:Lshapeless/LazyMacros$LazyDefinitions;
         8: aload_1
         9: aload_2
        10: aload_3
        11: aload         4
        13: aload         5
        15: aload         6
        17: invokespecial #122                // Method shapeless/LazyMacros$LazyDefinitions$Instance."<init>":(Lshapeless/LazyMacros$LazyDefinitions;Lscala/reflect/api/Types$TypeApi;Lscala/reflect/api/Names$TermNameApi;Lscala/reflect/api/Symbols$SymbolApi;Lscala/Option;Lscala/reflect/api/Types$TypeApi;Lscala/collection/immutable/List;)V
        20: areturn
      LineNumberTable:
        line 257: 0
      LocalVariableTable:
        Start  Length  Slot  Name   Signature
            0      21     0  this   Lshapeless/LazyMacros$LazyDefinitions$Instance$;
            0      21     1 instTpe   Lscala/reflect/api/Types$TypeApi;
            0      21     2  name   Lscala/reflect/api/Names$TermNameApi;
            0      21     3 symbol   Lscala/reflect/api/Symbols$SymbolApi;
            0      21     4  inst   Lscala/Option;
            0      21     5 actualTpe   Lscala/reflect/api/Types$TypeApi;
            0      21     6 dependsOn   Lscala/collection/immutable/List;
    Signature: #131                         // (Lscala/reflect/api/Types$TypeApi;Lscala/reflect/api/Names$TermNameApi;Lscala/reflect/api/Symbols$SymbolApi;Lscala/Option<Lscala/reflect/api/Trees$TreeApi;>;Lscala/reflect/api/Types$TypeApi;Lscala/collection/immutable/List<Lscala/reflect/api/Types$TypeApi;>;)Lshapeless/LazyMacros$LazyDefinitions$Instance;
    MethodParameters:
      Name                           Flags
      instTpe                        final
      name                           final
      symbol                         final
      inst                           final
      actualTpe                      final
      dependsOn                      final

  public scala.Option<scala.Tuple6<scala.reflect.api.Types$TypeApi, scala.reflect.api.Names$TermNameApi, scala.reflect.api.Symbols$SymbolApi, scala.Option<scala.reflect.api.Trees$TreeApi>, scala.reflect.api.Types$TypeApi, scala.collection.immutable.List<scala.reflect.api.Types$TypeApi>>> unapply(shapeless.LazyMacros$LazyDefinitions$Instance);
    descriptor: (Lshapeless/LazyMacros$LazyDefinitions$Instance;)Lscala/Option;
    flags: (0x0001) ACC_PUBLIC
    Code:
      stack=10, locals=2, args_size=2
         0: aload_1
         1: ifnonnull     10
         4: getstatic     #113                // Field scala/None$.MODULE$:Lscala/None$;
         7: goto          48
        10: new           #144                // class scala/Some
        13: dup
        14: new           #146                // class scala/Tuple6
        17: dup
        18: aload_1
        19: invokevirtual #149                // Method shapeless/LazyMacros$LazyDefinitions$Instance.instTpe:()Lscala/reflect/api/Types$TypeApi;
        22: aload_1
        23: invokevirtual #152                // Method shapeless/LazyMacros$LazyDefinitions$Instance.name:()Lscala/reflect/api/Names$TermNameApi;
        26: aload_1
        27: invokevirtual #154                // Method shapeless/LazyMacros$LazyDefinitions$Instance.symbol:()Lscala/reflect/api/Symbols$SymbolApi;
        30: aload_1
        31: invokevirtual #157                // Method shapeless/LazyMacros$LazyDefinitions$Instance.inst:()Lscala/Option;
        34: aload_1
        35: invokevirtual #159                // Method shapeless/LazyMacros$LazyDefinitions$Instance.actualTpe:()Lscala/reflect/api/Types$TypeApi;
        38: aload_1
        39: invokevirtual #162                // Method shapeless/LazyMacros$LazyDefinitions$Instance.dependsOn:()Lscala/collection/immutable/List;
        42: invokespecial #165                // Method scala/Tuple6."<init>":(Ljava/lang/Object;Ljava/lang/Object;Ljava/lang/Object;Ljava/lang/Object;Ljava/lang/Object;Ljava/lang/Object;)V
        45: invokespecial #168                // Method scala/Some."<init>":(Ljava/lang/Object;)V
        48: areturn
      StackMapTable: number_of_entries = 2
        frame_type = 10 /* same */
        frame_type = 101 /* same_locals_1_stack_item */
          stack = [ class scala/Option ]
      LineNumberTable:
        line 257: 0
      LocalVariableTable:
        Start  Length  Slot  Name   Signature
            0      49     0  this   Lshapeless/LazyMacros$LazyDefinitions$Instance$;
            0      49     1   x$0   Lshapeless/LazyMacros$LazyDefinitions$Instance;
    Signature: #141                         // (Lshapeless/LazyMacros$LazyDefinitions$Instance;)Lscala/Option<Lscala/Tuple6<Lscala/reflect/api/Types$TypeApi;Lscala/reflect/api/Names$TermNameApi;Lscala/reflect/api/Symbols$SymbolApi;Lscala/Option<Lscala/reflect/api/Trees$TreeApi;>;Lscala/reflect/api/Types$TypeApi;Lscala/collection/immutable/List<Lscala/reflect/api/Types$TypeApi;>;>;>;
    MethodParameters:
      Name                           Flags
      x$0                            final

  public shapeless.LazyMacros$LazyDefinitions$Instance$(shapeless.LazyMacros$LazyDefinitions);
    descriptor: (Lshapeless/LazyMacros$LazyDefinitions;)V
    flags: (0x0001) ACC_PUBLIC
    Code:
      stack=2, locals=2, args_size=2
         0: aload_1
         1: ifnonnull     6
         4: aconst_null
         5: athrow
         6: aload_0
         7: aload_1
         8: putfield      #54                 // Field $outer:Lshapeless/LazyMacros$LazyDefinitions;
        11: aload_0
        12: invokespecial #175                // Method java/lang/Object."<init>":()V
        15: return
      StackMapTable: number_of_entries = 1
        frame_type = 6 /* same */
      LineNumberTable:
        line 268: 0
        line 277: 11
        line 268: 15
      LocalVariableTable:
        Start  Length  Slot  Name   Signature
            0      16     0  this   Lshapeless/LazyMacros$LazyDefinitions$Instance$;
            0      16     1 $outer   Lshapeless/LazyMacros$LazyDefinitions;
    MethodParameters:
      Name                           Flags
      $outer                         final synthetic
}
InnerClasses:
  public #12= #9 of #11;                  // TermNameApi=class scala/reflect/api/Names$TermNameApi of class scala/reflect/api/Names
  public abstract #15= #14 of #11;        // TermNameExtractor=class scala/reflect/api/Names$TermNameExtractor of class scala/reflect/api/Names
  public #20= #17 of #19;                 // SymbolApi=class scala/reflect/api/Symbols$SymbolApi of class scala/reflect/api/Symbols
  public #23= #22 of #19;                 // TermSymbolApi=class scala/reflect/api/Symbols$TermSymbolApi of class scala/reflect/api/Symbols
  public #28= #25 of #27;                 // TreeApi=class scala/reflect/api/Trees$TreeApi of class scala/reflect/api/Trees
  public abstract #33= #30 of #32;        // TypeApi=class scala/reflect/api/Types$TypeApi of class scala/reflect/api/Types
  public #38= #35 of #37;                 // ContextInternalApi=class scala/reflect/macros/Internals$ContextInternalApi of class scala/reflect/macros/Internals
  public #43= #40 of #42;                 // LazyDefinitions=class shapeless/LazyMacros$LazyDefinitions of class shapeless/LazyMacros
  public #46= #45 of #40;                 // Instance=class shapeless/LazyMacros$LazyDefinitions$Instance of class shapeless/LazyMacros$LazyDefinitions
  public #47= #2 of #40;                  // Instance$=class shapeless/LazyMacros$LazyDefinitions$Instance$ of class shapeless/LazyMacros$LazyDefinitions
SourceFile: "lazy.scala"
  ScalaInlineInfo: length = 0x18 (unknown attribute)
   01 01 00 04 00 77 00 AC 01 00 32 00 33 01 00 32
   00 82 01 00 8B 00 8C 01
  Scala: length = 0x0 (unknown attribute)

