Classfile /Users/mw/Projects/slang-braindump/.jar/jar11/assemble/slang-braindump/assemble/content/shapeless/Lazy.class
  Last modified May 29, 2022; size 5505 bytes
  SHA-256 checksum 8b49f06359a7043ea454a5490084328e77a7bed678f719985027632d6e4d2d23
  Compiled from "lazy.scala"
public interface shapeless.Lazy<T extends java.lang.Object> extends java.io.Serializable
  minor version: 0
  major version: 52
  flags: (0x0601) ACC_PUBLIC, ACC_INTERFACE, ACC_ABSTRACT
  this_class: #2                          // shapeless/Lazy
  super_class: #5                         // java/lang/Object
  interfaces: 1, fields: 0, methods: 12, attributes: 7
Constant pool:
    #1 = Utf8               shapeless/Lazy
    #2 = Class              #1            // shapeless/Lazy
    #3 = Utf8               <T:Ljava/lang/Object;>Ljava/lang/Object;Ljava/io/Serializable;
    #4 = Utf8               java/lang/Object
    #5 = Class              #4            // java/lang/Object
    #6 = Utf8               java/io/Serializable
    #7 = Class              #6            // java/io/Serializable
    #8 = Utf8               lazy.scala
    #9 = Utf8               Lscala/reflect/ScalaSignature;
   #10 = Utf8               bytes
   #11 = Utf8               \u0006\u0005\t=ba\u0002\r\u001a!\u0003\r\t\u0001\b\u0005\u0006a\u0001!\t!\r\u0005\bk\u0001\u0011\rQ\"\u00017\u0011\u0015\u0011\u0005\u0001\"\u0001D\u0011\u0015y\u0005\u0001\"\u0001Q\u000f\u0015\u0001\u0017\u0004#\u0001b\r\u0015A\u0012\u0004#\u0001c\u0011\u0015Qg\u0001\"\u0001l\u0011\u0015ag\u0001b\u0001n\u0011\u00159h\u0001\"\u0001y\r\u0019\t)A\u0002\u0001\u0002\b!Q\u00111\u0002\u0006\u0003\u0006\u0004%\t!!\u0004\t\u0015\u0005m!B!A!\u0002\u0013\ty\u0001\u0003\u0004k\u0015\u0011\u0005\u0011QD\u0004\b\u0003W1\u0001\u0012AA\u0017\r\u001d\t)A\u0002E\u0001\u0003_AaA[\b\u0005\u0002\u0005E\u0002\"CA\u001a\u001f\t\u0007I1AA\u001b\u0011!\tyd\u0004Q\u0001\n\u0005]\u0002bBA!\u001f\u0011\r\u00111\t\u0005\n\u0003Gz\u0011\u0011!C\u0005\u0003KBq!a\u0003\u0007\t\u0003\t\u0019\b\u0003\u0005\u0002\u0004\u001a\u0011I1AAC\u0011%\t\u0019GBA\u0001\n\u0013\t)G\u0001\u0003MCjL(\"\u0001\u000e\u0002\u0013MD\u0017\r]3mKN\u001c8\u0001A\u000b\u0003;e\u001a2\u0001\u0001\u0010%!\ty\"%D\u0001!\u0015\u0005\t\u0013!B:dC2\f\u0017BA\u0012!\u0005\u0019\te.\u001f*fMB\u0011Q%\f\b\u0003M-r!a\n\u0016\u000e\u0003!R!!K\u000e\u0002\rq\u0012xn\u001c;?\u0013\u0005\t\u0013B\u0001\u0017!\u0003\u001d\u0001\u0018mY6bO\u0016L!AL\u0018\u0003\u0019M+\'/[1mSj\f\'\r\\3\u000b\u00051\u0002\u0013A\u0002\u0013j]&$H\u0005F\u00013!\ty2\'\u0003\u00025A\t!QK\\5u\u0003\u00151\u0018\r\\;f+\u00059\u0004C\u0001\u001d:\u0019\u0001!aA\u000f\u0001\u0005\u0006\u0004Y$!\u0001+\u0012\u0005qz\u0004CA\u0010>\u0013\tq\u0004EA\u0004O_RD\u0017N\\4\u0011\u0005}\u0001\u0015BA!!\u0005\r\te._\u0001\u0004[\u0006\u0004XC\u0001#I)\t)%\nE\u0002G\u0001\u001dk\u0011!\u0007\t\u0003q!#Q!S\u0002C\u0002m\u0012\u0011!\u0016\u0005\u0006\u0017\u000e\u0001\r\u0001T\u0001\u0002MB!q$T\u001cH\u0013\tq\u0005EA\u0005Gk:\u001cG/[8oc\u00059a\r\\1u\u001b\u0006\u0004XCA)U)\t\u0011V\u000bE\u0002G\u0001M\u0003\"\u0001\u000f+\u0005\u000b%#!\u0019A\u001e\t\u000b-#\u0001\u0019\u0001,\u0011\t}iuG\u0015\u0015\u0004\u0001as\u0006CA-]\u001b\u0005Q&BA.!\u0003)\tgN\\8uCRLwN\\\u0005\u0003;j\u0013\u0001#[7qY&\u001c\u0017\u000e\u001e(pi\u001a{WO\u001c3\"\u0003}\u000bqfY8vY\u0012\u0004cn\u001c;!M&tG\r\t\'buf\u0004\u0013.\u001c9mS\u000eLG\u000f\t<bYV,\u0007e\u001c4!if\u0004X\r\t\u0013|)v\fA\u0001T1{sB\u0011aIB\n\u0004\ry\u0019\u0007C\u00013j\u001b\u0005)\'B\u00014h\u0003\tIwNC\u0001i\u0003\u0011Q\u0017M^1\n\u00059*\u0017A\u0002\u001fj]&$h\bF\u0001b\u0003\u0015\t\u0007\u000f\u001d7z+\tq\u0017\u000f\u0006\u0002peB\u0019a\t\u00019\u0011\u0005a\nH!\u0002\u001e\t\u0005\u0004Y\u0004BB:\t\t\u0003\u0007A/A\u0001u!\ryR\u000f]\u0005\u0003m\u0002\u0012\u0001\u0002\u00102z]\u0006lWMP\u0001\bk:\f\u0007\u000f\u001d7z+\tIh\u0010\u0006\u0002{\u007fB\u0019qd_?\n\u0005q\u0004#AB(qi&|g\u000e\u0005\u00029}\u0012)!(\u0003b\u0001w!9\u0011\u0011A\u0005A\u0002\u0005\r\u0011A\u00017u!\r1\u0005! \u0002\u0007-\u0006dW/Z:\u0016\t\u0005%\u0011\u0011C\n\u0004\u0015y!\u0013A\u0002<bYV,7/\u0006\u0002\u0002\u0010A\u0019\u0001(!\u0005\u0005\riR!\u0019AA\n#\ra\u0014Q\u0003\t\u0004\r\u0006]\u0011bAA\r3\t)\u0001\nT5ti\u00069a/\u00197vKN\u0004C\u0003BA\u0010\u0003G\u0001R!!\t\u000b\u0003\u001fi\u0011A\u0002\u0005\b\u0003\u0017i\u0001\u0019AA\bQ\u0011Q\u0001,a\n\"\u0005\u0005%\u0012aS2pk2$\u0007E\\8uA\u0019Lg\u000e\u001a\u0011MCjL\b%[7qY&\u001c\u0017\u000e\u001e\u0011wC2,Xm\u001d\u0011g_J\u0004\u0013\r\u001c7!_\u001a\u0004C\u000f[3!if\u0004Xm\u001d\u0011f]VlWM]1uK\u0012\u0004\u0013N\u001c\u0011%wRk\u0018A\u0002,bYV,7\u000fE\u0002\u0002\"=\u00192a\u0004\u0010d)\t\ti#\u0001\u0006i]&dg+\u00197vKN,\"!a\u000e\u0011\u000b\u0005\u0005\"\"!\u000f\u0011\u0007\u0019\u000bY$C\u0002\u0002>e\u0011A\u0001\u0013(jY\u0006Y\u0001N\\5m-\u0006dW/Z:!\u0003-A7m\u001c8t-\u0006dW/Z:\u0016\r\u0005\u0015\u0013\u0011KA,)\u0019\t9%!\u0017\u0002`A)\u0011\u0011\u0005\u0006\u0002JA9a)a\u0013\u0002P\u0005U\u0013bAA\'3\taAeY8m_:$3m\u001c7p]B\u0019\u0001(!\u0015\u0005\r\u0005M3C1\u0001<\u0005\u0005A\u0005c\u0001\u001d\u0002X\u00111!h\u0005b\u0001\u0003\'Aq!a\u0017\u0014\u0001\b\ti&\u0001\u0002mQB!a\tAA(\u0011\u0019\u00198\u0003q\u0001\u0002bA)\u0011\u0011\u0005\u0006\u0002V\u0005aqO]5uKJ+\u0007\u000f\\1dKR\u0011\u0011q\r\t\u0005\u0003S\ny\'\u0004\u0002\u0002l)\u0019\u0011QN4\u0002\t1\fgnZ\u0005\u0005\u0003c\nYG\u0001\u0004PE*,7\r^\u000b\u0005\u0003k\nI\b\u0006\u0003\u0002x\u0005m\u0004c\u0001\u001d\u0002z\u00111!(\u0006b\u0001\u0003\'Aq!! \u0016\u0001\b\ty(\u0001\u0002mmB!a\tAAA!\u0015\t\tCCA<\u0003\u0019i7\u000eT1{sV!\u0011qQAG+\t\tI\t\u0005\u0003G\u0001\u0005-\u0005c\u0001\u001d\u0002\u000e\u00121\u0011q\u0012\fC\u0002m\u0012\u0011!\u0013\u0015\u0006-\u0005M\u0015q\u0015\t\u0005\u0003+\u000b\u0019+\u0004\u0002\u0002\u0018*!\u0011\u0011TAN\u0003!Ig\u000e^3s]\u0006d\'\u0002BAO\u0003?\u000ba!\\1de>\u001c(bAAQA\u00059!/\u001a4mK\u000e$\u0018\u0002BAS\u0003/\u0013\u0011\"\\1de>LU\u000e\u001d72\u000fy\tI+a+\u0003,-\u0001\u0011\'E\u0010\u0002*\u00065\u0016\u0011WAb\u0003\'\f\u0019/!>\u0003\bE2A%!+\u001c\u0003_\u000bQ!\\1de>\ftAFAU\u0003g\u000bY,M\u0003&\u0003k\u000b9l\u0004\u0002\u00028\u0006\u0012\u0011\u0011X\u0001\f[\u0006\u001c\'o\\#oO&tW-M\u0003&\u0003{\u000byl\u0004\u0002\u0002@\u0006\u0012\u0011\u0011Y\u0001&m^r\u0003\u0007\t\u0015j[BdW-\\3oi\u0016$\u0007%\u001b8!\'\u000e\fG.\u0019\u00113]E\nd\u0006M\u0017Nq%\ntAFAU\u0003\u000b\fi-M\u0003&\u0003\u000f\fIm\u0004\u0002\u0002J\u0006\u0012\u00111Z\u0001\tSN\u0014UO\u001c3mKF*Q%a4\u0002R>\u0011\u0011\u0011[\r\u0002\u0003E:a#!+\u0002V\u0006u\u0017\'B\u0013\u0002X\u0006ewBAAmC\t\tY.\u0001\u0006jg\nc\u0017mY6c_b\fT!JAp\u0003C|!!!9\u001a\u0003\u0001\ttAFAU\u0003K\fi/M\u0003&\u0003O\fIo\u0004\u0002\u0002j\u0006\u0012\u00111^\u0001\nG2\f7o\u001d(b[\u0016\fT!JAx\u0003c|!!!=\"\u0005\u0005M\u0018aF:iCB,G.Z:t]1\u000b\'0_\'bGJ|7OU3gc\u001d1\u0012\u0011VA|\u0003\u007f\fT!JA}\u0003w|!!a?\"\u0005\u0005u\u0018AC7fi\"|GMT1nKF*QE!\u0001\u0003\u0004=\u0011!1A\u0011\u0003\u0005\u000b\t!\"\\6MCjL\u0018*\u001c9mc\u001d1\u0012\u0011\u0016B\u0005\u0005#\tT!\nB\u0006\u0005\u001by!A!\u0004\"\u0005\t=\u0011!C:jO:\fG/\u001e:fc\u001dy\u0012\u0011\u0016B\n\u0005C\tt\u0001JAU\u0005+\u00119\"\u0003\u0003\u0003\u0018\te\u0011\u0001\u0002\'jgRTAAa\u0007\u0003\u001e\u0005I\u0011.\\7vi\u0006\u0014G.\u001a\u0006\u0004\u0005?\u0001\u0013AC2pY2,7\r^5p]F:q$!+\u0003$\t\u0015\u0012g\u0002\u0013\u0002*\nU!qC\u0019\u0006K\t\u001d\"\u0011F\b\u0003\u0005Si\u0012\u0001A\u0019\u0004M\t5\u0002c\u0001\u001d\u0002\u000e\u0002
   #12 = Utf8               java/lang/invoke/MethodHandles$Lookup
   #13 = Class              #12           // java/lang/invoke/MethodHandles$Lookup
   #14 = Utf8               java/lang/invoke/MethodHandles
   #15 = Class              #14           // java/lang/invoke/MethodHandles
   #16 = Utf8               Lookup
   #17 = Utf8               shapeless/Lazy$Values
   #18 = Class              #17           // shapeless/Lazy$Values
   #19 = Utf8               Values
   #20 = Utf8               shapeless/Lazy$Values$
   #21 = Class              #20           // shapeless/Lazy$Values$
   #22 = Utf8               Values$
   #23 = Utf8               values
   #24 = Utf8               (Lshapeless/Lazy;)Lshapeless/HList;
   #25 = Utf8               <T::Lshapeless/HList;>(Lshapeless/Lazy<Lshapeless/Lazy$Values<TT;>;>;)TT;
   #26 = Utf8               lv
   #27 = Utf8               shapeless/Lazy$
   #28 = Class              #27           // shapeless/Lazy$
   #29 = Utf8               MODULE$
   #30 = Utf8               Lshapeless/Lazy$;
   #31 = NameAndType        #29:#30       // MODULE$:Lshapeless/Lazy$;
   #32 = Fieldref           #28.#31       // shapeless/Lazy$.MODULE$:Lshapeless/Lazy$;
   #33 = NameAndType        #23:#24       // values:(Lshapeless/Lazy;)Lshapeless/HList;
   #34 = Methodref          #28.#33       // shapeless/Lazy$.values:(Lshapeless/Lazy;)Lshapeless/HList;
   #35 = Utf8               unapply
   #36 = Utf8               (Lshapeless/Lazy;)Lscala/Option;
   #37 = Utf8               <T:Ljava/lang/Object;>(Lshapeless/Lazy<TT;>;)Lscala/Option<TT;>;
   #38 = Utf8               lt
   #39 = NameAndType        #35:#36       // unapply:(Lshapeless/Lazy;)Lscala/Option;
   #40 = Methodref          #28.#39       // shapeless/Lazy$.unapply:(Lshapeless/Lazy;)Lscala/Option;
   #41 = Utf8               apply
   #42 = Utf8               (Lscala/Function0;)Lshapeless/Lazy;
   #43 = Utf8               <T:Ljava/lang/Object;>(Lscala/Function0<TT;>;)Lshapeless/Lazy<TT;>;
   #44 = Utf8               t
   #45 = NameAndType        #41:#42       // apply:(Lscala/Function0;)Lshapeless/Lazy;
   #46 = Methodref          #28.#45       // shapeless/Lazy$.apply:(Lscala/Function0;)Lshapeless/Lazy;
   #47 = Utf8               value
   #48 = Utf8               ()Ljava/lang/Object;
   #49 = Utf8               ()TT;
   #50 = Utf8               map$
   #51 = Utf8               (Lshapeless/Lazy;Lscala/Function1;)Lshapeless/Lazy;
   #52 = Utf8               $this
   #53 = Utf8               f
   #54 = Utf8               map
   #55 = Utf8               (Lscala/Function1;)Lshapeless/Lazy;
   #56 = NameAndType        #54:#55       // map:(Lscala/Function1;)Lshapeless/Lazy;
   #57 = InterfaceMethodref #2.#56        // shapeless/Lazy.map:(Lscala/Function1;)Lshapeless/Lazy;
   #58 = Utf8               Lshapeless/Lazy;
   #59 = Utf8               Lscala/Function1;
   #60 = Utf8               <U:Ljava/lang/Object;>(Lscala/Function1<TT;TU;>;)Lshapeless/Lazy<TU;>;
   #61 = MethodType         #48           //  ()Ljava/lang/Object;
   #62 = Utf8               $anonfun$map$1
   #63 = Utf8               (Lshapeless/Lazy;Lscala/Function1;)Ljava/lang/Object;
   #64 = NameAndType        #62:#63       // $anonfun$map$1:(Lshapeless/Lazy;Lscala/Function1;)Ljava/lang/Object;
   #65 = InterfaceMethodref #2.#64        // shapeless/Lazy.$anonfun$map$1:(Lshapeless/Lazy;Lscala/Function1;)Ljava/lang/Object;
   #66 = MethodHandle       6:#65         // REF_invokeStatic shapeless/Lazy.$anonfun$map$1:(Lshapeless/Lazy;Lscala/Function1;)Ljava/lang/Object;
   #67 = Integer            1
   #68 = Utf8               java/lang/invoke/LambdaMetafactory
   #69 = Class              #68           // java/lang/invoke/LambdaMetafactory
   #70 = Utf8               altMetafactory
   #71 = Utf8               (Ljava/lang/invoke/MethodHandles$Lookup;Ljava/lang/String;Ljava/lang/invoke/MethodType;[Ljava/lang/Object;)Ljava/lang/invoke/CallSite;
   #72 = NameAndType        #70:#71       // altMetafactory:(Ljava/lang/invoke/MethodHandles$Lookup;Ljava/lang/String;Ljava/lang/invoke/MethodType;[Ljava/lang/Object;)Ljava/lang/invoke/CallSite;
   #73 = Methodref          #69.#72       // java/lang/invoke/LambdaMetafactory.altMetafactory:(Ljava/lang/invoke/MethodHandles$Lookup;Ljava/lang/String;Ljava/lang/invoke/MethodType;[Ljava/lang/Object;)Ljava/lang/invoke/CallSite;
   #74 = MethodHandle       6:#73         // REF_invokeStatic java/lang/invoke/LambdaMetafactory.altMetafactory:(Ljava/lang/invoke/MethodHandles$Lookup;Ljava/lang/String;Ljava/lang/invoke/MethodType;[Ljava/lang/Object;)Ljava/lang/invoke/CallSite;
   #75 = Utf8               (Lshapeless/Lazy;Lscala/Function1;)Lscala/Function0;
   #76 = NameAndType        #41:#75       // apply:(Lshapeless/Lazy;Lscala/Function1;)Lscala/Function0;
   #77 = InvokeDynamic      #0:#76        // #0:apply:(Lshapeless/Lazy;Lscala/Function1;)Lscala/Function0;
   #78 = Utf8               this
   #79 = Utf8               flatMap$
   #80 = Utf8               flatMap
   #81 = NameAndType        #80:#55       // flatMap:(Lscala/Function1;)Lshapeless/Lazy;
   #82 = InterfaceMethodref #2.#81        // shapeless/Lazy.flatMap:(Lscala/Function1;)Lshapeless/Lazy;
   #83 = Utf8               <U:Ljava/lang/Object;>(Lscala/Function1<TT;Lshapeless/Lazy<TU;>;>;)Lshapeless/Lazy<TU;>;
   #84 = Utf8               $anonfun$flatMap$1
   #85 = NameAndType        #84:#63       // $anonfun$flatMap$1:(Lshapeless/Lazy;Lscala/Function1;)Ljava/lang/Object;
   #86 = InterfaceMethodref #2.#85        // shapeless/Lazy.$anonfun$flatMap$1:(Lshapeless/Lazy;Lscala/Function1;)Ljava/lang/Object;
   #87 = MethodHandle       6:#86         // REF_invokeStatic shapeless/Lazy.$anonfun$flatMap$1:(Lshapeless/Lazy;Lscala/Function1;)Ljava/lang/Object;
   #88 = InvokeDynamic      #1:#76        // #1:apply:(Lshapeless/Lazy;Lscala/Function1;)Lscala/Function0;
   #89 = Utf8               f$1
   #90 = NameAndType        #47:#48       // value:()Ljava/lang/Object;
   #91 = InterfaceMethodref #2.#90        // shapeless/Lazy.value:()Ljava/lang/Object;
   #92 = Utf8               scala/Function1
   #93 = Class              #92           // scala/Function1
   #94 = Utf8               (Ljava/lang/Object;)Ljava/lang/Object;
   #95 = NameAndType        #41:#94       // apply:(Ljava/lang/Object;)Ljava/lang/Object;
   #96 = InterfaceMethodref #93.#95       // scala/Function1.apply:(Ljava/lang/Object;)Ljava/lang/Object;
   #97 = Utf8               f$2
   #98 = Utf8               $init$
   #99 = Utf8               (Lshapeless/Lazy;)V
  #100 = Utf8               $deserializeLambda$
  #101 = Utf8               (Ljava/lang/invoke/SerializedLambda;)Ljava/lang/Object;
  #102 = Utf8               scala/runtime/LambdaDeserialize
  #103 = Class              #102          // scala/runtime/LambdaDeserialize
  #104 = Utf8               bootstrap
  #105 = Utf8               (Ljava/lang/invoke/MethodHandles$Lookup;Ljava/lang/String;Ljava/lang/invoke/MethodType;[Ljava/lang/invoke/MethodHandle;)Ljava/lang/invoke/CallSite;
  #106 = NameAndType        #104:#105     // bootstrap:(Ljava/lang/invoke/MethodHandles$Lookup;Ljava/lang/String;Ljava/lang/invoke/MethodType;[Ljava/lang/invoke/MethodHandle;)Ljava/lang/invoke/CallSite;
  #107 = Methodref          #103.#106     // scala/runtime/LambdaDeserialize.bootstrap:(Ljava/lang/invoke/MethodHandles$Lookup;Ljava/lang/String;Ljava/lang/invoke/MethodType;[Ljava/lang/invoke/MethodHandle;)Ljava/lang/invoke/CallSite;
  #108 = MethodHandle       6:#107        // REF_invokeStatic scala/runtime/LambdaDeserialize.bootstrap:(Ljava/lang/invoke/MethodHandles$Lookup;Ljava/lang/String;Ljava/lang/invoke/MethodType;[Ljava/lang/invoke/MethodHandle;)Ljava/lang/invoke/CallSite;
  #109 = Utf8               lambdaDeserialize
  #110 = NameAndType        #109:#101     // lambdaDeserialize:(Ljava/lang/invoke/SerializedLambda;)Ljava/lang/Object;
  #111 = InvokeDynamic      #2:#110       // #2:lambdaDeserialize:(Ljava/lang/invoke/SerializedLambda;)Ljava/lang/Object;
  #112 = Utf8               Code
  #113 = Utf8               Signature
  #114 = Utf8               MethodParameters
  #115 = Utf8               LineNumberTable
  #116 = Utf8               LocalVariableTable
  #117 = Utf8               InnerClasses
  #118 = Utf8               SourceFile
  #119 = Utf8               RuntimeVisibleAnnotations
  #120 = Utf8               BootstrapMethods
  #121 = Utf8               ScalaInlineInfo
  #122 = Utf8               ScalaSig
{
  public static <T extends shapeless.HList> T values(shapeless.Lazy<shapeless.Lazy$Values<T>>);
    descriptor: (Lshapeless/Lazy;)Lshapeless/HList;
    flags: (0x0009) ACC_PUBLIC, ACC_STATIC
    Code:
      stack=2, locals=1, args_size=1
         0: getstatic     #32                 // Field shapeless/Lazy$.MODULE$:Lshapeless/Lazy$;
         3: aload_0
         4: invokevirtual #34                 // Method shapeless/Lazy$.values:(Lshapeless/Lazy;)Lshapeless/HList;
         7: areturn
    Signature: #25                          // <T::Lshapeless/HList;>(Lshapeless/Lazy<Lshapeless/Lazy$Values<TT;>;>;)TT;
    MethodParameters:
      Name                           Flags
      lv                             final

  public static <T extends java.lang.Object> scala.Option<T> unapply(shapeless.Lazy<T>);
    descriptor: (Lshapeless/Lazy;)Lscala/Option;
    flags: (0x0009) ACC_PUBLIC, ACC_STATIC
    Code:
      stack=2, locals=1, args_size=1
         0: getstatic     #32                 // Field shapeless/Lazy$.MODULE$:Lshapeless/Lazy$;
         3: aload_0
         4: invokevirtual #40                 // Method shapeless/Lazy$.unapply:(Lshapeless/Lazy;)Lscala/Option;
         7: areturn
    Signature: #37                          // <T:Ljava/lang/Object;>(Lshapeless/Lazy<TT;>;)Lscala/Option<TT;>;
    MethodParameters:
      Name                           Flags
      lt                             final

  public static <T extends java.lang.Object> shapeless.Lazy<T> apply(scala.Function0<T>);
    descriptor: (Lscala/Function0;)Lshapeless/Lazy;
    flags: (0x0009) ACC_PUBLIC, ACC_STATIC
    Code:
      stack=2, locals=1, args_size=1
         0: getstatic     #32                 // Field shapeless/Lazy$.MODULE$:Lshapeless/Lazy$;
         3: aload_0
         4: invokevirtual #46                 // Method shapeless/Lazy$.apply:(Lscala/Function0;)Lshapeless/Lazy;
         7: areturn
    Signature: #43                          // <T:Ljava/lang/Object;>(Lscala/Function0<TT;>;)Lshapeless/Lazy<TT;>;
    MethodParameters:
      Name                           Flags
      t                              final

  public abstract T value();
    descriptor: ()Ljava/lang/Object;
    flags: (0x0401) ACC_PUBLIC, ACC_ABSTRACT
    Signature: #49                          // ()TT;

  public static shapeless.Lazy map$(shapeless.Lazy, scala.Function1);
    descriptor: (Lshapeless/Lazy;Lscala/Function1;)Lshapeless/Lazy;
    flags: (0x1009) ACC_PUBLIC, ACC_STATIC, ACC_SYNTHETIC
    Code:
      stack=2, locals=2, args_size=2
         0: aload_0
         1: aload_1
         2: invokespecial #57                 // InterfaceMethod map:(Lscala/Function1;)Lshapeless/Lazy;
         5: areturn
      LineNumberTable:
        line 116: 0
      LocalVariableTable:
        Start  Length  Slot  Name   Signature
            0       6     0 $this   Lshapeless/Lazy;
            0       6     1     f   Lscala/Function1;
    MethodParameters:
      Name                           Flags
      $this                          final synthetic
      f                              final

  public default <U extends java.lang.Object> shapeless.Lazy<U> map(scala.Function1<T, U>);
    descriptor: (Lscala/Function1;)Lshapeless/Lazy;
    flags: (0x0001) ACC_PUBLIC
    Code:
      stack=3, locals=2, args_size=2
         0: getstatic     #32                 // Field shapeless/Lazy$.MODULE$:Lshapeless/Lazy$;
         3: aload_0
         4: aload_1
         5: invokedynamic #77,  0             // InvokeDynamic #0:apply:(Lshapeless/Lazy;Lscala/Function1;)Lscala/Function0;
        10: invokevirtual #46                 // Method shapeless/Lazy$.apply:(Lscala/Function0;)Lshapeless/Lazy;
        13: areturn
      LineNumberTable:
        line 116: 0
      LocalVariableTable:
        Start  Length  Slot  Name   Signature
            0      14     0  this   Lshapeless/Lazy;
            0      14     1     f   Lscala/Function1;
    Signature: #60                          // <U:Ljava/lang/Object;>(Lscala/Function1<TT;TU;>;)Lshapeless/Lazy<TU;>;
    MethodParameters:
      Name                           Flags
      f                              final

  public static shapeless.Lazy flatMap$(shapeless.Lazy, scala.Function1);
    descriptor: (Lshapeless/Lazy;Lscala/Function1;)Lshapeless/Lazy;
    flags: (0x1009) ACC_PUBLIC, ACC_STATIC, ACC_SYNTHETIC
    Code:
      stack=2, locals=2, args_size=2
         0: aload_0
         1: aload_1
         2: invokespecial #82                 // InterfaceMethod flatMap:(Lscala/Function1;)Lshapeless/Lazy;
         5: areturn
      LineNumberTable:
        line 117: 0
      LocalVariableTable:
        Start  Length  Slot  Name   Signature
            0       6     0 $this   Lshapeless/Lazy;
            0       6     1     f   Lscala/Function1;
    MethodParameters:
      Name                           Flags
      $this                          final synthetic
      f                              final

  public default <U extends java.lang.Object> shapeless.Lazy<U> flatMap(scala.Function1<T, shapeless.Lazy<U>>);
    descriptor: (Lscala/Function1;)Lshapeless/Lazy;
    flags: (0x0001) ACC_PUBLIC
    Code:
      stack=3, locals=2, args_size=2
         0: getstatic     #32                 // Field shapeless/Lazy$.MODULE$:Lshapeless/Lazy$;
         3: aload_0
         4: aload_1
         5: invokedynamic #88,  0             // InvokeDynamic #1:apply:(Lshapeless/Lazy;Lscala/Function1;)Lscala/Function0;
        10: invokevirtual #46                 // Method shapeless/Lazy$.apply:(Lscala/Function0;)Lshapeless/Lazy;
        13: areturn
      LineNumberTable:
        line 117: 0
      LocalVariableTable:
        Start  Length  Slot  Name   Signature
            0      14     0  this   Lshapeless/Lazy;
            0      14     1     f   Lscala/Function1;
    Signature: #83                          // <U:Ljava/lang/Object;>(Lscala/Function1<TT;Lshapeless/Lazy<TU;>;>;)Lshapeless/Lazy<TU;>;
    MethodParameters:
      Name                           Flags
      f                              final

  public static java.lang.Object $anonfun$map$1(shapeless.Lazy, scala.Function1);
    descriptor: (Lshapeless/Lazy;Lscala/Function1;)Ljava/lang/Object;
    flags: (0x1009) ACC_PUBLIC, ACC_STATIC, ACC_SYNTHETIC
    Code:
      stack=2, locals=2, args_size=2
         0: aload_1
         1: aload_0
         2: invokeinterface #91,  1           // InterfaceMethod value:()Ljava/lang/Object;
         7: invokeinterface #96,  2           // InterfaceMethod scala/Function1.apply:(Ljava/lang/Object;)Ljava/lang/Object;
        12: areturn
      LineNumberTable:
        line 116: 0
      LocalVariableTable:
        Start  Length  Slot  Name   Signature
            0      13     0 $this   Lshapeless/Lazy;
            0      13     1   f$1   Lscala/Function1;
    MethodParameters:
      Name                           Flags
      $this                          final synthetic
      f$1                            final

  public static java.lang.Object $anonfun$flatMap$1(shapeless.Lazy, scala.Function1);
    descriptor: (Lshapeless/Lazy;Lscala/Function1;)Ljava/lang/Object;
    flags: (0x1009) ACC_PUBLIC, ACC_STATIC, ACC_SYNTHETIC
    Code:
      stack=2, locals=2, args_size=2
         0: aload_1
         1: aload_0
         2: invokeinterface #91,  1           // InterfaceMethod value:()Ljava/lang/Object;
         7: invokeinterface #96,  2           // InterfaceMethod scala/Function1.apply:(Ljava/lang/Object;)Ljava/lang/Object;
        12: checkcast     #2                  // class shapeless/Lazy
        15: invokeinterface #91,  1           // InterfaceMethod value:()Ljava/lang/Object;
        20: areturn
      LineNumberTable:
        line 117: 0
      LocalVariableTable:
        Start  Length  Slot  Name   Signature
            0      21     0 $this   Lshapeless/Lazy;
            0      21     1   f$2   Lscala/Function1;
    MethodParameters:
      Name                           Flags
      $this                          final synthetic
      f$2                            final

  public static void $init$(shapeless.Lazy);
    descriptor: (Lshapeless/Lazy;)V
    flags: (0x0009) ACC_PUBLIC, ACC_STATIC
    Code:
      stack=0, locals=1, args_size=1
         0: return
      LineNumberTable:
        line 113: 0
      LocalVariableTable:
        Start  Length  Slot  Name   Signature
            0       1     0 $this   Lshapeless/Lazy;
    MethodParameters:
      Name                           Flags
      $this                          final synthetic

  private static java.lang.Object $deserializeLambda$(java.lang.invoke.SerializedLambda);
    descriptor: (Ljava/lang/invoke/SerializedLambda;)Ljava/lang/Object;
    flags: (0x100a) ACC_PRIVATE, ACC_STATIC, ACC_SYNTHETIC
    Code:
      stack=1, locals=1, args_size=1
         0: aload_0
         1: invokedynamic #111,  0            // InvokeDynamic #2:lambdaDeserialize:(Ljava/lang/invoke/SerializedLambda;)Ljava/lang/Object;
         6: areturn
}
InnerClasses:
  public static final #16= #13 of #15;    // Lookup=class java/lang/invoke/MethodHandles$Lookup of class java/lang/invoke/MethodHandles
  public static #19= #18 of #2;           // Values=class shapeless/Lazy$Values of class shapeless/Lazy
  public static #22= #21 of #2;           // Values$=class shapeless/Lazy$Values$ of class shapeless/Lazy
Signature: #3                           // <T:Ljava/lang/Object;>Ljava/lang/Object;Ljava/io/Serializable;
SourceFile: "lazy.scala"
RuntimeVisibleAnnotations:
  0: #9(#10=s#11)
    scala.reflect.ScalaSignature(
      bytes="\u0006\u0005\t=ba\u0002\r\u001a!\u0003\r\t\u0001\b\u0005\u0006a\u0001!\t!\r\u0005\bk\u0001\u0011\rQ\"\u00017\u0011\u0015\u0011\u0005\u0001\"\u0001D\u0011\u0015y\u0005\u0001\"\u0001Q\u000f\u0015\u0001\u0017\u0004#\u0001b\r\u0015A\u0012\u0004#\u0001c\u0011\u0015Qg\u0001\"\u0001l\u0011\u0015ag\u0001b\u0001n\u0011\u00159h\u0001\"\u0001y\r\u0019\t)A\u0002\u0001\u0002\b!Q\u00111\u0002\u0006\u0003\u0006\u0004%\t!!\u0004\t\u0015\u0005m!B!A!\u0002\u0013\ty\u0001\u0003\u0004k\u0015\u0011\u0005\u0011QD\u0004\b\u0003W1\u0001\u0012AA\u0017\r\u001d\t)A\u0002E\u0001\u0003_AaA[\b\u0005\u0002\u0005E\u0002\"CA\u001a\u001f\t\u0007I1AA\u001b\u0011!\tyd\u0004Q\u0001\n\u0005]\u0002bBA!\u001f\u0011\r\u00111\t\u0005\n\u0003Gz\u0011\u0011!C\u0005\u0003KBq!a\u0003\u0007\t\u0003\t\u0019\b\u0003\u0005\u0002\u0004\u001a\u0011I1AAC\u0011%\t\u0019GBA\u0001\n\u0013\t)G\u0001\u0003MCjL(\"\u0001\u000e\u0002\u0013MD\u0017\r]3mKN\u001c8\u0001A\u000b\u0003;e\u001a2\u0001\u0001\u0010%!\ty\"%D\u0001!\u0015\u0005\t\u0013!B:dC2\f\u0017BA\u0012!\u0005\u0019\te.\u001f*fMB\u0011Q%\f\b\u0003M-r!a\n\u0016\u000e\u0003!R!!K\u000e\u0002\rq\u0012xn\u001c;?\u0013\u0005\t\u0013B\u0001\u0017!\u0003\u001d\u0001\u0018mY6bO\u0016L!AL\u0018\u0003\u0019M+\'/[1mSj\f\'\r\\3\u000b\u00051\u0002\u0013A\u0002\u0013j]&$H\u0005F\u00013!\ty2\'\u0003\u00025A\t!QK\\5u\u0003\u00151\u0018\r\\;f+\u00059\u0004C\u0001\u001d:\u0019\u0001!aA\u000f\u0001\u0005\u0006\u0004Y$!\u0001+\u0012\u0005qz\u0004CA\u0010>\u0013\tq\u0004EA\u0004O_RD\u0017N\\4\u0011\u0005}\u0001\u0015BA!!\u0005\r\te._\u0001\u0004[\u0006\u0004XC\u0001#I)\t)%\nE\u0002G\u0001\u001dk\u0011!\u0007\t\u0003q!#Q!S\u0002C\u0002m\u0012\u0011!\u0016\u0005\u0006\u0017\u000e\u0001\r\u0001T\u0001\u0002MB!q$T\u001cH\u0013\tq\u0005EA\u0005Gk:\u001cG/[8oc\u00059a\r\\1u\u001b\u0006\u0004XCA)U)\t\u0011V\u000bE\u0002G\u0001M\u0003\"\u0001\u000f+\u0005\u000b%#!\u0019A\u001e\t\u000b-#\u0001\u0019\u0001,\u0011\t}iuG\u0015\u0015\u0004\u0001as\u0006CA-]\u001b\u0005Q&BA.!\u0003)\tgN\\8uCRLwN\\\u0005\u0003;j\u0013\u0001#[7qY&\u001c\u0017\u000e\u001e(pi\u001a{WO\u001c3\"\u0003}\u000bqfY8vY\u0012\u0004cn\u001c;!M&tG\r\t\'buf\u0004\u0013.\u001c9mS\u000eLG\u000f\t<bYV,\u0007e\u001c4!if\u0004X\r\t\u0013|)v\fA\u0001T1{sB\u0011aIB\n\u0004\ry\u0019\u0007C\u00013j\u001b\u0005)\'B\u00014h\u0003\tIwNC\u0001i\u0003\u0011Q\u0017M^1\n\u00059*\u0017A\u0002\u001fj]&$h\bF\u0001b\u0003\u0015\t\u0007\u000f\u001d7z+\tq\u0017\u000f\u0006\u0002peB\u0019a\t\u00019\u0011\u0005a\nH!\u0002\u001e\t\u0005\u0004Y\u0004BB:\t\t\u0003\u0007A/A\u0001u!\ryR\u000f]\u0005\u0003m\u0002\u0012\u0001\u0002\u00102z]\u0006lWMP\u0001\bk:\f\u0007\u000f\u001d7z+\tIh\u0010\u0006\u0002{\u007fB\u0019qd_?\n\u0005q\u0004#AB(qi&|g\u000e\u0005\u00029}\u0012)!(\u0003b\u0001w!9\u0011\u0011A\u0005A\u0002\u0005\r\u0011A\u00017u!\r1\u0005! \u0002\u0007-\u0006dW/Z:\u0016\t\u0005%\u0011\u0011C\n\u0004\u0015y!\u0013A\u0002<bYV,7/\u0006\u0002\u0002\u0010A\u0019\u0001(!\u0005\u0005\riR!\u0019AA\n#\ra\u0014Q\u0003\t\u0004\r\u0006]\u0011bAA\r3\t)\u0001\nT5ti\u00069a/\u00197vKN\u0004C\u0003BA\u0010\u0003G\u0001R!!\t\u000b\u0003\u001fi\u0011A\u0002\u0005\b\u0003\u0017i\u0001\u0019AA\bQ\u0011Q\u0001,a\n\"\u0005\u0005%\u0012aS2pk2$\u0007E\\8uA\u0019Lg\u000e\u001a\u0011MCjL\b%[7qY&\u001c\u0017\u000e\u001e\u0011wC2,Xm\u001d\u0011g_J\u0004\u0013\r\u001c7!_\u001a\u0004C\u000f[3!if\u0004Xm\u001d\u0011f]VlWM]1uK\u0012\u0004\u0013N\u001c\u0011%wRk\u0018A\u0002,bYV,7\u000fE\u0002\u0002\"=\u00192a\u0004\u0010d)\t\ti#\u0001\u0006i]&dg+\u00197vKN,\"!a\u000e\u0011\u000b\u0005\u0005\"\"!\u000f\u0011\u0007\u0019\u000bY$C\u0002\u0002>e\u0011A\u0001\u0013(jY\u0006Y\u0001N\\5m-\u0006dW/Z:!\u0003-A7m\u001c8t-\u0006dW/Z:\u0016\r\u0005\u0015\u0013\u0011KA,)\u0019\t9%!\u0017\u0002`A)\u0011\u0011\u0005\u0006\u0002JA9a)a\u0013\u0002P\u0005U\u0013bAA\'3\taAeY8m_:$3m\u001c7p]B\u0019\u0001(!\u0015\u0005\r\u0005M3C1\u0001<\u0005\u0005A\u0005c\u0001\u001d\u0002X\u00111!h\u0005b\u0001\u0003\'Aq!a\u0017\u0014\u0001\b\ti&\u0001\u0002mQB!a\tAA(\u0011\u0019\u00198\u0003q\u0001\u0002bA)\u0011\u0011\u0005\u0006\u0002V\u0005aqO]5uKJ+\u0007\u000f\\1dKR\u0011\u0011q\r\t\u0005\u0003S\ny\'\u0004\u0002\u0002l)\u0019\u0011QN4\u0002\t1\fgnZ\u0005\u0005\u0003c\nYG\u0001\u0004PE*,7\r^\u000b\u0005\u0003k\nI\b\u0006\u0003\u0002x\u0005m\u0004c\u0001\u001d\u0002z\u00111!(\u0006b\u0001\u0003\'Aq!! \u0016\u0001\b\ty(\u0001\u0002mmB!a\tAAA!\u0015\t\tCCA<\u0003\u0019i7\u000eT1{sV!\u0011qQAG+\t\tI\t\u0005\u0003G\u0001\u0005-\u0005c\u0001\u001d\u0002\u000e\u00121\u0011q\u0012\fC\u0002m\u0012\u0011!\u0013\u0015\u0006-\u0005M\u0015q\u0015\t\u0005\u0003+\u000b\u0019+\u0004\u0002\u0002\u0018*!\u0011\u0011TAN\u0003!Ig\u000e^3s]\u0006d\'\u0002BAO\u0003?\u000ba!\\1de>\u001c(bAAQA\u00059!/\u001a4mK\u000e$\u0018\u0002BAS\u0003/\u0013\u0011\"\\1de>LU\u000e\u001d72\u000fy\tI+a+\u0003,-\u0001\u0011\'E\u0010\u0002*\u00065\u0016\u0011WAb\u0003\'\f\u0019/!>\u0003\bE2A%!+\u001c\u0003_\u000bQ!\\1de>\ftAFAU\u0003g\u000bY,M\u0003&\u0003k\u000b9l\u0004\u0002\u00028\u0006\u0012\u0011\u0011X\u0001\f[\u0006\u001c\'o\\#oO&tW-M\u0003&\u0003{\u000byl\u0004\u0002\u0002@\u0006\u0012\u0011\u0011Y\u0001&m^r\u0003\u0007\t\u0015j[BdW-\\3oi\u0016$\u0007%\u001b8!\'\u000e\fG.\u0019\u00113]E\nd\u0006M\u0017Nq%\ntAFAU\u0003\u000b\fi-M\u0003&\u0003\u000f\fIm\u0004\u0002\u0002J\u0006\u0012\u00111Z\u0001\tSN\u0014UO\u001c3mKF*Q%a4\u0002R>\u0011\u0011\u0011[\r\u0002\u0003E:a#!+\u0002V\u0006u\u0017\'B\u0013\u0002X\u0006ewBAAmC\t\tY.\u0001\u0006jg\nc\u0017mY6c_b\fT!JAp\u0003C|!!!9\u001a\u0003\u0001\ttAFAU\u0003K\fi/M\u0003&\u0003O\fIo\u0004\u0002\u0002j\u0006\u0012\u00111^\u0001\nG2\f7o\u001d(b[\u0016\fT!JAx\u0003c|!!!=\"\u0005\u0005M\u0018aF:iCB,G.Z:t]1\u000b\'0_\'bGJ|7OU3gc\u001d1\u0012\u0011VA|\u0003\u007f\fT!JA}\u0003w|!!a?\"\u0005\u0005u\u0018AC7fi\"|GMT1nKF*QE!\u0001\u0003\u0004=\u0011!1A\u0011\u0003\u0005\u000b\t!\"\\6MCjL\u0018*\u001c9mc\u001d1\u0012\u0011\u0016B\u0005\u0005#\tT!\nB\u0006\u0005\u001by!A!\u0004\"\u0005\t=\u0011!C:jO:\fG/\u001e:fc\u001dy\u0012\u0011\u0016B\n\u0005C\tt\u0001JAU\u0005+\u00119\"\u0003\u0003\u0003\u0018\te\u0011\u0001\u0002\'jgRTAAa\u0007\u0003\u001e\u0005I\u0011.\\7vi\u0006\u0014G.\u001a\u0006\u0004\u0005?\u0001\u0013AC2pY2,7\r^5p]F:q$!+\u0003$\t\u0015\u0012g\u0002\u0013\u0002*\nU!qC\u0019\u0006K\t\u001d\"\u0011F\b\u0003\u0005Si\u0012\u0001A\u0019\u0004M\t5\u0002c\u0001\u001d\u0002\u000e\u0002"
    )
BootstrapMethods:
  0: #74 REF_invokeStatic java/lang/invoke/LambdaMetafactory.altMetafactory:(Ljava/lang/invoke/MethodHandles$Lookup;Ljava/lang/String;Ljava/lang/invoke/MethodType;[Ljava/lang/Object;)Ljava/lang/invoke/CallSite;
    Method arguments:
      #61 ()Ljava/lang/Object;
      #66 REF_invokeStatic shapeless/Lazy.$anonfun$map$1:(Lshapeless/Lazy;Lscala/Function1;)Ljava/lang/Object;
      #61 ()Ljava/lang/Object;
      #67 1
  1: #74 REF_invokeStatic java/lang/invoke/LambdaMetafactory.altMetafactory:(Ljava/lang/invoke/MethodHandles$Lookup;Ljava/lang/String;Ljava/lang/invoke/MethodType;[Ljava/lang/Object;)Ljava/lang/invoke/CallSite;
    Method arguments:
      #61 ()Ljava/lang/Object;
      #87 REF_invokeStatic shapeless/Lazy.$anonfun$flatMap$1:(Lshapeless/Lazy;Lscala/Function1;)Ljava/lang/Object;
      #61 ()Ljava/lang/Object;
      #67 1
  2: #108 REF_invokeStatic scala/runtime/LambdaDeserialize.bootstrap:(Ljava/lang/invoke/MethodHandles$Lookup;Ljava/lang/String;Ljava/lang/invoke/MethodType;[Ljava/lang/invoke/MethodHandle;)Ljava/lang/invoke/CallSite;
    Method arguments:
      #87 REF_invokeStatic shapeless/Lazy.$anonfun$flatMap$1:(Lshapeless/Lazy;Lscala/Function1;)Ljava/lang/Object;
      #66 REF_invokeStatic shapeless/Lazy.$anonfun$map$1:(Lshapeless/Lazy;Lscala/Function1;)Ljava/lang/Object;
  ScalaInlineInfo: length = 0x2C (unknown attribute)
   01 00 00 08 00 54 00 3F 01 00 3E 00 3F 01 00 62
   00 63 01 00 4F 00 33 01 00 50 00 37 00 00 32 00
   33 01 00 36 00 37 00 00 2F 00 30 00
  ScalaSig: length = 0x3 (unknown attribute)
   05 02 00
