Classfile /Users/mw/Projects/slang-braindump/.jar/jar11/assemble/slang-braindump/assemble/content/shapeless/LazyMacros$LazyDefinitions$TypeWrapper$.class
  Last modified May 29, 2022; size 1644 bytes
  SHA-256 checksum bef1960d2b4955667f305261f40677fc816e399b6a69473b0f08a768bfb731aa
  Compiled from "lazy.scala"
public class shapeless.LazyMacros$LazyDefinitions$TypeWrapper$
  minor version: 0
  major version: 52
  flags: (0x0021) ACC_PUBLIC, ACC_SUPER
  this_class: #2                          // shapeless/LazyMacros$LazyDefinitions$TypeWrapper$
  super_class: #4                         // java/lang/Object
  interfaces: 0, fields: 1, methods: 3, attributes: 4
Constant pool:
   #1 = Utf8               shapeless/LazyMacros$LazyDefinitions$TypeWrapper$
   #2 = Class              #1             // shapeless/LazyMacros$LazyDefinitions$TypeWrapper$
   #3 = Utf8               java/lang/Object
   #4 = Class              #3             // java/lang/Object
   #5 = Utf8               lazy.scala
   #6 = Utf8               scala/reflect/api/Types$TypeApi
   #7 = Class              #6             // scala/reflect/api/Types$TypeApi
   #8 = Utf8               scala/reflect/api/Types
   #9 = Class              #8             // scala/reflect/api/Types
  #10 = Utf8               TypeApi
  #11 = Utf8               shapeless/LazyMacros$LazyDefinitions
  #12 = Class              #11            // shapeless/LazyMacros$LazyDefinitions
  #13 = Utf8               shapeless/LazyMacros
  #14 = Class              #13            // shapeless/LazyMacros
  #15 = Utf8               LazyDefinitions
  #16 = Utf8               shapeless/LazyMacros$LazyDefinitions$TypeWrapper
  #17 = Class              #16            // shapeless/LazyMacros$LazyDefinitions$TypeWrapper
  #18 = Utf8               TypeWrapper
  #19 = Utf8               TypeWrapper$
  #20 = Utf8               $outer
  #21 = Utf8               Lshapeless/LazyMacros$LazyDefinitions;
  #22 = Utf8               apply
  #23 = Utf8               (Lscala/reflect/api/Types$TypeApi;)Lshapeless/LazyMacros$LazyDefinitions$TypeWrapper;
  #24 = Utf8               tpe
  #25 = NameAndType        #20:#21        // $outer:Lshapeless/LazyMacros$LazyDefinitions;
  #26 = Fieldref           #2.#25         // shapeless/LazyMacros$LazyDefinitions$TypeWrapper$.$outer:Lshapeless/LazyMacros$LazyDefinitions;
  #27 = Utf8               <init>
  #28 = Utf8               (Lshapeless/LazyMacros$LazyDefinitions;Lscala/reflect/api/Types$TypeApi;)V
  #29 = NameAndType        #27:#28        // "<init>":(Lshapeless/LazyMacros$LazyDefinitions;Lscala/reflect/api/Types$TypeApi;)V
  #30 = Methodref          #17.#29        // shapeless/LazyMacros$LazyDefinitions$TypeWrapper."<init>":(Lshapeless/LazyMacros$LazyDefinitions;Lscala/reflect/api/Types$TypeApi;)V
  #31 = Utf8               this
  #32 = Utf8               Lshapeless/LazyMacros$LazyDefinitions$TypeWrapper$;
  #33 = Utf8               Lscala/reflect/api/Types$TypeApi;
  #34 = Utf8               unapply
  #35 = Utf8               (Lshapeless/LazyMacros$LazyDefinitions$TypeWrapper;)Lscala/Option;
  #36 = Utf8               (Lshapeless/LazyMacros$LazyDefinitions$TypeWrapper;)Lscala/Option<Lscala/reflect/api/Types$TypeApi;>;
  #37 = Utf8               tw
  #38 = Utf8               scala/Some
  #39 = Class              #38            // scala/Some
  #40 = Utf8               ()Lscala/reflect/api/Types$TypeApi;
  #41 = NameAndType        #24:#40        // tpe:()Lscala/reflect/api/Types$TypeApi;
  #42 = Methodref          #17.#41        // shapeless/LazyMacros$LazyDefinitions$TypeWrapper.tpe:()Lscala/reflect/api/Types$TypeApi;
  #43 = Utf8               (Ljava/lang/Object;)V
  #44 = NameAndType        #27:#43        // "<init>":(Ljava/lang/Object;)V
  #45 = Methodref          #39.#44        // scala/Some."<init>":(Ljava/lang/Object;)V
  #46 = Utf8               Lshapeless/LazyMacros$LazyDefinitions$TypeWrapper;
  #47 = Utf8               (Lshapeless/LazyMacros$LazyDefinitions;)V
  #48 = Utf8               ()V
  #49 = NameAndType        #27:#48        // "<init>":()V
  #50 = Methodref          #4.#49         // java/lang/Object."<init>":()V
  #51 = Utf8               Code
  #52 = Utf8               LineNumberTable
  #53 = Utf8               LocalVariableTable
  #54 = Utf8               MethodParameters
  #55 = Utf8               Signature
  #56 = Utf8               StackMapTable
  #57 = Utf8               InnerClasses
  #58 = Utf8               SourceFile
  #59 = Utf8               ScalaInlineInfo
  #60 = Utf8               Scala
{
  private final shapeless.LazyMacros$LazyDefinitions $outer;
    descriptor: Lshapeless/LazyMacros$LazyDefinitions;
    flags: (0x1012) ACC_PRIVATE, ACC_FINAL, ACC_SYNTHETIC

  public shapeless.LazyMacros$LazyDefinitions$TypeWrapper apply(scala.reflect.api.Types$TypeApi);
    descriptor: (Lscala/reflect/api/Types$TypeApi;)Lshapeless/LazyMacros$LazyDefinitions$TypeWrapper;
    flags: (0x0001) ACC_PUBLIC
    Code:
      stack=4, locals=2, args_size=2
         0: new           #17                 // class shapeless/LazyMacros$LazyDefinitions$TypeWrapper
         3: dup
         4: aload_0
         5: getfield      #26                 // Field $outer:Lshapeless/LazyMacros$LazyDefinitions;
         8: aload_1
         9: invokespecial #30                 // Method shapeless/LazyMacros$LazyDefinitions$TypeWrapper."<init>":(Lshapeless/LazyMacros$LazyDefinitions;Lscala/reflect/api/Types$TypeApi;)V
        12: areturn
      LineNumberTable:
        line 287: 0
      LocalVariableTable:
        Start  Length  Slot  Name   Signature
            0      13     0  this   Lshapeless/LazyMacros$LazyDefinitions$TypeWrapper$;
            0      13     1   tpe   Lscala/reflect/api/Types$TypeApi;
    MethodParameters:
      Name                           Flags
      tpe                            final

  public scala.Option<scala.reflect.api.Types$TypeApi> unapply(shapeless.LazyMacros$LazyDefinitions$TypeWrapper);
    descriptor: (Lshapeless/LazyMacros$LazyDefinitions$TypeWrapper;)Lscala/Option;
    flags: (0x0001) ACC_PUBLIC
    Code:
      stack=3, locals=2, args_size=2
         0: new           #39                 // class scala/Some
         3: dup
         4: aload_1
         5: invokevirtual #42                 // Method shapeless/LazyMacros$LazyDefinitions$TypeWrapper.tpe:()Lscala/reflect/api/Types$TypeApi;
         8: invokespecial #45                 // Method scala/Some."<init>":(Ljava/lang/Object;)V
        11: areturn
      LineNumberTable:
        line 288: 0
      LocalVariableTable:
        Start  Length  Slot  Name   Signature
            0      12     0  this   Lshapeless/LazyMacros$LazyDefinitions$TypeWrapper$;
            0      12     1    tw   Lshapeless/LazyMacros$LazyDefinitions$TypeWrapper;
    Signature: #36                          // (Lshapeless/LazyMacros$LazyDefinitions$TypeWrapper;)Lscala/Option<Lscala/reflect/api/Types$TypeApi;>;
    MethodParameters:
      Name                           Flags
      tw                             final

  public shapeless.LazyMacros$LazyDefinitions$TypeWrapper$(shapeless.LazyMacros$LazyDefinitions);
    descriptor: (Lshapeless/LazyMacros$LazyDefinitions;)V
    flags: (0x0001) ACC_PUBLIC
    Code:
      stack=2, locals=2, args_size=2
         0: aload_1
         1: ifnonnull     6
         4: aconst_null
         5: athrow
         6: aload_0
         7: aload_1
         8: putfield      #26                 // Field $outer:Lshapeless/LazyMacros$LazyDefinitions;
        11: aload_0
        12: invokespecial #50                 // Method java/lang/Object."<init>":()V
        15: return
      StackMapTable: number_of_entries = 1
        frame_type = 6 /* same */
      LineNumberTable:
        line 286: 0
        line 290: 11
        line 286: 15
      LocalVariableTable:
        Start  Length  Slot  Name   Signature
            0      16     0  this   Lshapeless/LazyMacros$LazyDefinitions$TypeWrapper$;
            0      16     1 $outer   Lshapeless/LazyMacros$LazyDefinitions;
    MethodParameters:
      Name                           Flags
      $outer                         final synthetic
}
InnerClasses:
  public abstract #10= #7 of #9;          // TypeApi=class scala/reflect/api/Types$TypeApi of class scala/reflect/api/Types
  public #15= #12 of #14;                 // LazyDefinitions=class shapeless/LazyMacros$LazyDefinitions of class shapeless/LazyMacros
  public #18= #17 of #12;                 // TypeWrapper=class shapeless/LazyMacros$LazyDefinitions$TypeWrapper of class shapeless/LazyMacros$LazyDefinitions
  public #19= #2 of #12;                  // TypeWrapper$=class shapeless/LazyMacros$LazyDefinitions$TypeWrapper$ of class shapeless/LazyMacros$LazyDefinitions
SourceFile: "lazy.scala"
  ScalaInlineInfo: length = 0x13 (unknown attribute)
   01 01 00 03 00 1B 00 2F 01 00 16 00 17 01 00 22
   00 23 01
  Scala: length = 0x0 (unknown attribute)

