Classfile /Users/mw/Projects/slang-braindump/.jar/jar11/assemble/slang-braindump/assemble/content/shapeless/LowPrioritySegment.class
  Last modified May 29, 2022; size 1497 bytes
  SHA-256 checksum 88e50f0a280bdd84422f79f4dc6d658cf3661f4e9a15d9424b12f8094741991e
  Compiled from "lenses.scala"
public interface shapeless.LowPrioritySegment
  minor version: 0
  major version: 52
  flags: (0x0601) ACC_PUBLIC, ACC_INTERFACE, ACC_ABSTRACT
  this_class: #2                          // shapeless/LowPrioritySegment
  super_class: #4                         // java/lang/Object
  interfaces: 0, fields: 0, methods: 3, attributes: 5
Constant pool:
   #1 = Utf8               shapeless/LowPrioritySegment
   #2 = Class              #1             // shapeless/LowPrioritySegment
   #3 = Utf8               java/lang/Object
   #4 = Class              #3             // java/lang/Object
   #5 = Utf8               lenses.scala
   #6 = Utf8               Lscala/reflect/ScalaSignature;
   #7 = Utf8               bytes
   #8 = Utf8               \u0006\u0005Y3q\u0001B\u0003\u0011\u0002\u0007\u0005\u0001\u0002C\u0003\u0010\u0001\u0011\u0005\u0001#\u0002\u0003\u0015\u0001\u0001)\u0002\"B\u001c\u0001\t\u0007A$A\u0005\'poB\u0013\u0018n\u001c:jif\u001cVmZ7f]RT\u0011AB\u0001\ng\"\f\u0007/\u001a7fgN\u001c\u0001a\u0005\u0002\u0001\u0013A\u0011!\"D\u0007\u0002\u0017)\tA\"A\u0003tG\u0006d\u0017-\u0003\u0002\u000f\u0017\t1\u0011I\\=SK\u001a\fa\u0001J5oSR$C#A\t\u0011\u0005)\u0011\u0012BA\n\f\u0005\u0011)f.\u001b;\u0003\u0007\u0005+\b0F\u0003\u0017?%bSG\u0005\u0002\u00183\u0019!\u0001\u0004\u0001\u0001\u0017\u00051a$/\u001a4j]\u0016lWM\u001c;?!\u0015Q2$\b\u0015,\u001b\u0005)\u0011B\u0001\u000f\u0006\u0005\u001d\u0019VmZ7f]R\u0004\"AH\u0010\r\u0001\u0011)\u0001E\u0001b\u0001C\t\t\u0001+\u0005\u0002#KA\u0011!bI\u0005\u0003I-\u0011qAT8uQ&tw\r\u0005\u0002\u000bM%\u0011qe\u0003\u0002\u0004\u0003:L\bC\u0001\u0010*\t\u0015Q#A1\u0001\"\u0005\u0005\u0019\u0006C\u0001\u0010-\t\u0015i#A1\u0001/\u0005\u0005!\u0016C\u0001\u00120!\tQ\u0002\'\u0003\u00022\u000b\t)\u0001\nT5ti\u0016!1g\u0006\u00115\u0005\ryU\u000f\u001e\t\u0003=U\"QA\u000e\u0002C\u00029\u0012AaT;ua\u0005\u0019Ao^8\u0016\tejt(Q\u000b\u0002uA11H\u0001\u001f?\u0001\nk\u0011\u0001\u0001\t\u0003=u\"Q\u0001I\u0002C\u0002\u0005\u0002\"AH \u0005\u000b)\u001a!\u0019A\u0011\u0011\u0005y\tE!B\u0017\u0004\u0005\u0004q\u0003\u0003\u0002\u000eD\u000b\"K!\u0001R\u0003\u0003\u0019\u0011\u001aw\u000e\\8oI\r|Gn\u001c8\u0011\u0007i1e(\u0003\u0002H\u000b\tA1i\\:fY\u0016\u001cG\u000f\u0005\u0003\u001b\u0007&\u0003\u0005c\u0001\u000eK\u0019&\u00111*\u0002\u0002\u0007\'\u0016dWm\u0019;\u0011\t5\u00036\u000b\u0010\b\u000359K!aT\u0003\u0002\u0007Q\fw-\u0003\u0002R%\n1A%\u0019;%CRT!aT\u0003\u0011\u0005)!\u0016BA+\f\u0005\u0019\u0019\u00160\u001c2pY\u0002
   #9 = Utf8               shapeless/LowPrioritySegment$$anon$43
  #10 = Class              #9             // shapeless/LowPrioritySegment$$anon$43
  #11 = Utf8               two$
  #12 = Utf8               (Lshapeless/LowPrioritySegment;)Lshapeless/Segment;
  #13 = Utf8               $this
  #14 = Utf8               two
  #15 = Utf8               ()Lshapeless/Segment;
  #16 = NameAndType        #14:#15        // two:()Lshapeless/Segment;
  #17 = InterfaceMethodref #2.#16         // shapeless/LowPrioritySegment.two:()Lshapeless/Segment;
  #18 = Utf8               Lshapeless/LowPrioritySegment;
  #19 = Utf8               <P:Ljava/lang/Object;S:Ljava/lang/Object;T::Lshapeless/HList;>()Lshapeless/Segment<TP;TS;TT;>;
  #20 = Utf8               <init>
  #21 = Utf8               (Lshapeless/LowPrioritySegment;)V
  #22 = NameAndType        #20:#21        // "<init>":(Lshapeless/LowPrioritySegment;)V
  #23 = Methodref          #10.#22        // shapeless/LowPrioritySegment$$anon$43."<init>":(Lshapeless/LowPrioritySegment;)V
  #24 = Utf8               this
  #25 = Utf8               $init$
  #26 = Utf8               Code
  #27 = Utf8               LineNumberTable
  #28 = Utf8               LocalVariableTable
  #29 = Utf8               MethodParameters
  #30 = Utf8               Signature
  #31 = Utf8               InnerClasses
  #32 = Utf8               SourceFile
  #33 = Utf8               RuntimeVisibleAnnotations
  #34 = Utf8               ScalaInlineInfo
  #35 = Utf8               ScalaSig
{
  public static shapeless.Segment two$(shapeless.LowPrioritySegment);
    descriptor: (Lshapeless/LowPrioritySegment;)Lshapeless/Segment;
    flags: (0x1009) ACC_PUBLIC, ACC_STATIC, ACC_SYNTHETIC
    Code:
      stack=1, locals=1, args_size=1
         0: aload_0
         1: invokespecial #17                 // InterfaceMethod two:()Lshapeless/Segment;
         4: areturn
      LineNumberTable:
        line 541: 0
      LocalVariableTable:
        Start  Length  Slot  Name   Signature
            0       5     0 $this   Lshapeless/LowPrioritySegment;
    MethodParameters:
      Name                           Flags
      $this                          final synthetic

  public default <P extends java.lang.Object, S extends java.lang.Object, T extends shapeless.HList> shapeless.Segment<P, S, T> two();
    descriptor: ()Lshapeless/Segment;
    flags: (0x0001) ACC_PUBLIC
    Code:
      stack=3, locals=1, args_size=1
         0: new           #10                 // class shapeless/LowPrioritySegment$$anon$43
         3: dup
         4: aconst_null
         5: invokespecial #23                 // Method shapeless/LowPrioritySegment$$anon$43."<init>":(Lshapeless/LowPrioritySegment;)V
         8: areturn
      LineNumberTable:
        line 541: 0
      LocalVariableTable:
        Start  Length  Slot  Name   Signature
            0       9     0  this   Lshapeless/LowPrioritySegment;
    Signature: #19                          // <P:Ljava/lang/Object;S:Ljava/lang/Object;T::Lshapeless/HList;>()Lshapeless/Segment<TP;TS;TT;>;

  public static void $init$(shapeless.LowPrioritySegment);
    descriptor: (Lshapeless/LowPrioritySegment;)V
    flags: (0x0009) ACC_PUBLIC, ACC_STATIC
    Code:
      stack=0, locals=1, args_size=1
         0: return
      LineNumberTable:
        line 538: 0
      LocalVariableTable:
        Start  Length  Slot  Name   Signature
            0       1     0 $this   Lshapeless/LowPrioritySegment;
    MethodParameters:
      Name                           Flags
      $this                          final synthetic
}
InnerClasses:
  public final #10;                       // class shapeless/LowPrioritySegment$$anon$43
SourceFile: "lenses.scala"
RuntimeVisibleAnnotations:
  0: #6(#7=s#8)
    scala.reflect.ScalaSignature(
      bytes="\u0006\u0005Y3q\u0001B\u0003\u0011\u0002\u0007\u0005\u0001\u0002C\u0003\u0010\u0001\u0011\u0005\u0001#\u0002\u0003\u0015\u0001\u0001)\u0002\"B\u001c\u0001\t\u0007A$A\u0005\'poB\u0013\u0018n\u001c:jif\u001cVmZ7f]RT\u0011AB\u0001\ng\"\f\u0007/\u001a7fgN\u001c\u0001a\u0005\u0002\u0001\u0013A\u0011!\"D\u0007\u0002\u0017)\tA\"A\u0003tG\u0006d\u0017-\u0003\u0002\u000f\u0017\t1\u0011I\\=SK\u001a\fa\u0001J5oSR$C#A\t\u0011\u0005)\u0011\u0012BA\n\f\u0005\u0011)f.\u001b;\u0003\u0007\u0005+\b0F\u0003\u0017?%bSG\u0005\u0002\u00183\u0019!\u0001\u0004\u0001\u0001\u0017\u00051a$/\u001a4j]\u0016lWM\u001c;?!\u0015Q2$\b\u0015,\u001b\u0005)\u0011B\u0001\u000f\u0006\u0005\u001d\u0019VmZ7f]R\u0004\"AH\u0010\r\u0001\u0011)\u0001E\u0001b\u0001C\t\t\u0001+\u0005\u0002#KA\u0011!bI\u0005\u0003I-\u0011qAT8uQ&tw\r\u0005\u0002\u000bM%\u0011qe\u0003\u0002\u0004\u0003:L\bC\u0001\u0010*\t\u0015Q#A1\u0001\"\u0005\u0005\u0019\u0006C\u0001\u0010-\t\u0015i#A1\u0001/\u0005\u0005!\u0016C\u0001\u00120!\tQ\u0002\'\u0003\u00022\u000b\t)\u0001\nT5ti\u0016!1g\u0006\u00115\u0005\ryU\u000f\u001e\t\u0003=U\"QA\u000e\u0002C\u00029\u0012AaT;ua\u0005\u0019Ao^8\u0016\tejt(Q\u000b\u0002uA11H\u0001\u001f?\u0001\nk\u0011\u0001\u0001\t\u0003=u\"Q\u0001I\u0002C\u0002\u0005\u0002\"AH \u0005\u000b)\u001a!\u0019A\u0011\u0011\u0005y\tE!B\u0017\u0004\u0005\u0004q\u0003\u0003\u0002\u000eD\u000b\"K!\u0001R\u0003\u0003\u0019\u0011\u001aw\u000e\\8oI\r|Gn\u001c8\u0011\u0007i1e(\u0003\u0002H\u000b\tA1i\\:fY\u0016\u001cG\u000f\u0005\u0003\u001b\u0007&\u0003\u0005c\u0001\u000eK\u0019&\u00111*\u0002\u0002\u0007\'\u0016dWm\u0019;\u0011\t5\u00036\u000b\u0010\b\u000359K!aT\u0003\u0002\u0007Q\fw-\u0003\u0002R%\n1A%\u0019;%CRT!aT\u0003\u0011\u0005)!\u0016BA+\f\u0005\u0019\u0019\u00160\u001c2pY\u0002"
    )
  ScalaInlineInfo: length = 0x13 (unknown attribute)
   01 00 00 03 00 19 00 15 01 00 0B 00 0C 01 00 0E
   00 0F 00
  ScalaSig: length = 0x3 (unknown attribute)
   05 02 00
