Classfile /Users/mw/Projects/slang-braindump/.jar/jar11/assemble/slang-braindump/assemble/content/shapeless/LowPriorityMkSelectDynamicOptic.class
  Last modified May 29, 2022; size 4080 bytes
  SHA-256 checksum a6b1781b569a8cf71055325ad98b849f289d7133f1dd4fdf0d5dac116d5d96dc
  Compiled from "lenses.scala"
public interface shapeless.LowPriorityMkSelectDynamicOptic
  minor version: 0
  major version: 52
  flags: (0x0601) ACC_PUBLIC, ACC_INTERFACE, ACC_ABSTRACT
  this_class: #2                          // shapeless/LowPriorityMkSelectDynamicOptic
  super_class: #4                         // java/lang/Object
  interfaces: 0, fields: 0, methods: 5, attributes: 5
Constant pool:
   #1 = Utf8               shapeless/LowPriorityMkSelectDynamicOptic
   #2 = Class              #1             // shapeless/LowPriorityMkSelectDynamicOptic
   #3 = Utf8               java/lang/Object
   #4 = Class              #3             // java/lang/Object
   #5 = Utf8               lenses.scala
   #6 = Utf8               Lscala/reflect/ScalaSignature;
   #7 = Utf8               bytes
   #8 = Utf8               \u0006\u0005\u0005uaaB\u0003\u0007!\u0003\r\t!\u0003\u0005\u0006!\u0001!\t!E\u0003\u0005+\u0001\u0001a\u0003C\u00038\u0001\u0011\r\u0001\bC\u0003x\u0001\u0011\r\u0001PA\u0010M_^\u0004&/[8sSRLXj[*fY\u0016\u001cG\u000fR=oC6L7m\u00149uS\u000eT\u0011aB\u0001\ng\"\f\u0007/\u001a7fgN\u001c\u0001a\u0005\u0002\u0001\u0015A\u00111BD\u0007\u0002\u0019)\tQ\"A\u0003tG\u0006d\u0017-\u0003\u0002\u0010\u0019\t1\u0011I\\=SK\u001a\fa\u0001J5oSR$C#\u0001\n\u0011\u0005-\u0019\u0012B\u0001\u000b\r\u0005\u0011)f.\u001b;\u0003\u0007\u0005+\b0\u0006\u0004\u0018A)j\u0003\'\u000e\n\u00031i1A!\u0007\u0001\u0001/\taAH]3gS:,W.\u001a8u}A11\u0004\b\u0010*Y=j\u0011AB\u0005\u0003;\u0019\u0011A#T6TK2,7\r\u001e#z]\u0006l\u0017nY(qi&\u001c\u0007CA\u0010!\u0019\u0001!Q!\t\u0002C\u0002\t\u0012\u0011AU\t\u0003G\u0019\u0002\"a\u0003\u0013\n\u0005\u0015b!a\u0002(pi\"Lgn\u001a\t\u0003\u0017\u001dJ!\u0001\u000b\u0007\u0003\u0007\u0005s\u0017\u0010\u0005\u0002 U\u0011)1F\u0001b\u0001E\t\t\u0011\t\u0005\u0002 [\u0011)aF\u0001b\u0001E\t\t1\n\u0005\u0002 a\u0011)\u0011G\u0001b\u0001E\t\t!)\u0002\u000341\u0001\"$aA(viB\u0011q$\u000e\u0003\u0006m\t\u0011\rA\t\u0002\u0005\u001fV$\b\'A\nnW&sg-\u001a:Di>\u00148+\u001a7GS\u0016dG-F\u0004:{}J\u0006.Q\'\u0015\ri\u0002vL[8E!\u001dY$\u0001\u0010 AG\tk\u0011\u0001\u0001\t\u0003?u\"Q!I\u0002C\u0002\t\u0002\"aH \u0005\u000b-\u001a!\u0019\u0001\u0012\u0011\u0005}\tE!\u0002\u0018\u0004\u0005\u0004\u0011\u0003CA\"P\u001d\tyB\tC\u0003F\u0007\u0001\u000fa)A\u0004d_6\u0004xn]3\u0011\tm9\u0015\nP\u0005\u0003\u0011\u001a\u0011Qb\u00149uS\u000e\u001cu.\u001c9pg\u0016\u0014\b\u0003B\u000eK}1K!a\u0013\u0004\u0003\u000bA\u0013\u0018n]7\u0011\u0005}iE!\u0002(\u0004\u0005\u0004\u0011#!A#\n\u0005M:\u0005\"B)\u0004\u0001\b\u0011\u0016aA4f]B!1K\u0016 Y\u001d\tYB+\u0003\u0002V\r\u00059q)\u001a8fe&\u001c\u0017BA\u000bX\u0015\t)f\u0001\u0005\u0002 3\u0012)!l\u0001b\u00017\n\t1)\u0005\u0002$9B\u00111$X\u0005\u0003=\u001a\u0011\u0011bQ8qe>$Wo\u0019;\t\u000b\u0001\u001c\u00019A1\u0002\u000b%tg-\u001a:\u0011\u000b\t,\u0007\fQ4\u000f\u0005m\u0019\u0017B\u00013\u0007\u00031IeNZ3s!J|G-^2u\u0013\t)bM\u0003\u0002e\rA\u0011q\u0004\u001b\u0003\u0006S\u000e\u0011\rA\t\u0002\u0002\u0013\")1n\u0001a\u0002Y\u00061Qn[\"TK2\u0004BaG7?O&\u0011aN\u0002\u0002\f\u001b.\u001cEo\u001c:Qe&\u001cX\u000eC\u0003q\u0007\u0001\u000f\u0011/\u0001\u0004nWB\u001bV\r\u001c\t\u0006eV<\u0007\t\u0014\b\u00037ML!\u0001\u001e\u0004\u0002\u00175[g)[3mI2+gn]\u0005\u0003+YT!\u0001\u001e\u0004\u0002\u001d5\\7+\u001a7GS\u0016dGm\u0011;peVI\u0011\u0010 @\u0002\u0002\u0005\u0015\u0011q\u0003\u000b\bu\u0006E\u0011\u0011DA\u0006!%Y$a_?\u0000\u0003\u0007\t9\u0001\u0005\u0002 y\u0012)\u0011\u0005\u0002b\u0001EA\u0011qD \u0003\u0006W\u0011\u0011\rA\t\t\u0004?\u0005\u0005A!\u0002\u0018\u0005\u0005\u0004\u0011\u0003cA\u0010\u0002\u0006\u0011)\u0011\u0007\u0002b\u0001EA\u0019\u0011\u0011B(\u000f\u0007}\tY\u0001\u0003\u0004F\t\u0001\u000f\u0011Q\u0002\t\u00067\u001d\u000bya\u001f\t\u00067)k\u00181\u0001\u0005\u0007a\u0012\u0001\u001d!a\u0005\u0011\rI,Xp`A\u000b!\ry\u0012q\u0003\u0003\u00065\u0012\u0011\rA\t\u0005\u0007W\u0012\u0001\u001d!a\u0007\u0011\rmi\u0017QCA\u0002\u0001
   #9 = Utf8               shapeless/LowPriorityMkSelectDynamicOptic$$anon$23
  #10 = Class              #9             // shapeless/LowPriorityMkSelectDynamicOptic$$anon$23
  #11 = Utf8               shapeless/LowPriorityMkSelectDynamicOptic$$anon$24
  #12 = Class              #11            // shapeless/LowPriorityMkSelectDynamicOptic$$anon$24
  #13 = Utf8               mkInferCtorSelField$
  #14 = Utf8               (Lshapeless/LowPriorityMkSelectDynamicOptic;Lshapeless/Generic;Lshapeless/InferProduct;Lshapeless/MkCtorPrism;Lshapeless/MkFieldLens;Lshapeless/OpticComposer;)Lshapeless/MkSelectDynamicOptic;
  #15 = Utf8               $this
  #16 = Utf8               gen
  #17 = Utf8               infer
  #18 = Utf8               mkCSel
  #19 = Utf8               mkPSel
  #20 = Utf8               compose
  #21 = Utf8               mkInferCtorSelField
  #22 = Utf8               (Lshapeless/Generic;Lshapeless/InferProduct;Lshapeless/MkCtorPrism;Lshapeless/MkFieldLens;Lshapeless/OpticComposer;)Lshapeless/MkSelectDynamicOptic;
  #23 = NameAndType        #21:#22        // mkInferCtorSelField:(Lshapeless/Generic;Lshapeless/InferProduct;Lshapeless/MkCtorPrism;Lshapeless/MkFieldLens;Lshapeless/OpticComposer;)Lshapeless/MkSelectDynamicOptic;
  #24 = InterfaceMethodref #2.#23         // shapeless/LowPriorityMkSelectDynamicOptic.mkInferCtorSelField:(Lshapeless/Generic;Lshapeless/InferProduct;Lshapeless/MkCtorPrism;Lshapeless/MkFieldLens;Lshapeless/OpticComposer;)Lshapeless/MkSelectDynamicOptic;
  #25 = Utf8               Lshapeless/LowPriorityMkSelectDynamicOptic;
  #26 = Utf8               Lshapeless/Generic;
  #27 = Utf8               Lshapeless/InferProduct;
  #28 = Utf8               Lshapeless/MkCtorPrism;
  #29 = Utf8               Lshapeless/MkFieldLens;
  #30 = Utf8               Lshapeless/OpticComposer;
  #31 = Utf8               <R:Ljava/lang/Object;A:Ljava/lang/Object;C::Lshapeless/Coproduct;I:Ljava/lang/Object;K:Ljava/lang/Object;E:Ljava/lang/Object;>(Lshapeless/Generic<TA;>;Lshapeless/InferProduct<TC;TK;>;Lshapeless/MkCtorPrism<TA;TI;>;Lshapeless/MkFieldLens<TI;TK;>;Lshapeless/OpticComposer<Lshapeless/Prism<TA;TE;>;TR;>;)Lshapeless/MkSelectDynamicOptic<TR;TA;TK;Lscala/runtime/Nothing$;>;
  #32 = Utf8               <init>
  #33 = Utf8               (Lshapeless/LowPriorityMkSelectDynamicOptic;Lshapeless/OpticComposer;Lshapeless/MkFieldLens;Lshapeless/MkCtorPrism;)V
  #34 = NameAndType        #32:#33        // "<init>":(Lshapeless/LowPriorityMkSelectDynamicOptic;Lshapeless/OpticComposer;Lshapeless/MkFieldLens;Lshapeless/MkCtorPrism;)V
  #35 = Methodref          #10.#34        // shapeless/LowPriorityMkSelectDynamicOptic$$anon$23."<init>":(Lshapeless/LowPriorityMkSelectDynamicOptic;Lshapeless/OpticComposer;Lshapeless/MkFieldLens;Lshapeless/MkCtorPrism;)V
  #36 = Utf8               this
  #37 = Utf8               mkSelFieldCtor$
  #38 = Utf8               (Lshapeless/LowPriorityMkSelectDynamicOptic;Lshapeless/MkFieldLens;Lshapeless/MkCtorPrism;Lshapeless/OpticComposer;)Lshapeless/MkSelectDynamicOptic;
  #39 = Utf8               mkSelFieldCtor
  #40 = Utf8               (Lshapeless/MkFieldLens;Lshapeless/MkCtorPrism;Lshapeless/OpticComposer;)Lshapeless/MkSelectDynamicOptic;
  #41 = NameAndType        #39:#40        // mkSelFieldCtor:(Lshapeless/MkFieldLens;Lshapeless/MkCtorPrism;Lshapeless/OpticComposer;)Lshapeless/MkSelectDynamicOptic;
  #42 = InterfaceMethodref #2.#41         // shapeless/LowPriorityMkSelectDynamicOptic.mkSelFieldCtor:(Lshapeless/MkFieldLens;Lshapeless/MkCtorPrism;Lshapeless/OpticComposer;)Lshapeless/MkSelectDynamicOptic;
  #43 = Utf8               <R:Ljava/lang/Object;A:Ljava/lang/Object;K:Ljava/lang/Object;B:Ljava/lang/Object;C:Ljava/lang/Object;>(Lshapeless/MkFieldLens<TA;TK;>;Lshapeless/MkCtorPrism<TC;TB;>;Lshapeless/OpticComposer<Lshapeless/Prism<TA;TB;>;TR;>;)Lshapeless/MkSelectDynamicOptic<TR;TA;TK;TB;>;
  #44 = Utf8               (Lshapeless/LowPriorityMkSelectDynamicOptic;Lshapeless/OpticComposer;Lshapeless/MkCtorPrism;Lshapeless/MkFieldLens;)V
  #45 = NameAndType        #32:#44        // "<init>":(Lshapeless/LowPriorityMkSelectDynamicOptic;Lshapeless/OpticComposer;Lshapeless/MkCtorPrism;Lshapeless/MkFieldLens;)V
  #46 = Methodref          #12.#45        // shapeless/LowPriorityMkSelectDynamicOptic$$anon$24."<init>":(Lshapeless/LowPriorityMkSelectDynamicOptic;Lshapeless/OpticComposer;Lshapeless/MkCtorPrism;Lshapeless/MkFieldLens;)V
  #47 = Utf8               $init$
  #48 = Utf8               (Lshapeless/LowPriorityMkSelectDynamicOptic;)V
  #49 = Utf8               Code
  #50 = Utf8               LineNumberTable
  #51 = Utf8               LocalVariableTable
  #52 = Utf8               MethodParameters
  #53 = Utf8               Signature
  #54 = Utf8               InnerClasses
  #55 = Utf8               SourceFile
  #56 = Utf8               RuntimeVisibleAnnotations
  #57 = Utf8               ScalaInlineInfo
  #58 = Utf8               ScalaSig
{
  public static shapeless.MkSelectDynamicOptic mkInferCtorSelField$(shapeless.LowPriorityMkSelectDynamicOptic, shapeless.Generic, shapeless.InferProduct, shapeless.MkCtorPrism, shapeless.MkFieldLens, shapeless.OpticComposer);
    descriptor: (Lshapeless/LowPriorityMkSelectDynamicOptic;Lshapeless/Generic;Lshapeless/InferProduct;Lshapeless/MkCtorPrism;Lshapeless/MkFieldLens;Lshapeless/OpticComposer;)Lshapeless/MkSelectDynamicOptic;
    flags: (0x1009) ACC_PUBLIC, ACC_STATIC, ACC_SYNTHETIC
    Code:
      stack=6, locals=6, args_size=6
         0: aload_0
         1: aload_1
         2: aload_2
         3: aload_3
         4: aload         4
         6: aload         5
         8: invokespecial #24                 // InterfaceMethod mkInferCtorSelField:(Lshapeless/Generic;Lshapeless/InferProduct;Lshapeless/MkCtorPrism;Lshapeless/MkFieldLens;Lshapeless/OpticComposer;)Lshapeless/MkSelectDynamicOptic;
        11: areturn
      LineNumberTable:
        line 314: 0
      LocalVariableTable:
        Start  Length  Slot  Name   Signature
            0      12     0 $this   Lshapeless/LowPriorityMkSelectDynamicOptic;
            0      12     1   gen   Lshapeless/Generic;
            0      12     2 infer   Lshapeless/InferProduct;
            0      12     3 mkCSel   Lshapeless/MkCtorPrism;
            0      12     4 mkPSel   Lshapeless/MkFieldLens;
            0      12     5 compose   Lshapeless/OpticComposer;
    MethodParameters:
      Name                           Flags
      $this                          final synthetic
      gen                            final
      infer                          final
      mkCSel                         final
      mkPSel                         final
      compose                        final

  public default <R extends java.lang.Object, A extends java.lang.Object, C extends shapeless.Coproduct, I extends java.lang.Object, K extends java.lang.Object, E extends java.lang.Object> shapeless.MkSelectDynamicOptic<R, A, K, scala.runtime.Nothing$> mkInferCtorSelField(shapeless.Generic<A>, shapeless.InferProduct<C, K>, shapeless.MkCtorPrism<A, I>, shapeless.MkFieldLens<I, K>, shapeless.OpticComposer<shapeless.Prism<A, E>, R>);
    descriptor: (Lshapeless/Generic;Lshapeless/InferProduct;Lshapeless/MkCtorPrism;Lshapeless/MkFieldLens;Lshapeless/OpticComposer;)Lshapeless/MkSelectDynamicOptic;
    flags: (0x0001) ACC_PUBLIC
    Code:
      stack=6, locals=6, args_size=6
         0: new           #10                 // class shapeless/LowPriorityMkSelectDynamicOptic$$anon$23
         3: dup
         4: aconst_null
         5: aload         5
         7: aload         4
         9: aload_3
        10: invokespecial #35                 // Method shapeless/LowPriorityMkSelectDynamicOptic$$anon$23."<init>":(Lshapeless/LowPriorityMkSelectDynamicOptic;Lshapeless/OpticComposer;Lshapeless/MkFieldLens;Lshapeless/MkCtorPrism;)V
        13: areturn
      LineNumberTable:
        line 322: 0
      LocalVariableTable:
        Start  Length  Slot  Name   Signature
            0      14     0  this   Lshapeless/LowPriorityMkSelectDynamicOptic;
            0      14     1   gen   Lshapeless/Generic;
            0      14     2 infer   Lshapeless/InferProduct;
            0      14     3 mkCSel   Lshapeless/MkCtorPrism;
            0      14     4 mkPSel   Lshapeless/MkFieldLens;
            0      14     5 compose   Lshapeless/OpticComposer;
    Signature: #31                          // <R:Ljava/lang/Object;A:Ljava/lang/Object;C::Lshapeless/Coproduct;I:Ljava/lang/Object;K:Ljava/lang/Object;E:Ljava/lang/Object;>(Lshapeless/Generic<TA;>;Lshapeless/InferProduct<TC;TK;>;Lshapeless/MkCtorPrism<TA;TI;>;Lshapeless/MkFieldLens<TI;TK;>;Lshapeless/OpticComposer<Lshapeless/Prism<TA;TE;>;TR;>;)Lshapeless/MkSelectDynamicOptic<TR;TA;TK;Lscala/runtime/Nothing$;>;
    MethodParameters:
      Name                           Flags
      gen                            final
      infer                          final
      mkCSel                         final
      mkPSel                         final
      compose                        final

  public static shapeless.MkSelectDynamicOptic mkSelFieldCtor$(shapeless.LowPriorityMkSelectDynamicOptic, shapeless.MkFieldLens, shapeless.MkCtorPrism, shapeless.OpticComposer);
    descriptor: (Lshapeless/LowPriorityMkSelectDynamicOptic;Lshapeless/MkFieldLens;Lshapeless/MkCtorPrism;Lshapeless/OpticComposer;)Lshapeless/MkSelectDynamicOptic;
    flags: (0x1009) ACC_PUBLIC, ACC_STATIC, ACC_SYNTHETIC
    Code:
      stack=4, locals=4, args_size=4
         0: aload_0
         1: aload_1
         2: aload_2
         3: aload_3
         4: invokespecial #42                 // InterfaceMethod mkSelFieldCtor:(Lshapeless/MkFieldLens;Lshapeless/MkCtorPrism;Lshapeless/OpticComposer;)Lshapeless/MkSelectDynamicOptic;
         7: areturn
      LineNumberTable:
        line 327: 0
      LocalVariableTable:
        Start  Length  Slot  Name   Signature
            0       8     0 $this   Lshapeless/LowPriorityMkSelectDynamicOptic;
            0       8     1 mkPSel   Lshapeless/MkFieldLens;
            0       8     2 mkCSel   Lshapeless/MkCtorPrism;
            0       8     3 compose   Lshapeless/OpticComposer;
    MethodParameters:
      Name                           Flags
      $this                          final synthetic
      mkPSel                         final
      mkCSel                         final
      compose                        final

  public default <R extends java.lang.Object, A extends java.lang.Object, K extends java.lang.Object, B extends java.lang.Object, C extends java.lang.Object> shapeless.MkSelectDynamicOptic<R, A, K, B> mkSelFieldCtor(shapeless.MkFieldLens<A, K>, shapeless.MkCtorPrism<C, B>, shapeless.OpticComposer<shapeless.Prism<A, B>, R>);
    descriptor: (Lshapeless/MkFieldLens;Lshapeless/MkCtorPrism;Lshapeless/OpticComposer;)Lshapeless/MkSelectDynamicOptic;
    flags: (0x0001) ACC_PUBLIC
    Code:
      stack=6, locals=4, args_size=4
         0: new           #12                 // class shapeless/LowPriorityMkSelectDynamicOptic$$anon$24
         3: dup
         4: aconst_null
         5: aload_3
         6: aload_2
         7: aload_1
         8: invokespecial #46                 // Method shapeless/LowPriorityMkSelectDynamicOptic$$anon$24."<init>":(Lshapeless/LowPriorityMkSelectDynamicOptic;Lshapeless/OpticComposer;Lshapeless/MkCtorPrism;Lshapeless/MkFieldLens;)V
        11: areturn
      LineNumberTable:
        line 333: 0
      LocalVariableTable:
        Start  Length  Slot  Name   Signature
            0      12     0  this   Lshapeless/LowPriorityMkSelectDynamicOptic;
            0      12     1 mkPSel   Lshapeless/MkFieldLens;
            0      12     2 mkCSel   Lshapeless/MkCtorPrism;
            0      12     3 compose   Lshapeless/OpticComposer;
    Signature: #43                          // <R:Ljava/lang/Object;A:Ljava/lang/Object;K:Ljava/lang/Object;B:Ljava/lang/Object;C:Ljava/lang/Object;>(Lshapeless/MkFieldLens<TA;TK;>;Lshapeless/MkCtorPrism<TC;TB;>;Lshapeless/OpticComposer<Lshapeless/Prism<TA;TB;>;TR;>;)Lshapeless/MkSelectDynamicOptic<TR;TA;TK;TB;>;
    MethodParameters:
      Name                           Flags
      mkPSel                         final
      mkCSel                         final
      compose                        final

  public static void $init$(shapeless.LowPriorityMkSelectDynamicOptic);
    descriptor: (Lshapeless/LowPriorityMkSelectDynamicOptic;)V
    flags: (0x0009) ACC_PUBLIC, ACC_STATIC
    Code:
      stack=0, locals=1, args_size=1
         0: return
      LineNumberTable:
        line 311: 0
      LocalVariableTable:
        Start  Length  Slot  Name   Signature
            0       1     0 $this   Lshapeless/LowPriorityMkSelectDynamicOptic;
    MethodParameters:
      Name                           Flags
      $this                          final synthetic
}
InnerClasses:
  public final #10;                       // class shapeless/LowPriorityMkSelectDynamicOptic$$anon$23
  public final #12;                       // class shapeless/LowPriorityMkSelectDynamicOptic$$anon$24
SourceFile: "lenses.scala"
RuntimeVisibleAnnotations:
  0: #6(#7=s#8)
    scala.reflect.ScalaSignature(
      bytes="\u0006\u0005\u0005uaaB\u0003\u0007!\u0003\r\t!\u0003\u0005\u0006!\u0001!\t!E\u0003\u0005+\u0001\u0001a\u0003C\u00038\u0001\u0011\r\u0001\bC\u0003x\u0001\u0011\r\u0001PA\u0010M_^\u0004&/[8sSRLXj[*fY\u0016\u001cG\u000fR=oC6L7m\u00149uS\u000eT\u0011aB\u0001\ng\"\f\u0007/\u001a7fgN\u001c\u0001a\u0005\u0002\u0001\u0015A\u00111BD\u0007\u0002\u0019)\tQ\"A\u0003tG\u0006d\u0017-\u0003\u0002\u0010\u0019\t1\u0011I\\=SK\u001a\fa\u0001J5oSR$C#\u0001\n\u0011\u0005-\u0019\u0012B\u0001\u000b\r\u0005\u0011)f.\u001b;\u0003\u0007\u0005+\b0\u0006\u0004\u0018A)j\u0003\'\u000e\n\u00031i1A!\u0007\u0001\u0001/\taAH]3gS:,W.\u001a8u}A11\u0004\b\u0010*Y=j\u0011AB\u0005\u0003;\u0019\u0011A#T6TK2,7\r\u001e#z]\u0006l\u0017nY(qi&\u001c\u0007CA\u0010!\u0019\u0001!Q!\t\u0002C\u0002\t\u0012\u0011AU\t\u0003G\u0019\u0002\"a\u0003\u0013\n\u0005\u0015b!a\u0002(pi\"Lgn\u001a\t\u0003\u0017\u001dJ!\u0001\u000b\u0007\u0003\u0007\u0005s\u0017\u0010\u0005\u0002 U\u0011)1F\u0001b\u0001E\t\t\u0011\t\u0005\u0002 [\u0011)aF\u0001b\u0001E\t\t1\n\u0005\u0002 a\u0011)\u0011G\u0001b\u0001E\t\t!)\u0002\u000341\u0001\"$aA(viB\u0011q$\u000e\u0003\u0006m\t\u0011\rA\t\u0002\u0005\u001fV$\b\'A\nnW&sg-\u001a:Di>\u00148+\u001a7GS\u0016dG-F\u0004:{}J\u0006.Q\'\u0015\ri\u0002vL[8E!\u001dY$\u0001\u0010 AG\tk\u0011\u0001\u0001\t\u0003?u\"Q!I\u0002C\u0002\t\u0002\"aH \u0005\u000b-\u001a!\u0019\u0001\u0012\u0011\u0005}\tE!\u0002\u0018\u0004\u0005\u0004\u0011\u0003CA\"P\u001d\tyB\tC\u0003F\u0007\u0001\u000fa)A\u0004d_6\u0004xn]3\u0011\tm9\u0015\nP\u0005\u0003\u0011\u001a\u0011Qb\u00149uS\u000e\u001cu.\u001c9pg\u0016\u0014\b\u0003B\u000eK}1K!a\u0013\u0004\u0003\u000bA\u0013\u0018n]7\u0011\u0005}iE!\u0002(\u0004\u0005\u0004\u0011#!A#\n\u0005M:\u0005\"B)\u0004\u0001\b\u0011\u0016aA4f]B!1K\u0016 Y\u001d\tYB+\u0003\u0002V\r\u00059q)\u001a8fe&\u001c\u0017BA\u000bX\u0015\t)f\u0001\u0005\u0002 3\u0012)!l\u0001b\u00017\n\t1)\u0005\u0002$9B\u00111$X\u0005\u0003=\u001a\u0011\u0011bQ8qe>$Wo\u0019;\t\u000b\u0001\u001c\u00019A1\u0002\u000b%tg-\u001a:\u0011\u000b\t,\u0007\fQ4\u000f\u0005m\u0019\u0017B\u00013\u0007\u00031IeNZ3s!J|G-^2u\u0013\t)bM\u0003\u0002e\rA\u0011q\u0004\u001b\u0003\u0006S\u000e\u0011\rA\t\u0002\u0002\u0013\")1n\u0001a\u0002Y\u00061Qn[\"TK2\u0004BaG7?O&\u0011aN\u0002\u0002\f\u001b.\u001cEo\u001c:Qe&\u001cX\u000eC\u0003q\u0007\u0001\u000f\u0011/\u0001\u0004nWB\u001bV\r\u001c\t\u0006eV<\u0007\t\u0014\b\u00037ML!\u0001\u001e\u0004\u0002\u00175[g)[3mI2+gn]\u0005\u0003+YT!\u0001\u001e\u0004\u0002\u001d5\\7+\u001a7GS\u0016dGm\u0011;peVI\u0011\u0010 @\u0002\u0002\u0005\u0015\u0011q\u0003\u000b\bu\u0006E\u0011\u0011DA\u0006!%Y$a_?\u0000\u0003\u0007\t9\u0001\u0005\u0002 y\u0012)\u0011\u0005\u0002b\u0001EA\u0011qD \u0003\u0006W\u0011\u0011\rA\t\t\u0004?\u0005\u0005A!\u0002\u0018\u0005\u0005\u0004\u0011\u0003cA\u0010\u0002\u0006\u0011)\u0011\u0007\u0002b\u0001EA\u0019\u0011\u0011B(\u000f\u0007}\tY\u0001\u0003\u0004F\t\u0001\u000f\u0011Q\u0002\t\u00067\u001d\u000bya\u001f\t\u00067)k\u00181\u0001\u0005\u0007a\u0012\u0001\u001d!a\u0005\u0011\rI,Xp`A\u000b!\ry\u0012q\u0003\u0003\u00065\u0012\u0011\rA\t\u0005\u0007W\u0012\u0001\u001d!a\u0007\u0011\rmi\u0017QCA\u0002\u0001"
    )
  ScalaInlineInfo: length = 0x1D (unknown attribute)
   01 00 00 05 00 2F 00 30 01 00 0D 00 0E 01 00 15
   00 16 00 00 25 00 26 01 00 27 00 28 00
  ScalaSig: length = 0x3 (unknown attribute)
   05 02 00
