Classfile /Users/mw/Projects/slang-braindump/.jar/jar11/assemble/slang-braindump/assemble/content/shapeless/LUBConstraint$.class
  Last modified May 29, 2022; size 1727 bytes
  SHA-256 checksum 3bf7517dca736fa075e4fa3d25c93a0b2767290db393c5c3346f903391501524
  Compiled from "hlistconstraints.scala"
public final class shapeless.LUBConstraint$ implements java.io.Serializable
  minor version: 0
  major version: 52
  flags: (0x0031) ACC_PUBLIC, ACC_FINAL, ACC_SUPER
  this_class: #2                          // shapeless/LUBConstraint$
  super_class: #4                         // java/lang/Object
  interfaces: 1, fields: 1, methods: 6, attributes: 4
Constant pool:
   #1 = Utf8               shapeless/LUBConstraint$
   #2 = Class              #1             // shapeless/LUBConstraint$
   #3 = Utf8               java/lang/Object
   #4 = Class              #3             // java/lang/Object
   #5 = Utf8               java/io/Serializable
   #6 = Class              #5             // java/io/Serializable
   #7 = Utf8               hlistconstraints.scala
   #8 = Utf8               shapeless/LUBConstraint$$anon$8
   #9 = Class              #8             // shapeless/LUBConstraint$$anon$8
  #10 = Utf8               shapeless/LUBConstraint$$anon$9
  #11 = Class              #10            // shapeless/LUBConstraint$$anon$9
  #12 = Utf8               MODULE$
  #13 = Utf8               Lshapeless/LUBConstraint$;
  #14 = Utf8               <clinit>
  #15 = Utf8               ()V
  #16 = Utf8               <init>
  #17 = NameAndType        #16:#15        // "<init>":()V
  #18 = Methodref          #2.#17         // shapeless/LUBConstraint$."<init>":()V
  #19 = NameAndType        #12:#13        // MODULE$:Lshapeless/LUBConstraint$;
  #20 = Fieldref           #2.#19         // shapeless/LUBConstraint$.MODULE$:Lshapeless/LUBConstraint$;
  #21 = Utf8               apply
  #22 = Utf8               (Lshapeless/LUBConstraint;)Lshapeless/LUBConstraint;
  #23 = Utf8               <L::Lshapeless/HList;B:Ljava/lang/Object;>(Lshapeless/LUBConstraint<TL;TB;>;)Lshapeless/LUBConstraint<TL;TB;>;
  #24 = Utf8               lc
  #25 = Utf8               this
  #26 = Utf8               Lshapeless/LUBConstraint;
  #27 = Utf8               hnilLUB
  #28 = Utf8               ()Lshapeless/LUBConstraint;
  #29 = Utf8               <T:Ljava/lang/Object;>()Lshapeless/LUBConstraint<Lshapeless/HNil;TT;>;
  #30 = Methodref          #9.#17         // shapeless/LUBConstraint$$anon$8."<init>":()V
  #31 = Utf8               hlistLUB
  #32 = Utf8               (Lshapeless/LUBConstraint;Lscala/$less$colon$less;)Lshapeless/LUBConstraint;
  #33 = Utf8               <H:Ljava/lang/Object;T::Lshapeless/HList;B:Ljava/lang/Object;>(Lshapeless/LUBConstraint<TT;TB;>;Lscala/$less$colon$less<TH;TB;>;)Lshapeless/LUBConstraint<Lshapeless/$colon$colon<TH;TT;>;TB;>;
  #34 = Utf8               bct
  #35 = Utf8               ev
  #36 = Methodref          #11.#17        // shapeless/LUBConstraint$$anon$9."<init>":()V
  #37 = Utf8               Lscala/$less$colon$less;
  #38 = Utf8               writeReplace
  #39 = Utf8               ()Ljava/lang/Object;
  #40 = Utf8               scala/runtime/ModuleSerializationProxy
  #41 = Class              #40            // scala/runtime/ModuleSerializationProxy
  #42 = Utf8               (Ljava/lang/Class;)V
  #43 = NameAndType        #16:#42        // "<init>":(Ljava/lang/Class;)V
  #44 = Methodref          #41.#43        // scala/runtime/ModuleSerializationProxy."<init>":(Ljava/lang/Class;)V
  #45 = Methodref          #4.#17         // java/lang/Object."<init>":()V
  #46 = Utf8               Code
  #47 = Utf8               LineNumberTable
  #48 = Utf8               LocalVariableTable
  #49 = Utf8               Signature
  #50 = Utf8               MethodParameters
  #51 = Utf8               InnerClasses
  #52 = Utf8               SourceFile
  #53 = Utf8               ScalaInlineInfo
  #54 = Utf8               Scala
{
  public static final shapeless.LUBConstraint$ MODULE$;
    descriptor: Lshapeless/LUBConstraint$;
    flags: (0x0019) ACC_PUBLIC, ACC_STATIC, ACC_FINAL

  public static {};
    descriptor: ()V
    flags: (0x0009) ACC_PUBLIC, ACC_STATIC
    Code:
      stack=2, locals=0, args_size=0
         0: new           #2                  // class shapeless/LUBConstraint$
         3: dup
         4: invokespecial #18                 // Method "<init>":()V
         7: putstatic     #20                 // Field MODULE$:Lshapeless/LUBConstraint$;
        10: return
      LineNumberTable:
        line 75: 0

  public <L extends shapeless.HList, B extends java.lang.Object> shapeless.LUBConstraint<L, B> apply(shapeless.LUBConstraint<L, B>);
    descriptor: (Lshapeless/LUBConstraint;)Lshapeless/LUBConstraint;
    flags: (0x0001) ACC_PUBLIC
    Code:
      stack=1, locals=2, args_size=2
         0: aload_1
         1: areturn
      LineNumberTable:
        line 76: 0
      LocalVariableTable:
        Start  Length  Slot  Name   Signature
            0       2     0  this   Lshapeless/LUBConstraint$;
            0       2     1    lc   Lshapeless/LUBConstraint;
    Signature: #23                          // <L::Lshapeless/HList;B:Ljava/lang/Object;>(Lshapeless/LUBConstraint<TL;TB;>;)Lshapeless/LUBConstraint<TL;TB;>;
    MethodParameters:
      Name                           Flags
      lc                             final

  public <T extends java.lang.Object> shapeless.LUBConstraint<shapeless.HNil, T> hnilLUB();
    descriptor: ()Lshapeless/LUBConstraint;
    flags: (0x0001) ACC_PUBLIC
    Code:
      stack=2, locals=1, args_size=1
         0: new           #9                  // class shapeless/LUBConstraint$$anon$8
         3: dup
         4: invokespecial #30                 // Method shapeless/LUBConstraint$$anon$8."<init>":()V
         7: areturn
      LineNumberTable:
        line 82: 0
      LocalVariableTable:
        Start  Length  Slot  Name   Signature
            0       8     0  this   Lshapeless/LUBConstraint$;
    Signature: #29                          // <T:Ljava/lang/Object;>()Lshapeless/LUBConstraint<Lshapeless/HNil;TT;>;

  public <H extends java.lang.Object, T extends shapeless.HList, B extends java.lang.Object> shapeless.LUBConstraint<shapeless.$colon$colon<H, T>, B> hlistLUB(shapeless.LUBConstraint<T, B>, scala.$less$colon$less<H, B>);
    descriptor: (Lshapeless/LUBConstraint;Lscala/$less$colon$less;)Lshapeless/LUBConstraint;
    flags: (0x0001) ACC_PUBLIC
    Code:
      stack=2, locals=3, args_size=3
         0: new           #11                 // class shapeless/LUBConstraint$$anon$9
         3: dup
         4: invokespecial #36                 // Method shapeless/LUBConstraint$$anon$9."<init>":()V
         7: areturn
      LineNumberTable:
        line 84: 0
      LocalVariableTable:
        Start  Length  Slot  Name   Signature
            0       8     0  this   Lshapeless/LUBConstraint$;
            0       8     1   bct   Lshapeless/LUBConstraint;
            0       8     2    ev   Lscala/$less$colon$less;
    Signature: #33                          // <H:Ljava/lang/Object;T::Lshapeless/HList;B:Ljava/lang/Object;>(Lshapeless/LUBConstraint<TT;TB;>;Lscala/$less$colon$less<TH;TB;>;)Lshapeless/LUBConstraint<Lshapeless/$colon$colon<TH;TT;>;TB;>;
    MethodParameters:
      Name                           Flags
      bct                            final
      ev                             final

  private java.lang.Object writeReplace();
    descriptor: ()Ljava/lang/Object;
    flags: (0x0002) ACC_PRIVATE
    Code:
      stack=3, locals=1, args_size=1
         0: new           #41                 // class scala/runtime/ModuleSerializationProxy
         3: dup
         4: ldc           #2                  // class shapeless/LUBConstraint$
         6: invokespecial #44                 // Method scala/runtime/ModuleSerializationProxy."<init>":(Ljava/lang/Class;)V
         9: areturn
      LineNumberTable:
        line 75: 0
      LocalVariableTable:
        Start  Length  Slot  Name   Signature
            0      10     0  this   Lshapeless/LUBConstraint$;

  private shapeless.LUBConstraint$();
    descriptor: ()V
    flags: (0x0002) ACC_PRIVATE
    Code:
      stack=1, locals=1, args_size=1
         0: aload_0
         1: invokespecial #45                 // Method java/lang/Object."<init>":()V
         4: return
      LineNumberTable:
        line 90: 0
        line 75: 4
      LocalVariableTable:
        Start  Length  Slot  Name   Signature
            0       5     0  this   Lshapeless/LUBConstraint$;
}
InnerClasses:
  public final #9;                        // class shapeless/LUBConstraint$$anon$8
  public final #11;                       // class shapeless/LUBConstraint$$anon$9
SourceFile: "hlistconstraints.scala"
  ScalaInlineInfo: length = 0x1D (unknown attribute)
   01 01 00 05 00 10 00 0F 01 00 15 00 16 01 00 1F
   00 20 01 00 1B 00 1C 01 00 26 00 27 01
  Scala: length = 0x0 (unknown attribute)

