Classfile /Users/mw/Projects/slang-braindump/.jar/jar11/assemble/slang-braindump/assemble/content/shapeless/MkCoproductSelectPrism$$anon$35.class
  Last modified May 29, 2022; size 1391 bytes
  SHA-256 checksum 57ae659006a0749a5e6109ea42d0096b6ad3850d2316856fb224d2f2e18ebe26
  Compiled from "lenses.scala"
public final class shapeless.MkCoproductSelectPrism$$anon$35 extends java.lang.Object implements shapeless.MkCoproductSelectPrism<C, T>
  minor version: 0
  major version: 52
  flags: (0x0031) ACC_PUBLIC, ACC_FINAL, ACC_SUPER
  this_class: #2                          // shapeless/MkCoproductSelectPrism$$anon$35
  super_class: #5                         // java/lang/Object
  interfaces: 1, fields: 2, methods: 2, attributes: 6
Constant pool:
   #1 = Utf8               shapeless/MkCoproductSelectPrism$$anon$35
   #2 = Class              #1             // shapeless/MkCoproductSelectPrism$$anon$35
   #3 = Utf8               Ljava/lang/Object;Lshapeless/MkCoproductSelectPrism<TC;TT;>;
   #4 = Utf8               java/lang/Object
   #5 = Class              #4             // java/lang/Object
   #6 = Utf8               shapeless/MkCoproductSelectPrism
   #7 = Class              #6             // shapeless/MkCoproductSelectPrism
   #8 = Utf8               lenses.scala
   #9 = Utf8               shapeless/MkCoproductSelectPrism$
  #10 = Class              #9             // shapeless/MkCoproductSelectPrism$
  #11 = Utf8               mKCoproductSelectPrism
  #12 = Utf8               (Lshapeless/ops/coproduct$Selector;Lshapeless/ops/coproduct$Inject;)Lshapeless/MkCoproductSelectPrism;
  #13 = NameAndType        #11:#12        // mKCoproductSelectPrism:(Lshapeless/ops/coproduct$Selector;Lshapeless/ops/coproduct$Inject;)Lshapeless/MkCoproductSelectPrism;
  #14 = Utf8               shapeless/MkCoproductSelectPrism$$anon$35$$anon$36
  #15 = Class              #14            // shapeless/MkCoproductSelectPrism$$anon$35$$anon$36
  #16 = Utf8               shapeless/ops/coproduct$Inject
  #17 = Class              #16            // shapeless/ops/coproduct$Inject
  #18 = Utf8               shapeless/ops/coproduct
  #19 = Class              #18            // shapeless/ops/coproduct
  #20 = Utf8               Inject
  #21 = Utf8               shapeless/ops/coproduct$Selector
  #22 = Class              #21            // shapeless/ops/coproduct$Selector
  #23 = Utf8               Selector
  #24 = Utf8               selector$2
  #25 = Utf8               Lshapeless/ops/coproduct$Selector;
  #26 = Utf8               injector$1
  #27 = Utf8               Lshapeless/ops/coproduct$Inject;
  #28 = Utf8               apply
  #29 = Utf8               ()Lshapeless/Prism;
  #30 = Utf8               ()Lshapeless/Prism<TC;TT;>;
  #31 = Utf8               <init>
  #32 = Utf8               (Lshapeless/MkCoproductSelectPrism$$anon$35;)V
  #33 = NameAndType        #31:#32        // "<init>":(Lshapeless/MkCoproductSelectPrism$$anon$35;)V
  #34 = Methodref          #15.#33        // shapeless/MkCoproductSelectPrism$$anon$35$$anon$36."<init>":(Lshapeless/MkCoproductSelectPrism$$anon$35;)V
  #35 = Utf8               this
  #36 = Utf8               Lshapeless/MkCoproductSelectPrism$$anon$35;
  #37 = Utf8               (Lshapeless/ops/coproduct$Selector;Lshapeless/ops/coproduct$Inject;)V
  #38 = NameAndType        #24:#25        // selector$2:Lshapeless/ops/coproduct$Selector;
  #39 = Fieldref           #2.#38         // shapeless/MkCoproductSelectPrism$$anon$35.selector$2:Lshapeless/ops/coproduct$Selector;
  #40 = NameAndType        #26:#27        // injector$1:Lshapeless/ops/coproduct$Inject;
  #41 = Fieldref           #2.#40         // shapeless/MkCoproductSelectPrism$$anon$35.injector$1:Lshapeless/ops/coproduct$Inject;
  #42 = Utf8               ()V
  #43 = NameAndType        #31:#42        // "<init>":()V
  #44 = Methodref          #5.#43         // java/lang/Object."<init>":()V
  #45 = Utf8               Code
  #46 = Utf8               LineNumberTable
  #47 = Utf8               LocalVariableTable
  #48 = Utf8               Signature
  #49 = Utf8               MethodParameters
  #50 = Utf8               InnerClasses
  #51 = Utf8               EnclosingMethod
  #52 = Utf8               SourceFile
  #53 = Utf8               ScalaInlineInfo
  #54 = Utf8               Scala
{
  public final shapeless.ops.coproduct$Selector selector$2;
    descriptor: Lshapeless/ops/coproduct$Selector;
    flags: (0x0011) ACC_PUBLIC, ACC_FINAL

  public final shapeless.ops.coproduct$Inject injector$1;
    descriptor: Lshapeless/ops/coproduct$Inject;
    flags: (0x0011) ACC_PUBLIC, ACC_FINAL

  public shapeless.Prism<C, T> apply();
    descriptor: ()Lshapeless/Prism;
    flags: (0x0001) ACC_PUBLIC
    Code:
      stack=3, locals=1, args_size=1
         0: new           #15                 // class shapeless/MkCoproductSelectPrism$$anon$35$$anon$36
         3: dup
         4: aload_0
         5: invokespecial #34                 // Method shapeless/MkCoproductSelectPrism$$anon$35$$anon$36."<init>":(Lshapeless/MkCoproductSelectPrism$$anon$35;)V
         8: areturn
      LineNumberTable:
        line 444: 0
      LocalVariableTable:
        Start  Length  Slot  Name   Signature
            0       9     0  this   Lshapeless/MkCoproductSelectPrism$$anon$35;
    Signature: #30                          // ()Lshapeless/Prism<TC;TT;>;

  public shapeless.MkCoproductSelectPrism$$anon$35(shapeless.ops.coproduct$Selector, shapeless.ops.coproduct$Inject);
    descriptor: (Lshapeless/ops/coproduct$Selector;Lshapeless/ops/coproduct$Inject;)V
    flags: (0x0001) ACC_PUBLIC
    Code:
      stack=2, locals=3, args_size=3
         0: aload_0
         1: aload_1
         2: putfield      #39                 // Field selector$2:Lshapeless/ops/coproduct$Selector;
         5: aload_0
         6: aload_2
         7: putfield      #41                 // Field injector$1:Lshapeless/ops/coproduct$Inject;
        10: aload_0
        11: invokespecial #44                 // Method java/lang/Object."<init>":()V
        14: return
      LineNumberTable:
        line 441: 0
        line 442: 10
      LocalVariableTable:
        Start  Length  Slot  Name   Signature
            0      15     0  this   Lshapeless/MkCoproductSelectPrism$$anon$35;
            0      15     1 selector$2   Lshapeless/ops/coproduct$Selector;
            0      15     2 injector$1   Lshapeless/ops/coproduct$Inject;
    MethodParameters:
      Name                           Flags
      selector$2                     final
      injector$1                     final
}
InnerClasses:
  public final #2;                        // class shapeless/MkCoproductSelectPrism$$anon$35
  public final #15;                       // class shapeless/MkCoproductSelectPrism$$anon$35$$anon$36
  public static #20= #17 of #19;          // Inject=class shapeless/ops/coproduct$Inject of class shapeless/ops/coproduct
  public static #23= #22 of #19;          // Selector=class shapeless/ops/coproduct$Selector of class shapeless/ops/coproduct
EnclosingMethod: #10.#13                // shapeless.MkCoproductSelectPrism$.mKCoproductSelectPrism
Signature: #3                           // Ljava/lang/Object;Lshapeless/MkCoproductSelectPrism<TC;TT;>;
SourceFile: "lenses.scala"
  ScalaInlineInfo: length = 0xE (unknown attribute)
   01 01 00 02 00 1F 00 25 01 00 1C 00 1D 01
  Scala: length = 0x0 (unknown attribute)

