Classfile /Users/mw/Projects/slang-braindump/.jar/jar11/assemble/slang-braindump/assemble/content/shapeless/MkHListSelectLens.class
  Last modified May 29, 2022; size 1812 bytes
  SHA-256 checksum 668442ffbfe68d55332bc1fd4186c674375235ee4ff59f319d93eab0ef23b92d
  Compiled from "lenses.scala"
public interface shapeless.MkHListSelectLens<L extends shapeless.HList, U extends java.lang.Object> extends java.io.Serializable
  minor version: 0
  major version: 52
  flags: (0x0601) ACC_PUBLIC, ACC_INTERFACE, ACC_ABSTRACT
  this_class: #2                          // shapeless/MkHListSelectLens
  super_class: #5                         // java/lang/Object
  interfaces: 1, fields: 0, methods: 2, attributes: 6
Constant pool:
   #1 = Utf8               shapeless/MkHListSelectLens
   #2 = Class              #1             // shapeless/MkHListSelectLens
   #3 = Utf8               <L::Lshapeless/HList;U:Ljava/lang/Object;>Ljava/lang/Object;Ljava/io/Serializable;
   #4 = Utf8               java/lang/Object
   #5 = Class              #4             // java/lang/Object
   #6 = Utf8               java/io/Serializable
   #7 = Class              #6             // java/io/Serializable
   #8 = Utf8               lenses.scala
   #9 = Utf8               Lscala/reflect/ScalaSignature;
  #10 = Utf8               bytes
  #11 = Utf8               \u0006\u000514qa\u0002\u0005\u0011\u0002G\u00051\u0002C\u0003 \u0001\u0019\u0005\u0001eB\u00038\u0011!\u0005\u0001HB\u0003\b\u0011!\u0005\u0011\bC\u0003B\u0007\u0011\u0005!\tC\u0003D\u0007\u0011\rA\tC\u0004e\u0007\u0005\u0005I\u0011B3\u0003#5[\u0007\nT5tiN+G.Z2u\u0019\u0016t7OC\u0001\n\u0003%\u0019\b.\u00199fY\u0016\u001c8o\u0001\u0001\u0016\u000719\u0013gE\u0002\u0001\u001bM\u0001\"AD\t\u000e\u0003=Q\u0011\u0001E\u0001\u0006g\u000e\fG.Y\u0005\u0003%=\u0011a!\u00118z%\u00164\u0007C\u0001\u000b\u001d\u001d\t)\"D\u0004\u0002\u001735\tqC\u0003\u0002\u0019\u0015\u00051AH]8pizJ\u0011\u0001E\u0005\u00037=\tq\u0001]1dW\u0006<W-\u0003\u0002\u001e=\ta1+\u001a:jC2L\'0\u00192mK*\u00111dD\u0001\u0006CB\u0004H.\u001f\u000b\u0002CA!!eI\u00131\u001b\u0005A\u0011B\u0001\u0013\t\u0005\u0011aUM\\:\u0011\u0005\u0019:C\u0002\u0001\u0003\u0006Q\u0001\u0011\r!\u000b\u0002\u0002\u0019F\u0011!&\f\t\u0003\u001d-J!\u0001L\b\u0003\u000f9{G\u000f[5oOB\u0011!EL\u0005\u0003_!\u0011Q\u0001\u0013\'jgR\u0004\"AJ\u0019\u0005\u000bI\u0002!\u0019A\u001a\u0003\u0003U\u000b\"A\u000b\u001b\u0011\u00059)\u0014B\u0001\u001c\u0010\u0005\r\te._\u0001\u0012\u001b.DE*[:u\'\u0016dWm\u0019;MK:\u001c\bC\u0001\u0012\u0004\'\r\u0019QB\u000f\t\u0003w\u0001k\u0011\u0001\u0010\u0006\u0003{y\n!![8\u000b\u0003}\nAA[1wC&\u0011Q\u0004P\u0001\u0007y%t\u0017\u000e\u001e \u0015\u0003a\n\u0011#\\&IY&\u001cHoU3mK\u000e$H*\u001a8t+\r)\u0005J\u0013\u000b\u0004\r.C\u0006\u0003\u0002\u0012\u0001\u000f&\u0003\"A\n%\u0005\u000b!*!\u0019A\u0015\u0011\u0005\u0019RE!\u0002\u001a\u0006\u0005\u0004\u0019\u0004\"\u0002\'\u0006\u0001\bi\u0015\u0001C:fY\u0016\u001cGo\u001c:\u0011\t9+v)\u0013\b\u0003\u001fJs!A\t)\n\u0005EC\u0011aA8qg&\u00111\u000bV\u0001\u0006Q2L7\u000f\u001e\u0006\u0003#\"I!AV,\u0003\u0011M+G.Z2u_JT!a\u0015+\t\u000be+\u00019\u0001.\u0002\u0011I,\u0007\u000f\\1dKJ\u0004ba\u00170H\u0013&\u000bgB\u0001(]\u0013\tiv+\u0001\u0005SKBd\u0017mY3s\u0013\ty\u0006MA\u0002BkbT!!X,\u0011\t9\u0011\u0017jR\u0005\u0003G>\u0011a\u0001V;qY\u0016\u0014\u0014\u0001D<sSR,\'+\u001a9mC\u000e,G#\u00014\u0011\u0005\u001dTW\"\u00015\u000b\u0005%t\u0014\u0001\u00027b]\u001eL!a\u001b5\u0003\r=\u0013\'.Z2u\u0001
  #12 = Utf8               shapeless/ops/hlist$Replacer
  #13 = Class              #12            // shapeless/ops/hlist$Replacer
  #14 = Utf8               shapeless/ops/hlist
  #15 = Class              #14            // shapeless/ops/hlist
  #16 = Utf8               Replacer
  #17 = Utf8               shapeless/ops/hlist$Selector
  #18 = Class              #17            // shapeless/ops/hlist$Selector
  #19 = Utf8               Selector
  #20 = Utf8               mKHlistSelectLens
  #21 = Utf8               (Lshapeless/ops/hlist$Selector;Lshapeless/ops/hlist$Replacer;)Lshapeless/MkHListSelectLens;
  #22 = Utf8               <L::Lshapeless/HList;U:Ljava/lang/Object;>(Lshapeless/ops/hlist$Selector<TL;TU;>;Lshapeless/ops/hlist$Replacer<TL;TU;TU;>;)Lshapeless/MkHListSelectLens<TL;TU;>;
  #23 = Utf8               selector
  #24 = Utf8               replacer
  #25 = Utf8               shapeless/MkHListSelectLens$
  #26 = Class              #25            // shapeless/MkHListSelectLens$
  #27 = Utf8               MODULE$
  #28 = Utf8               Lshapeless/MkHListSelectLens$;
  #29 = NameAndType        #27:#28        // MODULE$:Lshapeless/MkHListSelectLens$;
  #30 = Fieldref           #26.#29        // shapeless/MkHListSelectLens$.MODULE$:Lshapeless/MkHListSelectLens$;
  #31 = NameAndType        #20:#21        // mKHlistSelectLens:(Lshapeless/ops/hlist$Selector;Lshapeless/ops/hlist$Replacer;)Lshapeless/MkHListSelectLens;
  #32 = Methodref          #26.#31        // shapeless/MkHListSelectLens$.mKHlistSelectLens:(Lshapeless/ops/hlist$Selector;Lshapeless/ops/hlist$Replacer;)Lshapeless/MkHListSelectLens;
  #33 = Utf8               apply
  #34 = Utf8               ()Lshapeless/Lens;
  #35 = Utf8               ()Lshapeless/Lens<TL;TU;>;
  #36 = Utf8               Code
  #37 = Utf8               Signature
  #38 = Utf8               MethodParameters
  #39 = Utf8               InnerClasses
  #40 = Utf8               SourceFile
  #41 = Utf8               RuntimeVisibleAnnotations
  #42 = Utf8               ScalaInlineInfo
  #43 = Utf8               ScalaSig
{
  public static <L extends shapeless.HList, U extends java.lang.Object> shapeless.MkHListSelectLens<L, U> mKHlistSelectLens(shapeless.ops.hlist$Selector<L, U>, shapeless.ops.hlist$Replacer<L, U, U>);
    descriptor: (Lshapeless/ops/hlist$Selector;Lshapeless/ops/hlist$Replacer;)Lshapeless/MkHListSelectLens;
    flags: (0x0009) ACC_PUBLIC, ACC_STATIC
    Code:
      stack=3, locals=2, args_size=2
         0: getstatic     #30                 // Field shapeless/MkHListSelectLens$.MODULE$:Lshapeless/MkHListSelectLens$;
         3: aload_0
         4: aload_1
         5: invokevirtual #32                 // Method shapeless/MkHListSelectLens$.mKHlistSelectLens:(Lshapeless/ops/hlist$Selector;Lshapeless/ops/hlist$Replacer;)Lshapeless/MkHListSelectLens;
         8: areturn
    Signature: #22                          // <L::Lshapeless/HList;U:Ljava/lang/Object;>(Lshapeless/ops/hlist$Selector<TL;TU;>;Lshapeless/ops/hlist$Replacer<TL;TU;TU;>;)Lshapeless/MkHListSelectLens<TL;TU;>;
    MethodParameters:
      Name                           Flags
      selector                       final
      replacer                       final

  public abstract shapeless.Lens<L, U> apply();
    descriptor: ()Lshapeless/Lens;
    flags: (0x0401) ACC_PUBLIC, ACC_ABSTRACT
    Signature: #35                          // ()Lshapeless/Lens<TL;TU;>;
}
InnerClasses:
  public static #16= #13 of #15;          // Replacer=class shapeless/ops/hlist$Replacer of class shapeless/ops/hlist
  public static #19= #18 of #15;          // Selector=class shapeless/ops/hlist$Selector of class shapeless/ops/hlist
Signature: #3                           // <L::Lshapeless/HList;U:Ljava/lang/Object;>Ljava/lang/Object;Ljava/io/Serializable;
SourceFile: "lenses.scala"
RuntimeVisibleAnnotations:
  0: #9(#10=s#11)
    scala.reflect.ScalaSignature(
      bytes="\u0006\u000514qa\u0002\u0005\u0011\u0002G\u00051\u0002C\u0003 \u0001\u0019\u0005\u0001eB\u00038\u0011!\u0005\u0001HB\u0003\b\u0011!\u0005\u0011\bC\u0003B\u0007\u0011\u0005!\tC\u0003D\u0007\u0011\rA\tC\u0004e\u0007\u0005\u0005I\u0011B3\u0003#5[\u0007\nT5tiN+G.Z2u\u0019\u0016t7OC\u0001\n\u0003%\u0019\b.\u00199fY\u0016\u001c8o\u0001\u0001\u0016\u000719\u0013gE\u0002\u0001\u001bM\u0001\"AD\t\u000e\u0003=Q\u0011\u0001E\u0001\u0006g\u000e\fG.Y\u0005\u0003%=\u0011a!\u00118z%\u00164\u0007C\u0001\u000b\u001d\u001d\t)\"D\u0004\u0002\u001735\tqC\u0003\u0002\u0019\u0015\u00051AH]8pizJ\u0011\u0001E\u0005\u00037=\tq\u0001]1dW\u0006<W-\u0003\u0002\u001e=\ta1+\u001a:jC2L\'0\u00192mK*\u00111dD\u0001\u0006CB\u0004H.\u001f\u000b\u0002CA!!eI\u00131\u001b\u0005A\u0011B\u0001\u0013\t\u0005\u0011aUM\\:\u0011\u0005\u0019:C\u0002\u0001\u0003\u0006Q\u0001\u0011\r!\u000b\u0002\u0002\u0019F\u0011!&\f\t\u0003\u001d-J!\u0001L\b\u0003\u000f9{G\u000f[5oOB\u0011!EL\u0005\u0003_!\u0011Q\u0001\u0013\'jgR\u0004\"AJ\u0019\u0005\u000bI\u0002!\u0019A\u001a\u0003\u0003U\u000b\"A\u000b\u001b\u0011\u00059)\u0014B\u0001\u001c\u0010\u0005\r\te._\u0001\u0012\u001b.DE*[:u\'\u0016dWm\u0019;MK:\u001c\bC\u0001\u0012\u0004\'\r\u0019QB\u000f\t\u0003w\u0001k\u0011\u0001\u0010\u0006\u0003{y\n!![8\u000b\u0003}\nAA[1wC&\u0011Q\u0004P\u0001\u0007y%t\u0017\u000e\u001e \u0015\u0003a\n\u0011#\\&IY&\u001cHoU3mK\u000e$H*\u001a8t+\r)\u0005J\u0013\u000b\u0004\r.C\u0006\u0003\u0002\u0012\u0001\u000f&\u0003\"A\n%\u0005\u000b!*!\u0019A\u0015\u0011\u0005\u0019RE!\u0002\u001a\u0006\u0005\u0004\u0019\u0004\"\u0002\'\u0006\u0001\bi\u0015\u0001C:fY\u0016\u001cGo\u001c:\u0011\t9+v)\u0013\b\u0003\u001fJs!A\t)\n\u0005EC\u0011aA8qg&\u00111\u000bV\u0001\u0006Q2L7\u000f\u001e\u0006\u0003#\"I!AV,\u0003\u0011M+G.Z2u_JT!a\u0015+\t\u000be+\u00019\u0001.\u0002\u0011I,\u0007\u000f\\1dKJ\u0004ba\u00170H\u0013&\u000bgB\u0001(]\u0013\tiv+\u0001\u0005SKBd\u0017mY3s\u0013\ty\u0006MA\u0002BkbT!!X,\u0011\t9\u0011\u0017jR\u0005\u0003G>\u0011a\u0001V;qY\u0016\u0014\u0014\u0001D<sSR,\'+\u001a9mC\u000e,G#\u00014\u0011\u0005\u001dTW\"\u00015\u000b\u0005%t\u0014\u0001\u00027b]\u001eL!a\u001b5\u0003\r=\u0013\'.Z2u\u0001"
    )
  ScalaInlineInfo: length = 0x9 (unknown attribute)
   01 00 00 01 00 21 00 22 00
  ScalaSig: length = 0x3 (unknown attribute)
   05 02 00
