Classfile /Users/mw/Projects/slang-braindump/.jar/jar11/assemble/slang-braindump/assemble/content/shapeless/MkHListNthLens$$anon$31.class
  Last modified May 29, 2022; size 1260 bytes
  SHA-256 checksum d75d1b58fec6d64d9f6011d306802f76eb5d10e3518f3d377779db1de20ba98f
  Compiled from "lenses.scala"
public final class shapeless.MkHListNthLens$$anon$31 extends java.lang.Object implements shapeless.MkHListNthLens<L, N>
  minor version: 0
  major version: 52
  flags: (0x0031) ACC_PUBLIC, ACC_FINAL, ACC_SUPER
  this_class: #2                          // shapeless/MkHListNthLens$$anon$31
  super_class: #5                         // java/lang/Object
  interfaces: 1, fields: 2, methods: 2, attributes: 6
Constant pool:
   #1 = Utf8               shapeless/MkHListNthLens$$anon$31
   #2 = Class              #1             // shapeless/MkHListNthLens$$anon$31
   #3 = Utf8               Ljava/lang/Object;Lshapeless/MkHListNthLens<TL;TN;>;
   #4 = Utf8               java/lang/Object
   #5 = Class              #4             // java/lang/Object
   #6 = Utf8               shapeless/MkHListNthLens
   #7 = Class              #6             // shapeless/MkHListNthLens
   #8 = Utf8               lenses.scala
   #9 = Utf8               shapeless/MkHListNthLens$
  #10 = Class              #9             // shapeless/MkHListNthLens$
  #11 = Utf8               mkHListNthLens
  #12 = Utf8               (Lshapeless/ops/hlist$At;Lshapeless/ops/hlist$ReplaceAt;)Lshapeless/MkHListNthLens;
  #13 = NameAndType        #11:#12        // mkHListNthLens:(Lshapeless/ops/hlist$At;Lshapeless/ops/hlist$ReplaceAt;)Lshapeless/MkHListNthLens;
  #14 = Utf8               shapeless/MkHListNthLens$$anon$31$$anon$32
  #15 = Class              #14            // shapeless/MkHListNthLens$$anon$31$$anon$32
  #16 = Utf8               shapeless/ops/hlist$At
  #17 = Class              #16            // shapeless/ops/hlist$At
  #18 = Utf8               shapeless/ops/hlist
  #19 = Class              #18            // shapeless/ops/hlist
  #20 = Utf8               At
  #21 = Utf8               shapeless/ops/hlist$ReplaceAt
  #22 = Class              #21            // shapeless/ops/hlist$ReplaceAt
  #23 = Utf8               ReplaceAt
  #24 = Utf8               atx$1
  #25 = Utf8               Lshapeless/ops/hlist$At;
  #26 = Utf8               replace$1
  #27 = Utf8               Lshapeless/ops/hlist$ReplaceAt;
  #28 = Utf8               apply
  #29 = Utf8               ()Lshapeless/Lens;
  #30 = Utf8               ()Lshapeless/Lens<TL;TE;>;
  #31 = Utf8               <init>
  #32 = Utf8               (Lshapeless/MkHListNthLens$$anon$31;)V
  #33 = NameAndType        #31:#32        // "<init>":(Lshapeless/MkHListNthLens$$anon$31;)V
  #34 = Methodref          #15.#33        // shapeless/MkHListNthLens$$anon$31$$anon$32."<init>":(Lshapeless/MkHListNthLens$$anon$31;)V
  #35 = Utf8               this
  #36 = Utf8               Lshapeless/MkHListNthLens$$anon$31;
  #37 = Utf8               (Lshapeless/ops/hlist$At;Lshapeless/ops/hlist$ReplaceAt;)V
  #38 = NameAndType        #24:#25        // atx$1:Lshapeless/ops/hlist$At;
  #39 = Fieldref           #2.#38         // shapeless/MkHListNthLens$$anon$31.atx$1:Lshapeless/ops/hlist$At;
  #40 = NameAndType        #26:#27        // replace$1:Lshapeless/ops/hlist$ReplaceAt;
  #41 = Fieldref           #2.#40         // shapeless/MkHListNthLens$$anon$31.replace$1:Lshapeless/ops/hlist$ReplaceAt;
  #42 = Utf8               ()V
  #43 = NameAndType        #31:#42        // "<init>":()V
  #44 = Methodref          #5.#43         // java/lang/Object."<init>":()V
  #45 = Utf8               Code
  #46 = Utf8               LineNumberTable
  #47 = Utf8               LocalVariableTable
  #48 = Utf8               Signature
  #49 = Utf8               MethodParameters
  #50 = Utf8               InnerClasses
  #51 = Utf8               EnclosingMethod
  #52 = Utf8               SourceFile
  #53 = Utf8               ScalaInlineInfo
  #54 = Utf8               Scala
{
  public final shapeless.ops.hlist$At atx$1;
    descriptor: Lshapeless/ops/hlist$At;
    flags: (0x0011) ACC_PUBLIC, ACC_FINAL

  public final shapeless.ops.hlist$ReplaceAt replace$1;
    descriptor: Lshapeless/ops/hlist$ReplaceAt;
    flags: (0x0011) ACC_PUBLIC, ACC_FINAL

  public shapeless.Lens<L, E> apply();
    descriptor: ()Lshapeless/Lens;
    flags: (0x0001) ACC_PUBLIC
    Code:
      stack=3, locals=1, args_size=1
         0: new           #15                 // class shapeless/MkHListNthLens$$anon$31$$anon$32
         3: dup
         4: aload_0
         5: invokespecial #34                 // Method shapeless/MkHListNthLens$$anon$31$$anon$32."<init>":(Lshapeless/MkHListNthLens$$anon$31;)V
         8: areturn
      LineNumberTable:
        line 412: 0
      LocalVariableTable:
        Start  Length  Slot  Name   Signature
            0       9     0  this   Lshapeless/MkHListNthLens$$anon$31;
    Signature: #30                          // ()Lshapeless/Lens<TL;TE;>;

  public shapeless.MkHListNthLens$$anon$31(shapeless.ops.hlist$At, shapeless.ops.hlist$ReplaceAt);
    descriptor: (Lshapeless/ops/hlist$At;Lshapeless/ops/hlist$ReplaceAt;)V
    flags: (0x0001) ACC_PUBLIC
    Code:
      stack=2, locals=3, args_size=3
         0: aload_0
         1: aload_1
         2: putfield      #39                 // Field atx$1:Lshapeless/ops/hlist$At;
         5: aload_0
         6: aload_2
         7: putfield      #41                 // Field replace$1:Lshapeless/ops/hlist$ReplaceAt;
        10: aload_0
        11: invokespecial #44                 // Method java/lang/Object."<init>":()V
        14: return
      LineNumberTable:
        line 408: 0
        line 409: 10
      LocalVariableTable:
        Start  Length  Slot  Name   Signature
            0      15     0  this   Lshapeless/MkHListNthLens$$anon$31;
            0      15     1 atx$1   Lshapeless/ops/hlist$At;
            0      15     2 replace$1   Lshapeless/ops/hlist$ReplaceAt;
    MethodParameters:
      Name                           Flags
      atx$1                          final
      replace$1                      final
}
InnerClasses:
  public final #2;                        // class shapeless/MkHListNthLens$$anon$31
  public final #15;                       // class shapeless/MkHListNthLens$$anon$31$$anon$32
  public static #20= #17 of #19;          // At=class shapeless/ops/hlist$At of class shapeless/ops/hlist
  public static #23= #22 of #19;          // ReplaceAt=class shapeless/ops/hlist$ReplaceAt of class shapeless/ops/hlist
EnclosingMethod: #10.#13                // shapeless.MkHListNthLens$.mkHListNthLens
Signature: #3                           // Ljava/lang/Object;Lshapeless/MkHListNthLens<TL;TN;>;
SourceFile: "lenses.scala"
  ScalaInlineInfo: length = 0xE (unknown attribute)
   01 01 00 02 00 1F 00 25 01 00 1C 00 1D 01
  Scala: length = 0x0 (unknown attribute)

