Classfile /Users/mw/Projects/slang-braindump/.jar/jar11/assemble/slang-braindump/assemble/content/shapeless/MkNthFieldLens.class
  Last modified May 29, 2022; size 1770 bytes
  SHA-256 checksum 39113055bfc3bf5756c7572f2e726dde5acc306ab2ead81a9e12eb8353df9675
  Compiled from "lenses.scala"
public interface shapeless.MkNthFieldLens<A extends java.lang.Object, N extends shapeless.Nat> extends java.io.Serializable
  minor version: 0
  major version: 52
  flags: (0x0601) ACC_PUBLIC, ACC_INTERFACE, ACC_ABSTRACT
  this_class: #2                          // shapeless/MkNthFieldLens
  super_class: #5                         // java/lang/Object
  interfaces: 1, fields: 0, methods: 2, attributes: 5
Constant pool:
   #1 = Utf8               shapeless/MkNthFieldLens
   #2 = Class              #1             // shapeless/MkNthFieldLens
   #3 = Utf8               <A:Ljava/lang/Object;N::Lshapeless/Nat;>Ljava/lang/Object;Ljava/io/Serializable;
   #4 = Utf8               java/lang/Object
   #5 = Class              #4             // java/lang/Object
   #6 = Utf8               java/io/Serializable
   #7 = Class              #6             // java/io/Serializable
   #8 = Utf8               lenses.scala
   #9 = Utf8               Lscala/reflect/ScalaSignature;
  #10 = Utf8               bytes
  #11 = Utf8               \u0006\u0005}4q!\u0003\u0006\u0011\u0002G\u0005Q\u0002B\u0003\"\u0001\t\u0005!\u0005C\u0003*\u0001\u0019\u0005!fB\u0003<\u0015!\u0005AHB\u0003\n\u0015!\u0005Q\bC\u0003F\t\u0011\u0005a)\u0002\u0003H\t\u0001A\u0005\"B+\u0005\t\u00071\u0006bB<\u0005\u0003\u0003%I\u0001\u001f\u0002\u000f\u001b.tE\u000f\u001b$jK2$G*\u001a8t\u0015\u0005Y\u0011!C:iCB,G.Z:t\u0007\u0001)2AD\u00196\'\r\u0001q\"\u0006\t\u0003!Mi\u0011!\u0005\u0006\u0002%\u0005)1oY1mC&\u0011A#\u0005\u0002\u0007\u0003:L(+\u001a4\u0011\u0005YqbBA\f\u001d\u001d\tA2$D\u0001\u001a\u0015\tQB\"\u0001\u0004=e>|GOP\u0005\u0002%%\u0011Q$E\u0001\ba\u0006\u001c7.Y4f\u0013\ty\u0002E\u0001\u0007TKJL\u0017\r\\5{C\ndWM\u0003\u0002\u001e#\t!Q\t\\3n#\t\u0019c\u0005\u0005\u0002\u0011I%\u0011Q%\u0005\u0002\b\u001d>$\b.\u001b8h!\t\u0001r%\u0003\u0002)#\t\u0019\u0011I\\=\u0002\u000b\u0005\u0004\b\u000f\\=\u0015\u0003-\u0002B\u0001L\u00170g5\t!\"\u0003\u0002/\u0015\t!A*\u001a8t!\t\u0001\u0014\u0007\u0004\u0001\u0005\u000bI\u0002!\u0019\u0001\u0012\u0003\u0003\u0005\u0003\"\u0001N\u0001\u000e\u0003\u0001!QA\u000e\u0001C\u0002]\u0012\u0011AT\t\u0003Ga\u0002\"\u0001L\u001d\n\u0005iR!a\u0001(bi\u0006qQj\u001b(uQ\u001aKW\r\u001c3MK:\u001c\bC\u0001\u0017\u0005\'\r!qB\u0010\t\u0003\u007f\u0011k\u0011\u0001\u0011\u0006\u0003\u0003\n\u000b!![8\u000b\u0003\r\u000bAA[1wC&\u0011q\u0004Q\u0001\u0007y%t\u0017\u000e\u001e \u0015\u0003q\u00121!Q;y+\u0011Ie\nU*\u0013\u0005)ce\u0001B&\u0005\u0001%\u0013A\u0002\u0010:fM&tW-\\3oiz\u0002B\u0001\f\u0001N\u001fB\u0011\u0001G\u0014\u0003\u0006e\u0019\u0011\rA\t\t\u0003aA#QA\u000e\u0004C\u0002]*A!\t&!%B\u0011\u0001g\u0015\u0003\u0006)\u001a\u0011\rA\t\u0002\u0006\u000b2,W\u000eM\u0001\n[.<UM\u001c)Oi\",RaV.^MV$2\u0001W7a!\u0015IfA\u0017/_\u001b\u0005!\u0001C\u0001\u0019\\\t\u0015\u0011tA1\u0001#!\t\u0001T\fB\u00037\u000f\t\u0007q\u0007\u0005\u0002`Y:\u0011\u0001\u0007\u0019\u0005\u0006C\u001e\u0001\u001dAY\u0001\u0007[.dUM\\:\u0011\t1\u001aW\rX\u0005\u0003I*\u0011a\"T6I\u0019&\u001cHO\u0014;i\u0019\u0016t7\u000f\u0005\u00021M\u0012)qm\u0002b\u0001Q\n\t!+\u0005\u0002$SB\u0011AF[\u0005\u0003W*\u0011Q\u0001\u0013\'jgRL!!I2\t\u000b9<\u00019A8\u0002\u000b5\\w)\u001a8\u0011\tA\u001c(,\u001a\b\u0003YEL!A\u001d\u0006\u0002\u001b5[w)\u001a8fe&\u001cG*\u001a8t\u0013\t9EO\u0003\u0002s\u0015\u0011)ao\u0002b\u0001E\t\t!)\u0001\u0007xe&$XMU3qY\u0006\u001cW\rF\u0001z!\tQX0D\u0001|\u0015\ta()\u0001\u0003mC:<\u0017B\u0001@|\u0005\u0019y%M[3di\u0002
  #12 = Utf8               mkGenPNth
  #13 = Utf8               (Lshapeless/MkGenericLens;Lshapeless/MkHListNthLens;)Lshapeless/MkNthFieldLens;
  #14 = Utf8               <A:Ljava/lang/Object;N::Lshapeless/Nat;R::Lshapeless/HList;B:Ljava/lang/Object;>(Lshapeless/MkGenericLens<TA;>;Lshapeless/MkHListNthLens<TR;TN;>;)Lshapeless/MkNthFieldLens<TA;TN;>;
  #15 = Utf8               mkGen
  #16 = Utf8               mkLens
  #17 = Utf8               shapeless/MkNthFieldLens$
  #18 = Class              #17            // shapeless/MkNthFieldLens$
  #19 = Utf8               MODULE$
  #20 = Utf8               Lshapeless/MkNthFieldLens$;
  #21 = NameAndType        #19:#20        // MODULE$:Lshapeless/MkNthFieldLens$;
  #22 = Fieldref           #18.#21        // shapeless/MkNthFieldLens$.MODULE$:Lshapeless/MkNthFieldLens$;
  #23 = NameAndType        #12:#13        // mkGenPNth:(Lshapeless/MkGenericLens;Lshapeless/MkHListNthLens;)Lshapeless/MkNthFieldLens;
  #24 = Methodref          #18.#23        // shapeless/MkNthFieldLens$.mkGenPNth:(Lshapeless/MkGenericLens;Lshapeless/MkHListNthLens;)Lshapeless/MkNthFieldLens;
  #25 = Utf8               apply
  #26 = Utf8               ()Lshapeless/Lens;
  #27 = Utf8               ()Lshapeless/Lens<TA;Ljava/lang/Object;>;
  #28 = Utf8               Code
  #29 = Utf8               Signature
  #30 = Utf8               MethodParameters
  #31 = Utf8               SourceFile
  #32 = Utf8               RuntimeVisibleAnnotations
  #33 = Utf8               ScalaInlineInfo
  #34 = Utf8               ScalaSig
{
  public static <A extends java.lang.Object, N extends shapeless.Nat, R extends shapeless.HList, B extends java.lang.Object> shapeless.MkNthFieldLens<A, N> mkGenPNth(shapeless.MkGenericLens<A>, shapeless.MkHListNthLens<R, N>);
    descriptor: (Lshapeless/MkGenericLens;Lshapeless/MkHListNthLens;)Lshapeless/MkNthFieldLens;
    flags: (0x0009) ACC_PUBLIC, ACC_STATIC
    Code:
      stack=3, locals=2, args_size=2
         0: getstatic     #22                 // Field shapeless/MkNthFieldLens$.MODULE$:Lshapeless/MkNthFieldLens$;
         3: aload_0
         4: aload_1
         5: invokevirtual #24                 // Method shapeless/MkNthFieldLens$.mkGenPNth:(Lshapeless/MkGenericLens;Lshapeless/MkHListNthLens;)Lshapeless/MkNthFieldLens;
         8: areturn
    Signature: #14                          // <A:Ljava/lang/Object;N::Lshapeless/Nat;R::Lshapeless/HList;B:Ljava/lang/Object;>(Lshapeless/MkGenericLens<TA;>;Lshapeless/MkHListNthLens<TR;TN;>;)Lshapeless/MkNthFieldLens<TA;TN;>;
    MethodParameters:
      Name                           Flags
      mkGen                          final
      mkLens                         final

  public abstract shapeless.Lens<A, java.lang.Object> apply();
    descriptor: ()Lshapeless/Lens;
    flags: (0x0401) ACC_PUBLIC, ACC_ABSTRACT
    Signature: #27                          // ()Lshapeless/Lens<TA;Ljava/lang/Object;>;
}
Signature: #3                           // <A:Ljava/lang/Object;N::Lshapeless/Nat;>Ljava/lang/Object;Ljava/io/Serializable;
SourceFile: "lenses.scala"
RuntimeVisibleAnnotations:
  0: #9(#10=s#11)
    scala.reflect.ScalaSignature(
      bytes="\u0006\u0005}4q!\u0003\u0006\u0011\u0002G\u0005Q\u0002B\u0003\"\u0001\t\u0005!\u0005C\u0003*\u0001\u0019\u0005!fB\u0003<\u0015!\u0005AHB\u0003\n\u0015!\u0005Q\bC\u0003F\t\u0011\u0005a)\u0002\u0003H\t\u0001A\u0005\"B+\u0005\t\u00071\u0006bB<\u0005\u0003\u0003%I\u0001\u001f\u0002\u000f\u001b.tE\u000f\u001b$jK2$G*\u001a8t\u0015\u0005Y\u0011!C:iCB,G.Z:t\u0007\u0001)2AD\u00196\'\r\u0001q\"\u0006\t\u0003!Mi\u0011!\u0005\u0006\u0002%\u0005)1oY1mC&\u0011A#\u0005\u0002\u0007\u0003:L(+\u001a4\u0011\u0005YqbBA\f\u001d\u001d\tA2$D\u0001\u001a\u0015\tQB\"\u0001\u0004=e>|GOP\u0005\u0002%%\u0011Q$E\u0001\ba\u0006\u001c7.Y4f\u0013\ty\u0002E\u0001\u0007TKJL\u0017\r\\5{C\ndWM\u0003\u0002\u001e#\t!Q\t\\3n#\t\u0019c\u0005\u0005\u0002\u0011I%\u0011Q%\u0005\u0002\b\u001d>$\b.\u001b8h!\t\u0001r%\u0003\u0002)#\t\u0019\u0011I\\=\u0002\u000b\u0005\u0004\b\u000f\\=\u0015\u0003-\u0002B\u0001L\u00170g5\t!\"\u0003\u0002/\u0015\t!A*\u001a8t!\t\u0001\u0014\u0007\u0004\u0001\u0005\u000bI\u0002!\u0019\u0001\u0012\u0003\u0003\u0005\u0003\"\u0001N\u0001\u000e\u0003\u0001!QA\u000e\u0001C\u0002]\u0012\u0011AT\t\u0003Ga\u0002\"\u0001L\u001d\n\u0005iR!a\u0001(bi\u0006qQj\u001b(uQ\u001aKW\r\u001c3MK:\u001c\bC\u0001\u0017\u0005\'\r!qB\u0010\t\u0003\u007f\u0011k\u0011\u0001\u0011\u0006\u0003\u0003\n\u000b!![8\u000b\u0003\r\u000bAA[1wC&\u0011q\u0004Q\u0001\u0007y%t\u0017\u000e\u001e \u0015\u0003q\u00121!Q;y+\u0011Ie\nU*\u0013\u0005)ce\u0001B&\u0005\u0001%\u0013A\u0002\u0010:fM&tW-\\3oiz\u0002B\u0001\f\u0001N\u001fB\u0011\u0001G\u0014\u0003\u0006e\u0019\u0011\rA\t\t\u0003aA#QA\u000e\u0004C\u0002]*A!\t&!%B\u0011\u0001g\u0015\u0003\u0006)\u001a\u0011\rA\t\u0002\u0006\u000b2,W\u000eM\u0001\n[.<UM\u001c)Oi\",RaV.^MV$2\u0001W7a!\u0015IfA\u0017/_\u001b\u0005!\u0001C\u0001\u0019\\\t\u0015\u0011tA1\u0001#!\t\u0001T\fB\u00037\u000f\t\u0007q\u0007\u0005\u0002`Y:\u0011\u0001\u0007\u0019\u0005\u0006C\u001e\u0001\u001dAY\u0001\u0007[.dUM\\:\u0011\t1\u001aW\rX\u0005\u0003I*\u0011a\"T6I\u0019&\u001cHO\u0014;i\u0019\u0016t7\u000f\u0005\u00021M\u0012)qm\u0002b\u0001Q\n\t!+\u0005\u0002$SB\u0011AF[\u0005\u0003W*\u0011Q\u0001\u0013\'jgRL!!I2\t\u000b9<\u00019A8\u0002\u000b5\\w)\u001a8\u0011\tA\u001c(,\u001a\b\u0003YEL!A\u001d\u0006\u0002\u001b5[w)\u001a8fe&\u001cG*\u001a8t\u0013\t9EO\u0003\u0002s\u0015\u0011)ao\u0002b\u0001E\t\t!)\u0001\u0007xe&$XMU3qY\u0006\u001cW\rF\u0001z!\tQX0D\u0001|\u0015\ta()\u0001\u0003mC:<\u0017B\u0001@|\u0005\u0019y%M[3di\u0002"
    )
  ScalaInlineInfo: length = 0x9 (unknown attribute)
   01 00 00 01 00 19 00 1A 00
  ScalaSig: length = 0x3 (unknown attribute)
   05 02 00
