Classfile /Users/mw/Projects/slang-braindump/.jar/jar11/assemble/slang-braindump/assemble/content/shapeless/Nats.class
  Last modified May 29, 2022; size 14253 bytes
  SHA-256 checksum 5e8abcc684d470acfdfec2ebbf34f5ab85a0082b80e24d27a85bbb7f2d04f8a3
  Compiled from "nats.scala"
public interface shapeless.Nats
  minor version: 0
  major version: 52
  flags: (0x0601) ACC_PUBLIC, ACC_INTERFACE, ACC_ABSTRACT
  this_class: #2                          // shapeless/Nats
  super_class: #4                         // java/lang/Object
  interfaces: 0, fields: 0, methods: 45, attributes: 4
Constant pool:
    #1 = Utf8               shapeless/Nats
    #2 = Class              #1            // shapeless/Nats
    #3 = Utf8               java/lang/Object
    #4 = Class              #3            // java/lang/Object
    #5 = Utf8               nats.scala
    #6 = Utf8               Lscala/reflect/ScalaSignature;
    #7 = Utf8               bytes
    #8 = Utf8               \u0006\u0005\u0005\u001dda\u0002\u00180!\u0003\r\tA\r\u0005\u0006s\u0001!\tAO\u0003\u0005}\u0001\u0001q\bC\u0004G\u0001\t\u0007I\u0011A$\u0006\t)\u0003\u0001a\u0013\u0005\b\u0019\u0002\u0011\r\u0011\"\u0001N\u000b\u0011y\u0005\u0001\u0001)\t\u000fE\u0003!\u0019!C\u0001%\u0016!A\u000b\u0001\u0001V\u0011\u001d1\u0006A1A\u0005\u0002]+A!\u0017\u0001\u00015\"91\f\u0001b\u0001\n\u0003aV\u0001\u00020\u0001\u0001}Cq\u0001\u0019\u0001C\u0002\u0013\u0005\u0011-\u0002\u0003d\u0001\u0001!\u0007bB3\u0001\u0005\u0004%\tAZ\u0003\u0005Q\u0002\u0001\u0011\u000eC\u0004k\u0001\t\u0007I\u0011A6\u0006\t5\u0004\u0001A\u001c\u0005\b_\u0002\u0011\r\u0011\"\u0001q\u000b\u0011\u0011\b\u0001A:\t\u000fQ\u0004!\u0019!C\u0001k\u0016!q\u000f\u0001\u0001y\u0011\u001dI\bA1A\u0005\u0002i,A\u0001 \u0001\u0001{\"9a\u0010\u0001b\u0001\n\u0003yXABA\u0002\u0001\u0001\t)\u0001C\u0005\u0002\b\u0001\u0011\r\u0011\"\u0001\u0002\n\u00151\u0011Q\u0002\u0001\u0001\u0003\u001fA\u0011\"!\u0005\u0001\u0005\u0004%\t!a\u0005\u0006\r\u0005]\u0001\u0001AA\r\u0011%\tY\u0002\u0001b\u0001\n\u0003\ti\"\u0002\u0004\u0002\"\u0001\u0001\u00111\u0005\u0005\n\u0003K\u0001!\u0019!C\u0001\u0003O)a!a\u000b\u0001\u0001\u00055\u0002\"CA\u0018\u0001\t\u0007I\u0011AA\u0019\u000b\u0019\t)\u0004\u0001\u0001\u00028!I\u0011\u0011\b\u0001C\u0002\u0013\u0005\u00111H\u0003\u0007\u0003\u007f\u0001\u0001!!\u0011\t\u0013\u0005\r\u0003A1A\u0005\u0002\u0005\u0015SABA%\u0001\u0001\tY\u0005C\u0005\u0002N\u0001\u0011\r\u0011\"\u0001\u0002P\u00151\u00111\u000b\u0001\u0001\u0003+B\u0011\"a\u0016\u0001\u0005\u0004%\t!!\u0017\u0006\r\u0005u\u0003\u0001AA0\u0011%\t\t\u0007\u0001b\u0001\n\u0003\t\u0019G\u0001\u0003OCR\u001c(\"\u0001\u0019\u0002\u0013MD\u0017\r]3mKN\u001c8\u0001A\n\u0003\u0001M\u0002\"\u0001N\u001c\u000e\u0003UR\u0011AN\u0001\u0006g\u000e\fG.Y\u0005\u0003qU\u0012a!\u00118z%\u00164\u0017A\u0002\u0013j]&$H\u0005F\u0001<!\t!D(\u0003\u0002>k\t!QK\\5u\u0005\ty\u0016\u0007E\u0002A\u0003\u000ek\u0011aL\u0005\u0003\u0005>\u0012AaU;dGB\u0011\u0001\tR\u0005\u0003\u000b>\u0012!a\u0018\u0019\u0002\u0005}\u000bT#\u0001%\u0011\u0005%\u0013Q\"\u0001\u0001\u0003\u0005}\u0013\u0004c\u0001!B\u0011\u0006\u0011qLM\u000b\u0002\u001dB\u0011\u0011\n\u0002\u0002\u0003?N\u00022\u0001Q!O\u0003\ty6\'F\u0001T!\tIeA\u0001\u0002`iA\u0019\u0001)Q*\u0002\u0005}#T#\u0001-\u0011\u0005%C!AA06!\r\u0001\u0015\tW\u0001\u0003?V*\u0012!\u0018\t\u0003\u0013*\u0011!a\u0018\u001c\u0011\u0007\u0001\u000bU,\u0001\u0002`mU\t!\r\u0005\u0002J\u0019\t\u0011ql\u000e\t\u0004\u0001\u0006\u0013\u0017AA08+\u00059\u0007CA%\u000f\u0005\ty\u0006\bE\u0002A\u0003\u001e\f!a\u0018\u001d\u0016\u00031\u0004\"!\u0013\t\u0003\u0005}K\u0004c\u0001!BY\u0006\u0011q,O\u000b\u0002cB\u0011\u0011J\u0005\u0002\u0004?F\u0002\u0004c\u0001!Bc\u0006\u0019q,\r\u0019\u0016\u0003Y\u0004\"!\u0013\u000b\u0003\u0007}\u000b\u0014\u0007E\u0002A\u0003Z\f1aX\u00192+\u0005Y\bCA%\u0017\u0005\ry\u0016G\r\t\u0004\u0001\u0006[\u0018aA02eU\u0011\u0011\u0011\u0001\t\u0003\u0013b\u00111aX\u00194!\u0011\u0001\u0015)!\u0001\u0002\u0007}\u000b4\'\u0006\u0002\u0002\fA\u0011\u0011J\u0007\u0002\u0004?F\"\u0004\u0003\u0002!B\u0003\u0017\t1aX\u00195+\t\t)\u0002\u0005\u0002J9\t\u0019q,M\u001b\u0011\t\u0001\u000b\u0015QC\u0001\u0004?F*TCAA\u0010!\tIeDA\u0002`cY\u0002B\u0001Q!\u0002 \u0005\u0019q,\r\u001c\u0016\u0005\u0005%\u0002CA%!\u0005\ry\u0016g\u000e\t\u0005\u0001\u0006\u000bI#A\u0002`c]*\"!a\r\u0011\u0005%\u0013#aA02qA!\u0001)QA\u001a\u0003\ry\u0016\u0007O\u000b\u0003\u0003{\u0001\"!\u0013\u0013\u0003\u0007}\u000b\u0014\b\u0005\u0003A\u0003\u0006u\u0012aA02sU\u0011\u0011q\t\t\u0003\u0013\u001a\u00121a\u0018\u001a1!\u0011\u0001\u0015)a\u0012\u0002\u0007}\u0013\u0004\'\u0006\u0002\u0002RA\u0011\u0011\n\u000b\u0002\u0004?J\n\u0004\u0003\u0002!B\u0003#\n1a\u0018\u001a2+\t\tY\u0006\u0005\u0002JU\t\u0019qL\r\u001a\u0011\t\u0001\u000b\u00151L\u0001\u0004?J\u0012TCAA3!\tIE\u0006
    #9 = Utf8               shapeless$Nats$_setter_$_1_$eq
   #10 = Utf8               (Lshapeless/Succ;)V
   #11 = Utf8               (Lshapeless/Succ<Lshapeless/_0;>;)V
   #12 = Utf8               x$1
   #13 = Utf8               shapeless$Nats$_setter_$_2_$eq
   #14 = Utf8               (Lshapeless/Succ<Lshapeless/Succ<Lshapeless/_0;>;>;)V
   #15 = Utf8               shapeless$Nats$_setter_$_3_$eq
   #16 = Utf8               (Lshapeless/Succ<Lshapeless/Succ<Lshapeless/Succ<Lshapeless/_0;>;>;>;)V
   #17 = Utf8               shapeless$Nats$_setter_$_4_$eq
   #18 = Utf8               (Lshapeless/Succ<Lshapeless/Succ<Lshapeless/Succ<Lshapeless/Succ<Lshapeless/_0;>;>;>;>;)V
   #19 = Utf8               shapeless$Nats$_setter_$_5_$eq
   #20 = Utf8               (Lshapeless/Succ<Lshapeless/Succ<Lshapeless/Succ<Lshapeless/Succ<Lshapeless/Succ<Lshapeless/_0;>;>;>;>;>;)V
   #21 = Utf8               shapeless$Nats$_setter_$_6_$eq
   #22 = Utf8               (Lshapeless/Succ<Lshapeless/Succ<Lshapeless/Succ<Lshapeless/Succ<Lshapeless/Succ<Lshapeless/Succ<Lshapeless/_0;>;>;>;>;>;>;)V
   #23 = Utf8               shapeless$Nats$_setter_$_7_$eq
   #24 = Utf8               (Lshapeless/Succ<Lshapeless/Succ<Lshapeless/Succ<Lshapeless/Succ<Lshapeless/Succ<Lshapeless/Succ<Lshapeless/Succ<Lshapeless/_0;>;>;>;>;>;>;>;)V
   #25 = Utf8               shapeless$Nats$_setter_$_8_$eq
   #26 = Utf8               (Lshapeless/Succ<Lshapeless/Succ<Lshapeless/Succ<Lshapeless/Succ<Lshapeless/Succ<Lshapeless/Succ<Lshapeless/Succ<Lshapeless/Succ<Lshapeless/_0;>;>;>;>;>;>;>;>;)V
   #27 = Utf8               shapeless$Nats$_setter_$_9_$eq
   #28 = Utf8               (Lshapeless/Succ<Lshapeless/Succ<Lshapeless/Succ<Lshapeless/Succ<Lshapeless/Succ<Lshapeless/Succ<Lshapeless/Succ<Lshapeless/Succ<Lshapeless/Succ<Lshapeless/_0;>;>;>;>;>;>;>;>;>;)V
   #29 = Utf8               shapeless$Nats$_setter_$_10_$eq
   #30 = Utf8               (Lshapeless/Succ<Lshapeless/Succ<Lshapeless/Succ<Lshapeless/Succ<Lshapeless/Succ<Lshapeless/Succ<Lshapeless/Succ<Lshapeless/Succ<Lshapeless/Succ<Lshapeless/Succ<Lshapeless/_0;>;>;>;>;>;>;>;>;>;>;)V
   #31 = Utf8               shapeless$Nats$_setter_$_11_$eq
   #32 = Utf8               (Lshapeless/Succ<Lshapeless/Succ<Lshapeless/Succ<Lshapeless/Succ<Lshapeless/Succ<Lshapeless/Succ<Lshapeless/Succ<Lshapeless/Succ<Lshapeless/Succ<Lshapeless/Succ<Lshapeless/Succ<Lshapeless/_0;>;>;>;>;>;>;>;>;>;>;>;)V
   #33 = Utf8               shapeless$Nats$_setter_$_12_$eq
   #34 = Utf8               (Lshapeless/Succ<Lshapeless/Succ<Lshapeless/Succ<Lshapeless/Succ<Lshapeless/Succ<Lshapeless/Succ<Lshapeless/Succ<Lshapeless/Succ<Lshapeless/Succ<Lshapeless/Succ<Lshapeless/Succ<Lshapeless/Succ<Lshapeless/_0;>;>;>;>;>;>;>;>;>;>;>;>;)V
   #35 = Utf8               shapeless$Nats$_setter_$_13_$eq
   #36 = Utf8               (Lshapeless/Succ<Lshapeless/Succ<Lshapeless/Succ<Lshapeless/Succ<Lshapeless/Succ<Lshapeless/Succ<Lshapeless/Succ<Lshapeless/Succ<Lshapeless/Succ<Lshapeless/Succ<Lshapeless/Succ<Lshapeless/Succ<Lshapeless/Succ<Lshapeless/_0;>;>;>;>;>;>;>;>;>;>;>;>;>;)V
   #37 = Utf8               shapeless$Nats$_setter_$_14_$eq
   #38 = Utf8               (Lshapeless/Succ<Lshapeless/Succ<Lshapeless/Succ<Lshapeless/Succ<Lshapeless/Succ<Lshapeless/Succ<Lshapeless/Succ<Lshapeless/Succ<Lshapeless/Succ<Lshapeless/Succ<Lshapeless/Succ<Lshapeless/Succ<Lshapeless/Succ<Lshapeless/Succ<Lshapeless/_0;>;>;>;>;>;>;>;>;>;>;>;>;>;>;)V
   #39 = Utf8               shapeless$Nats$_setter_$_15_$eq
   #40 = Utf8               (Lshapeless/Succ<Lshapeless/Succ<Lshapeless/Succ<Lshapeless/Succ<Lshapeless/Succ<Lshapeless/Succ<Lshapeless/Succ<Lshapeless/Succ<Lshapeless/Succ<Lshapeless/Succ<Lshapeless/Succ<Lshapeless/Succ<Lshapeless/Succ<Lshapeless/Succ<Lshapeless/Succ<Lshapeless/_0;>;>;>;>;>;>;>;>;>;>;>;>;>;>;>;)V
   #41 = Utf8               shapeless$Nats$_setter_$_16_$eq
   #42 = Utf8               (Lshapeless/Succ<Lshapeless/Succ<Lshapeless/Succ<Lshapeless/Succ<Lshapeless/Succ<Lshapeless/Succ<Lshapeless/Succ<Lshapeless/Succ<Lshapeless/Succ<Lshapeless/Succ<Lshapeless/Succ<Lshapeless/Succ<Lshapeless/Succ<Lshapeless/Succ<Lshapeless/Succ<Lshapeless/Succ<Lshapeless/_0;>;>;>;>;>;>;>;>;>;>;>;>;>;>;>;>;)V
   #43 = Utf8               shapeless$Nats$_setter_$_17_$eq
   #44 = Utf8               (Lshapeless/Succ<Lshapeless/Succ<Lshapeless/Succ<Lshapeless/Succ<Lshapeless/Succ<Lshapeless/Succ<Lshapeless/Succ<Lshapeless/Succ<Lshapeless/Succ<Lshapeless/Succ<Lshapeless/Succ<Lshapeless/Succ<Lshapeless/Succ<Lshapeless/Succ<Lshapeless/Succ<Lshapeless/Succ<Lshapeless/Succ<Lshapeless/_0;>;>;>;>;>;>;>;>;>;>;>;>;>;>;>;>;>;)V
   #45 = Utf8               shapeless$Nats$_setter_$_18_$eq
   #46 = Utf8               (Lshapeless/Succ<Lshapeless/Succ<Lshapeless/Succ<Lshapeless/Succ<Lshapeless/Succ<Lshapeless/Succ<Lshapeless/Succ<Lshapeless/Succ<Lshapeless/Succ<Lshapeless/Succ<Lshapeless/Succ<Lshapeless/Succ<Lshapeless/Succ<Lshapeless/Succ<Lshapeless/Succ<Lshapeless/Succ<Lshapeless/Succ<Lshapeless/Succ<Lshapeless/_0;>;>;>;>;>;>;>;>;>;>;>;>;>;>;>;>;>;>;)V
   #47 = Utf8               shapeless$Nats$_setter_$_19_$eq
   #48 = Utf8               (Lshapeless/Succ<Lshapeless/Succ<Lshapeless/Succ<Lshapeless/Succ<Lshapeless/Succ<Lshapeless/Succ<Lshapeless/Succ<Lshapeless/Succ<Lshapeless/Succ<Lshapeless/Succ<Lshapeless/Succ<Lshapeless/Succ<Lshapeless/Succ<Lshapeless/Succ<Lshapeless/Succ<Lshapeless/Succ<Lshapeless/Succ<Lshapeless/Succ<Lshapeless/Succ<Lshapeless/_0;>;>;>;>;>;>;>;>;>;>;>;>;>;>;>;>;>;>;>;)V
   #49 = Utf8               shapeless$Nats$_setter_$_20_$eq
   #50 = Utf8               (Lshapeless/Succ<Lshapeless/Succ<Lshapeless/Succ<Lshapeless/Succ<Lshapeless/Succ<Lshapeless/Succ<Lshapeless/Succ<Lshapeless/Succ<Lshapeless/Succ<Lshapeless/Succ<Lshapeless/Succ<Lshapeless/Succ<Lshapeless/Succ<Lshapeless/Succ<Lshapeless/Succ<Lshapeless/Succ<Lshapeless/Succ<Lshapeless/Succ<Lshapeless/Succ<Lshapeless/Succ<Lshapeless/_0;>;>;>;>;>;>;>;>;>;>;>;>;>;>;>;>;>;>;>;>;)V
   #51 = Utf8               shapeless$Nats$_setter_$_21_$eq
   #52 = Utf8               (Lshapeless/Succ<Lshapeless/Succ<Lshapeless/Succ<Lshapeless/Succ<Lshapeless/Succ<Lshapeless/Succ<Lshapeless/Succ<Lshapeless/Succ<Lshapeless/Succ<Lshapeless/Succ<Lshapeless/Succ<Lshapeless/Succ<Lshapeless/Succ<Lshapeless/Succ<Lshapeless/Succ<Lshapeless/Succ<Lshapeless/Succ<Lshapeless/Succ<Lshapeless/Succ<Lshapeless/Succ<Lshapeless/Succ<Lshapeless/_0;>;>;>;>;>;>;>;>;>;>;>;>;>;>;>;>;>;>;>;>;>;)V
   #53 = Utf8               shapeless$Nats$_setter_$_22_$eq
   #54 = Utf8               (Lshapeless/Succ<Lshapeless/Succ<Lshapeless/Succ<Lshapeless/Succ<Lshapeless/Succ<Lshapeless/Succ<Lshapeless/Succ<Lshapeless/Succ<Lshapeless/Succ<Lshapeless/Succ<Lshapeless/Succ<Lshapeless/Succ<Lshapeless/Succ<Lshapeless/Succ<Lshapeless/Succ<Lshapeless/Succ<Lshapeless/Succ<Lshapeless/Succ<Lshapeless/Succ<Lshapeless/Succ<Lshapeless/Succ<Lshapeless/Succ<Lshapeless/_0;>;>;>;>;>;>;>;>;>;>;>;>;>;>;>;>;>;>;>;>;>;>;)V
   #55 = Utf8               _1
   #56 = Utf8               ()Lshapeless/Succ;
   #57 = Utf8               ()Lshapeless/Succ<Lshapeless/_0;>;
   #58 = Utf8               _2
   #59 = Utf8               ()Lshapeless/Succ<Lshapeless/Succ<Lshapeless/_0;>;>;
   #60 = Utf8               _3
   #61 = Utf8               ()Lshapeless/Succ<Lshapeless/Succ<Lshapeless/Succ<Lshapeless/_0;>;>;>;
   #62 = Utf8               _4
   #63 = Utf8               ()Lshapeless/Succ<Lshapeless/Succ<Lshapeless/Succ<Lshapeless/Succ<Lshapeless/_0;>;>;>;>;
   #64 = Utf8               _5
   #65 = Utf8               ()Lshapeless/Succ<Lshapeless/Succ<Lshapeless/Succ<Lshapeless/Succ<Lshapeless/Succ<Lshapeless/_0;>;>;>;>;>;
   #66 = Utf8               _6
   #67 = Utf8               ()Lshapeless/Succ<Lshapeless/Succ<Lshapeless/Succ<Lshapeless/Succ<Lshapeless/Succ<Lshapeless/Succ<Lshapeless/_0;>;>;>;>;>;>;
   #68 = Utf8               _7
   #69 = Utf8               ()Lshapeless/Succ<Lshapeless/Succ<Lshapeless/Succ<Lshapeless/Succ<Lshapeless/Succ<Lshapeless/Succ<Lshapeless/Succ<Lshapeless/_0;>;>;>;>;>;>;>;
   #70 = Utf8               _8
   #71 = Utf8               ()Lshapeless/Succ<Lshapeless/Succ<Lshapeless/Succ<Lshapeless/Succ<Lshapeless/Succ<Lshapeless/Succ<Lshapeless/Succ<Lshapeless/Succ<Lshapeless/_0;>;>;>;>;>;>;>;>;
   #72 = Utf8               _9
   #73 = Utf8               ()Lshapeless/Succ<Lshapeless/Succ<Lshapeless/Succ<Lshapeless/Succ<Lshapeless/Succ<Lshapeless/Succ<Lshapeless/Succ<Lshapeless/Succ<Lshapeless/Succ<Lshapeless/_0;>;>;>;>;>;>;>;>;>;
   #74 = Utf8               _10
   #75 = Utf8               ()Lshapeless/Succ<Lshapeless/Succ<Lshapeless/Succ<Lshapeless/Succ<Lshapeless/Succ<Lshapeless/Succ<Lshapeless/Succ<Lshapeless/Succ<Lshapeless/Succ<Lshapeless/Succ<Lshapeless/_0;>;>;>;>;>;>;>;>;>;>;
   #76 = Utf8               _11
   #77 = Utf8               ()Lshapeless/Succ<Lshapeless/Succ<Lshapeless/Succ<Lshapeless/Succ<Lshapeless/Succ<Lshapeless/Succ<Lshapeless/Succ<Lshapeless/Succ<Lshapeless/Succ<Lshapeless/Succ<Lshapeless/Succ<Lshapeless/_0;>;>;>;>;>;>;>;>;>;>;>;
   #78 = Utf8               _12
   #79 = Utf8               ()Lshapeless/Succ<Lshapeless/Succ<Lshapeless/Succ<Lshapeless/Succ<Lshapeless/Succ<Lshapeless/Succ<Lshapeless/Succ<Lshapeless/Succ<Lshapeless/Succ<Lshapeless/Succ<Lshapeless/Succ<Lshapeless/Succ<Lshapeless/_0;>;>;>;>;>;>;>;>;>;>;>;>;
   #80 = Utf8               _13
   #81 = Utf8               ()Lshapeless/Succ<Lshapeless/Succ<Lshapeless/Succ<Lshapeless/Succ<Lshapeless/Succ<Lshapeless/Succ<Lshapeless/Succ<Lshapeless/Succ<Lshapeless/Succ<Lshapeless/Succ<Lshapeless/Succ<Lshapeless/Succ<Lshapeless/Succ<Lshapeless/_0;>;>;>;>;>;>;>;>;>;>;>;>;>;
   #82 = Utf8               _14
   #83 = Utf8               ()Lshapeless/Succ<Lshapeless/Succ<Lshapeless/Succ<Lshapeless/Succ<Lshapeless/Succ<Lshapeless/Succ<Lshapeless/Succ<Lshapeless/Succ<Lshapeless/Succ<Lshapeless/Succ<Lshapeless/Succ<Lshapeless/Succ<Lshapeless/Succ<Lshapeless/Succ<Lshapeless/_0;>;>;>;>;>;>;>;>;>;>;>;>;>;>;
   #84 = Utf8               _15
   #85 = Utf8               ()Lshapeless/Succ<Lshapeless/Succ<Lshapeless/Succ<Lshapeless/Succ<Lshapeless/Succ<Lshapeless/Succ<Lshapeless/Succ<Lshapeless/Succ<Lshapeless/Succ<Lshapeless/Succ<Lshapeless/Succ<Lshapeless/Succ<Lshapeless/Succ<Lshapeless/Succ<Lshapeless/Succ<Lshapeless/_0;>;>;>;>;>;>;>;>;>;>;>;>;>;>;>;
   #86 = Utf8               _16
   #87 = Utf8               ()Lshapeless/Succ<Lshapeless/Succ<Lshapeless/Succ<Lshapeless/Succ<Lshapeless/Succ<Lshapeless/Succ<Lshapeless/Succ<Lshapeless/Succ<Lshapeless/Succ<Lshapeless/Succ<Lshapeless/Succ<Lshapeless/Succ<Lshapeless/Succ<Lshapeless/Succ<Lshapeless/Succ<Lshapeless/Succ<Lshapeless/_0;>;>;>;>;>;>;>;>;>;>;>;>;>;>;>;>;
   #88 = Utf8               _17
   #89 = Utf8               ()Lshapeless/Succ<Lshapeless/Succ<Lshapeless/Succ<Lshapeless/Succ<Lshapeless/Succ<Lshapeless/Succ<Lshapeless/Succ<Lshapeless/Succ<Lshapeless/Succ<Lshapeless/Succ<Lshapeless/Succ<Lshapeless/Succ<Lshapeless/Succ<Lshapeless/Succ<Lshapeless/Succ<Lshapeless/Succ<Lshapeless/Succ<Lshapeless/_0;>;>;>;>;>;>;>;>;>;>;>;>;>;>;>;>;>;
   #90 = Utf8               _18
   #91 = Utf8               ()Lshapeless/Succ<Lshapeless/Succ<Lshapeless/Succ<Lshapeless/Succ<Lshapeless/Succ<Lshapeless/Succ<Lshapeless/Succ<Lshapeless/Succ<Lshapeless/Succ<Lshapeless/Succ<Lshapeless/Succ<Lshapeless/Succ<Lshapeless/Succ<Lshapeless/Succ<Lshapeless/Succ<Lshapeless/Succ<Lshapeless/Succ<Lshapeless/Succ<Lshapeless/_0;>;>;>;>;>;>;>;>;>;>;>;>;>;>;>;>;>;>;
   #92 = Utf8               _19
   #93 = Utf8               ()Lshapeless/Succ<Lshapeless/Succ<Lshapeless/Succ<Lshapeless/Succ<Lshapeless/Succ<Lshapeless/Succ<Lshapeless/Succ<Lshapeless/Succ<Lshapeless/Succ<Lshapeless/Succ<Lshapeless/Succ<Lshapeless/Succ<Lshapeless/Succ<Lshapeless/Succ<Lshapeless/Succ<Lshapeless/Succ<Lshapeless/Succ<Lshapeless/Succ<Lshapeless/Succ<Lshapeless/_0;>;>;>;>;>;>;>;>;>;>;>;>;>;>;>;>;>;>;>;
   #94 = Utf8               _20
   #95 = Utf8               ()Lshapeless/Succ<Lshapeless/Succ<Lshapeless/Succ<Lshapeless/Succ<Lshapeless/Succ<Lshapeless/Succ<Lshapeless/Succ<Lshapeless/Succ<Lshapeless/Succ<Lshapeless/Succ<Lshapeless/Succ<Lshapeless/Succ<Lshapeless/Succ<Lshapeless/Succ<Lshapeless/Succ<Lshapeless/Succ<Lshapeless/Succ<Lshapeless/Succ<Lshapeless/Succ<Lshapeless/Succ<Lshapeless/_0;>;>;>;>;>;>;>;>;>;>;>;>;>;>;>;>;>;>;>;>;
   #96 = Utf8               _21
   #97 = Utf8               ()Lshapeless/Succ<Lshapeless/Succ<Lshapeless/Succ<Lshapeless/Succ<Lshapeless/Succ<Lshapeless/Succ<Lshapeless/Succ<Lshapeless/Succ<Lshapeless/Succ<Lshapeless/Succ<Lshapeless/Succ<Lshapeless/Succ<Lshapeless/Succ<Lshapeless/Succ<Lshapeless/Succ<Lshapeless/Succ<Lshapeless/Succ<Lshapeless/Succ<Lshapeless/Succ<Lshapeless/Succ<Lshapeless/Succ<Lshapeless/_0;>;>;>;>;>;>;>;>;>;>;>;>;>;>;>;>;>;>;>;>;>;
   #98 = Utf8               _22
   #99 = Utf8               ()Lshapeless/Succ<Lshapeless/Succ<Lshapeless/Succ<Lshapeless/Succ<Lshapeless/Succ<Lshapeless/Succ<Lshapeless/Succ<Lshapeless/Succ<Lshapeless/Succ<Lshapeless/Succ<Lshapeless/Succ<Lshapeless/Succ<Lshapeless/Succ<Lshapeless/Succ<Lshapeless/Succ<Lshapeless/Succ<Lshapeless/Succ<Lshapeless/Succ<Lshapeless/Succ<Lshapeless/Succ<Lshapeless/Succ<Lshapeless/Succ<Lshapeless/_0;>;>;>;>;>;>;>;>;>;>;>;>;>;>;>;>;>;>;>;>;>;>;
  #100 = Utf8               $init$
  #101 = Utf8               (Lshapeless/Nats;)V
  #102 = Utf8               $this
  #103 = Utf8               shapeless/Succ
  #104 = Class              #103          // shapeless/Succ
  #105 = Utf8               <init>
  #106 = Utf8               ()V
  #107 = NameAndType        #105:#106     // "<init>":()V
  #108 = Methodref          #104.#107     // shapeless/Succ."<init>":()V
  #109 = NameAndType        #9:#10        // shapeless$Nats$_setter_$_1_$eq:(Lshapeless/Succ;)V
  #110 = InterfaceMethodref #2.#109       // shapeless/Nats.shapeless$Nats$_setter_$_1_$eq:(Lshapeless/Succ;)V
  #111 = NameAndType        #13:#10       // shapeless$Nats$_setter_$_2_$eq:(Lshapeless/Succ;)V
  #112 = InterfaceMethodref #2.#111       // shapeless/Nats.shapeless$Nats$_setter_$_2_$eq:(Lshapeless/Succ;)V
  #113 = NameAndType        #15:#10       // shapeless$Nats$_setter_$_3_$eq:(Lshapeless/Succ;)V
  #114 = InterfaceMethodref #2.#113       // shapeless/Nats.shapeless$Nats$_setter_$_3_$eq:(Lshapeless/Succ;)V
  #115 = NameAndType        #17:#10       // shapeless$Nats$_setter_$_4_$eq:(Lshapeless/Succ;)V
  #116 = InterfaceMethodref #2.#115       // shapeless/Nats.shapeless$Nats$_setter_$_4_$eq:(Lshapeless/Succ;)V
  #117 = NameAndType        #19:#10       // shapeless$Nats$_setter_$_5_$eq:(Lshapeless/Succ;)V
  #118 = InterfaceMethodref #2.#117       // shapeless/Nats.shapeless$Nats$_setter_$_5_$eq:(Lshapeless/Succ;)V
  #119 = NameAndType        #21:#10       // shapeless$Nats$_setter_$_6_$eq:(Lshapeless/Succ;)V
  #120 = InterfaceMethodref #2.#119       // shapeless/Nats.shapeless$Nats$_setter_$_6_$eq:(Lshapeless/Succ;)V
  #121 = NameAndType        #23:#10       // shapeless$Nats$_setter_$_7_$eq:(Lshapeless/Succ;)V
  #122 = InterfaceMethodref #2.#121       // shapeless/Nats.shapeless$Nats$_setter_$_7_$eq:(Lshapeless/Succ;)V
  #123 = NameAndType        #25:#10       // shapeless$Nats$_setter_$_8_$eq:(Lshapeless/Succ;)V
  #124 = InterfaceMethodref #2.#123       // shapeless/Nats.shapeless$Nats$_setter_$_8_$eq:(Lshapeless/Succ;)V
  #125 = NameAndType        #27:#10       // shapeless$Nats$_setter_$_9_$eq:(Lshapeless/Succ;)V
  #126 = InterfaceMethodref #2.#125       // shapeless/Nats.shapeless$Nats$_setter_$_9_$eq:(Lshapeless/Succ;)V
  #127 = NameAndType        #29:#10       // shapeless$Nats$_setter_$_10_$eq:(Lshapeless/Succ;)V
  #128 = InterfaceMethodref #2.#127       // shapeless/Nats.shapeless$Nats$_setter_$_10_$eq:(Lshapeless/Succ;)V
  #129 = NameAndType        #31:#10       // shapeless$Nats$_setter_$_11_$eq:(Lshapeless/Succ;)V
  #130 = InterfaceMethodref #2.#129       // shapeless/Nats.shapeless$Nats$_setter_$_11_$eq:(Lshapeless/Succ;)V
  #131 = NameAndType        #33:#10       // shapeless$Nats$_setter_$_12_$eq:(Lshapeless/Succ;)V
  #132 = InterfaceMethodref #2.#131       // shapeless/Nats.shapeless$Nats$_setter_$_12_$eq:(Lshapeless/Succ;)V
  #133 = NameAndType        #35:#10       // shapeless$Nats$_setter_$_13_$eq:(Lshapeless/Succ;)V
  #134 = InterfaceMethodref #2.#133       // shapeless/Nats.shapeless$Nats$_setter_$_13_$eq:(Lshapeless/Succ;)V
  #135 = NameAndType        #37:#10       // shapeless$Nats$_setter_$_14_$eq:(Lshapeless/Succ;)V
  #136 = InterfaceMethodref #2.#135       // shapeless/Nats.shapeless$Nats$_setter_$_14_$eq:(Lshapeless/Succ;)V
  #137 = NameAndType        #39:#10       // shapeless$Nats$_setter_$_15_$eq:(Lshapeless/Succ;)V
  #138 = InterfaceMethodref #2.#137       // shapeless/Nats.shapeless$Nats$_setter_$_15_$eq:(Lshapeless/Succ;)V
  #139 = NameAndType        #41:#10       // shapeless$Nats$_setter_$_16_$eq:(Lshapeless/Succ;)V
  #140 = InterfaceMethodref #2.#139       // shapeless/Nats.shapeless$Nats$_setter_$_16_$eq:(Lshapeless/Succ;)V
  #141 = NameAndType        #43:#10       // shapeless$Nats$_setter_$_17_$eq:(Lshapeless/Succ;)V
  #142 = InterfaceMethodref #2.#141       // shapeless/Nats.shapeless$Nats$_setter_$_17_$eq:(Lshapeless/Succ;)V
  #143 = NameAndType        #45:#10       // shapeless$Nats$_setter_$_18_$eq:(Lshapeless/Succ;)V
  #144 = InterfaceMethodref #2.#143       // shapeless/Nats.shapeless$Nats$_setter_$_18_$eq:(Lshapeless/Succ;)V
  #145 = NameAndType        #47:#10       // shapeless$Nats$_setter_$_19_$eq:(Lshapeless/Succ;)V
  #146 = InterfaceMethodref #2.#145       // shapeless/Nats.shapeless$Nats$_setter_$_19_$eq:(Lshapeless/Succ;)V
  #147 = NameAndType        #49:#10       // shapeless$Nats$_setter_$_20_$eq:(Lshapeless/Succ;)V
  #148 = InterfaceMethodref #2.#147       // shapeless/Nats.shapeless$Nats$_setter_$_20_$eq:(Lshapeless/Succ;)V
  #149 = NameAndType        #51:#10       // shapeless$Nats$_setter_$_21_$eq:(Lshapeless/Succ;)V
  #150 = InterfaceMethodref #2.#149       // shapeless/Nats.shapeless$Nats$_setter_$_21_$eq:(Lshapeless/Succ;)V
  #151 = NameAndType        #53:#10       // shapeless$Nats$_setter_$_22_$eq:(Lshapeless/Succ;)V
  #152 = InterfaceMethodref #2.#151       // shapeless/Nats.shapeless$Nats$_setter_$_22_$eq:(Lshapeless/Succ;)V
  #153 = Utf8               Lshapeless/Nats;
  #154 = Utf8               Signature
  #155 = Utf8               MethodParameters
  #156 = Utf8               Code
  #157 = Utf8               LineNumberTable
  #158 = Utf8               LocalVariableTable
  #159 = Utf8               SourceFile
  #160 = Utf8               RuntimeVisibleAnnotations
  #161 = Utf8               ScalaInlineInfo
  #162 = Utf8               ScalaSig
{
  public abstract void shapeless$Nats$_setter_$_1_$eq(shapeless.Succ<shapeless._0>);
    descriptor: (Lshapeless/Succ;)V
    flags: (0x0401) ACC_PUBLIC, ACC_ABSTRACT
    Signature: #11                          // (Lshapeless/Succ<Lshapeless/_0;>;)V
    MethodParameters:
      Name                           Flags
      x$1                            final

  public abstract void shapeless$Nats$_setter_$_2_$eq(shapeless.Succ<shapeless.Succ<shapeless._0>>);
    descriptor: (Lshapeless/Succ;)V
    flags: (0x0401) ACC_PUBLIC, ACC_ABSTRACT
    Signature: #14                          // (Lshapeless/Succ<Lshapeless/Succ<Lshapeless/_0;>;>;)V
    MethodParameters:
      Name                           Flags
      x$1                            final

  public abstract void shapeless$Nats$_setter_$_3_$eq(shapeless.Succ<shapeless.Succ<shapeless.Succ<shapeless._0>>>);
    descriptor: (Lshapeless/Succ;)V
    flags: (0x0401) ACC_PUBLIC, ACC_ABSTRACT
    Signature: #16                          // (Lshapeless/Succ<Lshapeless/Succ<Lshapeless/Succ<Lshapeless/_0;>;>;>;)V
    MethodParameters:
      Name                           Flags
      x$1                            final

  public abstract void shapeless$Nats$_setter_$_4_$eq(shapeless.Succ<shapeless.Succ<shapeless.Succ<shapeless.Succ<shapeless._0>>>>);
    descriptor: (Lshapeless/Succ;)V
    flags: (0x0401) ACC_PUBLIC, ACC_ABSTRACT
    Signature: #18                          // (Lshapeless/Succ<Lshapeless/Succ<Lshapeless/Succ<Lshapeless/Succ<Lshapeless/_0;>;>;>;>;)V
    MethodParameters:
      Name                           Flags
      x$1                            final

  public abstract void shapeless$Nats$_setter_$_5_$eq(shapeless.Succ<shapeless.Succ<shapeless.Succ<shapeless.Succ<shapeless.Succ<shapeless._0>>>>>);
    descriptor: (Lshapeless/Succ;)V
    flags: (0x0401) ACC_PUBLIC, ACC_ABSTRACT
    Signature: #20                          // (Lshapeless/Succ<Lshapeless/Succ<Lshapeless/Succ<Lshapeless/Succ<Lshapeless/Succ<Lshapeless/_0;>;>;>;>;>;)V
    MethodParameters:
      Name                           Flags
      x$1                            final

  public abstract void shapeless$Nats$_setter_$_6_$eq(shapeless.Succ<shapeless.Succ<shapeless.Succ<shapeless.Succ<shapeless.Succ<shapeless.Succ<shapeless._0>>>>>>);
    descriptor: (Lshapeless/Succ;)V
    flags: (0x0401) ACC_PUBLIC, ACC_ABSTRACT
    Signature: #22                          // (Lshapeless/Succ<Lshapeless/Succ<Lshapeless/Succ<Lshapeless/Succ<Lshapeless/Succ<Lshapeless/Succ<Lshapeless/_0;>;>;>;>;>;>;)V
    MethodParameters:
      Name                           Flags
      x$1                            final

  public abstract void shapeless$Nats$_setter_$_7_$eq(shapeless.Succ<shapeless.Succ<shapeless.Succ<shapeless.Succ<shapeless.Succ<shapeless.Succ<shapeless.Succ<shapeless._0>>>>>>>);
    descriptor: (Lshapeless/Succ;)V
    flags: (0x0401) ACC_PUBLIC, ACC_ABSTRACT
    Signature: #24                          // (Lshapeless/Succ<Lshapeless/Succ<Lshapeless/Succ<Lshapeless/Succ<Lshapeless/Succ<Lshapeless/Succ<Lshapeless/Succ<Lshapeless/_0;>;>;>;>;>;>;>;)V
    MethodParameters:
      Name                           Flags
      x$1                            final

  public abstract void shapeless$Nats$_setter_$_8_$eq(shapeless.Succ<shapeless.Succ<shapeless.Succ<shapeless.Succ<shapeless.Succ<shapeless.Succ<shapeless.Succ<shapeless.Succ<shapeless._0>>>>>>>>);
    descriptor: (Lshapeless/Succ;)V
    flags: (0x0401) ACC_PUBLIC, ACC_ABSTRACT
    Signature: #26                          // (Lshapeless/Succ<Lshapeless/Succ<Lshapeless/Succ<Lshapeless/Succ<Lshapeless/Succ<Lshapeless/Succ<Lshapeless/Succ<Lshapeless/Succ<Lshapeless/_0;>;>;>;>;>;>;>;>;)V
    MethodParameters:
      Name                           Flags
      x$1                            final

  public abstract void shapeless$Nats$_setter_$_9_$eq(shapeless.Succ<shapeless.Succ<shapeless.Succ<shapeless.Succ<shapeless.Succ<shapeless.Succ<shapeless.Succ<shapeless.Succ<shapeless.Succ<shapeless._0>>>>>>>>>);
    descriptor: (Lshapeless/Succ;)V
    flags: (0x0401) ACC_PUBLIC, ACC_ABSTRACT
    Signature: #28                          // (Lshapeless/Succ<Lshapeless/Succ<Lshapeless/Succ<Lshapeless/Succ<Lshapeless/Succ<Lshapeless/Succ<Lshapeless/Succ<Lshapeless/Succ<Lshapeless/Succ<Lshapeless/_0;>;>;>;>;>;>;>;>;>;)V
    MethodParameters:
      Name                           Flags
      x$1                            final

  public abstract void shapeless$Nats$_setter_$_10_$eq(shapeless.Succ<shapeless.Succ<shapeless.Succ<shapeless.Succ<shapeless.Succ<shapeless.Succ<shapeless.Succ<shapeless.Succ<shapeless.Succ<shapeless.Succ<shapeless._0>>>>>>>>>>);
    descriptor: (Lshapeless/Succ;)V
    flags: (0x0401) ACC_PUBLIC, ACC_ABSTRACT
    Signature: #30                          // (Lshapeless/Succ<Lshapeless/Succ<Lshapeless/Succ<Lshapeless/Succ<Lshapeless/Succ<Lshapeless/Succ<Lshapeless/Succ<Lshapeless/Succ<Lshapeless/Succ<Lshapeless/Succ<Lshapeless/_0;>;>;>;>;>;>;>;>;>;>;)V
    MethodParameters:
      Name                           Flags
      x$1                            final

  public abstract void shapeless$Nats$_setter_$_11_$eq(shapeless.Succ<shapeless.Succ<shapeless.Succ<shapeless.Succ<shapeless.Succ<shapeless.Succ<shapeless.Succ<shapeless.Succ<shapeless.Succ<shapeless.Succ<shapeless.Succ<shapeless._0>>>>>>>>>>>);
    descriptor: (Lshapeless/Succ;)V
    flags: (0x0401) ACC_PUBLIC, ACC_ABSTRACT
    Signature: #32                          // (Lshapeless/Succ<Lshapeless/Succ<Lshapeless/Succ<Lshapeless/Succ<Lshapeless/Succ<Lshapeless/Succ<Lshapeless/Succ<Lshapeless/Succ<Lshapeless/Succ<Lshapeless/Succ<Lshapeless/Succ<Lshapeless/_0;>;>;>;>;>;>;>;>;>;>;>;)V
    MethodParameters:
      Name                           Flags
      x$1                            final

  public abstract void shapeless$Nats$_setter_$_12_$eq(shapeless.Succ<shapeless.Succ<shapeless.Succ<shapeless.Succ<shapeless.Succ<shapeless.Succ<shapeless.Succ<shapeless.Succ<shapeless.Succ<shapeless.Succ<shapeless.Succ<shapeless.Succ<shapeless._0>>>>>>>>>>>>);
    descriptor: (Lshapeless/Succ;)V
    flags: (0x0401) ACC_PUBLIC, ACC_ABSTRACT
    Signature: #34                          // (Lshapeless/Succ<Lshapeless/Succ<Lshapeless/Succ<Lshapeless/Succ<Lshapeless/Succ<Lshapeless/Succ<Lshapeless/Succ<Lshapeless/Succ<Lshapeless/Succ<Lshapeless/Succ<Lshapeless/Succ<Lshapeless/Succ<Lshapeless/_0;>;>;>;>;>;>;>;>;>;>;>;>;)V
    MethodParameters:
      Name                           Flags
      x$1                            final

  public abstract void shapeless$Nats$_setter_$_13_$eq(shapeless.Succ<shapeless.Succ<shapeless.Succ<shapeless.Succ<shapeless.Succ<shapeless.Succ<shapeless.Succ<shapeless.Succ<shapeless.Succ<shapeless.Succ<shapeless.Succ<shapeless.Succ<shapeless.Succ<shapeless._0>>>>>>>>>>>>>);
    descriptor: (Lshapeless/Succ;)V
    flags: (0x0401) ACC_PUBLIC, ACC_ABSTRACT
    Signature: #36                          // (Lshapeless/Succ<Lshapeless/Succ<Lshapeless/Succ<Lshapeless/Succ<Lshapeless/Succ<Lshapeless/Succ<Lshapeless/Succ<Lshapeless/Succ<Lshapeless/Succ<Lshapeless/Succ<Lshapeless/Succ<Lshapeless/Succ<Lshapeless/Succ<Lshapeless/_0;>;>;>;>;>;>;>;>;>;>;>;>;>;)V
    MethodParameters:
      Name                           Flags
      x$1                            final

  public abstract void shapeless$Nats$_setter_$_14_$eq(shapeless.Succ<shapeless.Succ<shapeless.Succ<shapeless.Succ<shapeless.Succ<shapeless.Succ<shapeless.Succ<shapeless.Succ<shapeless.Succ<shapeless.Succ<shapeless.Succ<shapeless.Succ<shapeless.Succ<shapeless.Succ<shapeless._0>>>>>>>>>>>>>>);
    descriptor: (Lshapeless/Succ;)V
    flags: (0x0401) ACC_PUBLIC, ACC_ABSTRACT
    Signature: #38                          // (Lshapeless/Succ<Lshapeless/Succ<Lshapeless/Succ<Lshapeless/Succ<Lshapeless/Succ<Lshapeless/Succ<Lshapeless/Succ<Lshapeless/Succ<Lshapeless/Succ<Lshapeless/Succ<Lshapeless/Succ<Lshapeless/Succ<Lshapeless/Succ<Lshapeless/Succ<Lshapeless/_0;>;>;>;>;>;>;>;>;>;>;>;>;>;>;)V
    MethodParameters:
      Name                           Flags
      x$1                            final

  public abstract void shapeless$Nats$_setter_$_15_$eq(shapeless.Succ<shapeless.Succ<shapeless.Succ<shapeless.Succ<shapeless.Succ<shapeless.Succ<shapeless.Succ<shapeless.Succ<shapeless.Succ<shapeless.Succ<shapeless.Succ<shapeless.Succ<shapeless.Succ<shapeless.Succ<shapeless.Succ<shapeless._0>>>>>>>>>>>>>>>);
    descriptor: (Lshapeless/Succ;)V
    flags: (0x0401) ACC_PUBLIC, ACC_ABSTRACT
    Signature: #40                          // (Lshapeless/Succ<Lshapeless/Succ<Lshapeless/Succ<Lshapeless/Succ<Lshapeless/Succ<Lshapeless/Succ<Lshapeless/Succ<Lshapeless/Succ<Lshapeless/Succ<Lshapeless/Succ<Lshapeless/Succ<Lshapeless/Succ<Lshapeless/Succ<Lshapeless/Succ<Lshapeless/Succ<Lshapeless/_0;>;>;>;>;>;>;>;>;>;>;>;>;>;>;>;)V
    MethodParameters:
      Name                           Flags
      x$1                            final

  public abstract void shapeless$Nats$_setter_$_16_$eq(shapeless.Succ<shapeless.Succ<shapeless.Succ<shapeless.Succ<shapeless.Succ<shapeless.Succ<shapeless.Succ<shapeless.Succ<shapeless.Succ<shapeless.Succ<shapeless.Succ<shapeless.Succ<shapeless.Succ<shapeless.Succ<shapeless.Succ<shapeless.Succ<shapeless._0>>>>>>>>>>>>>>>>);
    descriptor: (Lshapeless/Succ;)V
    flags: (0x0401) ACC_PUBLIC, ACC_ABSTRACT
    Signature: #42                          // (Lshapeless/Succ<Lshapeless/Succ<Lshapeless/Succ<Lshapeless/Succ<Lshapeless/Succ<Lshapeless/Succ<Lshapeless/Succ<Lshapeless/Succ<Lshapeless/Succ<Lshapeless/Succ<Lshapeless/Succ<Lshapeless/Succ<Lshapeless/Succ<Lshapeless/Succ<Lshapeless/Succ<Lshapeless/Succ<Lshapeless/_0;>;>;>;>;>;>;>;>;>;>;>;>;>;>;>;>;)V
    MethodParameters:
      Name                           Flags
      x$1                            final

  public abstract void shapeless$Nats$_setter_$_17_$eq(shapeless.Succ<shapeless.Succ<shapeless.Succ<shapeless.Succ<shapeless.Succ<shapeless.Succ<shapeless.Succ<shapeless.Succ<shapeless.Succ<shapeless.Succ<shapeless.Succ<shapeless.Succ<shapeless.Succ<shapeless.Succ<shapeless.Succ<shapeless.Succ<shapeless.Succ<shapeless._0>>>>>>>>>>>>>>>>>);
    descriptor: (Lshapeless/Succ;)V
    flags: (0x0401) ACC_PUBLIC, ACC_ABSTRACT
    Signature: #44                          // (Lshapeless/Succ<Lshapeless/Succ<Lshapeless/Succ<Lshapeless/Succ<Lshapeless/Succ<Lshapeless/Succ<Lshapeless/Succ<Lshapeless/Succ<Lshapeless/Succ<Lshapeless/Succ<Lshapeless/Succ<Lshapeless/Succ<Lshapeless/Succ<Lshapeless/Succ<Lshapeless/Succ<Lshapeless/Succ<Lshapeless/Succ<Lshapeless/_0;>;>;>;>;>;>;>;>;>;>;>;>;>;>;>;>;>;)V
    MethodParameters:
      Name                           Flags
      x$1                            final

  public abstract void shapeless$Nats$_setter_$_18_$eq(shapeless.Succ<shapeless.Succ<shapeless.Succ<shapeless.Succ<shapeless.Succ<shapeless.Succ<shapeless.Succ<shapeless.Succ<shapeless.Succ<shapeless.Succ<shapeless.Succ<shapeless.Succ<shapeless.Succ<shapeless.Succ<shapeless.Succ<shapeless.Succ<shapeless.Succ<shapeless.Succ<shapeless._0>>>>>>>>>>>>>>>>>>);
    descriptor: (Lshapeless/Succ;)V
    flags: (0x0401) ACC_PUBLIC, ACC_ABSTRACT
    Signature: #46                          // (Lshapeless/Succ<Lshapeless/Succ<Lshapeless/Succ<Lshapeless/Succ<Lshapeless/Succ<Lshapeless/Succ<Lshapeless/Succ<Lshapeless/Succ<Lshapeless/Succ<Lshapeless/Succ<Lshapeless/Succ<Lshapeless/Succ<Lshapeless/Succ<Lshapeless/Succ<Lshapeless/Succ<Lshapeless/Succ<Lshapeless/Succ<Lshapeless/Succ<Lshapeless/_0;>;>;>;>;>;>;>;>;>;>;>;>;>;>;>;>;>;>;)V
    MethodParameters:
      Name                           Flags
      x$1                            final

  public abstract void shapeless$Nats$_setter_$_19_$eq(shapeless.Succ<shapeless.Succ<shapeless.Succ<shapeless.Succ<shapeless.Succ<shapeless.Succ<shapeless.Succ<shapeless.Succ<shapeless.Succ<shapeless.Succ<shapeless.Succ<shapeless.Succ<shapeless.Succ<shapeless.Succ<shapeless.Succ<shapeless.Succ<shapeless.Succ<shapeless.Succ<shapeless.Succ<shapeless._0>>>>>>>>>>>>>>>>>>>);
    descriptor: (Lshapeless/Succ;)V
    flags: (0x0401) ACC_PUBLIC, ACC_ABSTRACT
    Signature: #48                          // (Lshapeless/Succ<Lshapeless/Succ<Lshapeless/Succ<Lshapeless/Succ<Lshapeless/Succ<Lshapeless/Succ<Lshapeless/Succ<Lshapeless/Succ<Lshapeless/Succ<Lshapeless/Succ<Lshapeless/Succ<Lshapeless/Succ<Lshapeless/Succ<Lshapeless/Succ<Lshapeless/Succ<Lshapeless/Succ<Lshapeless/Succ<Lshapeless/Succ<Lshapeless/Succ<Lshapeless/_0;>;>;>;>;>;>;>;>;>;>;>;>;>;>;>;>;>;>;>;)V
    MethodParameters:
      Name                           Flags
      x$1                            final

  public abstract void shapeless$Nats$_setter_$_20_$eq(shapeless.Succ<shapeless.Succ<shapeless.Succ<shapeless.Succ<shapeless.Succ<shapeless.Succ<shapeless.Succ<shapeless.Succ<shapeless.Succ<shapeless.Succ<shapeless.Succ<shapeless.Succ<shapeless.Succ<shapeless.Succ<shapeless.Succ<shapeless.Succ<shapeless.Succ<shapeless.Succ<shapeless.Succ<shapeless.Succ<shapeless._0>>>>>>>>>>>>>>>>>>>>);
    descriptor: (Lshapeless/Succ;)V
    flags: (0x0401) ACC_PUBLIC, ACC_ABSTRACT
    Signature: #50                          // (Lshapeless/Succ<Lshapeless/Succ<Lshapeless/Succ<Lshapeless/Succ<Lshapeless/Succ<Lshapeless/Succ<Lshapeless/Succ<Lshapeless/Succ<Lshapeless/Succ<Lshapeless/Succ<Lshapeless/Succ<Lshapeless/Succ<Lshapeless/Succ<Lshapeless/Succ<Lshapeless/Succ<Lshapeless/Succ<Lshapeless/Succ<Lshapeless/Succ<Lshapeless/Succ<Lshapeless/Succ<Lshapeless/_0;>;>;>;>;>;>;>;>;>;>;>;>;>;>;>;>;>;>;>;>;)V
    MethodParameters:
      Name                           Flags
      x$1                            final

  public abstract void shapeless$Nats$_setter_$_21_$eq(shapeless.Succ<shapeless.Succ<shapeless.Succ<shapeless.Succ<shapeless.Succ<shapeless.Succ<shapeless.Succ<shapeless.Succ<shapeless.Succ<shapeless.Succ<shapeless.Succ<shapeless.Succ<shapeless.Succ<shapeless.Succ<shapeless.Succ<shapeless.Succ<shapeless.Succ<shapeless.Succ<shapeless.Succ<shapeless.Succ<shapeless.Succ<shapeless._0>>>>>>>>>>>>>>>>>>>>>);
    descriptor: (Lshapeless/Succ;)V
    flags: (0x0401) ACC_PUBLIC, ACC_ABSTRACT
    Signature: #52                          // (Lshapeless/Succ<Lshapeless/Succ<Lshapeless/Succ<Lshapeless/Succ<Lshapeless/Succ<Lshapeless/Succ<Lshapeless/Succ<Lshapeless/Succ<Lshapeless/Succ<Lshapeless/Succ<Lshapeless/Succ<Lshapeless/Succ<Lshapeless/Succ<Lshapeless/Succ<Lshapeless/Succ<Lshapeless/Succ<Lshapeless/Succ<Lshapeless/Succ<Lshapeless/Succ<Lshapeless/Succ<Lshapeless/Succ<Lshapeless/_0;>;>;>;>;>;>;>;>;>;>;>;>;>;>;>;>;>;>;>;>;>;)V
    MethodParameters:
      Name                           Flags
      x$1                            final

  public abstract void shapeless$Nats$_setter_$_22_$eq(shapeless.Succ<shapeless.Succ<shapeless.Succ<shapeless.Succ<shapeless.Succ<shapeless.Succ<shapeless.Succ<shapeless.Succ<shapeless.Succ<shapeless.Succ<shapeless.Succ<shapeless.Succ<shapeless.Succ<shapeless.Succ<shapeless.Succ<shapeless.Succ<shapeless.Succ<shapeless.Succ<shapeless.Succ<shapeless.Succ<shapeless.Succ<shapeless.Succ<shapeless._0>>>>>>>>>>>>>>>>>>>>>>);
    descriptor: (Lshapeless/Succ;)V
    flags: (0x0401) ACC_PUBLIC, ACC_ABSTRACT
    Signature: #54                          // (Lshapeless/Succ<Lshapeless/Succ<Lshapeless/Succ<Lshapeless/Succ<Lshapeless/Succ<Lshapeless/Succ<Lshapeless/Succ<Lshapeless/Succ<Lshapeless/Succ<Lshapeless/Succ<Lshapeless/Succ<Lshapeless/Succ<Lshapeless/Succ<Lshapeless/Succ<Lshapeless/Succ<Lshapeless/Succ<Lshapeless/Succ<Lshapeless/Succ<Lshapeless/Succ<Lshapeless/Succ<Lshapeless/Succ<Lshapeless/Succ<Lshapeless/_0;>;>;>;>;>;>;>;>;>;>;>;>;>;>;>;>;>;>;>;>;>;>;)V
    MethodParameters:
      Name                           Flags
      x$1                            final

  public abstract shapeless.Succ<shapeless._0> _1();
    descriptor: ()Lshapeless/Succ;
    flags: (0x0401) ACC_PUBLIC, ACC_ABSTRACT
    Signature: #57                          // ()Lshapeless/Succ<Lshapeless/_0;>;

  public abstract shapeless.Succ<shapeless.Succ<shapeless._0>> _2();
    descriptor: ()Lshapeless/Succ;
    flags: (0x0401) ACC_PUBLIC, ACC_ABSTRACT
    Signature: #59                          // ()Lshapeless/Succ<Lshapeless/Succ<Lshapeless/_0;>;>;

  public abstract shapeless.Succ<shapeless.Succ<shapeless.Succ<shapeless._0>>> _3();
    descriptor: ()Lshapeless/Succ;
    flags: (0x0401) ACC_PUBLIC, ACC_ABSTRACT
    Signature: #61                          // ()Lshapeless/Succ<Lshapeless/Succ<Lshapeless/Succ<Lshapeless/_0;>;>;>;

  public abstract shapeless.Succ<shapeless.Succ<shapeless.Succ<shapeless.Succ<shapeless._0>>>> _4();
    descriptor: ()Lshapeless/Succ;
    flags: (0x0401) ACC_PUBLIC, ACC_ABSTRACT
    Signature: #63                          // ()Lshapeless/Succ<Lshapeless/Succ<Lshapeless/Succ<Lshapeless/Succ<Lshapeless/_0;>;>;>;>;

  public abstract shapeless.Succ<shapeless.Succ<shapeless.Succ<shapeless.Succ<shapeless.Succ<shapeless._0>>>>> _5();
    descriptor: ()Lshapeless/Succ;
    flags: (0x0401) ACC_PUBLIC, ACC_ABSTRACT
    Signature: #65                          // ()Lshapeless/Succ<Lshapeless/Succ<Lshapeless/Succ<Lshapeless/Succ<Lshapeless/Succ<Lshapeless/_0;>;>;>;>;>;

  public abstract shapeless.Succ<shapeless.Succ<shapeless.Succ<shapeless.Succ<shapeless.Succ<shapeless.Succ<shapeless._0>>>>>> _6();
    descriptor: ()Lshapeless/Succ;
    flags: (0x0401) ACC_PUBLIC, ACC_ABSTRACT
    Signature: #67                          // ()Lshapeless/Succ<Lshapeless/Succ<Lshapeless/Succ<Lshapeless/Succ<Lshapeless/Succ<Lshapeless/Succ<Lshapeless/_0;>;>;>;>;>;>;

  public abstract shapeless.Succ<shapeless.Succ<shapeless.Succ<shapeless.Succ<shapeless.Succ<shapeless.Succ<shapeless.Succ<shapeless._0>>>>>>> _7();
    descriptor: ()Lshapeless/Succ;
    flags: (0x0401) ACC_PUBLIC, ACC_ABSTRACT
    Signature: #69                          // ()Lshapeless/Succ<Lshapeless/Succ<Lshapeless/Succ<Lshapeless/Succ<Lshapeless/Succ<Lshapeless/Succ<Lshapeless/Succ<Lshapeless/_0;>;>;>;>;>;>;>;

  public abstract shapeless.Succ<shapeless.Succ<shapeless.Succ<shapeless.Succ<shapeless.Succ<shapeless.Succ<shapeless.Succ<shapeless.Succ<shapeless._0>>>>>>>> _8();
    descriptor: ()Lshapeless/Succ;
    flags: (0x0401) ACC_PUBLIC, ACC_ABSTRACT
    Signature: #71                          // ()Lshapeless/Succ<Lshapeless/Succ<Lshapeless/Succ<Lshapeless/Succ<Lshapeless/Succ<Lshapeless/Succ<Lshapeless/Succ<Lshapeless/Succ<Lshapeless/_0;>;>;>;>;>;>;>;>;

  public abstract shapeless.Succ<shapeless.Succ<shapeless.Succ<shapeless.Succ<shapeless.Succ<shapeless.Succ<shapeless.Succ<shapeless.Succ<shapeless.Succ<shapeless._0>>>>>>>>> _9();
    descriptor: ()Lshapeless/Succ;
    flags: (0x0401) ACC_PUBLIC, ACC_ABSTRACT
    Signature: #73                          // ()Lshapeless/Succ<Lshapeless/Succ<Lshapeless/Succ<Lshapeless/Succ<Lshapeless/Succ<Lshapeless/Succ<Lshapeless/Succ<Lshapeless/Succ<Lshapeless/Succ<Lshapeless/_0;>;>;>;>;>;>;>;>;>;

  public abstract shapeless.Succ<shapeless.Succ<shapeless.Succ<shapeless.Succ<shapeless.Succ<shapeless.Succ<shapeless.Succ<shapeless.Succ<shapeless.Succ<shapeless.Succ<shapeless._0>>>>>>>>>> _10();
    descriptor: ()Lshapeless/Succ;
    flags: (0x0401) ACC_PUBLIC, ACC_ABSTRACT
    Signature: #75                          // ()Lshapeless/Succ<Lshapeless/Succ<Lshapeless/Succ<Lshapeless/Succ<Lshapeless/Succ<Lshapeless/Succ<Lshapeless/Succ<Lshapeless/Succ<Lshapeless/Succ<Lshapeless/Succ<Lshapeless/_0;>;>;>;>;>;>;>;>;>;>;

  public abstract shapeless.Succ<shapeless.Succ<shapeless.Succ<shapeless.Succ<shapeless.Succ<shapeless.Succ<shapeless.Succ<shapeless.Succ<shapeless.Succ<shapeless.Succ<shapeless.Succ<shapeless._0>>>>>>>>>>> _11();
    descriptor: ()Lshapeless/Succ;
    flags: (0x0401) ACC_PUBLIC, ACC_ABSTRACT
    Signature: #77                          // ()Lshapeless/Succ<Lshapeless/Succ<Lshapeless/Succ<Lshapeless/Succ<Lshapeless/Succ<Lshapeless/Succ<Lshapeless/Succ<Lshapeless/Succ<Lshapeless/Succ<Lshapeless/Succ<Lshapeless/Succ<Lshapeless/_0;>;>;>;>;>;>;>;>;>;>;>;

  public abstract shapeless.Succ<shapeless.Succ<shapeless.Succ<shapeless.Succ<shapeless.Succ<shapeless.Succ<shapeless.Succ<shapeless.Succ<shapeless.Succ<shapeless.Succ<shapeless.Succ<shapeless.Succ<shapeless._0>>>>>>>>>>>> _12();
    descriptor: ()Lshapeless/Succ;
    flags: (0x0401) ACC_PUBLIC, ACC_ABSTRACT
    Signature: #79                          // ()Lshapeless/Succ<Lshapeless/Succ<Lshapeless/Succ<Lshapeless/Succ<Lshapeless/Succ<Lshapeless/Succ<Lshapeless/Succ<Lshapeless/Succ<Lshapeless/Succ<Lshapeless/Succ<Lshapeless/Succ<Lshapeless/Succ<Lshapeless/_0;>;>;>;>;>;>;>;>;>;>;>;>;

  public abstract shapeless.Succ<shapeless.Succ<shapeless.Succ<shapeless.Succ<shapeless.Succ<shapeless.Succ<shapeless.Succ<shapeless.Succ<shapeless.Succ<shapeless.Succ<shapeless.Succ<shapeless.Succ<shapeless.Succ<shapeless._0>>>>>>>>>>>>> _13();
    descriptor: ()Lshapeless/Succ;
    flags: (0x0401) ACC_PUBLIC, ACC_ABSTRACT
    Signature: #81                          // ()Lshapeless/Succ<Lshapeless/Succ<Lshapeless/Succ<Lshapeless/Succ<Lshapeless/Succ<Lshapeless/Succ<Lshapeless/Succ<Lshapeless/Succ<Lshapeless/Succ<Lshapeless/Succ<Lshapeless/Succ<Lshapeless/Succ<Lshapeless/Succ<Lshapeless/_0;>;>;>;>;>;>;>;>;>;>;>;>;>;

  public abstract shapeless.Succ<shapeless.Succ<shapeless.Succ<shapeless.Succ<shapeless.Succ<shapeless.Succ<shapeless.Succ<shapeless.Succ<shapeless.Succ<shapeless.Succ<shapeless.Succ<shapeless.Succ<shapeless.Succ<shapeless.Succ<shapeless._0>>>>>>>>>>>>>> _14();
    descriptor: ()Lshapeless/Succ;
    flags: (0x0401) ACC_PUBLIC, ACC_ABSTRACT
    Signature: #83                          // ()Lshapeless/Succ<Lshapeless/Succ<Lshapeless/Succ<Lshapeless/Succ<Lshapeless/Succ<Lshapeless/Succ<Lshapeless/Succ<Lshapeless/Succ<Lshapeless/Succ<Lshapeless/Succ<Lshapeless/Succ<Lshapeless/Succ<Lshapeless/Succ<Lshapeless/Succ<Lshapeless/_0;>;>;>;>;>;>;>;>;>;>;>;>;>;>;

  public abstract shapeless.Succ<shapeless.Succ<shapeless.Succ<shapeless.Succ<shapeless.Succ<shapeless.Succ<shapeless.Succ<shapeless.Succ<shapeless.Succ<shapeless.Succ<shapeless.Succ<shapeless.Succ<shapeless.Succ<shapeless.Succ<shapeless.Succ<shapeless._0>>>>>>>>>>>>>>> _15();
    descriptor: ()Lshapeless/Succ;
    flags: (0x0401) ACC_PUBLIC, ACC_ABSTRACT
    Signature: #85                          // ()Lshapeless/Succ<Lshapeless/Succ<Lshapeless/Succ<Lshapeless/Succ<Lshapeless/Succ<Lshapeless/Succ<Lshapeless/Succ<Lshapeless/Succ<Lshapeless/Succ<Lshapeless/Succ<Lshapeless/Succ<Lshapeless/Succ<Lshapeless/Succ<Lshapeless/Succ<Lshapeless/Succ<Lshapeless/_0;>;>;>;>;>;>;>;>;>;>;>;>;>;>;>;

  public abstract shapeless.Succ<shapeless.Succ<shapeless.Succ<shapeless.Succ<shapeless.Succ<shapeless.Succ<shapeless.Succ<shapeless.Succ<shapeless.Succ<shapeless.Succ<shapeless.Succ<shapeless.Succ<shapeless.Succ<shapeless.Succ<shapeless.Succ<shapeless.Succ<shapeless._0>>>>>>>>>>>>>>>> _16();
    descriptor: ()Lshapeless/Succ;
    flags: (0x0401) ACC_PUBLIC, ACC_ABSTRACT
    Signature: #87                          // ()Lshapeless/Succ<Lshapeless/Succ<Lshapeless/Succ<Lshapeless/Succ<Lshapeless/Succ<Lshapeless/Succ<Lshapeless/Succ<Lshapeless/Succ<Lshapeless/Succ<Lshapeless/Succ<Lshapeless/Succ<Lshapeless/Succ<Lshapeless/Succ<Lshapeless/Succ<Lshapeless/Succ<Lshapeless/Succ<Lshapeless/_0;>;>;>;>;>;>;>;>;>;>;>;>;>;>;>;>;

  public abstract shapeless.Succ<shapeless.Succ<shapeless.Succ<shapeless.Succ<shapeless.Succ<shapeless.Succ<shapeless.Succ<shapeless.Succ<shapeless.Succ<shapeless.Succ<shapeless.Succ<shapeless.Succ<shapeless.Succ<shapeless.Succ<shapeless.Succ<shapeless.Succ<shapeless.Succ<shapeless._0>>>>>>>>>>>>>>>>> _17();
    descriptor: ()Lshapeless/Succ;
    flags: (0x0401) ACC_PUBLIC, ACC_ABSTRACT
    Signature: #89                          // ()Lshapeless/Succ<Lshapeless/Succ<Lshapeless/Succ<Lshapeless/Succ<Lshapeless/Succ<Lshapeless/Succ<Lshapeless/Succ<Lshapeless/Succ<Lshapeless/Succ<Lshapeless/Succ<Lshapeless/Succ<Lshapeless/Succ<Lshapeless/Succ<Lshapeless/Succ<Lshapeless/Succ<Lshapeless/Succ<Lshapeless/Succ<Lshapeless/_0;>;>;>;>;>;>;>;>;>;>;>;>;>;>;>;>;>;

  public abstract shapeless.Succ<shapeless.Succ<shapeless.Succ<shapeless.Succ<shapeless.Succ<shapeless.Succ<shapeless.Succ<shapeless.Succ<shapeless.Succ<shapeless.Succ<shapeless.Succ<shapeless.Succ<shapeless.Succ<shapeless.Succ<shapeless.Succ<shapeless.Succ<shapeless.Succ<shapeless.Succ<shapeless._0>>>>>>>>>>>>>>>>>> _18();
    descriptor: ()Lshapeless/Succ;
    flags: (0x0401) ACC_PUBLIC, ACC_ABSTRACT
    Signature: #91                          // ()Lshapeless/Succ<Lshapeless/Succ<Lshapeless/Succ<Lshapeless/Succ<Lshapeless/Succ<Lshapeless/Succ<Lshapeless/Succ<Lshapeless/Succ<Lshapeless/Succ<Lshapeless/Succ<Lshapeless/Succ<Lshapeless/Succ<Lshapeless/Succ<Lshapeless/Succ<Lshapeless/Succ<Lshapeless/Succ<Lshapeless/Succ<Lshapeless/Succ<Lshapeless/_0;>;>;>;>;>;>;>;>;>;>;>;>;>;>;>;>;>;>;

  public abstract shapeless.Succ<shapeless.Succ<shapeless.Succ<shapeless.Succ<shapeless.Succ<shapeless.Succ<shapeless.Succ<shapeless.Succ<shapeless.Succ<shapeless.Succ<shapeless.Succ<shapeless.Succ<shapeless.Succ<shapeless.Succ<shapeless.Succ<shapeless.Succ<shapeless.Succ<shapeless.Succ<shapeless.Succ<shapeless._0>>>>>>>>>>>>>>>>>>> _19();
    descriptor: ()Lshapeless/Succ;
    flags: (0x0401) ACC_PUBLIC, ACC_ABSTRACT
    Signature: #93                          // ()Lshapeless/Succ<Lshapeless/Succ<Lshapeless/Succ<Lshapeless/Succ<Lshapeless/Succ<Lshapeless/Succ<Lshapeless/Succ<Lshapeless/Succ<Lshapeless/Succ<Lshapeless/Succ<Lshapeless/Succ<Lshapeless/Succ<Lshapeless/Succ<Lshapeless/Succ<Lshapeless/Succ<Lshapeless/Succ<Lshapeless/Succ<Lshapeless/Succ<Lshapeless/Succ<Lshapeless/_0;>;>;>;>;>;>;>;>;>;>;>;>;>;>;>;>;>;>;>;

  public abstract shapeless.Succ<shapeless.Succ<shapeless.Succ<shapeless.Succ<shapeless.Succ<shapeless.Succ<shapeless.Succ<shapeless.Succ<shapeless.Succ<shapeless.Succ<shapeless.Succ<shapeless.Succ<shapeless.Succ<shapeless.Succ<shapeless.Succ<shapeless.Succ<shapeless.Succ<shapeless.Succ<shapeless.Succ<shapeless.Succ<shapeless._0>>>>>>>>>>>>>>>>>>>> _20();
    descriptor: ()Lshapeless/Succ;
    flags: (0x0401) ACC_PUBLIC, ACC_ABSTRACT
    Signature: #95                          // ()Lshapeless/Succ<Lshapeless/Succ<Lshapeless/Succ<Lshapeless/Succ<Lshapeless/Succ<Lshapeless/Succ<Lshapeless/Succ<Lshapeless/Succ<Lshapeless/Succ<Lshapeless/Succ<Lshapeless/Succ<Lshapeless/Succ<Lshapeless/Succ<Lshapeless/Succ<Lshapeless/Succ<Lshapeless/Succ<Lshapeless/Succ<Lshapeless/Succ<Lshapeless/Succ<Lshapeless/Succ<Lshapeless/_0;>;>;>;>;>;>;>;>;>;>;>;>;>;>;>;>;>;>;>;>;

  public abstract shapeless.Succ<shapeless.Succ<shapeless.Succ<shapeless.Succ<shapeless.Succ<shapeless.Succ<shapeless.Succ<shapeless.Succ<shapeless.Succ<shapeless.Succ<shapeless.Succ<shapeless.Succ<shapeless.Succ<shapeless.Succ<shapeless.Succ<shapeless.Succ<shapeless.Succ<shapeless.Succ<shapeless.Succ<shapeless.Succ<shapeless.Succ<shapeless._0>>>>>>>>>>>>>>>>>>>>> _21();
    descriptor: ()Lshapeless/Succ;
    flags: (0x0401) ACC_PUBLIC, ACC_ABSTRACT
    Signature: #97                          // ()Lshapeless/Succ<Lshapeless/Succ<Lshapeless/Succ<Lshapeless/Succ<Lshapeless/Succ<Lshapeless/Succ<Lshapeless/Succ<Lshapeless/Succ<Lshapeless/Succ<Lshapeless/Succ<Lshapeless/Succ<Lshapeless/Succ<Lshapeless/Succ<Lshapeless/Succ<Lshapeless/Succ<Lshapeless/Succ<Lshapeless/Succ<Lshapeless/Succ<Lshapeless/Succ<Lshapeless/Succ<Lshapeless/Succ<Lshapeless/_0;>;>;>;>;>;>;>;>;>;>;>;>;>;>;>;>;>;>;>;>;>;

  public abstract shapeless.Succ<shapeless.Succ<shapeless.Succ<shapeless.Succ<shapeless.Succ<shapeless.Succ<shapeless.Succ<shapeless.Succ<shapeless.Succ<shapeless.Succ<shapeless.Succ<shapeless.Succ<shapeless.Succ<shapeless.Succ<shapeless.Succ<shapeless.Succ<shapeless.Succ<shapeless.Succ<shapeless.Succ<shapeless.Succ<shapeless.Succ<shapeless.Succ<shapeless._0>>>>>>>>>>>>>>>>>>>>>> _22();
    descriptor: ()Lshapeless/Succ;
    flags: (0x0401) ACC_PUBLIC, ACC_ABSTRACT
    Signature: #99                          // ()Lshapeless/Succ<Lshapeless/Succ<Lshapeless/Succ<Lshapeless/Succ<Lshapeless/Succ<Lshapeless/Succ<Lshapeless/Succ<Lshapeless/Succ<Lshapeless/Succ<Lshapeless/Succ<Lshapeless/Succ<Lshapeless/Succ<Lshapeless/Succ<Lshapeless/Succ<Lshapeless/Succ<Lshapeless/Succ<Lshapeless/Succ<Lshapeless/Succ<Lshapeless/Succ<Lshapeless/Succ<Lshapeless/Succ<Lshapeless/Succ<Lshapeless/_0;>;>;>;>;>;>;>;>;>;>;>;>;>;>;>;>;>;>;>;>;>;>;

  public static void $init$(shapeless.Nats);
    descriptor: (Lshapeless/Nats;)V
    flags: (0x0009) ACC_PUBLIC, ACC_STATIC
    Code:
      stack=3, locals=1, args_size=1
         0: aload_0
         1: new           #104                // class shapeless/Succ
         4: dup
         5: invokespecial #108                // Method shapeless/Succ."<init>":()V
         8: invokeinterface #110,  2          // InterfaceMethod shapeless$Nats$_setter_$_1_$eq:(Lshapeless/Succ;)V
        13: aload_0
        14: new           #104                // class shapeless/Succ
        17: dup
        18: invokespecial #108                // Method shapeless/Succ."<init>":()V
        21: invokeinterface #112,  2          // InterfaceMethod shapeless$Nats$_setter_$_2_$eq:(Lshapeless/Succ;)V
        26: aload_0
        27: new           #104                // class shapeless/Succ
        30: dup
        31: invokespecial #108                // Method shapeless/Succ."<init>":()V
        34: invokeinterface #114,  2          // InterfaceMethod shapeless$Nats$_setter_$_3_$eq:(Lshapeless/Succ;)V
        39: aload_0
        40: new           #104                // class shapeless/Succ
        43: dup
        44: invokespecial #108                // Method shapeless/Succ."<init>":()V
        47: invokeinterface #116,  2          // InterfaceMethod shapeless$Nats$_setter_$_4_$eq:(Lshapeless/Succ;)V
        52: aload_0
        53: new           #104                // class shapeless/Succ
        56: dup
        57: invokespecial #108                // Method shapeless/Succ."<init>":()V
        60: invokeinterface #118,  2          // InterfaceMethod shapeless$Nats$_setter_$_5_$eq:(Lshapeless/Succ;)V
        65: aload_0
        66: new           #104                // class shapeless/Succ
        69: dup
        70: invokespecial #108                // Method shapeless/Succ."<init>":()V
        73: invokeinterface #120,  2          // InterfaceMethod shapeless$Nats$_setter_$_6_$eq:(Lshapeless/Succ;)V
        78: aload_0
        79: new           #104                // class shapeless/Succ
        82: dup
        83: invokespecial #108                // Method shapeless/Succ."<init>":()V
        86: invokeinterface #122,  2          // InterfaceMethod shapeless$Nats$_setter_$_7_$eq:(Lshapeless/Succ;)V
        91: aload_0
        92: new           #104                // class shapeless/Succ
        95: dup
        96: invokespecial #108                // Method shapeless/Succ."<init>":()V
        99: invokeinterface #124,  2          // InterfaceMethod shapeless$Nats$_setter_$_8_$eq:(Lshapeless/Succ;)V
       104: aload_0
       105: new           #104                // class shapeless/Succ
       108: dup
       109: invokespecial #108                // Method shapeless/Succ."<init>":()V
       112: invokeinterface #126,  2          // InterfaceMethod shapeless$Nats$_setter_$_9_$eq:(Lshapeless/Succ;)V
       117: aload_0
       118: new           #104                // class shapeless/Succ
       121: dup
       122: invokespecial #108                // Method shapeless/Succ."<init>":()V
       125: invokeinterface #128,  2          // InterfaceMethod shapeless$Nats$_setter_$_10_$eq:(Lshapeless/Succ;)V
       130: aload_0
       131: new           #104                // class shapeless/Succ
       134: dup
       135: invokespecial #108                // Method shapeless/Succ."<init>":()V
       138: invokeinterface #130,  2          // InterfaceMethod shapeless$Nats$_setter_$_11_$eq:(Lshapeless/Succ;)V
       143: aload_0
       144: new           #104                // class shapeless/Succ
       147: dup
       148: invokespecial #108                // Method shapeless/Succ."<init>":()V
       151: invokeinterface #132,  2          // InterfaceMethod shapeless$Nats$_setter_$_12_$eq:(Lshapeless/Succ;)V
       156: aload_0
       157: new           #104                // class shapeless/Succ
       160: dup
       161: invokespecial #108                // Method shapeless/Succ."<init>":()V
       164: invokeinterface #134,  2          // InterfaceMethod shapeless$Nats$_setter_$_13_$eq:(Lshapeless/Succ;)V
       169: aload_0
       170: new           #104                // class shapeless/Succ
       173: dup
       174: invokespecial #108                // Method shapeless/Succ."<init>":()V
       177: invokeinterface #136,  2          // InterfaceMethod shapeless$Nats$_setter_$_14_$eq:(Lshapeless/Succ;)V
       182: aload_0
       183: new           #104                // class shapeless/Succ
       186: dup
       187: invokespecial #108                // Method shapeless/Succ."<init>":()V
       190: invokeinterface #138,  2          // InterfaceMethod shapeless$Nats$_setter_$_15_$eq:(Lshapeless/Succ;)V
       195: aload_0
       196: new           #104                // class shapeless/Succ
       199: dup
       200: invokespecial #108                // Method shapeless/Succ."<init>":()V
       203: invokeinterface #140,  2          // InterfaceMethod shapeless$Nats$_setter_$_16_$eq:(Lshapeless/Succ;)V
       208: aload_0
       209: new           #104                // class shapeless/Succ
       212: dup
       213: invokespecial #108                // Method shapeless/Succ."<init>":()V
       216: invokeinterface #142,  2          // InterfaceMethod shapeless$Nats$_setter_$_17_$eq:(Lshapeless/Succ;)V
       221: aload_0
       222: new           #104                // class shapeless/Succ
       225: dup
       226: invokespecial #108                // Method shapeless/Succ."<init>":()V
       229: invokeinterface #144,  2          // InterfaceMethod shapeless$Nats$_setter_$_18_$eq:(Lshapeless/Succ;)V
       234: aload_0
       235: new           #104                // class shapeless/Succ
       238: dup
       239: invokespecial #108                // Method shapeless/Succ."<init>":()V
       242: invokeinterface #146,  2          // InterfaceMethod shapeless$Nats$_setter_$_19_$eq:(Lshapeless/Succ;)V
       247: aload_0
       248: new           #104                // class shapeless/Succ
       251: dup
       252: invokespecial #108                // Method shapeless/Succ."<init>":()V
       255: invokeinterface #148,  2          // InterfaceMethod shapeless$Nats$_setter_$_20_$eq:(Lshapeless/Succ;)V
       260: aload_0
       261: new           #104                // class shapeless/Succ
       264: dup
       265: invokespecial #108                // Method shapeless/Succ."<init>":()V
       268: invokeinterface #150,  2          // InterfaceMethod shapeless$Nats$_setter_$_21_$eq:(Lshapeless/Succ;)V
       273: aload_0
       274: new           #104                // class shapeless/Succ
       277: dup
       278: invokespecial #108                // Method shapeless/Succ."<init>":()V
       281: invokeinterface #152,  2          // InterfaceMethod shapeless$Nats$_setter_$_22_$eq:(Lshapeless/Succ;)V
       286: return
      LineNumberTable:
        line 24: 0
        line 27: 13
        line 30: 26
        line 33: 39
        line 36: 52
        line 39: 65
        line 42: 78
        line 45: 91
        line 48: 104
        line 51: 117
        line 54: 130
        line 57: 143
        line 60: 156
        line 63: 169
        line 66: 182
        line 69: 195
        line 72: 208
        line 75: 221
        line 78: 234
        line 81: 247
        line 84: 260
        line 87: 273
        line 21: 286
      LocalVariableTable:
        Start  Length  Slot  Name   Signature
            0     287     0 $this   Lshapeless/Nats;
    MethodParameters:
      Name                           Flags
      $this                          final synthetic
}
SourceFile: "nats.scala"
RuntimeVisibleAnnotations:
  0: #6(#7=s#8)
    scala.reflect.ScalaSignature(
      bytes="\u0006\u0005\u0005\u001dda\u0002\u00180!\u0003\r\tA\r\u0005\u0006s\u0001!\tAO\u0003\u0005}\u0001\u0001q\bC\u0004G\u0001\t\u0007I\u0011A$\u0006\t)\u0003\u0001a\u0013\u0005\b\u0019\u0002\u0011\r\u0011\"\u0001N\u000b\u0011y\u0005\u0001\u0001)\t\u000fE\u0003!\u0019!C\u0001%\u0016!A\u000b\u0001\u0001V\u0011\u001d1\u0006A1A\u0005\u0002]+A!\u0017\u0001\u00015\"91\f\u0001b\u0001\n\u0003aV\u0001\u00020\u0001\u0001}Cq\u0001\u0019\u0001C\u0002\u0013\u0005\u0011-\u0002\u0003d\u0001\u0001!\u0007bB3\u0001\u0005\u0004%\tAZ\u0003\u0005Q\u0002\u0001\u0011\u000eC\u0004k\u0001\t\u0007I\u0011A6\u0006\t5\u0004\u0001A\u001c\u0005\b_\u0002\u0011\r\u0011\"\u0001q\u000b\u0011\u0011\b\u0001A:\t\u000fQ\u0004!\u0019!C\u0001k\u0016!q\u000f\u0001\u0001y\u0011\u001dI\bA1A\u0005\u0002i,A\u0001 \u0001\u0001{\"9a\u0010\u0001b\u0001\n\u0003yXABA\u0002\u0001\u0001\t)\u0001C\u0005\u0002\b\u0001\u0011\r\u0011\"\u0001\u0002\n\u00151\u0011Q\u0002\u0001\u0001\u0003\u001fA\u0011\"!\u0005\u0001\u0005\u0004%\t!a\u0005\u0006\r\u0005]\u0001\u0001AA\r\u0011%\tY\u0002\u0001b\u0001\n\u0003\ti\"\u0002\u0004\u0002\"\u0001\u0001\u00111\u0005\u0005\n\u0003K\u0001!\u0019!C\u0001\u0003O)a!a\u000b\u0001\u0001\u00055\u0002\"CA\u0018\u0001\t\u0007I\u0011AA\u0019\u000b\u0019\t)\u0004\u0001\u0001\u00028!I\u0011\u0011\b\u0001C\u0002\u0013\u0005\u00111H\u0003\u0007\u0003\u007f\u0001\u0001!!\u0011\t\u0013\u0005\r\u0003A1A\u0005\u0002\u0005\u0015SABA%\u0001\u0001\tY\u0005C\u0005\u0002N\u0001\u0011\r\u0011\"\u0001\u0002P\u00151\u00111\u000b\u0001\u0001\u0003+B\u0011\"a\u0016\u0001\u0005\u0004%\t!!\u0017\u0006\r\u0005u\u0003\u0001AA0\u0011%\t\t\u0007\u0001b\u0001\n\u0003\t\u0019G\u0001\u0003OCR\u001c(\"\u0001\u0019\u0002\u0013MD\u0017\r]3mKN\u001c8\u0001A\n\u0003\u0001M\u0002\"\u0001N\u001c\u000e\u0003UR\u0011AN\u0001\u0006g\u000e\fG.Y\u0005\u0003qU\u0012a!\u00118z%\u00164\u0017A\u0002\u0013j]&$H\u0005F\u0001<!\t!D(\u0003\u0002>k\t!QK\\5u\u0005\ty\u0016\u0007E\u0002A\u0003\u000ek\u0011aL\u0005\u0003\u0005>\u0012AaU;dGB\u0011\u0001\tR\u0005\u0003\u000b>\u0012!a\u0018\u0019\u0002\u0005}\u000bT#\u0001%\u0011\u0005%\u0013Q\"\u0001\u0001\u0003\u0005}\u0013\u0004c\u0001!B\u0011\u0006\u0011qLM\u000b\u0002\u001dB\u0011\u0011\n\u0002\u0002\u0003?N\u00022\u0001Q!O\u0003\ty6\'F\u0001T!\tIeA\u0001\u0002`iA\u0019\u0001)Q*\u0002\u0005}#T#\u0001-\u0011\u0005%C!AA06!\r\u0001\u0015\tW\u0001\u0003?V*\u0012!\u0018\t\u0003\u0013*\u0011!a\u0018\u001c\u0011\u0007\u0001\u000bU,\u0001\u0002`mU\t!\r\u0005\u0002J\u0019\t\u0011ql\u000e\t\u0004\u0001\u0006\u0013\u0017AA08+\u00059\u0007CA%\u000f\u0005\ty\u0006\bE\u0002A\u0003\u001e\f!a\u0018\u001d\u0016\u00031\u0004\"!\u0013\t\u0003\u0005}K\u0004c\u0001!BY\u0006\u0011q,O\u000b\u0002cB\u0011\u0011J\u0005\u0002\u0004?F\u0002\u0004c\u0001!Bc\u0006\u0019q,\r\u0019\u0016\u0003Y\u0004\"!\u0013\u000b\u0003\u0007}\u000b\u0014\u0007E\u0002A\u0003Z\f1aX\u00192+\u0005Y\bCA%\u0017\u0005\ry\u0016G\r\t\u0004\u0001\u0006[\u0018aA02eU\u0011\u0011\u0011\u0001\t\u0003\u0013b\u00111aX\u00194!\u0011\u0001\u0015)!\u0001\u0002\u0007}\u000b4\'\u0006\u0002\u0002\fA\u0011\u0011J\u0007\u0002\u0004?F\"\u0004\u0003\u0002!B\u0003\u0017\t1aX\u00195+\t\t)\u0002\u0005\u0002J9\t\u0019q,M\u001b\u0011\t\u0001\u000b\u0015QC\u0001\u0004?F*TCAA\u0010!\tIeDA\u0002`cY\u0002B\u0001Q!\u0002 \u0005\u0019q,\r\u001c\u0016\u0005\u0005%\u0002CA%!\u0005\ry\u0016g\u000e\t\u0005\u0001\u0006\u000bI#A\u0002`c]*\"!a\r\u0011\u0005%\u0013#aA02qA!\u0001)QA\u001a\u0003\ry\u0016\u0007O\u000b\u0003\u0003{\u0001\"!\u0013\u0013\u0003\u0007}\u000b\u0014\b\u0005\u0003A\u0003\u0006u\u0012aA02sU\u0011\u0011q\t\t\u0003\u0013\u001a\u00121a\u0018\u001a1!\u0011\u0001\u0015)a\u0012\u0002\u0007}\u0013\u0004\'\u0006\u0002\u0002RA\u0011\u0011\n\u000b\u0002\u0004?J\n\u0004\u0003\u0002!B\u0003#\n1a\u0018\u001a2+\t\tY\u0006\u0005\u0002JU\t\u0019qL\r\u001a\u0011\t\u0001\u000b\u00151L\u0001\u0004?J\u0012TCAA3!\tIE\u0006"
    )
  ScalaInlineInfo: length = 0xE5 (unknown attribute)
   01 00 00 2D 00 64 00 65 01 00 37 00 38 00 00 4A
   00 38 00 00 4C 00 38 00 00 4E 00 38 00 00 50 00
   38 00 00 52 00 38 00 00 54 00 38 00 00 56 00 38
   00 00 58 00 38 00 00 5A 00 38 00 00 5C 00 38 00
   00 3A 00 38 00 00 5E 00 38 00 00 60 00 38 00 00
   62 00 38 00 00 3C 00 38 00 00 3E 00 38 00 00 40
   00 38 00 00 42 00 38 00 00 44 00 38 00 00 46 00
   38 00 00 48 00 38 00 00 1D 00 0A 00 00 1F 00 0A
   00 00 21 00 0A 00 00 23 00 0A 00 00 25 00 0A 00
   00 27 00 0A 00 00 29 00 0A 00 00 2B 00 0A 00 00
   2D 00 0A 00 00 2F 00 0A 00 00 09 00 0A 00 00 31
   00 0A 00 00 33 00 0A 00 00 35 00 0A 00 00 0D 00
   0A 00 00 0F 00 0A 00 00 11 00 0A 00 00 13 00 0A
   00 00 15 00 0A 00 00 17 00 0A 00 00 19 00 0A 00
   00 1B 00 0A 00
  ScalaSig: length = 0x3 (unknown attribute)
   05 02 00
