Classfile /Users/mw/Projects/slang-braindump/.jar/jar11/assemble/slang-braindump/assemble/content/shapeless/OpticComposer.class
  Last modified May 29, 2022; size 2524 bytes
  SHA-256 checksum 66e75f8fdd2682b61fbacd3c2c2c5792ae9ab1f30e24be3494eba6bb062851fc
  Compiled from "lenses.scala"
public interface shapeless.OpticComposer<L extends java.lang.Object, R extends java.lang.Object> extends java.io.Serializable
  minor version: 0
  major version: 52
  flags: (0x0601) ACC_PUBLIC, ACC_INTERFACE, ACC_ABSTRACT
  this_class: #2                          // shapeless/OpticComposer
  super_class: #5                         // java/lang/Object
  interfaces: 1, fields: 0, methods: 5, attributes: 5
Constant pool:
   #1 = Utf8               shapeless/OpticComposer
   #2 = Class              #1             // shapeless/OpticComposer
   #3 = Utf8               <L:Ljava/lang/Object;R:Ljava/lang/Object;>Ljava/lang/Object;Ljava/io/Serializable;
   #4 = Utf8               java/lang/Object
   #5 = Class              #4             // java/lang/Object
   #6 = Utf8               java/io/Serializable
   #7 = Class              #6             // java/io/Serializable
   #8 = Utf8               lenses.scala
   #9 = Utf8               Lscala/reflect/ScalaSignature;
  #10 = Utf8               bytes
  #11 = Utf8               \u0006\u0005\u0005Uba\u0002\u0007\u000e!\u0003\r\n\u0001\u0005\u0003\u0006I\u0001\u0011\t!\n\u0005\u0006Y\u00011\t!L\u0004\u0006w5A\t\u0001\u0010\u0004\u0006\u00195A\tA\u0010\u0005\u0006\r\u0012!\taR\u0003\u0005\u0011\u0012\u0001\u0011\nC\u0003W\t\u0011\rq\u000bC\u0003j\t\u0011\r!\u000eC\u0003y\t\u0011\r\u0011\u0010C\u0004\u0002\f\u0011!\u0019!!\u0004\t\u0013\u0005\u0015B!!A\u0005\n\u0005\u001d\"!D(qi&\u001c7i\\7q_N,\'OC\u0001\u000f\u0003%\u0019\b.\u00199fY\u0016\u001c8o\u0001\u0001\u0016\u0007E!\u0014hE\u0002\u0001%a\u0001\"a\u0005\f\u000e\u0003QQ\u0011!F\u0001\u0006g\u000e\fG.Y\u0005\u0003/Q\u0011a!\u00118z%\u00164\u0007CA\r\"\u001d\tQrD\u0004\u0002\u001c=5\tAD\u0003\u0002\u001e\u001f\u00051AH]8pizJ\u0011!F\u0005\u0003AQ\tq\u0001]1dW\u0006<W-\u0003\u0002#G\ta1+\u001a:jC2L\'0\u00192mK*\u0011\u0001\u0005\u0006\u0002\u0004\u001fV$\u0018C\u0001\u0014*!\t\u0019r%\u0003\u0002))\t9aj\u001c;iS:<\u0007CA\n+\u0013\tYCCA\u0002B]f\fQ!\u00199qYf$2A\f\u00197!\ty\u0013!D\u0001\u0001\u0011\u0015\t$\u00011\u00013\u0003\u0005a\u0007CA\u001a5\u0019\u0001!Q!\u000e\u0001C\u0002\u0015\u0012\u0011\u0001\u0014\u0005\u0006o\t\u0001\r\u0001O\u0001\u0002eB\u00111\'\u000f\u0003\u0006u\u0001\u0011\r!\n\u0002\u0002%\u0006iq\n\u001d;jG\u000e{W\u000e]8tKJ\u0004\"!\u0010\u0003\u000e\u00035\u00192\u0001\u0002\n@!\t\u0001U)D\u0001B\u0015\t\u00115)\u0001\u0002j_*\tA)\u0001\u0003kCZ\f\u0017B\u0001\u0012B\u0003\u0019a\u0014N\\5u}Q\tAHA\u0002Bkb,BAS(R)J\u00111*\u0014\u0004\u0005\u0019\u0012\u0001!J\u0001\u0007=e\u00164\u0017N\\3nK:$h\b\u0005\u0003>\u00019\u0003\u0006CA\u001aP\t\u0015)dA1\u0001&!\t\u0019\u0014\u000bB\u0003;\r\t\u0007Q%\u0002\u0003%\u0017\u0002\u001a\u0006CA\u001aU\t\u0015)fA1\u0001&\u0005\u0011yU\u000f\u001e\u0019\u0002\u0013\r|W\u000e]8tK2cU\u0003\u0002-`E\u001a,\u0012!\u0017\t\u00065\u001aYF\r[\u0007\u0002\tA!Q\b\u00180b\u0013\tiVB\u0001\u0003MK:\u001c\bCA\u001a`\t\u0015\u0001wA1\u0001&\u0005\u0005\u0019\u0006CA\u001ac\t\u0015\u0019wA1\u0001&\u0005\u0005\t\u0005\u0003B\u001f]Kz\u0003\"a\r4\u0005\u000b\u001d<!\u0019A\u0013\u0003\u0003Q\u0003B!\u0010/fC\u0006I1m\\7q_N,G\nU\u000b\u0005W>\fh/F\u0001m!\u0015Qf!\u001c:x!\u0011iDL\u001c9\u0011\u0005MzG!\u00021\t\u0005\u0004)\u0003CA\u001ar\t\u0015\u0019\u0007B1\u0001&!\u0011i4/\u001e8\n\u0005Ql!!\u0002)sSNl\u0007CA\u001aw\t\u00159\u0007B1\u0001&!\u0011i4/\u001e9\u0002\u0013\r|W\u000e]8tKBcUC\u0002>\u007f\u0003\u0003\t9!F\u0001|!\u001dQf\u0001`A\u0002\u0003\u0013\u0001B!P:~\u007fB\u00111G \u0003\u0006A&\u0011\r!\n\t\u0004g\u0005\u0005A!B2\n\u0005\u0004)\u0003#B\u001f]\u0003\u000bi\bcA\u001a\u0002\b\u0011)q-\u0003b\u0001KA)Qh]A\u0003\u007f\u0006I1m\\7q_N,\u0007\u000bU\u000b\t\u0003\u001f\t9\"a\u0007\u0002\"U\u0011\u0011\u0011\u0003\t\t5\u001a\t\u0019\"!\b\u0002$A1Qh]A\u000b\u00033\u00012aMA\f\t\u0015\u0001\'B1\u0001&!\r\u0019\u00141\u0004\u0003\u0006G*\u0011\r!\n\t\u0007{M\fy\"!\u0006\u0011\u0007M\n\t\u0003B\u0003h\u0015\t\u0007Q\u0005\u0005\u0004>g\u0006}\u0011\u0011D\u0001\roJLG/\u001a*fa2\f7-\u001a\u000b\u0003\u0003S\u0001B!a\u000b\u000225\u0011\u0011Q\u0006\u0006\u0004\u0003_\u0019\u0015\u0001\u00027b]\u001eLA!a\r\u0002.\t1qJ\u00196fGR\u0004
  #12 = Utf8               composePP
  #13 = Utf8               ()Lshapeless/OpticComposer;
  #14 = Utf8               <S:Ljava/lang/Object;A:Ljava/lang/Object;T:Ljava/lang/Object;>()Lshapeless/OpticComposer<Lshapeless/Prism<TS;TA;>;Lshapeless/Prism<TT;TS;>;>;
  #15 = Utf8               shapeless/OpticComposer$
  #16 = Class              #15            // shapeless/OpticComposer$
  #17 = Utf8               MODULE$
  #18 = Utf8               Lshapeless/OpticComposer$;
  #19 = NameAndType        #17:#18        // MODULE$:Lshapeless/OpticComposer$;
  #20 = Fieldref           #16.#19        // shapeless/OpticComposer$.MODULE$:Lshapeless/OpticComposer$;
  #21 = NameAndType        #12:#13        // composePP:()Lshapeless/OpticComposer;
  #22 = Methodref          #16.#21        // shapeless/OpticComposer$.composePP:()Lshapeless/OpticComposer;
  #23 = Utf8               composePL
  #24 = Utf8               <S:Ljava/lang/Object;A:Ljava/lang/Object;T:Ljava/lang/Object;>()Lshapeless/OpticComposer<Lshapeless/Prism<TS;TA;>;Lshapeless/Lens<TT;TS;>;>;
  #25 = NameAndType        #23:#13        // composePL:()Lshapeless/OpticComposer;
  #26 = Methodref          #16.#25        // shapeless/OpticComposer$.composePL:()Lshapeless/OpticComposer;
  #27 = Utf8               composeLP
  #28 = Utf8               <S:Ljava/lang/Object;A:Ljava/lang/Object;T:Ljava/lang/Object;>()Lshapeless/OpticComposer<Lshapeless/Lens<TS;TA;>;Lshapeless/Prism<TT;TS;>;>;
  #29 = NameAndType        #27:#13        // composeLP:()Lshapeless/OpticComposer;
  #30 = Methodref          #16.#29        // shapeless/OpticComposer$.composeLP:()Lshapeless/OpticComposer;
  #31 = Utf8               composeLL
  #32 = Utf8               <S:Ljava/lang/Object;A:Ljava/lang/Object;T:Ljava/lang/Object;>()Lshapeless/OpticComposer<Lshapeless/Lens<TS;TA;>;Lshapeless/Lens<TT;TS;>;>;
  #33 = NameAndType        #31:#13        // composeLL:()Lshapeless/OpticComposer;
  #34 = Methodref          #16.#33        // shapeless/OpticComposer$.composeLL:()Lshapeless/OpticComposer;
  #35 = Utf8               apply
  #36 = Utf8               (Ljava/lang/Object;Ljava/lang/Object;)Ljava/lang/Object;
  #37 = Utf8               (TL;TR;)Ljava/lang/Object;
  #38 = Utf8               l
  #39 = Utf8               r
  #40 = Utf8               Code
  #41 = Utf8               Signature
  #42 = Utf8               MethodParameters
  #43 = Utf8               SourceFile
  #44 = Utf8               RuntimeVisibleAnnotations
  #45 = Utf8               ScalaInlineInfo
  #46 = Utf8               ScalaSig
{
  public static <S extends java.lang.Object, A extends java.lang.Object, T extends java.lang.Object> shapeless.OpticComposer<shapeless.Prism<S, A>, shapeless.Prism<T, S>> composePP();
    descriptor: ()Lshapeless/OpticComposer;
    flags: (0x0009) ACC_PUBLIC, ACC_STATIC
    Code:
      stack=1, locals=0, args_size=0
         0: getstatic     #20                 // Field shapeless/OpticComposer$.MODULE$:Lshapeless/OpticComposer$;
         3: invokevirtual #22                 // Method shapeless/OpticComposer$.composePP:()Lshapeless/OpticComposer;
         6: areturn
    Signature: #14                          // <S:Ljava/lang/Object;A:Ljava/lang/Object;T:Ljava/lang/Object;>()Lshapeless/OpticComposer<Lshapeless/Prism<TS;TA;>;Lshapeless/Prism<TT;TS;>;>;

  public static <S extends java.lang.Object, A extends java.lang.Object, T extends java.lang.Object> shapeless.OpticComposer<shapeless.Prism<S, A>, shapeless.Lens<T, S>> composePL();
    descriptor: ()Lshapeless/OpticComposer;
    flags: (0x0009) ACC_PUBLIC, ACC_STATIC
    Code:
      stack=1, locals=0, args_size=0
         0: getstatic     #20                 // Field shapeless/OpticComposer$.MODULE$:Lshapeless/OpticComposer$;
         3: invokevirtual #26                 // Method shapeless/OpticComposer$.composePL:()Lshapeless/OpticComposer;
         6: areturn
    Signature: #24                          // <S:Ljava/lang/Object;A:Ljava/lang/Object;T:Ljava/lang/Object;>()Lshapeless/OpticComposer<Lshapeless/Prism<TS;TA;>;Lshapeless/Lens<TT;TS;>;>;

  public static <S extends java.lang.Object, A extends java.lang.Object, T extends java.lang.Object> shapeless.OpticComposer<shapeless.Lens<S, A>, shapeless.Prism<T, S>> composeLP();
    descriptor: ()Lshapeless/OpticComposer;
    flags: (0x0009) ACC_PUBLIC, ACC_STATIC
    Code:
      stack=1, locals=0, args_size=0
         0: getstatic     #20                 // Field shapeless/OpticComposer$.MODULE$:Lshapeless/OpticComposer$;
         3: invokevirtual #30                 // Method shapeless/OpticComposer$.composeLP:()Lshapeless/OpticComposer;
         6: areturn
    Signature: #28                          // <S:Ljava/lang/Object;A:Ljava/lang/Object;T:Ljava/lang/Object;>()Lshapeless/OpticComposer<Lshapeless/Lens<TS;TA;>;Lshapeless/Prism<TT;TS;>;>;

  public static <S extends java.lang.Object, A extends java.lang.Object, T extends java.lang.Object> shapeless.OpticComposer<shapeless.Lens<S, A>, shapeless.Lens<T, S>> composeLL();
    descriptor: ()Lshapeless/OpticComposer;
    flags: (0x0009) ACC_PUBLIC, ACC_STATIC
    Code:
      stack=1, locals=0, args_size=0
         0: getstatic     #20                 // Field shapeless/OpticComposer$.MODULE$:Lshapeless/OpticComposer$;
         3: invokevirtual #34                 // Method shapeless/OpticComposer$.composeLL:()Lshapeless/OpticComposer;
         6: areturn
    Signature: #32                          // <S:Ljava/lang/Object;A:Ljava/lang/Object;T:Ljava/lang/Object;>()Lshapeless/OpticComposer<Lshapeless/Lens<TS;TA;>;Lshapeless/Lens<TT;TS;>;>;

  public abstract java.lang.Object apply(L, R);
    descriptor: (Ljava/lang/Object;Ljava/lang/Object;)Ljava/lang/Object;
    flags: (0x0401) ACC_PUBLIC, ACC_ABSTRACT
    Signature: #37                          // (TL;TR;)Ljava/lang/Object;
    MethodParameters:
      Name                           Flags
      l                              final
      r                              final
}
Signature: #3                           // <L:Ljava/lang/Object;R:Ljava/lang/Object;>Ljava/lang/Object;Ljava/io/Serializable;
SourceFile: "lenses.scala"
RuntimeVisibleAnnotations:
  0: #9(#10=s#11)
    scala.reflect.ScalaSignature(
      bytes="\u0006\u0005\u0005Uba\u0002\u0007\u000e!\u0003\r\n\u0001\u0005\u0003\u0006I\u0001\u0011\t!\n\u0005\u0006Y\u00011\t!L\u0004\u0006w5A\t\u0001\u0010\u0004\u0006\u00195A\tA\u0010\u0005\u0006\r\u0012!\taR\u0003\u0005\u0011\u0012\u0001\u0011\nC\u0003W\t\u0011\rq\u000bC\u0003j\t\u0011\r!\u000eC\u0003y\t\u0011\r\u0011\u0010C\u0004\u0002\f\u0011!\u0019!!\u0004\t\u0013\u0005\u0015B!!A\u0005\n\u0005\u001d\"!D(qi&\u001c7i\\7q_N,\'OC\u0001\u000f\u0003%\u0019\b.\u00199fY\u0016\u001c8o\u0001\u0001\u0016\u0007E!\u0014hE\u0002\u0001%a\u0001\"a\u0005\f\u000e\u0003QQ\u0011!F\u0001\u0006g\u000e\fG.Y\u0005\u0003/Q\u0011a!\u00118z%\u00164\u0007CA\r\"\u001d\tQrD\u0004\u0002\u001c=5\tAD\u0003\u0002\u001e\u001f\u00051AH]8pizJ\u0011!F\u0005\u0003AQ\tq\u0001]1dW\u0006<W-\u0003\u0002#G\ta1+\u001a:jC2L\'0\u00192mK*\u0011\u0001\u0005\u0006\u0002\u0004\u001fV$\u0018C\u0001\u0014*!\t\u0019r%\u0003\u0002))\t9aj\u001c;iS:<\u0007CA\n+\u0013\tYCCA\u0002B]f\fQ!\u00199qYf$2A\f\u00197!\ty\u0013!D\u0001\u0001\u0011\u0015\t$\u00011\u00013\u0003\u0005a\u0007CA\u001a5\u0019\u0001!Q!\u000e\u0001C\u0002\u0015\u0012\u0011\u0001\u0014\u0005\u0006o\t\u0001\r\u0001O\u0001\u0002eB\u00111\'\u000f\u0003\u0006u\u0001\u0011\r!\n\u0002\u0002%\u0006iq\n\u001d;jG\u000e{W\u000e]8tKJ\u0004\"!\u0010\u0003\u000e\u00035\u00192\u0001\u0002\n@!\t\u0001U)D\u0001B\u0015\t\u00115)\u0001\u0002j_*\tA)\u0001\u0003kCZ\f\u0017B\u0001\u0012B\u0003\u0019a\u0014N\\5u}Q\tAHA\u0002Bkb,BAS(R)J\u00111*\u0014\u0004\u0005\u0019\u0012\u0001!J\u0001\u0007=e\u00164\u0017N\\3nK:$h\b\u0005\u0003>\u00019\u0003\u0006CA\u001aP\t\u0015)dA1\u0001&!\t\u0019\u0014\u000bB\u0003;\r\t\u0007Q%\u0002\u0003%\u0017\u0002\u001a\u0006CA\u001aU\t\u0015)fA1\u0001&\u0005\u0011yU\u000f\u001e\u0019\u0002\u0013\r|W\u000e]8tK2cU\u0003\u0002-`E\u001a,\u0012!\u0017\t\u00065\u001aYF\r[\u0007\u0002\tA!Q\b\u00180b\u0013\tiVB\u0001\u0003MK:\u001c\bCA\u001a`\t\u0015\u0001wA1\u0001&\u0005\u0005\u0019\u0006CA\u001ac\t\u0015\u0019wA1\u0001&\u0005\u0005\t\u0005\u0003B\u001f]Kz\u0003\"a\r4\u0005\u000b\u001d<!\u0019A\u0013\u0003\u0003Q\u0003B!\u0010/fC\u0006I1m\\7q_N,G\nU\u000b\u0005W>\fh/F\u0001m!\u0015Qf!\u001c:x!\u0011iDL\u001c9\u0011\u0005MzG!\u00021\t\u0005\u0004)\u0003CA\u001ar\t\u0015\u0019\u0007B1\u0001&!\u0011i4/\u001e8\n\u0005Ql!!\u0002)sSNl\u0007CA\u001aw\t\u00159\u0007B1\u0001&!\u0011i4/\u001e9\u0002\u0013\r|W\u000e]8tKBcUC\u0002>\u007f\u0003\u0003\t9!F\u0001|!\u001dQf\u0001`A\u0002\u0003\u0013\u0001B!P:~\u007fB\u00111G \u0003\u0006A&\u0011\r!\n\t\u0004g\u0005\u0005A!B2\n\u0005\u0004)\u0003#B\u001f]\u0003\u000bi\bcA\u001a\u0002\b\u0011)q-\u0003b\u0001KA)Qh]A\u0003\u007f\u0006I1m\\7q_N,\u0007\u000bU\u000b\t\u0003\u001f\t9\"a\u0007\u0002\"U\u0011\u0011\u0011\u0003\t\t5\u001a\t\u0019\"!\b\u0002$A1Qh]A\u000b\u00033\u00012aMA\f\t\u0015\u0001\'B1\u0001&!\r\u0019\u00141\u0004\u0003\u0006G*\u0011\r!\n\t\u0007{M\fy\"!\u0006\u0011\u0007M\n\t\u0003B\u0003h\u0015\t\u0007Q\u0005\u0005\u0004>g\u0006}\u0011\u0011D\u0001\roJLG/\u001a*fa2\f7-\u001a\u000b\u0003\u0003S\u0001B!a\u000b\u000225\u0011\u0011Q\u0006\u0006\u0004\u0003_\u0019\u0015\u0001\u00027b]\u001eLA!a\r\u0002.\t1qJ\u00196fGR\u0004"
    )
  ScalaInlineInfo: length = 0x9 (unknown attribute)
   01 00 00 01 00 23 00 24 00
  ScalaSig: length = 0x3 (unknown attribute)
   05 02 00
