Classfile /Users/mw/Projects/slang-braindump/.jar/jar11/assemble/slang-braindump/assemble/content/shapeless/OpticComposer$.class
  Last modified May 29, 2022; size 1835 bytes
  SHA-256 checksum 0b9001e8455cacb42e571dcbb5d77d0722443a9c654a304b37a4bb7ae8512845
  Compiled from "lenses.scala"
public final class shapeless.OpticComposer$ implements java.io.Serializable
  minor version: 0
  major version: 52
  flags: (0x0031) ACC_PUBLIC, ACC_FINAL, ACC_SUPER
  this_class: #2                          // shapeless/OpticComposer$
  super_class: #4                         // java/lang/Object
  interfaces: 1, fields: 1, methods: 7, attributes: 4
Constant pool:
   #1 = Utf8               shapeless/OpticComposer$
   #2 = Class              #1             // shapeless/OpticComposer$
   #3 = Utf8               java/lang/Object
   #4 = Class              #3             // java/lang/Object
   #5 = Utf8               java/io/Serializable
   #6 = Class              #5             // java/io/Serializable
   #7 = Utf8               lenses.scala
   #8 = Utf8               shapeless/OpticComposer$$anon$14
   #9 = Class              #8             // shapeless/OpticComposer$$anon$14
  #10 = Utf8               shapeless/OpticComposer$$anon$15
  #11 = Class              #10            // shapeless/OpticComposer$$anon$15
  #12 = Utf8               shapeless/OpticComposer$$anon$16
  #13 = Class              #12            // shapeless/OpticComposer$$anon$16
  #14 = Utf8               shapeless/OpticComposer$$anon$17
  #15 = Class              #14            // shapeless/OpticComposer$$anon$17
  #16 = Utf8               MODULE$
  #17 = Utf8               Lshapeless/OpticComposer$;
  #18 = Utf8               <clinit>
  #19 = Utf8               ()V
  #20 = Utf8               <init>
  #21 = NameAndType        #20:#19        // "<init>":()V
  #22 = Methodref          #2.#21         // shapeless/OpticComposer$."<init>":()V
  #23 = NameAndType        #16:#17        // MODULE$:Lshapeless/OpticComposer$;
  #24 = Fieldref           #2.#23         // shapeless/OpticComposer$.MODULE$:Lshapeless/OpticComposer$;
  #25 = Utf8               composeLL
  #26 = Utf8               ()Lshapeless/OpticComposer;
  #27 = Utf8               <S:Ljava/lang/Object;A:Ljava/lang/Object;T:Ljava/lang/Object;>()Lshapeless/OpticComposer<Lshapeless/Lens<TS;TA;>;Lshapeless/Lens<TT;TS;>;>;
  #28 = Methodref          #9.#21         // shapeless/OpticComposer$$anon$14."<init>":()V
  #29 = Utf8               this
  #30 = Utf8               composeLP
  #31 = Utf8               <S:Ljava/lang/Object;A:Ljava/lang/Object;T:Ljava/lang/Object;>()Lshapeless/OpticComposer<Lshapeless/Lens<TS;TA;>;Lshapeless/Prism<TT;TS;>;>;
  #32 = Methodref          #11.#21        // shapeless/OpticComposer$$anon$15."<init>":()V
  #33 = Utf8               composePL
  #34 = Utf8               <S:Ljava/lang/Object;A:Ljava/lang/Object;T:Ljava/lang/Object;>()Lshapeless/OpticComposer<Lshapeless/Prism<TS;TA;>;Lshapeless/Lens<TT;TS;>;>;
  #35 = Methodref          #13.#21        // shapeless/OpticComposer$$anon$16."<init>":()V
  #36 = Utf8               composePP
  #37 = Utf8               <S:Ljava/lang/Object;A:Ljava/lang/Object;T:Ljava/lang/Object;>()Lshapeless/OpticComposer<Lshapeless/Prism<TS;TA;>;Lshapeless/Prism<TT;TS;>;>;
  #38 = Methodref          #15.#21        // shapeless/OpticComposer$$anon$17."<init>":()V
  #39 = Utf8               writeReplace
  #40 = Utf8               ()Ljava/lang/Object;
  #41 = Utf8               scala/runtime/ModuleSerializationProxy
  #42 = Class              #41            // scala/runtime/ModuleSerializationProxy
  #43 = Utf8               (Ljava/lang/Class;)V
  #44 = NameAndType        #20:#43        // "<init>":(Ljava/lang/Class;)V
  #45 = Methodref          #42.#44        // scala/runtime/ModuleSerializationProxy."<init>":(Ljava/lang/Class;)V
  #46 = Methodref          #4.#21         // java/lang/Object."<init>":()V
  #47 = Utf8               Code
  #48 = Utf8               LineNumberTable
  #49 = Utf8               LocalVariableTable
  #50 = Utf8               Signature
  #51 = Utf8               InnerClasses
  #52 = Utf8               SourceFile
  #53 = Utf8               ScalaInlineInfo
  #54 = Utf8               Scala
{
  public static final shapeless.OpticComposer$ MODULE$;
    descriptor: Lshapeless/OpticComposer$;
    flags: (0x0019) ACC_PUBLIC, ACC_STATIC, ACC_FINAL

  public static {};
    descriptor: ()V
    flags: (0x0009) ACC_PUBLIC, ACC_STATIC
    Code:
      stack=2, locals=0, args_size=0
         0: new           #2                  // class shapeless/OpticComposer$
         3: dup
         4: invokespecial #22                 // Method "<init>":()V
         7: putstatic     #24                 // Field MODULE$:Lshapeless/OpticComposer$;
        10: return
      LineNumberTable:
        line 209: 0

  public <S extends java.lang.Object, A extends java.lang.Object, T extends java.lang.Object> shapeless.OpticComposer<shapeless.Lens<S, A>, shapeless.Lens<T, S>> composeLL();
    descriptor: ()Lshapeless/OpticComposer;
    flags: (0x0001) ACC_PUBLIC
    Code:
      stack=2, locals=1, args_size=1
         0: new           #9                  // class shapeless/OpticComposer$$anon$14
         3: dup
         4: invokespecial #28                 // Method shapeless/OpticComposer$$anon$14."<init>":()V
         7: areturn
      LineNumberTable:
        line 213: 0
      LocalVariableTable:
        Start  Length  Slot  Name   Signature
            0       8     0  this   Lshapeless/OpticComposer$;
    Signature: #27                          // <S:Ljava/lang/Object;A:Ljava/lang/Object;T:Ljava/lang/Object;>()Lshapeless/OpticComposer<Lshapeless/Lens<TS;TA;>;Lshapeless/Lens<TT;TS;>;>;

  public <S extends java.lang.Object, A extends java.lang.Object, T extends java.lang.Object> shapeless.OpticComposer<shapeless.Lens<S, A>, shapeless.Prism<T, S>> composeLP();
    descriptor: ()Lshapeless/OpticComposer;
    flags: (0x0001) ACC_PUBLIC
    Code:
      stack=2, locals=1, args_size=1
         0: new           #11                 // class shapeless/OpticComposer$$anon$15
         3: dup
         4: invokespecial #32                 // Method shapeless/OpticComposer$$anon$15."<init>":()V
         7: areturn
      LineNumberTable:
        line 219: 0
      LocalVariableTable:
        Start  Length  Slot  Name   Signature
            0       8     0  this   Lshapeless/OpticComposer$;
    Signature: #31                          // <S:Ljava/lang/Object;A:Ljava/lang/Object;T:Ljava/lang/Object;>()Lshapeless/OpticComposer<Lshapeless/Lens<TS;TA;>;Lshapeless/Prism<TT;TS;>;>;

  public <S extends java.lang.Object, A extends java.lang.Object, T extends java.lang.Object> shapeless.OpticComposer<shapeless.Prism<S, A>, shapeless.Lens<T, S>> composePL();
    descriptor: ()Lshapeless/OpticComposer;
    flags: (0x0001) ACC_PUBLIC
    Code:
      stack=2, locals=1, args_size=1
         0: new           #13                 // class shapeless/OpticComposer$$anon$16
         3: dup
         4: invokespecial #35                 // Method shapeless/OpticComposer$$anon$16."<init>":()V
         7: areturn
      LineNumberTable:
        line 225: 0
      LocalVariableTable:
        Start  Length  Slot  Name   Signature
            0       8     0  this   Lshapeless/OpticComposer$;
    Signature: #34                          // <S:Ljava/lang/Object;A:Ljava/lang/Object;T:Ljava/lang/Object;>()Lshapeless/OpticComposer<Lshapeless/Prism<TS;TA;>;Lshapeless/Lens<TT;TS;>;>;

  public <S extends java.lang.Object, A extends java.lang.Object, T extends java.lang.Object> shapeless.OpticComposer<shapeless.Prism<S, A>, shapeless.Prism<T, S>> composePP();
    descriptor: ()Lshapeless/OpticComposer;
    flags: (0x0001) ACC_PUBLIC
    Code:
      stack=2, locals=1, args_size=1
         0: new           #15                 // class shapeless/OpticComposer$$anon$17
         3: dup
         4: invokespecial #38                 // Method shapeless/OpticComposer$$anon$17."<init>":()V
         7: areturn
      LineNumberTable:
        line 231: 0
      LocalVariableTable:
        Start  Length  Slot  Name   Signature
            0       8     0  this   Lshapeless/OpticComposer$;
    Signature: #37                          // <S:Ljava/lang/Object;A:Ljava/lang/Object;T:Ljava/lang/Object;>()Lshapeless/OpticComposer<Lshapeless/Prism<TS;TA;>;Lshapeless/Prism<TT;TS;>;>;

  private java.lang.Object writeReplace();
    descriptor: ()Ljava/lang/Object;
    flags: (0x0002) ACC_PRIVATE
    Code:
      stack=3, locals=1, args_size=1
         0: new           #42                 // class scala/runtime/ModuleSerializationProxy
         3: dup
         4: ldc           #2                  // class shapeless/OpticComposer$
         6: invokespecial #45                 // Method scala/runtime/ModuleSerializationProxy."<init>":(Ljava/lang/Class;)V
         9: areturn
      LineNumberTable:
        line 209: 0
      LocalVariableTable:
        Start  Length  Slot  Name   Signature
            0      10     0  this   Lshapeless/OpticComposer$;

  private shapeless.OpticComposer$();
    descriptor: ()V
    flags: (0x0002) ACC_PRIVATE
    Code:
      stack=1, locals=1, args_size=1
         0: aload_0
         1: invokespecial #46                 // Method java/lang/Object."<init>":()V
         4: return
      LineNumberTable:
        line 237: 0
        line 209: 4
      LocalVariableTable:
        Start  Length  Slot  Name   Signature
            0       5     0  this   Lshapeless/OpticComposer$;
}
InnerClasses:
  public final #9;                        // class shapeless/OpticComposer$$anon$14
  public final #11;                       // class shapeless/OpticComposer$$anon$15
  public final #13;                       // class shapeless/OpticComposer$$anon$16
  public final #15;                       // class shapeless/OpticComposer$$anon$17
SourceFile: "lenses.scala"
  ScalaInlineInfo: length = 0x22 (unknown attribute)
   01 01 00 06 00 14 00 13 01 00 19 00 1A 01 00 1E
   00 1A 01 00 21 00 1A 01 00 24 00 1A 01 00 27 00
   28 01
  Scala: length = 0x0 (unknown attribute)

