Classfile /Users/mw/Projects/slang-braindump/.jar/jar11/assemble/slang-braindump/assemble/content/shapeless/Path$.class
  Last modified May 29, 2022; size 1883 bytes
  SHA-256 checksum f47f0a76bf700b7dfb7ad3b3b979fb733d999660f1ec440e9dceeed4673dbd21
  Compiled from "lenses.scala"
public final class shapeless.Path$ extends java.lang.Object implements shapeless.Path<shapeless.HNil>
  minor version: 0
  major version: 52
  flags: (0x0031) ACC_PUBLIC, ACC_FINAL, ACC_SUPER
  this_class: #2                          // shapeless/Path$
  super_class: #5                         // java/lang/Object
  interfaces: 1, fields: 1, methods: 5, attributes: 4
Constant pool:
   #1 = Utf8               shapeless/Path$
   #2 = Class              #1             // shapeless/Path$
   #3 = Utf8               Ljava/lang/Object;Lshapeless/Path<Lshapeless/HNil;>;
   #4 = Utf8               java/lang/Object
   #5 = Class              #4             // java/lang/Object
   #6 = Utf8               shapeless/Path
   #7 = Class              #6             // shapeless/Path
   #8 = Utf8               lenses.scala
   #9 = Utf8               MODULE$
  #10 = Utf8               Lshapeless/Path$;
  #11 = Utf8               <clinit>
  #12 = Utf8               ()V
  #13 = Utf8               <init>
  #14 = NameAndType        #13:#12        // "<init>":()V
  #15 = Methodref          #2.#14         // shapeless/Path$."<init>":()V
  #16 = NameAndType        #9:#10         // MODULE$:Lshapeless/Path$;
  #17 = Fieldref           #2.#16         // shapeless/Path$.MODULE$:Lshapeless/Path$;
  #18 = Utf8               shapeless/LPPath
  #19 = Class              #18            // shapeless/LPPath
  #20 = Utf8               $init$
  #21 = Utf8               (Lshapeless/LPPath;)V
  #22 = NameAndType        #20:#21        // $init$:(Lshapeless/LPPath;)V
  #23 = InterfaceMethodref #19.#22        // shapeless/LPPath.$init$:(Lshapeless/LPPath;)V
  #24 = Utf8               (Lshapeless/Path;)V
  #25 = NameAndType        #20:#24        // $init$:(Lshapeless/Path;)V
  #26 = InterfaceMethodref #7.#25         // shapeless/Path.$init$:(Lshapeless/Path;)V
  #27 = Utf8               apply
  #28 = Utf8               ()Lshapeless/Path;
  #29 = Utf8               <H:Ljava/lang/Object;>()Lshapeless/Path<Lshapeless/$colon$colon<Lshapeless/Coselect<TH;>;Lshapeless/HNil;>;>;
  #30 = Utf8               apply$
  #31 = Utf8               (Lshapeless/Path;)Lshapeless/Path;
  #32 = NameAndType        #30:#31        // apply$:(Lshapeless/Path;)Lshapeless/Path;
  #33 = InterfaceMethodref #7.#32         // shapeless/Path.apply$:(Lshapeless/Path;)Lshapeless/Path;
  #34 = Utf8               this
  #35 = Utf8               selectDynamic
  #36 = Utf8               (Ljava/lang/String;Lshapeless/Segment;)Lshapeless/Path;
  #37 = Utf8               (Ljava/lang/String;Lshapeless/Segment<+Ljava/lang/String;Lscala/runtime/Nothing$;Lshapeless/HNil;>;)Lshapeless/Path<Lshapeless/HList;>;
  #38 = Utf8               h
  #39 = Utf8               segment
  #40 = Utf8               selectDynamic$
  #41 = Utf8               (Lshapeless/Path;Ljava/lang/String;Lshapeless/Segment;)Lshapeless/Path;
  #42 = NameAndType        #40:#41        // selectDynamic$:(Lshapeless/Path;Ljava/lang/String;Lshapeless/Segment;)Lshapeless/Path;
  #43 = InterfaceMethodref #7.#42         // shapeless/Path.selectDynamic$:(Lshapeless/Path;Ljava/lang/String;Lshapeless/Segment;)Lshapeless/Path;
  #44 = Utf8               Ljava/lang/String;
  #45 = Utf8               Lshapeless/Segment;
  #46 = Utf8               (Ljava/lang/String;Lshapeless/Segment;Lscala/DummyImplicit;)Lshapeless/Path;
  #47 = Utf8               <H:Ljava/lang/Object;>(Ljava/lang/String;Lshapeless/Segment<+Ljava/lang/String;TH;Lshapeless/HNil;>;Lscala/DummyImplicit;)Lshapeless/Path<Lshapeless/HList;>;
  #48 = Utf8               dummy
  #49 = Utf8               (Lshapeless/LPPath;Ljava/lang/String;Lshapeless/Segment;Lscala/DummyImplicit;)Lshapeless/Path;
  #50 = NameAndType        #40:#49        // selectDynamic$:(Lshapeless/LPPath;Ljava/lang/String;Lshapeless/Segment;Lscala/DummyImplicit;)Lshapeless/Path;
  #51 = InterfaceMethodref #19.#50        // shapeless/LPPath.selectDynamic$:(Lshapeless/LPPath;Ljava/lang/String;Lshapeless/Segment;Lscala/DummyImplicit;)Lshapeless/Path;
  #52 = Utf8               Lscala/DummyImplicit;
  #53 = Methodref          #5.#14         // java/lang/Object."<init>":()V
  #54 = Utf8               Code
  #55 = Utf8               LineNumberTable
  #56 = Utf8               LocalVariableTable
  #57 = Utf8               Signature
  #58 = Utf8               MethodParameters
  #59 = Utf8               SourceFile
  #60 = Utf8               ScalaInlineInfo
  #61 = Utf8               Scala
{
  public static final shapeless.Path$ MODULE$;
    descriptor: Lshapeless/Path$;
    flags: (0x0019) ACC_PUBLIC, ACC_STATIC, ACC_FINAL

  public static {};
    descriptor: ()V
    flags: (0x0009) ACC_PUBLIC, ACC_STATIC
    Code:
      stack=2, locals=0, args_size=0
         0: new           #2                  // class shapeless/Path$
         3: dup
         4: invokespecial #15                 // Method "<init>":()V
         7: putstatic     #17                 // Field MODULE$:Lshapeless/Path$;
        10: getstatic     #17                 // Field MODULE$:Lshapeless/Path$;
        13: invokestatic  #23                 // InterfaceMethod shapeless/LPPath.$init$:(Lshapeless/LPPath;)V
        16: getstatic     #17                 // Field MODULE$:Lshapeless/Path$;
        19: invokestatic  #26                 // InterfaceMethod shapeless/Path.$init$:(Lshapeless/Path;)V
        22: return
      LineNumberTable:
        line 570: 0

  public <H extends java.lang.Object> shapeless.Path<shapeless.$colon$colon<shapeless.Coselect<H>, shapeless.HNil>> apply();
    descriptor: ()Lshapeless/Path;
    flags: (0x0001) ACC_PUBLIC
    Code:
      stack=1, locals=1, args_size=1
         0: aload_0
         1: invokestatic  #33                 // InterfaceMethod shapeless/Path.apply$:(Lshapeless/Path;)Lshapeless/Path;
         4: areturn
      LineNumberTable:
        line 570: 0
      LocalVariableTable:
        Start  Length  Slot  Name   Signature
            0       5     0  this   Lshapeless/Path$;
    Signature: #29                          // <H:Ljava/lang/Object;>()Lshapeless/Path<Lshapeless/$colon$colon<Lshapeless/Coselect<TH;>;Lshapeless/HNil;>;>;

  public shapeless.Path<shapeless.HList> selectDynamic(java.lang.String, shapeless.Segment<? extends java.lang.String, scala.runtime.Nothing$, shapeless.HNil>);
    descriptor: (Ljava/lang/String;Lshapeless/Segment;)Lshapeless/Path;
    flags: (0x0001) ACC_PUBLIC
    Code:
      stack=3, locals=3, args_size=3
         0: aload_0
         1: aload_1
         2: aload_2
         3: invokestatic  #43                 // InterfaceMethod shapeless/Path.selectDynamic$:(Lshapeless/Path;Ljava/lang/String;Lshapeless/Segment;)Lshapeless/Path;
         6: areturn
      LineNumberTable:
        line 570: 0
      LocalVariableTable:
        Start  Length  Slot  Name   Signature
            0       7     0  this   Lshapeless/Path$;
            0       7     1     h   Ljava/lang/String;
            0       7     2 segment   Lshapeless/Segment;
    Signature: #37                          // (Ljava/lang/String;Lshapeless/Segment<+Ljava/lang/String;Lscala/runtime/Nothing$;Lshapeless/HNil;>;)Lshapeless/Path<Lshapeless/HList;>;
    MethodParameters:
      Name                           Flags
      h                              final
      segment                        final

  public <H extends java.lang.Object> shapeless.Path<shapeless.HList> selectDynamic(java.lang.String, shapeless.Segment<? extends java.lang.String, H, shapeless.HNil>, scala.DummyImplicit);
    descriptor: (Ljava/lang/String;Lshapeless/Segment;Lscala/DummyImplicit;)Lshapeless/Path;
    flags: (0x0001) ACC_PUBLIC
    Code:
      stack=4, locals=4, args_size=4
         0: aload_0
         1: aload_1
         2: aload_2
         3: aload_3
         4: invokestatic  #51                 // InterfaceMethod shapeless/LPPath.selectDynamic$:(Lshapeless/LPPath;Ljava/lang/String;Lshapeless/Segment;Lscala/DummyImplicit;)Lshapeless/Path;
         7: areturn
      LineNumberTable:
        line 570: 0
      LocalVariableTable:
        Start  Length  Slot  Name   Signature
            0       8     0  this   Lshapeless/Path$;
            0       8     1     h   Ljava/lang/String;
            0       8     2 segment   Lshapeless/Segment;
            0       8     3 dummy   Lscala/DummyImplicit;
    Signature: #47                          // <H:Ljava/lang/Object;>(Ljava/lang/String;Lshapeless/Segment<+Ljava/lang/String;TH;Lshapeless/HNil;>;Lscala/DummyImplicit;)Lshapeless/Path<Lshapeless/HList;>;
    MethodParameters:
      Name                           Flags
      h                              final
      segment                        final
      dummy                          final

  private shapeless.Path$();
    descriptor: ()V
    flags: (0x0002) ACC_PRIVATE
    Code:
      stack=1, locals=1, args_size=1
         0: aload_0
         1: invokespecial #53                 // Method java/lang/Object."<init>":()V
         4: return
      LineNumberTable:
        line 570: 0
      LocalVariableTable:
        Start  Length  Slot  Name   Signature
            0       5     0  this   Lshapeless/Path$;
}
Signature: #3                           // Ljava/lang/Object;Lshapeless/Path<Lshapeless/HNil;>;
SourceFile: "lenses.scala"
  ScalaInlineInfo: length = 0x18 (unknown attribute)
   01 01 00 04 00 0D 00 0C 01 00 1B 00 1C 01 00 23
   00 24 01 00 23 00 2E 01
  Scala: length = 0x0 (unknown attribute)

