Classfile /Users/mw/Projects/slang-braindump/.jar/jar11/assemble/slang-braindump/assemble/content/shapeless/PolyNBuilders$Function15TypeAt$$anon$60.class
  Last modified May 29, 2022; size 1607 bytes
  SHA-256 checksum c19e4f84c297d21f55474496dbb6a7414e83ad672e117e9f4d00fe8f15d0ed86
  Compiled from "polynbuilders.scala"
public final class shapeless.PolyNBuilders$Function15TypeAt$$anon$60 extends java.lang.Object implements shapeless.PolyNBuilders$Function15TypeAt<A, B, C, D, E, F, G, H, I, J, K, L, M, N, O, Out, shapeless.$colon$colon<Head, Tail>>
  minor version: 0
  major version: 52
  flags: (0x0031) ACC_PUBLIC, ACC_FINAL, ACC_SUPER
  this_class: #2                          // shapeless/PolyNBuilders$Function15TypeAt$$anon$60
  super_class: #5                         // java/lang/Object
  interfaces: 1, fields: 1, methods: 3, attributes: 6
Constant pool:
   #1 = Utf8               shapeless/PolyNBuilders$Function15TypeAt$$anon$60
   #2 = Class              #1             // shapeless/PolyNBuilders$Function15TypeAt$$anon$60
   #3 = Utf8               Ljava/lang/Object;Lshapeless/PolyNBuilders$Function15TypeAt<TA;TB;TC;TD;TE;TF;TG;TH;TI;TJ;TK;TL;TM;TN;TO;TOut;Lshapeless/$colon$colon<THead;TTail;>;>;
   #4 = Utf8               java/lang/Object
   #5 = Class              #4             // java/lang/Object
   #6 = Utf8               shapeless/PolyNBuilders$Function15TypeAt
   #7 = Class              #6             // shapeless/PolyNBuilders$Function15TypeAt
   #8 = Utf8               polynbuilders.scala
   #9 = Utf8               shapeless/PolyNBuilders$Function15TypeAt$
  #10 = Class              #9             // shapeless/PolyNBuilders$Function15TypeAt$
  #11 = Utf8               atOther
  #12 = Utf8               (Lshapeless/PolyNBuilders$Function15TypeAt;)Lshapeless/PolyNBuilders$Function15TypeAt;
  #13 = NameAndType        #11:#12        // atOther:(Lshapeless/PolyNBuilders$Function15TypeAt;)Lshapeless/PolyNBuilders$Function15TypeAt;
  #14 = Utf8               shapeless/PolyNBuilders
  #15 = Class              #14            // shapeless/PolyNBuilders
  #16 = Utf8               Function15TypeAt
  #17 = Utf8               Function15TypeAt$
  #18 = Utf8               tprev$15
  #19 = Utf8               Lshapeless/PolyNBuilders$Function15TypeAt;
  #20 = Utf8               apply
  #21 = Utf8               (Lshapeless/$colon$colon;)Lscala/Function15;
  #22 = Utf8               (Lshapeless/$colon$colon<THead;TTail;>;)Lscala/Function15<TA;TB;TC;TD;TE;TF;TG;TH;TI;TJ;TK;TL;TM;TN;TO;TOut;>;
  #23 = Utf8               l
  #24 = NameAndType        #18:#19        // tprev$15:Lshapeless/PolyNBuilders$Function15TypeAt;
  #25 = Fieldref           #2.#24         // shapeless/PolyNBuilders$Function15TypeAt$$anon$60.tprev$15:Lshapeless/PolyNBuilders$Function15TypeAt;
  #26 = Utf8               shapeless/$colon$colon
  #27 = Class              #26            // shapeless/$colon$colon
  #28 = Utf8               tail
  #29 = Utf8               ()Lshapeless/HList;
  #30 = NameAndType        #28:#29        // tail:()Lshapeless/HList;
  #31 = Methodref          #27.#30        // shapeless/$colon$colon.tail:()Lshapeless/HList;
  #32 = Utf8               (Lshapeless/HList;)Lscala/Function15;
  #33 = NameAndType        #20:#32        // apply:(Lshapeless/HList;)Lscala/Function15;
  #34 = InterfaceMethodref #7.#33         // shapeless/PolyNBuilders$Function15TypeAt.apply:(Lshapeless/HList;)Lscala/Function15;
  #35 = Utf8               this
  #36 = Utf8               Lshapeless/PolyNBuilders$Function15TypeAt$$anon$60;
  #37 = Utf8               Lshapeless/$colon$colon;
  #38 = NameAndType        #20:#21        // apply:(Lshapeless/$colon$colon;)Lscala/Function15;
  #39 = Methodref          #2.#38         // shapeless/PolyNBuilders$Function15TypeAt$$anon$60.apply:(Lshapeless/$colon$colon;)Lscala/Function15;
  #40 = Utf8               Lshapeless/HList;
  #41 = Utf8               <init>
  #42 = Utf8               (Lshapeless/PolyNBuilders$Function15TypeAt;)V
  #43 = Utf8               ()V
  #44 = NameAndType        #41:#43        // "<init>":()V
  #45 = Methodref          #5.#44         // java/lang/Object."<init>":()V
  #46 = Utf8               Code
  #47 = Utf8               LineNumberTable
  #48 = Utf8               LocalVariableTable
  #49 = Utf8               Signature
  #50 = Utf8               MethodParameters
  #51 = Utf8               InnerClasses
  #52 = Utf8               EnclosingMethod
  #53 = Utf8               SourceFile
  #54 = Utf8               ScalaInlineInfo
  #55 = Utf8               Scala
{
  private final shapeless.PolyNBuilders$Function15TypeAt tprev$15;
    descriptor: Lshapeless/PolyNBuilders$Function15TypeAt;
    flags: (0x0012) ACC_PRIVATE, ACC_FINAL

  public scala.Function15<A, B, C, D, E, F, G, H, I, J, K, L, M, N, O, Out> apply(shapeless.$colon$colon<Head, Tail>);
    descriptor: (Lshapeless/$colon$colon;)Lscala/Function15;
    flags: (0x0001) ACC_PUBLIC
    Code:
      stack=2, locals=2, args_size=2
         0: aload_0
         1: getfield      #25                 // Field tprev$15:Lshapeless/PolyNBuilders$Function15TypeAt;
         4: aload_1
         5: invokevirtual #31                 // Method shapeless/$colon$colon.tail:()Lshapeless/HList;
         8: invokeinterface #34,  2           // InterfaceMethod shapeless/PolyNBuilders$Function15TypeAt.apply:(Lshapeless/HList;)Lscala/Function15;
        13: areturn
      LineNumberTable:
        line 639: 0
      LocalVariableTable:
        Start  Length  Slot  Name   Signature
            0      14     0  this   Lshapeless/PolyNBuilders$Function15TypeAt$$anon$60;
            0      14     1     l   Lshapeless/$colon$colon;
    Signature: #22                          // (Lshapeless/$colon$colon<THead;TTail;>;)Lscala/Function15<TA;TB;TC;TD;TE;TF;TG;TH;TI;TJ;TK;TL;TM;TN;TO;TOut;>;
    MethodParameters:
      Name                           Flags
      l                              final

  public scala.Function15 apply(shapeless.HList);
    descriptor: (Lshapeless/HList;)Lscala/Function15;
    flags: (0x1041) ACC_PUBLIC, ACC_BRIDGE, ACC_SYNTHETIC
    Code:
      stack=2, locals=2, args_size=2
         0: aload_0
         1: aload_1
         2: checkcast     #27                 // class shapeless/$colon$colon
         5: invokevirtual #39                 // Method apply:(Lshapeless/$colon$colon;)Lscala/Function15;
         8: areturn
      LineNumberTable:
        line 637: 0
      LocalVariableTable:
        Start  Length  Slot  Name   Signature
            0       9     0  this   Lshapeless/PolyNBuilders$Function15TypeAt$$anon$60;
            0       9     1     l   Lshapeless/HList;
    MethodParameters:
      Name                           Flags
      l                              final

  public shapeless.PolyNBuilders$Function15TypeAt$$anon$60(shapeless.PolyNBuilders$Function15TypeAt);
    descriptor: (Lshapeless/PolyNBuilders$Function15TypeAt;)V
    flags: (0x0001) ACC_PUBLIC
    Code:
      stack=2, locals=2, args_size=2
         0: aload_0
         1: aload_1
         2: putfield      #25                 // Field tprev$15:Lshapeless/PolyNBuilders$Function15TypeAt;
         5: aload_0
         6: invokespecial #45                 // Method java/lang/Object."<init>":()V
         9: return
      LineNumberTable:
        line 637: 0
      LocalVariableTable:
        Start  Length  Slot  Name   Signature
            0      10     0  this   Lshapeless/PolyNBuilders$Function15TypeAt$$anon$60;
            0      10     1 tprev$15   Lshapeless/PolyNBuilders$Function15TypeAt;
    MethodParameters:
      Name                           Flags
      tprev$15                       final
}
InnerClasses:
  public static #16= #7 of #15;           // Function15TypeAt=class shapeless/PolyNBuilders$Function15TypeAt of class shapeless/PolyNBuilders
  public static #17= #10 of #15;          // Function15TypeAt$=class shapeless/PolyNBuilders$Function15TypeAt$ of class shapeless/PolyNBuilders
  public final #2;                        // class shapeless/PolyNBuilders$Function15TypeAt$$anon$60
EnclosingMethod: #10.#13                // shapeless.PolyNBuilders$Function15TypeAt$.atOther
Signature: #3                           // Ljava/lang/Object;Lshapeless/PolyNBuilders$Function15TypeAt<TA;TB;TC;TD;TE;TF;TG;TH;TI;TJ;TK;TL;TM;TN;TO;TOut;Lshapeless/$colon$colon<THead;TTail;>;>;
SourceFile: "polynbuilders.scala"
  ScalaInlineInfo: length = 0x13 (unknown attribute)
   01 01 00 03 00 29 00 2A 01 00 14 00 15 01 00 14
   00 20 01
  Scala: length = 0x0 (unknown attribute)

