Classfile /Users/mw/Projects/slang-braindump/.jar/jar11/assemble/slang-braindump/assemble/content/shapeless/PolyDefns$.class
  Last modified May 29, 2022; size 9001 bytes
  SHA-256 checksum 01ec80920a5054b6cb76e920059e8877a9322cd008c9fa63dce5f4e6c9749b34
  Compiled from "poly.scala"
public final class shapeless.PolyDefns$ implements shapeless.Cases
  minor version: 0
  major version: 52
  flags: (0x0031) ACC_PUBLIC, ACC_FINAL, ACC_SUPER
  this_class: #2                          // shapeless/PolyDefns$
  super_class: #4                         // java/lang/Object
  interfaces: 1, fields: 23, methods: 46, attributes: 4
Constant pool:
    #1 = Utf8               shapeless/PolyDefns$
    #2 = Class              #1            // shapeless/PolyDefns$
    #3 = Utf8               java/lang/Object
    #4 = Class              #3            // java/lang/Object
    #5 = Utf8               shapeless/Cases
    #6 = Class              #5            // shapeless/Cases
    #7 = Utf8               poly.scala
    #8 = Utf8               shapeless/Cases$Case1$
    #9 = Class              #8            // shapeless/Cases$Case1$
   #10 = Utf8               Case1$
   #11 = Utf8               shapeless/Cases$Case10$
   #12 = Class              #11           // shapeless/Cases$Case10$
   #13 = Utf8               Case10$
   #14 = Utf8               shapeless/Cases$Case11$
   #15 = Class              #14           // shapeless/Cases$Case11$
   #16 = Utf8               Case11$
   #17 = Utf8               shapeless/Cases$Case12$
   #18 = Class              #17           // shapeless/Cases$Case12$
   #19 = Utf8               Case12$
   #20 = Utf8               shapeless/Cases$Case13$
   #21 = Class              #20           // shapeless/Cases$Case13$
   #22 = Utf8               Case13$
   #23 = Utf8               shapeless/Cases$Case14$
   #24 = Class              #23           // shapeless/Cases$Case14$
   #25 = Utf8               Case14$
   #26 = Utf8               shapeless/Cases$Case15$
   #27 = Class              #26           // shapeless/Cases$Case15$
   #28 = Utf8               Case15$
   #29 = Utf8               shapeless/Cases$Case16$
   #30 = Class              #29           // shapeless/Cases$Case16$
   #31 = Utf8               Case16$
   #32 = Utf8               shapeless/Cases$Case17$
   #33 = Class              #32           // shapeless/Cases$Case17$
   #34 = Utf8               Case17$
   #35 = Utf8               shapeless/Cases$Case18$
   #36 = Class              #35           // shapeless/Cases$Case18$
   #37 = Utf8               Case18$
   #38 = Utf8               shapeless/Cases$Case19$
   #39 = Class              #38           // shapeless/Cases$Case19$
   #40 = Utf8               Case19$
   #41 = Utf8               shapeless/Cases$Case2$
   #42 = Class              #41           // shapeless/Cases$Case2$
   #43 = Utf8               Case2$
   #44 = Utf8               shapeless/Cases$Case20$
   #45 = Class              #44           // shapeless/Cases$Case20$
   #46 = Utf8               Case20$
   #47 = Utf8               shapeless/Cases$Case21$
   #48 = Class              #47           // shapeless/Cases$Case21$
   #49 = Utf8               Case21$
   #50 = Utf8               shapeless/Cases$Case22$
   #51 = Class              #50           // shapeless/Cases$Case22$
   #52 = Utf8               Case22$
   #53 = Utf8               shapeless/Cases$Case3$
   #54 = Class              #53           // shapeless/Cases$Case3$
   #55 = Utf8               Case3$
   #56 = Utf8               shapeless/Cases$Case4$
   #57 = Class              #56           // shapeless/Cases$Case4$
   #58 = Utf8               Case4$
   #59 = Utf8               shapeless/Cases$Case5$
   #60 = Class              #59           // shapeless/Cases$Case5$
   #61 = Utf8               Case5$
   #62 = Utf8               shapeless/Cases$Case6$
   #63 = Class              #62           // shapeless/Cases$Case6$
   #64 = Utf8               Case6$
   #65 = Utf8               shapeless/Cases$Case7$
   #66 = Class              #65           // shapeless/Cases$Case7$
   #67 = Utf8               Case7$
   #68 = Utf8               shapeless/Cases$Case8$
   #69 = Class              #68           // shapeless/Cases$Case8$
   #70 = Utf8               Case8$
   #71 = Utf8               shapeless/Cases$Case9$
   #72 = Class              #71           // shapeless/Cases$Case9$
   #73 = Utf8               Case9$
   #74 = Utf8               MODULE$
   #75 = Utf8               Lshapeless/PolyDefns$;
   #76 = Utf8               Case1$module
   #77 = Utf8               Lshapeless/Cases$Case1$;
   #78 = Utf8               Case2$module
   #79 = Utf8               Lshapeless/Cases$Case2$;
   #80 = Utf8               Case3$module
   #81 = Utf8               Lshapeless/Cases$Case3$;
   #82 = Utf8               Case4$module
   #83 = Utf8               Lshapeless/Cases$Case4$;
   #84 = Utf8               Case5$module
   #85 = Utf8               Lshapeless/Cases$Case5$;
   #86 = Utf8               Case6$module
   #87 = Utf8               Lshapeless/Cases$Case6$;
   #88 = Utf8               Case7$module
   #89 = Utf8               Lshapeless/Cases$Case7$;
   #90 = Utf8               Case8$module
   #91 = Utf8               Lshapeless/Cases$Case8$;
   #92 = Utf8               Case9$module
   #93 = Utf8               Lshapeless/Cases$Case9$;
   #94 = Utf8               Case10$module
   #95 = Utf8               Lshapeless/Cases$Case10$;
   #96 = Utf8               Case11$module
   #97 = Utf8               Lshapeless/Cases$Case11$;
   #98 = Utf8               Case12$module
   #99 = Utf8               Lshapeless/Cases$Case12$;
  #100 = Utf8               Case13$module
  #101 = Utf8               Lshapeless/Cases$Case13$;
  #102 = Utf8               Case14$module
  #103 = Utf8               Lshapeless/Cases$Case14$;
  #104 = Utf8               Case15$module
  #105 = Utf8               Lshapeless/Cases$Case15$;
  #106 = Utf8               Case16$module
  #107 = Utf8               Lshapeless/Cases$Case16$;
  #108 = Utf8               Case17$module
  #109 = Utf8               Lshapeless/Cases$Case17$;
  #110 = Utf8               Case18$module
  #111 = Utf8               Lshapeless/Cases$Case18$;
  #112 = Utf8               Case19$module
  #113 = Utf8               Lshapeless/Cases$Case19$;
  #114 = Utf8               Case20$module
  #115 = Utf8               Lshapeless/Cases$Case20$;
  #116 = Utf8               Case21$module
  #117 = Utf8               Lshapeless/Cases$Case21$;
  #118 = Utf8               Case22$module
  #119 = Utf8               Lshapeless/Cases$Case22$;
  #120 = Utf8               <clinit>
  #121 = Utf8               ()V
  #122 = Utf8               <init>
  #123 = NameAndType        #122:#121     // "<init>":()V
  #124 = Methodref          #2.#123       // shapeless/PolyDefns$."<init>":()V
  #125 = NameAndType        #74:#75       // MODULE$:Lshapeless/PolyDefns$;
  #126 = Fieldref           #2.#125       // shapeless/PolyDefns$.MODULE$:Lshapeless/PolyDefns$;
  #127 = Utf8               $init$
  #128 = Utf8               (Lshapeless/Cases;)V
  #129 = NameAndType        #127:#128     // $init$:(Lshapeless/Cases;)V
  #130 = InterfaceMethodref #6.#129       // shapeless/Cases.$init$:(Lshapeless/Cases;)V
  #131 = Utf8               Case1
  #132 = Utf8               ()Lshapeless/Cases$Case1$;
  #133 = NameAndType        #76:#77       // Case1$module:Lshapeless/Cases$Case1$;
  #134 = Fieldref           #2.#133       // shapeless/PolyDefns$.Case1$module:Lshapeless/Cases$Case1$;
  #135 = Utf8               Case1$lzycompute$1
  #136 = NameAndType        #135:#121     // Case1$lzycompute$1:()V
  #137 = Methodref          #2.#136       // shapeless/PolyDefns$.Case1$lzycompute$1:()V
  #138 = Utf8               this
  #139 = Utf8               Case2
  #140 = Utf8               ()Lshapeless/Cases$Case2$;
  #141 = NameAndType        #78:#79       // Case2$module:Lshapeless/Cases$Case2$;
  #142 = Fieldref           #2.#141       // shapeless/PolyDefns$.Case2$module:Lshapeless/Cases$Case2$;
  #143 = Utf8               Case2$lzycompute$1
  #144 = NameAndType        #143:#121     // Case2$lzycompute$1:()V
  #145 = Methodref          #2.#144       // shapeless/PolyDefns$.Case2$lzycompute$1:()V
  #146 = Utf8               Case3
  #147 = Utf8               ()Lshapeless/Cases$Case3$;
  #148 = NameAndType        #80:#81       // Case3$module:Lshapeless/Cases$Case3$;
  #149 = Fieldref           #2.#148       // shapeless/PolyDefns$.Case3$module:Lshapeless/Cases$Case3$;
  #150 = Utf8               Case3$lzycompute$1
  #151 = NameAndType        #150:#121     // Case3$lzycompute$1:()V
  #152 = Methodref          #2.#151       // shapeless/PolyDefns$.Case3$lzycompute$1:()V
  #153 = Utf8               Case4
  #154 = Utf8               ()Lshapeless/Cases$Case4$;
  #155 = NameAndType        #82:#83       // Case4$module:Lshapeless/Cases$Case4$;
  #156 = Fieldref           #2.#155       // shapeless/PolyDefns$.Case4$module:Lshapeless/Cases$Case4$;
  #157 = Utf8               Case4$lzycompute$1
  #158 = NameAndType        #157:#121     // Case4$lzycompute$1:()V
  #159 = Methodref          #2.#158       // shapeless/PolyDefns$.Case4$lzycompute$1:()V
  #160 = Utf8               Case5
  #161 = Utf8               ()Lshapeless/Cases$Case5$;
  #162 = NameAndType        #84:#85       // Case5$module:Lshapeless/Cases$Case5$;
  #163 = Fieldref           #2.#162       // shapeless/PolyDefns$.Case5$module:Lshapeless/Cases$Case5$;
  #164 = Utf8               Case5$lzycompute$1
  #165 = NameAndType        #164:#121     // Case5$lzycompute$1:()V
  #166 = Methodref          #2.#165       // shapeless/PolyDefns$.Case5$lzycompute$1:()V
  #167 = Utf8               Case6
  #168 = Utf8               ()Lshapeless/Cases$Case6$;
  #169 = NameAndType        #86:#87       // Case6$module:Lshapeless/Cases$Case6$;
  #170 = Fieldref           #2.#169       // shapeless/PolyDefns$.Case6$module:Lshapeless/Cases$Case6$;
  #171 = Utf8               Case6$lzycompute$1
  #172 = NameAndType        #171:#121     // Case6$lzycompute$1:()V
  #173 = Methodref          #2.#172       // shapeless/PolyDefns$.Case6$lzycompute$1:()V
  #174 = Utf8               Case7
  #175 = Utf8               ()Lshapeless/Cases$Case7$;
  #176 = NameAndType        #88:#89       // Case7$module:Lshapeless/Cases$Case7$;
  #177 = Fieldref           #2.#176       // shapeless/PolyDefns$.Case7$module:Lshapeless/Cases$Case7$;
  #178 = Utf8               Case7$lzycompute$1
  #179 = NameAndType        #178:#121     // Case7$lzycompute$1:()V
  #180 = Methodref          #2.#179       // shapeless/PolyDefns$.Case7$lzycompute$1:()V
  #181 = Utf8               Case8
  #182 = Utf8               ()Lshapeless/Cases$Case8$;
  #183 = NameAndType        #90:#91       // Case8$module:Lshapeless/Cases$Case8$;
  #184 = Fieldref           #2.#183       // shapeless/PolyDefns$.Case8$module:Lshapeless/Cases$Case8$;
  #185 = Utf8               Case8$lzycompute$1
  #186 = NameAndType        #185:#121     // Case8$lzycompute$1:()V
  #187 = Methodref          #2.#186       // shapeless/PolyDefns$.Case8$lzycompute$1:()V
  #188 = Utf8               Case9
  #189 = Utf8               ()Lshapeless/Cases$Case9$;
  #190 = NameAndType        #92:#93       // Case9$module:Lshapeless/Cases$Case9$;
  #191 = Fieldref           #2.#190       // shapeless/PolyDefns$.Case9$module:Lshapeless/Cases$Case9$;
  #192 = Utf8               Case9$lzycompute$1
  #193 = NameAndType        #192:#121     // Case9$lzycompute$1:()V
  #194 = Methodref          #2.#193       // shapeless/PolyDefns$.Case9$lzycompute$1:()V
  #195 = Utf8               Case10
  #196 = Utf8               ()Lshapeless/Cases$Case10$;
  #197 = NameAndType        #94:#95       // Case10$module:Lshapeless/Cases$Case10$;
  #198 = Fieldref           #2.#197       // shapeless/PolyDefns$.Case10$module:Lshapeless/Cases$Case10$;
  #199 = Utf8               Case10$lzycompute$1
  #200 = NameAndType        #199:#121     // Case10$lzycompute$1:()V
  #201 = Methodref          #2.#200       // shapeless/PolyDefns$.Case10$lzycompute$1:()V
  #202 = Utf8               Case11
  #203 = Utf8               ()Lshapeless/Cases$Case11$;
  #204 = NameAndType        #96:#97       // Case11$module:Lshapeless/Cases$Case11$;
  #205 = Fieldref           #2.#204       // shapeless/PolyDefns$.Case11$module:Lshapeless/Cases$Case11$;
  #206 = Utf8               Case11$lzycompute$1
  #207 = NameAndType        #206:#121     // Case11$lzycompute$1:()V
  #208 = Methodref          #2.#207       // shapeless/PolyDefns$.Case11$lzycompute$1:()V
  #209 = Utf8               Case12
  #210 = Utf8               ()Lshapeless/Cases$Case12$;
  #211 = NameAndType        #98:#99       // Case12$module:Lshapeless/Cases$Case12$;
  #212 = Fieldref           #2.#211       // shapeless/PolyDefns$.Case12$module:Lshapeless/Cases$Case12$;
  #213 = Utf8               Case12$lzycompute$1
  #214 = NameAndType        #213:#121     // Case12$lzycompute$1:()V
  #215 = Methodref          #2.#214       // shapeless/PolyDefns$.Case12$lzycompute$1:()V
  #216 = Utf8               Case13
  #217 = Utf8               ()Lshapeless/Cases$Case13$;
  #218 = NameAndType        #100:#101     // Case13$module:Lshapeless/Cases$Case13$;
  #219 = Fieldref           #2.#218       // shapeless/PolyDefns$.Case13$module:Lshapeless/Cases$Case13$;
  #220 = Utf8               Case13$lzycompute$1
  #221 = NameAndType        #220:#121     // Case13$lzycompute$1:()V
  #222 = Methodref          #2.#221       // shapeless/PolyDefns$.Case13$lzycompute$1:()V
  #223 = Utf8               Case14
  #224 = Utf8               ()Lshapeless/Cases$Case14$;
  #225 = NameAndType        #102:#103     // Case14$module:Lshapeless/Cases$Case14$;
  #226 = Fieldref           #2.#225       // shapeless/PolyDefns$.Case14$module:Lshapeless/Cases$Case14$;
  #227 = Utf8               Case14$lzycompute$1
  #228 = NameAndType        #227:#121     // Case14$lzycompute$1:()V
  #229 = Methodref          #2.#228       // shapeless/PolyDefns$.Case14$lzycompute$1:()V
  #230 = Utf8               Case15
  #231 = Utf8               ()Lshapeless/Cases$Case15$;
  #232 = NameAndType        #104:#105     // Case15$module:Lshapeless/Cases$Case15$;
  #233 = Fieldref           #2.#232       // shapeless/PolyDefns$.Case15$module:Lshapeless/Cases$Case15$;
  #234 = Utf8               Case15$lzycompute$1
  #235 = NameAndType        #234:#121     // Case15$lzycompute$1:()V
  #236 = Methodref          #2.#235       // shapeless/PolyDefns$.Case15$lzycompute$1:()V
  #237 = Utf8               Case16
  #238 = Utf8               ()Lshapeless/Cases$Case16$;
  #239 = NameAndType        #106:#107     // Case16$module:Lshapeless/Cases$Case16$;
  #240 = Fieldref           #2.#239       // shapeless/PolyDefns$.Case16$module:Lshapeless/Cases$Case16$;
  #241 = Utf8               Case16$lzycompute$1
  #242 = NameAndType        #241:#121     // Case16$lzycompute$1:()V
  #243 = Methodref          #2.#242       // shapeless/PolyDefns$.Case16$lzycompute$1:()V
  #244 = Utf8               Case17
  #245 = Utf8               ()Lshapeless/Cases$Case17$;
  #246 = NameAndType        #108:#109     // Case17$module:Lshapeless/Cases$Case17$;
  #247 = Fieldref           #2.#246       // shapeless/PolyDefns$.Case17$module:Lshapeless/Cases$Case17$;
  #248 = Utf8               Case17$lzycompute$1
  #249 = NameAndType        #248:#121     // Case17$lzycompute$1:()V
  #250 = Methodref          #2.#249       // shapeless/PolyDefns$.Case17$lzycompute$1:()V
  #251 = Utf8               Case18
  #252 = Utf8               ()Lshapeless/Cases$Case18$;
  #253 = NameAndType        #110:#111     // Case18$module:Lshapeless/Cases$Case18$;
  #254 = Fieldref           #2.#253       // shapeless/PolyDefns$.Case18$module:Lshapeless/Cases$Case18$;
  #255 = Utf8               Case18$lzycompute$1
  #256 = NameAndType        #255:#121     // Case18$lzycompute$1:()V
  #257 = Methodref          #2.#256       // shapeless/PolyDefns$.Case18$lzycompute$1:()V
  #258 = Utf8               Case19
  #259 = Utf8               ()Lshapeless/Cases$Case19$;
  #260 = NameAndType        #112:#113     // Case19$module:Lshapeless/Cases$Case19$;
  #261 = Fieldref           #2.#260       // shapeless/PolyDefns$.Case19$module:Lshapeless/Cases$Case19$;
  #262 = Utf8               Case19$lzycompute$1
  #263 = NameAndType        #262:#121     // Case19$lzycompute$1:()V
  #264 = Methodref          #2.#263       // shapeless/PolyDefns$.Case19$lzycompute$1:()V
  #265 = Utf8               Case20
  #266 = Utf8               ()Lshapeless/Cases$Case20$;
  #267 = NameAndType        #114:#115     // Case20$module:Lshapeless/Cases$Case20$;
  #268 = Fieldref           #2.#267       // shapeless/PolyDefns$.Case20$module:Lshapeless/Cases$Case20$;
  #269 = Utf8               Case20$lzycompute$1
  #270 = NameAndType        #269:#121     // Case20$lzycompute$1:()V
  #271 = Methodref          #2.#270       // shapeless/PolyDefns$.Case20$lzycompute$1:()V
  #272 = Utf8               Case21
  #273 = Utf8               ()Lshapeless/Cases$Case21$;
  #274 = NameAndType        #116:#117     // Case21$module:Lshapeless/Cases$Case21$;
  #275 = Fieldref           #2.#274       // shapeless/PolyDefns$.Case21$module:Lshapeless/Cases$Case21$;
  #276 = Utf8               Case21$lzycompute$1
  #277 = NameAndType        #276:#121     // Case21$lzycompute$1:()V
  #278 = Methodref          #2.#277       // shapeless/PolyDefns$.Case21$lzycompute$1:()V
  #279 = Utf8               Case22
  #280 = Utf8               ()Lshapeless/Cases$Case22$;
  #281 = NameAndType        #118:#119     // Case22$module:Lshapeless/Cases$Case22$;
  #282 = Fieldref           #2.#281       // shapeless/PolyDefns$.Case22$module:Lshapeless/Cases$Case22$;
  #283 = Utf8               Case22$lzycompute$1
  #284 = NameAndType        #283:#121     // Case22$lzycompute$1:()V
  #285 = Methodref          #2.#284       // shapeless/PolyDefns$.Case22$lzycompute$1:()V
  #286 = NameAndType        #122:#128     // "<init>":(Lshapeless/Cases;)V
  #287 = Methodref          #9.#286       // shapeless/Cases$Case1$."<init>":(Lshapeless/Cases;)V
  #288 = Utf8               java/lang/Throwable
  #289 = Class              #288          // java/lang/Throwable
  #290 = Methodref          #42.#286      // shapeless/Cases$Case2$."<init>":(Lshapeless/Cases;)V
  #291 = Methodref          #54.#286      // shapeless/Cases$Case3$."<init>":(Lshapeless/Cases;)V
  #292 = Methodref          #57.#286      // shapeless/Cases$Case4$."<init>":(Lshapeless/Cases;)V
  #293 = Methodref          #60.#286      // shapeless/Cases$Case5$."<init>":(Lshapeless/Cases;)V
  #294 = Methodref          #63.#286      // shapeless/Cases$Case6$."<init>":(Lshapeless/Cases;)V
  #295 = Methodref          #66.#286      // shapeless/Cases$Case7$."<init>":(Lshapeless/Cases;)V
  #296 = Methodref          #69.#286      // shapeless/Cases$Case8$."<init>":(Lshapeless/Cases;)V
  #297 = Methodref          #72.#286      // shapeless/Cases$Case9$."<init>":(Lshapeless/Cases;)V
  #298 = Methodref          #12.#286      // shapeless/Cases$Case10$."<init>":(Lshapeless/Cases;)V
  #299 = Methodref          #15.#286      // shapeless/Cases$Case11$."<init>":(Lshapeless/Cases;)V
  #300 = Methodref          #18.#286      // shapeless/Cases$Case12$."<init>":(Lshapeless/Cases;)V
  #301 = Methodref          #21.#286      // shapeless/Cases$Case13$."<init>":(Lshapeless/Cases;)V
  #302 = Methodref          #24.#286      // shapeless/Cases$Case14$."<init>":(Lshapeless/Cases;)V
  #303 = Methodref          #27.#286      // shapeless/Cases$Case15$."<init>":(Lshapeless/Cases;)V
  #304 = Methodref          #30.#286      // shapeless/Cases$Case16$."<init>":(Lshapeless/Cases;)V
  #305 = Methodref          #33.#286      // shapeless/Cases$Case17$."<init>":(Lshapeless/Cases;)V
  #306 = Methodref          #36.#286      // shapeless/Cases$Case18$."<init>":(Lshapeless/Cases;)V
  #307 = Methodref          #39.#286      // shapeless/Cases$Case19$."<init>":(Lshapeless/Cases;)V
  #308 = Methodref          #45.#286      // shapeless/Cases$Case20$."<init>":(Lshapeless/Cases;)V
  #309 = Methodref          #48.#286      // shapeless/Cases$Case21$."<init>":(Lshapeless/Cases;)V
  #310 = Methodref          #51.#286      // shapeless/Cases$Case22$."<init>":(Lshapeless/Cases;)V
  #311 = Methodref          #4.#123       // java/lang/Object."<init>":()V
  #312 = Utf8               Code
  #313 = Utf8               LineNumberTable
  #314 = Utf8               StackMapTable
  #315 = Utf8               LocalVariableTable
  #316 = Utf8               InnerClasses
  #317 = Utf8               SourceFile
  #318 = Utf8               ScalaInlineInfo
  #319 = Utf8               Scala
{
  public static final shapeless.PolyDefns$ MODULE$;
    descriptor: Lshapeless/PolyDefns$;
    flags: (0x0019) ACC_PUBLIC, ACC_STATIC, ACC_FINAL

  private static volatile shapeless.Cases$Case1$ Case1$module;
    descriptor: Lshapeless/Cases$Case1$;
    flags: (0x004a) ACC_PRIVATE, ACC_STATIC, ACC_VOLATILE

  private static volatile shapeless.Cases$Case2$ Case2$module;
    descriptor: Lshapeless/Cases$Case2$;
    flags: (0x004a) ACC_PRIVATE, ACC_STATIC, ACC_VOLATILE

  private static volatile shapeless.Cases$Case3$ Case3$module;
    descriptor: Lshapeless/Cases$Case3$;
    flags: (0x004a) ACC_PRIVATE, ACC_STATIC, ACC_VOLATILE

  private static volatile shapeless.Cases$Case4$ Case4$module;
    descriptor: Lshapeless/Cases$Case4$;
    flags: (0x004a) ACC_PRIVATE, ACC_STATIC, ACC_VOLATILE

  private static volatile shapeless.Cases$Case5$ Case5$module;
    descriptor: Lshapeless/Cases$Case5$;
    flags: (0x004a) ACC_PRIVATE, ACC_STATIC, ACC_VOLATILE

  private static volatile shapeless.Cases$Case6$ Case6$module;
    descriptor: Lshapeless/Cases$Case6$;
    flags: (0x004a) ACC_PRIVATE, ACC_STATIC, ACC_VOLATILE

  private static volatile shapeless.Cases$Case7$ Case7$module;
    descriptor: Lshapeless/Cases$Case7$;
    flags: (0x004a) ACC_PRIVATE, ACC_STATIC, ACC_VOLATILE

  private static volatile shapeless.Cases$Case8$ Case8$module;
    descriptor: Lshapeless/Cases$Case8$;
    flags: (0x004a) ACC_PRIVATE, ACC_STATIC, ACC_VOLATILE

  private static volatile shapeless.Cases$Case9$ Case9$module;
    descriptor: Lshapeless/Cases$Case9$;
    flags: (0x004a) ACC_PRIVATE, ACC_STATIC, ACC_VOLATILE

  private static volatile shapeless.Cases$Case10$ Case10$module;
    descriptor: Lshapeless/Cases$Case10$;
    flags: (0x004a) ACC_PRIVATE, ACC_STATIC, ACC_VOLATILE

  private static volatile shapeless.Cases$Case11$ Case11$module;
    descriptor: Lshapeless/Cases$Case11$;
    flags: (0x004a) ACC_PRIVATE, ACC_STATIC, ACC_VOLATILE

  private static volatile shapeless.Cases$Case12$ Case12$module;
    descriptor: Lshapeless/Cases$Case12$;
    flags: (0x004a) ACC_PRIVATE, ACC_STATIC, ACC_VOLATILE

  private static volatile shapeless.Cases$Case13$ Case13$module;
    descriptor: Lshapeless/Cases$Case13$;
    flags: (0x004a) ACC_PRIVATE, ACC_STATIC, ACC_VOLATILE

  private static volatile shapeless.Cases$Case14$ Case14$module;
    descriptor: Lshapeless/Cases$Case14$;
    flags: (0x004a) ACC_PRIVATE, ACC_STATIC, ACC_VOLATILE

  private static volatile shapeless.Cases$Case15$ Case15$module;
    descriptor: Lshapeless/Cases$Case15$;
    flags: (0x004a) ACC_PRIVATE, ACC_STATIC, ACC_VOLATILE

  private static volatile shapeless.Cases$Case16$ Case16$module;
    descriptor: Lshapeless/Cases$Case16$;
    flags: (0x004a) ACC_PRIVATE, ACC_STATIC, ACC_VOLATILE

  private static volatile shapeless.Cases$Case17$ Case17$module;
    descriptor: Lshapeless/Cases$Case17$;
    flags: (0x004a) ACC_PRIVATE, ACC_STATIC, ACC_VOLATILE

  private static volatile shapeless.Cases$Case18$ Case18$module;
    descriptor: Lshapeless/Cases$Case18$;
    flags: (0x004a) ACC_PRIVATE, ACC_STATIC, ACC_VOLATILE

  private static volatile shapeless.Cases$Case19$ Case19$module;
    descriptor: Lshapeless/Cases$Case19$;
    flags: (0x004a) ACC_PRIVATE, ACC_STATIC, ACC_VOLATILE

  private static volatile shapeless.Cases$Case20$ Case20$module;
    descriptor: Lshapeless/Cases$Case20$;
    flags: (0x004a) ACC_PRIVATE, ACC_STATIC, ACC_VOLATILE

  private static volatile shapeless.Cases$Case21$ Case21$module;
    descriptor: Lshapeless/Cases$Case21$;
    flags: (0x004a) ACC_PRIVATE, ACC_STATIC, ACC_VOLATILE

  private static volatile shapeless.Cases$Case22$ Case22$module;
    descriptor: Lshapeless/Cases$Case22$;
    flags: (0x004a) ACC_PRIVATE, ACC_STATIC, ACC_VOLATILE

  public static {};
    descriptor: ()V
    flags: (0x0009) ACC_PUBLIC, ACC_STATIC
    Code:
      stack=2, locals=0, args_size=0
         0: new           #2                  // class shapeless/PolyDefns$
         3: dup
         4: invokespecial #124                // Method "<init>":()V
         7: putstatic     #126                // Field MODULE$:Lshapeless/PolyDefns$;
        10: getstatic     #126                // Field MODULE$:Lshapeless/PolyDefns$;
        13: invokestatic  #130                // InterfaceMethod shapeless/Cases.$init$:(Lshapeless/Cases;)V
        16: return
      LineNumberTable:
        line 24: 0

  public shapeless.Cases$Case1$ Case1();
    descriptor: ()Lshapeless/Cases$Case1$;
    flags: (0x0001) ACC_PUBLIC
    Code:
      stack=1, locals=1, args_size=1
         0: getstatic     #134                // Field Case1$module:Lshapeless/Cases$Case1$;
         3: ifnonnull     10
         6: aload_0
         7: invokespecial #137                // Method Case1$lzycompute$1:()V
        10: getstatic     #134                // Field Case1$module:Lshapeless/Cases$Case1$;
        13: areturn
      StackMapTable: number_of_entries = 1
        frame_type = 10 /* same */
      LineNumberTable:
        line 24: 0
      LocalVariableTable:
        Start  Length  Slot  Name   Signature
            0      14     0  this   Lshapeless/PolyDefns$;

  public shapeless.Cases$Case2$ Case2();
    descriptor: ()Lshapeless/Cases$Case2$;
    flags: (0x0001) ACC_PUBLIC
    Code:
      stack=1, locals=1, args_size=1
         0: getstatic     #142                // Field Case2$module:Lshapeless/Cases$Case2$;
         3: ifnonnull     10
         6: aload_0
         7: invokespecial #145                // Method Case2$lzycompute$1:()V
        10: getstatic     #142                // Field Case2$module:Lshapeless/Cases$Case2$;
        13: areturn
      StackMapTable: number_of_entries = 1
        frame_type = 10 /* same */
      LineNumberTable:
        line 24: 0
      LocalVariableTable:
        Start  Length  Slot  Name   Signature
            0      14     0  this   Lshapeless/PolyDefns$;

  public shapeless.Cases$Case3$ Case3();
    descriptor: ()Lshapeless/Cases$Case3$;
    flags: (0x0001) ACC_PUBLIC
    Code:
      stack=1, locals=1, args_size=1
         0: getstatic     #149                // Field Case3$module:Lshapeless/Cases$Case3$;
         3: ifnonnull     10
         6: aload_0
         7: invokespecial #152                // Method Case3$lzycompute$1:()V
        10: getstatic     #149                // Field Case3$module:Lshapeless/Cases$Case3$;
        13: areturn
      StackMapTable: number_of_entries = 1
        frame_type = 10 /* same */
      LineNumberTable:
        line 24: 0
      LocalVariableTable:
        Start  Length  Slot  Name   Signature
            0      14     0  this   Lshapeless/PolyDefns$;

  public shapeless.Cases$Case4$ Case4();
    descriptor: ()Lshapeless/Cases$Case4$;
    flags: (0x0001) ACC_PUBLIC
    Code:
      stack=1, locals=1, args_size=1
         0: getstatic     #156                // Field Case4$module:Lshapeless/Cases$Case4$;
         3: ifnonnull     10
         6: aload_0
         7: invokespecial #159                // Method Case4$lzycompute$1:()V
        10: getstatic     #156                // Field Case4$module:Lshapeless/Cases$Case4$;
        13: areturn
      StackMapTable: number_of_entries = 1
        frame_type = 10 /* same */
      LineNumberTable:
        line 24: 0
      LocalVariableTable:
        Start  Length  Slot  Name   Signature
            0      14     0  this   Lshapeless/PolyDefns$;

  public shapeless.Cases$Case5$ Case5();
    descriptor: ()Lshapeless/Cases$Case5$;
    flags: (0x0001) ACC_PUBLIC
    Code:
      stack=1, locals=1, args_size=1
         0: getstatic     #163                // Field Case5$module:Lshapeless/Cases$Case5$;
         3: ifnonnull     10
         6: aload_0
         7: invokespecial #166                // Method Case5$lzycompute$1:()V
        10: getstatic     #163                // Field Case5$module:Lshapeless/Cases$Case5$;
        13: areturn
      StackMapTable: number_of_entries = 1
        frame_type = 10 /* same */
      LineNumberTable:
        line 24: 0
      LocalVariableTable:
        Start  Length  Slot  Name   Signature
            0      14     0  this   Lshapeless/PolyDefns$;

  public shapeless.Cases$Case6$ Case6();
    descriptor: ()Lshapeless/Cases$Case6$;
    flags: (0x0001) ACC_PUBLIC
    Code:
      stack=1, locals=1, args_size=1
         0: getstatic     #170                // Field Case6$module:Lshapeless/Cases$Case6$;
         3: ifnonnull     10
         6: aload_0
         7: invokespecial #173                // Method Case6$lzycompute$1:()V
        10: getstatic     #170                // Field Case6$module:Lshapeless/Cases$Case6$;
        13: areturn
      StackMapTable: number_of_entries = 1
        frame_type = 10 /* same */
      LineNumberTable:
        line 24: 0
      LocalVariableTable:
        Start  Length  Slot  Name   Signature
            0      14     0  this   Lshapeless/PolyDefns$;

  public shapeless.Cases$Case7$ Case7();
    descriptor: ()Lshapeless/Cases$Case7$;
    flags: (0x0001) ACC_PUBLIC
    Code:
      stack=1, locals=1, args_size=1
         0: getstatic     #177                // Field Case7$module:Lshapeless/Cases$Case7$;
         3: ifnonnull     10
         6: aload_0
         7: invokespecial #180                // Method Case7$lzycompute$1:()V
        10: getstatic     #177                // Field Case7$module:Lshapeless/Cases$Case7$;
        13: areturn
      StackMapTable: number_of_entries = 1
        frame_type = 10 /* same */
      LineNumberTable:
        line 24: 0
      LocalVariableTable:
        Start  Length  Slot  Name   Signature
            0      14     0  this   Lshapeless/PolyDefns$;

  public shapeless.Cases$Case8$ Case8();
    descriptor: ()Lshapeless/Cases$Case8$;
    flags: (0x0001) ACC_PUBLIC
    Code:
      stack=1, locals=1, args_size=1
         0: getstatic     #184                // Field Case8$module:Lshapeless/Cases$Case8$;
         3: ifnonnull     10
         6: aload_0
         7: invokespecial #187                // Method Case8$lzycompute$1:()V
        10: getstatic     #184                // Field Case8$module:Lshapeless/Cases$Case8$;
        13: areturn
      StackMapTable: number_of_entries = 1
        frame_type = 10 /* same */
      LineNumberTable:
        line 24: 0
      LocalVariableTable:
        Start  Length  Slot  Name   Signature
            0      14     0  this   Lshapeless/PolyDefns$;

  public shapeless.Cases$Case9$ Case9();
    descriptor: ()Lshapeless/Cases$Case9$;
    flags: (0x0001) ACC_PUBLIC
    Code:
      stack=1, locals=1, args_size=1
         0: getstatic     #191                // Field Case9$module:Lshapeless/Cases$Case9$;
         3: ifnonnull     10
         6: aload_0
         7: invokespecial #194                // Method Case9$lzycompute$1:()V
        10: getstatic     #191                // Field Case9$module:Lshapeless/Cases$Case9$;
        13: areturn
      StackMapTable: number_of_entries = 1
        frame_type = 10 /* same */
      LineNumberTable:
        line 24: 0
      LocalVariableTable:
        Start  Length  Slot  Name   Signature
            0      14     0  this   Lshapeless/PolyDefns$;

  public shapeless.Cases$Case10$ Case10();
    descriptor: ()Lshapeless/Cases$Case10$;
    flags: (0x0001) ACC_PUBLIC
    Code:
      stack=1, locals=1, args_size=1
         0: getstatic     #198                // Field Case10$module:Lshapeless/Cases$Case10$;
         3: ifnonnull     10
         6: aload_0
         7: invokespecial #201                // Method Case10$lzycompute$1:()V
        10: getstatic     #198                // Field Case10$module:Lshapeless/Cases$Case10$;
        13: areturn
      StackMapTable: number_of_entries = 1
        frame_type = 10 /* same */
      LineNumberTable:
        line 24: 0
      LocalVariableTable:
        Start  Length  Slot  Name   Signature
            0      14     0  this   Lshapeless/PolyDefns$;

  public shapeless.Cases$Case11$ Case11();
    descriptor: ()Lshapeless/Cases$Case11$;
    flags: (0x0001) ACC_PUBLIC
    Code:
      stack=1, locals=1, args_size=1
         0: getstatic     #205                // Field Case11$module:Lshapeless/Cases$Case11$;
         3: ifnonnull     10
         6: aload_0
         7: invokespecial #208                // Method Case11$lzycompute$1:()V
        10: getstatic     #205                // Field Case11$module:Lshapeless/Cases$Case11$;
        13: areturn
      StackMapTable: number_of_entries = 1
        frame_type = 10 /* same */
      LineNumberTable:
        line 24: 0
      LocalVariableTable:
        Start  Length  Slot  Name   Signature
            0      14     0  this   Lshapeless/PolyDefns$;

  public shapeless.Cases$Case12$ Case12();
    descriptor: ()Lshapeless/Cases$Case12$;
    flags: (0x0001) ACC_PUBLIC
    Code:
      stack=1, locals=1, args_size=1
         0: getstatic     #212                // Field Case12$module:Lshapeless/Cases$Case12$;
         3: ifnonnull     10
         6: aload_0
         7: invokespecial #215                // Method Case12$lzycompute$1:()V
        10: getstatic     #212                // Field Case12$module:Lshapeless/Cases$Case12$;
        13: areturn
      StackMapTable: number_of_entries = 1
        frame_type = 10 /* same */
      LineNumberTable:
        line 24: 0
      LocalVariableTable:
        Start  Length  Slot  Name   Signature
            0      14     0  this   Lshapeless/PolyDefns$;

  public shapeless.Cases$Case13$ Case13();
    descriptor: ()Lshapeless/Cases$Case13$;
    flags: (0x0001) ACC_PUBLIC
    Code:
      stack=1, locals=1, args_size=1
         0: getstatic     #219                // Field Case13$module:Lshapeless/Cases$Case13$;
         3: ifnonnull     10
         6: aload_0
         7: invokespecial #222                // Method Case13$lzycompute$1:()V
        10: getstatic     #219                // Field Case13$module:Lshapeless/Cases$Case13$;
        13: areturn
      StackMapTable: number_of_entries = 1
        frame_type = 10 /* same */
      LineNumberTable:
        line 24: 0
      LocalVariableTable:
        Start  Length  Slot  Name   Signature
            0      14     0  this   Lshapeless/PolyDefns$;

  public shapeless.Cases$Case14$ Case14();
    descriptor: ()Lshapeless/Cases$Case14$;
    flags: (0x0001) ACC_PUBLIC
    Code:
      stack=1, locals=1, args_size=1
         0: getstatic     #226                // Field Case14$module:Lshapeless/Cases$Case14$;
         3: ifnonnull     10
         6: aload_0
         7: invokespecial #229                // Method Case14$lzycompute$1:()V
        10: getstatic     #226                // Field Case14$module:Lshapeless/Cases$Case14$;
        13: areturn
      StackMapTable: number_of_entries = 1
        frame_type = 10 /* same */
      LineNumberTable:
        line 24: 0
      LocalVariableTable:
        Start  Length  Slot  Name   Signature
            0      14     0  this   Lshapeless/PolyDefns$;

  public shapeless.Cases$Case15$ Case15();
    descriptor: ()Lshapeless/Cases$Case15$;
    flags: (0x0001) ACC_PUBLIC
    Code:
      stack=1, locals=1, args_size=1
         0: getstatic     #233                // Field Case15$module:Lshapeless/Cases$Case15$;
         3: ifnonnull     10
         6: aload_0
         7: invokespecial #236                // Method Case15$lzycompute$1:()V
        10: getstatic     #233                // Field Case15$module:Lshapeless/Cases$Case15$;
        13: areturn
      StackMapTable: number_of_entries = 1
        frame_type = 10 /* same */
      LineNumberTable:
        line 24: 0
      LocalVariableTable:
        Start  Length  Slot  Name   Signature
            0      14     0  this   Lshapeless/PolyDefns$;

  public shapeless.Cases$Case16$ Case16();
    descriptor: ()Lshapeless/Cases$Case16$;
    flags: (0x0001) ACC_PUBLIC
    Code:
      stack=1, locals=1, args_size=1
         0: getstatic     #240                // Field Case16$module:Lshapeless/Cases$Case16$;
         3: ifnonnull     10
         6: aload_0
         7: invokespecial #243                // Method Case16$lzycompute$1:()V
        10: getstatic     #240                // Field Case16$module:Lshapeless/Cases$Case16$;
        13: areturn
      StackMapTable: number_of_entries = 1
        frame_type = 10 /* same */
      LineNumberTable:
        line 24: 0
      LocalVariableTable:
        Start  Length  Slot  Name   Signature
            0      14     0  this   Lshapeless/PolyDefns$;

  public shapeless.Cases$Case17$ Case17();
    descriptor: ()Lshapeless/Cases$Case17$;
    flags: (0x0001) ACC_PUBLIC
    Code:
      stack=1, locals=1, args_size=1
         0: getstatic     #247                // Field Case17$module:Lshapeless/Cases$Case17$;
         3: ifnonnull     10
         6: aload_0
         7: invokespecial #250                // Method Case17$lzycompute$1:()V
        10: getstatic     #247                // Field Case17$module:Lshapeless/Cases$Case17$;
        13: areturn
      StackMapTable: number_of_entries = 1
        frame_type = 10 /* same */
      LineNumberTable:
        line 24: 0
      LocalVariableTable:
        Start  Length  Slot  Name   Signature
            0      14     0  this   Lshapeless/PolyDefns$;

  public shapeless.Cases$Case18$ Case18();
    descriptor: ()Lshapeless/Cases$Case18$;
    flags: (0x0001) ACC_PUBLIC
    Code:
      stack=1, locals=1, args_size=1
         0: getstatic     #254                // Field Case18$module:Lshapeless/Cases$Case18$;
         3: ifnonnull     10
         6: aload_0
         7: invokespecial #257                // Method Case18$lzycompute$1:()V
        10: getstatic     #254                // Field Case18$module:Lshapeless/Cases$Case18$;
        13: areturn
      StackMapTable: number_of_entries = 1
        frame_type = 10 /* same */
      LineNumberTable:
        line 24: 0
      LocalVariableTable:
        Start  Length  Slot  Name   Signature
            0      14     0  this   Lshapeless/PolyDefns$;

  public shapeless.Cases$Case19$ Case19();
    descriptor: ()Lshapeless/Cases$Case19$;
    flags: (0x0001) ACC_PUBLIC
    Code:
      stack=1, locals=1, args_size=1
         0: getstatic     #261                // Field Case19$module:Lshapeless/Cases$Case19$;
         3: ifnonnull     10
         6: aload_0
         7: invokespecial #264                // Method Case19$lzycompute$1:()V
        10: getstatic     #261                // Field Case19$module:Lshapeless/Cases$Case19$;
        13: areturn
      StackMapTable: number_of_entries = 1
        frame_type = 10 /* same */
      LineNumberTable:
        line 24: 0
      LocalVariableTable:
        Start  Length  Slot  Name   Signature
            0      14     0  this   Lshapeless/PolyDefns$;

  public shapeless.Cases$Case20$ Case20();
    descriptor: ()Lshapeless/Cases$Case20$;
    flags: (0x0001) ACC_PUBLIC
    Code:
      stack=1, locals=1, args_size=1
         0: getstatic     #268                // Field Case20$module:Lshapeless/Cases$Case20$;
         3: ifnonnull     10
         6: aload_0
         7: invokespecial #271                // Method Case20$lzycompute$1:()V
        10: getstatic     #268                // Field Case20$module:Lshapeless/Cases$Case20$;
        13: areturn
      StackMapTable: number_of_entries = 1
        frame_type = 10 /* same */
      LineNumberTable:
        line 24: 0
      LocalVariableTable:
        Start  Length  Slot  Name   Signature
            0      14     0  this   Lshapeless/PolyDefns$;

  public shapeless.Cases$Case21$ Case21();
    descriptor: ()Lshapeless/Cases$Case21$;
    flags: (0x0001) ACC_PUBLIC
    Code:
      stack=1, locals=1, args_size=1
         0: getstatic     #275                // Field Case21$module:Lshapeless/Cases$Case21$;
         3: ifnonnull     10
         6: aload_0
         7: invokespecial #278                // Method Case21$lzycompute$1:()V
        10: getstatic     #275                // Field Case21$module:Lshapeless/Cases$Case21$;
        13: areturn
      StackMapTable: number_of_entries = 1
        frame_type = 10 /* same */
      LineNumberTable:
        line 24: 0
      LocalVariableTable:
        Start  Length  Slot  Name   Signature
            0      14     0  this   Lshapeless/PolyDefns$;

  public shapeless.Cases$Case22$ Case22();
    descriptor: ()Lshapeless/Cases$Case22$;
    flags: (0x0001) ACC_PUBLIC
    Code:
      stack=1, locals=1, args_size=1
         0: getstatic     #282                // Field Case22$module:Lshapeless/Cases$Case22$;
         3: ifnonnull     10
         6: aload_0
         7: invokespecial #285                // Method Case22$lzycompute$1:()V
        10: getstatic     #282                // Field Case22$module:Lshapeless/Cases$Case22$;
        13: areturn
      StackMapTable: number_of_entries = 1
        frame_type = 10 /* same */
      LineNumberTable:
        line 24: 0
      LocalVariableTable:
        Start  Length  Slot  Name   Signature
            0      14     0  this   Lshapeless/PolyDefns$;

  private final void Case1$lzycompute$1();
    descriptor: ()V
    flags: (0x0012) ACC_PRIVATE, ACC_FINAL
    Code:
      stack=3, locals=2, args_size=1
         0: aload_0
         1: dup
         2: astore_1
         3: monitorenter
         4: getstatic     #134                // Field Case1$module:Lshapeless/Cases$Case1$;
         7: ifnonnull     21
        10: new           #9                  // class shapeless/Cases$Case1$
        13: dup
        14: aload_0
        15: invokespecial #287                // Method shapeless/Cases$Case1$."<init>":(Lshapeless/Cases;)V
        18: putstatic     #134                // Field Case1$module:Lshapeless/Cases$Case1$;
        21: aload_1
        22: monitorexit
        23: goto          29
        26: aload_1
        27: monitorexit
        28: athrow
        29: return
      Exception table:
         from    to  target type
             4    21    26   any
      StackMapTable: number_of_entries = 3
        frame_type = 252 /* append */
          offset_delta = 21
          locals = [ class shapeless/PolyDefns$ ]
        frame_type = 68 /* same_locals_1_stack_item */
          stack = [ class java/lang/Throwable ]
        frame_type = 2 /* same */
      LineNumberTable:
        line 24: 0
      LocalVariableTable:
        Start  Length  Slot  Name   Signature
            0      30     0  this   Lshapeless/PolyDefns$;

  private final void Case2$lzycompute$1();
    descriptor: ()V
    flags: (0x0012) ACC_PRIVATE, ACC_FINAL
    Code:
      stack=3, locals=2, args_size=1
         0: aload_0
         1: dup
         2: astore_1
         3: monitorenter
         4: getstatic     #142                // Field Case2$module:Lshapeless/Cases$Case2$;
         7: ifnonnull     21
        10: new           #42                 // class shapeless/Cases$Case2$
        13: dup
        14: aload_0
        15: invokespecial #290                // Method shapeless/Cases$Case2$."<init>":(Lshapeless/Cases;)V
        18: putstatic     #142                // Field Case2$module:Lshapeless/Cases$Case2$;
        21: aload_1
        22: monitorexit
        23: goto          29
        26: aload_1
        27: monitorexit
        28: athrow
        29: return
      Exception table:
         from    to  target type
             4    21    26   any
      StackMapTable: number_of_entries = 3
        frame_type = 252 /* append */
          offset_delta = 21
          locals = [ class shapeless/PolyDefns$ ]
        frame_type = 68 /* same_locals_1_stack_item */
          stack = [ class java/lang/Throwable ]
        frame_type = 2 /* same */
      LineNumberTable:
        line 24: 0
      LocalVariableTable:
        Start  Length  Slot  Name   Signature
            0      30     0  this   Lshapeless/PolyDefns$;

  private final void Case3$lzycompute$1();
    descriptor: ()V
    flags: (0x0012) ACC_PRIVATE, ACC_FINAL
    Code:
      stack=3, locals=2, args_size=1
         0: aload_0
         1: dup
         2: astore_1
         3: monitorenter
         4: getstatic     #149                // Field Case3$module:Lshapeless/Cases$Case3$;
         7: ifnonnull     21
        10: new           #54                 // class shapeless/Cases$Case3$
        13: dup
        14: aload_0
        15: invokespecial #291                // Method shapeless/Cases$Case3$."<init>":(Lshapeless/Cases;)V
        18: putstatic     #149                // Field Case3$module:Lshapeless/Cases$Case3$;
        21: aload_1
        22: monitorexit
        23: goto          29
        26: aload_1
        27: monitorexit
        28: athrow
        29: return
      Exception table:
         from    to  target type
             4    21    26   any
      StackMapTable: number_of_entries = 3
        frame_type = 252 /* append */
          offset_delta = 21
          locals = [ class shapeless/PolyDefns$ ]
        frame_type = 68 /* same_locals_1_stack_item */
          stack = [ class java/lang/Throwable ]
        frame_type = 2 /* same */
      LineNumberTable:
        line 24: 0
      LocalVariableTable:
        Start  Length  Slot  Name   Signature
            0      30     0  this   Lshapeless/PolyDefns$;

  private final void Case4$lzycompute$1();
    descriptor: ()V
    flags: (0x0012) ACC_PRIVATE, ACC_FINAL
    Code:
      stack=3, locals=2, args_size=1
         0: aload_0
         1: dup
         2: astore_1
         3: monitorenter
         4: getstatic     #156                // Field Case4$module:Lshapeless/Cases$Case4$;
         7: ifnonnull     21
        10: new           #57                 // class shapeless/Cases$Case4$
        13: dup
        14: aload_0
        15: invokespecial #292                // Method shapeless/Cases$Case4$."<init>":(Lshapeless/Cases;)V
        18: putstatic     #156                // Field Case4$module:Lshapeless/Cases$Case4$;
        21: aload_1
        22: monitorexit
        23: goto          29
        26: aload_1
        27: monitorexit
        28: athrow
        29: return
      Exception table:
         from    to  target type
             4    21    26   any
      StackMapTable: number_of_entries = 3
        frame_type = 252 /* append */
          offset_delta = 21
          locals = [ class shapeless/PolyDefns$ ]
        frame_type = 68 /* same_locals_1_stack_item */
          stack = [ class java/lang/Throwable ]
        frame_type = 2 /* same */
      LineNumberTable:
        line 24: 0
      LocalVariableTable:
        Start  Length  Slot  Name   Signature
            0      30     0  this   Lshapeless/PolyDefns$;

  private final void Case5$lzycompute$1();
    descriptor: ()V
    flags: (0x0012) ACC_PRIVATE, ACC_FINAL
    Code:
      stack=3, locals=2, args_size=1
         0: aload_0
         1: dup
         2: astore_1
         3: monitorenter
         4: getstatic     #163                // Field Case5$module:Lshapeless/Cases$Case5$;
         7: ifnonnull     21
        10: new           #60                 // class shapeless/Cases$Case5$
        13: dup
        14: aload_0
        15: invokespecial #293                // Method shapeless/Cases$Case5$."<init>":(Lshapeless/Cases;)V
        18: putstatic     #163                // Field Case5$module:Lshapeless/Cases$Case5$;
        21: aload_1
        22: monitorexit
        23: goto          29
        26: aload_1
        27: monitorexit
        28: athrow
        29: return
      Exception table:
         from    to  target type
             4    21    26   any
      StackMapTable: number_of_entries = 3
        frame_type = 252 /* append */
          offset_delta = 21
          locals = [ class shapeless/PolyDefns$ ]
        frame_type = 68 /* same_locals_1_stack_item */
          stack = [ class java/lang/Throwable ]
        frame_type = 2 /* same */
      LineNumberTable:
        line 24: 0
      LocalVariableTable:
        Start  Length  Slot  Name   Signature
            0      30     0  this   Lshapeless/PolyDefns$;

  private final void Case6$lzycompute$1();
    descriptor: ()V
    flags: (0x0012) ACC_PRIVATE, ACC_FINAL
    Code:
      stack=3, locals=2, args_size=1
         0: aload_0
         1: dup
         2: astore_1
         3: monitorenter
         4: getstatic     #170                // Field Case6$module:Lshapeless/Cases$Case6$;
         7: ifnonnull     21
        10: new           #63                 // class shapeless/Cases$Case6$
        13: dup
        14: aload_0
        15: invokespecial #294                // Method shapeless/Cases$Case6$."<init>":(Lshapeless/Cases;)V
        18: putstatic     #170                // Field Case6$module:Lshapeless/Cases$Case6$;
        21: aload_1
        22: monitorexit
        23: goto          29
        26: aload_1
        27: monitorexit
        28: athrow
        29: return
      Exception table:
         from    to  target type
             4    21    26   any
      StackMapTable: number_of_entries = 3
        frame_type = 252 /* append */
          offset_delta = 21
          locals = [ class shapeless/PolyDefns$ ]
        frame_type = 68 /* same_locals_1_stack_item */
          stack = [ class java/lang/Throwable ]
        frame_type = 2 /* same */
      LineNumberTable:
        line 24: 0
      LocalVariableTable:
        Start  Length  Slot  Name   Signature
            0      30     0  this   Lshapeless/PolyDefns$;

  private final void Case7$lzycompute$1();
    descriptor: ()V
    flags: (0x0012) ACC_PRIVATE, ACC_FINAL
    Code:
      stack=3, locals=2, args_size=1
         0: aload_0
         1: dup
         2: astore_1
         3: monitorenter
         4: getstatic     #177                // Field Case7$module:Lshapeless/Cases$Case7$;
         7: ifnonnull     21
        10: new           #66                 // class shapeless/Cases$Case7$
        13: dup
        14: aload_0
        15: invokespecial #295                // Method shapeless/Cases$Case7$."<init>":(Lshapeless/Cases;)V
        18: putstatic     #177                // Field Case7$module:Lshapeless/Cases$Case7$;
        21: aload_1
        22: monitorexit
        23: goto          29
        26: aload_1
        27: monitorexit
        28: athrow
        29: return
      Exception table:
         from    to  target type
             4    21    26   any
      StackMapTable: number_of_entries = 3
        frame_type = 252 /* append */
          offset_delta = 21
          locals = [ class shapeless/PolyDefns$ ]
        frame_type = 68 /* same_locals_1_stack_item */
          stack = [ class java/lang/Throwable ]
        frame_type = 2 /* same */
      LineNumberTable:
        line 24: 0
      LocalVariableTable:
        Start  Length  Slot  Name   Signature
            0      30     0  this   Lshapeless/PolyDefns$;

  private final void Case8$lzycompute$1();
    descriptor: ()V
    flags: (0x0012) ACC_PRIVATE, ACC_FINAL
    Code:
      stack=3, locals=2, args_size=1
         0: aload_0
         1: dup
         2: astore_1
         3: monitorenter
         4: getstatic     #184                // Field Case8$module:Lshapeless/Cases$Case8$;
         7: ifnonnull     21
        10: new           #69                 // class shapeless/Cases$Case8$
        13: dup
        14: aload_0
        15: invokespecial #296                // Method shapeless/Cases$Case8$."<init>":(Lshapeless/Cases;)V
        18: putstatic     #184                // Field Case8$module:Lshapeless/Cases$Case8$;
        21: aload_1
        22: monitorexit
        23: goto          29
        26: aload_1
        27: monitorexit
        28: athrow
        29: return
      Exception table:
         from    to  target type
             4    21    26   any
      StackMapTable: number_of_entries = 3
        frame_type = 252 /* append */
          offset_delta = 21
          locals = [ class shapeless/PolyDefns$ ]
        frame_type = 68 /* same_locals_1_stack_item */
          stack = [ class java/lang/Throwable ]
        frame_type = 2 /* same */
      LineNumberTable:
        line 24: 0
      LocalVariableTable:
        Start  Length  Slot  Name   Signature
            0      30     0  this   Lshapeless/PolyDefns$;

  private final void Case9$lzycompute$1();
    descriptor: ()V
    flags: (0x0012) ACC_PRIVATE, ACC_FINAL
    Code:
      stack=3, locals=2, args_size=1
         0: aload_0
         1: dup
         2: astore_1
         3: monitorenter
         4: getstatic     #191                // Field Case9$module:Lshapeless/Cases$Case9$;
         7: ifnonnull     21
        10: new           #72                 // class shapeless/Cases$Case9$
        13: dup
        14: aload_0
        15: invokespecial #297                // Method shapeless/Cases$Case9$."<init>":(Lshapeless/Cases;)V
        18: putstatic     #191                // Field Case9$module:Lshapeless/Cases$Case9$;
        21: aload_1
        22: monitorexit
        23: goto          29
        26: aload_1
        27: monitorexit
        28: athrow
        29: return
      Exception table:
         from    to  target type
             4    21    26   any
      StackMapTable: number_of_entries = 3
        frame_type = 252 /* append */
          offset_delta = 21
          locals = [ class shapeless/PolyDefns$ ]
        frame_type = 68 /* same_locals_1_stack_item */
          stack = [ class java/lang/Throwable ]
        frame_type = 2 /* same */
      LineNumberTable:
        line 24: 0
      LocalVariableTable:
        Start  Length  Slot  Name   Signature
            0      30     0  this   Lshapeless/PolyDefns$;

  private final void Case10$lzycompute$1();
    descriptor: ()V
    flags: (0x0012) ACC_PRIVATE, ACC_FINAL
    Code:
      stack=3, locals=2, args_size=1
         0: aload_0
         1: dup
         2: astore_1
         3: monitorenter
         4: getstatic     #198                // Field Case10$module:Lshapeless/Cases$Case10$;
         7: ifnonnull     21
        10: new           #12                 // class shapeless/Cases$Case10$
        13: dup
        14: aload_0
        15: invokespecial #298                // Method shapeless/Cases$Case10$."<init>":(Lshapeless/Cases;)V
        18: putstatic     #198                // Field Case10$module:Lshapeless/Cases$Case10$;
        21: aload_1
        22: monitorexit
        23: goto          29
        26: aload_1
        27: monitorexit
        28: athrow
        29: return
      Exception table:
         from    to  target type
             4    21    26   any
      StackMapTable: number_of_entries = 3
        frame_type = 252 /* append */
          offset_delta = 21
          locals = [ class shapeless/PolyDefns$ ]
        frame_type = 68 /* same_locals_1_stack_item */
          stack = [ class java/lang/Throwable ]
        frame_type = 2 /* same */
      LineNumberTable:
        line 24: 0
      LocalVariableTable:
        Start  Length  Slot  Name   Signature
            0      30     0  this   Lshapeless/PolyDefns$;

  private final void Case11$lzycompute$1();
    descriptor: ()V
    flags: (0x0012) ACC_PRIVATE, ACC_FINAL
    Code:
      stack=3, locals=2, args_size=1
         0: aload_0
         1: dup
         2: astore_1
         3: monitorenter
         4: getstatic     #205                // Field Case11$module:Lshapeless/Cases$Case11$;
         7: ifnonnull     21
        10: new           #15                 // class shapeless/Cases$Case11$
        13: dup
        14: aload_0
        15: invokespecial #299                // Method shapeless/Cases$Case11$."<init>":(Lshapeless/Cases;)V
        18: putstatic     #205                // Field Case11$module:Lshapeless/Cases$Case11$;
        21: aload_1
        22: monitorexit
        23: goto          29
        26: aload_1
        27: monitorexit
        28: athrow
        29: return
      Exception table:
         from    to  target type
             4    21    26   any
      StackMapTable: number_of_entries = 3
        frame_type = 252 /* append */
          offset_delta = 21
          locals = [ class shapeless/PolyDefns$ ]
        frame_type = 68 /* same_locals_1_stack_item */
          stack = [ class java/lang/Throwable ]
        frame_type = 2 /* same */
      LineNumberTable:
        line 24: 0
      LocalVariableTable:
        Start  Length  Slot  Name   Signature
            0      30     0  this   Lshapeless/PolyDefns$;

  private final void Case12$lzycompute$1();
    descriptor: ()V
    flags: (0x0012) ACC_PRIVATE, ACC_FINAL
    Code:
      stack=3, locals=2, args_size=1
         0: aload_0
         1: dup
         2: astore_1
         3: monitorenter
         4: getstatic     #212                // Field Case12$module:Lshapeless/Cases$Case12$;
         7: ifnonnull     21
        10: new           #18                 // class shapeless/Cases$Case12$
        13: dup
        14: aload_0
        15: invokespecial #300                // Method shapeless/Cases$Case12$."<init>":(Lshapeless/Cases;)V
        18: putstatic     #212                // Field Case12$module:Lshapeless/Cases$Case12$;
        21: aload_1
        22: monitorexit
        23: goto          29
        26: aload_1
        27: monitorexit
        28: athrow
        29: return
      Exception table:
         from    to  target type
             4    21    26   any
      StackMapTable: number_of_entries = 3
        frame_type = 252 /* append */
          offset_delta = 21
          locals = [ class shapeless/PolyDefns$ ]
        frame_type = 68 /* same_locals_1_stack_item */
          stack = [ class java/lang/Throwable ]
        frame_type = 2 /* same */
      LineNumberTable:
        line 24: 0
      LocalVariableTable:
        Start  Length  Slot  Name   Signature
            0      30     0  this   Lshapeless/PolyDefns$;

  private final void Case13$lzycompute$1();
    descriptor: ()V
    flags: (0x0012) ACC_PRIVATE, ACC_FINAL
    Code:
      stack=3, locals=2, args_size=1
         0: aload_0
         1: dup
         2: astore_1
         3: monitorenter
         4: getstatic     #219                // Field Case13$module:Lshapeless/Cases$Case13$;
         7: ifnonnull     21
        10: new           #21                 // class shapeless/Cases$Case13$
        13: dup
        14: aload_0
        15: invokespecial #301                // Method shapeless/Cases$Case13$."<init>":(Lshapeless/Cases;)V
        18: putstatic     #219                // Field Case13$module:Lshapeless/Cases$Case13$;
        21: aload_1
        22: monitorexit
        23: goto          29
        26: aload_1
        27: monitorexit
        28: athrow
        29: return
      Exception table:
         from    to  target type
             4    21    26   any
      StackMapTable: number_of_entries = 3
        frame_type = 252 /* append */
          offset_delta = 21
          locals = [ class shapeless/PolyDefns$ ]
        frame_type = 68 /* same_locals_1_stack_item */
          stack = [ class java/lang/Throwable ]
        frame_type = 2 /* same */
      LineNumberTable:
        line 24: 0
      LocalVariableTable:
        Start  Length  Slot  Name   Signature
            0      30     0  this   Lshapeless/PolyDefns$;

  private final void Case14$lzycompute$1();
    descriptor: ()V
    flags: (0x0012) ACC_PRIVATE, ACC_FINAL
    Code:
      stack=3, locals=2, args_size=1
         0: aload_0
         1: dup
         2: astore_1
         3: monitorenter
         4: getstatic     #226                // Field Case14$module:Lshapeless/Cases$Case14$;
         7: ifnonnull     21
        10: new           #24                 // class shapeless/Cases$Case14$
        13: dup
        14: aload_0
        15: invokespecial #302                // Method shapeless/Cases$Case14$."<init>":(Lshapeless/Cases;)V
        18: putstatic     #226                // Field Case14$module:Lshapeless/Cases$Case14$;
        21: aload_1
        22: monitorexit
        23: goto          29
        26: aload_1
        27: monitorexit
        28: athrow
        29: return
      Exception table:
         from    to  target type
             4    21    26   any
      StackMapTable: number_of_entries = 3
        frame_type = 252 /* append */
          offset_delta = 21
          locals = [ class shapeless/PolyDefns$ ]
        frame_type = 68 /* same_locals_1_stack_item */
          stack = [ class java/lang/Throwable ]
        frame_type = 2 /* same */
      LineNumberTable:
        line 24: 0
      LocalVariableTable:
        Start  Length  Slot  Name   Signature
            0      30     0  this   Lshapeless/PolyDefns$;

  private final void Case15$lzycompute$1();
    descriptor: ()V
    flags: (0x0012) ACC_PRIVATE, ACC_FINAL
    Code:
      stack=3, locals=2, args_size=1
         0: aload_0
         1: dup
         2: astore_1
         3: monitorenter
         4: getstatic     #233                // Field Case15$module:Lshapeless/Cases$Case15$;
         7: ifnonnull     21
        10: new           #27                 // class shapeless/Cases$Case15$
        13: dup
        14: aload_0
        15: invokespecial #303                // Method shapeless/Cases$Case15$."<init>":(Lshapeless/Cases;)V
        18: putstatic     #233                // Field Case15$module:Lshapeless/Cases$Case15$;
        21: aload_1
        22: monitorexit
        23: goto          29
        26: aload_1
        27: monitorexit
        28: athrow
        29: return
      Exception table:
         from    to  target type
             4    21    26   any
      StackMapTable: number_of_entries = 3
        frame_type = 252 /* append */
          offset_delta = 21
          locals = [ class shapeless/PolyDefns$ ]
        frame_type = 68 /* same_locals_1_stack_item */
          stack = [ class java/lang/Throwable ]
        frame_type = 2 /* same */
      LineNumberTable:
        line 24: 0
      LocalVariableTable:
        Start  Length  Slot  Name   Signature
            0      30     0  this   Lshapeless/PolyDefns$;

  private final void Case16$lzycompute$1();
    descriptor: ()V
    flags: (0x0012) ACC_PRIVATE, ACC_FINAL
    Code:
      stack=3, locals=2, args_size=1
         0: aload_0
         1: dup
         2: astore_1
         3: monitorenter
         4: getstatic     #240                // Field Case16$module:Lshapeless/Cases$Case16$;
         7: ifnonnull     21
        10: new           #30                 // class shapeless/Cases$Case16$
        13: dup
        14: aload_0
        15: invokespecial #304                // Method shapeless/Cases$Case16$."<init>":(Lshapeless/Cases;)V
        18: putstatic     #240                // Field Case16$module:Lshapeless/Cases$Case16$;
        21: aload_1
        22: monitorexit
        23: goto          29
        26: aload_1
        27: monitorexit
        28: athrow
        29: return
      Exception table:
         from    to  target type
             4    21    26   any
      StackMapTable: number_of_entries = 3
        frame_type = 252 /* append */
          offset_delta = 21
          locals = [ class shapeless/PolyDefns$ ]
        frame_type = 68 /* same_locals_1_stack_item */
          stack = [ class java/lang/Throwable ]
        frame_type = 2 /* same */
      LineNumberTable:
        line 24: 0
      LocalVariableTable:
        Start  Length  Slot  Name   Signature
            0      30     0  this   Lshapeless/PolyDefns$;

  private final void Case17$lzycompute$1();
    descriptor: ()V
    flags: (0x0012) ACC_PRIVATE, ACC_FINAL
    Code:
      stack=3, locals=2, args_size=1
         0: aload_0
         1: dup
         2: astore_1
         3: monitorenter
         4: getstatic     #247                // Field Case17$module:Lshapeless/Cases$Case17$;
         7: ifnonnull     21
        10: new           #33                 // class shapeless/Cases$Case17$
        13: dup
        14: aload_0
        15: invokespecial #305                // Method shapeless/Cases$Case17$."<init>":(Lshapeless/Cases;)V
        18: putstatic     #247                // Field Case17$module:Lshapeless/Cases$Case17$;
        21: aload_1
        22: monitorexit
        23: goto          29
        26: aload_1
        27: monitorexit
        28: athrow
        29: return
      Exception table:
         from    to  target type
             4    21    26   any
      StackMapTable: number_of_entries = 3
        frame_type = 252 /* append */
          offset_delta = 21
          locals = [ class shapeless/PolyDefns$ ]
        frame_type = 68 /* same_locals_1_stack_item */
          stack = [ class java/lang/Throwable ]
        frame_type = 2 /* same */
      LineNumberTable:
        line 24: 0
      LocalVariableTable:
        Start  Length  Slot  Name   Signature
            0      30     0  this   Lshapeless/PolyDefns$;

  private final void Case18$lzycompute$1();
    descriptor: ()V
    flags: (0x0012) ACC_PRIVATE, ACC_FINAL
    Code:
      stack=3, locals=2, args_size=1
         0: aload_0
         1: dup
         2: astore_1
         3: monitorenter
         4: getstatic     #254                // Field Case18$module:Lshapeless/Cases$Case18$;
         7: ifnonnull     21
        10: new           #36                 // class shapeless/Cases$Case18$
        13: dup
        14: aload_0
        15: invokespecial #306                // Method shapeless/Cases$Case18$."<init>":(Lshapeless/Cases;)V
        18: putstatic     #254                // Field Case18$module:Lshapeless/Cases$Case18$;
        21: aload_1
        22: monitorexit
        23: goto          29
        26: aload_1
        27: monitorexit
        28: athrow
        29: return
      Exception table:
         from    to  target type
             4    21    26   any
      StackMapTable: number_of_entries = 3
        frame_type = 252 /* append */
          offset_delta = 21
          locals = [ class shapeless/PolyDefns$ ]
        frame_type = 68 /* same_locals_1_stack_item */
          stack = [ class java/lang/Throwable ]
        frame_type = 2 /* same */
      LineNumberTable:
        line 24: 0
      LocalVariableTable:
        Start  Length  Slot  Name   Signature
            0      30     0  this   Lshapeless/PolyDefns$;

  private final void Case19$lzycompute$1();
    descriptor: ()V
    flags: (0x0012) ACC_PRIVATE, ACC_FINAL
    Code:
      stack=3, locals=2, args_size=1
         0: aload_0
         1: dup
         2: astore_1
         3: monitorenter
         4: getstatic     #261                // Field Case19$module:Lshapeless/Cases$Case19$;
         7: ifnonnull     21
        10: new           #39                 // class shapeless/Cases$Case19$
        13: dup
        14: aload_0
        15: invokespecial #307                // Method shapeless/Cases$Case19$."<init>":(Lshapeless/Cases;)V
        18: putstatic     #261                // Field Case19$module:Lshapeless/Cases$Case19$;
        21: aload_1
        22: monitorexit
        23: goto          29
        26: aload_1
        27: monitorexit
        28: athrow
        29: return
      Exception table:
         from    to  target type
             4    21    26   any
      StackMapTable: number_of_entries = 3
        frame_type = 252 /* append */
          offset_delta = 21
          locals = [ class shapeless/PolyDefns$ ]
        frame_type = 68 /* same_locals_1_stack_item */
          stack = [ class java/lang/Throwable ]
        frame_type = 2 /* same */
      LineNumberTable:
        line 24: 0
      LocalVariableTable:
        Start  Length  Slot  Name   Signature
            0      30     0  this   Lshapeless/PolyDefns$;

  private final void Case20$lzycompute$1();
    descriptor: ()V
    flags: (0x0012) ACC_PRIVATE, ACC_FINAL
    Code:
      stack=3, locals=2, args_size=1
         0: aload_0
         1: dup
         2: astore_1
         3: monitorenter
         4: getstatic     #268                // Field Case20$module:Lshapeless/Cases$Case20$;
         7: ifnonnull     21
        10: new           #45                 // class shapeless/Cases$Case20$
        13: dup
        14: aload_0
        15: invokespecial #308                // Method shapeless/Cases$Case20$."<init>":(Lshapeless/Cases;)V
        18: putstatic     #268                // Field Case20$module:Lshapeless/Cases$Case20$;
        21: aload_1
        22: monitorexit
        23: goto          29
        26: aload_1
        27: monitorexit
        28: athrow
        29: return
      Exception table:
         from    to  target type
             4    21    26   any
      StackMapTable: number_of_entries = 3
        frame_type = 252 /* append */
          offset_delta = 21
          locals = [ class shapeless/PolyDefns$ ]
        frame_type = 68 /* same_locals_1_stack_item */
          stack = [ class java/lang/Throwable ]
        frame_type = 2 /* same */
      LineNumberTable:
        line 24: 0
      LocalVariableTable:
        Start  Length  Slot  Name   Signature
            0      30     0  this   Lshapeless/PolyDefns$;

  private final void Case21$lzycompute$1();
    descriptor: ()V
    flags: (0x0012) ACC_PRIVATE, ACC_FINAL
    Code:
      stack=3, locals=2, args_size=1
         0: aload_0
         1: dup
         2: astore_1
         3: monitorenter
         4: getstatic     #275                // Field Case21$module:Lshapeless/Cases$Case21$;
         7: ifnonnull     21
        10: new           #48                 // class shapeless/Cases$Case21$
        13: dup
        14: aload_0
        15: invokespecial #309                // Method shapeless/Cases$Case21$."<init>":(Lshapeless/Cases;)V
        18: putstatic     #275                // Field Case21$module:Lshapeless/Cases$Case21$;
        21: aload_1
        22: monitorexit
        23: goto          29
        26: aload_1
        27: monitorexit
        28: athrow
        29: return
      Exception table:
         from    to  target type
             4    21    26   any
      StackMapTable: number_of_entries = 3
        frame_type = 252 /* append */
          offset_delta = 21
          locals = [ class shapeless/PolyDefns$ ]
        frame_type = 68 /* same_locals_1_stack_item */
          stack = [ class java/lang/Throwable ]
        frame_type = 2 /* same */
      LineNumberTable:
        line 24: 0
      LocalVariableTable:
        Start  Length  Slot  Name   Signature
            0      30     0  this   Lshapeless/PolyDefns$;

  private final void Case22$lzycompute$1();
    descriptor: ()V
    flags: (0x0012) ACC_PRIVATE, ACC_FINAL
    Code:
      stack=3, locals=2, args_size=1
         0: aload_0
         1: dup
         2: astore_1
         3: monitorenter
         4: getstatic     #282                // Field Case22$module:Lshapeless/Cases$Case22$;
         7: ifnonnull     21
        10: new           #51                 // class shapeless/Cases$Case22$
        13: dup
        14: aload_0
        15: invokespecial #310                // Method shapeless/Cases$Case22$."<init>":(Lshapeless/Cases;)V
        18: putstatic     #282                // Field Case22$module:Lshapeless/Cases$Case22$;
        21: aload_1
        22: monitorexit
        23: goto          29
        26: aload_1
        27: monitorexit
        28: athrow
        29: return
      Exception table:
         from    to  target type
             4    21    26   any
      StackMapTable: number_of_entries = 3
        frame_type = 252 /* append */
          offset_delta = 21
          locals = [ class shapeless/PolyDefns$ ]
        frame_type = 68 /* same_locals_1_stack_item */
          stack = [ class java/lang/Throwable ]
        frame_type = 2 /* same */
      LineNumberTable:
        line 24: 0
      LocalVariableTable:
        Start  Length  Slot  Name   Signature
            0      30     0  this   Lshapeless/PolyDefns$;

  private shapeless.PolyDefns$();
    descriptor: ()V
    flags: (0x0002) ACC_PRIVATE
    Code:
      stack=1, locals=1, args_size=1
         0: aload_0
         1: invokespecial #311                // Method java/lang/Object."<init>":()V
         4: return
      LineNumberTable:
        line 24: 0
      LocalVariableTable:
        Start  Length  Slot  Name   Signature
            0       5     0  this   Lshapeless/PolyDefns$;
}
InnerClasses:
  public #10= #9 of #6;                   // Case1$=class shapeless/Cases$Case1$ of class shapeless/Cases
  public #13= #12 of #6;                  // Case10$=class shapeless/Cases$Case10$ of class shapeless/Cases
  public #16= #15 of #6;                  // Case11$=class shapeless/Cases$Case11$ of class shapeless/Cases
  public #19= #18 of #6;                  // Case12$=class shapeless/Cases$Case12$ of class shapeless/Cases
  public #22= #21 of #6;                  // Case13$=class shapeless/Cases$Case13$ of class shapeless/Cases
  public #25= #24 of #6;                  // Case14$=class shapeless/Cases$Case14$ of class shapeless/Cases
  public #28= #27 of #6;                  // Case15$=class shapeless/Cases$Case15$ of class shapeless/Cases
  public #31= #30 of #6;                  // Case16$=class shapeless/Cases$Case16$ of class shapeless/Cases
  public #34= #33 of #6;                  // Case17$=class shapeless/Cases$Case17$ of class shapeless/Cases
  public #37= #36 of #6;                  // Case18$=class shapeless/Cases$Case18$ of class shapeless/Cases
  public #40= #39 of #6;                  // Case19$=class shapeless/Cases$Case19$ of class shapeless/Cases
  public #43= #42 of #6;                  // Case2$=class shapeless/Cases$Case2$ of class shapeless/Cases
  public #46= #45 of #6;                  // Case20$=class shapeless/Cases$Case20$ of class shapeless/Cases
  public #49= #48 of #6;                  // Case21$=class shapeless/Cases$Case21$ of class shapeless/Cases
  public #52= #51 of #6;                  // Case22$=class shapeless/Cases$Case22$ of class shapeless/Cases
  public #55= #54 of #6;                  // Case3$=class shapeless/Cases$Case3$ of class shapeless/Cases
  public #58= #57 of #6;                  // Case4$=class shapeless/Cases$Case4$ of class shapeless/Cases
  public #61= #60 of #6;                  // Case5$=class shapeless/Cases$Case5$ of class shapeless/Cases
  public #64= #63 of #6;                  // Case6$=class shapeless/Cases$Case6$ of class shapeless/Cases
  public #67= #66 of #6;                  // Case7$=class shapeless/Cases$Case7$ of class shapeless/Cases
  public #70= #69 of #6;                  // Case8$=class shapeless/Cases$Case8$ of class shapeless/Cases
  public #73= #72 of #6;                  // Case9$=class shapeless/Cases$Case9$ of class shapeless/Cases
SourceFile: "poly.scala"
  ScalaInlineInfo: length = 0xE5 (unknown attribute)
   01 01 00 2D 00 7A 00 79 01 00 87 00 79 01 00 83
   00 84 01 00 C7 00 79 01 00 C3 00 C4 01 00 CE 00
   79 01 00 CA 00 CB 01 00 D5 00 79 01 00 D1 00 D2
   01 00 DC 00 79 01 00 D8 00 D9 01 00 E3 00 79 01
   00 DF 00 E0 01 00 EA 00 79 01 00 E6 00 E7 01 00
   F1 00 79 01 00 ED 00 EE 01 00 F8 00 79 01 00 F4
   00 F5 01 00 FF 00 79 01 00 FB 00 FC 01 01 06 00
   79 01 01 02 01 03 01 00 8F 00 79 01 00 8B 00 8C
   01 01 0D 00 79 01 01 09 01 0A 01 01 14 00 79 01
   01 10 01 11 01 01 1B 00 79 01 01 17 01 18 01 00
   96 00 79 01 00 92 00 93 01 00 9D 00 79 01 00 99
   00 9A 01 00 A4 00 79 01 00 A0 00 A1 01 00 AB 00
   79 01 00 A7 00 A8 01 00 B2 00 79 01 00 AE 00 AF
   01 00 B9 00 79 01 00 B5 00 B6 01 00 C0 00 79 01
   00 BC 00 BD 01
  Scala: length = 0x0 (unknown attribute)

