Classfile /Users/mw/Projects/slang-braindump/.jar/jar11/assemble/slang-braindump/assemble/content/shapeless/Poly7.class
  Last modified May 29, 2022; size 2919 bytes
  SHA-256 checksum 53518e6763f0e1e92b0bfc1a83fe75851ca95e1437f293b208d52cd51120ef28
  Compiled from "polyntraits.scala"
public interface shapeless.Poly7 extends shapeless.Poly
  minor version: 0
  major version: 52
  flags: (0x0601) ACC_PUBLIC, ACC_INTERFACE, ACC_ABSTRACT
  this_class: #2                          // shapeless/Poly7
  super_class: #4                         // java/lang/Object
  interfaces: 1, fields: 0, methods: 6, attributes: 5
Constant pool:
   #1 = Utf8               shapeless/Poly7
   #2 = Class              #1             // shapeless/Poly7
   #3 = Utf8               java/lang/Object
   #4 = Class              #3             // java/lang/Object
   #5 = Utf8               shapeless/Poly
   #6 = Class              #5             // shapeless/Poly
   #7 = Utf8               polyntraits.scala
   #8 = Utf8               Lscala/reflect/ScalaSignature;
   #9 = Utf8               bytes
  #10 = Utf8               \u0006\u0005\u00055faB\t\u0013!\u0003\r\t!\u0006\u0005\u0006A\u0001!\t!I\u0003\u0005K\u0001\u0001aeB\u0003]\u0001!\u0005QLB\u0003&\u0001!\u0005a\fC\u0003`\t\u0011\u0005\u0001-\u0002\u0003b\t\u0001\u0011gABA\u0002\u0001\u0001\t)\u0001\u0003\u0004`\u000f\u0011\u0005\u0011\u0011\u0002\u0005\b\u0003S9A\u0011AA\u0016\u0011\u001d\t9\u0005\u0001C\u0001\u0003\u0013:q!a\u001b\u0013\u0011\u0003\tiG\u0002\u0004\u0012%!\u0005\u0011q\u000e\u0005\u0007?2!\t!a$\t\u0013\u0005EEB1A\u0005\u0002\u0005M\u0005\u0002CAN\u0019\u0001\u0006I!!&\t\u0013\u0005uE\"!A\u0005\n\u0005}%!\u0002)pYf<$\"A\n\u0002\u0013MD\u0017\r]3mKN\u001c8\u0001A\n\u0004\u0001Ya\u0002CA\f\u001b\u001b\u0005A\"\"A\r\u0002\u000bM\u001c\u0017\r\\1\n\u0005mA\"AB!osJ+g\r\u0005\u0002\u001e=5\t!#\u0003\u0002 %\t!\u0001k\u001c7z\u0003\u0019!\u0013N\\5uIQ\t!\u0005\u0005\u0002\u0018G%\u0011A\u0005\u0007\u0002\u0005+:LGO\u0001\u0003DCN,W\u0003C\u00149\u0007\u001e[ujU,\u0011\t!z#g\r\b\u0003S1r!!\b\u0016\n\u0005-\u0012\u0012a\u00029bG.\fw-Z\u0005\u0003[9\nA\u0001]8ms*\u00111FE\u0005\u0003KAR!!\r\n\u0002\u0013A{G.\u001f#fM:\u001cX\"\u0001\u0001\u0011\tu!d\'Q\u0005\u0003kI\u0011A\u0002J2pY>tGeY8m_:\u0004\"a\u000e\u001d\r\u0001\u0011)\u0011H\u0001b\u0001u\t\t\u0011)\u0005\u0002<}A\u0011q\u0003P\u0005\u0003{a\u0011qAT8uQ&tw\r\u0005\u0002\u0018\u007f%\u0011\u0001\t\u0007\u0002\u0004\u0003:L\b\u0003B\u000f5\u0005\u0016\u0003\"aN\"\u0005\u000b\u0011\u0013!\u0019\u0001\u001e\u0003\u0003\t\u0003B!\b\u001bG\u0013B\u0011qg\u0012\u0003\u0006\u0011\n\u0011\rA\u000f\u0002\u0002\u0007B!Q\u0004\u000e&N!\t94\nB\u0003M\u0005\t\u0007!HA\u0001E!\u0011iBGT)\u0011\u0005]zE!\u0002)\u0003\u0005\u0004Q$!A#\u0011\tu!$+\u0016\t\u0003oM#Q\u0001\u0016\u0002C\u0002i\u0012\u0011A\u0012\t\u0005;Q2\u0016\f\u0005\u00028/\u0012)\u0001L\u0001b\u0001u\t\tq\t\u0005\u0002\u001e5&\u00111L\u0005\u0002\u0005\u0011:KG.\u0001\u0003DCN,\u0007C\u0001\u001a\u0005\'\t!a#\u0001\u0004=S:LGO\u0010\u000b\u0002;\n\u0019\u0011)\u001e=\u0016\u0013\rLGn\u001c:vqn|(C\u00013g\r\u0011)G\u0001A2\u0003\u0019q\u0012XMZ5oK6,g\u000e\u001e \u0011\t!z#g\u001a\t\u0005;QB\'\u000e\u0005\u00028S\u0012)\u0011H\u0002b\u0001uA!Q\u0004N6n!\t9D\u000eB\u0003E\r\t\u0007!\b\u0005\u0003\u001ei9\u0004\bCA\u001cp\t\u0015AeA1\u0001;!\u0011iB\']:\u0011\u0005]\u0012H!\u0002\'\u0007\u0005\u0004Q\u0004\u0003B\u000f5iZ\u0004\"aN;\u0005\u000bA3!\u0019\u0001\u001e\u0011\tu!t/\u001f\t\u0003oa$Q\u0001\u0016\u0004C\u0002i\u0002B!\b\u001b{3B\u0011qg\u001f\u0003\u00061\u001a\u0011\rAO\u0003\u0005{\u0012\u0004cP\u0001\u0004SKN,H\u000e\u001e\t\u0003o}$a!!\u0001\u0007\u0005\u0004Q$a\u0002*fgVdG\u000f\r\u0002\f\u0007\u0006\u001cXMQ;jY\u0012,\'/\u0006\t\u0002\b\u0005=\u00111CA\f\u00037\ty\"a\t\u0002(M\u0011qA\u0006\u000b\u0003\u0003\u0017\u0001\u0002CM\u0004\u0002\u000e\u0005E\u0011QCA\r\u0003;\t\t#!\n\u0011\u0007]\ny\u0001B\u0003:\u000f\t\u0007!\bE\u00028\u0003\'!Q\u0001R\u0004C\u0002i\u00022aNA\f\t\u0015AuA1\u0001;!\r9\u00141\u0004\u0003\u0006\u0019\u001e\u0011\rA\u000f\t\u0004o\u0005}A!\u0002)\b\u0005\u0004Q\u0004cA\u001c\u0002$\u0011)Ak\u0002b\u0001uA\u0019q\'a\n\u0005\u000ba;!\u0019\u0001\u001e\u0002\u000b\u0005\u0004\b\u000f\\=\u0016\t\u00055\u0012\u0011\b\u000b\u0005\u0003_\tiD\u0005\u0003\u00022\u0005Mb!B3\n\u0001\u0005=\u0002\u0003\u0005\u001a\u0003\u0003\u001b\t\t\"!\u0006\u0002\u001a\u0005u\u0011\u0011EA\u0013\u000b\u0019i\u0018\u0011\u0007\u0001\u00028A\u0019q\'!\u000f\u0005\r\u0005m\u0012B1\u0001;\u0005\r\u0011Vm\u001d\u0005\b\u0003\u007fI\u0001\u0019AA!\u0003\t1g\u000eE\n\u0018\u0003\u0007\ni!!\u0005\u0002\u0016\u0005e\u0011QDA\u0011\u0003K\t9$C\u0002\u0002Fa\u0011\u0011BR;oGRLwN\\\u001c\u0002\u0005\u0005$X\u0003EA&\u0003#\n)&!\u0017\u0002^\u0005\u0005\u0014QMA5+\t\ti\u0005\u0005\t3\u000f\u0005=\u00131KA,\u00037\ny&a\u0019\u0002hA\u0019q\'!\u0015\u0005\u000beR!\u0019\u0001\u001e\u0011\u0007]\n)\u0006B\u0003E\u0015\t\u0007!\bE\u00028\u00033\"Q\u0001\u0013\u0006C\u0002i\u00022aNA/\t\u0015a%B1\u0001;!\r9\u0014\u0011\r\u0003\u0006!*\u0011\rA\u000f\t\u0004o\u0005\u0015D!\u0002+\u000b\u0005\u0004Q\u0004cA\u001c\u0002j\u0011)\u0001L\u0003b\u0001u\u0005)\u0001k\u001c7zoA\u0011Q\u0004D\n\u0007\u0019Y\t\t(a \u0011\u000b\u0005M\u0014\u0011P-\u000f\u0007u\t)(C\u0002\u0002xI\tQ\u0002U8ms:\u0013U/\u001b7eKJ\u001c\u0018\u0002BA>\u0003{\u0012A\u0002U8ms^\u0012U/\u001b7eKJT1!a\u001e\u0013!\u0011\t\t)a#\u000e\u0005\u0005\r%\u0002BAC\u0003\u000f\u000b!![8\u000b\u0005\u0005%\u0015\u0001\u00026bm\u0006LA!!$\u0002\u0004\na1+\u001a:jC2L\'0\u00192mKR\u0011\u0011QN\u0001\nMVt7\r^5p]N,\"!!&\u000f\u0007u\t9*C\u0002\u0002\u001aJ\tA\u0001\u0013(jY\u0006Qa-\u001e8di&|gn\u001d\u0011\u0002\u0019]\u0014\u0018\u000e^3SKBd\u0017mY3\u0015\u0005\u0005\u0005\u0006\u0003BAR\u0003Sk!!!*\u000b\t\u0005\u001d\u0016qQ\u0001\u0005Y\u0006tw-\u0003\u0003\u0002,\u0006\u0015&AB(cU\u0016\u001cG\u000f
  #11 = Utf8               shapeless/Poly7$Case$
  #12 = Class              #11            // shapeless/Poly7$Case$
  #13 = Utf8               Case$
  #14 = Utf8               shapeless/Poly7$CaseBuilder
  #15 = Class              #14            // shapeless/Poly7$CaseBuilder
  #16 = Utf8               CaseBuilder
  #17 = Utf8               functions
  #18 = Utf8               ()Lshapeless/HNil$;
  #19 = Utf8               shapeless/Poly7$
  #20 = Class              #19            // shapeless/Poly7$
  #21 = Utf8               MODULE$
  #22 = Utf8               Lshapeless/Poly7$;
  #23 = NameAndType        #21:#22        // MODULE$:Lshapeless/Poly7$;
  #24 = Fieldref           #20.#23        // shapeless/Poly7$.MODULE$:Lshapeless/Poly7$;
  #25 = NameAndType        #17:#18        // functions:()Lshapeless/HNil$;
  #26 = Methodref          #20.#25        // shapeless/Poly7$.functions:()Lshapeless/HNil$;
  #27 = Utf8               build
  #28 = Utf8               ()Lshapeless/Poly7;
  #29 = NameAndType        #27:#28        // build:()Lshapeless/Poly7;
  #30 = Methodref          #20.#29        // shapeless/Poly7$.build:()Lshapeless/Poly7;
  #31 = Utf8               Case
  #32 = Utf8               ()Lshapeless/Poly7$Case$;
  #33 = Utf8               at$
  #34 = Utf8               (Lshapeless/Poly7;)Lshapeless/Poly7$CaseBuilder;
  #35 = Utf8               $this
  #36 = Utf8               at
  #37 = Utf8               ()Lshapeless/Poly7$CaseBuilder;
  #38 = NameAndType        #36:#37        // at:()Lshapeless/Poly7$CaseBuilder;
  #39 = InterfaceMethodref #2.#38         // shapeless/Poly7.at:()Lshapeless/Poly7$CaseBuilder;
  #40 = Utf8               Lshapeless/Poly7;
  #41 = Utf8               <A:Ljava/lang/Object;B:Ljava/lang/Object;C:Ljava/lang/Object;D:Ljava/lang/Object;E:Ljava/lang/Object;F:Ljava/lang/Object;G:Ljava/lang/Object;>()Lshapeless/Poly7$CaseBuilder<TA;TB;TC;TD;TE;TF;TG;>;
  #42 = Utf8               <init>
  #43 = Utf8               (Lshapeless/Poly7;)V
  #44 = NameAndType        #42:#43        // "<init>":(Lshapeless/Poly7;)V
  #45 = Methodref          #15.#44        // shapeless/Poly7$CaseBuilder."<init>":(Lshapeless/Poly7;)V
  #46 = Utf8               this
  #47 = Utf8               $init$
  #48 = Utf8               Code
  #49 = Utf8               LineNumberTable
  #50 = Utf8               LocalVariableTable
  #51 = Utf8               MethodParameters
  #52 = Utf8               Signature
  #53 = Utf8               InnerClasses
  #54 = Utf8               SourceFile
  #55 = Utf8               RuntimeVisibleAnnotations
  #56 = Utf8               ScalaInlineInfo
  #57 = Utf8               ScalaSig
{
  public static shapeless.HNil$ functions();
    descriptor: ()Lshapeless/HNil$;
    flags: (0x0009) ACC_PUBLIC, ACC_STATIC
    Code:
      stack=1, locals=0, args_size=0
         0: getstatic     #24                 // Field shapeless/Poly7$.MODULE$:Lshapeless/Poly7$;
         3: invokevirtual #26                 // Method shapeless/Poly7$.functions:()Lshapeless/HNil$;
         6: areturn

  public static shapeless.Poly7 build();
    descriptor: ()Lshapeless/Poly7;
    flags: (0x0009) ACC_PUBLIC, ACC_STATIC
    Code:
      stack=1, locals=0, args_size=0
         0: getstatic     #24                 // Field shapeless/Poly7$.MODULE$:Lshapeless/Poly7$;
         3: invokevirtual #30                 // Method shapeless/Poly7$.build:()Lshapeless/Poly7;
         6: areturn

  public abstract shapeless.Poly7$Case$ Case();
    descriptor: ()Lshapeless/Poly7$Case$;
    flags: (0x0401) ACC_PUBLIC, ACC_ABSTRACT

  public static shapeless.Poly7$CaseBuilder at$(shapeless.Poly7);
    descriptor: (Lshapeless/Poly7;)Lshapeless/Poly7$CaseBuilder;
    flags: (0x1009) ACC_PUBLIC, ACC_STATIC, ACC_SYNTHETIC
    Code:
      stack=1, locals=1, args_size=1
         0: aload_0
         1: invokespecial #39                 // InterfaceMethod at:()Lshapeless/Poly7$CaseBuilder;
         4: areturn
      LineNumberTable:
        line 196: 0
      LocalVariableTable:
        Start  Length  Slot  Name   Signature
            0       5     0 $this   Lshapeless/Poly7;
    MethodParameters:
      Name                           Flags
      $this                          final synthetic

  public default <A extends java.lang.Object, B extends java.lang.Object, C extends java.lang.Object, D extends java.lang.Object, E extends java.lang.Object, F extends java.lang.Object, G extends java.lang.Object> shapeless.Poly7$CaseBuilder<A, B, C, D, E, F, G> at();
    descriptor: ()Lshapeless/Poly7$CaseBuilder;
    flags: (0x0001) ACC_PUBLIC
    Code:
      stack=3, locals=1, args_size=1
         0: new           #15                 // class shapeless/Poly7$CaseBuilder
         3: dup
         4: aload_0
         5: invokespecial #45                 // Method shapeless/Poly7$CaseBuilder."<init>":(Lshapeless/Poly7;)V
         8: areturn
      LineNumberTable:
        line 197: 0
      LocalVariableTable:
        Start  Length  Slot  Name   Signature
            0       9     0  this   Lshapeless/Poly7;
    Signature: #41                          // <A:Ljava/lang/Object;B:Ljava/lang/Object;C:Ljava/lang/Object;D:Ljava/lang/Object;E:Ljava/lang/Object;F:Ljava/lang/Object;G:Ljava/lang/Object;>()Lshapeless/Poly7$CaseBuilder<TA;TB;TC;TD;TE;TF;TG;>;

  public static void $init$(shapeless.Poly7);
    descriptor: (Lshapeless/Poly7;)V
    flags: (0x0009) ACC_PUBLIC, ACC_STATIC
    Code:
      stack=0, locals=1, args_size=1
         0: return
      LineNumberTable:
        line 178: 0
      LocalVariableTable:
        Start  Length  Slot  Name   Signature
            0       1     0 $this   Lshapeless/Poly7;
    MethodParameters:
      Name                           Flags
      $this                          final synthetic
}
InnerClasses:
  public #13= #12 of #2;                  // Case$=class shapeless/Poly7$Case$ of class shapeless/Poly7
  public #16= #15 of #2;                  // CaseBuilder=class shapeless/Poly7$CaseBuilder of class shapeless/Poly7
SourceFile: "polyntraits.scala"
RuntimeVisibleAnnotations:
  0: #8(#9=s#10)
    scala.reflect.ScalaSignature(
      bytes="\u0006\u0005\u00055faB\t\u0013!\u0003\r\t!\u0006\u0005\u0006A\u0001!\t!I\u0003\u0005K\u0001\u0001aeB\u0003]\u0001!\u0005QLB\u0003&\u0001!\u0005a\fC\u0003`\t\u0011\u0005\u0001-\u0002\u0003b\t\u0001\u0011gABA\u0002\u0001\u0001\t)\u0001\u0003\u0004`\u000f\u0011\u0005\u0011\u0011\u0002\u0005\b\u0003S9A\u0011AA\u0016\u0011\u001d\t9\u0005\u0001C\u0001\u0003\u0013:q!a\u001b\u0013\u0011\u0003\tiG\u0002\u0004\u0012%!\u0005\u0011q\u000e\u0005\u0007?2!\t!a$\t\u0013\u0005EEB1A\u0005\u0002\u0005M\u0005\u0002CAN\u0019\u0001\u0006I!!&\t\u0013\u0005uE\"!A\u0005\n\u0005}%!\u0002)pYf<$\"A\n\u0002\u0013MD\u0017\r]3mKN\u001c8\u0001A\n\u0004\u0001Ya\u0002CA\f\u001b\u001b\u0005A\"\"A\r\u0002\u000bM\u001c\u0017\r\\1\n\u0005mA\"AB!osJ+g\r\u0005\u0002\u001e=5\t!#\u0003\u0002 %\t!\u0001k\u001c7z\u0003\u0019!\u0013N\\5uIQ\t!\u0005\u0005\u0002\u0018G%\u0011A\u0005\u0007\u0002\u0005+:LGO\u0001\u0003DCN,W\u0003C\u00149\u0007\u001e[ujU,\u0011\t!z#g\r\b\u0003S1r!!\b\u0016\n\u0005-\u0012\u0012a\u00029bG.\fw-Z\u0005\u0003[9\nA\u0001]8ms*\u00111FE\u0005\u0003KAR!!\r\n\u0002\u0013A{G.\u001f#fM:\u001cX\"\u0001\u0001\u0011\tu!d\'Q\u0005\u0003kI\u0011A\u0002J2pY>tGeY8m_:\u0004\"a\u000e\u001d\r\u0001\u0011)\u0011H\u0001b\u0001u\t\t\u0011)\u0005\u0002<}A\u0011q\u0003P\u0005\u0003{a\u0011qAT8uQ&tw\r\u0005\u0002\u0018\u007f%\u0011\u0001\t\u0007\u0002\u0004\u0003:L\b\u0003B\u000f5\u0005\u0016\u0003\"aN\"\u0005\u000b\u0011\u0013!\u0019\u0001\u001e\u0003\u0003\t\u0003B!\b\u001bG\u0013B\u0011qg\u0012\u0003\u0006\u0011\n\u0011\rA\u000f\u0002\u0002\u0007B!Q\u0004\u000e&N!\t94\nB\u0003M\u0005\t\u0007!HA\u0001E!\u0011iBGT)\u0011\u0005]zE!\u0002)\u0003\u0005\u0004Q$!A#\u0011\tu!$+\u0016\t\u0003oM#Q\u0001\u0016\u0002C\u0002i\u0012\u0011A\u0012\t\u0005;Q2\u0016\f\u0005\u00028/\u0012)\u0001L\u0001b\u0001u\t\tq\t\u0005\u0002\u001e5&\u00111L\u0005\u0002\u0005\u0011:KG.\u0001\u0003DCN,\u0007C\u0001\u001a\u0005\'\t!a#\u0001\u0004=S:LGO\u0010\u000b\u0002;\n\u0019\u0011)\u001e=\u0016\u0013\rLGn\u001c:vqn|(C\u00013g\r\u0011)G\u0001A2\u0003\u0019q\u0012XMZ5oK6,g\u000e\u001e \u0011\t!z#g\u001a\t\u0005;QB\'\u000e\u0005\u00028S\u0012)\u0011H\u0002b\u0001uA!Q\u0004N6n!\t9D\u000eB\u0003E\r\t\u0007!\b\u0005\u0003\u001ei9\u0004\bCA\u001cp\t\u0015AeA1\u0001;!\u0011iB\']:\u0011\u0005]\u0012H!\u0002\'\u0007\u0005\u0004Q\u0004\u0003B\u000f5iZ\u0004\"aN;\u0005\u000bA3!\u0019\u0001\u001e\u0011\tu!t/\u001f\t\u0003oa$Q\u0001\u0016\u0004C\u0002i\u0002B!\b\u001b{3B\u0011qg\u001f\u0003\u00061\u001a\u0011\rAO\u0003\u0005{\u0012\u0004cP\u0001\u0004SKN,H\u000e\u001e\t\u0003o}$a!!\u0001\u0007\u0005\u0004Q$a\u0002*fgVdG\u000f\r\u0002\f\u0007\u0006\u001cXMQ;jY\u0012,\'/\u0006\t\u0002\b\u0005=\u00111CA\f\u00037\ty\"a\t\u0002(M\u0011qA\u0006\u000b\u0003\u0003\u0017\u0001\u0002CM\u0004\u0002\u000e\u0005E\u0011QCA\r\u0003;\t\t#!\n\u0011\u0007]\ny\u0001B\u0003:\u000f\t\u0007!\bE\u00028\u0003\'!Q\u0001R\u0004C\u0002i\u00022aNA\f\t\u0015AuA1\u0001;!\r9\u00141\u0004\u0003\u0006\u0019\u001e\u0011\rA\u000f\t\u0004o\u0005}A!\u0002)\b\u0005\u0004Q\u0004cA\u001c\u0002$\u0011)Ak\u0002b\u0001uA\u0019q\'a\n\u0005\u000ba;!\u0019\u0001\u001e\u0002\u000b\u0005\u0004\b\u000f\\=\u0016\t\u00055\u0012\u0011\b\u000b\u0005\u0003_\tiD\u0005\u0003\u00022\u0005Mb!B3\n\u0001\u0005=\u0002\u0003\u0005\u001a\u0003\u0003\u001b\t\t\"!\u0006\u0002\u001a\u0005u\u0011\u0011EA\u0013\u000b\u0019i\u0018\u0011\u0007\u0001\u00028A\u0019q\'!\u000f\u0005\r\u0005m\u0012B1\u0001;\u0005\r\u0011Vm\u001d\u0005\b\u0003\u007fI\u0001\u0019AA!\u0003\t1g\u000eE\n\u0018\u0003\u0007\ni!!\u0005\u0002\u0016\u0005e\u0011QDA\u0011\u0003K\t9$C\u0002\u0002Fa\u0011\u0011BR;oGRLwN\\\u001c\u0002\u0005\u0005$X\u0003EA&\u0003#\n)&!\u0017\u0002^\u0005\u0005\u0014QMA5+\t\ti\u0005\u0005\t3\u000f\u0005=\u00131KA,\u00037\ny&a\u0019\u0002hA\u0019q\'!\u0015\u0005\u000beR!\u0019\u0001\u001e\u0011\u0007]\n)\u0006B\u0003E\u0015\t\u0007!\bE\u00028\u00033\"Q\u0001\u0013\u0006C\u0002i\u00022aNA/\t\u0015a%B1\u0001;!\r9\u0014\u0011\r\u0003\u0006!*\u0011\rA\u000f\t\u0004o\u0005\u0015D!\u0002+\u000b\u0005\u0004Q\u0004cA\u001c\u0002j\u0011)\u0001L\u0003b\u0001u\u0005)\u0001k\u001c7zoA\u0011Q\u0004D\n\u0007\u0019Y\t\t(a \u0011\u000b\u0005M\u0014\u0011P-\u000f\u0007u\t)(C\u0002\u0002xI\tQ\u0002U8ms:\u0013U/\u001b7eKJ\u001c\u0018\u0002BA>\u0003{\u0012A\u0002U8ms^\u0012U/\u001b7eKJT1!a\u001e\u0013!\u0011\t\t)a#\u000e\u0005\u0005\r%\u0002BAC\u0003\u000f\u000b!![8\u000b\u0005\u0005%\u0015\u0001\u00026bm\u0006LA!!$\u0002\u0004\na1+\u001a:jC2L\'0\u00192mKR\u0011\u0011QN\u0001\nMVt7\r^5p]N,\"!!&\u000f\u0007u\t9*C\u0002\u0002\u001aJ\tA\u0001\u0013(jY\u0006Qa-\u001e8di&|gn\u001d\u0011\u0002\u0019]\u0014\u0018\u000e^3SKBd\u0017mY3\u0015\u0005\u0005\u0005\u0006\u0003BAR\u0003Sk!!!*\u000b\t\u0005\u001d\u0016qQ\u0001\u0005Y\u0006tw-\u0003\u0003\u0002,\u0006\u0015&AB(cU\u0016\u001cG\u000f"
    )
  ScalaInlineInfo: length = 0x18 (unknown attribute)
   01 00 00 04 00 2F 00 2B 01 00 1F 00 20 00 00 21
   00 22 01 00 24 00 25 00
  ScalaSig: length = 0x3 (unknown attribute)
   05 02 00
