Classfile /Users/mw/Projects/slang-braindump/.jar/jar11/assemble/slang-braindump/assemble/content/shapeless/Poly22.class
  Last modified May 29, 2022; size 4751 bytes
  SHA-256 checksum 926f86a921203cf2f6b9fd606547cc74899c00a17b226f708767a668ec13a6d8
  Compiled from "polyntraits.scala"
public interface shapeless.Poly22 extends shapeless.Poly
  minor version: 0
  major version: 52
  flags: (0x0601) ACC_PUBLIC, ACC_INTERFACE, ACC_ABSTRACT
  this_class: #2                          // shapeless/Poly22
  super_class: #4                         // java/lang/Object
  interfaces: 1, fields: 0, methods: 6, attributes: 5
Constant pool:
   #1 = Utf8               shapeless/Poly22
   #2 = Class              #1             // shapeless/Poly22
   #3 = Utf8               java/lang/Object
   #4 = Class              #3             // java/lang/Object
   #5 = Utf8               shapeless/Poly
   #6 = Class              #5             // shapeless/Poly
   #7 = Utf8               polyntraits.scala
   #8 = Utf8               Lscala/reflect/ScalaSignature;
   #9 = Utf8               bytes
  #10 = Utf8               \u0006\u0005\t]haB\t\u0013!\u0003\r\t!\u0006\u0005\u0006A\u0001!\t!I\u0003\u0005K\u0001\u0001aeB\u0004\u00022\u0001A\t!a\r\u0007\r\u0015\u0002\u0001\u0012AA\u001b\u0011\u001d\t9\u0004\u0002C\u0001\u0003s)a!a\u000f\u0005\u0001\u0005ubABAk\u0001\u0001\t9\u000eC\u0004\u00028\u001d!\t!a7\t\u000f\t]r\u0001\"\u0001\u0003:!9!Q\u000b\u0001\u0005\u0002\t]sa\u0002B[%!\u0005!q\u0017\u0004\u0007#IA\tA!/\t\u000f\u0005]B\u0002\"\u0001\u0003Z\"I!1\u001c\u0007C\u0002\u0013\u0005!Q\u001c\u0005\t\u0005Kd\u0001\u0015!\u0003\u0003`\"I!q\u001d\u0007\u0002\u0002\u0013%!\u0011\u001e\u0002\u0007!>d\u0017P\r\u001a\u000b\u0003M\t\u0011b\u001d5ba\u0016dWm]:\u0004\u0001M\u0019\u0001A\u0006\u000f\u0011\u0005]QR\"\u0001\r\u000b\u0003e\tQa]2bY\u0006L!a\u0007\r\u0003\r\u0005s\u0017PU3g!\tib$D\u0001\u0013\u0013\ty\"C\u0001\u0003Q_2L\u0018A\u0002\u0013j]&$H\u0005F\u0001#!\t92%\u0003\u0002%1\t!QK\\5u\u0005\u0011\u0019\u0015m]3\u00169\u001dB4iR&P\'^[vlY4l_N<8p`A\u0004\u0003\u001f\t9\"a\b\u0002(A!\u0001f\f\u001a4\u001d\tICF\u0004\u0002\u001eU%\u00111FE\u0001\ba\u0006\u001c7.Y4f\u0013\tic&\u0001\u0003q_2L(BA\u0016\u0013\u0013\t)\u0003G\u0003\u00022%\u0005I\u0001k\u001c7z\t\u00164gn]\u0007\u0002\u0001A!Q\u0004\u000e\u001cB\u0013\t)$C\u0001\u0007%G>dwN\u001c\u0013d_2|g\u000e\u0005\u00028q1\u0001A!B\u001d\u0003\u0005\u0004Q$!A!\u0012\u0005mr\u0004CA\f=\u0013\ti\u0004DA\u0004O_RD\u0017N\\4\u0011\u0005]y\u0014B\u0001!\u0019\u0005\r\te.\u001f\t\u0005;Q\u0012U\t\u0005\u00028\u0007\u0012)AI\u0001b\u0001u\t\t!\t\u0005\u0003\u001ei\u0019K\u0005CA\u001cH\t\u0015A%A1\u0001;\u0005\u0005\u0019\u0005\u0003B\u000f5\u00156\u0003\"aN&\u0005\u000b1\u0013!\u0019\u0001\u001e\u0003\u0003\u0011\u0003B!\b\u001bO#B\u0011qg\u0014\u0003\u0006!\n\u0011\rA\u000f\u0002\u0002\u000bB!Q\u0004\u000e*V!\t94\u000bB\u0003U\u0005\t\u0007!HA\u0001G!\u0011iBGV-\u0011\u0005]:F!\u0002-\u0003\u0005\u0004Q$!A$\u0011\tu!$,\u0018\t\u0003om#Q\u0001\u0018\u0002C\u0002i\u0012\u0011\u0001\u0013\t\u0005;Qr\u0016\r\u0005\u00028?\u0012)\u0001M\u0001b\u0001u\t\t\u0011\n\u0005\u0003\u001ei\t,\u0007CA\u001cd\t\u0015!\'A1\u0001;\u0005\u0005Q\u0005\u0003B\u000f5M&\u0004\"aN4\u0005\u000b!\u0014!\u0019\u0001\u001e\u0003\u0003-\u0003B!\b\u001bk[B\u0011qg\u001b\u0003\u0006Y\n\u0011\rA\u000f\u0002\u0002\u0019B!Q\u0004\u000e8r!\t9t\u000eB\u0003q\u0005\t\u0007!HA\u0001N!\u0011iBG];\u0011\u0005]\u001aH!\u0002;\u0003\u0005\u0004Q$!\u0001(\u0011\tu!d/\u001f\t\u0003o]$Q\u0001\u001f\u0002C\u0002i\u0012\u0011a\u0014\t\u0005;QRX\u0010\u0005\u00028w\u0012)AP\u0001b\u0001u\t\t\u0001\u000bE\u0003\u001eiy\f\u0019\u0001\u0005\u00028\u007f\u00121\u0011\u0011\u0001\u0002C\u0002i\u0012\u0011!\u0015\t\u0007;Q\n)!a\u0003\u0011\u0007]\n9\u0001\u0002\u0004\u0002\n\t\u0011\rA\u000f\u0002\u0002%B1Q\u0004NA\u0007\u0003\'\u00012aNA\b\t\u0019\t\tB\u0001b\u0001u\t\t1\u000b\u0005\u0004\u001ei\u0005U\u00111\u0004\t\u0004o\u0005]AABA\r\u0005\t\u0007!HA\u0001U!\u0019iB\'!\b\u0002$A\u0019q\'a\b\u0005\r\u0005\u0005\"A1\u0001;\u0005\u0005)\u0006CB\u000f5\u0003K\tY\u0003E\u00028\u0003O!a!!\u000b\u0003\u0005\u0004Q$!\u0001,\u0011\u0007u\ti#C\u0002\u00020I\u0011A\u0001\u0013(jY\u0006!1)Y:f!\t\u0011Da\u0005\u0002\u0005-\u00051A(\u001b8jiz\"\"!a\r\u0003\u0007\u0005+\b0\u0006\u0019\u0002@\u0005-\u0013\u0011KA,\u0003;\n\u0019\'!\u001b\u0002p\u0005U\u00141PAA\u0003\u000f\u000bi)a%\u0002\u001a\u0006}\u0015QUAV\u0003c\u000b9,!0\u0002D\u0006%\u0017\u0011\u001b\n\u0005\u0003\u0003\n)E\u0002\u0004\u0002D\u0011\u0001\u0011q\b\u0002\ryI,g-\u001b8f[\u0016tGO\u0010\t\u0006Q=\u0012\u0014q\t\t\u0007;Q\nI%!\u0014\u0011\u0007]\nY\u0005B\u0003:\r\t\u0007!\b\u0005\u0004\u001ei\u0005=\u00131\u000b\t\u0004o\u0005EC!\u0002#\u0007\u0005\u0004Q\u0004CB\u000f5\u0003+\nI\u0006E\u00028\u0003/\"Q\u0001\u0013\u0004C\u0002i\u0002b!\b\u001b\u0002\\\u0005}\u0003cA\u001c\u0002^\u0011)AJ\u0002b\u0001uA1Q\u0004NA1\u0003K\u00022aNA2\t\u0015\u0001fA1\u0001;!\u0019iB\'a\u001a\u0002lA\u0019q\'!\u001b\u0005\u000bQ3!\u0019\u0001\u001e\u0011\ru!\u0014QNA9!\r9\u0014q\u000e\u0003\u00061\u001a\u0011\rA\u000f\t\u0007;Q\n\u0019(a\u001e\u0011\u0007]\n)\bB\u0003]\r\t\u0007!\b\u0005\u0004\u001ei\u0005e\u0014Q\u0010\t\u0004o\u0005mD!\u00021\u0007\u0005\u0004Q\u0004CB\u000f5\u0003\u007f\n\u0019\tE\u00028\u0003\u0003#Q\u0001\u001a\u0004C\u0002i\u0002b!\b\u001b\u0002\u0006\u0006%\u0005cA\u001c\u0002\b\u0012)\u0001N\u0002b\u0001uA1Q\u0004NAF\u0003\u001f\u00032aNAG\t\u0015agA1\u0001;!\u0019iB\'!%\u0002\u0016B\u0019q\'a%\u0005\u000bA4!\u0019\u0001\u001e\u0011\ru!\u0014qSAN!\r9\u0014\u0011\u0014\u0003\u0006i\u001a\u0011\rA\u000f\t\u0007;Q\ni*!)\u0011\u0007]\ny\nB\u0003y\r\t\u0007!\b\u0005\u0004\u001ei\u0005\r\u0016q\u0015\t\u0004o\u0005\u0015F!\u0002?\u0007\u0005\u0004Q\u0004CB\u000f5\u0003S\u000bi\u000bE\u00028\u0003W#a!!\u0001\u0007\u0005\u0004Q\u0004CB\u000f5\u0003_\u000b\u0019\fE\u00028\u0003c#a!!\u0003\u0007\u0005\u0004Q\u0004CB\u000f5\u0003k\u000bI\fE\u00028\u0003o#a!!\u0005\u0007\u0005\u0004Q\u0004CB\u000f5\u0003w\u000by\fE\u00028\u0003{#a!!\u0007\u0007\u0005\u0004Q\u0004CB\u000f5\u0003\u0003\f)\rE\u00028\u0003\u0007$a!!\t\u0007\u0005\u0004Q\u0004CB\u000f5\u0003\u000f\fY\u0003E\u00028\u0003\u0013$a!!\u000b\u0007\u0005\u0004QTaBAg\u0003\u0003\u0002\u0013q\u001a\u0002\u0007%\u0016\u001cX\u000f\u001c;\u0011\u0007]\n\t\u000e\u0002\u0004\u0002T\u001a\u0011\rA\u000f\u0002\b%\u0016\u001cX\u000f\u001c;1\u0005-\u0019\u0015m]3Ck&dG-\u001a:\u0016]\u0005e\u0017\u0011]As\u0003S\fi/!=\u0002v\u0006e\u0018Q B\u0001\u0005\u000b\u0011IA!\u0004\u0003\u0012\tU!\u0011\u0004B\u000f\u0005C\u0011)C!\u000b\u0003.\tE\"QG\n\u0003\u000fY!\"!!8\u0011]I:\u0011q\\Ar\u0003O\fY/a<\u0002t\u0006]\u00181`A\u0000\u0005\u0007\u00119Aa\u0003\u0003\u0010\tM!q\u0003B\u000e\u0005?\u0011\u0019Ca\n\u0003,\t=\"1\u0007\t\u0004o\u0005\u0005H!B\u001d\b\u0005\u0004Q\u0004cA\u001c\u0002f\u0012)Ai\u0002b\u0001uA\u0019q\'!;\u0005\u000b!;!\u0019\u0001\u001e\u0011\u0007]\ni\u000fB\u0003M\u000f\t\u0007!\bE\u00028\u0003c$Q\u0001U\u0004C\u0002i\u00022aNA{\t\u0015!vA1\u0001;!\r9\u0014\u0011 \u0003\u00061\u001e\u0011\rA\u000f\t\u0004o\u0005uH!\u0002/\b\u0005\u0004Q\u0004cA\u001c\u0003\u0002\u0011)\u0001m\u0002b\u0001uA\u0019qG!\u0002\u0005\u000b\u0011<!\u0019\u0001\u001e\u0011\u0007]\u0012I\u0001B\u0003i\u000f\t\u0007!\bE\u00028\u0005\u001b!Q\u0001\\\u0004C\u0002i\u00022a\u000eB\t\t\u0015\u0001xA1\u0001;!\r9$Q\u0003\u0003\u0006i\u001e\u0011\rA\u000f\t\u0004o\teA!\u0002=\b\u0005\u0004Q\u0004cA\u001c\u0003\u001e\u0011)Ap\u0002b\u0001uA\u0019qG!\t\u0005\r\u0005\u0005qA1\u0001;!\r9$Q\u0005\u0003\u0007\u0003\u00139!\u0019\u0001\u001e\u0011\u0007]\u0012I\u0003\u0002\u0004\u0002\u0012\u001d\u0011\rA\u000f\t\u0004o\t5BABA\r\u000f\t\u0007!\bE\u00028\u0005c!a!!\t\b\u0005\u0004Q\u0004cA\u001c\u00036\u00111\u0011\u0011F\u0004C\u0002i\nQ!\u00199qYf,BAa\u000f\u0003HQ!!Q\bB&%\u0011\u0011yD!\u0011\u0007\r\u0005\r\u0013\u0002\u0001B\u001f!9\u0012$!a8\u0002d\u0006\u001d\u00181^Ax\u0003g\f90a?\u0002\u0000\n\r!q\u0001B\u0006\u0005\u001f\u0011\u0019Ba\u0006\u0003\u001c\t}!1\u0005B\u0014\u0005W\u0011yCa\r\u0006\u000f\u00055\'q\b\u0001\u0003FA\u0019qGa\u0012\u0005\r\t%\u0013B1\u0001;\u0005\r\u0011Vm\u001d\u0005\b\u0005\u001bJ\u0001\u0019\u0001B(\u0003\t1g\u000eE\u0019\u0018\u0005#\ny.a9\u0002h\u0006-\u0018q^Az\u0003o\fY0a@\u0003\u0004\t\u001d!1\u0002B\b\u0005\'\u00119Ba\u0007\u0003 \t\r\"q\u0005B\u0016\u0005_\u0011\u0019D!\u0012\n\u0007\tM\u0003D\u0001\u0006Gk:\u001cG/[8oeI\n!!\u0019;\u0016]\te#q\fB2\u0005O\u0012YGa\u001c\u0003t\t]$1\u0010B@\u0005\u0007\u00139Ia#\u0003\u0010\nM%q\u0013BN\u0005?\u0013\u0019Ka*\u0003,\n=&1W\u000b\u0003\u00057\u0002bFM\u0004\u0003^\t\u0005$Q\rB5\u0005[\u0012\tH!\u001e\u0003z\tu$\u0011\u0011BC\u0005\u0013\u0013iI!%\u0003\u0016\ne%Q\u0014BQ\u0005K\u0013IK!,\u00032B\u0019qGa\u0018\u0005\u000beR!\u0019\u0001\u001e\u0011\u0007]\u0012\u0019\u0007B\u0003E\u0015\t\u0007!\bE\u00028\u0005O\"Q\u0001\u0013\u0006C\u0002i\u00022a\u000eB6\t\u0015a%B1\u0001;!\r9$q\u000e\u0003\u0006!*\u0011\rA\u000f\t\u0004o\tMD!\u0002+\u000b\u0005\u0004Q\u0004cA\u001c\u0003x\u0011)\u0001L\u0003b\u0001uA\u0019qGa\u001f\u0005\u000bqS!\u0019\u0001\u001e\u0011\u0007]\u0012y\bB\u0003a\u0015\t\u0007!\bE\u00028\u0005\u0007#Q\u0001\u001a\u0006C\u0002i\u00022a\u000eBD\t\u0015A\'B1\u0001;!\r9$1\u0012\u0003\u0006Y*\u0011\rA\u000f\t\u0004o\t=E!\u00029\u000b\u0005\u0004Q\u0004cA\u001c\u0003\u0014\u0012)AO\u0003b\u0001uA\u0019qGa&\u0005\u000baT!\u0019\u0001\u001e\u0011\u0007]\u0012Y\nB\u0003}\u0015\t\u0007!\bE\u00028\u0005?#a!!\u0001\u000b\u0005\u0004Q\u0004cA\u001c\u0003$\u00121\u0011\u0011\u0002\u0006C\u0002i\u00022a\u000eBT\t\u0019\t\tB\u0003b\u0001uA\u0019qGa+\u0005\r\u0005e!B1\u0001;!\r9$q\u0016\u0003\u0007\u0003CQ!\u0019\u0001\u001e\u0011\u0007]\u0012\u0019\f\u0002\u0004\u0002*)\u0011\rAO\u0001\u0007!>d\u0017P\r\u001a\u0011\u0005ua1C\u0002\u0007\u0017\u0005w\u0013I\r\u0005\u0004\u0003>\n\r\u00171\u0006\b\u0004;\t}\u0016b\u0001Ba%\u0005i\u0001k\u001c7z\u001d\n+\u0018\u000e\u001c3feNLAA!2\u0003H\ni\u0001k\u001c7zeI\u0012U/\u001b7eKJT1A!1\u0013!\u0011\u0011YM!6\u000e\u0005\t5\'\u0002\u0002Bh\u0005#\f!![8\u000b\u0005\tM\u0017\u0001\u00026bm\u0006LAAa6\u0003N\na1+\u001a:jC2L\'0\u00192mKR\u0011!qW\u0001\nMVt7\r^5p]N,\"Aa8\u000f\u0007u\u0011\t/C\u0002\u0003dJ\tA\u0001\u0013(jY\u0006Qa-\u001e8di&|gn\u001d\u0011\u0002\u0019]\u0014\u0018\u000e^3SKBd\u0017mY3\u0015\u0005\t-\b\u0003\u0002Bw\u0005gl!Aa<\u000b\t\tE(\u0011[\u0001\u0005Y\u0006tw-\u0003\u0003\u0003v\n=(AB(cU\u0016\u001cG\u000f
  #11 = Utf8               shapeless/Poly22$Case$
  #12 = Class              #11            // shapeless/Poly22$Case$
  #13 = Utf8               Case$
  #14 = Utf8               shapeless/Poly22$CaseBuilder
  #15 = Class              #14            // shapeless/Poly22$CaseBuilder
  #16 = Utf8               CaseBuilder
  #17 = Utf8               functions
  #18 = Utf8               ()Lshapeless/HNil$;
  #19 = Utf8               shapeless/Poly22$
  #20 = Class              #19            // shapeless/Poly22$
  #21 = Utf8               MODULE$
  #22 = Utf8               Lshapeless/Poly22$;
  #23 = NameAndType        #21:#22        // MODULE$:Lshapeless/Poly22$;
  #24 = Fieldref           #20.#23        // shapeless/Poly22$.MODULE$:Lshapeless/Poly22$;
  #25 = NameAndType        #17:#18        // functions:()Lshapeless/HNil$;
  #26 = Methodref          #20.#25        // shapeless/Poly22$.functions:()Lshapeless/HNil$;
  #27 = Utf8               build
  #28 = Utf8               ()Lshapeless/Poly22;
  #29 = NameAndType        #27:#28        // build:()Lshapeless/Poly22;
  #30 = Methodref          #20.#29        // shapeless/Poly22$.build:()Lshapeless/Poly22;
  #31 = Utf8               Case
  #32 = Utf8               ()Lshapeless/Poly22$Case$;
  #33 = Utf8               at$
  #34 = Utf8               (Lshapeless/Poly22;)Lshapeless/Poly22$CaseBuilder;
  #35 = Utf8               $this
  #36 = Utf8               at
  #37 = Utf8               ()Lshapeless/Poly22$CaseBuilder;
  #38 = NameAndType        #36:#37        // at:()Lshapeless/Poly22$CaseBuilder;
  #39 = InterfaceMethodref #2.#38         // shapeless/Poly22.at:()Lshapeless/Poly22$CaseBuilder;
  #40 = Utf8               Lshapeless/Poly22;
  #41 = Utf8               <A:Ljava/lang/Object;B:Ljava/lang/Object;C:Ljava/lang/Object;D:Ljava/lang/Object;E:Ljava/lang/Object;F:Ljava/lang/Object;G:Ljava/lang/Object;H:Ljava/lang/Object;I:Ljava/lang/Object;J:Ljava/lang/Object;K:Ljava/lang/Object;L:Ljava/lang/Object;M:Ljava/lang/Object;N:Ljava/lang/Object;O:Ljava/lang/Object;P:Ljava/lang/Object;Q:Ljava/lang/Object;R:Ljava/lang/Object;S:Ljava/lang/Object;T:Ljava/lang/Object;U:Ljava/lang/Object;V:Ljava/lang/Object;>()Lshapeless/Poly22$CaseBuilder<TA;TB;TC;TD;TE;TF;TG;TH;TI;TJ;TK;TL;TM;TN;TO;TP;TQ;TR;TS;TT;TU;TV;>;
  #42 = Utf8               <init>
  #43 = Utf8               (Lshapeless/Poly22;)V
  #44 = NameAndType        #42:#43        // "<init>":(Lshapeless/Poly22;)V
  #45 = Methodref          #15.#44        // shapeless/Poly22$CaseBuilder."<init>":(Lshapeless/Poly22;)V
  #46 = Utf8               this
  #47 = Utf8               $init$
  #48 = Utf8               Code
  #49 = Utf8               LineNumberTable
  #50 = Utf8               LocalVariableTable
  #51 = Utf8               MethodParameters
  #52 = Utf8               Signature
  #53 = Utf8               InnerClasses
  #54 = Utf8               SourceFile
  #55 = Utf8               RuntimeVisibleAnnotations
  #56 = Utf8               ScalaInlineInfo
  #57 = Utf8               ScalaSig
{
  public static shapeless.HNil$ functions();
    descriptor: ()Lshapeless/HNil$;
    flags: (0x0009) ACC_PUBLIC, ACC_STATIC
    Code:
      stack=1, locals=0, args_size=0
         0: getstatic     #24                 // Field shapeless/Poly22$.MODULE$:Lshapeless/Poly22$;
         3: invokevirtual #26                 // Method shapeless/Poly22$.functions:()Lshapeless/HNil$;
         6: areturn

  public static shapeless.Poly22 build();
    descriptor: ()Lshapeless/Poly22;
    flags: (0x0009) ACC_PUBLIC, ACC_STATIC
    Code:
      stack=1, locals=0, args_size=0
         0: getstatic     #24                 // Field shapeless/Poly22$.MODULE$:Lshapeless/Poly22$;
         3: invokevirtual #30                 // Method shapeless/Poly22$.build:()Lshapeless/Poly22;
         6: areturn

  public abstract shapeless.Poly22$Case$ Case();
    descriptor: ()Lshapeless/Poly22$Case$;
    flags: (0x0401) ACC_PUBLIC, ACC_ABSTRACT

  public static shapeless.Poly22$CaseBuilder at$(shapeless.Poly22);
    descriptor: (Lshapeless/Poly22;)Lshapeless/Poly22$CaseBuilder;
    flags: (0x1009) ACC_PUBLIC, ACC_STATIC, ACC_SYNTHETIC
    Code:
      stack=1, locals=1, args_size=1
         0: aload_0
         1: invokespecial #39                 // InterfaceMethod at:()Lshapeless/Poly22$CaseBuilder;
         4: areturn
      LineNumberTable:
        line 586: 0
      LocalVariableTable:
        Start  Length  Slot  Name   Signature
            0       5     0 $this   Lshapeless/Poly22;
    MethodParameters:
      Name                           Flags
      $this                          final synthetic

  public default <A extends java.lang.Object, B extends java.lang.Object, C extends java.lang.Object, D extends java.lang.Object, E extends java.lang.Object, F extends java.lang.Object, G extends java.lang.Object, H extends java.lang.Object, I extends java.lang.Object, J extends java.lang.Object, K extends java.lang.Object, L extends java.lang.Object, M extends java.lang.Object, N extends java.lang.Object, O extends java.lang.Object, P extends java.lang.Object, Q extends java.lang.Object, R extends java.lang.Object, S extends java.lang.Object, T extends java.lang.Object, U extends java.lang.Object, V extends java.lang.Object> shapeless.Poly22$CaseBuilder<A, B, C, D, E, F, G, H, I, J, K, L, M, N, O, P, Q, R, S, T, U, V> at();
    descriptor: ()Lshapeless/Poly22$CaseBuilder;
    flags: (0x0001) ACC_PUBLIC
    Code:
      stack=3, locals=1, args_size=1
         0: new           #15                 // class shapeless/Poly22$CaseBuilder
         3: dup
         4: aload_0
         5: invokespecial #45                 // Method shapeless/Poly22$CaseBuilder."<init>":(Lshapeless/Poly22;)V
         8: areturn
      LineNumberTable:
        line 587: 0
      LocalVariableTable:
        Start  Length  Slot  Name   Signature
            0       9     0  this   Lshapeless/Poly22;
    Signature: #41                          // <A:Ljava/lang/Object;B:Ljava/lang/Object;C:Ljava/lang/Object;D:Ljava/lang/Object;E:Ljava/lang/Object;F:Ljava/lang/Object;G:Ljava/lang/Object;H:Ljava/lang/Object;I:Ljava/lang/Object;J:Ljava/lang/Object;K:Ljava/lang/Object;L:Ljava/lang/Object;M:Ljava/lang/Object;N:Ljava/lang/Object;O:Ljava/lang/Object;P:Ljava/lang/Object;Q:Ljava/lang/Object;R:Ljava/lang/Object;S:Ljava/lang/Object;T:Ljava/lang/Object;U:Ljava/lang/Object;V:Ljava/lang/Object;>()Lshapeless/Poly22$CaseBuilder<TA;TB;TC;TD;TE;TF;TG;TH;TI;TJ;TK;TL;TM;TN;TO;TP;TQ;TR;TS;TT;TU;TV;>;

  public static void $init$(shapeless.Poly22);
    descriptor: (Lshapeless/Poly22;)V
    flags: (0x0009) ACC_PUBLIC, ACC_STATIC
    Code:
      stack=0, locals=1, args_size=1
         0: return
      LineNumberTable:
        line 568: 0
      LocalVariableTable:
        Start  Length  Slot  Name   Signature
            0       1     0 $this   Lshapeless/Poly22;
    MethodParameters:
      Name                           Flags
      $this                          final synthetic
}
InnerClasses:
  public #13= #12 of #2;                  // Case$=class shapeless/Poly22$Case$ of class shapeless/Poly22
  public #16= #15 of #2;                  // CaseBuilder=class shapeless/Poly22$CaseBuilder of class shapeless/Poly22
SourceFile: "polyntraits.scala"
RuntimeVisibleAnnotations:
  0: #8(#9=s#10)
    scala.reflect.ScalaSignature(
      bytes="\u0006\u0005\t]haB\t\u0013!\u0003\r\t!\u0006\u0005\u0006A\u0001!\t!I\u0003\u0005K\u0001\u0001aeB\u0004\u00022\u0001A\t!a\r\u0007\r\u0015\u0002\u0001\u0012AA\u001b\u0011\u001d\t9\u0004\u0002C\u0001\u0003s)a!a\u000f\u0005\u0001\u0005ubABAk\u0001\u0001\t9\u000eC\u0004\u00028\u001d!\t!a7\t\u000f\t]r\u0001\"\u0001\u0003:!9!Q\u000b\u0001\u0005\u0002\t]sa\u0002B[%!\u0005!q\u0017\u0004\u0007#IA\tA!/\t\u000f\u0005]B\u0002\"\u0001\u0003Z\"I!1\u001c\u0007C\u0002\u0013\u0005!Q\u001c\u0005\t\u0005Kd\u0001\u0015!\u0003\u0003`\"I!q\u001d\u0007\u0002\u0002\u0013%!\u0011\u001e\u0002\u0007!>d\u0017P\r\u001a\u000b\u0003M\t\u0011b\u001d5ba\u0016dWm]:\u0004\u0001M\u0019\u0001A\u0006\u000f\u0011\u0005]QR\"\u0001\r\u000b\u0003e\tQa]2bY\u0006L!a\u0007\r\u0003\r\u0005s\u0017PU3g!\tib$D\u0001\u0013\u0013\ty\"C\u0001\u0003Q_2L\u0018A\u0002\u0013j]&$H\u0005F\u0001#!\t92%\u0003\u0002%1\t!QK\\5u\u0005\u0011\u0019\u0015m]3\u00169\u001dB4iR&P\'^[vlY4l_N<8p`A\u0004\u0003\u001f\t9\"a\b\u0002(A!\u0001f\f\u001a4\u001d\tICF\u0004\u0002\u001eU%\u00111FE\u0001\ba\u0006\u001c7.Y4f\u0013\tic&\u0001\u0003q_2L(BA\u0016\u0013\u0013\t)\u0003G\u0003\u00022%\u0005I\u0001k\u001c7z\t\u00164gn]\u0007\u0002\u0001A!Q\u0004\u000e\u001cB\u0013\t)$C\u0001\u0007%G>dwN\u001c\u0013d_2|g\u000e\u0005\u00028q1\u0001A!B\u001d\u0003\u0005\u0004Q$!A!\u0012\u0005mr\u0004CA\f=\u0013\ti\u0004DA\u0004O_RD\u0017N\\4\u0011\u0005]y\u0014B\u0001!\u0019\u0005\r\te.\u001f\t\u0005;Q\u0012U\t\u0005\u00028\u0007\u0012)AI\u0001b\u0001u\t\t!\t\u0005\u0003\u001ei\u0019K\u0005CA\u001cH\t\u0015A%A1\u0001;\u0005\u0005\u0019\u0005\u0003B\u000f5\u00156\u0003\"aN&\u0005\u000b1\u0013!\u0019\u0001\u001e\u0003\u0003\u0011\u0003B!\b\u001bO#B\u0011qg\u0014\u0003\u0006!\n\u0011\rA\u000f\u0002\u0002\u000bB!Q\u0004\u000e*V!\t94\u000bB\u0003U\u0005\t\u0007!HA\u0001G!\u0011iBGV-\u0011\u0005]:F!\u0002-\u0003\u0005\u0004Q$!A$\u0011\tu!$,\u0018\t\u0003om#Q\u0001\u0018\u0002C\u0002i\u0012\u0011\u0001\u0013\t\u0005;Qr\u0016\r\u0005\u00028?\u0012)\u0001M\u0001b\u0001u\t\t\u0011\n\u0005\u0003\u001ei\t,\u0007CA\u001cd\t\u0015!\'A1\u0001;\u0005\u0005Q\u0005\u0003B\u000f5M&\u0004\"aN4\u0005\u000b!\u0014!\u0019\u0001\u001e\u0003\u0003-\u0003B!\b\u001bk[B\u0011qg\u001b\u0003\u0006Y\n\u0011\rA\u000f\u0002\u0002\u0019B!Q\u0004\u000e8r!\t9t\u000eB\u0003q\u0005\t\u0007!HA\u0001N!\u0011iBG];\u0011\u0005]\u001aH!\u0002;\u0003\u0005\u0004Q$!\u0001(\u0011\tu!d/\u001f\t\u0003o]$Q\u0001\u001f\u0002C\u0002i\u0012\u0011a\u0014\t\u0005;QRX\u0010\u0005\u00028w\u0012)AP\u0001b\u0001u\t\t\u0001\u000bE\u0003\u001eiy\f\u0019\u0001\u0005\u00028\u007f\u00121\u0011\u0011\u0001\u0002C\u0002i\u0012\u0011!\u0015\t\u0007;Q\n)!a\u0003\u0011\u0007]\n9\u0001\u0002\u0004\u0002\n\t\u0011\rA\u000f\u0002\u0002%B1Q\u0004NA\u0007\u0003\'\u00012aNA\b\t\u0019\t\tB\u0001b\u0001u\t\t1\u000b\u0005\u0004\u001ei\u0005U\u00111\u0004\t\u0004o\u0005]AABA\r\u0005\t\u0007!HA\u0001U!\u0019iB\'!\b\u0002$A\u0019q\'a\b\u0005\r\u0005\u0005\"A1\u0001;\u0005\u0005)\u0006CB\u000f5\u0003K\tY\u0003E\u00028\u0003O!a!!\u000b\u0003\u0005\u0004Q$!\u0001,\u0011\u0007u\ti#C\u0002\u00020I\u0011A\u0001\u0013(jY\u0006!1)Y:f!\t\u0011Da\u0005\u0002\u0005-\u00051A(\u001b8jiz\"\"!a\r\u0003\u0007\u0005+\b0\u0006\u0019\u0002@\u0005-\u0013\u0011KA,\u0003;\n\u0019\'!\u001b\u0002p\u0005U\u00141PAA\u0003\u000f\u000bi)a%\u0002\u001a\u0006}\u0015QUAV\u0003c\u000b9,!0\u0002D\u0006%\u0017\u0011\u001b\n\u0005\u0003\u0003\n)E\u0002\u0004\u0002D\u0011\u0001\u0011q\b\u0002\ryI,g-\u001b8f[\u0016tGO\u0010\t\u0006Q=\u0012\u0014q\t\t\u0007;Q\nI%!\u0014\u0011\u0007]\nY\u0005B\u0003:\r\t\u0007!\b\u0005\u0004\u001ei\u0005=\u00131\u000b\t\u0004o\u0005EC!\u0002#\u0007\u0005\u0004Q\u0004CB\u000f5\u0003+\nI\u0006E\u00028\u0003/\"Q\u0001\u0013\u0004C\u0002i\u0002b!\b\u001b\u0002\\\u0005}\u0003cA\u001c\u0002^\u0011)AJ\u0002b\u0001uA1Q\u0004NA1\u0003K\u00022aNA2\t\u0015\u0001fA1\u0001;!\u0019iB\'a\u001a\u0002lA\u0019q\'!\u001b\u0005\u000bQ3!\u0019\u0001\u001e\u0011\ru!\u0014QNA9!\r9\u0014q\u000e\u0003\u00061\u001a\u0011\rA\u000f\t\u0007;Q\n\u0019(a\u001e\u0011\u0007]\n)\bB\u0003]\r\t\u0007!\b\u0005\u0004\u001ei\u0005e\u0014Q\u0010\t\u0004o\u0005mD!\u00021\u0007\u0005\u0004Q\u0004CB\u000f5\u0003\u007f\n\u0019\tE\u00028\u0003\u0003#Q\u0001\u001a\u0004C\u0002i\u0002b!\b\u001b\u0002\u0006\u0006%\u0005cA\u001c\u0002\b\u0012)\u0001N\u0002b\u0001uA1Q\u0004NAF\u0003\u001f\u00032aNAG\t\u0015agA1\u0001;!\u0019iB\'!%\u0002\u0016B\u0019q\'a%\u0005\u000bA4!\u0019\u0001\u001e\u0011\ru!\u0014qSAN!\r9\u0014\u0011\u0014\u0003\u0006i\u001a\u0011\rA\u000f\t\u0007;Q\ni*!)\u0011\u0007]\ny\nB\u0003y\r\t\u0007!\b\u0005\u0004\u001ei\u0005\r\u0016q\u0015\t\u0004o\u0005\u0015F!\u0002?\u0007\u0005\u0004Q\u0004CB\u000f5\u0003S\u000bi\u000bE\u00028\u0003W#a!!\u0001\u0007\u0005\u0004Q\u0004CB\u000f5\u0003_\u000b\u0019\fE\u00028\u0003c#a!!\u0003\u0007\u0005\u0004Q\u0004CB\u000f5\u0003k\u000bI\fE\u00028\u0003o#a!!\u0005\u0007\u0005\u0004Q\u0004CB\u000f5\u0003w\u000by\fE\u00028\u0003{#a!!\u0007\u0007\u0005\u0004Q\u0004CB\u000f5\u0003\u0003\f)\rE\u00028\u0003\u0007$a!!\t\u0007\u0005\u0004Q\u0004CB\u000f5\u0003\u000f\fY\u0003E\u00028\u0003\u0013$a!!\u000b\u0007\u0005\u0004QTaBAg\u0003\u0003\u0002\u0013q\u001a\u0002\u0007%\u0016\u001cX\u000f\u001c;\u0011\u0007]\n\t\u000e\u0002\u0004\u0002T\u001a\u0011\rA\u000f\u0002\b%\u0016\u001cX\u000f\u001c;1\u0005-\u0019\u0015m]3Ck&dG-\u001a:\u0016]\u0005e\u0017\u0011]As\u0003S\fi/!=\u0002v\u0006e\u0018Q B\u0001\u0005\u000b\u0011IA!\u0004\u0003\u0012\tU!\u0011\u0004B\u000f\u0005C\u0011)C!\u000b\u0003.\tE\"QG\n\u0003\u000fY!\"!!8\u0011]I:\u0011q\\Ar\u0003O\fY/a<\u0002t\u0006]\u00181`A\u0000\u0005\u0007\u00119Aa\u0003\u0003\u0010\tM!q\u0003B\u000e\u0005?\u0011\u0019Ca\n\u0003,\t=\"1\u0007\t\u0004o\u0005\u0005H!B\u001d\b\u0005\u0004Q\u0004cA\u001c\u0002f\u0012)Ai\u0002b\u0001uA\u0019q\'!;\u0005\u000b!;!\u0019\u0001\u001e\u0011\u0007]\ni\u000fB\u0003M\u000f\t\u0007!\bE\u00028\u0003c$Q\u0001U\u0004C\u0002i\u00022aNA{\t\u0015!vA1\u0001;!\r9\u0014\u0011 \u0003\u00061\u001e\u0011\rA\u000f\t\u0004o\u0005uH!\u0002/\b\u0005\u0004Q\u0004cA\u001c\u0003\u0002\u0011)\u0001m\u0002b\u0001uA\u0019qG!\u0002\u0005\u000b\u0011<!\u0019\u0001\u001e\u0011\u0007]\u0012I\u0001B\u0003i\u000f\t\u0007!\bE\u00028\u0005\u001b!Q\u0001\\\u0004C\u0002i\u00022a\u000eB\t\t\u0015\u0001xA1\u0001;!\r9$Q\u0003\u0003\u0006i\u001e\u0011\rA\u000f\t\u0004o\teA!\u0002=\b\u0005\u0004Q\u0004cA\u001c\u0003\u001e\u0011)Ap\u0002b\u0001uA\u0019qG!\t\u0005\r\u0005\u0005qA1\u0001;!\r9$Q\u0005\u0003\u0007\u0003\u00139!\u0019\u0001\u001e\u0011\u0007]\u0012I\u0003\u0002\u0004\u0002\u0012\u001d\u0011\rA\u000f\t\u0004o\t5BABA\r\u000f\t\u0007!\bE\u00028\u0005c!a!!\t\b\u0005\u0004Q\u0004cA\u001c\u00036\u00111\u0011\u0011F\u0004C\u0002i\nQ!\u00199qYf,BAa\u000f\u0003HQ!!Q\bB&%\u0011\u0011yD!\u0011\u0007\r\u0005\r\u0013\u0002\u0001B\u001f!9\u0012$!a8\u0002d\u0006\u001d\u00181^Ax\u0003g\f90a?\u0002\u0000\n\r!q\u0001B\u0006\u0005\u001f\u0011\u0019Ba\u0006\u0003\u001c\t}!1\u0005B\u0014\u0005W\u0011yCa\r\u0006\u000f\u00055\'q\b\u0001\u0003FA\u0019qGa\u0012\u0005\r\t%\u0013B1\u0001;\u0005\r\u0011Vm\u001d\u0005\b\u0005\u001bJ\u0001\u0019\u0001B(\u0003\t1g\u000eE\u0019\u0018\u0005#\ny.a9\u0002h\u0006-\u0018q^Az\u0003o\fY0a@\u0003\u0004\t\u001d!1\u0002B\b\u0005\'\u00119Ba\u0007\u0003 \t\r\"q\u0005B\u0016\u0005_\u0011\u0019D!\u0012\n\u0007\tM\u0003D\u0001\u0006Gk:\u001cG/[8oeI\n!!\u0019;\u0016]\te#q\fB2\u0005O\u0012YGa\u001c\u0003t\t]$1\u0010B@\u0005\u0007\u00139Ia#\u0003\u0010\nM%q\u0013BN\u0005?\u0013\u0019Ka*\u0003,\n=&1W\u000b\u0003\u00057\u0002bFM\u0004\u0003^\t\u0005$Q\rB5\u0005[\u0012\tH!\u001e\u0003z\tu$\u0011\u0011BC\u0005\u0013\u0013iI!%\u0003\u0016\ne%Q\u0014BQ\u0005K\u0013IK!,\u00032B\u0019qGa\u0018\u0005\u000beR!\u0019\u0001\u001e\u0011\u0007]\u0012\u0019\u0007B\u0003E\u0015\t\u0007!\bE\u00028\u0005O\"Q\u0001\u0013\u0006C\u0002i\u00022a\u000eB6\t\u0015a%B1\u0001;!\r9$q\u000e\u0003\u0006!*\u0011\rA\u000f\t\u0004o\tMD!\u0002+\u000b\u0005\u0004Q\u0004cA\u001c\u0003x\u0011)\u0001L\u0003b\u0001uA\u0019qGa\u001f\u0005\u000bqS!\u0019\u0001\u001e\u0011\u0007]\u0012y\bB\u0003a\u0015\t\u0007!\bE\u00028\u0005\u0007#Q\u0001\u001a\u0006C\u0002i\u00022a\u000eBD\t\u0015A\'B1\u0001;!\r9$1\u0012\u0003\u0006Y*\u0011\rA\u000f\t\u0004o\t=E!\u00029\u000b\u0005\u0004Q\u0004cA\u001c\u0003\u0014\u0012)AO\u0003b\u0001uA\u0019qGa&\u0005\u000baT!\u0019\u0001\u001e\u0011\u0007]\u0012Y\nB\u0003}\u0015\t\u0007!\bE\u00028\u0005?#a!!\u0001\u000b\u0005\u0004Q\u0004cA\u001c\u0003$\u00121\u0011\u0011\u0002\u0006C\u0002i\u00022a\u000eBT\t\u0019\t\tB\u0003b\u0001uA\u0019qGa+\u0005\r\u0005e!B1\u0001;!\r9$q\u0016\u0003\u0007\u0003CQ!\u0019\u0001\u001e\u0011\u0007]\u0012\u0019\f\u0002\u0004\u0002*)\u0011\rAO\u0001\u0007!>d\u0017P\r\u001a\u0011\u0005ua1C\u0002\u0007\u0017\u0005w\u0013I\r\u0005\u0004\u0003>\n\r\u00171\u0006\b\u0004;\t}\u0016b\u0001Ba%\u0005i\u0001k\u001c7z\u001d\n+\u0018\u000e\u001c3feNLAA!2\u0003H\ni\u0001k\u001c7zeI\u0012U/\u001b7eKJT1A!1\u0013!\u0011\u0011YM!6\u000e\u0005\t5\'\u0002\u0002Bh\u0005#\f!![8\u000b\u0005\tM\u0017\u0001\u00026bm\u0006LAAa6\u0003N\na1+\u001a:jC2L\'0\u00192mKR\u0011!qW\u0001\nMVt7\r^5p]N,\"Aa8\u000f\u0007u\u0011\t/C\u0002\u0003dJ\tA\u0001\u0013(jY\u0006Qa-\u001e8di&|gn\u001d\u0011\u0002\u0019]\u0014\u0018\u000e^3SKBd\u0017mY3\u0015\u0005\t-\b\u0003\u0002Bw\u0005gl!Aa<\u000b\t\tE(\u0011[\u0001\u0005Y\u0006tw-\u0003\u0003\u0003v\n=(AB(cU\u0016\u001cG\u000f"
    )
  ScalaInlineInfo: length = 0x18 (unknown attribute)
   01 00 00 04 00 2F 00 2B 01 00 1F 00 20 00 00 21
   00 22 01 00 24 00 25 00
  ScalaSig: length = 0x3 (unknown attribute)
   05 02 00
