Classfile /Users/mw/Projects/slang-braindump/.jar/jar11/assemble/slang-braindump/assemble/content/shapeless/PolyDefns$Compose$.class
  Last modified May 29, 2022; size 1681 bytes
  SHA-256 checksum 38faaf507037e61edfa01203871d4351f3f71640871c6d41d7249aa3b979de76
  Compiled from "poly.scala"
public class shapeless.PolyDefns$Compose$ implements java.io.Serializable
  minor version: 0
  major version: 52
  flags: (0x0021) ACC_PUBLIC, ACC_SUPER
  this_class: #2                          // shapeless/PolyDefns$Compose$
  super_class: #4                         // java/lang/Object
  interfaces: 1, fields: 1, methods: 4, attributes: 4
Constant pool:
   #1 = Utf8               shapeless/PolyDefns$Compose$
   #2 = Class              #1             // shapeless/PolyDefns$Compose$
   #3 = Utf8               java/lang/Object
   #4 = Class              #3             // java/lang/Object
   #5 = Utf8               java/io/Serializable
   #6 = Class              #5             // java/io/Serializable
   #7 = Utf8               poly.scala
   #8 = Utf8               shapeless/PolyDefns$Case
   #9 = Class              #8             // shapeless/PolyDefns$Case
  #10 = Utf8               shapeless/PolyDefns
  #11 = Class              #10            // shapeless/PolyDefns
  #12 = Utf8               Case
  #13 = Utf8               shapeless/PolyDefns$Compose
  #14 = Class              #13            // shapeless/PolyDefns$Compose
  #15 = Utf8               Compose
  #16 = Utf8               Compose$
  #17 = Utf8               shapeless/PolyDefns$Compose$$anon$3
  #18 = Class              #17            // shapeless/PolyDefns$Compose$$anon$3
  #19 = Utf8               MODULE$
  #20 = Utf8               Lshapeless/PolyDefns$Compose$;
  #21 = Utf8               <clinit>
  #22 = Utf8               ()V
  #23 = Utf8               <init>
  #24 = NameAndType        #23:#22        // "<init>":()V
  #25 = Methodref          #2.#24         // shapeless/PolyDefns$Compose$."<init>":()V
  #26 = NameAndType        #19:#20        // MODULE$:Lshapeless/PolyDefns$Compose$;
  #27 = Fieldref           #2.#26         // shapeless/PolyDefns$Compose$.MODULE$:Lshapeless/PolyDefns$Compose$;
  #28 = Utf8               composeCase
  #29 = Utf8               (Lshapeless/Unpack2;Lshapeless/PolyDefns$Case;Lshapeless/PolyDefns$Case;)Lshapeless/PolyDefns$Case;
  #30 = Utf8               <C:Ljava/lang/Object;F::Lshapeless/Poly;G::Lshapeless/Poly;T:Ljava/lang/Object;U:Ljava/lang/Object;V:Ljava/lang/Object;>(Lshapeless/Unpack2<TC;Lshapeless/PolyDefns$Compose;TF;TG;>;Lshapeless/PolyDefns$Case<TG;Lshapeless/$colon$colon<TT;Lshapeless/HNil;>;>;Lshapeless/PolyDefns$Case<TF;Lshapeless/$colon$colon<TU;Lshapeless/HNil;>;>;)Lshapeless/PolyDefns$Case<TC;Lshapeless/$colon$colon<TT;Lshapeless/HNil;>;>;
  #31 = Utf8               unpack
  #32 = Utf8               cG
  #33 = Utf8               cF
  #34 = Utf8               (Lshapeless/PolyDefns$Case;Lshapeless/PolyDefns$Case;)V
  #35 = NameAndType        #23:#34        // "<init>":(Lshapeless/PolyDefns$Case;Lshapeless/PolyDefns$Case;)V
  #36 = Methodref          #18.#35        // shapeless/PolyDefns$Compose$$anon$3."<init>":(Lshapeless/PolyDefns$Case;Lshapeless/PolyDefns$Case;)V
  #37 = Utf8               this
  #38 = Utf8               Lshapeless/Unpack2;
  #39 = Utf8               Lshapeless/PolyDefns$Case;
  #40 = Utf8               writeReplace
  #41 = Utf8               ()Ljava/lang/Object;
  #42 = Utf8               scala/runtime/ModuleSerializationProxy
  #43 = Class              #42            // scala/runtime/ModuleSerializationProxy
  #44 = Utf8               (Ljava/lang/Class;)V
  #45 = NameAndType        #23:#44        // "<init>":(Ljava/lang/Class;)V
  #46 = Methodref          #43.#45        // scala/runtime/ModuleSerializationProxy."<init>":(Ljava/lang/Class;)V
  #47 = Methodref          #4.#24         // java/lang/Object."<init>":()V
  #48 = Utf8               Code
  #49 = Utf8               LineNumberTable
  #50 = Utf8               LocalVariableTable
  #51 = Utf8               Signature
  #52 = Utf8               MethodParameters
  #53 = Utf8               InnerClasses
  #54 = Utf8               SourceFile
  #55 = Utf8               ScalaInlineInfo
  #56 = Utf8               Scala
{
  public static final shapeless.PolyDefns$Compose$ MODULE$;
    descriptor: Lshapeless/PolyDefns$Compose$;
    flags: (0x0019) ACC_PUBLIC, ACC_STATIC, ACC_FINAL

  public static {};
    descriptor: ()V
    flags: (0x0009) ACC_PUBLIC, ACC_STATIC
    Code:
      stack=2, locals=0, args_size=0
         0: new           #2                  // class shapeless/PolyDefns$Compose$
         3: dup
         4: invokespecial #25                 // Method "<init>":()V
         7: putstatic     #27                 // Field MODULE$:Lshapeless/PolyDefns$Compose$;
        10: return
      LineNumberTable:
        line 74: 0

  public <C extends java.lang.Object, F extends shapeless.Poly, G extends shapeless.Poly, T extends java.lang.Object, U extends java.lang.Object, V extends java.lang.Object> shapeless.PolyDefns$Case<C, shapeless.$colon$colon<T, shapeless.HNil>> composeCase(shapeless.Unpack2<C, shapeless.PolyDefns$Compose, F, G>, shapeless.PolyDefns$Case<G, shapeless.$colon$colon<T, shapeless.HNil>>, shapeless.PolyDefns$Case<F, shapeless.$colon$colon<U, shapeless.HNil>>);
    descriptor: (Lshapeless/Unpack2;Lshapeless/PolyDefns$Case;Lshapeless/PolyDefns$Case;)Lshapeless/PolyDefns$Case;
    flags: (0x0001) ACC_PUBLIC
    Code:
      stack=4, locals=4, args_size=4
         0: new           #18                 // class shapeless/PolyDefns$Compose$$anon$3
         3: dup
         4: aload_3
         5: aload_2
         6: invokespecial #36                 // Method shapeless/PolyDefns$Compose$$anon$3."<init>":(Lshapeless/PolyDefns$Case;Lshapeless/PolyDefns$Case;)V
         9: areturn
      LineNumberTable:
        line 76: 0
      LocalVariableTable:
        Start  Length  Slot  Name   Signature
            0      10     0  this   Lshapeless/PolyDefns$Compose$;
            0      10     1 unpack   Lshapeless/Unpack2;
            0      10     2    cG   Lshapeless/PolyDefns$Case;
            0      10     3    cF   Lshapeless/PolyDefns$Case;
    Signature: #30                          // <C:Ljava/lang/Object;F::Lshapeless/Poly;G::Lshapeless/Poly;T:Ljava/lang/Object;U:Ljava/lang/Object;V:Ljava/lang/Object;>(Lshapeless/Unpack2<TC;Lshapeless/PolyDefns$Compose;TF;TG;>;Lshapeless/PolyDefns$Case<TG;Lshapeless/$colon$colon<TT;Lshapeless/HNil;>;>;Lshapeless/PolyDefns$Case<TF;Lshapeless/$colon$colon<TU;Lshapeless/HNil;>;>;)Lshapeless/PolyDefns$Case<TC;Lshapeless/$colon$colon<TT;Lshapeless/HNil;>;>;
    MethodParameters:
      Name                           Flags
      unpack                         final
      cG                             final
      cF                             final

  private java.lang.Object writeReplace();
    descriptor: ()Ljava/lang/Object;
    flags: (0x0002) ACC_PRIVATE
    Code:
      stack=3, locals=1, args_size=1
         0: new           #43                 // class scala/runtime/ModuleSerializationProxy
         3: dup
         4: ldc           #2                  // class shapeless/PolyDefns$Compose$
         6: invokespecial #46                 // Method scala/runtime/ModuleSerializationProxy."<init>":(Ljava/lang/Class;)V
         9: areturn
      LineNumberTable:
        line 74: 0
      LocalVariableTable:
        Start  Length  Slot  Name   Signature
            0      10     0  this   Lshapeless/PolyDefns$Compose$;

  public shapeless.PolyDefns$Compose$();
    descriptor: ()V
    flags: (0x0001) ACC_PUBLIC
    Code:
      stack=1, locals=1, args_size=1
         0: aload_0
         1: invokespecial #47                 // Method java/lang/Object."<init>":()V
         4: return
      LineNumberTable:
        line 87: 0
        line 74: 4
      LocalVariableTable:
        Start  Length  Slot  Name   Signature
            0       5     0  this   Lshapeless/PolyDefns$Compose$;
}
InnerClasses:
  public static abstract #12= #9 of #11;  // Case=class shapeless/PolyDefns$Case of class shapeless/PolyDefns
  public static #15= #14 of #11;          // Compose=class shapeless/PolyDefns$Compose of class shapeless/PolyDefns
  public static #16= #2 of #11;           // Compose$=class shapeless/PolyDefns$Compose$ of class shapeless/PolyDefns
  public final #18;                       // class shapeless/PolyDefns$Compose$$anon$3
SourceFile: "poly.scala"
  ScalaInlineInfo: length = 0x13 (unknown attribute)
   01 01 00 03 00 17 00 16 01 00 1C 00 1D 01 00 28
   00 29 01
  Scala: length = 0x0 (unknown attribute)

