Classfile /Users/mw/Projects/slang-braindump/.jar/jar11/assemble/slang-braindump/assemble/content/shapeless/PolyMacros.class
  Last modified May 29, 2022; size 9173 bytes
  SHA-256 checksum 4918fc0bafabb95982e61a954d88ff0cbab4fd029329246f02f98c85880c3484
  Compiled from "poly.scala"
public class shapeless.PolyMacros
  minor version: 0
  major version: 52
  flags: (0x0021) ACC_PUBLIC, ACC_SUPER
  this_class: #2                          // shapeless/PolyMacros
  super_class: #4                         // java/lang/Object
  interfaces: 0, fields: 1, methods: 6, attributes: 6
Constant pool:
    #1 = Utf8               shapeless/PolyMacros
    #2 = Class              #1            // shapeless/PolyMacros
    #3 = Utf8               java/lang/Object
    #4 = Class              #3            // java/lang/Object
    #5 = Utf8               poly.scala
    #6 = Utf8               Lscala/reflect/ScalaSignature;
    #7 = Utf8               bytes
    #8 = Utf8               \u0006\u0005I3A!\u0002\u0004\u0001\u0013!A\u0001\u0003\u0001BC\u0002\u0013\u0005\u0011\u0003\u0003\u0005\u001d\u0001\t\u0005\t\u0015!\u0003\u0013\u0011\u0015i\u0002\u0001\"\u0001\u001f\u0011\u0015\u0011\u0003\u0001\"\u0001$\u0005)\u0001v\u000e\\=NC\u000e\u0014xn\u001d\u0006\u0002\u000f\u0005I1\u000f[1qK2,7o]\u0002\u0001\'\t\u0001!\u0002\u0005\u0002\f\u001d5\tABC\u0001\u000e\u0003\u0015\u00198-\u00197b\u0013\tyAB\u0001\u0004B]f\u0014VMZ\u0001\u0002GV\t!\u0003\u0005\u0002\u001455\tAC\u0003\u0002\u0016-\u0005Aq\u000f[5uK\n|\u0007P\u0003\u0002\u00181\u00051Q.Y2s_NT!!\u0007\u0007\u0002\u000fI,g\r\\3di&\u00111\u0004\u0006\u0002\b\u0007>tG/\u001a=u\u0003\t\u0019\u0007%\u0001\u0004=S:LGO\u0010\u000b\u0003?\u0005\u0002\"\u0001\t\u0001\u000e\u0003\u0019AQ\u0001E\u0002A\u0002I\t\u0001$\\1uKJL\u0017\r\\5{K\u001a\u0013x.\u001c,bYV,\u0017*\u001c9m+\u0011!SH\u0013)\u0015\t\u0015\"d\t\u0014\t\u0003M9r!aJ\u0015\u000f\u0005!\nQ\"\u0001\u0001\n\u0005)Z\u0013\u0001C;oSZ,\'o]3\n\u0005ma#BA\u0017\u0017\u0003!\u0011G.Y2lE>D\u0018BA\u00181\u0005\u0011!&/Z3\n\u0005E\u0012$!\u0002+sK\u0016\u001c(BA\u001a\u0019\u0003\r\t\u0007/\u001b\u0005\bk\u0011\t\t\u0011q\u00017\u0003))g/\u001b3f]\u000e,G%\r\t\u0004M]Z\u0014B\u0001\u001d:\u0005-9V-Y6UsB,G+Y4\n\u0005i\u0012$\u0001\u0003+za\u0016$\u0016mZ:\u0011\u0005qjD\u0002\u0001\u0003\u0006}\u0011\u0011\ra\u0010\u0002\u0002!F\u0011\u0001i\u0011\t\u0003\u0017\u0005K!A\u0011\u0007\u0003\u000f9{G\u000f[5oOB\u00111\u0002R\u0005\u0003\u000b2\u00111!\u00118z\u0011\u001d9E!!AA\u0004!\u000b!\"\u001a<jI\u0016t7-\u001a\u00133!\r1s\'\u0013\t\u0003y)#Qa\u0013\u0003C\u0002}\u0012!A\u0012+\t\u000f5#\u0011\u0011!a\u0002\u001d\u0006QQM^5eK:\u001cW\rJ\u001a\u0011\u0007\u0019:t\n\u0005\u0002=!\u0012)\u0011\u000b\u0002b\u0001\u007f\t\tA\u000b
    #9 = Utf8               java/lang/invoke/MethodHandles$Lookup
   #10 = Class              #9            // java/lang/invoke/MethodHandles$Lookup
   #11 = Utf8               java/lang/invoke/MethodHandles
   #12 = Class              #11           // java/lang/invoke/MethodHandles
   #13 = Utf8               Lookup
   #14 = Utf8               scala/reflect/api/Internals$InternalApi
   #15 = Class              #14           // scala/reflect/api/Internals$InternalApi
   #16 = Utf8               scala/reflect/api/Internals
   #17 = Class              #16           // scala/reflect/api/Internals
   #18 = Utf8               InternalApi
   #19 = Utf8               scala/reflect/api/Internals$ReificationSupportApi
   #20 = Class              #19           // scala/reflect/api/Internals$ReificationSupportApi
   #21 = Utf8               ReificationSupportApi
   #22 = Utf8               scala/reflect/api/Internals$ReificationSupportApi$SyntacticSelectTermExtractor
   #23 = Class              #22           // scala/reflect/api/Internals$ReificationSupportApi$SyntacticSelectTermExtractor
   #24 = Utf8               SyntacticSelectTermExtractor
   #25 = Utf8               scala/reflect/api/Internals$ReificationSupportApi$SyntacticTypeAppliedExtractor
   #26 = Class              #25           // scala/reflect/api/Internals$ReificationSupportApi$SyntacticTypeAppliedExtractor
   #27 = Utf8               SyntacticTypeAppliedExtractor
   #28 = Utf8               scala/reflect/api/Liftables$Liftable
   #29 = Class              #28           // scala/reflect/api/Liftables$Liftable
   #30 = Utf8               scala/reflect/api/Liftables
   #31 = Class              #30           // scala/reflect/api/Liftables
   #32 = Utf8               Liftable
   #33 = Utf8               scala/reflect/api/Liftables$Liftable$
   #34 = Class              #33           // scala/reflect/api/Liftables$Liftable$
   #35 = Utf8               Liftable$
   #36 = Utf8               scala/reflect/api/Names$TermNameApi
   #37 = Class              #36           // scala/reflect/api/Names$TermNameApi
   #38 = Utf8               scala/reflect/api/Names
   #39 = Class              #38           // scala/reflect/api/Names
   #40 = Utf8               TermNameApi
   #41 = Utf8               scala/reflect/api/Names$TermNameExtractor
   #42 = Class              #41           // scala/reflect/api/Names$TermNameExtractor
   #43 = Utf8               TermNameExtractor
   #44 = Utf8               scala/reflect/api/Symbols$SymbolApi
   #45 = Class              #44           // scala/reflect/api/Symbols$SymbolApi
   #46 = Utf8               scala/reflect/api/Symbols
   #47 = Class              #46           // scala/reflect/api/Symbols
   #48 = Utf8               SymbolApi
   #49 = Utf8               scala/reflect/api/Trees$SelectApi
   #50 = Class              #49           // scala/reflect/api/Trees$SelectApi
   #51 = Utf8               scala/reflect/api/Trees
   #52 = Class              #51           // scala/reflect/api/Trees
   #53 = Utf8               SelectApi
   #54 = Utf8               scala/reflect/api/Trees$TreeApi
   #55 = Class              #54           // scala/reflect/api/Trees$TreeApi
   #56 = Utf8               TreeApi
   #57 = Utf8               scala/reflect/api/TypeTags$WeakTypeTag
   #58 = Class              #57           // scala/reflect/api/TypeTags$WeakTypeTag
   #59 = Utf8               scala/reflect/api/TypeTags
   #60 = Class              #59           // scala/reflect/api/TypeTags
   #61 = Utf8               WeakTypeTag
   #62 = Utf8               scala/reflect/api/TypeTags$WeakTypeTag$
   #63 = Class              #62           // scala/reflect/api/TypeTags$WeakTypeTag$
   #64 = Utf8               WeakTypeTag$
   #65 = Utf8               scala/reflect/api/Types$SingleTypeApi
   #66 = Class              #65           // scala/reflect/api/Types$SingleTypeApi
   #67 = Utf8               scala/reflect/api/Types
   #68 = Class              #67           // scala/reflect/api/Types
   #69 = Utf8               SingleTypeApi
   #70 = Utf8               scala/reflect/api/Types$SingleTypeExtractor
   #71 = Class              #70           // scala/reflect/api/Types$SingleTypeExtractor
   #72 = Utf8               SingleTypeExtractor
   #73 = Utf8               scala/reflect/api/Types$TypeApi
   #74 = Class              #73           // scala/reflect/api/Types$TypeApi
   #75 = Utf8               TypeApi
   #76 = Utf8               scala/reflect/macros/whitebox/Context$ImplicitCandidate
   #77 = Class              #76           // scala/reflect/macros/whitebox/Context$ImplicitCandidate
   #78 = Utf8               scala/reflect/macros/whitebox/Context
   #79 = Class              #78           // scala/reflect/macros/whitebox/Context
   #80 = Utf8               ImplicitCandidate
   #81 = Utf8               shapeless/PolyMacros$$typecreator1$1
   #82 = Class              #81           // shapeless/PolyMacros$$typecreator1$1
   #83 = Utf8               $typecreator1$1
   #84 = Utf8               c
   #85 = Utf8               Lscala/reflect/macros/whitebox/Context;
   #86 = Utf8               ()Lscala/reflect/macros/whitebox/Context;
   #87 = NameAndType        #84:#85       // c:Lscala/reflect/macros/whitebox/Context;
   #88 = Fieldref           #2.#87        // shapeless/PolyMacros.c:Lscala/reflect/macros/whitebox/Context;
   #89 = Utf8               this
   #90 = Utf8               Lshapeless/PolyMacros;
   #91 = Utf8               materializeFromValueImpl
   #92 = Utf8               (Lscala/reflect/api/TypeTags$WeakTypeTag;Lscala/reflect/api/TypeTags$WeakTypeTag;Lscala/reflect/api/TypeTags$WeakTypeTag;)Lscala/reflect/api/Trees$TreeApi;
   #93 = Utf8               <P:Ljava/lang/Object;FT:Ljava/lang/Object;T:Ljava/lang/Object;>(Lscala/reflect/api/TypeTags$WeakTypeTag<TP;>;Lscala/reflect/api/TypeTags$WeakTypeTag<TFT;>;Lscala/reflect/api/TypeTags$WeakTypeTag<TT;>;)Lscala/reflect/api/Trees$TreeApi;
   #94 = Utf8               evidence$1
   #95 = Utf8               evidence$2
   #96 = Utf8               evidence$3
   #97 = NameAndType        #84:#86       // c:()Lscala/reflect/macros/whitebox/Context;
   #98 = Methodref          #2.#97        // shapeless/PolyMacros.c:()Lscala/reflect/macros/whitebox/Context;
   #99 = Utf8               universe
  #100 = Utf8               ()Lscala/reflect/macros/Universe;
  #101 = NameAndType        #99:#100      // universe:()Lscala/reflect/macros/Universe;
  #102 = InterfaceMethodref #79.#101      // scala/reflect/macros/whitebox/Context.universe:()Lscala/reflect/macros/Universe;
  #103 = Utf8               scala/reflect/macros/Universe
  #104 = Class              #103          // scala/reflect/macros/Universe
  #105 = Utf8               weakTypeOf
  #106 = Utf8               (Lscala/reflect/api/TypeTags$WeakTypeTag;)Lscala/reflect/api/Types$TypeApi;
  #107 = NameAndType        #105:#106     // weakTypeOf:(Lscala/reflect/api/TypeTags$WeakTypeTag;)Lscala/reflect/api/Types$TypeApi;
  #108 = Methodref          #104.#107     // scala/reflect/macros/Universe.weakTypeOf:(Lscala/reflect/api/TypeTags$WeakTypeTag;)Lscala/reflect/api/Types$TypeApi;
  #109 = Utf8               rootMirror
  #110 = Utf8               ()Lscala/reflect/api/Mirror;
  #111 = NameAndType        #109:#110     // rootMirror:()Lscala/reflect/api/Mirror;
  #112 = Methodref          #104.#111     // scala/reflect/macros/Universe.rootMirror:()Lscala/reflect/api/Mirror;
  #113 = Utf8               ()Lscala/reflect/api/TypeTags$WeakTypeTag$;
  #114 = NameAndType        #61:#113      // WeakTypeTag:()Lscala/reflect/api/TypeTags$WeakTypeTag$;
  #115 = Methodref          #104.#114     // scala/reflect/macros/Universe.WeakTypeTag:()Lscala/reflect/api/TypeTags$WeakTypeTag$;
  #116 = Utf8               <init>
  #117 = Utf8               (Lshapeless/PolyMacros;Lscala/reflect/api/TypeTags$WeakTypeTag;Lscala/reflect/api/TypeTags$WeakTypeTag;)V
  #118 = NameAndType        #116:#117     // "<init>":(Lshapeless/PolyMacros;Lscala/reflect/api/TypeTags$WeakTypeTag;Lscala/reflect/api/TypeTags$WeakTypeTag;)V
  #119 = Methodref          #82.#118      // shapeless/PolyMacros$$typecreator1$1."<init>":(Lshapeless/PolyMacros;Lscala/reflect/api/TypeTags$WeakTypeTag;Lscala/reflect/api/TypeTags$WeakTypeTag;)V
  #120 = Utf8               apply
  #121 = Utf8               (Lscala/reflect/api/Mirror;Lscala/reflect/api/TypeCreator;)Lscala/reflect/api/TypeTags$WeakTypeTag;
  #122 = NameAndType        #120:#121     // apply:(Lscala/reflect/api/Mirror;Lscala/reflect/api/TypeCreator;)Lscala/reflect/api/TypeTags$WeakTypeTag;
  #123 = Methodref          #63.#122      // scala/reflect/api/TypeTags$WeakTypeTag$.apply:(Lscala/reflect/api/Mirror;Lscala/reflect/api/TypeCreator;)Lscala/reflect/api/TypeTags$WeakTypeTag;
  #124 = Utf8               openImplicits
  #125 = Utf8               ()Lscala/collection/immutable/List;
  #126 = NameAndType        #124:#125     // openImplicits:()Lscala/collection/immutable/List;
  #127 = InterfaceMethodref #79.#126      // scala/reflect/macros/whitebox/Context.openImplicits:()Lscala/collection/immutable/List;
  #128 = Utf8               scala/collection/immutable/List
  #129 = Class              #128          // scala/collection/immutable/List
  #130 = Utf8               tail
  #131 = Utf8               ()Ljava/lang/Object;
  #132 = NameAndType        #130:#131     // tail:()Ljava/lang/Object;
  #133 = Methodref          #129.#132     // scala/collection/immutable/List.tail:()Ljava/lang/Object;
  #134 = Utf8               (Ljava/lang/Object;)Ljava/lang/Object;
  #135 = MethodType         #134          //  (Ljava/lang/Object;)Ljava/lang/Object;
  #136 = Utf8               $anonfun$materializeFromValueImpl$1$adapted
  #137 = Utf8               (Lscala/reflect/api/Types$TypeApi;Lscala/reflect/macros/whitebox/Context$ImplicitCandidate;)Ljava/lang/Object;
  #138 = NameAndType        #136:#137     // $anonfun$materializeFromValueImpl$1$adapted:(Lscala/reflect/api/Types$TypeApi;Lscala/reflect/macros/whitebox/Context$ImplicitCandidate;)Ljava/lang/Object;
  #139 = Methodref          #2.#138       // shapeless/PolyMacros.$anonfun$materializeFromValueImpl$1$adapted:(Lscala/reflect/api/Types$TypeApi;Lscala/reflect/macros/whitebox/Context$ImplicitCandidate;)Ljava/lang/Object;
  #140 = MethodHandle       6:#139        // REF_invokeStatic shapeless/PolyMacros.$anonfun$materializeFromValueImpl$1$adapted:(Lscala/reflect/api/Types$TypeApi;Lscala/reflect/macros/whitebox/Context$ImplicitCandidate;)Ljava/lang/Object;
  #141 = Utf8               (Lscala/reflect/macros/whitebox/Context$ImplicitCandidate;)Ljava/lang/Object;
  #142 = MethodType         #141          //  (Lscala/reflect/macros/whitebox/Context$ImplicitCandidate;)Ljava/lang/Object;
  #143 = Integer            5
  #144 = Integer            1
  #145 = Utf8               java/lang/invoke/LambdaMetafactory
  #146 = Class              #145          // java/lang/invoke/LambdaMetafactory
  #147 = Utf8               altMetafactory
  #148 = Utf8               (Ljava/lang/invoke/MethodHandles$Lookup;Ljava/lang/String;Ljava/lang/invoke/MethodType;[Ljava/lang/Object;)Ljava/lang/invoke/CallSite;
  #149 = NameAndType        #147:#148     // altMetafactory:(Ljava/lang/invoke/MethodHandles$Lookup;Ljava/lang/String;Ljava/lang/invoke/MethodType;[Ljava/lang/Object;)Ljava/lang/invoke/CallSite;
  #150 = Methodref          #146.#149     // java/lang/invoke/LambdaMetafactory.altMetafactory:(Ljava/lang/invoke/MethodHandles$Lookup;Ljava/lang/String;Ljava/lang/invoke/MethodType;[Ljava/lang/Object;)Ljava/lang/invoke/CallSite;
  #151 = MethodHandle       6:#150        // REF_invokeStatic java/lang/invoke/LambdaMetafactory.altMetafactory:(Ljava/lang/invoke/MethodHandles$Lookup;Ljava/lang/String;Ljava/lang/invoke/MethodType;[Ljava/lang/Object;)Ljava/lang/invoke/CallSite;
  #152 = Utf8               (Lscala/reflect/api/Types$TypeApi;)Lscala/Function1;
  #153 = NameAndType        #120:#152     // apply:(Lscala/reflect/api/Types$TypeApi;)Lscala/Function1;
  #154 = InvokeDynamic      #0:#153       // #0:apply:(Lscala/reflect/api/Types$TypeApi;)Lscala/Function1;
  #155 = Utf8               exists
  #156 = Utf8               (Lscala/Function1;)Z
  #157 = NameAndType        #155:#156     // exists:(Lscala/Function1;)Z
  #158 = Methodref          #129.#157     // scala/collection/immutable/List.exists:(Lscala/Function1;)Z
  #159 = Utf8               enclosingPosition
  #160 = Utf8               ()Lscala/reflect/api/Position;
  #161 = NameAndType        #159:#160     // enclosingPosition:()Lscala/reflect/api/Position;
  #162 = InterfaceMethodref #79.#161      // scala/reflect/macros/whitebox/Context.enclosingPosition:()Lscala/reflect/api/Position;
  #163 = Utf8               java/lang/StringBuilder
  #164 = Class              #163          // java/lang/StringBuilder
  #165 = Integer            53
  #166 = Utf8               (I)V
  #167 = NameAndType        #116:#166     // "<init>":(I)V
  #168 = Methodref          #164.#167     // java/lang/StringBuilder."<init>":(I)V
  #169 = Utf8               Diverging implicit expansion for Case.Aux[
  #170 = String             #169          // Diverging implicit expansion for Case.Aux[
  #171 = Utf8               append
  #172 = Utf8               (Ljava/lang/String;)Ljava/lang/StringBuilder;
  #173 = NameAndType        #171:#172     // append:(Ljava/lang/String;)Ljava/lang/StringBuilder;
  #174 = Methodref          #164.#173     // java/lang/StringBuilder.append:(Ljava/lang/String;)Ljava/lang/StringBuilder;
  #175 = Utf8               (Ljava/lang/Object;)Ljava/lang/StringBuilder;
  #176 = NameAndType        #171:#175     // append:(Ljava/lang/Object;)Ljava/lang/StringBuilder;
  #177 = Methodref          #164.#176     // java/lang/StringBuilder.append:(Ljava/lang/Object;)Ljava/lang/StringBuilder;
  #178 = Utf8               ,
  #179 = String             #178          // ,
  #180 = Utf8                :: HNil]
  #181 = String             #180          //  :: HNil]
  #182 = Utf8               toString
  #183 = Utf8               ()Ljava/lang/String;
  #184 = NameAndType        #182:#183     // toString:()Ljava/lang/String;
  #185 = Methodref          #164.#184     // java/lang/StringBuilder.toString:()Ljava/lang/String;
  #186 = Utf8               abort
  #187 = Utf8               (Lscala/reflect/api/Position;Ljava/lang/String;)Lscala/runtime/Nothing$;
  #188 = NameAndType        #186:#187     // abort:(Lscala/reflect/api/Position;Ljava/lang/String;)Lscala/runtime/Nothing$;
  #189 = InterfaceMethodref #79.#188      // scala/reflect/macros/whitebox/Context.abort:(Lscala/reflect/api/Position;Ljava/lang/String;)Lscala/runtime/Nothing$;
  #190 = Utf8               SingleTypeTag
  #191 = Utf8               ()Lscala/reflect/ClassTag;
  #192 = NameAndType        #190:#191     // SingleTypeTag:()Lscala/reflect/ClassTag;
  #193 = Methodref          #104.#192     // scala/reflect/macros/Universe.SingleTypeTag:()Lscala/reflect/ClassTag;
  #194 = Utf8               scala/reflect/ClassTag
  #195 = Class              #194          // scala/reflect/ClassTag
  #196 = Utf8               unapply
  #197 = Utf8               (Ljava/lang/Object;)Lscala/Option;
  #198 = NameAndType        #196:#197     // unapply:(Ljava/lang/Object;)Lscala/Option;
  #199 = InterfaceMethodref #195.#198     // scala/reflect/ClassTag.unapply:(Ljava/lang/Object;)Lscala/Option;
  #200 = Utf8               scala/Option
  #201 = Class              #200          // scala/Option
  #202 = Utf8               isEmpty
  #203 = Utf8               ()Z
  #204 = NameAndType        #202:#203     // isEmpty:()Z
  #205 = Methodref          #201.#204     // scala/Option.isEmpty:()Z
  #206 = Utf8               get
  #207 = NameAndType        #206:#131     // get:()Ljava/lang/Object;
  #208 = Methodref          #201.#207     // scala/Option.get:()Ljava/lang/Object;
  #209 = Utf8               SingleType
  #210 = Utf8               ()Lscala/reflect/api/Types$SingleTypeExtractor;
  #211 = NameAndType        #209:#210     // SingleType:()Lscala/reflect/api/Types$SingleTypeExtractor;
  #212 = Methodref          #104.#211     // scala/reflect/macros/Universe.SingleType:()Lscala/reflect/api/Types$SingleTypeExtractor;
  #213 = Utf8               (Lscala/reflect/api/Types$SingleTypeApi;)Lscala/Option;
  #214 = NameAndType        #196:#213     // unapply:(Lscala/reflect/api/Types$SingleTypeApi;)Lscala/Option;
  #215 = Methodref          #71.#214      // scala/reflect/api/Types$SingleTypeExtractor.unapply:(Lscala/reflect/api/Types$SingleTypeApi;)Lscala/Option;
  #216 = Utf8               scala/Tuple2
  #217 = Class              #216          // scala/Tuple2
  #218 = Utf8               _2
  #219 = NameAndType        #218:#131     // _2:()Ljava/lang/Object;
  #220 = Methodref          #217.#219     // scala/Tuple2._2:()Ljava/lang/Object;
  #221 = Utf8               Can only materialize cases from singleton values
  #222 = String             #221          // Can only materialize cases from singleton values
  #223 = Utf8               internal
  #224 = Utf8               ()Lscala/reflect/api/Internals$InternalApi;
  #225 = NameAndType        #223:#224     // internal:()Lscala/reflect/api/Internals$InternalApi;
  #226 = Methodref          #104.#225     // scala/reflect/macros/Universe.internal:()Lscala/reflect/api/Internals$InternalApi;
  #227 = Utf8               reificationSupport
  #228 = Utf8               ()Lscala/reflect/api/Internals$ReificationSupportApi;
  #229 = NameAndType        #227:#228     // reificationSupport:()Lscala/reflect/api/Internals$ReificationSupportApi;
  #230 = InterfaceMethodref #15.#229      // scala/reflect/api/Internals$InternalApi.reificationSupport:()Lscala/reflect/api/Internals$ReificationSupportApi;
  #231 = Utf8               SyntacticTypeApplied
  #232 = Utf8               ()Lscala/reflect/api/Internals$ReificationSupportApi$SyntacticTypeAppliedExtractor;
  #233 = NameAndType        #231:#232     // SyntacticTypeApplied:()Lscala/reflect/api/Internals$ReificationSupportApi$SyntacticTypeAppliedExtractor;
  #234 = InterfaceMethodref #20.#233      // scala/reflect/api/Internals$ReificationSupportApi.SyntacticTypeApplied:()Lscala/reflect/api/Internals$ReificationSupportApi$SyntacticTypeAppliedExtractor;
  #235 = Utf8               SyntacticSelectTerm
  #236 = Utf8               ()Lscala/reflect/api/Internals$ReificationSupportApi$SyntacticSelectTermExtractor;
  #237 = NameAndType        #235:#236     // SyntacticSelectTerm:()Lscala/reflect/api/Internals$ReificationSupportApi$SyntacticSelectTermExtractor;
  #238 = InterfaceMethodref #20.#237      // scala/reflect/api/Internals$ReificationSupportApi.SyntacticSelectTerm:()Lscala/reflect/api/Internals$ReificationSupportApi$SyntacticSelectTermExtractor;
  #239 = Utf8               EmptyTree
  #240 = Utf8               ()Lscala/reflect/api/Trees$TreeApi;
  #241 = NameAndType        #239:#240     // EmptyTree:()Lscala/reflect/api/Trees$TreeApi;
  #242 = Methodref          #104.#241     // scala/reflect/macros/Universe.EmptyTree:()Lscala/reflect/api/Trees$TreeApi;
  #243 = Utf8               mkRefTree
  #244 = Utf8               (Lscala/reflect/api/Trees$TreeApi;Lscala/reflect/api/Symbols$SymbolApi;)Lscala/reflect/api/Trees$TreeApi;
  #245 = NameAndType        #243:#244     // mkRefTree:(Lscala/reflect/api/Trees$TreeApi;Lscala/reflect/api/Symbols$SymbolApi;)Lscala/reflect/api/Trees$TreeApi;
  #246 = InterfaceMethodref #20.#245      // scala/reflect/api/Internals$ReificationSupportApi.mkRefTree:(Lscala/reflect/api/Trees$TreeApi;Lscala/reflect/api/Symbols$SymbolApi;)Lscala/reflect/api/Trees$TreeApi;
  #247 = Utf8               TermName
  #248 = Utf8               ()Lscala/reflect/api/Names$TermNameExtractor;
  #249 = NameAndType        #247:#248     // TermName:()Lscala/reflect/api/Names$TermNameExtractor;
  #250 = Methodref          #104.#249     // scala/reflect/macros/Universe.TermName:()Lscala/reflect/api/Names$TermNameExtractor;
  #251 = Utf8               caseUniv
  #252 = String             #251          // caseUniv
  #253 = Utf8               (Ljava/lang/String;)Lscala/reflect/api/Names$TermNameApi;
  #254 = NameAndType        #120:#253     // apply:(Ljava/lang/String;)Lscala/reflect/api/Names$TermNameApi;
  #255 = Methodref          #42.#254      // scala/reflect/api/Names$TermNameExtractor.apply:(Ljava/lang/String;)Lscala/reflect/api/Names$TermNameApi;
  #256 = Utf8               (Lscala/reflect/api/Trees$TreeApi;Lscala/reflect/api/Names$TermNameApi;)Lscala/reflect/api/Trees$SelectApi;
  #257 = NameAndType        #120:#256     // apply:(Lscala/reflect/api/Trees$TreeApi;Lscala/reflect/api/Names$TermNameApi;)Lscala/reflect/api/Trees$SelectApi;
  #258 = InterfaceMethodref #23.#257      // scala/reflect/api/Internals$ReificationSupportApi$SyntacticSelectTermExtractor.apply:(Lscala/reflect/api/Trees$TreeApi;Lscala/reflect/api/Names$TermNameApi;)Lscala/reflect/api/Trees$SelectApi;
  #259 = Utf8               scala/collection/immutable/$colon$colon
  #260 = Class              #259          // scala/collection/immutable/$colon$colon
  #261 = Utf8               ()Lscala/reflect/api/Liftables$Liftable$;
  #262 = NameAndType        #32:#261      // Liftable:()Lscala/reflect/api/Liftables$Liftable$;
  #263 = Methodref          #104.#262     // scala/reflect/macros/Universe.Liftable:()Lscala/reflect/api/Liftables$Liftable$;
  #264 = Utf8               liftType
  #265 = Utf8               ()Lscala/reflect/api/Liftables$Liftable;
  #266 = NameAndType        #264:#265     // liftType:()Lscala/reflect/api/Liftables$Liftable;
  #267 = Methodref          #34.#266      // scala/reflect/api/Liftables$Liftable$.liftType:()Lscala/reflect/api/Liftables$Liftable;
  #268 = Utf8               (Ljava/lang/Object;)Lscala/reflect/api/Trees$TreeApi;
  #269 = NameAndType        #120:#268     // apply:(Ljava/lang/Object;)Lscala/reflect/api/Trees$TreeApi;
  #270 = InterfaceMethodref #29.#269      // scala/reflect/api/Liftables$Liftable.apply:(Ljava/lang/Object;)Lscala/reflect/api/Trees$TreeApi;
  #271 = Utf8               scala/collection/immutable/Nil$
  #272 = Class              #271          // scala/collection/immutable/Nil$
  #273 = Utf8               MODULE$
  #274 = Utf8               Lscala/collection/immutable/Nil$;
  #275 = NameAndType        #273:#274     // MODULE$:Lscala/collection/immutable/Nil$;
  #276 = Fieldref           #272.#275     // scala/collection/immutable/Nil$.MODULE$:Lscala/collection/immutable/Nil$;
  #277 = Utf8               (Ljava/lang/Object;Lscala/collection/immutable/List;)V
  #278 = NameAndType        #116:#277     // "<init>":(Ljava/lang/Object;Lscala/collection/immutable/List;)V
  #279 = Methodref          #260.#278     // scala/collection/immutable/$colon$colon."<init>":(Ljava/lang/Object;Lscala/collection/immutable/List;)V
  #280 = Utf8               (Lscala/reflect/api/Trees$TreeApi;Lscala/collection/immutable/List;)Lscala/reflect/api/Trees$TreeApi;
  #281 = NameAndType        #120:#280     // apply:(Lscala/reflect/api/Trees$TreeApi;Lscala/collection/immutable/List;)Lscala/reflect/api/Trees$TreeApi;
  #282 = InterfaceMethodref #26.#281      // scala/reflect/api/Internals$ReificationSupportApi$SyntacticTypeAppliedExtractor.apply:(Lscala/reflect/api/Trees$TreeApi;Lscala/collection/immutable/List;)Lscala/reflect/api/Trees$TreeApi;
  #283 = Utf8               $u
  #284 = Utf8               Lscala/reflect/macros/Universe;
  #285 = Utf8               $m
  #286 = Utf8               Lscala/reflect/api/Mirror;
  #287 = Utf8               f
  #288 = Utf8               Lscala/reflect/api/Symbols$SymbolApi;
  #289 = Utf8               pTpe
  #290 = Utf8               Lscala/reflect/api/Types$TypeApi;
  #291 = Utf8               ftTpe
  #292 = Utf8               tTpe
  #293 = Utf8               recTpe
  #294 = Utf8               value
  #295 = Utf8               Lscala/reflect/api/TypeTags$WeakTypeTag;
  #296 = Utf8               scala/reflect/api/Mirror
  #297 = Class              #296          // scala/reflect/api/Mirror
  #298 = Utf8               $anonfun$materializeFromValueImpl$1
  #299 = Utf8               (Lscala/reflect/api/Types$TypeApi;Lscala/reflect/macros/whitebox/Context$ImplicitCandidate;)Z
  #300 = Utf8               recTpe$1
  #301 = Utf8               x$12
  #302 = Utf8               pt
  #303 = Utf8               ()Lscala/reflect/api/Types$TypeApi;
  #304 = NameAndType        #302:#303     // pt:()Lscala/reflect/api/Types$TypeApi;
  #305 = Methodref          #77.#304      // scala/reflect/macros/whitebox/Context$ImplicitCandidate.pt:()Lscala/reflect/api/Types$TypeApi;
  #306 = Utf8               $eq$colon$eq
  #307 = Utf8               (Lscala/reflect/api/Types$TypeApi;)Z
  #308 = NameAndType        #306:#307     // $eq$colon$eq:(Lscala/reflect/api/Types$TypeApi;)Z
  #309 = Methodref          #74.#308      // scala/reflect/api/Types$TypeApi.$eq$colon$eq:(Lscala/reflect/api/Types$TypeApi;)Z
  #310 = Utf8               Lscala/reflect/macros/whitebox/Context$ImplicitCandidate;
  #311 = Utf8               (Lscala/reflect/macros/whitebox/Context;)V
  #312 = Utf8               ()V
  #313 = NameAndType        #116:#312     // "<init>":()V
  #314 = Methodref          #4.#313       // java/lang/Object."<init>":()V
  #315 = NameAndType        #298:#299     // $anonfun$materializeFromValueImpl$1:(Lscala/reflect/api/Types$TypeApi;Lscala/reflect/macros/whitebox/Context$ImplicitCandidate;)Z
  #316 = Methodref          #2.#315       // shapeless/PolyMacros.$anonfun$materializeFromValueImpl$1:(Lscala/reflect/api/Types$TypeApi;Lscala/reflect/macros/whitebox/Context$ImplicitCandidate;)Z
  #317 = Utf8               scala/runtime/BoxesRunTime
  #318 = Class              #317          // scala/runtime/BoxesRunTime
  #319 = Utf8               boxToBoolean
  #320 = Utf8               (Z)Ljava/lang/Boolean;
  #321 = NameAndType        #319:#320     // boxToBoolean:(Z)Ljava/lang/Boolean;
  #322 = Methodref          #318.#321     // scala/runtime/BoxesRunTime.boxToBoolean:(Z)Ljava/lang/Boolean;
  #323 = Utf8               $deserializeLambda$
  #324 = Utf8               (Ljava/lang/invoke/SerializedLambda;)Ljava/lang/Object;
  #325 = Utf8               scala/runtime/LambdaDeserialize
  #326 = Class              #325          // scala/runtime/LambdaDeserialize
  #327 = Utf8               bootstrap
  #328 = Utf8               (Ljava/lang/invoke/MethodHandles$Lookup;Ljava/lang/String;Ljava/lang/invoke/MethodType;[Ljava/lang/invoke/MethodHandle;)Ljava/lang/invoke/CallSite;
  #329 = NameAndType        #327:#328     // bootstrap:(Ljava/lang/invoke/MethodHandles$Lookup;Ljava/lang/String;Ljava/lang/invoke/MethodType;[Ljava/lang/invoke/MethodHandle;)Ljava/lang/invoke/CallSite;
  #330 = Methodref          #326.#329     // scala/runtime/LambdaDeserialize.bootstrap:(Ljava/lang/invoke/MethodHandles$Lookup;Ljava/lang/String;Ljava/lang/invoke/MethodType;[Ljava/lang/invoke/MethodHandle;)Ljava/lang/invoke/CallSite;
  #331 = MethodHandle       6:#330        // REF_invokeStatic scala/runtime/LambdaDeserialize.bootstrap:(Ljava/lang/invoke/MethodHandles$Lookup;Ljava/lang/String;Ljava/lang/invoke/MethodType;[Ljava/lang/invoke/MethodHandle;)Ljava/lang/invoke/CallSite;
  #332 = Utf8               lambdaDeserialize
  #333 = NameAndType        #332:#324     // lambdaDeserialize:(Ljava/lang/invoke/SerializedLambda;)Ljava/lang/Object;
  #334 = InvokeDynamic      #1:#333       // #1:lambdaDeserialize:(Ljava/lang/invoke/SerializedLambda;)Ljava/lang/Object;
  #335 = Utf8               Code
  #336 = Utf8               LineNumberTable
  #337 = Utf8               LocalVariableTable
  #338 = Utf8               StackMapTable
  #339 = Utf8               Signature
  #340 = Utf8               MethodParameters
  #341 = Utf8               InnerClasses
  #342 = Utf8               SourceFile
  #343 = Utf8               RuntimeVisibleAnnotations
  #344 = Utf8               BootstrapMethods
  #345 = Utf8               ScalaInlineInfo
  #346 = Utf8               ScalaSig
{
  private final scala.reflect.macros.whitebox.Context c;
    descriptor: Lscala/reflect/macros/whitebox/Context;
    flags: (0x0012) ACC_PRIVATE, ACC_FINAL

  public scala.reflect.macros.whitebox.Context c();
    descriptor: ()Lscala/reflect/macros/whitebox/Context;
    flags: (0x0001) ACC_PUBLIC
    Code:
      stack=1, locals=1, args_size=1
         0: aload_0
         1: getfield      #88                 // Field c:Lscala/reflect/macros/whitebox/Context;
         4: areturn
      LineNumberTable:
        line 264: 0
      LocalVariableTable:
        Start  Length  Slot  Name   Signature
            0       5     0  this   Lshapeless/PolyMacros;

  public <P extends java.lang.Object, FT extends java.lang.Object, T extends java.lang.Object> scala.reflect.api.Trees$TreeApi materializeFromValueImpl(scala.reflect.api.TypeTags$WeakTypeTag<P>, scala.reflect.api.TypeTags$WeakTypeTag<FT>, scala.reflect.api.TypeTags$WeakTypeTag<T>);
    descriptor: (Lscala/reflect/api/TypeTags$WeakTypeTag;Lscala/reflect/api/TypeTags$WeakTypeTag;Lscala/reflect/api/TypeTags$WeakTypeTag;)Lscala/reflect/api/Trees$TreeApi;
    flags: (0x0001) ACC_PUBLIC
    Code:
      stack=8, locals=17, args_size=4
         0: aload_0
         1: invokevirtual #98                 // Method c:()Lscala/reflect/macros/whitebox/Context;
         4: invokeinterface #102,  1          // InterfaceMethod scala/reflect/macros/whitebox/Context.universe:()Lscala/reflect/macros/Universe;
         9: aload_1
        10: invokevirtual #108                // Method scala/reflect/macros/Universe.weakTypeOf:(Lscala/reflect/api/TypeTags$WeakTypeTag;)Lscala/reflect/api/Types$TypeApi;
        13: astore        5
        15: aload_0
        16: invokevirtual #98                 // Method c:()Lscala/reflect/macros/whitebox/Context;
        19: invokeinterface #102,  1          // InterfaceMethod scala/reflect/macros/whitebox/Context.universe:()Lscala/reflect/macros/Universe;
        24: aload_2
        25: invokevirtual #108                // Method scala/reflect/macros/Universe.weakTypeOf:(Lscala/reflect/api/TypeTags$WeakTypeTag;)Lscala/reflect/api/Types$TypeApi;
        28: astore        6
        30: aload_0
        31: invokevirtual #98                 // Method c:()Lscala/reflect/macros/whitebox/Context;
        34: invokeinterface #102,  1          // InterfaceMethod scala/reflect/macros/whitebox/Context.universe:()Lscala/reflect/macros/Universe;
        39: aload_3
        40: invokevirtual #108                // Method scala/reflect/macros/Universe.weakTypeOf:(Lscala/reflect/api/TypeTags$WeakTypeTag;)Lscala/reflect/api/Types$TypeApi;
        43: astore        7
        45: aload_0
        46: invokevirtual #98                 // Method c:()Lscala/reflect/macros/whitebox/Context;
        49: invokeinterface #102,  1          // InterfaceMethod scala/reflect/macros/whitebox/Context.universe:()Lscala/reflect/macros/Universe;
        54: aload_0
        55: invokevirtual #98                 // Method c:()Lscala/reflect/macros/whitebox/Context;
        58: invokeinterface #102,  1          // InterfaceMethod scala/reflect/macros/whitebox/Context.universe:()Lscala/reflect/macros/Universe;
        63: astore        9
        65: aload_0
        66: invokevirtual #98                 // Method c:()Lscala/reflect/macros/whitebox/Context;
        69: invokeinterface #102,  1          // InterfaceMethod scala/reflect/macros/whitebox/Context.universe:()Lscala/reflect/macros/Universe;
        74: invokevirtual #112                // Method scala/reflect/macros/Universe.rootMirror:()Lscala/reflect/api/Mirror;
        77: astore        10
        79: aload         9
        81: invokevirtual #115                // Method scala/reflect/macros/Universe.WeakTypeTag:()Lscala/reflect/api/TypeTags$WeakTypeTag$;
        84: aload         10
        86: new           #82                 // class shapeless/PolyMacros$$typecreator1$1
        89: dup
        90: aconst_null
        91: aload_1
        92: aload_2
        93: invokespecial #119                // Method shapeless/PolyMacros$$typecreator1$1."<init>":(Lshapeless/PolyMacros;Lscala/reflect/api/TypeTags$WeakTypeTag;Lscala/reflect/api/TypeTags$WeakTypeTag;)V
        96: invokevirtual #123                // Method scala/reflect/api/TypeTags$WeakTypeTag$.apply:(Lscala/reflect/api/Mirror;Lscala/reflect/api/TypeCreator;)Lscala/reflect/api/TypeTags$WeakTypeTag;
        99: invokevirtual #108                // Method scala/reflect/macros/Universe.weakTypeOf:(Lscala/reflect/api/TypeTags$WeakTypeTag;)Lscala/reflect/api/Types$TypeApi;
       102: astore        8
       104: aload_0
       105: invokevirtual #98                 // Method c:()Lscala/reflect/macros/whitebox/Context;
       108: invokeinterface #127,  1          // InterfaceMethod scala/reflect/macros/whitebox/Context.openImplicits:()Lscala/collection/immutable/List;
       113: invokevirtual #133                // Method scala/collection/immutable/List.tail:()Ljava/lang/Object;
       116: checkcast     #129                // class scala/collection/immutable/List
       119: aload         8
       121: invokedynamic #154,  0            // InvokeDynamic #0:apply:(Lscala/reflect/api/Types$TypeApi;)Lscala/Function1;
       126: invokevirtual #158                // Method scala/collection/immutable/List.exists:(Lscala/Function1;)Z
       129: ifeq          188
       132: aload_0
       133: invokevirtual #98                 // Method c:()Lscala/reflect/macros/whitebox/Context;
       136: aload_0
       137: invokevirtual #98                 // Method c:()Lscala/reflect/macros/whitebox/Context;
       140: invokeinterface #162,  1          // InterfaceMethod scala/reflect/macros/whitebox/Context.enclosingPosition:()Lscala/reflect/api/Position;
       145: new           #164                // class java/lang/StringBuilder
       148: dup
       149: ldc           #165                // int 53
       151: invokespecial #168                // Method java/lang/StringBuilder."<init>":(I)V
       154: ldc           #170                // String Diverging implicit expansion for Case.Aux[
       156: invokevirtual #174                // Method java/lang/StringBuilder.append:(Ljava/lang/String;)Ljava/lang/StringBuilder;
       159: aload         5
       161: invokevirtual #177                // Method java/lang/StringBuilder.append:(Ljava/lang/Object;)Ljava/lang/StringBuilder;
       164: ldc           #179                // String ,
       166: invokevirtual #174                // Method java/lang/StringBuilder.append:(Ljava/lang/String;)Ljava/lang/StringBuilder;
       169: aload         6
       171: invokevirtual #177                // Method java/lang/StringBuilder.append:(Ljava/lang/Object;)Ljava/lang/StringBuilder;
       174: ldc           #181                // String  :: HNil]
       176: invokevirtual #174                // Method java/lang/StringBuilder.append:(Ljava/lang/String;)Ljava/lang/StringBuilder;
       179: invokevirtual #185                // Method java/lang/StringBuilder.toString:()Ljava/lang/String;
       182: invokeinterface #189,  3          // InterfaceMethod scala/reflect/macros/whitebox/Context.abort:(Lscala/reflect/api/Position;Ljava/lang/String;)Lscala/runtime/Nothing$;
       187: athrow
       188: aload         5
       190: astore        12
       192: aload         12
       194: ifnull        300
       197: aload_0
       198: invokevirtual #98                 // Method c:()Lscala/reflect/macros/whitebox/Context;
       201: invokeinterface #102,  1          // InterfaceMethod scala/reflect/macros/whitebox/Context.universe:()Lscala/reflect/macros/Universe;
       206: invokevirtual #193                // Method scala/reflect/macros/Universe.SingleTypeTag:()Lscala/reflect/ClassTag;
       209: aload         12
       211: invokeinterface #199,  2          // InterfaceMethod scala/reflect/ClassTag.unapply:(Ljava/lang/Object;)Lscala/Option;
       216: astore        13
       218: aload         13
       220: invokevirtual #205                // Method scala/Option.isEmpty:()Z
       223: ifne          297
       226: aload         13
       228: invokevirtual #208                // Method scala/Option.get:()Ljava/lang/Object;
       231: checkcast     #66                 // class scala/reflect/api/Types$SingleTypeApi
       234: astore        14
       236: aload         14
       238: ifnull        294
       241: aload_0
       242: invokevirtual #98                 // Method c:()Lscala/reflect/macros/whitebox/Context;
       245: invokeinterface #102,  1          // InterfaceMethod scala/reflect/macros/whitebox/Context.universe:()Lscala/reflect/macros/Universe;
       250: invokevirtual #212                // Method scala/reflect/macros/Universe.SingleType:()Lscala/reflect/api/Types$SingleTypeExtractor;
       253: aload         14
       255: invokevirtual #215                // Method scala/reflect/api/Types$SingleTypeExtractor.unapply:(Lscala/reflect/api/Types$SingleTypeApi;)Lscala/Option;
       258: astore        15
       260: aload         15
       262: invokevirtual #205                // Method scala/Option.isEmpty:()Z
       265: ifne          291
       268: aload         15
       270: invokevirtual #208                // Method scala/Option.get:()Ljava/lang/Object;
       273: checkcast     #217                // class scala/Tuple2
       276: invokevirtual #220                // Method scala/Tuple2._2:()Ljava/lang/Object;
       279: checkcast     #45                 // class scala/reflect/api/Symbols$SymbolApi
       282: astore        16
       284: aload         16
       286: astore        4
       288: goto          324
       291: goto          303
       294: goto          303
       297: goto          303
       300: goto          303
       303: aload_0
       304: invokevirtual #98                 // Method c:()Lscala/reflect/macros/whitebox/Context;
       307: aload_0
       308: invokevirtual #98                 // Method c:()Lscala/reflect/macros/whitebox/Context;
       311: invokeinterface #162,  1          // InterfaceMethod scala/reflect/macros/whitebox/Context.enclosingPosition:()Lscala/reflect/api/Position;
       316: ldc           #222                // String Can only materialize cases from singleton values
       318: invokeinterface #189,  3          // InterfaceMethod scala/reflect/macros/whitebox/Context.abort:(Lscala/reflect/api/Position;Ljava/lang/String;)Lscala/runtime/Nothing$;
       323: athrow
       324: aload         4
       326: astore        11
       328: aload_0
       329: invokevirtual #98                 // Method c:()Lscala/reflect/macros/whitebox/Context;
       332: invokeinterface #102,  1          // InterfaceMethod scala/reflect/macros/whitebox/Context.universe:()Lscala/reflect/macros/Universe;
       337: invokevirtual #226                // Method scala/reflect/macros/Universe.internal:()Lscala/reflect/api/Internals$InternalApi;
       340: invokeinterface #230,  1          // InterfaceMethod scala/reflect/api/Internals$InternalApi.reificationSupport:()Lscala/reflect/api/Internals$ReificationSupportApi;
       345: invokeinterface #234,  1          // InterfaceMethod scala/reflect/api/Internals$ReificationSupportApi.SyntacticTypeApplied:()Lscala/reflect/api/Internals$ReificationSupportApi$SyntacticTypeAppliedExtractor;
       350: aload_0
       351: invokevirtual #98                 // Method c:()Lscala/reflect/macros/whitebox/Context;
       354: invokeinterface #102,  1          // InterfaceMethod scala/reflect/macros/whitebox/Context.universe:()Lscala/reflect/macros/Universe;
       359: invokevirtual #226                // Method scala/reflect/macros/Universe.internal:()Lscala/reflect/api/Internals$InternalApi;
       362: invokeinterface #230,  1          // InterfaceMethod scala/reflect/api/Internals$InternalApi.reificationSupport:()Lscala/reflect/api/Internals$ReificationSupportApi;
       367: invokeinterface #238,  1          // InterfaceMethod scala/reflect/api/Internals$ReificationSupportApi.SyntacticSelectTerm:()Lscala/reflect/api/Internals$ReificationSupportApi$SyntacticSelectTermExtractor;
       372: aload_0
       373: invokevirtual #98                 // Method c:()Lscala/reflect/macros/whitebox/Context;
       376: invokeinterface #102,  1          // InterfaceMethod scala/reflect/macros/whitebox/Context.universe:()Lscala/reflect/macros/Universe;
       381: invokevirtual #226                // Method scala/reflect/macros/Universe.internal:()Lscala/reflect/api/Internals$InternalApi;
       384: invokeinterface #230,  1          // InterfaceMethod scala/reflect/api/Internals$InternalApi.reificationSupport:()Lscala/reflect/api/Internals$ReificationSupportApi;
       389: aload_0
       390: invokevirtual #98                 // Method c:()Lscala/reflect/macros/whitebox/Context;
       393: invokeinterface #102,  1          // InterfaceMethod scala/reflect/macros/whitebox/Context.universe:()Lscala/reflect/macros/Universe;
       398: invokevirtual #242                // Method scala/reflect/macros/Universe.EmptyTree:()Lscala/reflect/api/Trees$TreeApi;
       401: aload         11
       403: invokeinterface #246,  3          // InterfaceMethod scala/reflect/api/Internals$ReificationSupportApi.mkRefTree:(Lscala/reflect/api/Trees$TreeApi;Lscala/reflect/api/Symbols$SymbolApi;)Lscala/reflect/api/Trees$TreeApi;
       408: aload_0
       409: invokevirtual #98                 // Method c:()Lscala/reflect/macros/whitebox/Context;
       412: invokeinterface #102,  1          // InterfaceMethod scala/reflect/macros/whitebox/Context.universe:()Lscala/reflect/macros/Universe;
       417: invokevirtual #250                // Method scala/reflect/macros/Universe.TermName:()Lscala/reflect/api/Names$TermNameExtractor;
       420: ldc           #252                // String caseUniv
       422: invokevirtual #255                // Method scala/reflect/api/Names$TermNameExtractor.apply:(Ljava/lang/String;)Lscala/reflect/api/Names$TermNameApi;
       425: invokeinterface #258,  3          // InterfaceMethod scala/reflect/api/Internals$ReificationSupportApi$SyntacticSelectTermExtractor.apply:(Lscala/reflect/api/Trees$TreeApi;Lscala/reflect/api/Names$TermNameApi;)Lscala/reflect/api/Trees$SelectApi;
       430: new           #260                // class scala/collection/immutable/$colon$colon
       433: dup
       434: aload_0
       435: invokevirtual #98                 // Method c:()Lscala/reflect/macros/whitebox/Context;
       438: invokeinterface #102,  1          // InterfaceMethod scala/reflect/macros/whitebox/Context.universe:()Lscala/reflect/macros/Universe;
       443: invokevirtual #263                // Method scala/reflect/macros/Universe.Liftable:()Lscala/reflect/api/Liftables$Liftable$;
       446: invokevirtual #267                // Method scala/reflect/api/Liftables$Liftable$.liftType:()Lscala/reflect/api/Liftables$Liftable;
       449: aload         7
       451: invokeinterface #270,  2          // InterfaceMethod scala/reflect/api/Liftables$Liftable.apply:(Ljava/lang/Object;)Lscala/reflect/api/Trees$TreeApi;
       456: getstatic     #276                // Field scala/collection/immutable/Nil$.MODULE$:Lscala/collection/immutable/Nil$;
       459: invokespecial #279                // Method scala/collection/immutable/$colon$colon."<init>":(Ljava/lang/Object;Lscala/collection/immutable/List;)V
       462: checkcast     #129                // class scala/collection/immutable/List
       465: invokeinterface #282,  3          // InterfaceMethod scala/reflect/api/Internals$ReificationSupportApi$SyntacticTypeAppliedExtractor.apply:(Lscala/reflect/api/Trees$TreeApi;Lscala/collection/immutable/List;)Lscala/reflect/api/Trees$TreeApi;
       470: areturn
      StackMapTable: number_of_entries = 7
        frame_type = 255 /* full_frame */
          offset_delta = 188
          locals = [ class shapeless/PolyMacros, class scala/reflect/api/TypeTags$WeakTypeTag, class scala/reflect/api/TypeTags$WeakTypeTag, class scala/reflect/api/TypeTags$WeakTypeTag, top, class scala/reflect/api/Types$TypeApi, class scala/reflect/api/Types$TypeApi, class scala/reflect/api/Types$TypeApi, class scala/reflect/api/Types$TypeApi, class scala/reflect/macros/Universe, class scala/reflect/api/Mirror ]
          stack = []
        frame_type = 255 /* full_frame */
          offset_delta = 102
          locals = [ class shapeless/PolyMacros, class scala/reflect/api/TypeTags$WeakTypeTag, class scala/reflect/api/TypeTags$WeakTypeTag, class scala/reflect/api/TypeTags$WeakTypeTag, top, class scala/reflect/api/Types$TypeApi, class scala/reflect/api/Types$TypeApi, class scala/reflect/api/Types$TypeApi, class scala/reflect/api/Types$TypeApi, class scala/reflect/macros/Universe, class scala/reflect/api/Mirror, top, class scala/reflect/api/Types$TypeApi, class scala/Option, class scala/reflect/api/Types$SingleTypeApi, class scala/Option ]
          stack = []
        frame_type = 250 /* chop */
          offset_delta = 2
        frame_type = 250 /* chop */
          offset_delta = 2
        frame_type = 250 /* chop */
          offset_delta = 2
        frame_type = 2 /* same */
        frame_type = 255 /* full_frame */
          offset_delta = 20
          locals = [ class shapeless/PolyMacros, class scala/reflect/api/TypeTags$WeakTypeTag, class scala/reflect/api/TypeTags$WeakTypeTag, class scala/reflect/api/TypeTags$WeakTypeTag, class scala/reflect/api/Symbols$SymbolApi, class scala/reflect/api/Types$TypeApi, class scala/reflect/api/Types$TypeApi, class scala/reflect/api/Types$TypeApi, class scala/reflect/api/Types$TypeApi, class scala/reflect/macros/Universe, class scala/reflect/api/Mirror, top, class scala/reflect/api/Types$TypeApi, class scala/Option, class scala/reflect/api/Types$SingleTypeApi, class scala/Option, class scala/reflect/api/Symbols$SymbolApi ]
          stack = []
      LineNumberTable:
        line 270: 0
        line 271: 15
        line 272: 30
        line 274: 45
        line 275: 104
        line 276: 132
        line 278: 188
        line 279: 192
        line 278: 226
        line 279: 236
        line 278: 268
        line 279: 284
        line 280: 303
        line 278: 324
        line 283: 328
      LocalVariableTable:
        Start  Length  Slot  Name   Signature
           63      36     9    $u   Lscala/reflect/macros/Universe;
           77      22    10    $m   Lscala/reflect/api/Mirror;
          282       9    16     f   Lscala/reflect/api/Symbols$SymbolApi;
           13     457     5  pTpe   Lscala/reflect/api/Types$TypeApi;
           28     442     6 ftTpe   Lscala/reflect/api/Types$TypeApi;
           43     427     7  tTpe   Lscala/reflect/api/Types$TypeApi;
          102     368     8 recTpe   Lscala/reflect/api/Types$TypeApi;
          326     144    11 value   Lscala/reflect/api/Symbols$SymbolApi;
            0     471     0  this   Lshapeless/PolyMacros;
            0     471     1 evidence$1   Lscala/reflect/api/TypeTags$WeakTypeTag;
            0     471     2 evidence$2   Lscala/reflect/api/TypeTags$WeakTypeTag;
            0     471     3 evidence$3   Lscala/reflect/api/TypeTags$WeakTypeTag;
    Signature: #93                          // <P:Ljava/lang/Object;FT:Ljava/lang/Object;T:Ljava/lang/Object;>(Lscala/reflect/api/TypeTags$WeakTypeTag<TP;>;Lscala/reflect/api/TypeTags$WeakTypeTag<TFT;>;Lscala/reflect/api/TypeTags$WeakTypeTag<TT;>;)Lscala/reflect/api/Trees$TreeApi;
    MethodParameters:
      Name                           Flags
      evidence$1                     final
      evidence$2                     final
      evidence$3                     final

  public static final boolean $anonfun$materializeFromValueImpl$1(scala.reflect.api.Types$TypeApi, scala.reflect.macros.whitebox.Context$ImplicitCandidate);
    descriptor: (Lscala/reflect/api/Types$TypeApi;Lscala/reflect/macros/whitebox/Context$ImplicitCandidate;)Z
    flags: (0x1019) ACC_PUBLIC, ACC_STATIC, ACC_FINAL, ACC_SYNTHETIC
    Code:
      stack=2, locals=2, args_size=2
         0: aload_1
         1: invokevirtual #305                // Method scala/reflect/macros/whitebox/Context$ImplicitCandidate.pt:()Lscala/reflect/api/Types$TypeApi;
         4: aload_0
         5: invokevirtual #309                // Method scala/reflect/api/Types$TypeApi.$eq$colon$eq:(Lscala/reflect/api/Types$TypeApi;)Z
         8: ireturn
      LineNumberTable:
        line 275: 0
      LocalVariableTable:
        Start  Length  Slot  Name   Signature
            0       9     0 recTpe$1   Lscala/reflect/api/Types$TypeApi;
            0       9     1  x$12   Lscala/reflect/macros/whitebox/Context$ImplicitCandidate;
    MethodParameters:
      Name                           Flags
      recTpe$1                       final
      x$12                           final

  public shapeless.PolyMacros(scala.reflect.macros.whitebox.Context);
    descriptor: (Lscala/reflect/macros/whitebox/Context;)V
    flags: (0x0001) ACC_PUBLIC
    Code:
      stack=2, locals=2, args_size=2
         0: aload_0
         1: aload_1
         2: putfield      #88                 // Field c:Lscala/reflect/macros/whitebox/Context;
         5: aload_0
         6: invokespecial #314                // Method java/lang/Object."<init>":()V
         9: return
      LineNumberTable:
        line 264: 0
        line 285: 5
        line 264: 9
      LocalVariableTable:
        Start  Length  Slot  Name   Signature
            0      10     0  this   Lshapeless/PolyMacros;
            0      10     1     c   Lscala/reflect/macros/whitebox/Context;
    MethodParameters:
      Name                           Flags
      c                              final

  public static final java.lang.Object $anonfun$materializeFromValueImpl$1$adapted(scala.reflect.api.Types$TypeApi, scala.reflect.macros.whitebox.Context$ImplicitCandidate);
    descriptor: (Lscala/reflect/api/Types$TypeApi;Lscala/reflect/macros/whitebox/Context$ImplicitCandidate;)Ljava/lang/Object;
    flags: (0x1019) ACC_PUBLIC, ACC_STATIC, ACC_FINAL, ACC_SYNTHETIC
    Code:
      stack=2, locals=2, args_size=2
         0: aload_0
         1: aload_1
         2: invokestatic  #316                // Method $anonfun$materializeFromValueImpl$1:(Lscala/reflect/api/Types$TypeApi;Lscala/reflect/macros/whitebox/Context$ImplicitCandidate;)Z
         5: invokestatic  #322                // Method scala/runtime/BoxesRunTime.boxToBoolean:(Z)Ljava/lang/Boolean;
         8: areturn
      LineNumberTable:
        line 275: 0
      LocalVariableTable:
        Start  Length  Slot  Name   Signature
            0       9     0 recTpe$1   Lscala/reflect/api/Types$TypeApi;
            0       9     1  x$12   Lscala/reflect/macros/whitebox/Context$ImplicitCandidate;
    MethodParameters:
      Name                           Flags
      recTpe$1                       final
      x$12                           final

  private static java.lang.Object $deserializeLambda$(java.lang.invoke.SerializedLambda);
    descriptor: (Ljava/lang/invoke/SerializedLambda;)Ljava/lang/Object;
    flags: (0x100a) ACC_PRIVATE, ACC_STATIC, ACC_SYNTHETIC
    Code:
      stack=1, locals=1, args_size=1
         0: aload_0
         1: invokedynamic #334,  0            // InvokeDynamic #1:lambdaDeserialize:(Ljava/lang/invoke/SerializedLambda;)Ljava/lang/Object;
         6: areturn
}
InnerClasses:
  public static final #13= #10 of #12;    // Lookup=class java/lang/invoke/MethodHandles$Lookup of class java/lang/invoke/MethodHandles
  public #18= #15 of #17;                 // InternalApi=class scala/reflect/api/Internals$InternalApi of class scala/reflect/api/Internals
  public #21= #20 of #17;                 // ReificationSupportApi=class scala/reflect/api/Internals$ReificationSupportApi of class scala/reflect/api/Internals
  public #24= #23 of #20;                 // SyntacticSelectTermExtractor=class scala/reflect/api/Internals$ReificationSupportApi$SyntacticSelectTermExtractor of class scala/reflect/api/Internals$ReificationSupportApi
  public #27= #26 of #20;                 // SyntacticTypeAppliedExtractor=class scala/reflect/api/Internals$ReificationSupportApi$SyntacticTypeAppliedExtractor of class scala/reflect/api/Internals$ReificationSupportApi
  public #32= #29 of #31;                 // Liftable=class scala/reflect/api/Liftables$Liftable of class scala/reflect/api/Liftables
  public #35= #34 of #31;                 // Liftable$=class scala/reflect/api/Liftables$Liftable$ of class scala/reflect/api/Liftables
  public #40= #37 of #39;                 // TermNameApi=class scala/reflect/api/Names$TermNameApi of class scala/reflect/api/Names
  public abstract #43= #42 of #39;        // TermNameExtractor=class scala/reflect/api/Names$TermNameExtractor of class scala/reflect/api/Names
  public #48= #45 of #47;                 // SymbolApi=class scala/reflect/api/Symbols$SymbolApi of class scala/reflect/api/Symbols
  public #53= #50 of #52;                 // SelectApi=class scala/reflect/api/Trees$SelectApi of class scala/reflect/api/Trees
  public #56= #55 of #52;                 // TreeApi=class scala/reflect/api/Trees$TreeApi of class scala/reflect/api/Trees
  public #61= #58 of #60;                 // WeakTypeTag=class scala/reflect/api/TypeTags$WeakTypeTag of class scala/reflect/api/TypeTags
  public #64= #63 of #60;                 // WeakTypeTag$=class scala/reflect/api/TypeTags$WeakTypeTag$ of class scala/reflect/api/TypeTags
  public #69= #66 of #68;                 // SingleTypeApi=class scala/reflect/api/Types$SingleTypeApi of class scala/reflect/api/Types
  public abstract #72= #71 of #68;        // SingleTypeExtractor=class scala/reflect/api/Types$SingleTypeExtractor of class scala/reflect/api/Types
  public abstract #75= #74 of #68;        // TypeApi=class scala/reflect/api/Types$TypeApi of class scala/reflect/api/Types
  public #80= #77 of #79;                 // ImplicitCandidate=class scala/reflect/macros/whitebox/Context$ImplicitCandidate of class scala/reflect/macros/whitebox/Context
  public final #83= #82;                  // $typecreator1$1=class shapeless/PolyMacros$$typecreator1$1
SourceFile: "poly.scala"
RuntimeVisibleAnnotations:
  0: #6(#7=s#8)
    scala.reflect.ScalaSignature(
      bytes="\u0006\u0005I3A!\u0002\u0004\u0001\u0013!A\u0001\u0003\u0001BC\u0002\u0013\u0005\u0011\u0003\u0003\u0005\u001d\u0001\t\u0005\t\u0015!\u0003\u0013\u0011\u0015i\u0002\u0001\"\u0001\u001f\u0011\u0015\u0011\u0003\u0001\"\u0001$\u0005)\u0001v\u000e\\=NC\u000e\u0014xn\u001d\u0006\u0002\u000f\u0005I1\u000f[1qK2,7o]\u0002\u0001\'\t\u0001!\u0002\u0005\u0002\f\u001d5\tABC\u0001\u000e\u0003\u0015\u00198-\u00197b\u0013\tyAB\u0001\u0004B]f\u0014VMZ\u0001\u0002GV\t!\u0003\u0005\u0002\u001455\tAC\u0003\u0002\u0016-\u0005Aq\u000f[5uK\n|\u0007P\u0003\u0002\u00181\u00051Q.Y2s_NT!!\u0007\u0007\u0002\u000fI,g\r\\3di&\u00111\u0004\u0006\u0002\b\u0007>tG/\u001a=u\u0003\t\u0019\u0007%\u0001\u0004=S:LGO\u0010\u000b\u0003?\u0005\u0002\"\u0001\t\u0001\u000e\u0003\u0019AQ\u0001E\u0002A\u0002I\t\u0001$\\1uKJL\u0017\r\\5{K\u001a\u0013x.\u001c,bYV,\u0017*\u001c9m+\u0011!SH\u0013)\u0015\t\u0015\"d\t\u0014\t\u0003M9r!aJ\u0015\u000f\u0005!\nQ\"\u0001\u0001\n\u0005)Z\u0013\u0001C;oSZ,\'o]3\n\u0005ma#BA\u0017\u0017\u0003!\u0011G.Y2lE>D\u0018BA\u00181\u0005\u0011!&/Z3\n\u0005E\u0012$!\u0002+sK\u0016\u001c(BA\u001a\u0019\u0003\r\t\u0007/\u001b\u0005\bk\u0011\t\t\u0011q\u00017\u0003))g/\u001b3f]\u000e,G%\r\t\u0004M]Z\u0014B\u0001\u001d:\u0005-9V-Y6UsB,G+Y4\n\u0005i\u0012$\u0001\u0003+za\u0016$\u0016mZ:\u0011\u0005qjD\u0002\u0001\u0003\u0006}\u0011\u0011\ra\u0010\u0002\u0002!F\u0011\u0001i\u0011\t\u0003\u0017\u0005K!A\u0011\u0007\u0003\u000f9{G\u000f[5oOB\u00111\u0002R\u0005\u0003\u000b2\u00111!\u00118z\u0011\u001d9E!!AA\u0004!\u000b!\"\u001a<jI\u0016t7-\u001a\u00133!\r1s\'\u0013\t\u0003y)#Qa\u0013\u0003C\u0002}\u0012!A\u0012+\t\u000f5#\u0011\u0011!a\u0002\u001d\u0006QQM^5eK:\u001cW\rJ\u001a\u0011\u0007\u0019:t\n\u0005\u0002=!\u0012)\u0011\u000b\u0002b\u0001\u007f\t\tA\u000b"
    )
BootstrapMethods:
  0: #151 REF_invokeStatic java/lang/invoke/LambdaMetafactory.altMetafactory:(Ljava/lang/invoke/MethodHandles$Lookup;Ljava/lang/String;Ljava/lang/invoke/MethodType;[Ljava/lang/Object;)Ljava/lang/invoke/CallSite;
    Method arguments:
      #135 (Ljava/lang/Object;)Ljava/lang/Object;
      #140 REF_invokeStatic shapeless/PolyMacros.$anonfun$materializeFromValueImpl$1$adapted:(Lscala/reflect/api/Types$TypeApi;Lscala/reflect/macros/whitebox/Context$ImplicitCandidate;)Ljava/lang/Object;
      #142 (Lscala/reflect/macros/whitebox/Context$ImplicitCandidate;)Ljava/lang/Object;
      #143 5
      #144 1
      #142 (Lscala/reflect/macros/whitebox/Context$ImplicitCandidate;)Ljava/lang/Object;
  1: #331 REF_invokeStatic scala/runtime/LambdaDeserialize.bootstrap:(Ljava/lang/invoke/MethodHandles$Lookup;Ljava/lang/String;Ljava/lang/invoke/MethodType;[Ljava/lang/invoke/MethodHandle;)Ljava/lang/invoke/CallSite;
    Method arguments:
      #140 REF_invokeStatic shapeless/PolyMacros.$anonfun$materializeFromValueImpl$1$adapted:(Lscala/reflect/api/Types$TypeApi;Lscala/reflect/macros/whitebox/Context$ImplicitCandidate;)Ljava/lang/Object;
  ScalaInlineInfo: length = 0x1D (unknown attribute)
   01 00 00 05 00 88 00 89 01 01 2A 01 2B 01 00 74
   01 37 00 00 54 00 56 00 00 5B 00 5C 00
  ScalaSig: length = 0x3 (unknown attribute)
   05 02 00
