Classfile /Users/mw/Projects/slang-braindump/.jar/jar11/assemble/slang-braindump/assemble/content/shapeless/PolyDefns$Compose$$anon$3.class
  Last modified May 29, 2022; size 2628 bytes
  SHA-256 checksum 13a404d18df288c23bdb1682ce4ac2a6a8a200da331b7b1b2d9849f73a822a9c
  Compiled from "poly.scala"
public final class shapeless.PolyDefns$Compose$$anon$3 extends shapeless.PolyDefns$Case<C, shapeless.$colon$colon<T, shapeless.HNil>>
  minor version: 0
  major version: 52
  flags: (0x0031) ACC_PUBLIC, ACC_FINAL, ACC_SUPER
  this_class: #2                          // shapeless/PolyDefns$Compose$$anon$3
  super_class: #5                         // shapeless/PolyDefns$Case
  interfaces: 0, fields: 3, methods: 4, attributes: 7
Constant pool:
    #1 = Utf8               shapeless/PolyDefns$Compose$$anon$3
    #2 = Class              #1            // shapeless/PolyDefns$Compose$$anon$3
    #3 = Utf8               Lshapeless/PolyDefns$Case<TC;Lshapeless/$colon$colon<TT;Lshapeless/HNil;>;>;
    #4 = Utf8               shapeless/PolyDefns$Case
    #5 = Class              #4            // shapeless/PolyDefns$Case
    #6 = Utf8               poly.scala
    #7 = Utf8               shapeless/PolyDefns$Compose$
    #8 = Class              #7            // shapeless/PolyDefns$Compose$
    #9 = Utf8               composeCase
   #10 = Utf8               (Lshapeless/Unpack2;Lshapeless/PolyDefns$Case;Lshapeless/PolyDefns$Case;)Lshapeless/PolyDefns$Case;
   #11 = NameAndType        #9:#10        // composeCase:(Lshapeless/Unpack2;Lshapeless/PolyDefns$Case;Lshapeless/PolyDefns$Case;)Lshapeless/PolyDefns$Case;
   #12 = Utf8               java/lang/invoke/MethodHandles$Lookup
   #13 = Class              #12           // java/lang/invoke/MethodHandles$Lookup
   #14 = Utf8               java/lang/invoke/MethodHandles
   #15 = Class              #14           // java/lang/invoke/MethodHandles
   #16 = Utf8               Lookup
   #17 = Utf8               shapeless/PolyDefns
   #18 = Class              #17           // shapeless/PolyDefns
   #19 = Utf8               Case
   #20 = Utf8               Compose$
   #21 = Utf8               value
   #22 = Utf8               Lscala/Function1;
   #23 = Utf8               Lscala/Function1<Lshapeless/$colon$colon<TT;Lshapeless/HNil;>;TV;>;
   #24 = Utf8               cF$1
   #25 = Utf8               Lshapeless/PolyDefns$Case;
   #26 = Utf8               cG$1
   #27 = Utf8               ()Lscala/Function1;
   #28 = Utf8               ()Lscala/Function1<Lshapeless/$colon$colon<TT;Lshapeless/HNil;>;TV;>;
   #29 = NameAndType        #21:#22       // value:Lscala/Function1;
   #30 = Fieldref           #2.#29        // shapeless/PolyDefns$Compose$$anon$3.value:Lscala/Function1;
   #31 = Utf8               this
   #32 = Utf8               Lshapeless/PolyDefns$Compose$$anon$3;
   #33 = Utf8               $anonfun$value$2
   #34 = Utf8               (Lshapeless/PolyDefns$Compose$$anon$3;Lshapeless/$colon$colon;)Ljava/lang/Object;
   #35 = Utf8               $this
   #36 = Utf8               t
   #37 = NameAndType        #24:#25       // cF$1:Lshapeless/PolyDefns$Case;
   #38 = Fieldref           #2.#37        // shapeless/PolyDefns$Compose$$anon$3.cF$1:Lshapeless/PolyDefns$Case;
   #39 = NameAndType        #26:#25       // cG$1:Lshapeless/PolyDefns$Case;
   #40 = Fieldref           #2.#39        // shapeless/PolyDefns$Compose$$anon$3.cG$1:Lshapeless/PolyDefns$Case;
   #41 = NameAndType        #21:#27       // value:()Lscala/Function1;
   #42 = Methodref          #5.#41        // shapeless/PolyDefns$Case.value:()Lscala/Function1;
   #43 = Utf8               scala/Function1
   #44 = Class              #43           // scala/Function1
   #45 = Utf8               apply
   #46 = Utf8               (Ljava/lang/Object;)Ljava/lang/Object;
   #47 = NameAndType        #45:#46       // apply:(Ljava/lang/Object;)Ljava/lang/Object;
   #48 = InterfaceMethodref #44.#47       // scala/Function1.apply:(Ljava/lang/Object;)Ljava/lang/Object;
   #49 = Utf8               scala/$less$colon$less$
   #50 = Class              #49           // scala/$less$colon$less$
   #51 = Utf8               MODULE$
   #52 = Utf8               Lscala/$less$colon$less$;
   #53 = NameAndType        #51:#52       // MODULE$:Lscala/$less$colon$less$;
   #54 = Fieldref           #50.#53       // scala/$less$colon$less$.MODULE$:Lscala/$less$colon$less$;
   #55 = Utf8               refl
   #56 = Utf8               ()Lscala/$eq$colon$eq;
   #57 = NameAndType        #55:#56       // refl:()Lscala/$eq$colon$eq;
   #58 = Methodref          #50.#57       // scala/$less$colon$less$.refl:()Lscala/$eq$colon$eq;
   #59 = Utf8               (Ljava/lang/Object;Lscala/$eq$colon$eq;)Ljava/lang/Object;
   #60 = NameAndType        #45:#59       // apply:(Ljava/lang/Object;Lscala/$eq$colon$eq;)Ljava/lang/Object;
   #61 = Methodref          #5.#60        // shapeless/PolyDefns$Case.apply:(Ljava/lang/Object;Lscala/$eq$colon$eq;)Ljava/lang/Object;
   #62 = Utf8               Lshapeless/$colon$colon;
   #63 = Utf8               <init>
   #64 = Utf8               (Lshapeless/PolyDefns$Case;Lshapeless/PolyDefns$Case;)V
   #65 = Utf8               ()V
   #66 = NameAndType        #63:#65       // "<init>":()V
   #67 = Methodref          #5.#66        // shapeless/PolyDefns$Case."<init>":()V
   #68 = MethodType         #46           //  (Ljava/lang/Object;)Ljava/lang/Object;
   #69 = NameAndType        #33:#34       // $anonfun$value$2:(Lshapeless/PolyDefns$Compose$$anon$3;Lshapeless/$colon$colon;)Ljava/lang/Object;
   #70 = Methodref          #2.#69        // shapeless/PolyDefns$Compose$$anon$3.$anonfun$value$2:(Lshapeless/PolyDefns$Compose$$anon$3;Lshapeless/$colon$colon;)Ljava/lang/Object;
   #71 = MethodHandle       6:#70         // REF_invokeStatic shapeless/PolyDefns$Compose$$anon$3.$anonfun$value$2:(Lshapeless/PolyDefns$Compose$$anon$3;Lshapeless/$colon$colon;)Ljava/lang/Object;
   #72 = Utf8               (Lshapeless/$colon$colon;)Ljava/lang/Object;
   #73 = MethodType         #72           //  (Lshapeless/$colon$colon;)Ljava/lang/Object;
   #74 = Integer            5
   #75 = Integer            1
   #76 = Utf8               java/lang/invoke/LambdaMetafactory
   #77 = Class              #76           // java/lang/invoke/LambdaMetafactory
   #78 = Utf8               altMetafactory
   #79 = Utf8               (Ljava/lang/invoke/MethodHandles$Lookup;Ljava/lang/String;Ljava/lang/invoke/MethodType;[Ljava/lang/Object;)Ljava/lang/invoke/CallSite;
   #80 = NameAndType        #78:#79       // altMetafactory:(Ljava/lang/invoke/MethodHandles$Lookup;Ljava/lang/String;Ljava/lang/invoke/MethodType;[Ljava/lang/Object;)Ljava/lang/invoke/CallSite;
   #81 = Methodref          #77.#80       // java/lang/invoke/LambdaMetafactory.altMetafactory:(Ljava/lang/invoke/MethodHandles$Lookup;Ljava/lang/String;Ljava/lang/invoke/MethodType;[Ljava/lang/Object;)Ljava/lang/invoke/CallSite;
   #82 = MethodHandle       6:#81         // REF_invokeStatic java/lang/invoke/LambdaMetafactory.altMetafactory:(Ljava/lang/invoke/MethodHandles$Lookup;Ljava/lang/String;Ljava/lang/invoke/MethodType;[Ljava/lang/Object;)Ljava/lang/invoke/CallSite;
   #83 = Utf8               (Lshapeless/PolyDefns$Compose$$anon$3;)Lscala/Function1;
   #84 = NameAndType        #45:#83       // apply:(Lshapeless/PolyDefns$Compose$$anon$3;)Lscala/Function1;
   #85 = InvokeDynamic      #0:#84        // #0:apply:(Lshapeless/PolyDefns$Compose$$anon$3;)Lscala/Function1;
   #86 = Utf8               $deserializeLambda$
   #87 = Utf8               (Ljava/lang/invoke/SerializedLambda;)Ljava/lang/Object;
   #88 = Utf8               scala/runtime/LambdaDeserialize
   #89 = Class              #88           // scala/runtime/LambdaDeserialize
   #90 = Utf8               bootstrap
   #91 = Utf8               (Ljava/lang/invoke/MethodHandles$Lookup;Ljava/lang/String;Ljava/lang/invoke/MethodType;[Ljava/lang/invoke/MethodHandle;)Ljava/lang/invoke/CallSite;
   #92 = NameAndType        #90:#91       // bootstrap:(Ljava/lang/invoke/MethodHandles$Lookup;Ljava/lang/String;Ljava/lang/invoke/MethodType;[Ljava/lang/invoke/MethodHandle;)Ljava/lang/invoke/CallSite;
   #93 = Methodref          #89.#92       // scala/runtime/LambdaDeserialize.bootstrap:(Ljava/lang/invoke/MethodHandles$Lookup;Ljava/lang/String;Ljava/lang/invoke/MethodType;[Ljava/lang/invoke/MethodHandle;)Ljava/lang/invoke/CallSite;
   #94 = MethodHandle       6:#93         // REF_invokeStatic scala/runtime/LambdaDeserialize.bootstrap:(Ljava/lang/invoke/MethodHandles$Lookup;Ljava/lang/String;Ljava/lang/invoke/MethodType;[Ljava/lang/invoke/MethodHandle;)Ljava/lang/invoke/CallSite;
   #95 = Utf8               lambdaDeserialize
   #96 = NameAndType        #95:#87       // lambdaDeserialize:(Ljava/lang/invoke/SerializedLambda;)Ljava/lang/Object;
   #97 = InvokeDynamic      #1:#96        // #1:lambdaDeserialize:(Ljava/lang/invoke/SerializedLambda;)Ljava/lang/Object;
   #98 = Utf8               Signature
   #99 = Utf8               Code
  #100 = Utf8               LineNumberTable
  #101 = Utf8               LocalVariableTable
  #102 = Utf8               MethodParameters
  #103 = Utf8               InnerClasses
  #104 = Utf8               EnclosingMethod
  #105 = Utf8               SourceFile
  #106 = Utf8               BootstrapMethods
  #107 = Utf8               ScalaInlineInfo
  #108 = Utf8               Scala
{
  private final scala.Function1<shapeless.$colon$colon<T, shapeless.HNil>, V> value;
    descriptor: Lscala/Function1;
    flags: (0x0012) ACC_PRIVATE, ACC_FINAL
    Signature: #23                          // Lscala/Function1<Lshapeless/$colon$colon<TT;Lshapeless/HNil;>;TV;>;

  private final shapeless.PolyDefns$Case cF$1;
    descriptor: Lshapeless/PolyDefns$Case;
    flags: (0x0012) ACC_PRIVATE, ACC_FINAL

  private final shapeless.PolyDefns$Case cG$1;
    descriptor: Lshapeless/PolyDefns$Case;
    flags: (0x0012) ACC_PRIVATE, ACC_FINAL

  public scala.Function1<shapeless.$colon$colon<T, shapeless.HNil>, V> value();
    descriptor: ()Lscala/Function1;
    flags: (0x0001) ACC_PUBLIC
    Code:
      stack=1, locals=1, args_size=1
         0: aload_0
         1: getfield      #30                 // Field value:Lscala/Function1;
         4: areturn
      LineNumberTable:
        line 78: 0
      LocalVariableTable:
        Start  Length  Slot  Name   Signature
            0       5     0  this   Lshapeless/PolyDefns$Compose$$anon$3;
    Signature: #28                          // ()Lscala/Function1<Lshapeless/$colon$colon<TT;Lshapeless/HNil;>;TV;>;

  public static final java.lang.Object $anonfun$value$2(shapeless.PolyDefns$Compose$$anon$3, shapeless.$colon$colon);
    descriptor: (Lshapeless/PolyDefns$Compose$$anon$3;Lshapeless/$colon$colon;)Ljava/lang/Object;
    flags: (0x1019) ACC_PUBLIC, ACC_STATIC, ACC_FINAL, ACC_SYNTHETIC
    Code:
      stack=3, locals=2, args_size=2
         0: aload_0
         1: getfield      #38                 // Field cF$1:Lshapeless/PolyDefns$Case;
         4: aload_0
         5: getfield      #40                 // Field cG$1:Lshapeless/PolyDefns$Case;
         8: invokevirtual #42                 // Method shapeless/PolyDefns$Case.value:()Lscala/Function1;
        11: aload_1
        12: invokeinterface #48,  2           // InterfaceMethod scala/Function1.apply:(Ljava/lang/Object;)Ljava/lang/Object;
        17: getstatic     #54                 // Field scala/$less$colon$less$.MODULE$:Lscala/$less$colon$less$;
        20: invokevirtual #58                 // Method scala/$less$colon$less$.refl:()Lscala/$eq$colon$eq;
        23: invokevirtual #61                 // Method shapeless/PolyDefns$Case.apply:(Ljava/lang/Object;Lscala/$eq$colon$eq;)Ljava/lang/Object;
        26: areturn
      LineNumberTable:
        line 78: 0
      LocalVariableTable:
        Start  Length  Slot  Name   Signature
            0      27     0 $this   Lshapeless/PolyDefns$Compose$$anon$3;
            0      27     1     t   Lshapeless/$colon$colon;
    MethodParameters:
      Name                           Flags
      $this                          final synthetic
      t                              final

  public shapeless.PolyDefns$Compose$$anon$3(shapeless.PolyDefns$Case, shapeless.PolyDefns$Case);
    descriptor: (Lshapeless/PolyDefns$Case;Lshapeless/PolyDefns$Case;)V
    flags: (0x0001) ACC_PUBLIC
    Code:
      stack=2, locals=3, args_size=3
         0: aload_0
         1: aload_1
         2: putfield      #38                 // Field cF$1:Lshapeless/PolyDefns$Case;
         5: aload_0
         6: aload_2
         7: putfield      #40                 // Field cG$1:Lshapeless/PolyDefns$Case;
        10: aload_0
        11: invokespecial #67                 // Method shapeless/PolyDefns$Case."<init>":()V
        14: aload_0
        15: aload_0
        16: invokedynamic #85,  0             // InvokeDynamic #0:apply:(Lshapeless/PolyDefns$Compose$$anon$3;)Lscala/Function1;
        21: putfield      #30                 // Field value:Lscala/Function1;
        24: return
      LineNumberTable:
        line 76: 0
        line 78: 14
        line 76: 24
      LocalVariableTable:
        Start  Length  Slot  Name   Signature
            0      25     0  this   Lshapeless/PolyDefns$Compose$$anon$3;
            0      25     1  cF$1   Lshapeless/PolyDefns$Case;
            0      25     2  cG$1   Lshapeless/PolyDefns$Case;
    MethodParameters:
      Name                           Flags
      cF$1                           final
      cG$1                           final

  private static java.lang.Object $deserializeLambda$(java.lang.invoke.SerializedLambda);
    descriptor: (Ljava/lang/invoke/SerializedLambda;)Ljava/lang/Object;
    flags: (0x100a) ACC_PRIVATE, ACC_STATIC, ACC_SYNTHETIC
    Code:
      stack=1, locals=1, args_size=1
         0: aload_0
         1: invokedynamic #97,  0             // InvokeDynamic #1:lambdaDeserialize:(Ljava/lang/invoke/SerializedLambda;)Ljava/lang/Object;
         6: areturn
}
InnerClasses:
  public static final #16= #13 of #15;    // Lookup=class java/lang/invoke/MethodHandles$Lookup of class java/lang/invoke/MethodHandles
  public static abstract #19= #5 of #18;  // Case=class shapeless/PolyDefns$Case of class shapeless/PolyDefns
  public static #20= #8 of #18;           // Compose$=class shapeless/PolyDefns$Compose$ of class shapeless/PolyDefns
  public final #2;                        // class shapeless/PolyDefns$Compose$$anon$3
EnclosingMethod: #8.#11                 // shapeless.PolyDefns$Compose$.composeCase
Signature: #3                           // Lshapeless/PolyDefns$Case<TC;Lshapeless/$colon$colon<TT;Lshapeless/HNil;>;>;
SourceFile: "poly.scala"
BootstrapMethods:
  0: #82 REF_invokeStatic java/lang/invoke/LambdaMetafactory.altMetafactory:(Ljava/lang/invoke/MethodHandles$Lookup;Ljava/lang/String;Ljava/lang/invoke/MethodType;[Ljava/lang/Object;)Ljava/lang/invoke/CallSite;
    Method arguments:
      #68 (Ljava/lang/Object;)Ljava/lang/Object;
      #71 REF_invokeStatic shapeless/PolyDefns$Compose$$anon$3.$anonfun$value$2:(Lshapeless/PolyDefns$Compose$$anon$3;Lshapeless/$colon$colon;)Ljava/lang/Object;
      #73 (Lshapeless/$colon$colon;)Ljava/lang/Object;
      #74 5
      #75 1
      #73 (Lshapeless/$colon$colon;)Ljava/lang/Object;
  1: #94 REF_invokeStatic scala/runtime/LambdaDeserialize.bootstrap:(Ljava/lang/invoke/MethodHandles$Lookup;Ljava/lang/String;Ljava/lang/invoke/MethodType;[Ljava/lang/invoke/MethodHandle;)Ljava/lang/invoke/CallSite;
    Method arguments:
      #71 REF_invokeStatic shapeless/PolyDefns$Compose$$anon$3.$anonfun$value$2:(Lshapeless/PolyDefns$Compose$$anon$3;Lshapeless/$colon$colon;)Ljava/lang/Object;
  ScalaInlineInfo: length = 0x13 (unknown attribute)
   01 01 00 03 00 21 00 22 01 00 3F 00 40 01 00 15
   00 1B 01
  Scala: length = 0x0 (unknown attribute)

