Classfile /Users/mw/Projects/slang-braindump/.jar/jar11/assemble/slang-braindump/assemble/content/shapeless/Poly20.class
  Last modified May 29, 2022; size 4504 bytes
  SHA-256 checksum e287c8721c9b852cfb1897b4b332b3cafcea1f39ee55079d5bc9e62f8e799132
  Compiled from "polyntraits.scala"
public interface shapeless.Poly20 extends shapeless.Poly
  minor version: 0
  major version: 52
  flags: (0x0601) ACC_PUBLIC, ACC_INTERFACE, ACC_ABSTRACT
  this_class: #2                          // shapeless/Poly20
  super_class: #4                         // java/lang/Object
  interfaces: 1, fields: 0, methods: 6, attributes: 5
Constant pool:
   #1 = Utf8               shapeless/Poly20
   #2 = Class              #1             // shapeless/Poly20
   #3 = Utf8               java/lang/Object
   #4 = Class              #3             // java/lang/Object
   #5 = Utf8               shapeless/Poly
   #6 = Class              #5             // shapeless/Poly
   #7 = Utf8               polyntraits.scala
   #8 = Utf8               Lscala/reflect/ScalaSignature;
   #9 = Utf8               bytes
  #10 = Utf8               \u0006\u0005\t-gaB\t\u0013!\u0003\r\t!\u0006\u0005\u0006A\u0001!\t!I\u0003\u0005K\u0001\u0001aeB\u0004\u0002\"\u0001A\t!a\t\u0007\r\u0015\u0002\u0001\u0012AA\u0013\u0011\u001d\t9\u0003\u0002C\u0001\u0003S)a!a\u000b\u0005\u0001\u00055bABA]\u0001\u0001\tY\fC\u0004\u0002(\u001d!\t!a0\t\u000f\tMq\u0001\"\u0001\u0003\u0016!9!\u0011\u0007\u0001\u0005\u0002\tMra\u0002BE%!\u0005!1\u0012\u0004\u0007#IA\tA!$\t\u000f\u0005\u001dB\u0002\"\u0001\u0003.\"I!q\u0016\u0007C\u0002\u0013\u0005!\u0011\u0017\u0005\t\u0005sc\u0001\u0015!\u0003\u00034\"I!1\u0018\u0007\u0002\u0002\u0013%!Q\u0018\u0002\u0007!>d\u0017P\r\u0019\u000b\u0003M\t\u0011b\u001d5ba\u0016dWm]:\u0004\u0001M\u0019\u0001A\u0006\u000f\u0011\u0005]QR\"\u0001\r\u000b\u0003e\tQa]2bY\u0006L!a\u0007\r\u0003\r\u0005s\u0017PU3g!\tib$D\u0001\u0013\u0013\ty\"C\u0001\u0003Q_2L\u0018A\u0002\u0013j]&$H\u0005F\u0001#!\t92%\u0003\u0002%1\t!QK\\5u\u0005\u0011\u0019\u0015m]3\u00161\u001dB4iR&P\'^[vlY4l_N<8p`A\u0004\u0003\u001f\t9\u0002\u0005\u0003)_I\u001adBA\u0015-\u001d\ti\"&\u0003\u0002,%\u00059\u0001/Y2lC\u001e,\u0017BA\u0017/\u0003\u0011\u0001x\u000e\\=\u000b\u0005-\u0012\u0012BA\u00131\u0015\t\t$#A\u0005Q_2LH)\u001a4og6\t\u0001\u0001\u0005\u0003\u001eiY\n\u0015BA\u001b\u0013\u00051!3m\u001c7p]\u0012\u001aw\u000e\\8o!\t9\u0004\b\u0004\u0001\u0005\u000be\u0012!\u0019\u0001\u001e\u0003\u0003\u0005\u000b\"a\u000f \u0011\u0005]a\u0014BA\u001f\u0019\u0005\u001dqu\u000e\u001e5j]\u001e\u0004\"aF \n\u0005\u0001C\"aA!osB!Q\u0004\u000e\"F!\t94\tB\u0003E\u0005\t\u0007!HA\u0001C!\u0011iBGR%\u0011\u0005]:E!\u0002%\u0003\u0005\u0004Q$!A\"\u0011\tu!$*\u0014\t\u0003o-#Q\u0001\u0014\u0002C\u0002i\u0012\u0011\u0001\u0012\t\u0005;Qr\u0015\u000b\u0005\u00028\u001f\u0012)\u0001K\u0001b\u0001u\t\tQ\t\u0005\u0003\u001eiI+\u0006CA\u001cT\t\u0015!&A1\u0001;\u0005\u00051\u0005\u0003B\u000f5-f\u0003\"aN,\u0005\u000ba\u0013!\u0019\u0001\u001e\u0003\u0003\u001d\u0003B!\b\u001b[;B\u0011qg\u0017\u0003\u00069\n\u0011\rA\u000f\u0002\u0002\u0011B!Q\u0004\u000e0b!\t9t\fB\u0003a\u0005\t\u0007!HA\u0001J!\u0011iBGY3\u0011\u0005]\u001aG!\u00023\u0003\u0005\u0004Q$!\u0001&\u0011\tu!d-\u001b\t\u0003o\u001d$Q\u0001\u001b\u0002C\u0002i\u0012\u0011a\u0013\t\u0005;QRW\u000e\u0005\u00028W\u0012)AN\u0001b\u0001u\t\tA\n\u0005\u0003\u001ei9\f\bCA\u001cp\t\u0015\u0001(A1\u0001;\u0005\u0005i\u0005\u0003B\u000f5eV\u0004\"aN:\u0005\u000bQ\u0014!\u0019\u0001\u001e\u0003\u00039\u0003B!\b\u001bwsB\u0011qg\u001e\u0003\u0006q\n\u0011\rA\u000f\u0002\u0002\u001fB!Q\u0004\u000e>~!\t94\u0010B\u0003}\u0005\t\u0007!HA\u0001Q!\u0015iBG`A\u0002!\t9t\u0010\u0002\u0004\u0002\u0002\t\u0011\rA\u000f\u0002\u0002#B1Q\u0004NA\u0003\u0003\u0017\u00012aNA\u0004\t\u0019\tIA\u0001b\u0001u\t\t!\u000b\u0005\u0004\u001ei\u00055\u00111\u0003\t\u0004o\u0005=AABA\t\u0005\t\u0007!HA\u0001T!\u0019iB\'!\u0006\u0002\u001cA\u0019q\'a\u0006\u0005\r\u0005e!A1\u0001;\u0005\u0005!\u0006cA\u000f\u0002\u001e%\u0019\u0011q\u0004\n\u0003\t!s\u0015\u000e\\\u0001\u0005\u0007\u0006\u001cX\r\u0005\u00023\tM\u0011AAF\u0001\u0007y%t\u0017\u000e\u001e \u0015\u0005\u0005\r\"aA!vqVa\u0013qFA\u001e\u0003\u0003\n9%!\u0014\u0002T\u0005e\u0013qLA3\u0003W\n\t(a\u001e\u0002~\u0005\r\u0015\u0011RAH\u0003+\u000bY*!)\u0002(\u00065\u0016Q\u0017\n\u0005\u0003c\t)D\u0002\u0004\u00024\u0011\u0001\u0011q\u0006\u0002\ryI,g-\u001b8f[\u0016tGO\u0010\t\u0006Q=\u0012\u0014q\u0007\t\u0007;Q\nI$!\u0010\u0011\u0007]\nY\u0004B\u0003:\r\t\u0007!\b\u0005\u0004\u001ei\u0005}\u00121\t\t\u0004o\u0005\u0005C!\u0002#\u0007\u0005\u0004Q\u0004CB\u000f5\u0003\u000b\nI\u0005E\u00028\u0003\u000f\"Q\u0001\u0013\u0004C\u0002i\u0002b!\b\u001b\u0002L\u0005=\u0003cA\u001c\u0002N\u0011)AJ\u0002b\u0001uA1Q\u0004NA)\u0003+\u00022aNA*\t\u0015\u0001fA1\u0001;!\u0019iB\'a\u0016\u0002\\A\u0019q\'!\u0017\u0005\u000bQ3!\u0019\u0001\u001e\u0011\ru!\u0014QLA1!\r9\u0014q\f\u0003\u00061\u001a\u0011\rA\u000f\t\u0007;Q\n\u0019\'a\u001a\u0011\u0007]\n)\u0007B\u0003]\r\t\u0007!\b\u0005\u0004\u001ei\u0005%\u0014Q\u000e\t\u0004o\u0005-D!\u00021\u0007\u0005\u0004Q\u0004CB\u000f5\u0003_\n\u0019\bE\u00028\u0003c\"Q\u0001\u001a\u0004C\u0002i\u0002b!\b\u001b\u0002v\u0005e\u0004cA\u001c\u0002x\u0011)\u0001N\u0002b\u0001uA1Q\u0004NA>\u0003\u007f\u00022aNA?\t\u0015agA1\u0001;!\u0019iB\'!!\u0002\u0006B\u0019q\'a!\u0005\u000bA4!\u0019\u0001\u001e\u0011\ru!\u0014qQAF!\r9\u0014\u0011\u0012\u0003\u0006i\u001a\u0011\rA\u000f\t\u0007;Q\ni)!%\u0011\u0007]\ny\tB\u0003y\r\t\u0007!\b\u0005\u0004\u001ei\u0005M\u0015q\u0013\t\u0004o\u0005UE!\u0002?\u0007\u0005\u0004Q\u0004CB\u000f5\u00033\u000bi\nE\u00028\u00037#a!!\u0001\u0007\u0005\u0004Q\u0004CB\u000f5\u0003?\u000b\u0019\u000bE\u00028\u0003C#a!!\u0003\u0007\u0005\u0004Q\u0004CB\u000f5\u0003K\u000bI\u000bE\u00028\u0003O#a!!\u0005\u0007\u0005\u0004Q\u0004CB\u000f5\u0003W\u000bY\u0002E\u00028\u0003[#a!!\u0007\u0007\u0005\u0004QTaBAY\u0003c\u0001\u00131\u0017\u0002\u0007%\u0016\u001cX\u000f\u001c;\u0011\u0007]\n)\f\u0002\u0004\u00028\u001a\u0011\rA\u000f\u0002\b%\u0016\u001cX\u000f\u001c;1\u0005-\u0019\u0015m]3Ck&dG-\u001a:\u0016U\u0005u\u0016QYAe\u0003\u001b\f\t.!6\u0002Z\u0006u\u0017\u0011]As\u0003S\fi/!=\u0002v\u0006e\u0018Q B\u0001\u0005\u000b\u0011IA!\u0004\u0003\u0012M\u0011qA\u0006\u000b\u0003\u0003\u0003\u0004\"FM\u0004\u0002D\u0006\u001d\u00171ZAh\u0003\'\f9.a7\u0002`\u0006\r\u0018q]Av\u0003_\f\u00190a>\u0002|\u0006}(1\u0001B\u0004\u0005\u0017\u0011y\u0001E\u00028\u0003\u000b$Q!O\u0004C\u0002i\u00022aNAe\t\u0015!uA1\u0001;!\r9\u0014Q\u001a\u0003\u0006\u0011\u001e\u0011\rA\u000f\t\u0004o\u0005EG!\u0002\'\b\u0005\u0004Q\u0004cA\u001c\u0002V\u0012)\u0001k\u0002b\u0001uA\u0019q\'!7\u0005\u000bQ;!\u0019\u0001\u001e\u0011\u0007]\ni\u000eB\u0003Y\u000f\t\u0007!\bE\u00028\u0003C$Q\u0001X\u0004C\u0002i\u00022aNAs\t\u0015\u0001wA1\u0001;!\r9\u0014\u0011\u001e\u0003\u0006I\u001e\u0011\rA\u000f\t\u0004o\u00055H!\u00025\b\u0005\u0004Q\u0004cA\u001c\u0002r\u0012)An\u0002b\u0001uA\u0019q\'!>\u0005\u000bA<!\u0019\u0001\u001e\u0011\u0007]\nI\u0010B\u0003u\u000f\t\u0007!\bE\u00028\u0003{$Q\u0001_\u0004C\u0002i\u00022a\u000eB\u0001\t\u0015axA1\u0001;!\r9$Q\u0001\u0003\u0007\u0003\u00039!\u0019\u0001\u001e\u0011\u0007]\u0012I\u0001\u0002\u0004\u0002\n\u001d\u0011\rA\u000f\t\u0004o\t5AABA\t\u000f\t\u0007!\bE\u00028\u0005#!a!!\u0007\b\u0005\u0004Q\u0014!B1qa2LX\u0003\u0002B\f\u0005G!BA!\u0007\u0003(I!!1\u0004B\u000f\r\u0019\t\u0019$\u0003\u0001\u0003\u001aAQ#GAAb\u0003\u000f\fY-a4\u0002T\u0006]\u00171\\Ap\u0003G\f9/a;\u0002p\u0006M\u0018q_A~\u0003\u007f\u0014\u0019Aa\u0002\u0003\f\t=QaBAY\u00057\u0001!\u0011\u0005\t\u0004o\t\rBA\u0002B\u0013\u0013\t\u0007!HA\u0002SKNDqA!\u000b\n\u0001\u0004\u0011Y#\u0001\u0002g]BisC!\f\u0002D\u0006\u001d\u00171ZAh\u0003\'\f9.a7\u0002`\u0006\r\u0018q]Av\u0003_\f\u00190a>\u0002|\u0006}(1\u0001B\u0004\u0005\u0017\u0011yA!\t\n\u0007\t=\u0002D\u0001\u0006Gk:\u001cG/[8oeA\n!!\u0019;\u0016U\tU\"1\bB \u0005\u0007\u00129Ea\u0013\u0003P\tM#q\u000bB.\u0005?\u0012\u0019Ga\u001a\u0003l\t=$1\u000fB<\u0005w\u0012yHa!\u0003\bV\u0011!q\u0007\t+e\u001d\u0011ID!\u0010\u0003B\t\u0015#\u0011\nB\'\u0005#\u0012)F!\u0017\u0003^\t\u0005$Q\rB5\u0005[\u0012\tH!\u001e\u0003z\tu$\u0011\u0011BC!\r9$1\b\u0003\u0006s)\u0011\rA\u000f\t\u0004o\t}B!\u0002#\u000b\u0005\u0004Q\u0004cA\u001c\u0003D\u0011)\u0001J\u0003b\u0001uA\u0019qGa\u0012\u0005\u000b1S!\u0019\u0001\u001e\u0011\u0007]\u0012Y\u0005B\u0003Q\u0015\t\u0007!\bE\u00028\u0005\u001f\"Q\u0001\u0016\u0006C\u0002i\u00022a\u000eB*\t\u0015A&B1\u0001;!\r9$q\u000b\u0003\u00069*\u0011\rA\u000f\t\u0004o\tmC!\u00021\u000b\u0005\u0004Q\u0004cA\u001c\u0003`\u0011)AM\u0003b\u0001uA\u0019qGa\u0019\u0005\u000b!T!\u0019\u0001\u001e\u0011\u0007]\u00129\u0007B\u0003m\u0015\t\u0007!\bE\u00028\u0005W\"Q\u0001\u001d\u0006C\u0002i\u00022a\u000eB8\t\u0015!(B1\u0001;!\r9$1\u000f\u0003\u0006q*\u0011\rA\u000f\t\u0004o\t]D!\u0002?\u000b\u0005\u0004Q\u0004cA\u001c\u0003|\u00111\u0011\u0011\u0001\u0006C\u0002i\u00022a\u000eB@\t\u0019\tIA\u0003b\u0001uA\u0019qGa!\u0005\r\u0005E!B1\u0001;!\r9$q\u0011\u0003\u0007\u00033Q!\u0019\u0001\u001e\u0002\rA{G.\u001f\u001a1!\tiBb\u0005\u0004\r-\t=%Q\u0014\t\u0007\u0005#\u00139*a\u0007\u000f\u0007u\u0011\u0019*C\u0002\u0003\u0016J\tQ\u0002U8ms:\u0013U/\u001b7eKJ\u001c\u0018\u0002\u0002BM\u00057\u0013Q\u0002U8msJ\u0002$)^5mI\u0016\u0014(b\u0001BK%A!!q\u0014BU\u001b\t\u0011\tK\u0003\u0003\u0003$\n\u0015\u0016AA5p\u0015\t\u00119+\u0001\u0003kCZ\f\u0017\u0002\u0002BV\u0005C\u0013AbU3sS\u0006d\u0017N_1cY\u0016$\"Aa#\u0002\u0013\u0019,hn\u0019;j_:\u001cXC\u0001BZ\u001d\ri\"QW\u0005\u0004\u0005o\u0013\u0012\u0001\u0002%OS2\f!BZ;oGRLwN\\:!\u000319(/\u001b;f%\u0016\u0004H.Y2f)\t\u0011y\f\u0005\u0003\u0003B\n\u001dWB\u0001Bb\u0015\u0011\u0011)M!*\u0002\t1\fgnZ\u0005\u0005\u0005\u0013\u0014\u0019M\u0001\u0004PE*,7\r\u001e
  #11 = Utf8               shapeless/Poly20$Case$
  #12 = Class              #11            // shapeless/Poly20$Case$
  #13 = Utf8               Case$
  #14 = Utf8               shapeless/Poly20$CaseBuilder
  #15 = Class              #14            // shapeless/Poly20$CaseBuilder
  #16 = Utf8               CaseBuilder
  #17 = Utf8               functions
  #18 = Utf8               ()Lshapeless/HNil$;
  #19 = Utf8               shapeless/Poly20$
  #20 = Class              #19            // shapeless/Poly20$
  #21 = Utf8               MODULE$
  #22 = Utf8               Lshapeless/Poly20$;
  #23 = NameAndType        #21:#22        // MODULE$:Lshapeless/Poly20$;
  #24 = Fieldref           #20.#23        // shapeless/Poly20$.MODULE$:Lshapeless/Poly20$;
  #25 = NameAndType        #17:#18        // functions:()Lshapeless/HNil$;
  #26 = Methodref          #20.#25        // shapeless/Poly20$.functions:()Lshapeless/HNil$;
  #27 = Utf8               build
  #28 = Utf8               ()Lshapeless/Poly20;
  #29 = NameAndType        #27:#28        // build:()Lshapeless/Poly20;
  #30 = Methodref          #20.#29        // shapeless/Poly20$.build:()Lshapeless/Poly20;
  #31 = Utf8               Case
  #32 = Utf8               ()Lshapeless/Poly20$Case$;
  #33 = Utf8               at$
  #34 = Utf8               (Lshapeless/Poly20;)Lshapeless/Poly20$CaseBuilder;
  #35 = Utf8               $this
  #36 = Utf8               at
  #37 = Utf8               ()Lshapeless/Poly20$CaseBuilder;
  #38 = NameAndType        #36:#37        // at:()Lshapeless/Poly20$CaseBuilder;
  #39 = InterfaceMethodref #2.#38         // shapeless/Poly20.at:()Lshapeless/Poly20$CaseBuilder;
  #40 = Utf8               Lshapeless/Poly20;
  #41 = Utf8               <A:Ljava/lang/Object;B:Ljava/lang/Object;C:Ljava/lang/Object;D:Ljava/lang/Object;E:Ljava/lang/Object;F:Ljava/lang/Object;G:Ljava/lang/Object;H:Ljava/lang/Object;I:Ljava/lang/Object;J:Ljava/lang/Object;K:Ljava/lang/Object;L:Ljava/lang/Object;M:Ljava/lang/Object;N:Ljava/lang/Object;O:Ljava/lang/Object;P:Ljava/lang/Object;Q:Ljava/lang/Object;R:Ljava/lang/Object;S:Ljava/lang/Object;T:Ljava/lang/Object;>()Lshapeless/Poly20$CaseBuilder<TA;TB;TC;TD;TE;TF;TG;TH;TI;TJ;TK;TL;TM;TN;TO;TP;TQ;TR;TS;TT;>;
  #42 = Utf8               <init>
  #43 = Utf8               (Lshapeless/Poly20;)V
  #44 = NameAndType        #42:#43        // "<init>":(Lshapeless/Poly20;)V
  #45 = Methodref          #15.#44        // shapeless/Poly20$CaseBuilder."<init>":(Lshapeless/Poly20;)V
  #46 = Utf8               this
  #47 = Utf8               $init$
  #48 = Utf8               Code
  #49 = Utf8               LineNumberTable
  #50 = Utf8               LocalVariableTable
  #51 = Utf8               MethodParameters
  #52 = Utf8               Signature
  #53 = Utf8               InnerClasses
  #54 = Utf8               SourceFile
  #55 = Utf8               RuntimeVisibleAnnotations
  #56 = Utf8               ScalaInlineInfo
  #57 = Utf8               ScalaSig
{
  public static shapeless.HNil$ functions();
    descriptor: ()Lshapeless/HNil$;
    flags: (0x0009) ACC_PUBLIC, ACC_STATIC
    Code:
      stack=1, locals=0, args_size=0
         0: getstatic     #24                 // Field shapeless/Poly20$.MODULE$:Lshapeless/Poly20$;
         3: invokevirtual #26                 // Method shapeless/Poly20$.functions:()Lshapeless/HNil$;
         6: areturn

  public static shapeless.Poly20 build();
    descriptor: ()Lshapeless/Poly20;
    flags: (0x0009) ACC_PUBLIC, ACC_STATIC
    Code:
      stack=1, locals=0, args_size=0
         0: getstatic     #24                 // Field shapeless/Poly20$.MODULE$:Lshapeless/Poly20$;
         3: invokevirtual #30                 // Method shapeless/Poly20$.build:()Lshapeless/Poly20;
         6: areturn

  public abstract shapeless.Poly20$Case$ Case();
    descriptor: ()Lshapeless/Poly20$Case$;
    flags: (0x0401) ACC_PUBLIC, ACC_ABSTRACT

  public static shapeless.Poly20$CaseBuilder at$(shapeless.Poly20);
    descriptor: (Lshapeless/Poly20;)Lshapeless/Poly20$CaseBuilder;
    flags: (0x1009) ACC_PUBLIC, ACC_STATIC, ACC_SYNTHETIC
    Code:
      stack=1, locals=1, args_size=1
         0: aload_0
         1: invokespecial #39                 // InterfaceMethod at:()Lshapeless/Poly20$CaseBuilder;
         4: areturn
      LineNumberTable:
        line 534: 0
      LocalVariableTable:
        Start  Length  Slot  Name   Signature
            0       5     0 $this   Lshapeless/Poly20;
    MethodParameters:
      Name                           Flags
      $this                          final synthetic

  public default <A extends java.lang.Object, B extends java.lang.Object, C extends java.lang.Object, D extends java.lang.Object, E extends java.lang.Object, F extends java.lang.Object, G extends java.lang.Object, H extends java.lang.Object, I extends java.lang.Object, J extends java.lang.Object, K extends java.lang.Object, L extends java.lang.Object, M extends java.lang.Object, N extends java.lang.Object, O extends java.lang.Object, P extends java.lang.Object, Q extends java.lang.Object, R extends java.lang.Object, S extends java.lang.Object, T extends java.lang.Object> shapeless.Poly20$CaseBuilder<A, B, C, D, E, F, G, H, I, J, K, L, M, N, O, P, Q, R, S, T> at();
    descriptor: ()Lshapeless/Poly20$CaseBuilder;
    flags: (0x0001) ACC_PUBLIC
    Code:
      stack=3, locals=1, args_size=1
         0: new           #15                 // class shapeless/Poly20$CaseBuilder
         3: dup
         4: aload_0
         5: invokespecial #45                 // Method shapeless/Poly20$CaseBuilder."<init>":(Lshapeless/Poly20;)V
         8: areturn
      LineNumberTable:
        line 535: 0
      LocalVariableTable:
        Start  Length  Slot  Name   Signature
            0       9     0  this   Lshapeless/Poly20;
    Signature: #41                          // <A:Ljava/lang/Object;B:Ljava/lang/Object;C:Ljava/lang/Object;D:Ljava/lang/Object;E:Ljava/lang/Object;F:Ljava/lang/Object;G:Ljava/lang/Object;H:Ljava/lang/Object;I:Ljava/lang/Object;J:Ljava/lang/Object;K:Ljava/lang/Object;L:Ljava/lang/Object;M:Ljava/lang/Object;N:Ljava/lang/Object;O:Ljava/lang/Object;P:Ljava/lang/Object;Q:Ljava/lang/Object;R:Ljava/lang/Object;S:Ljava/lang/Object;T:Ljava/lang/Object;>()Lshapeless/Poly20$CaseBuilder<TA;TB;TC;TD;TE;TF;TG;TH;TI;TJ;TK;TL;TM;TN;TO;TP;TQ;TR;TS;TT;>;

  public static void $init$(shapeless.Poly20);
    descriptor: (Lshapeless/Poly20;)V
    flags: (0x0009) ACC_PUBLIC, ACC_STATIC
    Code:
      stack=0, locals=1, args_size=1
         0: return
      LineNumberTable:
        line 516: 0
      LocalVariableTable:
        Start  Length  Slot  Name   Signature
            0       1     0 $this   Lshapeless/Poly20;
    MethodParameters:
      Name                           Flags
      $this                          final synthetic
}
InnerClasses:
  public #13= #12 of #2;                  // Case$=class shapeless/Poly20$Case$ of class shapeless/Poly20
  public #16= #15 of #2;                  // CaseBuilder=class shapeless/Poly20$CaseBuilder of class shapeless/Poly20
SourceFile: "polyntraits.scala"
RuntimeVisibleAnnotations:
  0: #8(#9=s#10)
    scala.reflect.ScalaSignature(
      bytes="\u0006\u0005\t-gaB\t\u0013!\u0003\r\t!\u0006\u0005\u0006A\u0001!\t!I\u0003\u0005K\u0001\u0001aeB\u0004\u0002\"\u0001A\t!a\t\u0007\r\u0015\u0002\u0001\u0012AA\u0013\u0011\u001d\t9\u0003\u0002C\u0001\u0003S)a!a\u000b\u0005\u0001\u00055bABA]\u0001\u0001\tY\fC\u0004\u0002(\u001d!\t!a0\t\u000f\tMq\u0001\"\u0001\u0003\u0016!9!\u0011\u0007\u0001\u0005\u0002\tMra\u0002BE%!\u0005!1\u0012\u0004\u0007#IA\tA!$\t\u000f\u0005\u001dB\u0002\"\u0001\u0003.\"I!q\u0016\u0007C\u0002\u0013\u0005!\u0011\u0017\u0005\t\u0005sc\u0001\u0015!\u0003\u00034\"I!1\u0018\u0007\u0002\u0002\u0013%!Q\u0018\u0002\u0007!>d\u0017P\r\u0019\u000b\u0003M\t\u0011b\u001d5ba\u0016dWm]:\u0004\u0001M\u0019\u0001A\u0006\u000f\u0011\u0005]QR\"\u0001\r\u000b\u0003e\tQa]2bY\u0006L!a\u0007\r\u0003\r\u0005s\u0017PU3g!\tib$D\u0001\u0013\u0013\ty\"C\u0001\u0003Q_2L\u0018A\u0002\u0013j]&$H\u0005F\u0001#!\t92%\u0003\u0002%1\t!QK\\5u\u0005\u0011\u0019\u0015m]3\u00161\u001dB4iR&P\'^[vlY4l_N<8p`A\u0004\u0003\u001f\t9\u0002\u0005\u0003)_I\u001adBA\u0015-\u001d\ti\"&\u0003\u0002,%\u00059\u0001/Y2lC\u001e,\u0017BA\u0017/\u0003\u0011\u0001x\u000e\\=\u000b\u0005-\u0012\u0012BA\u00131\u0015\t\t$#A\u0005Q_2LH)\u001a4og6\t\u0001\u0001\u0005\u0003\u001eiY\n\u0015BA\u001b\u0013\u00051!3m\u001c7p]\u0012\u001aw\u000e\\8o!\t9\u0004\b\u0004\u0001\u0005\u000be\u0012!\u0019\u0001\u001e\u0003\u0003\u0005\u000b\"a\u000f \u0011\u0005]a\u0014BA\u001f\u0019\u0005\u001dqu\u000e\u001e5j]\u001e\u0004\"aF \n\u0005\u0001C\"aA!osB!Q\u0004\u000e\"F!\t94\tB\u0003E\u0005\t\u0007!HA\u0001C!\u0011iBGR%\u0011\u0005]:E!\u0002%\u0003\u0005\u0004Q$!A\"\u0011\tu!$*\u0014\t\u0003o-#Q\u0001\u0014\u0002C\u0002i\u0012\u0011\u0001\u0012\t\u0005;Qr\u0015\u000b\u0005\u00028\u001f\u0012)\u0001K\u0001b\u0001u\t\tQ\t\u0005\u0003\u001eiI+\u0006CA\u001cT\t\u0015!&A1\u0001;\u0005\u00051\u0005\u0003B\u000f5-f\u0003\"aN,\u0005\u000ba\u0013!\u0019\u0001\u001e\u0003\u0003\u001d\u0003B!\b\u001b[;B\u0011qg\u0017\u0003\u00069\n\u0011\rA\u000f\u0002\u0002\u0011B!Q\u0004\u000e0b!\t9t\fB\u0003a\u0005\t\u0007!HA\u0001J!\u0011iBGY3\u0011\u0005]\u001aG!\u00023\u0003\u0005\u0004Q$!\u0001&\u0011\tu!d-\u001b\t\u0003o\u001d$Q\u0001\u001b\u0002C\u0002i\u0012\u0011a\u0013\t\u0005;QRW\u000e\u0005\u00028W\u0012)AN\u0001b\u0001u\t\tA\n\u0005\u0003\u001ei9\f\bCA\u001cp\t\u0015\u0001(A1\u0001;\u0005\u0005i\u0005\u0003B\u000f5eV\u0004\"aN:\u0005\u000bQ\u0014!\u0019\u0001\u001e\u0003\u00039\u0003B!\b\u001bwsB\u0011qg\u001e\u0003\u0006q\n\u0011\rA\u000f\u0002\u0002\u001fB!Q\u0004\u000e>~!\t94\u0010B\u0003}\u0005\t\u0007!HA\u0001Q!\u0015iBG`A\u0002!\t9t\u0010\u0002\u0004\u0002\u0002\t\u0011\rA\u000f\u0002\u0002#B1Q\u0004NA\u0003\u0003\u0017\u00012aNA\u0004\t\u0019\tIA\u0001b\u0001u\t\t!\u000b\u0005\u0004\u001ei\u00055\u00111\u0003\t\u0004o\u0005=AABA\t\u0005\t\u0007!HA\u0001T!\u0019iB\'!\u0006\u0002\u001cA\u0019q\'a\u0006\u0005\r\u0005e!A1\u0001;\u0005\u0005!\u0006cA\u000f\u0002\u001e%\u0019\u0011q\u0004\n\u0003\t!s\u0015\u000e\\\u0001\u0005\u0007\u0006\u001cX\r\u0005\u00023\tM\u0011AAF\u0001\u0007y%t\u0017\u000e\u001e \u0015\u0005\u0005\r\"aA!vqVa\u0013qFA\u001e\u0003\u0003\n9%!\u0014\u0002T\u0005e\u0013qLA3\u0003W\n\t(a\u001e\u0002~\u0005\r\u0015\u0011RAH\u0003+\u000bY*!)\u0002(\u00065\u0016Q\u0017\n\u0005\u0003c\t)D\u0002\u0004\u00024\u0011\u0001\u0011q\u0006\u0002\ryI,g-\u001b8f[\u0016tGO\u0010\t\u0006Q=\u0012\u0014q\u0007\t\u0007;Q\nI$!\u0010\u0011\u0007]\nY\u0004B\u0003:\r\t\u0007!\b\u0005\u0004\u001ei\u0005}\u00121\t\t\u0004o\u0005\u0005C!\u0002#\u0007\u0005\u0004Q\u0004CB\u000f5\u0003\u000b\nI\u0005E\u00028\u0003\u000f\"Q\u0001\u0013\u0004C\u0002i\u0002b!\b\u001b\u0002L\u0005=\u0003cA\u001c\u0002N\u0011)AJ\u0002b\u0001uA1Q\u0004NA)\u0003+\u00022aNA*\t\u0015\u0001fA1\u0001;!\u0019iB\'a\u0016\u0002\\A\u0019q\'!\u0017\u0005\u000bQ3!\u0019\u0001\u001e\u0011\ru!\u0014QLA1!\r9\u0014q\f\u0003\u00061\u001a\u0011\rA\u000f\t\u0007;Q\n\u0019\'a\u001a\u0011\u0007]\n)\u0007B\u0003]\r\t\u0007!\b\u0005\u0004\u001ei\u0005%\u0014Q\u000e\t\u0004o\u0005-D!\u00021\u0007\u0005\u0004Q\u0004CB\u000f5\u0003_\n\u0019\bE\u00028\u0003c\"Q\u0001\u001a\u0004C\u0002i\u0002b!\b\u001b\u0002v\u0005e\u0004cA\u001c\u0002x\u0011)\u0001N\u0002b\u0001uA1Q\u0004NA>\u0003\u007f\u00022aNA?\t\u0015agA1\u0001;!\u0019iB\'!!\u0002\u0006B\u0019q\'a!\u0005\u000bA4!\u0019\u0001\u001e\u0011\ru!\u0014qQAF!\r9\u0014\u0011\u0012\u0003\u0006i\u001a\u0011\rA\u000f\t\u0007;Q\ni)!%\u0011\u0007]\ny\tB\u0003y\r\t\u0007!\b\u0005\u0004\u001ei\u0005M\u0015q\u0013\t\u0004o\u0005UE!\u0002?\u0007\u0005\u0004Q\u0004CB\u000f5\u00033\u000bi\nE\u00028\u00037#a!!\u0001\u0007\u0005\u0004Q\u0004CB\u000f5\u0003?\u000b\u0019\u000bE\u00028\u0003C#a!!\u0003\u0007\u0005\u0004Q\u0004CB\u000f5\u0003K\u000bI\u000bE\u00028\u0003O#a!!\u0005\u0007\u0005\u0004Q\u0004CB\u000f5\u0003W\u000bY\u0002E\u00028\u0003[#a!!\u0007\u0007\u0005\u0004QTaBAY\u0003c\u0001\u00131\u0017\u0002\u0007%\u0016\u001cX\u000f\u001c;\u0011\u0007]\n)\f\u0002\u0004\u00028\u001a\u0011\rA\u000f\u0002\b%\u0016\u001cX\u000f\u001c;1\u0005-\u0019\u0015m]3Ck&dG-\u001a:\u0016U\u0005u\u0016QYAe\u0003\u001b\f\t.!6\u0002Z\u0006u\u0017\u0011]As\u0003S\fi/!=\u0002v\u0006e\u0018Q B\u0001\u0005\u000b\u0011IA!\u0004\u0003\u0012M\u0011qA\u0006\u000b\u0003\u0003\u0003\u0004\"FM\u0004\u0002D\u0006\u001d\u00171ZAh\u0003\'\f9.a7\u0002`\u0006\r\u0018q]Av\u0003_\f\u00190a>\u0002|\u0006}(1\u0001B\u0004\u0005\u0017\u0011y\u0001E\u00028\u0003\u000b$Q!O\u0004C\u0002i\u00022aNAe\t\u0015!uA1\u0001;!\r9\u0014Q\u001a\u0003\u0006\u0011\u001e\u0011\rA\u000f\t\u0004o\u0005EG!\u0002\'\b\u0005\u0004Q\u0004cA\u001c\u0002V\u0012)\u0001k\u0002b\u0001uA\u0019q\'!7\u0005\u000bQ;!\u0019\u0001\u001e\u0011\u0007]\ni\u000eB\u0003Y\u000f\t\u0007!\bE\u00028\u0003C$Q\u0001X\u0004C\u0002i\u00022aNAs\t\u0015\u0001wA1\u0001;!\r9\u0014\u0011\u001e\u0003\u0006I\u001e\u0011\rA\u000f\t\u0004o\u00055H!\u00025\b\u0005\u0004Q\u0004cA\u001c\u0002r\u0012)An\u0002b\u0001uA\u0019q\'!>\u0005\u000bA<!\u0019\u0001\u001e\u0011\u0007]\nI\u0010B\u0003u\u000f\t\u0007!\bE\u00028\u0003{$Q\u0001_\u0004C\u0002i\u00022a\u000eB\u0001\t\u0015axA1\u0001;!\r9$Q\u0001\u0003\u0007\u0003\u00039!\u0019\u0001\u001e\u0011\u0007]\u0012I\u0001\u0002\u0004\u0002\n\u001d\u0011\rA\u000f\t\u0004o\t5AABA\t\u000f\t\u0007!\bE\u00028\u0005#!a!!\u0007\b\u0005\u0004Q\u0014!B1qa2LX\u0003\u0002B\f\u0005G!BA!\u0007\u0003(I!!1\u0004B\u000f\r\u0019\t\u0019$\u0003\u0001\u0003\u001aAQ#GAAb\u0003\u000f\fY-a4\u0002T\u0006]\u00171\\Ap\u0003G\f9/a;\u0002p\u0006M\u0018q_A~\u0003\u007f\u0014\u0019Aa\u0002\u0003\f\t=QaBAY\u00057\u0001!\u0011\u0005\t\u0004o\t\rBA\u0002B\u0013\u0013\t\u0007!HA\u0002SKNDqA!\u000b\n\u0001\u0004\u0011Y#\u0001\u0002g]BisC!\f\u0002D\u0006\u001d\u00171ZAh\u0003\'\f9.a7\u0002`\u0006\r\u0018q]Av\u0003_\f\u00190a>\u0002|\u0006}(1\u0001B\u0004\u0005\u0017\u0011yA!\t\n\u0007\t=\u0002D\u0001\u0006Gk:\u001cG/[8oeA\n!!\u0019;\u0016U\tU\"1\bB \u0005\u0007\u00129Ea\u0013\u0003P\tM#q\u000bB.\u0005?\u0012\u0019Ga\u001a\u0003l\t=$1\u000fB<\u0005w\u0012yHa!\u0003\bV\u0011!q\u0007\t+e\u001d\u0011ID!\u0010\u0003B\t\u0015#\u0011\nB\'\u0005#\u0012)F!\u0017\u0003^\t\u0005$Q\rB5\u0005[\u0012\tH!\u001e\u0003z\tu$\u0011\u0011BC!\r9$1\b\u0003\u0006s)\u0011\rA\u000f\t\u0004o\t}B!\u0002#\u000b\u0005\u0004Q\u0004cA\u001c\u0003D\u0011)\u0001J\u0003b\u0001uA\u0019qGa\u0012\u0005\u000b1S!\u0019\u0001\u001e\u0011\u0007]\u0012Y\u0005B\u0003Q\u0015\t\u0007!\bE\u00028\u0005\u001f\"Q\u0001\u0016\u0006C\u0002i\u00022a\u000eB*\t\u0015A&B1\u0001;!\r9$q\u000b\u0003\u00069*\u0011\rA\u000f\t\u0004o\tmC!\u00021\u000b\u0005\u0004Q\u0004cA\u001c\u0003`\u0011)AM\u0003b\u0001uA\u0019qGa\u0019\u0005\u000b!T!\u0019\u0001\u001e\u0011\u0007]\u00129\u0007B\u0003m\u0015\t\u0007!\bE\u00028\u0005W\"Q\u0001\u001d\u0006C\u0002i\u00022a\u000eB8\t\u0015!(B1\u0001;!\r9$1\u000f\u0003\u0006q*\u0011\rA\u000f\t\u0004o\t]D!\u0002?\u000b\u0005\u0004Q\u0004cA\u001c\u0003|\u00111\u0011\u0011\u0001\u0006C\u0002i\u00022a\u000eB@\t\u0019\tIA\u0003b\u0001uA\u0019qGa!\u0005\r\u0005E!B1\u0001;!\r9$q\u0011\u0003\u0007\u00033Q!\u0019\u0001\u001e\u0002\rA{G.\u001f\u001a1!\tiBb\u0005\u0004\r-\t=%Q\u0014\t\u0007\u0005#\u00139*a\u0007\u000f\u0007u\u0011\u0019*C\u0002\u0003\u0016J\tQ\u0002U8ms:\u0013U/\u001b7eKJ\u001c\u0018\u0002\u0002BM\u00057\u0013Q\u0002U8msJ\u0002$)^5mI\u0016\u0014(b\u0001BK%A!!q\u0014BU\u001b\t\u0011\tK\u0003\u0003\u0003$\n\u0015\u0016AA5p\u0015\t\u00119+\u0001\u0003kCZ\f\u0017\u0002\u0002BV\u0005C\u0013AbU3sS\u0006d\u0017N_1cY\u0016$\"Aa#\u0002\u0013\u0019,hn\u0019;j_:\u001cXC\u0001BZ\u001d\ri\"QW\u0005\u0004\u0005o\u0013\u0012\u0001\u0002%OS2\f!BZ;oGRLwN\\:!\u000319(/\u001b;f%\u0016\u0004H.Y2f)\t\u0011y\f\u0005\u0003\u0003B\n\u001dWB\u0001Bb\u0015\u0011\u0011)M!*\u0002\t1\fgnZ\u0005\u0005\u0005\u0013\u0014\u0019M\u0001\u0004PE*,7\r\u001e"
    )
  ScalaInlineInfo: length = 0x18 (unknown attribute)
   01 00 00 04 00 2F 00 2B 01 00 1F 00 20 00 00 21
   00 22 01 00 24 00 25 00
  ScalaSig: length = 0x3 (unknown attribute)
   05 02 00
