Classfile /Users/mw/Projects/slang-braindump/.jar/jar11/assemble/slang-braindump/assemble/content/shapeless/PolyDefns$Case$.class
  Last modified May 29, 2022; size 22500 bytes
  SHA-256 checksum e9715358045519ce70578c6a1c093f1d2c75c53bed4e8fada1fcaa1523ca10b0
  Compiled from "poly.scala"
public class shapeless.PolyDefns$Case$ implements shapeless.CaseInst,java.io.Serializable
  minor version: 0
  major version: 52
  flags: (0x0021) ACC_PUBLIC, ACC_SUPER
  this_class: #2                          // shapeless/PolyDefns$Case$
  super_class: #4                         // java/lang/Object
  interfaces: 2, fields: 1, methods: 26, attributes: 4
Constant pool:
    #1 = Utf8               shapeless/PolyDefns$Case$
    #2 = Class              #1            // shapeless/PolyDefns$Case$
    #3 = Utf8               java/lang/Object
    #4 = Class              #3            // java/lang/Object
    #5 = Utf8               shapeless/CaseInst
    #6 = Class              #5            // shapeless/CaseInst
    #7 = Utf8               java/io/Serializable
    #8 = Class              #7            // java/io/Serializable
    #9 = Utf8               poly.scala
   #10 = Utf8               shapeless/PolyDefns$Case
   #11 = Class              #10           // shapeless/PolyDefns$Case
   #12 = Utf8               shapeless/PolyDefns
   #13 = Class              #12           // shapeless/PolyDefns
   #14 = Utf8               Case
   #15 = Utf8               Case$
   #16 = Utf8               shapeless/PolyDefns$Case$$anon$1
   #17 = Class              #16           // shapeless/PolyDefns$Case$$anon$1
   #18 = Utf8               MODULE$
   #19 = Utf8               Lshapeless/PolyDefns$Case$;
   #20 = Utf8               <clinit>
   #21 = Utf8               ()V
   #22 = Utf8               <init>
   #23 = NameAndType        #22:#21       // "<init>":()V
   #24 = Methodref          #2.#23        // shapeless/PolyDefns$Case$."<init>":()V
   #25 = NameAndType        #18:#19       // MODULE$:Lshapeless/PolyDefns$Case$;
   #26 = Fieldref           #2.#25        // shapeless/PolyDefns$Case$.MODULE$:Lshapeless/PolyDefns$Case$;
   #27 = Utf8               $init$
   #28 = Utf8               (Lshapeless/CaseInst;)V
   #29 = NameAndType        #27:#28       // $init$:(Lshapeless/CaseInst;)V
   #30 = InterfaceMethodref #6.#29        // shapeless/CaseInst.$init$:(Lshapeless/CaseInst;)V
   #31 = Utf8               inst1
   #32 = Utf8               (Lshapeless/PolyDefns$Case;)Lscala/Function1;
   #33 = Utf8               <Fn::Lshapeless/Poly;A:Ljava/lang/Object;Res:Ljava/lang/Object;>(Lshapeless/PolyDefns$Case<TFn;Lshapeless/$colon$colon<TA;Lshapeless/HNil;>;>;)Lscala/Function1<TA;TRes;>;
   #34 = Utf8               cse
   #35 = Utf8               inst1$
   #36 = Utf8               (Lshapeless/CaseInst;Lshapeless/PolyDefns$Case;)Lscala/Function1;
   #37 = NameAndType        #35:#36       // inst1$:(Lshapeless/CaseInst;Lshapeless/PolyDefns$Case;)Lscala/Function1;
   #38 = InterfaceMethodref #6.#37        // shapeless/CaseInst.inst1$:(Lshapeless/CaseInst;Lshapeless/PolyDefns$Case;)Lscala/Function1;
   #39 = Utf8               this
   #40 = Utf8               Lshapeless/PolyDefns$Case;
   #41 = Utf8               inst2
   #42 = Utf8               (Lshapeless/PolyDefns$Case;)Lscala/Function2;
   #43 = Utf8               <Fn::Lshapeless/Poly;A:Ljava/lang/Object;B:Ljava/lang/Object;Res:Ljava/lang/Object;>(Lshapeless/PolyDefns$Case<TFn;Lshapeless/$colon$colon<TA;Lshapeless/$colon$colon<TB;Lshapeless/HNil;>;>;>;)Lscala/Function2<TA;TB;TRes;>;
   #44 = Utf8               inst2$
   #45 = Utf8               (Lshapeless/CaseInst;Lshapeless/PolyDefns$Case;)Lscala/Function2;
   #46 = NameAndType        #44:#45       // inst2$:(Lshapeless/CaseInst;Lshapeless/PolyDefns$Case;)Lscala/Function2;
   #47 = InterfaceMethodref #6.#46        // shapeless/CaseInst.inst2$:(Lshapeless/CaseInst;Lshapeless/PolyDefns$Case;)Lscala/Function2;
   #48 = Utf8               inst3
   #49 = Utf8               (Lshapeless/PolyDefns$Case;)Lscala/Function3;
   #50 = Utf8               <Fn::Lshapeless/Poly;A:Ljava/lang/Object;B:Ljava/lang/Object;C:Ljava/lang/Object;Res:Ljava/lang/Object;>(Lshapeless/PolyDefns$Case<TFn;Lshapeless/$colon$colon<TA;Lshapeless/$colon$colon<TB;Lshapeless/$colon$colon<TC;Lshapeless/HNil;>;>;>;>;)Lscala/Function3<TA;TB;TC;TRes;>;
   #51 = Utf8               inst3$
   #52 = Utf8               (Lshapeless/CaseInst;Lshapeless/PolyDefns$Case;)Lscala/Function3;
   #53 = NameAndType        #51:#52       // inst3$:(Lshapeless/CaseInst;Lshapeless/PolyDefns$Case;)Lscala/Function3;
   #54 = InterfaceMethodref #6.#53        // shapeless/CaseInst.inst3$:(Lshapeless/CaseInst;Lshapeless/PolyDefns$Case;)Lscala/Function3;
   #55 = Utf8               inst4
   #56 = Utf8               (Lshapeless/PolyDefns$Case;)Lscala/Function4;
   #57 = Utf8               <Fn::Lshapeless/Poly;A:Ljava/lang/Object;B:Ljava/lang/Object;C:Ljava/lang/Object;D:Ljava/lang/Object;Res:Ljava/lang/Object;>(Lshapeless/PolyDefns$Case<TFn;Lshapeless/$colon$colon<TA;Lshapeless/$colon$colon<TB;Lshapeless/$colon$colon<TC;Lshapeless/$colon$colon<TD;Lshapeless/HNil;>;>;>;>;>;)Lscala/Function4<TA;TB;TC;TD;TRes;>;
   #58 = Utf8               inst4$
   #59 = Utf8               (Lshapeless/CaseInst;Lshapeless/PolyDefns$Case;)Lscala/Function4;
   #60 = NameAndType        #58:#59       // inst4$:(Lshapeless/CaseInst;Lshapeless/PolyDefns$Case;)Lscala/Function4;
   #61 = InterfaceMethodref #6.#60        // shapeless/CaseInst.inst4$:(Lshapeless/CaseInst;Lshapeless/PolyDefns$Case;)Lscala/Function4;
   #62 = Utf8               inst5
   #63 = Utf8               (Lshapeless/PolyDefns$Case;)Lscala/Function5;
   #64 = Utf8               <Fn::Lshapeless/Poly;A:Ljava/lang/Object;B:Ljava/lang/Object;C:Ljava/lang/Object;D:Ljava/lang/Object;E:Ljava/lang/Object;Res:Ljava/lang/Object;>(Lshapeless/PolyDefns$Case<TFn;Lshapeless/$colon$colon<TA;Lshapeless/$colon$colon<TB;Lshapeless/$colon$colon<TC;Lshapeless/$colon$colon<TD;Lshapeless/$colon$colon<TE;Lshapeless/HNil;>;>;>;>;>;>;)Lscala/Function5<TA;TB;TC;TD;TE;TRes;>;
   #65 = Utf8               inst5$
   #66 = Utf8               (Lshapeless/CaseInst;Lshapeless/PolyDefns$Case;)Lscala/Function5;
   #67 = NameAndType        #65:#66       // inst5$:(Lshapeless/CaseInst;Lshapeless/PolyDefns$Case;)Lscala/Function5;
   #68 = InterfaceMethodref #6.#67        // shapeless/CaseInst.inst5$:(Lshapeless/CaseInst;Lshapeless/PolyDefns$Case;)Lscala/Function5;
   #69 = Utf8               inst6
   #70 = Utf8               (Lshapeless/PolyDefns$Case;)Lscala/Function6;
   #71 = Utf8               <Fn::Lshapeless/Poly;A:Ljava/lang/Object;B:Ljava/lang/Object;C:Ljava/lang/Object;D:Ljava/lang/Object;E:Ljava/lang/Object;F:Ljava/lang/Object;Res:Ljava/lang/Object;>(Lshapeless/PolyDefns$Case<TFn;Lshapeless/$colon$colon<TA;Lshapeless/$colon$colon<TB;Lshapeless/$colon$colon<TC;Lshapeless/$colon$colon<TD;Lshapeless/$colon$colon<TE;Lshapeless/$colon$colon<TF;Lshapeless/HNil;>;>;>;>;>;>;>;)Lscala/Function6<TA;TB;TC;TD;TE;TF;TRes;>;
   #72 = Utf8               inst6$
   #73 = Utf8               (Lshapeless/CaseInst;Lshapeless/PolyDefns$Case;)Lscala/Function6;
   #74 = NameAndType        #72:#73       // inst6$:(Lshapeless/CaseInst;Lshapeless/PolyDefns$Case;)Lscala/Function6;
   #75 = InterfaceMethodref #6.#74        // shapeless/CaseInst.inst6$:(Lshapeless/CaseInst;Lshapeless/PolyDefns$Case;)Lscala/Function6;
   #76 = Utf8               inst7
   #77 = Utf8               (Lshapeless/PolyDefns$Case;)Lscala/Function7;
   #78 = Utf8               <Fn::Lshapeless/Poly;A:Ljava/lang/Object;B:Ljava/lang/Object;C:Ljava/lang/Object;D:Ljava/lang/Object;E:Ljava/lang/Object;F:Ljava/lang/Object;G:Ljava/lang/Object;Res:Ljava/lang/Object;>(Lshapeless/PolyDefns$Case<TFn;Lshapeless/$colon$colon<TA;Lshapeless/$colon$colon<TB;Lshapeless/$colon$colon<TC;Lshapeless/$colon$colon<TD;Lshapeless/$colon$colon<TE;Lshapeless/$colon$colon<TF;Lshapeless/$colon$colon<TG;Lshapeless/HNil;>;>;>;>;>;>;>;>;)Lscala/Function7<TA;TB;TC;TD;TE;TF;TG;TRes;>;
   #79 = Utf8               inst7$
   #80 = Utf8               (Lshapeless/CaseInst;Lshapeless/PolyDefns$Case;)Lscala/Function7;
   #81 = NameAndType        #79:#80       // inst7$:(Lshapeless/CaseInst;Lshapeless/PolyDefns$Case;)Lscala/Function7;
   #82 = InterfaceMethodref #6.#81        // shapeless/CaseInst.inst7$:(Lshapeless/CaseInst;Lshapeless/PolyDefns$Case;)Lscala/Function7;
   #83 = Utf8               inst8
   #84 = Utf8               (Lshapeless/PolyDefns$Case;)Lscala/Function8;
   #85 = Utf8               <Fn::Lshapeless/Poly;A:Ljava/lang/Object;B:Ljava/lang/Object;C:Ljava/lang/Object;D:Ljava/lang/Object;E:Ljava/lang/Object;F:Ljava/lang/Object;G:Ljava/lang/Object;H:Ljava/lang/Object;Res:Ljava/lang/Object;>(Lshapeless/PolyDefns$Case<TFn;Lshapeless/$colon$colon<TA;Lshapeless/$colon$colon<TB;Lshapeless/$colon$colon<TC;Lshapeless/$colon$colon<TD;Lshapeless/$colon$colon<TE;Lshapeless/$colon$colon<TF;Lshapeless/$colon$colon<TG;Lshapeless/$colon$colon<TH;Lshapeless/HNil;>;>;>;>;>;>;>;>;>;)Lscala/Function8<TA;TB;TC;TD;TE;TF;TG;TH;TRes;>;
   #86 = Utf8               inst8$
   #87 = Utf8               (Lshapeless/CaseInst;Lshapeless/PolyDefns$Case;)Lscala/Function8;
   #88 = NameAndType        #86:#87       // inst8$:(Lshapeless/CaseInst;Lshapeless/PolyDefns$Case;)Lscala/Function8;
   #89 = InterfaceMethodref #6.#88        // shapeless/CaseInst.inst8$:(Lshapeless/CaseInst;Lshapeless/PolyDefns$Case;)Lscala/Function8;
   #90 = Utf8               inst9
   #91 = Utf8               (Lshapeless/PolyDefns$Case;)Lscala/Function9;
   #92 = Utf8               <Fn::Lshapeless/Poly;A:Ljava/lang/Object;B:Ljava/lang/Object;C:Ljava/lang/Object;D:Ljava/lang/Object;E:Ljava/lang/Object;F:Ljava/lang/Object;G:Ljava/lang/Object;H:Ljava/lang/Object;I:Ljava/lang/Object;Res:Ljava/lang/Object;>(Lshapeless/PolyDefns$Case<TFn;Lshapeless/$colon$colon<TA;Lshapeless/$colon$colon<TB;Lshapeless/$colon$colon<TC;Lshapeless/$colon$colon<TD;Lshapeless/$colon$colon<TE;Lshapeless/$colon$colon<TF;Lshapeless/$colon$colon<TG;Lshapeless/$colon$colon<TH;Lshapeless/$colon$colon<TI;Lshapeless/HNil;>;>;>;>;>;>;>;>;>;>;)Lscala/Function9<TA;TB;TC;TD;TE;TF;TG;TH;TI;TRes;>;
   #93 = Utf8               inst9$
   #94 = Utf8               (Lshapeless/CaseInst;Lshapeless/PolyDefns$Case;)Lscala/Function9;
   #95 = NameAndType        #93:#94       // inst9$:(Lshapeless/CaseInst;Lshapeless/PolyDefns$Case;)Lscala/Function9;
   #96 = InterfaceMethodref #6.#95        // shapeless/CaseInst.inst9$:(Lshapeless/CaseInst;Lshapeless/PolyDefns$Case;)Lscala/Function9;
   #97 = Utf8               inst10
   #98 = Utf8               (Lshapeless/PolyDefns$Case;)Lscala/Function10;
   #99 = Utf8               <Fn::Lshapeless/Poly;A:Ljava/lang/Object;B:Ljava/lang/Object;C:Ljava/lang/Object;D:Ljava/lang/Object;E:Ljava/lang/Object;F:Ljava/lang/Object;G:Ljava/lang/Object;H:Ljava/lang/Object;I:Ljava/lang/Object;J:Ljava/lang/Object;Res:Ljava/lang/Object;>(Lshapeless/PolyDefns$Case<TFn;Lshapeless/$colon$colon<TA;Lshapeless/$colon$colon<TB;Lshapeless/$colon$colon<TC;Lshapeless/$colon$colon<TD;Lshapeless/$colon$colon<TE;Lshapeless/$colon$colon<TF;Lshapeless/$colon$colon<TG;Lshapeless/$colon$colon<TH;Lshapeless/$colon$colon<TI;Lshapeless/$colon$colon<TJ;Lshapeless/HNil;>;>;>;>;>;>;>;>;>;>;>;)Lscala/Function10<TA;TB;TC;TD;TE;TF;TG;TH;TI;TJ;TRes;>;
  #100 = Utf8               inst10$
  #101 = Utf8               (Lshapeless/CaseInst;Lshapeless/PolyDefns$Case;)Lscala/Function10;
  #102 = NameAndType        #100:#101     // inst10$:(Lshapeless/CaseInst;Lshapeless/PolyDefns$Case;)Lscala/Function10;
  #103 = InterfaceMethodref #6.#102       // shapeless/CaseInst.inst10$:(Lshapeless/CaseInst;Lshapeless/PolyDefns$Case;)Lscala/Function10;
  #104 = Utf8               inst11
  #105 = Utf8               (Lshapeless/PolyDefns$Case;)Lscala/Function11;
  #106 = Utf8               <Fn::Lshapeless/Poly;A:Ljava/lang/Object;B:Ljava/lang/Object;C:Ljava/lang/Object;D:Ljava/lang/Object;E:Ljava/lang/Object;F:Ljava/lang/Object;G:Ljava/lang/Object;H:Ljava/lang/Object;I:Ljava/lang/Object;J:Ljava/lang/Object;K:Ljava/lang/Object;Res:Ljava/lang/Object;>(Lshapeless/PolyDefns$Case<TFn;Lshapeless/$colon$colon<TA;Lshapeless/$colon$colon<TB;Lshapeless/$colon$colon<TC;Lshapeless/$colon$colon<TD;Lshapeless/$colon$colon<TE;Lshapeless/$colon$colon<TF;Lshapeless/$colon$colon<TG;Lshapeless/$colon$colon<TH;Lshapeless/$colon$colon<TI;Lshapeless/$colon$colon<TJ;Lshapeless/$colon$colon<TK;Lshapeless/HNil;>;>;>;>;>;>;>;>;>;>;>;>;)Lscala/Function11<TA;TB;TC;TD;TE;TF;TG;TH;TI;TJ;TK;TRes;>;
  #107 = Utf8               inst11$
  #108 = Utf8               (Lshapeless/CaseInst;Lshapeless/PolyDefns$Case;)Lscala/Function11;
  #109 = NameAndType        #107:#108     // inst11$:(Lshapeless/CaseInst;Lshapeless/PolyDefns$Case;)Lscala/Function11;
  #110 = InterfaceMethodref #6.#109       // shapeless/CaseInst.inst11$:(Lshapeless/CaseInst;Lshapeless/PolyDefns$Case;)Lscala/Function11;
  #111 = Utf8               inst12
  #112 = Utf8               (Lshapeless/PolyDefns$Case;)Lscala/Function12;
  #113 = Utf8               <Fn::Lshapeless/Poly;A:Ljava/lang/Object;B:Ljava/lang/Object;C:Ljava/lang/Object;D:Ljava/lang/Object;E:Ljava/lang/Object;F:Ljava/lang/Object;G:Ljava/lang/Object;H:Ljava/lang/Object;I:Ljava/lang/Object;J:Ljava/lang/Object;K:Ljava/lang/Object;L:Ljava/lang/Object;Res:Ljava/lang/Object;>(Lshapeless/PolyDefns$Case<TFn;Lshapeless/$colon$colon<TA;Lshapeless/$colon$colon<TB;Lshapeless/$colon$colon<TC;Lshapeless/$colon$colon<TD;Lshapeless/$colon$colon<TE;Lshapeless/$colon$colon<TF;Lshapeless/$colon$colon<TG;Lshapeless/$colon$colon<TH;Lshapeless/$colon$colon<TI;Lshapeless/$colon$colon<TJ;Lshapeless/$colon$colon<TK;Lshapeless/$colon$colon<TL;Lshapeless/HNil;>;>;>;>;>;>;>;>;>;>;>;>;>;)Lscala/Function12<TA;TB;TC;TD;TE;TF;TG;TH;TI;TJ;TK;TL;TRes;>;
  #114 = Utf8               inst12$
  #115 = Utf8               (Lshapeless/CaseInst;Lshapeless/PolyDefns$Case;)Lscala/Function12;
  #116 = NameAndType        #114:#115     // inst12$:(Lshapeless/CaseInst;Lshapeless/PolyDefns$Case;)Lscala/Function12;
  #117 = InterfaceMethodref #6.#116       // shapeless/CaseInst.inst12$:(Lshapeless/CaseInst;Lshapeless/PolyDefns$Case;)Lscala/Function12;
  #118 = Utf8               inst13
  #119 = Utf8               (Lshapeless/PolyDefns$Case;)Lscala/Function13;
  #120 = Utf8               <Fn::Lshapeless/Poly;A:Ljava/lang/Object;B:Ljava/lang/Object;C:Ljava/lang/Object;D:Ljava/lang/Object;E:Ljava/lang/Object;F:Ljava/lang/Object;G:Ljava/lang/Object;H:Ljava/lang/Object;I:Ljava/lang/Object;J:Ljava/lang/Object;K:Ljava/lang/Object;L:Ljava/lang/Object;M:Ljava/lang/Object;Res:Ljava/lang/Object;>(Lshapeless/PolyDefns$Case<TFn;Lshapeless/$colon$colon<TA;Lshapeless/$colon$colon<TB;Lshapeless/$colon$colon<TC;Lshapeless/$colon$colon<TD;Lshapeless/$colon$colon<TE;Lshapeless/$colon$colon<TF;Lshapeless/$colon$colon<TG;Lshapeless/$colon$colon<TH;Lshapeless/$colon$colon<TI;Lshapeless/$colon$colon<TJ;Lshapeless/$colon$colon<TK;Lshapeless/$colon$colon<TL;Lshapeless/$colon$colon<TM;Lshapeless/HNil;>;>;>;>;>;>;>;>;>;>;>;>;>;>;)Lscala/Function13<TA;TB;TC;TD;TE;TF;TG;TH;TI;TJ;TK;TL;TM;TRes;>;
  #121 = Utf8               inst13$
  #122 = Utf8               (Lshapeless/CaseInst;Lshapeless/PolyDefns$Case;)Lscala/Function13;
  #123 = NameAndType        #121:#122     // inst13$:(Lshapeless/CaseInst;Lshapeless/PolyDefns$Case;)Lscala/Function13;
  #124 = InterfaceMethodref #6.#123       // shapeless/CaseInst.inst13$:(Lshapeless/CaseInst;Lshapeless/PolyDefns$Case;)Lscala/Function13;
  #125 = Utf8               inst14
  #126 = Utf8               (Lshapeless/PolyDefns$Case;)Lscala/Function14;
  #127 = Utf8               <Fn::Lshapeless/Poly;A:Ljava/lang/Object;B:Ljava/lang/Object;C:Ljava/lang/Object;D:Ljava/lang/Object;E:Ljava/lang/Object;F:Ljava/lang/Object;G:Ljava/lang/Object;H:Ljava/lang/Object;I:Ljava/lang/Object;J:Ljava/lang/Object;K:Ljava/lang/Object;L:Ljava/lang/Object;M:Ljava/lang/Object;N:Ljava/lang/Object;Res:Ljava/lang/Object;>(Lshapeless/PolyDefns$Case<TFn;Lshapeless/$colon$colon<TA;Lshapeless/$colon$colon<TB;Lshapeless/$colon$colon<TC;Lshapeless/$colon$colon<TD;Lshapeless/$colon$colon<TE;Lshapeless/$colon$colon<TF;Lshapeless/$colon$colon<TG;Lshapeless/$colon$colon<TH;Lshapeless/$colon$colon<TI;Lshapeless/$colon$colon<TJ;Lshapeless/$colon$colon<TK;Lshapeless/$colon$colon<TL;Lshapeless/$colon$colon<TM;Lshapeless/$colon$colon<TN;Lshapeless/HNil;>;>;>;>;>;>;>;>;>;>;>;>;>;>;>;)Lscala/Function14<TA;TB;TC;TD;TE;TF;TG;TH;TI;TJ;TK;TL;TM;TN;TRes;>;
  #128 = Utf8               inst14$
  #129 = Utf8               (Lshapeless/CaseInst;Lshapeless/PolyDefns$Case;)Lscala/Function14;
  #130 = NameAndType        #128:#129     // inst14$:(Lshapeless/CaseInst;Lshapeless/PolyDefns$Case;)Lscala/Function14;
  #131 = InterfaceMethodref #6.#130       // shapeless/CaseInst.inst14$:(Lshapeless/CaseInst;Lshapeless/PolyDefns$Case;)Lscala/Function14;
  #132 = Utf8               inst15
  #133 = Utf8               (Lshapeless/PolyDefns$Case;)Lscala/Function15;
  #134 = Utf8               <Fn::Lshapeless/Poly;A:Ljava/lang/Object;B:Ljava/lang/Object;C:Ljava/lang/Object;D:Ljava/lang/Object;E:Ljava/lang/Object;F:Ljava/lang/Object;G:Ljava/lang/Object;H:Ljava/lang/Object;I:Ljava/lang/Object;J:Ljava/lang/Object;K:Ljava/lang/Object;L:Ljava/lang/Object;M:Ljava/lang/Object;N:Ljava/lang/Object;O:Ljava/lang/Object;Res:Ljava/lang/Object;>(Lshapeless/PolyDefns$Case<TFn;Lshapeless/$colon$colon<TA;Lshapeless/$colon$colon<TB;Lshapeless/$colon$colon<TC;Lshapeless/$colon$colon<TD;Lshapeless/$colon$colon<TE;Lshapeless/$colon$colon<TF;Lshapeless/$colon$colon<TG;Lshapeless/$colon$colon<TH;Lshapeless/$colon$colon<TI;Lshapeless/$colon$colon<TJ;Lshapeless/$colon$colon<TK;Lshapeless/$colon$colon<TL;Lshapeless/$colon$colon<TM;Lshapeless/$colon$colon<TN;Lshapeless/$colon$colon<TO;Lshapeless/HNil;>;>;>;>;>;>;>;>;>;>;>;>;>;>;>;>;)Lscala/Function15<TA;TB;TC;TD;TE;TF;TG;TH;TI;TJ;TK;TL;TM;TN;TO;TRes;>;
  #135 = Utf8               inst15$
  #136 = Utf8               (Lshapeless/CaseInst;Lshapeless/PolyDefns$Case;)Lscala/Function15;
  #137 = NameAndType        #135:#136     // inst15$:(Lshapeless/CaseInst;Lshapeless/PolyDefns$Case;)Lscala/Function15;
  #138 = InterfaceMethodref #6.#137       // shapeless/CaseInst.inst15$:(Lshapeless/CaseInst;Lshapeless/PolyDefns$Case;)Lscala/Function15;
  #139 = Utf8               inst16
  #140 = Utf8               (Lshapeless/PolyDefns$Case;)Lscala/Function16;
  #141 = Utf8               <Fn::Lshapeless/Poly;A:Ljava/lang/Object;B:Ljava/lang/Object;C:Ljava/lang/Object;D:Ljava/lang/Object;E:Ljava/lang/Object;F:Ljava/lang/Object;G:Ljava/lang/Object;H:Ljava/lang/Object;I:Ljava/lang/Object;J:Ljava/lang/Object;K:Ljava/lang/Object;L:Ljava/lang/Object;M:Ljava/lang/Object;N:Ljava/lang/Object;O:Ljava/lang/Object;P:Ljava/lang/Object;Res:Ljava/lang/Object;>(Lshapeless/PolyDefns$Case<TFn;Lshapeless/$colon$colon<TA;Lshapeless/$colon$colon<TB;Lshapeless/$colon$colon<TC;Lshapeless/$colon$colon<TD;Lshapeless/$colon$colon<TE;Lshapeless/$colon$colon<TF;Lshapeless/$colon$colon<TG;Lshapeless/$colon$colon<TH;Lshapeless/$colon$colon<TI;Lshapeless/$colon$colon<TJ;Lshapeless/$colon$colon<TK;Lshapeless/$colon$colon<TL;Lshapeless/$colon$colon<TM;Lshapeless/$colon$colon<TN;Lshapeless/$colon$colon<TO;Lshapeless/$colon$colon<TP;Lshapeless/HNil;>;>;>;>;>;>;>;>;>;>;>;>;>;>;>;>;>;)Lscala/Function16<TA;TB;TC;TD;TE;TF;TG;TH;TI;TJ;TK;TL;TM;TN;TO;TP;TRes;>;
  #142 = Utf8               inst16$
  #143 = Utf8               (Lshapeless/CaseInst;Lshapeless/PolyDefns$Case;)Lscala/Function16;
  #144 = NameAndType        #142:#143     // inst16$:(Lshapeless/CaseInst;Lshapeless/PolyDefns$Case;)Lscala/Function16;
  #145 = InterfaceMethodref #6.#144       // shapeless/CaseInst.inst16$:(Lshapeless/CaseInst;Lshapeless/PolyDefns$Case;)Lscala/Function16;
  #146 = Utf8               inst17
  #147 = Utf8               (Lshapeless/PolyDefns$Case;)Lscala/Function17;
  #148 = Utf8               <Fn::Lshapeless/Poly;A:Ljava/lang/Object;B:Ljava/lang/Object;C:Ljava/lang/Object;D:Ljava/lang/Object;E:Ljava/lang/Object;F:Ljava/lang/Object;G:Ljava/lang/Object;H:Ljava/lang/Object;I:Ljava/lang/Object;J:Ljava/lang/Object;K:Ljava/lang/Object;L:Ljava/lang/Object;M:Ljava/lang/Object;N:Ljava/lang/Object;O:Ljava/lang/Object;P:Ljava/lang/Object;Q:Ljava/lang/Object;Res:Ljava/lang/Object;>(Lshapeless/PolyDefns$Case<TFn;Lshapeless/$colon$colon<TA;Lshapeless/$colon$colon<TB;Lshapeless/$colon$colon<TC;Lshapeless/$colon$colon<TD;Lshapeless/$colon$colon<TE;Lshapeless/$colon$colon<TF;Lshapeless/$colon$colon<TG;Lshapeless/$colon$colon<TH;Lshapeless/$colon$colon<TI;Lshapeless/$colon$colon<TJ;Lshapeless/$colon$colon<TK;Lshapeless/$colon$colon<TL;Lshapeless/$colon$colon<TM;Lshapeless/$colon$colon<TN;Lshapeless/$colon$colon<TO;Lshapeless/$colon$colon<TP;Lshapeless/$colon$colon<TQ;Lshapeless/HNil;>;>;>;>;>;>;>;>;>;>;>;>;>;>;>;>;>;>;)Lscala/Function17<TA;TB;TC;TD;TE;TF;TG;TH;TI;TJ;TK;TL;TM;TN;TO;TP;TQ;TRes;>;
  #149 = Utf8               inst17$
  #150 = Utf8               (Lshapeless/CaseInst;Lshapeless/PolyDefns$Case;)Lscala/Function17;
  #151 = NameAndType        #149:#150     // inst17$:(Lshapeless/CaseInst;Lshapeless/PolyDefns$Case;)Lscala/Function17;
  #152 = InterfaceMethodref #6.#151       // shapeless/CaseInst.inst17$:(Lshapeless/CaseInst;Lshapeless/PolyDefns$Case;)Lscala/Function17;
  #153 = Utf8               inst18
  #154 = Utf8               (Lshapeless/PolyDefns$Case;)Lscala/Function18;
  #155 = Utf8               <Fn::Lshapeless/Poly;A:Ljava/lang/Object;B:Ljava/lang/Object;C:Ljava/lang/Object;D:Ljava/lang/Object;E:Ljava/lang/Object;F:Ljava/lang/Object;G:Ljava/lang/Object;H:Ljava/lang/Object;I:Ljava/lang/Object;J:Ljava/lang/Object;K:Ljava/lang/Object;L:Ljava/lang/Object;M:Ljava/lang/Object;N:Ljava/lang/Object;O:Ljava/lang/Object;P:Ljava/lang/Object;Q:Ljava/lang/Object;R:Ljava/lang/Object;Res:Ljava/lang/Object;>(Lshapeless/PolyDefns$Case<TFn;Lshapeless/$colon$colon<TA;Lshapeless/$colon$colon<TB;Lshapeless/$colon$colon<TC;Lshapeless/$colon$colon<TD;Lshapeless/$colon$colon<TE;Lshapeless/$colon$colon<TF;Lshapeless/$colon$colon<TG;Lshapeless/$colon$colon<TH;Lshapeless/$colon$colon<TI;Lshapeless/$colon$colon<TJ;Lshapeless/$colon$colon<TK;Lshapeless/$colon$colon<TL;Lshapeless/$colon$colon<TM;Lshapeless/$colon$colon<TN;Lshapeless/$colon$colon<TO;Lshapeless/$colon$colon<TP;Lshapeless/$colon$colon<TQ;Lshapeless/$colon$colon<TR;Lshapeless/HNil;>;>;>;>;>;>;>;>;>;>;>;>;>;>;>;>;>;>;>;)Lscala/Function18<TA;TB;TC;TD;TE;TF;TG;TH;TI;TJ;TK;TL;TM;TN;TO;TP;TQ;TR;TRes;>;
  #156 = Utf8               inst18$
  #157 = Utf8               (Lshapeless/CaseInst;Lshapeless/PolyDefns$Case;)Lscala/Function18;
  #158 = NameAndType        #156:#157     // inst18$:(Lshapeless/CaseInst;Lshapeless/PolyDefns$Case;)Lscala/Function18;
  #159 = InterfaceMethodref #6.#158       // shapeless/CaseInst.inst18$:(Lshapeless/CaseInst;Lshapeless/PolyDefns$Case;)Lscala/Function18;
  #160 = Utf8               inst19
  #161 = Utf8               (Lshapeless/PolyDefns$Case;)Lscala/Function19;
  #162 = Utf8               <Fn::Lshapeless/Poly;A:Ljava/lang/Object;B:Ljava/lang/Object;C:Ljava/lang/Object;D:Ljava/lang/Object;E:Ljava/lang/Object;F:Ljava/lang/Object;G:Ljava/lang/Object;H:Ljava/lang/Object;I:Ljava/lang/Object;J:Ljava/lang/Object;K:Ljava/lang/Object;L:Ljava/lang/Object;M:Ljava/lang/Object;N:Ljava/lang/Object;O:Ljava/lang/Object;P:Ljava/lang/Object;Q:Ljava/lang/Object;R:Ljava/lang/Object;S:Ljava/lang/Object;Res:Ljava/lang/Object;>(Lshapeless/PolyDefns$Case<TFn;Lshapeless/$colon$colon<TA;Lshapeless/$colon$colon<TB;Lshapeless/$colon$colon<TC;Lshapeless/$colon$colon<TD;Lshapeless/$colon$colon<TE;Lshapeless/$colon$colon<TF;Lshapeless/$colon$colon<TG;Lshapeless/$colon$colon<TH;Lshapeless/$colon$colon<TI;Lshapeless/$colon$colon<TJ;Lshapeless/$colon$colon<TK;Lshapeless/$colon$colon<TL;Lshapeless/$colon$colon<TM;Lshapeless/$colon$colon<TN;Lshapeless/$colon$colon<TO;Lshapeless/$colon$colon<TP;Lshapeless/$colon$colon<TQ;Lshapeless/$colon$colon<TR;Lshapeless/$colon$colon<TS;Lshapeless/HNil;>;>;>;>;>;>;>;>;>;>;>;>;>;>;>;>;>;>;>;>;)Lscala/Function19<TA;TB;TC;TD;TE;TF;TG;TH;TI;TJ;TK;TL;TM;TN;TO;TP;TQ;TR;TS;TRes;>;
  #163 = Utf8               inst19$
  #164 = Utf8               (Lshapeless/CaseInst;Lshapeless/PolyDefns$Case;)Lscala/Function19;
  #165 = NameAndType        #163:#164     // inst19$:(Lshapeless/CaseInst;Lshapeless/PolyDefns$Case;)Lscala/Function19;
  #166 = InterfaceMethodref #6.#165       // shapeless/CaseInst.inst19$:(Lshapeless/CaseInst;Lshapeless/PolyDefns$Case;)Lscala/Function19;
  #167 = Utf8               inst20
  #168 = Utf8               (Lshapeless/PolyDefns$Case;)Lscala/Function20;
  #169 = Utf8               <Fn::Lshapeless/Poly;A:Ljava/lang/Object;B:Ljava/lang/Object;C:Ljava/lang/Object;D:Ljava/lang/Object;E:Ljava/lang/Object;F:Ljava/lang/Object;G:Ljava/lang/Object;H:Ljava/lang/Object;I:Ljava/lang/Object;J:Ljava/lang/Object;K:Ljava/lang/Object;L:Ljava/lang/Object;M:Ljava/lang/Object;N:Ljava/lang/Object;O:Ljava/lang/Object;P:Ljava/lang/Object;Q:Ljava/lang/Object;R:Ljava/lang/Object;S:Ljava/lang/Object;T:Ljava/lang/Object;Res:Ljava/lang/Object;>(Lshapeless/PolyDefns$Case<TFn;Lshapeless/$colon$colon<TA;Lshapeless/$colon$colon<TB;Lshapeless/$colon$colon<TC;Lshapeless/$colon$colon<TD;Lshapeless/$colon$colon<TE;Lshapeless/$colon$colon<TF;Lshapeless/$colon$colon<TG;Lshapeless/$colon$colon<TH;Lshapeless/$colon$colon<TI;Lshapeless/$colon$colon<TJ;Lshapeless/$colon$colon<TK;Lshapeless/$colon$colon<TL;Lshapeless/$colon$colon<TM;Lshapeless/$colon$colon<TN;Lshapeless/$colon$colon<TO;Lshapeless/$colon$colon<TP;Lshapeless/$colon$colon<TQ;Lshapeless/$colon$colon<TR;Lshapeless/$colon$colon<TS;Lshapeless/$colon$colon<TT;Lshapeless/HNil;>;>;>;>;>;>;>;>;>;>;>;>;>;>;>;>;>;>;>;>;>;)Lscala/Function20<TA;TB;TC;TD;TE;TF;TG;TH;TI;TJ;TK;TL;TM;TN;TO;TP;TQ;TR;TS;TT;TRes;>;
  #170 = Utf8               inst20$
  #171 = Utf8               (Lshapeless/CaseInst;Lshapeless/PolyDefns$Case;)Lscala/Function20;
  #172 = NameAndType        #170:#171     // inst20$:(Lshapeless/CaseInst;Lshapeless/PolyDefns$Case;)Lscala/Function20;
  #173 = InterfaceMethodref #6.#172       // shapeless/CaseInst.inst20$:(Lshapeless/CaseInst;Lshapeless/PolyDefns$Case;)Lscala/Function20;
  #174 = Utf8               inst21
  #175 = Utf8               (Lshapeless/PolyDefns$Case;)Lscala/Function21;
  #176 = Utf8               <Fn::Lshapeless/Poly;A:Ljava/lang/Object;B:Ljava/lang/Object;C:Ljava/lang/Object;D:Ljava/lang/Object;E:Ljava/lang/Object;F:Ljava/lang/Object;G:Ljava/lang/Object;H:Ljava/lang/Object;I:Ljava/lang/Object;J:Ljava/lang/Object;K:Ljava/lang/Object;L:Ljava/lang/Object;M:Ljava/lang/Object;N:Ljava/lang/Object;O:Ljava/lang/Object;P:Ljava/lang/Object;Q:Ljava/lang/Object;R:Ljava/lang/Object;S:Ljava/lang/Object;T:Ljava/lang/Object;U:Ljava/lang/Object;Res:Ljava/lang/Object;>(Lshapeless/PolyDefns$Case<TFn;Lshapeless/$colon$colon<TA;Lshapeless/$colon$colon<TB;Lshapeless/$colon$colon<TC;Lshapeless/$colon$colon<TD;Lshapeless/$colon$colon<TE;Lshapeless/$colon$colon<TF;Lshapeless/$colon$colon<TG;Lshapeless/$colon$colon<TH;Lshapeless/$colon$colon<TI;Lshapeless/$colon$colon<TJ;Lshapeless/$colon$colon<TK;Lshapeless/$colon$colon<TL;Lshapeless/$colon$colon<TM;Lshapeless/$colon$colon<TN;Lshapeless/$colon$colon<TO;Lshapeless/$colon$colon<TP;Lshapeless/$colon$colon<TQ;Lshapeless/$colon$colon<TR;Lshapeless/$colon$colon<TS;Lshapeless/$colon$colon<TT;Lshapeless/$colon$colon<TU;Lshapeless/HNil;>;>;>;>;>;>;>;>;>;>;>;>;>;>;>;>;>;>;>;>;>;>;)Lscala/Function21<TA;TB;TC;TD;TE;TF;TG;TH;TI;TJ;TK;TL;TM;TN;TO;TP;TQ;TR;TS;TT;TU;TRes;>;
  #177 = Utf8               inst21$
  #178 = Utf8               (Lshapeless/CaseInst;Lshapeless/PolyDefns$Case;)Lscala/Function21;
  #179 = NameAndType        #177:#178     // inst21$:(Lshapeless/CaseInst;Lshapeless/PolyDefns$Case;)Lscala/Function21;
  #180 = InterfaceMethodref #6.#179       // shapeless/CaseInst.inst21$:(Lshapeless/CaseInst;Lshapeless/PolyDefns$Case;)Lscala/Function21;
  #181 = Utf8               inst22
  #182 = Utf8               (Lshapeless/PolyDefns$Case;)Lscala/Function22;
  #183 = Utf8               <Fn::Lshapeless/Poly;A:Ljava/lang/Object;B:Ljava/lang/Object;C:Ljava/lang/Object;D:Ljava/lang/Object;E:Ljava/lang/Object;F:Ljava/lang/Object;G:Ljava/lang/Object;H:Ljava/lang/Object;I:Ljava/lang/Object;J:Ljava/lang/Object;K:Ljava/lang/Object;L:Ljava/lang/Object;M:Ljava/lang/Object;N:Ljava/lang/Object;O:Ljava/lang/Object;P:Ljava/lang/Object;Q:Ljava/lang/Object;R:Ljava/lang/Object;S:Ljava/lang/Object;T:Ljava/lang/Object;U:Ljava/lang/Object;V:Ljava/lang/Object;Res:Ljava/lang/Object;>(Lshapeless/PolyDefns$Case<TFn;Lshapeless/$colon$colon<TA;Lshapeless/$colon$colon<TB;Lshapeless/$colon$colon<TC;Lshapeless/$colon$colon<TD;Lshapeless/$colon$colon<TE;Lshapeless/$colon$colon<TF;Lshapeless/$colon$colon<TG;Lshapeless/$colon$colon<TH;Lshapeless/$colon$colon<TI;Lshapeless/$colon$colon<TJ;Lshapeless/$colon$colon<TK;Lshapeless/$colon$colon<TL;Lshapeless/$colon$colon<TM;Lshapeless/$colon$colon<TN;Lshapeless/$colon$colon<TO;Lshapeless/$colon$colon<TP;Lshapeless/$colon$colon<TQ;Lshapeless/$colon$colon<TR;Lshapeless/$colon$colon<TS;Lshapeless/$colon$colon<TT;Lshapeless/$colon$colon<TU;Lshapeless/$colon$colon<TV;Lshapeless/HNil;>;>;>;>;>;>;>;>;>;>;>;>;>;>;>;>;>;>;>;>;>;>;>;)Lscala/Function22<TA;TB;TC;TD;TE;TF;TG;TH;TI;TJ;TK;TL;TM;TN;TO;TP;TQ;TR;TS;TT;TU;TV;TRes;>;
  #184 = Utf8               inst22$
  #185 = Utf8               (Lshapeless/CaseInst;Lshapeless/PolyDefns$Case;)Lscala/Function22;
  #186 = NameAndType        #184:#185     // inst22$:(Lshapeless/CaseInst;Lshapeless/PolyDefns$Case;)Lscala/Function22;
  #187 = InterfaceMethodref #6.#186       // shapeless/CaseInst.inst22$:(Lshapeless/CaseInst;Lshapeless/PolyDefns$Case;)Lscala/Function22;
  #188 = Utf8               apply
  #189 = Utf8               (Lscala/Function1;)Lshapeless/PolyDefns$Case;
  #190 = Utf8               <P:Ljava/lang/Object;L::Lshapeless/HList;R:Ljava/lang/Object;>(Lscala/Function1<TL;TR;>;)Lshapeless/PolyDefns$Case<TP;TL;>;
  #191 = Utf8               v
  #192 = Utf8               (Lscala/Function1;)V
  #193 = NameAndType        #22:#192      // "<init>":(Lscala/Function1;)V
  #194 = Methodref          #17.#193      // shapeless/PolyDefns$Case$$anon$1."<init>":(Lscala/Function1;)V
  #195 = Utf8               Lscala/Function1;
  #196 = Utf8               writeReplace
  #197 = Utf8               ()Ljava/lang/Object;
  #198 = Utf8               scala/runtime/ModuleSerializationProxy
  #199 = Class              #198          // scala/runtime/ModuleSerializationProxy
  #200 = Utf8               (Ljava/lang/Class;)V
  #201 = NameAndType        #22:#200      // "<init>":(Ljava/lang/Class;)V
  #202 = Methodref          #199.#201     // scala/runtime/ModuleSerializationProxy."<init>":(Ljava/lang/Class;)V
  #203 = Methodref          #4.#23        // java/lang/Object."<init>":()V
  #204 = Utf8               Code
  #205 = Utf8               LineNumberTable
  #206 = Utf8               LocalVariableTable
  #207 = Utf8               Signature
  #208 = Utf8               MethodParameters
  #209 = Utf8               InnerClasses
  #210 = Utf8               SourceFile
  #211 = Utf8               ScalaInlineInfo
  #212 = Utf8               materializeFromValue1
  #213 = Utf8               ()Lshapeless/PolyDefns$Case;
  #214 = Utf8               materializeFromValue2
  #215 = Utf8               Scala
{
  public static final shapeless.PolyDefns$Case$ MODULE$;
    descriptor: Lshapeless/PolyDefns$Case$;
    flags: (0x0019) ACC_PUBLIC, ACC_STATIC, ACC_FINAL

  public static {};
    descriptor: ()V
    flags: (0x0009) ACC_PUBLIC, ACC_STATIC
    Code:
      stack=2, locals=0, args_size=0
         0: new           #2                  // class shapeless/PolyDefns$Case$
         3: dup
         4: invokespecial #24                 // Method "<init>":()V
         7: putstatic     #26                 // Field MODULE$:Lshapeless/PolyDefns$Case$;
        10: getstatic     #26                 // Field MODULE$:Lshapeless/PolyDefns$Case$;
        13: invokestatic  #30                 // InterfaceMethod shapeless/CaseInst.$init$:(Lshapeless/CaseInst;)V
        16: return
      LineNumberTable:
        line 42: 0

  public <Fn extends shapeless.Poly, A extends java.lang.Object, Res extends java.lang.Object> scala.Function1<A, Res> inst1(shapeless.PolyDefns$Case<Fn, shapeless.$colon$colon<A, shapeless.HNil>>);
    descriptor: (Lshapeless/PolyDefns$Case;)Lscala/Function1;
    flags: (0x0001) ACC_PUBLIC
    Code:
      stack=2, locals=2, args_size=2
         0: aload_0
         1: aload_1
         2: invokestatic  #38                 // InterfaceMethod shapeless/CaseInst.inst1$:(Lshapeless/CaseInst;Lshapeless/PolyDefns$Case;)Lscala/Function1;
         5: areturn
      LineNumberTable:
        line 42: 0
      LocalVariableTable:
        Start  Length  Slot  Name   Signature
            0       6     0  this   Lshapeless/PolyDefns$Case$;
            0       6     1   cse   Lshapeless/PolyDefns$Case;
    Signature: #33                          // <Fn::Lshapeless/Poly;A:Ljava/lang/Object;Res:Ljava/lang/Object;>(Lshapeless/PolyDefns$Case<TFn;Lshapeless/$colon$colon<TA;Lshapeless/HNil;>;>;)Lscala/Function1<TA;TRes;>;
    MethodParameters:
      Name                           Flags
      cse                            final

  public <Fn extends shapeless.Poly, A extends java.lang.Object, B extends java.lang.Object, Res extends java.lang.Object> scala.Function2<A, B, Res> inst2(shapeless.PolyDefns$Case<Fn, shapeless.$colon$colon<A, shapeless.$colon$colon<B, shapeless.HNil>>>);
    descriptor: (Lshapeless/PolyDefns$Case;)Lscala/Function2;
    flags: (0x0001) ACC_PUBLIC
    Code:
      stack=2, locals=2, args_size=2
         0: aload_0
         1: aload_1
         2: invokestatic  #47                 // InterfaceMethod shapeless/CaseInst.inst2$:(Lshapeless/CaseInst;Lshapeless/PolyDefns$Case;)Lscala/Function2;
         5: areturn
      LineNumberTable:
        line 42: 0
      LocalVariableTable:
        Start  Length  Slot  Name   Signature
            0       6     0  this   Lshapeless/PolyDefns$Case$;
            0       6     1   cse   Lshapeless/PolyDefns$Case;
    Signature: #43                          // <Fn::Lshapeless/Poly;A:Ljava/lang/Object;B:Ljava/lang/Object;Res:Ljava/lang/Object;>(Lshapeless/PolyDefns$Case<TFn;Lshapeless/$colon$colon<TA;Lshapeless/$colon$colon<TB;Lshapeless/HNil;>;>;>;)Lscala/Function2<TA;TB;TRes;>;
    MethodParameters:
      Name                           Flags
      cse                            final

  public <Fn extends shapeless.Poly, A extends java.lang.Object, B extends java.lang.Object, C extends java.lang.Object, Res extends java.lang.Object> scala.Function3<A, B, C, Res> inst3(shapeless.PolyDefns$Case<Fn, shapeless.$colon$colon<A, shapeless.$colon$colon<B, shapeless.$colon$colon<C, shapeless.HNil>>>>);
    descriptor: (Lshapeless/PolyDefns$Case;)Lscala/Function3;
    flags: (0x0001) ACC_PUBLIC
    Code:
      stack=2, locals=2, args_size=2
         0: aload_0
         1: aload_1
         2: invokestatic  #54                 // InterfaceMethod shapeless/CaseInst.inst3$:(Lshapeless/CaseInst;Lshapeless/PolyDefns$Case;)Lscala/Function3;
         5: areturn
      LineNumberTable:
        line 42: 0
      LocalVariableTable:
        Start  Length  Slot  Name   Signature
            0       6     0  this   Lshapeless/PolyDefns$Case$;
            0       6     1   cse   Lshapeless/PolyDefns$Case;
    Signature: #50                          // <Fn::Lshapeless/Poly;A:Ljava/lang/Object;B:Ljava/lang/Object;C:Ljava/lang/Object;Res:Ljava/lang/Object;>(Lshapeless/PolyDefns$Case<TFn;Lshapeless/$colon$colon<TA;Lshapeless/$colon$colon<TB;Lshapeless/$colon$colon<TC;Lshapeless/HNil;>;>;>;>;)Lscala/Function3<TA;TB;TC;TRes;>;
    MethodParameters:
      Name                           Flags
      cse                            final

  public <Fn extends shapeless.Poly, A extends java.lang.Object, B extends java.lang.Object, C extends java.lang.Object, D extends java.lang.Object, Res extends java.lang.Object> scala.Function4<A, B, C, D, Res> inst4(shapeless.PolyDefns$Case<Fn, shapeless.$colon$colon<A, shapeless.$colon$colon<B, shapeless.$colon$colon<C, shapeless.$colon$colon<D, shapeless.HNil>>>>>);
    descriptor: (Lshapeless/PolyDefns$Case;)Lscala/Function4;
    flags: (0x0001) ACC_PUBLIC
    Code:
      stack=2, locals=2, args_size=2
         0: aload_0
         1: aload_1
         2: invokestatic  #61                 // InterfaceMethod shapeless/CaseInst.inst4$:(Lshapeless/CaseInst;Lshapeless/PolyDefns$Case;)Lscala/Function4;
         5: areturn
      LineNumberTable:
        line 42: 0
      LocalVariableTable:
        Start  Length  Slot  Name   Signature
            0       6     0  this   Lshapeless/PolyDefns$Case$;
            0       6     1   cse   Lshapeless/PolyDefns$Case;
    Signature: #57                          // <Fn::Lshapeless/Poly;A:Ljava/lang/Object;B:Ljava/lang/Object;C:Ljava/lang/Object;D:Ljava/lang/Object;Res:Ljava/lang/Object;>(Lshapeless/PolyDefns$Case<TFn;Lshapeless/$colon$colon<TA;Lshapeless/$colon$colon<TB;Lshapeless/$colon$colon<TC;Lshapeless/$colon$colon<TD;Lshapeless/HNil;>;>;>;>;>;)Lscala/Function4<TA;TB;TC;TD;TRes;>;
    MethodParameters:
      Name                           Flags
      cse                            final

  public <Fn extends shapeless.Poly, A extends java.lang.Object, B extends java.lang.Object, C extends java.lang.Object, D extends java.lang.Object, E extends java.lang.Object, Res extends java.lang.Object> scala.Function5<A, B, C, D, E, Res> inst5(shapeless.PolyDefns$Case<Fn, shapeless.$colon$colon<A, shapeless.$colon$colon<B, shapeless.$colon$colon<C, shapeless.$colon$colon<D, shapeless.$colon$colon<E, shapeless.HNil>>>>>>);
    descriptor: (Lshapeless/PolyDefns$Case;)Lscala/Function5;
    flags: (0x0001) ACC_PUBLIC
    Code:
      stack=2, locals=2, args_size=2
         0: aload_0
         1: aload_1
         2: invokestatic  #68                 // InterfaceMethod shapeless/CaseInst.inst5$:(Lshapeless/CaseInst;Lshapeless/PolyDefns$Case;)Lscala/Function5;
         5: areturn
      LineNumberTable:
        line 42: 0
      LocalVariableTable:
        Start  Length  Slot  Name   Signature
            0       6     0  this   Lshapeless/PolyDefns$Case$;
            0       6     1   cse   Lshapeless/PolyDefns$Case;
    Signature: #64                          // <Fn::Lshapeless/Poly;A:Ljava/lang/Object;B:Ljava/lang/Object;C:Ljava/lang/Object;D:Ljava/lang/Object;E:Ljava/lang/Object;Res:Ljava/lang/Object;>(Lshapeless/PolyDefns$Case<TFn;Lshapeless/$colon$colon<TA;Lshapeless/$colon$colon<TB;Lshapeless/$colon$colon<TC;Lshapeless/$colon$colon<TD;Lshapeless/$colon$colon<TE;Lshapeless/HNil;>;>;>;>;>;>;)Lscala/Function5<TA;TB;TC;TD;TE;TRes;>;
    MethodParameters:
      Name                           Flags
      cse                            final

  public <Fn extends shapeless.Poly, A extends java.lang.Object, B extends java.lang.Object, C extends java.lang.Object, D extends java.lang.Object, E extends java.lang.Object, F extends java.lang.Object, Res extends java.lang.Object> scala.Function6<A, B, C, D, E, F, Res> inst6(shapeless.PolyDefns$Case<Fn, shapeless.$colon$colon<A, shapeless.$colon$colon<B, shapeless.$colon$colon<C, shapeless.$colon$colon<D, shapeless.$colon$colon<E, shapeless.$colon$colon<F, shapeless.HNil>>>>>>>);
    descriptor: (Lshapeless/PolyDefns$Case;)Lscala/Function6;
    flags: (0x0001) ACC_PUBLIC
    Code:
      stack=2, locals=2, args_size=2
         0: aload_0
         1: aload_1
         2: invokestatic  #75                 // InterfaceMethod shapeless/CaseInst.inst6$:(Lshapeless/CaseInst;Lshapeless/PolyDefns$Case;)Lscala/Function6;
         5: areturn
      LineNumberTable:
        line 42: 0
      LocalVariableTable:
        Start  Length  Slot  Name   Signature
            0       6     0  this   Lshapeless/PolyDefns$Case$;
            0       6     1   cse   Lshapeless/PolyDefns$Case;
    Signature: #71                          // <Fn::Lshapeless/Poly;A:Ljava/lang/Object;B:Ljava/lang/Object;C:Ljava/lang/Object;D:Ljava/lang/Object;E:Ljava/lang/Object;F:Ljava/lang/Object;Res:Ljava/lang/Object;>(Lshapeless/PolyDefns$Case<TFn;Lshapeless/$colon$colon<TA;Lshapeless/$colon$colon<TB;Lshapeless/$colon$colon<TC;Lshapeless/$colon$colon<TD;Lshapeless/$colon$colon<TE;Lshapeless/$colon$colon<TF;Lshapeless/HNil;>;>;>;>;>;>;>;)Lscala/Function6<TA;TB;TC;TD;TE;TF;TRes;>;
    MethodParameters:
      Name                           Flags
      cse                            final

  public <Fn extends shapeless.Poly, A extends java.lang.Object, B extends java.lang.Object, C extends java.lang.Object, D extends java.lang.Object, E extends java.lang.Object, F extends java.lang.Object, G extends java.lang.Object, Res extends java.lang.Object> scala.Function7<A, B, C, D, E, F, G, Res> inst7(shapeless.PolyDefns$Case<Fn, shapeless.$colon$colon<A, shapeless.$colon$colon<B, shapeless.$colon$colon<C, shapeless.$colon$colon<D, shapeless.$colon$colon<E, shapeless.$colon$colon<F, shapeless.$colon$colon<G, shapeless.HNil>>>>>>>>);
    descriptor: (Lshapeless/PolyDefns$Case;)Lscala/Function7;
    flags: (0x0001) ACC_PUBLIC
    Code:
      stack=2, locals=2, args_size=2
         0: aload_0
         1: aload_1
         2: invokestatic  #82                 // InterfaceMethod shapeless/CaseInst.inst7$:(Lshapeless/CaseInst;Lshapeless/PolyDefns$Case;)Lscala/Function7;
         5: areturn
      LineNumberTable:
        line 42: 0
      LocalVariableTable:
        Start  Length  Slot  Name   Signature
            0       6     0  this   Lshapeless/PolyDefns$Case$;
            0       6     1   cse   Lshapeless/PolyDefns$Case;
    Signature: #78                          // <Fn::Lshapeless/Poly;A:Ljava/lang/Object;B:Ljava/lang/Object;C:Ljava/lang/Object;D:Ljava/lang/Object;E:Ljava/lang/Object;F:Ljava/lang/Object;G:Ljava/lang/Object;Res:Ljava/lang/Object;>(Lshapeless/PolyDefns$Case<TFn;Lshapeless/$colon$colon<TA;Lshapeless/$colon$colon<TB;Lshapeless/$colon$colon<TC;Lshapeless/$colon$colon<TD;Lshapeless/$colon$colon<TE;Lshapeless/$colon$colon<TF;Lshapeless/$colon$colon<TG;Lshapeless/HNil;>;>;>;>;>;>;>;>;)Lscala/Function7<TA;TB;TC;TD;TE;TF;TG;TRes;>;
    MethodParameters:
      Name                           Flags
      cse                            final

  public <Fn extends shapeless.Poly, A extends java.lang.Object, B extends java.lang.Object, C extends java.lang.Object, D extends java.lang.Object, E extends java.lang.Object, F extends java.lang.Object, G extends java.lang.Object, H extends java.lang.Object, Res extends java.lang.Object> scala.Function8<A, B, C, D, E, F, G, H, Res> inst8(shapeless.PolyDefns$Case<Fn, shapeless.$colon$colon<A, shapeless.$colon$colon<B, shapeless.$colon$colon<C, shapeless.$colon$colon<D, shapeless.$colon$colon<E, shapeless.$colon$colon<F, shapeless.$colon$colon<G, shapeless.$colon$colon<H, shapeless.HNil>>>>>>>>>);
    descriptor: (Lshapeless/PolyDefns$Case;)Lscala/Function8;
    flags: (0x0001) ACC_PUBLIC
    Code:
      stack=2, locals=2, args_size=2
         0: aload_0
         1: aload_1
         2: invokestatic  #89                 // InterfaceMethod shapeless/CaseInst.inst8$:(Lshapeless/CaseInst;Lshapeless/PolyDefns$Case;)Lscala/Function8;
         5: areturn
      LineNumberTable:
        line 42: 0
      LocalVariableTable:
        Start  Length  Slot  Name   Signature
            0       6     0  this   Lshapeless/PolyDefns$Case$;
            0       6     1   cse   Lshapeless/PolyDefns$Case;
    Signature: #85                          // <Fn::Lshapeless/Poly;A:Ljava/lang/Object;B:Ljava/lang/Object;C:Ljava/lang/Object;D:Ljava/lang/Object;E:Ljava/lang/Object;F:Ljava/lang/Object;G:Ljava/lang/Object;H:Ljava/lang/Object;Res:Ljava/lang/Object;>(Lshapeless/PolyDefns$Case<TFn;Lshapeless/$colon$colon<TA;Lshapeless/$colon$colon<TB;Lshapeless/$colon$colon<TC;Lshapeless/$colon$colon<TD;Lshapeless/$colon$colon<TE;Lshapeless/$colon$colon<TF;Lshapeless/$colon$colon<TG;Lshapeless/$colon$colon<TH;Lshapeless/HNil;>;>;>;>;>;>;>;>;>;)Lscala/Function8<TA;TB;TC;TD;TE;TF;TG;TH;TRes;>;
    MethodParameters:
      Name                           Flags
      cse                            final

  public <Fn extends shapeless.Poly, A extends java.lang.Object, B extends java.lang.Object, C extends java.lang.Object, D extends java.lang.Object, E extends java.lang.Object, F extends java.lang.Object, G extends java.lang.Object, H extends java.lang.Object, I extends java.lang.Object, Res extends java.lang.Object> scala.Function9<A, B, C, D, E, F, G, H, I, Res> inst9(shapeless.PolyDefns$Case<Fn, shapeless.$colon$colon<A, shapeless.$colon$colon<B, shapeless.$colon$colon<C, shapeless.$colon$colon<D, shapeless.$colon$colon<E, shapeless.$colon$colon<F, shapeless.$colon$colon<G, shapeless.$colon$colon<H, shapeless.$colon$colon<I, shapeless.HNil>>>>>>>>>>);
    descriptor: (Lshapeless/PolyDefns$Case;)Lscala/Function9;
    flags: (0x0001) ACC_PUBLIC
    Code:
      stack=2, locals=2, args_size=2
         0: aload_0
         1: aload_1
         2: invokestatic  #96                 // InterfaceMethod shapeless/CaseInst.inst9$:(Lshapeless/CaseInst;Lshapeless/PolyDefns$Case;)Lscala/Function9;
         5: areturn
      LineNumberTable:
        line 42: 0
      LocalVariableTable:
        Start  Length  Slot  Name   Signature
            0       6     0  this   Lshapeless/PolyDefns$Case$;
            0       6     1   cse   Lshapeless/PolyDefns$Case;
    Signature: #92                          // <Fn::Lshapeless/Poly;A:Ljava/lang/Object;B:Ljava/lang/Object;C:Ljava/lang/Object;D:Ljava/lang/Object;E:Ljava/lang/Object;F:Ljava/lang/Object;G:Ljava/lang/Object;H:Ljava/lang/Object;I:Ljava/lang/Object;Res:Ljava/lang/Object;>(Lshapeless/PolyDefns$Case<TFn;Lshapeless/$colon$colon<TA;Lshapeless/$colon$colon<TB;Lshapeless/$colon$colon<TC;Lshapeless/$colon$colon<TD;Lshapeless/$colon$colon<TE;Lshapeless/$colon$colon<TF;Lshapeless/$colon$colon<TG;Lshapeless/$colon$colon<TH;Lshapeless/$colon$colon<TI;Lshapeless/HNil;>;>;>;>;>;>;>;>;>;>;)Lscala/Function9<TA;TB;TC;TD;TE;TF;TG;TH;TI;TRes;>;
    MethodParameters:
      Name                           Flags
      cse                            final

  public <Fn extends shapeless.Poly, A extends java.lang.Object, B extends java.lang.Object, C extends java.lang.Object, D extends java.lang.Object, E extends java.lang.Object, F extends java.lang.Object, G extends java.lang.Object, H extends java.lang.Object, I extends java.lang.Object, J extends java.lang.Object, Res extends java.lang.Object> scala.Function10<A, B, C, D, E, F, G, H, I, J, Res> inst10(shapeless.PolyDefns$Case<Fn, shapeless.$colon$colon<A, shapeless.$colon$colon<B, shapeless.$colon$colon<C, shapeless.$colon$colon<D, shapeless.$colon$colon<E, shapeless.$colon$colon<F, shapeless.$colon$colon<G, shapeless.$colon$colon<H, shapeless.$colon$colon<I, shapeless.$colon$colon<J, shapeless.HNil>>>>>>>>>>>);
    descriptor: (Lshapeless/PolyDefns$Case;)Lscala/Function10;
    flags: (0x0001) ACC_PUBLIC
    Code:
      stack=2, locals=2, args_size=2
         0: aload_0
         1: aload_1
         2: invokestatic  #103                // InterfaceMethod shapeless/CaseInst.inst10$:(Lshapeless/CaseInst;Lshapeless/PolyDefns$Case;)Lscala/Function10;
         5: areturn
      LineNumberTable:
        line 42: 0
      LocalVariableTable:
        Start  Length  Slot  Name   Signature
            0       6     0  this   Lshapeless/PolyDefns$Case$;
            0       6     1   cse   Lshapeless/PolyDefns$Case;
    Signature: #99                          // <Fn::Lshapeless/Poly;A:Ljava/lang/Object;B:Ljava/lang/Object;C:Ljava/lang/Object;D:Ljava/lang/Object;E:Ljava/lang/Object;F:Ljava/lang/Object;G:Ljava/lang/Object;H:Ljava/lang/Object;I:Ljava/lang/Object;J:Ljava/lang/Object;Res:Ljava/lang/Object;>(Lshapeless/PolyDefns$Case<TFn;Lshapeless/$colon$colon<TA;Lshapeless/$colon$colon<TB;Lshapeless/$colon$colon<TC;Lshapeless/$colon$colon<TD;Lshapeless/$colon$colon<TE;Lshapeless/$colon$colon<TF;Lshapeless/$colon$colon<TG;Lshapeless/$colon$colon<TH;Lshapeless/$colon$colon<TI;Lshapeless/$colon$colon<TJ;Lshapeless/HNil;>;>;>;>;>;>;>;>;>;>;>;)Lscala/Function10<TA;TB;TC;TD;TE;TF;TG;TH;TI;TJ;TRes;>;
    MethodParameters:
      Name                           Flags
      cse                            final

  public <Fn extends shapeless.Poly, A extends java.lang.Object, B extends java.lang.Object, C extends java.lang.Object, D extends java.lang.Object, E extends java.lang.Object, F extends java.lang.Object, G extends java.lang.Object, H extends java.lang.Object, I extends java.lang.Object, J extends java.lang.Object, K extends java.lang.Object, Res extends java.lang.Object> scala.Function11<A, B, C, D, E, F, G, H, I, J, K, Res> inst11(shapeless.PolyDefns$Case<Fn, shapeless.$colon$colon<A, shapeless.$colon$colon<B, shapeless.$colon$colon<C, shapeless.$colon$colon<D, shapeless.$colon$colon<E, shapeless.$colon$colon<F, shapeless.$colon$colon<G, shapeless.$colon$colon<H, shapeless.$colon$colon<I, shapeless.$colon$colon<J, shapeless.$colon$colon<K, shapeless.HNil>>>>>>>>>>>>);
    descriptor: (Lshapeless/PolyDefns$Case;)Lscala/Function11;
    flags: (0x0001) ACC_PUBLIC
    Code:
      stack=2, locals=2, args_size=2
         0: aload_0
         1: aload_1
         2: invokestatic  #110                // InterfaceMethod shapeless/CaseInst.inst11$:(Lshapeless/CaseInst;Lshapeless/PolyDefns$Case;)Lscala/Function11;
         5: areturn
      LineNumberTable:
        line 42: 0
      LocalVariableTable:
        Start  Length  Slot  Name   Signature
            0       6     0  this   Lshapeless/PolyDefns$Case$;
            0       6     1   cse   Lshapeless/PolyDefns$Case;
    Signature: #106                         // <Fn::Lshapeless/Poly;A:Ljava/lang/Object;B:Ljava/lang/Object;C:Ljava/lang/Object;D:Ljava/lang/Object;E:Ljava/lang/Object;F:Ljava/lang/Object;G:Ljava/lang/Object;H:Ljava/lang/Object;I:Ljava/lang/Object;J:Ljava/lang/Object;K:Ljava/lang/Object;Res:Ljava/lang/Object;>(Lshapeless/PolyDefns$Case<TFn;Lshapeless/$colon$colon<TA;Lshapeless/$colon$colon<TB;Lshapeless/$colon$colon<TC;Lshapeless/$colon$colon<TD;Lshapeless/$colon$colon<TE;Lshapeless/$colon$colon<TF;Lshapeless/$colon$colon<TG;Lshapeless/$colon$colon<TH;Lshapeless/$colon$colon<TI;Lshapeless/$colon$colon<TJ;Lshapeless/$colon$colon<TK;Lshapeless/HNil;>;>;>;>;>;>;>;>;>;>;>;>;)Lscala/Function11<TA;TB;TC;TD;TE;TF;TG;TH;TI;TJ;TK;TRes;>;
    MethodParameters:
      Name                           Flags
      cse                            final

  public <Fn extends shapeless.Poly, A extends java.lang.Object, B extends java.lang.Object, C extends java.lang.Object, D extends java.lang.Object, E extends java.lang.Object, F extends java.lang.Object, G extends java.lang.Object, H extends java.lang.Object, I extends java.lang.Object, J extends java.lang.Object, K extends java.lang.Object, L extends java.lang.Object, Res extends java.lang.Object> scala.Function12<A, B, C, D, E, F, G, H, I, J, K, L, Res> inst12(shapeless.PolyDefns$Case<Fn, shapeless.$colon$colon<A, shapeless.$colon$colon<B, shapeless.$colon$colon<C, shapeless.$colon$colon<D, shapeless.$colon$colon<E, shapeless.$colon$colon<F, shapeless.$colon$colon<G, shapeless.$colon$colon<H, shapeless.$colon$colon<I, shapeless.$colon$colon<J, shapeless.$colon$colon<K, shapeless.$colon$colon<L, shapeless.HNil>>>>>>>>>>>>>);
    descriptor: (Lshapeless/PolyDefns$Case;)Lscala/Function12;
    flags: (0x0001) ACC_PUBLIC
    Code:
      stack=2, locals=2, args_size=2
         0: aload_0
         1: aload_1
         2: invokestatic  #117                // InterfaceMethod shapeless/CaseInst.inst12$:(Lshapeless/CaseInst;Lshapeless/PolyDefns$Case;)Lscala/Function12;
         5: areturn
      LineNumberTable:
        line 42: 0
      LocalVariableTable:
        Start  Length  Slot  Name   Signature
            0       6     0  this   Lshapeless/PolyDefns$Case$;
            0       6     1   cse   Lshapeless/PolyDefns$Case;
    Signature: #113                         // <Fn::Lshapeless/Poly;A:Ljava/lang/Object;B:Ljava/lang/Object;C:Ljava/lang/Object;D:Ljava/lang/Object;E:Ljava/lang/Object;F:Ljava/lang/Object;G:Ljava/lang/Object;H:Ljava/lang/Object;I:Ljava/lang/Object;J:Ljava/lang/Object;K:Ljava/lang/Object;L:Ljava/lang/Object;Res:Ljava/lang/Object;>(Lshapeless/PolyDefns$Case<TFn;Lshapeless/$colon$colon<TA;Lshapeless/$colon$colon<TB;Lshapeless/$colon$colon<TC;Lshapeless/$colon$colon<TD;Lshapeless/$colon$colon<TE;Lshapeless/$colon$colon<TF;Lshapeless/$colon$colon<TG;Lshapeless/$colon$colon<TH;Lshapeless/$colon$colon<TI;Lshapeless/$colon$colon<TJ;Lshapeless/$colon$colon<TK;Lshapeless/$colon$colon<TL;Lshapeless/HNil;>;>;>;>;>;>;>;>;>;>;>;>;>;)Lscala/Function12<TA;TB;TC;TD;TE;TF;TG;TH;TI;TJ;TK;TL;TRes;>;
    MethodParameters:
      Name                           Flags
      cse                            final

  public <Fn extends shapeless.Poly, A extends java.lang.Object, B extends java.lang.Object, C extends java.lang.Object, D extends java.lang.Object, E extends java.lang.Object, F extends java.lang.Object, G extends java.lang.Object, H extends java.lang.Object, I extends java.lang.Object, J extends java.lang.Object, K extends java.lang.Object, L extends java.lang.Object, M extends java.lang.Object, Res extends java.lang.Object> scala.Function13<A, B, C, D, E, F, G, H, I, J, K, L, M, Res> inst13(shapeless.PolyDefns$Case<Fn, shapeless.$colon$colon<A, shapeless.$colon$colon<B, shapeless.$colon$colon<C, shapeless.$colon$colon<D, shapeless.$colon$colon<E, shapeless.$colon$colon<F, shapeless.$colon$colon<G, shapeless.$colon$colon<H, shapeless.$colon$colon<I, shapeless.$colon$colon<J, shapeless.$colon$colon<K, shapeless.$colon$colon<L, shapeless.$colon$colon<M, shapeless.HNil>>>>>>>>>>>>>>);
    descriptor: (Lshapeless/PolyDefns$Case;)Lscala/Function13;
    flags: (0x0001) ACC_PUBLIC
    Code:
      stack=2, locals=2, args_size=2
         0: aload_0
         1: aload_1
         2: invokestatic  #124                // InterfaceMethod shapeless/CaseInst.inst13$:(Lshapeless/CaseInst;Lshapeless/PolyDefns$Case;)Lscala/Function13;
         5: areturn
      LineNumberTable:
        line 42: 0
      LocalVariableTable:
        Start  Length  Slot  Name   Signature
            0       6     0  this   Lshapeless/PolyDefns$Case$;
            0       6     1   cse   Lshapeless/PolyDefns$Case;
    Signature: #120                         // <Fn::Lshapeless/Poly;A:Ljava/lang/Object;B:Ljava/lang/Object;C:Ljava/lang/Object;D:Ljava/lang/Object;E:Ljava/lang/Object;F:Ljava/lang/Object;G:Ljava/lang/Object;H:Ljava/lang/Object;I:Ljava/lang/Object;J:Ljava/lang/Object;K:Ljava/lang/Object;L:Ljava/lang/Object;M:Ljava/lang/Object;Res:Ljava/lang/Object;>(Lshapeless/PolyDefns$Case<TFn;Lshapeless/$colon$colon<TA;Lshapeless/$colon$colon<TB;Lshapeless/$colon$colon<TC;Lshapeless/$colon$colon<TD;Lshapeless/$colon$colon<TE;Lshapeless/$colon$colon<TF;Lshapeless/$colon$colon<TG;Lshapeless/$colon$colon<TH;Lshapeless/$colon$colon<TI;Lshapeless/$colon$colon<TJ;Lshapeless/$colon$colon<TK;Lshapeless/$colon$colon<TL;Lshapeless/$colon$colon<TM;Lshapeless/HNil;>;>;>;>;>;>;>;>;>;>;>;>;>;>;)Lscala/Function13<TA;TB;TC;TD;TE;TF;TG;TH;TI;TJ;TK;TL;TM;TRes;>;
    MethodParameters:
      Name                           Flags
      cse                            final

  public <Fn extends shapeless.Poly, A extends java.lang.Object, B extends java.lang.Object, C extends java.lang.Object, D extends java.lang.Object, E extends java.lang.Object, F extends java.lang.Object, G extends java.lang.Object, H extends java.lang.Object, I extends java.lang.Object, J extends java.lang.Object, K extends java.lang.Object, L extends java.lang.Object, M extends java.lang.Object, N extends java.lang.Object, Res extends java.lang.Object> scala.Function14<A, B, C, D, E, F, G, H, I, J, K, L, M, N, Res> inst14(shapeless.PolyDefns$Case<Fn, shapeless.$colon$colon<A, shapeless.$colon$colon<B, shapeless.$colon$colon<C, shapeless.$colon$colon<D, shapeless.$colon$colon<E, shapeless.$colon$colon<F, shapeless.$colon$colon<G, shapeless.$colon$colon<H, shapeless.$colon$colon<I, shapeless.$colon$colon<J, shapeless.$colon$colon<K, shapeless.$colon$colon<L, shapeless.$colon$colon<M, shapeless.$colon$colon<N, shapeless.HNil>>>>>>>>>>>>>>>);
    descriptor: (Lshapeless/PolyDefns$Case;)Lscala/Function14;
    flags: (0x0001) ACC_PUBLIC
    Code:
      stack=2, locals=2, args_size=2
         0: aload_0
         1: aload_1
         2: invokestatic  #131                // InterfaceMethod shapeless/CaseInst.inst14$:(Lshapeless/CaseInst;Lshapeless/PolyDefns$Case;)Lscala/Function14;
         5: areturn
      LineNumberTable:
        line 42: 0
      LocalVariableTable:
        Start  Length  Slot  Name   Signature
            0       6     0  this   Lshapeless/PolyDefns$Case$;
            0       6     1   cse   Lshapeless/PolyDefns$Case;
    Signature: #127                         // <Fn::Lshapeless/Poly;A:Ljava/lang/Object;B:Ljava/lang/Object;C:Ljava/lang/Object;D:Ljava/lang/Object;E:Ljava/lang/Object;F:Ljava/lang/Object;G:Ljava/lang/Object;H:Ljava/lang/Object;I:Ljava/lang/Object;J:Ljava/lang/Object;K:Ljava/lang/Object;L:Ljava/lang/Object;M:Ljava/lang/Object;N:Ljava/lang/Object;Res:Ljava/lang/Object;>(Lshapeless/PolyDefns$Case<TFn;Lshapeless/$colon$colon<TA;Lshapeless/$colon$colon<TB;Lshapeless/$colon$colon<TC;Lshapeless/$colon$colon<TD;Lshapeless/$colon$colon<TE;Lshapeless/$colon$colon<TF;Lshapeless/$colon$colon<TG;Lshapeless/$colon$colon<TH;Lshapeless/$colon$colon<TI;Lshapeless/$colon$colon<TJ;Lshapeless/$colon$colon<TK;Lshapeless/$colon$colon<TL;Lshapeless/$colon$colon<TM;Lshapeless/$colon$colon<TN;Lshapeless/HNil;>;>;>;>;>;>;>;>;>;>;>;>;>;>;>;)Lscala/Function14<TA;TB;TC;TD;TE;TF;TG;TH;TI;TJ;TK;TL;TM;TN;TRes;>;
    MethodParameters:
      Name                           Flags
      cse                            final

  public <Fn extends shapeless.Poly, A extends java.lang.Object, B extends java.lang.Object, C extends java.lang.Object, D extends java.lang.Object, E extends java.lang.Object, F extends java.lang.Object, G extends java.lang.Object, H extends java.lang.Object, I extends java.lang.Object, J extends java.lang.Object, K extends java.lang.Object, L extends java.lang.Object, M extends java.lang.Object, N extends java.lang.Object, O extends java.lang.Object, Res extends java.lang.Object> scala.Function15<A, B, C, D, E, F, G, H, I, J, K, L, M, N, O, Res> inst15(shapeless.PolyDefns$Case<Fn, shapeless.$colon$colon<A, shapeless.$colon$colon<B, shapeless.$colon$colon<C, shapeless.$colon$colon<D, shapeless.$colon$colon<E, shapeless.$colon$colon<F, shapeless.$colon$colon<G, shapeless.$colon$colon<H, shapeless.$colon$colon<I, shapeless.$colon$colon<J, shapeless.$colon$colon<K, shapeless.$colon$colon<L, shapeless.$colon$colon<M, shapeless.$colon$colon<N, shapeless.$colon$colon<O, shapeless.HNil>>>>>>>>>>>>>>>>);
    descriptor: (Lshapeless/PolyDefns$Case;)Lscala/Function15;
    flags: (0x0001) ACC_PUBLIC
    Code:
      stack=2, locals=2, args_size=2
         0: aload_0
         1: aload_1
         2: invokestatic  #138                // InterfaceMethod shapeless/CaseInst.inst15$:(Lshapeless/CaseInst;Lshapeless/PolyDefns$Case;)Lscala/Function15;
         5: areturn
      LineNumberTable:
        line 42: 0
      LocalVariableTable:
        Start  Length  Slot  Name   Signature
            0       6     0  this   Lshapeless/PolyDefns$Case$;
            0       6     1   cse   Lshapeless/PolyDefns$Case;
    Signature: #134                         // <Fn::Lshapeless/Poly;A:Ljava/lang/Object;B:Ljava/lang/Object;C:Ljava/lang/Object;D:Ljava/lang/Object;E:Ljava/lang/Object;F:Ljava/lang/Object;G:Ljava/lang/Object;H:Ljava/lang/Object;I:Ljava/lang/Object;J:Ljava/lang/Object;K:Ljava/lang/Object;L:Ljava/lang/Object;M:Ljava/lang/Object;N:Ljava/lang/Object;O:Ljava/lang/Object;Res:Ljava/lang/Object;>(Lshapeless/PolyDefns$Case<TFn;Lshapeless/$colon$colon<TA;Lshapeless/$colon$colon<TB;Lshapeless/$colon$colon<TC;Lshapeless/$colon$colon<TD;Lshapeless/$colon$colon<TE;Lshapeless/$colon$colon<TF;Lshapeless/$colon$colon<TG;Lshapeless/$colon$colon<TH;Lshapeless/$colon$colon<TI;Lshapeless/$colon$colon<TJ;Lshapeless/$colon$colon<TK;Lshapeless/$colon$colon<TL;Lshapeless/$colon$colon<TM;Lshapeless/$colon$colon<TN;Lshapeless/$colon$colon<TO;Lshapeless/HNil;>;>;>;>;>;>;>;>;>;>;>;>;>;>;>;>;)Lscala/Function15<TA;TB;TC;TD;TE;TF;TG;TH;TI;TJ;TK;TL;TM;TN;TO;TRes;>;
    MethodParameters:
      Name                           Flags
      cse                            final

  public <Fn extends shapeless.Poly, A extends java.lang.Object, B extends java.lang.Object, C extends java.lang.Object, D extends java.lang.Object, E extends java.lang.Object, F extends java.lang.Object, G extends java.lang.Object, H extends java.lang.Object, I extends java.lang.Object, J extends java.lang.Object, K extends java.lang.Object, L extends java.lang.Object, M extends java.lang.Object, N extends java.lang.Object, O extends java.lang.Object, P extends java.lang.Object, Res extends java.lang.Object> scala.Function16<A, B, C, D, E, F, G, H, I, J, K, L, M, N, O, P, Res> inst16(shapeless.PolyDefns$Case<Fn, shapeless.$colon$colon<A, shapeless.$colon$colon<B, shapeless.$colon$colon<C, shapeless.$colon$colon<D, shapeless.$colon$colon<E, shapeless.$colon$colon<F, shapeless.$colon$colon<G, shapeless.$colon$colon<H, shapeless.$colon$colon<I, shapeless.$colon$colon<J, shapeless.$colon$colon<K, shapeless.$colon$colon<L, shapeless.$colon$colon<M, shapeless.$colon$colon<N, shapeless.$colon$colon<O, shapeless.$colon$colon<P, shapeless.HNil>>>>>>>>>>>>>>>>>);
    descriptor: (Lshapeless/PolyDefns$Case;)Lscala/Function16;
    flags: (0x0001) ACC_PUBLIC
    Code:
      stack=2, locals=2, args_size=2
         0: aload_0
         1: aload_1
         2: invokestatic  #145                // InterfaceMethod shapeless/CaseInst.inst16$:(Lshapeless/CaseInst;Lshapeless/PolyDefns$Case;)Lscala/Function16;
         5: areturn
      LineNumberTable:
        line 42: 0
      LocalVariableTable:
        Start  Length  Slot  Name   Signature
            0       6     0  this   Lshapeless/PolyDefns$Case$;
            0       6     1   cse   Lshapeless/PolyDefns$Case;
    Signature: #141                         // <Fn::Lshapeless/Poly;A:Ljava/lang/Object;B:Ljava/lang/Object;C:Ljava/lang/Object;D:Ljava/lang/Object;E:Ljava/lang/Object;F:Ljava/lang/Object;G:Ljava/lang/Object;H:Ljava/lang/Object;I:Ljava/lang/Object;J:Ljava/lang/Object;K:Ljava/lang/Object;L:Ljava/lang/Object;M:Ljava/lang/Object;N:Ljava/lang/Object;O:Ljava/lang/Object;P:Ljava/lang/Object;Res:Ljava/lang/Object;>(Lshapeless/PolyDefns$Case<TFn;Lshapeless/$colon$colon<TA;Lshapeless/$colon$colon<TB;Lshapeless/$colon$colon<TC;Lshapeless/$colon$colon<TD;Lshapeless/$colon$colon<TE;Lshapeless/$colon$colon<TF;Lshapeless/$colon$colon<TG;Lshapeless/$colon$colon<TH;Lshapeless/$colon$colon<TI;Lshapeless/$colon$colon<TJ;Lshapeless/$colon$colon<TK;Lshapeless/$colon$colon<TL;Lshapeless/$colon$colon<TM;Lshapeless/$colon$colon<TN;Lshapeless/$colon$colon<TO;Lshapeless/$colon$colon<TP;Lshapeless/HNil;>;>;>;>;>;>;>;>;>;>;>;>;>;>;>;>;>;)Lscala/Function16<TA;TB;TC;TD;TE;TF;TG;TH;TI;TJ;TK;TL;TM;TN;TO;TP;TRes;>;
    MethodParameters:
      Name                           Flags
      cse                            final

  public <Fn extends shapeless.Poly, A extends java.lang.Object, B extends java.lang.Object, C extends java.lang.Object, D extends java.lang.Object, E extends java.lang.Object, F extends java.lang.Object, G extends java.lang.Object, H extends java.lang.Object, I extends java.lang.Object, J extends java.lang.Object, K extends java.lang.Object, L extends java.lang.Object, M extends java.lang.Object, N extends java.lang.Object, O extends java.lang.Object, P extends java.lang.Object, Q extends java.lang.Object, Res extends java.lang.Object> scala.Function17<A, B, C, D, E, F, G, H, I, J, K, L, M, N, O, P, Q, Res> inst17(shapeless.PolyDefns$Case<Fn, shapeless.$colon$colon<A, shapeless.$colon$colon<B, shapeless.$colon$colon<C, shapeless.$colon$colon<D, shapeless.$colon$colon<E, shapeless.$colon$colon<F, shapeless.$colon$colon<G, shapeless.$colon$colon<H, shapeless.$colon$colon<I, shapeless.$colon$colon<J, shapeless.$colon$colon<K, shapeless.$colon$colon<L, shapeless.$colon$colon<M, shapeless.$colon$colon<N, shapeless.$colon$colon<O, shapeless.$colon$colon<P, shapeless.$colon$colon<Q, shapeless.HNil>>>>>>>>>>>>>>>>>>);
    descriptor: (Lshapeless/PolyDefns$Case;)Lscala/Function17;
    flags: (0x0001) ACC_PUBLIC
    Code:
      stack=2, locals=2, args_size=2
         0: aload_0
         1: aload_1
         2: invokestatic  #152                // InterfaceMethod shapeless/CaseInst.inst17$:(Lshapeless/CaseInst;Lshapeless/PolyDefns$Case;)Lscala/Function17;
         5: areturn
      LineNumberTable:
        line 42: 0
      LocalVariableTable:
        Start  Length  Slot  Name   Signature
            0       6     0  this   Lshapeless/PolyDefns$Case$;
            0       6     1   cse   Lshapeless/PolyDefns$Case;
    Signature: #148                         // <Fn::Lshapeless/Poly;A:Ljava/lang/Object;B:Ljava/lang/Object;C:Ljava/lang/Object;D:Ljava/lang/Object;E:Ljava/lang/Object;F:Ljava/lang/Object;G:Ljava/lang/Object;H:Ljava/lang/Object;I:Ljava/lang/Object;J:Ljava/lang/Object;K:Ljava/lang/Object;L:Ljava/lang/Object;M:Ljava/lang/Object;N:Ljava/lang/Object;O:Ljava/lang/Object;P:Ljava/lang/Object;Q:Ljava/lang/Object;Res:Ljava/lang/Object;>(Lshapeless/PolyDefns$Case<TFn;Lshapeless/$colon$colon<TA;Lshapeless/$colon$colon<TB;Lshapeless/$colon$colon<TC;Lshapeless/$colon$colon<TD;Lshapeless/$colon$colon<TE;Lshapeless/$colon$colon<TF;Lshapeless/$colon$colon<TG;Lshapeless/$colon$colon<TH;Lshapeless/$colon$colon<TI;Lshapeless/$colon$colon<TJ;Lshapeless/$colon$colon<TK;Lshapeless/$colon$colon<TL;Lshapeless/$colon$colon<TM;Lshapeless/$colon$colon<TN;Lshapeless/$colon$colon<TO;Lshapeless/$colon$colon<TP;Lshapeless/$colon$colon<TQ;Lshapeless/HNil;>;>;>;>;>;>;>;>;>;>;>;>;>;>;>;>;>;>;)Lscala/Function17<TA;TB;TC;TD;TE;TF;TG;TH;TI;TJ;TK;TL;TM;TN;TO;TP;TQ;TRes;>;
    MethodParameters:
      Name                           Flags
      cse                            final

  public <Fn extends shapeless.Poly, A extends java.lang.Object, B extends java.lang.Object, C extends java.lang.Object, D extends java.lang.Object, E extends java.lang.Object, F extends java.lang.Object, G extends java.lang.Object, H extends java.lang.Object, I extends java.lang.Object, J extends java.lang.Object, K extends java.lang.Object, L extends java.lang.Object, M extends java.lang.Object, N extends java.lang.Object, O extends java.lang.Object, P extends java.lang.Object, Q extends java.lang.Object, R extends java.lang.Object, Res extends java.lang.Object> scala.Function18<A, B, C, D, E, F, G, H, I, J, K, L, M, N, O, P, Q, R, Res> inst18(shapeless.PolyDefns$Case<Fn, shapeless.$colon$colon<A, shapeless.$colon$colon<B, shapeless.$colon$colon<C, shapeless.$colon$colon<D, shapeless.$colon$colon<E, shapeless.$colon$colon<F, shapeless.$colon$colon<G, shapeless.$colon$colon<H, shapeless.$colon$colon<I, shapeless.$colon$colon<J, shapeless.$colon$colon<K, shapeless.$colon$colon<L, shapeless.$colon$colon<M, shapeless.$colon$colon<N, shapeless.$colon$colon<O, shapeless.$colon$colon<P, shapeless.$colon$colon<Q, shapeless.$colon$colon<R, shapeless.HNil>>>>>>>>>>>>>>>>>>>);
    descriptor: (Lshapeless/PolyDefns$Case;)Lscala/Function18;
    flags: (0x0001) ACC_PUBLIC
    Code:
      stack=2, locals=2, args_size=2
         0: aload_0
         1: aload_1
         2: invokestatic  #159                // InterfaceMethod shapeless/CaseInst.inst18$:(Lshapeless/CaseInst;Lshapeless/PolyDefns$Case;)Lscala/Function18;
         5: areturn
      LineNumberTable:
        line 42: 0
      LocalVariableTable:
        Start  Length  Slot  Name   Signature
            0       6     0  this   Lshapeless/PolyDefns$Case$;
            0       6     1   cse   Lshapeless/PolyDefns$Case;
    Signature: #155                         // <Fn::Lshapeless/Poly;A:Ljava/lang/Object;B:Ljava/lang/Object;C:Ljava/lang/Object;D:Ljava/lang/Object;E:Ljava/lang/Object;F:Ljava/lang/Object;G:Ljava/lang/Object;H:Ljava/lang/Object;I:Ljava/lang/Object;J:Ljava/lang/Object;K:Ljava/lang/Object;L:Ljava/lang/Object;M:Ljava/lang/Object;N:Ljava/lang/Object;O:Ljava/lang/Object;P:Ljava/lang/Object;Q:Ljava/lang/Object;R:Ljava/lang/Object;Res:Ljava/lang/Object;>(Lshapeless/PolyDefns$Case<TFn;Lshapeless/$colon$colon<TA;Lshapeless/$colon$colon<TB;Lshapeless/$colon$colon<TC;Lshapeless/$colon$colon<TD;Lshapeless/$colon$colon<TE;Lshapeless/$colon$colon<TF;Lshapeless/$colon$colon<TG;Lshapeless/$colon$colon<TH;Lshapeless/$colon$colon<TI;Lshapeless/$colon$colon<TJ;Lshapeless/$colon$colon<TK;Lshapeless/$colon$colon<TL;Lshapeless/$colon$colon<TM;Lshapeless/$colon$colon<TN;Lshapeless/$colon$colon<TO;Lshapeless/$colon$colon<TP;Lshapeless/$colon$colon<TQ;Lshapeless/$colon$colon<TR;Lshapeless/HNil;>;>;>;>;>;>;>;>;>;>;>;>;>;>;>;>;>;>;>;)Lscala/Function18<TA;TB;TC;TD;TE;TF;TG;TH;TI;TJ;TK;TL;TM;TN;TO;TP;TQ;TR;TRes;>;
    MethodParameters:
      Name                           Flags
      cse                            final

  public <Fn extends shapeless.Poly, A extends java.lang.Object, B extends java.lang.Object, C extends java.lang.Object, D extends java.lang.Object, E extends java.lang.Object, F extends java.lang.Object, G extends java.lang.Object, H extends java.lang.Object, I extends java.lang.Object, J extends java.lang.Object, K extends java.lang.Object, L extends java.lang.Object, M extends java.lang.Object, N extends java.lang.Object, O extends java.lang.Object, P extends java.lang.Object, Q extends java.lang.Object, R extends java.lang.Object, S extends java.lang.Object, Res extends java.lang.Object> scala.Function19<A, B, C, D, E, F, G, H, I, J, K, L, M, N, O, P, Q, R, S, Res> inst19(shapeless.PolyDefns$Case<Fn, shapeless.$colon$colon<A, shapeless.$colon$colon<B, shapeless.$colon$colon<C, shapeless.$colon$colon<D, shapeless.$colon$colon<E, shapeless.$colon$colon<F, shapeless.$colon$colon<G, shapeless.$colon$colon<H, shapeless.$colon$colon<I, shapeless.$colon$colon<J, shapeless.$colon$colon<K, shapeless.$colon$colon<L, shapeless.$colon$colon<M, shapeless.$colon$colon<N, shapeless.$colon$colon<O, shapeless.$colon$colon<P, shapeless.$colon$colon<Q, shapeless.$colon$colon<R, shapeless.$colon$colon<S, shapeless.HNil>>>>>>>>>>>>>>>>>>>>);
    descriptor: (Lshapeless/PolyDefns$Case;)Lscala/Function19;
    flags: (0x0001) ACC_PUBLIC
    Code:
      stack=2, locals=2, args_size=2
         0: aload_0
         1: aload_1
         2: invokestatic  #166                // InterfaceMethod shapeless/CaseInst.inst19$:(Lshapeless/CaseInst;Lshapeless/PolyDefns$Case;)Lscala/Function19;
         5: areturn
      LineNumberTable:
        line 42: 0
      LocalVariableTable:
        Start  Length  Slot  Name   Signature
            0       6     0  this   Lshapeless/PolyDefns$Case$;
            0       6     1   cse   Lshapeless/PolyDefns$Case;
    Signature: #162                         // <Fn::Lshapeless/Poly;A:Ljava/lang/Object;B:Ljava/lang/Object;C:Ljava/lang/Object;D:Ljava/lang/Object;E:Ljava/lang/Object;F:Ljava/lang/Object;G:Ljava/lang/Object;H:Ljava/lang/Object;I:Ljava/lang/Object;J:Ljava/lang/Object;K:Ljava/lang/Object;L:Ljava/lang/Object;M:Ljava/lang/Object;N:Ljava/lang/Object;O:Ljava/lang/Object;P:Ljava/lang/Object;Q:Ljava/lang/Object;R:Ljava/lang/Object;S:Ljava/lang/Object;Res:Ljava/lang/Object;>(Lshapeless/PolyDefns$Case<TFn;Lshapeless/$colon$colon<TA;Lshapeless/$colon$colon<TB;Lshapeless/$colon$colon<TC;Lshapeless/$colon$colon<TD;Lshapeless/$colon$colon<TE;Lshapeless/$colon$colon<TF;Lshapeless/$colon$colon<TG;Lshapeless/$colon$colon<TH;Lshapeless/$colon$colon<TI;Lshapeless/$colon$colon<TJ;Lshapeless/$colon$colon<TK;Lshapeless/$colon$colon<TL;Lshapeless/$colon$colon<TM;Lshapeless/$colon$colon<TN;Lshapeless/$colon$colon<TO;Lshapeless/$colon$colon<TP;Lshapeless/$colon$colon<TQ;Lshapeless/$colon$colon<TR;Lshapeless/$colon$colon<TS;Lshapeless/HNil;>;>;>;>;>;>;>;>;>;>;>;>;>;>;>;>;>;>;>;>;)Lscala/Function19<TA;TB;TC;TD;TE;TF;TG;TH;TI;TJ;TK;TL;TM;TN;TO;TP;TQ;TR;TS;TRes;>;
    MethodParameters:
      Name                           Flags
      cse                            final

  public <Fn extends shapeless.Poly, A extends java.lang.Object, B extends java.lang.Object, C extends java.lang.Object, D extends java.lang.Object, E extends java.lang.Object, F extends java.lang.Object, G extends java.lang.Object, H extends java.lang.Object, I extends java.lang.Object, J extends java.lang.Object, K extends java.lang.Object, L extends java.lang.Object, M extends java.lang.Object, N extends java.lang.Object, O extends java.lang.Object, P extends java.lang.Object, Q extends java.lang.Object, R extends java.lang.Object, S extends java.lang.Object, T extends java.lang.Object, Res extends java.lang.Object> scala.Function20<A, B, C, D, E, F, G, H, I, J, K, L, M, N, O, P, Q, R, S, T, Res> inst20(shapeless.PolyDefns$Case<Fn, shapeless.$colon$colon<A, shapeless.$colon$colon<B, shapeless.$colon$colon<C, shapeless.$colon$colon<D, shapeless.$colon$colon<E, shapeless.$colon$colon<F, shapeless.$colon$colon<G, shapeless.$colon$colon<H, shapeless.$colon$colon<I, shapeless.$colon$colon<J, shapeless.$colon$colon<K, shapeless.$colon$colon<L, shapeless.$colon$colon<M, shapeless.$colon$colon<N, shapeless.$colon$colon<O, shapeless.$colon$colon<P, shapeless.$colon$colon<Q, shapeless.$colon$colon<R, shapeless.$colon$colon<S, shapeless.$colon$colon<T, shapeless.HNil>>>>>>>>>>>>>>>>>>>>>);
    descriptor: (Lshapeless/PolyDefns$Case;)Lscala/Function20;
    flags: (0x0001) ACC_PUBLIC
    Code:
      stack=2, locals=2, args_size=2
         0: aload_0
         1: aload_1
         2: invokestatic  #173                // InterfaceMethod shapeless/CaseInst.inst20$:(Lshapeless/CaseInst;Lshapeless/PolyDefns$Case;)Lscala/Function20;
         5: areturn
      LineNumberTable:
        line 42: 0
      LocalVariableTable:
        Start  Length  Slot  Name   Signature
            0       6     0  this   Lshapeless/PolyDefns$Case$;
            0       6     1   cse   Lshapeless/PolyDefns$Case;
    Signature: #169                         // <Fn::Lshapeless/Poly;A:Ljava/lang/Object;B:Ljava/lang/Object;C:Ljava/lang/Object;D:Ljava/lang/Object;E:Ljava/lang/Object;F:Ljava/lang/Object;G:Ljava/lang/Object;H:Ljava/lang/Object;I:Ljava/lang/Object;J:Ljava/lang/Object;K:Ljava/lang/Object;L:Ljava/lang/Object;M:Ljava/lang/Object;N:Ljava/lang/Object;O:Ljava/lang/Object;P:Ljava/lang/Object;Q:Ljava/lang/Object;R:Ljava/lang/Object;S:Ljava/lang/Object;T:Ljava/lang/Object;Res:Ljava/lang/Object;>(Lshapeless/PolyDefns$Case<TFn;Lshapeless/$colon$colon<TA;Lshapeless/$colon$colon<TB;Lshapeless/$colon$colon<TC;Lshapeless/$colon$colon<TD;Lshapeless/$colon$colon<TE;Lshapeless/$colon$colon<TF;Lshapeless/$colon$colon<TG;Lshapeless/$colon$colon<TH;Lshapeless/$colon$colon<TI;Lshapeless/$colon$colon<TJ;Lshapeless/$colon$colon<TK;Lshapeless/$colon$colon<TL;Lshapeless/$colon$colon<TM;Lshapeless/$colon$colon<TN;Lshapeless/$colon$colon<TO;Lshapeless/$colon$colon<TP;Lshapeless/$colon$colon<TQ;Lshapeless/$colon$colon<TR;Lshapeless/$colon$colon<TS;Lshapeless/$colon$colon<TT;Lshapeless/HNil;>;>;>;>;>;>;>;>;>;>;>;>;>;>;>;>;>;>;>;>;>;)Lscala/Function20<TA;TB;TC;TD;TE;TF;TG;TH;TI;TJ;TK;TL;TM;TN;TO;TP;TQ;TR;TS;TT;TRes;>;
    MethodParameters:
      Name                           Flags
      cse                            final

  public <Fn extends shapeless.Poly, A extends java.lang.Object, B extends java.lang.Object, C extends java.lang.Object, D extends java.lang.Object, E extends java.lang.Object, F extends java.lang.Object, G extends java.lang.Object, H extends java.lang.Object, I extends java.lang.Object, J extends java.lang.Object, K extends java.lang.Object, L extends java.lang.Object, M extends java.lang.Object, N extends java.lang.Object, O extends java.lang.Object, P extends java.lang.Object, Q extends java.lang.Object, R extends java.lang.Object, S extends java.lang.Object, T extends java.lang.Object, U extends java.lang.Object, Res extends java.lang.Object> scala.Function21<A, B, C, D, E, F, G, H, I, J, K, L, M, N, O, P, Q, R, S, T, U, Res> inst21(shapeless.PolyDefns$Case<Fn, shapeless.$colon$colon<A, shapeless.$colon$colon<B, shapeless.$colon$colon<C, shapeless.$colon$colon<D, shapeless.$colon$colon<E, shapeless.$colon$colon<F, shapeless.$colon$colon<G, shapeless.$colon$colon<H, shapeless.$colon$colon<I, shapeless.$colon$colon<J, shapeless.$colon$colon<K, shapeless.$colon$colon<L, shapeless.$colon$colon<M, shapeless.$colon$colon<N, shapeless.$colon$colon<O, shapeless.$colon$colon<P, shapeless.$colon$colon<Q, shapeless.$colon$colon<R, shapeless.$colon$colon<S, shapeless.$colon$colon<T, shapeless.$colon$colon<U, shapeless.HNil>>>>>>>>>>>>>>>>>>>>>>);
    descriptor: (Lshapeless/PolyDefns$Case;)Lscala/Function21;
    flags: (0x0001) ACC_PUBLIC
    Code:
      stack=2, locals=2, args_size=2
         0: aload_0
         1: aload_1
         2: invokestatic  #180                // InterfaceMethod shapeless/CaseInst.inst21$:(Lshapeless/CaseInst;Lshapeless/PolyDefns$Case;)Lscala/Function21;
         5: areturn
      LineNumberTable:
        line 42: 0
      LocalVariableTable:
        Start  Length  Slot  Name   Signature
            0       6     0  this   Lshapeless/PolyDefns$Case$;
            0       6     1   cse   Lshapeless/PolyDefns$Case;
    Signature: #176                         // <Fn::Lshapeless/Poly;A:Ljava/lang/Object;B:Ljava/lang/Object;C:Ljava/lang/Object;D:Ljava/lang/Object;E:Ljava/lang/Object;F:Ljava/lang/Object;G:Ljava/lang/Object;H:Ljava/lang/Object;I:Ljava/lang/Object;J:Ljava/lang/Object;K:Ljava/lang/Object;L:Ljava/lang/Object;M:Ljava/lang/Object;N:Ljava/lang/Object;O:Ljava/lang/Object;P:Ljava/lang/Object;Q:Ljava/lang/Object;R:Ljava/lang/Object;S:Ljava/lang/Object;T:Ljava/lang/Object;U:Ljava/lang/Object;Res:Ljava/lang/Object;>(Lshapeless/PolyDefns$Case<TFn;Lshapeless/$colon$colon<TA;Lshapeless/$colon$colon<TB;Lshapeless/$colon$colon<TC;Lshapeless/$colon$colon<TD;Lshapeless/$colon$colon<TE;Lshapeless/$colon$colon<TF;Lshapeless/$colon$colon<TG;Lshapeless/$colon$colon<TH;Lshapeless/$colon$colon<TI;Lshapeless/$colon$colon<TJ;Lshapeless/$colon$colon<TK;Lshapeless/$colon$colon<TL;Lshapeless/$colon$colon<TM;Lshapeless/$colon$colon<TN;Lshapeless/$colon$colon<TO;Lshapeless/$colon$colon<TP;Lshapeless/$colon$colon<TQ;Lshapeless/$colon$colon<TR;Lshapeless/$colon$colon<TS;Lshapeless/$colon$colon<TT;Lshapeless/$colon$colon<TU;Lshapeless/HNil;>;>;>;>;>;>;>;>;>;>;>;>;>;>;>;>;>;>;>;>;>;>;)Lscala/Function21<TA;TB;TC;TD;TE;TF;TG;TH;TI;TJ;TK;TL;TM;TN;TO;TP;TQ;TR;TS;TT;TU;TRes;>;
    MethodParameters:
      Name                           Flags
      cse                            final

  public <Fn extends shapeless.Poly, A extends java.lang.Object, B extends java.lang.Object, C extends java.lang.Object, D extends java.lang.Object, E extends java.lang.Object, F extends java.lang.Object, G extends java.lang.Object, H extends java.lang.Object, I extends java.lang.Object, J extends java.lang.Object, K extends java.lang.Object, L extends java.lang.Object, M extends java.lang.Object, N extends java.lang.Object, O extends java.lang.Object, P extends java.lang.Object, Q extends java.lang.Object, R extends java.lang.Object, S extends java.lang.Object, T extends java.lang.Object, U extends java.lang.Object, V extends java.lang.Object, Res extends java.lang.Object> scala.Function22<A, B, C, D, E, F, G, H, I, J, K, L, M, N, O, P, Q, R, S, T, U, V, Res> inst22(shapeless.PolyDefns$Case<Fn, shapeless.$colon$colon<A, shapeless.$colon$colon<B, shapeless.$colon$colon<C, shapeless.$colon$colon<D, shapeless.$colon$colon<E, shapeless.$colon$colon<F, shapeless.$colon$colon<G, shapeless.$colon$colon<H, shapeless.$colon$colon<I, shapeless.$colon$colon<J, shapeless.$colon$colon<K, shapeless.$colon$colon<L, shapeless.$colon$colon<M, shapeless.$colon$colon<N, shapeless.$colon$colon<O, shapeless.$colon$colon<P, shapeless.$colon$colon<Q, shapeless.$colon$colon<R, shapeless.$colon$colon<S, shapeless.$colon$colon<T, shapeless.$colon$colon<U, shapeless.$colon$colon<V, shapeless.HNil>>>>>>>>>>>>>>>>>>>>>>>);
    descriptor: (Lshapeless/PolyDefns$Case;)Lscala/Function22;
    flags: (0x0001) ACC_PUBLIC
    Code:
      stack=2, locals=2, args_size=2
         0: aload_0
         1: aload_1
         2: invokestatic  #187                // InterfaceMethod shapeless/CaseInst.inst22$:(Lshapeless/CaseInst;Lshapeless/PolyDefns$Case;)Lscala/Function22;
         5: areturn
      LineNumberTable:
        line 42: 0
      LocalVariableTable:
        Start  Length  Slot  Name   Signature
            0       6     0  this   Lshapeless/PolyDefns$Case$;
            0       6     1   cse   Lshapeless/PolyDefns$Case;
    Signature: #183                         // <Fn::Lshapeless/Poly;A:Ljava/lang/Object;B:Ljava/lang/Object;C:Ljava/lang/Object;D:Ljava/lang/Object;E:Ljava/lang/Object;F:Ljava/lang/Object;G:Ljava/lang/Object;H:Ljava/lang/Object;I:Ljava/lang/Object;J:Ljava/lang/Object;K:Ljava/lang/Object;L:Ljava/lang/Object;M:Ljava/lang/Object;N:Ljava/lang/Object;O:Ljava/lang/Object;P:Ljava/lang/Object;Q:Ljava/lang/Object;R:Ljava/lang/Object;S:Ljava/lang/Object;T:Ljava/lang/Object;U:Ljava/lang/Object;V:Ljava/lang/Object;Res:Ljava/lang/Object;>(Lshapeless/PolyDefns$Case<TFn;Lshapeless/$colon$colon<TA;Lshapeless/$colon$colon<TB;Lshapeless/$colon$colon<TC;Lshapeless/$colon$colon<TD;Lshapeless/$colon$colon<TE;Lshapeless/$colon$colon<TF;Lshapeless/$colon$colon<TG;Lshapeless/$colon$colon<TH;Lshapeless/$colon$colon<TI;Lshapeless/$colon$colon<TJ;Lshapeless/$colon$colon<TK;Lshapeless/$colon$colon<TL;Lshapeless/$colon$colon<TM;Lshapeless/$colon$colon<TN;Lshapeless/$colon$colon<TO;Lshapeless/$colon$colon<TP;Lshapeless/$colon$colon<TQ;Lshapeless/$colon$colon<TR;Lshapeless/$colon$colon<TS;Lshapeless/$colon$colon<TT;Lshapeless/$colon$colon<TU;Lshapeless/$colon$colon<TV;Lshapeless/HNil;>;>;>;>;>;>;>;>;>;>;>;>;>;>;>;>;>;>;>;>;>;>;>;)Lscala/Function22<TA;TB;TC;TD;TE;TF;TG;TH;TI;TJ;TK;TL;TM;TN;TO;TP;TQ;TR;TS;TT;TU;TV;TRes;>;
    MethodParameters:
      Name                           Flags
      cse                            final

  public <P extends java.lang.Object, L extends shapeless.HList, R extends java.lang.Object> shapeless.PolyDefns$Case<P, L> apply(scala.Function1<L, R>);
    descriptor: (Lscala/Function1;)Lshapeless/PolyDefns$Case;
    flags: (0x0001) ACC_PUBLIC
    Code:
      stack=3, locals=2, args_size=2
         0: new           #17                 // class shapeless/PolyDefns$Case$$anon$1
         3: dup
         4: aload_1
         5: invokespecial #194                // Method shapeless/PolyDefns$Case$$anon$1."<init>":(Lscala/Function1;)V
         8: areturn
      LineNumberTable:
        line 46: 0
      LocalVariableTable:
        Start  Length  Slot  Name   Signature
            0       9     0  this   Lshapeless/PolyDefns$Case$;
            0       9     1     v   Lscala/Function1;
    Signature: #190                         // <P:Ljava/lang/Object;L::Lshapeless/HList;R:Ljava/lang/Object;>(Lscala/Function1<TL;TR;>;)Lshapeless/PolyDefns$Case<TP;TL;>;
    MethodParameters:
      Name                           Flags
      v                              final

  private java.lang.Object writeReplace();
    descriptor: ()Ljava/lang/Object;
    flags: (0x0002) ACC_PRIVATE
    Code:
      stack=3, locals=1, args_size=1
         0: new           #199                // class scala/runtime/ModuleSerializationProxy
         3: dup
         4: ldc           #2                  // class shapeless/PolyDefns$Case$
         6: invokespecial #202                // Method scala/runtime/ModuleSerializationProxy."<init>":(Ljava/lang/Class;)V
         9: areturn
      LineNumberTable:
        line 42: 0
      LocalVariableTable:
        Start  Length  Slot  Name   Signature
            0      10     0  this   Lshapeless/PolyDefns$Case$;

  public shapeless.PolyDefns$Case$();
    descriptor: ()V
    flags: (0x0001) ACC_PUBLIC
    Code:
      stack=1, locals=1, args_size=1
         0: aload_0
         1: invokespecial #203                // Method java/lang/Object."<init>":()V
         4: return
      LineNumberTable:
        line 42: 0
      LocalVariableTable:
        Start  Length  Slot  Name   Signature
            0       5     0  this   Lshapeless/PolyDefns$Case$;
}
InnerClasses:
  public static abstract #14= #11 of #13; // Case=class shapeless/PolyDefns$Case of class shapeless/PolyDefns
  public static #15= #2 of #13;           // Case$=class shapeless/PolyDefns$Case$ of class shapeless/PolyDefns
  public final #17;                       // class shapeless/PolyDefns$Case$$anon$1
SourceFile: "poly.scala"
  ScalaInlineInfo: length = 0x8B (unknown attribute)
   01 01 00 1B 00 16 00 15 01 00 BC 00 BD 01 00 1F
   00 20 01 00 61 00 62 01 00 68 00 69 01 00 6F 00
   70 01 00 76 00 77 01 00 7D 00 7E 01 00 84 00 85
   01 00 8B 00 8C 01 00 92 00 93 01 00 99 00 9A 01
   00 A0 00 A1 01 00 29 00 2A 01 00 A7 00 A8 01 00
   AE 00 AF 01 00 B5 00 B6 01 00 30 00 31 01 00 37
   00 38 01 00 3E 00 3F 01 00 45 00 46 01 00 4C 00
   4D 01 00 53 00 54 01 00 5A 00 5B 01 00 D4 00 D5
   01 00 D6 00 D5 01 00 C4 00 C5 01
  Scala: length = 0x0 (unknown attribute)

