Classfile /Users/mw/Projects/slang-braindump/.jar/jar11/assemble/slang-braindump/assemble/content/shapeless/Poly1.class
  Last modified May 29, 2022; size 2208 bytes
  SHA-256 checksum 19dfda4c1a9b89928f203092898c0cfacbd06dd9ba878b1fc657542f6c42a812
  Compiled from "polyntraits.scala"
public interface shapeless.Poly1 extends shapeless.Poly
  minor version: 0
  major version: 52
  flags: (0x0601) ACC_PUBLIC, ACC_INTERFACE, ACC_ABSTRACT
  this_class: #2                          // shapeless/Poly1
  super_class: #4                         // java/lang/Object
  interfaces: 1, fields: 0, methods: 6, attributes: 5
Constant pool:
   #1 = Utf8               shapeless/Poly1
   #2 = Class              #1             // shapeless/Poly1
   #3 = Utf8               java/lang/Object
   #4 = Class              #3             // java/lang/Object
   #5 = Utf8               shapeless/Poly
   #6 = Class              #5             // shapeless/Poly
   #7 = Utf8               polyntraits.scala
   #8 = Utf8               Lscala/reflect/ScalaSignature;
   #9 = Utf8               bytes
  #10 = Utf8               \u0006\u0005\u0005%baB\t\u0013!\u0003\r\t!\u0006\u0005\u0006A\u0001!\t!I\u0003\u0005K\u0001\u0001aeB\u0003E\u0001!\u0005QIB\u0003&\u0001!\u0005a\tC\u0003H\t\u0011\u0005\u0001*\u0002\u0003J\t\u0001Qe\u0001B,\u0001\u0001aCQaR\u0004\u0005\u0002iCQAX\u0004\u0005\u0002}CQ!\u001c\u0001\u0005\u00029<Qa\u001d\n\t\u0002Q4Q!\u0005\n\t\u0002UDaa\u0012\u0007\u0005\u0002\u0005-\u0001\"CA\u0007\u0019\t\u0007I\u0011AA\b\u0011!\t9\u0002\u0004Q\u0001\n\u0005E\u0001\"CA\r\u0019\u0005\u0005I\u0011BA\u000e\u0005\u0015\u0001v\u000e\\=2\u0015\u0005\u0019\u0012!C:iCB,G.Z:t\u0007\u0001\u00192\u0001\u0001\f\u001d!\t9\"$D\u0001\u0019\u0015\u0005I\u0012!B:dC2\f\u0017BA\u000e\u0019\u0005\u0019\te.\u001f*fMB\u0011QDH\u0007\u0002%%\u0011qD\u0005\u0002\u0005!>d\u00170\u0001\u0004%S:LG\u000f\n\u000b\u0002EA\u0011qcI\u0005\u0003Ia\u0011A!\u00168ji\n!1)Y:f+\t9\u0003\b\u0005\u0003)_I\u001adBA\u0015-\u001d\ti\"&\u0003\u0002,%\u00059\u0001/Y2lC\u001e,\u0017BA\u0017/\u0003\u0011\u0001x\u000e\\=\u000b\u0005-\u0012\u0012BA\u00131\u0015\t\t$#A\u0005Q_2LH)\u001a4og6\t\u0001\u0001\u0005\u0003\u001eiY\n\u0015BA\u001b\u0013\u00051!3m\u001c7p]\u0012\u001aw\u000e\\8o!\t9\u0004\b\u0004\u0001\u0005\u000be\u0012!\u0019\u0001\u001e\u0003\u0003\u0005\u000b\"a\u000f \u0011\u0005]a\u0014BA\u001f\u0019\u0005\u001dqu\u000e\u001e5j]\u001e\u0004\"aF \n\u0005\u0001C\"aA!osB\u0011QDQ\u0005\u0003\u0007J\u0011A\u0001\u0013(jY\u0006!1)Y:f!\t\u0011Da\u0005\u0002\u0005-\u00051A(\u001b8jiz\"\u0012!\u0012\u0002\u0004\u0003VDXcA&R+J\u0011AJ\u0014\u0004\u0005\u001b\u0012\u00011J\u0001\u0007=e\u00164\u0017N\\3nK:$h\b\u0005\u0003)_Iz\u0005\u0003B\u000f5!\u0006\u0003\"aN)\u0005\u000be2!\u0019\u0001\u001e\u0006\tMc\u0005\u0005\u0016\u0002\u0007%\u0016\u001cX\u000f\u001c;\u0011\u0005]*F!\u0002,\u0007\u0005\u0004Q$a\u0002*fgVdG\u000f\r\u0002\f\u0007\u0006\u001cXMQ;jY\u0012,\'/\u0006\u0002Z;N\u0011qA\u0006\u000b\u00027B\u0019!g\u0002/\u0011\u0005]jF!B\u001d\b\u0005\u0004Q\u0014!B1qa2LXC\u00011g)\t\t\u0007N\u0005\u0002cG\u001a!Q*\u0003\u0001b!\r\u0011$\u0001X\u0003\u0005\'\n\u0004Q\r\u0005\u00028M\u0012)q-\u0003b\u0001u\t\u0019!+Z:\t\u000b%L\u0001\u0019\u00016\u0002\u0005\u0019t\u0007\u0003B\fl9\u0016L!\u0001\u001c\r\u0003\u0013\u0019+hn\u0019;j_:\f\u0014AA1u+\ty\'/F\u0001q!\r\u0011t!\u001d\t\u0003oI$Q!\u000f\u0006C\u0002i\nQ\u0001U8msF\u0002\"!\b\u0007\u0014\t11b/ \t\u0004oj\feBA\u000fy\u0013\tI(#A\u0007Q_2LhJQ;jY\u0012,\'o]\u0005\u0003wr\u0014A\u0002U8msF\u0012U/\u001b7eKJT!!\u001f\n\u0011\u0007y\f9!D\u0001\u0000\u0015\u0011\t\t!a\u0001\u0002\u0005%|\'BAA\u0003\u0003\u0011Q\u0017M^1\n\u0007\u0005%qP\u0001\u0007TKJL\u0017\r\\5{C\ndW\rF\u0001u\u0003%1WO\\2uS>t7/\u0006\u0002\u0002\u00129\u0019Q$a\u0005\n\u0007\u0005U!#\u0001\u0003I\u001d&d\u0017A\u00034v]\u000e$\u0018n\u001c8tA\u0005aqO]5uKJ+\u0007\u000f\\1dKR\u0011\u0011Q\u0004\t\u0005\u0003?\t)#\u0004\u0002\u0002\")!\u00111EA\u0002\u0003\u0011a\u0017M\\4\n\t\u0005\u001d\u0012\u0011\u0005\u0002\u0007\u001f\nTWm\u0019;
  #11 = Utf8               shapeless/Poly1$Case$
  #12 = Class              #11            // shapeless/Poly1$Case$
  #13 = Utf8               Case$
  #14 = Utf8               shapeless/Poly1$CaseBuilder
  #15 = Class              #14            // shapeless/Poly1$CaseBuilder
  #16 = Utf8               CaseBuilder
  #17 = Utf8               functions
  #18 = Utf8               ()Lshapeless/HNil$;
  #19 = Utf8               shapeless/Poly1$
  #20 = Class              #19            // shapeless/Poly1$
  #21 = Utf8               MODULE$
  #22 = Utf8               Lshapeless/Poly1$;
  #23 = NameAndType        #21:#22        // MODULE$:Lshapeless/Poly1$;
  #24 = Fieldref           #20.#23        // shapeless/Poly1$.MODULE$:Lshapeless/Poly1$;
  #25 = NameAndType        #17:#18        // functions:()Lshapeless/HNil$;
  #26 = Methodref          #20.#25        // shapeless/Poly1$.functions:()Lshapeless/HNil$;
  #27 = Utf8               build
  #28 = Utf8               ()Lshapeless/Poly1;
  #29 = NameAndType        #27:#28        // build:()Lshapeless/Poly1;
  #30 = Methodref          #20.#29        // shapeless/Poly1$.build:()Lshapeless/Poly1;
  #31 = Utf8               Case
  #32 = Utf8               ()Lshapeless/Poly1$Case$;
  #33 = Utf8               at$
  #34 = Utf8               (Lshapeless/Poly1;)Lshapeless/Poly1$CaseBuilder;
  #35 = Utf8               $this
  #36 = Utf8               at
  #37 = Utf8               ()Lshapeless/Poly1$CaseBuilder;
  #38 = NameAndType        #36:#37        // at:()Lshapeless/Poly1$CaseBuilder;
  #39 = InterfaceMethodref #2.#38         // shapeless/Poly1.at:()Lshapeless/Poly1$CaseBuilder;
  #40 = Utf8               Lshapeless/Poly1;
  #41 = Utf8               <A:Ljava/lang/Object;>()Lshapeless/Poly1$CaseBuilder<TA;>;
  #42 = Utf8               <init>
  #43 = Utf8               (Lshapeless/Poly1;)V
  #44 = NameAndType        #42:#43        // "<init>":(Lshapeless/Poly1;)V
  #45 = Methodref          #15.#44        // shapeless/Poly1$CaseBuilder."<init>":(Lshapeless/Poly1;)V
  #46 = Utf8               this
  #47 = Utf8               $init$
  #48 = Utf8               Code
  #49 = Utf8               LineNumberTable
  #50 = Utf8               LocalVariableTable
  #51 = Utf8               MethodParameters
  #52 = Utf8               Signature
  #53 = Utf8               InnerClasses
  #54 = Utf8               SourceFile
  #55 = Utf8               RuntimeVisibleAnnotations
  #56 = Utf8               ScalaInlineInfo
  #57 = Utf8               ScalaSig
{
  public static shapeless.HNil$ functions();
    descriptor: ()Lshapeless/HNil$;
    flags: (0x0009) ACC_PUBLIC, ACC_STATIC
    Code:
      stack=1, locals=0, args_size=0
         0: getstatic     #24                 // Field shapeless/Poly1$.MODULE$:Lshapeless/Poly1$;
         3: invokevirtual #26                 // Method shapeless/Poly1$.functions:()Lshapeless/HNil$;
         6: areturn

  public static shapeless.Poly1 build();
    descriptor: ()Lshapeless/Poly1;
    flags: (0x0009) ACC_PUBLIC, ACC_STATIC
    Code:
      stack=1, locals=0, args_size=0
         0: getstatic     #24                 // Field shapeless/Poly1$.MODULE$:Lshapeless/Poly1$;
         3: invokevirtual #30                 // Method shapeless/Poly1$.build:()Lshapeless/Poly1;
         6: areturn

  public abstract shapeless.Poly1$Case$ Case();
    descriptor: ()Lshapeless/Poly1$Case$;
    flags: (0x0401) ACC_PUBLIC, ACC_ABSTRACT

  public static shapeless.Poly1$CaseBuilder at$(shapeless.Poly1);
    descriptor: (Lshapeless/Poly1;)Lshapeless/Poly1$CaseBuilder;
    flags: (0x1009) ACC_PUBLIC, ACC_STATIC, ACC_SYNTHETIC
    Code:
      stack=1, locals=1, args_size=1
         0: aload_0
         1: invokespecial #39                 // InterfaceMethod at:()Lshapeless/Poly1$CaseBuilder;
         4: areturn
      LineNumberTable:
        line 40: 0
      LocalVariableTable:
        Start  Length  Slot  Name   Signature
            0       5     0 $this   Lshapeless/Poly1;
    MethodParameters:
      Name                           Flags
      $this                          final synthetic

  public default <A extends java.lang.Object> shapeless.Poly1$CaseBuilder<A> at();
    descriptor: ()Lshapeless/Poly1$CaseBuilder;
    flags: (0x0001) ACC_PUBLIC
    Code:
      stack=3, locals=1, args_size=1
         0: new           #15                 // class shapeless/Poly1$CaseBuilder
         3: dup
         4: aload_0
         5: invokespecial #45                 // Method shapeless/Poly1$CaseBuilder."<init>":(Lshapeless/Poly1;)V
         8: areturn
      LineNumberTable:
        line 41: 0
      LocalVariableTable:
        Start  Length  Slot  Name   Signature
            0       9     0  this   Lshapeless/Poly1;
    Signature: #41                          // <A:Ljava/lang/Object;>()Lshapeless/Poly1$CaseBuilder<TA;>;

  public static void $init$(shapeless.Poly1);
    descriptor: (Lshapeless/Poly1;)V
    flags: (0x0009) ACC_PUBLIC, ACC_STATIC
    Code:
      stack=0, locals=1, args_size=1
         0: return
      LineNumberTable:
        line 22: 0
      LocalVariableTable:
        Start  Length  Slot  Name   Signature
            0       1     0 $this   Lshapeless/Poly1;
    MethodParameters:
      Name                           Flags
      $this                          final synthetic
}
InnerClasses:
  public #13= #12 of #2;                  // Case$=class shapeless/Poly1$Case$ of class shapeless/Poly1
  public #16= #15 of #2;                  // CaseBuilder=class shapeless/Poly1$CaseBuilder of class shapeless/Poly1
SourceFile: "polyntraits.scala"
RuntimeVisibleAnnotations:
  0: #8(#9=s#10)
    scala.reflect.ScalaSignature(
      bytes="\u0006\u0005\u0005%baB\t\u0013!\u0003\r\t!\u0006\u0005\u0006A\u0001!\t!I\u0003\u0005K\u0001\u0001aeB\u0003E\u0001!\u0005QIB\u0003&\u0001!\u0005a\tC\u0003H\t\u0011\u0005\u0001*\u0002\u0003J\t\u0001Qe\u0001B,\u0001\u0001aCQaR\u0004\u0005\u0002iCQAX\u0004\u0005\u0002}CQ!\u001c\u0001\u0005\u00029<Qa\u001d\n\t\u0002Q4Q!\u0005\n\t\u0002UDaa\u0012\u0007\u0005\u0002\u0005-\u0001\"CA\u0007\u0019\t\u0007I\u0011AA\b\u0011!\t9\u0002\u0004Q\u0001\n\u0005E\u0001\"CA\r\u0019\u0005\u0005I\u0011BA\u000e\u0005\u0015\u0001v\u000e\\=2\u0015\u0005\u0019\u0012!C:iCB,G.Z:t\u0007\u0001\u00192\u0001\u0001\f\u001d!\t9\"$D\u0001\u0019\u0015\u0005I\u0012!B:dC2\f\u0017BA\u000e\u0019\u0005\u0019\te.\u001f*fMB\u0011QDH\u0007\u0002%%\u0011qD\u0005\u0002\u0005!>d\u00170\u0001\u0004%S:LG\u000f\n\u000b\u0002EA\u0011qcI\u0005\u0003Ia\u0011A!\u00168ji\n!1)Y:f+\t9\u0003\b\u0005\u0003)_I\u001adBA\u0015-\u001d\ti\"&\u0003\u0002,%\u00059\u0001/Y2lC\u001e,\u0017BA\u0017/\u0003\u0011\u0001x\u000e\\=\u000b\u0005-\u0012\u0012BA\u00131\u0015\t\t$#A\u0005Q_2LH)\u001a4og6\t\u0001\u0001\u0005\u0003\u001eiY\n\u0015BA\u001b\u0013\u00051!3m\u001c7p]\u0012\u001aw\u000e\\8o!\t9\u0004\b\u0004\u0001\u0005\u000be\u0012!\u0019\u0001\u001e\u0003\u0003\u0005\u000b\"a\u000f \u0011\u0005]a\u0014BA\u001f\u0019\u0005\u001dqu\u000e\u001e5j]\u001e\u0004\"aF \n\u0005\u0001C\"aA!osB\u0011QDQ\u0005\u0003\u0007J\u0011A\u0001\u0013(jY\u0006!1)Y:f!\t\u0011Da\u0005\u0002\u0005-\u00051A(\u001b8jiz\"\u0012!\u0012\u0002\u0004\u0003VDXcA&R+J\u0011AJ\u0014\u0004\u0005\u001b\u0012\u00011J\u0001\u0007=e\u00164\u0017N\\3nK:$h\b\u0005\u0003)_Iz\u0005\u0003B\u000f5!\u0006\u0003\"aN)\u0005\u000be2!\u0019\u0001\u001e\u0006\tMc\u0005\u0005\u0016\u0002\u0007%\u0016\u001cX\u000f\u001c;\u0011\u0005]*F!\u0002,\u0007\u0005\u0004Q$a\u0002*fgVdG\u000f\r\u0002\f\u0007\u0006\u001cXMQ;jY\u0012,\'/\u0006\u0002Z;N\u0011qA\u0006\u000b\u00027B\u0019!g\u0002/\u0011\u0005]jF!B\u001d\b\u0005\u0004Q\u0014!B1qa2LXC\u00011g)\t\t\u0007N\u0005\u0002cG\u001a!Q*\u0003\u0001b!\r\u0011$\u0001X\u0003\u0005\'\n\u0004Q\r\u0005\u00028M\u0012)q-\u0003b\u0001u\t\u0019!+Z:\t\u000b%L\u0001\u0019\u00016\u0002\u0005\u0019t\u0007\u0003B\fl9\u0016L!\u0001\u001c\r\u0003\u0013\u0019+hn\u0019;j_:\f\u0014AA1u+\ty\'/F\u0001q!\r\u0011t!\u001d\t\u0003oI$Q!\u000f\u0006C\u0002i\nQ\u0001U8msF\u0002\"!\b\u0007\u0014\t11b/ \t\u0004oj\feBA\u000fy\u0013\tI(#A\u0007Q_2LhJQ;jY\u0012,\'o]\u0005\u0003wr\u0014A\u0002U8msF\u0012U/\u001b7eKJT!!\u001f\n\u0011\u0007y\f9!D\u0001\u0000\u0015\u0011\t\t!a\u0001\u0002\u0005%|\'BAA\u0003\u0003\u0011Q\u0017M^1\n\u0007\u0005%qP\u0001\u0007TKJL\u0017\r\\5{C\ndW\rF\u0001u\u0003%1WO\\2uS>t7/\u0006\u0002\u0002\u00129\u0019Q$a\u0005\n\u0007\u0005U!#\u0001\u0003I\u001d&d\u0017A\u00034v]\u000e$\u0018n\u001c8tA\u0005aqO]5uKJ+\u0007\u000f\\1dKR\u0011\u0011Q\u0004\t\u0005\u0003?\t)#\u0004\u0002\u0002\")!\u00111EA\u0002\u0003\u0011a\u0017M\\4\n\t\u0005\u001d\u0012\u0011\u0005\u0002\u0007\u001f\nTWm\u0019;"
    )
  ScalaInlineInfo: length = 0x18 (unknown attribute)
   01 00 00 04 00 2F 00 2B 01 00 1F 00 20 00 00 21
   00 22 01 00 24 00 25 00
  ScalaSig: length = 0x3 (unknown attribute)
   05 02 00
