Classfile /Users/mw/Projects/slang-braindump/.jar/jar11/assemble/slang-braindump/assemble/content/shapeless/Poly2.class
  Last modified May 29, 2022; size 2322 bytes
  SHA-256 checksum e0a2e0f375cc0ba450db2bab040eb561743cdfd7a3611254af0ea69eb7191742
  Compiled from "polyntraits.scala"
public interface shapeless.Poly2 extends shapeless.Poly
  minor version: 0
  major version: 52
  flags: (0x0601) ACC_PUBLIC, ACC_INTERFACE, ACC_ABSTRACT
  this_class: #2                          // shapeless/Poly2
  super_class: #4                         // java/lang/Object
  interfaces: 1, fields: 0, methods: 6, attributes: 5
Constant pool:
   #1 = Utf8               shapeless/Poly2
   #2 = Class              #1             // shapeless/Poly2
   #3 = Utf8               java/lang/Object
   #4 = Class              #3             // java/lang/Object
   #5 = Utf8               shapeless/Poly
   #6 = Class              #5             // shapeless/Poly
   #7 = Utf8               polyntraits.scala
   #8 = Utf8               Lscala/reflect/ScalaSignature;
   #9 = Utf8               bytes
  #10 = Utf8               \u0006\u0005\u0005}baB\t\u0013!\u0003\r\t!\u0006\u0005\u0006A\u0001!\t!I\u0003\u0005K\u0001\u0001aeB\u0003I\u0001!\u0005\u0011JB\u0003&\u0001!\u0005!\nC\u0003L\t\u0011\u0005A*\u0002\u0003N\t\u0001qe\u0001\u00020\u0001\u0001}CQaS\u0004\u0005\u0002\u0005DQaZ\u0004\u0005\u0002!DQA\u001e\u0001\u0005\u0002]<QA \n\t\u0002}4a!\u0005\n\t\u0002\u0005\u0005\u0001BB&\r\t\u0003\t\t\u0003C\u0005\u0002$1\u0011\r\u0011\"\u0001\u0002&!A\u0011Q\u0006\u0007!\u0002\u0013\t9\u0003C\u0005\u000201\t\t\u0011\"\u0003\u00022\t)\u0001k\u001c7ze)\t1#A\u0005tQ\u0006\u0004X\r\\3tg\u000e\u00011c\u0001\u0001\u00179A\u0011qCG\u0007\u00021)\t\u0011$A\u0003tG\u0006d\u0017-\u0003\u0002\u001c1\t1\u0011I\\=SK\u001a\u0004\"!\b\u0010\u000e\u0003II!a\b\n\u0003\tA{G._\u0001\u0007I%t\u0017\u000e\u001e\u0013\u0015\u0003\t\u0002\"aF\u0012\n\u0005\u0011B\"\u0001B+oSR\u0014AaQ1tKV\u0019q\u0005O\"\u0011\t!z#g\r\b\u0003S1r!!\b\u0016\n\u0005-\u0012\u0012a\u00029bG.\fw-Z\u0005\u0003[9\nA\u0001]8ms*\u00111FE\u0005\u0003KAR!!\r\n\u0002\u0013A{G.\u001f#fM:\u001cX\"\u0001\u0001\u0011\tu!d\'Q\u0005\u0003kI\u0011A\u0002J2pY>tGeY8m_:\u0004\"a\u000e\u001d\r\u0001\u0011)\u0011H\u0001b\u0001u\t\t\u0011)\u0005\u0002<}A\u0011q\u0003P\u0005\u0003{a\u0011qAT8uQ&tw\r\u0005\u0002\u0018\u007f%\u0011\u0001\t\u0007\u0002\u0004\u0003:L\b\u0003B\u000f5\u0005\u0016\u0003\"aN\"\u0005\u000b\u0011\u0013!\u0019\u0001\u001e\u0003\u0003\t\u0003\"!\b$\n\u0005\u001d\u0013\"\u0001\u0002%OS2\fAaQ1tKB\u0011!\u0007B\n\u0003\tY\ta\u0001P5oSRtD#A%\u0003\u0007\u0005+\b0\u0006\u0003P+bc&C\u0001)S\r\u0011\tF\u0001A(\u0003\u0019q\u0012XMZ5oK6,g\u000e\u001e \u0011\t!z#g\u0015\t\u0005;Q\"f\u000b\u0005\u00028+\u0012)\u0011H\u0002b\u0001uA!Q\u0004N,F!\t9\u0004\fB\u0003E\r\t\u0007!(\u0002\u0003[!\u0002Z&A\u0002*fgVdG\u000f\u0005\u000289\u0012)QL\u0002b\u0001u\t9!+Z:vYR\u0004$aC\"bg\u0016\u0014U/\u001b7eKJ,2\u0001\u00193g\'\t9a\u0003F\u0001c!\u0011\u0011taY3\u0011\u0005]\"G!B\u001d\b\u0005\u0004Q\u0004CA\u001cg\t\u0015!uA1\u0001;\u0003\u0015\t\u0007\u000f\u001d7z+\tIw\u000e\u0006\u0002kcJ\u00111\u000e\u001c\u0004\u0005#&\u0001!\u000e\u0005\u00033\u0005\r,W\u0001\u0002.l\u00019\u0004\"aN8\u0005\u000bAL!\u0019\u0001\u001e\u0003\u0007I+7\u000fC\u0003s\u0013\u0001\u00071/\u0001\u0002g]B)q\u0003^2f]&\u0011Q\u000f\u0007\u0002\n\rVt7\r^5p]J\n!!\u0019;\u0016\u0007a\\X0F\u0001z!\u0011\u0011tA\u001f?\u0011\u0005]ZH!B\u001d\u000b\u0005\u0004Q\u0004CA\u001c~\t\u0015!%B1\u0001;\u0003\u0015\u0001v\u000e\\=3!\tiBb\u0005\u0004\r-\u0005\r\u0011\u0011\u0003\t\u0006\u0003\u000b\tY!\u0012\b\u0004;\u0005\u001d\u0011bAA\u0005%\u0005i\u0001k\u001c7z\u001d\n+\u0018\u000e\u001c3feNLA!!\u0004\u0002\u0010\ta\u0001k\u001c7ze\t+\u0018\u000e\u001c3fe*\u0019\u0011\u0011\u0002\n\u0011\t\u0005M\u0011QD\u0007\u0003\u0003+QA!a\u0006\u0002\u001a\u0005\u0011\u0011n\u001c\u0006\u0003\u00037\tAA[1wC&!\u0011qDA\u000b\u00051\u0019VM]5bY&T\u0018M\u00197f)\u0005y\u0018!\u00034v]\u000e$\u0018n\u001c8t+\t\t9CD\u0002\u001e\u0003SI1!a\u000b\u0013\u0003\u0011Ae*\u001b7\u0002\u0015\u0019,hn\u0019;j_:\u001c\b%\u0001\u0007xe&$XMU3qY\u0006\u001cW\r\u0006\u0002\u00024A!\u0011QGA\u001e\u001b\t\t9D\u0003\u0003\u0002:\u0005e\u0011\u0001\u00027b]\u001eLA!!\u0010\u00028\t1qJ\u00196fGR\u0004
  #11 = Utf8               shapeless/Poly2$Case$
  #12 = Class              #11            // shapeless/Poly2$Case$
  #13 = Utf8               Case$
  #14 = Utf8               shapeless/Poly2$CaseBuilder
  #15 = Class              #14            // shapeless/Poly2$CaseBuilder
  #16 = Utf8               CaseBuilder
  #17 = Utf8               functions
  #18 = Utf8               ()Lshapeless/HNil$;
  #19 = Utf8               shapeless/Poly2$
  #20 = Class              #19            // shapeless/Poly2$
  #21 = Utf8               MODULE$
  #22 = Utf8               Lshapeless/Poly2$;
  #23 = NameAndType        #21:#22        // MODULE$:Lshapeless/Poly2$;
  #24 = Fieldref           #20.#23        // shapeless/Poly2$.MODULE$:Lshapeless/Poly2$;
  #25 = NameAndType        #17:#18        // functions:()Lshapeless/HNil$;
  #26 = Methodref          #20.#25        // shapeless/Poly2$.functions:()Lshapeless/HNil$;
  #27 = Utf8               build
  #28 = Utf8               ()Lshapeless/Poly2;
  #29 = NameAndType        #27:#28        // build:()Lshapeless/Poly2;
  #30 = Methodref          #20.#29        // shapeless/Poly2$.build:()Lshapeless/Poly2;
  #31 = Utf8               Case
  #32 = Utf8               ()Lshapeless/Poly2$Case$;
  #33 = Utf8               at$
  #34 = Utf8               (Lshapeless/Poly2;)Lshapeless/Poly2$CaseBuilder;
  #35 = Utf8               $this
  #36 = Utf8               at
  #37 = Utf8               ()Lshapeless/Poly2$CaseBuilder;
  #38 = NameAndType        #36:#37        // at:()Lshapeless/Poly2$CaseBuilder;
  #39 = InterfaceMethodref #2.#38         // shapeless/Poly2.at:()Lshapeless/Poly2$CaseBuilder;
  #40 = Utf8               Lshapeless/Poly2;
  #41 = Utf8               <A:Ljava/lang/Object;B:Ljava/lang/Object;>()Lshapeless/Poly2$CaseBuilder<TA;TB;>;
  #42 = Utf8               <init>
  #43 = Utf8               (Lshapeless/Poly2;)V
  #44 = NameAndType        #42:#43        // "<init>":(Lshapeless/Poly2;)V
  #45 = Methodref          #15.#44        // shapeless/Poly2$CaseBuilder."<init>":(Lshapeless/Poly2;)V
  #46 = Utf8               this
  #47 = Utf8               $init$
  #48 = Utf8               Code
  #49 = Utf8               LineNumberTable
  #50 = Utf8               LocalVariableTable
  #51 = Utf8               MethodParameters
  #52 = Utf8               Signature
  #53 = Utf8               InnerClasses
  #54 = Utf8               SourceFile
  #55 = Utf8               RuntimeVisibleAnnotations
  #56 = Utf8               ScalaInlineInfo
  #57 = Utf8               ScalaSig
{
  public static shapeless.HNil$ functions();
    descriptor: ()Lshapeless/HNil$;
    flags: (0x0009) ACC_PUBLIC, ACC_STATIC
    Code:
      stack=1, locals=0, args_size=0
         0: getstatic     #24                 // Field shapeless/Poly2$.MODULE$:Lshapeless/Poly2$;
         3: invokevirtual #26                 // Method shapeless/Poly2$.functions:()Lshapeless/HNil$;
         6: areturn

  public static shapeless.Poly2 build();
    descriptor: ()Lshapeless/Poly2;
    flags: (0x0009) ACC_PUBLIC, ACC_STATIC
    Code:
      stack=1, locals=0, args_size=0
         0: getstatic     #24                 // Field shapeless/Poly2$.MODULE$:Lshapeless/Poly2$;
         3: invokevirtual #30                 // Method shapeless/Poly2$.build:()Lshapeless/Poly2;
         6: areturn

  public abstract shapeless.Poly2$Case$ Case();
    descriptor: ()Lshapeless/Poly2$Case$;
    flags: (0x0401) ACC_PUBLIC, ACC_ABSTRACT

  public static shapeless.Poly2$CaseBuilder at$(shapeless.Poly2);
    descriptor: (Lshapeless/Poly2;)Lshapeless/Poly2$CaseBuilder;
    flags: (0x1009) ACC_PUBLIC, ACC_STATIC, ACC_SYNTHETIC
    Code:
      stack=1, locals=1, args_size=1
         0: aload_0
         1: invokespecial #39                 // InterfaceMethod at:()Lshapeless/Poly2$CaseBuilder;
         4: areturn
      LineNumberTable:
        line 66: 0
      LocalVariableTable:
        Start  Length  Slot  Name   Signature
            0       5     0 $this   Lshapeless/Poly2;
    MethodParameters:
      Name                           Flags
      $this                          final synthetic

  public default <A extends java.lang.Object, B extends java.lang.Object> shapeless.Poly2$CaseBuilder<A, B> at();
    descriptor: ()Lshapeless/Poly2$CaseBuilder;
    flags: (0x0001) ACC_PUBLIC
    Code:
      stack=3, locals=1, args_size=1
         0: new           #15                 // class shapeless/Poly2$CaseBuilder
         3: dup
         4: aload_0
         5: invokespecial #45                 // Method shapeless/Poly2$CaseBuilder."<init>":(Lshapeless/Poly2;)V
         8: areturn
      LineNumberTable:
        line 67: 0
      LocalVariableTable:
        Start  Length  Slot  Name   Signature
            0       9     0  this   Lshapeless/Poly2;
    Signature: #41                          // <A:Ljava/lang/Object;B:Ljava/lang/Object;>()Lshapeless/Poly2$CaseBuilder<TA;TB;>;

  public static void $init$(shapeless.Poly2);
    descriptor: (Lshapeless/Poly2;)V
    flags: (0x0009) ACC_PUBLIC, ACC_STATIC
    Code:
      stack=0, locals=1, args_size=1
         0: return
      LineNumberTable:
        line 48: 0
      LocalVariableTable:
        Start  Length  Slot  Name   Signature
            0       1     0 $this   Lshapeless/Poly2;
    MethodParameters:
      Name                           Flags
      $this                          final synthetic
}
InnerClasses:
  public #13= #12 of #2;                  // Case$=class shapeless/Poly2$Case$ of class shapeless/Poly2
  public #16= #15 of #2;                  // CaseBuilder=class shapeless/Poly2$CaseBuilder of class shapeless/Poly2
SourceFile: "polyntraits.scala"
RuntimeVisibleAnnotations:
  0: #8(#9=s#10)
    scala.reflect.ScalaSignature(
      bytes="\u0006\u0005\u0005}baB\t\u0013!\u0003\r\t!\u0006\u0005\u0006A\u0001!\t!I\u0003\u0005K\u0001\u0001aeB\u0003I\u0001!\u0005\u0011JB\u0003&\u0001!\u0005!\nC\u0003L\t\u0011\u0005A*\u0002\u0003N\t\u0001qe\u0001\u00020\u0001\u0001}CQaS\u0004\u0005\u0002\u0005DQaZ\u0004\u0005\u0002!DQA\u001e\u0001\u0005\u0002]<QA \n\t\u0002}4a!\u0005\n\t\u0002\u0005\u0005\u0001BB&\r\t\u0003\t\t\u0003C\u0005\u0002$1\u0011\r\u0011\"\u0001\u0002&!A\u0011Q\u0006\u0007!\u0002\u0013\t9\u0003C\u0005\u000201\t\t\u0011\"\u0003\u00022\t)\u0001k\u001c7ze)\t1#A\u0005tQ\u0006\u0004X\r\\3tg\u000e\u00011c\u0001\u0001\u00179A\u0011qCG\u0007\u00021)\t\u0011$A\u0003tG\u0006d\u0017-\u0003\u0002\u001c1\t1\u0011I\\=SK\u001a\u0004\"!\b\u0010\u000e\u0003II!a\b\n\u0003\tA{G._\u0001\u0007I%t\u0017\u000e\u001e\u0013\u0015\u0003\t\u0002\"aF\u0012\n\u0005\u0011B\"\u0001B+oSR\u0014AaQ1tKV\u0019q\u0005O\"\u0011\t!z#g\r\b\u0003S1r!!\b\u0016\n\u0005-\u0012\u0012a\u00029bG.\fw-Z\u0005\u0003[9\nA\u0001]8ms*\u00111FE\u0005\u0003KAR!!\r\n\u0002\u0013A{G.\u001f#fM:\u001cX\"\u0001\u0001\u0011\tu!d\'Q\u0005\u0003kI\u0011A\u0002J2pY>tGeY8m_:\u0004\"a\u000e\u001d\r\u0001\u0011)\u0011H\u0001b\u0001u\t\t\u0011)\u0005\u0002<}A\u0011q\u0003P\u0005\u0003{a\u0011qAT8uQ&tw\r\u0005\u0002\u0018\u007f%\u0011\u0001\t\u0007\u0002\u0004\u0003:L\b\u0003B\u000f5\u0005\u0016\u0003\"aN\"\u0005\u000b\u0011\u0013!\u0019\u0001\u001e\u0003\u0003\t\u0003\"!\b$\n\u0005\u001d\u0013\"\u0001\u0002%OS2\fAaQ1tKB\u0011!\u0007B\n\u0003\tY\ta\u0001P5oSRtD#A%\u0003\u0007\u0005+\b0\u0006\u0003P+bc&C\u0001)S\r\u0011\tF\u0001A(\u0003\u0019q\u0012XMZ5oK6,g\u000e\u001e \u0011\t!z#g\u0015\t\u0005;Q\"f\u000b\u0005\u00028+\u0012)\u0011H\u0002b\u0001uA!Q\u0004N,F!\t9\u0004\fB\u0003E\r\t\u0007!(\u0002\u0003[!\u0002Z&A\u0002*fgVdG\u000f\u0005\u000289\u0012)QL\u0002b\u0001u\t9!+Z:vYR\u0004$aC\"bg\u0016\u0014U/\u001b7eKJ,2\u0001\u00193g\'\t9a\u0003F\u0001c!\u0011\u0011taY3\u0011\u0005]\"G!B\u001d\b\u0005\u0004Q\u0004CA\u001cg\t\u0015!uA1\u0001;\u0003\u0015\t\u0007\u000f\u001d7z+\tIw\u000e\u0006\u0002kcJ\u00111\u000e\u001c\u0004\u0005#&\u0001!\u000e\u0005\u00033\u0005\r,W\u0001\u0002.l\u00019\u0004\"aN8\u0005\u000bAL!\u0019\u0001\u001e\u0003\u0007I+7\u000fC\u0003s\u0013\u0001\u00071/\u0001\u0002g]B)q\u0003^2f]&\u0011Q\u000f\u0007\u0002\n\rVt7\r^5p]J\n!!\u0019;\u0016\u0007a\\X0F\u0001z!\u0011\u0011tA\u001f?\u0011\u0005]ZH!B\u001d\u000b\u0005\u0004Q\u0004CA\u001c~\t\u0015!%B1\u0001;\u0003\u0015\u0001v\u000e\\=3!\tiBb\u0005\u0004\r-\u0005\r\u0011\u0011\u0003\t\u0006\u0003\u000b\tY!\u0012\b\u0004;\u0005\u001d\u0011bAA\u0005%\u0005i\u0001k\u001c7z\u001d\n+\u0018\u000e\u001c3feNLA!!\u0004\u0002\u0010\ta\u0001k\u001c7ze\t+\u0018\u000e\u001c3fe*\u0019\u0011\u0011\u0002\n\u0011\t\u0005M\u0011QD\u0007\u0003\u0003+QA!a\u0006\u0002\u001a\u0005\u0011\u0011n\u001c\u0006\u0003\u00037\tAA[1wC&!\u0011qDA\u000b\u00051\u0019VM]5bY&T\u0018M\u00197f)\u0005y\u0018!\u00034v]\u000e$\u0018n\u001c8t+\t\t9CD\u0002\u001e\u0003SI1!a\u000b\u0013\u0003\u0011Ae*\u001b7\u0002\u0015\u0019,hn\u0019;j_:\u001c\b%\u0001\u0007xe&$XMU3qY\u0006\u001cW\r\u0006\u0002\u00024A!\u0011QGA\u001e\u001b\t\t9D\u0003\u0003\u0002:\u0005e\u0011\u0001\u00027b]\u001eLA!!\u0010\u00028\t1qJ\u00196fGR\u0004"
    )
  ScalaInlineInfo: length = 0x18 (unknown attribute)
   01 00 00 04 00 2F 00 2B 01 00 1F 00 20 00 00 21
   00 22 01 00 24 00 25 00
  ScalaSig: length = 0x3 (unknown attribute)
   05 02 00
