Classfile /Users/mw/Projects/slang-braindump/.jar/jar11/assemble/slang-braindump/assemble/content/shapeless/PolyDefns.class
  Last modified May 29, 2022; size 11862 bytes
  SHA-256 checksum 1645760ba68f695ba7b406f515cef8af67e1331a2a71360255d98d2d6b4efbc7
  Compiled from "poly.scala"
public final class shapeless.PolyDefns
  minor version: 0
  major version: 52
  flags: (0x0031) ACC_PUBLIC, ACC_FINAL, ACC_SUPER
  this_class: #2                          // shapeless/PolyDefns
  super_class: #4                         // java/lang/Object
  interfaces: 0, fields: 0, methods: 22, attributes: 4
Constant pool:
    #1 = Utf8               shapeless/PolyDefns
    #2 = Class              #1            // shapeless/PolyDefns
    #3 = Utf8               java/lang/Object
    #4 = Class              #3            // java/lang/Object
    #5 = Utf8               poly.scala
    #6 = Utf8               Lscala/reflect/ScalaSignature;
    #7 = Utf8               bytes
    #8 = Utf8               \u0006\u0005\u0019Mx!\u0002.\\\u0011\u0003qf!\u00021\\\u0011\u0003\t\u0007\"B6\u0002\t\u0003ag!B7\u0002\u0003\u0003q\u0007\"B6\u0004\t\u0003aHaBA\u0012\u0007\t\u0005\u0011q\u0001\u0005\n\u0003K\u0019!\u0019!D\u0001\u0003OAq!a\r\u0004\t\u0003\t)\u0004C\u0004\u00024\r!\t!a\u000f\t\u000f\u0005M2\u0001\"\u0001\u0002P!9\u00111G\u0002\u0005\u0002\u0005\u001dtaBAC\u0003!\u0005\u0011q\u0011\u0004\u0007[\u0006A\t!!#\t\r-dA\u0011AAP\u000b\u0019\t\t\u000b\u0004\u0001\u0002$\u00161\u0011Q\u0018\u0007\u0001\u0003\u007fCq!a\r\r\t\u0003\ty\r\u0003\u0005\u0002j2\u0011I1AAv\u0011!\u0011I\f\u0004B\u0005\u0004\tm\u0006\"CB\u0007\u0019\u0005\u0005I\u0011BB\b\u000b\u0019\u0019i\"\u0001\u0001\u0004 \u001d91qE\u0001\t\u0002\r%baBB\u000f\u0003!\u000511\u0006\u0005\u0007WZ!\ta!\f\u0006\r\u0005\u0005f\u0003AB\u0018\u0011\u001d\t\u0019D\u0006C\u0001\u0007{1aaa\u0014\u0002\u0001\rE\u0003BCB.5\t\u0005\t\u0015!\u0003\u0004^!Q1\u0011\r\u000e\u0003\u0002\u0003\u0006Iaa\u0019\t\r-TB\u0011AB5\u000f\u001d\u0019\t(\u0001E\u0001\u0007g2qaa\u0014\u0002\u0011\u0003\u0019)\b\u0003\u0004l?\u0011\u00051q\u000f\u0005\b\u0007szB1AB>\u0011%\u0019iaHA\u0001\n\u0013\u0019yA\u0002\u0004\u0004J\u0006\u000111\u001a\u0005\u000b\u0007\u001f\u001c#\u0011!Q\u0001\n\rE\u0007BB6$\t\u0003\u0019)nB\u0004\u0004b\u0006A\taa9\u0007\u000f\r%\u0017\u0001#\u0001\u0004f\"11n\nC\u0001\u0007ODqa!;(\t\u0007\u0019Y\u000fC\u0005\u0004\u000e\u001d\n\t\u0011\"\u0003\u0004\u0010\u00191A\u0011I\u0001\u0001\t\u0007B!ba4,\u0005\u0003\u0005\u000b\u0011\u0002C$\u0011\u0019Y7\u0006\"\u0001\u0005L\u001d9AqG\u0001\t\u0002\u0011Uca\u0002C!\u0003!\u0005Aq\u000b\u0005\u0007W>\"\t\u0001\"\u0017\t\u000f\r%x\u0006b\u0001\u0005\\!I1QB\u0018\u0002\u0002\u0013%1q\u0002\u0004\u0007\t\'\u000b\u0001\u0001\"&\t\u0015\rm3G!A!\u0002\u0013!y\n\u0003\u0004lg\u0011\u0005A\u0011\u0016\u0005\b\t_\u001bD1\u0001CY\r%!i-\u0001I\u0001\u0004\u0003!y\rC\u0004\u0005R^\"\t\u0001b5\t\u000f\u0011mw\u0007b\u0001\u0005^\u001a1Aq^\u0001\u0001\tcD!ba\u0017;\u0005\u0003\u0005\u000b\u0011\u0002C|\u0011\u0019Y\'\b\"\u0001\u0006\u0002!9Aq\u0016\u001e\u0005\u0004\u0015\u001da!CC\u000f\u0003A\u0005\u0019\u0011AC\u0010\u0011\u001d!\tN\u0010C\u0001\t\'Dq\u0001b7?\t\u0007)\tC\u0002\u0004\u0006D\u0005\u0001QQ\t\u0005\u000b\u0007\u001f\f%\u0011!Q\u0001\n\u0015-\u0003BB6B\t\u0003)y\u0005C\u0004\u0006V\u0005#\u0019!b\u0016\u0007\u0013\u0015U\u0014\u0001%A\u0002\u0002\u0015]\u0004b\u0002Ci\u000b\u0012\u0005A1\u001b\u0005\b\u0003g)e\u0011AC>\u0011\u001d))*\u0012C\u0002\u000b/;q!b,\u0002\u0011\u0003)\tLB\u0004\u0006v\u0005A\t!b-\t\r-TE\u0011AC[\u0011\u001d)9L\u0013C\u0002\u000bsCq!b7K\t\u0007)i\u000eC\u0004\u0007\u0002)#\u0019Ab\u0001\t\u000f\u0019m!\nb\u0001\u0007\u001e!9a1\u0006&\u0005\u0002\u00195\u0002b\u0002D0\u0015\u0012\u0005a\u0011\r\u0005\b\r\u000bSE\u0011\u0001DD\u0011%\u0019iASA\u0001\n\u0013\u0019y!\u0002\u0004\u0007>\u0006\u0001aqX\u0004\b\r?\f\u0001\u0012\u0001Dq\r\u001d1\u0019/\u0001E\u0001\rKDaa\u001b,\u0005\u0002\u0019\u001d\bbBA\u001a-\u0012\u0005a\u0011\u001e\u0005\n\u0007\u001b1\u0016\u0011!C\u0005\u0007\u001f\t\u0011\u0002U8ms\u0012+gM\\:\u000b\u0003q\u000b\u0011b\u001d5ba\u0016dWm]:\u0004\u0001A\u0011q,A\u0007\u00027\nI\u0001k\u001c7z\t\u00164gn]\n\u0004\u0003\tD\u0007CA2g\u001b\u0005!\'\"A3\u0002\u000bM\u001c\u0017\r\\1\n\u0005\u001d$\'AB!osJ+g\r\u0005\u0002`S&\u0011!n\u0017\u0002\u0006\u0007\u0006\u001cXm]\u0001\u0007y%t\u0017\u000e\u001e \u0015\u0003y\u0013AaQ1tKV)q.a\u0001\u0002\u0018M\u00191A\u00199\u0011\u0005ELhB\u0001:x\u001d\t\u0019h/D\u0001u\u0015\t)X,\u0001\u0004=e>|GOP\u0005\u0002K&\u0011\u0001\u0010Z\u0001\ba\u0006\u001c7.Y4f\u0013\tQ8P\u0001\u0007TKJL\u0017\r\\5{C\ndWM\u0003\u0002yIR\tQ\u0010E\u0003\u007f\u0007}\f)\"D\u0001\u0002!\u0011\t\t!a\u0001\r\u0001\u00119\u0011QA\u0002C\u0002\u0005\u001d!!\u0001)\u0012\t\u0005%\u0011q\u0002\t\u0004G\u0006-\u0011bAA\u0007I\n9aj\u001c;iS:<\u0007cA2\u0002\u0012%\u0019\u00111\u00033\u0003\u0007\u0005s\u0017\u0010\u0005\u0003\u0002\u0002\u0005]AaBA\r\u0007\t\u0007\u00111\u0004\u0002\u0002\u0019F!\u0011\u0011BA\u000f!\ry\u0016qD\u0005\u0004\u0003CY&!\u0002%MSN$(A\u0002*fgVdG/A\u0003wC2,X-\u0006\u0002\u0002*A91-a\u000b\u0002\u0016\u0005=\u0012bAA\u0017I\nIa)\u001e8di&|g.\r\t\u0004\u0003c)Q\"A\u0002\u0002\u000b\u0005\u0004\b\u000f\\=\u0015\t\u0005=\u0012q\u0007\u0005\b\u0003s9\u0001\u0019AA\u000b\u0003\u0005!HCAA\u001f)\u0011\ty#a\u0010\t\u000f\u0005\u0005\u0003\u0002q\u0001\u0002D\u0005\u0011QM\u001e\t\bG\u0006\u0015\u0013\u0011JA\u000b\u0013\r\t9\u0005\u001a\u0002\rI\u0015\fHeY8m_:$S-\u001d\t\u0004?\u0006-\u0013bAA\'7\n!\u0001JT5m+\u0011\t\t&!\u0019\u0015\t\u0005M\u0013Q\r\u000b\u0005\u0003_\t)\u0006C\u0004\u0002B%\u0001\u001d!a\u0016\u0011\u000f\r\f)%!\u0017\u0002\u0016A9q,a\u0017\u0002`\u0005%\u0013bAA/7\naAeY8m_:$3m\u001c7p]B!\u0011\u0011AA1\t\u001d\t\u0019\'\u0003b\u0001\u0003\u000f\u0011\u0011\u0001\u0016\u0005\b\u0003sI\u0001\u0019AA0+\u0019\tI\'!\u001e\u0002|Q1\u00111NA@\u0003\u0003#B!a\f\u0002n!9\u0011\u0011\t\u0006A\u0004\u0005=\u0004cB2\u0002F\u0005E\u0014Q\u0003\t\b?\u0006m\u00131OA<!\u0011\t\t!!\u001e\u0005\u000f\u0005\r$B1\u0001\u0002\bA9q,a\u0017\u0002z\u0005%\u0003\u0003BA\u0001\u0003w\"q!! \u000b\u0005\u0004\t9AA\u0001V\u0011\u001d\tID\u0003a\u0001\u0003gBq!a!\u000b\u0001\u0004\tI(A\u0001v\u0003\u0011\u0019\u0015m]3\u0011\u0005yd1C\u0002\u0007c\u0003\u0017\u000b\t\nE\u0002`\u0003\u001bK1!a$\\\u0005!\u0019\u0015m]3J]N$\b\u0003BAJ\u0003;k!!!&\u000b\t\u0005]\u0015\u0011T\u0001\u0003S>T!!a\'\u0002\t)\fg/Y\u0005\u0004u\u0006UECAAD\u0005\r\tU\u000f_\u000b\t\u0003K\u000by+a-\u0002:J!\u0011qUAV\r\u0019\tI\u000b\u0004\u0001\u0002&\naAH]3gS:,W.\u001a8u}A1apAAW\u0003c\u0003B!!\u0001\u00020\u00129\u0011Q\u0001\bC\u0002\u0005\u001d\u0001\u0003BA\u0001\u0003g#q!!\u0007\u000f\u0005\u0004\tY\"B\u0004\u0002$\u0005\u001d\u0006%a.\u0011\t\u0005\u0005\u0011\u0011\u0018\u0003\b\u0003ws!\u0019AA\u0004\u0005\u001d\u0011Vm];miB\u00121\u0001S8n+\u0019\t\t-a2\u0002NBI\u00111\u0019\b\u0002F\u0006%\u00171Z\u0007\u0002\u0019A!\u0011\u0011AAd\t\u001d\t)a\u0004b\u0001\u0003\u000f\u0001raXA.\u0003\u0017\fI\u0005\u0005\u0003\u0002\u0002\u00055GaBA2\u001f\t\u0007\u0011qA\u000b\t\u0003#\f9.a7\u0002`R!\u00111[Ar!%\t\u0019MDAk\u00033\fi\u000e\u0005\u0003\u0002\u0002\u0005]GaBA\u0003!\t\u0007\u0011q\u0001\t\u0005\u0003\u0003\tY\u000eB\u0004\u0002\u001aA\u0011\r!a\u0007\u0011\t\u0005\u0005\u0011q\u001c\u0003\b\u0003C\u0004\"\u0019AA\u0004\u0005\u0005\u0011\u0006bBAs!\u0001\u0007\u0011q]\u0001\u0002mB91-a\u000b\u0002Z\u0006u\u0017!F7bi\u0016\u0014\u0018.\u00197ju\u00164%o\\7WC2,X-M\u000b\t\u0003[\f\u00190!?\u0003\u0006U\u0011\u0011q\u001e\t\u0007}\u000e\t\t0!>\u0011\t\u0005\u0005\u00111\u001f\u0003\b\u0003\u000b\t\"\u0019AA\u0004!\u001dy\u00161LA|\u0003\u0013\u0002b!!\u0001\u0002z\n\rAaBA~#\t\u0007\u0011Q \u0002\u0002\rV!\u0011qAA\u0000\t!\u0011\t!!?C\u0002\u0005\u001d!!A0\u0011\t\u0005\u0005!Q\u0001\u0003\b\u0003G\n\"\u0019AA\u0004Q\u0015\t\"\u0011\u0002B\u000f!\u0011\u0011YA!\u0007\u000e\u0005\t5!\u0002\u0002B\b\u0005#\t\u0001\"\u001b8uKJt\u0017\r\u001c\u0006\u0005\u0005\'\u0011)\"\u0001\u0004nC\u000e\u0014xn\u001d\u0006\u0004\u0005/!\u0017a\u0002:fM2,7\r^\u0005\u0005\u00057\u0011iAA\u0005nC\u000e\u0014x.S7qYFZaDa\b\u0003\"\t5&\u0011\u0017B\\\u0017\u0001\t\u0014c\bB\u0010\u0005G\u00119C!\u000f\u0003J\te#1\u000eB?c\u0019!#qD/\u0003&\u0005)Q.Y2s_F:aCa\b\u0003*\tE\u0012\'B\u0013\u0003,\t5rB\u0001B\u0017C\t\u0011y#A\u0006nC\u000e\u0014x.\u00128hS:,\u0017\'B\u0013\u00034\tUrB\u0001B\u001bC\t\u00119$A\u0013wo9\u0002\u0004\u0005K5na2,W.\u001a8uK\u0012\u0004\u0013N\u001c\u0011TG\u0006d\u0017\r\t\u001a/cEr\u0003\'L\'9SE:aCa\b\u0003<\t\r\u0013\'B\u0013\u0003>\t}rB\u0001B C\t\u0011\t%\u0001\u0005jg\n+h\u000e\u001a7fc\u0015)#Q\tB$\u001f\t\u00119%G\u0001\u0002c\u001d1\"q\u0004B&\u0005\'\nT!\nB\'\u0005\u001fz!Aa\u0014\"\u0005\tE\u0013AC5t\u00052\f7m\u001b2pqF*QE!\u0016\u0003X=\u0011!qK\r\u0002\u0001E:aCa\b\u0003\\\t\r\u0014\'B\u0013\u0003^\t}sB\u0001B0C\t\u0011\t\'A\u0005dY\u0006\u001c8OT1nKF*QE!\u001a\u0003h=\u0011!qM\u0011\u0003\u0005S\nAc\u001d5ba\u0016dWm]:/!>d\u00170T1de>\u001c\u0018g\u0002\f\u0003 \t5$QO\u0019\u0006K\t=$\u0011O\b\u0003\u0005c\n#Aa\u001d\u0002\u00155,G\u000f[8e\u001d\u0006lW-M\u0003&\u0005o\u0012Ih\u0004\u0002\u0003z\u0005\u0012!1P\u0001\u0019[\u0006$XM]5bY&TXM\u0012:p[Z\u000bG.^3J[Bd\u0017g\u0002\f\u0003 \t}$qQ\u0019\u0006K\t\u0005%1Q\b\u0003\u0005\u0007\u000b#A!\"\u0002\u0013MLwM\\1ukJ,\u0017gB\u0010\u0003 \t%%qS\u0019\bI\t}!1\u0012BG\u0013\u0011\u0011iIa$\u0002\t1K7\u000f\u001e\u0006\u0005\u0005#\u0013\u0019*A\u0005j[6,H/\u00192mK*\u0019!Q\u00133\u0002\u0015\r|G\u000e\\3di&|g.M\u0006 \u0005?\u0011IJa\'\u0003\"\n\u001d\u0016g\u0002\u0013\u0003 \t-%QR\u0019\u0006K\tu%qT\b\u0003\u0005?k\u0012\u0001A\u0019\u0006K\t\r&QU\b\u0003\u0005Kk\u0012!A\u0019\u0006K\t%&1V\b\u0003\u0005Wk\u0012AA\u0019\u0004M\t=\u0006\u0003BA\u0001\u0003g\f4A\nBZ!\u0019\t\t!!?\u00036B!\u0011\u0011\u0001B\u0003c\r1#QW\u0001\u0016[\u0006$XM]5bY&TXM\u0012:p[Z\u000bG.^33+\u0019\u0011iLa1\u0003JV\u0011!q\u0018\t\u0007}\u000e\u0011\tM!2\u0011\t\u0005\u0005!1\u0019\u0003\b\u0003\u000b\u0011\"\u0019AA\u0004!\u001dy\u00161\fBd\u0003\u0013\u0002B!!\u0001\u0003J\u00129\u00111\r\nC\u0002\u0005\u001d\u0001&\u0002\n\u0003\n\t5\u0017g\u0003\u0010\u0003 \t=71AB\u0004\u0007\u0017\t\u0014c\bB\u0010\u0005#\u0014\u0019N!7\u0003`\n\u0015(1\u001eByc\u0019!#qD/\u0003&E:aCa\b\u0003V\n]\u0017\'B\u0013\u0003,\t5\u0012\'B\u0013\u00034\tU\u0012g\u0002\f\u0003 \tm\'Q\\\u0019\u0006K\tu\"qH\u0019\u0006K\t\u0015#qI\u0019\b-\t}!\u0011\u001dBrc\u0015)#Q\nB(c\u0015)#Q\u000bB,c\u001d1\"q\u0004Bt\u0005S\fT!\nB/\u0005?\nT!\nB3\u0005O\ntA\u0006B\u0010\u0005[\u0014y/M\u0003&\u0005_\u0012\t(M\u0003&\u0005o\u0012I(M\u0004\u0017\u0005?\u0011\u0019P!>2\u000b\u0015\u0012\tIa!2\u000f}\u0011yBa>\u0003zF:AEa\b\u0003\f\n5\u0015gC\u0010\u0003 \tm(Q B\u0000\u0007\u0003\tt\u0001\nB\u0010\u0005\u0017\u0013i)M\u0003&\u0005;\u0013y*M\u0003&\u0005G\u0013)+M\u0003&\u0005S\u0013Y+M\u0002\'\u0007\u000b\u0001B!!\u0001\u0003DF\u001aae!\u0003\u0011\t\u0005\u0005!\u0011Z\u0019\u0004M\r%\u0011\u0001D<sSR,\'+\u001a9mC\u000e,GCAB\t!\u0011\u0019\u0019b!\u0007\u000e\u0005\rU!\u0002BB\f\u00033\u000bA\u0001\\1oO&!11DB\u000b\u0005\u0019y%M[3di\n)1)Y:faU!1\u0011EB\u0013!\u0019q8aa\t\u0002JA!\u0011\u0011AB\u0013\t\u001d\t)\u0001\u0006b\u0001\u0003\u000f\tQaQ1tKB\u0002\"A \f\u0014\u0005Y\u0011GCAB\u0015+\u0019\u0019\tda\u000e\u0004<AI11\u0007\b\u00046\u0005%3\u0011\b\b\u0003}.\u0001B!!\u0001\u00048\u00119\u0011Q\u0001\rC\u0002\u0005\u001d\u0001\u0003BA\u0001\u0007w!q!a\u0019\u0019\u0005\u0004\t9!\u0006\u0004\u0004@\r\u001d31\n\u000b\u0005\u0007\u0003\u001ai\u0005E\u0004\u0004Da\u0019)e!\u0013\u000e\u0003Y\u0001B!!\u0001\u0004H\u00119\u0011QA\rC\u0002\u0005\u001d\u0001\u0003BA\u0001\u0007\u0017\"q!a\u0019\u001a\u0005\u0004\t9\u0001C\u0004\u0002ff\u0001\ra!\u0013\u0003\u000f\r{W\u000e]8tKV111KB0\u0007K\u001aBA\u00072\u0004VA\u0019qla\u0016\n\u0007\re3L\u0001\u0003Q_2L\u0018!\u00014\u0011\t\u0005\u00051q\f\u0003\b\u0003wT\"\u0019AA\u0004\u0003\u00059\u0007\u0003BA\u0001\u0007K\"qaa\u001a\u001b\u0005\u0004\t9AA\u0001H)\u0019\u0019Yg!\u001c\u0004pA1aPGB/\u0007GBqaa\u0017\u001e\u0001\u0004\u0019i\u0006C\u0004\u0004bu\u0001\raa\u0019\u0002\u000f\r{W\u000e]8tKB\u0011apH\n\u0005?\t\f\t\n\u0006\u0002\u0004t\u0005Y1m\\7q_N,7)Y:f+9\u0019iha\"\u0004(\u000e56qRBa\u0007+#\u0002ba \u0004\u001a\u000e=61\u0019\n\u0005\u0007\u0003\u001b\u0019I\u0002\u0004\u0002*\u0006\u00021q\u0010\t\u0007}\u000e\u0019)ia#\u0011\t\u0005\u00051q\u0011\u0003\b\u0007\u0013\u000b#\u0019AA\u0004\u0005\u0005\u0019\u0005cB0\u0002\\\r5\u0015\u0011\n\t\u0005\u0003\u0003\u0019y\tB\u0004\u0002d\u0005\u0012\r!a\u0002\u0006\u000f\u0005\r2\u0011\u0011\u0001\u0004\u0014B!\u0011\u0011ABK\t\u001d\u00199*\tb\u0001\u0003\u000f\u0011\u0011A\u0016\u0005\b\u00077\u000b\u00039ABO\u0003\u0019)h\u000e]1dWBYqla(\u0004\u0006\u000e\r6QUBV\u0013\r\u0019\tk\u0017\u0002\b+:\u0004\u0018mY63!\tq(\u0004\u0005\u0003\u0002\u0002\r\u001dFaBA~C\t\u00071\u0011V\t\u0005\u0003\u0013\u0019)\u0006\u0005\u0003\u0002\u0002\r5FaBB4C\t\u00071\u0011\u0016\u0005\b\u0007c\u000b\u00039ABZ\u0003\t\u0019w\t\u0005\u0006\u00046\u000em61VBG\u0007\u007fs1A`B\\\u0013\r\u0019I,[\u0001\u0006\u0007\u0006\u001cX-M\u0005\u0005\u0003C\u001biLC\u0002\u0004:&\u0004B!!\u0001\u0004B\u00129\u0011QP\u0011C\u0002\u0005\u001d\u0001bBBcC\u0001\u000f1qY\u0001\u0003G\u001a\u0003\"b!.\u0004<\u000e\u00156qXBJ\u0005)\u0011v\u000e^1uK2+g\r^\u000b\u0007\u0007\u001b\u001c\u0019na7\u0014\t\r\u00127QK\u0001\u0002aB!\u0011\u0011ABj\t\u001d\t)a\tb\u0001\u0003\u000f!Baa6\u0004`B1apIBi\u00073\u0004B!!\u0001\u0004\\\u001291Q\\\u0012C\u0002\u0005\u001d!!\u0001(\t\u000f\r=W\u00051\u0001\u0004R\u0006Q!k\u001c;bi\u0016dUM\u001a;\u0011\u0005y<3\u0003B\u0014c\u0003##\"aa9\u0002\u001dI|G/\u0019;f\u0019\u00164GoQ1tKVq1Q^Bz\t\u0013!i\u0001b\b\u0004~\u000e]H\u0003CBx\t\u0003!9\u0002\"\t\u0011\u0013\rMbb!=\u0004v\u000em\b\u0003BA\u0001\u0007g$qa!#*\u0005\u0004\t9\u0001\u0005\u0003\u0002\u0002\r]HaBB}S\t\u0007\u00111\u0004\u0002\u0003%2\u0003B!!\u0001\u0004~\u001291q`\u0015C\u0002\u0005\u001d!\u0001\u0002\'PkRDqaa\'*\u0001\b!\u0019\u0001E\u0006`\u0007?\u001b\t\u0010\"\u0002\u0005\b\u0011-\u0001C\u0001@$!\u0011\t\t\u0001\"\u0003\u0005\u000f\u0005\u0015\u0011F1\u0001\u0004*B!\u0011\u0011\u0001C\u0007\t\u001d\u0019i.\u000bb\u0001\t\u001f\tB!!\u0003\u0005\u0012A\u0019q\fb\u0005\n\u0007\u0011U1LA\u0002OCRDq\u0001\"\u0007*\u0001\b!Y\"\u0001\u0002d!BI11\u0007\b\u0005\b\u0011u11 \t\u0005\u0003\u0003!y\u0002B\u0004\u0002\u001a%\u0012\r!a\u0007\t\u000f\u0011\r\u0012\u0006q\u0001\u0005&\u0005Y!o\u001c;bi\u0016\u0014\u0016n\u001a5u!)!9\u0003b\u000f\u0004v\u0012-AQ\u0004\b\u0005\tS!)D\u0004\u0003\u0005,\u0011ERB\u0001C\u0017\u0015\r!ycW\u0001\u0004_B\u001c\u0018\u0002\u0002C\u001a\t[\tQ\u0001\u001b7jgRLA\u0001b\u000e\u0005:\u0005Y!k\u001c;bi\u0016\u0014\u0016n\u001a5u\u0015\u0011!\u0019\u0004\"\f\n\t\u0005\u0005FQH\u0005\u0005\t\u007f!ID\u0001\fM_^\u0004&/[8sSRL(k\u001c;bi\u0016\u0014\u0016n\u001a5u\u0005-\u0011v\u000e^1uKJKw\r\u001b;\u0016\r\u0011\u0015C\u0011\nC)\'\u0011Y#m!\u0016\u0011\t\u0005\u0005A\u0011\n\u0003\b\u0003\u000bY#\u0019AA\u0004)\u0011!i\u0005b\u0015\u0011\ry\\Cq\tC(!\u0011\t\t\u0001\"\u0015\u0005\u000f\ru7F1\u0001\u0002\b!91qZ\u0017A\u0002\u0011\u001d\u0003C\u0001@0\'\u0011y#-!%\u0015\u0005\u0011USC\u0004C/\tG\")\b\"\u001f\u0005\u0002\u0012-Dq\r\u000b\t\t?\"i\u0007b\u001f\u0005\u0004BI11\u0007\b\u0005b\u0011\u0015D\u0011\u000e\t\u0005\u0003\u0003!\u0019\u0007B\u0004\u0004\nF\u0012\r!a\u0002\u0011\t\u0005\u0005Aq\r\u0003\b\u0007s\f$\u0019AA\u000e!\u0011\t\t\u0001b\u001b\u0005\u000f\r}\u0018G1\u0001\u0002\b!911T\u0019A\u0004\u0011=\u0004cC0\u0004 \u0012\u0005D\u0011\u000fC:\to\u0002\"A`\u0016\u0011\t\u0005\u0005AQ\u000f\u0003\b\u0003\u000b\t$\u0019ABU!\u0011\t\t\u0001\"\u001f\u0005\u000f\ru\u0017G1\u0001\u0005\u0010!9A\u0011D\u0019A\u0004\u0011u\u0004#CB\u001a\u001d\u0011MDq\u0010C5!\u0011\t\t\u0001\"!\u0005\u000f\u0005e\u0011G1\u0001\u0002\u001c!9AQQ\u0019A\u0004\u0011\u001d\u0015A\u0003:pi\u0006$X\rT3giBQA\u0011\u0012CG\tK\"9\bb \u000f\t\u0011%B1R\u0005\u0005\u0007C$I$\u0003\u0003\u0002\"\u0012=\u0015\u0002\u0002CI\ts\u0011Q\u0003T8x!JLwN]5usJ{G/\u0019;f\u0019\u00164GO\u0001\b%[&tWo\u001d\u0013he\u0016\fG/\u001a:\u0016\r\u0011]E1\u0015CT\'\u0011\u0019$\r\"\'\u0011\u0007}#Y*C\u0002\u0005\u001en\u0013Q\u0001U8msF\u0002raYA\u0016\tC#)\u000b\u0005\u0003\u0002\u0002\u0011\rFaBA2g\t\u0007\u0011q\u0001\t\u0005\u0003\u0003!9\u000bB\u0004\u0002bN\u0012\r!a\u0002\u0015\t\u0011-FQ\u0016\t\u0007}N\"\t\u000b\"*\t\u000f\rmS\u00071\u0001\u0005 \u0006!1/\u001e2U+\u0011!\u0019\fb2\u0016\u0005\u0011U&\u0003\u0002C\\\t\u007f3a!!+\u0001\u0001\u0011U\u0016\u0002BA\u001a\twKA\u0001\"0\u0005\u001c\nY1)Y:f\u0005VLG\u000eZ3s!\u0019!\t\rb1\u0005F6\t1\'C\u0002n\t7\u0003B!!\u0001\u0005H\u00129\u0011Q\u0010\u001cC\u0002\u0011%\u0017\u0003BA\u0005\tC+q!a\t\u00058\u0002!)K\u0001\rM_^\u0004&/[8sSRLH*\u001b4u\rVt7\r^5p]F\u001aBa\u000e2\u0005\u001a\u00061A%\u001b8ji\u0012\"\"\u0001\"6\u0011\u0007\r$9.C\u0002\u0005Z\u0012\u0014A!\u00168ji\u00069A-\u001a4bk2$X\u0003\u0002Cp\tW,\"\u0001\"9\u0013\t\u0011\rHQ\u001d\u0004\u0007\u0003S\u0003\u0001\u0001\"9\u0011\r\u0011\u001dH1\u0019Cu\u001b\u00059\u0004\u0003BA\u0001\tW$q!a\u0019:\u0005\u0004\t9!B\u0004\u0002$\u0011\r\b!!\u0013\u0003-\u0011:\'/Z1uKJ$S.\u001b8vg\u0012:\'/Z1uKJ,b\u0001b=\u0005|\u0012}8\u0003\u0002\u001ec\tk\u0004\"A`\u001c\u0011\u000f\r\fY\u0003\"?\u0005~B!\u0011\u0011\u0001C~\t\u001d\t\u0019G\u000fb\u0001\u0003\u000f\u0001B!!\u0001\u0005\u0000\u00129\u0011\u0011\u001d\u001eC\u0002\u0005\u001dA\u0003BC\u0002\u000b\u000b\u0001bA \u001e\u0005z\u0012u\bbBB.y\u0001\u0007Aq_\u000b\u0005\u000b\u0013))\"\u0006\u0002\u0006\fI!QQBC\b\r\u0019\tI\u000b\u0001\u0001\u0006\fA1Q\u0011\u0003Cb\u000b\'i\u0011A\u000f\t\u0005\u0003\u0003))\u0002B\u0004\u0002~u\u0012\r!b\u0006\u0012\t\u0005%A\u0011`\u0003\b\u0003G)i\u0001AC\u000e!\u001dy\u00161\fC\u007f\u0003\u0013\u0012\u0001\u0003T8x!JLwN]5us2Kg\r^+\u0014\ty\u00127QK\u000b\u0005\u000bG)\u0019$\u0006\u0002\u0006&I!QqEC\u0015\r\u0019\tI\u000b\u0011\u0001\u0006&A1Q1FC\u0017\u000bci\u0011AP\u0005\u0005\u000b_\u00199FA\u0006Qe>$Wo\u0019;DCN,\u0007\u0003BA\u0001\u000bg!q!!\u0007A\u0005\u0004\tY\"B\u0004\u0002$\u0015\u001d\u0002!!\u0013\t\u0015\u0005\u0015Rq\u0005b\u0001\n\u0003)I$\u0006\u0002\u0006<A91-a\u000b\u00062\u0015ubbA0\u0006@%\u0019Q\u0011I.\u0002\t!s\u0015\u000e\u001c\u0002\u0006\u0019&4G/V\u000b\u0005\u000b\u000f*ie\u0005\u0003BE\u0016%\u0003C\u0001@?!\u0011\t\t!\"\u0014\u0005\u000f\u0005\u0015\u0011I1\u0001\u0004*R!Q\u0011KC*!\u0011q\u0018)b\u0013\t\u000f\r=7\t1\u0001\u0006L\u00059A-\u001a4j]\u0016$W\u0003BC-\u000bK\"B!b\u0017\u0006pI!QQLC0\r\u0019\tI\u000b\u0012\u0001\u0006\\A1Q\u0011MC\u0017\u000bGj\u0011!\u0011\t\u0005\u0003\u0003))\u0007B\u0004\u0002\u001a\u0011\u0013\r!a\u0007\u0006\u000f\u0005\rRQ\f\u0001\u0006jA9q,a\u0017\u0006l\u0005%\u0003cAC7\u000b9!\u0011\u0011AC8\u0011\u001d)\t\b\u0012a\u0002\u000bg\nQaY1tKR\u0003bA`\u0002\u0006L\u0015\r$A\u0004\u0013uS2$W\rJ4sK\u0006$XM]\u000b\u0007\u000bs*y)\"!\u0014\t\u0015\u0013G\u0011T\u000b\u0005\u000b{*I\t\u0006\u0003\u0006\u0000\u0015-\u0005CBA\u0001\u000b\u0003+9\tB\u0004\u0004h\u0015\u0013\r!b!\u0016\t\u0005\u001dQQ\u0011\u0003\t\u0005\u0003)\tI1\u0001\u0002\bA!\u0011\u0011ACE\t\u001d\t\u0019g\u0012b\u0001\u0003\u000fAqaa\u0017H\u0001\u0004)i\t\u0005\u0004\u0002\u0002\u0015=Uq\u0011\u0003\b\u0003w,%\u0019ACI+\u0011\t9!b%\u0005\u0011\t\u0005Qq\u0012b\u0001\u0003\u000f\t\u0001bY1tKVs\u0017N^\u000b\u0005\u000b3+Y+\u0006\u0002\u0006\u001cBAQQTCR\u000bO+iK\u0004\u0003\u0006 \u0016\u0005V\"A#\n\t\u0005\u0015E1T\u0005\u0005\u0003C+)K\u0003\u0003\u0002\u0006\u0012m\u0005CBA\u0001\u000b\u001f+I\u000b\u0005\u0003\u0002\u0002\u0015-FaBA2\u0011\n\u0007\u0011q\u0001\t\u0007\u0003\u0003)\t)\"+\u0002\u001d\u0011\"\u0018\u000e\u001c3fI\u001d\u0014X-\u0019;feB\u0011aPS\n\u0005\u0015\n\f\t\n\u0006\u0002\u00062\u0006)\u0011N\\:ucUAQ1XCa\u000b\u001b,I\r\u0006\u0003\u0006>\u0016M\u0007cB2\u0002,\u0015}V1\u001a\t\u0007\u0003\u0003)\t-b2\u0005\u000f\u0005mHJ1\u0001\u0006DV!\u0011qACc\t!\u0011\t!\"1C\u0002\u0005\u001d\u0001\u0003BA\u0001\u000b\u0013$q!a\u0019M\u0005\u0004\t9\u0001\u0005\u0004\u0002\u0002\u00155Wq\u0019\u0003\b\u0007Ob%\u0019ACh+\u0011\t9!\"5\u0005\u0011\t\u0005QQ\u001ab\u0001\u0003\u000fAqaa\u0017M\u0001\u0004))\u000e\u0005\u0004\u007f\u000b\u0016]W\u0011\u001c\t\u0005\u0003\u0003)\t\r\u0005\u0003\u0002\u0002\u00155\u0017!B5ogR\u0014TCBCp\u000bS,)\u000f\u0006\u0003\u0006b\u0016=\bcB2\u0002,\u0015\rXq\u001d\t\u0005\u0003\u0003))\u000fB\u0004\u0002d5\u0013\r!a\u0002\u0011\r\u0005\u0005Q\u0011^Cr\t\u001d\u00199\'\u0014b\u0001\u000bW,B!a\u0002\u0006n\u0012A!\u0011ACu\u0005\u0004\t9\u0001C\u0004\u0004\\5\u0003\r!\"=\u0011\ry,U1_C\u0000!\u0011))0\"?\u000f\u0007}+90\u0003\u0002y7&!Q1`C\u007f\u0005\tIEM\u0003\u0002y7B!\u0011\u0011ACu\u0003\u0015Ign\u001d;4+\u00191)Ab\u0003\u0007\u0014Q!aq\u0001D\u000b!\u001d\u0019\u00171\u0006D\u0005\r#\u0001b!!\u0001\u0007\f\u0019EAaBA~\u001d\n\u0007aQB\u000b\u0005\u0003\u000f1y\u0001\u0002\u0005\u0003\u0002\u0019-!\u0019AA\u0004!\u0011\t\tAb\u0005\u0005\u000f\u0005\rdJ1\u0001\u0002\b!911\f(A\u0002\u0019]\u0001C\u0002@F\r3)\u0019\u0010\u0005\u0003\u0002\u0002\u0019-\u0011!B5ogR$T\u0003\u0002D\u0010\rK!BA\"\t\u0007(A91-a\u000b\u0007$\u0019\r\u0002\u0003BA\u0001\rK!q!a\u0019P\u0005\u0004\t9\u0001C\u0004\u0004\\=\u0003\rA\"\u000b\u0011\ry,U1_Cz\u0003\u0015Ign\u001d;6+!1yC\"\u000e\u0007B\u0019uB\u0003\u0002D\u0019\r\u0007\u0002raYA\u0016\rg1y\u0004\u0005\u0004\u0002\u0002\u0019Ub1\b\u0003\b\u0003w\u0004&\u0019\u0001D\u001c+\u0011\t9A\"\u000f\u0005\u0011\t\u0005aQ\u0007b\u0001\u0003\u000f\u0001B!!\u0001\u0007>\u00119\u00111\r)C\u0002\u0005\u001d\u0001\u0003BA\u0001\r\u0003\"qaa\u001aQ\u0005\u0004\t9\u0001C\u0004\u0004\\A\u0003\rA\"\u0012\u0011\ry,eq\tD%!\u0011\t\tA\"\u000e\u0016\t\u0019}b1\n\u0003\t\u0003G2iE1\u0001\u0002\b!9aq\nD)\u0001\t}\u0011A\u0003\u001fm_\u000e\fG\u000e\th<~\u00159a1\u000bD+\u0001\u0019e#A\u0001h<\u000e\u0019\tI\u000b\u0001\u0001\u0007XI\u0019aQ\u000b2\u0016\t\u0019mcQ\f\t\u0005\u0003\u00031\t\u0005\u0002\u0005\u0002d\u0019E#\u0019AA\u0004\u0003\u0015Ign\u001d;7+\u00191\u0019G\"\u001c\u0007jQ!aQ\rD8!\u001d\u0019\u00171\u0006D4\rW\u0002B!!\u0001\u0007j\u00119\u00111M)C\u0002\u0005\u001d\u0001\u0003BA\u0001\r[\"qaa\u001aR\u0005\u0004\t9\u0001C\u0004\u0004\\E\u0003\rA\"\u001d\u0011\ry,U1\u001fD:+\u00111YG\"\u001e\u0005\u0011\u0005\rdq\u000fb\u0001\u0003\u000fAqAb\u0014\u0007z\u0001\u0011y\"B\u0004\u0007T\u0019m\u0004Ab \u0007\r\u0005%\u0006\u0001\u0001D?%\r1YHY\u000b\u0005\r\u00033\u0019\t\u0005\u0003\u0002\u0002\u00195D\u0001CA2\rs\u0012\r!a\u0002\u0002\u000b%t7\u000f^\u001c\u0016\r\u0019%eq\u0012DJ)\u00111YI\"&\u0011\u000f\r\fYC\"$\u0007\u0012B!\u0011\u0011\u0001DH\t\u001d\tYP\u0015b\u0001\u0003\u000f\u0001B!!\u0001\u0007\u0014\u001291q\r*C\u0002\u0005\u001d\u0001bBB.%\u0002\u0007aq\u0013\t\u0007}\u00163IJb+\u0016\t\u00195e1\u0014\u0003\t\u0003G2iJ1\u0001\u0002\b!9aq\nDP\u0001\t}Qa\u0002D*\rC\u0003aQ\u0015\u0004\u0007\u0003S\u0003\u0001Ab)\u0013\u0007\u0019\u0005&-\u0006\u0003\u0007(\u001a%\u0006\u0003BA\u0001\r\u001f#\u0001\"a\u0019\u0007 \n\u0007\u0011qA\u000b\u0005\r#3i\u000b\u0002\u0005\u0002d\u0019=&\u0019AA\u0004\u0011\u001d1yE\"-\u0001\u0005?)qAb\u0015\u00074\u000219L\u0002\u0004\u0002*\u0002\u0001aQ\u0017\n\u0004\rg\u0013W\u0003\u0002D]\rw\u0003B!!\u0001\u0007\u0014\u0012A\u00111\rDY\u0005\u0004\t9A\u0001\f%i&dG-\u001a\u0013he\u0016\fG/\u001a:%OJ,\u0017\r^3s+\u00191\tM\"2\u0007PB1a0\u0012Db\r\u0017\u0004B!!\u0001\u0007F\u00129\u00111 +C\u0002\u0019\u001dW\u0003BA\u0004\r\u0013$\u0001B!\u0001\u0007F\n\u0007\u0011qA\u000b\u0005\r\u001b4\t\u000e\u0005\u0003\u0002\u0002\u0019=GaBAq)\n\u0007\u0011q\u0001\u0003\t\u0003G2\u0019N1\u0001\u0002\b!9aq\nDk\u0001\t}Qa\u0002D*\r/\u0004a1\u001c\u0004\u0007\u0003S\u0003\u0001A\"7\u0013\u0007\u0019]\'-\u0006\u0003\u0007N\u001auG\u0001CA2\r+\u0014\r!a\u0002\u0002\u0011%$WM\u001c;jif\u0004\"A ,\u0003\u0011%$WM\u001c;jif\u001cBA\u00162\u0007*Q\u0011a\u0011]\u000b\u0005\rW4y\u000f\u0006\u0003\u0007n\u001aE\b\u0003BA\u0001\r_$q!a\u0019Y\u0005\u0004\t9\u0001C\u0004\u0002:a\u0003\rA\"<
    #9 = Utf8               shapeless/Cases$Case1$
   #10 = Class              #9            // shapeless/Cases$Case1$
   #11 = Utf8               shapeless/Cases
   #12 = Class              #11           // shapeless/Cases
   #13 = Utf8               Case1$
   #14 = Utf8               shapeless/Cases$Case10$
   #15 = Class              #14           // shapeless/Cases$Case10$
   #16 = Utf8               Case10$
   #17 = Utf8               shapeless/Cases$Case11$
   #18 = Class              #17           // shapeless/Cases$Case11$
   #19 = Utf8               Case11$
   #20 = Utf8               shapeless/Cases$Case12$
   #21 = Class              #20           // shapeless/Cases$Case12$
   #22 = Utf8               Case12$
   #23 = Utf8               shapeless/Cases$Case13$
   #24 = Class              #23           // shapeless/Cases$Case13$
   #25 = Utf8               Case13$
   #26 = Utf8               shapeless/Cases$Case14$
   #27 = Class              #26           // shapeless/Cases$Case14$
   #28 = Utf8               Case14$
   #29 = Utf8               shapeless/Cases$Case15$
   #30 = Class              #29           // shapeless/Cases$Case15$
   #31 = Utf8               Case15$
   #32 = Utf8               shapeless/Cases$Case16$
   #33 = Class              #32           // shapeless/Cases$Case16$
   #34 = Utf8               Case16$
   #35 = Utf8               shapeless/Cases$Case17$
   #36 = Class              #35           // shapeless/Cases$Case17$
   #37 = Utf8               Case17$
   #38 = Utf8               shapeless/Cases$Case18$
   #39 = Class              #38           // shapeless/Cases$Case18$
   #40 = Utf8               Case18$
   #41 = Utf8               shapeless/Cases$Case19$
   #42 = Class              #41           // shapeless/Cases$Case19$
   #43 = Utf8               Case19$
   #44 = Utf8               shapeless/Cases$Case2$
   #45 = Class              #44           // shapeless/Cases$Case2$
   #46 = Utf8               Case2$
   #47 = Utf8               shapeless/Cases$Case20$
   #48 = Class              #47           // shapeless/Cases$Case20$
   #49 = Utf8               Case20$
   #50 = Utf8               shapeless/Cases$Case21$
   #51 = Class              #50           // shapeless/Cases$Case21$
   #52 = Utf8               Case21$
   #53 = Utf8               shapeless/Cases$Case22$
   #54 = Class              #53           // shapeless/Cases$Case22$
   #55 = Utf8               Case22$
   #56 = Utf8               shapeless/Cases$Case3$
   #57 = Class              #56           // shapeless/Cases$Case3$
   #58 = Utf8               Case3$
   #59 = Utf8               shapeless/Cases$Case4$
   #60 = Class              #59           // shapeless/Cases$Case4$
   #61 = Utf8               Case4$
   #62 = Utf8               shapeless/Cases$Case5$
   #63 = Class              #62           // shapeless/Cases$Case5$
   #64 = Utf8               Case5$
   #65 = Utf8               shapeless/Cases$Case6$
   #66 = Class              #65           // shapeless/Cases$Case6$
   #67 = Utf8               Case6$
   #68 = Utf8               shapeless/Cases$Case7$
   #69 = Class              #68           // shapeless/Cases$Case7$
   #70 = Utf8               Case7$
   #71 = Utf8               shapeless/Cases$Case8$
   #72 = Class              #71           // shapeless/Cases$Case8$
   #73 = Utf8               Case8$
   #74 = Utf8               shapeless/Cases$Case9$
   #75 = Class              #74           // shapeless/Cases$Case9$
   #76 = Utf8               Case9$
   #77 = Utf8               shapeless/PolyDefns$$greater$minus$greater
   #78 = Class              #77           // shapeless/PolyDefns$$greater$minus$greater
   #79 = Utf8               $greater$minus$greater
   #80 = Utf8               shapeless/PolyDefns$$minus$greater
   #81 = Class              #80           // shapeless/PolyDefns$$minus$greater
   #82 = Utf8               $minus$greater
   #83 = Utf8               shapeless/PolyDefns$$tilde$greater
   #84 = Class              #83           // shapeless/PolyDefns$$tilde$greater
   #85 = Utf8               $tilde$greater
   #86 = Utf8               shapeless/PolyDefns$$tilde$greater$
   #87 = Class              #86           // shapeless/PolyDefns$$tilde$greater$
   #88 = Utf8               $tilde$greater$
   #89 = Utf8               shapeless/PolyDefns$Case
   #90 = Class              #89           // shapeless/PolyDefns$Case
   #91 = Utf8               Case
   #92 = Utf8               shapeless/PolyDefns$Case$
   #93 = Class              #92           // shapeless/PolyDefns$Case$
   #94 = Utf8               Case$
   #95 = Utf8               shapeless/PolyDefns$Case0$
   #96 = Class              #95           // shapeless/PolyDefns$Case0$
   #97 = Utf8               Case0$
   #98 = Utf8               shapeless/PolyDefns$Compose
   #99 = Class              #98           // shapeless/PolyDefns$Compose
  #100 = Utf8               Compose
  #101 = Utf8               shapeless/PolyDefns$Compose$
  #102 = Class              #101          // shapeless/PolyDefns$Compose$
  #103 = Utf8               Compose$
  #104 = Utf8               shapeless/PolyDefns$LiftU
  #105 = Class              #104          // shapeless/PolyDefns$LiftU
  #106 = Utf8               LiftU
  #107 = Utf8               shapeless/PolyDefns$LowPriorityLiftFunction1
  #108 = Class              #107          // shapeless/PolyDefns$LowPriorityLiftFunction1
  #109 = Utf8               LowPriorityLiftFunction1
  #110 = Utf8               shapeless/PolyDefns$LowPriorityLiftU
  #111 = Class              #110          // shapeless/PolyDefns$LowPriorityLiftU
  #112 = Utf8               LowPriorityLiftU
  #113 = Utf8               shapeless/PolyDefns$RotateLeft
  #114 = Class              #113          // shapeless/PolyDefns$RotateLeft
  #115 = Utf8               RotateLeft
  #116 = Utf8               shapeless/PolyDefns$RotateLeft$
  #117 = Class              #116          // shapeless/PolyDefns$RotateLeft$
  #118 = Utf8               RotateLeft$
  #119 = Utf8               shapeless/PolyDefns$RotateRight
  #120 = Class              #119          // shapeless/PolyDefns$RotateRight
  #121 = Utf8               RotateRight
  #122 = Utf8               shapeless/PolyDefns$RotateRight$
  #123 = Class              #122          // shapeless/PolyDefns$RotateRight$
  #124 = Utf8               RotateRight$
  #125 = Utf8               shapeless/PolyDefns$identity$
  #126 = Class              #125          // shapeless/PolyDefns$identity$
  #127 = Utf8               identity$
  #128 = Utf8               Case22
  #129 = Utf8               ()Lshapeless/Cases$Case22$;
  #130 = Utf8               shapeless/PolyDefns$
  #131 = Class              #130          // shapeless/PolyDefns$
  #132 = Utf8               MODULE$
  #133 = Utf8               Lshapeless/PolyDefns$;
  #134 = NameAndType        #132:#133     // MODULE$:Lshapeless/PolyDefns$;
  #135 = Fieldref           #131.#134     // shapeless/PolyDefns$.MODULE$:Lshapeless/PolyDefns$;
  #136 = NameAndType        #128:#129     // Case22:()Lshapeless/Cases$Case22$;
  #137 = Methodref          #131.#136     // shapeless/PolyDefns$.Case22:()Lshapeless/Cases$Case22$;
  #138 = Utf8               Case21
  #139 = Utf8               ()Lshapeless/Cases$Case21$;
  #140 = NameAndType        #138:#139     // Case21:()Lshapeless/Cases$Case21$;
  #141 = Methodref          #131.#140     // shapeless/PolyDefns$.Case21:()Lshapeless/Cases$Case21$;
  #142 = Utf8               Case20
  #143 = Utf8               ()Lshapeless/Cases$Case20$;
  #144 = NameAndType        #142:#143     // Case20:()Lshapeless/Cases$Case20$;
  #145 = Methodref          #131.#144     // shapeless/PolyDefns$.Case20:()Lshapeless/Cases$Case20$;
  #146 = Utf8               Case19
  #147 = Utf8               ()Lshapeless/Cases$Case19$;
  #148 = NameAndType        #146:#147     // Case19:()Lshapeless/Cases$Case19$;
  #149 = Methodref          #131.#148     // shapeless/PolyDefns$.Case19:()Lshapeless/Cases$Case19$;
  #150 = Utf8               Case18
  #151 = Utf8               ()Lshapeless/Cases$Case18$;
  #152 = NameAndType        #150:#151     // Case18:()Lshapeless/Cases$Case18$;
  #153 = Methodref          #131.#152     // shapeless/PolyDefns$.Case18:()Lshapeless/Cases$Case18$;
  #154 = Utf8               Case17
  #155 = Utf8               ()Lshapeless/Cases$Case17$;
  #156 = NameAndType        #154:#155     // Case17:()Lshapeless/Cases$Case17$;
  #157 = Methodref          #131.#156     // shapeless/PolyDefns$.Case17:()Lshapeless/Cases$Case17$;
  #158 = Utf8               Case16
  #159 = Utf8               ()Lshapeless/Cases$Case16$;
  #160 = NameAndType        #158:#159     // Case16:()Lshapeless/Cases$Case16$;
  #161 = Methodref          #131.#160     // shapeless/PolyDefns$.Case16:()Lshapeless/Cases$Case16$;
  #162 = Utf8               Case15
  #163 = Utf8               ()Lshapeless/Cases$Case15$;
  #164 = NameAndType        #162:#163     // Case15:()Lshapeless/Cases$Case15$;
  #165 = Methodref          #131.#164     // shapeless/PolyDefns$.Case15:()Lshapeless/Cases$Case15$;
  #166 = Utf8               Case14
  #167 = Utf8               ()Lshapeless/Cases$Case14$;
  #168 = NameAndType        #166:#167     // Case14:()Lshapeless/Cases$Case14$;
  #169 = Methodref          #131.#168     // shapeless/PolyDefns$.Case14:()Lshapeless/Cases$Case14$;
  #170 = Utf8               Case13
  #171 = Utf8               ()Lshapeless/Cases$Case13$;
  #172 = NameAndType        #170:#171     // Case13:()Lshapeless/Cases$Case13$;
  #173 = Methodref          #131.#172     // shapeless/PolyDefns$.Case13:()Lshapeless/Cases$Case13$;
  #174 = Utf8               Case12
  #175 = Utf8               ()Lshapeless/Cases$Case12$;
  #176 = NameAndType        #174:#175     // Case12:()Lshapeless/Cases$Case12$;
  #177 = Methodref          #131.#176     // shapeless/PolyDefns$.Case12:()Lshapeless/Cases$Case12$;
  #178 = Utf8               Case11
  #179 = Utf8               ()Lshapeless/Cases$Case11$;
  #180 = NameAndType        #178:#179     // Case11:()Lshapeless/Cases$Case11$;
  #181 = Methodref          #131.#180     // shapeless/PolyDefns$.Case11:()Lshapeless/Cases$Case11$;
  #182 = Utf8               Case10
  #183 = Utf8               ()Lshapeless/Cases$Case10$;
  #184 = NameAndType        #182:#183     // Case10:()Lshapeless/Cases$Case10$;
  #185 = Methodref          #131.#184     // shapeless/PolyDefns$.Case10:()Lshapeless/Cases$Case10$;
  #186 = Utf8               Case9
  #187 = Utf8               ()Lshapeless/Cases$Case9$;
  #188 = NameAndType        #186:#187     // Case9:()Lshapeless/Cases$Case9$;
  #189 = Methodref          #131.#188     // shapeless/PolyDefns$.Case9:()Lshapeless/Cases$Case9$;
  #190 = Utf8               Case8
  #191 = Utf8               ()Lshapeless/Cases$Case8$;
  #192 = NameAndType        #190:#191     // Case8:()Lshapeless/Cases$Case8$;
  #193 = Methodref          #131.#192     // shapeless/PolyDefns$.Case8:()Lshapeless/Cases$Case8$;
  #194 = Utf8               Case7
  #195 = Utf8               ()Lshapeless/Cases$Case7$;
  #196 = NameAndType        #194:#195     // Case7:()Lshapeless/Cases$Case7$;
  #197 = Methodref          #131.#196     // shapeless/PolyDefns$.Case7:()Lshapeless/Cases$Case7$;
  #198 = Utf8               Case6
  #199 = Utf8               ()Lshapeless/Cases$Case6$;
  #200 = NameAndType        #198:#199     // Case6:()Lshapeless/Cases$Case6$;
  #201 = Methodref          #131.#200     // shapeless/PolyDefns$.Case6:()Lshapeless/Cases$Case6$;
  #202 = Utf8               Case5
  #203 = Utf8               ()Lshapeless/Cases$Case5$;
  #204 = NameAndType        #202:#203     // Case5:()Lshapeless/Cases$Case5$;
  #205 = Methodref          #131.#204     // shapeless/PolyDefns$.Case5:()Lshapeless/Cases$Case5$;
  #206 = Utf8               Case4
  #207 = Utf8               ()Lshapeless/Cases$Case4$;
  #208 = NameAndType        #206:#207     // Case4:()Lshapeless/Cases$Case4$;
  #209 = Methodref          #131.#208     // shapeless/PolyDefns$.Case4:()Lshapeless/Cases$Case4$;
  #210 = Utf8               Case3
  #211 = Utf8               ()Lshapeless/Cases$Case3$;
  #212 = NameAndType        #210:#211     // Case3:()Lshapeless/Cases$Case3$;
  #213 = Methodref          #131.#212     // shapeless/PolyDefns$.Case3:()Lshapeless/Cases$Case3$;
  #214 = Utf8               Case2
  #215 = Utf8               ()Lshapeless/Cases$Case2$;
  #216 = NameAndType        #214:#215     // Case2:()Lshapeless/Cases$Case2$;
  #217 = Methodref          #131.#216     // shapeless/PolyDefns$.Case2:()Lshapeless/Cases$Case2$;
  #218 = Utf8               Case1
  #219 = Utf8               ()Lshapeless/Cases$Case1$;
  #220 = NameAndType        #218:#219     // Case1:()Lshapeless/Cases$Case1$;
  #221 = Methodref          #131.#220     // shapeless/PolyDefns$.Case1:()Lshapeless/Cases$Case1$;
  #222 = Utf8               Code
  #223 = Utf8               InnerClasses
  #224 = Utf8               SourceFile
  #225 = Utf8               RuntimeVisibleAnnotations
  #226 = Utf8               ScalaSig
{
  public static shapeless.Cases$Case22$ Case22();
    descriptor: ()Lshapeless/Cases$Case22$;
    flags: (0x0009) ACC_PUBLIC, ACC_STATIC
    Code:
      stack=1, locals=0, args_size=0
         0: getstatic     #135                // Field shapeless/PolyDefns$.MODULE$:Lshapeless/PolyDefns$;
         3: invokevirtual #137                // Method shapeless/PolyDefns$.Case22:()Lshapeless/Cases$Case22$;
         6: areturn

  public static shapeless.Cases$Case21$ Case21();
    descriptor: ()Lshapeless/Cases$Case21$;
    flags: (0x0009) ACC_PUBLIC, ACC_STATIC
    Code:
      stack=1, locals=0, args_size=0
         0: getstatic     #135                // Field shapeless/PolyDefns$.MODULE$:Lshapeless/PolyDefns$;
         3: invokevirtual #141                // Method shapeless/PolyDefns$.Case21:()Lshapeless/Cases$Case21$;
         6: areturn

  public static shapeless.Cases$Case20$ Case20();
    descriptor: ()Lshapeless/Cases$Case20$;
    flags: (0x0009) ACC_PUBLIC, ACC_STATIC
    Code:
      stack=1, locals=0, args_size=0
         0: getstatic     #135                // Field shapeless/PolyDefns$.MODULE$:Lshapeless/PolyDefns$;
         3: invokevirtual #145                // Method shapeless/PolyDefns$.Case20:()Lshapeless/Cases$Case20$;
         6: areturn

  public static shapeless.Cases$Case19$ Case19();
    descriptor: ()Lshapeless/Cases$Case19$;
    flags: (0x0009) ACC_PUBLIC, ACC_STATIC
    Code:
      stack=1, locals=0, args_size=0
         0: getstatic     #135                // Field shapeless/PolyDefns$.MODULE$:Lshapeless/PolyDefns$;
         3: invokevirtual #149                // Method shapeless/PolyDefns$.Case19:()Lshapeless/Cases$Case19$;
         6: areturn

  public static shapeless.Cases$Case18$ Case18();
    descriptor: ()Lshapeless/Cases$Case18$;
    flags: (0x0009) ACC_PUBLIC, ACC_STATIC
    Code:
      stack=1, locals=0, args_size=0
         0: getstatic     #135                // Field shapeless/PolyDefns$.MODULE$:Lshapeless/PolyDefns$;
         3: invokevirtual #153                // Method shapeless/PolyDefns$.Case18:()Lshapeless/Cases$Case18$;
         6: areturn

  public static shapeless.Cases$Case17$ Case17();
    descriptor: ()Lshapeless/Cases$Case17$;
    flags: (0x0009) ACC_PUBLIC, ACC_STATIC
    Code:
      stack=1, locals=0, args_size=0
         0: getstatic     #135                // Field shapeless/PolyDefns$.MODULE$:Lshapeless/PolyDefns$;
         3: invokevirtual #157                // Method shapeless/PolyDefns$.Case17:()Lshapeless/Cases$Case17$;
         6: areturn

  public static shapeless.Cases$Case16$ Case16();
    descriptor: ()Lshapeless/Cases$Case16$;
    flags: (0x0009) ACC_PUBLIC, ACC_STATIC
    Code:
      stack=1, locals=0, args_size=0
         0: getstatic     #135                // Field shapeless/PolyDefns$.MODULE$:Lshapeless/PolyDefns$;
         3: invokevirtual #161                // Method shapeless/PolyDefns$.Case16:()Lshapeless/Cases$Case16$;
         6: areturn

  public static shapeless.Cases$Case15$ Case15();
    descriptor: ()Lshapeless/Cases$Case15$;
    flags: (0x0009) ACC_PUBLIC, ACC_STATIC
    Code:
      stack=1, locals=0, args_size=0
         0: getstatic     #135                // Field shapeless/PolyDefns$.MODULE$:Lshapeless/PolyDefns$;
         3: invokevirtual #165                // Method shapeless/PolyDefns$.Case15:()Lshapeless/Cases$Case15$;
         6: areturn

  public static shapeless.Cases$Case14$ Case14();
    descriptor: ()Lshapeless/Cases$Case14$;
    flags: (0x0009) ACC_PUBLIC, ACC_STATIC
    Code:
      stack=1, locals=0, args_size=0
         0: getstatic     #135                // Field shapeless/PolyDefns$.MODULE$:Lshapeless/PolyDefns$;
         3: invokevirtual #169                // Method shapeless/PolyDefns$.Case14:()Lshapeless/Cases$Case14$;
         6: areturn

  public static shapeless.Cases$Case13$ Case13();
    descriptor: ()Lshapeless/Cases$Case13$;
    flags: (0x0009) ACC_PUBLIC, ACC_STATIC
    Code:
      stack=1, locals=0, args_size=0
         0: getstatic     #135                // Field shapeless/PolyDefns$.MODULE$:Lshapeless/PolyDefns$;
         3: invokevirtual #173                // Method shapeless/PolyDefns$.Case13:()Lshapeless/Cases$Case13$;
         6: areturn

  public static shapeless.Cases$Case12$ Case12();
    descriptor: ()Lshapeless/Cases$Case12$;
    flags: (0x0009) ACC_PUBLIC, ACC_STATIC
    Code:
      stack=1, locals=0, args_size=0
         0: getstatic     #135                // Field shapeless/PolyDefns$.MODULE$:Lshapeless/PolyDefns$;
         3: invokevirtual #177                // Method shapeless/PolyDefns$.Case12:()Lshapeless/Cases$Case12$;
         6: areturn

  public static shapeless.Cases$Case11$ Case11();
    descriptor: ()Lshapeless/Cases$Case11$;
    flags: (0x0009) ACC_PUBLIC, ACC_STATIC
    Code:
      stack=1, locals=0, args_size=0
         0: getstatic     #135                // Field shapeless/PolyDefns$.MODULE$:Lshapeless/PolyDefns$;
         3: invokevirtual #181                // Method shapeless/PolyDefns$.Case11:()Lshapeless/Cases$Case11$;
         6: areturn

  public static shapeless.Cases$Case10$ Case10();
    descriptor: ()Lshapeless/Cases$Case10$;
    flags: (0x0009) ACC_PUBLIC, ACC_STATIC
    Code:
      stack=1, locals=0, args_size=0
         0: getstatic     #135                // Field shapeless/PolyDefns$.MODULE$:Lshapeless/PolyDefns$;
         3: invokevirtual #185                // Method shapeless/PolyDefns$.Case10:()Lshapeless/Cases$Case10$;
         6: areturn

  public static shapeless.Cases$Case9$ Case9();
    descriptor: ()Lshapeless/Cases$Case9$;
    flags: (0x0009) ACC_PUBLIC, ACC_STATIC
    Code:
      stack=1, locals=0, args_size=0
         0: getstatic     #135                // Field shapeless/PolyDefns$.MODULE$:Lshapeless/PolyDefns$;
         3: invokevirtual #189                // Method shapeless/PolyDefns$.Case9:()Lshapeless/Cases$Case9$;
         6: areturn

  public static shapeless.Cases$Case8$ Case8();
    descriptor: ()Lshapeless/Cases$Case8$;
    flags: (0x0009) ACC_PUBLIC, ACC_STATIC
    Code:
      stack=1, locals=0, args_size=0
         0: getstatic     #135                // Field shapeless/PolyDefns$.MODULE$:Lshapeless/PolyDefns$;
         3: invokevirtual #193                // Method shapeless/PolyDefns$.Case8:()Lshapeless/Cases$Case8$;
         6: areturn

  public static shapeless.Cases$Case7$ Case7();
    descriptor: ()Lshapeless/Cases$Case7$;
    flags: (0x0009) ACC_PUBLIC, ACC_STATIC
    Code:
      stack=1, locals=0, args_size=0
         0: getstatic     #135                // Field shapeless/PolyDefns$.MODULE$:Lshapeless/PolyDefns$;
         3: invokevirtual #197                // Method shapeless/PolyDefns$.Case7:()Lshapeless/Cases$Case7$;
         6: areturn

  public static shapeless.Cases$Case6$ Case6();
    descriptor: ()Lshapeless/Cases$Case6$;
    flags: (0x0009) ACC_PUBLIC, ACC_STATIC
    Code:
      stack=1, locals=0, args_size=0
         0: getstatic     #135                // Field shapeless/PolyDefns$.MODULE$:Lshapeless/PolyDefns$;
         3: invokevirtual #201                // Method shapeless/PolyDefns$.Case6:()Lshapeless/Cases$Case6$;
         6: areturn

  public static shapeless.Cases$Case5$ Case5();
    descriptor: ()Lshapeless/Cases$Case5$;
    flags: (0x0009) ACC_PUBLIC, ACC_STATIC
    Code:
      stack=1, locals=0, args_size=0
         0: getstatic     #135                // Field shapeless/PolyDefns$.MODULE$:Lshapeless/PolyDefns$;
         3: invokevirtual #205                // Method shapeless/PolyDefns$.Case5:()Lshapeless/Cases$Case5$;
         6: areturn

  public static shapeless.Cases$Case4$ Case4();
    descriptor: ()Lshapeless/Cases$Case4$;
    flags: (0x0009) ACC_PUBLIC, ACC_STATIC
    Code:
      stack=1, locals=0, args_size=0
         0: getstatic     #135                // Field shapeless/PolyDefns$.MODULE$:Lshapeless/PolyDefns$;
         3: invokevirtual #209                // Method shapeless/PolyDefns$.Case4:()Lshapeless/Cases$Case4$;
         6: areturn

  public static shapeless.Cases$Case3$ Case3();
    descriptor: ()Lshapeless/Cases$Case3$;
    flags: (0x0009) ACC_PUBLIC, ACC_STATIC
    Code:
      stack=1, locals=0, args_size=0
         0: getstatic     #135                // Field shapeless/PolyDefns$.MODULE$:Lshapeless/PolyDefns$;
         3: invokevirtual #213                // Method shapeless/PolyDefns$.Case3:()Lshapeless/Cases$Case3$;
         6: areturn

  public static shapeless.Cases$Case2$ Case2();
    descriptor: ()Lshapeless/Cases$Case2$;
    flags: (0x0009) ACC_PUBLIC, ACC_STATIC
    Code:
      stack=1, locals=0, args_size=0
         0: getstatic     #135                // Field shapeless/PolyDefns$.MODULE$:Lshapeless/PolyDefns$;
         3: invokevirtual #217                // Method shapeless/PolyDefns$.Case2:()Lshapeless/Cases$Case2$;
         6: areturn

  public static shapeless.Cases$Case1$ Case1();
    descriptor: ()Lshapeless/Cases$Case1$;
    flags: (0x0009) ACC_PUBLIC, ACC_STATIC
    Code:
      stack=1, locals=0, args_size=0
         0: getstatic     #135                // Field shapeless/PolyDefns$.MODULE$:Lshapeless/PolyDefns$;
         3: invokevirtual #221                // Method shapeless/PolyDefns$.Case1:()Lshapeless/Cases$Case1$;
         6: areturn
}
InnerClasses:
  public #13= #10 of #12;                 // Case1$=class shapeless/Cases$Case1$ of class shapeless/Cases
  public #16= #15 of #12;                 // Case10$=class shapeless/Cases$Case10$ of class shapeless/Cases
  public #19= #18 of #12;                 // Case11$=class shapeless/Cases$Case11$ of class shapeless/Cases
  public #22= #21 of #12;                 // Case12$=class shapeless/Cases$Case12$ of class shapeless/Cases
  public #25= #24 of #12;                 // Case13$=class shapeless/Cases$Case13$ of class shapeless/Cases
  public #28= #27 of #12;                 // Case14$=class shapeless/Cases$Case14$ of class shapeless/Cases
  public #31= #30 of #12;                 // Case15$=class shapeless/Cases$Case15$ of class shapeless/Cases
  public #34= #33 of #12;                 // Case16$=class shapeless/Cases$Case16$ of class shapeless/Cases
  public #37= #36 of #12;                 // Case17$=class shapeless/Cases$Case17$ of class shapeless/Cases
  public #40= #39 of #12;                 // Case18$=class shapeless/Cases$Case18$ of class shapeless/Cases
  public #43= #42 of #12;                 // Case19$=class shapeless/Cases$Case19$ of class shapeless/Cases
  public #46= #45 of #12;                 // Case2$=class shapeless/Cases$Case2$ of class shapeless/Cases
  public #49= #48 of #12;                 // Case20$=class shapeless/Cases$Case20$ of class shapeless/Cases
  public #52= #51 of #12;                 // Case21$=class shapeless/Cases$Case21$ of class shapeless/Cases
  public #55= #54 of #12;                 // Case22$=class shapeless/Cases$Case22$ of class shapeless/Cases
  public #58= #57 of #12;                 // Case3$=class shapeless/Cases$Case3$ of class shapeless/Cases
  public #61= #60 of #12;                 // Case4$=class shapeless/Cases$Case4$ of class shapeless/Cases
  public #64= #63 of #12;                 // Case5$=class shapeless/Cases$Case5$ of class shapeless/Cases
  public #67= #66 of #12;                 // Case6$=class shapeless/Cases$Case6$ of class shapeless/Cases
  public #70= #69 of #12;                 // Case7$=class shapeless/Cases$Case7$ of class shapeless/Cases
  public #73= #72 of #12;                 // Case8$=class shapeless/Cases$Case8$ of class shapeless/Cases
  public #76= #75 of #12;                 // Case9$=class shapeless/Cases$Case9$ of class shapeless/Cases
  public static #79= #78 of #2;           // $greater$minus$greater=class shapeless/PolyDefns$$greater$minus$greater of class shapeless/PolyDefns
  public static #82= #81 of #2;           // $minus$greater=class shapeless/PolyDefns$$minus$greater of class shapeless/PolyDefns
  public static #85= #84 of #2;           // $tilde$greater=class shapeless/PolyDefns$$tilde$greater of class shapeless/PolyDefns
  public static #88= #87 of #2;           // $tilde$greater$=class shapeless/PolyDefns$$tilde$greater$ of class shapeless/PolyDefns
  public static abstract #91= #90 of #2;  // Case=class shapeless/PolyDefns$Case of class shapeless/PolyDefns
  public static #94= #93 of #2;           // Case$=class shapeless/PolyDefns$Case$ of class shapeless/PolyDefns
  public static #97= #96 of #2;           // Case0$=class shapeless/PolyDefns$Case0$ of class shapeless/PolyDefns
  public static #100= #99 of #2;          // Compose=class shapeless/PolyDefns$Compose of class shapeless/PolyDefns
  public static #103= #102 of #2;         // Compose$=class shapeless/PolyDefns$Compose$ of class shapeless/PolyDefns
  public static #106= #105 of #2;         // LiftU=class shapeless/PolyDefns$LiftU of class shapeless/PolyDefns
  public static #109= #108 of #2;         // LowPriorityLiftFunction1=class shapeless/PolyDefns$LowPriorityLiftFunction1 of class shapeless/PolyDefns
  public static #112= #111 of #2;         // LowPriorityLiftU=class shapeless/PolyDefns$LowPriorityLiftU of class shapeless/PolyDefns
  public static #115= #114 of #2;         // RotateLeft=class shapeless/PolyDefns$RotateLeft of class shapeless/PolyDefns
  public static #118= #117 of #2;         // RotateLeft$=class shapeless/PolyDefns$RotateLeft$ of class shapeless/PolyDefns
  public static #121= #120 of #2;         // RotateRight=class shapeless/PolyDefns$RotateRight of class shapeless/PolyDefns
  public static #124= #123 of #2;         // RotateRight$=class shapeless/PolyDefns$RotateRight$ of class shapeless/PolyDefns
  public static #127= #126 of #2;         // identity$=class shapeless/PolyDefns$identity$ of class shapeless/PolyDefns
SourceFile: "poly.scala"
RuntimeVisibleAnnotations:
  0: #6(#7=s#8)
    scala.reflect.ScalaSignature(
      bytes="\u0006\u0005\u0019Mx!\u0002.\\\u0011\u0003qf!\u00021\\\u0011\u0003\t\u0007\"B6\u0002\t\u0003ag!B7\u0002\u0003\u0003q\u0007\"B6\u0004\t\u0003aHaBA\u0012\u0007\t\u0005\u0011q\u0001\u0005\n\u0003K\u0019!\u0019!D\u0001\u0003OAq!a\r\u0004\t\u0003\t)\u0004C\u0004\u00024\r!\t!a\u000f\t\u000f\u0005M2\u0001\"\u0001\u0002P!9\u00111G\u0002\u0005\u0002\u0005\u001dtaBAC\u0003!\u0005\u0011q\u0011\u0004\u0007[\u0006A\t!!#\t\r-dA\u0011AAP\u000b\u0019\t\t\u000b\u0004\u0001\u0002$\u00161\u0011Q\u0018\u0007\u0001\u0003\u007fCq!a\r\r\t\u0003\ty\r\u0003\u0005\u0002j2\u0011I1AAv\u0011!\u0011I\f\u0004B\u0005\u0004\tm\u0006\"CB\u0007\u0019\u0005\u0005I\u0011BB\b\u000b\u0019\u0019i\"\u0001\u0001\u0004 \u001d91qE\u0001\t\u0002\r%baBB\u000f\u0003!\u000511\u0006\u0005\u0007WZ!\ta!\f\u0006\r\u0005\u0005f\u0003AB\u0018\u0011\u001d\t\u0019D\u0006C\u0001\u0007{1aaa\u0014\u0002\u0001\rE\u0003BCB.5\t\u0005\t\u0015!\u0003\u0004^!Q1\u0011\r\u000e\u0003\u0002\u0003\u0006Iaa\u0019\t\r-TB\u0011AB5\u000f\u001d\u0019\t(\u0001E\u0001\u0007g2qaa\u0014\u0002\u0011\u0003\u0019)\b\u0003\u0004l?\u0011\u00051q\u000f\u0005\b\u0007szB1AB>\u0011%\u0019iaHA\u0001\n\u0013\u0019yA\u0002\u0004\u0004J\u0006\u000111\u001a\u0005\u000b\u0007\u001f\u001c#\u0011!Q\u0001\n\rE\u0007BB6$\t\u0003\u0019)nB\u0004\u0004b\u0006A\taa9\u0007\u000f\r%\u0017\u0001#\u0001\u0004f\"11n\nC\u0001\u0007ODqa!;(\t\u0007\u0019Y\u000fC\u0005\u0004\u000e\u001d\n\t\u0011\"\u0003\u0004\u0010\u00191A\u0011I\u0001\u0001\t\u0007B!ba4,\u0005\u0003\u0005\u000b\u0011\u0002C$\u0011\u0019Y7\u0006\"\u0001\u0005L\u001d9AqG\u0001\t\u0002\u0011Uca\u0002C!\u0003!\u0005Aq\u000b\u0005\u0007W>\"\t\u0001\"\u0017\t\u000f\r%x\u0006b\u0001\u0005\\!I1QB\u0018\u0002\u0002\u0013%1q\u0002\u0004\u0007\t\'\u000b\u0001\u0001\"&\t\u0015\rm3G!A!\u0002\u0013!y\n\u0003\u0004lg\u0011\u0005A\u0011\u0016\u0005\b\t_\u001bD1\u0001CY\r%!i-\u0001I\u0001\u0004\u0003!y\rC\u0004\u0005R^\"\t\u0001b5\t\u000f\u0011mw\u0007b\u0001\u0005^\u001a1Aq^\u0001\u0001\tcD!ba\u0017;\u0005\u0003\u0005\u000b\u0011\u0002C|\u0011\u0019Y\'\b\"\u0001\u0006\u0002!9Aq\u0016\u001e\u0005\u0004\u0015\u001da!CC\u000f\u0003A\u0005\u0019\u0011AC\u0010\u0011\u001d!\tN\u0010C\u0001\t\'Dq\u0001b7?\t\u0007)\tC\u0002\u0004\u0006D\u0005\u0001QQ\t\u0005\u000b\u0007\u001f\f%\u0011!Q\u0001\n\u0015-\u0003BB6B\t\u0003)y\u0005C\u0004\u0006V\u0005#\u0019!b\u0016\u0007\u0013\u0015U\u0014\u0001%A\u0002\u0002\u0015]\u0004b\u0002Ci\u000b\u0012\u0005A1\u001b\u0005\b\u0003g)e\u0011AC>\u0011\u001d))*\u0012C\u0002\u000b/;q!b,\u0002\u0011\u0003)\tLB\u0004\u0006v\u0005A\t!b-\t\r-TE\u0011AC[\u0011\u001d)9L\u0013C\u0002\u000bsCq!b7K\t\u0007)i\u000eC\u0004\u0007\u0002)#\u0019Ab\u0001\t\u000f\u0019m!\nb\u0001\u0007\u001e!9a1\u0006&\u0005\u0002\u00195\u0002b\u0002D0\u0015\u0012\u0005a\u0011\r\u0005\b\r\u000bSE\u0011\u0001DD\u0011%\u0019iASA\u0001\n\u0013\u0019y!\u0002\u0004\u0007>\u0006\u0001aqX\u0004\b\r?\f\u0001\u0012\u0001Dq\r\u001d1\u0019/\u0001E\u0001\rKDaa\u001b,\u0005\u0002\u0019\u001d\bbBA\u001a-\u0012\u0005a\u0011\u001e\u0005\n\u0007\u001b1\u0016\u0011!C\u0005\u0007\u001f\t\u0011\u0002U8ms\u0012+gM\\:\u000b\u0003q\u000b\u0011b\u001d5ba\u0016dWm]:\u0004\u0001A\u0011q,A\u0007\u00027\nI\u0001k\u001c7z\t\u00164gn]\n\u0004\u0003\tD\u0007CA2g\u001b\u0005!\'\"A3\u0002\u000bM\u001c\u0017\r\\1\n\u0005\u001d$\'AB!osJ+g\r\u0005\u0002`S&\u0011!n\u0017\u0002\u0006\u0007\u0006\u001cXm]\u0001\u0007y%t\u0017\u000e\u001e \u0015\u0003y\u0013AaQ1tKV)q.a\u0001\u0002\u0018M\u00191A\u00199\u0011\u0005ELhB\u0001:x\u001d\t\u0019h/D\u0001u\u0015\t)X,\u0001\u0004=e>|GOP\u0005\u0002K&\u0011\u0001\u0010Z\u0001\ba\u0006\u001c7.Y4f\u0013\tQ8P\u0001\u0007TKJL\u0017\r\\5{C\ndWM\u0003\u0002yIR\tQ\u0010E\u0003\u007f\u0007}\f)\"D\u0001\u0002!\u0011\t\t!a\u0001\r\u0001\u00119\u0011QA\u0002C\u0002\u0005\u001d!!\u0001)\u0012\t\u0005%\u0011q\u0002\t\u0004G\u0006-\u0011bAA\u0007I\n9aj\u001c;iS:<\u0007cA2\u0002\u0012%\u0019\u00111\u00033\u0003\u0007\u0005s\u0017\u0010\u0005\u0003\u0002\u0002\u0005]AaBA\r\u0007\t\u0007\u00111\u0004\u0002\u0002\u0019F!\u0011\u0011BA\u000f!\ry\u0016qD\u0005\u0004\u0003CY&!\u0002%MSN$(A\u0002*fgVdG/A\u0003wC2,X-\u0006\u0002\u0002*A91-a\u000b\u0002\u0016\u0005=\u0012bAA\u0017I\nIa)\u001e8di&|g.\r\t\u0004\u0003c)Q\"A\u0002\u0002\u000b\u0005\u0004\b\u000f\\=\u0015\t\u0005=\u0012q\u0007\u0005\b\u0003s9\u0001\u0019AA\u000b\u0003\u0005!HCAA\u001f)\u0011\ty#a\u0010\t\u000f\u0005\u0005\u0003\u0002q\u0001\u0002D\u0005\u0011QM\u001e\t\bG\u0006\u0015\u0013\u0011JA\u000b\u0013\r\t9\u0005\u001a\u0002\rI\u0015\fHeY8m_:$S-\u001d\t\u0004?\u0006-\u0013bAA\'7\n!\u0001JT5m+\u0011\t\t&!\u0019\u0015\t\u0005M\u0013Q\r\u000b\u0005\u0003_\t)\u0006C\u0004\u0002B%\u0001\u001d!a\u0016\u0011\u000f\r\f)%!\u0017\u0002\u0016A9q,a\u0017\u0002`\u0005%\u0013bAA/7\naAeY8m_:$3m\u001c7p]B!\u0011\u0011AA1\t\u001d\t\u0019\'\u0003b\u0001\u0003\u000f\u0011\u0011\u0001\u0016\u0005\b\u0003sI\u0001\u0019AA0+\u0019\tI\'!\u001e\u0002|Q1\u00111NA@\u0003\u0003#B!a\f\u0002n!9\u0011\u0011\t\u0006A\u0004\u0005=\u0004cB2\u0002F\u0005E\u0014Q\u0003\t\b?\u0006m\u00131OA<!\u0011\t\t!!\u001e\u0005\u000f\u0005\r$B1\u0001\u0002\bA9q,a\u0017\u0002z\u0005%\u0003\u0003BA\u0001\u0003w\"q!! \u000b\u0005\u0004\t9AA\u0001V\u0011\u001d\tID\u0003a\u0001\u0003gBq!a!\u000b\u0001\u0004\tI(A\u0001v\u0003\u0011\u0019\u0015m]3\u0011\u0005yd1C\u0002\u0007c\u0003\u0017\u000b\t\nE\u0002`\u0003\u001bK1!a$\\\u0005!\u0019\u0015m]3J]N$\b\u0003BAJ\u0003;k!!!&\u000b\t\u0005]\u0015\u0011T\u0001\u0003S>T!!a\'\u0002\t)\fg/Y\u0005\u0004u\u0006UECAAD\u0005\r\tU\u000f_\u000b\t\u0003K\u000by+a-\u0002:J!\u0011qUAV\r\u0019\tI\u000b\u0004\u0001\u0002&\naAH]3gS:,W.\u001a8u}A1apAAW\u0003c\u0003B!!\u0001\u00020\u00129\u0011Q\u0001\bC\u0002\u0005\u001d\u0001\u0003BA\u0001\u0003g#q!!\u0007\u000f\u0005\u0004\tY\"B\u0004\u0002$\u0005\u001d\u0006%a.\u0011\t\u0005\u0005\u0011\u0011\u0018\u0003\b\u0003ws!\u0019AA\u0004\u0005\u001d\u0011Vm];miB\u00121\u0001S8n+\u0019\t\t-a2\u0002NBI\u00111\u0019\b\u0002F\u0006%\u00171Z\u0007\u0002\u0019A!\u0011\u0011AAd\t\u001d\t)a\u0004b\u0001\u0003\u000f\u0001raXA.\u0003\u0017\fI\u0005\u0005\u0003\u0002\u0002\u00055GaBA2\u001f\t\u0007\u0011qA\u000b\t\u0003#\f9.a7\u0002`R!\u00111[Ar!%\t\u0019MDAk\u00033\fi\u000e\u0005\u0003\u0002\u0002\u0005]GaBA\u0003!\t\u0007\u0011q\u0001\t\u0005\u0003\u0003\tY\u000eB\u0004\u0002\u001aA\u0011\r!a\u0007\u0011\t\u0005\u0005\u0011q\u001c\u0003\b\u0003C\u0004\"\u0019AA\u0004\u0005\u0005\u0011\u0006bBAs!\u0001\u0007\u0011q]\u0001\u0002mB91-a\u000b\u0002Z\u0006u\u0017!F7bi\u0016\u0014\u0018.\u00197ju\u00164%o\\7WC2,X-M\u000b\t\u0003[\f\u00190!?\u0003\u0006U\u0011\u0011q\u001e\t\u0007}\u000e\t\t0!>\u0011\t\u0005\u0005\u00111\u001f\u0003\b\u0003\u000b\t\"\u0019AA\u0004!\u001dy\u00161LA|\u0003\u0013\u0002b!!\u0001\u0002z\n\rAaBA~#\t\u0007\u0011Q \u0002\u0002\rV!\u0011qAA\u0000\t!\u0011\t!!?C\u0002\u0005\u001d!!A0\u0011\t\u0005\u0005!Q\u0001\u0003\b\u0003G\n\"\u0019AA\u0004Q\u0015\t\"\u0011\u0002B\u000f!\u0011\u0011YA!\u0007\u000e\u0005\t5!\u0002\u0002B\b\u0005#\t\u0001\"\u001b8uKJt\u0017\r\u001c\u0006\u0005\u0005\'\u0011)\"\u0001\u0004nC\u000e\u0014xn\u001d\u0006\u0004\u0005/!\u0017a\u0002:fM2,7\r^\u0005\u0005\u00057\u0011iAA\u0005nC\u000e\u0014x.S7qYFZaDa\b\u0003\"\t5&\u0011\u0017B\\\u0017\u0001\t\u0014c\bB\u0010\u0005G\u00119C!\u000f\u0003J\te#1\u000eB?c\u0019!#qD/\u0003&\u0005)Q.Y2s_F:aCa\b\u0003*\tE\u0012\'B\u0013\u0003,\t5rB\u0001B\u0017C\t\u0011y#A\u0006nC\u000e\u0014x.\u00128hS:,\u0017\'B\u0013\u00034\tUrB\u0001B\u001bC\t\u00119$A\u0013wo9\u0002\u0004\u0005K5na2,W.\u001a8uK\u0012\u0004\u0013N\u001c\u0011TG\u0006d\u0017\r\t\u001a/cEr\u0003\'L\'9SE:aCa\b\u0003<\t\r\u0013\'B\u0013\u0003>\t}rB\u0001B C\t\u0011\t%\u0001\u0005jg\n+h\u000e\u001a7fc\u0015)#Q\tB$\u001f\t\u00119%G\u0001\u0002c\u001d1\"q\u0004B&\u0005\'\nT!\nB\'\u0005\u001fz!Aa\u0014\"\u0005\tE\u0013AC5t\u00052\f7m\u001b2pqF*QE!\u0016\u0003X=\u0011!qK\r\u0002\u0001E:aCa\b\u0003\\\t\r\u0014\'B\u0013\u0003^\t}sB\u0001B0C\t\u0011\t\'A\u0005dY\u0006\u001c8OT1nKF*QE!\u001a\u0003h=\u0011!qM\u0011\u0003\u0005S\nAc\u001d5ba\u0016dWm]:/!>d\u00170T1de>\u001c\u0018g\u0002\f\u0003 \t5$QO\u0019\u0006K\t=$\u0011O\b\u0003\u0005c\n#Aa\u001d\u0002\u00155,G\u000f[8e\u001d\u0006lW-M\u0003&\u0005o\u0012Ih\u0004\u0002\u0003z\u0005\u0012!1P\u0001\u0019[\u0006$XM]5bY&TXM\u0012:p[Z\u000bG.^3J[Bd\u0017g\u0002\f\u0003 \t}$qQ\u0019\u0006K\t\u0005%1Q\b\u0003\u0005\u0007\u000b#A!\"\u0002\u0013MLwM\\1ukJ,\u0017gB\u0010\u0003 \t%%qS\u0019\bI\t}!1\u0012BG\u0013\u0011\u0011iIa$\u0002\t1K7\u000f\u001e\u0006\u0005\u0005#\u0013\u0019*A\u0005j[6,H/\u00192mK*\u0019!Q\u00133\u0002\u0015\r|G\u000e\\3di&|g.M\u0006 \u0005?\u0011IJa\'\u0003\"\n\u001d\u0016g\u0002\u0013\u0003 \t-%QR\u0019\u0006K\tu%qT\b\u0003\u0005?k\u0012\u0001A\u0019\u0006K\t\r&QU\b\u0003\u0005Kk\u0012!A\u0019\u0006K\t%&1V\b\u0003\u0005Wk\u0012AA\u0019\u0004M\t=\u0006\u0003BA\u0001\u0003g\f4A\nBZ!\u0019\t\t!!?\u00036B!\u0011\u0011\u0001B\u0003c\r1#QW\u0001\u0016[\u0006$XM]5bY&TXM\u0012:p[Z\u000bG.^33+\u0019\u0011iLa1\u0003JV\u0011!q\u0018\t\u0007}\u000e\u0011\tM!2\u0011\t\u0005\u0005!1\u0019\u0003\b\u0003\u000b\u0011\"\u0019AA\u0004!\u001dy\u00161\fBd\u0003\u0013\u0002B!!\u0001\u0003J\u00129\u00111\r\nC\u0002\u0005\u001d\u0001&\u0002\n\u0003\n\t5\u0017g\u0003\u0010\u0003 \t=71AB\u0004\u0007\u0017\t\u0014c\bB\u0010\u0005#\u0014\u0019N!7\u0003`\n\u0015(1\u001eByc\u0019!#qD/\u0003&E:aCa\b\u0003V\n]\u0017\'B\u0013\u0003,\t5\u0012\'B\u0013\u00034\tU\u0012g\u0002\f\u0003 \tm\'Q\\\u0019\u0006K\tu\"qH\u0019\u0006K\t\u0015#qI\u0019\b-\t}!\u0011\u001dBrc\u0015)#Q\nB(c\u0015)#Q\u000bB,c\u001d1\"q\u0004Bt\u0005S\fT!\nB/\u0005?\nT!\nB3\u0005O\ntA\u0006B\u0010\u0005[\u0014y/M\u0003&\u0005_\u0012\t(M\u0003&\u0005o\u0012I(M\u0004\u0017\u0005?\u0011\u0019P!>2\u000b\u0015\u0012\tIa!2\u000f}\u0011yBa>\u0003zF:AEa\b\u0003\f\n5\u0015gC\u0010\u0003 \tm(Q B\u0000\u0007\u0003\tt\u0001\nB\u0010\u0005\u0017\u0013i)M\u0003&\u0005;\u0013y*M\u0003&\u0005G\u0013)+M\u0003&\u0005S\u0013Y+M\u0002\'\u0007\u000b\u0001B!!\u0001\u0003DF\u001aae!\u0003\u0011\t\u0005\u0005!\u0011Z\u0019\u0004M\r%\u0011\u0001D<sSR,\'+\u001a9mC\u000e,GCAB\t!\u0011\u0019\u0019b!\u0007\u000e\u0005\rU!\u0002BB\f\u00033\u000bA\u0001\\1oO&!11DB\u000b\u0005\u0019y%M[3di\n)1)Y:faU!1\u0011EB\u0013!\u0019q8aa\t\u0002JA!\u0011\u0011AB\u0013\t\u001d\t)\u0001\u0006b\u0001\u0003\u000f\tQaQ1tKB\u0002\"A \f\u0014\u0005Y\u0011GCAB\u0015+\u0019\u0019\tda\u000e\u0004<AI11\u0007\b\u00046\u0005%3\u0011\b\b\u0003}.\u0001B!!\u0001\u00048\u00119\u0011Q\u0001\rC\u0002\u0005\u001d\u0001\u0003BA\u0001\u0007w!q!a\u0019\u0019\u0005\u0004\t9!\u0006\u0004\u0004@\r\u001d31\n\u000b\u0005\u0007\u0003\u001ai\u0005E\u0004\u0004Da\u0019)e!\u0013\u000e\u0003Y\u0001B!!\u0001\u0004H\u00119\u0011QA\rC\u0002\u0005\u001d\u0001\u0003BA\u0001\u0007\u0017\"q!a\u0019\u001a\u0005\u0004\t9\u0001C\u0004\u0002ff\u0001\ra!\u0013\u0003\u000f\r{W\u000e]8tKV111KB0\u0007K\u001aBA\u00072\u0004VA\u0019qla\u0016\n\u0007\re3L\u0001\u0003Q_2L\u0018!\u00014\u0011\t\u0005\u00051q\f\u0003\b\u0003wT\"\u0019AA\u0004\u0003\u00059\u0007\u0003BA\u0001\u0007K\"qaa\u001a\u001b\u0005\u0004\t9AA\u0001H)\u0019\u0019Yg!\u001c\u0004pA1aPGB/\u0007GBqaa\u0017\u001e\u0001\u0004\u0019i\u0006C\u0004\u0004bu\u0001\raa\u0019\u0002\u000f\r{W\u000e]8tKB\u0011apH\n\u0005?\t\f\t\n\u0006\u0002\u0004t\u0005Y1m\\7q_N,7)Y:f+9\u0019iha\"\u0004(\u000e56qRBa\u0007+#\u0002ba \u0004\u001a\u000e=61\u0019\n\u0005\u0007\u0003\u001b\u0019I\u0002\u0004\u0002*\u0006\u00021q\u0010\t\u0007}\u000e\u0019)ia#\u0011\t\u0005\u00051q\u0011\u0003\b\u0007\u0013\u000b#\u0019AA\u0004\u0005\u0005\u0019\u0005cB0\u0002\\\r5\u0015\u0011\n\t\u0005\u0003\u0003\u0019y\tB\u0004\u0002d\u0005\u0012\r!a\u0002\u0006\u000f\u0005\r2\u0011\u0011\u0001\u0004\u0014B!\u0011\u0011ABK\t\u001d\u00199*\tb\u0001\u0003\u000f\u0011\u0011A\u0016\u0005\b\u00077\u000b\u00039ABO\u0003\u0019)h\u000e]1dWBYqla(\u0004\u0006\u000e\r6QUBV\u0013\r\u0019\tk\u0017\u0002\b+:\u0004\u0018mY63!\tq(\u0004\u0005\u0003\u0002\u0002\r\u001dFaBA~C\t\u00071\u0011V\t\u0005\u0003\u0013\u0019)\u0006\u0005\u0003\u0002\u0002\r5FaBB4C\t\u00071\u0011\u0016\u0005\b\u0007c\u000b\u00039ABZ\u0003\t\u0019w\t\u0005\u0006\u00046\u000em61VBG\u0007\u007fs1A`B\\\u0013\r\u0019I,[\u0001\u0006\u0007\u0006\u001cX-M\u0005\u0005\u0003C\u001biLC\u0002\u0004:&\u0004B!!\u0001\u0004B\u00129\u0011QP\u0011C\u0002\u0005\u001d\u0001bBBcC\u0001\u000f1qY\u0001\u0003G\u001a\u0003\"b!.\u0004<\u000e\u00156qXBJ\u0005)\u0011v\u000e^1uK2+g\r^\u000b\u0007\u0007\u001b\u001c\u0019na7\u0014\t\r\u00127QK\u0001\u0002aB!\u0011\u0011ABj\t\u001d\t)a\tb\u0001\u0003\u000f!Baa6\u0004`B1apIBi\u00073\u0004B!!\u0001\u0004\\\u001291Q\\\u0012C\u0002\u0005\u001d!!\u0001(\t\u000f\r=W\u00051\u0001\u0004R\u0006Q!k\u001c;bi\u0016dUM\u001a;\u0011\u0005y<3\u0003B\u0014c\u0003##\"aa9\u0002\u001dI|G/\u0019;f\u0019\u00164GoQ1tKVq1Q^Bz\t\u0013!i\u0001b\b\u0004~\u000e]H\u0003CBx\t\u0003!9\u0002\"\t\u0011\u0013\rMbb!=\u0004v\u000em\b\u0003BA\u0001\u0007g$qa!#*\u0005\u0004\t9\u0001\u0005\u0003\u0002\u0002\r]HaBB}S\t\u0007\u00111\u0004\u0002\u0003%2\u0003B!!\u0001\u0004~\u001291q`\u0015C\u0002\u0005\u001d!\u0001\u0002\'PkRDqaa\'*\u0001\b!\u0019\u0001E\u0006`\u0007?\u001b\t\u0010\"\u0002\u0005\b\u0011-\u0001C\u0001@$!\u0011\t\t\u0001\"\u0003\u0005\u000f\u0005\u0015\u0011F1\u0001\u0004*B!\u0011\u0011\u0001C\u0007\t\u001d\u0019i.\u000bb\u0001\t\u001f\tB!!\u0003\u0005\u0012A\u0019q\fb\u0005\n\u0007\u0011U1LA\u0002OCRDq\u0001\"\u0007*\u0001\b!Y\"\u0001\u0002d!BI11\u0007\b\u0005\b\u0011u11 \t\u0005\u0003\u0003!y\u0002B\u0004\u0002\u001a%\u0012\r!a\u0007\t\u000f\u0011\r\u0012\u0006q\u0001\u0005&\u0005Y!o\u001c;bi\u0016\u0014\u0016n\u001a5u!)!9\u0003b\u000f\u0004v\u0012-AQ\u0004\b\u0005\tS!)D\u0004\u0003\u0005,\u0011ERB\u0001C\u0017\u0015\r!ycW\u0001\u0004_B\u001c\u0018\u0002\u0002C\u001a\t[\tQ\u0001\u001b7jgRLA\u0001b\u000e\u0005:\u0005Y!k\u001c;bi\u0016\u0014\u0016n\u001a5u\u0015\u0011!\u0019\u0004\"\f\n\t\u0005\u0005FQH\u0005\u0005\t\u007f!ID\u0001\fM_^\u0004&/[8sSRL(k\u001c;bi\u0016\u0014\u0016n\u001a5u\u0005-\u0011v\u000e^1uKJKw\r\u001b;\u0016\r\u0011\u0015C\u0011\nC)\'\u0011Y#m!\u0016\u0011\t\u0005\u0005A\u0011\n\u0003\b\u0003\u000bY#\u0019AA\u0004)\u0011!i\u0005b\u0015\u0011\ry\\Cq\tC(!\u0011\t\t\u0001\"\u0015\u0005\u000f\ru7F1\u0001\u0002\b!91qZ\u0017A\u0002\u0011\u001d\u0003C\u0001@0\'\u0011y#-!%\u0015\u0005\u0011USC\u0004C/\tG\")\b\"\u001f\u0005\u0002\u0012-Dq\r\u000b\t\t?\"i\u0007b\u001f\u0005\u0004BI11\u0007\b\u0005b\u0011\u0015D\u0011\u000e\t\u0005\u0003\u0003!\u0019\u0007B\u0004\u0004\nF\u0012\r!a\u0002\u0011\t\u0005\u0005Aq\r\u0003\b\u0007s\f$\u0019AA\u000e!\u0011\t\t\u0001b\u001b\u0005\u000f\r}\u0018G1\u0001\u0002\b!911T\u0019A\u0004\u0011=\u0004cC0\u0004 \u0012\u0005D\u0011\u000fC:\to\u0002\"A`\u0016\u0011\t\u0005\u0005AQ\u000f\u0003\b\u0003\u000b\t$\u0019ABU!\u0011\t\t\u0001\"\u001f\u0005\u000f\ru\u0017G1\u0001\u0005\u0010!9A\u0011D\u0019A\u0004\u0011u\u0004#CB\u001a\u001d\u0011MDq\u0010C5!\u0011\t\t\u0001\"!\u0005\u000f\u0005e\u0011G1\u0001\u0002\u001c!9AQQ\u0019A\u0004\u0011\u001d\u0015A\u0003:pi\u0006$X\rT3giBQA\u0011\u0012CG\tK\"9\bb \u000f\t\u0011%B1R\u0005\u0005\u0007C$I$\u0003\u0003\u0002\"\u0012=\u0015\u0002\u0002CI\ts\u0011Q\u0003T8x!JLwN]5usJ{G/\u0019;f\u0019\u00164GO\u0001\b%[&tWo\u001d\u0013he\u0016\fG/\u001a:\u0016\r\u0011]E1\u0015CT\'\u0011\u0019$\r\"\'\u0011\u0007}#Y*C\u0002\u0005\u001en\u0013Q\u0001U8msF\u0002raYA\u0016\tC#)\u000b\u0005\u0003\u0002\u0002\u0011\rFaBA2g\t\u0007\u0011q\u0001\t\u0005\u0003\u0003!9\u000bB\u0004\u0002bN\u0012\r!a\u0002\u0015\t\u0011-FQ\u0016\t\u0007}N\"\t\u000b\"*\t\u000f\rmS\u00071\u0001\u0005 \u0006!1/\u001e2U+\u0011!\u0019\fb2\u0016\u0005\u0011U&\u0003\u0002C\\\t\u007f3a!!+\u0001\u0001\u0011U\u0016\u0002BA\u001a\twKA\u0001\"0\u0005\u001c\nY1)Y:f\u0005VLG\u000eZ3s!\u0019!\t\rb1\u0005F6\t1\'C\u0002n\t7\u0003B!!\u0001\u0005H\u00129\u0011Q\u0010\u001cC\u0002\u0011%\u0017\u0003BA\u0005\tC+q!a\t\u00058\u0002!)K\u0001\rM_^\u0004&/[8sSRLH*\u001b4u\rVt7\r^5p]F\u001aBa\u000e2\u0005\u001a\u00061A%\u001b8ji\u0012\"\"\u0001\"6\u0011\u0007\r$9.C\u0002\u0005Z\u0012\u0014A!\u00168ji\u00069A-\u001a4bk2$X\u0003\u0002Cp\tW,\"\u0001\"9\u0013\t\u0011\rHQ\u001d\u0004\u0007\u0003S\u0003\u0001\u0001\"9\u0011\r\u0011\u001dH1\u0019Cu\u001b\u00059\u0004\u0003BA\u0001\tW$q!a\u0019:\u0005\u0004\t9!B\u0004\u0002$\u0011\r\b!!\u0013\u0003-\u0011:\'/Z1uKJ$S.\u001b8vg\u0012:\'/Z1uKJ,b\u0001b=\u0005|\u0012}8\u0003\u0002\u001ec\tk\u0004\"A`\u001c\u0011\u000f\r\fY\u0003\"?\u0005~B!\u0011\u0011\u0001C~\t\u001d\t\u0019G\u000fb\u0001\u0003\u000f\u0001B!!\u0001\u0005\u0000\u00129\u0011\u0011\u001d\u001eC\u0002\u0005\u001dA\u0003BC\u0002\u000b\u000b\u0001bA \u001e\u0005z\u0012u\bbBB.y\u0001\u0007Aq_\u000b\u0005\u000b\u0013))\"\u0006\u0002\u0006\fI!QQBC\b\r\u0019\tI\u000b\u0001\u0001\u0006\fA1Q\u0011\u0003Cb\u000b\'i\u0011A\u000f\t\u0005\u0003\u0003))\u0002B\u0004\u0002~u\u0012\r!b\u0006\u0012\t\u0005%A\u0011`\u0003\b\u0003G)i\u0001AC\u000e!\u001dy\u00161\fC\u007f\u0003\u0013\u0012\u0001\u0003T8x!JLwN]5us2Kg\r^+\u0014\ty\u00127QK\u000b\u0005\u000bG)\u0019$\u0006\u0002\u0006&I!QqEC\u0015\r\u0019\tI\u000b\u0011\u0001\u0006&A1Q1FC\u0017\u000bci\u0011AP\u0005\u0005\u000b_\u00199FA\u0006Qe>$Wo\u0019;DCN,\u0007\u0003BA\u0001\u000bg!q!!\u0007A\u0005\u0004\tY\"B\u0004\u0002$\u0015\u001d\u0002!!\u0013\t\u0015\u0005\u0015Rq\u0005b\u0001\n\u0003)I$\u0006\u0002\u0006<A91-a\u000b\u00062\u0015ubbA0\u0006@%\u0019Q\u0011I.\u0002\t!s\u0015\u000e\u001c\u0002\u0006\u0019&4G/V\u000b\u0005\u000b\u000f*ie\u0005\u0003BE\u0016%\u0003C\u0001@?!\u0011\t\t!\"\u0014\u0005\u000f\u0005\u0015\u0011I1\u0001\u0004*R!Q\u0011KC*!\u0011q\u0018)b\u0013\t\u000f\r=7\t1\u0001\u0006L\u00059A-\u001a4j]\u0016$W\u0003BC-\u000bK\"B!b\u0017\u0006pI!QQLC0\r\u0019\tI\u000b\u0012\u0001\u0006\\A1Q\u0011MC\u0017\u000bGj\u0011!\u0011\t\u0005\u0003\u0003))\u0007B\u0004\u0002\u001a\u0011\u0013\r!a\u0007\u0006\u000f\u0005\rRQ\f\u0001\u0006jA9q,a\u0017\u0006l\u0005%\u0003cAC7\u000b9!\u0011\u0011AC8\u0011\u001d)\t\b\u0012a\u0002\u000bg\nQaY1tKR\u0003bA`\u0002\u0006L\u0015\r$A\u0004\u0013uS2$W\rJ4sK\u0006$XM]\u000b\u0007\u000bs*y)\"!\u0014\t\u0015\u0013G\u0011T\u000b\u0005\u000b{*I\t\u0006\u0003\u0006\u0000\u0015-\u0005CBA\u0001\u000b\u0003+9\tB\u0004\u0004h\u0015\u0013\r!b!\u0016\t\u0005\u001dQQ\u0011\u0003\t\u0005\u0003)\tI1\u0001\u0002\bA!\u0011\u0011ACE\t\u001d\t\u0019g\u0012b\u0001\u0003\u000fAqaa\u0017H\u0001\u0004)i\t\u0005\u0004\u0002\u0002\u0015=Uq\u0011\u0003\b\u0003w,%\u0019ACI+\u0011\t9!b%\u0005\u0011\t\u0005Qq\u0012b\u0001\u0003\u000f\t\u0001bY1tKVs\u0017N^\u000b\u0005\u000b3+Y+\u0006\u0002\u0006\u001cBAQQTCR\u000bO+iK\u0004\u0003\u0006 \u0016\u0005V\"A#\n\t\u0005\u0015E1T\u0005\u0005\u0003C+)K\u0003\u0003\u0002\u0006\u0012m\u0005CBA\u0001\u000b\u001f+I\u000b\u0005\u0003\u0002\u0002\u0015-FaBA2\u0011\n\u0007\u0011q\u0001\t\u0007\u0003\u0003)\t)\"+\u0002\u001d\u0011\"\u0018\u000e\u001c3fI\u001d\u0014X-\u0019;feB\u0011aPS\n\u0005\u0015\n\f\t\n\u0006\u0002\u00062\u0006)\u0011N\\:ucUAQ1XCa\u000b\u001b,I\r\u0006\u0003\u0006>\u0016M\u0007cB2\u0002,\u0015}V1\u001a\t\u0007\u0003\u0003)\t-b2\u0005\u000f\u0005mHJ1\u0001\u0006DV!\u0011qACc\t!\u0011\t!\"1C\u0002\u0005\u001d\u0001\u0003BA\u0001\u000b\u0013$q!a\u0019M\u0005\u0004\t9\u0001\u0005\u0004\u0002\u0002\u00155Wq\u0019\u0003\b\u0007Ob%\u0019ACh+\u0011\t9!\"5\u0005\u0011\t\u0005QQ\u001ab\u0001\u0003\u000fAqaa\u0017M\u0001\u0004))\u000e\u0005\u0004\u007f\u000b\u0016]W\u0011\u001c\t\u0005\u0003\u0003)\t\r\u0005\u0003\u0002\u0002\u00155\u0017!B5ogR\u0014TCBCp\u000bS,)\u000f\u0006\u0003\u0006b\u0016=\bcB2\u0002,\u0015\rXq\u001d\t\u0005\u0003\u0003))\u000fB\u0004\u0002d5\u0013\r!a\u0002\u0011\r\u0005\u0005Q\u0011^Cr\t\u001d\u00199\'\u0014b\u0001\u000bW,B!a\u0002\u0006n\u0012A!\u0011ACu\u0005\u0004\t9\u0001C\u0004\u0004\\5\u0003\r!\"=\u0011\ry,U1_C\u0000!\u0011))0\"?\u000f\u0007}+90\u0003\u0002y7&!Q1`C\u007f\u0005\tIEM\u0003\u0002y7B!\u0011\u0011ACu\u0003\u0015Ign\u001d;4+\u00191)Ab\u0003\u0007\u0014Q!aq\u0001D\u000b!\u001d\u0019\u00171\u0006D\u0005\r#\u0001b!!\u0001\u0007\f\u0019EAaBA~\u001d\n\u0007aQB\u000b\u0005\u0003\u000f1y\u0001\u0002\u0005\u0003\u0002\u0019-!\u0019AA\u0004!\u0011\t\tAb\u0005\u0005\u000f\u0005\rdJ1\u0001\u0002\b!911\f(A\u0002\u0019]\u0001C\u0002@F\r3)\u0019\u0010\u0005\u0003\u0002\u0002\u0019-\u0011!B5ogR$T\u0003\u0002D\u0010\rK!BA\"\t\u0007(A91-a\u000b\u0007$\u0019\r\u0002\u0003BA\u0001\rK!q!a\u0019P\u0005\u0004\t9\u0001C\u0004\u0004\\=\u0003\rA\"\u000b\u0011\ry,U1_Cz\u0003\u0015Ign\u001d;6+!1yC\"\u000e\u0007B\u0019uB\u0003\u0002D\u0019\r\u0007\u0002raYA\u0016\rg1y\u0004\u0005\u0004\u0002\u0002\u0019Ub1\b\u0003\b\u0003w\u0004&\u0019\u0001D\u001c+\u0011\t9A\"\u000f\u0005\u0011\t\u0005aQ\u0007b\u0001\u0003\u000f\u0001B!!\u0001\u0007>\u00119\u00111\r)C\u0002\u0005\u001d\u0001\u0003BA\u0001\r\u0003\"qaa\u001aQ\u0005\u0004\t9\u0001C\u0004\u0004\\A\u0003\rA\"\u0012\u0011\ry,eq\tD%!\u0011\t\tA\"\u000e\u0016\t\u0019}b1\n\u0003\t\u0003G2iE1\u0001\u0002\b!9aq\nD)\u0001\t}\u0011A\u0003\u001fm_\u000e\fG\u000e\th<~\u00159a1\u000bD+\u0001\u0019e#A\u0001h<\u000e\u0019\tI\u000b\u0001\u0001\u0007XI\u0019aQ\u000b2\u0016\t\u0019mcQ\f\t\u0005\u0003\u00031\t\u0005\u0002\u0005\u0002d\u0019E#\u0019AA\u0004\u0003\u0015Ign\u001d;7+\u00191\u0019G\"\u001c\u0007jQ!aQ\rD8!\u001d\u0019\u00171\u0006D4\rW\u0002B!!\u0001\u0007j\u00119\u00111M)C\u0002\u0005\u001d\u0001\u0003BA\u0001\r[\"qaa\u001aR\u0005\u0004\t9\u0001C\u0004\u0004\\E\u0003\rA\"\u001d\u0011\ry,U1\u001fD:+\u00111YG\"\u001e\u0005\u0011\u0005\rdq\u000fb\u0001\u0003\u000fAqAb\u0014\u0007z\u0001\u0011y\"B\u0004\u0007T\u0019m\u0004Ab \u0007\r\u0005%\u0006\u0001\u0001D?%\r1YHY\u000b\u0005\r\u00033\u0019\t\u0005\u0003\u0002\u0002\u00195D\u0001CA2\rs\u0012\r!a\u0002\u0002\u000b%t7\u000f^\u001c\u0016\r\u0019%eq\u0012DJ)\u00111YI\"&\u0011\u000f\r\fYC\"$\u0007\u0012B!\u0011\u0011\u0001DH\t\u001d\tYP\u0015b\u0001\u0003\u000f\u0001B!!\u0001\u0007\u0014\u001291q\r*C\u0002\u0005\u001d\u0001bBB.%\u0002\u0007aq\u0013\t\u0007}\u00163IJb+\u0016\t\u00195e1\u0014\u0003\t\u0003G2iJ1\u0001\u0002\b!9aq\nDP\u0001\t}Qa\u0002D*\rC\u0003aQ\u0015\u0004\u0007\u0003S\u0003\u0001Ab)\u0013\u0007\u0019\u0005&-\u0006\u0003\u0007(\u001a%\u0006\u0003BA\u0001\r\u001f#\u0001\"a\u0019\u0007 \n\u0007\u0011qA\u000b\u0005\r#3i\u000b\u0002\u0005\u0002d\u0019=&\u0019AA\u0004\u0011\u001d1yE\"-\u0001\u0005?)qAb\u0015\u00074\u000219L\u0002\u0004\u0002*\u0002\u0001aQ\u0017\n\u0004\rg\u0013W\u0003\u0002D]\rw\u0003B!!\u0001\u0007\u0014\u0012A\u00111\rDY\u0005\u0004\t9A\u0001\f%i&dG-\u001a\u0013he\u0016\fG/\u001a:%OJ,\u0017\r^3s+\u00191\tM\"2\u0007PB1a0\u0012Db\r\u0017\u0004B!!\u0001\u0007F\u00129\u00111 +C\u0002\u0019\u001dW\u0003BA\u0004\r\u0013$\u0001B!\u0001\u0007F\n\u0007\u0011qA\u000b\u0005\r\u001b4\t\u000e\u0005\u0003\u0002\u0002\u0019=GaBAq)\n\u0007\u0011q\u0001\u0003\t\u0003G2\u0019N1\u0001\u0002\b!9aq\nDk\u0001\t}Qa\u0002D*\r/\u0004a1\u001c\u0004\u0007\u0003S\u0003\u0001A\"7\u0013\u0007\u0019]\'-\u0006\u0003\u0007N\u001auG\u0001CA2\r+\u0014\r!a\u0002\u0002\u0011%$WM\u001c;jif\u0004\"A ,\u0003\u0011%$WM\u001c;jif\u001cBA\u00162\u0007*Q\u0011a\u0011]\u000b\u0005\rW4y\u000f\u0006\u0003\u0007n\u001aE\b\u0003BA\u0001\r_$q!a\u0019Y\u0005\u0004\t9\u0001C\u0004\u0002:a\u0003\rA\"<"
    )
  ScalaSig: length = 0x3 (unknown attribute)
   05 02 00
