Classfile /Users/mw/Projects/slang-braindump/.jar/jar11/assemble/slang-braindump/assemble/content/shapeless/Poly0.class
  Last modified May 29, 2022; size 1503 bytes
  SHA-256 checksum ad4af0c1f928b54ac7e49ad738a62c987a5aa9674ec791db6b306bf03cd38850
  Compiled from "poly.scala"
public interface shapeless.Poly0 extends shapeless.Poly
  minor version: 0
  major version: 52
  flags: (0x0601) ACC_PUBLIC, ACC_INTERFACE, ACC_ABSTRACT
  this_class: #2                          // shapeless/Poly0
  super_class: #4                         // java/lang/Object
  interfaces: 1, fields: 0, methods: 3, attributes: 5
Constant pool:
   #1 = Utf8               shapeless/Poly0
   #2 = Class              #1             // shapeless/Poly0
   #3 = Utf8               java/lang/Object
   #4 = Class              #3             // java/lang/Object
   #5 = Utf8               shapeless/Poly
   #6 = Class              #5             // shapeless/Poly
   #7 = Utf8               poly.scala
   #8 = Utf8               Lscala/reflect/ScalaSignature;
   #9 = Utf8               bytes
  #10 = Utf8               \u0006\u0005}2q\u0001B\u0003\u0011\u0002\u0007\u0005\u0001\u0002C\u0003\u0014\u0001\u0011\u0005A#\u0002\u0003\u0019\u0001\u0001I\u0002\"\u0002\u0019\u0001\t\u0003\t$!\u0002)pYf\u0004$\"\u0001\u0004\u0002\u0013MD\u0017\r]3mKN\u001c8\u0001A\n\u0004\u0001%y\u0001C\u0001\u0006\u000e\u001b\u0005Y!\"\u0001\u0007\u0002\u000bM\u001c\u0017\r\\1\n\u00059Y!AB!osJ+g\r\u0005\u0002\u0011#5\tQ!\u0003\u0002\u0013\u000b\t!\u0001k\u001c7z\u0003\u0019!\u0013N\\5uIQ\tQ\u0003\u0005\u0002\u000b-%\u0011qc\u0003\u0002\u0005+:LGOA\u0003DCN,\u0007\'\u0006\u0002\u001bOA!1d\b\u0012&\u001d\taR$D\u0001\u0001\u0013\tq\u0012#A\u0006Qe>$Wo\u0019;DCN,\u0017B\u0001\u0011\"\u0005\r\tU\u000f\u001f\u0006\u0003=E\u0001\"\u0001E\u0012\n\u0005\u0011*!\u0001\u0002%OS2\u0004\"AJ\u0014\r\u0001\u0011)\u0001F\u0001b\u0001S\t\tA+\u0005\u0002+[A\u0011!bK\u0005\u0003Y-\u0011qAT8uQ&tw\r\u0005\u0002\u000b]%\u0011qf\u0003\u0002\u0004\u0003:L\u0018AA1u+\t\u0011D\b\u0006\u00024{I\u0011AG\u000e\u0004\u0005k\r\u00011G\u0001\u0007=e\u00164\u0017N\\3nK:$h\bE\u0002\u001do\tJ!\u0001O\t\u0003\u0017A\u0013x\u000eZ;di\u000e\u000b7/Z\u0003\u0005uQ\u00021H\u0001\u0004SKN,H\u000e\u001e\t\u0003Mq\"Q\u0001K\u0002C\u0002%BQAP\u0002A\u0002m\n\u0011\u0001\u001e
  #11 = Utf8               shapeless/Poly0$$anon$11
  #12 = Class              #11            // shapeless/Poly0$$anon$11
  #13 = Utf8               shapeless/PolyDefns$Case
  #14 = Class              #13            // shapeless/PolyDefns$Case
  #15 = Utf8               shapeless/PolyDefns
  #16 = Class              #15            // shapeless/PolyDefns
  #17 = Utf8               Case
  #18 = Utf8               at$
  #19 = Utf8               (Lshapeless/Poly0;Ljava/lang/Object;)Lshapeless/PolyDefns$Case;
  #20 = Utf8               $this
  #21 = Utf8               t
  #22 = Utf8               at
  #23 = Utf8               (Ljava/lang/Object;)Lshapeless/PolyDefns$Case;
  #24 = NameAndType        #22:#23        // at:(Ljava/lang/Object;)Lshapeless/PolyDefns$Case;
  #25 = InterfaceMethodref #2.#24         // shapeless/Poly0.at:(Ljava/lang/Object;)Lshapeless/PolyDefns$Case;
  #26 = Utf8               Lshapeless/Poly0;
  #27 = Utf8               Ljava/lang/Object;
  #28 = Utf8               <T:Ljava/lang/Object;>(TT;)Lshapeless/PolyDefns$Case<Lshapeless/Poly0;Lshapeless/HNil;>;
  #29 = Utf8               <init>
  #30 = Utf8               (Lshapeless/Poly0;Ljava/lang/Object;)V
  #31 = NameAndType        #29:#30        // "<init>":(Lshapeless/Poly0;Ljava/lang/Object;)V
  #32 = Methodref          #12.#31        // shapeless/Poly0$$anon$11."<init>":(Lshapeless/Poly0;Ljava/lang/Object;)V
  #33 = Utf8               this
  #34 = Utf8               $init$
  #35 = Utf8               (Lshapeless/Poly0;)V
  #36 = Utf8               Code
  #37 = Utf8               LineNumberTable
  #38 = Utf8               LocalVariableTable
  #39 = Utf8               MethodParameters
  #40 = Utf8               Signature
  #41 = Utf8               InnerClasses
  #42 = Utf8               SourceFile
  #43 = Utf8               RuntimeVisibleAnnotations
  #44 = Utf8               ScalaInlineInfo
  #45 = Utf8               ScalaSig
{
  public static shapeless.PolyDefns$Case at$(shapeless.Poly0, java.lang.Object);
    descriptor: (Lshapeless/Poly0;Ljava/lang/Object;)Lshapeless/PolyDefns$Case;
    flags: (0x1009) ACC_PUBLIC, ACC_STATIC, ACC_SYNTHETIC
    Code:
      stack=2, locals=2, args_size=2
         0: aload_0
         1: aload_1
         2: invokespecial #25                 // InterfaceMethod at:(Ljava/lang/Object;)Lshapeless/PolyDefns$Case;
         5: areturn
      LineNumberTable:
        line 257: 0
      LocalVariableTable:
        Start  Length  Slot  Name   Signature
            0       6     0 $this   Lshapeless/Poly0;
            0       6     1     t   Ljava/lang/Object;
    MethodParameters:
      Name                           Flags
      $this                          final synthetic
      t                              final

  public default <T extends java.lang.Object> shapeless.PolyDefns$Case<shapeless.Poly0, shapeless.HNil> at(T);
    descriptor: (Ljava/lang/Object;)Lshapeless/PolyDefns$Case;
    flags: (0x0001) ACC_PUBLIC
    Code:
      stack=4, locals=2, args_size=2
         0: new           #12                 // class shapeless/Poly0$$anon$11
         3: dup
         4: aconst_null
         5: aload_1
         6: invokespecial #32                 // Method shapeless/Poly0$$anon$11."<init>":(Lshapeless/Poly0;Ljava/lang/Object;)V
         9: areturn
      LineNumberTable:
        line 257: 0
      LocalVariableTable:
        Start  Length  Slot  Name   Signature
            0      10     0  this   Lshapeless/Poly0;
            0      10     1     t   Ljava/lang/Object;
    Signature: #28                          // <T:Ljava/lang/Object;>(TT;)Lshapeless/PolyDefns$Case<Lshapeless/Poly0;Lshapeless/HNil;>;
    MethodParameters:
      Name                           Flags
      t                              final

  public static void $init$(shapeless.Poly0);
    descriptor: (Lshapeless/Poly0;)V
    flags: (0x0009) ACC_PUBLIC, ACC_STATIC
    Code:
      stack=0, locals=1, args_size=1
         0: return
      LineNumberTable:
        line 254: 0
      LocalVariableTable:
        Start  Length  Slot  Name   Signature
            0       1     0 $this   Lshapeless/Poly0;
    MethodParameters:
      Name                           Flags
      $this                          final synthetic
}
InnerClasses:
  public final #12;                       // class shapeless/Poly0$$anon$11
  public static abstract #17= #14 of #16; // Case=class shapeless/PolyDefns$Case of class shapeless/PolyDefns
SourceFile: "poly.scala"
RuntimeVisibleAnnotations:
  0: #8(#9=s#10)
    scala.reflect.ScalaSignature(
      bytes="\u0006\u0005}2q\u0001B\u0003\u0011\u0002\u0007\u0005\u0001\u0002C\u0003\u0014\u0001\u0011\u0005A#\u0002\u0003\u0019\u0001\u0001I\u0002\"\u0002\u0019\u0001\t\u0003\t$!\u0002)pYf\u0004$\"\u0001\u0004\u0002\u0013MD\u0017\r]3mKN\u001c8\u0001A\n\u0004\u0001%y\u0001C\u0001\u0006\u000e\u001b\u0005Y!\"\u0001\u0007\u0002\u000bM\u001c\u0017\r\\1\n\u00059Y!AB!osJ+g\r\u0005\u0002\u0011#5\tQ!\u0003\u0002\u0013\u000b\t!\u0001k\u001c7z\u0003\u0019!\u0013N\\5uIQ\tQ\u0003\u0005\u0002\u000b-%\u0011qc\u0003\u0002\u0005+:LGOA\u0003DCN,\u0007\'\u0006\u0002\u001bOA!1d\b\u0012&\u001d\taR$D\u0001\u0001\u0013\tq\u0012#A\u0006Qe>$Wo\u0019;DCN,\u0017B\u0001\u0011\"\u0005\r\tU\u000f\u001f\u0006\u0003=E\u0001\"\u0001E\u0012\n\u0005\u0011*!\u0001\u0002%OS2\u0004\"AJ\u0014\r\u0001\u0011)\u0001F\u0001b\u0001S\t\tA+\u0005\u0002+[A\u0011!bK\u0005\u0003Y-\u0011qAT8uQ&tw\r\u0005\u0002\u000b]%\u0011qf\u0003\u0002\u0004\u0003:L\u0018AA1u+\t\u0011D\b\u0006\u00024{I\u0011AG\u000e\u0004\u0005k\r\u00011G\u0001\u0007=e\u00164\u0017N\\3nK:$h\bE\u0002\u001do\tJ!\u0001O\t\u0003\u0017A\u0013x\u000eZ;di\u000e\u000b7/Z\u0003\u0005uQ\u00021H\u0001\u0004SKN,H\u000e\u001e\t\u0003Mq\"Q\u0001K\u0002C\u0002%BQAP\u0002A\u0002m\n\u0011\u0001\u001e"
    )
  ScalaInlineInfo: length = 0x13 (unknown attribute)
   01 00 00 03 00 22 00 23 01 00 12 00 13 01 00 16
   00 17 00
  ScalaSig: length = 0x3 (unknown attribute)
   05 02 00
