Classfile /Users/mw/Projects/slang-braindump/.jar/jar11/assemble/slang-braindump/assemble/content/shapeless/PolyDefns$LowPriorityLiftFunction1.class
  Last modified May 29, 2022; size 2250 bytes
  SHA-256 checksum 58d7d09f307800dc1ca15bdc123a925d7661378b413a5109c0ed7bbef7dd5440
  Compiled from "poly.scala"
public interface shapeless.PolyDefns$LowPriorityLiftFunction1 extends shapeless.Poly1
  minor version: 0
  major version: 52
  flags: (0x0601) ACC_PUBLIC, ACC_INTERFACE, ACC_ABSTRACT
  this_class: #2                          // shapeless/PolyDefns$LowPriorityLiftFunction1
  super_class: #4                         // java/lang/Object
  interfaces: 1, fields: 0, methods: 5, attributes: 5
Constant pool:
   #1 = Utf8               shapeless/PolyDefns$LowPriorityLiftFunction1
   #2 = Class              #1             // shapeless/PolyDefns$LowPriorityLiftFunction1
   #3 = Utf8               java/lang/Object
   #4 = Class              #3             // java/lang/Object
   #5 = Utf8               shapeless/Poly1
   #6 = Class              #5             // shapeless/Poly1
   #7 = Utf8               poly.scala
   #8 = Utf8               java/lang/invoke/MethodHandles$Lookup
   #9 = Class              #8             // java/lang/invoke/MethodHandles$Lookup
  #10 = Utf8               java/lang/invoke/MethodHandles
  #11 = Class              #10            // java/lang/invoke/MethodHandles
  #12 = Utf8               Lookup
  #13 = Utf8               shapeless/Poly1$CaseBuilder
  #14 = Class              #13            // shapeless/Poly1$CaseBuilder
  #15 = Utf8               CaseBuilder
  #16 = Utf8               shapeless/PolyDefns$Case
  #17 = Class              #16            // shapeless/PolyDefns$Case
  #18 = Utf8               shapeless/PolyDefns
  #19 = Class              #18            // shapeless/PolyDefns
  #20 = Utf8               Case
  #21 = Utf8               LowPriorityLiftFunction1
  #22 = Utf8               default$
  #23 = Utf8               (Lshapeless/PolyDefns$LowPriorityLiftFunction1;)Lshapeless/PolyDefns$Case;
  #24 = Utf8               $this
  #25 = Utf8               default
  #26 = Utf8               ()Lshapeless/PolyDefns$Case;
  #27 = NameAndType        #25:#26        // default:()Lshapeless/PolyDefns$Case;
  #28 = InterfaceMethodref #2.#27         // shapeless/PolyDefns$LowPriorityLiftFunction1.default:()Lshapeless/PolyDefns$Case;
  #29 = Utf8               Lshapeless/PolyDefns$LowPriorityLiftFunction1;
  #30 = Utf8               <T:Ljava/lang/Object;>()Lshapeless/PolyDefns$Case<Lshapeless/PolyDefns$LowPriorityLiftFunction1;Lshapeless/$colon$colon<TT;Lshapeless/HNil;>;>;
  #31 = Utf8               at
  #32 = Utf8               ()Lshapeless/Poly1$CaseBuilder;
  #33 = NameAndType        #31:#32        // at:()Lshapeless/Poly1$CaseBuilder;
  #34 = InterfaceMethodref #2.#33         // shapeless/PolyDefns$LowPriorityLiftFunction1.at:()Lshapeless/Poly1$CaseBuilder;
  #35 = Utf8               (Ljava/lang/Object;)Ljava/lang/Object;
  #36 = MethodType         #35            //  (Ljava/lang/Object;)Ljava/lang/Object;
  #37 = Utf8               $anonfun$default$1
  #38 = Utf8               (Ljava/lang/Object;)Lshapeless/HNil;
  #39 = NameAndType        #37:#38        // $anonfun$default$1:(Ljava/lang/Object;)Lshapeless/HNil;
  #40 = InterfaceMethodref #2.#39         // shapeless/PolyDefns$LowPriorityLiftFunction1.$anonfun$default$1:(Ljava/lang/Object;)Lshapeless/HNil;
  #41 = MethodHandle       6:#40          // REF_invokeStatic shapeless/PolyDefns$LowPriorityLiftFunction1.$anonfun$default$1:(Ljava/lang/Object;)Lshapeless/HNil;
  #42 = MethodType         #38            //  (Ljava/lang/Object;)Lshapeless/HNil;
  #43 = Integer            5
  #44 = Integer            1
  #45 = Utf8               java/lang/invoke/LambdaMetafactory
  #46 = Class              #45            // java/lang/invoke/LambdaMetafactory
  #47 = Utf8               altMetafactory
  #48 = Utf8               (Ljava/lang/invoke/MethodHandles$Lookup;Ljava/lang/String;Ljava/lang/invoke/MethodType;[Ljava/lang/Object;)Ljava/lang/invoke/CallSite;
  #49 = NameAndType        #47:#48        // altMetafactory:(Ljava/lang/invoke/MethodHandles$Lookup;Ljava/lang/String;Ljava/lang/invoke/MethodType;[Ljava/lang/Object;)Ljava/lang/invoke/CallSite;
  #50 = Methodref          #46.#49        // java/lang/invoke/LambdaMetafactory.altMetafactory:(Ljava/lang/invoke/MethodHandles$Lookup;Ljava/lang/String;Ljava/lang/invoke/MethodType;[Ljava/lang/Object;)Ljava/lang/invoke/CallSite;
  #51 = MethodHandle       6:#50          // REF_invokeStatic java/lang/invoke/LambdaMetafactory.altMetafactory:(Ljava/lang/invoke/MethodHandles$Lookup;Ljava/lang/String;Ljava/lang/invoke/MethodType;[Ljava/lang/Object;)Ljava/lang/invoke/CallSite;
  #52 = Utf8               apply
  #53 = Utf8               ()Lscala/Function1;
  #54 = NameAndType        #52:#53        // apply:()Lscala/Function1;
  #55 = InvokeDynamic      #0:#54         // #0:apply:()Lscala/Function1;
  #56 = Utf8               (Lscala/Function1;)Lshapeless/PolyDefns$Case;
  #57 = NameAndType        #52:#56        // apply:(Lscala/Function1;)Lshapeless/PolyDefns$Case;
  #58 = Methodref          #14.#57        // shapeless/Poly1$CaseBuilder.apply:(Lscala/Function1;)Lshapeless/PolyDefns$Case;
  #59 = Utf8               this
  #60 = Utf8               x$1
  #61 = Utf8               shapeless/HNil$
  #62 = Class              #61            // shapeless/HNil$
  #63 = Utf8               MODULE$
  #64 = Utf8               Lshapeless/HNil$;
  #65 = NameAndType        #63:#64        // MODULE$:Lshapeless/HNil$;
  #66 = Fieldref           #62.#65        // shapeless/HNil$.MODULE$:Lshapeless/HNil$;
  #67 = Utf8               Ljava/lang/Object;
  #68 = Utf8               $init$
  #69 = Utf8               (Lshapeless/PolyDefns$LowPriorityLiftFunction1;)V
  #70 = Utf8               $deserializeLambda$
  #71 = Utf8               (Ljava/lang/invoke/SerializedLambda;)Ljava/lang/Object;
  #72 = Utf8               scala/runtime/LambdaDeserialize
  #73 = Class              #72            // scala/runtime/LambdaDeserialize
  #74 = Utf8               bootstrap
  #75 = Utf8               (Ljava/lang/invoke/MethodHandles$Lookup;Ljava/lang/String;Ljava/lang/invoke/MethodType;[Ljava/lang/invoke/MethodHandle;)Ljava/lang/invoke/CallSite;
  #76 = NameAndType        #74:#75        // bootstrap:(Ljava/lang/invoke/MethodHandles$Lookup;Ljava/lang/String;Ljava/lang/invoke/MethodType;[Ljava/lang/invoke/MethodHandle;)Ljava/lang/invoke/CallSite;
  #77 = Methodref          #73.#76        // scala/runtime/LambdaDeserialize.bootstrap:(Ljava/lang/invoke/MethodHandles$Lookup;Ljava/lang/String;Ljava/lang/invoke/MethodType;[Ljava/lang/invoke/MethodHandle;)Ljava/lang/invoke/CallSite;
  #78 = MethodHandle       6:#77          // REF_invokeStatic scala/runtime/LambdaDeserialize.bootstrap:(Ljava/lang/invoke/MethodHandles$Lookup;Ljava/lang/String;Ljava/lang/invoke/MethodType;[Ljava/lang/invoke/MethodHandle;)Ljava/lang/invoke/CallSite;
  #79 = Utf8               lambdaDeserialize
  #80 = NameAndType        #79:#71        // lambdaDeserialize:(Ljava/lang/invoke/SerializedLambda;)Ljava/lang/Object;
  #81 = InvokeDynamic      #1:#80         // #1:lambdaDeserialize:(Ljava/lang/invoke/SerializedLambda;)Ljava/lang/Object;
  #82 = Utf8               Code
  #83 = Utf8               LineNumberTable
  #84 = Utf8               LocalVariableTable
  #85 = Utf8               MethodParameters
  #86 = Utf8               Signature
  #87 = Utf8               InnerClasses
  #88 = Utf8               SourceFile
  #89 = Utf8               BootstrapMethods
  #90 = Utf8               ScalaInlineInfo
  #91 = Utf8               Scala
{
  public static shapeless.PolyDefns$Case default$(shapeless.PolyDefns$LowPriorityLiftFunction1);
    descriptor: (Lshapeless/PolyDefns$LowPriorityLiftFunction1;)Lshapeless/PolyDefns$Case;
    flags: (0x1009) ACC_PUBLIC, ACC_STATIC, ACC_SYNTHETIC
    Code:
      stack=1, locals=1, args_size=1
         0: aload_0
         1: invokespecial #28                 // InterfaceMethod default:()Lshapeless/PolyDefns$Case;
         4: areturn
      LineNumberTable:
        line 124: 0
      LocalVariableTable:
        Start  Length  Slot  Name   Signature
            0       5     0 $this   Lshapeless/PolyDefns$LowPriorityLiftFunction1;
    MethodParameters:
      Name                           Flags
      $this                          final synthetic

  public default <T extends java.lang.Object> shapeless.PolyDefns$Case<shapeless.PolyDefns$LowPriorityLiftFunction1, shapeless.$colon$colon<T, shapeless.HNil>> default();
    descriptor: ()Lshapeless/PolyDefns$Case;
    flags: (0x0001) ACC_PUBLIC
    Code:
      stack=2, locals=1, args_size=1
         0: aload_0
         1: invokeinterface #34,  1           // InterfaceMethod at:()Lshapeless/Poly1$CaseBuilder;
         6: invokedynamic #55,  0             // InvokeDynamic #0:apply:()Lscala/Function1;
        11: invokevirtual #58                 // Method shapeless/Poly1$CaseBuilder.apply:(Lscala/Function1;)Lshapeless/PolyDefns$Case;
        14: areturn
      LineNumberTable:
        line 124: 0
      LocalVariableTable:
        Start  Length  Slot  Name   Signature
            0      15     0  this   Lshapeless/PolyDefns$LowPriorityLiftFunction1;
    Signature: #30                          // <T:Ljava/lang/Object;>()Lshapeless/PolyDefns$Case<Lshapeless/PolyDefns$LowPriorityLiftFunction1;Lshapeless/$colon$colon<TT;Lshapeless/HNil;>;>;

  public static shapeless.HNil $anonfun$default$1(java.lang.Object);
    descriptor: (Ljava/lang/Object;)Lshapeless/HNil;
    flags: (0x1009) ACC_PUBLIC, ACC_STATIC, ACC_SYNTHETIC
    Code:
      stack=1, locals=1, args_size=1
         0: getstatic     #66                 // Field shapeless/HNil$.MODULE$:Lshapeless/HNil$;
         3: areturn
      LineNumberTable:
        line 124: 0
      LocalVariableTable:
        Start  Length  Slot  Name   Signature
            0       4     0   x$1   Ljava/lang/Object;
    MethodParameters:
      Name                           Flags
      x$1                            final

  public static void $init$(shapeless.PolyDefns$LowPriorityLiftFunction1);
    descriptor: (Lshapeless/PolyDefns$LowPriorityLiftFunction1;)V
    flags: (0x0009) ACC_PUBLIC, ACC_STATIC
    Code:
      stack=0, locals=1, args_size=1
         0: return
      LineNumberTable:
        line 123: 0
      LocalVariableTable:
        Start  Length  Slot  Name   Signature
            0       1     0 $this   Lshapeless/PolyDefns$LowPriorityLiftFunction1;
    MethodParameters:
      Name                           Flags
      $this                          final synthetic

  private static java.lang.Object $deserializeLambda$(java.lang.invoke.SerializedLambda);
    descriptor: (Ljava/lang/invoke/SerializedLambda;)Ljava/lang/Object;
    flags: (0x100a) ACC_PRIVATE, ACC_STATIC, ACC_SYNTHETIC
    Code:
      stack=1, locals=1, args_size=1
         0: aload_0
         1: invokedynamic #81,  0             // InvokeDynamic #1:lambdaDeserialize:(Ljava/lang/invoke/SerializedLambda;)Ljava/lang/Object;
         6: areturn
}
InnerClasses:
  public static final #12= #9 of #11;     // Lookup=class java/lang/invoke/MethodHandles$Lookup of class java/lang/invoke/MethodHandles
  public #15= #14 of #6;                  // CaseBuilder=class shapeless/Poly1$CaseBuilder of class shapeless/Poly1
  public static abstract #20= #17 of #19; // Case=class shapeless/PolyDefns$Case of class shapeless/PolyDefns
  public static #21= #2 of #19;           // LowPriorityLiftFunction1=class shapeless/PolyDefns$LowPriorityLiftFunction1 of class shapeless/PolyDefns
SourceFile: "poly.scala"
BootstrapMethods:
  0: #51 REF_invokeStatic java/lang/invoke/LambdaMetafactory.altMetafactory:(Ljava/lang/invoke/MethodHandles$Lookup;Ljava/lang/String;Ljava/lang/invoke/MethodType;[Ljava/lang/Object;)Ljava/lang/invoke/CallSite;
    Method arguments:
      #36 (Ljava/lang/Object;)Ljava/lang/Object;
      #41 REF_invokeStatic shapeless/PolyDefns$LowPriorityLiftFunction1.$anonfun$default$1:(Ljava/lang/Object;)Lshapeless/HNil;
      #42 (Ljava/lang/Object;)Lshapeless/HNil;
      #43 5
      #44 1
      #42 (Ljava/lang/Object;)Lshapeless/HNil;
  1: #78 REF_invokeStatic scala/runtime/LambdaDeserialize.bootstrap:(Ljava/lang/invoke/MethodHandles$Lookup;Ljava/lang/String;Ljava/lang/invoke/MethodType;[Ljava/lang/invoke/MethodHandle;)Ljava/lang/invoke/CallSite;
    Method arguments:
      #41 REF_invokeStatic shapeless/PolyDefns$LowPriorityLiftFunction1.$anonfun$default$1:(Ljava/lang/Object;)Lshapeless/HNil;
  ScalaInlineInfo: length = 0x18 (unknown attribute)
   01 00 00 04 00 25 00 26 01 00 44 00 45 01 00 16
   00 17 01 00 19 00 1A 00
  Scala: length = 0x0 (unknown attribute)

