Classfile /Users/mw/Projects/slang-braindump/.jar/jar11/assemble/slang-braindump/assemble/content/shapeless/Prism$$anon$8.class
  Last modified May 29, 2022; size 8178 bytes
  SHA-256 checksum fbdfb8e3c91b152af9ea9edab5b55728ffd25dc0d1aa86cbde238abb674cbe34
  Compiled from "lenses.scala"
public final class shapeless.Prism$$anon$8 extends java.lang.Object implements shapeless.ProductPrismBuilder<S, scala.Tuple2<A, B>>
  minor version: 0
  major version: 52
  flags: (0x0031) ACC_PUBLIC, ACC_FINAL, ACC_SUPER
  this_class: #2                          // shapeless/Prism$$anon$8
  super_class: #5                         // java/lang/Object
  interfaces: 1, fields: 2, methods: 17, attributes: 7
Constant pool:
    #1 = Utf8               shapeless/Prism$$anon$8
    #2 = Class              #1            // shapeless/Prism$$anon$8
    #3 = Utf8               Ljava/lang/Object;Lshapeless/ProductPrismBuilder<TS;Lscala/Tuple2<TA;TB;>;>;
    #4 = Utf8               java/lang/Object
    #5 = Class              #4            // java/lang/Object
    #6 = Utf8               shapeless/ProductPrismBuilder
    #7 = Class              #6            // shapeless/ProductPrismBuilder
    #8 = Utf8               lenses.scala
    #9 = Utf8               shapeless/Prism
   #10 = Class              #9            // shapeless/Prism
   #11 = Utf8               $tilde
   #12 = Utf8               (Lshapeless/Prism;)Lshapeless/ProductPrismBuilder;
   #13 = NameAndType        #11:#12       // $tilde:(Lshapeless/Prism;)Lshapeless/ProductPrismBuilder;
   #14 = Utf8               java/lang/invoke/MethodHandles$Lookup
   #15 = Class              #14           // java/lang/invoke/MethodHandles$Lookup
   #16 = Utf8               java/lang/invoke/MethodHandles
   #17 = Class              #16           // java/lang/invoke/MethodHandles
   #18 = Utf8               Lookup
   #19 = Utf8               shapeless/ops/hlist$Init
   #20 = Class              #19           // shapeless/ops/hlist$Init
   #21 = Utf8               shapeless/ops/hlist
   #22 = Class              #21           // shapeless/ops/hlist
   #23 = Utf8               Init
   #24 = Utf8               shapeless/ops/hlist$Last
   #25 = Class              #24           // shapeless/ops/hlist$Last
   #26 = Utf8               Last
   #27 = Utf8               shapeless/ops/hlist$Prepend
   #28 = Class              #27           // shapeless/ops/hlist$Prepend
   #29 = Utf8               Prepend
   #30 = Utf8               shapeless/ops/hlist$Tupler
   #31 = Class              #30           // shapeless/ops/hlist$Tupler
   #32 = Utf8               Tupler
   #33 = Utf8               $outer
   #34 = Utf8               Lshapeless/Prism;
   #35 = Utf8               other$4
   #36 = Utf8               (Lshapeless/Prism;Lshapeless/Generic;Lshapeless/ops/hlist$Tupler;Lshapeless/ops/hlist$Prepend;Lshapeless/ops/hlist$Tupler;Lshapeless/Generic;Lshapeless/ops/hlist$Init;Lshapeless/ops/hlist$Last;)Lshapeless/ProductPrismBuilder;
   #37 = Utf8               <T:Ljava/lang/Object;L::Lshapeless/HList;LT::Lshapeless/HList;Q::Lscala/Product;QL::Lshapeless/HList;>(Lshapeless/Prism<TS;TT;>;Lshapeless/Generic<Lscala/Tuple2<TA;TB;>;>;Lshapeless/ops/hlist$Tupler<TL;>;Lshapeless/ops/hlist$Prepend<TL;Lshapeless/$colon$colon<TT;Lshapeless/HNil;>;>;Lshapeless/ops/hlist$Tupler<TLT;>;Lshapeless/Generic<TQ;>;Lshapeless/ops/hlist$Init<TQL;>;Lshapeless/ops/hlist$Last<TQL;>;)Lshapeless/ProductPrismBuilder<TS;TQ;>;
   #38 = Utf8               other
   #39 = Utf8               genp
   #40 = Utf8               tpp
   #41 = Utf8               pre
   #42 = Utf8               tpq
   #43 = Utf8               genq
   #44 = Utf8               init
   #45 = Utf8               last
   #46 = Utf8               $tilde$
   #47 = Utf8               (Lshapeless/ProductPrismBuilder;Lshapeless/Prism;Lshapeless/Generic;Lshapeless/ops/hlist$Tupler;Lshapeless/ops/hlist$Prepend;Lshapeless/ops/hlist$Tupler;Lshapeless/Generic;Lshapeless/ops/hlist$Init;Lshapeless/ops/hlist$Last;)Lshapeless/ProductPrismBuilder;
   #48 = NameAndType        #46:#47       // $tilde$:(Lshapeless/ProductPrismBuilder;Lshapeless/Prism;Lshapeless/Generic;Lshapeless/ops/hlist$Tupler;Lshapeless/ops/hlist$Prepend;Lshapeless/ops/hlist$Tupler;Lshapeless/Generic;Lshapeless/ops/hlist$Init;Lshapeless/ops/hlist$Last;)Lshapeless/ProductPrismBuilder;
   #49 = InterfaceMethodref #7.#48        // shapeless/ProductPrismBuilder.$tilde$:(Lshapeless/ProductPrismBuilder;Lshapeless/Prism;Lshapeless/Generic;Lshapeless/ops/hlist$Tupler;Lshapeless/ops/hlist$Prepend;Lshapeless/ops/hlist$Tupler;Lshapeless/Generic;Lshapeless/ops/hlist$Init;Lshapeless/ops/hlist$Last;)Lshapeless/ProductPrismBuilder;
   #50 = Utf8               this
   #51 = Utf8               Lshapeless/Prism$$anon$8;
   #52 = Utf8               Lshapeless/Generic;
   #53 = Utf8               Lshapeless/ops/hlist$Tupler;
   #54 = Utf8               Lshapeless/ops/hlist$Prepend;
   #55 = Utf8               Lshapeless/ops/hlist$Init;
   #56 = Utf8               Lshapeless/ops/hlist$Last;
   #57 = Utf8               modify
   #58 = Utf8               (Ljava/lang/Object;Lscala/Function1;)Ljava/lang/Object;
   #59 = Utf8               (TS;Lscala/Function1<Lscala/Tuple2<TA;TB;>;Lscala/Tuple2<TA;TB;>;>;)TS;
   #60 = Utf8               s
   #61 = Utf8               f
   #62 = Utf8               modify$
   #63 = Utf8               (Lshapeless/Prism;Ljava/lang/Object;Lscala/Function1;)Ljava/lang/Object;
   #64 = NameAndType        #62:#63       // modify$:(Lshapeless/Prism;Ljava/lang/Object;Lscala/Function1;)Ljava/lang/Object;
   #65 = InterfaceMethodref #10.#64       // shapeless/Prism.modify$:(Lshapeless/Prism;Ljava/lang/Object;Lscala/Function1;)Ljava/lang/Object;
   #66 = Utf8               Ljava/lang/Object;
   #67 = Utf8               Lscala/Function1;
   #68 = Utf8               compose
   #69 = Utf8               (Lshapeless/Lens;)Lshapeless/Prism;
   #70 = Utf8               <T:Ljava/lang/Object;>(Lshapeless/Lens<TT;TS;>;)Lshapeless/Prism<TT;Lscala/Tuple2<TA;TB;>;>;
   #71 = Utf8               g
   #72 = Utf8               compose$
   #73 = Utf8               (Lshapeless/Prism;Lshapeless/Lens;)Lshapeless/Prism;
   #74 = NameAndType        #72:#73       // compose$:(Lshapeless/Prism;Lshapeless/Lens;)Lshapeless/Prism;
   #75 = InterfaceMethodref #10.#74       // shapeless/Prism.compose$:(Lshapeless/Prism;Lshapeless/Lens;)Lshapeless/Prism;
   #76 = Utf8               Lshapeless/Lens;
   #77 = Utf8               (Lshapeless/Prism;)Lshapeless/Prism;
   #78 = Utf8               <T:Ljava/lang/Object;>(Lshapeless/Prism<TT;TS;>;)Lshapeless/Prism<TT;Lscala/Tuple2<TA;TB;>;>;
   #79 = Utf8               (Lshapeless/Prism;Lshapeless/Prism;)Lshapeless/Prism;
   #80 = NameAndType        #72:#79       // compose$:(Lshapeless/Prism;Lshapeless/Prism;)Lshapeless/Prism;
   #81 = InterfaceMethodref #10.#80       // shapeless/Prism.compose$:(Lshapeless/Prism;Lshapeless/Prism;)Lshapeless/Prism;
   #82 = Utf8               selectDynamic
   #83 = Utf8               (Ljava/lang/String;Lshapeless/MkSelectDynamicOptic;)Ljava/lang/Object;
   #84 = Utf8               (Ljava/lang/String;Lshapeless/MkSelectDynamicOptic<Lshapeless/Prism<TS;Lscala/Tuple2<TA;TB;>;>;Lscala/Tuple2<TA;TB;>;Lscala/Symbol;Lscala/runtime/Nothing$;>;)Ljava/lang/Object;
   #85 = Utf8               k
   #86 = Utf8               mkPrism
   #87 = Utf8               selectDynamic$
   #88 = Utf8               (Lshapeless/Prism;Ljava/lang/String;Lshapeless/MkSelectDynamicOptic;)Ljava/lang/Object;
   #89 = NameAndType        #87:#88       // selectDynamic$:(Lshapeless/Prism;Ljava/lang/String;Lshapeless/MkSelectDynamicOptic;)Ljava/lang/Object;
   #90 = InterfaceMethodref #10.#89       // shapeless/Prism.selectDynamic$:(Lshapeless/Prism;Ljava/lang/String;Lshapeless/MkSelectDynamicOptic;)Ljava/lang/Object;
   #91 = Utf8               Ljava/lang/String;
   #92 = Utf8               Lshapeless/MkSelectDynamicOptic;
   #93 = Utf8               apply
   #94 = Utf8               (Lshapeless/MkCtorPrism;)Lshapeless/Prism;
   #95 = Utf8               <B:Ljava/lang/Object;>(Lshapeless/MkCtorPrism<Lscala/Tuple2<TA;TB;>;TB;>;)Lshapeless/Prism<TS;TB;>;
   #96 = Utf8               apply$
   #97 = Utf8               (Lshapeless/Prism;Lshapeless/MkCtorPrism;)Lshapeless/Prism;
   #98 = NameAndType        #96:#97       // apply$:(Lshapeless/Prism;Lshapeless/MkCtorPrism;)Lshapeless/Prism;
   #99 = InterfaceMethodref #10.#98       // shapeless/Prism.apply$:(Lshapeless/Prism;Lshapeless/MkCtorPrism;)Lshapeless/Prism;
  #100 = Utf8               Lshapeless/MkCtorPrism;
  #101 = Utf8               unapply
  #102 = Utf8               (Ljava/lang/Object;)Lscala/Option;
  #103 = Utf8               (TS;)Lscala/Option<Lscala/Tuple2<TA;TB;>;>;
  #104 = Utf8               unapply$
  #105 = Utf8               (Lshapeless/Prism;Ljava/lang/Object;)Lscala/Option;
  #106 = NameAndType        #104:#105     // unapply$:(Lshapeless/Prism;Ljava/lang/Object;)Lscala/Option;
  #107 = InterfaceMethodref #10.#106      // shapeless/Prism.unapply$:(Lshapeless/Prism;Ljava/lang/Object;)Lscala/Option;
  #108 = Utf8               (Lshapeless/Lens;)Lshapeless/ProductPrismBuilder;
  #109 = Utf8               <B:Ljava/lang/Object;>(Lshapeless/Lens<TS;TB;>;)Lshapeless/ProductPrismBuilder<TS;Lscala/Tuple2<Lscala/Tuple2<TA;TB;>;TB;>;>;
  #110 = Utf8               (Lshapeless/Prism;Lshapeless/Lens;)Lshapeless/ProductPrismBuilder;
  #111 = NameAndType        #46:#110      // $tilde$:(Lshapeless/Prism;Lshapeless/Lens;)Lshapeless/ProductPrismBuilder;
  #112 = InterfaceMethodref #10.#111      // shapeless/Prism.$tilde$:(Lshapeless/Prism;Lshapeless/Lens;)Lshapeless/ProductPrismBuilder;
  #113 = Utf8               <B:Ljava/lang/Object;>(Lshapeless/Prism<TS;TB;>;)Lshapeless/ProductPrismBuilder<TS;Lscala/Tuple2<Lscala/Tuple2<TA;TB;>;TB;>;>;
  #114 = Utf8               (Lshapeless/Prism;Lshapeless/Prism;)Lshapeless/ProductPrismBuilder;
  #115 = NameAndType        #46:#114      // $tilde$:(Lshapeless/Prism;Lshapeless/Prism;)Lshapeless/ProductPrismBuilder;
  #116 = InterfaceMethodref #10.#115      // shapeless/Prism.$tilde$:(Lshapeless/Prism;Lshapeless/Prism;)Lshapeless/ProductPrismBuilder;
  #117 = Utf8               (Ljava/lang/String;Lshapeless/MkSelectDynamicOptic;Lscala/DummyImplicit;)Ljava/lang/Object;
  #118 = Utf8               <B:Ljava/lang/Object;>(Ljava/lang/String;Lshapeless/MkSelectDynamicOptic<Lshapeless/Prism<TS;Lscala/Tuple2<TA;TB;>;>;Lscala/Tuple2<TA;TB;>;Lscala/Symbol;TB;>;Lscala/DummyImplicit;)Ljava/lang/Object;
  #119 = Utf8               dummy
  #120 = Utf8               shapeless/LPPrism
  #121 = Class              #120          // shapeless/LPPrism
  #122 = Utf8               (Lshapeless/LPPrism;Ljava/lang/String;Lshapeless/MkSelectDynamicOptic;Lscala/DummyImplicit;)Ljava/lang/Object;
  #123 = NameAndType        #87:#122      // selectDynamic$:(Lshapeless/LPPrism;Ljava/lang/String;Lshapeless/MkSelectDynamicOptic;Lscala/DummyImplicit;)Ljava/lang/Object;
  #124 = InterfaceMethodref #121.#123     // shapeless/LPPrism.selectDynamic$:(Lshapeless/LPPrism;Ljava/lang/String;Lshapeless/MkSelectDynamicOptic;Lscala/DummyImplicit;)Ljava/lang/Object;
  #125 = Utf8               Lscala/DummyImplicit;
  #126 = Utf8               get
  #127 = NameAndType        #33:#34       // $outer:Lshapeless/Prism;
  #128 = Fieldref           #2.#127       // shapeless/Prism$$anon$8.$outer:Lshapeless/Prism;
  #129 = NameAndType        #126:#102     // get:(Ljava/lang/Object;)Lscala/Option;
  #130 = InterfaceMethodref #10.#129      // shapeless/Prism.get:(Ljava/lang/Object;)Lscala/Option;
  #131 = Utf8               (Ljava/lang/Object;)Ljava/lang/Object;
  #132 = MethodType         #131          //  (Ljava/lang/Object;)Ljava/lang/Object;
  #133 = Utf8               $anonfun$get$5
  #134 = Utf8               (Lshapeless/Prism$$anon$8;Ljava/lang/Object;Ljava/lang/Object;)Lscala/Option;
  #135 = NameAndType        #133:#134     // $anonfun$get$5:(Lshapeless/Prism$$anon$8;Ljava/lang/Object;Ljava/lang/Object;)Lscala/Option;
  #136 = Methodref          #2.#135       // shapeless/Prism$$anon$8.$anonfun$get$5:(Lshapeless/Prism$$anon$8;Ljava/lang/Object;Ljava/lang/Object;)Lscala/Option;
  #137 = MethodHandle       6:#136        // REF_invokeStatic shapeless/Prism$$anon$8.$anonfun$get$5:(Lshapeless/Prism$$anon$8;Ljava/lang/Object;Ljava/lang/Object;)Lscala/Option;
  #138 = MethodType         #102          //  (Ljava/lang/Object;)Lscala/Option;
  #139 = Integer            5
  #140 = Integer            1
  #141 = Utf8               java/lang/invoke/LambdaMetafactory
  #142 = Class              #141          // java/lang/invoke/LambdaMetafactory
  #143 = Utf8               altMetafactory
  #144 = Utf8               (Ljava/lang/invoke/MethodHandles$Lookup;Ljava/lang/String;Ljava/lang/invoke/MethodType;[Ljava/lang/Object;)Ljava/lang/invoke/CallSite;
  #145 = NameAndType        #143:#144     // altMetafactory:(Ljava/lang/invoke/MethodHandles$Lookup;Ljava/lang/String;Ljava/lang/invoke/MethodType;[Ljava/lang/Object;)Ljava/lang/invoke/CallSite;
  #146 = Methodref          #142.#145     // java/lang/invoke/LambdaMetafactory.altMetafactory:(Ljava/lang/invoke/MethodHandles$Lookup;Ljava/lang/String;Ljava/lang/invoke/MethodType;[Ljava/lang/Object;)Ljava/lang/invoke/CallSite;
  #147 = MethodHandle       6:#146        // REF_invokeStatic java/lang/invoke/LambdaMetafactory.altMetafactory:(Ljava/lang/invoke/MethodHandles$Lookup;Ljava/lang/String;Ljava/lang/invoke/MethodType;[Ljava/lang/Object;)Ljava/lang/invoke/CallSite;
  #148 = Utf8               (Lshapeless/Prism$$anon$8;Ljava/lang/Object;)Lscala/Function1;
  #149 = NameAndType        #93:#148      // apply:(Lshapeless/Prism$$anon$8;Ljava/lang/Object;)Lscala/Function1;
  #150 = InvokeDynamic      #0:#149       // #0:apply:(Lshapeless/Prism$$anon$8;Ljava/lang/Object;)Lscala/Function1;
  #151 = Utf8               scala/Option
  #152 = Class              #151          // scala/Option
  #153 = Utf8               flatMap
  #154 = Utf8               (Lscala/Function1;)Lscala/Option;
  #155 = NameAndType        #153:#154     // flatMap:(Lscala/Function1;)Lscala/Option;
  #156 = Methodref          #152.#155     // scala/Option.flatMap:(Lscala/Function1;)Lscala/Option;
  #157 = Utf8               set
  #158 = Utf8               (Ljava/lang/Object;Lscala/Tuple2;)Ljava/lang/Object;
  #159 = Utf8               (TS;Lscala/Tuple2<TA;TB;>;)TS;
  #160 = Utf8               ab
  #161 = NameAndType        #35:#34       // other$4:Lshapeless/Prism;
  #162 = Fieldref           #2.#161       // shapeless/Prism$$anon$8.other$4:Lshapeless/Prism;
  #163 = Utf8               scala/Tuple2
  #164 = Class              #163          // scala/Tuple2
  #165 = Utf8               _1
  #166 = Utf8               ()Ljava/lang/Object;
  #167 = NameAndType        #165:#166     // _1:()Ljava/lang/Object;
  #168 = Methodref          #164.#167     // scala/Tuple2._1:()Ljava/lang/Object;
  #169 = Utf8               (Ljava/lang/Object;Ljava/lang/Object;)Ljava/lang/Object;
  #170 = NameAndType        #157:#169     // set:(Ljava/lang/Object;Ljava/lang/Object;)Ljava/lang/Object;
  #171 = InterfaceMethodref #10.#170      // shapeless/Prism.set:(Ljava/lang/Object;Ljava/lang/Object;)Ljava/lang/Object;
  #172 = Utf8               _2
  #173 = NameAndType        #172:#166     // _2:()Ljava/lang/Object;
  #174 = Methodref          #164.#173     // scala/Tuple2._2:()Ljava/lang/Object;
  #175 = Utf8               Lscala/Tuple2;
  #176 = Utf8               a
  #177 = NameAndType        #157:#158     // set:(Ljava/lang/Object;Lscala/Tuple2;)Ljava/lang/Object;
  #178 = Methodref          #2.#177       // shapeless/Prism$$anon$8.set:(Ljava/lang/Object;Lscala/Tuple2;)Ljava/lang/Object;
  #179 = Utf8               $anonfun$get$6
  #180 = Utf8               (Ljava/lang/Object;Ljava/lang/Object;)Lscala/Tuple2;
  #181 = Utf8               fst$1
  #182 = Utf8               snd
  #183 = Utf8               <init>
  #184 = Utf8               (Ljava/lang/Object;Ljava/lang/Object;)V
  #185 = NameAndType        #183:#184     // "<init>":(Ljava/lang/Object;Ljava/lang/Object;)V
  #186 = Methodref          #164.#185     // scala/Tuple2."<init>":(Ljava/lang/Object;Ljava/lang/Object;)V
  #187 = Utf8               $this
  #188 = Utf8               s$4
  #189 = Utf8               fst
  #190 = NameAndType        #179:#180     // $anonfun$get$6:(Ljava/lang/Object;Ljava/lang/Object;)Lscala/Tuple2;
  #191 = Methodref          #2.#190       // shapeless/Prism$$anon$8.$anonfun$get$6:(Ljava/lang/Object;Ljava/lang/Object;)Lscala/Tuple2;
  #192 = MethodHandle       6:#191        // REF_invokeStatic shapeless/Prism$$anon$8.$anonfun$get$6:(Ljava/lang/Object;Ljava/lang/Object;)Lscala/Tuple2;
  #193 = Utf8               (Ljava/lang/Object;)Lscala/Tuple2;
  #194 = MethodType         #193          //  (Ljava/lang/Object;)Lscala/Tuple2;
  #195 = Utf8               (Ljava/lang/Object;)Lscala/Function1;
  #196 = NameAndType        #93:#195      // apply:(Ljava/lang/Object;)Lscala/Function1;
  #197 = InvokeDynamic      #1:#196       // #1:apply:(Ljava/lang/Object;)Lscala/Function1;
  #198 = Utf8               map
  #199 = NameAndType        #198:#154     // map:(Lscala/Function1;)Lscala/Option;
  #200 = Methodref          #152.#199     // scala/Option.map:(Lscala/Function1;)Lscala/Option;
  #201 = Utf8               (Lshapeless/Prism;Lshapeless/Prism;)V
  #202 = Utf8               ()V
  #203 = NameAndType        #183:#202     // "<init>":()V
  #204 = Methodref          #5.#203       // java/lang/Object."<init>":()V
  #205 = Utf8               $init$
  #206 = Utf8               (Lshapeless/LPPrism;)V
  #207 = NameAndType        #205:#206     // $init$:(Lshapeless/LPPrism;)V
  #208 = InterfaceMethodref #121.#207     // shapeless/LPPrism.$init$:(Lshapeless/LPPrism;)V
  #209 = Utf8               (Lshapeless/Prism;)V
  #210 = NameAndType        #205:#209     // $init$:(Lshapeless/Prism;)V
  #211 = InterfaceMethodref #10.#210      // shapeless/Prism.$init$:(Lshapeless/Prism;)V
  #212 = Utf8               (Lshapeless/ProductPrismBuilder;)V
  #213 = NameAndType        #205:#212     // $init$:(Lshapeless/ProductPrismBuilder;)V
  #214 = InterfaceMethodref #7.#213       // shapeless/ProductPrismBuilder.$init$:(Lshapeless/ProductPrismBuilder;)V
  #215 = Utf8               $deserializeLambda$
  #216 = Utf8               (Ljava/lang/invoke/SerializedLambda;)Ljava/lang/Object;
  #217 = Utf8               scala/runtime/LambdaDeserialize
  #218 = Class              #217          // scala/runtime/LambdaDeserialize
  #219 = Utf8               bootstrap
  #220 = Utf8               (Ljava/lang/invoke/MethodHandles$Lookup;Ljava/lang/String;Ljava/lang/invoke/MethodType;[Ljava/lang/invoke/MethodHandle;)Ljava/lang/invoke/CallSite;
  #221 = NameAndType        #219:#220     // bootstrap:(Ljava/lang/invoke/MethodHandles$Lookup;Ljava/lang/String;Ljava/lang/invoke/MethodType;[Ljava/lang/invoke/MethodHandle;)Ljava/lang/invoke/CallSite;
  #222 = Methodref          #218.#221     // scala/runtime/LambdaDeserialize.bootstrap:(Ljava/lang/invoke/MethodHandles$Lookup;Ljava/lang/String;Ljava/lang/invoke/MethodType;[Ljava/lang/invoke/MethodHandle;)Ljava/lang/invoke/CallSite;
  #223 = MethodHandle       6:#222        // REF_invokeStatic scala/runtime/LambdaDeserialize.bootstrap:(Ljava/lang/invoke/MethodHandles$Lookup;Ljava/lang/String;Ljava/lang/invoke/MethodType;[Ljava/lang/invoke/MethodHandle;)Ljava/lang/invoke/CallSite;
  #224 = Utf8               lambdaDeserialize
  #225 = NameAndType        #224:#216     // lambdaDeserialize:(Ljava/lang/invoke/SerializedLambda;)Ljava/lang/Object;
  #226 = InvokeDynamic      #2:#225       // #2:lambdaDeserialize:(Ljava/lang/invoke/SerializedLambda;)Ljava/lang/Object;
  #227 = Utf8               Code
  #228 = Utf8               LineNumberTable
  #229 = Utf8               LocalVariableTable
  #230 = Utf8               Signature
  #231 = Utf8               MethodParameters
  #232 = Utf8               StackMapTable
  #233 = Utf8               InnerClasses
  #234 = Utf8               EnclosingMethod
  #235 = Utf8               SourceFile
  #236 = Utf8               BootstrapMethods
  #237 = Utf8               ScalaInlineInfo
  #238 = Utf8               Scala
{
  private final shapeless.Prism $outer;
    descriptor: Lshapeless/Prism;
    flags: (0x1012) ACC_PRIVATE, ACC_FINAL, ACC_SYNTHETIC

  private final shapeless.Prism other$4;
    descriptor: Lshapeless/Prism;
    flags: (0x0012) ACC_PRIVATE, ACC_FINAL

  public <T extends java.lang.Object, L extends shapeless.HList, LT extends shapeless.HList, Q extends scala.Product, QL extends shapeless.HList> shapeless.ProductPrismBuilder<S, Q> $tilde(shapeless.Prism<S, T>, shapeless.Generic<scala.Tuple2<A, B>>, shapeless.ops.hlist$Tupler<L>, shapeless.ops.hlist$Prepend<L, shapeless.$colon$colon<T, shapeless.HNil>>, shapeless.ops.hlist$Tupler<LT>, shapeless.Generic<Q>, shapeless.ops.hlist$Init<QL>, shapeless.ops.hlist$Last<QL>);
    descriptor: (Lshapeless/Prism;Lshapeless/Generic;Lshapeless/ops/hlist$Tupler;Lshapeless/ops/hlist$Prepend;Lshapeless/ops/hlist$Tupler;Lshapeless/Generic;Lshapeless/ops/hlist$Init;Lshapeless/ops/hlist$Last;)Lshapeless/ProductPrismBuilder;
    flags: (0x0001) ACC_PUBLIC
    Code:
      stack=9, locals=9, args_size=9
         0: aload_0
         1: aload_1
         2: aload_2
         3: aload_3
         4: aload         4
         6: aload         5
         8: aload         6
        10: aload         7
        12: aload         8
        14: invokestatic  #49                 // InterfaceMethod shapeless/ProductPrismBuilder.$tilde$:(Lshapeless/ProductPrismBuilder;Lshapeless/Prism;Lshapeless/Generic;Lshapeless/ops/hlist$Tupler;Lshapeless/ops/hlist$Prepend;Lshapeless/ops/hlist$Tupler;Lshapeless/Generic;Lshapeless/ops/hlist$Init;Lshapeless/ops/hlist$Last;)Lshapeless/ProductPrismBuilder;
        17: areturn
      LineNumberTable:
        line 97: 0
      LocalVariableTable:
        Start  Length  Slot  Name   Signature
            0      18     0  this   Lshapeless/Prism$$anon$8;
            0      18     1 other   Lshapeless/Prism;
            0      18     2  genp   Lshapeless/Generic;
            0      18     3   tpp   Lshapeless/ops/hlist$Tupler;
            0      18     4   pre   Lshapeless/ops/hlist$Prepend;
            0      18     5   tpq   Lshapeless/ops/hlist$Tupler;
            0      18     6  genq   Lshapeless/Generic;
            0      18     7  init   Lshapeless/ops/hlist$Init;
            0      18     8  last   Lshapeless/ops/hlist$Last;
    Signature: #37                          // <T:Ljava/lang/Object;L::Lshapeless/HList;LT::Lshapeless/HList;Q::Lscala/Product;QL::Lshapeless/HList;>(Lshapeless/Prism<TS;TT;>;Lshapeless/Generic<Lscala/Tuple2<TA;TB;>;>;Lshapeless/ops/hlist$Tupler<TL;>;Lshapeless/ops/hlist$Prepend<TL;Lshapeless/$colon$colon<TT;Lshapeless/HNil;>;>;Lshapeless/ops/hlist$Tupler<TLT;>;Lshapeless/Generic<TQ;>;Lshapeless/ops/hlist$Init<TQL;>;Lshapeless/ops/hlist$Last<TQL;>;)Lshapeless/ProductPrismBuilder<TS;TQ;>;
    MethodParameters:
      Name                           Flags
      other                          final
      genp                           final
      tpp                            final
      pre                            final
      tpq                            final
      genq                           final
      init                           final
      last                           final

  public S modify(S, scala.Function1<scala.Tuple2<A, B>, scala.Tuple2<A, B>>);
    descriptor: (Ljava/lang/Object;Lscala/Function1;)Ljava/lang/Object;
    flags: (0x0001) ACC_PUBLIC
    Code:
      stack=3, locals=3, args_size=3
         0: aload_0
         1: aload_1
         2: aload_2
         3: invokestatic  #65                 // InterfaceMethod shapeless/Prism.modify$:(Lshapeless/Prism;Ljava/lang/Object;Lscala/Function1;)Ljava/lang/Object;
         6: areturn
      LineNumberTable:
        line 97: 0
      LocalVariableTable:
        Start  Length  Slot  Name   Signature
            0       7     0  this   Lshapeless/Prism$$anon$8;
            0       7     1     s   Ljava/lang/Object;
            0       7     2     f   Lscala/Function1;
    Signature: #59                          // (TS;Lscala/Function1<Lscala/Tuple2<TA;TB;>;Lscala/Tuple2<TA;TB;>;>;)TS;
    MethodParameters:
      Name                           Flags
      s                              final
      f                              final

  public <T extends java.lang.Object> shapeless.Prism<T, scala.Tuple2<A, B>> compose(shapeless.Lens<T, S>);
    descriptor: (Lshapeless/Lens;)Lshapeless/Prism;
    flags: (0x0001) ACC_PUBLIC
    Code:
      stack=2, locals=2, args_size=2
         0: aload_0
         1: aload_1
         2: invokestatic  #75                 // InterfaceMethod shapeless/Prism.compose$:(Lshapeless/Prism;Lshapeless/Lens;)Lshapeless/Prism;
         5: areturn
      LineNumberTable:
        line 97: 0
      LocalVariableTable:
        Start  Length  Slot  Name   Signature
            0       6     0  this   Lshapeless/Prism$$anon$8;
            0       6     1     g   Lshapeless/Lens;
    Signature: #70                          // <T:Ljava/lang/Object;>(Lshapeless/Lens<TT;TS;>;)Lshapeless/Prism<TT;Lscala/Tuple2<TA;TB;>;>;
    MethodParameters:
      Name                           Flags
      g                              final

  public <T extends java.lang.Object> shapeless.Prism<T, scala.Tuple2<A, B>> compose(shapeless.Prism<T, S>);
    descriptor: (Lshapeless/Prism;)Lshapeless/Prism;
    flags: (0x0001) ACC_PUBLIC
    Code:
      stack=2, locals=2, args_size=2
         0: aload_0
         1: aload_1
         2: invokestatic  #81                 // InterfaceMethod shapeless/Prism.compose$:(Lshapeless/Prism;Lshapeless/Prism;)Lshapeless/Prism;
         5: areturn
      LineNumberTable:
        line 97: 0
      LocalVariableTable:
        Start  Length  Slot  Name   Signature
            0       6     0  this   Lshapeless/Prism$$anon$8;
            0       6     1     g   Lshapeless/Prism;
    Signature: #78                          // <T:Ljava/lang/Object;>(Lshapeless/Prism<TT;TS;>;)Lshapeless/Prism<TT;Lscala/Tuple2<TA;TB;>;>;
    MethodParameters:
      Name                           Flags
      g                              final

  public java.lang.Object selectDynamic(java.lang.String, shapeless.MkSelectDynamicOptic<shapeless.Prism<S, scala.Tuple2<A, B>>, scala.Tuple2<A, B>, scala.Symbol, scala.runtime.Nothing$>);
    descriptor: (Ljava/lang/String;Lshapeless/MkSelectDynamicOptic;)Ljava/lang/Object;
    flags: (0x0001) ACC_PUBLIC
    Code:
      stack=3, locals=3, args_size=3
         0: aload_0
         1: aload_1
         2: aload_2
         3: invokestatic  #90                 // InterfaceMethod shapeless/Prism.selectDynamic$:(Lshapeless/Prism;Ljava/lang/String;Lshapeless/MkSelectDynamicOptic;)Ljava/lang/Object;
         6: areturn
      LineNumberTable:
        line 97: 0
      LocalVariableTable:
        Start  Length  Slot  Name   Signature
            0       7     0  this   Lshapeless/Prism$$anon$8;
            0       7     1     k   Ljava/lang/String;
            0       7     2 mkPrism   Lshapeless/MkSelectDynamicOptic;
    Signature: #84                          // (Ljava/lang/String;Lshapeless/MkSelectDynamicOptic<Lshapeless/Prism<TS;Lscala/Tuple2<TA;TB;>;>;Lscala/Tuple2<TA;TB;>;Lscala/Symbol;Lscala/runtime/Nothing$;>;)Ljava/lang/Object;
    MethodParameters:
      Name                           Flags
      k                              final
      mkPrism                        final

  public <B extends java.lang.Object> shapeless.Prism<S, B> apply(shapeless.MkCtorPrism<scala.Tuple2<A, B>, B>);
    descriptor: (Lshapeless/MkCtorPrism;)Lshapeless/Prism;
    flags: (0x0001) ACC_PUBLIC
    Code:
      stack=2, locals=2, args_size=2
         0: aload_0
         1: aload_1
         2: invokestatic  #99                 // InterfaceMethod shapeless/Prism.apply$:(Lshapeless/Prism;Lshapeless/MkCtorPrism;)Lshapeless/Prism;
         5: areturn
      LineNumberTable:
        line 97: 0
      LocalVariableTable:
        Start  Length  Slot  Name   Signature
            0       6     0  this   Lshapeless/Prism$$anon$8;
            0       6     1 mkPrism   Lshapeless/MkCtorPrism;
    Signature: #95                          // <B:Ljava/lang/Object;>(Lshapeless/MkCtorPrism<Lscala/Tuple2<TA;TB;>;TB;>;)Lshapeless/Prism<TS;TB;>;
    MethodParameters:
      Name                           Flags
      mkPrism                        final

  public scala.Option<scala.Tuple2<A, B>> unapply(S);
    descriptor: (Ljava/lang/Object;)Lscala/Option;
    flags: (0x0001) ACC_PUBLIC
    Code:
      stack=2, locals=2, args_size=2
         0: aload_0
         1: aload_1
         2: invokestatic  #107                // InterfaceMethod shapeless/Prism.unapply$:(Lshapeless/Prism;Ljava/lang/Object;)Lscala/Option;
         5: areturn
      LineNumberTable:
        line 97: 0
      LocalVariableTable:
        Start  Length  Slot  Name   Signature
            0       6     0  this   Lshapeless/Prism$$anon$8;
            0       6     1     s   Ljava/lang/Object;
    Signature: #103                         // (TS;)Lscala/Option<Lscala/Tuple2<TA;TB;>;>;
    MethodParameters:
      Name                           Flags
      s                              final

  public <B extends java.lang.Object> shapeless.ProductPrismBuilder<S, scala.Tuple2<scala.Tuple2<A, B>, B>> $tilde(shapeless.Lens<S, B>);
    descriptor: (Lshapeless/Lens;)Lshapeless/ProductPrismBuilder;
    flags: (0x0001) ACC_PUBLIC
    Code:
      stack=2, locals=2, args_size=2
         0: aload_0
         1: aload_1
         2: invokestatic  #112                // InterfaceMethod shapeless/Prism.$tilde$:(Lshapeless/Prism;Lshapeless/Lens;)Lshapeless/ProductPrismBuilder;
         5: areturn
      LineNumberTable:
        line 97: 0
      LocalVariableTable:
        Start  Length  Slot  Name   Signature
            0       6     0  this   Lshapeless/Prism$$anon$8;
            0       6     1 other   Lshapeless/Lens;
    Signature: #109                         // <B:Ljava/lang/Object;>(Lshapeless/Lens<TS;TB;>;)Lshapeless/ProductPrismBuilder<TS;Lscala/Tuple2<Lscala/Tuple2<TA;TB;>;TB;>;>;
    MethodParameters:
      Name                           Flags
      other                          final

  public <B extends java.lang.Object> shapeless.ProductPrismBuilder<S, scala.Tuple2<scala.Tuple2<A, B>, B>> $tilde(shapeless.Prism<S, B>);
    descriptor: (Lshapeless/Prism;)Lshapeless/ProductPrismBuilder;
    flags: (0x0001) ACC_PUBLIC
    Code:
      stack=2, locals=2, args_size=2
         0: aload_0
         1: aload_1
         2: invokestatic  #116                // InterfaceMethod shapeless/Prism.$tilde$:(Lshapeless/Prism;Lshapeless/Prism;)Lshapeless/ProductPrismBuilder;
         5: areturn
      LineNumberTable:
        line 97: 0
      LocalVariableTable:
        Start  Length  Slot  Name   Signature
            0       6     0  this   Lshapeless/Prism$$anon$8;
            0       6     1 other   Lshapeless/Prism;
    Signature: #113                         // <B:Ljava/lang/Object;>(Lshapeless/Prism<TS;TB;>;)Lshapeless/ProductPrismBuilder<TS;Lscala/Tuple2<Lscala/Tuple2<TA;TB;>;TB;>;>;
    MethodParameters:
      Name                           Flags
      other                          final

  public <B extends java.lang.Object> java.lang.Object selectDynamic(java.lang.String, shapeless.MkSelectDynamicOptic<shapeless.Prism<S, scala.Tuple2<A, B>>, scala.Tuple2<A, B>, scala.Symbol, B>, scala.DummyImplicit);
    descriptor: (Ljava/lang/String;Lshapeless/MkSelectDynamicOptic;Lscala/DummyImplicit;)Ljava/lang/Object;
    flags: (0x0001) ACC_PUBLIC
    Code:
      stack=4, locals=4, args_size=4
         0: aload_0
         1: aload_1
         2: aload_2
         3: aload_3
         4: invokestatic  #124                // InterfaceMethod shapeless/LPPrism.selectDynamic$:(Lshapeless/LPPrism;Ljava/lang/String;Lshapeless/MkSelectDynamicOptic;Lscala/DummyImplicit;)Ljava/lang/Object;
         7: areturn
      LineNumberTable:
        line 97: 0
      LocalVariableTable:
        Start  Length  Slot  Name   Signature
            0       8     0  this   Lshapeless/Prism$$anon$8;
            0       8     1     k   Ljava/lang/String;
            0       8     2 mkPrism   Lshapeless/MkSelectDynamicOptic;
            0       8     3 dummy   Lscala/DummyImplicit;
    Signature: #118                         // <B:Ljava/lang/Object;>(Ljava/lang/String;Lshapeless/MkSelectDynamicOptic<Lshapeless/Prism<TS;Lscala/Tuple2<TA;TB;>;>;Lscala/Tuple2<TA;TB;>;Lscala/Symbol;TB;>;Lscala/DummyImplicit;)Ljava/lang/Object;
    MethodParameters:
      Name                           Flags
      k                              final
      mkPrism                        final
      dummy                          final

  public scala.Option<scala.Tuple2<A, B>> get(S);
    descriptor: (Ljava/lang/Object;)Lscala/Option;
    flags: (0x0001) ACC_PUBLIC
    Code:
      stack=3, locals=2, args_size=2
         0: aload_0
         1: getfield      #128                // Field $outer:Lshapeless/Prism;
         4: aload_1
         5: invokeinterface #130,  2          // InterfaceMethod shapeless/Prism.get:(Ljava/lang/Object;)Lscala/Option;
        10: aload_0
        11: aload_1
        12: invokedynamic #150,  0            // InvokeDynamic #0:apply:(Lshapeless/Prism$$anon$8;Ljava/lang/Object;)Lscala/Function1;
        17: invokevirtual #156                // Method scala/Option.flatMap:(Lscala/Function1;)Lscala/Option;
        20: areturn
      LineNumberTable:
        line 100: 0
      LocalVariableTable:
        Start  Length  Slot  Name   Signature
            0      21     0  this   Lshapeless/Prism$$anon$8;
            0      21     1     s   Ljava/lang/Object;
    Signature: #103                         // (TS;)Lscala/Option<Lscala/Tuple2<TA;TB;>;>;
    MethodParameters:
      Name                           Flags
      s                              final

  public S set(S, scala.Tuple2<A, B>);
    descriptor: (Ljava/lang/Object;Lscala/Tuple2;)Ljava/lang/Object;
    flags: (0x0001) ACC_PUBLIC
    Code:
      stack=4, locals=3, args_size=3
         0: aload_0
         1: getfield      #162                // Field other$4:Lshapeless/Prism;
         4: aload_0
         5: getfield      #128                // Field $outer:Lshapeless/Prism;
         8: aload_1
         9: aload_2
        10: invokevirtual #168                // Method scala/Tuple2._1:()Ljava/lang/Object;
        13: invokeinterface #171,  3          // InterfaceMethod shapeless/Prism.set:(Ljava/lang/Object;Ljava/lang/Object;)Ljava/lang/Object;
        18: aload_2
        19: invokevirtual #174                // Method scala/Tuple2._2:()Ljava/lang/Object;
        22: invokeinterface #171,  3          // InterfaceMethod shapeless/Prism.set:(Ljava/lang/Object;Ljava/lang/Object;)Ljava/lang/Object;
        27: areturn
      LineNumberTable:
        line 104: 0
      LocalVariableTable:
        Start  Length  Slot  Name   Signature
            0      28     0  this   Lshapeless/Prism$$anon$8;
            0      28     1     s   Ljava/lang/Object;
            0      28     2    ab   Lscala/Tuple2;
    Signature: #159                         // (TS;Lscala/Tuple2<TA;TB;>;)TS;
    MethodParameters:
      Name                           Flags
      s                              final
      ab                             final

  public java.lang.Object set(java.lang.Object, java.lang.Object);
    descriptor: (Ljava/lang/Object;Ljava/lang/Object;)Ljava/lang/Object;
    flags: (0x1041) ACC_PUBLIC, ACC_BRIDGE, ACC_SYNTHETIC
    Code:
      stack=3, locals=3, args_size=3
         0: aload_0
         1: aload_1
         2: aload_2
         3: checkcast     #164                // class scala/Tuple2
         6: invokevirtual #178                // Method set:(Ljava/lang/Object;Lscala/Tuple2;)Ljava/lang/Object;
         9: areturn
      LineNumberTable:
        line 97: 0
      LocalVariableTable:
        Start  Length  Slot  Name   Signature
            0      10     0  this   Lshapeless/Prism$$anon$8;
            0      10     1     s   Ljava/lang/Object;
            0      10     2     a   Ljava/lang/Object;
    MethodParameters:
      Name                           Flags
      s                              final
      a                              final

  public static final scala.Tuple2 $anonfun$get$6(java.lang.Object, java.lang.Object);
    descriptor: (Ljava/lang/Object;Ljava/lang/Object;)Lscala/Tuple2;
    flags: (0x1019) ACC_PUBLIC, ACC_STATIC, ACC_FINAL, ACC_SYNTHETIC
    Code:
      stack=4, locals=2, args_size=2
         0: new           #164                // class scala/Tuple2
         3: dup
         4: aload_0
         5: aload_1
         6: invokespecial #186                // Method scala/Tuple2."<init>":(Ljava/lang/Object;Ljava/lang/Object;)V
         9: areturn
      LineNumberTable:
        line 102: 0
      LocalVariableTable:
        Start  Length  Slot  Name   Signature
            0      10     0 fst$1   Ljava/lang/Object;
            0      10     1   snd   Ljava/lang/Object;
    MethodParameters:
      Name                           Flags
      fst$1                          final
      snd                            final

  public static final scala.Option $anonfun$get$5(shapeless.Prism$$anon$8, java.lang.Object, java.lang.Object);
    descriptor: (Lshapeless/Prism$$anon$8;Ljava/lang/Object;Ljava/lang/Object;)Lscala/Option;
    flags: (0x1019) ACC_PUBLIC, ACC_STATIC, ACC_FINAL, ACC_SYNTHETIC
    Code:
      stack=2, locals=3, args_size=3
         0: aload_0
         1: getfield      #162                // Field other$4:Lshapeless/Prism;
         4: aload_1
         5: invokeinterface #130,  2          // InterfaceMethod shapeless/Prism.get:(Ljava/lang/Object;)Lscala/Option;
        10: aload_2
        11: invokedynamic #197,  0            // InvokeDynamic #1:apply:(Ljava/lang/Object;)Lscala/Function1;
        16: invokevirtual #200                // Method scala/Option.map:(Lscala/Function1;)Lscala/Option;
        19: areturn
      LineNumberTable:
        line 101: 0
      LocalVariableTable:
        Start  Length  Slot  Name   Signature
            0      20     0 $this   Lshapeless/Prism$$anon$8;
            0      20     1   s$4   Ljava/lang/Object;
            0      20     2   fst   Ljava/lang/Object;
    MethodParameters:
      Name                           Flags
      $this                          final synthetic
      s$4                            final
      fst                            final

  public shapeless.Prism$$anon$8(shapeless.Prism, shapeless.Prism);
    descriptor: (Lshapeless/Prism;Lshapeless/Prism;)V
    flags: (0x0001) ACC_PUBLIC
    Code:
      stack=2, locals=3, args_size=3
         0: aload_1
         1: ifnonnull     6
         4: aconst_null
         5: athrow
         6: aload_0
         7: aload_1
         8: putfield      #128                // Field $outer:Lshapeless/Prism;
        11: aload_0
        12: aload_2
        13: putfield      #162                // Field other$4:Lshapeless/Prism;
        16: aload_0
        17: invokespecial #204                // Method java/lang/Object."<init>":()V
        20: aload_0
        21: invokestatic  #208                // InterfaceMethod shapeless/LPPrism.$init$:(Lshapeless/LPPrism;)V
        24: aload_0
        25: invokestatic  #211                // InterfaceMethod shapeless/Prism.$init$:(Lshapeless/Prism;)V
        28: aload_0
        29: invokestatic  #214                // InterfaceMethod shapeless/ProductPrismBuilder.$init$:(Lshapeless/ProductPrismBuilder;)V
        32: return
      StackMapTable: number_of_entries = 1
        frame_type = 6 /* same */
      LineNumberTable:
        line 97: 0
      LocalVariableTable:
        Start  Length  Slot  Name   Signature
            0      33     0  this   Lshapeless/Prism$$anon$8;
            0      33     1 $outer   Lshapeless/Prism;
            0      33     2 other$4   Lshapeless/Prism;
    MethodParameters:
      Name                           Flags
      $outer                         final synthetic
      other$4                        final

  private static java.lang.Object $deserializeLambda$(java.lang.invoke.SerializedLambda);
    descriptor: (Ljava/lang/invoke/SerializedLambda;)Ljava/lang/Object;
    flags: (0x100a) ACC_PRIVATE, ACC_STATIC, ACC_SYNTHETIC
    Code:
      stack=1, locals=1, args_size=1
         0: aload_0
         1: invokedynamic #226,  0            // InvokeDynamic #2:lambdaDeserialize:(Ljava/lang/invoke/SerializedLambda;)Ljava/lang/Object;
         6: areturn
}
InnerClasses:
  public static final #18= #15 of #17;    // Lookup=class java/lang/invoke/MethodHandles$Lookup of class java/lang/invoke/MethodHandles
  public final #2;                        // class shapeless/Prism$$anon$8
  public static #23= #20 of #22;          // Init=class shapeless/ops/hlist$Init of class shapeless/ops/hlist
  public static #26= #25 of #22;          // Last=class shapeless/ops/hlist$Last of class shapeless/ops/hlist
  public static #29= #28 of #22;          // Prepend=class shapeless/ops/hlist$Prepend of class shapeless/ops/hlist
  public static #32= #31 of #22;          // Tupler=class shapeless/ops/hlist$Tupler of class shapeless/ops/hlist
EnclosingMethod: #10.#13                // shapeless.Prism.$tilde
Signature: #3                           // Ljava/lang/Object;Lshapeless/ProductPrismBuilder<TS;Lscala/Tuple2<TA;TB;>;>;
SourceFile: "lenses.scala"
BootstrapMethods:
  0: #147 REF_invokeStatic java/lang/invoke/LambdaMetafactory.altMetafactory:(Ljava/lang/invoke/MethodHandles$Lookup;Ljava/lang/String;Ljava/lang/invoke/MethodType;[Ljava/lang/Object;)Ljava/lang/invoke/CallSite;
    Method arguments:
      #132 (Ljava/lang/Object;)Ljava/lang/Object;
      #137 REF_invokeStatic shapeless/Prism$$anon$8.$anonfun$get$5:(Lshapeless/Prism$$anon$8;Ljava/lang/Object;Ljava/lang/Object;)Lscala/Option;
      #138 (Ljava/lang/Object;)Lscala/Option;
      #139 5
      #140 1
      #138 (Ljava/lang/Object;)Lscala/Option;
  1: #147 REF_invokeStatic java/lang/invoke/LambdaMetafactory.altMetafactory:(Ljava/lang/invoke/MethodHandles$Lookup;Ljava/lang/String;Ljava/lang/invoke/MethodType;[Ljava/lang/Object;)Ljava/lang/invoke/CallSite;
    Method arguments:
      #132 (Ljava/lang/Object;)Ljava/lang/Object;
      #192 REF_invokeStatic shapeless/Prism$$anon$8.$anonfun$get$6:(Ljava/lang/Object;Ljava/lang/Object;)Lscala/Tuple2;
      #194 (Ljava/lang/Object;)Lscala/Tuple2;
      #139 5
      #140 1
      #194 (Ljava/lang/Object;)Lscala/Tuple2;
  2: #223 REF_invokeStatic scala/runtime/LambdaDeserialize.bootstrap:(Ljava/lang/invoke/MethodHandles$Lookup;Ljava/lang/String;Ljava/lang/invoke/MethodType;[Ljava/lang/invoke/MethodHandle;)Ljava/lang/invoke/CallSite;
    Method arguments:
      #137 REF_invokeStatic shapeless/Prism$$anon$8.$anonfun$get$5:(Lshapeless/Prism$$anon$8;Ljava/lang/Object;Ljava/lang/Object;)Lscala/Option;
      #192 REF_invokeStatic shapeless/Prism$$anon$8.$anonfun$get$6:(Ljava/lang/Object;Ljava/lang/Object;)Lscala/Tuple2;
  ScalaInlineInfo: length = 0x54 (unknown attribute)
   01 01 00 10 00 85 00 86 01 00 B3 00 B4 01 00 0B
   00 6C 01 00 0B 00 0C 01 00 0B 00 24 01 00 B7 00
   C9 01 00 5D 00 5E 01 00 44 00 45 01 00 44 00 4D
   01 00 7E 00 66 01 00 39 00 3A 01 00 52 00 53 01
   00 52 00 75 01 00 9D 00 A9 01 00 9D 00 9E 01 00
   65 00 66 01
  Scala: length = 0x0 (unknown attribute)

