Classfile /Users/mw/Projects/slang-braindump/.jar/jar11/assemble/slang-braindump/assemble/content/shapeless/Prism.class
  Last modified May 29, 2022; size 7302 bytes
  SHA-256 checksum 35de02fb234ba3f7814c7ff4ffee1ce3016afa2b9e38651bb9b341586b63b4f8
  Compiled from "lenses.scala"
public interface shapeless.Prism<S extends java.lang.Object, A extends java.lang.Object> extends shapeless.LPPrism<S, A>
  minor version: 0
  major version: 52
  flags: (0x0601) ACC_PUBLIC, ACC_INTERFACE, ACC_ABSTRACT
  this_class: #2                          // shapeless/Prism
  super_class: #5                         // java/lang/Object
  interfaces: 1, fields: 0, methods: 22, attributes: 7
Constant pool:
    #1 = Utf8               shapeless/Prism
    #2 = Class              #1            // shapeless/Prism
    #3 = Utf8               <S:Ljava/lang/Object;A:Ljava/lang/Object;>Ljava/lang/Object;Lshapeless/LPPrism<TS;TA;>;
    #4 = Utf8               java/lang/Object
    #5 = Class              #4            // java/lang/Object
    #6 = Utf8               shapeless/LPPrism
    #7 = Class              #6            // shapeless/LPPrism
    #8 = Utf8               lenses.scala
    #9 = Utf8               Lscala/reflect/ScalaSignature;
   #10 = Utf8               bytes
   #11 = Utf8               \u0006\u0005\u0005Uca\u0002\u0007\u000e!\u0003\r\t\u0001\u0005\u0005\u0006U\u0001!\ta\u000b\u0005\u0006_\u00011\t\u0001\r\u0005\u0006m\u00011\ta\u000e\u0005\u0006y\u0001!\t!\u0010\u0005\u0006\u000b\u0002!\tA\u0012\u0005\u0006\u000b\u0002!\t\u0001\u0016\u0005\u0006;\u0002!\tA\u0018\u0005\b\u0003\u000b\u0001A\u0011AA\u0004\u0011\u001d\tY\u0002\u0001C\u0001\u0003;Aq!!\t\u0001\t\u0003\t\u0019\u0003C\u0004\u0002\"\u0001!\t!!\u0011\u0003\u000bA\u0013\u0018n]7\u000b\u00039\t\u0011b\u001d5ba\u0016dWm]:\u0004\u0001U\u0019\u0011C\b\u0015\u0014\u0007\u0001\u0011\u0002\u0004\u0005\u0002\u0014-5\tACC\u0001\u0016\u0003\u0015\u00198-\u00197b\u0013\t9BC\u0001\u0004B]f\u0014VM\u001a\t\u00053iar%D\u0001\u000e\u0013\tYRBA\u0004M!B\u0013\u0018n]7\u0011\u0005uqB\u0002\u0001\u0003\u0006?\u0001\u0011\r\u0001\t\u0002\u0002\'F\u0011\u0011\u0005\n\t\u0003\'\tJ!a\t\u000b\u0003\u000f9{G\u000f[5oOB\u00111#J\u0005\u0003MQ\u00111!\u00118z!\ti\u0002\u0006B\u0003*\u0001\t\u0007\u0001EA\u0001B\u0003\u0019!\u0013N\\5uIQ\tA\u0006\u0005\u0002\u0014[%\u0011a\u0006\u0006\u0002\u0005+:LG/A\u0002hKR$\"!\r\u001b\u0011\u0007M\u0011t%\u0003\u00024)\t1q\n\u001d;j_:DQ!\u000e\u0002A\u0002q\t\u0011a]\u0001\u0004g\u0016$HC\u0001\u001d<)\ta\u0012\bC\u0003;\u0007\u0001\u0007q%A\u0001b\u0011\u0015)4\u00011\u0001\u001d\u0003\u0019iw\u000eZ5gsR\u0011a\b\u0012\u000b\u00039}BQ\u0001\u0011\u0003A\u0002\u0005\u000b\u0011A\u001a\t\u0005\'\t;s%\u0003\u0002D)\tIa)\u001e8di&|g.\r\u0005\u0006k\u0011\u0001\r\u0001H\u0001\bG>l\u0007o\\:f+\t9U\n\u0006\u0002I\u001fJ\u0019\u0011JE&\u0007\t)+\u0001\u0001\u0013\u0002\ryI,g-\u001b8f[\u0016tGO\u0010\t\u00053\u0001au\u0005\u0005\u0002\u001e\u001b\u0012)a*\u0002b\u0001A\t\tA\u000bC\u0003Q\u000b\u0001\u0007\u0011+A\u0001h!\u0011I\"\u000b\u0014\u000f\n\u0005Mk!\u0001\u0002\'f]N,\"!\u0016.\u0015\u0005Y[&cA,\u00131\u001a!!J\u0002\u0001W!\u0011I\u0002!W\u0014\u0011\u0005uQF!\u0002(\u0007\u0005\u0004\u0001\u0003\"\u0002)\u0007\u0001\u0004a\u0006\u0003B\r\u00013r\tQb]3mK\u000e$H)\u001f8b[&\u001cGCA0t)\t\u0001\'\rE\u0002b\u0003\u0003q!!\b2\t\u000b\r<\u00019\u00013\u0002\u000f5\\\u0007K]5t[B1\u0011$Z4(Q\u0006J!AZ\u0007\u0003)5[7+\u001a7fGR$\u0015P\\1nS\u000e|\u0005\u000f^5d!\u0011I\u0002\u0001H\u0014\u0011\t%dwN\u001d\b\u00033)L!a[\u0007\u0002\u0007Q\fw-\u0003\u0002n]\n1A%\u0019;%CRT!a[\u0007\u0011\u0005M\u0001\u0018BA9\u0015\u0005\u0019\u0019\u00160\u001c2pY:\u0011Qd\u001d\u0005\u0006i\u001e\u0001\r!^\u0001\u0002WB\u0011a/ \b\u0003on\u0004\"\u0001\u001f\u000b\u000e\u0003eT!A_\b\u0002\rq\u0012xn\u001c;?\u0013\taH#\u0001\u0004Qe\u0016$WMZ\u0005\u0003}~\u0014aa\u0015;sS:<\'B\u0001?\u0015\u0013\r\t\u0019!\u001a\u0002\u0004\u001fV$\u0018!B1qa2LX\u0003BA\u0005\u0003\u001f!B!a\u0003\u0002\u0014A)\u0011\u0004\u0001\u000f\u0002\u000eA\u0019Q$a\u0004\u0005\r\u0005E\u0001B1\u0001!\u0005\u0005\u0011\u0005BB2\t\u0001\b\t)\u0002\u0005\u0004\u001a\u0003/9\u0013QB\u0005\u0004\u00033i!aC\'l\u0007R|\'\u000f\u0015:jg6\fq!\u001e8baBd\u0017\u0010F\u00022\u0003?AQ!N\u0005A\u0002q\ta\u0001\n;jY\u0012,W\u0003BA\u0013\u0003s!B!a\n\u0002<I)\u0011\u0011\u0006\n\u0002,\u0019)!J\u0003\u0001\u0002(A1\u0011$!\f\u001d\u0003cI1!a\f\u000e\u0005M\u0001&o\u001c3vGR\u0004&/[:n\u0005VLG\u000eZ3s!\u0019\u0019\u00121G\u0014\u00028%\u0019\u0011Q\u0007\u000b\u0003\rQ+\b\u000f\\33!\ri\u0012\u0011\b\u0003\u0007\u0003#Q!\u0019\u0001\u0011\t\u000f\u0005u\"\u00021\u0001\u0002@\u0005)q\u000e\u001e5feB)\u0011D\u0015\u000f\u00028U!\u00111IA()\u0011\t)%!\u0015\u0013\u000b\u0005\u001d##!\u0013\u0007\u000b)[\u0001!!\u0012\u0011\re\ti\u0003HA&!\u0019\u0019\u00121G\u0014\u0002NA\u0019Q$a\u0014\u0005\r\u0005E1B1\u0001!\u0011\u001d\tid\u0003a\u0001\u0003\'\u0002R!\u0007\u0001\u001d\u0003\u001b\u0002
   #12 = Utf8               java/lang/invoke/MethodHandles$Lookup
   #13 = Class              #12           // java/lang/invoke/MethodHandles$Lookup
   #14 = Utf8               java/lang/invoke/MethodHandles
   #15 = Class              #14           // java/lang/invoke/MethodHandles
   #16 = Utf8               Lookup
   #17 = Utf8               shapeless/Prism$$anon$5
   #18 = Class              #17           // shapeless/Prism$$anon$5
   #19 = Utf8               shapeless/Prism$$anon$6
   #20 = Class              #19           // shapeless/Prism$$anon$6
   #21 = Utf8               shapeless/Prism$$anon$7
   #22 = Class              #21           // shapeless/Prism$$anon$7
   #23 = Utf8               shapeless/Prism$$anon$8
   #24 = Class              #23           // shapeless/Prism$$anon$8
   #25 = Utf8               get
   #26 = Utf8               (Ljava/lang/Object;)Lscala/Option;
   #27 = Utf8               (TS;)Lscala/Option<TA;>;
   #28 = Utf8               s
   #29 = Utf8               set
   #30 = Utf8               (Ljava/lang/Object;Ljava/lang/Object;)Ljava/lang/Object;
   #31 = Utf8               (TS;TA;)TS;
   #32 = Utf8               a
   #33 = Utf8               modify$
   #34 = Utf8               (Lshapeless/Prism;Ljava/lang/Object;Lscala/Function1;)Ljava/lang/Object;
   #35 = Utf8               $this
   #36 = Utf8               f
   #37 = Utf8               modify
   #38 = Utf8               (Ljava/lang/Object;Lscala/Function1;)Ljava/lang/Object;
   #39 = NameAndType        #37:#38       // modify:(Ljava/lang/Object;Lscala/Function1;)Ljava/lang/Object;
   #40 = InterfaceMethodref #2.#39        // shapeless/Prism.modify:(Ljava/lang/Object;Lscala/Function1;)Ljava/lang/Object;
   #41 = Utf8               Lshapeless/Prism;
   #42 = Utf8               Ljava/lang/Object;
   #43 = Utf8               Lscala/Function1;
   #44 = Utf8               (TS;Lscala/Function1<TA;TA;>;)TS;
   #45 = NameAndType        #25:#26       // get:(Ljava/lang/Object;)Lscala/Option;
   #46 = InterfaceMethodref #2.#45        // shapeless/Prism.get:(Ljava/lang/Object;)Lscala/Option;
   #47 = Utf8               scala/Option
   #48 = Class              #47           // scala/Option
   #49 = Utf8               map
   #50 = Utf8               (Lscala/Function1;)Lscala/Option;
   #51 = NameAndType        #49:#50       // map:(Lscala/Function1;)Lscala/Option;
   #52 = Methodref          #48.#51       // scala/Option.map:(Lscala/Function1;)Lscala/Option;
   #53 = Utf8               (Ljava/lang/Object;)Ljava/lang/Object;
   #54 = MethodType         #53           //  (Ljava/lang/Object;)Ljava/lang/Object;
   #55 = Utf8               $anonfun$modify$1
   #56 = Utf8               (Lshapeless/Prism;Ljava/lang/Object;Ljava/lang/Object;)Ljava/lang/Object;
   #57 = NameAndType        #55:#56       // $anonfun$modify$1:(Lshapeless/Prism;Ljava/lang/Object;Ljava/lang/Object;)Ljava/lang/Object;
   #58 = InterfaceMethodref #2.#57        // shapeless/Prism.$anonfun$modify$1:(Lshapeless/Prism;Ljava/lang/Object;Ljava/lang/Object;)Ljava/lang/Object;
   #59 = MethodHandle       6:#58         // REF_invokeStatic shapeless/Prism.$anonfun$modify$1:(Lshapeless/Prism;Ljava/lang/Object;Ljava/lang/Object;)Ljava/lang/Object;
   #60 = Integer            1
   #61 = Utf8               java/lang/invoke/LambdaMetafactory
   #62 = Class              #61           // java/lang/invoke/LambdaMetafactory
   #63 = Utf8               altMetafactory
   #64 = Utf8               (Ljava/lang/invoke/MethodHandles$Lookup;Ljava/lang/String;Ljava/lang/invoke/MethodType;[Ljava/lang/Object;)Ljava/lang/invoke/CallSite;
   #65 = NameAndType        #63:#64       // altMetafactory:(Ljava/lang/invoke/MethodHandles$Lookup;Ljava/lang/String;Ljava/lang/invoke/MethodType;[Ljava/lang/Object;)Ljava/lang/invoke/CallSite;
   #66 = Methodref          #62.#65       // java/lang/invoke/LambdaMetafactory.altMetafactory:(Ljava/lang/invoke/MethodHandles$Lookup;Ljava/lang/String;Ljava/lang/invoke/MethodType;[Ljava/lang/Object;)Ljava/lang/invoke/CallSite;
   #67 = MethodHandle       6:#66         // REF_invokeStatic java/lang/invoke/LambdaMetafactory.altMetafactory:(Ljava/lang/invoke/MethodHandles$Lookup;Ljava/lang/String;Ljava/lang/invoke/MethodType;[Ljava/lang/Object;)Ljava/lang/invoke/CallSite;
   #68 = Utf8               apply
   #69 = Utf8               (Lshapeless/Prism;Ljava/lang/Object;)Lscala/Function1;
   #70 = NameAndType        #68:#69       // apply:(Lshapeless/Prism;Ljava/lang/Object;)Lscala/Function1;
   #71 = InvokeDynamic      #0:#70        // #0:apply:(Lshapeless/Prism;Ljava/lang/Object;)Lscala/Function1;
   #72 = Utf8               ()Ljava/lang/Object;
   #73 = MethodType         #72           //  ()Ljava/lang/Object;
   #74 = Utf8               $anonfun$modify$2
   #75 = NameAndType        #74:#53       // $anonfun$modify$2:(Ljava/lang/Object;)Ljava/lang/Object;
   #76 = InterfaceMethodref #2.#75        // shapeless/Prism.$anonfun$modify$2:(Ljava/lang/Object;)Ljava/lang/Object;
   #77 = MethodHandle       6:#76         // REF_invokeStatic shapeless/Prism.$anonfun$modify$2:(Ljava/lang/Object;)Ljava/lang/Object;
   #78 = Utf8               (Ljava/lang/Object;)Lscala/Function0;
   #79 = NameAndType        #68:#78       // apply:(Ljava/lang/Object;)Lscala/Function0;
   #80 = InvokeDynamic      #1:#79        // #1:apply:(Ljava/lang/Object;)Lscala/Function0;
   #81 = Utf8               getOrElse
   #82 = Utf8               (Lscala/Function0;)Ljava/lang/Object;
   #83 = NameAndType        #81:#82       // getOrElse:(Lscala/Function0;)Ljava/lang/Object;
   #84 = Methodref          #48.#83       // scala/Option.getOrElse:(Lscala/Function0;)Ljava/lang/Object;
   #85 = Utf8               this
   #86 = Utf8               compose$
   #87 = Utf8               (Lshapeless/Prism;Lshapeless/Lens;)Lshapeless/Prism;
   #88 = Utf8               g
   #89 = Utf8               compose
   #90 = Utf8               (Lshapeless/Lens;)Lshapeless/Prism;
   #91 = NameAndType        #89:#90       // compose:(Lshapeless/Lens;)Lshapeless/Prism;
   #92 = InterfaceMethodref #2.#91        // shapeless/Prism.compose:(Lshapeless/Lens;)Lshapeless/Prism;
   #93 = Utf8               Lshapeless/Lens;
   #94 = Utf8               <T:Ljava/lang/Object;>(Lshapeless/Lens<TT;TS;>;)Lshapeless/Prism<TT;TA;>;
   #95 = Utf8               <init>
   #96 = Utf8               (Lshapeless/Prism;Lshapeless/Lens;)V
   #97 = NameAndType        #95:#96       // "<init>":(Lshapeless/Prism;Lshapeless/Lens;)V
   #98 = Methodref          #18.#97       // shapeless/Prism$$anon$5."<init>":(Lshapeless/Prism;Lshapeless/Lens;)V
   #99 = Utf8               (Lshapeless/Prism;Lshapeless/Prism;)Lshapeless/Prism;
  #100 = Utf8               (Lshapeless/Prism;)Lshapeless/Prism;
  #101 = NameAndType        #89:#100      // compose:(Lshapeless/Prism;)Lshapeless/Prism;
  #102 = InterfaceMethodref #2.#101       // shapeless/Prism.compose:(Lshapeless/Prism;)Lshapeless/Prism;
  #103 = Utf8               <T:Ljava/lang/Object;>(Lshapeless/Prism<TT;TS;>;)Lshapeless/Prism<TT;TA;>;
  #104 = Utf8               (Lshapeless/Prism;Lshapeless/Prism;)V
  #105 = NameAndType        #95:#104      // "<init>":(Lshapeless/Prism;Lshapeless/Prism;)V
  #106 = Methodref          #20.#105      // shapeless/Prism$$anon$6."<init>":(Lshapeless/Prism;Lshapeless/Prism;)V
  #107 = Utf8               selectDynamic$
  #108 = Utf8               (Lshapeless/Prism;Ljava/lang/String;Lshapeless/MkSelectDynamicOptic;)Ljava/lang/Object;
  #109 = Utf8               k
  #110 = Utf8               mkPrism
  #111 = Utf8               selectDynamic
  #112 = Utf8               (Ljava/lang/String;Lshapeless/MkSelectDynamicOptic;)Ljava/lang/Object;
  #113 = NameAndType        #111:#112     // selectDynamic:(Ljava/lang/String;Lshapeless/MkSelectDynamicOptic;)Ljava/lang/Object;
  #114 = InterfaceMethodref #2.#113       // shapeless/Prism.selectDynamic:(Ljava/lang/String;Lshapeless/MkSelectDynamicOptic;)Ljava/lang/Object;
  #115 = Utf8               Ljava/lang/String;
  #116 = Utf8               Lshapeless/MkSelectDynamicOptic;
  #117 = Utf8               (Ljava/lang/String;Lshapeless/MkSelectDynamicOptic<Lshapeless/Prism<TS;TA;>;TA;Lscala/Symbol;Lscala/runtime/Nothing$;>;)Ljava/lang/Object;
  #118 = Utf8               shapeless/MkSelectDynamicOptic
  #119 = Class              #118          // shapeless/MkSelectDynamicOptic
  #120 = NameAndType        #68:#53       // apply:(Ljava/lang/Object;)Ljava/lang/Object;
  #121 = InterfaceMethodref #119.#120     // shapeless/MkSelectDynamicOptic.apply:(Ljava/lang/Object;)Ljava/lang/Object;
  #122 = Utf8               apply$
  #123 = Utf8               (Lshapeless/Prism;Lshapeless/MkCtorPrism;)Lshapeless/Prism;
  #124 = Utf8               (Lshapeless/MkCtorPrism;)Lshapeless/Prism;
  #125 = NameAndType        #68:#124      // apply:(Lshapeless/MkCtorPrism;)Lshapeless/Prism;
  #126 = InterfaceMethodref #2.#125       // shapeless/Prism.apply:(Lshapeless/MkCtorPrism;)Lshapeless/Prism;
  #127 = Utf8               Lshapeless/MkCtorPrism;
  #128 = Utf8               <B:Ljava/lang/Object;>(Lshapeless/MkCtorPrism<TA;TB;>;)Lshapeless/Prism<TS;TB;>;
  #129 = Utf8               shapeless/MkCtorPrism
  #130 = Class              #129          // shapeless/MkCtorPrism
  #131 = Utf8               ()Lshapeless/Prism;
  #132 = NameAndType        #68:#131      // apply:()Lshapeless/Prism;
  #133 = InterfaceMethodref #130.#132     // shapeless/MkCtorPrism.apply:()Lshapeless/Prism;
  #134 = Utf8               unapply$
  #135 = Utf8               (Lshapeless/Prism;Ljava/lang/Object;)Lscala/Option;
  #136 = Utf8               unapply
  #137 = NameAndType        #136:#26      // unapply:(Ljava/lang/Object;)Lscala/Option;
  #138 = InterfaceMethodref #2.#137       // shapeless/Prism.unapply:(Ljava/lang/Object;)Lscala/Option;
  #139 = Utf8               $tilde$
  #140 = Utf8               (Lshapeless/Prism;Lshapeless/Lens;)Lshapeless/ProductPrismBuilder;
  #141 = Utf8               other
  #142 = Utf8               $tilde
  #143 = Utf8               (Lshapeless/Lens;)Lshapeless/ProductPrismBuilder;
  #144 = NameAndType        #142:#143     // $tilde:(Lshapeless/Lens;)Lshapeless/ProductPrismBuilder;
  #145 = InterfaceMethodref #2.#144       // shapeless/Prism.$tilde:(Lshapeless/Lens;)Lshapeless/ProductPrismBuilder;
  #146 = Utf8               <B:Ljava/lang/Object;>(Lshapeless/Lens<TS;TB;>;)Lshapeless/ProductPrismBuilder<TS;Lscala/Tuple2<TA;TB;>;>;
  #147 = Methodref          #22.#97       // shapeless/Prism$$anon$7."<init>":(Lshapeless/Prism;Lshapeless/Lens;)V
  #148 = Utf8               (Lshapeless/Prism;Lshapeless/Prism;)Lshapeless/ProductPrismBuilder;
  #149 = Utf8               (Lshapeless/Prism;)Lshapeless/ProductPrismBuilder;
  #150 = NameAndType        #142:#149     // $tilde:(Lshapeless/Prism;)Lshapeless/ProductPrismBuilder;
  #151 = InterfaceMethodref #2.#150       // shapeless/Prism.$tilde:(Lshapeless/Prism;)Lshapeless/ProductPrismBuilder;
  #152 = Utf8               <B:Ljava/lang/Object;>(Lshapeless/Prism<TS;TB;>;)Lshapeless/ProductPrismBuilder<TS;Lscala/Tuple2<TA;TB;>;>;
  #153 = Methodref          #24.#105      // shapeless/Prism$$anon$8."<init>":(Lshapeless/Prism;Lshapeless/Prism;)V
  #154 = Utf8               s$2
  #155 = NameAndType        #29:#30       // set:(Ljava/lang/Object;Ljava/lang/Object;)Ljava/lang/Object;
  #156 = InterfaceMethodref #2.#155       // shapeless/Prism.set:(Ljava/lang/Object;Ljava/lang/Object;)Ljava/lang/Object;
  #157 = Utf8               $init$
  #158 = Utf8               (Lshapeless/Prism;)V
  #159 = Utf8               $deserializeLambda$
  #160 = Utf8               (Ljava/lang/invoke/SerializedLambda;)Ljava/lang/Object;
  #161 = Utf8               scala/runtime/LambdaDeserialize
  #162 = Class              #161          // scala/runtime/LambdaDeserialize
  #163 = Utf8               bootstrap
  #164 = Utf8               (Ljava/lang/invoke/MethodHandles$Lookup;Ljava/lang/String;Ljava/lang/invoke/MethodType;[Ljava/lang/invoke/MethodHandle;)Ljava/lang/invoke/CallSite;
  #165 = NameAndType        #163:#164     // bootstrap:(Ljava/lang/invoke/MethodHandles$Lookup;Ljava/lang/String;Ljava/lang/invoke/MethodType;[Ljava/lang/invoke/MethodHandle;)Ljava/lang/invoke/CallSite;
  #166 = Methodref          #162.#165     // scala/runtime/LambdaDeserialize.bootstrap:(Ljava/lang/invoke/MethodHandles$Lookup;Ljava/lang/String;Ljava/lang/invoke/MethodType;[Ljava/lang/invoke/MethodHandle;)Ljava/lang/invoke/CallSite;
  #167 = MethodHandle       6:#166        // REF_invokeStatic scala/runtime/LambdaDeserialize.bootstrap:(Ljava/lang/invoke/MethodHandles$Lookup;Ljava/lang/String;Ljava/lang/invoke/MethodType;[Ljava/lang/invoke/MethodHandle;)Ljava/lang/invoke/CallSite;
  #168 = Utf8               lambdaDeserialize
  #169 = NameAndType        #168:#160     // lambdaDeserialize:(Ljava/lang/invoke/SerializedLambda;)Ljava/lang/Object;
  #170 = InvokeDynamic      #2:#169       // #2:lambdaDeserialize:(Ljava/lang/invoke/SerializedLambda;)Ljava/lang/Object;
  #171 = Utf8               Signature
  #172 = Utf8               MethodParameters
  #173 = Utf8               Code
  #174 = Utf8               LineNumberTable
  #175 = Utf8               LocalVariableTable
  #176 = Utf8               InnerClasses
  #177 = Utf8               SourceFile
  #178 = Utf8               RuntimeVisibleAnnotations
  #179 = Utf8               BootstrapMethods
  #180 = Utf8               ScalaInlineInfo
  #181 = Utf8               ScalaSig
{
  public abstract scala.Option<A> get(S);
    descriptor: (Ljava/lang/Object;)Lscala/Option;
    flags: (0x0401) ACC_PUBLIC, ACC_ABSTRACT
    Signature: #27                          // (TS;)Lscala/Option<TA;>;
    MethodParameters:
      Name                           Flags
      s                              final

  public abstract S set(S, A);
    descriptor: (Ljava/lang/Object;Ljava/lang/Object;)Ljava/lang/Object;
    flags: (0x0401) ACC_PUBLIC, ACC_ABSTRACT
    Signature: #31                          // (TS;TA;)TS;
    MethodParameters:
      Name                           Flags
      s                              final
      a                              final

  public static java.lang.Object modify$(shapeless.Prism, java.lang.Object, scala.Function1);
    descriptor: (Lshapeless/Prism;Ljava/lang/Object;Lscala/Function1;)Ljava/lang/Object;
    flags: (0x1009) ACC_PUBLIC, ACC_STATIC, ACC_SYNTHETIC
    Code:
      stack=3, locals=3, args_size=3
         0: aload_0
         1: aload_1
         2: aload_2
         3: invokespecial #40                 // InterfaceMethod modify:(Ljava/lang/Object;Lscala/Function1;)Ljava/lang/Object;
         6: areturn
      LineNumberTable:
        line 72: 0
      LocalVariableTable:
        Start  Length  Slot  Name   Signature
            0       7     0 $this   Lshapeless/Prism;
            0       7     1     s   Ljava/lang/Object;
            0       7     2     f   Lscala/Function1;
    MethodParameters:
      Name                           Flags
      $this                          final synthetic
      s                              final
      f                              final

  public default S modify(S, scala.Function1<A, A>);
    descriptor: (Ljava/lang/Object;Lscala/Function1;)Ljava/lang/Object;
    flags: (0x0001) ACC_PUBLIC
    Code:
      stack=3, locals=3, args_size=3
         0: aload_0
         1: aload_1
         2: invokeinterface #46,  2           // InterfaceMethod get:(Ljava/lang/Object;)Lscala/Option;
         7: aload_2
         8: invokevirtual #52                 // Method scala/Option.map:(Lscala/Function1;)Lscala/Option;
        11: aload_0
        12: aload_1
        13: invokedynamic #71,  0             // InvokeDynamic #0:apply:(Lshapeless/Prism;Ljava/lang/Object;)Lscala/Function1;
        18: invokevirtual #52                 // Method scala/Option.map:(Lscala/Function1;)Lscala/Option;
        21: aload_1
        22: invokedynamic #80,  0             // InvokeDynamic #1:apply:(Ljava/lang/Object;)Lscala/Function0;
        27: invokevirtual #84                 // Method scala/Option.getOrElse:(Lscala/Function0;)Ljava/lang/Object;
        30: areturn
      LineNumberTable:
        line 72: 0
      LocalVariableTable:
        Start  Length  Slot  Name   Signature
            0      31     0  this   Lshapeless/Prism;
            0      31     1     s   Ljava/lang/Object;
            0      31     2     f   Lscala/Function1;
    Signature: #44                          // (TS;Lscala/Function1<TA;TA;>;)TS;
    MethodParameters:
      Name                           Flags
      s                              final
      f                              final

  public static shapeless.Prism compose$(shapeless.Prism, shapeless.Lens);
    descriptor: (Lshapeless/Prism;Lshapeless/Lens;)Lshapeless/Prism;
    flags: (0x1009) ACC_PUBLIC, ACC_STATIC, ACC_SYNTHETIC
    Code:
      stack=2, locals=2, args_size=2
         0: aload_0
         1: aload_1
         2: invokespecial #92                 // InterfaceMethod compose:(Lshapeless/Lens;)Lshapeless/Prism;
         5: areturn
      LineNumberTable:
        line 74: 0
      LocalVariableTable:
        Start  Length  Slot  Name   Signature
            0       6     0 $this   Lshapeless/Prism;
            0       6     1     g   Lshapeless/Lens;
    MethodParameters:
      Name                           Flags
      $this                          final synthetic
      g                              final

  public default <T extends java.lang.Object> shapeless.Prism<T, A> compose(shapeless.Lens<T, S>);
    descriptor: (Lshapeless/Lens;)Lshapeless/Prism;
    flags: (0x0001) ACC_PUBLIC
    Code:
      stack=4, locals=2, args_size=2
         0: new           #18                 // class shapeless/Prism$$anon$5
         3: dup
         4: aload_0
         5: aload_1
         6: invokespecial #98                 // Method shapeless/Prism$$anon$5."<init>":(Lshapeless/Prism;Lshapeless/Lens;)V
         9: areturn
      LineNumberTable:
        line 74: 0
      LocalVariableTable:
        Start  Length  Slot  Name   Signature
            0      10     0  this   Lshapeless/Prism;
            0      10     1     g   Lshapeless/Lens;
    Signature: #94                          // <T:Ljava/lang/Object;>(Lshapeless/Lens<TT;TS;>;)Lshapeless/Prism<TT;TA;>;
    MethodParameters:
      Name                           Flags
      g                              final

  public static shapeless.Prism compose$(shapeless.Prism, shapeless.Prism);
    descriptor: (Lshapeless/Prism;Lshapeless/Prism;)Lshapeless/Prism;
    flags: (0x1009) ACC_PUBLIC, ACC_STATIC, ACC_SYNTHETIC
    Code:
      stack=2, locals=2, args_size=2
         0: aload_0
         1: aload_1
         2: invokespecial #102                // InterfaceMethod compose:(Lshapeless/Prism;)Lshapeless/Prism;
         5: areturn
      LineNumberTable:
        line 79: 0
      LocalVariableTable:
        Start  Length  Slot  Name   Signature
            0       6     0 $this   Lshapeless/Prism;
            0       6     1     g   Lshapeless/Prism;
    MethodParameters:
      Name                           Flags
      $this                          final synthetic
      g                              final

  public default <T extends java.lang.Object> shapeless.Prism<T, A> compose(shapeless.Prism<T, S>);
    descriptor: (Lshapeless/Prism;)Lshapeless/Prism;
    flags: (0x0001) ACC_PUBLIC
    Code:
      stack=4, locals=2, args_size=2
         0: new           #20                 // class shapeless/Prism$$anon$6
         3: dup
         4: aload_0
         5: aload_1
         6: invokespecial #106                // Method shapeless/Prism$$anon$6."<init>":(Lshapeless/Prism;Lshapeless/Prism;)V
         9: areturn
      LineNumberTable:
        line 79: 0
      LocalVariableTable:
        Start  Length  Slot  Name   Signature
            0      10     0  this   Lshapeless/Prism;
            0      10     1     g   Lshapeless/Prism;
    Signature: #103                         // <T:Ljava/lang/Object;>(Lshapeless/Prism<TT;TS;>;)Lshapeless/Prism<TT;TA;>;
    MethodParameters:
      Name                           Flags
      g                              final

  public static java.lang.Object selectDynamic$(shapeless.Prism, java.lang.String, shapeless.MkSelectDynamicOptic);
    descriptor: (Lshapeless/Prism;Ljava/lang/String;Lshapeless/MkSelectDynamicOptic;)Ljava/lang/Object;
    flags: (0x1009) ACC_PUBLIC, ACC_STATIC, ACC_SYNTHETIC
    Code:
      stack=3, locals=3, args_size=3
         0: aload_0
         1: aload_1
         2: aload_2
         3: invokespecial #114                // InterfaceMethod selectDynamic:(Ljava/lang/String;Lshapeless/MkSelectDynamicOptic;)Ljava/lang/Object;
         6: areturn
      LineNumberTable:
        line 84: 0
      LocalVariableTable:
        Start  Length  Slot  Name   Signature
            0       7     0 $this   Lshapeless/Prism;
            0       7     1     k   Ljava/lang/String;
            0       7     2 mkPrism   Lshapeless/MkSelectDynamicOptic;
    MethodParameters:
      Name                           Flags
      $this                          final synthetic
      k                              final
      mkPrism                        final

  public default java.lang.Object selectDynamic(java.lang.String, shapeless.MkSelectDynamicOptic<shapeless.Prism<S, A>, A, scala.Symbol, scala.runtime.Nothing$>);
    descriptor: (Ljava/lang/String;Lshapeless/MkSelectDynamicOptic;)Ljava/lang/Object;
    flags: (0x0001) ACC_PUBLIC
    Code:
      stack=2, locals=4, args_size=3
         0: aload_2
         1: astore_3
         2: aload_3
         3: aload_0
         4: invokeinterface #121,  2          // InterfaceMethod shapeless/MkSelectDynamicOptic.apply:(Ljava/lang/Object;)Ljava/lang/Object;
         9: areturn
      LineNumberTable:
        line 85: 0
      LocalVariableTable:
        Start  Length  Slot  Name   Signature
            0      10     0  this   Lshapeless/Prism;
            0      10     1     k   Ljava/lang/String;
            0      10     2 mkPrism   Lshapeless/MkSelectDynamicOptic;
    Signature: #117                         // (Ljava/lang/String;Lshapeless/MkSelectDynamicOptic<Lshapeless/Prism<TS;TA;>;TA;Lscala/Symbol;Lscala/runtime/Nothing$;>;)Ljava/lang/Object;
    MethodParameters:
      Name                           Flags
      k                              final
      mkPrism                        final

  public static shapeless.Prism apply$(shapeless.Prism, shapeless.MkCtorPrism);
    descriptor: (Lshapeless/Prism;Lshapeless/MkCtorPrism;)Lshapeless/Prism;
    flags: (0x1009) ACC_PUBLIC, ACC_STATIC, ACC_SYNTHETIC
    Code:
      stack=2, locals=2, args_size=2
         0: aload_0
         1: aload_1
         2: invokespecial #126                // InterfaceMethod apply:(Lshapeless/MkCtorPrism;)Lshapeless/Prism;
         5: areturn
      LineNumberTable:
        line 87: 0
      LocalVariableTable:
        Start  Length  Slot  Name   Signature
            0       6     0 $this   Lshapeless/Prism;
            0       6     1 mkPrism   Lshapeless/MkCtorPrism;
    MethodParameters:
      Name                           Flags
      $this                          final synthetic
      mkPrism                        final

  public default <B extends java.lang.Object> shapeless.Prism<S, B> apply(shapeless.MkCtorPrism<A, B>);
    descriptor: (Lshapeless/MkCtorPrism;)Lshapeless/Prism;
    flags: (0x0001) ACC_PUBLIC
    Code:
      stack=2, locals=2, args_size=2
         0: aload_1
         1: invokeinterface #133,  1          // InterfaceMethod shapeless/MkCtorPrism.apply:()Lshapeless/Prism;
         6: aload_0
         7: invokeinterface #102,  2          // InterfaceMethod compose:(Lshapeless/Prism;)Lshapeless/Prism;
        12: areturn
      LineNumberTable:
        line 87: 0
      LocalVariableTable:
        Start  Length  Slot  Name   Signature
            0      13     0  this   Lshapeless/Prism;
            0      13     1 mkPrism   Lshapeless/MkCtorPrism;
    Signature: #128                         // <B:Ljava/lang/Object;>(Lshapeless/MkCtorPrism<TA;TB;>;)Lshapeless/Prism<TS;TB;>;
    MethodParameters:
      Name                           Flags
      mkPrism                        final

  public static scala.Option unapply$(shapeless.Prism, java.lang.Object);
    descriptor: (Lshapeless/Prism;Ljava/lang/Object;)Lscala/Option;
    flags: (0x1009) ACC_PUBLIC, ACC_STATIC, ACC_SYNTHETIC
    Code:
      stack=2, locals=2, args_size=2
         0: aload_0
         1: aload_1
         2: invokespecial #138                // InterfaceMethod unapply:(Ljava/lang/Object;)Lscala/Option;
         5: areturn
      LineNumberTable:
        line 89: 0
      LocalVariableTable:
        Start  Length  Slot  Name   Signature
            0       6     0 $this   Lshapeless/Prism;
            0       6     1     s   Ljava/lang/Object;
    MethodParameters:
      Name                           Flags
      $this                          final synthetic
      s                              final

  public default scala.Option<A> unapply(S);
    descriptor: (Ljava/lang/Object;)Lscala/Option;
    flags: (0x0001) ACC_PUBLIC
    Code:
      stack=2, locals=2, args_size=2
         0: aload_0
         1: aload_1
         2: invokeinterface #46,  2           // InterfaceMethod get:(Ljava/lang/Object;)Lscala/Option;
         7: areturn
      LineNumberTable:
        line 89: 0
      LocalVariableTable:
        Start  Length  Slot  Name   Signature
            0       8     0  this   Lshapeless/Prism;
            0       8     1     s   Ljava/lang/Object;
    Signature: #27                          // (TS;)Lscala/Option<TA;>;
    MethodParameters:
      Name                           Flags
      s                              final

  public static shapeless.ProductPrismBuilder $tilde$(shapeless.Prism, shapeless.Lens);
    descriptor: (Lshapeless/Prism;Lshapeless/Lens;)Lshapeless/ProductPrismBuilder;
    flags: (0x1009) ACC_PUBLIC, ACC_STATIC, ACC_SYNTHETIC
    Code:
      stack=2, locals=2, args_size=2
         0: aload_0
         1: aload_1
         2: invokespecial #145                // InterfaceMethod $tilde:(Lshapeless/Lens;)Lshapeless/ProductPrismBuilder;
         5: areturn
      LineNumberTable:
        line 91: 0
      LocalVariableTable:
        Start  Length  Slot  Name   Signature
            0       6     0 $this   Lshapeless/Prism;
            0       6     1 other   Lshapeless/Lens;
    MethodParameters:
      Name                           Flags
      $this                          final synthetic
      other                          final

  public default <B extends java.lang.Object> shapeless.ProductPrismBuilder<S, scala.Tuple2<A, B>> $tilde(shapeless.Lens<S, B>);
    descriptor: (Lshapeless/Lens;)Lshapeless/ProductPrismBuilder;
    flags: (0x0001) ACC_PUBLIC
    Code:
      stack=4, locals=2, args_size=2
         0: new           #22                 // class shapeless/Prism$$anon$7
         3: dup
         4: aload_0
         5: aload_1
         6: invokespecial #147                // Method shapeless/Prism$$anon$7."<init>":(Lshapeless/Prism;Lshapeless/Lens;)V
         9: areturn
      LineNumberTable:
        line 91: 0
      LocalVariableTable:
        Start  Length  Slot  Name   Signature
            0      10     0  this   Lshapeless/Prism;
            0      10     1 other   Lshapeless/Lens;
    Signature: #146                         // <B:Ljava/lang/Object;>(Lshapeless/Lens<TS;TB;>;)Lshapeless/ProductPrismBuilder<TS;Lscala/Tuple2<TA;TB;>;>;
    MethodParameters:
      Name                           Flags
      other                          final

  public static shapeless.ProductPrismBuilder $tilde$(shapeless.Prism, shapeless.Prism);
    descriptor: (Lshapeless/Prism;Lshapeless/Prism;)Lshapeless/ProductPrismBuilder;
    flags: (0x1009) ACC_PUBLIC, ACC_STATIC, ACC_SYNTHETIC
    Code:
      stack=2, locals=2, args_size=2
         0: aload_0
         1: aload_1
         2: invokespecial #151                // InterfaceMethod $tilde:(Lshapeless/Prism;)Lshapeless/ProductPrismBuilder;
         5: areturn
      LineNumberTable:
        line 97: 0
      LocalVariableTable:
        Start  Length  Slot  Name   Signature
            0       6     0 $this   Lshapeless/Prism;
            0       6     1 other   Lshapeless/Prism;
    MethodParameters:
      Name                           Flags
      $this                          final synthetic
      other                          final

  public default <B extends java.lang.Object> shapeless.ProductPrismBuilder<S, scala.Tuple2<A, B>> $tilde(shapeless.Prism<S, B>);
    descriptor: (Lshapeless/Prism;)Lshapeless/ProductPrismBuilder;
    flags: (0x0001) ACC_PUBLIC
    Code:
      stack=4, locals=2, args_size=2
         0: new           #24                 // class shapeless/Prism$$anon$8
         3: dup
         4: aload_0
         5: aload_1
         6: invokespecial #153                // Method shapeless/Prism$$anon$8."<init>":(Lshapeless/Prism;Lshapeless/Prism;)V
         9: areturn
      LineNumberTable:
        line 97: 0
      LocalVariableTable:
        Start  Length  Slot  Name   Signature
            0      10     0  this   Lshapeless/Prism;
            0      10     1 other   Lshapeless/Prism;
    Signature: #152                         // <B:Ljava/lang/Object;>(Lshapeless/Prism<TS;TB;>;)Lshapeless/ProductPrismBuilder<TS;Lscala/Tuple2<TA;TB;>;>;
    MethodParameters:
      Name                           Flags
      other                          final

  public static java.lang.Object $anonfun$modify$1(shapeless.Prism, java.lang.Object, java.lang.Object);
    descriptor: (Lshapeless/Prism;Ljava/lang/Object;Ljava/lang/Object;)Ljava/lang/Object;
    flags: (0x1009) ACC_PUBLIC, ACC_STATIC, ACC_SYNTHETIC
    Code:
      stack=3, locals=3, args_size=3
         0: aload_0
         1: aload_1
         2: aload_2
         3: invokeinterface #156,  3          // InterfaceMethod set:(Ljava/lang/Object;Ljava/lang/Object;)Ljava/lang/Object;
         8: areturn
      LineNumberTable:
        line 72: 0
      LocalVariableTable:
        Start  Length  Slot  Name   Signature
            0       9     0 $this   Lshapeless/Prism;
            0       9     1   s$2   Ljava/lang/Object;
            0       9     2     a   Ljava/lang/Object;
    MethodParameters:
      Name                           Flags
      $this                          final synthetic
      s$2                            final
      a                              final

  public static java.lang.Object $anonfun$modify$2(java.lang.Object);
    descriptor: (Ljava/lang/Object;)Ljava/lang/Object;
    flags: (0x1009) ACC_PUBLIC, ACC_STATIC, ACC_SYNTHETIC
    Code:
      stack=1, locals=1, args_size=1
         0: aload_0
         1: areturn
      LineNumberTable:
        line 72: 0
      LocalVariableTable:
        Start  Length  Slot  Name   Signature
            0       2     0   s$2   Ljava/lang/Object;
    MethodParameters:
      Name                           Flags
      s$2                            final

  public static void $init$(shapeless.Prism);
    descriptor: (Lshapeless/Prism;)V
    flags: (0x0009) ACC_PUBLIC, ACC_STATIC
    Code:
      stack=0, locals=1, args_size=1
         0: return
      LineNumberTable:
        line 69: 0
      LocalVariableTable:
        Start  Length  Slot  Name   Signature
            0       1     0 $this   Lshapeless/Prism;
    MethodParameters:
      Name                           Flags
      $this                          final synthetic

  private static java.lang.Object $deserializeLambda$(java.lang.invoke.SerializedLambda);
    descriptor: (Ljava/lang/invoke/SerializedLambda;)Ljava/lang/Object;
    flags: (0x100a) ACC_PRIVATE, ACC_STATIC, ACC_SYNTHETIC
    Code:
      stack=1, locals=1, args_size=1
         0: aload_0
         1: invokedynamic #170,  0            // InvokeDynamic #2:lambdaDeserialize:(Ljava/lang/invoke/SerializedLambda;)Ljava/lang/Object;
         6: areturn
}
InnerClasses:
  public static final #16= #13 of #15;    // Lookup=class java/lang/invoke/MethodHandles$Lookup of class java/lang/invoke/MethodHandles
  public final #18;                       // class shapeless/Prism$$anon$5
  public final #20;                       // class shapeless/Prism$$anon$6
  public final #22;                       // class shapeless/Prism$$anon$7
  public final #24;                       // class shapeless/Prism$$anon$8
Signature: #3                           // <S:Ljava/lang/Object;A:Ljava/lang/Object;>Ljava/lang/Object;Lshapeless/LPPrism<TS;TA;>;
SourceFile: "lenses.scala"
RuntimeVisibleAnnotations:
  0: #9(#10=s#11)
    scala.reflect.ScalaSignature(
      bytes="\u0006\u0005\u0005Uca\u0002\u0007\u000e!\u0003\r\t\u0001\u0005\u0005\u0006U\u0001!\ta\u000b\u0005\u0006_\u00011\t\u0001\r\u0005\u0006m\u00011\ta\u000e\u0005\u0006y\u0001!\t!\u0010\u0005\u0006\u000b\u0002!\tA\u0012\u0005\u0006\u000b\u0002!\t\u0001\u0016\u0005\u0006;\u0002!\tA\u0018\u0005\b\u0003\u000b\u0001A\u0011AA\u0004\u0011\u001d\tY\u0002\u0001C\u0001\u0003;Aq!!\t\u0001\t\u0003\t\u0019\u0003C\u0004\u0002\"\u0001!\t!!\u0011\u0003\u000bA\u0013\u0018n]7\u000b\u00039\t\u0011b\u001d5ba\u0016dWm]:\u0004\u0001U\u0019\u0011C\b\u0015\u0014\u0007\u0001\u0011\u0002\u0004\u0005\u0002\u0014-5\tACC\u0001\u0016\u0003\u0015\u00198-\u00197b\u0013\t9BC\u0001\u0004B]f\u0014VM\u001a\t\u00053iar%D\u0001\u000e\u0013\tYRBA\u0004M!B\u0013\u0018n]7\u0011\u0005uqB\u0002\u0001\u0003\u0006?\u0001\u0011\r\u0001\t\u0002\u0002\'F\u0011\u0011\u0005\n\t\u0003\'\tJ!a\t\u000b\u0003\u000f9{G\u000f[5oOB\u00111#J\u0005\u0003MQ\u00111!\u00118z!\ti\u0002\u0006B\u0003*\u0001\t\u0007\u0001EA\u0001B\u0003\u0019!\u0013N\\5uIQ\tA\u0006\u0005\u0002\u0014[%\u0011a\u0006\u0006\u0002\u0005+:LG/A\u0002hKR$\"!\r\u001b\u0011\u0007M\u0011t%\u0003\u00024)\t1q\n\u001d;j_:DQ!\u000e\u0002A\u0002q\t\u0011a]\u0001\u0004g\u0016$HC\u0001\u001d<)\ta\u0012\bC\u0003;\u0007\u0001\u0007q%A\u0001b\u0011\u0015)4\u00011\u0001\u001d\u0003\u0019iw\u000eZ5gsR\u0011a\b\u0012\u000b\u00039}BQ\u0001\u0011\u0003A\u0002\u0005\u000b\u0011A\u001a\t\u0005\'\t;s%\u0003\u0002D)\tIa)\u001e8di&|g.\r\u0005\u0006k\u0011\u0001\r\u0001H\u0001\bG>l\u0007o\\:f+\t9U\n\u0006\u0002I\u001fJ\u0019\u0011JE&\u0007\t)+\u0001\u0001\u0013\u0002\ryI,g-\u001b8f[\u0016tGO\u0010\t\u00053\u0001au\u0005\u0005\u0002\u001e\u001b\u0012)a*\u0002b\u0001A\t\tA\u000bC\u0003Q\u000b\u0001\u0007\u0011+A\u0001h!\u0011I\"\u000b\u0014\u000f\n\u0005Mk!\u0001\u0002\'f]N,\"!\u0016.\u0015\u0005Y[&cA,\u00131\u001a!!J\u0002\u0001W!\u0011I\u0002!W\u0014\u0011\u0005uQF!\u0002(\u0007\u0005\u0004\u0001\u0003\"\u0002)\u0007\u0001\u0004a\u0006\u0003B\r\u00013r\tQb]3mK\u000e$H)\u001f8b[&\u001cGCA0t)\t\u0001\'\rE\u0002b\u0003\u0003q!!\b2\t\u000b\r<\u00019\u00013\u0002\u000f5\\\u0007K]5t[B1\u0011$Z4(Q\u0006J!AZ\u0007\u0003)5[7+\u001a7fGR$\u0015P\\1nS\u000e|\u0005\u000f^5d!\u0011I\u0002\u0001H\u0014\u0011\t%dwN\u001d\b\u00033)L!a[\u0007\u0002\u0007Q\fw-\u0003\u0002n]\n1A%\u0019;%CRT!a[\u0007\u0011\u0005M\u0001\u0018BA9\u0015\u0005\u0019\u0019\u00160\u001c2pY:\u0011Qd\u001d\u0005\u0006i\u001e\u0001\r!^\u0001\u0002WB\u0011a/ \b\u0003on\u0004\"\u0001\u001f\u000b\u000e\u0003eT!A_\b\u0002\rq\u0012xn\u001c;?\u0013\taH#\u0001\u0004Qe\u0016$WMZ\u0005\u0003}~\u0014aa\u0015;sS:<\'B\u0001?\u0015\u0013\r\t\u0019!\u001a\u0002\u0004\u001fV$\u0018!B1qa2LX\u0003BA\u0005\u0003\u001f!B!a\u0003\u0002\u0014A)\u0011\u0004\u0001\u000f\u0002\u000eA\u0019Q$a\u0004\u0005\r\u0005E\u0001B1\u0001!\u0005\u0005\u0011\u0005BB2\t\u0001\b\t)\u0002\u0005\u0004\u001a\u0003/9\u0013QB\u0005\u0004\u00033i!aC\'l\u0007R|\'\u000f\u0015:jg6\fq!\u001e8baBd\u0017\u0010F\u00022\u0003?AQ!N\u0005A\u0002q\ta\u0001\n;jY\u0012,W\u0003BA\u0013\u0003s!B!a\n\u0002<I)\u0011\u0011\u0006\n\u0002,\u0019)!J\u0003\u0001\u0002(A1\u0011$!\f\u001d\u0003cI1!a\f\u000e\u0005M\u0001&o\u001c3vGR\u0004&/[:n\u0005VLG\u000eZ3s!\u0019\u0019\u00121G\u0014\u00028%\u0019\u0011Q\u0007\u000b\u0003\rQ+\b\u000f\\33!\ri\u0012\u0011\b\u0003\u0007\u0003#Q!\u0019\u0001\u0011\t\u000f\u0005u\"\u00021\u0001\u0002@\u0005)q\u000e\u001e5feB)\u0011D\u0015\u000f\u00028U!\u00111IA()\u0011\t)%!\u0015\u0013\u000b\u0005\u001d##!\u0013\u0007\u000b)[\u0001!!\u0012\u0011\re\ti\u0003HA&!\u0019\u0019\u00121G\u0014\u0002NA\u0019Q$a\u0014\u0005\r\u0005E1B1\u0001!\u0011\u001d\tid\u0003a\u0001\u0003\'\u0002R!\u0007\u0001\u001d\u0003\u001b\u0002"
    )
BootstrapMethods:
  0: #67 REF_invokeStatic java/lang/invoke/LambdaMetafactory.altMetafactory:(Ljava/lang/invoke/MethodHandles$Lookup;Ljava/lang/String;Ljava/lang/invoke/MethodType;[Ljava/lang/Object;)Ljava/lang/invoke/CallSite;
    Method arguments:
      #54 (Ljava/lang/Object;)Ljava/lang/Object;
      #59 REF_invokeStatic shapeless/Prism.$anonfun$modify$1:(Lshapeless/Prism;Ljava/lang/Object;Ljava/lang/Object;)Ljava/lang/Object;
      #54 (Ljava/lang/Object;)Ljava/lang/Object;
      #60 1
  1: #67 REF_invokeStatic java/lang/invoke/LambdaMetafactory.altMetafactory:(Ljava/lang/invoke/MethodHandles$Lookup;Ljava/lang/String;Ljava/lang/invoke/MethodType;[Ljava/lang/Object;)Ljava/lang/invoke/CallSite;
    Method arguments:
      #73 ()Ljava/lang/Object;
      #77 REF_invokeStatic shapeless/Prism.$anonfun$modify$2:(Ljava/lang/Object;)Ljava/lang/Object;
      #73 ()Ljava/lang/Object;
      #60 1
  2: #167 REF_invokeStatic scala/runtime/LambdaDeserialize.bootstrap:(Ljava/lang/invoke/MethodHandles$Lookup;Ljava/lang/String;Ljava/lang/invoke/MethodType;[Ljava/lang/invoke/MethodHandle;)Ljava/lang/invoke/CallSite;
    Method arguments:
      #59 REF_invokeStatic shapeless/Prism.$anonfun$modify$1:(Lshapeless/Prism;Ljava/lang/Object;Ljava/lang/Object;)Ljava/lang/Object;
      #77 REF_invokeStatic shapeless/Prism.$anonfun$modify$2:(Ljava/lang/Object;)Ljava/lang/Object;
  ScalaInlineInfo: length = 0x6D (unknown attribute)
   01 00 00 15 00 37 00 38 01 00 4A 00 35 01 00 9D
   00 9E 01 00 8B 00 8C 01 00 8B 00 94 01 00 8E 00
   8F 00 00 8E 00 95 00 00 7A 00 7B 01 00 44 00 7C
   00 00 56 00 57 01 00 56 00 63 01 00 59 00 5A 00
   00 59 00 64 00 00 19 00 1A 00 00 21 00 22 01 00
   25 00 26 00 00 6B 00 6C 01 00 6F 00 70 00 00 1D
   00 1E 00 00 86 00 87 01 00 88 00 1A 00
  ScalaSig: length = 0x3 (unknown attribute)
   05 02 00
