Classfile /Users/mw/Projects/slang-braindump/.jar/jar11/assemble/slang-braindump/assemble/content/shapeless/ProductPrismBuilder$$anon$10.class
  Last modified May 29, 2022; size 9181 bytes
  SHA-256 checksum 45a200ce579e3822c5b5683f308e6d67ccb36d8e16a1fb1d63927bef50d43ba4
  Compiled from "lenses.scala"
public final class shapeless.ProductPrismBuilder$$anon$10 extends java.lang.Object implements shapeless.ProductPrismBuilder<C, Q>
  minor version: 0
  major version: 52
  flags: (0x0031) ACC_PUBLIC, ACC_FINAL, ACC_SUPER
  this_class: #2                          // shapeless/ProductPrismBuilder$$anon$10
  super_class: #5                         // java/lang/Object
  interfaces: 1, fields: 9, methods: 17, attributes: 7
Constant pool:
    #1 = Utf8               shapeless/ProductPrismBuilder$$anon$10
    #2 = Class              #1            // shapeless/ProductPrismBuilder$$anon$10
    #3 = Utf8               Ljava/lang/Object;Lshapeless/ProductPrismBuilder<TC;TQ;>;
    #4 = Utf8               java/lang/Object
    #5 = Class              #4            // java/lang/Object
    #6 = Utf8               shapeless/ProductPrismBuilder
    #7 = Class              #6            // shapeless/ProductPrismBuilder
    #8 = Utf8               lenses.scala
    #9 = Utf8               $tilde
   #10 = Utf8               (Lshapeless/Prism;Lshapeless/Generic;Lshapeless/ops/hlist$Tupler;Lshapeless/ops/hlist$Prepend;Lshapeless/ops/hlist$Tupler;Lshapeless/Generic;Lshapeless/ops/hlist$Init;Lshapeless/ops/hlist$Last;)Lshapeless/ProductPrismBuilder;
   #11 = NameAndType        #9:#10        // $tilde:(Lshapeless/Prism;Lshapeless/Generic;Lshapeless/ops/hlist$Tupler;Lshapeless/ops/hlist$Prepend;Lshapeless/ops/hlist$Tupler;Lshapeless/Generic;Lshapeless/ops/hlist$Init;Lshapeless/ops/hlist$Last;)Lshapeless/ProductPrismBuilder;
   #12 = Utf8               java/lang/invoke/MethodHandles$Lookup
   #13 = Class              #12           // java/lang/invoke/MethodHandles$Lookup
   #14 = Utf8               java/lang/invoke/MethodHandles
   #15 = Class              #14           // java/lang/invoke/MethodHandles
   #16 = Utf8               Lookup
   #17 = Utf8               shapeless/ops/hlist$Init
   #18 = Class              #17           // shapeless/ops/hlist$Init
   #19 = Utf8               shapeless/ops/hlist
   #20 = Class              #19           // shapeless/ops/hlist
   #21 = Utf8               Init
   #22 = Utf8               shapeless/ops/hlist$Last
   #23 = Class              #22           // shapeless/ops/hlist$Last
   #24 = Utf8               Last
   #25 = Utf8               shapeless/ops/hlist$Prepend
   #26 = Class              #25           // shapeless/ops/hlist$Prepend
   #27 = Utf8               Prepend
   #28 = Utf8               shapeless/ops/hlist$Tupler
   #29 = Class              #28           // shapeless/ops/hlist$Tupler
   #30 = Utf8               Tupler
   #31 = Utf8               $outer
   #32 = Utf8               Lshapeless/ProductPrismBuilder;
   #33 = Utf8               other$6
   #34 = Utf8               Lshapeless/Prism;
   #35 = Utf8               genp$2
   #36 = Utf8               Lshapeless/Generic;
   #37 = Utf8               pre$2
   #38 = Utf8               Lshapeless/ops/hlist$Prepend;
   #39 = Utf8               tpq$2
   #40 = Utf8               Lshapeless/ops/hlist$Tupler;
   #41 = Utf8               genq$2
   #42 = Utf8               init$3
   #43 = Utf8               Lshapeless/ops/hlist$Init;
   #44 = Utf8               tpp$2
   #45 = Utf8               last$2
   #46 = Utf8               Lshapeless/ops/hlist$Last;
   #47 = Utf8               <T:Ljava/lang/Object;L::Lshapeless/HList;LT::Lshapeless/HList;Q::Lscala/Product;QL::Lshapeless/HList;>(Lshapeless/Prism<TC;TT;>;Lshapeless/Generic<TQ;>;Lshapeless/ops/hlist$Tupler<TL;>;Lshapeless/ops/hlist$Prepend<TL;Lshapeless/$colon$colon<TT;Lshapeless/HNil;>;>;Lshapeless/ops/hlist$Tupler<TLT;>;Lshapeless/Generic<TQ;>;Lshapeless/ops/hlist$Init<TQL;>;Lshapeless/ops/hlist$Last<TQL;>;)Lshapeless/ProductPrismBuilder<TC;TQ;>;
   #48 = Utf8               other
   #49 = Utf8               genp
   #50 = Utf8               tpp
   #51 = Utf8               pre
   #52 = Utf8               tpq
   #53 = Utf8               genq
   #54 = Utf8               init
   #55 = Utf8               last
   #56 = Utf8               $tilde$
   #57 = Utf8               (Lshapeless/ProductPrismBuilder;Lshapeless/Prism;Lshapeless/Generic;Lshapeless/ops/hlist$Tupler;Lshapeless/ops/hlist$Prepend;Lshapeless/ops/hlist$Tupler;Lshapeless/Generic;Lshapeless/ops/hlist$Init;Lshapeless/ops/hlist$Last;)Lshapeless/ProductPrismBuilder;
   #58 = NameAndType        #56:#57       // $tilde$:(Lshapeless/ProductPrismBuilder;Lshapeless/Prism;Lshapeless/Generic;Lshapeless/ops/hlist$Tupler;Lshapeless/ops/hlist$Prepend;Lshapeless/ops/hlist$Tupler;Lshapeless/Generic;Lshapeless/ops/hlist$Init;Lshapeless/ops/hlist$Last;)Lshapeless/ProductPrismBuilder;
   #59 = InterfaceMethodref #7.#58        // shapeless/ProductPrismBuilder.$tilde$:(Lshapeless/ProductPrismBuilder;Lshapeless/Prism;Lshapeless/Generic;Lshapeless/ops/hlist$Tupler;Lshapeless/ops/hlist$Prepend;Lshapeless/ops/hlist$Tupler;Lshapeless/Generic;Lshapeless/ops/hlist$Init;Lshapeless/ops/hlist$Last;)Lshapeless/ProductPrismBuilder;
   #60 = Utf8               this
   #61 = Utf8               Lshapeless/ProductPrismBuilder$$anon$10;
   #62 = Utf8               modify
   #63 = Utf8               (Ljava/lang/Object;Lscala/Function1;)Ljava/lang/Object;
   #64 = Utf8               (TC;Lscala/Function1<TQ;TQ;>;)TC;
   #65 = Utf8               s
   #66 = Utf8               f
   #67 = Utf8               shapeless/Prism
   #68 = Class              #67           // shapeless/Prism
   #69 = Utf8               modify$
   #70 = Utf8               (Lshapeless/Prism;Ljava/lang/Object;Lscala/Function1;)Ljava/lang/Object;
   #71 = NameAndType        #69:#70       // modify$:(Lshapeless/Prism;Ljava/lang/Object;Lscala/Function1;)Ljava/lang/Object;
   #72 = InterfaceMethodref #68.#71       // shapeless/Prism.modify$:(Lshapeless/Prism;Ljava/lang/Object;Lscala/Function1;)Ljava/lang/Object;
   #73 = Utf8               Ljava/lang/Object;
   #74 = Utf8               Lscala/Function1;
   #75 = Utf8               compose
   #76 = Utf8               (Lshapeless/Lens;)Lshapeless/Prism;
   #77 = Utf8               <T:Ljava/lang/Object;>(Lshapeless/Lens<TT;TC;>;)Lshapeless/Prism<TT;TQ;>;
   #78 = Utf8               g
   #79 = Utf8               compose$
   #80 = Utf8               (Lshapeless/Prism;Lshapeless/Lens;)Lshapeless/Prism;
   #81 = NameAndType        #79:#80       // compose$:(Lshapeless/Prism;Lshapeless/Lens;)Lshapeless/Prism;
   #82 = InterfaceMethodref #68.#81       // shapeless/Prism.compose$:(Lshapeless/Prism;Lshapeless/Lens;)Lshapeless/Prism;
   #83 = Utf8               Lshapeless/Lens;
   #84 = Utf8               (Lshapeless/Prism;)Lshapeless/Prism;
   #85 = Utf8               <T:Ljava/lang/Object;>(Lshapeless/Prism<TT;TC;>;)Lshapeless/Prism<TT;TQ;>;
   #86 = Utf8               (Lshapeless/Prism;Lshapeless/Prism;)Lshapeless/Prism;
   #87 = NameAndType        #79:#86       // compose$:(Lshapeless/Prism;Lshapeless/Prism;)Lshapeless/Prism;
   #88 = InterfaceMethodref #68.#87       // shapeless/Prism.compose$:(Lshapeless/Prism;Lshapeless/Prism;)Lshapeless/Prism;
   #89 = Utf8               selectDynamic
   #90 = Utf8               (Ljava/lang/String;Lshapeless/MkSelectDynamicOptic;)Ljava/lang/Object;
   #91 = Utf8               (Ljava/lang/String;Lshapeless/MkSelectDynamicOptic<Lshapeless/Prism<TC;TQ;>;TQ;Lscala/Symbol;Lscala/runtime/Nothing$;>;)Ljava/lang/Object;
   #92 = Utf8               k
   #93 = Utf8               mkPrism
   #94 = Utf8               selectDynamic$
   #95 = Utf8               (Lshapeless/Prism;Ljava/lang/String;Lshapeless/MkSelectDynamicOptic;)Ljava/lang/Object;
   #96 = NameAndType        #94:#95       // selectDynamic$:(Lshapeless/Prism;Ljava/lang/String;Lshapeless/MkSelectDynamicOptic;)Ljava/lang/Object;
   #97 = InterfaceMethodref #68.#96       // shapeless/Prism.selectDynamic$:(Lshapeless/Prism;Ljava/lang/String;Lshapeless/MkSelectDynamicOptic;)Ljava/lang/Object;
   #98 = Utf8               Ljava/lang/String;
   #99 = Utf8               Lshapeless/MkSelectDynamicOptic;
  #100 = Utf8               apply
  #101 = Utf8               (Lshapeless/MkCtorPrism;)Lshapeless/Prism;
  #102 = Utf8               <B:Ljava/lang/Object;>(Lshapeless/MkCtorPrism<TQ;TB;>;)Lshapeless/Prism<TC;TB;>;
  #103 = Utf8               apply$
  #104 = Utf8               (Lshapeless/Prism;Lshapeless/MkCtorPrism;)Lshapeless/Prism;
  #105 = NameAndType        #103:#104     // apply$:(Lshapeless/Prism;Lshapeless/MkCtorPrism;)Lshapeless/Prism;
  #106 = InterfaceMethodref #68.#105      // shapeless/Prism.apply$:(Lshapeless/Prism;Lshapeless/MkCtorPrism;)Lshapeless/Prism;
  #107 = Utf8               Lshapeless/MkCtorPrism;
  #108 = Utf8               unapply
  #109 = Utf8               (Ljava/lang/Object;)Lscala/Option;
  #110 = Utf8               (TC;)Lscala/Option<TQ;>;
  #111 = Utf8               unapply$
  #112 = Utf8               (Lshapeless/Prism;Ljava/lang/Object;)Lscala/Option;
  #113 = NameAndType        #111:#112     // unapply$:(Lshapeless/Prism;Ljava/lang/Object;)Lscala/Option;
  #114 = InterfaceMethodref #68.#113      // shapeless/Prism.unapply$:(Lshapeless/Prism;Ljava/lang/Object;)Lscala/Option;
  #115 = Utf8               (Lshapeless/Lens;)Lshapeless/ProductPrismBuilder;
  #116 = Utf8               <B:Ljava/lang/Object;>(Lshapeless/Lens<TC;TB;>;)Lshapeless/ProductPrismBuilder<TC;Lscala/Tuple2<TQ;TB;>;>;
  #117 = Utf8               (Lshapeless/Prism;Lshapeless/Lens;)Lshapeless/ProductPrismBuilder;
  #118 = NameAndType        #56:#117      // $tilde$:(Lshapeless/Prism;Lshapeless/Lens;)Lshapeless/ProductPrismBuilder;
  #119 = InterfaceMethodref #68.#118      // shapeless/Prism.$tilde$:(Lshapeless/Prism;Lshapeless/Lens;)Lshapeless/ProductPrismBuilder;
  #120 = Utf8               (Lshapeless/Prism;)Lshapeless/ProductPrismBuilder;
  #121 = Utf8               <B:Ljava/lang/Object;>(Lshapeless/Prism<TC;TB;>;)Lshapeless/ProductPrismBuilder<TC;Lscala/Tuple2<TQ;TB;>;>;
  #122 = Utf8               (Lshapeless/Prism;Lshapeless/Prism;)Lshapeless/ProductPrismBuilder;
  #123 = NameAndType        #56:#122      // $tilde$:(Lshapeless/Prism;Lshapeless/Prism;)Lshapeless/ProductPrismBuilder;
  #124 = InterfaceMethodref #68.#123      // shapeless/Prism.$tilde$:(Lshapeless/Prism;Lshapeless/Prism;)Lshapeless/ProductPrismBuilder;
  #125 = Utf8               (Ljava/lang/String;Lshapeless/MkSelectDynamicOptic;Lscala/DummyImplicit;)Ljava/lang/Object;
  #126 = Utf8               <B:Ljava/lang/Object;>(Ljava/lang/String;Lshapeless/MkSelectDynamicOptic<Lshapeless/Prism<TC;TQ;>;TQ;Lscala/Symbol;TB;>;Lscala/DummyImplicit;)Ljava/lang/Object;
  #127 = Utf8               dummy
  #128 = Utf8               shapeless/LPPrism
  #129 = Class              #128          // shapeless/LPPrism
  #130 = Utf8               (Lshapeless/LPPrism;Ljava/lang/String;Lshapeless/MkSelectDynamicOptic;Lscala/DummyImplicit;)Ljava/lang/Object;
  #131 = NameAndType        #94:#130      // selectDynamic$:(Lshapeless/LPPrism;Ljava/lang/String;Lshapeless/MkSelectDynamicOptic;Lscala/DummyImplicit;)Ljava/lang/Object;
  #132 = InterfaceMethodref #129.#131     // shapeless/LPPrism.selectDynamic$:(Lshapeless/LPPrism;Ljava/lang/String;Lshapeless/MkSelectDynamicOptic;Lscala/DummyImplicit;)Ljava/lang/Object;
  #133 = Utf8               Lscala/DummyImplicit;
  #134 = Utf8               get
  #135 = Utf8               c
  #136 = NameAndType        #31:#32       // $outer:Lshapeless/ProductPrismBuilder;
  #137 = Fieldref           #2.#136       // shapeless/ProductPrismBuilder$$anon$10.$outer:Lshapeless/ProductPrismBuilder;
  #138 = NameAndType        #134:#109     // get:(Ljava/lang/Object;)Lscala/Option;
  #139 = InterfaceMethodref #7.#138       // shapeless/ProductPrismBuilder.get:(Ljava/lang/Object;)Lscala/Option;
  #140 = Utf8               (Ljava/lang/Object;)Ljava/lang/Object;
  #141 = MethodType         #140          //  (Ljava/lang/Object;)Ljava/lang/Object;
  #142 = Utf8               $anonfun$get$7
  #143 = Utf8               (Lshapeless/ProductPrismBuilder$$anon$10;Ljava/lang/Object;Lscala/Product;)Lscala/Option;
  #144 = NameAndType        #142:#143     // $anonfun$get$7:(Lshapeless/ProductPrismBuilder$$anon$10;Ljava/lang/Object;Lscala/Product;)Lscala/Option;
  #145 = Methodref          #2.#144       // shapeless/ProductPrismBuilder$$anon$10.$anonfun$get$7:(Lshapeless/ProductPrismBuilder$$anon$10;Ljava/lang/Object;Lscala/Product;)Lscala/Option;
  #146 = MethodHandle       6:#145        // REF_invokeStatic shapeless/ProductPrismBuilder$$anon$10.$anonfun$get$7:(Lshapeless/ProductPrismBuilder$$anon$10;Ljava/lang/Object;Lscala/Product;)Lscala/Option;
  #147 = Utf8               (Lscala/Product;)Lscala/Option;
  #148 = MethodType         #147          //  (Lscala/Product;)Lscala/Option;
  #149 = Integer            5
  #150 = Integer            1
  #151 = Utf8               java/lang/invoke/LambdaMetafactory
  #152 = Class              #151          // java/lang/invoke/LambdaMetafactory
  #153 = Utf8               altMetafactory
  #154 = Utf8               (Ljava/lang/invoke/MethodHandles$Lookup;Ljava/lang/String;Ljava/lang/invoke/MethodType;[Ljava/lang/Object;)Ljava/lang/invoke/CallSite;
  #155 = NameAndType        #153:#154     // altMetafactory:(Ljava/lang/invoke/MethodHandles$Lookup;Ljava/lang/String;Ljava/lang/invoke/MethodType;[Ljava/lang/Object;)Ljava/lang/invoke/CallSite;
  #156 = Methodref          #152.#155     // java/lang/invoke/LambdaMetafactory.altMetafactory:(Ljava/lang/invoke/MethodHandles$Lookup;Ljava/lang/String;Ljava/lang/invoke/MethodType;[Ljava/lang/Object;)Ljava/lang/invoke/CallSite;
  #157 = MethodHandle       6:#156        // REF_invokeStatic java/lang/invoke/LambdaMetafactory.altMetafactory:(Ljava/lang/invoke/MethodHandles$Lookup;Ljava/lang/String;Ljava/lang/invoke/MethodType;[Ljava/lang/Object;)Ljava/lang/invoke/CallSite;
  #158 = Utf8               (Lshapeless/ProductPrismBuilder$$anon$10;Ljava/lang/Object;)Lscala/Function1;
  #159 = NameAndType        #100:#158     // apply:(Lshapeless/ProductPrismBuilder$$anon$10;Ljava/lang/Object;)Lscala/Function1;
  #160 = InvokeDynamic      #0:#159       // #0:apply:(Lshapeless/ProductPrismBuilder$$anon$10;Ljava/lang/Object;)Lscala/Function1;
  #161 = Utf8               scala/Option
  #162 = Class              #161          // scala/Option
  #163 = Utf8               flatMap
  #164 = Utf8               (Lscala/Function1;)Lscala/Option;
  #165 = NameAndType        #163:#164     // flatMap:(Lscala/Function1;)Lscala/Option;
  #166 = Methodref          #162.#165     // scala/Option.flatMap:(Lscala/Function1;)Lscala/Option;
  #167 = Utf8               set
  #168 = Utf8               (Ljava/lang/Object;Lscala/Product;)Ljava/lang/Object;
  #169 = Utf8               (TC;TQ;)TC;
  #170 = Utf8               q
  #171 = NameAndType        #41:#36       // genq$2:Lshapeless/Generic;
  #172 = Fieldref           #2.#171       // shapeless/ProductPrismBuilder$$anon$10.genq$2:Lshapeless/Generic;
  #173 = Utf8               shapeless/Generic
  #174 = Class              #173          // shapeless/Generic
  #175 = Utf8               to
  #176 = NameAndType        #175:#140     // to:(Ljava/lang/Object;)Ljava/lang/Object;
  #177 = InterfaceMethodref #174.#176     // shapeless/Generic.to:(Ljava/lang/Object;)Ljava/lang/Object;
  #178 = Utf8               shapeless/HList
  #179 = Class              #178          // shapeless/HList
  #180 = NameAndType        #33:#34       // other$6:Lshapeless/Prism;
  #181 = Fieldref           #2.#180       // shapeless/ProductPrismBuilder$$anon$10.other$6:Lshapeless/Prism;
  #182 = Utf8               shapeless/HList$
  #183 = Class              #182          // shapeless/HList$
  #184 = Utf8               MODULE$
  #185 = Utf8               Lshapeless/HList$;
  #186 = NameAndType        #184:#185     // MODULE$:Lshapeless/HList$;
  #187 = Fieldref           #183.#186     // shapeless/HList$.MODULE$:Lshapeless/HList$;
  #188 = Utf8               hlistOps
  #189 = Utf8               (Lshapeless/HList;)Lshapeless/syntax/HListOps;
  #190 = NameAndType        #188:#189     // hlistOps:(Lshapeless/HList;)Lshapeless/syntax/HListOps;
  #191 = Methodref          #183.#190     // shapeless/HList$.hlistOps:(Lshapeless/HList;)Lshapeless/syntax/HListOps;
  #192 = NameAndType        #42:#43       // init$3:Lshapeless/ops/hlist$Init;
  #193 = Fieldref           #2.#192       // shapeless/ProductPrismBuilder$$anon$10.init$3:Lshapeless/ops/hlist$Init;
  #194 = Utf8               shapeless/syntax/HListOps
  #195 = Class              #194          // shapeless/syntax/HListOps
  #196 = Utf8               (Lshapeless/ops/hlist$Init;)Lshapeless/HList;
  #197 = NameAndType        #54:#196      // init:(Lshapeless/ops/hlist$Init;)Lshapeless/HList;
  #198 = Methodref          #195.#197     // shapeless/syntax/HListOps.init:(Lshapeless/ops/hlist$Init;)Lshapeless/HList;
  #199 = NameAndType        #44:#40       // tpp$2:Lshapeless/ops/hlist$Tupler;
  #200 = Fieldref           #2.#199       // shapeless/ProductPrismBuilder$$anon$10.tpp$2:Lshapeless/ops/hlist$Tupler;
  #201 = Utf8               tupled
  #202 = Utf8               (Lshapeless/ops/hlist$Tupler;)Ljava/lang/Object;
  #203 = NameAndType        #201:#202     // tupled:(Lshapeless/ops/hlist$Tupler;)Ljava/lang/Object;
  #204 = Methodref          #195.#203     // shapeless/syntax/HListOps.tupled:(Lshapeless/ops/hlist$Tupler;)Ljava/lang/Object;
  #205 = Utf8               (Ljava/lang/Object;Ljava/lang/Object;)Ljava/lang/Object;
  #206 = NameAndType        #167:#205     // set:(Ljava/lang/Object;Ljava/lang/Object;)Ljava/lang/Object;
  #207 = InterfaceMethodref #7.#206       // shapeless/ProductPrismBuilder.set:(Ljava/lang/Object;Ljava/lang/Object;)Ljava/lang/Object;
  #208 = NameAndType        #45:#46       // last$2:Lshapeless/ops/hlist$Last;
  #209 = Fieldref           #2.#208       // shapeless/ProductPrismBuilder$$anon$10.last$2:Lshapeless/ops/hlist$Last;
  #210 = Utf8               (Lshapeless/ops/hlist$Last;)Ljava/lang/Object;
  #211 = NameAndType        #55:#210      // last:(Lshapeless/ops/hlist$Last;)Ljava/lang/Object;
  #212 = Methodref          #195.#211     // shapeless/syntax/HListOps.last:(Lshapeless/ops/hlist$Last;)Ljava/lang/Object;
  #213 = InterfaceMethodref #68.#206      // shapeless/Prism.set:(Ljava/lang/Object;Ljava/lang/Object;)Ljava/lang/Object;
  #214 = Utf8               l
  #215 = Utf8               Lshapeless/HList;
  #216 = Utf8               Lscala/Product;
  #217 = Utf8               a
  #218 = Utf8               scala/Product
  #219 = Class              #218          // scala/Product
  #220 = NameAndType        #167:#168     // set:(Ljava/lang/Object;Lscala/Product;)Ljava/lang/Object;
  #221 = Methodref          #2.#220       // shapeless/ProductPrismBuilder$$anon$10.set:(Ljava/lang/Object;Lscala/Product;)Ljava/lang/Object;
  #222 = Utf8               $anonfun$get$8
  #223 = Utf8               (Lshapeless/ProductPrismBuilder$$anon$10;Lscala/Product;Ljava/lang/Object;)Lscala/Product;
  #224 = Utf8               $this
  #225 = Utf8               init$2
  #226 = NameAndType        #35:#36       // genp$2:Lshapeless/Generic;
  #227 = Fieldref           #2.#226       // shapeless/ProductPrismBuilder$$anon$10.genp$2:Lshapeless/Generic;
  #228 = NameAndType        #37:#38       // pre$2:Lshapeless/ops/hlist$Prepend;
  #229 = Fieldref           #2.#228       // shapeless/ProductPrismBuilder$$anon$10.pre$2:Lshapeless/ops/hlist$Prepend;
  #230 = Utf8               $colon$plus
  #231 = Utf8               (Ljava/lang/Object;Lshapeless/ops/hlist$Prepend;)Lshapeless/HList;
  #232 = NameAndType        #230:#231     // $colon$plus:(Ljava/lang/Object;Lshapeless/ops/hlist$Prepend;)Lshapeless/HList;
  #233 = Methodref          #195.#232     // shapeless/syntax/HListOps.$colon$plus:(Ljava/lang/Object;Lshapeless/ops/hlist$Prepend;)Lshapeless/HList;
  #234 = NameAndType        #39:#40       // tpq$2:Lshapeless/ops/hlist$Tupler;
  #235 = Fieldref           #2.#234       // shapeless/ProductPrismBuilder$$anon$10.tpq$2:Lshapeless/ops/hlist$Tupler;
  #236 = Utf8               c$1
  #237 = InterfaceMethodref #68.#138      // shapeless/Prism.get:(Ljava/lang/Object;)Lscala/Option;
  #238 = NameAndType        #222:#223     // $anonfun$get$8:(Lshapeless/ProductPrismBuilder$$anon$10;Lscala/Product;Ljava/lang/Object;)Lscala/Product;
  #239 = Methodref          #2.#238       // shapeless/ProductPrismBuilder$$anon$10.$anonfun$get$8:(Lshapeless/ProductPrismBuilder$$anon$10;Lscala/Product;Ljava/lang/Object;)Lscala/Product;
  #240 = MethodHandle       6:#239        // REF_invokeStatic shapeless/ProductPrismBuilder$$anon$10.$anonfun$get$8:(Lshapeless/ProductPrismBuilder$$anon$10;Lscala/Product;Ljava/lang/Object;)Lscala/Product;
  #241 = Utf8               (Ljava/lang/Object;)Lscala/Product;
  #242 = MethodType         #241          //  (Ljava/lang/Object;)Lscala/Product;
  #243 = Utf8               (Lshapeless/ProductPrismBuilder$$anon$10;Lscala/Product;)Lscala/Function1;
  #244 = NameAndType        #100:#243     // apply:(Lshapeless/ProductPrismBuilder$$anon$10;Lscala/Product;)Lscala/Function1;
  #245 = InvokeDynamic      #1:#244       // #1:apply:(Lshapeless/ProductPrismBuilder$$anon$10;Lscala/Product;)Lscala/Function1;
  #246 = Utf8               map
  #247 = NameAndType        #246:#164     // map:(Lscala/Function1;)Lscala/Option;
  #248 = Methodref          #162.#247     // scala/Option.map:(Lscala/Function1;)Lscala/Option;
  #249 = Utf8               <init>
  #250 = Utf8               (Lshapeless/ProductPrismBuilder;Lshapeless/Prism;Lshapeless/Generic;Lshapeless/ops/hlist$Prepend;Lshapeless/ops/hlist$Tupler;Lshapeless/Generic;Lshapeless/ops/hlist$Init;Lshapeless/ops/hlist$Tupler;Lshapeless/ops/hlist$Last;)V
  #251 = Utf8               ()V
  #252 = NameAndType        #249:#251     // "<init>":()V
  #253 = Methodref          #5.#252       // java/lang/Object."<init>":()V
  #254 = Utf8               $init$
  #255 = Utf8               (Lshapeless/LPPrism;)V
  #256 = NameAndType        #254:#255     // $init$:(Lshapeless/LPPrism;)V
  #257 = InterfaceMethodref #129.#256     // shapeless/LPPrism.$init$:(Lshapeless/LPPrism;)V
  #258 = Utf8               (Lshapeless/Prism;)V
  #259 = NameAndType        #254:#258     // $init$:(Lshapeless/Prism;)V
  #260 = InterfaceMethodref #68.#259      // shapeless/Prism.$init$:(Lshapeless/Prism;)V
  #261 = Utf8               (Lshapeless/ProductPrismBuilder;)V
  #262 = NameAndType        #254:#261     // $init$:(Lshapeless/ProductPrismBuilder;)V
  #263 = InterfaceMethodref #7.#262       // shapeless/ProductPrismBuilder.$init$:(Lshapeless/ProductPrismBuilder;)V
  #264 = Utf8               $deserializeLambda$
  #265 = Utf8               (Ljava/lang/invoke/SerializedLambda;)Ljava/lang/Object;
  #266 = Utf8               scala/runtime/LambdaDeserialize
  #267 = Class              #266          // scala/runtime/LambdaDeserialize
  #268 = Utf8               bootstrap
  #269 = Utf8               (Ljava/lang/invoke/MethodHandles$Lookup;Ljava/lang/String;Ljava/lang/invoke/MethodType;[Ljava/lang/invoke/MethodHandle;)Ljava/lang/invoke/CallSite;
  #270 = NameAndType        #268:#269     // bootstrap:(Ljava/lang/invoke/MethodHandles$Lookup;Ljava/lang/String;Ljava/lang/invoke/MethodType;[Ljava/lang/invoke/MethodHandle;)Ljava/lang/invoke/CallSite;
  #271 = Methodref          #267.#270     // scala/runtime/LambdaDeserialize.bootstrap:(Ljava/lang/invoke/MethodHandles$Lookup;Ljava/lang/String;Ljava/lang/invoke/MethodType;[Ljava/lang/invoke/MethodHandle;)Ljava/lang/invoke/CallSite;
  #272 = MethodHandle       6:#271        // REF_invokeStatic scala/runtime/LambdaDeserialize.bootstrap:(Ljava/lang/invoke/MethodHandles$Lookup;Ljava/lang/String;Ljava/lang/invoke/MethodType;[Ljava/lang/invoke/MethodHandle;)Ljava/lang/invoke/CallSite;
  #273 = Utf8               lambdaDeserialize
  #274 = NameAndType        #273:#265     // lambdaDeserialize:(Ljava/lang/invoke/SerializedLambda;)Ljava/lang/Object;
  #275 = InvokeDynamic      #2:#274       // #2:lambdaDeserialize:(Ljava/lang/invoke/SerializedLambda;)Ljava/lang/Object;
  #276 = Utf8               Code
  #277 = Utf8               LineNumberTable
  #278 = Utf8               LocalVariableTable
  #279 = Utf8               Signature
  #280 = Utf8               MethodParameters
  #281 = Utf8               StackMapTable
  #282 = Utf8               InnerClasses
  #283 = Utf8               EnclosingMethod
  #284 = Utf8               SourceFile
  #285 = Utf8               BootstrapMethods
  #286 = Utf8               ScalaInlineInfo
  #287 = Utf8               Scala
{
  private final shapeless.ProductPrismBuilder $outer;
    descriptor: Lshapeless/ProductPrismBuilder;
    flags: (0x1012) ACC_PRIVATE, ACC_FINAL, ACC_SYNTHETIC

  private final shapeless.Prism other$6;
    descriptor: Lshapeless/Prism;
    flags: (0x0012) ACC_PRIVATE, ACC_FINAL

  private final shapeless.Generic genp$2;
    descriptor: Lshapeless/Generic;
    flags: (0x0012) ACC_PRIVATE, ACC_FINAL

  private final shapeless.ops.hlist$Prepend pre$2;
    descriptor: Lshapeless/ops/hlist$Prepend;
    flags: (0x0012) ACC_PRIVATE, ACC_FINAL

  private final shapeless.ops.hlist$Tupler tpq$2;
    descriptor: Lshapeless/ops/hlist$Tupler;
    flags: (0x0012) ACC_PRIVATE, ACC_FINAL

  private final shapeless.Generic genq$2;
    descriptor: Lshapeless/Generic;
    flags: (0x0012) ACC_PRIVATE, ACC_FINAL

  private final shapeless.ops.hlist$Init init$3;
    descriptor: Lshapeless/ops/hlist$Init;
    flags: (0x0012) ACC_PRIVATE, ACC_FINAL

  private final shapeless.ops.hlist$Tupler tpp$2;
    descriptor: Lshapeless/ops/hlist$Tupler;
    flags: (0x0012) ACC_PRIVATE, ACC_FINAL

  private final shapeless.ops.hlist$Last last$2;
    descriptor: Lshapeless/ops/hlist$Last;
    flags: (0x0012) ACC_PRIVATE, ACC_FINAL

  public <T extends java.lang.Object, L extends shapeless.HList, LT extends shapeless.HList, Q extends scala.Product, QL extends shapeless.HList> shapeless.ProductPrismBuilder<C, Q> $tilde(shapeless.Prism<C, T>, shapeless.Generic<Q>, shapeless.ops.hlist$Tupler<L>, shapeless.ops.hlist$Prepend<L, shapeless.$colon$colon<T, shapeless.HNil>>, shapeless.ops.hlist$Tupler<LT>, shapeless.Generic<Q>, shapeless.ops.hlist$Init<QL>, shapeless.ops.hlist$Last<QL>);
    descriptor: (Lshapeless/Prism;Lshapeless/Generic;Lshapeless/ops/hlist$Tupler;Lshapeless/ops/hlist$Prepend;Lshapeless/ops/hlist$Tupler;Lshapeless/Generic;Lshapeless/ops/hlist$Init;Lshapeless/ops/hlist$Last;)Lshapeless/ProductPrismBuilder;
    flags: (0x0001) ACC_PUBLIC
    Code:
      stack=9, locals=9, args_size=9
         0: aload_0
         1: aload_1
         2: aload_2
         3: aload_3
         4: aload         4
         6: aload         5
         8: aload         6
        10: aload         7
        12: aload         8
        14: invokestatic  #59                 // InterfaceMethod shapeless/ProductPrismBuilder.$tilde$:(Lshapeless/ProductPrismBuilder;Lshapeless/Prism;Lshapeless/Generic;Lshapeless/ops/hlist$Tupler;Lshapeless/ops/hlist$Prepend;Lshapeless/ops/hlist$Tupler;Lshapeless/Generic;Lshapeless/ops/hlist$Init;Lshapeless/ops/hlist$Last;)Lshapeless/ProductPrismBuilder;
        17: areturn
      LineNumberTable:
        line 144: 0
      LocalVariableTable:
        Start  Length  Slot  Name   Signature
            0      18     0  this   Lshapeless/ProductPrismBuilder$$anon$10;
            0      18     1 other   Lshapeless/Prism;
            0      18     2  genp   Lshapeless/Generic;
            0      18     3   tpp   Lshapeless/ops/hlist$Tupler;
            0      18     4   pre   Lshapeless/ops/hlist$Prepend;
            0      18     5   tpq   Lshapeless/ops/hlist$Tupler;
            0      18     6  genq   Lshapeless/Generic;
            0      18     7  init   Lshapeless/ops/hlist$Init;
            0      18     8  last   Lshapeless/ops/hlist$Last;
    Signature: #47                          // <T:Ljava/lang/Object;L::Lshapeless/HList;LT::Lshapeless/HList;Q::Lscala/Product;QL::Lshapeless/HList;>(Lshapeless/Prism<TC;TT;>;Lshapeless/Generic<TQ;>;Lshapeless/ops/hlist$Tupler<TL;>;Lshapeless/ops/hlist$Prepend<TL;Lshapeless/$colon$colon<TT;Lshapeless/HNil;>;>;Lshapeless/ops/hlist$Tupler<TLT;>;Lshapeless/Generic<TQ;>;Lshapeless/ops/hlist$Init<TQL;>;Lshapeless/ops/hlist$Last<TQL;>;)Lshapeless/ProductPrismBuilder<TC;TQ;>;
    MethodParameters:
      Name                           Flags
      other                          final
      genp                           final
      tpp                            final
      pre                            final
      tpq                            final
      genq                           final
      init                           final
      last                           final

  public C modify(C, scala.Function1<Q, Q>);
    descriptor: (Ljava/lang/Object;Lscala/Function1;)Ljava/lang/Object;
    flags: (0x0001) ACC_PUBLIC
    Code:
      stack=3, locals=3, args_size=3
         0: aload_0
         1: aload_1
         2: aload_2
         3: invokestatic  #72                 // InterfaceMethod shapeless/Prism.modify$:(Lshapeless/Prism;Ljava/lang/Object;Lscala/Function1;)Ljava/lang/Object;
         6: areturn
      LineNumberTable:
        line 144: 0
      LocalVariableTable:
        Start  Length  Slot  Name   Signature
            0       7     0  this   Lshapeless/ProductPrismBuilder$$anon$10;
            0       7     1     s   Ljava/lang/Object;
            0       7     2     f   Lscala/Function1;
    Signature: #64                          // (TC;Lscala/Function1<TQ;TQ;>;)TC;
    MethodParameters:
      Name                           Flags
      s                              final
      f                              final

  public <T extends java.lang.Object> shapeless.Prism<T, Q> compose(shapeless.Lens<T, C>);
    descriptor: (Lshapeless/Lens;)Lshapeless/Prism;
    flags: (0x0001) ACC_PUBLIC
    Code:
      stack=2, locals=2, args_size=2
         0: aload_0
         1: aload_1
         2: invokestatic  #82                 // InterfaceMethod shapeless/Prism.compose$:(Lshapeless/Prism;Lshapeless/Lens;)Lshapeless/Prism;
         5: areturn
      LineNumberTable:
        line 144: 0
      LocalVariableTable:
        Start  Length  Slot  Name   Signature
            0       6     0  this   Lshapeless/ProductPrismBuilder$$anon$10;
            0       6     1     g   Lshapeless/Lens;
    Signature: #77                          // <T:Ljava/lang/Object;>(Lshapeless/Lens<TT;TC;>;)Lshapeless/Prism<TT;TQ;>;
    MethodParameters:
      Name                           Flags
      g                              final

  public <T extends java.lang.Object> shapeless.Prism<T, Q> compose(shapeless.Prism<T, C>);
    descriptor: (Lshapeless/Prism;)Lshapeless/Prism;
    flags: (0x0001) ACC_PUBLIC
    Code:
      stack=2, locals=2, args_size=2
         0: aload_0
         1: aload_1
         2: invokestatic  #88                 // InterfaceMethod shapeless/Prism.compose$:(Lshapeless/Prism;Lshapeless/Prism;)Lshapeless/Prism;
         5: areturn
      LineNumberTable:
        line 144: 0
      LocalVariableTable:
        Start  Length  Slot  Name   Signature
            0       6     0  this   Lshapeless/ProductPrismBuilder$$anon$10;
            0       6     1     g   Lshapeless/Prism;
    Signature: #85                          // <T:Ljava/lang/Object;>(Lshapeless/Prism<TT;TC;>;)Lshapeless/Prism<TT;TQ;>;
    MethodParameters:
      Name                           Flags
      g                              final

  public java.lang.Object selectDynamic(java.lang.String, shapeless.MkSelectDynamicOptic<shapeless.Prism<C, Q>, Q, scala.Symbol, scala.runtime.Nothing$>);
    descriptor: (Ljava/lang/String;Lshapeless/MkSelectDynamicOptic;)Ljava/lang/Object;
    flags: (0x0001) ACC_PUBLIC
    Code:
      stack=3, locals=3, args_size=3
         0: aload_0
         1: aload_1
         2: aload_2
         3: invokestatic  #97                 // InterfaceMethod shapeless/Prism.selectDynamic$:(Lshapeless/Prism;Ljava/lang/String;Lshapeless/MkSelectDynamicOptic;)Ljava/lang/Object;
         6: areturn
      LineNumberTable:
        line 144: 0
      LocalVariableTable:
        Start  Length  Slot  Name   Signature
            0       7     0  this   Lshapeless/ProductPrismBuilder$$anon$10;
            0       7     1     k   Ljava/lang/String;
            0       7     2 mkPrism   Lshapeless/MkSelectDynamicOptic;
    Signature: #91                          // (Ljava/lang/String;Lshapeless/MkSelectDynamicOptic<Lshapeless/Prism<TC;TQ;>;TQ;Lscala/Symbol;Lscala/runtime/Nothing$;>;)Ljava/lang/Object;
    MethodParameters:
      Name                           Flags
      k                              final
      mkPrism                        final

  public <B extends java.lang.Object> shapeless.Prism<C, B> apply(shapeless.MkCtorPrism<Q, B>);
    descriptor: (Lshapeless/MkCtorPrism;)Lshapeless/Prism;
    flags: (0x0001) ACC_PUBLIC
    Code:
      stack=2, locals=2, args_size=2
         0: aload_0
         1: aload_1
         2: invokestatic  #106                // InterfaceMethod shapeless/Prism.apply$:(Lshapeless/Prism;Lshapeless/MkCtorPrism;)Lshapeless/Prism;
         5: areturn
      LineNumberTable:
        line 144: 0
      LocalVariableTable:
        Start  Length  Slot  Name   Signature
            0       6     0  this   Lshapeless/ProductPrismBuilder$$anon$10;
            0       6     1 mkPrism   Lshapeless/MkCtorPrism;
    Signature: #102                         // <B:Ljava/lang/Object;>(Lshapeless/MkCtorPrism<TQ;TB;>;)Lshapeless/Prism<TC;TB;>;
    MethodParameters:
      Name                           Flags
      mkPrism                        final

  public scala.Option<Q> unapply(C);
    descriptor: (Ljava/lang/Object;)Lscala/Option;
    flags: (0x0001) ACC_PUBLIC
    Code:
      stack=2, locals=2, args_size=2
         0: aload_0
         1: aload_1
         2: invokestatic  #114                // InterfaceMethod shapeless/Prism.unapply$:(Lshapeless/Prism;Ljava/lang/Object;)Lscala/Option;
         5: areturn
      LineNumberTable:
        line 144: 0
      LocalVariableTable:
        Start  Length  Slot  Name   Signature
            0       6     0  this   Lshapeless/ProductPrismBuilder$$anon$10;
            0       6     1     s   Ljava/lang/Object;
    Signature: #110                         // (TC;)Lscala/Option<TQ;>;
    MethodParameters:
      Name                           Flags
      s                              final

  public <B extends java.lang.Object> shapeless.ProductPrismBuilder<C, scala.Tuple2<Q, B>> $tilde(shapeless.Lens<C, B>);
    descriptor: (Lshapeless/Lens;)Lshapeless/ProductPrismBuilder;
    flags: (0x0001) ACC_PUBLIC
    Code:
      stack=2, locals=2, args_size=2
         0: aload_0
         1: aload_1
         2: invokestatic  #119                // InterfaceMethod shapeless/Prism.$tilde$:(Lshapeless/Prism;Lshapeless/Lens;)Lshapeless/ProductPrismBuilder;
         5: areturn
      LineNumberTable:
        line 144: 0
      LocalVariableTable:
        Start  Length  Slot  Name   Signature
            0       6     0  this   Lshapeless/ProductPrismBuilder$$anon$10;
            0       6     1 other   Lshapeless/Lens;
    Signature: #116                         // <B:Ljava/lang/Object;>(Lshapeless/Lens<TC;TB;>;)Lshapeless/ProductPrismBuilder<TC;Lscala/Tuple2<TQ;TB;>;>;
    MethodParameters:
      Name                           Flags
      other                          final

  public <B extends java.lang.Object> shapeless.ProductPrismBuilder<C, scala.Tuple2<Q, B>> $tilde(shapeless.Prism<C, B>);
    descriptor: (Lshapeless/Prism;)Lshapeless/ProductPrismBuilder;
    flags: (0x0001) ACC_PUBLIC
    Code:
      stack=2, locals=2, args_size=2
         0: aload_0
         1: aload_1
         2: invokestatic  #124                // InterfaceMethod shapeless/Prism.$tilde$:(Lshapeless/Prism;Lshapeless/Prism;)Lshapeless/ProductPrismBuilder;
         5: areturn
      LineNumberTable:
        line 144: 0
      LocalVariableTable:
        Start  Length  Slot  Name   Signature
            0       6     0  this   Lshapeless/ProductPrismBuilder$$anon$10;
            0       6     1 other   Lshapeless/Prism;
    Signature: #121                         // <B:Ljava/lang/Object;>(Lshapeless/Prism<TC;TB;>;)Lshapeless/ProductPrismBuilder<TC;Lscala/Tuple2<TQ;TB;>;>;
    MethodParameters:
      Name                           Flags
      other                          final

  public <B extends java.lang.Object> java.lang.Object selectDynamic(java.lang.String, shapeless.MkSelectDynamicOptic<shapeless.Prism<C, Q>, Q, scala.Symbol, B>, scala.DummyImplicit);
    descriptor: (Ljava/lang/String;Lshapeless/MkSelectDynamicOptic;Lscala/DummyImplicit;)Ljava/lang/Object;
    flags: (0x0001) ACC_PUBLIC
    Code:
      stack=4, locals=4, args_size=4
         0: aload_0
         1: aload_1
         2: aload_2
         3: aload_3
         4: invokestatic  #132                // InterfaceMethod shapeless/LPPrism.selectDynamic$:(Lshapeless/LPPrism;Ljava/lang/String;Lshapeless/MkSelectDynamicOptic;Lscala/DummyImplicit;)Ljava/lang/Object;
         7: areturn
      LineNumberTable:
        line 144: 0
      LocalVariableTable:
        Start  Length  Slot  Name   Signature
            0       8     0  this   Lshapeless/ProductPrismBuilder$$anon$10;
            0       8     1     k   Ljava/lang/String;
            0       8     2 mkPrism   Lshapeless/MkSelectDynamicOptic;
            0       8     3 dummy   Lscala/DummyImplicit;
    Signature: #126                         // <B:Ljava/lang/Object;>(Ljava/lang/String;Lshapeless/MkSelectDynamicOptic<Lshapeless/Prism<TC;TQ;>;TQ;Lscala/Symbol;TB;>;Lscala/DummyImplicit;)Ljava/lang/Object;
    MethodParameters:
      Name                           Flags
      k                              final
      mkPrism                        final
      dummy                          final

  public scala.Option<Q> get(C);
    descriptor: (Ljava/lang/Object;)Lscala/Option;
    flags: (0x0001) ACC_PUBLIC
    Code:
      stack=3, locals=2, args_size=2
         0: aload_0
         1: getfield      #137                // Field $outer:Lshapeless/ProductPrismBuilder;
         4: aload_1
         5: invokeinterface #139,  2          // InterfaceMethod shapeless/ProductPrismBuilder.get:(Ljava/lang/Object;)Lscala/Option;
        10: aload_0
        11: aload_1
        12: invokedynamic #160,  0            // InvokeDynamic #0:apply:(Lshapeless/ProductPrismBuilder$$anon$10;Ljava/lang/Object;)Lscala/Function1;
        17: invokevirtual #166                // Method scala/Option.flatMap:(Lscala/Function1;)Lscala/Option;
        20: areturn
      LineNumberTable:
        line 147: 0
      LocalVariableTable:
        Start  Length  Slot  Name   Signature
            0      21     0  this   Lshapeless/ProductPrismBuilder$$anon$10;
            0      21     1     c   Ljava/lang/Object;
    Signature: #110                         // (TC;)Lscala/Option<TQ;>;
    MethodParameters:
      Name                           Flags
      c                              final

  public C set(C, Q);
    descriptor: (Ljava/lang/Object;Lscala/Product;)Ljava/lang/Object;
    flags: (0x0001) ACC_PUBLIC
    Code:
      stack=6, locals=4, args_size=3
         0: aload_0
         1: getfield      #172                // Field genq$2:Lshapeless/Generic;
         4: aload_2
         5: invokeinterface #177,  2          // InterfaceMethod shapeless/Generic.to:(Ljava/lang/Object;)Ljava/lang/Object;
        10: checkcast     #179                // class shapeless/HList
        13: astore_3
        14: aload_0
        15: getfield      #181                // Field other$6:Lshapeless/Prism;
        18: aload_0
        19: getfield      #137                // Field $outer:Lshapeless/ProductPrismBuilder;
        22: aload_1
        23: getstatic     #187                // Field shapeless/HList$.MODULE$:Lshapeless/HList$;
        26: getstatic     #187                // Field shapeless/HList$.MODULE$:Lshapeless/HList$;
        29: aload_3
        30: invokevirtual #191                // Method shapeless/HList$.hlistOps:(Lshapeless/HList;)Lshapeless/syntax/HListOps;
        33: aload_0
        34: getfield      #193                // Field init$3:Lshapeless/ops/hlist$Init;
        37: invokevirtual #198                // Method shapeless/syntax/HListOps.init:(Lshapeless/ops/hlist$Init;)Lshapeless/HList;
        40: invokevirtual #191                // Method shapeless/HList$.hlistOps:(Lshapeless/HList;)Lshapeless/syntax/HListOps;
        43: aload_0
        44: getfield      #200                // Field tpp$2:Lshapeless/ops/hlist$Tupler;
        47: invokevirtual #204                // Method shapeless/syntax/HListOps.tupled:(Lshapeless/ops/hlist$Tupler;)Ljava/lang/Object;
        50: invokeinterface #207,  3          // InterfaceMethod shapeless/ProductPrismBuilder.set:(Ljava/lang/Object;Ljava/lang/Object;)Ljava/lang/Object;
        55: getstatic     #187                // Field shapeless/HList$.MODULE$:Lshapeless/HList$;
        58: aload_3
        59: invokevirtual #191                // Method shapeless/HList$.hlistOps:(Lshapeless/HList;)Lshapeless/syntax/HListOps;
        62: aload_0
        63: getfield      #209                // Field last$2:Lshapeless/ops/hlist$Last;
        66: invokevirtual #212                // Method shapeless/syntax/HListOps.last:(Lshapeless/ops/hlist$Last;)Ljava/lang/Object;
        69: invokeinterface #213,  3          // InterfaceMethod shapeless/Prism.set:(Ljava/lang/Object;Ljava/lang/Object;)Ljava/lang/Object;
        74: areturn
      LineNumberTable:
        line 152: 0
        line 153: 14
      LocalVariableTable:
        Start  Length  Slot  Name   Signature
           13      61     3     l   Lshapeless/HList;
            0      75     0  this   Lshapeless/ProductPrismBuilder$$anon$10;
            0      75     1     c   Ljava/lang/Object;
            0      75     2     q   Lscala/Product;
    Signature: #169                         // (TC;TQ;)TC;
    MethodParameters:
      Name                           Flags
      c                              final
      q                              final

  public java.lang.Object set(java.lang.Object, java.lang.Object);
    descriptor: (Ljava/lang/Object;Ljava/lang/Object;)Ljava/lang/Object;
    flags: (0x1041) ACC_PUBLIC, ACC_BRIDGE, ACC_SYNTHETIC
    Code:
      stack=3, locals=3, args_size=3
         0: aload_0
         1: aload_1
         2: aload_2
         3: checkcast     #219                // class scala/Product
         6: invokevirtual #221                // Method set:(Ljava/lang/Object;Lscala/Product;)Ljava/lang/Object;
         9: areturn
      LineNumberTable:
        line 144: 0
      LocalVariableTable:
        Start  Length  Slot  Name   Signature
            0      10     0  this   Lshapeless/ProductPrismBuilder$$anon$10;
            0      10     1     s   Ljava/lang/Object;
            0      10     2     a   Ljava/lang/Object;
    MethodParameters:
      Name                           Flags
      s                              final
      a                              final

  public static final scala.Product $anonfun$get$8(shapeless.ProductPrismBuilder$$anon$10, scala.Product, java.lang.Object);
    descriptor: (Lshapeless/ProductPrismBuilder$$anon$10;Lscala/Product;Ljava/lang/Object;)Lscala/Product;
    flags: (0x1019) ACC_PUBLIC, ACC_STATIC, ACC_FINAL, ACC_SYNTHETIC
    Code:
      stack=4, locals=3, args_size=3
         0: getstatic     #187                // Field shapeless/HList$.MODULE$:Lshapeless/HList$;
         3: getstatic     #187                // Field shapeless/HList$.MODULE$:Lshapeless/HList$;
         6: aload_0
         7: getfield      #227                // Field genp$2:Lshapeless/Generic;
        10: aload_1
        11: invokeinterface #177,  2          // InterfaceMethod shapeless/Generic.to:(Ljava/lang/Object;)Ljava/lang/Object;
        16: checkcast     #179                // class shapeless/HList
        19: invokevirtual #191                // Method shapeless/HList$.hlistOps:(Lshapeless/HList;)Lshapeless/syntax/HListOps;
        22: aload_2
        23: aload_0
        24: getfield      #229                // Field pre$2:Lshapeless/ops/hlist$Prepend;
        27: invokevirtual #233                // Method shapeless/syntax/HListOps.$colon$plus:(Ljava/lang/Object;Lshapeless/ops/hlist$Prepend;)Lshapeless/HList;
        30: invokevirtual #191                // Method shapeless/HList$.hlistOps:(Lshapeless/HList;)Lshapeless/syntax/HListOps;
        33: aload_0
        34: getfield      #235                // Field tpq$2:Lshapeless/ops/hlist$Tupler;
        37: invokevirtual #204                // Method shapeless/syntax/HListOps.tupled:(Lshapeless/ops/hlist$Tupler;)Ljava/lang/Object;
        40: checkcast     #219                // class scala/Product
        43: areturn
      LineNumberTable:
        line 149: 0
      LocalVariableTable:
        Start  Length  Slot  Name   Signature
            0      44     0 $this   Lshapeless/ProductPrismBuilder$$anon$10;
            0      44     1 init$2   Lscala/Product;
            0      44     2  last   Ljava/lang/Object;
    MethodParameters:
      Name                           Flags
      $this                          final synthetic
      init$2                         final
      last                           final

  public static final scala.Option $anonfun$get$7(shapeless.ProductPrismBuilder$$anon$10, java.lang.Object, scala.Product);
    descriptor: (Lshapeless/ProductPrismBuilder$$anon$10;Ljava/lang/Object;Lscala/Product;)Lscala/Option;
    flags: (0x1019) ACC_PUBLIC, ACC_STATIC, ACC_FINAL, ACC_SYNTHETIC
    Code:
      stack=3, locals=3, args_size=3
         0: aload_0
         1: getfield      #181                // Field other$6:Lshapeless/Prism;
         4: aload_1
         5: invokeinterface #237,  2          // InterfaceMethod shapeless/Prism.get:(Ljava/lang/Object;)Lscala/Option;
        10: aload_0
        11: aload_2
        12: invokedynamic #245,  0            // InvokeDynamic #1:apply:(Lshapeless/ProductPrismBuilder$$anon$10;Lscala/Product;)Lscala/Function1;
        17: invokevirtual #248                // Method scala/Option.map:(Lscala/Function1;)Lscala/Option;
        20: areturn
      LineNumberTable:
        line 148: 0
      LocalVariableTable:
        Start  Length  Slot  Name   Signature
            0      21     0 $this   Lshapeless/ProductPrismBuilder$$anon$10;
            0      21     1   c$1   Ljava/lang/Object;
            0      21     2  init   Lscala/Product;
    MethodParameters:
      Name                           Flags
      $this                          final synthetic
      c$1                            final
      init                           final

  public shapeless.ProductPrismBuilder$$anon$10(shapeless.ProductPrismBuilder, shapeless.Prism, shapeless.Generic, shapeless.ops.hlist$Prepend, shapeless.ops.hlist$Tupler, shapeless.Generic, shapeless.ops.hlist$Init, shapeless.ops.hlist$Tupler, shapeless.ops.hlist$Last);
    descriptor: (Lshapeless/ProductPrismBuilder;Lshapeless/Prism;Lshapeless/Generic;Lshapeless/ops/hlist$Prepend;Lshapeless/ops/hlist$Tupler;Lshapeless/Generic;Lshapeless/ops/hlist$Init;Lshapeless/ops/hlist$Tupler;Lshapeless/ops/hlist$Last;)V
    flags: (0x0001) ACC_PUBLIC
    Code:
      stack=2, locals=10, args_size=10
         0: aload_1
         1: ifnonnull     6
         4: aconst_null
         5: athrow
         6: aload_0
         7: aload_1
         8: putfield      #137                // Field $outer:Lshapeless/ProductPrismBuilder;
        11: aload_0
        12: aload_2
        13: putfield      #181                // Field other$6:Lshapeless/Prism;
        16: aload_0
        17: aload_3
        18: putfield      #227                // Field genp$2:Lshapeless/Generic;
        21: aload_0
        22: aload         4
        24: putfield      #229                // Field pre$2:Lshapeless/ops/hlist$Prepend;
        27: aload_0
        28: aload         5
        30: putfield      #235                // Field tpq$2:Lshapeless/ops/hlist$Tupler;
        33: aload_0
        34: aload         6
        36: putfield      #172                // Field genq$2:Lshapeless/Generic;
        39: aload_0
        40: aload         7
        42: putfield      #193                // Field init$3:Lshapeless/ops/hlist$Init;
        45: aload_0
        46: aload         8
        48: putfield      #200                // Field tpp$2:Lshapeless/ops/hlist$Tupler;
        51: aload_0
        52: aload         9
        54: putfield      #209                // Field last$2:Lshapeless/ops/hlist$Last;
        57: aload_0
        58: invokespecial #253                // Method java/lang/Object."<init>":()V
        61: aload_0
        62: invokestatic  #257                // InterfaceMethod shapeless/LPPrism.$init$:(Lshapeless/LPPrism;)V
        65: aload_0
        66: invokestatic  #260                // InterfaceMethod shapeless/Prism.$init$:(Lshapeless/Prism;)V
        69: aload_0
        70: invokestatic  #263                // InterfaceMethod shapeless/ProductPrismBuilder.$init$:(Lshapeless/ProductPrismBuilder;)V
        73: return
      StackMapTable: number_of_entries = 1
        frame_type = 6 /* same */
      LineNumberTable:
        line 144: 0
        line 135: 11
        line 137: 16
        line 139: 21
        line 140: 27
        line 141: 33
        line 142: 39
        line 138: 45
        line 143: 51
        line 144: 57
      LocalVariableTable:
        Start  Length  Slot  Name   Signature
            0      74     0  this   Lshapeless/ProductPrismBuilder$$anon$10;
            0      74     1 $outer   Lshapeless/ProductPrismBuilder;
            0      74     2 other$6   Lshapeless/Prism;
            0      74     3 genp$2   Lshapeless/Generic;
            0      74     4 pre$2   Lshapeless/ops/hlist$Prepend;
            0      74     5 tpq$2   Lshapeless/ops/hlist$Tupler;
            0      74     6 genq$2   Lshapeless/Generic;
            0      74     7 init$3   Lshapeless/ops/hlist$Init;
            0      74     8 tpp$2   Lshapeless/ops/hlist$Tupler;
            0      74     9 last$2   Lshapeless/ops/hlist$Last;
    MethodParameters:
      Name                           Flags
      $outer                         final synthetic
      other$6                        final
      genp$2                         final
      pre$2                          final
      tpq$2                          final
      genq$2                         final
      init$3                         final
      tpp$2                          final
      last$2                         final

  private static java.lang.Object $deserializeLambda$(java.lang.invoke.SerializedLambda);
    descriptor: (Ljava/lang/invoke/SerializedLambda;)Ljava/lang/Object;
    flags: (0x100a) ACC_PRIVATE, ACC_STATIC, ACC_SYNTHETIC
    Code:
      stack=1, locals=1, args_size=1
         0: aload_0
         1: invokedynamic #275,  0            // InvokeDynamic #2:lambdaDeserialize:(Ljava/lang/invoke/SerializedLambda;)Ljava/lang/Object;
         6: areturn
}
InnerClasses:
  public static final #16= #13 of #15;    // Lookup=class java/lang/invoke/MethodHandles$Lookup of class java/lang/invoke/MethodHandles
  public final #2;                        // class shapeless/ProductPrismBuilder$$anon$10
  public static #21= #18 of #20;          // Init=class shapeless/ops/hlist$Init of class shapeless/ops/hlist
  public static #24= #23 of #20;          // Last=class shapeless/ops/hlist$Last of class shapeless/ops/hlist
  public static #27= #26 of #20;          // Prepend=class shapeless/ops/hlist$Prepend of class shapeless/ops/hlist
  public static #30= #29 of #20;          // Tupler=class shapeless/ops/hlist$Tupler of class shapeless/ops/hlist
EnclosingMethod: #7.#11                 // shapeless.ProductPrismBuilder.$tilde
Signature: #3                           // Ljava/lang/Object;Lshapeless/ProductPrismBuilder<TC;TQ;>;
SourceFile: "lenses.scala"
BootstrapMethods:
  0: #157 REF_invokeStatic java/lang/invoke/LambdaMetafactory.altMetafactory:(Ljava/lang/invoke/MethodHandles$Lookup;Ljava/lang/String;Ljava/lang/invoke/MethodType;[Ljava/lang/Object;)Ljava/lang/invoke/CallSite;
    Method arguments:
      #141 (Ljava/lang/Object;)Ljava/lang/Object;
      #146 REF_invokeStatic shapeless/ProductPrismBuilder$$anon$10.$anonfun$get$7:(Lshapeless/ProductPrismBuilder$$anon$10;Ljava/lang/Object;Lscala/Product;)Lscala/Option;
      #148 (Lscala/Product;)Lscala/Option;
      #149 5
      #150 1
      #148 (Lscala/Product;)Lscala/Option;
  1: #157 REF_invokeStatic java/lang/invoke/LambdaMetafactory.altMetafactory:(Ljava/lang/invoke/MethodHandles$Lookup;Ljava/lang/String;Ljava/lang/invoke/MethodType;[Ljava/lang/Object;)Ljava/lang/invoke/CallSite;
    Method arguments:
      #141 (Ljava/lang/Object;)Ljava/lang/Object;
      #240 REF_invokeStatic shapeless/ProductPrismBuilder$$anon$10.$anonfun$get$8:(Lshapeless/ProductPrismBuilder$$anon$10;Lscala/Product;Ljava/lang/Object;)Lscala/Product;
      #242 (Ljava/lang/Object;)Lscala/Product;
      #149 5
      #150 1
      #242 (Ljava/lang/Object;)Lscala/Product;
  2: #272 REF_invokeStatic scala/runtime/LambdaDeserialize.bootstrap:(Ljava/lang/invoke/MethodHandles$Lookup;Ljava/lang/String;Ljava/lang/invoke/MethodType;[Ljava/lang/invoke/MethodHandle;)Ljava/lang/invoke/CallSite;
    Method arguments:
      #146 REF_invokeStatic shapeless/ProductPrismBuilder$$anon$10.$anonfun$get$7:(Lshapeless/ProductPrismBuilder$$anon$10;Ljava/lang/Object;Lscala/Product;)Lscala/Option;
      #240 REF_invokeStatic shapeless/ProductPrismBuilder$$anon$10.$anonfun$get$8:(Lshapeless/ProductPrismBuilder$$anon$10;Lscala/Product;Ljava/lang/Object;)Lscala/Product;
  ScalaInlineInfo: length = 0x54 (unknown attribute)
   01 01 00 10 00 8E 00 8F 01 00 DE 00 DF 01 00 09
   00 73 01 00 09 00 78 01 00 09 00 0A 01 00 F9 00
   FA 01 00 64 00 65 01 00 4B 00 4C 01 00 4B 00 54
   01 00 86 00 6D 01 00 3E 00 3F 01 00 59 00 5A 01
   00 59 00 7D 01 00 A7 00 CD 01 00 A7 00 A8 01 00
   6C 00 6D 01
  Scala: length = 0x0 (unknown attribute)

