Classfile /Users/mw/Projects/slang-braindump/.jar/jar11/assemble/slang-braindump/assemble/content/shapeless/ScalaVersionSpecifics$macrocompat$.class
  Last modified May 29, 2022; size 661 bytes
  SHA-256 checksum 2963eb1bee20dfbcb4ba4fddf1f064fbd5fcad1c44bafd32e48c0f4fe5f208ce
  Compiled from "versionspecifics.scala"
public class shapeless.ScalaVersionSpecifics$macrocompat$
  minor version: 0
  major version: 52
  flags: (0x0021) ACC_PUBLIC, ACC_SUPER
  this_class: #2                          // shapeless/ScalaVersionSpecifics$macrocompat$
  super_class: #4                         // java/lang/Object
  interfaces: 0, fields: 0, methods: 1, attributes: 4
Constant pool:
   #1 = Utf8               shapeless/ScalaVersionSpecifics$macrocompat$
   #2 = Class              #1             // shapeless/ScalaVersionSpecifics$macrocompat$
   #3 = Utf8               java/lang/Object
   #4 = Class              #3             // java/lang/Object
   #5 = Utf8               versionspecifics.scala
   #6 = Utf8               shapeless/ScalaVersionSpecifics
   #7 = Class              #6             // shapeless/ScalaVersionSpecifics
   #8 = Utf8               macrocompat$
   #9 = Utf8               shapeless/ScalaVersionSpecifics$macrocompat$bundle
  #10 = Class              #9             // shapeless/ScalaVersionSpecifics$macrocompat$bundle
  #11 = Utf8               bundle
  #12 = Utf8               <init>
  #13 = Utf8               (Lshapeless/ScalaVersionSpecifics;)V
  #14 = Utf8               $outer
  #15 = Utf8               ()V
  #16 = NameAndType        #12:#15        // "<init>":()V
  #17 = Methodref          #4.#16         // java/lang/Object."<init>":()V
  #18 = Utf8               this
  #19 = Utf8               Lshapeless/ScalaVersionSpecifics$macrocompat$;
  #20 = Utf8               Lshapeless/ScalaVersionSpecifics;
  #21 = Utf8               Code
  #22 = Utf8               LineNumberTable
  #23 = Utf8               LocalVariableTable
  #24 = Utf8               MethodParameters
  #25 = Utf8               InnerClasses
  #26 = Utf8               SourceFile
  #27 = Utf8               ScalaInlineInfo
  #28 = Utf8               Scala
{
  public shapeless.ScalaVersionSpecifics$macrocompat$(shapeless.ScalaVersionSpecifics);
    descriptor: (Lshapeless/ScalaVersionSpecifics;)V
    flags: (0x0001) ACC_PUBLIC
    Code:
      stack=1, locals=2, args_size=2
         0: aload_0
         1: invokespecial #17                 // Method java/lang/Object."<init>":()V
         4: return
      LineNumberTable:
        line 38: 0
        line 35: 4
      LocalVariableTable:
        Start  Length  Slot  Name   Signature
            0       5     0  this   Lshapeless/ScalaVersionSpecifics$macrocompat$;
            0       5     1 $outer   Lshapeless/ScalaVersionSpecifics;
    MethodParameters:
      Name                           Flags
      $outer                         final synthetic
}
InnerClasses:
  public #8= #2 of #7;                    // macrocompat$=class shapeless/ScalaVersionSpecifics$macrocompat$ of class shapeless/ScalaVersionSpecifics
  public #11= #10 of #2;                  // bundle=class shapeless/ScalaVersionSpecifics$macrocompat$bundle of class shapeless/ScalaVersionSpecifics$macrocompat$
SourceFile: "versionspecifics.scala"
  ScalaInlineInfo: length = 0x9 (unknown attribute)
   01 01 00 01 00 0C 00 0D 01
  Scala: length = 0x0 (unknown attribute)

