Classfile /Users/mw/Projects/slang-braindump/.jar/jar11/assemble/slang-braindump/assemble/content/shapeless/Segment$.class
  Last modified May 29, 2022; size 1038 bytes
  SHA-256 checksum 7c9b8a5ff7243ce4fd14ebd53e3ff619bc2d932b496422f34ce00b51a78a0bae
  Compiled from "lenses.scala"
public final class shapeless.Segment$ implements shapeless.LowPrioritySegment
  minor version: 0
  major version: 52
  flags: (0x0031) ACC_PUBLIC, ACC_FINAL, ACC_SUPER
  this_class: #2                          // shapeless/Segment$
  super_class: #4                         // java/lang/Object
  interfaces: 1, fields: 1, methods: 4, attributes: 4
Constant pool:
   #1 = Utf8               shapeless/Segment$
   #2 = Class              #1             // shapeless/Segment$
   #3 = Utf8               java/lang/Object
   #4 = Class              #3             // java/lang/Object
   #5 = Utf8               shapeless/LowPrioritySegment
   #6 = Class              #5             // shapeless/LowPrioritySegment
   #7 = Utf8               lenses.scala
   #8 = Utf8               shapeless/Segment$$anon$44
   #9 = Class              #8             // shapeless/Segment$$anon$44
  #10 = Utf8               MODULE$
  #11 = Utf8               Lshapeless/Segment$;
  #12 = Utf8               <clinit>
  #13 = Utf8               ()V
  #14 = Utf8               <init>
  #15 = NameAndType        #14:#13        // "<init>":()V
  #16 = Methodref          #2.#15         // shapeless/Segment$."<init>":()V
  #17 = NameAndType        #10:#11        // MODULE$:Lshapeless/Segment$;
  #18 = Fieldref           #2.#17         // shapeless/Segment$.MODULE$:Lshapeless/Segment$;
  #19 = Utf8               $init$
  #20 = Utf8               (Lshapeless/LowPrioritySegment;)V
  #21 = NameAndType        #19:#20        // $init$:(Lshapeless/LowPrioritySegment;)V
  #22 = InterfaceMethodref #6.#21         // shapeless/LowPrioritySegment.$init$:(Lshapeless/LowPrioritySegment;)V
  #23 = Utf8               two
  #24 = Utf8               ()Lshapeless/Segment;
  #25 = Utf8               <P:Ljava/lang/Object;S:Ljava/lang/Object;T::Lshapeless/HList;>()Lshapeless/Segment<TP;TS;TT;>;
  #26 = Utf8               two$
  #27 = Utf8               (Lshapeless/LowPrioritySegment;)Lshapeless/Segment;
  #28 = NameAndType        #26:#27        // two$:(Lshapeless/LowPrioritySegment;)Lshapeless/Segment;
  #29 = InterfaceMethodref #6.#28         // shapeless/LowPrioritySegment.two$:(Lshapeless/LowPrioritySegment;)Lshapeless/Segment;
  #30 = Utf8               this
  #31 = Utf8               one
  #32 = Utf8               <P:Ljava/lang/Object;T::Lshapeless/HList;>()Lshapeless/Segment<TP;Lscala/runtime/Nothing$;TT;>;
  #33 = Methodref          #9.#15         // shapeless/Segment$$anon$44."<init>":()V
  #34 = Methodref          #4.#15         // java/lang/Object."<init>":()V
  #35 = Utf8               Code
  #36 = Utf8               LineNumberTable
  #37 = Utf8               LocalVariableTable
  #38 = Utf8               Signature
  #39 = Utf8               InnerClasses
  #40 = Utf8               SourceFile
  #41 = Utf8               ScalaInlineInfo
  #42 = Utf8               Scala
{
  public static final shapeless.Segment$ MODULE$;
    descriptor: Lshapeless/Segment$;
    flags: (0x0019) ACC_PUBLIC, ACC_STATIC, ACC_FINAL

  public static {};
    descriptor: ()V
    flags: (0x0009) ACC_PUBLIC, ACC_STATIC
    Code:
      stack=2, locals=0, args_size=0
         0: new           #2                  // class shapeless/Segment$
         3: dup
         4: invokespecial #16                 // Method "<init>":()V
         7: putstatic     #18                 // Field MODULE$:Lshapeless/Segment$;
        10: getstatic     #18                 // Field MODULE$:Lshapeless/Segment$;
        13: invokestatic  #22                 // InterfaceMethod shapeless/LowPrioritySegment.$init$:(Lshapeless/LowPrioritySegment;)V
        16: return
      LineNumberTable:
        line 546: 0

  public <P extends java.lang.Object, S extends java.lang.Object, T extends shapeless.HList> shapeless.Segment<P, S, T> two();
    descriptor: ()Lshapeless/Segment;
    flags: (0x0001) ACC_PUBLIC
    Code:
      stack=1, locals=1, args_size=1
         0: aload_0
         1: invokestatic  #29                 // InterfaceMethod shapeless/LowPrioritySegment.two$:(Lshapeless/LowPrioritySegment;)Lshapeless/Segment;
         4: areturn
      LineNumberTable:
        line 546: 0
      LocalVariableTable:
        Start  Length  Slot  Name   Signature
            0       5     0  this   Lshapeless/Segment$;
    Signature: #25                          // <P:Ljava/lang/Object;S:Ljava/lang/Object;T::Lshapeless/HList;>()Lshapeless/Segment<TP;TS;TT;>;

  public <P extends java.lang.Object, T extends shapeless.HList> shapeless.Segment<P, scala.runtime.Nothing$, T> one();
    descriptor: ()Lshapeless/Segment;
    flags: (0x0001) ACC_PUBLIC
    Code:
      stack=2, locals=1, args_size=1
         0: new           #9                  // class shapeless/Segment$$anon$44
         3: dup
         4: invokespecial #33                 // Method shapeless/Segment$$anon$44."<init>":()V
         7: areturn
      LineNumberTable:
        line 547: 0
      LocalVariableTable:
        Start  Length  Slot  Name   Signature
            0       8     0  this   Lshapeless/Segment$;
    Signature: #32                          // <P:Ljava/lang/Object;T::Lshapeless/HList;>()Lshapeless/Segment<TP;Lscala/runtime/Nothing$;TT;>;

  private shapeless.Segment$();
    descriptor: ()V
    flags: (0x0002) ACC_PRIVATE
    Code:
      stack=1, locals=1, args_size=1
         0: aload_0
         1: invokespecial #34                 // Method java/lang/Object."<init>":()V
         4: return
      LineNumberTable:
        line 546: 0
      LocalVariableTable:
        Start  Length  Slot  Name   Signature
            0       5     0  this   Lshapeless/Segment$;
}
InnerClasses:
  public final #9;                        // class shapeless/Segment$$anon$44
SourceFile: "lenses.scala"
  ScalaInlineInfo: length = 0x13 (unknown attribute)
   01 01 00 03 00 0E 00 0D 01 00 1F 00 18 01 00 17
   00 18 01
  Scala: length = 0x0 (unknown attribute)

