Classfile /Users/mw/Projects/slang-braindump/.jar/jar11/assemble/slang-braindump/assemble/content/shapeless/Segment.class
  Last modified May 29, 2022; size 1219 bytes
  SHA-256 checksum 11e92a986745d816f096030a348639c8ee5622b78cd4bd778077a9772d412cf3
  Compiled from "lenses.scala"
public interface shapeless.Segment<P extends java.lang.Object, S extends java.lang.Object, T extends shapeless.HList>
  minor version: 0
  major version: 52
  flags: (0x0601) ACC_PUBLIC, ACC_INTERFACE, ACC_ABSTRACT
  this_class: #2                          // shapeless/Segment
  super_class: #5                         // java/lang/Object
  interfaces: 0, fields: 0, methods: 2, attributes: 5
Constant pool:
   #1 = Utf8               shapeless/Segment
   #2 = Class              #1             // shapeless/Segment
   #3 = Utf8               <P:Ljava/lang/Object;S:Ljava/lang/Object;T::Lshapeless/HList;>Ljava/lang/Object;
   #4 = Utf8               java/lang/Object
   #5 = Class              #4             // java/lang/Object
   #6 = Utf8               lenses.scala
   #7 = Utf8               Lscala/reflect/ScalaSignature;
   #8 = Utf8               bytes
   #9 = Utf8               \u0006\u0005%3qAB\u0004\u0011\u0002G\u0005!\u0002B\u0003\u0013\u0001\t\u00051cB\u0003&\u000f!\u0005aEB\u0003\u0007\u000f!\u0005q\u0005C\u0003,\u0007\u0011\u0005A\u0006C\u0003.\u0007\u0011\raFA\u0004TK\u001elWM\u001c;\u000b\u0003!\t\u0011b\u001d5ba\u0016dWm]:\u0004\u0001U!1bG\u0011$\'\t\u0001A\u0002\u0005\u0002\u000e!5\taBC\u0001\u0010\u0003\u0015\u00198-\u00197b\u0013\t\tbB\u0001\u0004B]f\u0014VM\u001a\u0002\u0004\u001fV$\u0018C\u0001\u000b\u0018!\tiQ#\u0003\u0002\u0017\u001d\t9aj\u001c;iS:<\u0007C\u0001\r\u001a\u001b\u00059\u0011B\u0001\u000e\b\u0005\u0015AE*[:u\t\u0015a\u0002A1\u0001\u001e\u0005\u0005\u0001\u0016C\u0001\u000b\u001f!\tiq$\u0003\u0002!\u001d\t\u0019\u0011I\\=\u0005\u000b\t\u0002!\u0019A\u000f\u0003\u0003M#Q\u0001\n\u0001C\u0002M\u0011\u0011\u0001V\u0001\b\'\u0016<W.\u001a8u!\tA2aE\u0002\u0004\u0019!\u0002\"\u0001G\u0015\n\u0005):!A\u0005\'poB\u0013\u0018n\u001c:jif\u001cVmZ7f]R\fa\u0001P5oSRtD#\u0001\u0014\u0002\u0007=tW-F\u00020ma*\u0012\u0001\r\t\u0007cI\"DcN\u001d\u000e\u0003\rI!aM\u0015\u0003\u0007\u0005+\b\u0010\u0005\u00026m1\u0001A!\u0002\u000f\u0006\u0005\u0004i\u0002CA\u001b9\t\u0015!SA1\u0001\u0014!\u0011A\"\bP\u001c\n\u0005m:!\u0001\u0004\u0013d_2|g\u000eJ2pY>t\u0007c\u0001\r>\u007f%\u0011ah\u0002\u0002\u0007\'\u0016dWm\u0019;\u0011\t\u0001\u001be\t\u000e\b\u00031\u0005K!AQ\u0004\u0002\u0007Q\fw-\u0003\u0002E\u000b\n1A%\u0019;%CRT!AQ\u0004\u0011\u000559\u0015B\u0001%\u000f\u0005\u0019\u0019\u00160\u001c2pY\u0002
  #10 = Utf8               one
  #11 = Utf8               ()Lshapeless/Segment;
  #12 = Utf8               <P:Ljava/lang/Object;T::Lshapeless/HList;>()Lshapeless/Segment<TP;Lscala/runtime/Nothing$;TT;>;
  #13 = Utf8               shapeless/Segment$
  #14 = Class              #13            // shapeless/Segment$
  #15 = Utf8               MODULE$
  #16 = Utf8               Lshapeless/Segment$;
  #17 = NameAndType        #15:#16        // MODULE$:Lshapeless/Segment$;
  #18 = Fieldref           #14.#17        // shapeless/Segment$.MODULE$:Lshapeless/Segment$;
  #19 = NameAndType        #10:#11        // one:()Lshapeless/Segment;
  #20 = Methodref          #14.#19        // shapeless/Segment$.one:()Lshapeless/Segment;
  #21 = Utf8               two
  #22 = Utf8               <P:Ljava/lang/Object;S:Ljava/lang/Object;T::Lshapeless/HList;>()Lshapeless/Segment<TP;TS;TT;>;
  #23 = NameAndType        #21:#11        // two:()Lshapeless/Segment;
  #24 = Methodref          #14.#23        // shapeless/Segment$.two:()Lshapeless/Segment;
  #25 = Utf8               Code
  #26 = Utf8               Signature
  #27 = Utf8               SourceFile
  #28 = Utf8               RuntimeVisibleAnnotations
  #29 = Utf8               ScalaInlineInfo
  #30 = Utf8               ScalaSig
{
  public static <P extends java.lang.Object, T extends shapeless.HList> shapeless.Segment<P, scala.runtime.Nothing$, T> one();
    descriptor: ()Lshapeless/Segment;
    flags: (0x0009) ACC_PUBLIC, ACC_STATIC
    Code:
      stack=1, locals=0, args_size=0
         0: getstatic     #18                 // Field shapeless/Segment$.MODULE$:Lshapeless/Segment$;
         3: invokevirtual #20                 // Method shapeless/Segment$.one:()Lshapeless/Segment;
         6: areturn
    Signature: #12                          // <P:Ljava/lang/Object;T::Lshapeless/HList;>()Lshapeless/Segment<TP;Lscala/runtime/Nothing$;TT;>;

  public static <P extends java.lang.Object, S extends java.lang.Object, T extends shapeless.HList> shapeless.Segment<P, S, T> two();
    descriptor: ()Lshapeless/Segment;
    flags: (0x0009) ACC_PUBLIC, ACC_STATIC
    Code:
      stack=1, locals=0, args_size=0
         0: getstatic     #18                 // Field shapeless/Segment$.MODULE$:Lshapeless/Segment$;
         3: invokevirtual #24                 // Method shapeless/Segment$.two:()Lshapeless/Segment;
         6: areturn
    Signature: #22                          // <P:Ljava/lang/Object;S:Ljava/lang/Object;T::Lshapeless/HList;>()Lshapeless/Segment<TP;TS;TT;>;
}
Signature: #3                           // <P:Ljava/lang/Object;S:Ljava/lang/Object;T::Lshapeless/HList;>Ljava/lang/Object;
SourceFile: "lenses.scala"
RuntimeVisibleAnnotations:
  0: #7(#8=s#9)
    scala.reflect.ScalaSignature(
      bytes="\u0006\u0005%3qAB\u0004\u0011\u0002G\u0005!\u0002B\u0003\u0013\u0001\t\u00051cB\u0003&\u000f!\u0005aEB\u0003\u0007\u000f!\u0005q\u0005C\u0003,\u0007\u0011\u0005A\u0006C\u0003.\u0007\u0011\raFA\u0004TK\u001elWM\u001c;\u000b\u0003!\t\u0011b\u001d5ba\u0016dWm]:\u0004\u0001U!1bG\u0011$\'\t\u0001A\u0002\u0005\u0002\u000e!5\taBC\u0001\u0010\u0003\u0015\u00198-\u00197b\u0013\t\tbB\u0001\u0004B]f\u0014VM\u001a\u0002\u0004\u001fV$\u0018C\u0001\u000b\u0018!\tiQ#\u0003\u0002\u0017\u001d\t9aj\u001c;iS:<\u0007C\u0001\r\u001a\u001b\u00059\u0011B\u0001\u000e\b\u0005\u0015AE*[:u\t\u0015a\u0002A1\u0001\u001e\u0005\u0005\u0001\u0016C\u0001\u000b\u001f!\tiq$\u0003\u0002!\u001d\t\u0019\u0011I\\=\u0005\u000b\t\u0002!\u0019A\u000f\u0003\u0003M#Q\u0001\n\u0001C\u0002M\u0011\u0011\u0001V\u0001\b\'\u0016<W.\u001a8u!\tA2aE\u0002\u0004\u0019!\u0002\"\u0001G\u0015\n\u0005):!A\u0005\'poB\u0013\u0018n\u001c:jif\u001cVmZ7f]R\fa\u0001P5oSRtD#\u0001\u0014\u0002\u0007=tW-F\u00020ma*\u0012\u0001\r\t\u0007cI\"DcN\u001d\u000e\u0003\rI!aM\u0015\u0003\u0007\u0005+\b\u0010\u0005\u00026m1\u0001A!\u0002\u000f\u0006\u0005\u0004i\u0002CA\u001b9\t\u0015!SA1\u0001\u0014!\u0011A\"\bP\u001c\n\u0005m:!\u0001\u0004\u0013d_2|g\u000eJ2pY>t\u0007c\u0001\r>\u007f%\u0011ah\u0002\u0002\u0007\'\u0016dWm\u0019;\u0011\t\u0001\u001be\t\u000e\b\u00031\u0005K!AQ\u0004\u0002\u0007Q\fw-\u0003\u0002E\u000b\n1A%\u0019;%CRT!AQ\u0004\u0011\u000559\u0015B\u0001%\u000f\u0005\u0019\u0019\u00160\u001c2pY\u0002"
    )
  ScalaInlineInfo: length = 0x4 (unknown attribute)
   01 00 00 00
  ScalaSig: length = 0x3 (unknown attribute)
   05 02 00
