Classfile /Users/mw/Projects/slang-braindump/.jar/jar11/assemble/slang-braindump/assemble/content/shapeless/ToStringFacet$ToStringMethods.class
  Last modified May 29, 2022; size 1053 bytes
  SHA-256 checksum afea46d6c3689474b14d23ff6a298c7a47c5b3a344f05c541ee644832326e18c
  Compiled from "alacarte.scala"
public interface shapeless.ToStringFacet$ToStringMethods
  minor version: 0
  major version: 52
  flags: (0x0601) ACC_PUBLIC, ACC_INTERFACE, ACC_ABSTRACT
  this_class: #2                          // shapeless/ToStringFacet$ToStringMethods
  super_class: #4                         // java/lang/Object
  interfaces: 0, fields: 0, methods: 4, attributes: 4
Constant pool:
   #1 = Utf8               shapeless/ToStringFacet$ToStringMethods
   #2 = Class              #1             // shapeless/ToStringFacet$ToStringMethods
   #3 = Utf8               java/lang/Object
   #4 = Class              #3             // java/lang/Object
   #5 = Utf8               alacarte.scala
   #6 = Utf8               shapeless/ToStringFacet
   #7 = Class              #6             // shapeless/ToStringFacet
   #8 = Utf8               ToStringMethods
   #9 = Utf8               shapeless/ToStringFacet$ToStringOps
  #10 = Class              #9             // shapeless/ToStringFacet$ToStringOps
  #11 = Utf8               ToStringOps
  #12 = Utf8               toString$
  #13 = Utf8               (Lshapeless/ToStringFacet$ToStringMethods;)Ljava/lang/String;
  #14 = Utf8               $this
  #15 = Utf8               toString
  #16 = Utf8               ()Ljava/lang/String;
  #17 = NameAndType        #15:#16        // toString:()Ljava/lang/String;
  #18 = InterfaceMethodref #2.#17         // shapeless/ToStringFacet$ToStringMethods.toString:()Ljava/lang/String;
  #19 = Utf8               Lshapeless/ToStringFacet$ToStringMethods;
  #20 = Utf8               shapeless$ToStringFacet$ToStringMethods$$$outer
  #21 = Utf8               ()Lshapeless/ToStringFacet;
  #22 = NameAndType        #20:#21        // shapeless$ToStringFacet$ToStringMethods$$$outer:()Lshapeless/ToStringFacet;
  #23 = InterfaceMethodref #2.#22         // shapeless/ToStringFacet$ToStringMethods.shapeless$ToStringFacet$ToStringMethods$$$outer:()Lshapeless/ToStringFacet;
  #24 = Utf8               ops
  #25 = Utf8               ()Lshapeless/ToStringFacet$ToStringOps;
  #26 = NameAndType        #24:#25        // ops:()Lshapeless/ToStringFacet$ToStringOps;
  #27 = InterfaceMethodref #7.#26         // shapeless/ToStringFacet.ops:()Lshapeless/ToStringFacet$ToStringOps;
  #28 = Utf8               (Ljava/lang/Object;)Ljava/lang/String;
  #29 = NameAndType        #15:#28        // toString:(Ljava/lang/Object;)Ljava/lang/String;
  #30 = InterfaceMethodref #10.#29        // shapeless/ToStringFacet$ToStringOps.toString:(Ljava/lang/Object;)Ljava/lang/String;
  #31 = Utf8               this
  #32 = Utf8               $init$
  #33 = Utf8               (Lshapeless/ToStringFacet$ToStringMethods;)V
  #34 = Utf8               Code
  #35 = Utf8               LineNumberTable
  #36 = Utf8               LocalVariableTable
  #37 = Utf8               MethodParameters
  #38 = Utf8               InnerClasses
  #39 = Utf8               SourceFile
  #40 = Utf8               ScalaInlineInfo
  #41 = Utf8               Scala
{
  public static java.lang.String toString$(shapeless.ToStringFacet$ToStringMethods);
    descriptor: (Lshapeless/ToStringFacet$ToStringMethods;)Ljava/lang/String;
    flags: (0x1009) ACC_PUBLIC, ACC_STATIC, ACC_SYNTHETIC
    Code:
      stack=1, locals=1, args_size=1
         0: aload_0
         1: invokespecial #18                 // InterfaceMethod toString:()Ljava/lang/String;
         4: areturn
      LineNumberTable:
        line 133: 0
      LocalVariableTable:
        Start  Length  Slot  Name   Signature
            0       5     0 $this   Lshapeless/ToStringFacet$ToStringMethods;
    MethodParameters:
      Name                           Flags
      $this                          final synthetic

  public default java.lang.String toString();
    descriptor: ()Ljava/lang/String;
    flags: (0x0001) ACC_PUBLIC
    Code:
      stack=2, locals=1, args_size=1
         0: aload_0
         1: invokeinterface #23,  1           // InterfaceMethod shapeless$ToStringFacet$ToStringMethods$$$outer:()Lshapeless/ToStringFacet;
         6: invokeinterface #27,  1           // InterfaceMethod shapeless/ToStringFacet.ops:()Lshapeless/ToStringFacet$ToStringOps;
        11: aload_0
        12: invokeinterface #30,  2           // InterfaceMethod shapeless/ToStringFacet$ToStringOps.toString:(Ljava/lang/Object;)Ljava/lang/String;
        17: areturn
      LineNumberTable:
        line 133: 0
      LocalVariableTable:
        Start  Length  Slot  Name   Signature
            0      18     0  this   Lshapeless/ToStringFacet$ToStringMethods;

  public abstract shapeless.ToStringFacet shapeless$ToStringFacet$ToStringMethods$$$outer();
    descriptor: ()Lshapeless/ToStringFacet;
    flags: (0x1401) ACC_PUBLIC, ACC_ABSTRACT, ACC_SYNTHETIC

  public static void $init$(shapeless.ToStringFacet$ToStringMethods);
    descriptor: (Lshapeless/ToStringFacet$ToStringMethods;)V
    flags: (0x0009) ACC_PUBLIC, ACC_STATIC
    Code:
      stack=0, locals=1, args_size=1
         0: return
      LineNumberTable:
        line 132: 0
      LocalVariableTable:
        Start  Length  Slot  Name   Signature
            0       1     0 $this   Lshapeless/ToStringFacet$ToStringMethods;
    MethodParameters:
      Name                           Flags
      $this                          final synthetic
}
InnerClasses:
  public #8= #2 of #7;                    // ToStringMethods=class shapeless/ToStringFacet$ToStringMethods of class shapeless/ToStringFacet
  public #11= #10 of #7;                  // ToStringOps=class shapeless/ToStringFacet$ToStringOps of class shapeless/ToStringFacet
SourceFile: "alacarte.scala"
  ScalaInlineInfo: length = 0x18 (unknown attribute)
   01 00 00 04 00 20 00 21 01 00 14 00 15 00 00 0C
   00 0D 01 00 0F 00 10 00
  Scala: length = 0x0 (unknown attribute)

