Classfile /Users/mw/Projects/slang-braindump/.jar/jar11/assemble/slang-braindump/assemble/content/shapeless/TypeCase$$anon$21.class
  Last modified May 29, 2022; size 1546 bytes
  SHA-256 checksum 54e775bac87336e5a58a79dd05e16a0d27efdeab4da8f8a2d4fb1f224430c8a0
  Compiled from "typeable.scala"
public final class shapeless.TypeCase$$anon$21 extends java.lang.Object implements shapeless.TypeCase<T>
  minor version: 0
  major version: 52
  flags: (0x0031) ACC_PUBLIC, ACC_FINAL, ACC_SUPER
  this_class: #2                          // shapeless/TypeCase$$anon$21
  super_class: #5                         // java/lang/Object
  interfaces: 1, fields: 1, methods: 3, attributes: 6
Constant pool:
   #1 = Utf8               shapeless/TypeCase$$anon$21
   #2 = Class              #1             // shapeless/TypeCase$$anon$21
   #3 = Utf8               Ljava/lang/Object;Lshapeless/TypeCase<TT;>;
   #4 = Utf8               java/lang/Object
   #5 = Class              #4             // java/lang/Object
   #6 = Utf8               shapeless/TypeCase
   #7 = Class              #6             // shapeless/TypeCase
   #8 = Utf8               typeable.scala
   #9 = Utf8               shapeless/TypeCase$
  #10 = Class              #9             // shapeless/TypeCase$
  #11 = Utf8               apply
  #12 = Utf8               (Lshapeless/Typeable;)Lshapeless/TypeCase;
  #13 = NameAndType        #11:#12        // apply:(Lshapeless/Typeable;)Lshapeless/TypeCase;
  #14 = Utf8               tt$1
  #15 = Utf8               Lshapeless/Typeable;
  #16 = Utf8               unapply
  #17 = Utf8               (Ljava/lang/Object;)Lscala/Option;
  #18 = Utf8               (Ljava/lang/Object;)Lscala/Option<TT;>;
  #19 = Utf8               t
  #20 = Utf8               shapeless/syntax/TypeableOps$
  #21 = Class              #20            // shapeless/syntax/TypeableOps$
  #22 = Utf8               MODULE$
  #23 = Utf8               Lshapeless/syntax/TypeableOps$;
  #24 = NameAndType        #22:#23        // MODULE$:Lshapeless/syntax/TypeableOps$;
  #25 = Fieldref           #21.#24        // shapeless/syntax/TypeableOps$.MODULE$:Lshapeless/syntax/TypeableOps$;
  #26 = Utf8               shapeless/syntax/typeable$
  #27 = Class              #26            // shapeless/syntax/typeable$
  #28 = Utf8               Lshapeless/syntax/typeable$;
  #29 = NameAndType        #22:#28        // MODULE$:Lshapeless/syntax/typeable$;
  #30 = Fieldref           #27.#29        // shapeless/syntax/typeable$.MODULE$:Lshapeless/syntax/typeable$;
  #31 = Utf8               typeableOps
  #32 = Utf8               (Ljava/lang/Object;)Ljava/lang/Object;
  #33 = NameAndType        #31:#32        // typeableOps:(Ljava/lang/Object;)Ljava/lang/Object;
  #34 = Methodref          #27.#33        // shapeless/syntax/typeable$.typeableOps:(Ljava/lang/Object;)Ljava/lang/Object;
  #35 = NameAndType        #14:#15        // tt$1:Lshapeless/Typeable;
  #36 = Fieldref           #2.#35         // shapeless/TypeCase$$anon$21.tt$1:Lshapeless/Typeable;
  #37 = Utf8               cast$extension
  #38 = Utf8               (Ljava/lang/Object;Lshapeless/Typeable;)Lscala/Option;
  #39 = NameAndType        #37:#38        // cast$extension:(Ljava/lang/Object;Lshapeless/Typeable;)Lscala/Option;
  #40 = Methodref          #21.#39        // shapeless/syntax/TypeableOps$.cast$extension:(Ljava/lang/Object;Lshapeless/Typeable;)Lscala/Option;
  #41 = Utf8               this
  #42 = Utf8               Lshapeless/TypeCase$$anon$21;
  #43 = Utf8               Ljava/lang/Object;
  #44 = Utf8               toString
  #45 = Utf8               ()Ljava/lang/String;
  #46 = Utf8               java/lang/StringBuilder
  #47 = Class              #46            // java/lang/StringBuilder
  #48 = Integer            10
  #49 = Utf8               <init>
  #50 = Utf8               (I)V
  #51 = NameAndType        #49:#50        // "<init>":(I)V
  #52 = Methodref          #47.#51        // java/lang/StringBuilder."<init>":(I)V
  #53 = Utf8               TypeCase[
  #54 = String             #53            // TypeCase[
  #55 = Utf8               append
  #56 = Utf8               (Ljava/lang/String;)Ljava/lang/StringBuilder;
  #57 = NameAndType        #55:#56        // append:(Ljava/lang/String;)Ljava/lang/StringBuilder;
  #58 = Methodref          #47.#57        // java/lang/StringBuilder.append:(Ljava/lang/String;)Ljava/lang/StringBuilder;
  #59 = Utf8               shapeless/Typeable
  #60 = Class              #59            // shapeless/Typeable
  #61 = Utf8               describe
  #62 = NameAndType        #61:#45        // describe:()Ljava/lang/String;
  #63 = InterfaceMethodref #60.#62        // shapeless/Typeable.describe:()Ljava/lang/String;
  #64 = Utf8               ]
  #65 = String             #64            // ]
  #66 = NameAndType        #44:#45        // toString:()Ljava/lang/String;
  #67 = Methodref          #47.#66        // java/lang/StringBuilder.toString:()Ljava/lang/String;
  #68 = Utf8               (Lshapeless/Typeable;)V
  #69 = Utf8               ()V
  #70 = NameAndType        #49:#69        // "<init>":()V
  #71 = Methodref          #5.#70         // java/lang/Object."<init>":()V
  #72 = Utf8               Code
  #73 = Utf8               LineNumberTable
  #74 = Utf8               LocalVariableTable
  #75 = Utf8               Signature
  #76 = Utf8               MethodParameters
  #77 = Utf8               InnerClasses
  #78 = Utf8               EnclosingMethod
  #79 = Utf8               SourceFile
  #80 = Utf8               ScalaInlineInfo
  #81 = Utf8               Scala
{
  private final shapeless.Typeable tt$1;
    descriptor: Lshapeless/Typeable;
    flags: (0x0012) ACC_PRIVATE, ACC_FINAL

  public scala.Option<T> unapply(java.lang.Object);
    descriptor: (Ljava/lang/Object;)Lscala/Option;
    flags: (0x0001) ACC_PUBLIC
    Code:
      stack=3, locals=2, args_size=2
         0: getstatic     #25                 // Field shapeless/syntax/TypeableOps$.MODULE$:Lshapeless/syntax/TypeableOps$;
         3: getstatic     #30                 // Field shapeless/syntax/typeable$.MODULE$:Lshapeless/syntax/typeable$;
         6: aload_1
         7: invokevirtual #34                 // Method shapeless/syntax/typeable$.typeableOps:(Ljava/lang/Object;)Ljava/lang/Object;
        10: aload_0
        11: getfield      #36                 // Field tt$1:Lshapeless/Typeable;
        14: invokevirtual #40                 // Method shapeless/syntax/TypeableOps$.cast$extension:(Ljava/lang/Object;Lshapeless/Typeable;)Lscala/Option;
        17: areturn
      LineNumberTable:
        line 363: 3
      LocalVariableTable:
        Start  Length  Slot  Name   Signature
            0      18     0  this   Lshapeless/TypeCase$$anon$21;
            0      18     1     t   Ljava/lang/Object;
    Signature: #18                          // (Ljava/lang/Object;)Lscala/Option<TT;>;
    MethodParameters:
      Name                           Flags
      t                              final

  public java.lang.String toString();
    descriptor: ()Ljava/lang/String;
    flags: (0x0001) ACC_PUBLIC
    Code:
      stack=3, locals=1, args_size=1
         0: new           #47                 // class java/lang/StringBuilder
         3: dup
         4: ldc           #48                 // int 10
         6: invokespecial #52                 // Method java/lang/StringBuilder."<init>":(I)V
         9: ldc           #54                 // String TypeCase[
        11: invokevirtual #58                 // Method java/lang/StringBuilder.append:(Ljava/lang/String;)Ljava/lang/StringBuilder;
        14: aload_0
        15: getfield      #36                 // Field tt$1:Lshapeless/Typeable;
        18: invokeinterface #63,  1           // InterfaceMethod shapeless/Typeable.describe:()Ljava/lang/String;
        23: invokevirtual #58                 // Method java/lang/StringBuilder.append:(Ljava/lang/String;)Ljava/lang/StringBuilder;
        26: ldc           #65                 // String ]
        28: invokevirtual #58                 // Method java/lang/StringBuilder.append:(Ljava/lang/String;)Ljava/lang/StringBuilder;
        31: invokevirtual #67                 // Method java/lang/StringBuilder.toString:()Ljava/lang/String;
        34: areturn
      LineNumberTable:
        line 364: 0
      LocalVariableTable:
        Start  Length  Slot  Name   Signature
            0      35     0  this   Lshapeless/TypeCase$$anon$21;

  public shapeless.TypeCase$$anon$21(shapeless.Typeable);
    descriptor: (Lshapeless/Typeable;)V
    flags: (0x0001) ACC_PUBLIC
    Code:
      stack=2, locals=2, args_size=2
         0: aload_0
         1: aload_1
         2: putfield      #36                 // Field tt$1:Lshapeless/Typeable;
         5: aload_0
         6: invokespecial #71                 // Method java/lang/Object."<init>":()V
         9: return
      LineNumberTable:
        line 362: 0
      LocalVariableTable:
        Start  Length  Slot  Name   Signature
            0      10     0  this   Lshapeless/TypeCase$$anon$21;
            0      10     1  tt$1   Lshapeless/Typeable;
    MethodParameters:
      Name                           Flags
      tt$1                           final
}
InnerClasses:
  public final #2;                        // class shapeless/TypeCase$$anon$21
EnclosingMethod: #10.#13                // shapeless.TypeCase$.apply
Signature: #3                           // Ljava/lang/Object;Lshapeless/TypeCase<TT;>;
SourceFile: "typeable.scala"
  ScalaInlineInfo: length = 0x13 (unknown attribute)
   01 01 00 03 00 31 00 44 01 00 2C 00 2D 01 00 10
   00 11 01
  Scala: length = 0x0 (unknown attribute)

