Classfile /Users/mw/Projects/slang-braindump/.jar/jar11/assemble/slang-braindump/assemble/content/shapeless/TypeCase$.class
  Last modified May 29, 2022; size 1018 bytes
  SHA-256 checksum 394f41151e63408caaa9144782c379814fa73d8c3364be23c359298d73d320c1
  Compiled from "typeable.scala"
public final class shapeless.TypeCase$ implements java.io.Serializable
  minor version: 0
  major version: 52
  flags: (0x0031) ACC_PUBLIC, ACC_FINAL, ACC_SUPER
  this_class: #2                          // shapeless/TypeCase$
  super_class: #4                         // java/lang/Object
  interfaces: 1, fields: 1, methods: 4, attributes: 4
Constant pool:
   #1 = Utf8               shapeless/TypeCase$
   #2 = Class              #1             // shapeless/TypeCase$
   #3 = Utf8               java/lang/Object
   #4 = Class              #3             // java/lang/Object
   #5 = Utf8               java/io/Serializable
   #6 = Class              #5             // java/io/Serializable
   #7 = Utf8               typeable.scala
   #8 = Utf8               shapeless/TypeCase$$anon$21
   #9 = Class              #8             // shapeless/TypeCase$$anon$21
  #10 = Utf8               MODULE$
  #11 = Utf8               Lshapeless/TypeCase$;
  #12 = Utf8               <clinit>
  #13 = Utf8               ()V
  #14 = Utf8               <init>
  #15 = NameAndType        #14:#13        // "<init>":()V
  #16 = Methodref          #2.#15         // shapeless/TypeCase$."<init>":()V
  #17 = NameAndType        #10:#11        // MODULE$:Lshapeless/TypeCase$;
  #18 = Fieldref           #2.#17         // shapeless/TypeCase$.MODULE$:Lshapeless/TypeCase$;
  #19 = Utf8               apply
  #20 = Utf8               (Lshapeless/Typeable;)Lshapeless/TypeCase;
  #21 = Utf8               <T:Ljava/lang/Object;>(Lshapeless/Typeable<TT;>;)Lshapeless/TypeCase<TT;>;
  #22 = Utf8               tt
  #23 = Utf8               (Lshapeless/Typeable;)V
  #24 = NameAndType        #14:#23        // "<init>":(Lshapeless/Typeable;)V
  #25 = Methodref          #9.#24         // shapeless/TypeCase$$anon$21."<init>":(Lshapeless/Typeable;)V
  #26 = Utf8               this
  #27 = Utf8               Lshapeless/Typeable;
  #28 = Utf8               writeReplace
  #29 = Utf8               ()Ljava/lang/Object;
  #30 = Utf8               scala/runtime/ModuleSerializationProxy
  #31 = Class              #30            // scala/runtime/ModuleSerializationProxy
  #32 = Utf8               (Ljava/lang/Class;)V
  #33 = NameAndType        #14:#32        // "<init>":(Ljava/lang/Class;)V
  #34 = Methodref          #31.#33        // scala/runtime/ModuleSerializationProxy."<init>":(Ljava/lang/Class;)V
  #35 = Methodref          #4.#15         // java/lang/Object."<init>":()V
  #36 = Utf8               Code
  #37 = Utf8               LineNumberTable
  #38 = Utf8               LocalVariableTable
  #39 = Utf8               Signature
  #40 = Utf8               MethodParameters
  #41 = Utf8               InnerClasses
  #42 = Utf8               SourceFile
  #43 = Utf8               ScalaInlineInfo
  #44 = Utf8               Scala
{
  public static final shapeless.TypeCase$ MODULE$;
    descriptor: Lshapeless/TypeCase$;
    flags: (0x0019) ACC_PUBLIC, ACC_STATIC, ACC_FINAL

  public static {};
    descriptor: ()V
    flags: (0x0009) ACC_PUBLIC, ACC_STATIC
    Code:
      stack=2, locals=0, args_size=0
         0: new           #2                  // class shapeless/TypeCase$
         3: dup
         4: invokespecial #16                 // Method "<init>":()V
         7: putstatic     #18                 // Field MODULE$:Lshapeless/TypeCase$;
        10: return
      LineNumberTable:
        line 360: 0

  public <T extends java.lang.Object> shapeless.TypeCase<T> apply(shapeless.Typeable<T>);
    descriptor: (Lshapeless/Typeable;)Lshapeless/TypeCase;
    flags: (0x0001) ACC_PUBLIC
    Code:
      stack=3, locals=2, args_size=2
         0: new           #9                  // class shapeless/TypeCase$$anon$21
         3: dup
         4: aload_1
         5: invokespecial #25                 // Method shapeless/TypeCase$$anon$21."<init>":(Lshapeless/Typeable;)V
         8: areturn
      LineNumberTable:
        line 362: 0
      LocalVariableTable:
        Start  Length  Slot  Name   Signature
            0       9     0  this   Lshapeless/TypeCase$;
            0       9     1    tt   Lshapeless/Typeable;
    Signature: #21                          // <T:Ljava/lang/Object;>(Lshapeless/Typeable<TT;>;)Lshapeless/TypeCase<TT;>;
    MethodParameters:
      Name                           Flags
      tt                             final

  private java.lang.Object writeReplace();
    descriptor: ()Ljava/lang/Object;
    flags: (0x0002) ACC_PRIVATE
    Code:
      stack=3, locals=1, args_size=1
         0: new           #31                 // class scala/runtime/ModuleSerializationProxy
         3: dup
         4: ldc           #2                  // class shapeless/TypeCase$
         6: invokespecial #34                 // Method scala/runtime/ModuleSerializationProxy."<init>":(Ljava/lang/Class;)V
         9: areturn
      LineNumberTable:
        line 360: 0
      LocalVariableTable:
        Start  Length  Slot  Name   Signature
            0      10     0  this   Lshapeless/TypeCase$;

  private shapeless.TypeCase$();
    descriptor: ()V
    flags: (0x0002) ACC_PRIVATE
    Code:
      stack=1, locals=1, args_size=1
         0: aload_0
         1: invokespecial #35                 // Method java/lang/Object."<init>":()V
         4: return
      LineNumberTable:
        line 368: 0
        line 360: 4
      LocalVariableTable:
        Start  Length  Slot  Name   Signature
            0       5     0  this   Lshapeless/TypeCase$;
}
InnerClasses:
  public final #9;                        // class shapeless/TypeCase$$anon$21
SourceFile: "typeable.scala"
  ScalaInlineInfo: length = 0x13 (unknown attribute)
   01 01 00 03 00 0E 00 0D 01 00 13 00 14 01 00 1C
   00 1D 01
  Scala: length = 0x0 (unknown attribute)

