Classfile /Users/mw/Projects/slang-braindump/.jar/jar11/assemble/slang-braindump/assemble/content/shapeless/UnaryTCConstraint.class
  Last modified May 29, 2022; size 2798 bytes
  SHA-256 checksum 45f37d35609aab7ce714379c9a2cb7076119daff12d6e222d420b64a8104a0e6
  Compiled from "hlistconstraints.scala"
public interface shapeless.UnaryTCConstraint<L extends shapeless.HList, TC extends java.lang.Object> extends java.io.Serializable
  minor version: 0
  major version: 52
  flags: (0x0601) ACC_PUBLIC, ACC_INTERFACE, ACC_ABSTRACT
  this_class: #2                          // shapeless/UnaryTCConstraint
  super_class: #5                         // java/lang/Object
  interfaces: 1, fields: 0, methods: 6, attributes: 5
Constant pool:
   #1 = Utf8               shapeless/UnaryTCConstraint
   #2 = Class              #1             // shapeless/UnaryTCConstraint
   #3 = Utf8               <L::Lshapeless/HList;TC:Ljava/lang/Object;>Ljava/lang/Object;Ljava/io/Serializable;
   #4 = Utf8               java/lang/Object
   #5 = Class              #4             // java/lang/Object
   #6 = Utf8               java/io/Serializable
   #7 = Class              #6             // java/io/Serializable
   #8 = Utf8               hlistconstraints.scala
   #9 = Utf8               Lscala/reflect/ScalaSignature;
  #10 = Utf8               bytes
  #11 = Utf8               \u0006\u0005\u0005-baB\u0005\u000b!\u0003\r\n!D\u0004\u0006i)A\t!\u000e\u0004\u0006\u0013)A\tA\u000e\u0005\u0006\u0003\n!\tA\u0011\u0005\u0006\u0007\n!\t\u0001R\u0003\u0005!\n\u0001\u0011\u000bC\u0003`\u0005\u0011\r\u0001\rC\u0003y\u0005\u0011\r\u0011\u0010C\u0005\u0002\u001c\t\t\t\u0011\"\u0003\u0002\u001e\t\tRK\\1ssR\u001b5i\u001c8tiJ\f\u0017N\u001c;\u000b\u0003-\t\u0011b\u001d5ba\u0016dWm]:\u0004\u0001U\u0019a\"I\u0016\u0014\u0007\u0001yQ\u0003\u0005\u0002\u0011\'5\t\u0011CC\u0001\u0013\u0003\u0015\u00198-\u00197b\u0013\t!\u0012C\u0001\u0004B]f\u0014VM\u001a\t\u0003-yq!a\u0006\u000f\u000f\u0005aYR\"A\r\u000b\u0005ia\u0011A\u0002\u001fs_>$h(C\u0001\u0013\u0013\ti\u0012#A\u0004qC\u000e\\\u0017mZ3\n\u0005}\u0001#\u0001D*fe&\fG.\u001b>bE2,\'BA\u000f\u0012\t\u0015\u0011\u0003A1\u0001$\u0005\u0005a\u0015C\u0001\u0013(!\t\u0001R%\u0003\u0002\'#\t9aj\u001c;iS:<\u0007C\u0001\u0015*\u001b\u0005Q\u0011B\u0001\u0016\u000b\u0005\u0015AE*[:u\t\u0015a\u0003A1\u0001.\u0005\t!6)\u0006\u0002/eE\u0011Ae\f\t\u0003!AJ!!M\t\u0003\u0007\u0005s\u0017\u0010B\u00034W\t\u0007aFA\u0001`\u0003E)f.\u0019:z)\u000e\u001buN\\:ue\u0006Lg\u000e\u001e\t\u0003Q\t\u0019BAA\b8uA\u0011\u0001\u0006O\u0005\u0003s)\u0011A\u0004T8x!JLwN]5usVs\u0017M]=U\u0007\u000e{gn\u001d;sC&tG\u000f\u0005\u0002<\u00016\tAH\u0003\u0002>}\u0005\u0011\u0011n\u001c\u0006\u0002\u007f\u0005!!.\u0019<b\u0013\tyB(\u0001\u0004=S:LGO\u0010\u000b\u0002k\u0005)\u0011\r\u001d9msV\u0019Q)S&\u0015\u0005\u0019s\u0005\u0003\u0002\u0015\u0001\u000f*\u0003\"\u0001S%\r\u0001\u0011)!\u0005\u0002b\u0001GA\u0011\u0001j\u0013\u0003\u0006Y\u0011\u0011\r\u0001T\u000b\u0003]5#QaM&C\u00029BQa\u0014\u0003A\u0004\u0019\u000bA!\u001e;dG\nQB\u0005^5nKN$S.\u001b8vg\u0012:\'/Z1uKJ$C/[7fgV\u0011!\u000b\u0018\n\u0003\'>1A\u0001\u0016\u0002\u0001%\naAH]3gS:,W.\u001a8u}\u0015!ak\u0015\u0001X\u0005\tq=8\u0006\u0002Y5B!\u0001\u0006A-\\!\tA%\fB\u0003#+\n\u00071\u0005\u0005\u0002I9\u0012)A&\u0002b\u0001;V\u0011aF\u0018\u0003\u0006gq\u0013\rAL\u0001\u0011Q:LGnQ8ogR,f.\u0019:z)\u000e+\"!\u00196\u0016\u0003\t\u00142aY\be\r\u0011!f\u0001\u00012\u0011\t!\u0002Q\r\u001b\t\u0003Q\u0019L!a\u001a\u0006\u0003\t!s\u0015\u000e\\\u000b\u0003S2\u0004\"\u0001\u00136\u0005\u000b-4!\u0019\u0001\u0018\u0003\u0003!#Q!\u001c8C\u00029\u0012\u0011\u0001\u0016\u0005\u0005_B\u0004q/\u0001\u0006=Y>\u001c\u0017\r\u001c\u0011Ox{*AAV9\u0001i\u001a!A\u000b\u0001\u0001t\u0015\ti\"B\u0005\u0002r\u001fU\u0011QO\u001e\t\u0003\u0011*$Q!\u001c9C\u00029Z\u0001!\u0001\u0007iY&\u001cH/\u00168bef$6)F\u0004{\u0003\u001b\t\t\"!\u0002\u0015\u0007m\f)BE\u0002}\u001fu4A\u0001V\u0004\u0001wB)\u0001\u0006\u0001@\u0002\u0014A1\u0001f`A\u0002\u0003\u001fI1!!\u0001\u000b\u00051!3m\u001c7p]\u0012\u001aw\u000e\\8o!\u0015A\u0015QAA\u0006\t\u0019asA1\u0001\u0002\bU\u0019a&!\u0003\u0005\rM\n)A1\u0001/!\rA\u0015Q\u0002\u0003\u0006W\u001e\u0011\rA\f\t\u0004\u0011\u0006EA!B7\b\u0005\u0004\u0019\u0003c\u0001%\u0002\u0006!9\u0011qC\u0004A\u0004\u0005e\u0011\u0001B;uGR\u0004b\u0001\u000b\u0001\u0002\u0010\u0005M\u0011\u0001D<sSR,\'+\u001a9mC\u000e,GCAA\u0010!\u0011\t\t#a\n\u000e\u0005\u0005\r\"bAA\u0013}\u0005!A.\u00198h\u0013\u0011\tI#a\t\u0003\r=\u0013\'.Z2u\u0001
  #12 = Utf8               hlistUnaryTC
  #13 = Utf8               (Lshapeless/UnaryTCConstraint;)Lshapeless/UnaryTCConstraint;
  #14 = Utf8               <H:Ljava/lang/Object;T::Lshapeless/HList;TC:Ljava/lang/Object;>(Lshapeless/UnaryTCConstraint<TT;TTC;>;)Lshapeless/UnaryTCConstraint<Lshapeless/$colon$colon<TTC;TT;>;TTC;>;
  #15 = Utf8               utct
  #16 = Utf8               shapeless/UnaryTCConstraint$
  #17 = Class              #16            // shapeless/UnaryTCConstraint$
  #18 = Utf8               MODULE$
  #19 = Utf8               Lshapeless/UnaryTCConstraint$;
  #20 = NameAndType        #18:#19        // MODULE$:Lshapeless/UnaryTCConstraint$;
  #21 = Fieldref           #17.#20        // shapeless/UnaryTCConstraint$.MODULE$:Lshapeless/UnaryTCConstraint$;
  #22 = NameAndType        #12:#13        // hlistUnaryTC:(Lshapeless/UnaryTCConstraint;)Lshapeless/UnaryTCConstraint;
  #23 = Methodref          #17.#22        // shapeless/UnaryTCConstraint$.hlistUnaryTC:(Lshapeless/UnaryTCConstraint;)Lshapeless/UnaryTCConstraint;
  #24 = Utf8               hnilConstUnaryTC
  #25 = Utf8               ()Lshapeless/UnaryTCConstraint;
  #26 = Utf8               <H:Ljava/lang/Object;>()Lshapeless/UnaryTCConstraint<Lshapeless/HNil;*>;
  #27 = NameAndType        #24:#25        // hnilConstUnaryTC:()Lshapeless/UnaryTCConstraint;
  #28 = Methodref          #17.#27        // shapeless/UnaryTCConstraint$.hnilConstUnaryTC:()Lshapeless/UnaryTCConstraint;
  #29 = Utf8               apply
  #30 = Utf8               <L::Lshapeless/HList;TC:Ljava/lang/Object;>(Lshapeless/UnaryTCConstraint<TL;TTC;>;)Lshapeless/UnaryTCConstraint<TL;TTC;>;
  #31 = Utf8               utcc
  #32 = NameAndType        #29:#13        // apply:(Lshapeless/UnaryTCConstraint;)Lshapeless/UnaryTCConstraint;
  #33 = Methodref          #17.#32        // shapeless/UnaryTCConstraint$.apply:(Lshapeless/UnaryTCConstraint;)Lshapeless/UnaryTCConstraint;
  #34 = Utf8               hlistConstUnaryTC
  #35 = Utf8               <H:Ljava/lang/Object;T::Lshapeless/HList;>(Lshapeless/UnaryTCConstraint<TT;*>;)Lshapeless/UnaryTCConstraint<Lshapeless/$colon$colon<TH;TT;>;*>;
  #36 = NameAndType        #34:#13        // hlistConstUnaryTC:(Lshapeless/UnaryTCConstraint;)Lshapeless/UnaryTCConstraint;
  #37 = Methodref          #17.#36        // shapeless/UnaryTCConstraint$.hlistConstUnaryTC:(Lshapeless/UnaryTCConstraint;)Lshapeless/UnaryTCConstraint;
  #38 = Utf8               hnilUnaryTC
  #39 = Utf8               <TC:Ljava/lang/Object;>()Lshapeless/UnaryTCConstraint<Lshapeless/HNil;TTC;>;
  #40 = NameAndType        #38:#25        // hnilUnaryTC:()Lshapeless/UnaryTCConstraint;
  #41 = Methodref          #17.#40        // shapeless/UnaryTCConstraint$.hnilUnaryTC:()Lshapeless/UnaryTCConstraint;
  #42 = Utf8               hlistIdUnaryTC
  #43 = Utf8               <L::Lshapeless/HList;>()Lshapeless/UnaryTCConstraint<TL;Ljava/lang/Object;>;
  #44 = NameAndType        #42:#25        // hlistIdUnaryTC:()Lshapeless/UnaryTCConstraint;
  #45 = Methodref          #17.#44        // shapeless/UnaryTCConstraint$.hlistIdUnaryTC:()Lshapeless/UnaryTCConstraint;
  #46 = Utf8               Code
  #47 = Utf8               Signature
  #48 = Utf8               MethodParameters
  #49 = Utf8               SourceFile
  #50 = Utf8               RuntimeVisibleAnnotations
  #51 = Utf8               ScalaInlineInfo
  #52 = Utf8               ScalaSig
{
  public static <H extends java.lang.Object, T extends shapeless.HList, TC extends java.lang.Object> shapeless.UnaryTCConstraint<shapeless.$colon$colon<TC, T>, TC> hlistUnaryTC(shapeless.UnaryTCConstraint<T, TC>);
    descriptor: (Lshapeless/UnaryTCConstraint;)Lshapeless/UnaryTCConstraint;
    flags: (0x0009) ACC_PUBLIC, ACC_STATIC
    Code:
      stack=2, locals=1, args_size=1
         0: getstatic     #21                 // Field shapeless/UnaryTCConstraint$.MODULE$:Lshapeless/UnaryTCConstraint$;
         3: aload_0
         4: invokevirtual #23                 // Method shapeless/UnaryTCConstraint$.hlistUnaryTC:(Lshapeless/UnaryTCConstraint;)Lshapeless/UnaryTCConstraint;
         7: areturn
    Signature: #14                          // <H:Ljava/lang/Object;T::Lshapeless/HList;TC:Ljava/lang/Object;>(Lshapeless/UnaryTCConstraint<TT;TTC;>;)Lshapeless/UnaryTCConstraint<Lshapeless/$colon$colon<TTC;TT;>;TTC;>;
    MethodParameters:
      Name                           Flags
      utct                           final

  public static <H extends java.lang.Object> shapeless.UnaryTCConstraint<shapeless.HNil, ?> hnilConstUnaryTC();
    descriptor: ()Lshapeless/UnaryTCConstraint;
    flags: (0x0009) ACC_PUBLIC, ACC_STATIC
    Code:
      stack=1, locals=0, args_size=0
         0: getstatic     #21                 // Field shapeless/UnaryTCConstraint$.MODULE$:Lshapeless/UnaryTCConstraint$;
         3: invokevirtual #28                 // Method shapeless/UnaryTCConstraint$.hnilConstUnaryTC:()Lshapeless/UnaryTCConstraint;
         6: areturn
    Signature: #26                          // <H:Ljava/lang/Object;>()Lshapeless/UnaryTCConstraint<Lshapeless/HNil;*>;

  public static <L extends shapeless.HList, TC extends java.lang.Object> shapeless.UnaryTCConstraint<L, TC> apply(shapeless.UnaryTCConstraint<L, TC>);
    descriptor: (Lshapeless/UnaryTCConstraint;)Lshapeless/UnaryTCConstraint;
    flags: (0x0009) ACC_PUBLIC, ACC_STATIC
    Code:
      stack=2, locals=1, args_size=1
         0: getstatic     #21                 // Field shapeless/UnaryTCConstraint$.MODULE$:Lshapeless/UnaryTCConstraint$;
         3: aload_0
         4: invokevirtual #33                 // Method shapeless/UnaryTCConstraint$.apply:(Lshapeless/UnaryTCConstraint;)Lshapeless/UnaryTCConstraint;
         7: areturn
    Signature: #30                          // <L::Lshapeless/HList;TC:Ljava/lang/Object;>(Lshapeless/UnaryTCConstraint<TL;TTC;>;)Lshapeless/UnaryTCConstraint<TL;TTC;>;
    MethodParameters:
      Name                           Flags
      utcc                           final

  public static <H extends java.lang.Object, T extends shapeless.HList> shapeless.UnaryTCConstraint<shapeless.$colon$colon<H, T>, ?> hlistConstUnaryTC(shapeless.UnaryTCConstraint<T, ?>);
    descriptor: (Lshapeless/UnaryTCConstraint;)Lshapeless/UnaryTCConstraint;
    flags: (0x0009) ACC_PUBLIC, ACC_STATIC
    Code:
      stack=2, locals=1, args_size=1
         0: getstatic     #21                 // Field shapeless/UnaryTCConstraint$.MODULE$:Lshapeless/UnaryTCConstraint$;
         3: aload_0
         4: invokevirtual #37                 // Method shapeless/UnaryTCConstraint$.hlistConstUnaryTC:(Lshapeless/UnaryTCConstraint;)Lshapeless/UnaryTCConstraint;
         7: areturn
    Signature: #35                          // <H:Ljava/lang/Object;T::Lshapeless/HList;>(Lshapeless/UnaryTCConstraint<TT;*>;)Lshapeless/UnaryTCConstraint<Lshapeless/$colon$colon<TH;TT;>;*>;
    MethodParameters:
      Name                           Flags
      utct                           final

  public static <TC extends java.lang.Object> shapeless.UnaryTCConstraint<shapeless.HNil, TC> hnilUnaryTC();
    descriptor: ()Lshapeless/UnaryTCConstraint;
    flags: (0x0009) ACC_PUBLIC, ACC_STATIC
    Code:
      stack=1, locals=0, args_size=0
         0: getstatic     #21                 // Field shapeless/UnaryTCConstraint$.MODULE$:Lshapeless/UnaryTCConstraint$;
         3: invokevirtual #41                 // Method shapeless/UnaryTCConstraint$.hnilUnaryTC:()Lshapeless/UnaryTCConstraint;
         6: areturn
    Signature: #39                          // <TC:Ljava/lang/Object;>()Lshapeless/UnaryTCConstraint<Lshapeless/HNil;TTC;>;

  public static <L extends shapeless.HList> shapeless.UnaryTCConstraint<L, java.lang.Object> hlistIdUnaryTC();
    descriptor: ()Lshapeless/UnaryTCConstraint;
    flags: (0x0009) ACC_PUBLIC, ACC_STATIC
    Code:
      stack=1, locals=0, args_size=0
         0: getstatic     #21                 // Field shapeless/UnaryTCConstraint$.MODULE$:Lshapeless/UnaryTCConstraint$;
         3: invokevirtual #45                 // Method shapeless/UnaryTCConstraint$.hlistIdUnaryTC:()Lshapeless/UnaryTCConstraint;
         6: areturn
    Signature: #43                          // <L::Lshapeless/HList;>()Lshapeless/UnaryTCConstraint<TL;Ljava/lang/Object;>;
}
Signature: #3                           // <L::Lshapeless/HList;TC:Ljava/lang/Object;>Ljava/lang/Object;Ljava/io/Serializable;
SourceFile: "hlistconstraints.scala"
RuntimeVisibleAnnotations:
  0: #9(#10=s#11)
    scala.reflect.ScalaSignature(
      bytes="\u0006\u0005\u0005-baB\u0005\u000b!\u0003\r\n!D\u0004\u0006i)A\t!\u000e\u0004\u0006\u0013)A\tA\u000e\u0005\u0006\u0003\n!\tA\u0011\u0005\u0006\u0007\n!\t\u0001R\u0003\u0005!\n\u0001\u0011\u000bC\u0003`\u0005\u0011\r\u0001\rC\u0003y\u0005\u0011\r\u0011\u0010C\u0005\u0002\u001c\t\t\t\u0011\"\u0003\u0002\u001e\t\tRK\\1ssR\u001b5i\u001c8tiJ\f\u0017N\u001c;\u000b\u0003-\t\u0011b\u001d5ba\u0016dWm]:\u0004\u0001U\u0019a\"I\u0016\u0014\u0007\u0001yQ\u0003\u0005\u0002\u0011\'5\t\u0011CC\u0001\u0013\u0003\u0015\u00198-\u00197b\u0013\t!\u0012C\u0001\u0004B]f\u0014VM\u001a\t\u0003-yq!a\u0006\u000f\u000f\u0005aYR\"A\r\u000b\u0005ia\u0011A\u0002\u001fs_>$h(C\u0001\u0013\u0013\ti\u0012#A\u0004qC\u000e\\\u0017mZ3\n\u0005}\u0001#\u0001D*fe&\fG.\u001b>bE2,\'BA\u000f\u0012\t\u0015\u0011\u0003A1\u0001$\u0005\u0005a\u0015C\u0001\u0013(!\t\u0001R%\u0003\u0002\'#\t9aj\u001c;iS:<\u0007C\u0001\u0015*\u001b\u0005Q\u0011B\u0001\u0016\u000b\u0005\u0015AE*[:u\t\u0015a\u0003A1\u0001.\u0005\t!6)\u0006\u0002/eE\u0011Ae\f\t\u0003!AJ!!M\t\u0003\u0007\u0005s\u0017\u0010B\u00034W\t\u0007aFA\u0001`\u0003E)f.\u0019:z)\u000e\u001buN\\:ue\u0006Lg\u000e\u001e\t\u0003Q\t\u0019BAA\b8uA\u0011\u0001\u0006O\u0005\u0003s)\u0011A\u0004T8x!JLwN]5usVs\u0017M]=U\u0007\u000e{gn\u001d;sC&tG\u000f\u0005\u0002<\u00016\tAH\u0003\u0002>}\u0005\u0011\u0011n\u001c\u0006\u0002\u007f\u0005!!.\u0019<b\u0013\tyB(\u0001\u0004=S:LGO\u0010\u000b\u0002k\u0005)\u0011\r\u001d9msV\u0019Q)S&\u0015\u0005\u0019s\u0005\u0003\u0002\u0015\u0001\u000f*\u0003\"\u0001S%\r\u0001\u0011)!\u0005\u0002b\u0001GA\u0011\u0001j\u0013\u0003\u0006Y\u0011\u0011\r\u0001T\u000b\u0003]5#QaM&C\u00029BQa\u0014\u0003A\u0004\u0019\u000bA!\u001e;dG\nQB\u0005^5nKN$S.\u001b8vg\u0012:\'/Z1uKJ$C/[7fgV\u0011!\u000b\u0018\n\u0003\'>1A\u0001\u0016\u0002\u0001%\naAH]3gS:,W.\u001a8u}\u0015!ak\u0015\u0001X\u0005\tq=8\u0006\u0002Y5B!\u0001\u0006A-\\!\tA%\fB\u0003#+\n\u00071\u0005\u0005\u0002I9\u0012)A&\u0002b\u0001;V\u0011aF\u0018\u0003\u0006gq\u0013\rAL\u0001\u0011Q:LGnQ8ogR,f.\u0019:z)\u000e+\"!\u00196\u0016\u0003\t\u00142aY\be\r\u0011!f\u0001\u00012\u0011\t!\u0002Q\r\u001b\t\u0003Q\u0019L!a\u001a\u0006\u0003\t!s\u0015\u000e\\\u000b\u0003S2\u0004\"\u0001\u00136\u0005\u000b-4!\u0019\u0001\u0018\u0003\u0003!#Q!\u001c8C\u00029\u0012\u0011\u0001\u0016\u0005\u0005_B\u0004q/\u0001\u0006=Y>\u001c\u0017\r\u001c\u0011Ox{*AAV9\u0001i\u001a!A\u000b\u0001\u0001t\u0015\ti\"B\u0005\u0002r\u001fU\u0011QO\u001e\t\u0003\u0011*$Q!\u001c9C\u00029Z\u0001!\u0001\u0007iY&\u001cH/\u00168bef$6)F\u0004{\u0003\u001b\t\t\"!\u0002\u0015\u0007m\f)BE\u0002}\u001fu4A\u0001V\u0004\u0001wB)\u0001\u0006\u0001@\u0002\u0014A1\u0001f`A\u0002\u0003\u001fI1!!\u0001\u000b\u00051!3m\u001c7p]\u0012\u001aw\u000e\\8o!\u0015A\u0015QAA\u0006\t\u0019asA1\u0001\u0002\bU\u0019a&!\u0003\u0005\rM\n)A1\u0001/!\rA\u0015Q\u0002\u0003\u0006W\u001e\u0011\rA\f\t\u0004\u0011\u0006EA!B7\b\u0005\u0004\u0019\u0003c\u0001%\u0002\u0006!9\u0011qC\u0004A\u0004\u0005e\u0011\u0001B;uGR\u0004b\u0001\u000b\u0001\u0002\u0010\u0005M\u0011\u0001D<sSR,\'+\u001a9mC\u000e,GCAA\u0010!\u0011\t\t#a\n\u000e\u0005\u0005\r\"bAA\u0013}\u0005!A.\u00198h\u0013\u0011\tI#a\t\u0003\r=\u0013\'.Z2u\u0001"
    )
  ScalaInlineInfo: length = 0x4 (unknown attribute)
   01 00 00 00
  ScalaSig: length = 0x3 (unknown attribute)
   05 02 00
