Classfile /Users/mw/Projects/slang-braindump/.jar/jar11/assemble/slang-braindump/assemble/content/shapeless/Unpack2.class
  Last modified May 29, 2022; size 994 bytes
  SHA-256 checksum 2e83e73299875804686e2009c0b8262fd778edcf79983ef43ad8e981b6ce3bbc
  Compiled from "unpack.scala"
public interface shapeless.Unpack2<PP extends java.lang.Object, FF extends java.lang.Object, A extends java.lang.Object, B extends java.lang.Object>
  minor version: 0
  major version: 52
  flags: (0x0601) ACC_PUBLIC, ACC_INTERFACE, ACC_ABSTRACT
  this_class: #2                          // shapeless/Unpack2
  super_class: #5                         // java/lang/Object
  interfaces: 0, fields: 0, methods: 1, attributes: 5
Constant pool:
   #1 = Utf8               shapeless/Unpack2
   #2 = Class              #1             // shapeless/Unpack2
   #3 = Utf8               <PP:Ljava/lang/Object;FF:Ljava/lang/Object;A:Ljava/lang/Object;B:Ljava/lang/Object;>Ljava/lang/Object;
   #4 = Utf8               java/lang/Object
   #5 = Class              #4             // java/lang/Object
   #6 = Utf8               unpack.scala
   #7 = Utf8               Lscala/reflect/ScalaSignature;
   #8 = Utf8               bytes
   #9 = Utf8               \u0006\u0005e2q!\u0002\u0004\u0011\u0002G\u0005\u0011bB\u0003%\r!\u0005QEB\u0003\u0006\r!\u0005q\u0005C\u0003)\u0005\u0011\u0005\u0011\u0006C\u0003+\u0005\u0011\r1FA\u0004V]B\f7m\u001b\u001a\u000b\u0003\u001d\t\u0011b\u001d5ba\u0016dWm]:\u0004\u0001U)!\"\u0005\u000e!EM\u0011\u0001a\u0003\t\u0003\u0019=i\u0011!\u0004\u0006\u0002\u001d\u0005)1oY1mC&\u0011\u0001#\u0004\u0002\u0007\u0003:L(+\u001a4\u0005\rI\u0001\u0001R1\u0001\u0014\u0005\t\u0001\u0006+\u0005\u0002\u0015/A\u0011A\"F\u0005\u0003-5\u0011qAT8uQ&tw\r\u0005\u0002\r1%\u0011\u0011$\u0004\u0002\u0004\u0003:LH!B\u000e\u0001\u0005\u0004a\"A\u0001$G+\r\u0019Rd\b\u0003\u0006=i\u0011\ra\u0005\u0002\u0002?\u0012)aD\u0007b\u0001\'\u0011)\u0011\u0005\u0001b\u0001\'\t\t\u0011\tB\u0003$\u0001\t\u00071CA\u0001C\u0003\u001d)f\u000e]1dWJ\u0002\"A\n\u0002\u000e\u0003\u0019\u0019\"AA\u0006\u0002\rqJg.\u001b;?)\u0005)\u0013AB;oa\u0006\u001c7.\u0006\u0003-aU:T#A\u0017\u0011\r\u0019\u0002a\u0006\u000f\u001b7!\u0011y\u0003\u0007\u000e\u001c\r\u0001\u0011)1\u0004\u0002b\u0001cU\u00191CM\u001a\u0005\u000by\u0001$\u0019A\n\u0005\u000by\u0001$\u0019A\n\u0011\u0005=*D!B\u0011\u0005\u0005\u0004\u0019\u0002CA\u00188\t\u0015\u0019CA1\u0001\u0014!\ty\u0003\u0007
  #10 = Utf8               unpack
  #11 = Utf8               ()Lshapeless/Unpack2;
  #12 = Utf8               <FF:Ljava/lang/Object;A:Ljava/lang/Object;B:Ljava/lang/Object;>()Lshapeless/Unpack2<TFF;TFF;TA;TB;>;
  #13 = Utf8               shapeless/Unpack2$
  #14 = Class              #13            // shapeless/Unpack2$
  #15 = Utf8               MODULE$
  #16 = Utf8               Lshapeless/Unpack2$;
  #17 = NameAndType        #15:#16        // MODULE$:Lshapeless/Unpack2$;
  #18 = Fieldref           #14.#17        // shapeless/Unpack2$.MODULE$:Lshapeless/Unpack2$;
  #19 = NameAndType        #10:#11        // unpack:()Lshapeless/Unpack2;
  #20 = Methodref          #14.#19        // shapeless/Unpack2$.unpack:()Lshapeless/Unpack2;
  #21 = Utf8               Code
  #22 = Utf8               Signature
  #23 = Utf8               SourceFile
  #24 = Utf8               RuntimeVisibleAnnotations
  #25 = Utf8               ScalaInlineInfo
  #26 = Utf8               ScalaSig
{
  public static <FF extends java.lang.Object, A extends java.lang.Object, B extends java.lang.Object> shapeless.Unpack2<FF, FF, A, B> unpack();
    descriptor: ()Lshapeless/Unpack2;
    flags: (0x0009) ACC_PUBLIC, ACC_STATIC
    Code:
      stack=1, locals=0, args_size=0
         0: getstatic     #18                 // Field shapeless/Unpack2$.MODULE$:Lshapeless/Unpack2$;
         3: invokevirtual #20                 // Method shapeless/Unpack2$.unpack:()Lshapeless/Unpack2;
         6: areturn
    Signature: #12                          // <FF:Ljava/lang/Object;A:Ljava/lang/Object;B:Ljava/lang/Object;>()Lshapeless/Unpack2<TFF;TFF;TA;TB;>;
}
Signature: #3                           // <PP:Ljava/lang/Object;FF:Ljava/lang/Object;A:Ljava/lang/Object;B:Ljava/lang/Object;>Ljava/lang/Object;
SourceFile: "unpack.scala"
RuntimeVisibleAnnotations:
  0: #7(#8=s#9)
    scala.reflect.ScalaSignature(
      bytes="\u0006\u0005e2q!\u0002\u0004\u0011\u0002G\u0005\u0011bB\u0003%\r!\u0005QEB\u0003\u0006\r!\u0005q\u0005C\u0003)\u0005\u0011\u0005\u0011\u0006C\u0003+\u0005\u0011\r1FA\u0004V]B\f7m\u001b\u001a\u000b\u0003\u001d\t\u0011b\u001d5ba\u0016dWm]:\u0004\u0001U)!\"\u0005\u000e!EM\u0011\u0001a\u0003\t\u0003\u0019=i\u0011!\u0004\u0006\u0002\u001d\u0005)1oY1mC&\u0011\u0001#\u0004\u0002\u0007\u0003:L(+\u001a4\u0005\rI\u0001\u0001R1\u0001\u0014\u0005\t\u0001\u0006+\u0005\u0002\u0015/A\u0011A\"F\u0005\u0003-5\u0011qAT8uQ&tw\r\u0005\u0002\r1%\u0011\u0011$\u0004\u0002\u0004\u0003:LH!B\u000e\u0001\u0005\u0004a\"A\u0001$G+\r\u0019Rd\b\u0003\u0006=i\u0011\ra\u0005\u0002\u0002?\u0012)aD\u0007b\u0001\'\u0011)\u0011\u0005\u0001b\u0001\'\t\t\u0011\tB\u0003$\u0001\t\u00071CA\u0001C\u0003\u001d)f\u000e]1dWJ\u0002\"A\n\u0002\u000e\u0003\u0019\u0019\"AA\u0006\u0002\rqJg.\u001b;?)\u0005)\u0013AB;oa\u0006\u001c7.\u0006\u0003-aU:T#A\u0017\u0011\r\u0019\u0002a\u0006\u000f\u001b7!\u0011y\u0003\u0007\u000e\u001c\r\u0001\u0011)1\u0004\u0002b\u0001cU\u00191CM\u001a\u0005\u000by\u0001$\u0019A\n\u0005\u000by\u0001$\u0019A\n\u0011\u0005=*D!B\u0011\u0005\u0005\u0004\u0019\u0002CA\u00188\t\u0015\u0019CA1\u0001\u0014!\ty\u0003\u0007"
    )
  ScalaInlineInfo: length = 0x4 (unknown attribute)
   01 00 00 00
  ScalaSig: length = 0x3 (unknown attribute)
   05 02 00
