Classfile /Users/mw/Projects/slang-braindump/.jar/jar11/assemble/slang-braindump/assemble/content/shapeless/Unpack18.class
  Last modified May 29, 2022; size 2496 bytes
  SHA-256 checksum c4d9d00864bb1dc07fe75e4e9b669f611e475a07c7f51f8d6873043f2f95b9ca
  Compiled from "unpack.scala"
public interface shapeless.Unpack18<PP extends java.lang.Object, FF extends java.lang.Object, A extends java.lang.Object, B extends java.lang.Object, C extends java.lang.Object, D extends java.lang.Object, E extends java.lang.Object, F extends java.lang.Object, G extends java.lang.Object, H extends java.lang.Object, I extends java.lang.Object, J extends java.lang.Object, K extends java.lang.Object, L extends java.lang.Object, M extends java.lang.Object, N extends java.lang.Object, O extends java.lang.Object, P extends java.lang.Object, Q extends java.lang.Object, R extends java.lang.Object>
  minor version: 0
  major version: 52
  flags: (0x0601) ACC_PUBLIC, ACC_INTERFACE, ACC_ABSTRACT
  this_class: #2                          // shapeless/Unpack18
  super_class: #5                         // java/lang/Object
  interfaces: 0, fields: 0, methods: 1, attributes: 5
Constant pool:
   #1 = Utf8               shapeless/Unpack18
   #2 = Class              #1             // shapeless/Unpack18
   #3 = Utf8               <PP:Ljava/lang/Object;FF:Ljava/lang/Object;A:Ljava/lang/Object;B:Ljava/lang/Object;C:Ljava/lang/Object;D:Ljava/lang/Object;E:Ljava/lang/Object;F:Ljava/lang/Object;G:Ljava/lang/Object;H:Ljava/lang/Object;I:Ljava/lang/Object;J:Ljava/lang/Object;K:Ljava/lang/Object;L:Ljava/lang/Object;M:Ljava/lang/Object;N:Ljava/lang/Object;O:Ljava/lang/Object;P:Ljava/lang/Object;Q:Ljava/lang/Object;R:Ljava/lang/Object;>Ljava/lang/Object;
   #4 = Utf8               java/lang/Object
   #5 = Class              #4             // java/lang/Object
   #6 = Utf8               unpack.scala
   #7 = Utf8               Lscala/reflect/ScalaSignature;
   #8 = Utf8               bytes
   #9 = Utf8               \u0006\u0005\u0005MbaB\u0003\u0007!\u0003\r\n!C\u0004\u0006)\u001aA\t!\u0016\u0004\u0006\u000b\u0019A\ta\u0016\u0005\u00061\n!\t!\u0017\u0005\u00065\n!\u0019a\u0017\u0002\t+:\u0004\u0018mY62q)\tq!A\u0005tQ\u0006\u0004X\r\\3tg\u000e\u0001Q#\u0006\u0006\u00125A\u0012DG\u000e\u001d;yy\u0002%\t\u0012$I\u00152s\u0005KU\n\u0003\u0001-\u0001\"\u0001D\b\u000e\u00035Q\u0011AD\u0001\u0006g\u000e\fG.Y\u0005\u0003!5\u0011a!\u00118z%\u00164GA\u0002\n\u0001\u0011\u000b\u00071C\u0001\u0002Q!F\u0011Ac\u0006\t\u0003\u0019UI!AF\u0007\u0003\u000f9{G\u000f[5oOB\u0011A\u0002G\u0005\u000335\u00111!\u00118z\t\u0015Y\u0002A1\u0001\u001d\u0005\t1e)F\n\u0014;}\u0001\u0013EI\u0012%K\u0019:\u0003&\u000b\u0016,Y5rs\u0006B\u0003\u001f5\t\u00071CA\u0001`\t\u0015q\"D1\u0001\u0014\t\u0015q\"D1\u0001\u0014\t\u0015q\"D1\u0001\u0014\t\u0015q\"D1\u0001\u0014\t\u0015q\"D1\u0001\u0014\t\u0015q\"D1\u0001\u0014\t\u0015q\"D1\u0001\u0014\t\u0015q\"D1\u0001\u0014\t\u0015q\"D1\u0001\u0014\t\u0015q\"D1\u0001\u0014\t\u0015q\"D1\u0001\u0014\t\u0015q\"D1\u0001\u0014\t\u0015q\"D1\u0001\u0014\t\u0015q\"D1\u0001\u0014\t\u0015q\"D1\u0001\u0014\t\u0015q\"D1\u0001\u0014\t\u0015q\"D1\u0001\u0014\t\u0015\t\u0004A1\u0001\u0014\u0005\u0005\tE!B\u001a\u0001\u0005\u0004\u0019\"!\u0001\"\u0005\u000bU\u0002!\u0019A\n\u0003\u0003\r#Qa\u000e\u0001C\u0002M\u0011\u0011\u0001\u0012\u0003\u0006s\u0001\u0011\ra\u0005\u0002\u0002\u000b\u0012)1\b\u0001b\u0001\'\t\ta\tB\u0003>\u0001\t\u00071CA\u0001H\t\u0015y\u0004A1\u0001\u0014\u0005\u0005AE!B!\u0001\u0005\u0004\u0019\"!A%\u0005\u000b\r\u0003!\u0019A\n\u0003\u0003)#Q!\u0012\u0001C\u0002M\u0011\u0011a\u0013\u0003\u0006\u000f\u0002\u0011\ra\u0005\u0002\u0002\u0019\u0012)\u0011\n\u0001b\u0001\'\t\tQ\nB\u0003L\u0001\t\u00071CA\u0001O\t\u0015i\u0005A1\u0001\u0014\u0005\u0005yE!B(\u0001\u0005\u0004\u0019\"!\u0001)\u0005\u000bE\u0003!\u0019A\n\u0003\u0003E#Qa\u0015\u0001C\u0002M\u0011\u0011AU\u0001\t+:\u0004\u0018mY62qA\u0011aKA\u0007\u0002\rM\u0011!aC\u0001\u0007y%t\u0017\u000e\u001e \u0015\u0003U\u000ba!\u001e8qC\u000e\\W\u0003\t/ak^L80`@\u0002\u0004\u0005\u001d\u00111BA\b\u0003\'\t9\"a\u0007\u0002 \u0005\r\u0012qEA\u0016\u0003_)\u0012!\u0018\t$-\u0002q\u0016\u0011\u0007;wqjdh0!\u0001\u0002\u0006\u0005%\u0011QBA\t\u0003+\tI\"!\b\u0002\"\u0005\u0015\u0012\u0011FA\u0017!\u0001z\u0006\r\u001e<yurt\u0018\u0011AA\u0003\u0003\u0013\ti!!\u0005\u0002\u0016\u0005e\u0011QDA\u0011\u0003K\tI#!\f\r\u0001\u0011)1\u0004\u0002b\u0001CV\u00192CY2eK\u001a<\u0007.\u001b6lY6tw\u000e]9sg\u0012)a\u0004\u0019b\u0001\'\u0011)a\u0004\u0019b\u0001\'\u0011)a\u0004\u0019b\u0001\'\u0011)a\u0004\u0019b\u0001\'\u0011)a\u0004\u0019b\u0001\'\u0011)a\u0004\u0019b\u0001\'\u0011)a\u0004\u0019b\u0001\'\u0011)a\u0004\u0019b\u0001\'\u0011)a\u0004\u0019b\u0001\'\u0011)a\u0004\u0019b\u0001\'\u0011)a\u0004\u0019b\u0001\'\u0011)a\u0004\u0019b\u0001\'\u0011)a\u0004\u0019b\u0001\'\u0011)a\u0004\u0019b\u0001\'\u0011)a\u0004\u0019b\u0001\'\u0011)a\u0004\u0019b\u0001\'\u0011)a\u0004\u0019b\u0001\'\u0011)a\u0004\u0019b\u0001\'A\u0011q,\u001e\u0003\u0006c\u0011\u0011\ra\u0005\t\u0003?^$Qa\r\u0003C\u0002M\u0001\"aX=\u0005\u000bU\"!\u0019A\n\u0011\u0005}[H!B\u001c\u0005\u0005\u0004\u0019\u0002CA0~\t\u0015IDA1\u0001\u0014!\tyv\u0010B\u0003<\t\t\u00071\u0003E\u0002`\u0003\u0007!Q!\u0010\u0003C\u0002M\u00012aXA\u0004\t\u0015yDA1\u0001\u0014!\ry\u00161\u0002\u0003\u0006\u0003\u0012\u0011\ra\u0005\t\u0004?\u0006=A!B\"\u0005\u0005\u0004\u0019\u0002cA0\u0002\u0014\u0011)Q\t\u0002b\u0001\'A\u0019q,a\u0006\u0005\u000b\u001d#!\u0019A\n\u0011\u0007}\u000bY\u0002B\u0003J\t\t\u00071\u0003E\u0002`\u0003?!Qa\u0013\u0003C\u0002M\u00012aXA\u0012\t\u0015iEA1\u0001\u0014!\ry\u0016q\u0005\u0003\u0006\u001f\u0012\u0011\ra\u0005\t\u0004?\u0006-B!B)\u0005\u0005\u0004\u0019\u0002cA0\u00020\u0011)1\u000b\u0002b\u0001\'A\u0011q\f\u0019
  #10 = Utf8               unpack
  #11 = Utf8               ()Lshapeless/Unpack18;
  #12 = Utf8               <FF:Ljava/lang/Object;A:Ljava/lang/Object;B:Ljava/lang/Object;C:Ljava/lang/Object;D:Ljava/lang/Object;E:Ljava/lang/Object;F:Ljava/lang/Object;G:Ljava/lang/Object;H:Ljava/lang/Object;I:Ljava/lang/Object;J:Ljava/lang/Object;K:Ljava/lang/Object;L:Ljava/lang/Object;M:Ljava/lang/Object;N:Ljava/lang/Object;O:Ljava/lang/Object;P:Ljava/lang/Object;Q:Ljava/lang/Object;R:Ljava/lang/Object;>()Lshapeless/Unpack18<TFF;TFF;TA;TB;TC;TD;TE;TF;TG;TH;TI;TJ;TK;TL;TM;TN;TO;TP;TQ;TR;>;
  #13 = Utf8               shapeless/Unpack18$
  #14 = Class              #13            // shapeless/Unpack18$
  #15 = Utf8               MODULE$
  #16 = Utf8               Lshapeless/Unpack18$;
  #17 = NameAndType        #15:#16        // MODULE$:Lshapeless/Unpack18$;
  #18 = Fieldref           #14.#17        // shapeless/Unpack18$.MODULE$:Lshapeless/Unpack18$;
  #19 = NameAndType        #10:#11        // unpack:()Lshapeless/Unpack18;
  #20 = Methodref          #14.#19        // shapeless/Unpack18$.unpack:()Lshapeless/Unpack18;
  #21 = Utf8               Code
  #22 = Utf8               Signature
  #23 = Utf8               SourceFile
  #24 = Utf8               RuntimeVisibleAnnotations
  #25 = Utf8               ScalaInlineInfo
  #26 = Utf8               ScalaSig
{
  public static <FF extends java.lang.Object, A extends java.lang.Object, B extends java.lang.Object, C extends java.lang.Object, D extends java.lang.Object, E extends java.lang.Object, F extends java.lang.Object, G extends java.lang.Object, H extends java.lang.Object, I extends java.lang.Object, J extends java.lang.Object, K extends java.lang.Object, L extends java.lang.Object, M extends java.lang.Object, N extends java.lang.Object, O extends java.lang.Object, P extends java.lang.Object, Q extends java.lang.Object, R extends java.lang.Object> shapeless.Unpack18<FF, FF, A, B, C, D, E, F, G, H, I, J, K, L, M, N, O, P, Q, R> unpack();
    descriptor: ()Lshapeless/Unpack18;
    flags: (0x0009) ACC_PUBLIC, ACC_STATIC
    Code:
      stack=1, locals=0, args_size=0
         0: getstatic     #18                 // Field shapeless/Unpack18$.MODULE$:Lshapeless/Unpack18$;
         3: invokevirtual #20                 // Method shapeless/Unpack18$.unpack:()Lshapeless/Unpack18;
         6: areturn
    Signature: #12                          // <FF:Ljava/lang/Object;A:Ljava/lang/Object;B:Ljava/lang/Object;C:Ljava/lang/Object;D:Ljava/lang/Object;E:Ljava/lang/Object;F:Ljava/lang/Object;G:Ljava/lang/Object;H:Ljava/lang/Object;I:Ljava/lang/Object;J:Ljava/lang/Object;K:Ljava/lang/Object;L:Ljava/lang/Object;M:Ljava/lang/Object;N:Ljava/lang/Object;O:Ljava/lang/Object;P:Ljava/lang/Object;Q:Ljava/lang/Object;R:Ljava/lang/Object;>()Lshapeless/Unpack18<TFF;TFF;TA;TB;TC;TD;TE;TF;TG;TH;TI;TJ;TK;TL;TM;TN;TO;TP;TQ;TR;>;
}
Signature: #3                           // <PP:Ljava/lang/Object;FF:Ljava/lang/Object;A:Ljava/lang/Object;B:Ljava/lang/Object;C:Ljava/lang/Object;D:Ljava/lang/Object;E:Ljava/lang/Object;F:Ljava/lang/Object;G:Ljava/lang/Object;H:Ljava/lang/Object;I:Ljava/lang/Object;J:Ljava/lang/Object;K:Ljava/lang/Object;L:Ljava/lang/Object;M:Ljava/lang/Object;N:Ljava/lang/Object;O:Ljava/lang/Object;P:Ljava/lang/Object;Q:Ljava/lang/Object;R:Ljava/lang/Object;>Ljava/lang/Object;
SourceFile: "unpack.scala"
RuntimeVisibleAnnotations:
  0: #7(#8=s#9)
    scala.reflect.ScalaSignature(
      bytes="\u0006\u0005\u0005MbaB\u0003\u0007!\u0003\r\n!C\u0004\u0006)\u001aA\t!\u0016\u0004\u0006\u000b\u0019A\ta\u0016\u0005\u00061\n!\t!\u0017\u0005\u00065\n!\u0019a\u0017\u0002\t+:\u0004\u0018mY62q)\tq!A\u0005tQ\u0006\u0004X\r\\3tg\u000e\u0001Q#\u0006\u0006\u00125A\u0012DG\u000e\u001d;yy\u0002%\t\u0012$I\u00152s\u0005KU\n\u0003\u0001-\u0001\"\u0001D\b\u000e\u00035Q\u0011AD\u0001\u0006g\u000e\fG.Y\u0005\u0003!5\u0011a!\u00118z%\u00164GA\u0002\n\u0001\u0011\u000b\u00071C\u0001\u0002Q!F\u0011Ac\u0006\t\u0003\u0019UI!AF\u0007\u0003\u000f9{G\u000f[5oOB\u0011A\u0002G\u0005\u000335\u00111!\u00118z\t\u0015Y\u0002A1\u0001\u001d\u0005\t1e)F\n\u0014;}\u0001\u0013EI\u0012%K\u0019:\u0003&\u000b\u0016,Y5rs\u0006B\u0003\u001f5\t\u00071CA\u0001`\t\u0015q\"D1\u0001\u0014\t\u0015q\"D1\u0001\u0014\t\u0015q\"D1\u0001\u0014\t\u0015q\"D1\u0001\u0014\t\u0015q\"D1\u0001\u0014\t\u0015q\"D1\u0001\u0014\t\u0015q\"D1\u0001\u0014\t\u0015q\"D1\u0001\u0014\t\u0015q\"D1\u0001\u0014\t\u0015q\"D1\u0001\u0014\t\u0015q\"D1\u0001\u0014\t\u0015q\"D1\u0001\u0014\t\u0015q\"D1\u0001\u0014\t\u0015q\"D1\u0001\u0014\t\u0015q\"D1\u0001\u0014\t\u0015q\"D1\u0001\u0014\t\u0015q\"D1\u0001\u0014\t\u0015\t\u0004A1\u0001\u0014\u0005\u0005\tE!B\u001a\u0001\u0005\u0004\u0019\"!\u0001\"\u0005\u000bU\u0002!\u0019A\n\u0003\u0003\r#Qa\u000e\u0001C\u0002M\u0011\u0011\u0001\u0012\u0003\u0006s\u0001\u0011\ra\u0005\u0002\u0002\u000b\u0012)1\b\u0001b\u0001\'\t\ta\tB\u0003>\u0001\t\u00071CA\u0001H\t\u0015y\u0004A1\u0001\u0014\u0005\u0005AE!B!\u0001\u0005\u0004\u0019\"!A%\u0005\u000b\r\u0003!\u0019A\n\u0003\u0003)#Q!\u0012\u0001C\u0002M\u0011\u0011a\u0013\u0003\u0006\u000f\u0002\u0011\ra\u0005\u0002\u0002\u0019\u0012)\u0011\n\u0001b\u0001\'\t\tQ\nB\u0003L\u0001\t\u00071CA\u0001O\t\u0015i\u0005A1\u0001\u0014\u0005\u0005yE!B(\u0001\u0005\u0004\u0019\"!\u0001)\u0005\u000bE\u0003!\u0019A\n\u0003\u0003E#Qa\u0015\u0001C\u0002M\u0011\u0011AU\u0001\t+:\u0004\u0018mY62qA\u0011aKA\u0007\u0002\rM\u0011!aC\u0001\u0007y%t\u0017\u000e\u001e \u0015\u0003U\u000ba!\u001e8qC\u000e\\W\u0003\t/ak^L80`@\u0002\u0004\u0005\u001d\u00111BA\b\u0003\'\t9\"a\u0007\u0002 \u0005\r\u0012qEA\u0016\u0003_)\u0012!\u0018\t$-\u0002q\u0016\u0011\u0007;wqjdh0!\u0001\u0002\u0006\u0005%\u0011QBA\t\u0003+\tI\"!\b\u0002\"\u0005\u0015\u0012\u0011FA\u0017!\u0001z\u0006\r\u001e<yurt\u0018\u0011AA\u0003\u0003\u0013\ti!!\u0005\u0002\u0016\u0005e\u0011QDA\u0011\u0003K\tI#!\f\r\u0001\u0011)1\u0004\u0002b\u0001CV\u00192CY2eK\u001a<\u0007.\u001b6lY6tw\u000e]9sg\u0012)a\u0004\u0019b\u0001\'\u0011)a\u0004\u0019b\u0001\'\u0011)a\u0004\u0019b\u0001\'\u0011)a\u0004\u0019b\u0001\'\u0011)a\u0004\u0019b\u0001\'\u0011)a\u0004\u0019b\u0001\'\u0011)a\u0004\u0019b\u0001\'\u0011)a\u0004\u0019b\u0001\'\u0011)a\u0004\u0019b\u0001\'\u0011)a\u0004\u0019b\u0001\'\u0011)a\u0004\u0019b\u0001\'\u0011)a\u0004\u0019b\u0001\'\u0011)a\u0004\u0019b\u0001\'\u0011)a\u0004\u0019b\u0001\'\u0011)a\u0004\u0019b\u0001\'\u0011)a\u0004\u0019b\u0001\'\u0011)a\u0004\u0019b\u0001\'\u0011)a\u0004\u0019b\u0001\'A\u0011q,\u001e\u0003\u0006c\u0011\u0011\ra\u0005\t\u0003?^$Qa\r\u0003C\u0002M\u0001\"aX=\u0005\u000bU\"!\u0019A\n\u0011\u0005}[H!B\u001c\u0005\u0005\u0004\u0019\u0002CA0~\t\u0015IDA1\u0001\u0014!\tyv\u0010B\u0003<\t\t\u00071\u0003E\u0002`\u0003\u0007!Q!\u0010\u0003C\u0002M\u00012aXA\u0004\t\u0015yDA1\u0001\u0014!\ry\u00161\u0002\u0003\u0006\u0003\u0012\u0011\ra\u0005\t\u0004?\u0006=A!B\"\u0005\u0005\u0004\u0019\u0002cA0\u0002\u0014\u0011)Q\t\u0002b\u0001\'A\u0019q,a\u0006\u0005\u000b\u001d#!\u0019A\n\u0011\u0007}\u000bY\u0002B\u0003J\t\t\u00071\u0003E\u0002`\u0003?!Qa\u0013\u0003C\u0002M\u00012aXA\u0012\t\u0015iEA1\u0001\u0014!\ry\u0016q\u0005\u0003\u0006\u001f\u0012\u0011\ra\u0005\t\u0004?\u0006-B!B)\u0005\u0005\u0004\u0019\u0002cA0\u00020\u0011)1\u000b\u0002b\u0001\'A\u0011q\f\u0019"
    )
  ScalaInlineInfo: length = 0x4 (unknown attribute)
   01 00 00 00
  ScalaSig: length = 0x3 (unknown attribute)
   05 02 00
