Classfile /Users/mw/Projects/slang-braindump/.jar/jar11/assemble/slang-braindump/assemble/content/shapeless/Unpack3.class
  Last modified May 29, 2022; size 1084 bytes
  SHA-256 checksum 24fcd19b72b2c31a4ad6cd5b7bd85af5d9541349f654007ed03cf8f5e5a87cb2
  Compiled from "unpack.scala"
public interface shapeless.Unpack3<PP extends java.lang.Object, FF extends java.lang.Object, A extends java.lang.Object, B extends java.lang.Object, C extends java.lang.Object>
  minor version: 0
  major version: 52
  flags: (0x0601) ACC_PUBLIC, ACC_INTERFACE, ACC_ABSTRACT
  this_class: #2                          // shapeless/Unpack3
  super_class: #5                         // java/lang/Object
  interfaces: 0, fields: 0, methods: 1, attributes: 5
Constant pool:
   #1 = Utf8               shapeless/Unpack3
   #2 = Class              #1             // shapeless/Unpack3
   #3 = Utf8               <PP:Ljava/lang/Object;FF:Ljava/lang/Object;A:Ljava/lang/Object;B:Ljava/lang/Object;C:Ljava/lang/Object;>Ljava/lang/Object;
   #4 = Utf8               java/lang/Object
   #5 = Class              #4             // java/lang/Object
   #6 = Utf8               unpack.scala
   #7 = Utf8               Lscala/reflect/ScalaSignature;
   #8 = Utf8               bytes
   #9 = Utf8               \u0006\u0005}2q!\u0002\u0004\u0011\u0002G\u0005\u0011bB\u0003(\r!\u0005\u0001FB\u0003\u0006\r!\u0005!\u0006C\u0003,\u0005\u0011\u0005A\u0006C\u0003.\u0005\u0011\raFA\u0004V]B\f7m[\u001a\u000b\u0003\u001d\t\u0011b\u001d5ba\u0016dWm]:\u0004\u0001U1!\"\u0005\u000e\"G\u0015\u001a\"\u0001A\u0006\u0011\u00051yQ\"A\u0007\u000b\u00039\tQa]2bY\u0006L!\u0001E\u0007\u0003\r\u0005s\u0017PU3g\t\u0019\u0011\u0002\u0001#b\u0001\'\t\u0011\u0001\u000bU\t\u0003)]\u0001\"\u0001D\u000b\n\u0005Yi!a\u0002(pi\"Lgn\u001a\t\u0003\u0019aI!!G\u0007\u0003\u0007\u0005s\u0017\u0010B\u0003\u001c\u0001\t\u0007AD\u0001\u0002G\rV!1#H\u0010!\t\u0015q\"D1\u0001\u0014\u0005\u0005yF!\u0002\u0010\u001b\u0005\u0004\u0019B!\u0002\u0010\u001b\u0005\u0004\u0019B!\u0002\u0012\u0001\u0005\u0004\u0019\"!A!\u0005\u000b\u0011\u0002!\u0019A\n\u0003\u0003\t#QA\n\u0001C\u0002M\u0011\u0011aQ\u0001\b+:\u0004\u0018mY64!\tI#!D\u0001\u0007\'\t\u00111\"\u0001\u0004=S:LGO\u0010\u000b\u0002Q\u00051QO\u001c9bG.,RaL\u001a:wu*\u0012\u0001\r\t\bS\u0001\td\b\u000f\u001e=!\u0015\u00114\u0007\u000f\u001e=\u0019\u0001!Qa\u0007\u0003C\u0002Q*BaE\u001b7o\u0011)ad\rb\u0001\'\u0011)ad\rb\u0001\'\u0011)ad\rb\u0001\'A\u0011!\'\u000f\u0003\u0006E\u0011\u0011\ra\u0005\t\u0003em\"Q\u0001\n\u0003C\u0002M\u0001\"AM\u001f\u0005\u000b\u0019\"!\u0019A\n\u0011\u0005I\u001a\u0004
  #10 = Utf8               unpack
  #11 = Utf8               ()Lshapeless/Unpack3;
  #12 = Utf8               <FF:Ljava/lang/Object;A:Ljava/lang/Object;B:Ljava/lang/Object;C:Ljava/lang/Object;>()Lshapeless/Unpack3<TFF;TFF;TA;TB;TC;>;
  #13 = Utf8               shapeless/Unpack3$
  #14 = Class              #13            // shapeless/Unpack3$
  #15 = Utf8               MODULE$
  #16 = Utf8               Lshapeless/Unpack3$;
  #17 = NameAndType        #15:#16        // MODULE$:Lshapeless/Unpack3$;
  #18 = Fieldref           #14.#17        // shapeless/Unpack3$.MODULE$:Lshapeless/Unpack3$;
  #19 = NameAndType        #10:#11        // unpack:()Lshapeless/Unpack3;
  #20 = Methodref          #14.#19        // shapeless/Unpack3$.unpack:()Lshapeless/Unpack3;
  #21 = Utf8               Code
  #22 = Utf8               Signature
  #23 = Utf8               SourceFile
  #24 = Utf8               RuntimeVisibleAnnotations
  #25 = Utf8               ScalaInlineInfo
  #26 = Utf8               ScalaSig
{
  public static <FF extends java.lang.Object, A extends java.lang.Object, B extends java.lang.Object, C extends java.lang.Object> shapeless.Unpack3<FF, FF, A, B, C> unpack();
    descriptor: ()Lshapeless/Unpack3;
    flags: (0x0009) ACC_PUBLIC, ACC_STATIC
    Code:
      stack=1, locals=0, args_size=0
         0: getstatic     #18                 // Field shapeless/Unpack3$.MODULE$:Lshapeless/Unpack3$;
         3: invokevirtual #20                 // Method shapeless/Unpack3$.unpack:()Lshapeless/Unpack3;
         6: areturn
    Signature: #12                          // <FF:Ljava/lang/Object;A:Ljava/lang/Object;B:Ljava/lang/Object;C:Ljava/lang/Object;>()Lshapeless/Unpack3<TFF;TFF;TA;TB;TC;>;
}
Signature: #3                           // <PP:Ljava/lang/Object;FF:Ljava/lang/Object;A:Ljava/lang/Object;B:Ljava/lang/Object;C:Ljava/lang/Object;>Ljava/lang/Object;
SourceFile: "unpack.scala"
RuntimeVisibleAnnotations:
  0: #7(#8=s#9)
    scala.reflect.ScalaSignature(
      bytes="\u0006\u0005}2q!\u0002\u0004\u0011\u0002G\u0005\u0011bB\u0003(\r!\u0005\u0001FB\u0003\u0006\r!\u0005!\u0006C\u0003,\u0005\u0011\u0005A\u0006C\u0003.\u0005\u0011\raFA\u0004V]B\f7m[\u001a\u000b\u0003\u001d\t\u0011b\u001d5ba\u0016dWm]:\u0004\u0001U1!\"\u0005\u000e\"G\u0015\u001a\"\u0001A\u0006\u0011\u00051yQ\"A\u0007\u000b\u00039\tQa]2bY\u0006L!\u0001E\u0007\u0003\r\u0005s\u0017PU3g\t\u0019\u0011\u0002\u0001#b\u0001\'\t\u0011\u0001\u000bU\t\u0003)]\u0001\"\u0001D\u000b\n\u0005Yi!a\u0002(pi\"Lgn\u001a\t\u0003\u0019aI!!G\u0007\u0003\u0007\u0005s\u0017\u0010B\u0003\u001c\u0001\t\u0007AD\u0001\u0002G\rV!1#H\u0010!\t\u0015q\"D1\u0001\u0014\u0005\u0005yF!\u0002\u0010\u001b\u0005\u0004\u0019B!\u0002\u0010\u001b\u0005\u0004\u0019B!\u0002\u0012\u0001\u0005\u0004\u0019\"!A!\u0005\u000b\u0011\u0002!\u0019A\n\u0003\u0003\t#QA\n\u0001C\u0002M\u0011\u0011aQ\u0001\b+:\u0004\u0018mY64!\tI#!D\u0001\u0007\'\t\u00111\"\u0001\u0004=S:LGO\u0010\u000b\u0002Q\u00051QO\u001c9bG.,RaL\u001a:wu*\u0012\u0001\r\t\bS\u0001\td\b\u000f\u001e=!\u0015\u00114\u0007\u000f\u001e=\u0019\u0001!Qa\u0007\u0003C\u0002Q*BaE\u001b7o\u0011)ad\rb\u0001\'\u0011)ad\rb\u0001\'\u0011)ad\rb\u0001\'A\u0011!\'\u000f\u0003\u0006E\u0011\u0011\ra\u0005\t\u0003em\"Q\u0001\n\u0003C\u0002M\u0001\"AM\u001f\u0005\u000b\u0019\"!\u0019A\n\u0011\u0005I\u001a\u0004"
    )
  ScalaInlineInfo: length = 0x4 (unknown attribute)
   01 00 00 00
  ScalaSig: length = 0x3 (unknown attribute)
   05 02 00
