Classfile /Users/mw/Projects/slang-braindump/.jar/jar11/assemble/slang-braindump/assemble/content/shapeless/Unwrapped$.class
  Last modified May 29, 2022; size 3909 bytes
  SHA-256 checksum e4a52020a329ed590baac17c3587c56afbc5aaef037e89e8fc4e498bfcdc9c85
  Compiled from "unwrapped.scala"
public final class shapeless.Unwrapped$ implements shapeless.UnwrappedInstances,java.io.Serializable
  minor version: 0
  major version: 52
  flags: (0x0031) ACC_PUBLIC, ACC_FINAL, ACC_SUPER
  this_class: #2                          // shapeless/Unwrapped$
  super_class: #4                         // java/lang/Object
  interfaces: 2, fields: 3, methods: 12, attributes: 4
Constant pool:
    #1 = Utf8               shapeless/Unwrapped$
    #2 = Class              #1            // shapeless/Unwrapped$
    #3 = Utf8               java/lang/Object
    #4 = Class              #3            // java/lang/Object
    #5 = Utf8               shapeless/UnwrappedInstances
    #6 = Class              #5            // shapeless/UnwrappedInstances
    #7 = Utf8               java/io/Serializable
    #8 = Class              #7            // java/io/Serializable
    #9 = Utf8               unwrapped.scala
   #10 = Utf8               shapeless/UnwrappedInstances$AnyValHelper
   #11 = Class              #10           // shapeless/UnwrappedInstances$AnyValHelper
   #12 = Utf8               AnyValHelper
   #13 = Utf8               shapeless/UnwrappedInstances$AnyValHelper$
   #14 = Class              #13           // shapeless/UnwrappedInstances$AnyValHelper$
   #15 = Utf8               AnyValHelper$
   #16 = Utf8               MODULE$
   #17 = Utf8               Lshapeless/Unwrapped$;
   #18 = Utf8               AnyValHelper$module
   #19 = Utf8               Lshapeless/UnwrappedInstances$AnyValHelper$;
   #20 = Utf8               theSelfUnwrapped
   #21 = Utf8               Lshapeless/Unwrapped;
   #22 = Utf8               Lshapeless/Unwrapped<Ljava/lang/Object;>;
   #23 = Utf8               <clinit>
   #24 = Utf8               ()V
   #25 = Utf8               <init>
   #26 = NameAndType        #25:#24       // "<init>":()V
   #27 = Methodref          #2.#26        // shapeless/Unwrapped$."<init>":()V
   #28 = NameAndType        #16:#17       // MODULE$:Lshapeless/Unwrapped$;
   #29 = Fieldref           #2.#28        // shapeless/Unwrapped$.MODULE$:Lshapeless/Unwrapped$;
   #30 = Utf8               shapeless/LowPriorityUnwrappedInstances
   #31 = Class              #30           // shapeless/LowPriorityUnwrappedInstances
   #32 = Utf8               $init$
   #33 = Utf8               (Lshapeless/LowPriorityUnwrappedInstances;)V
   #34 = NameAndType        #32:#33       // $init$:(Lshapeless/LowPriorityUnwrappedInstances;)V
   #35 = InterfaceMethodref #31.#34       // shapeless/LowPriorityUnwrappedInstances.$init$:(Lshapeless/LowPriorityUnwrappedInstances;)V
   #36 = Utf8               (Lshapeless/UnwrappedInstances;)V
   #37 = NameAndType        #32:#36       // $init$:(Lshapeless/UnwrappedInstances;)V
   #38 = InterfaceMethodref #6.#37        // shapeless/UnwrappedInstances.$init$:(Lshapeless/UnwrappedInstances;)V
   #39 = Utf8               unwrapAnyVal
   #40 = Utf8               (Lshapeless/Generic;Lshapeless/UnwrappedInstances$AnyValHelper;Lshapeless/Strict;)Lshapeless/Unwrapped;
   #41 = Utf8               <W:Ljava/lang/Object;Repr:Ljava/lang/Object;UI:Ljava/lang/Object;UF:Ljava/lang/Object;>(Lshapeless/Generic<TW;>;Lshapeless/UnwrappedInstances$AnyValHelper<TRepr;>;Lshapeless/Strict<Lshapeless/Unwrapped<TUI;>;>;)Lshapeless/Unwrapped<TW;>;
   #42 = Utf8               gen
   #43 = Utf8               avh
   #44 = Utf8               chain
   #45 = Utf8               unwrapAnyVal$
   #46 = Utf8               (Lshapeless/UnwrappedInstances;Lshapeless/Generic;Lshapeless/UnwrappedInstances$AnyValHelper;Lshapeless/Strict;)Lshapeless/Unwrapped;
   #47 = NameAndType        #45:#46       // unwrapAnyVal$:(Lshapeless/UnwrappedInstances;Lshapeless/Generic;Lshapeless/UnwrappedInstances$AnyValHelper;Lshapeless/Strict;)Lshapeless/Unwrapped;
   #48 = InterfaceMethodref #6.#47        // shapeless/UnwrappedInstances.unwrapAnyVal$:(Lshapeless/UnwrappedInstances;Lshapeless/Generic;Lshapeless/UnwrappedInstances$AnyValHelper;Lshapeless/Strict;)Lshapeless/Unwrapped;
   #49 = Utf8               this
   #50 = Utf8               Lshapeless/Generic;
   #51 = Utf8               Lshapeless/UnwrappedInstances$AnyValHelper;
   #52 = Utf8               Lshapeless/Strict;
   #53 = Utf8               newtypeUnwrapped
   #54 = Utf8               (Lshapeless/Strict;)Lshapeless/Unwrapped;
   #55 = Utf8               <UI:Ljava/lang/Object;Ops:Ljava/lang/Object;UF:Ljava/lang/Object;>(Lshapeless/Strict<Lshapeless/Unwrapped<TUI;>;>;)Lshapeless/Unwrapped<Ljava/lang/Object;>;
   #56 = Utf8               newtypeUnwrapped$
   #57 = Utf8               (Lshapeless/UnwrappedInstances;Lshapeless/Strict;)Lshapeless/Unwrapped;
   #58 = NameAndType        #56:#57       // newtypeUnwrapped$:(Lshapeless/UnwrappedInstances;Lshapeless/Strict;)Lshapeless/Unwrapped;
   #59 = InterfaceMethodref #6.#58        // shapeless/UnwrappedInstances.newtypeUnwrapped$:(Lshapeless/UnwrappedInstances;Lshapeless/Strict;)Lshapeless/Unwrapped;
   #60 = Utf8               tagUnwrapped
   #61 = Utf8               <T:Ljava/lang/Object;UI:Ljava/lang/Object;TT:Ljava/lang/Object;UF:Ljava/lang/Object;>(Lshapeless/Strict<Lshapeless/Unwrapped<TUI;>;>;)Lshapeless/Unwrapped<TT;>;
   #62 = Utf8               tagUnwrapped$
   #63 = NameAndType        #62:#57       // tagUnwrapped$:(Lshapeless/UnwrappedInstances;Lshapeless/Strict;)Lshapeless/Unwrapped;
   #64 = InterfaceMethodref #6.#63        // shapeless/UnwrappedInstances.tagUnwrapped$:(Lshapeless/UnwrappedInstances;Lshapeless/Strict;)Lshapeless/Unwrapped;
   #65 = Utf8               selfUnwrapped
   #66 = Utf8               ()Lshapeless/Unwrapped;
   #67 = Utf8               <T:Ljava/lang/Object;>()Lshapeless/Unwrapped<TT;>;
   #68 = Utf8               selfUnwrapped$
   #69 = Utf8               (Lshapeless/LowPriorityUnwrappedInstances;)Lshapeless/Unwrapped;
   #70 = NameAndType        #68:#69       // selfUnwrapped$:(Lshapeless/LowPriorityUnwrappedInstances;)Lshapeless/Unwrapped;
   #71 = InterfaceMethodref #31.#70       // shapeless/LowPriorityUnwrappedInstances.selfUnwrapped$:(Lshapeless/LowPriorityUnwrappedInstances;)Lshapeless/Unwrapped;
   #72 = Utf8               ()Lshapeless/UnwrappedInstances$AnyValHelper$;
   #73 = NameAndType        #18:#19       // AnyValHelper$module:Lshapeless/UnwrappedInstances$AnyValHelper$;
   #74 = Fieldref           #2.#73        // shapeless/Unwrapped$.AnyValHelper$module:Lshapeless/UnwrappedInstances$AnyValHelper$;
   #75 = Utf8               AnyValHelper$lzycompute$1
   #76 = NameAndType        #75:#24       // AnyValHelper$lzycompute$1:()V
   #77 = Methodref          #2.#76        // shapeless/Unwrapped$.AnyValHelper$lzycompute$1:()V
   #78 = Utf8               ()Lshapeless/Unwrapped<Ljava/lang/Object;>;
   #79 = NameAndType        #20:#21       // theSelfUnwrapped:Lshapeless/Unwrapped;
   #80 = Fieldref           #2.#79        // shapeless/Unwrapped$.theSelfUnwrapped:Lshapeless/Unwrapped;
   #81 = Utf8               shapeless$LowPriorityUnwrappedInstances$_setter_$theSelfUnwrapped_$eq
   #82 = Utf8               (Lshapeless/Unwrapped;)V
   #83 = Utf8               (Lshapeless/Unwrapped<Ljava/lang/Object;>;)V
   #84 = Utf8               x$1
   #85 = Utf8               apply
   #86 = Utf8               (Lshapeless/Unwrapped;)Lshapeless/Unwrapped;
   #87 = Utf8               <W:Ljava/lang/Object;>(Lshapeless/Unwrapped<TW;>;)Lshapeless/Unwrapped<TW;>;
   #88 = Utf8               w
   #89 = Utf8               writeReplace
   #90 = Utf8               ()Ljava/lang/Object;
   #91 = Utf8               scala/runtime/ModuleSerializationProxy
   #92 = Class              #91           // scala/runtime/ModuleSerializationProxy
   #93 = Utf8               (Ljava/lang/Class;)V
   #94 = NameAndType        #25:#93       // "<init>":(Ljava/lang/Class;)V
   #95 = Methodref          #92.#94       // scala/runtime/ModuleSerializationProxy."<init>":(Ljava/lang/Class;)V
   #96 = NameAndType        #25:#36       // "<init>":(Lshapeless/UnwrappedInstances;)V
   #97 = Methodref          #14.#96       // shapeless/UnwrappedInstances$AnyValHelper$."<init>":(Lshapeless/UnwrappedInstances;)V
   #98 = Utf8               java/lang/Throwable
   #99 = Class              #98           // java/lang/Throwable
  #100 = Methodref          #4.#26        // java/lang/Object."<init>":()V
  #101 = Utf8               Signature
  #102 = Utf8               Code
  #103 = Utf8               LineNumberTable
  #104 = Utf8               LocalVariableTable
  #105 = Utf8               MethodParameters
  #106 = Utf8               StackMapTable
  #107 = Utf8               InnerClasses
  #108 = Utf8               SourceFile
  #109 = Utf8               ScalaInlineInfo
  #110 = Utf8               Scala
{
  public static final shapeless.Unwrapped$ MODULE$;
    descriptor: Lshapeless/Unwrapped$;
    flags: (0x0019) ACC_PUBLIC, ACC_STATIC, ACC_FINAL

  private static volatile shapeless.UnwrappedInstances$AnyValHelper$ AnyValHelper$module;
    descriptor: Lshapeless/UnwrappedInstances$AnyValHelper$;
    flags: (0x004a) ACC_PRIVATE, ACC_STATIC, ACC_VOLATILE

  private static shapeless.Unwrapped<java.lang.Object> theSelfUnwrapped;
    descriptor: Lshapeless/Unwrapped;
    flags: (0x000a) ACC_PRIVATE, ACC_STATIC
    Signature: #22                          // Lshapeless/Unwrapped<Ljava/lang/Object;>;

  public static {};
    descriptor: ()V
    flags: (0x0009) ACC_PUBLIC, ACC_STATIC
    Code:
      stack=2, locals=0, args_size=0
         0: new           #2                  // class shapeless/Unwrapped$
         3: dup
         4: invokespecial #27                 // Method "<init>":()V
         7: putstatic     #29                 // Field MODULE$:Lshapeless/Unwrapped$;
        10: getstatic     #29                 // Field MODULE$:Lshapeless/Unwrapped$;
        13: invokestatic  #35                 // InterfaceMethod shapeless/LowPriorityUnwrappedInstances.$init$:(Lshapeless/LowPriorityUnwrappedInstances;)V
        16: getstatic     #29                 // Field MODULE$:Lshapeless/Unwrapped$;
        19: invokestatic  #38                 // InterfaceMethod shapeless/UnwrappedInstances.$init$:(Lshapeless/UnwrappedInstances;)V
        22: return
      LineNumberTable:
        line 27: 0

  public <W extends java.lang.Object, Repr extends java.lang.Object, UI extends java.lang.Object, UF extends java.lang.Object> shapeless.Unwrapped<W> unwrapAnyVal(shapeless.Generic<W>, shapeless.UnwrappedInstances$AnyValHelper<Repr>, shapeless.Strict<shapeless.Unwrapped<UI>>);
    descriptor: (Lshapeless/Generic;Lshapeless/UnwrappedInstances$AnyValHelper;Lshapeless/Strict;)Lshapeless/Unwrapped;
    flags: (0x0001) ACC_PUBLIC
    Code:
      stack=4, locals=4, args_size=4
         0: aload_0
         1: aload_1
         2: aload_2
         3: aload_3
         4: invokestatic  #48                 // InterfaceMethod shapeless/UnwrappedInstances.unwrapAnyVal$:(Lshapeless/UnwrappedInstances;Lshapeless/Generic;Lshapeless/UnwrappedInstances$AnyValHelper;Lshapeless/Strict;)Lshapeless/Unwrapped;
         7: areturn
      LineNumberTable:
        line 27: 0
      LocalVariableTable:
        Start  Length  Slot  Name   Signature
            0       8     0  this   Lshapeless/Unwrapped$;
            0       8     1   gen   Lshapeless/Generic;
            0       8     2   avh   Lshapeless/UnwrappedInstances$AnyValHelper;
            0       8     3 chain   Lshapeless/Strict;
    Signature: #41                          // <W:Ljava/lang/Object;Repr:Ljava/lang/Object;UI:Ljava/lang/Object;UF:Ljava/lang/Object;>(Lshapeless/Generic<TW;>;Lshapeless/UnwrappedInstances$AnyValHelper<TRepr;>;Lshapeless/Strict<Lshapeless/Unwrapped<TUI;>;>;)Lshapeless/Unwrapped<TW;>;
    MethodParameters:
      Name                           Flags
      gen                            final
      avh                            final
      chain                          final

  public <UI extends java.lang.Object, Ops extends java.lang.Object, UF extends java.lang.Object> shapeless.Unwrapped<java.lang.Object> newtypeUnwrapped(shapeless.Strict<shapeless.Unwrapped<UI>>);
    descriptor: (Lshapeless/Strict;)Lshapeless/Unwrapped;
    flags: (0x0001) ACC_PUBLIC
    Code:
      stack=2, locals=2, args_size=2
         0: aload_0
         1: aload_1
         2: invokestatic  #59                 // InterfaceMethod shapeless/UnwrappedInstances.newtypeUnwrapped$:(Lshapeless/UnwrappedInstances;Lshapeless/Strict;)Lshapeless/Unwrapped;
         5: areturn
      LineNumberTable:
        line 27: 0
      LocalVariableTable:
        Start  Length  Slot  Name   Signature
            0       6     0  this   Lshapeless/Unwrapped$;
            0       6     1 chain   Lshapeless/Strict;
    Signature: #55                          // <UI:Ljava/lang/Object;Ops:Ljava/lang/Object;UF:Ljava/lang/Object;>(Lshapeless/Strict<Lshapeless/Unwrapped<TUI;>;>;)Lshapeless/Unwrapped<Ljava/lang/Object;>;
    MethodParameters:
      Name                           Flags
      chain                          final

  public <T extends java.lang.Object, UI extends java.lang.Object, TT extends java.lang.Object, UF extends java.lang.Object> shapeless.Unwrapped<T> tagUnwrapped(shapeless.Strict<shapeless.Unwrapped<UI>>);
    descriptor: (Lshapeless/Strict;)Lshapeless/Unwrapped;
    flags: (0x0001) ACC_PUBLIC
    Code:
      stack=2, locals=2, args_size=2
         0: aload_0
         1: aload_1
         2: invokestatic  #64                 // InterfaceMethod shapeless/UnwrappedInstances.tagUnwrapped$:(Lshapeless/UnwrappedInstances;Lshapeless/Strict;)Lshapeless/Unwrapped;
         5: areturn
      LineNumberTable:
        line 27: 0
      LocalVariableTable:
        Start  Length  Slot  Name   Signature
            0       6     0  this   Lshapeless/Unwrapped$;
            0       6     1 chain   Lshapeless/Strict;
    Signature: #61                          // <T:Ljava/lang/Object;UI:Ljava/lang/Object;TT:Ljava/lang/Object;UF:Ljava/lang/Object;>(Lshapeless/Strict<Lshapeless/Unwrapped<TUI;>;>;)Lshapeless/Unwrapped<TT;>;
    MethodParameters:
      Name                           Flags
      chain                          final

  public <T extends java.lang.Object> shapeless.Unwrapped<T> selfUnwrapped();
    descriptor: ()Lshapeless/Unwrapped;
    flags: (0x0001) ACC_PUBLIC
    Code:
      stack=1, locals=1, args_size=1
         0: aload_0
         1: invokestatic  #71                 // InterfaceMethod shapeless/LowPriorityUnwrappedInstances.selfUnwrapped$:(Lshapeless/LowPriorityUnwrappedInstances;)Lshapeless/Unwrapped;
         4: areturn
      LineNumberTable:
        line 27: 0
      LocalVariableTable:
        Start  Length  Slot  Name   Signature
            0       5     0  this   Lshapeless/Unwrapped$;
    Signature: #67                          // <T:Ljava/lang/Object;>()Lshapeless/Unwrapped<TT;>;

  public shapeless.UnwrappedInstances$AnyValHelper$ AnyValHelper();
    descriptor: ()Lshapeless/UnwrappedInstances$AnyValHelper$;
    flags: (0x0001) ACC_PUBLIC
    Code:
      stack=1, locals=1, args_size=1
         0: getstatic     #74                 // Field AnyValHelper$module:Lshapeless/UnwrappedInstances$AnyValHelper$;
         3: ifnonnull     10
         6: aload_0
         7: invokespecial #77                 // Method AnyValHelper$lzycompute$1:()V
        10: getstatic     #74                 // Field AnyValHelper$module:Lshapeless/UnwrappedInstances$AnyValHelper$;
        13: areturn
      StackMapTable: number_of_entries = 1
        frame_type = 10 /* same */
      LineNumberTable:
        line 27: 0
      LocalVariableTable:
        Start  Length  Slot  Name   Signature
            0      14     0  this   Lshapeless/Unwrapped$;

  public shapeless.Unwrapped<java.lang.Object> theSelfUnwrapped();
    descriptor: ()Lshapeless/Unwrapped;
    flags: (0x0001) ACC_PUBLIC
    Code:
      stack=1, locals=1, args_size=1
         0: getstatic     #80                 // Field theSelfUnwrapped:Lshapeless/Unwrapped;
         3: areturn
      LineNumberTable:
        line 27: 0
      LocalVariableTable:
        Start  Length  Slot  Name   Signature
            0       4     0  this   Lshapeless/Unwrapped$;
    Signature: #78                          // ()Lshapeless/Unwrapped<Ljava/lang/Object;>;

  public void shapeless$LowPriorityUnwrappedInstances$_setter_$theSelfUnwrapped_$eq(shapeless.Unwrapped<java.lang.Object>);
    descriptor: (Lshapeless/Unwrapped;)V
    flags: (0x0001) ACC_PUBLIC
    Code:
      stack=1, locals=2, args_size=2
         0: aload_1
         1: putstatic     #80                 // Field theSelfUnwrapped:Lshapeless/Unwrapped;
         4: return
      LineNumberTable:
        line 27: 0
      LocalVariableTable:
        Start  Length  Slot  Name   Signature
            0       5     0  this   Lshapeless/Unwrapped$;
            0       5     1   x$1   Lshapeless/Unwrapped;
    Signature: #83                          // (Lshapeless/Unwrapped<Ljava/lang/Object;>;)V
    MethodParameters:
      Name                           Flags
      x$1                            final

  public <W extends java.lang.Object> shapeless.Unwrapped<W> apply(shapeless.Unwrapped<W>);
    descriptor: (Lshapeless/Unwrapped;)Lshapeless/Unwrapped;
    flags: (0x0001) ACC_PUBLIC
    Code:
      stack=1, locals=2, args_size=2
         0: aload_1
         1: areturn
      LineNumberTable:
        line 29: 0
      LocalVariableTable:
        Start  Length  Slot  Name   Signature
            0       2     0  this   Lshapeless/Unwrapped$;
            0       2     1     w   Lshapeless/Unwrapped;
    Signature: #87                          // <W:Ljava/lang/Object;>(Lshapeless/Unwrapped<TW;>;)Lshapeless/Unwrapped<TW;>;
    MethodParameters:
      Name                           Flags
      w                              final

  private java.lang.Object writeReplace();
    descriptor: ()Ljava/lang/Object;
    flags: (0x0002) ACC_PRIVATE
    Code:
      stack=3, locals=1, args_size=1
         0: new           #92                 // class scala/runtime/ModuleSerializationProxy
         3: dup
         4: ldc           #2                  // class shapeless/Unwrapped$
         6: invokespecial #95                 // Method scala/runtime/ModuleSerializationProxy."<init>":(Ljava/lang/Class;)V
         9: areturn
      LineNumberTable:
        line 27: 0
      LocalVariableTable:
        Start  Length  Slot  Name   Signature
            0      10     0  this   Lshapeless/Unwrapped$;

  private final void AnyValHelper$lzycompute$1();
    descriptor: ()V
    flags: (0x0012) ACC_PRIVATE, ACC_FINAL
    Code:
      stack=3, locals=2, args_size=1
         0: aload_0
         1: dup
         2: astore_1
         3: monitorenter
         4: getstatic     #74                 // Field AnyValHelper$module:Lshapeless/UnwrappedInstances$AnyValHelper$;
         7: ifnonnull     21
        10: new           #14                 // class shapeless/UnwrappedInstances$AnyValHelper$
        13: dup
        14: aload_0
        15: invokespecial #97                 // Method shapeless/UnwrappedInstances$AnyValHelper$."<init>":(Lshapeless/UnwrappedInstances;)V
        18: putstatic     #74                 // Field AnyValHelper$module:Lshapeless/UnwrappedInstances$AnyValHelper$;
        21: aload_1
        22: monitorexit
        23: goto          29
        26: aload_1
        27: monitorexit
        28: athrow
        29: return
      Exception table:
         from    to  target type
             4    21    26   any
      StackMapTable: number_of_entries = 3
        frame_type = 252 /* append */
          offset_delta = 21
          locals = [ class shapeless/Unwrapped$ ]
        frame_type = 68 /* same_locals_1_stack_item */
          stack = [ class java/lang/Throwable ]
        frame_type = 2 /* same */
      LineNumberTable:
        line 27: 0
      LocalVariableTable:
        Start  Length  Slot  Name   Signature
            0      30     0  this   Lshapeless/Unwrapped$;

  private shapeless.Unwrapped$();
    descriptor: ()V
    flags: (0x0002) ACC_PRIVATE
    Code:
      stack=1, locals=1, args_size=1
         0: aload_0
         1: invokespecial #100                // Method java/lang/Object."<init>":()V
         4: return
      LineNumberTable:
        line 27: 0
      LocalVariableTable:
        Start  Length  Slot  Name   Signature
            0       5     0  this   Lshapeless/Unwrapped$;
}
InnerClasses:
  public #12= #11 of #6;                  // AnyValHelper=class shapeless/UnwrappedInstances$AnyValHelper of class shapeless/UnwrappedInstances
  public #15= #14 of #6;                  // AnyValHelper$=class shapeless/UnwrappedInstances$AnyValHelper$ of class shapeless/UnwrappedInstances
SourceFile: "unwrapped.scala"
  ScalaInlineInfo: length = 0x3B (unknown attribute)
   01 01 00 0B 00 19 00 18 01 00 4B 00 18 01 00 0C
   00 48 01 00 55 00 56 01 00 35 00 36 01 00 41 00
   42 01 00 51 00 52 01 00 3C 00 36 01 00 14 00 42
   01 00 27 00 28 01 00 59 00 5A 01
  Scala: length = 0x0 (unknown attribute)

