Classfile /Users/mw/Projects/slang-braindump/.jar/jar11/assemble/slang-braindump/assemble/content/com/zaxxer/nuprocess/windows/NuWinNT.class
  Last modified May 29, 2022; size 1784 bytes
  SHA-256 checksum 99bd81713013f2f2100fd1be8e5948b6fd179a20ba944252a37e925ce9d09ab7
  Compiled from "NuWinNT.java"
public interface com.zaxxer.nuprocess.windows.NuWinNT
  minor version: 0
  major version: 51
  flags: (0x0601) ACC_PUBLIC, ACC_INTERFACE, ACC_ABSTRACT
  this_class: #1                          // com/zaxxer/nuprocess/windows/NuWinNT
  super_class: #6                         // java/lang/Object
  interfaces: 0, fields: 19, methods: 1, attributes: 2
Constant pool:
   #1 = Class              #67            // com/zaxxer/nuprocess/windows/NuWinNT
   #2 = Class              #68            // com/zaxxer/nuprocess/windows/NuWinNT$HANDLE
   #3 = Fieldref           #2.#69         // com/zaxxer/nuprocess/windows/NuWinNT$HANDLE.INVALID:Lcom/sun/jna/Pointer;
   #4 = Methodref          #2.#70         // com/zaxxer/nuprocess/windows/NuWinNT$HANDLE."<init>":(Lcom/sun/jna/Pointer;)V
   #5 = Fieldref           #1.#71         // com/zaxxer/nuprocess/windows/NuWinNT.INVALID_HANDLE_VALUE:Lcom/zaxxer/nuprocess/windows/NuWinNT$HANDLE;
   #6 = Class              #72            // java/lang/Object
   #7 = Class              #73            // com/zaxxer/nuprocess/windows/NuWinNT$PROCESS_INFORMATION
   #8 = Utf8               PROCESS_INFORMATION
   #9 = Utf8               InnerClasses
  #10 = Class              #74            // com/zaxxer/nuprocess/windows/NuWinNT$STARTUPINFO
  #11 = Utf8               STARTUPINFO
  #12 = Class              #75            // com/zaxxer/nuprocess/windows/NuWinNT$SECURITY_ATTRIBUTES
  #13 = Utf8               SECURITY_ATTRIBUTES
  #14 = Class              #76            // com/zaxxer/nuprocess/windows/NuWinNT$ULONG_PTRByReference
  #15 = Utf8               ULONG_PTRByReference
  #16 = Class              #77            // com/zaxxer/nuprocess/windows/NuWinNT$ULONG_PTR
  #17 = Utf8               ULONG_PTR
  #18 = Class              #78            // com/zaxxer/nuprocess/windows/NuWinNT$DWORD
  #19 = Utf8               DWORD
  #20 = Class              #79            // com/zaxxer/nuprocess/windows/NuWinNT$WORD
  #21 = Utf8               WORD
  #22 = Utf8               HANDLE
  #23 = Utf8               CREATE_SUSPENDED
  #24 = Utf8               I
  #25 = Utf8               ConstantValue
  #26 = Integer            4
  #27 = Utf8               CREATE_UNICODE_ENVIRONMENT
  #28 = Integer            1024
  #29 = Utf8               CREATE_NO_WINDOW
  #30 = Integer            134217728
  #31 = Utf8               ERROR_SUCCESS
  #32 = Integer            0
  #33 = Utf8               ERROR_BROKEN_PIPE
  #34 = Integer            109
  #35 = Utf8               ERROR_PIPE_NOT_CONNECTED
  #36 = Integer            233
  #37 = Utf8               ERROR_PIPE_CONNECTED
  #38 = Integer            535
  #39 = Utf8               ERROR_IO_PENDING
  #40 = Integer            997
  #41 = Utf8               FILE_ATTRIBUTE_NORMAL
  #42 = Integer            128
  #43 = Utf8               FILE_FLAG_OVERLAPPED
  #44 = Integer            1073741824
  #45 = Utf8               FILE_SHARE_READ
  #46 = Integer            1
  #47 = Utf8               FILE_SHARE_WRITE
  #48 = Integer            2
  #49 = Utf8               GENERIC_READ
  #50 = Integer            -2147483648
  #51 = Utf8               GENERIC_WRITE
  #52 = Utf8               OPEN_EXISTING
  #53 = Integer            3
  #54 = Utf8               STATUS_PENDING
  #55 = Integer            259
  #56 = Utf8               STILL_ACTIVE
  #57 = Utf8               STARTF_USESTDHANDLES
  #58 = Integer            256
  #59 = Utf8               INVALID_HANDLE_VALUE
  #60 = Utf8               Lcom/zaxxer/nuprocess/windows/NuWinNT$HANDLE;
  #61 = Utf8               <clinit>
  #62 = Utf8               ()V
  #63 = Utf8               Code
  #64 = Utf8               LineNumberTable
  #65 = Utf8               SourceFile
  #66 = Utf8               NuWinNT.java
  #67 = Utf8               com/zaxxer/nuprocess/windows/NuWinNT
  #68 = Utf8               com/zaxxer/nuprocess/windows/NuWinNT$HANDLE
  #69 = NameAndType        #80:#81        // INVALID:Lcom/sun/jna/Pointer;
  #70 = NameAndType        #82:#83        // "<init>":(Lcom/sun/jna/Pointer;)V
  #71 = NameAndType        #59:#60        // INVALID_HANDLE_VALUE:Lcom/zaxxer/nuprocess/windows/NuWinNT$HANDLE;
  #72 = Utf8               java/lang/Object
  #73 = Utf8               com/zaxxer/nuprocess/windows/NuWinNT$PROCESS_INFORMATION
  #74 = Utf8               com/zaxxer/nuprocess/windows/NuWinNT$STARTUPINFO
  #75 = Utf8               com/zaxxer/nuprocess/windows/NuWinNT$SECURITY_ATTRIBUTES
  #76 = Utf8               com/zaxxer/nuprocess/windows/NuWinNT$ULONG_PTRByReference
  #77 = Utf8               com/zaxxer/nuprocess/windows/NuWinNT$ULONG_PTR
  #78 = Utf8               com/zaxxer/nuprocess/windows/NuWinNT$DWORD
  #79 = Utf8               com/zaxxer/nuprocess/windows/NuWinNT$WORD
  #80 = Utf8               INVALID
  #81 = Utf8               Lcom/sun/jna/Pointer;
  #82 = Utf8               <init>
  #83 = Utf8               (Lcom/sun/jna/Pointer;)V
{
  public static final int CREATE_SUSPENDED;
    descriptor: I
    flags: (0x0019) ACC_PUBLIC, ACC_STATIC, ACC_FINAL
    ConstantValue: int 4

  public static final int CREATE_UNICODE_ENVIRONMENT;
    descriptor: I
    flags: (0x0019) ACC_PUBLIC, ACC_STATIC, ACC_FINAL
    ConstantValue: int 1024

  public static final int CREATE_NO_WINDOW;
    descriptor: I
    flags: (0x0019) ACC_PUBLIC, ACC_STATIC, ACC_FINAL
    ConstantValue: int 134217728

  public static final int ERROR_SUCCESS;
    descriptor: I
    flags: (0x0019) ACC_PUBLIC, ACC_STATIC, ACC_FINAL
    ConstantValue: int 0

  public static final int ERROR_BROKEN_PIPE;
    descriptor: I
    flags: (0x0019) ACC_PUBLIC, ACC_STATIC, ACC_FINAL
    ConstantValue: int 109

  public static final int ERROR_PIPE_NOT_CONNECTED;
    descriptor: I
    flags: (0x0019) ACC_PUBLIC, ACC_STATIC, ACC_FINAL
    ConstantValue: int 233

  public static final int ERROR_PIPE_CONNECTED;
    descriptor: I
    flags: (0x0019) ACC_PUBLIC, ACC_STATIC, ACC_FINAL
    ConstantValue: int 535

  public static final int ERROR_IO_PENDING;
    descriptor: I
    flags: (0x0019) ACC_PUBLIC, ACC_STATIC, ACC_FINAL
    ConstantValue: int 997

  public static final int FILE_ATTRIBUTE_NORMAL;
    descriptor: I
    flags: (0x0019) ACC_PUBLIC, ACC_STATIC, ACC_FINAL
    ConstantValue: int 128

  public static final int FILE_FLAG_OVERLAPPED;
    descriptor: I
    flags: (0x0019) ACC_PUBLIC, ACC_STATIC, ACC_FINAL
    ConstantValue: int 1073741824

  public static final int FILE_SHARE_READ;
    descriptor: I
    flags: (0x0019) ACC_PUBLIC, ACC_STATIC, ACC_FINAL
    ConstantValue: int 1

  public static final int FILE_SHARE_WRITE;
    descriptor: I
    flags: (0x0019) ACC_PUBLIC, ACC_STATIC, ACC_FINAL
    ConstantValue: int 2

  public static final int GENERIC_READ;
    descriptor: I
    flags: (0x0019) ACC_PUBLIC, ACC_STATIC, ACC_FINAL
    ConstantValue: int -2147483648

  public static final int GENERIC_WRITE;
    descriptor: I
    flags: (0x0019) ACC_PUBLIC, ACC_STATIC, ACC_FINAL
    ConstantValue: int 1073741824

  public static final int OPEN_EXISTING;
    descriptor: I
    flags: (0x0019) ACC_PUBLIC, ACC_STATIC, ACC_FINAL
    ConstantValue: int 3

  public static final int STATUS_PENDING;
    descriptor: I
    flags: (0x0019) ACC_PUBLIC, ACC_STATIC, ACC_FINAL
    ConstantValue: int 259

  public static final int STILL_ACTIVE;
    descriptor: I
    flags: (0x0019) ACC_PUBLIC, ACC_STATIC, ACC_FINAL
    ConstantValue: int 259

  public static final int STARTF_USESTDHANDLES;
    descriptor: I
    flags: (0x0019) ACC_PUBLIC, ACC_STATIC, ACC_FINAL
    ConstantValue: int 256

  public static final com.zaxxer.nuprocess.windows.NuWinNT$HANDLE INVALID_HANDLE_VALUE;
    descriptor: Lcom/zaxxer/nuprocess/windows/NuWinNT$HANDLE;
    flags: (0x0019) ACC_PUBLIC, ACC_STATIC, ACC_FINAL

  static {};
    descriptor: ()V
    flags: (0x0008) ACC_STATIC
    Code:
      stack=3, locals=0, args_size=0
         0: new           #2                  // class com/zaxxer/nuprocess/windows/NuWinNT$HANDLE
         3: dup
         4: getstatic     #3                  // Field com/zaxxer/nuprocess/windows/NuWinNT$HANDLE.INVALID:Lcom/sun/jna/Pointer;
         7: invokespecial #4                  // Method com/zaxxer/nuprocess/windows/NuWinNT$HANDLE."<init>":(Lcom/sun/jna/Pointer;)V
        10: putstatic     #5                  // Field INVALID_HANDLE_VALUE:Lcom/zaxxer/nuprocess/windows/NuWinNT$HANDLE;
        13: return
      LineNumberTable:
        line 61: 0
}
SourceFile: "NuWinNT.java"
InnerClasses:
  public static #8= #7 of #1;             // PROCESS_INFORMATION=class com/zaxxer/nuprocess/windows/NuWinNT$PROCESS_INFORMATION of class com/zaxxer/nuprocess/windows/NuWinNT
  public static #11= #10 of #1;           // STARTUPINFO=class com/zaxxer/nuprocess/windows/NuWinNT$STARTUPINFO of class com/zaxxer/nuprocess/windows/NuWinNT
  public static #13= #12 of #1;           // SECURITY_ATTRIBUTES=class com/zaxxer/nuprocess/windows/NuWinNT$SECURITY_ATTRIBUTES of class com/zaxxer/nuprocess/windows/NuWinNT
  public static #15= #14 of #1;           // ULONG_PTRByReference=class com/zaxxer/nuprocess/windows/NuWinNT$ULONG_PTRByReference of class com/zaxxer/nuprocess/windows/NuWinNT
  public static #17= #16 of #1;           // ULONG_PTR=class com/zaxxer/nuprocess/windows/NuWinNT$ULONG_PTR of class com/zaxxer/nuprocess/windows/NuWinNT
  public static #19= #18 of #1;           // DWORD=class com/zaxxer/nuprocess/windows/NuWinNT$DWORD of class com/zaxxer/nuprocess/windows/NuWinNT
  public static #21= #20 of #1;           // WORD=class com/zaxxer/nuprocess/windows/NuWinNT$WORD of class com/zaxxer/nuprocess/windows/NuWinNT
  public static #22= #2 of #1;            // HANDLE=class com/zaxxer/nuprocess/windows/NuWinNT$HANDLE of class com/zaxxer/nuprocess/windows/NuWinNT
