Classfile /Users/mw/Projects/slang-braindump/.jar/jar11/assemble/slang-braindump/assemble/content/com/zaxxer/nuprocess/windows/NuWinNT$ULONG_PTR.class
  Last modified May 29, 2022; size 592 bytes
  SHA-256 checksum 58d850d6a62b4e4eb90af02f8dd88c93c5337c5796f588c474d64631e549d21a
  Compiled from "NuWinNT.java"
public class com.zaxxer.nuprocess.windows.NuWinNT$ULONG_PTR extends com.sun.jna.IntegerType
  minor version: 0
  major version: 51
  flags: (0x0021) ACC_PUBLIC, ACC_SUPER
  this_class: #4                          // com/zaxxer/nuprocess/windows/NuWinNT$ULONG_PTR
  super_class: #5                         // com/sun/jna/IntegerType
  interfaces: 0, fields: 0, methods: 2, attributes: 2
Constant pool:
   #1 = Methodref          #4.#20         // com/zaxxer/nuprocess/windows/NuWinNT$ULONG_PTR."<init>":(J)V
   #2 = Fieldref           #21.#22        // com/sun/jna/Native.POINTER_SIZE:I
   #3 = Methodref          #5.#23         // com/sun/jna/IntegerType."<init>":(IJZ)V
   #4 = Class              #25            // com/zaxxer/nuprocess/windows/NuWinNT$ULONG_PTR
   #5 = Class              #26            // com/sun/jna/IntegerType
   #6 = Utf8               <init>
   #7 = Utf8               ()V
   #8 = Utf8               Code
   #9 = Utf8               LineNumberTable
  #10 = Utf8               LocalVariableTable
  #11 = Utf8               this
  #12 = Utf8               ULONG_PTR
  #13 = Utf8               InnerClasses
  #14 = Utf8               Lcom/zaxxer/nuprocess/windows/NuWinNT$ULONG_PTR;
  #15 = Utf8               (J)V
  #16 = Utf8               value
  #17 = Utf8               J
  #18 = Utf8               SourceFile
  #19 = Utf8               NuWinNT.java
  #20 = NameAndType        #6:#15         // "<init>":(J)V
  #21 = Class              #27            // com/sun/jna/Native
  #22 = NameAndType        #28:#29        // POINTER_SIZE:I
  #23 = NameAndType        #6:#30         // "<init>":(IJZ)V
  #24 = Class              #31            // com/zaxxer/nuprocess/windows/NuWinNT
  #25 = Utf8               com/zaxxer/nuprocess/windows/NuWinNT$ULONG_PTR
  #26 = Utf8               com/sun/jna/IntegerType
  #27 = Utf8               com/sun/jna/Native
  #28 = Utf8               POINTER_SIZE
  #29 = Utf8               I
  #30 = Utf8               (IJZ)V
  #31 = Utf8               com/zaxxer/nuprocess/windows/NuWinNT
{
  public com.zaxxer.nuprocess.windows.NuWinNT$ULONG_PTR();
    descriptor: ()V
    flags: (0x0001) ACC_PUBLIC
    Code:
      stack=3, locals=1, args_size=1
         0: aload_0
         1: lconst_0
         2: invokespecial #1                  // Method "<init>":(J)V
         5: return
      LineNumberTable:
        line 125: 0
        line 126: 5
      LocalVariableTable:
        Start  Length  Slot  Name   Signature
            0       6     0  this   Lcom/zaxxer/nuprocess/windows/NuWinNT$ULONG_PTR;

  public com.zaxxer.nuprocess.windows.NuWinNT$ULONG_PTR(long);
    descriptor: (J)V
    flags: (0x0001) ACC_PUBLIC
    Code:
      stack=5, locals=3, args_size=2
         0: aload_0
         1: getstatic     #2                  // Field com/sun/jna/Native.POINTER_SIZE:I
         4: lload_1
         5: iconst_1
         6: invokespecial #3                  // Method com/sun/jna/IntegerType."<init>":(IJZ)V
         9: return
      LineNumberTable:
        line 130: 0
        line 131: 9
      LocalVariableTable:
        Start  Length  Slot  Name   Signature
            0      10     0  this   Lcom/zaxxer/nuprocess/windows/NuWinNT$ULONG_PTR;
            0      10     1 value   J
}
SourceFile: "NuWinNT.java"
InnerClasses:
  public static #12= #4 of #24;           // ULONG_PTR=class com/zaxxer/nuprocess/windows/NuWinNT$ULONG_PTR of class com/zaxxer/nuprocess/windows/NuWinNT
