Classfile /Users/mw/Projects/slang-braindump/.jar/jar11/assemble/slang-braindump/assemble/content/com/zaxxer/nuprocess/windows/NuWinNT$ULONG_PTRByReference.class
  Last modified May 29, 2022; size 1417 bytes
  SHA-256 checksum 02daf4c6a333527fff24b4bcf3e09fc2d6baa4de68876ccf3b98499c780aadc1
  Compiled from "NuWinNT.java"
public class com.zaxxer.nuprocess.windows.NuWinNT$ULONG_PTRByReference extends com.sun.jna.ptr.ByReference
  minor version: 0
  major version: 51
  flags: (0x0021) ACC_PUBLIC, ACC_SUPER
  this_class: #14                         // com/zaxxer/nuprocess/windows/NuWinNT$ULONG_PTRByReference
  super_class: #15                        // com/sun/jna/ptr/ByReference
  interfaces: 0, fields: 0, methods: 4, attributes: 2
Constant pool:
   #1 = Class              #36            // com/zaxxer/nuprocess/windows/NuWinNT$ULONG_PTR
   #2 = Methodref          #1.#37         // com/zaxxer/nuprocess/windows/NuWinNT$ULONG_PTR."<init>":(J)V
   #3 = Methodref          #14.#38        // com/zaxxer/nuprocess/windows/NuWinNT$ULONG_PTRByReference."<init>":(Lcom/zaxxer/nuprocess/windows/NuWinNT$ULONG_PTR;)V
   #4 = Fieldref           #39.#40        // com/sun/jna/Native.POINTER_SIZE:I
   #5 = Methodref          #15.#41        // com/sun/jna/ptr/ByReference."<init>":(I)V
   #6 = Methodref          #14.#42        // com/zaxxer/nuprocess/windows/NuWinNT$ULONG_PTRByReference.setValue:(Lcom/zaxxer/nuprocess/windows/NuWinNT$ULONG_PTR;)V
   #7 = Methodref          #14.#43        // com/zaxxer/nuprocess/windows/NuWinNT$ULONG_PTRByReference.getPointer:()Lcom/sun/jna/Pointer;
   #8 = Methodref          #1.#44         // com/zaxxer/nuprocess/windows/NuWinNT$ULONG_PTR.intValue:()I
   #9 = Methodref          #45.#46        // com/sun/jna/Pointer.setInt:(JI)V
  #10 = Methodref          #1.#47         // com/zaxxer/nuprocess/windows/NuWinNT$ULONG_PTR.longValue:()J
  #11 = Methodref          #45.#48        // com/sun/jna/Pointer.setLong:(JJ)V
  #12 = Methodref          #45.#49        // com/sun/jna/Pointer.getInt:(J)I
  #13 = Methodref          #45.#50        // com/sun/jna/Pointer.getLong:(J)J
  #14 = Class              #51            // com/zaxxer/nuprocess/windows/NuWinNT$ULONG_PTRByReference
  #15 = Class              #52            // com/sun/jna/ptr/ByReference
  #16 = Utf8               <init>
  #17 = Utf8               ()V
  #18 = Utf8               Code
  #19 = Utf8               LineNumberTable
  #20 = Utf8               LocalVariableTable
  #21 = Utf8               this
  #22 = Utf8               ULONG_PTRByReference
  #23 = Utf8               InnerClasses
  #24 = Utf8               Lcom/zaxxer/nuprocess/windows/NuWinNT$ULONG_PTRByReference;
  #25 = Utf8               ULONG_PTR
  #26 = Utf8               (Lcom/zaxxer/nuprocess/windows/NuWinNT$ULONG_PTR;)V
  #27 = Utf8               value
  #28 = Utf8               Lcom/zaxxer/nuprocess/windows/NuWinNT$ULONG_PTR;
  #29 = Utf8               setValue
  #30 = Utf8               StackMapTable
  #31 = Utf8               getValue
  #32 = Utf8               ()Lcom/zaxxer/nuprocess/windows/NuWinNT$ULONG_PTR;
  #33 = Utf8               SourceFile
  #34 = Utf8               NuWinNT.java
  #35 = Class              #53            // com/zaxxer/nuprocess/windows/NuWinNT
  #36 = Utf8               com/zaxxer/nuprocess/windows/NuWinNT$ULONG_PTR
  #37 = NameAndType        #16:#54        // "<init>":(J)V
  #38 = NameAndType        #16:#26        // "<init>":(Lcom/zaxxer/nuprocess/windows/NuWinNT$ULONG_PTR;)V
  #39 = Class              #55            // com/sun/jna/Native
  #40 = NameAndType        #56:#57        // POINTER_SIZE:I
  #41 = NameAndType        #16:#58        // "<init>":(I)V
  #42 = NameAndType        #29:#26        // setValue:(Lcom/zaxxer/nuprocess/windows/NuWinNT$ULONG_PTR;)V
  #43 = NameAndType        #59:#60        // getPointer:()Lcom/sun/jna/Pointer;
  #44 = NameAndType        #61:#62        // intValue:()I
  #45 = Class              #63            // com/sun/jna/Pointer
  #46 = NameAndType        #64:#65        // setInt:(JI)V
  #47 = NameAndType        #66:#67        // longValue:()J
  #48 = NameAndType        #68:#69        // setLong:(JJ)V
  #49 = NameAndType        #70:#71        // getInt:(J)I
  #50 = NameAndType        #72:#73        // getLong:(J)J
  #51 = Utf8               com/zaxxer/nuprocess/windows/NuWinNT$ULONG_PTRByReference
  #52 = Utf8               com/sun/jna/ptr/ByReference
  #53 = Utf8               com/zaxxer/nuprocess/windows/NuWinNT
  #54 = Utf8               (J)V
  #55 = Utf8               com/sun/jna/Native
  #56 = Utf8               POINTER_SIZE
  #57 = Utf8               I
  #58 = Utf8               (I)V
  #59 = Utf8               getPointer
  #60 = Utf8               ()Lcom/sun/jna/Pointer;
  #61 = Utf8               intValue
  #62 = Utf8               ()I
  #63 = Utf8               com/sun/jna/Pointer
  #64 = Utf8               setInt
  #65 = Utf8               (JI)V
  #66 = Utf8               longValue
  #67 = Utf8               ()J
  #68 = Utf8               setLong
  #69 = Utf8               (JJ)V
  #70 = Utf8               getInt
  #71 = Utf8               (J)I
  #72 = Utf8               getLong
  #73 = Utf8               (J)J
{
  public com.zaxxer.nuprocess.windows.NuWinNT$ULONG_PTRByReference();
    descriptor: ()V
    flags: (0x0001) ACC_PUBLIC
    Code:
      stack=5, locals=1, args_size=1
         0: aload_0
         1: new           #1                  // class com/zaxxer/nuprocess/windows/NuWinNT$ULONG_PTR
         4: dup
         5: lconst_0
         6: invokespecial #2                  // Method com/zaxxer/nuprocess/windows/NuWinNT$ULONG_PTR."<init>":(J)V
         9: invokespecial #3                  // Method "<init>":(Lcom/zaxxer/nuprocess/windows/NuWinNT$ULONG_PTR;)V
        12: return
      LineNumberTable:
        line 138: 0
        line 139: 12
      LocalVariableTable:
        Start  Length  Slot  Name   Signature
            0      13     0  this   Lcom/zaxxer/nuprocess/windows/NuWinNT$ULONG_PTRByReference;

  public com.zaxxer.nuprocess.windows.NuWinNT$ULONG_PTRByReference(com.zaxxer.nuprocess.windows.NuWinNT$ULONG_PTR);
    descriptor: (Lcom/zaxxer/nuprocess/windows/NuWinNT$ULONG_PTR;)V
    flags: (0x0001) ACC_PUBLIC
    Code:
      stack=2, locals=2, args_size=2
         0: aload_0
         1: getstatic     #4                  // Field com/sun/jna/Native.POINTER_SIZE:I
         4: invokespecial #5                  // Method com/sun/jna/ptr/ByReference."<init>":(I)V
         7: aload_0
         8: aload_1
         9: invokevirtual #6                  // Method setValue:(Lcom/zaxxer/nuprocess/windows/NuWinNT$ULONG_PTR;)V
        12: return
      LineNumberTable:
        line 143: 0
        line 144: 7
        line 145: 12
      LocalVariableTable:
        Start  Length  Slot  Name   Signature
            0      13     0  this   Lcom/zaxxer/nuprocess/windows/NuWinNT$ULONG_PTRByReference;
            0      13     1 value   Lcom/zaxxer/nuprocess/windows/NuWinNT$ULONG_PTR;

  public void setValue(com.zaxxer.nuprocess.windows.NuWinNT$ULONG_PTR);
    descriptor: (Lcom/zaxxer/nuprocess/windows/NuWinNT$ULONG_PTR;)V
    flags: (0x0001) ACC_PUBLIC
    Code:
      stack=5, locals=2, args_size=2
         0: getstatic     #4                  // Field com/sun/jna/Native.POINTER_SIZE:I
         3: iconst_4
         4: if_icmpne     22
         7: aload_0
         8: invokevirtual #7                  // Method getPointer:()Lcom/sun/jna/Pointer;
        11: lconst_0
        12: aload_1
        13: invokevirtual #8                  // Method com/zaxxer/nuprocess/windows/NuWinNT$ULONG_PTR.intValue:()I
        16: invokevirtual #9                  // Method com/sun/jna/Pointer.setInt:(JI)V
        19: goto          34
        22: aload_0
        23: invokevirtual #7                  // Method getPointer:()Lcom/sun/jna/Pointer;
        26: lconst_0
        27: aload_1
        28: invokevirtual #10                 // Method com/zaxxer/nuprocess/windows/NuWinNT$ULONG_PTR.longValue:()J
        31: invokevirtual #11                 // Method com/sun/jna/Pointer.setLong:(JJ)V
        34: return
      LineNumberTable:
        line 149: 0
        line 150: 7
        line 153: 22
        line 155: 34
      LocalVariableTable:
        Start  Length  Slot  Name   Signature
            0      35     0  this   Lcom/zaxxer/nuprocess/windows/NuWinNT$ULONG_PTRByReference;
            0      35     1 value   Lcom/zaxxer/nuprocess/windows/NuWinNT$ULONG_PTR;
      StackMapTable: number_of_entries = 2
        frame_type = 22 /* same */
        frame_type = 11 /* same */

  public com.zaxxer.nuprocess.windows.NuWinNT$ULONG_PTR getValue();
    descriptor: ()Lcom/zaxxer/nuprocess/windows/NuWinNT$ULONG_PTR;
    flags: (0x0001) ACC_PUBLIC
    Code:
      stack=5, locals=1, args_size=1
         0: new           #1                  // class com/zaxxer/nuprocess/windows/NuWinNT$ULONG_PTR
         3: dup
         4: getstatic     #4                  // Field com/sun/jna/Native.POINTER_SIZE:I
         7: iconst_4
         8: if_icmpne     23
        11: aload_0
        12: invokevirtual #7                  // Method getPointer:()Lcom/sun/jna/Pointer;
        15: lconst_0
        16: invokevirtual #12                 // Method com/sun/jna/Pointer.getInt:(J)I
        19: i2l
        20: goto          31
        23: aload_0
        24: invokevirtual #7                  // Method getPointer:()Lcom/sun/jna/Pointer;
        27: lconst_0
        28: invokevirtual #13                 // Method com/sun/jna/Pointer.getLong:(J)J
        31: invokespecial #2                  // Method com/zaxxer/nuprocess/windows/NuWinNT$ULONG_PTR."<init>":(J)V
        34: areturn
      LineNumberTable:
        line 159: 0
      LocalVariableTable:
        Start  Length  Slot  Name   Signature
            0      35     0  this   Lcom/zaxxer/nuprocess/windows/NuWinNT$ULONG_PTRByReference;
      StackMapTable: number_of_entries = 2
        frame_type = 255 /* full_frame */
          offset_delta = 23
          locals = [ class com/zaxxer/nuprocess/windows/NuWinNT$ULONG_PTRByReference ]
          stack = [ uninitialized 0, uninitialized 0 ]
        frame_type = 255 /* full_frame */
          offset_delta = 7
          locals = [ class com/zaxxer/nuprocess/windows/NuWinNT$ULONG_PTRByReference ]
          stack = [ uninitialized 0, uninitialized 0, long ]
}
SourceFile: "NuWinNT.java"
InnerClasses:
  public static #22= #14 of #35;          // ULONG_PTRByReference=class com/zaxxer/nuprocess/windows/NuWinNT$ULONG_PTRByReference of class com/zaxxer/nuprocess/windows/NuWinNT
  public static #25= #1 of #35;           // ULONG_PTR=class com/zaxxer/nuprocess/windows/NuWinNT$ULONG_PTR of class com/zaxxer/nuprocess/windows/NuWinNT
