Classfile /Users/mw/Projects/slang-braindump/.jar/jar11/assemble/slang-braindump/assemble/content/com/zaxxer/nuprocess/windows/WindowsCreateProcessEscape.class
  Last modified May 29, 2022; size 1553 bytes
  SHA-256 checksum eed3d332d6b8d15407ca72c667a1573ea36fc601a402a399b004497a4d4346b5
  Compiled from "WindowsCreateProcessEscape.java"
class com.zaxxer.nuprocess.windows.WindowsCreateProcessEscape
  minor version: 0
  major version: 51
  flags: (0x0020) ACC_SUPER
  this_class: #11                         // com/zaxxer/nuprocess/windows/WindowsCreateProcessEscape
  super_class: #12                        // java/lang/Object
  interfaces: 0, fields: 0, methods: 4, attributes: 1
Constant pool:
   #1 = Methodref          #12.#38        // java/lang/Object."<init>":()V
   #2 = Methodref          #11.#39        // com/zaxxer/nuprocess/windows/WindowsCreateProcessEscape.mightNeedQuotes:(Ljava/lang/String;)Z
   #3 = Methodref          #7.#40         // java/lang/StringBuilder.append:(Ljava/lang/String;)Ljava/lang/StringBuilder;
   #4 = Methodref          #7.#41         // java/lang/StringBuilder.append:(C)Ljava/lang/StringBuilder;
   #5 = Methodref          #42.#43        // java/lang/String.length:()I
   #6 = Methodref          #42.#44        // java/lang/String.charAt:(I)C
   #7 = Class              #45            // java/lang/StringBuilder
   #8 = Methodref          #7.#46         // java/lang/StringBuilder."<init>":(I)V
   #9 = Methodref          #11.#47        // com/zaxxer/nuprocess/windows/WindowsCreateProcessEscape.quote:(Ljava/lang/StringBuilder;Ljava/lang/String;)V
  #10 = Methodref          #7.#48         // java/lang/StringBuilder.toString:()Ljava/lang/String;
  #11 = Class              #49            // com/zaxxer/nuprocess/windows/WindowsCreateProcessEscape
  #12 = Class              #50            // java/lang/Object
  #13 = Utf8               <init>
  #14 = Utf8               ()V
  #15 = Utf8               Code
  #16 = Utf8               LineNumberTable
  #17 = Utf8               LocalVariableTable
  #18 = Utf8               this
  #19 = Utf8               Lcom/zaxxer/nuprocess/windows/WindowsCreateProcessEscape;
  #20 = Utf8               quote
  #21 = Utf8               (Ljava/lang/StringBuilder;Ljava/lang/String;)V
  #22 = Utf8               j
  #23 = Utf8               I
  #24 = Utf8               c
  #25 = Utf8               C
  #26 = Utf8               i
  #27 = Utf8               buf
  #28 = Utf8               Ljava/lang/StringBuilder;
  #29 = Utf8               arg
  #30 = Utf8               Ljava/lang/String;
  #31 = Utf8               nPending
  #32 = Utf8               StackMapTable
  #33 = Utf8               (Ljava/lang/String;)Ljava/lang/String;
  #34 = Utf8               mightNeedQuotes
  #35 = Utf8               (Ljava/lang/String;)Z
  #36 = Utf8               SourceFile
  #37 = Utf8               WindowsCreateProcessEscape.java
  #38 = NameAndType        #13:#14        // "<init>":()V
  #39 = NameAndType        #34:#35        // mightNeedQuotes:(Ljava/lang/String;)Z
  #40 = NameAndType        #51:#52        // append:(Ljava/lang/String;)Ljava/lang/StringBuilder;
  #41 = NameAndType        #51:#53        // append:(C)Ljava/lang/StringBuilder;
  #42 = Class              #54            // java/lang/String
  #43 = NameAndType        #55:#56        // length:()I
  #44 = NameAndType        #57:#58        // charAt:(I)C
  #45 = Utf8               java/lang/StringBuilder
  #46 = NameAndType        #13:#59        // "<init>":(I)V
  #47 = NameAndType        #20:#21        // quote:(Ljava/lang/StringBuilder;Ljava/lang/String;)V
  #48 = NameAndType        #60:#61        // toString:()Ljava/lang/String;
  #49 = Utf8               com/zaxxer/nuprocess/windows/WindowsCreateProcessEscape
  #50 = Utf8               java/lang/Object
  #51 = Utf8               append
  #52 = Utf8               (Ljava/lang/String;)Ljava/lang/StringBuilder;
  #53 = Utf8               (C)Ljava/lang/StringBuilder;
  #54 = Utf8               java/lang/String
  #55 = Utf8               length
  #56 = Utf8               ()I
  #57 = Utf8               charAt
  #58 = Utf8               (I)C
  #59 = Utf8               (I)V
  #60 = Utf8               toString
  #61 = Utf8               ()Ljava/lang/String;
{
  private com.zaxxer.nuprocess.windows.WindowsCreateProcessEscape();
    descriptor: ()V
    flags: (0x0002) ACC_PRIVATE
    Code:
      stack=1, locals=1, args_size=1
         0: aload_0
         1: invokespecial #1                  // Method java/lang/Object."<init>":()V
         4: return
      LineNumberTable:
        line 38: 0
        line 39: 4
      LocalVariableTable:
        Start  Length  Slot  Name   Signature
            0       5     0  this   Lcom/zaxxer/nuprocess/windows/WindowsCreateProcessEscape;

  public static void quote(java.lang.StringBuilder, java.lang.String);
    descriptor: (Ljava/lang/StringBuilder;Ljava/lang/String;)V
    flags: (0x0009) ACC_PUBLIC, ACC_STATIC
    Code:
      stack=2, locals=6, args_size=2
         0: aload_1
         1: invokestatic  #2                  // Method mightNeedQuotes:(Ljava/lang/String;)Z
         4: ifne          14
         7: aload_0
         8: aload_1
         9: invokevirtual #3                  // Method java/lang/StringBuilder.append:(Ljava/lang/String;)Ljava/lang/StringBuilder;
        12: pop
        13: return
        14: aload_0
        15: bipush        34
        17: invokevirtual #4                  // Method java/lang/StringBuilder.append:(C)Ljava/lang/StringBuilder;
        20: pop
        21: iconst_0
        22: istore_2
        23: iconst_0
        24: istore_3
        25: iload_3
        26: aload_1
        27: invokevirtual #5                  // Method java/lang/String.length:()I
        30: if_icmpge     104
        33: aload_1
        34: iload_3
        35: invokevirtual #6                  // Method java/lang/String.charAt:(I)C
        38: istore        4
        40: iload         4
        42: bipush        92
        44: if_icmpne     53
        47: iinc          2, 1
        50: goto          91
        53: iload         4
        55: bipush        34
        57: if_icmpne     89
        60: iconst_0
        61: istore        5
        63: iload         5
        65: iload_2
        66: if_icmpge     82
        69: aload_0
        70: bipush        92
        72: invokevirtual #4                  // Method java/lang/StringBuilder.append:(C)Ljava/lang/StringBuilder;
        75: pop
        76: iinc          5, 1
        79: goto          63
        82: aload_0
        83: bipush        92
        85: invokevirtual #4                  // Method java/lang/StringBuilder.append:(C)Ljava/lang/StringBuilder;
        88: pop
        89: iconst_0
        90: istore_2
        91: aload_0
        92: iload         4
        94: invokevirtual #4                  // Method java/lang/StringBuilder.append:(C)Ljava/lang/StringBuilder;
        97: pop
        98: iinc          3, 1
       101: goto          25
       104: iconst_0
       105: istore_3
       106: iload_3
       107: iload_2
       108: if_icmpge     124
       111: aload_0
       112: bipush        92
       114: invokevirtual #4                  // Method java/lang/StringBuilder.append:(C)Ljava/lang/StringBuilder;
       117: pop
       118: iinc          3, 1
       121: goto          106
       124: aload_0
       125: bipush        34
       127: invokevirtual #4                  // Method java/lang/StringBuilder.append:(C)Ljava/lang/StringBuilder;
       130: pop
       131: return
      LineNumberTable:
        line 46: 0
        line 47: 7
        line 48: 13
        line 50: 14
        line 53: 21
        line 55: 23
        line 56: 33
        line 58: 40
        line 59: 47
        line 62: 53
        line 64: 60
        line 65: 69
        line 64: 76
        line 68: 82
        line 70: 89
        line 73: 91
        line 55: 98
        line 77: 104
        line 78: 111
        line 77: 118
        line 81: 124
        line 82: 131
      LocalVariableTable:
        Start  Length  Slot  Name   Signature
           63      19     5     j   I
           40      58     4     c   C
           25      79     3     i   I
          106      18     3     j   I
            0     132     0   buf   Ljava/lang/StringBuilder;
            0     132     1   arg   Ljava/lang/String;
           23     109     2 nPending   I
      StackMapTable: number_of_entries = 10
        frame_type = 14 /* same */
        frame_type = 253 /* append */
          offset_delta = 10
          locals = [ int, int ]
        frame_type = 252 /* append */
          offset_delta = 27
          locals = [ int ]
        frame_type = 252 /* append */
          offset_delta = 9
          locals = [ int ]
        frame_type = 250 /* chop */
          offset_delta = 18
        frame_type = 6 /* same */
        frame_type = 1 /* same */
        frame_type = 249 /* chop */
          offset_delta = 12
        frame_type = 252 /* append */
          offset_delta = 1
          locals = [ int ]
        frame_type = 250 /* chop */
          offset_delta = 17

  public static java.lang.String quote(java.lang.String);
    descriptor: (Ljava/lang/String;)Ljava/lang/String;
    flags: (0x0009) ACC_PUBLIC, ACC_STATIC
    Code:
      stack=5, locals=2, args_size=1
         0: new           #7                  // class java/lang/StringBuilder
         3: dup
         4: iconst_2
         5: aload_0
         6: invokevirtual #5                  // Method java/lang/String.length:()I
         9: iconst_2
        10: imul
        11: iadd
        12: invokespecial #8                  // Method java/lang/StringBuilder."<init>":(I)V
        15: astore_1
        16: aload_1
        17: aload_0
        18: invokestatic  #9                  // Method quote:(Ljava/lang/StringBuilder;Ljava/lang/String;)V
        21: aload_1
        22: invokevirtual #10                 // Method java/lang/StringBuilder.toString:()Ljava/lang/String;
        25: areturn
      LineNumberTable:
        line 97: 0
        line 98: 16
        line 99: 21
      LocalVariableTable:
        Start  Length  Slot  Name   Signature
            0      26     0   arg   Ljava/lang/String;
           16      10     1   buf   Ljava/lang/StringBuilder;

  private static boolean mightNeedQuotes(java.lang.String);
    descriptor: (Ljava/lang/String;)Z
    flags: (0x000a) ACC_PRIVATE, ACC_STATIC
    Code:
      stack=2, locals=3, args_size=1
         0: aload_0
         1: invokevirtual #5                  // Method java/lang/String.length:()I
         4: ifne          9
         7: iconst_1
         8: ireturn
         9: iconst_0
        10: istore_1
        11: iload_1
        12: aload_0
        13: invokevirtual #5                  // Method java/lang/String.length:()I
        16: if_icmpge     51
        19: aload_0
        20: iload_1
        21: invokevirtual #6                  // Method java/lang/String.charAt:(I)C
        24: istore_2
        25: iload_2
        26: bipush        34
        28: if_icmpeq     43
        31: iload_2
        32: bipush        32
        34: if_icmpeq     43
        37: iload_2
        38: bipush        9
        40: if_icmpne     45
        43: iconst_1
        44: ireturn
        45: iinc          1, 1
        48: goto          11
        51: iconst_0
        52: ireturn
      LineNumberTable:
        line 104: 0
        line 105: 7
        line 108: 9
        line 109: 19
        line 110: 25
        line 111: 43
        line 108: 45
        line 115: 51
      LocalVariableTable:
        Start  Length  Slot  Name   Signature
           25      20     2     c   C
           11      40     1     i   I
            0      53     0   arg   Ljava/lang/String;
      StackMapTable: number_of_entries = 5
        frame_type = 9 /* same */
        frame_type = 252 /* append */
          offset_delta = 1
          locals = [ int ]
        frame_type = 252 /* append */
          offset_delta = 31
          locals = [ int ]
        frame_type = 250 /* chop */
          offset_delta = 1
        frame_type = 250 /* chop */
          offset_delta = 5
}
SourceFile: "WindowsCreateProcessEscape.java"
