Classfile /Users/mw/Projects/slang-braindump/.jar/jar8/assemble/slang-braindump/assemble/content/scala/runtime/AbstractPartialFunction$mcJD$sp.class
  Last modified May 29, 2022; size 1428 bytes
  SHA-256 checksum 075347b3eec6eb625bf028bf6e3b1b3fac256a16dc83723ac9cb9525242d670f
  Compiled from "AbstractPartialFunction.scala"
public abstract class scala.runtime.AbstractPartialFunction$mcJD$sp extends scala.runtime.AbstractPartialFunction<java.lang.Object, java.lang.Object> implements scala.Function1$mcJD$sp
  minor version: 0
  major version: 52
  flags: (0x0421) ACC_PUBLIC, ACC_SUPER, ACC_ABSTRACT
  this_class: #2                          // scala/runtime/AbstractPartialFunction$mcJD$sp
  super_class: #5                         // scala/runtime/AbstractPartialFunction
  interfaces: 1, fields: 0, methods: 4, attributes: 4
Constant pool:
   #1 = Utf8               scala/runtime/AbstractPartialFunction$mcJD$sp
   #2 = Class              #1             // scala/runtime/AbstractPartialFunction$mcJD$sp
   #3 = Utf8               Lscala/runtime/AbstractPartialFunction<Ljava/lang/Object;Ljava/lang/Object;>;Lscala/Function1$mcJD$sp;
   #4 = Utf8               scala/runtime/AbstractPartialFunction
   #5 = Class              #4             // scala/runtime/AbstractPartialFunction
   #6 = Utf8               scala/Function1$mcJD$sp
   #7 = Class              #6             // scala/Function1$mcJD$sp
   #8 = Utf8               AbstractPartialFunction.scala
   #9 = Utf8               apply
  #10 = Utf8               (D)J
  #11 = Utf8               x
  #12 = Utf8               apply$mcJD$sp
  #13 = NameAndType        #12:#10        // apply$mcJD$sp:(D)J
  #14 = Methodref          #2.#13         // scala/runtime/AbstractPartialFunction$mcJD$sp.apply$mcJD$sp:(D)J
  #15 = Utf8               this
  #16 = Utf8               Lscala/runtime/AbstractPartialFunction$mcJD$sp;
  #17 = Utf8               D
  #18 = Utf8               java/lang/Double
  #19 = Class              #18            // java/lang/Double
  #20 = Utf8               valueOf
  #21 = Utf8               (D)Ljava/lang/Double;
  #22 = NameAndType        #20:#21        // valueOf:(D)Ljava/lang/Double;
  #23 = Methodref          #19.#22        // java/lang/Double.valueOf:(D)Ljava/lang/Double;
  #24 = Utf8               scala/PartialFunction$
  #25 = Class              #24            // scala/PartialFunction$
  #26 = Utf8               MODULE$
  #27 = Utf8               Lscala/PartialFunction$;
  #28 = NameAndType        #26:#27        // MODULE$:Lscala/PartialFunction$;
  #29 = Fieldref           #25.#28        // scala/PartialFunction$.MODULE$:Lscala/PartialFunction$;
  #30 = Utf8               empty
  #31 = Utf8               ()Lscala/PartialFunction;
  #32 = NameAndType        #30:#31        // empty:()Lscala/PartialFunction;
  #33 = Methodref          #25.#32        // scala/PartialFunction$.empty:()Lscala/PartialFunction;
  #34 = Utf8               applyOrElse
  #35 = Utf8               (Ljava/lang/Object;Lscala/Function1;)Ljava/lang/Object;
  #36 = NameAndType        #34:#35        // applyOrElse:(Ljava/lang/Object;Lscala/Function1;)Ljava/lang/Object;
  #37 = Methodref          #2.#36         // scala/runtime/AbstractPartialFunction$mcJD$sp.applyOrElse:(Ljava/lang/Object;Lscala/Function1;)Ljava/lang/Object;
  #38 = Utf8               scala/runtime/BoxesRunTime
  #39 = Class              #38            // scala/runtime/BoxesRunTime
  #40 = Utf8               unboxToLong
  #41 = Utf8               (Ljava/lang/Object;)J
  #42 = NameAndType        #40:#41        // unboxToLong:(Ljava/lang/Object;)J
  #43 = Methodref          #39.#42        // scala/runtime/BoxesRunTime.unboxToLong:(Ljava/lang/Object;)J
  #44 = Utf8               (Ljava/lang/Object;)Ljava/lang/Object;
  #45 = Utf8               unboxToDouble
  #46 = Utf8               (Ljava/lang/Object;)D
  #47 = NameAndType        #45:#46        // unboxToDouble:(Ljava/lang/Object;)D
  #48 = Methodref          #39.#47        // scala/runtime/BoxesRunTime.unboxToDouble:(Ljava/lang/Object;)D
  #49 = NameAndType        #9:#10         // apply:(D)J
  #50 = Methodref          #2.#49         // scala/runtime/AbstractPartialFunction$mcJD$sp.apply:(D)J
  #51 = Utf8               boxToLong
  #52 = Utf8               (J)Ljava/lang/Long;
  #53 = NameAndType        #51:#52        // boxToLong:(J)Ljava/lang/Long;
  #54 = Methodref          #39.#53        // scala/runtime/BoxesRunTime.boxToLong:(J)Ljava/lang/Long;
  #55 = Utf8               Ljava/lang/Object;
  #56 = Utf8               <init>
  #57 = Utf8               ()V
  #58 = NameAndType        #56:#57        // "<init>":()V
  #59 = Methodref          #5.#58         // scala/runtime/AbstractPartialFunction."<init>":()V
  #60 = Utf8               Code
  #61 = Utf8               LineNumberTable
  #62 = Utf8               LocalVariableTable
  #63 = Utf8               MethodParameters
  #64 = Utf8               Signature
  #65 = Utf8               SourceFile
  #66 = Utf8               ScalaInlineInfo
  #67 = Utf8               Scala
{
  public long apply(double);
    descriptor: (D)J
    flags: (0x0001) ACC_PUBLIC
    Code:
      stack=3, locals=3, args_size=2
         0: aload_0
         1: dload_1
         2: invokevirtual #14                 // Method apply$mcJD$sp:(D)J
         5: lreturn
      LineNumberTable:
        line 35: 0
      LocalVariableTable:
        Start  Length  Slot  Name   Signature
            0       6     0  this   Lscala/runtime/AbstractPartialFunction$mcJD$sp;
            0       6     1     x   D
    MethodParameters:
      Name                           Flags
      x                              final

  public long apply$mcJD$sp(double);
    descriptor: (D)J
    flags: (0x0001) ACC_PUBLIC
    Code:
      stack=3, locals=3, args_size=2
         0: aload_0
         1: dload_1
         2: invokestatic  #23                 // Method java/lang/Double.valueOf:(D)Ljava/lang/Double;
         5: getstatic     #29                 // Field scala/PartialFunction$.MODULE$:Lscala/PartialFunction$;
         8: invokevirtual #33                 // Method scala/PartialFunction$.empty:()Lscala/PartialFunction;
        11: invokevirtual #37                 // Method applyOrElse:(Ljava/lang/Object;Lscala/Function1;)Ljava/lang/Object;
        14: invokestatic  #43                 // Method scala/runtime/BoxesRunTime.unboxToLong:(Ljava/lang/Object;)J
        17: lreturn
      LineNumberTable:
        line 35: 0
      LocalVariableTable:
        Start  Length  Slot  Name   Signature
            0      18     0  this   Lscala/runtime/AbstractPartialFunction$mcJD$sp;
            0      18     1     x   D
    MethodParameters:
      Name                           Flags
      x                              final

  public java.lang.Object apply(java.lang.Object);
    descriptor: (Ljava/lang/Object;)Ljava/lang/Object;
    flags: (0x1041) ACC_PUBLIC, ACC_BRIDGE, ACC_SYNTHETIC
    Code:
      stack=3, locals=2, args_size=2
         0: aload_0
         1: aload_1
         2: invokestatic  #48                 // Method scala/runtime/BoxesRunTime.unboxToDouble:(Ljava/lang/Object;)D
         5: invokevirtual #50                 // Method apply:(D)J
         8: invokestatic  #54                 // Method scala/runtime/BoxesRunTime.boxToLong:(J)Ljava/lang/Long;
        11: areturn
      LineNumberTable:
        line 27: 0
      LocalVariableTable:
        Start  Length  Slot  Name   Signature
            0      12     0  this   Lscala/runtime/AbstractPartialFunction$mcJD$sp;
            0      12     1     x   Ljava/lang/Object;
    MethodParameters:
      Name                           Flags
      x                              final

  public scala.runtime.AbstractPartialFunction$mcJD$sp();
    descriptor: ()V
    flags: (0x0001) ACC_PUBLIC
    Code:
      stack=1, locals=1, args_size=1
         0: aload_0
         1: invokespecial #59                 // Method scala/runtime/AbstractPartialFunction."<init>":()V
         4: return
      LineNumberTable:
        line 27: 0
      LocalVariableTable:
        Start  Length  Slot  Name   Signature
            0       5     0  this   Lscala/runtime/AbstractPartialFunction$mcJD$sp;
}
Signature: #3                           // Lscala/runtime/AbstractPartialFunction<Ljava/lang/Object;Ljava/lang/Object;>;Lscala/Function1$mcJD$sp;
SourceFile: "AbstractPartialFunction.scala"
  ScalaInlineInfo: length = 0x18 (unknown attribute)
   01 00 00 04 00 38 00 39 00 00 09 00 0A 00 00 09
   00 2C 00 00 0C 00 0A 00
  Scala: length = 0x0 (unknown attribute)

