Classfile /Users/mw/Projects/slang-braindump/.jar/jar8/assemble/slang-braindump/assemble/content/scala/runtime/AbstractFunction0$mcZ$sp.class
  Last modified May 29, 2022; size 511 bytes
  SHA-256 checksum 35abd59a16fb970674c6bf391be1204ef7559417b00ae6029cb7298b1dab60ab
  Compiled from "AbstractFunction0.scala"
public abstract class scala.runtime.AbstractFunction0$mcZ$sp extends scala.runtime.AbstractFunction0<java.lang.Object> implements scala.Function0$mcZ$sp
  minor version: 0
  major version: 52
  flags: (0x0421) ACC_PUBLIC, ACC_SUPER, ACC_ABSTRACT
  this_class: #2                          // scala/runtime/AbstractFunction0$mcZ$sp
  super_class: #5                         // scala/runtime/AbstractFunction0
  interfaces: 1, fields: 0, methods: 1, attributes: 4
Constant pool:
   #1 = Utf8               scala/runtime/AbstractFunction0$mcZ$sp
   #2 = Class              #1             // scala/runtime/AbstractFunction0$mcZ$sp
   #3 = Utf8               Lscala/runtime/AbstractFunction0<Ljava/lang/Object;>;Lscala/Function0$mcZ$sp;
   #4 = Utf8               scala/runtime/AbstractFunction0
   #5 = Class              #4             // scala/runtime/AbstractFunction0
   #6 = Utf8               scala/Function0$mcZ$sp
   #7 = Class              #6             // scala/Function0$mcZ$sp
   #8 = Utf8               AbstractFunction0.scala
   #9 = Utf8               <init>
  #10 = Utf8               ()V
  #11 = NameAndType        #9:#10         // "<init>":()V
  #12 = Methodref          #5.#11         // scala/runtime/AbstractFunction0."<init>":()V
  #13 = Utf8               this
  #14 = Utf8               Lscala/runtime/AbstractFunction0$mcZ$sp;
  #15 = Utf8               Code
  #16 = Utf8               LineNumberTable
  #17 = Utf8               LocalVariableTable
  #18 = Utf8               Signature
  #19 = Utf8               SourceFile
  #20 = Utf8               ScalaInlineInfo
  #21 = Utf8               Scala
{
  public scala.runtime.AbstractFunction0$mcZ$sp();
    descriptor: ()V
    flags: (0x0001) ACC_PUBLIC
    Code:
      stack=1, locals=1, args_size=1
         0: aload_0
         1: invokespecial #12                 // Method scala/runtime/AbstractFunction0."<init>":()V
         4: return
      LineNumberTable:
        line 17: 0
      LocalVariableTable:
        Start  Length  Slot  Name   Signature
            0       5     0  this   Lscala/runtime/AbstractFunction0$mcZ$sp;
}
Signature: #3                           // Lscala/runtime/AbstractFunction0<Ljava/lang/Object;>;Lscala/Function0$mcZ$sp;
SourceFile: "AbstractFunction0.scala"
  ScalaInlineInfo: length = 0x9 (unknown attribute)
   01 00 00 01 00 09 00 0A 00
  Scala: length = 0x0 (unknown attribute)

