Classfile /Users/mw/Projects/slang-braindump/.jar/jar8/assemble/slang-braindump/assemble/content/scala/runtime/ArrayCharSequence.class
  Last modified May 29, 2022; size 2741 bytes
  SHA-256 checksum 5ea93627bc2096130ff9ad65585c24891f26ce16b8a5d3ff3b9a85eb2b042f14
  Compiled from "ArrayCharSequence.scala"
public final class scala.runtime.ArrayCharSequence implements java.lang.CharSequence
  minor version: 0
  major version: 52
  flags: (0x0031) ACC_PUBLIC, ACC_FINAL, ACC_SUPER
  this_class: #2                          // scala/runtime/ArrayCharSequence
  super_class: #4                         // java/lang/Object
  interfaces: 1, fields: 3, methods: 8, attributes: 4
Constant pool:
    #1 = Utf8               scala/runtime/ArrayCharSequence
    #2 = Class              #1            // scala/runtime/ArrayCharSequence
    #3 = Utf8               java/lang/Object
    #4 = Class              #3            // java/lang/Object
    #5 = Utf8               java/lang/CharSequence
    #6 = Class              #5            // java/lang/CharSequence
    #7 = Utf8               ArrayCharSequence.scala
    #8 = Utf8               Lscala/reflect/ScalaSignature;
    #9 = Utf8               bytes
   #10 = Utf8               \u0006\u0005\r3AAC\u0006\u0003!!AA\u0004\u0001BC\u0002\u0013\u0005Q\u0004\u0003\u0005&\u0001\t\u0005\t\u0015!\u0003\u001f\u0011!1\u0003A!A!\u0002\u00139\u0003\u0002\u0003\u0016\u0001\u0005\u0003\u0005\u000b\u0011B\u0014\t\u000b-\u0002A\u0011\u0001\u0017\t\u000bI\u0002A\u0011A\u001a\t\u000bQ\u0002A\u0011A\u001b\t\u000ba\u0002A\u0011A\u001d\t\u000by\u0002A\u0011I \u0003#\u0005\u0013(/Y=DQ\u0006\u00148+Z9vK:\u001cWM\u0003\u0002\r\u001b\u00059!/\u001e8uS6,\'\"\u0001\b\u0002\u000bM\u001c\u0017\r\\1\u0004\u0001M\u0019\u0001!E\r\u0011\u0005I9R\"A\n\u000b\u0005Q)\u0012\u0001\u00027b]\u001eT\u0011AF\u0001\u0005U\u00064\u0018-\u0003\u0002\u0019\'\t1qJ\u00196fGR\u0004\"A\u0005\u000e\n\u0005m\u0019\"\u0001D\"iCJ\u001cV-];f]\u000e,\u0017A\u0001=t+\u0005q\u0002cA\u0010!E5\tQ\"\u0003\u0002\"\u001b\t)\u0011I\u001d:bsB\u0011qdI\u0005\u0003I5\u0011Aa\u00115be\u0006\u0019\u0001p\u001d\u0011\u0002\u000bM$\u0018M\u001d;\u0011\u0005}A\u0013BA\u0015\u000e\u0005\rIe\u000e^\u0001\u0004K:$\u0017A\u0002\u001fj]&$h\b\u0006\u0003._A\n\u0004C\u0001\u0018\u0001\u001b\u0005Y\u0001\"\u0002\u000f\u0006\u0001\u0004q\u0002\"\u0002\u0014\u0006\u0001\u00049\u0003\"\u0002\u0016\u0006\u0001\u00049\u0013A\u00027f]\u001e$\b\u000eF\u0001(\u0003\u0019\u0019\u0007.\u0019:BiR\u0011!E\u000e\u0005\u0006o\u001d\u0001\raJ\u0001\u0006S:$W\r_\u0001\fgV\u00147+Z9vK:\u001cW\rF\u0002\u001auqBQa\u000f\u0005A\u0002\u001d\naa\u001d;beR\u0004\u0004\"B\u001f\t\u0001\u00049\u0013\u0001B3oIB\n\u0001\u0002^8TiJLgn\u001a\u000b\u0002\u0001B\u0011!#Q\u0005\u0003\u0005N\u0011aa\u0015;sS:<\u0007
   #11 = Utf8               xs
   #12 = Utf8               [C
   #13 = Utf8               start
   #14 = Utf8               I
   #15 = Utf8               end
   #16 = Utf8               chars
   #17 = Utf8               ()Ljava/util/stream/IntStream;
   #18 = NameAndType        #16:#17       // chars:()Ljava/util/stream/IntStream;
   #19 = InterfaceMethodref #6.#18        // java/lang/CharSequence.chars:()Ljava/util/stream/IntStream;
   #20 = Utf8               this
   #21 = Utf8               Lscala/runtime/ArrayCharSequence;
   #22 = Utf8               codePoints
   #23 = NameAndType        #22:#17       // codePoints:()Ljava/util/stream/IntStream;
   #24 = InterfaceMethodref #6.#23        // java/lang/CharSequence.codePoints:()Ljava/util/stream/IntStream;
   #25 = Utf8               ()[C
   #26 = NameAndType        #11:#12       // xs:[C
   #27 = Fieldref           #2.#26        // scala/runtime/ArrayCharSequence.xs:[C
   #28 = Utf8               length
   #29 = Utf8               ()I
   #30 = Utf8               scala/math/package$
   #31 = Class              #30           // scala/math/package$
   #32 = Utf8               MODULE$
   #33 = Utf8               Lscala/math/package$;
   #34 = NameAndType        #32:#33       // MODULE$:Lscala/math/package$;
   #35 = Fieldref           #31.#34       // scala/math/package$.MODULE$:Lscala/math/package$;
   #36 = NameAndType        #15:#14       // end:I
   #37 = Fieldref           #2.#36        // scala/runtime/ArrayCharSequence.end:I
   #38 = NameAndType        #13:#14       // start:I
   #39 = Fieldref           #2.#38        // scala/runtime/ArrayCharSequence.start:I
   #40 = Utf8               java/lang/Math
   #41 = Class              #40           // java/lang/Math
   #42 = Utf8               max
   #43 = Utf8               (II)I
   #44 = NameAndType        #42:#43       // max:(II)I
   #45 = Methodref          #41.#44       // java/lang/Math.max:(II)I
   #46 = Utf8               charAt
   #47 = Utf8               (I)C
   #48 = Utf8               index
   #49 = NameAndType        #28:#29       // length:()I
   #50 = Methodref          #2.#49        // scala/runtime/ArrayCharSequence.length:()I
   #51 = NameAndType        #11:#25       // xs:()[C
   #52 = Methodref          #2.#51        // scala/runtime/ArrayCharSequence.xs:()[C
   #53 = Utf8               java/lang/ArrayIndexOutOfBoundsException
   #54 = Class              #53           // java/lang/ArrayIndexOutOfBoundsException
   #55 = Utf8               java/lang/StringBuilder
   #56 = Class              #55           // java/lang/StringBuilder
   #57 = Integer            31
   #58 = Utf8               <init>
   #59 = Utf8               (I)V
   #60 = NameAndType        #58:#59       // "<init>":(I)V
   #61 = Methodref          #56.#60       // java/lang/StringBuilder."<init>":(I)V
   #62 = Utf8               append
   #63 = Utf8               (I)Ljava/lang/StringBuilder;
   #64 = NameAndType        #62:#63       // append:(I)Ljava/lang/StringBuilder;
   #65 = Methodref          #56.#64       // java/lang/StringBuilder.append:(I)Ljava/lang/StringBuilder;
   #66 = Utf8                is out of bounds (min 0, max
   #67 = String             #66           //  is out of bounds (min 0, max
   #68 = Utf8               (Ljava/lang/String;)Ljava/lang/StringBuilder;
   #69 = NameAndType        #62:#68       // append:(Ljava/lang/String;)Ljava/lang/StringBuilder;
   #70 = Methodref          #56.#69       // java/lang/StringBuilder.append:(Ljava/lang/String;)Ljava/lang/StringBuilder;
   #71 = Utf8               )
   #72 = String             #71           // )
   #73 = Utf8               toString
   #74 = Utf8               ()Ljava/lang/String;
   #75 = NameAndType        #73:#74       // toString:()Ljava/lang/String;
   #76 = Methodref          #56.#75       // java/lang/StringBuilder.toString:()Ljava/lang/String;
   #77 = Utf8               (Ljava/lang/String;)V
   #78 = NameAndType        #58:#77       // "<init>":(Ljava/lang/String;)V
   #79 = Methodref          #54.#78       // java/lang/ArrayIndexOutOfBoundsException."<init>":(Ljava/lang/String;)V
   #80 = Utf8               subSequence
   #81 = Utf8               (II)Ljava/lang/CharSequence;
   #82 = Utf8               start0
   #83 = Utf8               end0
   #84 = Utf8               ([CII)V
   #85 = NameAndType        #58:#84       // "<init>":([CII)V
   #86 = Methodref          #2.#85        // scala/runtime/ArrayCharSequence."<init>":([CII)V
   #87 = Utf8               newlen
   #88 = Utf8               start1
   #89 = Utf8               min
   #90 = NameAndType        #89:#43       // min:(II)I
   #91 = Methodref          #41.#90       // java/lang/Math.min:(II)I
   #92 = Utf8
   #93 = String             #92           //
   #94 = Utf8               java/lang/String
   #95 = Class              #94           // java/lang/String
   #96 = Methodref          #95.#85       // java/lang/String."<init>":([CII)V
   #97 = Utf8               ()V
   #98 = NameAndType        #58:#97       // "<init>":()V
   #99 = Methodref          #4.#98        // java/lang/Object."<init>":()V
  #100 = Utf8               Code
  #101 = Utf8               LineNumberTable
  #102 = Utf8               LocalVariableTable
  #103 = Utf8               StackMapTable
  #104 = Utf8               MethodParameters
  #105 = Utf8               SourceFile
  #106 = Utf8               RuntimeVisibleAnnotations
  #107 = Utf8               ScalaInlineInfo
  #108 = Utf8               ScalaSig
{
  private final char[] xs;
    descriptor: [C
    flags: (0x0012) ACC_PRIVATE, ACC_FINAL

  private final int start;
    descriptor: I
    flags: (0x0012) ACC_PRIVATE, ACC_FINAL

  private final int end;
    descriptor: I
    flags: (0x0012) ACC_PRIVATE, ACC_FINAL

  public java.util.stream.IntStream chars();
    descriptor: ()Ljava/util/stream/IntStream;
    flags: (0x0001) ACC_PUBLIC
    Code:
      stack=1, locals=1, args_size=1
         0: aload_0
         1: invokespecial #19                 // InterfaceMethod java/lang/CharSequence.chars:()Ljava/util/stream/IntStream;
         4: areturn
      LineNumberTable:
        line 18: 0
      LocalVariableTable:
        Start  Length  Slot  Name   Signature
            0       5     0  this   Lscala/runtime/ArrayCharSequence;

  public java.util.stream.IntStream codePoints();
    descriptor: ()Ljava/util/stream/IntStream;
    flags: (0x0001) ACC_PUBLIC
    Code:
      stack=1, locals=1, args_size=1
         0: aload_0
         1: invokespecial #24                 // InterfaceMethod java/lang/CharSequence.codePoints:()Ljava/util/stream/IntStream;
         4: areturn
      LineNumberTable:
        line 18: 0
      LocalVariableTable:
        Start  Length  Slot  Name   Signature
            0       5     0  this   Lscala/runtime/ArrayCharSequence;

  public char[] xs();
    descriptor: ()[C
    flags: (0x0001) ACC_PUBLIC
    Code:
      stack=1, locals=1, args_size=1
         0: aload_0
         1: getfield      #27                 // Field xs:[C
         4: areturn
      LineNumberTable:
        line 18: 0
      LocalVariableTable:
        Start  Length  Slot  Name   Signature
            0       5     0  this   Lscala/runtime/ArrayCharSequence;

  public int length();
    descriptor: ()I
    flags: (0x0001) ACC_PUBLIC
    Code:
      stack=3, locals=1, args_size=1
         0: getstatic     #35                 // Field scala/math/package$.MODULE$:Lscala/math/package$;
         3: pop
         4: iconst_0
         5: aload_0
         6: getfield      #37                 // Field end:I
         9: aload_0
        10: getfield      #39                 // Field start:I
        13: isub
        14: invokestatic  #45                 // Method java/lang/Math.max:(II)I
        17: ireturn
      LineNumberTable:
        line 25: 0
      LocalVariableTable:
        Start  Length  Slot  Name   Signature
            0      18     0  this   Lscala/runtime/ArrayCharSequence;

  public char charAt(int);
    descriptor: (I)C
    flags: (0x0001) ACC_PUBLIC
    Code:
      stack=5, locals=2, args_size=2
         0: iconst_0
         1: iload_1
         2: if_icmpgt     25
         5: iload_1
         6: aload_0
         7: invokevirtual #50                 // Method length:()I
        10: if_icmpge     25
        13: aload_0
        14: invokevirtual #52                 // Method xs:()[C
        17: aload_0
        18: getfield      #39                 // Field start:I
        21: iload_1
        22: iadd
        23: caload
        24: ireturn
        25: new           #54                 // class java/lang/ArrayIndexOutOfBoundsException
        28: dup
        29: new           #56                 // class java/lang/StringBuilder
        32: dup
        33: ldc           #57                 // int 31
        35: invokespecial #61                 // Method java/lang/StringBuilder."<init>":(I)V
        38: iload_1
        39: invokevirtual #65                 // Method java/lang/StringBuilder.append:(I)Ljava/lang/StringBuilder;
        42: ldc           #67                 // String  is out of bounds (min 0, max
        44: invokevirtual #70                 // Method java/lang/StringBuilder.append:(Ljava/lang/String;)Ljava/lang/StringBuilder;
        47: aload_0
        48: invokevirtual #52                 // Method xs:()[C
        51: arraylength
        52: iconst_1
        53: isub
        54: invokevirtual #65                 // Method java/lang/StringBuilder.append:(I)Ljava/lang/StringBuilder;
        57: ldc           #72                 // String )
        59: invokevirtual #70                 // Method java/lang/StringBuilder.append:(Ljava/lang/String;)Ljava/lang/StringBuilder;
        62: invokevirtual #76                 // Method java/lang/StringBuilder.toString:()Ljava/lang/String;
        65: invokespecial #79                 // Method java/lang/ArrayIndexOutOfBoundsException."<init>":(Ljava/lang/String;)V
        68: athrow
      StackMapTable: number_of_entries = 1
        frame_type = 25 /* same */
      LineNumberTable:
        line 27: 0
        line 28: 13
        line 29: 25
      LocalVariableTable:
        Start  Length  Slot  Name   Signature
            0      69     0  this   Lscala/runtime/ArrayCharSequence;
            0      69     1 index   I
    MethodParameters:
      Name                           Flags
      index                          final

  public java.lang.CharSequence subSequence(int, int);
    descriptor: (II)Ljava/lang/CharSequence;
    flags: (0x0001) ACC_PUBLIC
    Code:
      stack=6, locals=5, args_size=3
         0: iload_1
         1: iconst_0
         2: if_icmpge     48
         5: new           #54                 // class java/lang/ArrayIndexOutOfBoundsException
         8: dup
         9: new           #56                 // class java/lang/StringBuilder
        12: dup
        13: ldc           #57                 // int 31
        15: invokespecial #61                 // Method java/lang/StringBuilder."<init>":(I)V
        18: iload_1
        19: invokevirtual #65                 // Method java/lang/StringBuilder.append:(I)Ljava/lang/StringBuilder;
        22: ldc           #67                 // String  is out of bounds (min 0, max
        24: invokevirtual #70                 // Method java/lang/StringBuilder.append:(Ljava/lang/String;)Ljava/lang/StringBuilder;
        27: aload_0
        28: invokevirtual #50                 // Method length:()I
        31: iconst_1
        32: isub
        33: invokevirtual #65                 // Method java/lang/StringBuilder.append:(I)Ljava/lang/StringBuilder;
        36: ldc           #72                 // String )
        38: invokevirtual #70                 // Method java/lang/StringBuilder.append:(Ljava/lang/String;)Ljava/lang/StringBuilder;
        41: invokevirtual #76                 // Method java/lang/StringBuilder.toString:()Ljava/lang/String;
        44: invokespecial #79                 // Method java/lang/ArrayIndexOutOfBoundsException."<init>":(Ljava/lang/String;)V
        47: athrow
        48: iload_2
        49: aload_0
        50: invokevirtual #50                 // Method length:()I
        53: if_icmple     100
        56: new           #54                 // class java/lang/ArrayIndexOutOfBoundsException
        59: dup
        60: new           #56                 // class java/lang/StringBuilder
        63: dup
        64: ldc           #57                 // int 31
        66: invokespecial #61                 // Method java/lang/StringBuilder."<init>":(I)V
        69: iload_2
        70: invokevirtual #65                 // Method java/lang/StringBuilder.append:(I)Ljava/lang/StringBuilder;
        73: ldc           #67                 // String  is out of bounds (min 0, max
        75: invokevirtual #70                 // Method java/lang/StringBuilder.append:(Ljava/lang/String;)Ljava/lang/StringBuilder;
        78: aload_0
        79: invokevirtual #52                 // Method xs:()[C
        82: arraylength
        83: iconst_1
        84: isub
        85: invokevirtual #65                 // Method java/lang/StringBuilder.append:(I)Ljava/lang/StringBuilder;
        88: ldc           #72                 // String )
        90: invokevirtual #70                 // Method java/lang/StringBuilder.append:(Ljava/lang/String;)Ljava/lang/StringBuilder;
        93: invokevirtual #76                 // Method java/lang/StringBuilder.toString:()Ljava/lang/String;
        96: invokespecial #79                 // Method java/lang/ArrayIndexOutOfBoundsException."<init>":(Ljava/lang/String;)V
        99: athrow
       100: iload_2
       101: iload_1
       102: if_icmpgt     119
       105: new           #2                  // class scala/runtime/ArrayCharSequence
       108: dup
       109: aload_0
       110: invokevirtual #52                 // Method xs:()[C
       113: iconst_0
       114: iconst_0
       115: invokespecial #86                 // Method "<init>":([CII)V
       118: areturn
       119: iload_2
       120: iload_1
       121: isub
       122: istore_3
       123: aload_0
       124: getfield      #39                 // Field start:I
       127: iload_1
       128: iadd
       129: istore        4
       131: new           #2                  // class scala/runtime/ArrayCharSequence
       134: dup
       135: aload_0
       136: invokevirtual #52                 // Method xs:()[C
       139: iload         4
       141: iload         4
       143: iload_3
       144: iadd
       145: invokespecial #86                 // Method "<init>":([CII)V
       148: areturn
      StackMapTable: number_of_entries = 3
        frame_type = 48 /* same */
        frame_type = 51 /* same */
        frame_type = 18 /* same */
      LineNumberTable:
        line 32: 0
        line 33: 48
        line 34: 100
        line 36: 119
        line 37: 123
        line 38: 131
      LocalVariableTable:
        Start  Length  Slot  Name   Signature
          123      25     3 newlen   I
          131      17     4 start1   I
            0     149     0  this   Lscala/runtime/ArrayCharSequence;
            0     149     1 start0   I
            0     149     2  end0   I
    MethodParameters:
      Name                           Flags
      start0                         final
      end0                           final

  public java.lang.String toString();
    descriptor: ()Ljava/lang/String;
    flags: (0x0001) ACC_PUBLIC
    Code:
      stack=6, locals=3, args_size=1
         0: getstatic     #35                 // Field scala/math/package$.MODULE$:Lscala/math/package$;
         3: pop
         4: aload_0
         5: getfield      #39                 // Field start:I
         8: iconst_0
         9: invokestatic  #45                 // Method java/lang/Math.max:(II)I
        12: istore_1
        13: getstatic     #35                 // Field scala/math/package$.MODULE$:Lscala/math/package$;
        16: pop
        17: aload_0
        18: invokevirtual #52                 // Method xs:()[C
        21: arraylength
        22: iload_1
        23: aload_0
        24: invokevirtual #50                 // Method length:()I
        27: iadd
        28: invokestatic  #91                 // Method java/lang/Math.min:(II)I
        31: istore_2
        32: iload_1
        33: iload_2
        34: if_icmplt     40
        37: ldc           #93                 // String
        39: areturn
        40: new           #95                 // class java/lang/String
        43: dup
        44: aload_0
        45: invokevirtual #52                 // Method xs:()[C
        48: iload_1
        49: iload_2
        50: iload_1
        51: isub
        52: invokespecial #96                 // Method java/lang/String."<init>":([CII)V
        55: areturn
      StackMapTable: number_of_entries = 1
        frame_type = 253 /* append */
          offset_delta = 40
          locals = [ int, int ]
      LineNumberTable:
        line 42: 0
        line 43: 13
        line 45: 32
      LocalVariableTable:
        Start  Length  Slot  Name   Signature
            0      56     0  this   Lscala/runtime/ArrayCharSequence;

  public scala.runtime.ArrayCharSequence(char[], int, int);
    descriptor: ([CII)V
    flags: (0x0001) ACC_PUBLIC
    Code:
      stack=2, locals=4, args_size=4
         0: aload_0
         1: aload_1
         2: putfield      #27                 // Field xs:[C
         5: aload_0
         6: iload_2
         7: putfield      #39                 // Field start:I
        10: aload_0
        11: iload_3
        12: putfield      #37                 // Field end:I
        15: aload_0
        16: invokespecial #99                 // Method java/lang/Object."<init>":()V
        19: return
      LineNumberTable:
        line 18: 0
      LocalVariableTable:
        Start  Length  Slot  Name   Signature
            0      20     0  this   Lscala/runtime/ArrayCharSequence;
            0      20     1    xs   [C
            0      20     2 start   I
            0      20     3   end   I
    MethodParameters:
      Name                           Flags
      xs                             final
      start                          final
      end                            final
}
SourceFile: "ArrayCharSequence.scala"
RuntimeVisibleAnnotations:
  0: #8(#9=s#10)
    scala.reflect.ScalaSignature(
      bytes="\u0006\u0005\r3AAC\u0006\u0003!!AA\u0004\u0001BC\u0002\u0013\u0005Q\u0004\u0003\u0005&\u0001\t\u0005\t\u0015!\u0003\u001f\u0011!1\u0003A!A!\u0002\u00139\u0003\u0002\u0003\u0016\u0001\u0005\u0003\u0005\u000b\u0011B\u0014\t\u000b-\u0002A\u0011\u0001\u0017\t\u000bI\u0002A\u0011A\u001a\t\u000bQ\u0002A\u0011A\u001b\t\u000ba\u0002A\u0011A\u001d\t\u000by\u0002A\u0011I \u0003#\u0005\u0013(/Y=DQ\u0006\u00148+Z9vK:\u001cWM\u0003\u0002\r\u001b\u00059!/\u001e8uS6,\'\"\u0001\b\u0002\u000bM\u001c\u0017\r\\1\u0004\u0001M\u0019\u0001!E\r\u0011\u0005I9R\"A\n\u000b\u0005Q)\u0012\u0001\u00027b]\u001eT\u0011AF\u0001\u0005U\u00064\u0018-\u0003\u0002\u0019\'\t1qJ\u00196fGR\u0004\"A\u0005\u000e\n\u0005m\u0019\"\u0001D\"iCJ\u001cV-];f]\u000e,\u0017A\u0001=t+\u0005q\u0002cA\u0010!E5\tQ\"\u0003\u0002\"\u001b\t)\u0011I\u001d:bsB\u0011qdI\u0005\u0003I5\u0011Aa\u00115be\u0006\u0019\u0001p\u001d\u0011\u0002\u000bM$\u0018M\u001d;\u0011\u0005}A\u0013BA\u0015\u000e\u0005\rIe\u000e^\u0001\u0004K:$\u0017A\u0002\u001fj]&$h\b\u0006\u0003._A\n\u0004C\u0001\u0018\u0001\u001b\u0005Y\u0001\"\u0002\u000f\u0006\u0001\u0004q\u0002\"\u0002\u0014\u0006\u0001\u00049\u0003\"\u0002\u0016\u0006\u0001\u00049\u0013A\u00027f]\u001e$\b\u000eF\u0001(\u0003\u0019\u0019\u0007.\u0019:BiR\u0011!E\u000e\u0005\u0006o\u001d\u0001\raJ\u0001\u0006S:$W\r_\u0001\fgV\u00147+Z9vK:\u001cW\rF\u0002\u001auqBQa\u000f\u0005A\u0002\u001d\naa\u001d;beR\u0004\u0004\"B\u001f\t\u0001\u00049\u0013\u0001B3oIB\n\u0001\u0002^8TiJLgn\u001a\u000b\u0002\u0001B\u0011!#Q\u0005\u0003\u0005N\u0011aa\u0015;sS:<\u0007"
    )
  ScalaInlineInfo: length = 0x2C (unknown attribute)
   01 01 00 08 00 3A 00 54 01 00 2E 00 2F 01 00 10
   00 11 01 00 16 00 11 01 00 1C 00 1D 01 00 50 00
   51 01 00 49 00 4A 01 00 0B 00 19 01
  ScalaSig: length = 0x3 (unknown attribute)
   05 02 00
