Classfile /Users/mw/Projects/slang-braindump/.jar/jar8/assemble/slang-braindump/assemble/content/scala/runtime/ClassValueCompat$.class
  Last modified May 29, 2022; size 959 bytes
  SHA-256 checksum 0f577937ca8010f7d5183f5e77e230037fd72a938c0d60c71b3fe42d9f56a36a
  Compiled from "ClassValueCompat.scala"
public final class scala.runtime.ClassValueCompat$
  minor version: 0
  major version: 52
  flags: (0x0031) ACC_PUBLIC, ACC_FINAL, ACC_SUPER
  this_class: #2                          // scala/runtime/ClassValueCompat$
  super_class: #4                         // java/lang/Object
  interfaces: 0, fields: 2, methods: 4, attributes: 3
Constant pool:
   #1 = Utf8               scala/runtime/ClassValueCompat$
   #2 = Class              #1             // scala/runtime/ClassValueCompat$
   #3 = Utf8               java/lang/Object
   #4 = Class              #3             // java/lang/Object
   #5 = Utf8               ClassValueCompat.scala
   #6 = Utf8               MODULE$
   #7 = Utf8               Lscala/runtime/ClassValueCompat$;
   #8 = Utf8               scala$runtime$ClassValueCompat$$classValueAvailable
   #9 = Utf8               Z
  #10 = Utf8               <clinit>
  #11 = Utf8               ()V
  #12 = Utf8               <init>
  #13 = NameAndType        #12:#11        // "<init>":()V
  #14 = Methodref          #2.#13         // scala/runtime/ClassValueCompat$."<init>":()V
  #15 = NameAndType        #6:#7          // MODULE$:Lscala/runtime/ClassValueCompat$;
  #16 = Fieldref           #2.#15         // scala/runtime/ClassValueCompat$.MODULE$:Lscala/runtime/ClassValueCompat$;
  #17 = Utf8               liftedTree1$1
  #18 = Utf8               ()Z
  #19 = NameAndType        #17:#18        // liftedTree1$1:()Z
  #20 = Methodref          #2.#19         // scala/runtime/ClassValueCompat$.liftedTree1$1:()Z
  #21 = NameAndType        #8:#9          // scala$runtime$ClassValueCompat$$classValueAvailable:Z
  #22 = Fieldref           #2.#21         // scala/runtime/ClassValueCompat$.scala$runtime$ClassValueCompat$$classValueAvailable:Z
  #23 = Utf8               this
  #24 = Utf8               java/lang/ClassNotFoundException
  #25 = Class              #24            // java/lang/ClassNotFoundException
  #26 = Utf8               java.lang.ClassValue
  #27 = String             #26            // java.lang.ClassValue
  #28 = Utf8               java/lang/Class
  #29 = Class              #28            // java/lang/Class
  #30 = Utf8               getClassLoader
  #31 = Utf8               ()Ljava/lang/ClassLoader;
  #32 = NameAndType        #30:#31        // getClassLoader:()Ljava/lang/ClassLoader;
  #33 = Methodref          #29.#32        // java/lang/Class.getClassLoader:()Ljava/lang/ClassLoader;
  #34 = Utf8               forName
  #35 = Utf8               (Ljava/lang/String;ZLjava/lang/ClassLoader;)Ljava/lang/Class;
  #36 = NameAndType        #34:#35        // forName:(Ljava/lang/String;ZLjava/lang/ClassLoader;)Ljava/lang/Class;
  #37 = Methodref          #29.#36        // java/lang/Class.forName:(Ljava/lang/String;ZLjava/lang/ClassLoader;)Ljava/lang/Class;
  #38 = Methodref          #4.#13         // java/lang/Object."<init>":()V
  #39 = Utf8               Code
  #40 = Utf8               LineNumberTable
  #41 = Utf8               LocalVariableTable
  #42 = Utf8               StackMapTable
  #43 = Utf8               SourceFile
  #44 = Utf8               ScalaInlineInfo
  #45 = Utf8               Scala
{
  public static final scala.runtime.ClassValueCompat$ MODULE$;
    descriptor: Lscala/runtime/ClassValueCompat$;
    flags: (0x0019) ACC_PUBLIC, ACC_STATIC, ACC_FINAL

  private static final boolean scala$runtime$ClassValueCompat$$classValueAvailable;
    descriptor: Z
    flags: (0x001a) ACC_PRIVATE, ACC_STATIC, ACC_FINAL

  public static {};
    descriptor: ()V
    flags: (0x0009) ACC_PUBLIC, ACC_STATIC
    Code:
      stack=2, locals=0, args_size=0
         0: new           #2                  // class scala/runtime/ClassValueCompat$
         3: dup
         4: invokespecial #14                 // Method "<init>":()V
         7: putstatic     #16                 // Field MODULE$:Lscala/runtime/ClassValueCompat$;
        10: invokestatic  #20                 // Method liftedTree1$1:()Z
        13: putstatic     #22                 // Field scala$runtime$ClassValueCompat$$classValueAvailable:Z
        16: return
      LineNumberTable:
        line 40: 0
        line 47: 10
        line 40: 16

  public boolean scala$runtime$ClassValueCompat$$classValueAvailable();
    descriptor: ()Z
    flags: (0x0001) ACC_PUBLIC
    Code:
      stack=1, locals=1, args_size=1
         0: getstatic     #22                 // Field scala$runtime$ClassValueCompat$$classValueAvailable:Z
         3: ireturn
      LineNumberTable:
        line 47: 0
      LocalVariableTable:
        Start  Length  Slot  Name   Signature
            0       4     0  this   Lscala/runtime/ClassValueCompat$;

  private static final boolean liftedTree1$1();
    descriptor: ()Z
    flags: (0x101a) ACC_PRIVATE, ACC_STATIC, ACC_FINAL, ACC_SYNTHETIC
    Code:
      stack=3, locals=0, args_size=0
         0: ldc           #27                 // String java.lang.ClassValue
         2: iconst_0
         3: ldc           #4                  // class java/lang/Object
         5: invokevirtual #33                 // Method java/lang/Class.getClassLoader:()Ljava/lang/ClassLoader;
         8: invokestatic  #37                 // Method java/lang/Class.forName:(Ljava/lang/String;ZLjava/lang/ClassLoader;)Ljava/lang/Class;
        11: pop
        12: iconst_1
        13: ireturn
        14: pop
        15: iconst_0
        16: ireturn
      Exception table:
         from    to  target type
             0    13    14   Class java/lang/ClassNotFoundException
      StackMapTable: number_of_entries = 1
        frame_type = 78 /* same_locals_1_stack_item */
          stack = [ class java/lang/ClassNotFoundException ]
      LineNumberTable:
        line 48: 0
        line 49: 12
        line 51: 15

  private scala.runtime.ClassValueCompat$();
    descriptor: ()V
    flags: (0x0002) ACC_PRIVATE
    Code:
      stack=1, locals=1, args_size=1
         0: aload_0
         1: invokespecial #38                 // Method java/lang/Object."<init>":()V
         4: return
      LineNumberTable:
        line 40: 0
      LocalVariableTable:
        Start  Length  Slot  Name   Signature
            0       5     0  this   Lscala/runtime/ClassValueCompat$;
}
SourceFile: "ClassValueCompat.scala"
  ScalaInlineInfo: length = 0x13 (unknown attribute)
   01 01 00 03 00 0C 00 0B 01 00 11 00 12 01 00 08
   00 12 01
  Scala: length = 0x0 (unknown attribute)

