Classfile /Users/mw/Projects/slang-braindump/.jar/jar8/assemble/slang-braindump/assemble/content/scala/runtime/ClassValueCompat$FallbackClassValue.class
  Last modified May 29, 2022; size 1383 bytes
  SHA-256 checksum f644501fc0cc69e96dd8625bf8877885cd6596df23d175f0aeacffae63a0c94e
  Compiled from "ClassValueCompat.scala"
public class scala.runtime.ClassValueCompat$FallbackClassValue extends java.lang.Object implements scala.runtime.ClassValueCompat$ClassValueInterface<T>
  minor version: 0
  major version: 52
  flags: (0x0021) ACC_PUBLIC, ACC_SUPER
  this_class: #2                          // scala/runtime/ClassValueCompat$FallbackClassValue
  super_class: #5                         // java/lang/Object
  interfaces: 1, fields: 1, methods: 4, attributes: 5
Constant pool:
   #1 = Utf8               scala/runtime/ClassValueCompat$FallbackClassValue
   #2 = Class              #1             // scala/runtime/ClassValueCompat$FallbackClassValue
   #3 = Utf8               Ljava/lang/Object;Lscala/runtime/ClassValueCompat$ClassValueInterface<TT;>;
   #4 = Utf8               java/lang/Object
   #5 = Class              #4             // java/lang/Object
   #6 = Utf8               scala/runtime/ClassValueCompat$ClassValueInterface
   #7 = Class              #6             // scala/runtime/ClassValueCompat$ClassValueInterface
   #8 = Utf8               ClassValueCompat.scala
   #9 = Utf8               scala/runtime/ClassValueCompat
  #10 = Class              #9             // scala/runtime/ClassValueCompat
  #11 = Utf8               ClassValueInterface
  #12 = Utf8               FallbackClassValue
  #13 = Utf8               $outer
  #14 = Utf8               Lscala/runtime/ClassValueCompat;
  #15 = Utf8               get
  #16 = Utf8               (Ljava/lang/Class;)Ljava/lang/Object;
  #17 = Utf8               (Ljava/lang/Class<*>;)TT;
  #18 = Utf8               cls
  #19 = Utf8               scala$runtime$ClassValueCompat$FallbackClassValue$$$outer
  #20 = Utf8               ()Lscala/runtime/ClassValueCompat;
  #21 = NameAndType        #19:#20        // scala$runtime$ClassValueCompat$FallbackClassValue$$$outer:()Lscala/runtime/ClassValueCompat;
  #22 = Methodref          #2.#21         // scala/runtime/ClassValueCompat$FallbackClassValue.scala$runtime$ClassValueCompat$FallbackClassValue$$$outer:()Lscala/runtime/ClassValueCompat;
  #23 = Utf8               computeValue
  #24 = NameAndType        #23:#16        // computeValue:(Ljava/lang/Class;)Ljava/lang/Object;
  #25 = Methodref          #10.#24        // scala/runtime/ClassValueCompat.computeValue:(Ljava/lang/Class;)Ljava/lang/Object;
  #26 = Utf8               this
  #27 = Utf8               Lscala/runtime/ClassValueCompat$FallbackClassValue;
  #28 = Utf8               Ljava/lang/Class;
  #29 = Utf8               remove
  #30 = Utf8               (Ljava/lang/Class;)V
  #31 = Utf8               (Ljava/lang/Class<*>;)V
  #32 = NameAndType        #13:#14        // $outer:Lscala/runtime/ClassValueCompat;
  #33 = Fieldref           #2.#32         // scala/runtime/ClassValueCompat$FallbackClassValue.$outer:Lscala/runtime/ClassValueCompat;
  #34 = Utf8               <init>
  #35 = Utf8               (Lscala/runtime/ClassValueCompat;)V
  #36 = Utf8               ()V
  #37 = NameAndType        #34:#36        // "<init>":()V
  #38 = Methodref          #5.#37         // java/lang/Object."<init>":()V
  #39 = Utf8               Code
  #40 = Utf8               LineNumberTable
  #41 = Utf8               LocalVariableTable
  #42 = Utf8               Signature
  #43 = Utf8               MethodParameters
  #44 = Utf8               StackMapTable
  #45 = Utf8               InnerClasses
  #46 = Utf8               SourceFile
  #47 = Utf8               ScalaInlineInfo
  #48 = Utf8               Scala
{
  public final scala.runtime.ClassValueCompat $outer;
    descriptor: Lscala/runtime/ClassValueCompat;
    flags: (0x1011) ACC_PUBLIC, ACC_FINAL, ACC_SYNTHETIC

  public T get(java.lang.Class<?>);
    descriptor: (Ljava/lang/Class;)Ljava/lang/Object;
    flags: (0x0001) ACC_PUBLIC
    Code:
      stack=2, locals=2, args_size=2
         0: aload_0
         1: invokevirtual #22                 // Method scala$runtime$ClassValueCompat$FallbackClassValue$$$outer:()Lscala/runtime/ClassValueCompat;
         4: aload_1
         5: invokevirtual #25                 // Method scala/runtime/ClassValueCompat.computeValue:(Ljava/lang/Class;)Ljava/lang/Object;
         8: areturn
      LineNumberTable:
        line 28: 0
      LocalVariableTable:
        Start  Length  Slot  Name   Signature
            0       9     0  this   Lscala/runtime/ClassValueCompat$FallbackClassValue;
            0       9     1   cls   Ljava/lang/Class;
    Signature: #17                          // (Ljava/lang/Class<*>;)TT;
    MethodParameters:
      Name                           Flags
      cls                            final

  public void remove(java.lang.Class<?>);
    descriptor: (Ljava/lang/Class;)V
    flags: (0x0001) ACC_PUBLIC
    Code:
      stack=0, locals=2, args_size=2
         0: return
      LineNumberTable:
        line 30: 0
      LocalVariableTable:
        Start  Length  Slot  Name   Signature
            0       1     0  this   Lscala/runtime/ClassValueCompat$FallbackClassValue;
            0       1     1   cls   Ljava/lang/Class;
    Signature: #31                          // (Ljava/lang/Class<*>;)V
    MethodParameters:
      Name                           Flags
      cls                            final

  public scala.runtime.ClassValueCompat scala$runtime$ClassValueCompat$FallbackClassValue$$$outer();
    descriptor: ()Lscala/runtime/ClassValueCompat;
    flags: (0x1001) ACC_PUBLIC, ACC_SYNTHETIC
    Code:
      stack=1, locals=1, args_size=1
         0: aload_0
         1: getfield      #33                 // Field $outer:Lscala/runtime/ClassValueCompat;
         4: areturn
      LineNumberTable:
        line 27: 0
      LocalVariableTable:
        Start  Length  Slot  Name   Signature
            0       5     0  this   Lscala/runtime/ClassValueCompat$FallbackClassValue;

  public scala.runtime.ClassValueCompat$FallbackClassValue(scala.runtime.ClassValueCompat);
    descriptor: (Lscala/runtime/ClassValueCompat;)V
    flags: (0x0001) ACC_PUBLIC
    Code:
      stack=2, locals=2, args_size=2
         0: aload_1
         1: ifnonnull     6
         4: aconst_null
         5: athrow
         6: aload_0
         7: aload_1
         8: putfield      #33                 // Field $outer:Lscala/runtime/ClassValueCompat;
        11: aload_0
        12: invokespecial #38                 // Method java/lang/Object."<init>":()V
        15: return
      StackMapTable: number_of_entries = 1
        frame_type = 6 /* same */
      LineNumberTable:
        line 27: 0
      LocalVariableTable:
        Start  Length  Slot  Name   Signature
            0      16     0  this   Lscala/runtime/ClassValueCompat$FallbackClassValue;
            0      16     1 $outer   Lscala/runtime/ClassValueCompat;
    MethodParameters:
      Name                           Flags
      $outer                         final synthetic
}
InnerClasses:
  public static #11= #7 of #10;           // ClassValueInterface=class scala/runtime/ClassValueCompat$ClassValueInterface of class scala/runtime/ClassValueCompat
  private #12= #2 of #10;                 // FallbackClassValue=class scala/runtime/ClassValueCompat$FallbackClassValue of class scala/runtime/ClassValueCompat
Signature: #3                           // Ljava/lang/Object;Lscala/runtime/ClassValueCompat$ClassValueInterface<TT;>;
SourceFile: "ClassValueCompat.scala"
  ScalaInlineInfo: length = 0x18 (unknown attribute)
   01 00 00 04 00 22 00 23 00 00 0F 00 10 00 00 1D
   00 1E 00 00 13 00 14 00
  Scala: length = 0x0 (unknown attribute)

