Classfile /Users/mw/Projects/slang-braindump/.jar/jar8/assemble/slang-braindump/assemble/content/scala/runtime/ClassValueCompat.class
  Last modified May 29, 2022; size 3162 bytes
  SHA-256 checksum 5d578d3d6a45da4360dac716441c3b50984403510d72e98b009638f3a1e864c6
  Compiled from "ClassValueCompat.scala"
public abstract class scala.runtime.ClassValueCompat<T extends java.lang.Object> extends java.lang.Object implements scala.runtime.ClassValueCompat$ClassValueInterface<T>
  minor version: 0
  major version: 52
  flags: (0x0421) ACC_PUBLIC, ACC_SUPER, ACC_ABSTRACT
  this_class: #2                          // scala/runtime/ClassValueCompat
  super_class: #5                         // java/lang/Object
  interfaces: 1, fields: 1, methods: 5, attributes: 6
Constant pool:
   #1 = Utf8               scala/runtime/ClassValueCompat
   #2 = Class              #1             // scala/runtime/ClassValueCompat
   #3 = Utf8               <T:Ljava/lang/Object;>Ljava/lang/Object;Lscala/runtime/ClassValueCompat$ClassValueInterface<TT;>;
   #4 = Utf8               java/lang/Object
   #5 = Class              #4             // java/lang/Object
   #6 = Utf8               scala/runtime/ClassValueCompat$ClassValueInterface
   #7 = Class              #6             // scala/runtime/ClassValueCompat$ClassValueInterface
   #8 = Utf8               ClassValueCompat.scala
   #9 = Utf8               Lscala/reflect/ScalaSignature;
  #10 = Utf8               bytes
  #11 = Utf8               \u0006\u0005\u0005\u001dcA\u0002\f\u0018\u0003\u0003I2\u0004C\u00030\u0001\u0011\u0005!\rC\u0004e\u0001\t\u0007I\u0011B3\t\r\u0019\u0004\u0001\u0015!\u0003\"\r\u00119\u0007\u0001\u00025\t\u000b=\"A\u0011A9\t\u000bQ$A\u0011I;\u0007\tq\u0004A! \u0005\u0006_\u001d!\tA \u0005\u0007i\u001d!\t%!\u0001\t\r=;A\u0011IA\b\u0011\u0019!\u0004\u0001\"\u0001\u0002\u001e!1q\n\u0001C\u0001\u0003WAa\u0001\u001e\u0001\u0007\u0012\u0005erAB\u0016\u0018\u0011\u0003IBF\u0002\u0004\u0017/!\u0005\u0011D\f\u0005\u0006_=!\t\u0001\r\u0004\bc=\u0001\n1%\u00013\u0011\u0015!\u0014C\"\u00016\u0011\u0015y\u0015C\"\u0001Q\u0011\u001dQvB1A\u0005\nmCaaX\b!\u0002\u0013a&\u0001E\"mCN\u001ch+\u00197vK\u000e{W\u000e]1u\u0015\tA\u0012$A\u0004sk:$\u0018.\\3\u000b\u0003i\tQa]2bY\u0006,\"\u0001H1\u0014\u0007\u0001i\u0012\u0005\u0005\u0002\u001f?5\t\u0011$\u0003\u0002!3\t1\u0011I\\=SK\u001a\u00042AI\ta\u001d\t\u0019cB\u0004\u0002%U9\u0011Q%K\u0007\u0002M)\u0011q\u0005K\u0001\u0007yI|w\u000e\u001e \u0004\u0001%\t!$\u0003\u0002\u00193\u0005\u00012\t\\1tgZ\u000bG.^3D_6\u0004\u0018\r\u001e\t\u0003[=i\u0011aF\n\u0003\u001fu\ta\u0001P5oSRtD#\u0001\u0017\u0003\'\rc\u0017m]:WC2,X-\u00138uKJ4\u0017mY3\u0016\u0005MB4CA\t\u001e\u0003\r9W\r\u001e\u000b\u0003m\u0005\u0003\"a\u000e\u001d\r\u0001\u0011)\u0011(\u0005b\u0001u\t\tA+\u0005\u0002<}A\u0011a\u0004P\u0005\u0003{e\u0011qAT8uQ&tw\r\u0005\u0002\u001f\u007f%\u0011\u0001)\u0007\u0002\u0004\u0003:L\b\"\u0002\"\u0013\u0001\u0004\u0019\u0015aA2mgB\u0012A)\u0014\t\u0004\u000b&ceB\u0001$H!\t)\u0013$\u0003\u0002I3\u00051\u0001K]3eK\u001aL!AS&\u0003\u000b\rc\u0017m]:\u000b\u0005!K\u0002CA\u001cN\t%q\u0015)!A\u0001\u0002\u000b\u0005!HA\u0002`I]\naA]3n_Z,GCA)U!\tq\"+\u0003\u0002T3\t!QK\\5u\u0011\u0015\u00115\u00031\u0001Va\t1\u0006\fE\u0002F\u0013^\u0003\"a\u000e-\u0005\u0013e#\u0016\u0011!A\u0001\u0006\u0003Q$aA0%q\u0005\u00192\r\\1tgZ\u000bG.^3Bm\u0006LG.\u00192mKV\tA\f\u0005\u0002\u001f;&\u0011a,\u0007\u0002\b\u0005>|G.Z1o\u0003Q\u0019G.Y:t-\u0006dW/Z!wC&d\u0017M\u00197fAA\u0011q\'\u0019\u0003\u0006s\u0001\u0011\rA\u000f\u000b\u0002GB\u0019Q\u0006\u00011\u0002\u0011%t7\u000f^1oG\u0016,\u0012!I\u0001\nS:\u001cH/\u00198dK\u0002\u0012aBS1wC\u000ec\u0017m]:WC2,XmE\u0002\u0005S\u0006\u00022A[8a\u001b\u0005Y\'B\u00017n\u0003\u0011a\u0017M\\4\u000b\u00039\fAA[1wC&\u0011\u0001o\u001b\u0002\u000b\u00072\f7o\u001d,bYV,G#\u0001:\u0011\u0005M$Q\"\u0001\u0001\u0002\u0019\r|W\u000e];uKZ\u000bG.^3\u0015\u0005\u00014\b\"\u0002\"\u0007\u0001\u00049\bG\u0001={!\r)\u0015*\u001f\t\u0003oi$\u0011b\u001f<\u0002\u0002\u0003\u0005)\u0011\u0001\u001e\u0003\u0007}#\u0013G\u0001\nGC2d\'-Y2l\u00072\f7o\u001d,bYV,7cA\u0004\u001eCQ\tq\u0010\u0005\u0002t\u000fQ\u0019\u0001-a\u0001\t\r\tK\u0001\u0019AA\u0003a\u0011\t9!a\u0003\u0011\t\u0015K\u0015\u0011\u0002\t\u0004o\u0005-AaCA\u0007\u0003\u0007\t\t\u0011!A\u0003\u0002i\u00121a\u0018\u00133)\r\t\u0016\u0011\u0003\u0005\u0007\u0005*\u0001\r!a\u00051\t\u0005U\u0011\u0011\u0004\t\u0005\u000b&\u000b9\u0002E\u00028\u00033!1\"a\u0007\u0002\u0012\u0005\u0005\t\u0011!B\u0001u\t\u0019q\fJ\u001a\u0015\u0007\u0001\fy\u0002\u0003\u0004C\u0017\u0001\u0007\u0011\u0011\u0005\u0019\u0005\u0003G\t9\u0003\u0005\u0003F\u0013\u0006\u0015\u0002cA\u001c\u0002(\u0011Y\u0011\u0011FA\u0010\u0003\u0003\u0005\tQ!\u0001;\u0005\ryF\u0005\u000e\u000b\u0004#\u00065\u0002B\u0002\"\r\u0001\u0004\ty\u0003\r\u0003\u00022\u0005U\u0002\u0003B#J\u0003g\u00012aNA\u001b\t-\t9$!\f\u0002\u0002\u0003\u0005)\u0011\u0001\u001e\u0003\u0007}#S\u0007F\u0002a\u0003wAaAQ\u0007A\u0002\u0005u\u0002\u0007BA \u0003\u0007\u0002B!R%\u0002BA\u0019q\'a\u0011\u0005\u0017\u0005\u0015\u00131HA\u0001\u0002\u0003\u0015\tA\u000f\u0002\u0004?\u00122\u0004
  #12 = Utf8               ClassValueInterface
  #13 = Utf8               scala/runtime/ClassValueCompat$FallbackClassValue
  #14 = Class              #13            // scala/runtime/ClassValueCompat$FallbackClassValue
  #15 = Utf8               FallbackClassValue
  #16 = Utf8               scala/runtime/ClassValueCompat$JavaClassValue
  #17 = Class              #16            // scala/runtime/ClassValueCompat$JavaClassValue
  #18 = Utf8               JavaClassValue
  #19 = Utf8               instance
  #20 = Utf8               Lscala/runtime/ClassValueCompat$ClassValueInterface;
  #21 = Utf8               Lscala/runtime/ClassValueCompat$ClassValueInterface<TT;>;
  #22 = Utf8               ()Lscala/runtime/ClassValueCompat$ClassValueInterface;
  #23 = Utf8               ()Lscala/runtime/ClassValueCompat$ClassValueInterface<TT;>;
  #24 = NameAndType        #19:#20        // instance:Lscala/runtime/ClassValueCompat$ClassValueInterface;
  #25 = Fieldref           #2.#24         // scala/runtime/ClassValueCompat.instance:Lscala/runtime/ClassValueCompat$ClassValueInterface;
  #26 = Utf8               this
  #27 = Utf8               Lscala/runtime/ClassValueCompat;
  #28 = Utf8               get
  #29 = Utf8               (Ljava/lang/Class;)Ljava/lang/Object;
  #30 = Utf8               (Ljava/lang/Class<*>;)TT;
  #31 = Utf8               cls
  #32 = NameAndType        #19:#22        // instance:()Lscala/runtime/ClassValueCompat$ClassValueInterface;
  #33 = Methodref          #2.#32         // scala/runtime/ClassValueCompat.instance:()Lscala/runtime/ClassValueCompat$ClassValueInterface;
  #34 = NameAndType        #28:#29        // get:(Ljava/lang/Class;)Ljava/lang/Object;
  #35 = InterfaceMethodref #7.#34         // scala/runtime/ClassValueCompat$ClassValueInterface.get:(Ljava/lang/Class;)Ljava/lang/Object;
  #36 = Utf8               Ljava/lang/Class;
  #37 = Utf8               remove
  #38 = Utf8               (Ljava/lang/Class;)V
  #39 = Utf8               (Ljava/lang/Class<*>;)V
  #40 = NameAndType        #37:#38        // remove:(Ljava/lang/Class;)V
  #41 = InterfaceMethodref #7.#40         // scala/runtime/ClassValueCompat$ClassValueInterface.remove:(Ljava/lang/Class;)V
  #42 = Utf8               computeValue
  #43 = Utf8               <init>
  #44 = Utf8               ()V
  #45 = NameAndType        #43:#44        // "<init>":()V
  #46 = Methodref          #5.#45         // java/lang/Object."<init>":()V
  #47 = Utf8               scala/runtime/ClassValueCompat$
  #48 = Class              #47            // scala/runtime/ClassValueCompat$
  #49 = Utf8               MODULE$
  #50 = Utf8               Lscala/runtime/ClassValueCompat$;
  #51 = NameAndType        #49:#50        // MODULE$:Lscala/runtime/ClassValueCompat$;
  #52 = Fieldref           #48.#51        // scala/runtime/ClassValueCompat$.MODULE$:Lscala/runtime/ClassValueCompat$;
  #53 = Utf8               scala$runtime$ClassValueCompat$$classValueAvailable
  #54 = Utf8               ()Z
  #55 = NameAndType        #53:#54        // scala$runtime$ClassValueCompat$$classValueAvailable:()Z
  #56 = Methodref          #48.#55        // scala/runtime/ClassValueCompat$.scala$runtime$ClassValueCompat$$classValueAvailable:()Z
  #57 = Utf8               (Lscala/runtime/ClassValueCompat;)V
  #58 = NameAndType        #43:#57        // "<init>":(Lscala/runtime/ClassValueCompat;)V
  #59 = Methodref          #17.#58        // scala/runtime/ClassValueCompat$JavaClassValue."<init>":(Lscala/runtime/ClassValueCompat;)V
  #60 = Methodref          #14.#58        // scala/runtime/ClassValueCompat$FallbackClassValue."<init>":(Lscala/runtime/ClassValueCompat;)V
  #61 = Utf8               Signature
  #62 = Utf8               Code
  #63 = Utf8               LineNumberTable
  #64 = Utf8               LocalVariableTable
  #65 = Utf8               MethodParameters
  #66 = Utf8               StackMapTable
  #67 = Utf8               InnerClasses
  #68 = Utf8               SourceFile
  #69 = Utf8               RuntimeVisibleAnnotations
  #70 = Utf8               ScalaInlineInfo
  #71 = Utf8               ScalaSig
{
  private final scala.runtime.ClassValueCompat$ClassValueInterface<T> instance;
    descriptor: Lscala/runtime/ClassValueCompat$ClassValueInterface;
    flags: (0x0012) ACC_PRIVATE, ACC_FINAL
    Signature: #21                          // Lscala/runtime/ClassValueCompat$ClassValueInterface<TT;>;

  private scala.runtime.ClassValueCompat$ClassValueInterface<T> instance();
    descriptor: ()Lscala/runtime/ClassValueCompat$ClassValueInterface;
    flags: (0x0002) ACC_PRIVATE
    Code:
      stack=1, locals=1, args_size=1
         0: aload_0
         1: getfield      #25                 // Field instance:Lscala/runtime/ClassValueCompat$ClassValueInterface;
         4: areturn
      LineNumberTable:
        line 19: 0
      LocalVariableTable:
        Start  Length  Slot  Name   Signature
            0       5     0  this   Lscala/runtime/ClassValueCompat;
    Signature: #23                          // ()Lscala/runtime/ClassValueCompat$ClassValueInterface<TT;>;

  public T get(java.lang.Class<?>);
    descriptor: (Ljava/lang/Class;)Ljava/lang/Object;
    flags: (0x0001) ACC_PUBLIC
    Code:
      stack=2, locals=2, args_size=2
         0: aload_0
         1: invokespecial #33                 // Method instance:()Lscala/runtime/ClassValueCompat$ClassValueInterface;
         4: aload_1
         5: invokeinterface #35,  2           // InterfaceMethod scala/runtime/ClassValueCompat$ClassValueInterface.get:(Ljava/lang/Class;)Ljava/lang/Object;
        10: areturn
      LineNumberTable:
        line 33: 0
      LocalVariableTable:
        Start  Length  Slot  Name   Signature
            0      11     0  this   Lscala/runtime/ClassValueCompat;
            0      11     1   cls   Ljava/lang/Class;
    Signature: #30                          // (Ljava/lang/Class<*>;)TT;
    MethodParameters:
      Name                           Flags
      cls                            final

  public void remove(java.lang.Class<?>);
    descriptor: (Ljava/lang/Class;)V
    flags: (0x0001) ACC_PUBLIC
    Code:
      stack=2, locals=2, args_size=2
         0: aload_0
         1: invokespecial #33                 // Method instance:()Lscala/runtime/ClassValueCompat$ClassValueInterface;
         4: aload_1
         5: invokeinterface #41,  2           // InterfaceMethod scala/runtime/ClassValueCompat$ClassValueInterface.remove:(Ljava/lang/Class;)V
        10: return
      LineNumberTable:
        line 35: 0
      LocalVariableTable:
        Start  Length  Slot  Name   Signature
            0      11     0  this   Lscala/runtime/ClassValueCompat;
            0      11     1   cls   Ljava/lang/Class;
    Signature: #39                          // (Ljava/lang/Class<*>;)V
    MethodParameters:
      Name                           Flags
      cls                            final

  public abstract T computeValue(java.lang.Class<?>);
    descriptor: (Ljava/lang/Class;)Ljava/lang/Object;
    flags: (0x0401) ACC_PUBLIC, ACC_ABSTRACT
    Signature: #30                          // (Ljava/lang/Class<*>;)TT;
    MethodParameters:
      Name                           Flags
      cls                            final

  public scala.runtime.ClassValueCompat();
    descriptor: ()V
    flags: (0x0001) ACC_PUBLIC
    Code:
      stack=4, locals=1, args_size=1
         0: aload_0
         1: invokespecial #46                 // Method java/lang/Object."<init>":()V
         4: aload_0
         5: getstatic     #52                 // Field scala/runtime/ClassValueCompat$.MODULE$:Lscala/runtime/ClassValueCompat$;
         8: invokevirtual #56                 // Method scala/runtime/ClassValueCompat$.scala$runtime$ClassValueCompat$$classValueAvailable:()Z
        11: ifeq          25
        14: new           #17                 // class scala/runtime/ClassValueCompat$JavaClassValue
        17: dup
        18: aload_0
        19: invokespecial #59                 // Method scala/runtime/ClassValueCompat$JavaClassValue."<init>":(Lscala/runtime/ClassValueCompat;)V
        22: goto          33
        25: new           #14                 // class scala/runtime/ClassValueCompat$FallbackClassValue
        28: dup
        29: aload_0
        30: invokespecial #60                 // Method scala/runtime/ClassValueCompat$FallbackClassValue."<init>":(Lscala/runtime/ClassValueCompat;)V
        33: putfield      #25                 // Field instance:Lscala/runtime/ClassValueCompat$ClassValueInterface;
        36: return
      StackMapTable: number_of_entries = 2
        frame_type = 255 /* full_frame */
          offset_delta = 25
          locals = [ class scala/runtime/ClassValueCompat ]
          stack = [ class scala/runtime/ClassValueCompat ]
        frame_type = 255 /* full_frame */
          offset_delta = 7
          locals = [ class scala/runtime/ClassValueCompat ]
          stack = [ class scala/runtime/ClassValueCompat, class java/lang/Object ]
      LineNumberTable:
        line 18: 0
        line 19: 4
        line 20: 5
        line 21: 25
        line 19: 33
        line 18: 36
      LocalVariableTable:
        Start  Length  Slot  Name   Signature
            0      37     0  this   Lscala/runtime/ClassValueCompat;
}
InnerClasses:
  public static #12= #7 of #2;            // ClassValueInterface=class scala/runtime/ClassValueCompat$ClassValueInterface of class scala/runtime/ClassValueCompat
  private #15= #14 of #2;                 // FallbackClassValue=class scala/runtime/ClassValueCompat$FallbackClassValue of class scala/runtime/ClassValueCompat
  private #18= #17 of #2;                 // JavaClassValue=class scala/runtime/ClassValueCompat$JavaClassValue of class scala/runtime/ClassValueCompat
Signature: #3                           // <T:Ljava/lang/Object;>Ljava/lang/Object;Lscala/runtime/ClassValueCompat$ClassValueInterface<TT;>;
SourceFile: "ClassValueCompat.scala"
RuntimeVisibleAnnotations:
  0: #9(#10=s#11)
    scala.reflect.ScalaSignature(
      bytes="\u0006\u0005\u0005\u001dcA\u0002\f\u0018\u0003\u0003I2\u0004C\u00030\u0001\u0011\u0005!\rC\u0004e\u0001\t\u0007I\u0011B3\t\r\u0019\u0004\u0001\u0015!\u0003\"\r\u00119\u0007\u0001\u00025\t\u000b=\"A\u0011A9\t\u000bQ$A\u0011I;\u0007\tq\u0004A! \u0005\u0006_\u001d!\tA \u0005\u0007i\u001d!\t%!\u0001\t\r=;A\u0011IA\b\u0011\u0019!\u0004\u0001\"\u0001\u0002\u001e!1q\n\u0001C\u0001\u0003WAa\u0001\u001e\u0001\u0007\u0012\u0005erAB\u0016\u0018\u0011\u0003IBF\u0002\u0004\u0017/!\u0005\u0011D\f\u0005\u0006_=!\t\u0001\r\u0004\bc=\u0001\n1%\u00013\u0011\u0015!\u0014C\"\u00016\u0011\u0015y\u0015C\"\u0001Q\u0011\u001dQvB1A\u0005\nmCaaX\b!\u0002\u0013a&\u0001E\"mCN\u001ch+\u00197vK\u000e{W\u000e]1u\u0015\tA\u0012$A\u0004sk:$\u0018.\\3\u000b\u0003i\tQa]2bY\u0006,\"\u0001H1\u0014\u0007\u0001i\u0012\u0005\u0005\u0002\u001f?5\t\u0011$\u0003\u0002!3\t1\u0011I\\=SK\u001a\u00042AI\ta\u001d\t\u0019cB\u0004\u0002%U9\u0011Q%K\u0007\u0002M)\u0011q\u0005K\u0001\u0007yI|w\u000e\u001e \u0004\u0001%\t!$\u0003\u0002\u00193\u0005\u00012\t\\1tgZ\u000bG.^3D_6\u0004\u0018\r\u001e\t\u0003[=i\u0011aF\n\u0003\u001fu\ta\u0001P5oSRtD#\u0001\u0017\u0003\'\rc\u0017m]:WC2,X-\u00138uKJ4\u0017mY3\u0016\u0005MB4CA\t\u001e\u0003\r9W\r\u001e\u000b\u0003m\u0005\u0003\"a\u000e\u001d\r\u0001\u0011)\u0011(\u0005b\u0001u\t\tA+\u0005\u0002<}A\u0011a\u0004P\u0005\u0003{e\u0011qAT8uQ&tw\r\u0005\u0002\u001f\u007f%\u0011\u0001)\u0007\u0002\u0004\u0003:L\b\"\u0002\"\u0013\u0001\u0004\u0019\u0015aA2mgB\u0012A)\u0014\t\u0004\u000b&ceB\u0001$H!\t)\u0013$\u0003\u0002I3\u00051\u0001K]3eK\u001aL!AS&\u0003\u000b\rc\u0017m]:\u000b\u0005!K\u0002CA\u001cN\t%q\u0015)!A\u0001\u0002\u000b\u0005!HA\u0002`I]\naA]3n_Z,GCA)U!\tq\"+\u0003\u0002T3\t!QK\\5u\u0011\u0015\u00115\u00031\u0001Va\t1\u0006\fE\u0002F\u0013^\u0003\"a\u000e-\u0005\u0013e#\u0016\u0011!A\u0001\u0006\u0003Q$aA0%q\u0005\u00192\r\\1tgZ\u000bG.^3Bm\u0006LG.\u00192mKV\tA\f\u0005\u0002\u001f;&\u0011a,\u0007\u0002\b\u0005>|G.Z1o\u0003Q\u0019G.Y:t-\u0006dW/Z!wC&d\u0017M\u00197fAA\u0011q\'\u0019\u0003\u0006s\u0001\u0011\rA\u000f\u000b\u0002GB\u0019Q\u0006\u00011\u0002\u0011%t7\u000f^1oG\u0016,\u0012!I\u0001\nS:\u001cH/\u00198dK\u0002\u0012aBS1wC\u000ec\u0017m]:WC2,XmE\u0002\u0005S\u0006\u00022A[8a\u001b\u0005Y\'B\u00017n\u0003\u0011a\u0017M\\4\u000b\u00039\fAA[1wC&\u0011\u0001o\u001b\u0002\u000b\u00072\f7o\u001d,bYV,G#\u0001:\u0011\u0005M$Q\"\u0001\u0001\u0002\u0019\r|W\u000e];uKZ\u000bG.^3\u0015\u0005\u00014\b\"\u0002\"\u0007\u0001\u00049\bG\u0001={!\r)\u0015*\u001f\t\u0003oi$\u0011b\u001f<\u0002\u0002\u0003\u0005)\u0011\u0001\u001e\u0003\u0007}#\u0013G\u0001\nGC2d\'-Y2l\u00072\f7o\u001d,bYV,7cA\u0004\u001eCQ\tq\u0010\u0005\u0002t\u000fQ\u0019\u0001-a\u0001\t\r\tK\u0001\u0019AA\u0003a\u0011\t9!a\u0003\u0011\t\u0015K\u0015\u0011\u0002\t\u0004o\u0005-AaCA\u0007\u0003\u0007\t\t\u0011!A\u0003\u0002i\u00121a\u0018\u00133)\r\t\u0016\u0011\u0003\u0005\u0007\u0005*\u0001\r!a\u00051\t\u0005U\u0011\u0011\u0004\t\u0005\u000b&\u000b9\u0002E\u00028\u00033!1\"a\u0007\u0002\u0012\u0005\u0005\t\u0011!B\u0001u\t\u0019q\fJ\u001a\u0015\u0007\u0001\fy\u0002\u0003\u0004C\u0017\u0001\u0007\u0011\u0011\u0005\u0019\u0005\u0003G\t9\u0003\u0005\u0003F\u0013\u0006\u0015\u0002cA\u001c\u0002(\u0011Y\u0011\u0011FA\u0010\u0003\u0003\u0005\tQ!\u0001;\u0005\ryF\u0005\u000e\u000b\u0004#\u00065\u0002B\u0002\"\r\u0001\u0004\ty\u0003\r\u0003\u00022\u0005U\u0002\u0003B#J\u0003g\u00012aNA\u001b\t-\t9$!\f\u0002\u0002\u0003\u0005)\u0011\u0001\u001e\u0003\u0007}#S\u0007F\u0002a\u0003wAaAQ\u0007A\u0002\u0005u\u0002\u0007BA \u0003\u0007\u0002B!R%\u0002BA\u0019q\'a\u0011\u0005\u0017\u0005\u0015\u00131HA\u0001\u0002\u0003\u0015\tA\u000f\u0002\u0004?\u00122\u0004"
    )
  ScalaInlineInfo: length = 0x1D (unknown attribute)
   01 00 00 05 00 2B 00 2C 00 00 2A 00 1D 00 00 1C
   00 1D 00 00 13 00 16 01 00 25 00 26 00
  ScalaSig: length = 0x3 (unknown attribute)
   05 02 00
