Classfile /Users/mw/Projects/slang-braindump/.jar/jar8/assemble/slang-braindump/assemble/content/scala/runtime/LazyRef.class
  Last modified May 29, 2022; size 2056 bytes
  SHA-256 checksum 59109f97b00c381fea6267e7ba51671e21c859cab59a7019e241ae27c0fa28aa
  Compiled from "LazyRef.scala"
public class scala.runtime.LazyRef<T extends java.lang.Object> extends java.lang.Object implements java.io.Serializable
  minor version: 0
  major version: 52
  flags: (0x0021) ACC_PUBLIC, ACC_SUPER
  this_class: #2                          // scala/runtime/LazyRef
  super_class: #5                         // java/lang/Object
  interfaces: 1, fields: 3, methods: 5, attributes: 5
Constant pool:
   #1 = Utf8               scala/runtime/LazyRef
   #2 = Class              #1             // scala/runtime/LazyRef
   #3 = Utf8               <T:Ljava/lang/Object;>Ljava/lang/Object;Ljava/io/Serializable;
   #4 = Utf8               java/lang/Object
   #5 = Class              #4             // java/lang/Object
   #6 = Utf8               java/io/Serializable
   #7 = Class              #6             // java/io/Serializable
   #8 = Utf8               LazyRef.scala
   #9 = Utf8               Lscala/reflect/ScalaSignature;
  #10 = Utf8               bytes
  #11 = Utf8               \u0006\u000593A\u0001C\u0005\u0001\u001d!)\u0001\u0005\u0001C\u0001C!Iq\u0006\u0001a\u0001\u0002\u0003\u0006K\u0001\r\u0005\u0006o\u0001!\t\u0001\u000f\u0005\ns\u0001\u0001\r\u0011!Q!\n\u0011BQA\u000f\u0001\u0005\u0002mBQ\u0001\u0010\u0001\u0005\u0002uBQa\u0010\u0001\u0005B\u0001\u0013q\u0001T1{sJ+gM\u0003\u0002\u000b\u0017\u00059!/\u001e8uS6,\'\"\u0001\u0007\u0002\u000bM\u001c\u0017\r\\1\u0004\u0001U\u0011qBJ\n\u0004\u0001A!\u0002CA\t\u0013\u001b\u0005Y\u0011BA\n\f\u0005\u0019\te.\u001f*fMB\u0011Q#\b\b\u0003-mq!a\u0006\u000e\u000e\u0003aQ!!G\u0007\u0002\rq\u0012xn\u001c;?\u0013\u0005a\u0011B\u0001\u000f\f\u0003\u001d\u0001\u0018mY6bO\u0016L!AH\u0010\u0003\u0019M+\'/[1mSj\f\'\r\\3\u000b\u0005qY\u0011A\u0002\u001fj]&$h\bF\u0001#!\r\u0019\u0003\u0001J\u0007\u0002\u0013A\u0011QE\n\u0007\u0001\t\u00159\u0003A1\u0001)\u0005\u0005!\u0016CA\u0015-!\t\t\"&\u0003\u0002,\u0017\t9aj\u001c;iS:<\u0007CA\t.\u0013\tq3BA\u0002B]f\fAbX5oSRL\u0017\r\\5{K\u0012\u0004\"!E\u0019\n\u0005IZ!a\u0002\"p_2,\u0017M\u001c\u0015\u0003\u0005Q\u0002\"!E\u001b\n\u0005YZ!\u0001\u0003<pY\u0006$\u0018\u000e\\3\u0002\u0017%t\u0017\u000e^5bY&TX\rZ\u000b\u0002a\u00051qL^1mk\u0016\fQA^1mk\u0016,\u0012\u0001J\u0001\u000bS:LG/[1mSj,GC\u0001\u0013?\u0011\u0015Qd\u00011\u0001%\u0003!!xn\u0015;sS:<G#A!\u0011\u0005\t3eBA\"E!\t92\"\u0003\u0002F\u0017\u00051\u0001K]3eK\u001aL!a\u0012%\u0003\rM#(/\u001b8h\u0015\t)5\u0002\u000b\u0003\u0001\u0015jj\u0005CA\tL\u0013\ta5B\u0001\tTKJL\u0017\r\u001c,feNLwN\\+J\tz\t\u0011\u0001
  #12 = Utf8               serialVersionUID
  #13 = Utf8               J
  #14 = Long               1l
  #16 = Utf8               _initialized
  #17 = Utf8               Z
  #18 = Utf8               _value
  #19 = Utf8               Ljava/lang/Object;
  #20 = Utf8               TT;
  #21 = Utf8               initialized
  #22 = Utf8               ()Z
  #23 = NameAndType        #16:#17        // _initialized:Z
  #24 = Fieldref           #2.#23         // scala/runtime/LazyRef._initialized:Z
  #25 = Utf8               this
  #26 = Utf8               Lscala/runtime/LazyRef;
  #27 = Utf8               value
  #28 = Utf8               ()Ljava/lang/Object;
  #29 = Utf8               ()TT;
  #30 = NameAndType        #18:#19        // _value:Ljava/lang/Object;
  #31 = Fieldref           #2.#30         // scala/runtime/LazyRef._value:Ljava/lang/Object;
  #32 = Utf8               initialize
  #33 = Utf8               (Ljava/lang/Object;)Ljava/lang/Object;
  #34 = Utf8               (TT;)TT;
  #35 = Utf8               toString
  #36 = Utf8               ()Ljava/lang/String;
  #37 = Utf8               java/lang/StringBuilder
  #38 = Class              #37            // java/lang/StringBuilder
  #39 = Integer            8
  #40 = Utf8               <init>
  #41 = Utf8               (I)V
  #42 = NameAndType        #40:#41        // "<init>":(I)V
  #43 = Methodref          #38.#42        // java/lang/StringBuilder."<init>":(I)V
  #44 = Utf8               LazyRef
  #45 = String             #44            // LazyRef
  #46 = Utf8               append
  #47 = Utf8               (Ljava/lang/String;)Ljava/lang/StringBuilder;
  #48 = NameAndType        #46:#47        // append:(Ljava/lang/String;)Ljava/lang/StringBuilder;
  #49 = Methodref          #38.#48        // java/lang/StringBuilder.append:(Ljava/lang/String;)Ljava/lang/StringBuilder;
  #50 = Integer            4
  #51 = Utf8               of:
  #52 = String             #51            // of:
  #53 = Utf8               (Ljava/lang/Object;)Ljava/lang/StringBuilder;
  #54 = NameAndType        #46:#53        // append:(Ljava/lang/Object;)Ljava/lang/StringBuilder;
  #55 = Methodref          #38.#54        // java/lang/StringBuilder.append:(Ljava/lang/Object;)Ljava/lang/StringBuilder;
  #56 = NameAndType        #35:#36        // toString:()Ljava/lang/String;
  #57 = Methodref          #38.#56        // java/lang/StringBuilder.toString:()Ljava/lang/String;
  #58 = Utf8               thunk
  #59 = String             #58            // thunk
  #60 = Utf8               java/lang/String
  #61 = Class              #60            // java/lang/String
  #62 = Utf8               ()V
  #63 = NameAndType        #40:#62        // "<init>":()V
  #64 = Methodref          #5.#63         // java/lang/Object."<init>":()V
  #65 = Utf8               ConstantValue
  #66 = Utf8               Signature
  #67 = Utf8               Code
  #68 = Utf8               LineNumberTable
  #69 = Utf8               LocalVariableTable
  #70 = Utf8               MethodParameters
  #71 = Utf8               StackMapTable
  #72 = Utf8               SourceFile
  #73 = Utf8               RuntimeVisibleAnnotations
  #74 = Utf8               ScalaInlineInfo
  #75 = Utf8               ScalaSig
{
  private static final long serialVersionUID;
    descriptor: J
    flags: (0x001a) ACC_PRIVATE, ACC_STATIC, ACC_FINAL
    ConstantValue: long 1l

  private volatile boolean _initialized;
    descriptor: Z
    flags: (0x0042) ACC_PRIVATE, ACC_VOLATILE

  private T _value;
    descriptor: Ljava/lang/Object;
    flags: (0x0002) ACC_PRIVATE
    Signature: #20                          // TT;

  public boolean initialized();
    descriptor: ()Z
    flags: (0x0001) ACC_PUBLIC
    Code:
      stack=1, locals=1, args_size=1
         0: aload_0
         1: getfield      #24                 // Field _initialized:Z
         4: ireturn
      LineNumberTable:
        line 20: 0
      LocalVariableTable:
        Start  Length  Slot  Name   Signature
            0       5     0  this   Lscala/runtime/LazyRef;

  public T value();
    descriptor: ()Ljava/lang/Object;
    flags: (0x0001) ACC_PUBLIC
    Code:
      stack=1, locals=1, args_size=1
         0: aload_0
         1: getfield      #31                 // Field _value:Ljava/lang/Object;
         4: areturn
      LineNumberTable:
        line 23: 0
      LocalVariableTable:
        Start  Length  Slot  Name   Signature
            0       5     0  this   Lscala/runtime/LazyRef;
    Signature: #29                          // ()TT;

  public T initialize(T);
    descriptor: (Ljava/lang/Object;)Ljava/lang/Object;
    flags: (0x0001) ACC_PUBLIC
    Code:
      stack=2, locals=2, args_size=2
         0: aload_0
         1: aload_1
         2: putfield      #31                 // Field _value:Ljava/lang/Object;
         5: aload_0
         6: iconst_1
         7: putfield      #24                 // Field _initialized:Z
        10: aload_1
        11: areturn
      LineNumberTable:
        line 25: 0
        line 26: 5
        line 27: 10
      LocalVariableTable:
        Start  Length  Slot  Name   Signature
            0      12     0  this   Lscala/runtime/LazyRef;
            0      12     1 value   Ljava/lang/Object;
    Signature: #34                          // (TT;)TT;
    MethodParameters:
      Name                           Flags
      value                          final

  public java.lang.String toString();
    descriptor: ()Ljava/lang/String;
    flags: (0x0001) ACC_PUBLIC
    Code:
      stack=4, locals=1, args_size=1
         0: new           #38                 // class java/lang/StringBuilder
         3: dup
         4: ldc           #39                 // int 8
         6: invokespecial #43                 // Method java/lang/StringBuilder."<init>":(I)V
         9: ldc           #45                 // String LazyRef
        11: invokevirtual #49                 // Method java/lang/StringBuilder.append:(Ljava/lang/String;)Ljava/lang/StringBuilder;
        14: aload_0
        15: getfield      #24                 // Field _initialized:Z
        18: ifeq          48
        21: new           #38                 // class java/lang/StringBuilder
        24: dup
        25: ldc           #50                 // int 4
        27: invokespecial #43                 // Method java/lang/StringBuilder."<init>":(I)V
        30: ldc           #52                 // String of:
        32: invokevirtual #49                 // Method java/lang/StringBuilder.append:(Ljava/lang/String;)Ljava/lang/StringBuilder;
        35: aload_0
        36: getfield      #31                 // Field _value:Ljava/lang/Object;
        39: invokevirtual #55                 // Method java/lang/StringBuilder.append:(Ljava/lang/Object;)Ljava/lang/StringBuilder;
        42: invokevirtual #57                 // Method java/lang/StringBuilder.toString:()Ljava/lang/String;
        45: goto          50
        48: ldc           #59                 // String thunk
        50: invokevirtual #55                 // Method java/lang/StringBuilder.append:(Ljava/lang/Object;)Ljava/lang/StringBuilder;
        53: invokevirtual #57                 // Method java/lang/StringBuilder.toString:()Ljava/lang/String;
        56: areturn
      StackMapTable: number_of_entries = 2
        frame_type = 112 /* same_locals_1_stack_item */
          stack = [ class java/lang/StringBuilder ]
        frame_type = 255 /* full_frame */
          offset_delta = 1
          locals = [ class scala/runtime/LazyRef ]
          stack = [ class java/lang/StringBuilder, class java/lang/String ]
      LineNumberTable:
        line 30: 0
      LocalVariableTable:
        Start  Length  Slot  Name   Signature
            0      57     0  this   Lscala/runtime/LazyRef;

  public scala.runtime.LazyRef();
    descriptor: ()V
    flags: (0x0001) ACC_PUBLIC
    Code:
      stack=1, locals=1, args_size=1
         0: aload_0
         1: invokespecial #64                 // Method java/lang/Object."<init>":()V
         4: return
      LineNumberTable:
        line 18: 0
      LocalVariableTable:
        Start  Length  Slot  Name   Signature
            0       5     0  this   Lscala/runtime/LazyRef;
}
Signature: #3                           // <T:Ljava/lang/Object;>Ljava/lang/Object;Ljava/io/Serializable;
SourceFile: "LazyRef.scala"
RuntimeVisibleAnnotations:
  0: #9(#10=s#11)
    scala.reflect.ScalaSignature(
      bytes="\u0006\u000593A\u0001C\u0005\u0001\u001d!)\u0001\u0005\u0001C\u0001C!Iq\u0006\u0001a\u0001\u0002\u0003\u0006K\u0001\r\u0005\u0006o\u0001!\t\u0001\u000f\u0005\ns\u0001\u0001\r\u0011!Q!\n\u0011BQA\u000f\u0001\u0005\u0002mBQ\u0001\u0010\u0001\u0005\u0002uBQa\u0010\u0001\u0005B\u0001\u0013q\u0001T1{sJ+gM\u0003\u0002\u000b\u0017\u00059!/\u001e8uS6,\'\"\u0001\u0007\u0002\u000bM\u001c\u0017\r\\1\u0004\u0001U\u0011qBJ\n\u0004\u0001A!\u0002CA\t\u0013\u001b\u0005Y\u0011BA\n\f\u0005\u0019\te.\u001f*fMB\u0011Q#\b\b\u0003-mq!a\u0006\u000e\u000e\u0003aQ!!G\u0007\u0002\rq\u0012xn\u001c;?\u0013\u0005a\u0011B\u0001\u000f\f\u0003\u001d\u0001\u0018mY6bO\u0016L!AH\u0010\u0003\u0019M+\'/[1mSj\f\'\r\\3\u000b\u0005qY\u0011A\u0002\u001fj]&$h\bF\u0001#!\r\u0019\u0003\u0001J\u0007\u0002\u0013A\u0011QE\n\u0007\u0001\t\u00159\u0003A1\u0001)\u0005\u0005!\u0016CA\u0015-!\t\t\"&\u0003\u0002,\u0017\t9aj\u001c;iS:<\u0007CA\t.\u0013\tq3BA\u0002B]f\fAbX5oSRL\u0017\r\\5{K\u0012\u0004\"!E\u0019\n\u0005IZ!a\u0002\"p_2,\u0017M\u001c\u0015\u0003\u0005Q\u0002\"!E\u001b\n\u0005YZ!\u0001\u0003<pY\u0006$\u0018\u000e\\3\u0002\u0017%t\u0017\u000e^5bY&TX\rZ\u000b\u0002a\u00051qL^1mk\u0016\fQA^1mk\u0016,\u0012\u0001J\u0001\u000bS:LG/[1mSj,GC\u0001\u0013?\u0011\u0015Qd\u00011\u0001%\u0003!!xn\u0015;sS:<G#A!\u0011\u0005\t3eBA\"E!\t92\"\u0003\u0002F\u0017\u00051\u0001K]3eK\u001aL!a\u0012%\u0003\rM#(/\u001b8h\u0015\t)5\u0002\u000b\u0003\u0001\u0015jj\u0005CA\tL\u0013\ta5B\u0001\tTKJL\u0017\r\u001c,feNLwN\\+J\tz\t\u0011\u0001"
    )
  ScalaInlineInfo: length = 0x1D (unknown attribute)
   01 00 00 05 00 28 00 3E 00 00 20 00 21 00 00 15
   00 16 00 00 23 00 24 00 00 1B 00 1C 00
  ScalaSig: length = 0x3 (unknown attribute)
   05 02 00
