Classfile /Users/mw/Projects/slang-braindump/.jar/jar8/assemble/slang-braindump/assemble/content/scala/runtime/ModuleSerializationProxy$$anon$1.class
  Last modified May 29, 2022; size 2205 bytes
  SHA-256 checksum f184b89934b3cb06ec62d478871cb96c78f2b6c948a388d2ca0596e37f66312e
  Compiled from "ModuleSerializationProxy.scala"
public final class scala.runtime.ModuleSerializationProxy$$anon$1 extends scala.runtime.ClassValueCompat<java.lang.Object>
  minor version: 0
  major version: 52
  flags: (0x0031) ACC_PUBLIC, ACC_FINAL, ACC_SUPER
  this_class: #2                          // scala/runtime/ModuleSerializationProxy$$anon$1
  super_class: #5                         // scala/runtime/ClassValueCompat
  interfaces: 0, fields: 0, methods: 4, attributes: 7
Constant pool:
   #1 = Utf8               scala/runtime/ModuleSerializationProxy$$anon$1
   #2 = Class              #1             // scala/runtime/ModuleSerializationProxy$$anon$1
   #3 = Utf8               Lscala/runtime/ClassValueCompat<Ljava/lang/Object;>;
   #4 = Utf8               scala/runtime/ClassValueCompat
   #5 = Class              #4             // scala/runtime/ClassValueCompat
   #6 = Utf8               ModuleSerializationProxy.scala
   #7 = Utf8               scala/runtime/ModuleSerializationProxy$
   #8 = Class              #7             // scala/runtime/ModuleSerializationProxy$
   #9 = Utf8               java/lang/invoke/MethodHandles$Lookup
  #10 = Class              #9             // java/lang/invoke/MethodHandles$Lookup
  #11 = Utf8               java/lang/invoke/MethodHandles
  #12 = Class              #11            // java/lang/invoke/MethodHandles
  #13 = Utf8               Lookup
  #14 = Utf8               getModule
  #15 = Utf8               (Ljava/lang/Class;)Ljava/lang/Object;
  #16 = Utf8               (Ljava/lang/Class<*>;)Ljava/lang/Object;
  #17 = Utf8               cls
  #18 = Utf8               ()Ljava/lang/Object;
  #19 = MethodType         #18            //  ()Ljava/lang/Object;
  #20 = Utf8               $anonfun$getModule$1
  #21 = NameAndType        #20:#15        // $anonfun$getModule$1:(Ljava/lang/Class;)Ljava/lang/Object;
  #22 = Methodref          #2.#21         // scala/runtime/ModuleSerializationProxy$$anon$1.$anonfun$getModule$1:(Ljava/lang/Class;)Ljava/lang/Object;
  #23 = MethodHandle       6:#22          // REF_invokeStatic scala/runtime/ModuleSerializationProxy$$anon$1.$anonfun$getModule$1:(Ljava/lang/Class;)Ljava/lang/Object;
  #24 = Integer            0
  #25 = Utf8               java/lang/invoke/LambdaMetafactory
  #26 = Class              #25            // java/lang/invoke/LambdaMetafactory
  #27 = Utf8               altMetafactory
  #28 = Utf8               (Ljava/lang/invoke/MethodHandles$Lookup;Ljava/lang/String;Ljava/lang/invoke/MethodType;[Ljava/lang/Object;)Ljava/lang/invoke/CallSite;
  #29 = NameAndType        #27:#28        // altMetafactory:(Ljava/lang/invoke/MethodHandles$Lookup;Ljava/lang/String;Ljava/lang/invoke/MethodType;[Ljava/lang/Object;)Ljava/lang/invoke/CallSite;
  #30 = Methodref          #26.#29        // java/lang/invoke/LambdaMetafactory.altMetafactory:(Ljava/lang/invoke/MethodHandles$Lookup;Ljava/lang/String;Ljava/lang/invoke/MethodType;[Ljava/lang/Object;)Ljava/lang/invoke/CallSite;
  #31 = MethodHandle       6:#30          // REF_invokeStatic java/lang/invoke/LambdaMetafactory.altMetafactory:(Ljava/lang/invoke/MethodHandles$Lookup;Ljava/lang/String;Ljava/lang/invoke/MethodType;[Ljava/lang/Object;)Ljava/lang/invoke/CallSite;
  #32 = Utf8               run
  #33 = Utf8               (Ljava/lang/Class;)Ljava/security/PrivilegedExceptionAction;
  #34 = NameAndType        #32:#33        // run:(Ljava/lang/Class;)Ljava/security/PrivilegedExceptionAction;
  #35 = InvokeDynamic      #0:#34         // #0:run:(Ljava/lang/Class;)Ljava/security/PrivilegedExceptionAction;
  #36 = Utf8               java/security/AccessController
  #37 = Class              #36            // java/security/AccessController
  #38 = Utf8               doPrivileged
  #39 = Utf8               (Ljava/security/PrivilegedExceptionAction;)Ljava/lang/Object;
  #40 = NameAndType        #38:#39        // doPrivileged:(Ljava/security/PrivilegedExceptionAction;)Ljava/lang/Object;
  #41 = Methodref          #37.#40        // java/security/AccessController.doPrivileged:(Ljava/security/PrivilegedExceptionAction;)Ljava/lang/Object;
  #42 = Utf8               this
  #43 = Utf8               Lscala/runtime/ModuleSerializationProxy$$anon$1;
  #44 = Utf8               Ljava/lang/Class;
  #45 = Utf8               computeValue
  #46 = Utf8               java/security/PrivilegedActionException
  #47 = Class              #46            // java/security/PrivilegedActionException
  #48 = NameAndType        #14:#15        // getModule:(Ljava/lang/Class;)Ljava/lang/Object;
  #49 = Methodref          #2.#48         // scala/runtime/ModuleSerializationProxy$$anon$1.getModule:(Ljava/lang/Class;)Ljava/lang/Object;
  #50 = Utf8               MODULE$
  #51 = Utf8               Lscala/runtime/ModuleSerializationProxy$;
  #52 = NameAndType        #50:#51        // MODULE$:Lscala/runtime/ModuleSerializationProxy$;
  #53 = Fieldref           #8.#52         // scala/runtime/ModuleSerializationProxy$.MODULE$:Lscala/runtime/ModuleSerializationProxy$;
  #54 = Utf8               getCause
  #55 = Utf8               ()Ljava/lang/Throwable;
  #56 = NameAndType        #54:#55        // getCause:()Ljava/lang/Throwable;
  #57 = Methodref          #47.#56        // java/security/PrivilegedActionException.getCause:()Ljava/lang/Throwable;
  #58 = Utf8               scala$runtime$ModuleSerializationProxy$$rethrowRuntime
  #59 = Utf8               (Ljava/lang/Throwable;)Ljava/lang/Object;
  #60 = NameAndType        #58:#59        // scala$runtime$ModuleSerializationProxy$$rethrowRuntime:(Ljava/lang/Throwable;)Ljava/lang/Object;
  #61 = Methodref          #8.#60         // scala/runtime/ModuleSerializationProxy$.scala$runtime$ModuleSerializationProxy$$rethrowRuntime:(Ljava/lang/Throwable;)Ljava/lang/Object;
  #62 = Utf8               e
  #63 = Utf8               Ljava/security/PrivilegedActionException;
  #64 = Utf8               cls$1
  #65 = String             #50            // MODULE$
  #66 = Utf8               java/lang/Class
  #67 = Class              #66            // java/lang/Class
  #68 = Utf8               getField
  #69 = Utf8               (Ljava/lang/String;)Ljava/lang/reflect/Field;
  #70 = NameAndType        #68:#69        // getField:(Ljava/lang/String;)Ljava/lang/reflect/Field;
  #71 = Methodref          #67.#70        // java/lang/Class.getField:(Ljava/lang/String;)Ljava/lang/reflect/Field;
  #72 = Utf8               java/lang/reflect/Field
  #73 = Class              #72            // java/lang/reflect/Field
  #74 = Utf8               get
  #75 = Utf8               (Ljava/lang/Object;)Ljava/lang/Object;
  #76 = NameAndType        #74:#75        // get:(Ljava/lang/Object;)Ljava/lang/Object;
  #77 = Methodref          #73.#76        // java/lang/reflect/Field.get:(Ljava/lang/Object;)Ljava/lang/Object;
  #78 = Utf8               <init>
  #79 = Utf8               ()V
  #80 = NameAndType        #78:#79        // "<init>":()V
  #81 = Methodref          #5.#80         // scala/runtime/ClassValueCompat."<init>":()V
  #82 = Utf8               Code
  #83 = Utf8               LineNumberTable
  #84 = Utf8               LocalVariableTable
  #85 = Utf8               Signature
  #86 = Utf8               MethodParameters
  #87 = Utf8               StackMapTable
  #88 = Utf8               InnerClasses
  #89 = Utf8               EnclosingMethod
  #90 = Utf8               SourceFile
  #91 = Utf8               BootstrapMethods
  #92 = Utf8               ScalaInlineInfo
  #93 = Utf8               Scala
{
  public java.lang.Object getModule(java.lang.Class<?>);
    descriptor: (Ljava/lang/Class;)Ljava/lang/Object;
    flags: (0x0001) ACC_PUBLIC
    Code:
      stack=1, locals=2, args_size=2
         0: aload_1
         1: invokedynamic #35,  0             // InvokeDynamic #0:run:(Ljava/lang/Class;)Ljava/security/PrivilegedExceptionAction;
         6: invokestatic  #41                 // Method java/security/AccessController.doPrivileged:(Ljava/security/PrivilegedExceptionAction;)Ljava/lang/Object;
         9: areturn
      LineNumberTable:
        line 25: 0
      LocalVariableTable:
        Start  Length  Slot  Name   Signature
            0      10     0  this   Lscala/runtime/ModuleSerializationProxy$$anon$1;
            0      10     1   cls   Ljava/lang/Class;
    Signature: #16                          // (Ljava/lang/Class<*>;)Ljava/lang/Object;
    MethodParameters:
      Name                           Flags
      cls                            final

  public java.lang.Object computeValue(java.lang.Class<?>);
    descriptor: (Ljava/lang/Class;)Ljava/lang/Object;
    flags: (0x0001) ACC_PUBLIC
    Code:
      stack=2, locals=3, args_size=2
         0: aload_0
         1: aload_1
         2: invokevirtual #49                 // Method getModule:(Ljava/lang/Class;)Ljava/lang/Object;
         5: areturn
         6: astore_2
         7: getstatic     #53                 // Field scala/runtime/ModuleSerializationProxy$.MODULE$:Lscala/runtime/ModuleSerializationProxy$;
        10: aload_2
        11: invokevirtual #57                 // Method java/security/PrivilegedActionException.getCause:()Ljava/lang/Throwable;
        14: invokevirtual #61                 // Method scala/runtime/ModuleSerializationProxy$.scala$runtime$ModuleSerializationProxy$$rethrowRuntime:(Ljava/lang/Throwable;)Ljava/lang/Object;
        17: areturn
      Exception table:
         from    to  target type
             0     5     6   Class java/security/PrivilegedActionException
      StackMapTable: number_of_entries = 1
        frame_type = 70 /* same_locals_1_stack_item */
          stack = [ class java/security/PrivilegedActionException ]
      LineNumberTable:
        line 27: 0
        line 30: 7
      LocalVariableTable:
        Start  Length  Slot  Name   Signature
            6      11     2     e   Ljava/security/PrivilegedActionException;
            0      18     0  this   Lscala/runtime/ModuleSerializationProxy$$anon$1;
            0      18     1   cls   Ljava/lang/Class;
    Signature: #16                          // (Ljava/lang/Class<*>;)Ljava/lang/Object;
    MethodParameters:
      Name                           Flags
      cls                            final

  public static final java.lang.Object $anonfun$getModule$1(java.lang.Class);
    descriptor: (Ljava/lang/Class;)Ljava/lang/Object;
    flags: (0x1019) ACC_PUBLIC, ACC_STATIC, ACC_FINAL, ACC_SYNTHETIC
    Code:
      stack=2, locals=1, args_size=1
         0: aload_0
         1: ldc           #65                 // String MODULE$
         3: invokevirtual #71                 // Method java/lang/Class.getField:(Ljava/lang/String;)Ljava/lang/reflect/Field;
         6: aconst_null
         7: invokevirtual #77                 // Method java/lang/reflect/Field.get:(Ljava/lang/Object;)Ljava/lang/Object;
        10: areturn
      LineNumberTable:
        line 25: 0
      LocalVariableTable:
        Start  Length  Slot  Name   Signature
            0      11     0 cls$1   Ljava/lang/Class;
    MethodParameters:
      Name                           Flags
      cls$1                          final

  public scala.runtime.ModuleSerializationProxy$$anon$1();
    descriptor: ()V
    flags: (0x0001) ACC_PUBLIC
    Code:
      stack=1, locals=1, args_size=1
         0: aload_0
         1: invokespecial #81                 // Method scala/runtime/ClassValueCompat."<init>":()V
         4: return
      LineNumberTable:
        line 21: 0
      LocalVariableTable:
        Start  Length  Slot  Name   Signature
            0       5     0  this   Lscala/runtime/ModuleSerializationProxy$$anon$1;
}
InnerClasses:
  public static final #13= #10 of #12;    // Lookup=class java/lang/invoke/MethodHandles$Lookup of class java/lang/invoke/MethodHandles
  public final #2;                        // class scala/runtime/ModuleSerializationProxy$$anon$1
EnclosingMethod: #8.#0                  // scala.runtime.ModuleSerializationProxy$
Signature: #3                           // Lscala/runtime/ClassValueCompat<Ljava/lang/Object;>;
SourceFile: "ModuleSerializationProxy.scala"
BootstrapMethods:
  0: #31 REF_invokeStatic java/lang/invoke/LambdaMetafactory.altMetafactory:(Ljava/lang/invoke/MethodHandles$Lookup;Ljava/lang/String;Ljava/lang/invoke/MethodType;[Ljava/lang/Object;)Ljava/lang/invoke/CallSite;
    Method arguments:
      #19 ()Ljava/lang/Object;
      #23 REF_invokeStatic scala/runtime/ModuleSerializationProxy$$anon$1.$anonfun$getModule$1:(Ljava/lang/Class;)Ljava/lang/Object;
      #19 ()Ljava/lang/Object;
      #24 0
  ScalaInlineInfo: length = 0x18 (unknown attribute)
   01 01 00 04 00 14 00 0F 01 00 4E 00 4F 01 00 2D
   00 0F 01 00 0E 00 0F 01
  Scala: length = 0x0 (unknown attribute)

