Classfile /Users/mw/Projects/slang-braindump/.jar/jar8/assemble/slang-braindump/assemble/content/scala/runtime/RichLong.class
  Last modified May 29, 2022; size 14398 bytes
  SHA-256 checksum 6c549e3bdeebe646ff21ea118a5d17de0043c6d96b1b6738f45cfd8946855ade
  Compiled from "RichLong.scala"
public final class scala.runtime.RichLong extends java.lang.Object implements scala.runtime.IntegralProxy<java.lang.Object>
  minor version: 0
  major version: 52
  flags: (0x0031) ACC_PUBLIC, ACC_FINAL, ACC_SUPER
  this_class: #2                          // scala/runtime/RichLong
  super_class: #5                         // java/lang/Object
  interfaces: 1, fields: 1, methods: 80, attributes: 6
Constant pool:
    #1 = Utf8               scala/runtime/RichLong
    #2 = Class              #1            // scala/runtime/RichLong
    #3 = Utf8               Ljava/lang/Object;Lscala/runtime/IntegralProxy<Ljava/lang/Object;>;
    #4 = Utf8               java/lang/Object
    #5 = Class              #4            // java/lang/Object
    #6 = Utf8               scala/runtime/IntegralProxy
    #7 = Class              #6            // scala/runtime/IntegralProxy
    #8 = Utf8               RichLong.scala
    #9 = Utf8               Lscala/reflect/ScalaSignature;
   #10 = Utf8               bytes
   #11 = Utf8               \u0006\u0005\t\u001da\u0001B\u001a5\u0005eB\u0001\"\u0012\u0001\u0003\u0006\u0004%\tA\u0012\u0005\t\u000f\u0002\u0011\t\u0011)A\u0005\u0005\")\u0001\n\u0001C\u0001\u0013\")A\n\u0001C\t\u001b\")a\f\u0001C\t?\")q\r\u0001C!Q\")A\u000e\u0001C![\")\u0011\u000f\u0001C!\r\")!\u000f\u0001C!g\")q\u000f\u0001C!q\")A\u0010\u0001C!{\"9\u00111\u0001\u0001\u0005B\u0005\u0015\u0001bBA\u0007\u0001\u0011\u0005\u0013Q\u0001\u0005\b\u0003\u001f\u0001A\u0011IA\u0003\u0011\u001d\t\t\u0002\u0001C!\u0003\u000bAq!a\u0005\u0001\t\u0003\t)\u0001\u0003\u0004\u0002\u0016\u0001!\tE\u0012\u0005\b\u0003/\u0001A\u0011IA\r\u0011\u001d\ty\u0002\u0001C!\u0003CAa!!\n\u0001\t\u00031\u0005bBA\u001e\u0001\u0011\u0005\u0011Q\b\u0005\b\u0003\u001f\u0002A\u0011AA\u001f\u0011\u001d\t\t\u0006\u0001C\u0001\u0003{A\u0011\"a\u0015\u0001\u0003\u0003%\t%!\u0016\t\u0013\u0005]\u0003!!A\u0005B\u0005es!CA3i\u0005\u0005\t\u0012AA4\r!\u0019D\'!A\t\u0002\u0005%\u0004B\u0002%\u001c\t\u0003\t\t\bC\u0004\u0002tm!)!!\u001e\t\u000f\u0005m4\u0004\"\u0002\u0002~!9\u0011\u0011Q\u000e\u0005\u0006\u0005\r\u0005bBAD7\u0011\u0015\u0011\u0011\u0012\u0005\b\u0003\u001b[BQAAH\u0011\u001d\t\u0019j\u0007C\u0003\u0003+Cq!!\'\u001c\t\u000b\tY\nC\u0004\u0002 n!)!!)\t\u000f\u0005\u00156\u0004\"\u0002\u0002(\"9\u00111V\u000e\u0005\u0006\u00055\u0006bBAY7\u0011\u0015\u00111\u0017\u0005\b\u0003o[BQAA]\u0011\u001d\til\u0007C\u0003\u0003\u007fCq!a1\u001c\t\u000b\t)\rC\u0004\u0002Jn!)!a3\t\u000f\u0005M7\u0004\"\u0002\u0002V\"9\u0011Q\\\u000e\u0005\u0006\u0005}\u0007bBAs7\u0011\u0015\u0011q\u001d\u0005\b\u0003W\\BQAAw\u0011\u001d\t\tp\u0007C\u0003\u0003gD\u0011\"a>\u001c\u0003\u0003%)!!?\t\u0013\u0005u8$!A\u0005\u0006\u0005}(\u0001\u0003*jG\"duN\\4\u000b\u0005U2\u0014a\u0002:v]RLW.\u001a\u0006\u0002o\u0005)1oY1mC\u000e\u00011c\u0001\u0001;}A\u00111\bP\u0007\u0002m%\u0011QH\u000e\u0002\u0007\u0003:Lh+\u00197\u0011\u0007}\u0002%)D\u00015\u0013\t\tEGA\u0007J]R,wM]1m!J|\u00070\u001f\t\u0003w\rK!\u0001\u0012\u001c\u0003\t1{gnZ\u0001\u0005g\u0016dg-F\u0001C\u0003\u0015\u0019X\r\u001c4!\u0003\u0019a\u0014N\\5u}Q\u0011!j\u0013\t\u0003\u007f\u0001AQ!R\u0002A\u0002\t\u000b1A\\;n+\u0005q\u0005CA(\\\u001d\t\u0001\u0006L\u0004\u0002R-:\u0011!+V\u0007\u0002\'*\u0011A\u000bO\u0001\u0007yI|w\u000e\u001e \n\u0003]J!a\u0016\u001c\u0002\t5\fG\u000f[\u0005\u00033j\u000bqAT;nKJL7M\u0003\u0002Xm)\u0011A,X\u0001\u000f\u0019>tw-S:J]R,wM]1m\u0015\tI&,A\u0002pe\u0012,\u0012\u0001\u0019\t\u0003C\u0012t!\u0001\u00152\n\u0005\rT\u0016\u0001C(sI\u0016\u0014\u0018N\\4\u000b\u0005\u00154\u0017\u0001\u0002\'p]\u001eT!a\u0019.\u0002\u0017\u0011|WO\u00197f-\u0006dW/Z\u000b\u0002SB\u00111H[\u0005\u0003WZ\u0012a\u0001R8vE2,\u0017A\u00034m_\u0006$h+\u00197vKV\ta\u000e\u0005\u0002<_&\u0011\u0001O\u000e\u0002\u0006\r2|\u0017\r^\u0001\nY>twMV1mk\u0016\f\u0001\"\u001b8u-\u0006dW/Z\u000b\u0002iB\u00111(^\u0005\u0003mZ\u00121!\u00138u\u0003%\u0011\u0017\u0010^3WC2,X-F\u0001z!\tY$0\u0003\u0002|m\t!!)\u001f;f\u0003)\u0019\bn\u001c:u-\u0006dW/Z\u000b\u0002}B\u00111h`\u0005\u0004\u0003\u00031$!B*i_J$\u0018aC5t-\u0006d\u0017\u000e\u001a\"zi\u0016,\"!a\u0002\u0011\u0007m\nI!C\u0002\u0002\fY\u0012qAQ8pY\u0016\fg.\u0001\u0007jgZ\u000bG.\u001b3TQ>\u0014H/A\u0006jgZ\u000bG.\u001b3DQ\u0006\u0014\u0018AC5t-\u0006d\u0017\u000eZ%oi\u0006Y\u0011n\u001d,bY&$Gj\u001c8h\u0003\r\t\'m]\u0001\u0004[\u0006DHc\u0001\"\u0002\u001c!1\u0011Q\u0004\nA\u0002\t\u000bA\u0001\u001e5bi\u0006\u0019Q.\u001b8\u0015\u0007\t\u000b\u0019\u0003\u0003\u0004\u0002\u001eM\u0001\rAQ\u0001\u0006e>,h\u000e\u001a\u0015\f)\u0005%\u0012qFA\u0019\u0003k\t9\u0004E\u0002<\u0003WI1!!\f7\u0005)!W\r\u001d:fG\u0006$X\rZ\u0001\b[\u0016\u001c8/Y4fC\t\t\u0019$A:uQ&\u001c\b%[:!C:\u0004\u0013N\u001c;fO\u0016\u0014\b\u0005^=qKn\u0002C\u000f[3sK\u0002J7\u000f\t8pAI,\u0017m]8oAQ|\u0007E]8v]\u0012\u0004\u0013\u000e\u001e\u0018!AA+\'\u000f[1qg\u0002Jx.\u001e\u0011nK\u0006tG\u000f\t;pA\r\fG\u000e\u001c\u0011uQ&\u001c\be\u001c8!C\u00022Gn\\1uS:<W\u0006]8j]R\u0004c/\u00197vK~\nQa]5oG\u0016\f#!!\u000f\u0002\rIr\u0013\'\r\u00181\u00039!xNQ5oCJL8\u000b\u001e:j]\u001e,\"!a\u0010\u0011\t\u0005\u0005\u0013\u0011\n\b\u0005\u0003\u0007\n)\u0005\u0005\u0002Sm%\u0019\u0011q\t\u001c\u0002\rA\u0013X\rZ3g\u0013\u0011\tY%!\u0014\u0003\rM#(/\u001b8h\u0015\r\t9EN\u0001\fi>DU\r_*ue&tw-A\u0007u_>\u001bG/\u00197TiJLgnZ\u0001\tQ\u0006\u001c\bnQ8eKR\tA/\u0001\u0004fcV\fGn\u001d\u000b\u0005\u0003\u000f\tY\u0006C\u0005\u0002^e\t\t\u00111\u0001\u0002`\u0005\u0019\u0001\u0010J\u0019\u0011\u0007m\n\t\'C\u0002\u0002dY\u00121!\u00118z\u0003!\u0011\u0016n\u00195M_:<\u0007CA \u001c\'\rY\u00121\u000e\t\u0004w\u00055\u0014bAA8m\t1\u0011I\\=SK\u001a$\"!a\u001a\u0002\u001b9,X\u000eJ3yi\u0016t7/[8o)\rq\u0015q\u000f\u0005\u0007\u0003sj\u0002\u0019\u0001&\u0002\u000b\u0011\"\b.[:\u0002\u001b=\u0014H\rJ3yi\u0016t7/[8o)\r\u0001\u0017q\u0010\u0005\u0007\u0003sr\u0002\u0019\u0001&\u0002+\u0011|WO\u00197f-\u0006dW/\u001a\u0013fqR,gn]5p]R\u0019\u0011.!\"\t\r\u0005et\u00041\u0001K\u0003Q1Gn\\1u-\u0006dW/\u001a\u0013fqR,gn]5p]R\u0019a.a#\t\r\u0005e\u0004\u00051\u0001K\u0003MawN\\4WC2,X\rJ3yi\u0016t7/[8o)\r\u0011\u0015\u0011\u0013\u0005\u0007\u0003s\n\u0003\u0019\u0001&\u0002%%tGOV1mk\u0016$S\r\u001f;f]NLwN\u001c\u000b\u0004i\u0006]\u0005BBA=E\u0001\u0007!*A\ncsR,g+\u00197vK\u0012*\u0007\u0010^3og&|g\u000eF\u0002z\u0003;Ca!!\u001f$\u0001\u0004Q\u0015\u0001F:i_J$h+\u00197vK\u0012*\u0007\u0010^3og&|g\u000eF\u0002\u007f\u0003GCa!!\u001f%\u0001\u0004Q\u0015!F5t-\u0006d\u0017\u000e\u001a\"zi\u0016$S\r\u001f;f]NLwN\u001c\u000b\u0005\u0003\u000f\tI\u000b\u0003\u0004\u0002z\u0015\u0002\rAS\u0001\u0017SN4\u0016\r\\5e\'\"|\'\u000f\u001e\u0013fqR,gn]5p]R!\u0011qAAX\u0011\u0019\tIH\na\u0001\u0015\u0006)\u0012n\u001d,bY&$7\t[1sI\u0015DH/\u001a8tS>tG\u0003BA\u0004\u0003kCa!!\u001f(\u0001\u0004Q\u0015\u0001F5t-\u0006d\u0017\u000eZ%oi\u0012*\u0007\u0010^3og&|g\u000e\u0006\u0003\u0002\b\u0005m\u0006BBA=Q\u0001\u0007!*A\u000bjgZ\u000bG.\u001b3M_:<G%\u001a=uK:\u001c\u0018n\u001c8\u0015\t\u0005\u001d\u0011\u0011\u0019\u0005\u0007\u0003sJ\u0003\u0019\u0001&\u0002\u001b\u0005\u00147\u000fJ3yi\u0016t7/[8o)\r\u0011\u0015q\u0019\u0005\u0007\u0003sR\u0003\u0019\u0001&\u0002\u001b5\f\u0007\u0010J3yi\u0016t7/[8o)\u0011\ti-!5\u0015\u0007\t\u000by\r\u0003\u0004\u0002\u001e-\u0002\rA\u0011\u0005\u0007\u0003sZ\u0003\u0019\u0001&\u0002\u001b5Lg\u000eJ3yi\u0016t7/[8o)\u0011\t9.a7\u0015\u0007\t\u000bI\u000e\u0003\u0004\u0002\u001e1\u0002\rA\u0011\u0005\u0007\u0003sb\u0003\u0019\u0001&\u0002\u001fI|WO\u001c3%Kb$XM\\:j_:$2AQAq\u0011\u0019\tI(\fa\u0001\u0015\"ZQ&!\u000b\u00020\u0005E\u0012QGA\u001c\u0003a!xNQ5oCJL8\u000b\u001e:j]\u001e$S\r\u001f;f]NLwN\u001c\u000b\u0005\u0003\u007f\tI\u000f\u0003\u0004\u0002z9\u0002\rAS\u0001\u0016i>DU\r_*ue&tw\rJ3yi\u0016t7/[8o)\u0011\ty$a<\t\r\u0005et\u00061\u0001K\u0003]!xnT2uC2\u001cFO]5oO\u0012*\u0007\u0010^3og&|g\u000e\u0006\u0003\u0002@\u0005U\bBBA=a\u0001\u0007!*\u0001\niCND7i\u001c3fI\u0015DH/\u001a8tS>tG\u0003BA+\u0003wDa!!\u001f2\u0001\u0004Q\u0015\u0001E3rk\u0006d7\u000fJ3yi\u0016t7/[8o)\u0011\u0011\tA!\u0002\u0015\t\u0005\u001d!1\u0001\u0005\n\u0003;\u0012\u0014\u0011!a\u0001\u0003?Ba!!\u001f3\u0001\u0004Q\u0005
   #12 = Utf8               scala/collection/immutable/NumericRange$Exclusive
   #13 = Class              #12           // scala/collection/immutable/NumericRange$Exclusive
   #14 = Utf8               scala/collection/immutable/NumericRange
   #15 = Class              #14           // scala/collection/immutable/NumericRange
   #16 = Utf8               Exclusive
   #17 = Utf8               scala/collection/immutable/NumericRange$Inclusive
   #18 = Class              #17           // scala/collection/immutable/NumericRange$Inclusive
   #19 = Utf8               Inclusive
   #20 = Utf8               scala/math/Numeric$LongIsIntegral$
   #21 = Class              #20           // scala/math/Numeric$LongIsIntegral$
   #22 = Utf8               scala/math/Numeric
   #23 = Class              #22           // scala/math/Numeric
   #24 = Utf8               LongIsIntegral$
   #25 = Utf8               scala/math/Ordering$Long$
   #26 = Class              #25           // scala/math/Ordering$Long$
   #27 = Utf8               scala/math/Ordering
   #28 = Class              #27           // scala/math/Ordering
   #29 = Utf8               Long$
   #30 = Utf8               self
   #31 = Utf8               J
   #32 = Utf8               equals$extension
   #33 = Utf8               (JLjava/lang/Object;)Z
   #34 = Utf8               $this
   #35 = Utf8               x$1
   #36 = Utf8               scala/runtime/RichLong$
   #37 = Class              #36           // scala/runtime/RichLong$
   #38 = Utf8               MODULE$
   #39 = Utf8               Lscala/runtime/RichLong$;
   #40 = NameAndType        #38:#39       // MODULE$:Lscala/runtime/RichLong$;
   #41 = Fieldref           #37.#40       // scala/runtime/RichLong$.MODULE$:Lscala/runtime/RichLong$;
   #42 = NameAndType        #32:#33       // equals$extension:(JLjava/lang/Object;)Z
   #43 = Methodref          #37.#42       // scala/runtime/RichLong$.equals$extension:(JLjava/lang/Object;)Z
   #44 = Utf8               Ljava/lang/Object;
   #45 = Utf8               hashCode$extension
   #46 = Utf8               (J)I
   #47 = Utf8               java/lang/Long
   #48 = Class              #47           // java/lang/Long
   #49 = Utf8               hashCode
   #50 = NameAndType        #49:#46       // hashCode:(J)I
   #51 = Methodref          #48.#50       // java/lang/Long.hashCode:(J)I
   #52 = Utf8               toOctalString$extension
   #53 = Utf8               (J)Ljava/lang/String;
   #54 = Utf8               toOctalString
   #55 = NameAndType        #54:#53       // toOctalString:(J)Ljava/lang/String;
   #56 = Methodref          #48.#55       // java/lang/Long.toOctalString:(J)Ljava/lang/String;
   #57 = Utf8               toHexString$extension
   #58 = Utf8               toHexString
   #59 = NameAndType        #58:#53       // toHexString:(J)Ljava/lang/String;
   #60 = Methodref          #48.#59       // java/lang/Long.toHexString:(J)Ljava/lang/String;
   #61 = Utf8               toBinaryString$extension
   #62 = Utf8               toBinaryString
   #63 = NameAndType        #62:#53       // toBinaryString:(J)Ljava/lang/String;
   #64 = Methodref          #48.#63       // java/lang/Long.toBinaryString:(J)Ljava/lang/String;
   #65 = Utf8               round$extension
   #66 = Utf8               (J)J
   #67 = Utf8               min$extension
   #68 = Utf8               (JJ)J
   #69 = Utf8               that
   #70 = Utf8               scala/math/package$
   #71 = Class              #70           // scala/math/package$
   #72 = Utf8               Lscala/math/package$;
   #73 = NameAndType        #38:#72       // MODULE$:Lscala/math/package$;
   #74 = Fieldref           #71.#73       // scala/math/package$.MODULE$:Lscala/math/package$;
   #75 = Utf8               java/lang/Math
   #76 = Class              #75           // java/lang/Math
   #77 = Utf8               min
   #78 = NameAndType        #77:#68       // min:(JJ)J
   #79 = Methodref          #76.#78       // java/lang/Math.min:(JJ)J
   #80 = Utf8               max$extension
   #81 = Utf8               max
   #82 = NameAndType        #81:#68       // max:(JJ)J
   #83 = Methodref          #76.#82       // java/lang/Math.max:(JJ)J
   #84 = Utf8               abs$extension
   #85 = Utf8               abs
   #86 = NameAndType        #85:#66       // abs:(J)J
   #87 = Methodref          #76.#86       // java/lang/Math.abs:(J)J
   #88 = Utf8               isValidLong$extension
   #89 = Utf8               (J)Z
   #90 = Utf8               isValidInt$extension
   #91 = NameAndType        #90:#89       // isValidInt$extension:(J)Z
   #92 = Methodref          #37.#91       // scala/runtime/RichLong$.isValidInt$extension:(J)Z
   #93 = Utf8               isValidChar$extension
   #94 = NameAndType        #93:#89       // isValidChar$extension:(J)Z
   #95 = Methodref          #37.#94       // scala/runtime/RichLong$.isValidChar$extension:(J)Z
   #96 = Utf8               isValidShort$extension
   #97 = NameAndType        #96:#89       // isValidShort$extension:(J)Z
   #98 = Methodref          #37.#97       // scala/runtime/RichLong$.isValidShort$extension:(J)Z
   #99 = Utf8               isValidByte$extension
  #100 = NameAndType        #99:#89       // isValidByte$extension:(J)Z
  #101 = Methodref          #37.#100      // scala/runtime/RichLong$.isValidByte$extension:(J)Z
  #102 = Utf8               shortValue$extension
  #103 = Utf8               (J)S
  #104 = Utf8               byteValue$extension
  #105 = Utf8               (J)B
  #106 = Utf8               intValue$extension
  #107 = Utf8               longValue$extension
  #108 = Utf8               floatValue$extension
  #109 = Utf8               (J)F
  #110 = Utf8               doubleValue$extension
  #111 = Utf8               (J)D
  #112 = Utf8               ord$extension
  #113 = Utf8               (J)Lscala/math/Ordering$Long$;
  #114 = Utf8               Lscala/math/Ordering$Long$;
  #115 = NameAndType        #38:#114      // MODULE$:Lscala/math/Ordering$Long$;
  #116 = Fieldref           #26.#115      // scala/math/Ordering$Long$.MODULE$:Lscala/math/Ordering$Long$;
  #117 = Utf8               num$extension
  #118 = Utf8               (J)Lscala/math/Numeric$LongIsIntegral$;
  #119 = Utf8               Lscala/math/Numeric$LongIsIntegral$;
  #120 = NameAndType        #38:#119      // MODULE$:Lscala/math/Numeric$LongIsIntegral$;
  #121 = Fieldref           #21.#120      // scala/math/Numeric$LongIsIntegral$.MODULE$:Lscala/math/Numeric$LongIsIntegral$;
  #122 = Utf8               until
  #123 = Utf8               (Ljava/lang/Object;)Lscala/collection/immutable/NumericRange$Exclusive;
  #124 = Utf8               end
  #125 = Utf8               until$
  #126 = Utf8               (Lscala/runtime/IntegralProxy;Ljava/lang/Object;)Lscala/collection/immutable/NumericRange$Exclusive;
  #127 = NameAndType        #125:#126     // until$:(Lscala/runtime/IntegralProxy;Ljava/lang/Object;)Lscala/collection/immutable/NumericRange$Exclusive;
  #128 = InterfaceMethodref #7.#127       // scala/runtime/IntegralProxy.until$:(Lscala/runtime/IntegralProxy;Ljava/lang/Object;)Lscala/collection/immutable/NumericRange$Exclusive;
  #129 = Utf8               this
  #130 = Utf8               Lscala/runtime/RichLong;
  #131 = Utf8               (Ljava/lang/Object;Ljava/lang/Object;)Lscala/collection/immutable/NumericRange$Exclusive;
  #132 = Utf8               step
  #133 = Utf8               (Lscala/runtime/IntegralProxy;Ljava/lang/Object;Ljava/lang/Object;)Lscala/collection/immutable/NumericRange$Exclusive;
  #134 = NameAndType        #125:#133     // until$:(Lscala/runtime/IntegralProxy;Ljava/lang/Object;Ljava/lang/Object;)Lscala/collection/immutable/NumericRange$Exclusive;
  #135 = InterfaceMethodref #7.#134       // scala/runtime/IntegralProxy.until$:(Lscala/runtime/IntegralProxy;Ljava/lang/Object;Ljava/lang/Object;)Lscala/collection/immutable/NumericRange$Exclusive;
  #136 = Utf8               to
  #137 = Utf8               (Ljava/lang/Object;)Lscala/collection/immutable/NumericRange$Inclusive;
  #138 = Utf8               to$
  #139 = Utf8               (Lscala/runtime/IntegralProxy;Ljava/lang/Object;)Lscala/collection/immutable/NumericRange$Inclusive;
  #140 = NameAndType        #138:#139     // to$:(Lscala/runtime/IntegralProxy;Ljava/lang/Object;)Lscala/collection/immutable/NumericRange$Inclusive;
  #141 = InterfaceMethodref #7.#140       // scala/runtime/IntegralProxy.to$:(Lscala/runtime/IntegralProxy;Ljava/lang/Object;)Lscala/collection/immutable/NumericRange$Inclusive;
  #142 = Utf8               (Ljava/lang/Object;Ljava/lang/Object;)Lscala/collection/immutable/NumericRange$Inclusive;
  #143 = Utf8               (Lscala/runtime/IntegralProxy;Ljava/lang/Object;Ljava/lang/Object;)Lscala/collection/immutable/NumericRange$Inclusive;
  #144 = NameAndType        #138:#143     // to$:(Lscala/runtime/IntegralProxy;Ljava/lang/Object;Ljava/lang/Object;)Lscala/collection/immutable/NumericRange$Inclusive;
  #145 = InterfaceMethodref #7.#144       // scala/runtime/IntegralProxy.to$:(Lscala/runtime/IntegralProxy;Ljava/lang/Object;Ljava/lang/Object;)Lscala/collection/immutable/NumericRange$Inclusive;
  #146 = Utf8               isWhole
  #147 = Utf8               ()Z
  #148 = Utf8               scala/runtime/ScalaWholeNumberProxy
  #149 = Class              #148          // scala/runtime/ScalaWholeNumberProxy
  #150 = Utf8               isWhole$
  #151 = Utf8               (Lscala/runtime/ScalaWholeNumberProxy;)Z
  #152 = NameAndType        #150:#151     // isWhole$:(Lscala/runtime/ScalaWholeNumberProxy;)Z
  #153 = InterfaceMethodref #149.#152     // scala/runtime/ScalaWholeNumberProxy.isWhole$:(Lscala/runtime/ScalaWholeNumberProxy;)Z
  #154 = Utf8               sign
  #155 = Utf8               ()Ljava/lang/Object;
  #156 = Utf8               scala/runtime/ScalaNumberProxy
  #157 = Class              #156          // scala/runtime/ScalaNumberProxy
  #158 = Utf8               sign$
  #159 = Utf8               (Lscala/runtime/ScalaNumberProxy;)Ljava/lang/Object;
  #160 = NameAndType        #158:#159     // sign$:(Lscala/runtime/ScalaNumberProxy;)Ljava/lang/Object;
  #161 = InterfaceMethodref #157.#160     // scala/runtime/ScalaNumberProxy.sign$:(Lscala/runtime/ScalaNumberProxy;)Ljava/lang/Object;
  #162 = Utf8               signum
  #163 = Utf8               ()I
  #164 = Utf8               signum$
  #165 = Utf8               (Lscala/runtime/ScalaNumberProxy;)I
  #166 = NameAndType        #164:#165     // signum$:(Lscala/runtime/ScalaNumberProxy;)I
  #167 = InterfaceMethodref #157.#166     // scala/runtime/ScalaNumberProxy.signum$:(Lscala/runtime/ScalaNumberProxy;)I
  #168 = Utf8               compare
  #169 = Utf8               (Ljava/lang/Object;)I
  #170 = Utf8               y
  #171 = Utf8               scala/runtime/OrderedProxy
  #172 = Class              #171          // scala/runtime/OrderedProxy
  #173 = Utf8               compare$
  #174 = Utf8               (Lscala/runtime/OrderedProxy;Ljava/lang/Object;)I
  #175 = NameAndType        #173:#174     // compare$:(Lscala/runtime/OrderedProxy;Ljava/lang/Object;)I
  #176 = InterfaceMethodref #172.#175     // scala/runtime/OrderedProxy.compare$:(Lscala/runtime/OrderedProxy;Ljava/lang/Object;)I
  #177 = Utf8               $less
  #178 = Utf8               (Ljava/lang/Object;)Z
  #179 = Utf8               scala/math/Ordered
  #180 = Class              #179          // scala/math/Ordered
  #181 = Utf8               $less$
  #182 = Utf8               (Lscala/math/Ordered;Ljava/lang/Object;)Z
  #183 = NameAndType        #181:#182     // $less$:(Lscala/math/Ordered;Ljava/lang/Object;)Z
  #184 = InterfaceMethodref #180.#183     // scala/math/Ordered.$less$:(Lscala/math/Ordered;Ljava/lang/Object;)Z
  #185 = Utf8               $greater
  #186 = Utf8               $greater$
  #187 = NameAndType        #186:#182     // $greater$:(Lscala/math/Ordered;Ljava/lang/Object;)Z
  #188 = InterfaceMethodref #180.#187     // scala/math/Ordered.$greater$:(Lscala/math/Ordered;Ljava/lang/Object;)Z
  #189 = Utf8               $less$eq
  #190 = Utf8               $less$eq$
  #191 = NameAndType        #190:#182     // $less$eq$:(Lscala/math/Ordered;Ljava/lang/Object;)Z
  #192 = InterfaceMethodref #180.#191     // scala/math/Ordered.$less$eq$:(Lscala/math/Ordered;Ljava/lang/Object;)Z
  #193 = Utf8               $greater$eq
  #194 = Utf8               $greater$eq$
  #195 = NameAndType        #194:#182     // $greater$eq$:(Lscala/math/Ordered;Ljava/lang/Object;)Z
  #196 = InterfaceMethodref #180.#195     // scala/math/Ordered.$greater$eq$:(Lscala/math/Ordered;Ljava/lang/Object;)Z
  #197 = Utf8               compareTo
  #198 = Utf8               compareTo$
  #199 = Utf8               (Lscala/math/Ordered;Ljava/lang/Object;)I
  #200 = NameAndType        #198:#199     // compareTo$:(Lscala/math/Ordered;Ljava/lang/Object;)I
  #201 = InterfaceMethodref #180.#200     // scala/math/Ordered.compareTo$:(Lscala/math/Ordered;Ljava/lang/Object;)I
  #202 = Utf8               toString
  #203 = Utf8               ()Ljava/lang/String;
  #204 = Utf8               scala/Proxy
  #205 = Class              #204          // scala/Proxy
  #206 = Utf8               toString$
  #207 = Utf8               (Lscala/Proxy;)Ljava/lang/String;
  #208 = NameAndType        #206:#207     // toString$:(Lscala/Proxy;)Ljava/lang/String;
  #209 = InterfaceMethodref #205.#208     // scala/Proxy.toString$:(Lscala/Proxy;)Ljava/lang/String;
  #210 = Utf8               toChar
  #211 = Utf8               ()C
  #212 = Utf8               scala/math/ScalaNumericAnyConversions
  #213 = Class              #212          // scala/math/ScalaNumericAnyConversions
  #214 = Utf8               toChar$
  #215 = Utf8               (Lscala/math/ScalaNumericAnyConversions;)C
  #216 = NameAndType        #214:#215     // toChar$:(Lscala/math/ScalaNumericAnyConversions;)C
  #217 = InterfaceMethodref #213.#216     // scala/math/ScalaNumericAnyConversions.toChar$:(Lscala/math/ScalaNumericAnyConversions;)C
  #218 = Utf8               toByte
  #219 = Utf8               ()B
  #220 = Utf8               toByte$
  #221 = Utf8               (Lscala/math/ScalaNumericAnyConversions;)B
  #222 = NameAndType        #220:#221     // toByte$:(Lscala/math/ScalaNumericAnyConversions;)B
  #223 = InterfaceMethodref #213.#222     // scala/math/ScalaNumericAnyConversions.toByte$:(Lscala/math/ScalaNumericAnyConversions;)B
  #224 = Utf8               toShort
  #225 = Utf8               ()S
  #226 = Utf8               toShort$
  #227 = Utf8               (Lscala/math/ScalaNumericAnyConversions;)S
  #228 = NameAndType        #226:#227     // toShort$:(Lscala/math/ScalaNumericAnyConversions;)S
  #229 = InterfaceMethodref #213.#228     // scala/math/ScalaNumericAnyConversions.toShort$:(Lscala/math/ScalaNumericAnyConversions;)S
  #230 = Utf8               toInt
  #231 = Utf8               toInt$
  #232 = Utf8               (Lscala/math/ScalaNumericAnyConversions;)I
  #233 = NameAndType        #231:#232     // toInt$:(Lscala/math/ScalaNumericAnyConversions;)I
  #234 = InterfaceMethodref #213.#233     // scala/math/ScalaNumericAnyConversions.toInt$:(Lscala/math/ScalaNumericAnyConversions;)I
  #235 = Utf8               toLong
  #236 = Utf8               ()J
  #237 = Utf8               toLong$
  #238 = Utf8               (Lscala/math/ScalaNumericAnyConversions;)J
  #239 = NameAndType        #237:#238     // toLong$:(Lscala/math/ScalaNumericAnyConversions;)J
  #240 = InterfaceMethodref #213.#239     // scala/math/ScalaNumericAnyConversions.toLong$:(Lscala/math/ScalaNumericAnyConversions;)J
  #241 = Utf8               toFloat
  #242 = Utf8               ()F
  #243 = Utf8               toFloat$
  #244 = Utf8               (Lscala/math/ScalaNumericAnyConversions;)F
  #245 = NameAndType        #243:#244     // toFloat$:(Lscala/math/ScalaNumericAnyConversions;)F
  #246 = InterfaceMethodref #213.#245     // scala/math/ScalaNumericAnyConversions.toFloat$:(Lscala/math/ScalaNumericAnyConversions;)F
  #247 = Utf8               toDouble
  #248 = Utf8               ()D
  #249 = Utf8               toDouble$
  #250 = Utf8               (Lscala/math/ScalaNumericAnyConversions;)D
  #251 = NameAndType        #249:#250     // toDouble$:(Lscala/math/ScalaNumericAnyConversions;)D
  #252 = InterfaceMethodref #213.#251     // scala/math/ScalaNumericAnyConversions.toDouble$:(Lscala/math/ScalaNumericAnyConversions;)D
  #253 = Utf8               unifiedPrimitiveHashcode
  #254 = Utf8               unifiedPrimitiveHashcode$
  #255 = NameAndType        #254:#232     // unifiedPrimitiveHashcode$:(Lscala/math/ScalaNumericAnyConversions;)I
  #256 = InterfaceMethodref #213.#255     // scala/math/ScalaNumericAnyConversions.unifiedPrimitiveHashcode$:(Lscala/math/ScalaNumericAnyConversions;)I
  #257 = Utf8               unifiedPrimitiveEquals
  #258 = Utf8               x
  #259 = Utf8               unifiedPrimitiveEquals$
  #260 = Utf8               (Lscala/math/ScalaNumericAnyConversions;Ljava/lang/Object;)Z
  #261 = NameAndType        #259:#260     // unifiedPrimitiveEquals$:(Lscala/math/ScalaNumericAnyConversions;Ljava/lang/Object;)Z
  #262 = InterfaceMethodref #213.#261     // scala/math/ScalaNumericAnyConversions.unifiedPrimitiveEquals$:(Lscala/math/ScalaNumericAnyConversions;Ljava/lang/Object;)Z
  #263 = NameAndType        #30:#31       // self:J
  #264 = Fieldref           #2.#263       // scala/runtime/RichLong.self:J
  #265 = Utf8               num
  #266 = Utf8               ()Lscala/math/Numeric$LongIsIntegral$;
  #267 = NameAndType        #30:#236      // self:()J
  #268 = Methodref          #2.#267       // scala/runtime/RichLong.self:()J
  #269 = Utf8               ord
  #270 = Utf8               ()Lscala/math/Ordering$Long$;
  #271 = Utf8               doubleValue
  #272 = Utf8               floatValue
  #273 = Utf8               longValue
  #274 = Utf8               intValue
  #275 = Utf8               byteValue
  #276 = Utf8               shortValue
  #277 = Utf8               isValidByte
  #278 = Utf8               isValidShort
  #279 = Utf8               isValidChar
  #280 = Utf8               isValidInt
  #281 = Utf8               isValidLong
  #282 = Utf8               abs$extension_$this
  #283 = Utf8               max$extension_$this
  #284 = Utf8               min$extension_$this
  #285 = Utf8               round
  #286 = Utf8               equals
  #287 = Utf8               (Ljava/lang/Object;Ljava/lang/Object;)Lscala/collection/immutable/IndexedSeq;
  #288 = NameAndType        #136:#142     // to:(Ljava/lang/Object;Ljava/lang/Object;)Lscala/collection/immutable/NumericRange$Inclusive;
  #289 = Methodref          #2.#288       // scala/runtime/RichLong.to:(Ljava/lang/Object;Ljava/lang/Object;)Lscala/collection/immutable/NumericRange$Inclusive;
  #290 = Utf8               (Ljava/lang/Object;)Ljava/lang/Object;
  #291 = NameAndType        #136:#137     // to:(Ljava/lang/Object;)Lscala/collection/immutable/NumericRange$Inclusive;
  #292 = Methodref          #2.#291       // scala/runtime/RichLong.to:(Ljava/lang/Object;)Lscala/collection/immutable/NumericRange$Inclusive;
  #293 = NameAndType        #122:#131     // until:(Ljava/lang/Object;Ljava/lang/Object;)Lscala/collection/immutable/NumericRange$Exclusive;
  #294 = Methodref          #2.#293       // scala/runtime/RichLong.until:(Ljava/lang/Object;Ljava/lang/Object;)Lscala/collection/immutable/NumericRange$Exclusive;
  #295 = NameAndType        #122:#123     // until:(Ljava/lang/Object;)Lscala/collection/immutable/NumericRange$Exclusive;
  #296 = Methodref          #2.#295       // scala/runtime/RichLong.until:(Ljava/lang/Object;)Lscala/collection/immutable/NumericRange$Exclusive;
  #297 = Utf8               scala/runtime/BoxesRunTime
  #298 = Class              #297          // scala/runtime/BoxesRunTime
  #299 = Utf8               unboxToLong
  #300 = Utf8               (Ljava/lang/Object;)J
  #301 = NameAndType        #299:#300     // unboxToLong:(Ljava/lang/Object;)J
  #302 = Methodref          #298.#301     // scala/runtime/BoxesRunTime.unboxToLong:(Ljava/lang/Object;)J
  #303 = Utf8               valueOf
  #304 = Utf8               (J)Ljava/lang/Long;
  #305 = NameAndType        #303:#304     // valueOf:(J)Ljava/lang/Long;
  #306 = Methodref          #48.#305      // java/lang/Long.valueOf:(J)Ljava/lang/Long;
  #307 = Utf8               min$extension_that
  #308 = Utf8               max$extension_that
  #309 = Utf8               ()Lscala/math/Ordering;
  #310 = Utf8               ()Lscala/math/Numeric;
  #311 = Utf8               ()Lscala/math/Integral;
  #312 = Utf8               boxToLong
  #313 = NameAndType        #312:#304     // boxToLong:(J)Ljava/lang/Long;
  #314 = Methodref          #298.#313     // scala/runtime/BoxesRunTime.boxToLong:(J)Ljava/lang/Long;
  #315 = Utf8               <init>
  #316 = Utf8               (J)V
  #317 = Utf8               ()V
  #318 = NameAndType        #315:#317     // "<init>":()V
  #319 = Methodref          #5.#318       // java/lang/Object."<init>":()V
  #320 = Utf8               Code
  #321 = Utf8               LocalVariableTable
  #322 = Utf8               MethodParameters
  #323 = Utf8               LineNumberTable
  #324 = Utf8               Deprecated
  #325 = Utf8               InnerClasses
  #326 = Utf8               Signature
  #327 = Utf8               SourceFile
  #328 = Utf8               RuntimeVisibleAnnotations
  #329 = Utf8               ScalaInlineInfo
  #330 = Utf8               ScalaSig
{
  private final long self;
    descriptor: J
    flags: (0x0012) ACC_PRIVATE, ACC_FINAL

  public static boolean equals$extension(long, java.lang.Object);
    descriptor: (JLjava/lang/Object;)Z
    flags: (0x0009) ACC_PUBLIC, ACC_STATIC
    Code:
      stack=4, locals=3, args_size=2
         0: getstatic     #41                 // Field scala/runtime/RichLong$.MODULE$:Lscala/runtime/RichLong$;
         3: lload_0
         4: aload_2
         5: invokevirtual #43                 // Method scala/runtime/RichLong$.equals$extension:(JLjava/lang/Object;)Z
         8: ireturn
      LocalVariableTable:
        Start  Length  Slot  Name   Signature
            0       9     0 $this   J
            0       9     2   x$1   Ljava/lang/Object;
    MethodParameters:
      Name                           Flags
      $this                          final
      x$1                            final

  public static int hashCode$extension(long);
    descriptor: (J)I
    flags: (0x0009) ACC_PUBLIC, ACC_STATIC
    Code:
      stack=2, locals=2, args_size=1
         0: getstatic     #41                 // Field scala/runtime/RichLong$.MODULE$:Lscala/runtime/RichLong$;
         3: pop
         4: lload_0
         5: invokestatic  #51                 // Method java/lang/Long.hashCode:(J)I
         8: ireturn
      LineNumberTable:
        line 16: 4
      LocalVariableTable:
        Start  Length  Slot  Name   Signature
            0       9     0 $this   J
    MethodParameters:
      Name                           Flags
      $this                          final

  public static java.lang.String toOctalString$extension(long);
    descriptor: (J)Ljava/lang/String;
    flags: (0x0009) ACC_PUBLIC, ACC_STATIC
    Code:
      stack=2, locals=2, args_size=1
         0: getstatic     #41                 // Field scala/runtime/RichLong$.MODULE$:Lscala/runtime/RichLong$;
         3: pop
         4: lload_0
         5: invokestatic  #56                 // Method java/lang/Long.toOctalString:(J)Ljava/lang/String;
         8: areturn
      LineNumberTable:
        line 48: 4
      LocalVariableTable:
        Start  Length  Slot  Name   Signature
            0       9     0 $this   J
    MethodParameters:
      Name                           Flags
      $this                          final

  public static java.lang.String toHexString$extension(long);
    descriptor: (J)Ljava/lang/String;
    flags: (0x0009) ACC_PUBLIC, ACC_STATIC
    Code:
      stack=2, locals=2, args_size=1
         0: getstatic     #41                 // Field scala/runtime/RichLong$.MODULE$:Lscala/runtime/RichLong$;
         3: pop
         4: lload_0
         5: invokestatic  #60                 // Method java/lang/Long.toHexString:(J)Ljava/lang/String;
         8: areturn
      LineNumberTable:
        line 47: 4
      LocalVariableTable:
        Start  Length  Slot  Name   Signature
            0       9     0 $this   J
    MethodParameters:
      Name                           Flags
      $this                          final

  public static java.lang.String toBinaryString$extension(long);
    descriptor: (J)Ljava/lang/String;
    flags: (0x0009) ACC_PUBLIC, ACC_STATIC
    Code:
      stack=2, locals=2, args_size=1
         0: getstatic     #41                 // Field scala/runtime/RichLong$.MODULE$:Lscala/runtime/RichLong$;
         3: pop
         4: lload_0
         5: invokestatic  #64                 // Method java/lang/Long.toBinaryString:(J)Ljava/lang/String;
         8: areturn
      LineNumberTable:
        line 46: 4
      LocalVariableTable:
        Start  Length  Slot  Name   Signature
            0       9     0 $this   J
    MethodParameters:
      Name                           Flags
      $this                          final

  public static long round$extension(long);
    descriptor: (J)J
    flags: (0x0009) ACC_PUBLIC, ACC_STATIC
    Code:
      stack=2, locals=2, args_size=1
         0: getstatic     #41                 // Field scala/runtime/RichLong$.MODULE$:Lscala/runtime/RichLong$;
         3: pop
         4: lload_0
         5: lreturn
      LocalVariableTable:
        Start  Length  Slot  Name   Signature
            0       6     0 $this   J
    Deprecated: true
    MethodParameters:
      Name                           Flags
      $this                          final

  public static long min$extension(long, long);
    descriptor: (JJ)J
    flags: (0x0009) ACC_PUBLIC, ACC_STATIC
    Code:
      stack=4, locals=4, args_size=2
         0: getstatic     #41                 // Field scala/runtime/RichLong$.MODULE$:Lscala/runtime/RichLong$;
         3: pop
         4: getstatic     #74                 // Field scala/math/package$.MODULE$:Lscala/math/package$;
         7: pop
         8: lload_0
         9: lload_2
        10: invokestatic  #79                 // Method java/lang/Math.min:(JJ)J
        13: lreturn
      LineNumberTable:
        line 40: 4
      LocalVariableTable:
        Start  Length  Slot  Name   Signature
            0      14     0 $this   J
            0      14     2  that   J
    MethodParameters:
      Name                           Flags
      $this                          final
      that                           final

  public static long max$extension(long, long);
    descriptor: (JJ)J
    flags: (0x0009) ACC_PUBLIC, ACC_STATIC
    Code:
      stack=4, locals=4, args_size=2
         0: getstatic     #41                 // Field scala/runtime/RichLong$.MODULE$:Lscala/runtime/RichLong$;
         3: pop
         4: getstatic     #74                 // Field scala/math/package$.MODULE$:Lscala/math/package$;
         7: pop
         8: lload_0
         9: lload_2
        10: invokestatic  #83                 // Method java/lang/Math.max:(JJ)J
        13: lreturn
      LineNumberTable:
        line 39: 4
      LocalVariableTable:
        Start  Length  Slot  Name   Signature
            0      14     0 $this   J
            0      14     2  that   J
    MethodParameters:
      Name                           Flags
      $this                          final
      that                           final

  public static long abs$extension(long);
    descriptor: (J)J
    flags: (0x0009) ACC_PUBLIC, ACC_STATIC
    Code:
      stack=2, locals=2, args_size=1
         0: getstatic     #41                 // Field scala/runtime/RichLong$.MODULE$:Lscala/runtime/RichLong$;
         3: pop
         4: getstatic     #74                 // Field scala/math/package$.MODULE$:Lscala/math/package$;
         7: pop
         8: lload_0
         9: invokestatic  #87                 // Method java/lang/Math.abs:(J)J
        12: lreturn
      LineNumberTable:
        line 38: 4
      LocalVariableTable:
        Start  Length  Slot  Name   Signature
            0      13     0 $this   J
    MethodParameters:
      Name                           Flags
      $this                          final

  public static boolean isValidLong$extension(long);
    descriptor: (J)Z
    flags: (0x0009) ACC_PUBLIC, ACC_STATIC
    Code:
      stack=1, locals=2, args_size=1
         0: getstatic     #41                 // Field scala/runtime/RichLong$.MODULE$:Lscala/runtime/RichLong$;
         3: pop
         4: iconst_1
         5: ireturn
      LineNumberTable:
        line 31: 4
      LocalVariableTable:
        Start  Length  Slot  Name   Signature
            0       6     0 $this   J
    MethodParameters:
      Name                           Flags
      $this                          final

  public static boolean isValidInt$extension(long);
    descriptor: (J)Z
    flags: (0x0009) ACC_PUBLIC, ACC_STATIC
    Code:
      stack=3, locals=2, args_size=1
         0: getstatic     #41                 // Field scala/runtime/RichLong$.MODULE$:Lscala/runtime/RichLong$;
         3: lload_0
         4: invokevirtual #92                 // Method scala/runtime/RichLong$.isValidInt$extension:(J)Z
         7: ireturn
      LocalVariableTable:
        Start  Length  Slot  Name   Signature
            0       8     0 $this   J
    MethodParameters:
      Name                           Flags
      $this                          final

  public static boolean isValidChar$extension(long);
    descriptor: (J)Z
    flags: (0x0009) ACC_PUBLIC, ACC_STATIC
    Code:
      stack=3, locals=2, args_size=1
         0: getstatic     #41                 // Field scala/runtime/RichLong$.MODULE$:Lscala/runtime/RichLong$;
         3: lload_0
         4: invokevirtual #95                 // Method scala/runtime/RichLong$.isValidChar$extension:(J)Z
         7: ireturn
      LocalVariableTable:
        Start  Length  Slot  Name   Signature
            0       8     0 $this   J
    MethodParameters:
      Name                           Flags
      $this                          final

  public static boolean isValidShort$extension(long);
    descriptor: (J)Z
    flags: (0x0009) ACC_PUBLIC, ACC_STATIC
    Code:
      stack=3, locals=2, args_size=1
         0: getstatic     #41                 // Field scala/runtime/RichLong$.MODULE$:Lscala/runtime/RichLong$;
         3: lload_0
         4: invokevirtual #98                 // Method scala/runtime/RichLong$.isValidShort$extension:(J)Z
         7: ireturn
      LocalVariableTable:
        Start  Length  Slot  Name   Signature
            0       8     0 $this   J
    MethodParameters:
      Name                           Flags
      $this                          final

  public static boolean isValidByte$extension(long);
    descriptor: (J)Z
    flags: (0x0009) ACC_PUBLIC, ACC_STATIC
    Code:
      stack=3, locals=2, args_size=1
         0: getstatic     #41                 // Field scala/runtime/RichLong$.MODULE$:Lscala/runtime/RichLong$;
         3: lload_0
         4: invokevirtual #101                // Method scala/runtime/RichLong$.isValidByte$extension:(J)Z
         7: ireturn
      LocalVariableTable:
        Start  Length  Slot  Name   Signature
            0       8     0 $this   J
    MethodParameters:
      Name                           Flags
      $this                          final

  public static short shortValue$extension(long);
    descriptor: (J)S
    flags: (0x0009) ACC_PUBLIC, ACC_STATIC
    Code:
      stack=2, locals=2, args_size=1
         0: getstatic     #41                 // Field scala/runtime/RichLong$.MODULE$:Lscala/runtime/RichLong$;
         3: pop
         4: lload_0
         5: l2i
         6: i2s
         7: ireturn
      LineNumberTable:
        line 25: 4
      LocalVariableTable:
        Start  Length  Slot  Name   Signature
            0       8     0 $this   J
    MethodParameters:
      Name                           Flags
      $this                          final

  public static byte byteValue$extension(long);
    descriptor: (J)B
    flags: (0x0009) ACC_PUBLIC, ACC_STATIC
    Code:
      stack=2, locals=2, args_size=1
         0: getstatic     #41                 // Field scala/runtime/RichLong$.MODULE$:Lscala/runtime/RichLong$;
         3: pop
         4: lload_0
         5: l2i
         6: i2b
         7: ireturn
      LineNumberTable:
        line 24: 4
      LocalVariableTable:
        Start  Length  Slot  Name   Signature
            0       8     0 $this   J
    MethodParameters:
      Name                           Flags
      $this                          final

  public static int intValue$extension(long);
    descriptor: (J)I
    flags: (0x0009) ACC_PUBLIC, ACC_STATIC
    Code:
      stack=2, locals=2, args_size=1
         0: getstatic     #41                 // Field scala/runtime/RichLong$.MODULE$:Lscala/runtime/RichLong$;
         3: pop
         4: lload_0
         5: l2i
         6: ireturn
      LineNumberTable:
        line 23: 4
      LocalVariableTable:
        Start  Length  Slot  Name   Signature
            0       7     0 $this   J
    MethodParameters:
      Name                           Flags
      $this                          final

  public static long longValue$extension(long);
    descriptor: (J)J
    flags: (0x0009) ACC_PUBLIC, ACC_STATIC
    Code:
      stack=2, locals=2, args_size=1
         0: getstatic     #41                 // Field scala/runtime/RichLong$.MODULE$:Lscala/runtime/RichLong$;
         3: pop
         4: lload_0
         5: lreturn
      LocalVariableTable:
        Start  Length  Slot  Name   Signature
            0       6     0 $this   J
    MethodParameters:
      Name                           Flags
      $this                          final

  public static float floatValue$extension(long);
    descriptor: (J)F
    flags: (0x0009) ACC_PUBLIC, ACC_STATIC
    Code:
      stack=2, locals=2, args_size=1
         0: getstatic     #41                 // Field scala/runtime/RichLong$.MODULE$:Lscala/runtime/RichLong$;
         3: pop
         4: lload_0
         5: l2f
         6: freturn
      LineNumberTable:
        line 21: 4
      LocalVariableTable:
        Start  Length  Slot  Name   Signature
            0       7     0 $this   J
    MethodParameters:
      Name                           Flags
      $this                          final

  public static double doubleValue$extension(long);
    descriptor: (J)D
    flags: (0x0009) ACC_PUBLIC, ACC_STATIC
    Code:
      stack=2, locals=2, args_size=1
         0: getstatic     #41                 // Field scala/runtime/RichLong$.MODULE$:Lscala/runtime/RichLong$;
         3: pop
         4: lload_0
         5: l2d
         6: dreturn
      LineNumberTable:
        line 20: 4
      LocalVariableTable:
        Start  Length  Slot  Name   Signature
            0       7     0 $this   J
    MethodParameters:
      Name                           Flags
      $this                          final

  public static scala.math.Ordering$Long$ ord$extension(long);
    descriptor: (J)Lscala/math/Ordering$Long$;
    flags: (0x0009) ACC_PUBLIC, ACC_STATIC
    Code:
      stack=1, locals=2, args_size=1
         0: getstatic     #41                 // Field scala/runtime/RichLong$.MODULE$:Lscala/runtime/RichLong$;
         3: pop
         4: getstatic     #116                // Field scala/math/Ordering$Long$.MODULE$:Lscala/math/Ordering$Long$;
         7: areturn
      LineNumberTable:
        line 18: 4
      LocalVariableTable:
        Start  Length  Slot  Name   Signature
            0       8     0 $this   J
    MethodParameters:
      Name                           Flags
      $this                          final

  public static scala.math.Numeric$LongIsIntegral$ num$extension(long);
    descriptor: (J)Lscala/math/Numeric$LongIsIntegral$;
    flags: (0x0009) ACC_PUBLIC, ACC_STATIC
    Code:
      stack=1, locals=2, args_size=1
         0: getstatic     #41                 // Field scala/runtime/RichLong$.MODULE$:Lscala/runtime/RichLong$;
         3: pop
         4: getstatic     #121                // Field scala/math/Numeric$LongIsIntegral$.MODULE$:Lscala/math/Numeric$LongIsIntegral$;
         7: areturn
      LineNumberTable:
        line 17: 4
      LocalVariableTable:
        Start  Length  Slot  Name   Signature
            0       8     0 $this   J
    MethodParameters:
      Name                           Flags
      $this                          final

  public scala.collection.immutable.NumericRange$Exclusive until(java.lang.Object);
    descriptor: (Ljava/lang/Object;)Lscala/collection/immutable/NumericRange$Exclusive;
    flags: (0x0001) ACC_PUBLIC
    Code:
      stack=2, locals=2, args_size=2
         0: aload_0
         1: aload_1
         2: invokestatic  #128                // InterfaceMethod scala/runtime/IntegralProxy.until$:(Lscala/runtime/IntegralProxy;Ljava/lang/Object;)Lscala/collection/immutable/NumericRange$Exclusive;
         5: areturn
      LineNumberTable:
        line 16: 0
      LocalVariableTable:
        Start  Length  Slot  Name   Signature
            0       6     0  this   Lscala/runtime/RichLong;
            0       6     1   end   Ljava/lang/Object;
    MethodParameters:
      Name                           Flags
      end                            final

  public scala.collection.immutable.NumericRange$Exclusive until(java.lang.Object, java.lang.Object);
    descriptor: (Ljava/lang/Object;Ljava/lang/Object;)Lscala/collection/immutable/NumericRange$Exclusive;
    flags: (0x0001) ACC_PUBLIC
    Code:
      stack=3, locals=3, args_size=3
         0: aload_0
         1: aload_1
         2: aload_2
         3: invokestatic  #135                // InterfaceMethod scala/runtime/IntegralProxy.until$:(Lscala/runtime/IntegralProxy;Ljava/lang/Object;Ljava/lang/Object;)Lscala/collection/immutable/NumericRange$Exclusive;
         6: areturn
      LineNumberTable:
        line 16: 0
      LocalVariableTable:
        Start  Length  Slot  Name   Signature
            0       7     0  this   Lscala/runtime/RichLong;
            0       7     1   end   Ljava/lang/Object;
            0       7     2  step   Ljava/lang/Object;
    MethodParameters:
      Name                           Flags
      end                            final
      step                           final

  public scala.collection.immutable.NumericRange$Inclusive to(java.lang.Object);
    descriptor: (Ljava/lang/Object;)Lscala/collection/immutable/NumericRange$Inclusive;
    flags: (0x0001) ACC_PUBLIC
    Code:
      stack=2, locals=2, args_size=2
         0: aload_0
         1: aload_1
         2: invokestatic  #141                // InterfaceMethod scala/runtime/IntegralProxy.to$:(Lscala/runtime/IntegralProxy;Ljava/lang/Object;)Lscala/collection/immutable/NumericRange$Inclusive;
         5: areturn
      LineNumberTable:
        line 16: 0
      LocalVariableTable:
        Start  Length  Slot  Name   Signature
            0       6     0  this   Lscala/runtime/RichLong;
            0       6     1   end   Ljava/lang/Object;
    MethodParameters:
      Name                           Flags
      end                            final

  public scala.collection.immutable.NumericRange$Inclusive to(java.lang.Object, java.lang.Object);
    descriptor: (Ljava/lang/Object;Ljava/lang/Object;)Lscala/collection/immutable/NumericRange$Inclusive;
    flags: (0x0001) ACC_PUBLIC
    Code:
      stack=3, locals=3, args_size=3
         0: aload_0
         1: aload_1
         2: aload_2
         3: invokestatic  #145                // InterfaceMethod scala/runtime/IntegralProxy.to$:(Lscala/runtime/IntegralProxy;Ljava/lang/Object;Ljava/lang/Object;)Lscala/collection/immutable/NumericRange$Inclusive;
         6: areturn
      LineNumberTable:
        line 16: 0
      LocalVariableTable:
        Start  Length  Slot  Name   Signature
            0       7     0  this   Lscala/runtime/RichLong;
            0       7     1   end   Ljava/lang/Object;
            0       7     2  step   Ljava/lang/Object;
    MethodParameters:
      Name                           Flags
      end                            final
      step                           final

  public boolean isWhole();
    descriptor: ()Z
    flags: (0x0001) ACC_PUBLIC
    Code:
      stack=1, locals=1, args_size=1
         0: aload_0
         1: invokestatic  #153                // InterfaceMethod scala/runtime/ScalaWholeNumberProxy.isWhole$:(Lscala/runtime/ScalaWholeNumberProxy;)Z
         4: ireturn
      LineNumberTable:
        line 16: 0
      LocalVariableTable:
        Start  Length  Slot  Name   Signature
            0       5     0  this   Lscala/runtime/RichLong;

  public java.lang.Object sign();
    descriptor: ()Ljava/lang/Object;
    flags: (0x0001) ACC_PUBLIC
    Code:
      stack=1, locals=1, args_size=1
         0: aload_0
         1: invokestatic  #161                // InterfaceMethod scala/runtime/ScalaNumberProxy.sign$:(Lscala/runtime/ScalaNumberProxy;)Ljava/lang/Object;
         4: areturn
      LineNumberTable:
        line 16: 0
      LocalVariableTable:
        Start  Length  Slot  Name   Signature
            0       5     0  this   Lscala/runtime/RichLong;

  public int signum();
    descriptor: ()I
    flags: (0x0001) ACC_PUBLIC
    Code:
      stack=1, locals=1, args_size=1
         0: aload_0
         1: invokestatic  #167                // InterfaceMethod scala/runtime/ScalaNumberProxy.signum$:(Lscala/runtime/ScalaNumberProxy;)I
         4: ireturn
      LineNumberTable:
        line 16: 0
      LocalVariableTable:
        Start  Length  Slot  Name   Signature
            0       5     0  this   Lscala/runtime/RichLong;
    Deprecated: true

  public int compare(java.lang.Object);
    descriptor: (Ljava/lang/Object;)I
    flags: (0x0001) ACC_PUBLIC
    Code:
      stack=2, locals=2, args_size=2
         0: aload_0
         1: aload_1
         2: invokestatic  #176                // InterfaceMethod scala/runtime/OrderedProxy.compare$:(Lscala/runtime/OrderedProxy;Ljava/lang/Object;)I
         5: ireturn
      LineNumberTable:
        line 16: 0
      LocalVariableTable:
        Start  Length  Slot  Name   Signature
            0       6     0  this   Lscala/runtime/RichLong;
            0       6     1     y   Ljava/lang/Object;
    MethodParameters:
      Name                           Flags
      y                              final

  public boolean $less(java.lang.Object);
    descriptor: (Ljava/lang/Object;)Z
    flags: (0x0001) ACC_PUBLIC
    Code:
      stack=2, locals=2, args_size=2
         0: aload_0
         1: aload_1
         2: invokestatic  #184                // InterfaceMethod scala/math/Ordered.$less$:(Lscala/math/Ordered;Ljava/lang/Object;)Z
         5: ireturn
      LineNumberTable:
        line 16: 0
      LocalVariableTable:
        Start  Length  Slot  Name   Signature
            0       6     0  this   Lscala/runtime/RichLong;
            0       6     1  that   Ljava/lang/Object;
    MethodParameters:
      Name                           Flags
      that                           final

  public boolean $greater(java.lang.Object);
    descriptor: (Ljava/lang/Object;)Z
    flags: (0x0001) ACC_PUBLIC
    Code:
      stack=2, locals=2, args_size=2
         0: aload_0
         1: aload_1
         2: invokestatic  #188                // InterfaceMethod scala/math/Ordered.$greater$:(Lscala/math/Ordered;Ljava/lang/Object;)Z
         5: ireturn
      LineNumberTable:
        line 16: 0
      LocalVariableTable:
        Start  Length  Slot  Name   Signature
            0       6     0  this   Lscala/runtime/RichLong;
            0       6     1  that   Ljava/lang/Object;
    MethodParameters:
      Name                           Flags
      that                           final

  public boolean $less$eq(java.lang.Object);
    descriptor: (Ljava/lang/Object;)Z
    flags: (0x0001) ACC_PUBLIC
    Code:
      stack=2, locals=2, args_size=2
         0: aload_0
         1: aload_1
         2: invokestatic  #192                // InterfaceMethod scala/math/Ordered.$less$eq$:(Lscala/math/Ordered;Ljava/lang/Object;)Z
         5: ireturn
      LineNumberTable:
        line 16: 0
      LocalVariableTable:
        Start  Length  Slot  Name   Signature
            0       6     0  this   Lscala/runtime/RichLong;
            0       6     1  that   Ljava/lang/Object;
    MethodParameters:
      Name                           Flags
      that                           final

  public boolean $greater$eq(java.lang.Object);
    descriptor: (Ljava/lang/Object;)Z
    flags: (0x0001) ACC_PUBLIC
    Code:
      stack=2, locals=2, args_size=2
         0: aload_0
         1: aload_1
         2: invokestatic  #196                // InterfaceMethod scala/math/Ordered.$greater$eq$:(Lscala/math/Ordered;Ljava/lang/Object;)Z
         5: ireturn
      LineNumberTable:
        line 16: 0
      LocalVariableTable:
        Start  Length  Slot  Name   Signature
            0       6     0  this   Lscala/runtime/RichLong;
            0       6     1  that   Ljava/lang/Object;
    MethodParameters:
      Name                           Flags
      that                           final

  public int compareTo(java.lang.Object);
    descriptor: (Ljava/lang/Object;)I
    flags: (0x0001) ACC_PUBLIC
    Code:
      stack=2, locals=2, args_size=2
         0: aload_0
         1: aload_1
         2: invokestatic  #201                // InterfaceMethod scala/math/Ordered.compareTo$:(Lscala/math/Ordered;Ljava/lang/Object;)I
         5: ireturn
      LineNumberTable:
        line 16: 0
      LocalVariableTable:
        Start  Length  Slot  Name   Signature
            0       6     0  this   Lscala/runtime/RichLong;
            0       6     1  that   Ljava/lang/Object;
    MethodParameters:
      Name                           Flags
      that                           final

  public java.lang.String toString();
    descriptor: ()Ljava/lang/String;
    flags: (0x0001) ACC_PUBLIC
    Code:
      stack=1, locals=1, args_size=1
         0: aload_0
         1: invokestatic  #209                // InterfaceMethod scala/Proxy.toString$:(Lscala/Proxy;)Ljava/lang/String;
         4: areturn
      LineNumberTable:
        line 16: 0
      LocalVariableTable:
        Start  Length  Slot  Name   Signature
            0       5     0  this   Lscala/runtime/RichLong;

  public char toChar();
    descriptor: ()C
    flags: (0x0001) ACC_PUBLIC
    Code:
      stack=1, locals=1, args_size=1
         0: aload_0
         1: invokestatic  #217                // InterfaceMethod scala/math/ScalaNumericAnyConversions.toChar$:(Lscala/math/ScalaNumericAnyConversions;)C
         4: ireturn
      LineNumberTable:
        line 16: 0
      LocalVariableTable:
        Start  Length  Slot  Name   Signature
            0       5     0  this   Lscala/runtime/RichLong;

  public byte toByte();
    descriptor: ()B
    flags: (0x0001) ACC_PUBLIC
    Code:
      stack=1, locals=1, args_size=1
         0: aload_0
         1: invokestatic  #223                // InterfaceMethod scala/math/ScalaNumericAnyConversions.toByte$:(Lscala/math/ScalaNumericAnyConversions;)B
         4: ireturn
      LineNumberTable:
        line 16: 0
      LocalVariableTable:
        Start  Length  Slot  Name   Signature
            0       5     0  this   Lscala/runtime/RichLong;

  public short toShort();
    descriptor: ()S
    flags: (0x0001) ACC_PUBLIC
    Code:
      stack=1, locals=1, args_size=1
         0: aload_0
         1: invokestatic  #229                // InterfaceMethod scala/math/ScalaNumericAnyConversions.toShort$:(Lscala/math/ScalaNumericAnyConversions;)S
         4: ireturn
      LineNumberTable:
        line 16: 0
      LocalVariableTable:
        Start  Length  Slot  Name   Signature
            0       5     0  this   Lscala/runtime/RichLong;

  public int toInt();
    descriptor: ()I
    flags: (0x0001) ACC_PUBLIC
    Code:
      stack=1, locals=1, args_size=1
         0: aload_0
         1: invokestatic  #234                // InterfaceMethod scala/math/ScalaNumericAnyConversions.toInt$:(Lscala/math/ScalaNumericAnyConversions;)I
         4: ireturn
      LineNumberTable:
        line 16: 0
      LocalVariableTable:
        Start  Length  Slot  Name   Signature
            0       5     0  this   Lscala/runtime/RichLong;

  public long toLong();
    descriptor: ()J
    flags: (0x0001) ACC_PUBLIC
    Code:
      stack=2, locals=1, args_size=1
         0: aload_0
         1: invokestatic  #240                // InterfaceMethod scala/math/ScalaNumericAnyConversions.toLong$:(Lscala/math/ScalaNumericAnyConversions;)J
         4: lreturn
      LineNumberTable:
        line 16: 0
      LocalVariableTable:
        Start  Length  Slot  Name   Signature
            0       5     0  this   Lscala/runtime/RichLong;

  public float toFloat();
    descriptor: ()F
    flags: (0x0001) ACC_PUBLIC
    Code:
      stack=1, locals=1, args_size=1
         0: aload_0
         1: invokestatic  #246                // InterfaceMethod scala/math/ScalaNumericAnyConversions.toFloat$:(Lscala/math/ScalaNumericAnyConversions;)F
         4: freturn
      LineNumberTable:
        line 16: 0
      LocalVariableTable:
        Start  Length  Slot  Name   Signature
            0       5     0  this   Lscala/runtime/RichLong;

  public double toDouble();
    descriptor: ()D
    flags: (0x0001) ACC_PUBLIC
    Code:
      stack=2, locals=1, args_size=1
         0: aload_0
         1: invokestatic  #252                // InterfaceMethod scala/math/ScalaNumericAnyConversions.toDouble$:(Lscala/math/ScalaNumericAnyConversions;)D
         4: dreturn
      LineNumberTable:
        line 16: 0
      LocalVariableTable:
        Start  Length  Slot  Name   Signature
            0       5     0  this   Lscala/runtime/RichLong;

  public int unifiedPrimitiveHashcode();
    descriptor: ()I
    flags: (0x0001) ACC_PUBLIC
    Code:
      stack=1, locals=1, args_size=1
         0: aload_0
         1: invokestatic  #256                // InterfaceMethod scala/math/ScalaNumericAnyConversions.unifiedPrimitiveHashcode$:(Lscala/math/ScalaNumericAnyConversions;)I
         4: ireturn
      LineNumberTable:
        line 16: 0
      LocalVariableTable:
        Start  Length  Slot  Name   Signature
            0       5     0  this   Lscala/runtime/RichLong;

  public boolean unifiedPrimitiveEquals(java.lang.Object);
    descriptor: (Ljava/lang/Object;)Z
    flags: (0x0001) ACC_PUBLIC
    Code:
      stack=2, locals=2, args_size=2
         0: aload_0
         1: aload_1
         2: invokestatic  #262                // InterfaceMethod scala/math/ScalaNumericAnyConversions.unifiedPrimitiveEquals$:(Lscala/math/ScalaNumericAnyConversions;Ljava/lang/Object;)Z
         5: ireturn
      LineNumberTable:
        line 16: 0
      LocalVariableTable:
        Start  Length  Slot  Name   Signature
            0       6     0  this   Lscala/runtime/RichLong;
            0       6     1     x   Ljava/lang/Object;
    MethodParameters:
      Name                           Flags
      x                              final

  public long self();
    descriptor: ()J
    flags: (0x0001) ACC_PUBLIC
    Code:
      stack=2, locals=1, args_size=1
         0: aload_0
         1: getfield      #264                // Field self:J
         4: lreturn
      LineNumberTable:
        line 16: 0
      LocalVariableTable:
        Start  Length  Slot  Name   Signature
            0       5     0  this   Lscala/runtime/RichLong;

  public scala.math.Numeric$LongIsIntegral$ num();
    descriptor: ()Lscala/math/Numeric$LongIsIntegral$;
    flags: (0x0001) ACC_PUBLIC
    Code:
      stack=2, locals=1, args_size=1
         0: getstatic     #41                 // Field scala/runtime/RichLong$.MODULE$:Lscala/runtime/RichLong$;
         3: pop
         4: aload_0
         5: invokevirtual #268                // Method self:()J
         8: pop2
         9: getstatic     #121                // Field scala/math/Numeric$LongIsIntegral$.MODULE$:Lscala/math/Numeric$LongIsIntegral$;
        12: areturn
      LineNumberTable:
        line 17: 0
        line 17: 9
        line 17: 12
      LocalVariableTable:
        Start  Length  Slot  Name   Signature
            0      13     0  this   Lscala/runtime/RichLong;

  public scala.math.Ordering$Long$ ord();
    descriptor: ()Lscala/math/Ordering$Long$;
    flags: (0x0001) ACC_PUBLIC
    Code:
      stack=2, locals=1, args_size=1
         0: getstatic     #41                 // Field scala/runtime/RichLong$.MODULE$:Lscala/runtime/RichLong$;
         3: pop
         4: aload_0
         5: invokevirtual #268                // Method self:()J
         8: pop2
         9: getstatic     #116                // Field scala/math/Ordering$Long$.MODULE$:Lscala/math/Ordering$Long$;
        12: areturn
      LineNumberTable:
        line 18: 0
        line 18: 9
        line 18: 12
      LocalVariableTable:
        Start  Length  Slot  Name   Signature
            0      13     0  this   Lscala/runtime/RichLong;

  public double doubleValue();
    descriptor: ()D
    flags: (0x0001) ACC_PUBLIC
    Code:
      stack=2, locals=1, args_size=1
         0: getstatic     #41                 // Field scala/runtime/RichLong$.MODULE$:Lscala/runtime/RichLong$;
         3: pop
         4: aload_0
         5: invokevirtual #268                // Method self:()J
         8: l2d
         9: dreturn
      LineNumberTable:
        line 20: 0
        line 20: 8
        line 20: 9
      LocalVariableTable:
        Start  Length  Slot  Name   Signature
            0      10     0  this   Lscala/runtime/RichLong;

  public float floatValue();
    descriptor: ()F
    flags: (0x0001) ACC_PUBLIC
    Code:
      stack=2, locals=1, args_size=1
         0: getstatic     #41                 // Field scala/runtime/RichLong$.MODULE$:Lscala/runtime/RichLong$;
         3: pop
         4: aload_0
         5: invokevirtual #268                // Method self:()J
         8: l2f
         9: freturn
      LineNumberTable:
        line 21: 0
        line 21: 8
        line 21: 9
      LocalVariableTable:
        Start  Length  Slot  Name   Signature
            0      10     0  this   Lscala/runtime/RichLong;

  public long longValue();
    descriptor: ()J
    flags: (0x0001) ACC_PUBLIC
    Code:
      stack=2, locals=1, args_size=1
         0: getstatic     #41                 // Field scala/runtime/RichLong$.MODULE$:Lscala/runtime/RichLong$;
         3: pop
         4: aload_0
         5: invokevirtual #268                // Method self:()J
         8: lreturn
      LineNumberTable:
        line 22: 0
        line 22: 8
      LocalVariableTable:
        Start  Length  Slot  Name   Signature
            0       9     0  this   Lscala/runtime/RichLong;

  public int intValue();
    descriptor: ()I
    flags: (0x0001) ACC_PUBLIC
    Code:
      stack=2, locals=1, args_size=1
         0: getstatic     #41                 // Field scala/runtime/RichLong$.MODULE$:Lscala/runtime/RichLong$;
         3: pop
         4: aload_0
         5: invokevirtual #268                // Method self:()J
         8: l2i
         9: ireturn
      LineNumberTable:
        line 23: 0
        line 23: 8
        line 23: 9
      LocalVariableTable:
        Start  Length  Slot  Name   Signature
            0      10     0  this   Lscala/runtime/RichLong;

  public byte byteValue();
    descriptor: ()B
    flags: (0x0001) ACC_PUBLIC
    Code:
      stack=2, locals=1, args_size=1
         0: getstatic     #41                 // Field scala/runtime/RichLong$.MODULE$:Lscala/runtime/RichLong$;
         3: pop
         4: aload_0
         5: invokevirtual #268                // Method self:()J
         8: l2i
         9: i2b
        10: ireturn
      LineNumberTable:
        line 24: 0
        line 24: 8
        line 24: 10
      LocalVariableTable:
        Start  Length  Slot  Name   Signature
            0      11     0  this   Lscala/runtime/RichLong;

  public short shortValue();
    descriptor: ()S
    flags: (0x0001) ACC_PUBLIC
    Code:
      stack=2, locals=1, args_size=1
         0: getstatic     #41                 // Field scala/runtime/RichLong$.MODULE$:Lscala/runtime/RichLong$;
         3: pop
         4: aload_0
         5: invokevirtual #268                // Method self:()J
         8: l2i
         9: i2s
        10: ireturn
      LineNumberTable:
        line 25: 0
        line 25: 8
        line 25: 10
      LocalVariableTable:
        Start  Length  Slot  Name   Signature
            0      11     0  this   Lscala/runtime/RichLong;

  public boolean isValidByte();
    descriptor: ()Z
    flags: (0x0001) ACC_PUBLIC
    Code:
      stack=3, locals=1, args_size=1
         0: getstatic     #41                 // Field scala/runtime/RichLong$.MODULE$:Lscala/runtime/RichLong$;
         3: aload_0
         4: invokevirtual #268                // Method self:()J
         7: invokevirtual #101                // Method scala/runtime/RichLong$.isValidByte$extension:(J)Z
        10: ireturn
      LineNumberTable:
        line 27: 0
      LocalVariableTable:
        Start  Length  Slot  Name   Signature
            0      11     0  this   Lscala/runtime/RichLong;

  public boolean isValidShort();
    descriptor: ()Z
    flags: (0x0001) ACC_PUBLIC
    Code:
      stack=3, locals=1, args_size=1
         0: getstatic     #41                 // Field scala/runtime/RichLong$.MODULE$:Lscala/runtime/RichLong$;
         3: aload_0
         4: invokevirtual #268                // Method self:()J
         7: invokevirtual #98                 // Method scala/runtime/RichLong$.isValidShort$extension:(J)Z
        10: ireturn
      LineNumberTable:
        line 28: 0
      LocalVariableTable:
        Start  Length  Slot  Name   Signature
            0      11     0  this   Lscala/runtime/RichLong;

  public boolean isValidChar();
    descriptor: ()Z
    flags: (0x0001) ACC_PUBLIC
    Code:
      stack=3, locals=1, args_size=1
         0: getstatic     #41                 // Field scala/runtime/RichLong$.MODULE$:Lscala/runtime/RichLong$;
         3: aload_0
         4: invokevirtual #268                // Method self:()J
         7: invokevirtual #95                 // Method scala/runtime/RichLong$.isValidChar$extension:(J)Z
        10: ireturn
      LineNumberTable:
        line 29: 0
      LocalVariableTable:
        Start  Length  Slot  Name   Signature
            0      11     0  this   Lscala/runtime/RichLong;

  public boolean isValidInt();
    descriptor: ()Z
    flags: (0x0001) ACC_PUBLIC
    Code:
      stack=3, locals=1, args_size=1
         0: getstatic     #41                 // Field scala/runtime/RichLong$.MODULE$:Lscala/runtime/RichLong$;
         3: aload_0
         4: invokevirtual #268                // Method self:()J
         7: invokevirtual #92                 // Method scala/runtime/RichLong$.isValidInt$extension:(J)Z
        10: ireturn
      LineNumberTable:
        line 30: 0
      LocalVariableTable:
        Start  Length  Slot  Name   Signature
            0      11     0  this   Lscala/runtime/RichLong;

  public boolean isValidLong();
    descriptor: ()Z
    flags: (0x0001) ACC_PUBLIC
    Code:
      stack=2, locals=1, args_size=1
         0: getstatic     #41                 // Field scala/runtime/RichLong$.MODULE$:Lscala/runtime/RichLong$;
         3: pop
         4: aload_0
         5: invokevirtual #268                // Method self:()J
         8: pop2
         9: iconst_1
        10: ireturn
      LineNumberTable:
        line 31: 0
        line 31: 9
        line 31: 10
      LocalVariableTable:
        Start  Length  Slot  Name   Signature
            0      11     0  this   Lscala/runtime/RichLong;

  public long abs();
    descriptor: ()J
    flags: (0x0001) ACC_PUBLIC
    Code:
      stack=2, locals=3, args_size=1
         0: getstatic     #41                 // Field scala/runtime/RichLong$.MODULE$:Lscala/runtime/RichLong$;
         3: pop
         4: aload_0
         5: invokevirtual #268                // Method self:()J
         8: lstore_1
         9: getstatic     #74                 // Field scala/math/package$.MODULE$:Lscala/math/package$;
        12: pop
        13: lload_1
        14: invokestatic  #87                 // Method java/lang/Math.abs:(J)J
        17: lreturn
      LineNumberTable:
        line 38: 0
        line 38: 9
        line 38: 17
      LocalVariableTable:
        Start  Length  Slot  Name   Signature
            0      18     0  this   Lscala/runtime/RichLong;
            9       8     1 abs$extension_$this   J

  public long max(long);
    descriptor: (J)J
    flags: (0x0001) ACC_PUBLIC
    Code:
      stack=4, locals=5, args_size=2
         0: getstatic     #41                 // Field scala/runtime/RichLong$.MODULE$:Lscala/runtime/RichLong$;
         3: pop
         4: aload_0
         5: invokevirtual #268                // Method self:()J
         8: lstore_3
         9: getstatic     #74                 // Field scala/math/package$.MODULE$:Lscala/math/package$;
        12: pop
        13: lload_3
        14: lload_1
        15: invokestatic  #83                 // Method java/lang/Math.max:(JJ)J
        18: lreturn
      LineNumberTable:
        line 39: 0
        line 39: 9
        line 39: 18
      LocalVariableTable:
        Start  Length  Slot  Name   Signature
            0      19     0  this   Lscala/runtime/RichLong;
            0      19     1  that   J
            9       9     3 max$extension_$this   J
    MethodParameters:
      Name                           Flags
      that                           final

  public long min(long);
    descriptor: (J)J
    flags: (0x0001) ACC_PUBLIC
    Code:
      stack=4, locals=5, args_size=2
         0: getstatic     #41                 // Field scala/runtime/RichLong$.MODULE$:Lscala/runtime/RichLong$;
         3: pop
         4: aload_0
         5: invokevirtual #268                // Method self:()J
         8: lstore_3
         9: getstatic     #74                 // Field scala/math/package$.MODULE$:Lscala/math/package$;
        12: pop
        13: lload_3
        14: lload_1
        15: invokestatic  #79                 // Method java/lang/Math.min:(JJ)J
        18: lreturn
      LineNumberTable:
        line 40: 0
        line 40: 9
        line 40: 18
      LocalVariableTable:
        Start  Length  Slot  Name   Signature
            0      19     0  this   Lscala/runtime/RichLong;
            0      19     1  that   J
            9       9     3 min$extension_$this   J
    MethodParameters:
      Name                           Flags
      that                           final

  public long round();
    descriptor: ()J
    flags: (0x0001) ACC_PUBLIC
    Code:
      stack=2, locals=1, args_size=1
         0: getstatic     #41                 // Field scala/runtime/RichLong$.MODULE$:Lscala/runtime/RichLong$;
         3: pop
         4: aload_0
         5: invokevirtual #268                // Method self:()J
         8: lreturn
      LineNumberTable:
        line 44: 0
        line 44: 8
      LocalVariableTable:
        Start  Length  Slot  Name   Signature
            0       9     0  this   Lscala/runtime/RichLong;
    Deprecated: true

  public java.lang.String toBinaryString();
    descriptor: ()Ljava/lang/String;
    flags: (0x0001) ACC_PUBLIC
    Code:
      stack=2, locals=1, args_size=1
         0: getstatic     #41                 // Field scala/runtime/RichLong$.MODULE$:Lscala/runtime/RichLong$;
         3: pop
         4: aload_0
         5: invokevirtual #268                // Method self:()J
         8: invokestatic  #64                 // Method java/lang/Long.toBinaryString:(J)Ljava/lang/String;
        11: areturn
      LineNumberTable:
        line 46: 0
        line 46: 8
        line 46: 11
      LocalVariableTable:
        Start  Length  Slot  Name   Signature
            0      12     0  this   Lscala/runtime/RichLong;

  public java.lang.String toHexString();
    descriptor: ()Ljava/lang/String;
    flags: (0x0001) ACC_PUBLIC
    Code:
      stack=2, locals=1, args_size=1
         0: getstatic     #41                 // Field scala/runtime/RichLong$.MODULE$:Lscala/runtime/RichLong$;
         3: pop
         4: aload_0
         5: invokevirtual #268                // Method self:()J
         8: invokestatic  #60                 // Method java/lang/Long.toHexString:(J)Ljava/lang/String;
        11: areturn
      LineNumberTable:
        line 47: 0
        line 47: 8
        line 47: 11
      LocalVariableTable:
        Start  Length  Slot  Name   Signature
            0      12     0  this   Lscala/runtime/RichLong;

  public java.lang.String toOctalString();
    descriptor: ()Ljava/lang/String;
    flags: (0x0001) ACC_PUBLIC
    Code:
      stack=2, locals=1, args_size=1
         0: getstatic     #41                 // Field scala/runtime/RichLong$.MODULE$:Lscala/runtime/RichLong$;
         3: pop
         4: aload_0
         5: invokevirtual #268                // Method self:()J
         8: invokestatic  #56                 // Method java/lang/Long.toOctalString:(J)Ljava/lang/String;
        11: areturn
      LineNumberTable:
        line 48: 0
        line 48: 8
        line 48: 11
      LocalVariableTable:
        Start  Length  Slot  Name   Signature
            0      12     0  this   Lscala/runtime/RichLong;

  public int hashCode();
    descriptor: ()I
    flags: (0x0001) ACC_PUBLIC
    Code:
      stack=2, locals=1, args_size=1
         0: getstatic     #41                 // Field scala/runtime/RichLong$.MODULE$:Lscala/runtime/RichLong$;
         3: pop
         4: aload_0
         5: invokevirtual #268                // Method self:()J
         8: invokestatic  #51                 // Method java/lang/Long.hashCode:(J)I
        11: ireturn
      LineNumberTable:
        line 16: 0
        line 16: 8
        line 16: 11
      LocalVariableTable:
        Start  Length  Slot  Name   Signature
            0      12     0  this   Lscala/runtime/RichLong;

  public boolean equals(java.lang.Object);
    descriptor: (Ljava/lang/Object;)Z
    flags: (0x0001) ACC_PUBLIC
    Code:
      stack=4, locals=2, args_size=2
         0: getstatic     #41                 // Field scala/runtime/RichLong$.MODULE$:Lscala/runtime/RichLong$;
         3: aload_0
         4: invokevirtual #268                // Method self:()J
         7: aload_1
         8: invokevirtual #43                 // Method scala/runtime/RichLong$.equals$extension:(JLjava/lang/Object;)Z
        11: ireturn
      LineNumberTable:
        line 16: 0
      LocalVariableTable:
        Start  Length  Slot  Name   Signature
            0      12     0  this   Lscala/runtime/RichLong;
            0      12     1   x$1   Ljava/lang/Object;
    MethodParameters:
      Name                           Flags
      x$1                            final

  public scala.collection.immutable.IndexedSeq to(java.lang.Object, java.lang.Object);
    descriptor: (Ljava/lang/Object;Ljava/lang/Object;)Lscala/collection/immutable/IndexedSeq;
    flags: (0x1041) ACC_PUBLIC, ACC_BRIDGE, ACC_SYNTHETIC
    Code:
      stack=3, locals=3, args_size=3
         0: aload_0
         1: aload_1
         2: aload_2
         3: invokevirtual #289                // Method to:(Ljava/lang/Object;Ljava/lang/Object;)Lscala/collection/immutable/NumericRange$Inclusive;
         6: areturn
      LineNumberTable:
        line 16: 0
      LocalVariableTable:
        Start  Length  Slot  Name   Signature
            0       7     0  this   Lscala/runtime/RichLong;
            0       7     1   end   Ljava/lang/Object;
            0       7     2  step   Ljava/lang/Object;
    MethodParameters:
      Name                           Flags
      end                            final
      step                           final

  public java.lang.Object to(java.lang.Object);
    descriptor: (Ljava/lang/Object;)Ljava/lang/Object;
    flags: (0x1041) ACC_PUBLIC, ACC_BRIDGE, ACC_SYNTHETIC
    Code:
      stack=2, locals=2, args_size=2
         0: aload_0
         1: aload_1
         2: invokevirtual #292                // Method to:(Ljava/lang/Object;)Lscala/collection/immutable/NumericRange$Inclusive;
         5: areturn
      LineNumberTable:
        line 16: 0
      LocalVariableTable:
        Start  Length  Slot  Name   Signature
            0       6     0  this   Lscala/runtime/RichLong;
            0       6     1   end   Ljava/lang/Object;
    MethodParameters:
      Name                           Flags
      end                            final

  public scala.collection.immutable.IndexedSeq until(java.lang.Object, java.lang.Object);
    descriptor: (Ljava/lang/Object;Ljava/lang/Object;)Lscala/collection/immutable/IndexedSeq;
    flags: (0x1041) ACC_PUBLIC, ACC_BRIDGE, ACC_SYNTHETIC
    Code:
      stack=3, locals=3, args_size=3
         0: aload_0
         1: aload_1
         2: aload_2
         3: invokevirtual #294                // Method until:(Ljava/lang/Object;Ljava/lang/Object;)Lscala/collection/immutable/NumericRange$Exclusive;
         6: areturn
      LineNumberTable:
        line 16: 0
      LocalVariableTable:
        Start  Length  Slot  Name   Signature
            0       7     0  this   Lscala/runtime/RichLong;
            0       7     1   end   Ljava/lang/Object;
            0       7     2  step   Ljava/lang/Object;
    MethodParameters:
      Name                           Flags
      end                            final
      step                           final

  public java.lang.Object until(java.lang.Object);
    descriptor: (Ljava/lang/Object;)Ljava/lang/Object;
    flags: (0x1041) ACC_PUBLIC, ACC_BRIDGE, ACC_SYNTHETIC
    Code:
      stack=2, locals=2, args_size=2
         0: aload_0
         1: aload_1
         2: invokevirtual #296                // Method until:(Ljava/lang/Object;)Lscala/collection/immutable/NumericRange$Exclusive;
         5: areturn
      LineNumberTable:
        line 16: 0
      LocalVariableTable:
        Start  Length  Slot  Name   Signature
            0       6     0  this   Lscala/runtime/RichLong;
            0       6     1   end   Ljava/lang/Object;
    MethodParameters:
      Name                           Flags
      end                            final

  public java.lang.Object min(java.lang.Object);
    descriptor: (Ljava/lang/Object;)Ljava/lang/Object;
    flags: (0x1041) ACC_PUBLIC, ACC_BRIDGE, ACC_SYNTHETIC
    Code:
      stack=4, locals=6, args_size=2
         0: getstatic     #41                 // Field scala/runtime/RichLong$.MODULE$:Lscala/runtime/RichLong$;
         3: pop
         4: aload_0
         5: invokevirtual #268                // Method self:()J
         8: aload_1
         9: invokestatic  #302                // Method scala/runtime/BoxesRunTime.unboxToLong:(Ljava/lang/Object;)J
        12: lstore        4
        14: lstore_2
        15: getstatic     #74                 // Field scala/math/package$.MODULE$:Lscala/math/package$;
        18: pop
        19: lload_2
        20: lload         4
        22: invokestatic  #79                 // Method java/lang/Math.min:(JJ)J
        25: invokestatic  #306                // Method java/lang/Long.valueOf:(J)Ljava/lang/Long;
        28: areturn
      LineNumberTable:
        line 16: 4
        line 40: 15
        line 16: 25
      LocalVariableTable:
        Start  Length  Slot  Name   Signature
            0      29     0  this   Lscala/runtime/RichLong;
            0      29     1  that   Ljava/lang/Object;
           15      10     2 min$extension_$this   J
           15      10     4 min$extension_that   J
    MethodParameters:
      Name                           Flags
      that                           final

  public java.lang.Object max(java.lang.Object);
    descriptor: (Ljava/lang/Object;)Ljava/lang/Object;
    flags: (0x1041) ACC_PUBLIC, ACC_BRIDGE, ACC_SYNTHETIC
    Code:
      stack=4, locals=6, args_size=2
         0: getstatic     #41                 // Field scala/runtime/RichLong$.MODULE$:Lscala/runtime/RichLong$;
         3: pop
         4: aload_0
         5: invokevirtual #268                // Method self:()J
         8: aload_1
         9: invokestatic  #302                // Method scala/runtime/BoxesRunTime.unboxToLong:(Ljava/lang/Object;)J
        12: lstore        4
        14: lstore_2
        15: getstatic     #74                 // Field scala/math/package$.MODULE$:Lscala/math/package$;
        18: pop
        19: lload_2
        20: lload         4
        22: invokestatic  #83                 // Method java/lang/Math.max:(JJ)J
        25: invokestatic  #306                // Method java/lang/Long.valueOf:(J)Ljava/lang/Long;
        28: areturn
      LineNumberTable:
        line 16: 4
        line 39: 15
        line 16: 25
      LocalVariableTable:
        Start  Length  Slot  Name   Signature
            0      29     0  this   Lscala/runtime/RichLong;
            0      29     1  that   Ljava/lang/Object;
           15      10     2 max$extension_$this   J
           15      10     4 max$extension_that   J
    MethodParameters:
      Name                           Flags
      that                           final

  public java.lang.Object abs();
    descriptor: ()Ljava/lang/Object;
    flags: (0x1041) ACC_PUBLIC, ACC_BRIDGE, ACC_SYNTHETIC
    Code:
      stack=2, locals=3, args_size=1
         0: getstatic     #41                 // Field scala/runtime/RichLong$.MODULE$:Lscala/runtime/RichLong$;
         3: pop
         4: aload_0
         5: invokevirtual #268                // Method self:()J
         8: lstore_1
         9: getstatic     #74                 // Field scala/math/package$.MODULE$:Lscala/math/package$;
        12: pop
        13: lload_1
        14: invokestatic  #87                 // Method java/lang/Math.abs:(J)J
        17: invokestatic  #306                // Method java/lang/Long.valueOf:(J)Ljava/lang/Long;
        20: areturn
      LineNumberTable:
        line 16: 4
        line 38: 9
        line 16: 17
      LocalVariableTable:
        Start  Length  Slot  Name   Signature
            0      21     0  this   Lscala/runtime/RichLong;
            9       8     1 abs$extension_$this   J

  public scala.math.Ordering ord();
    descriptor: ()Lscala/math/Ordering;
    flags: (0x1041) ACC_PUBLIC, ACC_BRIDGE, ACC_SYNTHETIC
    Code:
      stack=2, locals=1, args_size=1
         0: getstatic     #41                 // Field scala/runtime/RichLong$.MODULE$:Lscala/runtime/RichLong$;
         3: pop
         4: aload_0
         5: invokevirtual #268                // Method self:()J
         8: pop2
         9: getstatic     #116                // Field scala/math/Ordering$Long$.MODULE$:Lscala/math/Ordering$Long$;
        12: areturn
      LineNumberTable:
        line 16: 4
        line 18: 9
        line 16: 12
      LocalVariableTable:
        Start  Length  Slot  Name   Signature
            0      13     0  this   Lscala/runtime/RichLong;

  public scala.math.Numeric num();
    descriptor: ()Lscala/math/Numeric;
    flags: (0x1041) ACC_PUBLIC, ACC_BRIDGE, ACC_SYNTHETIC
    Code:
      stack=2, locals=1, args_size=1
         0: getstatic     #41                 // Field scala/runtime/RichLong$.MODULE$:Lscala/runtime/RichLong$;
         3: pop
         4: aload_0
         5: invokevirtual #268                // Method self:()J
         8: pop2
         9: getstatic     #121                // Field scala/math/Numeric$LongIsIntegral$.MODULE$:Lscala/math/Numeric$LongIsIntegral$;
        12: areturn
      LineNumberTable:
        line 16: 4
        line 17: 9
        line 16: 12
      LocalVariableTable:
        Start  Length  Slot  Name   Signature
            0      13     0  this   Lscala/runtime/RichLong;

  public scala.math.Integral num();
    descriptor: ()Lscala/math/Integral;
    flags: (0x1041) ACC_PUBLIC, ACC_BRIDGE, ACC_SYNTHETIC
    Code:
      stack=2, locals=1, args_size=1
         0: getstatic     #41                 // Field scala/runtime/RichLong$.MODULE$:Lscala/runtime/RichLong$;
         3: pop
         4: aload_0
         5: invokevirtual #268                // Method self:()J
         8: pop2
         9: getstatic     #121                // Field scala/math/Numeric$LongIsIntegral$.MODULE$:Lscala/math/Numeric$LongIsIntegral$;
        12: areturn
      LineNumberTable:
        line 16: 4
        line 17: 9
        line 16: 12
      LocalVariableTable:
        Start  Length  Slot  Name   Signature
            0      13     0  this   Lscala/runtime/RichLong;

  public java.lang.Object self();
    descriptor: ()Ljava/lang/Object;
    flags: (0x1041) ACC_PUBLIC, ACC_BRIDGE, ACC_SYNTHETIC
    Code:
      stack=2, locals=1, args_size=1
         0: aload_0
         1: invokevirtual #268                // Method self:()J
         4: invokestatic  #314                // Method scala/runtime/BoxesRunTime.boxToLong:(J)Ljava/lang/Long;
         7: areturn
      LineNumberTable:
        line 16: 0
      LocalVariableTable:
        Start  Length  Slot  Name   Signature
            0       8     0  this   Lscala/runtime/RichLong;

  public scala.runtime.RichLong(long);
    descriptor: (J)V
    flags: (0x0001) ACC_PUBLIC
    Code:
      stack=3, locals=3, args_size=2
         0: aload_0
         1: lload_1
         2: putfield      #264                // Field self:J
         5: aload_0
         6: invokespecial #319                // Method java/lang/Object."<init>":()V
         9: return
      LineNumberTable:
        line 16: 0
      LocalVariableTable:
        Start  Length  Slot  Name   Signature
            0      10     0  this   Lscala/runtime/RichLong;
            0      10     1  self   J
    MethodParameters:
      Name                           Flags
      self                           final
}
InnerClasses:
  public static #16= #13 of #15;          // Exclusive=class scala/collection/immutable/NumericRange$Exclusive of class scala/collection/immutable/NumericRange
  public static #19= #18 of #15;          // Inclusive=class scala/collection/immutable/NumericRange$Inclusive of class scala/collection/immutable/NumericRange
  public static #24= #21 of #23;          // LongIsIntegral$=class scala/math/Numeric$LongIsIntegral$ of class scala/math/Numeric
  public static #29= #26 of #28;          // Long$=class scala/math/Ordering$Long$ of class scala/math/Ordering
Signature: #3                           // Ljava/lang/Object;Lscala/runtime/IntegralProxy<Ljava/lang/Object;>;
SourceFile: "RichLong.scala"
RuntimeVisibleAnnotations:
  0: #9(#10=s#11)
    scala.reflect.ScalaSignature(
      bytes="\u0006\u0005\t\u001da\u0001B\u001a5\u0005eB\u0001\"\u0012\u0001\u0003\u0006\u0004%\tA\u0012\u0005\t\u000f\u0002\u0011\t\u0011)A\u0005\u0005\")\u0001\n\u0001C\u0001\u0013\")A\n\u0001C\t\u001b\")a\f\u0001C\t?\")q\r\u0001C!Q\")A\u000e\u0001C![\")\u0011\u000f\u0001C!\r\")!\u000f\u0001C!g\")q\u000f\u0001C!q\")A\u0010\u0001C!{\"9\u00111\u0001\u0001\u0005B\u0005\u0015\u0001bBA\u0007\u0001\u0011\u0005\u0013Q\u0001\u0005\b\u0003\u001f\u0001A\u0011IA\u0003\u0011\u001d\t\t\u0002\u0001C!\u0003\u000bAq!a\u0005\u0001\t\u0003\t)\u0001\u0003\u0004\u0002\u0016\u0001!\tE\u0012\u0005\b\u0003/\u0001A\u0011IA\r\u0011\u001d\ty\u0002\u0001C!\u0003CAa!!\n\u0001\t\u00031\u0005bBA\u001e\u0001\u0011\u0005\u0011Q\b\u0005\b\u0003\u001f\u0002A\u0011AA\u001f\u0011\u001d\t\t\u0006\u0001C\u0001\u0003{A\u0011\"a\u0015\u0001\u0003\u0003%\t%!\u0016\t\u0013\u0005]\u0003!!A\u0005B\u0005es!CA3i\u0005\u0005\t\u0012AA4\r!\u0019D\'!A\t\u0002\u0005%\u0004B\u0002%\u001c\t\u0003\t\t\bC\u0004\u0002tm!)!!\u001e\t\u000f\u0005m4\u0004\"\u0002\u0002~!9\u0011\u0011Q\u000e\u0005\u0006\u0005\r\u0005bBAD7\u0011\u0015\u0011\u0011\u0012\u0005\b\u0003\u001b[BQAAH\u0011\u001d\t\u0019j\u0007C\u0003\u0003+Cq!!\'\u001c\t\u000b\tY\nC\u0004\u0002 n!)!!)\t\u000f\u0005\u00156\u0004\"\u0002\u0002(\"9\u00111V\u000e\u0005\u0006\u00055\u0006bBAY7\u0011\u0015\u00111\u0017\u0005\b\u0003o[BQAA]\u0011\u001d\til\u0007C\u0003\u0003\u007fCq!a1\u001c\t\u000b\t)\rC\u0004\u0002Jn!)!a3\t\u000f\u0005M7\u0004\"\u0002\u0002V\"9\u0011Q\\\u000e\u0005\u0006\u0005}\u0007bBAs7\u0011\u0015\u0011q\u001d\u0005\b\u0003W\\BQAAw\u0011\u001d\t\tp\u0007C\u0003\u0003gD\u0011\"a>\u001c\u0003\u0003%)!!?\t\u0013\u0005u8$!A\u0005\u0006\u0005}(\u0001\u0003*jG\"duN\\4\u000b\u0005U2\u0014a\u0002:v]RLW.\u001a\u0006\u0002o\u0005)1oY1mC\u000e\u00011c\u0001\u0001;}A\u00111\bP\u0007\u0002m%\u0011QH\u000e\u0002\u0007\u0003:Lh+\u00197\u0011\u0007}\u0002%)D\u00015\u0013\t\tEGA\u0007J]R,wM]1m!J|\u00070\u001f\t\u0003w\rK!\u0001\u0012\u001c\u0003\t1{gnZ\u0001\u0005g\u0016dg-F\u0001C\u0003\u0015\u0019X\r\u001c4!\u0003\u0019a\u0014N\\5u}Q\u0011!j\u0013\t\u0003\u007f\u0001AQ!R\u0002A\u0002\t\u000b1A\\;n+\u0005q\u0005CA(\\\u001d\t\u0001\u0006L\u0004\u0002R-:\u0011!+V\u0007\u0002\'*\u0011A\u000bO\u0001\u0007yI|w\u000e\u001e \n\u0003]J!a\u0016\u001c\u0002\t5\fG\u000f[\u0005\u00033j\u000bqAT;nKJL7M\u0003\u0002Xm)\u0011A,X\u0001\u000f\u0019>tw-S:J]R,wM]1m\u0015\tI&,A\u0002pe\u0012,\u0012\u0001\u0019\t\u0003C\u0012t!\u0001\u00152\n\u0005\rT\u0016\u0001C(sI\u0016\u0014\u0018N\\4\u000b\u0005\u00154\u0017\u0001\u0002\'p]\u001eT!a\u0019.\u0002\u0017\u0011|WO\u00197f-\u0006dW/Z\u000b\u0002SB\u00111H[\u0005\u0003WZ\u0012a\u0001R8vE2,\u0017A\u00034m_\u0006$h+\u00197vKV\ta\u000e\u0005\u0002<_&\u0011\u0001O\u000e\u0002\u0006\r2|\u0017\r^\u0001\nY>twMV1mk\u0016\f\u0001\"\u001b8u-\u0006dW/Z\u000b\u0002iB\u00111(^\u0005\u0003mZ\u00121!\u00138u\u0003%\u0011\u0017\u0010^3WC2,X-F\u0001z!\tY$0\u0003\u0002|m\t!!)\u001f;f\u0003)\u0019\bn\u001c:u-\u0006dW/Z\u000b\u0002}B\u00111h`\u0005\u0004\u0003\u00031$!B*i_J$\u0018aC5t-\u0006d\u0017\u000e\u001a\"zi\u0016,\"!a\u0002\u0011\u0007m\nI!C\u0002\u0002\fY\u0012qAQ8pY\u0016\fg.\u0001\u0007jgZ\u000bG.\u001b3TQ>\u0014H/A\u0006jgZ\u000bG.\u001b3DQ\u0006\u0014\u0018AC5t-\u0006d\u0017\u000eZ%oi\u0006Y\u0011n\u001d,bY&$Gj\u001c8h\u0003\r\t\'m]\u0001\u0004[\u0006DHc\u0001\"\u0002\u001c!1\u0011Q\u0004\nA\u0002\t\u000bA\u0001\u001e5bi\u0006\u0019Q.\u001b8\u0015\u0007\t\u000b\u0019\u0003\u0003\u0004\u0002\u001eM\u0001\rAQ\u0001\u0006e>,h\u000e\u001a\u0015\f)\u0005%\u0012qFA\u0019\u0003k\t9\u0004E\u0002<\u0003WI1!!\f7\u0005)!W\r\u001d:fG\u0006$X\rZ\u0001\b[\u0016\u001c8/Y4fC\t\t\u0019$A:uQ&\u001c\b%[:!C:\u0004\u0013N\u001c;fO\u0016\u0014\b\u0005^=qKn\u0002C\u000f[3sK\u0002J7\u000f\t8pAI,\u0017m]8oAQ|\u0007E]8v]\u0012\u0004\u0013\u000e\u001e\u0018!AA+\'\u000f[1qg\u0002Jx.\u001e\u0011nK\u0006tG\u000f\t;pA\r\fG\u000e\u001c\u0011uQ&\u001c\be\u001c8!C\u00022Gn\\1uS:<W\u0006]8j]R\u0004c/\u00197vK~\nQa]5oG\u0016\f#!!\u000f\u0002\rIr\u0013\'\r\u00181\u00039!xNQ5oCJL8\u000b\u001e:j]\u001e,\"!a\u0010\u0011\t\u0005\u0005\u0013\u0011\n\b\u0005\u0003\u0007\n)\u0005\u0005\u0002Sm%\u0019\u0011q\t\u001c\u0002\rA\u0013X\rZ3g\u0013\u0011\tY%!\u0014\u0003\rM#(/\u001b8h\u0015\r\t9EN\u0001\fi>DU\r_*ue&tw-A\u0007u_>\u001bG/\u00197TiJLgnZ\u0001\tQ\u0006\u001c\bnQ8eKR\tA/\u0001\u0004fcV\fGn\u001d\u000b\u0005\u0003\u000f\tY\u0006C\u0005\u0002^e\t\t\u00111\u0001\u0002`\u0005\u0019\u0001\u0010J\u0019\u0011\u0007m\n\t\'C\u0002\u0002dY\u00121!\u00118z\u0003!\u0011\u0016n\u00195M_:<\u0007CA \u001c\'\rY\u00121\u000e\t\u0004w\u00055\u0014bAA8m\t1\u0011I\\=SK\u001a$\"!a\u001a\u0002\u001b9,X\u000eJ3yi\u0016t7/[8o)\rq\u0015q\u000f\u0005\u0007\u0003sj\u0002\u0019\u0001&\u0002\u000b\u0011\"\b.[:\u0002\u001b=\u0014H\rJ3yi\u0016t7/[8o)\r\u0001\u0017q\u0010\u0005\u0007\u0003sr\u0002\u0019\u0001&\u0002+\u0011|WO\u00197f-\u0006dW/\u001a\u0013fqR,gn]5p]R\u0019\u0011.!\"\t\r\u0005et\u00041\u0001K\u0003Q1Gn\\1u-\u0006dW/\u001a\u0013fqR,gn]5p]R\u0019a.a#\t\r\u0005e\u0004\u00051\u0001K\u0003MawN\\4WC2,X\rJ3yi\u0016t7/[8o)\r\u0011\u0015\u0011\u0013\u0005\u0007\u0003s\n\u0003\u0019\u0001&\u0002%%tGOV1mk\u0016$S\r\u001f;f]NLwN\u001c\u000b\u0004i\u0006]\u0005BBA=E\u0001\u0007!*A\ncsR,g+\u00197vK\u0012*\u0007\u0010^3og&|g\u000eF\u0002z\u0003;Ca!!\u001f$\u0001\u0004Q\u0015\u0001F:i_J$h+\u00197vK\u0012*\u0007\u0010^3og&|g\u000eF\u0002\u007f\u0003GCa!!\u001f%\u0001\u0004Q\u0015!F5t-\u0006d\u0017\u000e\u001a\"zi\u0016$S\r\u001f;f]NLwN\u001c\u000b\u0005\u0003\u000f\tI\u000b\u0003\u0004\u0002z\u0015\u0002\rAS\u0001\u0017SN4\u0016\r\\5e\'\"|\'\u000f\u001e\u0013fqR,gn]5p]R!\u0011qAAX\u0011\u0019\tIH\na\u0001\u0015\u0006)\u0012n\u001d,bY&$7\t[1sI\u0015DH/\u001a8tS>tG\u0003BA\u0004\u0003kCa!!\u001f(\u0001\u0004Q\u0015\u0001F5t-\u0006d\u0017\u000eZ%oi\u0012*\u0007\u0010^3og&|g\u000e\u0006\u0003\u0002\b\u0005m\u0006BBA=Q\u0001\u0007!*A\u000bjgZ\u000bG.\u001b3M_:<G%\u001a=uK:\u001c\u0018n\u001c8\u0015\t\u0005\u001d\u0011\u0011\u0019\u0005\u0007\u0003sJ\u0003\u0019\u0001&\u0002\u001b\u0005\u00147\u000fJ3yi\u0016t7/[8o)\r\u0011\u0015q\u0019\u0005\u0007\u0003sR\u0003\u0019\u0001&\u0002\u001b5\f\u0007\u0010J3yi\u0016t7/[8o)\u0011\ti-!5\u0015\u0007\t\u000by\r\u0003\u0004\u0002\u001e-\u0002\rA\u0011\u0005\u0007\u0003sZ\u0003\u0019\u0001&\u0002\u001b5Lg\u000eJ3yi\u0016t7/[8o)\u0011\t9.a7\u0015\u0007\t\u000bI\u000e\u0003\u0004\u0002\u001e1\u0002\rA\u0011\u0005\u0007\u0003sb\u0003\u0019\u0001&\u0002\u001fI|WO\u001c3%Kb$XM\\:j_:$2AQAq\u0011\u0019\tI(\fa\u0001\u0015\"ZQ&!\u000b\u00020\u0005E\u0012QGA\u001c\u0003a!xNQ5oCJL8\u000b\u001e:j]\u001e$S\r\u001f;f]NLwN\u001c\u000b\u0005\u0003\u007f\tI\u000f\u0003\u0004\u0002z9\u0002\rAS\u0001\u0016i>DU\r_*ue&tw\rJ3yi\u0016t7/[8o)\u0011\ty$a<\t\r\u0005et\u00061\u0001K\u0003]!xnT2uC2\u001cFO]5oO\u0012*\u0007\u0010^3og&|g\u000e\u0006\u0003\u0002@\u0005U\bBBA=a\u0001\u0007!*\u0001\niCND7i\u001c3fI\u0015DH/\u001a8tS>tG\u0003BA+\u0003wDa!!\u001f2\u0001\u0004Q\u0015\u0001E3rk\u0006d7\u000fJ3yi\u0016t7/[8o)\u0011\u0011\tA!\u0002\u0015\t\u0005\u001d!1\u0001\u0005\n\u0003;\u0012\u0014\u0011!a\u0001\u0003?Ba!!\u001f3\u0001\u0004Q\u0005"
    )
  ScalaInlineInfo: length = 0x126 (unknown attribute)
   01 01 00 3A 00 B9 00 B2 01 00 C1 00 B2 01 00 B1
   00 B2 01 00 BD 00 B2 01 01 3B 01 3C 01 00 55 00
   EC 01 00 55 00 9B 01 01 13 00 DB 01 00 A8 00 A9
   01 00 C5 00 A9 01 01 0F 00 F8 01 01 1E 00 B2 01
   01 10 00 F2 01 00 31 00 A3 01 01 12 00 A3 01 01
   15 00 93 01 01 17 00 93 01 01 18 00 93 01 01 19
   00 93 01 01 16 00 93 01 00 92 00 93 01 01 11 00
   EC 01 00 51 00 42 01 00 51 01 22 01 00 4D 00 42
   01 00 4D 01 22 01 01 09 01 37 01 01 09 01 0A 01
   01 09 01 36 01 01 0D 01 0E 01 01 0D 01 35 01 01
   1D 00 EC 01 00 1E 00 EC 01 00 1E 00 9B 01 01 14
   00 E1 01 00 9A 00 9B 01 00 A2 00 A3 01 00 88 01
   22 01 00 88 00 89 01 00 88 01 1F 01 00 88 00 8E
   01 00 3E 00 CB 01 00 DA 00 DB 01 00 D2 00 D3 01
   00 F7 00 F8 01 00 F1 00 F2 01 00 3A 00 CB 01 00
   E6 00 A3 01 00 EB 00 EC 01 00 36 00 CB 01 00 E0
   00 E1 01 00 CA 00 CB 01 01 01 00 B2 01 00 FD 00
   A3 01 00 7A 01 22 01 00 7A 00 7B 01 00 7A 01 1F
   01 00 7A 00 83 01
  ScalaSig: length = 0x3 (unknown attribute)
   05 02 00
