Classfile /Users/mw/Projects/slang-braindump/.jar/jar8/assemble/slang-braindump/assemble/content/scala/runtime/RichBoolean.class
  Last modified May 29, 2022; size 3735 bytes
  SHA-256 checksum b1b51eb5d864611d393ae8dff55e5055558505abf77920066bbee8a97d59d545
  Compiled from "RichBoolean.scala"
public final class scala.runtime.RichBoolean extends java.lang.Object implements scala.runtime.OrderedProxy<java.lang.Object>
  minor version: 0
  major version: 52
  flags: (0x0031) ACC_PUBLIC, ACC_FINAL, ACC_SUPER
  this_class: #2                          // scala/runtime/RichBoolean
  super_class: #5                         // java/lang/Object
  interfaces: 1, fields: 1, methods: 17, attributes: 6
Constant pool:
    #1 = Utf8               scala/runtime/RichBoolean
    #2 = Class              #1            // scala/runtime/RichBoolean
    #3 = Utf8               Ljava/lang/Object;Lscala/runtime/OrderedProxy<Ljava/lang/Object;>;
    #4 = Utf8               java/lang/Object
    #5 = Class              #4            // java/lang/Object
    #6 = Utf8               scala/runtime/OrderedProxy
    #7 = Class              #6            // scala/runtime/OrderedProxy
    #8 = Utf8               RichBoolean.scala
    #9 = Utf8               Lscala/reflect/ScalaSignature;
   #10 = Utf8               bytes
   #11 = Utf8               \u0006\u0005]3A!\u0004\b\u0003\'!Aq\u0004\u0001BC\u0002\u0013\u0005\u0001\u0005\u0003\u0005\"\u0001\t\u0005\t\u0015!\u0003\u001d\u0011\u0015\u0011\u0003\u0001\"\u0001$\u0011\u00151\u0003\u0001\"\u0005(\u0011\u001dA\u0004!!A\u0005BeBq!\u0010\u0001\u0002\u0002\u0013\u0005chB\u0004E\u001d\u0005\u0005\t\u0012A#\u0007\u000f5q\u0011\u0011!E\u0001\r\")!\u0005\u0003C\u0001\u0015\")1\n\u0003C\u0003\u0019\"9q\nCA\u0001\n\u000b\u0001\u0006b\u0002*\t\u0003\u0003%)a\u0015\u0002\f%&\u001c\u0007NQ8pY\u0016\fgN\u0003\u0002\u0010!\u00059!/\u001e8uS6,\'\"A\t\u0002\u000bM\u001c\u0017\r\\1\u0004\u0001M\u0019\u0001\u0001\u0006\r\u0011\u0005U1R\"\u0001\t\n\u0005]\u0001\"AB!osZ\u000bG\u000eE\u0002\u001a5qi\u0011AD\u0005\u000379\u0011Ab\u0014:eKJ,G\r\u0015:pqf\u0004\"!F\u000f\n\u0005y\u0001\"a\u0002\"p_2,\u0017M\\\u0001\u0005g\u0016dg-F\u0001\u001d\u0003\u0015\u0019X\r\u001c4!\u0003\u0019a\u0014N\\5u}Q\u0011A%\n\t\u00033\u0001AQaH\u0002A\u0002q\t1a\u001c:e+\u0005A\u0003CA\u00156\u001d\tQ#G\u0004\u0002,a9\u0011AfL\u0007\u0002[)\u0011aFE\u0001\u0007yI|w\u000e\u001e \n\u0003EI!!\r\t\u0002\t5\fG\u000f[\u0005\u0003gQ\n\u0001b\u0014:eKJLgn\u001a\u0006\u0003cAQ!AN\u001c\u0002\u000f\t{w\u000e\\3b]*\u00111\u0007N\u0001\tQ\u0006\u001c\bnQ8eKR\t!\b\u0005\u0002\u0016w%\u0011A\b\u0005\u0002\u0004\u0013:$\u0018AB3rk\u0006d7\u000f\u0006\u0002\u001d\u007f!9\u0001IBA\u0001\u0002\u0004\t\u0015a\u0001=%cA\u0011QCQ\u0005\u0003\u0007B\u00111!\u00118z\u0003-\u0011\u0016n\u00195C_>dW-\u00198\u0011\u0005eA1C\u0001\u0005H!\t)\u0002*\u0003\u0002J!\t1\u0011I\\=SK\u001a$\u0012!R\u0001\u000e_J$G%\u001a=uK:\u001c\u0018n\u001c8\u0015\u0005!j\u0005\"\u0002(\u000b\u0001\u0004!\u0013!\u0002\u0013uQ&\u001c\u0018A\u00055bg\"\u001cu\u000eZ3%Kb$XM\\:j_:$\"!O)\t\u000b9[\u0001\u0019\u0001\u0013\u0002!\u0015\fX/\u00197tI\u0015DH/\u001a8tS>tGC\u0001+W)\taR\u000bC\u0004A\u0019\u0005\u0005\t\u0019A!\t\u000b9c\u0001\u0019\u0001\u0013
   #12 = Utf8               scala/math/Ordering$Boolean$
   #13 = Class              #12           // scala/math/Ordering$Boolean$
   #14 = Utf8               scala/math/Ordering
   #15 = Class              #14           // scala/math/Ordering
   #16 = Utf8               Boolean$
   #17 = Utf8               self
   #18 = Utf8               Z
   #19 = Utf8               equals$extension
   #20 = Utf8               (ZLjava/lang/Object;)Z
   #21 = Utf8               $this
   #22 = Utf8               x$1
   #23 = Utf8               scala/runtime/RichBoolean$
   #24 = Class              #23           // scala/runtime/RichBoolean$
   #25 = Utf8               MODULE$
   #26 = Utf8               Lscala/runtime/RichBoolean$;
   #27 = NameAndType        #25:#26       // MODULE$:Lscala/runtime/RichBoolean$;
   #28 = Fieldref           #24.#27       // scala/runtime/RichBoolean$.MODULE$:Lscala/runtime/RichBoolean$;
   #29 = NameAndType        #19:#20       // equals$extension:(ZLjava/lang/Object;)Z
   #30 = Methodref          #24.#29       // scala/runtime/RichBoolean$.equals$extension:(ZLjava/lang/Object;)Z
   #31 = Utf8               Ljava/lang/Object;
   #32 = Utf8               hashCode$extension
   #33 = Utf8               (Z)I
   #34 = Utf8               java/lang/Boolean
   #35 = Class              #34           // java/lang/Boolean
   #36 = Utf8               hashCode
   #37 = NameAndType        #36:#33       // hashCode:(Z)I
   #38 = Methodref          #35.#37       // java/lang/Boolean.hashCode:(Z)I
   #39 = Utf8               ord$extension
   #40 = Utf8               (Z)Lscala/math/Ordering$Boolean$;
   #41 = Utf8               Lscala/math/Ordering$Boolean$;
   #42 = NameAndType        #25:#41       // MODULE$:Lscala/math/Ordering$Boolean$;
   #43 = Fieldref           #13.#42       // scala/math/Ordering$Boolean$.MODULE$:Lscala/math/Ordering$Boolean$;
   #44 = Utf8               compare
   #45 = Utf8               (Ljava/lang/Object;)I
   #46 = Utf8               y
   #47 = Utf8               compare$
   #48 = Utf8               (Lscala/runtime/OrderedProxy;Ljava/lang/Object;)I
   #49 = NameAndType        #47:#48       // compare$:(Lscala/runtime/OrderedProxy;Ljava/lang/Object;)I
   #50 = InterfaceMethodref #7.#49        // scala/runtime/OrderedProxy.compare$:(Lscala/runtime/OrderedProxy;Ljava/lang/Object;)I
   #51 = Utf8               this
   #52 = Utf8               Lscala/runtime/RichBoolean;
   #53 = Utf8               toString
   #54 = Utf8               ()Ljava/lang/String;
   #55 = Utf8               scala/Proxy
   #56 = Class              #55           // scala/Proxy
   #57 = Utf8               toString$
   #58 = Utf8               (Lscala/Proxy;)Ljava/lang/String;
   #59 = NameAndType        #57:#58       // toString$:(Lscala/Proxy;)Ljava/lang/String;
   #60 = InterfaceMethodref #56.#59       // scala/Proxy.toString$:(Lscala/Proxy;)Ljava/lang/String;
   #61 = Utf8               $less
   #62 = Utf8               (Ljava/lang/Object;)Z
   #63 = Utf8               that
   #64 = Utf8               scala/math/Ordered
   #65 = Class              #64           // scala/math/Ordered
   #66 = Utf8               $less$
   #67 = Utf8               (Lscala/math/Ordered;Ljava/lang/Object;)Z
   #68 = NameAndType        #66:#67       // $less$:(Lscala/math/Ordered;Ljava/lang/Object;)Z
   #69 = InterfaceMethodref #65.#68       // scala/math/Ordered.$less$:(Lscala/math/Ordered;Ljava/lang/Object;)Z
   #70 = Utf8               $greater
   #71 = Utf8               $greater$
   #72 = NameAndType        #71:#67       // $greater$:(Lscala/math/Ordered;Ljava/lang/Object;)Z
   #73 = InterfaceMethodref #65.#72       // scala/math/Ordered.$greater$:(Lscala/math/Ordered;Ljava/lang/Object;)Z
   #74 = Utf8               $less$eq
   #75 = Utf8               $less$eq$
   #76 = NameAndType        #75:#67       // $less$eq$:(Lscala/math/Ordered;Ljava/lang/Object;)Z
   #77 = InterfaceMethodref #65.#76       // scala/math/Ordered.$less$eq$:(Lscala/math/Ordered;Ljava/lang/Object;)Z
   #78 = Utf8               $greater$eq
   #79 = Utf8               $greater$eq$
   #80 = NameAndType        #79:#67       // $greater$eq$:(Lscala/math/Ordered;Ljava/lang/Object;)Z
   #81 = InterfaceMethodref #65.#80       // scala/math/Ordered.$greater$eq$:(Lscala/math/Ordered;Ljava/lang/Object;)Z
   #82 = Utf8               compareTo
   #83 = Utf8               compareTo$
   #84 = Utf8               (Lscala/math/Ordered;Ljava/lang/Object;)I
   #85 = NameAndType        #83:#84       // compareTo$:(Lscala/math/Ordered;Ljava/lang/Object;)I
   #86 = InterfaceMethodref #65.#85       // scala/math/Ordered.compareTo$:(Lscala/math/Ordered;Ljava/lang/Object;)I
   #87 = Utf8               ()Z
   #88 = NameAndType        #17:#18       // self:Z
   #89 = Fieldref           #2.#88        // scala/runtime/RichBoolean.self:Z
   #90 = Utf8               ord
   #91 = Utf8               ()Lscala/math/Ordering$Boolean$;
   #92 = NameAndType        #17:#87       // self:()Z
   #93 = Methodref          #2.#92        // scala/runtime/RichBoolean.self:()Z
   #94 = Utf8               ()I
   #95 = Utf8               equals
   #96 = Utf8               ()Lscala/math/Ordering;
   #97 = Utf8               ()Ljava/lang/Object;
   #98 = Utf8               scala/runtime/BoxesRunTime
   #99 = Class              #98           // scala/runtime/BoxesRunTime
  #100 = Utf8               boxToBoolean
  #101 = Utf8               (Z)Ljava/lang/Boolean;
  #102 = NameAndType        #100:#101     // boxToBoolean:(Z)Ljava/lang/Boolean;
  #103 = Methodref          #99.#102      // scala/runtime/BoxesRunTime.boxToBoolean:(Z)Ljava/lang/Boolean;
  #104 = Utf8               <init>
  #105 = Utf8               (Z)V
  #106 = Utf8               ()V
  #107 = NameAndType        #104:#106     // "<init>":()V
  #108 = Methodref          #5.#107       // java/lang/Object."<init>":()V
  #109 = Utf8               Code
  #110 = Utf8               LocalVariableTable
  #111 = Utf8               MethodParameters
  #112 = Utf8               LineNumberTable
  #113 = Utf8               InnerClasses
  #114 = Utf8               Signature
  #115 = Utf8               SourceFile
  #116 = Utf8               RuntimeVisibleAnnotations
  #117 = Utf8               ScalaInlineInfo
  #118 = Utf8               ScalaSig
{
  private final boolean self;
    descriptor: Z
    flags: (0x0012) ACC_PRIVATE, ACC_FINAL

  public static boolean equals$extension(boolean, java.lang.Object);
    descriptor: (ZLjava/lang/Object;)Z
    flags: (0x0009) ACC_PUBLIC, ACC_STATIC
    Code:
      stack=3, locals=2, args_size=2
         0: getstatic     #28                 // Field scala/runtime/RichBoolean$.MODULE$:Lscala/runtime/RichBoolean$;
         3: iload_0
         4: aload_1
         5: invokevirtual #30                 // Method scala/runtime/RichBoolean$.equals$extension:(ZLjava/lang/Object;)Z
         8: ireturn
      LocalVariableTable:
        Start  Length  Slot  Name   Signature
            0       9     0 $this   Z
            0       9     1   x$1   Ljava/lang/Object;
    MethodParameters:
      Name                           Flags
      $this                          final
      x$1                            final

  public static int hashCode$extension(boolean);
    descriptor: (Z)I
    flags: (0x0009) ACC_PUBLIC, ACC_STATIC
    Code:
      stack=1, locals=1, args_size=1
         0: getstatic     #28                 // Field scala/runtime/RichBoolean$.MODULE$:Lscala/runtime/RichBoolean$;
         3: pop
         4: iload_0
         5: invokestatic  #38                 // Method java/lang/Boolean.hashCode:(Z)I
         8: ireturn
      LineNumberTable:
        line 17: 4
      LocalVariableTable:
        Start  Length  Slot  Name   Signature
            0       9     0 $this   Z
    MethodParameters:
      Name                           Flags
      $this                          final

  public static scala.math.Ordering$Boolean$ ord$extension(boolean);
    descriptor: (Z)Lscala/math/Ordering$Boolean$;
    flags: (0x0009) ACC_PUBLIC, ACC_STATIC
    Code:
      stack=1, locals=1, args_size=1
         0: getstatic     #28                 // Field scala/runtime/RichBoolean$.MODULE$:Lscala/runtime/RichBoolean$;
         3: pop
         4: getstatic     #43                 // Field scala/math/Ordering$Boolean$.MODULE$:Lscala/math/Ordering$Boolean$;
         7: areturn
      LineNumberTable:
        line 18: 4
      LocalVariableTable:
        Start  Length  Slot  Name   Signature
            0       8     0 $this   Z
    MethodParameters:
      Name                           Flags
      $this                          final

  public int compare(java.lang.Object);
    descriptor: (Ljava/lang/Object;)I
    flags: (0x0001) ACC_PUBLIC
    Code:
      stack=2, locals=2, args_size=2
         0: aload_0
         1: aload_1
         2: invokestatic  #50                 // InterfaceMethod scala/runtime/OrderedProxy.compare$:(Lscala/runtime/OrderedProxy;Ljava/lang/Object;)I
         5: ireturn
      LineNumberTable:
        line 17: 0
      LocalVariableTable:
        Start  Length  Slot  Name   Signature
            0       6     0  this   Lscala/runtime/RichBoolean;
            0       6     1     y   Ljava/lang/Object;
    MethodParameters:
      Name                           Flags
      y                              final

  public java.lang.String toString();
    descriptor: ()Ljava/lang/String;
    flags: (0x0001) ACC_PUBLIC
    Code:
      stack=1, locals=1, args_size=1
         0: aload_0
         1: invokestatic  #60                 // InterfaceMethod scala/Proxy.toString$:(Lscala/Proxy;)Ljava/lang/String;
         4: areturn
      LineNumberTable:
        line 17: 0
      LocalVariableTable:
        Start  Length  Slot  Name   Signature
            0       5     0  this   Lscala/runtime/RichBoolean;

  public boolean $less(java.lang.Object);
    descriptor: (Ljava/lang/Object;)Z
    flags: (0x0001) ACC_PUBLIC
    Code:
      stack=2, locals=2, args_size=2
         0: aload_0
         1: aload_1
         2: invokestatic  #69                 // InterfaceMethod scala/math/Ordered.$less$:(Lscala/math/Ordered;Ljava/lang/Object;)Z
         5: ireturn
      LineNumberTable:
        line 17: 0
      LocalVariableTable:
        Start  Length  Slot  Name   Signature
            0       6     0  this   Lscala/runtime/RichBoolean;
            0       6     1  that   Ljava/lang/Object;
    MethodParameters:
      Name                           Flags
      that                           final

  public boolean $greater(java.lang.Object);
    descriptor: (Ljava/lang/Object;)Z
    flags: (0x0001) ACC_PUBLIC
    Code:
      stack=2, locals=2, args_size=2
         0: aload_0
         1: aload_1
         2: invokestatic  #73                 // InterfaceMethod scala/math/Ordered.$greater$:(Lscala/math/Ordered;Ljava/lang/Object;)Z
         5: ireturn
      LineNumberTable:
        line 17: 0
      LocalVariableTable:
        Start  Length  Slot  Name   Signature
            0       6     0  this   Lscala/runtime/RichBoolean;
            0       6     1  that   Ljava/lang/Object;
    MethodParameters:
      Name                           Flags
      that                           final

  public boolean $less$eq(java.lang.Object);
    descriptor: (Ljava/lang/Object;)Z
    flags: (0x0001) ACC_PUBLIC
    Code:
      stack=2, locals=2, args_size=2
         0: aload_0
         1: aload_1
         2: invokestatic  #77                 // InterfaceMethod scala/math/Ordered.$less$eq$:(Lscala/math/Ordered;Ljava/lang/Object;)Z
         5: ireturn
      LineNumberTable:
        line 17: 0
      LocalVariableTable:
        Start  Length  Slot  Name   Signature
            0       6     0  this   Lscala/runtime/RichBoolean;
            0       6     1  that   Ljava/lang/Object;
    MethodParameters:
      Name                           Flags
      that                           final

  public boolean $greater$eq(java.lang.Object);
    descriptor: (Ljava/lang/Object;)Z
    flags: (0x0001) ACC_PUBLIC
    Code:
      stack=2, locals=2, args_size=2
         0: aload_0
         1: aload_1
         2: invokestatic  #81                 // InterfaceMethod scala/math/Ordered.$greater$eq$:(Lscala/math/Ordered;Ljava/lang/Object;)Z
         5: ireturn
      LineNumberTable:
        line 17: 0
      LocalVariableTable:
        Start  Length  Slot  Name   Signature
            0       6     0  this   Lscala/runtime/RichBoolean;
            0       6     1  that   Ljava/lang/Object;
    MethodParameters:
      Name                           Flags
      that                           final

  public int compareTo(java.lang.Object);
    descriptor: (Ljava/lang/Object;)I
    flags: (0x0001) ACC_PUBLIC
    Code:
      stack=2, locals=2, args_size=2
         0: aload_0
         1: aload_1
         2: invokestatic  #86                 // InterfaceMethod scala/math/Ordered.compareTo$:(Lscala/math/Ordered;Ljava/lang/Object;)I
         5: ireturn
      LineNumberTable:
        line 17: 0
      LocalVariableTable:
        Start  Length  Slot  Name   Signature
            0       6     0  this   Lscala/runtime/RichBoolean;
            0       6     1  that   Ljava/lang/Object;
    MethodParameters:
      Name                           Flags
      that                           final

  public boolean self();
    descriptor: ()Z
    flags: (0x0001) ACC_PUBLIC
    Code:
      stack=1, locals=1, args_size=1
         0: aload_0
         1: getfield      #89                 // Field self:Z
         4: ireturn
      LineNumberTable:
        line 17: 0
      LocalVariableTable:
        Start  Length  Slot  Name   Signature
            0       5     0  this   Lscala/runtime/RichBoolean;

  public scala.math.Ordering$Boolean$ ord();
    descriptor: ()Lscala/math/Ordering$Boolean$;
    flags: (0x0001) ACC_PUBLIC
    Code:
      stack=1, locals=1, args_size=1
         0: getstatic     #28                 // Field scala/runtime/RichBoolean$.MODULE$:Lscala/runtime/RichBoolean$;
         3: pop
         4: aload_0
         5: invokevirtual #93                 // Method self:()Z
         8: pop
         9: getstatic     #43                 // Field scala/math/Ordering$Boolean$.MODULE$:Lscala/math/Ordering$Boolean$;
        12: areturn
      LineNumberTable:
        line 18: 0
        line 18: 9
        line 18: 12
      LocalVariableTable:
        Start  Length  Slot  Name   Signature
            0      13     0  this   Lscala/runtime/RichBoolean;

  public int hashCode();
    descriptor: ()I
    flags: (0x0001) ACC_PUBLIC
    Code:
      stack=1, locals=1, args_size=1
         0: getstatic     #28                 // Field scala/runtime/RichBoolean$.MODULE$:Lscala/runtime/RichBoolean$;
         3: pop
         4: aload_0
         5: invokevirtual #93                 // Method self:()Z
         8: invokestatic  #38                 // Method java/lang/Boolean.hashCode:(Z)I
        11: ireturn
      LineNumberTable:
        line 17: 0
        line 17: 8
        line 17: 11
      LocalVariableTable:
        Start  Length  Slot  Name   Signature
            0      12     0  this   Lscala/runtime/RichBoolean;

  public boolean equals(java.lang.Object);
    descriptor: (Ljava/lang/Object;)Z
    flags: (0x0001) ACC_PUBLIC
    Code:
      stack=3, locals=2, args_size=2
         0: getstatic     #28                 // Field scala/runtime/RichBoolean$.MODULE$:Lscala/runtime/RichBoolean$;
         3: aload_0
         4: invokevirtual #93                 // Method self:()Z
         7: aload_1
         8: invokevirtual #30                 // Method scala/runtime/RichBoolean$.equals$extension:(ZLjava/lang/Object;)Z
        11: ireturn
      LineNumberTable:
        line 17: 0
      LocalVariableTable:
        Start  Length  Slot  Name   Signature
            0      12     0  this   Lscala/runtime/RichBoolean;
            0      12     1   x$1   Ljava/lang/Object;
    MethodParameters:
      Name                           Flags
      x$1                            final

  public scala.math.Ordering ord();
    descriptor: ()Lscala/math/Ordering;
    flags: (0x1041) ACC_PUBLIC, ACC_BRIDGE, ACC_SYNTHETIC
    Code:
      stack=1, locals=1, args_size=1
         0: getstatic     #28                 // Field scala/runtime/RichBoolean$.MODULE$:Lscala/runtime/RichBoolean$;
         3: pop
         4: aload_0
         5: invokevirtual #93                 // Method self:()Z
         8: pop
         9: getstatic     #43                 // Field scala/math/Ordering$Boolean$.MODULE$:Lscala/math/Ordering$Boolean$;
        12: areturn
      LineNumberTable:
        line 17: 4
        line 18: 9
        line 17: 12
      LocalVariableTable:
        Start  Length  Slot  Name   Signature
            0      13     0  this   Lscala/runtime/RichBoolean;

  public java.lang.Object self();
    descriptor: ()Ljava/lang/Object;
    flags: (0x1041) ACC_PUBLIC, ACC_BRIDGE, ACC_SYNTHETIC
    Code:
      stack=1, locals=1, args_size=1
         0: aload_0
         1: invokevirtual #93                 // Method self:()Z
         4: invokestatic  #103                // Method scala/runtime/BoxesRunTime.boxToBoolean:(Z)Ljava/lang/Boolean;
         7: areturn
      LineNumberTable:
        line 17: 0
      LocalVariableTable:
        Start  Length  Slot  Name   Signature
            0       8     0  this   Lscala/runtime/RichBoolean;

  public scala.runtime.RichBoolean(boolean);
    descriptor: (Z)V
    flags: (0x0001) ACC_PUBLIC
    Code:
      stack=2, locals=2, args_size=2
         0: aload_0
         1: iload_1
         2: putfield      #89                 // Field self:Z
         5: aload_0
         6: invokespecial #108                // Method java/lang/Object."<init>":()V
         9: return
      LineNumberTable:
        line 17: 0
      LocalVariableTable:
        Start  Length  Slot  Name   Signature
            0      10     0  this   Lscala/runtime/RichBoolean;
            0      10     1  self   Z
    MethodParameters:
      Name                           Flags
      self                           final
}
InnerClasses:
  public static #16= #13 of #15;          // Boolean$=class scala/math/Ordering$Boolean$ of class scala/math/Ordering
Signature: #3                           // Ljava/lang/Object;Lscala/runtime/OrderedProxy<Ljava/lang/Object;>;
SourceFile: "RichBoolean.scala"
RuntimeVisibleAnnotations:
  0: #9(#10=s#11)
    scala.reflect.ScalaSignature(
      bytes="\u0006\u0005]3A!\u0004\b\u0003\'!Aq\u0004\u0001BC\u0002\u0013\u0005\u0001\u0005\u0003\u0005\"\u0001\t\u0005\t\u0015!\u0003\u001d\u0011\u0015\u0011\u0003\u0001\"\u0001$\u0011\u00151\u0003\u0001\"\u0005(\u0011\u001dA\u0004!!A\u0005BeBq!\u0010\u0001\u0002\u0002\u0013\u0005chB\u0004E\u001d\u0005\u0005\t\u0012A#\u0007\u000f5q\u0011\u0011!E\u0001\r\")!\u0005\u0003C\u0001\u0015\")1\n\u0003C\u0003\u0019\"9q\nCA\u0001\n\u000b\u0001\u0006b\u0002*\t\u0003\u0003%)a\u0015\u0002\f%&\u001c\u0007NQ8pY\u0016\fgN\u0003\u0002\u0010!\u00059!/\u001e8uS6,\'\"A\t\u0002\u000bM\u001c\u0017\r\\1\u0004\u0001M\u0019\u0001\u0001\u0006\r\u0011\u0005U1R\"\u0001\t\n\u0005]\u0001\"AB!osZ\u000bG\u000eE\u0002\u001a5qi\u0011AD\u0005\u000379\u0011Ab\u0014:eKJ,G\r\u0015:pqf\u0004\"!F\u000f\n\u0005y\u0001\"a\u0002\"p_2,\u0017M\\\u0001\u0005g\u0016dg-F\u0001\u001d\u0003\u0015\u0019X\r\u001c4!\u0003\u0019a\u0014N\\5u}Q\u0011A%\n\t\u00033\u0001AQaH\u0002A\u0002q\t1a\u001c:e+\u0005A\u0003CA\u00156\u001d\tQ#G\u0004\u0002,a9\u0011AfL\u0007\u0002[)\u0011aFE\u0001\u0007yI|w\u000e\u001e \n\u0003EI!!\r\t\u0002\t5\fG\u000f[\u0005\u0003gQ\n\u0001b\u0014:eKJLgn\u001a\u0006\u0003cAQ!AN\u001c\u0002\u000f\t{w\u000e\\3b]*\u00111\u0007N\u0001\tQ\u0006\u001c\bnQ8eKR\t!\b\u0005\u0002\u0016w%\u0011A\b\u0005\u0002\u0004\u0013:$\u0018AB3rk\u0006d7\u000f\u0006\u0002\u001d\u007f!9\u0001IBA\u0001\u0002\u0004\t\u0015a\u0001=%cA\u0011QCQ\u0005\u0003\u0007B\u00111!\u00118z\u0003-\u0011\u0016n\u00195C_>dW-\u00198\u0011\u0005eA1C\u0001\u0005H!\t)\u0002*\u0003\u0002J!\t1\u0011I\\=SK\u001a$\u0012!R\u0001\u000e_J$G%\u001a=uK:\u001c\u0018n\u001c8\u0015\u0005!j\u0005\"\u0002(\u000b\u0001\u0004!\u0013!\u0002\u0013uQ&\u001c\u0018A\u00055bg\"\u001cu\u000eZ3%Kb$XM\\:j_:$\"!O)\t\u000b9[\u0001\u0019\u0001\u0013\u0002!\u0015\fX/\u00197tI\u0015DH/\u001a8tS>tGC\u0001+W)\taR\u000bC\u0004A\u0019\u0005\u0005\t\u0019A!\t\u000b9c\u0001\u0019\u0001\u0013"
    )
  ScalaInlineInfo: length = 0x4A (unknown attribute)
   01 01 00 0E 00 46 00 3E 01 00 4E 00 3E 01 00 3D
   00 3E 01 00 4A 00 3E 01 00 68 00 69 01 00 2C 00
   2D 01 00 52 00 2D 01 00 5F 00 3E 01 00 24 00 5E
   01 00 5A 00 5B 01 00 5A 00 60 01 00 11 00 61 01
   00 11 00 57 01 00 35 00 36 01
  ScalaSig: length = 0x3 (unknown attribute)
   05 02 00
