Classfile /Users/mw/Projects/slang-braindump/.jar/jar8/assemble/slang-braindump/assemble/content/scala/runtime/ScalaRunTime$.class
  Last modified May 29, 2022; size 22271 bytes
  SHA-256 checksum dc1d94d372da957003e2651d22b465a0e3b9e37ea1460fc87a8887156d4fa838
  Compiled from "ScalaRunTime.scala"
public final class scala.runtime.ScalaRunTime$
  minor version: 0
  major version: 52
  flags: (0x0031) ACC_PUBLIC, ACC_FINAL, ACC_SUPER
  this_class: #2                          // scala/runtime/ScalaRunTime$
  super_class: #4                         // java/lang/Object
  interfaces: 0, fields: 1, methods: 60, attributes: 5
Constant pool:
    #1 = Utf8               scala/runtime/ScalaRunTime$
    #2 = Class              #1            // scala/runtime/ScalaRunTime$
    #3 = Utf8               java/lang/Object
    #4 = Class              #3            // java/lang/Object
    #5 = Utf8               ScalaRunTime.scala
    #6 = Utf8               java/lang/invoke/MethodHandles$Lookup
    #7 = Class              #6            // java/lang/invoke/MethodHandles$Lookup
    #8 = Utf8               java/lang/invoke/MethodHandles
    #9 = Class              #8            // java/lang/invoke/MethodHandles
   #10 = Utf8               Lookup
   #11 = Utf8               scala/collection/immutable/ArraySeq$ofBoolean
   #12 = Class              #11           // scala/collection/immutable/ArraySeq$ofBoolean
   #13 = Utf8               scala/collection/immutable/ArraySeq
   #14 = Class              #13           // scala/collection/immutable/ArraySeq
   #15 = Utf8               ofBoolean
   #16 = Utf8               scala/collection/immutable/ArraySeq$ofByte
   #17 = Class              #16           // scala/collection/immutable/ArraySeq$ofByte
   #18 = Utf8               ofByte
   #19 = Utf8               scala/collection/immutable/ArraySeq$ofChar
   #20 = Class              #19           // scala/collection/immutable/ArraySeq$ofChar
   #21 = Utf8               ofChar
   #22 = Utf8               scala/collection/immutable/ArraySeq$ofDouble
   #23 = Class              #22           // scala/collection/immutable/ArraySeq$ofDouble
   #24 = Utf8               ofDouble
   #25 = Utf8               scala/collection/immutable/ArraySeq$ofFloat
   #26 = Class              #25           // scala/collection/immutable/ArraySeq$ofFloat
   #27 = Utf8               ofFloat
   #28 = Utf8               scala/collection/immutable/ArraySeq$ofInt
   #29 = Class              #28           // scala/collection/immutable/ArraySeq$ofInt
   #30 = Utf8               ofInt
   #31 = Utf8               scala/collection/immutable/ArraySeq$ofLong
   #32 = Class              #31           // scala/collection/immutable/ArraySeq$ofLong
   #33 = Utf8               ofLong
   #34 = Utf8               scala/collection/immutable/ArraySeq$ofRef
   #35 = Class              #34           // scala/collection/immutable/ArraySeq$ofRef
   #36 = Utf8               ofRef
   #37 = Utf8               scala/collection/immutable/ArraySeq$ofShort
   #38 = Class              #37           // scala/collection/immutable/ArraySeq$ofShort
   #39 = Utf8               ofShort
   #40 = Utf8               scala/collection/immutable/ArraySeq$ofUnit
   #41 = Class              #40           // scala/collection/immutable/ArraySeq$ofUnit
   #42 = Utf8               ofUnit
   #43 = Utf8               scala/collection/immutable/Range$Exclusive
   #44 = Class              #43           // scala/collection/immutable/Range$Exclusive
   #45 = Utf8               scala/collection/immutable/Range
   #46 = Class              #45           // scala/collection/immutable/Range
   #47 = Utf8               Exclusive
   #48 = Utf8               scala/runtime/ScalaRunTime$$anon$1
   #49 = Class              #48           // scala/runtime/ScalaRunTime$$anon$1
   #50 = Utf8               MODULE$
   #51 = Utf8               Lscala/runtime/ScalaRunTime$;
   #52 = Utf8               <clinit>
   #53 = Utf8               ()V
   #54 = Utf8               <init>
   #55 = NameAndType        #54:#53       // "<init>":()V
   #56 = Methodref          #2.#55        // scala/runtime/ScalaRunTime$."<init>":()V
   #57 = NameAndType        #50:#51       // MODULE$:Lscala/runtime/ScalaRunTime$;
   #58 = Fieldref           #2.#57        // scala/runtime/ScalaRunTime$.MODULE$:Lscala/runtime/ScalaRunTime$;
   #59 = Utf8               isArray
   #60 = Utf8               (Ljava/lang/Object;I)Z
   #61 = Utf8               x
   #62 = Utf8               atLevel
   #63 = Utf8               getClass
   #64 = Utf8               ()Ljava/lang/Class;
   #65 = NameAndType        #63:#64       // getClass:()Ljava/lang/Class;
   #66 = Methodref          #4.#65        // java/lang/Object.getClass:()Ljava/lang/Class;
   #67 = Utf8               isArrayClass
   #68 = Utf8               (Ljava/lang/Class;I)Z
   #69 = NameAndType        #67:#68       // isArrayClass:(Ljava/lang/Class;I)Z
   #70 = Methodref          #2.#69        // scala/runtime/ScalaRunTime$.isArrayClass:(Ljava/lang/Class;I)Z
   #71 = Utf8               this
   #72 = Utf8               Ljava/lang/Object;
   #73 = Utf8               I
   #74 = Utf8               isArray$default$2
   #75 = Utf8               ()I
   #76 = Utf8               (Ljava/lang/Class<*>;I)Z
   #77 = Utf8               clazz
   #78 = Utf8               java/lang/Class
   #79 = Class              #78           // java/lang/Class
   #80 = Utf8               ()Z
   #81 = NameAndType        #59:#80       // isArray:()Z
   #82 = Methodref          #79.#81       // java/lang/Class.isArray:()Z
   #83 = Utf8               getComponentType
   #84 = NameAndType        #83:#64       // getComponentType:()Ljava/lang/Class;
   #85 = Methodref          #79.#84       // java/lang/Class.getComponentType:()Ljava/lang/Class;
   #86 = Utf8               Ljava/lang/Class;
   #87 = Utf8               drop
   #88 = Utf8               (Ljava/lang/Object;ILscala/collection/generic/IsIterable;)Ljava/lang/Object;
   #89 = Utf8               <Repr:Ljava/lang/Object;>(TRepr;ILscala/collection/generic/IsIterable<TRepr;>;)TRepr;
   #90 = Utf8               coll
   #91 = Utf8               num
   #92 = Utf8               iterable
   #93 = Utf8               scala/collection/generic/IsIterable
   #94 = Class              #93           // scala/collection/generic/IsIterable
   #95 = Utf8               apply
   #96 = Utf8               (Ljava/lang/Object;)Lscala/collection/IterableOps;
   #97 = NameAndType        #95:#96       // apply:(Ljava/lang/Object;)Lscala/collection/IterableOps;
   #98 = InterfaceMethodref #94.#97       // scala/collection/generic/IsIterable.apply:(Ljava/lang/Object;)Lscala/collection/IterableOps;
   #99 = Utf8               scala/collection/IterableOps
  #100 = Class              #99           // scala/collection/IterableOps
  #101 = Utf8               (I)Ljava/lang/Object;
  #102 = NameAndType        #87:#101      // drop:(I)Ljava/lang/Object;
  #103 = InterfaceMethodref #100.#102     // scala/collection/IterableOps.drop:(I)Ljava/lang/Object;
  #104 = Utf8               Lscala/collection/generic/IsIterable;
  #105 = Utf8               arrayClass
  #106 = Utf8               (Ljava/lang/Class;)Ljava/lang/Class;
  #107 = Utf8               (Ljava/lang/Class<*>;)Ljava/lang/Class<*>;
  #108 = Utf8               java/lang/Void
  #109 = Class              #108          // java/lang/Void
  #110 = Utf8               TYPE
  #111 = NameAndType        #110:#86      // TYPE:Ljava/lang/Class;
  #112 = Fieldref           #109.#111     // java/lang/Void.TYPE:Ljava/lang/Class;
  #113 = Utf8               equals
  #114 = Utf8               (Ljava/lang/Object;)Z
  #115 = NameAndType        #113:#114     // equals:(Ljava/lang/Object;)Z
  #116 = Methodref          #4.#115       // java/lang/Object.equals:(Ljava/lang/Object;)Z
  #117 = Utf8               [Lscala/runtime/BoxedUnit;
  #118 = Class              #117          // "[Lscala/runtime/BoxedUnit;"
  #119 = Utf8               java/lang/reflect/Array
  #120 = Class              #119          // java/lang/reflect/Array
  #121 = Utf8               newInstance
  #122 = Utf8               (Ljava/lang/Class;I)Ljava/lang/Object;
  #123 = NameAndType        #121:#122     // newInstance:(Ljava/lang/Class;I)Ljava/lang/Object;
  #124 = Methodref          #120.#123     // java/lang/reflect/Array.newInstance:(Ljava/lang/Class;I)Ljava/lang/Object;
  #125 = Utf8               anyValClass
  #126 = Utf8               (Ljava/lang/Object;Lscala/reflect/ClassTag;)Ljava/lang/Class;
  #127 = Utf8               <T:Ljava/lang/Object;>(TT;Lscala/reflect/ClassTag<TT;>;)Ljava/lang/Class<TT;>;
  #128 = Utf8               value
  #129 = Utf8               evidence$1
  #130 = Utf8               scala/reflect/package$
  #131 = Class              #130          // scala/reflect/package$
  #132 = Utf8               Lscala/reflect/package$;
  #133 = NameAndType        #50:#132      // MODULE$:Lscala/reflect/package$;
  #134 = Fieldref           #131.#133     // scala/reflect/package$.MODULE$:Lscala/reflect/package$;
  #135 = Utf8               scala/reflect/ClassTag
  #136 = Class              #135          // scala/reflect/ClassTag
  #137 = Utf8               runtimeClass
  #138 = NameAndType        #137:#64      // runtimeClass:()Ljava/lang/Class;
  #139 = InterfaceMethodref #136.#138     // scala/reflect/ClassTag.runtimeClass:()Ljava/lang/Class;
  #140 = Utf8               Lscala/reflect/ClassTag;
  #141 = Utf8               array_apply
  #142 = Utf8               (Ljava/lang/Object;I)Ljava/lang/Object;
  #143 = Utf8               xs
  #144 = Utf8               idx
  #145 = Utf8               [Ljava/lang/Object;
  #146 = Class              #145          // "[Ljava/lang/Object;"
  #147 = Utf8               [I
  #148 = Class              #147          // "[I"
  #149 = Utf8               java/lang/Integer
  #150 = Class              #149          // java/lang/Integer
  #151 = Utf8               valueOf
  #152 = Utf8               (I)Ljava/lang/Integer;
  #153 = NameAndType        #151:#152     // valueOf:(I)Ljava/lang/Integer;
  #154 = Methodref          #150.#153     // java/lang/Integer.valueOf:(I)Ljava/lang/Integer;
  #155 = Utf8               [D
  #156 = Class              #155          // "[D"
  #157 = Utf8               java/lang/Double
  #158 = Class              #157          // java/lang/Double
  #159 = Utf8               (D)Ljava/lang/Double;
  #160 = NameAndType        #151:#159     // valueOf:(D)Ljava/lang/Double;
  #161 = Methodref          #158.#160     // java/lang/Double.valueOf:(D)Ljava/lang/Double;
  #162 = Utf8               [J
  #163 = Class              #162          // "[J"
  #164 = Utf8               java/lang/Long
  #165 = Class              #164          // java/lang/Long
  #166 = Utf8               (J)Ljava/lang/Long;
  #167 = NameAndType        #151:#166     // valueOf:(J)Ljava/lang/Long;
  #168 = Methodref          #165.#167     // java/lang/Long.valueOf:(J)Ljava/lang/Long;
  #169 = Utf8               [F
  #170 = Class              #169          // "[F"
  #171 = Utf8               java/lang/Float
  #172 = Class              #171          // java/lang/Float
  #173 = Utf8               (F)Ljava/lang/Float;
  #174 = NameAndType        #151:#173     // valueOf:(F)Ljava/lang/Float;
  #175 = Methodref          #172.#174     // java/lang/Float.valueOf:(F)Ljava/lang/Float;
  #176 = Utf8               [C
  #177 = Class              #176          // "[C"
  #178 = Utf8               java/lang/Character
  #179 = Class              #178          // java/lang/Character
  #180 = Utf8               (C)Ljava/lang/Character;
  #181 = NameAndType        #151:#180     // valueOf:(C)Ljava/lang/Character;
  #182 = Methodref          #179.#181     // java/lang/Character.valueOf:(C)Ljava/lang/Character;
  #183 = Utf8               [B
  #184 = Class              #183          // "[B"
  #185 = Utf8               java/lang/Byte
  #186 = Class              #185          // java/lang/Byte
  #187 = Utf8               (B)Ljava/lang/Byte;
  #188 = NameAndType        #151:#187     // valueOf:(B)Ljava/lang/Byte;
  #189 = Methodref          #186.#188     // java/lang/Byte.valueOf:(B)Ljava/lang/Byte;
  #190 = Utf8               [S
  #191 = Class              #190          // "[S"
  #192 = Utf8               java/lang/Short
  #193 = Class              #192          // java/lang/Short
  #194 = Utf8               (S)Ljava/lang/Short;
  #195 = NameAndType        #151:#194     // valueOf:(S)Ljava/lang/Short;
  #196 = Methodref          #193.#195     // java/lang/Short.valueOf:(S)Ljava/lang/Short;
  #197 = Utf8               [Z
  #198 = Class              #197          // "[Z"
  #199 = Utf8               java/lang/Boolean
  #200 = Class              #199          // java/lang/Boolean
  #201 = Utf8               (Z)Ljava/lang/Boolean;
  #202 = NameAndType        #151:#201     // valueOf:(Z)Ljava/lang/Boolean;
  #203 = Methodref          #200.#202     // java/lang/Boolean.valueOf:(Z)Ljava/lang/Boolean;
  #204 = Utf8               java/lang/NullPointerException
  #205 = Class              #204          // java/lang/NullPointerException
  #206 = Methodref          #205.#55      // java/lang/NullPointerException."<init>":()V
  #207 = Utf8               scala/MatchError
  #208 = Class              #207          // scala/MatchError
  #209 = Utf8               (Ljava/lang/Object;)V
  #210 = NameAndType        #54:#209      // "<init>":(Ljava/lang/Object;)V
  #211 = Methodref          #208.#210     // scala/MatchError."<init>":(Ljava/lang/Object;)V
  #212 = Utf8               array_update
  #213 = Utf8               (Ljava/lang/Object;ILjava/lang/Object;)V
  #214 = Utf8               scala/runtime/BoxesRunTime
  #215 = Class              #214          // scala/runtime/BoxesRunTime
  #216 = Utf8               unboxToInt
  #217 = Utf8               (Ljava/lang/Object;)I
  #218 = NameAndType        #216:#217     // unboxToInt:(Ljava/lang/Object;)I
  #219 = Methodref          #215.#218     // scala/runtime/BoxesRunTime.unboxToInt:(Ljava/lang/Object;)I
  #220 = Utf8               unboxToDouble
  #221 = Utf8               (Ljava/lang/Object;)D
  #222 = NameAndType        #220:#221     // unboxToDouble:(Ljava/lang/Object;)D
  #223 = Methodref          #215.#222     // scala/runtime/BoxesRunTime.unboxToDouble:(Ljava/lang/Object;)D
  #224 = Utf8               unboxToLong
  #225 = Utf8               (Ljava/lang/Object;)J
  #226 = NameAndType        #224:#225     // unboxToLong:(Ljava/lang/Object;)J
  #227 = Methodref          #215.#226     // scala/runtime/BoxesRunTime.unboxToLong:(Ljava/lang/Object;)J
  #228 = Utf8               unboxToFloat
  #229 = Utf8               (Ljava/lang/Object;)F
  #230 = NameAndType        #228:#229     // unboxToFloat:(Ljava/lang/Object;)F
  #231 = Methodref          #215.#230     // scala/runtime/BoxesRunTime.unboxToFloat:(Ljava/lang/Object;)F
  #232 = Utf8               unboxToChar
  #233 = Utf8               (Ljava/lang/Object;)C
  #234 = NameAndType        #232:#233     // unboxToChar:(Ljava/lang/Object;)C
  #235 = Methodref          #215.#234     // scala/runtime/BoxesRunTime.unboxToChar:(Ljava/lang/Object;)C
  #236 = Utf8               unboxToByte
  #237 = Utf8               (Ljava/lang/Object;)B
  #238 = NameAndType        #236:#237     // unboxToByte:(Ljava/lang/Object;)B
  #239 = Methodref          #215.#238     // scala/runtime/BoxesRunTime.unboxToByte:(Ljava/lang/Object;)B
  #240 = Utf8               unboxToShort
  #241 = Utf8               (Ljava/lang/Object;)S
  #242 = NameAndType        #240:#241     // unboxToShort:(Ljava/lang/Object;)S
  #243 = Methodref          #215.#242     // scala/runtime/BoxesRunTime.unboxToShort:(Ljava/lang/Object;)S
  #244 = Utf8               unboxToBoolean
  #245 = NameAndType        #244:#114     // unboxToBoolean:(Ljava/lang/Object;)Z
  #246 = Methodref          #215.#245     // scala/runtime/BoxesRunTime.unboxToBoolean:(Ljava/lang/Object;)Z
  #247 = Utf8               array_length
  #248 = Utf8               getLength
  #249 = NameAndType        #248:#217     // getLength:(Ljava/lang/Object;)I
  #250 = Methodref          #120.#249     // java/lang/reflect/Array.getLength:(Ljava/lang/Object;)I
  #251 = Utf8               array_clone
  #252 = Utf8               (Ljava/lang/Object;)Ljava/lang/Object;
  #253 = Utf8               clone
  #254 = Utf8               ()Ljava/lang/Object;
  #255 = NameAndType        #253:#254     // clone:()Ljava/lang/Object;
  #256 = Methodref          #146.#255     // "[Ljava/lang/Object;".clone:()Ljava/lang/Object;
  #257 = Methodref          #148.#255     // "[I".clone:()Ljava/lang/Object;
  #258 = Methodref          #156.#255     // "[D".clone:()Ljava/lang/Object;
  #259 = Methodref          #163.#255     // "[J".clone:()Ljava/lang/Object;
  #260 = Methodref          #170.#255     // "[F".clone:()Ljava/lang/Object;
  #261 = Methodref          #177.#255     // "[C".clone:()Ljava/lang/Object;
  #262 = Methodref          #184.#255     // "[B".clone:()Ljava/lang/Object;
  #263 = Methodref          #191.#255     // "[S".clone:()Ljava/lang/Object;
  #264 = Methodref          #198.#255     // "[Z".clone:()Ljava/lang/Object;
  #265 = Utf8               toObjectArray
  #266 = Utf8               (Ljava/lang/Object;)[Ljava/lang/Object;
  #267 = Utf8               src
  #268 = Utf8               copy$mIc$sp$1
  #269 = Utf8               ([I)[Ljava/lang/Object;
  #270 = NameAndType        #268:#269     // copy$mIc$sp$1:([I)[Ljava/lang/Object;
  #271 = Methodref          #2.#270       // scala/runtime/ScalaRunTime$.copy$mIc$sp$1:([I)[Ljava/lang/Object;
  #272 = Utf8               copy$mDc$sp$1
  #273 = Utf8               ([D)[Ljava/lang/Object;
  #274 = NameAndType        #272:#273     // copy$mDc$sp$1:([D)[Ljava/lang/Object;
  #275 = Methodref          #2.#274       // scala/runtime/ScalaRunTime$.copy$mDc$sp$1:([D)[Ljava/lang/Object;
  #276 = Utf8               copy$mJc$sp$1
  #277 = Utf8               ([J)[Ljava/lang/Object;
  #278 = NameAndType        #276:#277     // copy$mJc$sp$1:([J)[Ljava/lang/Object;
  #279 = Methodref          #2.#278       // scala/runtime/ScalaRunTime$.copy$mJc$sp$1:([J)[Ljava/lang/Object;
  #280 = Utf8               copy$mFc$sp$1
  #281 = Utf8               ([F)[Ljava/lang/Object;
  #282 = NameAndType        #280:#281     // copy$mFc$sp$1:([F)[Ljava/lang/Object;
  #283 = Methodref          #2.#282       // scala/runtime/ScalaRunTime$.copy$mFc$sp$1:([F)[Ljava/lang/Object;
  #284 = Utf8               copy$mCc$sp$1
  #285 = Utf8               ([C)[Ljava/lang/Object;
  #286 = NameAndType        #284:#285     // copy$mCc$sp$1:([C)[Ljava/lang/Object;
  #287 = Methodref          #2.#286       // scala/runtime/ScalaRunTime$.copy$mCc$sp$1:([C)[Ljava/lang/Object;
  #288 = Utf8               copy$mBc$sp$1
  #289 = Utf8               ([B)[Ljava/lang/Object;
  #290 = NameAndType        #288:#289     // copy$mBc$sp$1:([B)[Ljava/lang/Object;
  #291 = Methodref          #2.#290       // scala/runtime/ScalaRunTime$.copy$mBc$sp$1:([B)[Ljava/lang/Object;
  #292 = Utf8               copy$mSc$sp$1
  #293 = Utf8               ([S)[Ljava/lang/Object;
  #294 = NameAndType        #292:#293     // copy$mSc$sp$1:([S)[Ljava/lang/Object;
  #295 = Methodref          #2.#294       // scala/runtime/ScalaRunTime$.copy$mSc$sp$1:([S)[Ljava/lang/Object;
  #296 = Utf8               copy$mZc$sp$1
  #297 = Utf8               ([Z)[Ljava/lang/Object;
  #298 = NameAndType        #296:#297     // copy$mZc$sp$1:([Z)[Ljava/lang/Object;
  #299 = Methodref          #2.#298       // scala/runtime/ScalaRunTime$.copy$mZc$sp$1:([Z)[Ljava/lang/Object;
  #300 = Utf8               toArray
  #301 = Utf8               (Lscala/collection/Seq;)[Ljava/lang/Object;
  #302 = Utf8               <T:Ljava/lang/Object;>(Lscala/collection/Seq<TT;>;)[Ljava/lang/Object;
  #303 = Utf8               scala/collection/Seq
  #304 = Class              #303          // scala/collection/Seq
  #305 = Utf8               isEmpty
  #306 = NameAndType        #305:#80      // isEmpty:()Z
  #307 = InterfaceMethodref #304.#306     // scala/collection/Seq.isEmpty:()Z
  #308 = Utf8               scala/Array$
  #309 = Class              #308          // scala/Array$
  #310 = Utf8               Lscala/Array$;
  #311 = NameAndType        #50:#310      // MODULE$:Lscala/Array$;
  #312 = Fieldref           #309.#311     // scala/Array$.MODULE$:Lscala/Array$;
  #313 = Utf8               emptyObjectArray
  #314 = Utf8               ()[Ljava/lang/Object;
  #315 = NameAndType        #313:#314     // emptyObjectArray:()[Ljava/lang/Object;
  #316 = Methodref          #309.#315     // scala/Array$.emptyObjectArray:()[Ljava/lang/Object;
  #317 = Utf8               length
  #318 = NameAndType        #317:#75      // length:()I
  #319 = InterfaceMethodref #304.#318     // scala/collection/Seq.length:()I
  #320 = Utf8               iterator
  #321 = Utf8               ()Lscala/collection/Iterator;
  #322 = NameAndType        #320:#321     // iterator:()Lscala/collection/Iterator;
  #323 = InterfaceMethodref #304.#322     // scala/collection/Seq.iterator:()Lscala/collection/Iterator;
  #324 = Utf8               scala/collection/Iterator
  #325 = Class              #324          // scala/collection/Iterator
  #326 = Utf8               hasNext
  #327 = NameAndType        #326:#80      // hasNext:()Z
  #328 = InterfaceMethodref #325.#327     // scala/collection/Iterator.hasNext:()Z
  #329 = Utf8               next
  #330 = NameAndType        #329:#254     // next:()Ljava/lang/Object;
  #331 = InterfaceMethodref #325.#330     // scala/collection/Iterator.next:()Ljava/lang/Object;
  #332 = Utf8               arr
  #333 = Utf8               it
  #334 = Utf8               Lscala/collection/Iterator;
  #335 = Utf8               i
  #336 = Utf8               Lscala/collection/Seq;
  #337 = Utf8               ensureAccessible
  #338 = Utf8               (Ljava/lang/reflect/Method;)Ljava/lang/reflect/Method;
  #339 = Utf8               m
  #340 = Utf8               (Ljava/lang/reflect/AccessibleObject;)Ljava/lang/reflect/AccessibleObject;
  #341 = NameAndType        #337:#340     // ensureAccessible:(Ljava/lang/reflect/AccessibleObject;)Ljava/lang/reflect/AccessibleObject;
  #342 = Methodref          #131.#341     // scala/reflect/package$.ensureAccessible:(Ljava/lang/reflect/AccessibleObject;)Ljava/lang/reflect/AccessibleObject;
  #343 = Utf8               java/lang/reflect/Method
  #344 = Class              #343          // java/lang/reflect/Method
  #345 = Utf8               Ljava/lang/reflect/Method;
  #346 = Utf8               _toString
  #347 = Utf8               (Lscala/Product;)Ljava/lang/String;
  #348 = Utf8               scala/Product
  #349 = Class              #348          // scala/Product
  #350 = Utf8               productIterator
  #351 = NameAndType        #350:#321     // productIterator:()Lscala/collection/Iterator;
  #352 = InterfaceMethodref #349.#351     // scala/Product.productIterator:()Lscala/collection/Iterator;
  #353 = Utf8               java/lang/StringBuilder
  #354 = Class              #353          // java/lang/StringBuilder
  #355 = Integer            1
  #356 = Utf8               (I)V
  #357 = NameAndType        #54:#356      // "<init>":(I)V
  #358 = Methodref          #354.#357     // java/lang/StringBuilder."<init>":(I)V
  #359 = Utf8               productPrefix
  #360 = Utf8               ()Ljava/lang/String;
  #361 = NameAndType        #359:#360     // productPrefix:()Ljava/lang/String;
  #362 = InterfaceMethodref #349.#361     // scala/Product.productPrefix:()Ljava/lang/String;
  #363 = Utf8               append
  #364 = Utf8               (Ljava/lang/String;)Ljava/lang/StringBuilder;
  #365 = NameAndType        #363:#364     // append:(Ljava/lang/String;)Ljava/lang/StringBuilder;
  #366 = Methodref          #354.#365     // java/lang/StringBuilder.append:(Ljava/lang/String;)Ljava/lang/StringBuilder;
  #367 = Utf8               (
  #368 = String             #367          // (
  #369 = Utf8               toString
  #370 = NameAndType        #369:#360     // toString:()Ljava/lang/String;
  #371 = Methodref          #354.#370     // java/lang/StringBuilder.toString:()Ljava/lang/String;
  #372 = Utf8               ,
  #373 = String             #372          // ,
  #374 = Utf8               )
  #375 = String             #374          // )
  #376 = Utf8               mkString
  #377 = Utf8               (Ljava/lang/String;Ljava/lang/String;Ljava/lang/String;)Ljava/lang/String;
  #378 = NameAndType        #376:#377     // mkString:(Ljava/lang/String;Ljava/lang/String;Ljava/lang/String;)Ljava/lang/String;
  #379 = InterfaceMethodref #325.#378     // scala/collection/Iterator.mkString:(Ljava/lang/String;Ljava/lang/String;Ljava/lang/String;)Ljava/lang/String;
  #380 = Utf8               Lscala/Product;
  #381 = Utf8               _hashCode
  #382 = Utf8               (Lscala/Product;)I
  #383 = Utf8               scala/util/hashing/MurmurHash3$
  #384 = Class              #383          // scala/util/hashing/MurmurHash3$
  #385 = Utf8               Lscala/util/hashing/MurmurHash3$;
  #386 = NameAndType        #50:#385      // MODULE$:Lscala/util/hashing/MurmurHash3$;
  #387 = Fieldref           #384.#386     // scala/util/hashing/MurmurHash3$.MODULE$:Lscala/util/hashing/MurmurHash3$;
  #388 = Utf8               productHash
  #389 = NameAndType        #388:#382     // productHash:(Lscala/Product;)I
  #390 = Methodref          #384.#389     // scala/util/hashing/MurmurHash3$.productHash:(Lscala/Product;)I
  #391 = Utf8               typedProductIterator
  #392 = Utf8               (Lscala/Product;)Lscala/collection/Iterator;
  #393 = Utf8               <T:Ljava/lang/Object;>(Lscala/Product;)Lscala/collection/Iterator<TT;>;
  #394 = Utf8               (Lscala/Product;)V
  #395 = NameAndType        #54:#394      // "<init>":(Lscala/Product;)V
  #396 = Methodref          #49.#395      // scala/runtime/ScalaRunTime$$anon$1."<init>":(Lscala/Product;)V
  #397 = Utf8               stringOf
  #398 = Utf8               (Ljava/lang/Object;)Ljava/lang/String;
  #399 = Utf8               arg
  #400 = Integer            2147483647
  #401 = Utf8               (Ljava/lang/Object;I)Ljava/lang/String;
  #402 = NameAndType        #397:#401     // stringOf:(Ljava/lang/Object;I)Ljava/lang/String;
  #403 = Methodref          #2.#402       // scala/runtime/ScalaRunTime$.stringOf:(Ljava/lang/Object;I)Ljava/lang/String;
  #404 = Utf8               maxElements
  #405 = Utf8               java/lang/Throwable
  #406 = Class              #405          // java/lang/Throwable
  #407 = Utf8               inner$1
  #408 = NameAndType        #407:#401     // inner$1:(Ljava/lang/Object;I)Ljava/lang/String;
  #409 = Methodref          #2.#408       // scala/runtime/ScalaRunTime$.inner$1:(Ljava/lang/Object;I)Ljava/lang/String;
  #410 = Utf8               java/lang/UnsupportedOperationException
  #411 = Class              #410          // java/lang/UnsupportedOperationException
  #412 = Utf8               java/lang/AssertionError
  #413 = Class              #412          // java/lang/AssertionError
  #414 = Utf8               java/lang/String
  #415 = Class              #414          // java/lang/String
  #416 = NameAndType        #151:#398     // valueOf:(Ljava/lang/Object;)Ljava/lang/String;
  #417 = Methodref          #415.#416     // java/lang/String.valueOf:(Ljava/lang/Object;)Ljava/lang/String;
  #418 = Utf8               replStringOf
  #419 = Utf8               hashCode
  #420 = NameAndType        #419:#75      // hashCode:()I
  #421 = Methodref          #415.#420     // java/lang/String.hashCode:()I
  #422 = Utf8               null toString
  #423 = String             #422          // null toString
  #424 = Utf8               indexOf
  #425 = Utf8               (I)I
  #426 = NameAndType        #424:#425     // indexOf:(I)I
  #427 = Methodref          #415.#426     // java/lang/String.indexOf:(I)I
  #428 = Integer            2
  #429 = Utf8               \n
  #430 = String             #429          // \n
  #431 = Utf8               genericWrapArray
  #432 = Utf8               (Ljava/lang/Object;)Lscala/collection/immutable/ArraySeq;
  #433 = Utf8               <T:Ljava/lang/Object;>(Ljava/lang/Object;)Lscala/collection/immutable/ArraySeq<TT;>;
  #434 = Utf8               scala/collection/immutable/ArraySeq$
  #435 = Class              #434          // scala/collection/immutable/ArraySeq$
  #436 = Utf8               Lscala/collection/immutable/ArraySeq$;
  #437 = NameAndType        #50:#436      // MODULE$:Lscala/collection/immutable/ArraySeq$;
  #438 = Fieldref           #435.#437     // scala/collection/immutable/ArraySeq$.MODULE$:Lscala/collection/immutable/ArraySeq$;
  #439 = Utf8               unsafeWrapArray
  #440 = NameAndType        #439:#432     // unsafeWrapArray:(Ljava/lang/Object;)Lscala/collection/immutable/ArraySeq;
  #441 = Methodref          #435.#440     // scala/collection/immutable/ArraySeq$.unsafeWrapArray:(Ljava/lang/Object;)Lscala/collection/immutable/ArraySeq;
  #442 = Utf8               wrapRefArray
  #443 = Utf8               ([Ljava/lang/Object;)Lscala/collection/immutable/ArraySeq;
  #444 = Utf8               <T:Ljava/lang/Object;>([TT;)Lscala/collection/immutable/ArraySeq<TT;>;
  #445 = Utf8               scala/reflect/ClassTag$
  #446 = Class              #445          // scala/reflect/ClassTag$
  #447 = Utf8               Lscala/reflect/ClassTag$;
  #448 = NameAndType        #50:#447      // MODULE$:Lscala/reflect/ClassTag$;
  #449 = Fieldref           #446.#448     // scala/reflect/ClassTag$.MODULE$:Lscala/reflect/ClassTag$;
  #450 = Utf8               AnyRef
  #451 = Utf8               ()Lscala/reflect/ClassTag;
  #452 = NameAndType        #450:#451     // AnyRef:()Lscala/reflect/ClassTag;
  #453 = Methodref          #446.#452     // scala/reflect/ClassTag$.AnyRef:()Lscala/reflect/ClassTag;
  #454 = Utf8               empty
  #455 = Utf8               (Lscala/reflect/ClassTag;)Lscala/collection/immutable/ArraySeq;
  #456 = NameAndType        #454:#455     // empty:(Lscala/reflect/ClassTag;)Lscala/collection/immutable/ArraySeq;
  #457 = Methodref          #435.#456     // scala/collection/immutable/ArraySeq$.empty:(Lscala/reflect/ClassTag;)Lscala/collection/immutable/ArraySeq;
  #458 = Utf8               ([Ljava/lang/Object;)V
  #459 = NameAndType        #54:#458      // "<init>":([Ljava/lang/Object;)V
  #460 = Methodref          #35.#459      // scala/collection/immutable/ArraySeq$ofRef."<init>":([Ljava/lang/Object;)V
  #461 = Utf8               wrapIntArray
  #462 = Utf8               ([I)Lscala/collection/immutable/ArraySeq;
  #463 = Utf8               ([I)Lscala/collection/immutable/ArraySeq<Ljava/lang/Object;>;
  #464 = Utf8               ([I)V
  #465 = NameAndType        #54:#464      // "<init>":([I)V
  #466 = Methodref          #29.#465      // scala/collection/immutable/ArraySeq$ofInt."<init>":([I)V
  #467 = Utf8               wrapDoubleArray
  #468 = Utf8               ([D)Lscala/collection/immutable/ArraySeq;
  #469 = Utf8               ([D)Lscala/collection/immutable/ArraySeq<Ljava/lang/Object;>;
  #470 = Utf8               ([D)V
  #471 = NameAndType        #54:#470      // "<init>":([D)V
  #472 = Methodref          #23.#471      // scala/collection/immutable/ArraySeq$ofDouble."<init>":([D)V
  #473 = Utf8               wrapLongArray
  #474 = Utf8               ([J)Lscala/collection/immutable/ArraySeq;
  #475 = Utf8               ([J)Lscala/collection/immutable/ArraySeq<Ljava/lang/Object;>;
  #476 = Utf8               ([J)V
  #477 = NameAndType        #54:#476      // "<init>":([J)V
  #478 = Methodref          #32.#477      // scala/collection/immutable/ArraySeq$ofLong."<init>":([J)V
  #479 = Utf8               wrapFloatArray
  #480 = Utf8               ([F)Lscala/collection/immutable/ArraySeq;
  #481 = Utf8               ([F)Lscala/collection/immutable/ArraySeq<Ljava/lang/Object;>;
  #482 = Utf8               ([F)V
  #483 = NameAndType        #54:#482      // "<init>":([F)V
  #484 = Methodref          #26.#483      // scala/collection/immutable/ArraySeq$ofFloat."<init>":([F)V
  #485 = Utf8               wrapCharArray
  #486 = Utf8               ([C)Lscala/collection/immutable/ArraySeq;
  #487 = Utf8               ([C)Lscala/collection/immutable/ArraySeq<Ljava/lang/Object;>;
  #488 = Utf8               ([C)V
  #489 = NameAndType        #54:#488      // "<init>":([C)V
  #490 = Methodref          #20.#489      // scala/collection/immutable/ArraySeq$ofChar."<init>":([C)V
  #491 = Utf8               wrapByteArray
  #492 = Utf8               ([B)Lscala/collection/immutable/ArraySeq;
  #493 = Utf8               ([B)Lscala/collection/immutable/ArraySeq<Ljava/lang/Object;>;
  #494 = Utf8               ([B)V
  #495 = NameAndType        #54:#494      // "<init>":([B)V
  #496 = Methodref          #17.#495      // scala/collection/immutable/ArraySeq$ofByte."<init>":([B)V
  #497 = Utf8               wrapShortArray
  #498 = Utf8               ([S)Lscala/collection/immutable/ArraySeq;
  #499 = Utf8               ([S)Lscala/collection/immutable/ArraySeq<Ljava/lang/Object;>;
  #500 = Utf8               ([S)V
  #501 = NameAndType        #54:#500      // "<init>":([S)V
  #502 = Methodref          #38.#501      // scala/collection/immutable/ArraySeq$ofShort."<init>":([S)V
  #503 = Utf8               wrapBooleanArray
  #504 = Utf8               ([Z)Lscala/collection/immutable/ArraySeq;
  #505 = Utf8               ([Z)Lscala/collection/immutable/ArraySeq<Ljava/lang/Object;>;
  #506 = Utf8               ([Z)V
  #507 = NameAndType        #54:#506      // "<init>":([Z)V
  #508 = Methodref          #12.#507      // scala/collection/immutable/ArraySeq$ofBoolean."<init>":([Z)V
  #509 = Utf8               wrapUnitArray
  #510 = Utf8               ([Lscala/runtime/BoxedUnit;)Lscala/collection/immutable/ArraySeq;
  #511 = Utf8               ([Lscala/runtime/BoxedUnit;)Lscala/collection/immutable/ArraySeq<Lscala/runtime/BoxedUnit;>;
  #512 = Utf8               ([Lscala/runtime/BoxedUnit;)V
  #513 = NameAndType        #54:#512      // "<init>":([Lscala/runtime/BoxedUnit;)V
  #514 = Methodref          #41.#513      // scala/collection/immutable/ArraySeq$ofUnit."<init>":([Lscala/runtime/BoxedUnit;)V
  #515 = Utf8               dest
  #516 = Utf8               copy$mVc$sp$1
  #517 = Utf8               ([Lscala/runtime/BoxedUnit;)[Ljava/lang/Object;
  #518 = Utf8               copy$1
  #519 = NameAndType        #141:#142     // array_apply:(Ljava/lang/Object;I)Ljava/lang/Object;
  #520 = Methodref          #2.#519       // scala/runtime/ScalaRunTime$.array_apply:(Ljava/lang/Object;I)Ljava/lang/Object;
  #521 = Utf8               packageOf$1
  #522 = Utf8               getPackage
  #523 = Utf8               ()Ljava/lang/Package;
  #524 = NameAndType        #522:#523     // getPackage:()Ljava/lang/Package;
  #525 = Methodref          #79.#524      // java/lang/Class.getPackage:()Ljava/lang/Package;
  #526 = Utf8
  #527 = String             #526          //
  #528 = Utf8               java/lang/Package
  #529 = Class              #528          // java/lang/Package
  #530 = Utf8               getName
  #531 = NameAndType        #530:#360     // getName:()Ljava/lang/String;
  #532 = Methodref          #529.#531     // java/lang/Package.getName:()Ljava/lang/String;
  #533 = Utf8               isScalaClass$1
  #534 = NameAndType        #521:#398     // packageOf$1:(Ljava/lang/Object;)Ljava/lang/String;
  #535 = Methodref          #2.#534       // scala/runtime/ScalaRunTime$.packageOf$1:(Ljava/lang/Object;)Ljava/lang/String;
  #536 = Utf8               scala.
  #537 = String             #536          // scala.
  #538 = Utf8               startsWith
  #539 = Utf8               (Ljava/lang/String;)Z
  #540 = NameAndType        #538:#539     // startsWith:(Ljava/lang/String;)Z
  #541 = Methodref          #415.#540     // java/lang/String.startsWith:(Ljava/lang/String;)Z
  #542 = Utf8               isScalaCompilerClass$1
  #543 = Utf8               scala.tools.nsc.
  #544 = String             #543          // scala.tools.nsc.
  #545 = Utf8               isTuple$1
  #546 = Methodref          #79.#531      // java/lang/Class.getName:()Ljava/lang/String;
  #547 = Utf8               scala.Tuple
  #548 = String             #547          // scala.Tuple
  #549 = Utf8               isSubClassOf$1
  #550 = Utf8               (Ljava/lang/Class;Ljava/lang/String;)Z
  #551 = Utf8               potentialSubClass
  #552 = Utf8               ofClass
  #553 = Utf8               java/lang/ClassNotFoundException
  #554 = Class              #553          // java/lang/ClassNotFoundException
  #555 = Utf8               getClassLoader
  #556 = Utf8               ()Ljava/lang/ClassLoader;
  #557 = NameAndType        #555:#556     // getClassLoader:()Ljava/lang/ClassLoader;
  #558 = Methodref          #79.#557      // java/lang/Class.getClassLoader:()Ljava/lang/ClassLoader;
  #559 = Utf8               forName
  #560 = Utf8               (Ljava/lang/String;ZLjava/lang/ClassLoader;)Ljava/lang/Class;
  #561 = NameAndType        #559:#560     // forName:(Ljava/lang/String;ZLjava/lang/ClassLoader;)Ljava/lang/Class;
  #562 = Methodref          #79.#561      // java/lang/Class.forName:(Ljava/lang/String;ZLjava/lang/ClassLoader;)Ljava/lang/Class;
  #563 = Utf8               isAssignableFrom
  #564 = Utf8               (Ljava/lang/Class;)Z
  #565 = NameAndType        #563:#564     // isAssignableFrom:(Ljava/lang/Class;)Z
  #566 = Methodref          #79.#565      // java/lang/Class.isAssignableFrom:(Ljava/lang/Class;)Z
  #567 = Utf8               classLoader
  #568 = Utf8               Ljava/lang/ClassLoader;
  #569 = Utf8               Ljava/lang/String;
  #570 = Utf8               isXmlNode$1
  #571 = Utf8               scala.xml.Node
  #572 = String             #571          // scala.xml.Node
  #573 = NameAndType        #549:#550     // isSubClassOf$1:(Ljava/lang/Class;Ljava/lang/String;)Z
  #574 = Methodref          #2.#573       // scala/runtime/ScalaRunTime$.isSubClassOf$1:(Ljava/lang/Class;Ljava/lang/String;)Z
  #575 = Utf8               isXmlMetaData$1
  #576 = Utf8               scala.xml.MetaData
  #577 = String             #576          // scala.xml.MetaData
  #578 = Utf8               useOwnToString$1
  #579 = Utf8               scala/collection/immutable/NumericRange
  #580 = Class              #579          // scala/collection/immutable/NumericRange
  #581 = Utf8               scala/collection/SortedOps
  #582 = Class              #581          // scala/collection/SortedOps
  #583 = Utf8               scala/collection/StringView
  #584 = Class              #583          // scala/collection/StringView
  #585 = Utf8               scala/collection/StringOps
  #586 = Class              #585          // scala/collection/StringOps
  #587 = Utf8               scala/collection/mutable/StringBuilder
  #588 = Class              #587          // scala/collection/mutable/StringBuilder
  #589 = Utf8               scala/collection/View
  #590 = Class              #589          // scala/collection/View
  #591 = Utf8               scala/collection/Iterable
  #592 = Class              #591          // scala/collection/Iterable
  #593 = Utf8               scala/collection/StrictOptimizedIterableOps
  #594 = Class              #593          // scala/collection/StrictOptimizedIterableOps
  #595 = NameAndType        #533:#114     // isScalaClass$1:(Ljava/lang/Object;)Z
  #596 = Methodref          #2.#595       // scala/runtime/ScalaRunTime$.isScalaClass$1:(Ljava/lang/Object;)Z
  #597 = NameAndType        #542:#114     // isScalaCompilerClass$1:(Ljava/lang/Object;)Z
  #598 = Methodref          #2.#597       // scala/runtime/ScalaRunTime$.isScalaCompilerClass$1:(Ljava/lang/Object;)Z
  #599 = Utf8               mapInner$1
  #600 = Utf8               maxElements$1
  #601 = Utf8               scala/Tuple2
  #602 = Class              #601          // scala/Tuple2
  #603 = Utf8               _1
  #604 = NameAndType        #603:#254     // _1:()Ljava/lang/Object;
  #605 = Methodref          #602.#604     // scala/Tuple2._1:()Ljava/lang/Object;
  #606 = Utf8               _2
  #607 = NameAndType        #606:#254     // _2:()Ljava/lang/Object;
  #608 = Methodref          #602.#607     // scala/Tuple2._2:()Ljava/lang/Object;
  #609 = Integer            4
  #610 = Utf8                ->
  #611 = String             #610          //  ->
  #612 = Utf8               k
  #613 = Utf8               v
  #614 = Utf8               $anonfun$stringOf$1
  #615 = Utf8               (I)Ljava/lang/String;
  #616 = Utf8               x$1
  #617 = Utf8               ()
  #618 = String             #617          // ()
  #619 = Utf8               $anonfun$stringOf$2
  #620 = Utf8               (Lscala/runtime/ScalaRunTime$;ILjava/lang/Object;)Ljava/lang/String;
  #621 = Utf8               $this
  #622 = Utf8               arrayToString$1
  #623 = Utf8               scala/runtime/BoxedUnit
  #624 = Class              #623          // scala/runtime/BoxedUnit
  #625 = Utf8               scala/runtime/RichInt$
  #626 = Class              #625          // scala/runtime/RichInt$
  #627 = Utf8               Lscala/runtime/RichInt$;
  #628 = NameAndType        #50:#627      // MODULE$:Lscala/runtime/RichInt$;
  #629 = Fieldref           #626.#628     // scala/runtime/RichInt$.MODULE$:Lscala/runtime/RichInt$;
  #630 = Utf8               scala/math/package$
  #631 = Class              #630          // scala/math/package$
  #632 = Utf8               Lscala/math/package$;
  #633 = NameAndType        #50:#632      // MODULE$:Lscala/math/package$;
  #634 = Fieldref           #631.#633     // scala/math/package$.MODULE$:Lscala/math/package$;
  #635 = Utf8               java/lang/Math
  #636 = Class              #635          // java/lang/Math
  #637 = Utf8               min
  #638 = Utf8               (II)I
  #639 = NameAndType        #637:#638     // min:(II)I
  #640 = Methodref          #636.#639     // java/lang/Math.min:(II)I
  #641 = Utf8               scala/collection/immutable/Range$
  #642 = Class              #641          // scala/collection/immutable/Range$
  #643 = Utf8               Lscala/collection/immutable/Range$;
  #644 = NameAndType        #50:#643      // MODULE$:Lscala/collection/immutable/Range$;
  #645 = Fieldref           #642.#644     // scala/collection/immutable/Range$.MODULE$:Lscala/collection/immutable/Range$;
  #646 = Utf8               (III)V
  #647 = NameAndType        #54:#646      // "<init>":(III)V
  #648 = Methodref          #44.#647      // scala/collection/immutable/Range$Exclusive."<init>":(III)V
  #649 = Utf8               scala$collection$immutable$Range$$validateMaxLength
  #650 = NameAndType        #649:#53      // scala$collection$immutable$Range$$validateMaxLength:()V
  #651 = Methodref          #46.#650      // scala/collection/immutable/Range.scala$collection$immutable$Range$$validateMaxLength:()V
  #652 = Utf8               scala/collection/immutable/IndexedSeq$
  #653 = Class              #652          // scala/collection/immutable/IndexedSeq$
  #654 = Utf8               Lscala/collection/immutable/IndexedSeq$;
  #655 = NameAndType        #50:#654      // MODULE$:Lscala/collection/immutable/IndexedSeq$;
  #656 = Fieldref           #653.#655     // scala/collection/immutable/IndexedSeq$.MODULE$:Lscala/collection/immutable/IndexedSeq$;
  #657 = Utf8               scala/collection/IterableFactory
  #658 = Class              #657          // scala/collection/IterableFactory
  #659 = Utf8               newBuilder
  #660 = Utf8               ()Lscala/collection/mutable/Builder;
  #661 = NameAndType        #659:#660     // newBuilder:()Lscala/collection/mutable/Builder;
  #662 = InterfaceMethodref #658.#661     // scala/collection/IterableFactory.newBuilder:()Lscala/collection/mutable/Builder;
  #663 = InterfaceMethodref #594.#322     // scala/collection/StrictOptimizedIterableOps.iterator:()Lscala/collection/Iterator;
  #664 = Utf8               scala/collection/mutable/Growable
  #665 = Class              #664          // scala/collection/mutable/Growable
  #666 = Utf8               addOne
  #667 = Utf8               (Ljava/lang/Object;)Lscala/collection/mutable/Growable;
  #668 = NameAndType        #666:#667     // addOne:(Ljava/lang/Object;)Lscala/collection/mutable/Growable;
  #669 = InterfaceMethodref #665.#668     // scala/collection/mutable/Growable.addOne:(Ljava/lang/Object;)Lscala/collection/mutable/Growable;
  #670 = Utf8               scala/collection/mutable/Builder
  #671 = Class              #670          // scala/collection/mutable/Builder
  #672 = Utf8               result
  #673 = NameAndType        #672:#254     // result:()Ljava/lang/Object;
  #674 = InterfaceMethodref #671.#673     // scala/collection/mutable/Builder.result:()Ljava/lang/Object;
  #675 = Utf8               scala/collection/immutable/IndexedSeq
  #676 = Class              #675          // scala/collection/immutable/IndexedSeq
  #677 = Utf8               Array(
  #678 = String             #677          // Array(
  #679 = Utf8               ,
  #680 = String             #679          // ,
  #681 = InterfaceMethodref #676.#378     // scala/collection/immutable/IndexedSeq.mkString:(Ljava/lang/String;Ljava/lang/String;Ljava/lang/String;)Ljava/lang/String;
  #682 = Utf8               scala/collection/ArrayOps$
  #683 = Class              #682          // scala/collection/ArrayOps$
  #684 = Utf8               Lscala/collection/ArrayOps$;
  #685 = NameAndType        #50:#684      // MODULE$:Lscala/collection/ArrayOps$;
  #686 = Fieldref           #683.#685     // scala/collection/ArrayOps$.MODULE$:Lscala/collection/ArrayOps$;
  #687 = Utf8               iterator$extension
  #688 = Utf8               (Ljava/lang/Object;)Lscala/collection/Iterator;
  #689 = NameAndType        #687:#688     // iterator$extension:(Ljava/lang/Object;)Lscala/collection/Iterator;
  #690 = Methodref          #683.#689     // scala/collection/ArrayOps$.iterator$extension:(Ljava/lang/Object;)Lscala/collection/Iterator;
  #691 = Utf8               take
  #692 = Utf8               (I)Lscala/collection/Iterator;
  #693 = NameAndType        #691:#692     // take:(I)Lscala/collection/Iterator;
  #694 = InterfaceMethodref #325.#693     // scala/collection/Iterator.take:(I)Lscala/collection/Iterator;
  #695 = MethodType         #252          //  (Ljava/lang/Object;)Ljava/lang/Object;
  #696 = NameAndType        #619:#620     // $anonfun$stringOf$2:(Lscala/runtime/ScalaRunTime$;ILjava/lang/Object;)Ljava/lang/String;
  #697 = Methodref          #2.#696       // scala/runtime/ScalaRunTime$.$anonfun$stringOf$2:(Lscala/runtime/ScalaRunTime$;ILjava/lang/Object;)Ljava/lang/String;
  #698 = MethodHandle       6:#697        // REF_invokeStatic scala/runtime/ScalaRunTime$.$anonfun$stringOf$2:(Lscala/runtime/ScalaRunTime$;ILjava/lang/Object;)Ljava/lang/String;
  #699 = MethodType         #398          //  (Ljava/lang/Object;)Ljava/lang/String;
  #700 = Integer            5
  #701 = Utf8               java/lang/invoke/LambdaMetafactory
  #702 = Class              #701          // java/lang/invoke/LambdaMetafactory
  #703 = Utf8               altMetafactory
  #704 = Utf8               (Ljava/lang/invoke/MethodHandles$Lookup;Ljava/lang/String;Ljava/lang/invoke/MethodType;[Ljava/lang/Object;)Ljava/lang/invoke/CallSite;
  #705 = NameAndType        #703:#704     // altMetafactory:(Ljava/lang/invoke/MethodHandles$Lookup;Ljava/lang/String;Ljava/lang/invoke/MethodType;[Ljava/lang/Object;)Ljava/lang/invoke/CallSite;
  #706 = Methodref          #702.#705     // java/lang/invoke/LambdaMetafactory.altMetafactory:(Ljava/lang/invoke/MethodHandles$Lookup;Ljava/lang/String;Ljava/lang/invoke/MethodType;[Ljava/lang/Object;)Ljava/lang/invoke/CallSite;
  #707 = MethodHandle       6:#706        // REF_invokeStatic java/lang/invoke/LambdaMetafactory.altMetafactory:(Ljava/lang/invoke/MethodHandles$Lookup;Ljava/lang/String;Ljava/lang/invoke/MethodType;[Ljava/lang/Object;)Ljava/lang/invoke/CallSite;
  #708 = Utf8               (Lscala/runtime/ScalaRunTime$;I)Lscala/Function1;
  #709 = NameAndType        #95:#708      // apply:(Lscala/runtime/ScalaRunTime$;I)Lscala/Function1;
  #710 = InvokeDynamic      #0:#709       // #0:apply:(Lscala/runtime/ScalaRunTime$;I)Lscala/Function1;
  #711 = Utf8               map
  #712 = Utf8               (Lscala/Function1;)Lscala/collection/Iterator;
  #713 = NameAndType        #711:#712     // map:(Lscala/Function1;)Lscala/collection/Iterator;
  #714 = InterfaceMethodref #325.#713     // scala/collection/Iterator.map:(Lscala/Function1;)Lscala/collection/Iterator;
  #715 = Utf8               map_this
  #716 = Utf8               Lscala/collection/immutable/Range;
  #717 = Utf8               strictOptimizedMap_b
  #718 = Utf8               Lscala/collection/mutable/Builder;
  #719 = Utf8               strictOptimizedMap_it
  #720 = Utf8               strictOptimizedMap_$plus$eq_elem
  #721 = Utf8               $anonfun$stringOf$3
  #722 = NameAndType        #599:#401     // mapInner$1:(Ljava/lang/Object;I)Ljava/lang/String;
  #723 = Methodref          #2.#722       // scala/runtime/ScalaRunTime$.mapInner$1:(Ljava/lang/Object;I)Ljava/lang/String;
  #724 = Utf8               $anonfun$stringOf$4
  #725 = Utf8               $anonfun$stringOf$5
  #726 = Utf8               null
  #727 = String             #726          // null
  #728 = Utf8               \"\"
  #729 = String             #728          // \"\"
  #730 = Utf8               scala/runtime/RichChar$
  #731 = Class              #730          // scala/runtime/RichChar$
  #732 = Utf8               Lscala/runtime/RichChar$;
  #733 = NameAndType        #50:#732      // MODULE$:Lscala/runtime/RichChar$;
  #734 = Fieldref           #731.#733     // scala/runtime/RichChar$.MODULE$:Lscala/runtime/RichChar$;
  #735 = Utf8               scala/collection/StringOps$
  #736 = Class              #735          // scala/collection/StringOps$
  #737 = Utf8               Lscala/collection/StringOps$;
  #738 = NameAndType        #50:#737      // MODULE$:Lscala/collection/StringOps$;
  #739 = Fieldref           #736.#738     // scala/collection/StringOps$.MODULE$:Lscala/collection/StringOps$;
  #740 = Utf8               head$extension
  #741 = Utf8               (Ljava/lang/String;)C
  #742 = NameAndType        #740:#741     // head$extension:(Ljava/lang/String;)C
  #743 = Methodref          #736.#742     // scala/collection/StringOps$.head$extension:(Ljava/lang/String;)C
  #744 = Utf8               isWhitespace
  #745 = Utf8               (C)Z
  #746 = NameAndType        #744:#745     // isWhitespace:(C)Z
  #747 = Methodref          #179.#746     // java/lang/Character.isWhitespace:(C)Z
  #748 = Utf8               last$extension
  #749 = NameAndType        #748:#741     // last$extension:(Ljava/lang/String;)C
  #750 = Methodref          #736.#749     // scala/collection/StringOps$.last$extension:(Ljava/lang/String;)C
  #751 = Utf8               \"
  #752 = String             #751          // \"
  #753 = NameAndType        #578:#114     // useOwnToString$1:(Ljava/lang/Object;)Z
  #754 = Methodref          #2.#753       // scala/runtime/ScalaRunTime$.useOwnToString$1:(Ljava/lang/Object;)Z
  #755 = Methodref          #4.#370       // java/lang/Object.toString:()Ljava/lang/String;
  #756 = NameAndType        #59:#60       // isArray:(Ljava/lang/Object;I)Z
  #757 = Methodref          #2.#756       // scala/runtime/ScalaRunTime$.isArray:(Ljava/lang/Object;I)Z
  #758 = NameAndType        #622:#401     // arrayToString$1:(Ljava/lang/Object;I)Ljava/lang/String;
  #759 = Methodref          #2.#758       // scala/runtime/ScalaRunTime$.arrayToString$1:(Ljava/lang/Object;I)Ljava/lang/String;
  #760 = Utf8               scala/collection/Map
  #761 = Class              #760          // scala/collection/Map
  #762 = InterfaceMethodref #761.#322     // scala/collection/Map.iterator:()Lscala/collection/Iterator;
  #763 = NameAndType        #721:#620     // $anonfun$stringOf$3:(Lscala/runtime/ScalaRunTime$;ILjava/lang/Object;)Ljava/lang/String;
  #764 = Methodref          #2.#763       // scala/runtime/ScalaRunTime$.$anonfun$stringOf$3:(Lscala/runtime/ScalaRunTime$;ILjava/lang/Object;)Ljava/lang/String;
  #765 = MethodHandle       6:#764        // REF_invokeStatic scala/runtime/ScalaRunTime$.$anonfun$stringOf$3:(Lscala/runtime/ScalaRunTime$;ILjava/lang/Object;)Ljava/lang/String;
  #766 = InvokeDynamic      #1:#709       // #1:apply:(Lscala/runtime/ScalaRunTime$;I)Lscala/Function1;
  #767 = Utf8               className
  #768 = NameAndType        #767:#360     // className:()Ljava/lang/String;
  #769 = InterfaceMethodref #592.#768     // scala/collection/Iterable.className:()Ljava/lang/String;
  #770 = InterfaceMethodref #592.#322     // scala/collection/Iterable.iterator:()Lscala/collection/Iterator;
  #771 = NameAndType        #724:#620     // $anonfun$stringOf$4:(Lscala/runtime/ScalaRunTime$;ILjava/lang/Object;)Ljava/lang/String;
  #772 = Methodref          #2.#771       // scala/runtime/ScalaRunTime$.$anonfun$stringOf$4:(Lscala/runtime/ScalaRunTime$;ILjava/lang/Object;)Ljava/lang/String;
  #773 = MethodHandle       6:#772        // REF_invokeStatic scala/runtime/ScalaRunTime$.$anonfun$stringOf$4:(Lscala/runtime/ScalaRunTime$;ILjava/lang/Object;)Ljava/lang/String;
  #774 = InvokeDynamic      #2:#709       // #2:apply:(Lscala/runtime/ScalaRunTime$;I)Lscala/Function1;
  #775 = Utf8               scala/Product1
  #776 = Class              #775          // scala/Product1
  #777 = NameAndType        #545:#114     // isTuple$1:(Ljava/lang/Object;)Z
  #778 = Methodref          #2.#777       // scala/runtime/ScalaRunTime$.isTuple$1:(Ljava/lang/Object;)Z
  #779 = Integer            3
  #780 = InterfaceMethodref #776.#604     // scala/Product1._1:()Ljava/lang/Object;
  #781 = Utf8               ,)
  #782 = String             #781          // ,)
  #783 = NameAndType        #725:#620     // $anonfun$stringOf$5:(Lscala/runtime/ScalaRunTime$;ILjava/lang/Object;)Ljava/lang/String;
  #784 = Methodref          #2.#783       // scala/runtime/ScalaRunTime$.$anonfun$stringOf$5:(Lscala/runtime/ScalaRunTime$;ILjava/lang/Object;)Ljava/lang/String;
  #785 = MethodHandle       6:#784        // REF_invokeStatic scala/runtime/ScalaRunTime$.$anonfun$stringOf$5:(Lscala/runtime/ScalaRunTime$;ILjava/lang/Object;)Ljava/lang/String;
  #786 = InvokeDynamic      #3:#709       // #3:apply:(Lscala/runtime/ScalaRunTime$;I)Lscala/Function1;
  #787 = Methodref          #4.#55        // java/lang/Object."<init>":()V
  #788 = Utf8               $anonfun$stringOf$1$adapted
  #789 = NameAndType        #614:#615     // $anonfun$stringOf$1:(I)Ljava/lang/String;
  #790 = Methodref          #2.#789       // scala/runtime/ScalaRunTime$.$anonfun$stringOf$1:(I)Ljava/lang/String;
  #791 = Utf8               $deserializeLambda$
  #792 = Utf8               (Ljava/lang/invoke/SerializedLambda;)Ljava/lang/Object;
  #793 = Utf8               scala/runtime/LambdaDeserialize
  #794 = Class              #793          // scala/runtime/LambdaDeserialize
  #795 = Utf8               bootstrap
  #796 = Utf8               (Ljava/lang/invoke/MethodHandles$Lookup;Ljava/lang/String;Ljava/lang/invoke/MethodType;[Ljava/lang/invoke/MethodHandle;)Ljava/lang/invoke/CallSite;
  #797 = NameAndType        #795:#796     // bootstrap:(Ljava/lang/invoke/MethodHandles$Lookup;Ljava/lang/String;Ljava/lang/invoke/MethodType;[Ljava/lang/invoke/MethodHandle;)Ljava/lang/invoke/CallSite;
  #798 = Methodref          #794.#797     // scala/runtime/LambdaDeserialize.bootstrap:(Ljava/lang/invoke/MethodHandles$Lookup;Ljava/lang/String;Ljava/lang/invoke/MethodType;[Ljava/lang/invoke/MethodHandle;)Ljava/lang/invoke/CallSite;
  #799 = MethodHandle       6:#798        // REF_invokeStatic scala/runtime/LambdaDeserialize.bootstrap:(Ljava/lang/invoke/MethodHandles$Lookup;Ljava/lang/String;Ljava/lang/invoke/MethodType;[Ljava/lang/invoke/MethodHandle;)Ljava/lang/invoke/CallSite;
  #800 = Utf8               lambdaDeserialize
  #801 = NameAndType        #800:#792     // lambdaDeserialize:(Ljava/lang/invoke/SerializedLambda;)Ljava/lang/Object;
  #802 = InvokeDynamic      #4:#801       // #4:lambdaDeserialize:(Ljava/lang/invoke/SerializedLambda;)Ljava/lang/Object;
  #803 = Utf8               Code
  #804 = Utf8               LineNumberTable
  #805 = Utf8               StackMapTable
  #806 = Utf8               LocalVariableTable
  #807 = Utf8               MethodParameters
  #808 = Utf8               Signature
  #809 = Utf8               InnerClasses
  #810 = Utf8               SourceFile
  #811 = Utf8               BootstrapMethods
  #812 = Utf8               ScalaInlineInfo
  #813 = Utf8               Scala
{
  public static final scala.runtime.ScalaRunTime$ MODULE$;
    descriptor: Lscala/runtime/ScalaRunTime$;
    flags: (0x0019) ACC_PUBLIC, ACC_STATIC, ACC_FINAL

  public static {};
    descriptor: ()V
    flags: (0x0009) ACC_PUBLIC, ACC_STATIC
    Code:
      stack=2, locals=0, args_size=0
         0: new           #2                  // class scala/runtime/ScalaRunTime$
         3: dup
         4: invokespecial #56                 // Method "<init>":()V
         7: putstatic     #58                 // Field MODULE$:Lscala/runtime/ScalaRunTime$;
        10: return
      LineNumberTable:
        line 29: 0

  public boolean isArray(java.lang.Object, int);
    descriptor: (Ljava/lang/Object;I)Z
    flags: (0x0001) ACC_PUBLIC
    Code:
      stack=3, locals=3, args_size=3
         0: aload_1
         1: ifnull        18
         4: aload_0
         5: aload_1
         6: invokevirtual #66                 // Method java/lang/Object.getClass:()Ljava/lang/Class;
         9: iload_2
        10: invokespecial #70                 // Method isArrayClass:(Ljava/lang/Class;I)Z
        13: ifeq          18
        16: iconst_1
        17: ireturn
        18: iconst_0
        19: ireturn
      StackMapTable: number_of_entries = 1
        frame_type = 18 /* same */
      LineNumberTable:
        line 31: 0
      LocalVariableTable:
        Start  Length  Slot  Name   Signature
            0      20     0  this   Lscala/runtime/ScalaRunTime$;
            0      20     1     x   Ljava/lang/Object;
            0      20     2 atLevel   I
    MethodParameters:
      Name                           Flags
      x                              final
      atLevel                        final

  public int isArray$default$2();
    descriptor: ()I
    flags: (0x0001) ACC_PUBLIC
    Code:
      stack=1, locals=1, args_size=1
         0: iconst_1
         1: ireturn
      LineNumberTable:
        line 30: 0
      LocalVariableTable:
        Start  Length  Slot  Name   Signature
            0       2     0  this   Lscala/runtime/ScalaRunTime$;

  private boolean isArrayClass(java.lang.Class<?>, int);
    descriptor: (Ljava/lang/Class;I)Z
    flags: (0x0002) ACC_PRIVATE
    Code:
      stack=3, locals=3, args_size=3
         0: aload_1
         1: invokevirtual #82                 // Method java/lang/Class.isArray:()Z
         4: ifeq          26
         7: iload_2
         8: iconst_1
         9: if_icmpeq     24
        12: aload_1
        13: invokevirtual #85                 // Method java/lang/Class.getComponentType:()Ljava/lang/Class;
        16: iload_2
        17: iconst_1
        18: isub
        19: istore_2
        20: astore_1
        21: goto          0
        24: iconst_1
        25: ireturn
        26: iconst_0
        27: ireturn
      StackMapTable: number_of_entries = 3
        frame_type = 0 /* same */
        frame_type = 23 /* same */
        frame_type = 1 /* same */
      LineNumberTable:
        line 34: 0
      LocalVariableTable:
        Start  Length  Slot  Name   Signature
            0      28     0  this   Lscala/runtime/ScalaRunTime$;
            0      28     1 clazz   Ljava/lang/Class;
            0      28     2 atLevel   I
    Signature: #76                          // (Ljava/lang/Class<*>;I)Z
    MethodParameters:
      Name                           Flags
      clazz                          final
      atLevel                        final

  public <Repr extends java.lang.Object> Repr drop(Repr, int, scala.collection.generic.IsIterable<Repr>);
    descriptor: (Ljava/lang/Object;ILscala/collection/generic/IsIterable;)Ljava/lang/Object;
    flags: (0x0001) ACC_PUBLIC
    Code:
      stack=2, locals=4, args_size=4
         0: aload_3
         1: aload_1
         2: invokeinterface #98,  2           // InterfaceMethod scala/collection/generic/IsIterable.apply:(Ljava/lang/Object;)Lscala/collection/IterableOps;
         7: iload_2
         8: invokeinterface #103,  2          // InterfaceMethod scala/collection/IterableOps.drop:(I)Ljava/lang/Object;
        13: areturn
      LineNumberTable:
        line 38: 0
      LocalVariableTable:
        Start  Length  Slot  Name   Signature
            0      14     0  this   Lscala/runtime/ScalaRunTime$;
            0      14     1  coll   Ljava/lang/Object;
            0      14     2   num   I
            0      14     3 iterable   Lscala/collection/generic/IsIterable;
    Signature: #89                          // <Repr:Ljava/lang/Object;>(TRepr;ILscala/collection/generic/IsIterable<TRepr;>;)TRepr;
    MethodParameters:
      Name                           Flags
      coll                           final
      num                            final
      iterable                       final

  public java.lang.Class<?> arrayClass(java.lang.Class<?>);
    descriptor: (Ljava/lang/Class;)Ljava/lang/Class;
    flags: (0x0001) ACC_PUBLIC
    Code:
      stack=2, locals=3, args_size=2
         0: aload_1
         1: getstatic     #112                // Field java/lang/Void.TYPE:Ljava/lang/Class;
         4: astore_2
         5: dup
         6: ifnonnull     17
         9: pop
        10: aload_2
        11: ifnull        24
        14: goto          27
        17: aload_2
        18: invokevirtual #116                // Method java/lang/Object.equals:(Ljava/lang/Object;)Z
        21: ifeq          27
        24: ldc           #118                // class "[Lscala/runtime/BoxedUnit;"
        26: areturn
        27: aload_1
        28: iconst_0
        29: invokestatic  #124                // Method java/lang/reflect/Array.newInstance:(Ljava/lang/Class;I)Ljava/lang/Object;
        32: invokevirtual #66                 // Method java/lang/Object.getClass:()Ljava/lang/Class;
        35: areturn
      StackMapTable: number_of_entries = 3
        frame_type = 255 /* full_frame */
          offset_delta = 17
          locals = [ class scala/runtime/ScalaRunTime$, class java/lang/Class, class java/lang/Class ]
          stack = [ class java/lang/Class ]
        frame_type = 6 /* same */
        frame_type = 2 /* same */
      LineNumberTable:
        line 44: 0
        line 45: 27
      LocalVariableTable:
        Start  Length  Slot  Name   Signature
            0      36     0  this   Lscala/runtime/ScalaRunTime$;
            0      36     1 clazz   Ljava/lang/Class;
    Signature: #107                         // (Ljava/lang/Class<*>;)Ljava/lang/Class<*>;
    MethodParameters:
      Name                           Flags
      clazz                          final

  public <T extends java.lang.Object> java.lang.Class<T> anyValClass(T, scala.reflect.ClassTag<T>);
    descriptor: (Ljava/lang/Object;Lscala/reflect/ClassTag;)Ljava/lang/Class;
    flags: (0x0001) ACC_PUBLIC
    Code:
      stack=1, locals=3, args_size=3
         0: getstatic     #134                // Field scala/reflect/package$.MODULE$:Lscala/reflect/package$;
         3: pop
         4: aload_2
         5: invokeinterface #139,  1          // InterfaceMethod scala/reflect/ClassTag.runtimeClass:()Ljava/lang/Class;
        10: areturn
      LineNumberTable:
        line 53: 0
      LocalVariableTable:
        Start  Length  Slot  Name   Signature
            0      11     0  this   Lscala/runtime/ScalaRunTime$;
            0      11     1 value   Ljava/lang/Object;
            0      11     2 evidence$1   Lscala/reflect/ClassTag;
    Signature: #127                         // <T:Ljava/lang/Object;>(TT;Lscala/reflect/ClassTag<TT;>;)Ljava/lang/Class<TT;>;
    MethodParameters:
      Name                           Flags
      value                          final
      evidence$1                     final

  public java.lang.Object array_apply(java.lang.Object, int);
    descriptor: (Ljava/lang/Object;I)Ljava/lang/Object;
    flags: (0x0001) ACC_PUBLIC
    Code:
      stack=3, locals=12, args_size=3
         0: aload_1
         1: instanceof    #146                // class "[Ljava/lang/Object;"
         4: ifeq          17
         7: aload_1
         8: checkcast     #146                // class "[Ljava/lang/Object;"
        11: iload_2
        12: aaload
        13: astore_3
        14: goto          254
        17: aload_1
        18: instanceof    #148                // class "[I"
        21: ifeq          44
        24: aload_1
        25: checkcast     #148                // class "[I"
        28: iload_2
        29: iaload
        30: invokestatic  #154                // Method java/lang/Integer.valueOf:(I)Ljava/lang/Integer;
        33: astore        4
        35: aload         4
        37: aconst_null
        38: astore        4
        40: astore_3
        41: goto          254
        44: aload_1
        45: instanceof    #156                // class "[D"
        48: ifeq          71
        51: aload_1
        52: checkcast     #156                // class "[D"
        55: iload_2
        56: daload
        57: invokestatic  #161                // Method java/lang/Double.valueOf:(D)Ljava/lang/Double;
        60: astore        5
        62: aload         5
        64: aconst_null
        65: astore        5
        67: astore_3
        68: goto          254
        71: aload_1
        72: instanceof    #163                // class "[J"
        75: ifeq          98
        78: aload_1
        79: checkcast     #163                // class "[J"
        82: iload_2
        83: laload
        84: invokestatic  #168                // Method java/lang/Long.valueOf:(J)Ljava/lang/Long;
        87: astore        6
        89: aload         6
        91: aconst_null
        92: astore        6
        94: astore_3
        95: goto          254
        98: aload_1
        99: instanceof    #170                // class "[F"
       102: ifeq          125
       105: aload_1
       106: checkcast     #170                // class "[F"
       109: iload_2
       110: faload
       111: invokestatic  #175                // Method java/lang/Float.valueOf:(F)Ljava/lang/Float;
       114: astore        7
       116: aload         7
       118: aconst_null
       119: astore        7
       121: astore_3
       122: goto          254
       125: aload_1
       126: instanceof    #177                // class "[C"
       129: ifeq          152
       132: aload_1
       133: checkcast     #177                // class "[C"
       136: iload_2
       137: caload
       138: invokestatic  #182                // Method java/lang/Character.valueOf:(C)Ljava/lang/Character;
       141: astore        8
       143: aload         8
       145: aconst_null
       146: astore        8
       148: astore_3
       149: goto          254
       152: aload_1
       153: instanceof    #184                // class "[B"
       156: ifeq          179
       159: aload_1
       160: checkcast     #184                // class "[B"
       163: iload_2
       164: baload
       165: invokestatic  #189                // Method java/lang/Byte.valueOf:(B)Ljava/lang/Byte;
       168: astore        9
       170: aload         9
       172: aconst_null
       173: astore        9
       175: astore_3
       176: goto          254
       179: aload_1
       180: instanceof    #191                // class "[S"
       183: ifeq          206
       186: aload_1
       187: checkcast     #191                // class "[S"
       190: iload_2
       191: saload
       192: invokestatic  #196                // Method java/lang/Short.valueOf:(S)Ljava/lang/Short;
       195: astore        10
       197: aload         10
       199: aconst_null
       200: astore        10
       202: astore_3
       203: goto          254
       206: aload_1
       207: instanceof    #198                // class "[Z"
       210: ifeq          233
       213: aload_1
       214: checkcast     #198                // class "[Z"
       217: iload_2
       218: baload
       219: invokestatic  #203                // Method java/lang/Boolean.valueOf:(Z)Ljava/lang/Boolean;
       222: astore        11
       224: aload         11
       226: aconst_null
       227: astore        11
       229: astore_3
       230: goto          254
       233: aload_1
       234: ifnonnull     245
       237: new           #205                // class java/lang/NullPointerException
       240: dup
       241: invokespecial #206                // Method java/lang/NullPointerException."<init>":()V
       244: athrow
       245: new           #208                // class scala/MatchError
       248: dup
       249: aload_1
       250: invokespecial #211                // Method scala/MatchError."<init>":(Ljava/lang/Object;)V
       253: athrow
       254: aload_3
       255: areturn
      StackMapTable: number_of_entries = 11
        frame_type = 17 /* same */
        frame_type = 26 /* same */
        frame_type = 26 /* same */
        frame_type = 26 /* same */
        frame_type = 26 /* same */
        frame_type = 26 /* same */
        frame_type = 26 /* same */
        frame_type = 26 /* same */
        frame_type = 26 /* same */
        frame_type = 11 /* same */
        frame_type = 252 /* append */
          offset_delta = 8
          locals = [ class java/lang/Object ]
      LineNumberTable:
        line 58: 0
        line 59: 17
        line 60: 44
        line 61: 71
        line 62: 98
        line 63: 125
        line 64: 152
        line 65: 179
        line 66: 206
        line 67: 233
        line 57: 245
      LocalVariableTable:
        Start  Length  Slot  Name   Signature
            0     256     0  this   Lscala/runtime/ScalaRunTime$;
            0     256     1    xs   Ljava/lang/Object;
            0     256     2   idx   I
    MethodParameters:
      Name                           Flags
      xs                             final
      idx                            final

  public void array_update(java.lang.Object, int, java.lang.Object);
    descriptor: (Ljava/lang/Object;ILjava/lang/Object;)V
    flags: (0x0001) ACC_PUBLIC
    Code:
      stack=4, locals=4, args_size=4
         0: aload_1
         1: instanceof    #146                // class "[Ljava/lang/Object;"
         4: ifeq          15
         7: aload_1
         8: checkcast     #146                // class "[Ljava/lang/Object;"
        11: iload_2
        12: aload_3
        13: aastore
        14: return
        15: aload_1
        16: instanceof    #148                // class "[I"
        19: ifeq          33
        22: aload_1
        23: checkcast     #148                // class "[I"
        26: iload_2
        27: aload_3
        28: invokestatic  #219                // Method scala/runtime/BoxesRunTime.unboxToInt:(Ljava/lang/Object;)I
        31: iastore
        32: return
        33: aload_1
        34: instanceof    #156                // class "[D"
        37: ifeq          51
        40: aload_1
        41: checkcast     #156                // class "[D"
        44: iload_2
        45: aload_3
        46: invokestatic  #223                // Method scala/runtime/BoxesRunTime.unboxToDouble:(Ljava/lang/Object;)D
        49: dastore
        50: return
        51: aload_1
        52: instanceof    #163                // class "[J"
        55: ifeq          69
        58: aload_1
        59: checkcast     #163                // class "[J"
        62: iload_2
        63: aload_3
        64: invokestatic  #227                // Method scala/runtime/BoxesRunTime.unboxToLong:(Ljava/lang/Object;)J
        67: lastore
        68: return
        69: aload_1
        70: instanceof    #170                // class "[F"
        73: ifeq          87
        76: aload_1
        77: checkcast     #170                // class "[F"
        80: iload_2
        81: aload_3
        82: invokestatic  #231                // Method scala/runtime/BoxesRunTime.unboxToFloat:(Ljava/lang/Object;)F
        85: fastore
        86: return
        87: aload_1
        88: instanceof    #177                // class "[C"
        91: ifeq          105
        94: aload_1
        95: checkcast     #177                // class "[C"
        98: iload_2
        99: aload_3
       100: invokestatic  #235                // Method scala/runtime/BoxesRunTime.unboxToChar:(Ljava/lang/Object;)C
       103: castore
       104: return
       105: aload_1
       106: instanceof    #184                // class "[B"
       109: ifeq          123
       112: aload_1
       113: checkcast     #184                // class "[B"
       116: iload_2
       117: aload_3
       118: invokestatic  #239                // Method scala/runtime/BoxesRunTime.unboxToByte:(Ljava/lang/Object;)B
       121: bastore
       122: return
       123: aload_1
       124: instanceof    #191                // class "[S"
       127: ifeq          141
       130: aload_1
       131: checkcast     #191                // class "[S"
       134: iload_2
       135: aload_3
       136: invokestatic  #243                // Method scala/runtime/BoxesRunTime.unboxToShort:(Ljava/lang/Object;)S
       139: sastore
       140: return
       141: aload_1
       142: instanceof    #198                // class "[Z"
       145: ifeq          159
       148: aload_1
       149: checkcast     #198                // class "[Z"
       152: iload_2
       153: aload_3
       154: invokestatic  #246                // Method scala/runtime/BoxesRunTime.unboxToBoolean:(Ljava/lang/Object;)Z
       157: bastore
       158: return
       159: aload_1
       160: ifnonnull     171
       163: new           #205                // class java/lang/NullPointerException
       166: dup
       167: invokespecial #206                // Method java/lang/NullPointerException."<init>":()V
       170: athrow
       171: new           #208                // class scala/MatchError
       174: dup
       175: aload_1
       176: invokespecial #211                // Method scala/MatchError."<init>":(Ljava/lang/Object;)V
       179: athrow
      StackMapTable: number_of_entries = 10
        frame_type = 15 /* same */
        frame_type = 17 /* same */
        frame_type = 17 /* same */
        frame_type = 17 /* same */
        frame_type = 17 /* same */
        frame_type = 17 /* same */
        frame_type = 17 /* same */
        frame_type = 17 /* same */
        frame_type = 17 /* same */
        frame_type = 11 /* same */
      LineNumberTable:
        line 74: 0
        line 75: 15
        line 76: 33
        line 77: 51
        line 78: 69
        line 79: 87
        line 80: 105
        line 81: 123
        line 82: 141
        line 83: 159
        line 73: 171
      LocalVariableTable:
        Start  Length  Slot  Name   Signature
            0     180     0  this   Lscala/runtime/ScalaRunTime$;
            0     180     1    xs   Ljava/lang/Object;
            0     180     2   idx   I
            0     180     3 value   Ljava/lang/Object;
    MethodParameters:
      Name                           Flags
      xs                             final
      idx                            final
      value                          final

  public int array_length(java.lang.Object);
    descriptor: (Ljava/lang/Object;)I
    flags: (0x0001) ACC_PUBLIC
    Code:
      stack=1, locals=2, args_size=2
         0: aload_1
         1: invokestatic  #250                // Method java/lang/reflect/Array.getLength:(Ljava/lang/Object;)I
         4: ireturn
      LineNumberTable:
        line 88: 0
      LocalVariableTable:
        Start  Length  Slot  Name   Signature
            0       5     0  this   Lscala/runtime/ScalaRunTime$;
            0       5     1    xs   Ljava/lang/Object;
    MethodParameters:
      Name                           Flags
      xs                             final

  public java.lang.Object array_clone(java.lang.Object);
    descriptor: (Ljava/lang/Object;)Ljava/lang/Object;
    flags: (0x0001) ACC_PUBLIC
    Code:
      stack=3, locals=3, args_size=2
         0: aload_1
         1: instanceof    #146                // class "[Ljava/lang/Object;"
         4: ifeq          18
         7: aload_1
         8: checkcast     #146                // class "[Ljava/lang/Object;"
        11: invokevirtual #256                // Method "[Ljava/lang/Object;".clone:()Ljava/lang/Object;
        14: astore_2
        15: goto          183
        18: aload_1
        19: instanceof    #148                // class "[I"
        22: ifeq          36
        25: aload_1
        26: checkcast     #148                // class "[I"
        29: invokevirtual #257                // Method "[I".clone:()Ljava/lang/Object;
        32: astore_2
        33: goto          183
        36: aload_1
        37: instanceof    #156                // class "[D"
        40: ifeq          54
        43: aload_1
        44: checkcast     #156                // class "[D"
        47: invokevirtual #258                // Method "[D".clone:()Ljava/lang/Object;
        50: astore_2
        51: goto          183
        54: aload_1
        55: instanceof    #163                // class "[J"
        58: ifeq          72
        61: aload_1
        62: checkcast     #163                // class "[J"
        65: invokevirtual #259                // Method "[J".clone:()Ljava/lang/Object;
        68: astore_2
        69: goto          183
        72: aload_1
        73: instanceof    #170                // class "[F"
        76: ifeq          90
        79: aload_1
        80: checkcast     #170                // class "[F"
        83: invokevirtual #260                // Method "[F".clone:()Ljava/lang/Object;
        86: astore_2
        87: goto          183
        90: aload_1
        91: instanceof    #177                // class "[C"
        94: ifeq          108
        97: aload_1
        98: checkcast     #177                // class "[C"
       101: invokevirtual #261                // Method "[C".clone:()Ljava/lang/Object;
       104: astore_2
       105: goto          183
       108: aload_1
       109: instanceof    #184                // class "[B"
       112: ifeq          126
       115: aload_1
       116: checkcast     #184                // class "[B"
       119: invokevirtual #262                // Method "[B".clone:()Ljava/lang/Object;
       122: astore_2
       123: goto          183
       126: aload_1
       127: instanceof    #191                // class "[S"
       130: ifeq          144
       133: aload_1
       134: checkcast     #191                // class "[S"
       137: invokevirtual #263                // Method "[S".clone:()Ljava/lang/Object;
       140: astore_2
       141: goto          183
       144: aload_1
       145: instanceof    #198                // class "[Z"
       148: ifeq          162
       151: aload_1
       152: checkcast     #198                // class "[Z"
       155: invokevirtual #264                // Method "[Z".clone:()Ljava/lang/Object;
       158: astore_2
       159: goto          183
       162: aload_1
       163: ifnonnull     174
       166: new           #205                // class java/lang/NullPointerException
       169: dup
       170: invokespecial #206                // Method java/lang/NullPointerException."<init>":()V
       173: athrow
       174: new           #208                // class scala/MatchError
       177: dup
       178: aload_1
       179: invokespecial #211                // Method scala/MatchError."<init>":(Ljava/lang/Object;)V
       182: athrow
       183: aload_2
       184: areturn
      StackMapTable: number_of_entries = 11
        frame_type = 18 /* same */
        frame_type = 17 /* same */
        frame_type = 17 /* same */
        frame_type = 17 /* same */
        frame_type = 17 /* same */
        frame_type = 17 /* same */
        frame_type = 17 /* same */
        frame_type = 17 /* same */
        frame_type = 17 /* same */
        frame_type = 11 /* same */
        frame_type = 252 /* append */
          offset_delta = 8
          locals = [ class java/lang/Object ]
      LineNumberTable:
        line 93: 0
        line 94: 18
        line 95: 36
        line 96: 54
        line 97: 72
        line 98: 90
        line 99: 108
        line 100: 126
        line 101: 144
        line 102: 162
        line 92: 174
      LocalVariableTable:
        Start  Length  Slot  Name   Signature
            0     185     0  this   Lscala/runtime/ScalaRunTime$;
            0     185     1    xs   Ljava/lang/Object;
    MethodParameters:
      Name                           Flags
      xs                             final

  public java.lang.Object[] toObjectArray(java.lang.Object);
    descriptor: (Ljava/lang/Object;)[Ljava/lang/Object;
    flags: (0x0001) ACC_PUBLIC
    Code:
      stack=3, locals=3, args_size=2
         0: aload_1
         1: instanceof    #146                // class "[Ljava/lang/Object;"
         4: ifeq          15
         7: aload_1
         8: checkcast     #146                // class "[Ljava/lang/Object;"
        11: astore_2
        12: goto          180
        15: aload_1
        16: instanceof    #148                // class "[I"
        19: ifeq          33
        22: aload_1
        23: checkcast     #148                // class "[I"
        26: invokestatic  #271                // Method copy$mIc$sp$1:([I)[Ljava/lang/Object;
        29: astore_2
        30: goto          180
        33: aload_1
        34: instanceof    #156                // class "[D"
        37: ifeq          51
        40: aload_1
        41: checkcast     #156                // class "[D"
        44: invokestatic  #275                // Method copy$mDc$sp$1:([D)[Ljava/lang/Object;
        47: astore_2
        48: goto          180
        51: aload_1
        52: instanceof    #163                // class "[J"
        55: ifeq          69
        58: aload_1
        59: checkcast     #163                // class "[J"
        62: invokestatic  #279                // Method copy$mJc$sp$1:([J)[Ljava/lang/Object;
        65: astore_2
        66: goto          180
        69: aload_1
        70: instanceof    #170                // class "[F"
        73: ifeq          87
        76: aload_1
        77: checkcast     #170                // class "[F"
        80: invokestatic  #283                // Method copy$mFc$sp$1:([F)[Ljava/lang/Object;
        83: astore_2
        84: goto          180
        87: aload_1
        88: instanceof    #177                // class "[C"
        91: ifeq          105
        94: aload_1
        95: checkcast     #177                // class "[C"
        98: invokestatic  #287                // Method copy$mCc$sp$1:([C)[Ljava/lang/Object;
       101: astore_2
       102: goto          180
       105: aload_1
       106: instanceof    #184                // class "[B"
       109: ifeq          123
       112: aload_1
       113: checkcast     #184                // class "[B"
       116: invokestatic  #291                // Method copy$mBc$sp$1:([B)[Ljava/lang/Object;
       119: astore_2
       120: goto          180
       123: aload_1
       124: instanceof    #191                // class "[S"
       127: ifeq          141
       130: aload_1
       131: checkcast     #191                // class "[S"
       134: invokestatic  #295                // Method copy$mSc$sp$1:([S)[Ljava/lang/Object;
       137: astore_2
       138: goto          180
       141: aload_1
       142: instanceof    #198                // class "[Z"
       145: ifeq          159
       148: aload_1
       149: checkcast     #198                // class "[Z"
       152: invokestatic  #299                // Method copy$mZc$sp$1:([Z)[Ljava/lang/Object;
       155: astore_2
       156: goto          180
       159: aload_1
       160: ifnonnull     171
       163: new           #205                // class java/lang/NullPointerException
       166: dup
       167: invokespecial #206                // Method java/lang/NullPointerException."<init>":()V
       170: athrow
       171: new           #208                // class scala/MatchError
       174: dup
       175: aload_1
       176: invokespecial #211                // Method scala/MatchError."<init>":(Ljava/lang/Object;)V
       179: athrow
       180: aload_2
       181: areturn
      StackMapTable: number_of_entries = 11
        frame_type = 15 /* same */
        frame_type = 17 /* same */
        frame_type = 17 /* same */
        frame_type = 17 /* same */
        frame_type = 17 /* same */
        frame_type = 17 /* same */
        frame_type = 17 /* same */
        frame_type = 17 /* same */
        frame_type = 17 /* same */
        frame_type = 11 /* same */
        frame_type = 252 /* append */
          offset_delta = 8
          locals = [ class "[Ljava/lang/Object;" ]
      LineNumberTable:
        line 124: 0
        line 125: 15
        line 126: 33
        line 127: 51
        line 128: 69
        line 129: 87
        line 130: 105
        line 131: 123
        line 132: 141
        line 133: 159
        line 123: 171
      LocalVariableTable:
        Start  Length  Slot  Name   Signature
            0     182     0  this   Lscala/runtime/ScalaRunTime$;
            0     182     1   src   Ljava/lang/Object;
    MethodParameters:
      Name                           Flags
      src                            final

  public <T extends java.lang.Object> java.lang.Object[] toArray(scala.collection.Seq<T>);
    descriptor: (Lscala/collection/Seq;)[Ljava/lang/Object;
    flags: (0x0001) ACC_PUBLIC
    Code:
      stack=3, locals=5, args_size=2
         0: aload_1
         1: invokeinterface #307,  1          // InterfaceMethod scala/collection/Seq.isEmpty:()Z
         6: ifeq          16
         9: getstatic     #312                // Field scala/Array$.MODULE$:Lscala/Array$;
        12: invokevirtual #316                // Method scala/Array$.emptyObjectArray:()[Ljava/lang/Object;
        15: areturn
        16: aload_1
        17: invokeinterface #319,  1          // InterfaceMethod scala/collection/Seq.length:()I
        22: anewarray     #4                  // class java/lang/Object
        25: astore_2
        26: aload_1
        27: invokeinterface #323,  1          // InterfaceMethod scala/collection/Seq.iterator:()Lscala/collection/Iterator;
        32: astore_3
        33: iconst_0
        34: istore        4
        36: aload_3
        37: invokeinterface #328,  1          // InterfaceMethod scala/collection/Iterator.hasNext:()Z
        42: ifeq          61
        45: aload_2
        46: iload         4
        48: aload_3
        49: invokeinterface #331,  1          // InterfaceMethod scala/collection/Iterator.next:()Ljava/lang/Object;
        54: aastore
        55: iinc          4, 1
        58: goto          36
        61: aload_2
        62: areturn
      StackMapTable: number_of_entries = 3
        frame_type = 16 /* same */
        frame_type = 254 /* append */
          offset_delta = 19
          locals = [ class "[Ljava/lang/Object;", class scala/collection/Iterator, int ]
        frame_type = 24 /* same */
      LineNumberTable:
        line 138: 0
        line 140: 16
        line 141: 26
        line 142: 33
        line 143: 36
        line 144: 45
        line 145: 55
        line 143: 58
        line 147: 61
      LocalVariableTable:
        Start  Length  Slot  Name   Signature
           26      36     2   arr   [Ljava/lang/Object;
           33      29     3    it   Lscala/collection/Iterator;
           36      26     4     i   I
            0      63     0  this   Lscala/runtime/ScalaRunTime$;
            0      63     1    xs   Lscala/collection/Seq;
    Signature: #302                         // <T:Ljava/lang/Object;>(Lscala/collection/Seq<TT;>;)[Ljava/lang/Object;
    MethodParameters:
      Name                           Flags
      xs                             final

  public java.lang.reflect.Method ensureAccessible(java.lang.reflect.Method);
    descriptor: (Ljava/lang/reflect/Method;)Ljava/lang/reflect/Method;
    flags: (0x0001) ACC_PUBLIC
    Code:
      stack=2, locals=2, args_size=2
         0: getstatic     #134                // Field scala/reflect/package$.MODULE$:Lscala/reflect/package$;
         3: aload_1
         4: invokevirtual #342                // Method scala/reflect/package$.ensureAccessible:(Ljava/lang/reflect/AccessibleObject;)Ljava/lang/reflect/AccessibleObject;
         7: checkcast     #344                // class java/lang/reflect/Method
        10: areturn
      LineNumberTable:
        line 153: 0
      LocalVariableTable:
        Start  Length  Slot  Name   Signature
            0      11     0  this   Lscala/runtime/ScalaRunTime$;
            0      11     1     m   Ljava/lang/reflect/Method;
    MethodParameters:
      Name                           Flags
      m                              final

  public java.lang.String _toString(scala.Product);
    descriptor: (Lscala/Product;)Ljava/lang/String;
    flags: (0x0001) ACC_PUBLIC
    Code:
      stack=4, locals=2, args_size=2
         0: aload_1
         1: invokeinterface #352,  1          // InterfaceMethod scala/Product.productIterator:()Lscala/collection/Iterator;
         6: new           #354                // class java/lang/StringBuilder
         9: dup
        10: ldc_w         #355                // int 1
        13: invokespecial #358                // Method java/lang/StringBuilder."<init>":(I)V
        16: aload_1
        17: invokeinterface #362,  1          // InterfaceMethod scala/Product.productPrefix:()Ljava/lang/String;
        22: invokevirtual #366                // Method java/lang/StringBuilder.append:(Ljava/lang/String;)Ljava/lang/StringBuilder;
        25: ldc_w         #368                // String (
        28: invokevirtual #366                // Method java/lang/StringBuilder.append:(Ljava/lang/String;)Ljava/lang/StringBuilder;
        31: invokevirtual #371                // Method java/lang/StringBuilder.toString:()Ljava/lang/String;
        34: ldc_w         #373                // String ,
        37: ldc_w         #375                // String )
        40: invokeinterface #379,  4          // InterfaceMethod scala/collection/Iterator.mkString:(Ljava/lang/String;Ljava/lang/String;Ljava/lang/String;)Ljava/lang/String;
        45: areturn
      LineNumberTable:
        line 156: 0
      LocalVariableTable:
        Start  Length  Slot  Name   Signature
            0      46     0  this   Lscala/runtime/ScalaRunTime$;
            0      46     1     x   Lscala/Product;
    MethodParameters:
      Name                           Flags
      x                              final

  public int _hashCode(scala.Product);
    descriptor: (Lscala/Product;)I
    flags: (0x0001) ACC_PUBLIC
    Code:
      stack=2, locals=2, args_size=2
         0: getstatic     #387                // Field scala/util/hashing/MurmurHash3$.MODULE$:Lscala/util/hashing/MurmurHash3$;
         3: aload_1
         4: invokevirtual #390                // Method scala/util/hashing/MurmurHash3$.productHash:(Lscala/Product;)I
         7: ireturn
      LineNumberTable:
        line 158: 0
      LocalVariableTable:
        Start  Length  Slot  Name   Signature
            0       8     0  this   Lscala/runtime/ScalaRunTime$;
            0       8     1     x   Lscala/Product;
    MethodParameters:
      Name                           Flags
      x                              final

  public <T extends java.lang.Object> scala.collection.Iterator<T> typedProductIterator(scala.Product);
    descriptor: (Lscala/Product;)Lscala/collection/Iterator;
    flags: (0x0001) ACC_PUBLIC
    Code:
      stack=3, locals=2, args_size=2
         0: new           #49                 // class scala/runtime/ScalaRunTime$$anon$1
         3: dup
         4: aload_1
         5: invokespecial #396                // Method scala/runtime/ScalaRunTime$$anon$1."<init>":(Lscala/Product;)V
         8: areturn
      LineNumberTable:
        line 162: 0
      LocalVariableTable:
        Start  Length  Slot  Name   Signature
            0       9     0  this   Lscala/runtime/ScalaRunTime$;
            0       9     1     x   Lscala/Product;
    Signature: #393                         // <T:Ljava/lang/Object;>(Lscala/Product;)Lscala/collection/Iterator<TT;>;
    MethodParameters:
      Name                           Flags
      x                              final

  public java.lang.String stringOf(java.lang.Object);
    descriptor: (Ljava/lang/Object;)Ljava/lang/String;
    flags: (0x0001) ACC_PUBLIC
    Code:
      stack=3, locals=2, args_size=2
         0: aload_0
         1: aload_1
         2: ldc_w         #400                // int 2147483647
         5: invokevirtual #403                // Method stringOf:(Ljava/lang/Object;I)Ljava/lang/String;
         8: areturn
      LineNumberTable:
        line 186: 0
      LocalVariableTable:
        Start  Length  Slot  Name   Signature
            0       9     0  this   Lscala/runtime/ScalaRunTime$;
            0       9     1   arg   Ljava/lang/Object;
    MethodParameters:
      Name                           Flags
      arg                            final

  public java.lang.String stringOf(java.lang.Object, int);
    descriptor: (Ljava/lang/Object;I)Ljava/lang/String;
    flags: (0x0001) ACC_PUBLIC
    Code:
      stack=3, locals=6, args_size=3
         0: aload_0
         1: aload_1
         2: iload_2
         3: invokespecial #409                // Method inner$1:(Ljava/lang/Object;I)Ljava/lang/String;
         6: areturn
         7: astore        5
         9: aload         5
        11: instanceof    #411                // class java/lang/UnsupportedOperationException
        14: ifeq          23
        17: iconst_1
        18: istore        4
        20: goto          40
        23: aload         5
        25: instanceof    #413                // class java/lang/AssertionError
        28: ifeq          37
        31: iconst_1
        32: istore        4
        34: goto          40
        37: iconst_0
        38: istore        4
        40: iload         4
        42: ifeq          53
        45: aload_1
        46: invokestatic  #417                // Method java/lang/String.valueOf:(Ljava/lang/Object;)Ljava/lang/String;
        49: astore_3
        50: goto          56
        53: aload         5
        55: athrow
        56: aload_3
        57: areturn
      Exception table:
         from    to  target type
             0     6     7   Class java/lang/Throwable
      StackMapTable: number_of_entries = 6
        frame_type = 71 /* same_locals_1_stack_item */
          stack = [ class java/lang/Throwable ]
        frame_type = 254 /* append */
          offset_delta = 15
          locals = [ top, top, class java/lang/Throwable ]
        frame_type = 13 /* same */
        frame_type = 255 /* full_frame */
          offset_delta = 2
          locals = [ class scala/runtime/ScalaRunTime$, class java/lang/Object, int, top, int, class java/lang/Throwable ]
          stack = []
        frame_type = 12 /* same */
        frame_type = 255 /* full_frame */
          offset_delta = 2
          locals = [ class scala/runtime/ScalaRunTime$, class java/lang/Object, int, class java/lang/String, int, class java/lang/Throwable ]
          stack = []
      LineNumberTable:
        line 263: 0
        line 265: 9
        line 263: 53
      LocalVariableTable:
        Start  Length  Slot  Name   Signature
            0      58     0  this   Lscala/runtime/ScalaRunTime$;
            0      58     1   arg   Ljava/lang/Object;
            0      58     2 maxElements   I
    MethodParameters:
      Name                           Flags
      arg                            final
      maxElements                    final

  public java.lang.String replStringOf(java.lang.Object, int);
    descriptor: (Ljava/lang/Object;I)Ljava/lang/String;
    flags: (0x0001) ACC_PUBLIC
    Code:
      stack=3, locals=5, args_size=3
         0: aload_0
         1: aload_1
         2: iload_2
         3: invokevirtual #403                // Method stringOf:(Ljava/lang/Object;I)Ljava/lang/String;
         6: astore        4
         8: aload         4
        10: ifnonnull     17
        13: iconst_0
        14: goto          22
        17: aload         4
        19: invokevirtual #421                // Method java/lang/String.hashCode:()I
        22: tableswitch   { // 0 to 0
                       0: 40
                 default: 52
            }
        40: aload         4
        42: ifnonnull     52
        45: ldc_w         #423                // String null toString
        48: astore_3
        49: goto          121
        52: aload         4
        54: bipush        10
        56: invokevirtual #427                // Method java/lang/String.indexOf:(I)I
        59: iconst_0
        60: if_icmplt     96
        63: new           #354                // class java/lang/StringBuilder
        66: dup
        67: ldc_w         #428                // int 2
        70: invokespecial #358                // Method java/lang/StringBuilder."<init>":(I)V
        73: ldc_w         #430                // String \n
        76: invokevirtual #366                // Method java/lang/StringBuilder.append:(Ljava/lang/String;)Ljava/lang/StringBuilder;
        79: aload         4
        81: invokevirtual #366                // Method java/lang/StringBuilder.append:(Ljava/lang/String;)Ljava/lang/StringBuilder;
        84: ldc_w         #430                // String \n
        87: invokevirtual #366                // Method java/lang/StringBuilder.append:(Ljava/lang/String;)Ljava/lang/StringBuilder;
        90: invokevirtual #371                // Method java/lang/StringBuilder.toString:()Ljava/lang/String;
        93: goto          120
        96: new           #354                // class java/lang/StringBuilder
        99: dup
       100: ldc_w         #355                // int 1
       103: invokespecial #358                // Method java/lang/StringBuilder."<init>":(I)V
       106: aload         4
       108: invokevirtual #366                // Method java/lang/StringBuilder.append:(Ljava/lang/String;)Ljava/lang/StringBuilder;
       111: ldc_w         #430                // String \n
       114: invokevirtual #366                // Method java/lang/StringBuilder.append:(Ljava/lang/String;)Ljava/lang/StringBuilder;
       117: invokevirtual #371                // Method java/lang/StringBuilder.toString:()Ljava/lang/String;
       120: astore_3
       121: aload_3
       122: areturn
      StackMapTable: number_of_entries = 7
        frame_type = 253 /* append */
          offset_delta = 17
          locals = [ top, class java/lang/String ]
        frame_type = 68 /* same_locals_1_stack_item */
          stack = [ int ]
        frame_type = 17 /* same */
        frame_type = 11 /* same */
        frame_type = 43 /* same */
        frame_type = 87 /* same_locals_1_stack_item */
          stack = [ class java/lang/String ]
        frame_type = 255 /* full_frame */
          offset_delta = 0
          locals = [ class scala/runtime/ScalaRunTime$, class java/lang/Object, int, class java/lang/String, class java/lang/String ]
          stack = []
      LineNumberTable:
        line 271: 0
        line 272: 40
        line 273: 52
        line 274: 96
        line 271: 121
      LocalVariableTable:
        Start  Length  Slot  Name   Signature
            0     123     0  this   Lscala/runtime/ScalaRunTime$;
            0     123     1   arg   Ljava/lang/Object;
            0     123     2 maxElements   I
    MethodParameters:
      Name                           Flags
      arg                            final
      maxElements                    final

  public <T extends java.lang.Object> scala.collection.immutable.ArraySeq<T> genericWrapArray(java.lang.Object);
    descriptor: (Ljava/lang/Object;)Lscala/collection/immutable/ArraySeq;
    flags: (0x0001) ACC_PUBLIC
    Code:
      stack=2, locals=2, args_size=2
         0: aload_1
         1: ifnonnull     6
         4: aconst_null
         5: areturn
         6: getstatic     #438                // Field scala/collection/immutable/ArraySeq$.MODULE$:Lscala/collection/immutable/ArraySeq$;
         9: aload_1
        10: invokevirtual #441                // Method scala/collection/immutable/ArraySeq$.unsafeWrapArray:(Ljava/lang/Object;)Lscala/collection/immutable/ArraySeq;
        13: areturn
      StackMapTable: number_of_entries = 1
        frame_type = 6 /* same */
      LineNumberTable:
        line 279: 0
        line 280: 6
      LocalVariableTable:
        Start  Length  Slot  Name   Signature
            0      14     0  this   Lscala/runtime/ScalaRunTime$;
            0      14     1    xs   Ljava/lang/Object;
    Signature: #433                         // <T:Ljava/lang/Object;>(Ljava/lang/Object;)Lscala/collection/immutable/ArraySeq<TT;>;
    MethodParameters:
      Name                           Flags
      xs                             final

  public <T extends java.lang.Object> scala.collection.immutable.ArraySeq<T> wrapRefArray(T[]);
    descriptor: ([Ljava/lang/Object;)Lscala/collection/immutable/ArraySeq;
    flags: (0x0001) ACC_PUBLIC
    Code:
      stack=3, locals=2, args_size=2
         0: aload_1
         1: ifnonnull     6
         4: aconst_null
         5: areturn
         6: aload_1
         7: arraylength
         8: iconst_0
         9: if_icmpne     25
        12: getstatic     #438                // Field scala/collection/immutable/ArraySeq$.MODULE$:Lscala/collection/immutable/ArraySeq$;
        15: getstatic     #449                // Field scala/reflect/ClassTag$.MODULE$:Lscala/reflect/ClassTag$;
        18: invokevirtual #453                // Method scala/reflect/ClassTag$.AnyRef:()Lscala/reflect/ClassTag;
        21: invokevirtual #457                // Method scala/collection/immutable/ArraySeq$.empty:(Lscala/reflect/ClassTag;)Lscala/collection/immutable/ArraySeq;
        24: areturn
        25: new           #35                 // class scala/collection/immutable/ArraySeq$ofRef
        28: dup
        29: aload_1
        30: invokespecial #460                // Method scala/collection/immutable/ArraySeq$ofRef."<init>":([Ljava/lang/Object;)V
        33: areturn
      StackMapTable: number_of_entries = 2
        frame_type = 6 /* same */
        frame_type = 18 /* same */
      LineNumberTable:
        line 282: 0
        line 283: 6
        line 284: 25
      LocalVariableTable:
        Start  Length  Slot  Name   Signature
            0      34     0  this   Lscala/runtime/ScalaRunTime$;
            0      34     1    xs   [Ljava/lang/Object;
    Signature: #444                         // <T:Ljava/lang/Object;>([TT;)Lscala/collection/immutable/ArraySeq<TT;>;
    MethodParameters:
      Name                           Flags
      xs                             final

  public scala.collection.immutable.ArraySeq<java.lang.Object> wrapIntArray(int[]);
    descriptor: ([I)Lscala/collection/immutable/ArraySeq;
    flags: (0x0001) ACC_PUBLIC
    Code:
      stack=3, locals=2, args_size=2
         0: aload_1
         1: ifnull        13
         4: new           #29                 // class scala/collection/immutable/ArraySeq$ofInt
         7: dup
         8: aload_1
         9: invokespecial #466                // Method scala/collection/immutable/ArraySeq$ofInt."<init>":([I)V
        12: areturn
        13: aconst_null
        14: areturn
      StackMapTable: number_of_entries = 1
        frame_type = 13 /* same */
      LineNumberTable:
        line 286: 0
      LocalVariableTable:
        Start  Length  Slot  Name   Signature
            0      15     0  this   Lscala/runtime/ScalaRunTime$;
            0      15     1    xs   [I
    Signature: #463                         // ([I)Lscala/collection/immutable/ArraySeq<Ljava/lang/Object;>;
    MethodParameters:
      Name                           Flags
      xs                             final

  public scala.collection.immutable.ArraySeq<java.lang.Object> wrapDoubleArray(double[]);
    descriptor: ([D)Lscala/collection/immutable/ArraySeq;
    flags: (0x0001) ACC_PUBLIC
    Code:
      stack=3, locals=2, args_size=2
         0: aload_1
         1: ifnull        13
         4: new           #23                 // class scala/collection/immutable/ArraySeq$ofDouble
         7: dup
         8: aload_1
         9: invokespecial #472                // Method scala/collection/immutable/ArraySeq$ofDouble."<init>":([D)V
        12: areturn
        13: aconst_null
        14: areturn
      StackMapTable: number_of_entries = 1
        frame_type = 13 /* same */
      LineNumberTable:
        line 287: 0
      LocalVariableTable:
        Start  Length  Slot  Name   Signature
            0      15     0  this   Lscala/runtime/ScalaRunTime$;
            0      15     1    xs   [D
    Signature: #469                         // ([D)Lscala/collection/immutable/ArraySeq<Ljava/lang/Object;>;
    MethodParameters:
      Name                           Flags
      xs                             final

  public scala.collection.immutable.ArraySeq<java.lang.Object> wrapLongArray(long[]);
    descriptor: ([J)Lscala/collection/immutable/ArraySeq;
    flags: (0x0001) ACC_PUBLIC
    Code:
      stack=3, locals=2, args_size=2
         0: aload_1
         1: ifnull        13
         4: new           #32                 // class scala/collection/immutable/ArraySeq$ofLong
         7: dup
         8: aload_1
         9: invokespecial #478                // Method scala/collection/immutable/ArraySeq$ofLong."<init>":([J)V
        12: areturn
        13: aconst_null
        14: areturn
      StackMapTable: number_of_entries = 1
        frame_type = 13 /* same */
      LineNumberTable:
        line 288: 0
      LocalVariableTable:
        Start  Length  Slot  Name   Signature
            0      15     0  this   Lscala/runtime/ScalaRunTime$;
            0      15     1    xs   [J
    Signature: #475                         // ([J)Lscala/collection/immutable/ArraySeq<Ljava/lang/Object;>;
    MethodParameters:
      Name                           Flags
      xs                             final

  public scala.collection.immutable.ArraySeq<java.lang.Object> wrapFloatArray(float[]);
    descriptor: ([F)Lscala/collection/immutable/ArraySeq;
    flags: (0x0001) ACC_PUBLIC
    Code:
      stack=3, locals=2, args_size=2
         0: aload_1
         1: ifnull        13
         4: new           #26                 // class scala/collection/immutable/ArraySeq$ofFloat
         7: dup
         8: aload_1
         9: invokespecial #484                // Method scala/collection/immutable/ArraySeq$ofFloat."<init>":([F)V
        12: areturn
        13: aconst_null
        14: areturn
      StackMapTable: number_of_entries = 1
        frame_type = 13 /* same */
      LineNumberTable:
        line 289: 0
      LocalVariableTable:
        Start  Length  Slot  Name   Signature
            0      15     0  this   Lscala/runtime/ScalaRunTime$;
            0      15     1    xs   [F
    Signature: #481                         // ([F)Lscala/collection/immutable/ArraySeq<Ljava/lang/Object;>;
    MethodParameters:
      Name                           Flags
      xs                             final

  public scala.collection.immutable.ArraySeq<java.lang.Object> wrapCharArray(char[]);
    descriptor: ([C)Lscala/collection/immutable/ArraySeq;
    flags: (0x0001) ACC_PUBLIC
    Code:
      stack=3, locals=2, args_size=2
         0: aload_1
         1: ifnull        13
         4: new           #20                 // class scala/collection/immutable/ArraySeq$ofChar
         7: dup
         8: aload_1
         9: invokespecial #490                // Method scala/collection/immutable/ArraySeq$ofChar."<init>":([C)V
        12: areturn
        13: aconst_null
        14: areturn
      StackMapTable: number_of_entries = 1
        frame_type = 13 /* same */
      LineNumberTable:
        line 290: 0
      LocalVariableTable:
        Start  Length  Slot  Name   Signature
            0      15     0  this   Lscala/runtime/ScalaRunTime$;
            0      15     1    xs   [C
    Signature: #487                         // ([C)Lscala/collection/immutable/ArraySeq<Ljava/lang/Object;>;
    MethodParameters:
      Name                           Flags
      xs                             final

  public scala.collection.immutable.ArraySeq<java.lang.Object> wrapByteArray(byte[]);
    descriptor: ([B)Lscala/collection/immutable/ArraySeq;
    flags: (0x0001) ACC_PUBLIC
    Code:
      stack=3, locals=2, args_size=2
         0: aload_1
         1: ifnull        13
         4: new           #17                 // class scala/collection/immutable/ArraySeq$ofByte
         7: dup
         8: aload_1
         9: invokespecial #496                // Method scala/collection/immutable/ArraySeq$ofByte."<init>":([B)V
        12: areturn
        13: aconst_null
        14: areturn
      StackMapTable: number_of_entries = 1
        frame_type = 13 /* same */
      LineNumberTable:
        line 291: 0
      LocalVariableTable:
        Start  Length  Slot  Name   Signature
            0      15     0  this   Lscala/runtime/ScalaRunTime$;
            0      15     1    xs   [B
    Signature: #493                         // ([B)Lscala/collection/immutable/ArraySeq<Ljava/lang/Object;>;
    MethodParameters:
      Name                           Flags
      xs                             final

  public scala.collection.immutable.ArraySeq<java.lang.Object> wrapShortArray(short[]);
    descriptor: ([S)Lscala/collection/immutable/ArraySeq;
    flags: (0x0001) ACC_PUBLIC
    Code:
      stack=3, locals=2, args_size=2
         0: aload_1
         1: ifnull        13
         4: new           #38                 // class scala/collection/immutable/ArraySeq$ofShort
         7: dup
         8: aload_1
         9: invokespecial #502                // Method scala/collection/immutable/ArraySeq$ofShort."<init>":([S)V
        12: areturn
        13: aconst_null
        14: areturn
      StackMapTable: number_of_entries = 1
        frame_type = 13 /* same */
      LineNumberTable:
        line 292: 0
      LocalVariableTable:
        Start  Length  Slot  Name   Signature
            0      15     0  this   Lscala/runtime/ScalaRunTime$;
            0      15     1    xs   [S
    Signature: #499                         // ([S)Lscala/collection/immutable/ArraySeq<Ljava/lang/Object;>;
    MethodParameters:
      Name                           Flags
      xs                             final

  public scala.collection.immutable.ArraySeq<java.lang.Object> wrapBooleanArray(boolean[]);
    descriptor: ([Z)Lscala/collection/immutable/ArraySeq;
    flags: (0x0001) ACC_PUBLIC
    Code:
      stack=3, locals=2, args_size=2
         0: aload_1
         1: ifnull        13
         4: new           #12                 // class scala/collection/immutable/ArraySeq$ofBoolean
         7: dup
         8: aload_1
         9: invokespecial #508                // Method scala/collection/immutable/ArraySeq$ofBoolean."<init>":([Z)V
        12: areturn
        13: aconst_null
        14: areturn
      StackMapTable: number_of_entries = 1
        frame_type = 13 /* same */
      LineNumberTable:
        line 293: 0
      LocalVariableTable:
        Start  Length  Slot  Name   Signature
            0      15     0  this   Lscala/runtime/ScalaRunTime$;
            0      15     1    xs   [Z
    Signature: #505                         // ([Z)Lscala/collection/immutable/ArraySeq<Ljava/lang/Object;>;
    MethodParameters:
      Name                           Flags
      xs                             final

  public scala.collection.immutable.ArraySeq<scala.runtime.BoxedUnit> wrapUnitArray(scala.runtime.BoxedUnit[]);
    descriptor: ([Lscala/runtime/BoxedUnit;)Lscala/collection/immutable/ArraySeq;
    flags: (0x0001) ACC_PUBLIC
    Code:
      stack=3, locals=2, args_size=2
         0: aload_1
         1: ifnull        13
         4: new           #41                 // class scala/collection/immutable/ArraySeq$ofUnit
         7: dup
         8: aload_1
         9: invokespecial #514                // Method scala/collection/immutable/ArraySeq$ofUnit."<init>":([Lscala/runtime/BoxedUnit;)V
        12: areturn
        13: aconst_null
        14: areturn
      StackMapTable: number_of_entries = 1
        frame_type = 13 /* same */
      LineNumberTable:
        line 294: 0
      LocalVariableTable:
        Start  Length  Slot  Name   Signature
            0      15     0  this   Lscala/runtime/ScalaRunTime$;
            0      15     1    xs   [Lscala/runtime/BoxedUnit;
    Signature: #511                         // ([Lscala/runtime/BoxedUnit;)Lscala/collection/immutable/ArraySeq<Lscala/runtime/BoxedUnit;>;
    MethodParameters:
      Name                           Flags
      xs                             final

  private static final java.lang.Object[] copy$mZc$sp$1(boolean[]);
    descriptor: ([Z)[Ljava/lang/Object;
    flags: (0x001a) ACC_PRIVATE, ACC_STATIC, ACC_FINAL
    Code:
      stack=4, locals=4, args_size=1
         0: aload_0
         1: arraylength
         2: istore_1
         3: iload_1
         4: iconst_0
         5: if_icmpne     15
         8: getstatic     #312                // Field scala/Array$.MODULE$:Lscala/Array$;
        11: invokevirtual #316                // Method scala/Array$.emptyObjectArray:()[Ljava/lang/Object;
        14: areturn
        15: iload_1
        16: anewarray     #4                  // class java/lang/Object
        19: astore_2
        20: iconst_0
        21: istore_3
        22: iload_3
        23: iload_1
        24: if_icmpge     42
        27: aload_2
        28: iload_3
        29: aload_0
        30: iload_3
        31: baload
        32: invokestatic  #203                // Method java/lang/Boolean.valueOf:(Z)Ljava/lang/Boolean;
        35: aastore
        36: iinc          3, 1
        39: goto          22
        42: aload_2
        43: areturn
      StackMapTable: number_of_entries = 3
        frame_type = 252 /* append */
          offset_delta = 15
          locals = [ int ]
        frame_type = 253 /* append */
          offset_delta = 6
          locals = [ class "[Ljava/lang/Object;", int ]
        frame_type = 19 /* same */
      LineNumberTable:
        line 111: 0
        line 112: 3
        line 114: 15
        line 115: 20
        line 116: 22
        line 117: 27
        line 118: 36
        line 116: 39
        line 120: 42
      LocalVariableTable:
        Start  Length  Slot  Name   Signature
           20      23     2  dest   [Ljava/lang/Object;
           22      21     3     i   I
            3      40     1 length   I
            0      44     0   src   [Z
    MethodParameters:
      Name                           Flags
      src                            final

  private static final java.lang.Object[] copy$mBc$sp$1(byte[]);
    descriptor: ([B)[Ljava/lang/Object;
    flags: (0x001a) ACC_PRIVATE, ACC_STATIC, ACC_FINAL
    Code:
      stack=4, locals=4, args_size=1
         0: aload_0
         1: arraylength
         2: istore_1
         3: iload_1
         4: iconst_0
         5: if_icmpne     15
         8: getstatic     #312                // Field scala/Array$.MODULE$:Lscala/Array$;
        11: invokevirtual #316                // Method scala/Array$.emptyObjectArray:()[Ljava/lang/Object;
        14: areturn
        15: iload_1
        16: anewarray     #4                  // class java/lang/Object
        19: astore_2
        20: iconst_0
        21: istore_3
        22: iload_3
        23: iload_1
        24: if_icmpge     42
        27: aload_2
        28: iload_3
        29: aload_0
        30: iload_3
        31: baload
        32: invokestatic  #189                // Method java/lang/Byte.valueOf:(B)Ljava/lang/Byte;
        35: aastore
        36: iinc          3, 1
        39: goto          22
        42: aload_2
        43: areturn
      StackMapTable: number_of_entries = 3
        frame_type = 252 /* append */
          offset_delta = 15
          locals = [ int ]
        frame_type = 253 /* append */
          offset_delta = 6
          locals = [ class "[Ljava/lang/Object;", int ]
        frame_type = 19 /* same */
      LineNumberTable:
        line 111: 0
        line 112: 3
        line 114: 15
        line 115: 20
        line 116: 22
        line 117: 27
        line 118: 36
        line 116: 39
        line 120: 42
      LocalVariableTable:
        Start  Length  Slot  Name   Signature
           20      23     2  dest   [Ljava/lang/Object;
           22      21     3     i   I
            3      40     1 length   I
            0      44     0   src   [B
    MethodParameters:
      Name                           Flags
      src                            final

  private static final java.lang.Object[] copy$mCc$sp$1(char[]);
    descriptor: ([C)[Ljava/lang/Object;
    flags: (0x001a) ACC_PRIVATE, ACC_STATIC, ACC_FINAL
    Code:
      stack=4, locals=4, args_size=1
         0: aload_0
         1: arraylength
         2: istore_1
         3: iload_1
         4: iconst_0
         5: if_icmpne     15
         8: getstatic     #312                // Field scala/Array$.MODULE$:Lscala/Array$;
        11: invokevirtual #316                // Method scala/Array$.emptyObjectArray:()[Ljava/lang/Object;
        14: areturn
        15: iload_1
        16: anewarray     #4                  // class java/lang/Object
        19: astore_2
        20: iconst_0
        21: istore_3
        22: iload_3
        23: iload_1
        24: if_icmpge     42
        27: aload_2
        28: iload_3
        29: aload_0
        30: iload_3
        31: caload
        32: invokestatic  #182                // Method java/lang/Character.valueOf:(C)Ljava/lang/Character;
        35: aastore
        36: iinc          3, 1
        39: goto          22
        42: aload_2
        43: areturn
      StackMapTable: number_of_entries = 3
        frame_type = 252 /* append */
          offset_delta = 15
          locals = [ int ]
        frame_type = 253 /* append */
          offset_delta = 6
          locals = [ class "[Ljava/lang/Object;", int ]
        frame_type = 19 /* same */
      LineNumberTable:
        line 111: 0
        line 112: 3
        line 114: 15
        line 115: 20
        line 116: 22
        line 117: 27
        line 118: 36
        line 116: 39
        line 120: 42
      LocalVariableTable:
        Start  Length  Slot  Name   Signature
           20      23     2  dest   [Ljava/lang/Object;
           22      21     3     i   I
            3      40     1 length   I
            0      44     0   src   [C
    MethodParameters:
      Name                           Flags
      src                            final

  private static final java.lang.Object[] copy$mDc$sp$1(double[]);
    descriptor: ([D)[Ljava/lang/Object;
    flags: (0x001a) ACC_PRIVATE, ACC_STATIC, ACC_FINAL
    Code:
      stack=4, locals=4, args_size=1
         0: aload_0
         1: arraylength
         2: istore_1
         3: iload_1
         4: iconst_0
         5: if_icmpne     15
         8: getstatic     #312                // Field scala/Array$.MODULE$:Lscala/Array$;
        11: invokevirtual #316                // Method scala/Array$.emptyObjectArray:()[Ljava/lang/Object;
        14: areturn
        15: iload_1
        16: anewarray     #4                  // class java/lang/Object
        19: astore_2
        20: iconst_0
        21: istore_3
        22: iload_3
        23: iload_1
        24: if_icmpge     42
        27: aload_2
        28: iload_3
        29: aload_0
        30: iload_3
        31: daload
        32: invokestatic  #161                // Method java/lang/Double.valueOf:(D)Ljava/lang/Double;
        35: aastore
        36: iinc          3, 1
        39: goto          22
        42: aload_2
        43: areturn
      StackMapTable: number_of_entries = 3
        frame_type = 252 /* append */
          offset_delta = 15
          locals = [ int ]
        frame_type = 253 /* append */
          offset_delta = 6
          locals = [ class "[Ljava/lang/Object;", int ]
        frame_type = 19 /* same */
      LineNumberTable:
        line 111: 0
        line 112: 3
        line 114: 15
        line 115: 20
        line 116: 22
        line 117: 27
        line 118: 36
        line 116: 39
        line 120: 42
      LocalVariableTable:
        Start  Length  Slot  Name   Signature
           20      23     2  dest   [Ljava/lang/Object;
           22      21     3     i   I
            3      40     1 length   I
            0      44     0   src   [D
    MethodParameters:
      Name                           Flags
      src                            final

  private static final java.lang.Object[] copy$mFc$sp$1(float[]);
    descriptor: ([F)[Ljava/lang/Object;
    flags: (0x001a) ACC_PRIVATE, ACC_STATIC, ACC_FINAL
    Code:
      stack=4, locals=4, args_size=1
         0: aload_0
         1: arraylength
         2: istore_1
         3: iload_1
         4: iconst_0
         5: if_icmpne     15
         8: getstatic     #312                // Field scala/Array$.MODULE$:Lscala/Array$;
        11: invokevirtual #316                // Method scala/Array$.emptyObjectArray:()[Ljava/lang/Object;
        14: areturn
        15: iload_1
        16: anewarray     #4                  // class java/lang/Object
        19: astore_2
        20: iconst_0
        21: istore_3
        22: iload_3
        23: iload_1
        24: if_icmpge     42
        27: aload_2
        28: iload_3
        29: aload_0
        30: iload_3
        31: faload
        32: invokestatic  #175                // Method java/lang/Float.valueOf:(F)Ljava/lang/Float;
        35: aastore
        36: iinc          3, 1
        39: goto          22
        42: aload_2
        43: areturn
      StackMapTable: number_of_entries = 3
        frame_type = 252 /* append */
          offset_delta = 15
          locals = [ int ]
        frame_type = 253 /* append */
          offset_delta = 6
          locals = [ class "[Ljava/lang/Object;", int ]
        frame_type = 19 /* same */
      LineNumberTable:
        line 111: 0
        line 112: 3
        line 114: 15
        line 115: 20
        line 116: 22
        line 117: 27
        line 118: 36
        line 116: 39
        line 120: 42
      LocalVariableTable:
        Start  Length  Slot  Name   Signature
           20      23     2  dest   [Ljava/lang/Object;
           22      21     3     i   I
            3      40     1 length   I
            0      44     0   src   [F
    MethodParameters:
      Name                           Flags
      src                            final

  private static final java.lang.Object[] copy$mIc$sp$1(int[]);
    descriptor: ([I)[Ljava/lang/Object;
    flags: (0x001a) ACC_PRIVATE, ACC_STATIC, ACC_FINAL
    Code:
      stack=4, locals=4, args_size=1
         0: aload_0
         1: arraylength
         2: istore_1
         3: iload_1
         4: iconst_0
         5: if_icmpne     15
         8: getstatic     #312                // Field scala/Array$.MODULE$:Lscala/Array$;
        11: invokevirtual #316                // Method scala/Array$.emptyObjectArray:()[Ljava/lang/Object;
        14: areturn
        15: iload_1
        16: anewarray     #4                  // class java/lang/Object
        19: astore_2
        20: iconst_0
        21: istore_3
        22: iload_3
        23: iload_1
        24: if_icmpge     42
        27: aload_2
        28: iload_3
        29: aload_0
        30: iload_3
        31: iaload
        32: invokestatic  #154                // Method java/lang/Integer.valueOf:(I)Ljava/lang/Integer;
        35: aastore
        36: iinc          3, 1
        39: goto          22
        42: aload_2
        43: areturn
      StackMapTable: number_of_entries = 3
        frame_type = 252 /* append */
          offset_delta = 15
          locals = [ int ]
        frame_type = 253 /* append */
          offset_delta = 6
          locals = [ class "[Ljava/lang/Object;", int ]
        frame_type = 19 /* same */
      LineNumberTable:
        line 111: 0
        line 112: 3
        line 114: 15
        line 115: 20
        line 116: 22
        line 117: 27
        line 118: 36
        line 116: 39
        line 120: 42
      LocalVariableTable:
        Start  Length  Slot  Name   Signature
           20      23     2  dest   [Ljava/lang/Object;
           22      21     3     i   I
            3      40     1 length   I
            0      44     0   src   [I
    MethodParameters:
      Name                           Flags
      src                            final

  private static final java.lang.Object[] copy$mJc$sp$1(long[]);
    descriptor: ([J)[Ljava/lang/Object;
    flags: (0x001a) ACC_PRIVATE, ACC_STATIC, ACC_FINAL
    Code:
      stack=4, locals=4, args_size=1
         0: aload_0
         1: arraylength
         2: istore_1
         3: iload_1
         4: iconst_0
         5: if_icmpne     15
         8: getstatic     #312                // Field scala/Array$.MODULE$:Lscala/Array$;
        11: invokevirtual #316                // Method scala/Array$.emptyObjectArray:()[Ljava/lang/Object;
        14: areturn
        15: iload_1
        16: anewarray     #4                  // class java/lang/Object
        19: astore_2
        20: iconst_0
        21: istore_3
        22: iload_3
        23: iload_1
        24: if_icmpge     42
        27: aload_2
        28: iload_3
        29: aload_0
        30: iload_3
        31: laload
        32: invokestatic  #168                // Method java/lang/Long.valueOf:(J)Ljava/lang/Long;
        35: aastore
        36: iinc          3, 1
        39: goto          22
        42: aload_2
        43: areturn
      StackMapTable: number_of_entries = 3
        frame_type = 252 /* append */
          offset_delta = 15
          locals = [ int ]
        frame_type = 253 /* append */
          offset_delta = 6
          locals = [ class "[Ljava/lang/Object;", int ]
        frame_type = 19 /* same */
      LineNumberTable:
        line 111: 0
        line 112: 3
        line 114: 15
        line 115: 20
        line 116: 22
        line 117: 27
        line 118: 36
        line 116: 39
        line 120: 42
      LocalVariableTable:
        Start  Length  Slot  Name   Signature
           20      23     2  dest   [Ljava/lang/Object;
           22      21     3     i   I
            3      40     1 length   I
            0      44     0   src   [J
    MethodParameters:
      Name                           Flags
      src                            final

  private static final java.lang.Object[] copy$mSc$sp$1(short[]);
    descriptor: ([S)[Ljava/lang/Object;
    flags: (0x001a) ACC_PRIVATE, ACC_STATIC, ACC_FINAL
    Code:
      stack=4, locals=4, args_size=1
         0: aload_0
         1: arraylength
         2: istore_1
         3: iload_1
         4: iconst_0
         5: if_icmpne     15
         8: getstatic     #312                // Field scala/Array$.MODULE$:Lscala/Array$;
        11: invokevirtual #316                // Method scala/Array$.emptyObjectArray:()[Ljava/lang/Object;
        14: areturn
        15: iload_1
        16: anewarray     #4                  // class java/lang/Object
        19: astore_2
        20: iconst_0
        21: istore_3
        22: iload_3
        23: iload_1
        24: if_icmpge     42
        27: aload_2
        28: iload_3
        29: aload_0
        30: iload_3
        31: saload
        32: invokestatic  #196                // Method java/lang/Short.valueOf:(S)Ljava/lang/Short;
        35: aastore
        36: iinc          3, 1
        39: goto          22
        42: aload_2
        43: areturn
      StackMapTable: number_of_entries = 3
        frame_type = 252 /* append */
          offset_delta = 15
          locals = [ int ]
        frame_type = 253 /* append */
          offset_delta = 6
          locals = [ class "[Ljava/lang/Object;", int ]
        frame_type = 19 /* same */
      LineNumberTable:
        line 111: 0
        line 112: 3
        line 114: 15
        line 115: 20
        line 116: 22
        line 117: 27
        line 118: 36
        line 116: 39
        line 120: 42
      LocalVariableTable:
        Start  Length  Slot  Name   Signature
           20      23     2  dest   [Ljava/lang/Object;
           22      21     3     i   I
            3      40     1 length   I
            0      44     0   src   [S
    MethodParameters:
      Name                           Flags
      src                            final

  private static final java.lang.Object[] copy$mVc$sp$1(scala.runtime.BoxedUnit[]);
    descriptor: ([Lscala/runtime/BoxedUnit;)[Ljava/lang/Object;
    flags: (0x001a) ACC_PRIVATE, ACC_STATIC, ACC_FINAL
    Code:
      stack=4, locals=4, args_size=1
         0: aload_0
         1: arraylength
         2: istore_1
         3: iload_1
         4: iconst_0
         5: if_icmpne     15
         8: getstatic     #312                // Field scala/Array$.MODULE$:Lscala/Array$;
        11: invokevirtual #316                // Method scala/Array$.emptyObjectArray:()[Ljava/lang/Object;
        14: areturn
        15: iload_1
        16: anewarray     #4                  // class java/lang/Object
        19: astore_2
        20: iconst_0
        21: istore_3
        22: iload_3
        23: iload_1
        24: if_icmpge     39
        27: aload_2
        28: iload_3
        29: aload_0
        30: iload_3
        31: aaload
        32: aastore
        33: iinc          3, 1
        36: goto          22
        39: aload_2
        40: areturn
      StackMapTable: number_of_entries = 3
        frame_type = 252 /* append */
          offset_delta = 15
          locals = [ int ]
        frame_type = 253 /* append */
          offset_delta = 6
          locals = [ class "[Ljava/lang/Object;", int ]
        frame_type = 16 /* same */
      LineNumberTable:
        line 111: 0
        line 112: 3
        line 114: 15
        line 115: 20
        line 116: 22
        line 117: 27
        line 118: 33
        line 116: 36
        line 120: 39
      LocalVariableTable:
        Start  Length  Slot  Name   Signature
           20      20     2  dest   [Ljava/lang/Object;
           22      18     3     i   I
            3      37     1 length   I
            0      41     0   src   [Lscala/runtime/BoxedUnit;
    MethodParameters:
      Name                           Flags
      src                            final

  private static final java.lang.Object[] copy$1(java.lang.Object);
    descriptor: (Ljava/lang/Object;)[Ljava/lang/Object;
    flags: (0x001a) ACC_PRIVATE, ACC_STATIC, ACC_FINAL
    Code:
      stack=5, locals=4, args_size=1
         0: aload_0
         1: invokestatic  #250                // Method java/lang/reflect/Array.getLength:(Ljava/lang/Object;)I
         4: istore_3
         5: iload_3
         6: iconst_0
         7: if_icmpne     17
        10: getstatic     #312                // Field scala/Array$.MODULE$:Lscala/Array$;
        13: invokevirtual #316                // Method scala/Array$.emptyObjectArray:()[Ljava/lang/Object;
        16: areturn
        17: iload_3
        18: anewarray     #4                  // class java/lang/Object
        21: astore_1
        22: iconst_0
        23: istore_2
        24: iload_2
        25: iload_3
        26: if_icmpge     46
        29: aload_1
        30: iload_2
        31: getstatic     #58                 // Field MODULE$:Lscala/runtime/ScalaRunTime$;
        34: aload_0
        35: iload_2
        36: invokevirtual #520                // Method array_apply:(Ljava/lang/Object;I)Ljava/lang/Object;
        39: aastore
        40: iinc          2, 1
        43: goto          24
        46: aload_1
        47: areturn
      StackMapTable: number_of_entries = 3
        frame_type = 254 /* append */
          offset_delta = 17
          locals = [ top, top, int ]
        frame_type = 255 /* full_frame */
          offset_delta = 6
          locals = [ class java/lang/Object, class "[Ljava/lang/Object;", int, int ]
          stack = []
        frame_type = 21 /* same */
      LineNumberTable:
        line 88: 0
        line 112: 5
        line 114: 17
        line 115: 22
        line 116: 24
        line 117: 29
        line 118: 40
        line 116: 43
        line 120: 46
      LocalVariableTable:
        Start  Length  Slot  Name   Signature
           22      25     1  dest   [Ljava/lang/Object;
           24      23     2     i   I
            0      48     0   src   Ljava/lang/Object;
    MethodParameters:
      Name                           Flags
      src                            final

  private static final java.lang.String packageOf$1(java.lang.Object);
    descriptor: (Ljava/lang/Object;)Ljava/lang/String;
    flags: (0x001a) ACC_PRIVATE, ACC_STATIC, ACC_FINAL
    Code:
      stack=1, locals=3, args_size=1
         0: aload_0
         1: invokevirtual #66                 // Method java/lang/Object.getClass:()Ljava/lang/Class;
         4: invokevirtual #525                // Method java/lang/Class.getPackage:()Ljava/lang/Package;
         7: astore_2
         8: aload_2
         9: ifnonnull     19
        12: ldc_w         #527                // String
        15: astore_1
        16: goto          24
        19: aload_2
        20: invokevirtual #532                // Method java/lang/Package.getName:()Ljava/lang/String;
        23: astore_1
        24: aload_1
        25: areturn
      StackMapTable: number_of_entries = 2
        frame_type = 253 /* append */
          offset_delta = 19
          locals = [ top, class java/lang/Package ]
        frame_type = 255 /* full_frame */
          offset_delta = 4
          locals = [ class java/lang/Object, class java/lang/String, class java/lang/Package ]
          stack = []
      LineNumberTable:
        line 188: 0
        line 189: 8
        line 190: 19
        line 188: 24
      LocalVariableTable:
        Start  Length  Slot  Name   Signature
            0      26     0     x   Ljava/lang/Object;
    MethodParameters:
      Name                           Flags
      x                              final

  private static final boolean isScalaClass$1(java.lang.Object);
    descriptor: (Ljava/lang/Object;)Z
    flags: (0x001a) ACC_PRIVATE, ACC_STATIC, ACC_FINAL
    Code:
      stack=2, locals=1, args_size=1
         0: aload_0
         1: invokestatic  #535                // Method packageOf$1:(Ljava/lang/Object;)Ljava/lang/String;
         4: ldc_w         #537                // String scala.
         7: invokevirtual #541                // Method java/lang/String.startsWith:(Ljava/lang/String;)Z
        10: ireturn
      LineNumberTable:
        line 192: 0
      LocalVariableTable:
        Start  Length  Slot  Name   Signature
            0      11     0     x   Ljava/lang/Object;
    MethodParameters:
      Name                           Flags
      x                              final

  private static final boolean isScalaCompilerClass$1(java.lang.Object);
    descriptor: (Ljava/lang/Object;)Z
    flags: (0x001a) ACC_PRIVATE, ACC_STATIC, ACC_FINAL
    Code:
      stack=2, locals=1, args_size=1
         0: aload_0
         1: invokestatic  #535                // Method packageOf$1:(Ljava/lang/Object;)Ljava/lang/String;
         4: ldc_w         #544                // String scala.tools.nsc.
         7: invokevirtual #541                // Method java/lang/String.startsWith:(Ljava/lang/String;)Z
        10: ireturn
      LineNumberTable:
        line 193: 0
      LocalVariableTable:
        Start  Length  Slot  Name   Signature
            0      11     0     x   Ljava/lang/Object;
    MethodParameters:
      Name                           Flags
      x                              final

  private static final boolean isTuple$1(java.lang.Object);
    descriptor: (Ljava/lang/Object;)Z
    flags: (0x001a) ACC_PRIVATE, ACC_STATIC, ACC_FINAL
    Code:
      stack=2, locals=1, args_size=1
         0: aload_0
         1: ifnull        22
         4: aload_0
         5: invokevirtual #66                 // Method java/lang/Object.getClass:()Ljava/lang/Class;
         8: invokevirtual #546                // Method java/lang/Class.getName:()Ljava/lang/String;
        11: ldc_w         #548                // String scala.Tuple
        14: invokevirtual #541                // Method java/lang/String.startsWith:(Ljava/lang/String;)Z
        17: ifeq          22
        20: iconst_1
        21: ireturn
        22: iconst_0
        23: ireturn
      StackMapTable: number_of_entries = 1
        frame_type = 22 /* same */
      LineNumberTable:
        line 196: 0
      LocalVariableTable:
        Start  Length  Slot  Name   Signature
            0      24     0     x   Ljava/lang/Object;
    MethodParameters:
      Name                           Flags
      x                              final

  private static final boolean isSubClassOf$1(java.lang.Class, java.lang.String);
    descriptor: (Ljava/lang/Class;Ljava/lang/String;)Z
    flags: (0x001a) ACC_PRIVATE, ACC_STATIC, ACC_FINAL
    Code:
      stack=3, locals=3, args_size=2
         0: aload_0
         1: invokevirtual #558                // Method java/lang/Class.getClassLoader:()Ljava/lang/ClassLoader;
         4: astore_2
         5: aload_1
         6: iconst_0
         7: aload_2
         8: invokestatic  #562                // Method java/lang/Class.forName:(Ljava/lang/String;ZLjava/lang/ClassLoader;)Ljava/lang/Class;
        11: aload_0
        12: invokevirtual #566                // Method java/lang/Class.isAssignableFrom:(Ljava/lang/Class;)Z
        15: ireturn
        16: pop
        17: iconst_0
        18: ireturn
      Exception table:
         from    to  target type
             0    15    16   Class java/lang/ClassNotFoundException
      StackMapTable: number_of_entries = 1
        frame_type = 80 /* same_locals_1_stack_item */
          stack = [ class java/lang/ClassNotFoundException ]
      LineNumberTable:
        line 201: 0
        line 202: 5
        line 203: 11
        line 205: 17
      LocalVariableTable:
        Start  Length  Slot  Name   Signature
            5      10     2 classLoader   Ljava/lang/ClassLoader;
            0      19     0 potentialSubClass   Ljava/lang/Class;
            0      19     1 ofClass   Ljava/lang/String;
    MethodParameters:
      Name                           Flags
      potentialSubClass              final
      ofClass                        final

  private static final boolean isXmlNode$1(java.lang.Class);
    descriptor: (Ljava/lang/Class;)Z
    flags: (0x001a) ACC_PRIVATE, ACC_STATIC, ACC_FINAL
    Code:
      stack=2, locals=1, args_size=1
         0: aload_0
         1: ldc_w         #572                // String scala.xml.Node
         4: invokestatic  #574                // Method isSubClassOf$1:(Ljava/lang/Class;Ljava/lang/String;)Z
         7: ireturn
      LineNumberTable:
        line 207: 0
      LocalVariableTable:
        Start  Length  Slot  Name   Signature
            0       8     0 potentialSubClass   Ljava/lang/Class;
    MethodParameters:
      Name                           Flags
      potentialSubClass              final

  private static final boolean isXmlMetaData$1(java.lang.Class);
    descriptor: (Ljava/lang/Class;)Z
    flags: (0x001a) ACC_PRIVATE, ACC_STATIC, ACC_FINAL
    Code:
      stack=2, locals=1, args_size=1
         0: aload_0
         1: ldc_w         #577                // String scala.xml.MetaData
         4: invokestatic  #574                // Method isSubClassOf$1:(Ljava/lang/Class;Ljava/lang/String;)Z
         7: ireturn
      LineNumberTable:
        line 208: 0
      LocalVariableTable:
        Start  Length  Slot  Name   Signature
            0       8     0 potentialSubClass   Ljava/lang/Class;
    MethodParameters:
      Name                           Flags
      potentialSubClass              final

  private static final boolean useOwnToString$1(java.lang.Object);
    descriptor: (Ljava/lang/Object;)Z
    flags: (0x001a) ACC_PRIVATE, ACC_STATIC, ACC_FINAL
    Code:
      stack=2, locals=5, args_size=1
         0: aload_0
         1: instanceof    #46                 // class scala/collection/immutable/Range
         4: ifeq          12
         7: iconst_1
         8: istore_3
         9: goto          26
        12: aload_0
        13: instanceof    #580                // class scala/collection/immutable/NumericRange
        16: ifeq          24
        19: iconst_1
        20: istore_3
        21: goto          26
        24: iconst_0
        25: istore_3
        26: iload_3
        27: ifeq          35
        30: iconst_1
        31: istore_1
        32: goto          182
        35: aload_0
        36: instanceof    #582                // class scala/collection/SortedOps
        39: ifeq          47
        42: iconst_1
        43: istore_1
        44: goto          182
        47: aload_0
        48: instanceof    #584                // class scala/collection/StringView
        51: ifeq          59
        54: iconst_1
        55: istore_2
        56: goto          85
        59: aload_0
        60: instanceof    #586                // class scala/collection/StringOps
        63: ifeq          71
        66: iconst_1
        67: istore_2
        68: goto          85
        71: aload_0
        72: instanceof    #588                // class scala/collection/mutable/StringBuilder
        75: ifeq          83
        78: iconst_1
        79: istore_2
        80: goto          85
        83: iconst_0
        84: istore_2
        85: iload_2
        86: ifeq          94
        89: iconst_1
        90: istore_1
        91: goto          182
        94: aload_0
        95: instanceof    #590                // class scala/collection/View
        98: ifeq          106
       101: iconst_1
       102: istore_1
       103: goto          182
       106: aload_0
       107: instanceof    #592                // class scala/collection/Iterable
       110: ifeq          180
       113: aload_0
       114: checkcast     #592                // class scala/collection/Iterable
       117: astore        4
       119: aload         4
       121: instanceof    #594                // class scala/collection/StrictOptimizedIterableOps
       124: ifeq          171
       127: aload         4
       129: invokestatic  #596                // Method isScalaClass$1:(Ljava/lang/Object;)Z
       132: ifeq          171
       135: aload         4
       137: invokestatic  #598                // Method isScalaCompilerClass$1:(Ljava/lang/Object;)Z
       140: ifne          171
       143: aload         4
       145: invokevirtual #66                 // Method java/lang/Object.getClass:()Ljava/lang/Class;
       148: ldc_w         #572                // String scala.xml.Node
       151: invokestatic  #574                // Method isSubClassOf$1:(Ljava/lang/Class;Ljava/lang/String;)Z
       154: ifne          171
       157: aload         4
       159: invokevirtual #66                 // Method java/lang/Object.getClass:()Ljava/lang/Class;
       162: ldc_w         #577                // String scala.xml.MetaData
       165: invokestatic  #574                // Method isSubClassOf$1:(Ljava/lang/Class;Ljava/lang/String;)Z
       168: ifeq          175
       171: iconst_1
       172: goto          176
       175: iconst_0
       176: istore_1
       177: goto          182
       180: iconst_0
       181: istore_1
       182: iload_1
       183: ireturn
      StackMapTable: number_of_entries = 16
        frame_type = 12 /* same */
        frame_type = 11 /* same */
        frame_type = 254 /* append */
          offset_delta = 1
          locals = [ top, top, int ]
        frame_type = 8 /* same */
        frame_type = 11 /* same */
        frame_type = 11 /* same */
        frame_type = 11 /* same */
        frame_type = 11 /* same */
        frame_type = 255 /* full_frame */
          offset_delta = 1
          locals = [ class java/lang/Object, top, int, int ]
          stack = []
        frame_type = 8 /* same */
        frame_type = 11 /* same */
        frame_type = 252 /* append */
          offset_delta = 64
          locals = [ class scala/collection/Iterable ]
        frame_type = 3 /* same */
        frame_type = 64 /* same_locals_1_stack_item */
          stack = [ int ]
        frame_type = 250 /* chop */
          offset_delta = 3
        frame_type = 255 /* full_frame */
          offset_delta = 1
          locals = [ class java/lang/Object, int, top, int ]
          stack = []
      LineNumberTable:
        line 213: 0
        line 215: 35
        line 217: 47
        line 219: 94
        line 225: 106
        line 207: 148
        line 225: 154
        line 208: 162
        line 225: 168
        line 227: 180
        line 211: 182
      LocalVariableTable:
        Start  Length  Slot  Name   Signature
            0     184     0     x   Ljava/lang/Object;
    MethodParameters:
      Name                           Flags
      x                              final

  private final java.lang.String mapInner$1(java.lang.Object, int);
    descriptor: (Ljava/lang/Object;I)Ljava/lang/String;
    flags: (0x0012) ACC_PRIVATE, ACC_FINAL
    Code:
      stack=4, locals=7, args_size=3
         0: aload_1
         1: instanceof    #602                // class scala/Tuple2
         4: ifeq          70
         7: aload_1
         8: checkcast     #602                // class scala/Tuple2
        11: astore        4
        13: aload         4
        15: invokevirtual #605                // Method scala/Tuple2._1:()Ljava/lang/Object;
        18: astore        5
        20: aload         4
        22: invokevirtual #608                // Method scala/Tuple2._2:()Ljava/lang/Object;
        25: astore        6
        27: new           #354                // class java/lang/StringBuilder
        30: dup
        31: ldc_w         #609                // int 4
        34: invokespecial #358                // Method java/lang/StringBuilder."<init>":(I)V
        37: aload_0
        38: aload         5
        40: iload_2
        41: invokespecial #409                // Method inner$1:(Ljava/lang/Object;I)Ljava/lang/String;
        44: invokevirtual #366                // Method java/lang/StringBuilder.append:(Ljava/lang/String;)Ljava/lang/StringBuilder;
        47: ldc_w         #611                // String  ->
        50: invokevirtual #366                // Method java/lang/StringBuilder.append:(Ljava/lang/String;)Ljava/lang/StringBuilder;
        53: aload_0
        54: aload         6
        56: iload_2
        57: invokespecial #409                // Method inner$1:(Ljava/lang/Object;I)Ljava/lang/String;
        60: invokevirtual #366                // Method java/lang/StringBuilder.append:(Ljava/lang/String;)Ljava/lang/StringBuilder;
        63: invokevirtual #371                // Method java/lang/StringBuilder.toString:()Ljava/lang/String;
        66: astore_3
        67: goto          77
        70: aload_0
        71: aload_1
        72: iload_2
        73: invokespecial #409                // Method inner$1:(Ljava/lang/Object;I)Ljava/lang/String;
        76: astore_3
        77: aload_3
        78: areturn
      StackMapTable: number_of_entries = 2
        frame_type = 251 /* same_frame_extended */
          offset_delta = 70
        frame_type = 252 /* append */
          offset_delta = 6
          locals = [ class java/lang/String ]
      LineNumberTable:
        line 232: 0
        line 233: 70
        line 231: 77
      LocalVariableTable:
        Start  Length  Slot  Name   Signature
           20      50     5     k   Ljava/lang/Object;
           27      43     6     v   Ljava/lang/Object;
            0      79     0  this   Lscala/runtime/ScalaRunTime$;
            0      79     1   arg   Ljava/lang/Object;
            0      79     2 maxElements$1   I
    MethodParameters:
      Name                           Flags
      arg                            final
      maxElements$1                  final

  public static final java.lang.String $anonfun$stringOf$1(int);
    descriptor: (I)Ljava/lang/String;
    flags: (0x1019) ACC_PUBLIC, ACC_STATIC, ACC_FINAL, ACC_SYNTHETIC
    Code:
      stack=1, locals=1, args_size=1
         0: ldc_w         #618                // String ()
         3: areturn
      LineNumberTable:
        line 239: 0
      LocalVariableTable:
        Start  Length  Slot  Name   Signature
            0       4     0   x$1   I
    MethodParameters:
      Name                           Flags
      x$1                            final

  public static final java.lang.String $anonfun$stringOf$2(scala.runtime.ScalaRunTime$, int, java.lang.Object);
    descriptor: (Lscala/runtime/ScalaRunTime$;ILjava/lang/Object;)Ljava/lang/String;
    flags: (0x1019) ACC_PUBLIC, ACC_STATIC, ACC_FINAL, ACC_SYNTHETIC
    Code:
      stack=3, locals=3, args_size=3
         0: aload_0
         1: aload_2
         2: iload_1
         3: invokespecial #409                // Method inner$1:(Ljava/lang/Object;I)Ljava/lang/String;
         6: areturn
      LineNumberTable:
        line 241: 0
      LocalVariableTable:
        Start  Length  Slot  Name   Signature
            0       7     0 $this   Lscala/runtime/ScalaRunTime$;
            0       7     1 maxElements$1   I
            0       7     2   arg   Ljava/lang/Object;
    MethodParameters:
      Name                           Flags
      $this                          final synthetic
      maxElements$1                  final
      arg                            final

  private final java.lang.String arrayToString$1(java.lang.Object, int);
    descriptor: (Ljava/lang/Object;I)Ljava/lang/String;
    flags: (0x0012) ACC_PRIVATE, ACC_FINAL
    Code:
      stack=5, locals=12, args_size=3
         0: aload_1
         1: invokevirtual #66                 // Method java/lang/Object.getClass:()Ljava/lang/Class;
         4: invokevirtual #85                 // Method java/lang/Class.getComponentType:()Ljava/lang/Class;
         7: ldc_w         #624                // class scala/runtime/BoxedUnit
        10: astore_3
        11: dup
        12: ifnonnull     19
        15: pop
        16: goto          189
        19: aload_3
        20: invokevirtual #116                // Method java/lang/Object.equals:(Ljava/lang/Object;)Z
        23: ifeq          189
        26: getstatic     #629                // Field scala/runtime/RichInt$.MODULE$:Lscala/runtime/RichInt$;
        29: pop
        30: iconst_0
        31: istore        4
        33: getstatic     #634                // Field scala/math/package$.MODULE$:Lscala/math/package$;
        36: pop
        37: aload_1
        38: invokestatic  #250                // Method java/lang/reflect/Array.getLength:(Ljava/lang/Object;)I
        41: iload_2
        42: invokestatic  #640                // Method java/lang/Math.min:(II)I
        45: istore        6
        47: getstatic     #645                // Field scala/collection/immutable/Range$.MODULE$:Lscala/collection/immutable/Range$;
        50: pop
        51: new           #44                 // class scala/collection/immutable/Range$Exclusive
        54: dup
        55: iload         4
        57: iload         6
        59: iconst_1
        60: invokespecial #648                // Method scala/collection/immutable/Range$Exclusive."<init>":(III)V
        63: astore        5
        65: aload         5
        67: invokevirtual #651                // Method scala/collection/immutable/Range.scala$collection$immutable$Range$$validateMaxLength:()V
        70: getstatic     #656                // Field scala/collection/immutable/IndexedSeq$.MODULE$:Lscala/collection/immutable/IndexedSeq$;
        73: invokeinterface #662,  1          // InterfaceMethod scala/collection/IterableFactory.newBuilder:()Lscala/collection/mutable/Builder;
        78: astore        7
        80: aload         5
        82: invokeinterface #663,  1          // InterfaceMethod scala/collection/StrictOptimizedIterableOps.iterator:()Lscala/collection/Iterator;
        87: astore        8
        89: aload         8
        91: invokeinterface #328,  1          // InterfaceMethod scala/collection/Iterator.hasNext:()Z
        96: ifeq          152
        99: aload         7
       101: aload         8
       103: invokeinterface #331,  1          // InterfaceMethod scala/collection/Iterator.next:()Ljava/lang/Object;
       108: checkcast     #150                // class java/lang/Integer
       111: pop
       112: ldc_w         #618                // String ()
       115: astore        11
       117: aload         11
       119: aconst_null
       120: astore        11
       122: astore        10
       124: aload         10
       126: aconst_null
       127: astore        10
       129: astore        9
       131: ifnonnull     136
       134: aconst_null
       135: athrow
       136: aload         7
       138: aload         9
       140: invokeinterface #669,  2          // InterfaceMethod scala/collection/mutable/Growable.addOne:(Ljava/lang/Object;)Lscala/collection/mutable/Growable;
       145: pop
       146: aconst_null
       147: astore        9
       149: goto          89
       152: aload         7
       154: invokeinterface #674,  1          // InterfaceMethod scala/collection/mutable/Builder.result:()Ljava/lang/Object;
       159: aconst_null
       160: astore        8
       162: aconst_null
       163: astore        9
       165: aconst_null
       166: astore        7
       168: checkcast     #676                // class scala/collection/immutable/IndexedSeq
       171: aconst_null
       172: astore        5
       174: ldc_w         #678                // String Array(
       177: ldc_w         #680                // String ,
       180: ldc_w         #375                // String )
       183: invokeinterface #681,  4          // InterfaceMethod scala/collection/immutable/IndexedSeq.mkString:(Ljava/lang/String;Ljava/lang/String;Ljava/lang/String;)Ljava/lang/String;
       188: areturn
       189: getstatic     #686                // Field scala/collection/ArrayOps$.MODULE$:Lscala/collection/ArrayOps$;
       192: aload_1
       193: invokevirtual #690                // Method scala/collection/ArrayOps$.iterator$extension:(Ljava/lang/Object;)Lscala/collection/Iterator;
       196: iload_2
       197: invokeinterface #694,  2          // InterfaceMethod scala/collection/Iterator.take:(I)Lscala/collection/Iterator;
       202: aload_0
       203: iload_2
       204: invokedynamic #710,  0            // InvokeDynamic #0:apply:(Lscala/runtime/ScalaRunTime$;I)Lscala/Function1;
       209: invokeinterface #714,  2          // InterfaceMethod scala/collection/Iterator.map:(Lscala/Function1;)Lscala/collection/Iterator;
       214: ldc_w         #678                // String Array(
       217: ldc_w         #680                // String ,
       220: ldc_w         #375                // String )
       223: invokeinterface #379,  4          // InterfaceMethod scala/collection/Iterator.mkString:(Ljava/lang/String;Ljava/lang/String;Ljava/lang/String;)Ljava/lang/String;
       228: areturn
      StackMapTable: number_of_entries = 5
        frame_type = 255 /* full_frame */
          offset_delta = 19
          locals = [ class scala/runtime/ScalaRunTime$, class java/lang/Object, int, class java/lang/Class ]
          stack = [ class java/lang/Class ]
        frame_type = 255 /* full_frame */
          offset_delta = 69
          locals = [ class scala/runtime/ScalaRunTime$, class java/lang/Object, int, class java/lang/Class, int, class scala/collection/immutable/Range$Exclusive, int, class scala/collection/mutable/Builder, class scala/collection/Iterator ]
          stack = []
        frame_type = 254 /* append */
          offset_delta = 46
          locals = [ class java/lang/String, null, null ]
        frame_type = 248 /* chop */
          offset_delta = 15
        frame_type = 255 /* full_frame */
          offset_delta = 36
          locals = [ class scala/runtime/ScalaRunTime$, class java/lang/Object, int, class java/lang/Class ]
          stack = []
      LineNumberTable:
        line 238: 0
        line 239: 26
        line 88: 37
        line 239: 41
        line 239: 108
        line 239: 112
        line 239: 117
        line 239: 124
        line 241: 189
      LocalVariableTable:
        Start  Length  Slot  Name   Signature
            0     229     0  this   Lscala/runtime/ScalaRunTime$;
            0     229     1     x   Ljava/lang/Object;
            0     229     2 maxElements$1   I
           65     106     5 map_this   Lscala/collection/immutable/Range;
           80      85     7 strictOptimizedMap_b   Lscala/collection/mutable/Builder;
           89      70     8 strictOptimizedMap_it   Lscala/collection/Iterator;
          136      10     9 strictOptimizedMap_$plus$eq_elem   Ljava/lang/Object;
    MethodParameters:
      Name                           Flags
      x                              final
      maxElements$1                  final

  public static final java.lang.String $anonfun$stringOf$3(scala.runtime.ScalaRunTime$, int, java.lang.Object);
    descriptor: (Lscala/runtime/ScalaRunTime$;ILjava/lang/Object;)Ljava/lang/String;
    flags: (0x1019) ACC_PUBLIC, ACC_STATIC, ACC_FINAL, ACC_SYNTHETIC
    Code:
      stack=3, locals=3, args_size=3
         0: aload_0
         1: aload_2
         2: iload_1
         3: invokespecial #723                // Method mapInner$1:(Ljava/lang/Object;I)Ljava/lang/String;
         6: areturn
      LineNumberTable:
        line 254: 0
      LocalVariableTable:
        Start  Length  Slot  Name   Signature
            0       7     0 $this   Lscala/runtime/ScalaRunTime$;
            0       7     1 maxElements$1   I
            0       7     2   arg   Ljava/lang/Object;
    MethodParameters:
      Name                           Flags
      $this                          final synthetic
      maxElements$1                  final
      arg                            final

  public static final java.lang.String $anonfun$stringOf$4(scala.runtime.ScalaRunTime$, int, java.lang.Object);
    descriptor: (Lscala/runtime/ScalaRunTime$;ILjava/lang/Object;)Ljava/lang/String;
    flags: (0x1019) ACC_PUBLIC, ACC_STATIC, ACC_FINAL, ACC_SYNTHETIC
    Code:
      stack=3, locals=3, args_size=3
         0: aload_0
         1: aload_2
         2: iload_1
         3: invokespecial #409                // Method inner$1:(Ljava/lang/Object;I)Ljava/lang/String;
         6: areturn
      LineNumberTable:
        line 255: 0
      LocalVariableTable:
        Start  Length  Slot  Name   Signature
            0       7     0 $this   Lscala/runtime/ScalaRunTime$;
            0       7     1 maxElements$1   I
            0       7     2   arg   Ljava/lang/Object;
    MethodParameters:
      Name                           Flags
      $this                          final synthetic
      maxElements$1                  final
      arg                            final

  public static final java.lang.String $anonfun$stringOf$5(scala.runtime.ScalaRunTime$, int, java.lang.Object);
    descriptor: (Lscala/runtime/ScalaRunTime$;ILjava/lang/Object;)Ljava/lang/String;
    flags: (0x1019) ACC_PUBLIC, ACC_STATIC, ACC_FINAL, ACC_SYNTHETIC
    Code:
      stack=3, locals=3, args_size=3
         0: aload_0
         1: aload_2
         2: iload_1
         3: invokespecial #409                // Method inner$1:(Ljava/lang/Object;I)Ljava/lang/String;
         6: areturn
      LineNumberTable:
        line 257: 0
      LocalVariableTable:
        Start  Length  Slot  Name   Signature
            0       7     0 $this   Lscala/runtime/ScalaRunTime$;
            0       7     1 maxElements$1   I
            0       7     2   arg   Ljava/lang/Object;
    MethodParameters:
      Name                           Flags
      $this                          final synthetic
      maxElements$1                  final
      arg                            final

  private final java.lang.String inner$1(java.lang.Object, int);
    descriptor: (Ljava/lang/Object;I)Ljava/lang/String;
    flags: (0x0012) ACC_PRIVATE, ACC_FINAL
    Code:
      stack=4, locals=9, args_size=3
         0: aload_1
         1: ifnonnull     11
         4: ldc_w         #727                // String null
         7: astore_3
         8: goto          442
        11: ldc_w         #527                // String
        14: aload_1
        15: invokevirtual #116                // Method java/lang/Object.equals:(Ljava/lang/Object;)Z
        18: ifeq          28
        21: ldc_w         #729                // String \"\"
        24: astore_3
        25: goto          442
        28: aload_1
        29: instanceof    #415                // class java/lang/String
        32: ifeq          116
        35: aload_1
        36: checkcast     #415                // class java/lang/String
        39: astore        4
        41: getstatic     #734                // Field scala/runtime/RichChar$.MODULE$:Lscala/runtime/RichChar$;
        44: pop
        45: getstatic     #739                // Field scala/collection/StringOps$.MODULE$:Lscala/collection/StringOps$;
        48: aload         4
        50: invokevirtual #743                // Method scala/collection/StringOps$.head$extension:(Ljava/lang/String;)C
        53: invokestatic  #747                // Method java/lang/Character.isWhitespace:(C)Z
        56: ifne          77
        59: getstatic     #734                // Field scala/runtime/RichChar$.MODULE$:Lscala/runtime/RichChar$;
        62: pop
        63: getstatic     #739                // Field scala/collection/StringOps$.MODULE$:Lscala/collection/StringOps$;
        66: aload         4
        68: invokevirtual #750                // Method scala/collection/StringOps$.last$extension:(Ljava/lang/String;)C
        71: invokestatic  #747                // Method java/lang/Character.isWhitespace:(C)Z
        74: ifeq          110
        77: new           #354                // class java/lang/StringBuilder
        80: dup
        81: ldc_w         #428                // int 2
        84: invokespecial #358                // Method java/lang/StringBuilder."<init>":(I)V
        87: ldc_w         #752                // String \"
        90: invokevirtual #366                // Method java/lang/StringBuilder.append:(Ljava/lang/String;)Ljava/lang/StringBuilder;
        93: aload         4
        95: invokevirtual #366                // Method java/lang/StringBuilder.append:(Ljava/lang/String;)Ljava/lang/StringBuilder;
        98: ldc_w         #752                // String \"
       101: invokevirtual #366                // Method java/lang/StringBuilder.append:(Ljava/lang/String;)Ljava/lang/StringBuilder;
       104: invokevirtual #371                // Method java/lang/StringBuilder.toString:()Ljava/lang/String;
       107: goto          112
       110: aload         4
       112: astore_3
       113: goto          442
       116: aload_1
       117: invokestatic  #754                // Method useOwnToString$1:(Ljava/lang/Object;)Z
       120: ifeq          131
       123: aload_1
       124: invokevirtual #755                // Method java/lang/Object.toString:()Ljava/lang/String;
       127: astore_3
       128: goto          442
       131: aload_0
       132: aload_1
       133: iconst_1
       134: invokevirtual #757                // Method isArray:(Ljava/lang/Object;I)Z
       137: ifeq          150
       140: aload_0
       141: aload_1
       142: iload_2
       143: invokespecial #759                // Method arrayToString$1:(Ljava/lang/Object;I)Ljava/lang/String;
       146: astore_3
       147: goto          442
       150: aload_1
       151: instanceof    #761                // class scala/collection/Map
       154: ifeq          232
       157: aload_1
       158: checkcast     #761                // class scala/collection/Map
       161: astore        5
       163: aload         5
       165: invokeinterface #762,  1          // InterfaceMethod scala/collection/Map.iterator:()Lscala/collection/Iterator;
       170: iload_2
       171: invokeinterface #694,  2          // InterfaceMethod scala/collection/Iterator.take:(I)Lscala/collection/Iterator;
       176: aload_0
       177: iload_2
       178: invokedynamic #766,  0            // InvokeDynamic #1:apply:(Lscala/runtime/ScalaRunTime$;I)Lscala/Function1;
       183: invokeinterface #714,  2          // InterfaceMethod scala/collection/Iterator.map:(Lscala/Function1;)Lscala/collection/Iterator;
       188: new           #354                // class java/lang/StringBuilder
       191: dup
       192: ldc_w         #355                // int 1
       195: invokespecial #358                // Method java/lang/StringBuilder."<init>":(I)V
       198: aload         5
       200: invokeinterface #769,  1          // InterfaceMethod scala/collection/Iterable.className:()Ljava/lang/String;
       205: invokevirtual #366                // Method java/lang/StringBuilder.append:(Ljava/lang/String;)Ljava/lang/StringBuilder;
       208: ldc_w         #368                // String (
       211: invokevirtual #366                // Method java/lang/StringBuilder.append:(Ljava/lang/String;)Ljava/lang/StringBuilder;
       214: invokevirtual #371                // Method java/lang/StringBuilder.toString:()Ljava/lang/String;
       217: ldc_w         #680                // String ,
       220: ldc_w         #375                // String )
       223: invokeinterface #379,  4          // InterfaceMethod scala/collection/Iterator.mkString:(Ljava/lang/String;Ljava/lang/String;Ljava/lang/String;)Ljava/lang/String;
       228: astore_3
       229: goto          442
       232: aload_1
       233: instanceof    #592                // class scala/collection/Iterable
       236: ifeq          314
       239: aload_1
       240: checkcast     #592                // class scala/collection/Iterable
       243: astore        6
       245: aload         6
       247: invokeinterface #770,  1          // InterfaceMethod scala/collection/Iterable.iterator:()Lscala/collection/Iterator;
       252: iload_2
       253: invokeinterface #694,  2          // InterfaceMethod scala/collection/Iterator.take:(I)Lscala/collection/Iterator;
       258: aload_0
       259: iload_2
       260: invokedynamic #774,  0            // InvokeDynamic #2:apply:(Lscala/runtime/ScalaRunTime$;I)Lscala/Function1;
       265: invokeinterface #714,  2          // InterfaceMethod scala/collection/Iterator.map:(Lscala/Function1;)Lscala/collection/Iterator;
       270: new           #354                // class java/lang/StringBuilder
       273: dup
       274: ldc_w         #355                // int 1
       277: invokespecial #358                // Method java/lang/StringBuilder."<init>":(I)V
       280: aload         6
       282: invokeinterface #769,  1          // InterfaceMethod scala/collection/Iterable.className:()Ljava/lang/String;
       287: invokevirtual #366                // Method java/lang/StringBuilder.append:(Ljava/lang/String;)Ljava/lang/StringBuilder;
       290: ldc_w         #368                // String (
       293: invokevirtual #366                // Method java/lang/StringBuilder.append:(Ljava/lang/String;)Ljava/lang/StringBuilder;
       296: invokevirtual #371                // Method java/lang/StringBuilder.toString:()Ljava/lang/String;
       299: ldc_w         #680                // String ,
       302: ldc_w         #375                // String )
       305: invokeinterface #379,  4          // InterfaceMethod scala/collection/Iterator.mkString:(Ljava/lang/String;Ljava/lang/String;Ljava/lang/String;)Ljava/lang/String;
       310: astore_3
       311: goto          442
       314: aload_1
       315: instanceof    #776                // class scala/Product1
       318: ifeq          379
       321: aload_1
       322: checkcast     #776                // class scala/Product1
       325: astore        7
       327: aload         7
       329: invokestatic  #778                // Method isTuple$1:(Ljava/lang/Object;)Z
       332: ifeq          379
       335: new           #354                // class java/lang/StringBuilder
       338: dup
       339: ldc_w         #779                // int 3
       342: invokespecial #358                // Method java/lang/StringBuilder."<init>":(I)V
       345: ldc_w         #368                // String (
       348: invokevirtual #366                // Method java/lang/StringBuilder.append:(Ljava/lang/String;)Ljava/lang/StringBuilder;
       351: aload_0
       352: aload         7
       354: invokeinterface #780,  1          // InterfaceMethod scala/Product1._1:()Ljava/lang/Object;
       359: iload_2
       360: invokespecial #409                // Method inner$1:(Ljava/lang/Object;I)Ljava/lang/String;
       363: invokevirtual #366                // Method java/lang/StringBuilder.append:(Ljava/lang/String;)Ljava/lang/StringBuilder;
       366: ldc_w         #782                // String ,)
       369: invokevirtual #366                // Method java/lang/StringBuilder.append:(Ljava/lang/String;)Ljava/lang/StringBuilder;
       372: invokevirtual #371                // Method java/lang/StringBuilder.toString:()Ljava/lang/String;
       375: astore_3
       376: goto          442
       379: aload_1
       380: instanceof    #349                // class scala/Product
       383: ifeq          437
       386: aload_1
       387: checkcast     #349                // class scala/Product
       390: astore        8
       392: aload         8
       394: invokestatic  #778                // Method isTuple$1:(Ljava/lang/Object;)Z
       397: ifeq          437
       400: aload         8
       402: invokeinterface #352,  1          // InterfaceMethod scala/Product.productIterator:()Lscala/collection/Iterator;
       407: aload_0
       408: iload_2
       409: invokedynamic #786,  0            // InvokeDynamic #3:apply:(Lscala/runtime/ScalaRunTime$;I)Lscala/Function1;
       414: invokeinterface #714,  2          // InterfaceMethod scala/collection/Iterator.map:(Lscala/Function1;)Lscala/collection/Iterator;
       419: ldc_w         #368                // String (
       422: ldc_w         #373                // String ,
       425: ldc_w         #375                // String )
       428: invokeinterface #379,  4          // InterfaceMethod scala/collection/Iterator.mkString:(Ljava/lang/String;Ljava/lang/String;Ljava/lang/String;)Ljava/lang/String;
       433: astore_3
       434: goto          442
       437: aload_1
       438: invokevirtual #755                // Method java/lang/Object.toString:()Ljava/lang/String;
       441: astore_3
       442: aload_3
       443: areturn
      StackMapTable: number_of_entries = 13
        frame_type = 11 /* same */
        frame_type = 16 /* same */
        frame_type = 253 /* append */
          offset_delta = 48
          locals = [ top, class java/lang/String ]
        frame_type = 32 /* same */
        frame_type = 65 /* same_locals_1_stack_item */
          stack = [ class java/lang/String ]
        frame_type = 249 /* chop */
          offset_delta = 3
        frame_type = 14 /* same */
        frame_type = 18 /* same */
        frame_type = 251 /* same_frame_extended */
          offset_delta = 81
        frame_type = 251 /* same_frame_extended */
          offset_delta = 81
        frame_type = 251 /* same_frame_extended */
          offset_delta = 64
        frame_type = 57 /* same */
        frame_type = 252 /* append */
          offset_delta = 4
          locals = [ class java/lang/String ]
      LineNumberTable:
        line 249: 0
        line 250: 11
        line 251: 28
        line 252: 116
        line 253: 131
        line 30: 133
        line 253: 134
        line 254: 150
        line 255: 232
        line 256: 314
        line 257: 379
        line 258: 437
        line 248: 442
      LocalVariableTable:
        Start  Length  Slot  Name   Signature
            0     444     0  this   Lscala/runtime/ScalaRunTime$;
            0     444     1   arg   Ljava/lang/Object;
            0     444     2 maxElements$1   I
    MethodParameters:
      Name                           Flags
      arg                            final
      maxElements$1                  final

  private scala.runtime.ScalaRunTime$();
    descriptor: ()V
    flags: (0x0002) ACC_PRIVATE
    Code:
      stack=1, locals=1, args_size=1
         0: aload_0
         1: invokespecial #787                // Method java/lang/Object."<init>":()V
         4: return
      LineNumberTable:
        line 29: 0
      LocalVariableTable:
        Start  Length  Slot  Name   Signature
            0       5     0  this   Lscala/runtime/ScalaRunTime$;

  public static final java.lang.String $anonfun$stringOf$1$adapted(java.lang.Object);
    descriptor: (Ljava/lang/Object;)Ljava/lang/String;
    flags: (0x1019) ACC_PUBLIC, ACC_STATIC, ACC_FINAL, ACC_SYNTHETIC
    Code:
      stack=1, locals=1, args_size=1
         0: aload_0
         1: invokestatic  #219                // Method scala/runtime/BoxesRunTime.unboxToInt:(Ljava/lang/Object;)I
         4: invokestatic  #790                // Method $anonfun$stringOf$1:(I)Ljava/lang/String;
         7: areturn
      LineNumberTable:
        line 239: 0
      LocalVariableTable:
        Start  Length  Slot  Name   Signature
            0       8     0   x$1   Ljava/lang/Object;
    MethodParameters:
      Name                           Flags
      x$1                            final

  private static java.lang.Object $deserializeLambda$(java.lang.invoke.SerializedLambda);
    descriptor: (Ljava/lang/invoke/SerializedLambda;)Ljava/lang/Object;
    flags: (0x100a) ACC_PRIVATE, ACC_STATIC, ACC_SYNTHETIC
    Code:
      stack=1, locals=1, args_size=1
         0: aload_0
         1: invokedynamic #802,  0            // InvokeDynamic #4:lambdaDeserialize:(Ljava/lang/invoke/SerializedLambda;)Ljava/lang/Object;
         6: areturn
}
InnerClasses:
  public static final #10= #7 of #9;      // Lookup=class java/lang/invoke/MethodHandles$Lookup of class java/lang/invoke/MethodHandles
  public static final #15= #12 of #14;    // ofBoolean=class scala/collection/immutable/ArraySeq$ofBoolean of class scala/collection/immutable/ArraySeq
  public static final #18= #17 of #14;    // ofByte=class scala/collection/immutable/ArraySeq$ofByte of class scala/collection/immutable/ArraySeq
  public static final #21= #20 of #14;    // ofChar=class scala/collection/immutable/ArraySeq$ofChar of class scala/collection/immutable/ArraySeq
  public static final #24= #23 of #14;    // ofDouble=class scala/collection/immutable/ArraySeq$ofDouble of class scala/collection/immutable/ArraySeq
  public static final #27= #26 of #14;    // ofFloat=class scala/collection/immutable/ArraySeq$ofFloat of class scala/collection/immutable/ArraySeq
  public static final #30= #29 of #14;    // ofInt=class scala/collection/immutable/ArraySeq$ofInt of class scala/collection/immutable/ArraySeq
  public static final #33= #32 of #14;    // ofLong=class scala/collection/immutable/ArraySeq$ofLong of class scala/collection/immutable/ArraySeq
  public static final #36= #35 of #14;    // ofRef=class scala/collection/immutable/ArraySeq$ofRef of class scala/collection/immutable/ArraySeq
  public static final #39= #38 of #14;    // ofShort=class scala/collection/immutable/ArraySeq$ofShort of class scala/collection/immutable/ArraySeq
  public static final #42= #41 of #14;    // ofUnit=class scala/collection/immutable/ArraySeq$ofUnit of class scala/collection/immutable/ArraySeq
  public static final #47= #44 of #46;    // Exclusive=class scala/collection/immutable/Range$Exclusive of class scala/collection/immutable/Range
  public final #49;                       // class scala/runtime/ScalaRunTime$$anon$1
SourceFile: "ScalaRunTime.scala"
BootstrapMethods:
  0: #707 REF_invokeStatic java/lang/invoke/LambdaMetafactory.altMetafactory:(Ljava/lang/invoke/MethodHandles$Lookup;Ljava/lang/String;Ljava/lang/invoke/MethodType;[Ljava/lang/Object;)Ljava/lang/invoke/CallSite;
    Method arguments:
      #695 (Ljava/lang/Object;)Ljava/lang/Object;
      #698 REF_invokeStatic scala/runtime/ScalaRunTime$.$anonfun$stringOf$2:(Lscala/runtime/ScalaRunTime$;ILjava/lang/Object;)Ljava/lang/String;
      #699 (Ljava/lang/Object;)Ljava/lang/String;
      #700 5
      #355 1
      #699 (Ljava/lang/Object;)Ljava/lang/String;
  1: #707 REF_invokeStatic java/lang/invoke/LambdaMetafactory.altMetafactory:(Ljava/lang/invoke/MethodHandles$Lookup;Ljava/lang/String;Ljava/lang/invoke/MethodType;[Ljava/lang/Object;)Ljava/lang/invoke/CallSite;
    Method arguments:
      #695 (Ljava/lang/Object;)Ljava/lang/Object;
      #765 REF_invokeStatic scala/runtime/ScalaRunTime$.$anonfun$stringOf$3:(Lscala/runtime/ScalaRunTime$;ILjava/lang/Object;)Ljava/lang/String;
      #699 (Ljava/lang/Object;)Ljava/lang/String;
      #700 5
      #355 1
      #699 (Ljava/lang/Object;)Ljava/lang/String;
  2: #707 REF_invokeStatic java/lang/invoke/LambdaMetafactory.altMetafactory:(Ljava/lang/invoke/MethodHandles$Lookup;Ljava/lang/String;Ljava/lang/invoke/MethodType;[Ljava/lang/Object;)Ljava/lang/invoke/CallSite;
    Method arguments:
      #695 (Ljava/lang/Object;)Ljava/lang/Object;
      #773 REF_invokeStatic scala/runtime/ScalaRunTime$.$anonfun$stringOf$4:(Lscala/runtime/ScalaRunTime$;ILjava/lang/Object;)Ljava/lang/String;
      #699 (Ljava/lang/Object;)Ljava/lang/String;
      #700 5
      #355 1
      #699 (Ljava/lang/Object;)Ljava/lang/String;
  3: #707 REF_invokeStatic java/lang/invoke/LambdaMetafactory.altMetafactory:(Ljava/lang/invoke/MethodHandles$Lookup;Ljava/lang/String;Ljava/lang/invoke/MethodType;[Ljava/lang/Object;)Ljava/lang/invoke/CallSite;
    Method arguments:
      #695 (Ljava/lang/Object;)Ljava/lang/Object;
      #785 REF_invokeStatic scala/runtime/ScalaRunTime$.$anonfun$stringOf$5:(Lscala/runtime/ScalaRunTime$;ILjava/lang/Object;)Ljava/lang/String;
      #699 (Ljava/lang/Object;)Ljava/lang/String;
      #700 5
      #355 1
      #699 (Ljava/lang/Object;)Ljava/lang/String;
  4: #799 REF_invokeStatic scala/runtime/LambdaDeserialize.bootstrap:(Ljava/lang/invoke/MethodHandles$Lookup;Ljava/lang/String;Ljava/lang/invoke/MethodType;[Ljava/lang/invoke/MethodHandle;)Ljava/lang/invoke/CallSite;
    Method arguments:
      #698 REF_invokeStatic scala/runtime/ScalaRunTime$.$anonfun$stringOf$2:(Lscala/runtime/ScalaRunTime$;ILjava/lang/Object;)Ljava/lang/String;
      #765 REF_invokeStatic scala/runtime/ScalaRunTime$.$anonfun$stringOf$3:(Lscala/runtime/ScalaRunTime$;ILjava/lang/Object;)Ljava/lang/String;
      #773 REF_invokeStatic scala/runtime/ScalaRunTime$.$anonfun$stringOf$4:(Lscala/runtime/ScalaRunTime$;ILjava/lang/Object;)Ljava/lang/String;
      #785 REF_invokeStatic scala/runtime/ScalaRunTime$.$anonfun$stringOf$5:(Lscala/runtime/ScalaRunTime$;ILjava/lang/Object;)Ljava/lang/String;
  ScalaInlineInfo: length = 0x126 (unknown attribute)
   01 01 00 3A 02 66 02 67 01 03 14 01 8E 01 02 6B
   02 6C 01 02 D1 02 6C 01 02 D4 02 6C 01 02 D5 02
   6C 01 00 36 00 35 01 01 7D 01 7E 01 01 5A 01 5B
   01 00 7D 00 7E 01 00 69 00 6A 01 02 6E 01 91 01
   00 8D 00 8E 01 00 FB 00 FC 01 00 F7 00 D9 05 00
   D4 00 D5 01 02 06 01 0A 01 01 20 01 21 01 01 1C
   01 1D 01 01 10 01 11 01 01 18 01 19 01 01 0C 01
   0D 01 01 14 01 15 01 01 24 01 25 01 02 04 02 05
   01 01 28 01 29 01 00 57 00 58 01 01 51 01 52 01
   01 AF 01 B0 01 01 97 01 91 01 00 3B 00 3C 01 00
   4A 00 4B 01 00 43 00 44 01 02 15 00 72 01 02 1E
   00 72 01 02 25 02 26 01 02 21 00 72 01 02 3F 02
   34 01 02 3A 02 34 01 02 57 01 91 01 02 09 01 8E
   01 01 A2 01 91 01 01 8D 01 8E 01 01 8D 01 91 01
   01 2C 01 2D 01 01 09 01 0A 01 01 87 01 88 01 02
   42 00 72 01 01 F7 01 F8 01 01 EB 01 EC 01 01 E5
   01 E6 01 01 D3 01 D4 01 01 DF 01 E0 01 01 CD 01
   CE 01 01 D9 01 DA 01 01 BA 01 BB 01 01 F1 01 F2
   01 01 FD 01 FE 01
  Scala: length = 0x0 (unknown attribute)

