Classfile /Users/mw/Projects/slang-braindump/.jar/jar8/assemble/slang-braindump/assemble/content/scala/runtime/VolatileBooleanRef.class
  Last modified May 29, 2022; size 835 bytes
  SHA-256 checksum 3bf10efb9c8ba29d533bf6d0425a1be9c0d88c39bf247c7fa8a1ccfd81b3e2b1
  Compiled from "VolatileBooleanRef.java"
public final class scala.runtime.VolatileBooleanRef implements java.io.Serializable
  minor version: 0
  major version: 52
  flags: (0x0031) ACC_PUBLIC, ACC_FINAL, ACC_SUPER
  this_class: #4                          // scala/runtime/VolatileBooleanRef
  super_class: #6                         // java/lang/Object
  interfaces: 1, fields: 2, methods: 4, attributes: 1
Constant pool:
   #1 = Methodref          #6.#31         // java/lang/Object."<init>":()V
   #2 = Fieldref           #4.#32         // scala/runtime/VolatileBooleanRef.elem:Z
   #3 = Methodref          #33.#34        // java/lang/String.valueOf:(Z)Ljava/lang/String;
   #4 = Class              #35            // scala/runtime/VolatileBooleanRef
   #5 = Methodref          #4.#36         // scala/runtime/VolatileBooleanRef."<init>":(Z)V
   #6 = Class              #37            // java/lang/Object
   #7 = Class              #38            // java/io/Serializable
   #8 = Utf8               serialVersionUID
   #9 = Utf8               J
  #10 = Utf8               ConstantValue
  #11 = Long               -5730524563015615974l
  #13 = Utf8               elem
  #14 = Utf8               Z
  #15 = Utf8               <init>
  #16 = Utf8               (Z)V
  #17 = Utf8               Code
  #18 = Utf8               LineNumberTable
  #19 = Utf8               LocalVariableTable
  #20 = Utf8               this
  #21 = Utf8               Lscala/runtime/VolatileBooleanRef;
  #22 = Utf8               toString
  #23 = Utf8               ()Ljava/lang/String;
  #24 = Utf8               create
  #25 = Utf8               (Z)Lscala/runtime/VolatileBooleanRef;
  #26 = Utf8               e
  #27 = Utf8               zero
  #28 = Utf8               ()Lscala/runtime/VolatileBooleanRef;
  #29 = Utf8               SourceFile
  #30 = Utf8               VolatileBooleanRef.java
  #31 = NameAndType        #15:#39        // "<init>":()V
  #32 = NameAndType        #13:#14        // elem:Z
  #33 = Class              #40            // java/lang/String
  #34 = NameAndType        #41:#42        // valueOf:(Z)Ljava/lang/String;
  #35 = Utf8               scala/runtime/VolatileBooleanRef
  #36 = NameAndType        #15:#16        // "<init>":(Z)V
  #37 = Utf8               java/lang/Object
  #38 = Utf8               java/io/Serializable
  #39 = Utf8               ()V
  #40 = Utf8               java/lang/String
  #41 = Utf8               valueOf
  #42 = Utf8               (Z)Ljava/lang/String;
{
  private static final long serialVersionUID;
    descriptor: J
    flags: (0x001a) ACC_PRIVATE, ACC_STATIC, ACC_FINAL
    ConstantValue: long -5730524563015615974l

  public volatile boolean elem;
    descriptor: Z
    flags: (0x0041) ACC_PUBLIC, ACC_VOLATILE

  public scala.runtime.VolatileBooleanRef(boolean);
    descriptor: (Z)V
    flags: (0x0001) ACC_PUBLIC
    Code:
      stack=2, locals=2, args_size=2
         0: aload_0
         1: invokespecial #1                  // Method java/lang/Object."<init>":()V
         4: aload_0
         5: iload_1
         6: putfield      #2                  // Field elem:Z
         9: return
      LineNumberTable:
        line 19: 0
      LocalVariableTable:
        Start  Length  Slot  Name   Signature
            0      10     0  this   Lscala/runtime/VolatileBooleanRef;
            0      10     1  elem   Z

  public java.lang.String toString();
    descriptor: ()Ljava/lang/String;
    flags: (0x0001) ACC_PUBLIC
    Code:
      stack=1, locals=1, args_size=1
         0: aload_0
         1: getfield      #2                  // Field elem:Z
         4: invokestatic  #3                  // Method java/lang/String.valueOf:(Z)Ljava/lang/String;
         7: areturn
      LineNumberTable:
        line 20: 0
      LocalVariableTable:
        Start  Length  Slot  Name   Signature
            0       8     0  this   Lscala/runtime/VolatileBooleanRef;

  public static scala.runtime.VolatileBooleanRef create(boolean);
    descriptor: (Z)Lscala/runtime/VolatileBooleanRef;
    flags: (0x0009) ACC_PUBLIC, ACC_STATIC
    Code:
      stack=3, locals=1, args_size=1
         0: new           #4                  // class scala/runtime/VolatileBooleanRef
         3: dup
         4: iload_0
         5: invokespecial #5                  // Method "<init>":(Z)V
         8: areturn
      LineNumberTable:
        line 22: 0
      LocalVariableTable:
        Start  Length  Slot  Name   Signature
            0       9     0     e   Z

  public static scala.runtime.VolatileBooleanRef zero();
    descriptor: ()Lscala/runtime/VolatileBooleanRef;
    flags: (0x0009) ACC_PUBLIC, ACC_STATIC
    Code:
      stack=3, locals=0, args_size=0
         0: new           #4                  // class scala/runtime/VolatileBooleanRef
         3: dup
         4: iconst_0
         5: invokespecial #5                  // Method "<init>":(Z)V
         8: areturn
      LineNumberTable:
        line 23: 0
}
SourceFile: "VolatileBooleanRef.java"
