Classfile /Users/mw/Projects/slang-braindump/.jar/jar8/assemble/slang-braindump/assemble/content/scala/runtime/ZippedIterable3$$anon$1.class
  Last modified May 29, 2022; size 1132 bytes
  SHA-256 checksum 6ad6422258132e9babd0702f252e62baeb1b39c4f5f359833165497973fd7a9a
  Compiled from "Tuple3Zipped.scala"
public final class scala.runtime.ZippedIterable3$$anon$1 extends scala.collection.AbstractIterable<scala.Tuple3<El1, El2, El3>>
  minor version: 0
  major version: 52
  flags: (0x0031) ACC_PUBLIC, ACC_FINAL, ACC_SUPER
  this_class: #2                          // scala/runtime/ZippedIterable3$$anon$1
  super_class: #5                         // scala/collection/AbstractIterable
  interfaces: 0, fields: 1, methods: 3, attributes: 6
Constant pool:
   #1 = Utf8               scala/runtime/ZippedIterable3$$anon$1
   #2 = Class              #1             // scala/runtime/ZippedIterable3$$anon$1
   #3 = Utf8               Lscala/collection/AbstractIterable<Lscala/Tuple3<TEl1;TEl2;TEl3;>;>;
   #4 = Utf8               scala/collection/AbstractIterable
   #5 = Class              #4             // scala/collection/AbstractIterable
   #6 = Utf8               Tuple3Zipped.scala
   #7 = Utf8               scala/runtime/ZippedIterable3$
   #8 = Class              #7             // scala/runtime/ZippedIterable3$
   #9 = Utf8               zippedIterable3ToIterable
  #10 = Utf8               (Lscala/runtime/ZippedIterable3;)Lscala/collection/Iterable;
  #11 = NameAndType        #9:#10         // zippedIterable3ToIterable:(Lscala/runtime/ZippedIterable3;)Lscala/collection/Iterable;
  #12 = Utf8               zz$1
  #13 = Utf8               Lscala/runtime/ZippedIterable3;
  #14 = Utf8               iterator
  #15 = Utf8               ()Lscala/collection/Iterator;
  #16 = Utf8               ()Lscala/collection/Iterator<Lscala/Tuple3<TEl1;TEl2;TEl3;>;>;
  #17 = NameAndType        #12:#13        // zz$1:Lscala/runtime/ZippedIterable3;
  #18 = Fieldref           #2.#17         // scala/runtime/ZippedIterable3$$anon$1.zz$1:Lscala/runtime/ZippedIterable3;
  #19 = Utf8               scala/runtime/ZippedIterable3
  #20 = Class              #19            // scala/runtime/ZippedIterable3
  #21 = NameAndType        #14:#15        // iterator:()Lscala/collection/Iterator;
  #22 = InterfaceMethodref #20.#21        // scala/runtime/ZippedIterable3.iterator:()Lscala/collection/Iterator;
  #23 = Utf8               this
  #24 = Utf8               Lscala/runtime/ZippedIterable3$$anon$1;
  #25 = Utf8               isEmpty
  #26 = Utf8               ()Z
  #27 = NameAndType        #25:#26        // isEmpty:()Z
  #28 = InterfaceMethodref #20.#27        // scala/runtime/ZippedIterable3.isEmpty:()Z
  #29 = Utf8               <init>
  #30 = Utf8               (Lscala/runtime/ZippedIterable3;)V
  #31 = Utf8               ()V
  #32 = NameAndType        #29:#31        // "<init>":()V
  #33 = Methodref          #5.#32         // scala/collection/AbstractIterable."<init>":()V
  #34 = Utf8               Code
  #35 = Utf8               LineNumberTable
  #36 = Utf8               LocalVariableTable
  #37 = Utf8               Signature
  #38 = Utf8               MethodParameters
  #39 = Utf8               InnerClasses
  #40 = Utf8               EnclosingMethod
  #41 = Utf8               SourceFile
  #42 = Utf8               ScalaInlineInfo
  #43 = Utf8               Scala
{
  private final scala.runtime.ZippedIterable3 zz$1;
    descriptor: Lscala/runtime/ZippedIterable3;
    flags: (0x0012) ACC_PRIVATE, ACC_FINAL

  public scala.collection.Iterator<scala.Tuple3<El1, El2, El3>> iterator();
    descriptor: ()Lscala/collection/Iterator;
    flags: (0x0001) ACC_PUBLIC
    Code:
      stack=1, locals=1, args_size=1
         0: aload_0
         1: getfield      #18                 // Field zz$1:Lscala/runtime/ZippedIterable3;
         4: invokeinterface #22,  1           // InterfaceMethod scala/runtime/ZippedIterable3.iterator:()Lscala/collection/Iterator;
         9: areturn
      LineNumberTable:
        line 35: 0
      LocalVariableTable:
        Start  Length  Slot  Name   Signature
            0      10     0  this   Lscala/runtime/ZippedIterable3$$anon$1;
    Signature: #16                          // ()Lscala/collection/Iterator<Lscala/Tuple3<TEl1;TEl2;TEl3;>;>;

  public boolean isEmpty();
    descriptor: ()Z
    flags: (0x0001) ACC_PUBLIC
    Code:
      stack=1, locals=1, args_size=1
         0: aload_0
         1: getfield      #18                 // Field zz$1:Lscala/runtime/ZippedIterable3;
         4: invokeinterface #28,  1           // InterfaceMethod scala/runtime/ZippedIterable3.isEmpty:()Z
         9: ireturn
      LineNumberTable:
        line 36: 0
      LocalVariableTable:
        Start  Length  Slot  Name   Signature
            0      10     0  this   Lscala/runtime/ZippedIterable3$$anon$1;

  public scala.runtime.ZippedIterable3$$anon$1(scala.runtime.ZippedIterable3);
    descriptor: (Lscala/runtime/ZippedIterable3;)V
    flags: (0x0001) ACC_PUBLIC
    Code:
      stack=2, locals=2, args_size=2
         0: aload_0
         1: aload_1
         2: putfield      #18                 // Field zz$1:Lscala/runtime/ZippedIterable3;
         5: aload_0
         6: invokespecial #33                 // Method scala/collection/AbstractIterable."<init>":()V
         9: return
      LineNumberTable:
        line 33: 0
        line 34: 5
      LocalVariableTable:
        Start  Length  Slot  Name   Signature
            0      10     0  this   Lscala/runtime/ZippedIterable3$$anon$1;
            0      10     1  zz$1   Lscala/runtime/ZippedIterable3;
    MethodParameters:
      Name                           Flags
      zz$1                           final
}
InnerClasses:
  public final #2;                        // class scala/runtime/ZippedIterable3$$anon$1
EnclosingMethod: #8.#11                 // scala.runtime.ZippedIterable3$.zippedIterable3ToIterable
Signature: #3                           // Lscala/collection/AbstractIterable<Lscala/Tuple3<TEl1;TEl2;TEl3;>;>;
SourceFile: "Tuple3Zipped.scala"
  ScalaInlineInfo: length = 0x13 (unknown attribute)
   01 01 00 03 00 1D 00 1E 01 00 19 00 1A 01 00 0E
   00 0F 01
  Scala: length = 0x0 (unknown attribute)

