Classfile /Users/mw/Projects/slang-braindump/.jar/jar8/assemble/slang-braindump/assemble/content/coursier/parse/CachePolicyParser$.class
  Last modified May 29, 2022; size 9591 bytes
  SHA-256 checksum 9b316bf291a430290483b6c31ce9c75d50781256803aef1246a4ce15129fb936
  Compiled from "CachePolicyParser.scala"
public final class coursier.parse.CachePolicyParser$
  minor version: 0
  major version: 52
  flags: (0x0031) ACC_PUBLIC, ACC_FINAL, ACC_SUPER
  this_class: #2                          // coursier/parse/CachePolicyParser$
  super_class: #4                         // java/lang/Object
  interfaces: 0, fields: 1, methods: 13, attributes: 5
Constant pool:
    #1 = Utf8               coursier/parse/CachePolicyParser$
    #2 = Class              #1            // coursier/parse/CachePolicyParser$
    #3 = Utf8               java/lang/Object
    #4 = Class              #3            // java/lang/Object
    #5 = Utf8               CachePolicyParser.scala
    #6 = Utf8               coursier/cache/CachePolicy$FetchMissing$
    #7 = Class              #6            // coursier/cache/CachePolicy$FetchMissing$
    #8 = Utf8               coursier/cache/CachePolicy
    #9 = Class              #8            // coursier/cache/CachePolicy
   #10 = Utf8
   #11 = Utf8               coursier/cache/CachePolicy$ForceDownload$
   #12 = Class              #11           // coursier/cache/CachePolicy$ForceDownload$
   #13 = Utf8               coursier/cache/CachePolicy$LocalOnly$
   #14 = Class              #13           // coursier/cache/CachePolicy$LocalOnly$
   #15 = Utf8               coursier/cache/CachePolicy$LocalOnlyIfValid$
   #16 = Class              #15           // coursier/cache/CachePolicy$LocalOnlyIfValid$
   #17 = Utf8               coursier/cache/CachePolicy$LocalUpdate$
   #18 = Class              #17           // coursier/cache/CachePolicy$LocalUpdate$
   #19 = Utf8               coursier/cache/CachePolicy$LocalUpdateChanging$
   #20 = Class              #19           // coursier/cache/CachePolicy$LocalUpdateChanging$
   #21 = Utf8               coursier/cache/CachePolicy$NoChanging
   #22 = Class              #21           // coursier/cache/CachePolicy$NoChanging
   #23 = Utf8               NoChanging
   #24 = Utf8               coursier/cache/CachePolicy$NoChanging$
   #25 = Class              #24           // coursier/cache/CachePolicy$NoChanging$
   #26 = Utf8               coursier/cache/CachePolicy$NoChanging$FetchMissing$
   #27 = Class              #26           // coursier/cache/CachePolicy$NoChanging$FetchMissing$
   #28 = Utf8               coursier/cache/CachePolicy$NoChanging$ForceDownload$
   #29 = Class              #28           // coursier/cache/CachePolicy$NoChanging$ForceDownload$
   #30 = Utf8               coursier/cache/CachePolicy$NoChanging$LocalOnly$
   #31 = Class              #30           // coursier/cache/CachePolicy$NoChanging$LocalOnly$
   #32 = Utf8               coursier/cache/CachePolicy$NoChanging$LocalUpdate$
   #33 = Class              #32           // coursier/cache/CachePolicy$NoChanging$LocalUpdate$
   #34 = Utf8               coursier/cache/CachePolicy$Update$
   #35 = Class              #34           // coursier/cache/CachePolicy$Update$
   #36 = Utf8               coursier/cache/CachePolicy$UpdateChanging$
   #37 = Class              #36           // coursier/cache/CachePolicy$UpdateChanging$
   #38 = Utf8               coursier/util/Traverse$TraverseOps
   #39 = Class              #38           // coursier/util/Traverse$TraverseOps
   #40 = Utf8               coursier/util/Traverse
   #41 = Class              #40           // coursier/util/Traverse
   #42 = Utf8               TraverseOps
   #43 = Utf8               coursier/util/ValidationNel$SuccessBuilder
   #44 = Class              #43           // coursier/util/ValidationNel$SuccessBuilder
   #45 = Utf8               coursier/util/ValidationNel
   #46 = Class              #45           // coursier/util/ValidationNel
   #47 = Utf8               SuccessBuilder
   #48 = Utf8               java/lang/invoke/MethodHandles$Lookup
   #49 = Class              #48           // java/lang/invoke/MethodHandles$Lookup
   #50 = Utf8               java/lang/invoke/MethodHandles
   #51 = Class              #50           // java/lang/invoke/MethodHandles
   #52 = Utf8               Lookup
   #53 = Utf8               scala/collection/mutable/ArraySeq$ofRef
   #54 = Class              #53           // scala/collection/mutable/ArraySeq$ofRef
   #55 = Utf8               scala/collection/mutable/ArraySeq
   #56 = Class              #55           // scala/collection/mutable/ArraySeq
   #57 = Utf8               ofRef
   #58 = Utf8               MODULE$
   #59 = Utf8               Lcoursier/parse/CachePolicyParser$;
   #60 = Utf8               <clinit>
   #61 = Utf8               ()V
   #62 = Utf8               <init>
   #63 = NameAndType        #62:#61       // "<init>":()V
   #64 = Methodref          #2.#63        // coursier/parse/CachePolicyParser$."<init>":()V
   #65 = NameAndType        #58:#59       // MODULE$:Lcoursier/parse/CachePolicyParser$;
   #66 = Fieldref           #2.#65        // coursier/parse/CachePolicyParser$.MODULE$:Lcoursier/parse/CachePolicyParser$;
   #67 = Utf8               cachePolicy
   #68 = Utf8               (Ljava/lang/String;)Lscala/util/Either;
   #69 = Utf8               (Ljava/lang/String;)Lscala/util/Either<Ljava/lang/String;Lcoursier/cache/CachePolicy;>;
   #70 = Utf8               input
   #71 = Utf8               java/lang/String
   #72 = Class              #71           // java/lang/String
   #73 = Utf8               hashCode
   #74 = Utf8               ()I
   #75 = NameAndType        #73:#74       // hashCode:()I
   #76 = Methodref          #72.#75       // java/lang/String.hashCode:()I
   #77 = Utf8               update-local
   #78 = String             #77           // update-local
   #79 = Utf8               equals
   #80 = Utf8               (Ljava/lang/Object;)Z
   #81 = NameAndType        #79:#80       // equals:(Ljava/lang/Object;)Z
   #82 = Methodref          #72.#81       // java/lang/String.equals:(Ljava/lang/Object;)Z
   #83 = Utf8               offline
   #84 = String             #83           // offline
   #85 = Utf8               update
   #86 = String             #85           // update
   #87 = Utf8               update-local-changing
   #88 = String             #87           // update-local-changing
   #89 = Utf8               force
   #90 = String             #89           // force
   #91 = Utf8               local
   #92 = String             #91           // local
   #93 = Utf8               update-local-no-changing
   #94 = String             #93           // update-local-no-changing
   #95 = Utf8               force-no-changing
   #96 = String             #95           // force-no-changing
   #97 = Utf8               update-changing
   #98 = String             #97           // update-changing
   #99 = Utf8               missing
  #100 = String             #99           // missing
  #101 = Utf8               missing-no-changing
  #102 = String             #101          // missing-no-changing
  #103 = Utf8               offline-no-changing
  #104 = String             #103          // offline-no-changing
  #105 = Utf8               scala/package$
  #106 = Class              #105          // scala/package$
  #107 = Utf8               Lscala/package$;
  #108 = NameAndType        #58:#107      // MODULE$:Lscala/package$;
  #109 = Fieldref           #106.#108     // scala/package$.MODULE$:Lscala/package$;
  #110 = Utf8               Right
  #111 = Utf8               ()Lscala/util/Right$;
  #112 = NameAndType        #110:#111     // Right:()Lscala/util/Right$;
  #113 = Methodref          #106.#112     // scala/package$.Right:()Lscala/util/Right$;
  #114 = Utf8               Lcoursier/cache/CachePolicy$LocalOnly$;
  #115 = NameAndType        #58:#114      // MODULE$:Lcoursier/cache/CachePolicy$LocalOnly$;
  #116 = Fieldref           #14.#115      // coursier/cache/CachePolicy$LocalOnly$.MODULE$:Lcoursier/cache/CachePolicy$LocalOnly$;
  #117 = Utf8               scala/util/Right$
  #118 = Class              #117          // scala/util/Right$
  #119 = Utf8               apply
  #120 = Utf8               (Ljava/lang/Object;)Lscala/util/Right;
  #121 = NameAndType        #119:#120     // apply:(Ljava/lang/Object;)Lscala/util/Right;
  #122 = Methodref          #118.#121     // scala/util/Right$.apply:(Ljava/lang/Object;)Lscala/util/Right;
  #123 = Utf8               Lcoursier/cache/CachePolicy$NoChanging$LocalOnly$;
  #124 = NameAndType        #58:#123      // MODULE$:Lcoursier/cache/CachePolicy$NoChanging$LocalOnly$;
  #125 = Fieldref           #31.#124      // coursier/cache/CachePolicy$NoChanging$LocalOnly$.MODULE$:Lcoursier/cache/CachePolicy$NoChanging$LocalOnly$;
  #126 = Utf8               Lcoursier/cache/CachePolicy$LocalOnlyIfValid$;
  #127 = NameAndType        #58:#126      // MODULE$:Lcoursier/cache/CachePolicy$LocalOnlyIfValid$;
  #128 = Fieldref           #16.#127      // coursier/cache/CachePolicy$LocalOnlyIfValid$.MODULE$:Lcoursier/cache/CachePolicy$LocalOnlyIfValid$;
  #129 = Utf8               Lcoursier/cache/CachePolicy$LocalUpdateChanging$;
  #130 = NameAndType        #58:#129      // MODULE$:Lcoursier/cache/CachePolicy$LocalUpdateChanging$;
  #131 = Fieldref           #20.#130      // coursier/cache/CachePolicy$LocalUpdateChanging$.MODULE$:Lcoursier/cache/CachePolicy$LocalUpdateChanging$;
  #132 = Utf8               Lcoursier/cache/CachePolicy$LocalUpdate$;
  #133 = NameAndType        #58:#132      // MODULE$:Lcoursier/cache/CachePolicy$LocalUpdate$;
  #134 = Fieldref           #18.#133      // coursier/cache/CachePolicy$LocalUpdate$.MODULE$:Lcoursier/cache/CachePolicy$LocalUpdate$;
  #135 = Utf8               Lcoursier/cache/CachePolicy$NoChanging$LocalUpdate$;
  #136 = NameAndType        #58:#135      // MODULE$:Lcoursier/cache/CachePolicy$NoChanging$LocalUpdate$;
  #137 = Fieldref           #33.#136      // coursier/cache/CachePolicy$NoChanging$LocalUpdate$.MODULE$:Lcoursier/cache/CachePolicy$NoChanging$LocalUpdate$;
  #138 = Utf8               Lcoursier/cache/CachePolicy$UpdateChanging$;
  #139 = NameAndType        #58:#138      // MODULE$:Lcoursier/cache/CachePolicy$UpdateChanging$;
  #140 = Fieldref           #37.#139      // coursier/cache/CachePolicy$UpdateChanging$.MODULE$:Lcoursier/cache/CachePolicy$UpdateChanging$;
  #141 = Utf8               Lcoursier/cache/CachePolicy$Update$;
  #142 = NameAndType        #58:#141      // MODULE$:Lcoursier/cache/CachePolicy$Update$;
  #143 = Fieldref           #35.#142      // coursier/cache/CachePolicy$Update$.MODULE$:Lcoursier/cache/CachePolicy$Update$;
  #144 = Utf8               Lcoursier/cache/CachePolicy$FetchMissing$;
  #145 = NameAndType        #58:#144      // MODULE$:Lcoursier/cache/CachePolicy$FetchMissing$;
  #146 = Fieldref           #7.#145       // coursier/cache/CachePolicy$FetchMissing$.MODULE$:Lcoursier/cache/CachePolicy$FetchMissing$;
  #147 = Utf8               Lcoursier/cache/CachePolicy$NoChanging$FetchMissing$;
  #148 = NameAndType        #58:#147      // MODULE$:Lcoursier/cache/CachePolicy$NoChanging$FetchMissing$;
  #149 = Fieldref           #27.#148      // coursier/cache/CachePolicy$NoChanging$FetchMissing$.MODULE$:Lcoursier/cache/CachePolicy$NoChanging$FetchMissing$;
  #150 = Utf8               Lcoursier/cache/CachePolicy$ForceDownload$;
  #151 = NameAndType        #58:#150      // MODULE$:Lcoursier/cache/CachePolicy$ForceDownload$;
  #152 = Fieldref           #12.#151      // coursier/cache/CachePolicy$ForceDownload$.MODULE$:Lcoursier/cache/CachePolicy$ForceDownload$;
  #153 = Utf8               Lcoursier/cache/CachePolicy$NoChanging$ForceDownload$;
  #154 = NameAndType        #58:#153      // MODULE$:Lcoursier/cache/CachePolicy$NoChanging$ForceDownload$;
  #155 = Fieldref           #29.#154      // coursier/cache/CachePolicy$NoChanging$ForceDownload$.MODULE$:Lcoursier/cache/CachePolicy$NoChanging$ForceDownload$;
  #156 = Utf8               Left
  #157 = Utf8               ()Lscala/util/Left$;
  #158 = NameAndType        #156:#157     // Left:()Lscala/util/Left$;
  #159 = Methodref          #106.#158     // scala/package$.Left:()Lscala/util/Left$;
  #160 = Utf8               java/lang/StringBuilder
  #161 = Class              #160          // java/lang/StringBuilder
  #162 = Integer            27
  #163 = Utf8               (I)V
  #164 = NameAndType        #62:#163      // "<init>":(I)V
  #165 = Methodref          #161.#164     // java/lang/StringBuilder."<init>":(I)V
  #166 = Utf8               Unrecognized cache policy:
  #167 = String             #166          // Unrecognized cache policy:
  #168 = Utf8               append
  #169 = Utf8               (Ljava/lang/String;)Ljava/lang/StringBuilder;
  #170 = NameAndType        #168:#169     // append:(Ljava/lang/String;)Ljava/lang/StringBuilder;
  #171 = Methodref          #161.#170     // java/lang/StringBuilder.append:(Ljava/lang/String;)Ljava/lang/StringBuilder;
  #172 = Utf8               toString
  #173 = Utf8               ()Ljava/lang/String;
  #174 = NameAndType        #172:#173     // toString:()Ljava/lang/String;
  #175 = Methodref          #161.#174     // java/lang/StringBuilder.toString:()Ljava/lang/String;
  #176 = Utf8               scala/util/Left$
  #177 = Class              #176          // scala/util/Left$
  #178 = Utf8               (Ljava/lang/Object;)Lscala/util/Left;
  #179 = NameAndType        #119:#178     // apply:(Ljava/lang/Object;)Lscala/util/Left;
  #180 = Methodref          #177.#179     // scala/util/Left$.apply:(Ljava/lang/Object;)Lscala/util/Left;
  #181 = Utf8               scala/util/Either
  #182 = Class              #181          // scala/util/Either
  #183 = Utf8               this
  #184 = Utf8               Ljava/lang/String;
  #185 = Utf8               cachePolicies0
  #186 = Utf8               (Ljava/lang/String;Lscala/Option;)Lcoursier/util/ValidationNel;
  #187 = Utf8               (Ljava/lang/String;Lscala/Option<Lscala/collection/immutable/Seq<Lcoursier/cache/CachePolicy;>;>;)Lcoursier/util/ValidationNel<Ljava/lang/String;Lscala/collection/immutable/Seq<Lcoursier/cache/CachePolicy;>;>;
  #188 = Utf8               default
  #189 = Utf8               coursier/util/Traverse$
  #190 = Class              #189          // coursier/util/Traverse$
  #191 = Utf8               Lcoursier/util/Traverse$;
  #192 = NameAndType        #58:#191      // MODULE$:Lcoursier/util/Traverse$;
  #193 = Fieldref           #190.#192     // coursier/util/Traverse$.MODULE$:Lcoursier/util/Traverse$;
  #194 = Utf8               scala/Predef$
  #195 = Class              #194          // scala/Predef$
  #196 = Utf8               Lscala/Predef$;
  #197 = NameAndType        #58:#196      // MODULE$:Lscala/Predef$;
  #198 = Fieldref           #195.#197     // scala/Predef$.MODULE$:Lscala/Predef$;
  #199 = Utf8               scala/collection/StringOps$
  #200 = Class              #199          // scala/collection/StringOps$
  #201 = Utf8               Lscala/collection/StringOps$;
  #202 = NameAndType        #58:#201      // MODULE$:Lscala/collection/StringOps$;
  #203 = Fieldref           #200.#202     // scala/collection/StringOps$.MODULE$:Lscala/collection/StringOps$;
  #204 = Utf8               augmentString
  #205 = Utf8               (Ljava/lang/String;)Ljava/lang/String;
  #206 = NameAndType        #204:#205     // augmentString:(Ljava/lang/String;)Ljava/lang/String;
  #207 = Methodref          #195.#206     // scala/Predef$.augmentString:(Ljava/lang/String;)Ljava/lang/String;
  #208 = Utf8               split$extension
  #209 = Utf8               (Ljava/lang/String;C)[Ljava/lang/String;
  #210 = NameAndType        #208:#209     // split$extension:(Ljava/lang/String;C)[Ljava/lang/String;
  #211 = Methodref          #200.#210     // scala/collection/StringOps$.split$extension:(Ljava/lang/String;C)[Ljava/lang/String;
  #212 = Utf8               [Ljava/lang/Object;
  #213 = Class              #212          // "[Ljava/lang/Object;"
  #214 = Utf8               wrapRefArray
  #215 = Utf8               ([Ljava/lang/Object;)Lscala/collection/mutable/ArraySeq$ofRef;
  #216 = NameAndType        #214:#215     // wrapRefArray:([Ljava/lang/Object;)Lscala/collection/mutable/ArraySeq$ofRef;
  #217 = Methodref          #195.#216     // scala/Predef$.wrapRefArray:([Ljava/lang/Object;)Lscala/collection/mutable/ArraySeq$ofRef;
  #218 = Utf8               toVector
  #219 = Utf8               ()Lscala/collection/immutable/Vector;
  #220 = NameAndType        #218:#219     // toVector:()Lscala/collection/immutable/Vector;
  #221 = Methodref          #54.#220      // scala/collection/mutable/ArraySeq$ofRef.toVector:()Lscala/collection/immutable/Vector;
  #222 = Utf8               (Lscala/collection/immutable/Seq;)Lcoursier/util/Traverse$TraverseOps;
  #223 = NameAndType        #42:#222      // TraverseOps:(Lscala/collection/immutable/Seq;)Lcoursier/util/Traverse$TraverseOps;
  #224 = Methodref          #190.#223     // coursier/util/Traverse$.TraverseOps:(Lscala/collection/immutable/Seq;)Lcoursier/util/Traverse$TraverseOps;
  #225 = Utf8               (Ljava/lang/Object;)Ljava/lang/Object;
  #226 = MethodType         #225          //  (Ljava/lang/Object;)Ljava/lang/Object;
  #227 = Utf8               $anonfun$cachePolicies0$1
  #228 = Utf8               (Lscala/Option;Ljava/lang/String;)Lcoursier/util/ValidationNel;
  #229 = NameAndType        #227:#228     // $anonfun$cachePolicies0$1:(Lscala/Option;Ljava/lang/String;)Lcoursier/util/ValidationNel;
  #230 = Methodref          #2.#229       // coursier/parse/CachePolicyParser$.$anonfun$cachePolicies0$1:(Lscala/Option;Ljava/lang/String;)Lcoursier/util/ValidationNel;
  #231 = MethodHandle       6:#230        // REF_invokeStatic coursier/parse/CachePolicyParser$.$anonfun$cachePolicies0$1:(Lscala/Option;Ljava/lang/String;)Lcoursier/util/ValidationNel;
  #232 = Utf8               (Ljava/lang/String;)Lcoursier/util/ValidationNel;
  #233 = MethodType         #232          //  (Ljava/lang/String;)Lcoursier/util/ValidationNel;
  #234 = Integer            5
  #235 = Integer            1
  #236 = Utf8               java/lang/invoke/LambdaMetafactory
  #237 = Class              #236          // java/lang/invoke/LambdaMetafactory
  #238 = Utf8               altMetafactory
  #239 = Utf8               (Ljava/lang/invoke/MethodHandles$Lookup;Ljava/lang/String;Ljava/lang/invoke/MethodType;[Ljava/lang/Object;)Ljava/lang/invoke/CallSite;
  #240 = NameAndType        #238:#239     // altMetafactory:(Ljava/lang/invoke/MethodHandles$Lookup;Ljava/lang/String;Ljava/lang/invoke/MethodType;[Ljava/lang/Object;)Ljava/lang/invoke/CallSite;
  #241 = Methodref          #237.#240     // java/lang/invoke/LambdaMetafactory.altMetafactory:(Ljava/lang/invoke/MethodHandles$Lookup;Ljava/lang/String;Ljava/lang/invoke/MethodType;[Ljava/lang/Object;)Ljava/lang/invoke/CallSite;
  #242 = MethodHandle       6:#241        // REF_invokeStatic java/lang/invoke/LambdaMetafactory.altMetafactory:(Ljava/lang/invoke/MethodHandles$Lookup;Ljava/lang/String;Ljava/lang/invoke/MethodType;[Ljava/lang/Object;)Ljava/lang/invoke/CallSite;
  #243 = Utf8               (Lscala/Option;)Lscala/Function1;
  #244 = NameAndType        #119:#243     // apply:(Lscala/Option;)Lscala/Function1;
  #245 = InvokeDynamic      #0:#244       // #0:apply:(Lscala/Option;)Lscala/Function1;
  #246 = Utf8               validationNelTraverse
  #247 = Utf8               (Lscala/Function1;)Lcoursier/util/ValidationNel;
  #248 = NameAndType        #246:#247     // validationNelTraverse:(Lscala/Function1;)Lcoursier/util/ValidationNel;
  #249 = Methodref          #39.#248      // coursier/util/Traverse$TraverseOps.validationNelTraverse:(Lscala/Function1;)Lcoursier/util/ValidationNel;
  #250 = Utf8               $anonfun$cachePolicies0$6
  #251 = Utf8               (Lscala/collection/immutable/Seq;)Lscala/collection/immutable/Seq;
  #252 = NameAndType        #250:#251     // $anonfun$cachePolicies0$6:(Lscala/collection/immutable/Seq;)Lscala/collection/immutable/Seq;
  #253 = Methodref          #2.#252       // coursier/parse/CachePolicyParser$.$anonfun$cachePolicies0$6:(Lscala/collection/immutable/Seq;)Lscala/collection/immutable/Seq;
  #254 = MethodHandle       6:#253        // REF_invokeStatic coursier/parse/CachePolicyParser$.$anonfun$cachePolicies0$6:(Lscala/collection/immutable/Seq;)Lscala/collection/immutable/Seq;
  #255 = MethodType         #251          //  (Lscala/collection/immutable/Seq;)Lscala/collection/immutable/Seq;
  #256 = Utf8               ()Lscala/Function1;
  #257 = NameAndType        #119:#256     // apply:()Lscala/Function1;
  #258 = InvokeDynamic      #1:#257       // #1:apply:()Lscala/Function1;
  #259 = Utf8               map
  #260 = NameAndType        #259:#247     // map:(Lscala/Function1;)Lcoursier/util/ValidationNel;
  #261 = Methodref          #46.#260      // coursier/util/ValidationNel.map:(Lscala/Function1;)Lcoursier/util/ValidationNel;
  #262 = Utf8               Lscala/Option;
  #263 = Utf8               cachePolicies
  #264 = Utf8               (Ljava/lang/String;)Lcoursier/util/ValidationNel<Ljava/lang/String;Lscala/collection/immutable/Seq<Lcoursier/cache/CachePolicy;>;>;
  #265 = Utf8               scala/None$
  #266 = Class              #265          // scala/None$
  #267 = Utf8               Lscala/None$;
  #268 = NameAndType        #58:#267      // MODULE$:Lscala/None$;
  #269 = Fieldref           #266.#268     // scala/None$.MODULE$:Lscala/None$;
  #270 = NameAndType        #185:#186     // cachePolicies0:(Ljava/lang/String;Lscala/Option;)Lcoursier/util/ValidationNel;
  #271 = Methodref          #2.#270       // coursier/parse/CachePolicyParser$.cachePolicies0:(Ljava/lang/String;Lscala/Option;)Lcoursier/util/ValidationNel;
  #272 = Utf8               (Ljava/lang/String;Lscala/collection/immutable/Seq;)Lcoursier/util/ValidationNel;
  #273 = Utf8               (Ljava/lang/String;Lscala/collection/immutable/Seq<Lcoursier/cache/CachePolicy;>;)Lcoursier/util/ValidationNel<Ljava/lang/String;Lscala/collection/immutable/Seq<Lcoursier/cache/CachePolicy;>;>;
  #274 = Utf8               scala/Some
  #275 = Class              #274          // scala/Some
  #276 = Utf8               (Ljava/lang/Object;)V
  #277 = NameAndType        #62:#276      // "<init>":(Ljava/lang/Object;)V
  #278 = Methodref          #275.#277     // scala/Some."<init>":(Ljava/lang/Object;)V
  #279 = Utf8               Lscala/collection/immutable/Seq;
  #280 = Utf8               $anonfun$cachePolicies0$2
  #281 = Utf8               ()Lscala/collection/immutable/Nil$;
  #282 = Utf8               scala/collection/immutable/Nil$
  #283 = Class              #282          // scala/collection/immutable/Nil$
  #284 = Utf8               Lscala/collection/immutable/Nil$;
  #285 = NameAndType        #58:#284      // MODULE$:Lscala/collection/immutable/Nil$;
  #286 = Fieldref           #283.#285     // scala/collection/immutable/Nil$.MODULE$:Lscala/collection/immutable/Nil$;
  #287 = Utf8               $anonfun$cachePolicies0$3
  #288 = Utf8               $anonfun$cachePolicies0$4
  #289 = Utf8               (Lcoursier/cache/CachePolicy;)Lcoursier/cache/CachePolicy$NoChanging;
  #290 = Utf8               x$1
  #291 = Utf8               rejectChanging
  #292 = Utf8               ()Lcoursier/cache/CachePolicy$NoChanging;
  #293 = NameAndType        #291:#292     // rejectChanging:()Lcoursier/cache/CachePolicy$NoChanging;
  #294 = Methodref          #9.#293       // coursier/cache/CachePolicy.rejectChanging:()Lcoursier/cache/CachePolicy$NoChanging;
  #295 = Utf8               Lcoursier/cache/CachePolicy;
  #296 = Utf8               $anonfun$cachePolicies0$5
  #297 = Utf8               (Lcoursier/cache/CachePolicy;)Lscala/collection/immutable/Seq;
  #298 = Utf8               x$2
  #299 = Utf8               scala/collection/immutable/$colon$colon
  #300 = Class              #299          // scala/collection/immutable/$colon$colon
  #301 = Utf8               (Ljava/lang/Object;Lscala/collection/immutable/List;)V
  #302 = NameAndType        #62:#301      // "<init>":(Ljava/lang/Object;Lscala/collection/immutable/List;)V
  #303 = Methodref          #300.#302     // scala/collection/immutable/$colon$colon."<init>":(Ljava/lang/Object;Lscala/collection/immutable/List;)V
  #304 = Utf8               scala/collection/immutable/Seq
  #305 = Class              #304          // scala/collection/immutable/Seq
  #306 = Utf8               default$1
  #307 = Utf8               x0$1
  #308 = Utf8               pure
  #309 = String             #308          // pure
  #310 = Utf8               no-changing
  #311 = String             #310          // no-changing
  #312 = String             #188          // default
  #313 = Utf8               scala/Option
  #314 = Class              #313          // scala/Option
  #315 = Utf8               nonEmpty
  #316 = Utf8               ()Z
  #317 = NameAndType        #315:#316     // nonEmpty:()Z
  #318 = Methodref          #314.#317     // scala/Option.nonEmpty:()Z
  #319 = Utf8               coursier/util/ValidationNel$
  #320 = Class              #319          // coursier/util/ValidationNel$
  #321 = Utf8               Lcoursier/util/ValidationNel$;
  #322 = NameAndType        #58:#321      // MODULE$:Lcoursier/util/ValidationNel$;
  #323 = Fieldref           #320.#322     // coursier/util/ValidationNel$.MODULE$:Lcoursier/util/ValidationNel$;
  #324 = Utf8               success
  #325 = Utf8               ()Lcoursier/util/ValidationNel$SuccessBuilder;
  #326 = NameAndType        #324:#325     // success:()Lcoursier/util/ValidationNel$SuccessBuilder;
  #327 = Methodref          #320.#326     // coursier/util/ValidationNel$.success:()Lcoursier/util/ValidationNel$SuccessBuilder;
  #328 = Utf8               ()Ljava/lang/Object;
  #329 = MethodType         #328          //  ()Ljava/lang/Object;
  #330 = NameAndType        #280:#281     // $anonfun$cachePolicies0$2:()Lscala/collection/immutable/Nil$;
  #331 = Methodref          #2.#330       // coursier/parse/CachePolicyParser$.$anonfun$cachePolicies0$2:()Lscala/collection/immutable/Nil$;
  #332 = MethodHandle       6:#331        // REF_invokeStatic coursier/parse/CachePolicyParser$.$anonfun$cachePolicies0$2:()Lscala/collection/immutable/Nil$;
  #333 = MethodType         #281          //  ()Lscala/collection/immutable/Nil$;
  #334 = Utf8               ()Lscala/Function0;
  #335 = NameAndType        #119:#334     // apply:()Lscala/Function0;
  #336 = InvokeDynamic      #2:#335       // #2:apply:()Lscala/Function0;
  #337 = Utf8               getOrElse
  #338 = Utf8               (Lscala/Function0;)Ljava/lang/Object;
  #339 = NameAndType        #337:#338     // getOrElse:(Lscala/Function0;)Ljava/lang/Object;
  #340 = Methodref          #314.#339     // scala/Option.getOrElse:(Lscala/Function0;)Ljava/lang/Object;
  #341 = Utf8               (Ljava/lang/Object;)Lcoursier/util/ValidationNel;
  #342 = NameAndType        #119:#341     // apply:(Ljava/lang/Object;)Lcoursier/util/ValidationNel;
  #343 = Methodref          #44.#342      // coursier/util/ValidationNel$SuccessBuilder.apply:(Ljava/lang/Object;)Lcoursier/util/ValidationNel;
  #344 = NameAndType        #287:#281     // $anonfun$cachePolicies0$3:()Lscala/collection/immutable/Nil$;
  #345 = Methodref          #2.#344       // coursier/parse/CachePolicyParser$.$anonfun$cachePolicies0$3:()Lscala/collection/immutable/Nil$;
  #346 = MethodHandle       6:#345        // REF_invokeStatic coursier/parse/CachePolicyParser$.$anonfun$cachePolicies0$3:()Lscala/collection/immutable/Nil$;
  #347 = InvokeDynamic      #3:#335       // #3:apply:()Lscala/Function0;
  #348 = Utf8               scala/collection/IterableOps
  #349 = Class              #348          // scala/collection/IterableOps
  #350 = NameAndType        #288:#289     // $anonfun$cachePolicies0$4:(Lcoursier/cache/CachePolicy;)Lcoursier/cache/CachePolicy$NoChanging;
  #351 = Methodref          #2.#350       // coursier/parse/CachePolicyParser$.$anonfun$cachePolicies0$4:(Lcoursier/cache/CachePolicy;)Lcoursier/cache/CachePolicy$NoChanging;
  #352 = MethodHandle       6:#351        // REF_invokeStatic coursier/parse/CachePolicyParser$.$anonfun$cachePolicies0$4:(Lcoursier/cache/CachePolicy;)Lcoursier/cache/CachePolicy$NoChanging;
  #353 = MethodType         #289          //  (Lcoursier/cache/CachePolicy;)Lcoursier/cache/CachePolicy$NoChanging;
  #354 = InvokeDynamic      #4:#257       // #4:apply:()Lscala/Function1;
  #355 = Utf8               (Lscala/Function1;)Ljava/lang/Object;
  #356 = NameAndType        #259:#355     // map:(Lscala/Function1;)Ljava/lang/Object;
  #357 = InterfaceMethodref #349.#356     // scala/collection/IterableOps.map:(Lscala/Function1;)Ljava/lang/Object;
  #358 = Utf8               scala/collection/SeqOps
  #359 = Class              #358          // scala/collection/SeqOps
  #360 = Utf8               distinct
  #361 = NameAndType        #360:#328     // distinct:()Ljava/lang/Object;
  #362 = InterfaceMethodref #359.#361     // scala/collection/SeqOps.distinct:()Ljava/lang/Object;
  #363 = NameAndType        #67:#68       // cachePolicy:(Ljava/lang/String;)Lscala/util/Either;
  #364 = Methodref          #2.#363       // coursier/parse/CachePolicyParser$.cachePolicy:(Ljava/lang/String;)Lscala/util/Either;
  #365 = NameAndType        #296:#297     // $anonfun$cachePolicies0$5:(Lcoursier/cache/CachePolicy;)Lscala/collection/immutable/Seq;
  #366 = Methodref          #2.#365       // coursier/parse/CachePolicyParser$.$anonfun$cachePolicies0$5:(Lcoursier/cache/CachePolicy;)Lscala/collection/immutable/Seq;
  #367 = MethodHandle       6:#366        // REF_invokeStatic coursier/parse/CachePolicyParser$.$anonfun$cachePolicies0$5:(Lcoursier/cache/CachePolicy;)Lscala/collection/immutable/Seq;
  #368 = MethodType         #297          //  (Lcoursier/cache/CachePolicy;)Lscala/collection/immutable/Seq;
  #369 = InvokeDynamic      #5:#257       // #5:apply:()Lscala/Function1;
  #370 = Utf8               (Lscala/Function1;)Lscala/util/Either;
  #371 = NameAndType        #259:#370     // map:(Lscala/Function1;)Lscala/util/Either;
  #372 = Methodref          #182.#371     // scala/util/Either.map:(Lscala/Function1;)Lscala/util/Either;
  #373 = Utf8               fromEither
  #374 = Utf8               (Lscala/util/Either;)Lcoursier/util/ValidationNel;
  #375 = NameAndType        #373:#374     // fromEither:(Lscala/util/Either;)Lcoursier/util/ValidationNel;
  #376 = Methodref          #320.#375     // coursier/util/ValidationNel$.fromEither:(Lscala/util/Either;)Lcoursier/util/ValidationNel;
  #377 = Utf8               x$3
  #378 = Utf8               $conforms
  #379 = NameAndType        #378:#256     // $conforms:()Lscala/Function1;
  #380 = Methodref          #195.#379     // scala/Predef$.$conforms:()Lscala/Function1;
  #381 = Utf8               flatten
  #382 = NameAndType        #381:#355     // flatten:(Lscala/Function1;)Ljava/lang/Object;
  #383 = InterfaceMethodref #305.#382     // scala/collection/immutable/Seq.flatten:(Lscala/Function1;)Ljava/lang/Object;
  #384 = Methodref          #4.#63        // java/lang/Object."<init>":()V
  #385 = Utf8               $deserializeLambda$
  #386 = Utf8               (Ljava/lang/invoke/SerializedLambda;)Ljava/lang/Object;
  #387 = Utf8               scala/runtime/LambdaDeserialize
  #388 = Class              #387          // scala/runtime/LambdaDeserialize
  #389 = Utf8               bootstrap
  #390 = Utf8               (Ljava/lang/invoke/MethodHandles$Lookup;Ljava/lang/String;Ljava/lang/invoke/MethodType;[Ljava/lang/invoke/MethodHandle;)Ljava/lang/invoke/CallSite;
  #391 = NameAndType        #389:#390     // bootstrap:(Ljava/lang/invoke/MethodHandles$Lookup;Ljava/lang/String;Ljava/lang/invoke/MethodType;[Ljava/lang/invoke/MethodHandle;)Ljava/lang/invoke/CallSite;
  #392 = Methodref          #388.#391     // scala/runtime/LambdaDeserialize.bootstrap:(Ljava/lang/invoke/MethodHandles$Lookup;Ljava/lang/String;Ljava/lang/invoke/MethodType;[Ljava/lang/invoke/MethodHandle;)Ljava/lang/invoke/CallSite;
  #393 = MethodHandle       6:#392        // REF_invokeStatic scala/runtime/LambdaDeserialize.bootstrap:(Ljava/lang/invoke/MethodHandles$Lookup;Ljava/lang/String;Ljava/lang/invoke/MethodType;[Ljava/lang/invoke/MethodHandle;)Ljava/lang/invoke/CallSite;
  #394 = Utf8               lambdaDeserialize
  #395 = NameAndType        #394:#386     // lambdaDeserialize:(Ljava/lang/invoke/SerializedLambda;)Ljava/lang/Object;
  #396 = InvokeDynamic      #6:#395       // #6:lambdaDeserialize:(Ljava/lang/invoke/SerializedLambda;)Ljava/lang/Object;
  #397 = Utf8               Code
  #398 = Utf8               LineNumberTable
  #399 = Utf8               StackMapTable
  #400 = Utf8               LocalVariableTable
  #401 = Utf8               Signature
  #402 = Utf8               MethodParameters
  #403 = Utf8               InnerClasses
  #404 = Utf8               SourceFile
  #405 = Utf8               BootstrapMethods
  #406 = Utf8               ScalaInlineInfo
  #407 = Utf8               Scala
{
  public static final coursier.parse.CachePolicyParser$ MODULE$;
    descriptor: Lcoursier/parse/CachePolicyParser$;
    flags: (0x0019) ACC_PUBLIC, ACC_STATIC, ACC_FINAL

  public static {};
    descriptor: ()V
    flags: (0x0009) ACC_PUBLIC, ACC_STATIC
    Code:
      stack=2, locals=0, args_size=0
         0: new           #2                  // class coursier/parse/CachePolicyParser$
         3: dup
         4: invokespecial #64                 // Method "<init>":()V
         7: putstatic     #66                 // Field MODULE$:Lcoursier/parse/CachePolicyParser$;
        10: return
      LineNumberTable:
        line 7: 0

  public scala.util.Either<java.lang.String, coursier.cache.CachePolicy> cachePolicy(java.lang.String);
    descriptor: (Ljava/lang/String;)Lscala/util/Either;
    flags: (0x0001) ACC_PUBLIC
    Code:
      stack=4, locals=4, args_size=2
         0: aload_1
         1: astore_3
         2: aload_3
         3: ifnonnull     10
         6: iconst_0
         7: goto          14
        10: aload_3
        11: invokevirtual #76                 // Method java/lang/String.hashCode:()I
        14: lookupswitch  { // 12
             -2035633817: 120
             -1548612125: 135
              -838846263: 150
              -826181101: 165
                97618667: 180
               103145323: 195
               195052435: 210
               232322839: 225
               902897905: 240
              1069449574: 255
              1190726930: 270
              1945421327: 285
                 default: 300
            }
       120: ldc           #78                 // String update-local
       122: aload_3
       123: invokevirtual #82                 // Method java/lang/String.equals:(Ljava/lang/Object;)Z
       126: ifeq          132
       129: goto          367
       132: goto          495
       135: ldc           #84                 // String offline
       137: aload_3
       138: invokevirtual #82                 // Method java/lang/String.equals:(Ljava/lang/Object;)Z
       141: ifeq          147
       144: goto          303
       147: goto          495
       150: ldc           #86                 // String update
       152: aload_3
       153: invokevirtual #82                 // Method java/lang/String.equals:(Ljava/lang/Object;)Z
       156: ifeq          162
       159: goto          415
       162: goto          495
       165: ldc           #88                 // String update-local-changing
       167: aload_3
       168: invokevirtual #82                 // Method java/lang/String.equals:(Ljava/lang/Object;)Z
       171: ifeq          177
       174: goto          351
       177: goto          495
       180: ldc           #90                 // String force
       182: aload_3
       183: invokevirtual #82                 // Method java/lang/String.equals:(Ljava/lang/Object;)Z
       186: ifeq          192
       189: goto          463
       192: goto          495
       195: ldc           #92                 // String local
       197: aload_3
       198: invokevirtual #82                 // Method java/lang/String.equals:(Ljava/lang/Object;)Z
       201: ifeq          207
       204: goto          335
       207: goto          495
       210: ldc           #94                 // String update-local-no-changing
       212: aload_3
       213: invokevirtual #82                 // Method java/lang/String.equals:(Ljava/lang/Object;)Z
       216: ifeq          222
       219: goto          383
       222: goto          495
       225: ldc           #96                 // String force-no-changing
       227: aload_3
       228: invokevirtual #82                 // Method java/lang/String.equals:(Ljava/lang/Object;)Z
       231: ifeq          237
       234: goto          479
       237: goto          495
       240: ldc           #98                 // String update-changing
       242: aload_3
       243: invokevirtual #82                 // Method java/lang/String.equals:(Ljava/lang/Object;)Z
       246: ifeq          252
       249: goto          399
       252: goto          495
       255: ldc           #100                // String missing
       257: aload_3
       258: invokevirtual #82                 // Method java/lang/String.equals:(Ljava/lang/Object;)Z
       261: ifeq          267
       264: goto          431
       267: goto          495
       270: ldc           #102                // String missing-no-changing
       272: aload_3
       273: invokevirtual #82                 // Method java/lang/String.equals:(Ljava/lang/Object;)Z
       276: ifeq          282
       279: goto          447
       282: goto          495
       285: ldc           #104                // String offline-no-changing
       287: aload_3
       288: invokevirtual #82                 // Method java/lang/String.equals:(Ljava/lang/Object;)Z
       291: ifeq          297
       294: goto          319
       297: goto          495
       300: goto          495
       303: getstatic     #109                // Field scala/package$.MODULE$:Lscala/package$;
       306: invokevirtual #113                // Method scala/package$.Right:()Lscala/util/Right$;
       309: getstatic     #116                // Field coursier/cache/CachePolicy$LocalOnly$.MODULE$:Lcoursier/cache/CachePolicy$LocalOnly$;
       312: invokevirtual #122                // Method scala/util/Right$.apply:(Ljava/lang/Object;)Lscala/util/Right;
       315: astore_2
       316: goto          529
       319: getstatic     #109                // Field scala/package$.MODULE$:Lscala/package$;
       322: invokevirtual #113                // Method scala/package$.Right:()Lscala/util/Right$;
       325: getstatic     #125                // Field coursier/cache/CachePolicy$NoChanging$LocalOnly$.MODULE$:Lcoursier/cache/CachePolicy$NoChanging$LocalOnly$;
       328: invokevirtual #122                // Method scala/util/Right$.apply:(Ljava/lang/Object;)Lscala/util/Right;
       331: astore_2
       332: goto          529
       335: getstatic     #109                // Field scala/package$.MODULE$:Lscala/package$;
       338: invokevirtual #113                // Method scala/package$.Right:()Lscala/util/Right$;
       341: getstatic     #128                // Field coursier/cache/CachePolicy$LocalOnlyIfValid$.MODULE$:Lcoursier/cache/CachePolicy$LocalOnlyIfValid$;
       344: invokevirtual #122                // Method scala/util/Right$.apply:(Ljava/lang/Object;)Lscala/util/Right;
       347: astore_2
       348: goto          529
       351: getstatic     #109                // Field scala/package$.MODULE$:Lscala/package$;
       354: invokevirtual #113                // Method scala/package$.Right:()Lscala/util/Right$;
       357: getstatic     #131                // Field coursier/cache/CachePolicy$LocalUpdateChanging$.MODULE$:Lcoursier/cache/CachePolicy$LocalUpdateChanging$;
       360: invokevirtual #122                // Method scala/util/Right$.apply:(Ljava/lang/Object;)Lscala/util/Right;
       363: astore_2
       364: goto          529
       367: getstatic     #109                // Field scala/package$.MODULE$:Lscala/package$;
       370: invokevirtual #113                // Method scala/package$.Right:()Lscala/util/Right$;
       373: getstatic     #134                // Field coursier/cache/CachePolicy$LocalUpdate$.MODULE$:Lcoursier/cache/CachePolicy$LocalUpdate$;
       376: invokevirtual #122                // Method scala/util/Right$.apply:(Ljava/lang/Object;)Lscala/util/Right;
       379: astore_2
       380: goto          529
       383: getstatic     #109                // Field scala/package$.MODULE$:Lscala/package$;
       386: invokevirtual #113                // Method scala/package$.Right:()Lscala/util/Right$;
       389: getstatic     #137                // Field coursier/cache/CachePolicy$NoChanging$LocalUpdate$.MODULE$:Lcoursier/cache/CachePolicy$NoChanging$LocalUpdate$;
       392: invokevirtual #122                // Method scala/util/Right$.apply:(Ljava/lang/Object;)Lscala/util/Right;
       395: astore_2
       396: goto          529
       399: getstatic     #109                // Field scala/package$.MODULE$:Lscala/package$;
       402: invokevirtual #113                // Method scala/package$.Right:()Lscala/util/Right$;
       405: getstatic     #140                // Field coursier/cache/CachePolicy$UpdateChanging$.MODULE$:Lcoursier/cache/CachePolicy$UpdateChanging$;
       408: invokevirtual #122                // Method scala/util/Right$.apply:(Ljava/lang/Object;)Lscala/util/Right;
       411: astore_2
       412: goto          529
       415: getstatic     #109                // Field scala/package$.MODULE$:Lscala/package$;
       418: invokevirtual #113                // Method scala/package$.Right:()Lscala/util/Right$;
       421: getstatic     #143                // Field coursier/cache/CachePolicy$Update$.MODULE$:Lcoursier/cache/CachePolicy$Update$;
       424: invokevirtual #122                // Method scala/util/Right$.apply:(Ljava/lang/Object;)Lscala/util/Right;
       427: astore_2
       428: goto          529
       431: getstatic     #109                // Field scala/package$.MODULE$:Lscala/package$;
       434: invokevirtual #113                // Method scala/package$.Right:()Lscala/util/Right$;
       437: getstatic     #146                // Field coursier/cache/CachePolicy$FetchMissing$.MODULE$:Lcoursier/cache/CachePolicy$FetchMissing$;
       440: invokevirtual #122                // Method scala/util/Right$.apply:(Ljava/lang/Object;)Lscala/util/Right;
       443: astore_2
       444: goto          529
       447: getstatic     #109                // Field scala/package$.MODULE$:Lscala/package$;
       450: invokevirtual #113                // Method scala/package$.Right:()Lscala/util/Right$;
       453: getstatic     #149                // Field coursier/cache/CachePolicy$NoChanging$FetchMissing$.MODULE$:Lcoursier/cache/CachePolicy$NoChanging$FetchMissing$;
       456: invokevirtual #122                // Method scala/util/Right$.apply:(Ljava/lang/Object;)Lscala/util/Right;
       459: astore_2
       460: goto          529
       463: getstatic     #109                // Field scala/package$.MODULE$:Lscala/package$;
       466: invokevirtual #113                // Method scala/package$.Right:()Lscala/util/Right$;
       469: getstatic     #152                // Field coursier/cache/CachePolicy$ForceDownload$.MODULE$:Lcoursier/cache/CachePolicy$ForceDownload$;
       472: invokevirtual #122                // Method scala/util/Right$.apply:(Ljava/lang/Object;)Lscala/util/Right;
       475: astore_2
       476: goto          529
       479: getstatic     #109                // Field scala/package$.MODULE$:Lscala/package$;
       482: invokevirtual #113                // Method scala/package$.Right:()Lscala/util/Right$;
       485: getstatic     #155                // Field coursier/cache/CachePolicy$NoChanging$ForceDownload$.MODULE$:Lcoursier/cache/CachePolicy$NoChanging$ForceDownload$;
       488: invokevirtual #122                // Method scala/util/Right$.apply:(Ljava/lang/Object;)Lscala/util/Right;
       491: astore_2
       492: goto          529
       495: getstatic     #109                // Field scala/package$.MODULE$:Lscala/package$;
       498: invokevirtual #159                // Method scala/package$.Left:()Lscala/util/Left$;
       501: new           #161                // class java/lang/StringBuilder
       504: dup
       505: ldc           #162                // int 27
       507: invokespecial #165                // Method java/lang/StringBuilder."<init>":(I)V
       510: ldc           #167                // String Unrecognized cache policy:
       512: invokevirtual #171                // Method java/lang/StringBuilder.append:(Ljava/lang/String;)Ljava/lang/StringBuilder;
       515: aload_3
       516: invokevirtual #171                // Method java/lang/StringBuilder.append:(Ljava/lang/String;)Ljava/lang/StringBuilder;
       519: invokevirtual #175                // Method java/lang/StringBuilder.toString:()Ljava/lang/String;
       522: invokevirtual #180                // Method scala/util/Left$.apply:(Ljava/lang/Object;)Lscala/util/Left;
       525: astore_2
       526: goto          529
       529: aload_2
       530: areturn
      StackMapTable: number_of_entries = 41
        frame_type = 253 /* append */
          offset_delta = 10
          locals = [ top, class java/lang/String ]
        frame_type = 67 /* same_locals_1_stack_item */
          stack = [ int ]
        frame_type = 251 /* same_frame_extended */
          offset_delta = 105
        frame_type = 11 /* same */
        frame_type = 2 /* same */
        frame_type = 11 /* same */
        frame_type = 2 /* same */
        frame_type = 11 /* same */
        frame_type = 2 /* same */
        frame_type = 11 /* same */
        frame_type = 2 /* same */
        frame_type = 11 /* same */
        frame_type = 2 /* same */
        frame_type = 11 /* same */
        frame_type = 2 /* same */
        frame_type = 11 /* same */
        frame_type = 2 /* same */
        frame_type = 11 /* same */
        frame_type = 2 /* same */
        frame_type = 11 /* same */
        frame_type = 2 /* same */
        frame_type = 11 /* same */
        frame_type = 2 /* same */
        frame_type = 11 /* same */
        frame_type = 2 /* same */
        frame_type = 11 /* same */
        frame_type = 2 /* same */
        frame_type = 2 /* same */
        frame_type = 15 /* same */
        frame_type = 15 /* same */
        frame_type = 15 /* same */
        frame_type = 15 /* same */
        frame_type = 15 /* same */
        frame_type = 15 /* same */
        frame_type = 15 /* same */
        frame_type = 15 /* same */
        frame_type = 15 /* same */
        frame_type = 15 /* same */
        frame_type = 15 /* same */
        frame_type = 15 /* same */
        frame_type = 255 /* full_frame */
          offset_delta = 33
          locals = [ class coursier/parse/CachePolicyParser$, class java/lang/String, class scala/util/Either, class java/lang/String ]
          stack = []
      LineNumberTable:
        line 10: 0
        line 19: 120
        line 10: 132
        line 11: 135
        line 10: 147
        line 25: 150
        line 10: 162
        line 17: 165
        line 10: 177
        line 31: 180
        line 10: 192
        line 15: 195
        line 10: 207
        line 21: 210
        line 10: 222
        line 33: 225
        line 10: 237
        line 23: 240
        line 10: 252
        line 27: 255
        line 10: 267
        line 29: 270
        line 10: 282
        line 13: 285
        line 10: 297
        line 12: 303
        line 14: 319
        line 16: 335
        line 18: 351
        line 20: 367
        line 22: 383
        line 24: 399
        line 26: 415
        line 28: 431
        line 30: 447
        line 32: 463
        line 34: 479
        line 36: 495
        line 10: 529
      LocalVariableTable:
        Start  Length  Slot  Name   Signature
            0     531     0  this   Lcoursier/parse/CachePolicyParser$;
            0     531     1 input   Ljava/lang/String;
    Signature: #69                          // (Ljava/lang/String;)Lscala/util/Either<Ljava/lang/String;Lcoursier/cache/CachePolicy;>;
    MethodParameters:
      Name                           Flags
      input                          final

  private coursier.util.ValidationNel<java.lang.String, scala.collection.immutable.Seq<coursier.cache.CachePolicy>> cachePolicies0(java.lang.String, scala.Option<scala.collection.immutable.Seq<coursier.cache.CachePolicy>>);
    descriptor: (Ljava/lang/String;Lscala/Option;)Lcoursier/util/ValidationNel;
    flags: (0x0002) ACC_PRIVATE
    Code:
      stack=5, locals=3, args_size=3
         0: getstatic     #193                // Field coursier/util/Traverse$.MODULE$:Lcoursier/util/Traverse$;
         3: getstatic     #198                // Field scala/Predef$.MODULE$:Lscala/Predef$;
         6: getstatic     #203                // Field scala/collection/StringOps$.MODULE$:Lscala/collection/StringOps$;
         9: getstatic     #198                // Field scala/Predef$.MODULE$:Lscala/Predef$;
        12: aload_1
        13: invokevirtual #207                // Method scala/Predef$.augmentString:(Ljava/lang/String;)Ljava/lang/String;
        16: bipush        44
        18: invokevirtual #211                // Method scala/collection/StringOps$.split$extension:(Ljava/lang/String;C)[Ljava/lang/String;
        21: checkcast     #213                // class "[Ljava/lang/Object;"
        24: invokevirtual #217                // Method scala/Predef$.wrapRefArray:([Ljava/lang/Object;)Lscala/collection/mutable/ArraySeq$ofRef;
        27: invokevirtual #221                // Method scala/collection/mutable/ArraySeq$ofRef.toVector:()Lscala/collection/immutable/Vector;
        30: invokevirtual #224                // Method coursier/util/Traverse$.TraverseOps:(Lscala/collection/immutable/Seq;)Lcoursier/util/Traverse$TraverseOps;
        33: aload_2
        34: invokedynamic #245,  0            // InvokeDynamic #0:apply:(Lscala/Option;)Lscala/Function1;
        39: invokevirtual #249                // Method coursier/util/Traverse$TraverseOps.validationNelTraverse:(Lscala/Function1;)Lcoursier/util/ValidationNel;
        42: invokedynamic #258,  0            // InvokeDynamic #1:apply:()Lscala/Function1;
        47: invokevirtual #261                // Method coursier/util/ValidationNel.map:(Lscala/Function1;)Lcoursier/util/ValidationNel;
        50: areturn
      LineNumberTable:
        line 42: 0
        line 41: 3
        line 40: 9
        line 41: 16
        line 43: 33
        line 51: 42
      LocalVariableTable:
        Start  Length  Slot  Name   Signature
            0      51     0  this   Lcoursier/parse/CachePolicyParser$;
            0      51     1 input   Ljava/lang/String;
            0      51     2 default   Lscala/Option;
    Signature: #187                         // (Ljava/lang/String;Lscala/Option<Lscala/collection/immutable/Seq<Lcoursier/cache/CachePolicy;>;>;)Lcoursier/util/ValidationNel<Ljava/lang/String;Lscala/collection/immutable/Seq<Lcoursier/cache/CachePolicy;>;>;
    MethodParameters:
      Name                           Flags
      input                          final
      default                        final

  public coursier.util.ValidationNel<java.lang.String, scala.collection.immutable.Seq<coursier.cache.CachePolicy>> cachePolicies(java.lang.String);
    descriptor: (Ljava/lang/String;)Lcoursier/util/ValidationNel;
    flags: (0x0001) ACC_PUBLIC
    Code:
      stack=3, locals=2, args_size=2
         0: aload_0
         1: aload_1
         2: getstatic     #269                // Field scala/None$.MODULE$:Lscala/None$;
         5: invokespecial #271                // Method cachePolicies0:(Ljava/lang/String;Lscala/Option;)Lcoursier/util/ValidationNel;
         8: areturn
      LineNumberTable:
        line 54: 0
      LocalVariableTable:
        Start  Length  Slot  Name   Signature
            0       9     0  this   Lcoursier/parse/CachePolicyParser$;
            0       9     1 input   Ljava/lang/String;
    Signature: #264                         // (Ljava/lang/String;)Lcoursier/util/ValidationNel<Ljava/lang/String;Lscala/collection/immutable/Seq<Lcoursier/cache/CachePolicy;>;>;
    MethodParameters:
      Name                           Flags
      input                          final

  public coursier.util.ValidationNel<java.lang.String, scala.collection.immutable.Seq<coursier.cache.CachePolicy>> cachePolicies(java.lang.String, scala.collection.immutable.Seq<coursier.cache.CachePolicy>);
    descriptor: (Ljava/lang/String;Lscala/collection/immutable/Seq;)Lcoursier/util/ValidationNel;
    flags: (0x0001) ACC_PUBLIC
    Code:
      stack=5, locals=3, args_size=3
         0: aload_0
         1: aload_1
         2: new           #275                // class scala/Some
         5: dup
         6: aload_2
         7: invokespecial #278                // Method scala/Some."<init>":(Ljava/lang/Object;)V
        10: invokespecial #271                // Method cachePolicies0:(Ljava/lang/String;Lscala/Option;)Lcoursier/util/ValidationNel;
        13: areturn
      LineNumberTable:
        line 57: 0
      LocalVariableTable:
        Start  Length  Slot  Name   Signature
            0      14     0  this   Lcoursier/parse/CachePolicyParser$;
            0      14     1 input   Ljava/lang/String;
            0      14     2 default   Lscala/collection/immutable/Seq;
    Signature: #273                         // (Ljava/lang/String;Lscala/collection/immutable/Seq<Lcoursier/cache/CachePolicy;>;)Lcoursier/util/ValidationNel<Ljava/lang/String;Lscala/collection/immutable/Seq<Lcoursier/cache/CachePolicy;>;>;
    MethodParameters:
      Name                           Flags
      input                          final
      default                        final

  public static final scala.collection.immutable.Nil$ $anonfun$cachePolicies0$2();
    descriptor: ()Lscala/collection/immutable/Nil$;
    flags: (0x1019) ACC_PUBLIC, ACC_STATIC, ACC_FINAL, ACC_SYNTHETIC
    Code:
      stack=1, locals=0, args_size=0
         0: getstatic     #286                // Field scala/collection/immutable/Nil$.MODULE$:Lscala/collection/immutable/Nil$;
         3: areturn
      LineNumberTable:
        line 45: 0

  public static final scala.collection.immutable.Nil$ $anonfun$cachePolicies0$3();
    descriptor: ()Lscala/collection/immutable/Nil$;
    flags: (0x1019) ACC_PUBLIC, ACC_STATIC, ACC_FINAL, ACC_SYNTHETIC
    Code:
      stack=1, locals=0, args_size=0
         0: getstatic     #286                // Field scala/collection/immutable/Nil$.MODULE$:Lscala/collection/immutable/Nil$;
         3: areturn
      LineNumberTable:
        line 47: 0

  public static final coursier.cache.CachePolicy$NoChanging $anonfun$cachePolicies0$4(coursier.cache.CachePolicy);
    descriptor: (Lcoursier/cache/CachePolicy;)Lcoursier/cache/CachePolicy$NoChanging;
    flags: (0x1019) ACC_PUBLIC, ACC_STATIC, ACC_FINAL, ACC_SYNTHETIC
    Code:
      stack=1, locals=1, args_size=1
         0: aload_0
         1: invokevirtual #294                // Method coursier/cache/CachePolicy.rejectChanging:()Lcoursier/cache/CachePolicy$NoChanging;
         4: areturn
      LineNumberTable:
        line 47: 0
      LocalVariableTable:
        Start  Length  Slot  Name   Signature
            0       5     0   x$1   Lcoursier/cache/CachePolicy;
    MethodParameters:
      Name                           Flags
      x$1                            final

  public static final scala.collection.immutable.Seq $anonfun$cachePolicies0$5(coursier.cache.CachePolicy);
    descriptor: (Lcoursier/cache/CachePolicy;)Lscala/collection/immutable/Seq;
    flags: (0x1019) ACC_PUBLIC, ACC_STATIC, ACC_FINAL, ACC_SYNTHETIC
    Code:
      stack=4, locals=1, args_size=1
         0: new           #300                // class scala/collection/immutable/$colon$colon
         3: dup
         4: aload_0
         5: getstatic     #286                // Field scala/collection/immutable/Nil$.MODULE$:Lscala/collection/immutable/Nil$;
         8: invokespecial #303                // Method scala/collection/immutable/$colon$colon."<init>":(Ljava/lang/Object;Lscala/collection/immutable/List;)V
        11: checkcast     #305                // class scala/collection/immutable/Seq
        14: areturn
      LineNumberTable:
        line 49: 0
      LocalVariableTable:
        Start  Length  Slot  Name   Signature
            0      15     0   x$2   Lcoursier/cache/CachePolicy;
    MethodParameters:
      Name                           Flags
      x$2                            final

  public static final coursier.util.ValidationNel $anonfun$cachePolicies0$1(scala.Option, java.lang.String);
    descriptor: (Lscala/Option;Ljava/lang/String;)Lcoursier/util/ValidationNel;
    flags: (0x1019) ACC_PUBLIC, ACC_STATIC, ACC_FINAL, ACC_SYNTHETIC
    Code:
      stack=3, locals=4, args_size=2
         0: aload_1
         1: astore_3
         2: aload_3
         3: ifnonnull     10
         6: iconst_0
         7: goto          14
        10: aload_3
        11: invokevirtual #76                 // Method java/lang/String.hashCode:()I
        14: lookupswitch  { // 3
                 3452664: 48
              1267032825: 64
              1544803905: 80
                 default: 96
            }
        48: ldc_w         #309                // String pure
        51: aload_3
        52: invokevirtual #82                 // Method java/lang/String.equals:(Ljava/lang/Object;)Z
        55: ifeq          61
        58: goto          134
        61: goto          190
        64: ldc_w         #311                // String no-changing
        67: aload_3
        68: invokevirtual #82                 // Method java/lang/String.equals:(Ljava/lang/Object;)Z
        71: ifeq          77
        74: goto          134
        77: goto          190
        80: ldc_w         #312                // String default
        83: aload_3
        84: invokevirtual #82                 // Method java/lang/String.equals:(Ljava/lang/Object;)Z
        87: ifeq          93
        90: goto          99
        93: goto          190
        96: goto          190
        99: aload_0
       100: invokevirtual #318                // Method scala/Option.nonEmpty:()Z
       103: ifeq          127
       106: getstatic     #323                // Field coursier/util/ValidationNel$.MODULE$:Lcoursier/util/ValidationNel$;
       109: invokevirtual #327                // Method coursier/util/ValidationNel$.success:()Lcoursier/util/ValidationNel$SuccessBuilder;
       112: aload_0
       113: invokedynamic #336,  0            // InvokeDynamic #2:apply:()Lscala/Function0;
       118: invokevirtual #340                // Method scala/Option.getOrElse:(Lscala/Function0;)Ljava/lang/Object;
       121: invokevirtual #343                // Method coursier/util/ValidationNel$SuccessBuilder.apply:(Ljava/lang/Object;)Lcoursier/util/ValidationNel;
       124: goto          130
       127: goto          190
       130: astore_2
       131: goto          215
       134: aload_0
       135: invokevirtual #318                // Method scala/Option.nonEmpty:()Z
       138: ifeq          183
       141: getstatic     #323                // Field coursier/util/ValidationNel$.MODULE$:Lcoursier/util/ValidationNel$;
       144: invokevirtual #327                // Method coursier/util/ValidationNel$.success:()Lcoursier/util/ValidationNel$SuccessBuilder;
       147: aload_0
       148: invokedynamic #347,  0            // InvokeDynamic #3:apply:()Lscala/Function0;
       153: invokevirtual #340                // Method scala/Option.getOrElse:(Lscala/Function0;)Ljava/lang/Object;
       156: checkcast     #349                // class scala/collection/IterableOps
       159: invokedynamic #354,  0            // InvokeDynamic #4:apply:()Lscala/Function1;
       164: invokeinterface #357,  2          // InterfaceMethod scala/collection/IterableOps.map:(Lscala/Function1;)Ljava/lang/Object;
       169: checkcast     #359                // class scala/collection/SeqOps
       172: invokeinterface #362,  1          // InterfaceMethod scala/collection/SeqOps.distinct:()Ljava/lang/Object;
       177: invokevirtual #343                // Method coursier/util/ValidationNel$SuccessBuilder.apply:(Ljava/lang/Object;)Lcoursier/util/ValidationNel;
       180: goto          186
       183: goto          190
       186: astore_2
       187: goto          215
       190: getstatic     #323                // Field coursier/util/ValidationNel$.MODULE$:Lcoursier/util/ValidationNel$;
       193: getstatic     #66                 // Field MODULE$:Lcoursier/parse/CachePolicyParser$;
       196: aload_3
       197: invokevirtual #364                // Method cachePolicy:(Ljava/lang/String;)Lscala/util/Either;
       200: invokedynamic #369,  0            // InvokeDynamic #5:apply:()Lscala/Function1;
       205: invokevirtual #372                // Method scala/util/Either.map:(Lscala/Function1;)Lscala/util/Either;
       208: invokevirtual #376                // Method coursier/util/ValidationNel$.fromEither:(Lscala/util/Either;)Lcoursier/util/ValidationNel;
       211: astore_2
       212: goto          215
       215: aload_2
       216: areturn
      StackMapTable: number_of_entries = 17
        frame_type = 253 /* append */
          offset_delta = 10
          locals = [ top, class java/lang/String ]
        frame_type = 67 /* same_locals_1_stack_item */
          stack = [ int ]
        frame_type = 33 /* same */
        frame_type = 12 /* same */
        frame_type = 2 /* same */
        frame_type = 12 /* same */
        frame_type = 2 /* same */
        frame_type = 12 /* same */
        frame_type = 2 /* same */
        frame_type = 2 /* same */
        frame_type = 27 /* same */
        frame_type = 66 /* same_locals_1_stack_item */
          stack = [ class coursier/util/ValidationNel ]
        frame_type = 3 /* same */
        frame_type = 48 /* same */
        frame_type = 66 /* same_locals_1_stack_item */
          stack = [ class coursier/util/ValidationNel ]
        frame_type = 3 /* same */
        frame_type = 255 /* full_frame */
          offset_delta = 24
          locals = [ class scala/Option, class java/lang/String, class coursier/util/ValidationNel, class java/lang/String ]
          stack = []
      LineNumberTable:
        line 43: 0
        line 44: 80
        line 43: 93
        line 44: 99
        line 45: 106
        line 44: 127
        line 46: 134
        line 47: 141
        line 43: 183
        line 49: 190
        line 43: 215
      LocalVariableTable:
        Start  Length  Slot  Name   Signature
            0     217     0 default$1   Lscala/Option;
            0     217     1  x0$1   Ljava/lang/String;
    MethodParameters:
      Name                           Flags
      default$1                      final
      x0$1                           final

  public static final scala.collection.immutable.Seq $anonfun$cachePolicies0$6(scala.collection.immutable.Seq);
    descriptor: (Lscala/collection/immutable/Seq;)Lscala/collection/immutable/Seq;
    flags: (0x1019) ACC_PUBLIC, ACC_STATIC, ACC_FINAL, ACC_SYNTHETIC
    Code:
      stack=2, locals=1, args_size=1
         0: aload_0
         1: getstatic     #198                // Field scala/Predef$.MODULE$:Lscala/Predef$;
         4: invokevirtual #380                // Method scala/Predef$.$conforms:()Lscala/Function1;
         7: invokeinterface #383,  2          // InterfaceMethod scala/collection/immutable/Seq.flatten:(Lscala/Function1;)Ljava/lang/Object;
        12: checkcast     #305                // class scala/collection/immutable/Seq
        15: areturn
      LineNumberTable:
        line 51: 0
      LocalVariableTable:
        Start  Length  Slot  Name   Signature
            0      16     0   x$3   Lscala/collection/immutable/Seq;
    MethodParameters:
      Name                           Flags
      x$3                            final

  private coursier.parse.CachePolicyParser$();
    descriptor: ()V
    flags: (0x0002) ACC_PRIVATE
    Code:
      stack=1, locals=1, args_size=1
         0: aload_0
         1: invokespecial #384                // Method java/lang/Object."<init>":()V
         4: return
      LineNumberTable:
        line 59: 0
        line 7: 4
      LocalVariableTable:
        Start  Length  Slot  Name   Signature
            0       5     0  this   Lcoursier/parse/CachePolicyParser$;

  private static java.lang.Object $deserializeLambda$(java.lang.invoke.SerializedLambda);
    descriptor: (Ljava/lang/invoke/SerializedLambda;)Ljava/lang/Object;
    flags: (0x100a) ACC_PRIVATE, ACC_STATIC, ACC_SYNTHETIC
    Code:
      stack=1, locals=1, args_size=1
         0: aload_0
         1: invokedynamic #396,  0            // InvokeDynamic #6:lambdaDeserialize:(Ljava/lang/invoke/SerializedLambda;)Ljava/lang/Object;
         6: areturn
}
InnerClasses:
  public static #10= #7 of #9;            // =class coursier/cache/CachePolicy$FetchMissing$ of class coursier/cache/CachePolicy
  public static #10= #12 of #9;           // =class coursier/cache/CachePolicy$ForceDownload$ of class coursier/cache/CachePolicy
  public static #10= #14 of #9;           // =class coursier/cache/CachePolicy$LocalOnly$ of class coursier/cache/CachePolicy
  public static #10= #16 of #9;           // =class coursier/cache/CachePolicy$LocalOnlyIfValid$ of class coursier/cache/CachePolicy
  public static #10= #18 of #9;           // =class coursier/cache/CachePolicy$LocalUpdate$ of class coursier/cache/CachePolicy
  public static #10= #20 of #9;           // =class coursier/cache/CachePolicy$LocalUpdateChanging$ of class coursier/cache/CachePolicy
  public static abstract #23= #22 of #9;  // NoChanging=class coursier/cache/CachePolicy$NoChanging of class coursier/cache/CachePolicy
  public static #10= #25 of #9;           // =class coursier/cache/CachePolicy$NoChanging$ of class coursier/cache/CachePolicy
  public static #10= #27 of #25;          // =class coursier/cache/CachePolicy$NoChanging$FetchMissing$ of class coursier/cache/CachePolicy$NoChanging$
  public static #10= #29 of #25;          // =class coursier/cache/CachePolicy$NoChanging$ForceDownload$ of class coursier/cache/CachePolicy$NoChanging$
  public static #10= #31 of #25;          // =class coursier/cache/CachePolicy$NoChanging$LocalOnly$ of class coursier/cache/CachePolicy$NoChanging$
  public static #10= #33 of #25;          // =class coursier/cache/CachePolicy$NoChanging$LocalUpdate$ of class coursier/cache/CachePolicy$NoChanging$
  public static #10= #35 of #9;           // =class coursier/cache/CachePolicy$Update$ of class coursier/cache/CachePolicy
  public static #10= #37 of #9;           // =class coursier/cache/CachePolicy$UpdateChanging$ of class coursier/cache/CachePolicy
  public static #42= #39 of #41;          // TraverseOps=class coursier/util/Traverse$TraverseOps of class coursier/util/Traverse
  public static final #47= #44 of #46;    // SuccessBuilder=class coursier/util/ValidationNel$SuccessBuilder of class coursier/util/ValidationNel
  public static final #52= #49 of #51;    // Lookup=class java/lang/invoke/MethodHandles$Lookup of class java/lang/invoke/MethodHandles
  public static final #57= #54 of #56;    // ofRef=class scala/collection/mutable/ArraySeq$ofRef of class scala/collection/mutable/ArraySeq
SourceFile: "CachePolicyParser.scala"
BootstrapMethods:
  0: #242 REF_invokeStatic java/lang/invoke/LambdaMetafactory.altMetafactory:(Ljava/lang/invoke/MethodHandles$Lookup;Ljava/lang/String;Ljava/lang/invoke/MethodType;[Ljava/lang/Object;)Ljava/lang/invoke/CallSite;
    Method arguments:
      #226 (Ljava/lang/Object;)Ljava/lang/Object;
      #231 REF_invokeStatic coursier/parse/CachePolicyParser$.$anonfun$cachePolicies0$1:(Lscala/Option;Ljava/lang/String;)Lcoursier/util/ValidationNel;
      #233 (Ljava/lang/String;)Lcoursier/util/ValidationNel;
      #234 5
      #235 1
      #233 (Ljava/lang/String;)Lcoursier/util/ValidationNel;
  1: #242 REF_invokeStatic java/lang/invoke/LambdaMetafactory.altMetafactory:(Ljava/lang/invoke/MethodHandles$Lookup;Ljava/lang/String;Ljava/lang/invoke/MethodType;[Ljava/lang/Object;)Ljava/lang/invoke/CallSite;
    Method arguments:
      #226 (Ljava/lang/Object;)Ljava/lang/Object;
      #254 REF_invokeStatic coursier/parse/CachePolicyParser$.$anonfun$cachePolicies0$6:(Lscala/collection/immutable/Seq;)Lscala/collection/immutable/Seq;
      #255 (Lscala/collection/immutable/Seq;)Lscala/collection/immutable/Seq;
      #234 5
      #235 1
      #255 (Lscala/collection/immutable/Seq;)Lscala/collection/immutable/Seq;
  2: #242 REF_invokeStatic java/lang/invoke/LambdaMetafactory.altMetafactory:(Ljava/lang/invoke/MethodHandles$Lookup;Ljava/lang/String;Ljava/lang/invoke/MethodType;[Ljava/lang/Object;)Ljava/lang/invoke/CallSite;
    Method arguments:
      #329 ()Ljava/lang/Object;
      #332 REF_invokeStatic coursier/parse/CachePolicyParser$.$anonfun$cachePolicies0$2:()Lscala/collection/immutable/Nil$;
      #333 ()Lscala/collection/immutable/Nil$;
      #234 5
      #235 1
      #333 ()Lscala/collection/immutable/Nil$;
  3: #242 REF_invokeStatic java/lang/invoke/LambdaMetafactory.altMetafactory:(Ljava/lang/invoke/MethodHandles$Lookup;Ljava/lang/String;Ljava/lang/invoke/MethodType;[Ljava/lang/Object;)Ljava/lang/invoke/CallSite;
    Method arguments:
      #329 ()Ljava/lang/Object;
      #346 REF_invokeStatic coursier/parse/CachePolicyParser$.$anonfun$cachePolicies0$3:()Lscala/collection/immutable/Nil$;
      #333 ()Lscala/collection/immutable/Nil$;
      #234 5
      #235 1
      #333 ()Lscala/collection/immutable/Nil$;
  4: #242 REF_invokeStatic java/lang/invoke/LambdaMetafactory.altMetafactory:(Ljava/lang/invoke/MethodHandles$Lookup;Ljava/lang/String;Ljava/lang/invoke/MethodType;[Ljava/lang/Object;)Ljava/lang/invoke/CallSite;
    Method arguments:
      #226 (Ljava/lang/Object;)Ljava/lang/Object;
      #352 REF_invokeStatic coursier/parse/CachePolicyParser$.$anonfun$cachePolicies0$4:(Lcoursier/cache/CachePolicy;)Lcoursier/cache/CachePolicy$NoChanging;
      #353 (Lcoursier/cache/CachePolicy;)Lcoursier/cache/CachePolicy$NoChanging;
      #234 5
      #235 1
      #353 (Lcoursier/cache/CachePolicy;)Lcoursier/cache/CachePolicy$NoChanging;
  5: #242 REF_invokeStatic java/lang/invoke/LambdaMetafactory.altMetafactory:(Ljava/lang/invoke/MethodHandles$Lookup;Ljava/lang/String;Ljava/lang/invoke/MethodType;[Ljava/lang/Object;)Ljava/lang/invoke/CallSite;
    Method arguments:
      #226 (Ljava/lang/Object;)Ljava/lang/Object;
      #367 REF_invokeStatic coursier/parse/CachePolicyParser$.$anonfun$cachePolicies0$5:(Lcoursier/cache/CachePolicy;)Lscala/collection/immutable/Seq;
      #368 (Lcoursier/cache/CachePolicy;)Lscala/collection/immutable/Seq;
      #234 5
      #235 1
      #368 (Lcoursier/cache/CachePolicy;)Lscala/collection/immutable/Seq;
  6: #393 REF_invokeStatic scala/runtime/LambdaDeserialize.bootstrap:(Ljava/lang/invoke/MethodHandles$Lookup;Ljava/lang/String;Ljava/lang/invoke/MethodType;[Ljava/lang/invoke/MethodHandle;)Ljava/lang/invoke/CallSite;
    Method arguments:
      #231 REF_invokeStatic coursier/parse/CachePolicyParser$.$anonfun$cachePolicies0$1:(Lscala/Option;Ljava/lang/String;)Lcoursier/util/ValidationNel;
      #332 REF_invokeStatic coursier/parse/CachePolicyParser$.$anonfun$cachePolicies0$2:()Lscala/collection/immutable/Nil$;
      #346 REF_invokeStatic coursier/parse/CachePolicyParser$.$anonfun$cachePolicies0$3:()Lscala/collection/immutable/Nil$;
      #352 REF_invokeStatic coursier/parse/CachePolicyParser$.$anonfun$cachePolicies0$4:(Lcoursier/cache/CachePolicy;)Lcoursier/cache/CachePolicy$NoChanging;
      #367 REF_invokeStatic coursier/parse/CachePolicyParser$.$anonfun$cachePolicies0$5:(Lcoursier/cache/CachePolicy;)Lscala/collection/immutable/Seq;
      #254 REF_invokeStatic coursier/parse/CachePolicyParser$.$anonfun$cachePolicies0$6:(Lscala/collection/immutable/Seq;)Lscala/collection/immutable/Seq;
  ScalaInlineInfo: length = 0x3B (unknown attribute)
   01 01 00 0B 00 EB 00 EC 01 01 20 01 21 01 01 27
   01 21 01 01 28 01 29 01 01 30 01 31 01 01 02 01
   03 01 00 46 00 45 01 01 0F 00 F0 01 01 0F 01 18
   01 00 C1 00 C2 01 00 4B 00 4C 01
  Scala: length = 0x0 (unknown attribute)

