Classfile /Users/mw/Projects/slang-braindump/.jar/jar8/assemble/slang-braindump/assemble/content/coursier/parse/CredentialsParser.class
  Last modified May 29, 2022; size 1421 bytes
  SHA-256 checksum 31dbcb8d9a9e1b65af97664a8b94d30d62001dee45e3d7095927d9eecf944f26
  Compiled from "CredentialsParser.scala"
public final class coursier.parse.CredentialsParser
  minor version: 0
  major version: 52
  flags: (0x0031) ACC_PUBLIC, ACC_FINAL, ACC_SUPER
  this_class: #2                          // coursier/parse/CredentialsParser
  super_class: #4                         // java/lang/Object
  interfaces: 0, fields: 0, methods: 2, attributes: 3
Constant pool:
   #1 = Utf8               coursier/parse/CredentialsParser
   #2 = Class              #1             // coursier/parse/CredentialsParser
   #3 = Utf8               java/lang/Object
   #4 = Class              #3             // java/lang/Object
   #5 = Utf8               CredentialsParser.scala
   #6 = Utf8               Lscala/reflect/ScalaSignature;
   #7 = Utf8               bytes
   #8 = Utf8               \u0006\u0005=;Qa\u0002\u0005\t\u000251Qa\u0004\u0005\t\u0002AAQaF\u0001\u0005\u0002aAq!G\u0001C\u0002\u0013%!\u0004\u0003\u0004&\u0003\u0001\u0006Ia\u0007\u0005\u0006\u0013\u0005!\tA\n\u0005\u0006\u0007\u0006!\t\u0001R\u0001\u0012\u0007J,G-\u001a8uS\u0006d7\u000fU1sg\u0016\u0014(BA\u0005\u000b\u0003\u0015\u0001\u0018M]:f\u0015\u0005Y\u0011\u0001C2pkJ\u001c\u0018.\u001a:\u0004\u0001A\u0011a\"A\u0007\u0002\u0011\t\t2I]3eK:$\u0018.\u00197t!\u0006\u00148/\u001a:\u0014\u0005\u0005\t\u0002C\u0001\n\u0016\u001b\u0005\u0019\"\"\u0001\u000b\u0002\u000bM\u001c\u0017\r\\1\n\u0005Y\u0019\"AB!osJ+g-\u0001\u0004=S:LGO\u0010\u000b\u0002\u001b\u00059\u0001/\u0019;uKJtW#A\u000e\u0011\u0005q\u0019S\"A\u000f\u000b\u0005yy\u0012!\u0002:fO\u0016D(B\u0001\u0011\"\u0003\u0011)H/\u001b7\u000b\u0003\t\nAA[1wC&\u0011A%\b\u0002\b!\u0006$H/\u001a:o\u0003!\u0001\u0018\r\u001e;fe:\u0004CCA\u0014B!\u0011A\u0003gM\u001e\u000f\u0005%rcB\u0001\u0016.\u001b\u0005Y#B\u0001\u0017\r\u0003\u0019a$o\\8u}%\tA#\u0003\u00020\'\u00059\u0001/Y2lC\u001e,\u0017BA\u00193\u0005\u0019)\u0015\u000e\u001e5fe*\u0011qf\u0005\t\u0003iar!!\u000e\u001c\u0011\u0005)\u001a\u0012BA\u001c\u0014\u0003\u0019\u0001&/\u001a3fM&\u0011\u0011H\u000f\u0002\u0007\'R\u0014\u0018N\\4\u000b\u0005]\u001a\u0002C\u0001\u001f@\u001b\u0005i$B\u0001 \u000b\u0003-\u0019\'/\u001a3f]RL\u0017\r\\:\n\u0005\u0001k$!\u0005#je\u0016\u001cGo\u0011:fI\u0016tG/[1mg\")!)\u0002a\u0001g\u0005\t1/\u0001\u0005qCJ\u001cXmU3r)\t)U\n\u0005\u0003G\u0011NRU\"A$\u000b\u0005\u0001R\u0011BA%H\u000551\u0016\r\\5eCRLwN\u001c(fYB\u0019\u0001fS\u001e\n\u00051\u0013$aA*fc\")aJ\u0002a\u0001g\u0005)\u0011N\u001c9vi\u0002
   #9 = Utf8               parseSeq
  #10 = Utf8               (Ljava/lang/String;)Lcoursier/util/ValidationNel;
  #11 = Utf8               (Ljava/lang/String;)Lcoursier/util/ValidationNel<Ljava/lang/String;Lscala/collection/immutable/Seq<Lcoursier/credentials/DirectCredentials;>;>;
  #12 = Utf8               input
  #13 = Utf8               coursier/parse/CredentialsParser$
  #14 = Class              #13            // coursier/parse/CredentialsParser$
  #15 = Utf8               MODULE$
  #16 = Utf8               Lcoursier/parse/CredentialsParser$;
  #17 = NameAndType        #15:#16        // MODULE$:Lcoursier/parse/CredentialsParser$;
  #18 = Fieldref           #14.#17        // coursier/parse/CredentialsParser$.MODULE$:Lcoursier/parse/CredentialsParser$;
  #19 = NameAndType        #9:#10         // parseSeq:(Ljava/lang/String;)Lcoursier/util/ValidationNel;
  #20 = Methodref          #14.#19        // coursier/parse/CredentialsParser$.parseSeq:(Ljava/lang/String;)Lcoursier/util/ValidationNel;
  #21 = Utf8               parse
  #22 = Utf8               (Ljava/lang/String;)Lscala/util/Either;
  #23 = Utf8               (Ljava/lang/String;)Lscala/util/Either<Ljava/lang/String;Lcoursier/credentials/DirectCredentials;>;
  #24 = Utf8               s
  #25 = NameAndType        #21:#22        // parse:(Ljava/lang/String;)Lscala/util/Either;
  #26 = Methodref          #14.#25        // coursier/parse/CredentialsParser$.parse:(Ljava/lang/String;)Lscala/util/Either;
  #27 = Utf8               Code
  #28 = Utf8               Signature
  #29 = Utf8               MethodParameters
  #30 = Utf8               SourceFile
  #31 = Utf8               RuntimeVisibleAnnotations
  #32 = Utf8               ScalaSig
{
  public static coursier.util.ValidationNel<java.lang.String, scala.collection.immutable.Seq<coursier.credentials.DirectCredentials>> parseSeq(java.lang.String);
    descriptor: (Ljava/lang/String;)Lcoursier/util/ValidationNel;
    flags: (0x0009) ACC_PUBLIC, ACC_STATIC
    Code:
      stack=2, locals=1, args_size=1
         0: getstatic     #18                 // Field coursier/parse/CredentialsParser$.MODULE$:Lcoursier/parse/CredentialsParser$;
         3: aload_0
         4: invokevirtual #20                 // Method coursier/parse/CredentialsParser$.parseSeq:(Ljava/lang/String;)Lcoursier/util/ValidationNel;
         7: areturn
    Signature: #11                          // (Ljava/lang/String;)Lcoursier/util/ValidationNel<Ljava/lang/String;Lscala/collection/immutable/Seq<Lcoursier/credentials/DirectCredentials;>;>;
    MethodParameters:
      Name                           Flags
      input                          final

  public static scala.util.Either<java.lang.String, coursier.credentials.DirectCredentials> parse(java.lang.String);
    descriptor: (Ljava/lang/String;)Lscala/util/Either;
    flags: (0x0009) ACC_PUBLIC, ACC_STATIC
    Code:
      stack=2, locals=1, args_size=1
         0: getstatic     #18                 // Field coursier/parse/CredentialsParser$.MODULE$:Lcoursier/parse/CredentialsParser$;
         3: aload_0
         4: invokevirtual #26                 // Method coursier/parse/CredentialsParser$.parse:(Ljava/lang/String;)Lscala/util/Either;
         7: areturn
    Signature: #23                          // (Ljava/lang/String;)Lscala/util/Either<Ljava/lang/String;Lcoursier/credentials/DirectCredentials;>;
    MethodParameters:
      Name                           Flags
      s                              final
}
SourceFile: "CredentialsParser.scala"
RuntimeVisibleAnnotations:
  0: #6(#7=s#8)
    scala.reflect.ScalaSignature(
      bytes="\u0006\u0005=;Qa\u0002\u0005\t\u000251Qa\u0004\u0005\t\u0002AAQaF\u0001\u0005\u0002aAq!G\u0001C\u0002\u0013%!\u0004\u0003\u0004&\u0003\u0001\u0006Ia\u0007\u0005\u0006\u0013\u0005!\tA\n\u0005\u0006\u0007\u0006!\t\u0001R\u0001\u0012\u0007J,G-\u001a8uS\u0006d7\u000fU1sg\u0016\u0014(BA\u0005\u000b\u0003\u0015\u0001\u0018M]:f\u0015\u0005Y\u0011\u0001C2pkJ\u001c\u0018.\u001a:\u0004\u0001A\u0011a\"A\u0007\u0002\u0011\t\t2I]3eK:$\u0018.\u00197t!\u0006\u00148/\u001a:\u0014\u0005\u0005\t\u0002C\u0001\n\u0016\u001b\u0005\u0019\"\"\u0001\u000b\u0002\u000bM\u001c\u0017\r\\1\n\u0005Y\u0019\"AB!osJ+g-\u0001\u0004=S:LGO\u0010\u000b\u0002\u001b\u00059\u0001/\u0019;uKJtW#A\u000e\u0011\u0005q\u0019S\"A\u000f\u000b\u0005yy\u0012!\u0002:fO\u0016D(B\u0001\u0011\"\u0003\u0011)H/\u001b7\u000b\u0003\t\nAA[1wC&\u0011A%\b\u0002\b!\u0006$H/\u001a:o\u0003!\u0001\u0018\r\u001e;fe:\u0004CCA\u0014B!\u0011A\u0003gM\u001e\u000f\u0005%rcB\u0001\u0016.\u001b\u0005Y#B\u0001\u0017\r\u0003\u0019a$o\\8u}%\tA#\u0003\u00020\'\u00059\u0001/Y2lC\u001e,\u0017BA\u00193\u0005\u0019)\u0015\u000e\u001e5fe*\u0011qf\u0005\t\u0003iar!!\u000e\u001c\u0011\u0005)\u001a\u0012BA\u001c\u0014\u0003\u0019\u0001&/\u001a3fM&\u0011\u0011H\u000f\u0002\u0007\'R\u0014\u0018N\\4\u000b\u0005]\u001a\u0002C\u0001\u001f@\u001b\u0005i$B\u0001 \u000b\u0003-\u0019\'/\u001a3f]RL\u0017\r\\:\n\u0005\u0001k$!\u0005#je\u0016\u001cGo\u0011:fI\u0016tG/[1mg\")!)\u0002a\u0001g\u0005\t1/\u0001\u0005qCJ\u001cXmU3r)\t)U\n\u0005\u0003G\u0011NRU\"A$\u000b\u0005\u0001R\u0011BA%H\u000551\u0016\r\\5eCRLwN\u001c(fYB\u0019\u0001fS\u001e\n\u00051\u0013$aA*fc\")aJ\u0002a\u0001g\u0005)\u0011N\u001c9vi\u0002"
    )
  ScalaSig: length = 0x3 (unknown attribute)
   05 02 00
