Classfile /Users/mw/Projects/slang-braindump/.jar/jar8/assemble/slang-braindump/assemble/content/coursier/parse/JavaOrScalaDependency$ScalaDependency.class
  Last modified May 29, 2022; size 9665 bytes
  SHA-256 checksum 75a7b1ac53466cf9277012bd930fd7820e2041ca2d10763965c824fdcd2df0a5
  Compiled from "JavaOrScalaDependency.scala"
public final class coursier.parse.JavaOrScalaDependency$ScalaDependency extends coursier.parse.JavaOrScalaDependency
  minor version: 0
  major version: 52
  flags: (0x0031) ACC_PUBLIC, ACC_FINAL, ACC_SUPER
  this_class: #2                          // coursier/parse/JavaOrScalaDependency$ScalaDependency
  super_class: #4                         // coursier/parse/JavaOrScalaDependency
  interfaces: 0, fields: 4, methods: 31, attributes: 5
Constant pool:
    #1 = Utf8               coursier/parse/JavaOrScalaDependency$ScalaDependency
    #2 = Class              #1            // coursier/parse/JavaOrScalaDependency$ScalaDependency
    #3 = Utf8               coursier/parse/JavaOrScalaDependency
    #4 = Class              #3            // coursier/parse/JavaOrScalaDependency
    #5 = Utf8               JavaOrScalaDependency.scala
    #6 = Utf8               ScalaDependency
    #7 = Utf8               coursier/parse/JavaOrScalaModule$ScalaModule
    #8 = Class              #7            // coursier/parse/JavaOrScalaModule$ScalaModule
    #9 = Utf8               coursier/parse/JavaOrScalaModule
   #10 = Class              #9            // coursier/parse/JavaOrScalaModule
   #11 = Utf8               ScalaModule
   #12 = Utf8               coursier/parse/JavaOrScalaModule$ScalaModule$
   #13 = Class              #12           // coursier/parse/JavaOrScalaModule$ScalaModule$
   #14 = Utf8
   #15 = Utf8               java/lang/invoke/MethodHandles$Lookup
   #16 = Class              #15           // java/lang/invoke/MethodHandles$Lookup
   #17 = Utf8               java/lang/invoke/MethodHandles
   #18 = Class              #17           // java/lang/invoke/MethodHandles
   #19 = Utf8               Lookup
   #20 = Utf8               baseDependency
   #21 = Utf8               Lcoursier/core/Dependency;
   #22 = Utf8               fullCrossVersion
   #23 = Utf8               Z
   #24 = Utf8               withPlatformSuffix
   #25 = Utf8               exclude
   #26 = Utf8               Lscala/collection/immutable/Set;
   #27 = Utf8               Lscala/collection/immutable/Set<Lcoursier/parse/JavaOrScalaModule;>;
   #28 = Utf8               ()Lcoursier/core/Dependency;
   #29 = NameAndType        #20:#21       // baseDependency:Lcoursier/core/Dependency;
   #30 = Fieldref           #2.#29        // coursier/parse/JavaOrScalaDependency$ScalaDependency.baseDependency:Lcoursier/core/Dependency;
   #31 = Utf8               this
   #32 = Utf8               Lcoursier/parse/JavaOrScalaDependency$ScalaDependency;
   #33 = Utf8               ()Z
   #34 = NameAndType        #22:#23       // fullCrossVersion:Z
   #35 = Fieldref           #2.#34        // coursier/parse/JavaOrScalaDependency$ScalaDependency.fullCrossVersion:Z
   #36 = NameAndType        #24:#23       // withPlatformSuffix:Z
   #37 = Fieldref           #2.#36        // coursier/parse/JavaOrScalaDependency$ScalaDependency.withPlatformSuffix:Z
   #38 = Utf8               ()Lscala/collection/immutable/Set;
   #39 = Utf8               ()Lscala/collection/immutable/Set<Lcoursier/parse/JavaOrScalaModule;>;
   #40 = NameAndType        #25:#26       // exclude:Lscala/collection/immutable/Set;
   #41 = Fieldref           #2.#40        // coursier/parse/JavaOrScalaDependency$ScalaDependency.exclude:Lscala/collection/immutable/Set;
   #42 = Utf8               module
   #43 = Utf8               ()Lcoursier/parse/JavaOrScalaModule$ScalaModule;
   #44 = Utf8               MODULE$
   #45 = Utf8               Lcoursier/parse/JavaOrScalaModule$ScalaModule$;
   #46 = NameAndType        #44:#45       // MODULE$:Lcoursier/parse/JavaOrScalaModule$ScalaModule$;
   #47 = Fieldref           #13.#46       // coursier/parse/JavaOrScalaModule$ScalaModule$.MODULE$:Lcoursier/parse/JavaOrScalaModule$ScalaModule$;
   #48 = NameAndType        #20:#28       // baseDependency:()Lcoursier/core/Dependency;
   #49 = Methodref          #2.#48        // coursier/parse/JavaOrScalaDependency$ScalaDependency.baseDependency:()Lcoursier/core/Dependency;
   #50 = Utf8               coursier/core/Dependency
   #51 = Class              #50           // coursier/core/Dependency
   #52 = Utf8               ()Lcoursier/core/Module;
   #53 = NameAndType        #42:#52       // module:()Lcoursier/core/Module;
   #54 = Methodref          #51.#53       // coursier/core/Dependency.module:()Lcoursier/core/Module;
   #55 = NameAndType        #22:#33       // fullCrossVersion:()Z
   #56 = Methodref          #2.#55        // coursier/parse/JavaOrScalaDependency$ScalaDependency.fullCrossVersion:()Z
   #57 = Utf8               apply
   #58 = Utf8               (Lcoursier/core/Module;Z)Lcoursier/parse/JavaOrScalaModule$ScalaModule;
   #59 = NameAndType        #57:#58       // apply:(Lcoursier/core/Module;Z)Lcoursier/parse/JavaOrScalaModule$ScalaModule;
   #60 = Methodref          #13.#59       // coursier/parse/JavaOrScalaModule$ScalaModule$.apply:(Lcoursier/core/Module;Z)Lcoursier/parse/JavaOrScalaModule$ScalaModule;
   #61 = Utf8               repr
   #62 = Utf8               ()Ljava/lang/String;
   #63 = Utf8               java/lang/StringBuilder
   #64 = Class              #63           // java/lang/StringBuilder
   #65 = Integer            1
   #66 = Utf8               <init>
   #67 = Utf8               (I)V
   #68 = NameAndType        #66:#67       // "<init>":(I)V
   #69 = Methodref          #64.#68       // java/lang/StringBuilder."<init>":(I)V
   #70 = NameAndType        #42:#43       // module:()Lcoursier/parse/JavaOrScalaModule$ScalaModule;
   #71 = Methodref          #2.#70        // coursier/parse/JavaOrScalaDependency$ScalaDependency.module:()Lcoursier/parse/JavaOrScalaModule$ScalaModule;
   #72 = Utf8               append
   #73 = Utf8               (Ljava/lang/Object;)Ljava/lang/StringBuilder;
   #74 = NameAndType        #72:#73       // append:(Ljava/lang/Object;)Ljava/lang/StringBuilder;
   #75 = Methodref          #64.#74       // java/lang/StringBuilder.append:(Ljava/lang/Object;)Ljava/lang/StringBuilder;
   #76 = Utf8               :
   #77 = String             #76           // :
   #78 = Utf8               (Ljava/lang/String;)Ljava/lang/StringBuilder;
   #79 = NameAndType        #72:#78       // append:(Ljava/lang/String;)Ljava/lang/StringBuilder;
   #80 = Methodref          #64.#79       // java/lang/StringBuilder.append:(Ljava/lang/String;)Ljava/lang/StringBuilder;
   #81 = NameAndType        #24:#33       // withPlatformSuffix:()Z
   #82 = Methodref          #2.#81        // coursier/parse/JavaOrScalaDependency$ScalaDependency.withPlatformSuffix:()Z
   #83 = String             #14           //
   #84 = Utf8               java/lang/String
   #85 = Class              #84           // java/lang/String
   #86 = Utf8               version
   #87 = NameAndType        #86:#62       // version:()Ljava/lang/String;
   #88 = Methodref          #51.#87       // coursier/core/Dependency.version:()Ljava/lang/String;
   #89 = Utf8               toString
   #90 = NameAndType        #89:#62       // toString:()Ljava/lang/String;
   #91 = Methodref          #64.#90       // java/lang/StringBuilder.toString:()Ljava/lang/String;
   #92 = Utf8               dependency
   #93 = Utf8               (Ljava/lang/String;Ljava/lang/String;Ljava/lang/String;)Lcoursier/core/Dependency;
   #94 = Utf8               scalaBinaryVersion
   #95 = Utf8               scalaVersion
   #96 = Utf8               platformName
   #97 = Utf8               scala/collection/StringOps$
   #98 = Class              #97           // scala/collection/StringOps$
   #99 = Utf8               Lscala/collection/StringOps$;
  #100 = NameAndType        #44:#99       // MODULE$:Lscala/collection/StringOps$;
  #101 = Fieldref           #98.#100      // scala/collection/StringOps$.MODULE$:Lscala/collection/StringOps$;
  #102 = Utf8               scala/Predef$
  #103 = Class              #102          // scala/Predef$
  #104 = Utf8               Lscala/Predef$;
  #105 = NameAndType        #44:#104      // MODULE$:Lscala/Predef$;
  #106 = Fieldref           #103.#105     // scala/Predef$.MODULE$:Lscala/Predef$;
  #107 = Utf8               augmentString
  #108 = Utf8               (Ljava/lang/String;)Ljava/lang/String;
  #109 = NameAndType        #107:#108     // augmentString:(Ljava/lang/String;)Ljava/lang/String;
  #110 = Methodref          #103.#109     // scala/Predef$.augmentString:(Ljava/lang/String;)Ljava/lang/String;
  #111 = Utf8               nonEmpty$extension
  #112 = Utf8               (Ljava/lang/String;)Z
  #113 = NameAndType        #111:#112     // nonEmpty$extension:(Ljava/lang/String;)Z
  #114 = Methodref          #98.#113      // scala/collection/StringOps$.nonEmpty$extension:(Ljava/lang/String;)Z
  #115 = Utf8               _
  #116 = String             #115          // _
  #117 = Integer            0
  #118 = Utf8               coursier/core/Module
  #119 = Class              #118          // coursier/core/Module
  #120 = Utf8               name
  #121 = NameAndType        #120:#62      // name:()Ljava/lang/String;
  #122 = Methodref          #119.#121     // coursier/core/Module.name:()Ljava/lang/String;
  #123 = Utf8               withName
  #124 = Utf8               (Ljava/lang/String;)Lcoursier/core/Module;
  #125 = NameAndType        #123:#124     // withName:(Ljava/lang/String;)Lcoursier/core/Module;
  #126 = Methodref          #119.#125     // coursier/core/Module.withName:(Ljava/lang/String;)Lcoursier/core/Module;
  #127 = Utf8               withModule
  #128 = Utf8               (Lcoursier/core/Module;)Lcoursier/core/Dependency;
  #129 = NameAndType        #127:#128     // withModule:(Lcoursier/core/Module;)Lcoursier/core/Dependency;
  #130 = Methodref          #51.#129      // coursier/core/Dependency.withModule:(Lcoursier/core/Module;)Lcoursier/core/Dependency;
  #131 = Utf8               platformSuffix
  #132 = Utf8               Ljava/lang/String;
  #133 = Utf8               scalaSuffix
  #134 = Utf8               newName
  #135 = Utf8               withPlatform
  #136 = Utf8               (Ljava/lang/String;)Lcoursier/parse/JavaOrScalaDependency$ScalaDependency;
  #137 = Utf8               (Ljava/lang/Object;)Ljava/lang/Object;
  #138 = MethodType         #137          //  (Ljava/lang/Object;)Ljava/lang/Object;
  #139 = Utf8               $anonfun$withPlatform$1
  #140 = Utf8               (Ljava/lang/String;Lcoursier/core/Dependency;)Lcoursier/core/Dependency;
  #141 = NameAndType        #139:#140     // $anonfun$withPlatform$1:(Ljava/lang/String;Lcoursier/core/Dependency;)Lcoursier/core/Dependency;
  #142 = Methodref          #2.#141       // coursier/parse/JavaOrScalaDependency$ScalaDependency.$anonfun$withPlatform$1:(Ljava/lang/String;Lcoursier/core/Dependency;)Lcoursier/core/Dependency;
  #143 = MethodHandle       6:#142        // REF_invokeStatic coursier/parse/JavaOrScalaDependency$ScalaDependency.$anonfun$withPlatform$1:(Ljava/lang/String;Lcoursier/core/Dependency;)Lcoursier/core/Dependency;
  #144 = Utf8               (Lcoursier/core/Dependency;)Lcoursier/core/Dependency;
  #145 = MethodType         #144          //  (Lcoursier/core/Dependency;)Lcoursier/core/Dependency;
  #146 = Integer            5
  #147 = Utf8               java/lang/invoke/LambdaMetafactory
  #148 = Class              #147          // java/lang/invoke/LambdaMetafactory
  #149 = Utf8               altMetafactory
  #150 = Utf8               (Ljava/lang/invoke/MethodHandles$Lookup;Ljava/lang/String;Ljava/lang/invoke/MethodType;[Ljava/lang/Object;)Ljava/lang/invoke/CallSite;
  #151 = NameAndType        #149:#150     // altMetafactory:(Ljava/lang/invoke/MethodHandles$Lookup;Ljava/lang/String;Ljava/lang/invoke/MethodType;[Ljava/lang/Object;)Ljava/lang/invoke/CallSite;
  #152 = Methodref          #148.#151     // java/lang/invoke/LambdaMetafactory.altMetafactory:(Ljava/lang/invoke/MethodHandles$Lookup;Ljava/lang/String;Ljava/lang/invoke/MethodType;[Ljava/lang/Object;)Ljava/lang/invoke/CallSite;
  #153 = MethodHandle       6:#152        // REF_invokeStatic java/lang/invoke/LambdaMetafactory.altMetafactory:(Ljava/lang/invoke/MethodHandles$Lookup;Ljava/lang/String;Ljava/lang/invoke/MethodType;[Ljava/lang/Object;)Ljava/lang/invoke/CallSite;
  #154 = Utf8               (Ljava/lang/String;)Lscala/Function1;
  #155 = NameAndType        #57:#154      // apply:(Ljava/lang/String;)Lscala/Function1;
  #156 = InvokeDynamic      #0:#155       // #0:apply:(Ljava/lang/String;)Lscala/Function1;
  #157 = Utf8               withUnderlyingDependency
  #158 = Utf8               (Lscala/Function1;)Lcoursier/parse/JavaOrScalaDependency$ScalaDependency;
  #159 = NameAndType        #157:#158     // withUnderlyingDependency:(Lscala/Function1;)Lcoursier/parse/JavaOrScalaDependency$ScalaDependency;
  #160 = Methodref          #2.#159       // coursier/parse/JavaOrScalaDependency$ScalaDependency.withUnderlyingDependency:(Lscala/Function1;)Lcoursier/parse/JavaOrScalaDependency$ScalaDependency;
  #161 = Utf8               addExclude
  #162 = Utf8               (Lscala/collection/immutable/Seq;)Lcoursier/parse/JavaOrScalaDependency$ScalaDependency;
  #163 = Utf8               (Lscala/collection/immutable/Seq<Lcoursier/parse/JavaOrScalaModule;>;)Lcoursier/parse/JavaOrScalaDependency$ScalaDependency;
  #164 = Utf8               excl
  #165 = NameAndType        #25:#38       // exclude:()Lscala/collection/immutable/Set;
  #166 = Methodref          #2.#165       // coursier/parse/JavaOrScalaDependency$ScalaDependency.exclude:()Lscala/collection/immutable/Set;
  #167 = Utf8               scala/collection/immutable/Set
  #168 = Class              #167          // scala/collection/immutable/Set
  #169 = Utf8               $plus$plus
  #170 = Utf8               (Lscala/collection/IterableOnce;)Lscala/collection/SetOps;
  #171 = NameAndType        #169:#170     // $plus$plus:(Lscala/collection/IterableOnce;)Lscala/collection/SetOps;
  #172 = InterfaceMethodref #168.#171     // scala/collection/immutable/Set.$plus$plus:(Lscala/collection/IterableOnce;)Lscala/collection/SetOps;
  #173 = Utf8               withExclude
  #174 = Utf8               (Lscala/collection/immutable/Set;)Lcoursier/parse/JavaOrScalaDependency$ScalaDependency;
  #175 = NameAndType        #173:#174     // withExclude:(Lscala/collection/immutable/Set;)Lcoursier/parse/JavaOrScalaDependency$ScalaDependency;
  #176 = Methodref          #2.#175       // coursier/parse/JavaOrScalaDependency$ScalaDependency.withExclude:(Lscala/collection/immutable/Set;)Lcoursier/parse/JavaOrScalaDependency$ScalaDependency;
  #177 = Utf8               Lscala/collection/immutable/Seq;
  #178 = Utf8               (Lscala/Function1<Lcoursier/core/Dependency;Lcoursier/core/Dependency;>;)Lcoursier/parse/JavaOrScalaDependency$ScalaDependency;
  #179 = Utf8               f
  #180 = Utf8               scala/Function1
  #181 = Class              #180          // scala/Function1
  #182 = NameAndType        #57:#137      // apply:(Ljava/lang/Object;)Ljava/lang/Object;
  #183 = InterfaceMethodref #181.#182     // scala/Function1.apply:(Ljava/lang/Object;)Ljava/lang/Object;
  #184 = Utf8               withBaseDependency
  #185 = Utf8               (Lcoursier/core/Dependency;)Lcoursier/parse/JavaOrScalaDependency$ScalaDependency;
  #186 = NameAndType        #184:#185     // withBaseDependency:(Lcoursier/core/Dependency;)Lcoursier/parse/JavaOrScalaDependency$ScalaDependency;
  #187 = Methodref          #2.#186       // coursier/parse/JavaOrScalaDependency$ScalaDependency.withBaseDependency:(Lcoursier/core/Dependency;)Lcoursier/parse/JavaOrScalaDependency$ScalaDependency;
  #188 = Utf8               Lscala/Function1;
  #189 = Utf8               (Lcoursier/core/Dependency;ZZLscala/collection/immutable/Set;)V
  #190 = NameAndType        #66:#189      // "<init>":(Lcoursier/core/Dependency;ZZLscala/collection/immutable/Set;)V
  #191 = Methodref          #2.#190       // coursier/parse/JavaOrScalaDependency$ScalaDependency."<init>":(Lcoursier/core/Dependency;ZZLscala/collection/immutable/Set;)V
  #192 = Utf8               withFullCrossVersion
  #193 = Utf8               (Z)Lcoursier/parse/JavaOrScalaDependency$ScalaDependency;
  #194 = Utf8               withWithPlatformSuffix
  #195 = Utf8               (Lscala/collection/immutable/Set<Lcoursier/parse/JavaOrScalaModule;>;)Lcoursier/parse/JavaOrScalaDependency$ScalaDependency;
  #196 = Utf8               ScalaDependency(
  #197 = String             #196          // ScalaDependency(
  #198 = Utf8               (Ljava/lang/String;)V
  #199 = NameAndType        #66:#198      // "<init>":(Ljava/lang/String;)V
  #200 = Methodref          #64.#199      // java/lang/StringBuilder."<init>":(Ljava/lang/String;)V
  #201 = Utf8               valueOf
  #202 = Utf8               (Ljava/lang/Object;)Ljava/lang/String;
  #203 = NameAndType        #201:#202     // valueOf:(Ljava/lang/Object;)Ljava/lang/String;
  #204 = Methodref          #85.#203      // java/lang/String.valueOf:(Ljava/lang/Object;)Ljava/lang/String;
  #205 = Utf8               ,
  #206 = String             #205          // ,
  #207 = Utf8               (Z)Ljava/lang/String;
  #208 = NameAndType        #201:#207     // valueOf:(Z)Ljava/lang/String;
  #209 = Methodref          #85.#208      // java/lang/String.valueOf:(Z)Ljava/lang/String;
  #210 = Utf8               )
  #211 = String             #210          // )
  #212 = Utf8               b
  #213 = Utf8               Ljava/lang/StringBuilder;
  #214 = Utf8               canEqual
  #215 = Utf8               (Ljava/lang/Object;)Z
  #216 = Utf8               obj
  #217 = Utf8               Ljava/lang/Object;
  #218 = Utf8               equals
  #219 = NameAndType        #214:#215     // canEqual:(Ljava/lang/Object;)Z
  #220 = Methodref          #2.#219       // coursier/parse/JavaOrScalaDependency$ScalaDependency.canEqual:(Ljava/lang/Object;)Z
  #221 = Utf8               java/lang/Object
  #222 = Class              #221          // java/lang/Object
  #223 = NameAndType        #218:#215     // equals:(Ljava/lang/Object;)Z
  #224 = Methodref          #222.#223     // java/lang/Object.equals:(Ljava/lang/Object;)Z
  #225 = Utf8               other
  #226 = Utf8               hashCode
  #227 = Utf8               ()I
  #228 = String             #6            // ScalaDependency
  #229 = Utf8               scala/runtime/Statics
  #230 = Class              #229          // scala/runtime/Statics
  #231 = Utf8               anyHash
  #232 = Utf8               (Ljava/lang/Object;)I
  #233 = NameAndType        #231:#232     // anyHash:(Ljava/lang/Object;)I
  #234 = Methodref          #230.#233     // scala/runtime/Statics.anyHash:(Ljava/lang/Object;)I
  #235 = Utf8               code
  #236 = Utf8               I
  #237 = Utf8               tuple
  #238 = Utf8               ()Lscala/Tuple4;
  #239 = Utf8               ()Lscala/Tuple4<Lcoursier/core/Dependency;Ljava/lang/Object;Ljava/lang/Object;Lscala/collection/immutable/Set<Lcoursier/parse/JavaOrScalaModule;>;>;
  #240 = Utf8               scala/Tuple4
  #241 = Class              #240          // scala/Tuple4
  #242 = Utf8               scala/runtime/BoxesRunTime
  #243 = Class              #242          // scala/runtime/BoxesRunTime
  #244 = Utf8               boxToBoolean
  #245 = Utf8               (Z)Ljava/lang/Boolean;
  #246 = NameAndType        #244:#245     // boxToBoolean:(Z)Ljava/lang/Boolean;
  #247 = Methodref          #243.#246     // scala/runtime/BoxesRunTime.boxToBoolean:(Z)Ljava/lang/Boolean;
  #248 = Utf8               (Ljava/lang/Object;Ljava/lang/Object;Ljava/lang/Object;Ljava/lang/Object;)V
  #249 = NameAndType        #66:#248      // "<init>":(Ljava/lang/Object;Ljava/lang/Object;Ljava/lang/Object;Ljava/lang/Object;)V
  #250 = Methodref          #241.#249     // scala/Tuple4."<init>":(Ljava/lang/Object;Ljava/lang/Object;Ljava/lang/Object;Ljava/lang/Object;)V
  #251 = Utf8               productPrefix
  #252 = Utf8               productArity
  #253 = Utf8               productElement
  #254 = Utf8               (I)Ljava/lang/Object;
  #255 = Utf8               n
  #256 = Utf8               java/lang/IndexOutOfBoundsException
  #257 = Class              #256          // java/lang/IndexOutOfBoundsException
  #258 = Utf8               boxToInteger
  #259 = Utf8               (I)Ljava/lang/Integer;
  #260 = NameAndType        #258:#259     // boxToInteger:(I)Ljava/lang/Integer;
  #261 = Methodref          #243.#260     // scala/runtime/BoxesRunTime.boxToInteger:(I)Ljava/lang/Integer;
  #262 = Methodref          #222.#90      // java/lang/Object.toString:()Ljava/lang/String;
  #263 = Methodref          #257.#199     // java/lang/IndexOutOfBoundsException."<init>":(Ljava/lang/String;)V
  #264 = Utf8               productElementName
  #265 = Utf8               (I)Ljava/lang/String;
  #266 = String             #20           // baseDependency
  #267 = String             #22           // fullCrossVersion
  #268 = String             #24           // withPlatformSuffix
  #269 = String             #25           // exclude
  #270 = Utf8               (Lscala/Function1;)Lcoursier/parse/JavaOrScalaDependency;
  #271 = Utf8               (Lscala/collection/immutable/Seq;)Lcoursier/parse/JavaOrScalaDependency;
  #272 = NameAndType        #161:#162     // addExclude:(Lscala/collection/immutable/Seq;)Lcoursier/parse/JavaOrScalaDependency$ScalaDependency;
  #273 = Methodref          #2.#272       // coursier/parse/JavaOrScalaDependency$ScalaDependency.addExclude:(Lscala/collection/immutable/Seq;)Lcoursier/parse/JavaOrScalaDependency$ScalaDependency;
  #274 = Utf8               (Ljava/lang/String;)Lcoursier/parse/JavaOrScalaDependency;
  #275 = NameAndType        #135:#136     // withPlatform:(Ljava/lang/String;)Lcoursier/parse/JavaOrScalaDependency$ScalaDependency;
  #276 = Methodref          #2.#275       // coursier/parse/JavaOrScalaDependency$ScalaDependency.withPlatform:(Ljava/lang/String;)Lcoursier/parse/JavaOrScalaDependency$ScalaDependency;
  #277 = Utf8               ()Lcoursier/parse/JavaOrScalaModule;
  #278 = Utf8               platformSuffix$1
  #279 = Utf8               dep
  #280 = Utf8               (Lcoursier/core/Dependency;ZZLscala/collection/immutable/Set<Lcoursier/parse/JavaOrScalaModule;>;)V
  #281 = Utf8               ()V
  #282 = NameAndType        #66:#281      // "<init>":()V
  #283 = Methodref          #4.#282       // coursier/parse/JavaOrScalaDependency."<init>":()V
  #284 = Utf8               $deserializeLambda$
  #285 = Utf8               (Ljava/lang/invoke/SerializedLambda;)Ljava/lang/Object;
  #286 = Utf8               scala/runtime/LambdaDeserialize
  #287 = Class              #286          // scala/runtime/LambdaDeserialize
  #288 = Utf8               bootstrap
  #289 = Utf8               (Ljava/lang/invoke/MethodHandles$Lookup;Ljava/lang/String;Ljava/lang/invoke/MethodType;[Ljava/lang/invoke/MethodHandle;)Ljava/lang/invoke/CallSite;
  #290 = NameAndType        #288:#289     // bootstrap:(Ljava/lang/invoke/MethodHandles$Lookup;Ljava/lang/String;Ljava/lang/invoke/MethodType;[Ljava/lang/invoke/MethodHandle;)Ljava/lang/invoke/CallSite;
  #291 = Methodref          #287.#290     // scala/runtime/LambdaDeserialize.bootstrap:(Ljava/lang/invoke/MethodHandles$Lookup;Ljava/lang/String;Ljava/lang/invoke/MethodType;[Ljava/lang/invoke/MethodHandle;)Ljava/lang/invoke/CallSite;
  #292 = MethodHandle       6:#291        // REF_invokeStatic scala/runtime/LambdaDeserialize.bootstrap:(Ljava/lang/invoke/MethodHandles$Lookup;Ljava/lang/String;Ljava/lang/invoke/MethodType;[Ljava/lang/invoke/MethodHandle;)Ljava/lang/invoke/CallSite;
  #293 = Utf8               lambdaDeserialize
  #294 = NameAndType        #293:#285     // lambdaDeserialize:(Ljava/lang/invoke/SerializedLambda;)Ljava/lang/Object;
  #295 = InvokeDynamic      #1:#294       // #1:lambdaDeserialize:(Ljava/lang/invoke/SerializedLambda;)Ljava/lang/Object;
  #296 = Utf8               Signature
  #297 = Utf8               Code
  #298 = Utf8               LineNumberTable
  #299 = Utf8               LocalVariableTable
  #300 = Utf8               StackMapTable
  #301 = Utf8               MethodParameters
  #302 = Utf8               InnerClasses
  #303 = Utf8               SourceFile
  #304 = Utf8               BootstrapMethods
  #305 = Utf8               ScalaInlineInfo
  #306 = Utf8               Scala
{
  private final coursier.core.Dependency baseDependency;
    descriptor: Lcoursier/core/Dependency;
    flags: (0x0012) ACC_PRIVATE, ACC_FINAL

  private final boolean fullCrossVersion;
    descriptor: Z
    flags: (0x0012) ACC_PRIVATE, ACC_FINAL

  private final boolean withPlatformSuffix;
    descriptor: Z
    flags: (0x0012) ACC_PRIVATE, ACC_FINAL

  private final scala.collection.immutable.Set<coursier.parse.JavaOrScalaModule> exclude;
    descriptor: Lscala/collection/immutable/Set;
    flags: (0x0012) ACC_PRIVATE, ACC_FINAL
    Signature: #27                          // Lscala/collection/immutable/Set<Lcoursier/parse/JavaOrScalaModule;>;

  public coursier.core.Dependency baseDependency();
    descriptor: ()Lcoursier/core/Dependency;
    flags: (0x0001) ACC_PUBLIC
    Code:
      stack=1, locals=1, args_size=1
         0: aload_0
         1: getfield      #30                 // Field baseDependency:Lcoursier/core/Dependency;
         4: areturn
      LineNumberTable:
        line 49: 0
      LocalVariableTable:
        Start  Length  Slot  Name   Signature
            0       5     0  this   Lcoursier/parse/JavaOrScalaDependency$ScalaDependency;

  public boolean fullCrossVersion();
    descriptor: ()Z
    flags: (0x0001) ACC_PUBLIC
    Code:
      stack=1, locals=1, args_size=1
         0: aload_0
         1: getfield      #35                 // Field fullCrossVersion:Z
         4: ireturn
      LineNumberTable:
        line 49: 0
      LocalVariableTable:
        Start  Length  Slot  Name   Signature
            0       5     0  this   Lcoursier/parse/JavaOrScalaDependency$ScalaDependency;

  public boolean withPlatformSuffix();
    descriptor: ()Z
    flags: (0x0001) ACC_PUBLIC
    Code:
      stack=1, locals=1, args_size=1
         0: aload_0
         1: getfield      #37                 // Field withPlatformSuffix:Z
         4: ireturn
      LineNumberTable:
        line 49: 0
      LocalVariableTable:
        Start  Length  Slot  Name   Signature
            0       5     0  this   Lcoursier/parse/JavaOrScalaDependency$ScalaDependency;

  public scala.collection.immutable.Set<coursier.parse.JavaOrScalaModule> exclude();
    descriptor: ()Lscala/collection/immutable/Set;
    flags: (0x0001) ACC_PUBLIC
    Code:
      stack=1, locals=1, args_size=1
         0: aload_0
         1: getfield      #41                 // Field exclude:Lscala/collection/immutable/Set;
         4: areturn
      LineNumberTable:
        line 49: 0
      LocalVariableTable:
        Start  Length  Slot  Name   Signature
            0       5     0  this   Lcoursier/parse/JavaOrScalaDependency$ScalaDependency;
    Signature: #39                          // ()Lscala/collection/immutable/Set<Lcoursier/parse/JavaOrScalaModule;>;

  public coursier.parse.JavaOrScalaModule$ScalaModule module();
    descriptor: ()Lcoursier/parse/JavaOrScalaModule$ScalaModule;
    flags: (0x0001) ACC_PUBLIC
    Code:
      stack=3, locals=1, args_size=1
         0: getstatic     #47                 // Field coursier/parse/JavaOrScalaModule$ScalaModule$.MODULE$:Lcoursier/parse/JavaOrScalaModule$ScalaModule$;
         3: aload_0
         4: invokevirtual #49                 // Method baseDependency:()Lcoursier/core/Dependency;
         7: invokevirtual #54                 // Method coursier/core/Dependency.module:()Lcoursier/core/Module;
        10: aload_0
        11: invokevirtual #56                 // Method fullCrossVersion:()Z
        14: invokevirtual #60                 // Method coursier/parse/JavaOrScalaModule$ScalaModule$.apply:(Lcoursier/core/Module;Z)Lcoursier/parse/JavaOrScalaModule$ScalaModule;
        17: areturn
      LineNumberTable:
        line 57: 0
      LocalVariableTable:
        Start  Length  Slot  Name   Signature
            0      18     0  this   Lcoursier/parse/JavaOrScalaDependency$ScalaDependency;

  public java.lang.String repr();
    descriptor: ()Ljava/lang/String;
    flags: (0x0001) ACC_PUBLIC
    Code:
      stack=3, locals=1, args_size=1
         0: new           #64                 // class java/lang/StringBuilder
         3: dup
         4: ldc           #65                 // int 1
         6: invokespecial #69                 // Method java/lang/StringBuilder."<init>":(I)V
         9: aload_0
        10: invokevirtual #71                 // Method module:()Lcoursier/parse/JavaOrScalaModule$ScalaModule;
        13: invokevirtual #75                 // Method java/lang/StringBuilder.append:(Ljava/lang/Object;)Ljava/lang/StringBuilder;
        16: ldc           #77                 // String :
        18: invokevirtual #80                 // Method java/lang/StringBuilder.append:(Ljava/lang/String;)Ljava/lang/StringBuilder;
        21: aload_0
        22: invokevirtual #82                 // Method withPlatformSuffix:()Z
        25: ifeq          33
        28: ldc           #77                 // String :
        30: goto          35
        33: ldc           #83                 // String
        35: invokevirtual #75                 // Method java/lang/StringBuilder.append:(Ljava/lang/Object;)Ljava/lang/StringBuilder;
        38: aload_0
        39: invokevirtual #49                 // Method baseDependency:()Lcoursier/core/Dependency;
        42: invokevirtual #88                 // Method coursier/core/Dependency.version:()Ljava/lang/String;
        45: invokevirtual #80                 // Method java/lang/StringBuilder.append:(Ljava/lang/String;)Ljava/lang/StringBuilder;
        48: invokevirtual #91                 // Method java/lang/StringBuilder.toString:()Ljava/lang/String;
        51: areturn
      StackMapTable: number_of_entries = 2
        frame_type = 97 /* same_locals_1_stack_item */
          stack = [ class java/lang/StringBuilder ]
        frame_type = 255 /* full_frame */
          offset_delta = 1
          locals = [ class coursier/parse/JavaOrScalaDependency$ScalaDependency ]
          stack = [ class java/lang/StringBuilder, class java/lang/String ]
      LineNumberTable:
        line 59: 0
      LocalVariableTable:
        Start  Length  Slot  Name   Signature
            0      52     0  this   Lcoursier/parse/JavaOrScalaDependency$ScalaDependency;

  public java.lang.String version();
    descriptor: ()Ljava/lang/String;
    flags: (0x0001) ACC_PUBLIC
    Code:
      stack=1, locals=1, args_size=1
         0: aload_0
         1: invokevirtual #49                 // Method baseDependency:()Lcoursier/core/Dependency;
         4: invokevirtual #88                 // Method coursier/core/Dependency.version:()Ljava/lang/String;
         7: areturn
      LineNumberTable:
        line 61: 0
      LocalVariableTable:
        Start  Length  Slot  Name   Signature
            0       8     0  this   Lcoursier/parse/JavaOrScalaDependency$ScalaDependency;

  public coursier.core.Dependency dependency(java.lang.String, java.lang.String, java.lang.String);
    descriptor: (Ljava/lang/String;Ljava/lang/String;Ljava/lang/String;)Lcoursier/core/Dependency;
    flags: (0x0001) ACC_PUBLIC
    Code:
      stack=3, locals=7, args_size=4
         0: aload_0
         1: invokevirtual #82                 // Method withPlatformSuffix:()Z
         4: ifeq          47
         7: getstatic     #101                // Field scala/collection/StringOps$.MODULE$:Lscala/collection/StringOps$;
        10: getstatic     #106                // Field scala/Predef$.MODULE$:Lscala/Predef$;
        13: aload_3
        14: invokevirtual #110                // Method scala/Predef$.augmentString:(Ljava/lang/String;)Ljava/lang/String;
        17: invokevirtual #114                // Method scala/collection/StringOps$.nonEmpty$extension:(Ljava/lang/String;)Z
        20: ifeq          47
        23: new           #64                 // class java/lang/StringBuilder
        26: dup
        27: ldc           #65                 // int 1
        29: invokespecial #69                 // Method java/lang/StringBuilder."<init>":(I)V
        32: ldc           #116                // String _
        34: invokevirtual #80                 // Method java/lang/StringBuilder.append:(Ljava/lang/String;)Ljava/lang/StringBuilder;
        37: aload_3
        38: invokevirtual #80                 // Method java/lang/StringBuilder.append:(Ljava/lang/String;)Ljava/lang/StringBuilder;
        41: invokevirtual #91                 // Method java/lang/StringBuilder.toString:()Ljava/lang/String;
        44: goto          49
        47: ldc           #83                 // String
        49: astore        4
        51: aload_0
        52: invokevirtual #56                 // Method fullCrossVersion:()Z
        55: ifeq          82
        58: new           #64                 // class java/lang/StringBuilder
        61: dup
        62: ldc           #65                 // int 1
        64: invokespecial #69                 // Method java/lang/StringBuilder."<init>":(I)V
        67: ldc           #116                // String _
        69: invokevirtual #80                 // Method java/lang/StringBuilder.append:(Ljava/lang/String;)Ljava/lang/StringBuilder;
        72: aload_2
        73: invokevirtual #80                 // Method java/lang/StringBuilder.append:(Ljava/lang/String;)Ljava/lang/StringBuilder;
        76: invokevirtual #91                 // Method java/lang/StringBuilder.toString:()Ljava/lang/String;
        79: goto          103
        82: new           #64                 // class java/lang/StringBuilder
        85: dup
        86: ldc           #65                 // int 1
        88: invokespecial #69                 // Method java/lang/StringBuilder."<init>":(I)V
        91: ldc           #116                // String _
        93: invokevirtual #80                 // Method java/lang/StringBuilder.append:(Ljava/lang/String;)Ljava/lang/StringBuilder;
        96: aload_1
        97: invokevirtual #80                 // Method java/lang/StringBuilder.append:(Ljava/lang/String;)Ljava/lang/StringBuilder;
       100: invokevirtual #91                 // Method java/lang/StringBuilder.toString:()Ljava/lang/String;
       103: astore        5
       105: new           #64                 // class java/lang/StringBuilder
       108: dup
       109: ldc           #117                // int 0
       111: invokespecial #69                 // Method java/lang/StringBuilder."<init>":(I)V
       114: aload_0
       115: invokevirtual #49                 // Method baseDependency:()Lcoursier/core/Dependency;
       118: invokevirtual #54                 // Method coursier/core/Dependency.module:()Lcoursier/core/Module;
       121: invokevirtual #122                // Method coursier/core/Module.name:()Ljava/lang/String;
       124: invokevirtual #80                 // Method java/lang/StringBuilder.append:(Ljava/lang/String;)Ljava/lang/StringBuilder;
       127: aload         4
       129: invokevirtual #80                 // Method java/lang/StringBuilder.append:(Ljava/lang/String;)Ljava/lang/StringBuilder;
       132: aload         5
       134: invokevirtual #80                 // Method java/lang/StringBuilder.append:(Ljava/lang/String;)Ljava/lang/StringBuilder;
       137: invokevirtual #91                 // Method java/lang/StringBuilder.toString:()Ljava/lang/String;
       140: astore        6
       142: aload_0
       143: invokevirtual #49                 // Method baseDependency:()Lcoursier/core/Dependency;
       146: aload_0
       147: invokevirtual #49                 // Method baseDependency:()Lcoursier/core/Dependency;
       150: invokevirtual #54                 // Method coursier/core/Dependency.module:()Lcoursier/core/Module;
       153: aload         6
       155: invokevirtual #126                // Method coursier/core/Module.withName:(Ljava/lang/String;)Lcoursier/core/Module;
       158: invokevirtual #130                // Method coursier/core/Dependency.withModule:(Lcoursier/core/Module;)Lcoursier/core/Dependency;
       161: areturn
      StackMapTable: number_of_entries = 4
        frame_type = 47 /* same */
        frame_type = 65 /* same_locals_1_stack_item */
          stack = [ class java/lang/String ]
        frame_type = 252 /* append */
          offset_delta = 32
          locals = [ class java/lang/String ]
        frame_type = 84 /* same_locals_1_stack_item */
          stack = [ class java/lang/String ]
      LineNumberTable:
        line 65: 0
        line 66: 47
        line 68: 51
        line 69: 82
        line 71: 105
        line 73: 142
      LocalVariableTable:
        Start  Length  Slot  Name   Signature
           51     110     4 platformSuffix   Ljava/lang/String;
          105      56     5 scalaSuffix   Ljava/lang/String;
          142      19     6 newName   Ljava/lang/String;
            0     162     0  this   Lcoursier/parse/JavaOrScalaDependency$ScalaDependency;
            0     162     1 scalaBinaryVersion   Ljava/lang/String;
            0     162     2 scalaVersion   Ljava/lang/String;
            0     162     3 platformName   Ljava/lang/String;
    MethodParameters:
      Name                           Flags
      scalaBinaryVersion             final
      scalaVersion                   final
      platformName                   final

  public coursier.parse.JavaOrScalaDependency$ScalaDependency withPlatform(java.lang.String);
    descriptor: (Ljava/lang/String;)Lcoursier/parse/JavaOrScalaDependency$ScalaDependency;
    flags: (0x0001) ACC_PUBLIC
    Code:
      stack=2, locals=2, args_size=2
         0: aload_0
         1: invokevirtual #82                 // Method withPlatformSuffix:()Z
         4: ifeq          20
         7: aload_0
         8: aload_1
         9: invokedynamic #156,  0            // InvokeDynamic #0:apply:(Ljava/lang/String;)Lscala/Function1;
        14: invokevirtual #160                // Method withUnderlyingDependency:(Lscala/Function1;)Lcoursier/parse/JavaOrScalaDependency$ScalaDependency;
        17: goto          21
        20: aload_0
        21: areturn
      StackMapTable: number_of_entries = 2
        frame_type = 20 /* same */
        frame_type = 64 /* same_locals_1_stack_item */
          stack = [ class coursier/parse/JavaOrScalaDependency$ScalaDependency ]
      LineNumberTable:
        line 77: 0
        line 78: 7
        line 86: 20
      LocalVariableTable:
        Start  Length  Slot  Name   Signature
            0      22     0  this   Lcoursier/parse/JavaOrScalaDependency$ScalaDependency;
            0      22     1 platformSuffix   Ljava/lang/String;
    MethodParameters:
      Name                           Flags
      platformSuffix                 final

  public coursier.parse.JavaOrScalaDependency$ScalaDependency addExclude(scala.collection.immutable.Seq<coursier.parse.JavaOrScalaModule>);
    descriptor: (Lscala/collection/immutable/Seq;)Lcoursier/parse/JavaOrScalaDependency$ScalaDependency;
    flags: (0x0001) ACC_PUBLIC
    Code:
      stack=3, locals=2, args_size=2
         0: aload_0
         1: aload_0
         2: invokevirtual #166                // Method exclude:()Lscala/collection/immutable/Set;
         5: aload_1
         6: invokeinterface #172,  2          // InterfaceMethod scala/collection/immutable/Set.$plus$plus:(Lscala/collection/IterableOnce;)Lscala/collection/SetOps;
        11: checkcast     #168                // class scala/collection/immutable/Set
        14: invokevirtual #176                // Method withExclude:(Lscala/collection/immutable/Set;)Lcoursier/parse/JavaOrScalaDependency$ScalaDependency;
        17: areturn
      LineNumberTable:
        line 89: 0
      LocalVariableTable:
        Start  Length  Slot  Name   Signature
            0      18     0  this   Lcoursier/parse/JavaOrScalaDependency$ScalaDependency;
            0      18     1  excl   Lscala/collection/immutable/Seq;
    Signature: #163                         // (Lscala/collection/immutable/Seq<Lcoursier/parse/JavaOrScalaModule;>;)Lcoursier/parse/JavaOrScalaDependency$ScalaDependency;
    MethodParameters:
      Name                           Flags
      excl                           final

  public coursier.parse.JavaOrScalaDependency$ScalaDependency withUnderlyingDependency(scala.Function1<coursier.core.Dependency, coursier.core.Dependency>);
    descriptor: (Lscala/Function1;)Lcoursier/parse/JavaOrScalaDependency$ScalaDependency;
    flags: (0x0001) ACC_PUBLIC
    Code:
      stack=3, locals=2, args_size=2
         0: aload_0
         1: aload_1
         2: aload_0
         3: invokevirtual #49                 // Method baseDependency:()Lcoursier/core/Dependency;
         6: invokeinterface #183,  2          // InterfaceMethod scala/Function1.apply:(Ljava/lang/Object;)Ljava/lang/Object;
        11: checkcast     #51                 // class coursier/core/Dependency
        14: invokevirtual #187                // Method withBaseDependency:(Lcoursier/core/Dependency;)Lcoursier/parse/JavaOrScalaDependency$ScalaDependency;
        17: areturn
      LineNumberTable:
        line 91: 0
      LocalVariableTable:
        Start  Length  Slot  Name   Signature
            0      18     0  this   Lcoursier/parse/JavaOrScalaDependency$ScalaDependency;
            0      18     1     f   Lscala/Function1;
    Signature: #178                         // (Lscala/Function1<Lcoursier/core/Dependency;Lcoursier/core/Dependency;>;)Lcoursier/parse/JavaOrScalaDependency$ScalaDependency;
    MethodParameters:
      Name                           Flags
      f                              final

  public coursier.parse.JavaOrScalaDependency$ScalaDependency withBaseDependency(coursier.core.Dependency);
    descriptor: (Lcoursier/core/Dependency;)Lcoursier/parse/JavaOrScalaDependency$ScalaDependency;
    flags: (0x0001) ACC_PUBLIC
    Code:
      stack=6, locals=2, args_size=2
         0: new           #2                  // class coursier/parse/JavaOrScalaDependency$ScalaDependency
         3: dup
         4: aload_1
         5: aload_0
         6: invokevirtual #56                 // Method fullCrossVersion:()Z
         9: aload_0
        10: invokevirtual #82                 // Method withPlatformSuffix:()Z
        13: aload_0
        14: invokevirtual #166                // Method exclude:()Lscala/collection/immutable/Set;
        17: invokespecial #191                // Method "<init>":(Lcoursier/core/Dependency;ZZLscala/collection/immutable/Set;)V
        20: areturn
      LineNumberTable:
        line 49: 0
      LocalVariableTable:
        Start  Length  Slot  Name   Signature
            0      21     0  this   Lcoursier/parse/JavaOrScalaDependency$ScalaDependency;
            0      21     1 baseDependency   Lcoursier/core/Dependency;
    MethodParameters:
      Name                           Flags
      baseDependency                 final

  public coursier.parse.JavaOrScalaDependency$ScalaDependency withFullCrossVersion(boolean);
    descriptor: (Z)Lcoursier/parse/JavaOrScalaDependency$ScalaDependency;
    flags: (0x0001) ACC_PUBLIC
    Code:
      stack=6, locals=2, args_size=2
         0: new           #2                  // class coursier/parse/JavaOrScalaDependency$ScalaDependency
         3: dup
         4: aload_0
         5: invokevirtual #49                 // Method baseDependency:()Lcoursier/core/Dependency;
         8: iload_1
         9: aload_0
        10: invokevirtual #82                 // Method withPlatformSuffix:()Z
        13: aload_0
        14: invokevirtual #166                // Method exclude:()Lscala/collection/immutable/Set;
        17: invokespecial #191                // Method "<init>":(Lcoursier/core/Dependency;ZZLscala/collection/immutable/Set;)V
        20: areturn
      LineNumberTable:
        line 49: 0
      LocalVariableTable:
        Start  Length  Slot  Name   Signature
            0      21     0  this   Lcoursier/parse/JavaOrScalaDependency$ScalaDependency;
            0      21     1 fullCrossVersion   Z
    MethodParameters:
      Name                           Flags
      fullCrossVersion               final

  public coursier.parse.JavaOrScalaDependency$ScalaDependency withWithPlatformSuffix(boolean);
    descriptor: (Z)Lcoursier/parse/JavaOrScalaDependency$ScalaDependency;
    flags: (0x0001) ACC_PUBLIC
    Code:
      stack=6, locals=2, args_size=2
         0: new           #2                  // class coursier/parse/JavaOrScalaDependency$ScalaDependency
         3: dup
         4: aload_0
         5: invokevirtual #49                 // Method baseDependency:()Lcoursier/core/Dependency;
         8: aload_0
         9: invokevirtual #56                 // Method fullCrossVersion:()Z
        12: iload_1
        13: aload_0
        14: invokevirtual #166                // Method exclude:()Lscala/collection/immutable/Set;
        17: invokespecial #191                // Method "<init>":(Lcoursier/core/Dependency;ZZLscala/collection/immutable/Set;)V
        20: areturn
      LineNumberTable:
        line 49: 0
      LocalVariableTable:
        Start  Length  Slot  Name   Signature
            0      21     0  this   Lcoursier/parse/JavaOrScalaDependency$ScalaDependency;
            0      21     1 withPlatformSuffix   Z
    MethodParameters:
      Name                           Flags
      withPlatformSuffix             final

  public coursier.parse.JavaOrScalaDependency$ScalaDependency withExclude(scala.collection.immutable.Set<coursier.parse.JavaOrScalaModule>);
    descriptor: (Lscala/collection/immutable/Set;)Lcoursier/parse/JavaOrScalaDependency$ScalaDependency;
    flags: (0x0001) ACC_PUBLIC
    Code:
      stack=6, locals=2, args_size=2
         0: new           #2                  // class coursier/parse/JavaOrScalaDependency$ScalaDependency
         3: dup
         4: aload_0
         5: invokevirtual #49                 // Method baseDependency:()Lcoursier/core/Dependency;
         8: aload_0
         9: invokevirtual #56                 // Method fullCrossVersion:()Z
        12: aload_0
        13: invokevirtual #82                 // Method withPlatformSuffix:()Z
        16: aload_1
        17: invokespecial #191                // Method "<init>":(Lcoursier/core/Dependency;ZZLscala/collection/immutable/Set;)V
        20: areturn
      LineNumberTable:
        line 49: 0
      LocalVariableTable:
        Start  Length  Slot  Name   Signature
            0      21     0  this   Lcoursier/parse/JavaOrScalaDependency$ScalaDependency;
            0      21     1 exclude   Lscala/collection/immutable/Set;
    Signature: #195                         // (Lscala/collection/immutable/Set<Lcoursier/parse/JavaOrScalaModule;>;)Lcoursier/parse/JavaOrScalaDependency$ScalaDependency;
    MethodParameters:
      Name                           Flags
      exclude                        final

  public java.lang.String toString();
    descriptor: ()Ljava/lang/String;
    flags: (0x0001) ACC_PUBLIC
    Code:
      stack=3, locals=2, args_size=1
         0: new           #64                 // class java/lang/StringBuilder
         3: dup
         4: ldc           #197                // String ScalaDependency(
         6: invokespecial #200                // Method java/lang/StringBuilder."<init>":(Ljava/lang/String;)V
         9: astore_1
        10: aload_1
        11: aload_0
        12: invokevirtual #49                 // Method baseDependency:()Lcoursier/core/Dependency;
        15: invokestatic  #204                // Method java/lang/String.valueOf:(Ljava/lang/Object;)Ljava/lang/String;
        18: invokevirtual #80                 // Method java/lang/StringBuilder.append:(Ljava/lang/String;)Ljava/lang/StringBuilder;
        21: pop
        22: aload_1
        23: ldc           #206                // String ,
        25: invokevirtual #80                 // Method java/lang/StringBuilder.append:(Ljava/lang/String;)Ljava/lang/StringBuilder;
        28: pop
        29: aload_1
        30: aload_0
        31: invokevirtual #56                 // Method fullCrossVersion:()Z
        34: invokestatic  #209                // Method java/lang/String.valueOf:(Z)Ljava/lang/String;
        37: invokevirtual #80                 // Method java/lang/StringBuilder.append:(Ljava/lang/String;)Ljava/lang/StringBuilder;
        40: pop
        41: aload_1
        42: ldc           #206                // String ,
        44: invokevirtual #80                 // Method java/lang/StringBuilder.append:(Ljava/lang/String;)Ljava/lang/StringBuilder;
        47: pop
        48: aload_1
        49: aload_0
        50: invokevirtual #82                 // Method withPlatformSuffix:()Z
        53: invokestatic  #209                // Method java/lang/String.valueOf:(Z)Ljava/lang/String;
        56: invokevirtual #80                 // Method java/lang/StringBuilder.append:(Ljava/lang/String;)Ljava/lang/StringBuilder;
        59: pop
        60: aload_1
        61: ldc           #206                // String ,
        63: invokevirtual #80                 // Method java/lang/StringBuilder.append:(Ljava/lang/String;)Ljava/lang/StringBuilder;
        66: pop
        67: aload_1
        68: aload_0
        69: invokevirtual #166                // Method exclude:()Lscala/collection/immutable/Set;
        72: invokestatic  #204                // Method java/lang/String.valueOf:(Ljava/lang/Object;)Ljava/lang/String;
        75: invokevirtual #80                 // Method java/lang/StringBuilder.append:(Ljava/lang/String;)Ljava/lang/StringBuilder;
        78: pop
        79: aload_1
        80: ldc           #211                // String )
        82: invokevirtual #80                 // Method java/lang/StringBuilder.append:(Ljava/lang/String;)Ljava/lang/StringBuilder;
        85: pop
        86: aload_1
        87: invokevirtual #91                 // Method java/lang/StringBuilder.toString:()Ljava/lang/String;
        90: areturn
      LineNumberTable:
        line 49: 0
      LocalVariableTable:
        Start  Length  Slot  Name   Signature
           10      80     1     b   Ljava/lang/StringBuilder;
            0      91     0  this   Lcoursier/parse/JavaOrScalaDependency$ScalaDependency;

  public boolean canEqual(java.lang.Object);
    descriptor: (Ljava/lang/Object;)Z
    flags: (0x0001) ACC_PUBLIC
    Code:
      stack=1, locals=2, args_size=2
         0: aload_1
         1: ifnull        15
         4: aload_1
         5: instanceof    #2                  // class coursier/parse/JavaOrScalaDependency$ScalaDependency
         8: ifeq          15
        11: iconst_1
        12: goto          16
        15: iconst_0
        16: ireturn
      StackMapTable: number_of_entries = 2
        frame_type = 15 /* same */
        frame_type = 64 /* same_locals_1_stack_item */
          stack = [ int ]
      LineNumberTable:
        line 49: 0
      LocalVariableTable:
        Start  Length  Slot  Name   Signature
            0      17     0  this   Lcoursier/parse/JavaOrScalaDependency$ScalaDependency;
            0      17     1   obj   Ljava/lang/Object;
    MethodParameters:
      Name                           Flags
      obj                            final

  public boolean equals(java.lang.Object);
    descriptor: (Ljava/lang/Object;)Z
    flags: (0x0001) ACC_PUBLIC
    Code:
      stack=2, locals=5, args_size=2
         0: aload_0
         1: aload_1
         2: if_acmpeq     111
         5: aload_0
         6: aload_1
         7: invokevirtual #220                // Method canEqual:(Ljava/lang/Object;)Z
        10: ifeq          115
        13: aload_1
        14: checkcast     #2                  // class coursier/parse/JavaOrScalaDependency$ScalaDependency
        17: astore_2
        18: iconst_1
        19: ifeq          107
        22: aload_0
        23: invokevirtual #49                 // Method baseDependency:()Lcoursier/core/Dependency;
        26: aload_2
        27: invokevirtual #49                 // Method baseDependency:()Lcoursier/core/Dependency;
        30: astore_3
        31: dup
        32: ifnonnull     43
        35: pop
        36: aload_3
        37: ifnull        50
        40: goto          107
        43: aload_3
        44: invokevirtual #224                // Method java/lang/Object.equals:(Ljava/lang/Object;)Z
        47: ifeq          107
        50: aload_0
        51: invokevirtual #56                 // Method fullCrossVersion:()Z
        54: aload_2
        55: invokevirtual #56                 // Method fullCrossVersion:()Z
        58: if_icmpne     107
        61: aload_0
        62: invokevirtual #82                 // Method withPlatformSuffix:()Z
        65: aload_2
        66: invokevirtual #82                 // Method withPlatformSuffix:()Z
        69: if_icmpne     107
        72: aload_0
        73: invokevirtual #166                // Method exclude:()Lscala/collection/immutable/Set;
        76: aload_2
        77: invokevirtual #166                // Method exclude:()Lscala/collection/immutable/Set;
        80: astore        4
        82: dup
        83: ifnonnull     95
        86: pop
        87: aload         4
        89: ifnull        103
        92: goto          107
        95: aload         4
        97: invokevirtual #224                // Method java/lang/Object.equals:(Ljava/lang/Object;)Z
       100: ifeq          107
       103: iconst_1
       104: goto          108
       107: iconst_0
       108: ifeq          115
       111: iconst_1
       112: goto          116
       115: iconst_0
       116: ireturn
      StackMapTable: number_of_entries = 9
        frame_type = 255 /* full_frame */
          offset_delta = 43
          locals = [ class coursier/parse/JavaOrScalaDependency$ScalaDependency, class java/lang/Object, class coursier/parse/JavaOrScalaDependency$ScalaDependency, class coursier/core/Dependency ]
          stack = [ class coursier/core/Dependency ]
        frame_type = 6 /* same */
        frame_type = 255 /* full_frame */
          offset_delta = 44
          locals = [ class coursier/parse/JavaOrScalaDependency$ScalaDependency, class java/lang/Object, class coursier/parse/JavaOrScalaDependency$ScalaDependency, class coursier/core/Dependency, class scala/collection/immutable/Set ]
          stack = [ class scala/collection/immutable/Set ]
        frame_type = 7 /* same */
        frame_type = 249 /* chop */
          offset_delta = 3
        frame_type = 64 /* same_locals_1_stack_item */
          stack = [ int ]
        frame_type = 250 /* chop */
          offset_delta = 2
        frame_type = 3 /* same */
        frame_type = 64 /* same_locals_1_stack_item */
          stack = [ int ]
      LineNumberTable:
        line 49: 0
      LocalVariableTable:
        Start  Length  Slot  Name   Signature
           18      90     2 other   Lcoursier/parse/JavaOrScalaDependency$ScalaDependency;
            0     117     0  this   Lcoursier/parse/JavaOrScalaDependency$ScalaDependency;
            0     117     1   obj   Ljava/lang/Object;
    MethodParameters:
      Name                           Flags
      obj                            final

  public int hashCode();
    descriptor: ()I
    flags: (0x0001) ACC_PUBLIC
    Code:
      stack=2, locals=2, args_size=1
         0: bipush        17
         2: ldc           #228                // String ScalaDependency
         4: invokestatic  #234                // Method scala/runtime/Statics.anyHash:(Ljava/lang/Object;)I
         7: iadd
         8: istore_1
         9: bipush        37
        11: iload_1
        12: imul
        13: aload_0
        14: invokevirtual #49                 // Method baseDependency:()Lcoursier/core/Dependency;
        17: invokestatic  #234                // Method scala/runtime/Statics.anyHash:(Ljava/lang/Object;)I
        20: iadd
        21: istore_1
        22: bipush        37
        24: iload_1
        25: imul
        26: aload_0
        27: invokevirtual #56                 // Method fullCrossVersion:()Z
        30: ifeq          39
        33: sipush        1231
        36: goto          42
        39: sipush        1237
        42: iadd
        43: istore_1
        44: bipush        37
        46: iload_1
        47: imul
        48: aload_0
        49: invokevirtual #82                 // Method withPlatformSuffix:()Z
        52: ifeq          61
        55: sipush        1231
        58: goto          64
        61: sipush        1237
        64: iadd
        65: istore_1
        66: bipush        37
        68: iload_1
        69: imul
        70: aload_0
        71: invokevirtual #166                // Method exclude:()Lscala/collection/immutable/Set;
        74: invokestatic  #234                // Method scala/runtime/Statics.anyHash:(Ljava/lang/Object;)I
        77: iadd
        78: istore_1
        79: bipush        37
        81: iload_1
        82: imul
        83: ireturn
      StackMapTable: number_of_entries = 4
        frame_type = 255 /* full_frame */
          offset_delta = 39
          locals = [ class coursier/parse/JavaOrScalaDependency$ScalaDependency, int ]
          stack = [ int ]
        frame_type = 255 /* full_frame */
          offset_delta = 2
          locals = [ class coursier/parse/JavaOrScalaDependency$ScalaDependency, int ]
          stack = [ int, int ]
        frame_type = 82 /* same_locals_1_stack_item */
          stack = [ int ]
        frame_type = 255 /* full_frame */
          offset_delta = 2
          locals = [ class coursier/parse/JavaOrScalaDependency$ScalaDependency, int ]
          stack = [ int, int ]
      LineNumberTable:
        line 49: 0
      LocalVariableTable:
        Start  Length  Slot  Name   Signature
            9      74     1  code   I
            0      84     0  this   Lcoursier/parse/JavaOrScalaDependency$ScalaDependency;

  private scala.Tuple4<coursier.core.Dependency, java.lang.Object, java.lang.Object, scala.collection.immutable.Set<coursier.parse.JavaOrScalaModule>> tuple();
    descriptor: ()Lscala/Tuple4;
    flags: (0x0002) ACC_PRIVATE
    Code:
      stack=6, locals=1, args_size=1
         0: new           #241                // class scala/Tuple4
         3: dup
         4: aload_0
         5: invokevirtual #49                 // Method baseDependency:()Lcoursier/core/Dependency;
         8: aload_0
         9: invokevirtual #56                 // Method fullCrossVersion:()Z
        12: invokestatic  #247                // Method scala/runtime/BoxesRunTime.boxToBoolean:(Z)Ljava/lang/Boolean;
        15: aload_0
        16: invokevirtual #82                 // Method withPlatformSuffix:()Z
        19: invokestatic  #247                // Method scala/runtime/BoxesRunTime.boxToBoolean:(Z)Ljava/lang/Boolean;
        22: aload_0
        23: invokevirtual #166                // Method exclude:()Lscala/collection/immutable/Set;
        26: invokespecial #250                // Method scala/Tuple4."<init>":(Ljava/lang/Object;Ljava/lang/Object;Ljava/lang/Object;Ljava/lang/Object;)V
        29: areturn
      LineNumberTable:
        line 49: 0
      LocalVariableTable:
        Start  Length  Slot  Name   Signature
            0      30     0  this   Lcoursier/parse/JavaOrScalaDependency$ScalaDependency;
    Signature: #239                         // ()Lscala/Tuple4<Lcoursier/core/Dependency;Ljava/lang/Object;Ljava/lang/Object;Lscala/collection/immutable/Set<Lcoursier/parse/JavaOrScalaModule;>;>;

  public java.lang.String productPrefix();
    descriptor: ()Ljava/lang/String;
    flags: (0x0001) ACC_PUBLIC
    Code:
      stack=1, locals=1, args_size=1
         0: ldc           #228                // String ScalaDependency
         2: areturn
      LineNumberTable:
        line 49: 0
      LocalVariableTable:
        Start  Length  Slot  Name   Signature
            0       3     0  this   Lcoursier/parse/JavaOrScalaDependency$ScalaDependency;

  public int productArity();
    descriptor: ()I
    flags: (0x0001) ACC_PUBLIC
    Code:
      stack=1, locals=1, args_size=1
         0: iconst_4
         1: ireturn
      LineNumberTable:
        line 49: 0
      LocalVariableTable:
        Start  Length  Slot  Name   Signature
            0       2     0  this   Lcoursier/parse/JavaOrScalaDependency$ScalaDependency;

  public java.lang.Object productElement(int);
    descriptor: (I)Ljava/lang/Object;
    flags: (0x0001) ACC_PUBLIC
    Code:
      stack=3, locals=3, args_size=2
         0: iload_1
         1: istore_2
         2: iload_2
         3: tableswitch   { // 0 to 3
                       0: 32
                       1: 39
                       2: 49
                       3: 59
                 default: 66
            }
        32: aload_0
        33: invokevirtual #49                 // Method baseDependency:()Lcoursier/core/Dependency;
        36: goto          81
        39: aload_0
        40: invokevirtual #56                 // Method fullCrossVersion:()Z
        43: invokestatic  #247                // Method scala/runtime/BoxesRunTime.boxToBoolean:(Z)Ljava/lang/Boolean;
        46: goto          81
        49: aload_0
        50: invokevirtual #82                 // Method withPlatformSuffix:()Z
        53: invokestatic  #247                // Method scala/runtime/BoxesRunTime.boxToBoolean:(Z)Ljava/lang/Boolean;
        56: goto          81
        59: aload_0
        60: invokevirtual #166                // Method exclude:()Lscala/collection/immutable/Set;
        63: goto          81
        66: new           #257                // class java/lang/IndexOutOfBoundsException
        69: dup
        70: iload_2
        71: invokestatic  #261                // Method scala/runtime/BoxesRunTime.boxToInteger:(I)Ljava/lang/Integer;
        74: invokevirtual #262                // Method java/lang/Object.toString:()Ljava/lang/String;
        77: invokespecial #263                // Method java/lang/IndexOutOfBoundsException."<init>":(Ljava/lang/String;)V
        80: athrow
        81: areturn
      StackMapTable: number_of_entries = 6
        frame_type = 252 /* append */
          offset_delta = 32
          locals = [ int ]
        frame_type = 6 /* same */
        frame_type = 9 /* same */
        frame_type = 9 /* same */
        frame_type = 6 /* same */
        frame_type = 78 /* same_locals_1_stack_item */
          stack = [ class java/lang/Object ]
      LineNumberTable:
        line 49: 0
      LocalVariableTable:
        Start  Length  Slot  Name   Signature
            0      82     0  this   Lcoursier/parse/JavaOrScalaDependency$ScalaDependency;
            0      82     1     n   I
    MethodParameters:
      Name                           Flags
      n                              final

  public java.lang.String productElementName(int);
    descriptor: (I)Ljava/lang/String;
    flags: (0x0001) ACC_PUBLIC
    Code:
      stack=3, locals=3, args_size=2
         0: iload_1
         1: istore_2
         2: iload_2
         3: tableswitch   { // 0 to 3
                       0: 32
                       1: 38
                       2: 44
                       3: 50
                 default: 56
            }
        32: ldc_w         #266                // String baseDependency
        35: goto          71
        38: ldc_w         #267                // String fullCrossVersion
        41: goto          71
        44: ldc_w         #268                // String withPlatformSuffix
        47: goto          71
        50: ldc_w         #269                // String exclude
        53: goto          71
        56: new           #257                // class java/lang/IndexOutOfBoundsException
        59: dup
        60: iload_2
        61: invokestatic  #261                // Method scala/runtime/BoxesRunTime.boxToInteger:(I)Ljava/lang/Integer;
        64: invokevirtual #262                // Method java/lang/Object.toString:()Ljava/lang/String;
        67: invokespecial #263                // Method java/lang/IndexOutOfBoundsException."<init>":(Ljava/lang/String;)V
        70: athrow
        71: areturn
      StackMapTable: number_of_entries = 6
        frame_type = 252 /* append */
          offset_delta = 32
          locals = [ int ]
        frame_type = 5 /* same */
        frame_type = 5 /* same */
        frame_type = 5 /* same */
        frame_type = 5 /* same */
        frame_type = 78 /* same_locals_1_stack_item */
          stack = [ class java/lang/String ]
      LineNumberTable:
        line 49: 0
      LocalVariableTable:
        Start  Length  Slot  Name   Signature
            0      72     0  this   Lcoursier/parse/JavaOrScalaDependency$ScalaDependency;
            0      72     1     n   I
    MethodParameters:
      Name                           Flags
      n                              final

  public coursier.parse.JavaOrScalaDependency withUnderlyingDependency(scala.Function1);
    descriptor: (Lscala/Function1;)Lcoursier/parse/JavaOrScalaDependency;
    flags: (0x1041) ACC_PUBLIC, ACC_BRIDGE, ACC_SYNTHETIC
    Code:
      stack=2, locals=2, args_size=2
         0: aload_0
         1: aload_1
         2: invokevirtual #160                // Method withUnderlyingDependency:(Lscala/Function1;)Lcoursier/parse/JavaOrScalaDependency$ScalaDependency;
         5: areturn
      LineNumberTable:
        line 49: 0
      LocalVariableTable:
        Start  Length  Slot  Name   Signature
            0       6     0  this   Lcoursier/parse/JavaOrScalaDependency$ScalaDependency;
            0       6     1     f   Lscala/Function1;
    MethodParameters:
      Name                           Flags
      f                              final

  public coursier.parse.JavaOrScalaDependency addExclude(scala.collection.immutable.Seq);
    descriptor: (Lscala/collection/immutable/Seq;)Lcoursier/parse/JavaOrScalaDependency;
    flags: (0x1041) ACC_PUBLIC, ACC_BRIDGE, ACC_SYNTHETIC
    Code:
      stack=2, locals=2, args_size=2
         0: aload_0
         1: aload_1
         2: invokevirtual #273                // Method addExclude:(Lscala/collection/immutable/Seq;)Lcoursier/parse/JavaOrScalaDependency$ScalaDependency;
         5: areturn
      LineNumberTable:
        line 49: 0
      LocalVariableTable:
        Start  Length  Slot  Name   Signature
            0       6     0  this   Lcoursier/parse/JavaOrScalaDependency$ScalaDependency;
            0       6     1  excl   Lscala/collection/immutable/Seq;
    MethodParameters:
      Name                           Flags
      excl                           final

  public coursier.parse.JavaOrScalaDependency withPlatform(java.lang.String);
    descriptor: (Ljava/lang/String;)Lcoursier/parse/JavaOrScalaDependency;
    flags: (0x1041) ACC_PUBLIC, ACC_BRIDGE, ACC_SYNTHETIC
    Code:
      stack=2, locals=2, args_size=2
         0: aload_0
         1: aload_1
         2: invokevirtual #276                // Method withPlatform:(Ljava/lang/String;)Lcoursier/parse/JavaOrScalaDependency$ScalaDependency;
         5: areturn
      LineNumberTable:
        line 49: 0
      LocalVariableTable:
        Start  Length  Slot  Name   Signature
            0       6     0  this   Lcoursier/parse/JavaOrScalaDependency$ScalaDependency;
            0       6     1 platformSuffix   Ljava/lang/String;
    MethodParameters:
      Name                           Flags
      platformSuffix                 final

  public coursier.parse.JavaOrScalaModule module();
    descriptor: ()Lcoursier/parse/JavaOrScalaModule;
    flags: (0x1041) ACC_PUBLIC, ACC_BRIDGE, ACC_SYNTHETIC
    Code:
      stack=1, locals=1, args_size=1
         0: aload_0
         1: invokevirtual #71                 // Method module:()Lcoursier/parse/JavaOrScalaModule$ScalaModule;
         4: areturn
      LineNumberTable:
        line 49: 0
      LocalVariableTable:
        Start  Length  Slot  Name   Signature
            0       5     0  this   Lcoursier/parse/JavaOrScalaDependency$ScalaDependency;

  public static final coursier.core.Dependency $anonfun$withPlatform$1(java.lang.String, coursier.core.Dependency);
    descriptor: (Ljava/lang/String;Lcoursier/core/Dependency;)Lcoursier/core/Dependency;
    flags: (0x1019) ACC_PUBLIC, ACC_STATIC, ACC_FINAL, ACC_SYNTHETIC
    Code:
      stack=5, locals=2, args_size=2
         0: aload_1
         1: aload_1
         2: invokevirtual #54                 // Method coursier/core/Dependency.module:()Lcoursier/core/Module;
         5: new           #64                 // class java/lang/StringBuilder
         8: dup
         9: ldc           #117                // int 0
        11: invokespecial #69                 // Method java/lang/StringBuilder."<init>":(I)V
        14: aload_1
        15: invokevirtual #54                 // Method coursier/core/Dependency.module:()Lcoursier/core/Module;
        18: invokevirtual #122                // Method coursier/core/Module.name:()Ljava/lang/String;
        21: invokevirtual #80                 // Method java/lang/StringBuilder.append:(Ljava/lang/String;)Ljava/lang/StringBuilder;
        24: aload_0
        25: invokevirtual #80                 // Method java/lang/StringBuilder.append:(Ljava/lang/String;)Ljava/lang/StringBuilder;
        28: invokevirtual #91                 // Method java/lang/StringBuilder.toString:()Ljava/lang/String;
        31: invokevirtual #126                // Method coursier/core/Module.withName:(Ljava/lang/String;)Lcoursier/core/Module;
        34: invokevirtual #130                // Method coursier/core/Dependency.withModule:(Lcoursier/core/Module;)Lcoursier/core/Dependency;
        37: areturn
      LineNumberTable:
        line 79: 0
        line 80: 1
        line 81: 5
      LocalVariableTable:
        Start  Length  Slot  Name   Signature
            0      38     0 platformSuffix$1   Ljava/lang/String;
            0      38     1   dep   Lcoursier/core/Dependency;
    MethodParameters:
      Name                           Flags
      platformSuffix$1               final
      dep                            final

  public coursier.parse.JavaOrScalaDependency$ScalaDependency(coursier.core.Dependency, boolean, boolean, scala.collection.immutable.Set<coursier.parse.JavaOrScalaModule>);
    descriptor: (Lcoursier/core/Dependency;ZZLscala/collection/immutable/Set;)V
    flags: (0x0001) ACC_PUBLIC
    Code:
      stack=2, locals=5, args_size=5
         0: aload_0
         1: aload_1
         2: putfield      #30                 // Field baseDependency:Lcoursier/core/Dependency;
         5: aload_0
         6: iload_2
         7: putfield      #35                 // Field fullCrossVersion:Z
        10: aload_0
        11: iload_3
        12: putfield      #37                 // Field withPlatformSuffix:Z
        15: aload_0
        16: aload         4
        18: putfield      #41                 // Field exclude:Lscala/collection/immutable/Set;
        21: aload_0
        22: invokespecial #283                // Method coursier/parse/JavaOrScalaDependency."<init>":()V
        25: return
      LineNumberTable:
        line 49: 0
        line 54: 21
        line 49: 25
      LocalVariableTable:
        Start  Length  Slot  Name   Signature
            0      26     0  this   Lcoursier/parse/JavaOrScalaDependency$ScalaDependency;
            0      26     1 baseDependency   Lcoursier/core/Dependency;
            0      26     2 fullCrossVersion   Z
            0      26     3 withPlatformSuffix   Z
            0      26     4 exclude   Lscala/collection/immutable/Set;
    Signature: #280                         // (Lcoursier/core/Dependency;ZZLscala/collection/immutable/Set<Lcoursier/parse/JavaOrScalaModule;>;)V
    MethodParameters:
      Name                           Flags
      baseDependency                 final
      fullCrossVersion               final
      withPlatformSuffix             final
      exclude                        final

  private static java.lang.Object $deserializeLambda$(java.lang.invoke.SerializedLambda);
    descriptor: (Ljava/lang/invoke/SerializedLambda;)Ljava/lang/Object;
    flags: (0x100a) ACC_PRIVATE, ACC_STATIC, ACC_SYNTHETIC
    Code:
      stack=1, locals=1, args_size=1
         0: aload_0
         1: invokedynamic #295,  0            // InvokeDynamic #1:lambdaDeserialize:(Ljava/lang/invoke/SerializedLambda;)Ljava/lang/Object;
         6: areturn
}
InnerClasses:
  public static final #6= #2 of #4;       // ScalaDependency=class coursier/parse/JavaOrScalaDependency$ScalaDependency of class coursier/parse/JavaOrScalaDependency
  public static final #11= #8 of #10;     // ScalaModule=class coursier/parse/JavaOrScalaModule$ScalaModule of class coursier/parse/JavaOrScalaModule
  public static #14= #13 of #10;          // =class coursier/parse/JavaOrScalaModule$ScalaModule$ of class coursier/parse/JavaOrScalaModule
  public static final #19= #16 of #18;    // Lookup=class java/lang/invoke/MethodHandles$Lookup of class java/lang/invoke/MethodHandles
SourceFile: "JavaOrScalaDependency.scala"
BootstrapMethods:
  0: #153 REF_invokeStatic java/lang/invoke/LambdaMetafactory.altMetafactory:(Ljava/lang/invoke/MethodHandles$Lookup;Ljava/lang/String;Ljava/lang/invoke/MethodType;[Ljava/lang/Object;)Ljava/lang/invoke/CallSite;
    Method arguments:
      #138 (Ljava/lang/Object;)Ljava/lang/Object;
      #143 REF_invokeStatic coursier/parse/JavaOrScalaDependency$ScalaDependency.$anonfun$withPlatform$1:(Ljava/lang/String;Lcoursier/core/Dependency;)Lcoursier/core/Dependency;
      #145 (Lcoursier/core/Dependency;)Lcoursier/core/Dependency;
      #146 5
      #65 1
      #145 (Lcoursier/core/Dependency;)Lcoursier/core/Dependency;
  1: #292 REF_invokeStatic scala/runtime/LambdaDeserialize.bootstrap:(Ljava/lang/invoke/MethodHandles$Lookup;Ljava/lang/String;Ljava/lang/invoke/MethodType;[Ljava/lang/invoke/MethodHandle;)Ljava/lang/invoke/CallSite;
    Method arguments:
      #143 REF_invokeStatic coursier/parse/JavaOrScalaDependency$ScalaDependency.$anonfun$withPlatform$1:(Ljava/lang/String;Lcoursier/core/Dependency;)Lcoursier/core/Dependency;
  ScalaInlineInfo: length = 0x9A (unknown attribute)
   01 01 00 1E 00 8C 00 8D 01 00 42 00 BE 01 00 A2
   00 A3 01 00 A2 01 10 01 00 14 00 1C 01 00 D7 00
   D8 01 00 5D 00 5E 01 00 DB 00 D8 01 00 19 00 26
   01 00 16 00 21 01 00 E3 00 E4 01 00 2A 00 2B 01
   00 2A 01 16 01 00 FD 00 E4 01 00 FE 00 FF 01 01
   09 01 0A 01 00 FC 00 3E 01 00 3D 00 3E 01 00 58
   00 3E 01 00 EE 00 EF 01 00 55 00 3E 01 00 B9 00
   BA 01 00 AE 00 AF 01 00 C1 00 C2 01 00 88 00 89
   01 00 88 01 13 01 00 18 00 21 01 00 9E 00 9F 01
   00 9E 01 0F 01 00 C3 00 C2 01
  Scala: length = 0x0 (unknown attribute)

