Classfile /Users/mw/Projects/slang-braindump/.jar/jar8/assemble/slang-braindump/assemble/content/coursier/parse/JavaOrScalaDependency.class
  Last modified May 29, 2022; size 6451 bytes
  SHA-256 checksum 742aefdfa3f10f0ef12836e0d3b27ad704af9e2ed3da2514fb7d43bd25d4a9c1
  Compiled from "JavaOrScalaDependency.scala"
public abstract class coursier.parse.JavaOrScalaDependency implements scala.Product,java.io.Serializable
  minor version: 0
  major version: 52
  flags: (0x0421) ACC_PUBLIC, ACC_SUPER, ACC_ABSTRACT
  this_class: #2                          // coursier/parse/JavaOrScalaDependency
  super_class: #4                         // java/lang/Object
  interfaces: 2, fields: 0, methods: 14, attributes: 5
Constant pool:
    #1 = Utf8               coursier/parse/JavaOrScalaDependency
    #2 = Class              #1            // coursier/parse/JavaOrScalaDependency
    #3 = Utf8               java/lang/Object
    #4 = Class              #3            // java/lang/Object
    #5 = Utf8               scala/Product
    #6 = Class              #5            // scala/Product
    #7 = Utf8               java/io/Serializable
    #8 = Class              #7            // java/io/Serializable
    #9 = Utf8               JavaOrScalaDependency.scala
   #10 = Utf8               Lscala/reflect/ScalaSignature;
   #11 = Utf8               bytes
   #12 = Utf8               \u0006\u0005\t]e!\u0002(P\u0003C!\u0006\"\u00026\u0001\t\u0003Y\u0007\"\u00028\u0001\r\u0003y\u0007\"B:\u0001\r\u0003!\b\"B?\u0001\r\u0003q\bbBA\u0003\u0001\u0019\u0005\u0011q\u0001\u0005\b\u0003\'\u0001a\u0011AA\u000b\u0011\u001d\ty\u0003\u0001D\u0001\u0003cAq!a\u000e\u0001\r\u0003\tI\u0004C\u0004\u0002\u0014\u0001!)!!\u0012\b\u000f\tUu\n#\u0001\u0002`\u00191aj\u0014E\u0001\u0003\u001bBaA[\u0006\u0005\u0002\u0005u\u0003bBA1\u0017\u0011\u0005\u00111\r\u0004\u0007\u0003\u0017Z!A!\u0014\t\u0015\u0005MaB!b\u0001\n\u0003\t)\n\u0003\u0006\u0003P9\u0011\t\u0011)A\u0005\u0003/A\u0001\" \b\u0003\u0006\u0004%\tA \u0005\n\u0003Ss!\u0011!Q\u0001\n}DaA\u001b\b\u0005\u0002\tE\u0003B\u00028\u000f\t\u0003\u00119\u0006C\u0003t\u001d\u0011\u0005A\u000fC\u0004\u0002\u00149!\tAa\u0018\t\u000f\u0005=b\u0002\"\u0001\u0003h!9\u0011Q\u0001\b\u0005\u0002\t-\u0004bBA\u001c\u001d\u0011\u0005!q\u000e\u0005\b\u0005grA\u0011\u0001B;\u0011\u001d\tyO\u0004C\u0001\u0005sBq!!>\u000f\t\u0003\n9\u0010C\u0004\u0002~:!\tE! \t\u000f\t-a\u0002\"\u0011\u0003\u0002\"9!\u0011\u0003\b\u0005B\tM\u0001b\u0002B\u000e\u001d\u0011%!Q\u0011\u0005\b\u0005KqA\u0011\tB\u0014\u0011\u001d\u0011IC\u0004C!\u0005WAqA!\f\u000f\t\u0003\u0012i\tC\u0004\u000369!\tE!%\b\u000f\u000554\u0002#\u0001\u0002p\u00199\u00111J\u0006\t\u0002\u0005M\u0004B\u00026\'\t\u0003\t)\bC\u0004\u0002b\u0019\"\t!a\u001e\t\u0013\u0005}d%!A\u0005\n\u0005\u0005eABAH\u0017\t\t\t\n\u0003\u0006\u0002\u0014*\u0012)\u0019!C\u0001\u0003+C!\"a&+\u0005\u0003\u0005\u000b\u0011BA\f\u0011)\tIJ\u000bBC\u0002\u0013\u0005\u00111\u0014\u0005\u000b\u0003GS#\u0011!Q\u0001\n\u0005u\u0005BCASU\t\u0015\r\u0011\"\u0001\u0002\u001c\"Q\u0011q\u0015\u0016\u0003\u0002\u0003\u0006I!!(\t\u0011uT#Q1A\u0005\u0002yD\u0011\"!++\u0005\u0003\u0005\u000b\u0011B@\t\r)TC\u0011AAV\u0011\u0019q\'\u0006\"\u0001\u00028\"1\u0011q\u0019\u0016\u0005\u0002QDQa\u001d\u0016\u0005\u0002QDq!a\u0005+\t\u0003\tI\rC\u0004\u00020)\"\t!!5\t\u000f\u0005\u0015!\u0006\"\u0001\u0002V\"9\u0011q\u0007\u0016\u0005\u0002\u0005e\u0007bBAoU\u0011\u0005\u0011q\u001c\u0005\b\u0003GTC\u0011AAs\u0011\u001d\tIO\u000bC\u0001\u0003WDq!a<+\t\u0003\t\t\u0010C\u0004\u0002v*\"\t%a>\t\u000f\u0005u(\u0006\"\u0011\u0002\u0000\"9!1\u0002\u0016\u0005B\t5\u0001b\u0002B\tU\u0011\u0005#1\u0003\u0005\b\u00057QC\u0011\u0002B\u000f\u0011\u001d\u0011)C\u000bC!\u0005OAqA!\u000b+\t\u0003\u0012Y\u0003C\u0004\u0003.)\"\tEa\f\t\u000f\tU\"\u0006\"\u0011\u00038\u001d9!1H\u0006\t\u0002\tubaBAH\u0017!\u0005!q\b\u0005\u0007U&#\tA!\u0011\t\u000f\u0005\u0005\u0014\n\"\u0001\u0003D!I\u0011qP%\u0002\u0002\u0013%\u0011\u0011\u0011\u0005\n\u0003\u007fZ\u0011\u0011!C\u0005\u0003\u0003\u0013QCS1wC>\u00138kY1mC\u0012+\u0007/\u001a8eK:\u001c\u0017P\u0003\u0002Q#\u0006)\u0001/\u0019:tK*\t!+\u0001\u0005d_V\u00148/[3s\u0007\u0001\u0019B\u0001A+\\=B\u0011a+W\u0007\u0002/*\t\u0001,A\u0003tG\u0006d\u0017-\u0003\u0002[/\n1\u0011I\\=SK\u001a\u0004\"A\u0016/\n\u0005u;&a\u0002)s_\u0012,8\r\u001e\t\u0003?\u001et!\u0001Y3\u000f\u0005\u0005$W\"\u00012\u000b\u0005\r\u001c\u0016A\u0002\u001fs_>$h(C\u0001Y\u0013\t1w+A\u0004qC\u000e\\\u0017mZ3\n\u0005!L\'\u0001D*fe&\fG.\u001b>bE2,\'B\u00014X\u0003\u0019a\u0014N\\5u}Q\tA\u000e\u0005\u0002n\u00015\tq*\u0001\u0004n_\u0012,H.Z\u000b\u0002aB\u0011Q.]\u0005\u0003e>\u0013\u0011CS1wC>\u00138kY1mC6{G-\u001e7f\u0003\u001d1XM]:j_:,\u0012!\u001e\t\u0003mjt!a\u001e=\u0011\u0005\u0005<\u0016BA=X\u0003\u0019\u0001&/\u001a3fM&\u00111\u0010 \u0002\u0007\'R\u0014\u0018N\\4\u000b\u0005e<\u0016aB3yG2,H-Z\u000b\u0002\u007fB!a/!\u0001q\u0013\r\t\u0019\u0001 \u0002\u0004\'\u0016$\u0018AC1eI\u0016C8\r\\;eKR\u0019A.!\u0003\t\u000f\u0005-Q\u00011\u0001\u0002\u000e\u0005!Q\r_2m!\u00111\u0016q\u00029\n\u0007\u0005EqK\u0001\u0006=e\u0016\u0004X-\u0019;fIz\n!\u0002Z3qK:$WM\\2z)!\t9\"a\t\u0002(\u0005-\u0002\u0003BA\r\u0003?i!!a\u0007\u000b\u0007\u0005u\u0011+\u0001\u0003d_J,\u0017\u0002BA\u0011\u00037\u0011!\u0002R3qK:$WM\\2z\u0011\u0019\t)C\u0002a\u0001k\u0006\u00112oY1mC\nKg.\u0019:z-\u0016\u00148/[8o\u0011\u0019\tIC\u0002a\u0001k\u0006a1oY1mCZ+\'o]5p]\"1\u0011Q\u0006\u0004A\u0002U\fA\u0002\u001d7bi\u001a|\'/\u001c(b[\u0016\fAb^5uQBc\u0017\r\u001e4pe6$2\u0001\\A\u001a\u0011\u0019\t)d\u0002a\u0001k\u0006q\u0001\u000f\\1uM>\u0014XnU;gM&D\u0018\u0001G<ji\",f\u000eZ3sYfLgn\u001a#fa\u0016tG-\u001a8dsR\u0019A.a\u000f\t\u000f\u0005u\u0002\u00021\u0001\u0002@\u0005\ta\rE\u0004W\u0003\u0003\n9\"a\u0006\n\u0007\u0005\rsKA\u0005Gk:\u001cG/[8ocQ!\u0011qCA$\u0011\u0019\tI#\u0003a\u0001k&\u001a\u0001A\u0004\u0016\u0003\u001d)\u000bg/\u0019#fa\u0016tG-\u001a8dsN!1\"VA(!\u0011\t\t&a\u0017\u000e\u0005\u0005M#\u0002BA+\u0003/\n!![8\u000b\u0005\u0005e\u0013\u0001\u00026bm\u0006L1\u0001[A*)\t\ty\u0006\u0005\u0002n\u0017\u0005)\u0011\r\u001d9msR)A.!\u001a\u0002j!1\u0011qM\u0007A\u0002A\f1!\\8e\u0011\u001d\tY\'\u0004a\u0001\u0003/\t1\u0001Z3q\u00039Q\u0015M^1EKB,g\u000eZ3oGf\u00042!!\u001d\'\u001b\u0005Y1\u0003\u0002\u0014V\u0003\u001f\"\"!a\u001c\u0015\r\u0005e\u00141PA?!\r\t\tH\u0004\u0005\b\u0003\'A\u0003\u0019AA\f\u0011\u0015i\b\u00061\u0001\u0000\u000319(/\u001b;f%\u0016\u0004H.Y2f)\t\t\u0019\t\u0005\u0003\u0002\u0006\u0006-UBAAD\u0015\u0011\tI)a\u0016\u0002\t1\fgnZ\u0005\u0005\u0003\u001b\u000b9I\u0001\u0004PE*,7\r\u001e\u0002\u0010\'\u000e\fG.\u0019#fa\u0016tG-\u001a8dsN!!\u0006\\._\u00039\u0011\u0017m]3EKB,g\u000eZ3oGf,\"!a\u0006\u0002\u001f\t\f7/\u001a#fa\u0016tG-\u001a8ds\u0002\n\u0001CZ;mY\u000e\u0013xn]:WKJ\u001c\u0018n\u001c8\u0016\u0005\u0005u\u0005c\u0001,\u0002 &\u0019\u0011\u0011U,\u0003\u000f\t{w\u000e\\3b]\u0006\tb-\u001e7m\u0007J|7o\u001d,feNLwN\u001c\u0011\u0002%]LG\u000f\u001b)mCR4wN]7Tk\u001a4\u0017\u000e_\u0001\u0014o&$\b\u000e\u00157bi\u001a|\'/\\*vM\u001aL\u0007\u0010I\u0001\tKb\u001cG.\u001e3fAQQ\u0011QVAX\u0003c\u000b\u0019,!.\u0011\u0007\u0005E$\u0006C\u0004\u0002\u0014N\u0002\r!a\u0006\t\u000f\u0005e5\u00071\u0001\u0002\u001e\"9\u0011QU\u001aA\u0002\u0005u\u0005\"B?4\u0001\u0004yXCAA]!\u0011\tY,!1\u000f\u00075\fi,C\u0002\u0002@>\u000b\u0011CS1wC>\u00138kY1mC6{G-\u001e7f\u0013\u0011\t\u0019-!2\u0003\u0017M\u001b\u0017\r\\1N_\u0012,H.\u001a\u0006\u0004\u0003\u007f{\u0015\u0001\u0002:faJ$\u0002\"a\u0006\u0002L\u00065\u0017q\u001a\u0005\u0007\u0003K9\u0004\u0019A;\t\r\u0005%r\u00071\u0001v\u0011\u0019\tic\u000ea\u0001kR!\u0011QVAj\u0011\u0019\t)\u0004\u000fa\u0001kR!\u0011QVAl\u0011\u001d\tY!\u000fa\u0001\u0003\u001b!B!!,\u0002\\\"9\u0011Q\b\u001eA\u0002\u0005}\u0012AE<ji\"\u0014\u0015m]3EKB,g\u000eZ3oGf$B!!,\u0002b\"9\u00111S\u001eA\u0002\u0005]\u0011\u0001F<ji\"4U\u000f\u001c7De>\u001c8OV3sg&|g\u000e\u0006\u0003\u0002.\u0006\u001d\bbBAMy\u0001\u0007\u0011QT\u0001\u0017o&$\bnV5uQBc\u0017\r\u001e4pe6\u001cVO\u001a4jqR!\u0011QVAw\u0011\u001d\t)+\u0010a\u0001\u0003;\u000b1b^5uQ\u0016C8\r\\;eKR!\u0011QVAz\u0011\u0015ih\b1\u0001\u0000\u0003!!xn\u0015;sS:<GCAA}!\u0011\t))a?\n\u0007m\f9)\u0001\u0005dC:,\u0015/^1m)\u0011\tiJ!\u0001\t\u000f\t\r\u0001\t1\u0001\u0003\u0006\u0005\u0019qN\u00196\u0011\u0007Y\u00139!C\u0002\u0003\n]\u00131!\u00118z\u0003\u0019)\u0017/^1mgR!\u0011Q\u0014B\b\u0011\u001d\u0011\u0019!\u0011a\u0001\u0005\u000b\t\u0001\u0002[1tQ\u000e{G-\u001a\u000b\u0003\u0005+\u00012A\u0016B\f\u0013\r\u0011Ib\u0016\u0002\u0004\u0013:$\u0018!\u0002;va2,WC\u0001B\u0010!)1&\u0011EA\f\u0003;\u000bij`\u0005\u0004\u0005G9&A\u0002+va2,G\'A\u0007qe>$Wo\u0019;Qe\u00164\u0017\u000e_\u000b\u0003\u0003s\fA\u0002\u001d:pIV\u001cG/\u0011:jif,\"A!\u0006\u0002\u001dA\u0014x\u000eZ;di\u0016cW-\\3oiR!!Q\u0001B\u0019\u0011\u001d\u0011\u0019D\u0012a\u0001\u0005+\t\u0011A\\\u0001\u0013aJ|G-^2u\u000b2,W.\u001a8u\u001d\u0006lW\r\u0006\u0003\u0002z\ne\u0002b\u0002B\u001a\u000f\u0002\u0007!QC\u0001\u0010\'\u000e\fG.\u0019#fa\u0016tG-\u001a8dsB\u0019\u0011\u0011O%\u0014\t%+\u0016q\n\u000b\u0003\u0005{!\"\"!,\u0003F\t\u001d#\u0011\nB&\u0011\u001d\t\u0019j\u0013a\u0001\u0003/Aq!!\'L\u0001\u0004\ti\nC\u0004\u0002&.\u0003\r!!(\t\u000bu\\\u0005\u0019A@\u0014\t9a7LX\u0001\fI\u0016\u0004XM\u001c3f]\u000eL\b\u0005\u0006\u0004\u0002z\tM#Q\u000b\u0005\b\u0003\'\u0019\u0002\u0019AA\f\u0011\u0015i8\u00031\u0001\u0000+\t\u0011I\u0006\u0005\u0003\u0002<\nm\u0013\u0002\u0002B/\u0003\u000b\u0014!BS1wC6{G-\u001e7f)!\t9B!\u0019\u0003d\t\u0015\u0004BBA\u0013-\u0001\u0007Q\u000f\u0003\u0004\u0002*Y\u0001\r!\u001e\u0005\u0007\u0003[1\u0002\u0019A;\u0015\t\u0005e$\u0011\u000e\u0005\u0007\u0003k9\u0002\u0019A;\u0015\t\u0005e$Q\u000e\u0005\b\u0003\u0017A\u0002\u0019AA\u0007)\u0011\tIH!\u001d\t\u000f\u0005u\u0012\u00041\u0001\u0002@\u0005qq/\u001b;i\t\u0016\u0004XM\u001c3f]\u000eLH\u0003BA=\u0005oBq!a\u0005\u001b\u0001\u0004\t9\u0002\u0006\u0003\u0002z\tm\u0004\"B?\u001c\u0001\u0004yH\u0003BAO\u0005\u007fBqAa\u0001\u001e\u0001\u0004\u0011)\u0001\u0006\u0003\u0002\u001e\n\r\u0005b\u0002B\u0002=\u0001\u0007!QA\u000b\u0003\u0005\u000f\u0003bA\u0016BE\u0003/y\u0018b\u0001BF/\n1A+\u001e9mKJ\"BA!\u0002\u0003\u0010\"9!1G\u0012A\u0002\tUA\u0003BA}\u0005\'CqAa\r%\u0001\u0004\u0011)\"A\u000bKCZ\fwJ]*dC2\fG)\u001a9f]\u0012,gnY=
   #13 = Utf8               coursier/parse/JavaOrScalaDependency$JavaDependency
   #14 = Class              #13           // coursier/parse/JavaOrScalaDependency$JavaDependency
   #15 = Utf8               JavaDependency
   #16 = Utf8               coursier/parse/JavaOrScalaDependency$JavaDependency$
   #17 = Class              #16           // coursier/parse/JavaOrScalaDependency$JavaDependency$
   #18 = Utf8
   #19 = Utf8               coursier/parse/JavaOrScalaDependency$ScalaDependency
   #20 = Class              #19           // coursier/parse/JavaOrScalaDependency$ScalaDependency
   #21 = Utf8               ScalaDependency
   #22 = Utf8               coursier/parse/JavaOrScalaDependency$ScalaDependency$
   #23 = Class              #22           // coursier/parse/JavaOrScalaDependency$ScalaDependency$
   #24 = Utf8               apply
   #25 = Utf8               (Lcoursier/parse/JavaOrScalaModule;Lcoursier/core/Dependency;)Lcoursier/parse/JavaOrScalaDependency;
   #26 = Utf8               mod
   #27 = Utf8               dep
   #28 = Utf8               coursier/parse/JavaOrScalaDependency$
   #29 = Class              #28           // coursier/parse/JavaOrScalaDependency$
   #30 = Utf8               MODULE$
   #31 = Utf8               Lcoursier/parse/JavaOrScalaDependency$;
   #32 = NameAndType        #30:#31       // MODULE$:Lcoursier/parse/JavaOrScalaDependency$;
   #33 = Fieldref           #29.#32       // coursier/parse/JavaOrScalaDependency$.MODULE$:Lcoursier/parse/JavaOrScalaDependency$;
   #34 = NameAndType        #24:#25       // apply:(Lcoursier/parse/JavaOrScalaModule;Lcoursier/core/Dependency;)Lcoursier/parse/JavaOrScalaDependency;
   #35 = Methodref          #29.#34       // coursier/parse/JavaOrScalaDependency$.apply:(Lcoursier/parse/JavaOrScalaModule;Lcoursier/core/Dependency;)Lcoursier/parse/JavaOrScalaDependency;
   #36 = Utf8               productIterator
   #37 = Utf8               ()Lscala/collection/Iterator;
   #38 = Utf8               ()Lscala/collection/Iterator<Ljava/lang/Object;>;
   #39 = Utf8               productIterator$
   #40 = Utf8               (Lscala/Product;)Lscala/collection/Iterator;
   #41 = NameAndType        #39:#40       // productIterator$:(Lscala/Product;)Lscala/collection/Iterator;
   #42 = InterfaceMethodref #6.#41        // scala/Product.productIterator$:(Lscala/Product;)Lscala/collection/Iterator;
   #43 = Utf8               this
   #44 = Utf8               Lcoursier/parse/JavaOrScalaDependency;
   #45 = Utf8               productPrefix
   #46 = Utf8               ()Ljava/lang/String;
   #47 = Utf8               productPrefix$
   #48 = Utf8               (Lscala/Product;)Ljava/lang/String;
   #49 = NameAndType        #47:#48       // productPrefix$:(Lscala/Product;)Ljava/lang/String;
   #50 = InterfaceMethodref #6.#49        // scala/Product.productPrefix$:(Lscala/Product;)Ljava/lang/String;
   #51 = Utf8               productElementName
   #52 = Utf8               (I)Ljava/lang/String;
   #53 = Utf8               n
   #54 = Utf8               productElementName$
   #55 = Utf8               (Lscala/Product;I)Ljava/lang/String;
   #56 = NameAndType        #54:#55       // productElementName$:(Lscala/Product;I)Ljava/lang/String;
   #57 = InterfaceMethodref #6.#56        // scala/Product.productElementName$:(Lscala/Product;I)Ljava/lang/String;
   #58 = Utf8               I
   #59 = Utf8               productElementNames
   #60 = Utf8               ()Lscala/collection/Iterator<Ljava/lang/String;>;
   #61 = Utf8               productElementNames$
   #62 = NameAndType        #61:#40       // productElementNames$:(Lscala/Product;)Lscala/collection/Iterator;
   #63 = InterfaceMethodref #6.#62        // scala/Product.productElementNames$:(Lscala/Product;)Lscala/collection/Iterator;
   #64 = Utf8               module
   #65 = Utf8               ()Lcoursier/parse/JavaOrScalaModule;
   #66 = Utf8               version
   #67 = Utf8               exclude
   #68 = Utf8               ()Lscala/collection/immutable/Set;
   #69 = Utf8               ()Lscala/collection/immutable/Set<Lcoursier/parse/JavaOrScalaModule;>;
   #70 = Utf8               addExclude
   #71 = Utf8               (Lscala/collection/immutable/Seq;)Lcoursier/parse/JavaOrScalaDependency;
   #72 = Utf8               (Lscala/collection/immutable/Seq<Lcoursier/parse/JavaOrScalaModule;>;)Lcoursier/parse/JavaOrScalaDependency;
   #73 = Utf8               excl
   #74 = Utf8               dependency
   #75 = Utf8               (Ljava/lang/String;Ljava/lang/String;Ljava/lang/String;)Lcoursier/core/Dependency;
   #76 = Utf8               scalaBinaryVersion
   #77 = Utf8               scalaVersion
   #78 = Utf8               platformName
   #79 = Utf8               withPlatform
   #80 = Utf8               (Ljava/lang/String;)Lcoursier/parse/JavaOrScalaDependency;
   #81 = Utf8               platformSuffix
   #82 = Utf8               withUnderlyingDependency
   #83 = Utf8               (Lscala/Function1;)Lcoursier/parse/JavaOrScalaDependency;
   #84 = Utf8               (Lscala/Function1<Lcoursier/core/Dependency;Lcoursier/core/Dependency;>;)Lcoursier/parse/JavaOrScalaDependency;
   #85 = Utf8               f
   #86 = Utf8               (Ljava/lang/String;)Lcoursier/core/Dependency;
   #87 = Utf8               coursier/parse/JavaOrScalaModule$
   #88 = Class              #87           // coursier/parse/JavaOrScalaModule$
   #89 = Utf8               Lcoursier/parse/JavaOrScalaModule$;
   #90 = NameAndType        #30:#89       // MODULE$:Lcoursier/parse/JavaOrScalaModule$;
   #91 = Fieldref           #88.#90       // coursier/parse/JavaOrScalaModule$.MODULE$:Lcoursier/parse/JavaOrScalaModule$;
   #92 = Utf8               (Ljava/lang/String;)Ljava/lang/String;
   #93 = NameAndType        #76:#92       // scalaBinaryVersion:(Ljava/lang/String;)Ljava/lang/String;
   #94 = Methodref          #88.#93       // coursier/parse/JavaOrScalaModule$.scalaBinaryVersion:(Ljava/lang/String;)Ljava/lang/String;
   #95 = String             #18           //
   #96 = NameAndType        #74:#75       // dependency:(Ljava/lang/String;Ljava/lang/String;Ljava/lang/String;)Lcoursier/core/Dependency;
   #97 = Methodref          #2.#96        // coursier/parse/JavaOrScalaDependency.dependency:(Ljava/lang/String;Ljava/lang/String;Ljava/lang/String;)Lcoursier/core/Dependency;
   #98 = Utf8               sbv
   #99 = Utf8               Ljava/lang/String;
  #100 = Utf8               <init>
  #101 = Utf8               ()V
  #102 = NameAndType        #100:#101     // "<init>":()V
  #103 = Methodref          #4.#102       // java/lang/Object."<init>":()V
  #104 = Utf8               $init$
  #105 = Utf8               (Lscala/Product;)V
  #106 = NameAndType        #104:#105     // $init$:(Lscala/Product;)V
  #107 = InterfaceMethodref #6.#106       // scala/Product.$init$:(Lscala/Product;)V
  #108 = Utf8               Code
  #109 = Utf8               MethodParameters
  #110 = Utf8               LineNumberTable
  #111 = Utf8               LocalVariableTable
  #112 = Utf8               Signature
  #113 = Utf8               InnerClasses
  #114 = Utf8               SourceFile
  #115 = Utf8               RuntimeVisibleAnnotations
  #116 = Utf8               ScalaInlineInfo
  #117 = Utf8               ScalaSig
{
  public static coursier.parse.JavaOrScalaDependency apply(coursier.parse.JavaOrScalaModule, coursier.core.Dependency);
    descriptor: (Lcoursier/parse/JavaOrScalaModule;Lcoursier/core/Dependency;)Lcoursier/parse/JavaOrScalaDependency;
    flags: (0x0009) ACC_PUBLIC, ACC_STATIC
    Code:
      stack=3, locals=2, args_size=2
         0: getstatic     #33                 // Field coursier/parse/JavaOrScalaDependency$.MODULE$:Lcoursier/parse/JavaOrScalaDependency$;
         3: aload_0
         4: aload_1
         5: invokevirtual #35                 // Method coursier/parse/JavaOrScalaDependency$.apply:(Lcoursier/parse/JavaOrScalaModule;Lcoursier/core/Dependency;)Lcoursier/parse/JavaOrScalaDependency;
         8: areturn
    MethodParameters:
      Name                           Flags
      mod                            final
      dep                            final

  public scala.collection.Iterator<java.lang.Object> productIterator();
    descriptor: ()Lscala/collection/Iterator;
    flags: (0x0001) ACC_PUBLIC
    Code:
      stack=1, locals=1, args_size=1
         0: aload_0
         1: invokestatic  #42                 // InterfaceMethod scala/Product.productIterator$:(Lscala/Product;)Lscala/collection/Iterator;
         4: areturn
      LineNumberTable:
        line 6: 0
      LocalVariableTable:
        Start  Length  Slot  Name   Signature
            0       5     0  this   Lcoursier/parse/JavaOrScalaDependency;
    Signature: #38                          // ()Lscala/collection/Iterator<Ljava/lang/Object;>;

  public java.lang.String productPrefix();
    descriptor: ()Ljava/lang/String;
    flags: (0x0001) ACC_PUBLIC
    Code:
      stack=1, locals=1, args_size=1
         0: aload_0
         1: invokestatic  #50                 // InterfaceMethod scala/Product.productPrefix$:(Lscala/Product;)Ljava/lang/String;
         4: areturn
      LineNumberTable:
        line 6: 0
      LocalVariableTable:
        Start  Length  Slot  Name   Signature
            0       5     0  this   Lcoursier/parse/JavaOrScalaDependency;

  public java.lang.String productElementName(int);
    descriptor: (I)Ljava/lang/String;
    flags: (0x0001) ACC_PUBLIC
    Code:
      stack=2, locals=2, args_size=2
         0: aload_0
         1: iload_1
         2: invokestatic  #57                 // InterfaceMethod scala/Product.productElementName$:(Lscala/Product;I)Ljava/lang/String;
         5: areturn
      LineNumberTable:
        line 6: 0
      LocalVariableTable:
        Start  Length  Slot  Name   Signature
            0       6     0  this   Lcoursier/parse/JavaOrScalaDependency;
            0       6     1     n   I
    MethodParameters:
      Name                           Flags
      n                              final

  public scala.collection.Iterator<java.lang.String> productElementNames();
    descriptor: ()Lscala/collection/Iterator;
    flags: (0x0001) ACC_PUBLIC
    Code:
      stack=1, locals=1, args_size=1
         0: aload_0
         1: invokestatic  #63                 // InterfaceMethod scala/Product.productElementNames$:(Lscala/Product;)Lscala/collection/Iterator;
         4: areturn
      LineNumberTable:
        line 6: 0
      LocalVariableTable:
        Start  Length  Slot  Name   Signature
            0       5     0  this   Lcoursier/parse/JavaOrScalaDependency;
    Signature: #60                          // ()Lscala/collection/Iterator<Ljava/lang/String;>;

  public abstract coursier.parse.JavaOrScalaModule module();
    descriptor: ()Lcoursier/parse/JavaOrScalaModule;
    flags: (0x0401) ACC_PUBLIC, ACC_ABSTRACT

  public abstract java.lang.String version();
    descriptor: ()Ljava/lang/String;
    flags: (0x0401) ACC_PUBLIC, ACC_ABSTRACT

  public abstract scala.collection.immutable.Set<coursier.parse.JavaOrScalaModule> exclude();
    descriptor: ()Lscala/collection/immutable/Set;
    flags: (0x0401) ACC_PUBLIC, ACC_ABSTRACT
    Signature: #69                          // ()Lscala/collection/immutable/Set<Lcoursier/parse/JavaOrScalaModule;>;

  public abstract coursier.parse.JavaOrScalaDependency addExclude(scala.collection.immutable.Seq<coursier.parse.JavaOrScalaModule>);
    descriptor: (Lscala/collection/immutable/Seq;)Lcoursier/parse/JavaOrScalaDependency;
    flags: (0x0401) ACC_PUBLIC, ACC_ABSTRACT
    Signature: #72                          // (Lscala/collection/immutable/Seq<Lcoursier/parse/JavaOrScalaModule;>;)Lcoursier/parse/JavaOrScalaDependency;
    MethodParameters:
      Name                           Flags
      excl                           final

  public abstract coursier.core.Dependency dependency(java.lang.String, java.lang.String, java.lang.String);
    descriptor: (Ljava/lang/String;Ljava/lang/String;Ljava/lang/String;)Lcoursier/core/Dependency;
    flags: (0x0401) ACC_PUBLIC, ACC_ABSTRACT
    MethodParameters:
      Name                           Flags
      scalaBinaryVersion             final
      scalaVersion                   final
      platformName                   final

  public abstract coursier.parse.JavaOrScalaDependency withPlatform(java.lang.String);
    descriptor: (Ljava/lang/String;)Lcoursier/parse/JavaOrScalaDependency;
    flags: (0x0401) ACC_PUBLIC, ACC_ABSTRACT
    MethodParameters:
      Name                           Flags
      platformSuffix                 final

  public abstract coursier.parse.JavaOrScalaDependency withUnderlyingDependency(scala.Function1<coursier.core.Dependency, coursier.core.Dependency>);
    descriptor: (Lscala/Function1;)Lcoursier/parse/JavaOrScalaDependency;
    flags: (0x0401) ACC_PUBLIC, ACC_ABSTRACT
    Signature: #84                          // (Lscala/Function1<Lcoursier/core/Dependency;Lcoursier/core/Dependency;>;)Lcoursier/parse/JavaOrScalaDependency;
    MethodParameters:
      Name                           Flags
      f                              final

  public final coursier.core.Dependency dependency(java.lang.String);
    descriptor: (Ljava/lang/String;)Lcoursier/core/Dependency;
    flags: (0x0011) ACC_PUBLIC, ACC_FINAL
    Code:
      stack=4, locals=3, args_size=2
         0: getstatic     #91                 // Field coursier/parse/JavaOrScalaModule$.MODULE$:Lcoursier/parse/JavaOrScalaModule$;
         3: aload_1
         4: invokevirtual #94                 // Method coursier/parse/JavaOrScalaModule$.scalaBinaryVersion:(Ljava/lang/String;)Ljava/lang/String;
         7: astore_2
         8: aload_0
         9: aload_2
        10: aload_1
        11: ldc           #95                 // String
        13: invokevirtual #97                 // Method dependency:(Ljava/lang/String;Ljava/lang/String;Ljava/lang/String;)Lcoursier/core/Dependency;
        16: areturn
      LineNumberTable:
        line 18: 0
        line 19: 8
      LocalVariableTable:
        Start  Length  Slot  Name   Signature
            8       8     2   sbv   Ljava/lang/String;
            0      17     0  this   Lcoursier/parse/JavaOrScalaDependency;
            0      17     1 scalaVersion   Ljava/lang/String;
    MethodParameters:
      Name                           Flags
      scalaVersion                   final

  public coursier.parse.JavaOrScalaDependency();
    descriptor: ()V
    flags: (0x0001) ACC_PUBLIC
    Code:
      stack=1, locals=1, args_size=1
         0: aload_0
         1: invokespecial #103                // Method java/lang/Object."<init>":()V
         4: aload_0
         5: invokestatic  #107                // InterfaceMethod scala/Product.$init$:(Lscala/Product;)V
         8: return
      LineNumberTable:
        line 6: 0
      LocalVariableTable:
        Start  Length  Slot  Name   Signature
            0       9     0  this   Lcoursier/parse/JavaOrScalaDependency;
}
InnerClasses:
  public static final #15= #14 of #2;     // JavaDependency=class coursier/parse/JavaOrScalaDependency$JavaDependency of class coursier/parse/JavaOrScalaDependency
  public static #18= #17 of #2;           // =class coursier/parse/JavaOrScalaDependency$JavaDependency$ of class coursier/parse/JavaOrScalaDependency
  public static final #21= #20 of #2;     // ScalaDependency=class coursier/parse/JavaOrScalaDependency$ScalaDependency of class coursier/parse/JavaOrScalaDependency
  public static #18= #23 of #2;           // =class coursier/parse/JavaOrScalaDependency$ScalaDependency$ of class coursier/parse/JavaOrScalaDependency
SourceFile: "JavaOrScalaDependency.scala"
RuntimeVisibleAnnotations:
  0: #10(#11=s#12)
    scala.reflect.ScalaSignature(
      bytes="\u0006\u0005\t]e!\u0002(P\u0003C!\u0006\"\u00026\u0001\t\u0003Y\u0007\"\u00028\u0001\r\u0003y\u0007\"B:\u0001\r\u0003!\b\"B?\u0001\r\u0003q\bbBA\u0003\u0001\u0019\u0005\u0011q\u0001\u0005\b\u0003\'\u0001a\u0011AA\u000b\u0011\u001d\ty\u0003\u0001D\u0001\u0003cAq!a\u000e\u0001\r\u0003\tI\u0004C\u0004\u0002\u0014\u0001!)!!\u0012\b\u000f\tUu\n#\u0001\u0002`\u00191aj\u0014E\u0001\u0003\u001bBaA[\u0006\u0005\u0002\u0005u\u0003bBA1\u0017\u0011\u0005\u00111\r\u0004\u0007\u0003\u0017Z!A!\u0014\t\u0015\u0005MaB!b\u0001\n\u0003\t)\n\u0003\u0006\u0003P9\u0011\t\u0011)A\u0005\u0003/A\u0001\" \b\u0003\u0006\u0004%\tA \u0005\n\u0003Ss!\u0011!Q\u0001\n}DaA\u001b\b\u0005\u0002\tE\u0003B\u00028\u000f\t\u0003\u00119\u0006C\u0003t\u001d\u0011\u0005A\u000fC\u0004\u0002\u00149!\tAa\u0018\t\u000f\u0005=b\u0002\"\u0001\u0003h!9\u0011Q\u0001\b\u0005\u0002\t-\u0004bBA\u001c\u001d\u0011\u0005!q\u000e\u0005\b\u0005grA\u0011\u0001B;\u0011\u001d\tyO\u0004C\u0001\u0005sBq!!>\u000f\t\u0003\n9\u0010C\u0004\u0002~:!\tE! \t\u000f\t-a\u0002\"\u0011\u0003\u0002\"9!\u0011\u0003\b\u0005B\tM\u0001b\u0002B\u000e\u001d\u0011%!Q\u0011\u0005\b\u0005KqA\u0011\tB\u0014\u0011\u001d\u0011IC\u0004C!\u0005WAqA!\f\u000f\t\u0003\u0012i\tC\u0004\u000369!\tE!%\b\u000f\u000554\u0002#\u0001\u0002p\u00199\u00111J\u0006\t\u0002\u0005M\u0004B\u00026\'\t\u0003\t)\bC\u0004\u0002b\u0019\"\t!a\u001e\t\u0013\u0005}d%!A\u0005\n\u0005\u0005eABAH\u0017\t\t\t\n\u0003\u0006\u0002\u0014*\u0012)\u0019!C\u0001\u0003+C!\"a&+\u0005\u0003\u0005\u000b\u0011BA\f\u0011)\tIJ\u000bBC\u0002\u0013\u0005\u00111\u0014\u0005\u000b\u0003GS#\u0011!Q\u0001\n\u0005u\u0005BCASU\t\u0015\r\u0011\"\u0001\u0002\u001c\"Q\u0011q\u0015\u0016\u0003\u0002\u0003\u0006I!!(\t\u0011uT#Q1A\u0005\u0002yD\u0011\"!++\u0005\u0003\u0005\u000b\u0011B@\t\r)TC\u0011AAV\u0011\u0019q\'\u0006\"\u0001\u00028\"1\u0011q\u0019\u0016\u0005\u0002QDQa\u001d\u0016\u0005\u0002QDq!a\u0005+\t\u0003\tI\rC\u0004\u00020)\"\t!!5\t\u000f\u0005\u0015!\u0006\"\u0001\u0002V\"9\u0011q\u0007\u0016\u0005\u0002\u0005e\u0007bBAoU\u0011\u0005\u0011q\u001c\u0005\b\u0003GTC\u0011AAs\u0011\u001d\tIO\u000bC\u0001\u0003WDq!a<+\t\u0003\t\t\u0010C\u0004\u0002v*\"\t%a>\t\u000f\u0005u(\u0006\"\u0011\u0002\u0000\"9!1\u0002\u0016\u0005B\t5\u0001b\u0002B\tU\u0011\u0005#1\u0003\u0005\b\u00057QC\u0011\u0002B\u000f\u0011\u001d\u0011)C\u000bC!\u0005OAqA!\u000b+\t\u0003\u0012Y\u0003C\u0004\u0003.)\"\tEa\f\t\u000f\tU\"\u0006\"\u0011\u00038\u001d9!1H\u0006\t\u0002\tubaBAH\u0017!\u0005!q\b\u0005\u0007U&#\tA!\u0011\t\u000f\u0005\u0005\u0014\n\"\u0001\u0003D!I\u0011qP%\u0002\u0002\u0013%\u0011\u0011\u0011\u0005\n\u0003\u007fZ\u0011\u0011!C\u0005\u0003\u0003\u0013QCS1wC>\u00138kY1mC\u0012+\u0007/\u001a8eK:\u001c\u0017P\u0003\u0002Q#\u0006)\u0001/\u0019:tK*\t!+\u0001\u0005d_V\u00148/[3s\u0007\u0001\u0019B\u0001A+\\=B\u0011a+W\u0007\u0002/*\t\u0001,A\u0003tG\u0006d\u0017-\u0003\u0002[/\n1\u0011I\\=SK\u001a\u0004\"A\u0016/\n\u0005u;&a\u0002)s_\u0012,8\r\u001e\t\u0003?\u001et!\u0001Y3\u000f\u0005\u0005$W\"\u00012\u000b\u0005\r\u001c\u0016A\u0002\u001fs_>$h(C\u0001Y\u0013\t1w+A\u0004qC\u000e\\\u0017mZ3\n\u0005!L\'\u0001D*fe&\fG.\u001b>bE2,\'B\u00014X\u0003\u0019a\u0014N\\5u}Q\tA\u000e\u0005\u0002n\u00015\tq*\u0001\u0004n_\u0012,H.Z\u000b\u0002aB\u0011Q.]\u0005\u0003e>\u0013\u0011CS1wC>\u00138kY1mC6{G-\u001e7f\u0003\u001d1XM]:j_:,\u0012!\u001e\t\u0003mjt!a\u001e=\u0011\u0005\u0005<\u0016BA=X\u0003\u0019\u0001&/\u001a3fM&\u00111\u0010 \u0002\u0007\'R\u0014\u0018N\\4\u000b\u0005e<\u0016aB3yG2,H-Z\u000b\u0002\u007fB!a/!\u0001q\u0013\r\t\u0019\u0001 \u0002\u0004\'\u0016$\u0018AC1eI\u0016C8\r\\;eKR\u0019A.!\u0003\t\u000f\u0005-Q\u00011\u0001\u0002\u000e\u0005!Q\r_2m!\u00111\u0016q\u00029\n\u0007\u0005EqK\u0001\u0006=e\u0016\u0004X-\u0019;fIz\n!\u0002Z3qK:$WM\\2z)!\t9\"a\t\u0002(\u0005-\u0002\u0003BA\r\u0003?i!!a\u0007\u000b\u0007\u0005u\u0011+\u0001\u0003d_J,\u0017\u0002BA\u0011\u00037\u0011!\u0002R3qK:$WM\\2z\u0011\u0019\t)C\u0002a\u0001k\u0006\u00112oY1mC\nKg.\u0019:z-\u0016\u00148/[8o\u0011\u0019\tIC\u0002a\u0001k\u0006a1oY1mCZ+\'o]5p]\"1\u0011Q\u0006\u0004A\u0002U\fA\u0002\u001d7bi\u001a|\'/\u001c(b[\u0016\fAb^5uQBc\u0017\r\u001e4pe6$2\u0001\\A\u001a\u0011\u0019\t)d\u0002a\u0001k\u0006q\u0001\u000f\\1uM>\u0014XnU;gM&D\u0018\u0001G<ji\",f\u000eZ3sYfLgn\u001a#fa\u0016tG-\u001a8dsR\u0019A.a\u000f\t\u000f\u0005u\u0002\u00021\u0001\u0002@\u0005\ta\rE\u0004W\u0003\u0003\n9\"a\u0006\n\u0007\u0005\rsKA\u0005Gk:\u001cG/[8ocQ!\u0011qCA$\u0011\u0019\tI#\u0003a\u0001k&\u001a\u0001A\u0004\u0016\u0003\u001d)\u000bg/\u0019#fa\u0016tG-\u001a8dsN!1\"VA(!\u0011\t\t&a\u0017\u000e\u0005\u0005M#\u0002BA+\u0003/\n!![8\u000b\u0005\u0005e\u0013\u0001\u00026bm\u0006L1\u0001[A*)\t\ty\u0006\u0005\u0002n\u0017\u0005)\u0011\r\u001d9msR)A.!\u001a\u0002j!1\u0011qM\u0007A\u0002A\f1!\\8e\u0011\u001d\tY\'\u0004a\u0001\u0003/\t1\u0001Z3q\u00039Q\u0015M^1EKB,g\u000eZ3oGf\u00042!!\u001d\'\u001b\u0005Y1\u0003\u0002\u0014V\u0003\u001f\"\"!a\u001c\u0015\r\u0005e\u00141PA?!\r\t\tH\u0004\u0005\b\u0003\'A\u0003\u0019AA\f\u0011\u0015i\b\u00061\u0001\u0000\u000319(/\u001b;f%\u0016\u0004H.Y2f)\t\t\u0019\t\u0005\u0003\u0002\u0006\u0006-UBAAD\u0015\u0011\tI)a\u0016\u0002\t1\fgnZ\u0005\u0005\u0003\u001b\u000b9I\u0001\u0004PE*,7\r\u001e\u0002\u0010\'\u000e\fG.\u0019#fa\u0016tG-\u001a8dsN!!\u0006\\._\u00039\u0011\u0017m]3EKB,g\u000eZ3oGf,\"!a\u0006\u0002\u001f\t\f7/\u001a#fa\u0016tG-\u001a8ds\u0002\n\u0001CZ;mY\u000e\u0013xn]:WKJ\u001c\u0018n\u001c8\u0016\u0005\u0005u\u0005c\u0001,\u0002 &\u0019\u0011\u0011U,\u0003\u000f\t{w\u000e\\3b]\u0006\tb-\u001e7m\u0007J|7o\u001d,feNLwN\u001c\u0011\u0002%]LG\u000f\u001b)mCR4wN]7Tk\u001a4\u0017\u000e_\u0001\u0014o&$\b\u000e\u00157bi\u001a|\'/\\*vM\u001aL\u0007\u0010I\u0001\tKb\u001cG.\u001e3fAQQ\u0011QVAX\u0003c\u000b\u0019,!.\u0011\u0007\u0005E$\u0006C\u0004\u0002\u0014N\u0002\r!a\u0006\t\u000f\u0005e5\u00071\u0001\u0002\u001e\"9\u0011QU\u001aA\u0002\u0005u\u0005\"B?4\u0001\u0004yXCAA]!\u0011\tY,!1\u000f\u00075\fi,C\u0002\u0002@>\u000b\u0011CS1wC>\u00138kY1mC6{G-\u001e7f\u0013\u0011\t\u0019-!2\u0003\u0017M\u001b\u0017\r\\1N_\u0012,H.\u001a\u0006\u0004\u0003\u007f{\u0015\u0001\u0002:faJ$\u0002\"a\u0006\u0002L\u00065\u0017q\u001a\u0005\u0007\u0003K9\u0004\u0019A;\t\r\u0005%r\u00071\u0001v\u0011\u0019\tic\u000ea\u0001kR!\u0011QVAj\u0011\u0019\t)\u0004\u000fa\u0001kR!\u0011QVAl\u0011\u001d\tY!\u000fa\u0001\u0003\u001b!B!!,\u0002\\\"9\u0011Q\b\u001eA\u0002\u0005}\u0012AE<ji\"\u0014\u0015m]3EKB,g\u000eZ3oGf$B!!,\u0002b\"9\u00111S\u001eA\u0002\u0005]\u0011\u0001F<ji\"4U\u000f\u001c7De>\u001c8OV3sg&|g\u000e\u0006\u0003\u0002.\u0006\u001d\bbBAMy\u0001\u0007\u0011QT\u0001\u0017o&$\bnV5uQBc\u0017\r\u001e4pe6\u001cVO\u001a4jqR!\u0011QVAw\u0011\u001d\t)+\u0010a\u0001\u0003;\u000b1b^5uQ\u0016C8\r\\;eKR!\u0011QVAz\u0011\u0015ih\b1\u0001\u0000\u0003!!xn\u0015;sS:<GCAA}!\u0011\t))a?\n\u0007m\f9)\u0001\u0005dC:,\u0015/^1m)\u0011\tiJ!\u0001\t\u000f\t\r\u0001\t1\u0001\u0003\u0006\u0005\u0019qN\u00196\u0011\u0007Y\u00139!C\u0002\u0003\n]\u00131!\u00118z\u0003\u0019)\u0017/^1mgR!\u0011Q\u0014B\b\u0011\u001d\u0011\u0019!\u0011a\u0001\u0005\u000b\t\u0001\u0002[1tQ\u000e{G-\u001a\u000b\u0003\u0005+\u00012A\u0016B\f\u0013\r\u0011Ib\u0016\u0002\u0004\u0013:$\u0018!\u0002;va2,WC\u0001B\u0010!)1&\u0011EA\f\u0003;\u000bij`\u0005\u0004\u0005G9&A\u0002+va2,G\'A\u0007qe>$Wo\u0019;Qe\u00164\u0017\u000e_\u000b\u0003\u0003s\fA\u0002\u001d:pIV\u001cG/\u0011:jif,\"A!\u0006\u0002\u001dA\u0014x\u000eZ;di\u0016cW-\\3oiR!!Q\u0001B\u0019\u0011\u001d\u0011\u0019D\u0012a\u0001\u0005+\t\u0011A\\\u0001\u0013aJ|G-^2u\u000b2,W.\u001a8u\u001d\u0006lW\r\u0006\u0003\u0002z\ne\u0002b\u0002B\u001a\u000f\u0002\u0007!QC\u0001\u0010\'\u000e\fG.\u0019#fa\u0016tG-\u001a8dsB\u0019\u0011\u0011O%\u0014\t%+\u0016q\n\u000b\u0003\u0005{!\"\"!,\u0003F\t\u001d#\u0011\nB&\u0011\u001d\t\u0019j\u0013a\u0001\u0003/Aq!!\'L\u0001\u0004\ti\nC\u0004\u0002&.\u0003\r!!(\t\u000bu\\\u0005\u0019A@\u0014\t9a7LX\u0001\fI\u0016\u0004XM\u001c3f]\u000eL\b\u0005\u0006\u0004\u0002z\tM#Q\u000b\u0005\b\u0003\'\u0019\u0002\u0019AA\f\u0011\u0015i8\u00031\u0001\u0000+\t\u0011I\u0006\u0005\u0003\u0002<\nm\u0013\u0002\u0002B/\u0003\u000b\u0014!BS1wC6{G-\u001e7f)!\t9B!\u0019\u0003d\t\u0015\u0004BBA\u0013-\u0001\u0007Q\u000f\u0003\u0004\u0002*Y\u0001\r!\u001e\u0005\u0007\u0003[1\u0002\u0019A;\u0015\t\u0005e$\u0011\u000e\u0005\u0007\u0003k9\u0002\u0019A;\u0015\t\u0005e$Q\u000e\u0005\b\u0003\u0017A\u0002\u0019AA\u0007)\u0011\tIH!\u001d\t\u000f\u0005u\u0012\u00041\u0001\u0002@\u0005qq/\u001b;i\t\u0016\u0004XM\u001c3f]\u000eLH\u0003BA=\u0005oBq!a\u0005\u001b\u0001\u0004\t9\u0002\u0006\u0003\u0002z\tm\u0004\"B?\u001c\u0001\u0004yH\u0003BAO\u0005\u007fBqAa\u0001\u001e\u0001\u0004\u0011)\u0001\u0006\u0003\u0002\u001e\n\r\u0005b\u0002B\u0002=\u0001\u0007!QA\u000b\u0003\u0005\u000f\u0003bA\u0016BE\u0003/y\u0018b\u0001BF/\n1A+\u001e9mKJ\"BA!\u0002\u0003\u0010\"9!1G\u0012A\u0002\tUA\u0003BA}\u0005\'CqAa\r%\u0001\u0004\u0011)\"A\u000bKCZ\fwJ]*dC2\fG)\u001a9f]\u0012,gnY="
    )
  ScalaInlineInfo: length = 0x45 (unknown attribute)
   01 00 00 0D 00 66 00 67 01 00 47 00 48 00 00 4B
   00 57 01 00 4B 00 4C 00 00 44 00 45 00 00 41 00
   42 00 00 34 00 35 00 00 3C 00 26 01 00 25 00 26
   01 00 2E 00 2F 00 00 43 00 2F 00 00 50 00 51 00
   00 53 00 54 00
  ScalaSig: length = 0x3 (unknown attribute)
   05 02 00
