Classfile /Users/mw/Projects/slang-braindump/.jar/jar8/assemble/slang-braindump/assemble/content/coursier/parse/RepositoryParser.class
  Last modified May 29, 2022; size 1553 bytes
  SHA-256 checksum 901d2db529bef7162f4896b5ab70b327c140e9dd10fd2683092c9777658fd3f8
  Compiled from "RepositoryParser.scala"
public final class coursier.parse.RepositoryParser
  minor version: 0
  major version: 52
  flags: (0x0031) ACC_PUBLIC, ACC_FINAL, ACC_SUPER
  this_class: #2                          // coursier/parse/RepositoryParser
  super_class: #4                         // java/lang/Object
  interfaces: 0, fields: 0, methods: 3, attributes: 3
Constant pool:
   #1 = Utf8               coursier/parse/RepositoryParser
   #2 = Class              #1             // coursier/parse/RepositoryParser
   #3 = Utf8               java/lang/Object
   #4 = Class              #3             // java/lang/Object
   #5 = Utf8               RepositoryParser.scala
   #6 = Utf8               Lscala/reflect/ScalaSignature;
   #7 = Utf8               bytes
   #8 = Utf8               \u0006\u0005u:Q\u0001B\u0003\t\u0002)1Q\u0001D\u0003\t\u00025AQ\u0001F\u0001\u0005\u0002UAQAF\u0001\u0005\u0002]\t\u0001CU3q_NLGo\u001c:z!\u0006\u00148/\u001a:\u000b\u0005\u00199\u0011!\u00029beN,\'\"\u0001\u0005\u0002\u0011\r|WO]:jKJ\u001c\u0001\u0001\u0005\u0002\f\u00035\tQA\u0001\tSKB|7/\u001b;pef\u0004\u0016M]:feN\u0011\u0011A\u0004\t\u0003\u001fIi\u0011\u0001\u0005\u0006\u0003#\u001d\t\u0001\"\u001b8uKJt\u0017\r\\\u0005\u0003\'A\u0011\u0001\u0004\u00157bi\u001a|\'/\u001c*fa>\u001c\u0018\u000e^8ssB\u000b\'o]3s\u0003\u0019a\u0014N\\5u}Q\t!\"\u0001\u0007sKB|7/\u001b;pe&,7\u000f\u0006\u0002\u0019uA!\u0011\u0004\b\u0010,\u001b\u0005Q\"BA\u000e\b\u0003\u0011)H/\u001b7\n\u0005uQ\"!\u0004,bY&$\u0017\r^5p]:+G\u000e\u0005\u0002 Q9\u0011\u0001E\n\t\u0003C\u0011j\u0011A\t\u0006\u0003G%\ta\u0001\u0010:p_Rt$\"A\u0013\u0002\u000bM\u001c\u0017\r\\1\n\u0005\u001d\"\u0013A\u0002)sK\u0012,g-\u0003\u0002*U\t11\u000b\u001e:j]\u001eT!a\n\u0013\u0011\u00071\nDG\u0004\u0002._9\u0011\u0011EL\u0005\u0002K%\u0011\u0001\u0007J\u0001\ba\u0006\u001c7.Y4f\u0013\t\u00114GA\u0002TKFT!\u0001\r\u0013\u0011\u0005UBT\"\u0001\u001c\u000b\u0005]:\u0011\u0001B2pe\u0016L!!\u000f\u001c\u0003\u0015I+\u0007o\\:ji>\u0014\u0018\u0010C\u0003<\u0007\u0001\u0007A(\u0001\u0004j]B,Ho\u001d\t\u0004YEr\u0002
   #9 = Utf8               repositories
  #10 = Utf8               (Lscala/collection/immutable/Seq;)Lcoursier/util/ValidationNel;
  #11 = Utf8               (Lscala/collection/immutable/Seq<Ljava/lang/String;>;)Lcoursier/util/ValidationNel<Ljava/lang/String;Lscala/collection/immutable/Seq<Lcoursier/core/Repository;>;>;
  #12 = Utf8               inputs
  #13 = Utf8               coursier/parse/RepositoryParser$
  #14 = Class              #13            // coursier/parse/RepositoryParser$
  #15 = Utf8               MODULE$
  #16 = Utf8               Lcoursier/parse/RepositoryParser$;
  #17 = NameAndType        #15:#16        // MODULE$:Lcoursier/parse/RepositoryParser$;
  #18 = Fieldref           #14.#17        // coursier/parse/RepositoryParser$.MODULE$:Lcoursier/parse/RepositoryParser$;
  #19 = NameAndType        #9:#10         // repositories:(Lscala/collection/immutable/Seq;)Lcoursier/util/ValidationNel;
  #20 = Methodref          #14.#19        // coursier/parse/RepositoryParser$.repositories:(Lscala/collection/immutable/Seq;)Lcoursier/util/ValidationNel;
  #21 = Utf8               repository
  #22 = Utf8               (Ljava/lang/String;Z)Lscala/util/Either;
  #23 = Utf8               (Ljava/lang/String;Z)Lscala/util/Either<Ljava/lang/String;Lcoursier/core/Repository;>;
  #24 = Utf8               input
  #25 = Utf8               maybeFile
  #26 = NameAndType        #21:#22        // repository:(Ljava/lang/String;Z)Lscala/util/Either;
  #27 = Methodref          #14.#26        // coursier/parse/RepositoryParser$.repository:(Ljava/lang/String;Z)Lscala/util/Either;
  #28 = Utf8               (Ljava/lang/String;)Lscala/util/Either;
  #29 = Utf8               (Ljava/lang/String;)Lscala/util/Either<Ljava/lang/String;Lcoursier/core/Repository;>;
  #30 = NameAndType        #21:#28        // repository:(Ljava/lang/String;)Lscala/util/Either;
  #31 = Methodref          #14.#30        // coursier/parse/RepositoryParser$.repository:(Ljava/lang/String;)Lscala/util/Either;
  #32 = Utf8               Code
  #33 = Utf8               Signature
  #34 = Utf8               MethodParameters
  #35 = Utf8               SourceFile
  #36 = Utf8               RuntimeVisibleAnnotations
  #37 = Utf8               ScalaSig
{
  public static coursier.util.ValidationNel<java.lang.String, scala.collection.immutable.Seq<coursier.core.Repository>> repositories(scala.collection.immutable.Seq<java.lang.String>);
    descriptor: (Lscala/collection/immutable/Seq;)Lcoursier/util/ValidationNel;
    flags: (0x0009) ACC_PUBLIC, ACC_STATIC
    Code:
      stack=2, locals=1, args_size=1
         0: getstatic     #18                 // Field coursier/parse/RepositoryParser$.MODULE$:Lcoursier/parse/RepositoryParser$;
         3: aload_0
         4: invokevirtual #20                 // Method coursier/parse/RepositoryParser$.repositories:(Lscala/collection/immutable/Seq;)Lcoursier/util/ValidationNel;
         7: areturn
    Signature: #11                          // (Lscala/collection/immutable/Seq<Ljava/lang/String;>;)Lcoursier/util/ValidationNel<Ljava/lang/String;Lscala/collection/immutable/Seq<Lcoursier/core/Repository;>;>;
    MethodParameters:
      Name                           Flags
      inputs                         final

  public static scala.util.Either<java.lang.String, coursier.core.Repository> repository(java.lang.String, boolean);
    descriptor: (Ljava/lang/String;Z)Lscala/util/Either;
    flags: (0x0009) ACC_PUBLIC, ACC_STATIC
    Code:
      stack=3, locals=2, args_size=2
         0: getstatic     #18                 // Field coursier/parse/RepositoryParser$.MODULE$:Lcoursier/parse/RepositoryParser$;
         3: aload_0
         4: iload_1
         5: invokevirtual #27                 // Method coursier/parse/RepositoryParser$.repository:(Ljava/lang/String;Z)Lscala/util/Either;
         8: areturn
    Signature: #23                          // (Ljava/lang/String;Z)Lscala/util/Either<Ljava/lang/String;Lcoursier/core/Repository;>;
    MethodParameters:
      Name                           Flags
      input                          final
      maybeFile                      final

  public static scala.util.Either<java.lang.String, coursier.core.Repository> repository(java.lang.String);
    descriptor: (Ljava/lang/String;)Lscala/util/Either;
    flags: (0x0009) ACC_PUBLIC, ACC_STATIC
    Code:
      stack=2, locals=1, args_size=1
         0: getstatic     #18                 // Field coursier/parse/RepositoryParser$.MODULE$:Lcoursier/parse/RepositoryParser$;
         3: aload_0
         4: invokevirtual #31                 // Method coursier/parse/RepositoryParser$.repository:(Ljava/lang/String;)Lscala/util/Either;
         7: areturn
    Signature: #29                          // (Ljava/lang/String;)Lscala/util/Either<Ljava/lang/String;Lcoursier/core/Repository;>;
    MethodParameters:
      Name                           Flags
      input                          final
}
SourceFile: "RepositoryParser.scala"
RuntimeVisibleAnnotations:
  0: #6(#7=s#8)
    scala.reflect.ScalaSignature(
      bytes="\u0006\u0005u:Q\u0001B\u0003\t\u0002)1Q\u0001D\u0003\t\u00025AQ\u0001F\u0001\u0005\u0002UAQAF\u0001\u0005\u0002]\t\u0001CU3q_NLGo\u001c:z!\u0006\u00148/\u001a:\u000b\u0005\u00199\u0011!\u00029beN,\'\"\u0001\u0005\u0002\u0011\r|WO]:jKJ\u001c\u0001\u0001\u0005\u0002\f\u00035\tQA\u0001\tSKB|7/\u001b;pef\u0004\u0016M]:feN\u0011\u0011A\u0004\t\u0003\u001fIi\u0011\u0001\u0005\u0006\u0003#\u001d\t\u0001\"\u001b8uKJt\u0017\r\\\u0005\u0003\'A\u0011\u0001\u0004\u00157bi\u001a|\'/\u001c*fa>\u001c\u0018\u000e^8ssB\u000b\'o]3s\u0003\u0019a\u0014N\\5u}Q\t!\"\u0001\u0007sKB|7/\u001b;pe&,7\u000f\u0006\u0002\u0019uA!\u0011\u0004\b\u0010,\u001b\u0005Q\"BA\u000e\b\u0003\u0011)H/\u001b7\n\u0005uQ\"!\u0004,bY&$\u0017\r^5p]:+G\u000e\u0005\u0002 Q9\u0011\u0001E\n\t\u0003C\u0011j\u0011A\t\u0006\u0003G%\ta\u0001\u0010:p_Rt$\"A\u0013\u0002\u000bM\u001c\u0017\r\\1\n\u0005\u001d\"\u0013A\u0002)sK\u0012,g-\u0003\u0002*U\t11\u000b\u001e:j]\u001eT!a\n\u0013\u0011\u00071\nDG\u0004\u0002._9\u0011\u0011EL\u0005\u0002K%\u0011\u0001\u0007J\u0001\ba\u0006\u001c7.Y4f\u0013\t\u00114GA\u0002TKFT!\u0001\r\u0013\u0011\u0005UBT\"\u0001\u001c\u000b\u0005]:\u0011\u0001B2pe\u0016L!!\u000f\u001c\u0003\u0015I+\u0007o\\:ji>\u0014\u0018\u0010C\u0003<\u0007\u0001\u0007A(\u0001\u0004j]B,Ho\u001d\t\u0004YEr\u0002"
    )
  ScalaSig: length = 0x3 (unknown attribute)
   05 02 00
