Classfile /Users/mw/Projects/slang-braindump/.jar/jar8/assemble/slang-braindump/assemble/content/coursier/parse/RuleParser.class
  Last modified May 29, 2022; size 2253 bytes
  SHA-256 checksum 2cc74cf9acfd7ad5dca98cf6aede9756ec66140051522aa661da4c0621417409
  Compiled from "RuleParser.scala"
public final class coursier.parse.RuleParser
  minor version: 0
  major version: 52
  flags: (0x0031) ACC_PUBLIC, ACC_FINAL, ACC_SUPER
  this_class: #2                          // coursier/parse/RuleParser
  super_class: #4                         // java/lang/Object
  interfaces: 0, fields: 0, methods: 4, attributes: 3
Constant pool:
   #1 = Utf8               coursier/parse/RuleParser
   #2 = Class              #1             // coursier/parse/RuleParser
   #3 = Utf8               java/lang/Object
   #4 = Class              #3             // java/lang/Object
   #5 = Utf8               RuleParser.scala
   #6 = Utf8               Lscala/reflect/ScalaSignature;
   #7 = Utf8               bytes
   #8 = Utf8               \u0006\u0005I<Q!\u0003\u0006\t\u0002=1Q!\u0005\u0006\t\u0002IAQ!G\u0001\u0005\u0002iAQaG\u0001\u0005\nqAQ!S\u0001\u0005\n)CQaM\u0001\u0005\u0002iCQaM\u0001\u0005\u0002!DQa[\u0001\u0005\u00021DQa[\u0001\u0005\u0002=\f!BU;mKB\u000b\'o]3s\u0015\tYA\"A\u0003qCJ\u001cXMC\u0001\u000e\u0003!\u0019w.\u001e:tS\u0016\u00148\u0001\u0001\t\u0003!\u0005i\u0011A\u0003\u0002\u000b%VdW\rU1sg\u0016\u00148CA\u0001\u0014!\t!r#D\u0001\u0016\u0015\u00051\u0012!B:dC2\f\u0017B\u0001\r\u0016\u0005\u0019\te.\u001f*fM\u00061A(\u001b8jiz\"\u0012aD\u0001\u000beVdW\rU1sg\u0016\u0014XCA\u000fD)\tq\u0012\t\u0006\u0002 wA\u0019\u0001EK\u0017\u000f\u0005\u0005:cB\u0001\u0012&\u001b\u0005\u0019#B\u0001\u0013\u000f\u0003\u0019a$o\\8u}%\ta%A\u0005gCN$\b/\u0019:tK&\u0011\u0001&K\u0001\ba\u0006\u001c7.Y4f\u0015\u00051\u0013BA\u0016-\u0005\u0005\u0001&B\u0001\u0015*!\u0011!b\u0006\r\u001d\n\u0005=*\"A\u0002+va2,\'\u0007\u0005\u00022m5\t!G\u0003\u00024i\u0005!!/\u001e7f\u0015\t)D\"\u0001\u0004qCJ\fWn]\u0005\u0003oI\u0012AAU;mKB\u0011\u0011\'O\u0005\u0003uI\u0012aBU;mKJ+7o\u001c7vi&|g\u000eC\u0004=\u0007\u0005\u0005\t9A\u001f\u0002\u0015\u00154\u0018\u000eZ3oG\u0016$\u0013\u0007E\u0002!Uy\u0002\"\u0001F \n\u0005\u0001+\"aA!os\")!i\u0001a\u0001q\u0005\tB-\u001a4bk2$(+Z:pYV$\u0018n\u001c8\u0005\u000b\u0011\u001b!\u0019A#\u0003\u0003}\u000b\"A\u0012 \u0011\u0005Q9\u0015B\u0001%\u0016\u0005\u001dqu\u000e\u001e5j]\u001e\f1B];mKN\u0004\u0016M]:feV\u00111*\u0017\u000b\u0003\u0019b#\"!\u0014,\u0011\u0007\u0001Rc\nE\u0002P\'6r!\u0001\u0015*\u000f\u0005\t\n\u0016\"\u0001\f\n\u0005!*\u0012B\u0001+V\u0005\r\u0019V-\u001d\u0006\u0003QUAqa\u0016\u0003\u0002\u0002\u0003\u000fQ(\u0001\u0006fm&$WM\\2fIIBQA\u0011\u0003A\u0002a\"Q\u0001\u0012\u0003C\u0002\u0015#\"a\u00174\u0011\t=cf,L\u0005\u0003;V\u0013a!R5uQ\u0016\u0014\bCA0d\u001d\t\u0001\u0017\r\u0005\u0002#+%\u0011!-F\u0001\u0007!J,G-\u001a4\n\u0005\u0011,\'AB*ue&twM\u0003\u0002c+!)q-\u0002a\u0001=\u0006)\u0011N\u001c9viR\u00191,\u001b6\t\u000b\u001d4\u0001\u0019\u00010\t\u000b\t3\u0001\u0019\u0001\u001d\u0002\u000bI,H.Z:\u0015\u00055t\u0007\u0003B(]=:CQaZ\u0004A\u0002y#2!\u001c9r\u0011\u00159\u0007\u00021\u0001_\u0011\u0015\u0011\u0005\u00021\u00019\u0001
   #9 = Utf8               rules
  #10 = Utf8               (Ljava/lang/String;Lcoursier/params/rule/RuleResolution;)Lscala/util/Either;
  #11 = Utf8               (Ljava/lang/String;Lcoursier/params/rule/RuleResolution;)Lscala/util/Either<Ljava/lang/String;Lscala/collection/immutable/Seq<Lscala/Tuple2<Lcoursier/params/rule/Rule;Lcoursier/params/rule/RuleResolution;>;>;>;
  #12 = Utf8               input
  #13 = Utf8               defaultResolution
  #14 = Utf8               coursier/parse/RuleParser$
  #15 = Class              #14            // coursier/parse/RuleParser$
  #16 = Utf8               MODULE$
  #17 = Utf8               Lcoursier/parse/RuleParser$;
  #18 = NameAndType        #16:#17        // MODULE$:Lcoursier/parse/RuleParser$;
  #19 = Fieldref           #15.#18        // coursier/parse/RuleParser$.MODULE$:Lcoursier/parse/RuleParser$;
  #20 = NameAndType        #9:#10         // rules:(Ljava/lang/String;Lcoursier/params/rule/RuleResolution;)Lscala/util/Either;
  #21 = Methodref          #15.#20        // coursier/parse/RuleParser$.rules:(Ljava/lang/String;Lcoursier/params/rule/RuleResolution;)Lscala/util/Either;
  #22 = Utf8               (Ljava/lang/String;)Lscala/util/Either;
  #23 = Utf8               (Ljava/lang/String;)Lscala/util/Either<Ljava/lang/String;Lscala/collection/immutable/Seq<Lscala/Tuple2<Lcoursier/params/rule/Rule;Lcoursier/params/rule/RuleResolution;>;>;>;
  #24 = NameAndType        #9:#22         // rules:(Ljava/lang/String;)Lscala/util/Either;
  #25 = Methodref          #15.#24        // coursier/parse/RuleParser$.rules:(Ljava/lang/String;)Lscala/util/Either;
  #26 = Utf8               rule
  #27 = Utf8               (Ljava/lang/String;Lcoursier/params/rule/RuleResolution;)Lscala/util/Either<Ljava/lang/String;Lscala/Tuple2<Lcoursier/params/rule/Rule;Lcoursier/params/rule/RuleResolution;>;>;
  #28 = NameAndType        #26:#10        // rule:(Ljava/lang/String;Lcoursier/params/rule/RuleResolution;)Lscala/util/Either;
  #29 = Methodref          #15.#28        // coursier/parse/RuleParser$.rule:(Ljava/lang/String;Lcoursier/params/rule/RuleResolution;)Lscala/util/Either;
  #30 = Utf8               (Ljava/lang/String;)Lscala/util/Either<Ljava/lang/String;Lscala/Tuple2<Lcoursier/params/rule/Rule;Lcoursier/params/rule/RuleResolution;>;>;
  #31 = NameAndType        #26:#22        // rule:(Ljava/lang/String;)Lscala/util/Either;
  #32 = Methodref          #15.#31        // coursier/parse/RuleParser$.rule:(Ljava/lang/String;)Lscala/util/Either;
  #33 = Utf8               Code
  #34 = Utf8               Signature
  #35 = Utf8               MethodParameters
  #36 = Utf8               SourceFile
  #37 = Utf8               RuntimeVisibleAnnotations
  #38 = Utf8               ScalaSig
{
  public static scala.util.Either<java.lang.String, scala.collection.immutable.Seq<scala.Tuple2<coursier.params.rule.Rule, coursier.params.rule.RuleResolution>>> rules(java.lang.String, coursier.params.rule.RuleResolution);
    descriptor: (Ljava/lang/String;Lcoursier/params/rule/RuleResolution;)Lscala/util/Either;
    flags: (0x0009) ACC_PUBLIC, ACC_STATIC
    Code:
      stack=3, locals=2, args_size=2
         0: getstatic     #19                 // Field coursier/parse/RuleParser$.MODULE$:Lcoursier/parse/RuleParser$;
         3: aload_0
         4: aload_1
         5: invokevirtual #21                 // Method coursier/parse/RuleParser$.rules:(Ljava/lang/String;Lcoursier/params/rule/RuleResolution;)Lscala/util/Either;
         8: areturn
    Signature: #11                          // (Ljava/lang/String;Lcoursier/params/rule/RuleResolution;)Lscala/util/Either<Ljava/lang/String;Lscala/collection/immutable/Seq<Lscala/Tuple2<Lcoursier/params/rule/Rule;Lcoursier/params/rule/RuleResolution;>;>;>;
    MethodParameters:
      Name                           Flags
      input                          final
      defaultResolution              final

  public static scala.util.Either<java.lang.String, scala.collection.immutable.Seq<scala.Tuple2<coursier.params.rule.Rule, coursier.params.rule.RuleResolution>>> rules(java.lang.String);
    descriptor: (Ljava/lang/String;)Lscala/util/Either;
    flags: (0x0009) ACC_PUBLIC, ACC_STATIC
    Code:
      stack=2, locals=1, args_size=1
         0: getstatic     #19                 // Field coursier/parse/RuleParser$.MODULE$:Lcoursier/parse/RuleParser$;
         3: aload_0
         4: invokevirtual #25                 // Method coursier/parse/RuleParser$.rules:(Ljava/lang/String;)Lscala/util/Either;
         7: areturn
    Signature: #23                          // (Ljava/lang/String;)Lscala/util/Either<Ljava/lang/String;Lscala/collection/immutable/Seq<Lscala/Tuple2<Lcoursier/params/rule/Rule;Lcoursier/params/rule/RuleResolution;>;>;>;
    MethodParameters:
      Name                           Flags
      input                          final

  public static scala.util.Either<java.lang.String, scala.Tuple2<coursier.params.rule.Rule, coursier.params.rule.RuleResolution>> rule(java.lang.String, coursier.params.rule.RuleResolution);
    descriptor: (Ljava/lang/String;Lcoursier/params/rule/RuleResolution;)Lscala/util/Either;
    flags: (0x0009) ACC_PUBLIC, ACC_STATIC
    Code:
      stack=3, locals=2, args_size=2
         0: getstatic     #19                 // Field coursier/parse/RuleParser$.MODULE$:Lcoursier/parse/RuleParser$;
         3: aload_0
         4: aload_1
         5: invokevirtual #29                 // Method coursier/parse/RuleParser$.rule:(Ljava/lang/String;Lcoursier/params/rule/RuleResolution;)Lscala/util/Either;
         8: areturn
    Signature: #27                          // (Ljava/lang/String;Lcoursier/params/rule/RuleResolution;)Lscala/util/Either<Ljava/lang/String;Lscala/Tuple2<Lcoursier/params/rule/Rule;Lcoursier/params/rule/RuleResolution;>;>;
    MethodParameters:
      Name                           Flags
      input                          final
      defaultResolution              final

  public static scala.util.Either<java.lang.String, scala.Tuple2<coursier.params.rule.Rule, coursier.params.rule.RuleResolution>> rule(java.lang.String);
    descriptor: (Ljava/lang/String;)Lscala/util/Either;
    flags: (0x0009) ACC_PUBLIC, ACC_STATIC
    Code:
      stack=2, locals=1, args_size=1
         0: getstatic     #19                 // Field coursier/parse/RuleParser$.MODULE$:Lcoursier/parse/RuleParser$;
         3: aload_0
         4: invokevirtual #32                 // Method coursier/parse/RuleParser$.rule:(Ljava/lang/String;)Lscala/util/Either;
         7: areturn
    Signature: #30                          // (Ljava/lang/String;)Lscala/util/Either<Ljava/lang/String;Lscala/Tuple2<Lcoursier/params/rule/Rule;Lcoursier/params/rule/RuleResolution;>;>;
    MethodParameters:
      Name                           Flags
      input                          final
}
SourceFile: "RuleParser.scala"
RuntimeVisibleAnnotations:
  0: #6(#7=s#8)
    scala.reflect.ScalaSignature(
      bytes="\u0006\u0005I<Q!\u0003\u0006\t\u0002=1Q!\u0005\u0006\t\u0002IAQ!G\u0001\u0005\u0002iAQaG\u0001\u0005\nqAQ!S\u0001\u0005\n)CQaM\u0001\u0005\u0002iCQaM\u0001\u0005\u0002!DQa[\u0001\u0005\u00021DQa[\u0001\u0005\u0002=\f!BU;mKB\u000b\'o]3s\u0015\tYA\"A\u0003qCJ\u001cXMC\u0001\u000e\u0003!\u0019w.\u001e:tS\u0016\u00148\u0001\u0001\t\u0003!\u0005i\u0011A\u0003\u0002\u000b%VdW\rU1sg\u0016\u00148CA\u0001\u0014!\t!r#D\u0001\u0016\u0015\u00051\u0012!B:dC2\f\u0017B\u0001\r\u0016\u0005\u0019\te.\u001f*fM\u00061A(\u001b8jiz\"\u0012aD\u0001\u000beVdW\rU1sg\u0016\u0014XCA\u000fD)\tq\u0012\t\u0006\u0002 wA\u0019\u0001EK\u0017\u000f\u0005\u0005:cB\u0001\u0012&\u001b\u0005\u0019#B\u0001\u0013\u000f\u0003\u0019a$o\\8u}%\ta%A\u0005gCN$\b/\u0019:tK&\u0011\u0001&K\u0001\ba\u0006\u001c7.Y4f\u0015\u00051\u0013BA\u0016-\u0005\u0005\u0001&B\u0001\u0015*!\u0011!b\u0006\r\u001d\n\u0005=*\"A\u0002+va2,\'\u0007\u0005\u00022m5\t!G\u0003\u00024i\u0005!!/\u001e7f\u0015\t)D\"\u0001\u0004qCJ\fWn]\u0005\u0003oI\u0012AAU;mKB\u0011\u0011\'O\u0005\u0003uI\u0012aBU;mKJ+7o\u001c7vi&|g\u000eC\u0004=\u0007\u0005\u0005\t9A\u001f\u0002\u0015\u00154\u0018\u000eZ3oG\u0016$\u0013\u0007E\u0002!Uy\u0002\"\u0001F \n\u0005\u0001+\"aA!os\")!i\u0001a\u0001q\u0005\tB-\u001a4bk2$(+Z:pYV$\u0018n\u001c8\u0005\u000b\u0011\u001b!\u0019A#\u0003\u0003}\u000b\"A\u0012 \u0011\u0005Q9\u0015B\u0001%\u0016\u0005\u001dqu\u000e\u001e5j]\u001e\f1B];mKN\u0004\u0016M]:feV\u00111*\u0017\u000b\u0003\u0019b#\"!\u0014,\u0011\u0007\u0001Rc\nE\u0002P\'6r!\u0001\u0015*\u000f\u0005\t\n\u0016\"\u0001\f\n\u0005!*\u0012B\u0001+V\u0005\r\u0019V-\u001d\u0006\u0003QUAqa\u0016\u0003\u0002\u0002\u0003\u000fQ(\u0001\u0006fm&$WM\\2fIIBQA\u0011\u0003A\u0002a\"Q\u0001\u0012\u0003C\u0002\u0015#\"a\u00174\u0011\t=cf,L\u0005\u0003;V\u0013a!R5uQ\u0016\u0014\bCA0d\u001d\t\u0001\u0017\r\u0005\u0002#+%\u0011!-F\u0001\u0007!J,G-\u001a4\n\u0005\u0011,\'AB*ue&twM\u0003\u0002c+!)q-\u0002a\u0001=\u0006)\u0011N\u001c9viR\u00191,\u001b6\t\u000b\u001d4\u0001\u0019\u00010\t\u000b\t3\u0001\u0019\u0001\u001d\u0002\u000bI,H.Z:\u0015\u00055t\u0007\u0003B(]=:CQaZ\u0004A\u0002y#2!\u001c9r\u0011\u00159\u0007\u00021\u0001_\u0011\u0015\u0011\u0005\u00021\u00019\u0001"
    )
  ScalaSig: length = 0x3 (unknown attribute)
   05 02 00
