Classfile /Users/mw/Projects/slang-braindump/.jar/jar11/assemble/slang-braindump/assemble/content/coursier/error/ResolutionError$CantDownloadModule.class
  Last modified May 29, 2022; size 2437 bytes
  SHA-256 checksum b3867d055796fb0caa927a4fb2d5580a7b2e730ead3a314be80611b48c998b40
  Compiled from "ResolutionError.scala"
public final class coursier.error.ResolutionError$CantDownloadModule extends coursier.error.ResolutionError$Simple
  minor version: 0
  major version: 52
  flags: (0x0031) ACC_PUBLIC, ACC_FINAL, ACC_SUPER
  this_class: #2                          // coursier/error/ResolutionError$CantDownloadModule
  super_class: #4                         // coursier/error/ResolutionError$Simple
  interfaces: 0, fields: 3, methods: 4, attributes: 4
Constant pool:
    #1 = Utf8               coursier/error/ResolutionError$CantDownloadModule
    #2 = Class              #1            // coursier/error/ResolutionError$CantDownloadModule
    #3 = Utf8               coursier/error/ResolutionError$Simple
    #4 = Class              #3            // coursier/error/ResolutionError$Simple
    #5 = Utf8               ResolutionError.scala
    #6 = Utf8               coursier/error/ResolutionError
    #7 = Class              #6            // coursier/error/ResolutionError
    #8 = Utf8               CantDownloadModule
    #9 = Utf8               coursier/error/ResolutionError$CantDownloadModule$$anonfun$$lessinit$greater$1
   #10 = Class              #9            // coursier/error/ResolutionError$CantDownloadModule$$anonfun$$lessinit$greater$1
   #11 = Utf8               Simple
   #12 = Utf8               coursier/error/ResolutionError$Simple$
   #13 = Class              #12           // coursier/error/ResolutionError$Simple$
   #14 = Utf8
   #15 = Utf8               module
   #16 = Utf8               Lcoursier/core/Module;
   #17 = Utf8               version
   #18 = Utf8               Ljava/lang/String;
   #19 = Utf8               perRepositoryErrors
   #20 = Utf8               Lscala/collection/immutable/Seq;
   #21 = Utf8               Lscala/collection/immutable/Seq<Ljava/lang/String;>;
   #22 = Utf8               ()Lcoursier/core/Module;
   #23 = NameAndType        #15:#16       // module:Lcoursier/core/Module;
   #24 = Fieldref           #2.#23        // coursier/error/ResolutionError$CantDownloadModule.module:Lcoursier/core/Module;
   #25 = Utf8               this
   #26 = Utf8               Lcoursier/error/ResolutionError$CantDownloadModule;
   #27 = Utf8               ()Ljava/lang/String;
   #28 = NameAndType        #17:#18       // version:Ljava/lang/String;
   #29 = Fieldref           #2.#28        // coursier/error/ResolutionError$CantDownloadModule.version:Ljava/lang/String;
   #30 = Utf8               ()Lscala/collection/immutable/Seq;
   #31 = Utf8               ()Lscala/collection/immutable/Seq<Ljava/lang/String;>;
   #32 = NameAndType        #19:#20       // perRepositoryErrors:Lscala/collection/immutable/Seq;
   #33 = Fieldref           #2.#32        // coursier/error/ResolutionError$CantDownloadModule.perRepositoryErrors:Lscala/collection/immutable/Seq;
   #34 = Utf8               <init>
   #35 = Utf8               (Lcoursier/core/Resolution;Lcoursier/core/Module;Ljava/lang/String;Lscala/collection/immutable/Seq;)V
   #36 = Utf8               (Lcoursier/core/Resolution;Lcoursier/core/Module;Ljava/lang/String;Lscala/collection/immutable/Seq<Ljava/lang/String;>;)V
   #37 = Utf8               resolution
   #38 = Utf8               java/lang/StringBuilder
   #39 = Class              #38           // java/lang/StringBuilder
   #40 = Integer            0
   #41 = Utf8               (I)V
   #42 = NameAndType        #34:#41       // "<init>":(I)V
   #43 = Methodref          #39.#42       // java/lang/StringBuilder."<init>":(I)V
   #44 = Integer            19
   #45 = Utf8               Error downloading
   #46 = String             #45           // Error downloading
   #47 = Utf8               append
   #48 = Utf8               (Ljava/lang/String;)Ljava/lang/StringBuilder;
   #49 = NameAndType        #47:#48       // append:(Ljava/lang/String;)Ljava/lang/StringBuilder;
   #50 = Methodref          #39.#49       // java/lang/StringBuilder.append:(Ljava/lang/String;)Ljava/lang/StringBuilder;
   #51 = Utf8               (Ljava/lang/Object;)Ljava/lang/StringBuilder;
   #52 = NameAndType        #47:#51       // append:(Ljava/lang/Object;)Ljava/lang/StringBuilder;
   #53 = Methodref          #39.#52       // java/lang/StringBuilder.append:(Ljava/lang/Object;)Ljava/lang/StringBuilder;
   #54 = Utf8               :
   #55 = String             #54           // :
   #56 = Utf8               toString
   #57 = NameAndType        #56:#27       // toString:()Ljava/lang/String;
   #58 = Methodref          #39.#57       // java/lang/StringBuilder.toString:()Ljava/lang/String;
   #59 = Utf8               java/lang/System
   #60 = Class              #59           // java/lang/System
   #61 = Utf8               lineSeparator
   #62 = NameAndType        #61:#27       // lineSeparator:()Ljava/lang/String;
   #63 = Methodref          #60.#62       // java/lang/System.lineSeparator:()Ljava/lang/String;
   #64 = Utf8               ()V
   #65 = NameAndType        #34:#64       // "<init>":()V
   #66 = Methodref          #10.#65       // coursier/error/ResolutionError$CantDownloadModule$$anonfun$$lessinit$greater$1."<init>":()V
   #67 = Utf8               scala/collection/immutable/Seq
   #68 = Class              #67           // scala/collection/immutable/Seq
   #69 = Utf8               map
   #70 = Utf8               (Lscala/Function1;)Ljava/lang/Object;
   #71 = NameAndType        #69:#70       // map:(Lscala/Function1;)Ljava/lang/Object;
   #72 = InterfaceMethodref #68.#71       // scala/collection/immutable/Seq.map:(Lscala/Function1;)Ljava/lang/Object;
   #73 = Utf8               scala/collection/IterableOnceOps
   #74 = Class              #73           // scala/collection/IterableOnceOps
   #75 = Utf8               mkString
   #76 = Utf8               (Ljava/lang/String;)Ljava/lang/String;
   #77 = NameAndType        #75:#76       // mkString:(Ljava/lang/String;)Ljava/lang/String;
   #78 = InterfaceMethodref #74.#77       // scala/collection/IterableOnceOps.mkString:(Ljava/lang/String;)Ljava/lang/String;
   #79 = Utf8               MODULE$
   #80 = Utf8               Lcoursier/error/ResolutionError$Simple$;
   #81 = NameAndType        #79:#80       // MODULE$:Lcoursier/error/ResolutionError$Simple$;
   #82 = Fieldref           #13.#81       // coursier/error/ResolutionError$Simple$.MODULE$:Lcoursier/error/ResolutionError$Simple$;
   #83 = Utf8               $lessinit$greater$default$3
   #84 = Utf8               ()Ljava/lang/Throwable;
   #85 = NameAndType        #83:#84       // $lessinit$greater$default$3:()Ljava/lang/Throwable;
   #86 = Methodref          #13.#85       // coursier/error/ResolutionError$Simple$.$lessinit$greater$default$3:()Ljava/lang/Throwable;
   #87 = Utf8               (Lcoursier/core/Resolution;Ljava/lang/String;Ljava/lang/Throwable;)V
   #88 = NameAndType        #34:#87       // "<init>":(Lcoursier/core/Resolution;Ljava/lang/String;Ljava/lang/Throwable;)V
   #89 = Methodref          #4.#88        // coursier/error/ResolutionError$Simple."<init>":(Lcoursier/core/Resolution;Ljava/lang/String;Ljava/lang/Throwable;)V
   #90 = Utf8               Lcoursier/core/Resolution;
   #91 = Utf8               Signature
   #92 = Utf8               Code
   #93 = Utf8               LineNumberTable
   #94 = Utf8               LocalVariableTable
   #95 = Utf8               MethodParameters
   #96 = Utf8               InnerClasses
   #97 = Utf8               SourceFile
   #98 = Utf8               ScalaInlineInfo
   #99 = Utf8               Scala
{
  private final coursier.core.Module module;
    descriptor: Lcoursier/core/Module;
    flags: (0x0012) ACC_PRIVATE, ACC_FINAL

  private final java.lang.String version;
    descriptor: Ljava/lang/String;
    flags: (0x0012) ACC_PRIVATE, ACC_FINAL

  private final scala.collection.immutable.Seq<java.lang.String> perRepositoryErrors;
    descriptor: Lscala/collection/immutable/Seq;
    flags: (0x0012) ACC_PRIVATE, ACC_FINAL
    Signature: #21                          // Lscala/collection/immutable/Seq<Ljava/lang/String;>;

  public coursier.core.Module module();
    descriptor: ()Lcoursier/core/Module;
    flags: (0x0001) ACC_PUBLIC
    Code:
      stack=1, locals=1, args_size=1
         0: aload_0
         1: getfield      #24                 // Field module:Lcoursier/core/Module;
         4: areturn
      LineNumberTable:
        line 29: 0
      LocalVariableTable:
        Start  Length  Slot  Name   Signature
            0       5     0  this   Lcoursier/error/ResolutionError$CantDownloadModule;

  public java.lang.String version();
    descriptor: ()Ljava/lang/String;
    flags: (0x0001) ACC_PUBLIC
    Code:
      stack=1, locals=1, args_size=1
         0: aload_0
         1: getfield      #29                 // Field version:Ljava/lang/String;
         4: areturn
      LineNumberTable:
        line 30: 0
      LocalVariableTable:
        Start  Length  Slot  Name   Signature
            0       5     0  this   Lcoursier/error/ResolutionError$CantDownloadModule;

  public scala.collection.immutable.Seq<java.lang.String> perRepositoryErrors();
    descriptor: ()Lscala/collection/immutable/Seq;
    flags: (0x0001) ACC_PUBLIC
    Code:
      stack=1, locals=1, args_size=1
         0: aload_0
         1: getfield      #33                 // Field perRepositoryErrors:Lscala/collection/immutable/Seq;
         4: areturn
      LineNumberTable:
        line 31: 0
      LocalVariableTable:
        Start  Length  Slot  Name   Signature
            0       5     0  this   Lcoursier/error/ResolutionError$CantDownloadModule;
    Signature: #31                          // ()Lscala/collection/immutable/Seq<Ljava/lang/String;>;

  public coursier.error.ResolutionError$CantDownloadModule(coursier.core.Resolution, coursier.core.Module, java.lang.String, scala.collection.immutable.Seq<java.lang.String>);
    descriptor: (Lcoursier/core/Resolution;Lcoursier/core/Module;Ljava/lang/String;Lscala/collection/immutable/Seq;)V
    flags: (0x0001) ACC_PUBLIC
    Code:
      stack=6, locals=5, args_size=5
         0: aload_0
         1: aload_2
         2: putfield      #24                 // Field module:Lcoursier/core/Module;
         5: aload_0
         6: aload_3
         7: putfield      #29                 // Field version:Ljava/lang/String;
        10: aload_0
        11: aload         4
        13: putfield      #33                 // Field perRepositoryErrors:Lscala/collection/immutable/Seq;
        16: aload_0
        17: aload_1
        18: new           #39                 // class java/lang/StringBuilder
        21: dup
        22: ldc           #40                 // int 0
        24: invokespecial #43                 // Method java/lang/StringBuilder."<init>":(I)V
        27: new           #39                 // class java/lang/StringBuilder
        30: dup
        31: ldc           #44                 // int 19
        33: invokespecial #43                 // Method java/lang/StringBuilder."<init>":(I)V
        36: ldc           #46                 // String Error downloading
        38: invokevirtual #50                 // Method java/lang/StringBuilder.append:(Ljava/lang/String;)Ljava/lang/StringBuilder;
        41: aload_2
        42: invokevirtual #53                 // Method java/lang/StringBuilder.append:(Ljava/lang/Object;)Ljava/lang/StringBuilder;
        45: ldc           #55                 // String :
        47: invokevirtual #50                 // Method java/lang/StringBuilder.append:(Ljava/lang/String;)Ljava/lang/StringBuilder;
        50: aload_3
        51: invokevirtual #50                 // Method java/lang/StringBuilder.append:(Ljava/lang/String;)Ljava/lang/StringBuilder;
        54: invokevirtual #58                 // Method java/lang/StringBuilder.toString:()Ljava/lang/String;
        57: invokevirtual #50                 // Method java/lang/StringBuilder.append:(Ljava/lang/String;)Ljava/lang/StringBuilder;
        60: invokestatic  #63                 // Method java/lang/System.lineSeparator:()Ljava/lang/String;
        63: invokevirtual #50                 // Method java/lang/StringBuilder.append:(Ljava/lang/String;)Ljava/lang/StringBuilder;
        66: aload         4
        68: new           #10                 // class coursier/error/ResolutionError$CantDownloadModule$$anonfun$$lessinit$greater$1
        71: dup
        72: invokespecial #66                 // Method coursier/error/ResolutionError$CantDownloadModule$$anonfun$$lessinit$greater$1."<init>":()V
        75: invokeinterface #72,  2           // InterfaceMethod scala/collection/immutable/Seq.map:(Lscala/Function1;)Ljava/lang/Object;
        80: checkcast     #74                 // class scala/collection/IterableOnceOps
        83: invokestatic  #63                 // Method java/lang/System.lineSeparator:()Ljava/lang/String;
        86: invokeinterface #78,  2           // InterfaceMethod scala/collection/IterableOnceOps.mkString:(Ljava/lang/String;)Ljava/lang/String;
        91: invokevirtual #50                 // Method java/lang/StringBuilder.append:(Ljava/lang/String;)Ljava/lang/StringBuilder;
        94: invokevirtual #58                 // Method java/lang/StringBuilder.toString:()Ljava/lang/String;
        97: getstatic     #82                 // Field coursier/error/ResolutionError$Simple$.MODULE$:Lcoursier/error/ResolutionError$Simple$;
       100: invokevirtual #86                 // Method coursier/error/ResolutionError$Simple$.$lessinit$greater$default$3:()Ljava/lang/Throwable;
       103: invokespecial #89                 // Method coursier/error/ResolutionError$Simple."<init>":(Lcoursier/core/Resolution;Ljava/lang/String;Ljava/lang/Throwable;)V
       106: return
      LineNumberTable:
        line 29: 0
        line 30: 5
        line 31: 10
        line 32: 16
        line 33: 17
        line 34: 18
        line 35: 66
        line 32: 97
        line 27: 106
      LocalVariableTable:
        Start  Length  Slot  Name   Signature
            0     107     0  this   Lcoursier/error/ResolutionError$CantDownloadModule;
            0     107     1 resolution   Lcoursier/core/Resolution;
            0     107     2 module   Lcoursier/core/Module;
            0     107     3 version   Ljava/lang/String;
            0     107     4 perRepositoryErrors   Lscala/collection/immutable/Seq;
    Signature: #36                          // (Lcoursier/core/Resolution;Lcoursier/core/Module;Ljava/lang/String;Lscala/collection/immutable/Seq<Ljava/lang/String;>;)V
    MethodParameters:
      Name                           Flags
      resolution                     final
      module                         final
      version                        final
      perRepositoryErrors            final
}
InnerClasses:
  public static final #8= #2 of #7;       // CantDownloadModule=class coursier/error/ResolutionError$CantDownloadModule of class coursier/error/ResolutionError
  public final #10;                       // class coursier/error/ResolutionError$CantDownloadModule$$anonfun$$lessinit$greater$1
  public static abstract #11= #4 of #7;   // Simple=class coursier/error/ResolutionError$Simple of class coursier/error/ResolutionError
  public static #14= #13 of #7;           // =class coursier/error/ResolutionError$Simple$ of class coursier/error/ResolutionError
SourceFile: "ResolutionError.scala"
  ScalaInlineInfo: length = 0x18 (unknown attribute)
   01 01 00 04 00 22 00 23 01 00 0F 00 16 01 00 13
   00 1E 01 00 11 00 1B 01
  Scala: length = 0x0 (unknown attribute)

