Classfile /Users/mw/Projects/slang-braindump/.jar/jar11/assemble/slang-braindump/assemble/content/coursier/error/ResolutionError$Several.class
  Last modified May 29, 2022; size 2175 bytes
  SHA-256 checksum 955338b21c1768b6a5987d049478eaa1e74608e9503fbf883105ce0b9023037c
  Compiled from "ResolutionError.scala"
public final class coursier.error.ResolutionError$Several extends coursier.error.ResolutionError
  minor version: 0
  major version: 52
  flags: (0x0031) ACC_PUBLIC, ACC_FINAL, ACC_SUPER
  this_class: #2                          // coursier/error/ResolutionError$Several
  super_class: #4                         // coursier/error/ResolutionError
  interfaces: 0, fields: 2, methods: 4, attributes: 4
Constant pool:
   #1 = Utf8               coursier/error/ResolutionError$Several
   #2 = Class              #1             // coursier/error/ResolutionError$Several
   #3 = Utf8               coursier/error/ResolutionError
   #4 = Class              #3             // coursier/error/ResolutionError
   #5 = Utf8               ResolutionError.scala
   #6 = Utf8               Several
   #7 = Utf8               coursier/error/ResolutionError$Several$$anonfun$$lessinit$greater$2
   #8 = Class              #7             // coursier/error/ResolutionError$Several$$anonfun$$lessinit$greater$2
   #9 = Utf8               coursier/error/ResolutionError$Simple
  #10 = Class              #9             // coursier/error/ResolutionError$Simple
  #11 = Utf8               Simple
  #12 = Utf8               head
  #13 = Utf8               Lcoursier/error/ResolutionError$Simple;
  #14 = Utf8               tail
  #15 = Utf8               Lscala/collection/immutable/Seq;
  #16 = Utf8               Lscala/collection/immutable/Seq<Lcoursier/error/ResolutionError$Simple;>;
  #17 = Utf8               ()Lcoursier/error/ResolutionError$Simple;
  #18 = NameAndType        #12:#13        // head:Lcoursier/error/ResolutionError$Simple;
  #19 = Fieldref           #2.#18         // coursier/error/ResolutionError$Several.head:Lcoursier/error/ResolutionError$Simple;
  #20 = Utf8               this
  #21 = Utf8               Lcoursier/error/ResolutionError$Several;
  #22 = Utf8               ()Lscala/collection/immutable/Seq;
  #23 = Utf8               ()Lscala/collection/immutable/Seq<Lcoursier/error/ResolutionError$Simple;>;
  #24 = NameAndType        #14:#15        // tail:Lscala/collection/immutable/Seq;
  #25 = Fieldref           #2.#24         // coursier/error/ResolutionError$Several.tail:Lscala/collection/immutable/Seq;
  #26 = Utf8               errors
  #27 = NameAndType        #12:#17        // head:()Lcoursier/error/ResolutionError$Simple;
  #28 = Methodref          #2.#27         // coursier/error/ResolutionError$Several.head:()Lcoursier/error/ResolutionError$Simple;
  #29 = NameAndType        #14:#22        // tail:()Lscala/collection/immutable/Seq;
  #30 = Methodref          #2.#29         // coursier/error/ResolutionError$Several.tail:()Lscala/collection/immutable/Seq;
  #31 = Utf8               scala/collection/immutable/Seq
  #32 = Class              #31            // scala/collection/immutable/Seq
  #33 = Utf8               $plus$colon
  #34 = Utf8               (Ljava/lang/Object;)Ljava/lang/Object;
  #35 = NameAndType        #33:#34        // $plus$colon:(Ljava/lang/Object;)Ljava/lang/Object;
  #36 = InterfaceMethodref #32.#35        // scala/collection/immutable/Seq.$plus$colon:(Ljava/lang/Object;)Ljava/lang/Object;
  #37 = Utf8               <init>
  #38 = Utf8               (Lcoursier/error/ResolutionError$Simple;Lscala/collection/immutable/Seq;)V
  #39 = Utf8               (Lcoursier/error/ResolutionError$Simple;Lscala/collection/immutable/Seq<Lcoursier/error/ResolutionError$Simple;>;)V
  #40 = Utf8               resolution
  #41 = Utf8               ()Lcoursier/core/Resolution;
  #42 = NameAndType        #40:#41        // resolution:()Lcoursier/core/Resolution;
  #43 = Methodref          #10.#42        // coursier/error/ResolutionError$Simple.resolution:()Lcoursier/core/Resolution;
  #44 = Utf8               scala/collection/IterableOps
  #45 = Class              #44            // scala/collection/IterableOps
  #46 = Utf8               ()V
  #47 = NameAndType        #37:#46        // "<init>":()V
  #48 = Methodref          #8.#47         // coursier/error/ResolutionError$Several$$anonfun$$lessinit$greater$2."<init>":()V
  #49 = Utf8               map
  #50 = Utf8               (Lscala/Function1;)Ljava/lang/Object;
  #51 = NameAndType        #49:#50        // map:(Lscala/Function1;)Ljava/lang/Object;
  #52 = InterfaceMethodref #45.#51        // scala/collection/IterableOps.map:(Lscala/Function1;)Ljava/lang/Object;
  #53 = Utf8               scala/collection/IterableOnceOps
  #54 = Class              #53            // scala/collection/IterableOnceOps
  #55 = Utf8               java/lang/System
  #56 = Class              #55            // java/lang/System
  #57 = Utf8               lineSeparator
  #58 = Utf8               ()Ljava/lang/String;
  #59 = NameAndType        #57:#58        // lineSeparator:()Ljava/lang/String;
  #60 = Methodref          #56.#59        // java/lang/System.lineSeparator:()Ljava/lang/String;
  #61 = Utf8               mkString
  #62 = Utf8               (Ljava/lang/String;)Ljava/lang/String;
  #63 = NameAndType        #61:#62        // mkString:(Ljava/lang/String;)Ljava/lang/String;
  #64 = InterfaceMethodref #54.#63        // scala/collection/IterableOnceOps.mkString:(Ljava/lang/String;)Ljava/lang/String;
  #65 = Utf8               coursier/error/ResolutionError$
  #66 = Class              #65            // coursier/error/ResolutionError$
  #67 = Utf8               MODULE$
  #68 = Utf8               Lcoursier/error/ResolutionError$;
  #69 = NameAndType        #67:#68        // MODULE$:Lcoursier/error/ResolutionError$;
  #70 = Fieldref           #66.#69        // coursier/error/ResolutionError$.MODULE$:Lcoursier/error/ResolutionError$;
  #71 = Utf8               $lessinit$greater$default$3
  #72 = Utf8               ()Ljava/lang/Throwable;
  #73 = NameAndType        #71:#72        // $lessinit$greater$default$3:()Ljava/lang/Throwable;
  #74 = Methodref          #66.#73        // coursier/error/ResolutionError$.$lessinit$greater$default$3:()Ljava/lang/Throwable;
  #75 = Utf8               (Lcoursier/core/Resolution;Ljava/lang/String;Ljava/lang/Throwable;)V
  #76 = NameAndType        #37:#75        // "<init>":(Lcoursier/core/Resolution;Ljava/lang/String;Ljava/lang/Throwable;)V
  #77 = Methodref          #4.#76         // coursier/error/ResolutionError."<init>":(Lcoursier/core/Resolution;Ljava/lang/String;Ljava/lang/Throwable;)V
  #78 = Utf8               Signature
  #79 = Utf8               Code
  #80 = Utf8               LineNumberTable
  #81 = Utf8               LocalVariableTable
  #82 = Utf8               MethodParameters
  #83 = Utf8               InnerClasses
  #84 = Utf8               SourceFile
  #85 = Utf8               ScalaInlineInfo
  #86 = Utf8               Scala
{
  private final coursier.error.ResolutionError$Simple head;
    descriptor: Lcoursier/error/ResolutionError$Simple;
    flags: (0x0012) ACC_PRIVATE, ACC_FINAL

  private final scala.collection.immutable.Seq<coursier.error.ResolutionError$Simple> tail;
    descriptor: Lscala/collection/immutable/Seq;
    flags: (0x0012) ACC_PRIVATE, ACC_FINAL
    Signature: #16                          // Lscala/collection/immutable/Seq<Lcoursier/error/ResolutionError$Simple;>;

  public coursier.error.ResolutionError$Simple head();
    descriptor: ()Lcoursier/error/ResolutionError$Simple;
    flags: (0x0001) ACC_PUBLIC
    Code:
      stack=1, locals=1, args_size=1
         0: aload_0
         1: getfield      #19                 // Field head:Lcoursier/error/ResolutionError$Simple;
         4: areturn
      LineNumberTable:
        line 101: 0
      LocalVariableTable:
        Start  Length  Slot  Name   Signature
            0       5     0  this   Lcoursier/error/ResolutionError$Several;

  public scala.collection.immutable.Seq<coursier.error.ResolutionError$Simple> tail();
    descriptor: ()Lscala/collection/immutable/Seq;
    flags: (0x0001) ACC_PUBLIC
    Code:
      stack=1, locals=1, args_size=1
         0: aload_0
         1: getfield      #25                 // Field tail:Lscala/collection/immutable/Seq;
         4: areturn
      LineNumberTable:
        line 101: 0
      LocalVariableTable:
        Start  Length  Slot  Name   Signature
            0       5     0  this   Lcoursier/error/ResolutionError$Several;
    Signature: #23                          // ()Lscala/collection/immutable/Seq<Lcoursier/error/ResolutionError$Simple;>;

  public scala.collection.immutable.Seq<coursier.error.ResolutionError$Simple> errors();
    descriptor: ()Lscala/collection/immutable/Seq;
    flags: (0x0001) ACC_PUBLIC
    Code:
      stack=2, locals=2, args_size=1
         0: aload_0
         1: invokevirtual #28                 // Method head:()Lcoursier/error/ResolutionError$Simple;
         4: astore_1
         5: aload_0
         6: invokevirtual #30                 // Method tail:()Lscala/collection/immutable/Seq;
         9: aload_1
        10: invokeinterface #36,  2           // InterfaceMethod scala/collection/immutable/Seq.$plus$colon:(Ljava/lang/Object;)Ljava/lang/Object;
        15: checkcast     #32                 // class scala/collection/immutable/Seq
        18: areturn
      LineNumberTable:
        line 105: 0
      LocalVariableTable:
        Start  Length  Slot  Name   Signature
            0      19     0  this   Lcoursier/error/ResolutionError$Several;
    Signature: #23                          // ()Lscala/collection/immutable/Seq<Lcoursier/error/ResolutionError$Simple;>;

  public coursier.error.ResolutionError$Several(coursier.error.ResolutionError$Simple, scala.collection.immutable.Seq<coursier.error.ResolutionError$Simple>);
    descriptor: (Lcoursier/error/ResolutionError$Simple;Lscala/collection/immutable/Seq;)V
    flags: (0x0001) ACC_PUBLIC
    Code:
      stack=5, locals=4, args_size=3
         0: aload_0
         1: aload_1
         2: putfield      #19                 // Field head:Lcoursier/error/ResolutionError$Simple;
         5: aload_0
         6: aload_2
         7: putfield      #25                 // Field tail:Lscala/collection/immutable/Seq;
        10: aload_0
        11: aload_1
        12: invokevirtual #43                 // Method coursier/error/ResolutionError$Simple.resolution:()Lcoursier/core/Resolution;
        15: aload_1
        16: astore_3
        17: aload_2
        18: aload_3
        19: invokeinterface #36,  2           // InterfaceMethod scala/collection/immutable/Seq.$plus$colon:(Ljava/lang/Object;)Ljava/lang/Object;
        24: checkcast     #45                 // class scala/collection/IterableOps
        27: new           #8                  // class coursier/error/ResolutionError$Several$$anonfun$$lessinit$greater$2
        30: dup
        31: invokespecial #48                 // Method coursier/error/ResolutionError$Several$$anonfun$$lessinit$greater$2."<init>":()V
        34: invokeinterface #52,  2           // InterfaceMethod scala/collection/IterableOps.map:(Lscala/Function1;)Ljava/lang/Object;
        39: checkcast     #54                 // class scala/collection/IterableOnceOps
        42: invokestatic  #60                 // Method java/lang/System.lineSeparator:()Ljava/lang/String;
        45: invokeinterface #64,  2           // InterfaceMethod scala/collection/IterableOnceOps.mkString:(Ljava/lang/String;)Ljava/lang/String;
        50: getstatic     #70                 // Field coursier/error/ResolutionError$.MODULE$:Lcoursier/error/ResolutionError$;
        53: invokevirtual #74                 // Method coursier/error/ResolutionError$.$lessinit$greater$default$3:()Ljava/lang/Throwable;
        56: invokespecial #77                 // Method coursier/error/ResolutionError."<init>":(Lcoursier/core/Resolution;Ljava/lang/String;Ljava/lang/Throwable;)V
        59: return
      LineNumberTable:
        line 101: 0
        line 102: 11
        line 101: 50
      LocalVariableTable:
        Start  Length  Slot  Name   Signature
            0      60     0  this   Lcoursier/error/ResolutionError$Several;
            0      60     1  head   Lcoursier/error/ResolutionError$Simple;
            0      60     2  tail   Lscala/collection/immutable/Seq;
    Signature: #39                          // (Lcoursier/error/ResolutionError$Simple;Lscala/collection/immutable/Seq<Lcoursier/error/ResolutionError$Simple;>;)V
    MethodParameters:
      Name                           Flags
      head                           final
      tail                           final
}
InnerClasses:
  public static final #6= #2 of #4;       // Several=class coursier/error/ResolutionError$Several of class coursier/error/ResolutionError
  public final #8;                        // class coursier/error/ResolutionError$Several$$anonfun$$lessinit$greater$2
  public static abstract #11= #10 of #4;  // Simple=class coursier/error/ResolutionError$Simple of class coursier/error/ResolutionError
SourceFile: "ResolutionError.scala"
  ScalaInlineInfo: length = 0x18 (unknown attribute)
   01 01 00 04 00 25 00 26 01 00 1A 00 16 01 00 0C
   00 11 01 00 0E 00 16 01
  Scala: length = 0x0 (unknown attribute)

