Classfile /Users/mw/Projects/slang-braindump/.jar/jar11/assemble/slang-braindump/assemble/content/coursier/error/ResolutionError$.class
  Last modified May 29, 2022; size 3472 bytes
  SHA-256 checksum c832019b50497a4cb554257fae4191461d98080936915ecf5452643f667b8ae2
  Compiled from "ResolutionError.scala"
public final class coursier.error.ResolutionError$ implements java.io.Serializable
  minor version: 0
  major version: 52
  flags: (0x0031) ACC_PUBLIC, ACC_FINAL, ACC_SUPER
  this_class: #2                          // coursier/error/ResolutionError$
  super_class: #4                         // java/lang/Object
  interfaces: 1, fields: 1, methods: 7, attributes: 5
Constant pool:
    #1 = Utf8               coursier/error/ResolutionError$
    #2 = Class              #1            // coursier/error/ResolutionError$
    #3 = Utf8               java/lang/Object
    #4 = Class              #3            // java/lang/Object
    #5 = Utf8               java/io/Serializable
    #6 = Class              #5            // java/io/Serializable
    #7 = Utf8               ResolutionError.scala
    #8 = Utf8               coursier/error/ResolutionError$Several
    #9 = Class              #8            // coursier/error/ResolutionError$Several
   #10 = Utf8               coursier/error/ResolutionError
   #11 = Class              #10           // coursier/error/ResolutionError
   #12 = Utf8               Several
   #13 = Utf8               coursier/error/ResolutionError$Simple
   #14 = Class              #13           // coursier/error/ResolutionError$Simple
   #15 = Utf8               Simple
   #16 = Utf8               java/lang/invoke/MethodHandles$Lookup
   #17 = Class              #16           // java/lang/invoke/MethodHandles$Lookup
   #18 = Utf8               java/lang/invoke/MethodHandles
   #19 = Class              #18           // java/lang/invoke/MethodHandles
   #20 = Utf8               Lookup
   #21 = Utf8               MODULE$
   #22 = Utf8               Lcoursier/error/ResolutionError$;
   #23 = Utf8               <clinit>
   #24 = Utf8               ()V
   #25 = Utf8               <init>
   #26 = NameAndType        #25:#24       // "<init>":()V
   #27 = Methodref          #2.#26        // coursier/error/ResolutionError$."<init>":()V
   #28 = NameAndType        #21:#22       // MODULE$:Lcoursier/error/ResolutionError$;
   #29 = Fieldref           #2.#28        // coursier/error/ResolutionError$.MODULE$:Lcoursier/error/ResolutionError$;
   #30 = Utf8               $lessinit$greater$default$3
   #31 = Utf8               ()Ljava/lang/Throwable;
   #32 = Utf8               this
   #33 = Utf8               from
   #34 = Utf8               (Lcoursier/error/ResolutionError;Lscala/collection/immutable/Seq;)Lcoursier/error/ResolutionError;
   #35 = Utf8               (Lcoursier/error/ResolutionError;Lscala/collection/immutable/Seq<Lcoursier/error/ResolutionError;>;)Lcoursier/error/ResolutionError;
   #36 = Utf8               head
   #37 = Utf8               tail
   #38 = Utf8               scala/collection/immutable/Seq
   #39 = Class              #38           // scala/collection/immutable/Seq
   #40 = Utf8               $plus$colon
   #41 = Utf8               (Ljava/lang/Object;)Ljava/lang/Object;
   #42 = NameAndType        #40:#41       // $plus$colon:(Ljava/lang/Object;)Ljava/lang/Object;
   #43 = InterfaceMethodref #39.#42       // scala/collection/immutable/Seq.$plus$colon:(Ljava/lang/Object;)Ljava/lang/Object;
   #44 = Utf8               scala/collection/IterableOps
   #45 = Class              #44           // scala/collection/IterableOps
   #46 = MethodType         #41           //  (Ljava/lang/Object;)Ljava/lang/Object;
   #47 = Utf8               $anonfun$from$1
   #48 = Utf8               (Lcoursier/error/ResolutionError;)Lscala/collection/immutable/Seq;
   #49 = NameAndType        #47:#48       // $anonfun$from$1:(Lcoursier/error/ResolutionError;)Lscala/collection/immutable/Seq;
   #50 = Methodref          #2.#49        // coursier/error/ResolutionError$.$anonfun$from$1:(Lcoursier/error/ResolutionError;)Lscala/collection/immutable/Seq;
   #51 = MethodHandle       6:#50         // REF_invokeStatic coursier/error/ResolutionError$.$anonfun$from$1:(Lcoursier/error/ResolutionError;)Lscala/collection/immutable/Seq;
   #52 = MethodType         #48           //  (Lcoursier/error/ResolutionError;)Lscala/collection/immutable/Seq;
   #53 = Integer            5
   #54 = Integer            1
   #55 = Utf8               java/lang/invoke/LambdaMetafactory
   #56 = Class              #55           // java/lang/invoke/LambdaMetafactory
   #57 = Utf8               altMetafactory
   #58 = Utf8               (Ljava/lang/invoke/MethodHandles$Lookup;Ljava/lang/String;Ljava/lang/invoke/MethodType;[Ljava/lang/Object;)Ljava/lang/invoke/CallSite;
   #59 = NameAndType        #57:#58       // altMetafactory:(Ljava/lang/invoke/MethodHandles$Lookup;Ljava/lang/String;Ljava/lang/invoke/MethodType;[Ljava/lang/Object;)Ljava/lang/invoke/CallSite;
   #60 = Methodref          #56.#59       // java/lang/invoke/LambdaMetafactory.altMetafactory:(Ljava/lang/invoke/MethodHandles$Lookup;Ljava/lang/String;Ljava/lang/invoke/MethodType;[Ljava/lang/Object;)Ljava/lang/invoke/CallSite;
   #61 = MethodHandle       6:#60         // REF_invokeStatic java/lang/invoke/LambdaMetafactory.altMetafactory:(Ljava/lang/invoke/MethodHandles$Lookup;Ljava/lang/String;Ljava/lang/invoke/MethodType;[Ljava/lang/Object;)Ljava/lang/invoke/CallSite;
   #62 = Utf8               apply
   #63 = Utf8               ()Lscala/Function1;
   #64 = NameAndType        #62:#63       // apply:()Lscala/Function1;
   #65 = InvokeDynamic      #0:#64        // #0:apply:()Lscala/Function1;
   #66 = Utf8               flatMap
   #67 = Utf8               (Lscala/Function1;)Ljava/lang/Object;
   #68 = NameAndType        #66:#67       // flatMap:(Lscala/Function1;)Ljava/lang/Object;
   #69 = InterfaceMethodref #45.#68       // scala/collection/IterableOps.flatMap:(Lscala/Function1;)Ljava/lang/Object;
   #70 = Utf8               scala/Predef$
   #71 = Class              #70           // scala/Predef$
   #72 = Utf8               Lscala/Predef$;
   #73 = NameAndType        #21:#72       // MODULE$:Lscala/Predef$;
   #74 = Fieldref           #71.#73       // scala/Predef$.MODULE$:Lscala/Predef$;
   #75 = Utf8               nonEmpty
   #76 = Utf8               ()Z
   #77 = NameAndType        #75:#76       // nonEmpty:()Z
   #78 = InterfaceMethodref #39.#77       // scala/collection/immutable/Seq.nonEmpty:()Z
   #79 = Utf8               assert
   #80 = Utf8               (Z)V
   #81 = NameAndType        #79:#80       // assert:(Z)V
   #82 = Methodref          #71.#81       // scala/Predef$.assert:(Z)V
   #83 = Utf8               ()Ljava/lang/Object;
   #84 = NameAndType        #37:#83       // tail:()Ljava/lang/Object;
   #85 = InterfaceMethodref #39.#84       // scala/collection/immutable/Seq.tail:()Ljava/lang/Object;
   #86 = Utf8               scala/collection/SeqOps
   #87 = Class              #86           // scala/collection/SeqOps
   #88 = Utf8               isEmpty
   #89 = NameAndType        #88:#76       // isEmpty:()Z
   #90 = InterfaceMethodref #87.#89       // scala/collection/SeqOps.isEmpty:()Z
   #91 = NameAndType        #36:#83       // head:()Ljava/lang/Object;
   #92 = InterfaceMethodref #39.#91       // scala/collection/immutable/Seq.head:()Ljava/lang/Object;
   #93 = Utf8               (Lcoursier/error/ResolutionError$Simple;Lscala/collection/immutable/Seq;)V
   #94 = NameAndType        #25:#93       // "<init>":(Lcoursier/error/ResolutionError$Simple;Lscala/collection/immutable/Seq;)V
   #95 = Methodref          #9.#94        // coursier/error/ResolutionError$Several."<init>":(Lcoursier/error/ResolutionError$Simple;Lscala/collection/immutable/Seq;)V
   #96 = Utf8               errors
   #97 = Utf8               Lscala/collection/immutable/Seq;
   #98 = Utf8               Lcoursier/error/ResolutionError;
   #99 = Utf8               writeReplace
  #100 = Utf8               scala/runtime/ModuleSerializationProxy
  #101 = Class              #100          // scala/runtime/ModuleSerializationProxy
  #102 = Utf8               (Ljava/lang/Class;)V
  #103 = NameAndType        #25:#102      // "<init>":(Ljava/lang/Class;)V
  #104 = Methodref          #101.#103     // scala/runtime/ModuleSerializationProxy."<init>":(Ljava/lang/Class;)V
  #105 = Utf8               x0$1
  #106 = Utf8               scala/collection/immutable/$colon$colon
  #107 = Class              #106          // scala/collection/immutable/$colon$colon
  #108 = Utf8               scala/collection/immutable/Nil$
  #109 = Class              #108          // scala/collection/immutable/Nil$
  #110 = Utf8               Lscala/collection/immutable/Nil$;
  #111 = NameAndType        #21:#110      // MODULE$:Lscala/collection/immutable/Nil$;
  #112 = Fieldref           #109.#111     // scala/collection/immutable/Nil$.MODULE$:Lscala/collection/immutable/Nil$;
  #113 = Utf8               (Ljava/lang/Object;Lscala/collection/immutable/List;)V
  #114 = NameAndType        #25:#113      // "<init>":(Ljava/lang/Object;Lscala/collection/immutable/List;)V
  #115 = Methodref          #107.#114     // scala/collection/immutable/$colon$colon."<init>":(Ljava/lang/Object;Lscala/collection/immutable/List;)V
  #116 = Utf8               ()Lcoursier/error/ResolutionError$Simple;
  #117 = NameAndType        #36:#116      // head:()Lcoursier/error/ResolutionError$Simple;
  #118 = Methodref          #9.#117       // coursier/error/ResolutionError$Several.head:()Lcoursier/error/ResolutionError$Simple;
  #119 = Utf8               ()Lscala/collection/immutable/Seq;
  #120 = NameAndType        #37:#119      // tail:()Lscala/collection/immutable/Seq;
  #121 = Methodref          #9.#120       // coursier/error/ResolutionError$Several.tail:()Lscala/collection/immutable/Seq;
  #122 = Utf8               scala/MatchError
  #123 = Class              #122          // scala/MatchError
  #124 = Utf8               (Ljava/lang/Object;)V
  #125 = NameAndType        #25:#124      // "<init>":(Ljava/lang/Object;)V
  #126 = Methodref          #123.#125     // scala/MatchError."<init>":(Ljava/lang/Object;)V
  #127 = Methodref          #4.#26        // java/lang/Object."<init>":()V
  #128 = Utf8               $deserializeLambda$
  #129 = Utf8               (Ljava/lang/invoke/SerializedLambda;)Ljava/lang/Object;
  #130 = Utf8               scala/runtime/LambdaDeserialize
  #131 = Class              #130          // scala/runtime/LambdaDeserialize
  #132 = Utf8               bootstrap
  #133 = Utf8               (Ljava/lang/invoke/MethodHandles$Lookup;Ljava/lang/String;Ljava/lang/invoke/MethodType;[Ljava/lang/invoke/MethodHandle;)Ljava/lang/invoke/CallSite;
  #134 = NameAndType        #132:#133     // bootstrap:(Ljava/lang/invoke/MethodHandles$Lookup;Ljava/lang/String;Ljava/lang/invoke/MethodType;[Ljava/lang/invoke/MethodHandle;)Ljava/lang/invoke/CallSite;
  #135 = Methodref          #131.#134     // scala/runtime/LambdaDeserialize.bootstrap:(Ljava/lang/invoke/MethodHandles$Lookup;Ljava/lang/String;Ljava/lang/invoke/MethodType;[Ljava/lang/invoke/MethodHandle;)Ljava/lang/invoke/CallSite;
  #136 = MethodHandle       6:#135        // REF_invokeStatic scala/runtime/LambdaDeserialize.bootstrap:(Ljava/lang/invoke/MethodHandles$Lookup;Ljava/lang/String;Ljava/lang/invoke/MethodType;[Ljava/lang/invoke/MethodHandle;)Ljava/lang/invoke/CallSite;
  #137 = Utf8               lambdaDeserialize
  #138 = NameAndType        #137:#129     // lambdaDeserialize:(Ljava/lang/invoke/SerializedLambda;)Ljava/lang/Object;
  #139 = InvokeDynamic      #1:#138       // #1:lambdaDeserialize:(Ljava/lang/invoke/SerializedLambda;)Ljava/lang/Object;
  #140 = Utf8               Code
  #141 = Utf8               LineNumberTable
  #142 = Utf8               LocalVariableTable
  #143 = Utf8               StackMapTable
  #144 = Utf8               Signature
  #145 = Utf8               MethodParameters
  #146 = Utf8               InnerClasses
  #147 = Utf8               SourceFile
  #148 = Utf8               BootstrapMethods
  #149 = Utf8               ScalaInlineInfo
  #150 = Utf8               Scala
{
  public static final coursier.error.ResolutionError$ MODULE$;
    descriptor: Lcoursier/error/ResolutionError$;
    flags: (0x0019) ACC_PUBLIC, ACC_STATIC, ACC_FINAL

  public static {};
    descriptor: ()V
    flags: (0x0009) ACC_PUBLIC, ACC_STATIC
    Code:
      stack=2, locals=0, args_size=0
         0: new           #2                  // class coursier/error/ResolutionError$
         3: dup
         4: invokespecial #27                 // Method "<init>":()V
         7: putstatic     #29                 // Field MODULE$:Lcoursier/error/ResolutionError$;
        10: return
      LineNumberTable:
        line 20: 0

  public java.lang.Throwable $lessinit$greater$default$3();
    descriptor: ()Ljava/lang/Throwable;
    flags: (0x0001) ACC_PUBLIC
    Code:
      stack=1, locals=1, args_size=1
         0: aconst_null
         1: areturn
      LineNumberTable:
        line 15: 0
      LocalVariableTable:
        Start  Length  Slot  Name   Signature
            0       2     0  this   Lcoursier/error/ResolutionError$;

  public coursier.error.ResolutionError from(coursier.error.ResolutionError, scala.collection.immutable.Seq<coursier.error.ResolutionError>);
    descriptor: (Lcoursier/error/ResolutionError;Lscala/collection/immutable/Seq;)Lcoursier/error/ResolutionError;
    flags: (0x0001) ACC_PUBLIC
    Code:
      stack=4, locals=5, args_size=3
         0: aload_1
         1: astore        4
         3: aload_2
         4: aload         4
         6: invokeinterface #43,  2           // InterfaceMethod scala/collection/immutable/Seq.$plus$colon:(Ljava/lang/Object;)Ljava/lang/Object;
        11: checkcast     #45                 // class scala/collection/IterableOps
        14: invokedynamic #65,  0             // InvokeDynamic #0:apply:()Lscala/Function1;
        19: invokeinterface #69,  2           // InterfaceMethod scala/collection/IterableOps.flatMap:(Lscala/Function1;)Ljava/lang/Object;
        24: checkcast     #39                 // class scala/collection/immutable/Seq
        27: astore_3
        28: getstatic     #74                 // Field scala/Predef$.MODULE$:Lscala/Predef$;
        31: aload_3
        32: invokeinterface #78,  1           // InterfaceMethod scala/collection/immutable/Seq.nonEmpty:()Z
        37: invokevirtual #82                 // Method scala/Predef$.assert:(Z)V
        40: aload_3
        41: invokeinterface #85,  1           // InterfaceMethod scala/collection/immutable/Seq.tail:()Ljava/lang/Object;
        46: checkcast     #87                 // class scala/collection/SeqOps
        49: invokeinterface #90,  1           // InterfaceMethod scala/collection/SeqOps.isEmpty:()Z
        54: ifeq          69
        57: aload_3
        58: invokeinterface #92,  1           // InterfaceMethod scala/collection/immutable/Seq.head:()Ljava/lang/Object;
        63: checkcast     #11                 // class coursier/error/ResolutionError
        66: goto          94
        69: new           #9                  // class coursier/error/ResolutionError$Several
        72: dup
        73: aload_3
        74: invokeinterface #92,  1           // InterfaceMethod scala/collection/immutable/Seq.head:()Ljava/lang/Object;
        79: checkcast     #14                 // class coursier/error/ResolutionError$Simple
        82: aload_3
        83: invokeinterface #85,  1           // InterfaceMethod scala/collection/immutable/Seq.tail:()Ljava/lang/Object;
        88: checkcast     #39                 // class scala/collection/immutable/Seq
        91: invokespecial #95                 // Method coursier/error/ResolutionError$Several."<init>":(Lcoursier/error/ResolutionError$Simple;Lscala/collection/immutable/Seq;)V
        94: areturn
      StackMapTable: number_of_entries = 2
        frame_type = 253 /* append */
          offset_delta = 69
          locals = [ class scala/collection/immutable/Seq, class coursier/error/ResolutionError ]
        frame_type = 88 /* same_locals_1_stack_item */
          stack = [ class coursier/error/ResolutionError ]
      LineNumberTable:
        line 109: 0
        line 113: 28
        line 114: 40
        line 115: 57
        line 117: 69
      LocalVariableTable:
        Start  Length  Slot  Name   Signature
           28      66     3 errors   Lscala/collection/immutable/Seq;
            0      95     0  this   Lcoursier/error/ResolutionError$;
            0      95     1  head   Lcoursier/error/ResolutionError;
            0      95     2  tail   Lscala/collection/immutable/Seq;
    Signature: #35                          // (Lcoursier/error/ResolutionError;Lscala/collection/immutable/Seq<Lcoursier/error/ResolutionError;>;)Lcoursier/error/ResolutionError;
    MethodParameters:
      Name                           Flags
      head                           final
      tail                           final

  private java.lang.Object writeReplace();
    descriptor: ()Ljava/lang/Object;
    flags: (0x0002) ACC_PRIVATE
    Code:
      stack=3, locals=1, args_size=1
         0: new           #101                // class scala/runtime/ModuleSerializationProxy
         3: dup
         4: ldc           #2                  // class coursier/error/ResolutionError$
         6: invokespecial #104                // Method scala/runtime/ModuleSerializationProxy."<init>":(Ljava/lang/Class;)V
         9: areturn
      LineNumberTable:
        line 20: 0
      LocalVariableTable:
        Start  Length  Slot  Name   Signature
            0      10     0  this   Lcoursier/error/ResolutionError$;

  public static final scala.collection.immutable.Seq $anonfun$from$1(coursier.error.ResolutionError);
    descriptor: (Lcoursier/error/ResolutionError;)Lscala/collection/immutable/Seq;
    flags: (0x1019) ACC_PUBLIC, ACC_STATIC, ACC_FINAL, ACC_SYNTHETIC
    Code:
      stack=4, locals=6, args_size=1
         0: aload_0
         1: astore_2
         2: aload_2
         3: instanceof    #14                 // class coursier/error/ResolutionError$Simple
         6: ifeq          32
         9: aload_2
        10: checkcast     #14                 // class coursier/error/ResolutionError$Simple
        13: astore_3
        14: new           #107                // class scala/collection/immutable/$colon$colon
        17: dup
        18: aload_3
        19: getstatic     #112                // Field scala/collection/immutable/Nil$.MODULE$:Lscala/collection/immutable/Nil$;
        22: invokespecial #115                // Method scala/collection/immutable/$colon$colon."<init>":(Ljava/lang/Object;Lscala/collection/immutable/List;)V
        25: checkcast     #39                 // class scala/collection/immutable/Seq
        28: astore_1
        29: goto          86
        32: goto          35
        35: aload_2
        36: instanceof    #9                  // class coursier/error/ResolutionError$Several
        39: ifeq          74
        42: aload_2
        43: checkcast     #9                  // class coursier/error/ResolutionError$Several
        46: astore        4
        48: aload         4
        50: invokevirtual #118                // Method coursier/error/ResolutionError$Several.head:()Lcoursier/error/ResolutionError$Simple;
        53: astore        5
        55: aload         4
        57: invokevirtual #121                // Method coursier/error/ResolutionError$Several.tail:()Lscala/collection/immutable/Seq;
        60: aload         5
        62: invokeinterface #43,  2           // InterfaceMethod scala/collection/immutable/Seq.$plus$colon:(Ljava/lang/Object;)Ljava/lang/Object;
        67: checkcast     #39                 // class scala/collection/immutable/Seq
        70: astore_1
        71: goto          86
        74: goto          77
        77: new           #123                // class scala/MatchError
        80: dup
        81: aload_2
        82: invokespecial #126                // Method scala/MatchError."<init>":(Ljava/lang/Object;)V
        85: athrow
        86: aload_1
        87: areturn
      StackMapTable: number_of_entries = 5
        frame_type = 253 /* append */
          offset_delta = 32
          locals = [ top, class coursier/error/ResolutionError ]
        frame_type = 2 /* same */
        frame_type = 38 /* same */
        frame_type = 2 /* same */
        frame_type = 255 /* full_frame */
          offset_delta = 8
          locals = [ class coursier/error/ResolutionError, class scala/collection/immutable/Seq, class coursier/error/ResolutionError ]
          stack = []
      LineNumberTable:
        line 109: 0
        line 110: 2
        line 111: 35
        line 109: 77
      LocalVariableTable:
        Start  Length  Slot  Name   Signature
            0      88     0  x0$1   Lcoursier/error/ResolutionError;
    MethodParameters:
      Name                           Flags
      x0$1                           final

  private coursier.error.ResolutionError$();
    descriptor: ()V
    flags: (0x0002) ACC_PRIVATE
    Code:
      stack=1, locals=1, args_size=1
         0: aload_0
         1: invokespecial #127                // Method java/lang/Object."<init>":()V
         4: return
      LineNumberTable:
        line 128: 0
        line 20: 4
      LocalVariableTable:
        Start  Length  Slot  Name   Signature
            0       5     0  this   Lcoursier/error/ResolutionError$;

  private static java.lang.Object $deserializeLambda$(java.lang.invoke.SerializedLambda);
    descriptor: (Ljava/lang/invoke/SerializedLambda;)Ljava/lang/Object;
    flags: (0x100a) ACC_PRIVATE, ACC_STATIC, ACC_SYNTHETIC
    Code:
      stack=1, locals=1, args_size=1
         0: aload_0
         1: invokedynamic #139,  0            // InvokeDynamic #1:lambdaDeserialize:(Ljava/lang/invoke/SerializedLambda;)Ljava/lang/Object;
         6: areturn
}
InnerClasses:
  public static final #12= #9 of #11;     // Several=class coursier/error/ResolutionError$Several of class coursier/error/ResolutionError
  public static abstract #15= #14 of #11; // Simple=class coursier/error/ResolutionError$Simple of class coursier/error/ResolutionError
  public static final #20= #17 of #19;    // Lookup=class java/lang/invoke/MethodHandles$Lookup of class java/lang/invoke/MethodHandles
SourceFile: "ResolutionError.scala"
BootstrapMethods:
  0: #61 REF_invokeStatic java/lang/invoke/LambdaMetafactory.altMetafactory:(Ljava/lang/invoke/MethodHandles$Lookup;Ljava/lang/String;Ljava/lang/invoke/MethodType;[Ljava/lang/Object;)Ljava/lang/invoke/CallSite;
    Method arguments:
      #46 (Ljava/lang/Object;)Ljava/lang/Object;
      #51 REF_invokeStatic coursier/error/ResolutionError$.$anonfun$from$1:(Lcoursier/error/ResolutionError;)Lscala/collection/immutable/Seq;
      #52 (Lcoursier/error/ResolutionError;)Lscala/collection/immutable/Seq;
      #53 5
      #54 1
      #52 (Lcoursier/error/ResolutionError;)Lscala/collection/immutable/Seq;
  1: #136 REF_invokeStatic scala/runtime/LambdaDeserialize.bootstrap:(Ljava/lang/invoke/MethodHandles$Lookup;Ljava/lang/String;Ljava/lang/invoke/MethodType;[Ljava/lang/invoke/MethodHandle;)Ljava/lang/invoke/CallSite;
    Method arguments:
      #51 REF_invokeStatic coursier/error/ResolutionError$.$anonfun$from$1:(Lcoursier/error/ResolutionError;)Lscala/collection/immutable/Seq;
  ScalaInlineInfo: length = 0x1D (unknown attribute)
   01 01 00 05 00 2F 00 30 01 00 1E 00 1F 01 00 19
   00 18 01 00 21 00 22 01 00 63 00 53 01
  Scala: length = 0x0 (unknown attribute)

