Classfile /Users/mw/Projects/slang-braindump/.jar/jar8/assemble/slang-braindump/assemble/content/com/fasterxml/jackson/databind/util/ArrayIterator.class
  Last modified May 29, 2022; size 1426 bytes
  SHA-256 checksum d3851b69463a94578d882b89189bcf7f1aaf2715cfe701ae4682885e913dc2e3
  Compiled from "ArrayIterator.java"
public class com.fasterxml.jackson.databind.util.ArrayIterator<T extends java.lang.Object> extends java.lang.Object implements java.util.Iterator<T>, java.lang.Iterable<T>
  minor version: 0
  major version: 52
  flags: (0x0021) ACC_PUBLIC, ACC_SUPER
  this_class: #8                          // com/fasterxml/jackson/databind/util/ArrayIterator
  super_class: #9                         // java/lang/Object
  interfaces: 2, fields: 2, methods: 5, attributes: 2
Constant pool:
   #1 = Methodref          #9.#43         // java/lang/Object."<init>":()V
   #2 = Fieldref           #8.#44         // com/fasterxml/jackson/databind/util/ArrayIterator._a:[Ljava/lang/Object;
   #3 = Fieldref           #8.#45         // com/fasterxml/jackson/databind/util/ArrayIterator._index:I
   #4 = Class              #46            // java/util/NoSuchElementException
   #5 = Methodref          #4.#43         // java/util/NoSuchElementException."<init>":()V
   #6 = Class              #47            // java/lang/UnsupportedOperationException
   #7 = Methodref          #6.#43         // java/lang/UnsupportedOperationException."<init>":()V
   #8 = Class              #48            // com/fasterxml/jackson/databind/util/ArrayIterator
   #9 = Class              #49            // java/lang/Object
  #10 = Class              #50            // java/util/Iterator
  #11 = Class              #51            // java/lang/Iterable
  #12 = Utf8               _a
  #13 = Utf8               [Ljava/lang/Object;
  #14 = Utf8               Signature
  #15 = Utf8               [TT;
  #16 = Utf8               _index
  #17 = Utf8               I
  #18 = Utf8               <init>
  #19 = Utf8               ([Ljava/lang/Object;)V
  #20 = Utf8               Code
  #21 = Utf8               LineNumberTable
  #22 = Utf8               LocalVariableTable
  #23 = Utf8               this
  #24 = Utf8               Lcom/fasterxml/jackson/databind/util/ArrayIterator;
  #25 = Utf8               a
  #26 = Utf8               LocalVariableTypeTable
  #27 = Utf8               Lcom/fasterxml/jackson/databind/util/ArrayIterator<TT;>;
  #28 = Utf8               ([TT;)V
  #29 = Utf8               hasNext
  #30 = Utf8               ()Z
  #31 = Utf8               StackMapTable
  #32 = Utf8               next
  #33 = Utf8               ()Ljava/lang/Object;
  #34 = Utf8               ()TT;
  #35 = Utf8               remove
  #36 = Utf8               ()V
  #37 = Utf8               iterator
  #38 = Utf8               ()Ljava/util/Iterator;
  #39 = Utf8               ()Ljava/util/Iterator<TT;>;
  #40 = Utf8               <T:Ljava/lang/Object;>Ljava/lang/Object;Ljava/util/Iterator<TT;>;Ljava/lang/Iterable<TT;>;
  #41 = Utf8               SourceFile
  #42 = Utf8               ArrayIterator.java
  #43 = NameAndType        #18:#36        // "<init>":()V
  #44 = NameAndType        #12:#13        // _a:[Ljava/lang/Object;
  #45 = NameAndType        #16:#17        // _index:I
  #46 = Utf8               java/util/NoSuchElementException
  #47 = Utf8               java/lang/UnsupportedOperationException
  #48 = Utf8               com/fasterxml/jackson/databind/util/ArrayIterator
  #49 = Utf8               java/lang/Object
  #50 = Utf8               java/util/Iterator
  #51 = Utf8               java/lang/Iterable
{
  private final T[] _a;
    descriptor: [Ljava/lang/Object;
    flags: (0x0012) ACC_PRIVATE, ACC_FINAL
    Signature: #15                          // [TT;

  private int _index;
    descriptor: I
    flags: (0x0002) ACC_PRIVATE

  public com.fasterxml.jackson.databind.util.ArrayIterator(T[]);
    descriptor: ([Ljava/lang/Object;)V
    flags: (0x0001) ACC_PUBLIC
    Code:
      stack=2, locals=2, args_size=2
         0: aload_0
         1: invokespecial #1                  // Method java/lang/Object."<init>":()V
         4: aload_0
         5: aload_1
         6: putfield      #2                  // Field _a:[Ljava/lang/Object;
         9: aload_0
        10: iconst_0
        11: putfield      #3                  // Field _index:I
        14: return
      LineNumberTable:
        line 17: 0
        line 18: 4
        line 19: 9
        line 20: 14
      LocalVariableTable:
        Start  Length  Slot  Name   Signature
            0      15     0  this   Lcom/fasterxml/jackson/databind/util/ArrayIterator;
            0      15     1     a   [Ljava/lang/Object;
      LocalVariableTypeTable:
        Start  Length  Slot  Name   Signature
            0      15     0  this   Lcom/fasterxml/jackson/databind/util/ArrayIterator<TT;>;
            0      15     1     a   [TT;
    Signature: #28                          // ([TT;)V

  public boolean hasNext();
    descriptor: ()Z
    flags: (0x0001) ACC_PUBLIC
    Code:
      stack=2, locals=1, args_size=1
         0: aload_0
         1: getfield      #3                  // Field _index:I
         4: aload_0
         5: getfield      #2                  // Field _a:[Ljava/lang/Object;
         8: arraylength
         9: if_icmpge     16
        12: iconst_1
        13: goto          17
        16: iconst_0
        17: ireturn
      LineNumberTable:
        line 23: 0
      LocalVariableTable:
        Start  Length  Slot  Name   Signature
            0      18     0  this   Lcom/fasterxml/jackson/databind/util/ArrayIterator;
      LocalVariableTypeTable:
        Start  Length  Slot  Name   Signature
            0      18     0  this   Lcom/fasterxml/jackson/databind/util/ArrayIterator<TT;>;
      StackMapTable: number_of_entries = 2
        frame_type = 16 /* same */
        frame_type = 64 /* same_locals_1_stack_item */
          stack = [ int ]

  public T next();
    descriptor: ()Ljava/lang/Object;
    flags: (0x0001) ACC_PUBLIC
    Code:
      stack=5, locals=1, args_size=1
         0: aload_0
         1: getfield      #3                  // Field _index:I
         4: aload_0
         5: getfield      #2                  // Field _a:[Ljava/lang/Object;
         8: arraylength
         9: if_icmplt     20
        12: new           #4                  // class java/util/NoSuchElementException
        15: dup
        16: invokespecial #5                  // Method java/util/NoSuchElementException."<init>":()V
        19: athrow
        20: aload_0
        21: getfield      #2                  // Field _a:[Ljava/lang/Object;
        24: aload_0
        25: dup
        26: getfield      #3                  // Field _index:I
        29: dup_x1
        30: iconst_1
        31: iadd
        32: putfield      #3                  // Field _index:I
        35: aaload
        36: areturn
      LineNumberTable:
        line 27: 0
        line 28: 12
        line 30: 20
      LocalVariableTable:
        Start  Length  Slot  Name   Signature
            0      37     0  this   Lcom/fasterxml/jackson/databind/util/ArrayIterator;
      LocalVariableTypeTable:
        Start  Length  Slot  Name   Signature
            0      37     0  this   Lcom/fasterxml/jackson/databind/util/ArrayIterator<TT;>;
      StackMapTable: number_of_entries = 1
        frame_type = 20 /* same */
    Signature: #34                          // ()TT;

  public void remove();
    descriptor: ()V
    flags: (0x0001) ACC_PUBLIC
    Code:
      stack=2, locals=1, args_size=1
         0: new           #6                  // class java/lang/UnsupportedOperationException
         3: dup
         4: invokespecial #7                  // Method java/lang/UnsupportedOperationException."<init>":()V
         7: athrow
      LineNumberTable:
        line 33: 0
      LocalVariableTable:
        Start  Length  Slot  Name   Signature
            0       8     0  this   Lcom/fasterxml/jackson/databind/util/ArrayIterator;
      LocalVariableTypeTable:
        Start  Length  Slot  Name   Signature
            0       8     0  this   Lcom/fasterxml/jackson/databind/util/ArrayIterator<TT;>;

  public java.util.Iterator<T> iterator();
    descriptor: ()Ljava/util/Iterator;
    flags: (0x0001) ACC_PUBLIC
    Code:
      stack=1, locals=1, args_size=1
         0: aload_0
         1: areturn
      LineNumberTable:
        line 34: 0
      LocalVariableTable:
        Start  Length  Slot  Name   Signature
            0       2     0  this   Lcom/fasterxml/jackson/databind/util/ArrayIterator;
      LocalVariableTypeTable:
        Start  Length  Slot  Name   Signature
            0       2     0  this   Lcom/fasterxml/jackson/databind/util/ArrayIterator<TT;>;
    Signature: #39                          // ()Ljava/util/Iterator<TT;>;
}
Signature: #40                          // <T:Ljava/lang/Object;>Ljava/lang/Object;Ljava/util/Iterator<TT;>;Ljava/lang/Iterable<TT;>;
SourceFile: "ArrayIterator.java"
