Classfile /Users/mw/Projects/slang-braindump/.jar/jar8/assemble/slang-braindump/assemble/content/com/fasterxml/jackson/databind/util/ClassUtil$EnumTypeLocator.class
  Last modified May 29, 2022; size 3641 bytes
  SHA-256 checksum cb6e8b69237031c27707669643dfeabadabdb41f816bf09d336c0abcfd5973cc
  Compiled from "ClassUtil.java"
class com.fasterxml.jackson.databind.util.ClassUtil$EnumTypeLocator
  minor version: 0
  major version: 52
  flags: (0x0020) ACC_SUPER
  this_class: #35                         // com/fasterxml/jackson/databind/util/ClassUtil$EnumTypeLocator
  super_class: #32                        // java/lang/Object
  interfaces: 0, fields: 5, methods: 6, attributes: 2
Constant pool:
    #1 = Methodref          #32.#96       // java/lang/Object."<init>":()V
    #2 = Class              #97           // java/util/EnumSet
    #3 = String             #98           // elementType
    #4 = Class              #99           // java/lang/Class
    #5 = Methodref          #35.#100      // com/fasterxml/jackson/databind/util/ClassUtil$EnumTypeLocator.locateField:(Ljava/lang/Class;Ljava/lang/String;Ljava/lang/Class;)Ljava/lang/reflect/Field;
    #6 = Class              #101          // java/lang/Exception
    #7 = Methodref          #6.#102       // java/lang/Exception.toString:()Ljava/lang/String;
    #8 = Fieldref           #35.#103      // com/fasterxml/jackson/databind/util/ClassUtil$EnumTypeLocator.enumSetTypeField:Ljava/lang/reflect/Field;
    #9 = Fieldref           #35.#104      // com/fasterxml/jackson/databind/util/ClassUtil$EnumTypeLocator.failForEnumSet:Ljava/lang/String;
   #10 = Class              #105          // java/util/EnumMap
   #11 = String             #106          // keyType
   #12 = Fieldref           #35.#107      // com/fasterxml/jackson/databind/util/ClassUtil$EnumTypeLocator.enumMapTypeField:Ljava/lang/reflect/Field;
   #13 = Fieldref           #35.#108      // com/fasterxml/jackson/databind/util/ClassUtil$EnumTypeLocator.failForEnumMap:Ljava/lang/String;
   #14 = Methodref          #35.#109      // com/fasterxml/jackson/databind/util/ClassUtil$EnumTypeLocator.get:(Ljava/lang/Object;Ljava/lang/reflect/Field;)Ljava/lang/Object;
   #15 = Class              #110          // java/lang/IllegalStateException
   #16 = Class              #111          // java/lang/StringBuilder
   #17 = Methodref          #16.#96       // java/lang/StringBuilder."<init>":()V
   #18 = String             #112          // Cannot figure out type parameter for `EnumSet` (odd JDK platform?), problem:
   #19 = Methodref          #16.#113      // java/lang/StringBuilder.append:(Ljava/lang/String;)Ljava/lang/StringBuilder;
   #20 = Methodref          #16.#102      // java/lang/StringBuilder.toString:()Ljava/lang/String;
   #21 = Methodref          #15.#114      // java/lang/IllegalStateException."<init>":(Ljava/lang/String;)V
   #22 = String             #115          // Cannot figure out type parameter for `EnumMap` (odd JDK platform?), problem:
   #23 = Methodref          #116.#117     // java/lang/reflect/Field.get:(Ljava/lang/Object;)Ljava/lang/Object;
   #24 = Class              #118          // java/lang/IllegalArgumentException
   #25 = Methodref          #24.#119      // java/lang/IllegalArgumentException."<init>":(Ljava/lang/Throwable;)V
   #26 = Methodref          #4.#120       // java/lang/Class.getDeclaredFields:()[Ljava/lang/reflect/Field;
   #27 = Methodref          #116.#121     // java/lang/reflect/Field.getName:()Ljava/lang/String;
   #28 = Methodref          #122.#123     // java/lang/String.equals:(Ljava/lang/Object;)Z
   #29 = Methodref          #116.#124     // java/lang/reflect/Field.getType:()Ljava/lang/Class;
   #30 = Methodref          #116.#125     // java/lang/reflect/Field.setAccessible:(Z)V
   #31 = String             #126          // No field named \'%s\' in class \'%s\'
   #32 = Class              #127          // java/lang/Object
   #33 = Methodref          #4.#128       // java/lang/Class.getTypeName:()Ljava/lang/String;
   #34 = Methodref          #122.#129     // java/lang/String.format:(Ljava/lang/String;[Ljava/lang/Object;)Ljava/lang/String;
   #35 = Class              #131          // com/fasterxml/jackson/databind/util/ClassUtil$EnumTypeLocator
   #36 = Methodref          #35.#96       // com/fasterxml/jackson/databind/util/ClassUtil$EnumTypeLocator."<init>":()V
   #37 = Fieldref           #35.#132      // com/fasterxml/jackson/databind/util/ClassUtil$EnumTypeLocator.instance:Lcom/fasterxml/jackson/databind/util/ClassUtil$EnumTypeLocator;
   #38 = Utf8               instance
   #39 = Utf8               EnumTypeLocator
   #40 = Utf8               InnerClasses
   #41 = Utf8               Lcom/fasterxml/jackson/databind/util/ClassUtil$EnumTypeLocator;
   #42 = Utf8               enumSetTypeField
   #43 = Utf8               Ljava/lang/reflect/Field;
   #44 = Utf8               enumMapTypeField
   #45 = Utf8               failForEnumSet
   #46 = Utf8               Ljava/lang/String;
   #47 = Utf8               failForEnumMap
   #48 = Utf8               <init>
   #49 = Utf8               ()V
   #50 = Utf8               Code
   #51 = Utf8               LineNumberTable
   #52 = Utf8               LocalVariableTable
   #53 = Utf8               e
   #54 = Utf8               Ljava/lang/Exception;
   #55 = Utf8               this
   #56 = Utf8               f
   #57 = Utf8               msg
   #58 = Utf8               StackMapTable
   #59 = Class              #131          // com/fasterxml/jackson/databind/util/ClassUtil$EnumTypeLocator
   #60 = Class              #133          // java/lang/reflect/Field
   #61 = Class              #134          // java/lang/String
   #62 = Class              #101          // java/lang/Exception
   #63 = Utf8               enumTypeFor
   #64 = Utf8               (Ljava/util/EnumSet;)Ljava/lang/Class;
   #65 = Utf8               set
   #66 = Utf8               Ljava/util/EnumSet;
   #67 = Utf8               LocalVariableTypeTable
   #68 = Utf8               Ljava/util/EnumSet<*>;
   #69 = Utf8               Signature
   #70 = Utf8               (Ljava/util/EnumSet<*>;)Ljava/lang/Class<+Ljava/lang/Enum<*>;>;
   #71 = Utf8               (Ljava/util/EnumMap;)Ljava/lang/Class;
   #72 = Utf8               Ljava/util/EnumMap;
   #73 = Utf8               Ljava/util/EnumMap<**>;
   #74 = Utf8               (Ljava/util/EnumMap<**>;)Ljava/lang/Class<+Ljava/lang/Enum<*>;>;
   #75 = Utf8               get
   #76 = Utf8               (Ljava/lang/Object;Ljava/lang/reflect/Field;)Ljava/lang/Object;
   #77 = Utf8               bean
   #78 = Utf8               Ljava/lang/Object;
   #79 = Utf8               field
   #80 = Utf8               locateField
   #81 = Utf8               (Ljava/lang/Class;Ljava/lang/String;Ljava/lang/Class;)Ljava/lang/reflect/Field;
   #82 = Utf8               fromClass
   #83 = Utf8               Ljava/lang/Class;
   #84 = Utf8               expectedName
   #85 = Utf8               type
   #86 = Utf8               fields
   #87 = Utf8               [Ljava/lang/reflect/Field;
   #88 = Utf8               Ljava/lang/Class<*>;
   #89 = Class              #99           // java/lang/Class
   #90 = Class              #87           // "[Ljava/lang/reflect/Field;"
   #91 = Utf8               Exceptions
   #92 = Utf8               (Ljava/lang/Class<*>;Ljava/lang/String;Ljava/lang/Class<*>;)Ljava/lang/reflect/Field;
   #93 = Utf8               <clinit>
   #94 = Utf8               SourceFile
   #95 = Utf8               ClassUtil.java
   #96 = NameAndType        #48:#49       // "<init>":()V
   #97 = Utf8               java/util/EnumSet
   #98 = Utf8               elementType
   #99 = Utf8               java/lang/Class
  #100 = NameAndType        #80:#81       // locateField:(Ljava/lang/Class;Ljava/lang/String;Ljava/lang/Class;)Ljava/lang/reflect/Field;
  #101 = Utf8               java/lang/Exception
  #102 = NameAndType        #135:#136     // toString:()Ljava/lang/String;
  #103 = NameAndType        #42:#43       // enumSetTypeField:Ljava/lang/reflect/Field;
  #104 = NameAndType        #45:#46       // failForEnumSet:Ljava/lang/String;
  #105 = Utf8               java/util/EnumMap
  #106 = Utf8               keyType
  #107 = NameAndType        #44:#43       // enumMapTypeField:Ljava/lang/reflect/Field;
  #108 = NameAndType        #47:#46       // failForEnumMap:Ljava/lang/String;
  #109 = NameAndType        #75:#76       // get:(Ljava/lang/Object;Ljava/lang/reflect/Field;)Ljava/lang/Object;
  #110 = Utf8               java/lang/IllegalStateException
  #111 = Utf8               java/lang/StringBuilder
  #112 = Utf8               Cannot figure out type parameter for `EnumSet` (odd JDK platform?), problem:
  #113 = NameAndType        #137:#138     // append:(Ljava/lang/String;)Ljava/lang/StringBuilder;
  #114 = NameAndType        #48:#139      // "<init>":(Ljava/lang/String;)V
  #115 = Utf8               Cannot figure out type parameter for `EnumMap` (odd JDK platform?), problem:
  #116 = Class              #133          // java/lang/reflect/Field
  #117 = NameAndType        #75:#140      // get:(Ljava/lang/Object;)Ljava/lang/Object;
  #118 = Utf8               java/lang/IllegalArgumentException
  #119 = NameAndType        #48:#141      // "<init>":(Ljava/lang/Throwable;)V
  #120 = NameAndType        #142:#143     // getDeclaredFields:()[Ljava/lang/reflect/Field;
  #121 = NameAndType        #144:#136     // getName:()Ljava/lang/String;
  #122 = Class              #134          // java/lang/String
  #123 = NameAndType        #145:#146     // equals:(Ljava/lang/Object;)Z
  #124 = NameAndType        #147:#148     // getType:()Ljava/lang/Class;
  #125 = NameAndType        #149:#150     // setAccessible:(Z)V
  #126 = Utf8               No field named \'%s\' in class \'%s\'
  #127 = Utf8               java/lang/Object
  #128 = NameAndType        #151:#136     // getTypeName:()Ljava/lang/String;
  #129 = NameAndType        #152:#153     // format:(Ljava/lang/String;[Ljava/lang/Object;)Ljava/lang/String;
  #130 = Class              #154          // com/fasterxml/jackson/databind/util/ClassUtil
  #131 = Utf8               com/fasterxml/jackson/databind/util/ClassUtil$EnumTypeLocator
  #132 = NameAndType        #38:#41       // instance:Lcom/fasterxml/jackson/databind/util/ClassUtil$EnumTypeLocator;
  #133 = Utf8               java/lang/reflect/Field
  #134 = Utf8               java/lang/String
  #135 = Utf8               toString
  #136 = Utf8               ()Ljava/lang/String;
  #137 = Utf8               append
  #138 = Utf8               (Ljava/lang/String;)Ljava/lang/StringBuilder;
  #139 = Utf8               (Ljava/lang/String;)V
  #140 = Utf8               (Ljava/lang/Object;)Ljava/lang/Object;
  #141 = Utf8               (Ljava/lang/Throwable;)V
  #142 = Utf8               getDeclaredFields
  #143 = Utf8               ()[Ljava/lang/reflect/Field;
  #144 = Utf8               getName
  #145 = Utf8               equals
  #146 = Utf8               (Ljava/lang/Object;)Z
  #147 = Utf8               getType
  #148 = Utf8               ()Ljava/lang/Class;
  #149 = Utf8               setAccessible
  #150 = Utf8               (Z)V
  #151 = Utf8               getTypeName
  #152 = Utf8               format
  #153 = Utf8               (Ljava/lang/String;[Ljava/lang/Object;)Ljava/lang/String;
  #154 = Utf8               com/fasterxml/jackson/databind/util/ClassUtil
{
  static final com.fasterxml.jackson.databind.util.ClassUtil$EnumTypeLocator instance;
    descriptor: Lcom/fasterxml/jackson/databind/util/ClassUtil$EnumTypeLocator;
    flags: (0x0018) ACC_STATIC, ACC_FINAL

  private final java.lang.reflect.Field enumSetTypeField;
    descriptor: Ljava/lang/reflect/Field;
    flags: (0x0012) ACC_PRIVATE, ACC_FINAL

  private final java.lang.reflect.Field enumMapTypeField;
    descriptor: Ljava/lang/reflect/Field;
    flags: (0x0012) ACC_PRIVATE, ACC_FINAL

  private final java.lang.String failForEnumSet;
    descriptor: Ljava/lang/String;
    flags: (0x0012) ACC_PRIVATE, ACC_FINAL

  private final java.lang.String failForEnumMap;
    descriptor: Ljava/lang/String;
    flags: (0x0012) ACC_PRIVATE, ACC_FINAL

  private com.fasterxml.jackson.databind.util.ClassUtil$EnumTypeLocator();
    descriptor: ()V
    flags: (0x0002) ACC_PRIVATE
    Code:
      stack=3, locals=4, args_size=1
         0: aload_0
         1: invokespecial #1                  // Method java/lang/Object."<init>":()V
         4: aconst_null
         5: astore_1
         6: aconst_null
         7: astore_2
         8: ldc           #2                  // class java/util/EnumSet
        10: ldc           #3                  // String elementType
        12: ldc           #4                  // class java/lang/Class
        14: invokestatic  #5                  // Method locateField:(Ljava/lang/Class;Ljava/lang/String;Ljava/lang/Class;)Ljava/lang/reflect/Field;
        17: astore_1
        18: goto          27
        21: astore_3
        22: aload_3
        23: invokevirtual #7                  // Method java/lang/Exception.toString:()Ljava/lang/String;
        26: astore_2
        27: aload_0
        28: aload_1
        29: putfield      #8                  // Field enumSetTypeField:Ljava/lang/reflect/Field;
        32: aload_0
        33: aload_2
        34: putfield      #9                  // Field failForEnumSet:Ljava/lang/String;
        37: aconst_null
        38: astore_1
        39: aconst_null
        40: astore_2
        41: ldc           #10                 // class java/util/EnumMap
        43: ldc           #11                 // String keyType
        45: ldc           #4                  // class java/lang/Class
        47: invokestatic  #5                  // Method locateField:(Ljava/lang/Class;Ljava/lang/String;Ljava/lang/Class;)Ljava/lang/reflect/Field;
        50: astore_1
        51: goto          60
        54: astore_3
        55: aload_3
        56: invokevirtual #7                  // Method java/lang/Exception.toString:()Ljava/lang/String;
        59: astore_2
        60: aload_0
        61: aload_1
        62: putfield      #12                 // Field enumMapTypeField:Ljava/lang/reflect/Field;
        65: aload_0
        66: aload_2
        67: putfield      #13                 // Field failForEnumMap:Ljava/lang/String;
        70: return
      Exception table:
         from    to  target type
             8    18    21   Class java/lang/Exception
            41    51    54   Class java/lang/Exception
      LineNumberTable:
        line 1343: 0
        line 1347: 4
        line 1348: 6
        line 1351: 8
        line 1354: 18
        line 1352: 21
        line 1353: 22
        line 1355: 27
        line 1356: 32
        line 1358: 37
        line 1359: 39
        line 1361: 41
        line 1364: 51
        line 1362: 54
        line 1363: 55
        line 1365: 60
        line 1366: 65
        line 1367: 70
      LocalVariableTable:
        Start  Length  Slot  Name   Signature
           22       5     3     e   Ljava/lang/Exception;
           55       5     3     e   Ljava/lang/Exception;
            0      71     0  this   Lcom/fasterxml/jackson/databind/util/ClassUtil$EnumTypeLocator;
            6      65     1     f   Ljava/lang/reflect/Field;
            8      63     2   msg   Ljava/lang/String;
      StackMapTable: number_of_entries = 4
        frame_type = 255 /* full_frame */
          offset_delta = 21
          locals = [ class com/fasterxml/jackson/databind/util/ClassUtil$EnumTypeLocator, class java/lang/reflect/Field, class java/lang/String ]
          stack = [ class java/lang/Exception ]
        frame_type = 5 /* same */
        frame_type = 90 /* same_locals_1_stack_item */
          stack = [ class java/lang/Exception ]
        frame_type = 5 /* same */

  public java.lang.Class<? extends java.lang.Enum<?>> enumTypeFor(java.util.EnumSet<?>);
    descriptor: (Ljava/util/EnumSet;)Ljava/lang/Class;
    flags: (0x0001) ACC_PUBLIC
    Code:
      stack=4, locals=2, args_size=2
         0: aload_0
         1: getfield      #8                  // Field enumSetTypeField:Ljava/lang/reflect/Field;
         4: ifnull        20
         7: aload_0
         8: aload_1
         9: aload_0
        10: getfield      #8                  // Field enumSetTypeField:Ljava/lang/reflect/Field;
        13: invokespecial #14                 // Method get:(Ljava/lang/Object;Ljava/lang/reflect/Field;)Ljava/lang/Object;
        16: checkcast     #4                  // class java/lang/Class
        19: areturn
        20: new           #15                 // class java/lang/IllegalStateException
        23: dup
        24: new           #16                 // class java/lang/StringBuilder
        27: dup
        28: invokespecial #17                 // Method java/lang/StringBuilder."<init>":()V
        31: ldc           #18                 // String Cannot figure out type parameter for `EnumSet` (odd JDK platform?), problem:
        33: invokevirtual #19                 // Method java/lang/StringBuilder.append:(Ljava/lang/String;)Ljava/lang/StringBuilder;
        36: aload_0
        37: getfield      #9                  // Field failForEnumSet:Ljava/lang/String;
        40: invokevirtual #19                 // Method java/lang/StringBuilder.append:(Ljava/lang/String;)Ljava/lang/StringBuilder;
        43: invokevirtual #20                 // Method java/lang/StringBuilder.toString:()Ljava/lang/String;
        46: invokespecial #21                 // Method java/lang/IllegalStateException."<init>":(Ljava/lang/String;)V
        49: athrow
      LineNumberTable:
        line 1372: 0
        line 1373: 7
        line 1375: 20
      LocalVariableTable:
        Start  Length  Slot  Name   Signature
            0      50     0  this   Lcom/fasterxml/jackson/databind/util/ClassUtil$EnumTypeLocator;
            0      50     1   set   Ljava/util/EnumSet;
      LocalVariableTypeTable:
        Start  Length  Slot  Name   Signature
            0      50     1   set   Ljava/util/EnumSet<*>;
      StackMapTable: number_of_entries = 1
        frame_type = 20 /* same */
    Signature: #70                          // (Ljava/util/EnumSet<*>;)Ljava/lang/Class<+Ljava/lang/Enum<*>;>;

  public java.lang.Class<? extends java.lang.Enum<?>> enumTypeFor(java.util.EnumMap<?, ?>);
    descriptor: (Ljava/util/EnumMap;)Ljava/lang/Class;
    flags: (0x0001) ACC_PUBLIC
    Code:
      stack=4, locals=2, args_size=2
         0: aload_0
         1: getfield      #12                 // Field enumMapTypeField:Ljava/lang/reflect/Field;
         4: ifnull        20
         7: aload_0
         8: aload_1
         9: aload_0
        10: getfield      #12                 // Field enumMapTypeField:Ljava/lang/reflect/Field;
        13: invokespecial #14                 // Method get:(Ljava/lang/Object;Ljava/lang/reflect/Field;)Ljava/lang/Object;
        16: checkcast     #4                  // class java/lang/Class
        19: areturn
        20: new           #15                 // class java/lang/IllegalStateException
        23: dup
        24: new           #16                 // class java/lang/StringBuilder
        27: dup
        28: invokespecial #17                 // Method java/lang/StringBuilder."<init>":()V
        31: ldc           #22                 // String Cannot figure out type parameter for `EnumMap` (odd JDK platform?), problem:
        33: invokevirtual #19                 // Method java/lang/StringBuilder.append:(Ljava/lang/String;)Ljava/lang/StringBuilder;
        36: aload_0
        37: getfield      #13                 // Field failForEnumMap:Ljava/lang/String;
        40: invokevirtual #19                 // Method java/lang/StringBuilder.append:(Ljava/lang/String;)Ljava/lang/StringBuilder;
        43: invokevirtual #20                 // Method java/lang/StringBuilder.toString:()Ljava/lang/String;
        46: invokespecial #21                 // Method java/lang/IllegalStateException."<init>":(Ljava/lang/String;)V
        49: athrow
      LineNumberTable:
        line 1382: 0
        line 1383: 7
        line 1385: 20
      LocalVariableTable:
        Start  Length  Slot  Name   Signature
            0      50     0  this   Lcom/fasterxml/jackson/databind/util/ClassUtil$EnumTypeLocator;
            0      50     1   set   Ljava/util/EnumMap;
      LocalVariableTypeTable:
        Start  Length  Slot  Name   Signature
            0      50     1   set   Ljava/util/EnumMap<**>;
      StackMapTable: number_of_entries = 1
        frame_type = 20 /* same */
    Signature: #74                          // (Ljava/util/EnumMap<**>;)Ljava/lang/Class<+Ljava/lang/Enum<*>;>;

  private java.lang.Object get(java.lang.Object, java.lang.reflect.Field);
    descriptor: (Ljava/lang/Object;Ljava/lang/reflect/Field;)Ljava/lang/Object;
    flags: (0x0002) ACC_PRIVATE
    Code:
      stack=3, locals=4, args_size=3
         0: aload_2
         1: aload_1
         2: invokevirtual #23                 // Method java/lang/reflect/Field.get:(Ljava/lang/Object;)Ljava/lang/Object;
         5: areturn
         6: astore_3
         7: new           #24                 // class java/lang/IllegalArgumentException
        10: dup
        11: aload_3
        12: invokespecial #25                 // Method java/lang/IllegalArgumentException."<init>":(Ljava/lang/Throwable;)V
        15: athrow
      Exception table:
         from    to  target type
             0     5     6   Class java/lang/Exception
      LineNumberTable:
        line 1392: 0
        line 1393: 6
        line 1394: 7
      LocalVariableTable:
        Start  Length  Slot  Name   Signature
            7       9     3     e   Ljava/lang/Exception;
            0      16     0  this   Lcom/fasterxml/jackson/databind/util/ClassUtil$EnumTypeLocator;
            0      16     1  bean   Ljava/lang/Object;
            0      16     2 field   Ljava/lang/reflect/Field;
      StackMapTable: number_of_entries = 1
        frame_type = 70 /* same_locals_1_stack_item */
          stack = [ class java/lang/Exception ]

  private static java.lang.reflect.Field locateField(java.lang.Class<?>, java.lang.String, java.lang.Class<?>) throws java.lang.Exception;
    descriptor: (Ljava/lang/Class;Ljava/lang/String;Ljava/lang/Class;)Ljava/lang/reflect/Field;
    flags: (0x000a) ACC_PRIVATE, ACC_STATIC
    Code:
      stack=7, locals=8, args_size=3
         0: aload_0
         1: invokevirtual #26                 // Method java/lang/Class.getDeclaredFields:()[Ljava/lang/reflect/Field;
         4: astore_3
         5: aload_3
         6: astore        4
         8: aload         4
        10: arraylength
        11: istore        5
        13: iconst_0
        14: istore        6
        16: iload         6
        18: iload         5
        20: if_icmpge     69
        23: aload         4
        25: iload         6
        27: aaload
        28: astore        7
        30: aload_1
        31: aload         7
        33: invokevirtual #27                 // Method java/lang/reflect/Field.getName:()Ljava/lang/String;
        36: invokevirtual #28                 // Method java/lang/String.equals:(Ljava/lang/Object;)Z
        39: ifeq          63
        42: aload         7
        44: invokevirtual #29                 // Method java/lang/reflect/Field.getType:()Ljava/lang/Class;
        47: aload_2
        48: if_acmpeq     54
        51: goto          63
        54: aload         7
        56: iconst_1
        57: invokevirtual #30                 // Method java/lang/reflect/Field.setAccessible:(Z)V
        60: aload         7
        62: areturn
        63: iinc          6, 1
        66: goto          16
        69: new           #15                 // class java/lang/IllegalStateException
        72: dup
        73: ldc           #31                 // String No field named \'%s\' in class \'%s\'
        75: iconst_2
        76: anewarray     #32                 // class java/lang/Object
        79: dup
        80: iconst_0
        81: aload_1
        82: aastore
        83: dup
        84: iconst_1
        85: aload_0
        86: invokevirtual #33                 // Method java/lang/Class.getTypeName:()Ljava/lang/String;
        89: aastore
        90: invokestatic  #34                 // Method java/lang/String.format:(Ljava/lang/String;[Ljava/lang/Object;)Ljava/lang/String;
        93: invokespecial #21                 // Method java/lang/IllegalStateException."<init>":(Ljava/lang/String;)V
        96: athrow
      LineNumberTable:
        line 1402: 0
        line 1403: 5
        line 1404: 30
        line 1405: 51
        line 1407: 54
        line 1408: 60
        line 1403: 63
        line 1411: 69
        line 1412: 86
        line 1411: 90
      LocalVariableTable:
        Start  Length  Slot  Name   Signature
           30      33     7     f   Ljava/lang/reflect/Field;
            0      97     0 fromClass   Ljava/lang/Class;
            0      97     1 expectedName   Ljava/lang/String;
            0      97     2  type   Ljava/lang/Class;
            5      92     3 fields   [Ljava/lang/reflect/Field;
      LocalVariableTypeTable:
        Start  Length  Slot  Name   Signature
            0      97     0 fromClass   Ljava/lang/Class<*>;
            0      97     2  type   Ljava/lang/Class<*>;
      StackMapTable: number_of_entries = 4
        frame_type = 255 /* full_frame */
          offset_delta = 16
          locals = [ class java/lang/Class, class java/lang/String, class java/lang/Class, class "[Ljava/lang/reflect/Field;", class "[Ljava/lang/reflect/Field;", int, int ]
          stack = []
        frame_type = 252 /* append */
          offset_delta = 37
          locals = [ class java/lang/reflect/Field ]
        frame_type = 250 /* chop */
          offset_delta = 8
        frame_type = 248 /* chop */
          offset_delta = 5
    Exceptions:
      throws java.lang.Exception
    Signature: #92                          // (Ljava/lang/Class<*>;Ljava/lang/String;Ljava/lang/Class<*>;)Ljava/lang/reflect/Field;

  static {};
    descriptor: ()V
    flags: (0x0008) ACC_STATIC
    Code:
      stack=2, locals=0, args_size=0
         0: new           #35                 // class com/fasterxml/jackson/databind/util/ClassUtil$EnumTypeLocator
         3: dup
         4: invokespecial #36                 // Method "<init>":()V
         7: putstatic     #37                 // Field instance:Lcom/fasterxml/jackson/databind/util/ClassUtil$EnumTypeLocator;
        10: return
      LineNumberTable:
        line 1335: 0
}
SourceFile: "ClassUtil.java"
InnerClasses:
  private static #39= #35 of #130;        // EnumTypeLocator=class com/fasterxml/jackson/databind/util/ClassUtil$EnumTypeLocator of class com/fasterxml/jackson/databind/util/ClassUtil
