Classfile /Users/mw/Projects/slang-braindump/.jar/jar8/assemble/slang-braindump/assemble/content/com/fasterxml/jackson/databind/util/CompactStringObjectMap.class
  Last modified May 29, 2022; size 3994 bytes
  SHA-256 checksum e5a39be148351b25e6a1a1703d8b9825ef818ae63cdacfb49ec34aa8d8b0dd73
  Compiled from "CompactStringObjectMap.java"
public final class com.fasterxml.jackson.databind.util.CompactStringObjectMap implements java.io.Serializable
  minor version: 0
  major version: 52
  flags: (0x0031) ACC_PUBLIC, ACC_FINAL, ACC_SUPER
  this_class: #20                         // com/fasterxml/jackson/databind/util/CompactStringObjectMap
  super_class: #9                         // java/lang/Object
  interfaces: 1, fields: 5, methods: 8, attributes: 2
Constant pool:
    #1 = Methodref          #9.#103       // java/lang/Object."<init>":()V
    #2 = Fieldref           #20.#104      // com/fasterxml/jackson/databind/util/CompactStringObjectMap._hashMask:I
    #3 = Fieldref           #20.#105      // com/fasterxml/jackson/databind/util/CompactStringObjectMap._spillCount:I
    #4 = Fieldref           #20.#106      // com/fasterxml/jackson/databind/util/CompactStringObjectMap._hashArea:[Ljava/lang/Object;
    #5 = InterfaceMethodref #107.#108     // java/util/Map.isEmpty:()Z
    #6 = Fieldref           #20.#109      // com/fasterxml/jackson/databind/util/CompactStringObjectMap.EMPTY:Lcom/fasterxml/jackson/databind/util/CompactStringObjectMap;
    #7 = InterfaceMethodref #107.#110     // java/util/Map.size:()I
    #8 = Methodref          #20.#111      // com/fasterxml/jackson/databind/util/CompactStringObjectMap.findSize:(I)I
    #9 = Class              #112          // java/lang/Object
   #10 = InterfaceMethodref #107.#113     // java/util/Map.entrySet:()Ljava/util/Set;
   #11 = InterfaceMethodref #114.#115     // java/util/Set.iterator:()Ljava/util/Iterator;
   #12 = InterfaceMethodref #116.#117     // java/util/Iterator.hasNext:()Z
   #13 = InterfaceMethodref #116.#118     // java/util/Iterator.next:()Ljava/lang/Object;
   #14 = Class              #119          // java/util/Map$Entry
   #15 = InterfaceMethodref #14.#120      // java/util/Map$Entry.getKey:()Ljava/lang/Object;
   #16 = Class              #121          // java/lang/String
   #17 = Methodref          #16.#122      // java/lang/String.hashCode:()I
   #18 = Methodref          #123.#124     // java/util/Arrays.copyOf:([Ljava/lang/Object;I)[Ljava/lang/Object;
   #19 = InterfaceMethodref #14.#125      // java/util/Map$Entry.getValue:()Ljava/lang/Object;
   #20 = Class              #126          // com/fasterxml/jackson/databind/util/CompactStringObjectMap
   #21 = Methodref          #20.#127      // com/fasterxml/jackson/databind/util/CompactStringObjectMap."<init>":(II[Ljava/lang/Object;)V
   #22 = Methodref          #16.#128      // java/lang/String.equals:(Ljava/lang/Object;)Z
   #23 = Methodref          #20.#129      // com/fasterxml/jackson/databind/util/CompactStringObjectMap._find2:(Ljava/lang/String;ILjava/lang/Object;)Ljava/lang/Object;
   #24 = Methodref          #16.#130      // java/lang/String.equalsIgnoreCase:(Ljava/lang/String;)Z
   #25 = Class              #131          // java/util/ArrayList
   #26 = Methodref          #25.#132      // java/util/ArrayList."<init>":(I)V
   #27 = InterfaceMethodref #133.#134     // java/util/List.add:(Ljava/lang/Object;)Z
   #28 = Class              #135          // java/io/Serializable
   #29 = Utf8               serialVersionUID
   #30 = Utf8               J
   #31 = Utf8               ConstantValue
   #32 = Long               1l
   #34 = Utf8               EMPTY
   #35 = Utf8               Lcom/fasterxml/jackson/databind/util/CompactStringObjectMap;
   #36 = Utf8               _hashMask
   #37 = Utf8               I
   #38 = Utf8               _spillCount
   #39 = Utf8               _hashArea
   #40 = Utf8               [Ljava/lang/Object;
   #41 = Utf8               <init>
   #42 = Utf8               (II[Ljava/lang/Object;)V
   #43 = Utf8               Code
   #44 = Utf8               LineNumberTable
   #45 = Utf8               LocalVariableTable
   #46 = Utf8               this
   #47 = Utf8               hashMask
   #48 = Utf8               spillCount
   #49 = Utf8               hashArea
   #50 = Utf8               construct
   #51 = Utf8               (Ljava/util/Map;)Lcom/fasterxml/jackson/databind/util/CompactStringObjectMap;
   #52 = Utf8               key
   #53 = Utf8               Ljava/lang/String;
   #54 = Utf8               slot
   #55 = Utf8               ix
   #56 = Utf8               entry
   #57 = Utf8               Entry
   #58 = Utf8               InnerClasses
   #59 = Utf8               Ljava/util/Map$Entry;
   #60 = Utf8               all
   #61 = Utf8               Ljava/util/Map;
   #62 = Utf8               size
   #63 = Utf8               mask
   #64 = Utf8               alloc
   #65 = Utf8               LocalVariableTypeTable
   #66 = Utf8               Ljava/util/Map$Entry<Ljava/lang/String;TT;>;
   #67 = Utf8               Ljava/util/Map<Ljava/lang/String;TT;>;
   #68 = Utf8               StackMapTable
   #69 = Class              #136          // java/util/Map
   #70 = Class              #40           // "[Ljava/lang/Object;"
   #71 = Class              #137          // java/util/Iterator
   #72 = Class              #119          // java/util/Map$Entry
   #73 = Class              #121          // java/lang/String
   #74 = Utf8               Signature
   #75 = Utf8               <T:Ljava/lang/Object;>(Ljava/util/Map<Ljava/lang/String;TT;>;)Lcom/fasterxml/jackson/databind/util/CompactStringObjectMap;
   #76 = Utf8               findSize
   #77 = Utf8               (I)I
   #78 = Utf8               needed
   #79 = Utf8               result
   #80 = Utf8               find
   #81 = Utf8               (Ljava/lang/String;)Ljava/lang/Object;
   #82 = Utf8               match
   #83 = Utf8               Ljava/lang/Object;
   #84 = Class              #112          // java/lang/Object
   #85 = Utf8               _find2
   #86 = Utf8               (Ljava/lang/String;ILjava/lang/Object;)Ljava/lang/Object;
   #87 = Utf8               end
   #88 = Utf8               i
   #89 = Utf8               hashSize
   #90 = Utf8               findCaseInsensitive
   #91 = Utf8               s
   #92 = Utf8               k2
   #93 = Utf8               keys
   #94 = Utf8               ()Ljava/util/List;
   #95 = Utf8               Ljava/util/List;
   #96 = Utf8               Ljava/util/List<Ljava/lang/String;>;
   #97 = Class              #138          // java/util/List
   #98 = Utf8               ()Ljava/util/List<Ljava/lang/String;>;
   #99 = Utf8               <clinit>
  #100 = Utf8               ()V
  #101 = Utf8               SourceFile
  #102 = Utf8               CompactStringObjectMap.java
  #103 = NameAndType        #41:#100      // "<init>":()V
  #104 = NameAndType        #36:#37       // _hashMask:I
  #105 = NameAndType        #38:#37       // _spillCount:I
  #106 = NameAndType        #39:#40       // _hashArea:[Ljava/lang/Object;
  #107 = Class              #136          // java/util/Map
  #108 = NameAndType        #139:#140     // isEmpty:()Z
  #109 = NameAndType        #34:#35       // EMPTY:Lcom/fasterxml/jackson/databind/util/CompactStringObjectMap;
  #110 = NameAndType        #62:#141      // size:()I
  #111 = NameAndType        #76:#77       // findSize:(I)I
  #112 = Utf8               java/lang/Object
  #113 = NameAndType        #142:#143     // entrySet:()Ljava/util/Set;
  #114 = Class              #144          // java/util/Set
  #115 = NameAndType        #145:#146     // iterator:()Ljava/util/Iterator;
  #116 = Class              #137          // java/util/Iterator
  #117 = NameAndType        #147:#140     // hasNext:()Z
  #118 = NameAndType        #148:#149     // next:()Ljava/lang/Object;
  #119 = Utf8               java/util/Map$Entry
  #120 = NameAndType        #150:#149     // getKey:()Ljava/lang/Object;
  #121 = Utf8               java/lang/String
  #122 = NameAndType        #151:#141     // hashCode:()I
  #123 = Class              #152          // java/util/Arrays
  #124 = NameAndType        #153:#154     // copyOf:([Ljava/lang/Object;I)[Ljava/lang/Object;
  #125 = NameAndType        #155:#149     // getValue:()Ljava/lang/Object;
  #126 = Utf8               com/fasterxml/jackson/databind/util/CompactStringObjectMap
  #127 = NameAndType        #41:#42       // "<init>":(II[Ljava/lang/Object;)V
  #128 = NameAndType        #156:#157     // equals:(Ljava/lang/Object;)Z
  #129 = NameAndType        #85:#86       // _find2:(Ljava/lang/String;ILjava/lang/Object;)Ljava/lang/Object;
  #130 = NameAndType        #158:#159     // equalsIgnoreCase:(Ljava/lang/String;)Z
  #131 = Utf8               java/util/ArrayList
  #132 = NameAndType        #41:#160      // "<init>":(I)V
  #133 = Class              #138          // java/util/List
  #134 = NameAndType        #161:#157     // add:(Ljava/lang/Object;)Z
  #135 = Utf8               java/io/Serializable
  #136 = Utf8               java/util/Map
  #137 = Utf8               java/util/Iterator
  #138 = Utf8               java/util/List
  #139 = Utf8               isEmpty
  #140 = Utf8               ()Z
  #141 = Utf8               ()I
  #142 = Utf8               entrySet
  #143 = Utf8               ()Ljava/util/Set;
  #144 = Utf8               java/util/Set
  #145 = Utf8               iterator
  #146 = Utf8               ()Ljava/util/Iterator;
  #147 = Utf8               hasNext
  #148 = Utf8               next
  #149 = Utf8               ()Ljava/lang/Object;
  #150 = Utf8               getKey
  #151 = Utf8               hashCode
  #152 = Utf8               java/util/Arrays
  #153 = Utf8               copyOf
  #154 = Utf8               ([Ljava/lang/Object;I)[Ljava/lang/Object;
  #155 = Utf8               getValue
  #156 = Utf8               equals
  #157 = Utf8               (Ljava/lang/Object;)Z
  #158 = Utf8               equalsIgnoreCase
  #159 = Utf8               (Ljava/lang/String;)Z
  #160 = Utf8               (I)V
  #161 = Utf8               add
{
  private static final long serialVersionUID;
    descriptor: J
    flags: (0x001a) ACC_PRIVATE, ACC_STATIC, ACC_FINAL
    ConstantValue: long 1l

  private static final com.fasterxml.jackson.databind.util.CompactStringObjectMap EMPTY;
    descriptor: Lcom/fasterxml/jackson/databind/util/CompactStringObjectMap;
    flags: (0x001a) ACC_PRIVATE, ACC_STATIC, ACC_FINAL

  private final int _hashMask;
    descriptor: I
    flags: (0x0012) ACC_PRIVATE, ACC_FINAL

  private final int _spillCount;
    descriptor: I
    flags: (0x0012) ACC_PRIVATE, ACC_FINAL

  private final java.lang.Object[] _hashArea;
    descriptor: [Ljava/lang/Object;
    flags: (0x0012) ACC_PRIVATE, ACC_FINAL

  private com.fasterxml.jackson.databind.util.CompactStringObjectMap(int, int, java.lang.Object[]);
    descriptor: (II[Ljava/lang/Object;)V
    flags: (0x0002) ACC_PRIVATE
    Code:
      stack=2, locals=4, args_size=4
         0: aload_0
         1: invokespecial #1                  // Method java/lang/Object."<init>":()V
         4: aload_0
         5: iload_1
         6: putfield      #2                  // Field _hashMask:I
         9: aload_0
        10: iload_2
        11: putfield      #3                  // Field _spillCount:I
        14: aload_0
        15: aload_3
        16: putfield      #4                  // Field _hashArea:[Ljava/lang/Object;
        19: return
      LineNumberTable:
        line 33: 0
        line 34: 4
        line 35: 9
        line 36: 14
        line 37: 19
      LocalVariableTable:
        Start  Length  Slot  Name   Signature
            0      20     0  this   Lcom/fasterxml/jackson/databind/util/CompactStringObjectMap;
            0      20     1 hashMask   I
            0      20     2 spillCount   I
            0      20     3 hashArea   [Ljava/lang/Object;

  public static <T extends java.lang.Object> com.fasterxml.jackson.databind.util.CompactStringObjectMap construct(java.util.Map<java.lang.String, T>);
    descriptor: (Ljava/util/Map;)Lcom/fasterxml/jackson/databind/util/CompactStringObjectMap;
    flags: (0x0009) ACC_PUBLIC, ACC_STATIC
    Code:
      stack=5, locals=11, args_size=1
         0: aload_0
         1: invokeinterface #5,  1            // InterfaceMethod java/util/Map.isEmpty:()Z
         6: ifeq          13
         9: getstatic     #6                  // Field EMPTY:Lcom/fasterxml/jackson/databind/util/CompactStringObjectMap;
        12: areturn
        13: aload_0
        14: invokeinterface #7,  1            // InterfaceMethod java/util/Map.size:()I
        19: invokestatic  #8                  // Method findSize:(I)I
        22: istore_1
        23: iload_1
        24: iconst_1
        25: isub
        26: istore_2
        27: iload_1
        28: iload_1
        29: iconst_1
        30: ishr
        31: iadd
        32: iconst_2
        33: imul
        34: istore_3
        35: iload_3
        36: anewarray     #9                  // class java/lang/Object
        39: astore        4
        41: iconst_0
        42: istore        5
        44: aload_0
        45: invokeinterface #10,  1           // InterfaceMethod java/util/Map.entrySet:()Ljava/util/Set;
        50: invokeinterface #11,  1           // InterfaceMethod java/util/Set.iterator:()Ljava/util/Iterator;
        55: astore        6
        57: aload         6
        59: invokeinterface #12,  1           // InterfaceMethod java/util/Iterator.hasNext:()Z
        64: ifeq          200
        67: aload         6
        69: invokeinterface #13,  1           // InterfaceMethod java/util/Iterator.next:()Ljava/lang/Object;
        74: checkcast     #14                 // class java/util/Map$Entry
        77: astore        7
        79: aload         7
        81: invokeinterface #15,  1           // InterfaceMethod java/util/Map$Entry.getKey:()Ljava/lang/Object;
        86: checkcast     #16                 // class java/lang/String
        89: astore        8
        91: aload         8
        93: ifnonnull     99
        96: goto          57
        99: aload         8
       101: invokevirtual #17                 // Method java/lang/String.hashCode:()I
       104: iload_2
       105: iand
       106: istore        9
       108: iload         9
       110: iload         9
       112: iadd
       113: istore        10
       115: aload         4
       117: iload         10
       119: aaload
       120: ifnull        176
       123: iload_1
       124: iload         9
       126: iconst_1
       127: ishr
       128: iadd
       129: iconst_1
       130: ishl
       131: istore        10
       133: aload         4
       135: iload         10
       137: aaload
       138: ifnull        176
       141: iload_1
       142: iload_1
       143: iconst_1
       144: ishr
       145: iadd
       146: iconst_1
       147: ishl
       148: iload         5
       150: iadd
       151: istore        10
       153: iinc          5, 2
       156: iload         10
       158: aload         4
       160: arraylength
       161: if_icmplt     176
       164: aload         4
       166: aload         4
       168: arraylength
       169: iconst_4
       170: iadd
       171: invokestatic  #18                 // Method java/util/Arrays.copyOf:([Ljava/lang/Object;I)[Ljava/lang/Object;
       174: astore        4
       176: aload         4
       178: iload         10
       180: aload         8
       182: aastore
       183: aload         4
       185: iload         10
       187: iconst_1
       188: iadd
       189: aload         7
       191: invokeinterface #19,  1           // InterfaceMethod java/util/Map$Entry.getValue:()Ljava/lang/Object;
       196: aastore
       197: goto          57
       200: new           #20                 // class com/fasterxml/jackson/databind/util/CompactStringObjectMap
       203: dup
       204: iload_2
       205: iload         5
       207: aload         4
       209: invokespecial #21                 // Method "<init>":(II[Ljava/lang/Object;)V
       212: areturn
      LineNumberTable:
        line 41: 0
        line 42: 9
        line 46: 13
        line 47: 23
        line 49: 27
        line 50: 35
        line 51: 41
        line 53: 44
        line 54: 79
        line 57: 91
        line 58: 96
        line 61: 99
        line 62: 108
        line 65: 115
        line 67: 123
        line 68: 133
        line 70: 141
        line 71: 153
        line 72: 156
        line 73: 164
        line 77: 176
        line 78: 183
        line 79: 197
        line 80: 200
      LocalVariableTable:
        Start  Length  Slot  Name   Signature
           91     106     8   key   Ljava/lang/String;
          108      89     9  slot   I
          115      82    10    ix   I
           79     118     7 entry   Ljava/util/Map$Entry;
            0     213     0   all   Ljava/util/Map;
           23     190     1  size   I
           27     186     2  mask   I
           35     178     3 alloc   I
           41     172     4 hashArea   [Ljava/lang/Object;
           44     169     5 spillCount   I
      LocalVariableTypeTable:
        Start  Length  Slot  Name   Signature
           79     118     7 entry   Ljava/util/Map$Entry<Ljava/lang/String;TT;>;
            0     213     0   all   Ljava/util/Map<Ljava/lang/String;TT;>;
      StackMapTable: number_of_entries = 5
        frame_type = 13 /* same */
        frame_type = 255 /* full_frame */
          offset_delta = 43
          locals = [ class java/util/Map, int, int, int, class "[Ljava/lang/Object;", int, class java/util/Iterator ]
          stack = []
        frame_type = 253 /* append */
          offset_delta = 41
          locals = [ class java/util/Map$Entry, class java/lang/String ]
        frame_type = 253 /* append */
          offset_delta = 76
          locals = [ int, int ]
        frame_type = 255 /* full_frame */
          offset_delta = 23
          locals = [ class java/util/Map, int, int, int, class "[Ljava/lang/Object;", int ]
          stack = []
    Signature: #75                          // <T:Ljava/lang/Object;>(Ljava/util/Map<Ljava/lang/String;TT;>;)Lcom/fasterxml/jackson/databind/util/CompactStringObjectMap;

  private static final int findSize(int);
    descriptor: (I)I
    flags: (0x001a) ACC_PRIVATE, ACC_STATIC, ACC_FINAL
    Code:
      stack=3, locals=3, args_size=1
         0: iload_0
         1: iconst_5
         2: if_icmpgt     8
         5: bipush        8
         7: ireturn
         8: iload_0
         9: bipush        12
        11: if_icmpgt     17
        14: bipush        16
        16: ireturn
        17: iload_0
        18: iload_0
        19: iconst_2
        20: ishr
        21: iadd
        22: istore_1
        23: bipush        32
        25: istore_2
        26: iload_2
        27: iload_1
        28: if_icmpge     38
        31: iload_2
        32: iload_2
        33: iadd
        34: istore_2
        35: goto          26
        38: iload_2
        39: ireturn
      LineNumberTable:
        line 85: 0
        line 86: 5
        line 88: 8
        line 89: 14
        line 91: 17
        line 92: 23
        line 93: 26
        line 94: 31
        line 96: 38
      LocalVariableTable:
        Start  Length  Slot  Name   Signature
            0      40     0  size   I
           23      17     1 needed   I
           26      14     2 result   I
      StackMapTable: number_of_entries = 4
        frame_type = 8 /* same */
        frame_type = 8 /* same */
        frame_type = 253 /* append */
          offset_delta = 8
          locals = [ int, int ]
        frame_type = 11 /* same */

  public java.lang.Object find(java.lang.String);
    descriptor: (Ljava/lang/String;)Ljava/lang/Object;
    flags: (0x0001) ACC_PUBLIC
    Code:
      stack=4, locals=5, args_size=2
         0: aload_1
         1: invokevirtual #17                 // Method java/lang/String.hashCode:()I
         4: aload_0
         5: getfield      #2                  // Field _hashMask:I
         8: iand
         9: istore_2
        10: iload_2
        11: iconst_1
        12: ishl
        13: istore_3
        14: aload_0
        15: getfield      #4                  // Field _hashArea:[Ljava/lang/Object;
        18: iload_3
        19: aaload
        20: astore        4
        22: aload         4
        24: aload_1
        25: if_acmpeq     37
        28: aload_1
        29: aload         4
        31: invokevirtual #22                 // Method java/lang/String.equals:(Ljava/lang/Object;)Z
        34: ifeq          46
        37: aload_0
        38: getfield      #4                  // Field _hashArea:[Ljava/lang/Object;
        41: iload_3
        42: iconst_1
        43: iadd
        44: aaload
        45: areturn
        46: aload_0
        47: aload_1
        48: iload_2
        49: aload         4
        51: invokespecial #23                 // Method _find2:(Ljava/lang/String;ILjava/lang/Object;)Ljava/lang/Object;
        54: areturn
      LineNumberTable:
        line 100: 0
        line 101: 10
        line 102: 14
        line 103: 22
        line 104: 37
        line 106: 46
      LocalVariableTable:
        Start  Length  Slot  Name   Signature
            0      55     0  this   Lcom/fasterxml/jackson/databind/util/CompactStringObjectMap;
            0      55     1   key   Ljava/lang/String;
           10      45     2  slot   I
           14      41     3    ix   I
           22      33     4 match   Ljava/lang/Object;
      StackMapTable: number_of_entries = 2
        frame_type = 254 /* append */
          offset_delta = 37
          locals = [ int, int, class java/lang/Object ]
        frame_type = 8 /* same */

  private final java.lang.Object _find2(java.lang.String, int, java.lang.Object);
    descriptor: (Ljava/lang/String;ILjava/lang/Object;)Ljava/lang/Object;
    flags: (0x0012) ACC_PRIVATE, ACC_FINAL
    Code:
      stack=3, locals=8, args_size=4
         0: aload_3
         1: ifnonnull     6
         4: aconst_null
         5: areturn
         6: aload_0
         7: getfield      #2                  // Field _hashMask:I
        10: iconst_1
        11: iadd
        12: istore        4
        14: iload         4
        16: iload_2
        17: iconst_1
        18: ishr
        19: iadd
        20: iconst_1
        21: ishl
        22: istore        5
        24: aload_0
        25: getfield      #4                  // Field _hashArea:[Ljava/lang/Object;
        28: iload         5
        30: aaload
        31: astore_3
        32: aload_1
        33: aload_3
        34: invokevirtual #22                 // Method java/lang/String.equals:(Ljava/lang/Object;)Z
        37: ifeq          50
        40: aload_0
        41: getfield      #4                  // Field _hashArea:[Ljava/lang/Object;
        44: iload         5
        46: iconst_1
        47: iadd
        48: aaload
        49: areturn
        50: aload_3
        51: ifnull        118
        54: iload         4
        56: iload         4
        58: iconst_1
        59: ishr
        60: iadd
        61: iconst_1
        62: ishl
        63: istore        6
        65: iload         6
        67: aload_0
        68: getfield      #3                  // Field _spillCount:I
        71: iadd
        72: istore        7
        74: iload         6
        76: iload         7
        78: if_icmpge     118
        81: aload_0
        82: getfield      #4                  // Field _hashArea:[Ljava/lang/Object;
        85: iload         6
        87: aaload
        88: astore_3
        89: aload_3
        90: aload_1
        91: if_acmpeq     102
        94: aload_1
        95: aload_3
        96: invokevirtual #22                 // Method java/lang/String.equals:(Ljava/lang/Object;)Z
        99: ifeq          112
       102: aload_0
       103: getfield      #4                  // Field _hashArea:[Ljava/lang/Object;
       106: iload         6
       108: iconst_1
       109: iadd
       110: aaload
       111: areturn
       112: iinc          6, 2
       115: goto          74
       118: aconst_null
       119: areturn
      LineNumberTable:
        line 111: 0
        line 112: 4
        line 114: 6
        line 115: 14
        line 116: 24
        line 117: 32
        line 118: 40
        line 120: 50
        line 121: 54
        line 122: 65
        line 123: 81
        line 124: 89
        line 125: 102
        line 122: 112
        line 129: 118
      LocalVariableTable:
        Start  Length  Slot  Name   Signature
           74      44     7   end   I
           65      53     6     i   I
            0     120     0  this   Lcom/fasterxml/jackson/databind/util/CompactStringObjectMap;
            0     120     1   key   Ljava/lang/String;
            0     120     2  slot   I
            0     120     3 match   Ljava/lang/Object;
           14     106     4 hashSize   I
           24      96     5    ix   I
      StackMapTable: number_of_entries = 6
        frame_type = 6 /* same */
        frame_type = 253 /* append */
          offset_delta = 43
          locals = [ int, int ]
        frame_type = 253 /* append */
          offset_delta = 23
          locals = [ int, int ]
        frame_type = 27 /* same */
        frame_type = 9 /* same */
        frame_type = 249 /* chop */
          offset_delta = 5

  public java.lang.Object findCaseInsensitive(java.lang.String);
    descriptor: (Ljava/lang/String;)Ljava/lang/Object;
    flags: (0x0001) ACC_PUBLIC
    Code:
      stack=3, locals=6, args_size=2
         0: iconst_0
         1: istore_2
         2: aload_0
         3: getfield      #4                  // Field _hashArea:[Ljava/lang/Object;
         6: arraylength
         7: istore_3
         8: iload_2
         9: iload_3
        10: if_icmpge     57
        13: aload_0
        14: getfield      #4                  // Field _hashArea:[Ljava/lang/Object;
        17: iload_2
        18: aaload
        19: astore        4
        21: aload         4
        23: ifnull        51
        26: aload         4
        28: checkcast     #16                 // class java/lang/String
        31: astore        5
        33: aload         5
        35: aload_1
        36: invokevirtual #24                 // Method java/lang/String.equalsIgnoreCase:(Ljava/lang/String;)Z
        39: ifeq          51
        42: aload_0
        43: getfield      #4                  // Field _hashArea:[Ljava/lang/Object;
        46: iload_2
        47: iconst_1
        48: iadd
        49: aaload
        50: areturn
        51: iinc          2, 2
        54: goto          8
        57: aconst_null
        58: areturn
      LineNumberTable:
        line 134: 0
        line 135: 13
        line 136: 21
        line 137: 26
        line 138: 33
        line 139: 42
        line 134: 51
        line 143: 57
      LocalVariableTable:
        Start  Length  Slot  Name   Signature
           33      18     5     s   Ljava/lang/String;
           21      30     4    k2   Ljava/lang/Object;
            2      55     2     i   I
            8      49     3   end   I
            0      59     0  this   Lcom/fasterxml/jackson/databind/util/CompactStringObjectMap;
            0      59     1   key   Ljava/lang/String;
      StackMapTable: number_of_entries = 3
        frame_type = 253 /* append */
          offset_delta = 8
          locals = [ int, int ]
        frame_type = 42 /* same */
        frame_type = 249 /* chop */
          offset_delta = 5

  public java.util.List<java.lang.String> keys();
    descriptor: ()Ljava/util/List;
    flags: (0x0001) ACC_PUBLIC
    Code:
      stack=4, locals=5, args_size=1
         0: aload_0
         1: getfield      #4                  // Field _hashArea:[Ljava/lang/Object;
         4: arraylength
         5: istore_1
         6: new           #25                 // class java/util/ArrayList
         9: dup
        10: iload_1
        11: iconst_2
        12: ishr
        13: invokespecial #26                 // Method java/util/ArrayList."<init>":(I)V
        16: astore_2
        17: iconst_0
        18: istore_3
        19: iload_3
        20: iload_1
        21: if_icmpge     55
        24: aload_0
        25: getfield      #4                  // Field _hashArea:[Ljava/lang/Object;
        28: iload_3
        29: aaload
        30: astore        4
        32: aload         4
        34: ifnull        49
        37: aload_2
        38: aload         4
        40: checkcast     #16                 // class java/lang/String
        43: invokeinterface #27,  2           // InterfaceMethod java/util/List.add:(Ljava/lang/Object;)Z
        48: pop
        49: iinc          3, 2
        52: goto          19
        55: aload_2
        56: areturn
      LineNumberTable:
        line 147: 0
        line 148: 6
        line 149: 17
        line 150: 24
        line 151: 32
        line 152: 37
        line 149: 49
        line 155: 55
      LocalVariableTable:
        Start  Length  Slot  Name   Signature
           32      17     4   key   Ljava/lang/Object;
           19      36     3     i   I
            0      57     0  this   Lcom/fasterxml/jackson/databind/util/CompactStringObjectMap;
            6      51     1   end   I
           17      40     2  keys   Ljava/util/List;
      LocalVariableTypeTable:
        Start  Length  Slot  Name   Signature
           17      40     2  keys   Ljava/util/List<Ljava/lang/String;>;
      StackMapTable: number_of_entries = 3
        frame_type = 254 /* append */
          offset_delta = 19
          locals = [ int, class java/util/List, int ]
        frame_type = 29 /* same */
        frame_type = 250 /* chop */
          offset_delta = 5
    Signature: #98                          // ()Ljava/util/List<Ljava/lang/String;>;

  static {};
    descriptor: ()V
    flags: (0x0008) ACC_STATIC
    Code:
      stack=5, locals=0, args_size=0
         0: new           #20                 // class com/fasterxml/jackson/databind/util/CompactStringObjectMap
         3: dup
         4: iconst_1
         5: iconst_0
         6: iconst_4
         7: anewarray     #9                  // class java/lang/Object
        10: invokespecial #21                 // Method "<init>":(II[Ljava/lang/Object;)V
        13: putstatic     #6                  // Field EMPTY:Lcom/fasterxml/jackson/databind/util/CompactStringObjectMap;
        16: return
      LineNumberTable:
        line 25: 0
}
SourceFile: "CompactStringObjectMap.java"
InnerClasses:
  public static #57= #14 of #107;         // Entry=class java/util/Map$Entry of class java/util/Map
