Classfile /Users/mw/Projects/slang-braindump/.jar/jar8/assemble/slang-braindump/assemble/content/com/fasterxml/jackson/databind/util/RootNameLookup.class
  Last modified May 29, 2022; size 3610 bytes
  SHA-256 checksum 8701b5fcde484b67419b247391e908bf6661715bb4adc4095ebaf8306399f767
  Compiled from "RootNameLookup.java"
public class com.fasterxml.jackson.databind.util.RootNameLookup implements java.io.Serializable
  minor version: 0
  major version: 52
  flags: (0x0021) ACC_PUBLIC, ACC_SUPER
  this_class: #19                         // com/fasterxml/jackson/databind/util/RootNameLookup
  super_class: #21                        // java/lang/Object
  interfaces: 1, fields: 2, methods: 4, attributes: 1
Constant pool:
    #1 = Methodref          #21.#72       // java/lang/Object."<init>":()V
    #2 = Class              #73           // com/fasterxml/jackson/databind/util/LRUMap
    #3 = Methodref          #2.#74        // com/fasterxml/jackson/databind/util/LRUMap."<init>":(II)V
    #4 = Fieldref           #19.#75       // com/fasterxml/jackson/databind/util/RootNameLookup._rootNames:Lcom/fasterxml/jackson/databind/util/LRUMap;
    #5 = Methodref          #76.#77       // com/fasterxml/jackson/databind/JavaType.getRawClass:()Ljava/lang/Class;
    #6 = Methodref          #19.#78       // com/fasterxml/jackson/databind/util/RootNameLookup.findRootName:(Ljava/lang/Class;Lcom/fasterxml/jackson/databind/cfg/MapperConfig;)Lcom/fasterxml/jackson/databind/PropertyName;
    #7 = Class              #79           // com/fasterxml/jackson/databind/type/ClassKey
    #8 = Methodref          #7.#80        // com/fasterxml/jackson/databind/type/ClassKey."<init>":(Ljava/lang/Class;)V
    #9 = Methodref          #2.#81        // com/fasterxml/jackson/databind/util/LRUMap.get:(Ljava/lang/Object;)Ljava/lang/Object;
   #10 = Class              #82           // com/fasterxml/jackson/databind/PropertyName
   #11 = Methodref          #83.#84       // com/fasterxml/jackson/databind/cfg/MapperConfig.introspectClassAnnotations:(Ljava/lang/Class;)Lcom/fasterxml/jackson/databind/BeanDescription;
   #12 = Methodref          #83.#85       // com/fasterxml/jackson/databind/cfg/MapperConfig.getAnnotationIntrospector:()Lcom/fasterxml/jackson/databind/AnnotationIntrospector;
   #13 = Methodref          #86.#87       // com/fasterxml/jackson/databind/BeanDescription.getClassInfo:()Lcom/fasterxml/jackson/databind/introspect/AnnotatedClass;
   #14 = Methodref          #88.#89       // com/fasterxml/jackson/databind/AnnotationIntrospector.findRootName:(Lcom/fasterxml/jackson/databind/introspect/AnnotatedClass;)Lcom/fasterxml/jackson/databind/PropertyName;
   #15 = Methodref          #10.#90       // com/fasterxml/jackson/databind/PropertyName.hasSimpleName:()Z
   #16 = Methodref          #91.#92       // java/lang/Class.getSimpleName:()Ljava/lang/String;
   #17 = Methodref          #10.#93       // com/fasterxml/jackson/databind/PropertyName.construct:(Ljava/lang/String;)Lcom/fasterxml/jackson/databind/PropertyName;
   #18 = Methodref          #2.#94        // com/fasterxml/jackson/databind/util/LRUMap.put:(Ljava/lang/Object;Ljava/lang/Object;)Ljava/lang/Object;
   #19 = Class              #95           // com/fasterxml/jackson/databind/util/RootNameLookup
   #20 = Methodref          #19.#72       // com/fasterxml/jackson/databind/util/RootNameLookup."<init>":()V
   #21 = Class              #96           // java/lang/Object
   #22 = Class              #97           // java/io/Serializable
   #23 = Utf8               serialVersionUID
   #24 = Utf8               J
   #25 = Utf8               ConstantValue
   #26 = Long               1l
   #28 = Utf8               _rootNames
   #29 = Utf8               Lcom/fasterxml/jackson/databind/util/LRUMap;
   #30 = Utf8               Signature
   #31 = Utf8               Lcom/fasterxml/jackson/databind/util/LRUMap<Lcom/fasterxml/jackson/databind/type/ClassKey;Lcom/fasterxml/jackson/databind/PropertyName;>;
   #32 = Utf8               <init>
   #33 = Utf8               ()V
   #34 = Utf8               Code
   #35 = Utf8               LineNumberTable
   #36 = Utf8               LocalVariableTable
   #37 = Utf8               this
   #38 = Utf8               Lcom/fasterxml/jackson/databind/util/RootNameLookup;
   #39 = Utf8               findRootName
   #40 = Utf8               (Lcom/fasterxml/jackson/databind/JavaType;Lcom/fasterxml/jackson/databind/cfg/MapperConfig;)Lcom/fasterxml/jackson/databind/PropertyName;
   #41 = Utf8               rootType
   #42 = Utf8               Lcom/fasterxml/jackson/databind/JavaType;
   #43 = Utf8               config
   #44 = Utf8               Lcom/fasterxml/jackson/databind/cfg/MapperConfig;
   #45 = Utf8               LocalVariableTypeTable
   #46 = Utf8               Lcom/fasterxml/jackson/databind/cfg/MapperConfig<*>;
   #47 = Utf8               (Lcom/fasterxml/jackson/databind/JavaType;Lcom/fasterxml/jackson/databind/cfg/MapperConfig<*>;)Lcom/fasterxml/jackson/databind/PropertyName;
   #48 = Utf8               (Ljava/lang/Class;Lcom/fasterxml/jackson/databind/cfg/MapperConfig;)Lcom/fasterxml/jackson/databind/PropertyName;
   #49 = Utf8               Ljava/lang/Class;
   #50 = Utf8               key
   #51 = Utf8               Lcom/fasterxml/jackson/databind/type/ClassKey;
   #52 = Utf8               name
   #53 = Utf8               Lcom/fasterxml/jackson/databind/PropertyName;
   #54 = Utf8               beanDesc
   #55 = Utf8               Lcom/fasterxml/jackson/databind/BeanDescription;
   #56 = Utf8               intr
   #57 = Utf8               Lcom/fasterxml/jackson/databind/AnnotationIntrospector;
   #58 = Utf8               ac
   #59 = Utf8               Lcom/fasterxml/jackson/databind/introspect/AnnotatedClass;
   #60 = Utf8               Ljava/lang/Class<*>;
   #61 = Utf8               StackMapTable
   #62 = Class              #79           // com/fasterxml/jackson/databind/type/ClassKey
   #63 = Class              #82           // com/fasterxml/jackson/databind/PropertyName
   #64 = Class              #98           // com/fasterxml/jackson/databind/BeanDescription
   #65 = Class              #99           // com/fasterxml/jackson/databind/AnnotationIntrospector
   #66 = Class              #100          // com/fasterxml/jackson/databind/introspect/AnnotatedClass
   #67 = Utf8               (Ljava/lang/Class<*>;Lcom/fasterxml/jackson/databind/cfg/MapperConfig<*>;)Lcom/fasterxml/jackson/databind/PropertyName;
   #68 = Utf8               readResolve
   #69 = Utf8               ()Ljava/lang/Object;
   #70 = Utf8               SourceFile
   #71 = Utf8               RootNameLookup.java
   #72 = NameAndType        #32:#33       // "<init>":()V
   #73 = Utf8               com/fasterxml/jackson/databind/util/LRUMap
   #74 = NameAndType        #32:#101      // "<init>":(II)V
   #75 = NameAndType        #28:#29       // _rootNames:Lcom/fasterxml/jackson/databind/util/LRUMap;
   #76 = Class              #102          // com/fasterxml/jackson/databind/JavaType
   #77 = NameAndType        #103:#104     // getRawClass:()Ljava/lang/Class;
   #78 = NameAndType        #39:#48       // findRootName:(Ljava/lang/Class;Lcom/fasterxml/jackson/databind/cfg/MapperConfig;)Lcom/fasterxml/jackson/databind/PropertyName;
   #79 = Utf8               com/fasterxml/jackson/databind/type/ClassKey
   #80 = NameAndType        #32:#105      // "<init>":(Ljava/lang/Class;)V
   #81 = NameAndType        #106:#107     // get:(Ljava/lang/Object;)Ljava/lang/Object;
   #82 = Utf8               com/fasterxml/jackson/databind/PropertyName
   #83 = Class              #108          // com/fasterxml/jackson/databind/cfg/MapperConfig
   #84 = NameAndType        #109:#110     // introspectClassAnnotations:(Ljava/lang/Class;)Lcom/fasterxml/jackson/databind/BeanDescription;
   #85 = NameAndType        #111:#112     // getAnnotationIntrospector:()Lcom/fasterxml/jackson/databind/AnnotationIntrospector;
   #86 = Class              #98           // com/fasterxml/jackson/databind/BeanDescription
   #87 = NameAndType        #113:#114     // getClassInfo:()Lcom/fasterxml/jackson/databind/introspect/AnnotatedClass;
   #88 = Class              #99           // com/fasterxml/jackson/databind/AnnotationIntrospector
   #89 = NameAndType        #39:#115      // findRootName:(Lcom/fasterxml/jackson/databind/introspect/AnnotatedClass;)Lcom/fasterxml/jackson/databind/PropertyName;
   #90 = NameAndType        #116:#117     // hasSimpleName:()Z
   #91 = Class              #118          // java/lang/Class
   #92 = NameAndType        #119:#120     // getSimpleName:()Ljava/lang/String;
   #93 = NameAndType        #121:#122     // construct:(Ljava/lang/String;)Lcom/fasterxml/jackson/databind/PropertyName;
   #94 = NameAndType        #123:#124     // put:(Ljava/lang/Object;Ljava/lang/Object;)Ljava/lang/Object;
   #95 = Utf8               com/fasterxml/jackson/databind/util/RootNameLookup
   #96 = Utf8               java/lang/Object
   #97 = Utf8               java/io/Serializable
   #98 = Utf8               com/fasterxml/jackson/databind/BeanDescription
   #99 = Utf8               com/fasterxml/jackson/databind/AnnotationIntrospector
  #100 = Utf8               com/fasterxml/jackson/databind/introspect/AnnotatedClass
  #101 = Utf8               (II)V
  #102 = Utf8               com/fasterxml/jackson/databind/JavaType
  #103 = Utf8               getRawClass
  #104 = Utf8               ()Ljava/lang/Class;
  #105 = Utf8               (Ljava/lang/Class;)V
  #106 = Utf8               get
  #107 = Utf8               (Ljava/lang/Object;)Ljava/lang/Object;
  #108 = Utf8               com/fasterxml/jackson/databind/cfg/MapperConfig
  #109 = Utf8               introspectClassAnnotations
  #110 = Utf8               (Ljava/lang/Class;)Lcom/fasterxml/jackson/databind/BeanDescription;
  #111 = Utf8               getAnnotationIntrospector
  #112 = Utf8               ()Lcom/fasterxml/jackson/databind/AnnotationIntrospector;
  #113 = Utf8               getClassInfo
  #114 = Utf8               ()Lcom/fasterxml/jackson/databind/introspect/AnnotatedClass;
  #115 = Utf8               (Lcom/fasterxml/jackson/databind/introspect/AnnotatedClass;)Lcom/fasterxml/jackson/databind/PropertyName;
  #116 = Utf8               hasSimpleName
  #117 = Utf8               ()Z
  #118 = Utf8               java/lang/Class
  #119 = Utf8               getSimpleName
  #120 = Utf8               ()Ljava/lang/String;
  #121 = Utf8               construct
  #122 = Utf8               (Ljava/lang/String;)Lcom/fasterxml/jackson/databind/PropertyName;
  #123 = Utf8               put
  #124 = Utf8               (Ljava/lang/Object;Ljava/lang/Object;)Ljava/lang/Object;
{
  private static final long serialVersionUID;
    descriptor: J
    flags: (0x001a) ACC_PRIVATE, ACC_STATIC, ACC_FINAL
    ConstantValue: long 1l

  protected transient com.fasterxml.jackson.databind.util.LRUMap<com.fasterxml.jackson.databind.type.ClassKey, com.fasterxml.jackson.databind.PropertyName> _rootNames;
    descriptor: Lcom/fasterxml/jackson/databind/util/LRUMap;
    flags: (0x0084) ACC_PROTECTED, ACC_TRANSIENT
    Signature: #31                          // Lcom/fasterxml/jackson/databind/util/LRUMap<Lcom/fasterxml/jackson/databind/type/ClassKey;Lcom/fasterxml/jackson/databind/PropertyName;>;

  public com.fasterxml.jackson.databind.util.RootNameLookup();
    descriptor: ()V
    flags: (0x0001) ACC_PUBLIC
    Code:
      stack=5, locals=1, args_size=1
         0: aload_0
         1: invokespecial #1                  // Method java/lang/Object."<init>":()V
         4: aload_0
         5: new           #2                  // class com/fasterxml/jackson/databind/util/LRUMap
         8: dup
         9: bipush        20
        11: sipush        200
        14: invokespecial #3                  // Method com/fasterxml/jackson/databind/util/LRUMap."<init>":(II)V
        17: putfield      #4                  // Field _rootNames:Lcom/fasterxml/jackson/databind/util/LRUMap;
        20: return
      LineNumberTable:
        line 21: 0
        line 22: 4
        line 23: 20
      LocalVariableTable:
        Start  Length  Slot  Name   Signature
            0      21     0  this   Lcom/fasterxml/jackson/databind/util/RootNameLookup;

  public com.fasterxml.jackson.databind.PropertyName findRootName(com.fasterxml.jackson.databind.JavaType, com.fasterxml.jackson.databind.cfg.MapperConfig<?>);
    descriptor: (Lcom/fasterxml/jackson/databind/JavaType;Lcom/fasterxml/jackson/databind/cfg/MapperConfig;)Lcom/fasterxml/jackson/databind/PropertyName;
    flags: (0x0001) ACC_PUBLIC
    Code:
      stack=3, locals=3, args_size=3
         0: aload_0
         1: aload_1
         2: invokevirtual #5                  // Method com/fasterxml/jackson/databind/JavaType.getRawClass:()Ljava/lang/Class;
         5: aload_2
         6: invokevirtual #6                  // Method findRootName:(Ljava/lang/Class;Lcom/fasterxml/jackson/databind/cfg/MapperConfig;)Lcom/fasterxml/jackson/databind/PropertyName;
         9: areturn
      LineNumberTable:
        line 26: 0
      LocalVariableTable:
        Start  Length  Slot  Name   Signature
            0      10     0  this   Lcom/fasterxml/jackson/databind/util/RootNameLookup;
            0      10     1 rootType   Lcom/fasterxml/jackson/databind/JavaType;
            0      10     2 config   Lcom/fasterxml/jackson/databind/cfg/MapperConfig;
      LocalVariableTypeTable:
        Start  Length  Slot  Name   Signature
            0      10     2 config   Lcom/fasterxml/jackson/databind/cfg/MapperConfig<*>;
    Signature: #47                          // (Lcom/fasterxml/jackson/databind/JavaType;Lcom/fasterxml/jackson/databind/cfg/MapperConfig<*>;)Lcom/fasterxml/jackson/databind/PropertyName;

  public com.fasterxml.jackson.databind.PropertyName findRootName(java.lang.Class<?>, com.fasterxml.jackson.databind.cfg.MapperConfig<?>);
    descriptor: (Ljava/lang/Class;Lcom/fasterxml/jackson/databind/cfg/MapperConfig;)Lcom/fasterxml/jackson/databind/PropertyName;
    flags: (0x0001) ACC_PUBLIC
    Code:
      stack=3, locals=8, args_size=3
         0: new           #7                  // class com/fasterxml/jackson/databind/type/ClassKey
         3: dup
         4: aload_1
         5: invokespecial #8                  // Method com/fasterxml/jackson/databind/type/ClassKey."<init>":(Ljava/lang/Class;)V
         8: astore_3
         9: aload_0
        10: getfield      #4                  // Field _rootNames:Lcom/fasterxml/jackson/databind/util/LRUMap;
        13: aload_3
        14: invokevirtual #9                  // Method com/fasterxml/jackson/databind/util/LRUMap.get:(Ljava/lang/Object;)Ljava/lang/Object;
        17: checkcast     #10                 // class com/fasterxml/jackson/databind/PropertyName
        20: astore        4
        22: aload         4
        24: ifnull        30
        27: aload         4
        29: areturn
        30: aload_2
        31: aload_1
        32: invokevirtual #11                 // Method com/fasterxml/jackson/databind/cfg/MapperConfig.introspectClassAnnotations:(Ljava/lang/Class;)Lcom/fasterxml/jackson/databind/BeanDescription;
        35: astore        5
        37: aload_2
        38: invokevirtual #12                 // Method com/fasterxml/jackson/databind/cfg/MapperConfig.getAnnotationIntrospector:()Lcom/fasterxml/jackson/databind/AnnotationIntrospector;
        41: astore        6
        43: aload         5
        45: invokevirtual #13                 // Method com/fasterxml/jackson/databind/BeanDescription.getClassInfo:()Lcom/fasterxml/jackson/databind/introspect/AnnotatedClass;
        48: astore        7
        50: aload         6
        52: aload         7
        54: invokevirtual #14                 // Method com/fasterxml/jackson/databind/AnnotationIntrospector.findRootName:(Lcom/fasterxml/jackson/databind/introspect/AnnotatedClass;)Lcom/fasterxml/jackson/databind/PropertyName;
        57: astore        4
        59: aload         4
        61: ifnull        72
        64: aload         4
        66: invokevirtual #15                 // Method com/fasterxml/jackson/databind/PropertyName.hasSimpleName:()Z
        69: ifne          81
        72: aload_1
        73: invokevirtual #16                 // Method java/lang/Class.getSimpleName:()Ljava/lang/String;
        76: invokestatic  #17                 // Method com/fasterxml/jackson/databind/PropertyName.construct:(Ljava/lang/String;)Lcom/fasterxml/jackson/databind/PropertyName;
        79: astore        4
        81: aload_0
        82: getfield      #4                  // Field _rootNames:Lcom/fasterxml/jackson/databind/util/LRUMap;
        85: aload_3
        86: aload         4
        88: invokevirtual #18                 // Method com/fasterxml/jackson/databind/util/LRUMap.put:(Ljava/lang/Object;Ljava/lang/Object;)Ljava/lang/Object;
        91: pop
        92: aload         4
        94: areturn
      LineNumberTable:
        line 31: 0
        line 32: 9
        line 33: 22
        line 34: 27
        line 36: 30
        line 37: 37
        line 38: 43
        line 39: 50
        line 41: 59
        line 43: 72
        line 45: 81
        line 46: 92
      LocalVariableTable:
        Start  Length  Slot  Name   Signature
            0      95     0  this   Lcom/fasterxml/jackson/databind/util/RootNameLookup;
            0      95     1 rootType   Ljava/lang/Class;
            0      95     2 config   Lcom/fasterxml/jackson/databind/cfg/MapperConfig;
            9      86     3   key   Lcom/fasterxml/jackson/databind/type/ClassKey;
           22      73     4  name   Lcom/fasterxml/jackson/databind/PropertyName;
           37      58     5 beanDesc   Lcom/fasterxml/jackson/databind/BeanDescription;
           43      52     6  intr   Lcom/fasterxml/jackson/databind/AnnotationIntrospector;
           50      45     7    ac   Lcom/fasterxml/jackson/databind/introspect/AnnotatedClass;
      LocalVariableTypeTable:
        Start  Length  Slot  Name   Signature
            0      95     1 rootType   Ljava/lang/Class<*>;
            0      95     2 config   Lcom/fasterxml/jackson/databind/cfg/MapperConfig<*>;
      StackMapTable: number_of_entries = 3
        frame_type = 253 /* append */
          offset_delta = 30
          locals = [ class com/fasterxml/jackson/databind/type/ClassKey, class com/fasterxml/jackson/databind/PropertyName ]
        frame_type = 254 /* append */
          offset_delta = 41
          locals = [ class com/fasterxml/jackson/databind/BeanDescription, class com/fasterxml/jackson/databind/AnnotationIntrospector, class com/fasterxml/jackson/databind/introspect/AnnotatedClass ]
        frame_type = 8 /* same */
    Signature: #67                          // (Ljava/lang/Class<*>;Lcom/fasterxml/jackson/databind/cfg/MapperConfig<*>;)Lcom/fasterxml/jackson/databind/PropertyName;

  protected java.lang.Object readResolve();
    descriptor: ()Ljava/lang/Object;
    flags: (0x0004) ACC_PROTECTED
    Code:
      stack=2, locals=1, args_size=1
         0: new           #19                 // class com/fasterxml/jackson/databind/util/RootNameLookup
         3: dup
         4: invokespecial #20                 // Method "<init>":()V
         7: areturn
      LineNumberTable:
        line 60: 0
      LocalVariableTable:
        Start  Length  Slot  Name   Signature
            0       8     0  this   Lcom/fasterxml/jackson/databind/util/RootNameLookup;
}
SourceFile: "RootNameLookup.java"
