Classfile /Users/mw/Projects/slang-braindump/.jar/jar11/assemble/slang-braindump/assemble/content/coursier/Artifacts$ArtifactsTaskOps$.class
  Last modified May 29, 2022; size 7067 bytes
  SHA-256 checksum 8b518ae21742ca141399bcbbc702299c74497f683f155be96bd26c2d980e33c0
  Compiled from "Artifacts.scala"
public class coursier.Artifacts$ArtifactsTaskOps$
  minor version: 0
  major version: 52
  flags: (0x0021) ACC_PUBLIC, ACC_SUPER
  this_class: #2                          // coursier/Artifacts$ArtifactsTaskOps$
  super_class: #4                         // java/lang/Object
  interfaces: 0, fields: 1, methods: 19, attributes: 5
Constant pool:
    #1 = Utf8               coursier/Artifacts$ArtifactsTaskOps$
    #2 = Class              #1            // coursier/Artifacts$ArtifactsTaskOps$
    #3 = Utf8               java/lang/Object
    #4 = Class              #3            // java/lang/Object
    #5 = Utf8               Artifacts.scala
    #6 = Utf8               coursier/Artifacts$ArtifactsTaskOps
    #7 = Class              #6            // coursier/Artifacts$ArtifactsTaskOps
    #8 = Utf8               coursier/Artifacts
    #9 = Class              #8            // coursier/Artifacts
   #10 = Utf8               ArtifactsTaskOps
   #11 = Utf8
   #12 = Utf8               coursier/Artifacts$ArtifactsTaskOps$$anonfun$1
   #13 = Class              #12           // coursier/Artifacts$ArtifactsTaskOps$$anonfun$1
   #14 = Utf8               coursier/Artifacts$ArtifactsTaskOps$$anonfun$2
   #15 = Class              #14           // coursier/Artifacts$ArtifactsTaskOps$$anonfun$2
   #16 = Utf8               coursier/Artifacts$Result
   #17 = Class              #16           // coursier/Artifacts$Result
   #18 = Utf8               Result
   #19 = Utf8               java/lang/invoke/MethodHandles$Lookup
   #20 = Class              #19           // java/lang/invoke/MethodHandles$Lookup
   #21 = Utf8               java/lang/invoke/MethodHandles
   #22 = Class              #21           // java/lang/invoke/MethodHandles
   #23 = Utf8               Lookup
   #24 = Utf8               scala/concurrent/duration/Duration$Infinite
   #25 = Class              #24           // scala/concurrent/duration/Duration$Infinite
   #26 = Utf8               scala/concurrent/duration/Duration
   #27 = Class              #26           // scala/concurrent/duration/Duration
   #28 = Utf8               Infinite
   #29 = Utf8               MODULE$
   #30 = Utf8               Lcoursier/Artifacts$ArtifactsTaskOps$;
   #31 = Utf8               <clinit>
   #32 = Utf8               ()V
   #33 = Utf8               <init>
   #34 = NameAndType        #33:#32       // "<init>":()V
   #35 = Methodref          #2.#34        // coursier/Artifacts$ArtifactsTaskOps$."<init>":()V
   #36 = NameAndType        #29:#30       // MODULE$:Lcoursier/Artifacts$ArtifactsTaskOps$;
   #37 = Fieldref           #2.#36        // coursier/Artifacts$ArtifactsTaskOps$.MODULE$:Lcoursier/Artifacts$ArtifactsTaskOps$;
   #38 = Utf8               future$extension
   #39 = Utf8               (Lcoursier/Artifacts;Lscala/concurrent/ExecutionContext;)Lscala/concurrent/Future;
   #40 = Utf8               (Lcoursier/Artifacts<Lcoursier/util/Task;>;Lscala/concurrent/ExecutionContext;)Lscala/concurrent/Future<Lscala/collection/immutable/Seq<Lscala/Tuple2<Lcoursier/util/Artifact;Ljava/io/File;>;>;>;
   #41 = Utf8               $this
   #42 = Utf8               ec
   #43 = Utf8               coursier/util/Task$
   #44 = Class              #43           // coursier/util/Task$
   #45 = Utf8               Lcoursier/util/Task$;
   #46 = NameAndType        #29:#45       // MODULE$:Lcoursier/util/Task$;
   #47 = Fieldref           #44.#46       // coursier/util/Task$.MODULE$:Lcoursier/util/Task$;
   #48 = Utf8               io
   #49 = Utf8               ()Ljava/lang/Object;
   #50 = NameAndType        #48:#49       // io:()Ljava/lang/Object;
   #51 = Methodref          #9.#50        // coursier/Artifacts.io:()Ljava/lang/Object;
   #52 = Utf8               coursier/util/Task
   #53 = Class              #52           // coursier/util/Task
   #54 = Utf8               value
   #55 = Utf8               ()Lscala/Function1;
   #56 = NameAndType        #54:#55       // value:()Lscala/Function1;
   #57 = Methodref          #53.#56       // coursier/util/Task.value:()Lscala/Function1;
   #58 = Utf8               (Lscala/Function1;Lscala/concurrent/ExecutionContext;)Lscala/concurrent/Future;
   #59 = NameAndType        #38:#58       // future$extension:(Lscala/Function1;Lscala/concurrent/ExecutionContext;)Lscala/concurrent/Future;
   #60 = Methodref          #44.#59       // coursier/util/Task$.future$extension:(Lscala/Function1;Lscala/concurrent/ExecutionContext;)Lscala/concurrent/Future;
   #61 = Utf8               this
   #62 = Utf8               Lcoursier/Artifacts;
   #63 = Utf8               Lscala/concurrent/ExecutionContext;
   #64 = Utf8               future$default$1$extension
   #65 = Utf8               (Lcoursier/Artifacts;)Lscala/concurrent/ExecutionContext;
   #66 = Utf8               cache
   #67 = Utf8               ()Lcoursier/cache/Cache;
   #68 = NameAndType        #66:#67       // cache:()Lcoursier/cache/Cache;
   #69 = Methodref          #9.#68        // coursier/Artifacts.cache:()Lcoursier/cache/Cache;
   #70 = Utf8               coursier/cache/Cache
   #71 = Class              #70           // coursier/cache/Cache
   #72 = Utf8               ()Lscala/concurrent/ExecutionContext;
   #73 = NameAndType        #42:#72       // ec:()Lscala/concurrent/ExecutionContext;
   #74 = Methodref          #71.#73       // coursier/cache/Cache.ec:()Lscala/concurrent/ExecutionContext;
   #75 = Utf8               either$extension
   #76 = Utf8               (Lcoursier/Artifacts;Lscala/concurrent/ExecutionContext;)Lscala/util/Either;
   #77 = Utf8               (Lcoursier/Artifacts<Lcoursier/util/Task;>;Lscala/concurrent/ExecutionContext;)Lscala/util/Either<Lcoursier/error/FetchError;Lscala/collection/immutable/Seq<Lscala/Tuple2<Lcoursier/util/Artifact;Ljava/io/File;>;>;>;
   #78 = Utf8               (Ljava/lang/Object;)Ljava/lang/Object;
   #79 = MethodType         #78           //  (Ljava/lang/Object;)Ljava/lang/Object;
   #80 = Utf8               $anonfun$either$1
   #81 = Utf8               (Lscala/collection/immutable/Seq;)Lscala/util/Right;
   #82 = NameAndType        #80:#81       // $anonfun$either$1:(Lscala/collection/immutable/Seq;)Lscala/util/Right;
   #83 = Methodref          #2.#82        // coursier/Artifacts$ArtifactsTaskOps$.$anonfun$either$1:(Lscala/collection/immutable/Seq;)Lscala/util/Right;
   #84 = MethodHandle       6:#83         // REF_invokeStatic coursier/Artifacts$ArtifactsTaskOps$.$anonfun$either$1:(Lscala/collection/immutable/Seq;)Lscala/util/Right;
   #85 = MethodType         #81           //  (Lscala/collection/immutable/Seq;)Lscala/util/Right;
   #86 = Integer            5
   #87 = Integer            1
   #88 = Utf8               java/lang/invoke/LambdaMetafactory
   #89 = Class              #88           // java/lang/invoke/LambdaMetafactory
   #90 = Utf8               altMetafactory
   #91 = Utf8               (Ljava/lang/invoke/MethodHandles$Lookup;Ljava/lang/String;Ljava/lang/invoke/MethodType;[Ljava/lang/Object;)Ljava/lang/invoke/CallSite;
   #92 = NameAndType        #90:#91       // altMetafactory:(Ljava/lang/invoke/MethodHandles$Lookup;Ljava/lang/String;Ljava/lang/invoke/MethodType;[Ljava/lang/Object;)Ljava/lang/invoke/CallSite;
   #93 = Methodref          #89.#92       // java/lang/invoke/LambdaMetafactory.altMetafactory:(Ljava/lang/invoke/MethodHandles$Lookup;Ljava/lang/String;Ljava/lang/invoke/MethodType;[Ljava/lang/Object;)Ljava/lang/invoke/CallSite;
   #94 = MethodHandle       6:#93         // REF_invokeStatic java/lang/invoke/LambdaMetafactory.altMetafactory:(Ljava/lang/invoke/MethodHandles$Lookup;Ljava/lang/String;Ljava/lang/invoke/MethodType;[Ljava/lang/Object;)Ljava/lang/invoke/CallSite;
   #95 = Utf8               apply
   #96 = NameAndType        #95:#55       // apply:()Lscala/Function1;
   #97 = InvokeDynamic      #0:#96        // #0:apply:()Lscala/Function1;
   #98 = Utf8               map$extension
   #99 = Utf8               (Lscala/Function1;Lscala/Function1;)Lscala/Function1;
  #100 = NameAndType        #98:#99       // map$extension:(Lscala/Function1;Lscala/Function1;)Lscala/Function1;
  #101 = Methodref          #44.#100      // coursier/util/Task$.map$extension:(Lscala/Function1;Lscala/Function1;)Lscala/Function1;
  #102 = Methodref          #13.#34       // coursier/Artifacts$ArtifactsTaskOps$$anonfun$1."<init>":()V
  #103 = Utf8               handle$extension
  #104 = Utf8               (Lscala/Function1;Lscala/PartialFunction;)Lscala/Function1;
  #105 = NameAndType        #103:#104     // handle$extension:(Lscala/Function1;Lscala/PartialFunction;)Lscala/Function1;
  #106 = Methodref          #44.#105      // coursier/util/Task$.handle$extension:(Lscala/Function1;Lscala/PartialFunction;)Lscala/Function1;
  #107 = Utf8               scala/concurrent/Await$
  #108 = Class              #107          // scala/concurrent/Await$
  #109 = Utf8               Lscala/concurrent/Await$;
  #110 = NameAndType        #29:#109      // MODULE$:Lscala/concurrent/Await$;
  #111 = Fieldref           #108.#110     // scala/concurrent/Await$.MODULE$:Lscala/concurrent/Await$;
  #112 = Utf8               scala/concurrent/duration/Duration$
  #113 = Class              #112          // scala/concurrent/duration/Duration$
  #114 = Utf8               Lscala/concurrent/duration/Duration$;
  #115 = NameAndType        #29:#114      // MODULE$:Lscala/concurrent/duration/Duration$;
  #116 = Fieldref           #113.#115     // scala/concurrent/duration/Duration$.MODULE$:Lscala/concurrent/duration/Duration$;
  #117 = Utf8               Inf
  #118 = Utf8               ()Lscala/concurrent/duration/Duration$Infinite;
  #119 = NameAndType        #117:#118     // Inf:()Lscala/concurrent/duration/Duration$Infinite;
  #120 = Methodref          #113.#119     // scala/concurrent/duration/Duration$.Inf:()Lscala/concurrent/duration/Duration$Infinite;
  #121 = Utf8               result
  #122 = Utf8               (Lscala/concurrent/Awaitable;Lscala/concurrent/duration/Duration;)Ljava/lang/Object;
  #123 = NameAndType        #121:#122     // result:(Lscala/concurrent/Awaitable;Lscala/concurrent/duration/Duration;)Ljava/lang/Object;
  #124 = Methodref          #108.#123     // scala/concurrent/Await$.result:(Lscala/concurrent/Awaitable;Lscala/concurrent/duration/Duration;)Ljava/lang/Object;
  #125 = Utf8               scala/util/Either
  #126 = Class              #125          // scala/util/Either
  #127 = Utf8               f
  #128 = Utf8               Lscala/concurrent/Future;
  #129 = Utf8               either$default$1$extension
  #130 = Utf8               run$extension
  #131 = Utf8               (Lcoursier/Artifacts;Lscala/concurrent/ExecutionContext;)Lscala/collection/immutable/Seq;
  #132 = Utf8               (Lcoursier/Artifacts<Lcoursier/util/Task;>;Lscala/concurrent/ExecutionContext;)Lscala/collection/immutable/Seq<Lscala/Tuple2<Lcoursier/util/Artifact;Ljava/io/File;>;>;
  #133 = Utf8               scala/collection/immutable/Seq
  #134 = Class              #133          // scala/collection/immutable/Seq
  #135 = Utf8               run$default$1$extension
  #136 = Utf8               futureResult$extension
  #137 = Utf8               (Lcoursier/Artifacts<Lcoursier/util/Task;>;Lscala/concurrent/ExecutionContext;)Lscala/concurrent/Future<Lcoursier/Artifacts$Result;>;
  #138 = Utf8               ioResult
  #139 = NameAndType        #138:#49      // ioResult:()Ljava/lang/Object;
  #140 = Methodref          #9.#139       // coursier/Artifacts.ioResult:()Ljava/lang/Object;
  #141 = Utf8               futureResult$default$1$extension
  #142 = Utf8               eitherResult$extension
  #143 = Utf8               (Lcoursier/Artifacts<Lcoursier/util/Task;>;Lscala/concurrent/ExecutionContext;)Lscala/util/Either<Lcoursier/error/FetchError;Lcoursier/Artifacts$Result;>;
  #144 = Utf8               $anonfun$eitherResult$1
  #145 = Utf8               (Lcoursier/Artifacts$Result;)Lscala/util/Right;
  #146 = NameAndType        #144:#145     // $anonfun$eitherResult$1:(Lcoursier/Artifacts$Result;)Lscala/util/Right;
  #147 = Methodref          #2.#146       // coursier/Artifacts$ArtifactsTaskOps$.$anonfun$eitherResult$1:(Lcoursier/Artifacts$Result;)Lscala/util/Right;
  #148 = MethodHandle       6:#147        // REF_invokeStatic coursier/Artifacts$ArtifactsTaskOps$.$anonfun$eitherResult$1:(Lcoursier/Artifacts$Result;)Lscala/util/Right;
  #149 = MethodType         #145          //  (Lcoursier/Artifacts$Result;)Lscala/util/Right;
  #150 = InvokeDynamic      #1:#96        // #1:apply:()Lscala/Function1;
  #151 = Methodref          #15.#34       // coursier/Artifacts$ArtifactsTaskOps$$anonfun$2."<init>":()V
  #152 = Utf8               eitherResult$default$1$extension
  #153 = Utf8               runResult$extension
  #154 = Utf8               (Lcoursier/Artifacts;Lscala/concurrent/ExecutionContext;)Lcoursier/Artifacts$Result;
  #155 = Utf8               runResult$default$1$extension
  #156 = Utf8               hashCode$extension
  #157 = Utf8               (Lcoursier/Artifacts;)I
  #158 = Utf8               hashCode
  #159 = Utf8               ()I
  #160 = NameAndType        #158:#159     // hashCode:()I
  #161 = Methodref          #9.#160       // coursier/Artifacts.hashCode:()I
  #162 = Utf8               equals$extension
  #163 = Utf8               (Lcoursier/Artifacts;Ljava/lang/Object;)Z
  #164 = Utf8               x$1
  #165 = Utf8               coursier$Artifacts$ArtifactsTaskOps$$artifacts
  #166 = Utf8               ()Lcoursier/Artifacts;
  #167 = NameAndType        #165:#166     // coursier$Artifacts$ArtifactsTaskOps$$artifacts:()Lcoursier/Artifacts;
  #168 = Methodref          #7.#167       // coursier/Artifacts$ArtifactsTaskOps.coursier$Artifacts$ArtifactsTaskOps$$artifacts:()Lcoursier/Artifacts;
  #169 = Utf8               equals
  #170 = Utf8               (Ljava/lang/Object;)Z
  #171 = NameAndType        #169:#170     // equals:(Ljava/lang/Object;)Z
  #172 = Methodref          #4.#171       // java/lang/Object.equals:(Ljava/lang/Object;)Z
  #173 = Utf8               Ljava/lang/Object;
  #174 = Utf8               x$10
  #175 = Utf8               scala/package$
  #176 = Class              #175          // scala/package$
  #177 = Utf8               Lscala/package$;
  #178 = NameAndType        #29:#177      // MODULE$:Lscala/package$;
  #179 = Fieldref           #176.#178     // scala/package$.MODULE$:Lscala/package$;
  #180 = Utf8               Right
  #181 = Utf8               ()Lscala/util/Right$;
  #182 = NameAndType        #180:#181     // Right:()Lscala/util/Right$;
  #183 = Methodref          #176.#182     // scala/package$.Right:()Lscala/util/Right$;
  #184 = Utf8               scala/util/Right$
  #185 = Class              #184          // scala/util/Right$
  #186 = Utf8               (Ljava/lang/Object;)Lscala/util/Right;
  #187 = NameAndType        #95:#186      // apply:(Ljava/lang/Object;)Lscala/util/Right;
  #188 = Methodref          #185.#187     // scala/util/Right$.apply:(Ljava/lang/Object;)Lscala/util/Right;
  #189 = Utf8               Lscala/collection/immutable/Seq;
  #190 = Utf8               x$11
  #191 = Utf8               Lcoursier/Artifacts$Result;
  #192 = Methodref          #4.#34        // java/lang/Object."<init>":()V
  #193 = Utf8               $deserializeLambda$
  #194 = Utf8               (Ljava/lang/invoke/SerializedLambda;)Ljava/lang/Object;
  #195 = Utf8               scala/runtime/LambdaDeserialize
  #196 = Class              #195          // scala/runtime/LambdaDeserialize
  #197 = Utf8               bootstrap
  #198 = Utf8               (Ljava/lang/invoke/MethodHandles$Lookup;Ljava/lang/String;Ljava/lang/invoke/MethodType;[Ljava/lang/invoke/MethodHandle;)Ljava/lang/invoke/CallSite;
  #199 = NameAndType        #197:#198     // bootstrap:(Ljava/lang/invoke/MethodHandles$Lookup;Ljava/lang/String;Ljava/lang/invoke/MethodType;[Ljava/lang/invoke/MethodHandle;)Ljava/lang/invoke/CallSite;
  #200 = Methodref          #196.#199     // scala/runtime/LambdaDeserialize.bootstrap:(Ljava/lang/invoke/MethodHandles$Lookup;Ljava/lang/String;Ljava/lang/invoke/MethodType;[Ljava/lang/invoke/MethodHandle;)Ljava/lang/invoke/CallSite;
  #201 = MethodHandle       6:#200        // REF_invokeStatic scala/runtime/LambdaDeserialize.bootstrap:(Ljava/lang/invoke/MethodHandles$Lookup;Ljava/lang/String;Ljava/lang/invoke/MethodType;[Ljava/lang/invoke/MethodHandle;)Ljava/lang/invoke/CallSite;
  #202 = Utf8               lambdaDeserialize
  #203 = NameAndType        #202:#194     // lambdaDeserialize:(Ljava/lang/invoke/SerializedLambda;)Ljava/lang/Object;
  #204 = InvokeDynamic      #2:#203       // #2:lambdaDeserialize:(Ljava/lang/invoke/SerializedLambda;)Ljava/lang/Object;
  #205 = Utf8               Code
  #206 = Utf8               LineNumberTable
  #207 = Utf8               LocalVariableTable
  #208 = Utf8               Signature
  #209 = Utf8               MethodParameters
  #210 = Utf8               StackMapTable
  #211 = Utf8               InnerClasses
  #212 = Utf8               SourceFile
  #213 = Utf8               BootstrapMethods
  #214 = Utf8               ScalaInlineInfo
  #215 = Utf8               Scala
{
  public static final coursier.Artifacts$ArtifactsTaskOps$ MODULE$;
    descriptor: Lcoursier/Artifacts$ArtifactsTaskOps$;
    flags: (0x0019) ACC_PUBLIC, ACC_STATIC, ACC_FINAL

  public static {};
    descriptor: ()V
    flags: (0x0009) ACC_PUBLIC, ACC_STATIC
    Code:
      stack=2, locals=0, args_size=0
         0: new           #2                  // class coursier/Artifacts$ArtifactsTaskOps$
         3: dup
         4: invokespecial #35                 // Method "<init>":()V
         7: putstatic     #37                 // Field MODULE$:Lcoursier/Artifacts$ArtifactsTaskOps$;
        10: return
      LineNumberTable:
        line 161: 0

  public final scala.concurrent.Future<scala.collection.immutable.Seq<scala.Tuple2<coursier.util.Artifact, java.io.File>>> future$extension(coursier.Artifacts<coursier.util.Task>, scala.concurrent.ExecutionContext);
    descriptor: (Lcoursier/Artifacts;Lscala/concurrent/ExecutionContext;)Lscala/concurrent/Future;
    flags: (0x0011) ACC_PUBLIC, ACC_FINAL
    Code:
      stack=3, locals=3, args_size=3
         0: getstatic     #47                 // Field coursier/util/Task$.MODULE$:Lcoursier/util/Task$;
         3: aload_1
         4: invokevirtual #51                 // Method coursier/Artifacts.io:()Ljava/lang/Object;
         7: checkcast     #53                 // class coursier/util/Task
        10: invokevirtual #57                 // Method coursier/util/Task.value:()Lscala/Function1;
        13: aload_2
        14: invokevirtual #60                 // Method coursier/util/Task$.future$extension:(Lscala/Function1;Lscala/concurrent/ExecutionContext;)Lscala/concurrent/Future;
        17: areturn
      LineNumberTable:
        line 164: 3
      LocalVariableTable:
        Start  Length  Slot  Name   Signature
            0      18     0  this   Lcoursier/Artifacts$ArtifactsTaskOps$;
            0      18     1 $this   Lcoursier/Artifacts;
            0      18     2    ec   Lscala/concurrent/ExecutionContext;
    Signature: #40                          // (Lcoursier/Artifacts<Lcoursier/util/Task;>;Lscala/concurrent/ExecutionContext;)Lscala/concurrent/Future<Lscala/collection/immutable/Seq<Lscala/Tuple2<Lcoursier/util/Artifact;Ljava/io/File;>;>;>;
    MethodParameters:
      Name                           Flags
      $this                          final
      ec                             final

  public final scala.concurrent.ExecutionContext future$default$1$extension(coursier.Artifacts);
    descriptor: (Lcoursier/Artifacts;)Lscala/concurrent/ExecutionContext;
    flags: (0x0011) ACC_PUBLIC, ACC_FINAL
    Code:
      stack=1, locals=2, args_size=2
         0: aload_1
         1: invokevirtual #69                 // Method coursier/Artifacts.cache:()Lcoursier/cache/Cache;
         4: invokevirtual #74                 // Method coursier/cache/Cache.ec:()Lscala/concurrent/ExecutionContext;
         7: areturn
      LineNumberTable:
        line 163: 0
      LocalVariableTable:
        Start  Length  Slot  Name   Signature
            0       8     0  this   Lcoursier/Artifacts$ArtifactsTaskOps$;
            0       8     1 $this   Lcoursier/Artifacts;
    MethodParameters:
      Name                           Flags
      $this                          final

  public final scala.util.Either<coursier.error.FetchError, scala.collection.immutable.Seq<scala.Tuple2<coursier.util.Artifact, java.io.File>>> either$extension(coursier.Artifacts<coursier.util.Task>, scala.concurrent.ExecutionContext);
    descriptor: (Lcoursier/Artifacts;Lscala/concurrent/ExecutionContext;)Lscala/util/Either;
    flags: (0x0011) ACC_PUBLIC, ACC_FINAL
    Code:
      stack=5, locals=4, args_size=3
         0: getstatic     #47                 // Field coursier/util/Task$.MODULE$:Lcoursier/util/Task$;
         3: getstatic     #47                 // Field coursier/util/Task$.MODULE$:Lcoursier/util/Task$;
         6: getstatic     #47                 // Field coursier/util/Task$.MODULE$:Lcoursier/util/Task$;
         9: aload_1
        10: invokevirtual #51                 // Method coursier/Artifacts.io:()Ljava/lang/Object;
        13: checkcast     #53                 // class coursier/util/Task
        16: invokevirtual #57                 // Method coursier/util/Task.value:()Lscala/Function1;
        19: invokedynamic #97,  0             // InvokeDynamic #0:apply:()Lscala/Function1;
        24: invokevirtual #101                // Method coursier/util/Task$.map$extension:(Lscala/Function1;Lscala/Function1;)Lscala/Function1;
        27: new           #13                 // class coursier/Artifacts$ArtifactsTaskOps$$anonfun$1
        30: dup
        31: invokespecial #102                // Method coursier/Artifacts$ArtifactsTaskOps$$anonfun$1."<init>":()V
        34: invokevirtual #106                // Method coursier/util/Task$.handle$extension:(Lscala/Function1;Lscala/PartialFunction;)Lscala/Function1;
        37: aload_2
        38: invokevirtual #60                 // Method coursier/util/Task$.future$extension:(Lscala/Function1;Lscala/concurrent/ExecutionContext;)Lscala/concurrent/Future;
        41: astore_3
        42: getstatic     #111                // Field scala/concurrent/Await$.MODULE$:Lscala/concurrent/Await$;
        45: aload_3
        46: getstatic     #116                // Field scala/concurrent/duration/Duration$.MODULE$:Lscala/concurrent/duration/Duration$;
        49: invokevirtual #120                // Method scala/concurrent/duration/Duration$.Inf:()Lscala/concurrent/duration/Duration$Infinite;
        52: invokevirtual #124                // Method scala/concurrent/Await$.result:(Lscala/concurrent/Awaitable;Lscala/concurrent/duration/Duration;)Ljava/lang/Object;
        55: checkcast     #126                // class scala/util/Either
        58: areturn
      LineNumberTable:
        line 168: 0
        line 169: 9
        line 170: 19
        line 171: 27
        line 172: 37
        line 174: 42
      LocalVariableTable:
        Start  Length  Slot  Name   Signature
           42      16     3     f   Lscala/concurrent/Future;
            0      59     0  this   Lcoursier/Artifacts$ArtifactsTaskOps$;
            0      59     1 $this   Lcoursier/Artifacts;
            0      59     2    ec   Lscala/concurrent/ExecutionContext;
    Signature: #77                          // (Lcoursier/Artifacts<Lcoursier/util/Task;>;Lscala/concurrent/ExecutionContext;)Lscala/util/Either<Lcoursier/error/FetchError;Lscala/collection/immutable/Seq<Lscala/Tuple2<Lcoursier/util/Artifact;Ljava/io/File;>;>;>;
    MethodParameters:
      Name                           Flags
      $this                          final
      ec                             final

  public final scala.concurrent.ExecutionContext either$default$1$extension(coursier.Artifacts);
    descriptor: (Lcoursier/Artifacts;)Lscala/concurrent/ExecutionContext;
    flags: (0x0011) ACC_PUBLIC, ACC_FINAL
    Code:
      stack=1, locals=2, args_size=2
         0: aload_1
         1: invokevirtual #69                 // Method coursier/Artifacts.cache:()Lcoursier/cache/Cache;
         4: invokevirtual #74                 // Method coursier/cache/Cache.ec:()Lscala/concurrent/ExecutionContext;
         7: areturn
      LineNumberTable:
        line 166: 0
      LocalVariableTable:
        Start  Length  Slot  Name   Signature
            0       8     0  this   Lcoursier/Artifacts$ArtifactsTaskOps$;
            0       8     1 $this   Lcoursier/Artifacts;
    MethodParameters:
      Name                           Flags
      $this                          final

  public final scala.collection.immutable.Seq<scala.Tuple2<coursier.util.Artifact, java.io.File>> run$extension(coursier.Artifacts<coursier.util.Task>, scala.concurrent.ExecutionContext);
    descriptor: (Lcoursier/Artifacts;Lscala/concurrent/ExecutionContext;)Lscala/collection/immutable/Seq;
    flags: (0x0011) ACC_PUBLIC, ACC_FINAL
    Code:
      stack=3, locals=4, args_size=3
         0: getstatic     #47                 // Field coursier/util/Task$.MODULE$:Lcoursier/util/Task$;
         3: aload_1
         4: invokevirtual #51                 // Method coursier/Artifacts.io:()Ljava/lang/Object;
         7: checkcast     #53                 // class coursier/util/Task
        10: invokevirtual #57                 // Method coursier/util/Task.value:()Lscala/Function1;
        13: aload_2
        14: invokevirtual #60                 // Method coursier/util/Task$.future$extension:(Lscala/Function1;Lscala/concurrent/ExecutionContext;)Lscala/concurrent/Future;
        17: astore_3
        18: getstatic     #111                // Field scala/concurrent/Await$.MODULE$:Lscala/concurrent/Await$;
        21: aload_3
        22: getstatic     #116                // Field scala/concurrent/duration/Duration$.MODULE$:Lscala/concurrent/duration/Duration$;
        25: invokevirtual #120                // Method scala/concurrent/duration/Duration$.Inf:()Lscala/concurrent/duration/Duration$Infinite;
        28: invokevirtual #124                // Method scala/concurrent/Await$.result:(Lscala/concurrent/Awaitable;Lscala/concurrent/duration/Duration;)Ljava/lang/Object;
        31: checkcast     #134                // class scala/collection/immutable/Seq
        34: areturn
      LineNumberTable:
        line 178: 0
        line 179: 18
      LocalVariableTable:
        Start  Length  Slot  Name   Signature
           18      16     3     f   Lscala/concurrent/Future;
            0      35     0  this   Lcoursier/Artifacts$ArtifactsTaskOps$;
            0      35     1 $this   Lcoursier/Artifacts;
            0      35     2    ec   Lscala/concurrent/ExecutionContext;
    Signature: #132                         // (Lcoursier/Artifacts<Lcoursier/util/Task;>;Lscala/concurrent/ExecutionContext;)Lscala/collection/immutable/Seq<Lscala/Tuple2<Lcoursier/util/Artifact;Ljava/io/File;>;>;
    MethodParameters:
      Name                           Flags
      $this                          final
      ec                             final

  public final scala.concurrent.ExecutionContext run$default$1$extension(coursier.Artifacts);
    descriptor: (Lcoursier/Artifacts;)Lscala/concurrent/ExecutionContext;
    flags: (0x0011) ACC_PUBLIC, ACC_FINAL
    Code:
      stack=1, locals=2, args_size=2
         0: aload_1
         1: invokevirtual #69                 // Method coursier/Artifacts.cache:()Lcoursier/cache/Cache;
         4: invokevirtual #74                 // Method coursier/cache/Cache.ec:()Lscala/concurrent/ExecutionContext;
         7: areturn
      LineNumberTable:
        line 177: 0
      LocalVariableTable:
        Start  Length  Slot  Name   Signature
            0       8     0  this   Lcoursier/Artifacts$ArtifactsTaskOps$;
            0       8     1 $this   Lcoursier/Artifacts;
    MethodParameters:
      Name                           Flags
      $this                          final

  public final scala.concurrent.Future<coursier.Artifacts$Result> futureResult$extension(coursier.Artifacts<coursier.util.Task>, scala.concurrent.ExecutionContext);
    descriptor: (Lcoursier/Artifacts;Lscala/concurrent/ExecutionContext;)Lscala/concurrent/Future;
    flags: (0x0011) ACC_PUBLIC, ACC_FINAL
    Code:
      stack=3, locals=3, args_size=3
         0: getstatic     #47                 // Field coursier/util/Task$.MODULE$:Lcoursier/util/Task$;
         3: aload_1
         4: invokevirtual #140                // Method coursier/Artifacts.ioResult:()Ljava/lang/Object;
         7: checkcast     #53                 // class coursier/util/Task
        10: invokevirtual #57                 // Method coursier/util/Task.value:()Lscala/Function1;
        13: aload_2
        14: invokevirtual #60                 // Method coursier/util/Task$.future$extension:(Lscala/Function1;Lscala/concurrent/ExecutionContext;)Lscala/concurrent/Future;
        17: areturn
      LineNumberTable:
        line 183: 3
      LocalVariableTable:
        Start  Length  Slot  Name   Signature
            0      18     0  this   Lcoursier/Artifacts$ArtifactsTaskOps$;
            0      18     1 $this   Lcoursier/Artifacts;
            0      18     2    ec   Lscala/concurrent/ExecutionContext;
    Signature: #137                         // (Lcoursier/Artifacts<Lcoursier/util/Task;>;Lscala/concurrent/ExecutionContext;)Lscala/concurrent/Future<Lcoursier/Artifacts$Result;>;
    MethodParameters:
      Name                           Flags
      $this                          final
      ec                             final

  public final scala.concurrent.ExecutionContext futureResult$default$1$extension(coursier.Artifacts);
    descriptor: (Lcoursier/Artifacts;)Lscala/concurrent/ExecutionContext;
    flags: (0x0011) ACC_PUBLIC, ACC_FINAL
    Code:
      stack=1, locals=2, args_size=2
         0: aload_1
         1: invokevirtual #69                 // Method coursier/Artifacts.cache:()Lcoursier/cache/Cache;
         4: invokevirtual #74                 // Method coursier/cache/Cache.ec:()Lscala/concurrent/ExecutionContext;
         7: areturn
      LineNumberTable:
        line 182: 0
      LocalVariableTable:
        Start  Length  Slot  Name   Signature
            0       8     0  this   Lcoursier/Artifacts$ArtifactsTaskOps$;
            0       8     1 $this   Lcoursier/Artifacts;
    MethodParameters:
      Name                           Flags
      $this                          final

  public final scala.util.Either<coursier.error.FetchError, coursier.Artifacts$Result> eitherResult$extension(coursier.Artifacts<coursier.util.Task>, scala.concurrent.ExecutionContext);
    descriptor: (Lcoursier/Artifacts;Lscala/concurrent/ExecutionContext;)Lscala/util/Either;
    flags: (0x0011) ACC_PUBLIC, ACC_FINAL
    Code:
      stack=5, locals=4, args_size=3
         0: getstatic     #47                 // Field coursier/util/Task$.MODULE$:Lcoursier/util/Task$;
         3: getstatic     #47                 // Field coursier/util/Task$.MODULE$:Lcoursier/util/Task$;
         6: getstatic     #47                 // Field coursier/util/Task$.MODULE$:Lcoursier/util/Task$;
         9: aload_1
        10: invokevirtual #140                // Method coursier/Artifacts.ioResult:()Ljava/lang/Object;
        13: checkcast     #53                 // class coursier/util/Task
        16: invokevirtual #57                 // Method coursier/util/Task.value:()Lscala/Function1;
        19: invokedynamic #150,  0            // InvokeDynamic #1:apply:()Lscala/Function1;
        24: invokevirtual #101                // Method coursier/util/Task$.map$extension:(Lscala/Function1;Lscala/Function1;)Lscala/Function1;
        27: new           #15                 // class coursier/Artifacts$ArtifactsTaskOps$$anonfun$2
        30: dup
        31: invokespecial #151                // Method coursier/Artifacts$ArtifactsTaskOps$$anonfun$2."<init>":()V
        34: invokevirtual #106                // Method coursier/util/Task$.handle$extension:(Lscala/Function1;Lscala/PartialFunction;)Lscala/Function1;
        37: aload_2
        38: invokevirtual #60                 // Method coursier/util/Task$.future$extension:(Lscala/Function1;Lscala/concurrent/ExecutionContext;)Lscala/concurrent/Future;
        41: astore_3
        42: getstatic     #111                // Field scala/concurrent/Await$.MODULE$:Lscala/concurrent/Await$;
        45: aload_3
        46: getstatic     #116                // Field scala/concurrent/duration/Duration$.MODULE$:Lscala/concurrent/duration/Duration$;
        49: invokevirtual #120                // Method scala/concurrent/duration/Duration$.Inf:()Lscala/concurrent/duration/Duration$Infinite;
        52: invokevirtual #124                // Method scala/concurrent/Await$.result:(Lscala/concurrent/Awaitable;Lscala/concurrent/duration/Duration;)Ljava/lang/Object;
        55: checkcast     #126                // class scala/util/Either
        58: areturn
      LineNumberTable:
        line 187: 0
        line 188: 9
        line 189: 19
        line 190: 27
        line 191: 37
        line 193: 42
      LocalVariableTable:
        Start  Length  Slot  Name   Signature
           42      16     3     f   Lscala/concurrent/Future;
            0      59     0  this   Lcoursier/Artifacts$ArtifactsTaskOps$;
            0      59     1 $this   Lcoursier/Artifacts;
            0      59     2    ec   Lscala/concurrent/ExecutionContext;
    Signature: #143                         // (Lcoursier/Artifacts<Lcoursier/util/Task;>;Lscala/concurrent/ExecutionContext;)Lscala/util/Either<Lcoursier/error/FetchError;Lcoursier/Artifacts$Result;>;
    MethodParameters:
      Name                           Flags
      $this                          final
      ec                             final

  public final scala.concurrent.ExecutionContext eitherResult$default$1$extension(coursier.Artifacts);
    descriptor: (Lcoursier/Artifacts;)Lscala/concurrent/ExecutionContext;
    flags: (0x0011) ACC_PUBLIC, ACC_FINAL
    Code:
      stack=1, locals=2, args_size=2
         0: aload_1
         1: invokevirtual #69                 // Method coursier/Artifacts.cache:()Lcoursier/cache/Cache;
         4: invokevirtual #74                 // Method coursier/cache/Cache.ec:()Lscala/concurrent/ExecutionContext;
         7: areturn
      LineNumberTable:
        line 185: 0
      LocalVariableTable:
        Start  Length  Slot  Name   Signature
            0       8     0  this   Lcoursier/Artifacts$ArtifactsTaskOps$;
            0       8     1 $this   Lcoursier/Artifacts;
    MethodParameters:
      Name                           Flags
      $this                          final

  public final coursier.Artifacts$Result runResult$extension(coursier.Artifacts, scala.concurrent.ExecutionContext);
    descriptor: (Lcoursier/Artifacts;Lscala/concurrent/ExecutionContext;)Lcoursier/Artifacts$Result;
    flags: (0x0011) ACC_PUBLIC, ACC_FINAL
    Code:
      stack=3, locals=4, args_size=3
         0: getstatic     #47                 // Field coursier/util/Task$.MODULE$:Lcoursier/util/Task$;
         3: aload_1
         4: invokevirtual #140                // Method coursier/Artifacts.ioResult:()Ljava/lang/Object;
         7: checkcast     #53                 // class coursier/util/Task
        10: invokevirtual #57                 // Method coursier/util/Task.value:()Lscala/Function1;
        13: aload_2
        14: invokevirtual #60                 // Method coursier/util/Task$.future$extension:(Lscala/Function1;Lscala/concurrent/ExecutionContext;)Lscala/concurrent/Future;
        17: astore_3
        18: getstatic     #111                // Field scala/concurrent/Await$.MODULE$:Lscala/concurrent/Await$;
        21: aload_3
        22: getstatic     #116                // Field scala/concurrent/duration/Duration$.MODULE$:Lscala/concurrent/duration/Duration$;
        25: invokevirtual #120                // Method scala/concurrent/duration/Duration$.Inf:()Lscala/concurrent/duration/Duration$Infinite;
        28: invokevirtual #124                // Method scala/concurrent/Await$.result:(Lscala/concurrent/Awaitable;Lscala/concurrent/duration/Duration;)Ljava/lang/Object;
        31: checkcast     #17                 // class coursier/Artifacts$Result
        34: areturn
      LineNumberTable:
        line 197: 0
        line 198: 18
      LocalVariableTable:
        Start  Length  Slot  Name   Signature
           18      16     3     f   Lscala/concurrent/Future;
            0      35     0  this   Lcoursier/Artifacts$ArtifactsTaskOps$;
            0      35     1 $this   Lcoursier/Artifacts;
            0      35     2    ec   Lscala/concurrent/ExecutionContext;
    MethodParameters:
      Name                           Flags
      $this                          final
      ec                             final

  public final scala.concurrent.ExecutionContext runResult$default$1$extension(coursier.Artifacts);
    descriptor: (Lcoursier/Artifacts;)Lscala/concurrent/ExecutionContext;
    flags: (0x0011) ACC_PUBLIC, ACC_FINAL
    Code:
      stack=1, locals=2, args_size=2
         0: aload_1
         1: invokevirtual #69                 // Method coursier/Artifacts.cache:()Lcoursier/cache/Cache;
         4: invokevirtual #74                 // Method coursier/cache/Cache.ec:()Lscala/concurrent/ExecutionContext;
         7: areturn
      LineNumberTable:
        line 196: 0
      LocalVariableTable:
        Start  Length  Slot  Name   Signature
            0       8     0  this   Lcoursier/Artifacts$ArtifactsTaskOps$;
            0       8     1 $this   Lcoursier/Artifacts;
    MethodParameters:
      Name                           Flags
      $this                          final

  public final int hashCode$extension(coursier.Artifacts);
    descriptor: (Lcoursier/Artifacts;)I
    flags: (0x0011) ACC_PUBLIC, ACC_FINAL
    Code:
      stack=1, locals=2, args_size=2
         0: aload_1
         1: invokevirtual #161                // Method coursier/Artifacts.hashCode:()I
         4: ireturn
      LineNumberTable:
        line 161: 0
      LocalVariableTable:
        Start  Length  Slot  Name   Signature
            0       5     0  this   Lcoursier/Artifacts$ArtifactsTaskOps$;
            0       5     1 $this   Lcoursier/Artifacts;
    MethodParameters:
      Name                           Flags
      $this                          final

  public final boolean equals$extension(coursier.Artifacts, java.lang.Object);
    descriptor: (Lcoursier/Artifacts;Ljava/lang/Object;)Z
    flags: (0x0011) ACC_PUBLIC, ACC_FINAL
    Code:
      stack=2, locals=7, args_size=3
         0: aload_2
         1: astore        4
         3: aload         4
         5: instanceof    #7                  // class coursier/Artifacts$ArtifactsTaskOps
         8: ifeq          16
        11: iconst_1
        12: istore_3
        13: goto          24
        16: goto          19
        19: iconst_0
        20: istore_3
        21: goto          24
        24: iload_3
        25: ifeq          83
        28: aload_2
        29: ifnonnull     36
        32: aconst_null
        33: goto          43
        36: aload_2
        37: checkcast     #7                  // class coursier/Artifacts$ArtifactsTaskOps
        40: invokevirtual #168                // Method coursier/Artifacts$ArtifactsTaskOps.coursier$Artifacts$ArtifactsTaskOps$$artifacts:()Lcoursier/Artifacts;
        43: astore        5
        45: aload_1
        46: aload         5
        48: astore        6
        50: dup
        51: ifnonnull     63
        54: pop
        55: aload         6
        57: ifnull        71
        60: goto          75
        63: aload         6
        65: invokevirtual #172                // Method java/lang/Object.equals:(Ljava/lang/Object;)Z
        68: ifeq          75
        71: iconst_1
        72: goto          76
        75: iconst_0
        76: ifeq          83
        79: iconst_1
        80: goto          84
        83: iconst_0
        84: ireturn
      StackMapTable: number_of_entries = 11
        frame_type = 253 /* append */
          offset_delta = 16
          locals = [ top, class java/lang/Object ]
        frame_type = 2 /* same */
        frame_type = 255 /* full_frame */
          offset_delta = 4
          locals = [ class coursier/Artifacts$ArtifactsTaskOps$, class coursier/Artifacts, class java/lang/Object, int, class java/lang/Object ]
          stack = []
        frame_type = 11 /* same */
        frame_type = 70 /* same_locals_1_stack_item */
          stack = [ class coursier/Artifacts ]
        frame_type = 255 /* full_frame */
          offset_delta = 19
          locals = [ class coursier/Artifacts$ArtifactsTaskOps$, class coursier/Artifacts, class java/lang/Object, int, class java/lang/Object, class coursier/Artifacts, class coursier/Artifacts ]
          stack = [ class coursier/Artifacts ]
        frame_type = 7 /* same */
        frame_type = 3 /* same */
        frame_type = 64 /* same_locals_1_stack_item */
          stack = [ int ]
        frame_type = 249 /* chop */
          offset_delta = 6
        frame_type = 64 /* same_locals_1_stack_item */
          stack = [ int ]
      LineNumberTable:
        line 161: 0
      LocalVariableTable:
        Start  Length  Slot  Name   Signature
            0      85     0  this   Lcoursier/Artifacts$ArtifactsTaskOps$;
            0      85     1 $this   Lcoursier/Artifacts;
            0      85     2   x$1   Ljava/lang/Object;
    MethodParameters:
      Name                           Flags
      $this                          final
      x$1                            final

  public static final scala.util.Right $anonfun$either$1(scala.collection.immutable.Seq);
    descriptor: (Lscala/collection/immutable/Seq;)Lscala/util/Right;
    flags: (0x1019) ACC_PUBLIC, ACC_STATIC, ACC_FINAL, ACC_SYNTHETIC
    Code:
      stack=2, locals=1, args_size=1
         0: getstatic     #179                // Field scala/package$.MODULE$:Lscala/package$;
         3: invokevirtual #183                // Method scala/package$.Right:()Lscala/util/Right$;
         6: aload_0
         7: invokevirtual #188                // Method scala/util/Right$.apply:(Ljava/lang/Object;)Lscala/util/Right;
        10: areturn
      LineNumberTable:
        line 170: 0
      LocalVariableTable:
        Start  Length  Slot  Name   Signature
            0      11     0  x$10   Lscala/collection/immutable/Seq;
    MethodParameters:
      Name                           Flags
      x$10                           final

  public static final scala.util.Right $anonfun$eitherResult$1(coursier.Artifacts$Result);
    descriptor: (Lcoursier/Artifacts$Result;)Lscala/util/Right;
    flags: (0x1019) ACC_PUBLIC, ACC_STATIC, ACC_FINAL, ACC_SYNTHETIC
    Code:
      stack=2, locals=1, args_size=1
         0: getstatic     #179                // Field scala/package$.MODULE$:Lscala/package$;
         3: invokevirtual #183                // Method scala/package$.Right:()Lscala/util/Right$;
         6: aload_0
         7: invokevirtual #188                // Method scala/util/Right$.apply:(Ljava/lang/Object;)Lscala/util/Right;
        10: areturn
      LineNumberTable:
        line 189: 0
      LocalVariableTable:
        Start  Length  Slot  Name   Signature
            0      11     0  x$11   Lcoursier/Artifacts$Result;
    MethodParameters:
      Name                           Flags
      x$11                           final

  public coursier.Artifacts$ArtifactsTaskOps$();
    descriptor: ()V
    flags: (0x0001) ACC_PUBLIC
    Code:
      stack=1, locals=1, args_size=1
         0: aload_0
         1: invokespecial #192                // Method java/lang/Object."<init>":()V
         4: return
      LineNumberTable:
        line 161: 0
      LocalVariableTable:
        Start  Length  Slot  Name   Signature
            0       5     0  this   Lcoursier/Artifacts$ArtifactsTaskOps$;

  private static java.lang.Object $deserializeLambda$(java.lang.invoke.SerializedLambda);
    descriptor: (Ljava/lang/invoke/SerializedLambda;)Ljava/lang/Object;
    flags: (0x100a) ACC_PRIVATE, ACC_STATIC, ACC_SYNTHETIC
    Code:
      stack=1, locals=1, args_size=1
         0: aload_0
         1: invokedynamic #204,  0            // InvokeDynamic #2:lambdaDeserialize:(Ljava/lang/invoke/SerializedLambda;)Ljava/lang/Object;
         6: areturn
}
InnerClasses:
  public static final #10= #7 of #9;      // ArtifactsTaskOps=class coursier/Artifacts$ArtifactsTaskOps of class coursier/Artifacts
  public static #11= #2 of #9;            // =class coursier/Artifacts$ArtifactsTaskOps$ of class coursier/Artifacts
  public final #13;                       // class coursier/Artifacts$ArtifactsTaskOps$$anonfun$1
  public final #15;                       // class coursier/Artifacts$ArtifactsTaskOps$$anonfun$2
  public static final #18= #17 of #9;     // Result=class coursier/Artifacts$Result of class coursier/Artifacts
  public static final #23= #20 of #22;    // Lookup=class java/lang/invoke/MethodHandles$Lookup of class java/lang/invoke/MethodHandles
  public static abstract #28= #25 of #27; // Infinite=class scala/concurrent/duration/Duration$Infinite of class scala/concurrent/duration/Duration
SourceFile: "Artifacts.scala"
BootstrapMethods:
  0: #94 REF_invokeStatic java/lang/invoke/LambdaMetafactory.altMetafactory:(Ljava/lang/invoke/MethodHandles$Lookup;Ljava/lang/String;Ljava/lang/invoke/MethodType;[Ljava/lang/Object;)Ljava/lang/invoke/CallSite;
    Method arguments:
      #79 (Ljava/lang/Object;)Ljava/lang/Object;
      #84 REF_invokeStatic coursier/Artifacts$ArtifactsTaskOps$.$anonfun$either$1:(Lscala/collection/immutable/Seq;)Lscala/util/Right;
      #85 (Lscala/collection/immutable/Seq;)Lscala/util/Right;
      #86 5
      #87 1
      #85 (Lscala/collection/immutable/Seq;)Lscala/util/Right;
  1: #94 REF_invokeStatic java/lang/invoke/LambdaMetafactory.altMetafactory:(Ljava/lang/invoke/MethodHandles$Lookup;Ljava/lang/String;Ljava/lang/invoke/MethodType;[Ljava/lang/Object;)Ljava/lang/invoke/CallSite;
    Method arguments:
      #79 (Ljava/lang/Object;)Ljava/lang/Object;
      #148 REF_invokeStatic coursier/Artifacts$ArtifactsTaskOps$.$anonfun$eitherResult$1:(Lcoursier/Artifacts$Result;)Lscala/util/Right;
      #149 (Lcoursier/Artifacts$Result;)Lscala/util/Right;
      #86 5
      #87 1
      #149 (Lcoursier/Artifacts$Result;)Lscala/util/Right;
  2: #201 REF_invokeStatic scala/runtime/LambdaDeserialize.bootstrap:(Ljava/lang/invoke/MethodHandles$Lookup;Ljava/lang/String;Ljava/lang/invoke/MethodType;[Ljava/lang/invoke/MethodHandle;)Ljava/lang/invoke/CallSite;
    Method arguments:
      #84 REF_invokeStatic coursier/Artifacts$ArtifactsTaskOps$.$anonfun$either$1:(Lscala/collection/immutable/Seq;)Lscala/util/Right;
      #148 REF_invokeStatic coursier/Artifacts$ArtifactsTaskOps$.$anonfun$eitherResult$1:(Lcoursier/Artifacts$Result;)Lscala/util/Right;
  ScalaInlineInfo: length = 0x59 (unknown attribute)
   01 01 00 11 00 50 00 51 01 00 90 00 91 01 00 21
   00 20 01 00 81 00 41 01 00 4B 00 4C 01 00 98 00
   41 01 00 8E 00 4C 01 00 A2 00 A3 01 00 40 00 41
   01 00 26 00 27 01 00 8D 00 41 01 00 88 00 27 01
   00 9C 00 9D 01 00 87 00 41 01 00 82 00 83 01 00
   9B 00 41 01 00 99 00 9A 01
  Scala: length = 0x0 (unknown attribute)

