Classfile /Users/mw/Projects/slang-braindump/.jar/jar11/assemble/slang-braindump/assemble/content/coursier/Fetch$Result$$anonfun$detailedArtifacts$1.class
  Last modified May 29, 2022; size 3026 bytes
  SHA-256 checksum cc19d8ecbccad69f626ab539d2e958027c621410c000590891c48a01dd07255f
  Compiled from "Fetch.scala"
public final class coursier.Fetch$Result$$anonfun$detailedArtifacts$1 extends scala.runtime.AbstractPartialFunction<scala.Tuple4<coursier.core.Dependency, coursier.core.Publication, coursier.util.Artifact, scala.Option<java.io.File>>, scala.Tuple4<coursier.core.Dependency, coursier.core.Publication, coursier.util.Artifact, java.io.File>> implements java.io.Serializable
  minor version: 0
  major version: 52
  flags: (0x0031) ACC_PUBLIC, ACC_FINAL, ACC_SUPER
  this_class: #2                          // coursier/Fetch$Result$$anonfun$detailedArtifacts$1
  super_class: #5                         // scala/runtime/AbstractPartialFunction
  interfaces: 1, fields: 1, methods: 5, attributes: 6
Constant pool:
    #1 = Utf8               coursier/Fetch$Result$$anonfun$detailedArtifacts$1
    #2 = Class              #1            // coursier/Fetch$Result$$anonfun$detailedArtifacts$1
    #3 = Utf8               Lscala/runtime/AbstractPartialFunction<Lscala/Tuple4<Lcoursier/core/Dependency;Lcoursier/core/Publication;Lcoursier/util/Artifact;Lscala/Option<Ljava/io/File;>;>;Lscala/Tuple4<Lcoursier/core/Dependency;Lcoursier/core/Publication;Lcoursier/util/Artifact;Ljava/io/File;>;>;Ljava/io/Serializable;
    #4 = Utf8               scala/runtime/AbstractPartialFunction
    #5 = Class              #4            // scala/runtime/AbstractPartialFunction
    #6 = Utf8               java/io/Serializable
    #7 = Class              #6            // java/io/Serializable
    #8 = Utf8               Fetch.scala
    #9 = Utf8               coursier/Fetch$Result
   #10 = Class              #9            // coursier/Fetch$Result
   #11 = Utf8               detailedArtifacts
   #12 = Utf8               ()Lscala/collection/immutable/Seq;
   #13 = NameAndType        #11:#12       // detailedArtifacts:()Lscala/collection/immutable/Seq;
   #14 = Utf8               coursier/Fetch
   #15 = Class              #14           // coursier/Fetch
   #16 = Utf8               Result
   #17 = Utf8               serialVersionUID
   #18 = Utf8               J
   #19 = Long               0l
   #21 = Utf8               applyOrElse
   #22 = Utf8               (Lscala/Tuple4;Lscala/Function1;)Ljava/lang/Object;
   #23 = Utf8               <A1:Lscala/Tuple4<Lcoursier/core/Dependency;Lcoursier/core/Publication;Lcoursier/util/Artifact;Lscala/Option<Ljava/io/File;>;>;B1:Ljava/lang/Object;>(TA1;Lscala/Function1<TA1;TB1;>;)TB1;
   #24 = Utf8               x1
   #25 = Utf8               default
   #26 = Utf8               scala/Tuple4
   #27 = Class              #26           // scala/Tuple4
   #28 = Utf8               _1
   #29 = Utf8               ()Ljava/lang/Object;
   #30 = NameAndType        #28:#29       // _1:()Ljava/lang/Object;
   #31 = Methodref          #27.#30       // scala/Tuple4._1:()Ljava/lang/Object;
   #32 = Utf8               coursier/core/Dependency
   #33 = Class              #32           // coursier/core/Dependency
   #34 = Utf8               _2
   #35 = NameAndType        #34:#29       // _2:()Ljava/lang/Object;
   #36 = Methodref          #27.#35       // scala/Tuple4._2:()Ljava/lang/Object;
   #37 = Utf8               coursier/core/Publication
   #38 = Class              #37           // coursier/core/Publication
   #39 = Utf8               _3
   #40 = NameAndType        #39:#29       // _3:()Ljava/lang/Object;
   #41 = Methodref          #27.#40       // scala/Tuple4._3:()Ljava/lang/Object;
   #42 = Utf8               coursier/util/Artifact
   #43 = Class              #42           // coursier/util/Artifact
   #44 = Utf8               _4
   #45 = NameAndType        #44:#29       // _4:()Ljava/lang/Object;
   #46 = Methodref          #27.#45       // scala/Tuple4._4:()Ljava/lang/Object;
   #47 = Utf8               scala/Option
   #48 = Class              #47           // scala/Option
   #49 = Utf8               scala/Some
   #50 = Class              #49           // scala/Some
   #51 = Utf8               value
   #52 = NameAndType        #51:#29       // value:()Ljava/lang/Object;
   #53 = Methodref          #50.#52       // scala/Some.value:()Ljava/lang/Object;
   #54 = Utf8               java/io/File
   #55 = Class              #54           // java/io/File
   #56 = Utf8               <init>
   #57 = Utf8               (Ljava/lang/Object;Ljava/lang/Object;Ljava/lang/Object;Ljava/lang/Object;)V
   #58 = NameAndType        #56:#57       // "<init>":(Ljava/lang/Object;Ljava/lang/Object;Ljava/lang/Object;Ljava/lang/Object;)V
   #59 = Methodref          #27.#58       // scala/Tuple4."<init>":(Ljava/lang/Object;Ljava/lang/Object;Ljava/lang/Object;Ljava/lang/Object;)V
   #60 = Utf8               scala/Function1
   #61 = Class              #60           // scala/Function1
   #62 = Utf8               apply
   #63 = Utf8               (Ljava/lang/Object;)Ljava/lang/Object;
   #64 = NameAndType        #62:#63       // apply:(Ljava/lang/Object;)Ljava/lang/Object;
   #65 = InterfaceMethodref #61.#64       // scala/Function1.apply:(Ljava/lang/Object;)Ljava/lang/Object;
   #66 = Utf8               java/lang/Object
   #67 = Class              #66           // java/lang/Object
   #68 = Utf8               file
   #69 = Utf8               Ljava/io/File;
   #70 = Utf8               dep
   #71 = Utf8               Lcoursier/core/Dependency;
   #72 = Utf8               pub
   #73 = Utf8               Lcoursier/core/Publication;
   #74 = Utf8               art
   #75 = Utf8               Lcoursier/util/Artifact;
   #76 = Utf8               this
   #77 = Utf8               Lcoursier/Fetch$Result$$anonfun$detailedArtifacts$1;
   #78 = Utf8               Lscala/Tuple4;
   #79 = Utf8               Lscala/Function1;
   #80 = Utf8               isDefinedAt
   #81 = Utf8               (Lscala/Tuple4;)Z
   #82 = Utf8               (Lscala/Tuple4<Lcoursier/core/Dependency;Lcoursier/core/Publication;Lcoursier/util/Artifact;Lscala/Option<Ljava/io/File;>;>;)Z
   #83 = Utf8               (Ljava/lang/Object;)Z
   #84 = Utf8               x
   #85 = NameAndType        #80:#81       // isDefinedAt:(Lscala/Tuple4;)Z
   #86 = Methodref          #2.#85        // coursier/Fetch$Result$$anonfun$detailedArtifacts$1.isDefinedAt:(Lscala/Tuple4;)Z
   #87 = Utf8               Ljava/lang/Object;
   #88 = Utf8               (Ljava/lang/Object;Lscala/Function1;)Ljava/lang/Object;
   #89 = NameAndType        #21:#22       // applyOrElse:(Lscala/Tuple4;Lscala/Function1;)Ljava/lang/Object;
   #90 = Methodref          #2.#89        // coursier/Fetch$Result$$anonfun$detailedArtifacts$1.applyOrElse:(Lscala/Tuple4;Lscala/Function1;)Ljava/lang/Object;
   #91 = Utf8               (Lcoursier/Fetch$Result;)V
   #92 = Utf8               $outer
   #93 = Utf8               ()V
   #94 = NameAndType        #56:#93       // "<init>":()V
   #95 = Methodref          #5.#94        // scala/runtime/AbstractPartialFunction."<init>":()V
   #96 = Utf8               Lcoursier/Fetch$Result;
   #97 = Utf8               ConstantValue
   #98 = Utf8               Code
   #99 = Utf8               StackMapTable
  #100 = Utf8               LineNumberTable
  #101 = Utf8               LocalVariableTable
  #102 = Utf8               Signature
  #103 = Utf8               MethodParameters
  #104 = Utf8               InnerClasses
  #105 = Utf8               EnclosingMethod
  #106 = Utf8               SourceFile
  #107 = Utf8               ScalaInlineInfo
  #108 = Utf8               Scala
{
  private static final long serialVersionUID;
    descriptor: J
    flags: (0x001a) ACC_PRIVATE, ACC_STATIC, ACC_FINAL
    ConstantValue: long 0l

  public final <A1 extends scala.Tuple4<coursier.core.Dependency, coursier.core.Publication, coursier.util.Artifact, scala.Option<java.io.File>>, B1 extends java.lang.Object> B1 applyOrElse(A1, scala.Function1<A1, B1>);
    descriptor: (Lscala/Tuple4;Lscala/Function1;)Ljava/lang/Object;
    flags: (0x0011) ACC_PUBLIC, ACC_FINAL
    Code:
      stack=6, locals=11, args_size=3
         0: aload_1
         1: astore        4
         3: aload         4
         5: ifnull        95
         8: aload         4
        10: invokevirtual #31                 // Method scala/Tuple4._1:()Ljava/lang/Object;
        13: checkcast     #33                 // class coursier/core/Dependency
        16: astore        5
        18: aload         4
        20: invokevirtual #36                 // Method scala/Tuple4._2:()Ljava/lang/Object;
        23: checkcast     #38                 // class coursier/core/Publication
        26: astore        6
        28: aload         4
        30: invokevirtual #41                 // Method scala/Tuple4._3:()Ljava/lang/Object;
        33: checkcast     #43                 // class coursier/util/Artifact
        36: astore        7
        38: aload         4
        40: invokevirtual #46                 // Method scala/Tuple4._4:()Ljava/lang/Object;
        43: checkcast     #48                 // class scala/Option
        46: astore        8
        48: aload         8
        50: instanceof    #50                 // class scala/Some
        53: ifeq          92
        56: aload         8
        58: checkcast     #50                 // class scala/Some
        61: astore        9
        63: aload         9
        65: invokevirtual #53                 // Method scala/Some.value:()Ljava/lang/Object;
        68: checkcast     #55                 // class java/io/File
        71: astore        10
        73: new           #27                 // class scala/Tuple4
        76: dup
        77: aload         5
        79: aload         6
        81: aload         7
        83: aload         10
        85: invokespecial #59                 // Method scala/Tuple4."<init>":(Ljava/lang/Object;Ljava/lang/Object;Ljava/lang/Object;Ljava/lang/Object;)V
        88: astore_3
        89: goto          109
        92: goto          98
        95: goto          98
        98: aload_2
        99: aload_1
       100: invokeinterface #65,  2           // InterfaceMethod scala/Function1.apply:(Ljava/lang/Object;)Ljava/lang/Object;
       105: astore_3
       106: goto          109
       109: aload_3
       110: areturn
      StackMapTable: number_of_entries = 4
        frame_type = 255 /* full_frame */
          offset_delta = 92
          locals = [ class coursier/Fetch$Result$$anonfun$detailedArtifacts$1, class scala/Tuple4, class scala/Function1, top, class scala/Tuple4, class coursier/core/Dependency, class coursier/core/Publication, class coursier/util/Artifact, class scala/Option ]
          stack = []
        frame_type = 255 /* full_frame */
          offset_delta = 2
          locals = [ class coursier/Fetch$Result$$anonfun$detailedArtifacts$1, class scala/Tuple4, class scala/Function1, top, class scala/Tuple4 ]
          stack = []
        frame_type = 2 /* same */
        frame_type = 255 /* full_frame */
          offset_delta = 10
          locals = [ class coursier/Fetch$Result$$anonfun$detailedArtifacts$1, class scala/Tuple4, class scala/Function1, class java/lang/Object, class scala/Tuple4 ]
          stack = []
      LineNumberTable:
        line 242: 0
        line 243: 3
        line 244: 73
        line 243: 92
        line 242: 98
      LocalVariableTable:
        Start  Length  Slot  Name   Signature
           73      19    10  file   Ljava/io/File;
           18      77     5   dep   Lcoursier/core/Dependency;
           28      67     6   pub   Lcoursier/core/Publication;
           38      57     7   art   Lcoursier/util/Artifact;
            0     111     0  this   Lcoursier/Fetch$Result$$anonfun$detailedArtifacts$1;
            0     111     1    x1   Lscala/Tuple4;
            0     111     2 default   Lscala/Function1;
    Signature: #23                          // <A1:Lscala/Tuple4<Lcoursier/core/Dependency;Lcoursier/core/Publication;Lcoursier/util/Artifact;Lscala/Option<Ljava/io/File;>;>;B1:Ljava/lang/Object;>(TA1;Lscala/Function1<TA1;TB1;>;)TB1;
    MethodParameters:
      Name                           Flags
      x1                             final
      default                        final

  public final boolean isDefinedAt(scala.Tuple4<coursier.core.Dependency, coursier.core.Publication, coursier.util.Artifact, scala.Option<java.io.File>>);
    descriptor: (Lscala/Tuple4;)Z
    flags: (0x0011) ACC_PUBLIC, ACC_FINAL
    Code:
      stack=1, locals=5, args_size=2
         0: aload_1
         1: astore_3
         2: aload_3
         3: ifnull        31
         6: aload_3
         7: invokevirtual #46                 // Method scala/Tuple4._4:()Ljava/lang/Object;
        10: checkcast     #48                 // class scala/Option
        13: astore        4
        15: aload         4
        17: instanceof    #50                 // class scala/Some
        20: ifeq          28
        23: iconst_1
        24: istore_2
        25: goto          39
        28: goto          34
        31: goto          34
        34: iconst_0
        35: istore_2
        36: goto          39
        39: iload_2
        40: ireturn
      StackMapTable: number_of_entries = 4
        frame_type = 254 /* append */
          offset_delta = 28
          locals = [ top, class scala/Tuple4, class scala/Option ]
        frame_type = 250 /* chop */
          offset_delta = 2
        frame_type = 2 /* same */
        frame_type = 255 /* full_frame */
          offset_delta = 4
          locals = [ class coursier/Fetch$Result$$anonfun$detailedArtifacts$1, class scala/Tuple4, int, class scala/Tuple4 ]
          stack = []
      LineNumberTable:
        line 242: 0
        line 243: 2
        line 244: 23
        line 243: 28
        line 242: 34
      LocalVariableTable:
        Start  Length  Slot  Name   Signature
            0      41     0  this   Lcoursier/Fetch$Result$$anonfun$detailedArtifacts$1;
            0      41     1    x1   Lscala/Tuple4;
    Signature: #82                          // (Lscala/Tuple4<Lcoursier/core/Dependency;Lcoursier/core/Publication;Lcoursier/util/Artifact;Lscala/Option<Ljava/io/File;>;>;)Z
    MethodParameters:
      Name                           Flags
      x1                             final

  public final boolean isDefinedAt(java.lang.Object);
    descriptor: (Ljava/lang/Object;)Z
    flags: (0x1051) ACC_PUBLIC, ACC_FINAL, ACC_BRIDGE, ACC_SYNTHETIC
    Code:
      stack=2, locals=2, args_size=2
         0: aload_0
         1: aload_1
         2: checkcast     #27                 // class scala/Tuple4
         5: invokevirtual #86                 // Method isDefinedAt:(Lscala/Tuple4;)Z
         8: ireturn
      LineNumberTable:
        line 242: 0
      LocalVariableTable:
        Start  Length  Slot  Name   Signature
            0       9     0  this   Lcoursier/Fetch$Result$$anonfun$detailedArtifacts$1;
            0       9     1     x   Ljava/lang/Object;
    MethodParameters:
      Name                           Flags
      x                              final

  public final java.lang.Object applyOrElse(java.lang.Object, scala.Function1);
    descriptor: (Ljava/lang/Object;Lscala/Function1;)Ljava/lang/Object;
    flags: (0x1051) ACC_PUBLIC, ACC_FINAL, ACC_BRIDGE, ACC_SYNTHETIC
    Code:
      stack=3, locals=3, args_size=3
         0: aload_0
         1: aload_1
         2: checkcast     #27                 // class scala/Tuple4
         5: aload_2
         6: invokevirtual #90                 // Method applyOrElse:(Lscala/Tuple4;Lscala/Function1;)Ljava/lang/Object;
         9: areturn
      LineNumberTable:
        line 242: 0
      LocalVariableTable:
        Start  Length  Slot  Name   Signature
            0      10     0  this   Lcoursier/Fetch$Result$$anonfun$detailedArtifacts$1;
            0      10     1     x   Ljava/lang/Object;
            0      10     2 default   Lscala/Function1;
    MethodParameters:
      Name                           Flags
      x                              final
      default                        final

  public coursier.Fetch$Result$$anonfun$detailedArtifacts$1(coursier.Fetch$Result);
    descriptor: (Lcoursier/Fetch$Result;)V
    flags: (0x0001) ACC_PUBLIC
    Code:
      stack=1, locals=2, args_size=2
         0: aload_0
         1: invokespecial #95                 // Method scala/runtime/AbstractPartialFunction."<init>":()V
         4: return
      LineNumberTable:
        line 242: 0
      LocalVariableTable:
        Start  Length  Slot  Name   Signature
            0       5     0  this   Lcoursier/Fetch$Result$$anonfun$detailedArtifacts$1;
            0       5     1 $outer   Lcoursier/Fetch$Result;
    MethodParameters:
      Name                           Flags
      $outer                         final synthetic
}
InnerClasses:
  public static final #16= #10 of #15;    // Result=class coursier/Fetch$Result of class coursier/Fetch
  public final #2;                        // class coursier/Fetch$Result$$anonfun$detailedArtifacts$1
EnclosingMethod: #10.#13                // coursier.Fetch$Result.detailedArtifacts
Signature: #3                           // Lscala/runtime/AbstractPartialFunction<Lscala/Tuple4<Lcoursier/core/Dependency;Lcoursier/core/Publication;Lcoursier/util/Artifact;Lscala/Option<Ljava/io/File;>;>;Lscala/Tuple4<Lcoursier/core/Dependency;Lcoursier/core/Publication;Lcoursier/util/Artifact;Ljava/io/File;>;>;Ljava/io/Serializable;
SourceFile: "Fetch.scala"
  ScalaInlineInfo: length = 0x1D (unknown attribute)
   01 01 00 05 00 38 00 5B 01 00 15 00 58 01 00 15
   00 16 01 00 50 00 53 01 00 50 00 51 01
  Scala: length = 0x0 (unknown attribute)

