Classfile /Users/mw/Projects/slang-braindump/.jar/jar11/assemble/slang-braindump/assemble/content/coursier/Versions.class
  Last modified May 29, 2022; size 21594 bytes
  SHA-256 checksum 3de4857076c0f2a55b81ac11e1d50533d92cf232632f0991ec05a9958e1e50ec
  Compiled from "Versions.scala"
public final class coursier.Versions<F extends java.lang.Object> extends java.lang.Object implements scala.Product, java.io.Serializable
  minor version: 0
  major version: 52
  flags: (0x0031) ACC_PUBLIC, ACC_FINAL, ACC_SUPER
  this_class: #2                          // coursier/Versions
  super_class: #5                         // java/lang/Object
  interfaces: 2, fields: 6, methods: 54, attributes: 7
Constant pool:
    #1 = Utf8               coursier/Versions
    #2 = Class              #1            // coursier/Versions
    #3 = Utf8               <F:Ljava/lang/Object;>Ljava/lang/Object;Lscala/Product;Ljava/io/Serializable;
    #4 = Utf8               java/lang/Object
    #5 = Class              #4            // java/lang/Object
    #6 = Utf8               scala/Product
    #7 = Class              #6            // scala/Product
    #8 = Utf8               java/io/Serializable
    #9 = Class              #8            // java/io/Serializable
   #10 = Utf8               Versions.scala
   #11 = Utf8               Lscala/reflect/ScalaSignature;
   #12 = Utf8               bytes
   #13 = Utf8               \u0006\u0005\rUb\u0001B$I\u0005-C\u0001B\u0019\u0001\u0003\u0006\u0004%\ta\u0019\u0005\to\u0002\u0011\t\u0011)A\u0005I\"A\u0001\u0010\u0001BC\u0002\u0013\u0005\u0011\u0010C\u0005\u0002\n\u0001\u0011\t\u0011)A\u0005u\"Q\u00111\u0002\u0001\u0003\u0006\u0004%\t!!\u0004\t\u0015\u0005m\u0001A!A!\u0002\u0013\ty\u0001\u0003\u0006\u0002\u001e\u0001\u0011)\u0019!C\u0001\u0003?A!\"a\f\u0001\u0005\u0003\u0005\u000b\u0011BA\u0011\u0011)\t\t\u0004\u0001BC\u0002\u0013\u0005\u00111\u0007\u0005\u000b\u0003{\u0001!\u0011!Q\u0001\n\u0005U\u0002BCA \u0001\t\u0015\r\u0011b\u0001\u0002B!Q\u0011q\n\u0001\u0003\u0002\u0003\u0006I!a\u0011\t\u000f\u0005E\u0003\u0001\"\u0001\u0002T!9\u0011\u0011\u000b\u0001\u0005\u0002\u0005\u0015\u0004bBA)\u0001\u0011\u0005\u0011\u0011\u000f\u0005\b\u0003s\u0002A\u0011BA!\u0011\u001d\tY\b\u0001C\u0001\u0003{Bq!!#\u0001\t\u0003\tY\tC\u0004\u0002\u000e\u0002!\t!a$\t\u000f\u0005U\u0005\u0001\"\u0001\u0002\u0018\"9\u0011Q\u0014\u0001\u0005\u0002\u0005}\u0005bBAS\u0001\u0011\u0005\u0011q\u0015\u0005\b\u0003k\u0003A\u0011AA\\\u0011\u001d\tY\f\u0001C\u0005\u0003{Cq!!4\u0001\t\u0003\ty\rC\u0004\u0002T\u0002!\t!!6\t\u000f\te\b\u0001\"\u0001\u0003|\"9!q \u0001\u0005\u0002\r\u0005\u0001bBB\u0003\u0001\u0011\u00051q\u0001\u0005\b\u0007\u0017\u0001A\u0011AB\u0007\u0011\u001d\u0019\t\u0002\u0001C\u0001\u0007\'Aqaa\u0006\u0001\t\u0003\u0019I\u0002C\u0004\u0003\u0018\u0002!\tE!\'\t\u000f\t\u0015\u0006\u0001\"\u0011\u0004\u001e!9!1\u0017\u0001\u0005B\r\u0005\u0002b\u0002B]\u0001\u0011\u0005#1\u0018\u0005\b\u0005\u0007\u0004A\u0011BB\u0013\u0011\u001d\u0011i\r\u0001C!\u0005\u001fDqA!5\u0001\t\u0003\u0012\u0019\u000eC\u0004\u0003V\u0002!\te!\f\t\u000f\tu\u0007\u0001\"\u0011\u00042\u001d9\u0011Q\u001c%\t\u0002\u0005}gAB$I\u0011\u0003\t\t\u000fC\u0004\u0002R-\"\t!!=\t\u000f\u0005M8\u0006\"\u0001\u0002v\"9\u0011q`\u0016\u0005\n\t\u0005\u0001bBAzW\u0011\u0005!1\u0002\u0005\b\u0003g\\C\u0011\u0001B\u0012\u0011\u001d\t\u0019p\u000bC\u0001\u0005\u007f1aAa\u0018,\u0005\t\u0005\u0004B\u0003B2e\t\u0015\r\u0011\"\u0001\u0003f!Q!Q\u0011\u001a\u0003\u0002\u0003\u0006IAa\u001a\t\u000f\u0005E#\u0007\"\u0001\u0003\b\"9\u0011Q\u0015\u001a\u0005\u0002\t=\u0005b\u0002BIe\u0011\u0005!1\u0013\u0005\b\u0005/\u0013D\u0011\tBM\u0011\u001d\u0011)K\rC!\u0005OCqAa-3\t\u0003\u0012)\fC\u0004\u0003:J\"\tEa/\t\u000f\t\r\'\u0007\"\u0003\u0003F\"9!Q\u001a\u001a\u0005B\t=\u0007b\u0002Bie\u0011\u0005#1\u001b\u0005\b\u0005+\u0014D\u0011\tBl\u0011\u001d\u0011iN\rC!\u0005?<qAa9,\u0011\u0003\u0011)OB\u0004\u0003`-B\tAa:\t\u000f\u0005E#\t\"\u0001\u0003j\"9\u00111\u001f\"\u0005\u0002\t-\b\"\u0003Bx\u0005\u0006\u0005I\u0011\u0002By\u0011%\u0011yoKA\u0001\n\u0013\u0011\tP\u0001\u0005WKJ\u001c\u0018n\u001c8t\u0015\u0005I\u0015\u0001C2pkJ\u001c\u0018.\u001a:\u0004\u0001U\u0011Aj[\n\u0005\u00015\u001bf\u000b\u0005\u0002O#6\tqJC\u0001Q\u0003\u0015\u00198-\u00197b\u0013\t\u0011vJ\u0001\u0004B]f\u0014VM\u001a\t\u0003\u001dRK!!V(\u0003\u000fA\u0013x\u000eZ;diB\u0011qk\u0018\b\u00031vs!!\u0017/\u000e\u0003iS!a\u0017&\u0002\rq\u0012xn\u001c;?\u0013\u0005\u0001\u0016B\u00010P\u0003\u001d\u0001\u0018mY6bO\u0016L!\u0001Y1\u0003\u0019M+\'/[1mSj\f\'\r\\3\u000b\u0005y{\u0015!B2bG\",W#\u00013\u0011\u0007\u0015<\u0017.D\u0001g\u0015\t\u0011\u0007*\u0003\u0002iM\n)1)Y2iKB\u0011!n\u001b\u0007\u0001\t\u0015a\u0007A1\u0001n\u0005\u00051UC\u00018v#\ty\'\u000f\u0005\u0002Oa&\u0011\u0011o\u0014\u0002\b\u001d>$\b.\u001b8h!\tq5/\u0003\u0002u\u001f\n\u0019\u0011I\\=\u0005\u000bY\\\'\u0019\u00018\u0003\u0003}\u000baaY1dQ\u0016\u0004\u0013!C7pIVdWm\u00149u+\u0005Q\bc\u0001(|{&\u0011Ap\u0014\u0002\u0007\u001fB$\u0018n\u001c8\u0011\u0007y\f\u0019AD\u0002\u0000\u0003\u0003i\u0011\u0001S\u0005\u0003=\"KA!!\u0002\u0002\b\t1Qj\u001c3vY\u0016T!A\u0018%\u0002\u00155|G-\u001e7f\u001fB$\b%\u0001\u0007sKB|7/\u001b;pe&,7/\u0006\u0002\u0002\u0010A)q+!\u0005\u0002\u0016%\u0019\u00111C1\u0003\u0007M+\u0017\u000fE\u0002\u007f\u0003/IA!!\u0007\u0002\b\tQ!+\u001a9pg&$xN]=\u0002\u001bI,\u0007o\\:ji>\u0014\u0018.Z:!\u0003=i\u0017N\u001d:pe\u000e{gN\u001a$jY\u0016\u001cXCAA\u0011!\u00159\u0016\u0011CA\u0012!\u0011\t)#a\u000b\u000e\u0005\u0005\u001d\"bAA\u0015\u0011\u00061\u0001/\u0019:b[NLA!!\f\u0002(\tqQ*\u001b:s_J\u001cuN\u001c4GS2,\u0017\u0001E7jeJ|\'oQ8oM\u001aKG.Z:!\u0003\u001di\u0017N\u001d:peN,\"!!\u000e\u0011\u000b]\u000b\t\"a\u000e\u0011\t\u0005\u0015\u0012\u0011H\u0005\u0005\u0003w\t9C\u0001\u0004NSJ\u0014xN]\u0001\t[&\u0014(o\u001c:tA\u0005!1/\u001f8d+\t\t\u0019\u0005E\u0003\u0002F\u0005-\u0013.\u0004\u0002\u0002H)\u0019\u0011\u0011\n%\u0002\tU$\u0018\u000e\\\u0005\u0005\u0003\u001b\n9E\u0001\u0003Ts:\u001c\u0017!B:z]\u000e\u0004\u0013A\u0002\u001fj]&$h\b\u0006\u0007\u0002V\u0005m\u0013QLA0\u0003C\n\u0019\u0007\u0006\u0003\u0002X\u0005e\u0003cA@\u0001S\"9\u0011qH\u0007A\u0004\u0005\r\u0003\"\u00022\u000e\u0001\u0004!\u0007\"\u0002=\u000e\u0001\u0004Q\bbBA\u0006\u001b\u0001\u0007\u0011q\u0002\u0005\b\u0003;i\u0001\u0019AA\u0011\u0011\u001d\t\t$\u0004a\u0001\u0003k!\u0002\"a\u001a\u0002l\u00055\u0014q\u000e\u000b\u0005\u0003/\nI\u0007C\u0004\u0002@9\u0001\u001d!a\u0011\t\u000b\tt\u0001\u0019\u00013\t\u000bat\u0001\u0019\u0001>\t\u000f\u0005-a\u00021\u0001\u0002\u0010Q!\u00111OA<)\u0011\t9&!\u001e\t\u000f\u0005}r\u0002q\u0001\u0002D!)!m\u0004a\u0001I\u0006\ta)A\bbI\u0012\u0014V\r]8tSR|\'/[3t)\u0011\t9&a \t\u000f\u0005\u0005\u0015\u00031\u0001\u0002\u0004\u0006Q!/\u001a9pg&$xN]=\u0011\u000b9\u000b))!\u0006\n\u0007\u0005\u001duJ\u0001\u0006=e\u0016\u0004X-\u0019;fIz\n\u0011B\\8NSJ\u0014xN]:\u0016\u0005\u0005]\u0013AC1eI6K\'O]8sgR!\u0011qKAI\u0011\u001d\t\td\u0005a\u0001\u0003\'\u0003RATAC\u0003o\t!#\u00193e\u001b&\u0014(o\u001c:D_:4g)\u001b7fgR!\u0011qKAM\u0011\u001d\ti\u0002\u0006a\u0001\u00037\u0003RATAC\u0003G\t!b^5uQ6{G-\u001e7f)\u0011\t9&!)\t\r\u0005\rV\u00031\u0001~\u0003\u0019iw\u000eZ;mK\u0006Aa/\u001a:tS>t7\u000f\u0006\u0002\u0002*B!!n[AV!\u0011\ti+a-\u000e\u0005\u0005=&bAAY\u0011\u0006!1m\u001c:f\u0013\r9\u0015qV\u0001\u0012M&t\u0017\r\u001c*fa>\u001c\u0018\u000e^8sS\u0016\u001cXCAA]!\u0011Q7.a\u0004\u0002\u0017\u0005dG.T5se>\u00148\u000fM\u000b\u0003\u0003\u007f\u0003b!!1\u0002L\u0006]RBAAb\u0015\u0011\t)-a2\u0002\u0013%lW.\u001e;bE2,\'bAAe\u001f\u0006Q1m\u001c7mK\u000e$\u0018n\u001c8\n\t\u0005M\u00111Y\u0001\u000bC2dW*\u001b:s_J\u001cXCAAi!\u0011Q7.!\u000e\u0002\rI,7/\u001e7u)\t\t9\u000e\u0005\u0003kW\u0006e\u0007cAAne9\u0011qPK\u0001\t-\u0016\u00148/[8ogB\u0011qpK\n\u0005W5\u000b\u0019\u000f\u0005\u0003\u0002f\u0006=XBAAt\u0015\u0011\tI/a;\u0002\u0005%|\'BAAw\u0003\u0011Q\u0017M^1\n\u0007\u0001\f9\u000f\u0006\u0002\u0002`\u0006)\u0011\r\u001d9msR\u0011\u0011q\u001f\t\u0005\u007f\u0002\tI\u0010\u0005\u0003\u0002F\u0005m\u0018\u0002BA\u007f\u0003\u000f\u0012A\u0001V1tW\u0006)Q.\u001a:hKR!\u00111\u0016B\u0002\u0011\u001d\t)K\fa\u0001\u0005\u000b\u0001Ra\u0016B\u0004\u0003WK1A!\u0003b\u0005\u00191Vm\u0019;peV!!Q\u0002B\u000b)\u0011\u0011yAa\b\u0015\t\tE!1\u0004\t\u0005\u007f\u0002\u0011\u0019\u0002E\u0002k\u0005+!a\u0001\\\u0018C\u0002\t]Qc\u00018\u0003\u001a\u00111aO!\u0006C\u00029Dq!a\u00100\u0001\b\u0011i\u0002\u0005\u0004\u0002F\u0005-#1\u0003\u0005\u0007E>\u0002\rA!\t\u0011\t\u0015<\'1C\u000b\u0005\u0005K\u0011i\u0003\u0006\u0005\u0003(\t]\"1\bB\u001f)\u0011\u0011ICa\r\u0011\t}\u0004!1\u0006\t\u0004U\n5BA\u000271\u0005\u0004\u0011y#F\u0002o\u0005c!aA\u001eB\u0017\u0005\u0004q\u0007bBA a\u0001\u000f!Q\u0007\t\u0007\u0003\u000b\nYEa\u000b\t\r\t\u0004\u0004\u0019\u0001B\u001d!\u0011)wMa\u000b\t\u000ba\u0004\u0004\u0019\u0001>\t\u000f\u0005-\u0001\u00071\u0001\u0002\u0010U!!\u0011\tB%)1\u0011\u0019Ea\u0015\u0003X\te#1\fB/)\u0011\u0011)Ea\u0014\u0011\t}\u0004!q\t\t\u0004U\n%CA\u000272\u0005\u0004\u0011Y%F\u0002o\u0005\u001b\"aA\u001eB%\u0005\u0004q\u0007bBA c\u0001\u000f!\u0011\u000b\t\u0007\u0003\u000b\nYEa\u0012\t\r\t\f\u0004\u0019\u0001B+!\u0011)wMa\u0012\t\u000ba\f\u0004\u0019\u0001>\t\u000f\u0005-\u0011\u00071\u0001\u0002\u0010!9\u0011QD\u0019A\u0002\u0005\u0005\u0002bBA\u0019c\u0001\u0007\u0011Q\u0007\u0002\u0007%\u0016\u001cX\u000f\u001c;\u0014\tIj5KV\u0001\be\u0016\u001cX\u000f\u001c;t+\t\u00119\u0007E\u0003X\u0003#\u0011I\u0007E\u0004O\u0005W\n)Ba\u001c\n\u0007\t5tJ\u0001\u0004UkBdWM\r\t\b/\nE$QOAV\u0013\r\u0011\u0019(\u0019\u0002\u0007\u000b&$\b.\u001a:\u0011\t\t]$q\u0010\b\u0005\u0005s\u0012Y\b\u0005\u0002Z\u001f&\u0019!QP(\u0002\rA\u0013X\rZ3g\u0013\u0011\u0011\tIa!\u0003\rM#(/\u001b8h\u0015\r\u0011ihT\u0001\te\u0016\u001cX\u000f\u001c;tAQ!!\u0011\u0012BG!\r\u0011YIM\u0007\u0002W!9!1M\u001bA\u0002\t\u001dTCAAV\u0003-9\u0018\u000e\u001e5SKN,H\u000e^:\u0015\t\t%%Q\u0013\u0005\b\u0005G:\u0004\u0019\u0001B4\u0003!!xn\u0015;sS:<GC\u0001BN!\u0011\u0011iJa)\u000e\u0005\t}%\u0002\u0002BQ\u0003W\fA\u0001\\1oO&!!\u0011\u0011BP\u0003!\u0019\u0017M\\#rk\u0006dG\u0003\u0002BU\u0005_\u00032A\u0014BV\u0013\r\u0011ik\u0014\u0002\b\u0005>|G.Z1o\u0011\u0019\u0011\t,\u000fa\u0001e\u0006\u0019qN\u00196\u0002\r\u0015\fX/\u00197t)\u0011\u0011IKa.\t\r\tE&\b1\u0001s\u0003!A\u0017m\u001d5D_\u0012,GC\u0001B_!\rq%qX\u0005\u0004\u0005\u0003|%aA%oi\u0006)A/\u001e9mKV\u0011!q\u0019\t\u0006\u001d\n%\'qM\u0005\u0004\u0005\u0017|%A\u0002+va2,\u0017\'A\u0007qe>$Wo\u0019;Qe\u00164\u0017\u000e_\u000b\u0003\u00057\u000bA\u0002\u001d:pIV\u001cG/\u0011:jif,\"A!0\u0002\u001dA\u0014x\u000eZ;di\u0016cW-\\3oiR\u0019!O!7\t\u000f\tmw\b1\u0001\u0003>\u0006\ta.\u0001\nqe>$Wo\u0019;FY\u0016lWM\u001c;OC6,G\u0003\u0002BN\u0005CDqAa7A\u0001\u0004\u0011i,\u0001\u0004SKN,H\u000e\u001e\t\u0004\u0005\u0017\u00135\u0003\u0002\"N\u0003G$\"A!:\u0015\t\t%%Q\u001e\u0005\b\u0005G\"\u0005\u0019\u0001B4\u000319(/\u001b;f%\u0016\u0004H.Y2f)\t\u0011\u0019\u0010\u0005\u0003\u0003\u001e\nU\u0018\u0002\u0002B|\u0005?\u0013aa\u00142kK\u000e$\u0018!C<ji\"\u001c\u0015m\u00195f)\u0011\t9F!@\t\u000b\t\\\u0002\u0019\u00013\u0002\u001b]LG\u000f[\'pIVdWm\u00149u)\u0011\t9fa\u0001\t\u000bad\u0002\u0019\u0001>\u0002!]LG\u000f\u001b*fa>\u001c\u0018\u000e^8sS\u0016\u001cH\u0003BA,\u0007\u0013Aq!a\u0003\u001e\u0001\u0004\ty!A\nxSRDW*\u001b:s_J\u001cuN\u001c4GS2,7\u000f\u0006\u0003\u0002X\r=\u0001bBA\u000f=\u0001\u0007\u0011\u0011E\u0001\fo&$\b.T5se>\u00148\u000f\u0006\u0003\u0002X\rU\u0001bBA\u0019?\u0001\u0007\u0011QG\u0001\to&$\bnU=oGR!\u0011qKB\u000e\u0011\u001d\ty\u0004\ta\u0001\u0003\u0007\"BA!+\u0004 !1!\u0011\u0017\u0012A\u0002I$BA!+\u0004$!1!\u0011W\u0012A\u0002I,\"aa\n\u0011\u001b9\u001bI\u0003\u001a>\u0002\u0010\u0005\u0005\u0012QGA\"\u0013\r\u0019Yc\u0014\u0002\u0007)V\u0004H.\u001a\u001c\u0015\u0007I\u001cy\u0003C\u0004\u0003\\\"\u0002\rA!0\u0015\t\tm51\u0007\u0005\b\u00057L\u0003\u0019\u0001B_\u0001
   #14 = Utf8               coursier/Versions$Result
   #15 = Class              #14           // coursier/Versions$Result
   #16 = Utf8               Result
   #17 = Utf8               coursier/Versions$Result$
   #18 = Class              #17           // coursier/Versions$Result$
   #19 = Utf8
   #20 = Utf8               coursier/cache/CacheLogger$Using
   #21 = Class              #20           // coursier/cache/CacheLogger$Using
   #22 = Utf8               coursier/cache/CacheLogger
   #23 = Class              #22           // coursier/cache/CacheLogger
   #24 = Utf8               Using
   #25 = Utf8               coursier/util/Monad$AllOps
   #26 = Class              #25           // coursier/util/Monad$AllOps
   #27 = Utf8               coursier/util/Monad
   #28 = Class              #27           // coursier/util/Monad
   #29 = Utf8               AllOps
   #30 = Utf8               coursier/util/Monad$ops$
   #31 = Class              #30           // coursier/util/Monad$ops$
   #32 = Utf8               java/lang/invoke/MethodHandles$Lookup
   #33 = Class              #32           // java/lang/invoke/MethodHandles$Lookup
   #34 = Utf8               java/lang/invoke/MethodHandles
   #35 = Class              #34           // java/lang/invoke/MethodHandles
   #36 = Utf8               Lookup
   #37 = Utf8               scala/Predef$ArrowAssoc$
   #38 = Class              #37           // scala/Predef$ArrowAssoc$
   #39 = Utf8               scala/Predef
   #40 = Class              #39           // scala/Predef
   #41 = Utf8               cache
   #42 = Utf8               Lcoursier/cache/Cache;
   #43 = Utf8               Lcoursier/cache/Cache<TF;>;
   #44 = Utf8               moduleOpt
   #45 = Utf8               Lscala/Option;
   #46 = Utf8               Lscala/Option<Lcoursier/core/Module;>;
   #47 = Utf8               repositories
   #48 = Utf8               Lscala/collection/immutable/Seq;
   #49 = Utf8               Lscala/collection/immutable/Seq<Lcoursier/core/Repository;>;
   #50 = Utf8               mirrorConfFiles
   #51 = Utf8               Lscala/collection/immutable/Seq<Lcoursier/params/MirrorConfFile;>;
   #52 = Utf8               mirrors
   #53 = Utf8               Lscala/collection/immutable/Seq<Lcoursier/params/Mirror;>;
   #54 = Utf8               sync
   #55 = Utf8               Lcoursier/util/Sync;
   #56 = Utf8               Lcoursier/util/Sync<TF;>;
   #57 = Utf8               apply
   #58 = Utf8               (Lcoursier/cache/Cache;Lscala/Option;Lscala/collection/immutable/Seq;Lscala/collection/immutable/Seq;Lscala/collection/immutable/Seq;Lcoursier/util/Sync;)Lcoursier/Versions;
   #59 = Utf8               <F:Ljava/lang/Object;>(Lcoursier/cache/Cache<TF;>;Lscala/Option<Lcoursier/core/Module;>;Lscala/collection/immutable/Seq<Lcoursier/core/Repository;>;Lscala/collection/immutable/Seq<Lcoursier/params/MirrorConfFile;>;Lscala/collection/immutable/Seq<Lcoursier/params/Mirror;>;Lcoursier/util/Sync<TF;>;)Lcoursier/Versions<TF;>;
   #60 = Utf8               coursier/Versions$
   #61 = Class              #60           // coursier/Versions$
   #62 = Utf8               MODULE$
   #63 = Utf8               Lcoursier/Versions$;
   #64 = NameAndType        #62:#63       // MODULE$:Lcoursier/Versions$;
   #65 = Fieldref           #61.#64       // coursier/Versions$.MODULE$:Lcoursier/Versions$;
   #66 = NameAndType        #57:#58       // apply:(Lcoursier/cache/Cache;Lscala/Option;Lscala/collection/immutable/Seq;Lscala/collection/immutable/Seq;Lscala/collection/immutable/Seq;Lcoursier/util/Sync;)Lcoursier/Versions;
   #67 = Methodref          #61.#66       // coursier/Versions$.apply:(Lcoursier/cache/Cache;Lscala/Option;Lscala/collection/immutable/Seq;Lscala/collection/immutable/Seq;Lscala/collection/immutable/Seq;Lcoursier/util/Sync;)Lcoursier/Versions;
   #68 = Utf8               (Lcoursier/cache/Cache;Lscala/Option;Lscala/collection/immutable/Seq;Lcoursier/util/Sync;)Lcoursier/Versions;
   #69 = Utf8               <F:Ljava/lang/Object;>(Lcoursier/cache/Cache<TF;>;Lscala/Option<Lcoursier/core/Module;>;Lscala/collection/immutable/Seq<Lcoursier/core/Repository;>;Lcoursier/util/Sync<TF;>;)Lcoursier/Versions<TF;>;
   #70 = NameAndType        #57:#68       // apply:(Lcoursier/cache/Cache;Lscala/Option;Lscala/collection/immutable/Seq;Lcoursier/util/Sync;)Lcoursier/Versions;
   #71 = Methodref          #61.#70       // coursier/Versions$.apply:(Lcoursier/cache/Cache;Lscala/Option;Lscala/collection/immutable/Seq;Lcoursier/util/Sync;)Lcoursier/Versions;
   #72 = Utf8               (Lcoursier/cache/Cache;Lcoursier/util/Sync;)Lcoursier/Versions;
   #73 = Utf8               <F:Ljava/lang/Object;>(Lcoursier/cache/Cache<TF;>;Lcoursier/util/Sync<TF;>;)Lcoursier/Versions<TF;>;
   #74 = NameAndType        #57:#72       // apply:(Lcoursier/cache/Cache;Lcoursier/util/Sync;)Lcoursier/Versions;
   #75 = Methodref          #61.#74       // coursier/Versions$.apply:(Lcoursier/cache/Cache;Lcoursier/util/Sync;)Lcoursier/Versions;
   #76 = Utf8               ()Lcoursier/Versions;
   #77 = Utf8               ()Lcoursier/Versions<Lcoursier/util/Task;>;
   #78 = NameAndType        #57:#76       // apply:()Lcoursier/Versions;
   #79 = Methodref          #61.#78       // coursier/Versions$.apply:()Lcoursier/Versions;
   #80 = Utf8               productIterator
   #81 = Utf8               ()Lscala/collection/Iterator;
   #82 = Utf8               ()Lscala/collection/Iterator<Ljava/lang/Object;>;
   #83 = Utf8               productIterator$
   #84 = Utf8               (Lscala/Product;)Lscala/collection/Iterator;
   #85 = NameAndType        #83:#84       // productIterator$:(Lscala/Product;)Lscala/collection/Iterator;
   #86 = InterfaceMethodref #7.#85        // scala/Product.productIterator$:(Lscala/Product;)Lscala/collection/Iterator;
   #87 = Utf8               this
   #88 = Utf8               Lcoursier/Versions;
   #89 = Utf8               productElementNames
   #90 = Utf8               ()Lscala/collection/Iterator<Ljava/lang/String;>;
   #91 = Utf8               productElementNames$
   #92 = NameAndType        #91:#84       // productElementNames$:(Lscala/Product;)Lscala/collection/Iterator;
   #93 = InterfaceMethodref #7.#92        // scala/Product.productElementNames$:(Lscala/Product;)Lscala/collection/Iterator;
   #94 = Utf8               ()Lcoursier/cache/Cache;
   #95 = Utf8               ()Lcoursier/cache/Cache<TF;>;
   #96 = NameAndType        #41:#42       // cache:Lcoursier/cache/Cache;
   #97 = Fieldref           #2.#96        // coursier/Versions.cache:Lcoursier/cache/Cache;
   #98 = Utf8               ()Lscala/Option;
   #99 = Utf8               ()Lscala/Option<Lcoursier/core/Module;>;
  #100 = NameAndType        #44:#45       // moduleOpt:Lscala/Option;
  #101 = Fieldref           #2.#100       // coursier/Versions.moduleOpt:Lscala/Option;
  #102 = Utf8               ()Lscala/collection/immutable/Seq;
  #103 = Utf8               ()Lscala/collection/immutable/Seq<Lcoursier/core/Repository;>;
  #104 = NameAndType        #47:#48       // repositories:Lscala/collection/immutable/Seq;
  #105 = Fieldref           #2.#104       // coursier/Versions.repositories:Lscala/collection/immutable/Seq;
  #106 = Utf8               ()Lscala/collection/immutable/Seq<Lcoursier/params/MirrorConfFile;>;
  #107 = NameAndType        #50:#48       // mirrorConfFiles:Lscala/collection/immutable/Seq;
  #108 = Fieldref           #2.#107       // coursier/Versions.mirrorConfFiles:Lscala/collection/immutable/Seq;
  #109 = Utf8               ()Lscala/collection/immutable/Seq<Lcoursier/params/Mirror;>;
  #110 = NameAndType        #52:#48       // mirrors:Lscala/collection/immutable/Seq;
  #111 = Fieldref           #2.#110       // coursier/Versions.mirrors:Lscala/collection/immutable/Seq;
  #112 = Utf8               ()Lcoursier/util/Sync;
  #113 = Utf8               ()Lcoursier/util/Sync<TF;>;
  #114 = NameAndType        #54:#55       // sync:Lcoursier/util/Sync;
  #115 = Fieldref           #2.#114       // coursier/Versions.sync:Lcoursier/util/Sync;
  #116 = Utf8               F
  #117 = NameAndType        #54:#112      // sync:()Lcoursier/util/Sync;
  #118 = Methodref          #2.#117       // coursier/Versions.sync:()Lcoursier/util/Sync;
  #119 = Utf8               addRepositories
  #120 = Utf8               (Lscala/collection/immutable/Seq;)Lcoursier/Versions;
  #121 = Utf8               (Lscala/collection/immutable/Seq<Lcoursier/core/Repository;>;)Lcoursier/Versions<TF;>;
  #122 = Utf8               repository
  #123 = NameAndType        #47:#102      // repositories:()Lscala/collection/immutable/Seq;
  #124 = Methodref          #2.#123       // coursier/Versions.repositories:()Lscala/collection/immutable/Seq;
  #125 = Utf8               scala/collection/immutable/Seq
  #126 = Class              #125          // scala/collection/immutable/Seq
  #127 = Utf8               $plus$plus
  #128 = Utf8               (Lscala/collection/IterableOnce;)Ljava/lang/Object;
  #129 = NameAndType        #127:#128     // $plus$plus:(Lscala/collection/IterableOnce;)Ljava/lang/Object;
  #130 = InterfaceMethodref #126.#129     // scala/collection/immutable/Seq.$plus$plus:(Lscala/collection/IterableOnce;)Ljava/lang/Object;
  #131 = Utf8               withRepositories
  #132 = NameAndType        #131:#120     // withRepositories:(Lscala/collection/immutable/Seq;)Lcoursier/Versions;
  #133 = Methodref          #2.#132       // coursier/Versions.withRepositories:(Lscala/collection/immutable/Seq;)Lcoursier/Versions;
  #134 = Utf8               noMirrors
  #135 = Utf8               ()Lcoursier/Versions<TF;>;
  #136 = Utf8               scala/collection/immutable/Nil$
  #137 = Class              #136          // scala/collection/immutable/Nil$
  #138 = Utf8               Lscala/collection/immutable/Nil$;
  #139 = NameAndType        #62:#138      // MODULE$:Lscala/collection/immutable/Nil$;
  #140 = Fieldref           #137.#139     // scala/collection/immutable/Nil$.MODULE$:Lscala/collection/immutable/Nil$;
  #141 = Utf8               withMirrors
  #142 = NameAndType        #141:#120     // withMirrors:(Lscala/collection/immutable/Seq;)Lcoursier/Versions;
  #143 = Methodref          #2.#142       // coursier/Versions.withMirrors:(Lscala/collection/immutable/Seq;)Lcoursier/Versions;
  #144 = Utf8               withMirrorConfFiles
  #145 = NameAndType        #144:#120     // withMirrorConfFiles:(Lscala/collection/immutable/Seq;)Lcoursier/Versions;
  #146 = Methodref          #2.#145       // coursier/Versions.withMirrorConfFiles:(Lscala/collection/immutable/Seq;)Lcoursier/Versions;
  #147 = Utf8               addMirrors
  #148 = Utf8               (Lscala/collection/immutable/Seq<Lcoursier/params/Mirror;>;)Lcoursier/Versions<TF;>;
  #149 = NameAndType        #52:#102      // mirrors:()Lscala/collection/immutable/Seq;
  #150 = Methodref          #2.#149       // coursier/Versions.mirrors:()Lscala/collection/immutable/Seq;
  #151 = Utf8               addMirrorConfFiles
  #152 = Utf8               (Lscala/collection/immutable/Seq<Lcoursier/params/MirrorConfFile;>;)Lcoursier/Versions<TF;>;
  #153 = NameAndType        #50:#102      // mirrorConfFiles:()Lscala/collection/immutable/Seq;
  #154 = Methodref          #2.#153       // coursier/Versions.mirrorConfFiles:()Lscala/collection/immutable/Seq;
  #155 = Utf8               withModule
  #156 = Utf8               (Lcoursier/core/Module;)Lcoursier/Versions;
  #157 = Utf8               (Lcoursier/core/Module;)Lcoursier/Versions<TF;>;
  #158 = Utf8               module
  #159 = Utf8               scala/Some
  #160 = Class              #159          // scala/Some
  #161 = Utf8               <init>
  #162 = Utf8               (Ljava/lang/Object;)V
  #163 = NameAndType        #161:#162     // "<init>":(Ljava/lang/Object;)V
  #164 = Methodref          #160.#163     // scala/Some."<init>":(Ljava/lang/Object;)V
  #165 = Utf8               withModuleOpt
  #166 = Utf8               (Lscala/Option;)Lcoursier/Versions;
  #167 = NameAndType        #165:#166     // withModuleOpt:(Lscala/Option;)Lcoursier/Versions;
  #168 = Methodref          #2.#167       // coursier/Versions.withModuleOpt:(Lscala/Option;)Lcoursier/Versions;
  #169 = Utf8               Lcoursier/core/Module;
  #170 = Utf8               versions
  #171 = Utf8               ()Ljava/lang/Object;
  #172 = Utf8               ()TF;
  #173 = Utf8               Lcoursier/util/Monad$ops$;
  #174 = NameAndType        #62:#173      // MODULE$:Lcoursier/util/Monad$ops$;
  #175 = Fieldref           #31.#174      // coursier/util/Monad$ops$.MODULE$:Lcoursier/util/Monad$ops$;
  #176 = Utf8               result
  #177 = NameAndType        #176:#171     // result:()Ljava/lang/Object;
  #178 = Methodref          #2.#177       // coursier/Versions.result:()Ljava/lang/Object;
  #179 = Utf8               toAllMonadOps
  #180 = Utf8               (Ljava/lang/Object;Lcoursier/util/Monad;)Lcoursier/util/Monad$AllOps;
  #181 = NameAndType        #179:#180     // toAllMonadOps:(Ljava/lang/Object;Lcoursier/util/Monad;)Lcoursier/util/Monad$AllOps;
  #182 = Methodref          #31.#181      // coursier/util/Monad$ops$.toAllMonadOps:(Ljava/lang/Object;Lcoursier/util/Monad;)Lcoursier/util/Monad$AllOps;
  #183 = Utf8               (Ljava/lang/Object;)Ljava/lang/Object;
  #184 = MethodType         #183          //  (Ljava/lang/Object;)Ljava/lang/Object;
  #185 = Utf8               $anonfun$versions$1
  #186 = Utf8               (Lcoursier/Versions$Result;)Lcoursier/core/Versions;
  #187 = NameAndType        #185:#186     // $anonfun$versions$1:(Lcoursier/Versions$Result;)Lcoursier/core/Versions;
  #188 = Methodref          #2.#187       // coursier/Versions.$anonfun$versions$1:(Lcoursier/Versions$Result;)Lcoursier/core/Versions;
  #189 = MethodHandle       6:#188        // REF_invokeStatic coursier/Versions.$anonfun$versions$1:(Lcoursier/Versions$Result;)Lcoursier/core/Versions;
  #190 = MethodType         #186          //  (Lcoursier/Versions$Result;)Lcoursier/core/Versions;
  #191 = Integer            5
  #192 = Integer            1
  #193 = Utf8               java/lang/invoke/LambdaMetafactory
  #194 = Class              #193          // java/lang/invoke/LambdaMetafactory
  #195 = Utf8               altMetafactory
  #196 = Utf8               (Ljava/lang/invoke/MethodHandles$Lookup;Ljava/lang/String;Ljava/lang/invoke/MethodType;[Ljava/lang/Object;)Ljava/lang/invoke/CallSite;
  #197 = NameAndType        #195:#196     // altMetafactory:(Ljava/lang/invoke/MethodHandles$Lookup;Ljava/lang/String;Ljava/lang/invoke/MethodType;[Ljava/lang/Object;)Ljava/lang/invoke/CallSite;
  #198 = Methodref          #194.#197     // java/lang/invoke/LambdaMetafactory.altMetafactory:(Ljava/lang/invoke/MethodHandles$Lookup;Ljava/lang/String;Ljava/lang/invoke/MethodType;[Ljava/lang/Object;)Ljava/lang/invoke/CallSite;
  #199 = MethodHandle       6:#198        // REF_invokeStatic java/lang/invoke/LambdaMetafactory.altMetafactory:(Ljava/lang/invoke/MethodHandles$Lookup;Ljava/lang/String;Ljava/lang/invoke/MethodType;[Ljava/lang/Object;)Ljava/lang/invoke/CallSite;
  #200 = Utf8               ()Lscala/Function1;
  #201 = NameAndType        #57:#200      // apply:()Lscala/Function1;
  #202 = InvokeDynamic      #0:#201       // #0:apply:()Lscala/Function1;
  #203 = Utf8               map
  #204 = Utf8               (Lscala/Function1;)Ljava/lang/Object;
  #205 = NameAndType        #203:#204     // map:(Lscala/Function1;)Ljava/lang/Object;
  #206 = InterfaceMethodref #26.#205      // coursier/util/Monad$AllOps.map:(Lscala/Function1;)Ljava/lang/Object;
  #207 = Utf8               finalRepositories
  #208 = Utf8               allMirrors
  #209 = NameAndType        #208:#171     // allMirrors:()Ljava/lang/Object;
  #210 = Methodref          #2.#209       // coursier/Versions.allMirrors:()Ljava/lang/Object;
  #211 = Utf8               $anonfun$finalRepositories$1
  #212 = Utf8               (Lcoursier/Versions;Lscala/collection/immutable/Seq;)Lscala/collection/immutable/Seq;
  #213 = NameAndType        #211:#212     // $anonfun$finalRepositories$1:(Lcoursier/Versions;Lscala/collection/immutable/Seq;)Lscala/collection/immutable/Seq;
  #214 = Methodref          #2.#213       // coursier/Versions.$anonfun$finalRepositories$1:(Lcoursier/Versions;Lscala/collection/immutable/Seq;)Lscala/collection/immutable/Seq;
  #215 = MethodHandle       6:#214        // REF_invokeStatic coursier/Versions.$anonfun$finalRepositories$1:(Lcoursier/Versions;Lscala/collection/immutable/Seq;)Lscala/collection/immutable/Seq;
  #216 = Utf8               (Lscala/collection/immutable/Seq;)Lscala/collection/immutable/Seq;
  #217 = MethodType         #216          //  (Lscala/collection/immutable/Seq;)Lscala/collection/immutable/Seq;
  #218 = Utf8               (Lcoursier/Versions;)Lscala/Function1;
  #219 = NameAndType        #57:#218      // apply:(Lcoursier/Versions;)Lscala/Function1;
  #220 = InvokeDynamic      #1:#219       // #1:apply:(Lcoursier/Versions;)Lscala/Function1;
  #221 = Utf8               allMirrors0
  #222 = Utf8               $anonfun$allMirrors0$1
  #223 = Utf8               (Lcoursier/params/MirrorConfFile;)Lscala/collection/immutable/Seq;
  #224 = NameAndType        #222:#223     // $anonfun$allMirrors0$1:(Lcoursier/params/MirrorConfFile;)Lscala/collection/immutable/Seq;
  #225 = Methodref          #2.#224       // coursier/Versions.$anonfun$allMirrors0$1:(Lcoursier/params/MirrorConfFile;)Lscala/collection/immutable/Seq;
  #226 = MethodHandle       6:#225        // REF_invokeStatic coursier/Versions.$anonfun$allMirrors0$1:(Lcoursier/params/MirrorConfFile;)Lscala/collection/immutable/Seq;
  #227 = MethodType         #223          //  (Lcoursier/params/MirrorConfFile;)Lscala/collection/immutable/Seq;
  #228 = InvokeDynamic      #2:#201       // #2:apply:()Lscala/Function1;
  #229 = Utf8               flatMap
  #230 = NameAndType        #229:#204     // flatMap:(Lscala/Function1;)Ljava/lang/Object;
  #231 = InterfaceMethodref #126.#230     // scala/collection/immutable/Seq.flatMap:(Lscala/Function1;)Ljava/lang/Object;
  #232 = Utf8               scala/collection/IterableOnce
  #233 = Class              #232          // scala/collection/IterableOnce
  #234 = NameAndType        #116:#112     // F:()Lcoursier/util/Sync;
  #235 = Methodref          #2.#234       // coursier/Versions.F:()Lcoursier/util/Sync;
  #236 = MethodType         #171          //  ()Ljava/lang/Object;
  #237 = Utf8               $anonfun$allMirrors$1
  #238 = Utf8               (Lcoursier/Versions;)Lscala/collection/immutable/Seq;
  #239 = NameAndType        #237:#238     // $anonfun$allMirrors$1:(Lcoursier/Versions;)Lscala/collection/immutable/Seq;
  #240 = Methodref          #2.#239       // coursier/Versions.$anonfun$allMirrors$1:(Lcoursier/Versions;)Lscala/collection/immutable/Seq;
  #241 = MethodHandle       6:#240        // REF_invokeStatic coursier/Versions.$anonfun$allMirrors$1:(Lcoursier/Versions;)Lscala/collection/immutable/Seq;
  #242 = MethodType         #102          //  ()Lscala/collection/immutable/Seq;
  #243 = Utf8               (Lcoursier/Versions;)Lscala/Function0;
  #244 = NameAndType        #57:#243      // apply:(Lcoursier/Versions;)Lscala/Function0;
  #245 = InvokeDynamic      #3:#244       // #3:apply:(Lcoursier/Versions;)Lscala/Function0;
  #246 = Utf8               coursier/util/Sync
  #247 = Class              #246          // coursier/util/Sync
  #248 = Utf8               delay
  #249 = Utf8               (Lscala/Function0;)Ljava/lang/Object;
  #250 = NameAndType        #248:#249     // delay:(Lscala/Function0;)Ljava/lang/Object;
  #251 = InterfaceMethodref #247.#250     // coursier/util/Sync.delay:(Lscala/Function0;)Ljava/lang/Object;
  #252 = NameAndType        #207:#171     // finalRepositories:()Ljava/lang/Object;
  #253 = Methodref          #2.#252       // coursier/Versions.finalRepositories:()Ljava/lang/Object;
  #254 = Utf8               $anonfun$result$1
  #255 = Utf8               (Lcoursier/Versions;Lscala/collection/immutable/Seq;)Ljava/lang/Object;
  #256 = NameAndType        #254:#255     // $anonfun$result$1:(Lcoursier/Versions;Lscala/collection/immutable/Seq;)Ljava/lang/Object;
  #257 = Methodref          #2.#256       // coursier/Versions.$anonfun$result$1:(Lcoursier/Versions;Lscala/collection/immutable/Seq;)Ljava/lang/Object;
  #258 = MethodHandle       6:#257        // REF_invokeStatic coursier/Versions.$anonfun$result$1:(Lcoursier/Versions;Lscala/collection/immutable/Seq;)Ljava/lang/Object;
  #259 = Utf8               (Lscala/collection/immutable/Seq;)Ljava/lang/Object;
  #260 = MethodType         #259          //  (Lscala/collection/immutable/Seq;)Ljava/lang/Object;
  #261 = InvokeDynamic      #4:#219       // #4:apply:(Lcoursier/Versions;)Lscala/Function1;
  #262 = InterfaceMethodref #26.#230      // coursier/util/Monad$AllOps.flatMap:(Lscala/Function1;)Ljava/lang/Object;
  #263 = NameAndType        #41:#94       // cache:()Lcoursier/cache/Cache;
  #264 = Methodref          #2.#263       // coursier/Versions.cache:()Lcoursier/cache/Cache;
  #265 = Utf8               coursier/cache/Cache
  #266 = Class              #265          // coursier/cache/Cache
  #267 = Utf8               loggerOpt
  #268 = NameAndType        #267:#98      // loggerOpt:()Lscala/Option;
  #269 = Methodref          #266.#268     // coursier/cache/Cache.loggerOpt:()Lscala/Option;
  #270 = Utf8               $anonfun$result$6
  #271 = NameAndType        #270:#183     // $anonfun$result$6:(Ljava/lang/Object;)Ljava/lang/Object;
  #272 = Methodref          #2.#271       // coursier/Versions.$anonfun$result$6:(Ljava/lang/Object;)Ljava/lang/Object;
  #273 = MethodHandle       6:#272        // REF_invokeStatic coursier/Versions.$anonfun$result$6:(Ljava/lang/Object;)Ljava/lang/Object;
  #274 = Utf8               (Ljava/lang/Object;)Lscala/Function0;
  #275 = NameAndType        #57:#274      // apply:(Ljava/lang/Object;)Lscala/Function0;
  #276 = InvokeDynamic      #5:#275       // #5:apply:(Ljava/lang/Object;)Lscala/Function0;
  #277 = Utf8               $anonfun$result$7
  #278 = Utf8               (Lcoursier/Versions;Ljava/lang/Object;Lcoursier/cache/CacheLogger;)Ljava/lang/Object;
  #279 = NameAndType        #277:#278     // $anonfun$result$7:(Lcoursier/Versions;Ljava/lang/Object;Lcoursier/cache/CacheLogger;)Ljava/lang/Object;
  #280 = Methodref          #2.#279       // coursier/Versions.$anonfun$result$7:(Lcoursier/Versions;Ljava/lang/Object;Lcoursier/cache/CacheLogger;)Ljava/lang/Object;
  #281 = MethodHandle       6:#280        // REF_invokeStatic coursier/Versions.$anonfun$result$7:(Lcoursier/Versions;Ljava/lang/Object;Lcoursier/cache/CacheLogger;)Ljava/lang/Object;
  #282 = Utf8               (Lcoursier/cache/CacheLogger;)Ljava/lang/Object;
  #283 = MethodType         #282          //  (Lcoursier/cache/CacheLogger;)Ljava/lang/Object;
  #284 = Utf8               (Lcoursier/Versions;Ljava/lang/Object;)Lscala/Function1;
  #285 = NameAndType        #57:#284      // apply:(Lcoursier/Versions;Ljava/lang/Object;)Lscala/Function1;
  #286 = InvokeDynamic      #6:#285       // #6:apply:(Lcoursier/Versions;Ljava/lang/Object;)Lscala/Function1;
  #287 = Utf8               scala/Option
  #288 = Class              #287          // scala/Option
  #289 = Utf8               fold
  #290 = Utf8               (Lscala/Function0;Lscala/Function1;)Ljava/lang/Object;
  #291 = NameAndType        #289:#290     // fold:(Lscala/Function0;Lscala/Function1;)Ljava/lang/Object;
  #292 = Methodref          #288.#291     // scala/Option.fold:(Lscala/Function0;Lscala/Function1;)Ljava/lang/Object;
  #293 = Utf8               $anonfun$result$8
  #294 = Utf8               (Lscala/collection/immutable/Seq;)Lcoursier/Versions$Result;
  #295 = NameAndType        #293:#294     // $anonfun$result$8:(Lscala/collection/immutable/Seq;)Lcoursier/Versions$Result;
  #296 = Methodref          #2.#295       // coursier/Versions.$anonfun$result$8:(Lscala/collection/immutable/Seq;)Lcoursier/Versions$Result;
  #297 = MethodHandle       6:#296        // REF_invokeStatic coursier/Versions.$anonfun$result$8:(Lscala/collection/immutable/Seq;)Lcoursier/Versions$Result;
  #298 = MethodType         #294          //  (Lscala/collection/immutable/Seq;)Lcoursier/Versions$Result;
  #299 = InvokeDynamic      #7:#201       // #7:apply:()Lscala/Function1;
  #300 = Utf8               t
  #301 = Utf8               Ljava/lang/Object;
  #302 = Utf8               t0
  #303 = Utf8               withCache
  #304 = Utf8               (Lcoursier/cache/Cache;)Lcoursier/Versions;
  #305 = Utf8               (Lcoursier/cache/Cache<TF;>;)Lcoursier/Versions<TF;>;
  #306 = NameAndType        #44:#98       // moduleOpt:()Lscala/Option;
  #307 = Methodref          #2.#306       // coursier/Versions.moduleOpt:()Lscala/Option;
  #308 = Utf8               (Lcoursier/cache/Cache;Lscala/Option;Lscala/collection/immutable/Seq;Lscala/collection/immutable/Seq;Lscala/collection/immutable/Seq;Lcoursier/util/Sync;)V
  #309 = NameAndType        #161:#308     // "<init>":(Lcoursier/cache/Cache;Lscala/Option;Lscala/collection/immutable/Seq;Lscala/collection/immutable/Seq;Lscala/collection/immutable/Seq;Lcoursier/util/Sync;)V
  #310 = Methodref          #2.#309       // coursier/Versions."<init>":(Lcoursier/cache/Cache;Lscala/Option;Lscala/collection/immutable/Seq;Lscala/collection/immutable/Seq;Lscala/collection/immutable/Seq;Lcoursier/util/Sync;)V
  #311 = Utf8               (Lscala/Option<Lcoursier/core/Module;>;)Lcoursier/Versions<TF;>;
  #312 = Utf8               withSync
  #313 = Utf8               (Lcoursier/util/Sync;)Lcoursier/Versions;
  #314 = Utf8               (Lcoursier/util/Sync<TF;>;)Lcoursier/Versions<TF;>;
  #315 = Utf8               toString
  #316 = Utf8               ()Ljava/lang/String;
  #317 = Utf8               java/lang/StringBuilder
  #318 = Class              #317          // java/lang/StringBuilder
  #319 = Utf8               Versions(
  #320 = String             #319          // Versions(
  #321 = Utf8               (Ljava/lang/String;)V
  #322 = NameAndType        #161:#321     // "<init>":(Ljava/lang/String;)V
  #323 = Methodref          #318.#322     // java/lang/StringBuilder."<init>":(Ljava/lang/String;)V
  #324 = Utf8               java/lang/String
  #325 = Class              #324          // java/lang/String
  #326 = Utf8               valueOf
  #327 = Utf8               (Ljava/lang/Object;)Ljava/lang/String;
  #328 = NameAndType        #326:#327     // valueOf:(Ljava/lang/Object;)Ljava/lang/String;
  #329 = Methodref          #325.#328     // java/lang/String.valueOf:(Ljava/lang/Object;)Ljava/lang/String;
  #330 = Utf8               append
  #331 = Utf8               (Ljava/lang/String;)Ljava/lang/StringBuilder;
  #332 = NameAndType        #330:#331     // append:(Ljava/lang/String;)Ljava/lang/StringBuilder;
  #333 = Methodref          #318.#332     // java/lang/StringBuilder.append:(Ljava/lang/String;)Ljava/lang/StringBuilder;
  #334 = Utf8               ,
  #335 = String             #334          // ,
  #336 = Utf8               )
  #337 = String             #336          // )
  #338 = NameAndType        #315:#316     // toString:()Ljava/lang/String;
  #339 = Methodref          #318.#338     // java/lang/StringBuilder.toString:()Ljava/lang/String;
  #340 = Utf8               b
  #341 = Utf8               Ljava/lang/StringBuilder;
  #342 = Utf8               canEqual
  #343 = Utf8               (Ljava/lang/Object;)Z
  #344 = Utf8               obj
  #345 = Utf8               equals
  #346 = NameAndType        #342:#343     // canEqual:(Ljava/lang/Object;)Z
  #347 = Methodref          #2.#346       // coursier/Versions.canEqual:(Ljava/lang/Object;)Z
  #348 = NameAndType        #345:#343     // equals:(Ljava/lang/Object;)Z
  #349 = Methodref          #5.#348       // java/lang/Object.equals:(Ljava/lang/Object;)Z
  #350 = Utf8               other
  #351 = Utf8               hashCode
  #352 = Utf8               ()I
  #353 = Utf8               Versions
  #354 = String             #353          // Versions
  #355 = Utf8               scala/runtime/Statics
  #356 = Class              #355          // scala/runtime/Statics
  #357 = Utf8               anyHash
  #358 = Utf8               (Ljava/lang/Object;)I
  #359 = NameAndType        #357:#358     // anyHash:(Ljava/lang/Object;)I
  #360 = Methodref          #356.#359     // scala/runtime/Statics.anyHash:(Ljava/lang/Object;)I
  #361 = Utf8               code
  #362 = Utf8               I
  #363 = Utf8               tuple
  #364 = Utf8               ()Lscala/Tuple6;
  #365 = Utf8               ()Lscala/Tuple6<Lcoursier/cache/Cache<TF;>;Lscala/Option<Lcoursier/core/Module;>;Lscala/collection/immutable/Seq<Lcoursier/core/Repository;>;Lscala/collection/immutable/Seq<Lcoursier/params/MirrorConfFile;>;Lscala/collection/immutable/Seq<Lcoursier/params/Mirror;>;Lcoursier/util/Sync<TF;>;>;
  #366 = Utf8               scala/Tuple6
  #367 = Class              #366          // scala/Tuple6
  #368 = Utf8               (Ljava/lang/Object;Ljava/lang/Object;Ljava/lang/Object;Ljava/lang/Object;Ljava/lang/Object;Ljava/lang/Object;)V
  #369 = NameAndType        #161:#368     // "<init>":(Ljava/lang/Object;Ljava/lang/Object;Ljava/lang/Object;Ljava/lang/Object;Ljava/lang/Object;Ljava/lang/Object;)V
  #370 = Methodref          #367.#369     // scala/Tuple6."<init>":(Ljava/lang/Object;Ljava/lang/Object;Ljava/lang/Object;Ljava/lang/Object;Ljava/lang/Object;Ljava/lang/Object;)V
  #371 = Utf8               productPrefix
  #372 = Utf8               productArity
  #373 = Utf8               productElement
  #374 = Utf8               (I)Ljava/lang/Object;
  #375 = Utf8               n
  #376 = Utf8               java/lang/IndexOutOfBoundsException
  #377 = Class              #376          // java/lang/IndexOutOfBoundsException
  #378 = Utf8               scala/runtime/BoxesRunTime
  #379 = Class              #378          // scala/runtime/BoxesRunTime
  #380 = Utf8               boxToInteger
  #381 = Utf8               (I)Ljava/lang/Integer;
  #382 = NameAndType        #380:#381     // boxToInteger:(I)Ljava/lang/Integer;
  #383 = Methodref          #379.#382     // scala/runtime/BoxesRunTime.boxToInteger:(I)Ljava/lang/Integer;
  #384 = Methodref          #5.#338       // java/lang/Object.toString:()Ljava/lang/String;
  #385 = Methodref          #377.#322     // java/lang/IndexOutOfBoundsException."<init>":(Ljava/lang/String;)V
  #386 = Utf8               productElementName
  #387 = Utf8               (I)Ljava/lang/String;
  #388 = String             #41           // cache
  #389 = String             #44           // moduleOpt
  #390 = String             #47           // repositories
  #391 = String             #50           // mirrorConfFiles
  #392 = String             #52           // mirrors
  #393 = String             #54           // sync
  #394 = Utf8               x$1
  #395 = Utf8               ()Lcoursier/core/Versions;
  #396 = NameAndType        #170:#395     // versions:()Lcoursier/core/Versions;
  #397 = Methodref          #15.#396      // coursier/Versions$Result.versions:()Lcoursier/core/Versions;
  #398 = Utf8               Lcoursier/Versions$Result;
  #399 = Utf8               $this
  #400 = Utf8               x$2
  #401 = Utf8               coursier/params/Mirror$
  #402 = Class              #401          // coursier/params/Mirror$
  #403 = Utf8               Lcoursier/params/Mirror$;
  #404 = NameAndType        #62:#403      // MODULE$:Lcoursier/params/Mirror$;
  #405 = Fieldref           #402.#404     // coursier/params/Mirror$.MODULE$:Lcoursier/params/Mirror$;
  #406 = Utf8               replace
  #407 = Utf8               (Lscala/collection/immutable/Seq;Lscala/collection/immutable/Seq;)Lscala/collection/immutable/Seq;
  #408 = NameAndType        #406:#407     // replace:(Lscala/collection/immutable/Seq;Lscala/collection/immutable/Seq;)Lscala/collection/immutable/Seq;
  #409 = Methodref          #402.#408     // coursier/params/Mirror$.replace:(Lscala/collection/immutable/Seq;Lscala/collection/immutable/Seq;)Lscala/collection/immutable/Seq;
  #410 = Utf8               x$3
  #411 = Utf8               coursier/params/MirrorConfFile
  #412 = Class              #411          // coursier/params/MirrorConfFile
  #413 = Methodref          #412.#149     // coursier/params/MirrorConfFile.mirrors:()Lscala/collection/immutable/Seq;
  #414 = Utf8               Lcoursier/params/MirrorConfFile;
  #415 = NameAndType        #221:#102     // allMirrors0:()Lscala/collection/immutable/Seq;
  #416 = Methodref          #2.#415       // coursier/Versions.allMirrors0:()Lscala/collection/immutable/Seq;
  #417 = Utf8               $anonfun$result$5
  #418 = Utf8               (Lscala/Tuple2;)Lcoursier/core/Versions;
  #419 = Utf8               x$5
  #420 = Utf8               scala/Tuple2
  #421 = Class              #420          // scala/Tuple2
  #422 = Utf8               _1
  #423 = NameAndType        #422:#171     // _1:()Ljava/lang/Object;
  #424 = Methodref          #421.#423     // scala/Tuple2._1:()Ljava/lang/Object;
  #425 = Utf8               coursier/core/Versions
  #426 = Class              #425          // coursier/core/Versions
  #427 = Utf8               Lscala/Tuple2;
  #428 = Utf8               $anonfun$result$4
  #429 = Utf8               (Lcoursier/core/Repository;Lscala/util/Either;)Lscala/Tuple2;
  #430 = Utf8               repo$1
  #431 = Utf8               x$4
  #432 = Utf8               Lscala/Predef$ArrowAssoc$;
  #433 = NameAndType        #62:#432      // MODULE$:Lscala/Predef$ArrowAssoc$;
  #434 = Fieldref           #38.#433      // scala/Predef$ArrowAssoc$.MODULE$:Lscala/Predef$ArrowAssoc$;
  #435 = Utf8               scala/Predef$
  #436 = Class              #435          // scala/Predef$
  #437 = Utf8               Lscala/Predef$;
  #438 = NameAndType        #62:#437      // MODULE$:Lscala/Predef$;
  #439 = Fieldref           #436.#438     // scala/Predef$.MODULE$:Lscala/Predef$;
  #440 = Utf8               ArrowAssoc
  #441 = NameAndType        #440:#183     // ArrowAssoc:(Ljava/lang/Object;)Ljava/lang/Object;
  #442 = Methodref          #436.#441     // scala/Predef$.ArrowAssoc:(Ljava/lang/Object;)Ljava/lang/Object;
  #443 = NameAndType        #417:#418     // $anonfun$result$5:(Lscala/Tuple2;)Lcoursier/core/Versions;
  #444 = Methodref          #2.#443       // coursier/Versions.$anonfun$result$5:(Lscala/Tuple2;)Lcoursier/core/Versions;
  #445 = MethodHandle       6:#444        // REF_invokeStatic coursier/Versions.$anonfun$result$5:(Lscala/Tuple2;)Lcoursier/core/Versions;
  #446 = MethodType         #418          //  (Lscala/Tuple2;)Lcoursier/core/Versions;
  #447 = InvokeDynamic      #8:#201       // #8:apply:()Lscala/Function1;
  #448 = Utf8               scala/util/Either
  #449 = Class              #448          // scala/util/Either
  #450 = Utf8               (Lscala/Function1;)Lscala/util/Either;
  #451 = NameAndType        #203:#450     // map:(Lscala/Function1;)Lscala/util/Either;
  #452 = Methodref          #449.#451     // scala/util/Either.map:(Lscala/Function1;)Lscala/util/Either;
  #453 = Utf8               $minus$greater$extension
  #454 = Utf8               (Ljava/lang/Object;Ljava/lang/Object;)Lscala/Tuple2;
  #455 = NameAndType        #453:#454     // $minus$greater$extension:(Ljava/lang/Object;Ljava/lang/Object;)Lscala/Tuple2;
  #456 = Methodref          #38.#455      // scala/Predef$ArrowAssoc$.$minus$greater$extension:(Ljava/lang/Object;Ljava/lang/Object;)Lscala/Tuple2;
  #457 = Utf8               Lcoursier/core/Repository;
  #458 = Utf8               Lscala/util/Either;
  #459 = Utf8               $anonfun$result$3
  #460 = Utf8               (Lcoursier/Versions;Lcoursier/core/Module;Lcoursier/core/Repository;)Ljava/lang/Object;
  #461 = Utf8               mod$1
  #462 = Utf8               repo
  #463 = Utf8               fetch
  #464 = NameAndType        #463:#200     // fetch:()Lscala/Function1;
  #465 = Methodref          #266.#464     // coursier/cache/Cache.fetch:()Lscala/Function1;
  #466 = Utf8               coursier/core/Repository
  #467 = Class              #466          // coursier/core/Repository
  #468 = Utf8               (Lcoursier/core/Module;Lscala/Function1;Lcoursier/util/Monad;)Lcoursier/util/EitherT;
  #469 = NameAndType        #170:#468     // versions:(Lcoursier/core/Module;Lscala/Function1;Lcoursier/util/Monad;)Lcoursier/util/EitherT;
  #470 = InterfaceMethodref #467.#469     // coursier/core/Repository.versions:(Lcoursier/core/Module;Lscala/Function1;Lcoursier/util/Monad;)Lcoursier/util/EitherT;
  #471 = Utf8               coursier/util/EitherT
  #472 = Class              #471          // coursier/util/EitherT
  #473 = Utf8               run
  #474 = NameAndType        #473:#171     // run:()Ljava/lang/Object;
  #475 = Methodref          #472.#474     // coursier/util/EitherT.run:()Ljava/lang/Object;
  #476 = NameAndType        #428:#429     // $anonfun$result$4:(Lcoursier/core/Repository;Lscala/util/Either;)Lscala/Tuple2;
  #477 = Methodref          #2.#476       // coursier/Versions.$anonfun$result$4:(Lcoursier/core/Repository;Lscala/util/Either;)Lscala/Tuple2;
  #478 = MethodHandle       6:#477        // REF_invokeStatic coursier/Versions.$anonfun$result$4:(Lcoursier/core/Repository;Lscala/util/Either;)Lscala/Tuple2;
  #479 = Utf8               (Lscala/util/Either;)Lscala/Tuple2;
  #480 = MethodType         #479          //  (Lscala/util/Either;)Lscala/Tuple2;
  #481 = Utf8               (Lcoursier/core/Repository;)Lscala/Function1;
  #482 = NameAndType        #57:#481      // apply:(Lcoursier/core/Repository;)Lscala/Function1;
  #483 = InvokeDynamic      #9:#482       // #9:apply:(Lcoursier/core/Repository;)Lscala/Function1;
  #484 = Utf8               $anonfun$result$2
  #485 = Utf8               (Lcoursier/Versions;Lscala/collection/immutable/Seq;Lcoursier/core/Module;)Lscala/collection/immutable/Seq;
  #486 = Utf8               repositories$1
  #487 = Utf8               mod
  #488 = NameAndType        #459:#460     // $anonfun$result$3:(Lcoursier/Versions;Lcoursier/core/Module;Lcoursier/core/Repository;)Ljava/lang/Object;
  #489 = Methodref          #2.#488       // coursier/Versions.$anonfun$result$3:(Lcoursier/Versions;Lcoursier/core/Module;Lcoursier/core/Repository;)Ljava/lang/Object;
  #490 = MethodHandle       6:#489        // REF_invokeStatic coursier/Versions.$anonfun$result$3:(Lcoursier/Versions;Lcoursier/core/Module;Lcoursier/core/Repository;)Ljava/lang/Object;
  #491 = Utf8               (Lcoursier/core/Repository;)Ljava/lang/Object;
  #492 = MethodType         #491          //  (Lcoursier/core/Repository;)Ljava/lang/Object;
  #493 = Utf8               (Lcoursier/Versions;Lcoursier/core/Module;)Lscala/Function1;
  #494 = NameAndType        #57:#493      // apply:(Lcoursier/Versions;Lcoursier/core/Module;)Lscala/Function1;
  #495 = InvokeDynamic      #10:#494      // #10:apply:(Lcoursier/Versions;Lcoursier/core/Module;)Lscala/Function1;
  #496 = InterfaceMethodref #126.#205     // scala/collection/immutable/Seq.map:(Lscala/Function1;)Ljava/lang/Object;
  #497 = Utf8               scala/Option$
  #498 = Class              #497          // scala/Option$
  #499 = Utf8               Lscala/Option$;
  #500 = NameAndType        #62:#499      // MODULE$:Lscala/Option$;
  #501 = Fieldref           #498.#500     // scala/Option$.MODULE$:Lscala/Option$;
  #502 = Utf8               option2Iterable
  #503 = Utf8               (Lscala/Option;)Lscala/collection/Iterable;
  #504 = NameAndType        #502:#503     // option2Iterable:(Lscala/Option;)Lscala/collection/Iterable;
  #505 = Methodref          #498.#504     // scala/Option$.option2Iterable:(Lscala/Option;)Lscala/collection/Iterable;
  #506 = Utf8               scala/collection/Iterable
  #507 = Class              #506          // scala/collection/Iterable
  #508 = Utf8               toSeq
  #509 = NameAndType        #508:#102     // toSeq:()Lscala/collection/immutable/Seq;
  #510 = InterfaceMethodref #507.#509     // scala/collection/Iterable.toSeq:()Lscala/collection/immutable/Seq;
  #511 = NameAndType        #484:#485     // $anonfun$result$2:(Lcoursier/Versions;Lscala/collection/immutable/Seq;Lcoursier/core/Module;)Lscala/collection/immutable/Seq;
  #512 = Methodref          #2.#511       // coursier/Versions.$anonfun$result$2:(Lcoursier/Versions;Lscala/collection/immutable/Seq;Lcoursier/core/Module;)Lscala/collection/immutable/Seq;
  #513 = MethodHandle       6:#512        // REF_invokeStatic coursier/Versions.$anonfun$result$2:(Lcoursier/Versions;Lscala/collection/immutable/Seq;Lcoursier/core/Module;)Lscala/collection/immutable/Seq;
  #514 = Utf8               (Lcoursier/core/Module;)Lscala/collection/immutable/Seq;
  #515 = MethodType         #514          //  (Lcoursier/core/Module;)Lscala/collection/immutable/Seq;
  #516 = Utf8               (Lcoursier/Versions;Lscala/collection/immutable/Seq;)Lscala/Function1;
  #517 = NameAndType        #57:#516      // apply:(Lcoursier/Versions;Lscala/collection/immutable/Seq;)Lscala/Function1;
  #518 = InvokeDynamic      #11:#517      // #11:apply:(Lcoursier/Versions;Lscala/collection/immutable/Seq;)Lscala/Function1;
  #519 = Utf8               gather
  #520 = NameAndType        #519:#259     // gather:(Lscala/collection/immutable/Seq;)Ljava/lang/Object;
  #521 = InterfaceMethodref #247.#520     // coursier/util/Sync.gather:(Lscala/collection/immutable/Seq;)Ljava/lang/Object;
  #522 = Utf8               t$1
  #523 = Utf8               logger
  #524 = Utf8               using
  #525 = Utf8               ()Lcoursier/cache/CacheLogger$Using;
  #526 = NameAndType        #524:#525     // using:()Lcoursier/cache/CacheLogger$Using;
  #527 = InterfaceMethodref #23.#526      // coursier/cache/CacheLogger.using:()Lcoursier/cache/CacheLogger$Using;
  #528 = Utf8               (Ljava/lang/Object;Lcoursier/util/Sync;)Ljava/lang/Object;
  #529 = NameAndType        #57:#528      // apply:(Ljava/lang/Object;Lcoursier/util/Sync;)Ljava/lang/Object;
  #530 = Methodref          #21.#529      // coursier/cache/CacheLogger$Using.apply:(Ljava/lang/Object;Lcoursier/util/Sync;)Ljava/lang/Object;
  #531 = Utf8               Lcoursier/cache/CacheLogger;
  #532 = Utf8               l
  #533 = Utf8               Lcoursier/Versions$Result$;
  #534 = NameAndType        #62:#533      // MODULE$:Lcoursier/Versions$Result$;
  #535 = Fieldref           #18.#534      // coursier/Versions$Result$.MODULE$:Lcoursier/Versions$Result$;
  #536 = NameAndType        #57:#294      // apply:(Lscala/collection/immutable/Seq;)Lcoursier/Versions$Result;
  #537 = Methodref          #18.#536      // coursier/Versions$Result$.apply:(Lscala/collection/immutable/Seq;)Lcoursier/Versions$Result;
  #538 = Utf8               (Lcoursier/cache/Cache<TF;>;Lscala/Option<Lcoursier/core/Module;>;Lscala/collection/immutable/Seq<Lcoursier/core/Repository;>;Lscala/collection/immutable/Seq<Lcoursier/params/MirrorConfFile;>;Lscala/collection/immutable/Seq<Lcoursier/params/Mirror;>;Lcoursier/util/Sync<TF;>;)V
  #539 = Utf8               ()V
  #540 = NameAndType        #161:#539     // "<init>":()V
  #541 = Methodref          #5.#540       // java/lang/Object."<init>":()V
  #542 = Utf8               $init$
  #543 = Utf8               (Lscala/Product;)V
  #544 = NameAndType        #542:#543     // $init$:(Lscala/Product;)V
  #545 = InterfaceMethodref #7.#544       // scala/Product.$init$:(Lscala/Product;)V
  #546 = Utf8               (Lcoursier/cache/Cache;Lscala/Option;Lscala/collection/immutable/Seq;Lcoursier/util/Sync;)V
  #547 = Utf8               (Lcoursier/cache/Cache<TF;>;Lscala/Option<Lcoursier/core/Module;>;Lscala/collection/immutable/Seq<Lcoursier/core/Repository;>;Lcoursier/util/Sync<TF;>;)V
  #548 = Utf8               coursier/Resolve$
  #549 = Class              #548          // coursier/Resolve$
  #550 = Utf8               Lcoursier/Resolve$;
  #551 = NameAndType        #62:#550      // MODULE$:Lcoursier/Resolve$;
  #552 = Fieldref           #549.#551     // coursier/Resolve$.MODULE$:Lcoursier/Resolve$;
  #553 = Utf8               defaultMirrorConfFiles
  #554 = NameAndType        #553:#102     // defaultMirrorConfFiles:()Lscala/collection/immutable/Seq;
  #555 = Methodref          #549.#554     // coursier/Resolve$.defaultMirrorConfFiles:()Lscala/collection/immutable/Seq;
  #556 = Utf8               (Lcoursier/cache/Cache;Lcoursier/util/Sync;)V
  #557 = Utf8               (Lcoursier/cache/Cache<TF;>;Lcoursier/util/Sync<TF;>;)V
  #558 = Utf8               scala/None$
  #559 = Class              #558          // scala/None$
  #560 = Utf8               Lscala/None$;
  #561 = NameAndType        #62:#560      // MODULE$:Lscala/None$;
  #562 = Fieldref           #559.#561     // scala/None$.MODULE$:Lscala/None$;
  #563 = Utf8               defaultRepositories
  #564 = NameAndType        #563:#102     // defaultRepositories:()Lscala/collection/immutable/Seq;
  #565 = Methodref          #549.#564     // coursier/Resolve$.defaultRepositories:()Lscala/collection/immutable/Seq;
  #566 = Utf8               $deserializeLambda$
  #567 = Utf8               (Ljava/lang/invoke/SerializedLambda;)Ljava/lang/Object;
  #568 = Utf8               scala/runtime/LambdaDeserialize
  #569 = Class              #568          // scala/runtime/LambdaDeserialize
  #570 = Utf8               bootstrap
  #571 = Utf8               (Ljava/lang/invoke/MethodHandles$Lookup;Ljava/lang/String;Ljava/lang/invoke/MethodType;[Ljava/lang/invoke/MethodHandle;)Ljava/lang/invoke/CallSite;
  #572 = NameAndType        #570:#571     // bootstrap:(Ljava/lang/invoke/MethodHandles$Lookup;Ljava/lang/String;Ljava/lang/invoke/MethodType;[Ljava/lang/invoke/MethodHandle;)Ljava/lang/invoke/CallSite;
  #573 = Methodref          #569.#572     // scala/runtime/LambdaDeserialize.bootstrap:(Ljava/lang/invoke/MethodHandles$Lookup;Ljava/lang/String;Ljava/lang/invoke/MethodType;[Ljava/lang/invoke/MethodHandle;)Ljava/lang/invoke/CallSite;
  #574 = MethodHandle       6:#573        // REF_invokeStatic scala/runtime/LambdaDeserialize.bootstrap:(Ljava/lang/invoke/MethodHandles$Lookup;Ljava/lang/String;Ljava/lang/invoke/MethodType;[Ljava/lang/invoke/MethodHandle;)Ljava/lang/invoke/CallSite;
  #575 = Utf8               lambdaDeserialize
  #576 = NameAndType        #575:#567     // lambdaDeserialize:(Ljava/lang/invoke/SerializedLambda;)Ljava/lang/Object;
  #577 = InvokeDynamic      #12:#576      // #12:lambdaDeserialize:(Ljava/lang/invoke/SerializedLambda;)Ljava/lang/Object;
  #578 = Utf8               Signature
  #579 = Utf8               Code
  #580 = Utf8               MethodParameters
  #581 = Utf8               LineNumberTable
  #582 = Utf8               LocalVariableTable
  #583 = Utf8               StackMapTable
  #584 = Utf8               InnerClasses
  #585 = Utf8               SourceFile
  #586 = Utf8               RuntimeVisibleAnnotations
  #587 = Utf8               BootstrapMethods
  #588 = Utf8               ScalaInlineInfo
  #589 = Utf8               ScalaSig
{
  private final coursier.cache.Cache<F> cache;
    descriptor: Lcoursier/cache/Cache;
    flags: (0x0012) ACC_PRIVATE, ACC_FINAL
    Signature: #43                          // Lcoursier/cache/Cache<TF;>;

  private final scala.Option<coursier.core.Module> moduleOpt;
    descriptor: Lscala/Option;
    flags: (0x0012) ACC_PRIVATE, ACC_FINAL
    Signature: #46                          // Lscala/Option<Lcoursier/core/Module;>;

  private final scala.collection.immutable.Seq<coursier.core.Repository> repositories;
    descriptor: Lscala/collection/immutable/Seq;
    flags: (0x0012) ACC_PRIVATE, ACC_FINAL
    Signature: #49                          // Lscala/collection/immutable/Seq<Lcoursier/core/Repository;>;

  private final scala.collection.immutable.Seq<coursier.params.MirrorConfFile> mirrorConfFiles;
    descriptor: Lscala/collection/immutable/Seq;
    flags: (0x0012) ACC_PRIVATE, ACC_FINAL
    Signature: #51                          // Lscala/collection/immutable/Seq<Lcoursier/params/MirrorConfFile;>;

  private final scala.collection.immutable.Seq<coursier.params.Mirror> mirrors;
    descriptor: Lscala/collection/immutable/Seq;
    flags: (0x0012) ACC_PRIVATE, ACC_FINAL
    Signature: #53                          // Lscala/collection/immutable/Seq<Lcoursier/params/Mirror;>;

  private final coursier.util.Sync<F> sync;
    descriptor: Lcoursier/util/Sync;
    flags: (0x0012) ACC_PRIVATE, ACC_FINAL
    Signature: #56                          // Lcoursier/util/Sync<TF;>;

  public static <F extends java.lang.Object> coursier.Versions<F> apply(coursier.cache.Cache<F>, scala.Option<coursier.core.Module>, scala.collection.immutable.Seq<coursier.core.Repository>, scala.collection.immutable.Seq<coursier.params.MirrorConfFile>, scala.collection.immutable.Seq<coursier.params.Mirror>, coursier.util.Sync<F>);
    descriptor: (Lcoursier/cache/Cache;Lscala/Option;Lscala/collection/immutable/Seq;Lscala/collection/immutable/Seq;Lscala/collection/immutable/Seq;Lcoursier/util/Sync;)Lcoursier/Versions;
    flags: (0x0009) ACC_PUBLIC, ACC_STATIC
    Code:
      stack=7, locals=6, args_size=6
         0: getstatic     #65                 // Field coursier/Versions$.MODULE$:Lcoursier/Versions$;
         3: aload_0
         4: aload_1
         5: aload_2
         6: aload_3
         7: aload         4
         9: aload         5
        11: invokevirtual #67                 // Method coursier/Versions$.apply:(Lcoursier/cache/Cache;Lscala/Option;Lscala/collection/immutable/Seq;Lscala/collection/immutable/Seq;Lscala/collection/immutable/Seq;Lcoursier/util/Sync;)Lcoursier/Versions;
        14: areturn
    Signature: #59                          // <F:Ljava/lang/Object;>(Lcoursier/cache/Cache<TF;>;Lscala/Option<Lcoursier/core/Module;>;Lscala/collection/immutable/Seq<Lcoursier/core/Repository;>;Lscala/collection/immutable/Seq<Lcoursier/params/MirrorConfFile;>;Lscala/collection/immutable/Seq<Lcoursier/params/Mirror;>;Lcoursier/util/Sync<TF;>;)Lcoursier/Versions<TF;>;
    MethodParameters:
      Name                           Flags
      cache                          final
      moduleOpt                      final
      repositories                   final
      mirrorConfFiles                final
      mirrors                        final
      sync                           final

  public static <F extends java.lang.Object> coursier.Versions<F> apply(coursier.cache.Cache<F>, scala.Option<coursier.core.Module>, scala.collection.immutable.Seq<coursier.core.Repository>, coursier.util.Sync<F>);
    descriptor: (Lcoursier/cache/Cache;Lscala/Option;Lscala/collection/immutable/Seq;Lcoursier/util/Sync;)Lcoursier/Versions;
    flags: (0x0009) ACC_PUBLIC, ACC_STATIC
    Code:
      stack=5, locals=4, args_size=4
         0: getstatic     #65                 // Field coursier/Versions$.MODULE$:Lcoursier/Versions$;
         3: aload_0
         4: aload_1
         5: aload_2
         6: aload_3
         7: invokevirtual #71                 // Method coursier/Versions$.apply:(Lcoursier/cache/Cache;Lscala/Option;Lscala/collection/immutable/Seq;Lcoursier/util/Sync;)Lcoursier/Versions;
        10: areturn
    Signature: #69                          // <F:Ljava/lang/Object;>(Lcoursier/cache/Cache<TF;>;Lscala/Option<Lcoursier/core/Module;>;Lscala/collection/immutable/Seq<Lcoursier/core/Repository;>;Lcoursier/util/Sync<TF;>;)Lcoursier/Versions<TF;>;
    MethodParameters:
      Name                           Flags
      cache                          final
      moduleOpt                      final
      repositories                   final
      sync                           final

  public static <F extends java.lang.Object> coursier.Versions<F> apply(coursier.cache.Cache<F>, coursier.util.Sync<F>);
    descriptor: (Lcoursier/cache/Cache;Lcoursier/util/Sync;)Lcoursier/Versions;
    flags: (0x0009) ACC_PUBLIC, ACC_STATIC
    Code:
      stack=3, locals=2, args_size=2
         0: getstatic     #65                 // Field coursier/Versions$.MODULE$:Lcoursier/Versions$;
         3: aload_0
         4: aload_1
         5: invokevirtual #75                 // Method coursier/Versions$.apply:(Lcoursier/cache/Cache;Lcoursier/util/Sync;)Lcoursier/Versions;
         8: areturn
    Signature: #73                          // <F:Ljava/lang/Object;>(Lcoursier/cache/Cache<TF;>;Lcoursier/util/Sync<TF;>;)Lcoursier/Versions<TF;>;
    MethodParameters:
      Name                           Flags
      cache                          final
      sync                           final

  public static coursier.Versions<coursier.util.Task> apply();
    descriptor: ()Lcoursier/Versions;
    flags: (0x0009) ACC_PUBLIC, ACC_STATIC
    Code:
      stack=1, locals=0, args_size=0
         0: getstatic     #65                 // Field coursier/Versions$.MODULE$:Lcoursier/Versions$;
         3: invokevirtual #79                 // Method coursier/Versions$.apply:()Lcoursier/Versions;
         6: areturn
    Signature: #77                          // ()Lcoursier/Versions<Lcoursier/util/Task;>;

  public scala.collection.Iterator<java.lang.Object> productIterator();
    descriptor: ()Lscala/collection/Iterator;
    flags: (0x0001) ACC_PUBLIC
    Code:
      stack=1, locals=1, args_size=1
         0: aload_0
         1: invokestatic  #86                 // InterfaceMethod scala/Product.productIterator$:(Lscala/Product;)Lscala/collection/Iterator;
         4: areturn
      LineNumberTable:
        line 10: 0
      LocalVariableTable:
        Start  Length  Slot  Name   Signature
            0       5     0  this   Lcoursier/Versions;
    Signature: #82                          // ()Lscala/collection/Iterator<Ljava/lang/Object;>;

  public scala.collection.Iterator<java.lang.String> productElementNames();
    descriptor: ()Lscala/collection/Iterator;
    flags: (0x0001) ACC_PUBLIC
    Code:
      stack=1, locals=1, args_size=1
         0: aload_0
         1: invokestatic  #93                 // InterfaceMethod scala/Product.productElementNames$:(Lscala/Product;)Lscala/collection/Iterator;
         4: areturn
      LineNumberTable:
        line 10: 0
      LocalVariableTable:
        Start  Length  Slot  Name   Signature
            0       5     0  this   Lcoursier/Versions;
    Signature: #90                          // ()Lscala/collection/Iterator<Ljava/lang/String;>;

  public coursier.cache.Cache<F> cache();
    descriptor: ()Lcoursier/cache/Cache;
    flags: (0x0001) ACC_PUBLIC
    Code:
      stack=1, locals=1, args_size=1
         0: aload_0
         1: getfield      #97                 // Field cache:Lcoursier/cache/Cache;
         4: areturn
      LineNumberTable:
        line 10: 0
      LocalVariableTable:
        Start  Length  Slot  Name   Signature
            0       5     0  this   Lcoursier/Versions;
    Signature: #95                          // ()Lcoursier/cache/Cache<TF;>;

  public scala.Option<coursier.core.Module> moduleOpt();
    descriptor: ()Lscala/Option;
    flags: (0x0001) ACC_PUBLIC
    Code:
      stack=1, locals=1, args_size=1
         0: aload_0
         1: getfield      #101                // Field moduleOpt:Lscala/Option;
         4: areturn
      LineNumberTable:
        line 10: 0
      LocalVariableTable:
        Start  Length  Slot  Name   Signature
            0       5     0  this   Lcoursier/Versions;
    Signature: #99                          // ()Lscala/Option<Lcoursier/core/Module;>;

  public scala.collection.immutable.Seq<coursier.core.Repository> repositories();
    descriptor: ()Lscala/collection/immutable/Seq;
    flags: (0x0001) ACC_PUBLIC
    Code:
      stack=1, locals=1, args_size=1
         0: aload_0
         1: getfield      #105                // Field repositories:Lscala/collection/immutable/Seq;
         4: areturn
      LineNumberTable:
        line 10: 0
      LocalVariableTable:
        Start  Length  Slot  Name   Signature
            0       5     0  this   Lcoursier/Versions;
    Signature: #103                         // ()Lscala/collection/immutable/Seq<Lcoursier/core/Repository;>;

  public scala.collection.immutable.Seq<coursier.params.MirrorConfFile> mirrorConfFiles();
    descriptor: ()Lscala/collection/immutable/Seq;
    flags: (0x0001) ACC_PUBLIC
    Code:
      stack=1, locals=1, args_size=1
         0: aload_0
         1: getfield      #108                // Field mirrorConfFiles:Lscala/collection/immutable/Seq;
         4: areturn
      LineNumberTable:
        line 10: 0
      LocalVariableTable:
        Start  Length  Slot  Name   Signature
            0       5     0  this   Lcoursier/Versions;
    Signature: #106                         // ()Lscala/collection/immutable/Seq<Lcoursier/params/MirrorConfFile;>;

  public scala.collection.immutable.Seq<coursier.params.Mirror> mirrors();
    descriptor: ()Lscala/collection/immutable/Seq;
    flags: (0x0001) ACC_PUBLIC
    Code:
      stack=1, locals=1, args_size=1
         0: aload_0
         1: getfield      #111                // Field mirrors:Lscala/collection/immutable/Seq;
         4: areturn
      LineNumberTable:
        line 10: 0
      LocalVariableTable:
        Start  Length  Slot  Name   Signature
            0       5     0  this   Lcoursier/Versions;
    Signature: #109                         // ()Lscala/collection/immutable/Seq<Lcoursier/params/Mirror;>;

  public coursier.util.Sync<F> sync();
    descriptor: ()Lcoursier/util/Sync;
    flags: (0x0001) ACC_PUBLIC
    Code:
      stack=1, locals=1, args_size=1
         0: aload_0
         1: getfield      #115                // Field sync:Lcoursier/util/Sync;
         4: areturn
      LineNumberTable:
        line 10: 0
      LocalVariableTable:
        Start  Length  Slot  Name   Signature
            0       5     0  this   Lcoursier/Versions;
    Signature: #113                         // ()Lcoursier/util/Sync<TF;>;

  private coursier.util.Sync<F> F();
    descriptor: ()Lcoursier/util/Sync;
    flags: (0x0002) ACC_PRIVATE
    Code:
      stack=1, locals=1, args_size=1
         0: aload_0
         1: invokevirtual #118                // Method sync:()Lcoursier/util/Sync;
         4: areturn
      LineNumberTable:
        line 21: 0
      LocalVariableTable:
        Start  Length  Slot  Name   Signature
            0       5     0  this   Lcoursier/Versions;
    Signature: #113                         // ()Lcoursier/util/Sync<TF;>;

  public coursier.Versions<F> addRepositories(scala.collection.immutable.Seq<coursier.core.Repository>);
    descriptor: (Lscala/collection/immutable/Seq;)Lcoursier/Versions;
    flags: (0x0001) ACC_PUBLIC
    Code:
      stack=3, locals=2, args_size=2
         0: aload_0
         1: aload_0
         2: invokevirtual #124                // Method repositories:()Lscala/collection/immutable/Seq;
         5: aload_1
         6: invokeinterface #130,  2          // InterfaceMethod scala/collection/immutable/Seq.$plus$plus:(Lscala/collection/IterableOnce;)Ljava/lang/Object;
        11: checkcast     #126                // class scala/collection/immutable/Seq
        14: invokevirtual #133                // Method withRepositories:(Lscala/collection/immutable/Seq;)Lcoursier/Versions;
        17: areturn
      LineNumberTable:
        line 24: 0
      LocalVariableTable:
        Start  Length  Slot  Name   Signature
            0      18     0  this   Lcoursier/Versions;
            0      18     1 repository   Lscala/collection/immutable/Seq;
    Signature: #121                         // (Lscala/collection/immutable/Seq<Lcoursier/core/Repository;>;)Lcoursier/Versions<TF;>;
    MethodParameters:
      Name                           Flags
      repository                     final

  public coursier.Versions<F> noMirrors();
    descriptor: ()Lcoursier/Versions;
    flags: (0x0001) ACC_PUBLIC
    Code:
      stack=2, locals=1, args_size=1
         0: aload_0
         1: getstatic     #140                // Field scala/collection/immutable/Nil$.MODULE$:Lscala/collection/immutable/Nil$;
         4: invokevirtual #143                // Method withMirrors:(Lscala/collection/immutable/Seq;)Lcoursier/Versions;
         7: getstatic     #140                // Field scala/collection/immutable/Nil$.MODULE$:Lscala/collection/immutable/Nil$;
        10: invokevirtual #146                // Method withMirrorConfFiles:(Lscala/collection/immutable/Seq;)Lcoursier/Versions;
        13: areturn
      LineNumberTable:
        line 27: 0
      LocalVariableTable:
        Start  Length  Slot  Name   Signature
            0      14     0  this   Lcoursier/Versions;
    Signature: #135                         // ()Lcoursier/Versions<TF;>;

  public coursier.Versions<F> addMirrors(scala.collection.immutable.Seq<coursier.params.Mirror>);
    descriptor: (Lscala/collection/immutable/Seq;)Lcoursier/Versions;
    flags: (0x0001) ACC_PUBLIC
    Code:
      stack=3, locals=2, args_size=2
         0: aload_0
         1: aload_0
         2: invokevirtual #150                // Method mirrors:()Lscala/collection/immutable/Seq;
         5: aload_1
         6: invokeinterface #130,  2          // InterfaceMethod scala/collection/immutable/Seq.$plus$plus:(Lscala/collection/IterableOnce;)Ljava/lang/Object;
        11: checkcast     #126                // class scala/collection/immutable/Seq
        14: invokevirtual #143                // Method withMirrors:(Lscala/collection/immutable/Seq;)Lcoursier/Versions;
        17: areturn
      LineNumberTable:
        line 30: 0
      LocalVariableTable:
        Start  Length  Slot  Name   Signature
            0      18     0  this   Lcoursier/Versions;
            0      18     1 mirrors   Lscala/collection/immutable/Seq;
    Signature: #148                         // (Lscala/collection/immutable/Seq<Lcoursier/params/Mirror;>;)Lcoursier/Versions<TF;>;
    MethodParameters:
      Name                           Flags
      mirrors                        final

  public coursier.Versions<F> addMirrorConfFiles(scala.collection.immutable.Seq<coursier.params.MirrorConfFile>);
    descriptor: (Lscala/collection/immutable/Seq;)Lcoursier/Versions;
    flags: (0x0001) ACC_PUBLIC
    Code:
      stack=3, locals=2, args_size=2
         0: aload_0
         1: aload_0
         2: invokevirtual #154                // Method mirrorConfFiles:()Lscala/collection/immutable/Seq;
         5: aload_1
         6: invokeinterface #130,  2          // InterfaceMethod scala/collection/immutable/Seq.$plus$plus:(Lscala/collection/IterableOnce;)Ljava/lang/Object;
        11: checkcast     #126                // class scala/collection/immutable/Seq
        14: invokevirtual #146                // Method withMirrorConfFiles:(Lscala/collection/immutable/Seq;)Lcoursier/Versions;
        17: areturn
      LineNumberTable:
        line 33: 0
      LocalVariableTable:
        Start  Length  Slot  Name   Signature
            0      18     0  this   Lcoursier/Versions;
            0      18     1 mirrorConfFiles   Lscala/collection/immutable/Seq;
    Signature: #152                         // (Lscala/collection/immutable/Seq<Lcoursier/params/MirrorConfFile;>;)Lcoursier/Versions<TF;>;
    MethodParameters:
      Name                           Flags
      mirrorConfFiles                final

  public coursier.Versions<F> withModule(coursier.core.Module);
    descriptor: (Lcoursier/core/Module;)Lcoursier/Versions;
    flags: (0x0001) ACC_PUBLIC
    Code:
      stack=4, locals=2, args_size=2
         0: aload_0
         1: new           #160                // class scala/Some
         4: dup
         5: aload_1
         6: invokespecial #164                // Method scala/Some."<init>":(Ljava/lang/Object;)V
         9: invokevirtual #168                // Method withModuleOpt:(Lscala/Option;)Lcoursier/Versions;
        12: areturn
      LineNumberTable:
        line 36: 0
      LocalVariableTable:
        Start  Length  Slot  Name   Signature
            0      13     0  this   Lcoursier/Versions;
            0      13     1 module   Lcoursier/core/Module;
    Signature: #157                         // (Lcoursier/core/Module;)Lcoursier/Versions<TF;>;
    MethodParameters:
      Name                           Flags
      module                         final

  public F versions();
    descriptor: ()Ljava/lang/Object;
    flags: (0x0001) ACC_PUBLIC
    Code:
      stack=3, locals=1, args_size=1
         0: getstatic     #175                // Field coursier/util/Monad$ops$.MODULE$:Lcoursier/util/Monad$ops$;
         3: aload_0
         4: invokevirtual #178                // Method result:()Ljava/lang/Object;
         7: aload_0
         8: invokevirtual #118                // Method sync:()Lcoursier/util/Sync;
        11: invokevirtual #182                // Method coursier/util/Monad$ops$.toAllMonadOps:(Ljava/lang/Object;Lcoursier/util/Monad;)Lcoursier/util/Monad$AllOps;
        14: invokedynamic #202,  0            // InvokeDynamic #0:apply:()Lscala/Function1;
        19: invokeinterface #206,  2          // InterfaceMethod coursier/util/Monad$AllOps.map:(Lscala/Function1;)Ljava/lang/Object;
        24: areturn
      LineNumberTable:
        line 39: 0
      LocalVariableTable:
        Start  Length  Slot  Name   Signature
            0      25     0  this   Lcoursier/Versions;
    Signature: #172                         // ()TF;

  public F finalRepositories();
    descriptor: ()Ljava/lang/Object;
    flags: (0x0001) ACC_PUBLIC
    Code:
      stack=3, locals=1, args_size=1
         0: getstatic     #175                // Field coursier/util/Monad$ops$.MODULE$:Lcoursier/util/Monad$ops$;
         3: aload_0
         4: invokevirtual #210                // Method allMirrors:()Ljava/lang/Object;
         7: aload_0
         8: invokevirtual #118                // Method sync:()Lcoursier/util/Sync;
        11: invokevirtual #182                // Method coursier/util/Monad$ops$.toAllMonadOps:(Ljava/lang/Object;Lcoursier/util/Monad;)Lcoursier/util/Monad$AllOps;
        14: aload_0
        15: invokedynamic #220,  0            // InvokeDynamic #1:apply:(Lcoursier/Versions;)Lscala/Function1;
        20: invokeinterface #206,  2          // InterfaceMethod coursier/util/Monad$AllOps.map:(Lscala/Function1;)Ljava/lang/Object;
        25: areturn
      LineNumberTable:
        line 42: 0
      LocalVariableTable:
        Start  Length  Slot  Name   Signature
            0      26     0  this   Lcoursier/Versions;
    Signature: #172                         // ()TF;

  private scala.collection.immutable.Seq<coursier.params.Mirror> allMirrors0();
    descriptor: ()Lscala/collection/immutable/Seq;
    flags: (0x0002) ACC_PRIVATE
    Code:
      stack=3, locals=1, args_size=1
         0: aload_0
         1: invokevirtual #150                // Method mirrors:()Lscala/collection/immutable/Seq;
         4: aload_0
         5: invokevirtual #154                // Method mirrorConfFiles:()Lscala/collection/immutable/Seq;
         8: invokedynamic #228,  0            // InvokeDynamic #2:apply:()Lscala/Function1;
        13: invokeinterface #231,  2          // InterfaceMethod scala/collection/immutable/Seq.flatMap:(Lscala/Function1;)Ljava/lang/Object;
        18: checkcast     #233                // class scala/collection/IterableOnce
        21: invokeinterface #130,  2          // InterfaceMethod scala/collection/immutable/Seq.$plus$plus:(Lscala/collection/IterableOnce;)Ljava/lang/Object;
        26: checkcast     #126                // class scala/collection/immutable/Seq
        29: areturn
      LineNumberTable:
        line 45: 0
      LocalVariableTable:
        Start  Length  Slot  Name   Signature
            0      30     0  this   Lcoursier/Versions;
    Signature: #109                         // ()Lscala/collection/immutable/Seq<Lcoursier/params/Mirror;>;

  public F allMirrors();
    descriptor: ()Ljava/lang/Object;
    flags: (0x0001) ACC_PUBLIC
    Code:
      stack=2, locals=1, args_size=1
         0: aload_0
         1: invokespecial #235                // Method F:()Lcoursier/util/Sync;
         4: aload_0
         5: invokedynamic #245,  0            // InvokeDynamic #3:apply:(Lcoursier/Versions;)Lscala/Function0;
        10: invokeinterface #251,  2          // InterfaceMethod coursier/util/Sync.delay:(Lscala/Function0;)Ljava/lang/Object;
        15: areturn
      LineNumberTable:
        line 48: 0
      LocalVariableTable:
        Start  Length  Slot  Name   Signature
            0      16     0  this   Lcoursier/Versions;
    Signature: #172                         // ()TF;

  public F result();
    descriptor: ()Ljava/lang/Object;
    flags: (0x0001) ACC_PUBLIC
    Code:
      stack=4, locals=3, args_size=1
         0: getstatic     #175                // Field coursier/util/Monad$ops$.MODULE$:Lcoursier/util/Monad$ops$;
         3: aload_0
         4: invokevirtual #253                // Method finalRepositories:()Ljava/lang/Object;
         7: aload_0
         8: invokevirtual #118                // Method sync:()Lcoursier/util/Sync;
        11: invokevirtual #182                // Method coursier/util/Monad$ops$.toAllMonadOps:(Ljava/lang/Object;Lcoursier/util/Monad;)Lcoursier/util/Monad$AllOps;
        14: aload_0
        15: invokedynamic #261,  0            // InvokeDynamic #4:apply:(Lcoursier/Versions;)Lscala/Function1;
        20: invokeinterface #262,  2          // InterfaceMethod coursier/util/Monad$AllOps.flatMap:(Lscala/Function1;)Ljava/lang/Object;
        25: astore_1
        26: aload_0
        27: invokevirtual #264                // Method cache:()Lcoursier/cache/Cache;
        30: invokevirtual #269                // Method coursier/cache/Cache.loggerOpt:()Lscala/Option;
        33: aload_1
        34: invokedynamic #276,  0            // InvokeDynamic #5:apply:(Ljava/lang/Object;)Lscala/Function0;
        39: aload_0
        40: aload_1
        41: invokedynamic #286,  0            // InvokeDynamic #6:apply:(Lcoursier/Versions;Ljava/lang/Object;)Lscala/Function1;
        46: invokevirtual #292                // Method scala/Option.fold:(Lscala/Function0;Lscala/Function1;)Ljava/lang/Object;
        49: astore_2
        50: getstatic     #175                // Field coursier/util/Monad$ops$.MODULE$:Lcoursier/util/Monad$ops$;
        53: aload_2
        54: aload_0
        55: invokevirtual #118                // Method sync:()Lcoursier/util/Sync;
        58: invokevirtual #182                // Method coursier/util/Monad$ops$.toAllMonadOps:(Ljava/lang/Object;Lcoursier/util/Monad;)Lcoursier/util/Monad$AllOps;
        61: invokedynamic #299,  0            // InvokeDynamic #7:apply:()Lscala/Function1;
        66: invokeinterface #206,  2          // InterfaceMethod coursier/util/Monad$AllOps.map:(Lscala/Function1;)Ljava/lang/Object;
        71: areturn
      LineNumberTable:
        line 53: 0
        line 64: 26
        line 68: 50
      LocalVariableTable:
        Start  Length  Slot  Name   Signature
           26      45     1     t   Ljava/lang/Object;
           50      21     2    t0   Ljava/lang/Object;
            0      72     0  this   Lcoursier/Versions;
    Signature: #172                         // ()TF;

  public coursier.Versions<F> withCache(coursier.cache.Cache<F>);
    descriptor: (Lcoursier/cache/Cache;)Lcoursier/Versions;
    flags: (0x0001) ACC_PUBLIC
    Code:
      stack=8, locals=2, args_size=2
         0: new           #2                  // class coursier/Versions
         3: dup
         4: aload_1
         5: aload_0
         6: invokevirtual #307                // Method moduleOpt:()Lscala/Option;
         9: aload_0
        10: invokevirtual #124                // Method repositories:()Lscala/collection/immutable/Seq;
        13: aload_0
        14: invokevirtual #154                // Method mirrorConfFiles:()Lscala/collection/immutable/Seq;
        17: aload_0
        18: invokevirtual #150                // Method mirrors:()Lscala/collection/immutable/Seq;
        21: aload_0
        22: invokevirtual #118                // Method sync:()Lcoursier/util/Sync;
        25: invokespecial #310                // Method "<init>":(Lcoursier/cache/Cache;Lscala/Option;Lscala/collection/immutable/Seq;Lscala/collection/immutable/Seq;Lscala/collection/immutable/Seq;Lcoursier/util/Sync;)V
        28: areturn
      LineNumberTable:
        line 10: 0
      LocalVariableTable:
        Start  Length  Slot  Name   Signature
            0      29     0  this   Lcoursier/Versions;
            0      29     1 cache   Lcoursier/cache/Cache;
    Signature: #305                         // (Lcoursier/cache/Cache<TF;>;)Lcoursier/Versions<TF;>;
    MethodParameters:
      Name                           Flags
      cache                          final

  public coursier.Versions<F> withModuleOpt(scala.Option<coursier.core.Module>);
    descriptor: (Lscala/Option;)Lcoursier/Versions;
    flags: (0x0001) ACC_PUBLIC
    Code:
      stack=8, locals=2, args_size=2
         0: new           #2                  // class coursier/Versions
         3: dup
         4: aload_0
         5: invokevirtual #264                // Method cache:()Lcoursier/cache/Cache;
         8: aload_1
         9: aload_0
        10: invokevirtual #124                // Method repositories:()Lscala/collection/immutable/Seq;
        13: aload_0
        14: invokevirtual #154                // Method mirrorConfFiles:()Lscala/collection/immutable/Seq;
        17: aload_0
        18: invokevirtual #150                // Method mirrors:()Lscala/collection/immutable/Seq;
        21: aload_0
        22: invokevirtual #118                // Method sync:()Lcoursier/util/Sync;
        25: invokespecial #310                // Method "<init>":(Lcoursier/cache/Cache;Lscala/Option;Lscala/collection/immutable/Seq;Lscala/collection/immutable/Seq;Lscala/collection/immutable/Seq;Lcoursier/util/Sync;)V
        28: areturn
      LineNumberTable:
        line 10: 0
      LocalVariableTable:
        Start  Length  Slot  Name   Signature
            0      29     0  this   Lcoursier/Versions;
            0      29     1 moduleOpt   Lscala/Option;
    Signature: #311                         // (Lscala/Option<Lcoursier/core/Module;>;)Lcoursier/Versions<TF;>;
    MethodParameters:
      Name                           Flags
      moduleOpt                      final

  public coursier.Versions<F> withRepositories(scala.collection.immutable.Seq<coursier.core.Repository>);
    descriptor: (Lscala/collection/immutable/Seq;)Lcoursier/Versions;
    flags: (0x0001) ACC_PUBLIC
    Code:
      stack=8, locals=2, args_size=2
         0: new           #2                  // class coursier/Versions
         3: dup
         4: aload_0
         5: invokevirtual #264                // Method cache:()Lcoursier/cache/Cache;
         8: aload_0
         9: invokevirtual #307                // Method moduleOpt:()Lscala/Option;
        12: aload_1
        13: aload_0
        14: invokevirtual #154                // Method mirrorConfFiles:()Lscala/collection/immutable/Seq;
        17: aload_0
        18: invokevirtual #150                // Method mirrors:()Lscala/collection/immutable/Seq;
        21: aload_0
        22: invokevirtual #118                // Method sync:()Lcoursier/util/Sync;
        25: invokespecial #310                // Method "<init>":(Lcoursier/cache/Cache;Lscala/Option;Lscala/collection/immutable/Seq;Lscala/collection/immutable/Seq;Lscala/collection/immutable/Seq;Lcoursier/util/Sync;)V
        28: areturn
      LineNumberTable:
        line 10: 0
      LocalVariableTable:
        Start  Length  Slot  Name   Signature
            0      29     0  this   Lcoursier/Versions;
            0      29     1 repositories   Lscala/collection/immutable/Seq;
    Signature: #121                         // (Lscala/collection/immutable/Seq<Lcoursier/core/Repository;>;)Lcoursier/Versions<TF;>;
    MethodParameters:
      Name                           Flags
      repositories                   final

  public coursier.Versions<F> withMirrorConfFiles(scala.collection.immutable.Seq<coursier.params.MirrorConfFile>);
    descriptor: (Lscala/collection/immutable/Seq;)Lcoursier/Versions;
    flags: (0x0001) ACC_PUBLIC
    Code:
      stack=8, locals=2, args_size=2
         0: new           #2                  // class coursier/Versions
         3: dup
         4: aload_0
         5: invokevirtual #264                // Method cache:()Lcoursier/cache/Cache;
         8: aload_0
         9: invokevirtual #307                // Method moduleOpt:()Lscala/Option;
        12: aload_0
        13: invokevirtual #124                // Method repositories:()Lscala/collection/immutable/Seq;
        16: aload_1
        17: aload_0
        18: invokevirtual #150                // Method mirrors:()Lscala/collection/immutable/Seq;
        21: aload_0
        22: invokevirtual #118                // Method sync:()Lcoursier/util/Sync;
        25: invokespecial #310                // Method "<init>":(Lcoursier/cache/Cache;Lscala/Option;Lscala/collection/immutable/Seq;Lscala/collection/immutable/Seq;Lscala/collection/immutable/Seq;Lcoursier/util/Sync;)V
        28: areturn
      LineNumberTable:
        line 10: 0
      LocalVariableTable:
        Start  Length  Slot  Name   Signature
            0      29     0  this   Lcoursier/Versions;
            0      29     1 mirrorConfFiles   Lscala/collection/immutable/Seq;
    Signature: #152                         // (Lscala/collection/immutable/Seq<Lcoursier/params/MirrorConfFile;>;)Lcoursier/Versions<TF;>;
    MethodParameters:
      Name                           Flags
      mirrorConfFiles                final

  public coursier.Versions<F> withMirrors(scala.collection.immutable.Seq<coursier.params.Mirror>);
    descriptor: (Lscala/collection/immutable/Seq;)Lcoursier/Versions;
    flags: (0x0001) ACC_PUBLIC
    Code:
      stack=8, locals=2, args_size=2
         0: new           #2                  // class coursier/Versions
         3: dup
         4: aload_0
         5: invokevirtual #264                // Method cache:()Lcoursier/cache/Cache;
         8: aload_0
         9: invokevirtual #307                // Method moduleOpt:()Lscala/Option;
        12: aload_0
        13: invokevirtual #124                // Method repositories:()Lscala/collection/immutable/Seq;
        16: aload_0
        17: invokevirtual #154                // Method mirrorConfFiles:()Lscala/collection/immutable/Seq;
        20: aload_1
        21: aload_0
        22: invokevirtual #118                // Method sync:()Lcoursier/util/Sync;
        25: invokespecial #310                // Method "<init>":(Lcoursier/cache/Cache;Lscala/Option;Lscala/collection/immutable/Seq;Lscala/collection/immutable/Seq;Lscala/collection/immutable/Seq;Lcoursier/util/Sync;)V
        28: areturn
      LineNumberTable:
        line 10: 0
      LocalVariableTable:
        Start  Length  Slot  Name   Signature
            0      29     0  this   Lcoursier/Versions;
            0      29     1 mirrors   Lscala/collection/immutable/Seq;
    Signature: #148                         // (Lscala/collection/immutable/Seq<Lcoursier/params/Mirror;>;)Lcoursier/Versions<TF;>;
    MethodParameters:
      Name                           Flags
      mirrors                        final

  public coursier.Versions<F> withSync(coursier.util.Sync<F>);
    descriptor: (Lcoursier/util/Sync;)Lcoursier/Versions;
    flags: (0x0001) ACC_PUBLIC
    Code:
      stack=8, locals=2, args_size=2
         0: new           #2                  // class coursier/Versions
         3: dup
         4: aload_0
         5: invokevirtual #264                // Method cache:()Lcoursier/cache/Cache;
         8: aload_0
         9: invokevirtual #307                // Method moduleOpt:()Lscala/Option;
        12: aload_0
        13: invokevirtual #124                // Method repositories:()Lscala/collection/immutable/Seq;
        16: aload_0
        17: invokevirtual #154                // Method mirrorConfFiles:()Lscala/collection/immutable/Seq;
        20: aload_0
        21: invokevirtual #150                // Method mirrors:()Lscala/collection/immutable/Seq;
        24: aload_1
        25: invokespecial #310                // Method "<init>":(Lcoursier/cache/Cache;Lscala/Option;Lscala/collection/immutable/Seq;Lscala/collection/immutable/Seq;Lscala/collection/immutable/Seq;Lcoursier/util/Sync;)V
        28: areturn
      LineNumberTable:
        line 10: 0
      LocalVariableTable:
        Start  Length  Slot  Name   Signature
            0      29     0  this   Lcoursier/Versions;
            0      29     1  sync   Lcoursier/util/Sync;
    Signature: #314                         // (Lcoursier/util/Sync<TF;>;)Lcoursier/Versions<TF;>;
    MethodParameters:
      Name                           Flags
      sync                           final

  public java.lang.String toString();
    descriptor: ()Ljava/lang/String;
    flags: (0x0001) ACC_PUBLIC
    Code:
      stack=3, locals=2, args_size=1
         0: new           #318                // class java/lang/StringBuilder
         3: dup
         4: ldc_w         #320                // String Versions(
         7: invokespecial #323                // Method java/lang/StringBuilder."<init>":(Ljava/lang/String;)V
        10: astore_1
        11: aload_1
        12: aload_0
        13: invokevirtual #264                // Method cache:()Lcoursier/cache/Cache;
        16: invokestatic  #329                // Method java/lang/String.valueOf:(Ljava/lang/Object;)Ljava/lang/String;
        19: invokevirtual #333                // Method java/lang/StringBuilder.append:(Ljava/lang/String;)Ljava/lang/StringBuilder;
        22: pop
        23: aload_1
        24: ldc_w         #335                // String ,
        27: invokevirtual #333                // Method java/lang/StringBuilder.append:(Ljava/lang/String;)Ljava/lang/StringBuilder;
        30: pop
        31: aload_1
        32: aload_0
        33: invokevirtual #307                // Method moduleOpt:()Lscala/Option;
        36: invokestatic  #329                // Method java/lang/String.valueOf:(Ljava/lang/Object;)Ljava/lang/String;
        39: invokevirtual #333                // Method java/lang/StringBuilder.append:(Ljava/lang/String;)Ljava/lang/StringBuilder;
        42: pop
        43: aload_1
        44: ldc_w         #335                // String ,
        47: invokevirtual #333                // Method java/lang/StringBuilder.append:(Ljava/lang/String;)Ljava/lang/StringBuilder;
        50: pop
        51: aload_1
        52: aload_0
        53: invokevirtual #124                // Method repositories:()Lscala/collection/immutable/Seq;
        56: invokestatic  #329                // Method java/lang/String.valueOf:(Ljava/lang/Object;)Ljava/lang/String;
        59: invokevirtual #333                // Method java/lang/StringBuilder.append:(Ljava/lang/String;)Ljava/lang/StringBuilder;
        62: pop
        63: aload_1
        64: ldc_w         #335                // String ,
        67: invokevirtual #333                // Method java/lang/StringBuilder.append:(Ljava/lang/String;)Ljava/lang/StringBuilder;
        70: pop
        71: aload_1
        72: aload_0
        73: invokevirtual #154                // Method mirrorConfFiles:()Lscala/collection/immutable/Seq;
        76: invokestatic  #329                // Method java/lang/String.valueOf:(Ljava/lang/Object;)Ljava/lang/String;
        79: invokevirtual #333                // Method java/lang/StringBuilder.append:(Ljava/lang/String;)Ljava/lang/StringBuilder;
        82: pop
        83: aload_1
        84: ldc_w         #335                // String ,
        87: invokevirtual #333                // Method java/lang/StringBuilder.append:(Ljava/lang/String;)Ljava/lang/StringBuilder;
        90: pop
        91: aload_1
        92: aload_0
        93: invokevirtual #150                // Method mirrors:()Lscala/collection/immutable/Seq;
        96: invokestatic  #329                // Method java/lang/String.valueOf:(Ljava/lang/Object;)Ljava/lang/String;
        99: invokevirtual #333                // Method java/lang/StringBuilder.append:(Ljava/lang/String;)Ljava/lang/StringBuilder;
       102: pop
       103: aload_1
       104: ldc_w         #335                // String ,
       107: invokevirtual #333                // Method java/lang/StringBuilder.append:(Ljava/lang/String;)Ljava/lang/StringBuilder;
       110: pop
       111: aload_1
       112: aload_0
       113: invokevirtual #118                // Method sync:()Lcoursier/util/Sync;
       116: invokestatic  #329                // Method java/lang/String.valueOf:(Ljava/lang/Object;)Ljava/lang/String;
       119: invokevirtual #333                // Method java/lang/StringBuilder.append:(Ljava/lang/String;)Ljava/lang/StringBuilder;
       122: pop
       123: aload_1
       124: ldc_w         #337                // String )
       127: invokevirtual #333                // Method java/lang/StringBuilder.append:(Ljava/lang/String;)Ljava/lang/StringBuilder;
       130: pop
       131: aload_1
       132: invokevirtual #339                // Method java/lang/StringBuilder.toString:()Ljava/lang/String;
       135: areturn
      LineNumberTable:
        line 10: 0
      LocalVariableTable:
        Start  Length  Slot  Name   Signature
           11     124     1     b   Ljava/lang/StringBuilder;
            0     136     0  this   Lcoursier/Versions;

  public boolean canEqual(java.lang.Object);
    descriptor: (Ljava/lang/Object;)Z
    flags: (0x0001) ACC_PUBLIC
    Code:
      stack=1, locals=2, args_size=2
         0: aload_1
         1: ifnull        15
         4: aload_1
         5: instanceof    #2                  // class coursier/Versions
         8: ifeq          15
        11: iconst_1
        12: goto          16
        15: iconst_0
        16: ireturn
      StackMapTable: number_of_entries = 2
        frame_type = 15 /* same */
        frame_type = 64 /* same_locals_1_stack_item */
          stack = [ int ]
      LineNumberTable:
        line 10: 0
      LocalVariableTable:
        Start  Length  Slot  Name   Signature
            0      17     0  this   Lcoursier/Versions;
            0      17     1   obj   Ljava/lang/Object;
    MethodParameters:
      Name                           Flags
      obj                            final

  public boolean equals(java.lang.Object);
    descriptor: (Ljava/lang/Object;)Z
    flags: (0x0001) ACC_PUBLIC
    Code:
      stack=2, locals=9, args_size=2
         0: aload_0
         1: aload_1
         2: if_acmpeq     213
         5: aload_0
         6: aload_1
         7: invokevirtual #347                // Method canEqual:(Ljava/lang/Object;)Z
        10: ifeq          217
        13: aload_1
        14: checkcast     #2                  // class coursier/Versions
        17: astore_2
        18: iconst_1
        19: ifeq          209
        22: aload_0
        23: invokevirtual #264                // Method cache:()Lcoursier/cache/Cache;
        26: aload_2
        27: invokevirtual #264                // Method cache:()Lcoursier/cache/Cache;
        30: astore_3
        31: dup
        32: ifnonnull     43
        35: pop
        36: aload_3
        37: ifnull        50
        40: goto          209
        43: aload_3
        44: invokevirtual #349                // Method java/lang/Object.equals:(Ljava/lang/Object;)Z
        47: ifeq          209
        50: aload_0
        51: invokevirtual #307                // Method moduleOpt:()Lscala/Option;
        54: aload_2
        55: invokevirtual #307                // Method moduleOpt:()Lscala/Option;
        58: astore        4
        60: dup
        61: ifnonnull     73
        64: pop
        65: aload         4
        67: ifnull        81
        70: goto          209
        73: aload         4
        75: invokevirtual #349                // Method java/lang/Object.equals:(Ljava/lang/Object;)Z
        78: ifeq          209
        81: aload_0
        82: invokevirtual #124                // Method repositories:()Lscala/collection/immutable/Seq;
        85: aload_2
        86: invokevirtual #124                // Method repositories:()Lscala/collection/immutable/Seq;
        89: astore        5
        91: dup
        92: ifnonnull     104
        95: pop
        96: aload         5
        98: ifnull        112
       101: goto          209
       104: aload         5
       106: invokevirtual #349                // Method java/lang/Object.equals:(Ljava/lang/Object;)Z
       109: ifeq          209
       112: aload_0
       113: invokevirtual #154                // Method mirrorConfFiles:()Lscala/collection/immutable/Seq;
       116: aload_2
       117: invokevirtual #154                // Method mirrorConfFiles:()Lscala/collection/immutable/Seq;
       120: astore        6
       122: dup
       123: ifnonnull     135
       126: pop
       127: aload         6
       129: ifnull        143
       132: goto          209
       135: aload         6
       137: invokevirtual #349                // Method java/lang/Object.equals:(Ljava/lang/Object;)Z
       140: ifeq          209
       143: aload_0
       144: invokevirtual #150                // Method mirrors:()Lscala/collection/immutable/Seq;
       147: aload_2
       148: invokevirtual #150                // Method mirrors:()Lscala/collection/immutable/Seq;
       151: astore        7
       153: dup
       154: ifnonnull     166
       157: pop
       158: aload         7
       160: ifnull        174
       163: goto          209
       166: aload         7
       168: invokevirtual #349                // Method java/lang/Object.equals:(Ljava/lang/Object;)Z
       171: ifeq          209
       174: aload_0
       175: invokevirtual #118                // Method sync:()Lcoursier/util/Sync;
       178: aload_2
       179: invokevirtual #118                // Method sync:()Lcoursier/util/Sync;
       182: astore        8
       184: dup
       185: ifnonnull     197
       188: pop
       189: aload         8
       191: ifnull        205
       194: goto          209
       197: aload         8
       199: invokevirtual #349                // Method java/lang/Object.equals:(Ljava/lang/Object;)Z
       202: ifeq          209
       205: iconst_1
       206: goto          210
       209: iconst_0
       210: ifeq          217
       213: iconst_1
       214: goto          218
       217: iconst_0
       218: ireturn
      StackMapTable: number_of_entries = 17
        frame_type = 255 /* full_frame */
          offset_delta = 43
          locals = [ class coursier/Versions, class java/lang/Object, class coursier/Versions, class coursier/cache/Cache ]
          stack = [ class coursier/cache/Cache ]
        frame_type = 6 /* same */
        frame_type = 255 /* full_frame */
          offset_delta = 22
          locals = [ class coursier/Versions, class java/lang/Object, class coursier/Versions, class coursier/cache/Cache, class scala/Option ]
          stack = [ class scala/Option ]
        frame_type = 7 /* same */
        frame_type = 255 /* full_frame */
          offset_delta = 22
          locals = [ class coursier/Versions, class java/lang/Object, class coursier/Versions, class coursier/cache/Cache, class scala/Option, class scala/collection/immutable/Seq ]
          stack = [ class scala/collection/immutable/Seq ]
        frame_type = 7 /* same */
        frame_type = 255 /* full_frame */
          offset_delta = 22
          locals = [ class coursier/Versions, class java/lang/Object, class coursier/Versions, class coursier/cache/Cache, class scala/Option, class scala/collection/immutable/Seq, class scala/collection/immutable/Seq ]
          stack = [ class scala/collection/immutable/Seq ]
        frame_type = 7 /* same */
        frame_type = 255 /* full_frame */
          offset_delta = 22
          locals = [ class coursier/Versions, class java/lang/Object, class coursier/Versions, class coursier/cache/Cache, class scala/Option, class scala/collection/immutable/Seq, class scala/collection/immutable/Seq, class scala/collection/immutable/Seq ]
          stack = [ class scala/collection/immutable/Seq ]
        frame_type = 7 /* same */
        frame_type = 255 /* full_frame */
          offset_delta = 22
          locals = [ class coursier/Versions, class java/lang/Object, class coursier/Versions, class coursier/cache/Cache, class scala/Option, class scala/collection/immutable/Seq, class scala/collection/immutable/Seq, class scala/collection/immutable/Seq, class coursier/util/Sync ]
          stack = [ class coursier/util/Sync ]
        frame_type = 7 /* same */
        frame_type = 255 /* full_frame */
          offset_delta = 3
          locals = [ class coursier/Versions, class java/lang/Object, class coursier/Versions ]
          stack = []
        frame_type = 64 /* same_locals_1_stack_item */
          stack = [ int ]
        frame_type = 250 /* chop */
          offset_delta = 2
        frame_type = 3 /* same */
        frame_type = 64 /* same_locals_1_stack_item */
          stack = [ int ]
      LineNumberTable:
        line 10: 0
      LocalVariableTable:
        Start  Length  Slot  Name   Signature
           18     192     2 other   Lcoursier/Versions;
            0     219     0  this   Lcoursier/Versions;
            0     219     1   obj   Ljava/lang/Object;
    MethodParameters:
      Name                           Flags
      obj                            final

  public int hashCode();
    descriptor: ()I
    flags: (0x0001) ACC_PUBLIC
    Code:
      stack=2, locals=2, args_size=1
         0: bipush        17
         2: ldc_w         #354                // String Versions
         5: invokestatic  #360                // Method scala/runtime/Statics.anyHash:(Ljava/lang/Object;)I
         8: iadd
         9: istore_1
        10: bipush        37
        12: iload_1
        13: imul
        14: aload_0
        15: invokevirtual #264                // Method cache:()Lcoursier/cache/Cache;
        18: invokestatic  #360                // Method scala/runtime/Statics.anyHash:(Ljava/lang/Object;)I
        21: iadd
        22: istore_1
        23: bipush        37
        25: iload_1
        26: imul
        27: aload_0
        28: invokevirtual #307                // Method moduleOpt:()Lscala/Option;
        31: invokestatic  #360                // Method scala/runtime/Statics.anyHash:(Ljava/lang/Object;)I
        34: iadd
        35: istore_1
        36: bipush        37
        38: iload_1
        39: imul
        40: aload_0
        41: invokevirtual #124                // Method repositories:()Lscala/collection/immutable/Seq;
        44: invokestatic  #360                // Method scala/runtime/Statics.anyHash:(Ljava/lang/Object;)I
        47: iadd
        48: istore_1
        49: bipush        37
        51: iload_1
        52: imul
        53: aload_0
        54: invokevirtual #154                // Method mirrorConfFiles:()Lscala/collection/immutable/Seq;
        57: invokestatic  #360                // Method scala/runtime/Statics.anyHash:(Ljava/lang/Object;)I
        60: iadd
        61: istore_1
        62: bipush        37
        64: iload_1
        65: imul
        66: aload_0
        67: invokevirtual #150                // Method mirrors:()Lscala/collection/immutable/Seq;
        70: invokestatic  #360                // Method scala/runtime/Statics.anyHash:(Ljava/lang/Object;)I
        73: iadd
        74: istore_1
        75: bipush        37
        77: iload_1
        78: imul
        79: aload_0
        80: invokevirtual #118                // Method sync:()Lcoursier/util/Sync;
        83: invokestatic  #360                // Method scala/runtime/Statics.anyHash:(Ljava/lang/Object;)I
        86: iadd
        87: istore_1
        88: bipush        37
        90: iload_1
        91: imul
        92: ireturn
      LineNumberTable:
        line 10: 0
      LocalVariableTable:
        Start  Length  Slot  Name   Signature
           10      82     1  code   I
            0      93     0  this   Lcoursier/Versions;

  private scala.Tuple6<coursier.cache.Cache<F>, scala.Option<coursier.core.Module>, scala.collection.immutable.Seq<coursier.core.Repository>, scala.collection.immutable.Seq<coursier.params.MirrorConfFile>, scala.collection.immutable.Seq<coursier.params.Mirror>, coursier.util.Sync<F>> tuple();
    descriptor: ()Lscala/Tuple6;
    flags: (0x0002) ACC_PRIVATE
    Code:
      stack=8, locals=1, args_size=1
         0: new           #367                // class scala/Tuple6
         3: dup
         4: aload_0
         5: invokevirtual #264                // Method cache:()Lcoursier/cache/Cache;
         8: aload_0
         9: invokevirtual #307                // Method moduleOpt:()Lscala/Option;
        12: aload_0
        13: invokevirtual #124                // Method repositories:()Lscala/collection/immutable/Seq;
        16: aload_0
        17: invokevirtual #154                // Method mirrorConfFiles:()Lscala/collection/immutable/Seq;
        20: aload_0
        21: invokevirtual #150                // Method mirrors:()Lscala/collection/immutable/Seq;
        24: aload_0
        25: invokevirtual #118                // Method sync:()Lcoursier/util/Sync;
        28: invokespecial #370                // Method scala/Tuple6."<init>":(Ljava/lang/Object;Ljava/lang/Object;Ljava/lang/Object;Ljava/lang/Object;Ljava/lang/Object;Ljava/lang/Object;)V
        31: areturn
      LineNumberTable:
        line 10: 0
      LocalVariableTable:
        Start  Length  Slot  Name   Signature
            0      32     0  this   Lcoursier/Versions;
    Signature: #365                         // ()Lscala/Tuple6<Lcoursier/cache/Cache<TF;>;Lscala/Option<Lcoursier/core/Module;>;Lscala/collection/immutable/Seq<Lcoursier/core/Repository;>;Lscala/collection/immutable/Seq<Lcoursier/params/MirrorConfFile;>;Lscala/collection/immutable/Seq<Lcoursier/params/Mirror;>;Lcoursier/util/Sync<TF;>;>;

  public java.lang.String productPrefix();
    descriptor: ()Ljava/lang/String;
    flags: (0x0001) ACC_PUBLIC
    Code:
      stack=1, locals=1, args_size=1
         0: ldc_w         #354                // String Versions
         3: areturn
      LineNumberTable:
        line 10: 0
      LocalVariableTable:
        Start  Length  Slot  Name   Signature
            0       4     0  this   Lcoursier/Versions;

  public int productArity();
    descriptor: ()I
    flags: (0x0001) ACC_PUBLIC
    Code:
      stack=1, locals=1, args_size=1
         0: bipush        6
         2: ireturn
      LineNumberTable:
        line 10: 0
      LocalVariableTable:
        Start  Length  Slot  Name   Signature
            0       3     0  this   Lcoursier/Versions;

  public java.lang.Object productElement(int);
    descriptor: (I)Ljava/lang/Object;
    flags: (0x0001) ACC_PUBLIC
    Code:
      stack=3, locals=3, args_size=2
         0: iload_1
         1: istore_2
         2: iload_2
         3: tableswitch   { // 0 to 5
                       0: 40
                       1: 47
                       2: 54
                       3: 61
                       4: 68
                       5: 75
                 default: 82
            }
        40: aload_0
        41: invokevirtual #264                // Method cache:()Lcoursier/cache/Cache;
        44: goto          97
        47: aload_0
        48: invokevirtual #307                // Method moduleOpt:()Lscala/Option;
        51: goto          97
        54: aload_0
        55: invokevirtual #124                // Method repositories:()Lscala/collection/immutable/Seq;
        58: goto          97
        61: aload_0
        62: invokevirtual #154                // Method mirrorConfFiles:()Lscala/collection/immutable/Seq;
        65: goto          97
        68: aload_0
        69: invokevirtual #150                // Method mirrors:()Lscala/collection/immutable/Seq;
        72: goto          97
        75: aload_0
        76: invokevirtual #118                // Method sync:()Lcoursier/util/Sync;
        79: goto          97
        82: new           #377                // class java/lang/IndexOutOfBoundsException
        85: dup
        86: iload_2
        87: invokestatic  #383                // Method scala/runtime/BoxesRunTime.boxToInteger:(I)Ljava/lang/Integer;
        90: invokevirtual #384                // Method java/lang/Object.toString:()Ljava/lang/String;
        93: invokespecial #385                // Method java/lang/IndexOutOfBoundsException."<init>":(Ljava/lang/String;)V
        96: athrow
        97: areturn
      StackMapTable: number_of_entries = 8
        frame_type = 252 /* append */
          offset_delta = 40
          locals = [ int ]
        frame_type = 6 /* same */
        frame_type = 6 /* same */
        frame_type = 6 /* same */
        frame_type = 6 /* same */
        frame_type = 6 /* same */
        frame_type = 6 /* same */
        frame_type = 78 /* same_locals_1_stack_item */
          stack = [ class java/lang/Object ]
      LineNumberTable:
        line 10: 0
      LocalVariableTable:
        Start  Length  Slot  Name   Signature
            0      98     0  this   Lcoursier/Versions;
            0      98     1     n   I
    MethodParameters:
      Name                           Flags
      n                              final

  public java.lang.String productElementName(int);
    descriptor: (I)Ljava/lang/String;
    flags: (0x0001) ACC_PUBLIC
    Code:
      stack=3, locals=3, args_size=2
         0: iload_1
         1: istore_2
         2: iload_2
         3: tableswitch   { // 0 to 5
                       0: 40
                       1: 46
                       2: 52
                       3: 58
                       4: 64
                       5: 70
                 default: 76
            }
        40: ldc_w         #388                // String cache
        43: goto          91
        46: ldc_w         #389                // String moduleOpt
        49: goto          91
        52: ldc_w         #390                // String repositories
        55: goto          91
        58: ldc_w         #391                // String mirrorConfFiles
        61: goto          91
        64: ldc_w         #392                // String mirrors
        67: goto          91
        70: ldc_w         #393                // String sync
        73: goto          91
        76: new           #377                // class java/lang/IndexOutOfBoundsException
        79: dup
        80: iload_2
        81: invokestatic  #383                // Method scala/runtime/BoxesRunTime.boxToInteger:(I)Ljava/lang/Integer;
        84: invokevirtual #384                // Method java/lang/Object.toString:()Ljava/lang/String;
        87: invokespecial #385                // Method java/lang/IndexOutOfBoundsException."<init>":(Ljava/lang/String;)V
        90: athrow
        91: areturn
      StackMapTable: number_of_entries = 8
        frame_type = 252 /* append */
          offset_delta = 40
          locals = [ int ]
        frame_type = 5 /* same */
        frame_type = 5 /* same */
        frame_type = 5 /* same */
        frame_type = 5 /* same */
        frame_type = 5 /* same */
        frame_type = 5 /* same */
        frame_type = 78 /* same_locals_1_stack_item */
          stack = [ class java/lang/String ]
      LineNumberTable:
        line 10: 0
      LocalVariableTable:
        Start  Length  Slot  Name   Signature
            0      92     0  this   Lcoursier/Versions;
            0      92     1     n   I
    MethodParameters:
      Name                           Flags
      n                              final

  public static final coursier.core.Versions $anonfun$versions$1(coursier.Versions$Result);
    descriptor: (Lcoursier/Versions$Result;)Lcoursier/core/Versions;
    flags: (0x1019) ACC_PUBLIC, ACC_STATIC, ACC_FINAL, ACC_SYNTHETIC
    Code:
      stack=1, locals=1, args_size=1
         0: aload_0
         1: invokevirtual #397                // Method coursier/Versions$Result.versions:()Lcoursier/core/Versions;
         4: areturn
      LineNumberTable:
        line 39: 0
      LocalVariableTable:
        Start  Length  Slot  Name   Signature
            0       5     0   x$1   Lcoursier/Versions$Result;
    MethodParameters:
      Name                           Flags
      x$1                            final

  public static final scala.collection.immutable.Seq $anonfun$finalRepositories$1(coursier.Versions, scala.collection.immutable.Seq);
    descriptor: (Lcoursier/Versions;Lscala/collection/immutable/Seq;)Lscala/collection/immutable/Seq;
    flags: (0x1019) ACC_PUBLIC, ACC_STATIC, ACC_FINAL, ACC_SYNTHETIC
    Code:
      stack=3, locals=2, args_size=2
         0: getstatic     #405                // Field coursier/params/Mirror$.MODULE$:Lcoursier/params/Mirror$;
         3: aload_0
         4: invokevirtual #124                // Method repositories:()Lscala/collection/immutable/Seq;
         7: aload_1
         8: invokevirtual #409                // Method coursier/params/Mirror$.replace:(Lscala/collection/immutable/Seq;Lscala/collection/immutable/Seq;)Lscala/collection/immutable/Seq;
        11: areturn
      LineNumberTable:
        line 42: 0
      LocalVariableTable:
        Start  Length  Slot  Name   Signature
            0      12     0 $this   Lcoursier/Versions;
            0      12     1   x$2   Lscala/collection/immutable/Seq;
    MethodParameters:
      Name                           Flags
      $this                          final synthetic
      x$2                            final

  public static final scala.collection.immutable.Seq $anonfun$allMirrors0$1(coursier.params.MirrorConfFile);
    descriptor: (Lcoursier/params/MirrorConfFile;)Lscala/collection/immutable/Seq;
    flags: (0x1019) ACC_PUBLIC, ACC_STATIC, ACC_FINAL, ACC_SYNTHETIC
    Code:
      stack=1, locals=1, args_size=1
         0: aload_0
         1: invokevirtual #413                // Method coursier/params/MirrorConfFile.mirrors:()Lscala/collection/immutable/Seq;
         4: areturn
      LineNumberTable:
        line 45: 0
      LocalVariableTable:
        Start  Length  Slot  Name   Signature
            0       5     0   x$3   Lcoursier/params/MirrorConfFile;
    MethodParameters:
      Name                           Flags
      x$3                            final

  public static final scala.collection.immutable.Seq $anonfun$allMirrors$1(coursier.Versions);
    descriptor: (Lcoursier/Versions;)Lscala/collection/immutable/Seq;
    flags: (0x1019) ACC_PUBLIC, ACC_STATIC, ACC_FINAL, ACC_SYNTHETIC
    Code:
      stack=1, locals=1, args_size=1
         0: aload_0
         1: invokespecial #416                // Method allMirrors0:()Lscala/collection/immutable/Seq;
         4: areturn
      LineNumberTable:
        line 48: 0
      LocalVariableTable:
        Start  Length  Slot  Name   Signature
            0       5     0 $this   Lcoursier/Versions;
    MethodParameters:
      Name                           Flags
      $this                          final synthetic

  public static final coursier.core.Versions $anonfun$result$5(scala.Tuple2);
    descriptor: (Lscala/Tuple2;)Lcoursier/core/Versions;
    flags: (0x1019) ACC_PUBLIC, ACC_STATIC, ACC_FINAL, ACC_SYNTHETIC
    Code:
      stack=1, locals=1, args_size=1
         0: aload_0
         1: invokevirtual #424                // Method scala/Tuple2._1:()Ljava/lang/Object;
         4: checkcast     #426                // class coursier/core/Versions
         7: areturn
      LineNumberTable:
        line 59: 0
      LocalVariableTable:
        Start  Length  Slot  Name   Signature
            0       8     0   x$5   Lscala/Tuple2;
    MethodParameters:
      Name                           Flags
      x$5                            final

  public static final scala.Tuple2 $anonfun$result$4(coursier.core.Repository, scala.util.Either);
    descriptor: (Lcoursier/core/Repository;Lscala/util/Either;)Lscala/Tuple2;
    flags: (0x1019) ACC_PUBLIC, ACC_STATIC, ACC_FINAL, ACC_SYNTHETIC
    Code:
      stack=4, locals=2, args_size=2
         0: getstatic     #434                // Field scala/Predef$ArrowAssoc$.MODULE$:Lscala/Predef$ArrowAssoc$;
         3: getstatic     #439                // Field scala/Predef$.MODULE$:Lscala/Predef$;
         6: aload_0
         7: invokevirtual #442                // Method scala/Predef$.ArrowAssoc:(Ljava/lang/Object;)Ljava/lang/Object;
        10: aload_1
        11: invokedynamic #447,  0            // InvokeDynamic #8:apply:()Lscala/Function1;
        16: invokevirtual #452                // Method scala/util/Either.map:(Lscala/Function1;)Lscala/util/Either;
        19: invokevirtual #456                // Method scala/Predef$ArrowAssoc$.$minus$greater$extension:(Ljava/lang/Object;Ljava/lang/Object;)Lscala/Tuple2;
        22: areturn
      LineNumberTable:
        line 59: 3
      LocalVariableTable:
        Start  Length  Slot  Name   Signature
            0      23     0 repo$1   Lcoursier/core/Repository;
            0      23     1   x$4   Lscala/util/Either;
    MethodParameters:
      Name                           Flags
      repo$1                         final
      x$4                            final

  public static final java.lang.Object $anonfun$result$3(coursier.Versions, coursier.core.Module, coursier.core.Repository);
    descriptor: (Lcoursier/Versions;Lcoursier/core/Module;Lcoursier/core/Repository;)Ljava/lang/Object;
    flags: (0x1019) ACC_PUBLIC, ACC_STATIC, ACC_FINAL, ACC_SYNTHETIC
    Code:
      stack=5, locals=3, args_size=3
         0: getstatic     #175                // Field coursier/util/Monad$ops$.MODULE$:Lcoursier/util/Monad$ops$;
         3: aload_2
         4: aload_1
         5: aload_0
         6: invokevirtual #264                // Method cache:()Lcoursier/cache/Cache;
         9: invokevirtual #465                // Method coursier/cache/Cache.fetch:()Lscala/Function1;
        12: aload_0
        13: invokevirtual #118                // Method sync:()Lcoursier/util/Sync;
        16: invokeinterface #470,  4          // InterfaceMethod coursier/core/Repository.versions:(Lcoursier/core/Module;Lscala/Function1;Lcoursier/util/Monad;)Lcoursier/util/EitherT;
        21: invokevirtual #475                // Method coursier/util/EitherT.run:()Ljava/lang/Object;
        24: aload_0
        25: invokevirtual #118                // Method sync:()Lcoursier/util/Sync;
        28: invokevirtual #182                // Method coursier/util/Monad$ops$.toAllMonadOps:(Ljava/lang/Object;Lcoursier/util/Monad;)Lcoursier/util/Monad$AllOps;
        31: aload_2
        32: invokedynamic #483,  0            // InvokeDynamic #9:apply:(Lcoursier/core/Repository;)Lscala/Function1;
        37: invokeinterface #206,  2          // InterfaceMethod coursier/util/Monad$AllOps.map:(Lscala/Function1;)Ljava/lang/Object;
        42: areturn
      LineNumberTable:
        line 59: 0
      LocalVariableTable:
        Start  Length  Slot  Name   Signature
            0      43     0 $this   Lcoursier/Versions;
            0      43     1 mod$1   Lcoursier/core/Module;
            0      43     2  repo   Lcoursier/core/Repository;
    MethodParameters:
      Name                           Flags
      $this                          final synthetic
      mod$1                          final
      repo                           final

  public static final scala.collection.immutable.Seq $anonfun$result$2(coursier.Versions, scala.collection.immutable.Seq, coursier.core.Module);
    descriptor: (Lcoursier/Versions;Lscala/collection/immutable/Seq;Lcoursier/core/Module;)Lscala/collection/immutable/Seq;
    flags: (0x1019) ACC_PUBLIC, ACC_STATIC, ACC_FINAL, ACC_SYNTHETIC
    Code:
      stack=3, locals=3, args_size=3
         0: aload_1
         1: aload_0
         2: aload_2
         3: invokedynamic #495,  0            // InvokeDynamic #10:apply:(Lcoursier/Versions;Lcoursier/core/Module;)Lscala/Function1;
         8: invokeinterface #496,  2          // InterfaceMethod scala/collection/immutable/Seq.map:(Lscala/Function1;)Ljava/lang/Object;
        13: checkcast     #126                // class scala/collection/immutable/Seq
        16: areturn
      LineNumberTable:
        line 57: 0
      LocalVariableTable:
        Start  Length  Slot  Name   Signature
            0      17     0 $this   Lcoursier/Versions;
            0      17     1 repositories$1   Lscala/collection/immutable/Seq;
            0      17     2   mod   Lcoursier/core/Module;
    MethodParameters:
      Name                           Flags
      $this                          final synthetic
      repositories$1                 final
      mod                            final

  public static final java.lang.Object $anonfun$result$1(coursier.Versions, scala.collection.immutable.Seq);
    descriptor: (Lcoursier/Versions;Lscala/collection/immutable/Seq;)Ljava/lang/Object;
    flags: (0x1019) ACC_PUBLIC, ACC_STATIC, ACC_FINAL, ACC_SYNTHETIC
    Code:
      stack=4, locals=2, args_size=2
         0: aload_0
         1: invokespecial #235                // Method F:()Lcoursier/util/Sync;
         4: getstatic     #501                // Field scala/Option$.MODULE$:Lscala/Option$;
         7: aload_0
         8: invokevirtual #307                // Method moduleOpt:()Lscala/Option;
        11: invokevirtual #505                // Method scala/Option$.option2Iterable:(Lscala/Option;)Lscala/collection/Iterable;
        14: invokeinterface #510,  1          // InterfaceMethod scala/collection/Iterable.toSeq:()Lscala/collection/immutable/Seq;
        19: aload_0
        20: aload_1
        21: invokedynamic #518,  0            // InvokeDynamic #11:apply:(Lcoursier/Versions;Lscala/collection/immutable/Seq;)Lscala/Function1;
        26: invokeinterface #231,  2          // InterfaceMethod scala/collection/immutable/Seq.flatMap:(Lscala/Function1;)Ljava/lang/Object;
        31: checkcast     #126                // class scala/collection/immutable/Seq
        34: invokeinterface #521,  2          // InterfaceMethod coursier/util/Sync.gather:(Lscala/collection/immutable/Seq;)Ljava/lang/Object;
        39: areturn
      LineNumberTable:
        line 54: 0
        line 56: 4
      LocalVariableTable:
        Start  Length  Slot  Name   Signature
            0      40     0 $this   Lcoursier/Versions;
            0      40     1 repositories   Lscala/collection/immutable/Seq;
    MethodParameters:
      Name                           Flags
      $this                          final synthetic
      repositories                   final

  public static final java.lang.Object $anonfun$result$6(java.lang.Object);
    descriptor: (Ljava/lang/Object;)Ljava/lang/Object;
    flags: (0x1019) ACC_PUBLIC, ACC_STATIC, ACC_FINAL, ACC_SYNTHETIC
    Code:
      stack=1, locals=1, args_size=1
         0: aload_0
         1: areturn
      LineNumberTable:
        line 64: 0
      LocalVariableTable:
        Start  Length  Slot  Name   Signature
            0       2     0   t$1   Ljava/lang/Object;
    MethodParameters:
      Name                           Flags
      t$1                            final

  public static final java.lang.Object $anonfun$result$7(coursier.Versions, java.lang.Object, coursier.cache.CacheLogger);
    descriptor: (Lcoursier/Versions;Ljava/lang/Object;Lcoursier/cache/CacheLogger;)Ljava/lang/Object;
    flags: (0x1019) ACC_PUBLIC, ACC_STATIC, ACC_FINAL, ACC_SYNTHETIC
    Code:
      stack=3, locals=3, args_size=3
         0: aload_2
         1: invokeinterface #527,  1          // InterfaceMethod coursier/cache/CacheLogger.using:()Lcoursier/cache/CacheLogger$Using;
         6: aload_1
         7: aload_0
         8: invokevirtual #118                // Method sync:()Lcoursier/util/Sync;
        11: invokevirtual #530                // Method coursier/cache/CacheLogger$Using.apply:(Ljava/lang/Object;Lcoursier/util/Sync;)Ljava/lang/Object;
        14: areturn
      LineNumberTable:
        line 65: 0
      LocalVariableTable:
        Start  Length  Slot  Name   Signature
            0      15     0 $this   Lcoursier/Versions;
            0      15     1   t$1   Ljava/lang/Object;
            0      15     2 logger   Lcoursier/cache/CacheLogger;
    MethodParameters:
      Name                           Flags
      $this                          final synthetic
      t$1                            final
      logger                         final

  public static final coursier.Versions$Result $anonfun$result$8(scala.collection.immutable.Seq);
    descriptor: (Lscala/collection/immutable/Seq;)Lcoursier/Versions$Result;
    flags: (0x1019) ACC_PUBLIC, ACC_STATIC, ACC_FINAL, ACC_SYNTHETIC
    Code:
      stack=2, locals=1, args_size=1
         0: getstatic     #535                // Field coursier/Versions$Result$.MODULE$:Lcoursier/Versions$Result$;
         3: aload_0
         4: invokevirtual #537                // Method coursier/Versions$Result$.apply:(Lscala/collection/immutable/Seq;)Lcoursier/Versions$Result;
         7: areturn
      LineNumberTable:
        line 69: 0
      LocalVariableTable:
        Start  Length  Slot  Name   Signature
            0       8     0     l   Lscala/collection/immutable/Seq;
    MethodParameters:
      Name                           Flags
      l                              final

  public coursier.Versions(coursier.cache.Cache<F>, scala.Option<coursier.core.Module>, scala.collection.immutable.Seq<coursier.core.Repository>, scala.collection.immutable.Seq<coursier.params.MirrorConfFile>, scala.collection.immutable.Seq<coursier.params.Mirror>, coursier.util.Sync<F>);
    descriptor: (Lcoursier/cache/Cache;Lscala/Option;Lscala/collection/immutable/Seq;Lscala/collection/immutable/Seq;Lscala/collection/immutable/Seq;Lcoursier/util/Sync;)V
    flags: (0x0001) ACC_PUBLIC
    Code:
      stack=2, locals=7, args_size=7
         0: aload_0
         1: aload_1
         2: putfield      #97                 // Field cache:Lcoursier/cache/Cache;
         5: aload_0
         6: aload_2
         7: putfield      #101                // Field moduleOpt:Lscala/Option;
        10: aload_0
        11: aload_3
        12: putfield      #105                // Field repositories:Lscala/collection/immutable/Seq;
        15: aload_0
        16: aload         4
        18: putfield      #108                // Field mirrorConfFiles:Lscala/collection/immutable/Seq;
        21: aload_0
        22: aload         5
        24: putfield      #111                // Field mirrors:Lscala/collection/immutable/Seq;
        27: aload_0
        28: aload         6
        30: putfield      #115                // Field sync:Lcoursier/util/Sync;
        33: aload_0
        34: invokespecial #541                // Method java/lang/Object."<init>":()V
        37: aload_0
        38: invokestatic  #545                // InterfaceMethod scala/Product.$init$:(Lscala/Product;)V
        41: return
      LineNumberTable:
        line 10: 0
        line 74: 33
        line 10: 41
      LocalVariableTable:
        Start  Length  Slot  Name   Signature
            0      42     0  this   Lcoursier/Versions;
            0      42     1 cache   Lcoursier/cache/Cache;
            0      42     2 moduleOpt   Lscala/Option;
            0      42     3 repositories   Lscala/collection/immutable/Seq;
            0      42     4 mirrorConfFiles   Lscala/collection/immutable/Seq;
            0      42     5 mirrors   Lscala/collection/immutable/Seq;
            0      42     6  sync   Lcoursier/util/Sync;
    Signature: #538                         // (Lcoursier/cache/Cache<TF;>;Lscala/Option<Lcoursier/core/Module;>;Lscala/collection/immutable/Seq<Lcoursier/core/Repository;>;Lscala/collection/immutable/Seq<Lcoursier/params/MirrorConfFile;>;Lscala/collection/immutable/Seq<Lcoursier/params/Mirror;>;Lcoursier/util/Sync<TF;>;)V
    MethodParameters:
      Name                           Flags
      cache                          final
      moduleOpt                      final
      repositories                   final
      mirrorConfFiles                final
      mirrors                        final
      sync                           final

  public coursier.Versions(coursier.cache.Cache<F>, scala.Option<coursier.core.Module>, scala.collection.immutable.Seq<coursier.core.Repository>, coursier.util.Sync<F>);
    descriptor: (Lcoursier/cache/Cache;Lscala/Option;Lscala/collection/immutable/Seq;Lcoursier/util/Sync;)V
    flags: (0x0001) ACC_PUBLIC
    Code:
      stack=7, locals=5, args_size=5
         0: aload_0
         1: aload_1
         2: aload_2
         3: aload_3
         4: getstatic     #552                // Field coursier/Resolve$.MODULE$:Lcoursier/Resolve$;
         7: invokevirtual #555                // Method coursier/Resolve$.defaultMirrorConfFiles:()Lscala/collection/immutable/Seq;
        10: getstatic     #140                // Field scala/collection/immutable/Nil$.MODULE$:Lscala/collection/immutable/Nil$;
        13: aload         4
        15: invokespecial #310                // Method "<init>":(Lcoursier/cache/Cache;Lscala/Option;Lscala/collection/immutable/Seq;Lscala/collection/immutable/Seq;Lscala/collection/immutable/Seq;Lcoursier/util/Sync;)V
        18: return
      LineNumberTable:
        line 10: 0
        line 15: 4
        line 16: 10
        line 10: 13
      LocalVariableTable:
        Start  Length  Slot  Name   Signature
            0      19     0  this   Lcoursier/Versions;
            0      19     1 cache   Lcoursier/cache/Cache;
            0      19     2 moduleOpt   Lscala/Option;
            0      19     3 repositories   Lscala/collection/immutable/Seq;
            0      19     4  sync   Lcoursier/util/Sync;
    Signature: #547                         // (Lcoursier/cache/Cache<TF;>;Lscala/Option<Lcoursier/core/Module;>;Lscala/collection/immutable/Seq<Lcoursier/core/Repository;>;Lcoursier/util/Sync<TF;>;)V
    MethodParameters:
      Name                           Flags
      cache                          final
      moduleOpt                      final
      repositories                   final
      sync                           final

  public coursier.Versions(coursier.cache.Cache<F>, coursier.util.Sync<F>);
    descriptor: (Lcoursier/cache/Cache;Lcoursier/util/Sync;)V
    flags: (0x0001) ACC_PUBLIC
    Code:
      stack=7, locals=3, args_size=3
         0: aload_0
         1: aload_1
         2: getstatic     #562                // Field scala/None$.MODULE$:Lscala/None$;
         5: getstatic     #552                // Field coursier/Resolve$.MODULE$:Lcoursier/Resolve$;
         8: invokevirtual #565                // Method coursier/Resolve$.defaultRepositories:()Lscala/collection/immutable/Seq;
        11: getstatic     #552                // Field coursier/Resolve$.MODULE$:Lcoursier/Resolve$;
        14: invokevirtual #555                // Method coursier/Resolve$.defaultMirrorConfFiles:()Lscala/collection/immutable/Seq;
        17: getstatic     #140                // Field scala/collection/immutable/Nil$.MODULE$:Lscala/collection/immutable/Nil$;
        20: aload_2
        21: invokespecial #310                // Method "<init>":(Lcoursier/cache/Cache;Lscala/Option;Lscala/collection/immutable/Seq;Lscala/collection/immutable/Seq;Lscala/collection/immutable/Seq;Lcoursier/util/Sync;)V
        24: return
      LineNumberTable:
        line 10: 0
        line 12: 2
        line 13: 5
        line 15: 11
        line 16: 17
        line 10: 20
      LocalVariableTable:
        Start  Length  Slot  Name   Signature
            0      25     0  this   Lcoursier/Versions;
            0      25     1 cache   Lcoursier/cache/Cache;
            0      25     2  sync   Lcoursier/util/Sync;
    Signature: #557                         // (Lcoursier/cache/Cache<TF;>;Lcoursier/util/Sync<TF;>;)V
    MethodParameters:
      Name                           Flags
      cache                          final
      sync                           final

  private static java.lang.Object $deserializeLambda$(java.lang.invoke.SerializedLambda);
    descriptor: (Ljava/lang/invoke/SerializedLambda;)Ljava/lang/Object;
    flags: (0x100a) ACC_PRIVATE, ACC_STATIC, ACC_SYNTHETIC
    Code:
      stack=1, locals=1, args_size=1
         0: aload_0
         1: invokedynamic #577,  0            // InvokeDynamic #12:lambdaDeserialize:(Ljava/lang/invoke/SerializedLambda;)Ljava/lang/Object;
         6: areturn
}
InnerClasses:
  public static final #16= #15 of #2;     // Result=class coursier/Versions$Result of class coursier/Versions
  public static #19= #18 of #2;           // =class coursier/Versions$Result$ of class coursier/Versions
  public static final #24= #21 of #23;    // Using=class coursier/cache/CacheLogger$Using of class coursier/cache/CacheLogger
  public static #29= #26 of #28;          // AllOps=class coursier/util/Monad$AllOps of class coursier/util/Monad
  public static #19= #31 of #28;          // =class coursier/util/Monad$ops$ of class coursier/util/Monad
  public static final #36= #33 of #35;    // Lookup=class java/lang/invoke/MethodHandles$Lookup of class java/lang/invoke/MethodHandles
  public static #19= #38 of #40;          // =class scala/Predef$ArrowAssoc$ of class scala/Predef
Signature: #3                           // <F:Ljava/lang/Object;>Ljava/lang/Object;Lscala/Product;Ljava/io/Serializable;
SourceFile: "Versions.scala"
RuntimeVisibleAnnotations:
  0: #11(#12=s#13)
    scala.reflect.ScalaSignature(
      bytes="\u0006\u0005\rUb\u0001B$I\u0005-C\u0001B\u0019\u0001\u0003\u0006\u0004%\ta\u0019\u0005\to\u0002\u0011\t\u0011)A\u0005I\"A\u0001\u0010\u0001BC\u0002\u0013\u0005\u0011\u0010C\u0005\u0002\n\u0001\u0011\t\u0011)A\u0005u\"Q\u00111\u0002\u0001\u0003\u0006\u0004%\t!!\u0004\t\u0015\u0005m\u0001A!A!\u0002\u0013\ty\u0001\u0003\u0006\u0002\u001e\u0001\u0011)\u0019!C\u0001\u0003?A!\"a\f\u0001\u0005\u0003\u0005\u000b\u0011BA\u0011\u0011)\t\t\u0004\u0001BC\u0002\u0013\u0005\u00111\u0007\u0005\u000b\u0003{\u0001!\u0011!Q\u0001\n\u0005U\u0002BCA \u0001\t\u0015\r\u0011b\u0001\u0002B!Q\u0011q\n\u0001\u0003\u0002\u0003\u0006I!a\u0011\t\u000f\u0005E\u0003\u0001\"\u0001\u0002T!9\u0011\u0011\u000b\u0001\u0005\u0002\u0005\u0015\u0004bBA)\u0001\u0011\u0005\u0011\u0011\u000f\u0005\b\u0003s\u0002A\u0011BA!\u0011\u001d\tY\b\u0001C\u0001\u0003{Bq!!#\u0001\t\u0003\tY\tC\u0004\u0002\u000e\u0002!\t!a$\t\u000f\u0005U\u0005\u0001\"\u0001\u0002\u0018\"9\u0011Q\u0014\u0001\u0005\u0002\u0005}\u0005bBAS\u0001\u0011\u0005\u0011q\u0015\u0005\b\u0003k\u0003A\u0011AA\\\u0011\u001d\tY\f\u0001C\u0005\u0003{Cq!!4\u0001\t\u0003\ty\rC\u0004\u0002T\u0002!\t!!6\t\u000f\te\b\u0001\"\u0001\u0003|\"9!q \u0001\u0005\u0002\r\u0005\u0001bBB\u0003\u0001\u0011\u00051q\u0001\u0005\b\u0007\u0017\u0001A\u0011AB\u0007\u0011\u001d\u0019\t\u0002\u0001C\u0001\u0007\'Aqaa\u0006\u0001\t\u0003\u0019I\u0002C\u0004\u0003\u0018\u0002!\tE!\'\t\u000f\t\u0015\u0006\u0001\"\u0011\u0004\u001e!9!1\u0017\u0001\u0005B\r\u0005\u0002b\u0002B]\u0001\u0011\u0005#1\u0018\u0005\b\u0005\u0007\u0004A\u0011BB\u0013\u0011\u001d\u0011i\r\u0001C!\u0005\u001fDqA!5\u0001\t\u0003\u0012\u0019\u000eC\u0004\u0003V\u0002!\te!\f\t\u000f\tu\u0007\u0001\"\u0011\u00042\u001d9\u0011Q\u001c%\t\u0002\u0005}gAB$I\u0011\u0003\t\t\u000fC\u0004\u0002R-\"\t!!=\t\u000f\u0005M8\u0006\"\u0001\u0002v\"9\u0011q`\u0016\u0005\n\t\u0005\u0001bBAzW\u0011\u0005!1\u0002\u0005\b\u0003g\\C\u0011\u0001B\u0012\u0011\u001d\t\u0019p\u000bC\u0001\u0005\u007f1aAa\u0018,\u0005\t\u0005\u0004B\u0003B2e\t\u0015\r\u0011\"\u0001\u0003f!Q!Q\u0011\u001a\u0003\u0002\u0003\u0006IAa\u001a\t\u000f\u0005E#\u0007\"\u0001\u0003\b\"9\u0011Q\u0015\u001a\u0005\u0002\t=\u0005b\u0002BIe\u0011\u0005!1\u0013\u0005\b\u0005/\u0013D\u0011\tBM\u0011\u001d\u0011)K\rC!\u0005OCqAa-3\t\u0003\u0012)\fC\u0004\u0003:J\"\tEa/\t\u000f\t\r\'\u0007\"\u0003\u0003F\"9!Q\u001a\u001a\u0005B\t=\u0007b\u0002Bie\u0011\u0005#1\u001b\u0005\b\u0005+\u0014D\u0011\tBl\u0011\u001d\u0011iN\rC!\u0005?<qAa9,\u0011\u0003\u0011)OB\u0004\u0003`-B\tAa:\t\u000f\u0005E#\t\"\u0001\u0003j\"9\u00111\u001f\"\u0005\u0002\t-\b\"\u0003Bx\u0005\u0006\u0005I\u0011\u0002By\u0011%\u0011yoKA\u0001\n\u0013\u0011\tP\u0001\u0005WKJ\u001c\u0018n\u001c8t\u0015\u0005I\u0015\u0001C2pkJ\u001c\u0018.\u001a:\u0004\u0001U\u0011Aj[\n\u0005\u00015\u001bf\u000b\u0005\u0002O#6\tqJC\u0001Q\u0003\u0015\u00198-\u00197b\u0013\t\u0011vJ\u0001\u0004B]f\u0014VM\u001a\t\u0003\u001dRK!!V(\u0003\u000fA\u0013x\u000eZ;diB\u0011qk\u0018\b\u00031vs!!\u0017/\u000e\u0003iS!a\u0017&\u0002\rq\u0012xn\u001c;?\u0013\u0005\u0001\u0016B\u00010P\u0003\u001d\u0001\u0018mY6bO\u0016L!\u0001Y1\u0003\u0019M+\'/[1mSj\f\'\r\\3\u000b\u0005y{\u0015!B2bG\",W#\u00013\u0011\u0007\u0015<\u0017.D\u0001g\u0015\t\u0011\u0007*\u0003\u0002iM\n)1)Y2iKB\u0011!n\u001b\u0007\u0001\t\u0015a\u0007A1\u0001n\u0005\u00051UC\u00018v#\ty\'\u000f\u0005\u0002Oa&\u0011\u0011o\u0014\u0002\b\u001d>$\b.\u001b8h!\tq5/\u0003\u0002u\u001f\n\u0019\u0011I\\=\u0005\u000bY\\\'\u0019\u00018\u0003\u0003}\u000baaY1dQ\u0016\u0004\u0013!C7pIVdWm\u00149u+\u0005Q\bc\u0001(|{&\u0011Ap\u0014\u0002\u0007\u001fB$\u0018n\u001c8\u0011\u0007y\f\u0019AD\u0002\u0000\u0003\u0003i\u0011\u0001S\u0005\u0003=\"KA!!\u0002\u0002\b\t1Qj\u001c3vY\u0016T!A\u0018%\u0002\u00155|G-\u001e7f\u001fB$\b%\u0001\u0007sKB|7/\u001b;pe&,7/\u0006\u0002\u0002\u0010A)q+!\u0005\u0002\u0016%\u0019\u00111C1\u0003\u0007M+\u0017\u000fE\u0002\u007f\u0003/IA!!\u0007\u0002\b\tQ!+\u001a9pg&$xN]=\u0002\u001bI,\u0007o\\:ji>\u0014\u0018.Z:!\u0003=i\u0017N\u001d:pe\u000e{gN\u001a$jY\u0016\u001cXCAA\u0011!\u00159\u0016\u0011CA\u0012!\u0011\t)#a\u000b\u000e\u0005\u0005\u001d\"bAA\u0015\u0011\u00061\u0001/\u0019:b[NLA!!\f\u0002(\tqQ*\u001b:s_J\u001cuN\u001c4GS2,\u0017\u0001E7jeJ|\'oQ8oM\u001aKG.Z:!\u0003\u001di\u0017N\u001d:peN,\"!!\u000e\u0011\u000b]\u000b\t\"a\u000e\u0011\t\u0005\u0015\u0012\u0011H\u0005\u0005\u0003w\t9C\u0001\u0004NSJ\u0014xN]\u0001\t[&\u0014(o\u001c:tA\u0005!1/\u001f8d+\t\t\u0019\u0005E\u0003\u0002F\u0005-\u0013.\u0004\u0002\u0002H)\u0019\u0011\u0011\n%\u0002\tU$\u0018\u000e\\\u0005\u0005\u0003\u001b\n9E\u0001\u0003Ts:\u001c\u0017!B:z]\u000e\u0004\u0013A\u0002\u001fj]&$h\b\u0006\u0007\u0002V\u0005m\u0013QLA0\u0003C\n\u0019\u0007\u0006\u0003\u0002X\u0005e\u0003cA@\u0001S\"9\u0011qH\u0007A\u0004\u0005\r\u0003\"\u00022\u000e\u0001\u0004!\u0007\"\u0002=\u000e\u0001\u0004Q\bbBA\u0006\u001b\u0001\u0007\u0011q\u0002\u0005\b\u0003;i\u0001\u0019AA\u0011\u0011\u001d\t\t$\u0004a\u0001\u0003k!\u0002\"a\u001a\u0002l\u00055\u0014q\u000e\u000b\u0005\u0003/\nI\u0007C\u0004\u0002@9\u0001\u001d!a\u0011\t\u000b\tt\u0001\u0019\u00013\t\u000bat\u0001\u0019\u0001>\t\u000f\u0005-a\u00021\u0001\u0002\u0010Q!\u00111OA<)\u0011\t9&!\u001e\t\u000f\u0005}r\u0002q\u0001\u0002D!)!m\u0004a\u0001I\u0006\ta)A\bbI\u0012\u0014V\r]8tSR|\'/[3t)\u0011\t9&a \t\u000f\u0005\u0005\u0015\u00031\u0001\u0002\u0004\u0006Q!/\u001a9pg&$xN]=\u0011\u000b9\u000b))!\u0006\n\u0007\u0005\u001duJ\u0001\u0006=e\u0016\u0004X-\u0019;fIz\n\u0011B\\8NSJ\u0014xN]:\u0016\u0005\u0005]\u0013AC1eI6K\'O]8sgR!\u0011qKAI\u0011\u001d\t\td\u0005a\u0001\u0003\'\u0003RATAC\u0003o\t!#\u00193e\u001b&\u0014(o\u001c:D_:4g)\u001b7fgR!\u0011qKAM\u0011\u001d\ti\u0002\u0006a\u0001\u00037\u0003RATAC\u0003G\t!b^5uQ6{G-\u001e7f)\u0011\t9&!)\t\r\u0005\rV\u00031\u0001~\u0003\u0019iw\u000eZ;mK\u0006Aa/\u001a:tS>t7\u000f\u0006\u0002\u0002*B!!n[AV!\u0011\ti+a-\u000e\u0005\u0005=&bAAY\u0011\u0006!1m\u001c:f\u0013\r9\u0015qV\u0001\u0012M&t\u0017\r\u001c*fa>\u001c\u0018\u000e^8sS\u0016\u001cXCAA]!\u0011Q7.a\u0004\u0002\u0017\u0005dG.T5se>\u00148\u000fM\u000b\u0003\u0003\u007f\u0003b!!1\u0002L\u0006]RBAAb\u0015\u0011\t)-a2\u0002\u0013%lW.\u001e;bE2,\'bAAe\u001f\u0006Q1m\u001c7mK\u000e$\u0018n\u001c8\n\t\u0005M\u00111Y\u0001\u000bC2dW*\u001b:s_J\u001cXCAAi!\u0011Q7.!\u000e\u0002\rI,7/\u001e7u)\t\t9\u000e\u0005\u0003kW\u0006e\u0007cAAne9\u0011qPK\u0001\t-\u0016\u00148/[8ogB\u0011qpK\n\u0005W5\u000b\u0019\u000f\u0005\u0003\u0002f\u0006=XBAAt\u0015\u0011\tI/a;\u0002\u0005%|\'BAAw\u0003\u0011Q\u0017M^1\n\u0007\u0001\f9\u000f\u0006\u0002\u0002`\u0006)\u0011\r\u001d9msR\u0011\u0011q\u001f\t\u0005\u007f\u0002\tI\u0010\u0005\u0003\u0002F\u0005m\u0018\u0002BA\u007f\u0003\u000f\u0012A\u0001V1tW\u0006)Q.\u001a:hKR!\u00111\u0016B\u0002\u0011\u001d\t)K\fa\u0001\u0005\u000b\u0001Ra\u0016B\u0004\u0003WK1A!\u0003b\u0005\u00191Vm\u0019;peV!!Q\u0002B\u000b)\u0011\u0011yAa\b\u0015\t\tE!1\u0004\t\u0005\u007f\u0002\u0011\u0019\u0002E\u0002k\u0005+!a\u0001\\\u0018C\u0002\t]Qc\u00018\u0003\u001a\u00111aO!\u0006C\u00029Dq!a\u00100\u0001\b\u0011i\u0002\u0005\u0004\u0002F\u0005-#1\u0003\u0005\u0007E>\u0002\rA!\t\u0011\t\u0015<\'1C\u000b\u0005\u0005K\u0011i\u0003\u0006\u0005\u0003(\t]\"1\bB\u001f)\u0011\u0011ICa\r\u0011\t}\u0004!1\u0006\t\u0004U\n5BA\u000271\u0005\u0004\u0011y#F\u0002o\u0005c!aA\u001eB\u0017\u0005\u0004q\u0007bBA a\u0001\u000f!Q\u0007\t\u0007\u0003\u000b\nYEa\u000b\t\r\t\u0004\u0004\u0019\u0001B\u001d!\u0011)wMa\u000b\t\u000ba\u0004\u0004\u0019\u0001>\t\u000f\u0005-\u0001\u00071\u0001\u0002\u0010U!!\u0011\tB%)1\u0011\u0019Ea\u0015\u0003X\te#1\fB/)\u0011\u0011)Ea\u0014\u0011\t}\u0004!q\t\t\u0004U\n%CA\u000272\u0005\u0004\u0011Y%F\u0002o\u0005\u001b\"aA\u001eB%\u0005\u0004q\u0007bBA c\u0001\u000f!\u0011\u000b\t\u0007\u0003\u000b\nYEa\u0012\t\r\t\f\u0004\u0019\u0001B+!\u0011)wMa\u0012\t\u000ba\f\u0004\u0019\u0001>\t\u000f\u0005-\u0011\u00071\u0001\u0002\u0010!9\u0011QD\u0019A\u0002\u0005\u0005\u0002bBA\u0019c\u0001\u0007\u0011Q\u0007\u0002\u0007%\u0016\u001cX\u000f\u001c;\u0014\tIj5KV\u0001\be\u0016\u001cX\u000f\u001c;t+\t\u00119\u0007E\u0003X\u0003#\u0011I\u0007E\u0004O\u0005W\n)Ba\u001c\n\u0007\t5tJ\u0001\u0004UkBdWM\r\t\b/\nE$QOAV\u0013\r\u0011\u0019(\u0019\u0002\u0007\u000b&$\b.\u001a:\u0011\t\t]$q\u0010\b\u0005\u0005s\u0012Y\b\u0005\u0002Z\u001f&\u0019!QP(\u0002\rA\u0013X\rZ3g\u0013\u0011\u0011\tIa!\u0003\rM#(/\u001b8h\u0015\r\u0011ihT\u0001\te\u0016\u001cX\u000f\u001c;tAQ!!\u0011\u0012BG!\r\u0011YIM\u0007\u0002W!9!1M\u001bA\u0002\t\u001dTCAAV\u0003-9\u0018\u000e\u001e5SKN,H\u000e^:\u0015\t\t%%Q\u0013\u0005\b\u0005G:\u0004\u0019\u0001B4\u0003!!xn\u0015;sS:<GC\u0001BN!\u0011\u0011iJa)\u000e\u0005\t}%\u0002\u0002BQ\u0003W\fA\u0001\\1oO&!!\u0011\u0011BP\u0003!\u0019\u0017M\\#rk\u0006dG\u0003\u0002BU\u0005_\u00032A\u0014BV\u0013\r\u0011ik\u0014\u0002\b\u0005>|G.Z1o\u0011\u0019\u0011\t,\u000fa\u0001e\u0006\u0019qN\u00196\u0002\r\u0015\fX/\u00197t)\u0011\u0011IKa.\t\r\tE&\b1\u0001s\u0003!A\u0017m\u001d5D_\u0012,GC\u0001B_!\rq%qX\u0005\u0004\u0005\u0003|%aA%oi\u0006)A/\u001e9mKV\u0011!q\u0019\t\u0006\u001d\n%\'qM\u0005\u0004\u0005\u0017|%A\u0002+va2,\u0017\'A\u0007qe>$Wo\u0019;Qe\u00164\u0017\u000e_\u000b\u0003\u00057\u000bA\u0002\u001d:pIV\u001cG/\u0011:jif,\"A!0\u0002\u001dA\u0014x\u000eZ;di\u0016cW-\\3oiR\u0019!O!7\t\u000f\tmw\b1\u0001\u0003>\u0006\ta.\u0001\nqe>$Wo\u0019;FY\u0016lWM\u001c;OC6,G\u0003\u0002BN\u0005CDqAa7A\u0001\u0004\u0011i,\u0001\u0004SKN,H\u000e\u001e\t\u0004\u0005\u0017\u00135\u0003\u0002\"N\u0003G$\"A!:\u0015\t\t%%Q\u001e\u0005\b\u0005G\"\u0005\u0019\u0001B4\u000319(/\u001b;f%\u0016\u0004H.Y2f)\t\u0011\u0019\u0010\u0005\u0003\u0003\u001e\nU\u0018\u0002\u0002B|\u0005?\u0013aa\u00142kK\u000e$\u0018!C<ji\"\u001c\u0015m\u00195f)\u0011\t9F!@\t\u000b\t\\\u0002\u0019\u00013\u0002\u001b]LG\u000f[\'pIVdWm\u00149u)\u0011\t9fa\u0001\t\u000bad\u0002\u0019\u0001>\u0002!]LG\u000f\u001b*fa>\u001c\u0018\u000e^8sS\u0016\u001cH\u0003BA,\u0007\u0013Aq!a\u0003\u001e\u0001\u0004\ty!A\nxSRDW*\u001b:s_J\u001cuN\u001c4GS2,7\u000f\u0006\u0003\u0002X\r=\u0001bBA\u000f=\u0001\u0007\u0011\u0011E\u0001\fo&$\b.T5se>\u00148\u000f\u0006\u0003\u0002X\rU\u0001bBA\u0019?\u0001\u0007\u0011QG\u0001\to&$\bnU=oGR!\u0011qKB\u000e\u0011\u001d\ty\u0004\ta\u0001\u0003\u0007\"BA!+\u0004 !1!\u0011\u0017\u0012A\u0002I$BA!+\u0004$!1!\u0011W\u0012A\u0002I,\"aa\n\u0011\u001b9\u001bI\u0003\u001a>\u0002\u0010\u0005\u0005\u0012QGA\"\u0013\r\u0019Yc\u0014\u0002\u0007)V\u0004H.\u001a\u001c\u0015\u0007I\u001cy\u0003C\u0004\u0003\\\"\u0002\rA!0\u0015\t\tm51\u0007\u0005\b\u00057L\u0003\u0019\u0001B_\u0001"
    )
BootstrapMethods:
  0: #199 REF_invokeStatic java/lang/invoke/LambdaMetafactory.altMetafactory:(Ljava/lang/invoke/MethodHandles$Lookup;Ljava/lang/String;Ljava/lang/invoke/MethodType;[Ljava/lang/Object;)Ljava/lang/invoke/CallSite;
    Method arguments:
      #184 (Ljava/lang/Object;)Ljava/lang/Object;
      #189 REF_invokeStatic coursier/Versions.$anonfun$versions$1:(Lcoursier/Versions$Result;)Lcoursier/core/Versions;
      #190 (Lcoursier/Versions$Result;)Lcoursier/core/Versions;
      #191 5
      #192 1
      #190 (Lcoursier/Versions$Result;)Lcoursier/core/Versions;
  1: #199 REF_invokeStatic java/lang/invoke/LambdaMetafactory.altMetafactory:(Ljava/lang/invoke/MethodHandles$Lookup;Ljava/lang/String;Ljava/lang/invoke/MethodType;[Ljava/lang/Object;)Ljava/lang/invoke/CallSite;
    Method arguments:
      #184 (Ljava/lang/Object;)Ljava/lang/Object;
      #215 REF_invokeStatic coursier/Versions.$anonfun$finalRepositories$1:(Lcoursier/Versions;Lscala/collection/immutable/Seq;)Lscala/collection/immutable/Seq;
      #217 (Lscala/collection/immutable/Seq;)Lscala/collection/immutable/Seq;
      #191 5
      #192 1
      #217 (Lscala/collection/immutable/Seq;)Lscala/collection/immutable/Seq;
  2: #199 REF_invokeStatic java/lang/invoke/LambdaMetafactory.altMetafactory:(Ljava/lang/invoke/MethodHandles$Lookup;Ljava/lang/String;Ljava/lang/invoke/MethodType;[Ljava/lang/Object;)Ljava/lang/invoke/CallSite;
    Method arguments:
      #184 (Ljava/lang/Object;)Ljava/lang/Object;
      #226 REF_invokeStatic coursier/Versions.$anonfun$allMirrors0$1:(Lcoursier/params/MirrorConfFile;)Lscala/collection/immutable/Seq;
      #227 (Lcoursier/params/MirrorConfFile;)Lscala/collection/immutable/Seq;
      #191 5
      #192 1
      #227 (Lcoursier/params/MirrorConfFile;)Lscala/collection/immutable/Seq;
  3: #199 REF_invokeStatic java/lang/invoke/LambdaMetafactory.altMetafactory:(Ljava/lang/invoke/MethodHandles$Lookup;Ljava/lang/String;Ljava/lang/invoke/MethodType;[Ljava/lang/Object;)Ljava/lang/invoke/CallSite;
    Method arguments:
      #236 ()Ljava/lang/Object;
      #241 REF_invokeStatic coursier/Versions.$anonfun$allMirrors$1:(Lcoursier/Versions;)Lscala/collection/immutable/Seq;
      #242 ()Lscala/collection/immutable/Seq;
      #191 5
      #192 1
      #242 ()Lscala/collection/immutable/Seq;
  4: #199 REF_invokeStatic java/lang/invoke/LambdaMetafactory.altMetafactory:(Ljava/lang/invoke/MethodHandles$Lookup;Ljava/lang/String;Ljava/lang/invoke/MethodType;[Ljava/lang/Object;)Ljava/lang/invoke/CallSite;
    Method arguments:
      #184 (Ljava/lang/Object;)Ljava/lang/Object;
      #258 REF_invokeStatic coursier/Versions.$anonfun$result$1:(Lcoursier/Versions;Lscala/collection/immutable/Seq;)Ljava/lang/Object;
      #260 (Lscala/collection/immutable/Seq;)Ljava/lang/Object;
      #191 5
      #192 1
      #260 (Lscala/collection/immutable/Seq;)Ljava/lang/Object;
  5: #199 REF_invokeStatic java/lang/invoke/LambdaMetafactory.altMetafactory:(Ljava/lang/invoke/MethodHandles$Lookup;Ljava/lang/String;Ljava/lang/invoke/MethodType;[Ljava/lang/Object;)Ljava/lang/invoke/CallSite;
    Method arguments:
      #236 ()Ljava/lang/Object;
      #273 REF_invokeStatic coursier/Versions.$anonfun$result$6:(Ljava/lang/Object;)Ljava/lang/Object;
      #236 ()Ljava/lang/Object;
      #192 1
  6: #199 REF_invokeStatic java/lang/invoke/LambdaMetafactory.altMetafactory:(Ljava/lang/invoke/MethodHandles$Lookup;Ljava/lang/String;Ljava/lang/invoke/MethodType;[Ljava/lang/Object;)Ljava/lang/invoke/CallSite;
    Method arguments:
      #184 (Ljava/lang/Object;)Ljava/lang/Object;
      #281 REF_invokeStatic coursier/Versions.$anonfun$result$7:(Lcoursier/Versions;Ljava/lang/Object;Lcoursier/cache/CacheLogger;)Ljava/lang/Object;
      #283 (Lcoursier/cache/CacheLogger;)Ljava/lang/Object;
      #191 5
      #192 1
      #283 (Lcoursier/cache/CacheLogger;)Ljava/lang/Object;
  7: #199 REF_invokeStatic java/lang/invoke/LambdaMetafactory.altMetafactory:(Ljava/lang/invoke/MethodHandles$Lookup;Ljava/lang/String;Ljava/lang/invoke/MethodType;[Ljava/lang/Object;)Ljava/lang/invoke/CallSite;
    Method arguments:
      #184 (Ljava/lang/Object;)Ljava/lang/Object;
      #297 REF_invokeStatic coursier/Versions.$anonfun$result$8:(Lscala/collection/immutable/Seq;)Lcoursier/Versions$Result;
      #298 (Lscala/collection/immutable/Seq;)Lcoursier/Versions$Result;
      #191 5
      #192 1
      #298 (Lscala/collection/immutable/Seq;)Lcoursier/Versions$Result;
  8: #199 REF_invokeStatic java/lang/invoke/LambdaMetafactory.altMetafactory:(Ljava/lang/invoke/MethodHandles$Lookup;Ljava/lang/String;Ljava/lang/invoke/MethodType;[Ljava/lang/Object;)Ljava/lang/invoke/CallSite;
    Method arguments:
      #184 (Ljava/lang/Object;)Ljava/lang/Object;
      #445 REF_invokeStatic coursier/Versions.$anonfun$result$5:(Lscala/Tuple2;)Lcoursier/core/Versions;
      #446 (Lscala/Tuple2;)Lcoursier/core/Versions;
      #191 5
      #192 1
      #446 (Lscala/Tuple2;)Lcoursier/core/Versions;
  9: #199 REF_invokeStatic java/lang/invoke/LambdaMetafactory.altMetafactory:(Ljava/lang/invoke/MethodHandles$Lookup;Ljava/lang/String;Ljava/lang/invoke/MethodType;[Ljava/lang/Object;)Ljava/lang/invoke/CallSite;
    Method arguments:
      #184 (Ljava/lang/Object;)Ljava/lang/Object;
      #478 REF_invokeStatic coursier/Versions.$anonfun$result$4:(Lcoursier/core/Repository;Lscala/util/Either;)Lscala/Tuple2;
      #480 (Lscala/util/Either;)Lscala/Tuple2;
      #191 5
      #192 1
      #480 (Lscala/util/Either;)Lscala/Tuple2;
  10: #199 REF_invokeStatic java/lang/invoke/LambdaMetafactory.altMetafactory:(Ljava/lang/invoke/MethodHandles$Lookup;Ljava/lang/String;Ljava/lang/invoke/MethodType;[Ljava/lang/Object;)Ljava/lang/invoke/CallSite;
    Method arguments:
      #184 (Ljava/lang/Object;)Ljava/lang/Object;
      #490 REF_invokeStatic coursier/Versions.$anonfun$result$3:(Lcoursier/Versions;Lcoursier/core/Module;Lcoursier/core/Repository;)Ljava/lang/Object;
      #492 (Lcoursier/core/Repository;)Ljava/lang/Object;
      #191 5
      #192 1
      #492 (Lcoursier/core/Repository;)Ljava/lang/Object;
  11: #199 REF_invokeStatic java/lang/invoke/LambdaMetafactory.altMetafactory:(Ljava/lang/invoke/MethodHandles$Lookup;Ljava/lang/String;Ljava/lang/invoke/MethodType;[Ljava/lang/Object;)Ljava/lang/invoke/CallSite;
    Method arguments:
      #184 (Ljava/lang/Object;)Ljava/lang/Object;
      #513 REF_invokeStatic coursier/Versions.$anonfun$result$2:(Lcoursier/Versions;Lscala/collection/immutable/Seq;Lcoursier/core/Module;)Lscala/collection/immutable/Seq;
      #515 (Lcoursier/core/Module;)Lscala/collection/immutable/Seq;
      #191 5
      #192 1
      #515 (Lcoursier/core/Module;)Lscala/collection/immutable/Seq;
  12: #574 REF_invokeStatic scala/runtime/LambdaDeserialize.bootstrap:(Ljava/lang/invoke/MethodHandles$Lookup;Ljava/lang/String;Ljava/lang/invoke/MethodType;[Ljava/lang/invoke/MethodHandle;)Ljava/lang/invoke/CallSite;
    Method arguments:
      #241 REF_invokeStatic coursier/Versions.$anonfun$allMirrors$1:(Lcoursier/Versions;)Lscala/collection/immutable/Seq;
      #226 REF_invokeStatic coursier/Versions.$anonfun$allMirrors0$1:(Lcoursier/params/MirrorConfFile;)Lscala/collection/immutable/Seq;
      #215 REF_invokeStatic coursier/Versions.$anonfun$finalRepositories$1:(Lcoursier/Versions;Lscala/collection/immutable/Seq;)Lscala/collection/immutable/Seq;
      #258 REF_invokeStatic coursier/Versions.$anonfun$result$1:(Lcoursier/Versions;Lscala/collection/immutable/Seq;)Ljava/lang/Object;
      #513 REF_invokeStatic coursier/Versions.$anonfun$result$2:(Lcoursier/Versions;Lscala/collection/immutable/Seq;Lcoursier/core/Module;)Lscala/collection/immutable/Seq;
      #490 REF_invokeStatic coursier/Versions.$anonfun$result$3:(Lcoursier/Versions;Lcoursier/core/Module;Lcoursier/core/Repository;)Ljava/lang/Object;
      #478 REF_invokeStatic coursier/Versions.$anonfun$result$4:(Lcoursier/core/Repository;Lscala/util/Either;)Lscala/Tuple2;
      #445 REF_invokeStatic coursier/Versions.$anonfun$result$5:(Lscala/Tuple2;)Lcoursier/core/Versions;
      #273 REF_invokeStatic coursier/Versions.$anonfun$result$6:(Ljava/lang/Object;)Ljava/lang/Object;
      #281 REF_invokeStatic coursier/Versions.$anonfun$result$7:(Lcoursier/Versions;Ljava/lang/Object;Lcoursier/cache/CacheLogger;)Ljava/lang/Object;
      #297 REF_invokeStatic coursier/Versions.$anonfun$result$8:(Lscala/collection/immutable/Seq;)Lcoursier/Versions$Result;
      #189 REF_invokeStatic coursier/Versions.$anonfun$versions$1:(Lcoursier/Versions$Result;)Lcoursier/core/Versions;
  ScalaInlineInfo: length = 0xF9 (unknown attribute)
   01 01 00 31 00 EF 00 F0 01 00 E0 00 E1 01 00 D5
   00 D6 01 01 00 01 01 01 01 E6 01 E7 01 01 CD 01
   CE 01 01 AE 01 AF 01 01 A3 01 A4 01 01 10 00 B9
   01 01 17 01 18 01 01 27 01 28 01 00 BB 00 BC 01
   00 A3 02 2E 01 00 A3 02 24 01 00 A3 01 36 01 00
   76 00 72 01 00 99 00 7A 01 00 95 00 7A 01 00 79
   00 7A 01 00 D2 00 AD 01 00 DF 00 68 01 00 2B 00
   60 01 01 58 01 59 01 01 5B 01 59 01 00 D1 00 AD
   01 01 61 01 62 01 00 34 00 68 01 00 36 00 68 01
   00 2E 00 64 01 00 88 00 4E 01 01 76 01 62 01 01
   77 01 78 01 01 84 01 85 01 00 5B 00 53 01 00 52
   00 53 01 01 75 01 3E 01 00 31 00 68 01 00 B2 00
   AD 01 00 38 00 72 01 01 3D 01 3E 01 01 6D 01 6E
   01 00 AC 00 AD 01 01 31 01 32 01 00 92 00 7A 01
   00 8F 00 7A 01 00 9D 00 9E 01 00 A7 00 A8 01 00
   85 00 7A 01 01 3A 01 3B 01
  ScalaSig: length = 0x3 (unknown attribute)
   05 02 00
