Classfile /Users/mw/Projects/slang-braindump/.jar/jar8/assemble/slang-braindump/assemble/content/org/apache/commons/io/filefilter/RegexFileFilter.class
  Last modified May 29, 2022; size 1893 bytes
  SHA-256 checksum 2e0f79b377a01f1d07bbde94556f7c1d16632c723fcf6d5ebc9509f395953a2d
  Compiled from "RegexFileFilter.java"
public class org.apache.commons.io.filefilter.RegexFileFilter extends org.apache.commons.io.filefilter.AbstractFileFilter implements java.io.Serializable
  minor version: 0
  major version: 52
  flags: (0x0021) ACC_PUBLIC, ACC_SUPER
  this_class: #12                         // org/apache/commons/io/filefilter/RegexFileFilter
  super_class: #13                        // org/apache/commons/io/filefilter/AbstractFileFilter
  interfaces: 1, fields: 2, methods: 5, attributes: 1
Constant pool:
   #1 = Methodref          #13.#49        // org/apache/commons/io/filefilter/AbstractFileFilter."<init>":()V
   #2 = Class              #50            // java/lang/IllegalArgumentException
   #3 = String             #51            // Pattern is missing
   #4 = Methodref          #2.#52         // java/lang/IllegalArgumentException."<init>":(Ljava/lang/String;)V
   #5 = Methodref          #8.#53         // java/util/regex/Pattern.compile:(Ljava/lang/String;)Ljava/util/regex/Pattern;
   #6 = Fieldref           #12.#54        // org/apache/commons/io/filefilter/RegexFileFilter.pattern:Ljava/util/regex/Pattern;
   #7 = Methodref          #55.#56        // org/apache/commons/io/IOCase.isCaseSensitive:()Z
   #8 = Class              #57            // java/util/regex/Pattern
   #9 = Methodref          #8.#58         // java/util/regex/Pattern.compile:(Ljava/lang/String;I)Ljava/util/regex/Pattern;
  #10 = Methodref          #8.#59         // java/util/regex/Pattern.matcher:(Ljava/lang/CharSequence;)Ljava/util/regex/Matcher;
  #11 = Methodref          #60.#61        // java/util/regex/Matcher.matches:()Z
  #12 = Class              #62            // org/apache/commons/io/filefilter/RegexFileFilter
  #13 = Class              #63            // org/apache/commons/io/filefilter/AbstractFileFilter
  #14 = Class              #64            // java/io/Serializable
  #15 = Utf8               serialVersionUID
  #16 = Utf8               J
  #17 = Utf8               ConstantValue
  #18 = Long               4269646126155225062l
  #20 = Utf8               pattern
  #21 = Utf8               Ljava/util/regex/Pattern;
  #22 = Utf8               <init>
  #23 = Utf8               (Ljava/lang/String;)V
  #24 = Utf8               Code
  #25 = Utf8               LineNumberTable
  #26 = Utf8               LocalVariableTable
  #27 = Utf8               this
  #28 = Utf8               Lorg/apache/commons/io/filefilter/RegexFileFilter;
  #29 = Utf8               Ljava/lang/String;
  #30 = Utf8               StackMapTable
  #31 = Class              #62            // org/apache/commons/io/filefilter/RegexFileFilter
  #32 = Class              #65            // java/lang/String
  #33 = Utf8               (Ljava/lang/String;Lorg/apache/commons/io/IOCase;)V
  #34 = Utf8               caseSensitivity
  #35 = Utf8               Lorg/apache/commons/io/IOCase;
  #36 = Utf8               flags
  #37 = Utf8               I
  #38 = Class              #66            // org/apache/commons/io/IOCase
  #39 = Utf8               (Ljava/lang/String;I)V
  #40 = Utf8               (Ljava/util/regex/Pattern;)V
  #41 = Class              #57            // java/util/regex/Pattern
  #42 = Utf8               accept
  #43 = Utf8               (Ljava/io/File;Ljava/lang/String;)Z
  #44 = Utf8               dir
  #45 = Utf8               Ljava/io/File;
  #46 = Utf8               name
  #47 = Utf8               SourceFile
  #48 = Utf8               RegexFileFilter.java
  #49 = NameAndType        #22:#67        // "<init>":()V
  #50 = Utf8               java/lang/IllegalArgumentException
  #51 = Utf8               Pattern is missing
  #52 = NameAndType        #22:#23        // "<init>":(Ljava/lang/String;)V
  #53 = NameAndType        #68:#69        // compile:(Ljava/lang/String;)Ljava/util/regex/Pattern;
  #54 = NameAndType        #20:#21        // pattern:Ljava/util/regex/Pattern;
  #55 = Class              #66            // org/apache/commons/io/IOCase
  #56 = NameAndType        #70:#71        // isCaseSensitive:()Z
  #57 = Utf8               java/util/regex/Pattern
  #58 = NameAndType        #68:#72        // compile:(Ljava/lang/String;I)Ljava/util/regex/Pattern;
  #59 = NameAndType        #73:#74        // matcher:(Ljava/lang/CharSequence;)Ljava/util/regex/Matcher;
  #60 = Class              #75            // java/util/regex/Matcher
  #61 = NameAndType        #76:#71        // matches:()Z
  #62 = Utf8               org/apache/commons/io/filefilter/RegexFileFilter
  #63 = Utf8               org/apache/commons/io/filefilter/AbstractFileFilter
  #64 = Utf8               java/io/Serializable
  #65 = Utf8               java/lang/String
  #66 = Utf8               org/apache/commons/io/IOCase
  #67 = Utf8               ()V
  #68 = Utf8               compile
  #69 = Utf8               (Ljava/lang/String;)Ljava/util/regex/Pattern;
  #70 = Utf8               isCaseSensitive
  #71 = Utf8               ()Z
  #72 = Utf8               (Ljava/lang/String;I)Ljava/util/regex/Pattern;
  #73 = Utf8               matcher
  #74 = Utf8               (Ljava/lang/CharSequence;)Ljava/util/regex/Matcher;
  #75 = Utf8               java/util/regex/Matcher
  #76 = Utf8               matches
{
  private static final long serialVersionUID;
    descriptor: J
    flags: (0x001a) ACC_PRIVATE, ACC_STATIC, ACC_FINAL
    ConstantValue: long 4269646126155225062l

  private final java.util.regex.Pattern pattern;
    descriptor: Ljava/util/regex/Pattern;
    flags: (0x0012) ACC_PRIVATE, ACC_FINAL

  public org.apache.commons.io.filefilter.RegexFileFilter(java.lang.String);
    descriptor: (Ljava/lang/String;)V
    flags: (0x0001) ACC_PUBLIC
    Code:
      stack=3, locals=2, args_size=2
         0: aload_0
         1: invokespecial #1                  // Method org/apache/commons/io/filefilter/AbstractFileFilter."<init>":()V
         4: aload_1
         5: ifnonnull     18
         8: new           #2                  // class java/lang/IllegalArgumentException
        11: dup
        12: ldc           #3                  // String Pattern is missing
        14: invokespecial #4                  // Method java/lang/IllegalArgumentException."<init>":(Ljava/lang/String;)V
        17: athrow
        18: aload_0
        19: aload_1
        20: invokestatic  #5                  // Method java/util/regex/Pattern.compile:(Ljava/lang/String;)Ljava/util/regex/Pattern;
        23: putfield      #6                  // Field pattern:Ljava/util/regex/Pattern;
        26: return
      LineNumberTable:
        line 56: 0
        line 57: 4
        line 58: 8
        line 61: 18
        line 62: 26
      LocalVariableTable:
        Start  Length  Slot  Name   Signature
            0      27     0  this   Lorg/apache/commons/io/filefilter/RegexFileFilter;
            0      27     1 pattern   Ljava/lang/String;
      StackMapTable: number_of_entries = 1
        frame_type = 255 /* full_frame */
          offset_delta = 18
          locals = [ class org/apache/commons/io/filefilter/RegexFileFilter, class java/lang/String ]
          stack = []

  public org.apache.commons.io.filefilter.RegexFileFilter(java.lang.String, org.apache.commons.io.IOCase);
    descriptor: (Ljava/lang/String;Lorg/apache/commons/io/IOCase;)V
    flags: (0x0001) ACC_PUBLIC
    Code:
      stack=3, locals=4, args_size=3
         0: aload_0
         1: invokespecial #1                  // Method org/apache/commons/io/filefilter/AbstractFileFilter."<init>":()V
         4: aload_1
         5: ifnonnull     18
         8: new           #2                  // class java/lang/IllegalArgumentException
        11: dup
        12: ldc           #3                  // String Pattern is missing
        14: invokespecial #4                  // Method java/lang/IllegalArgumentException."<init>":(Ljava/lang/String;)V
        17: athrow
        18: iconst_0
        19: istore_3
        20: aload_2
        21: ifnull        33
        24: aload_2
        25: invokevirtual #7                  // Method org/apache/commons/io/IOCase.isCaseSensitive:()Z
        28: ifne          33
        31: iconst_2
        32: istore_3
        33: aload_0
        34: aload_1
        35: iload_3
        36: invokestatic  #9                  // Method java/util/regex/Pattern.compile:(Ljava/lang/String;I)Ljava/util/regex/Pattern;
        39: putfield      #6                  // Field pattern:Ljava/util/regex/Pattern;
        42: return
      LineNumberTable:
        line 71: 0
        line 72: 4
        line 73: 8
        line 75: 18
        line 76: 20
        line 77: 31
        line 79: 33
        line 80: 42
      LocalVariableTable:
        Start  Length  Slot  Name   Signature
            0      43     0  this   Lorg/apache/commons/io/filefilter/RegexFileFilter;
            0      43     1 pattern   Ljava/lang/String;
            0      43     2 caseSensitivity   Lorg/apache/commons/io/IOCase;
           20      23     3 flags   I
      StackMapTable: number_of_entries = 2
        frame_type = 255 /* full_frame */
          offset_delta = 18
          locals = [ class org/apache/commons/io/filefilter/RegexFileFilter, class java/lang/String, class org/apache/commons/io/IOCase ]
          stack = []
        frame_type = 252 /* append */
          offset_delta = 14
          locals = [ int ]

  public org.apache.commons.io.filefilter.RegexFileFilter(java.lang.String, int);
    descriptor: (Ljava/lang/String;I)V
    flags: (0x0001) ACC_PUBLIC
    Code:
      stack=3, locals=3, args_size=3
         0: aload_0
         1: invokespecial #1                  // Method org/apache/commons/io/filefilter/AbstractFileFilter."<init>":()V
         4: aload_1
         5: ifnonnull     18
         8: new           #2                  // class java/lang/IllegalArgumentException
        11: dup
        12: ldc           #3                  // String Pattern is missing
        14: invokespecial #4                  // Method java/lang/IllegalArgumentException."<init>":(Ljava/lang/String;)V
        17: athrow
        18: aload_0
        19: aload_1
        20: iload_2
        21: invokestatic  #9                  // Method java/util/regex/Pattern.compile:(Ljava/lang/String;I)Ljava/util/regex/Pattern;
        24: putfield      #6                  // Field pattern:Ljava/util/regex/Pattern;
        27: return
      LineNumberTable:
        line 89: 0
        line 90: 4
        line 91: 8
        line 93: 18
        line 94: 27
      LocalVariableTable:
        Start  Length  Slot  Name   Signature
            0      28     0  this   Lorg/apache/commons/io/filefilter/RegexFileFilter;
            0      28     1 pattern   Ljava/lang/String;
            0      28     2 flags   I
      StackMapTable: number_of_entries = 1
        frame_type = 255 /* full_frame */
          offset_delta = 18
          locals = [ class org/apache/commons/io/filefilter/RegexFileFilter, class java/lang/String, int ]
          stack = []

  public org.apache.commons.io.filefilter.RegexFileFilter(java.util.regex.Pattern);
    descriptor: (Ljava/util/regex/Pattern;)V
    flags: (0x0001) ACC_PUBLIC
    Code:
      stack=3, locals=2, args_size=2
         0: aload_0
         1: invokespecial #1                  // Method org/apache/commons/io/filefilter/AbstractFileFilter."<init>":()V
         4: aload_1
         5: ifnonnull     18
         8: new           #2                  // class java/lang/IllegalArgumentException
        11: dup
        12: ldc           #3                  // String Pattern is missing
        14: invokespecial #4                  // Method java/lang/IllegalArgumentException."<init>":(Ljava/lang/String;)V
        17: athrow
        18: aload_0
        19: aload_1
        20: putfield      #6                  // Field pattern:Ljava/util/regex/Pattern;
        23: return
      LineNumberTable:
        line 102: 0
        line 103: 4
        line 104: 8
        line 107: 18
        line 108: 23
      LocalVariableTable:
        Start  Length  Slot  Name   Signature
            0      24     0  this   Lorg/apache/commons/io/filefilter/RegexFileFilter;
            0      24     1 pattern   Ljava/util/regex/Pattern;
      StackMapTable: number_of_entries = 1
        frame_type = 255 /* full_frame */
          offset_delta = 18
          locals = [ class org/apache/commons/io/filefilter/RegexFileFilter, class java/util/regex/Pattern ]
          stack = []

  public boolean accept(java.io.File, java.lang.String);
    descriptor: (Ljava/io/File;Ljava/lang/String;)Z
    flags: (0x0001) ACC_PUBLIC
    Code:
      stack=2, locals=3, args_size=3
         0: aload_0
         1: getfield      #6                  // Field pattern:Ljava/util/regex/Pattern;
         4: aload_2
         5: invokevirtual #10                 // Method java/util/regex/Pattern.matcher:(Ljava/lang/CharSequence;)Ljava/util/regex/Matcher;
         8: invokevirtual #11                 // Method java/util/regex/Matcher.matches:()Z
        11: ireturn
      LineNumberTable:
        line 119: 0
      LocalVariableTable:
        Start  Length  Slot  Name   Signature
            0      12     0  this   Lorg/apache/commons/io/filefilter/RegexFileFilter;
            0      12     1   dir   Ljava/io/File;
            0      12     2  name   Ljava/lang/String;
}
SourceFile: "RegexFileFilter.java"
