Classfile /Users/mw/Projects/slang-braindump/.jar/jar11/assemble/slang-braindump/assemble/content/org/scalatest/enablers/AggregatingImpls$ZipNoMatch$1$.class
  Last modified May 29, 2022; size 764 bytes
  SHA-256 checksum becbf687929bb38f6104fe6140b5584e4843fde3caa05b6b30b2e51cf22819f8
  Compiled from "Aggregating.scala"
public class org.scalatest.enablers.AggregatingImpls$ZipNoMatch$1$
  minor version: 0
  major version: 52
  flags: (0x0021) ACC_PUBLIC, ACC_SUPER
  this_class: #2                          // org/scalatest/enablers/AggregatingImpls$ZipNoMatch$1$
  super_class: #4                         // java/lang/Object
  interfaces: 0, fields: 0, methods: 1, attributes: 5
Constant pool:
   #1 = Utf8               org/scalatest/enablers/AggregatingImpls$ZipNoMatch$1$
   #2 = Class              #1             // org/scalatest/enablers/AggregatingImpls$ZipNoMatch$1$
   #3 = Utf8               java/lang/Object
   #4 = Class              #3             // java/lang/Object
   #5 = Utf8               Aggregating.scala
   #6 = Utf8               org/scalatest/enablers/AggregatingImpls
   #7 = Class              #6             // org/scalatest/enablers/AggregatingImpls
   #8 = Utf8               checkTheSameElementsAs
   #9 = Utf8               (Lscala/collection/Iterable;Lscala/collection/Iterable;Lorg/scalactic/Equality;)Z
  #10 = NameAndType        #8:#9          // checkTheSameElementsAs:(Lscala/collection/Iterable;Lscala/collection/Iterable;Lorg/scalactic/Equality;)Z
  #11 = Utf8               ZipNoMatch$1$
  #12 = Utf8               <init>
  #13 = Utf8               (Lorg/scalatest/enablers/AggregatingImpls;)V
  #14 = Utf8               $outer
  #15 = Utf8               ()V
  #16 = NameAndType        #12:#15        // "<init>":()V
  #17 = Methodref          #4.#16         // java/lang/Object."<init>":()V
  #18 = Utf8               this
  #19 = Utf8               Lorg/scalatest/enablers/AggregatingImpls$ZipNoMatch$1$;
  #20 = Utf8               Lorg/scalatest/enablers/AggregatingImpls;
  #21 = Utf8               Code
  #22 = Utf8               LineNumberTable
  #23 = Utf8               LocalVariableTable
  #24 = Utf8               MethodParameters
  #25 = Utf8               InnerClasses
  #26 = Utf8               EnclosingMethod
  #27 = Utf8               SourceFile
  #28 = Utf8               ScalaInlineInfo
  #29 = Utf8               Scala
{
  public org.scalatest.enablers.AggregatingImpls$ZipNoMatch$1$(org.scalatest.enablers.AggregatingImpls);
    descriptor: (Lorg/scalatest/enablers/AggregatingImpls;)V
    flags: (0x0001) ACC_PUBLIC
    Code:
      stack=1, locals=2, args_size=2
         0: aload_0
         1: invokespecial #17                 // Method java/lang/Object."<init>":()V
         4: return
      LineNumberTable:
        line 130: 0
      LocalVariableTable:
        Start  Length  Slot  Name   Signature
            0       5     0  this   Lorg/scalatest/enablers/AggregatingImpls$ZipNoMatch$1$;
            0       5     1 $outer   Lorg/scalatest/enablers/AggregatingImpls;
    MethodParameters:
      Name                           Flags
      $outer                         final synthetic
}
InnerClasses:
  public #11= #2;                         // ZipNoMatch$1$=class org/scalatest/enablers/AggregatingImpls$ZipNoMatch$1$
EnclosingMethod: #7.#10                 // org.scalatest.enablers.AggregatingImpls.checkTheSameElementsAs
SourceFile: "Aggregating.scala"
  ScalaInlineInfo: length = 0x9 (unknown attribute)
   01 01 00 01 00 0C 00 0D 01
  Scala: length = 0x0 (unknown attribute)

