Classfile /Users/mw/Projects/slang-braindump/.jar/jar11/assemble/slang-braindump/assemble/content/org/scalatest/enablers/AggregatingStandardImplicits.class
  Last modified May 29, 2022; size 5253 bytes
  SHA-256 checksum ac00bfcaae5ce07db5fd15eeb2c9ceade6674533d2348826cd7e809f1d9dddac
  Compiled from "Aggregating.scala"
public interface org.scalatest.enablers.AggregatingStandardImplicits extends org.scalatest.enablers.AggregatingJavaImplicits
  minor version: 0
  major version: 52
  flags: (0x0601) ACC_PUBLIC, ACC_INTERFACE, ACC_ABSTRACT
  this_class: #2                          // org/scalatest/enablers/AggregatingStandardImplicits
  super_class: #4                         // java/lang/Object
  interfaces: 1, fields: 0, methods: 17, attributes: 5
Constant pool:
   #1 = Utf8               org/scalatest/enablers/AggregatingStandardImplicits
   #2 = Class              #1             // org/scalatest/enablers/AggregatingStandardImplicits
   #3 = Utf8               java/lang/Object
   #4 = Class              #3             // java/lang/Object
   #5 = Utf8               org/scalatest/enablers/AggregatingJavaImplicits
   #6 = Class              #5             // org/scalatest/enablers/AggregatingJavaImplicits
   #7 = Utf8               Aggregating.scala
   #8 = Utf8               Lscala/reflect/ScalaSignature;
   #9 = Utf8               bytes
  #10 = Utf8               \u0006\u0005\u0005mba\u0002\u0006\f!\u0003\r\tA\u0005\u0005\u0006;\u0001!\tA\b\u0005\u0006E\u0001!\u0019a\t\u0005\u0006}\u0001!\u0019a\u0010\u0005\u0006\u000f\u0002!\u0019\u0001\u0013\u0005\u00065\u0002!\u0019a\u0017\u0005\u0006;\u0002!\u0019A\u0018\u0005\u0006Q\u0002!\u0019!\u001b\u0005\u0006c\u0002!\u0019A\u001d\u0005\b\u0003;\u0001A1AA\u0010\u0005q\tum\u001a:fO\u0006$\u0018N\\4Ti\u0006tG-\u0019:e\u00136\u0004H.[2jiNT!\u0001D\u0007\u0002\u0011\u0015t\u0017M\u00197feNT!AD\b\u0002\u0013M\u001c\u0017\r\\1uKN$(\"\u0001\t\u0002\u0007=\u0014xm\u0001\u0001\u0014\u0007\u0001\u0019\u0012\u0004\u0005\u0002\u0015/5\tQCC\u0001\u0017\u0003\u0015\u00198-\u00197b\u0013\tARC\u0001\u0004B]f\u0014VM\u001a\t\u00035mi\u0011aC\u0005\u00039-\u0011\u0001$Q4he\u0016<\u0017\r^5oO*\u000bg/Y%na2L7-\u001b;t\u0003\u0019!\u0013N\\5uIQ\tq\u0004\u0005\u0002\u0015A%\u0011\u0011%\u0006\u0002\u0005+:LG/\u0001\rbO\u001e\u0014XmZ1uS:<g*\u0019;ve\u0016|e-\u0011:sCf,\"\u0001J\u0017\u0015\u0005\u00152\u0004c\u0001\u000e\'Q%\u0011qe\u0003\u0002\f\u0003\u001e<\'/Z4bi&tw\rE\u0002\u0015S-J!AK\u000b\u0003\u000b\u0005\u0013(/Y=\u0011\u00051jC\u0002\u0001\u0003\u0006]\t\u0011\ra\f\u0002\u0002\u000bF\u0011\u0001g\r\t\u0003)EJ!AM\u000b\u0003\u000f9{G\u000f[5oOB\u0011A\u0003N\u0005\u0003kU\u00111!\u00118z\u0011\u00159$\u0001q\u00019\u0003!)\u0017/^1mSRL\bcA\u001d=W5\t!H\u0003\u0002<\u001f\u0005I1oY1mC\u000e$\u0018nY\u0005\u0003{i\u0012\u0001\"R9vC2LG/_\u0001\"G>tg/\u001a:u\u000bF,\u0018\r\\5usR{\u0017I\u001d:bs\u0006;wM]3hCRLgnZ\u000b\u0003\u0001\u0012#\"!Q#\u0011\u0007i1#\tE\u0002\u0015S\r\u0003\"\u0001\f#\u0005\u000b9\u001a!\u0019A\u0018\t\u000b]\u001a\u0001\u0019\u0001$\u0011\u0007eb4)A\rbO\u001e\u0014XmZ1uS:<g*\u0019;ve\u0016|em\u0015;sS:<GCA%V!\rQbE\u0013\t\u0003\u0017Js!\u0001\u0014)\u0011\u00055+R\"\u0001(\u000b\u0005=\u000b\u0012A\u0002\u001fs_>$h(\u0003\u0002R+\u00051\u0001K]3eK\u001aL!a\u0015+\u0003\rM#(/\u001b8h\u0015\t\tV\u0003C\u00038\t\u0001\u000fa\u000bE\u0002:y]\u0003\"\u0001\u0006-\n\u0005e+\"\u0001B\"iCJ\f!eY8om\u0016\u0014H/R9vC2LG/\u001f+p\'R\u0014\u0018N\\4BO\u001e\u0014XmZ1uS:<GCA%]\u0011\u00159T\u00011\u0001W\u0003a\twm\u001a:fO\u0006$\u0018N\\4OCR,(/Z(g\u000bZ,\'/_\u000b\u0003?\u0016$\"\u0001\u00194\u0011\u0007i1\u0013\rE\u0002:E\u0012L!a\u0019\u001e\u0003\u000b\u00153XM]=\u0011\u00051*G!\u0002\u0018\u0007\u0005\u0004y\u0003\"B\u001c\u0007\u0001\b9\u0007cA\u001d=I\u0006\t3m\u001c8wKJ$X)];bY&$\u0018\u0010V8Fm\u0016\u0014\u00180Q4he\u0016<\u0017\r^5oOV\u0011!N\u001c\u000b\u0003W>\u00042A\u0007\u0014m!\rI$-\u001c\t\u0003Y9$QAL\u0004C\u0002=BQaN\u0004A\u0002A\u00042!\u000f\u001fn\u0003\u0005\nwm\u001a:fO\u0006$\u0018N\\4OCR,(/Z(g\u000f\u0016tGK]1wKJ\u001c\u0018M\u00197f+\u0011\u0019\u0018q\u0003<\u0015\u0007Q\fI\u0002E\u0002\u001bMU\u0004B\u0001\f<\u0002\u0016\u0011)q\u000f\u0003b\u0001q\n!AKU!W+\rI\u0018\u0011C\t\u0003ai\u0004Ra_A\u0005\u0003\u001fq1\u0001`A\u0002\u001d\tixP\u0004\u0002N}&\ta#C\u0002\u0002\u0002U\t!bY8mY\u0016\u001cG/[8o\u0013\u0011\t)!a\u0002\u0002\u000fA\f7m[1hK*\u0019\u0011\u0011A\u000b\n\t\u0005-\u0011Q\u0002\u0002\u000f\u000f\u0016tGK]1wKJ\u001c\u0018M\u00197f\u0015\u0011\t)!a\u0002\u0011\u00071\n\t\u0002\u0002\u0004\u0002\u0014Y\u0014\ra\f\u0002\u0002KB\u0019A&a\u0006\u0005\u000b9B!\u0019A\u0018\t\r]B\u00019AA\u000e!\u0011ID(!\u0006\u0002U\r|gN^3si\u0016\u000bX/\u00197jif$vnR3o)J\fg/\u001a:tC\ndW-Q4he\u0016<\u0017\r^5oOV1\u0011\u0011EA\u001b\u0003O!B!a\t\u00028A!!DJA\u0013!\u0015a\u0013qEA\u001a\t\u00199\u0018B1\u0001\u0002*U!\u00111FA\u0019#\r\u0001\u0014Q\u0006\t\u0006w\u0006%\u0011q\u0006\t\u0004Y\u0005EBaBA\n\u0003O\u0011\ra\f\t\u0004Y\u0005UB!\u0002\u0018\n\u0005\u0004y\u0003BB\u001c\n\u0001\u0004\tI\u0004\u0005\u0003:y\u0005M\u0002
  #11 = Utf8               org/scalatest/enablers/AggregatingStandardImplicits$$anon$3
  #12 = Class              #11            // org/scalatest/enablers/AggregatingStandardImplicits$$anon$3
  #13 = Utf8               org/scalatest/enablers/AggregatingStandardImplicits$$anon$4
  #14 = Class              #13            // org/scalatest/enablers/AggregatingStandardImplicits$$anon$4
  #15 = Utf8               org/scalatest/enablers/AggregatingStandardImplicits$$anon$5
  #16 = Class              #15            // org/scalatest/enablers/AggregatingStandardImplicits$$anon$5
  #17 = Utf8               org/scalatest/enablers/AggregatingStandardImplicits$$anon$6
  #18 = Class              #17            // org/scalatest/enablers/AggregatingStandardImplicits$$anon$6
  #19 = Utf8               aggregatingNatureOfArray$
  #20 = Utf8               (Lorg/scalatest/enablers/AggregatingStandardImplicits;Lorg/scalactic/Equality;)Lorg/scalatest/enablers/Aggregating;
  #21 = Utf8               $this
  #22 = Utf8               equality
  #23 = Utf8               aggregatingNatureOfArray
  #24 = Utf8               (Lorg/scalactic/Equality;)Lorg/scalatest/enablers/Aggregating;
  #25 = NameAndType        #23:#24        // aggregatingNatureOfArray:(Lorg/scalactic/Equality;)Lorg/scalatest/enablers/Aggregating;
  #26 = InterfaceMethodref #2.#25         // org/scalatest/enablers/AggregatingStandardImplicits.aggregatingNatureOfArray:(Lorg/scalactic/Equality;)Lorg/scalatest/enablers/Aggregating;
  #27 = Utf8               Lorg/scalatest/enablers/AggregatingStandardImplicits;
  #28 = Utf8               Lorg/scalactic/Equality;
  #29 = Utf8               <E:Ljava/lang/Object;>(Lorg/scalactic/Equality<TE;>;)Lorg/scalatest/enablers/Aggregating<Ljava/lang/Object;>;
  #30 = Utf8               <init>
  #31 = Utf8               (Lorg/scalatest/enablers/AggregatingStandardImplicits;Lorg/scalactic/Equality;)V
  #32 = NameAndType        #30:#31        // "<init>":(Lorg/scalatest/enablers/AggregatingStandardImplicits;Lorg/scalactic/Equality;)V
  #33 = Methodref          #12.#32        // org/scalatest/enablers/AggregatingStandardImplicits$$anon$3."<init>":(Lorg/scalatest/enablers/AggregatingStandardImplicits;Lorg/scalactic/Equality;)V
  #34 = Utf8               this
  #35 = Utf8               convertEqualityToArrayAggregating$
  #36 = Utf8               convertEqualityToArrayAggregating
  #37 = NameAndType        #36:#24        // convertEqualityToArrayAggregating:(Lorg/scalactic/Equality;)Lorg/scalatest/enablers/Aggregating;
  #38 = InterfaceMethodref #2.#37         // org/scalatest/enablers/AggregatingStandardImplicits.convertEqualityToArrayAggregating:(Lorg/scalactic/Equality;)Lorg/scalatest/enablers/Aggregating;
  #39 = Utf8               aggregatingNatureOfString$
  #40 = Utf8               aggregatingNatureOfString
  #41 = NameAndType        #40:#24        // aggregatingNatureOfString:(Lorg/scalactic/Equality;)Lorg/scalatest/enablers/Aggregating;
  #42 = InterfaceMethodref #2.#41         // org/scalatest/enablers/AggregatingStandardImplicits.aggregatingNatureOfString:(Lorg/scalactic/Equality;)Lorg/scalatest/enablers/Aggregating;
  #43 = Utf8               (Lorg/scalactic/Equality<Ljava/lang/Object;>;)Lorg/scalatest/enablers/Aggregating<Ljava/lang/String;>;
  #44 = Methodref          #14.#32        // org/scalatest/enablers/AggregatingStandardImplicits$$anon$4."<init>":(Lorg/scalatest/enablers/AggregatingStandardImplicits;Lorg/scalactic/Equality;)V
  #45 = Utf8               convertEqualityToStringAggregating$
  #46 = Utf8               convertEqualityToStringAggregating
  #47 = NameAndType        #46:#24        // convertEqualityToStringAggregating:(Lorg/scalactic/Equality;)Lorg/scalatest/enablers/Aggregating;
  #48 = InterfaceMethodref #2.#47         // org/scalatest/enablers/AggregatingStandardImplicits.convertEqualityToStringAggregating:(Lorg/scalactic/Equality;)Lorg/scalatest/enablers/Aggregating;
  #49 = Utf8               aggregatingNatureOfEvery$
  #50 = Utf8               aggregatingNatureOfEvery
  #51 = NameAndType        #50:#24        // aggregatingNatureOfEvery:(Lorg/scalactic/Equality;)Lorg/scalatest/enablers/Aggregating;
  #52 = InterfaceMethodref #2.#51         // org/scalatest/enablers/AggregatingStandardImplicits.aggregatingNatureOfEvery:(Lorg/scalactic/Equality;)Lorg/scalatest/enablers/Aggregating;
  #53 = Utf8               <E:Ljava/lang/Object;>(Lorg/scalactic/Equality<TE;>;)Lorg/scalatest/enablers/Aggregating<Lorg/scalactic/Every<TE;>;>;
  #54 = Methodref          #16.#32        // org/scalatest/enablers/AggregatingStandardImplicits$$anon$5."<init>":(Lorg/scalatest/enablers/AggregatingStandardImplicits;Lorg/scalactic/Equality;)V
  #55 = Utf8               convertEqualityToEveryAggregating$
  #56 = Utf8               convertEqualityToEveryAggregating
  #57 = NameAndType        #56:#24        // convertEqualityToEveryAggregating:(Lorg/scalactic/Equality;)Lorg/scalatest/enablers/Aggregating;
  #58 = InterfaceMethodref #2.#57         // org/scalatest/enablers/AggregatingStandardImplicits.convertEqualityToEveryAggregating:(Lorg/scalactic/Equality;)Lorg/scalatest/enablers/Aggregating;
  #59 = Utf8               aggregatingNatureOfGenTraversable$
  #60 = Utf8               aggregatingNatureOfGenTraversable
  #61 = NameAndType        #60:#24        // aggregatingNatureOfGenTraversable:(Lorg/scalactic/Equality;)Lorg/scalatest/enablers/Aggregating;
  #62 = InterfaceMethodref #2.#61         // org/scalatest/enablers/AggregatingStandardImplicits.aggregatingNatureOfGenTraversable:(Lorg/scalactic/Equality;)Lorg/scalatest/enablers/Aggregating;
  #63 = Utf8               <E:Ljava/lang/Object;TRAV::Lscala/collection/Iterable<Ljava/lang/Object;>;>(Lorg/scalactic/Equality<TE;>;)Lorg/scalatest/enablers/Aggregating<TTRAV;>;
  #64 = Methodref          #18.#32        // org/scalatest/enablers/AggregatingStandardImplicits$$anon$6."<init>":(Lorg/scalatest/enablers/AggregatingStandardImplicits;Lorg/scalactic/Equality;)V
  #65 = Utf8               convertEqualityToGenTraversableAggregating$
  #66 = Utf8               convertEqualityToGenTraversableAggregating
  #67 = NameAndType        #66:#24        // convertEqualityToGenTraversableAggregating:(Lorg/scalactic/Equality;)Lorg/scalatest/enablers/Aggregating;
  #68 = InterfaceMethodref #2.#67         // org/scalatest/enablers/AggregatingStandardImplicits.convertEqualityToGenTraversableAggregating:(Lorg/scalactic/Equality;)Lorg/scalatest/enablers/Aggregating;
  #69 = Utf8               $init$
  #70 = Utf8               (Lorg/scalatest/enablers/AggregatingStandardImplicits;)V
  #71 = Utf8               Code
  #72 = Utf8               LineNumberTable
  #73 = Utf8               LocalVariableTable
  #74 = Utf8               MethodParameters
  #75 = Utf8               Signature
  #76 = Utf8               InnerClasses
  #77 = Utf8               SourceFile
  #78 = Utf8               RuntimeVisibleAnnotations
  #79 = Utf8               ScalaInlineInfo
  #80 = Utf8               ScalaSig
{
  public static org.scalatest.enablers.Aggregating aggregatingNatureOfArray$(org.scalatest.enablers.AggregatingStandardImplicits, org.scalactic.Equality);
    descriptor: (Lorg/scalatest/enablers/AggregatingStandardImplicits;Lorg/scalactic/Equality;)Lorg/scalatest/enablers/Aggregating;
    flags: (0x1009) ACC_PUBLIC, ACC_STATIC, ACC_SYNTHETIC
    Code:
      stack=2, locals=2, args_size=2
         0: aload_0
         1: aload_1
         2: invokespecial #26                 // InterfaceMethod aggregatingNatureOfArray:(Lorg/scalactic/Equality;)Lorg/scalatest/enablers/Aggregating;
         5: areturn
      LineNumberTable:
        line 334: 0
      LocalVariableTable:
        Start  Length  Slot  Name   Signature
            0       6     0 $this   Lorg/scalatest/enablers/AggregatingStandardImplicits;
            0       6     1 equality   Lorg/scalactic/Equality;
    MethodParameters:
      Name                           Flags
      $this                          final synthetic
      equality                       final

  public default <E extends java.lang.Object> org.scalatest.enablers.Aggregating<java.lang.Object> aggregatingNatureOfArray(org.scalactic.Equality<E>);
    descriptor: (Lorg/scalactic/Equality;)Lorg/scalatest/enablers/Aggregating;
    flags: (0x0001) ACC_PUBLIC
    Code:
      stack=4, locals=2, args_size=2
         0: new           #12                 // class org/scalatest/enablers/AggregatingStandardImplicits$$anon$3
         3: dup
         4: aload_0
         5: aload_1
         6: invokespecial #33                 // Method org/scalatest/enablers/AggregatingStandardImplicits$$anon$3."<init>":(Lorg/scalatest/enablers/AggregatingStandardImplicits;Lorg/scalactic/Equality;)V
         9: areturn
      LineNumberTable:
        line 335: 0
      LocalVariableTable:
        Start  Length  Slot  Name   Signature
            0      10     0  this   Lorg/scalatest/enablers/AggregatingStandardImplicits;
            0      10     1 equality   Lorg/scalactic/Equality;
    Signature: #29                          // <E:Ljava/lang/Object;>(Lorg/scalactic/Equality<TE;>;)Lorg/scalatest/enablers/Aggregating<Ljava/lang/Object;>;
    MethodParameters:
      Name                           Flags
      equality                       final

  public static org.scalatest.enablers.Aggregating convertEqualityToArrayAggregating$(org.scalatest.enablers.AggregatingStandardImplicits, org.scalactic.Equality);
    descriptor: (Lorg/scalatest/enablers/AggregatingStandardImplicits;Lorg/scalactic/Equality;)Lorg/scalatest/enablers/Aggregating;
    flags: (0x1009) ACC_PUBLIC, ACC_STATIC, ACC_SYNTHETIC
    Code:
      stack=2, locals=2, args_size=2
         0: aload_0
         1: aload_1
         2: invokespecial #38                 // InterfaceMethod convertEqualityToArrayAggregating:(Lorg/scalactic/Equality;)Lorg/scalatest/enablers/Aggregating;
         5: areturn
      LineNumberTable:
        line 369: 0
      LocalVariableTable:
        Start  Length  Slot  Name   Signature
            0       6     0 $this   Lorg/scalatest/enablers/AggregatingStandardImplicits;
            0       6     1 equality   Lorg/scalactic/Equality;
    MethodParameters:
      Name                           Flags
      $this                          final synthetic
      equality                       final

  public default <E extends java.lang.Object> org.scalatest.enablers.Aggregating<java.lang.Object> convertEqualityToArrayAggregating(org.scalactic.Equality<E>);
    descriptor: (Lorg/scalactic/Equality;)Lorg/scalatest/enablers/Aggregating;
    flags: (0x0001) ACC_PUBLIC
    Code:
      stack=2, locals=2, args_size=2
         0: aload_0
         1: aload_1
         2: invokeinterface #26,  2           // InterfaceMethod aggregatingNatureOfArray:(Lorg/scalactic/Equality;)Lorg/scalatest/enablers/Aggregating;
         7: areturn
      LineNumberTable:
        line 370: 0
      LocalVariableTable:
        Start  Length  Slot  Name   Signature
            0       8     0  this   Lorg/scalatest/enablers/AggregatingStandardImplicits;
            0       8     1 equality   Lorg/scalactic/Equality;
    Signature: #29                          // <E:Ljava/lang/Object;>(Lorg/scalactic/Equality<TE;>;)Lorg/scalatest/enablers/Aggregating<Ljava/lang/Object;>;
    MethodParameters:
      Name                           Flags
      equality                       final

  public static org.scalatest.enablers.Aggregating aggregatingNatureOfString$(org.scalatest.enablers.AggregatingStandardImplicits, org.scalactic.Equality);
    descriptor: (Lorg/scalatest/enablers/AggregatingStandardImplicits;Lorg/scalactic/Equality;)Lorg/scalatest/enablers/Aggregating;
    flags: (0x1009) ACC_PUBLIC, ACC_STATIC, ACC_SYNTHETIC
    Code:
      stack=2, locals=2, args_size=2
         0: aload_0
         1: aload_1
         2: invokespecial #42                 // InterfaceMethod aggregatingNatureOfString:(Lorg/scalactic/Equality;)Lorg/scalatest/enablers/Aggregating;
         5: areturn
      LineNumberTable:
        line 378: 0
      LocalVariableTable:
        Start  Length  Slot  Name   Signature
            0       6     0 $this   Lorg/scalatest/enablers/AggregatingStandardImplicits;
            0       6     1 equality   Lorg/scalactic/Equality;
    MethodParameters:
      Name                           Flags
      $this                          final synthetic
      equality                       final

  public default org.scalatest.enablers.Aggregating<java.lang.String> aggregatingNatureOfString(org.scalactic.Equality<java.lang.Object>);
    descriptor: (Lorg/scalactic/Equality;)Lorg/scalatest/enablers/Aggregating;
    flags: (0x0001) ACC_PUBLIC
    Code:
      stack=4, locals=2, args_size=2
         0: new           #14                 // class org/scalatest/enablers/AggregatingStandardImplicits$$anon$4
         3: dup
         4: aload_0
         5: aload_1
         6: invokespecial #44                 // Method org/scalatest/enablers/AggregatingStandardImplicits$$anon$4."<init>":(Lorg/scalatest/enablers/AggregatingStandardImplicits;Lorg/scalactic/Equality;)V
         9: areturn
      LineNumberTable:
        line 379: 0
      LocalVariableTable:
        Start  Length  Slot  Name   Signature
            0      10     0  this   Lorg/scalatest/enablers/AggregatingStandardImplicits;
            0      10     1 equality   Lorg/scalactic/Equality;
    Signature: #43                          // (Lorg/scalactic/Equality<Ljava/lang/Object;>;)Lorg/scalatest/enablers/Aggregating<Ljava/lang/String;>;
    MethodParameters:
      Name                           Flags
      equality                       final

  public static org.scalatest.enablers.Aggregating convertEqualityToStringAggregating$(org.scalatest.enablers.AggregatingStandardImplicits, org.scalactic.Equality);
    descriptor: (Lorg/scalatest/enablers/AggregatingStandardImplicits;Lorg/scalactic/Equality;)Lorg/scalatest/enablers/Aggregating;
    flags: (0x1009) ACC_PUBLIC, ACC_STATIC, ACC_SYNTHETIC
    Code:
      stack=2, locals=2, args_size=2
         0: aload_0
         1: aload_1
         2: invokespecial #48                 // InterfaceMethod convertEqualityToStringAggregating:(Lorg/scalactic/Equality;)Lorg/scalatest/enablers/Aggregating;
         5: areturn
      LineNumberTable:
        line 413: 0
      LocalVariableTable:
        Start  Length  Slot  Name   Signature
            0       6     0 $this   Lorg/scalatest/enablers/AggregatingStandardImplicits;
            0       6     1 equality   Lorg/scalactic/Equality;
    MethodParameters:
      Name                           Flags
      $this                          final synthetic
      equality                       final

  public default org.scalatest.enablers.Aggregating<java.lang.String> convertEqualityToStringAggregating(org.scalactic.Equality<java.lang.Object>);
    descriptor: (Lorg/scalactic/Equality;)Lorg/scalatest/enablers/Aggregating;
    flags: (0x0001) ACC_PUBLIC
    Code:
      stack=2, locals=2, args_size=2
         0: aload_0
         1: aload_1
         2: invokeinterface #42,  2           // InterfaceMethod aggregatingNatureOfString:(Lorg/scalactic/Equality;)Lorg/scalatest/enablers/Aggregating;
         7: areturn
      LineNumberTable:
        line 414: 0
      LocalVariableTable:
        Start  Length  Slot  Name   Signature
            0       8     0  this   Lorg/scalatest/enablers/AggregatingStandardImplicits;
            0       8     1 equality   Lorg/scalactic/Equality;
    Signature: #43                          // (Lorg/scalactic/Equality<Ljava/lang/Object;>;)Lorg/scalatest/enablers/Aggregating<Ljava/lang/String;>;
    MethodParameters:
      Name                           Flags
      equality                       final

  public static org.scalatest.enablers.Aggregating aggregatingNatureOfEvery$(org.scalatest.enablers.AggregatingStandardImplicits, org.scalactic.Equality);
    descriptor: (Lorg/scalatest/enablers/AggregatingStandardImplicits;Lorg/scalactic/Equality;)Lorg/scalatest/enablers/Aggregating;
    flags: (0x1009) ACC_PUBLIC, ACC_STATIC, ACC_SYNTHETIC
    Code:
      stack=2, locals=2, args_size=2
         0: aload_0
         1: aload_1
         2: invokespecial #52                 // InterfaceMethod aggregatingNatureOfEvery:(Lorg/scalactic/Equality;)Lorg/scalatest/enablers/Aggregating;
         5: areturn
      LineNumberTable:
        line 423: 0
      LocalVariableTable:
        Start  Length  Slot  Name   Signature
            0       6     0 $this   Lorg/scalatest/enablers/AggregatingStandardImplicits;
            0       6     1 equality   Lorg/scalactic/Equality;
    MethodParameters:
      Name                           Flags
      $this                          final synthetic
      equality                       final

  public default <E extends java.lang.Object> org.scalatest.enablers.Aggregating<org.scalactic.Every<E>> aggregatingNatureOfEvery(org.scalactic.Equality<E>);
    descriptor: (Lorg/scalactic/Equality;)Lorg/scalatest/enablers/Aggregating;
    flags: (0x0001) ACC_PUBLIC
    Code:
      stack=4, locals=2, args_size=2
         0: new           #16                 // class org/scalatest/enablers/AggregatingStandardImplicits$$anon$5
         3: dup
         4: aload_0
         5: aload_1
         6: invokespecial #54                 // Method org/scalatest/enablers/AggregatingStandardImplicits$$anon$5."<init>":(Lorg/scalatest/enablers/AggregatingStandardImplicits;Lorg/scalactic/Equality;)V
         9: areturn
      LineNumberTable:
        line 424: 0
      LocalVariableTable:
        Start  Length  Slot  Name   Signature
            0      10     0  this   Lorg/scalatest/enablers/AggregatingStandardImplicits;
            0      10     1 equality   Lorg/scalactic/Equality;
    Signature: #53                          // <E:Ljava/lang/Object;>(Lorg/scalactic/Equality<TE;>;)Lorg/scalatest/enablers/Aggregating<Lorg/scalactic/Every<TE;>;>;
    MethodParameters:
      Name                           Flags
      equality                       final

  public static org.scalatest.enablers.Aggregating convertEqualityToEveryAggregating$(org.scalatest.enablers.AggregatingStandardImplicits, org.scalactic.Equality);
    descriptor: (Lorg/scalatest/enablers/AggregatingStandardImplicits;Lorg/scalactic/Equality;)Lorg/scalatest/enablers/Aggregating;
    flags: (0x1009) ACC_PUBLIC, ACC_STATIC, ACC_SYNTHETIC
    Code:
      stack=2, locals=2, args_size=2
         0: aload_0
         1: aload_1
         2: invokespecial #58                 // InterfaceMethod convertEqualityToEveryAggregating:(Lorg/scalactic/Equality;)Lorg/scalatest/enablers/Aggregating;
         5: areturn
      LineNumberTable:
        line 458: 0
      LocalVariableTable:
        Start  Length  Slot  Name   Signature
            0       6     0 $this   Lorg/scalatest/enablers/AggregatingStandardImplicits;
            0       6     1 equality   Lorg/scalactic/Equality;
    MethodParameters:
      Name                           Flags
      $this                          final synthetic
      equality                       final

  public default <E extends java.lang.Object> org.scalatest.enablers.Aggregating<org.scalactic.Every<E>> convertEqualityToEveryAggregating(org.scalactic.Equality<E>);
    descriptor: (Lorg/scalactic/Equality;)Lorg/scalatest/enablers/Aggregating;
    flags: (0x0001) ACC_PUBLIC
    Code:
      stack=2, locals=2, args_size=2
         0: aload_0
         1: aload_1
         2: invokeinterface #52,  2           // InterfaceMethod aggregatingNatureOfEvery:(Lorg/scalactic/Equality;)Lorg/scalatest/enablers/Aggregating;
         7: areturn
      LineNumberTable:
        line 459: 0
      LocalVariableTable:
        Start  Length  Slot  Name   Signature
            0       8     0  this   Lorg/scalatest/enablers/AggregatingStandardImplicits;
            0       8     1 equality   Lorg/scalactic/Equality;
    Signature: #53                          // <E:Ljava/lang/Object;>(Lorg/scalactic/Equality<TE;>;)Lorg/scalatest/enablers/Aggregating<Lorg/scalactic/Every<TE;>;>;
    MethodParameters:
      Name                           Flags
      equality                       final

  public static org.scalatest.enablers.Aggregating aggregatingNatureOfGenTraversable$(org.scalatest.enablers.AggregatingStandardImplicits, org.scalactic.Equality);
    descriptor: (Lorg/scalatest/enablers/AggregatingStandardImplicits;Lorg/scalactic/Equality;)Lorg/scalatest/enablers/Aggregating;
    flags: (0x1009) ACC_PUBLIC, ACC_STATIC, ACC_SYNTHETIC
    Code:
      stack=2, locals=2, args_size=2
         0: aload_0
         1: aload_1
         2: invokespecial #62                 // InterfaceMethod aggregatingNatureOfGenTraversable:(Lorg/scalactic/Equality;)Lorg/scalatest/enablers/Aggregating;
         5: areturn
      LineNumberTable:
        line 469: 0
      LocalVariableTable:
        Start  Length  Slot  Name   Signature
            0       6     0 $this   Lorg/scalatest/enablers/AggregatingStandardImplicits;
            0       6     1 equality   Lorg/scalactic/Equality;
    MethodParameters:
      Name                           Flags
      $this                          final synthetic
      equality                       final

  public default <E extends java.lang.Object, TRAV extends scala.collection.Iterable<java.lang.Object>> org.scalatest.enablers.Aggregating<TRAV> aggregatingNatureOfGenTraversable(org.scalactic.Equality<E>);
    descriptor: (Lorg/scalactic/Equality;)Lorg/scalatest/enablers/Aggregating;
    flags: (0x0001) ACC_PUBLIC
    Code:
      stack=4, locals=2, args_size=2
         0: new           #18                 // class org/scalatest/enablers/AggregatingStandardImplicits$$anon$6
         3: dup
         4: aload_0
         5: aload_1
         6: invokespecial #64                 // Method org/scalatest/enablers/AggregatingStandardImplicits$$anon$6."<init>":(Lorg/scalatest/enablers/AggregatingStandardImplicits;Lorg/scalactic/Equality;)V
         9: areturn
      LineNumberTable:
        line 470: 0
      LocalVariableTable:
        Start  Length  Slot  Name   Signature
            0      10     0  this   Lorg/scalatest/enablers/AggregatingStandardImplicits;
            0      10     1 equality   Lorg/scalactic/Equality;
    Signature: #63                          // <E:Ljava/lang/Object;TRAV::Lscala/collection/Iterable<Ljava/lang/Object;>;>(Lorg/scalactic/Equality<TE;>;)Lorg/scalatest/enablers/Aggregating<TTRAV;>;
    MethodParameters:
      Name                           Flags
      equality                       final

  public static org.scalatest.enablers.Aggregating convertEqualityToGenTraversableAggregating$(org.scalatest.enablers.AggregatingStandardImplicits, org.scalactic.Equality);
    descriptor: (Lorg/scalatest/enablers/AggregatingStandardImplicits;Lorg/scalactic/Equality;)Lorg/scalatest/enablers/Aggregating;
    flags: (0x1009) ACC_PUBLIC, ACC_STATIC, ACC_SYNTHETIC
    Code:
      stack=2, locals=2, args_size=2
         0: aload_0
         1: aload_1
         2: invokespecial #68                 // InterfaceMethod convertEqualityToGenTraversableAggregating:(Lorg/scalactic/Equality;)Lorg/scalatest/enablers/Aggregating;
         5: areturn
      LineNumberTable:
        line 505: 0
      LocalVariableTable:
        Start  Length  Slot  Name   Signature
            0       6     0 $this   Lorg/scalatest/enablers/AggregatingStandardImplicits;
            0       6     1 equality   Lorg/scalactic/Equality;
    MethodParameters:
      Name                           Flags
      $this                          final synthetic
      equality                       final

  public default <E extends java.lang.Object, TRAV extends scala.collection.Iterable<java.lang.Object>> org.scalatest.enablers.Aggregating<TRAV> convertEqualityToGenTraversableAggregating(org.scalactic.Equality<E>);
    descriptor: (Lorg/scalactic/Equality;)Lorg/scalatest/enablers/Aggregating;
    flags: (0x0001) ACC_PUBLIC
    Code:
      stack=2, locals=2, args_size=2
         0: aload_0
         1: aload_1
         2: invokeinterface #62,  2           // InterfaceMethod aggregatingNatureOfGenTraversable:(Lorg/scalactic/Equality;)Lorg/scalatest/enablers/Aggregating;
         7: areturn
      LineNumberTable:
        line 506: 0
      LocalVariableTable:
        Start  Length  Slot  Name   Signature
            0       8     0  this   Lorg/scalatest/enablers/AggregatingStandardImplicits;
            0       8     1 equality   Lorg/scalactic/Equality;
    Signature: #63                          // <E:Ljava/lang/Object;TRAV::Lscala/collection/Iterable<Ljava/lang/Object;>;>(Lorg/scalactic/Equality<TE;>;)Lorg/scalatest/enablers/Aggregating<TTRAV;>;
    MethodParameters:
      Name                           Flags
      equality                       final

  public static void $init$(org.scalatest.enablers.AggregatingStandardImplicits);
    descriptor: (Lorg/scalatest/enablers/AggregatingStandardImplicits;)V
    flags: (0x0009) ACC_PUBLIC, ACC_STATIC
    Code:
      stack=0, locals=1, args_size=1
         0: return
      LineNumberTable:
        line 322: 0
      LocalVariableTable:
        Start  Length  Slot  Name   Signature
            0       1     0 $this   Lorg/scalatest/enablers/AggregatingStandardImplicits;
    MethodParameters:
      Name                           Flags
      $this                          final synthetic
}
InnerClasses:
  public final #12;                       // class org/scalatest/enablers/AggregatingStandardImplicits$$anon$3
  public final #14;                       // class org/scalatest/enablers/AggregatingStandardImplicits$$anon$4
  public final #16;                       // class org/scalatest/enablers/AggregatingStandardImplicits$$anon$5
  public final #18;                       // class org/scalatest/enablers/AggregatingStandardImplicits$$anon$6
SourceFile: "Aggregating.scala"
RuntimeVisibleAnnotations:
  0: #8(#9=s#10)
    scala.reflect.ScalaSignature(
      bytes="\u0006\u0005\u0005mba\u0002\u0006\f!\u0003\r\tA\u0005\u0005\u0006;\u0001!\tA\b\u0005\u0006E\u0001!\u0019a\t\u0005\u0006}\u0001!\u0019a\u0010\u0005\u0006\u000f\u0002!\u0019\u0001\u0013\u0005\u00065\u0002!\u0019a\u0017\u0005\u0006;\u0002!\u0019A\u0018\u0005\u0006Q\u0002!\u0019!\u001b\u0005\u0006c\u0002!\u0019A\u001d\u0005\b\u0003;\u0001A1AA\u0010\u0005q\tum\u001a:fO\u0006$\u0018N\\4Ti\u0006tG-\u0019:e\u00136\u0004H.[2jiNT!\u0001D\u0007\u0002\u0011\u0015t\u0017M\u00197feNT!AD\b\u0002\u0013M\u001c\u0017\r\\1uKN$(\"\u0001\t\u0002\u0007=\u0014xm\u0001\u0001\u0014\u0007\u0001\u0019\u0012\u0004\u0005\u0002\u0015/5\tQCC\u0001\u0017\u0003\u0015\u00198-\u00197b\u0013\tARC\u0001\u0004B]f\u0014VM\u001a\t\u00035mi\u0011aC\u0005\u00039-\u0011\u0001$Q4he\u0016<\u0017\r^5oO*\u000bg/Y%na2L7-\u001b;t\u0003\u0019!\u0013N\\5uIQ\tq\u0004\u0005\u0002\u0015A%\u0011\u0011%\u0006\u0002\u0005+:LG/\u0001\rbO\u001e\u0014XmZ1uS:<g*\u0019;ve\u0016|e-\u0011:sCf,\"\u0001J\u0017\u0015\u0005\u00152\u0004c\u0001\u000e\'Q%\u0011qe\u0003\u0002\f\u0003\u001e<\'/Z4bi&tw\rE\u0002\u0015S-J!AK\u000b\u0003\u000b\u0005\u0013(/Y=\u0011\u00051jC\u0002\u0001\u0003\u0006]\t\u0011\ra\f\u0002\u0002\u000bF\u0011\u0001g\r\t\u0003)EJ!AM\u000b\u0003\u000f9{G\u000f[5oOB\u0011A\u0003N\u0005\u0003kU\u00111!\u00118z\u0011\u00159$\u0001q\u00019\u0003!)\u0017/^1mSRL\bcA\u001d=W5\t!H\u0003\u0002<\u001f\u0005I1oY1mC\u000e$\u0018nY\u0005\u0003{i\u0012\u0001\"R9vC2LG/_\u0001\"G>tg/\u001a:u\u000bF,\u0018\r\\5usR{\u0017I\u001d:bs\u0006;wM]3hCRLgnZ\u000b\u0003\u0001\u0012#\"!Q#\u0011\u0007i1#\tE\u0002\u0015S\r\u0003\"\u0001\f#\u0005\u000b9\u001a!\u0019A\u0018\t\u000b]\u001a\u0001\u0019\u0001$\u0011\u0007eb4)A\rbO\u001e\u0014XmZ1uS:<g*\u0019;ve\u0016|em\u0015;sS:<GCA%V!\rQbE\u0013\t\u0003\u0017Js!\u0001\u0014)\u0011\u00055+R\"\u0001(\u000b\u0005=\u000b\u0012A\u0002\u001fs_>$h(\u0003\u0002R+\u00051\u0001K]3eK\u001aL!a\u0015+\u0003\rM#(/\u001b8h\u0015\t\tV\u0003C\u00038\t\u0001\u000fa\u000bE\u0002:y]\u0003\"\u0001\u0006-\n\u0005e+\"\u0001B\"iCJ\f!eY8om\u0016\u0014H/R9vC2LG/\u001f+p\'R\u0014\u0018N\\4BO\u001e\u0014XmZ1uS:<GCA%]\u0011\u00159T\u00011\u0001W\u0003a\twm\u001a:fO\u0006$\u0018N\\4OCR,(/Z(g\u000bZ,\'/_\u000b\u0003?\u0016$\"\u0001\u00194\u0011\u0007i1\u0013\rE\u0002:E\u0012L!a\u0019\u001e\u0003\u000b\u00153XM]=\u0011\u00051*G!\u0002\u0018\u0007\u0005\u0004y\u0003\"B\u001c\u0007\u0001\b9\u0007cA\u001d=I\u0006\t3m\u001c8wKJ$X)];bY&$\u0018\u0010V8Fm\u0016\u0014\u00180Q4he\u0016<\u0017\r^5oOV\u0011!N\u001c\u000b\u0003W>\u00042A\u0007\u0014m!\rI$-\u001c\t\u0003Y9$QAL\u0004C\u0002=BQaN\u0004A\u0002A\u00042!\u000f\u001fn\u0003\u0005\nwm\u001a:fO\u0006$\u0018N\\4OCR,(/Z(g\u000f\u0016tGK]1wKJ\u001c\u0018M\u00197f+\u0011\u0019\u0018q\u0003<\u0015\u0007Q\fI\u0002E\u0002\u001bMU\u0004B\u0001\f<\u0002\u0016\u0011)q\u000f\u0003b\u0001q\n!AKU!W+\rI\u0018\u0011C\t\u0003ai\u0004Ra_A\u0005\u0003\u001fq1\u0001`A\u0002\u001d\tixP\u0004\u0002N}&\ta#C\u0002\u0002\u0002U\t!bY8mY\u0016\u001cG/[8o\u0013\u0011\t)!a\u0002\u0002\u000fA\f7m[1hK*\u0019\u0011\u0011A\u000b\n\t\u0005-\u0011Q\u0002\u0002\u000f\u000f\u0016tGK]1wKJ\u001c\u0018M\u00197f\u0015\u0011\t)!a\u0002\u0011\u00071\n\t\u0002\u0002\u0004\u0002\u0014Y\u0014\ra\f\u0002\u0002KB\u0019A&a\u0006\u0005\u000b9B!\u0019A\u0018\t\r]B\u00019AA\u000e!\u0011ID(!\u0006\u0002U\r|gN^3si\u0016\u000bX/\u00197jif$vnR3o)J\fg/\u001a:tC\ndW-Q4he\u0016<\u0017\r^5oOV1\u0011\u0011EA\u001b\u0003O!B!a\t\u00028A!!DJA\u0013!\u0015a\u0013qEA\u001a\t\u00199\u0018B1\u0001\u0002*U!\u00111FA\u0019#\r\u0001\u0014Q\u0006\t\u0006w\u0006%\u0011q\u0006\t\u0004Y\u0005EBaBA\n\u0003O\u0011\ra\f\t\u0004Y\u0005UB!\u0002\u0018\n\u0005\u0004y\u0003BB\u001c\n\u0001\u0004\tI\u0004\u0005\u0003:y\u0005M\u0002"
    )
  ScalaInlineInfo: length = 0x59 (unknown attribute)
   01 00 00 11 00 45 00 46 01 00 17 00 18 00 00 13
   00 14 01 00 32 00 18 00 00 31 00 14 01 00 3C 00
   18 00 00 3B 00 14 01 00 28 00 18 00 00 27 00 14
   01 00 24 00 18 00 00 23 00 14 01 00 38 00 18 00
   00 37 00 14 01 00 42 00 18 00 00 41 00 14 01 00
   2E 00 18 00 00 2D 00 14 01
  ScalaSig: length = 0x3 (unknown attribute)
   05 02 00
