Classfile /Users/mw/Projects/slang-braindump/.jar/jar11/assemble/slang-braindump/assemble/content/org/scalatest/enablers/AggregatingHighPriorityImplicits.class
  Last modified May 29, 2022; size 2798 bytes
  SHA-256 checksum 763b9c04242db99134507fe0ffa4c85124cea29e1d781e7a2edb6bc3abe20e74
  Compiled from "Aggregating.scala"
public interface org.scalatest.enablers.AggregatingHighPriorityImplicits extends org.scalatest.enablers.AggregatingStandardImplicits
  minor version: 0
  major version: 52
  flags: (0x0601) ACC_PUBLIC, ACC_INTERFACE, ACC_ABSTRACT
  this_class: #2                          // org/scalatest/enablers/AggregatingHighPriorityImplicits
  super_class: #4                         // java/lang/Object
  interfaces: 1, fields: 0, methods: 5, attributes: 5
Constant pool:
   #1 = Utf8               org/scalatest/enablers/AggregatingHighPriorityImplicits
   #2 = Class              #1             // org/scalatest/enablers/AggregatingHighPriorityImplicits
   #3 = Utf8               java/lang/Object
   #4 = Class              #3             // java/lang/Object
   #5 = Utf8               org/scalatest/enablers/AggregatingStandardImplicits
   #6 = Class              #5             // org/scalatest/enablers/AggregatingStandardImplicits
   #7 = Utf8               Aggregating.scala
   #8 = Utf8               Lscala/reflect/ScalaSignature;
   #9 = Utf8               bytes
  #10 = Utf8               \u0006\u0005)4q\u0001B\u0003\u0011\u0002\u0007\u0005A\u0002C\u0003\u0018\u0001\u0011\u0005\u0001\u0004C\u0003\u001d\u0001\u0011\rQ\u0004C\u0003W\u0001\u0011\rqK\u0001\u0011BO\u001e\u0014XmZ1uS:<\u0007*[4i!JLwN]5us&k\u0007\u000f\\5dSR\u001c(B\u0001\u0004\b\u0003!)g.\u00192mKJ\u001c(B\u0001\u0005\n\u0003%\u00198-\u00197bi\u0016\u001cHOC\u0001\u000b\u0003\ry\'oZ\u0002\u0001\'\r\u0001Qb\u0005\t\u0003\u001dEi\u0011a\u0004\u0006\u0002!\u0005)1oY1mC&\u0011!c\u0004\u0002\u0007\u0003:L(+\u001a4\u0011\u0005Q)R\"A\u0003\n\u0005Y)!\u0001H!hOJ,w-\u0019;j]\u001e\u001cF/\u00198eCJ$\u0017*\u001c9mS\u000eLGo]\u0001\u0007I%t\u0017\u000e\u001e\u0013\u0015\u0003e\u0001\"A\u0004\u000e\n\u0005my!\u0001B+oSR\fa#Y4he\u0016<\u0017\r^5oO:\u000bG/\u001e:f\u001f\u001al\u0015\r]\u000b\u0005=\u0019KE\u0005\u0006\u0002 \u0017B\u0019A\u0003\t\u0012\n\u0005\u0005*!aC!hOJ,w-\u0019;j]\u001e\u0004Ba\t\u0013F\u00112\u0001A!B\u0013\u0003\u0005\u00041#aA\'B!V\u0019q\u0005P\"\u0012\u0005!Z\u0003C\u0001\b*\u0013\tQsBA\u0004O_RD\u0017N\\4\u0011\t1B4H\u0011\b\u0003[Ur!AL\u001a\u000f\u0005=\u0012T\"\u0001\u0019\u000b\u0005EZ\u0011A\u0002\u001fs_>$h(C\u0001\u0011\u0013\t!t\"\u0001\u0006d_2dWm\u0019;j_:L!AN\u001c\u0002\u000fA\f7m[1hK*\u0011AgD\u0005\u0003si\u0012aaR3o\u001b\u0006\u0004(B\u0001\u001c8!\t\u0019C\bB\u0003>I\t\u0007aHA\u0001l#\tAs\b\u0005\u0002\u000f\u0001&\u0011\u0011i\u0004\u0002\u0004\u0003:L\bCA\u0012D\t\u0015!EE1\u0001?\u0005\u00051\bCA\u0012G\t\u00159%A1\u0001?\u0005\u0005Y\u0005CA\u0012J\t\u0015Q%A1\u0001?\u0005\u00051\u0006\"\u0002\'\u0003\u0001\bi\u0015\u0001C3rk\u0006d\u0017\u000e^=\u0011\u00079\u000b6+D\u0001P\u0015\t\u0001\u0016\"A\u0005tG\u0006d\u0017m\u0019;jG&\u0011!k\u0014\u0002\t\u000bF,\u0018\r\\5usB!a\u0002V#I\u0013\t)vB\u0001\u0004UkBdWMM\u0001 G>tg/\u001a:u\u000bF,\u0018\r\\5usR{W*\u00199BO\u001e\u0014XmZ1uS:<W\u0003\u0002-]=\n$\"!W0\u0011\u0007Q\u0001#\f\u0005\u0003-qmk\u0006CA\u0012]\t\u001595A1\u0001?!\t\u0019c\fB\u0003K\u0007\t\u0007a\bC\u0003M\u0007\u0001\u0007\u0001\rE\u0002O#\u0006\u0004BA\u0004+\\;\u0012)Qe\u0001b\u0001GV\u0019AmZ5\u0012\u0005!*\u0007\u0003\u0002\u00179M\"\u0004\"aI4\u0005\u000bu\u0012\'\u0019\u0001 \u0011\u0005\rJG!\u0002#c\u0005\u0004q\u0004
  #11 = Utf8               org/scalatest/enablers/AggregatingHighPriorityImplicits$$anon$7
  #12 = Class              #11            // org/scalatest/enablers/AggregatingHighPriorityImplicits$$anon$7
  #13 = Utf8               aggregatingNatureOfMap$
  #14 = Utf8               (Lorg/scalatest/enablers/AggregatingHighPriorityImplicits;Lorg/scalactic/Equality;)Lorg/scalatest/enablers/Aggregating;
  #15 = Utf8               $this
  #16 = Utf8               equality
  #17 = Utf8               aggregatingNatureOfMap
  #18 = Utf8               (Lorg/scalactic/Equality;)Lorg/scalatest/enablers/Aggregating;
  #19 = NameAndType        #17:#18        // aggregatingNatureOfMap:(Lorg/scalactic/Equality;)Lorg/scalatest/enablers/Aggregating;
  #20 = InterfaceMethodref #2.#19         // org/scalatest/enablers/AggregatingHighPriorityImplicits.aggregatingNatureOfMap:(Lorg/scalactic/Equality;)Lorg/scalatest/enablers/Aggregating;
  #21 = Utf8               Lorg/scalatest/enablers/AggregatingHighPriorityImplicits;
  #22 = Utf8               Lorg/scalactic/Equality;
  #23 = Utf8               <K:Ljava/lang/Object;V:Ljava/lang/Object;MAP::Lscala/collection/Map<Ljava/lang/Object;Ljava/lang/Object;>;>(Lorg/scalactic/Equality<Lscala/Tuple2<TK;TV;>;>;)Lorg/scalatest/enablers/Aggregating<TMAP;>;
  #24 = Utf8               <init>
  #25 = Utf8               (Lorg/scalatest/enablers/AggregatingHighPriorityImplicits;Lorg/scalactic/Equality;)V
  #26 = NameAndType        #24:#25        // "<init>":(Lorg/scalatest/enablers/AggregatingHighPriorityImplicits;Lorg/scalactic/Equality;)V
  #27 = Methodref          #12.#26        // org/scalatest/enablers/AggregatingHighPriorityImplicits$$anon$7."<init>":(Lorg/scalatest/enablers/AggregatingHighPriorityImplicits;Lorg/scalactic/Equality;)V
  #28 = Utf8               this
  #29 = Utf8               convertEqualityToMapAggregating$
  #30 = Utf8               convertEqualityToMapAggregating
  #31 = NameAndType        #30:#18        // convertEqualityToMapAggregating:(Lorg/scalactic/Equality;)Lorg/scalatest/enablers/Aggregating;
  #32 = InterfaceMethodref #2.#31         // org/scalatest/enablers/AggregatingHighPriorityImplicits.convertEqualityToMapAggregating:(Lorg/scalactic/Equality;)Lorg/scalatest/enablers/Aggregating;
  #33 = Utf8               <K:Ljava/lang/Object;V:Ljava/lang/Object;MAP::Lscala/collection/Map<Ljava/lang/Object;Ljava/lang/Object;>;>(Lorg/scalactic/Equality<Lscala/Tuple2<TK;TV;>;>;)Lorg/scalatest/enablers/Aggregating<Lscala/collection/Map<TK;TV;>;>;
  #34 = Utf8               $init$
  #35 = Utf8               (Lorg/scalatest/enablers/AggregatingHighPriorityImplicits;)V
  #36 = Utf8               Code
  #37 = Utf8               LineNumberTable
  #38 = Utf8               LocalVariableTable
  #39 = Utf8               MethodParameters
  #40 = Utf8               Signature
  #41 = Utf8               InnerClasses
  #42 = Utf8               SourceFile
  #43 = Utf8               RuntimeVisibleAnnotations
  #44 = Utf8               ScalaInlineInfo
  #45 = Utf8               ScalaSig
{
  public static org.scalatest.enablers.Aggregating aggregatingNatureOfMap$(org.scalatest.enablers.AggregatingHighPriorityImplicits, org.scalactic.Equality);
    descriptor: (Lorg/scalatest/enablers/AggregatingHighPriorityImplicits;Lorg/scalactic/Equality;)Lorg/scalatest/enablers/Aggregating;
    flags: (0x1009) ACC_PUBLIC, ACC_STATIC, ACC_SYNTHETIC
    Code:
      stack=2, locals=2, args_size=2
         0: aload_0
         1: aload_1
         2: invokespecial #20                 // InterfaceMethod aggregatingNatureOfMap:(Lorg/scalactic/Equality;)Lorg/scalatest/enablers/Aggregating;
         5: areturn
      LineNumberTable:
        line 521: 0
      LocalVariableTable:
        Start  Length  Slot  Name   Signature
            0       6     0 $this   Lorg/scalatest/enablers/AggregatingHighPriorityImplicits;
            0       6     1 equality   Lorg/scalactic/Equality;
    MethodParameters:
      Name                           Flags
      $this                          final synthetic
      equality                       final

  public default <K extends java.lang.Object, V extends java.lang.Object, MAP extends scala.collection.Map<java.lang.Object, java.lang.Object>> org.scalatest.enablers.Aggregating<MAP> aggregatingNatureOfMap(org.scalactic.Equality<scala.Tuple2<K, V>>);
    descriptor: (Lorg/scalactic/Equality;)Lorg/scalatest/enablers/Aggregating;
    flags: (0x0001) ACC_PUBLIC
    Code:
      stack=4, locals=2, args_size=2
         0: new           #12                 // class org/scalatest/enablers/AggregatingHighPriorityImplicits$$anon$7
         3: dup
         4: aload_0
         5: aload_1
         6: invokespecial #27                 // Method org/scalatest/enablers/AggregatingHighPriorityImplicits$$anon$7."<init>":(Lorg/scalatest/enablers/AggregatingHighPriorityImplicits;Lorg/scalactic/Equality;)V
         9: areturn
      LineNumberTable:
        line 522: 0
      LocalVariableTable:
        Start  Length  Slot  Name   Signature
            0      10     0  this   Lorg/scalatest/enablers/AggregatingHighPriorityImplicits;
            0      10     1 equality   Lorg/scalactic/Equality;
    Signature: #23                          // <K:Ljava/lang/Object;V:Ljava/lang/Object;MAP::Lscala/collection/Map<Ljava/lang/Object;Ljava/lang/Object;>;>(Lorg/scalactic/Equality<Lscala/Tuple2<TK;TV;>;>;)Lorg/scalatest/enablers/Aggregating<TMAP;>;
    MethodParameters:
      Name                           Flags
      equality                       final

  public static org.scalatest.enablers.Aggregating convertEqualityToMapAggregating$(org.scalatest.enablers.AggregatingHighPriorityImplicits, org.scalactic.Equality);
    descriptor: (Lorg/scalatest/enablers/AggregatingHighPriorityImplicits;Lorg/scalactic/Equality;)Lorg/scalatest/enablers/Aggregating;
    flags: (0x1009) ACC_PUBLIC, ACC_STATIC, ACC_SYNTHETIC
    Code:
      stack=2, locals=2, args_size=2
         0: aload_0
         1: aload_1
         2: invokespecial #32                 // InterfaceMethod convertEqualityToMapAggregating:(Lorg/scalactic/Equality;)Lorg/scalatest/enablers/Aggregating;
         5: areturn
      LineNumberTable:
        line 560: 0
      LocalVariableTable:
        Start  Length  Slot  Name   Signature
            0       6     0 $this   Lorg/scalatest/enablers/AggregatingHighPriorityImplicits;
            0       6     1 equality   Lorg/scalactic/Equality;
    MethodParameters:
      Name                           Flags
      $this                          final synthetic
      equality                       final

  public default <K extends java.lang.Object, V extends java.lang.Object, MAP extends scala.collection.Map<java.lang.Object, java.lang.Object>> org.scalatest.enablers.Aggregating<scala.collection.Map<K, V>> convertEqualityToMapAggregating(org.scalactic.Equality<scala.Tuple2<K, V>>);
    descriptor: (Lorg/scalactic/Equality;)Lorg/scalatest/enablers/Aggregating;
    flags: (0x0001) ACC_PUBLIC
    Code:
      stack=2, locals=2, args_size=2
         0: aload_0
         1: aload_1
         2: invokeinterface #20,  2           // InterfaceMethod aggregatingNatureOfMap:(Lorg/scalactic/Equality;)Lorg/scalatest/enablers/Aggregating;
         7: areturn
      LineNumberTable:
        line 561: 0
      LocalVariableTable:
        Start  Length  Slot  Name   Signature
            0       8     0  this   Lorg/scalatest/enablers/AggregatingHighPriorityImplicits;
            0       8     1 equality   Lorg/scalactic/Equality;
    Signature: #33                          // <K:Ljava/lang/Object;V:Ljava/lang/Object;MAP::Lscala/collection/Map<Ljava/lang/Object;Ljava/lang/Object;>;>(Lorg/scalactic/Equality<Lscala/Tuple2<TK;TV;>;>;)Lorg/scalatest/enablers/Aggregating<Lscala/collection/Map<TK;TV;>;>;
    MethodParameters:
      Name                           Flags
      equality                       final

  public static void $init$(org.scalatest.enablers.AggregatingHighPriorityImplicits);
    descriptor: (Lorg/scalatest/enablers/AggregatingHighPriorityImplicits;)V
    flags: (0x0009) ACC_PUBLIC, ACC_STATIC
    Code:
      stack=0, locals=1, args_size=1
         0: return
      LineNumberTable:
        line 510: 0
      LocalVariableTable:
        Start  Length  Slot  Name   Signature
            0       1     0 $this   Lorg/scalatest/enablers/AggregatingHighPriorityImplicits;
    MethodParameters:
      Name                           Flags
      $this                          final synthetic
}
InnerClasses:
  public final #12;                       // class org/scalatest/enablers/AggregatingHighPriorityImplicits$$anon$7
SourceFile: "Aggregating.scala"
RuntimeVisibleAnnotations:
  0: #8(#9=s#10)
    scala.reflect.ScalaSignature(
      bytes="\u0006\u0005)4q\u0001B\u0003\u0011\u0002\u0007\u0005A\u0002C\u0003\u0018\u0001\u0011\u0005\u0001\u0004C\u0003\u001d\u0001\u0011\rQ\u0004C\u0003W\u0001\u0011\rqK\u0001\u0011BO\u001e\u0014XmZ1uS:<\u0007*[4i!JLwN]5us&k\u0007\u000f\\5dSR\u001c(B\u0001\u0004\b\u0003!)g.\u00192mKJ\u001c(B\u0001\u0005\n\u0003%\u00198-\u00197bi\u0016\u001cHOC\u0001\u000b\u0003\ry\'oZ\u0002\u0001\'\r\u0001Qb\u0005\t\u0003\u001dEi\u0011a\u0004\u0006\u0002!\u0005)1oY1mC&\u0011!c\u0004\u0002\u0007\u0003:L(+\u001a4\u0011\u0005Q)R\"A\u0003\n\u0005Y)!\u0001H!hOJ,w-\u0019;j]\u001e\u001cF/\u00198eCJ$\u0017*\u001c9mS\u000eLGo]\u0001\u0007I%t\u0017\u000e\u001e\u0013\u0015\u0003e\u0001\"A\u0004\u000e\n\u0005my!\u0001B+oSR\fa#Y4he\u0016<\u0017\r^5oO:\u000bG/\u001e:f\u001f\u001al\u0015\r]\u000b\u0005=\u0019KE\u0005\u0006\u0002 \u0017B\u0019A\u0003\t\u0012\n\u0005\u0005*!aC!hOJ,w-\u0019;j]\u001e\u0004Ba\t\u0013F\u00112\u0001A!B\u0013\u0003\u0005\u00041#aA\'B!V\u0019q\u0005P\"\u0012\u0005!Z\u0003C\u0001\b*\u0013\tQsBA\u0004O_RD\u0017N\\4\u0011\t1B4H\u0011\b\u0003[Ur!AL\u001a\u000f\u0005=\u0012T\"\u0001\u0019\u000b\u0005EZ\u0011A\u0002\u001fs_>$h(C\u0001\u0011\u0013\t!t\"\u0001\u0006d_2dWm\u0019;j_:L!AN\u001c\u0002\u000fA\f7m[1hK*\u0011AgD\u0005\u0003si\u0012aaR3o\u001b\u0006\u0004(B\u0001\u001c8!\t\u0019C\bB\u0003>I\t\u0007aHA\u0001l#\tAs\b\u0005\u0002\u000f\u0001&\u0011\u0011i\u0004\u0002\u0004\u0003:L\bCA\u0012D\t\u0015!EE1\u0001?\u0005\u00051\bCA\u0012G\t\u00159%A1\u0001?\u0005\u0005Y\u0005CA\u0012J\t\u0015Q%A1\u0001?\u0005\u00051\u0006\"\u0002\'\u0003\u0001\bi\u0015\u0001C3rk\u0006d\u0017\u000e^=\u0011\u00079\u000b6+D\u0001P\u0015\t\u0001\u0016\"A\u0005tG\u0006d\u0017m\u0019;jG&\u0011!k\u0014\u0002\t\u000bF,\u0018\r\\5usB!a\u0002V#I\u0013\t)vB\u0001\u0004UkBdWMM\u0001 G>tg/\u001a:u\u000bF,\u0018\r\\5usR{W*\u00199BO\u001e\u0014XmZ1uS:<W\u0003\u0002-]=\n$\"!W0\u0011\u0007Q\u0001#\f\u0005\u0003-qmk\u0006CA\u0012]\t\u001595A1\u0001?!\t\u0019c\fB\u0003K\u0007\t\u0007a\bC\u0003M\u0007\u0001\u0007\u0001\rE\u0002O#\u0006\u0004BA\u0004+\\;\u0012)Qe\u0001b\u0001GV\u0019AmZ5\u0012\u0005!*\u0007\u0003\u0002\u00179M\"\u0004\"aI4\u0005\u000bu\u0012\'\u0019\u0001 \u0011\u0005\rJG!\u0002#c\u0005\u0004q\u0004"
    )
  ScalaInlineInfo: length = 0x1D (unknown attribute)
   01 00 00 05 00 22 00 23 01 00 11 00 12 00 00 0D
   00 0E 01 00 1E 00 12 00 00 1D 00 0E 01
  ScalaSig: length = 0x3 (unknown attribute)
   05 02 00
