Classfile /Users/mw/Projects/slang-braindump/.jar/jar11/assemble/slang-braindump/assemble/content/org/scalatest/enablers/ContainingStandardImplicits$$anon$7.class
  Last modified May 29, 2022; size 5509 bytes
  SHA-256 checksum 3a28976de6b69823aba1e305f73e97429fca432dffc38d0c1d9a624a75d184e9
  Compiled from "Containing.scala"
public final class org.scalatest.enablers.ContainingStandardImplicits$$anon$7 extends java.lang.Object implements org.scalatest.enablers.Containing<org.scalactic.Every<E>>
  minor version: 0
  major version: 52
  flags: (0x0031) ACC_PUBLIC, ACC_FINAL, ACC_SUPER
  this_class: #2                          // org/scalatest/enablers/ContainingStandardImplicits$$anon$7
  super_class: #5                         // java/lang/Object
  interfaces: 1, fields: 2, methods: 12, attributes: 7
Constant pool:
    #1 = Utf8               org/scalatest/enablers/ContainingStandardImplicits$$anon$7
    #2 = Class              #1            // org/scalatest/enablers/ContainingStandardImplicits$$anon$7
    #3 = Utf8               Ljava/lang/Object;Lorg/scalatest/enablers/Containing<Lorg/scalactic/Every<TE;>;>;
    #4 = Utf8               java/lang/Object
    #5 = Class              #4            // java/lang/Object
    #6 = Utf8               org/scalatest/enablers/Containing
    #7 = Class              #6            // org/scalatest/enablers/Containing
    #8 = Utf8               Containing.scala
    #9 = Utf8               org/scalatest/enablers/ContainingStandardImplicits
   #10 = Class              #9            // org/scalatest/enablers/ContainingStandardImplicits
   #11 = Utf8               containingNatureOfEvery
   #12 = Utf8               (Lorg/scalactic/Equality;)Lorg/scalatest/enablers/Containing;
   #13 = NameAndType        #11:#12       // containingNatureOfEvery:(Lorg/scalactic/Equality;)Lorg/scalatest/enablers/Containing;
   #14 = Utf8               java/lang/invoke/MethodHandles$Lookup
   #15 = Class              #14           // java/lang/invoke/MethodHandles$Lookup
   #16 = Utf8               java/lang/invoke/MethodHandles
   #17 = Class              #16           // java/lang/invoke/MethodHandles
   #18 = Utf8               Lookup
   #19 = Utf8               $outer
   #20 = Utf8               Lorg/scalatest/enablers/ContainingStandardImplicits;
   #21 = Utf8               equality$9
   #22 = Utf8               Lorg/scalactic/Equality;
   #23 = Utf8               contains
   #24 = Utf8               (Lorg/scalactic/Every;Ljava/lang/Object;)Z
   #25 = Utf8               (Lorg/scalactic/Every<TE;>;Ljava/lang/Object;)Z
   #26 = Utf8               every
   #27 = Utf8               ele
   #28 = NameAndType        #21:#22       // equality$9:Lorg/scalactic/Equality;
   #29 = Fieldref           #2.#28        // org/scalatest/enablers/ContainingStandardImplicits$$anon$7.equality$9:Lorg/scalactic/Equality;
   #30 = Utf8               org/scalactic/NormalizingEquality
   #31 = Class              #30           // org/scalactic/NormalizingEquality
   #32 = Utf8               normalizedOrSame
   #33 = Utf8               (Ljava/lang/Object;)Ljava/lang/Object;
   #34 = NameAndType        #32:#33       // normalizedOrSame:(Ljava/lang/Object;)Ljava/lang/Object;
   #35 = InterfaceMethodref #31.#34       // org/scalactic/NormalizingEquality.normalizedOrSame:(Ljava/lang/Object;)Ljava/lang/Object;
   #36 = MethodType         #33           //  (Ljava/lang/Object;)Ljava/lang/Object;
   #37 = Utf8               $anonfun$contains$7$adapted
   #38 = Utf8               (Lorg/scalactic/NormalizingEquality;Ljava/lang/Object;Ljava/lang/Object;)Ljava/lang/Object;
   #39 = NameAndType        #37:#38       // $anonfun$contains$7$adapted:(Lorg/scalactic/NormalizingEquality;Ljava/lang/Object;Ljava/lang/Object;)Ljava/lang/Object;
   #40 = Methodref          #2.#39        // org/scalatest/enablers/ContainingStandardImplicits$$anon$7.$anonfun$contains$7$adapted:(Lorg/scalactic/NormalizingEquality;Ljava/lang/Object;Ljava/lang/Object;)Ljava/lang/Object;
   #41 = MethodHandle       6:#40         // REF_invokeStatic org/scalatest/enablers/ContainingStandardImplicits$$anon$7.$anonfun$contains$7$adapted:(Lorg/scalactic/NormalizingEquality;Ljava/lang/Object;Ljava/lang/Object;)Ljava/lang/Object;
   #42 = Integer            1
   #43 = Utf8               java/lang/invoke/LambdaMetafactory
   #44 = Class              #43           // java/lang/invoke/LambdaMetafactory
   #45 = Utf8               altMetafactory
   #46 = Utf8               (Ljava/lang/invoke/MethodHandles$Lookup;Ljava/lang/String;Ljava/lang/invoke/MethodType;[Ljava/lang/Object;)Ljava/lang/invoke/CallSite;
   #47 = NameAndType        #45:#46       // altMetafactory:(Ljava/lang/invoke/MethodHandles$Lookup;Ljava/lang/String;Ljava/lang/invoke/MethodType;[Ljava/lang/Object;)Ljava/lang/invoke/CallSite;
   #48 = Methodref          #44.#47       // java/lang/invoke/LambdaMetafactory.altMetafactory:(Ljava/lang/invoke/MethodHandles$Lookup;Ljava/lang/String;Ljava/lang/invoke/MethodType;[Ljava/lang/Object;)Ljava/lang/invoke/CallSite;
   #49 = MethodHandle       6:#48         // REF_invokeStatic java/lang/invoke/LambdaMetafactory.altMetafactory:(Ljava/lang/invoke/MethodHandles$Lookup;Ljava/lang/String;Ljava/lang/invoke/MethodType;[Ljava/lang/Object;)Ljava/lang/invoke/CallSite;
   #50 = Utf8               apply
   #51 = Utf8               (Lorg/scalactic/NormalizingEquality;Ljava/lang/Object;)Lscala/Function1;
   #52 = NameAndType        #50:#51       // apply:(Lorg/scalactic/NormalizingEquality;Ljava/lang/Object;)Lscala/Function1;
   #53 = InvokeDynamic      #0:#52        // #0:apply:(Lorg/scalactic/NormalizingEquality;Ljava/lang/Object;)Lscala/Function1;
   #54 = Utf8               org/scalactic/Every
   #55 = Class              #54           // org/scalactic/Every
   #56 = Utf8               exists
   #57 = Utf8               (Lscala/Function1;)Z
   #58 = NameAndType        #56:#57       // exists:(Lscala/Function1;)Z
   #59 = Methodref          #55.#58       // org/scalactic/Every.exists:(Lscala/Function1;)Z
   #60 = Utf8               $anonfun$contains$8$adapted
   #61 = Utf8               (Lorg/scalatest/enablers/ContainingStandardImplicits$$anon$7;Ljava/lang/Object;Ljava/lang/Object;)Ljava/lang/Object;
   #62 = NameAndType        #60:#61       // $anonfun$contains$8$adapted:(Lorg/scalatest/enablers/ContainingStandardImplicits$$anon$7;Ljava/lang/Object;Ljava/lang/Object;)Ljava/lang/Object;
   #63 = Methodref          #2.#62        // org/scalatest/enablers/ContainingStandardImplicits$$anon$7.$anonfun$contains$8$adapted:(Lorg/scalatest/enablers/ContainingStandardImplicits$$anon$7;Ljava/lang/Object;Ljava/lang/Object;)Ljava/lang/Object;
   #64 = MethodHandle       6:#63         // REF_invokeStatic org/scalatest/enablers/ContainingStandardImplicits$$anon$7.$anonfun$contains$8$adapted:(Lorg/scalatest/enablers/ContainingStandardImplicits$$anon$7;Ljava/lang/Object;Ljava/lang/Object;)Ljava/lang/Object;
   #65 = Utf8               (Lorg/scalatest/enablers/ContainingStandardImplicits$$anon$7;Ljava/lang/Object;)Lscala/Function1;
   #66 = NameAndType        #50:#65       // apply:(Lorg/scalatest/enablers/ContainingStandardImplicits$$anon$7;Ljava/lang/Object;)Lscala/Function1;
   #67 = InvokeDynamic      #1:#66        // #1:apply:(Lorg/scalatest/enablers/ContainingStandardImplicits$$anon$7;Ljava/lang/Object;)Lscala/Function1;
   #68 = Utf8               normRight
   #69 = Utf8               Ljava/lang/Object;
   #70 = Utf8               this
   #71 = Utf8               Lorg/scalatest/enablers/ContainingStandardImplicits$$anon$7;
   #72 = Utf8               Lorg/scalactic/Every;
   #73 = Utf8               org/scalactic/Equality
   #74 = Class              #73           // org/scalactic/Equality
   #75 = Utf8               containsOneOf
   #76 = Utf8               (Lorg/scalactic/Every;Lscala/collection/Seq;)Z
   #77 = Utf8               (Lorg/scalactic/Every<TE;>;Lscala/collection/Seq<Ljava/lang/Object;>;)Z
   #78 = Utf8               elements
   #79 = NameAndType        #19:#20       // $outer:Lorg/scalatest/enablers/ContainingStandardImplicits;
   #80 = Fieldref           #2.#79        // org/scalatest/enablers/ContainingStandardImplicits$$anon$7.$outer:Lorg/scalatest/enablers/ContainingStandardImplicits;
   #81 = Utf8               org/scalactic/Every$
   #82 = Class              #81           // org/scalactic/Every$
   #83 = Utf8               MODULE$
   #84 = Utf8               Lorg/scalactic/Every$;
   #85 = NameAndType        #83:#84       // MODULE$:Lorg/scalactic/Every$;
   #86 = Fieldref           #82.#85       // org/scalactic/Every$.MODULE$:Lorg/scalactic/Every$;
   #87 = Utf8               everyToGenTraversableOnce
   #88 = Utf8               (Lorg/scalactic/Every;)Lscala/collection/immutable/IndexedSeq;
   #89 = NameAndType        #87:#88       // everyToGenTraversableOnce:(Lorg/scalactic/Every;)Lscala/collection/immutable/IndexedSeq;
   #90 = Methodref          #82.#89       // org/scalactic/Every$.everyToGenTraversableOnce:(Lorg/scalactic/Every;)Lscala/collection/immutable/IndexedSeq;
   #91 = Utf8               checkOneOf
   #92 = Utf8               (Lscala/collection/IterableOnce;Lscala/collection/Iterable;Lorg/scalactic/Equality;)Lscala/collection/immutable/Set;
   #93 = NameAndType        #91:#92       // checkOneOf:(Lscala/collection/IterableOnce;Lscala/collection/Iterable;Lorg/scalactic/Equality;)Lscala/collection/immutable/Set;
   #94 = InterfaceMethodref #10.#93       // org/scalatest/enablers/ContainingStandardImplicits.checkOneOf:(Lscala/collection/IterableOnce;Lscala/collection/Iterable;Lorg/scalactic/Equality;)Lscala/collection/immutable/Set;
   #95 = Utf8               scala/collection/immutable/Set
   #96 = Class              #95           // scala/collection/immutable/Set
   #97 = Utf8               size
   #98 = Utf8               ()I
   #99 = NameAndType        #97:#98       // size:()I
  #100 = InterfaceMethodref #96.#99       // scala/collection/immutable/Set.size:()I
  #101 = Utf8               foundSet
  #102 = Utf8               Lscala/collection/immutable/Set;
  #103 = Utf8               Lscala/collection/Seq;
  #104 = Utf8               containsNoneOf
  #105 = Utf8               checkNoneOf
  #106 = Utf8               (Lscala/collection/IterableOnce;Lscala/collection/Iterable;Lorg/scalactic/Equality;)Lscala/Option;
  #107 = NameAndType        #105:#106     // checkNoneOf:(Lscala/collection/IterableOnce;Lscala/collection/Iterable;Lorg/scalactic/Equality;)Lscala/Option;
  #108 = InterfaceMethodref #10.#107      // org/scalatest/enablers/ContainingStandardImplicits.checkNoneOf:(Lscala/collection/IterableOnce;Lscala/collection/Iterable;Lorg/scalactic/Equality;)Lscala/Option;
  #109 = Utf8               scala/Option
  #110 = Class              #109          // scala/Option
  #111 = Utf8               isDefined
  #112 = Utf8               ()Z
  #113 = NameAndType        #111:#112     // isDefined:()Z
  #114 = Methodref          #110.#113     // scala/Option.isDefined:()Z
  #115 = Utf8               found
  #116 = Utf8               Lscala/Option;
  #117 = Utf8               (Ljava/lang/Object;Lscala/collection/Seq;)Z
  #118 = Utf8               container
  #119 = NameAndType        #104:#76      // containsNoneOf:(Lorg/scalactic/Every;Lscala/collection/Seq;)Z
  #120 = Methodref          #2.#119       // org/scalatest/enablers/ContainingStandardImplicits$$anon$7.containsNoneOf:(Lorg/scalactic/Every;Lscala/collection/Seq;)Z
  #121 = NameAndType        #75:#76       // containsOneOf:(Lorg/scalactic/Every;Lscala/collection/Seq;)Z
  #122 = Methodref          #2.#121       // org/scalatest/enablers/ContainingStandardImplicits$$anon$7.containsOneOf:(Lorg/scalactic/Every;Lscala/collection/Seq;)Z
  #123 = Utf8               (Ljava/lang/Object;Ljava/lang/Object;)Z
  #124 = Utf8               element
  #125 = NameAndType        #23:#24       // contains:(Lorg/scalactic/Every;Ljava/lang/Object;)Z
  #126 = Methodref          #2.#125       // org/scalatest/enablers/ContainingStandardImplicits$$anon$7.contains:(Lorg/scalactic/Every;Ljava/lang/Object;)Z
  #127 = Utf8               $anonfun$contains$7
  #128 = Utf8               (Lorg/scalactic/NormalizingEquality;Ljava/lang/Object;Ljava/lang/Object;)Z
  #129 = Utf8               x2$2
  #130 = Utf8               normRight$2
  #131 = Utf8               e
  #132 = Utf8               afterNormalizationEquality
  #133 = Utf8               ()Lorg/scalactic/Equality;
  #134 = NameAndType        #132:#133     // afterNormalizationEquality:()Lorg/scalactic/Equality;
  #135 = InterfaceMethodref #31.#134      // org/scalactic/NormalizingEquality.afterNormalizationEquality:()Lorg/scalactic/Equality;
  #136 = Utf8               normalized
  #137 = NameAndType        #136:#33      // normalized:(Ljava/lang/Object;)Ljava/lang/Object;
  #138 = InterfaceMethodref #31.#137      // org/scalactic/NormalizingEquality.normalized:(Ljava/lang/Object;)Ljava/lang/Object;
  #139 = Utf8               areEqual
  #140 = NameAndType        #139:#123     // areEqual:(Ljava/lang/Object;Ljava/lang/Object;)Z
  #141 = InterfaceMethodref #74.#140      // org/scalactic/Equality.areEqual:(Ljava/lang/Object;Ljava/lang/Object;)Z
  #142 = Utf8               Lorg/scalactic/NormalizingEquality;
  #143 = Utf8               $anonfun$contains$8
  #144 = Utf8               (Lorg/scalatest/enablers/ContainingStandardImplicits$$anon$7;Ljava/lang/Object;Ljava/lang/Object;)Z
  #145 = Utf8               $this
  #146 = Utf8               ele$6
  #147 = Utf8               <init>
  #148 = Utf8               (Lorg/scalatest/enablers/ContainingStandardImplicits;Lorg/scalactic/Equality;)V
  #149 = Utf8               ()V
  #150 = NameAndType        #147:#149     // "<init>":()V
  #151 = Methodref          #5.#150       // java/lang/Object."<init>":()V
  #152 = NameAndType        #127:#128     // $anonfun$contains$7:(Lorg/scalactic/NormalizingEquality;Ljava/lang/Object;Ljava/lang/Object;)Z
  #153 = Methodref          #2.#152       // org/scalatest/enablers/ContainingStandardImplicits$$anon$7.$anonfun$contains$7:(Lorg/scalactic/NormalizingEquality;Ljava/lang/Object;Ljava/lang/Object;)Z
  #154 = Utf8               scala/runtime/BoxesRunTime
  #155 = Class              #154          // scala/runtime/BoxesRunTime
  #156 = Utf8               boxToBoolean
  #157 = Utf8               (Z)Ljava/lang/Boolean;
  #158 = NameAndType        #156:#157     // boxToBoolean:(Z)Ljava/lang/Boolean;
  #159 = Methodref          #155.#158     // scala/runtime/BoxesRunTime.boxToBoolean:(Z)Ljava/lang/Boolean;
  #160 = NameAndType        #143:#144     // $anonfun$contains$8:(Lorg/scalatest/enablers/ContainingStandardImplicits$$anon$7;Ljava/lang/Object;Ljava/lang/Object;)Z
  #161 = Methodref          #2.#160       // org/scalatest/enablers/ContainingStandardImplicits$$anon$7.$anonfun$contains$8:(Lorg/scalatest/enablers/ContainingStandardImplicits$$anon$7;Ljava/lang/Object;Ljava/lang/Object;)Z
  #162 = Utf8               $deserializeLambda$
  #163 = Utf8               (Ljava/lang/invoke/SerializedLambda;)Ljava/lang/Object;
  #164 = Utf8               scala/runtime/LambdaDeserialize
  #165 = Class              #164          // scala/runtime/LambdaDeserialize
  #166 = Utf8               bootstrap
  #167 = Utf8               (Ljava/lang/invoke/MethodHandles$Lookup;Ljava/lang/String;Ljava/lang/invoke/MethodType;[Ljava/lang/invoke/MethodHandle;)Ljava/lang/invoke/CallSite;
  #168 = NameAndType        #166:#167     // bootstrap:(Ljava/lang/invoke/MethodHandles$Lookup;Ljava/lang/String;Ljava/lang/invoke/MethodType;[Ljava/lang/invoke/MethodHandle;)Ljava/lang/invoke/CallSite;
  #169 = Methodref          #165.#168     // scala/runtime/LambdaDeserialize.bootstrap:(Ljava/lang/invoke/MethodHandles$Lookup;Ljava/lang/String;Ljava/lang/invoke/MethodType;[Ljava/lang/invoke/MethodHandle;)Ljava/lang/invoke/CallSite;
  #170 = MethodHandle       6:#169        // REF_invokeStatic scala/runtime/LambdaDeserialize.bootstrap:(Ljava/lang/invoke/MethodHandles$Lookup;Ljava/lang/String;Ljava/lang/invoke/MethodType;[Ljava/lang/invoke/MethodHandle;)Ljava/lang/invoke/CallSite;
  #171 = Utf8               lambdaDeserialize
  #172 = NameAndType        #171:#163     // lambdaDeserialize:(Ljava/lang/invoke/SerializedLambda;)Ljava/lang/Object;
  #173 = InvokeDynamic      #2:#172       // #2:lambdaDeserialize:(Ljava/lang/invoke/SerializedLambda;)Ljava/lang/Object;
  #174 = Utf8               Code
  #175 = Utf8               StackMapTable
  #176 = Utf8               LineNumberTable
  #177 = Utf8               LocalVariableTable
  #178 = Utf8               Signature
  #179 = Utf8               MethodParameters
  #180 = Utf8               InnerClasses
  #181 = Utf8               EnclosingMethod
  #182 = Utf8               SourceFile
  #183 = Utf8               BootstrapMethods
  #184 = Utf8               ScalaInlineInfo
  #185 = Utf8               Scala
{
  private final org.scalatest.enablers.ContainingStandardImplicits $outer;
    descriptor: Lorg/scalatest/enablers/ContainingStandardImplicits;
    flags: (0x1012) ACC_PRIVATE, ACC_FINAL, ACC_SYNTHETIC

  private final org.scalactic.Equality equality$9;
    descriptor: Lorg/scalactic/Equality;
    flags: (0x0012) ACC_PRIVATE, ACC_FINAL

  public boolean contains(org.scalactic.Every<E>, java.lang.Object);
    descriptor: (Lorg/scalactic/Every;Ljava/lang/Object;)Z
    flags: (0x0001) ACC_PUBLIC
    Code:
      stack=3, locals=7, args_size=3
         0: aload_0
         1: getfield      #29                 // Field equality$9:Lorg/scalactic/Equality;
         4: astore        4
         6: aload         4
         8: instanceof    #31                 // class org/scalactic/NormalizingEquality
        11: ifeq          48
        14: aload         4
        16: checkcast     #31                 // class org/scalactic/NormalizingEquality
        19: astore        5
        21: aload         5
        23: aload_2
        24: invokeinterface #35,  2           // InterfaceMethod org/scalactic/NormalizingEquality.normalizedOrSame:(Ljava/lang/Object;)Ljava/lang/Object;
        29: astore        6
        31: aload_1
        32: aload         5
        34: aload         6
        36: invokedynamic #53,  0             // InvokeDynamic #0:apply:(Lorg/scalactic/NormalizingEquality;Ljava/lang/Object;)Lscala/Function1;
        41: invokevirtual #59                 // Method org/scalactic/Every.exists:(Lscala/Function1;)Z
        44: istore_3
        45: goto          66
        48: goto          51
        51: aload_1
        52: aload_0
        53: aload_2
        54: invokedynamic #67,  0             // InvokeDynamic #1:apply:(Lorg/scalatest/enablers/ContainingStandardImplicits$$anon$7;Ljava/lang/Object;)Lscala/Function1;
        59: invokevirtual #59                 // Method org/scalactic/Every.exists:(Lscala/Function1;)Z
        62: istore_3
        63: goto          66
        66: iload_3
        67: ireturn
      StackMapTable: number_of_entries = 3
        frame_type = 253 /* append */
          offset_delta = 48
          locals = [ top, class org/scalactic/Equality ]
        frame_type = 2 /* same */
        frame_type = 255 /* full_frame */
          offset_delta = 14
          locals = [ class org/scalatest/enablers/ContainingStandardImplicits$$anon$7, class org/scalactic/Every, class java/lang/Object, int, class org/scalactic/Equality ]
          stack = []
      LineNumberTable:
        line 457: 0
        line 458: 6
        line 459: 21
        line 460: 31
        line 458: 48
        line 461: 51
        line 457: 66
      LocalVariableTable:
        Start  Length  Slot  Name   Signature
           31      13     6 normRight   Ljava/lang/Object;
            0      68     0  this   Lorg/scalatest/enablers/ContainingStandardImplicits$$anon$7;
            0      68     1 every   Lorg/scalactic/Every;
            0      68     2   ele   Ljava/lang/Object;
    Signature: #25                          // (Lorg/scalactic/Every<TE;>;Ljava/lang/Object;)Z
    MethodParameters:
      Name                           Flags
      every                          final
      ele                            final

  public boolean containsOneOf(org.scalactic.Every<E>, scala.collection.Seq<java.lang.Object>);
    descriptor: (Lorg/scalactic/Every;Lscala/collection/Seq;)Z
    flags: (0x0001) ACC_PUBLIC
    Code:
      stack=4, locals=4, args_size=3
         0: aload_0
         1: getfield      #80                 // Field $outer:Lorg/scalatest/enablers/ContainingStandardImplicits;
         4: getstatic     #86                 // Field org/scalactic/Every$.MODULE$:Lorg/scalactic/Every$;
         7: aload_1
         8: invokevirtual #90                 // Method org/scalactic/Every$.everyToGenTraversableOnce:(Lorg/scalactic/Every;)Lscala/collection/immutable/IndexedSeq;
        11: aload_2
        12: aload_0
        13: getfield      #29                 // Field equality$9:Lorg/scalactic/Equality;
        16: invokeinterface #94,  4           // InterfaceMethod org/scalatest/enablers/ContainingStandardImplicits.checkOneOf:(Lscala/collection/IterableOnce;Lscala/collection/Iterable;Lorg/scalactic/Equality;)Lscala/collection/immutable/Set;
        21: astore_3
        22: aload_3
        23: invokeinterface #100,  1          // InterfaceMethod scala/collection/immutable/Set.size:()I
        28: iconst_1
        29: if_icmpne     36
        32: iconst_1
        33: goto          37
        36: iconst_0
        37: ireturn
      StackMapTable: number_of_entries = 2
        frame_type = 252 /* append */
          offset_delta = 36
          locals = [ class scala/collection/immutable/Set ]
        frame_type = 64 /* same_locals_1_stack_item */
          stack = [ int ]
      LineNumberTable:
        line 464: 0
        line 465: 22
      LocalVariableTable:
        Start  Length  Slot  Name   Signature
           22      15     3 foundSet   Lscala/collection/immutable/Set;
            0      38     0  this   Lorg/scalatest/enablers/ContainingStandardImplicits$$anon$7;
            0      38     1 every   Lorg/scalactic/Every;
            0      38     2 elements   Lscala/collection/Seq;
    Signature: #77                          // (Lorg/scalactic/Every<TE;>;Lscala/collection/Seq<Ljava/lang/Object;>;)Z
    MethodParameters:
      Name                           Flags
      every                          final
      elements                       final

  public boolean containsNoneOf(org.scalactic.Every<E>, scala.collection.Seq<java.lang.Object>);
    descriptor: (Lorg/scalactic/Every;Lscala/collection/Seq;)Z
    flags: (0x0001) ACC_PUBLIC
    Code:
      stack=4, locals=4, args_size=3
         0: aload_0
         1: getfield      #80                 // Field $outer:Lorg/scalatest/enablers/ContainingStandardImplicits;
         4: getstatic     #86                 // Field org/scalactic/Every$.MODULE$:Lorg/scalactic/Every$;
         7: aload_1
         8: invokevirtual #90                 // Method org/scalactic/Every$.everyToGenTraversableOnce:(Lorg/scalactic/Every;)Lscala/collection/immutable/IndexedSeq;
        11: aload_2
        12: aload_0
        13: getfield      #29                 // Field equality$9:Lorg/scalactic/Equality;
        16: invokeinterface #108,  4          // InterfaceMethod org/scalatest/enablers/ContainingStandardImplicits.checkNoneOf:(Lscala/collection/IterableOnce;Lscala/collection/Iterable;Lorg/scalactic/Equality;)Lscala/Option;
        21: astore_3
        22: aload_3
        23: invokevirtual #114                // Method scala/Option.isDefined:()Z
        26: ifne          33
        29: iconst_1
        30: goto          34
        33: iconst_0
        34: ireturn
      StackMapTable: number_of_entries = 2
        frame_type = 252 /* append */
          offset_delta = 33
          locals = [ class scala/Option ]
        frame_type = 64 /* same_locals_1_stack_item */
          stack = [ int ]
      LineNumberTable:
        line 468: 0
        line 469: 22
      LocalVariableTable:
        Start  Length  Slot  Name   Signature
           22      12     3 found   Lscala/Option;
            0      35     0  this   Lorg/scalatest/enablers/ContainingStandardImplicits$$anon$7;
            0      35     1 every   Lorg/scalactic/Every;
            0      35     2 elements   Lscala/collection/Seq;
    Signature: #77                          // (Lorg/scalactic/Every<TE;>;Lscala/collection/Seq<Ljava/lang/Object;>;)Z
    MethodParameters:
      Name                           Flags
      every                          final
      elements                       final

  public boolean containsNoneOf(java.lang.Object, scala.collection.Seq);
    descriptor: (Ljava/lang/Object;Lscala/collection/Seq;)Z
    flags: (0x1041) ACC_PUBLIC, ACC_BRIDGE, ACC_SYNTHETIC
    Code:
      stack=3, locals=3, args_size=3
         0: aload_0
         1: aload_1
         2: checkcast     #55                 // class org/scalactic/Every
         5: aload_2
         6: invokevirtual #120                // Method containsNoneOf:(Lorg/scalactic/Every;Lscala/collection/Seq;)Z
         9: ireturn
      LineNumberTable:
        line 455: 0
      LocalVariableTable:
        Start  Length  Slot  Name   Signature
            0      10     0  this   Lorg/scalatest/enablers/ContainingStandardImplicits$$anon$7;
            0      10     1 container   Ljava/lang/Object;
            0      10     2 elements   Lscala/collection/Seq;
    MethodParameters:
      Name                           Flags
      container                      final
      elements                       final

  public boolean containsOneOf(java.lang.Object, scala.collection.Seq);
    descriptor: (Ljava/lang/Object;Lscala/collection/Seq;)Z
    flags: (0x1041) ACC_PUBLIC, ACC_BRIDGE, ACC_SYNTHETIC
    Code:
      stack=3, locals=3, args_size=3
         0: aload_0
         1: aload_1
         2: checkcast     #55                 // class org/scalactic/Every
         5: aload_2
         6: invokevirtual #122                // Method containsOneOf:(Lorg/scalactic/Every;Lscala/collection/Seq;)Z
         9: ireturn
      LineNumberTable:
        line 455: 0
      LocalVariableTable:
        Start  Length  Slot  Name   Signature
            0      10     0  this   Lorg/scalatest/enablers/ContainingStandardImplicits$$anon$7;
            0      10     1 container   Ljava/lang/Object;
            0      10     2 elements   Lscala/collection/Seq;
    MethodParameters:
      Name                           Flags
      container                      final
      elements                       final

  public boolean contains(java.lang.Object, java.lang.Object);
    descriptor: (Ljava/lang/Object;Ljava/lang/Object;)Z
    flags: (0x1041) ACC_PUBLIC, ACC_BRIDGE, ACC_SYNTHETIC
    Code:
      stack=3, locals=3, args_size=3
         0: aload_0
         1: aload_1
         2: checkcast     #55                 // class org/scalactic/Every
         5: aload_2
         6: invokevirtual #126                // Method contains:(Lorg/scalactic/Every;Ljava/lang/Object;)Z
         9: ireturn
      LineNumberTable:
        line 455: 0
      LocalVariableTable:
        Start  Length  Slot  Name   Signature
            0      10     0  this   Lorg/scalatest/enablers/ContainingStandardImplicits$$anon$7;
            0      10     1 container   Ljava/lang/Object;
            0      10     2 element   Ljava/lang/Object;
    MethodParameters:
      Name                           Flags
      container                      final
      element                        final

  public static final boolean $anonfun$contains$7(org.scalactic.NormalizingEquality, java.lang.Object, java.lang.Object);
    descriptor: (Lorg/scalactic/NormalizingEquality;Ljava/lang/Object;Ljava/lang/Object;)Z
    flags: (0x1019) ACC_PUBLIC, ACC_STATIC, ACC_FINAL, ACC_SYNTHETIC
    Code:
      stack=3, locals=3, args_size=3
         0: aload_0
         1: invokeinterface #135,  1          // InterfaceMethod org/scalactic/NormalizingEquality.afterNormalizationEquality:()Lorg/scalactic/Equality;
         6: aload_0
         7: aload_2
         8: invokeinterface #138,  2          // InterfaceMethod org/scalactic/NormalizingEquality.normalized:(Ljava/lang/Object;)Ljava/lang/Object;
        13: aload_1
        14: invokeinterface #141,  3          // InterfaceMethod org/scalactic/Equality.areEqual:(Ljava/lang/Object;Ljava/lang/Object;)Z
        19: ireturn
      LineNumberTable:
        line 460: 0
      LocalVariableTable:
        Start  Length  Slot  Name   Signature
            0      20     0  x2$2   Lorg/scalactic/NormalizingEquality;
            0      20     1 normRight$2   Ljava/lang/Object;
            0      20     2     e   Ljava/lang/Object;
    MethodParameters:
      Name                           Flags
      x2$2                           final
      normRight$2                    final
      e                              final

  public static final boolean $anonfun$contains$8(org.scalatest.enablers.ContainingStandardImplicits$$anon$7, java.lang.Object, java.lang.Object);
    descriptor: (Lorg/scalatest/enablers/ContainingStandardImplicits$$anon$7;Ljava/lang/Object;Ljava/lang/Object;)Z
    flags: (0x1019) ACC_PUBLIC, ACC_STATIC, ACC_FINAL, ACC_SYNTHETIC
    Code:
      stack=3, locals=3, args_size=3
         0: aload_0
         1: getfield      #29                 // Field equality$9:Lorg/scalactic/Equality;
         4: aload_2
         5: aload_1
         6: invokeinterface #141,  3          // InterfaceMethod org/scalactic/Equality.areEqual:(Ljava/lang/Object;Ljava/lang/Object;)Z
        11: ireturn
      LineNumberTable:
        line 461: 0
      LocalVariableTable:
        Start  Length  Slot  Name   Signature
            0      12     0 $this   Lorg/scalatest/enablers/ContainingStandardImplicits$$anon$7;
            0      12     1 ele$6   Ljava/lang/Object;
            0      12     2     e   Ljava/lang/Object;
    MethodParameters:
      Name                           Flags
      $this                          final synthetic
      ele$6                          final
      e                              final

  public org.scalatest.enablers.ContainingStandardImplicits$$anon$7(org.scalatest.enablers.ContainingStandardImplicits, org.scalactic.Equality);
    descriptor: (Lorg/scalatest/enablers/ContainingStandardImplicits;Lorg/scalactic/Equality;)V
    flags: (0x0001) ACC_PUBLIC
    Code:
      stack=2, locals=3, args_size=3
         0: aload_1
         1: ifnonnull     6
         4: aconst_null
         5: athrow
         6: aload_0
         7: aload_1
         8: putfield      #80                 // Field $outer:Lorg/scalatest/enablers/ContainingStandardImplicits;
        11: aload_0
        12: aload_2
        13: putfield      #29                 // Field equality$9:Lorg/scalactic/Equality;
        16: aload_0
        17: invokespecial #151                // Method java/lang/Object."<init>":()V
        20: return
      StackMapTable: number_of_entries = 1
        frame_type = 6 /* same */
      LineNumberTable:
        line 455: 0
        line 454: 11
        line 455: 16
      LocalVariableTable:
        Start  Length  Slot  Name   Signature
            0      21     0  this   Lorg/scalatest/enablers/ContainingStandardImplicits$$anon$7;
            0      21     1 $outer   Lorg/scalatest/enablers/ContainingStandardImplicits;
            0      21     2 equality$9   Lorg/scalactic/Equality;
    MethodParameters:
      Name                           Flags
      $outer                         final synthetic
      equality$9                     final

  public static final java.lang.Object $anonfun$contains$7$adapted(org.scalactic.NormalizingEquality, java.lang.Object, java.lang.Object);
    descriptor: (Lorg/scalactic/NormalizingEquality;Ljava/lang/Object;Ljava/lang/Object;)Ljava/lang/Object;
    flags: (0x1019) ACC_PUBLIC, ACC_STATIC, ACC_FINAL, ACC_SYNTHETIC
    Code:
      stack=3, locals=3, args_size=3
         0: aload_0
         1: aload_1
         2: aload_2
         3: invokestatic  #153                // Method $anonfun$contains$7:(Lorg/scalactic/NormalizingEquality;Ljava/lang/Object;Ljava/lang/Object;)Z
         6: invokestatic  #159                // Method scala/runtime/BoxesRunTime.boxToBoolean:(Z)Ljava/lang/Boolean;
         9: areturn
      LineNumberTable:
        line 460: 0
      LocalVariableTable:
        Start  Length  Slot  Name   Signature
            0      10     0  x2$2   Lorg/scalactic/NormalizingEquality;
            0      10     1 normRight$2   Ljava/lang/Object;
            0      10     2     e   Ljava/lang/Object;
    MethodParameters:
      Name                           Flags
      x2$2                           final
      normRight$2                    final
      e                              final

  public static final java.lang.Object $anonfun$contains$8$adapted(org.scalatest.enablers.ContainingStandardImplicits$$anon$7, java.lang.Object, java.lang.Object);
    descriptor: (Lorg/scalatest/enablers/ContainingStandardImplicits$$anon$7;Ljava/lang/Object;Ljava/lang/Object;)Ljava/lang/Object;
    flags: (0x1019) ACC_PUBLIC, ACC_STATIC, ACC_FINAL, ACC_SYNTHETIC
    Code:
      stack=3, locals=3, args_size=3
         0: aload_0
         1: aload_1
         2: aload_2
         3: invokestatic  #161                // Method $anonfun$contains$8:(Lorg/scalatest/enablers/ContainingStandardImplicits$$anon$7;Ljava/lang/Object;Ljava/lang/Object;)Z
         6: invokestatic  #159                // Method scala/runtime/BoxesRunTime.boxToBoolean:(Z)Ljava/lang/Boolean;
         9: areturn
      LineNumberTable:
        line 461: 0
      LocalVariableTable:
        Start  Length  Slot  Name   Signature
            0      10     0 $this   Lorg/scalatest/enablers/ContainingStandardImplicits$$anon$7;
            0      10     1 ele$6   Ljava/lang/Object;
            0      10     2     e   Ljava/lang/Object;
    MethodParameters:
      Name                           Flags
      $this                          final
      ele$6                          final
      e                              final

  private static java.lang.Object $deserializeLambda$(java.lang.invoke.SerializedLambda);
    descriptor: (Ljava/lang/invoke/SerializedLambda;)Ljava/lang/Object;
    flags: (0x100a) ACC_PRIVATE, ACC_STATIC, ACC_SYNTHETIC
    Code:
      stack=1, locals=1, args_size=1
         0: aload_0
         1: invokedynamic #173,  0            // InvokeDynamic #2:lambdaDeserialize:(Ljava/lang/invoke/SerializedLambda;)Ljava/lang/Object;
         6: areturn
}
InnerClasses:
  public static final #18= #15 of #17;    // Lookup=class java/lang/invoke/MethodHandles$Lookup of class java/lang/invoke/MethodHandles
  public final #2;                        // class org/scalatest/enablers/ContainingStandardImplicits$$anon$7
EnclosingMethod: #10.#13                // org.scalatest.enablers.ContainingStandardImplicits.containingNatureOfEvery
Signature: #3                           // Ljava/lang/Object;Lorg/scalatest/enablers/Containing<Lorg/scalactic/Every<TE;>;>;
SourceFile: "Containing.scala"
BootstrapMethods:
  0: #49 REF_invokeStatic java/lang/invoke/LambdaMetafactory.altMetafactory:(Ljava/lang/invoke/MethodHandles$Lookup;Ljava/lang/String;Ljava/lang/invoke/MethodType;[Ljava/lang/Object;)Ljava/lang/invoke/CallSite;
    Method arguments:
      #36 (Ljava/lang/Object;)Ljava/lang/Object;
      #41 REF_invokeStatic org/scalatest/enablers/ContainingStandardImplicits$$anon$7.$anonfun$contains$7$adapted:(Lorg/scalactic/NormalizingEquality;Ljava/lang/Object;Ljava/lang/Object;)Ljava/lang/Object;
      #36 (Ljava/lang/Object;)Ljava/lang/Object;
      #42 1
  1: #49 REF_invokeStatic java/lang/invoke/LambdaMetafactory.altMetafactory:(Ljava/lang/invoke/MethodHandles$Lookup;Ljava/lang/String;Ljava/lang/invoke/MethodType;[Ljava/lang/Object;)Ljava/lang/invoke/CallSite;
    Method arguments:
      #36 (Ljava/lang/Object;)Ljava/lang/Object;
      #64 REF_invokeStatic org/scalatest/enablers/ContainingStandardImplicits$$anon$7.$anonfun$contains$8$adapted:(Lorg/scalatest/enablers/ContainingStandardImplicits$$anon$7;Ljava/lang/Object;Ljava/lang/Object;)Ljava/lang/Object;
      #36 (Ljava/lang/Object;)Ljava/lang/Object;
      #42 1
  2: #170 REF_invokeStatic scala/runtime/LambdaDeserialize.bootstrap:(Ljava/lang/invoke/MethodHandles$Lookup;Ljava/lang/String;Ljava/lang/invoke/MethodType;[Ljava/lang/invoke/MethodHandle;)Ljava/lang/invoke/CallSite;
    Method arguments:
      #41 REF_invokeStatic org/scalatest/enablers/ContainingStandardImplicits$$anon$7.$anonfun$contains$7$adapted:(Lorg/scalactic/NormalizingEquality;Ljava/lang/Object;Ljava/lang/Object;)Ljava/lang/Object;
      #64 REF_invokeStatic org/scalatest/enablers/ContainingStandardImplicits$$anon$7.$anonfun$contains$8$adapted:(Lorg/scalatest/enablers/ContainingStandardImplicits$$anon$7;Ljava/lang/Object;Ljava/lang/Object;)Ljava/lang/Object;
  ScalaInlineInfo: length = 0x3B (unknown attribute)
   01 01 00 0B 00 7F 00 80 01 00 25 00 26 01 00 8F
   00 90 01 00 3C 00 3D 01 00 93 00 94 01 00 17 00
   7B 01 00 17 00 18 01 00 68 00 75 01 00 68 00 4C
   01 00 4B 00 75 01 00 4B 00 4C 01
  Scala: length = 0x0 (unknown attribute)

