Classfile /Users/mw/Projects/slang-braindump/.jar/jar11/assemble/slang-braindump/assemble/content/org/scalatest/enablers/ContainingHighPriorityImplicits.class
  Last modified May 29, 2022; size 2549 bytes
  SHA-256 checksum 896689aabdca85376bd45d0a3510892df5ef41dae830b0124d3072e070f34632
  Compiled from "Containing.scala"
public interface org.scalatest.enablers.ContainingHighPriorityImplicits extends org.scalatest.enablers.ContainingStandardImplicits
  minor version: 0
  major version: 52
  flags: (0x0601) ACC_PUBLIC, ACC_INTERFACE, ACC_ABSTRACT
  this_class: #2                          // org/scalatest/enablers/ContainingHighPriorityImplicits
  super_class: #4                         // java/lang/Object
  interfaces: 1, fields: 0, methods: 5, attributes: 5
Constant pool:
   #1 = Utf8               org/scalatest/enablers/ContainingHighPriorityImplicits
   #2 = Class              #1             // org/scalatest/enablers/ContainingHighPriorityImplicits
   #3 = Utf8               java/lang/Object
   #4 = Class              #3             // java/lang/Object
   #5 = Utf8               org/scalatest/enablers/ContainingStandardImplicits
   #6 = Class              #5             // org/scalatest/enablers/ContainingStandardImplicits
   #7 = Utf8               Containing.scala
   #8 = Utf8               Lscala/reflect/ScalaSignature;
   #9 = Utf8               bytes
  #10 = Utf8               \u0006\u0005)4q\u0001B\u0003\u0011\u0002\u0007\u0005A\u0002C\u0003\u0018\u0001\u0011\u0005\u0001\u0004C\u0003\u001d\u0001\u0011\rQ\u0004C\u0003W\u0001\u0011\rqKA\u0010D_:$\u0018-\u001b8j]\u001eD\u0015n\u001a5Qe&|\'/\u001b;z\u00136\u0004H.[2jiNT!AB\u0004\u0002\u0011\u0015t\u0017M\u00197feNT!\u0001C\u0005\u0002\u0013M\u001c\u0017\r\\1uKN$(\"\u0001\u0006\u0002\u0007=\u0014xm\u0001\u0001\u0014\u0007\u0001i1\u0003\u0005\u0002\u000f#5\tqBC\u0001\u0011\u0003\u0015\u00198-\u00197b\u0013\t\u0011rB\u0001\u0004B]f\u0014VM\u001a\t\u0003)Ui\u0011!B\u0005\u0003-\u0015\u00111dQ8oi\u0006Lg.\u001b8h\'R\fg\u000eZ1sI&k\u0007\u000f\\5dSR\u001c\u0018A\u0002\u0013j]&$H\u0005F\u0001\u001a!\tq!$\u0003\u0002\u001c\u001f\t!QK\\5u\u0003U\u0019wN\u001c;bS:Lgn\u001a(biV\u0014Xm\u00144NCB,BA\b$JIQ\u0011qd\u0013\t\u0004)\u0001\u0012\u0013BA\u0011\u0006\u0005)\u0019uN\u001c;bS:Lgn\u001a\t\u0005G\u0011*\u0005\n\u0004\u0001\u0005\u000b\u0015\u0012!\u0019\u0001\u0014\u0003\u00075\u000b\u0005+F\u0002(y\r\u000b\"\u0001K\u0016\u0011\u00059I\u0013B\u0001\u0016\u0010\u0005\u001dqu\u000e\u001e5j]\u001e\u0004B\u0001\f\u001d<\u0005:\u0011Q&\u000e\b\u0003]Mr!a\f\u001a\u000e\u0003AR!!M\u0006\u0002\rq\u0012xn\u001c;?\u0013\u0005\u0001\u0012B\u0001\u001b\u0010\u0003)\u0019w\u000e\u001c7fGRLwN\\\u0005\u0003m]\nq\u0001]1dW\u0006<WM\u0003\u00025\u001f%\u0011\u0011H\u000f\u0002\u0007\u000f\u0016tW*\u00199\u000b\u0005Y:\u0004CA\u0012=\t\u0015iDE1\u0001?\u0005\u0005Y\u0017C\u0001\u0015@!\tq\u0001)\u0003\u0002B\u001f\t\u0019\u0011I\\=\u0011\u0005\r\u001aE!\u0002#%\u0005\u0004q$!\u0001<\u0011\u0005\r2E!B$\u0003\u0005\u0004q$!A&\u0011\u0005\rJE!\u0002&\u0003\u0005\u0004q$!\u0001,\t\u000b1\u0013\u00019A\'\u0002\u0011\u0015\fX/\u00197jif\u00042AT)T\u001b\u0005y%B\u0001)\n\u0003%\u00198-\u00197bGRL7-\u0003\u0002S\u001f\nAQ)];bY&$\u0018\u0010\u0005\u0003\u000f)\u0016C\u0015BA+\u0010\u0005\u0019!V\u000f\u001d7fe\u0005q2m\u001c8wKJ$X)];bY&$\u0018\u0010V8NCB\u001cuN\u001c;bS:LgnZ\u000b\u00051\u001247\f\u0006\u0002ZOB\u0019A\u0003\t.\u0011\t\rZ6-\u001a\u0003\u0006K\r\u0011\r\u0001X\u000b\u0004;\u0002\u0014\u0017C\u0001\u0015_!\u0011a\u0003hX1\u0011\u0005\r\u0002G!B\u001f\\\u0005\u0004q\u0004CA\u0012c\t\u0015!5L1\u0001?!\t\u0019C\rB\u0003H\u0007\t\u0007a\b\u0005\u0002$M\u0012)!j\u0001b\u0001}!)Aj\u0001a\u0001QB\u0019a*U5\u0011\t9!6-\u001a
  #11 = Utf8               org/scalatest/enablers/ContainingHighPriorityImplicits$$anon$8
  #12 = Class              #11            // org/scalatest/enablers/ContainingHighPriorityImplicits$$anon$8
  #13 = Utf8               containingNatureOfMap$
  #14 = Utf8               (Lorg/scalatest/enablers/ContainingHighPriorityImplicits;Lorg/scalactic/Equality;)Lorg/scalatest/enablers/Containing;
  #15 = Utf8               $this
  #16 = Utf8               equality
  #17 = Utf8               containingNatureOfMap
  #18 = Utf8               (Lorg/scalactic/Equality;)Lorg/scalatest/enablers/Containing;
  #19 = NameAndType        #17:#18        // containingNatureOfMap:(Lorg/scalactic/Equality;)Lorg/scalatest/enablers/Containing;
  #20 = InterfaceMethodref #2.#19         // org/scalatest/enablers/ContainingHighPriorityImplicits.containingNatureOfMap:(Lorg/scalactic/Equality;)Lorg/scalatest/enablers/Containing;
  #21 = Utf8               Lorg/scalatest/enablers/ContainingHighPriorityImplicits;
  #22 = Utf8               Lorg/scalactic/Equality;
  #23 = Utf8               <K:Ljava/lang/Object;V:Ljava/lang/Object;MAP::Lscala/collection/Map<Ljava/lang/Object;Ljava/lang/Object;>;>(Lorg/scalactic/Equality<Lscala/Tuple2<TK;TV;>;>;)Lorg/scalatest/enablers/Containing<TMAP;>;
  #24 = Utf8               <init>
  #25 = Utf8               (Lorg/scalatest/enablers/ContainingHighPriorityImplicits;Lorg/scalactic/Equality;)V
  #26 = NameAndType        #24:#25        // "<init>":(Lorg/scalatest/enablers/ContainingHighPriorityImplicits;Lorg/scalactic/Equality;)V
  #27 = Methodref          #12.#26        // org/scalatest/enablers/ContainingHighPriorityImplicits$$anon$8."<init>":(Lorg/scalatest/enablers/ContainingHighPriorityImplicits;Lorg/scalactic/Equality;)V
  #28 = Utf8               this
  #29 = Utf8               convertEqualityToMapContaining$
  #30 = Utf8               convertEqualityToMapContaining
  #31 = NameAndType        #30:#18        // convertEqualityToMapContaining:(Lorg/scalactic/Equality;)Lorg/scalatest/enablers/Containing;
  #32 = InterfaceMethodref #2.#31         // org/scalatest/enablers/ContainingHighPriorityImplicits.convertEqualityToMapContaining:(Lorg/scalactic/Equality;)Lorg/scalatest/enablers/Containing;
  #33 = Utf8               $init$
  #34 = Utf8               (Lorg/scalatest/enablers/ContainingHighPriorityImplicits;)V
  #35 = Utf8               Code
  #36 = Utf8               LineNumberTable
  #37 = Utf8               LocalVariableTable
  #38 = Utf8               MethodParameters
  #39 = Utf8               Signature
  #40 = Utf8               InnerClasses
  #41 = Utf8               SourceFile
  #42 = Utf8               RuntimeVisibleAnnotations
  #43 = Utf8               ScalaInlineInfo
  #44 = Utf8               ScalaSig
{
  public static org.scalatest.enablers.Containing containingNatureOfMap$(org.scalatest.enablers.ContainingHighPriorityImplicits, org.scalactic.Equality);
    descriptor: (Lorg/scalatest/enablers/ContainingHighPriorityImplicits;Lorg/scalactic/Equality;)Lorg/scalatest/enablers/Containing;
    flags: (0x1009) ACC_PUBLIC, ACC_STATIC, ACC_SYNTHETIC
    Code:
      stack=2, locals=2, args_size=2
         0: aload_0
         1: aload_1
         2: invokespecial #20                 // InterfaceMethod containingNatureOfMap:(Lorg/scalactic/Equality;)Lorg/scalatest/enablers/Containing;
         5: areturn
      LineNumberTable:
        line 504: 0
      LocalVariableTable:
        Start  Length  Slot  Name   Signature
            0       6     0 $this   Lorg/scalatest/enablers/ContainingHighPriorityImplicits;
            0       6     1 equality   Lorg/scalactic/Equality;
    MethodParameters:
      Name                           Flags
      $this                          final synthetic
      equality                       final

  public default <K extends java.lang.Object, V extends java.lang.Object, MAP extends scala.collection.Map<java.lang.Object, java.lang.Object>> org.scalatest.enablers.Containing<MAP> containingNatureOfMap(org.scalactic.Equality<scala.Tuple2<K, V>>);
    descriptor: (Lorg/scalactic/Equality;)Lorg/scalatest/enablers/Containing;
    flags: (0x0001) ACC_PUBLIC
    Code:
      stack=4, locals=2, args_size=2
         0: new           #12                 // class org/scalatest/enablers/ContainingHighPriorityImplicits$$anon$8
         3: dup
         4: aload_0
         5: aload_1
         6: invokespecial #27                 // Method org/scalatest/enablers/ContainingHighPriorityImplicits$$anon$8."<init>":(Lorg/scalatest/enablers/ContainingHighPriorityImplicits;Lorg/scalactic/Equality;)V
         9: areturn
      LineNumberTable:
        line 505: 0
      LocalVariableTable:
        Start  Length  Slot  Name   Signature
            0      10     0  this   Lorg/scalatest/enablers/ContainingHighPriorityImplicits;
            0      10     1 equality   Lorg/scalactic/Equality;
    Signature: #23                          // <K:Ljava/lang/Object;V:Ljava/lang/Object;MAP::Lscala/collection/Map<Ljava/lang/Object;Ljava/lang/Object;>;>(Lorg/scalactic/Equality<Lscala/Tuple2<TK;TV;>;>;)Lorg/scalatest/enablers/Containing<TMAP;>;
    MethodParameters:
      Name                           Flags
      equality                       final

  public static org.scalatest.enablers.Containing convertEqualityToMapContaining$(org.scalatest.enablers.ContainingHighPriorityImplicits, org.scalactic.Equality);
    descriptor: (Lorg/scalatest/enablers/ContainingHighPriorityImplicits;Lorg/scalactic/Equality;)Lorg/scalatest/enablers/Containing;
    flags: (0x1009) ACC_PUBLIC, ACC_STATIC, ACC_SYNTHETIC
    Code:
      stack=2, locals=2, args_size=2
         0: aload_0
         1: aload_1
         2: invokespecial #32                 // InterfaceMethod convertEqualityToMapContaining:(Lorg/scalactic/Equality;)Lorg/scalatest/enablers/Containing;
         5: areturn
      LineNumberTable:
        line 539: 0
      LocalVariableTable:
        Start  Length  Slot  Name   Signature
            0       6     0 $this   Lorg/scalatest/enablers/ContainingHighPriorityImplicits;
            0       6     1 equality   Lorg/scalactic/Equality;
    MethodParameters:
      Name                           Flags
      $this                          final synthetic
      equality                       final

  public default <K extends java.lang.Object, V extends java.lang.Object, MAP extends scala.collection.Map<java.lang.Object, java.lang.Object>> org.scalatest.enablers.Containing<MAP> convertEqualityToMapContaining(org.scalactic.Equality<scala.Tuple2<K, V>>);
    descriptor: (Lorg/scalactic/Equality;)Lorg/scalatest/enablers/Containing;
    flags: (0x0001) ACC_PUBLIC
    Code:
      stack=2, locals=2, args_size=2
         0: aload_0
         1: aload_1
         2: invokeinterface #20,  2           // InterfaceMethod containingNatureOfMap:(Lorg/scalactic/Equality;)Lorg/scalatest/enablers/Containing;
         7: areturn
      LineNumberTable:
        line 540: 0
      LocalVariableTable:
        Start  Length  Slot  Name   Signature
            0       8     0  this   Lorg/scalatest/enablers/ContainingHighPriorityImplicits;
            0       8     1 equality   Lorg/scalactic/Equality;
    Signature: #23                          // <K:Ljava/lang/Object;V:Ljava/lang/Object;MAP::Lscala/collection/Map<Ljava/lang/Object;Ljava/lang/Object;>;>(Lorg/scalactic/Equality<Lscala/Tuple2<TK;TV;>;>;)Lorg/scalatest/enablers/Containing<TMAP;>;
    MethodParameters:
      Name                           Flags
      equality                       final

  public static void $init$(org.scalatest.enablers.ContainingHighPriorityImplicits);
    descriptor: (Lorg/scalatest/enablers/ContainingHighPriorityImplicits;)V
    flags: (0x0009) ACC_PUBLIC, ACC_STATIC
    Code:
      stack=0, locals=1, args_size=1
         0: return
      LineNumberTable:
        line 493: 0
      LocalVariableTable:
        Start  Length  Slot  Name   Signature
            0       1     0 $this   Lorg/scalatest/enablers/ContainingHighPriorityImplicits;
    MethodParameters:
      Name                           Flags
      $this                          final synthetic
}
InnerClasses:
  public final #12;                       // class org/scalatest/enablers/ContainingHighPriorityImplicits$$anon$8
SourceFile: "Containing.scala"
RuntimeVisibleAnnotations:
  0: #8(#9=s#10)
    scala.reflect.ScalaSignature(
      bytes="\u0006\u0005)4q\u0001B\u0003\u0011\u0002\u0007\u0005A\u0002C\u0003\u0018\u0001\u0011\u0005\u0001\u0004C\u0003\u001d\u0001\u0011\rQ\u0004C\u0003W\u0001\u0011\rqKA\u0010D_:$\u0018-\u001b8j]\u001eD\u0015n\u001a5Qe&|\'/\u001b;z\u00136\u0004H.[2jiNT!AB\u0004\u0002\u0011\u0015t\u0017M\u00197feNT!\u0001C\u0005\u0002\u0013M\u001c\u0017\r\\1uKN$(\"\u0001\u0006\u0002\u0007=\u0014xm\u0001\u0001\u0014\u0007\u0001i1\u0003\u0005\u0002\u000f#5\tqBC\u0001\u0011\u0003\u0015\u00198-\u00197b\u0013\t\u0011rB\u0001\u0004B]f\u0014VM\u001a\t\u0003)Ui\u0011!B\u0005\u0003-\u0015\u00111dQ8oi\u0006Lg.\u001b8h\'R\fg\u000eZ1sI&k\u0007\u000f\\5dSR\u001c\u0018A\u0002\u0013j]&$H\u0005F\u0001\u001a!\tq!$\u0003\u0002\u001c\u001f\t!QK\\5u\u0003U\u0019wN\u001c;bS:Lgn\u001a(biV\u0014Xm\u00144NCB,BA\b$JIQ\u0011qd\u0013\t\u0004)\u0001\u0012\u0013BA\u0011\u0006\u0005)\u0019uN\u001c;bS:Lgn\u001a\t\u0005G\u0011*\u0005\n\u0004\u0001\u0005\u000b\u0015\u0012!\u0019\u0001\u0014\u0003\u00075\u000b\u0005+F\u0002(y\r\u000b\"\u0001K\u0016\u0011\u00059I\u0013B\u0001\u0016\u0010\u0005\u001dqu\u000e\u001e5j]\u001e\u0004B\u0001\f\u001d<\u0005:\u0011Q&\u000e\b\u0003]Mr!a\f\u001a\u000e\u0003AR!!M\u0006\u0002\rq\u0012xn\u001c;?\u0013\u0005\u0001\u0012B\u0001\u001b\u0010\u0003)\u0019w\u000e\u001c7fGRLwN\\\u0005\u0003m]\nq\u0001]1dW\u0006<WM\u0003\u00025\u001f%\u0011\u0011H\u000f\u0002\u0007\u000f\u0016tW*\u00199\u000b\u0005Y:\u0004CA\u0012=\t\u0015iDE1\u0001?\u0005\u0005Y\u0017C\u0001\u0015@!\tq\u0001)\u0003\u0002B\u001f\t\u0019\u0011I\\=\u0011\u0005\r\u001aE!\u0002#%\u0005\u0004q$!\u0001<\u0011\u0005\r2E!B$\u0003\u0005\u0004q$!A&\u0011\u0005\rJE!\u0002&\u0003\u0005\u0004q$!\u0001,\t\u000b1\u0013\u00019A\'\u0002\u0011\u0015\fX/\u00197jif\u00042AT)T\u001b\u0005y%B\u0001)\n\u0003%\u00198-\u00197bGRL7-\u0003\u0002S\u001f\nAQ)];bY&$\u0018\u0010\u0005\u0003\u000f)\u0016C\u0015BA+\u0010\u0005\u0019!V\u000f\u001d7fe\u0005q2m\u001c8wKJ$X)];bY&$\u0018\u0010V8NCB\u001cuN\u001c;bS:LgnZ\u000b\u00051\u001247\f\u0006\u0002ZOB\u0019A\u0003\t.\u0011\t\rZ6-\u001a\u0003\u0006K\r\u0011\r\u0001X\u000b\u0004;\u0002\u0014\u0017C\u0001\u0015_!\u0011a\u0003hX1\u0011\u0005\r\u0002G!B\u001f\\\u0005\u0004q\u0004CA\u0012c\t\u0015!5L1\u0001?!\t\u0019C\rB\u0003H\u0007\t\u0007a\b\u0005\u0002$M\u0012)!j\u0001b\u0001}!)Aj\u0001a\u0001QB\u0019a*U5\u0011\t9!6-\u001a"
    )
  ScalaInlineInfo: length = 0x1D (unknown attribute)
   01 00 00 05 00 21 00 22 01 00 11 00 12 00 00 0D
   00 0E 01 00 1E 00 12 00 00 1D 00 0E 01
  ScalaSig: length = 0x3 (unknown attribute)
   05 02 00
