Classfile /Users/mw/Projects/slang-braindump/.jar/jar11/assemble/slang-braindump/assemble/content/org/scalatest/enablers/Existence$.class
  Last modified May 29, 2022; size 741 bytes
  SHA-256 checksum f1852bf7c8377b0c8b3d48e9fbb6d9daed2bdc31c8cbf77a47ada74c11c3e4b4
  Compiled from "Existence.scala"
public final class org.scalatest.enablers.Existence$
  minor version: 0
  major version: 52
  flags: (0x0031) ACC_PUBLIC, ACC_FINAL, ACC_SUPER
  this_class: #2                          // org/scalatest/enablers/Existence$
  super_class: #4                         // java/lang/Object
  interfaces: 0, fields: 1, methods: 3, attributes: 4
Constant pool:
   #1 = Utf8               org/scalatest/enablers/Existence$
   #2 = Class              #1             // org/scalatest/enablers/Existence$
   #3 = Utf8               java/lang/Object
   #4 = Class              #3             // java/lang/Object
   #5 = Utf8               Existence.scala
   #6 = Utf8               org/scalatest/enablers/Existence$$anon$1
   #7 = Class              #6             // org/scalatest/enablers/Existence$$anon$1
   #8 = Utf8               MODULE$
   #9 = Utf8               Lorg/scalatest/enablers/Existence$;
  #10 = Utf8               <clinit>
  #11 = Utf8               ()V
  #12 = Utf8               <init>
  #13 = NameAndType        #12:#11        // "<init>":()V
  #14 = Methodref          #2.#13         // org/scalatest/enablers/Existence$."<init>":()V
  #15 = NameAndType        #8:#9          // MODULE$:Lorg/scalatest/enablers/Existence$;
  #16 = Fieldref           #2.#15         // org/scalatest/enablers/Existence$.MODULE$:Lorg/scalatest/enablers/Existence$;
  #17 = Utf8               existenceOfFile
  #18 = Utf8               ()Lorg/scalatest/enablers/Existence;
  #19 = Utf8               <FILE:Ljava/io/File;>()Lorg/scalatest/enablers/Existence<TFILE;>;
  #20 = Methodref          #7.#13         // org/scalatest/enablers/Existence$$anon$1."<init>":()V
  #21 = Utf8               this
  #22 = Methodref          #4.#13         // java/lang/Object."<init>":()V
  #23 = Utf8               Code
  #24 = Utf8               LineNumberTable
  #25 = Utf8               LocalVariableTable
  #26 = Utf8               Signature
  #27 = Utf8               InnerClasses
  #28 = Utf8               SourceFile
  #29 = Utf8               ScalaInlineInfo
  #30 = Utf8               Scala
{
  public static final org.scalatest.enablers.Existence$ MODULE$;
    descriptor: Lorg/scalatest/enablers/Existence$;
    flags: (0x0019) ACC_PUBLIC, ACC_STATIC, ACC_FINAL

  public static {};
    descriptor: ()V
    flags: (0x0009) ACC_PUBLIC, ACC_STATIC
    Code:
      stack=2, locals=0, args_size=0
         0: new           #2                  // class org/scalatest/enablers/Existence$
         3: dup
         4: invokespecial #14                 // Method "<init>":()V
         7: putstatic     #16                 // Field MODULE$:Lorg/scalatest/enablers/Existence$;
        10: return
      LineNumberTable:
        line 47: 0

  public <FILE extends java.io.File> org.scalatest.enablers.Existence<FILE> existenceOfFile();
    descriptor: ()Lorg/scalatest/enablers/Existence;
    flags: (0x0001) ACC_PUBLIC
    Code:
      stack=2, locals=1, args_size=1
         0: new           #7                  // class org/scalatest/enablers/Existence$$anon$1
         3: dup
         4: invokespecial #20                 // Method org/scalatest/enablers/Existence$$anon$1."<init>":()V
         7: areturn
      LineNumberTable:
        line 56: 0
      LocalVariableTable:
        Start  Length  Slot  Name   Signature
            0       8     0  this   Lorg/scalatest/enablers/Existence$;
    Signature: #19                          // <FILE:Ljava/io/File;>()Lorg/scalatest/enablers/Existence<TFILE;>;

  private org.scalatest.enablers.Existence$();
    descriptor: ()V
    flags: (0x0002) ACC_PRIVATE
    Code:
      stack=1, locals=1, args_size=1
         0: aload_0
         1: invokespecial #22                 // Method java/lang/Object."<init>":()V
         4: return
      LineNumberTable:
        line 60: 0
        line 47: 4
      LocalVariableTable:
        Start  Length  Slot  Name   Signature
            0       5     0  this   Lorg/scalatest/enablers/Existence$;
}
InnerClasses:
  public final #7;                        // class org/scalatest/enablers/Existence$$anon$1
SourceFile: "Existence.scala"
  ScalaInlineInfo: length = 0xE (unknown attribute)
   01 01 00 02 00 0C 00 0B 01 00 11 00 12 01
  Scala: length = 0x0 (unknown attribute)

