Classfile /Users/mw/Projects/slang-braindump/.jar/jar11/assemble/slang-braindump/assemble/content/org/scalatest/enablers/Existence.class
  Last modified May 29, 2022; size 1099 bytes
  SHA-256 checksum b946137be8e4ba4d86193d3ea9e5854faa5ed42d50409953cec93abf8c7f7007
  Compiled from "Existence.scala"
public interface org.scalatest.enablers.Existence<S extends java.lang.Object>
  minor version: 0
  major version: 52
  flags: (0x0601) ACC_PUBLIC, ACC_INTERFACE, ACC_ABSTRACT
  this_class: #2                          // org/scalatest/enablers/Existence
  super_class: #5                         // java/lang/Object
  interfaces: 0, fields: 0, methods: 2, attributes: 5
Constant pool:
   #1 = Utf8               org/scalatest/enablers/Existence
   #2 = Class              #1             // org/scalatest/enablers/Existence
   #3 = Utf8               <S:Ljava/lang/Object;>Ljava/lang/Object;
   #4 = Utf8               java/lang/Object
   #5 = Class              #4             // java/lang/Object
   #6 = Utf8               Existence.scala
   #7 = Utf8               Lscala/reflect/ScalaSignature;
   #8 = Utf8               bytes
   #9 = Utf8               \u0006\u0005y2qAB\u0004\u0011\u0002G\u0005a\u0002C\u0003\u0017\u0001\u0019\u0005qcB\u0003)\u000f!\u0005\u0011FB\u0003\u0007\u000f!\u00051\u0006C\u0003-\u0007\u0011\u0005Q\u0006C\u0003/\u0007\u0011\rqFA\u0005Fq&\u001cH/\u001a8dK*\u0011\u0001\"C\u0001\tK:\f\'\r\\3sg*\u0011!bC\u0001\ng\u000e\fG.\u0019;fgRT\u0011\u0001D\u0001\u0004_J<7\u0001A\u000b\u0003\u001f}\u0019\"\u0001\u0001\t\u0011\u0005E!R\"\u0001\n\u000b\u0003M\tQa]2bY\u0006L!!\u0006\n\u0003\r\u0005s\u0017PU3g\u0003\u0019)\u00070[:ugR\u0011\u0001d\u0007\t\u0003#eI!A\u0007\n\u0003\u000f\t{w\u000e\\3b]\")A$\u0001a\u0001;\u0005)A\u000f[5oOB\u0011ad\b\u0007\u0001\t\u0019\u0001\u0003\u0001#b\u0001C\t\t1+\u0005\u0002#KA\u0011\u0011cI\u0005\u0003II\u0011qAT8uQ&tw\r\u0005\u0002\u0012M%\u0011qE\u0005\u0002\u0004\u0003:L\u0018!C#ySN$XM\\2f!\tQ3!D\u0001\b\'\t\u0019\u0001#\u0001\u0004=S:LGO\u0010\u000b\u0002S\u0005yQ\r_5ti\u0016t7-Z(g\r&dW-\u0006\u00021gU\t\u0011\u0007E\u0002+\u0001I\u0002\"AH\u001a\u0005\u000bQ*!\u0019A\u001b\u0003\t\u0019KE*R\t\u0003EY\u0002\"a\u000e\u001f\u000e\u0003aR!!\u000f\u001e\u0002\u0005%|\'\"A\u001e\u0002\t)\fg/Y\u0005\u0003{a\u0012AAR5mK\u0002
  #10 = Utf8               existenceOfFile
  #11 = Utf8               ()Lorg/scalatest/enablers/Existence;
  #12 = Utf8               <FILE:Ljava/io/File;>()Lorg/scalatest/enablers/Existence<TFILE;>;
  #13 = Utf8               org/scalatest/enablers/Existence$
  #14 = Class              #13            // org/scalatest/enablers/Existence$
  #15 = Utf8               MODULE$
  #16 = Utf8               Lorg/scalatest/enablers/Existence$;
  #17 = NameAndType        #15:#16        // MODULE$:Lorg/scalatest/enablers/Existence$;
  #18 = Fieldref           #14.#17        // org/scalatest/enablers/Existence$.MODULE$:Lorg/scalatest/enablers/Existence$;
  #19 = NameAndType        #10:#11        // existenceOfFile:()Lorg/scalatest/enablers/Existence;
  #20 = Methodref          #14.#19        // org/scalatest/enablers/Existence$.existenceOfFile:()Lorg/scalatest/enablers/Existence;
  #21 = Utf8               exists
  #22 = Utf8               (Ljava/lang/Object;)Z
  #23 = Utf8               (TS;)Z
  #24 = Utf8               thing
  #25 = Utf8               Code
  #26 = Utf8               Signature
  #27 = Utf8               MethodParameters
  #28 = Utf8               SourceFile
  #29 = Utf8               RuntimeVisibleAnnotations
  #30 = Utf8               ScalaInlineInfo
  #31 = Utf8               ScalaSig
{
  public static <FILE extends java.io.File> org.scalatest.enablers.Existence<FILE> existenceOfFile();
    descriptor: ()Lorg/scalatest/enablers/Existence;
    flags: (0x0009) ACC_PUBLIC, ACC_STATIC
    Code:
      stack=1, locals=0, args_size=0
         0: getstatic     #18                 // Field org/scalatest/enablers/Existence$.MODULE$:Lorg/scalatest/enablers/Existence$;
         3: invokevirtual #20                 // Method org/scalatest/enablers/Existence$.existenceOfFile:()Lorg/scalatest/enablers/Existence;
         6: areturn
    Signature: #12                          // <FILE:Ljava/io/File;>()Lorg/scalatest/enablers/Existence<TFILE;>;

  public abstract boolean exists(S);
    descriptor: (Ljava/lang/Object;)Z
    flags: (0x0401) ACC_PUBLIC, ACC_ABSTRACT
    Signature: #23                          // (TS;)Z
    MethodParameters:
      Name                           Flags
      thing                          final
}
Signature: #3                           // <S:Ljava/lang/Object;>Ljava/lang/Object;
SourceFile: "Existence.scala"
RuntimeVisibleAnnotations:
  0: #7(#8=s#9)
    scala.reflect.ScalaSignature(
      bytes="\u0006\u0005y2qAB\u0004\u0011\u0002G\u0005a\u0002C\u0003\u0017\u0001\u0019\u0005qcB\u0003)\u000f!\u0005\u0011FB\u0003\u0007\u000f!\u00051\u0006C\u0003-\u0007\u0011\u0005Q\u0006C\u0003/\u0007\u0011\rqFA\u0005Fq&\u001cH/\u001a8dK*\u0011\u0001\"C\u0001\tK:\f\'\r\\3sg*\u0011!bC\u0001\ng\u000e\fG.\u0019;fgRT\u0011\u0001D\u0001\u0004_J<7\u0001A\u000b\u0003\u001f}\u0019\"\u0001\u0001\t\u0011\u0005E!R\"\u0001\n\u000b\u0003M\tQa]2bY\u0006L!!\u0006\n\u0003\r\u0005s\u0017PU3g\u0003\u0019)\u00070[:ugR\u0011\u0001d\u0007\t\u0003#eI!A\u0007\n\u0003\u000f\t{w\u000e\\3b]\")A$\u0001a\u0001;\u0005)A\u000f[5oOB\u0011ad\b\u0007\u0001\t\u0019\u0001\u0003\u0001#b\u0001C\t\t1+\u0005\u0002#KA\u0011\u0011cI\u0005\u0003II\u0011qAT8uQ&tw\r\u0005\u0002\u0012M%\u0011qE\u0005\u0002\u0004\u0003:L\u0018!C#ySN$XM\\2f!\tQ3!D\u0001\b\'\t\u0019\u0001#\u0001\u0004=S:LGO\u0010\u000b\u0002S\u0005yQ\r_5ti\u0016t7-Z(g\r&dW-\u0006\u00021gU\t\u0011\u0007E\u0002+\u0001I\u0002\"AH\u001a\u0005\u000bQ*!\u0019A\u001b\u0003\t\u0019KE*R\t\u0003EY\u0002\"a\u000e\u001f\u000e\u0003aR!!\u000f\u001e\u0002\u0005%|\'\"A\u001e\u0002\t)\fg/Y\u0005\u0003{a\u0012AAR5mK\u0002"
    )
  ScalaInlineInfo: length = 0x9 (unknown attribute)
   01 00 00 01 00 15 00 16 00
  ScalaSig: length = 0x3 (unknown attribute)
   05 02 00
