Classfile /Users/mw/Projects/slang-braindump/.jar/jar11/assemble/slang-braindump/assemble/content/org/scalatest/enablers/Futuristic$$anon$1.class
  Last modified May 29, 2022; size 3022 bytes
  SHA-256 checksum c7ef6cf8878b819dc29f88901348fb18e9c0f7b6469bdd48522e22bc02e1f38e
  Compiled from "Futuristic.scala"
public final class org.scalatest.enablers.Futuristic$$anon$1 extends java.lang.Object implements org.scalatest.enablers.Futuristic<org.scalatest.FutureOutcome>
  minor version: 0
  major version: 52
  flags: (0x0031) ACC_PUBLIC, ACC_FINAL, ACC_SUPER
  this_class: #2                          // org/scalatest/enablers/Futuristic$$anon$1
  super_class: #5                         // java/lang/Object
  interfaces: 1, fields: 1, methods: 6, attributes: 7
Constant pool:
    #1 = Utf8               org/scalatest/enablers/Futuristic$$anon$1
    #2 = Class              #1            // org/scalatest/enablers/Futuristic$$anon$1
    #3 = Utf8               Ljava/lang/Object;Lorg/scalatest/enablers/Futuristic<Lorg/scalatest/FutureOutcome;>;
    #4 = Utf8               java/lang/Object
    #5 = Class              #4            // java/lang/Object
    #6 = Utf8               org/scalatest/enablers/Futuristic
    #7 = Class              #6            // org/scalatest/enablers/Futuristic
    #8 = Utf8               Futuristic.scala
    #9 = Utf8               org/scalatest/enablers/Futuristic$
   #10 = Class              #9            // org/scalatest/enablers/Futuristic$
   #11 = Utf8               futuristicNatureOfFutureOutcome
   #12 = Utf8               (Lscala/concurrent/ExecutionContext;)Lorg/scalatest/enablers/Futuristic;
   #13 = NameAndType        #11:#12       // futuristicNatureOfFutureOutcome:(Lscala/concurrent/ExecutionContext;)Lorg/scalatest/enablers/Futuristic;
   #14 = Utf8               java/lang/invoke/MethodHandles$Lookup
   #15 = Class              #14           // java/lang/invoke/MethodHandles$Lookup
   #16 = Utf8               java/lang/invoke/MethodHandles
   #17 = Class              #16           // java/lang/invoke/MethodHandles
   #18 = Utf8               Lookup
   #19 = Utf8               executionContext$1
   #20 = Utf8               Lscala/concurrent/ExecutionContext;
   #21 = Utf8               withCleanup
   #22 = Utf8               (Lorg/scalatest/FutureOutcome;Lscala/Function0;)Lorg/scalatest/FutureOutcome;
   #23 = Utf8               (Lorg/scalatest/FutureOutcome;Lscala/Function0<Lscala/runtime/BoxedUnit;>;)Lorg/scalatest/FutureOutcome;
   #24 = Utf8               futuristic
   #25 = Utf8               cleanup
   #26 = Utf8               (Ljava/lang/Object;)Ljava/lang/Object;
   #27 = MethodType         #26           //  (Ljava/lang/Object;)Ljava/lang/Object;
   #28 = Utf8               $anonfun$withCleanup$1$adapted
   #29 = Utf8               (Lscala/Function0;Lorg/scalactic/Or;)Ljava/lang/Object;
   #30 = NameAndType        #28:#29       // $anonfun$withCleanup$1$adapted:(Lscala/Function0;Lorg/scalactic/Or;)Ljava/lang/Object;
   #31 = Methodref          #2.#30        // org/scalatest/enablers/Futuristic$$anon$1.$anonfun$withCleanup$1$adapted:(Lscala/Function0;Lorg/scalactic/Or;)Ljava/lang/Object;
   #32 = MethodHandle       6:#31         // REF_invokeStatic org/scalatest/enablers/Futuristic$$anon$1.$anonfun$withCleanup$1$adapted:(Lscala/Function0;Lorg/scalactic/Or;)Ljava/lang/Object;
   #33 = Utf8               (Lorg/scalactic/Or;)Ljava/lang/Object;
   #34 = MethodType         #33           //  (Lorg/scalactic/Or;)Ljava/lang/Object;
   #35 = Integer            5
   #36 = Integer            1
   #37 = Utf8               java/lang/invoke/LambdaMetafactory
   #38 = Class              #37           // java/lang/invoke/LambdaMetafactory
   #39 = Utf8               altMetafactory
   #40 = Utf8               (Ljava/lang/invoke/MethodHandles$Lookup;Ljava/lang/String;Ljava/lang/invoke/MethodType;[Ljava/lang/Object;)Ljava/lang/invoke/CallSite;
   #41 = NameAndType        #39:#40       // altMetafactory:(Ljava/lang/invoke/MethodHandles$Lookup;Ljava/lang/String;Ljava/lang/invoke/MethodType;[Ljava/lang/Object;)Ljava/lang/invoke/CallSite;
   #42 = Methodref          #38.#41       // java/lang/invoke/LambdaMetafactory.altMetafactory:(Ljava/lang/invoke/MethodHandles$Lookup;Ljava/lang/String;Ljava/lang/invoke/MethodType;[Ljava/lang/Object;)Ljava/lang/invoke/CallSite;
   #43 = MethodHandle       6:#42         // REF_invokeStatic java/lang/invoke/LambdaMetafactory.altMetafactory:(Ljava/lang/invoke/MethodHandles$Lookup;Ljava/lang/String;Ljava/lang/invoke/MethodType;[Ljava/lang/Object;)Ljava/lang/invoke/CallSite;
   #44 = Utf8               apply
   #45 = Utf8               (Lscala/Function0;)Lscala/Function1;
   #46 = NameAndType        #44:#45       // apply:(Lscala/Function0;)Lscala/Function1;
   #47 = InvokeDynamic      #0:#46        // #0:apply:(Lscala/Function0;)Lscala/Function1;
   #48 = NameAndType        #19:#20       // executionContext$1:Lscala/concurrent/ExecutionContext;
   #49 = Fieldref           #2.#48        // org/scalatest/enablers/Futuristic$$anon$1.executionContext$1:Lscala/concurrent/ExecutionContext;
   #50 = Utf8               org/scalatest/FutureOutcome
   #51 = Class              #50           // org/scalatest/FutureOutcome
   #52 = Utf8               onCompletedThen
   #53 = Utf8               (Lscala/Function1;Lscala/concurrent/ExecutionContext;)Lorg/scalatest/FutureOutcome;
   #54 = NameAndType        #52:#53       // onCompletedThen:(Lscala/Function1;Lscala/concurrent/ExecutionContext;)Lorg/scalatest/FutureOutcome;
   #55 = Methodref          #51.#54       // org/scalatest/FutureOutcome.onCompletedThen:(Lscala/Function1;Lscala/concurrent/ExecutionContext;)Lorg/scalatest/FutureOutcome;
   #56 = Utf8               this
   #57 = Utf8               Lorg/scalatest/enablers/Futuristic$$anon$1;
   #58 = Utf8               Lorg/scalatest/FutureOutcome;
   #59 = Utf8               Lscala/Function0;
   #60 = Utf8               (Ljava/lang/Object;Lscala/Function0;)Ljava/lang/Object;
   #61 = NameAndType        #21:#22       // withCleanup:(Lorg/scalatest/FutureOutcome;Lscala/Function0;)Lorg/scalatest/FutureOutcome;
   #62 = Methodref          #2.#61        // org/scalatest/enablers/Futuristic$$anon$1.withCleanup:(Lorg/scalatest/FutureOutcome;Lscala/Function0;)Lorg/scalatest/FutureOutcome;
   #63 = Utf8               Ljava/lang/Object;
   #64 = Utf8               $anonfun$withCleanup$1
   #65 = Utf8               (Lscala/Function0;Lorg/scalactic/Or;)V
   #66 = Utf8               cleanup$1
   #67 = Utf8               x$1
   #68 = Utf8               scala/Function0
   #69 = Class              #68           // scala/Function0
   #70 = Utf8               apply$mcV$sp
   #71 = Utf8               ()V
   #72 = NameAndType        #70:#71       // apply$mcV$sp:()V
   #73 = InterfaceMethodref #69.#72       // scala/Function0.apply$mcV$sp:()V
   #74 = Utf8               Lorg/scalactic/Or;
   #75 = Utf8               <init>
   #76 = Utf8               (Lscala/concurrent/ExecutionContext;)V
   #77 = NameAndType        #75:#71       // "<init>":()V
   #78 = Methodref          #5.#77        // java/lang/Object."<init>":()V
   #79 = NameAndType        #64:#65       // $anonfun$withCleanup$1:(Lscala/Function0;Lorg/scalactic/Or;)V
   #80 = Methodref          #2.#79        // org/scalatest/enablers/Futuristic$$anon$1.$anonfun$withCleanup$1:(Lscala/Function0;Lorg/scalactic/Or;)V
   #81 = Utf8               scala/runtime/BoxedUnit
   #82 = Class              #81           // scala/runtime/BoxedUnit
   #83 = Utf8               UNIT
   #84 = Utf8               Lscala/runtime/BoxedUnit;
   #85 = NameAndType        #83:#84       // UNIT:Lscala/runtime/BoxedUnit;
   #86 = Fieldref           #82.#85       // scala/runtime/BoxedUnit.UNIT:Lscala/runtime/BoxedUnit;
   #87 = Utf8               $deserializeLambda$
   #88 = Utf8               (Ljava/lang/invoke/SerializedLambda;)Ljava/lang/Object;
   #89 = Utf8               scala/runtime/LambdaDeserialize
   #90 = Class              #89           // scala/runtime/LambdaDeserialize
   #91 = Utf8               bootstrap
   #92 = Utf8               (Ljava/lang/invoke/MethodHandles$Lookup;Ljava/lang/String;Ljava/lang/invoke/MethodType;[Ljava/lang/invoke/MethodHandle;)Ljava/lang/invoke/CallSite;
   #93 = NameAndType        #91:#92       // bootstrap:(Ljava/lang/invoke/MethodHandles$Lookup;Ljava/lang/String;Ljava/lang/invoke/MethodType;[Ljava/lang/invoke/MethodHandle;)Ljava/lang/invoke/CallSite;
   #94 = Methodref          #90.#93       // scala/runtime/LambdaDeserialize.bootstrap:(Ljava/lang/invoke/MethodHandles$Lookup;Ljava/lang/String;Ljava/lang/invoke/MethodType;[Ljava/lang/invoke/MethodHandle;)Ljava/lang/invoke/CallSite;
   #95 = MethodHandle       6:#94         // REF_invokeStatic scala/runtime/LambdaDeserialize.bootstrap:(Ljava/lang/invoke/MethodHandles$Lookup;Ljava/lang/String;Ljava/lang/invoke/MethodType;[Ljava/lang/invoke/MethodHandle;)Ljava/lang/invoke/CallSite;
   #96 = Utf8               lambdaDeserialize
   #97 = NameAndType        #96:#88       // lambdaDeserialize:(Ljava/lang/invoke/SerializedLambda;)Ljava/lang/Object;
   #98 = InvokeDynamic      #1:#97        // #1:lambdaDeserialize:(Ljava/lang/invoke/SerializedLambda;)Ljava/lang/Object;
   #99 = Utf8               Code
  #100 = Utf8               LineNumberTable
  #101 = Utf8               LocalVariableTable
  #102 = Utf8               Signature
  #103 = Utf8               MethodParameters
  #104 = Utf8               InnerClasses
  #105 = Utf8               EnclosingMethod
  #106 = Utf8               SourceFile
  #107 = Utf8               BootstrapMethods
  #108 = Utf8               ScalaInlineInfo
  #109 = Utf8               Scala
{
  private final scala.concurrent.ExecutionContext executionContext$1;
    descriptor: Lscala/concurrent/ExecutionContext;
    flags: (0x0012) ACC_PRIVATE, ACC_FINAL

  public org.scalatest.FutureOutcome withCleanup(org.scalatest.FutureOutcome, scala.Function0<scala.runtime.BoxedUnit>);
    descriptor: (Lorg/scalatest/FutureOutcome;Lscala/Function0;)Lorg/scalatest/FutureOutcome;
    flags: (0x0001) ACC_PUBLIC
    Code:
      stack=3, locals=3, args_size=3
         0: aload_1
         1: aload_2
         2: invokedynamic #47,  0             // InvokeDynamic #0:apply:(Lscala/Function0;)Lscala/Function1;
         7: aload_0
         8: getfield      #49                 // Field executionContext$1:Lscala/concurrent/ExecutionContext;
        11: invokevirtual #55                 // Method org/scalatest/FutureOutcome.onCompletedThen:(Lscala/Function1;Lscala/concurrent/ExecutionContext;)Lorg/scalatest/FutureOutcome;
        14: areturn
      LineNumberTable:
        line 68: 0
      LocalVariableTable:
        Start  Length  Slot  Name   Signature
            0      15     0  this   Lorg/scalatest/enablers/Futuristic$$anon$1;
            0      15     1 futuristic   Lorg/scalatest/FutureOutcome;
            0      15     2 cleanup   Lscala/Function0;
    Signature: #23                          // (Lorg/scalatest/FutureOutcome;Lscala/Function0<Lscala/runtime/BoxedUnit;>;)Lorg/scalatest/FutureOutcome;
    MethodParameters:
      Name                           Flags
      futuristic                     final
      cleanup                        final

  public java.lang.Object withCleanup(java.lang.Object, scala.Function0);
    descriptor: (Ljava/lang/Object;Lscala/Function0;)Ljava/lang/Object;
    flags: (0x1041) ACC_PUBLIC, ACC_BRIDGE, ACC_SYNTHETIC
    Code:
      stack=3, locals=3, args_size=3
         0: aload_0
         1: aload_1
         2: checkcast     #51                 // class org/scalatest/FutureOutcome
         5: aload_2
         6: invokevirtual #62                 // Method withCleanup:(Lorg/scalatest/FutureOutcome;Lscala/Function0;)Lorg/scalatest/FutureOutcome;
         9: areturn
      LineNumberTable:
        line 66: 0
      LocalVariableTable:
        Start  Length  Slot  Name   Signature
            0      10     0  this   Lorg/scalatest/enablers/Futuristic$$anon$1;
            0      10     1 futuristic   Ljava/lang/Object;
            0      10     2 cleanup   Lscala/Function0;
    MethodParameters:
      Name                           Flags
      futuristic                     final
      cleanup                        final

  public static final void $anonfun$withCleanup$1(scala.Function0, org.scalactic.Or);
    descriptor: (Lscala/Function0;Lorg/scalactic/Or;)V
    flags: (0x1019) ACC_PUBLIC, ACC_STATIC, ACC_FINAL, ACC_SYNTHETIC
    Code:
      stack=1, locals=2, args_size=2
         0: aload_0
         1: invokeinterface #73,  1           // InterfaceMethod scala/Function0.apply$mcV$sp:()V
         6: return
      LineNumberTable:
        line 68: 0
      LocalVariableTable:
        Start  Length  Slot  Name   Signature
            0       7     0 cleanup$1   Lscala/Function0;
            0       7     1   x$1   Lorg/scalactic/Or;
    MethodParameters:
      Name                           Flags
      cleanup$1                      final
      x$1                            final

  public org.scalatest.enablers.Futuristic$$anon$1(scala.concurrent.ExecutionContext);
    descriptor: (Lscala/concurrent/ExecutionContext;)V
    flags: (0x0001) ACC_PUBLIC
    Code:
      stack=2, locals=2, args_size=2
         0: aload_0
         1: aload_1
         2: putfield      #49                 // Field executionContext$1:Lscala/concurrent/ExecutionContext;
         5: aload_0
         6: invokespecial #78                 // Method java/lang/Object."<init>":()V
         9: return
      LineNumberTable:
        line 65: 0
        line 66: 5
      LocalVariableTable:
        Start  Length  Slot  Name   Signature
            0      10     0  this   Lorg/scalatest/enablers/Futuristic$$anon$1;
            0      10     1 executionContext$1   Lscala/concurrent/ExecutionContext;
    MethodParameters:
      Name                           Flags
      executionContext$1             final

  public static final java.lang.Object $anonfun$withCleanup$1$adapted(scala.Function0, org.scalactic.Or);
    descriptor: (Lscala/Function0;Lorg/scalactic/Or;)Ljava/lang/Object;
    flags: (0x1019) ACC_PUBLIC, ACC_STATIC, ACC_FINAL, ACC_SYNTHETIC
    Code:
      stack=2, locals=2, args_size=2
         0: aload_0
         1: aload_1
         2: invokestatic  #80                 // Method $anonfun$withCleanup$1:(Lscala/Function0;Lorg/scalactic/Or;)V
         5: getstatic     #86                 // Field scala/runtime/BoxedUnit.UNIT:Lscala/runtime/BoxedUnit;
         8: areturn
      LineNumberTable:
        line 68: 0
      LocalVariableTable:
        Start  Length  Slot  Name   Signature
            0       9     0 cleanup$1   Lscala/Function0;
            0       9     1   x$1   Lorg/scalactic/Or;
    MethodParameters:
      Name                           Flags
      cleanup$1                      final
      x$1                            final

  private static java.lang.Object $deserializeLambda$(java.lang.invoke.SerializedLambda);
    descriptor: (Ljava/lang/invoke/SerializedLambda;)Ljava/lang/Object;
    flags: (0x100a) ACC_PRIVATE, ACC_STATIC, ACC_SYNTHETIC
    Code:
      stack=1, locals=1, args_size=1
         0: aload_0
         1: invokedynamic #98,  0             // InvokeDynamic #1:lambdaDeserialize:(Ljava/lang/invoke/SerializedLambda;)Ljava/lang/Object;
         6: areturn
}
InnerClasses:
  public static final #18= #15 of #17;    // Lookup=class java/lang/invoke/MethodHandles$Lookup of class java/lang/invoke/MethodHandles
  public final #2;                        // class org/scalatest/enablers/Futuristic$$anon$1
EnclosingMethod: #10.#13                // org.scalatest.enablers.Futuristic$.futuristicNatureOfFutureOutcome
Signature: #3                           // Ljava/lang/Object;Lorg/scalatest/enablers/Futuristic<Lorg/scalatest/FutureOutcome;>;
SourceFile: "Futuristic.scala"
BootstrapMethods:
  0: #43 REF_invokeStatic java/lang/invoke/LambdaMetafactory.altMetafactory:(Ljava/lang/invoke/MethodHandles$Lookup;Ljava/lang/String;Ljava/lang/invoke/MethodType;[Ljava/lang/Object;)Ljava/lang/invoke/CallSite;
    Method arguments:
      #27 (Ljava/lang/Object;)Ljava/lang/Object;
      #32 REF_invokeStatic org/scalatest/enablers/Futuristic$$anon$1.$anonfun$withCleanup$1$adapted:(Lscala/Function0;Lorg/scalactic/Or;)Ljava/lang/Object;
      #34 (Lorg/scalactic/Or;)Ljava/lang/Object;
      #35 5
      #36 1
      #34 (Lorg/scalactic/Or;)Ljava/lang/Object;
  1: #95 REF_invokeStatic scala/runtime/LambdaDeserialize.bootstrap:(Ljava/lang/invoke/MethodHandles$Lookup;Ljava/lang/String;Ljava/lang/invoke/MethodType;[Ljava/lang/invoke/MethodHandle;)Ljava/lang/invoke/CallSite;
    Method arguments:
      #32 REF_invokeStatic org/scalatest/enablers/Futuristic$$anon$1.$anonfun$withCleanup$1$adapted:(Lscala/Function0;Lorg/scalactic/Or;)Ljava/lang/Object;
  ScalaInlineInfo: length = 0x1D (unknown attribute)
   01 01 00 05 00 40 00 41 01 00 1C 00 1D 01 00 4B
   00 4C 01 00 15 00 3C 01 00 15 00 16 01
  Scala: length = 0x0 (unknown attribute)

