Classfile /Users/mw/Projects/slang-braindump/.jar/jar11/assemble/slang-braindump/assemble/content/org/scalatest/enablers/Readability.class
  Last modified May 29, 2022; size 1643 bytes
  SHA-256 checksum 5f603b295773f33af72a5346e43435726311b7c3692bf3f6a8eba338a9db78a7
  Compiled from "Readability.scala"
public interface org.scalatest.enablers.Readability<T extends java.lang.Object>
  minor version: 0
  major version: 52
  flags: (0x0601) ACC_PUBLIC, ACC_INTERFACE, ACC_ABSTRACT
  this_class: #2                          // org/scalatest/enablers/Readability
  super_class: #5                         // java/lang/Object
  interfaces: 0, fields: 0, methods: 4, attributes: 5
Constant pool:
   #1 = Utf8               org/scalatest/enablers/Readability
   #2 = Class              #1             // org/scalatest/enablers/Readability
   #3 = Utf8               <T:Ljava/lang/Object;>Ljava/lang/Object;
   #4 = Utf8               java/lang/Object
   #5 = Class              #4             // java/lang/Object
   #6 = Utf8               Readability.scala
   #7 = Utf8               Lscala/reflect/ScalaSignature;
   #8 = Utf8               bytes
   #9 = Utf8               \u0006\u0005]3q\u0001C\u0005\u0011\u0002G\u0005\u0001\u0003C\u0003\u0019\u0001\u0019\u0005\u0011dB\u0003+\u0013!\u00051FB\u0003\t\u0013!\u0005Q\u0006C\u0003/\u0007\u0011\u0005q\u0006C\u00031\u0007\u0011\r\u0011\u0007C\u0003A\u0007\u0011\r\u0011\tC\u0003M\u0007\u0011\rQJA\u0006SK\u0006$\u0017MY5mSRL(B\u0001\u0006\f\u0003!)g.\u00192mKJ\u001c(B\u0001\u0007\u000e\u0003%\u00198-\u00197bi\u0016\u001cHOC\u0001\u000f\u0003\ry\'oZ\u0002\u0001+\t\t\u0012e\u0005\u0002\u0001%A\u00111CF\u0007\u0002))\tQ#A\u0003tG\u0006d\u0017-\u0003\u0002\u0018)\t1\u0011I\\=SK\u001a\f!\"[:SK\u0006$\u0017M\u00197f)\tQR\u0004\u0005\u0002\u00147%\u0011A\u0004\u0006\u0002\b\u0005>|G.Z1o\u0011\u0015q\u0012\u00011\u0001 \u0003\u0015!\b.\u001b8h!\t\u0001\u0013\u0005\u0004\u0001\u0005\r\t\u0002\u0001R1\u0001$\u0005\u0005!\u0016C\u0001\u0013(!\t\u0019R%\u0003\u0002\')\t9aj\u001c;iS:<\u0007CA\n)\u0013\tICCA\u0002B]f\f1BU3bI\u0006\u0014\u0017\u000e\\5usB\u0011AfA\u0007\u0002\u0013M\u00111AE\u0001\u0007y%t\u0017\u000e\u001e \u0015\u0003-\n\u0011C]3bI\u0006\u0014\u0017\u000e\\5us>3g)\u001b7f+\t\u0011T\'F\u00014!\ra\u0003\u0001\u000e\t\u0003AU\"QAN\u0003C\u0002]\u0012AAR%M\u000bF\u0011A\u0005\u000f\t\u0003syj\u0011A\u000f\u0006\u0003wq\n!![8\u000b\u0003u\nAA[1wC&\u0011qH\u000f\u0002\u0005\r&dW-A\u0014sK\u0006$\u0017MY5mSRLxJZ!osJ+gmV5uQ&\u001b(+Z1eC\ndW-T3uQ>$WC\u0001\"F+\u0005\u0019\u0005c\u0001\u0017\u0001\tB\u0011\u0001%\u0012\u0003\u0006E\u0019\u0011\rAR\t\u0003I\u001d\u0013\"\u0001\u0013\n\u0007\t%\u001b\u0001a\u0012\u0002\ryI,g-\u001b8f[\u0016tGO\u0010\u0005\u00061!3\ta\u0013\u000b\u00025\u0005!$/Z1eC\nLG.\u001b;z\u001f\u001a\fe.\u001f*fM^KG\u000f\u001b)be\u0006lW\r^3sY\u0016\u001c8/S:SK\u0006$\u0017M\u00197f\u001b\u0016$\bn\u001c3\u0016\u00059\u000bV#A(\u0011\u00071\u0002\u0001\u000b\u0005\u0002!#\u0012)!e\u0002b\u0001%F\u0011Ae\u0015\n\u0003)J1A!S\u0002\u0001\'\")\u0001\u0004\u0016D\u0001-V\t!\u0004
  #10 = Utf8               readabilityOfAnyRefWithParameterlessIsReadableMethod
  #11 = Utf8               ()Lorg/scalatest/enablers/Readability;
  #12 = Utf8               <T:Ljava/lang/Object;>()Lorg/scalatest/enablers/Readability<TT;>;
  #13 = Utf8               org/scalatest/enablers/Readability$
  #14 = Class              #13            // org/scalatest/enablers/Readability$
  #15 = Utf8               MODULE$
  #16 = Utf8               Lorg/scalatest/enablers/Readability$;
  #17 = NameAndType        #15:#16        // MODULE$:Lorg/scalatest/enablers/Readability$;
  #18 = Fieldref           #14.#17        // org/scalatest/enablers/Readability$.MODULE$:Lorg/scalatest/enablers/Readability$;
  #19 = NameAndType        #10:#11        // readabilityOfAnyRefWithParameterlessIsReadableMethod:()Lorg/scalatest/enablers/Readability;
  #20 = Methodref          #14.#19        // org/scalatest/enablers/Readability$.readabilityOfAnyRefWithParameterlessIsReadableMethod:()Lorg/scalatest/enablers/Readability;
  #21 = Utf8               readabilityOfAnyRefWithIsReadableMethod
  #22 = NameAndType        #21:#11        // readabilityOfAnyRefWithIsReadableMethod:()Lorg/scalatest/enablers/Readability;
  #23 = Methodref          #14.#22        // org/scalatest/enablers/Readability$.readabilityOfAnyRefWithIsReadableMethod:()Lorg/scalatest/enablers/Readability;
  #24 = Utf8               readabilityOfFile
  #25 = Utf8               <FILE:Ljava/io/File;>()Lorg/scalatest/enablers/Readability<TFILE;>;
  #26 = NameAndType        #24:#11        // readabilityOfFile:()Lorg/scalatest/enablers/Readability;
  #27 = Methodref          #14.#26        // org/scalatest/enablers/Readability$.readabilityOfFile:()Lorg/scalatest/enablers/Readability;
  #28 = Utf8               isReadable
  #29 = Utf8               (Ljava/lang/Object;)Z
  #30 = Utf8               (TT;)Z
  #31 = Utf8               thing
  #32 = Utf8               Code
  #33 = Utf8               Signature
  #34 = Utf8               MethodParameters
  #35 = Utf8               SourceFile
  #36 = Utf8               RuntimeVisibleAnnotations
  #37 = Utf8               ScalaInlineInfo
  #38 = Utf8               ScalaSig
{
  public static <T extends java.lang.Object> org.scalatest.enablers.Readability<T> readabilityOfAnyRefWithParameterlessIsReadableMethod();
    descriptor: ()Lorg/scalatest/enablers/Readability;
    flags: (0x0009) ACC_PUBLIC, ACC_STATIC
    Code:
      stack=1, locals=0, args_size=0
         0: getstatic     #18                 // Field org/scalatest/enablers/Readability$.MODULE$:Lorg/scalatest/enablers/Readability$;
         3: invokevirtual #20                 // Method org/scalatest/enablers/Readability$.readabilityOfAnyRefWithParameterlessIsReadableMethod:()Lorg/scalatest/enablers/Readability;
         6: areturn
    Signature: #12                          // <T:Ljava/lang/Object;>()Lorg/scalatest/enablers/Readability<TT;>;

  public static <T extends java.lang.Object> org.scalatest.enablers.Readability<T> readabilityOfAnyRefWithIsReadableMethod();
    descriptor: ()Lorg/scalatest/enablers/Readability;
    flags: (0x0009) ACC_PUBLIC, ACC_STATIC
    Code:
      stack=1, locals=0, args_size=0
         0: getstatic     #18                 // Field org/scalatest/enablers/Readability$.MODULE$:Lorg/scalatest/enablers/Readability$;
         3: invokevirtual #23                 // Method org/scalatest/enablers/Readability$.readabilityOfAnyRefWithIsReadableMethod:()Lorg/scalatest/enablers/Readability;
         6: areturn
    Signature: #12                          // <T:Ljava/lang/Object;>()Lorg/scalatest/enablers/Readability<TT;>;

  public static <FILE extends java.io.File> org.scalatest.enablers.Readability<FILE> readabilityOfFile();
    descriptor: ()Lorg/scalatest/enablers/Readability;
    flags: (0x0009) ACC_PUBLIC, ACC_STATIC
    Code:
      stack=1, locals=0, args_size=0
         0: getstatic     #18                 // Field org/scalatest/enablers/Readability$.MODULE$:Lorg/scalatest/enablers/Readability$;
         3: invokevirtual #27                 // Method org/scalatest/enablers/Readability$.readabilityOfFile:()Lorg/scalatest/enablers/Readability;
         6: areturn
    Signature: #25                          // <FILE:Ljava/io/File;>()Lorg/scalatest/enablers/Readability<TFILE;>;

  public abstract boolean isReadable(T);
    descriptor: (Ljava/lang/Object;)Z
    flags: (0x0401) ACC_PUBLIC, ACC_ABSTRACT
    Signature: #30                          // (TT;)Z
    MethodParameters:
      Name                           Flags
      thing                          final
}
Signature: #3                           // <T:Ljava/lang/Object;>Ljava/lang/Object;
SourceFile: "Readability.scala"
RuntimeVisibleAnnotations:
  0: #7(#8=s#9)
    scala.reflect.ScalaSignature(
      bytes="\u0006\u0005]3q\u0001C\u0005\u0011\u0002G\u0005\u0001\u0003C\u0003\u0019\u0001\u0019\u0005\u0011dB\u0003+\u0013!\u00051FB\u0003\t\u0013!\u0005Q\u0006C\u0003/\u0007\u0011\u0005q\u0006C\u00031\u0007\u0011\r\u0011\u0007C\u0003A\u0007\u0011\r\u0011\tC\u0003M\u0007\u0011\rQJA\u0006SK\u0006$\u0017MY5mSRL(B\u0001\u0006\f\u0003!)g.\u00192mKJ\u001c(B\u0001\u0007\u000e\u0003%\u00198-\u00197bi\u0016\u001cHOC\u0001\u000f\u0003\ry\'oZ\u0002\u0001+\t\t\u0012e\u0005\u0002\u0001%A\u00111CF\u0007\u0002))\tQ#A\u0003tG\u0006d\u0017-\u0003\u0002\u0018)\t1\u0011I\\=SK\u001a\f!\"[:SK\u0006$\u0017M\u00197f)\tQR\u0004\u0005\u0002\u00147%\u0011A\u0004\u0006\u0002\b\u0005>|G.Z1o\u0011\u0015q\u0012\u00011\u0001 \u0003\u0015!\b.\u001b8h!\t\u0001\u0013\u0005\u0004\u0001\u0005\r\t\u0002\u0001R1\u0001$\u0005\u0005!\u0016C\u0001\u0013(!\t\u0019R%\u0003\u0002\')\t9aj\u001c;iS:<\u0007CA\n)\u0013\tICCA\u0002B]f\f1BU3bI\u0006\u0014\u0017\u000e\\5usB\u0011AfA\u0007\u0002\u0013M\u00111AE\u0001\u0007y%t\u0017\u000e\u001e \u0015\u0003-\n\u0011C]3bI\u0006\u0014\u0017\u000e\\5us>3g)\u001b7f+\t\u0011T\'F\u00014!\ra\u0003\u0001\u000e\t\u0003AU\"QAN\u0003C\u0002]\u0012AAR%M\u000bF\u0011A\u0005\u000f\t\u0003syj\u0011A\u000f\u0006\u0003wq\n!![8\u000b\u0003u\nAA[1wC&\u0011qH\u000f\u0002\u0005\r&dW-A\u0014sK\u0006$\u0017MY5mSRLxJZ!osJ+gmV5uQ&\u001b(+Z1eC\ndW-T3uQ>$WC\u0001\"F+\u0005\u0019\u0005c\u0001\u0017\u0001\tB\u0011\u0001%\u0012\u0003\u0006E\u0019\u0011\rAR\t\u0003I\u001d\u0013\"\u0001\u0013\n\u0007\t%\u001b\u0001a\u0012\u0002\ryI,g-\u001b8f[\u0016tGO\u0010\u0005\u00061!3\ta\u0013\u000b\u00025\u0005!$/Z1eC\nLG.\u001b;z\u001f\u001a\fe.\u001f*fM^KG\u000f\u001b)be\u0006lW\r^3sY\u0016\u001c8/S:SK\u0006$\u0017M\u00197f\u001b\u0016$\bn\u001c3\u0016\u00059\u000bV#A(\u0011\u00071\u0002\u0001\u000b\u0005\u0002!#\u0012)!e\u0002b\u0001%F\u0011Ae\u0015\n\u0003)J1A!S\u0002\u0001\'\")\u0001\u0004\u0016D\u0001-V\t!\u0004"
    )
  ScalaInlineInfo: length = 0x9 (unknown attribute)
   01 00 00 01 00 1C 00 1D 00
  ScalaSig: length = 0x3 (unknown attribute)
   05 02 00
