Classfile /Users/mw/Projects/slang-braindump/.jar/jar11/assemble/slang-braindump/assemble/content/org/scalatest/enablers/Retrying$$anon$1.class
  Last modified May 29, 2022; size 1267 bytes
  SHA-256 checksum 6da552744393f3e3386d8afab7cb8d40c370d659da70ab0a909007a45ae03e8b
  Compiled from "Retrying.scala"
public final class org.scalatest.enablers.Retrying$$anon$1 implements java.util.concurrent.ThreadFactory
  minor version: 0
  major version: 52
  flags: (0x0031) ACC_PUBLIC, ACC_FINAL, ACC_SUPER
  this_class: #2                          // org/scalatest/enablers/Retrying$$anon$1
  super_class: #4                         // java/lang/Object
  interfaces: 1, fields: 1, methods: 3, attributes: 5
Constant pool:
   #1 = Utf8               org/scalatest/enablers/Retrying$$anon$1
   #2 = Class              #1             // org/scalatest/enablers/Retrying$$anon$1
   #3 = Utf8               java/lang/Object
   #4 = Class              #3             // java/lang/Object
   #5 = Utf8               java/util/concurrent/ThreadFactory
   #6 = Class              #5             // java/util/concurrent/ThreadFactory
   #7 = Utf8               Retrying.scala
   #8 = Utf8               org/scalatest/enablers/Retrying$
   #9 = Class              #8             // org/scalatest/enablers/Retrying$
  #10 = Utf8               org$scalatest$enablers$Retrying$$createScheduler
  #11 = Utf8               ()Ljava/util/concurrent/ScheduledExecutorService;
  #12 = NameAndType        #10:#11        // org$scalatest$enablers$Retrying$$createScheduler:()Ljava/util/concurrent/ScheduledExecutorService;
  #13 = Utf8               inner
  #14 = Utf8               Ljava/util/concurrent/ThreadFactory;
  #15 = Utf8               ()Ljava/util/concurrent/ThreadFactory;
  #16 = NameAndType        #13:#14        // inner:Ljava/util/concurrent/ThreadFactory;
  #17 = Fieldref           #2.#16         // org/scalatest/enablers/Retrying$$anon$1.inner:Ljava/util/concurrent/ThreadFactory;
  #18 = Utf8               this
  #19 = Utf8               Lorg/scalatest/enablers/Retrying$$anon$1;
  #20 = Utf8               newThread
  #21 = Utf8               (Ljava/lang/Runnable;)Ljava/lang/Thread;
  #22 = Utf8               runnable
  #23 = NameAndType        #13:#15        // inner:()Ljava/util/concurrent/ThreadFactory;
  #24 = Methodref          #2.#23         // org/scalatest/enablers/Retrying$$anon$1.inner:()Ljava/util/concurrent/ThreadFactory;
  #25 = NameAndType        #20:#21        // newThread:(Ljava/lang/Runnable;)Ljava/lang/Thread;
  #26 = InterfaceMethodref #6.#25         // java/util/concurrent/ThreadFactory.newThread:(Ljava/lang/Runnable;)Ljava/lang/Thread;
  #27 = Utf8               ScalaTest-retrying
  #28 = String             #27            // ScalaTest-retrying
  #29 = Utf8               java/lang/Thread
  #30 = Class              #29            // java/lang/Thread
  #31 = Utf8               setName
  #32 = Utf8               (Ljava/lang/String;)V
  #33 = NameAndType        #31:#32        // setName:(Ljava/lang/String;)V
  #34 = Methodref          #30.#33        // java/lang/Thread.setName:(Ljava/lang/String;)V
  #35 = Utf8               setDaemon
  #36 = Utf8               (Z)V
  #37 = NameAndType        #35:#36        // setDaemon:(Z)V
  #38 = Methodref          #30.#37        // java/lang/Thread.setDaemon:(Z)V
  #39 = Utf8               thread
  #40 = Utf8               Ljava/lang/Thread;
  #41 = Utf8               Ljava/lang/Runnable;
  #42 = Utf8               <init>
  #43 = Utf8               ()V
  #44 = NameAndType        #42:#43        // "<init>":()V
  #45 = Methodref          #4.#44         // java/lang/Object."<init>":()V
  #46 = Utf8               java/util/concurrent/Executors
  #47 = Class              #46            // java/util/concurrent/Executors
  #48 = Utf8               defaultThreadFactory
  #49 = NameAndType        #48:#15        // defaultThreadFactory:()Ljava/util/concurrent/ThreadFactory;
  #50 = Methodref          #47.#49        // java/util/concurrent/Executors.defaultThreadFactory:()Ljava/util/concurrent/ThreadFactory;
  #51 = Utf8               Code
  #52 = Utf8               LineNumberTable
  #53 = Utf8               LocalVariableTable
  #54 = Utf8               MethodParameters
  #55 = Utf8               InnerClasses
  #56 = Utf8               EnclosingMethod
  #57 = Utf8               SourceFile
  #58 = Utf8               ScalaInlineInfo
  #59 = Utf8               Scala
{
  private final java.util.concurrent.ThreadFactory inner;
    descriptor: Ljava/util/concurrent/ThreadFactory;
    flags: (0x0012) ACC_PRIVATE, ACC_FINAL

  public java.util.concurrent.ThreadFactory inner();
    descriptor: ()Ljava/util/concurrent/ThreadFactory;
    flags: (0x0001) ACC_PUBLIC
    Code:
      stack=1, locals=1, args_size=1
         0: aload_0
         1: getfield      #17                 // Field inner:Ljava/util/concurrent/ThreadFactory;
         4: areturn
      LineNumberTable:
        line 61: 0
      LocalVariableTable:
        Start  Length  Slot  Name   Signature
            0       5     0  this   Lorg/scalatest/enablers/Retrying$$anon$1;

  public java.lang.Thread newThread(java.lang.Runnable);
    descriptor: (Ljava/lang/Runnable;)Ljava/lang/Thread;
    flags: (0x0001) ACC_PUBLIC
    Code:
      stack=2, locals=3, args_size=2
         0: aload_0
         1: invokevirtual #24                 // Method inner:()Ljava/util/concurrent/ThreadFactory;
         4: aload_1
         5: invokeinterface #26,  2           // InterfaceMethod java/util/concurrent/ThreadFactory.newThread:(Ljava/lang/Runnable;)Ljava/lang/Thread;
        10: astore_2
        11: aload_2
        12: ldc           #28                 // String ScalaTest-retrying
        14: invokevirtual #34                 // Method java/lang/Thread.setName:(Ljava/lang/String;)V
        17: aload_2
        18: iconst_1
        19: invokevirtual #38                 // Method java/lang/Thread.setDaemon:(Z)V
        22: aload_2
        23: areturn
      LineNumberTable:
        line 63: 0
        line 64: 11
        line 65: 17
        line 66: 22
      LocalVariableTable:
        Start  Length  Slot  Name   Signature
           11      12     2 thread   Ljava/lang/Thread;
            0      24     0  this   Lorg/scalatest/enablers/Retrying$$anon$1;
            0      24     1 runnable   Ljava/lang/Runnable;
    MethodParameters:
      Name                           Flags
      runnable                       final

  public org.scalatest.enablers.Retrying$$anon$1();
    descriptor: ()V
    flags: (0x0001) ACC_PUBLIC
    Code:
      stack=2, locals=1, args_size=1
         0: aload_0
         1: invokespecial #45                 // Method java/lang/Object."<init>":()V
         4: aload_0
         5: invokestatic  #50                 // Method java/util/concurrent/Executors.defaultThreadFactory:()Ljava/util/concurrent/ThreadFactory;
         8: putfield      #17                 // Field inner:Ljava/util/concurrent/ThreadFactory;
        11: return
      LineNumberTable:
        line 60: 0
        line 61: 4
        line 60: 11
      LocalVariableTable:
        Start  Length  Slot  Name   Signature
            0      12     0  this   Lorg/scalatest/enablers/Retrying$$anon$1;
}
InnerClasses:
  public final #2;                        // class org/scalatest/enablers/Retrying$$anon$1
EnclosingMethod: #9.#12                 // org.scalatest.enablers.Retrying$.org$scalatest$enablers$Retrying$$createScheduler
SourceFile: "Retrying.scala"
  ScalaInlineInfo: length = 0x13 (unknown attribute)
   01 01 00 03 00 2A 00 2B 01 00 0D 00 0F 01 00 14
   00 15 01
  Scala: length = 0x0 (unknown attribute)

