Classfile /Users/mw/Projects/slang-braindump/.jar/jar11/assemble/slang-braindump/assemble/content/org/scalatest/enablers/Retrying$.class
  Last modified May 29, 2022; size 1704 bytes
  SHA-256 checksum 585510912c1841da01a25779a0695e7cfec92cc0cc34a2d37a59ec65ffd779e2
  Compiled from "Retrying.scala"
public final class org.scalatest.enablers.Retrying$
  minor version: 0
  major version: 52
  flags: (0x0031) ACC_PUBLIC, ACC_FINAL, ACC_SUPER
  this_class: #2                          // org/scalatest/enablers/Retrying$
  super_class: #4                         // java/lang/Object
  interfaces: 0, fields: 1, methods: 5, attributes: 4
Constant pool:
   #1 = Utf8               org/scalatest/enablers/Retrying$
   #2 = Class              #1             // org/scalatest/enablers/Retrying$
   #3 = Utf8               java/lang/Object
   #4 = Class              #3             // java/lang/Object
   #5 = Utf8               Retrying.scala
   #6 = Utf8               org/scalatest/enablers/Retrying$$anon$1
   #7 = Class              #6             // org/scalatest/enablers/Retrying$$anon$1
   #8 = Utf8               org/scalatest/enablers/Retrying$$anon$2
   #9 = Class              #8             // org/scalatest/enablers/Retrying$$anon$2
  #10 = Utf8               org/scalatest/enablers/Retrying$$anon$4
  #11 = Class              #10            // org/scalatest/enablers/Retrying$$anon$4
  #12 = Utf8               MODULE$
  #13 = Utf8               Lorg/scalatest/enablers/Retrying$;
  #14 = Utf8               <clinit>
  #15 = Utf8               ()V
  #16 = Utf8               <init>
  #17 = NameAndType        #16:#15        // "<init>":()V
  #18 = Methodref          #2.#17         // org/scalatest/enablers/Retrying$."<init>":()V
  #19 = NameAndType        #12:#13        // MODULE$:Lorg/scalatest/enablers/Retrying$;
  #20 = Fieldref           #2.#19         // org/scalatest/enablers/Retrying$.MODULE$:Lorg/scalatest/enablers/Retrying$;
  #21 = Utf8               org$scalatest$enablers$Retrying$$createScheduler
  #22 = Utf8               ()Ljava/util/concurrent/ScheduledExecutorService;
  #23 = Methodref          #7.#17         // org/scalatest/enablers/Retrying$$anon$1."<init>":()V
  #24 = Utf8               java/util/concurrent/Executors
  #25 = Class              #24            // java/util/concurrent/Executors
  #26 = Utf8               newSingleThreadScheduledExecutor
  #27 = Utf8               (Ljava/util/concurrent/ThreadFactory;)Ljava/util/concurrent/ScheduledExecutorService;
  #28 = NameAndType        #26:#27        // newSingleThreadScheduledExecutor:(Ljava/util/concurrent/ThreadFactory;)Ljava/util/concurrent/ScheduledExecutorService;
  #29 = Methodref          #25.#28        // java/util/concurrent/Executors.newSingleThreadScheduledExecutor:(Ljava/util/concurrent/ThreadFactory;)Ljava/util/concurrent/ScheduledExecutorService;
  #30 = Utf8               threadFactory
  #31 = Utf8               Ljava/util/concurrent/ThreadFactory;
  #32 = Utf8               this
  #33 = Utf8               retryingNatureOfFutureT
  #34 = Utf8               (Lscala/concurrent/ExecutionContext;)Lorg/scalatest/enablers/Retrying;
  #35 = Utf8               <T:Ljava/lang/Object;>(Lscala/concurrent/ExecutionContext;)Lorg/scalatest/enablers/Retrying<Lscala/concurrent/Future<TT;>;>;
  #36 = Utf8               execCtx
  #37 = Utf8               (Lscala/concurrent/ExecutionContext;)V
  #38 = NameAndType        #16:#37        // "<init>":(Lscala/concurrent/ExecutionContext;)V
  #39 = Methodref          #9.#38         // org/scalatest/enablers/Retrying$$anon$2."<init>":(Lscala/concurrent/ExecutionContext;)V
  #40 = Utf8               Lscala/concurrent/ExecutionContext;
  #41 = Utf8               retryingNatureOfT
  #42 = Utf8               ()Lorg/scalatest/enablers/Retrying;
  #43 = Utf8               <T:Ljava/lang/Object;>()Lorg/scalatest/enablers/Retrying<TT;>;
  #44 = Methodref          #11.#17        // org/scalatest/enablers/Retrying$$anon$4."<init>":()V
  #45 = Methodref          #4.#17         // java/lang/Object."<init>":()V
  #46 = Utf8               Code
  #47 = Utf8               LineNumberTable
  #48 = Utf8               LocalVariableTable
  #49 = Utf8               Signature
  #50 = Utf8               MethodParameters
  #51 = Utf8               InnerClasses
  #52 = Utf8               SourceFile
  #53 = Utf8               ScalaInlineInfo
  #54 = Utf8               Scala
{
  public static final org.scalatest.enablers.Retrying$ MODULE$;
    descriptor: Lorg/scalatest/enablers/Retrying$;
    flags: (0x0019) ACC_PUBLIC, ACC_STATIC, ACC_FINAL

  public static {};
    descriptor: ()V
    flags: (0x0009) ACC_PUBLIC, ACC_STATIC
    Code:
      stack=2, locals=0, args_size=0
         0: new           #2                  // class org/scalatest/enablers/Retrying$
         3: dup
         4: invokespecial #18                 // Method "<init>":()V
         7: putstatic     #20                 // Field MODULE$:Lorg/scalatest/enablers/Retrying$;
        10: return
      LineNumberTable:
        line 57: 0

  public java.util.concurrent.ScheduledExecutorService org$scalatest$enablers$Retrying$$createScheduler();
    descriptor: ()Ljava/util/concurrent/ScheduledExecutorService;
    flags: (0x0001) ACC_PUBLIC
    Code:
      stack=2, locals=2, args_size=1
         0: new           #7                  // class org/scalatest/enablers/Retrying$$anon$1
         3: dup
         4: invokespecial #23                 // Method org/scalatest/enablers/Retrying$$anon$1."<init>":()V
         7: astore_1
         8: aload_1
         9: invokestatic  #29                 // Method java/util/concurrent/Executors.newSingleThreadScheduledExecutor:(Ljava/util/concurrent/ThreadFactory;)Ljava/util/concurrent/ScheduledExecutorService;
        12: areturn
      LineNumberTable:
        line 60: 0
        line 70: 8
      LocalVariableTable:
        Start  Length  Slot  Name   Signature
            8       4     1 threadFactory   Ljava/util/concurrent/ThreadFactory;
            0      13     0  this   Lorg/scalatest/enablers/Retrying$;

  public <T extends java.lang.Object> org.scalatest.enablers.Retrying<scala.concurrent.Future<T>> retryingNatureOfFutureT(scala.concurrent.ExecutionContext);
    descriptor: (Lscala/concurrent/ExecutionContext;)Lorg/scalatest/enablers/Retrying;
    flags: (0x0001) ACC_PUBLIC
    Code:
      stack=3, locals=2, args_size=2
         0: new           #9                  // class org/scalatest/enablers/Retrying$$anon$2
         3: dup
         4: aload_1
         5: invokespecial #39                 // Method org/scalatest/enablers/Retrying$$anon$2."<init>":(Lscala/concurrent/ExecutionContext;)V
         8: areturn
      LineNumberTable:
        line 77: 0
      LocalVariableTable:
        Start  Length  Slot  Name   Signature
            0       9     0  this   Lorg/scalatest/enablers/Retrying$;
            0       9     1 execCtx   Lscala/concurrent/ExecutionContext;
    Signature: #35                          // <T:Ljava/lang/Object;>(Lscala/concurrent/ExecutionContext;)Lorg/scalatest/enablers/Retrying<Lscala/concurrent/Future<TT;>;>;
    MethodParameters:
      Name                           Flags
      execCtx                        final

  public <T extends java.lang.Object> org.scalatest.enablers.Retrying<T> retryingNatureOfT();
    descriptor: ()Lorg/scalatest/enablers/Retrying;
    flags: (0x0001) ACC_PUBLIC
    Code:
      stack=2, locals=1, args_size=1
         0: new           #11                 // class org/scalatest/enablers/Retrying$$anon$4
         3: dup
         4: invokespecial #44                 // Method org/scalatest/enablers/Retrying$$anon$4."<init>":()V
         7: areturn
      LineNumberTable:
        line 179: 0
      LocalVariableTable:
        Start  Length  Slot  Name   Signature
            0       8     0  this   Lorg/scalatest/enablers/Retrying$;
    Signature: #43                          // <T:Ljava/lang/Object;>()Lorg/scalatest/enablers/Retrying<TT;>;

  private org.scalatest.enablers.Retrying$();
    descriptor: ()V
    flags: (0x0002) ACC_PRIVATE
    Code:
      stack=1, locals=1, args_size=1
         0: aload_0
         1: invokespecial #45                 // Method java/lang/Object."<init>":()V
         4: return
      LineNumberTable:
        line 230: 0
        line 57: 4
      LocalVariableTable:
        Start  Length  Slot  Name   Signature
            0       5     0  this   Lorg/scalatest/enablers/Retrying$;
}
InnerClasses:
  public final #7;                        // class org/scalatest/enablers/Retrying$$anon$1
  public final #9;                        // class org/scalatest/enablers/Retrying$$anon$2
  public final #11;                       // class org/scalatest/enablers/Retrying$$anon$4
SourceFile: "Retrying.scala"
  ScalaInlineInfo: length = 0x18 (unknown attribute)
   01 01 00 04 00 10 00 0F 01 00 15 00 16 01 00 21
   00 22 01 00 29 00 2A 01
  Scala: length = 0x0 (unknown attribute)

