Classfile /Users/mw/Projects/slang-braindump/.jar/jar11/assemble/slang-braindump/assemble/content/org/scalatest/enablers/Size$.class
  Last modified May 29, 2022; size 3188 bytes
  SHA-256 checksum 032acf90687c18afc34898a789bf7774efcc3d8aa2bf13da84a0e592604a895e
  Compiled from "Size.scala"
public final class org.scalatest.enablers.Size$
  minor version: 0
  major version: 52
  flags: (0x0031) ACC_PUBLIC, ACC_FINAL, ACC_SUPER
  this_class: #2                          // org/scalatest/enablers/Size$
  super_class: #4                         // java/lang/Object
  interfaces: 0, fields: 2, methods: 15, attributes: 4
Constant pool:
   #1 = Utf8               org/scalatest/enablers/Size$
   #2 = Class              #1             // org/scalatest/enablers/Size$
   #3 = Utf8               java/lang/Object
   #4 = Class              #3             // java/lang/Object
   #5 = Utf8               Size.scala
   #6 = Utf8               org/scalatest/enablers/Size$$anon$1
   #7 = Class              #6             // org/scalatest/enablers/Size$$anon$1
   #8 = Utf8               org/scalatest/enablers/Size$$anon$10
   #9 = Class              #8             // org/scalatest/enablers/Size$$anon$10
  #10 = Utf8               org/scalatest/enablers/Size$$anon$11
  #11 = Class              #10            // org/scalatest/enablers/Size$$anon$11
  #12 = Utf8               org/scalatest/enablers/Size$$anon$12
  #13 = Class              #12            // org/scalatest/enablers/Size$$anon$12
  #14 = Utf8               org/scalatest/enablers/Size$$anon$13
  #15 = Class              #14            // org/scalatest/enablers/Size$$anon$13
  #16 = Utf8               org/scalatest/enablers/Size$$anon$2
  #17 = Class              #16            // org/scalatest/enablers/Size$$anon$2
  #18 = Utf8               org/scalatest/enablers/Size$$anon$3
  #19 = Class              #18            // org/scalatest/enablers/Size$$anon$3
  #20 = Utf8               org/scalatest/enablers/Size$$anon$4
  #21 = Class              #20            // org/scalatest/enablers/Size$$anon$4
  #22 = Utf8               org/scalatest/enablers/Size$$anon$5
  #23 = Class              #22            // org/scalatest/enablers/Size$$anon$5
  #24 = Utf8               org/scalatest/enablers/Size$$anon$6
  #25 = Class              #24            // org/scalatest/enablers/Size$$anon$6
  #26 = Utf8               org/scalatest/enablers/Size$$anon$7
  #27 = Class              #26            // org/scalatest/enablers/Size$$anon$7
  #28 = Utf8               org/scalatest/enablers/Size$$anon$8
  #29 = Class              #28            // org/scalatest/enablers/Size$$anon$8
  #30 = Utf8               org/scalatest/enablers/Size$$anon$9
  #31 = Class              #30            // org/scalatest/enablers/Size$$anon$9
  #32 = Utf8               MODULE$
  #33 = Utf8               Lorg/scalatest/enablers/Size$;
  #34 = Utf8               sizeOfString
  #35 = Utf8               Lorg/scalatest/enablers/Size;
  #36 = Utf8               Lorg/scalatest/enablers/Size<Ljava/lang/String;>;
  #37 = Utf8               <clinit>
  #38 = Utf8               ()V
  #39 = Utf8               <init>
  #40 = NameAndType        #39:#38        // "<init>":()V
  #41 = Methodref          #2.#40         // org/scalatest/enablers/Size$."<init>":()V
  #42 = NameAndType        #32:#33        // MODULE$:Lorg/scalatest/enablers/Size$;
  #43 = Fieldref           #2.#42         // org/scalatest/enablers/Size$.MODULE$:Lorg/scalatest/enablers/Size$;
  #44 = Methodref          #23.#40        // org/scalatest/enablers/Size$$anon$5."<init>":()V
  #45 = NameAndType        #34:#35        // sizeOfString:Lorg/scalatest/enablers/Size;
  #46 = Fieldref           #2.#45         // org/scalatest/enablers/Size$.sizeOfString:Lorg/scalatest/enablers/Size;
  #47 = Utf8               sizeOfJavaCollection
  #48 = Utf8               ()Lorg/scalatest/enablers/Size;
  #49 = Utf8               <JCOL::Ljava/util/Collection<*>;>()Lorg/scalatest/enablers/Size<TJCOL;>;
  #50 = Methodref          #7.#40         // org/scalatest/enablers/Size$$anon$1."<init>":()V
  #51 = Utf8               this
  #52 = Utf8               sizeOfJavaMap
  #53 = Utf8               <JMAP::Ljava/util/Map<**>;>()Lorg/scalatest/enablers/Size<TJMAP;>;
  #54 = Methodref          #17.#40        // org/scalatest/enablers/Size$$anon$2."<init>":()V
  #55 = Utf8               sizeOfGenTraversable
  #56 = Utf8               <TRAV::Lscala/collection/Iterable<*>;>()Lorg/scalatest/enablers/Size<TTRAV;>;
  #57 = Methodref          #19.#40        // org/scalatest/enablers/Size$$anon$3."<init>":()V
  #58 = Utf8               sizeOfArray
  #59 = Utf8               <E:Ljava/lang/Object;>()Lorg/scalatest/enablers/Size<Ljava/lang/Object;>;
  #60 = Methodref          #21.#40        // org/scalatest/enablers/Size$$anon$4."<init>":()V
  #61 = Utf8               ()Lorg/scalatest/enablers/Size<Ljava/lang/String;>;
  #62 = Utf8               sizeOfAnyRefWithSizeMethodForInt
  #63 = Utf8               <T:Ljava/lang/Object;>()Lorg/scalatest/enablers/Size<TT;>;
  #64 = Methodref          #25.#40        // org/scalatest/enablers/Size$$anon$6."<init>":()V
  #65 = Utf8               sizeOfAnyRefWithParameterlessSizeMethodForInt
  #66 = Methodref          #27.#40        // org/scalatest/enablers/Size$$anon$7."<init>":()V
  #67 = Utf8               sizeOfAnyRefWithGetSizeMethodForInt
  #68 = Methodref          #29.#40        // org/scalatest/enablers/Size$$anon$8."<init>":()V
  #69 = Utf8               sizeOfAnyRefWithParameterlessGetSizeMethodForInt
  #70 = Methodref          #31.#40        // org/scalatest/enablers/Size$$anon$9."<init>":()V
  #71 = Utf8               sizeOfAnyRefWithSizeMethodForLong
  #72 = Methodref          #9.#40         // org/scalatest/enablers/Size$$anon$10."<init>":()V
  #73 = Utf8               sizeOfAnyRefWithParameterlessSizeMethodForLong
  #74 = Methodref          #11.#40        // org/scalatest/enablers/Size$$anon$11."<init>":()V
  #75 = Utf8               sizeOfAnyRefWithGetSizeMethodForLong
  #76 = Methodref          #13.#40        // org/scalatest/enablers/Size$$anon$12."<init>":()V
  #77 = Utf8               sizeOfAnyRefWithParameterlessGetSizeMethodForLong
  #78 = Methodref          #15.#40        // org/scalatest/enablers/Size$$anon$13."<init>":()V
  #79 = Methodref          #4.#40         // java/lang/Object."<init>":()V
  #80 = Utf8               Signature
  #81 = Utf8               Code
  #82 = Utf8               LineNumberTable
  #83 = Utf8               LocalVariableTable
  #84 = Utf8               InnerClasses
  #85 = Utf8               SourceFile
  #86 = Utf8               ScalaInlineInfo
  #87 = Utf8               Scala
{
  public static final org.scalatest.enablers.Size$ MODULE$;
    descriptor: Lorg/scalatest/enablers/Size$;
    flags: (0x0019) ACC_PUBLIC, ACC_STATIC, ACC_FINAL

  private static final org.scalatest.enablers.Size<java.lang.String> sizeOfString;
    descriptor: Lorg/scalatest/enablers/Size;
    flags: (0x001a) ACC_PRIVATE, ACC_STATIC, ACC_FINAL
    Signature: #36                          // Lorg/scalatest/enablers/Size<Ljava/lang/String;>;

  public static {};
    descriptor: ()V
    flags: (0x0009) ACC_PUBLIC, ACC_STATIC
    Code:
      stack=2, locals=0, args_size=0
         0: new           #2                  // class org/scalatest/enablers/Size$
         3: dup
         4: invokespecial #41                 // Method "<init>":()V
         7: putstatic     #43                 // Field MODULE$:Lorg/scalatest/enablers/Size$;
        10: new           #23                 // class org/scalatest/enablers/Size$$anon$5
        13: dup
        14: invokespecial #44                 // Method org/scalatest/enablers/Size$$anon$5."<init>":()V
        17: putstatic     #46                 // Field sizeOfString:Lorg/scalatest/enablers/Size;
        20: return
      LineNumberTable:
        line 120: 0
        line 174: 10
        line 173: 17
        line 120: 20

  public <JCOL extends java.util.Collection<?>> org.scalatest.enablers.Size<JCOL> sizeOfJavaCollection();
    descriptor: ()Lorg/scalatest/enablers/Size;
    flags: (0x0001) ACC_PUBLIC
    Code:
      stack=2, locals=1, args_size=1
         0: new           #7                  // class org/scalatest/enablers/Size$$anon$1
         3: dup
         4: invokespecial #50                 // Method org/scalatest/enablers/Size$$anon$1."<init>":()V
         7: areturn
      LineNumberTable:
        line 131: 0
      LocalVariableTable:
        Start  Length  Slot  Name   Signature
            0       8     0  this   Lorg/scalatest/enablers/Size$;
    Signature: #49                          // <JCOL::Ljava/util/Collection<*>;>()Lorg/scalatest/enablers/Size<TJCOL;>;

  public <JMAP extends java.util.Map<?, ?>> org.scalatest.enablers.Size<JMAP> sizeOfJavaMap();
    descriptor: ()Lorg/scalatest/enablers/Size;
    flags: (0x0001) ACC_PUBLIC
    Code:
      stack=2, locals=1, args_size=1
         0: new           #17                 // class org/scalatest/enablers/Size$$anon$2
         3: dup
         4: invokespecial #54                 // Method org/scalatest/enablers/Size$$anon$2."<init>":()V
         7: areturn
      LineNumberTable:
        line 142: 0
      LocalVariableTable:
        Start  Length  Slot  Name   Signature
            0       8     0  this   Lorg/scalatest/enablers/Size$;
    Signature: #53                          // <JMAP::Ljava/util/Map<**>;>()Lorg/scalatest/enablers/Size<TJMAP;>;

  public <TRAV extends scala.collection.Iterable<?>> org.scalatest.enablers.Size<TRAV> sizeOfGenTraversable();
    descriptor: ()Lorg/scalatest/enablers/Size;
    flags: (0x0001) ACC_PUBLIC
    Code:
      stack=2, locals=1, args_size=1
         0: new           #19                 // class org/scalatest/enablers/Size$$anon$3
         3: dup
         4: invokespecial #57                 // Method org/scalatest/enablers/Size$$anon$3."<init>":()V
         7: areturn
      LineNumberTable:
        line 153: 0
      LocalVariableTable:
        Start  Length  Slot  Name   Signature
            0       8     0  this   Lorg/scalatest/enablers/Size$;
    Signature: #56                          // <TRAV::Lscala/collection/Iterable<*>;>()Lorg/scalatest/enablers/Size<TTRAV;>;

  public <E extends java.lang.Object> org.scalatest.enablers.Size<java.lang.Object> sizeOfArray();
    descriptor: ()Lorg/scalatest/enablers/Size;
    flags: (0x0001) ACC_PUBLIC
    Code:
      stack=2, locals=1, args_size=1
         0: new           #21                 // class org/scalatest/enablers/Size$$anon$4
         3: dup
         4: invokespecial #60                 // Method org/scalatest/enablers/Size$$anon$4."<init>":()V
         7: areturn
      LineNumberTable:
        line 164: 0
      LocalVariableTable:
        Start  Length  Slot  Name   Signature
            0       8     0  this   Lorg/scalatest/enablers/Size$;
    Signature: #59                          // <E:Ljava/lang/Object;>()Lorg/scalatest/enablers/Size<Ljava/lang/Object;>;

  public org.scalatest.enablers.Size<java.lang.String> sizeOfString();
    descriptor: ()Lorg/scalatest/enablers/Size;
    flags: (0x0001) ACC_PUBLIC
    Code:
      stack=1, locals=1, args_size=1
         0: getstatic     #46                 // Field sizeOfString:Lorg/scalatest/enablers/Size;
         3: areturn
      LineNumberTable:
        line 173: 0
      LocalVariableTable:
        Start  Length  Slot  Name   Signature
            0       4     0  this   Lorg/scalatest/enablers/Size$;
    Signature: #61                          // ()Lorg/scalatest/enablers/Size<Ljava/lang/String;>;

  public <T extends java.lang.Object> org.scalatest.enablers.Size<T> sizeOfAnyRefWithSizeMethodForInt();
    descriptor: ()Lorg/scalatest/enablers/Size;
    flags: (0x0001) ACC_PUBLIC
    Code:
      stack=2, locals=1, args_size=1
         0: new           #25                 // class org/scalatest/enablers/Size$$anon$6
         3: dup
         4: invokespecial #64                 // Method org/scalatest/enablers/Size$$anon$6."<init>":()V
         7: areturn
      LineNumberTable:
        line 187: 0
      LocalVariableTable:
        Start  Length  Slot  Name   Signature
            0       8     0  this   Lorg/scalatest/enablers/Size$;
    Signature: #63                          // <T:Ljava/lang/Object;>()Lorg/scalatest/enablers/Size<TT;>;

  public <T extends java.lang.Object> org.scalatest.enablers.Size<T> sizeOfAnyRefWithParameterlessSizeMethodForInt();
    descriptor: ()Lorg/scalatest/enablers/Size;
    flags: (0x0001) ACC_PUBLIC
    Code:
      stack=2, locals=1, args_size=1
         0: new           #27                 // class org/scalatest/enablers/Size$$anon$7
         3: dup
         4: invokespecial #66                 // Method org/scalatest/enablers/Size$$anon$7."<init>":()V
         7: areturn
      LineNumberTable:
        line 198: 0
      LocalVariableTable:
        Start  Length  Slot  Name   Signature
            0       8     0  this   Lorg/scalatest/enablers/Size$;
    Signature: #63                          // <T:Ljava/lang/Object;>()Lorg/scalatest/enablers/Size<TT;>;

  public <T extends java.lang.Object> org.scalatest.enablers.Size<T> sizeOfAnyRefWithGetSizeMethodForInt();
    descriptor: ()Lorg/scalatest/enablers/Size;
    flags: (0x0001) ACC_PUBLIC
    Code:
      stack=2, locals=1, args_size=1
         0: new           #29                 // class org/scalatest/enablers/Size$$anon$8
         3: dup
         4: invokespecial #68                 // Method org/scalatest/enablers/Size$$anon$8."<init>":()V
         7: areturn
      LineNumberTable:
        line 209: 0
      LocalVariableTable:
        Start  Length  Slot  Name   Signature
            0       8     0  this   Lorg/scalatest/enablers/Size$;
    Signature: #63                          // <T:Ljava/lang/Object;>()Lorg/scalatest/enablers/Size<TT;>;

  public <T extends java.lang.Object> org.scalatest.enablers.Size<T> sizeOfAnyRefWithParameterlessGetSizeMethodForInt();
    descriptor: ()Lorg/scalatest/enablers/Size;
    flags: (0x0001) ACC_PUBLIC
    Code:
      stack=2, locals=1, args_size=1
         0: new           #31                 // class org/scalatest/enablers/Size$$anon$9
         3: dup
         4: invokespecial #70                 // Method org/scalatest/enablers/Size$$anon$9."<init>":()V
         7: areturn
      LineNumberTable:
        line 220: 0
      LocalVariableTable:
        Start  Length  Slot  Name   Signature
            0       8     0  this   Lorg/scalatest/enablers/Size$;
    Signature: #63                          // <T:Ljava/lang/Object;>()Lorg/scalatest/enablers/Size<TT;>;

  public <T extends java.lang.Object> org.scalatest.enablers.Size<T> sizeOfAnyRefWithSizeMethodForLong();
    descriptor: ()Lorg/scalatest/enablers/Size;
    flags: (0x0001) ACC_PUBLIC
    Code:
      stack=2, locals=1, args_size=1
         0: new           #9                  // class org/scalatest/enablers/Size$$anon$10
         3: dup
         4: invokespecial #72                 // Method org/scalatest/enablers/Size$$anon$10."<init>":()V
         7: areturn
      LineNumberTable:
        line 231: 0
      LocalVariableTable:
        Start  Length  Slot  Name   Signature
            0       8     0  this   Lorg/scalatest/enablers/Size$;
    Signature: #63                          // <T:Ljava/lang/Object;>()Lorg/scalatest/enablers/Size<TT;>;

  public <T extends java.lang.Object> org.scalatest.enablers.Size<T> sizeOfAnyRefWithParameterlessSizeMethodForLong();
    descriptor: ()Lorg/scalatest/enablers/Size;
    flags: (0x0001) ACC_PUBLIC
    Code:
      stack=2, locals=1, args_size=1
         0: new           #11                 // class org/scalatest/enablers/Size$$anon$11
         3: dup
         4: invokespecial #74                 // Method org/scalatest/enablers/Size$$anon$11."<init>":()V
         7: areturn
      LineNumberTable:
        line 242: 0
      LocalVariableTable:
        Start  Length  Slot  Name   Signature
            0       8     0  this   Lorg/scalatest/enablers/Size$;
    Signature: #63                          // <T:Ljava/lang/Object;>()Lorg/scalatest/enablers/Size<TT;>;

  public <T extends java.lang.Object> org.scalatest.enablers.Size<T> sizeOfAnyRefWithGetSizeMethodForLong();
    descriptor: ()Lorg/scalatest/enablers/Size;
    flags: (0x0001) ACC_PUBLIC
    Code:
      stack=2, locals=1, args_size=1
         0: new           #13                 // class org/scalatest/enablers/Size$$anon$12
         3: dup
         4: invokespecial #76                 // Method org/scalatest/enablers/Size$$anon$12."<init>":()V
         7: areturn
      LineNumberTable:
        line 253: 0
      LocalVariableTable:
        Start  Length  Slot  Name   Signature
            0       8     0  this   Lorg/scalatest/enablers/Size$;
    Signature: #63                          // <T:Ljava/lang/Object;>()Lorg/scalatest/enablers/Size<TT;>;

  public <T extends java.lang.Object> org.scalatest.enablers.Size<T> sizeOfAnyRefWithParameterlessGetSizeMethodForLong();
    descriptor: ()Lorg/scalatest/enablers/Size;
    flags: (0x0001) ACC_PUBLIC
    Code:
      stack=2, locals=1, args_size=1
         0: new           #15                 // class org/scalatest/enablers/Size$$anon$13
         3: dup
         4: invokespecial #78                 // Method org/scalatest/enablers/Size$$anon$13."<init>":()V
         7: areturn
      LineNumberTable:
        line 264: 0
      LocalVariableTable:
        Start  Length  Slot  Name   Signature
            0       8     0  this   Lorg/scalatest/enablers/Size$;
    Signature: #63                          // <T:Ljava/lang/Object;>()Lorg/scalatest/enablers/Size<TT;>;

  private org.scalatest.enablers.Size$();
    descriptor: ()V
    flags: (0x0002) ACC_PRIVATE
    Code:
      stack=1, locals=1, args_size=1
         0: aload_0
         1: invokespecial #79                 // Method java/lang/Object."<init>":()V
         4: return
      LineNumberTable:
        line 267: 0
        line 120: 4
      LocalVariableTable:
        Start  Length  Slot  Name   Signature
            0       5     0  this   Lorg/scalatest/enablers/Size$;
}
InnerClasses:
  public final #7;                        // class org/scalatest/enablers/Size$$anon$1
  public final #9;                        // class org/scalatest/enablers/Size$$anon$10
  public final #11;                       // class org/scalatest/enablers/Size$$anon$11
  public final #13;                       // class org/scalatest/enablers/Size$$anon$12
  public final #15;                       // class org/scalatest/enablers/Size$$anon$13
  public final #17;                       // class org/scalatest/enablers/Size$$anon$2
  public final #19;                       // class org/scalatest/enablers/Size$$anon$3
  public final #21;                       // class org/scalatest/enablers/Size$$anon$4
  public final #23;                       // class org/scalatest/enablers/Size$$anon$5
  public final #25;                       // class org/scalatest/enablers/Size$$anon$6
  public final #27;                       // class org/scalatest/enablers/Size$$anon$7
  public final #29;                       // class org/scalatest/enablers/Size$$anon$8
  public final #31;                       // class org/scalatest/enablers/Size$$anon$9
SourceFile: "Size.scala"
  ScalaInlineInfo: length = 0x4A (unknown attribute)
   01 01 00 0E 00 27 00 26 01 00 43 00 30 01 00 4B
   00 30 01 00 45 00 30 01 00 4D 00 30 01 00 41 00
   30 01 00 49 00 30 01 00 3E 00 30 01 00 47 00 30
   01 00 3A 00 30 01 00 37 00 30 01 00 2F 00 30 01
   00 34 00 30 01 00 22 00 30 01
  Scala: length = 0x0 (unknown attribute)

