Classfile /Users/mw/Projects/slang-braindump/.jar/jar11/assemble/slang-braindump/assemble/content/org/scalatest/enablers/Slicing$$anon$1.class
  Last modified May 29, 2022; size 1702 bytes
  SHA-256 checksum 9f28eb5bfe79d821f06aead4f64c8fcbd51fcfcd5352167217778cf6d7603d88
  Compiled from "Slicing.scala"
public final class org.scalatest.enablers.Slicing$$anon$1 extends java.lang.Object implements org.scalatest.enablers.Slicing<java.lang.String>
  minor version: 0
  major version: 52
  flags: (0x0031) ACC_PUBLIC, ACC_FINAL, ACC_SUPER
  this_class: #2                          // org/scalatest/enablers/Slicing$$anon$1
  super_class: #5                         // java/lang/Object
  interfaces: 1, fields: 0, methods: 7, attributes: 6
Constant pool:
   #1 = Utf8               org/scalatest/enablers/Slicing$$anon$1
   #2 = Class              #1             // org/scalatest/enablers/Slicing$$anon$1
   #3 = Utf8               Ljava/lang/Object;Lorg/scalatest/enablers/Slicing<Ljava/lang/String;>;
   #4 = Utf8               java/lang/Object
   #5 = Class              #4             // java/lang/Object
   #6 = Utf8               org/scalatest/enablers/Slicing
   #7 = Class              #6             // org/scalatest/enablers/Slicing
   #8 = Utf8               Slicing.scala
   #9 = Utf8               org/scalatest/enablers/Slicing$
  #10 = Class              #9             // org/scalatest/enablers/Slicing$
  #11 = Utf8               slicingNatureOfString
  #12 = Utf8               ()Lorg/scalatest/enablers/Slicing;
  #13 = NameAndType        #11:#12        // slicingNatureOfString:()Lorg/scalatest/enablers/Slicing;
  #14 = Utf8               includes
  #15 = Utf8               (Ljava/lang/String;Ljava/lang/String;)Z
  #16 = Utf8               string
  #17 = Utf8               subString
  #18 = Utf8               java/lang/String
  #19 = Class              #18            // java/lang/String
  #20 = Utf8               indexOf
  #21 = Utf8               (Ljava/lang/String;)I
  #22 = NameAndType        #20:#21        // indexOf:(Ljava/lang/String;)I
  #23 = Methodref          #19.#22        // java/lang/String.indexOf:(Ljava/lang/String;)I
  #24 = Utf8               this
  #25 = Utf8               Lorg/scalatest/enablers/Slicing$$anon$1;
  #26 = Utf8               Ljava/lang/String;
  #27 = Utf8               startsWith
  #28 = Utf8               prefix
  #29 = Utf8               (Ljava/lang/String;)Z
  #30 = NameAndType        #27:#29        // startsWith:(Ljava/lang/String;)Z
  #31 = Methodref          #19.#30        // java/lang/String.startsWith:(Ljava/lang/String;)Z
  #32 = Utf8               endsWith
  #33 = Utf8               suffix
  #34 = NameAndType        #32:#29        // endsWith:(Ljava/lang/String;)Z
  #35 = Methodref          #19.#34        // java/lang/String.endsWith:(Ljava/lang/String;)Z
  #36 = Utf8               (Ljava/lang/Object;Ljava/lang/Object;)Z
  #37 = Utf8               sequence
  #38 = NameAndType        #32:#15        // endsWith:(Ljava/lang/String;Ljava/lang/String;)Z
  #39 = Methodref          #2.#38         // org/scalatest/enablers/Slicing$$anon$1.endsWith:(Ljava/lang/String;Ljava/lang/String;)Z
  #40 = Utf8               Ljava/lang/Object;
  #41 = NameAndType        #27:#15        // startsWith:(Ljava/lang/String;Ljava/lang/String;)Z
  #42 = Methodref          #2.#41         // org/scalatest/enablers/Slicing$$anon$1.startsWith:(Ljava/lang/String;Ljava/lang/String;)Z
  #43 = Utf8               subSequence
  #44 = NameAndType        #14:#15        // includes:(Ljava/lang/String;Ljava/lang/String;)Z
  #45 = Methodref          #2.#44         // org/scalatest/enablers/Slicing$$anon$1.includes:(Ljava/lang/String;Ljava/lang/String;)Z
  #46 = Utf8               <init>
  #47 = Utf8               ()V
  #48 = NameAndType        #46:#47        // "<init>":()V
  #49 = Methodref          #5.#48         // java/lang/Object."<init>":()V
  #50 = Utf8               Code
  #51 = Utf8               StackMapTable
  #52 = Utf8               LineNumberTable
  #53 = Utf8               LocalVariableTable
  #54 = Utf8               MethodParameters
  #55 = Utf8               InnerClasses
  #56 = Utf8               EnclosingMethod
  #57 = Utf8               Signature
  #58 = Utf8               SourceFile
  #59 = Utf8               ScalaInlineInfo
  #60 = Utf8               Scala
{
  public boolean includes(java.lang.String, java.lang.String);
    descriptor: (Ljava/lang/String;Ljava/lang/String;)Z
    flags: (0x0001) ACC_PUBLIC
    Code:
      stack=2, locals=3, args_size=3
         0: aload_1
         1: aload_2
         2: invokevirtual #23                 // Method java/lang/String.indexOf:(Ljava/lang/String;)I
         5: iconst_0
         6: if_icmplt     13
         9: iconst_1
        10: goto          14
        13: iconst_0
        14: ireturn
      StackMapTable: number_of_entries = 2
        frame_type = 13 /* same */
        frame_type = 64 /* same_locals_1_stack_item */
          stack = [ int ]
      LineNumberTable:
        line 115: 0
      LocalVariableTable:
        Start  Length  Slot  Name   Signature
            0      15     0  this   Lorg/scalatest/enablers/Slicing$$anon$1;
            0      15     1 string   Ljava/lang/String;
            0      15     2 subString   Ljava/lang/String;
    MethodParameters:
      Name                           Flags
      string                         final
      subString                      final

  public boolean startsWith(java.lang.String, java.lang.String);
    descriptor: (Ljava/lang/String;Ljava/lang/String;)Z
    flags: (0x0001) ACC_PUBLIC
    Code:
      stack=2, locals=3, args_size=3
         0: aload_1
         1: aload_2
         2: invokevirtual #31                 // Method java/lang/String.startsWith:(Ljava/lang/String;)Z
         5: ireturn
      LineNumberTable:
        line 116: 0
      LocalVariableTable:
        Start  Length  Slot  Name   Signature
            0       6     0  this   Lorg/scalatest/enablers/Slicing$$anon$1;
            0       6     1 string   Ljava/lang/String;
            0       6     2 prefix   Ljava/lang/String;
    MethodParameters:
      Name                           Flags
      string                         final
      prefix                         final

  public boolean endsWith(java.lang.String, java.lang.String);
    descriptor: (Ljava/lang/String;Ljava/lang/String;)Z
    flags: (0x0001) ACC_PUBLIC
    Code:
      stack=2, locals=3, args_size=3
         0: aload_1
         1: aload_2
         2: invokevirtual #35                 // Method java/lang/String.endsWith:(Ljava/lang/String;)Z
         5: ireturn
      LineNumberTable:
        line 117: 0
      LocalVariableTable:
        Start  Length  Slot  Name   Signature
            0       6     0  this   Lorg/scalatest/enablers/Slicing$$anon$1;
            0       6     1 string   Ljava/lang/String;
            0       6     2 suffix   Ljava/lang/String;
    MethodParameters:
      Name                           Flags
      string                         final
      suffix                         final

  public boolean endsWith(java.lang.Object, java.lang.Object);
    descriptor: (Ljava/lang/Object;Ljava/lang/Object;)Z
    flags: (0x1041) ACC_PUBLIC, ACC_BRIDGE, ACC_SYNTHETIC
    Code:
      stack=3, locals=3, args_size=3
         0: aload_0
         1: aload_1
         2: checkcast     #19                 // class java/lang/String
         5: aload_2
         6: checkcast     #19                 // class java/lang/String
         9: invokevirtual #39                 // Method endsWith:(Ljava/lang/String;Ljava/lang/String;)Z
        12: ireturn
      LineNumberTable:
        line 114: 0
      LocalVariableTable:
        Start  Length  Slot  Name   Signature
            0      13     0  this   Lorg/scalatest/enablers/Slicing$$anon$1;
            0      13     1 sequence   Ljava/lang/Object;
            0      13     2 suffix   Ljava/lang/Object;
    MethodParameters:
      Name                           Flags
      sequence                       final
      suffix                         final

  public boolean startsWith(java.lang.Object, java.lang.Object);
    descriptor: (Ljava/lang/Object;Ljava/lang/Object;)Z
    flags: (0x1041) ACC_PUBLIC, ACC_BRIDGE, ACC_SYNTHETIC
    Code:
      stack=3, locals=3, args_size=3
         0: aload_0
         1: aload_1
         2: checkcast     #19                 // class java/lang/String
         5: aload_2
         6: checkcast     #19                 // class java/lang/String
         9: invokevirtual #42                 // Method startsWith:(Ljava/lang/String;Ljava/lang/String;)Z
        12: ireturn
      LineNumberTable:
        line 114: 0
      LocalVariableTable:
        Start  Length  Slot  Name   Signature
            0      13     0  this   Lorg/scalatest/enablers/Slicing$$anon$1;
            0      13     1 sequence   Ljava/lang/Object;
            0      13     2 prefix   Ljava/lang/Object;
    MethodParameters:
      Name                           Flags
      sequence                       final
      prefix                         final

  public boolean includes(java.lang.Object, java.lang.Object);
    descriptor: (Ljava/lang/Object;Ljava/lang/Object;)Z
    flags: (0x1041) ACC_PUBLIC, ACC_BRIDGE, ACC_SYNTHETIC
    Code:
      stack=3, locals=3, args_size=3
         0: aload_0
         1: aload_1
         2: checkcast     #19                 // class java/lang/String
         5: aload_2
         6: checkcast     #19                 // class java/lang/String
         9: invokevirtual #45                 // Method includes:(Ljava/lang/String;Ljava/lang/String;)Z
        12: ireturn
      LineNumberTable:
        line 114: 0
      LocalVariableTable:
        Start  Length  Slot  Name   Signature
            0      13     0  this   Lorg/scalatest/enablers/Slicing$$anon$1;
            0      13     1 sequence   Ljava/lang/Object;
            0      13     2 subSequence   Ljava/lang/Object;
    MethodParameters:
      Name                           Flags
      sequence                       final
      subSequence                    final

  public org.scalatest.enablers.Slicing$$anon$1();
    descriptor: ()V
    flags: (0x0001) ACC_PUBLIC
    Code:
      stack=1, locals=1, args_size=1
         0: aload_0
         1: invokespecial #49                 // Method java/lang/Object."<init>":()V
         4: return
      LineNumberTable:
        line 114: 0
      LocalVariableTable:
        Start  Length  Slot  Name   Signature
            0       5     0  this   Lorg/scalatest/enablers/Slicing$$anon$1;
}
InnerClasses:
  public final #2;                        // class org/scalatest/enablers/Slicing$$anon$1
EnclosingMethod: #10.#13                // org.scalatest.enablers.Slicing$.slicingNatureOfString
Signature: #3                           // Ljava/lang/Object;Lorg/scalatest/enablers/Slicing<Ljava/lang/String;>;
SourceFile: "Slicing.scala"
  ScalaInlineInfo: length = 0x27 (unknown attribute)
   01 01 00 07 00 2E 00 2F 01 00 20 00 24 01 00 20
   00 0F 01 00 0E 00 24 01 00 0E 00 0F 01 00 1B 00
   24 01 00 1B 00 0F 01
  Scala: length = 0x0 (unknown attribute)

