Classfile /Users/mw/Projects/slang-braindump/.jar/jar11/assemble/slang-braindump/assemble/content/org/scalatest/enablers/Timed$$anon$2.class
  Last modified May 29, 2022; size 6098 bytes
  SHA-256 checksum 038f5e53ac0068d63f2b90d74bad53914d3163e60beb8b3c8c5c71df8ab465d6
  Compiled from "Timed.scala"
public final class org.scalatest.enablers.Timed$$anon$2 extends java.lang.Object implements org.scalatest.enablers.Timed<scala.concurrent.Future<T>>
  minor version: 0
  major version: 52
  flags: (0x0031) ACC_PUBLIC, ACC_FINAL, ACC_SUPER
  this_class: #2                          // org/scalatest/enablers/Timed$$anon$2
  super_class: #5                         // java/lang/Object
  interfaces: 1, fields: 1, methods: 5, attributes: 7
Constant pool:
    #1 = Utf8               org/scalatest/enablers/Timed$$anon$2
    #2 = Class              #1            // org/scalatest/enablers/Timed$$anon$2
    #3 = Utf8               Ljava/lang/Object;Lorg/scalatest/enablers/Timed<Lscala/concurrent/Future<TT;>;>;
    #4 = Utf8               java/lang/Object
    #5 = Class              #4            // java/lang/Object
    #6 = Utf8               org/scalatest/enablers/Timed
    #7 = Class              #6            // org/scalatest/enablers/Timed
    #8 = Utf8               Timed.scala
    #9 = Utf8               org/scalatest/enablers/Timed$
   #10 = Class              #9            // org/scalatest/enablers/Timed$
   #11 = Utf8               timedFutureOf
   #12 = Utf8               (Lscala/concurrent/ExecutionContext;)Lorg/scalatest/enablers/Timed;
   #13 = NameAndType        #11:#12       // timedFutureOf:(Lscala/concurrent/ExecutionContext;)Lorg/scalatest/enablers/Timed;
   #14 = Utf8               java/lang/invoke/MethodHandles$Lookup
   #15 = Class              #14           // java/lang/invoke/MethodHandles$Lookup
   #16 = Utf8               java/lang/invoke/MethodHandles
   #17 = Class              #16           // java/lang/invoke/MethodHandles
   #18 = Utf8               Lookup
   #19 = Utf8               executionContext$1
   #20 = Utf8               Lscala/concurrent/ExecutionContext;
   #21 = Utf8               timeoutAfter
   #22 = Utf8               (Lorg/scalatest/time/Span;Lscala/Function0;Lorg/scalatest/concurrent/Signaler;Lscala/Function1;)Lscala/concurrent/Future;
   #23 = Utf8               (Lorg/scalatest/time/Span;Lscala/Function0<Lscala/concurrent/Future<TT;>;>;Lorg/scalatest/concurrent/Signaler;Lscala/Function1<Lscala/Option<Ljava/lang/Throwable;>;Lorg/scalatest/exceptions/StackDepthException;>;)Lscala/concurrent/Future<TT;>;
   #24 = Utf8               timeout
   #25 = Utf8               f
   #26 = Utf8               signaler
   #27 = Utf8               exceptionFun
   #28 = Utf8               java/lang/Throwable
   #29 = Class              #28           // java/lang/Throwable
   #30 = Utf8               org/scalatest/Timer
   #31 = Class              #30           // org/scalatest/Timer
   #32 = Utf8               <init>
   #33 = Utf8               ()V
   #34 = NameAndType        #32:#33       // "<init>":()V
   #35 = Methodref          #31.#34       // org/scalatest/Timer."<init>":()V
   #36 = Utf8               org/scalatest/time/Span
   #37 = Class              #36           // org/scalatest/time/Span
   #38 = Utf8               totalNanos
   #39 = Utf8               ()J
   #40 = NameAndType        #38:#39       // totalNanos:()J
   #41 = Methodref          #37.#40       // org/scalatest/time/Span.totalNanos:()J
   #42 = Long               1000l
   #44 = Utf8               scala/compat/Platform$
   #45 = Class              #44           // scala/compat/Platform$
   #46 = Utf8               MODULE$
   #47 = Utf8               Lscala/compat/Platform$;
   #48 = NameAndType        #46:#47       // MODULE$:Lscala/compat/Platform$;
   #49 = Fieldref           #45.#48       // scala/compat/Platform$.MODULE$:Lscala/compat/Platform$;
   #50 = Utf8               currentTime
   #51 = NameAndType        #50:#39       // currentTime:()J
   #52 = Methodref          #45.#51       // scala/compat/Platform$.currentTime:()J
   #53 = Utf8               scala/Function0
   #54 = Class              #53           // scala/Function0
   #55 = Utf8               apply
   #56 = Utf8               ()Ljava/lang/Object;
   #57 = NameAndType        #55:#56       // apply:()Ljava/lang/Object;
   #58 = InterfaceMethodref #54.#57       // scala/Function0.apply:()Ljava/lang/Object;
   #59 = Utf8               scala/concurrent/Future
   #60 = Class              #59           // scala/concurrent/Future
   #61 = Utf8               scala/None$
   #62 = Class              #61           // scala/None$
   #63 = Utf8               Lscala/None$;
   #64 = NameAndType        #46:#63       // MODULE$:Lscala/None$;
   #65 = Fieldref           #62.#64       // scala/None$.MODULE$:Lscala/None$;
   #66 = Utf8               scala/Function1
   #67 = Class              #66           // scala/Function1
   #68 = Utf8               (Ljava/lang/Object;)Ljava/lang/Object;
   #69 = NameAndType        #55:#68       // apply:(Ljava/lang/Object;)Ljava/lang/Object;
   #70 = InterfaceMethodref #67.#69       // scala/Function1.apply:(Ljava/lang/Object;)Ljava/lang/Object;
   #71 = Utf8               scala/concurrent/Promise$
   #72 = Class              #71           // scala/concurrent/Promise$
   #73 = Utf8               Lscala/concurrent/Promise$;
   #74 = NameAndType        #46:#73       // MODULE$:Lscala/concurrent/Promise$;
   #75 = Fieldref           #72.#74       // scala/concurrent/Promise$.MODULE$:Lscala/concurrent/Promise$;
   #76 = Utf8               ()Lscala/concurrent/Promise;
   #77 = NameAndType        #55:#76       // apply:()Lscala/concurrent/Promise;
   #78 = Methodref          #72.#77       // scala/concurrent/Promise$.apply:()Lscala/concurrent/Promise;
   #79 = Utf8               org/scalatest/concurrent/SignalerTimeoutTask
   #80 = Class              #79           // org/scalatest/concurrent/SignalerTimeoutTask
   #81 = Utf8               java/lang/Thread
   #82 = Class              #81           // java/lang/Thread
   #83 = Utf8               currentThread
   #84 = Utf8               ()Ljava/lang/Thread;
   #85 = NameAndType        #83:#84       // currentThread:()Ljava/lang/Thread;
   #86 = Methodref          #82.#85       // java/lang/Thread.currentThread:()Ljava/lang/Thread;
   #87 = Utf8               (Ljava/lang/Thread;Lorg/scalatest/concurrent/Signaler;)V
   #88 = NameAndType        #32:#87       // "<init>":(Ljava/lang/Thread;Lorg/scalatest/concurrent/Signaler;)V
   #89 = Methodref          #80.#88       // org/scalatest/concurrent/SignalerTimeoutTask."<init>":(Ljava/lang/Thread;Lorg/scalatest/concurrent/Signaler;)V
   #90 = Utf8               schedule
   #91 = Utf8               (Lorg/scalatest/TimerTask;J)V
   #92 = NameAndType        #90:#91       // schedule:(Lorg/scalatest/TimerTask;J)V
   #93 = Methodref          #31.#92       // org/scalatest/Timer.schedule:(Lorg/scalatest/TimerTask;J)V
   #94 = MethodType         #68           //  (Ljava/lang/Object;)Ljava/lang/Object;
   #95 = Utf8               $anonfun$timeoutAfter$1
   #96 = Utf8               (Lorg/scalatest/concurrent/SignalerTimeoutTask;Lorg/scalatest/Timer;Lscala/concurrent/Promise;JJLscala/Function1;Lscala/util/Try;)Ljava/lang/Object;
   #97 = NameAndType        #95:#96       // $anonfun$timeoutAfter$1:(Lorg/scalatest/concurrent/SignalerTimeoutTask;Lorg/scalatest/Timer;Lscala/concurrent/Promise;JJLscala/Function1;Lscala/util/Try;)Ljava/lang/Object;
   #98 = Methodref          #2.#97        // org/scalatest/enablers/Timed$$anon$2.$anonfun$timeoutAfter$1:(Lorg/scalatest/concurrent/SignalerTimeoutTask;Lorg/scalatest/Timer;Lscala/concurrent/Promise;JJLscala/Function1;Lscala/util/Try;)Ljava/lang/Object;
   #99 = MethodHandle       6:#98         // REF_invokeStatic org/scalatest/enablers/Timed$$anon$2.$anonfun$timeoutAfter$1:(Lorg/scalatest/concurrent/SignalerTimeoutTask;Lorg/scalatest/Timer;Lscala/concurrent/Promise;JJLscala/Function1;Lscala/util/Try;)Ljava/lang/Object;
  #100 = Utf8               (Lscala/util/Try;)Ljava/lang/Object;
  #101 = MethodType         #100          //  (Lscala/util/Try;)Ljava/lang/Object;
  #102 = Integer            5
  #103 = Integer            1
  #104 = Utf8               java/lang/invoke/LambdaMetafactory
  #105 = Class              #104          // java/lang/invoke/LambdaMetafactory
  #106 = Utf8               altMetafactory
  #107 = Utf8               (Ljava/lang/invoke/MethodHandles$Lookup;Ljava/lang/String;Ljava/lang/invoke/MethodType;[Ljava/lang/Object;)Ljava/lang/invoke/CallSite;
  #108 = NameAndType        #106:#107     // altMetafactory:(Ljava/lang/invoke/MethodHandles$Lookup;Ljava/lang/String;Ljava/lang/invoke/MethodType;[Ljava/lang/Object;)Ljava/lang/invoke/CallSite;
  #109 = Methodref          #105.#108     // java/lang/invoke/LambdaMetafactory.altMetafactory:(Ljava/lang/invoke/MethodHandles$Lookup;Ljava/lang/String;Ljava/lang/invoke/MethodType;[Ljava/lang/Object;)Ljava/lang/invoke/CallSite;
  #110 = MethodHandle       6:#109        // REF_invokeStatic java/lang/invoke/LambdaMetafactory.altMetafactory:(Ljava/lang/invoke/MethodHandles$Lookup;Ljava/lang/String;Ljava/lang/invoke/MethodType;[Ljava/lang/Object;)Ljava/lang/invoke/CallSite;
  #111 = Utf8               (Lorg/scalatest/concurrent/SignalerTimeoutTask;Lorg/scalatest/Timer;Lscala/concurrent/Promise;JJLscala/Function1;)Lscala/Function1;
  #112 = NameAndType        #55:#111      // apply:(Lorg/scalatest/concurrent/SignalerTimeoutTask;Lorg/scalatest/Timer;Lscala/concurrent/Promise;JJLscala/Function1;)Lscala/Function1;
  #113 = InvokeDynamic      #0:#112       // #0:apply:(Lorg/scalatest/concurrent/SignalerTimeoutTask;Lorg/scalatest/Timer;Lscala/concurrent/Promise;JJLscala/Function1;)Lscala/Function1;
  #114 = NameAndType        #19:#20       // executionContext$1:Lscala/concurrent/ExecutionContext;
  #115 = Fieldref           #2.#114       // org/scalatest/enablers/Timed$$anon$2.executionContext$1:Lscala/concurrent/ExecutionContext;
  #116 = Utf8               onComplete
  #117 = Utf8               (Lscala/Function1;Lscala/concurrent/ExecutionContext;)V
  #118 = NameAndType        #116:#117     // onComplete:(Lscala/Function1;Lscala/concurrent/ExecutionContext;)V
  #119 = InterfaceMethodref #60.#118      // scala/concurrent/Future.onComplete:(Lscala/Function1;Lscala/concurrent/ExecutionContext;)V
  #120 = Utf8               scala/concurrent/Promise
  #121 = Class              #120          // scala/concurrent/Promise
  #122 = Utf8               future
  #123 = Utf8               ()Lscala/concurrent/Future;
  #124 = NameAndType        #122:#123     // future:()Lscala/concurrent/Future;
  #125 = InterfaceMethodref #121.#124     // scala/concurrent/Promise.future:()Lscala/concurrent/Future;
  #126 = Utf8               scala/Some
  #127 = Class              #126          // scala/Some
  #128 = Utf8               (Ljava/lang/Object;)V
  #129 = NameAndType        #32:#128      // "<init>":(Ljava/lang/Object;)V
  #130 = Methodref          #127.#129     // scala/Some."<init>":(Ljava/lang/Object;)V
  #131 = Utf8               result
  #132 = Utf8               Lscala/concurrent/Future;
  #133 = Utf8               endTime
  #134 = Utf8               J
  #135 = Utf8               promise
  #136 = Utf8               Lscala/concurrent/Promise;
  #137 = Utf8               task
  #138 = Utf8               Lorg/scalatest/concurrent/SignalerTimeoutTask;
  #139 = Utf8               delay
  #140 = Utf8               timer
  #141 = Utf8               Lorg/scalatest/Timer;
  #142 = Utf8               t
  #143 = Utf8               Ljava/lang/Throwable;
  #144 = Utf8               maxDuration
  #145 = Utf8               startTime
  #146 = Utf8               this
  #147 = Utf8               Lorg/scalatest/enablers/Timed$$anon$2;
  #148 = Utf8               Lorg/scalatest/time/Span;
  #149 = Utf8               Lscala/Function0;
  #150 = Utf8               Lorg/scalatest/concurrent/Signaler;
  #151 = Utf8               Lscala/Function1;
  #152 = Utf8               org/scalatest/concurrent/Signaler
  #153 = Class              #152          // org/scalatest/concurrent/Signaler
  #154 = Utf8               (Lorg/scalatest/time/Span;Lscala/Function0;Lorg/scalatest/concurrent/Signaler;Lscala/Function1;)Ljava/lang/Object;
  #155 = NameAndType        #21:#22       // timeoutAfter:(Lorg/scalatest/time/Span;Lscala/Function0;Lorg/scalatest/concurrent/Signaler;Lscala/Function1;)Lscala/concurrent/Future;
  #156 = Methodref          #2.#155       // org/scalatest/enablers/Timed$$anon$2.timeoutAfter:(Lorg/scalatest/time/Span;Lscala/Function0;Lorg/scalatest/concurrent/Signaler;Lscala/Function1;)Lscala/concurrent/Future;
  #157 = Utf8               task$1
  #158 = Utf8               timer$1
  #159 = Utf8               promise$1
  #160 = Utf8               startTime$1
  #161 = Utf8               maxDuration$1
  #162 = Utf8               exceptionFun$1
  #163 = Utf8               scala/util/Success
  #164 = Class              #163          // scala/util/Success
  #165 = Utf8               value
  #166 = NameAndType        #165:#56      // value:()Ljava/lang/Object;
  #167 = Methodref          #164.#166     // scala/util/Success.value:()Ljava/lang/Object;
  #168 = Utf8               cancel
  #169 = NameAndType        #168:#33      // cancel:()V
  #170 = Methodref          #80.#169      // org/scalatest/concurrent/SignalerTimeoutTask.cancel:()V
  #171 = Methodref          #31.#169      // org/scalatest/Timer.cancel:()V
  #172 = Utf8               isCompleted
  #173 = Utf8               ()Z
  #174 = NameAndType        #172:#173     // isCompleted:()Z
  #175 = InterfaceMethodref #121.#174     // scala/concurrent/Promise.isCompleted:()Z
  #176 = Utf8               scala/util/Failure
  #177 = Class              #176          // scala/util/Failure
  #178 = Utf8               (Ljava/lang/Throwable;)V
  #179 = NameAndType        #32:#178      // "<init>":(Ljava/lang/Throwable;)V
  #180 = Methodref          #177.#179     // scala/util/Failure."<init>":(Ljava/lang/Throwable;)V
  #181 = Utf8               complete
  #182 = Utf8               (Lscala/util/Try;)Lscala/concurrent/Promise;
  #183 = NameAndType        #181:#182     // complete:(Lscala/util/Try;)Lscala/concurrent/Promise;
  #184 = InterfaceMethodref #121.#183     // scala/concurrent/Promise.complete:(Lscala/util/Try;)Lscala/concurrent/Promise;
  #185 = Utf8               success
  #186 = Utf8               (Ljava/lang/Object;)Lscala/concurrent/Promise;
  #187 = NameAndType        #185:#186     // success:(Ljava/lang/Object;)Lscala/concurrent/Promise;
  #188 = InterfaceMethodref #121.#187     // scala/concurrent/Promise.success:(Ljava/lang/Object;)Lscala/concurrent/Promise;
  #189 = Utf8               scala/runtime/BoxedUnit
  #190 = Class              #189          // scala/runtime/BoxedUnit
  #191 = Utf8               UNIT
  #192 = Utf8               Lscala/runtime/BoxedUnit;
  #193 = NameAndType        #191:#192     // UNIT:Lscala/runtime/BoxedUnit;
  #194 = Fieldref           #190.#193     // scala/runtime/BoxedUnit.UNIT:Lscala/runtime/BoxedUnit;
  #195 = Utf8               exception
  #196 = Utf8               ()Ljava/lang/Throwable;
  #197 = NameAndType        #195:#196     // exception:()Ljava/lang/Throwable;
  #198 = Methodref          #177.#197     // scala/util/Failure.exception:()Ljava/lang/Throwable;
  #199 = Utf8               failure
  #200 = Utf8               (Ljava/lang/Throwable;)Lscala/concurrent/Promise;
  #201 = NameAndType        #199:#200     // failure:(Ljava/lang/Throwable;)Lscala/concurrent/Promise;
  #202 = InterfaceMethodref #121.#201     // scala/concurrent/Promise.failure:(Ljava/lang/Throwable;)Lscala/concurrent/Promise;
  #203 = Utf8               scala/MatchError
  #204 = Class              #203          // scala/MatchError
  #205 = Methodref          #204.#129     // scala/MatchError."<init>":(Ljava/lang/Object;)V
  #206 = Utf8               duration
  #207 = Utf8               r
  #208 = Utf8               Ljava/lang/Object;
  #209 = Utf8               e
  #210 = Utf8               Lscala/util/Try;
  #211 = Utf8               scala/util/Try
  #212 = Class              #211          // scala/util/Try
  #213 = Utf8               (Lscala/concurrent/ExecutionContext;)V
  #214 = Methodref          #5.#34        // java/lang/Object."<init>":()V
  #215 = Utf8               $deserializeLambda$
  #216 = Utf8               (Ljava/lang/invoke/SerializedLambda;)Ljava/lang/Object;
  #217 = Utf8               scala/runtime/LambdaDeserialize
  #218 = Class              #217          // scala/runtime/LambdaDeserialize
  #219 = Utf8               bootstrap
  #220 = Utf8               (Ljava/lang/invoke/MethodHandles$Lookup;Ljava/lang/String;Ljava/lang/invoke/MethodType;[Ljava/lang/invoke/MethodHandle;)Ljava/lang/invoke/CallSite;
  #221 = NameAndType        #219:#220     // bootstrap:(Ljava/lang/invoke/MethodHandles$Lookup;Ljava/lang/String;Ljava/lang/invoke/MethodType;[Ljava/lang/invoke/MethodHandle;)Ljava/lang/invoke/CallSite;
  #222 = Methodref          #218.#221     // scala/runtime/LambdaDeserialize.bootstrap:(Ljava/lang/invoke/MethodHandles$Lookup;Ljava/lang/String;Ljava/lang/invoke/MethodType;[Ljava/lang/invoke/MethodHandle;)Ljava/lang/invoke/CallSite;
  #223 = MethodHandle       6:#222        // REF_invokeStatic scala/runtime/LambdaDeserialize.bootstrap:(Ljava/lang/invoke/MethodHandles$Lookup;Ljava/lang/String;Ljava/lang/invoke/MethodType;[Ljava/lang/invoke/MethodHandle;)Ljava/lang/invoke/CallSite;
  #224 = Utf8               lambdaDeserialize
  #225 = NameAndType        #224:#216     // lambdaDeserialize:(Ljava/lang/invoke/SerializedLambda;)Ljava/lang/Object;
  #226 = InvokeDynamic      #1:#225       // #1:lambdaDeserialize:(Ljava/lang/invoke/SerializedLambda;)Ljava/lang/Object;
  #227 = Utf8               Code
  #228 = Utf8               StackMapTable
  #229 = Utf8               LineNumberTable
  #230 = Utf8               LocalVariableTable
  #231 = Utf8               Signature
  #232 = Utf8               MethodParameters
  #233 = Utf8               InnerClasses
  #234 = Utf8               EnclosingMethod
  #235 = Utf8               SourceFile
  #236 = Utf8               BootstrapMethods
  #237 = Utf8               ScalaInlineInfo
  #238 = Utf8               Scala
{
  private final scala.concurrent.ExecutionContext executionContext$1;
    descriptor: Lscala/concurrent/ExecutionContext;
    flags: (0x0012) ACC_PRIVATE, ACC_FINAL

  public scala.concurrent.Future<T> timeoutAfter(org.scalatest.time.Span, scala.Function0<scala.concurrent.Future<T>>, org.scalatest.concurrent.Signaler, scala.Function1<scala.Option<java.lang.Throwable>, org.scalatest.exceptions.StackDepthException>);
    descriptor: (Lorg/scalatest/time/Span;Lscala/Function0;Lorg/scalatest/concurrent/Signaler;Lscala/Function1;)Lscala/concurrent/Future;
    flags: (0x0001) ACC_PUBLIC
    Code:
      stack=9, locals=21, args_size=5
         0: new           #31                 // class org/scalatest/Timer
         3: dup
         4: invokespecial #35                 // Method org/scalatest/Timer."<init>":()V
         7: astore        5
         9: aload_1
        10: invokevirtual #41                 // Method org/scalatest/time/Span.totalNanos:()J
        13: ldc2_w        #42                 // long 1000l
        16: ldiv
        17: ldc2_w        #42                 // long 1000l
        20: ldiv
        21: lstore        6
        23: getstatic     #49                 // Field scala/compat/Platform$.MODULE$:Lscala/compat/Platform$;
        26: invokevirtual #52                 // Method scala/compat/Platform$.currentTime:()J
        29: lstore        8
        31: aload_2
        32: invokeinterface #58,  1           // InterfaceMethod scala/Function0.apply:()Ljava/lang/Object;
        37: checkcast     #60                 // class scala/concurrent/Future
        40: astore        10
        42: getstatic     #49                 // Field scala/compat/Platform$.MODULE$:Lscala/compat/Platform$;
        45: invokevirtual #52                 // Method scala/compat/Platform$.currentTime:()J
        48: lstore        11
        50: lload         11
        52: lload         8
        54: lsub
        55: lload         6
        57: lcmp
        58: ifle          75
        61: aload         4
        63: getstatic     #65                 // Field scala/None$.MODULE$:Lscala/None$;
        66: invokeinterface #70,  2           // InterfaceMethod scala/Function1.apply:(Ljava/lang/Object;)Ljava/lang/Object;
        71: checkcast     #29                 // class java/lang/Throwable
        74: athrow
        75: getstatic     #75                 // Field scala/concurrent/Promise$.MODULE$:Lscala/concurrent/Promise$;
        78: invokevirtual #78                 // Method scala/concurrent/Promise$.apply:()Lscala/concurrent/Promise;
        81: astore        13
        83: new           #80                 // class org/scalatest/concurrent/SignalerTimeoutTask
        86: dup
        87: invokestatic  #86                 // Method java/lang/Thread.currentThread:()Ljava/lang/Thread;
        90: aload_3
        91: invokespecial #89                 // Method org/scalatest/concurrent/SignalerTimeoutTask."<init>":(Ljava/lang/Thread;Lorg/scalatest/concurrent/Signaler;)V
        94: astore        14
        96: lload         6
        98: getstatic     #49                 // Field scala/compat/Platform$.MODULE$:Lscala/compat/Platform$;
       101: invokevirtual #52                 // Method scala/compat/Platform$.currentTime:()J
       104: lload         8
       106: lsub
       107: lsub
       108: lstore        15
       110: new           #31                 // class org/scalatest/Timer
       113: dup
       114: invokespecial #35                 // Method org/scalatest/Timer."<init>":()V
       117: astore        17
       119: aload         17
       121: aload         14
       123: lload         15
       125: invokevirtual #93                 // Method org/scalatest/Timer.schedule:(Lorg/scalatest/TimerTask;J)V
       128: aload         10
       130: aload         14
       132: aload         17
       134: aload         13
       136: lload         8
       138: lload         6
       140: aload         4
       142: invokedynamic #113,  0            // InvokeDynamic #0:apply:(Lorg/scalatest/concurrent/SignalerTimeoutTask;Lorg/scalatest/Timer;Lscala/concurrent/Promise;JJLscala/Function1;)Lscala/Function1;
       147: aload_0
       148: getfield      #115                // Field executionContext$1:Lscala/concurrent/ExecutionContext;
       151: invokeinterface #119,  3          // InterfaceMethod scala/concurrent/Future.onComplete:(Lscala/Function1;Lscala/concurrent/ExecutionContext;)V
       156: aload         13
       158: invokeinterface #125,  1          // InterfaceMethod scala/concurrent/Promise.future:()Lscala/concurrent/Future;
       163: goto          210
       166: astore        18
       168: getstatic     #49                 // Field scala/compat/Platform$.MODULE$:Lscala/compat/Platform$;
       171: invokevirtual #52                 // Method scala/compat/Platform$.currentTime:()J
       174: lstore        19
       176: lload         19
       178: lload         8
       180: lsub
       181: lload         6
       183: lcmp
       184: ifle          207
       187: aload         4
       189: new           #127                // class scala/Some
       192: dup
       193: aload         18
       195: invokespecial #130                // Method scala/Some."<init>":(Ljava/lang/Object;)V
       198: invokeinterface #70,  2           // InterfaceMethod scala/Function1.apply:(Ljava/lang/Object;)Ljava/lang/Object;
       203: checkcast     #29                 // class java/lang/Throwable
       206: athrow
       207: aload         18
       209: athrow
       210: areturn
      Exception table:
         from    to  target type
            31   163   166   Class java/lang/Throwable
      StackMapTable: number_of_entries = 4
        frame_type = 255 /* full_frame */
          offset_delta = 75
          locals = [ class org/scalatest/enablers/Timed$$anon$2, class org/scalatest/time/Span, class scala/Function0, class org/scalatest/concurrent/Signaler, class scala/Function1, class org/scalatest/Timer, long, long, class scala/concurrent/Future, long ]
          stack = []
        frame_type = 255 /* full_frame */
          offset_delta = 90
          locals = [ class org/scalatest/enablers/Timed$$anon$2, class org/scalatest/time/Span, class scala/Function0, class org/scalatest/concurrent/Signaler, class scala/Function1, class org/scalatest/Timer, long, long ]
          stack = [ class java/lang/Throwable ]
        frame_type = 255 /* full_frame */
          offset_delta = 40
          locals = [ class org/scalatest/enablers/Timed$$anon$2, class org/scalatest/time/Span, class scala/Function0, class org/scalatest/concurrent/Signaler, class scala/Function1, class org/scalatest/Timer, long, long, top, top, top, top, top, top, top, top, class java/lang/Throwable, long ]
          stack = []
        frame_type = 255 /* full_frame */
          offset_delta = 2
          locals = [ class org/scalatest/enablers/Timed$$anon$2, class org/scalatest/time/Span, class scala/Function0, class org/scalatest/concurrent/Signaler, class scala/Function1, class org/scalatest/Timer, long, long, class scala/concurrent/Future, long, class scala/concurrent/Promise, class org/scalatest/concurrent/SignalerTimeoutTask, long, class org/scalatest/Timer ]
          stack = [ class scala/concurrent/Future ]
      LineNumberTable:
        line 191: 0
        line 192: 9
        line 193: 23
        line 195: 31
        line 196: 42
        line 198: 50
        line 199: 61
        line 202: 75
        line 203: 83
        line 204: 96
        line 205: 110
        line 209: 119
        line 210: 128
        line 238: 156
        line 242: 168
        line 243: 176
        line 244: 187
        line 247: 207
      LocalVariableTable:
        Start  Length  Slot  Name   Signature
           42     121    10 result   Lscala/concurrent/Future;
           50     113    11 endTime   J
           83      80    13 promise   Lscala/concurrent/Promise;
           96      67    14  task   Lorg/scalatest/concurrent/SignalerTimeoutTask;
          110      53    15 delay   J
          119      44    17 timer   Lorg/scalatest/Timer;
          176      34    19 endTime   J
          166      44    18     t   Ljava/lang/Throwable;
            9     201     5 timer   Lorg/scalatest/Timer;
           23     187     6 maxDuration   J
           31     179     8 startTime   J
            0     211     0  this   Lorg/scalatest/enablers/Timed$$anon$2;
            0     211     1 timeout   Lorg/scalatest/time/Span;
            0     211     2     f   Lscala/Function0;
            0     211     3 signaler   Lorg/scalatest/concurrent/Signaler;
            0     211     4 exceptionFun   Lscala/Function1;
    Signature: #23                          // (Lorg/scalatest/time/Span;Lscala/Function0<Lscala/concurrent/Future<TT;>;>;Lorg/scalatest/concurrent/Signaler;Lscala/Function1<Lscala/Option<Ljava/lang/Throwable;>;Lorg/scalatest/exceptions/StackDepthException;>;)Lscala/concurrent/Future<TT;>;
    MethodParameters:
      Name                           Flags
      timeout                        final
      f                              final
      signaler                       final
      exceptionFun                   final

  public java.lang.Object timeoutAfter(org.scalatest.time.Span, scala.Function0, org.scalatest.concurrent.Signaler, scala.Function1);
    descriptor: (Lorg/scalatest/time/Span;Lscala/Function0;Lorg/scalatest/concurrent/Signaler;Lscala/Function1;)Ljava/lang/Object;
    flags: (0x1041) ACC_PUBLIC, ACC_BRIDGE, ACC_SYNTHETIC
    Code:
      stack=5, locals=5, args_size=5
         0: aload_0
         1: aload_1
         2: aload_2
         3: aload_3
         4: aload         4
         6: invokevirtual #156                // Method timeoutAfter:(Lorg/scalatest/time/Span;Lscala/Function0;Lorg/scalatest/concurrent/Signaler;Lscala/Function1;)Lscala/concurrent/Future;
         9: areturn
      LineNumberTable:
        line 184: 0
      LocalVariableTable:
        Start  Length  Slot  Name   Signature
            0      10     0  this   Lorg/scalatest/enablers/Timed$$anon$2;
            0      10     1 timeout   Lorg/scalatest/time/Span;
            0      10     2     f   Lscala/Function0;
            0      10     3 signaler   Lorg/scalatest/concurrent/Signaler;
            0      10     4 exceptionFun   Lscala/Function1;
    MethodParameters:
      Name                           Flags
      timeout                        final
      f                              final
      signaler                       final
      exceptionFun                   final

  public static final java.lang.Object $anonfun$timeoutAfter$1(org.scalatest.concurrent.SignalerTimeoutTask, org.scalatest.Timer, scala.concurrent.Promise, long, long, scala.Function1, scala.util.Try);
    descriptor: (Lorg/scalatest/concurrent/SignalerTimeoutTask;Lorg/scalatest/Timer;Lscala/concurrent/Promise;JJLscala/Function1;Lscala/util/Try;)Ljava/lang/Object;
    flags: (0x1019) ACC_PUBLIC, ACC_STATIC, ACC_FINAL, ACC_SYNTHETIC
    Code:
      stack=7, locals=23, args_size=7
         0: aload         8
         2: astore        10
         4: aload         10
         6: instanceof    #164                // class scala/util/Success
         9: ifeq          113
        12: aload         10
        14: checkcast     #164                // class scala/util/Success
        17: astore        11
        19: aload         11
        21: invokevirtual #167                // Method scala/util/Success.value:()Ljava/lang/Object;
        24: astore        12
        26: aload_0
        27: invokevirtual #170                // Method org/scalatest/concurrent/SignalerTimeoutTask.cancel:()V
        30: aload_1
        31: invokevirtual #171                // Method org/scalatest/Timer.cancel:()V
        34: aload_2
        35: invokeinterface #175,  1          // InterfaceMethod scala/concurrent/Promise.isCompleted:()Z
        40: ifne          105
        43: getstatic     #49                 // Field scala/compat/Platform$.MODULE$:Lscala/compat/Platform$;
        46: invokevirtual #52                 // Method scala/compat/Platform$.currentTime:()J
        49: lstore        13
        51: lload         13
        53: lload_3
        54: lsub
        55: lstore        15
        57: lload         15
        59: lload         5
        61: lcmp
        62: ifle          94
        65: aload_2
        66: new           #177                // class scala/util/Failure
        69: dup
        70: aload         7
        72: getstatic     #65                 // Field scala/None$.MODULE$:Lscala/None$;
        75: invokeinterface #70,  2           // InterfaceMethod scala/Function1.apply:(Ljava/lang/Object;)Ljava/lang/Object;
        80: checkcast     #29                 // class java/lang/Throwable
        83: invokespecial #180                // Method scala/util/Failure."<init>":(Ljava/lang/Throwable;)V
        86: invokeinterface #184,  2          // InterfaceMethod scala/concurrent/Promise.complete:(Lscala/util/Try;)Lscala/concurrent/Promise;
        91: goto          102
        94: aload_2
        95: aload         12
        97: invokeinterface #188,  2          // InterfaceMethod scala/concurrent/Promise.success:(Ljava/lang/Object;)Lscala/concurrent/Promise;
       102: goto          108
       105: getstatic     #194                // Field scala/runtime/BoxedUnit.UNIT:Lscala/runtime/BoxedUnit;
       108: astore        9
       110: goto          244
       113: goto          116
       116: aload         10
       118: instanceof    #177                // class scala/util/Failure
       121: ifeq          231
       124: aload         10
       126: checkcast     #177                // class scala/util/Failure
       129: astore        17
       131: aload         17
       133: invokevirtual #198                // Method scala/util/Failure.exception:()Ljava/lang/Throwable;
       136: astore        18
       138: aload_0
       139: invokevirtual #170                // Method org/scalatest/concurrent/SignalerTimeoutTask.cancel:()V
       142: aload_1
       143: invokevirtual #171                // Method org/scalatest/Timer.cancel:()V
       146: aload_2
       147: invokeinterface #175,  1          // InterfaceMethod scala/concurrent/Promise.isCompleted:()Z
       152: ifne          223
       155: getstatic     #49                 // Field scala/compat/Platform$.MODULE$:Lscala/compat/Platform$;
       158: invokevirtual #52                 // Method scala/compat/Platform$.currentTime:()J
       161: lstore        19
       163: lload         19
       165: lload_3
       166: lsub
       167: lstore        21
       169: lload         21
       171: lload         5
       173: lcmp
       174: ifle          212
       177: aload_2
       178: new           #177                // class scala/util/Failure
       181: dup
       182: aload         7
       184: new           #127                // class scala/Some
       187: dup
       188: aload         18
       190: invokespecial #130                // Method scala/Some."<init>":(Ljava/lang/Object;)V
       193: invokeinterface #70,  2           // InterfaceMethod scala/Function1.apply:(Ljava/lang/Object;)Ljava/lang/Object;
       198: checkcast     #29                 // class java/lang/Throwable
       201: invokespecial #180                // Method scala/util/Failure."<init>":(Ljava/lang/Throwable;)V
       204: invokeinterface #184,  2          // InterfaceMethod scala/concurrent/Promise.complete:(Lscala/util/Try;)Lscala/concurrent/Promise;
       209: goto          220
       212: aload_2
       213: aload         18
       215: invokeinterface #202,  2          // InterfaceMethod scala/concurrent/Promise.failure:(Ljava/lang/Throwable;)Lscala/concurrent/Promise;
       220: goto          226
       223: getstatic     #194                // Field scala/runtime/BoxedUnit.UNIT:Lscala/runtime/BoxedUnit;
       226: astore        9
       228: goto          244
       231: goto          234
       234: new           #204                // class scala/MatchError
       237: dup
       238: aload         10
       240: invokespecial #205                // Method scala/MatchError."<init>":(Ljava/lang/Object;)V
       243: athrow
       244: aload         9
       246: areturn
      StackMapTable: number_of_entries = 13
        frame_type = 255 /* full_frame */
          offset_delta = 94
          locals = [ class org/scalatest/concurrent/SignalerTimeoutTask, class org/scalatest/Timer, class scala/concurrent/Promise, long, long, class scala/Function1, class scala/util/Try, top, class scala/util/Try, class scala/util/Success, class java/lang/Object, long, long ]
          stack = []
        frame_type = 71 /* same_locals_1_stack_item */
          stack = [ class scala/concurrent/Promise ]
        frame_type = 249 /* chop */
          offset_delta = 2
        frame_type = 66 /* same_locals_1_stack_item */
          stack = [ class java/lang/Object ]
        frame_type = 249 /* chop */
          offset_delta = 4
        frame_type = 2 /* same */
        frame_type = 255 /* full_frame */
          offset_delta = 95
          locals = [ class org/scalatest/concurrent/SignalerTimeoutTask, class org/scalatest/Timer, class scala/concurrent/Promise, long, long, class scala/Function1, class scala/util/Try, top, class scala/util/Try, top, top, top, top, top, top, class scala/util/Failure, class java/lang/Throwable, long, long ]
          stack = []
        frame_type = 71 /* same_locals_1_stack_item */
          stack = [ class scala/concurrent/Promise ]
        frame_type = 249 /* chop */
          offset_delta = 2
        frame_type = 66 /* same_locals_1_stack_item */
          stack = [ class java/lang/Object ]
        frame_type = 255 /* full_frame */
          offset_delta = 4
          locals = [ class org/scalatest/concurrent/SignalerTimeoutTask, class org/scalatest/Timer, class scala/concurrent/Promise, long, long, class scala/Function1, class scala/util/Try, top, class scala/util/Try ]
          stack = []
        frame_type = 2 /* same */
        frame_type = 255 /* full_frame */
          offset_delta = 9
          locals = [ class org/scalatest/concurrent/SignalerTimeoutTask, class org/scalatest/Timer, class scala/concurrent/Promise, long, long, class scala/Function1, class scala/util/Try, class java/lang/Object, class scala/util/Try ]
          stack = []
      LineNumberTable:
        line 211: 0
        line 212: 4
        line 213: 26
        line 214: 30
        line 215: 34
        line 216: 43
        line 217: 51
        line 218: 57
        line 219: 65
        line 221: 94
        line 215: 105
        line 212: 113
        line 224: 116
        line 225: 138
        line 226: 142
        line 227: 146
        line 228: 155
        line 229: 163
        line 230: 169
        line 231: 177
        line 233: 212
        line 227: 223
        line 224: 231
        line 211: 234
      LocalVariableTable:
        Start  Length  Slot  Name   Signature
           51      51    13 endTime   J
           57      45    15 duration   J
           26      87    12     r   Ljava/lang/Object;
          163      57    19 endTime   J
          169      51    21 duration   J
          138      93    18     e   Ljava/lang/Throwable;
            0     247     0 task$1   Lorg/scalatest/concurrent/SignalerTimeoutTask;
            0     247     1 timer$1   Lorg/scalatest/Timer;
            0     247     2 promise$1   Lscala/concurrent/Promise;
            0     247     3 startTime$1   J
            0     247     5 maxDuration$1   J
            0     247     7 exceptionFun$1   Lscala/Function1;
            0     247     8     t   Lscala/util/Try;
    MethodParameters:
      Name                           Flags
      task$1                         final
      timer$1                        final
      promise$1                      final
      startTime$1                    final
      maxDuration$1                  final
      exceptionFun$1                 final
      t                              final

  public org.scalatest.enablers.Timed$$anon$2(scala.concurrent.ExecutionContext);
    descriptor: (Lscala/concurrent/ExecutionContext;)V
    flags: (0x0001) ACC_PUBLIC
    Code:
      stack=2, locals=2, args_size=2
         0: aload_0
         1: aload_1
         2: putfield      #115                // Field executionContext$1:Lscala/concurrent/ExecutionContext;
         5: aload_0
         6: invokespecial #214                // Method java/lang/Object."<init>":()V
         9: return
      LineNumberTable:
        line 183: 0
        line 184: 5
      LocalVariableTable:
        Start  Length  Slot  Name   Signature
            0      10     0  this   Lorg/scalatest/enablers/Timed$$anon$2;
            0      10     1 executionContext$1   Lscala/concurrent/ExecutionContext;
    MethodParameters:
      Name                           Flags
      executionContext$1             final

  private static java.lang.Object $deserializeLambda$(java.lang.invoke.SerializedLambda);
    descriptor: (Ljava/lang/invoke/SerializedLambda;)Ljava/lang/Object;
    flags: (0x100a) ACC_PRIVATE, ACC_STATIC, ACC_SYNTHETIC
    Code:
      stack=1, locals=1, args_size=1
         0: aload_0
         1: invokedynamic #226,  0            // InvokeDynamic #1:lambdaDeserialize:(Ljava/lang/invoke/SerializedLambda;)Ljava/lang/Object;
         6: areturn
}
InnerClasses:
  public static final #18= #15 of #17;    // Lookup=class java/lang/invoke/MethodHandles$Lookup of class java/lang/invoke/MethodHandles
  public final #2;                        // class org/scalatest/enablers/Timed$$anon$2
EnclosingMethod: #10.#13                // org.scalatest.enablers.Timed$.timedFutureOf
Signature: #3                           // Ljava/lang/Object;Lorg/scalatest/enablers/Timed<Lscala/concurrent/Future<TT;>;>;
SourceFile: "Timed.scala"
BootstrapMethods:
  0: #110 REF_invokeStatic java/lang/invoke/LambdaMetafactory.altMetafactory:(Ljava/lang/invoke/MethodHandles$Lookup;Ljava/lang/String;Ljava/lang/invoke/MethodType;[Ljava/lang/Object;)Ljava/lang/invoke/CallSite;
    Method arguments:
      #94 (Ljava/lang/Object;)Ljava/lang/Object;
      #99 REF_invokeStatic org/scalatest/enablers/Timed$$anon$2.$anonfun$timeoutAfter$1:(Lorg/scalatest/concurrent/SignalerTimeoutTask;Lorg/scalatest/Timer;Lscala/concurrent/Promise;JJLscala/Function1;Lscala/util/Try;)Ljava/lang/Object;
      #101 (Lscala/util/Try;)Ljava/lang/Object;
      #102 5
      #103 1
      #101 (Lscala/util/Try;)Ljava/lang/Object;
  1: #223 REF_invokeStatic scala/runtime/LambdaDeserialize.bootstrap:(Ljava/lang/invoke/MethodHandles$Lookup;Ljava/lang/String;Ljava/lang/invoke/MethodType;[Ljava/lang/invoke/MethodHandle;)Ljava/lang/invoke/CallSite;
    Method arguments:
      #99 REF_invokeStatic org/scalatest/enablers/Timed$$anon$2.$anonfun$timeoutAfter$1:(Lorg/scalatest/concurrent/SignalerTimeoutTask;Lorg/scalatest/Timer;Lscala/concurrent/Promise;JJLscala/Function1;Lscala/util/Try;)Ljava/lang/Object;
  ScalaInlineInfo: length = 0x18 (unknown attribute)
   01 01 00 04 00 5F 00 60 01 00 20 00 D5 01 00 15
   00 9A 01 00 15 00 16 01
  Scala: length = 0x0 (unknown attribute)

