Classfile /Users/mw/Projects/slang-braindump/.jar/jar11/assemble/slang-braindump/assemble/content/org/scalatest/enablers/UnitInspectorAsserting.class
  Last modified May 29, 2022; size 3106 bytes
  SHA-256 checksum 2518edef42f1bfb9cd139828f81610d16c6fd80fe929d9f3e01dcb2061f8d83b
  Compiled from "InspectorAsserting.scala"
public abstract class org.scalatest.enablers.UnitInspectorAsserting
  minor version: 0
  major version: 52
  flags: (0x0421) ACC_PUBLIC, ACC_SUPER, ACC_ABSTRACT
  this_class: #2                          // org/scalatest/enablers/UnitInspectorAsserting
  super_class: #4                         // java/lang/Object
  interfaces: 0, fields: 0, methods: 2, attributes: 5
Constant pool:
   #1 = Utf8               org/scalatest/enablers/UnitInspectorAsserting
   #2 = Class              #1             // org/scalatest/enablers/UnitInspectorAsserting
   #3 = Utf8               java/lang/Object
   #4 = Class              #3             // java/lang/Object
   #5 = Utf8               InspectorAsserting.scala
   #6 = Utf8               Lscala/reflect/ScalaSignature;
   #7 = Utf8               bytes
   #8 = Utf8               \u0006\u0005\t=a!B\b\u0011\u0003\u00039\u0002\"\u0002\u0010\u0001\t\u0003yb!\u0002\u0012\u0001\u0003\u0003\u0019\u0003\"\u0002\u0010\u0003\t\u0003\u0019\u0004\"\u0002\u001c\u0003\t\u00039\u0004\"B8\u0003\t\u0003\u0001\bbBA\u0003\u0005\u0011\u0005\u0011q\u0001\u0005\b\u0003K\u0011A\u0011AA\u0014\u0011\u001d\t)E\u0001C\u0001\u0003\u000fBq!!\u0019\u0003\t\u0003\t\u0019\u0007C\u0004\u0002\u0006\n!\t!a\"\t\u0011\u0005\u0005&A\"\u0001\u0013\u0003GC\u0001\"a0\u0003\r\u0003\u0011\u0012\u0011\u0019\u0005\t\u0003\u007f\u0013a\u0011\u0001\n\u0002^\"9\u0011Q\u001f\u0001\u0005\u0004\u0005](AF+oSRLen\u001d9fGR|\'/Q:tKJ$\u0018N\\4\u000b\u0005E\u0011\u0012\u0001C3oC\ndWM]:\u000b\u0005M!\u0012!C:dC2\fG/Z:u\u0015\u0005)\u0012aA8sO\u000e\u00011C\u0001\u0001\u0019!\tIB$D\u0001\u001b\u0015\u0005Y\u0012!B:dC2\f\u0017BA\u000f\u001b\u0005\u0019\te.\u001f*fM\u00061A(\u001b8jiz\"\u0012\u0001\t\t\u0003C\u0001i\u0011\u0001\u0005\u0002\u0017\u0013:\u001c\b/Z2u_J\f5o]3si&tw-S7qYV\u0011AEK\n\u0004\u0005a)\u0003cA\u0011\'Q%\u0011q\u0005\u0005\u0002\u0013\u0013:\u001c\b/Z2u_J\f5o]3si&tw\r\u0005\u0002*U1\u0001A!B\u0016\u0003\u0005\u0004a#!\u0001+\u0012\u00055\u0002\u0004CA\r/\u0013\ty#DA\u0004O_RD\u0017N\\4\u0011\u0005e\t\u0014B\u0001\u001a\u001b\u0005\r\te.\u001f\u000b\u0002iA\u0019QG\u0001\u0015\u000e\u0003\u0001\taAZ8s\u00032dWC\u0001\u001dE)\u0019Id\t\u0017.`OR\u0011!H\u0010\t\u0003wqj\u0011AA\u0005\u0003{\u0019\u0012aAU3tk2$\b\"B \u0005\u0001\u0004\u0001\u0015a\u00014v]B!\u0011$Q\")\u0013\t\u0011%DA\u0005Gk:\u001cG/[8ocA\u0011\u0011\u0006\u0012\u0003\u0006\u000b\u0012\u0011\r\u0001\f\u0002\u0002\u000b\")q\t\u0002a\u0001\u0011\u0006\u0011\u0001p\u001d\t\u0004\u0013V\u001beB\u0001&S\u001d\tY\u0005K\u0004\u0002M\u001f6\tQJ\u0003\u0002O-\u00051AH]8pizJ\u0011aG\u0005\u0003#j\t!bY8mY\u0016\u001cG/[8o\u0013\t\u0019F+A\u0004qC\u000e\\\u0017mZ3\u000b\u0005ES\u0012B\u0001,X\u000599UM\u001c+sCZ,\'o]1cY\u0016T!a\u0015+\t\u000be#\u0001\u0019\u0001\u0019\u0002\u0011=\u0014\u0018nZ5oC2DQa\u0017\u0003A\u0002q\u000b\u0011b\u001d5peRD\u0017M\u001c3\u0011\u0005ei\u0016B\u00010\u001b\u0005\u001d\u0011un\u001c7fC:DQ\u0001\u0019\u0003A\u0002\u0005\f!\u0002\u001d:fiRLg-[3s!\t\u0011W-D\u0001d\u0015\t!G#A\u0005tG\u0006d\u0017m\u0019;jG&\u0011am\u0019\u0002\u000b!J,G\u000f^5gS\u0016\u0014\b\"\u00025\u0005\u0001\u0004I\u0017a\u00019pgB\u0011!.\\\u0007\u0002W*\u0011AnY\u0001\u0007g>,(oY3\n\u00059\\\'\u0001\u0003)pg&$\u0018n\u001c8\u0002\u0015\u0019|\'/\u0011;MK\u0006\u001cH/\u0006\u0002rmRI!o\u001e?\u007f\u007f\u0006\u0005\u00111\u0001\u000b\u0003uMDQaP\u0003A\u0002Q\u0004B!G!vQA\u0011\u0011F\u001e\u0003\u0006\u000b\u0016\u0011\r\u0001\f\u0005\u0006q\u0016\u0001\r!_\u0001\u0004[&t\u0007CA\r{\u0013\tY(DA\u0002J]RDQaR\u0003A\u0002u\u00042!S+v\u0011\u0015IV\u00011\u00011\u0011\u0015YV\u00011\u0001]\u0011\u0015\u0001W\u00011\u0001b\u0011\u0015AW\u00011\u0001j\u0003%1wN]!u\u001b>\u001cH/\u0006\u0003\u0002\n\u0005MACDA\u0006\u0003+\tI\"!\b\u0002 \u0005\u0005\u00121\u0005\u000b\u0004u\u00055\u0001BB \u0007\u0001\u0004\ty\u0001E\u0003\u001a\u0003\u0006E\u0001\u0006E\u0002*\u0003\'!Q!\u0012\u0004C\u00021Ba!a\u0006\u0007\u0001\u0004I\u0018aA7bq\"1qI\u0002a\u0001\u00037\u0001B!S+\u0002\u0012!)\u0011L\u0002a\u0001a!)1L\u0002a\u00019\")\u0001M\u0002a\u0001C\")\u0001N\u0002a\u0001S\u0006Qam\u001c:Fq\u0006\u001cG\u000f\\=\u0016\t\u0005%\u00121\u0007\u000b\u000f\u0003W\t)$!\u000f\u0002>\u0005}\u0012\u0011IA\")\rQ\u0014Q\u0006\u0005\u0007\u007f\u001d\u0001\r!a\f\u0011\u000be\t\u0015\u0011\u0007\u0015\u0011\u0007%\n\u0019\u0004B\u0003F\u000f\t\u0007A\u0006\u0003\u0004\u00028\u001d\u0001\r!_\u0001\u000fgV\u001c7-Z3eK\u0012\u001cu.\u001e8u\u0011\u00199u\u00011\u0001\u0002<A!\u0011*VA\u0019\u0011\u0015Iv\u00011\u00011\u0011\u0015Yv\u00011\u0001]\u0011\u0015\u0001w\u00011\u0001b\u0011\u0015Aw\u00011\u0001j\u0003\u00151wN\u001d(p+\u0011\tI%a\u0015\u0015\u0019\u0005-\u0013QKA-\u00037\ni&a\u0018\u0015\u0007i\ni\u0005\u0003\u0004@\u0011\u0001\u0007\u0011q\n\t\u00063\u0005\u000b\t\u0006\u000b\t\u0004S\u0005MC!B#\t\u0005\u0004a\u0003BB$\t\u0001\u0004\t9\u0006\u0005\u0003J+\u0006E\u0003\"B-\t\u0001\u0004\u0001\u0004\"B.\t\u0001\u0004a\u0006\"\u00021\t\u0001\u0004\t\u0007\"\u00025\t\u0001\u0004I\u0017A\u00034pe\n+Go^3f]V!\u0011QMA8)A\t9\'!\u001d\u0002v\u0005e\u0014QPA@\u0003\u0003\u000b\u0019\tF\u0002;\u0003SBaaP\u0005A\u0002\u0005-\u0004#B\rB\u0003[B\u0003cA\u0015\u0002p\u0011)Q)\u0003b\u0001Y!1\u00111O\u0005A\u0002e\fAA\u001a:p[\"1\u0011qO\u0005A\u0002e\fA!\u001e9U_\"1q)\u0003a\u0001\u0003w\u0002B!S+\u0002n!)\u0011,\u0003a\u0001a!)1,\u0003a\u00019\")\u0001-\u0003a\u0001C\")\u0001.\u0003a\u0001S\u0006Aam\u001c:Fm\u0016\u0014\u00180\u0006\u0003\u0002\n\u0006ME\u0003DAF\u0003+\u000bI*a\'\u0002\u001e\u0006}Ec\u0001\u001e\u0002\u000e\"1qH\u0003a\u0001\u0003\u001f\u0003R!G!\u0002\u0012\"\u00022!KAJ\t\u0015)%B1\u0001-\u0011\u00199%\u00021\u0001\u0002\u0018B!\u0011*VAI\u0011\u0015I&\u00021\u00011\u0011\u0015Y&\u00021\u0001]\u0011\u0015\u0001\'\u00021\u0001b\u0011\u0015A\'\u00021\u0001j\u0003=Ig\u000eZ5dCR,7+^2dKN\u001cHc\u0001\u001e\u0002&\"A\u0011qU\u0006\u0005\u0002\u0004\tI+A\u0004nKN\u001c\u0018mZ3\u0011\u000be\tY+a,\n\u0007\u00055&D\u0001\u0005=Eft\u0017-\\3?!\u0011\t\t,!/\u000f\t\u0005M\u0016Q\u0017\t\u0003\u0019jI1!a.\u001b\u0003\u0019\u0001&/\u001a3fM&!\u00111XA_\u0005\u0019\u0019FO]5oO*\u0019\u0011q\u0017\u000e\u0002\u001f%tG-[2bi\u00164\u0015-\u001b7ve\u0016$rAOAb\u0003\u000b\fY\u000e\u0003\u0005\u0002(2!\t\u0019AAU\u0011\u001d\t9\r\u0004a\u0001\u0003\u0013\fQb\u001c9uS>t\u0017\r\\\"bkN,\u0007#B\r\u0002L\u0006=\u0017bAAg5\t1q\n\u001d;j_:\u0004B!!5\u0002V:\u00191*a5\n\u0005MS\u0012\u0002BAl\u00033\u0014\u0011\u0002\u00165s_^\f\'\r\\3\u000b\u0005MS\u0002\"\u00025\r\u0001\u0004IG#\u0003\u001e\u0002`\u0006\u0005\u00181]As\u0011!\t9+\u0004CA\u0002\u0005%\u0006bBAd\u001b\u0001\u0007\u0011\u0011\u001a\u0005\u0006Q6\u0001\r!\u001b\u0005\b\u0003Ol\u0001\u0019AAu\u0003!\tg.\u00197zg&\u001c\bCBAv\u0003c\fy+\u0004\u0002\u0002n*\u0019\u0011q\u001e+\u0002\u0013%lW.\u001e;bE2,\u0017\u0002BAz\u0003[\u0014!\"\u00138eKb,GmU3r\u0003I\t7o]3si&twMT1ukJ,wJ\u001a+\u0016\t\u0005e(QA\u000b\u0003\u0003w\u0014B!!@\u0003\u0002\u00191\u0011q \u0001\u0001\u0003w\u0014A\u0002\u0010:fM&tW-\\3oiz\u0002B!\t\u0014\u0003\u0004A\u0019\u0011F!\u0002\u0005\u000b-r!\u0019\u0001\u0017\u0006\ru\ni\u0010\u0001B\u0005!\rI\"1B\u0005\u0004\u0005\u001bQ\"\u0001B+oSR\u0004
   #9 = Utf8               org/scalatest/enablers/UnitInspectorAsserting$$anon$1
  #10 = Class              #9             // org/scalatest/enablers/UnitInspectorAsserting$$anon$1
  #11 = Utf8               org/scalatest/enablers/UnitInspectorAsserting$InspectorAssertingImpl
  #12 = Class              #11            // org/scalatest/enablers/UnitInspectorAsserting$InspectorAssertingImpl
  #13 = Utf8               InspectorAssertingImpl
  #14 = Utf8               assertingNatureOfT
  #15 = Utf8               ()Lorg/scalatest/enablers/InspectorAsserting;
  #16 = Utf8               <T:Ljava/lang/Object;>()Lorg/scalatest/enablers/InspectorAsserting<TT;>;
  #17 = Utf8               <init>
  #18 = Utf8               (Lorg/scalatest/enablers/UnitInspectorAsserting;)V
  #19 = NameAndType        #17:#18        // "<init>":(Lorg/scalatest/enablers/UnitInspectorAsserting;)V
  #20 = Methodref          #10.#19        // org/scalatest/enablers/UnitInspectorAsserting$$anon$1."<init>":(Lorg/scalatest/enablers/UnitInspectorAsserting;)V
  #21 = Utf8               this
  #22 = Utf8               Lorg/scalatest/enablers/UnitInspectorAsserting;
  #23 = Utf8               ()V
  #24 = NameAndType        #17:#23        // "<init>":()V
  #25 = Methodref          #4.#24         // java/lang/Object."<init>":()V
  #26 = Utf8               Code
  #27 = Utf8               LineNumberTable
  #28 = Utf8               LocalVariableTable
  #29 = Utf8               Signature
  #30 = Utf8               InnerClasses
  #31 = Utf8               SourceFile
  #32 = Utf8               RuntimeVisibleAnnotations
  #33 = Utf8               ScalaInlineInfo
  #34 = Utf8               ScalaSig
{
  public <T extends java.lang.Object> org.scalatest.enablers.InspectorAsserting<T> assertingNatureOfT();
    descriptor: ()Lorg/scalatest/enablers/InspectorAsserting;
    flags: (0x0001) ACC_PUBLIC
    Code:
      stack=3, locals=1, args_size=1
         0: new           #10                 // class org/scalatest/enablers/UnitInspectorAsserting$$anon$1
         3: dup
         4: aload_0
         5: invokespecial #20                 // Method org/scalatest/enablers/UnitInspectorAsserting$$anon$1."<init>":(Lorg/scalatest/enablers/UnitInspectorAsserting;)V
         8: areturn
      LineNumberTable:
        line 318: 0
      LocalVariableTable:
        Start  Length  Slot  Name   Signature
            0       9     0  this   Lorg/scalatest/enablers/UnitInspectorAsserting;
    Signature: #16                          // <T:Ljava/lang/Object;>()Lorg/scalatest/enablers/InspectorAsserting<TT;>;

  public org.scalatest.enablers.UnitInspectorAsserting();
    descriptor: ()V
    flags: (0x0001) ACC_PUBLIC
    Code:
      stack=1, locals=1, args_size=1
         0: aload_0
         1: invokespecial #25                 // Method java/lang/Object."<init>":()V
         4: return
      LineNumberTable:
        line 361: 0
        line 80: 4
      LocalVariableTable:
        Start  Length  Slot  Name   Signature
            0       5     0  this   Lorg/scalatest/enablers/UnitInspectorAsserting;
}
InnerClasses:
  public final #10;                       // class org/scalatest/enablers/UnitInspectorAsserting$$anon$1
  public abstract #13= #12 of #2;         // InspectorAssertingImpl=class org/scalatest/enablers/UnitInspectorAsserting$InspectorAssertingImpl of class org/scalatest/enablers/UnitInspectorAsserting
SourceFile: "InspectorAsserting.scala"
RuntimeVisibleAnnotations:
  0: #6(#7=s#8)
    scala.reflect.ScalaSignature(
      bytes="\u0006\u0005\t=a!B\b\u0011\u0003\u00039\u0002\"\u0002\u0010\u0001\t\u0003yb!\u0002\u0012\u0001\u0003\u0003\u0019\u0003\"\u0002\u0010\u0003\t\u0003\u0019\u0004\"\u0002\u001c\u0003\t\u00039\u0004\"B8\u0003\t\u0003\u0001\bbBA\u0003\u0005\u0011\u0005\u0011q\u0001\u0005\b\u0003K\u0011A\u0011AA\u0014\u0011\u001d\t)E\u0001C\u0001\u0003\u000fBq!!\u0019\u0003\t\u0003\t\u0019\u0007C\u0004\u0002\u0006\n!\t!a\"\t\u0011\u0005\u0005&A\"\u0001\u0013\u0003GC\u0001\"a0\u0003\r\u0003\u0011\u0012\u0011\u0019\u0005\t\u0003\u007f\u0013a\u0011\u0001\n\u0002^\"9\u0011Q\u001f\u0001\u0005\u0004\u0005](AF+oSRLen\u001d9fGR|\'/Q:tKJ$\u0018N\\4\u000b\u0005E\u0011\u0012\u0001C3oC\ndWM]:\u000b\u0005M!\u0012!C:dC2\fG/Z:u\u0015\u0005)\u0012aA8sO\u000e\u00011C\u0001\u0001\u0019!\tIB$D\u0001\u001b\u0015\u0005Y\u0012!B:dC2\f\u0017BA\u000f\u001b\u0005\u0019\te.\u001f*fM\u00061A(\u001b8jiz\"\u0012\u0001\t\t\u0003C\u0001i\u0011\u0001\u0005\u0002\u0017\u0013:\u001c\b/Z2u_J\f5o]3si&tw-S7qYV\u0011AEK\n\u0004\u0005a)\u0003cA\u0011\'Q%\u0011q\u0005\u0005\u0002\u0013\u0013:\u001c\b/Z2u_J\f5o]3si&tw\r\u0005\u0002*U1\u0001A!B\u0016\u0003\u0005\u0004a#!\u0001+\u0012\u00055\u0002\u0004CA\r/\u0013\ty#DA\u0004O_RD\u0017N\\4\u0011\u0005e\t\u0014B\u0001\u001a\u001b\u0005\r\te.\u001f\u000b\u0002iA\u0019QG\u0001\u0015\u000e\u0003\u0001\taAZ8s\u00032dWC\u0001\u001dE)\u0019Id\t\u0017.`OR\u0011!H\u0010\t\u0003wqj\u0011AA\u0005\u0003{\u0019\u0012aAU3tk2$\b\"B \u0005\u0001\u0004\u0001\u0015a\u00014v]B!\u0011$Q\")\u0013\t\u0011%DA\u0005Gk:\u001cG/[8ocA\u0011\u0011\u0006\u0012\u0003\u0006\u000b\u0012\u0011\r\u0001\f\u0002\u0002\u000b\")q\t\u0002a\u0001\u0011\u0006\u0011\u0001p\u001d\t\u0004\u0013V\u001beB\u0001&S\u001d\tY\u0005K\u0004\u0002M\u001f6\tQJ\u0003\u0002O-\u00051AH]8pizJ\u0011aG\u0005\u0003#j\t!bY8mY\u0016\u001cG/[8o\u0013\t\u0019F+A\u0004qC\u000e\\\u0017mZ3\u000b\u0005ES\u0012B\u0001,X\u000599UM\u001c+sCZ,\'o]1cY\u0016T!a\u0015+\t\u000be#\u0001\u0019\u0001\u0019\u0002\u0011=\u0014\u0018nZ5oC2DQa\u0017\u0003A\u0002q\u000b\u0011b\u001d5peRD\u0017M\u001c3\u0011\u0005ei\u0016B\u00010\u001b\u0005\u001d\u0011un\u001c7fC:DQ\u0001\u0019\u0003A\u0002\u0005\f!\u0002\u001d:fiRLg-[3s!\t\u0011W-D\u0001d\u0015\t!G#A\u0005tG\u0006d\u0017m\u0019;jG&\u0011am\u0019\u0002\u000b!J,G\u000f^5gS\u0016\u0014\b\"\u00025\u0005\u0001\u0004I\u0017a\u00019pgB\u0011!.\\\u0007\u0002W*\u0011AnY\u0001\u0007g>,(oY3\n\u00059\\\'\u0001\u0003)pg&$\u0018n\u001c8\u0002\u0015\u0019|\'/\u0011;MK\u0006\u001cH/\u0006\u0002rmRI!o\u001e?\u007f\u007f\u0006\u0005\u00111\u0001\u000b\u0003uMDQaP\u0003A\u0002Q\u0004B!G!vQA\u0011\u0011F\u001e\u0003\u0006\u000b\u0016\u0011\r\u0001\f\u0005\u0006q\u0016\u0001\r!_\u0001\u0004[&t\u0007CA\r{\u0013\tY(DA\u0002J]RDQaR\u0003A\u0002u\u00042!S+v\u0011\u0015IV\u00011\u00011\u0011\u0015YV\u00011\u0001]\u0011\u0015\u0001W\u00011\u0001b\u0011\u0015AW\u00011\u0001j\u0003%1wN]!u\u001b>\u001cH/\u0006\u0003\u0002\n\u0005MACDA\u0006\u0003+\tI\"!\b\u0002 \u0005\u0005\u00121\u0005\u000b\u0004u\u00055\u0001BB \u0007\u0001\u0004\ty\u0001E\u0003\u001a\u0003\u0006E\u0001\u0006E\u0002*\u0003\'!Q!\u0012\u0004C\u00021Ba!a\u0006\u0007\u0001\u0004I\u0018aA7bq\"1qI\u0002a\u0001\u00037\u0001B!S+\u0002\u0012!)\u0011L\u0002a\u0001a!)1L\u0002a\u00019\")\u0001M\u0002a\u0001C\")\u0001N\u0002a\u0001S\u0006Qam\u001c:Fq\u0006\u001cG\u000f\\=\u0016\t\u0005%\u00121\u0007\u000b\u000f\u0003W\t)$!\u000f\u0002>\u0005}\u0012\u0011IA\")\rQ\u0014Q\u0006\u0005\u0007\u007f\u001d\u0001\r!a\f\u0011\u000be\t\u0015\u0011\u0007\u0015\u0011\u0007%\n\u0019\u0004B\u0003F\u000f\t\u0007A\u0006\u0003\u0004\u00028\u001d\u0001\r!_\u0001\u000fgV\u001c7-Z3eK\u0012\u001cu.\u001e8u\u0011\u00199u\u00011\u0001\u0002<A!\u0011*VA\u0019\u0011\u0015Iv\u00011\u00011\u0011\u0015Yv\u00011\u0001]\u0011\u0015\u0001w\u00011\u0001b\u0011\u0015Aw\u00011\u0001j\u0003\u00151wN\u001d(p+\u0011\tI%a\u0015\u0015\u0019\u0005-\u0013QKA-\u00037\ni&a\u0018\u0015\u0007i\ni\u0005\u0003\u0004@\u0011\u0001\u0007\u0011q\n\t\u00063\u0005\u000b\t\u0006\u000b\t\u0004S\u0005MC!B#\t\u0005\u0004a\u0003BB$\t\u0001\u0004\t9\u0006\u0005\u0003J+\u0006E\u0003\"B-\t\u0001\u0004\u0001\u0004\"B.\t\u0001\u0004a\u0006\"\u00021\t\u0001\u0004\t\u0007\"\u00025\t\u0001\u0004I\u0017A\u00034pe\n+Go^3f]V!\u0011QMA8)A\t9\'!\u001d\u0002v\u0005e\u0014QPA@\u0003\u0003\u000b\u0019\tF\u0002;\u0003SBaaP\u0005A\u0002\u0005-\u0004#B\rB\u0003[B\u0003cA\u0015\u0002p\u0011)Q)\u0003b\u0001Y!1\u00111O\u0005A\u0002e\fAA\u001a:p[\"1\u0011qO\u0005A\u0002e\fA!\u001e9U_\"1q)\u0003a\u0001\u0003w\u0002B!S+\u0002n!)\u0011,\u0003a\u0001a!)1,\u0003a\u00019\")\u0001-\u0003a\u0001C\")\u0001.\u0003a\u0001S\u0006Aam\u001c:Fm\u0016\u0014\u00180\u0006\u0003\u0002\n\u0006ME\u0003DAF\u0003+\u000bI*a\'\u0002\u001e\u0006}Ec\u0001\u001e\u0002\u000e\"1qH\u0003a\u0001\u0003\u001f\u0003R!G!\u0002\u0012\"\u00022!KAJ\t\u0015)%B1\u0001-\u0011\u00199%\u00021\u0001\u0002\u0018B!\u0011*VAI\u0011\u0015I&\u00021\u00011\u0011\u0015Y&\u00021\u0001]\u0011\u0015\u0001\'\u00021\u0001b\u0011\u0015A\'\u00021\u0001j\u0003=Ig\u000eZ5dCR,7+^2dKN\u001cHc\u0001\u001e\u0002&\"A\u0011qU\u0006\u0005\u0002\u0004\tI+A\u0004nKN\u001c\u0018mZ3\u0011\u000be\tY+a,\n\u0007\u00055&D\u0001\u0005=Eft\u0017-\\3?!\u0011\t\t,!/\u000f\t\u0005M\u0016Q\u0017\t\u0003\u0019jI1!a.\u001b\u0003\u0019\u0001&/\u001a3fM&!\u00111XA_\u0005\u0019\u0019FO]5oO*\u0019\u0011q\u0017\u000e\u0002\u001f%tG-[2bi\u00164\u0015-\u001b7ve\u0016$rAOAb\u0003\u000b\fY\u000e\u0003\u0005\u0002(2!\t\u0019AAU\u0011\u001d\t9\r\u0004a\u0001\u0003\u0013\fQb\u001c9uS>t\u0017\r\\\"bkN,\u0007#B\r\u0002L\u0006=\u0017bAAg5\t1q\n\u001d;j_:\u0004B!!5\u0002V:\u00191*a5\n\u0005MS\u0012\u0002BAl\u00033\u0014\u0011\u0002\u00165s_^\f\'\r\\3\u000b\u0005MS\u0002\"\u00025\r\u0001\u0004IG#\u0003\u001e\u0002`\u0006\u0005\u00181]As\u0011!\t9+\u0004CA\u0002\u0005%\u0006bBAd\u001b\u0001\u0007\u0011\u0011\u001a\u0005\u0006Q6\u0001\r!\u001b\u0005\b\u0003Ol\u0001\u0019AAu\u0003!\tg.\u00197zg&\u001c\bCBAv\u0003c\fy+\u0004\u0002\u0002n*\u0019\u0011q\u001e+\u0002\u0013%lW.\u001e;bE2,\u0017\u0002BAz\u0003[\u0014!\"\u00138eKb,GmU3r\u0003I\t7o]3si&twMT1ukJ,wJ\u001a+\u0016\t\u0005e(QA\u000b\u0003\u0003w\u0014B!!@\u0003\u0002\u00191\u0011q \u0001\u0001\u0003w\u0014A\u0002\u0010:fM&tW-\\3oiz\u0002B!\t\u0014\u0003\u0004A\u0019\u0011F!\u0002\u0005\u000b-r!\u0019\u0001\u0017\u0006\ru\ni\u0010\u0001B\u0005!\rI\"1B\u0005\u0004\u0005\u001bQ\"\u0001B+oSR\u0004"
    )
  ScalaInlineInfo: length = 0xE (unknown attribute)
   01 00 00 02 00 11 00 17 00 00 0E 00 0F 00
  ScalaSig: length = 0x3 (unknown attribute)
   05 02 00
