Classfile /Users/mw/Projects/slang-braindump/.jar/jar8/assemble/slang-braindump/assemble/content/org/scalactic/anyvals/End.class
  Last modified May 29, 2022; size 963 bytes
  SHA-256 checksum cb1b029ff2d638b9b7c8cd253e0b82487358d7c9d5b222a77d9e9b8f16adc2c7
  Compiled from "End.scala"
public final class org.scalactic.anyvals.End
  minor version: 0
  major version: 52
  flags: (0x0031) ACC_PUBLIC, ACC_FINAL, ACC_SUPER
  this_class: #2                          // org/scalactic/anyvals/End
  super_class: #4                         // java/lang/Object
  interfaces: 0, fields: 0, methods: 2, attributes: 3
Constant pool:
   #1 = Utf8               org/scalactic/anyvals/End
   #2 = Class              #1             // org/scalactic/anyvals/End
   #3 = Utf8               java/lang/Object
   #4 = Class              #3             // java/lang/Object
   #5 = Utf8               End.scala
   #6 = Utf8               Lscala/reflect/ScalaSignature;
   #7 = Utf8               bytes
   #8 = Utf8               \u0006\u0005e:Q!\u0002\u0004\t\u000251Qa\u0004\u0004\t\u0002AAQaF\u0001\u0005\u0002aAQ!G\u0001\u0005\u0002iAQ\u0001L\u0001\u0005B5\n1!\u00128e\u0015\t9\u0001\"A\u0004b]f4\u0018\r\\:\u000b\u0005%Q\u0011!C:dC2\f7\r^5d\u0015\u0005Y\u0011aA8sO\u000e\u0001\u0001C\u0001\b\u0002\u001b\u00051!aA#oIN\u0011\u0011!\u0005\t\u0003%Ui\u0011a\u0005\u0006\u0002)\u0005)1oY1mC&\u0011ac\u0005\u0002\u0007\u0003:L(+\u001a4\u0002\rqJg.\u001b;?)\u0005i\u0011\u0001\u0004\u0013d_2|g\u000eJ2pY>tWCA\u000e\")\ta\"\u0006E\u0002\u000f;}I!A\b\u0004\u0003\u00199{g.R7qifd\u0015n\u001d;\u0011\u0005\u0001\nC\u0002\u0001\u0003\u0006E\r\u0011\ra\t\u0002\u0002)F\u0011Ae\n\t\u0003%\u0015J!AJ\n\u0003\u000f9{G\u000f[5oOB\u0011!\u0003K\u0005\u0003SM\u00111!\u00118z\u0011\u0015Y3\u00011\u0001 \u0003\u001d)G.Z7f]R\f\u0001\u0002^8TiJLgn\u001a\u000b\u0002]A\u0011qF\u000e\b\u0003aQ\u0002\"!M\n\u000e\u0003IR!a\r\u0007\u0002\rq\u0012xn\u001c;?\u0013\t)4#\u0001\u0004Qe\u0016$WMZ\u0005\u0003oa\u0012aa\u0015;sS:<\'BA\u001b\u0014\u0001
   #9 = Utf8               toString
  #10 = Utf8               ()Ljava/lang/String;
  #11 = Utf8               org/scalactic/anyvals/End$
  #12 = Class              #11            // org/scalactic/anyvals/End$
  #13 = Utf8               MODULE$
  #14 = Utf8               Lorg/scalactic/anyvals/End$;
  #15 = NameAndType        #13:#14        // MODULE$:Lorg/scalactic/anyvals/End$;
  #16 = Fieldref           #12.#15        // org/scalactic/anyvals/End$.MODULE$:Lorg/scalactic/anyvals/End$;
  #17 = NameAndType        #9:#10         // toString:()Ljava/lang/String;
  #18 = Methodref          #12.#17        // org/scalactic/anyvals/End$.toString:()Ljava/lang/String;
  #19 = Utf8               $colon$colon
  #20 = Utf8               (Ljava/lang/Object;)Lscala/collection/immutable/List;
  #21 = Utf8               element
  #22 = NameAndType        #19:#20        // $colon$colon:(Ljava/lang/Object;)Lscala/collection/immutable/List;
  #23 = Methodref          #12.#22        // org/scalactic/anyvals/End$.$colon$colon:(Ljava/lang/Object;)Lscala/collection/immutable/List;
  #24 = Utf8               Ljava/lang/Object;
  #25 = Utf8               Code
  #26 = Utf8               LocalVariableTable
  #27 = Utf8               MethodParameters
  #28 = Utf8               SourceFile
  #29 = Utf8               RuntimeVisibleAnnotations
  #30 = Utf8               ScalaSig
{
  public static java.lang.String toString();
    descriptor: ()Ljava/lang/String;
    flags: (0x0009) ACC_PUBLIC, ACC_STATIC
    Code:
      stack=1, locals=0, args_size=0
         0: getstatic     #16                 // Field org/scalactic/anyvals/End$.MODULE$:Lorg/scalactic/anyvals/End$;
         3: invokevirtual #18                 // Method org/scalactic/anyvals/End$.toString:()Ljava/lang/String;
         6: areturn

  public static scala.collection.immutable.List $colon$colon(java.lang.Object);
    descriptor: (Ljava/lang/Object;)Lscala/collection/immutable/List;
    flags: (0x0009) ACC_PUBLIC, ACC_STATIC
    Code:
      stack=2, locals=1, args_size=1
         0: getstatic     #16                 // Field org/scalactic/anyvals/End$.MODULE$:Lorg/scalactic/anyvals/End$;
         3: aload_0
         4: invokevirtual #23                 // Method org/scalactic/anyvals/End$.$colon$colon:(Ljava/lang/Object;)Lscala/collection/immutable/List;
         7: areturn
      LocalVariableTable:
        Start  Length  Slot  Name   Signature
            0       8     0 element   Ljava/lang/Object;
    MethodParameters:
      Name                           Flags
      element                        final
}
SourceFile: "End.scala"
RuntimeVisibleAnnotations:
  0: #6(#7=s#8)
    scala.reflect.ScalaSignature(
      bytes="\u0006\u0005e:Q!\u0002\u0004\t\u000251Qa\u0004\u0004\t\u0002AAQaF\u0001\u0005\u0002aAQ!G\u0001\u0005\u0002iAQ\u0001L\u0001\u0005B5\n1!\u00128e\u0015\t9\u0001\"A\u0004b]f4\u0018\r\\:\u000b\u0005%Q\u0011!C:dC2\f7\r^5d\u0015\u0005Y\u0011aA8sO\u000e\u0001\u0001C\u0001\b\u0002\u001b\u00051!aA#oIN\u0011\u0011!\u0005\t\u0003%Ui\u0011a\u0005\u0006\u0002)\u0005)1oY1mC&\u0011ac\u0005\u0002\u0007\u0003:L(+\u001a4\u0002\rqJg.\u001b;?)\u0005i\u0011\u0001\u0004\u0013d_2|g\u000eJ2pY>tWCA\u000e\")\ta\"\u0006E\u0002\u000f;}I!A\b\u0004\u0003\u00199{g.R7qifd\u0015n\u001d;\u0011\u0005\u0001\nC\u0002\u0001\u0003\u0006E\r\u0011\ra\t\u0002\u0002)F\u0011Ae\n\t\u0003%\u0015J!AJ\n\u0003\u000f9{G\u000f[5oOB\u0011!\u0003K\u0005\u0003SM\u00111!\u00118z\u0011\u0015Y3\u00011\u0001 \u0003\u001d)G.Z7f]R\f\u0001\u0002^8TiJLgn\u001a\u000b\u0002]A\u0011qF\u000e\b\u0003aQ\u0002\"!M\n\u000e\u0003IR!a\r\u0007\u0002\rq\u0012xn\u001c;?\u0013\t)4#\u0001\u0004Qe\u0016$WMZ\u0005\u0003oa\u0012aa\u0015;sS:<\'BA\u001b\u0014\u0001"
    )
  ScalaSig: length = 0x3 (unknown attribute)
   05 02 00
