Classfile /Users/mw/Projects/slang-braindump/.jar/jar8/assemble/slang-braindump/assemble/content/org/scalactic/anyvals/NonZeroFiniteDouble.class
  Last modified May 29, 2022; size 27668 bytes
  SHA-256 checksum 452438bd18accb3dacfca3eb22b4d8622a783b074ce1c6213a7b88483bbd71a3
  Compiled from "NonZeroFiniteDouble.scala"
public final class org.scalactic.anyvals.NonZeroFiniteDouble
  minor version: 0
  major version: 52
  flags: (0x0031) ACC_PUBLIC, ACC_FINAL, ACC_SUPER
  this_class: #2                          // org/scalactic/anyvals/NonZeroFiniteDouble
  super_class: #4                         // java/lang/Object
  interfaces: 0, fields: 1, methods: 179, attributes: 4
Constant pool:
    #1 = Utf8               org/scalactic/anyvals/NonZeroFiniteDouble
    #2 = Class              #1            // org/scalactic/anyvals/NonZeroFiniteDouble
    #3 = Utf8               java/lang/Object
    #4 = Class              #3            // java/lang/Object
    #5 = Utf8               NonZeroFiniteDouble.scala
    #6 = Utf8               Lscala/reflect/ScalaSignature;
    #7 = Utf8               bytes
    #8 = Utf8               \u0006\u0005\u001d%daBA?\u0003\u007f\u0012\u0011Q\u0012\u0005\u000b\u00037\u0003!Q1A\u0005\u0002\u0005u\u0005BCAS\u0001\t\u0005\t\u0015!\u0003\u0002 \"q\u0011q\u0015\u0001\u0005\u0002\u0003\u0005\t\u0011!A\u0005\n\u0005%\u0006bBAY\u0001\u0011\u0005\u00131\u0017\u0005\b\u0003\u0017\u0004A\u0011AAg\u0011\u001d\t)\u000e\u0001C\u0001\u0003/Dq!a8\u0001\t\u0003\t\t\u000fC\u0004\u0002j\u0002!\t!a;\t\u000f\u0005M\b\u0001\"\u0001\u0002v\"9\u0011Q \u0001\u0005\u0002\u0005}\bb\u0002B\u0004\u0001\u0011\u0005\u0011Q\u0014\u0005\b\u0005\u0013\u0001A\u0011\u0001B\u0006\u0011\u001d\u0011i\u0001\u0001C\u0001\u0005\u0017AqAa\u0004\u0001\t\u0003\u0011\t\u0002C\u0004\u0003\u0018\u0001!\tA!\u0007\t\u000f\t]\u0001\u0001\"\u0001\u0003$!9!q\u0003\u0001\u0005\u0002\t\u001d\u0002b\u0002B\f\u0001\u0011\u0005!1\u0006\u0005\b\u0005/\u0001A\u0011\u0001B\u0018\u0011\u001d\u00119\u0002\u0001C\u0001\u0005gAqAa\u0006\u0001\t\u0003\u00119\u0004C\u0004\u0003<\u0001!\tA!\u0010\t\u000f\tm\u0002\u0001\"\u0001\u0003B!9!1\b\u0001\u0005\u0002\t\u0015\u0003b\u0002B\u001e\u0001\u0011\u0005!\u0011\n\u0005\b\u0005w\u0001A\u0011\u0001B\'\u0011\u001d\u0011Y\u0004\u0001C\u0001\u0005#BqAa\u000f\u0001\t\u0003\u0011)\u0006C\u0004\u0003Z\u0001!\tAa\u0017\t\u000f\te\u0003\u0001\"\u0001\u0003`!9!\u0011\f\u0001\u0005\u0002\t\r\u0004b\u0002B-\u0001\u0011\u0005!q\r\u0005\b\u00053\u0002A\u0011\u0001B6\u0011\u001d\u0011I\u0006\u0001C\u0001\u0005_BqA!\u0017\u0001\t\u0003\u0011\u0019\bC\u0004\u0003x\u0001!\tA!\u001f\t\u000f\t]\u0004\u0001\"\u0001\u0003~!9!q\u000f\u0001\u0005\u0002\t\u0005\u0005b\u0002B<\u0001\u0011\u0005!Q\u0011\u0005\b\u0005o\u0002A\u0011\u0001BE\u0011\u001d\u00119\b\u0001C\u0001\u0005\u001bCqAa\u001e\u0001\t\u0003\u0011\t\nC\u0004\u0003\u0010\u0001!\tA!&\t\u000f\t=\u0001\u0001\"\u0001\u0003\u001a\"9!q\u0002\u0001\u0005\u0002\tu\u0005b\u0002B\b\u0001\u0011\u0005!\u0011\u0015\u0005\b\u0005\u001f\u0001A\u0011\u0001BS\u0011\u001d\u0011y\u0001\u0001C\u0001\u0005SCqAa\u0004\u0001\t\u0003\u0011i\u000bC\u0004\u00032\u0002!\tAa-\t\u000f\tE\u0006\u0001\"\u0001\u00038\"9!\u0011\u0017\u0001\u0005\u0002\tm\u0006b\u0002BY\u0001\u0011\u0005!q\u0018\u0005\b\u0005c\u0003A\u0011\u0001Bb\u0011\u001d\u0011\t\f\u0001C\u0001\u0005\u000fDqA!-\u0001\t\u0003\u0011Y\rC\u0004\u0003P\u0002!\tA!5\t\u000f\t=\u0007\u0001\"\u0001\u0003V\"9!q\u001a\u0001\u0005\u0002\te\u0007b\u0002Bh\u0001\u0011\u0005!Q\u001c\u0005\b\u0005\u001f\u0004A\u0011\u0001Bq\u0011\u001d\u0011y\r\u0001C\u0001\u0005KDqAa4\u0001\t\u0003\u0011I\u000fC\u0004\u0003n\u0002!\tAa<\t\u000f\t5\b\u0001\"\u0001\u0003t\"9!Q\u001e\u0001\u0005\u0002\t]\bb\u0002Bw\u0001\u0011\u0005!1 \u0005\b\u0005[\u0004A\u0011\u0001B\u0000\u0011\u001d\u0011i\u000f\u0001C\u0001\u0007\u0007AqA!<\u0001\t\u0003\u00199\u0001C\u0004\u0004\f\u0001!\ta!\u0004\t\u000f\r-\u0001\u0001\"\u0001\u0004\u0012!911\u0002\u0001\u0005\u0002\rU\u0001bBB\u0006\u0001\u0011\u00051\u0011\u0004\u0005\b\u0007\u0017\u0001A\u0011AB\u000f\u0011\u001d\u0019Y\u0001\u0001C\u0001\u0007CAqaa\u0003\u0001\t\u0003\u0019)\u0003C\u0004\u0004*\u0001!\taa\u000b\t\u000f\rE\u0002\u0001\"\u0001\u00044!91q\u0007\u0001\u0005\u0002\re\u0002bBB\u001e\u0001\u0011\u0005\u0011Q\u0014\u0005\b\u0007{\u0001A\u0011AAO\u0011\u001d\u0019y\u0004\u0001C\u0001\u0007\u0003B\u0011b!\u0014\u0001\u0003\u0003%\tea\u0014\t\u0013\rE\u0003!!A\u0005B\rMs\u0001CB0\u0003\u007fB\ta!\u0019\u0007\u0011\u0005u\u0014q\u0010E\u0001\u0007GBq!a*X\t\u0003\u0019Y\u0007C\u0005\u0004n]\u0013\r\u0011\"\u0002\u0003\f!A1qN,!\u0002\u001b\tY\u000bC\u0005\u0004r]\u0013\r\u0011\"\u0002\u0003\f!A11O,!\u0002\u001b\tY\u000bC\u0004\u0004v]#\taa\u001e\t\u000f\r}r\u000b\"\u0001\u0004\u0002\"91QQ,\u0005\u0002\r\u001d\u0005bBBL/\u0012\u00051\u0011\u0014\u0005\b\u0007{;F\u0011AB`\u0011\u001d\u00199n\u0016C\u0001\u00073Dqa!@X\t\u0003\u0019y\u0010C\u0004\u0005\u0004]#\t\u0001\"\u0002\t\u0011\u0011MqK!C\u0002\t+Aq\u0001\".X\t\u0007!9\fC\u0004\u0005>^#\u0019\u0001b0\t\u0013\u0011%wK1A\u0005\u0004\u0011-\u0007\u0002\u0003Cj/\u0002\u0006I\u0001\"4\t\u0013\u0011UwK1A\u0005\u0006\t-\u0001\u0002\u0003Cl/\u0002\u0006i!a+\t\u000f\u0011ew\u000b\"\u0002\u0005\\\"9A\u0011],\u0005\u0006\u0011\r\bb\u0002Ct/\u0012\u0015A\u0011\u001e\u0005\b\t[<FQ\u0001Cx\u0011\u001d!\u0019p\u0016C\u0003\tkDq\u0001\"?X\t\u000b!Y\u0010C\u0004\u0005\u0000^#)!\"\u0001\t\u000f\u0015\u0015q\u000b\"\u0002\u0006\b!9Q1B,\u0005\u0006\u00155\u0001bBC\t/\u0012\u0015Q1\u0003\u0005\b\u000b/9FQAC\r\u0011\u001d)\tc\u0016C\u0003\u000bGAq!\"\tX\t\u000b)Y\u0003C\u0004\u0006\"]#)!b\r\t\u000f\u0015\u0005r\u000b\"\u0002\u0006<!9Q\u0011E,\u0005\u0006\u0015\r\u0003bBC\u0011/\u0012\u0015Q1\n\u0005\b\u000bC9FQAC*\u0011\u001d)Yf\u0016C\u0003\u000b;Bq!b\u0017X\t\u000b))\u0007C\u0004\u0006\\]#)!\"\u001c\t\u000f\u0015ms\u000b\"\u0002\u0006v!9Q1L,\u0005\u0006\u0015u\u0004bBC./\u0012\u0015QQ\u0011\u0005\b\u000b7:FQACG\u0011\u001d))j\u0016C\u0003\u000b/Cq!\"&X\t\u000b)y\nC\u0004\u0006\u0016^#)!b*\t\u000f\u0015Uu\u000b\"\u0002\u00060\"9QQS,\u0005\u0006\u0015]\u0006bBCK/\u0012\u0015Qq\u0018\u0005\b\u000b+;FQACd\u0011\u001d)ym\u0016C\u0003\u000b#Dq!b4X\t\u000b)I\u000eC\u0004\u0006P^#)!\"9\t\u000f\u0015=w\u000b\"\u0002\u0006j\"9QqZ,\u0005\u0006\u0015E\bbBCh/\u0012\u0015Q\u0011 \u0005\b\u000b\u001f<FQ\u0001D\u0001\u0011\u001d)9b\u0016C\u0003\r\u0013Aq!b\u0006X\t\u000b1\t\u0002C\u0004\u0006\u0018]#)A\"\u0007\t\u000f\u0015]q\u000b\"\u0002\u0007\"!9QqC,\u0005\u0006\u0019%\u0002bBC\f/\u0012\u0015a\u0011\u0007\u0005\b\u000b/9FQ\u0001D\u001d\u0011\u001d1\te\u0016C\u0003\r\u0007BqA\"\u0011X\t\u000b1Y\u0005C\u0004\u0007B]#)Ab\u0015\t\u000f\u0019\u0005s\u000b\"\u0002\u0007\\!9a\u0011I,\u0005\u0006\u0019\r\u0004b\u0002D!/\u0012\u0015a1\u000e\u0005\b\r\u0003:FQ\u0001D:\u0011\u001d1Yh\u0016C\u0003\r{BqAb\u001fX\t\u000b1)\tC\u0004\u0007|]#)A\"$\t\u000f\u0019mt\u000b\"\u0002\u0007\u0016\"9a1P,\u0005\u0006\u0019u\u0005b\u0002D>/\u0012\u0015aQ\u0015\u0005\b\rw:FQ\u0001DW\u0011\u001d1)l\u0016C\u0003\roCqA\".X\t\u000b1y\fC\u0004\u00076^#)Ab2\t\u000f\u0019Uv\u000b\"\u0002\u0007P\"9aQW,\u0005\u0006\u0019]\u0007b\u0002D[/\u0012\u0015aq\u001c\u0005\b\rk;FQ\u0001Dt\u0011\u001d1yo\u0016C\u0003\rcDqAb<X\t\u000b1I\u0010C\u0004\u0007p^#)a\"\u0001\t\u000f\u0019=x\u000b\"\u0002\b\n!9aq^,\u0005\u0006\u001dE\u0001b\u0002Dx/\u0012\u0015q\u0011\u0004\u0005\b\r_<FQAD\u0011\u0011\u001d9Ic\u0016C\u0003\u000fWAqab\rX\t\u000b9)\u0004C\u0004\b>]#)ab\u0010\t\u000f\u001d\rs\u000b\"\u0002\bF!9q\u0011J,\u0005\u0006\u001d-\u0003bBD(/\u0012\u0015q\u0011\u000b\u0005\n\u000f3:\u0016\u0011!C\u0003\u000f7B\u0011bb\u0018X\u0003\u0003%)a\"\u0019\u0003\'9{gNW3s_\u001aKg.\u001b;f\t>,(\r\\3\u000b\t\u0005\u0005\u00151Q\u0001\bC:Lh/\u00197t\u0015\u0011\t))a\"\u0002\u0013M\u001c\u0017\r\\1di&\u001c\'BAAE\u0003\ry\'oZ\u0002\u0001\'\r\u0001\u0011q\u0012\t\u0005\u0003#\u000b9*\u0004\u0002\u0002\u0014*\u0011\u0011QS\u0001\u0006g\u000e\fG.Y\u0005\u0005\u00033\u000b\u0019J\u0001\u0004B]f4\u0016\r\\\u0001\u0006m\u0006dW/Z\u000b\u0003\u0003?\u0003B!!%\u0002\"&!\u00111UAJ\u0005\u0019!u.\u001e2mK\u00061a/\u00197vK\u0002\na\u0001P5oSRtD\u0003BAV\u0003_\u00032!!,\u0001\u001b\t\ty\bC\u0004\u0002\u001c\u000e\u0001\r!a(\u0002\u0011Q|7\u000b\u001e:j]\u001e$\"!!.\u0011\t\u0005]\u0016Q\u0019\b\u0005\u0003s\u000b\t\r\u0005\u0003\u0002<\u0006MUBAA_\u0015\u0011\ty,a#\u0002\rq\u0012xn\u001c;?\u0013\u0011\t\u0019-a%\u0002\rA\u0013X\rZ3g\u0013\u0011\t9-!3\u0003\rM#(/\u001b8h\u0015\u0011\t\u0019-a%\u0002\rQ|\')\u001f;f+\t\ty\r\u0005\u0003\u0002\u0012\u0006E\u0017\u0002BAj\u0003\'\u0013AAQ=uK\u00069Ao\\*i_J$XCAAm!\u0011\t\t*a7\n\t\u0005u\u00171\u0013\u0002\u0006\'\"|\'\u000f^\u0001\u0007i>\u001c\u0005.\u0019:\u0016\u0005\u0005\r\b\u0003BAI\u0003KLA!a:\u0002\u0014\n!1\t[1s\u0003\u0015!x.\u00138u+\t\ti\u000f\u0005\u0003\u0002\u0012\u0006=\u0018\u0002BAy\u0003\'\u00131!\u00138u\u0003\u0019!x\u000eT8oOV\u0011\u0011q\u001f\t\u0005\u0003#\u000bI0\u0003\u0003\u0002|\u0006M%\u0001\u0002\'p]\u001e\fq\u0001^8GY>\fG/\u0006\u0002\u0003\u0002A!\u0011\u0011\u0013B\u0002\u0013\u0011\u0011)!a%\u0003\u000b\u0019cw.\u0019;\u0002\u0011Q|Gi\\;cY\u0016\f1\"\u001e8bef|F\u0005\u001d7vgV\u0011\u00111V\u0001\rk:\f\'/_0%[&tWo]\u0001\u0006IAdWo\u001d\u000b\u0005\u0003k\u0013\u0019\u0002C\u0004\u0003\u00169\u0001\r!!.\u0002\u0003a\fQ\u0001\n7fgN$BAa\u0007\u0003\"A!\u0011\u0011\u0013B\u000f\u0013\u0011\u0011y\"a%\u0003\u000f\t{w\u000e\\3b]\"9!QC\bA\u0002\u0005=G\u0003\u0002B\u000e\u0005KAqA!\u0006\u0011\u0001\u0004\tI\u000e\u0006\u0003\u0003\u001c\t%\u0002b\u0002B\u000b#\u0001\u0007\u00111\u001d\u000b\u0005\u00057\u0011i\u0003C\u0004\u0003\u0016I\u0001\r!!<\u0015\t\tm!\u0011\u0007\u0005\b\u0005+\u0019\u0002\u0019AA|)\u0011\u0011YB!\u000e\t\u000f\tUA\u00031\u0001\u0003\u0002Q!!1\u0004B\u001d\u0011\u001d\u0011)\"\u0006a\u0001\u0003?\u000b\u0001\u0002\n7fgN$S-\u001d\u000b\u0005\u00057\u0011y\u0004C\u0004\u0003\u0016Y\u0001\r!a4\u0015\t\tm!1\t\u0005\b\u0005+9\u0002\u0019AAm)\u0011\u0011YBa\u0012\t\u000f\tU\u0001\u00041\u0001\u0002dR!!1\u0004B&\u0011\u001d\u0011)\"\u0007a\u0001\u0003[$BAa\u0007\u0003P!9!Q\u0003\u000eA\u0002\u0005]H\u0003\u0002B\u000e\u0005\'BqA!\u0006\u001c\u0001\u0004\u0011\t\u0001\u0006\u0003\u0003\u001c\t]\u0003b\u0002B\u000b9\u0001\u0007\u0011qT\u0001\tI\u001d\u0014X-\u0019;feR!!1\u0004B/\u0011\u001d\u0011)\"\ba\u0001\u0003\u001f$BAa\u0007\u0003b!9!Q\u0003\u0010A\u0002\u0005eG\u0003\u0002B\u000e\u0005KBqA!\u0006 \u0001\u0004\t\u0019\u000f\u0006\u0003\u0003\u001c\t%\u0004b\u0002B\u000bA\u0001\u0007\u0011Q\u001e\u000b\u0005\u00057\u0011i\u0007C\u0004\u0003\u0016\u0005\u0002\r!a>\u0015\t\tm!\u0011\u000f\u0005\b\u0005+\u0011\u0003\u0019\u0001B\u0001)\u0011\u0011YB!\u001e\t\u000f\tU1\u00051\u0001\u0002 \u0006YAe\u001a:fCR,\'\u000fJ3r)\u0011\u0011YBa\u001f\t\u000f\tUA\u00051\u0001\u0002PR!!1\u0004B@\u0011\u001d\u0011)\"\na\u0001\u00033$BAa\u0007\u0003\u0004\"9!Q\u0003\u0014A\u0002\u0005\rH\u0003\u0002B\u000e\u0005\u000fCqA!\u0006(\u0001\u0004\ti\u000f\u0006\u0003\u0003\u001c\t-\u0005b\u0002B\u000bQ\u0001\u0007\u0011q\u001f\u000b\u0005\u00057\u0011y\tC\u0004\u0003\u0016%\u0002\rA!\u0001\u0015\t\tm!1\u0013\u0005\b\u0005+Q\u0003\u0019AAP)\u0011\tyJa&\t\u000f\tU1\u00061\u0001\u0002PR!\u0011q\u0014BN\u0011\u001d\u0011)\u0002\fa\u0001\u00033$B!a(\u0003 \"9!QC\u0017A\u0002\u0005\rH\u0003BAP\u0005GCqA!\u0006/\u0001\u0004\ti\u000f\u0006\u0003\u0002 \n\u001d\u0006b\u0002B\u000b_\u0001\u0007\u0011q\u001f\u000b\u0005\u0003?\u0013Y\u000bC\u0004\u0003\u0016A\u0002\rA!\u0001\u0015\t\u0005}%q\u0016\u0005\b\u0005+\t\u0004\u0019AAP\u0003\u0019!S.\u001b8vgR!\u0011q\u0014B[\u0011\u001d\u0011)B\ra\u0001\u0003\u001f$B!a(\u0003:\"9!QC\u001aA\u0002\u0005eG\u0003BAP\u0005{CqA!\u00065\u0001\u0004\t\u0019\u000f\u0006\u0003\u0002 \n\u0005\u0007b\u0002B\u000bk\u0001\u0007\u0011Q\u001e\u000b\u0005\u0003?\u0013)\rC\u0004\u0003\u0016Y\u0002\r!a>\u0015\t\u0005}%\u0011\u001a\u0005\b\u0005+9\u0004\u0019\u0001B\u0001)\u0011\tyJ!4\t\u000f\tU\u0001\b1\u0001\u0002 \u00061A\u0005^5nKN$B!a(\u0003T\"9!QC\u001dA\u0002\u0005=G\u0003BAP\u0005/DqA!\u0006;\u0001\u0004\tI\u000e\u0006\u0003\u0002 \nm\u0007b\u0002B\u000bw\u0001\u0007\u00111\u001d\u000b\u0005\u0003?\u0013y\u000eC\u0004\u0003\u0016q\u0002\r!!<\u0015\t\u0005}%1\u001d\u0005\b\u0005+i\u0004\u0019AA|)\u0011\tyJa:\t\u000f\tUa\b1\u0001\u0003\u0002Q!\u0011q\u0014Bv\u0011\u001d\u0011)b\u0010a\u0001\u0003?\u000bA\u0001\n3jmR!\u0011q\u0014By\u0011\u001d\u0011)\u0002\u0011a\u0001\u0003\u001f$B!a(\u0003v\"9!QC!A\u0002\u0005eG\u0003BAP\u0005sDqA!\u0006C\u0001\u0004\t\u0019\u000f\u0006\u0003\u0002 \nu\bb\u0002B\u000b\u0007\u0002\u0007\u0011Q\u001e\u000b\u0005\u0003?\u001b\t\u0001C\u0004\u0003\u0016\u0011\u0003\r!a>\u0015\t\u0005}5Q\u0001\u0005\b\u0005+)\u0005\u0019\u0001B\u0001)\u0011\tyj!\u0003\t\u000f\tUa\t1\u0001\u0002 \u0006AA\u0005]3sG\u0016tG\u000f\u0006\u0003\u0002 \u000e=\u0001b\u0002B\u000b\u000f\u0002\u0007\u0011q\u001a\u000b\u0005\u0003?\u001b\u0019\u0002C\u0004\u0003\u0016!\u0003\r!!7\u0015\t\u0005}5q\u0003\u0005\b\u0005+I\u0005\u0019AAr)\u0011\tyja\u0007\t\u000f\tU!\n1\u0001\u0002nR!\u0011qTB\u0010\u0011\u001d\u0011)b\u0013a\u0001\u0003o$B!a(\u0004$!9!Q\u0003\'A\u0002\t\u0005A\u0003BAP\u0007OAqA!\u0006N\u0001\u0004\ty*A\u0002nCb$B!a+\u0004.!91q\u0006(A\u0002\u0005-\u0016\u0001\u0002;iCR\f1!\\5o)\u0011\tYk!\u000e\t\u000f\r=r\n1\u0001\u0002,\u00069\u0011n],i_2,WC\u0001B\u000e\u0003%!xNU1eS\u0006t7/A\u0005u_\u0012+wM]3fg\u0006iQM\\:ve&twMV1mS\u0012$B!a+\u0004D!91QI*A\u0002\r\u001d\u0013!\u00014\u0011\u0011\u0005E5\u0011JAP\u0003?KAaa\u0013\u0002\u0014\nIa)\u001e8di&|g.M\u0001\tQ\u0006\u001c\bnQ8eKR\u0011\u0011Q^\u0001\u0007KF,\u0018\r\\:\u0015\t\tm1Q\u000b\u0005\n\u0007/*\u0016\u0011!a\u0001\u00073\n1\u0001\u001f\u00132!\u0011\t\tja\u0017\n\t\ru\u00131\u0013\u0002\u0004\u0003:L\u0018a\u0005(p]j+\'o\u001c$j]&$X\rR8vE2,\u0007cAAW/N\u0019qk!\u001a\u0011\t\u0005E5qM\u0005\u0005\u0007S\n\u0019J\u0001\u0004B]f\u0014VM\u001a\u000b\u0003\u0007C\n\u0001\"T1y-\u0006dW/Z\u0001\n\u001b\u0006Dh+\u00197vK\u0002\n\u0001\"T5o-\u0006dW/Z\u0001\n\u001b&tg+\u00197vK\u0002\nAA\u001a:p[R!1\u0011PB@!\u0019\t\tja\u001f\u0002,&!1QPAJ\u0005\u0019y\u0005\u000f^5p]\"9\u00111T/A\u0002\u0005}E\u0003BAV\u0007\u0007Cq!a\'_\u0001\u0004\ty*A\u0006uefLgn\u001a,bY&$G\u0003BBE\u0007+\u0003baa#\u0004\u0012\u0006-VBABG\u0015\u0011\u0019y)a%\u0002\tU$\u0018\u000e\\\u0005\u0005\u0007\'\u001biIA\u0002UefDq!a\'`\u0001\u0004\ty*\u0001\u0006qCN\u001cxJ]#mg\u0016,Baa\'\u0004,R!1QTB^)\u0011\u0019yja.\u0011\r\r\u000561UBT\u001b\t\t\u0019)\u0003\u0003\u0004&\u0006\r%A\u0003,bY&$\u0017\r^5p]B!1\u0011VBV\u0019\u0001!qa!,a\u0005\u0004\u0019yKA\u0001F#\u0011\u0019\tl!\u0017\u0011\t\u0005E51W\u0005\u0005\u0007k\u000b\u0019JA\u0004O_RD\u0017N\\4\t\u000f\r\u0015\u0003\r1\u0001\u0004:BA\u0011\u0011SB%\u0003?\u001b9\u000bC\u0004\u0002\u001c\u0002\u0004\r!a(\u0002\u0015\u001d|w\u000eZ(s\u000b2\u001cX-\u0006\u0003\u0004B\u000e5G\u0003BBb\u0007+$Ba!2\u0004RBA1\u0011UBd\u0003W\u001bY-\u0003\u0003\u0004J\u0006\r%AA(s!\u0011\u0019Ik!4\u0005\u000f\r=\u0017M1\u0001\u00040\n\t!\tC\u0004\u0004F\u0005\u0004\raa5\u0011\u0011\u0005E5\u0011JAP\u0007\u0017Dq!a\'b\u0001\u0004\ty*A\u0006sS\u001eDGo\u0014:FYN,W\u0003BBn\u0007g$Ba!8\u0004|R!1q\\B|!!\u0019\toa;\u0004r\u0006-f\u0002BBr\u0007OtA!a/\u0004f&\u0011\u0011QS\u0005\u0005\u0007S\f\u0019*A\u0004qC\u000e\\\u0017mZ3\n\t\r58q\u001e\u0002\u0007\u000b&$\b.\u001a:\u000b\t\r%\u00181\u0013\t\u0005\u0007S\u001b\u0019\u0010B\u0004\u0004v\n\u0014\raa,\u0003\u00031Cqa!\u0012c\u0001\u0004\u0019I\u0010\u0005\u0005\u0002\u0012\u000e%\u0013qTBy\u0011\u001d\tYJ\u0019a\u0001\u0003?\u000bq![:WC2LG\r\u0006\u0003\u0003\u001c\u0011\u0005\u0001bBANG\u0002\u0007\u0011qT\u0001\u000bMJ|Wn\u0014:FYN,GCBAV\t\u000f!I\u0001C\u0004\u0002\u001c\u0012\u0004\r!a(\t\u0011\u0011-A\r\"a\u0001\t\u001b\tq\u0001Z3gCVdG\u000f\u0005\u0004\u0002\u0012\u0012=\u00111V\u0005\u0005\t#\t\u0019J\u0001\u0005=Eft\u0017-\\3?\u0003\u0015\t\u0007\u000f\u001d7z)\u0011\tY\u000bb\u0006\t\u000f\u0005mU\r1\u0001\u0002 \"*Q\rb\u0007\u00050A!AQ\u0004C\u0016\u001b\t!yB\u0003\u0003\u0005\"\u0011\r\u0012\u0001C5oi\u0016\u0014h.\u00197\u000b\t\u0011\u0015BqE\u0001\u0007[\u0006\u001c\'o\\:\u000b\t\u0011%\u00121S\u0001\be\u00164G.Z2u\u0013\u0011!i\u0003b\b\u0003\u00135\f7M]8J[Bd\u0017\'E\u0010\u00052\u0011MBq\u0007C%\t3\")\u0007b\u001e\u0005\b.\u0001\u0011g\u0002\u0013\u00052\u0005-EQG\u0001\u0006[\u0006\u001c\'o\\\u0019\b-\u0011EB\u0011\bC!c\u0015)C1\bC\u001f\u001f\t!i$\t\u0002\u0005@\u0005YQ.Y2s_\u0016sw-\u001b8fc\u0015)C1\tC#\u001f\t!)%\t\u0002\u0005H\u0005)co\u000e\u00181A!JW\u000e\u001d7f[\u0016tG/\u001a3!S:\u00043kY1mC\u0002\u0012d&M\u0019/a5j\u0005(K\u0019\b-\u0011EB1\nC*c\u0015)CQ\nC(\u001f\t!y%\t\u0002\u0005R\u0005A\u0011n\u001d\"v]\u0012dW-M\u0003&\t+\"9f\u0004\u0002\u0005Xe\t\u0001!M\u0004\u0017\tc!Y\u0006b\u00192\u000b\u0015\"i\u0006b\u0018\u0010\u0005\u0011}\u0013E\u0001C1\u0003)I7O\u00117bG.\u0014w\u000e_\u0019\u0006K\u0011UCqK\u0019\b-\u0011EBq\rC8c\u0015)C\u0011\u000eC6\u001f\t!Y\'\t\u0002\u0005n\u0005I1\r\\1tg:\u000bW.Z\u0019\u0006K\u0011ED1O\b\u0003\tg\n#\u0001\"\u001e\u0002_=\u0014xML:dC2\f7\r^5d]\u0005t\u0017P^1mg:ruN\u001c.fe>4\u0015N\\5uK\u0012{WO\u00197f\u001b\u0006\u001c\'o\u001c\u00132\u000fY!\t\u0004\"\u001f\u0005\u0002F*Q\u0005b\u001f\u0005~=\u0011AQP\u0011\u0003\t\u007f\n!\"\\3uQ>$g*Y7fc\u0015)C1\u0011CC\u001f\t!))\t\u0002\u0005\u0014E:a\u0003\"\r\u0005\n\u0012E\u0015\'B\u0013\u0005\f\u00125uB\u0001CGC\t!y)A\u0005tS\u001et\u0017\r^;sKFJq\u0004\"\r\u0005\u0014\u0012\u0005F1V\u0019\bI\u0011EBQ\u0013CL\u0013\u0011!9\n\"\'\u0002\t1K7\u000f\u001e\u0006\u0005\t7#i*A\u0005j[6,H/\u00192mK*!AqTAJ\u0003)\u0019w\u000e\u001c7fGRLwN\\\u0019\b?\u0011EB1\u0015CSc\u001d!C\u0011\u0007CK\t/\u000bT!\nCT\tS{!\u0001\"+\u001e\u0003}\u0010ta\bC\u0019\t[#y+M\u0004%\tc!)\nb&2\u000b\u0015\"\t\fb-\u0010\u0005\u0011MV$\u0001\u0000\u0002\u001b]LG-\u001a8U_\u0012{WO\u00197f)\u0011\ty\n\"/\t\u000f\u0011mf\r1\u0001\u0002,\u0006\u0019\u0001o\\:\u0002)]LG-\u001a8U_:{gNW3s_\u0012{WO\u00197f)\u0011!\t\rb2\u0011\t\u00055F1Y\u0005\u0005\t\u000b\fyHA\u0007O_:TVM]8E_V\u0014G.\u001a\u0005\b\tw;\u0007\u0019AAV\u0003!y\'\u000fZ3sS:<WC\u0001Cg!\u0019\u0019\t\u000fb4\u0002,&!A\u0011[Bx\u0005!y%\u000fZ3sS:<\u0017!C8sI\u0016\u0014\u0018N\\4!\u0003Ai\u0015N\u001c)pg&$\u0018N^3WC2,X-A\tNS:\u0004vn]5uSZ,g+\u00197vK\u0002\n!\u0003^8TiJLgn\u001a\u0013fqR,gn]5p]R!\u00111\u0017Co\u0011\u001d!y\u000e\u001ca\u0001\u0003W\u000bQ\u0001\n;iSN\f\u0001\u0003^8CsR,G%\u001a=uK:\u001c\u0018n\u001c8\u0015\t\u0005=GQ\u001d\u0005\b\t?l\u0007\u0019AAV\u0003E!xn\u00155peR$S\r\u001f;f]NLwN\u001c\u000b\u0005\u00033$Y\u000fC\u0004\u0005`:\u0004\r!a+\u0002!Q|7\t[1sI\u0015DH/\u001a8tS>tG\u0003BAr\tcDq\u0001b8p\u0001\u0004\tY+A\bu_&sG\u000fJ3yi\u0016t7/[8o)\u0011\ti\u000fb>\t\u000f\u0011}\u0007\u000f1\u0001\u0002,\u0006\u0001Bo\u001c\'p]\u001e$S\r\u001f;f]NLwN\u001c\u000b\u0005\u0003o$i\u0010C\u0004\u0005`F\u0004\r!a+\u0002#Q|g\t\\8bi\u0012*\u0007\u0010^3og&|g\u000e\u0006\u0003\u0003\u0002\u0015\r\u0001b\u0002Cpe\u0002\u0007\u00111V\u0001\u0013i>$u.\u001e2mK\u0012*\u0007\u0010^3og&|g\u000e\u0006\u0003\u0002 \u0016%\u0001b\u0002Cpg\u0002\u0007\u00111V\u0001\u0016k:\f\'/_0%a2,8\u000fJ3yi\u0016t7/[8o)\u0011\tY+b\u0004\t\u000f\u0011}G\u000f1\u0001\u0002,\u00061RO\\1ss~#S.\u001b8vg\u0012*\u0007\u0010^3og&|g\u000e\u0006\u0003\u0002,\u0016U\u0001b\u0002Cpk\u0002\u0007\u00111V\u0001\u0010IAdWo\u001d\u0013fqR,gn]5p]R!Q1DC\u0010)\u0011\t),\"\b\t\u000f\tUa\u000f1\u0001\u00026\"9Aq\u001c<A\u0002\u0005-\u0016a\u0004\u0013mKN\u001cH%\u001a=uK:\u001c\u0018n\u001c8\u0015\t\u0015\u0015R\u0011\u0006\u000b\u0005\u00057)9\u0003C\u0004\u0003\u0016]\u0004\r!a4\t\u000f\u0011}w\u000f1\u0001\u0002,R!QQFC\u0019)\u0011\u0011Y\"b\f\t\u000f\tU\u0001\u00101\u0001\u0002Z\"9Aq\u001c=A\u0002\u0005-F\u0003BC\u001b\u000bs!BAa\u0007\u00068!9!QC=A\u0002\u0005\r\bb\u0002Cps\u0002\u0007\u00111\u0016\u000b\u0005\u000b{)\t\u0005\u0006\u0003\u0003\u001c\u0015}\u0002b\u0002B\u000bu\u0002\u0007\u0011Q\u001e\u0005\b\t?T\b\u0019AAV)\u0011))%\"\u0013\u0015\t\tmQq\t\u0005\b\u0005+Y\b\u0019AA|\u0011\u001d!yn\u001fa\u0001\u0003W#B!\"\u0014\u0006RQ!!1DC(\u0011\u001d\u0011)\u0002 a\u0001\u0005\u0003Aq\u0001b8}\u0001\u0004\tY\u000b\u0006\u0003\u0006V\u0015eC\u0003\u0002B\u000e\u000b/BqA!\u0006~\u0001\u0004\ty\nC\u0004\u0005`v\u0004\r!a+\u0002%\u0011bWm]:%KF$S\r\u001f;f]NLwN\u001c\u000b\u0005\u000b?*\u0019\u0007\u0006\u0003\u0003\u001c\u0015\u0005\u0004b\u0002B\u000b}\u0002\u0007\u0011q\u001a\u0005\b\t?t\b\u0019AAV)\u0011)9\'b\u001b\u0015\t\tmQ\u0011\u000e\u0005\b\u0005+y\b\u0019AAm\u0011\u001d!yn a\u0001\u0003W#B!b\u001c\u0006tQ!!1DC9\u0011!\u0011)\"!\u0001A\u0002\u0005\r\b\u0002\u0003Cp\u0003\u0003\u0001\r!a+\u0015\t\u0015]T1\u0010\u000b\u0005\u00057)I\b\u0003\u0005\u0003\u0016\u0005\r\u0001\u0019AAw\u0011!!y.a\u0001A\u0002\u0005-F\u0003BC@\u000b\u0007#BAa\u0007\u0006\u0002\"A!QCA\u0003\u0001\u0004\t9\u0010\u0003\u0005\u0005`\u0006\u0015\u0001\u0019AAV)\u0011)9)b#\u0015\t\tmQ\u0011\u0012\u0005\t\u0005+\t9\u00011\u0001\u0003\u0002!AAq\\A\u0004\u0001\u0004\tY\u000b\u0006\u0003\u0006\u0010\u0016ME\u0003\u0002B\u000e\u000b#C\u0001B!\u0006\u0002\n\u0001\u0007\u0011q\u0014\u0005\t\t?\fI\u00011\u0001\u0002,\u0006\u0011Be\u001a:fCR,\'\u000fJ3yi\u0016t7/[8o)\u0011)I*\"(\u0015\t\tmQ1\u0014\u0005\t\u0005+\tY\u00011\u0001\u0002P\"AAq\\A\u0006\u0001\u0004\tY\u000b\u0006\u0003\u0006\"\u0016\u0015F\u0003\u0002B\u000e\u000bGC\u0001B!\u0006\u0002\u000e\u0001\u0007\u0011\u0011\u001c\u0005\t\t?\fi\u00011\u0001\u0002,R!Q\u0011VCW)\u0011\u0011Y\"b+\t\u0011\tU\u0011q\u0002a\u0001\u0003GD\u0001\u0002b8\u0002\u0010\u0001\u0007\u00111\u0016\u000b\u0005\u000bc+)\f\u0006\u0003\u0003\u001c\u0015M\u0006\u0002\u0003B\u000b\u0003#\u0001\r!!<\t\u0011\u0011}\u0017\u0011\u0003a\u0001\u0003W#B!\"/\u0006>R!!1DC^\u0011!\u0011)\"a\u0005A\u0002\u0005]\b\u0002\u0003Cp\u0003\'\u0001\r!a+\u0015\t\u0015\u0005WQ\u0019\u000b\u0005\u00057)\u0019\r\u0003\u0005\u0003\u0016\u0005U\u0001\u0019\u0001B\u0001\u0011!!y.!\u0006A\u0002\u0005-F\u0003BCe\u000b\u001b$BAa\u0007\u0006L\"A!QCA\f\u0001\u0004\ty\n\u0003\u0005\u0005`\u0006]\u0001\u0019AAV\u0003U!sM]3bi\u0016\u0014H%Z9%Kb$XM\\:j_:$B!b5\u0006XR!!1DCk\u0011!\u0011)\"!\u0007A\u0002\u0005=\u0007\u0002\u0003Cp\u00033\u0001\r!a+\u0015\t\u0015mWq\u001c\u000b\u0005\u00057)i\u000e\u0003\u0005\u0003\u0016\u0005m\u0001\u0019AAm\u0011!!y.a\u0007A\u0002\u0005-F\u0003BCr\u000bO$BAa\u0007\u0006f\"A!QCA\u000f\u0001\u0004\t\u0019\u000f\u0003\u0005\u0005`\u0006u\u0001\u0019AAV)\u0011)Y/b<\u0015\t\tmQQ\u001e\u0005\t\u0005+\ty\u00021\u0001\u0002n\"AAq\\A\u0010\u0001\u0004\tY\u000b\u0006\u0003\u0006t\u0016]H\u0003\u0002B\u000e\u000bkD\u0001B!\u0006\u0002\"\u0001\u0007\u0011q\u001f\u0005\t\t?\f\t\u00031\u0001\u0002,R!Q1`C\u0000)\u0011\u0011Y\"\"@\t\u0011\tU\u00111\u0005a\u0001\u0005\u0003A\u0001\u0002b8\u0002$\u0001\u0007\u00111\u0016\u000b\u0005\r\u000719\u0001\u0006\u0003\u0003\u001c\u0019\u0015\u0001\u0002\u0003B\u000b\u0003K\u0001\r!a(\t\u0011\u0011}\u0017Q\u0005a\u0001\u0003W#BAb\u0003\u0007\u0010Q!\u0011q\u0014D\u0007\u0011!\u0011)\"a\nA\u0002\u0005=\u0007\u0002\u0003Cp\u0003O\u0001\r!a+\u0015\t\u0019Maq\u0003\u000b\u0005\u0003?3)\u0002\u0003\u0005\u0003\u0016\u0005%\u0002\u0019AAm\u0011!!y.!\u000bA\u0002\u0005-F\u0003\u0002D\u000e\r?!B!a(\u0007\u001e!A!QCA\u0016\u0001\u0004\t\u0019\u000f\u0003\u0005\u0005`\u0006-\u0002\u0019AAV)\u00111\u0019Cb\n\u0015\t\u0005}eQ\u0005\u0005\t\u0005+\ti\u00031\u0001\u0002n\"AAq\\A\u0017\u0001\u0004\tY\u000b\u0006\u0003\u0007,\u0019=B\u0003BAP\r[A\u0001B!\u0006\u00020\u0001\u0007\u0011q\u001f\u0005\t\t?\fy\u00031\u0001\u0002,R!a1\u0007D\u001c)\u0011\tyJ\"\u000e\t\u0011\tU\u0011\u0011\u0007a\u0001\u0005\u0003A\u0001\u0002b8\u00022\u0001\u0007\u00111\u0016\u000b\u0005\rw1y\u0004\u0006\u0003\u0002 \u001au\u0002\u0002\u0003B\u000b\u0003g\u0001\r!a(\t\u0011\u0011}\u00171\u0007a\u0001\u0003W\u000b\u0001\u0003J7j]V\u001cH%\u001a=uK:\u001c\u0018n\u001c8\u0015\t\u0019\u0015c\u0011\n\u000b\u0005\u0003?39\u0005\u0003\u0005\u0003\u0016\u0005U\u0002\u0019AAh\u0011!!y.!\u000eA\u0002\u0005-F\u0003\u0002D\'\r#\"B!a(\u0007P!A!QCA\u001c\u0001\u0004\tI\u000e\u0003\u0005\u0005`\u0006]\u0002\u0019AAV)\u00111)F\"\u0017\u0015\t\u0005}eq\u000b\u0005\t\u0005+\tI\u00041\u0001\u0002d\"AAq\\A\u001d\u0001\u0004\tY\u000b\u0006\u0003\u0007^\u0019\u0005D\u0003BAP\r?B\u0001B!\u0006\u0002<\u0001\u0007\u0011Q\u001e\u0005\t\t?\fY\u00041\u0001\u0002,R!aQ\rD5)\u0011\tyJb\u001a\t\u0011\tU\u0011Q\ba\u0001\u0003oD\u0001\u0002b8\u0002>\u0001\u0007\u00111\u0016\u000b\u0005\r[2\t\b\u0006\u0003\u0002 \u001a=\u0004\u0002\u0003B\u000b\u0003\u007f\u0001\rA!\u0001\t\u0011\u0011}\u0017q\ba\u0001\u0003W#BA\"\u001e\u0007zQ!\u0011q\u0014D<\u0011!\u0011)\"!\u0011A\u0002\u0005}\u0005\u0002\u0003Cp\u0003\u0003\u0002\r!a+\u0002!\u0011\"\u0018.\\3tI\u0015DH/\u001a8tS>tG\u0003\u0002D@\r\u0007#B!a(\u0007\u0002\"A!QCA\"\u0001\u0004\ty\r\u0003\u0005\u0005`\u0006\r\u0003\u0019AAV)\u001119Ib#\u0015\t\u0005}e\u0011\u0012\u0005\t\u0005+\t)\u00051\u0001\u0002Z\"AAq\\A#\u0001\u0004\tY\u000b\u0006\u0003\u0007\u0010\u001aME\u0003BAP\r#C\u0001B!\u0006\u0002H\u0001\u0007\u00111\u001d\u0005\t\t?\f9\u00051\u0001\u0002,R!aq\u0013DN)\u0011\tyJ\"\'\t\u0011\tU\u0011\u0011\na\u0001\u0003[D\u0001\u0002b8\u0002J\u0001\u0007\u00111\u0016\u000b\u0005\r?3\u0019\u000b\u0006\u0003\u0002 \u001a\u0005\u0006\u0002\u0003B\u000b\u0003\u0017\u0002\r!a>\t\u0011\u0011}\u00171\na\u0001\u0003W#BAb*\u0007,R!\u0011q\u0014DU\u0011!\u0011)\"!\u0014A\u0002\t\u0005\u0001\u0002\u0003Cp\u0003\u001b\u0002\r!a+\u0015\t\u0019=f1\u0017\u000b\u0005\u0003?3\t\f\u0003\u0005\u0003\u0016\u0005=\u0003\u0019AAP\u0011!!y.a\u0014A\u0002\u0005-\u0016A\u0004\u0013eSZ$S\r\u001f;f]NLwN\u001c\u000b\u0005\rs3i\f\u0006\u0003\u0002 \u001am\u0006\u0002\u0003B\u000b\u0003#\u0002\r!a4\t\u0011\u0011}\u0017\u0011\u000ba\u0001\u0003W#BA\"1\u0007FR!\u0011q\u0014Db\u0011!\u0011)\"a\u0015A\u0002\u0005e\u0007\u0002\u0003Cp\u0003\'\u0002\r!a+\u0015\t\u0019%gQ\u001a\u000b\u0005\u0003?3Y\r\u0003\u0005\u0003\u0016\u0005U\u0003\u0019AAr\u0011!!y.!\u0016A\u0002\u0005-F\u0003\u0002Di\r+$B!a(\u0007T\"A!QCA,\u0001\u0004\ti\u000f\u0003\u0005\u0005`\u0006]\u0003\u0019AAV)\u00111IN\"8\u0015\t\u0005}e1\u001c\u0005\t\u0005+\tI\u00061\u0001\u0002x\"AAq\\A-\u0001\u0004\tY\u000b\u0006\u0003\u0007b\u001a\u0015H\u0003BAP\rGD\u0001B!\u0006\u0002\\\u0001\u0007!\u0011\u0001\u0005\t\t?\fY\u00061\u0001\u0002,R!a\u0011\u001eDw)\u0011\tyJb;\t\u0011\tU\u0011Q\fa\u0001\u0003?C\u0001\u0002b8\u0002^\u0001\u0007\u00111V\u0001\u0013IA,\'oY3oi\u0012*\u0007\u0010^3og&|g\u000e\u0006\u0003\u0007t\u001a]H\u0003BAP\rkD\u0001B!\u0006\u0002`\u0001\u0007\u0011q\u001a\u0005\t\t?\fy\u00061\u0001\u0002,R!a1 D\u0000)\u0011\tyJ\"@\t\u0011\tU\u0011\u0011\ra\u0001\u00033D\u0001\u0002b8\u0002b\u0001\u0007\u00111\u0016\u000b\u0005\u000f\u000799\u0001\u0006\u0003\u0002 \u001e\u0015\u0001\u0002\u0003B\u000b\u0003G\u0002\r!a9\t\u0011\u0011}\u00171\ra\u0001\u0003W#Bab\u0003\b\u0010Q!\u0011qTD\u0007\u0011!\u0011)\"!\u001aA\u0002\u00055\b\u0002\u0003Cp\u0003K\u0002\r!a+\u0015\t\u001dMqq\u0003\u000b\u0005\u0003?;)\u0002\u0003\u0005\u0003\u0016\u0005\u001d\u0004\u0019AA|\u0011!!y.a\u001aA\u0002\u0005-F\u0003BD\u000e\u000f?!B!a(\b\u001e!A!QCA5\u0001\u0004\u0011\t\u0001\u0003\u0005\u0005`\u0006%\u0004\u0019AAV)\u00119\u0019cb\n\u0015\t\u0005}uQ\u0005\u0005\t\u0005+\tY\u00071\u0001\u0002 \"AAq\\A6\u0001\u0004\tY+A\u0007nCb$S\r\u001f;f]NLwN\u001c\u000b\u0005\u000f[9\t\u0004\u0006\u0003\u0002,\u001e=\u0002\u0002CB\u0018\u0003[\u0002\r!a+\t\u0011\u0011}\u0017Q\u000ea\u0001\u0003W\u000bQ\"\\5oI\u0015DH/\u001a8tS>tG\u0003BD\u001c\u000fw!B!a+\b:!A1qFA8\u0001\u0004\tY\u000b\u0003\u0005\u0005`\u0006=\u0004\u0019AAV\u0003EI7o\u00165pY\u0016$S\r\u001f;f]NLwN\u001c\u000b\u0005\u000579\t\u0005\u0003\u0005\u0005`\u0006E\u0004\u0019AAV\u0003M!xNU1eS\u0006t7\u000fJ3yi\u0016t7/[8o)\u0011\tyjb\u0012\t\u0011\u0011}\u00171\u000fa\u0001\u0003W\u000b1\u0003^8EK\u001e\u0014X-Z:%Kb$XM\\:j_:$B!a(\bN!AAq\\A;\u0001\u0004\tY+A\ff]N,(/\u001b8h-\u0006d\u0017\u000e\u001a\u0013fqR,gn]5p]R!q1KD,)\u0011\tYk\"\u0016\t\u0011\r\u0015\u0013q\u000fa\u0001\u0007\u000fB\u0001\u0002b8\u0002x\u0001\u0007\u00111V\u0001\u0013Q\u0006\u001c\bnQ8eK\u0012*\u0007\u0010^3og&|g\u000e\u0006\u0003\u0004P\u001du\u0003\u0002\u0003Cp\u0003s\u0002\r!a+\u0002!\u0015\fX/\u00197tI\u0015DH/\u001a8tS>tG\u0003BD2\u000fO\"BAa\u0007\bf!Q1qKA>\u0003\u0003\u0005\ra!\u0017\t\u0011\u0011}\u00171\u0010a\u0001\u0003W\u0003
    #9 = Utf8               value
   #10 = Utf8               D
   #11 = Utf8               equals$extension
   #12 = Utf8               (DLjava/lang/Object;)Z
   #13 = Utf8               $this
   #14 = Utf8               x$1
   #15 = Utf8               org/scalactic/anyvals/NonZeroFiniteDouble$
   #16 = Class              #15           // org/scalactic/anyvals/NonZeroFiniteDouble$
   #17 = Utf8               MODULE$
   #18 = Utf8               Lorg/scalactic/anyvals/NonZeroFiniteDouble$;
   #19 = NameAndType        #17:#18       // MODULE$:Lorg/scalactic/anyvals/NonZeroFiniteDouble$;
   #20 = Fieldref           #16.#19       // org/scalactic/anyvals/NonZeroFiniteDouble$.MODULE$:Lorg/scalactic/anyvals/NonZeroFiniteDouble$;
   #21 = NameAndType        #11:#12       // equals$extension:(DLjava/lang/Object;)Z
   #22 = Methodref          #16.#21       // org/scalactic/anyvals/NonZeroFiniteDouble$.equals$extension:(DLjava/lang/Object;)Z
   #23 = Utf8               Ljava/lang/Object;
   #24 = Utf8               hashCode$extension
   #25 = Utf8               (D)I
   #26 = NameAndType        #24:#25       // hashCode$extension:(D)I
   #27 = Methodref          #16.#26       // org/scalactic/anyvals/NonZeroFiniteDouble$.hashCode$extension:(D)I
   #28 = Utf8               ensuringValid$extension
   #29 = Utf8               (DLscala/Function1;)D
   #30 = Utf8               f
   #31 = NameAndType        #28:#29       // ensuringValid$extension:(DLscala/Function1;)D
   #32 = Methodref          #16.#31       // org/scalactic/anyvals/NonZeroFiniteDouble$.ensuringValid$extension:(DLscala/Function1;)D
   #33 = Utf8               Lscala/Function1;
   #34 = Utf8               toDegrees$extension
   #35 = Utf8               (D)D
   #36 = NameAndType        #34:#35       // toDegrees$extension:(D)D
   #37 = Methodref          #16.#36       // org/scalactic/anyvals/NonZeroFiniteDouble$.toDegrees$extension:(D)D
   #38 = Utf8               toRadians$extension
   #39 = NameAndType        #38:#35       // toRadians$extension:(D)D
   #40 = Methodref          #16.#39       // org/scalactic/anyvals/NonZeroFiniteDouble$.toRadians$extension:(D)D
   #41 = Utf8               isWhole$extension
   #42 = Utf8               (D)Z
   #43 = NameAndType        #41:#42       // isWhole$extension:(D)Z
   #44 = Methodref          #16.#43       // org/scalactic/anyvals/NonZeroFiniteDouble$.isWhole$extension:(D)Z
   #45 = Utf8               min$extension
   #46 = Utf8               (DD)D
   #47 = Utf8               that
   #48 = NameAndType        #45:#46       // min$extension:(DD)D
   #49 = Methodref          #16.#48       // org/scalactic/anyvals/NonZeroFiniteDouble$.min$extension:(DD)D
   #50 = Utf8               max$extension
   #51 = NameAndType        #50:#46       // max$extension:(DD)D
   #52 = Methodref          #16.#51       // org/scalactic/anyvals/NonZeroFiniteDouble$.max$extension:(DD)D
   #53 = Utf8               $percent$extension
   #54 = Utf8               x
   #55 = NameAndType        #53:#46       // $percent$extension:(DD)D
   #56 = Methodref          #16.#55       // org/scalactic/anyvals/NonZeroFiniteDouble$.$percent$extension:(DD)D
   #57 = Utf8               (DF)D
   #58 = NameAndType        #53:#57       // $percent$extension:(DF)D
   #59 = Methodref          #16.#58       // org/scalactic/anyvals/NonZeroFiniteDouble$.$percent$extension:(DF)D
   #60 = Utf8               F
   #61 = Utf8               (DJ)D
   #62 = NameAndType        #53:#61       // $percent$extension:(DJ)D
   #63 = Methodref          #16.#62       // org/scalactic/anyvals/NonZeroFiniteDouble$.$percent$extension:(DJ)D
   #64 = Utf8               J
   #65 = Utf8               (DI)D
   #66 = NameAndType        #53:#65       // $percent$extension:(DI)D
   #67 = Methodref          #16.#66       // org/scalactic/anyvals/NonZeroFiniteDouble$.$percent$extension:(DI)D
   #68 = Utf8               I
   #69 = Utf8               (DC)D
   #70 = NameAndType        #53:#69       // $percent$extension:(DC)D
   #71 = Methodref          #16.#70       // org/scalactic/anyvals/NonZeroFiniteDouble$.$percent$extension:(DC)D
   #72 = Utf8               C
   #73 = Utf8               (DS)D
   #74 = NameAndType        #53:#73       // $percent$extension:(DS)D
   #75 = Methodref          #16.#74       // org/scalactic/anyvals/NonZeroFiniteDouble$.$percent$extension:(DS)D
   #76 = Utf8               S
   #77 = Utf8               (DB)D
   #78 = NameAndType        #53:#77       // $percent$extension:(DB)D
   #79 = Methodref          #16.#78       // org/scalactic/anyvals/NonZeroFiniteDouble$.$percent$extension:(DB)D
   #80 = Utf8               B
   #81 = Utf8               $div$extension
   #82 = NameAndType        #81:#46       // $div$extension:(DD)D
   #83 = Methodref          #16.#82       // org/scalactic/anyvals/NonZeroFiniteDouble$.$div$extension:(DD)D
   #84 = NameAndType        #81:#57       // $div$extension:(DF)D
   #85 = Methodref          #16.#84       // org/scalactic/anyvals/NonZeroFiniteDouble$.$div$extension:(DF)D
   #86 = NameAndType        #81:#61       // $div$extension:(DJ)D
   #87 = Methodref          #16.#86       // org/scalactic/anyvals/NonZeroFiniteDouble$.$div$extension:(DJ)D
   #88 = NameAndType        #81:#65       // $div$extension:(DI)D
   #89 = Methodref          #16.#88       // org/scalactic/anyvals/NonZeroFiniteDouble$.$div$extension:(DI)D
   #90 = NameAndType        #81:#69       // $div$extension:(DC)D
   #91 = Methodref          #16.#90       // org/scalactic/anyvals/NonZeroFiniteDouble$.$div$extension:(DC)D
   #92 = NameAndType        #81:#73       // $div$extension:(DS)D
   #93 = Methodref          #16.#92       // org/scalactic/anyvals/NonZeroFiniteDouble$.$div$extension:(DS)D
   #94 = NameAndType        #81:#77       // $div$extension:(DB)D
   #95 = Methodref          #16.#94       // org/scalactic/anyvals/NonZeroFiniteDouble$.$div$extension:(DB)D
   #96 = Utf8               $times$extension
   #97 = NameAndType        #96:#46       // $times$extension:(DD)D
   #98 = Methodref          #16.#97       // org/scalactic/anyvals/NonZeroFiniteDouble$.$times$extension:(DD)D
   #99 = NameAndType        #96:#57       // $times$extension:(DF)D
  #100 = Methodref          #16.#99       // org/scalactic/anyvals/NonZeroFiniteDouble$.$times$extension:(DF)D
  #101 = NameAndType        #96:#61       // $times$extension:(DJ)D
  #102 = Methodref          #16.#101      // org/scalactic/anyvals/NonZeroFiniteDouble$.$times$extension:(DJ)D
  #103 = NameAndType        #96:#65       // $times$extension:(DI)D
  #104 = Methodref          #16.#103      // org/scalactic/anyvals/NonZeroFiniteDouble$.$times$extension:(DI)D
  #105 = NameAndType        #96:#69       // $times$extension:(DC)D
  #106 = Methodref          #16.#105      // org/scalactic/anyvals/NonZeroFiniteDouble$.$times$extension:(DC)D
  #107 = NameAndType        #96:#73       // $times$extension:(DS)D
  #108 = Methodref          #16.#107      // org/scalactic/anyvals/NonZeroFiniteDouble$.$times$extension:(DS)D
  #109 = NameAndType        #96:#77       // $times$extension:(DB)D
  #110 = Methodref          #16.#109      // org/scalactic/anyvals/NonZeroFiniteDouble$.$times$extension:(DB)D
  #111 = Utf8               $minus$extension
  #112 = NameAndType        #111:#46      // $minus$extension:(DD)D
  #113 = Methodref          #16.#112      // org/scalactic/anyvals/NonZeroFiniteDouble$.$minus$extension:(DD)D
  #114 = NameAndType        #111:#57      // $minus$extension:(DF)D
  #115 = Methodref          #16.#114      // org/scalactic/anyvals/NonZeroFiniteDouble$.$minus$extension:(DF)D
  #116 = NameAndType        #111:#61      // $minus$extension:(DJ)D
  #117 = Methodref          #16.#116      // org/scalactic/anyvals/NonZeroFiniteDouble$.$minus$extension:(DJ)D
  #118 = NameAndType        #111:#65      // $minus$extension:(DI)D
  #119 = Methodref          #16.#118      // org/scalactic/anyvals/NonZeroFiniteDouble$.$minus$extension:(DI)D
  #120 = NameAndType        #111:#69      // $minus$extension:(DC)D
  #121 = Methodref          #16.#120      // org/scalactic/anyvals/NonZeroFiniteDouble$.$minus$extension:(DC)D
  #122 = NameAndType        #111:#73      // $minus$extension:(DS)D
  #123 = Methodref          #16.#122      // org/scalactic/anyvals/NonZeroFiniteDouble$.$minus$extension:(DS)D
  #124 = NameAndType        #111:#77      // $minus$extension:(DB)D
  #125 = Methodref          #16.#124      // org/scalactic/anyvals/NonZeroFiniteDouble$.$minus$extension:(DB)D
  #126 = Utf8               $plus$extension
  #127 = NameAndType        #126:#46      // $plus$extension:(DD)D
  #128 = Methodref          #16.#127      // org/scalactic/anyvals/NonZeroFiniteDouble$.$plus$extension:(DD)D
  #129 = NameAndType        #126:#57      // $plus$extension:(DF)D
  #130 = Methodref          #16.#129      // org/scalactic/anyvals/NonZeroFiniteDouble$.$plus$extension:(DF)D
  #131 = NameAndType        #126:#61      // $plus$extension:(DJ)D
  #132 = Methodref          #16.#131      // org/scalactic/anyvals/NonZeroFiniteDouble$.$plus$extension:(DJ)D
  #133 = NameAndType        #126:#65      // $plus$extension:(DI)D
  #134 = Methodref          #16.#133      // org/scalactic/anyvals/NonZeroFiniteDouble$.$plus$extension:(DI)D
  #135 = NameAndType        #126:#69      // $plus$extension:(DC)D
  #136 = Methodref          #16.#135      // org/scalactic/anyvals/NonZeroFiniteDouble$.$plus$extension:(DC)D
  #137 = NameAndType        #126:#73      // $plus$extension:(DS)D
  #138 = Methodref          #16.#137      // org/scalactic/anyvals/NonZeroFiniteDouble$.$plus$extension:(DS)D
  #139 = NameAndType        #126:#77      // $plus$extension:(DB)D
  #140 = Methodref          #16.#139      // org/scalactic/anyvals/NonZeroFiniteDouble$.$plus$extension:(DB)D
  #141 = Utf8               $greater$eq$extension
  #142 = Utf8               (DD)Z
  #143 = NameAndType        #141:#142     // $greater$eq$extension:(DD)Z
  #144 = Methodref          #16.#143      // org/scalactic/anyvals/NonZeroFiniteDouble$.$greater$eq$extension:(DD)Z
  #145 = Utf8               (DF)Z
  #146 = NameAndType        #141:#145     // $greater$eq$extension:(DF)Z
  #147 = Methodref          #16.#146      // org/scalactic/anyvals/NonZeroFiniteDouble$.$greater$eq$extension:(DF)Z
  #148 = Utf8               (DJ)Z
  #149 = NameAndType        #141:#148     // $greater$eq$extension:(DJ)Z
  #150 = Methodref          #16.#149      // org/scalactic/anyvals/NonZeroFiniteDouble$.$greater$eq$extension:(DJ)Z
  #151 = Utf8               (DI)Z
  #152 = NameAndType        #141:#151     // $greater$eq$extension:(DI)Z
  #153 = Methodref          #16.#152      // org/scalactic/anyvals/NonZeroFiniteDouble$.$greater$eq$extension:(DI)Z
  #154 = Utf8               (DC)Z
  #155 = NameAndType        #141:#154     // $greater$eq$extension:(DC)Z
  #156 = Methodref          #16.#155      // org/scalactic/anyvals/NonZeroFiniteDouble$.$greater$eq$extension:(DC)Z
  #157 = Utf8               (DS)Z
  #158 = NameAndType        #141:#157     // $greater$eq$extension:(DS)Z
  #159 = Methodref          #16.#158      // org/scalactic/anyvals/NonZeroFiniteDouble$.$greater$eq$extension:(DS)Z
  #160 = Utf8               (DB)Z
  #161 = NameAndType        #141:#160     // $greater$eq$extension:(DB)Z
  #162 = Methodref          #16.#161      // org/scalactic/anyvals/NonZeroFiniteDouble$.$greater$eq$extension:(DB)Z
  #163 = Utf8               $greater$extension
  #164 = NameAndType        #163:#142     // $greater$extension:(DD)Z
  #165 = Methodref          #16.#164      // org/scalactic/anyvals/NonZeroFiniteDouble$.$greater$extension:(DD)Z
  #166 = NameAndType        #163:#145     // $greater$extension:(DF)Z
  #167 = Methodref          #16.#166      // org/scalactic/anyvals/NonZeroFiniteDouble$.$greater$extension:(DF)Z
  #168 = NameAndType        #163:#148     // $greater$extension:(DJ)Z
  #169 = Methodref          #16.#168      // org/scalactic/anyvals/NonZeroFiniteDouble$.$greater$extension:(DJ)Z
  #170 = NameAndType        #163:#151     // $greater$extension:(DI)Z
  #171 = Methodref          #16.#170      // org/scalactic/anyvals/NonZeroFiniteDouble$.$greater$extension:(DI)Z
  #172 = NameAndType        #163:#154     // $greater$extension:(DC)Z
  #173 = Methodref          #16.#172      // org/scalactic/anyvals/NonZeroFiniteDouble$.$greater$extension:(DC)Z
  #174 = NameAndType        #163:#157     // $greater$extension:(DS)Z
  #175 = Methodref          #16.#174      // org/scalactic/anyvals/NonZeroFiniteDouble$.$greater$extension:(DS)Z
  #176 = NameAndType        #163:#160     // $greater$extension:(DB)Z
  #177 = Methodref          #16.#176      // org/scalactic/anyvals/NonZeroFiniteDouble$.$greater$extension:(DB)Z
  #178 = Utf8               $less$eq$extension
  #179 = NameAndType        #178:#142     // $less$eq$extension:(DD)Z
  #180 = Methodref          #16.#179      // org/scalactic/anyvals/NonZeroFiniteDouble$.$less$eq$extension:(DD)Z
  #181 = NameAndType        #178:#145     // $less$eq$extension:(DF)Z
  #182 = Methodref          #16.#181      // org/scalactic/anyvals/NonZeroFiniteDouble$.$less$eq$extension:(DF)Z
  #183 = NameAndType        #178:#148     // $less$eq$extension:(DJ)Z
  #184 = Methodref          #16.#183      // org/scalactic/anyvals/NonZeroFiniteDouble$.$less$eq$extension:(DJ)Z
  #185 = NameAndType        #178:#151     // $less$eq$extension:(DI)Z
  #186 = Methodref          #16.#185      // org/scalactic/anyvals/NonZeroFiniteDouble$.$less$eq$extension:(DI)Z
  #187 = NameAndType        #178:#154     // $less$eq$extension:(DC)Z
  #188 = Methodref          #16.#187      // org/scalactic/anyvals/NonZeroFiniteDouble$.$less$eq$extension:(DC)Z
  #189 = NameAndType        #178:#157     // $less$eq$extension:(DS)Z
  #190 = Methodref          #16.#189      // org/scalactic/anyvals/NonZeroFiniteDouble$.$less$eq$extension:(DS)Z
  #191 = NameAndType        #178:#160     // $less$eq$extension:(DB)Z
  #192 = Methodref          #16.#191      // org/scalactic/anyvals/NonZeroFiniteDouble$.$less$eq$extension:(DB)Z
  #193 = Utf8               $less$extension
  #194 = NameAndType        #193:#142     // $less$extension:(DD)Z
  #195 = Methodref          #16.#194      // org/scalactic/anyvals/NonZeroFiniteDouble$.$less$extension:(DD)Z
  #196 = NameAndType        #193:#145     // $less$extension:(DF)Z
  #197 = Methodref          #16.#196      // org/scalactic/anyvals/NonZeroFiniteDouble$.$less$extension:(DF)Z
  #198 = NameAndType        #193:#148     // $less$extension:(DJ)Z
  #199 = Methodref          #16.#198      // org/scalactic/anyvals/NonZeroFiniteDouble$.$less$extension:(DJ)Z
  #200 = NameAndType        #193:#151     // $less$extension:(DI)Z
  #201 = Methodref          #16.#200      // org/scalactic/anyvals/NonZeroFiniteDouble$.$less$extension:(DI)Z
  #202 = NameAndType        #193:#154     // $less$extension:(DC)Z
  #203 = Methodref          #16.#202      // org/scalactic/anyvals/NonZeroFiniteDouble$.$less$extension:(DC)Z
  #204 = NameAndType        #193:#157     // $less$extension:(DS)Z
  #205 = Methodref          #16.#204      // org/scalactic/anyvals/NonZeroFiniteDouble$.$less$extension:(DS)Z
  #206 = NameAndType        #193:#160     // $less$extension:(DB)Z
  #207 = Methodref          #16.#206      // org/scalactic/anyvals/NonZeroFiniteDouble$.$less$extension:(DB)Z
  #208 = Utf8               (DLjava/lang/String;)Ljava/lang/String;
  #209 = NameAndType        #126:#208     // $plus$extension:(DLjava/lang/String;)Ljava/lang/String;
  #210 = Methodref          #16.#209      // org/scalactic/anyvals/NonZeroFiniteDouble$.$plus$extension:(DLjava/lang/String;)Ljava/lang/String;
  #211 = Utf8               Ljava/lang/String;
  #212 = Utf8               unary_$minus$extension
  #213 = NameAndType        #212:#35      // unary_$minus$extension:(D)D
  #214 = Methodref          #16.#213      // org/scalactic/anyvals/NonZeroFiniteDouble$.unary_$minus$extension:(D)D
  #215 = Utf8               unary_$plus$extension
  #216 = NameAndType        #215:#35      // unary_$plus$extension:(D)D
  #217 = Methodref          #16.#216      // org/scalactic/anyvals/NonZeroFiniteDouble$.unary_$plus$extension:(D)D
  #218 = Utf8               toDouble$extension
  #219 = NameAndType        #218:#35      // toDouble$extension:(D)D
  #220 = Methodref          #16.#219      // org/scalactic/anyvals/NonZeroFiniteDouble$.toDouble$extension:(D)D
  #221 = Utf8               toFloat$extension
  #222 = Utf8               (D)F
  #223 = NameAndType        #221:#222     // toFloat$extension:(D)F
  #224 = Methodref          #16.#223      // org/scalactic/anyvals/NonZeroFiniteDouble$.toFloat$extension:(D)F
  #225 = Utf8               toLong$extension
  #226 = Utf8               (D)J
  #227 = NameAndType        #225:#226     // toLong$extension:(D)J
  #228 = Methodref          #16.#227      // org/scalactic/anyvals/NonZeroFiniteDouble$.toLong$extension:(D)J
  #229 = Utf8               toInt$extension
  #230 = NameAndType        #229:#25      // toInt$extension:(D)I
  #231 = Methodref          #16.#230      // org/scalactic/anyvals/NonZeroFiniteDouble$.toInt$extension:(D)I
  #232 = Utf8               toChar$extension
  #233 = Utf8               (D)C
  #234 = NameAndType        #232:#233     // toChar$extension:(D)C
  #235 = Methodref          #16.#234      // org/scalactic/anyvals/NonZeroFiniteDouble$.toChar$extension:(D)C
  #236 = Utf8               toShort$extension
  #237 = Utf8               (D)S
  #238 = NameAndType        #236:#237     // toShort$extension:(D)S
  #239 = Methodref          #16.#238      // org/scalactic/anyvals/NonZeroFiniteDouble$.toShort$extension:(D)S
  #240 = Utf8               toByte$extension
  #241 = Utf8               (D)B
  #242 = NameAndType        #240:#241     // toByte$extension:(D)B
  #243 = Methodref          #16.#242      // org/scalactic/anyvals/NonZeroFiniteDouble$.toByte$extension:(D)B
  #244 = Utf8               toString$extension
  #245 = Utf8               (D)Ljava/lang/String;
  #246 = NameAndType        #244:#245     // toString$extension:(D)Ljava/lang/String;
  #247 = Methodref          #16.#246      // org/scalactic/anyvals/NonZeroFiniteDouble$.toString$extension:(D)Ljava/lang/String;
  #248 = Utf8               MinPositiveValue
  #249 = Utf8               ()D
  #250 = NameAndType        #248:#249     // MinPositiveValue:()D
  #251 = Methodref          #16.#250      // org/scalactic/anyvals/NonZeroFiniteDouble$.MinPositiveValue:()D
  #252 = Utf8               ordering
  #253 = Utf8               ()Lscala/math/Ordering;
  #254 = Utf8               ()Lscala/math/Ordering<Lorg/scalactic/anyvals/NonZeroFiniteDouble;>;
  #255 = NameAndType        #252:#253     // ordering:()Lscala/math/Ordering;
  #256 = Methodref          #16.#255      // org/scalactic/anyvals/NonZeroFiniteDouble$.ordering:()Lscala/math/Ordering;
  #257 = Utf8               widenToNonZeroDouble
  #258 = Utf8               pos
  #259 = NameAndType        #257:#35      // widenToNonZeroDouble:(D)D
  #260 = Methodref          #16.#259      // org/scalactic/anyvals/NonZeroFiniteDouble$.widenToNonZeroDouble:(D)D
  #261 = Utf8               widenToDouble
  #262 = NameAndType        #261:#35      // widenToDouble:(D)D
  #263 = Methodref          #16.#262      // org/scalactic/anyvals/NonZeroFiniteDouble$.widenToDouble:(D)D
  #264 = Utf8               fromOrElse
  #265 = Utf8               (DLscala/Function0;)D
  #266 = Utf8               default
  #267 = NameAndType        #264:#265     // fromOrElse:(DLscala/Function0;)D
  #268 = Methodref          #16.#267      // org/scalactic/anyvals/NonZeroFiniteDouble$.fromOrElse:(DLscala/Function0;)D
  #269 = Utf8               Lscala/Function0;
  #270 = Utf8               isValid
  #271 = NameAndType        #270:#42      // isValid:(D)Z
  #272 = Methodref          #16.#271      // org/scalactic/anyvals/NonZeroFiniteDouble$.isValid:(D)Z
  #273 = Utf8               rightOrElse
  #274 = Utf8               (DLscala/Function1;)Lscala/util/Either;
  #275 = Utf8               <L:Ljava/lang/Object;>(DLscala/Function1<Ljava/lang/Object;TL;>;)Lscala/util/Either<TL;Lorg/scalactic/anyvals/NonZeroFiniteDouble;>;
  #276 = NameAndType        #273:#274     // rightOrElse:(DLscala/Function1;)Lscala/util/Either;
  #277 = Methodref          #16.#276      // org/scalactic/anyvals/NonZeroFiniteDouble$.rightOrElse:(DLscala/Function1;)Lscala/util/Either;
  #278 = Utf8               goodOrElse
  #279 = Utf8               (DLscala/Function1;)Lorg/scalactic/Or;
  #280 = Utf8               <B:Ljava/lang/Object;>(DLscala/Function1<Ljava/lang/Object;TB;>;)Lorg/scalactic/Or<Lorg/scalactic/anyvals/NonZeroFiniteDouble;TB;>;
  #281 = NameAndType        #278:#279     // goodOrElse:(DLscala/Function1;)Lorg/scalactic/Or;
  #282 = Methodref          #16.#281      // org/scalactic/anyvals/NonZeroFiniteDouble$.goodOrElse:(DLscala/Function1;)Lorg/scalactic/Or;
  #283 = Utf8               passOrElse
  #284 = Utf8               (DLscala/Function1;)Lorg/scalactic/Validation;
  #285 = Utf8               <E:Ljava/lang/Object;>(DLscala/Function1<Ljava/lang/Object;TE;>;)Lorg/scalactic/Validation<TE;>;
  #286 = NameAndType        #283:#284     // passOrElse:(DLscala/Function1;)Lorg/scalactic/Validation;
  #287 = Methodref          #16.#286      // org/scalactic/anyvals/NonZeroFiniteDouble$.passOrElse:(DLscala/Function1;)Lorg/scalactic/Validation;
  #288 = Utf8               tryingValid
  #289 = Utf8               (D)Lscala/util/Try;
  #290 = Utf8               (D)Lscala/util/Try<Lorg/scalactic/anyvals/NonZeroFiniteDouble;>;
  #291 = NameAndType        #288:#289     // tryingValid:(D)Lscala/util/Try;
  #292 = Methodref          #16.#291      // org/scalactic/anyvals/NonZeroFiniteDouble$.tryingValid:(D)Lscala/util/Try;
  #293 = Utf8               from
  #294 = Utf8               (D)Lscala/Option;
  #295 = Utf8               (D)Lscala/Option<Lorg/scalactic/anyvals/NonZeroFiniteDouble;>;
  #296 = NameAndType        #293:#294     // from:(D)Lscala/Option;
  #297 = Methodref          #16.#296      // org/scalactic/anyvals/NonZeroFiniteDouble$.from:(D)Lscala/Option;
  #298 = Utf8               MinValue
  #299 = NameAndType        #298:#249     // MinValue:()D
  #300 = Methodref          #16.#299      // org/scalactic/anyvals/NonZeroFiniteDouble$.MinValue:()D
  #301 = Utf8               MaxValue
  #302 = NameAndType        #301:#249     // MaxValue:()D
  #303 = Methodref          #16.#302      // org/scalactic/anyvals/NonZeroFiniteDouble$.MaxValue:()D
  #304 = NameAndType        #9:#10        // value:D
  #305 = Fieldref           #2.#304       // org/scalactic/anyvals/NonZeroFiniteDouble.value:D
  #306 = Utf8               this
  #307 = Utf8               Lorg/scalactic/anyvals/NonZeroFiniteDouble;
  #308 = Utf8               toString
  #309 = Utf8               ()Ljava/lang/String;
  #310 = NameAndType        #9:#249       // value:()D
  #311 = Methodref          #2.#310       // org/scalactic/anyvals/NonZeroFiniteDouble.value:()D
  #312 = Utf8               toByte
  #313 = Utf8               ()B
  #314 = Utf8               toShort
  #315 = Utf8               ()S
  #316 = Utf8               toChar
  #317 = Utf8               ()C
  #318 = Utf8               toInt
  #319 = Utf8               ()I
  #320 = Utf8               toLong
  #321 = Utf8               ()J
  #322 = Utf8               toFloat
  #323 = Utf8               ()F
  #324 = Utf8               toDouble
  #325 = Utf8               unary_$plus
  #326 = Utf8               unary_$minus
  #327 = Utf8               $plus
  #328 = Utf8               (Ljava/lang/String;)Ljava/lang/String;
  #329 = Utf8               $less
  #330 = Utf8               (B)Z
  #331 = Utf8               (S)Z
  #332 = Utf8               (C)Z
  #333 = Utf8               (I)Z
  #334 = Utf8               (J)Z
  #335 = Utf8               (F)Z
  #336 = Utf8               $less$eq
  #337 = Utf8               $greater
  #338 = Utf8               $greater$eq
  #339 = Utf8               (B)D
  #340 = Utf8               (S)D
  #341 = Utf8               (C)D
  #342 = Utf8               (I)D
  #343 = Utf8               (J)D
  #344 = Utf8               (F)D
  #345 = Utf8               $minus
  #346 = Utf8               $times
  #347 = Utf8               $div
  #348 = Utf8               $percent
  #349 = Utf8               max
  #350 = Utf8               min
  #351 = Utf8               isWhole
  #352 = Utf8               ()Z
  #353 = Utf8               toRadians
  #354 = Utf8               toDegrees
  #355 = Utf8               ensuringValid
  #356 = Utf8               (Lscala/Function1;)D
  #357 = Utf8               (Lscala/Function1<Ljava/lang/Object;Ljava/lang/Object;>;)D
  #358 = Utf8               hashCode
  #359 = Utf8               equals
  #360 = Utf8               (Ljava/lang/Object;)Z
  #361 = Utf8               <init>
  #362 = Utf8               (D)V
  #363 = Utf8               ()V
  #364 = NameAndType        #361:#363     // "<init>":()V
  #365 = Methodref          #4.#364       // java/lang/Object."<init>":()V
  #366 = Utf8               Code
  #367 = Utf8               LocalVariableTable
  #368 = Utf8               MethodParameters
  #369 = Utf8               Signature
  #370 = Utf8               LineNumberTable
  #371 = Utf8               SourceFile
  #372 = Utf8               RuntimeVisibleAnnotations
  #373 = Utf8               ScalaInlineInfo
  #374 = Utf8               ScalaSig
{
  private final double value;
    descriptor: D
    flags: (0x0012) ACC_PRIVATE, ACC_FINAL

  public static boolean equals$extension(double, java.lang.Object);
    descriptor: (DLjava/lang/Object;)Z
    flags: (0x0009) ACC_PUBLIC, ACC_STATIC
    Code:
      stack=4, locals=3, args_size=2
         0: getstatic     #20                 // Field org/scalactic/anyvals/NonZeroFiniteDouble$.MODULE$:Lorg/scalactic/anyvals/NonZeroFiniteDouble$;
         3: dload_0
         4: aload_2
         5: invokevirtual #22                 // Method org/scalactic/anyvals/NonZeroFiniteDouble$.equals$extension:(DLjava/lang/Object;)Z
         8: ireturn
      LocalVariableTable:
        Start  Length  Slot  Name   Signature
            0       9     0 $this   D
            0       9     2   x$1   Ljava/lang/Object;
    MethodParameters:
      Name                           Flags
      $this                          final
      x$1                            final

  public static int hashCode$extension(double);
    descriptor: (D)I
    flags: (0x0009) ACC_PUBLIC, ACC_STATIC
    Code:
      stack=3, locals=2, args_size=1
         0: getstatic     #20                 // Field org/scalactic/anyvals/NonZeroFiniteDouble$.MODULE$:Lorg/scalactic/anyvals/NonZeroFiniteDouble$;
         3: dload_0
         4: invokevirtual #27                 // Method org/scalactic/anyvals/NonZeroFiniteDouble$.hashCode$extension:(D)I
         7: ireturn
      LocalVariableTable:
        Start  Length  Slot  Name   Signature
            0       8     0 $this   D
    MethodParameters:
      Name                           Flags
      $this                          final

  public static double ensuringValid$extension(double, scala.Function1);
    descriptor: (DLscala/Function1;)D
    flags: (0x0009) ACC_PUBLIC, ACC_STATIC
    Code:
      stack=4, locals=3, args_size=2
         0: getstatic     #20                 // Field org/scalactic/anyvals/NonZeroFiniteDouble$.MODULE$:Lorg/scalactic/anyvals/NonZeroFiniteDouble$;
         3: dload_0
         4: aload_2
         5: invokevirtual #32                 // Method org/scalactic/anyvals/NonZeroFiniteDouble$.ensuringValid$extension:(DLscala/Function1;)D
         8: dreturn
      LocalVariableTable:
        Start  Length  Slot  Name   Signature
            0       9     0 $this   D
            0       9     2     f   Lscala/Function1;
    MethodParameters:
      Name                           Flags
      $this                          final
      f                              final

  public static double toDegrees$extension(double);
    descriptor: (D)D
    flags: (0x0009) ACC_PUBLIC, ACC_STATIC
    Code:
      stack=3, locals=2, args_size=1
         0: getstatic     #20                 // Field org/scalactic/anyvals/NonZeroFiniteDouble$.MODULE$:Lorg/scalactic/anyvals/NonZeroFiniteDouble$;
         3: dload_0
         4: invokevirtual #37                 // Method org/scalactic/anyvals/NonZeroFiniteDouble$.toDegrees$extension:(D)D
         7: dreturn
      LocalVariableTable:
        Start  Length  Slot  Name   Signature
            0       8     0 $this   D
    MethodParameters:
      Name                           Flags
      $this                          final

  public static double toRadians$extension(double);
    descriptor: (D)D
    flags: (0x0009) ACC_PUBLIC, ACC_STATIC
    Code:
      stack=3, locals=2, args_size=1
         0: getstatic     #20                 // Field org/scalactic/anyvals/NonZeroFiniteDouble$.MODULE$:Lorg/scalactic/anyvals/NonZeroFiniteDouble$;
         3: dload_0
         4: invokevirtual #40                 // Method org/scalactic/anyvals/NonZeroFiniteDouble$.toRadians$extension:(D)D
         7: dreturn
      LocalVariableTable:
        Start  Length  Slot  Name   Signature
            0       8     0 $this   D
    MethodParameters:
      Name                           Flags
      $this                          final

  public static boolean isWhole$extension(double);
    descriptor: (D)Z
    flags: (0x0009) ACC_PUBLIC, ACC_STATIC
    Code:
      stack=3, locals=2, args_size=1
         0: getstatic     #20                 // Field org/scalactic/anyvals/NonZeroFiniteDouble$.MODULE$:Lorg/scalactic/anyvals/NonZeroFiniteDouble$;
         3: dload_0
         4: invokevirtual #44                 // Method org/scalactic/anyvals/NonZeroFiniteDouble$.isWhole$extension:(D)Z
         7: ireturn
      LocalVariableTable:
        Start  Length  Slot  Name   Signature
            0       8     0 $this   D
    MethodParameters:
      Name                           Flags
      $this                          final

  public static double min$extension(double, double);
    descriptor: (DD)D
    flags: (0x0009) ACC_PUBLIC, ACC_STATIC
    Code:
      stack=5, locals=4, args_size=2
         0: getstatic     #20                 // Field org/scalactic/anyvals/NonZeroFiniteDouble$.MODULE$:Lorg/scalactic/anyvals/NonZeroFiniteDouble$;
         3: dload_0
         4: dload_2
         5: invokevirtual #49                 // Method org/scalactic/anyvals/NonZeroFiniteDouble$.min$extension:(DD)D
         8: dreturn
      LocalVariableTable:
        Start  Length  Slot  Name   Signature
            0       9     0 $this   D
            0       9     2  that   D
    MethodParameters:
      Name                           Flags
      $this                          final
      that                           final

  public static double max$extension(double, double);
    descriptor: (DD)D
    flags: (0x0009) ACC_PUBLIC, ACC_STATIC
    Code:
      stack=5, locals=4, args_size=2
         0: getstatic     #20                 // Field org/scalactic/anyvals/NonZeroFiniteDouble$.MODULE$:Lorg/scalactic/anyvals/NonZeroFiniteDouble$;
         3: dload_0
         4: dload_2
         5: invokevirtual #52                 // Method org/scalactic/anyvals/NonZeroFiniteDouble$.max$extension:(DD)D
         8: dreturn
      LocalVariableTable:
        Start  Length  Slot  Name   Signature
            0       9     0 $this   D
            0       9     2  that   D
    MethodParameters:
      Name                           Flags
      $this                          final
      that                           final

  public static double $percent$extension(double, double);
    descriptor: (DD)D
    flags: (0x0009) ACC_PUBLIC, ACC_STATIC
    Code:
      stack=5, locals=4, args_size=2
         0: getstatic     #20                 // Field org/scalactic/anyvals/NonZeroFiniteDouble$.MODULE$:Lorg/scalactic/anyvals/NonZeroFiniteDouble$;
         3: dload_0
         4: dload_2
         5: invokevirtual #56                 // Method org/scalactic/anyvals/NonZeroFiniteDouble$.$percent$extension:(DD)D
         8: dreturn
      LocalVariableTable:
        Start  Length  Slot  Name   Signature
            0       9     0 $this   D
            0       9     2     x   D
    MethodParameters:
      Name                           Flags
      $this                          final
      x                              final

  public static double $percent$extension(double, float);
    descriptor: (DF)D
    flags: (0x0009) ACC_PUBLIC, ACC_STATIC
    Code:
      stack=4, locals=3, args_size=2
         0: getstatic     #20                 // Field org/scalactic/anyvals/NonZeroFiniteDouble$.MODULE$:Lorg/scalactic/anyvals/NonZeroFiniteDouble$;
         3: dload_0
         4: fload_2
         5: invokevirtual #59                 // Method org/scalactic/anyvals/NonZeroFiniteDouble$.$percent$extension:(DF)D
         8: dreturn
      LocalVariableTable:
        Start  Length  Slot  Name   Signature
            0       9     0 $this   D
            0       9     2     x   F
    MethodParameters:
      Name                           Flags
      $this                          final
      x                              final

  public static double $percent$extension(double, long);
    descriptor: (DJ)D
    flags: (0x0009) ACC_PUBLIC, ACC_STATIC
    Code:
      stack=5, locals=4, args_size=2
         0: getstatic     #20                 // Field org/scalactic/anyvals/NonZeroFiniteDouble$.MODULE$:Lorg/scalactic/anyvals/NonZeroFiniteDouble$;
         3: dload_0
         4: lload_2
         5: invokevirtual #63                 // Method org/scalactic/anyvals/NonZeroFiniteDouble$.$percent$extension:(DJ)D
         8: dreturn
      LocalVariableTable:
        Start  Length  Slot  Name   Signature
            0       9     0 $this   D
            0       9     2     x   J
    MethodParameters:
      Name                           Flags
      $this                          final
      x                              final

  public static double $percent$extension(double, int);
    descriptor: (DI)D
    flags: (0x0009) ACC_PUBLIC, ACC_STATIC
    Code:
      stack=4, locals=3, args_size=2
         0: getstatic     #20                 // Field org/scalactic/anyvals/NonZeroFiniteDouble$.MODULE$:Lorg/scalactic/anyvals/NonZeroFiniteDouble$;
         3: dload_0
         4: iload_2
         5: invokevirtual #67                 // Method org/scalactic/anyvals/NonZeroFiniteDouble$.$percent$extension:(DI)D
         8: dreturn
      LocalVariableTable:
        Start  Length  Slot  Name   Signature
            0       9     0 $this   D
            0       9     2     x   I
    MethodParameters:
      Name                           Flags
      $this                          final
      x                              final

  public static double $percent$extension(double, char);
    descriptor: (DC)D
    flags: (0x0009) ACC_PUBLIC, ACC_STATIC
    Code:
      stack=4, locals=3, args_size=2
         0: getstatic     #20                 // Field org/scalactic/anyvals/NonZeroFiniteDouble$.MODULE$:Lorg/scalactic/anyvals/NonZeroFiniteDouble$;
         3: dload_0
         4: iload_2
         5: invokevirtual #71                 // Method org/scalactic/anyvals/NonZeroFiniteDouble$.$percent$extension:(DC)D
         8: dreturn
      LocalVariableTable:
        Start  Length  Slot  Name   Signature
            0       9     0 $this   D
            0       9     2     x   C
    MethodParameters:
      Name                           Flags
      $this                          final
      x                              final

  public static double $percent$extension(double, short);
    descriptor: (DS)D
    flags: (0x0009) ACC_PUBLIC, ACC_STATIC
    Code:
      stack=4, locals=3, args_size=2
         0: getstatic     #20                 // Field org/scalactic/anyvals/NonZeroFiniteDouble$.MODULE$:Lorg/scalactic/anyvals/NonZeroFiniteDouble$;
         3: dload_0
         4: iload_2
         5: invokevirtual #75                 // Method org/scalactic/anyvals/NonZeroFiniteDouble$.$percent$extension:(DS)D
         8: dreturn
      LocalVariableTable:
        Start  Length  Slot  Name   Signature
            0       9     0 $this   D
            0       9     2     x   S
    MethodParameters:
      Name                           Flags
      $this                          final
      x                              final

  public static double $percent$extension(double, byte);
    descriptor: (DB)D
    flags: (0x0009) ACC_PUBLIC, ACC_STATIC
    Code:
      stack=4, locals=3, args_size=2
         0: getstatic     #20                 // Field org/scalactic/anyvals/NonZeroFiniteDouble$.MODULE$:Lorg/scalactic/anyvals/NonZeroFiniteDouble$;
         3: dload_0
         4: iload_2
         5: invokevirtual #79                 // Method org/scalactic/anyvals/NonZeroFiniteDouble$.$percent$extension:(DB)D
         8: dreturn
      LocalVariableTable:
        Start  Length  Slot  Name   Signature
            0       9     0 $this   D
            0       9     2     x   B
    MethodParameters:
      Name                           Flags
      $this                          final
      x                              final

  public static double $div$extension(double, double);
    descriptor: (DD)D
    flags: (0x0009) ACC_PUBLIC, ACC_STATIC
    Code:
      stack=5, locals=4, args_size=2
         0: getstatic     #20                 // Field org/scalactic/anyvals/NonZeroFiniteDouble$.MODULE$:Lorg/scalactic/anyvals/NonZeroFiniteDouble$;
         3: dload_0
         4: dload_2
         5: invokevirtual #83                 // Method org/scalactic/anyvals/NonZeroFiniteDouble$.$div$extension:(DD)D
         8: dreturn
      LocalVariableTable:
        Start  Length  Slot  Name   Signature
            0       9     0 $this   D
            0       9     2     x   D
    MethodParameters:
      Name                           Flags
      $this                          final
      x                              final

  public static double $div$extension(double, float);
    descriptor: (DF)D
    flags: (0x0009) ACC_PUBLIC, ACC_STATIC
    Code:
      stack=4, locals=3, args_size=2
         0: getstatic     #20                 // Field org/scalactic/anyvals/NonZeroFiniteDouble$.MODULE$:Lorg/scalactic/anyvals/NonZeroFiniteDouble$;
         3: dload_0
         4: fload_2
         5: invokevirtual #85                 // Method org/scalactic/anyvals/NonZeroFiniteDouble$.$div$extension:(DF)D
         8: dreturn
      LocalVariableTable:
        Start  Length  Slot  Name   Signature
            0       9     0 $this   D
            0       9     2     x   F
    MethodParameters:
      Name                           Flags
      $this                          final
      x                              final

  public static double $div$extension(double, long);
    descriptor: (DJ)D
    flags: (0x0009) ACC_PUBLIC, ACC_STATIC
    Code:
      stack=5, locals=4, args_size=2
         0: getstatic     #20                 // Field org/scalactic/anyvals/NonZeroFiniteDouble$.MODULE$:Lorg/scalactic/anyvals/NonZeroFiniteDouble$;
         3: dload_0
         4: lload_2
         5: invokevirtual #87                 // Method org/scalactic/anyvals/NonZeroFiniteDouble$.$div$extension:(DJ)D
         8: dreturn
      LocalVariableTable:
        Start  Length  Slot  Name   Signature
            0       9     0 $this   D
            0       9     2     x   J
    MethodParameters:
      Name                           Flags
      $this                          final
      x                              final

  public static double $div$extension(double, int);
    descriptor: (DI)D
    flags: (0x0009) ACC_PUBLIC, ACC_STATIC
    Code:
      stack=4, locals=3, args_size=2
         0: getstatic     #20                 // Field org/scalactic/anyvals/NonZeroFiniteDouble$.MODULE$:Lorg/scalactic/anyvals/NonZeroFiniteDouble$;
         3: dload_0
         4: iload_2
         5: invokevirtual #89                 // Method org/scalactic/anyvals/NonZeroFiniteDouble$.$div$extension:(DI)D
         8: dreturn
      LocalVariableTable:
        Start  Length  Slot  Name   Signature
            0       9     0 $this   D
            0       9     2     x   I
    MethodParameters:
      Name                           Flags
      $this                          final
      x                              final

  public static double $div$extension(double, char);
    descriptor: (DC)D
    flags: (0x0009) ACC_PUBLIC, ACC_STATIC
    Code:
      stack=4, locals=3, args_size=2
         0: getstatic     #20                 // Field org/scalactic/anyvals/NonZeroFiniteDouble$.MODULE$:Lorg/scalactic/anyvals/NonZeroFiniteDouble$;
         3: dload_0
         4: iload_2
         5: invokevirtual #91                 // Method org/scalactic/anyvals/NonZeroFiniteDouble$.$div$extension:(DC)D
         8: dreturn
      LocalVariableTable:
        Start  Length  Slot  Name   Signature
            0       9     0 $this   D
            0       9     2     x   C
    MethodParameters:
      Name                           Flags
      $this                          final
      x                              final

  public static double $div$extension(double, short);
    descriptor: (DS)D
    flags: (0x0009) ACC_PUBLIC, ACC_STATIC
    Code:
      stack=4, locals=3, args_size=2
         0: getstatic     #20                 // Field org/scalactic/anyvals/NonZeroFiniteDouble$.MODULE$:Lorg/scalactic/anyvals/NonZeroFiniteDouble$;
         3: dload_0
         4: iload_2
         5: invokevirtual #93                 // Method org/scalactic/anyvals/NonZeroFiniteDouble$.$div$extension:(DS)D
         8: dreturn
      LocalVariableTable:
        Start  Length  Slot  Name   Signature
            0       9     0 $this   D
            0       9     2     x   S
    MethodParameters:
      Name                           Flags
      $this                          final
      x                              final

  public static double $div$extension(double, byte);
    descriptor: (DB)D
    flags: (0x0009) ACC_PUBLIC, ACC_STATIC
    Code:
      stack=4, locals=3, args_size=2
         0: getstatic     #20                 // Field org/scalactic/anyvals/NonZeroFiniteDouble$.MODULE$:Lorg/scalactic/anyvals/NonZeroFiniteDouble$;
         3: dload_0
         4: iload_2
         5: invokevirtual #95                 // Method org/scalactic/anyvals/NonZeroFiniteDouble$.$div$extension:(DB)D
         8: dreturn
      LocalVariableTable:
        Start  Length  Slot  Name   Signature
            0       9     0 $this   D
            0       9     2     x   B
    MethodParameters:
      Name                           Flags
      $this                          final
      x                              final

  public static double $times$extension(double, double);
    descriptor: (DD)D
    flags: (0x0009) ACC_PUBLIC, ACC_STATIC
    Code:
      stack=5, locals=4, args_size=2
         0: getstatic     #20                 // Field org/scalactic/anyvals/NonZeroFiniteDouble$.MODULE$:Lorg/scalactic/anyvals/NonZeroFiniteDouble$;
         3: dload_0
         4: dload_2
         5: invokevirtual #98                 // Method org/scalactic/anyvals/NonZeroFiniteDouble$.$times$extension:(DD)D
         8: dreturn
      LocalVariableTable:
        Start  Length  Slot  Name   Signature
            0       9     0 $this   D
            0       9     2     x   D
    MethodParameters:
      Name                           Flags
      $this                          final
      x                              final

  public static double $times$extension(double, float);
    descriptor: (DF)D
    flags: (0x0009) ACC_PUBLIC, ACC_STATIC
    Code:
      stack=4, locals=3, args_size=2
         0: getstatic     #20                 // Field org/scalactic/anyvals/NonZeroFiniteDouble$.MODULE$:Lorg/scalactic/anyvals/NonZeroFiniteDouble$;
         3: dload_0
         4: fload_2
         5: invokevirtual #100                // Method org/scalactic/anyvals/NonZeroFiniteDouble$.$times$extension:(DF)D
         8: dreturn
      LocalVariableTable:
        Start  Length  Slot  Name   Signature
            0       9     0 $this   D
            0       9     2     x   F
    MethodParameters:
      Name                           Flags
      $this                          final
      x                              final

  public static double $times$extension(double, long);
    descriptor: (DJ)D
    flags: (0x0009) ACC_PUBLIC, ACC_STATIC
    Code:
      stack=5, locals=4, args_size=2
         0: getstatic     #20                 // Field org/scalactic/anyvals/NonZeroFiniteDouble$.MODULE$:Lorg/scalactic/anyvals/NonZeroFiniteDouble$;
         3: dload_0
         4: lload_2
         5: invokevirtual #102                // Method org/scalactic/anyvals/NonZeroFiniteDouble$.$times$extension:(DJ)D
         8: dreturn
      LocalVariableTable:
        Start  Length  Slot  Name   Signature
            0       9     0 $this   D
            0       9     2     x   J
    MethodParameters:
      Name                           Flags
      $this                          final
      x                              final

  public static double $times$extension(double, int);
    descriptor: (DI)D
    flags: (0x0009) ACC_PUBLIC, ACC_STATIC
    Code:
      stack=4, locals=3, args_size=2
         0: getstatic     #20                 // Field org/scalactic/anyvals/NonZeroFiniteDouble$.MODULE$:Lorg/scalactic/anyvals/NonZeroFiniteDouble$;
         3: dload_0
         4: iload_2
         5: invokevirtual #104                // Method org/scalactic/anyvals/NonZeroFiniteDouble$.$times$extension:(DI)D
         8: dreturn
      LocalVariableTable:
        Start  Length  Slot  Name   Signature
            0       9     0 $this   D
            0       9     2     x   I
    MethodParameters:
      Name                           Flags
      $this                          final
      x                              final

  public static double $times$extension(double, char);
    descriptor: (DC)D
    flags: (0x0009) ACC_PUBLIC, ACC_STATIC
    Code:
      stack=4, locals=3, args_size=2
         0: getstatic     #20                 // Field org/scalactic/anyvals/NonZeroFiniteDouble$.MODULE$:Lorg/scalactic/anyvals/NonZeroFiniteDouble$;
         3: dload_0
         4: iload_2
         5: invokevirtual #106                // Method org/scalactic/anyvals/NonZeroFiniteDouble$.$times$extension:(DC)D
         8: dreturn
      LocalVariableTable:
        Start  Length  Slot  Name   Signature
            0       9     0 $this   D
            0       9     2     x   C
    MethodParameters:
      Name                           Flags
      $this                          final
      x                              final

  public static double $times$extension(double, short);
    descriptor: (DS)D
    flags: (0x0009) ACC_PUBLIC, ACC_STATIC
    Code:
      stack=4, locals=3, args_size=2
         0: getstatic     #20                 // Field org/scalactic/anyvals/NonZeroFiniteDouble$.MODULE$:Lorg/scalactic/anyvals/NonZeroFiniteDouble$;
         3: dload_0
         4: iload_2
         5: invokevirtual #108                // Method org/scalactic/anyvals/NonZeroFiniteDouble$.$times$extension:(DS)D
         8: dreturn
      LocalVariableTable:
        Start  Length  Slot  Name   Signature
            0       9     0 $this   D
            0       9     2     x   S
    MethodParameters:
      Name                           Flags
      $this                          final
      x                              final

  public static double $times$extension(double, byte);
    descriptor: (DB)D
    flags: (0x0009) ACC_PUBLIC, ACC_STATIC
    Code:
      stack=4, locals=3, args_size=2
         0: getstatic     #20                 // Field org/scalactic/anyvals/NonZeroFiniteDouble$.MODULE$:Lorg/scalactic/anyvals/NonZeroFiniteDouble$;
         3: dload_0
         4: iload_2
         5: invokevirtual #110                // Method org/scalactic/anyvals/NonZeroFiniteDouble$.$times$extension:(DB)D
         8: dreturn
      LocalVariableTable:
        Start  Length  Slot  Name   Signature
            0       9     0 $this   D
            0       9     2     x   B
    MethodParameters:
      Name                           Flags
      $this                          final
      x                              final

  public static double $minus$extension(double, double);
    descriptor: (DD)D
    flags: (0x0009) ACC_PUBLIC, ACC_STATIC
    Code:
      stack=5, locals=4, args_size=2
         0: getstatic     #20                 // Field org/scalactic/anyvals/NonZeroFiniteDouble$.MODULE$:Lorg/scalactic/anyvals/NonZeroFiniteDouble$;
         3: dload_0
         4: dload_2
         5: invokevirtual #113                // Method org/scalactic/anyvals/NonZeroFiniteDouble$.$minus$extension:(DD)D
         8: dreturn
      LocalVariableTable:
        Start  Length  Slot  Name   Signature
            0       9     0 $this   D
            0       9     2     x   D
    MethodParameters:
      Name                           Flags
      $this                          final
      x                              final

  public static double $minus$extension(double, float);
    descriptor: (DF)D
    flags: (0x0009) ACC_PUBLIC, ACC_STATIC
    Code:
      stack=4, locals=3, args_size=2
         0: getstatic     #20                 // Field org/scalactic/anyvals/NonZeroFiniteDouble$.MODULE$:Lorg/scalactic/anyvals/NonZeroFiniteDouble$;
         3: dload_0
         4: fload_2
         5: invokevirtual #115                // Method org/scalactic/anyvals/NonZeroFiniteDouble$.$minus$extension:(DF)D
         8: dreturn
      LocalVariableTable:
        Start  Length  Slot  Name   Signature
            0       9     0 $this   D
            0       9     2     x   F
    MethodParameters:
      Name                           Flags
      $this                          final
      x                              final

  public static double $minus$extension(double, long);
    descriptor: (DJ)D
    flags: (0x0009) ACC_PUBLIC, ACC_STATIC
    Code:
      stack=5, locals=4, args_size=2
         0: getstatic     #20                 // Field org/scalactic/anyvals/NonZeroFiniteDouble$.MODULE$:Lorg/scalactic/anyvals/NonZeroFiniteDouble$;
         3: dload_0
         4: lload_2
         5: invokevirtual #117                // Method org/scalactic/anyvals/NonZeroFiniteDouble$.$minus$extension:(DJ)D
         8: dreturn
      LocalVariableTable:
        Start  Length  Slot  Name   Signature
            0       9     0 $this   D
            0       9     2     x   J
    MethodParameters:
      Name                           Flags
      $this                          final
      x                              final

  public static double $minus$extension(double, int);
    descriptor: (DI)D
    flags: (0x0009) ACC_PUBLIC, ACC_STATIC
    Code:
      stack=4, locals=3, args_size=2
         0: getstatic     #20                 // Field org/scalactic/anyvals/NonZeroFiniteDouble$.MODULE$:Lorg/scalactic/anyvals/NonZeroFiniteDouble$;
         3: dload_0
         4: iload_2
         5: invokevirtual #119                // Method org/scalactic/anyvals/NonZeroFiniteDouble$.$minus$extension:(DI)D
         8: dreturn
      LocalVariableTable:
        Start  Length  Slot  Name   Signature
            0       9     0 $this   D
            0       9     2     x   I
    MethodParameters:
      Name                           Flags
      $this                          final
      x                              final

  public static double $minus$extension(double, char);
    descriptor: (DC)D
    flags: (0x0009) ACC_PUBLIC, ACC_STATIC
    Code:
      stack=4, locals=3, args_size=2
         0: getstatic     #20                 // Field org/scalactic/anyvals/NonZeroFiniteDouble$.MODULE$:Lorg/scalactic/anyvals/NonZeroFiniteDouble$;
         3: dload_0
         4: iload_2
         5: invokevirtual #121                // Method org/scalactic/anyvals/NonZeroFiniteDouble$.$minus$extension:(DC)D
         8: dreturn
      LocalVariableTable:
        Start  Length  Slot  Name   Signature
            0       9     0 $this   D
            0       9     2     x   C
    MethodParameters:
      Name                           Flags
      $this                          final
      x                              final

  public static double $minus$extension(double, short);
    descriptor: (DS)D
    flags: (0x0009) ACC_PUBLIC, ACC_STATIC
    Code:
      stack=4, locals=3, args_size=2
         0: getstatic     #20                 // Field org/scalactic/anyvals/NonZeroFiniteDouble$.MODULE$:Lorg/scalactic/anyvals/NonZeroFiniteDouble$;
         3: dload_0
         4: iload_2
         5: invokevirtual #123                // Method org/scalactic/anyvals/NonZeroFiniteDouble$.$minus$extension:(DS)D
         8: dreturn
      LocalVariableTable:
        Start  Length  Slot  Name   Signature
            0       9     0 $this   D
            0       9     2     x   S
    MethodParameters:
      Name                           Flags
      $this                          final
      x                              final

  public static double $minus$extension(double, byte);
    descriptor: (DB)D
    flags: (0x0009) ACC_PUBLIC, ACC_STATIC
    Code:
      stack=4, locals=3, args_size=2
         0: getstatic     #20                 // Field org/scalactic/anyvals/NonZeroFiniteDouble$.MODULE$:Lorg/scalactic/anyvals/NonZeroFiniteDouble$;
         3: dload_0
         4: iload_2
         5: invokevirtual #125                // Method org/scalactic/anyvals/NonZeroFiniteDouble$.$minus$extension:(DB)D
         8: dreturn
      LocalVariableTable:
        Start  Length  Slot  Name   Signature
            0       9     0 $this   D
            0       9     2     x   B
    MethodParameters:
      Name                           Flags
      $this                          final
      x                              final

  public static double $plus$extension(double, double);
    descriptor: (DD)D
    flags: (0x0009) ACC_PUBLIC, ACC_STATIC
    Code:
      stack=5, locals=4, args_size=2
         0: getstatic     #20                 // Field org/scalactic/anyvals/NonZeroFiniteDouble$.MODULE$:Lorg/scalactic/anyvals/NonZeroFiniteDouble$;
         3: dload_0
         4: dload_2
         5: invokevirtual #128                // Method org/scalactic/anyvals/NonZeroFiniteDouble$.$plus$extension:(DD)D
         8: dreturn
      LocalVariableTable:
        Start  Length  Slot  Name   Signature
            0       9     0 $this   D
            0       9     2     x   D
    MethodParameters:
      Name                           Flags
      $this                          final
      x                              final

  public static double $plus$extension(double, float);
    descriptor: (DF)D
    flags: (0x0009) ACC_PUBLIC, ACC_STATIC
    Code:
      stack=4, locals=3, args_size=2
         0: getstatic     #20                 // Field org/scalactic/anyvals/NonZeroFiniteDouble$.MODULE$:Lorg/scalactic/anyvals/NonZeroFiniteDouble$;
         3: dload_0
         4: fload_2
         5: invokevirtual #130                // Method org/scalactic/anyvals/NonZeroFiniteDouble$.$plus$extension:(DF)D
         8: dreturn
      LocalVariableTable:
        Start  Length  Slot  Name   Signature
            0       9     0 $this   D
            0       9     2     x   F
    MethodParameters:
      Name                           Flags
      $this                          final
      x                              final

  public static double $plus$extension(double, long);
    descriptor: (DJ)D
    flags: (0x0009) ACC_PUBLIC, ACC_STATIC
    Code:
      stack=5, locals=4, args_size=2
         0: getstatic     #20                 // Field org/scalactic/anyvals/NonZeroFiniteDouble$.MODULE$:Lorg/scalactic/anyvals/NonZeroFiniteDouble$;
         3: dload_0
         4: lload_2
         5: invokevirtual #132                // Method org/scalactic/anyvals/NonZeroFiniteDouble$.$plus$extension:(DJ)D
         8: dreturn
      LocalVariableTable:
        Start  Length  Slot  Name   Signature
            0       9     0 $this   D
            0       9     2     x   J
    MethodParameters:
      Name                           Flags
      $this                          final
      x                              final

  public static double $plus$extension(double, int);
    descriptor: (DI)D
    flags: (0x0009) ACC_PUBLIC, ACC_STATIC
    Code:
      stack=4, locals=3, args_size=2
         0: getstatic     #20                 // Field org/scalactic/anyvals/NonZeroFiniteDouble$.MODULE$:Lorg/scalactic/anyvals/NonZeroFiniteDouble$;
         3: dload_0
         4: iload_2
         5: invokevirtual #134                // Method org/scalactic/anyvals/NonZeroFiniteDouble$.$plus$extension:(DI)D
         8: dreturn
      LocalVariableTable:
        Start  Length  Slot  Name   Signature
            0       9     0 $this   D
            0       9     2     x   I
    MethodParameters:
      Name                           Flags
      $this                          final
      x                              final

  public static double $plus$extension(double, char);
    descriptor: (DC)D
    flags: (0x0009) ACC_PUBLIC, ACC_STATIC
    Code:
      stack=4, locals=3, args_size=2
         0: getstatic     #20                 // Field org/scalactic/anyvals/NonZeroFiniteDouble$.MODULE$:Lorg/scalactic/anyvals/NonZeroFiniteDouble$;
         3: dload_0
         4: iload_2
         5: invokevirtual #136                // Method org/scalactic/anyvals/NonZeroFiniteDouble$.$plus$extension:(DC)D
         8: dreturn
      LocalVariableTable:
        Start  Length  Slot  Name   Signature
            0       9     0 $this   D
            0       9     2     x   C
    MethodParameters:
      Name                           Flags
      $this                          final
      x                              final

  public static double $plus$extension(double, short);
    descriptor: (DS)D
    flags: (0x0009) ACC_PUBLIC, ACC_STATIC
    Code:
      stack=4, locals=3, args_size=2
         0: getstatic     #20                 // Field org/scalactic/anyvals/NonZeroFiniteDouble$.MODULE$:Lorg/scalactic/anyvals/NonZeroFiniteDouble$;
         3: dload_0
         4: iload_2
         5: invokevirtual #138                // Method org/scalactic/anyvals/NonZeroFiniteDouble$.$plus$extension:(DS)D
         8: dreturn
      LocalVariableTable:
        Start  Length  Slot  Name   Signature
            0       9     0 $this   D
            0       9     2     x   S
    MethodParameters:
      Name                           Flags
      $this                          final
      x                              final

  public static double $plus$extension(double, byte);
    descriptor: (DB)D
    flags: (0x0009) ACC_PUBLIC, ACC_STATIC
    Code:
      stack=4, locals=3, args_size=2
         0: getstatic     #20                 // Field org/scalactic/anyvals/NonZeroFiniteDouble$.MODULE$:Lorg/scalactic/anyvals/NonZeroFiniteDouble$;
         3: dload_0
         4: iload_2
         5: invokevirtual #140                // Method org/scalactic/anyvals/NonZeroFiniteDouble$.$plus$extension:(DB)D
         8: dreturn
      LocalVariableTable:
        Start  Length  Slot  Name   Signature
            0       9     0 $this   D
            0       9     2     x   B
    MethodParameters:
      Name                           Flags
      $this                          final
      x                              final

  public static boolean $greater$eq$extension(double, double);
    descriptor: (DD)Z
    flags: (0x0009) ACC_PUBLIC, ACC_STATIC
    Code:
      stack=5, locals=4, args_size=2
         0: getstatic     #20                 // Field org/scalactic/anyvals/NonZeroFiniteDouble$.MODULE$:Lorg/scalactic/anyvals/NonZeroFiniteDouble$;
         3: dload_0
         4: dload_2
         5: invokevirtual #144                // Method org/scalactic/anyvals/NonZeroFiniteDouble$.$greater$eq$extension:(DD)Z
         8: ireturn
      LocalVariableTable:
        Start  Length  Slot  Name   Signature
            0       9     0 $this   D
            0       9     2     x   D
    MethodParameters:
      Name                           Flags
      $this                          final
      x                              final

  public static boolean $greater$eq$extension(double, float);
    descriptor: (DF)Z
    flags: (0x0009) ACC_PUBLIC, ACC_STATIC
    Code:
      stack=4, locals=3, args_size=2
         0: getstatic     #20                 // Field org/scalactic/anyvals/NonZeroFiniteDouble$.MODULE$:Lorg/scalactic/anyvals/NonZeroFiniteDouble$;
         3: dload_0
         4: fload_2
         5: invokevirtual #147                // Method org/scalactic/anyvals/NonZeroFiniteDouble$.$greater$eq$extension:(DF)Z
         8: ireturn
      LocalVariableTable:
        Start  Length  Slot  Name   Signature
            0       9     0 $this   D
            0       9     2     x   F
    MethodParameters:
      Name                           Flags
      $this                          final
      x                              final

  public static boolean $greater$eq$extension(double, long);
    descriptor: (DJ)Z
    flags: (0x0009) ACC_PUBLIC, ACC_STATIC
    Code:
      stack=5, locals=4, args_size=2
         0: getstatic     #20                 // Field org/scalactic/anyvals/NonZeroFiniteDouble$.MODULE$:Lorg/scalactic/anyvals/NonZeroFiniteDouble$;
         3: dload_0
         4: lload_2
         5: invokevirtual #150                // Method org/scalactic/anyvals/NonZeroFiniteDouble$.$greater$eq$extension:(DJ)Z
         8: ireturn
      LocalVariableTable:
        Start  Length  Slot  Name   Signature
            0       9     0 $this   D
            0       9     2     x   J
    MethodParameters:
      Name                           Flags
      $this                          final
      x                              final

  public static boolean $greater$eq$extension(double, int);
    descriptor: (DI)Z
    flags: (0x0009) ACC_PUBLIC, ACC_STATIC
    Code:
      stack=4, locals=3, args_size=2
         0: getstatic     #20                 // Field org/scalactic/anyvals/NonZeroFiniteDouble$.MODULE$:Lorg/scalactic/anyvals/NonZeroFiniteDouble$;
         3: dload_0
         4: iload_2
         5: invokevirtual #153                // Method org/scalactic/anyvals/NonZeroFiniteDouble$.$greater$eq$extension:(DI)Z
         8: ireturn
      LocalVariableTable:
        Start  Length  Slot  Name   Signature
            0       9     0 $this   D
            0       9     2     x   I
    MethodParameters:
      Name                           Flags
      $this                          final
      x                              final

  public static boolean $greater$eq$extension(double, char);
    descriptor: (DC)Z
    flags: (0x0009) ACC_PUBLIC, ACC_STATIC
    Code:
      stack=4, locals=3, args_size=2
         0: getstatic     #20                 // Field org/scalactic/anyvals/NonZeroFiniteDouble$.MODULE$:Lorg/scalactic/anyvals/NonZeroFiniteDouble$;
         3: dload_0
         4: iload_2
         5: invokevirtual #156                // Method org/scalactic/anyvals/NonZeroFiniteDouble$.$greater$eq$extension:(DC)Z
         8: ireturn
      LocalVariableTable:
        Start  Length  Slot  Name   Signature
            0       9     0 $this   D
            0       9     2     x   C
    MethodParameters:
      Name                           Flags
      $this                          final
      x                              final

  public static boolean $greater$eq$extension(double, short);
    descriptor: (DS)Z
    flags: (0x0009) ACC_PUBLIC, ACC_STATIC
    Code:
      stack=4, locals=3, args_size=2
         0: getstatic     #20                 // Field org/scalactic/anyvals/NonZeroFiniteDouble$.MODULE$:Lorg/scalactic/anyvals/NonZeroFiniteDouble$;
         3: dload_0
         4: iload_2
         5: invokevirtual #159                // Method org/scalactic/anyvals/NonZeroFiniteDouble$.$greater$eq$extension:(DS)Z
         8: ireturn
      LocalVariableTable:
        Start  Length  Slot  Name   Signature
            0       9     0 $this   D
            0       9     2     x   S
    MethodParameters:
      Name                           Flags
      $this                          final
      x                              final

  public static boolean $greater$eq$extension(double, byte);
    descriptor: (DB)Z
    flags: (0x0009) ACC_PUBLIC, ACC_STATIC
    Code:
      stack=4, locals=3, args_size=2
         0: getstatic     #20                 // Field org/scalactic/anyvals/NonZeroFiniteDouble$.MODULE$:Lorg/scalactic/anyvals/NonZeroFiniteDouble$;
         3: dload_0
         4: iload_2
         5: invokevirtual #162                // Method org/scalactic/anyvals/NonZeroFiniteDouble$.$greater$eq$extension:(DB)Z
         8: ireturn
      LocalVariableTable:
        Start  Length  Slot  Name   Signature
            0       9     0 $this   D
            0       9     2     x   B
    MethodParameters:
      Name                           Flags
      $this                          final
      x                              final

  public static boolean $greater$extension(double, double);
    descriptor: (DD)Z
    flags: (0x0009) ACC_PUBLIC, ACC_STATIC
    Code:
      stack=5, locals=4, args_size=2
         0: getstatic     #20                 // Field org/scalactic/anyvals/NonZeroFiniteDouble$.MODULE$:Lorg/scalactic/anyvals/NonZeroFiniteDouble$;
         3: dload_0
         4: dload_2
         5: invokevirtual #165                // Method org/scalactic/anyvals/NonZeroFiniteDouble$.$greater$extension:(DD)Z
         8: ireturn
      LocalVariableTable:
        Start  Length  Slot  Name   Signature
            0       9     0 $this   D
            0       9     2     x   D
    MethodParameters:
      Name                           Flags
      $this                          final
      x                              final

  public static boolean $greater$extension(double, float);
    descriptor: (DF)Z
    flags: (0x0009) ACC_PUBLIC, ACC_STATIC
    Code:
      stack=4, locals=3, args_size=2
         0: getstatic     #20                 // Field org/scalactic/anyvals/NonZeroFiniteDouble$.MODULE$:Lorg/scalactic/anyvals/NonZeroFiniteDouble$;
         3: dload_0
         4: fload_2
         5: invokevirtual #167                // Method org/scalactic/anyvals/NonZeroFiniteDouble$.$greater$extension:(DF)Z
         8: ireturn
      LocalVariableTable:
        Start  Length  Slot  Name   Signature
            0       9     0 $this   D
            0       9     2     x   F
    MethodParameters:
      Name                           Flags
      $this                          final
      x                              final

  public static boolean $greater$extension(double, long);
    descriptor: (DJ)Z
    flags: (0x0009) ACC_PUBLIC, ACC_STATIC
    Code:
      stack=5, locals=4, args_size=2
         0: getstatic     #20                 // Field org/scalactic/anyvals/NonZeroFiniteDouble$.MODULE$:Lorg/scalactic/anyvals/NonZeroFiniteDouble$;
         3: dload_0
         4: lload_2
         5: invokevirtual #169                // Method org/scalactic/anyvals/NonZeroFiniteDouble$.$greater$extension:(DJ)Z
         8: ireturn
      LocalVariableTable:
        Start  Length  Slot  Name   Signature
            0       9     0 $this   D
            0       9     2     x   J
    MethodParameters:
      Name                           Flags
      $this                          final
      x                              final

  public static boolean $greater$extension(double, int);
    descriptor: (DI)Z
    flags: (0x0009) ACC_PUBLIC, ACC_STATIC
    Code:
      stack=4, locals=3, args_size=2
         0: getstatic     #20                 // Field org/scalactic/anyvals/NonZeroFiniteDouble$.MODULE$:Lorg/scalactic/anyvals/NonZeroFiniteDouble$;
         3: dload_0
         4: iload_2
         5: invokevirtual #171                // Method org/scalactic/anyvals/NonZeroFiniteDouble$.$greater$extension:(DI)Z
         8: ireturn
      LocalVariableTable:
        Start  Length  Slot  Name   Signature
            0       9     0 $this   D
            0       9     2     x   I
    MethodParameters:
      Name                           Flags
      $this                          final
      x                              final

  public static boolean $greater$extension(double, char);
    descriptor: (DC)Z
    flags: (0x0009) ACC_PUBLIC, ACC_STATIC
    Code:
      stack=4, locals=3, args_size=2
         0: getstatic     #20                 // Field org/scalactic/anyvals/NonZeroFiniteDouble$.MODULE$:Lorg/scalactic/anyvals/NonZeroFiniteDouble$;
         3: dload_0
         4: iload_2
         5: invokevirtual #173                // Method org/scalactic/anyvals/NonZeroFiniteDouble$.$greater$extension:(DC)Z
         8: ireturn
      LocalVariableTable:
        Start  Length  Slot  Name   Signature
            0       9     0 $this   D
            0       9     2     x   C
    MethodParameters:
      Name                           Flags
      $this                          final
      x                              final

  public static boolean $greater$extension(double, short);
    descriptor: (DS)Z
    flags: (0x0009) ACC_PUBLIC, ACC_STATIC
    Code:
      stack=4, locals=3, args_size=2
         0: getstatic     #20                 // Field org/scalactic/anyvals/NonZeroFiniteDouble$.MODULE$:Lorg/scalactic/anyvals/NonZeroFiniteDouble$;
         3: dload_0
         4: iload_2
         5: invokevirtual #175                // Method org/scalactic/anyvals/NonZeroFiniteDouble$.$greater$extension:(DS)Z
         8: ireturn
      LocalVariableTable:
        Start  Length  Slot  Name   Signature
            0       9     0 $this   D
            0       9     2     x   S
    MethodParameters:
      Name                           Flags
      $this                          final
      x                              final

  public static boolean $greater$extension(double, byte);
    descriptor: (DB)Z
    flags: (0x0009) ACC_PUBLIC, ACC_STATIC
    Code:
      stack=4, locals=3, args_size=2
         0: getstatic     #20                 // Field org/scalactic/anyvals/NonZeroFiniteDouble$.MODULE$:Lorg/scalactic/anyvals/NonZeroFiniteDouble$;
         3: dload_0
         4: iload_2
         5: invokevirtual #177                // Method org/scalactic/anyvals/NonZeroFiniteDouble$.$greater$extension:(DB)Z
         8: ireturn
      LocalVariableTable:
        Start  Length  Slot  Name   Signature
            0       9     0 $this   D
            0       9     2     x   B
    MethodParameters:
      Name                           Flags
      $this                          final
      x                              final

  public static boolean $less$eq$extension(double, double);
    descriptor: (DD)Z
    flags: (0x0009) ACC_PUBLIC, ACC_STATIC
    Code:
      stack=5, locals=4, args_size=2
         0: getstatic     #20                 // Field org/scalactic/anyvals/NonZeroFiniteDouble$.MODULE$:Lorg/scalactic/anyvals/NonZeroFiniteDouble$;
         3: dload_0
         4: dload_2
         5: invokevirtual #180                // Method org/scalactic/anyvals/NonZeroFiniteDouble$.$less$eq$extension:(DD)Z
         8: ireturn
      LocalVariableTable:
        Start  Length  Slot  Name   Signature
            0       9     0 $this   D
            0       9     2     x   D
    MethodParameters:
      Name                           Flags
      $this                          final
      x                              final

  public static boolean $less$eq$extension(double, float);
    descriptor: (DF)Z
    flags: (0x0009) ACC_PUBLIC, ACC_STATIC
    Code:
      stack=4, locals=3, args_size=2
         0: getstatic     #20                 // Field org/scalactic/anyvals/NonZeroFiniteDouble$.MODULE$:Lorg/scalactic/anyvals/NonZeroFiniteDouble$;
         3: dload_0
         4: fload_2
         5: invokevirtual #182                // Method org/scalactic/anyvals/NonZeroFiniteDouble$.$less$eq$extension:(DF)Z
         8: ireturn
      LocalVariableTable:
        Start  Length  Slot  Name   Signature
            0       9     0 $this   D
            0       9     2     x   F
    MethodParameters:
      Name                           Flags
      $this                          final
      x                              final

  public static boolean $less$eq$extension(double, long);
    descriptor: (DJ)Z
    flags: (0x0009) ACC_PUBLIC, ACC_STATIC
    Code:
      stack=5, locals=4, args_size=2
         0: getstatic     #20                 // Field org/scalactic/anyvals/NonZeroFiniteDouble$.MODULE$:Lorg/scalactic/anyvals/NonZeroFiniteDouble$;
         3: dload_0
         4: lload_2
         5: invokevirtual #184                // Method org/scalactic/anyvals/NonZeroFiniteDouble$.$less$eq$extension:(DJ)Z
         8: ireturn
      LocalVariableTable:
        Start  Length  Slot  Name   Signature
            0       9     0 $this   D
            0       9     2     x   J
    MethodParameters:
      Name                           Flags
      $this                          final
      x                              final

  public static boolean $less$eq$extension(double, int);
    descriptor: (DI)Z
    flags: (0x0009) ACC_PUBLIC, ACC_STATIC
    Code:
      stack=4, locals=3, args_size=2
         0: getstatic     #20                 // Field org/scalactic/anyvals/NonZeroFiniteDouble$.MODULE$:Lorg/scalactic/anyvals/NonZeroFiniteDouble$;
         3: dload_0
         4: iload_2
         5: invokevirtual #186                // Method org/scalactic/anyvals/NonZeroFiniteDouble$.$less$eq$extension:(DI)Z
         8: ireturn
      LocalVariableTable:
        Start  Length  Slot  Name   Signature
            0       9     0 $this   D
            0       9     2     x   I
    MethodParameters:
      Name                           Flags
      $this                          final
      x                              final

  public static boolean $less$eq$extension(double, char);
    descriptor: (DC)Z
    flags: (0x0009) ACC_PUBLIC, ACC_STATIC
    Code:
      stack=4, locals=3, args_size=2
         0: getstatic     #20                 // Field org/scalactic/anyvals/NonZeroFiniteDouble$.MODULE$:Lorg/scalactic/anyvals/NonZeroFiniteDouble$;
         3: dload_0
         4: iload_2
         5: invokevirtual #188                // Method org/scalactic/anyvals/NonZeroFiniteDouble$.$less$eq$extension:(DC)Z
         8: ireturn
      LocalVariableTable:
        Start  Length  Slot  Name   Signature
            0       9     0 $this   D
            0       9     2     x   C
    MethodParameters:
      Name                           Flags
      $this                          final
      x                              final

  public static boolean $less$eq$extension(double, short);
    descriptor: (DS)Z
    flags: (0x0009) ACC_PUBLIC, ACC_STATIC
    Code:
      stack=4, locals=3, args_size=2
         0: getstatic     #20                 // Field org/scalactic/anyvals/NonZeroFiniteDouble$.MODULE$:Lorg/scalactic/anyvals/NonZeroFiniteDouble$;
         3: dload_0
         4: iload_2
         5: invokevirtual #190                // Method org/scalactic/anyvals/NonZeroFiniteDouble$.$less$eq$extension:(DS)Z
         8: ireturn
      LocalVariableTable:
        Start  Length  Slot  Name   Signature
            0       9     0 $this   D
            0       9     2     x   S
    MethodParameters:
      Name                           Flags
      $this                          final
      x                              final

  public static boolean $less$eq$extension(double, byte);
    descriptor: (DB)Z
    flags: (0x0009) ACC_PUBLIC, ACC_STATIC
    Code:
      stack=4, locals=3, args_size=2
         0: getstatic     #20                 // Field org/scalactic/anyvals/NonZeroFiniteDouble$.MODULE$:Lorg/scalactic/anyvals/NonZeroFiniteDouble$;
         3: dload_0
         4: iload_2
         5: invokevirtual #192                // Method org/scalactic/anyvals/NonZeroFiniteDouble$.$less$eq$extension:(DB)Z
         8: ireturn
      LocalVariableTable:
        Start  Length  Slot  Name   Signature
            0       9     0 $this   D
            0       9     2     x   B
    MethodParameters:
      Name                           Flags
      $this                          final
      x                              final

  public static boolean $less$extension(double, double);
    descriptor: (DD)Z
    flags: (0x0009) ACC_PUBLIC, ACC_STATIC
    Code:
      stack=5, locals=4, args_size=2
         0: getstatic     #20                 // Field org/scalactic/anyvals/NonZeroFiniteDouble$.MODULE$:Lorg/scalactic/anyvals/NonZeroFiniteDouble$;
         3: dload_0
         4: dload_2
         5: invokevirtual #195                // Method org/scalactic/anyvals/NonZeroFiniteDouble$.$less$extension:(DD)Z
         8: ireturn
      LocalVariableTable:
        Start  Length  Slot  Name   Signature
            0       9     0 $this   D
            0       9     2     x   D
    MethodParameters:
      Name                           Flags
      $this                          final
      x                              final

  public static boolean $less$extension(double, float);
    descriptor: (DF)Z
    flags: (0x0009) ACC_PUBLIC, ACC_STATIC
    Code:
      stack=4, locals=3, args_size=2
         0: getstatic     #20                 // Field org/scalactic/anyvals/NonZeroFiniteDouble$.MODULE$:Lorg/scalactic/anyvals/NonZeroFiniteDouble$;
         3: dload_0
         4: fload_2
         5: invokevirtual #197                // Method org/scalactic/anyvals/NonZeroFiniteDouble$.$less$extension:(DF)Z
         8: ireturn
      LocalVariableTable:
        Start  Length  Slot  Name   Signature
            0       9     0 $this   D
            0       9     2     x   F
    MethodParameters:
      Name                           Flags
      $this                          final
      x                              final

  public static boolean $less$extension(double, long);
    descriptor: (DJ)Z
    flags: (0x0009) ACC_PUBLIC, ACC_STATIC
    Code:
      stack=5, locals=4, args_size=2
         0: getstatic     #20                 // Field org/scalactic/anyvals/NonZeroFiniteDouble$.MODULE$:Lorg/scalactic/anyvals/NonZeroFiniteDouble$;
         3: dload_0
         4: lload_2
         5: invokevirtual #199                // Method org/scalactic/anyvals/NonZeroFiniteDouble$.$less$extension:(DJ)Z
         8: ireturn
      LocalVariableTable:
        Start  Length  Slot  Name   Signature
            0       9     0 $this   D
            0       9     2     x   J
    MethodParameters:
      Name                           Flags
      $this                          final
      x                              final

  public static boolean $less$extension(double, int);
    descriptor: (DI)Z
    flags: (0x0009) ACC_PUBLIC, ACC_STATIC
    Code:
      stack=4, locals=3, args_size=2
         0: getstatic     #20                 // Field org/scalactic/anyvals/NonZeroFiniteDouble$.MODULE$:Lorg/scalactic/anyvals/NonZeroFiniteDouble$;
         3: dload_0
         4: iload_2
         5: invokevirtual #201                // Method org/scalactic/anyvals/NonZeroFiniteDouble$.$less$extension:(DI)Z
         8: ireturn
      LocalVariableTable:
        Start  Length  Slot  Name   Signature
            0       9     0 $this   D
            0       9     2     x   I
    MethodParameters:
      Name                           Flags
      $this                          final
      x                              final

  public static boolean $less$extension(double, char);
    descriptor: (DC)Z
    flags: (0x0009) ACC_PUBLIC, ACC_STATIC
    Code:
      stack=4, locals=3, args_size=2
         0: getstatic     #20                 // Field org/scalactic/anyvals/NonZeroFiniteDouble$.MODULE$:Lorg/scalactic/anyvals/NonZeroFiniteDouble$;
         3: dload_0
         4: iload_2
         5: invokevirtual #203                // Method org/scalactic/anyvals/NonZeroFiniteDouble$.$less$extension:(DC)Z
         8: ireturn
      LocalVariableTable:
        Start  Length  Slot  Name   Signature
            0       9     0 $this   D
            0       9     2     x   C
    MethodParameters:
      Name                           Flags
      $this                          final
      x                              final

  public static boolean $less$extension(double, short);
    descriptor: (DS)Z
    flags: (0x0009) ACC_PUBLIC, ACC_STATIC
    Code:
      stack=4, locals=3, args_size=2
         0: getstatic     #20                 // Field org/scalactic/anyvals/NonZeroFiniteDouble$.MODULE$:Lorg/scalactic/anyvals/NonZeroFiniteDouble$;
         3: dload_0
         4: iload_2
         5: invokevirtual #205                // Method org/scalactic/anyvals/NonZeroFiniteDouble$.$less$extension:(DS)Z
         8: ireturn
      LocalVariableTable:
        Start  Length  Slot  Name   Signature
            0       9     0 $this   D
            0       9     2     x   S
    MethodParameters:
      Name                           Flags
      $this                          final
      x                              final

  public static boolean $less$extension(double, byte);
    descriptor: (DB)Z
    flags: (0x0009) ACC_PUBLIC, ACC_STATIC
    Code:
      stack=4, locals=3, args_size=2
         0: getstatic     #20                 // Field org/scalactic/anyvals/NonZeroFiniteDouble$.MODULE$:Lorg/scalactic/anyvals/NonZeroFiniteDouble$;
         3: dload_0
         4: iload_2
         5: invokevirtual #207                // Method org/scalactic/anyvals/NonZeroFiniteDouble$.$less$extension:(DB)Z
         8: ireturn
      LocalVariableTable:
        Start  Length  Slot  Name   Signature
            0       9     0 $this   D
            0       9     2     x   B
    MethodParameters:
      Name                           Flags
      $this                          final
      x                              final

  public static java.lang.String $plus$extension(double, java.lang.String);
    descriptor: (DLjava/lang/String;)Ljava/lang/String;
    flags: (0x0009) ACC_PUBLIC, ACC_STATIC
    Code:
      stack=4, locals=3, args_size=2
         0: getstatic     #20                 // Field org/scalactic/anyvals/NonZeroFiniteDouble$.MODULE$:Lorg/scalactic/anyvals/NonZeroFiniteDouble$;
         3: dload_0
         4: aload_2
         5: invokevirtual #210                // Method org/scalactic/anyvals/NonZeroFiniteDouble$.$plus$extension:(DLjava/lang/String;)Ljava/lang/String;
         8: areturn
      LocalVariableTable:
        Start  Length  Slot  Name   Signature
            0       9     0 $this   D
            0       9     2     x   Ljava/lang/String;
    MethodParameters:
      Name                           Flags
      $this                          final
      x                              final

  public static double unary_$minus$extension(double);
    descriptor: (D)D
    flags: (0x0009) ACC_PUBLIC, ACC_STATIC
    Code:
      stack=3, locals=2, args_size=1
         0: getstatic     #20                 // Field org/scalactic/anyvals/NonZeroFiniteDouble$.MODULE$:Lorg/scalactic/anyvals/NonZeroFiniteDouble$;
         3: dload_0
         4: invokevirtual #214                // Method org/scalactic/anyvals/NonZeroFiniteDouble$.unary_$minus$extension:(D)D
         7: dreturn
      LocalVariableTable:
        Start  Length  Slot  Name   Signature
            0       8     0 $this   D
    MethodParameters:
      Name                           Flags
      $this                          final

  public static double unary_$plus$extension(double);
    descriptor: (D)D
    flags: (0x0009) ACC_PUBLIC, ACC_STATIC
    Code:
      stack=3, locals=2, args_size=1
         0: getstatic     #20                 // Field org/scalactic/anyvals/NonZeroFiniteDouble$.MODULE$:Lorg/scalactic/anyvals/NonZeroFiniteDouble$;
         3: dload_0
         4: invokevirtual #217                // Method org/scalactic/anyvals/NonZeroFiniteDouble$.unary_$plus$extension:(D)D
         7: dreturn
      LocalVariableTable:
        Start  Length  Slot  Name   Signature
            0       8     0 $this   D
    MethodParameters:
      Name                           Flags
      $this                          final

  public static double toDouble$extension(double);
    descriptor: (D)D
    flags: (0x0009) ACC_PUBLIC, ACC_STATIC
    Code:
      stack=3, locals=2, args_size=1
         0: getstatic     #20                 // Field org/scalactic/anyvals/NonZeroFiniteDouble$.MODULE$:Lorg/scalactic/anyvals/NonZeroFiniteDouble$;
         3: dload_0
         4: invokevirtual #220                // Method org/scalactic/anyvals/NonZeroFiniteDouble$.toDouble$extension:(D)D
         7: dreturn
      LocalVariableTable:
        Start  Length  Slot  Name   Signature
            0       8     0 $this   D
    MethodParameters:
      Name                           Flags
      $this                          final

  public static float toFloat$extension(double);
    descriptor: (D)F
    flags: (0x0009) ACC_PUBLIC, ACC_STATIC
    Code:
      stack=3, locals=2, args_size=1
         0: getstatic     #20                 // Field org/scalactic/anyvals/NonZeroFiniteDouble$.MODULE$:Lorg/scalactic/anyvals/NonZeroFiniteDouble$;
         3: dload_0
         4: invokevirtual #224                // Method org/scalactic/anyvals/NonZeroFiniteDouble$.toFloat$extension:(D)F
         7: freturn
      LocalVariableTable:
        Start  Length  Slot  Name   Signature
            0       8     0 $this   D
    MethodParameters:
      Name                           Flags
      $this                          final

  public static long toLong$extension(double);
    descriptor: (D)J
    flags: (0x0009) ACC_PUBLIC, ACC_STATIC
    Code:
      stack=3, locals=2, args_size=1
         0: getstatic     #20                 // Field org/scalactic/anyvals/NonZeroFiniteDouble$.MODULE$:Lorg/scalactic/anyvals/NonZeroFiniteDouble$;
         3: dload_0
         4: invokevirtual #228                // Method org/scalactic/anyvals/NonZeroFiniteDouble$.toLong$extension:(D)J
         7: lreturn
      LocalVariableTable:
        Start  Length  Slot  Name   Signature
            0       8     0 $this   D
    MethodParameters:
      Name                           Flags
      $this                          final

  public static int toInt$extension(double);
    descriptor: (D)I
    flags: (0x0009) ACC_PUBLIC, ACC_STATIC
    Code:
      stack=3, locals=2, args_size=1
         0: getstatic     #20                 // Field org/scalactic/anyvals/NonZeroFiniteDouble$.MODULE$:Lorg/scalactic/anyvals/NonZeroFiniteDouble$;
         3: dload_0
         4: invokevirtual #231                // Method org/scalactic/anyvals/NonZeroFiniteDouble$.toInt$extension:(D)I
         7: ireturn
      LocalVariableTable:
        Start  Length  Slot  Name   Signature
            0       8     0 $this   D
    MethodParameters:
      Name                           Flags
      $this                          final

  public static char toChar$extension(double);
    descriptor: (D)C
    flags: (0x0009) ACC_PUBLIC, ACC_STATIC
    Code:
      stack=3, locals=2, args_size=1
         0: getstatic     #20                 // Field org/scalactic/anyvals/NonZeroFiniteDouble$.MODULE$:Lorg/scalactic/anyvals/NonZeroFiniteDouble$;
         3: dload_0
         4: invokevirtual #235                // Method org/scalactic/anyvals/NonZeroFiniteDouble$.toChar$extension:(D)C
         7: ireturn
      LocalVariableTable:
        Start  Length  Slot  Name   Signature
            0       8     0 $this   D
    MethodParameters:
      Name                           Flags
      $this                          final

  public static short toShort$extension(double);
    descriptor: (D)S
    flags: (0x0009) ACC_PUBLIC, ACC_STATIC
    Code:
      stack=3, locals=2, args_size=1
         0: getstatic     #20                 // Field org/scalactic/anyvals/NonZeroFiniteDouble$.MODULE$:Lorg/scalactic/anyvals/NonZeroFiniteDouble$;
         3: dload_0
         4: invokevirtual #239                // Method org/scalactic/anyvals/NonZeroFiniteDouble$.toShort$extension:(D)S
         7: ireturn
      LocalVariableTable:
        Start  Length  Slot  Name   Signature
            0       8     0 $this   D
    MethodParameters:
      Name                           Flags
      $this                          final

  public static byte toByte$extension(double);
    descriptor: (D)B
    flags: (0x0009) ACC_PUBLIC, ACC_STATIC
    Code:
      stack=3, locals=2, args_size=1
         0: getstatic     #20                 // Field org/scalactic/anyvals/NonZeroFiniteDouble$.MODULE$:Lorg/scalactic/anyvals/NonZeroFiniteDouble$;
         3: dload_0
         4: invokevirtual #243                // Method org/scalactic/anyvals/NonZeroFiniteDouble$.toByte$extension:(D)B
         7: ireturn
      LocalVariableTable:
        Start  Length  Slot  Name   Signature
            0       8     0 $this   D
    MethodParameters:
      Name                           Flags
      $this                          final

  public static java.lang.String toString$extension(double);
    descriptor: (D)Ljava/lang/String;
    flags: (0x0009) ACC_PUBLIC, ACC_STATIC
    Code:
      stack=3, locals=2, args_size=1
         0: getstatic     #20                 // Field org/scalactic/anyvals/NonZeroFiniteDouble$.MODULE$:Lorg/scalactic/anyvals/NonZeroFiniteDouble$;
         3: dload_0
         4: invokevirtual #247                // Method org/scalactic/anyvals/NonZeroFiniteDouble$.toString$extension:(D)Ljava/lang/String;
         7: areturn
      LocalVariableTable:
        Start  Length  Slot  Name   Signature
            0       8     0 $this   D
    MethodParameters:
      Name                           Flags
      $this                          final

  public static double MinPositiveValue();
    descriptor: ()D
    flags: (0x0009) ACC_PUBLIC, ACC_STATIC
    Code:
      stack=2, locals=0, args_size=0
         0: getstatic     #20                 // Field org/scalactic/anyvals/NonZeroFiniteDouble$.MODULE$:Lorg/scalactic/anyvals/NonZeroFiniteDouble$;
         3: invokevirtual #251                // Method org/scalactic/anyvals/NonZeroFiniteDouble$.MinPositiveValue:()D
         6: dreturn

  public static scala.math.Ordering<org.scalactic.anyvals.NonZeroFiniteDouble> ordering();
    descriptor: ()Lscala/math/Ordering;
    flags: (0x0009) ACC_PUBLIC, ACC_STATIC
    Code:
      stack=1, locals=0, args_size=0
         0: getstatic     #20                 // Field org/scalactic/anyvals/NonZeroFiniteDouble$.MODULE$:Lorg/scalactic/anyvals/NonZeroFiniteDouble$;
         3: invokevirtual #256                // Method org/scalactic/anyvals/NonZeroFiniteDouble$.ordering:()Lscala/math/Ordering;
         6: areturn
    Signature: #254                         // ()Lscala/math/Ordering<Lorg/scalactic/anyvals/NonZeroFiniteDouble;>;

  public static double widenToNonZeroDouble(double);
    descriptor: (D)D
    flags: (0x0009) ACC_PUBLIC, ACC_STATIC
    Code:
      stack=3, locals=2, args_size=1
         0: getstatic     #20                 // Field org/scalactic/anyvals/NonZeroFiniteDouble$.MODULE$:Lorg/scalactic/anyvals/NonZeroFiniteDouble$;
         3: dload_0
         4: invokevirtual #260                // Method org/scalactic/anyvals/NonZeroFiniteDouble$.widenToNonZeroDouble:(D)D
         7: dreturn
      LocalVariableTable:
        Start  Length  Slot  Name   Signature
            0       8     0   pos   D
    MethodParameters:
      Name                           Flags
      pos                            final

  public static double widenToDouble(double);
    descriptor: (D)D
    flags: (0x0009) ACC_PUBLIC, ACC_STATIC
    Code:
      stack=3, locals=2, args_size=1
         0: getstatic     #20                 // Field org/scalactic/anyvals/NonZeroFiniteDouble$.MODULE$:Lorg/scalactic/anyvals/NonZeroFiniteDouble$;
         3: dload_0
         4: invokevirtual #263                // Method org/scalactic/anyvals/NonZeroFiniteDouble$.widenToDouble:(D)D
         7: dreturn
      LocalVariableTable:
        Start  Length  Slot  Name   Signature
            0       8     0   pos   D
    MethodParameters:
      Name                           Flags
      pos                            final

  public static double fromOrElse(double, scala.Function0);
    descriptor: (DLscala/Function0;)D
    flags: (0x0009) ACC_PUBLIC, ACC_STATIC
    Code:
      stack=4, locals=3, args_size=2
         0: getstatic     #20                 // Field org/scalactic/anyvals/NonZeroFiniteDouble$.MODULE$:Lorg/scalactic/anyvals/NonZeroFiniteDouble$;
         3: dload_0
         4: aload_2
         5: invokevirtual #268                // Method org/scalactic/anyvals/NonZeroFiniteDouble$.fromOrElse:(DLscala/Function0;)D
         8: dreturn
      LocalVariableTable:
        Start  Length  Slot  Name   Signature
            0       9     0 value   D
            0       9     2 default   Lscala/Function0;
    MethodParameters:
      Name                           Flags
      value                          final
      default                        final

  public static boolean isValid(double);
    descriptor: (D)Z
    flags: (0x0009) ACC_PUBLIC, ACC_STATIC
    Code:
      stack=3, locals=2, args_size=1
         0: getstatic     #20                 // Field org/scalactic/anyvals/NonZeroFiniteDouble$.MODULE$:Lorg/scalactic/anyvals/NonZeroFiniteDouble$;
         3: dload_0
         4: invokevirtual #272                // Method org/scalactic/anyvals/NonZeroFiniteDouble$.isValid:(D)Z
         7: ireturn
      LocalVariableTable:
        Start  Length  Slot  Name   Signature
            0       8     0 value   D
    MethodParameters:
      Name                           Flags
      value                          final

  public static <L extends java.lang.Object> scala.util.Either<L, org.scalactic.anyvals.NonZeroFiniteDouble> rightOrElse(double, scala.Function1<java.lang.Object, L>);
    descriptor: (DLscala/Function1;)Lscala/util/Either;
    flags: (0x0009) ACC_PUBLIC, ACC_STATIC
    Code:
      stack=4, locals=3, args_size=2
         0: getstatic     #20                 // Field org/scalactic/anyvals/NonZeroFiniteDouble$.MODULE$:Lorg/scalactic/anyvals/NonZeroFiniteDouble$;
         3: dload_0
         4: aload_2
         5: invokevirtual #277                // Method org/scalactic/anyvals/NonZeroFiniteDouble$.rightOrElse:(DLscala/Function1;)Lscala/util/Either;
         8: areturn
      LocalVariableTable:
        Start  Length  Slot  Name   Signature
            0       9     0 value   D
            0       9     2     f   Lscala/Function1;
    Signature: #275                         // <L:Ljava/lang/Object;>(DLscala/Function1<Ljava/lang/Object;TL;>;)Lscala/util/Either<TL;Lorg/scalactic/anyvals/NonZeroFiniteDouble;>;
    MethodParameters:
      Name                           Flags
      value                          final
      f                              final

  public static <B extends java.lang.Object> org.scalactic.Or<org.scalactic.anyvals.NonZeroFiniteDouble, B> goodOrElse(double, scala.Function1<java.lang.Object, B>);
    descriptor: (DLscala/Function1;)Lorg/scalactic/Or;
    flags: (0x0009) ACC_PUBLIC, ACC_STATIC
    Code:
      stack=4, locals=3, args_size=2
         0: getstatic     #20                 // Field org/scalactic/anyvals/NonZeroFiniteDouble$.MODULE$:Lorg/scalactic/anyvals/NonZeroFiniteDouble$;
         3: dload_0
         4: aload_2
         5: invokevirtual #282                // Method org/scalactic/anyvals/NonZeroFiniteDouble$.goodOrElse:(DLscala/Function1;)Lorg/scalactic/Or;
         8: areturn
      LocalVariableTable:
        Start  Length  Slot  Name   Signature
            0       9     0 value   D
            0       9     2     f   Lscala/Function1;
    Signature: #280                         // <B:Ljava/lang/Object;>(DLscala/Function1<Ljava/lang/Object;TB;>;)Lorg/scalactic/Or<Lorg/scalactic/anyvals/NonZeroFiniteDouble;TB;>;
    MethodParameters:
      Name                           Flags
      value                          final
      f                              final

  public static <E extends java.lang.Object> org.scalactic.Validation<E> passOrElse(double, scala.Function1<java.lang.Object, E>);
    descriptor: (DLscala/Function1;)Lorg/scalactic/Validation;
    flags: (0x0009) ACC_PUBLIC, ACC_STATIC
    Code:
      stack=4, locals=3, args_size=2
         0: getstatic     #20                 // Field org/scalactic/anyvals/NonZeroFiniteDouble$.MODULE$:Lorg/scalactic/anyvals/NonZeroFiniteDouble$;
         3: dload_0
         4: aload_2
         5: invokevirtual #287                // Method org/scalactic/anyvals/NonZeroFiniteDouble$.passOrElse:(DLscala/Function1;)Lorg/scalactic/Validation;
         8: areturn
      LocalVariableTable:
        Start  Length  Slot  Name   Signature
            0       9     0 value   D
            0       9     2     f   Lscala/Function1;
    Signature: #285                         // <E:Ljava/lang/Object;>(DLscala/Function1<Ljava/lang/Object;TE;>;)Lorg/scalactic/Validation<TE;>;
    MethodParameters:
      Name                           Flags
      value                          final
      f                              final

  public static scala.util.Try<org.scalactic.anyvals.NonZeroFiniteDouble> tryingValid(double);
    descriptor: (D)Lscala/util/Try;
    flags: (0x0009) ACC_PUBLIC, ACC_STATIC
    Code:
      stack=3, locals=2, args_size=1
         0: getstatic     #20                 // Field org/scalactic/anyvals/NonZeroFiniteDouble$.MODULE$:Lorg/scalactic/anyvals/NonZeroFiniteDouble$;
         3: dload_0
         4: invokevirtual #292                // Method org/scalactic/anyvals/NonZeroFiniteDouble$.tryingValid:(D)Lscala/util/Try;
         7: areturn
      LocalVariableTable:
        Start  Length  Slot  Name   Signature
            0       8     0 value   D
    Signature: #290                         // (D)Lscala/util/Try<Lorg/scalactic/anyvals/NonZeroFiniteDouble;>;
    MethodParameters:
      Name                           Flags
      value                          final

  public static scala.Option<org.scalactic.anyvals.NonZeroFiniteDouble> from(double);
    descriptor: (D)Lscala/Option;
    flags: (0x0009) ACC_PUBLIC, ACC_STATIC
    Code:
      stack=3, locals=2, args_size=1
         0: getstatic     #20                 // Field org/scalactic/anyvals/NonZeroFiniteDouble$.MODULE$:Lorg/scalactic/anyvals/NonZeroFiniteDouble$;
         3: dload_0
         4: invokevirtual #297                // Method org/scalactic/anyvals/NonZeroFiniteDouble$.from:(D)Lscala/Option;
         7: areturn
      LocalVariableTable:
        Start  Length  Slot  Name   Signature
            0       8     0 value   D
    Signature: #295                         // (D)Lscala/Option<Lorg/scalactic/anyvals/NonZeroFiniteDouble;>;
    MethodParameters:
      Name                           Flags
      value                          final

  public static double MinValue();
    descriptor: ()D
    flags: (0x0009) ACC_PUBLIC, ACC_STATIC
    Code:
      stack=2, locals=0, args_size=0
         0: getstatic     #20                 // Field org/scalactic/anyvals/NonZeroFiniteDouble$.MODULE$:Lorg/scalactic/anyvals/NonZeroFiniteDouble$;
         3: invokevirtual #300                // Method org/scalactic/anyvals/NonZeroFiniteDouble$.MinValue:()D
         6: dreturn

  public static double MaxValue();
    descriptor: ()D
    flags: (0x0009) ACC_PUBLIC, ACC_STATIC
    Code:
      stack=2, locals=0, args_size=0
         0: getstatic     #20                 // Field org/scalactic/anyvals/NonZeroFiniteDouble$.MODULE$:Lorg/scalactic/anyvals/NonZeroFiniteDouble$;
         3: invokevirtual #303                // Method org/scalactic/anyvals/NonZeroFiniteDouble$.MaxValue:()D
         6: dreturn

  public double value();
    descriptor: ()D
    flags: (0x0001) ACC_PUBLIC
    Code:
      stack=2, locals=1, args_size=1
         0: aload_0
         1: getfield      #305                // Field value:D
         4: dreturn
      LineNumberTable:
        line 144: 0
      LocalVariableTable:
        Start  Length  Slot  Name   Signature
            0       5     0  this   Lorg/scalactic/anyvals/NonZeroFiniteDouble;

  public java.lang.String toString();
    descriptor: ()Ljava/lang/String;
    flags: (0x0001) ACC_PUBLIC
    Code:
      stack=3, locals=1, args_size=1
         0: getstatic     #20                 // Field org/scalactic/anyvals/NonZeroFiniteDouble$.MODULE$:Lorg/scalactic/anyvals/NonZeroFiniteDouble$;
         3: aload_0
         4: invokevirtual #311                // Method value:()D
         7: invokevirtual #247                // Method org/scalactic/anyvals/NonZeroFiniteDouble$.toString$extension:(D)Ljava/lang/String;
        10: areturn
      LineNumberTable:
        line 149: 0
      LocalVariableTable:
        Start  Length  Slot  Name   Signature
            0      11     0  this   Lorg/scalactic/anyvals/NonZeroFiniteDouble;

  public byte toByte();
    descriptor: ()B
    flags: (0x0001) ACC_PUBLIC
    Code:
      stack=3, locals=1, args_size=1
         0: getstatic     #20                 // Field org/scalactic/anyvals/NonZeroFiniteDouble$.MODULE$:Lorg/scalactic/anyvals/NonZeroFiniteDouble$;
         3: aload_0
         4: invokevirtual #311                // Method value:()D
         7: invokevirtual #243                // Method org/scalactic/anyvals/NonZeroFiniteDouble$.toByte$extension:(D)B
        10: ireturn
      LineNumberTable:
        line 154: 0
      LocalVariableTable:
        Start  Length  Slot  Name   Signature
            0      11     0  this   Lorg/scalactic/anyvals/NonZeroFiniteDouble;

  public short toShort();
    descriptor: ()S
    flags: (0x0001) ACC_PUBLIC
    Code:
      stack=3, locals=1, args_size=1
         0: getstatic     #20                 // Field org/scalactic/anyvals/NonZeroFiniteDouble$.MODULE$:Lorg/scalactic/anyvals/NonZeroFiniteDouble$;
         3: aload_0
         4: invokevirtual #311                // Method value:()D
         7: invokevirtual #239                // Method org/scalactic/anyvals/NonZeroFiniteDouble$.toShort$extension:(D)S
        10: ireturn
      LineNumberTable:
        line 159: 0
      LocalVariableTable:
        Start  Length  Slot  Name   Signature
            0      11     0  this   Lorg/scalactic/anyvals/NonZeroFiniteDouble;

  public char toChar();
    descriptor: ()C
    flags: (0x0001) ACC_PUBLIC
    Code:
      stack=3, locals=1, args_size=1
         0: getstatic     #20                 // Field org/scalactic/anyvals/NonZeroFiniteDouble$.MODULE$:Lorg/scalactic/anyvals/NonZeroFiniteDouble$;
         3: aload_0
         4: invokevirtual #311                // Method value:()D
         7: invokevirtual #235                // Method org/scalactic/anyvals/NonZeroFiniteDouble$.toChar$extension:(D)C
        10: ireturn
      LineNumberTable:
        line 164: 0
      LocalVariableTable:
        Start  Length  Slot  Name   Signature
            0      11     0  this   Lorg/scalactic/anyvals/NonZeroFiniteDouble;

  public int toInt();
    descriptor: ()I
    flags: (0x0001) ACC_PUBLIC
    Code:
      stack=3, locals=1, args_size=1
         0: getstatic     #20                 // Field org/scalactic/anyvals/NonZeroFiniteDouble$.MODULE$:Lorg/scalactic/anyvals/NonZeroFiniteDouble$;
         3: aload_0
         4: invokevirtual #311                // Method value:()D
         7: invokevirtual #231                // Method org/scalactic/anyvals/NonZeroFiniteDouble$.toInt$extension:(D)I
        10: ireturn
      LineNumberTable:
        line 169: 0
      LocalVariableTable:
        Start  Length  Slot  Name   Signature
            0      11     0  this   Lorg/scalactic/anyvals/NonZeroFiniteDouble;

  public long toLong();
    descriptor: ()J
    flags: (0x0001) ACC_PUBLIC
    Code:
      stack=3, locals=1, args_size=1
         0: getstatic     #20                 // Field org/scalactic/anyvals/NonZeroFiniteDouble$.MODULE$:Lorg/scalactic/anyvals/NonZeroFiniteDouble$;
         3: aload_0
         4: invokevirtual #311                // Method value:()D
         7: invokevirtual #228                // Method org/scalactic/anyvals/NonZeroFiniteDouble$.toLong$extension:(D)J
        10: lreturn
      LineNumberTable:
        line 174: 0
      LocalVariableTable:
        Start  Length  Slot  Name   Signature
            0      11     0  this   Lorg/scalactic/anyvals/NonZeroFiniteDouble;

  public float toFloat();
    descriptor: ()F
    flags: (0x0001) ACC_PUBLIC
    Code:
      stack=3, locals=1, args_size=1
         0: getstatic     #20                 // Field org/scalactic/anyvals/NonZeroFiniteDouble$.MODULE$:Lorg/scalactic/anyvals/NonZeroFiniteDouble$;
         3: aload_0
         4: invokevirtual #311                // Method value:()D
         7: invokevirtual #224                // Method org/scalactic/anyvals/NonZeroFiniteDouble$.toFloat$extension:(D)F
        10: freturn
      LineNumberTable:
        line 179: 0
      LocalVariableTable:
        Start  Length  Slot  Name   Signature
            0      11     0  this   Lorg/scalactic/anyvals/NonZeroFiniteDouble;

  public double toDouble();
    descriptor: ()D
    flags: (0x0001) ACC_PUBLIC
    Code:
      stack=3, locals=1, args_size=1
         0: getstatic     #20                 // Field org/scalactic/anyvals/NonZeroFiniteDouble$.MODULE$:Lorg/scalactic/anyvals/NonZeroFiniteDouble$;
         3: aload_0
         4: invokevirtual #311                // Method value:()D
         7: invokevirtual #220                // Method org/scalactic/anyvals/NonZeroFiniteDouble$.toDouble$extension:(D)D
        10: dreturn
      LineNumberTable:
        line 184: 0
      LocalVariableTable:
        Start  Length  Slot  Name   Signature
            0      11     0  this   Lorg/scalactic/anyvals/NonZeroFiniteDouble;

  public double unary_$plus();
    descriptor: ()D
    flags: (0x0001) ACC_PUBLIC
    Code:
      stack=3, locals=1, args_size=1
         0: getstatic     #20                 // Field org/scalactic/anyvals/NonZeroFiniteDouble$.MODULE$:Lorg/scalactic/anyvals/NonZeroFiniteDouble$;
         3: aload_0
         4: invokevirtual #311                // Method value:()D
         7: invokevirtual #217                // Method org/scalactic/anyvals/NonZeroFiniteDouble$.unary_$plus$extension:(D)D
        10: dreturn
      LineNumberTable:
        line 187: 0
      LocalVariableTable:
        Start  Length  Slot  Name   Signature
            0      11     0  this   Lorg/scalactic/anyvals/NonZeroFiniteDouble;

  public double unary_$minus();
    descriptor: ()D
    flags: (0x0001) ACC_PUBLIC
    Code:
      stack=3, locals=1, args_size=1
         0: getstatic     #20                 // Field org/scalactic/anyvals/NonZeroFiniteDouble$.MODULE$:Lorg/scalactic/anyvals/NonZeroFiniteDouble$;
         3: aload_0
         4: invokevirtual #311                // Method value:()D
         7: invokevirtual #214                // Method org/scalactic/anyvals/NonZeroFiniteDouble$.unary_$minus$extension:(D)D
        10: dreturn
      LineNumberTable:
        line 189: 0
      LocalVariableTable:
        Start  Length  Slot  Name   Signature
            0      11     0  this   Lorg/scalactic/anyvals/NonZeroFiniteDouble;

  public java.lang.String $plus(java.lang.String);
    descriptor: (Ljava/lang/String;)Ljava/lang/String;
    flags: (0x0001) ACC_PUBLIC
    Code:
      stack=4, locals=2, args_size=2
         0: getstatic     #20                 // Field org/scalactic/anyvals/NonZeroFiniteDouble$.MODULE$:Lorg/scalactic/anyvals/NonZeroFiniteDouble$;
         3: aload_0
         4: invokevirtual #311                // Method value:()D
         7: aload_1
         8: invokevirtual #210                // Method org/scalactic/anyvals/NonZeroFiniteDouble$.$plus$extension:(DLjava/lang/String;)Ljava/lang/String;
        11: areturn
      LineNumberTable:
        line 194: 0
      LocalVariableTable:
        Start  Length  Slot  Name   Signature
            0      12     0  this   Lorg/scalactic/anyvals/NonZeroFiniteDouble;
            0      12     1     x   Ljava/lang/String;
    MethodParameters:
      Name                           Flags
      x                              final

  public boolean $less(byte);
    descriptor: (B)Z
    flags: (0x0001) ACC_PUBLIC
    Code:
      stack=4, locals=2, args_size=2
         0: getstatic     #20                 // Field org/scalactic/anyvals/NonZeroFiniteDouble$.MODULE$:Lorg/scalactic/anyvals/NonZeroFiniteDouble$;
         3: aload_0
         4: invokevirtual #311                // Method value:()D
         7: iload_1
         8: invokevirtual #207                // Method org/scalactic/anyvals/NonZeroFiniteDouble$.$less$extension:(DB)Z
        11: ireturn
      LineNumberTable:
        line 197: 0
      LocalVariableTable:
        Start  Length  Slot  Name   Signature
            0      12     0  this   Lorg/scalactic/anyvals/NonZeroFiniteDouble;
            0      12     1     x   B
    MethodParameters:
      Name                           Flags
      x                              final

  public boolean $less(short);
    descriptor: (S)Z
    flags: (0x0001) ACC_PUBLIC
    Code:
      stack=4, locals=2, args_size=2
         0: getstatic     #20                 // Field org/scalactic/anyvals/NonZeroFiniteDouble$.MODULE$:Lorg/scalactic/anyvals/NonZeroFiniteDouble$;
         3: aload_0
         4: invokevirtual #311                // Method value:()D
         7: iload_1
         8: invokevirtual #205                // Method org/scalactic/anyvals/NonZeroFiniteDouble$.$less$extension:(DS)Z
        11: ireturn
      LineNumberTable:
        line 199: 0
      LocalVariableTable:
        Start  Length  Slot  Name   Signature
            0      12     0  this   Lorg/scalactic/anyvals/NonZeroFiniteDouble;
            0      12     1     x   S
    MethodParameters:
      Name                           Flags
      x                              final

  public boolean $less(char);
    descriptor: (C)Z
    flags: (0x0001) ACC_PUBLIC
    Code:
      stack=4, locals=2, args_size=2
         0: getstatic     #20                 // Field org/scalactic/anyvals/NonZeroFiniteDouble$.MODULE$:Lorg/scalactic/anyvals/NonZeroFiniteDouble$;
         3: aload_0
         4: invokevirtual #311                // Method value:()D
         7: iload_1
         8: invokevirtual #203                // Method org/scalactic/anyvals/NonZeroFiniteDouble$.$less$extension:(DC)Z
        11: ireturn
      LineNumberTable:
        line 201: 0
      LocalVariableTable:
        Start  Length  Slot  Name   Signature
            0      12     0  this   Lorg/scalactic/anyvals/NonZeroFiniteDouble;
            0      12     1     x   C
    MethodParameters:
      Name                           Flags
      x                              final

  public boolean $less(int);
    descriptor: (I)Z
    flags: (0x0001) ACC_PUBLIC
    Code:
      stack=4, locals=2, args_size=2
         0: getstatic     #20                 // Field org/scalactic/anyvals/NonZeroFiniteDouble$.MODULE$:Lorg/scalactic/anyvals/NonZeroFiniteDouble$;
         3: aload_0
         4: invokevirtual #311                // Method value:()D
         7: iload_1
         8: invokevirtual #201                // Method org/scalactic/anyvals/NonZeroFiniteDouble$.$less$extension:(DI)Z
        11: ireturn
      LineNumberTable:
        line 203: 0
      LocalVariableTable:
        Start  Length  Slot  Name   Signature
            0      12     0  this   Lorg/scalactic/anyvals/NonZeroFiniteDouble;
            0      12     1     x   I
    MethodParameters:
      Name                           Flags
      x                              final

  public boolean $less(long);
    descriptor: (J)Z
    flags: (0x0001) ACC_PUBLIC
    Code:
      stack=5, locals=3, args_size=2
         0: getstatic     #20                 // Field org/scalactic/anyvals/NonZeroFiniteDouble$.MODULE$:Lorg/scalactic/anyvals/NonZeroFiniteDouble$;
         3: aload_0
         4: invokevirtual #311                // Method value:()D
         7: lload_1
         8: invokevirtual #199                // Method org/scalactic/anyvals/NonZeroFiniteDouble$.$less$extension:(DJ)Z
        11: ireturn
      LineNumberTable:
        line 205: 0
      LocalVariableTable:
        Start  Length  Slot  Name   Signature
            0      12     0  this   Lorg/scalactic/anyvals/NonZeroFiniteDouble;
            0      12     1     x   J
    MethodParameters:
      Name                           Flags
      x                              final

  public boolean $less(float);
    descriptor: (F)Z
    flags: (0x0001) ACC_PUBLIC
    Code:
      stack=4, locals=2, args_size=2
         0: getstatic     #20                 // Field org/scalactic/anyvals/NonZeroFiniteDouble$.MODULE$:Lorg/scalactic/anyvals/NonZeroFiniteDouble$;
         3: aload_0
         4: invokevirtual #311                // Method value:()D
         7: fload_1
         8: invokevirtual #197                // Method org/scalactic/anyvals/NonZeroFiniteDouble$.$less$extension:(DF)Z
        11: ireturn
      LineNumberTable:
        line 207: 0
      LocalVariableTable:
        Start  Length  Slot  Name   Signature
            0      12     0  this   Lorg/scalactic/anyvals/NonZeroFiniteDouble;
            0      12     1     x   F
    MethodParameters:
      Name                           Flags
      x                              final

  public boolean $less(double);
    descriptor: (D)Z
    flags: (0x0001) ACC_PUBLIC
    Code:
      stack=5, locals=3, args_size=2
         0: getstatic     #20                 // Field org/scalactic/anyvals/NonZeroFiniteDouble$.MODULE$:Lorg/scalactic/anyvals/NonZeroFiniteDouble$;
         3: aload_0
         4: invokevirtual #311                // Method value:()D
         7: dload_1
         8: invokevirtual #195                // Method org/scalactic/anyvals/NonZeroFiniteDouble$.$less$extension:(DD)Z
        11: ireturn
      LineNumberTable:
        line 209: 0
      LocalVariableTable:
        Start  Length  Slot  Name   Signature
            0      12     0  this   Lorg/scalactic/anyvals/NonZeroFiniteDouble;
            0      12     1     x   D
    MethodParameters:
      Name                           Flags
      x                              final

  public boolean $less$eq(byte);
    descriptor: (B)Z
    flags: (0x0001) ACC_PUBLIC
    Code:
      stack=4, locals=2, args_size=2
         0: getstatic     #20                 // Field org/scalactic/anyvals/NonZeroFiniteDouble$.MODULE$:Lorg/scalactic/anyvals/NonZeroFiniteDouble$;
         3: aload_0
         4: invokevirtual #311                // Method value:()D
         7: iload_1
         8: invokevirtual #192                // Method org/scalactic/anyvals/NonZeroFiniteDouble$.$less$eq$extension:(DB)Z
        11: ireturn
      LineNumberTable:
        line 212: 0
      LocalVariableTable:
        Start  Length  Slot  Name   Signature
            0      12     0  this   Lorg/scalactic/anyvals/NonZeroFiniteDouble;
            0      12     1     x   B
    MethodParameters:
      Name                           Flags
      x                              final

  public boolean $less$eq(short);
    descriptor: (S)Z
    flags: (0x0001) ACC_PUBLIC
    Code:
      stack=4, locals=2, args_size=2
         0: getstatic     #20                 // Field org/scalactic/anyvals/NonZeroFiniteDouble$.MODULE$:Lorg/scalactic/anyvals/NonZeroFiniteDouble$;
         3: aload_0
         4: invokevirtual #311                // Method value:()D
         7: iload_1
         8: invokevirtual #190                // Method org/scalactic/anyvals/NonZeroFiniteDouble$.$less$eq$extension:(DS)Z
        11: ireturn
      LineNumberTable:
        line 214: 0
      LocalVariableTable:
        Start  Length  Slot  Name   Signature
            0      12     0  this   Lorg/scalactic/anyvals/NonZeroFiniteDouble;
            0      12     1     x   S
    MethodParameters:
      Name                           Flags
      x                              final

  public boolean $less$eq(char);
    descriptor: (C)Z
    flags: (0x0001) ACC_PUBLIC
    Code:
      stack=4, locals=2, args_size=2
         0: getstatic     #20                 // Field org/scalactic/anyvals/NonZeroFiniteDouble$.MODULE$:Lorg/scalactic/anyvals/NonZeroFiniteDouble$;
         3: aload_0
         4: invokevirtual #311                // Method value:()D
         7: iload_1
         8: invokevirtual #188                // Method org/scalactic/anyvals/NonZeroFiniteDouble$.$less$eq$extension:(DC)Z
        11: ireturn
      LineNumberTable:
        line 216: 0
      LocalVariableTable:
        Start  Length  Slot  Name   Signature
            0      12     0  this   Lorg/scalactic/anyvals/NonZeroFiniteDouble;
            0      12     1     x   C
    MethodParameters:
      Name                           Flags
      x                              final

  public boolean $less$eq(int);
    descriptor: (I)Z
    flags: (0x0001) ACC_PUBLIC
    Code:
      stack=4, locals=2, args_size=2
         0: getstatic     #20                 // Field org/scalactic/anyvals/NonZeroFiniteDouble$.MODULE$:Lorg/scalactic/anyvals/NonZeroFiniteDouble$;
         3: aload_0
         4: invokevirtual #311                // Method value:()D
         7: iload_1
         8: invokevirtual #186                // Method org/scalactic/anyvals/NonZeroFiniteDouble$.$less$eq$extension:(DI)Z
        11: ireturn
      LineNumberTable:
        line 218: 0
      LocalVariableTable:
        Start  Length  Slot  Name   Signature
            0      12     0  this   Lorg/scalactic/anyvals/NonZeroFiniteDouble;
            0      12     1     x   I
    MethodParameters:
      Name                           Flags
      x                              final

  public boolean $less$eq(long);
    descriptor: (J)Z
    flags: (0x0001) ACC_PUBLIC
    Code:
      stack=5, locals=3, args_size=2
         0: getstatic     #20                 // Field org/scalactic/anyvals/NonZeroFiniteDouble$.MODULE$:Lorg/scalactic/anyvals/NonZeroFiniteDouble$;
         3: aload_0
         4: invokevirtual #311                // Method value:()D
         7: lload_1
         8: invokevirtual #184                // Method org/scalactic/anyvals/NonZeroFiniteDouble$.$less$eq$extension:(DJ)Z
        11: ireturn
      LineNumberTable:
        line 220: 0
      LocalVariableTable:
        Start  Length  Slot  Name   Signature
            0      12     0  this   Lorg/scalactic/anyvals/NonZeroFiniteDouble;
            0      12     1     x   J
    MethodParameters:
      Name                           Flags
      x                              final

  public boolean $less$eq(float);
    descriptor: (F)Z
    flags: (0x0001) ACC_PUBLIC
    Code:
      stack=4, locals=2, args_size=2
         0: getstatic     #20                 // Field org/scalactic/anyvals/NonZeroFiniteDouble$.MODULE$:Lorg/scalactic/anyvals/NonZeroFiniteDouble$;
         3: aload_0
         4: invokevirtual #311                // Method value:()D
         7: fload_1
         8: invokevirtual #182                // Method org/scalactic/anyvals/NonZeroFiniteDouble$.$less$eq$extension:(DF)Z
        11: ireturn
      LineNumberTable:
        line 222: 0
      LocalVariableTable:
        Start  Length  Slot  Name   Signature
            0      12     0  this   Lorg/scalactic/anyvals/NonZeroFiniteDouble;
            0      12     1     x   F
    MethodParameters:
      Name                           Flags
      x                              final

  public boolean $less$eq(double);
    descriptor: (D)Z
    flags: (0x0001) ACC_PUBLIC
    Code:
      stack=5, locals=3, args_size=2
         0: getstatic     #20                 // Field org/scalactic/anyvals/NonZeroFiniteDouble$.MODULE$:Lorg/scalactic/anyvals/NonZeroFiniteDouble$;
         3: aload_0
         4: invokevirtual #311                // Method value:()D
         7: dload_1
         8: invokevirtual #180                // Method org/scalactic/anyvals/NonZeroFiniteDouble$.$less$eq$extension:(DD)Z
        11: ireturn
      LineNumberTable:
        line 224: 0
      LocalVariableTable:
        Start  Length  Slot  Name   Signature
            0      12     0  this   Lorg/scalactic/anyvals/NonZeroFiniteDouble;
            0      12     1     x   D
    MethodParameters:
      Name                           Flags
      x                              final

  public boolean $greater(byte);
    descriptor: (B)Z
    flags: (0x0001) ACC_PUBLIC
    Code:
      stack=4, locals=2, args_size=2
         0: getstatic     #20                 // Field org/scalactic/anyvals/NonZeroFiniteDouble$.MODULE$:Lorg/scalactic/anyvals/NonZeroFiniteDouble$;
         3: aload_0
         4: invokevirtual #311                // Method value:()D
         7: iload_1
         8: invokevirtual #177                // Method org/scalactic/anyvals/NonZeroFiniteDouble$.$greater$extension:(DB)Z
        11: ireturn
      LineNumberTable:
        line 227: 0
      LocalVariableTable:
        Start  Length  Slot  Name   Signature
            0      12     0  this   Lorg/scalactic/anyvals/NonZeroFiniteDouble;
            0      12     1     x   B
    MethodParameters:
      Name                           Flags
      x                              final

  public boolean $greater(short);
    descriptor: (S)Z
    flags: (0x0001) ACC_PUBLIC
    Code:
      stack=4, locals=2, args_size=2
         0: getstatic     #20                 // Field org/scalactic/anyvals/NonZeroFiniteDouble$.MODULE$:Lorg/scalactic/anyvals/NonZeroFiniteDouble$;
         3: aload_0
         4: invokevirtual #311                // Method value:()D
         7: iload_1
         8: invokevirtual #175                // Method org/scalactic/anyvals/NonZeroFiniteDouble$.$greater$extension:(DS)Z
        11: ireturn
      LineNumberTable:
        line 229: 0
      LocalVariableTable:
        Start  Length  Slot  Name   Signature
            0      12     0  this   Lorg/scalactic/anyvals/NonZeroFiniteDouble;
            0      12     1     x   S
    MethodParameters:
      Name                           Flags
      x                              final

  public boolean $greater(char);
    descriptor: (C)Z
    flags: (0x0001) ACC_PUBLIC
    Code:
      stack=4, locals=2, args_size=2
         0: getstatic     #20                 // Field org/scalactic/anyvals/NonZeroFiniteDouble$.MODULE$:Lorg/scalactic/anyvals/NonZeroFiniteDouble$;
         3: aload_0
         4: invokevirtual #311                // Method value:()D
         7: iload_1
         8: invokevirtual #173                // Method org/scalactic/anyvals/NonZeroFiniteDouble$.$greater$extension:(DC)Z
        11: ireturn
      LineNumberTable:
        line 231: 0
      LocalVariableTable:
        Start  Length  Slot  Name   Signature
            0      12     0  this   Lorg/scalactic/anyvals/NonZeroFiniteDouble;
            0      12     1     x   C
    MethodParameters:
      Name                           Flags
      x                              final

  public boolean $greater(int);
    descriptor: (I)Z
    flags: (0x0001) ACC_PUBLIC
    Code:
      stack=4, locals=2, args_size=2
         0: getstatic     #20                 // Field org/scalactic/anyvals/NonZeroFiniteDouble$.MODULE$:Lorg/scalactic/anyvals/NonZeroFiniteDouble$;
         3: aload_0
         4: invokevirtual #311                // Method value:()D
         7: iload_1
         8: invokevirtual #171                // Method org/scalactic/anyvals/NonZeroFiniteDouble$.$greater$extension:(DI)Z
        11: ireturn
      LineNumberTable:
        line 233: 0
      LocalVariableTable:
        Start  Length  Slot  Name   Signature
            0      12     0  this   Lorg/scalactic/anyvals/NonZeroFiniteDouble;
            0      12     1     x   I
    MethodParameters:
      Name                           Flags
      x                              final

  public boolean $greater(long);
    descriptor: (J)Z
    flags: (0x0001) ACC_PUBLIC
    Code:
      stack=5, locals=3, args_size=2
         0: getstatic     #20                 // Field org/scalactic/anyvals/NonZeroFiniteDouble$.MODULE$:Lorg/scalactic/anyvals/NonZeroFiniteDouble$;
         3: aload_0
         4: invokevirtual #311                // Method value:()D
         7: lload_1
         8: invokevirtual #169                // Method org/scalactic/anyvals/NonZeroFiniteDouble$.$greater$extension:(DJ)Z
        11: ireturn
      LineNumberTable:
        line 235: 0
      LocalVariableTable:
        Start  Length  Slot  Name   Signature
            0      12     0  this   Lorg/scalactic/anyvals/NonZeroFiniteDouble;
            0      12     1     x   J
    MethodParameters:
      Name                           Flags
      x                              final

  public boolean $greater(float);
    descriptor: (F)Z
    flags: (0x0001) ACC_PUBLIC
    Code:
      stack=4, locals=2, args_size=2
         0: getstatic     #20                 // Field org/scalactic/anyvals/NonZeroFiniteDouble$.MODULE$:Lorg/scalactic/anyvals/NonZeroFiniteDouble$;
         3: aload_0
         4: invokevirtual #311                // Method value:()D
         7: fload_1
         8: invokevirtual #167                // Method org/scalactic/anyvals/NonZeroFiniteDouble$.$greater$extension:(DF)Z
        11: ireturn
      LineNumberTable:
        line 237: 0
      LocalVariableTable:
        Start  Length  Slot  Name   Signature
            0      12     0  this   Lorg/scalactic/anyvals/NonZeroFiniteDouble;
            0      12     1     x   F
    MethodParameters:
      Name                           Flags
      x                              final

  public boolean $greater(double);
    descriptor: (D)Z
    flags: (0x0001) ACC_PUBLIC
    Code:
      stack=5, locals=3, args_size=2
         0: getstatic     #20                 // Field org/scalactic/anyvals/NonZeroFiniteDouble$.MODULE$:Lorg/scalactic/anyvals/NonZeroFiniteDouble$;
         3: aload_0
         4: invokevirtual #311                // Method value:()D
         7: dload_1
         8: invokevirtual #165                // Method org/scalactic/anyvals/NonZeroFiniteDouble$.$greater$extension:(DD)Z
        11: ireturn
      LineNumberTable:
        line 239: 0
      LocalVariableTable:
        Start  Length  Slot  Name   Signature
            0      12     0  this   Lorg/scalactic/anyvals/NonZeroFiniteDouble;
            0      12     1     x   D
    MethodParameters:
      Name                           Flags
      x                              final

  public boolean $greater$eq(byte);
    descriptor: (B)Z
    flags: (0x0001) ACC_PUBLIC
    Code:
      stack=4, locals=2, args_size=2
         0: getstatic     #20                 // Field org/scalactic/anyvals/NonZeroFiniteDouble$.MODULE$:Lorg/scalactic/anyvals/NonZeroFiniteDouble$;
         3: aload_0
         4: invokevirtual #311                // Method value:()D
         7: iload_1
         8: invokevirtual #162                // Method org/scalactic/anyvals/NonZeroFiniteDouble$.$greater$eq$extension:(DB)Z
        11: ireturn
      LineNumberTable:
        line 242: 0
      LocalVariableTable:
        Start  Length  Slot  Name   Signature
            0      12     0  this   Lorg/scalactic/anyvals/NonZeroFiniteDouble;
            0      12     1     x   B
    MethodParameters:
      Name                           Flags
      x                              final

  public boolean $greater$eq(short);
    descriptor: (S)Z
    flags: (0x0001) ACC_PUBLIC
    Code:
      stack=4, locals=2, args_size=2
         0: getstatic     #20                 // Field org/scalactic/anyvals/NonZeroFiniteDouble$.MODULE$:Lorg/scalactic/anyvals/NonZeroFiniteDouble$;
         3: aload_0
         4: invokevirtual #311                // Method value:()D
         7: iload_1
         8: invokevirtual #159                // Method org/scalactic/anyvals/NonZeroFiniteDouble$.$greater$eq$extension:(DS)Z
        11: ireturn
      LineNumberTable:
        line 244: 0
      LocalVariableTable:
        Start  Length  Slot  Name   Signature
            0      12     0  this   Lorg/scalactic/anyvals/NonZeroFiniteDouble;
            0      12     1     x   S
    MethodParameters:
      Name                           Flags
      x                              final

  public boolean $greater$eq(char);
    descriptor: (C)Z
    flags: (0x0001) ACC_PUBLIC
    Code:
      stack=4, locals=2, args_size=2
         0: getstatic     #20                 // Field org/scalactic/anyvals/NonZeroFiniteDouble$.MODULE$:Lorg/scalactic/anyvals/NonZeroFiniteDouble$;
         3: aload_0
         4: invokevirtual #311                // Method value:()D
         7: iload_1
         8: invokevirtual #156                // Method org/scalactic/anyvals/NonZeroFiniteDouble$.$greater$eq$extension:(DC)Z
        11: ireturn
      LineNumberTable:
        line 246: 0
      LocalVariableTable:
        Start  Length  Slot  Name   Signature
            0      12     0  this   Lorg/scalactic/anyvals/NonZeroFiniteDouble;
            0      12     1     x   C
    MethodParameters:
      Name                           Flags
      x                              final

  public boolean $greater$eq(int);
    descriptor: (I)Z
    flags: (0x0001) ACC_PUBLIC
    Code:
      stack=4, locals=2, args_size=2
         0: getstatic     #20                 // Field org/scalactic/anyvals/NonZeroFiniteDouble$.MODULE$:Lorg/scalactic/anyvals/NonZeroFiniteDouble$;
         3: aload_0
         4: invokevirtual #311                // Method value:()D
         7: iload_1
         8: invokevirtual #153                // Method org/scalactic/anyvals/NonZeroFiniteDouble$.$greater$eq$extension:(DI)Z
        11: ireturn
      LineNumberTable:
        line 248: 0
      LocalVariableTable:
        Start  Length  Slot  Name   Signature
            0      12     0  this   Lorg/scalactic/anyvals/NonZeroFiniteDouble;
            0      12     1     x   I
    MethodParameters:
      Name                           Flags
      x                              final

  public boolean $greater$eq(long);
    descriptor: (J)Z
    flags: (0x0001) ACC_PUBLIC
    Code:
      stack=5, locals=3, args_size=2
         0: getstatic     #20                 // Field org/scalactic/anyvals/NonZeroFiniteDouble$.MODULE$:Lorg/scalactic/anyvals/NonZeroFiniteDouble$;
         3: aload_0
         4: invokevirtual #311                // Method value:()D
         7: lload_1
         8: invokevirtual #150                // Method org/scalactic/anyvals/NonZeroFiniteDouble$.$greater$eq$extension:(DJ)Z
        11: ireturn
      LineNumberTable:
        line 250: 0
      LocalVariableTable:
        Start  Length  Slot  Name   Signature
            0      12     0  this   Lorg/scalactic/anyvals/NonZeroFiniteDouble;
            0      12     1     x   J
    MethodParameters:
      Name                           Flags
      x                              final

  public boolean $greater$eq(float);
    descriptor: (F)Z
    flags: (0x0001) ACC_PUBLIC
    Code:
      stack=4, locals=2, args_size=2
         0: getstatic     #20                 // Field org/scalactic/anyvals/NonZeroFiniteDouble$.MODULE$:Lorg/scalactic/anyvals/NonZeroFiniteDouble$;
         3: aload_0
         4: invokevirtual #311                // Method value:()D
         7: fload_1
         8: invokevirtual #147                // Method org/scalactic/anyvals/NonZeroFiniteDouble$.$greater$eq$extension:(DF)Z
        11: ireturn
      LineNumberTable:
        line 252: 0
      LocalVariableTable:
        Start  Length  Slot  Name   Signature
            0      12     0  this   Lorg/scalactic/anyvals/NonZeroFiniteDouble;
            0      12     1     x   F
    MethodParameters:
      Name                           Flags
      x                              final

  public boolean $greater$eq(double);
    descriptor: (D)Z
    flags: (0x0001) ACC_PUBLIC
    Code:
      stack=5, locals=3, args_size=2
         0: getstatic     #20                 // Field org/scalactic/anyvals/NonZeroFiniteDouble$.MODULE$:Lorg/scalactic/anyvals/NonZeroFiniteDouble$;
         3: aload_0
         4: invokevirtual #311                // Method value:()D
         7: dload_1
         8: invokevirtual #144                // Method org/scalactic/anyvals/NonZeroFiniteDouble$.$greater$eq$extension:(DD)Z
        11: ireturn
      LineNumberTable:
        line 254: 0
      LocalVariableTable:
        Start  Length  Slot  Name   Signature
            0      12     0  this   Lorg/scalactic/anyvals/NonZeroFiniteDouble;
            0      12     1     x   D
    MethodParameters:
      Name                           Flags
      x                              final

  public double $plus(byte);
    descriptor: (B)D
    flags: (0x0001) ACC_PUBLIC
    Code:
      stack=4, locals=2, args_size=2
         0: getstatic     #20                 // Field org/scalactic/anyvals/NonZeroFiniteDouble$.MODULE$:Lorg/scalactic/anyvals/NonZeroFiniteDouble$;
         3: aload_0
         4: invokevirtual #311                // Method value:()D
         7: iload_1
         8: invokevirtual #140                // Method org/scalactic/anyvals/NonZeroFiniteDouble$.$plus$extension:(DB)D
        11: dreturn
      LineNumberTable:
        line 257: 0
      LocalVariableTable:
        Start  Length  Slot  Name   Signature
            0      12     0  this   Lorg/scalactic/anyvals/NonZeroFiniteDouble;
            0      12     1     x   B
    MethodParameters:
      Name                           Flags
      x                              final

  public double $plus(short);
    descriptor: (S)D
    flags: (0x0001) ACC_PUBLIC
    Code:
      stack=4, locals=2, args_size=2
         0: getstatic     #20                 // Field org/scalactic/anyvals/NonZeroFiniteDouble$.MODULE$:Lorg/scalactic/anyvals/NonZeroFiniteDouble$;
         3: aload_0
         4: invokevirtual #311                // Method value:()D
         7: iload_1
         8: invokevirtual #138                // Method org/scalactic/anyvals/NonZeroFiniteDouble$.$plus$extension:(DS)D
        11: dreturn
      LineNumberTable:
        line 259: 0
      LocalVariableTable:
        Start  Length  Slot  Name   Signature
            0      12     0  this   Lorg/scalactic/anyvals/NonZeroFiniteDouble;
            0      12     1     x   S
    MethodParameters:
      Name                           Flags
      x                              final

  public double $plus(char);
    descriptor: (C)D
    flags: (0x0001) ACC_PUBLIC
    Code:
      stack=4, locals=2, args_size=2
         0: getstatic     #20                 // Field org/scalactic/anyvals/NonZeroFiniteDouble$.MODULE$:Lorg/scalactic/anyvals/NonZeroFiniteDouble$;
         3: aload_0
         4: invokevirtual #311                // Method value:()D
         7: iload_1
         8: invokevirtual #136                // Method org/scalactic/anyvals/NonZeroFiniteDouble$.$plus$extension:(DC)D
        11: dreturn
      LineNumberTable:
        line 261: 0
      LocalVariableTable:
        Start  Length  Slot  Name   Signature
            0      12     0  this   Lorg/scalactic/anyvals/NonZeroFiniteDouble;
            0      12     1     x   C
    MethodParameters:
      Name                           Flags
      x                              final

  public double $plus(int);
    descriptor: (I)D
    flags: (0x0001) ACC_PUBLIC
    Code:
      stack=4, locals=2, args_size=2
         0: getstatic     #20                 // Field org/scalactic/anyvals/NonZeroFiniteDouble$.MODULE$:Lorg/scalactic/anyvals/NonZeroFiniteDouble$;
         3: aload_0
         4: invokevirtual #311                // Method value:()D
         7: iload_1
         8: invokevirtual #134                // Method org/scalactic/anyvals/NonZeroFiniteDouble$.$plus$extension:(DI)D
        11: dreturn
      LineNumberTable:
        line 263: 0
      LocalVariableTable:
        Start  Length  Slot  Name   Signature
            0      12     0  this   Lorg/scalactic/anyvals/NonZeroFiniteDouble;
            0      12     1     x   I
    MethodParameters:
      Name                           Flags
      x                              final

  public double $plus(long);
    descriptor: (J)D
    flags: (0x0001) ACC_PUBLIC
    Code:
      stack=5, locals=3, args_size=2
         0: getstatic     #20                 // Field org/scalactic/anyvals/NonZeroFiniteDouble$.MODULE$:Lorg/scalactic/anyvals/NonZeroFiniteDouble$;
         3: aload_0
         4: invokevirtual #311                // Method value:()D
         7: lload_1
         8: invokevirtual #132                // Method org/scalactic/anyvals/NonZeroFiniteDouble$.$plus$extension:(DJ)D
        11: dreturn
      LineNumberTable:
        line 265: 0
      LocalVariableTable:
        Start  Length  Slot  Name   Signature
            0      12     0  this   Lorg/scalactic/anyvals/NonZeroFiniteDouble;
            0      12     1     x   J
    MethodParameters:
      Name                           Flags
      x                              final

  public double $plus(float);
    descriptor: (F)D
    flags: (0x0001) ACC_PUBLIC
    Code:
      stack=4, locals=2, args_size=2
         0: getstatic     #20                 // Field org/scalactic/anyvals/NonZeroFiniteDouble$.MODULE$:Lorg/scalactic/anyvals/NonZeroFiniteDouble$;
         3: aload_0
         4: invokevirtual #311                // Method value:()D
         7: fload_1
         8: invokevirtual #130                // Method org/scalactic/anyvals/NonZeroFiniteDouble$.$plus$extension:(DF)D
        11: dreturn
      LineNumberTable:
        line 267: 0
      LocalVariableTable:
        Start  Length  Slot  Name   Signature
            0      12     0  this   Lorg/scalactic/anyvals/NonZeroFiniteDouble;
            0      12     1     x   F
    MethodParameters:
      Name                           Flags
      x                              final

  public double $plus(double);
    descriptor: (D)D
    flags: (0x0001) ACC_PUBLIC
    Code:
      stack=5, locals=3, args_size=2
         0: getstatic     #20                 // Field org/scalactic/anyvals/NonZeroFiniteDouble$.MODULE$:Lorg/scalactic/anyvals/NonZeroFiniteDouble$;
         3: aload_0
         4: invokevirtual #311                // Method value:()D
         7: dload_1
         8: invokevirtual #128                // Method org/scalactic/anyvals/NonZeroFiniteDouble$.$plus$extension:(DD)D
        11: dreturn
      LineNumberTable:
        line 269: 0
      LocalVariableTable:
        Start  Length  Slot  Name   Signature
            0      12     0  this   Lorg/scalactic/anyvals/NonZeroFiniteDouble;
            0      12     1     x   D
    MethodParameters:
      Name                           Flags
      x                              final

  public double $minus(byte);
    descriptor: (B)D
    flags: (0x0001) ACC_PUBLIC
    Code:
      stack=4, locals=2, args_size=2
         0: getstatic     #20                 // Field org/scalactic/anyvals/NonZeroFiniteDouble$.MODULE$:Lorg/scalactic/anyvals/NonZeroFiniteDouble$;
         3: aload_0
         4: invokevirtual #311                // Method value:()D
         7: iload_1
         8: invokevirtual #125                // Method org/scalactic/anyvals/NonZeroFiniteDouble$.$minus$extension:(DB)D
        11: dreturn
      LineNumberTable:
        line 272: 0
      LocalVariableTable:
        Start  Length  Slot  Name   Signature
            0      12     0  this   Lorg/scalactic/anyvals/NonZeroFiniteDouble;
            0      12     1     x   B
    MethodParameters:
      Name                           Flags
      x                              final

  public double $minus(short);
    descriptor: (S)D
    flags: (0x0001) ACC_PUBLIC
    Code:
      stack=4, locals=2, args_size=2
         0: getstatic     #20                 // Field org/scalactic/anyvals/NonZeroFiniteDouble$.MODULE$:Lorg/scalactic/anyvals/NonZeroFiniteDouble$;
         3: aload_0
         4: invokevirtual #311                // Method value:()D
         7: iload_1
         8: invokevirtual #123                // Method org/scalactic/anyvals/NonZeroFiniteDouble$.$minus$extension:(DS)D
        11: dreturn
      LineNumberTable:
        line 274: 0
      LocalVariableTable:
        Start  Length  Slot  Name   Signature
            0      12     0  this   Lorg/scalactic/anyvals/NonZeroFiniteDouble;
            0      12     1     x   S
    MethodParameters:
      Name                           Flags
      x                              final

  public double $minus(char);
    descriptor: (C)D
    flags: (0x0001) ACC_PUBLIC
    Code:
      stack=4, locals=2, args_size=2
         0: getstatic     #20                 // Field org/scalactic/anyvals/NonZeroFiniteDouble$.MODULE$:Lorg/scalactic/anyvals/NonZeroFiniteDouble$;
         3: aload_0
         4: invokevirtual #311                // Method value:()D
         7: iload_1
         8: invokevirtual #121                // Method org/scalactic/anyvals/NonZeroFiniteDouble$.$minus$extension:(DC)D
        11: dreturn
      LineNumberTable:
        line 276: 0
      LocalVariableTable:
        Start  Length  Slot  Name   Signature
            0      12     0  this   Lorg/scalactic/anyvals/NonZeroFiniteDouble;
            0      12     1     x   C
    MethodParameters:
      Name                           Flags
      x                              final

  public double $minus(int);
    descriptor: (I)D
    flags: (0x0001) ACC_PUBLIC
    Code:
      stack=4, locals=2, args_size=2
         0: getstatic     #20                 // Field org/scalactic/anyvals/NonZeroFiniteDouble$.MODULE$:Lorg/scalactic/anyvals/NonZeroFiniteDouble$;
         3: aload_0
         4: invokevirtual #311                // Method value:()D
         7: iload_1
         8: invokevirtual #119                // Method org/scalactic/anyvals/NonZeroFiniteDouble$.$minus$extension:(DI)D
        11: dreturn
      LineNumberTable:
        line 278: 0
      LocalVariableTable:
        Start  Length  Slot  Name   Signature
            0      12     0  this   Lorg/scalactic/anyvals/NonZeroFiniteDouble;
            0      12     1     x   I
    MethodParameters:
      Name                           Flags
      x                              final

  public double $minus(long);
    descriptor: (J)D
    flags: (0x0001) ACC_PUBLIC
    Code:
      stack=5, locals=3, args_size=2
         0: getstatic     #20                 // Field org/scalactic/anyvals/NonZeroFiniteDouble$.MODULE$:Lorg/scalactic/anyvals/NonZeroFiniteDouble$;
         3: aload_0
         4: invokevirtual #311                // Method value:()D
         7: lload_1
         8: invokevirtual #117                // Method org/scalactic/anyvals/NonZeroFiniteDouble$.$minus$extension:(DJ)D
        11: dreturn
      LineNumberTable:
        line 280: 0
      LocalVariableTable:
        Start  Length  Slot  Name   Signature
            0      12     0  this   Lorg/scalactic/anyvals/NonZeroFiniteDouble;
            0      12     1     x   J
    MethodParameters:
      Name                           Flags
      x                              final

  public double $minus(float);
    descriptor: (F)D
    flags: (0x0001) ACC_PUBLIC
    Code:
      stack=4, locals=2, args_size=2
         0: getstatic     #20                 // Field org/scalactic/anyvals/NonZeroFiniteDouble$.MODULE$:Lorg/scalactic/anyvals/NonZeroFiniteDouble$;
         3: aload_0
         4: invokevirtual #311                // Method value:()D
         7: fload_1
         8: invokevirtual #115                // Method org/scalactic/anyvals/NonZeroFiniteDouble$.$minus$extension:(DF)D
        11: dreturn
      LineNumberTable:
        line 282: 0
      LocalVariableTable:
        Start  Length  Slot  Name   Signature
            0      12     0  this   Lorg/scalactic/anyvals/NonZeroFiniteDouble;
            0      12     1     x   F
    MethodParameters:
      Name                           Flags
      x                              final

  public double $minus(double);
    descriptor: (D)D
    flags: (0x0001) ACC_PUBLIC
    Code:
      stack=5, locals=3, args_size=2
         0: getstatic     #20                 // Field org/scalactic/anyvals/NonZeroFiniteDouble$.MODULE$:Lorg/scalactic/anyvals/NonZeroFiniteDouble$;
         3: aload_0
         4: invokevirtual #311                // Method value:()D
         7: dload_1
         8: invokevirtual #113                // Method org/scalactic/anyvals/NonZeroFiniteDouble$.$minus$extension:(DD)D
        11: dreturn
      LineNumberTable:
        line 284: 0
      LocalVariableTable:
        Start  Length  Slot  Name   Signature
            0      12     0  this   Lorg/scalactic/anyvals/NonZeroFiniteDouble;
            0      12     1     x   D
    MethodParameters:
      Name                           Flags
      x                              final

  public double $times(byte);
    descriptor: (B)D
    flags: (0x0001) ACC_PUBLIC
    Code:
      stack=4, locals=2, args_size=2
         0: getstatic     #20                 // Field org/scalactic/anyvals/NonZeroFiniteDouble$.MODULE$:Lorg/scalactic/anyvals/NonZeroFiniteDouble$;
         3: aload_0
         4: invokevirtual #311                // Method value:()D
         7: iload_1
         8: invokevirtual #110                // Method org/scalactic/anyvals/NonZeroFiniteDouble$.$times$extension:(DB)D
        11: dreturn
      LineNumberTable:
        line 287: 0
      LocalVariableTable:
        Start  Length  Slot  Name   Signature
            0      12     0  this   Lorg/scalactic/anyvals/NonZeroFiniteDouble;
            0      12     1     x   B
    MethodParameters:
      Name                           Flags
      x                              final

  public double $times(short);
    descriptor: (S)D
    flags: (0x0001) ACC_PUBLIC
    Code:
      stack=4, locals=2, args_size=2
         0: getstatic     #20                 // Field org/scalactic/anyvals/NonZeroFiniteDouble$.MODULE$:Lorg/scalactic/anyvals/NonZeroFiniteDouble$;
         3: aload_0
         4: invokevirtual #311                // Method value:()D
         7: iload_1
         8: invokevirtual #108                // Method org/scalactic/anyvals/NonZeroFiniteDouble$.$times$extension:(DS)D
        11: dreturn
      LineNumberTable:
        line 289: 0
      LocalVariableTable:
        Start  Length  Slot  Name   Signature
            0      12     0  this   Lorg/scalactic/anyvals/NonZeroFiniteDouble;
            0      12     1     x   S
    MethodParameters:
      Name                           Flags
      x                              final

  public double $times(char);
    descriptor: (C)D
    flags: (0x0001) ACC_PUBLIC
    Code:
      stack=4, locals=2, args_size=2
         0: getstatic     #20                 // Field org/scalactic/anyvals/NonZeroFiniteDouble$.MODULE$:Lorg/scalactic/anyvals/NonZeroFiniteDouble$;
         3: aload_0
         4: invokevirtual #311                // Method value:()D
         7: iload_1
         8: invokevirtual #106                // Method org/scalactic/anyvals/NonZeroFiniteDouble$.$times$extension:(DC)D
        11: dreturn
      LineNumberTable:
        line 291: 0
      LocalVariableTable:
        Start  Length  Slot  Name   Signature
            0      12     0  this   Lorg/scalactic/anyvals/NonZeroFiniteDouble;
            0      12     1     x   C
    MethodParameters:
      Name                           Flags
      x                              final

  public double $times(int);
    descriptor: (I)D
    flags: (0x0001) ACC_PUBLIC
    Code:
      stack=4, locals=2, args_size=2
         0: getstatic     #20                 // Field org/scalactic/anyvals/NonZeroFiniteDouble$.MODULE$:Lorg/scalactic/anyvals/NonZeroFiniteDouble$;
         3: aload_0
         4: invokevirtual #311                // Method value:()D
         7: iload_1
         8: invokevirtual #104                // Method org/scalactic/anyvals/NonZeroFiniteDouble$.$times$extension:(DI)D
        11: dreturn
      LineNumberTable:
        line 293: 0
      LocalVariableTable:
        Start  Length  Slot  Name   Signature
            0      12     0  this   Lorg/scalactic/anyvals/NonZeroFiniteDouble;
            0      12     1     x   I
    MethodParameters:
      Name                           Flags
      x                              final

  public double $times(long);
    descriptor: (J)D
    flags: (0x0001) ACC_PUBLIC
    Code:
      stack=5, locals=3, args_size=2
         0: getstatic     #20                 // Field org/scalactic/anyvals/NonZeroFiniteDouble$.MODULE$:Lorg/scalactic/anyvals/NonZeroFiniteDouble$;
         3: aload_0
         4: invokevirtual #311                // Method value:()D
         7: lload_1
         8: invokevirtual #102                // Method org/scalactic/anyvals/NonZeroFiniteDouble$.$times$extension:(DJ)D
        11: dreturn
      LineNumberTable:
        line 295: 0
      LocalVariableTable:
        Start  Length  Slot  Name   Signature
            0      12     0  this   Lorg/scalactic/anyvals/NonZeroFiniteDouble;
            0      12     1     x   J
    MethodParameters:
      Name                           Flags
      x                              final

  public double $times(float);
    descriptor: (F)D
    flags: (0x0001) ACC_PUBLIC
    Code:
      stack=4, locals=2, args_size=2
         0: getstatic     #20                 // Field org/scalactic/anyvals/NonZeroFiniteDouble$.MODULE$:Lorg/scalactic/anyvals/NonZeroFiniteDouble$;
         3: aload_0
         4: invokevirtual #311                // Method value:()D
         7: fload_1
         8: invokevirtual #100                // Method org/scalactic/anyvals/NonZeroFiniteDouble$.$times$extension:(DF)D
        11: dreturn
      LineNumberTable:
        line 297: 0
      LocalVariableTable:
        Start  Length  Slot  Name   Signature
            0      12     0  this   Lorg/scalactic/anyvals/NonZeroFiniteDouble;
            0      12     1     x   F
    MethodParameters:
      Name                           Flags
      x                              final

  public double $times(double);
    descriptor: (D)D
    flags: (0x0001) ACC_PUBLIC
    Code:
      stack=5, locals=3, args_size=2
         0: getstatic     #20                 // Field org/scalactic/anyvals/NonZeroFiniteDouble$.MODULE$:Lorg/scalactic/anyvals/NonZeroFiniteDouble$;
         3: aload_0
         4: invokevirtual #311                // Method value:()D
         7: dload_1
         8: invokevirtual #98                 // Method org/scalactic/anyvals/NonZeroFiniteDouble$.$times$extension:(DD)D
        11: dreturn
      LineNumberTable:
        line 299: 0
      LocalVariableTable:
        Start  Length  Slot  Name   Signature
            0      12     0  this   Lorg/scalactic/anyvals/NonZeroFiniteDouble;
            0      12     1     x   D
    MethodParameters:
      Name                           Flags
      x                              final

  public double $div(byte);
    descriptor: (B)D
    flags: (0x0001) ACC_PUBLIC
    Code:
      stack=4, locals=2, args_size=2
         0: getstatic     #20                 // Field org/scalactic/anyvals/NonZeroFiniteDouble$.MODULE$:Lorg/scalactic/anyvals/NonZeroFiniteDouble$;
         3: aload_0
         4: invokevirtual #311                // Method value:()D
         7: iload_1
         8: invokevirtual #95                 // Method org/scalactic/anyvals/NonZeroFiniteDouble$.$div$extension:(DB)D
        11: dreturn
      LineNumberTable:
        line 302: 0
      LocalVariableTable:
        Start  Length  Slot  Name   Signature
            0      12     0  this   Lorg/scalactic/anyvals/NonZeroFiniteDouble;
            0      12     1     x   B
    MethodParameters:
      Name                           Flags
      x                              final

  public double $div(short);
    descriptor: (S)D
    flags: (0x0001) ACC_PUBLIC
    Code:
      stack=4, locals=2, args_size=2
         0: getstatic     #20                 // Field org/scalactic/anyvals/NonZeroFiniteDouble$.MODULE$:Lorg/scalactic/anyvals/NonZeroFiniteDouble$;
         3: aload_0
         4: invokevirtual #311                // Method value:()D
         7: iload_1
         8: invokevirtual #93                 // Method org/scalactic/anyvals/NonZeroFiniteDouble$.$div$extension:(DS)D
        11: dreturn
      LineNumberTable:
        line 304: 0
      LocalVariableTable:
        Start  Length  Slot  Name   Signature
            0      12     0  this   Lorg/scalactic/anyvals/NonZeroFiniteDouble;
            0      12     1     x   S
    MethodParameters:
      Name                           Flags
      x                              final

  public double $div(char);
    descriptor: (C)D
    flags: (0x0001) ACC_PUBLIC
    Code:
      stack=4, locals=2, args_size=2
         0: getstatic     #20                 // Field org/scalactic/anyvals/NonZeroFiniteDouble$.MODULE$:Lorg/scalactic/anyvals/NonZeroFiniteDouble$;
         3: aload_0
         4: invokevirtual #311                // Method value:()D
         7: iload_1
         8: invokevirtual #91                 // Method org/scalactic/anyvals/NonZeroFiniteDouble$.$div$extension:(DC)D
        11: dreturn
      LineNumberTable:
        line 306: 0
      LocalVariableTable:
        Start  Length  Slot  Name   Signature
            0      12     0  this   Lorg/scalactic/anyvals/NonZeroFiniteDouble;
            0      12     1     x   C
    MethodParameters:
      Name                           Flags
      x                              final

  public double $div(int);
    descriptor: (I)D
    flags: (0x0001) ACC_PUBLIC
    Code:
      stack=4, locals=2, args_size=2
         0: getstatic     #20                 // Field org/scalactic/anyvals/NonZeroFiniteDouble$.MODULE$:Lorg/scalactic/anyvals/NonZeroFiniteDouble$;
         3: aload_0
         4: invokevirtual #311                // Method value:()D
         7: iload_1
         8: invokevirtual #89                 // Method org/scalactic/anyvals/NonZeroFiniteDouble$.$div$extension:(DI)D
        11: dreturn
      LineNumberTable:
        line 308: 0
      LocalVariableTable:
        Start  Length  Slot  Name   Signature
            0      12     0  this   Lorg/scalactic/anyvals/NonZeroFiniteDouble;
            0      12     1     x   I
    MethodParameters:
      Name                           Flags
      x                              final

  public double $div(long);
    descriptor: (J)D
    flags: (0x0001) ACC_PUBLIC
    Code:
      stack=5, locals=3, args_size=2
         0: getstatic     #20                 // Field org/scalactic/anyvals/NonZeroFiniteDouble$.MODULE$:Lorg/scalactic/anyvals/NonZeroFiniteDouble$;
         3: aload_0
         4: invokevirtual #311                // Method value:()D
         7: lload_1
         8: invokevirtual #87                 // Method org/scalactic/anyvals/NonZeroFiniteDouble$.$div$extension:(DJ)D
        11: dreturn
      LineNumberTable:
        line 310: 0
      LocalVariableTable:
        Start  Length  Slot  Name   Signature
            0      12     0  this   Lorg/scalactic/anyvals/NonZeroFiniteDouble;
            0      12     1     x   J
    MethodParameters:
      Name                           Flags
      x                              final

  public double $div(float);
    descriptor: (F)D
    flags: (0x0001) ACC_PUBLIC
    Code:
      stack=4, locals=2, args_size=2
         0: getstatic     #20                 // Field org/scalactic/anyvals/NonZeroFiniteDouble$.MODULE$:Lorg/scalactic/anyvals/NonZeroFiniteDouble$;
         3: aload_0
         4: invokevirtual #311                // Method value:()D
         7: fload_1
         8: invokevirtual #85                 // Method org/scalactic/anyvals/NonZeroFiniteDouble$.$div$extension:(DF)D
        11: dreturn
      LineNumberTable:
        line 312: 0
      LocalVariableTable:
        Start  Length  Slot  Name   Signature
            0      12     0  this   Lorg/scalactic/anyvals/NonZeroFiniteDouble;
            0      12     1     x   F
    MethodParameters:
      Name                           Flags
      x                              final

  public double $div(double);
    descriptor: (D)D
    flags: (0x0001) ACC_PUBLIC
    Code:
      stack=5, locals=3, args_size=2
         0: getstatic     #20                 // Field org/scalactic/anyvals/NonZeroFiniteDouble$.MODULE$:Lorg/scalactic/anyvals/NonZeroFiniteDouble$;
         3: aload_0
         4: invokevirtual #311                // Method value:()D
         7: dload_1
         8: invokevirtual #83                 // Method org/scalactic/anyvals/NonZeroFiniteDouble$.$div$extension:(DD)D
        11: dreturn
      LineNumberTable:
        line 314: 0
      LocalVariableTable:
        Start  Length  Slot  Name   Signature
            0      12     0  this   Lorg/scalactic/anyvals/NonZeroFiniteDouble;
            0      12     1     x   D
    MethodParameters:
      Name                           Flags
      x                              final

  public double $percent(byte);
    descriptor: (B)D
    flags: (0x0001) ACC_PUBLIC
    Code:
      stack=4, locals=2, args_size=2
         0: getstatic     #20                 // Field org/scalactic/anyvals/NonZeroFiniteDouble$.MODULE$:Lorg/scalactic/anyvals/NonZeroFiniteDouble$;
         3: aload_0
         4: invokevirtual #311                // Method value:()D
         7: iload_1
         8: invokevirtual #79                 // Method org/scalactic/anyvals/NonZeroFiniteDouble$.$percent$extension:(DB)D
        11: dreturn
      LineNumberTable:
        line 317: 0
      LocalVariableTable:
        Start  Length  Slot  Name   Signature
            0      12     0  this   Lorg/scalactic/anyvals/NonZeroFiniteDouble;
            0      12     1     x   B
    MethodParameters:
      Name                           Flags
      x                              final

  public double $percent(short);
    descriptor: (S)D
    flags: (0x0001) ACC_PUBLIC
    Code:
      stack=4, locals=2, args_size=2
         0: getstatic     #20                 // Field org/scalactic/anyvals/NonZeroFiniteDouble$.MODULE$:Lorg/scalactic/anyvals/NonZeroFiniteDouble$;
         3: aload_0
         4: invokevirtual #311                // Method value:()D
         7: iload_1
         8: invokevirtual #75                 // Method org/scalactic/anyvals/NonZeroFiniteDouble$.$percent$extension:(DS)D
        11: dreturn
      LineNumberTable:
        line 319: 0
      LocalVariableTable:
        Start  Length  Slot  Name   Signature
            0      12     0  this   Lorg/scalactic/anyvals/NonZeroFiniteDouble;
            0      12     1     x   S
    MethodParameters:
      Name                           Flags
      x                              final

  public double $percent(char);
    descriptor: (C)D
    flags: (0x0001) ACC_PUBLIC
    Code:
      stack=4, locals=2, args_size=2
         0: getstatic     #20                 // Field org/scalactic/anyvals/NonZeroFiniteDouble$.MODULE$:Lorg/scalactic/anyvals/NonZeroFiniteDouble$;
         3: aload_0
         4: invokevirtual #311                // Method value:()D
         7: iload_1
         8: invokevirtual #71                 // Method org/scalactic/anyvals/NonZeroFiniteDouble$.$percent$extension:(DC)D
        11: dreturn
      LineNumberTable:
        line 321: 0
      LocalVariableTable:
        Start  Length  Slot  Name   Signature
            0      12     0  this   Lorg/scalactic/anyvals/NonZeroFiniteDouble;
            0      12     1     x   C
    MethodParameters:
      Name                           Flags
      x                              final

  public double $percent(int);
    descriptor: (I)D
    flags: (0x0001) ACC_PUBLIC
    Code:
      stack=4, locals=2, args_size=2
         0: getstatic     #20                 // Field org/scalactic/anyvals/NonZeroFiniteDouble$.MODULE$:Lorg/scalactic/anyvals/NonZeroFiniteDouble$;
         3: aload_0
         4: invokevirtual #311                // Method value:()D
         7: iload_1
         8: invokevirtual #67                 // Method org/scalactic/anyvals/NonZeroFiniteDouble$.$percent$extension:(DI)D
        11: dreturn
      LineNumberTable:
        line 323: 0
      LocalVariableTable:
        Start  Length  Slot  Name   Signature
            0      12     0  this   Lorg/scalactic/anyvals/NonZeroFiniteDouble;
            0      12     1     x   I
    MethodParameters:
      Name                           Flags
      x                              final

  public double $percent(long);
    descriptor: (J)D
    flags: (0x0001) ACC_PUBLIC
    Code:
      stack=5, locals=3, args_size=2
         0: getstatic     #20                 // Field org/scalactic/anyvals/NonZeroFiniteDouble$.MODULE$:Lorg/scalactic/anyvals/NonZeroFiniteDouble$;
         3: aload_0
         4: invokevirtual #311                // Method value:()D
         7: lload_1
         8: invokevirtual #63                 // Method org/scalactic/anyvals/NonZeroFiniteDouble$.$percent$extension:(DJ)D
        11: dreturn
      LineNumberTable:
        line 325: 0
      LocalVariableTable:
        Start  Length  Slot  Name   Signature
            0      12     0  this   Lorg/scalactic/anyvals/NonZeroFiniteDouble;
            0      12     1     x   J
    MethodParameters:
      Name                           Flags
      x                              final

  public double $percent(float);
    descriptor: (F)D
    flags: (0x0001) ACC_PUBLIC
    Code:
      stack=4, locals=2, args_size=2
         0: getstatic     #20                 // Field org/scalactic/anyvals/NonZeroFiniteDouble$.MODULE$:Lorg/scalactic/anyvals/NonZeroFiniteDouble$;
         3: aload_0
         4: invokevirtual #311                // Method value:()D
         7: fload_1
         8: invokevirtual #59                 // Method org/scalactic/anyvals/NonZeroFiniteDouble$.$percent$extension:(DF)D
        11: dreturn
      LineNumberTable:
        line 327: 0
      LocalVariableTable:
        Start  Length  Slot  Name   Signature
            0      12     0  this   Lorg/scalactic/anyvals/NonZeroFiniteDouble;
            0      12     1     x   F
    MethodParameters:
      Name                           Flags
      x                              final

  public double $percent(double);
    descriptor: (D)D
    flags: (0x0001) ACC_PUBLIC
    Code:
      stack=5, locals=3, args_size=2
         0: getstatic     #20                 // Field org/scalactic/anyvals/NonZeroFiniteDouble$.MODULE$:Lorg/scalactic/anyvals/NonZeroFiniteDouble$;
         3: aload_0
         4: invokevirtual #311                // Method value:()D
         7: dload_1
         8: invokevirtual #56                 // Method org/scalactic/anyvals/NonZeroFiniteDouble$.$percent$extension:(DD)D
        11: dreturn
      LineNumberTable:
        line 329: 0
      LocalVariableTable:
        Start  Length  Slot  Name   Signature
            0      12     0  this   Lorg/scalactic/anyvals/NonZeroFiniteDouble;
            0      12     1     x   D
    MethodParameters:
      Name                           Flags
      x                              final

  public double max(double);
    descriptor: (D)D
    flags: (0x0001) ACC_PUBLIC
    Code:
      stack=5, locals=3, args_size=2
         0: getstatic     #20                 // Field org/scalactic/anyvals/NonZeroFiniteDouble$.MODULE$:Lorg/scalactic/anyvals/NonZeroFiniteDouble$;
         3: aload_0
         4: invokevirtual #311                // Method value:()D
         7: dload_1
         8: invokevirtual #52                 // Method org/scalactic/anyvals/NonZeroFiniteDouble$.max$extension:(DD)D
        11: dreturn
      LineNumberTable:
        line 337: 0
      LocalVariableTable:
        Start  Length  Slot  Name   Signature
            0      12     0  this   Lorg/scalactic/anyvals/NonZeroFiniteDouble;
            0      12     1  that   D
    MethodParameters:
      Name                           Flags
      that                           final

  public double min(double);
    descriptor: (D)D
    flags: (0x0001) ACC_PUBLIC
    Code:
      stack=5, locals=3, args_size=2
         0: getstatic     #20                 // Field org/scalactic/anyvals/NonZeroFiniteDouble$.MODULE$:Lorg/scalactic/anyvals/NonZeroFiniteDouble$;
         3: aload_0
         4: invokevirtual #311                // Method value:()D
         7: dload_1
         8: invokevirtual #49                 // Method org/scalactic/anyvals/NonZeroFiniteDouble$.min$extension:(DD)D
        11: dreturn
      LineNumberTable:
        line 342: 0
      LocalVariableTable:
        Start  Length  Slot  Name   Signature
            0      12     0  this   Lorg/scalactic/anyvals/NonZeroFiniteDouble;
            0      12     1  that   D
    MethodParameters:
      Name                           Flags
      that                           final

  public boolean isWhole();
    descriptor: ()Z
    flags: (0x0001) ACC_PUBLIC
    Code:
      stack=3, locals=1, args_size=1
         0: getstatic     #20                 // Field org/scalactic/anyvals/NonZeroFiniteDouble$.MODULE$:Lorg/scalactic/anyvals/NonZeroFiniteDouble$;
         3: aload_0
         4: invokevirtual #311                // Method value:()D
         7: invokevirtual #44                 // Method org/scalactic/anyvals/NonZeroFiniteDouble$.isWhole$extension:(D)Z
        10: ireturn
      LineNumberTable:
        line 347: 0
      LocalVariableTable:
        Start  Length  Slot  Name   Signature
            0      11     0  this   Lorg/scalactic/anyvals/NonZeroFiniteDouble;

  public double toRadians();
    descriptor: ()D
    flags: (0x0001) ACC_PUBLIC
    Code:
      stack=3, locals=1, args_size=1
         0: getstatic     #20                 // Field org/scalactic/anyvals/NonZeroFiniteDouble$.MODULE$:Lorg/scalactic/anyvals/NonZeroFiniteDouble$;
         3: aload_0
         4: invokevirtual #311                // Method value:()D
         7: invokevirtual #40                 // Method org/scalactic/anyvals/NonZeroFiniteDouble$.toRadians$extension:(D)D
        10: dreturn
      LineNumberTable:
        line 357: 0
      LocalVariableTable:
        Start  Length  Slot  Name   Signature
            0      11     0  this   Lorg/scalactic/anyvals/NonZeroFiniteDouble;

  public double toDegrees();
    descriptor: ()D
    flags: (0x0001) ACC_PUBLIC
    Code:
      stack=3, locals=1, args_size=1
         0: getstatic     #20                 // Field org/scalactic/anyvals/NonZeroFiniteDouble$.MODULE$:Lorg/scalactic/anyvals/NonZeroFiniteDouble$;
         3: aload_0
         4: invokevirtual #311                // Method value:()D
         7: invokevirtual #37                 // Method org/scalactic/anyvals/NonZeroFiniteDouble$.toDegrees$extension:(D)D
        10: dreturn
      LineNumberTable:
        line 363: 0
      LocalVariableTable:
        Start  Length  Slot  Name   Signature
            0      11     0  this   Lorg/scalactic/anyvals/NonZeroFiniteDouble;

  public double ensuringValid(scala.Function1<java.lang.Object, java.lang.Object>);
    descriptor: (Lscala/Function1;)D
    flags: (0x0001) ACC_PUBLIC
    Code:
      stack=4, locals=2, args_size=2
         0: getstatic     #20                 // Field org/scalactic/anyvals/NonZeroFiniteDouble$.MODULE$:Lorg/scalactic/anyvals/NonZeroFiniteDouble$;
         3: aload_0
         4: invokevirtual #311                // Method value:()D
         7: aload_1
         8: invokevirtual #32                 // Method org/scalactic/anyvals/NonZeroFiniteDouble$.ensuringValid$extension:(DLscala/Function1;)D
        11: dreturn
      LineNumberTable:
        line 395: 0
      LocalVariableTable:
        Start  Length  Slot  Name   Signature
            0      12     0  this   Lorg/scalactic/anyvals/NonZeroFiniteDouble;
            0      12     1     f   Lscala/Function1;
    Signature: #357                         // (Lscala/Function1<Ljava/lang/Object;Ljava/lang/Object;>;)D
    MethodParameters:
      Name                           Flags
      f                              final

  public int hashCode();
    descriptor: ()I
    flags: (0x0001) ACC_PUBLIC
    Code:
      stack=3, locals=1, args_size=1
         0: getstatic     #20                 // Field org/scalactic/anyvals/NonZeroFiniteDouble$.MODULE$:Lorg/scalactic/anyvals/NonZeroFiniteDouble$;
         3: aload_0
         4: invokevirtual #311                // Method value:()D
         7: invokevirtual #27                 // Method org/scalactic/anyvals/NonZeroFiniteDouble$.hashCode$extension:(D)I
        10: ireturn
      LineNumberTable:
        line 144: 0
      LocalVariableTable:
        Start  Length  Slot  Name   Signature
            0      11     0  this   Lorg/scalactic/anyvals/NonZeroFiniteDouble;

  public boolean equals(java.lang.Object);
    descriptor: (Ljava/lang/Object;)Z
    flags: (0x0001) ACC_PUBLIC
    Code:
      stack=4, locals=2, args_size=2
         0: getstatic     #20                 // Field org/scalactic/anyvals/NonZeroFiniteDouble$.MODULE$:Lorg/scalactic/anyvals/NonZeroFiniteDouble$;
         3: aload_0
         4: invokevirtual #311                // Method value:()D
         7: aload_1
         8: invokevirtual #22                 // Method org/scalactic/anyvals/NonZeroFiniteDouble$.equals$extension:(DLjava/lang/Object;)Z
        11: ireturn
      LineNumberTable:
        line 144: 0
      LocalVariableTable:
        Start  Length  Slot  Name   Signature
            0      12     0  this   Lorg/scalactic/anyvals/NonZeroFiniteDouble;
            0      12     1   x$1   Ljava/lang/Object;
    MethodParameters:
      Name                           Flags
      x$1                            final

  public org.scalactic.anyvals.NonZeroFiniteDouble(double);
    descriptor: (D)V
    flags: (0x0001) ACC_PUBLIC
    Code:
      stack=3, locals=3, args_size=2
         0: aload_0
         1: dload_1
         2: putfield      #305                // Field value:D
         5: aload_0
         6: invokespecial #365                // Method java/lang/Object."<init>":()V
         9: return
      LineNumberTable:
        line 144: 0
      LocalVariableTable:
        Start  Length  Slot  Name   Signature
            0      10     0  this   Lorg/scalactic/anyvals/NonZeroFiniteDouble;
            0      10     1 value   D
    MethodParameters:
      Name                           Flags
      value                          final
}
SourceFile: "NonZeroFiniteDouble.scala"
RuntimeVisibleAnnotations:
  0: #6(#7=s#8)
    scala.reflect.ScalaSignature(
      bytes="\u0006\u0005\u001d%daBA?\u0003\u007f\u0012\u0011Q\u0012\u0005\u000b\u00037\u0003!Q1A\u0005\u0002\u0005u\u0005BCAS\u0001\t\u0005\t\u0015!\u0003\u0002 \"q\u0011q\u0015\u0001\u0005\u0002\u0003\u0005\t\u0011!A\u0005\n\u0005%\u0006bBAY\u0001\u0011\u0005\u00131\u0017\u0005\b\u0003\u0017\u0004A\u0011AAg\u0011\u001d\t)\u000e\u0001C\u0001\u0003/Dq!a8\u0001\t\u0003\t\t\u000fC\u0004\u0002j\u0002!\t!a;\t\u000f\u0005M\b\u0001\"\u0001\u0002v\"9\u0011Q \u0001\u0005\u0002\u0005}\bb\u0002B\u0004\u0001\u0011\u0005\u0011Q\u0014\u0005\b\u0005\u0013\u0001A\u0011\u0001B\u0006\u0011\u001d\u0011i\u0001\u0001C\u0001\u0005\u0017AqAa\u0004\u0001\t\u0003\u0011\t\u0002C\u0004\u0003\u0018\u0001!\tA!\u0007\t\u000f\t]\u0001\u0001\"\u0001\u0003$!9!q\u0003\u0001\u0005\u0002\t\u001d\u0002b\u0002B\f\u0001\u0011\u0005!1\u0006\u0005\b\u0005/\u0001A\u0011\u0001B\u0018\u0011\u001d\u00119\u0002\u0001C\u0001\u0005gAqAa\u0006\u0001\t\u0003\u00119\u0004C\u0004\u0003<\u0001!\tA!\u0010\t\u000f\tm\u0002\u0001\"\u0001\u0003B!9!1\b\u0001\u0005\u0002\t\u0015\u0003b\u0002B\u001e\u0001\u0011\u0005!\u0011\n\u0005\b\u0005w\u0001A\u0011\u0001B\'\u0011\u001d\u0011Y\u0004\u0001C\u0001\u0005#BqAa\u000f\u0001\t\u0003\u0011)\u0006C\u0004\u0003Z\u0001!\tAa\u0017\t\u000f\te\u0003\u0001\"\u0001\u0003`!9!\u0011\f\u0001\u0005\u0002\t\r\u0004b\u0002B-\u0001\u0011\u0005!q\r\u0005\b\u00053\u0002A\u0011\u0001B6\u0011\u001d\u0011I\u0006\u0001C\u0001\u0005_BqA!\u0017\u0001\t\u0003\u0011\u0019\bC\u0004\u0003x\u0001!\tA!\u001f\t\u000f\t]\u0004\u0001\"\u0001\u0003~!9!q\u000f\u0001\u0005\u0002\t\u0005\u0005b\u0002B<\u0001\u0011\u0005!Q\u0011\u0005\b\u0005o\u0002A\u0011\u0001BE\u0011\u001d\u00119\b\u0001C\u0001\u0005\u001bCqAa\u001e\u0001\t\u0003\u0011\t\nC\u0004\u0003\u0010\u0001!\tA!&\t\u000f\t=\u0001\u0001\"\u0001\u0003\u001a\"9!q\u0002\u0001\u0005\u0002\tu\u0005b\u0002B\b\u0001\u0011\u0005!\u0011\u0015\u0005\b\u0005\u001f\u0001A\u0011\u0001BS\u0011\u001d\u0011y\u0001\u0001C\u0001\u0005SCqAa\u0004\u0001\t\u0003\u0011i\u000bC\u0004\u00032\u0002!\tAa-\t\u000f\tE\u0006\u0001\"\u0001\u00038\"9!\u0011\u0017\u0001\u0005\u0002\tm\u0006b\u0002BY\u0001\u0011\u0005!q\u0018\u0005\b\u0005c\u0003A\u0011\u0001Bb\u0011\u001d\u0011\t\f\u0001C\u0001\u0005\u000fDqA!-\u0001\t\u0003\u0011Y\rC\u0004\u0003P\u0002!\tA!5\t\u000f\t=\u0007\u0001\"\u0001\u0003V\"9!q\u001a\u0001\u0005\u0002\te\u0007b\u0002Bh\u0001\u0011\u0005!Q\u001c\u0005\b\u0005\u001f\u0004A\u0011\u0001Bq\u0011\u001d\u0011y\r\u0001C\u0001\u0005KDqAa4\u0001\t\u0003\u0011I\u000fC\u0004\u0003n\u0002!\tAa<\t\u000f\t5\b\u0001\"\u0001\u0003t\"9!Q\u001e\u0001\u0005\u0002\t]\bb\u0002Bw\u0001\u0011\u0005!1 \u0005\b\u0005[\u0004A\u0011\u0001B\u0000\u0011\u001d\u0011i\u000f\u0001C\u0001\u0007\u0007AqA!<\u0001\t\u0003\u00199\u0001C\u0004\u0004\f\u0001!\ta!\u0004\t\u000f\r-\u0001\u0001\"\u0001\u0004\u0012!911\u0002\u0001\u0005\u0002\rU\u0001bBB\u0006\u0001\u0011\u00051\u0011\u0004\u0005\b\u0007\u0017\u0001A\u0011AB\u000f\u0011\u001d\u0019Y\u0001\u0001C\u0001\u0007CAqaa\u0003\u0001\t\u0003\u0019)\u0003C\u0004\u0004*\u0001!\taa\u000b\t\u000f\rE\u0002\u0001\"\u0001\u00044!91q\u0007\u0001\u0005\u0002\re\u0002bBB\u001e\u0001\u0011\u0005\u0011Q\u0014\u0005\b\u0007{\u0001A\u0011AAO\u0011\u001d\u0019y\u0004\u0001C\u0001\u0007\u0003B\u0011b!\u0014\u0001\u0003\u0003%\tea\u0014\t\u0013\rE\u0003!!A\u0005B\rMs\u0001CB0\u0003\u007fB\ta!\u0019\u0007\u0011\u0005u\u0014q\u0010E\u0001\u0007GBq!a*X\t\u0003\u0019Y\u0007C\u0005\u0004n]\u0013\r\u0011\"\u0002\u0003\f!A1qN,!\u0002\u001b\tY\u000bC\u0005\u0004r]\u0013\r\u0011\"\u0002\u0003\f!A11O,!\u0002\u001b\tY\u000bC\u0004\u0004v]#\taa\u001e\t\u000f\r}r\u000b\"\u0001\u0004\u0002\"91QQ,\u0005\u0002\r\u001d\u0005bBBL/\u0012\u00051\u0011\u0014\u0005\b\u0007{;F\u0011AB`\u0011\u001d\u00199n\u0016C\u0001\u00073Dqa!@X\t\u0003\u0019y\u0010C\u0004\u0005\u0004]#\t\u0001\"\u0002\t\u0011\u0011MqK!C\u0002\t+Aq\u0001\".X\t\u0007!9\fC\u0004\u0005>^#\u0019\u0001b0\t\u0013\u0011%wK1A\u0005\u0004\u0011-\u0007\u0002\u0003Cj/\u0002\u0006I\u0001\"4\t\u0013\u0011UwK1A\u0005\u0006\t-\u0001\u0002\u0003Cl/\u0002\u0006i!a+\t\u000f\u0011ew\u000b\"\u0002\u0005\\\"9A\u0011],\u0005\u0006\u0011\r\bb\u0002Ct/\u0012\u0015A\u0011\u001e\u0005\b\t[<FQ\u0001Cx\u0011\u001d!\u0019p\u0016C\u0003\tkDq\u0001\"?X\t\u000b!Y\u0010C\u0004\u0005\u0000^#)!\"\u0001\t\u000f\u0015\u0015q\u000b\"\u0002\u0006\b!9Q1B,\u0005\u0006\u00155\u0001bBC\t/\u0012\u0015Q1\u0003\u0005\b\u000b/9FQAC\r\u0011\u001d)\tc\u0016C\u0003\u000bGAq!\"\tX\t\u000b)Y\u0003C\u0004\u0006\"]#)!b\r\t\u000f\u0015\u0005r\u000b\"\u0002\u0006<!9Q\u0011E,\u0005\u0006\u0015\r\u0003bBC\u0011/\u0012\u0015Q1\n\u0005\b\u000bC9FQAC*\u0011\u001d)Yf\u0016C\u0003\u000b;Bq!b\u0017X\t\u000b))\u0007C\u0004\u0006\\]#)!\"\u001c\t\u000f\u0015ms\u000b\"\u0002\u0006v!9Q1L,\u0005\u0006\u0015u\u0004bBC./\u0012\u0015QQ\u0011\u0005\b\u000b7:FQACG\u0011\u001d))j\u0016C\u0003\u000b/Cq!\"&X\t\u000b)y\nC\u0004\u0006\u0016^#)!b*\t\u000f\u0015Uu\u000b\"\u0002\u00060\"9QQS,\u0005\u0006\u0015]\u0006bBCK/\u0012\u0015Qq\u0018\u0005\b\u000b+;FQACd\u0011\u001d)ym\u0016C\u0003\u000b#Dq!b4X\t\u000b)I\u000eC\u0004\u0006P^#)!\"9\t\u000f\u0015=w\u000b\"\u0002\u0006j\"9QqZ,\u0005\u0006\u0015E\bbBCh/\u0012\u0015Q\u0011 \u0005\b\u000b\u001f<FQ\u0001D\u0001\u0011\u001d)9b\u0016C\u0003\r\u0013Aq!b\u0006X\t\u000b1\t\u0002C\u0004\u0006\u0018]#)A\"\u0007\t\u000f\u0015]q\u000b\"\u0002\u0007\"!9QqC,\u0005\u0006\u0019%\u0002bBC\f/\u0012\u0015a\u0011\u0007\u0005\b\u000b/9FQ\u0001D\u001d\u0011\u001d1\te\u0016C\u0003\r\u0007BqA\"\u0011X\t\u000b1Y\u0005C\u0004\u0007B]#)Ab\u0015\t\u000f\u0019\u0005s\u000b\"\u0002\u0007\\!9a\u0011I,\u0005\u0006\u0019\r\u0004b\u0002D!/\u0012\u0015a1\u000e\u0005\b\r\u0003:FQ\u0001D:\u0011\u001d1Yh\u0016C\u0003\r{BqAb\u001fX\t\u000b1)\tC\u0004\u0007|]#)A\"$\t\u000f\u0019mt\u000b\"\u0002\u0007\u0016\"9a1P,\u0005\u0006\u0019u\u0005b\u0002D>/\u0012\u0015aQ\u0015\u0005\b\rw:FQ\u0001DW\u0011\u001d1)l\u0016C\u0003\roCqA\".X\t\u000b1y\fC\u0004\u00076^#)Ab2\t\u000f\u0019Uv\u000b\"\u0002\u0007P\"9aQW,\u0005\u0006\u0019]\u0007b\u0002D[/\u0012\u0015aq\u001c\u0005\b\rk;FQ\u0001Dt\u0011\u001d1yo\u0016C\u0003\rcDqAb<X\t\u000b1I\u0010C\u0004\u0007p^#)a\"\u0001\t\u000f\u0019=x\u000b\"\u0002\b\n!9aq^,\u0005\u0006\u001dE\u0001b\u0002Dx/\u0012\u0015q\u0011\u0004\u0005\b\r_<FQAD\u0011\u0011\u001d9Ic\u0016C\u0003\u000fWAqab\rX\t\u000b9)\u0004C\u0004\b>]#)ab\u0010\t\u000f\u001d\rs\u000b\"\u0002\bF!9q\u0011J,\u0005\u0006\u001d-\u0003bBD(/\u0012\u0015q\u0011\u000b\u0005\n\u000f3:\u0016\u0011!C\u0003\u000f7B\u0011bb\u0018X\u0003\u0003%)a\"\u0019\u0003\'9{gNW3s_\u001aKg.\u001b;f\t>,(\r\\3\u000b\t\u0005\u0005\u00151Q\u0001\bC:Lh/\u00197t\u0015\u0011\t))a\"\u0002\u0013M\u001c\u0017\r\\1di&\u001c\'BAAE\u0003\ry\'oZ\u0002\u0001\'\r\u0001\u0011q\u0012\t\u0005\u0003#\u000b9*\u0004\u0002\u0002\u0014*\u0011\u0011QS\u0001\u0006g\u000e\fG.Y\u0005\u0005\u00033\u000b\u0019J\u0001\u0004B]f4\u0016\r\\\u0001\u0006m\u0006dW/Z\u000b\u0003\u0003?\u0003B!!%\u0002\"&!\u00111UAJ\u0005\u0019!u.\u001e2mK\u00061a/\u00197vK\u0002\na\u0001P5oSRtD\u0003BAV\u0003_\u00032!!,\u0001\u001b\t\ty\bC\u0004\u0002\u001c\u000e\u0001\r!a(\u0002\u0011Q|7\u000b\u001e:j]\u001e$\"!!.\u0011\t\u0005]\u0016Q\u0019\b\u0005\u0003s\u000b\t\r\u0005\u0003\u0002<\u0006MUBAA_\u0015\u0011\ty,a#\u0002\rq\u0012xn\u001c;?\u0013\u0011\t\u0019-a%\u0002\rA\u0013X\rZ3g\u0013\u0011\t9-!3\u0003\rM#(/\u001b8h\u0015\u0011\t\u0019-a%\u0002\rQ|\')\u001f;f+\t\ty\r\u0005\u0003\u0002\u0012\u0006E\u0017\u0002BAj\u0003\'\u0013AAQ=uK\u00069Ao\\*i_J$XCAAm!\u0011\t\t*a7\n\t\u0005u\u00171\u0013\u0002\u0006\'\"|\'\u000f^\u0001\u0007i>\u001c\u0005.\u0019:\u0016\u0005\u0005\r\b\u0003BAI\u0003KLA!a:\u0002\u0014\n!1\t[1s\u0003\u0015!x.\u00138u+\t\ti\u000f\u0005\u0003\u0002\u0012\u0006=\u0018\u0002BAy\u0003\'\u00131!\u00138u\u0003\u0019!x\u000eT8oOV\u0011\u0011q\u001f\t\u0005\u0003#\u000bI0\u0003\u0003\u0002|\u0006M%\u0001\u0002\'p]\u001e\fq\u0001^8GY>\fG/\u0006\u0002\u0003\u0002A!\u0011\u0011\u0013B\u0002\u0013\u0011\u0011)!a%\u0003\u000b\u0019cw.\u0019;\u0002\u0011Q|Gi\\;cY\u0016\f1\"\u001e8bef|F\u0005\u001d7vgV\u0011\u00111V\u0001\rk:\f\'/_0%[&tWo]\u0001\u0006IAdWo\u001d\u000b\u0005\u0003k\u0013\u0019\u0002C\u0004\u0003\u00169\u0001\r!!.\u0002\u0003a\fQ\u0001\n7fgN$BAa\u0007\u0003\"A!\u0011\u0011\u0013B\u000f\u0013\u0011\u0011y\"a%\u0003\u000f\t{w\u000e\\3b]\"9!QC\bA\u0002\u0005=G\u0003\u0002B\u000e\u0005KAqA!\u0006\u0011\u0001\u0004\tI\u000e\u0006\u0003\u0003\u001c\t%\u0002b\u0002B\u000b#\u0001\u0007\u00111\u001d\u000b\u0005\u00057\u0011i\u0003C\u0004\u0003\u0016I\u0001\r!!<\u0015\t\tm!\u0011\u0007\u0005\b\u0005+\u0019\u0002\u0019AA|)\u0011\u0011YB!\u000e\t\u000f\tUA\u00031\u0001\u0003\u0002Q!!1\u0004B\u001d\u0011\u001d\u0011)\"\u0006a\u0001\u0003?\u000b\u0001\u0002\n7fgN$S-\u001d\u000b\u0005\u00057\u0011y\u0004C\u0004\u0003\u0016Y\u0001\r!a4\u0015\t\tm!1\t\u0005\b\u0005+9\u0002\u0019AAm)\u0011\u0011YBa\u0012\t\u000f\tU\u0001\u00041\u0001\u0002dR!!1\u0004B&\u0011\u001d\u0011)\"\u0007a\u0001\u0003[$BAa\u0007\u0003P!9!Q\u0003\u000eA\u0002\u0005]H\u0003\u0002B\u000e\u0005\'BqA!\u0006\u001c\u0001\u0004\u0011\t\u0001\u0006\u0003\u0003\u001c\t]\u0003b\u0002B\u000b9\u0001\u0007\u0011qT\u0001\tI\u001d\u0014X-\u0019;feR!!1\u0004B/\u0011\u001d\u0011)\"\ba\u0001\u0003\u001f$BAa\u0007\u0003b!9!Q\u0003\u0010A\u0002\u0005eG\u0003\u0002B\u000e\u0005KBqA!\u0006 \u0001\u0004\t\u0019\u000f\u0006\u0003\u0003\u001c\t%\u0004b\u0002B\u000bA\u0001\u0007\u0011Q\u001e\u000b\u0005\u00057\u0011i\u0007C\u0004\u0003\u0016\u0005\u0002\r!a>\u0015\t\tm!\u0011\u000f\u0005\b\u0005+\u0011\u0003\u0019\u0001B\u0001)\u0011\u0011YB!\u001e\t\u000f\tU1\u00051\u0001\u0002 \u0006YAe\u001a:fCR,\'\u000fJ3r)\u0011\u0011YBa\u001f\t\u000f\tUA\u00051\u0001\u0002PR!!1\u0004B@\u0011\u001d\u0011)\"\na\u0001\u00033$BAa\u0007\u0003\u0004\"9!Q\u0003\u0014A\u0002\u0005\rH\u0003\u0002B\u000e\u0005\u000fCqA!\u0006(\u0001\u0004\ti\u000f\u0006\u0003\u0003\u001c\t-\u0005b\u0002B\u000bQ\u0001\u0007\u0011q\u001f\u000b\u0005\u00057\u0011y\tC\u0004\u0003\u0016%\u0002\rA!\u0001\u0015\t\tm!1\u0013\u0005\b\u0005+Q\u0003\u0019AAP)\u0011\tyJa&\t\u000f\tU1\u00061\u0001\u0002PR!\u0011q\u0014BN\u0011\u001d\u0011)\u0002\fa\u0001\u00033$B!a(\u0003 \"9!QC\u0017A\u0002\u0005\rH\u0003BAP\u0005GCqA!\u0006/\u0001\u0004\ti\u000f\u0006\u0003\u0002 \n\u001d\u0006b\u0002B\u000b_\u0001\u0007\u0011q\u001f\u000b\u0005\u0003?\u0013Y\u000bC\u0004\u0003\u0016A\u0002\rA!\u0001\u0015\t\u0005}%q\u0016\u0005\b\u0005+\t\u0004\u0019AAP\u0003\u0019!S.\u001b8vgR!\u0011q\u0014B[\u0011\u001d\u0011)B\ra\u0001\u0003\u001f$B!a(\u0003:\"9!QC\u001aA\u0002\u0005eG\u0003BAP\u0005{CqA!\u00065\u0001\u0004\t\u0019\u000f\u0006\u0003\u0002 \n\u0005\u0007b\u0002B\u000bk\u0001\u0007\u0011Q\u001e\u000b\u0005\u0003?\u0013)\rC\u0004\u0003\u0016Y\u0002\r!a>\u0015\t\u0005}%\u0011\u001a\u0005\b\u0005+9\u0004\u0019\u0001B\u0001)\u0011\tyJ!4\t\u000f\tU\u0001\b1\u0001\u0002 \u00061A\u0005^5nKN$B!a(\u0003T\"9!QC\u001dA\u0002\u0005=G\u0003BAP\u0005/DqA!\u0006;\u0001\u0004\tI\u000e\u0006\u0003\u0002 \nm\u0007b\u0002B\u000bw\u0001\u0007\u00111\u001d\u000b\u0005\u0003?\u0013y\u000eC\u0004\u0003\u0016q\u0002\r!!<\u0015\t\u0005}%1\u001d\u0005\b\u0005+i\u0004\u0019AA|)\u0011\tyJa:\t\u000f\tUa\b1\u0001\u0003\u0002Q!\u0011q\u0014Bv\u0011\u001d\u0011)b\u0010a\u0001\u0003?\u000bA\u0001\n3jmR!\u0011q\u0014By\u0011\u001d\u0011)\u0002\u0011a\u0001\u0003\u001f$B!a(\u0003v\"9!QC!A\u0002\u0005eG\u0003BAP\u0005sDqA!\u0006C\u0001\u0004\t\u0019\u000f\u0006\u0003\u0002 \nu\bb\u0002B\u000b\u0007\u0002\u0007\u0011Q\u001e\u000b\u0005\u0003?\u001b\t\u0001C\u0004\u0003\u0016\u0011\u0003\r!a>\u0015\t\u0005}5Q\u0001\u0005\b\u0005+)\u0005\u0019\u0001B\u0001)\u0011\tyj!\u0003\t\u000f\tUa\t1\u0001\u0002 \u0006AA\u0005]3sG\u0016tG\u000f\u0006\u0003\u0002 \u000e=\u0001b\u0002B\u000b\u000f\u0002\u0007\u0011q\u001a\u000b\u0005\u0003?\u001b\u0019\u0002C\u0004\u0003\u0016!\u0003\r!!7\u0015\t\u0005}5q\u0003\u0005\b\u0005+I\u0005\u0019AAr)\u0011\tyja\u0007\t\u000f\tU!\n1\u0001\u0002nR!\u0011qTB\u0010\u0011\u001d\u0011)b\u0013a\u0001\u0003o$B!a(\u0004$!9!Q\u0003\'A\u0002\t\u0005A\u0003BAP\u0007OAqA!\u0006N\u0001\u0004\ty*A\u0002nCb$B!a+\u0004.!91q\u0006(A\u0002\u0005-\u0016\u0001\u0002;iCR\f1!\\5o)\u0011\tYk!\u000e\t\u000f\r=r\n1\u0001\u0002,\u00069\u0011n],i_2,WC\u0001B\u000e\u0003%!xNU1eS\u0006t7/A\u0005u_\u0012+wM]3fg\u0006iQM\\:ve&twMV1mS\u0012$B!a+\u0004D!91QI*A\u0002\r\u001d\u0013!\u00014\u0011\u0011\u0005E5\u0011JAP\u0003?KAaa\u0013\u0002\u0014\nIa)\u001e8di&|g.M\u0001\tQ\u0006\u001c\bnQ8eKR\u0011\u0011Q^\u0001\u0007KF,\u0018\r\\:\u0015\t\tm1Q\u000b\u0005\n\u0007/*\u0016\u0011!a\u0001\u00073\n1\u0001\u001f\u00132!\u0011\t\tja\u0017\n\t\ru\u00131\u0013\u0002\u0004\u0003:L\u0018a\u0005(p]j+\'o\u001c$j]&$X\rR8vE2,\u0007cAAW/N\u0019qk!\u001a\u0011\t\u0005E5qM\u0005\u0005\u0007S\n\u0019J\u0001\u0004B]f\u0014VM\u001a\u000b\u0003\u0007C\n\u0001\"T1y-\u0006dW/Z\u0001\n\u001b\u0006Dh+\u00197vK\u0002\n\u0001\"T5o-\u0006dW/Z\u0001\n\u001b&tg+\u00197vK\u0002\nAA\u001a:p[R!1\u0011PB@!\u0019\t\tja\u001f\u0002,&!1QPAJ\u0005\u0019y\u0005\u000f^5p]\"9\u00111T/A\u0002\u0005}E\u0003BAV\u0007\u0007Cq!a\'_\u0001\u0004\ty*A\u0006uefLgn\u001a,bY&$G\u0003BBE\u0007+\u0003baa#\u0004\u0012\u0006-VBABG\u0015\u0011\u0019y)a%\u0002\tU$\u0018\u000e\\\u0005\u0005\u0007\'\u001biIA\u0002UefDq!a\'`\u0001\u0004\ty*\u0001\u0006qCN\u001cxJ]#mg\u0016,Baa\'\u0004,R!1QTB^)\u0011\u0019yja.\u0011\r\r\u000561UBT\u001b\t\t\u0019)\u0003\u0003\u0004&\u0006\r%A\u0003,bY&$\u0017\r^5p]B!1\u0011VBV\u0019\u0001!qa!,a\u0005\u0004\u0019yKA\u0001F#\u0011\u0019\tl!\u0017\u0011\t\u0005E51W\u0005\u0005\u0007k\u000b\u0019JA\u0004O_RD\u0017N\\4\t\u000f\r\u0015\u0003\r1\u0001\u0004:BA\u0011\u0011SB%\u0003?\u001b9\u000bC\u0004\u0002\u001c\u0002\u0004\r!a(\u0002\u0015\u001d|w\u000eZ(s\u000b2\u001cX-\u0006\u0003\u0004B\u000e5G\u0003BBb\u0007+$Ba!2\u0004RBA1\u0011UBd\u0003W\u001bY-\u0003\u0003\u0004J\u0006\r%AA(s!\u0011\u0019Ik!4\u0005\u000f\r=\u0017M1\u0001\u00040\n\t!\tC\u0004\u0004F\u0005\u0004\raa5\u0011\u0011\u0005E5\u0011JAP\u0007\u0017Dq!a\'b\u0001\u0004\ty*A\u0006sS\u001eDGo\u0014:FYN,W\u0003BBn\u0007g$Ba!8\u0004|R!1q\\B|!!\u0019\toa;\u0004r\u0006-f\u0002BBr\u0007OtA!a/\u0004f&\u0011\u0011QS\u0005\u0005\u0007S\f\u0019*A\u0004qC\u000e\\\u0017mZ3\n\t\r58q\u001e\u0002\u0007\u000b&$\b.\u001a:\u000b\t\r%\u00181\u0013\t\u0005\u0007S\u001b\u0019\u0010B\u0004\u0004v\n\u0014\raa,\u0003\u00031Cqa!\u0012c\u0001\u0004\u0019I\u0010\u0005\u0005\u0002\u0012\u000e%\u0013qTBy\u0011\u001d\tYJ\u0019a\u0001\u0003?\u000bq![:WC2LG\r\u0006\u0003\u0003\u001c\u0011\u0005\u0001bBANG\u0002\u0007\u0011qT\u0001\u000bMJ|Wn\u0014:FYN,GCBAV\t\u000f!I\u0001C\u0004\u0002\u001c\u0012\u0004\r!a(\t\u0011\u0011-A\r\"a\u0001\t\u001b\tq\u0001Z3gCVdG\u000f\u0005\u0004\u0002\u0012\u0012=\u00111V\u0005\u0005\t#\t\u0019J\u0001\u0005=Eft\u0017-\\3?\u0003\u0015\t\u0007\u000f\u001d7z)\u0011\tY\u000bb\u0006\t\u000f\u0005mU\r1\u0001\u0002 \"*Q\rb\u0007\u00050A!AQ\u0004C\u0016\u001b\t!yB\u0003\u0003\u0005\"\u0011\r\u0012\u0001C5oi\u0016\u0014h.\u00197\u000b\t\u0011\u0015BqE\u0001\u0007[\u0006\u001c\'o\\:\u000b\t\u0011%\u00121S\u0001\be\u00164G.Z2u\u0013\u0011!i\u0003b\b\u0003\u00135\f7M]8J[Bd\u0017\'E\u0010\u00052\u0011MBq\u0007C%\t3\")\u0007b\u001e\u0005\b.\u0001\u0011g\u0002\u0013\u00052\u0005-EQG\u0001\u0006[\u0006\u001c\'o\\\u0019\b-\u0011EB\u0011\bC!c\u0015)C1\bC\u001f\u001f\t!i$\t\u0002\u0005@\u0005YQ.Y2s_\u0016sw-\u001b8fc\u0015)C1\tC#\u001f\t!)%\t\u0002\u0005H\u0005)co\u000e\u00181A!JW\u000e\u001d7f[\u0016tG/\u001a3!S:\u00043kY1mC\u0002\u0012d&M\u0019/a5j\u0005(K\u0019\b-\u0011EB1\nC*c\u0015)CQ\nC(\u001f\t!y%\t\u0002\u0005R\u0005A\u0011n\u001d\"v]\u0012dW-M\u0003&\t+\"9f\u0004\u0002\u0005Xe\t\u0001!M\u0004\u0017\tc!Y\u0006b\u00192\u000b\u0015\"i\u0006b\u0018\u0010\u0005\u0011}\u0013E\u0001C1\u0003)I7O\u00117bG.\u0014w\u000e_\u0019\u0006K\u0011UCqK\u0019\b-\u0011EBq\rC8c\u0015)C\u0011\u000eC6\u001f\t!Y\'\t\u0002\u0005n\u0005I1\r\\1tg:\u000bW.Z\u0019\u0006K\u0011ED1O\b\u0003\tg\n#\u0001\"\u001e\u0002_=\u0014xML:dC2\f7\r^5d]\u0005t\u0017P^1mg:ruN\u001c.fe>4\u0015N\\5uK\u0012{WO\u00197f\u001b\u0006\u001c\'o\u001c\u00132\u000fY!\t\u0004\"\u001f\u0005\u0002F*Q\u0005b\u001f\u0005~=\u0011AQP\u0011\u0003\t\u007f\n!\"\\3uQ>$g*Y7fc\u0015)C1\u0011CC\u001f\t!))\t\u0002\u0005\u0014E:a\u0003\"\r\u0005\n\u0012E\u0015\'B\u0013\u0005\f\u00125uB\u0001CGC\t!y)A\u0005tS\u001et\u0017\r^;sKFJq\u0004\"\r\u0005\u0014\u0012\u0005F1V\u0019\bI\u0011EBQ\u0013CL\u0013\u0011!9\n\"\'\u0002\t1K7\u000f\u001e\u0006\u0005\t7#i*A\u0005j[6,H/\u00192mK*!AqTAJ\u0003)\u0019w\u000e\u001c7fGRLwN\\\u0019\b?\u0011EB1\u0015CSc\u001d!C\u0011\u0007CK\t/\u000bT!\nCT\tS{!\u0001\"+\u001e\u0003}\u0010ta\bC\u0019\t[#y+M\u0004%\tc!)\nb&2\u000b\u0015\"\t\fb-\u0010\u0005\u0011MV$\u0001\u0000\u0002\u001b]LG-\u001a8U_\u0012{WO\u00197f)\u0011\ty\n\"/\t\u000f\u0011mf\r1\u0001\u0002,\u0006\u0019\u0001o\\:\u0002)]LG-\u001a8U_:{gNW3s_\u0012{WO\u00197f)\u0011!\t\rb2\u0011\t\u00055F1Y\u0005\u0005\t\u000b\fyHA\u0007O_:TVM]8E_V\u0014G.\u001a\u0005\b\tw;\u0007\u0019AAV\u0003!y\'\u000fZ3sS:<WC\u0001Cg!\u0019\u0019\t\u000fb4\u0002,&!A\u0011[Bx\u0005!y%\u000fZ3sS:<\u0017!C8sI\u0016\u0014\u0018N\\4!\u0003Ai\u0015N\u001c)pg&$\u0018N^3WC2,X-A\tNS:\u0004vn]5uSZ,g+\u00197vK\u0002\n!\u0003^8TiJLgn\u001a\u0013fqR,gn]5p]R!\u00111\u0017Co\u0011\u001d!y\u000e\u001ca\u0001\u0003W\u000bQ\u0001\n;iSN\f\u0001\u0003^8CsR,G%\u001a=uK:\u001c\u0018n\u001c8\u0015\t\u0005=GQ\u001d\u0005\b\t?l\u0007\u0019AAV\u0003E!xn\u00155peR$S\r\u001f;f]NLwN\u001c\u000b\u0005\u00033$Y\u000fC\u0004\u0005`:\u0004\r!a+\u0002!Q|7\t[1sI\u0015DH/\u001a8tS>tG\u0003BAr\tcDq\u0001b8p\u0001\u0004\tY+A\bu_&sG\u000fJ3yi\u0016t7/[8o)\u0011\ti\u000fb>\t\u000f\u0011}\u0007\u000f1\u0001\u0002,\u0006\u0001Bo\u001c\'p]\u001e$S\r\u001f;f]NLwN\u001c\u000b\u0005\u0003o$i\u0010C\u0004\u0005`F\u0004\r!a+\u0002#Q|g\t\\8bi\u0012*\u0007\u0010^3og&|g\u000e\u0006\u0003\u0003\u0002\u0015\r\u0001b\u0002Cpe\u0002\u0007\u00111V\u0001\u0013i>$u.\u001e2mK\u0012*\u0007\u0010^3og&|g\u000e\u0006\u0003\u0002 \u0016%\u0001b\u0002Cpg\u0002\u0007\u00111V\u0001\u0016k:\f\'/_0%a2,8\u000fJ3yi\u0016t7/[8o)\u0011\tY+b\u0004\t\u000f\u0011}G\u000f1\u0001\u0002,\u00061RO\\1ss~#S.\u001b8vg\u0012*\u0007\u0010^3og&|g\u000e\u0006\u0003\u0002,\u0016U\u0001b\u0002Cpk\u0002\u0007\u00111V\u0001\u0010IAdWo\u001d\u0013fqR,gn]5p]R!Q1DC\u0010)\u0011\t),\"\b\t\u000f\tUa\u000f1\u0001\u00026\"9Aq\u001c<A\u0002\u0005-\u0016a\u0004\u0013mKN\u001cH%\u001a=uK:\u001c\u0018n\u001c8\u0015\t\u0015\u0015R\u0011\u0006\u000b\u0005\u00057)9\u0003C\u0004\u0003\u0016]\u0004\r!a4\t\u000f\u0011}w\u000f1\u0001\u0002,R!QQFC\u0019)\u0011\u0011Y\"b\f\t\u000f\tU\u0001\u00101\u0001\u0002Z\"9Aq\u001c=A\u0002\u0005-F\u0003BC\u001b\u000bs!BAa\u0007\u00068!9!QC=A\u0002\u0005\r\bb\u0002Cps\u0002\u0007\u00111\u0016\u000b\u0005\u000b{)\t\u0005\u0006\u0003\u0003\u001c\u0015}\u0002b\u0002B\u000bu\u0002\u0007\u0011Q\u001e\u0005\b\t?T\b\u0019AAV)\u0011))%\"\u0013\u0015\t\tmQq\t\u0005\b\u0005+Y\b\u0019AA|\u0011\u001d!yn\u001fa\u0001\u0003W#B!\"\u0014\u0006RQ!!1DC(\u0011\u001d\u0011)\u0002 a\u0001\u0005\u0003Aq\u0001b8}\u0001\u0004\tY\u000b\u0006\u0003\u0006V\u0015eC\u0003\u0002B\u000e\u000b/BqA!\u0006~\u0001\u0004\ty\nC\u0004\u0005`v\u0004\r!a+\u0002%\u0011bWm]:%KF$S\r\u001f;f]NLwN\u001c\u000b\u0005\u000b?*\u0019\u0007\u0006\u0003\u0003\u001c\u0015\u0005\u0004b\u0002B\u000b}\u0002\u0007\u0011q\u001a\u0005\b\t?t\b\u0019AAV)\u0011)9\'b\u001b\u0015\t\tmQ\u0011\u000e\u0005\b\u0005+y\b\u0019AAm\u0011\u001d!yn a\u0001\u0003W#B!b\u001c\u0006tQ!!1DC9\u0011!\u0011)\"!\u0001A\u0002\u0005\r\b\u0002\u0003Cp\u0003\u0003\u0001\r!a+\u0015\t\u0015]T1\u0010\u000b\u0005\u00057)I\b\u0003\u0005\u0003\u0016\u0005\r\u0001\u0019AAw\u0011!!y.a\u0001A\u0002\u0005-F\u0003BC@\u000b\u0007#BAa\u0007\u0006\u0002\"A!QCA\u0003\u0001\u0004\t9\u0010\u0003\u0005\u0005`\u0006\u0015\u0001\u0019AAV)\u0011)9)b#\u0015\t\tmQ\u0011\u0012\u0005\t\u0005+\t9\u00011\u0001\u0003\u0002!AAq\\A\u0004\u0001\u0004\tY\u000b\u0006\u0003\u0006\u0010\u0016ME\u0003\u0002B\u000e\u000b#C\u0001B!\u0006\u0002\n\u0001\u0007\u0011q\u0014\u0005\t\t?\fI\u00011\u0001\u0002,\u0006\u0011Be\u001a:fCR,\'\u000fJ3yi\u0016t7/[8o)\u0011)I*\"(\u0015\t\tmQ1\u0014\u0005\t\u0005+\tY\u00011\u0001\u0002P\"AAq\\A\u0006\u0001\u0004\tY\u000b\u0006\u0003\u0006\"\u0016\u0015F\u0003\u0002B\u000e\u000bGC\u0001B!\u0006\u0002\u000e\u0001\u0007\u0011\u0011\u001c\u0005\t\t?\fi\u00011\u0001\u0002,R!Q\u0011VCW)\u0011\u0011Y\"b+\t\u0011\tU\u0011q\u0002a\u0001\u0003GD\u0001\u0002b8\u0002\u0010\u0001\u0007\u00111\u0016\u000b\u0005\u000bc+)\f\u0006\u0003\u0003\u001c\u0015M\u0006\u0002\u0003B\u000b\u0003#\u0001\r!!<\t\u0011\u0011}\u0017\u0011\u0003a\u0001\u0003W#B!\"/\u0006>R!!1DC^\u0011!\u0011)\"a\u0005A\u0002\u0005]\b\u0002\u0003Cp\u0003\'\u0001\r!a+\u0015\t\u0015\u0005WQ\u0019\u000b\u0005\u00057)\u0019\r\u0003\u0005\u0003\u0016\u0005U\u0001\u0019\u0001B\u0001\u0011!!y.!\u0006A\u0002\u0005-F\u0003BCe\u000b\u001b$BAa\u0007\u0006L\"A!QCA\f\u0001\u0004\ty\n\u0003\u0005\u0005`\u0006]\u0001\u0019AAV\u0003U!sM]3bi\u0016\u0014H%Z9%Kb$XM\\:j_:$B!b5\u0006XR!!1DCk\u0011!\u0011)\"!\u0007A\u0002\u0005=\u0007\u0002\u0003Cp\u00033\u0001\r!a+\u0015\t\u0015mWq\u001c\u000b\u0005\u00057)i\u000e\u0003\u0005\u0003\u0016\u0005m\u0001\u0019AAm\u0011!!y.a\u0007A\u0002\u0005-F\u0003BCr\u000bO$BAa\u0007\u0006f\"A!QCA\u000f\u0001\u0004\t\u0019\u000f\u0003\u0005\u0005`\u0006u\u0001\u0019AAV)\u0011)Y/b<\u0015\t\tmQQ\u001e\u0005\t\u0005+\ty\u00021\u0001\u0002n\"AAq\\A\u0010\u0001\u0004\tY\u000b\u0006\u0003\u0006t\u0016]H\u0003\u0002B\u000e\u000bkD\u0001B!\u0006\u0002\"\u0001\u0007\u0011q\u001f\u0005\t\t?\f\t\u00031\u0001\u0002,R!Q1`C\u0000)\u0011\u0011Y\"\"@\t\u0011\tU\u00111\u0005a\u0001\u0005\u0003A\u0001\u0002b8\u0002$\u0001\u0007\u00111\u0016\u000b\u0005\r\u000719\u0001\u0006\u0003\u0003\u001c\u0019\u0015\u0001\u0002\u0003B\u000b\u0003K\u0001\r!a(\t\u0011\u0011}\u0017Q\u0005a\u0001\u0003W#BAb\u0003\u0007\u0010Q!\u0011q\u0014D\u0007\u0011!\u0011)\"a\nA\u0002\u0005=\u0007\u0002\u0003Cp\u0003O\u0001\r!a+\u0015\t\u0019Maq\u0003\u000b\u0005\u0003?3)\u0002\u0003\u0005\u0003\u0016\u0005%\u0002\u0019AAm\u0011!!y.!\u000bA\u0002\u0005-F\u0003\u0002D\u000e\r?!B!a(\u0007\u001e!A!QCA\u0016\u0001\u0004\t\u0019\u000f\u0003\u0005\u0005`\u0006-\u0002\u0019AAV)\u00111\u0019Cb\n\u0015\t\u0005}eQ\u0005\u0005\t\u0005+\ti\u00031\u0001\u0002n\"AAq\\A\u0017\u0001\u0004\tY\u000b\u0006\u0003\u0007,\u0019=B\u0003BAP\r[A\u0001B!\u0006\u00020\u0001\u0007\u0011q\u001f\u0005\t\t?\fy\u00031\u0001\u0002,R!a1\u0007D\u001c)\u0011\tyJ\"\u000e\t\u0011\tU\u0011\u0011\u0007a\u0001\u0005\u0003A\u0001\u0002b8\u00022\u0001\u0007\u00111\u0016\u000b\u0005\rw1y\u0004\u0006\u0003\u0002 \u001au\u0002\u0002\u0003B\u000b\u0003g\u0001\r!a(\t\u0011\u0011}\u00171\u0007a\u0001\u0003W\u000b\u0001\u0003J7j]V\u001cH%\u001a=uK:\u001c\u0018n\u001c8\u0015\t\u0019\u0015c\u0011\n\u000b\u0005\u0003?39\u0005\u0003\u0005\u0003\u0016\u0005U\u0002\u0019AAh\u0011!!y.!\u000eA\u0002\u0005-F\u0003\u0002D\'\r#\"B!a(\u0007P!A!QCA\u001c\u0001\u0004\tI\u000e\u0003\u0005\u0005`\u0006]\u0002\u0019AAV)\u00111)F\"\u0017\u0015\t\u0005}eq\u000b\u0005\t\u0005+\tI\u00041\u0001\u0002d\"AAq\\A\u001d\u0001\u0004\tY\u000b\u0006\u0003\u0007^\u0019\u0005D\u0003BAP\r?B\u0001B!\u0006\u0002<\u0001\u0007\u0011Q\u001e\u0005\t\t?\fY\u00041\u0001\u0002,R!aQ\rD5)\u0011\tyJb\u001a\t\u0011\tU\u0011Q\ba\u0001\u0003oD\u0001\u0002b8\u0002>\u0001\u0007\u00111\u0016\u000b\u0005\r[2\t\b\u0006\u0003\u0002 \u001a=\u0004\u0002\u0003B\u000b\u0003\u007f\u0001\rA!\u0001\t\u0011\u0011}\u0017q\ba\u0001\u0003W#BA\"\u001e\u0007zQ!\u0011q\u0014D<\u0011!\u0011)\"!\u0011A\u0002\u0005}\u0005\u0002\u0003Cp\u0003\u0003\u0002\r!a+\u0002!\u0011\"\u0018.\\3tI\u0015DH/\u001a8tS>tG\u0003\u0002D@\r\u0007#B!a(\u0007\u0002\"A!QCA\"\u0001\u0004\ty\r\u0003\u0005\u0005`\u0006\r\u0003\u0019AAV)\u001119Ib#\u0015\t\u0005}e\u0011\u0012\u0005\t\u0005+\t)\u00051\u0001\u0002Z\"AAq\\A#\u0001\u0004\tY\u000b\u0006\u0003\u0007\u0010\u001aME\u0003BAP\r#C\u0001B!\u0006\u0002H\u0001\u0007\u00111\u001d\u0005\t\t?\f9\u00051\u0001\u0002,R!aq\u0013DN)\u0011\tyJ\"\'\t\u0011\tU\u0011\u0011\na\u0001\u0003[D\u0001\u0002b8\u0002J\u0001\u0007\u00111\u0016\u000b\u0005\r?3\u0019\u000b\u0006\u0003\u0002 \u001a\u0005\u0006\u0002\u0003B\u000b\u0003\u0017\u0002\r!a>\t\u0011\u0011}\u00171\na\u0001\u0003W#BAb*\u0007,R!\u0011q\u0014DU\u0011!\u0011)\"!\u0014A\u0002\t\u0005\u0001\u0002\u0003Cp\u0003\u001b\u0002\r!a+\u0015\t\u0019=f1\u0017\u000b\u0005\u0003?3\t\f\u0003\u0005\u0003\u0016\u0005=\u0003\u0019AAP\u0011!!y.a\u0014A\u0002\u0005-\u0016A\u0004\u0013eSZ$S\r\u001f;f]NLwN\u001c\u000b\u0005\rs3i\f\u0006\u0003\u0002 \u001am\u0006\u0002\u0003B\u000b\u0003#\u0002\r!a4\t\u0011\u0011}\u0017\u0011\u000ba\u0001\u0003W#BA\"1\u0007FR!\u0011q\u0014Db\u0011!\u0011)\"a\u0015A\u0002\u0005e\u0007\u0002\u0003Cp\u0003\'\u0002\r!a+\u0015\t\u0019%gQ\u001a\u000b\u0005\u0003?3Y\r\u0003\u0005\u0003\u0016\u0005U\u0003\u0019AAr\u0011!!y.!\u0016A\u0002\u0005-F\u0003\u0002Di\r+$B!a(\u0007T\"A!QCA,\u0001\u0004\ti\u000f\u0003\u0005\u0005`\u0006]\u0003\u0019AAV)\u00111IN\"8\u0015\t\u0005}e1\u001c\u0005\t\u0005+\tI\u00061\u0001\u0002x\"AAq\\A-\u0001\u0004\tY\u000b\u0006\u0003\u0007b\u001a\u0015H\u0003BAP\rGD\u0001B!\u0006\u0002\\\u0001\u0007!\u0011\u0001\u0005\t\t?\fY\u00061\u0001\u0002,R!a\u0011\u001eDw)\u0011\tyJb;\t\u0011\tU\u0011Q\fa\u0001\u0003?C\u0001\u0002b8\u0002^\u0001\u0007\u00111V\u0001\u0013IA,\'oY3oi\u0012*\u0007\u0010^3og&|g\u000e\u0006\u0003\u0007t\u001a]H\u0003BAP\rkD\u0001B!\u0006\u0002`\u0001\u0007\u0011q\u001a\u0005\t\t?\fy\u00061\u0001\u0002,R!a1 D\u0000)\u0011\tyJ\"@\t\u0011\tU\u0011\u0011\ra\u0001\u00033D\u0001\u0002b8\u0002b\u0001\u0007\u00111\u0016\u000b\u0005\u000f\u000799\u0001\u0006\u0003\u0002 \u001e\u0015\u0001\u0002\u0003B\u000b\u0003G\u0002\r!a9\t\u0011\u0011}\u00171\ra\u0001\u0003W#Bab\u0003\b\u0010Q!\u0011qTD\u0007\u0011!\u0011)\"!\u001aA\u0002\u00055\b\u0002\u0003Cp\u0003K\u0002\r!a+\u0015\t\u001dMqq\u0003\u000b\u0005\u0003?;)\u0002\u0003\u0005\u0003\u0016\u0005\u001d\u0004\u0019AA|\u0011!!y.a\u001aA\u0002\u0005-F\u0003BD\u000e\u000f?!B!a(\b\u001e!A!QCA5\u0001\u0004\u0011\t\u0001\u0003\u0005\u0005`\u0006%\u0004\u0019AAV)\u00119\u0019cb\n\u0015\t\u0005}uQ\u0005\u0005\t\u0005+\tY\u00071\u0001\u0002 \"AAq\\A6\u0001\u0004\tY+A\u0007nCb$S\r\u001f;f]NLwN\u001c\u000b\u0005\u000f[9\t\u0004\u0006\u0003\u0002,\u001e=\u0002\u0002CB\u0018\u0003[\u0002\r!a+\t\u0011\u0011}\u0017Q\u000ea\u0001\u0003W\u000bQ\"\\5oI\u0015DH/\u001a8tS>tG\u0003BD\u001c\u000fw!B!a+\b:!A1qFA8\u0001\u0004\tY\u000b\u0003\u0005\u0005`\u0006=\u0004\u0019AAV\u0003EI7o\u00165pY\u0016$S\r\u001f;f]NLwN\u001c\u000b\u0005\u000579\t\u0005\u0003\u0005\u0005`\u0006E\u0004\u0019AAV\u0003M!xNU1eS\u0006t7\u000fJ3yi\u0016t7/[8o)\u0011\tyjb\u0012\t\u0011\u0011}\u00171\u000fa\u0001\u0003W\u000b1\u0003^8EK\u001e\u0014X-Z:%Kb$XM\\:j_:$B!a(\bN!AAq\\A;\u0001\u0004\tY+A\ff]N,(/\u001b8h-\u0006d\u0017\u000e\u001a\u0013fqR,gn]5p]R!q1KD,)\u0011\tYk\"\u0016\t\u0011\r\u0015\u0013q\u000fa\u0001\u0007\u000fB\u0001\u0002b8\u0002x\u0001\u0007\u00111V\u0001\u0013Q\u0006\u001c\bnQ8eK\u0012*\u0007\u0010^3og&|g\u000e\u0006\u0003\u0004P\u001du\u0003\u0002\u0003Cp\u0003s\u0002\r!a+\u0002!\u0015\fX/\u00197tI\u0015DH/\u001a8tS>tG\u0003BD2\u000fO\"BAa\u0007\bf!Q1qKA>\u0003\u0003\u0005\ra!\u0017\t\u0011\u0011}\u00171\u0010a\u0001\u0003W\u0003"
    )
  ScalaInlineInfo: length = 0x1A8 (unknown attribute)
   01 01 00 54 01 5B 01 53 01 01 5B 01 55 01 01 5B
   00 23 01 01 5B 01 58 01 01 5B 01 56 01 01 5B 01
   57 01 01 5B 01 54 01 01 51 01 4A 01 01 51 01 4C
   01 01 51 00 2A 01 01 51 01 4F 01 01 51 01 4D 01
   01 51 01 4E 01 01 51 01 4B 01 01 52 01 4A 01 01
   52 01 4C 01 01 52 00 2A 01 01 52 01 4F 01 01 52
   01 4D 01 01 52 01 4E 01 01 52 01 4B 01 01 49 01
   4A 01 01 49 01 4C 01 01 49 00 2A 01 01 49 01 4F
   01 01 49 01 4D 01 01 49 01 4E 01 01 49 01 4B 01
   01 50 01 4A 01 01 50 01 4C 01 01 50 00 2A 01 01
   50 01 4F 01 01 50 01 4D 01 01 50 01 4E 01 01 50
   01 4B 01 01 59 01 53 01 01 59 01 55 01 01 59 00
   23 01 01 59 01 58 01 01 59 01 56 01 01 59 01 57
   01 01 59 01 54 01 01 5C 01 53 01 01 5C 01 55 01
   01 5C 00 23 01 01 5C 01 58 01 01 5C 01 56 01 01
   5C 01 57 01 01 5C 01 54 01 01 47 01 53 01 01 47
   01 55 01 01 47 00 23 01 01 47 01 58 01 01 47 01
   56 01 01 47 01 57 01 01 47 01 48 01 01 47 01 54
   01 01 5A 01 53 01 01 5A 01 55 01 01 5A 00 23 01
   01 5A 01 58 01 01 5A 01 56 01 01 5A 01 57 01 01
   5A 01 54 01 01 69 01 6A 01 01 63 01 64 01 01 67
   01 68 01 01 66 01 3F 01 01 5F 01 60 01 01 5D 00
   23 01 01 5E 00 23 01 01 38 01 39 01 01 3C 01 3D
   01 01 62 00 F9 01 01 44 00 F9 01 01 42 01 43 01
   01 3E 01 3F 01 01 40 01 41 01 01 61 00 F9 01 01
   3A 01 3B 01 01 34 01 35 01 01 46 00 F9 01 01 45
   00 F9 01 00 09 00 F9 01
  ScalaSig: length = 0x3 (unknown attribute)
   05 02 00
