Classfile /Users/mw/Projects/slang-braindump/.jar/jar8/assemble/slang-braindump/assemble/content/org/scalactic/anyvals/PosFiniteDoubleMacro.class
  Last modified May 29, 2022; size 3172 bytes
  SHA-256 checksum 4b1c48c104e8d17381723a457a837d9aa1787074409ea6f88b7c48cc724ff555
  Compiled from "PosFiniteDoubleMacro.scala"
public final class org.scalactic.anyvals.PosFiniteDoubleMacro
  minor version: 0
  major version: 52
  flags: (0x0031) ACC_PUBLIC, ACC_FINAL, ACC_SUPER
  this_class: #2                          // org/scalactic/anyvals/PosFiniteDoubleMacro
  super_class: #4                         // java/lang/Object
  interfaces: 0, fields: 0, methods: 8, attributes: 4
Constant pool:
   #1 = Utf8               org/scalactic/anyvals/PosFiniteDoubleMacro
   #2 = Class              #1             // org/scalactic/anyvals/PosFiniteDoubleMacro
   #3 = Utf8               java/lang/Object
   #4 = Class              #3             // java/lang/Object
   #5 = Utf8               PosFiniteDoubleMacro.scala
   #6 = Utf8               Lscala/reflect/ScalaSignature;
   #7 = Utf8               bytes
   #8 = Utf8               \u0006\u0005\u001d;a!\u0002\u0004\t\u0002\u0019aaA\u0002\b\u0007\u0011\u00031q\u0002C\u0003\u001a\u0003\u0011\u00051\u0004C\u0003\u001d\u0003\u0011\u0005Q\u0004C\u0003\'\u0003\u0011\u0005q%\u0001\u000bQ_N4\u0015N\\5uK\u0012{WO\u00197f\u001b\u0006\u001c\'o\u001c\u0006\u0003\u000f!\tq!\u00198zm\u0006d7O\u0003\u0002\n\u0015\u0005I1oY1mC\u000e$\u0018n\u0019\u0006\u0002\u0017\u0005\u0019qN]4\u0011\u00055\tQ\"\u0001\u0004\u0003)A{7OR5oSR,Gi\\;cY\u0016l\u0015m\u0019:p\'\r\t\u0001C\u0006\t\u0003#Qi\u0011A\u0005\u0006\u0002\'\u0005)1oY1mC&\u0011QC\u0005\u0002\u0007\u0003:L(+\u001a4\u0011\u000559\u0012B\u0001\r\u0007\u0005U\u0019u.\u001c9jY\u0016$\u0016.\\3BgN,\'\u000f^5p]N\fa\u0001P5oSRt4\u0001\u0001\u000b\u0002\u0019\u00059\u0011n\u001d,bY&$GC\u0001\u0010\"!\t\tr$\u0003\u0002!%\t9!i\\8mK\u0006t\u0007\"\u0002\u0012\u0004\u0001\u0004\u0019\u0013!A5\u0011\u0005E!\u0013BA\u0013\u0013\u0005\u0019!u.\u001e2mK\u0006)\u0011\r\u001d9msR\u0011\u0001\u0006\f\u000b\u0003S\u0011\u00032AK\u001fB\u001d\tYC\u0006\u0004\u0001\t\u000b5\"\u0001\u0019\u0001\u0018\u0002\u0003\r\u0004\"a\f\u001e\u000f\u0005A:dBA\u00195\u001d\t\t\"\'\u0003\u00024%\u00059!/\u001a4mK\u000e$\u0018BA\u001b7\u0003\u0019i\u0017m\u0019:pg*\u00111GE\u0005\u0003qe\nq\u0001]1dW\u0006<WM\u0003\u00026m%\u00111\b\u0010\u0002\b\u0007>tG/\u001a=u\u0015\tA\u0014(\u0003\u0002?\u007f\t!Q\t\u001f9s\u0013\t\u0001\u0015HA\u0004BY&\f7/Z:\u0011\u00055\u0011\u0015BA\"\u0007\u0005=\u0001vn\u001d$j]&$X\rR8vE2,\u0007\"B#\u0005\u0001\u00041\u0015!\u0002<bYV,\u0007c\u0001\u0016>G\u0001
   #9 = Utf8               scala/reflect/api/Exprs$Expr
  #10 = Class              #9             // scala/reflect/api/Exprs$Expr
  #11 = Utf8               scala/reflect/api/Exprs
  #12 = Class              #11            // scala/reflect/api/Exprs
  #13 = Utf8               Expr
  #14 = Utf8               apply
  #15 = Utf8               (Lscala/reflect/macros/whitebox/Context;Lscala/reflect/api/Exprs$Expr;)Lscala/reflect/api/Exprs$Expr;
  #16 = Utf8               (Lscala/reflect/macros/whitebox/Context;Lscala/reflect/api/Exprs$Expr<Ljava/lang/Object;>;)Lscala/reflect/api/Exprs$Expr<Lorg/scalactic/anyvals/PosFiniteDouble;>;
  #17 = Utf8               c
  #18 = Utf8               value
  #19 = Utf8               org/scalactic/anyvals/PosFiniteDoubleMacro$
  #20 = Class              #19            // org/scalactic/anyvals/PosFiniteDoubleMacro$
  #21 = Utf8               MODULE$
  #22 = Utf8               Lorg/scalactic/anyvals/PosFiniteDoubleMacro$;
  #23 = NameAndType        #21:#22        // MODULE$:Lorg/scalactic/anyvals/PosFiniteDoubleMacro$;
  #24 = Fieldref           #20.#23        // org/scalactic/anyvals/PosFiniteDoubleMacro$.MODULE$:Lorg/scalactic/anyvals/PosFiniteDoubleMacro$;
  #25 = NameAndType        #14:#15        // apply:(Lscala/reflect/macros/whitebox/Context;Lscala/reflect/api/Exprs$Expr;)Lscala/reflect/api/Exprs$Expr;
  #26 = Methodref          #20.#25        // org/scalactic/anyvals/PosFiniteDoubleMacro$.apply:(Lscala/reflect/macros/whitebox/Context;Lscala/reflect/api/Exprs$Expr;)Lscala/reflect/api/Exprs$Expr;
  #27 = Utf8               Lscala/reflect/macros/whitebox/Context;
  #28 = Utf8               Lscala/reflect/api/Exprs$Expr;
  #29 = Utf8               isValid
  #30 = Utf8               (D)Z
  #31 = Utf8               i
  #32 = NameAndType        #29:#30        // isValid:(D)Z
  #33 = Methodref          #20.#32        // org/scalactic/anyvals/PosFiniteDoubleMacro$.isValid:(D)Z
  #34 = Utf8               D
  #35 = Utf8               ensureValidCharLiteral
  #36 = Utf8               (Lscala/reflect/macros/whitebox/Context;Lscala/reflect/api/Exprs$Expr;Ljava/lang/String;Ljava/lang/String;Lscala/Function1;)V
  #37 = Utf8               (Lscala/reflect/macros/whitebox/Context;Lscala/reflect/api/Exprs$Expr<Ljava/lang/Object;>;Ljava/lang/String;Ljava/lang/String;Lscala/Function1<Ljava/lang/Object;Ljava/lang/Object;>;)V
  #38 = Utf8               notValidMsg
  #39 = Utf8               notLiteralMsg
  #40 = NameAndType        #35:#36        // ensureValidCharLiteral:(Lscala/reflect/macros/whitebox/Context;Lscala/reflect/api/Exprs$Expr;Ljava/lang/String;Ljava/lang/String;Lscala/Function1;)V
  #41 = Methodref          #20.#40        // org/scalactic/anyvals/PosFiniteDoubleMacro$.ensureValidCharLiteral:(Lscala/reflect/macros/whitebox/Context;Lscala/reflect/api/Exprs$Expr;Ljava/lang/String;Ljava/lang/String;Lscala/Function1;)V
  #42 = Utf8               Ljava/lang/String;
  #43 = Utf8               Lscala/Function1;
  #44 = Utf8               ensureValidStringLiteral
  #45 = Utf8               (Lscala/reflect/macros/whitebox/Context;Lscala/reflect/api/Exprs$Expr<Ljava/lang/String;>;Ljava/lang/String;Ljava/lang/String;Lscala/Function1<Ljava/lang/String;Ljava/lang/Object;>;)V
  #46 = NameAndType        #44:#36        // ensureValidStringLiteral:(Lscala/reflect/macros/whitebox/Context;Lscala/reflect/api/Exprs$Expr;Ljava/lang/String;Ljava/lang/String;Lscala/Function1;)V
  #47 = Methodref          #20.#46        // org/scalactic/anyvals/PosFiniteDoubleMacro$.ensureValidStringLiteral:(Lscala/reflect/macros/whitebox/Context;Lscala/reflect/api/Exprs$Expr;Ljava/lang/String;Ljava/lang/String;Lscala/Function1;)V
  #48 = Utf8               ensureValidDoubleLiteral
  #49 = NameAndType        #48:#36        // ensureValidDoubleLiteral:(Lscala/reflect/macros/whitebox/Context;Lscala/reflect/api/Exprs$Expr;Ljava/lang/String;Ljava/lang/String;Lscala/Function1;)V
  #50 = Methodref          #20.#49        // org/scalactic/anyvals/PosFiniteDoubleMacro$.ensureValidDoubleLiteral:(Lscala/reflect/macros/whitebox/Context;Lscala/reflect/api/Exprs$Expr;Ljava/lang/String;Ljava/lang/String;Lscala/Function1;)V
  #51 = Utf8               ensureValidFloatLiteral
  #52 = NameAndType        #51:#36        // ensureValidFloatLiteral:(Lscala/reflect/macros/whitebox/Context;Lscala/reflect/api/Exprs$Expr;Ljava/lang/String;Ljava/lang/String;Lscala/Function1;)V
  #53 = Methodref          #20.#52        // org/scalactic/anyvals/PosFiniteDoubleMacro$.ensureValidFloatLiteral:(Lscala/reflect/macros/whitebox/Context;Lscala/reflect/api/Exprs$Expr;Ljava/lang/String;Ljava/lang/String;Lscala/Function1;)V
  #54 = Utf8               ensureValidLongLiteral
  #55 = NameAndType        #54:#36        // ensureValidLongLiteral:(Lscala/reflect/macros/whitebox/Context;Lscala/reflect/api/Exprs$Expr;Ljava/lang/String;Ljava/lang/String;Lscala/Function1;)V
  #56 = Methodref          #20.#55        // org/scalactic/anyvals/PosFiniteDoubleMacro$.ensureValidLongLiteral:(Lscala/reflect/macros/whitebox/Context;Lscala/reflect/api/Exprs$Expr;Ljava/lang/String;Ljava/lang/String;Lscala/Function1;)V
  #57 = Utf8               ensureValidIntLiteral
  #58 = NameAndType        #57:#36        // ensureValidIntLiteral:(Lscala/reflect/macros/whitebox/Context;Lscala/reflect/api/Exprs$Expr;Ljava/lang/String;Ljava/lang/String;Lscala/Function1;)V
  #59 = Methodref          #20.#58        // org/scalactic/anyvals/PosFiniteDoubleMacro$.ensureValidIntLiteral:(Lscala/reflect/macros/whitebox/Context;Lscala/reflect/api/Exprs$Expr;Ljava/lang/String;Ljava/lang/String;Lscala/Function1;)V
  #60 = Utf8               Code
  #61 = Utf8               LocalVariableTable
  #62 = Utf8               Signature
  #63 = Utf8               MethodParameters
  #64 = Utf8               InnerClasses
  #65 = Utf8               SourceFile
  #66 = Utf8               RuntimeVisibleAnnotations
  #67 = Utf8               ScalaSig
{
  public static scala.reflect.api.Exprs$Expr<org.scalactic.anyvals.PosFiniteDouble> apply(scala.reflect.macros.whitebox.Context, scala.reflect.api.Exprs$Expr<java.lang.Object>);
    descriptor: (Lscala/reflect/macros/whitebox/Context;Lscala/reflect/api/Exprs$Expr;)Lscala/reflect/api/Exprs$Expr;
    flags: (0x0009) ACC_PUBLIC, ACC_STATIC
    Code:
      stack=3, locals=2, args_size=2
         0: getstatic     #24                 // Field org/scalactic/anyvals/PosFiniteDoubleMacro$.MODULE$:Lorg/scalactic/anyvals/PosFiniteDoubleMacro$;
         3: aload_0
         4: aload_1
         5: invokevirtual #26                 // Method org/scalactic/anyvals/PosFiniteDoubleMacro$.apply:(Lscala/reflect/macros/whitebox/Context;Lscala/reflect/api/Exprs$Expr;)Lscala/reflect/api/Exprs$Expr;
         8: areturn
      LocalVariableTable:
        Start  Length  Slot  Name   Signature
            0       9     0     c   Lscala/reflect/macros/whitebox/Context;
            0       9     1 value   Lscala/reflect/api/Exprs$Expr;
    Signature: #16                          // (Lscala/reflect/macros/whitebox/Context;Lscala/reflect/api/Exprs$Expr<Ljava/lang/Object;>;)Lscala/reflect/api/Exprs$Expr<Lorg/scalactic/anyvals/PosFiniteDouble;>;
    MethodParameters:
      Name                           Flags
      c                              final
      value                          final

  public static boolean isValid(double);
    descriptor: (D)Z
    flags: (0x0009) ACC_PUBLIC, ACC_STATIC
    Code:
      stack=3, locals=2, args_size=1
         0: getstatic     #24                 // Field org/scalactic/anyvals/PosFiniteDoubleMacro$.MODULE$:Lorg/scalactic/anyvals/PosFiniteDoubleMacro$;
         3: dload_0
         4: invokevirtual #33                 // Method org/scalactic/anyvals/PosFiniteDoubleMacro$.isValid:(D)Z
         7: ireturn
      LocalVariableTable:
        Start  Length  Slot  Name   Signature
            0       8     0     i   D
    MethodParameters:
      Name                           Flags
      i                              final

  public static void ensureValidCharLiteral(scala.reflect.macros.whitebox.Context, scala.reflect.api.Exprs$Expr<java.lang.Object>, java.lang.String, java.lang.String, scala.Function1<java.lang.Object, java.lang.Object>);
    descriptor: (Lscala/reflect/macros/whitebox/Context;Lscala/reflect/api/Exprs$Expr;Ljava/lang/String;Ljava/lang/String;Lscala/Function1;)V
    flags: (0x0009) ACC_PUBLIC, ACC_STATIC
    Code:
      stack=6, locals=5, args_size=5
         0: getstatic     #24                 // Field org/scalactic/anyvals/PosFiniteDoubleMacro$.MODULE$:Lorg/scalactic/anyvals/PosFiniteDoubleMacro$;
         3: aload_0
         4: aload_1
         5: aload_2
         6: aload_3
         7: aload         4
         9: invokevirtual #41                 // Method org/scalactic/anyvals/PosFiniteDoubleMacro$.ensureValidCharLiteral:(Lscala/reflect/macros/whitebox/Context;Lscala/reflect/api/Exprs$Expr;Ljava/lang/String;Ljava/lang/String;Lscala/Function1;)V
        12: return
      LocalVariableTable:
        Start  Length  Slot  Name   Signature
            0      13     0     c   Lscala/reflect/macros/whitebox/Context;
            0      13     1 value   Lscala/reflect/api/Exprs$Expr;
            0      13     2 notValidMsg   Ljava/lang/String;
            0      13     3 notLiteralMsg   Ljava/lang/String;
            0      13     4 isValid   Lscala/Function1;
    Signature: #37                          // (Lscala/reflect/macros/whitebox/Context;Lscala/reflect/api/Exprs$Expr<Ljava/lang/Object;>;Ljava/lang/String;Ljava/lang/String;Lscala/Function1<Ljava/lang/Object;Ljava/lang/Object;>;)V
    MethodParameters:
      Name                           Flags
      c                              final
      value                          final
      notValidMsg                    final
      notLiteralMsg                  final
      isValid                        final

  public static void ensureValidStringLiteral(scala.reflect.macros.whitebox.Context, scala.reflect.api.Exprs$Expr<java.lang.String>, java.lang.String, java.lang.String, scala.Function1<java.lang.String, java.lang.Object>);
    descriptor: (Lscala/reflect/macros/whitebox/Context;Lscala/reflect/api/Exprs$Expr;Ljava/lang/String;Ljava/lang/String;Lscala/Function1;)V
    flags: (0x0009) ACC_PUBLIC, ACC_STATIC
    Code:
      stack=6, locals=5, args_size=5
         0: getstatic     #24                 // Field org/scalactic/anyvals/PosFiniteDoubleMacro$.MODULE$:Lorg/scalactic/anyvals/PosFiniteDoubleMacro$;
         3: aload_0
         4: aload_1
         5: aload_2
         6: aload_3
         7: aload         4
         9: invokevirtual #47                 // Method org/scalactic/anyvals/PosFiniteDoubleMacro$.ensureValidStringLiteral:(Lscala/reflect/macros/whitebox/Context;Lscala/reflect/api/Exprs$Expr;Ljava/lang/String;Ljava/lang/String;Lscala/Function1;)V
        12: return
      LocalVariableTable:
        Start  Length  Slot  Name   Signature
            0      13     0     c   Lscala/reflect/macros/whitebox/Context;
            0      13     1 value   Lscala/reflect/api/Exprs$Expr;
            0      13     2 notValidMsg   Ljava/lang/String;
            0      13     3 notLiteralMsg   Ljava/lang/String;
            0      13     4 isValid   Lscala/Function1;
    Signature: #45                          // (Lscala/reflect/macros/whitebox/Context;Lscala/reflect/api/Exprs$Expr<Ljava/lang/String;>;Ljava/lang/String;Ljava/lang/String;Lscala/Function1<Ljava/lang/String;Ljava/lang/Object;>;)V
    MethodParameters:
      Name                           Flags
      c                              final
      value                          final
      notValidMsg                    final
      notLiteralMsg                  final
      isValid                        final

  public static void ensureValidDoubleLiteral(scala.reflect.macros.whitebox.Context, scala.reflect.api.Exprs$Expr<java.lang.Object>, java.lang.String, java.lang.String, scala.Function1<java.lang.Object, java.lang.Object>);
    descriptor: (Lscala/reflect/macros/whitebox/Context;Lscala/reflect/api/Exprs$Expr;Ljava/lang/String;Ljava/lang/String;Lscala/Function1;)V
    flags: (0x0009) ACC_PUBLIC, ACC_STATIC
    Code:
      stack=6, locals=5, args_size=5
         0: getstatic     #24                 // Field org/scalactic/anyvals/PosFiniteDoubleMacro$.MODULE$:Lorg/scalactic/anyvals/PosFiniteDoubleMacro$;
         3: aload_0
         4: aload_1
         5: aload_2
         6: aload_3
         7: aload         4
         9: invokevirtual #50                 // Method org/scalactic/anyvals/PosFiniteDoubleMacro$.ensureValidDoubleLiteral:(Lscala/reflect/macros/whitebox/Context;Lscala/reflect/api/Exprs$Expr;Ljava/lang/String;Ljava/lang/String;Lscala/Function1;)V
        12: return
      LocalVariableTable:
        Start  Length  Slot  Name   Signature
            0      13     0     c   Lscala/reflect/macros/whitebox/Context;
            0      13     1 value   Lscala/reflect/api/Exprs$Expr;
            0      13     2 notValidMsg   Ljava/lang/String;
            0      13     3 notLiteralMsg   Ljava/lang/String;
            0      13     4 isValid   Lscala/Function1;
    Signature: #37                          // (Lscala/reflect/macros/whitebox/Context;Lscala/reflect/api/Exprs$Expr<Ljava/lang/Object;>;Ljava/lang/String;Ljava/lang/String;Lscala/Function1<Ljava/lang/Object;Ljava/lang/Object;>;)V
    MethodParameters:
      Name                           Flags
      c                              final
      value                          final
      notValidMsg                    final
      notLiteralMsg                  final
      isValid                        final

  public static void ensureValidFloatLiteral(scala.reflect.macros.whitebox.Context, scala.reflect.api.Exprs$Expr<java.lang.Object>, java.lang.String, java.lang.String, scala.Function1<java.lang.Object, java.lang.Object>);
    descriptor: (Lscala/reflect/macros/whitebox/Context;Lscala/reflect/api/Exprs$Expr;Ljava/lang/String;Ljava/lang/String;Lscala/Function1;)V
    flags: (0x0009) ACC_PUBLIC, ACC_STATIC
    Code:
      stack=6, locals=5, args_size=5
         0: getstatic     #24                 // Field org/scalactic/anyvals/PosFiniteDoubleMacro$.MODULE$:Lorg/scalactic/anyvals/PosFiniteDoubleMacro$;
         3: aload_0
         4: aload_1
         5: aload_2
         6: aload_3
         7: aload         4
         9: invokevirtual #53                 // Method org/scalactic/anyvals/PosFiniteDoubleMacro$.ensureValidFloatLiteral:(Lscala/reflect/macros/whitebox/Context;Lscala/reflect/api/Exprs$Expr;Ljava/lang/String;Ljava/lang/String;Lscala/Function1;)V
        12: return
      LocalVariableTable:
        Start  Length  Slot  Name   Signature
            0      13     0     c   Lscala/reflect/macros/whitebox/Context;
            0      13     1 value   Lscala/reflect/api/Exprs$Expr;
            0      13     2 notValidMsg   Ljava/lang/String;
            0      13     3 notLiteralMsg   Ljava/lang/String;
            0      13     4 isValid   Lscala/Function1;
    Signature: #37                          // (Lscala/reflect/macros/whitebox/Context;Lscala/reflect/api/Exprs$Expr<Ljava/lang/Object;>;Ljava/lang/String;Ljava/lang/String;Lscala/Function1<Ljava/lang/Object;Ljava/lang/Object;>;)V
    MethodParameters:
      Name                           Flags
      c                              final
      value                          final
      notValidMsg                    final
      notLiteralMsg                  final
      isValid                        final

  public static void ensureValidLongLiteral(scala.reflect.macros.whitebox.Context, scala.reflect.api.Exprs$Expr<java.lang.Object>, java.lang.String, java.lang.String, scala.Function1<java.lang.Object, java.lang.Object>);
    descriptor: (Lscala/reflect/macros/whitebox/Context;Lscala/reflect/api/Exprs$Expr;Ljava/lang/String;Ljava/lang/String;Lscala/Function1;)V
    flags: (0x0009) ACC_PUBLIC, ACC_STATIC
    Code:
      stack=6, locals=5, args_size=5
         0: getstatic     #24                 // Field org/scalactic/anyvals/PosFiniteDoubleMacro$.MODULE$:Lorg/scalactic/anyvals/PosFiniteDoubleMacro$;
         3: aload_0
         4: aload_1
         5: aload_2
         6: aload_3
         7: aload         4
         9: invokevirtual #56                 // Method org/scalactic/anyvals/PosFiniteDoubleMacro$.ensureValidLongLiteral:(Lscala/reflect/macros/whitebox/Context;Lscala/reflect/api/Exprs$Expr;Ljava/lang/String;Ljava/lang/String;Lscala/Function1;)V
        12: return
      LocalVariableTable:
        Start  Length  Slot  Name   Signature
            0      13     0     c   Lscala/reflect/macros/whitebox/Context;
            0      13     1 value   Lscala/reflect/api/Exprs$Expr;
            0      13     2 notValidMsg   Ljava/lang/String;
            0      13     3 notLiteralMsg   Ljava/lang/String;
            0      13     4 isValid   Lscala/Function1;
    Signature: #37                          // (Lscala/reflect/macros/whitebox/Context;Lscala/reflect/api/Exprs$Expr<Ljava/lang/Object;>;Ljava/lang/String;Ljava/lang/String;Lscala/Function1<Ljava/lang/Object;Ljava/lang/Object;>;)V
    MethodParameters:
      Name                           Flags
      c                              final
      value                          final
      notValidMsg                    final
      notLiteralMsg                  final
      isValid                        final

  public static void ensureValidIntLiteral(scala.reflect.macros.whitebox.Context, scala.reflect.api.Exprs$Expr<java.lang.Object>, java.lang.String, java.lang.String, scala.Function1<java.lang.Object, java.lang.Object>);
    descriptor: (Lscala/reflect/macros/whitebox/Context;Lscala/reflect/api/Exprs$Expr;Ljava/lang/String;Ljava/lang/String;Lscala/Function1;)V
    flags: (0x0009) ACC_PUBLIC, ACC_STATIC
    Code:
      stack=6, locals=5, args_size=5
         0: getstatic     #24                 // Field org/scalactic/anyvals/PosFiniteDoubleMacro$.MODULE$:Lorg/scalactic/anyvals/PosFiniteDoubleMacro$;
         3: aload_0
         4: aload_1
         5: aload_2
         6: aload_3
         7: aload         4
         9: invokevirtual #59                 // Method org/scalactic/anyvals/PosFiniteDoubleMacro$.ensureValidIntLiteral:(Lscala/reflect/macros/whitebox/Context;Lscala/reflect/api/Exprs$Expr;Ljava/lang/String;Ljava/lang/String;Lscala/Function1;)V
        12: return
      LocalVariableTable:
        Start  Length  Slot  Name   Signature
            0      13     0     c   Lscala/reflect/macros/whitebox/Context;
            0      13     1 value   Lscala/reflect/api/Exprs$Expr;
            0      13     2 notValidMsg   Ljava/lang/String;
            0      13     3 notLiteralMsg   Ljava/lang/String;
            0      13     4 isValid   Lscala/Function1;
    Signature: #37                          // (Lscala/reflect/macros/whitebox/Context;Lscala/reflect/api/Exprs$Expr<Ljava/lang/Object;>;Ljava/lang/String;Ljava/lang/String;Lscala/Function1<Ljava/lang/Object;Ljava/lang/Object;>;)V
    MethodParameters:
      Name                           Flags
      c                              final
      value                          final
      notValidMsg                    final
      notLiteralMsg                  final
      isValid                        final
}
InnerClasses:
  public #13= #10 of #12;                 // Expr=class scala/reflect/api/Exprs$Expr of class scala/reflect/api/Exprs
SourceFile: "PosFiniteDoubleMacro.scala"
RuntimeVisibleAnnotations:
  0: #6(#7=s#8)
    scala.reflect.ScalaSignature(
      bytes="\u0006\u0005\u001d;a!\u0002\u0004\t\u0002\u0019aaA\u0002\b\u0007\u0011\u00031q\u0002C\u0003\u001a\u0003\u0011\u00051\u0004C\u0003\u001d\u0003\u0011\u0005Q\u0004C\u0003\'\u0003\u0011\u0005q%\u0001\u000bQ_N4\u0015N\\5uK\u0012{WO\u00197f\u001b\u0006\u001c\'o\u001c\u0006\u0003\u000f!\tq!\u00198zm\u0006d7O\u0003\u0002\n\u0015\u0005I1oY1mC\u000e$\u0018n\u0019\u0006\u0002\u0017\u0005\u0019qN]4\u0011\u00055\tQ\"\u0001\u0004\u0003)A{7OR5oSR,Gi\\;cY\u0016l\u0015m\u0019:p\'\r\t\u0001C\u0006\t\u0003#Qi\u0011A\u0005\u0006\u0002\'\u0005)1oY1mC&\u0011QC\u0005\u0002\u0007\u0003:L(+\u001a4\u0011\u000559\u0012B\u0001\r\u0007\u0005U\u0019u.\u001c9jY\u0016$\u0016.\\3BgN,\'\u000f^5p]N\fa\u0001P5oSRt4\u0001\u0001\u000b\u0002\u0019\u00059\u0011n\u001d,bY&$GC\u0001\u0010\"!\t\tr$\u0003\u0002!%\t9!i\\8mK\u0006t\u0007\"\u0002\u0012\u0004\u0001\u0004\u0019\u0013!A5\u0011\u0005E!\u0013BA\u0013\u0013\u0005\u0019!u.\u001e2mK\u0006)\u0011\r\u001d9msR\u0011\u0001\u0006\f\u000b\u0003S\u0011\u00032AK\u001fB\u001d\tYC\u0006\u0004\u0001\t\u000b5\"\u0001\u0019\u0001\u0018\u0002\u0003\r\u0004\"a\f\u001e\u000f\u0005A:dBA\u00195\u001d\t\t\"\'\u0003\u00024%\u00059!/\u001a4mK\u000e$\u0018BA\u001b7\u0003\u0019i\u0017m\u0019:pg*\u00111GE\u0005\u0003qe\nq\u0001]1dW\u0006<WM\u0003\u00026m%\u00111\b\u0010\u0002\b\u0007>tG/\u001a=u\u0015\tA\u0014(\u0003\u0002?\u007f\t!Q\t\u001f9s\u0013\t\u0001\u0015HA\u0004BY&\f7/Z:\u0011\u00055\u0011\u0015BA\"\u0007\u0005=\u0001vn\u001d$j]&$X\rR8vE2,\u0007\"B#\u0005\u0001\u00041\u0015!\u0002<bYV,\u0007c\u0001\u0016>G\u0001"
    )
  ScalaSig: length = 0x3 (unknown attribute)
   05 02 00
