Classfile /Users/mw/Projects/slang-braindump/.jar/jar11/assemble/slang-braindump/assemble/content/org/apache/commons/lang3/ArrayUtils$1.class
  Last modified May 29, 2022; size 1001 bytes
  SHA-256 checksum e3e2c310080e58efd73d2fdcb741e547e172f8b7b2f8756d14e117427ed4e3cb
  Compiled from "ArrayUtils.java"
class org.apache.commons.lang3.ArrayUtils$1 extends java.lang.Object implements java.util.Comparator<T>
  minor version: 0
  major version: 52
  flags: (0x0020) ACC_SUPER
  this_class: #5                          // org/apache/commons/lang3/ArrayUtils$1
  super_class: #6                         // java/lang/Object
  interfaces: 1, fields: 0, methods: 3, attributes: 4
Constant pool:
   #1 = Methodref          #6.#32         // java/lang/Object."<init>":()V
   #2 = InterfaceMethodref #3.#33         // java/lang/Comparable.compareTo:(Ljava/lang/Object;)I
   #3 = Class              #34            // java/lang/Comparable
   #4 = Methodref          #5.#35         // org/apache/commons/lang3/ArrayUtils$1.compare:(Ljava/lang/Comparable;Ljava/lang/Comparable;)I
   #5 = Class              #36            // org/apache/commons/lang3/ArrayUtils$1
   #6 = Class              #37            // java/lang/Object
   #7 = Class              #38            // java/util/Comparator
   #8 = Utf8               <init>
   #9 = Utf8               ()V
  #10 = Utf8               Code
  #11 = Utf8               LineNumberTable
  #12 = Utf8               LocalVariableTable
  #13 = Utf8               this
  #14 = Utf8               InnerClasses
  #15 = Utf8               Lorg/apache/commons/lang3/ArrayUtils$1;
  #16 = Utf8               compare
  #17 = Utf8               (Ljava/lang/Comparable;Ljava/lang/Comparable;)I
  #18 = Utf8               o1
  #19 = Utf8               Ljava/lang/Comparable;
  #20 = Utf8               o2
  #21 = Utf8               LocalVariableTypeTable
  #22 = Utf8               TT;
  #23 = Utf8               Signature
  #24 = Utf8               (TT;TT;)I
  #25 = Utf8               (Ljava/lang/Object;Ljava/lang/Object;)I
  #26 = Utf8               Ljava/lang/Object;Ljava/util/Comparator<TT;>;
  #27 = Utf8               SourceFile
  #28 = Utf8               ArrayUtils.java
  #29 = Utf8               EnclosingMethod
  #30 = Class              #39            // org/apache/commons/lang3/ArrayUtils
  #31 = NameAndType        #40:#41        // isSorted:([Ljava/lang/Comparable;)Z
  #32 = NameAndType        #8:#9          // "<init>":()V
  #33 = NameAndType        #42:#43        // compareTo:(Ljava/lang/Object;)I
  #34 = Utf8               java/lang/Comparable
  #35 = NameAndType        #16:#17        // compare:(Ljava/lang/Comparable;Ljava/lang/Comparable;)I
  #36 = Utf8               org/apache/commons/lang3/ArrayUtils$1
  #37 = Utf8               java/lang/Object
  #38 = Utf8               java/util/Comparator
  #39 = Utf8               org/apache/commons/lang3/ArrayUtils
  #40 = Utf8               isSorted
  #41 = Utf8               ([Ljava/lang/Comparable;)Z
  #42 = Utf8               compareTo
  #43 = Utf8               (Ljava/lang/Object;)I
{
  org.apache.commons.lang3.ArrayUtils$1();
    descriptor: ()V
    flags: (0x0000)
    Code:
      stack=1, locals=1, args_size=1
         0: aload_0
         1: invokespecial #1                  // Method java/lang/Object."<init>":()V
         4: return
      LineNumberTable:
        line 7477: 0
      LocalVariableTable:
        Start  Length  Slot  Name   Signature
            0       5     0  this   Lorg/apache/commons/lang3/ArrayUtils$1;

  public int compare(T, T);
    descriptor: (Ljava/lang/Comparable;Ljava/lang/Comparable;)I
    flags: (0x0001) ACC_PUBLIC
    Code:
      stack=2, locals=3, args_size=3
         0: aload_1
         1: aload_2
         2: invokeinterface #2,  2            // InterfaceMethod java/lang/Comparable.compareTo:(Ljava/lang/Object;)I
         7: ireturn
      LineNumberTable:
        line 7480: 0
      LocalVariableTable:
        Start  Length  Slot  Name   Signature
            0       8     0  this   Lorg/apache/commons/lang3/ArrayUtils$1;
            0       8     1    o1   Ljava/lang/Comparable;
            0       8     2    o2   Ljava/lang/Comparable;
      LocalVariableTypeTable:
        Start  Length  Slot  Name   Signature
            0       8     1    o1   TT;
            0       8     2    o2   TT;
    Signature: #24                          // (TT;TT;)I

  public int compare(java.lang.Object, java.lang.Object);
    descriptor: (Ljava/lang/Object;Ljava/lang/Object;)I
    flags: (0x1041) ACC_PUBLIC, ACC_BRIDGE, ACC_SYNTHETIC
    Code:
      stack=3, locals=3, args_size=3
         0: aload_0
         1: aload_1
         2: checkcast     #3                  // class java/lang/Comparable
         5: aload_2
         6: checkcast     #3                  // class java/lang/Comparable
         9: invokevirtual #4                  // Method compare:(Ljava/lang/Comparable;Ljava/lang/Comparable;)I
        12: ireturn
      LineNumberTable:
        line 7477: 0
      LocalVariableTable:
        Start  Length  Slot  Name   Signature
            0      13     0  this   Lorg/apache/commons/lang3/ArrayUtils$1;
}
Signature: #26                          // Ljava/lang/Object;Ljava/util/Comparator<TT;>;
SourceFile: "ArrayUtils.java"
EnclosingMethod: #30.#31                // org.apache.commons.lang3.ArrayUtils.isSorted
InnerClasses:
  #5;                                     // class org/apache/commons/lang3/ArrayUtils$1
