Classfile /Users/mw/Projects/slang-braindump/.jar/jar11/assemble/slang-braindump/assemble/content/org/apache/commons/lang3/CharSetUtils.class
  Last modified May 29, 2022; size 3089 bytes
  SHA-256 checksum bba569ef41fcf2992702582ea65184ac7b512acd5783656052dba9204376d24a
  Compiled from "CharSetUtils.java"
public class org.apache.commons.lang3.CharSetUtils
  minor version: 0
  major version: 52
  flags: (0x0021) ACC_PUBLIC, ACC_SUPER
  this_class: #19                         // org/apache/commons/lang3/CharSetUtils
  super_class: #20                        // java/lang/Object
  interfaces: 0, fields: 0, methods: 8, attributes: 1
Constant pool:
    #1 = Methodref          #20.#73       // java/lang/Object."<init>":()V
    #2 = Methodref          #15.#74       // org/apache/commons/lang3/StringUtils.isEmpty:(Ljava/lang/CharSequence;)Z
    #3 = Methodref          #19.#75       // org/apache/commons/lang3/CharSetUtils.deepEmpty:([Ljava/lang/String;)Z
    #4 = Methodref          #52.#76       // org/apache/commons/lang3/CharSet.getInstance:([Ljava/lang/String;)Lorg/apache/commons/lang3/CharSet;
    #5 = Class              #77           // java/lang/StringBuilder
    #6 = Methodref          #50.#78       // java/lang/String.length:()I
    #7 = Methodref          #5.#79        // java/lang/StringBuilder."<init>":(I)V
    #8 = Methodref          #50.#80       // java/lang/String.toCharArray:()[C
    #9 = Methodref          #5.#81        // java/lang/StringBuilder.append:(C)Ljava/lang/StringBuilder;
   #10 = Methodref          #54.#82       // java/lang/Character.charValue:()C
   #11 = Methodref          #52.#83       // org/apache/commons/lang3/CharSet.contains:(C)Z
   #12 = Methodref          #54.#84       // java/lang/Character.valueOf:(C)Ljava/lang/Character;
   #13 = Methodref          #5.#85        // java/lang/StringBuilder.toString:()Ljava/lang/String;
   #14 = Methodref          #50.#86       // java/lang/String.isEmpty:()Z
   #15 = Class              #87           // org/apache/commons/lang3/StringUtils
   #16 = String             #88           //
   #17 = Methodref          #19.#89       // org/apache/commons/lang3/CharSetUtils.modify:(Ljava/lang/String;[Ljava/lang/String;Z)Ljava/lang/String;
   #18 = Methodref          #15.#90       // org/apache/commons/lang3/StringUtils.isNotEmpty:(Ljava/lang/CharSequence;)Z
   #19 = Class              #91           // org/apache/commons/lang3/CharSetUtils
   #20 = Class              #92           // java/lang/Object
   #21 = Utf8               <init>
   #22 = Utf8               ()V
   #23 = Utf8               Code
   #24 = Utf8               LineNumberTable
   #25 = Utf8               LocalVariableTable
   #26 = Utf8               this
   #27 = Utf8               Lorg/apache/commons/lang3/CharSetUtils;
   #28 = Utf8               squeeze
   #29 = Utf8               (Ljava/lang/String;[Ljava/lang/String;)Ljava/lang/String;
   #30 = Utf8               i
   #31 = Utf8               I
   #32 = Utf8               str
   #33 = Utf8               Ljava/lang/String;
   #34 = Utf8               set
   #35 = Utf8               [Ljava/lang/String;
   #36 = Utf8               chars
   #37 = Utf8               Lorg/apache/commons/lang3/CharSet;
   #38 = Utf8               buffer
   #39 = Utf8               Ljava/lang/StringBuilder;
   #40 = Utf8               chrs
   #41 = Utf8               [C
   #42 = Utf8               sz
   #43 = Utf8               lastChar
   #44 = Utf8               C
   #45 = Utf8               ch
   #46 = Utf8               inChars
   #47 = Utf8               Ljava/lang/Character;
   #48 = Utf8               notInChars
   #49 = Utf8               StackMapTable
   #50 = Class              #93           // java/lang/String
   #51 = Class              #35           // "[Ljava/lang/String;"
   #52 = Class              #94           // org/apache/commons/lang3/CharSet
   #53 = Class              #41           // "[C"
   #54 = Class              #95           // java/lang/Character
   #55 = Utf8               containsAny
   #56 = Utf8               (Ljava/lang/String;[Ljava/lang/String;)Z
   #57 = Utf8               c
   #58 = Utf8               count
   #59 = Utf8               (Ljava/lang/String;[Ljava/lang/String;)I
   #60 = Utf8               keep
   #61 = Utf8               delete
   #62 = Utf8               modify
   #63 = Utf8               (Ljava/lang/String;[Ljava/lang/String;Z)Ljava/lang/String;
   #64 = Utf8               chr
   #65 = Utf8               expect
   #66 = Utf8               Z
   #67 = Utf8               deepEmpty
   #68 = Utf8               ([Ljava/lang/String;)Z
   #69 = Utf8               s
   #70 = Utf8               strings
   #71 = Utf8               SourceFile
   #72 = Utf8               CharSetUtils.java
   #73 = NameAndType        #21:#22       // "<init>":()V
   #74 = NameAndType        #96:#97       // isEmpty:(Ljava/lang/CharSequence;)Z
   #75 = NameAndType        #67:#68       // deepEmpty:([Ljava/lang/String;)Z
   #76 = NameAndType        #98:#99       // getInstance:([Ljava/lang/String;)Lorg/apache/commons/lang3/CharSet;
   #77 = Utf8               java/lang/StringBuilder
   #78 = NameAndType        #100:#101     // length:()I
   #79 = NameAndType        #21:#102      // "<init>":(I)V
   #80 = NameAndType        #103:#104     // toCharArray:()[C
   #81 = NameAndType        #105:#106     // append:(C)Ljava/lang/StringBuilder;
   #82 = NameAndType        #107:#108     // charValue:()C
   #83 = NameAndType        #109:#110     // contains:(C)Z
   #84 = NameAndType        #111:#112     // valueOf:(C)Ljava/lang/Character;
   #85 = NameAndType        #113:#114     // toString:()Ljava/lang/String;
   #86 = NameAndType        #96:#115      // isEmpty:()Z
   #87 = Utf8               org/apache/commons/lang3/StringUtils
   #88 = Utf8
   #89 = NameAndType        #62:#63       // modify:(Ljava/lang/String;[Ljava/lang/String;Z)Ljava/lang/String;
   #90 = NameAndType        #116:#97      // isNotEmpty:(Ljava/lang/CharSequence;)Z
   #91 = Utf8               org/apache/commons/lang3/CharSetUtils
   #92 = Utf8               java/lang/Object
   #93 = Utf8               java/lang/String
   #94 = Utf8               org/apache/commons/lang3/CharSet
   #95 = Utf8               java/lang/Character
   #96 = Utf8               isEmpty
   #97 = Utf8               (Ljava/lang/CharSequence;)Z
   #98 = Utf8               getInstance
   #99 = Utf8               ([Ljava/lang/String;)Lorg/apache/commons/lang3/CharSet;
  #100 = Utf8               length
  #101 = Utf8               ()I
  #102 = Utf8               (I)V
  #103 = Utf8               toCharArray
  #104 = Utf8               ()[C
  #105 = Utf8               append
  #106 = Utf8               (C)Ljava/lang/StringBuilder;
  #107 = Utf8               charValue
  #108 = Utf8               ()C
  #109 = Utf8               contains
  #110 = Utf8               (C)Z
  #111 = Utf8               valueOf
  #112 = Utf8               (C)Ljava/lang/Character;
  #113 = Utf8               toString
  #114 = Utf8               ()Ljava/lang/String;
  #115 = Utf8               ()Z
  #116 = Utf8               isNotEmpty
{
  public org.apache.commons.lang3.CharSetUtils();
    descriptor: ()V
    flags: (0x0001) ACC_PUBLIC
    Code:
      stack=1, locals=1, args_size=1
         0: aload_0
         1: invokespecial #1                  // Method java/lang/Object."<init>":()V
         4: return
      LineNumberTable:
        line 40: 0
        line 41: 4
      LocalVariableTable:
        Start  Length  Slot  Name   Signature
            0       5     0  this   Lorg/apache/commons/lang3/CharSetUtils;

  public static java.lang.String squeeze(java.lang.String, java.lang.String...);
    descriptor: (Ljava/lang/String;[Ljava/lang/String;)Ljava/lang/String;
    flags: (0x0089) ACC_PUBLIC, ACC_STATIC, ACC_VARARGS
    Code:
      stack=3, locals=11, args_size=2
         0: aload_0
         1: invokestatic  #2                  // Method org/apache/commons/lang3/StringUtils.isEmpty:(Ljava/lang/CharSequence;)Z
         4: ifne          14
         7: aload_1
         8: invokestatic  #3                  // Method deepEmpty:([Ljava/lang/String;)Z
        11: ifeq          16
        14: aload_0
        15: areturn
        16: aload_1
        17: invokestatic  #4                  // Method org/apache/commons/lang3/CharSet.getInstance:([Ljava/lang/String;)Lorg/apache/commons/lang3/CharSet;
        20: astore_2
        21: new           #5                  // class java/lang/StringBuilder
        24: dup
        25: aload_0
        26: invokevirtual #6                  // Method java/lang/String.length:()I
        29: invokespecial #7                  // Method java/lang/StringBuilder."<init>":(I)V
        32: astore_3
        33: aload_0
        34: invokevirtual #8                  // Method java/lang/String.toCharArray:()[C
        37: astore        4
        39: aload         4
        41: arraylength
        42: istore        5
        44: aload         4
        46: iconst_0
        47: caload
        48: istore        6
        50: bipush        32
        52: istore        7
        54: aconst_null
        55: astore        8
        57: aconst_null
        58: astore        9
        60: aload_3
        61: iload         6
        63: invokevirtual #9                  // Method java/lang/StringBuilder.append:(C)Ljava/lang/StringBuilder;
        66: pop
        67: iconst_1
        68: istore        10
        70: iload         10
        72: iload         5
        74: if_icmpge     167
        77: aload         4
        79: iload         10
        81: caload
        82: istore        7
        84: iload         7
        86: iload         6
        88: if_icmpne     150
        91: aload         8
        93: ifnull        109
        96: iload         7
        98: aload         8
       100: invokevirtual #10                 // Method java/lang/Character.charValue:()C
       103: if_icmpne     109
       106: goto          161
       109: aload         9
       111: ifnull        124
       114: iload         7
       116: aload         9
       118: invokevirtual #10                 // Method java/lang/Character.charValue:()C
       121: if_icmpeq     150
       124: aload_2
       125: iload         7
       127: invokevirtual #11                 // Method org/apache/commons/lang3/CharSet.contains:(C)Z
       130: ifeq          143
       133: iload         7
       135: invokestatic  #12                 // Method java/lang/Character.valueOf:(C)Ljava/lang/Character;
       138: astore        8
       140: goto          161
       143: iload         7
       145: invokestatic  #12                 // Method java/lang/Character.valueOf:(C)Ljava/lang/Character;
       148: astore        9
       150: aload_3
       151: iload         7
       153: invokevirtual #9                  // Method java/lang/StringBuilder.append:(C)Ljava/lang/StringBuilder;
       156: pop
       157: iload         7
       159: istore        6
       161: iinc          10, 1
       164: goto          70
       167: aload_3
       168: invokevirtual #13                 // Method java/lang/StringBuilder.toString:()Ljava/lang/String;
       171: areturn
      LineNumberTable:
        line 64: 0
        line 65: 14
        line 67: 16
        line 68: 21
        line 69: 33
        line 70: 39
        line 71: 44
        line 72: 50
        line 73: 54
        line 74: 57
        line 75: 60
        line 76: 67
        line 77: 77
        line 78: 84
        line 79: 91
        line 80: 106
        line 82: 109
        line 83: 124
        line 84: 133
        line 85: 140
        line 87: 143
        line 90: 150
        line 91: 157
        line 76: 161
        line 93: 167
      LocalVariableTable:
        Start  Length  Slot  Name   Signature
           70      97    10     i   I
            0     172     0   str   Ljava/lang/String;
            0     172     1   set   [Ljava/lang/String;
           21     151     2 chars   Lorg/apache/commons/lang3/CharSet;
           33     139     3 buffer   Ljava/lang/StringBuilder;
           39     133     4  chrs   [C
           44     128     5    sz   I
           50     122     6 lastChar   C
           54     118     7    ch   C
           57     115     8 inChars   Ljava/lang/Character;
           60     112     9 notInChars   Ljava/lang/Character;
      StackMapTable: number_of_entries = 9
        frame_type = 14 /* same */
        frame_type = 1 /* same */
        frame_type = 255 /* full_frame */
          offset_delta = 53
          locals = [ class java/lang/String, class "[Ljava/lang/String;", class org/apache/commons/lang3/CharSet, class java/lang/StringBuilder, class "[C", int, int, int, class java/lang/Character, class java/lang/Character, int ]
          stack = []
        frame_type = 38 /* same */
        frame_type = 14 /* same */
        frame_type = 18 /* same */
        frame_type = 6 /* same */
        frame_type = 10 /* same */
        frame_type = 250 /* chop */
          offset_delta = 5

  public static boolean containsAny(java.lang.String, java.lang.String...);
    descriptor: (Ljava/lang/String;[Ljava/lang/String;)Z
    flags: (0x0089) ACC_PUBLIC, ACC_STATIC, ACC_VARARGS
    Code:
      stack=2, locals=7, args_size=2
         0: aload_0
         1: invokestatic  #2                  // Method org/apache/commons/lang3/StringUtils.isEmpty:(Ljava/lang/CharSequence;)Z
         4: ifne          14
         7: aload_1
         8: invokestatic  #3                  // Method deepEmpty:([Ljava/lang/String;)Z
        11: ifeq          16
        14: iconst_0
        15: ireturn
        16: aload_1
        17: invokestatic  #4                  // Method org/apache/commons/lang3/CharSet.getInstance:([Ljava/lang/String;)Lorg/apache/commons/lang3/CharSet;
        20: astore_2
        21: aload_0
        22: invokevirtual #8                  // Method java/lang/String.toCharArray:()[C
        25: astore_3
        26: aload_3
        27: arraylength
        28: istore        4
        30: iconst_0
        31: istore        5
        33: iload         5
        35: iload         4
        37: if_icmpge     63
        40: aload_3
        41: iload         5
        43: caload
        44: istore        6
        46: aload_2
        47: iload         6
        49: invokevirtual #11                 // Method org/apache/commons/lang3/CharSet.contains:(C)Z
        52: ifeq          57
        55: iconst_1
        56: ireturn
        57: iinc          5, 1
        60: goto          33
        63: iconst_0
        64: ireturn
      LineNumberTable:
        line 118: 0
        line 119: 14
        line 121: 16
        line 122: 21
        line 123: 46
        line 124: 55
        line 122: 57
        line 127: 63
      LocalVariableTable:
        Start  Length  Slot  Name   Signature
           46      11     6     c   C
            0      65     0   str   Ljava/lang/String;
            0      65     1   set   [Ljava/lang/String;
           21      44     2 chars   Lorg/apache/commons/lang3/CharSet;
      StackMapTable: number_of_entries = 5
        frame_type = 14 /* same */
        frame_type = 1 /* same */
        frame_type = 255 /* full_frame */
          offset_delta = 16
          locals = [ class java/lang/String, class "[Ljava/lang/String;", class org/apache/commons/lang3/CharSet, class "[C", int, int ]
          stack = []
        frame_type = 23 /* same */
        frame_type = 248 /* chop */
          offset_delta = 5

  public static int count(java.lang.String, java.lang.String...);
    descriptor: (Ljava/lang/String;[Ljava/lang/String;)I
    flags: (0x0089) ACC_PUBLIC, ACC_STATIC, ACC_VARARGS
    Code:
      stack=2, locals=8, args_size=2
         0: aload_0
         1: invokestatic  #2                  // Method org/apache/commons/lang3/StringUtils.isEmpty:(Ljava/lang/CharSequence;)Z
         4: ifne          14
         7: aload_1
         8: invokestatic  #3                  // Method deepEmpty:([Ljava/lang/String;)Z
        11: ifeq          16
        14: iconst_0
        15: ireturn
        16: aload_1
        17: invokestatic  #4                  // Method org/apache/commons/lang3/CharSet.getInstance:([Ljava/lang/String;)Lorg/apache/commons/lang3/CharSet;
        20: astore_2
        21: iconst_0
        22: istore_3
        23: aload_0
        24: invokevirtual #8                  // Method java/lang/String.toCharArray:()[C
        27: astore        4
        29: aload         4
        31: arraylength
        32: istore        5
        34: iconst_0
        35: istore        6
        37: iload         6
        39: iload         5
        41: if_icmpge     69
        44: aload         4
        46: iload         6
        48: caload
        49: istore        7
        51: aload_2
        52: iload         7
        54: invokevirtual #11                 // Method org/apache/commons/lang3/CharSet.contains:(C)Z
        57: ifeq          63
        60: iinc          3, 1
        63: iinc          6, 1
        66: goto          37
        69: iload_3
        70: ireturn
      LineNumberTable:
        line 151: 0
        line 152: 14
        line 154: 16
        line 155: 21
        line 156: 23
        line 157: 51
        line 158: 60
        line 156: 63
        line 161: 69
      LocalVariableTable:
        Start  Length  Slot  Name   Signature
           51      12     7     c   C
            0      71     0   str   Ljava/lang/String;
            0      71     1   set   [Ljava/lang/String;
           21      50     2 chars   Lorg/apache/commons/lang3/CharSet;
           23      48     3 count   I
      StackMapTable: number_of_entries = 5
        frame_type = 14 /* same */
        frame_type = 1 /* same */
        frame_type = 255 /* full_frame */
          offset_delta = 20
          locals = [ class java/lang/String, class "[Ljava/lang/String;", class org/apache/commons/lang3/CharSet, int, class "[C", int, int ]
          stack = []
        frame_type = 25 /* same */
        frame_type = 248 /* chop */
          offset_delta = 5

  public static java.lang.String keep(java.lang.String, java.lang.String...);
    descriptor: (Ljava/lang/String;[Ljava/lang/String;)Ljava/lang/String;
    flags: (0x0089) ACC_PUBLIC, ACC_STATIC, ACC_VARARGS
    Code:
      stack=3, locals=2, args_size=2
         0: aload_0
         1: ifnonnull     6
         4: aconst_null
         5: areturn
         6: aload_0
         7: invokevirtual #14                 // Method java/lang/String.isEmpty:()Z
        10: ifne          20
        13: aload_1
        14: invokestatic  #3                  // Method deepEmpty:([Ljava/lang/String;)Z
        17: ifeq          23
        20: ldc           #16                 // String
        22: areturn
        23: aload_0
        24: aload_1
        25: iconst_1
        26: invokestatic  #17                 // Method modify:(Ljava/lang/String;[Ljava/lang/String;Z)Ljava/lang/String;
        29: areturn
      LineNumberTable:
        line 186: 0
        line 187: 4
        line 189: 6
        line 190: 20
        line 192: 23
      LocalVariableTable:
        Start  Length  Slot  Name   Signature
            0      30     0   str   Ljava/lang/String;
            0      30     1   set   [Ljava/lang/String;
      StackMapTable: number_of_entries = 3
        frame_type = 6 /* same */
        frame_type = 13 /* same */
        frame_type = 2 /* same */

  public static java.lang.String delete(java.lang.String, java.lang.String...);
    descriptor: (Ljava/lang/String;[Ljava/lang/String;)Ljava/lang/String;
    flags: (0x0089) ACC_PUBLIC, ACC_STATIC, ACC_VARARGS
    Code:
      stack=3, locals=2, args_size=2
         0: aload_0
         1: invokestatic  #2                  // Method org/apache/commons/lang3/StringUtils.isEmpty:(Ljava/lang/CharSequence;)Z
         4: ifne          14
         7: aload_1
         8: invokestatic  #3                  // Method deepEmpty:([Ljava/lang/String;)Z
        11: ifeq          16
        14: aload_0
        15: areturn
        16: aload_0
        17: aload_1
        18: iconst_0
        19: invokestatic  #17                 // Method modify:(Ljava/lang/String;[Ljava/lang/String;Z)Ljava/lang/String;
        22: areturn
      LineNumberTable:
        line 216: 0
        line 217: 14
        line 219: 16
      LocalVariableTable:
        Start  Length  Slot  Name   Signature
            0      23     0   str   Ljava/lang/String;
            0      23     1   set   [Ljava/lang/String;
      StackMapTable: number_of_entries = 2
        frame_type = 14 /* same */
        frame_type = 1 /* same */

  private static java.lang.String modify(java.lang.String, java.lang.String[], boolean);
    descriptor: (Ljava/lang/String;[Ljava/lang/String;Z)Ljava/lang/String;
    flags: (0x000a) ACC_PRIVATE, ACC_STATIC
    Code:
      stack=3, locals=10, args_size=3
         0: aload_1
         1: invokestatic  #4                  // Method org/apache/commons/lang3/CharSet.getInstance:([Ljava/lang/String;)Lorg/apache/commons/lang3/CharSet;
         4: astore_3
         5: new           #5                  // class java/lang/StringBuilder
         8: dup
         9: aload_0
        10: invokevirtual #6                  // Method java/lang/String.length:()I
        13: invokespecial #7                  // Method java/lang/StringBuilder."<init>":(I)V
        16: astore        4
        18: aload_0
        19: invokevirtual #8                  // Method java/lang/String.toCharArray:()[C
        22: astore        5
        24: aload         5
        26: astore        6
        28: aload         6
        30: arraylength
        31: istore        7
        33: iconst_0
        34: istore        8
        36: iload         8
        38: iload         7
        40: if_icmpge     74
        43: aload         6
        45: iload         8
        47: caload
        48: istore        9
        50: aload_3
        51: iload         9
        53: invokevirtual #11                 // Method org/apache/commons/lang3/CharSet.contains:(C)Z
        56: iload_2
        57: if_icmpne     68
        60: aload         4
        62: iload         9
        64: invokevirtual #9                  // Method java/lang/StringBuilder.append:(C)Ljava/lang/StringBuilder;
        67: pop
        68: iinc          8, 1
        71: goto          36
        74: aload         4
        76: invokevirtual #13                 // Method java/lang/StringBuilder.toString:()Ljava/lang/String;
        79: areturn
      LineNumberTable:
        line 232: 0
        line 233: 5
        line 234: 18
        line 235: 24
        line 236: 50
        line 237: 60
        line 235: 68
        line 240: 74
      LocalVariableTable:
        Start  Length  Slot  Name   Signature
           50      18     9   chr   C
            0      80     0   str   Ljava/lang/String;
            0      80     1   set   [Ljava/lang/String;
            0      80     2 expect   Z
            5      75     3 chars   Lorg/apache/commons/lang3/CharSet;
           18      62     4 buffer   Ljava/lang/StringBuilder;
           24      56     5  chrs   [C
      StackMapTable: number_of_entries = 3
        frame_type = 255 /* full_frame */
          offset_delta = 36
          locals = [ class java/lang/String, class "[Ljava/lang/String;", int, class org/apache/commons/lang3/CharSet, class java/lang/StringBuilder, class "[C", class "[C", int, int ]
          stack = []
        frame_type = 31 /* same */
        frame_type = 248 /* chop */
          offset_delta = 5

  private static boolean deepEmpty(java.lang.String[]);
    descriptor: ([Ljava/lang/String;)Z
    flags: (0x000a) ACC_PRIVATE, ACC_STATIC
    Code:
      stack=2, locals=5, args_size=1
         0: aload_0
         1: ifnull        37
         4: aload_0
         5: astore_1
         6: aload_1
         7: arraylength
         8: istore_2
         9: iconst_0
        10: istore_3
        11: iload_3
        12: iload_2
        13: if_icmpge     37
        16: aload_1
        17: iload_3
        18: aaload
        19: astore        4
        21: aload         4
        23: invokestatic  #18                 // Method org/apache/commons/lang3/StringUtils.isNotEmpty:(Ljava/lang/CharSequence;)Z
        26: ifeq          31
        29: iconst_0
        30: ireturn
        31: iinc          3, 1
        34: goto          11
        37: iconst_1
        38: ireturn
      LineNumberTable:
        line 251: 0
        line 252: 4
        line 253: 21
        line 254: 29
        line 252: 31
        line 258: 37
      LocalVariableTable:
        Start  Length  Slot  Name   Signature
           21      10     4     s   Ljava/lang/String;
            0      39     0 strings   [Ljava/lang/String;
      StackMapTable: number_of_entries = 3
        frame_type = 254 /* append */
          offset_delta = 11
          locals = [ class "[Ljava/lang/String;", int, int ]
        frame_type = 19 /* same */
        frame_type = 248 /* chop */
          offset_delta = 5
}
SourceFile: "CharSetUtils.java"
