Classfile /Users/mw/Projects/slang-braindump/.jar/jar11/assemble/slang-braindump/assemble/content/org/apache/commons/lang3/ObjectUtils$Null.class
  Last modified May 29, 2022; size 608 bytes
  SHA-256 checksum e60f3cad923b4d467714274ed16a9efc353f4264be0c3e1ecc1d9d129ae1a6e3
  Compiled from "ObjectUtils.java"
public class org.apache.commons.lang3.ObjectUtils$Null implements java.io.Serializable
  minor version: 0
  major version: 52
  flags: (0x0021) ACC_PUBLIC, ACC_SUPER
  this_class: #3                          // org/apache/commons/lang3/ObjectUtils$Null
  super_class: #4                         // java/lang/Object
  interfaces: 1, fields: 1, methods: 2, attributes: 2
Constant pool:
   #1 = Methodref          #4.#24         // java/lang/Object."<init>":()V
   #2 = Fieldref           #25.#26        // org/apache/commons/lang3/ObjectUtils.NULL:Lorg/apache/commons/lang3/ObjectUtils$Null;
   #3 = Class              #27            // org/apache/commons/lang3/ObjectUtils$Null
   #4 = Class              #28            // java/lang/Object
   #5 = Class              #29            // java/io/Serializable
   #6 = Utf8               serialVersionUID
   #7 = Utf8               J
   #8 = Utf8               ConstantValue
   #9 = Long               7092611880189329093l
  #11 = Utf8               <init>
  #12 = Utf8               ()V
  #13 = Utf8               Code
  #14 = Utf8               LineNumberTable
  #15 = Utf8               LocalVariableTable
  #16 = Utf8               this
  #17 = Utf8               Null
  #18 = Utf8               InnerClasses
  #19 = Utf8               Lorg/apache/commons/lang3/ObjectUtils$Null;
  #20 = Utf8               readResolve
  #21 = Utf8               ()Ljava/lang/Object;
  #22 = Utf8               SourceFile
  #23 = Utf8               ObjectUtils.java
  #24 = NameAndType        #11:#12        // "<init>":()V
  #25 = Class              #30            // org/apache/commons/lang3/ObjectUtils
  #26 = NameAndType        #31:#19        // NULL:Lorg/apache/commons/lang3/ObjectUtils$Null;
  #27 = Utf8               org/apache/commons/lang3/ObjectUtils$Null
  #28 = Utf8               java/lang/Object
  #29 = Utf8               java/io/Serializable
  #30 = Utf8               org/apache/commons/lang3/ObjectUtils
  #31 = Utf8               NULL
{
  private static final long serialVersionUID;
    descriptor: J
    flags: (0x001a) ACC_PRIVATE, ACC_STATIC, ACC_FINAL
    ConstantValue: long 7092611880189329093l

  org.apache.commons.lang3.ObjectUtils$Null();
    descriptor: ()V
    flags: (0x0000)
    Code:
      stack=1, locals=1, args_size=1
         0: aload_0
         1: invokespecial #1                  // Method java/lang/Object."<init>":()V
         4: return
      LineNumberTable:
        line 849: 0
        line 850: 4
      LocalVariableTable:
        Start  Length  Slot  Name   Signature
            0       5     0  this   Lorg/apache/commons/lang3/ObjectUtils$Null;

  private java.lang.Object readResolve();
    descriptor: ()Ljava/lang/Object;
    flags: (0x0002) ACC_PRIVATE
    Code:
      stack=1, locals=1, args_size=1
         0: getstatic     #2                  // Field org/apache/commons/lang3/ObjectUtils.NULL:Lorg/apache/commons/lang3/ObjectUtils$Null;
         3: areturn
      LineNumberTable:
        line 858: 0
      LocalVariableTable:
        Start  Length  Slot  Name   Signature
            0       4     0  this   Lorg/apache/commons/lang3/ObjectUtils$Null;
}
SourceFile: "ObjectUtils.java"
InnerClasses:
  public static #17= #3 of #25;           // Null=class org/apache/commons/lang3/ObjectUtils$Null of class org/apache/commons/lang3/ObjectUtils
