Classfile /Users/mw/Projects/slang-braindump/.jar/jar11/assemble/slang-braindump/assemble/content/org/apache/commons/lang3/SerializationUtils.class
  Last modified May 29, 2022; size 4037 bytes
  SHA-256 checksum 5210e16219b7a9de1d7b3a1d13cc49c43978a4f4b091b7f58dcdb21f9ce61dd4
  Compiled from "SerializationUtils.java"
public class org.apache.commons.lang3.SerializationUtils
  minor version: 0
  major version: 52
  flags: (0x0021) ACC_PUBLIC, ACC_SUPER
  this_class: #40                         // org/apache/commons/lang3/SerializationUtils
  super_class: #22                        // java/lang/Object
  interfaces: 0, fields: 0, methods: 7, attributes: 2
Constant pool:
    #1 = Methodref          #22.#97       // java/lang/Object."<init>":()V
    #2 = Methodref          #40.#98       // org/apache/commons/lang3/SerializationUtils.serialize:(Ljava/io/Serializable;)[B
    #3 = Class              #99           // java/io/ByteArrayInputStream
    #4 = Methodref          #3.#100       // java/io/ByteArrayInputStream."<init>":([B)V
    #5 = Class              #101          // org/apache/commons/lang3/SerializationUtils$ClassLoaderAwareObjectInputStream
    #6 = Methodref          #22.#102      // java/lang/Object.getClass:()Ljava/lang/Class;
    #7 = Methodref          #103.#104     // java/lang/Class.getClassLoader:()Ljava/lang/ClassLoader;
    #8 = Methodref          #5.#105       // org/apache/commons/lang3/SerializationUtils$ClassLoaderAwareObjectInputStream."<init>":(Ljava/io/InputStream;Ljava/lang/ClassLoader;)V
    #9 = Methodref          #5.#106       // org/apache/commons/lang3/SerializationUtils$ClassLoaderAwareObjectInputStream.readObject:()Ljava/lang/Object;
   #10 = Class              #107          // java/io/Serializable
   #11 = Methodref          #5.#108       // org/apache/commons/lang3/SerializationUtils$ClassLoaderAwareObjectInputStream.close:()V
   #12 = Class              #109          // java/lang/Throwable
   #13 = Methodref          #12.#110      // java/lang/Throwable.addSuppressed:(Ljava/lang/Throwable;)V
   #14 = Class              #111          // java/lang/ClassNotFoundException
   #15 = Class              #112          // org/apache/commons/lang3/SerializationException
   #16 = String             #113          // ClassNotFoundException while reading cloned object data
   #17 = Methodref          #15.#114      // org/apache/commons/lang3/SerializationException."<init>":(Ljava/lang/String;Ljava/lang/Throwable;)V
   #18 = Class              #115          // java/io/IOException
   #19 = String             #116          // IOException while reading or closing cloned object data
   #20 = Methodref          #40.#117      // org/apache/commons/lang3/SerializationUtils.deserialize:([B)Ljava/lang/Object;
   #21 = String             #118          // The OutputStream must not be null
   #22 = Class              #119          // java/lang/Object
   #23 = Methodref          #120.#121     // org/apache/commons/lang3/Validate.isTrue:(ZLjava/lang/String;[Ljava/lang/Object;)V
   #24 = Class              #122          // java/io/ObjectOutputStream
   #25 = Methodref          #24.#123      // java/io/ObjectOutputStream."<init>":(Ljava/io/OutputStream;)V
   #26 = Methodref          #24.#124      // java/io/ObjectOutputStream.writeObject:(Ljava/lang/Object;)V
   #27 = Methodref          #24.#108      // java/io/ObjectOutputStream.close:()V
   #28 = Methodref          #15.#125      // org/apache/commons/lang3/SerializationException."<init>":(Ljava/lang/Throwable;)V
   #29 = Class              #126          // java/io/ByteArrayOutputStream
   #30 = Methodref          #29.#127      // java/io/ByteArrayOutputStream."<init>":(I)V
   #31 = Methodref          #40.#128      // org/apache/commons/lang3/SerializationUtils.serialize:(Ljava/io/Serializable;Ljava/io/OutputStream;)V
   #32 = Methodref          #29.#129      // java/io/ByteArrayOutputStream.toByteArray:()[B
   #33 = String             #130          // The InputStream must not be null
   #34 = Class              #131          // java/io/ObjectInputStream
   #35 = Methodref          #34.#132      // java/io/ObjectInputStream."<init>":(Ljava/io/InputStream;)V
   #36 = Methodref          #34.#106      // java/io/ObjectInputStream.readObject:()Ljava/lang/Object;
   #37 = Methodref          #34.#108      // java/io/ObjectInputStream.close:()V
   #38 = String             #133          // The byte[] must not be null
   #39 = Methodref          #40.#134      // org/apache/commons/lang3/SerializationUtils.deserialize:(Ljava/io/InputStream;)Ljava/lang/Object;
   #40 = Class              #135          // org/apache/commons/lang3/SerializationUtils
   #41 = Utf8               ClassLoaderAwareObjectInputStream
   #42 = Utf8               InnerClasses
   #43 = Utf8               <init>
   #44 = Utf8               ()V
   #45 = Utf8               Code
   #46 = Utf8               LineNumberTable
   #47 = Utf8               LocalVariableTable
   #48 = Utf8               this
   #49 = Utf8               Lorg/apache/commons/lang3/SerializationUtils;
   #50 = Utf8               clone
   #51 = Utf8               (Ljava/io/Serializable;)Ljava/io/Serializable;
   #52 = Utf8               readObject
   #53 = Utf8               Ljava/io/Serializable;
   #54 = Utf8               in
   #55 = Utf8               Lorg/apache/commons/lang3/SerializationUtils$ClassLoaderAwareObjectInputStream;
   #56 = Utf8               ex
   #57 = Utf8               Ljava/lang/ClassNotFoundException;
   #58 = Utf8               Ljava/io/IOException;
   #59 = Utf8               object
   #60 = Utf8               objectData
   #61 = Utf8               [B
   #62 = Utf8               bais
   #63 = Utf8               Ljava/io/ByteArrayInputStream;
   #64 = Utf8               LocalVariableTypeTable
   #65 = Utf8               TT;
   #66 = Utf8               StackMapTable
   #67 = Class              #61           // "[B"
   #68 = Utf8               Signature
   #69 = Utf8               <T::Ljava/io/Serializable;>(TT;)TT;
   #70 = Utf8               roundtrip
   #71 = Utf8               msg
   #72 = Utf8               serialize
   #73 = Utf8               (Ljava/io/Serializable;Ljava/io/OutputStream;)V
   #74 = Utf8               out
   #75 = Utf8               Ljava/io/ObjectOutputStream;
   #76 = Utf8               obj
   #77 = Utf8               outputStream
   #78 = Utf8               Ljava/io/OutputStream;
   #79 = Class              #136          // java/io/OutputStream
   #80 = Utf8               (Ljava/io/Serializable;)[B
   #81 = Utf8               baos
   #82 = Utf8               Ljava/io/ByteArrayOutputStream;
   #83 = Utf8               deserialize
   #84 = Utf8               (Ljava/io/InputStream;)Ljava/lang/Object;
   #85 = Utf8               Ljava/lang/Object;
   #86 = Utf8               Ljava/io/ObjectInputStream;
   #87 = Utf8               Ljava/lang/Exception;
   #88 = Utf8               inputStream
   #89 = Utf8               Ljava/io/InputStream;
   #90 = Class              #137          // java/io/InputStream
   #91 = Class              #138          // java/lang/Exception
   #92 = Utf8               <T:Ljava/lang/Object;>(Ljava/io/InputStream;)TT;
   #93 = Utf8               ([B)Ljava/lang/Object;
   #94 = Utf8               <T:Ljava/lang/Object;>([B)TT;
   #95 = Utf8               SourceFile
   #96 = Utf8               SerializationUtils.java
   #97 = NameAndType        #43:#44       // "<init>":()V
   #98 = NameAndType        #72:#80       // serialize:(Ljava/io/Serializable;)[B
   #99 = Utf8               java/io/ByteArrayInputStream
  #100 = NameAndType        #43:#139      // "<init>":([B)V
  #101 = Utf8               org/apache/commons/lang3/SerializationUtils$ClassLoaderAwareObjectInputStream
  #102 = NameAndType        #140:#141     // getClass:()Ljava/lang/Class;
  #103 = Class              #142          // java/lang/Class
  #104 = NameAndType        #143:#144     // getClassLoader:()Ljava/lang/ClassLoader;
  #105 = NameAndType        #43:#145      // "<init>":(Ljava/io/InputStream;Ljava/lang/ClassLoader;)V
  #106 = NameAndType        #52:#146      // readObject:()Ljava/lang/Object;
  #107 = Utf8               java/io/Serializable
  #108 = NameAndType        #147:#44      // close:()V
  #109 = Utf8               java/lang/Throwable
  #110 = NameAndType        #148:#149     // addSuppressed:(Ljava/lang/Throwable;)V
  #111 = Utf8               java/lang/ClassNotFoundException
  #112 = Utf8               org/apache/commons/lang3/SerializationException
  #113 = Utf8               ClassNotFoundException while reading cloned object data
  #114 = NameAndType        #43:#150      // "<init>":(Ljava/lang/String;Ljava/lang/Throwable;)V
  #115 = Utf8               java/io/IOException
  #116 = Utf8               IOException while reading or closing cloned object data
  #117 = NameAndType        #83:#93       // deserialize:([B)Ljava/lang/Object;
  #118 = Utf8               The OutputStream must not be null
  #119 = Utf8               java/lang/Object
  #120 = Class              #151          // org/apache/commons/lang3/Validate
  #121 = NameAndType        #152:#153     // isTrue:(ZLjava/lang/String;[Ljava/lang/Object;)V
  #122 = Utf8               java/io/ObjectOutputStream
  #123 = NameAndType        #43:#154      // "<init>":(Ljava/io/OutputStream;)V
  #124 = NameAndType        #155:#156     // writeObject:(Ljava/lang/Object;)V
  #125 = NameAndType        #43:#149      // "<init>":(Ljava/lang/Throwable;)V
  #126 = Utf8               java/io/ByteArrayOutputStream
  #127 = NameAndType        #43:#157      // "<init>":(I)V
  #128 = NameAndType        #72:#73       // serialize:(Ljava/io/Serializable;Ljava/io/OutputStream;)V
  #129 = NameAndType        #158:#159     // toByteArray:()[B
  #130 = Utf8               The InputStream must not be null
  #131 = Utf8               java/io/ObjectInputStream
  #132 = NameAndType        #43:#160      // "<init>":(Ljava/io/InputStream;)V
  #133 = Utf8               The byte[] must not be null
  #134 = NameAndType        #83:#84       // deserialize:(Ljava/io/InputStream;)Ljava/lang/Object;
  #135 = Utf8               org/apache/commons/lang3/SerializationUtils
  #136 = Utf8               java/io/OutputStream
  #137 = Utf8               java/io/InputStream
  #138 = Utf8               java/lang/Exception
  #139 = Utf8               ([B)V
  #140 = Utf8               getClass
  #141 = Utf8               ()Ljava/lang/Class;
  #142 = Utf8               java/lang/Class
  #143 = Utf8               getClassLoader
  #144 = Utf8               ()Ljava/lang/ClassLoader;
  #145 = Utf8               (Ljava/io/InputStream;Ljava/lang/ClassLoader;)V
  #146 = Utf8               ()Ljava/lang/Object;
  #147 = Utf8               close
  #148 = Utf8               addSuppressed
  #149 = Utf8               (Ljava/lang/Throwable;)V
  #150 = Utf8               (Ljava/lang/String;Ljava/lang/Throwable;)V
  #151 = Utf8               org/apache/commons/lang3/Validate
  #152 = Utf8               isTrue
  #153 = Utf8               (ZLjava/lang/String;[Ljava/lang/Object;)V
  #154 = Utf8               (Ljava/io/OutputStream;)V
  #155 = Utf8               writeObject
  #156 = Utf8               (Ljava/lang/Object;)V
  #157 = Utf8               (I)V
  #158 = Utf8               toByteArray
  #159 = Utf8               ()[B
  #160 = Utf8               (Ljava/io/InputStream;)V
{
  public org.apache.commons.lang3.SerializationUtils();
    descriptor: ()V
    flags: (0x0001) ACC_PUBLIC
    Code:
      stack=1, locals=1, args_size=1
         0: aload_0
         1: invokespecial #1                  // Method java/lang/Object."<init>":()V
         4: return
      LineNumberTable:
        line 58: 0
        line 59: 4
      LocalVariableTable:
        Start  Length  Slot  Name   Signature
            0       5     0  this   Lorg/apache/commons/lang3/SerializationUtils;

  public static <T extends java.io.Serializable> T clone(T);
    descriptor: (Ljava/io/Serializable;)Ljava/io/Serializable;
    flags: (0x0009) ACC_PUBLIC, ACC_STATIC
    Code:
      stack=4, locals=6, args_size=1
         0: aload_0
         1: ifnonnull     6
         4: aconst_null
         5: areturn
         6: aload_0
         7: invokestatic  #2                  // Method serialize:(Ljava/io/Serializable;)[B
        10: astore_1
        11: new           #3                  // class java/io/ByteArrayInputStream
        14: dup
        15: aload_1
        16: invokespecial #4                  // Method java/io/ByteArrayInputStream."<init>":([B)V
        19: astore_2
        20: new           #5                  // class org/apache/commons/lang3/SerializationUtils$ClassLoaderAwareObjectInputStream
        23: dup
        24: aload_2
        25: aload_0
        26: invokevirtual #6                  // Method java/lang/Object.getClass:()Ljava/lang/Class;
        29: invokevirtual #7                  // Method java/lang/Class.getClassLoader:()Ljava/lang/ClassLoader;
        32: invokespecial #8                  // Method org/apache/commons/lang3/SerializationUtils$ClassLoaderAwareObjectInputStream."<init>":(Ljava/io/InputStream;Ljava/lang/ClassLoader;)V
        35: astore_3
        36: aload_3
        37: invokevirtual #9                  // Method org/apache/commons/lang3/SerializationUtils$ClassLoaderAwareObjectInputStream.readObject:()Ljava/lang/Object;
        40: checkcast     #10                 // class java/io/Serializable
        43: astore        4
        45: aload         4
        47: astore        5
        49: aload_3
        50: invokevirtual #11                 // Method org/apache/commons/lang3/SerializationUtils$ClassLoaderAwareObjectInputStream.close:()V
        53: aload         5
        55: areturn
        56: astore        4
        58: aload_3
        59: invokevirtual #11                 // Method org/apache/commons/lang3/SerializationUtils$ClassLoaderAwareObjectInputStream.close:()V
        62: goto          74
        65: astore        5
        67: aload         4
        69: aload         5
        71: invokevirtual #13                 // Method java/lang/Throwable.addSuppressed:(Ljava/lang/Throwable;)V
        74: aload         4
        76: athrow
        77: astore_3
        78: new           #15                 // class org/apache/commons/lang3/SerializationException
        81: dup
        82: ldc           #16                 // String ClassNotFoundException while reading cloned object data
        84: aload_3
        85: invokespecial #17                 // Method org/apache/commons/lang3/SerializationException."<init>":(Ljava/lang/String;Ljava/lang/Throwable;)V
        88: athrow
        89: astore_3
        90: new           #15                 // class org/apache/commons/lang3/SerializationException
        93: dup
        94: ldc           #19                 // String IOException while reading or closing cloned object data
        96: aload_3
        97: invokespecial #17                 // Method org/apache/commons/lang3/SerializationException."<init>":(Ljava/lang/String;Ljava/lang/Throwable;)V
       100: athrow
      Exception table:
         from    to  target type
            36    49    56   Class java/lang/Throwable
            58    62    65   Class java/lang/Throwable
            20    53    77   Class java/lang/ClassNotFoundException
            56    77    77   Class java/lang/ClassNotFoundException
            20    53    89   Class java/io/IOException
            56    77    89   Class java/io/IOException
      LineNumberTable:
        line 78: 0
        line 79: 4
        line 81: 6
        line 82: 11
        line 84: 20
        line 85: 26
        line 92: 36
        line 93: 45
        line 95: 49
        line 93: 53
        line 84: 56
        line 95: 77
        line 96: 78
        line 97: 89
        line 98: 90
      LocalVariableTable:
        Start  Length  Slot  Name   Signature
           45      11     4 readObject   Ljava/io/Serializable;
           36      41     3    in   Lorg/apache/commons/lang3/SerializationUtils$ClassLoaderAwareObjectInputStream;
           78      11     3    ex   Ljava/lang/ClassNotFoundException;
           90      11     3    ex   Ljava/io/IOException;
            0     101     0 object   Ljava/io/Serializable;
           11      90     1 objectData   [B
           20      81     2  bais   Ljava/io/ByteArrayInputStream;
      LocalVariableTypeTable:
        Start  Length  Slot  Name   Signature
           45      11     4 readObject   TT;
            0     101     0 object   TT;
      StackMapTable: number_of_entries = 6
        frame_type = 6 /* same */
        frame_type = 255 /* full_frame */
          offset_delta = 49
          locals = [ class java/io/Serializable, class "[B", class java/io/ByteArrayInputStream, class org/apache/commons/lang3/SerializationUtils$ClassLoaderAwareObjectInputStream ]
          stack = [ class java/lang/Throwable ]
        frame_type = 255 /* full_frame */
          offset_delta = 8
          locals = [ class java/io/Serializable, class "[B", class java/io/ByteArrayInputStream, class org/apache/commons/lang3/SerializationUtils$ClassLoaderAwareObjectInputStream, class java/lang/Throwable ]
          stack = [ class java/lang/Throwable ]
        frame_type = 8 /* same */
        frame_type = 255 /* full_frame */
          offset_delta = 2
          locals = [ class java/io/Serializable, class "[B", class java/io/ByteArrayInputStream ]
          stack = [ class java/lang/ClassNotFoundException ]
        frame_type = 75 /* same_locals_1_stack_item */
          stack = [ class java/io/IOException ]
    Signature: #69                          // <T::Ljava/io/Serializable;>(TT;)TT;

  public static <T extends java.io.Serializable> T roundtrip(T);
    descriptor: (Ljava/io/Serializable;)Ljava/io/Serializable;
    flags: (0x0009) ACC_PUBLIC, ACC_STATIC
    Code:
      stack=1, locals=1, args_size=1
         0: aload_0
         1: invokestatic  #2                  // Method serialize:(Ljava/io/Serializable;)[B
         4: invokestatic  #20                 // Method deserialize:([B)Ljava/lang/Object;
         7: checkcast     #10                 // class java/io/Serializable
        10: areturn
      LineNumberTable:
        line 115: 0
      LocalVariableTable:
        Start  Length  Slot  Name   Signature
            0      11     0   msg   Ljava/io/Serializable;
      LocalVariableTypeTable:
        Start  Length  Slot  Name   Signature
            0      11     0   msg   TT;
    Signature: #69                          // <T::Ljava/io/Serializable;>(TT;)TT;

  public static void serialize(java.io.Serializable, java.io.OutputStream);
    descriptor: (Ljava/io/Serializable;Ljava/io/OutputStream;)V
    flags: (0x0009) ACC_PUBLIC, ACC_STATIC
    Code:
      stack=3, locals=5, args_size=2
         0: aload_1
         1: ifnull        8
         4: iconst_1
         5: goto          9
         8: iconst_0
         9: ldc           #21                 // String The OutputStream must not be null
        11: iconst_0
        12: anewarray     #22                 // class java/lang/Object
        15: invokestatic  #23                 // Method org/apache/commons/lang3/Validate.isTrue:(ZLjava/lang/String;[Ljava/lang/Object;)V
        18: new           #24                 // class java/io/ObjectOutputStream
        21: dup
        22: aload_1
        23: invokespecial #25                 // Method java/io/ObjectOutputStream."<init>":(Ljava/io/OutputStream;)V
        26: astore_2
        27: aload_2
        28: aload_0
        29: invokevirtual #26                 // Method java/io/ObjectOutputStream.writeObject:(Ljava/lang/Object;)V
        32: aload_2
        33: invokevirtual #27                 // Method java/io/ObjectOutputStream.close:()V
        36: goto          57
        39: astore_3
        40: aload_2
        41: invokevirtual #27                 // Method java/io/ObjectOutputStream.close:()V
        44: goto          55
        47: astore        4
        49: aload_3
        50: aload         4
        52: invokevirtual #13                 // Method java/lang/Throwable.addSuppressed:(Ljava/lang/Throwable;)V
        55: aload_3
        56: athrow
        57: goto          70
        60: astore_2
        61: new           #15                 // class org/apache/commons/lang3/SerializationException
        64: dup
        65: aload_2
        66: invokespecial #28                 // Method org/apache/commons/lang3/SerializationException."<init>":(Ljava/lang/Throwable;)V
        69: athrow
        70: return
      Exception table:
         from    to  target type
            27    32    39   Class java/lang/Throwable
            40    44    47   Class java/lang/Throwable
            18    57    60   Class java/io/IOException
      LineNumberTable:
        line 136: 0
        line 137: 18
        line 138: 27
        line 139: 32
        line 137: 39
        line 141: 57
        line 139: 60
        line 140: 61
        line 142: 70
      LocalVariableTable:
        Start  Length  Slot  Name   Signature
           27      30     2   out   Ljava/io/ObjectOutputStream;
           61       9     2    ex   Ljava/io/IOException;
            0      71     0   obj   Ljava/io/Serializable;
            0      71     1 outputStream   Ljava/io/OutputStream;
      StackMapTable: number_of_entries = 8
        frame_type = 8 /* same */
        frame_type = 64 /* same_locals_1_stack_item */
          stack = [ int ]
        frame_type = 255 /* full_frame */
          offset_delta = 29
          locals = [ class java/io/Serializable, class java/io/OutputStream, class java/io/ObjectOutputStream ]
          stack = [ class java/lang/Throwable ]
        frame_type = 255 /* full_frame */
          offset_delta = 7
          locals = [ class java/io/Serializable, class java/io/OutputStream, class java/io/ObjectOutputStream, class java/lang/Throwable ]
          stack = [ class java/lang/Throwable ]
        frame_type = 7 /* same */
        frame_type = 249 /* chop */
          offset_delta = 1
        frame_type = 66 /* same_locals_1_stack_item */
          stack = [ class java/io/IOException ]
        frame_type = 9 /* same */

  public static byte[] serialize(java.io.Serializable);
    descriptor: (Ljava/io/Serializable;)[B
    flags: (0x0009) ACC_PUBLIC, ACC_STATIC
    Code:
      stack=3, locals=2, args_size=1
         0: new           #29                 // class java/io/ByteArrayOutputStream
         3: dup
         4: sipush        512
         7: invokespecial #30                 // Method java/io/ByteArrayOutputStream."<init>":(I)V
        10: astore_1
        11: aload_0
        12: aload_1
        13: invokestatic  #31                 // Method serialize:(Ljava/io/Serializable;Ljava/io/OutputStream;)V
        16: aload_1
        17: invokevirtual #32                 // Method java/io/ByteArrayOutputStream.toByteArray:()[B
        20: areturn
      LineNumberTable:
        line 153: 0
        line 154: 11
        line 155: 16
      LocalVariableTable:
        Start  Length  Slot  Name   Signature
            0      21     0   obj   Ljava/io/Serializable;
           11      10     1  baos   Ljava/io/ByteArrayOutputStream;

  public static <T extends java.lang.Object> T deserialize(java.io.InputStream);
    descriptor: (Ljava/io/InputStream;)Ljava/lang/Object;
    flags: (0x0009) ACC_PUBLIC, ACC_STATIC
    Code:
      stack=3, locals=4, args_size=1
         0: aload_0
         1: ifnull        8
         4: iconst_1
         5: goto          9
         8: iconst_0
         9: ldc           #33                 // String The InputStream must not be null
        11: iconst_0
        12: anewarray     #22                 // class java/lang/Object
        15: invokestatic  #23                 // Method org/apache/commons/lang3/Validate.isTrue:(ZLjava/lang/String;[Ljava/lang/Object;)V
        18: new           #34                 // class java/io/ObjectInputStream
        21: dup
        22: aload_0
        23: invokespecial #35                 // Method java/io/ObjectInputStream."<init>":(Ljava/io/InputStream;)V
        26: astore_1
        27: aload_1
        28: invokevirtual #36                 // Method java/io/ObjectInputStream.readObject:()Ljava/lang/Object;
        31: astore_2
        32: aload_2
        33: astore_3
        34: aload_1
        35: invokevirtual #37                 // Method java/io/ObjectInputStream.close:()V
        38: aload_3
        39: areturn
        40: astore_2
        41: aload_1
        42: invokevirtual #37                 // Method java/io/ObjectInputStream.close:()V
        45: goto          54
        48: astore_3
        49: aload_2
        50: aload_3
        51: invokevirtual #13                 // Method java/lang/Throwable.addSuppressed:(Ljava/lang/Throwable;)V
        54: aload_2
        55: athrow
        56: astore_1
        57: new           #15                 // class org/apache/commons/lang3/SerializationException
        60: dup
        61: aload_1
        62: invokespecial #28                 // Method org/apache/commons/lang3/SerializationException."<init>":(Ljava/lang/Throwable;)V
        65: athrow
      Exception table:
         from    to  target type
            27    34    40   Class java/lang/Throwable
            41    45    48   Class java/lang/Throwable
            18    38    56   Class java/lang/ClassNotFoundException
            18    38    56   Class java/io/IOException
            40    56    56   Class java/lang/ClassNotFoundException
            40    56    56   Class java/io/IOException
      LineNumberTable:
        line 191: 0
        line 192: 18
        line 194: 27
        line 195: 32
        line 196: 34
        line 195: 38
        line 192: 40
        line 196: 56
        line 197: 57
      LocalVariableTable:
        Start  Length  Slot  Name   Signature
           32       8     2   obj   Ljava/lang/Object;
           27      29     1    in   Ljava/io/ObjectInputStream;
           57       9     1    ex   Ljava/lang/Exception;
            0      66     0 inputStream   Ljava/io/InputStream;
      LocalVariableTypeTable:
        Start  Length  Slot  Name   Signature
           32       8     2   obj   TT;
      StackMapTable: number_of_entries = 6
        frame_type = 8 /* same */
        frame_type = 64 /* same_locals_1_stack_item */
          stack = [ int ]
        frame_type = 255 /* full_frame */
          offset_delta = 30
          locals = [ class java/io/InputStream, class java/io/ObjectInputStream ]
          stack = [ class java/lang/Throwable ]
        frame_type = 255 /* full_frame */
          offset_delta = 7
          locals = [ class java/io/InputStream, class java/io/ObjectInputStream, class java/lang/Throwable ]
          stack = [ class java/lang/Throwable ]
        frame_type = 5 /* same */
        frame_type = 255 /* full_frame */
          offset_delta = 1
          locals = [ class java/io/InputStream ]
          stack = [ class java/lang/Exception ]
    Signature: #92                          // <T:Ljava/lang/Object;>(Ljava/io/InputStream;)TT;

  public static <T extends java.lang.Object> T deserialize(byte[]);
    descriptor: ([B)Ljava/lang/Object;
    flags: (0x0009) ACC_PUBLIC, ACC_STATIC
    Code:
      stack=3, locals=1, args_size=1
         0: aload_0
         1: ifnull        8
         4: iconst_1
         5: goto          9
         8: iconst_0
         9: ldc           #38                 // String The byte[] must not be null
        11: iconst_0
        12: anewarray     #22                 // class java/lang/Object
        15: invokestatic  #23                 // Method org/apache/commons/lang3/Validate.isTrue:(ZLjava/lang/String;[Ljava/lang/Object;)V
        18: new           #3                  // class java/io/ByteArrayInputStream
        21: dup
        22: aload_0
        23: invokespecial #4                  // Method java/io/ByteArrayInputStream."<init>":([B)V
        26: invokestatic  #39                 // Method deserialize:(Ljava/io/InputStream;)Ljava/lang/Object;
        29: areturn
      LineNumberTable:
        line 222: 0
        line 223: 18
      LocalVariableTable:
        Start  Length  Slot  Name   Signature
            0      30     0 objectData   [B
      StackMapTable: number_of_entries = 2
        frame_type = 8 /* same */
        frame_type = 64 /* same_locals_1_stack_item */
          stack = [ int ]
    Signature: #94                          // <T:Ljava/lang/Object;>([B)TT;
}
SourceFile: "SerializationUtils.java"
InnerClasses:
  static #41= #5 of #40;                  // ClassLoaderAwareObjectInputStream=class org/apache/commons/lang3/SerializationUtils$ClassLoaderAwareObjectInputStream of class org/apache/commons/lang3/SerializationUtils
