Classfile /Users/mw/Projects/slang-braindump/.jar/jar8/assemble/slang-braindump/assemble/content/scala/collection/parallel/immutable/HashSetCombiner.class
  Last modified May 29, 2022; size 8300 bytes
  SHA-256 checksum e5db3502ffcc0dc2bdf856ad5e29f4fe7ebd4c21727c9f43457c5763e667486a
  Compiled from "ParHashSet.scala"
public abstract class scala.collection.parallel.immutable.HashSetCombiner<T extends java.lang.Object> extends scala.collection.parallel.BucketCombiner<T, scala.collection.parallel.immutable.ParHashSet<T>, java.lang.Object, scala.collection.parallel.immutable.HashSetCombiner<T>>
  minor version: 0
  major version: 52
  flags: (0x0421) ACC_PUBLIC, ACC_SUPER, ACC_ABSTRACT
  this_class: #2                          // scala/collection/parallel/immutable/HashSetCombiner
  super_class: #5                         // scala/collection/parallel/BucketCombiner
  interfaces: 0, fields: 1, methods: 13, attributes: 7
Constant pool:
    #1 = Utf8               scala/collection/parallel/immutable/HashSetCombiner
    #2 = Class              #1            // scala/collection/parallel/immutable/HashSetCombiner
    #3 = Utf8               <T:Ljava/lang/Object;>Lscala/collection/parallel/BucketCombiner<TT;Lscala/collection/parallel/immutable/ParHashSet<TT;>;Ljava/lang/Object;Lscala/collection/parallel/immutable/HashSetCombiner<TT;>;>;
    #4 = Utf8               scala/collection/parallel/BucketCombiner
    #5 = Class              #4            // scala/collection/parallel/BucketCombiner
    #6 = Utf8               ParHashSet.scala
    #7 = Utf8               Lscala/reflect/ScalaSignature;
    #8 = Utf8               bytes
    #9 = Utf8               \u0006\u0005\u0005-cAB\u000e\u001d\u0003\u0003aB\u0005C\u0003=\u0001\u0011\u0005Q\bC\u0004?\u0001\t\u0007I\u0011A \t\r\u0015\u0003\u0001\u0015!\u0003A\u0011\u00151\u0005\u0001\"\u0001H\u0011\u0015Y\u0005\u0001\"\u0001M\r\u0011i\u0005\u0001\u0001(\t\u0011e3!\u0011!Q\u0001\niC\u0001b\u001c\u0004\u0003\u0002\u0003\u0006I\u0001\u001d\u0005\tc\u001a\u0011\t\u0011)A\u0005e\"AQO\u0002B\u0001B\u0003%!\u000fC\u0003=\r\u0011\u0005a\u000fC\u0004L\r\u0001\u0007I\u0011A>\t\u000fq4\u0001\u0019!C\u0001{\"9\u0011\u0011\u0001\u0004!B\u0013)\u0006bBA\u0002\r\u0011\u0005\u0011Q\u0001\u0005\b\u0003#1A\u0011BA\n\u0011\u001d\tIB\u0002C\u0001\u00037Aq!a\t\u0007\t\u0003\t)cB\u0004\u0002.qA\t!a\f\u0007\rma\u0002\u0012AA\u0019\u0011\u0019aD\u0003\"\u0001\u00024!9\u0011Q\u0007\u000b\u0005\u0002\u0005]\u0002BCA!)\t\u0007I\u0011\u0001\u000f\u0002D!9\u0011Q\t\u000b!\u0002\u0013\u0011\bBCA$)\t\u0007I\u0011\u0001\u000f\u0002D!9\u0011\u0011\n\u000b!\u0002\u0013\u0011(a\u0004%bg\"\u001cV\r^\"p[\nLg.\u001a:\u000b\u0005uq\u0012!C5n[V$\u0018M\u00197f\u0015\ty\u0002%\u0001\u0005qCJ\fG\u000e\\3m\u0015\t\t#%\u0001\u0006d_2dWm\u0019;j_:T\u0011aI\u0001\u0006g\u000e\fG.Y\u000b\u0003K1\u001a\"\u0001\u0001\u0014\u0011\r\u001dB#f\u000e\u001b<\u001b\u0005q\u0012BA\u0015\u001f\u00059\u0011UoY6fi\u000e{WNY5oKJ\u0004\"a\u000b\u0017\r\u0001\u0011)Q\u0006\u0001b\u0001_\t\tAk\u0001\u0001\u0012\u0005A\"\u0004CA\u00193\u001b\u0005\u0011\u0013BA\u001a#\u0005\u001dqu\u000e\u001e5j]\u001e\u0004\"!M\u001b\n\u0005Y\u0012#aA!osB\u0019\u0001(\u000f\u0016\u000e\u0003qI!A\u000f\u000f\u0003\u0015A\u000b\'\u000fS1tQN+G\u000fE\u00029\u0001)\na\u0001P5oSRtD#A\u001e\u0002\u0013\u0015l\u0007\u000f^=Ue&,W#\u0001!\u0011\u0007\u0005\u001b%&D\u0001C\u0015\ti\u0002%\u0003\u0002E\u0005\nQq\n\u001c3ICND7+\u001a;\u0002\u0015\u0015l\u0007\u000f^=Ue&,\u0007%\u0001\u0004bI\u0012|e.\u001a\u000b\u0003\u0011&k\u0011\u0001\u0001\u0005\u0006\u0015\u0012\u0001\rAK\u0001\u0005K2,W.\u0001\u0004sKN,H\u000e\u001e\u000b\u0002o\tQ1I]3bi\u0016$&/[3\u0014\u0007\u0019y%\u000b\u0005\u00022!&\u0011\u0011K\t\u0002\u0007\u0003:L(+\u001a4\u0011\t\u001d\u001aV\u000bW\u0005\u0003)z\u0011A\u0001V1tWB\u0011\u0011GV\u0005\u0003/\n\u0012A!\u00168jiB\u0011\u0001JB\u0001\u0006EV\u001c7n\u001d\t\u0004cmk\u0016B\u0001/#\u0005\u0015\t%O]1z!\rqF\u000e\u000e\b\u0003?&t!\u0001Y4\u000f\u0005\u00054gB\u00012f\u001b\u0005\u0019\'B\u00013/\u0003\u0019a$o\\8u}%\t1%\u0003\u0002\"E%\u0011\u0001\u000eI\u0001\b[V$\u0018M\u00197f\u0013\tQ7.\u0001\bV]J|G\u000e\\3e\u0005V4g-\u001a:\u000b\u0005!\u0004\u0013BA7o\u0005!)fN]8mY\u0016$\'B\u00016l\u0003\u0011\u0011xn\u001c;\u0011\u0007EZ\u0006)\u0001\u0004pM\u001a\u001cX\r\u001e\t\u0003cML!\u0001\u001e\u0012\u0003\u0007%sG/A\u0004i_^l\u0017M\\=\u0015\u000ba;\b0\u001f>\t\u000be[\u0001\u0019\u0001.\t\u000b=\\\u0001\u0019\u00019\t\u000bE\\\u0001\u0019\u0001:\t\u000bU\\\u0001\u0019\u0001:\u0016\u0003U\u000b!B]3tk2$x\fJ3r)\t)f\u0010C\u0004\u0000\u001b\u0005\u0005\t\u0019A+\u0002\u0007a$\u0013\'A\u0004sKN,H\u000e\u001e\u0011\u0002\t1,\u0017M\u001a\u000b\u0004+\u0006\u001d\u0001bBA\u0005\u001f\u0001\u0007\u00111B\u0001\u0005aJ,g\u000f\u0005\u00032\u0003\u001b)\u0016bAA\bE\t1q\n\u001d;j_:\f!b\u0019:fCR,GK]5f)\r\u0001\u0015Q\u0003\u0005\u0007\u0003/\u0001\u0002\u0019A/\u0002\u000b\u0015dW-\\:\u0002\u000bM\u0004H.\u001b;\u0016\u0005\u0005u\u0001\u0003B!\u0002 aK1!!\tC\u0005\u0011a\u0015n\u001d;\u0002%MDw.\u001e7e\'Bd\u0017\u000e\u001e$veRDWM]\u000b\u0003\u0003O\u00012!MA\u0015\u0013\r\tYC\t\u0002\b\u0005>|G.Z1o\u0003=A\u0015m\u001d5TKR\u001cu.\u001c2j]\u0016\u0014\bC\u0001\u001d\u0015\'\t!r\n\u0006\u0002\u00020\u0005)\u0011\r\u001d9msV!\u0011\u0011HA +\t\tY\u0004\u0005\u00039\u0001\u0005u\u0002cA\u0016\u0002@\u0011)QF\u0006b\u0001_\u0005A!o\\8uE&$8/F\u0001s\u0003%\u0011xn\u001c;cSR\u001c\b%\u0001\u0005s_>$8/\u001b>f\u0003%\u0011xn\u001c;tSj,\u0007\u0005
   #10 = Utf8               java/lang/invoke/MethodHandles$Lookup
   #11 = Class              #10           // java/lang/invoke/MethodHandles$Lookup
   #12 = Utf8               java/lang/invoke/MethodHandles
   #13 = Class              #12           // java/lang/invoke/MethodHandles
   #14 = Utf8               Lookup
   #15 = Utf8               scala/collection/immutable/OldHashSet$HashTrieSet
   #16 = Class              #15           // scala/collection/immutable/OldHashSet$HashTrieSet
   #17 = Utf8               scala/collection/immutable/OldHashSet
   #18 = Class              #17           // scala/collection/immutable/OldHashSet
   #19 = Utf8               HashTrieSet
   #20 = Utf8               scala/collection/mutable/UnrolledBuffer$Unrolled
   #21 = Class              #20           // scala/collection/mutable/UnrolledBuffer$Unrolled
   #22 = Utf8               scala/collection/mutable/UnrolledBuffer
   #23 = Class              #22           // scala/collection/mutable/UnrolledBuffer
   #24 = Utf8               Unrolled
   #25 = Utf8               scala/collection/parallel/immutable/HashSetCombiner$CreateTrie
   #26 = Class              #25           // scala/collection/parallel/immutable/HashSetCombiner$CreateTrie
   #27 = Utf8               CreateTrie
   #28 = Utf8               emptyTrie
   #29 = Utf8               Lscala/collection/immutable/OldHashSet;
   #30 = Utf8               Lscala/collection/immutable/OldHashSet<TT;>;
   #31 = Utf8               apply
   #32 = Utf8               ()Lscala/collection/parallel/immutable/HashSetCombiner;
   #33 = Utf8               <T:Ljava/lang/Object;>()Lscala/collection/parallel/immutable/HashSetCombiner<TT;>;
   #34 = Utf8               scala/collection/parallel/immutable/HashSetCombiner$
   #35 = Class              #34           // scala/collection/parallel/immutable/HashSetCombiner$
   #36 = Utf8               MODULE$
   #37 = Utf8               Lscala/collection/parallel/immutable/HashSetCombiner$;
   #38 = NameAndType        #36:#37       // MODULE$:Lscala/collection/parallel/immutable/HashSetCombiner$;
   #39 = Fieldref           #35.#38       // scala/collection/parallel/immutable/HashSetCombiner$.MODULE$:Lscala/collection/parallel/immutable/HashSetCombiner$;
   #40 = NameAndType        #31:#32       // apply:()Lscala/collection/parallel/immutable/HashSetCombiner;
   #41 = Methodref          #35.#40       // scala/collection/parallel/immutable/HashSetCombiner$.apply:()Lscala/collection/parallel/immutable/HashSetCombiner;
   #42 = Utf8               ()Lscala/collection/immutable/OldHashSet;
   #43 = Utf8               ()Lscala/collection/immutable/OldHashSet<TT;>;
   #44 = NameAndType        #28:#29       // emptyTrie:Lscala/collection/immutable/OldHashSet;
   #45 = Fieldref           #2.#44        // scala/collection/parallel/immutable/HashSetCombiner.emptyTrie:Lscala/collection/immutable/OldHashSet;
   #46 = Utf8               this
   #47 = Utf8               Lscala/collection/parallel/immutable/HashSetCombiner;
   #48 = Utf8               addOne
   #49 = Utf8               (Ljava/lang/Object;)Lscala/collection/parallel/immutable/HashSetCombiner;
   #50 = Utf8               (TT;)Lscala/collection/parallel/immutable/HashSetCombiner<TT;>;
   #51 = Utf8               elem
   #52 = Utf8               sz
   #53 = Utf8               ()I
   #54 = NameAndType        #52:#53       // sz:()I
   #55 = Methodref          #2.#54        // scala/collection/parallel/immutable/HashSetCombiner.sz:()I
   #56 = Utf8               sz_$eq
   #57 = Utf8               (I)V
   #58 = NameAndType        #56:#57       // sz_$eq:(I)V
   #59 = Methodref          #2.#58        // scala/collection/parallel/immutable/HashSetCombiner.sz_$eq:(I)V
   #60 = Utf8               scala/collection/Hashing$
   #61 = Class              #60           // scala/collection/Hashing$
   #62 = Utf8               Lscala/collection/Hashing$;
   #63 = NameAndType        #36:#62       // MODULE$:Lscala/collection/Hashing$;
   #64 = Fieldref           #61.#63       // scala/collection/Hashing$.MODULE$:Lscala/collection/Hashing$;
   #65 = Utf8               computeHash
   #66 = Utf8               (Ljava/lang/Object;)I
   #67 = NameAndType        #65:#66       // computeHash:(Ljava/lang/Object;)I
   #68 = Methodref          #61.#67       // scala/collection/Hashing$.computeHash:(Ljava/lang/Object;)I
   #69 = Utf8               buckets
   #70 = Utf8               ()[Lscala/collection/mutable/UnrolledBuffer;
   #71 = NameAndType        #69:#70       // buckets:()[Lscala/collection/mutable/UnrolledBuffer;
   #72 = Methodref          #2.#71        // scala/collection/parallel/immutable/HashSetCombiner.buckets:()[Lscala/collection/mutable/UnrolledBuffer;
   #73 = Utf8               scala/reflect/ClassTag$
   #74 = Class              #73           // scala/reflect/ClassTag$
   #75 = Utf8               Lscala/reflect/ClassTag$;
   #76 = NameAndType        #36:#75       // MODULE$:Lscala/reflect/ClassTag$;
   #77 = Fieldref           #74.#76       // scala/reflect/ClassTag$.MODULE$:Lscala/reflect/ClassTag$;
   #78 = Utf8               Any
   #79 = Utf8               ()Lscala/reflect/ClassTag;
   #80 = NameAndType        #78:#79       // Any:()Lscala/reflect/ClassTag;
   #81 = Methodref          #74.#80       // scala/reflect/ClassTag$.Any:()Lscala/reflect/ClassTag;
   #82 = Utf8               <init>
   #83 = Utf8               (Lscala/reflect/ClassTag;)V
   #84 = NameAndType        #82:#83       // "<init>":(Lscala/reflect/ClassTag;)V
   #85 = Methodref          #23.#84       // scala/collection/mutable/UnrolledBuffer."<init>":(Lscala/reflect/ClassTag;)V
   #86 = Utf8               $plus$eq
   #87 = Utf8               (Ljava/lang/Object;)Lscala/collection/mutable/Growable;
   #88 = NameAndType        #86:#87       // $plus$eq:(Ljava/lang/Object;)Lscala/collection/mutable/Growable;
   #89 = Methodref          #23.#88       // scala/collection/mutable/UnrolledBuffer.$plus$eq:(Ljava/lang/Object;)Lscala/collection/mutable/Growable;
   #90 = Utf8               hc
   #91 = Utf8               I
   #92 = Utf8               pos
   #93 = Utf8               Ljava/lang/Object;
   #94 = Utf8               result
   #95 = Utf8               ()Lscala/collection/parallel/immutable/ParHashSet;
   #96 = Utf8               ()Lscala/collection/parallel/immutable/ParHashSet<TT;>;
   #97 = Utf8               scala/collection/ArrayOps$
   #98 = Class              #97           // scala/collection/ArrayOps$
   #99 = Utf8               Lscala/collection/ArrayOps$;
  #100 = NameAndType        #36:#99       // MODULE$:Lscala/collection/ArrayOps$;
  #101 = Fieldref           #98.#100      // scala/collection/ArrayOps$.MODULE$:Lscala/collection/ArrayOps$;
  #102 = Utf8               scala/Predef$
  #103 = Class              #102          // scala/Predef$
  #104 = Utf8               Lscala/Predef$;
  #105 = NameAndType        #36:#104      // MODULE$:Lscala/Predef$;
  #106 = Fieldref           #103.#105     // scala/Predef$.MODULE$:Lscala/Predef$;
  #107 = Utf8               [Ljava/lang/Object;
  #108 = Class              #107          // "[Ljava/lang/Object;"
  #109 = Utf8               refArrayOps
  #110 = Utf8               ([Ljava/lang/Object;)Ljava/lang/Object;
  #111 = NameAndType        #109:#110     // refArrayOps:([Ljava/lang/Object;)Ljava/lang/Object;
  #112 = Methodref          #103.#111     // scala/Predef$.refArrayOps:([Ljava/lang/Object;)Ljava/lang/Object;
  #113 = Utf8               (Ljava/lang/Object;)Ljava/lang/Object;
  #114 = MethodType         #113          //  (Ljava/lang/Object;)Ljava/lang/Object;
  #115 = Utf8               $anonfun$result$1$adapted
  #116 = Utf8               (Lscala/collection/mutable/UnrolledBuffer;)Ljava/lang/Object;
  #117 = NameAndType        #115:#116     // $anonfun$result$1$adapted:(Lscala/collection/mutable/UnrolledBuffer;)Ljava/lang/Object;
  #118 = Methodref          #2.#117       // scala/collection/parallel/immutable/HashSetCombiner.$anonfun$result$1$adapted:(Lscala/collection/mutable/UnrolledBuffer;)Ljava/lang/Object;
  #119 = MethodHandle       6:#118        // REF_invokeStatic scala/collection/parallel/immutable/HashSetCombiner.$anonfun$result$1$adapted:(Lscala/collection/mutable/UnrolledBuffer;)Ljava/lang/Object;
  #120 = MethodType         #116          //  (Lscala/collection/mutable/UnrolledBuffer;)Ljava/lang/Object;
  #121 = Integer            5
  #122 = Integer            1
  #123 = Utf8               java/lang/invoke/LambdaMetafactory
  #124 = Class              #123          // java/lang/invoke/LambdaMetafactory
  #125 = Utf8               altMetafactory
  #126 = Utf8               (Ljava/lang/invoke/MethodHandles$Lookup;Ljava/lang/String;Ljava/lang/invoke/MethodType;[Ljava/lang/Object;)Ljava/lang/invoke/CallSite;
  #127 = NameAndType        #125:#126     // altMetafactory:(Ljava/lang/invoke/MethodHandles$Lookup;Ljava/lang/String;Ljava/lang/invoke/MethodType;[Ljava/lang/Object;)Ljava/lang/invoke/CallSite;
  #128 = Methodref          #124.#127     // java/lang/invoke/LambdaMetafactory.altMetafactory:(Ljava/lang/invoke/MethodHandles$Lookup;Ljava/lang/String;Ljava/lang/invoke/MethodType;[Ljava/lang/Object;)Ljava/lang/invoke/CallSite;
  #129 = MethodHandle       6:#128        // REF_invokeStatic java/lang/invoke/LambdaMetafactory.altMetafactory:(Ljava/lang/invoke/MethodHandles$Lookup;Ljava/lang/String;Ljava/lang/invoke/MethodType;[Ljava/lang/Object;)Ljava/lang/invoke/CallSite;
  #130 = Utf8               ()Lscala/Function1;
  #131 = NameAndType        #31:#130      // apply:()Lscala/Function1;
  #132 = InvokeDynamic      #0:#131       // #0:apply:()Lscala/Function1;
  #133 = Utf8               filter$extension
  #134 = Utf8               (Ljava/lang/Object;Lscala/Function1;)Ljava/lang/Object;
  #135 = NameAndType        #133:#134     // filter$extension:(Ljava/lang/Object;Lscala/Function1;)Ljava/lang/Object;
  #136 = Methodref          #98.#135      // scala/collection/ArrayOps$.filter$extension:(Ljava/lang/Object;Lscala/Function1;)Ljava/lang/Object;
  #137 = Utf8               $anonfun$result$2
  #138 = Utf8               (Lscala/collection/mutable/UnrolledBuffer;)Lscala/collection/mutable/UnrolledBuffer$Unrolled;
  #139 = NameAndType        #137:#138     // $anonfun$result$2:(Lscala/collection/mutable/UnrolledBuffer;)Lscala/collection/mutable/UnrolledBuffer$Unrolled;
  #140 = Methodref          #2.#139       // scala/collection/parallel/immutable/HashSetCombiner.$anonfun$result$2:(Lscala/collection/mutable/UnrolledBuffer;)Lscala/collection/mutable/UnrolledBuffer$Unrolled;
  #141 = MethodHandle       6:#140        // REF_invokeStatic scala/collection/parallel/immutable/HashSetCombiner.$anonfun$result$2:(Lscala/collection/mutable/UnrolledBuffer;)Lscala/collection/mutable/UnrolledBuffer$Unrolled;
  #142 = MethodType         #138          //  (Lscala/collection/mutable/UnrolledBuffer;)Lscala/collection/mutable/UnrolledBuffer$Unrolled;
  #143 = InvokeDynamic      #1:#131       // #1:apply:()Lscala/Function1;
  #144 = Utf8               (Ljava/lang/Class;)Lscala/reflect/ClassTag;
  #145 = NameAndType        #31:#144      // apply:(Ljava/lang/Class;)Lscala/reflect/ClassTag;
  #146 = Methodref          #74.#145      // scala/reflect/ClassTag$.apply:(Ljava/lang/Class;)Lscala/reflect/ClassTag;
  #147 = Utf8               map$extension
  #148 = Utf8               (Ljava/lang/Object;Lscala/Function1;Lscala/reflect/ClassTag;)Ljava/lang/Object;
  #149 = NameAndType        #147:#148     // map$extension:(Ljava/lang/Object;Lscala/Function1;Lscala/reflect/ClassTag;)Ljava/lang/Object;
  #150 = Methodref          #98.#149      // scala/collection/ArrayOps$.map$extension:(Ljava/lang/Object;Lscala/Function1;Lscala/reflect/ClassTag;)Ljava/lang/Object;
  #151 = Utf8               [Lscala/collection/mutable/UnrolledBuffer$Unrolled;
  #152 = Class              #151          // "[Lscala/collection/mutable/UnrolledBuffer$Unrolled;"
  #153 = Utf8               combinerTaskSupport
  #154 = Utf8               ()Lscala/collection/parallel/TaskSupport;
  #155 = NameAndType        #153:#154     // combinerTaskSupport:()Lscala/collection/parallel/TaskSupport;
  #156 = Methodref          #2.#155       // scala/collection/parallel/immutable/HashSetCombiner.combinerTaskSupport:()Lscala/collection/parallel/TaskSupport;
  #157 = Utf8               (Lscala/collection/parallel/immutable/HashSetCombiner;[Lscala/collection/mutable/UnrolledBuffer$Unrolled;[Lscala/collection/immutable/OldHashSet;II)V
  #158 = NameAndType        #82:#157      // "<init>":(Lscala/collection/parallel/immutable/HashSetCombiner;[Lscala/collection/mutable/UnrolledBuffer$Unrolled;[Lscala/collection/immutable/OldHashSet;II)V
  #159 = Methodref          #26.#158      // scala/collection/parallel/immutable/HashSetCombiner$CreateTrie."<init>":(Lscala/collection/parallel/immutable/HashSetCombiner;[Lscala/collection/mutable/UnrolledBuffer$Unrolled;[Lscala/collection/immutable/OldHashSet;II)V
  #160 = Utf8               scala/collection/parallel/TaskSupport
  #161 = Class              #160          // scala/collection/parallel/TaskSupport
  #162 = Utf8               executeAndWaitResult
  #163 = Utf8               (Lscala/collection/parallel/Task;)Ljava/lang/Object;
  #164 = NameAndType        #162:#163     // executeAndWaitResult:(Lscala/collection/parallel/Task;)Ljava/lang/Object;
  #165 = InterfaceMethodref #161.#164     // scala/collection/parallel/TaskSupport.executeAndWaitResult:(Lscala/collection/parallel/Task;)Ljava/lang/Object;
  #166 = Utf8               rootsize
  #167 = NameAndType        #166:#53      // rootsize:()I
  #168 = Methodref          #35.#167      // scala/collection/parallel/immutable/HashSetCombiner$.rootsize:()I
  #169 = Utf8               scala/runtime/BoxesRunTime
  #170 = Class              #169          // scala/runtime/BoxesRunTime
  #171 = Utf8               boxToInteger
  #172 = Utf8               (I)Ljava/lang/Integer;
  #173 = NameAndType        #171:#172     // boxToInteger:(I)Ljava/lang/Integer;
  #174 = Methodref          #170.#173     // scala/runtime/BoxesRunTime.boxToInteger:(I)Ljava/lang/Integer;
  #175 = Utf8               (Ljava/lang/Object;Ljava/lang/Object;)Ljava/lang/Object;
  #176 = MethodType         #175          //  (Ljava/lang/Object;Ljava/lang/Object;)Ljava/lang/Object;
  #177 = Utf8               $anonfun$result$3$adapted
  #178 = Utf8               (Ljava/lang/Object;Lscala/collection/immutable/OldHashSet;)Ljava/lang/Object;
  #179 = NameAndType        #177:#178     // $anonfun$result$3$adapted:(Ljava/lang/Object;Lscala/collection/immutable/OldHashSet;)Ljava/lang/Object;
  #180 = Methodref          #2.#179       // scala/collection/parallel/immutable/HashSetCombiner.$anonfun$result$3$adapted:(Ljava/lang/Object;Lscala/collection/immutable/OldHashSet;)Ljava/lang/Object;
  #181 = MethodHandle       6:#180        // REF_invokeStatic scala/collection/parallel/immutable/HashSetCombiner.$anonfun$result$3$adapted:(Ljava/lang/Object;Lscala/collection/immutable/OldHashSet;)Ljava/lang/Object;
  #182 = MethodType         #178          //  (Ljava/lang/Object;Lscala/collection/immutable/OldHashSet;)Ljava/lang/Object;
  #183 = Utf8               ()Lscala/Function2;
  #184 = NameAndType        #31:#183      // apply:()Lscala/Function2;
  #185 = InvokeDynamic      #2:#184       // #2:apply:()Lscala/Function2;
  #186 = Utf8               foldLeft$extension
  #187 = Utf8               (Ljava/lang/Object;Ljava/lang/Object;Lscala/Function2;)Ljava/lang/Object;
  #188 = NameAndType        #186:#187     // foldLeft$extension:(Ljava/lang/Object;Ljava/lang/Object;Lscala/Function2;)Ljava/lang/Object;
  #189 = Methodref          #98.#188      // scala/collection/ArrayOps$.foldLeft$extension:(Ljava/lang/Object;Ljava/lang/Object;Lscala/Function2;)Ljava/lang/Object;
  #190 = Utf8               unboxToInt
  #191 = NameAndType        #190:#66      // unboxToInt:(Ljava/lang/Object;)I
  #192 = Methodref          #170.#191     // scala/runtime/BoxesRunTime.unboxToInt:(Ljava/lang/Object;)I
  #193 = Utf8               scala/collection/parallel/immutable/ParHashSet
  #194 = Class              #193          // scala/collection/parallel/immutable/ParHashSet
  #195 = Utf8               ()V
  #196 = NameAndType        #82:#195      // "<init>":()V
  #197 = Methodref          #194.#196     // scala/collection/parallel/immutable/ParHashSet."<init>":()V
  #198 = Utf8               (Lscala/collection/immutable/OldHashSet;)V
  #199 = NameAndType        #82:#198      // "<init>":(Lscala/collection/immutable/OldHashSet;)V
  #200 = Methodref          #194.#199     // scala/collection/parallel/immutable/ParHashSet."<init>":(Lscala/collection/immutable/OldHashSet;)V
  #201 = Utf8               (I[Lscala/collection/immutable/OldHashSet;I)V
  #202 = NameAndType        #82:#201      // "<init>":(I[Lscala/collection/immutable/OldHashSet;I)V
  #203 = Methodref          #16.#202      // scala/collection/immutable/OldHashSet$HashTrieSet."<init>":(I[Lscala/collection/immutable/OldHashSet;I)V
  #204 = Utf8               trie
  #205 = Utf8               Lscala/collection/immutable/OldHashSet$HashTrieSet;
  #206 = Utf8               bucks
  #207 = Utf8               root
  #208 = Utf8               [Lscala/collection/immutable/OldHashSet;
  #209 = Utf8               bitmap
  #210 = Utf8               i
  #211 = Class              #208          // "[Lscala/collection/immutable/OldHashSet;"
  #212 = Utf8               ()Ljava/lang/Object;
  #213 = NameAndType        #94:#95       // result:()Lscala/collection/parallel/immutable/ParHashSet;
  #214 = Methodref          #2.#213       // scala/collection/parallel/immutable/HashSetCombiner.result:()Lscala/collection/parallel/immutable/ParHashSet;
  #215 = NameAndType        #48:#49       // addOne:(Ljava/lang/Object;)Lscala/collection/parallel/immutable/HashSetCombiner;
  #216 = Methodref          #2.#215       // scala/collection/parallel/immutable/HashSetCombiner.addOne:(Ljava/lang/Object;)Lscala/collection/parallel/immutable/HashSetCombiner;
  #217 = Utf8               $anonfun$result$1
  #218 = Utf8               (Lscala/collection/mutable/UnrolledBuffer;)Z
  #219 = Utf8               x$3
  #220 = Utf8               Lscala/collection/mutable/UnrolledBuffer;
  #221 = Utf8               x$4
  #222 = Utf8               headPtr
  #223 = Utf8               ()Lscala/collection/mutable/UnrolledBuffer$Unrolled;
  #224 = NameAndType        #222:#223     // headPtr:()Lscala/collection/mutable/UnrolledBuffer$Unrolled;
  #225 = Methodref          #23.#224      // scala/collection/mutable/UnrolledBuffer.headPtr:()Lscala/collection/mutable/UnrolledBuffer$Unrolled;
  #226 = Utf8               $anonfun$result$3
  #227 = Utf8               (ILscala/collection/immutable/OldHashSet;)I
  #228 = Utf8               x$5
  #229 = Utf8               x$6
  #230 = Utf8               size
  #231 = NameAndType        #230:#53      // size:()I
  #232 = Methodref          #18.#231      // scala/collection/immutable/OldHashSet.size:()I
  #233 = NameAndType        #82:#57       // "<init>":(I)V
  #234 = Methodref          #5.#233       // scala/collection/parallel/BucketCombiner."<init>":(I)V
  #235 = Utf8               scala/collection/immutable/OldHashSet$
  #236 = Class              #235          // scala/collection/immutable/OldHashSet$
  #237 = Utf8               Lscala/collection/immutable/OldHashSet$;
  #238 = NameAndType        #36:#237      // MODULE$:Lscala/collection/immutable/OldHashSet$;
  #239 = Fieldref           #236.#238     // scala/collection/immutable/OldHashSet$.MODULE$:Lscala/collection/immutable/OldHashSet$;
  #240 = Utf8               empty
  #241 = NameAndType        #240:#42      // empty:()Lscala/collection/immutable/OldHashSet;
  #242 = Methodref          #236.#241     // scala/collection/immutable/OldHashSet$.empty:()Lscala/collection/immutable/OldHashSet;
  #243 = NameAndType        #217:#218     // $anonfun$result$1:(Lscala/collection/mutable/UnrolledBuffer;)Z
  #244 = Methodref          #2.#243       // scala/collection/parallel/immutable/HashSetCombiner.$anonfun$result$1:(Lscala/collection/mutable/UnrolledBuffer;)Z
  #245 = Utf8               boxToBoolean
  #246 = Utf8               (Z)Ljava/lang/Boolean;
  #247 = NameAndType        #245:#246     // boxToBoolean:(Z)Ljava/lang/Boolean;
  #248 = Methodref          #170.#247     // scala/runtime/BoxesRunTime.boxToBoolean:(Z)Ljava/lang/Boolean;
  #249 = NameAndType        #226:#227     // $anonfun$result$3:(ILscala/collection/immutable/OldHashSet;)I
  #250 = Methodref          #2.#249       // scala/collection/parallel/immutable/HashSetCombiner.$anonfun$result$3:(ILscala/collection/immutable/OldHashSet;)I
  #251 = Utf8               $deserializeLambda$
  #252 = Utf8               (Ljava/lang/invoke/SerializedLambda;)Ljava/lang/Object;
  #253 = Utf8               scala/runtime/LambdaDeserialize
  #254 = Class              #253          // scala/runtime/LambdaDeserialize
  #255 = Utf8               bootstrap
  #256 = Utf8               (Ljava/lang/invoke/MethodHandles$Lookup;Ljava/lang/String;Ljava/lang/invoke/MethodType;[Ljava/lang/invoke/MethodHandle;)Ljava/lang/invoke/CallSite;
  #257 = NameAndType        #255:#256     // bootstrap:(Ljava/lang/invoke/MethodHandles$Lookup;Ljava/lang/String;Ljava/lang/invoke/MethodType;[Ljava/lang/invoke/MethodHandle;)Ljava/lang/invoke/CallSite;
  #258 = Methodref          #254.#257     // scala/runtime/LambdaDeserialize.bootstrap:(Ljava/lang/invoke/MethodHandles$Lookup;Ljava/lang/String;Ljava/lang/invoke/MethodType;[Ljava/lang/invoke/MethodHandle;)Ljava/lang/invoke/CallSite;
  #259 = MethodHandle       6:#258        // REF_invokeStatic scala/runtime/LambdaDeserialize.bootstrap:(Ljava/lang/invoke/MethodHandles$Lookup;Ljava/lang/String;Ljava/lang/invoke/MethodType;[Ljava/lang/invoke/MethodHandle;)Ljava/lang/invoke/CallSite;
  #260 = Utf8               lambdaDeserialize
  #261 = NameAndType        #260:#252     // lambdaDeserialize:(Ljava/lang/invoke/SerializedLambda;)Ljava/lang/Object;
  #262 = InvokeDynamic      #3:#261       // #3:lambdaDeserialize:(Ljava/lang/invoke/SerializedLambda;)Ljava/lang/Object;
  #263 = Utf8               Signature
  #264 = Utf8               Code
  #265 = Utf8               LineNumberTable
  #266 = Utf8               LocalVariableTable
  #267 = Utf8               StackMapTable
  #268 = Utf8               MethodParameters
  #269 = Utf8               InnerClasses
  #270 = Utf8               SourceFile
  #271 = Utf8               RuntimeVisibleAnnotations
  #272 = Utf8               BootstrapMethods
  #273 = Utf8               ScalaInlineInfo
  #274 = Utf8               ScalaSig
{
  private final scala.collection.immutable.OldHashSet<T> emptyTrie;
    descriptor: Lscala/collection/immutable/OldHashSet;
    flags: (0x0012) ACC_PRIVATE, ACC_FINAL
    Signature: #30                          // Lscala/collection/immutable/OldHashSet<TT;>;

  public static <T extends java.lang.Object> scala.collection.parallel.immutable.HashSetCombiner<T> apply();
    descriptor: ()Lscala/collection/parallel/immutable/HashSetCombiner;
    flags: (0x0009) ACC_PUBLIC, ACC_STATIC
    Code:
      stack=1, locals=0, args_size=0
         0: getstatic     #39                 // Field scala/collection/parallel/immutable/HashSetCombiner$.MODULE$:Lscala/collection/parallel/immutable/HashSetCombiner$;
         3: invokevirtual #41                 // Method scala/collection/parallel/immutable/HashSetCombiner$.apply:()Lscala/collection/parallel/immutable/HashSetCombiner;
         6: areturn
    Signature: #33                          // <T:Ljava/lang/Object;>()Lscala/collection/parallel/immutable/HashSetCombiner<TT;>;

  public scala.collection.immutable.OldHashSet<T> emptyTrie();
    descriptor: ()Lscala/collection/immutable/OldHashSet;
    flags: (0x0001) ACC_PUBLIC
    Code:
      stack=1, locals=1, args_size=1
         0: aload_0
         1: getfield      #45                 // Field emptyTrie:Lscala/collection/immutable/OldHashSet;
         4: areturn
      LineNumberTable:
        line 139: 0
      LocalVariableTable:
        Start  Length  Slot  Name   Signature
            0       5     0  this   Lscala/collection/parallel/immutable/HashSetCombiner;
    Signature: #43                          // ()Lscala/collection/immutable/OldHashSet<TT;>;

  public scala.collection.parallel.immutable.HashSetCombiner<T> addOne(T);
    descriptor: (Ljava/lang/Object;)Lscala/collection/parallel/immutable/HashSetCombiner;
    flags: (0x0001) ACC_PUBLIC
    Code:
      stack=5, locals=4, args_size=2
         0: aload_0
         1: aload_0
         2: invokevirtual #55                 // Method sz:()I
         5: iconst_1
         6: iadd
         7: invokevirtual #59                 // Method sz_$eq:(I)V
        10: getstatic     #64                 // Field scala/collection/Hashing$.MODULE$:Lscala/collection/Hashing$;
        13: aload_1
        14: invokevirtual #68                 // Method scala/collection/Hashing$.computeHash:(Ljava/lang/Object;)I
        17: istore_2
        18: iload_2
        19: bipush        31
        21: iand
        22: istore_3
        23: aload_0
        24: invokevirtual #72                 // Method buckets:()[Lscala/collection/mutable/UnrolledBuffer;
        27: iload_3
        28: aaload
        29: ifnonnull     54
        32: aload_0
        33: invokevirtual #72                 // Method buckets:()[Lscala/collection/mutable/UnrolledBuffer;
        36: iload_3
        37: new           #23                 // class scala/collection/mutable/UnrolledBuffer
        40: dup
        41: getstatic     #77                 // Field scala/reflect/ClassTag$.MODULE$:Lscala/reflect/ClassTag$;
        44: invokevirtual #81                 // Method scala/reflect/ClassTag$.Any:()Lscala/reflect/ClassTag;
        47: invokespecial #85                 // Method scala/collection/mutable/UnrolledBuffer."<init>":(Lscala/reflect/ClassTag;)V
        50: aastore
        51: goto          54
        54: aload_0
        55: invokevirtual #72                 // Method buckets:()[Lscala/collection/mutable/UnrolledBuffer;
        58: iload_3
        59: aaload
        60: aload_1
        61: invokevirtual #89                 // Method scala/collection/mutable/UnrolledBuffer.$plus$eq:(Ljava/lang/Object;)Lscala/collection/mutable/Growable;
        64: pop
        65: aload_0
        66: areturn
      StackMapTable: number_of_entries = 1
        frame_type = 253 /* append */
          offset_delta = 54
          locals = [ int, int ]
      LineNumberTable:
        line 142: 0
        line 143: 10
        line 144: 18
        line 145: 23
        line 147: 32
        line 150: 54
        line 151: 65
      LocalVariableTable:
        Start  Length  Slot  Name   Signature
           18      48     2    hc   I
           23      43     3   pos   I
            0      67     0  this   Lscala/collection/parallel/immutable/HashSetCombiner;
            0      67     1  elem   Ljava/lang/Object;
    Signature: #50                          // (TT;)Lscala/collection/parallel/immutable/HashSetCombiner<TT;>;
    MethodParameters:
      Name                           Flags
      elem                           final

  public scala.collection.parallel.immutable.ParHashSet<T> result();
    descriptor: ()Lscala/collection/parallel/immutable/ParHashSet;
    flags: (0x0001) ACC_PUBLIC
    Code:
      stack=8, locals=7, args_size=1
         0: getstatic     #101                // Field scala/collection/ArrayOps$.MODULE$:Lscala/collection/ArrayOps$;
         3: getstatic     #106                // Field scala/Predef$.MODULE$:Lscala/Predef$;
         6: getstatic     #101                // Field scala/collection/ArrayOps$.MODULE$:Lscala/collection/ArrayOps$;
         9: getstatic     #106                // Field scala/Predef$.MODULE$:Lscala/Predef$;
        12: aload_0
        13: invokevirtual #72                 // Method buckets:()[Lscala/collection/mutable/UnrolledBuffer;
        16: checkcast     #108                // class "[Ljava/lang/Object;"
        19: invokevirtual #112                // Method scala/Predef$.refArrayOps:([Ljava/lang/Object;)Ljava/lang/Object;
        22: invokedynamic #132,  0            // InvokeDynamic #0:apply:()Lscala/Function1;
        27: invokevirtual #136                // Method scala/collection/ArrayOps$.filter$extension:(Ljava/lang/Object;Lscala/Function1;)Ljava/lang/Object;
        30: checkcast     #108                // class "[Ljava/lang/Object;"
        33: invokevirtual #112                // Method scala/Predef$.refArrayOps:([Ljava/lang/Object;)Ljava/lang/Object;
        36: invokedynamic #143,  0            // InvokeDynamic #1:apply:()Lscala/Function1;
        41: getstatic     #77                 // Field scala/reflect/ClassTag$.MODULE$:Lscala/reflect/ClassTag$;
        44: ldc           #21                 // class scala/collection/mutable/UnrolledBuffer$Unrolled
        46: invokevirtual #146                // Method scala/reflect/ClassTag$.apply:(Ljava/lang/Class;)Lscala/reflect/ClassTag;
        49: invokevirtual #150                // Method scala/collection/ArrayOps$.map$extension:(Ljava/lang/Object;Lscala/Function1;Lscala/reflect/ClassTag;)Ljava/lang/Object;
        52: checkcast     #152                // class "[Lscala/collection/mutable/UnrolledBuffer$Unrolled;"
        55: astore_1
        56: aload_1
        57: arraylength
        58: anewarray     #18                 // class scala/collection/immutable/OldHashSet
        61: astore_2
        62: aload_0
        63: invokevirtual #156                // Method combinerTaskSupport:()Lscala/collection/parallel/TaskSupport;
        66: new           #26                 // class scala/collection/parallel/immutable/HashSetCombiner$CreateTrie
        69: dup
        70: aload_0
        71: aload_1
        72: aload_2
        73: iconst_0
        74: aload_1
        75: arraylength
        76: invokespecial #159                // Method scala/collection/parallel/immutable/HashSetCombiner$CreateTrie."<init>":(Lscala/collection/parallel/immutable/HashSetCombiner;[Lscala/collection/mutable/UnrolledBuffer$Unrolled;[Lscala/collection/immutable/OldHashSet;II)V
        79: invokeinterface #165,  2          // InterfaceMethod scala/collection/parallel/TaskSupport.executeAndWaitResult:(Lscala/collection/parallel/Task;)Ljava/lang/Object;
        84: pop
        85: iconst_0
        86: istore_3
        87: iconst_0
        88: istore        4
        90: iload         4
        92: getstatic     #39                 // Field scala/collection/parallel/immutable/HashSetCombiner$.MODULE$:Lscala/collection/parallel/immutable/HashSetCombiner$;
        95: invokevirtual #168                // Method scala/collection/parallel/immutable/HashSetCombiner$.rootsize:()I
        98: if_icmpge     130
       101: aload_0
       102: invokevirtual #72                 // Method buckets:()[Lscala/collection/mutable/UnrolledBuffer;
       105: iload         4
       107: aaload
       108: ifnull        121
       111: iload_3
       112: iconst_1
       113: iload         4
       115: ishl
       116: ior
       117: istore_3
       118: goto          121
       121: iload         4
       123: iconst_1
       124: iadd
       125: istore        4
       127: goto          90
       130: getstatic     #101                // Field scala/collection/ArrayOps$.MODULE$:Lscala/collection/ArrayOps$;
       133: getstatic     #106                // Field scala/Predef$.MODULE$:Lscala/Predef$;
       136: aload_2
       137: checkcast     #108                // class "[Ljava/lang/Object;"
       140: invokevirtual #112                // Method scala/Predef$.refArrayOps:([Ljava/lang/Object;)Ljava/lang/Object;
       143: iconst_0
       144: invokestatic  #174                // Method scala/runtime/BoxesRunTime.boxToInteger:(I)Ljava/lang/Integer;
       147: invokedynamic #185,  0            // InvokeDynamic #2:apply:()Lscala/Function2;
       152: invokevirtual #189                // Method scala/collection/ArrayOps$.foldLeft$extension:(Ljava/lang/Object;Ljava/lang/Object;Lscala/Function2;)Ljava/lang/Object;
       155: invokestatic  #192                // Method scala/runtime/BoxesRunTime.unboxToInt:(Ljava/lang/Object;)I
       158: istore        5
       160: iload         5
       162: iconst_0
       163: if_icmpne     176
       166: new           #194                // class scala/collection/parallel/immutable/ParHashSet
       169: dup
       170: invokespecial #197                // Method scala/collection/parallel/immutable/ParHashSet."<init>":()V
       173: goto          217
       176: iload         5
       178: iconst_1
       179: if_icmpne     195
       182: new           #194                // class scala/collection/parallel/immutable/ParHashSet
       185: dup
       186: aload_2
       187: iconst_0
       188: aaload
       189: invokespecial #200                // Method scala/collection/parallel/immutable/ParHashSet."<init>":(Lscala/collection/immutable/OldHashSet;)V
       192: goto          217
       195: new           #16                 // class scala/collection/immutable/OldHashSet$HashTrieSet
       198: dup
       199: iload_3
       200: aload_2
       201: iload         5
       203: invokespecial #203                // Method scala/collection/immutable/OldHashSet$HashTrieSet."<init>":(I[Lscala/collection/immutable/OldHashSet;I)V
       206: astore        6
       208: new           #194                // class scala/collection/parallel/immutable/ParHashSet
       211: dup
       212: aload         6
       214: invokespecial #200                // Method scala/collection/parallel/immutable/ParHashSet."<init>":(Lscala/collection/immutable/OldHashSet;)V
       217: areturn
      StackMapTable: number_of_entries = 6
        frame_type = 255 /* full_frame */
          offset_delta = 90
          locals = [ class scala/collection/parallel/immutable/HashSetCombiner, class "[Lscala/collection/mutable/UnrolledBuffer$Unrolled;", class "[Lscala/collection/immutable/OldHashSet;", int, int ]
          stack = []
        frame_type = 30 /* same */
        frame_type = 8 /* same */
        frame_type = 252 /* append */
          offset_delta = 45
          locals = [ int ]
        frame_type = 18 /* same */
        frame_type = 85 /* same_locals_1_stack_item */
          stack = [ class scala/collection/parallel/immutable/ParHashSet ]
      LineNumberTable:
        line 155: 0
        line 156: 56
        line 158: 62
        line 160: 85
        line 161: 87
        line 162: 90
        line 163: 101
        line 164: 121
        line 162: 127
        line 166: 130
        line 168: 160
        line 169: 176
        line 171: 195
        line 172: 208
      LocalVariableTable:
        Start  Length  Slot  Name   Signature
          208       9     6  trie   Lscala/collection/immutable/OldHashSet$HashTrieSet;
           56     161     1 bucks   [Lscala/collection/mutable/UnrolledBuffer$Unrolled;
           62     155     2  root   [Lscala/collection/immutable/OldHashSet;
           87     130     3 bitmap   I
           90     127     4     i   I
          160      57     5    sz   I
            0     218     0  this   Lscala/collection/parallel/immutable/HashSetCombiner;
    Signature: #96                          // ()Lscala/collection/parallel/immutable/ParHashSet<TT;>;

  public java.lang.Object result();
    descriptor: ()Ljava/lang/Object;
    flags: (0x1041) ACC_PUBLIC, ACC_BRIDGE, ACC_SYNTHETIC
    Code:
      stack=1, locals=1, args_size=1
         0: aload_0
         1: invokevirtual #214                // Method result:()Lscala/collection/parallel/immutable/ParHashSet;
         4: areturn
      LineNumberTable:
        line 135: 0
      LocalVariableTable:
        Start  Length  Slot  Name   Signature
            0       5     0  this   Lscala/collection/parallel/immutable/HashSetCombiner;

  public scala.collection.mutable.Growable addOne(java.lang.Object);
    descriptor: (Ljava/lang/Object;)Lscala/collection/mutable/Growable;
    flags: (0x1041) ACC_PUBLIC, ACC_BRIDGE, ACC_SYNTHETIC
    Code:
      stack=2, locals=2, args_size=2
         0: aload_0
         1: aload_1
         2: invokevirtual #216                // Method addOne:(Ljava/lang/Object;)Lscala/collection/parallel/immutable/HashSetCombiner;
         5: areturn
      LineNumberTable:
        line 135: 0
      LocalVariableTable:
        Start  Length  Slot  Name   Signature
            0       6     0  this   Lscala/collection/parallel/immutable/HashSetCombiner;
            0       6     1  elem   Ljava/lang/Object;
    MethodParameters:
      Name                           Flags
      elem                           final

  public static final boolean $anonfun$result$1(scala.collection.mutable.UnrolledBuffer);
    descriptor: (Lscala/collection/mutable/UnrolledBuffer;)Z
    flags: (0x1019) ACC_PUBLIC, ACC_STATIC, ACC_FINAL, ACC_SYNTHETIC
    Code:
      stack=1, locals=1, args_size=1
         0: aload_0
         1: ifnull        8
         4: iconst_1
         5: goto          9
         8: iconst_0
         9: ireturn
      StackMapTable: number_of_entries = 2
        frame_type = 8 /* same */
        frame_type = 64 /* same_locals_1_stack_item */
          stack = [ int ]
      LineNumberTable:
        line 155: 0
      LocalVariableTable:
        Start  Length  Slot  Name   Signature
            0      10     0   x$3   Lscala/collection/mutable/UnrolledBuffer;
    MethodParameters:
      Name                           Flags
      x$3                            final

  public static final scala.collection.mutable.UnrolledBuffer$Unrolled $anonfun$result$2(scala.collection.mutable.UnrolledBuffer);
    descriptor: (Lscala/collection/mutable/UnrolledBuffer;)Lscala/collection/mutable/UnrolledBuffer$Unrolled;
    flags: (0x1019) ACC_PUBLIC, ACC_STATIC, ACC_FINAL, ACC_SYNTHETIC
    Code:
      stack=1, locals=1, args_size=1
         0: aload_0
         1: invokevirtual #225                // Method scala/collection/mutable/UnrolledBuffer.headPtr:()Lscala/collection/mutable/UnrolledBuffer$Unrolled;
         4: areturn
      LineNumberTable:
        line 155: 0
      LocalVariableTable:
        Start  Length  Slot  Name   Signature
            0       5     0   x$4   Lscala/collection/mutable/UnrolledBuffer;
    MethodParameters:
      Name                           Flags
      x$4                            final

  public static final int $anonfun$result$3(int, scala.collection.immutable.OldHashSet);
    descriptor: (ILscala/collection/immutable/OldHashSet;)I
    flags: (0x1019) ACC_PUBLIC, ACC_STATIC, ACC_FINAL, ACC_SYNTHETIC
    Code:
      stack=2, locals=2, args_size=2
         0: iload_0
         1: aload_1
         2: invokevirtual #232                // Method scala/collection/immutable/OldHashSet.size:()I
         5: iadd
         6: ireturn
      LineNumberTable:
        line 166: 0
      LocalVariableTable:
        Start  Length  Slot  Name   Signature
            0       7     0   x$5   I
            0       7     1   x$6   Lscala/collection/immutable/OldHashSet;
    MethodParameters:
      Name                           Flags
      x$5                            final
      x$6                            final

  public scala.collection.parallel.immutable.HashSetCombiner();
    descriptor: ()V
    flags: (0x0001) ACC_PUBLIC
    Code:
      stack=2, locals=1, args_size=1
         0: aload_0
         1: getstatic     #39                 // Field scala/collection/parallel/immutable/HashSetCombiner$.MODULE$:Lscala/collection/parallel/immutable/HashSetCombiner$;
         4: invokevirtual #168                // Method scala/collection/parallel/immutable/HashSetCombiner$.rootsize:()I
         7: invokespecial #234                // Method scala/collection/parallel/BucketCombiner."<init>":(I)V
        10: aload_0
        11: getstatic     #239                // Field scala/collection/immutable/OldHashSet$.MODULE$:Lscala/collection/immutable/OldHashSet$;
        14: invokevirtual #242                // Method scala/collection/immutable/OldHashSet$.empty:()Lscala/collection/immutable/OldHashSet;
        17: putfield      #45                 // Field emptyTrie:Lscala/collection/immutable/OldHashSet;
        20: return
      LineNumberTable:
        line 136: 0
        line 139: 10
        line 136: 20
      LocalVariableTable:
        Start  Length  Slot  Name   Signature
            0      21     0  this   Lscala/collection/parallel/immutable/HashSetCombiner;

  public static final java.lang.Object $anonfun$result$1$adapted(scala.collection.mutable.UnrolledBuffer);
    descriptor: (Lscala/collection/mutable/UnrolledBuffer;)Ljava/lang/Object;
    flags: (0x1019) ACC_PUBLIC, ACC_STATIC, ACC_FINAL, ACC_SYNTHETIC
    Code:
      stack=1, locals=1, args_size=1
         0: aload_0
         1: invokestatic  #244                // Method $anonfun$result$1:(Lscala/collection/mutable/UnrolledBuffer;)Z
         4: invokestatic  #248                // Method scala/runtime/BoxesRunTime.boxToBoolean:(Z)Ljava/lang/Boolean;
         7: areturn
      LineNumberTable:
        line 155: 0
      LocalVariableTable:
        Start  Length  Slot  Name   Signature
            0       8     0   x$3   Lscala/collection/mutable/UnrolledBuffer;
    MethodParameters:
      Name                           Flags
      x$3                            final

  public static final java.lang.Object $anonfun$result$3$adapted(java.lang.Object, scala.collection.immutable.OldHashSet);
    descriptor: (Ljava/lang/Object;Lscala/collection/immutable/OldHashSet;)Ljava/lang/Object;
    flags: (0x1019) ACC_PUBLIC, ACC_STATIC, ACC_FINAL, ACC_SYNTHETIC
    Code:
      stack=2, locals=2, args_size=2
         0: aload_0
         1: invokestatic  #192                // Method scala/runtime/BoxesRunTime.unboxToInt:(Ljava/lang/Object;)I
         4: aload_1
         5: invokestatic  #250                // Method $anonfun$result$3:(ILscala/collection/immutable/OldHashSet;)I
         8: invokestatic  #174                // Method scala/runtime/BoxesRunTime.boxToInteger:(I)Ljava/lang/Integer;
        11: areturn
      LineNumberTable:
        line 166: 0
      LocalVariableTable:
        Start  Length  Slot  Name   Signature
            0      12     0   x$5   Ljava/lang/Object;
            0      12     1   x$6   Lscala/collection/immutable/OldHashSet;
    MethodParameters:
      Name                           Flags
      x$5                            final
      x$6                            final

  private static java.lang.Object $deserializeLambda$(java.lang.invoke.SerializedLambda);
    descriptor: (Ljava/lang/invoke/SerializedLambda;)Ljava/lang/Object;
    flags: (0x100a) ACC_PRIVATE, ACC_STATIC, ACC_SYNTHETIC
    Code:
      stack=1, locals=1, args_size=1
         0: aload_0
         1: invokedynamic #262,  0            // InvokeDynamic #3:lambdaDeserialize:(Ljava/lang/invoke/SerializedLambda;)Ljava/lang/Object;
         6: areturn
}
InnerClasses:
  public static final #14= #11 of #13;    // Lookup=class java/lang/invoke/MethodHandles$Lookup of class java/lang/invoke/MethodHandles
  public static final #19= #16 of #18;    // HashTrieSet=class scala/collection/immutable/OldHashSet$HashTrieSet of class scala/collection/immutable/OldHashSet
  public static #24= #21 of #23;          // Unrolled=class scala/collection/mutable/UnrolledBuffer$Unrolled of class scala/collection/mutable/UnrolledBuffer
  public #27= #26 of #2;                  // CreateTrie=class scala/collection/parallel/immutable/HashSetCombiner$CreateTrie of class scala/collection/parallel/immutable/HashSetCombiner
Signature: #3                           // <T:Ljava/lang/Object;>Lscala/collection/parallel/BucketCombiner<TT;Lscala/collection/parallel/immutable/ParHashSet<TT;>;Ljava/lang/Object;Lscala/collection/parallel/immutable/HashSetCombiner<TT;>;>;
SourceFile: "ParHashSet.scala"
RuntimeVisibleAnnotations:
  0: #7(#8=s#9)
    scala.reflect.ScalaSignature(
      bytes="\u0006\u0005\u0005-cAB\u000e\u001d\u0003\u0003aB\u0005C\u0003=\u0001\u0011\u0005Q\bC\u0004?\u0001\t\u0007I\u0011A \t\r\u0015\u0003\u0001\u0015!\u0003A\u0011\u00151\u0005\u0001\"\u0001H\u0011\u0015Y\u0005\u0001\"\u0001M\r\u0011i\u0005\u0001\u0001(\t\u0011e3!\u0011!Q\u0001\niC\u0001b\u001c\u0004\u0003\u0002\u0003\u0006I\u0001\u001d\u0005\tc\u001a\u0011\t\u0011)A\u0005e\"AQO\u0002B\u0001B\u0003%!\u000fC\u0003=\r\u0011\u0005a\u000fC\u0004L\r\u0001\u0007I\u0011A>\t\u000fq4\u0001\u0019!C\u0001{\"9\u0011\u0011\u0001\u0004!B\u0013)\u0006bBA\u0002\r\u0011\u0005\u0011Q\u0001\u0005\b\u0003#1A\u0011BA\n\u0011\u001d\tIB\u0002C\u0001\u00037Aq!a\t\u0007\t\u0003\t)cB\u0004\u0002.qA\t!a\f\u0007\rma\u0002\u0012AA\u0019\u0011\u0019aD\u0003\"\u0001\u00024!9\u0011Q\u0007\u000b\u0005\u0002\u0005]\u0002BCA!)\t\u0007I\u0011\u0001\u000f\u0002D!9\u0011Q\t\u000b!\u0002\u0013\u0011\bBCA$)\t\u0007I\u0011\u0001\u000f\u0002D!9\u0011\u0011\n\u000b!\u0002\u0013\u0011(a\u0004%bg\"\u001cV\r^\"p[\nLg.\u001a:\u000b\u0005uq\u0012!C5n[V$\u0018M\u00197f\u0015\ty\u0002%\u0001\u0005qCJ\fG\u000e\\3m\u0015\t\t#%\u0001\u0006d_2dWm\u0019;j_:T\u0011aI\u0001\u0006g\u000e\fG.Y\u000b\u0003K1\u001a\"\u0001\u0001\u0014\u0011\r\u001dB#f\u000e\u001b<\u001b\u0005q\u0012BA\u0015\u001f\u00059\u0011UoY6fi\u000e{WNY5oKJ\u0004\"a\u000b\u0017\r\u0001\u0011)Q\u0006\u0001b\u0001_\t\tAk\u0001\u0001\u0012\u0005A\"\u0004CA\u00193\u001b\u0005\u0011\u0013BA\u001a#\u0005\u001dqu\u000e\u001e5j]\u001e\u0004\"!M\u001b\n\u0005Y\u0012#aA!osB\u0019\u0001(\u000f\u0016\u000e\u0003qI!A\u000f\u000f\u0003\u0015A\u000b\'\u000fS1tQN+G\u000fE\u00029\u0001)\na\u0001P5oSRtD#A\u001e\u0002\u0013\u0015l\u0007\u000f^=Ue&,W#\u0001!\u0011\u0007\u0005\u001b%&D\u0001C\u0015\ti\u0002%\u0003\u0002E\u0005\nQq\n\u001c3ICND7+\u001a;\u0002\u0015\u0015l\u0007\u000f^=Ue&,\u0007%\u0001\u0004bI\u0012|e.\u001a\u000b\u0003\u0011&k\u0011\u0001\u0001\u0005\u0006\u0015\u0012\u0001\rAK\u0001\u0005K2,W.\u0001\u0004sKN,H\u000e\u001e\u000b\u0002o\tQ1I]3bi\u0016$&/[3\u0014\u0007\u0019y%\u000b\u0005\u00022!&\u0011\u0011K\t\u0002\u0007\u0003:L(+\u001a4\u0011\t\u001d\u001aV\u000bW\u0005\u0003)z\u0011A\u0001V1tWB\u0011\u0011GV\u0005\u0003/\n\u0012A!\u00168jiB\u0011\u0001JB\u0001\u0006EV\u001c7n\u001d\t\u0004cmk\u0016B\u0001/#\u0005\u0015\t%O]1z!\rqF\u000e\u000e\b\u0003?&t!\u0001Y4\u000f\u0005\u00054gB\u00012f\u001b\u0005\u0019\'B\u00013/\u0003\u0019a$o\\8u}%\t1%\u0003\u0002\"E%\u0011\u0001\u000eI\u0001\b[V$\u0018M\u00197f\u0013\tQ7.\u0001\bV]J|G\u000e\\3e\u0005V4g-\u001a:\u000b\u0005!\u0004\u0013BA7o\u0005!)fN]8mY\u0016$\'B\u00016l\u0003\u0011\u0011xn\u001c;\u0011\u0007EZ\u0006)\u0001\u0004pM\u001a\u001cX\r\u001e\t\u0003cML!\u0001\u001e\u0012\u0003\u0007%sG/A\u0004i_^l\u0017M\\=\u0015\u000ba;\b0\u001f>\t\u000be[\u0001\u0019\u0001.\t\u000b=\\\u0001\u0019\u00019\t\u000bE\\\u0001\u0019\u0001:\t\u000bU\\\u0001\u0019\u0001:\u0016\u0003U\u000b!B]3tk2$x\fJ3r)\t)f\u0010C\u0004\u0000\u001b\u0005\u0005\t\u0019A+\u0002\u0007a$\u0013\'A\u0004sKN,H\u000e\u001e\u0011\u0002\t1,\u0017M\u001a\u000b\u0004+\u0006\u001d\u0001bBA\u0005\u001f\u0001\u0007\u00111B\u0001\u0005aJ,g\u000f\u0005\u00032\u0003\u001b)\u0016bAA\bE\t1q\n\u001d;j_:\f!b\u0019:fCR,GK]5f)\r\u0001\u0015Q\u0003\u0005\u0007\u0003/\u0001\u0002\u0019A/\u0002\u000b\u0015dW-\\:\u0002\u000bM\u0004H.\u001b;\u0016\u0005\u0005u\u0001\u0003B!\u0002 aK1!!\tC\u0005\u0011a\u0015n\u001d;\u0002%MDw.\u001e7e\'Bd\u0017\u000e\u001e$veRDWM]\u000b\u0003\u0003O\u00012!MA\u0015\u0013\r\tYC\t\u0002\b\u0005>|G.Z1o\u0003=A\u0015m\u001d5TKR\u001cu.\u001c2j]\u0016\u0014\bC\u0001\u001d\u0015\'\t!r\n\u0006\u0002\u00020\u0005)\u0011\r\u001d9msV!\u0011\u0011HA +\t\tY\u0004\u0005\u00039\u0001\u0005u\u0002cA\u0016\u0002@\u0011)QF\u0006b\u0001_\u0005A!o\\8uE&$8/F\u0001s\u0003%\u0011xn\u001c;cSR\u001c\b%\u0001\u0005s_>$8/\u001b>f\u0003%\u0011xn\u001c;tSj,\u0007\u0005"
    )
BootstrapMethods:
  0: #129 REF_invokeStatic java/lang/invoke/LambdaMetafactory.altMetafactory:(Ljava/lang/invoke/MethodHandles$Lookup;Ljava/lang/String;Ljava/lang/invoke/MethodType;[Ljava/lang/Object;)Ljava/lang/invoke/CallSite;
    Method arguments:
      #114 (Ljava/lang/Object;)Ljava/lang/Object;
      #119 REF_invokeStatic scala/collection/parallel/immutable/HashSetCombiner.$anonfun$result$1$adapted:(Lscala/collection/mutable/UnrolledBuffer;)Ljava/lang/Object;
      #120 (Lscala/collection/mutable/UnrolledBuffer;)Ljava/lang/Object;
      #121 5
      #122 1
      #120 (Lscala/collection/mutable/UnrolledBuffer;)Ljava/lang/Object;
  1: #129 REF_invokeStatic java/lang/invoke/LambdaMetafactory.altMetafactory:(Ljava/lang/invoke/MethodHandles$Lookup;Ljava/lang/String;Ljava/lang/invoke/MethodType;[Ljava/lang/Object;)Ljava/lang/invoke/CallSite;
    Method arguments:
      #114 (Ljava/lang/Object;)Ljava/lang/Object;
      #141 REF_invokeStatic scala/collection/parallel/immutable/HashSetCombiner.$anonfun$result$2:(Lscala/collection/mutable/UnrolledBuffer;)Lscala/collection/mutable/UnrolledBuffer$Unrolled;
      #142 (Lscala/collection/mutable/UnrolledBuffer;)Lscala/collection/mutable/UnrolledBuffer$Unrolled;
      #121 5
      #122 1
      #142 (Lscala/collection/mutable/UnrolledBuffer;)Lscala/collection/mutable/UnrolledBuffer$Unrolled;
  2: #129 REF_invokeStatic java/lang/invoke/LambdaMetafactory.altMetafactory:(Ljava/lang/invoke/MethodHandles$Lookup;Ljava/lang/String;Ljava/lang/invoke/MethodType;[Ljava/lang/Object;)Ljava/lang/invoke/CallSite;
    Method arguments:
      #176 (Ljava/lang/Object;Ljava/lang/Object;)Ljava/lang/Object;
      #181 REF_invokeStatic scala/collection/parallel/immutable/HashSetCombiner.$anonfun$result$3$adapted:(Ljava/lang/Object;Lscala/collection/immutable/OldHashSet;)Ljava/lang/Object;
      #182 (Ljava/lang/Object;Lscala/collection/immutable/OldHashSet;)Ljava/lang/Object;
      #121 5
      #122 1
      #182 (Ljava/lang/Object;Lscala/collection/immutable/OldHashSet;)Ljava/lang/Object;
  3: #259 REF_invokeStatic scala/runtime/LambdaDeserialize.bootstrap:(Ljava/lang/invoke/MethodHandles$Lookup;Ljava/lang/String;Ljava/lang/invoke/MethodType;[Ljava/lang/invoke/MethodHandle;)Ljava/lang/invoke/CallSite;
    Method arguments:
      #119 REF_invokeStatic scala/collection/parallel/immutable/HashSetCombiner.$anonfun$result$1$adapted:(Lscala/collection/mutable/UnrolledBuffer;)Ljava/lang/Object;
      #141 REF_invokeStatic scala/collection/parallel/immutable/HashSetCombiner.$anonfun$result$2:(Lscala/collection/mutable/UnrolledBuffer;)Lscala/collection/mutable/UnrolledBuffer$Unrolled;
      #181 REF_invokeStatic scala/collection/parallel/immutable/HashSetCombiner.$anonfun$result$3$adapted:(Ljava/lang/Object;Lscala/collection/immutable/OldHashSet;)Ljava/lang/Object;
  ScalaInlineInfo: length = 0x3B (unknown attribute)
   01 00 00 0B 00 D9 00 DA 01 00 73 00 74 01 00 89
   00 8A 01 00 E2 00 E3 01 00 B1 00 B2 01 00 52 00
   C3 00 00 30 00 57 00 00 30 00 31 00 00 1C 00 2A
   00 00 5E 00 D4 00 00 5E 00 5F 00
  ScalaSig: length = 0x3 (unknown attribute)
   05 02 00
