Classfile /Users/mw/Projects/slang-braindump/.jar/jar8/assemble/slang-braindump/assemble/content/scala/collection/parallel/immutable/package.class
  Last modified May 29, 2022; size 1039 bytes
  SHA-256 checksum a4e659747a09b6fe65dc8f02a7b47b8a9c71fdde0f4187ee61d198240449f0c9
  Compiled from "package.scala"
public final class scala.collection.parallel.immutable.package
  minor version: 0
  major version: 52
  flags: (0x0031) ACC_PUBLIC, ACC_FINAL, ACC_SUPER
  this_class: #2                          // scala/collection/parallel/immutable/package
  super_class: #4                         // java/lang/Object
  interfaces: 0, fields: 0, methods: 1, attributes: 3
Constant pool:
   #1 = Utf8               scala/collection/parallel/immutable/package
   #2 = Class              #1             // scala/collection/parallel/immutable/package
   #3 = Utf8               java/lang/Object
   #4 = Class              #3             // java/lang/Object
   #5 = Utf8               package.scala
   #6 = Utf8               Lscala/reflect/ScalaSignature;
   #7 = Utf8               bytes
   #8 = Utf8               \u0006\u0005A:Q\u0001B\u0003\t\u000291Q\u0001E\u0003\t\u0002EAQAF\u0001\u0005\u0002]AQ\u0001G\u0001\u0005\u0002e\tq\u0001]1dW\u0006<WM\u0003\u0002\u0007\u000f\u0005I\u0011.\\7vi\u0006\u0014G.\u001a\u0006\u0003\u0011%\t\u0001\u0002]1sC2dW\r\u001c\u0006\u0003\u0015-\t!bY8mY\u0016\u001cG/[8o\u0015\u0005a\u0011!B:dC2\f7\u0001\u0001\t\u0003\u001f\u0005i\u0011!\u0002\u0002\ba\u0006\u001c7.Y4f\'\t\t!\u0003\u0005\u0002\u0014)5\t1\"\u0003\u0002\u0016\u0017\t1\u0011I\\=SK\u001a\fa\u0001P5oSRtD#\u0001\b\u0002\u0015I,\u0007/\u001a;ji&|g.\u0006\u0002\u001bAQ\u00191$K\u0016\u0011\u0007=ab$\u0003\u0002\u001e\u000b\tQ!+\u001a9fi&$\u0018n\u001c8\u0011\u0005}\u0001C\u0002\u0001\u0003\u0006C\r\u0011\rA\t\u0002\u0002)F\u00111E\n\t\u0003\'\u0011J!!J\u0006\u0003\u000f9{G\u000f[5oOB\u00111cJ\u0005\u0003Q-\u00111!\u00118z\u0011\u0015Q3\u00011\u0001\u001f\u0003\u0011)G.Z7\t\u000b1\u001a\u0001\u0019A\u0017\u0002\u00071,g\u000e\u0005\u0002\u0014]%\u0011qf\u0003\u0002\u0004\u0013:$\b
   #9 = Utf8               repetition
  #10 = Utf8               (Ljava/lang/Object;I)Lscala/collection/parallel/immutable/Repetition;
  #11 = Utf8               <T:Ljava/lang/Object;>(TT;I)Lscala/collection/parallel/immutable/Repetition<TT;>;
  #12 = Utf8               elem
  #13 = Utf8               len
  #14 = Utf8               scala/collection/parallel/immutable/package$
  #15 = Class              #14            // scala/collection/parallel/immutable/package$
  #16 = Utf8               MODULE$
  #17 = Utf8               Lscala/collection/parallel/immutable/package$;
  #18 = NameAndType        #16:#17        // MODULE$:Lscala/collection/parallel/immutable/package$;
  #19 = Fieldref           #15.#18        // scala/collection/parallel/immutable/package$.MODULE$:Lscala/collection/parallel/immutable/package$;
  #20 = NameAndType        #9:#10         // repetition:(Ljava/lang/Object;I)Lscala/collection/parallel/immutable/Repetition;
  #21 = Methodref          #15.#20        // scala/collection/parallel/immutable/package$.repetition:(Ljava/lang/Object;I)Lscala/collection/parallel/immutable/Repetition;
  #22 = Utf8               Ljava/lang/Object;
  #23 = Utf8               I
  #24 = Utf8               Code
  #25 = Utf8               LocalVariableTable
  #26 = Utf8               Signature
  #27 = Utf8               MethodParameters
  #28 = Utf8               SourceFile
  #29 = Utf8               RuntimeVisibleAnnotations
  #30 = Utf8               ScalaSig
{
  public static <T extends java.lang.Object> scala.collection.parallel.immutable.Repetition<T> repetition(T, int);
    descriptor: (Ljava/lang/Object;I)Lscala/collection/parallel/immutable/Repetition;
    flags: (0x0009) ACC_PUBLIC, ACC_STATIC
    Code:
      stack=3, locals=2, args_size=2
         0: getstatic     #19                 // Field scala/collection/parallel/immutable/package$.MODULE$:Lscala/collection/parallel/immutable/package$;
         3: aload_0
         4: iload_1
         5: invokevirtual #21                 // Method scala/collection/parallel/immutable/package$.repetition:(Ljava/lang/Object;I)Lscala/collection/parallel/immutable/Repetition;
         8: areturn
      LocalVariableTable:
        Start  Length  Slot  Name   Signature
            0       9     0  elem   Ljava/lang/Object;
            0       9     1   len   I
    Signature: #11                          // <T:Ljava/lang/Object;>(TT;I)Lscala/collection/parallel/immutable/Repetition<TT;>;
    MethodParameters:
      Name                           Flags
      elem                           final
      len                            final
}
SourceFile: "package.scala"
RuntimeVisibleAnnotations:
  0: #6(#7=s#8)
    scala.reflect.ScalaSignature(
      bytes="\u0006\u0005A:Q\u0001B\u0003\t\u000291Q\u0001E\u0003\t\u0002EAQAF\u0001\u0005\u0002]AQ\u0001G\u0001\u0005\u0002e\tq\u0001]1dW\u0006<WM\u0003\u0002\u0007\u000f\u0005I\u0011.\\7vi\u0006\u0014G.\u001a\u0006\u0003\u0011%\t\u0001\u0002]1sC2dW\r\u001c\u0006\u0003\u0015-\t!bY8mY\u0016\u001cG/[8o\u0015\u0005a\u0011!B:dC2\f7\u0001\u0001\t\u0003\u001f\u0005i\u0011!\u0002\u0002\ba\u0006\u001c7.Y4f\'\t\t!\u0003\u0005\u0002\u0014)5\t1\"\u0003\u0002\u0016\u0017\t1\u0011I\\=SK\u001a\fa\u0001P5oSRtD#\u0001\b\u0002\u0015I,\u0007/\u001a;ji&|g.\u0006\u0002\u001bAQ\u00191$K\u0016\u0011\u0007=ab$\u0003\u0002\u001e\u000b\tQ!+\u001a9fi&$\u0018n\u001c8\u0011\u0005}\u0001C\u0002\u0001\u0003\u0006C\r\u0011\rA\t\u0002\u0002)F\u00111E\n\t\u0003\'\u0011J!!J\u0006\u0003\u000f9{G\u000f[5oOB\u00111cJ\u0005\u0003Q-\u00111!\u00118z\u0011\u0015Q3\u00011\u0001\u001f\u0003\u0011)G.Z7\t\u000b1\u001a\u0001\u0019A\u0017\u0002\u00071,g\u000e\u0005\u0002\u0014]%\u0011qf\u0003\u0002\u0004\u0013:$\b"
    )
  ScalaSig: length = 0x3 (unknown attribute)
   05 02 00
