Classfile /Users/mw/Projects/slang-braindump/.jar/jar11/assemble/slang-braindump/assemble/content/org/kohsuke/github/extras/okhttp3/ObsoleteUrlFactory$OkHttpsURLConnection.class
  Last modified May 29, 2022; size 2640 bytes
  SHA-256 checksum fac7b6703b47063442ea7b1575710a7395ac864524c4822dfc3dccd45dbd8048
  Compiled from "ObsoleteUrlFactory.java"
final class org.kohsuke.github.extras.okhttp3.ObsoleteUrlFactory$OkHttpsURLConnection extends org.kohsuke.github.extras.okhttp3.ObsoleteUrlFactory$DelegatingHttpsURLConnection
  minor version: 0
  major version: 52
  flags: (0x0030) ACC_FINAL, ACC_SUPER
  this_class: #21                         // org/kohsuke/github/extras/okhttp3/ObsoleteUrlFactory$OkHttpsURLConnection
  super_class: #22                        // org/kohsuke/github/extras/okhttp3/ObsoleteUrlFactory$DelegatingHttpsURLConnection
  interfaces: 0, fields: 1, methods: 7, attributes: 2
Constant pool:
   #1 = Class              #58            // org/kohsuke/github/extras/okhttp3/ObsoleteUrlFactory$OkHttpURLConnection
   #2 = Methodref          #1.#59         // org/kohsuke/github/extras/okhttp3/ObsoleteUrlFactory$OkHttpURLConnection."<init>":(Ljava/net/URL;Lokhttp3/OkHttpClient;)V
   #3 = Methodref          #21.#60        // org/kohsuke/github/extras/okhttp3/ObsoleteUrlFactory$OkHttpsURLConnection."<init>":(Lorg/kohsuke/github/extras/okhttp3/ObsoleteUrlFactory$OkHttpURLConnection;)V
   #4 = Methodref          #22.#61        // org/kohsuke/github/extras/okhttp3/ObsoleteUrlFactory$DelegatingHttpsURLConnection."<init>":(Ljava/net/HttpURLConnection;)V
   #5 = Fieldref           #21.#62        // org/kohsuke/github/extras/okhttp3/ObsoleteUrlFactory$OkHttpsURLConnection.delegate:Lorg/kohsuke/github/extras/okhttp3/ObsoleteUrlFactory$OkHttpURLConnection;
   #6 = Fieldref           #1.#63         // org/kohsuke/github/extras/okhttp3/ObsoleteUrlFactory$OkHttpURLConnection.call:Lokhttp3/Call;
   #7 = Class              #64            // java/lang/IllegalStateException
   #8 = String             #65            // Connection has not yet been established
   #9 = Methodref          #7.#66         // java/lang/IllegalStateException."<init>":(Ljava/lang/String;)V
  #10 = Fieldref           #1.#67         // org/kohsuke/github/extras/okhttp3/ObsoleteUrlFactory$OkHttpURLConnection.handshake:Lokhttp3/Handshake;
  #11 = Fieldref           #1.#68         // org/kohsuke/github/extras/okhttp3/ObsoleteUrlFactory$OkHttpURLConnection.client:Lokhttp3/OkHttpClient;
  #12 = Methodref          #69.#70        // okhttp3/OkHttpClient.newBuilder:()Lokhttp3/OkHttpClient$Builder;
  #13 = Methodref          #71.#72        // okhttp3/OkHttpClient$Builder.hostnameVerifier:(Ljavax/net/ssl/HostnameVerifier;)Lokhttp3/OkHttpClient$Builder;
  #14 = Methodref          #71.#73        // okhttp3/OkHttpClient$Builder.build:()Lokhttp3/OkHttpClient;
  #15 = Methodref          #69.#74        // okhttp3/OkHttpClient.hostnameVerifier:()Ljavax/net/ssl/HostnameVerifier;
  #16 = Class              #75            // java/lang/IllegalArgumentException
  #17 = String             #76            // sslSocketFactory == null
  #18 = Methodref          #16.#66        // java/lang/IllegalArgumentException."<init>":(Ljava/lang/String;)V
  #19 = Methodref          #71.#77        // okhttp3/OkHttpClient$Builder.sslSocketFactory:(Ljavax/net/ssl/SSLSocketFactory;)Lokhttp3/OkHttpClient$Builder;
  #20 = Methodref          #69.#78        // okhttp3/OkHttpClient.sslSocketFactory:()Ljavax/net/ssl/SSLSocketFactory;
  #21 = Class              #79            // org/kohsuke/github/extras/okhttp3/ObsoleteUrlFactory$OkHttpsURLConnection
  #22 = Class              #80            // org/kohsuke/github/extras/okhttp3/ObsoleteUrlFactory$DelegatingHttpsURLConnection
  #23 = Utf8               delegate
  #24 = Utf8               OkHttpURLConnection
  #25 = Utf8               InnerClasses
  #26 = Utf8               Lorg/kohsuke/github/extras/okhttp3/ObsoleteUrlFactory$OkHttpURLConnection;
  #27 = Utf8               <init>
  #28 = Utf8               (Ljava/net/URL;Lokhttp3/OkHttpClient;)V
  #29 = Utf8               Code
  #30 = Utf8               LineNumberTable
  #31 = Utf8               LocalVariableTable
  #32 = Utf8               this
  #33 = Utf8               OkHttpsURLConnection
  #34 = Utf8               Lorg/kohsuke/github/extras/okhttp3/ObsoleteUrlFactory$OkHttpsURLConnection;
  #35 = Utf8               url
  #36 = Utf8               Ljava/net/URL;
  #37 = Utf8               client
  #38 = Utf8               Lokhttp3/OkHttpClient;
  #39 = Utf8               (Lorg/kohsuke/github/extras/okhttp3/ObsoleteUrlFactory$OkHttpURLConnection;)V
  #40 = Utf8               handshake
  #41 = Utf8               ()Lokhttp3/Handshake;
  #42 = Utf8               StackMapTable
  #43 = Utf8               setHostnameVerifier
  #44 = Utf8               (Ljavax/net/ssl/HostnameVerifier;)V
  #45 = Utf8               hostnameVerifier
  #46 = Utf8               Ljavax/net/ssl/HostnameVerifier;
  #47 = Utf8               getHostnameVerifier
  #48 = Utf8               ()Ljavax/net/ssl/HostnameVerifier;
  #49 = Utf8               setSSLSocketFactory
  #50 = Utf8               (Ljavax/net/ssl/SSLSocketFactory;)V
  #51 = Utf8               sslSocketFactory
  #52 = Utf8               Ljavax/net/ssl/SSLSocketFactory;
  #53 = Utf8               getSSLSocketFactory
  #54 = Utf8               ()Ljavax/net/ssl/SSLSocketFactory;
  #55 = Utf8               SourceFile
  #56 = Utf8               ObsoleteUrlFactory.java
  #57 = Class              #82            // org/kohsuke/github/extras/okhttp3/ObsoleteUrlFactory
  #58 = Utf8               org/kohsuke/github/extras/okhttp3/ObsoleteUrlFactory$OkHttpURLConnection
  #59 = NameAndType        #27:#28        // "<init>":(Ljava/net/URL;Lokhttp3/OkHttpClient;)V
  #60 = NameAndType        #27:#39        // "<init>":(Lorg/kohsuke/github/extras/okhttp3/ObsoleteUrlFactory$OkHttpURLConnection;)V
  #61 = NameAndType        #27:#83        // "<init>":(Ljava/net/HttpURLConnection;)V
  #62 = NameAndType        #23:#26        // delegate:Lorg/kohsuke/github/extras/okhttp3/ObsoleteUrlFactory$OkHttpURLConnection;
  #63 = NameAndType        #84:#85        // call:Lokhttp3/Call;
  #64 = Utf8               java/lang/IllegalStateException
  #65 = Utf8               Connection has not yet been established
  #66 = NameAndType        #27:#86        // "<init>":(Ljava/lang/String;)V
  #67 = NameAndType        #40:#87        // handshake:Lokhttp3/Handshake;
  #68 = NameAndType        #37:#38        // client:Lokhttp3/OkHttpClient;
  #69 = Class              #88            // okhttp3/OkHttpClient
  #70 = NameAndType        #89:#91        // newBuilder:()Lokhttp3/OkHttpClient$Builder;
  #71 = Class              #92            // okhttp3/OkHttpClient$Builder
  #72 = NameAndType        #45:#93        // hostnameVerifier:(Ljavax/net/ssl/HostnameVerifier;)Lokhttp3/OkHttpClient$Builder;
  #73 = NameAndType        #94:#95        // build:()Lokhttp3/OkHttpClient;
  #74 = NameAndType        #45:#48        // hostnameVerifier:()Ljavax/net/ssl/HostnameVerifier;
  #75 = Utf8               java/lang/IllegalArgumentException
  #76 = Utf8               sslSocketFactory == null
  #77 = NameAndType        #51:#96        // sslSocketFactory:(Ljavax/net/ssl/SSLSocketFactory;)Lokhttp3/OkHttpClient$Builder;
  #78 = NameAndType        #51:#54        // sslSocketFactory:()Ljavax/net/ssl/SSLSocketFactory;
  #79 = Utf8               org/kohsuke/github/extras/okhttp3/ObsoleteUrlFactory$OkHttpsURLConnection
  #80 = Utf8               org/kohsuke/github/extras/okhttp3/ObsoleteUrlFactory$DelegatingHttpsURLConnection
  #81 = Utf8               DelegatingHttpsURLConnection
  #82 = Utf8               org/kohsuke/github/extras/okhttp3/ObsoleteUrlFactory
  #83 = Utf8               (Ljava/net/HttpURLConnection;)V
  #84 = Utf8               call
  #85 = Utf8               Lokhttp3/Call;
  #86 = Utf8               (Ljava/lang/String;)V
  #87 = Utf8               Lokhttp3/Handshake;
  #88 = Utf8               okhttp3/OkHttpClient
  #89 = Utf8               newBuilder
  #90 = Utf8               Builder
  #91 = Utf8               ()Lokhttp3/OkHttpClient$Builder;
  #92 = Utf8               okhttp3/OkHttpClient$Builder
  #93 = Utf8               (Ljavax/net/ssl/HostnameVerifier;)Lokhttp3/OkHttpClient$Builder;
  #94 = Utf8               build
  #95 = Utf8               ()Lokhttp3/OkHttpClient;
  #96 = Utf8               (Ljavax/net/ssl/SSLSocketFactory;)Lokhttp3/OkHttpClient$Builder;
{
  private final org.kohsuke.github.extras.okhttp3.ObsoleteUrlFactory$OkHttpURLConnection delegate;
    descriptor: Lorg/kohsuke/github/extras/okhttp3/ObsoleteUrlFactory$OkHttpURLConnection;
    flags: (0x0012) ACC_PRIVATE, ACC_FINAL

  org.kohsuke.github.extras.okhttp3.ObsoleteUrlFactory$OkHttpsURLConnection(java.net.URL, okhttp3.OkHttpClient);
    descriptor: (Ljava/net/URL;Lokhttp3/OkHttpClient;)V
    flags: (0x0000)
    Code:
      stack=5, locals=3, args_size=3
         0: aload_0
         1: new           #1                  // class org/kohsuke/github/extras/okhttp3/ObsoleteUrlFactory$OkHttpURLConnection
         4: dup
         5: aload_1
         6: aload_2
         7: invokespecial #2                  // Method org/kohsuke/github/extras/okhttp3/ObsoleteUrlFactory$OkHttpURLConnection."<init>":(Ljava/net/URL;Lokhttp3/OkHttpClient;)V
        10: invokespecial #3                  // Method "<init>":(Lorg/kohsuke/github/extras/okhttp3/ObsoleteUrlFactory$OkHttpURLConnection;)V
        13: return
      LineNumberTable:
        line 1320: 0
        line 1321: 13
      LocalVariableTable:
        Start  Length  Slot  Name   Signature
            0      14     0  this   Lorg/kohsuke/github/extras/okhttp3/ObsoleteUrlFactory$OkHttpsURLConnection;
            0      14     1   url   Ljava/net/URL;
            0      14     2 client   Lokhttp3/OkHttpClient;

  org.kohsuke.github.extras.okhttp3.ObsoleteUrlFactory$OkHttpsURLConnection(org.kohsuke.github.extras.okhttp3.ObsoleteUrlFactory$OkHttpURLConnection);
    descriptor: (Lorg/kohsuke/github/extras/okhttp3/ObsoleteUrlFactory$OkHttpURLConnection;)V
    flags: (0x0000)
    Code:
      stack=2, locals=2, args_size=2
         0: aload_0
         1: aload_1
         2: invokespecial #4                  // Method org/kohsuke/github/extras/okhttp3/ObsoleteUrlFactory$DelegatingHttpsURLConnection."<init>":(Ljava/net/HttpURLConnection;)V
         5: aload_0
         6: aload_1
         7: putfield      #5                  // Field delegate:Lorg/kohsuke/github/extras/okhttp3/ObsoleteUrlFactory$OkHttpURLConnection;
        10: return
      LineNumberTable:
        line 1324: 0
        line 1325: 5
        line 1326: 10
      LocalVariableTable:
        Start  Length  Slot  Name   Signature
            0      11     0  this   Lorg/kohsuke/github/extras/okhttp3/ObsoleteUrlFactory$OkHttpsURLConnection;
            0      11     1 delegate   Lorg/kohsuke/github/extras/okhttp3/ObsoleteUrlFactory$OkHttpURLConnection;

  protected okhttp3.Handshake handshake();
    descriptor: ()Lokhttp3/Handshake;
    flags: (0x0004) ACC_PROTECTED
    Code:
      stack=3, locals=1, args_size=1
         0: aload_0
         1: getfield      #5                  // Field delegate:Lorg/kohsuke/github/extras/okhttp3/ObsoleteUrlFactory$OkHttpURLConnection;
         4: getfield      #6                  // Field org/kohsuke/github/extras/okhttp3/ObsoleteUrlFactory$OkHttpURLConnection.call:Lokhttp3/Call;
         7: ifnonnull     20
        10: new           #7                  // class java/lang/IllegalStateException
        13: dup
        14: ldc           #8                  // String Connection has not yet been established
        16: invokespecial #9                  // Method java/lang/IllegalStateException."<init>":(Ljava/lang/String;)V
        19: athrow
        20: aload_0
        21: getfield      #5                  // Field delegate:Lorg/kohsuke/github/extras/okhttp3/ObsoleteUrlFactory$OkHttpURLConnection;
        24: getfield      #10                 // Field org/kohsuke/github/extras/okhttp3/ObsoleteUrlFactory$OkHttpURLConnection.handshake:Lokhttp3/Handshake;
        27: areturn
      LineNumberTable:
        line 1330: 0
        line 1331: 10
        line 1334: 20
      LocalVariableTable:
        Start  Length  Slot  Name   Signature
            0      28     0  this   Lorg/kohsuke/github/extras/okhttp3/ObsoleteUrlFactory$OkHttpsURLConnection;
      StackMapTable: number_of_entries = 1
        frame_type = 20 /* same */

  public void setHostnameVerifier(javax.net.ssl.HostnameVerifier);
    descriptor: (Ljavax/net/ssl/HostnameVerifier;)V
    flags: (0x0001) ACC_PUBLIC
    Code:
      stack=3, locals=2, args_size=2
         0: aload_0
         1: getfield      #5                  // Field delegate:Lorg/kohsuke/github/extras/okhttp3/ObsoleteUrlFactory$OkHttpURLConnection;
         4: aload_0
         5: getfield      #5                  // Field delegate:Lorg/kohsuke/github/extras/okhttp3/ObsoleteUrlFactory$OkHttpURLConnection;
         8: getfield      #11                 // Field org/kohsuke/github/extras/okhttp3/ObsoleteUrlFactory$OkHttpURLConnection.client:Lokhttp3/OkHttpClient;
        11: invokevirtual #12                 // Method okhttp3/OkHttpClient.newBuilder:()Lokhttp3/OkHttpClient$Builder;
        14: aload_1
        15: invokevirtual #13                 // Method okhttp3/OkHttpClient$Builder.hostnameVerifier:(Ljavax/net/ssl/HostnameVerifier;)Lokhttp3/OkHttpClient$Builder;
        18: invokevirtual #14                 // Method okhttp3/OkHttpClient$Builder.build:()Lokhttp3/OkHttpClient;
        21: putfield      #11                 // Field org/kohsuke/github/extras/okhttp3/ObsoleteUrlFactory$OkHttpURLConnection.client:Lokhttp3/OkHttpClient;
        24: return
      LineNumberTable:
        line 1339: 0
        line 1340: 24
      LocalVariableTable:
        Start  Length  Slot  Name   Signature
            0      25     0  this   Lorg/kohsuke/github/extras/okhttp3/ObsoleteUrlFactory$OkHttpsURLConnection;
            0      25     1 hostnameVerifier   Ljavax/net/ssl/HostnameVerifier;

  public javax.net.ssl.HostnameVerifier getHostnameVerifier();
    descriptor: ()Ljavax/net/ssl/HostnameVerifier;
    flags: (0x0001) ACC_PUBLIC
    Code:
      stack=1, locals=1, args_size=1
         0: aload_0
         1: getfield      #5                  // Field delegate:Lorg/kohsuke/github/extras/okhttp3/ObsoleteUrlFactory$OkHttpURLConnection;
         4: getfield      #11                 // Field org/kohsuke/github/extras/okhttp3/ObsoleteUrlFactory$OkHttpURLConnection.client:Lokhttp3/OkHttpClient;
         7: invokevirtual #15                 // Method okhttp3/OkHttpClient.hostnameVerifier:()Ljavax/net/ssl/HostnameVerifier;
        10: areturn
      LineNumberTable:
        line 1344: 0
      LocalVariableTable:
        Start  Length  Slot  Name   Signature
            0      11     0  this   Lorg/kohsuke/github/extras/okhttp3/ObsoleteUrlFactory$OkHttpsURLConnection;

  public void setSSLSocketFactory(javax.net.ssl.SSLSocketFactory);
    descriptor: (Ljavax/net/ssl/SSLSocketFactory;)V
    flags: (0x0001) ACC_PUBLIC
    Code:
      stack=3, locals=2, args_size=2
         0: aload_1
         1: ifnonnull     14
         4: new           #16                 // class java/lang/IllegalArgumentException
         7: dup
         8: ldc           #17                 // String sslSocketFactory == null
        10: invokespecial #18                 // Method java/lang/IllegalArgumentException."<init>":(Ljava/lang/String;)V
        13: athrow
        14: aload_0
        15: getfield      #5                  // Field delegate:Lorg/kohsuke/github/extras/okhttp3/ObsoleteUrlFactory$OkHttpURLConnection;
        18: aload_0
        19: getfield      #5                  // Field delegate:Lorg/kohsuke/github/extras/okhttp3/ObsoleteUrlFactory$OkHttpURLConnection;
        22: getfield      #11                 // Field org/kohsuke/github/extras/okhttp3/ObsoleteUrlFactory$OkHttpURLConnection.client:Lokhttp3/OkHttpClient;
        25: invokevirtual #12                 // Method okhttp3/OkHttpClient.newBuilder:()Lokhttp3/OkHttpClient$Builder;
        28: aload_1
        29: invokevirtual #19                 // Method okhttp3/OkHttpClient$Builder.sslSocketFactory:(Ljavax/net/ssl/SSLSocketFactory;)Lokhttp3/OkHttpClient$Builder;
        32: invokevirtual #14                 // Method okhttp3/OkHttpClient$Builder.build:()Lokhttp3/OkHttpClient;
        35: putfield      #11                 // Field org/kohsuke/github/extras/okhttp3/ObsoleteUrlFactory$OkHttpURLConnection.client:Lokhttp3/OkHttpClient;
        38: return
      LineNumberTable:
        line 1349: 0
        line 1350: 4
        line 1353: 14
        line 1354: 38
      LocalVariableTable:
        Start  Length  Slot  Name   Signature
            0      39     0  this   Lorg/kohsuke/github/extras/okhttp3/ObsoleteUrlFactory$OkHttpsURLConnection;
            0      39     1 sslSocketFactory   Ljavax/net/ssl/SSLSocketFactory;
      StackMapTable: number_of_entries = 1
        frame_type = 14 /* same */

  public javax.net.ssl.SSLSocketFactory getSSLSocketFactory();
    descriptor: ()Ljavax/net/ssl/SSLSocketFactory;
    flags: (0x0001) ACC_PUBLIC
    Code:
      stack=1, locals=1, args_size=1
         0: aload_0
         1: getfield      #5                  // Field delegate:Lorg/kohsuke/github/extras/okhttp3/ObsoleteUrlFactory$OkHttpURLConnection;
         4: getfield      #11                 // Field org/kohsuke/github/extras/okhttp3/ObsoleteUrlFactory$OkHttpURLConnection.client:Lokhttp3/OkHttpClient;
         7: invokevirtual #20                 // Method okhttp3/OkHttpClient.sslSocketFactory:()Ljavax/net/ssl/SSLSocketFactory;
        10: areturn
      LineNumberTable:
        line 1358: 0
      LocalVariableTable:
        Start  Length  Slot  Name   Signature
            0      11     0  this   Lorg/kohsuke/github/extras/okhttp3/ObsoleteUrlFactory$OkHttpsURLConnection;
}
SourceFile: "ObsoleteUrlFactory.java"
InnerClasses:
  static final #24= #1 of #57;            // OkHttpURLConnection=class org/kohsuke/github/extras/okhttp3/ObsoleteUrlFactory$OkHttpURLConnection of class org/kohsuke/github/extras/okhttp3/ObsoleteUrlFactory
  static final #33= #21 of #57;           // OkHttpsURLConnection=class org/kohsuke/github/extras/okhttp3/ObsoleteUrlFactory$OkHttpsURLConnection of class org/kohsuke/github/extras/okhttp3/ObsoleteUrlFactory
  static abstract #81= #22 of #57;        // DelegatingHttpsURLConnection=class org/kohsuke/github/extras/okhttp3/ObsoleteUrlFactory$DelegatingHttpsURLConnection of class org/kohsuke/github/extras/okhttp3/ObsoleteUrlFactory
  public static final #90= #71 of #69;    // Builder=class okhttp3/OkHttpClient$Builder of class okhttp3/OkHttpClient
