Classfile /Users/mw/Projects/slang-braindump/.jar/jar11/assemble/slang-braindump/assemble/content/com/fasterxml/jackson/databind/ser/std/ArraySerializerBase.class
  Last modified May 29, 2022; size 6965 bytes
  SHA-256 checksum 30ee6e16bd4774b52534491f36207b807a6b3a66a5697d63f0461e800e593505
  Compiled from "ArraySerializerBase.java"
public abstract class com.fasterxml.jackson.databind.ser.std.ArraySerializerBase<T extends java.lang.Object> extends com.fasterxml.jackson.databind.ser.ContainerSerializer<T> implements com.fasterxml.jackson.databind.ser.ContextualSerializer
  minor version: 0
  major version: 52
  flags: (0x0421) ACC_PUBLIC, ACC_SUPER, ACC_ABSTRACT
  this_class: #25                         // com/fasterxml/jackson/databind/ser/std/ArraySerializerBase
  super_class: #26                        // com/fasterxml/jackson/databind/ser/ContainerSerializer
  interfaces: 1, fields: 2, methods: 11, attributes: 3
Constant pool:
    #1 = Methodref          #26.#102      // com/fasterxml/jackson/databind/ser/ContainerSerializer."<init>":(Ljava/lang/Class;)V
    #2 = Fieldref           #25.#103      // com/fasterxml/jackson/databind/ser/std/ArraySerializerBase._property:Lcom/fasterxml/jackson/databind/BeanProperty;
    #3 = Fieldref           #25.#104      // com/fasterxml/jackson/databind/ser/std/ArraySerializerBase._unwrapSingle:Ljava/lang/Boolean;
    #4 = Fieldref           #25.#105      // com/fasterxml/jackson/databind/ser/std/ArraySerializerBase._handledType:Ljava/lang/Class;
    #5 = Methodref          #26.#106      // com/fasterxml/jackson/databind/ser/ContainerSerializer."<init>":(Ljava/lang/Class;Z)V
    #6 = Methodref          #25.#107      // com/fasterxml/jackson/databind/ser/std/ArraySerializerBase.handledType:()Ljava/lang/Class;
    #7 = Methodref          #25.#108      // com/fasterxml/jackson/databind/ser/std/ArraySerializerBase.findFormatOverrides:(Lcom/fasterxml/jackson/databind/SerializerProvider;Lcom/fasterxml/jackson/databind/BeanProperty;Ljava/lang/Class;)Lcom/fasterxml/jackson/annotation/JsonFormat$Value;
    #8 = Fieldref           #109.#110     // com/fasterxml/jackson/annotation/JsonFormat$Feature.WRITE_SINGLE_ELEM_ARRAYS_UNWRAPPED:Lcom/fasterxml/jackson/annotation/JsonFormat$Feature;
    #9 = Methodref          #67.#111      // com/fasterxml/jackson/annotation/JsonFormat$Value.getFeature:(Lcom/fasterxml/jackson/annotation/JsonFormat$Feature;)Ljava/lang/Boolean;
   #10 = Methodref          #112.#113     // java/util/Objects.equals:(Ljava/lang/Object;Ljava/lang/Object;)Z
   #11 = Methodref          #25.#114      // com/fasterxml/jackson/databind/ser/std/ArraySerializerBase._withResolved:(Lcom/fasterxml/jackson/databind/BeanProperty;Ljava/lang/Boolean;)Lcom/fasterxml/jackson/databind/JsonSerializer;
   #12 = Methodref          #25.#115      // com/fasterxml/jackson/databind/ser/std/ArraySerializerBase._shouldUnwrapSingle:(Lcom/fasterxml/jackson/databind/SerializerProvider;)Z
   #13 = Methodref          #25.#116      // com/fasterxml/jackson/databind/ser/std/ArraySerializerBase.hasSingleElement:(Ljava/lang/Object;)Z
   #14 = Methodref          #25.#117      // com/fasterxml/jackson/databind/ser/std/ArraySerializerBase.serializeContents:(Ljava/lang/Object;Lcom/fasterxml/jackson/core/JsonGenerator;Lcom/fasterxml/jackson/databind/SerializerProvider;)V
   #15 = Methodref          #118.#119     // com/fasterxml/jackson/core/JsonGenerator.writeStartArray:(Ljava/lang/Object;)V
   #16 = Methodref          #118.#120     // com/fasterxml/jackson/core/JsonGenerator.writeEndArray:()V
   #17 = Fieldref           #121.#122     // com/fasterxml/jackson/core/JsonToken.START_ARRAY:Lcom/fasterxml/jackson/core/JsonToken;
   #18 = Methodref          #123.#124     // com/fasterxml/jackson/databind/jsontype/TypeSerializer.typeId:(Ljava/lang/Object;Lcom/fasterxml/jackson/core/JsonToken;)Lcom/fasterxml/jackson/core/type/WritableTypeId;
   #19 = Methodref          #123.#125     // com/fasterxml/jackson/databind/jsontype/TypeSerializer.writeTypePrefix:(Lcom/fasterxml/jackson/core/JsonGenerator;Lcom/fasterxml/jackson/core/type/WritableTypeId;)Lcom/fasterxml/jackson/core/type/WritableTypeId;
   #20 = Methodref          #118.#126     // com/fasterxml/jackson/core/JsonGenerator.setCurrentValue:(Ljava/lang/Object;)V
   #21 = Methodref          #123.#127     // com/fasterxml/jackson/databind/jsontype/TypeSerializer.writeTypeSuffix:(Lcom/fasterxml/jackson/core/JsonGenerator;Lcom/fasterxml/jackson/core/type/WritableTypeId;)Lcom/fasterxml/jackson/core/type/WritableTypeId;
   #22 = Fieldref           #128.#129     // com/fasterxml/jackson/databind/SerializationFeature.WRITE_SINGLE_ELEM_ARRAYS_UNWRAPPED:Lcom/fasterxml/jackson/databind/SerializationFeature;
   #23 = Methodref          #130.#131     // com/fasterxml/jackson/databind/SerializerProvider.isEnabled:(Lcom/fasterxml/jackson/databind/SerializationFeature;)Z
   #24 = Methodref          #132.#133     // java/lang/Boolean.booleanValue:()Z
   #25 = Class              #134          // com/fasterxml/jackson/databind/ser/std/ArraySerializerBase
   #26 = Class              #135          // com/fasterxml/jackson/databind/ser/ContainerSerializer
   #27 = Class              #136          // com/fasterxml/jackson/databind/ser/ContextualSerializer
   #28 = Utf8               _property
   #29 = Utf8               Lcom/fasterxml/jackson/databind/BeanProperty;
   #30 = Utf8               _unwrapSingle
   #31 = Utf8               Ljava/lang/Boolean;
   #32 = Utf8               <init>
   #33 = Utf8               (Ljava/lang/Class;)V
   #34 = Utf8               Code
   #35 = Utf8               LineNumberTable
   #36 = Utf8               LocalVariableTable
   #37 = Utf8               this
   #38 = Utf8               Lcom/fasterxml/jackson/databind/ser/std/ArraySerializerBase;
   #39 = Utf8               cls
   #40 = Utf8               Ljava/lang/Class;
   #41 = Utf8               LocalVariableTypeTable
   #42 = Utf8               Lcom/fasterxml/jackson/databind/ser/std/ArraySerializerBase<TT;>;
   #43 = Utf8               Ljava/lang/Class<TT;>;
   #44 = Utf8               Signature
   #45 = Utf8               (Ljava/lang/Class<TT;>;)V
   #46 = Utf8               (Ljava/lang/Class;Lcom/fasterxml/jackson/databind/BeanProperty;)V
   #47 = Utf8               property
   #48 = Utf8               Deprecated
   #49 = Utf8               (Ljava/lang/Class<TT;>;Lcom/fasterxml/jackson/databind/BeanProperty;)V
   #50 = Utf8               RuntimeVisibleAnnotations
   #51 = Utf8               Ljava/lang/Deprecated;
   #52 = Utf8               (Lcom/fasterxml/jackson/databind/ser/std/ArraySerializerBase;)V
   #53 = Utf8               src
   #54 = Utf8               Lcom/fasterxml/jackson/databind/ser/std/ArraySerializerBase<*>;
   #55 = Utf8               (Lcom/fasterxml/jackson/databind/ser/std/ArraySerializerBase<*>;)V
   #56 = Utf8               (Lcom/fasterxml/jackson/databind/ser/std/ArraySerializerBase;Lcom/fasterxml/jackson/databind/BeanProperty;Ljava/lang/Boolean;)V
   #57 = Utf8               unwrapSingle
   #58 = Utf8               (Lcom/fasterxml/jackson/databind/ser/std/ArraySerializerBase<*>;Lcom/fasterxml/jackson/databind/BeanProperty;Ljava/lang/Boolean;)V
   #59 = Utf8               (Lcom/fasterxml/jackson/databind/ser/std/ArraySerializerBase;Lcom/fasterxml/jackson/databind/BeanProperty;)V
   #60 = Utf8               (Lcom/fasterxml/jackson/databind/ser/std/ArraySerializerBase<*>;Lcom/fasterxml/jackson/databind/BeanProperty;)V
   #61 = Utf8               _withResolved
   #62 = Utf8               (Lcom/fasterxml/jackson/databind/BeanProperty;Ljava/lang/Boolean;)Lcom/fasterxml/jackson/databind/JsonSerializer;
   #63 = Utf8               (Lcom/fasterxml/jackson/databind/BeanProperty;Ljava/lang/Boolean;)Lcom/fasterxml/jackson/databind/JsonSerializer<*>;
   #64 = Utf8               createContextual
   #65 = Utf8               (Lcom/fasterxml/jackson/databind/SerializerProvider;Lcom/fasterxml/jackson/databind/BeanProperty;)Lcom/fasterxml/jackson/databind/JsonSerializer;
   #66 = Utf8               format
   #67 = Class              #138          // com/fasterxml/jackson/annotation/JsonFormat$Value
   #68 = Utf8               Value
   #69 = Utf8               InnerClasses
   #70 = Utf8               Lcom/fasterxml/jackson/annotation/JsonFormat$Value;
   #71 = Utf8               serializers
   #72 = Utf8               Lcom/fasterxml/jackson/databind/SerializerProvider;
   #73 = Utf8               StackMapTable
   #74 = Class              #139          // java/lang/Boolean
   #75 = Utf8               Exceptions
   #76 = Class              #140          // com/fasterxml/jackson/databind/JsonMappingException
   #77 = Utf8               (Lcom/fasterxml/jackson/databind/SerializerProvider;Lcom/fasterxml/jackson/databind/BeanProperty;)Lcom/fasterxml/jackson/databind/JsonSerializer<*>;
   #78 = Utf8               serialize
   #79 = Utf8               (Ljava/lang/Object;Lcom/fasterxml/jackson/core/JsonGenerator;Lcom/fasterxml/jackson/databind/SerializerProvider;)V
   #80 = Utf8               value
   #81 = Utf8               Ljava/lang/Object;
   #82 = Utf8               gen
   #83 = Utf8               Lcom/fasterxml/jackson/core/JsonGenerator;
   #84 = Utf8               provider
   #85 = Utf8               TT;
   #86 = Class              #141          // java/io/IOException
   #87 = Utf8               (TT;Lcom/fasterxml/jackson/core/JsonGenerator;Lcom/fasterxml/jackson/databind/SerializerProvider;)V
   #88 = Utf8               serializeWithType
   #89 = Utf8               (Ljava/lang/Object;Lcom/fasterxml/jackson/core/JsonGenerator;Lcom/fasterxml/jackson/databind/SerializerProvider;Lcom/fasterxml/jackson/databind/jsontype/TypeSerializer;)V
   #90 = Utf8               g
   #91 = Utf8               typeSer
   #92 = Utf8               Lcom/fasterxml/jackson/databind/jsontype/TypeSerializer;
   #93 = Utf8               typeIdDef
   #94 = Utf8               Lcom/fasterxml/jackson/core/type/WritableTypeId;
   #95 = Utf8               (TT;Lcom/fasterxml/jackson/core/JsonGenerator;Lcom/fasterxml/jackson/databind/SerializerProvider;Lcom/fasterxml/jackson/databind/jsontype/TypeSerializer;)V
   #96 = Utf8               serializeContents
   #97 = Utf8               _shouldUnwrapSingle
   #98 = Utf8               (Lcom/fasterxml/jackson/databind/SerializerProvider;)Z
   #99 = Utf8               <T:Ljava/lang/Object;>Lcom/fasterxml/jackson/databind/ser/ContainerSerializer<TT;>;Lcom/fasterxml/jackson/databind/ser/ContextualSerializer;
  #100 = Utf8               SourceFile
  #101 = Utf8               ArraySerializerBase.java
  #102 = NameAndType        #32:#33       // "<init>":(Ljava/lang/Class;)V
  #103 = NameAndType        #28:#29       // _property:Lcom/fasterxml/jackson/databind/BeanProperty;
  #104 = NameAndType        #30:#31       // _unwrapSingle:Ljava/lang/Boolean;
  #105 = NameAndType        #142:#40      // _handledType:Ljava/lang/Class;
  #106 = NameAndType        #32:#143      // "<init>":(Ljava/lang/Class;Z)V
  #107 = NameAndType        #144:#145     // handledType:()Ljava/lang/Class;
  #108 = NameAndType        #146:#147     // findFormatOverrides:(Lcom/fasterxml/jackson/databind/SerializerProvider;Lcom/fasterxml/jackson/databind/BeanProperty;Ljava/lang/Class;)Lcom/fasterxml/jackson/annotation/JsonFormat$Value;
  #109 = Class              #148          // com/fasterxml/jackson/annotation/JsonFormat$Feature
  #110 = NameAndType        #150:#151     // WRITE_SINGLE_ELEM_ARRAYS_UNWRAPPED:Lcom/fasterxml/jackson/annotation/JsonFormat$Feature;
  #111 = NameAndType        #152:#153     // getFeature:(Lcom/fasterxml/jackson/annotation/JsonFormat$Feature;)Ljava/lang/Boolean;
  #112 = Class              #154          // java/util/Objects
  #113 = NameAndType        #155:#156     // equals:(Ljava/lang/Object;Ljava/lang/Object;)Z
  #114 = NameAndType        #61:#62       // _withResolved:(Lcom/fasterxml/jackson/databind/BeanProperty;Ljava/lang/Boolean;)Lcom/fasterxml/jackson/databind/JsonSerializer;
  #115 = NameAndType        #97:#98       // _shouldUnwrapSingle:(Lcom/fasterxml/jackson/databind/SerializerProvider;)Z
  #116 = NameAndType        #157:#158     // hasSingleElement:(Ljava/lang/Object;)Z
  #117 = NameAndType        #96:#79       // serializeContents:(Ljava/lang/Object;Lcom/fasterxml/jackson/core/JsonGenerator;Lcom/fasterxml/jackson/databind/SerializerProvider;)V
  #118 = Class              #159          // com/fasterxml/jackson/core/JsonGenerator
  #119 = NameAndType        #160:#161     // writeStartArray:(Ljava/lang/Object;)V
  #120 = NameAndType        #162:#163     // writeEndArray:()V
  #121 = Class              #164          // com/fasterxml/jackson/core/JsonToken
  #122 = NameAndType        #165:#166     // START_ARRAY:Lcom/fasterxml/jackson/core/JsonToken;
  #123 = Class              #167          // com/fasterxml/jackson/databind/jsontype/TypeSerializer
  #124 = NameAndType        #168:#169     // typeId:(Ljava/lang/Object;Lcom/fasterxml/jackson/core/JsonToken;)Lcom/fasterxml/jackson/core/type/WritableTypeId;
  #125 = NameAndType        #170:#171     // writeTypePrefix:(Lcom/fasterxml/jackson/core/JsonGenerator;Lcom/fasterxml/jackson/core/type/WritableTypeId;)Lcom/fasterxml/jackson/core/type/WritableTypeId;
  #126 = NameAndType        #172:#161     // setCurrentValue:(Ljava/lang/Object;)V
  #127 = NameAndType        #173:#171     // writeTypeSuffix:(Lcom/fasterxml/jackson/core/JsonGenerator;Lcom/fasterxml/jackson/core/type/WritableTypeId;)Lcom/fasterxml/jackson/core/type/WritableTypeId;
  #128 = Class              #174          // com/fasterxml/jackson/databind/SerializationFeature
  #129 = NameAndType        #150:#175     // WRITE_SINGLE_ELEM_ARRAYS_UNWRAPPED:Lcom/fasterxml/jackson/databind/SerializationFeature;
  #130 = Class              #176          // com/fasterxml/jackson/databind/SerializerProvider
  #131 = NameAndType        #177:#178     // isEnabled:(Lcom/fasterxml/jackson/databind/SerializationFeature;)Z
  #132 = Class              #139          // java/lang/Boolean
  #133 = NameAndType        #179:#180     // booleanValue:()Z
  #134 = Utf8               com/fasterxml/jackson/databind/ser/std/ArraySerializerBase
  #135 = Utf8               com/fasterxml/jackson/databind/ser/ContainerSerializer
  #136 = Utf8               com/fasterxml/jackson/databind/ser/ContextualSerializer
  #137 = Class              #181          // com/fasterxml/jackson/annotation/JsonFormat
  #138 = Utf8               com/fasterxml/jackson/annotation/JsonFormat$Value
  #139 = Utf8               java/lang/Boolean
  #140 = Utf8               com/fasterxml/jackson/databind/JsonMappingException
  #141 = Utf8               java/io/IOException
  #142 = Utf8               _handledType
  #143 = Utf8               (Ljava/lang/Class;Z)V
  #144 = Utf8               handledType
  #145 = Utf8               ()Ljava/lang/Class;
  #146 = Utf8               findFormatOverrides
  #147 = Utf8               (Lcom/fasterxml/jackson/databind/SerializerProvider;Lcom/fasterxml/jackson/databind/BeanProperty;Ljava/lang/Class;)Lcom/fasterxml/jackson/annotation/JsonFormat$Value;
  #148 = Utf8               com/fasterxml/jackson/annotation/JsonFormat$Feature
  #149 = Utf8               Feature
  #150 = Utf8               WRITE_SINGLE_ELEM_ARRAYS_UNWRAPPED
  #151 = Utf8               Lcom/fasterxml/jackson/annotation/JsonFormat$Feature;
  #152 = Utf8               getFeature
  #153 = Utf8               (Lcom/fasterxml/jackson/annotation/JsonFormat$Feature;)Ljava/lang/Boolean;
  #154 = Utf8               java/util/Objects
  #155 = Utf8               equals
  #156 = Utf8               (Ljava/lang/Object;Ljava/lang/Object;)Z
  #157 = Utf8               hasSingleElement
  #158 = Utf8               (Ljava/lang/Object;)Z
  #159 = Utf8               com/fasterxml/jackson/core/JsonGenerator
  #160 = Utf8               writeStartArray
  #161 = Utf8               (Ljava/lang/Object;)V
  #162 = Utf8               writeEndArray
  #163 = Utf8               ()V
  #164 = Utf8               com/fasterxml/jackson/core/JsonToken
  #165 = Utf8               START_ARRAY
  #166 = Utf8               Lcom/fasterxml/jackson/core/JsonToken;
  #167 = Utf8               com/fasterxml/jackson/databind/jsontype/TypeSerializer
  #168 = Utf8               typeId
  #169 = Utf8               (Ljava/lang/Object;Lcom/fasterxml/jackson/core/JsonToken;)Lcom/fasterxml/jackson/core/type/WritableTypeId;
  #170 = Utf8               writeTypePrefix
  #171 = Utf8               (Lcom/fasterxml/jackson/core/JsonGenerator;Lcom/fasterxml/jackson/core/type/WritableTypeId;)Lcom/fasterxml/jackson/core/type/WritableTypeId;
  #172 = Utf8               setCurrentValue
  #173 = Utf8               writeTypeSuffix
  #174 = Utf8               com/fasterxml/jackson/databind/SerializationFeature
  #175 = Utf8               Lcom/fasterxml/jackson/databind/SerializationFeature;
  #176 = Utf8               com/fasterxml/jackson/databind/SerializerProvider
  #177 = Utf8               isEnabled
  #178 = Utf8               (Lcom/fasterxml/jackson/databind/SerializationFeature;)Z
  #179 = Utf8               booleanValue
  #180 = Utf8               ()Z
  #181 = Utf8               com/fasterxml/jackson/annotation/JsonFormat
{
  protected final com.fasterxml.jackson.databind.BeanProperty _property;
    descriptor: Lcom/fasterxml/jackson/databind/BeanProperty;
    flags: (0x0014) ACC_PROTECTED, ACC_FINAL

  protected final java.lang.Boolean _unwrapSingle;
    descriptor: Ljava/lang/Boolean;
    flags: (0x0014) ACC_PROTECTED, ACC_FINAL

  protected com.fasterxml.jackson.databind.ser.std.ArraySerializerBase(java.lang.Class<T>);
    descriptor: (Ljava/lang/Class;)V
    flags: (0x0004) ACC_PROTECTED
    Code:
      stack=2, locals=2, args_size=2
         0: aload_0
         1: aload_1
         2: invokespecial #1                  // Method com/fasterxml/jackson/databind/ser/ContainerSerializer."<init>":(Ljava/lang/Class;)V
         5: aload_0
         6: aconst_null
         7: putfield      #2                  // Field _property:Lcom/fasterxml/jackson/databind/BeanProperty;
        10: aload_0
        11: aconst_null
        12: putfield      #3                  // Field _unwrapSingle:Ljava/lang/Boolean;
        15: return
      LineNumberTable:
        line 39: 0
        line 40: 5
        line 41: 10
        line 42: 15
      LocalVariableTable:
        Start  Length  Slot  Name   Signature
            0      16     0  this   Lcom/fasterxml/jackson/databind/ser/std/ArraySerializerBase;
            0      16     1   cls   Ljava/lang/Class;
      LocalVariableTypeTable:
        Start  Length  Slot  Name   Signature
            0      16     0  this   Lcom/fasterxml/jackson/databind/ser/std/ArraySerializerBase<TT;>;
            0      16     1   cls   Ljava/lang/Class<TT;>;
    Signature: #45                          // (Ljava/lang/Class<TT;>;)V

  protected com.fasterxml.jackson.databind.ser.std.ArraySerializerBase(java.lang.Class<T>, com.fasterxml.jackson.databind.BeanProperty);
    descriptor: (Ljava/lang/Class;Lcom/fasterxml/jackson/databind/BeanProperty;)V
    flags: (0x0004) ACC_PROTECTED
    Code:
      stack=2, locals=3, args_size=3
         0: aload_0
         1: aload_1
         2: invokespecial #1                  // Method com/fasterxml/jackson/databind/ser/ContainerSerializer."<init>":(Ljava/lang/Class;)V
         5: aload_0
         6: aload_2
         7: putfield      #2                  // Field _property:Lcom/fasterxml/jackson/databind/BeanProperty;
        10: aload_0
        11: aconst_null
        12: putfield      #3                  // Field _unwrapSingle:Ljava/lang/Boolean;
        15: return
      LineNumberTable:
        line 53: 0
        line 54: 5
        line 55: 10
        line 56: 15
      LocalVariableTable:
        Start  Length  Slot  Name   Signature
            0      16     0  this   Lcom/fasterxml/jackson/databind/ser/std/ArraySerializerBase;
            0      16     1   cls   Ljava/lang/Class;
            0      16     2 property   Lcom/fasterxml/jackson/databind/BeanProperty;
      LocalVariableTypeTable:
        Start  Length  Slot  Name   Signature
            0      16     0  this   Lcom/fasterxml/jackson/databind/ser/std/ArraySerializerBase<TT;>;
            0      16     1   cls   Ljava/lang/Class<TT;>;
    Deprecated: true
    Signature: #49                          // (Ljava/lang/Class<TT;>;Lcom/fasterxml/jackson/databind/BeanProperty;)V
    RuntimeVisibleAnnotations:
      0: #51()
        java.lang.Deprecated

  protected com.fasterxml.jackson.databind.ser.std.ArraySerializerBase(com.fasterxml.jackson.databind.ser.std.ArraySerializerBase<?>);
    descriptor: (Lcom/fasterxml/jackson/databind/ser/std/ArraySerializerBase;)V
    flags: (0x0004) ACC_PROTECTED
    Code:
      stack=3, locals=2, args_size=2
         0: aload_0
         1: aload_1
         2: getfield      #4                  // Field _handledType:Ljava/lang/Class;
         5: iconst_0
         6: invokespecial #5                  // Method com/fasterxml/jackson/databind/ser/ContainerSerializer."<init>":(Ljava/lang/Class;Z)V
         9: aload_0
        10: aload_1
        11: getfield      #2                  // Field _property:Lcom/fasterxml/jackson/databind/BeanProperty;
        14: putfield      #2                  // Field _property:Lcom/fasterxml/jackson/databind/BeanProperty;
        17: aload_0
        18: aload_1
        19: getfield      #3                  // Field _unwrapSingle:Ljava/lang/Boolean;
        22: putfield      #3                  // Field _unwrapSingle:Ljava/lang/Boolean;
        25: return
      LineNumberTable:
        line 60: 0
        line 61: 9
        line 62: 17
        line 63: 25
      LocalVariableTable:
        Start  Length  Slot  Name   Signature
            0      26     0  this   Lcom/fasterxml/jackson/databind/ser/std/ArraySerializerBase;
            0      26     1   src   Lcom/fasterxml/jackson/databind/ser/std/ArraySerializerBase;
      LocalVariableTypeTable:
        Start  Length  Slot  Name   Signature
            0      26     0  this   Lcom/fasterxml/jackson/databind/ser/std/ArraySerializerBase<TT;>;
            0      26     1   src   Lcom/fasterxml/jackson/databind/ser/std/ArraySerializerBase<*>;
    Signature: #55                          // (Lcom/fasterxml/jackson/databind/ser/std/ArraySerializerBase<*>;)V

  protected com.fasterxml.jackson.databind.ser.std.ArraySerializerBase(com.fasterxml.jackson.databind.ser.std.ArraySerializerBase<?>, com.fasterxml.jackson.databind.BeanProperty, java.lang.Boolean);
    descriptor: (Lcom/fasterxml/jackson/databind/ser/std/ArraySerializerBase;Lcom/fasterxml/jackson/databind/BeanProperty;Ljava/lang/Boolean;)V
    flags: (0x0004) ACC_PROTECTED
    Code:
      stack=3, locals=4, args_size=4
         0: aload_0
         1: aload_1
         2: getfield      #4                  // Field _handledType:Ljava/lang/Class;
         5: iconst_0
         6: invokespecial #5                  // Method com/fasterxml/jackson/databind/ser/ContainerSerializer."<init>":(Ljava/lang/Class;Z)V
         9: aload_0
        10: aload_2
        11: putfield      #2                  // Field _property:Lcom/fasterxml/jackson/databind/BeanProperty;
        14: aload_0
        15: aload_3
        16: putfield      #3                  // Field _unwrapSingle:Ljava/lang/Boolean;
        19: return
      LineNumberTable:
        line 71: 0
        line 72: 9
        line 73: 14
        line 74: 19
      LocalVariableTable:
        Start  Length  Slot  Name   Signature
            0      20     0  this   Lcom/fasterxml/jackson/databind/ser/std/ArraySerializerBase;
            0      20     1   src   Lcom/fasterxml/jackson/databind/ser/std/ArraySerializerBase;
            0      20     2 property   Lcom/fasterxml/jackson/databind/BeanProperty;
            0      20     3 unwrapSingle   Ljava/lang/Boolean;
      LocalVariableTypeTable:
        Start  Length  Slot  Name   Signature
            0      20     0  this   Lcom/fasterxml/jackson/databind/ser/std/ArraySerializerBase<TT;>;
            0      20     1   src   Lcom/fasterxml/jackson/databind/ser/std/ArraySerializerBase<*>;
    Signature: #58                          // (Lcom/fasterxml/jackson/databind/ser/std/ArraySerializerBase<*>;Lcom/fasterxml/jackson/databind/BeanProperty;Ljava/lang/Boolean;)V

  protected com.fasterxml.jackson.databind.ser.std.ArraySerializerBase(com.fasterxml.jackson.databind.ser.std.ArraySerializerBase<?>, com.fasterxml.jackson.databind.BeanProperty);
    descriptor: (Lcom/fasterxml/jackson/databind/ser/std/ArraySerializerBase;Lcom/fasterxml/jackson/databind/BeanProperty;)V
    flags: (0x0004) ACC_PROTECTED
    Code:
      stack=3, locals=3, args_size=3
         0: aload_0
         1: aload_1
         2: getfield      #4                  // Field _handledType:Ljava/lang/Class;
         5: iconst_0
         6: invokespecial #5                  // Method com/fasterxml/jackson/databind/ser/ContainerSerializer."<init>":(Ljava/lang/Class;Z)V
         9: aload_0
        10: aload_2
        11: putfield      #2                  // Field _property:Lcom/fasterxml/jackson/databind/BeanProperty;
        14: aload_0
        15: aload_1
        16: getfield      #3                  // Field _unwrapSingle:Ljava/lang/Boolean;
        19: putfield      #3                  // Field _unwrapSingle:Ljava/lang/Boolean;
        22: return
      LineNumberTable:
        line 82: 0
        line 83: 9
        line 84: 14
        line 85: 22
      LocalVariableTable:
        Start  Length  Slot  Name   Signature
            0      23     0  this   Lcom/fasterxml/jackson/databind/ser/std/ArraySerializerBase;
            0      23     1   src   Lcom/fasterxml/jackson/databind/ser/std/ArraySerializerBase;
            0      23     2 property   Lcom/fasterxml/jackson/databind/BeanProperty;
      LocalVariableTypeTable:
        Start  Length  Slot  Name   Signature
            0      23     0  this   Lcom/fasterxml/jackson/databind/ser/std/ArraySerializerBase<TT;>;
            0      23     1   src   Lcom/fasterxml/jackson/databind/ser/std/ArraySerializerBase<*>;
    Deprecated: true
    Signature: #60                          // (Lcom/fasterxml/jackson/databind/ser/std/ArraySerializerBase<*>;Lcom/fasterxml/jackson/databind/BeanProperty;)V
    RuntimeVisibleAnnotations:
      0: #51()
        java.lang.Deprecated

  public abstract com.fasterxml.jackson.databind.JsonSerializer<?> _withResolved(com.fasterxml.jackson.databind.BeanProperty, java.lang.Boolean);
    descriptor: (Lcom/fasterxml/jackson/databind/BeanProperty;Ljava/lang/Boolean;)Lcom/fasterxml/jackson/databind/JsonSerializer;
    flags: (0x0401) ACC_PUBLIC, ACC_ABSTRACT
    Signature: #63                          // (Lcom/fasterxml/jackson/databind/BeanProperty;Ljava/lang/Boolean;)Lcom/fasterxml/jackson/databind/JsonSerializer<*>;

  public com.fasterxml.jackson.databind.JsonSerializer<?> createContextual(com.fasterxml.jackson.databind.SerializerProvider, com.fasterxml.jackson.databind.BeanProperty) throws com.fasterxml.jackson.databind.JsonMappingException;
    descriptor: (Lcom/fasterxml/jackson/databind/SerializerProvider;Lcom/fasterxml/jackson/databind/BeanProperty;)Lcom/fasterxml/jackson/databind/JsonSerializer;
    flags: (0x0001) ACC_PUBLIC
    Code:
      stack=4, locals=5, args_size=3
         0: aconst_null
         1: astore_3
         2: aload_2
         3: ifnull        50
         6: aload_0
         7: aload_1
         8: aload_2
         9: aload_0
        10: invokevirtual #6                  // Method handledType:()Ljava/lang/Class;
        13: invokevirtual #7                  // Method findFormatOverrides:(Lcom/fasterxml/jackson/databind/SerializerProvider;Lcom/fasterxml/jackson/databind/BeanProperty;Ljava/lang/Class;)Lcom/fasterxml/jackson/annotation/JsonFormat$Value;
        16: astore        4
        18: aload         4
        20: ifnull        50
        23: aload         4
        25: getstatic     #8                  // Field com/fasterxml/jackson/annotation/JsonFormat$Feature.WRITE_SINGLE_ELEM_ARRAYS_UNWRAPPED:Lcom/fasterxml/jackson/annotation/JsonFormat$Feature;
        28: invokevirtual #9                  // Method com/fasterxml/jackson/annotation/JsonFormat$Value.getFeature:(Lcom/fasterxml/jackson/annotation/JsonFormat$Feature;)Ljava/lang/Boolean;
        31: astore_3
        32: aload_3
        33: aload_0
        34: getfield      #3                  // Field _unwrapSingle:Ljava/lang/Boolean;
        37: invokestatic  #10                 // Method java/util/Objects.equals:(Ljava/lang/Object;Ljava/lang/Object;)Z
        40: ifne          50
        43: aload_0
        44: aload_2
        45: aload_3
        46: invokevirtual #11                 // Method _withResolved:(Lcom/fasterxml/jackson/databind/BeanProperty;Ljava/lang/Boolean;)Lcom/fasterxml/jackson/databind/JsonSerializer;
        49: areturn
        50: aload_0
        51: areturn
      LineNumberTable:
        line 97: 0
        line 100: 2
        line 101: 6
        line 102: 18
        line 103: 23
        line 104: 32
        line 105: 43
        line 109: 50
      LocalVariableTable:
        Start  Length  Slot  Name   Signature
           18      32     4 format   Lcom/fasterxml/jackson/annotation/JsonFormat$Value;
            0      52     0  this   Lcom/fasterxml/jackson/databind/ser/std/ArraySerializerBase;
            0      52     1 serializers   Lcom/fasterxml/jackson/databind/SerializerProvider;
            0      52     2 property   Lcom/fasterxml/jackson/databind/BeanProperty;
            2      50     3 unwrapSingle   Ljava/lang/Boolean;
      LocalVariableTypeTable:
        Start  Length  Slot  Name   Signature
            0      52     0  this   Lcom/fasterxml/jackson/databind/ser/std/ArraySerializerBase<TT;>;
      StackMapTable: number_of_entries = 1
        frame_type = 252 /* append */
          offset_delta = 50
          locals = [ class java/lang/Boolean ]
    Exceptions:
      throws com.fasterxml.jackson.databind.JsonMappingException
    Signature: #77                          // (Lcom/fasterxml/jackson/databind/SerializerProvider;Lcom/fasterxml/jackson/databind/BeanProperty;)Lcom/fasterxml/jackson/databind/JsonSerializer<*>;

  public void serialize(T, com.fasterxml.jackson.core.JsonGenerator, com.fasterxml.jackson.databind.SerializerProvider) throws java.io.IOException;
    descriptor: (Ljava/lang/Object;Lcom/fasterxml/jackson/core/JsonGenerator;Lcom/fasterxml/jackson/databind/SerializerProvider;)V
    flags: (0x0001) ACC_PUBLIC
    Code:
      stack=4, locals=4, args_size=4
         0: aload_0
         1: aload_3
         2: invokevirtual #12                 // Method _shouldUnwrapSingle:(Lcom/fasterxml/jackson/databind/SerializerProvider;)Z
         5: ifeq          24
         8: aload_0
         9: aload_1
        10: invokevirtual #13                 // Method hasSingleElement:(Ljava/lang/Object;)Z
        13: ifeq          24
        16: aload_0
        17: aload_1
        18: aload_2
        19: aload_3
        20: invokevirtual #14                 // Method serializeContents:(Ljava/lang/Object;Lcom/fasterxml/jackson/core/JsonGenerator;Lcom/fasterxml/jackson/databind/SerializerProvider;)V
        23: return
        24: aload_2
        25: aload_1
        26: invokevirtual #15                 // Method com/fasterxml/jackson/core/JsonGenerator.writeStartArray:(Ljava/lang/Object;)V
        29: aload_0
        30: aload_1
        31: aload_2
        32: aload_3
        33: invokevirtual #14                 // Method serializeContents:(Ljava/lang/Object;Lcom/fasterxml/jackson/core/JsonGenerator;Lcom/fasterxml/jackson/databind/SerializerProvider;)V
        36: aload_2
        37: invokevirtual #16                 // Method com/fasterxml/jackson/core/JsonGenerator.writeEndArray:()V
        40: return
      LineNumberTable:
        line 118: 0
        line 119: 8
        line 120: 16
        line 121: 23
        line 124: 24
        line 125: 29
        line 126: 36
        line 127: 40
      LocalVariableTable:
        Start  Length  Slot  Name   Signature
            0      41     0  this   Lcom/fasterxml/jackson/databind/ser/std/ArraySerializerBase;
            0      41     1 value   Ljava/lang/Object;
            0      41     2   gen   Lcom/fasterxml/jackson/core/JsonGenerator;
            0      41     3 provider   Lcom/fasterxml/jackson/databind/SerializerProvider;
      LocalVariableTypeTable:
        Start  Length  Slot  Name   Signature
            0      41     0  this   Lcom/fasterxml/jackson/databind/ser/std/ArraySerializerBase<TT;>;
            0      41     1 value   TT;
      StackMapTable: number_of_entries = 1
        frame_type = 24 /* same */
    Exceptions:
      throws java.io.IOException
    Signature: #87                          // (TT;Lcom/fasterxml/jackson/core/JsonGenerator;Lcom/fasterxml/jackson/databind/SerializerProvider;)V

  public final void serializeWithType(T, com.fasterxml.jackson.core.JsonGenerator, com.fasterxml.jackson.databind.SerializerProvider, com.fasterxml.jackson.databind.jsontype.TypeSerializer) throws java.io.IOException;
    descriptor: (Ljava/lang/Object;Lcom/fasterxml/jackson/core/JsonGenerator;Lcom/fasterxml/jackson/databind/SerializerProvider;Lcom/fasterxml/jackson/databind/jsontype/TypeSerializer;)V
    flags: (0x0011) ACC_PUBLIC, ACC_FINAL
    Code:
      stack=5, locals=6, args_size=5
         0: aload         4
         2: aload_2
         3: aload         4
         5: aload_1
         6: getstatic     #17                 // Field com/fasterxml/jackson/core/JsonToken.START_ARRAY:Lcom/fasterxml/jackson/core/JsonToken;
         9: invokevirtual #18                 // Method com/fasterxml/jackson/databind/jsontype/TypeSerializer.typeId:(Ljava/lang/Object;Lcom/fasterxml/jackson/core/JsonToken;)Lcom/fasterxml/jackson/core/type/WritableTypeId;
        12: invokevirtual #19                 // Method com/fasterxml/jackson/databind/jsontype/TypeSerializer.writeTypePrefix:(Lcom/fasterxml/jackson/core/JsonGenerator;Lcom/fasterxml/jackson/core/type/WritableTypeId;)Lcom/fasterxml/jackson/core/type/WritableTypeId;
        15: astore        5
        17: aload_2
        18: aload_1
        19: invokevirtual #20                 // Method com/fasterxml/jackson/core/JsonGenerator.setCurrentValue:(Ljava/lang/Object;)V
        22: aload_0
        23: aload_1
        24: aload_2
        25: aload_3
        26: invokevirtual #14                 // Method serializeContents:(Ljava/lang/Object;Lcom/fasterxml/jackson/core/JsonGenerator;Lcom/fasterxml/jackson/databind/SerializerProvider;)V
        29: aload         4
        31: aload_2
        32: aload         5
        34: invokevirtual #21                 // Method com/fasterxml/jackson/databind/jsontype/TypeSerializer.writeTypeSuffix:(Lcom/fasterxml/jackson/core/JsonGenerator;Lcom/fasterxml/jackson/core/type/WritableTypeId;)Lcom/fasterxml/jackson/core/type/WritableTypeId;
        37: pop
        38: return
      LineNumberTable:
        line 134: 0
        line 135: 9
        line 134: 12
        line 137: 17
        line 138: 22
        line 139: 29
        line 140: 38
      LocalVariableTable:
        Start  Length  Slot  Name   Signature
            0      39     0  this   Lcom/fasterxml/jackson/databind/ser/std/ArraySerializerBase;
            0      39     1 value   Ljava/lang/Object;
            0      39     2     g   Lcom/fasterxml/jackson/core/JsonGenerator;
            0      39     3 provider   Lcom/fasterxml/jackson/databind/SerializerProvider;
            0      39     4 typeSer   Lcom/fasterxml/jackson/databind/jsontype/TypeSerializer;
           17      22     5 typeIdDef   Lcom/fasterxml/jackson/core/type/WritableTypeId;
      LocalVariableTypeTable:
        Start  Length  Slot  Name   Signature
            0      39     0  this   Lcom/fasterxml/jackson/databind/ser/std/ArraySerializerBase<TT;>;
            0      39     1 value   TT;
    Exceptions:
      throws java.io.IOException
    Signature: #95                          // (TT;Lcom/fasterxml/jackson/core/JsonGenerator;Lcom/fasterxml/jackson/databind/SerializerProvider;Lcom/fasterxml/jackson/databind/jsontype/TypeSerializer;)V

  protected abstract void serializeContents(T, com.fasterxml.jackson.core.JsonGenerator, com.fasterxml.jackson.databind.SerializerProvider) throws java.io.IOException;
    descriptor: (Ljava/lang/Object;Lcom/fasterxml/jackson/core/JsonGenerator;Lcom/fasterxml/jackson/databind/SerializerProvider;)V
    flags: (0x0404) ACC_PROTECTED, ACC_ABSTRACT
    Exceptions:
      throws java.io.IOException
    Signature: #87                          // (TT;Lcom/fasterxml/jackson/core/JsonGenerator;Lcom/fasterxml/jackson/databind/SerializerProvider;)V

  protected final boolean _shouldUnwrapSingle(com.fasterxml.jackson.databind.SerializerProvider);
    descriptor: (Lcom/fasterxml/jackson/databind/SerializerProvider;)Z
    flags: (0x0014) ACC_PROTECTED, ACC_FINAL
    Code:
      stack=2, locals=2, args_size=2
         0: aload_0
         1: getfield      #3                  // Field _unwrapSingle:Ljava/lang/Boolean;
         4: ifnonnull     15
         7: aload_1
         8: getstatic     #22                 // Field com/fasterxml/jackson/databind/SerializationFeature.WRITE_SINGLE_ELEM_ARRAYS_UNWRAPPED:Lcom/fasterxml/jackson/databind/SerializationFeature;
        11: invokevirtual #23                 // Method com/fasterxml/jackson/databind/SerializerProvider.isEnabled:(Lcom/fasterxml/jackson/databind/SerializationFeature;)Z
        14: ireturn
        15: aload_0
        16: getfield      #3                  // Field _unwrapSingle:Ljava/lang/Boolean;
        19: invokevirtual #24                 // Method java/lang/Boolean.booleanValue:()Z
        22: ireturn
      LineNumberTable:
        line 149: 0
        line 150: 7
        line 152: 15
      LocalVariableTable:
        Start  Length  Slot  Name   Signature
            0      23     0  this   Lcom/fasterxml/jackson/databind/ser/std/ArraySerializerBase;
            0      23     1 provider   Lcom/fasterxml/jackson/databind/SerializerProvider;
      LocalVariableTypeTable:
        Start  Length  Slot  Name   Signature
            0      23     0  this   Lcom/fasterxml/jackson/databind/ser/std/ArraySerializerBase<TT;>;
      StackMapTable: number_of_entries = 1
        frame_type = 15 /* same */
}
Signature: #99                          // <T:Ljava/lang/Object;>Lcom/fasterxml/jackson/databind/ser/ContainerSerializer<TT;>;Lcom/fasterxml/jackson/databind/ser/ContextualSerializer;
SourceFile: "ArraySerializerBase.java"
InnerClasses:
  public static #68= #67 of #137;         // Value=class com/fasterxml/jackson/annotation/JsonFormat$Value of class com/fasterxml/jackson/annotation/JsonFormat
  public static final #149= #109 of #137; // Feature=class com/fasterxml/jackson/annotation/JsonFormat$Feature of class com/fasterxml/jackson/annotation/JsonFormat
