Classfile /Users/mw/Projects/slang-braindump/.jar/jar11/assemble/slang-braindump/assemble/content/com/fasterxml/jackson/databind/ser/std/ToStringSerializerBase.class
  Last modified May 29, 2022; size 3347 bytes
  SHA-256 checksum f4b354000075a07d8d9425a9fa95e2e45a4a35e4f13fc951882d9d640c486253
  Compiled from "ToStringSerializerBase.java"
public abstract class com.fasterxml.jackson.databind.ser.std.ToStringSerializerBase extends com.fasterxml.jackson.databind.ser.std.StdSerializer<java.lang.Object>
  minor version: 0
  major version: 52
  flags: (0x0421) ACC_PUBLIC, ACC_SUPER, ACC_ABSTRACT
  this_class: #13                         // com/fasterxml/jackson/databind/ser/std/ToStringSerializerBase
  super_class: #14                        // com/fasterxml/jackson/databind/ser/std/StdSerializer
  interfaces: 0, fields: 0, methods: 7, attributes: 2
Constant pool:
    #1 = Methodref          #14.#63       // com/fasterxml/jackson/databind/ser/std/StdSerializer."<init>":(Ljava/lang/Class;Z)V
    #2 = Methodref          #13.#64       // com/fasterxml/jackson/databind/ser/std/ToStringSerializerBase.valueToString:(Ljava/lang/Object;)Ljava/lang/String;
    #3 = Methodref          #65.#66       // java/lang/String.isEmpty:()Z
    #4 = Methodref          #67.#68       // com/fasterxml/jackson/core/JsonGenerator.writeString:(Ljava/lang/String;)V
    #5 = Fieldref           #69.#70       // com/fasterxml/jackson/core/JsonToken.VALUE_STRING:Lcom/fasterxml/jackson/core/JsonToken;
    #6 = Methodref          #71.#72       // com/fasterxml/jackson/databind/jsontype/TypeSerializer.typeId:(Ljava/lang/Object;Lcom/fasterxml/jackson/core/JsonToken;)Lcom/fasterxml/jackson/core/type/WritableTypeId;
    #7 = Methodref          #71.#73       // com/fasterxml/jackson/databind/jsontype/TypeSerializer.writeTypePrefix:(Lcom/fasterxml/jackson/core/JsonGenerator;Lcom/fasterxml/jackson/core/type/WritableTypeId;)Lcom/fasterxml/jackson/core/type/WritableTypeId;
    #8 = Methodref          #13.#74       // com/fasterxml/jackson/databind/ser/std/ToStringSerializerBase.serialize:(Ljava/lang/Object;Lcom/fasterxml/jackson/core/JsonGenerator;Lcom/fasterxml/jackson/databind/SerializerProvider;)V
    #9 = Methodref          #71.#75       // com/fasterxml/jackson/databind/jsontype/TypeSerializer.writeTypeSuffix:(Lcom/fasterxml/jackson/core/JsonGenerator;Lcom/fasterxml/jackson/core/type/WritableTypeId;)Lcom/fasterxml/jackson/core/type/WritableTypeId;
   #10 = String             #76           // string
   #11 = Methodref          #13.#77       // com/fasterxml/jackson/databind/ser/std/ToStringSerializerBase.createSchemaNode:(Ljava/lang/String;Z)Lcom/fasterxml/jackson/databind/node/ObjectNode;
   #12 = Methodref          #13.#78       // com/fasterxml/jackson/databind/ser/std/ToStringSerializerBase.visitStringFormat:(Lcom/fasterxml/jackson/databind/jsonFormatVisitors/JsonFormatVisitorWrapper;Lcom/fasterxml/jackson/databind/JavaType;)V
   #13 = Class              #79           // com/fasterxml/jackson/databind/ser/std/ToStringSerializerBase
   #14 = Class              #80           // com/fasterxml/jackson/databind/ser/std/StdSerializer
   #15 = Utf8               <init>
   #16 = Utf8               (Ljava/lang/Class;)V
   #17 = Utf8               Code
   #18 = Utf8               LineNumberTable
   #19 = Utf8               LocalVariableTable
   #20 = Utf8               this
   #21 = Utf8               Lcom/fasterxml/jackson/databind/ser/std/ToStringSerializerBase;
   #22 = Utf8               handledType
   #23 = Utf8               Ljava/lang/Class;
   #24 = Utf8               LocalVariableTypeTable
   #25 = Utf8               Ljava/lang/Class<*>;
   #26 = Utf8               Signature
   #27 = Utf8               (Ljava/lang/Class<*>;)V
   #28 = Utf8               isEmpty
   #29 = Utf8               (Lcom/fasterxml/jackson/databind/SerializerProvider;Ljava/lang/Object;)Z
   #30 = Utf8               prov
   #31 = Utf8               Lcom/fasterxml/jackson/databind/SerializerProvider;
   #32 = Utf8               value
   #33 = Utf8               Ljava/lang/Object;
   #34 = Utf8               serialize
   #35 = Utf8               (Ljava/lang/Object;Lcom/fasterxml/jackson/core/JsonGenerator;Lcom/fasterxml/jackson/databind/SerializerProvider;)V
   #36 = Utf8               gen
   #37 = Utf8               Lcom/fasterxml/jackson/core/JsonGenerator;
   #38 = Utf8               provider
   #39 = Utf8               Exceptions
   #40 = Class              #81           // java/io/IOException
   #41 = Utf8               serializeWithType
   #42 = Utf8               (Ljava/lang/Object;Lcom/fasterxml/jackson/core/JsonGenerator;Lcom/fasterxml/jackson/databind/SerializerProvider;Lcom/fasterxml/jackson/databind/jsontype/TypeSerializer;)V
   #43 = Utf8               g
   #44 = Utf8               typeSer
   #45 = Utf8               Lcom/fasterxml/jackson/databind/jsontype/TypeSerializer;
   #46 = Utf8               typeIdDef
   #47 = Utf8               Lcom/fasterxml/jackson/core/type/WritableTypeId;
   #48 = Utf8               getSchema
   #49 = Utf8               (Lcom/fasterxml/jackson/databind/SerializerProvider;Ljava/lang/reflect/Type;)Lcom/fasterxml/jackson/databind/JsonNode;
   #50 = Utf8               typeHint
   #51 = Utf8               Ljava/lang/reflect/Type;
   #52 = Class              #82           // com/fasterxml/jackson/databind/JsonMappingException
   #53 = Utf8               acceptJsonFormatVisitor
   #54 = Utf8               (Lcom/fasterxml/jackson/databind/jsonFormatVisitors/JsonFormatVisitorWrapper;Lcom/fasterxml/jackson/databind/JavaType;)V
   #55 = Utf8               visitor
   #56 = Utf8               Lcom/fasterxml/jackson/databind/jsonFormatVisitors/JsonFormatVisitorWrapper;
   #57 = Utf8               Lcom/fasterxml/jackson/databind/JavaType;
   #58 = Utf8               valueToString
   #59 = Utf8               (Ljava/lang/Object;)Ljava/lang/String;
   #60 = Utf8               Lcom/fasterxml/jackson/databind/ser/std/StdSerializer<Ljava/lang/Object;>;
   #61 = Utf8               SourceFile
   #62 = Utf8               ToStringSerializerBase.java
   #63 = NameAndType        #15:#83       // "<init>":(Ljava/lang/Class;Z)V
   #64 = NameAndType        #58:#59       // valueToString:(Ljava/lang/Object;)Ljava/lang/String;
   #65 = Class              #84           // java/lang/String
   #66 = NameAndType        #28:#85       // isEmpty:()Z
   #67 = Class              #86           // com/fasterxml/jackson/core/JsonGenerator
   #68 = NameAndType        #87:#88       // writeString:(Ljava/lang/String;)V
   #69 = Class              #89           // com/fasterxml/jackson/core/JsonToken
   #70 = NameAndType        #90:#91       // VALUE_STRING:Lcom/fasterxml/jackson/core/JsonToken;
   #71 = Class              #92           // com/fasterxml/jackson/databind/jsontype/TypeSerializer
   #72 = NameAndType        #93:#94       // typeId:(Ljava/lang/Object;Lcom/fasterxml/jackson/core/JsonToken;)Lcom/fasterxml/jackson/core/type/WritableTypeId;
   #73 = NameAndType        #95:#96       // writeTypePrefix:(Lcom/fasterxml/jackson/core/JsonGenerator;Lcom/fasterxml/jackson/core/type/WritableTypeId;)Lcom/fasterxml/jackson/core/type/WritableTypeId;
   #74 = NameAndType        #34:#35       // serialize:(Ljava/lang/Object;Lcom/fasterxml/jackson/core/JsonGenerator;Lcom/fasterxml/jackson/databind/SerializerProvider;)V
   #75 = NameAndType        #97:#96       // writeTypeSuffix:(Lcom/fasterxml/jackson/core/JsonGenerator;Lcom/fasterxml/jackson/core/type/WritableTypeId;)Lcom/fasterxml/jackson/core/type/WritableTypeId;
   #76 = Utf8               string
   #77 = NameAndType        #98:#99       // createSchemaNode:(Ljava/lang/String;Z)Lcom/fasterxml/jackson/databind/node/ObjectNode;
   #78 = NameAndType        #100:#54      // visitStringFormat:(Lcom/fasterxml/jackson/databind/jsonFormatVisitors/JsonFormatVisitorWrapper;Lcom/fasterxml/jackson/databind/JavaType;)V
   #79 = Utf8               com/fasterxml/jackson/databind/ser/std/ToStringSerializerBase
   #80 = Utf8               com/fasterxml/jackson/databind/ser/std/StdSerializer
   #81 = Utf8               java/io/IOException
   #82 = Utf8               com/fasterxml/jackson/databind/JsonMappingException
   #83 = Utf8               (Ljava/lang/Class;Z)V
   #84 = Utf8               java/lang/String
   #85 = Utf8               ()Z
   #86 = Utf8               com/fasterxml/jackson/core/JsonGenerator
   #87 = Utf8               writeString
   #88 = Utf8               (Ljava/lang/String;)V
   #89 = Utf8               com/fasterxml/jackson/core/JsonToken
   #90 = Utf8               VALUE_STRING
   #91 = Utf8               Lcom/fasterxml/jackson/core/JsonToken;
   #92 = Utf8               com/fasterxml/jackson/databind/jsontype/TypeSerializer
   #93 = Utf8               typeId
   #94 = Utf8               (Ljava/lang/Object;Lcom/fasterxml/jackson/core/JsonToken;)Lcom/fasterxml/jackson/core/type/WritableTypeId;
   #95 = Utf8               writeTypePrefix
   #96 = Utf8               (Lcom/fasterxml/jackson/core/JsonGenerator;Lcom/fasterxml/jackson/core/type/WritableTypeId;)Lcom/fasterxml/jackson/core/type/WritableTypeId;
   #97 = Utf8               writeTypeSuffix
   #98 = Utf8               createSchemaNode
   #99 = Utf8               (Ljava/lang/String;Z)Lcom/fasterxml/jackson/databind/node/ObjectNode;
  #100 = Utf8               visitStringFormat
{
  public com.fasterxml.jackson.databind.ser.std.ToStringSerializerBase(java.lang.Class<?>);
    descriptor: (Ljava/lang/Class;)V
    flags: (0x0001) ACC_PUBLIC
    Code:
      stack=3, locals=2, args_size=2
         0: aload_0
         1: aload_1
         2: iconst_0
         3: invokespecial #1                  // Method com/fasterxml/jackson/databind/ser/std/StdSerializer."<init>":(Ljava/lang/Class;Z)V
         6: return
      LineNumberTable:
        line 29: 0
        line 30: 6
      LocalVariableTable:
        Start  Length  Slot  Name   Signature
            0       7     0  this   Lcom/fasterxml/jackson/databind/ser/std/ToStringSerializerBase;
            0       7     1 handledType   Ljava/lang/Class;
      LocalVariableTypeTable:
        Start  Length  Slot  Name   Signature
            0       7     1 handledType   Ljava/lang/Class<*>;
    Signature: #27                          // (Ljava/lang/Class<*>;)V

  public boolean isEmpty(com.fasterxml.jackson.databind.SerializerProvider, java.lang.Object);
    descriptor: (Lcom/fasterxml/jackson/databind/SerializerProvider;Ljava/lang/Object;)Z
    flags: (0x0001) ACC_PUBLIC
    Code:
      stack=2, locals=3, args_size=3
         0: aload_0
         1: aload_2
         2: invokevirtual #2                  // Method valueToString:(Ljava/lang/Object;)Ljava/lang/String;
         5: invokevirtual #3                  // Method java/lang/String.isEmpty:()Z
         8: ireturn
      LineNumberTable:
        line 34: 0
      LocalVariableTable:
        Start  Length  Slot  Name   Signature
            0       9     0  this   Lcom/fasterxml/jackson/databind/ser/std/ToStringSerializerBase;
            0       9     1  prov   Lcom/fasterxml/jackson/databind/SerializerProvider;
            0       9     2 value   Ljava/lang/Object;

  public void serialize(java.lang.Object, com.fasterxml.jackson.core.JsonGenerator, com.fasterxml.jackson.databind.SerializerProvider) throws java.io.IOException;
    descriptor: (Ljava/lang/Object;Lcom/fasterxml/jackson/core/JsonGenerator;Lcom/fasterxml/jackson/databind/SerializerProvider;)V
    flags: (0x0001) ACC_PUBLIC
    Code:
      stack=3, locals=4, args_size=4
         0: aload_2
         1: aload_0
         2: aload_1
         3: invokevirtual #2                  // Method valueToString:(Ljava/lang/Object;)Ljava/lang/String;
         6: invokevirtual #4                  // Method com/fasterxml/jackson/core/JsonGenerator.writeString:(Ljava/lang/String;)V
         9: return
      LineNumberTable:
        line 41: 0
        line 42: 9
      LocalVariableTable:
        Start  Length  Slot  Name   Signature
            0      10     0  this   Lcom/fasterxml/jackson/databind/ser/std/ToStringSerializerBase;
            0      10     1 value   Ljava/lang/Object;
            0      10     2   gen   Lcom/fasterxml/jackson/core/JsonGenerator;
            0      10     3 provider   Lcom/fasterxml/jackson/databind/SerializerProvider;
    Exceptions:
      throws java.io.IOException

  public void serializeWithType(java.lang.Object, com.fasterxml.jackson.core.JsonGenerator, com.fasterxml.jackson.databind.SerializerProvider, com.fasterxml.jackson.databind.jsontype.TypeSerializer) throws java.io.IOException;
    descriptor: (Ljava/lang/Object;Lcom/fasterxml/jackson/core/JsonGenerator;Lcom/fasterxml/jackson/databind/SerializerProvider;Lcom/fasterxml/jackson/databind/jsontype/TypeSerializer;)V
    flags: (0x0001) ACC_PUBLIC
    Code:
      stack=5, locals=6, args_size=5
         0: aload         4
         2: aload_2
         3: aload         4
         5: aload_1
         6: getstatic     #5                  // Field com/fasterxml/jackson/core/JsonToken.VALUE_STRING:Lcom/fasterxml/jackson/core/JsonToken;
         9: invokevirtual #6                  // Method com/fasterxml/jackson/databind/jsontype/TypeSerializer.typeId:(Ljava/lang/Object;Lcom/fasterxml/jackson/core/JsonToken;)Lcom/fasterxml/jackson/core/type/WritableTypeId;
        12: invokevirtual #7                  // Method com/fasterxml/jackson/databind/jsontype/TypeSerializer.writeTypePrefix:(Lcom/fasterxml/jackson/core/JsonGenerator;Lcom/fasterxml/jackson/core/type/WritableTypeId;)Lcom/fasterxml/jackson/core/type/WritableTypeId;
        15: astore        5
        17: aload_0
        18: aload_1
        19: aload_2
        20: aload_3
        21: invokevirtual #8                  // Method serialize:(Ljava/lang/Object;Lcom/fasterxml/jackson/core/JsonGenerator;Lcom/fasterxml/jackson/databind/SerializerProvider;)V
        24: aload         4
        26: aload_2
        27: aload         5
        29: invokevirtual #9                  // Method com/fasterxml/jackson/databind/jsontype/TypeSerializer.writeTypeSuffix:(Lcom/fasterxml/jackson/core/JsonGenerator;Lcom/fasterxml/jackson/core/type/WritableTypeId;)Lcom/fasterxml/jackson/core/type/WritableTypeId;
        32: pop
        33: return
      LineNumberTable:
        line 56: 0
        line 57: 9
        line 56: 12
        line 58: 17
        line 59: 24
        line 60: 33
      LocalVariableTable:
        Start  Length  Slot  Name   Signature
            0      34     0  this   Lcom/fasterxml/jackson/databind/ser/std/ToStringSerializerBase;
            0      34     1 value   Ljava/lang/Object;
            0      34     2     g   Lcom/fasterxml/jackson/core/JsonGenerator;
            0      34     3 provider   Lcom/fasterxml/jackson/databind/SerializerProvider;
            0      34     4 typeSer   Lcom/fasterxml/jackson/databind/jsontype/TypeSerializer;
           17      17     5 typeIdDef   Lcom/fasterxml/jackson/core/type/WritableTypeId;
    Exceptions:
      throws java.io.IOException

  public com.fasterxml.jackson.databind.JsonNode getSchema(com.fasterxml.jackson.databind.SerializerProvider, java.lang.reflect.Type) throws com.fasterxml.jackson.databind.JsonMappingException;
    descriptor: (Lcom/fasterxml/jackson/databind/SerializerProvider;Ljava/lang/reflect/Type;)Lcom/fasterxml/jackson/databind/JsonNode;
    flags: (0x0001) ACC_PUBLIC
    Code:
      stack=3, locals=3, args_size=3
         0: aload_0
         1: ldc           #10                 // String string
         3: iconst_1
         4: invokevirtual #11                 // Method createSchemaNode:(Ljava/lang/String;Z)Lcom/fasterxml/jackson/databind/node/ObjectNode;
         7: areturn
      LineNumberTable:
        line 64: 0
      LocalVariableTable:
        Start  Length  Slot  Name   Signature
            0       8     0  this   Lcom/fasterxml/jackson/databind/ser/std/ToStringSerializerBase;
            0       8     1 provider   Lcom/fasterxml/jackson/databind/SerializerProvider;
            0       8     2 typeHint   Ljava/lang/reflect/Type;
    Exceptions:
      throws com.fasterxml.jackson.databind.JsonMappingException

  public void acceptJsonFormatVisitor(com.fasterxml.jackson.databind.jsonFormatVisitors.JsonFormatVisitorWrapper, com.fasterxml.jackson.databind.JavaType) throws com.fasterxml.jackson.databind.JsonMappingException;
    descriptor: (Lcom/fasterxml/jackson/databind/jsonFormatVisitors/JsonFormatVisitorWrapper;Lcom/fasterxml/jackson/databind/JavaType;)V
    flags: (0x0001) ACC_PUBLIC
    Code:
      stack=3, locals=3, args_size=3
         0: aload_0
         1: aload_1
         2: aload_2
         3: invokevirtual #12                 // Method visitStringFormat:(Lcom/fasterxml/jackson/databind/jsonFormatVisitors/JsonFormatVisitorWrapper;Lcom/fasterxml/jackson/databind/JavaType;)V
         6: return
      LineNumberTable:
        line 70: 0
        line 71: 6
      LocalVariableTable:
        Start  Length  Slot  Name   Signature
            0       7     0  this   Lcom/fasterxml/jackson/databind/ser/std/ToStringSerializerBase;
            0       7     1 visitor   Lcom/fasterxml/jackson/databind/jsonFormatVisitors/JsonFormatVisitorWrapper;
            0       7     2 typeHint   Lcom/fasterxml/jackson/databind/JavaType;
    Exceptions:
      throws com.fasterxml.jackson.databind.JsonMappingException

  public abstract java.lang.String valueToString(java.lang.Object);
    descriptor: (Ljava/lang/Object;)Ljava/lang/String;
    flags: (0x0401) ACC_PUBLIC, ACC_ABSTRACT
}
Signature: #60                          // Lcom/fasterxml/jackson/databind/ser/std/StdSerializer<Ljava/lang/Object;>;
SourceFile: "ToStringSerializerBase.java"
