Classfile /Users/mw/Projects/slang-braindump/.jar/jar11/assemble/slang-braindump/assemble/content/os/Internals.class
  Last modified May 29, 2022; size 1268 bytes
  SHA-256 checksum d802f55c1aea7ddb62e72b7744d73e0076b6a48da97055c840fa5d4dacd432a0
  Compiled from "Internals.scala"
public final class os.Internals
  minor version: 0
  major version: 52
  flags: (0x0031) ACC_PUBLIC, ACC_FINAL, ACC_SUPER
  this_class: #2                          // os/Internals
  super_class: #4                         // java/lang/Object
  interfaces: 0, fields: 0, methods: 3, attributes: 3
Constant pool:
   #1 = Utf8               os/Internals
   #2 = Class              #1             // os/Internals
   #3 = Utf8               java/lang/Object
   #4 = Class              #3             // java/lang/Object
   #5 = Utf8               Internals.scala
   #6 = Utf8               Lscala/reflect/ScalaSignature;
   #7 = Utf8               bytes
   #8 = Utf8               \u0006\u0005-;Qa\u0002\u0005\t\u0002-1Q!\u0004\u0005\t\u00029AQ!F\u0001\u0005\u0002YAqaF\u0001C\u0002\u0013\u0005\u0001\u0004\u0003\u0004(\u0003\u0001\u0006I!\u0007\u0005\u0006Q\u0005!\t!\u000b\u0005\u0006\u0007\u0006!\t\u0001R\u0001\n\u0013:$XM\u001d8bYNT\u0011!C\u0001\u0003_N\u001c\u0001\u0001\u0005\u0002\r\u00035\t\u0001BA\u0005J]R,\'O\\1mgN\u0011\u0011a\u0004\t\u0003!Mi\u0011!\u0005\u0006\u0002%\u0005)1oY1mC&\u0011A#\u0005\u0002\u0007\u0003:L(+\u001a4\u0002\rqJg.\u001b;?)\u0005Y\u0011\u0001E3naRL8\u000b\u001e:j]\u001e\f%O]1z+\u0005I\u0002c\u0001\t\u001b9%\u00111$\u0005\u0002\u0006\u0003J\u0014\u0018-\u001f\t\u0003;\u0011r!A\b\u0012\u0011\u0005}\tR\"\u0001\u0011\u000b\u0005\u0005R\u0011A\u0002\u001fs_>$h(\u0003\u0002$#\u00051\u0001K]3eK\u001aL!!\n\u0014\u0003\rM#(/\u001b8h\u0015\t\u0019\u0013#A\tf[B$\u0018p\u0015;sS:<\u0017I\u001d:bs\u0002\n\u0011\u0002\u001e:b]N4WM\u001d\u0019\u0015\u0007)js\u0007\u0005\u0002\u0011W%\u0011A&\u0005\u0002\u0005+:LG\u000fC\u0003/\u000b\u0001\u0007q&A\u0002te\u000e\u0004\"\u0001M\u001b\u000e\u0003ER!AM\u001a\u0002\u0005%|\'\"\u0001\u001b\u0002\t)\fg/Y\u0005\u0003mE\u00121\"\u00138qkR\u001cFO]3b[\")\u0001(\u0002a\u0001s\u0005!1/\u001b8l!\u0015\u0001\"\b\u0010!+\u0013\tY\u0014CA\u0005Gk:\u001cG/[8oeA\u0019\u0001CG\u001f\u0011\u0005Aq\u0014BA \u0012\u0005\u0011\u0011\u0015\u0010^3\u0011\u0005A\t\u0015B\u0001\"\u0012\u0005\rIe\u000e^\u0001\tiJ\fgn\u001d4feR\u0019!&\u0012$\t\u000b92\u0001\u0019A\u0018\t\u000b\u001d3\u0001\u0019\u0001%\u0002\t\u0011,7\u000f\u001e\t\u0003a%K!AS\u0019\u0003\u0019=+H\u000f];u\'R\u0014X-Y7
   #9 = Utf8               transfer
  #10 = Utf8               (Ljava/io/InputStream;Ljava/io/OutputStream;)V
  #11 = Utf8               src
  #12 = Utf8               dest
  #13 = Utf8               os/Internals$
  #14 = Class              #13            // os/Internals$
  #15 = Utf8               MODULE$
  #16 = Utf8               Los/Internals$;
  #17 = NameAndType        #15:#16        // MODULE$:Los/Internals$;
  #18 = Fieldref           #14.#17        // os/Internals$.MODULE$:Los/Internals$;
  #19 = NameAndType        #9:#10         // transfer:(Ljava/io/InputStream;Ljava/io/OutputStream;)V
  #20 = Methodref          #14.#19        // os/Internals$.transfer:(Ljava/io/InputStream;Ljava/io/OutputStream;)V
  #21 = Utf8               transfer0
  #22 = Utf8               (Ljava/io/InputStream;Lscala/Function2;)V
  #23 = Utf8               (Ljava/io/InputStream;Lscala/Function2<[BLjava/lang/Object;Lscala/runtime/BoxedUnit;>;)V
  #24 = Utf8               sink
  #25 = NameAndType        #21:#22        // transfer0:(Ljava/io/InputStream;Lscala/Function2;)V
  #26 = Methodref          #14.#25        // os/Internals$.transfer0:(Ljava/io/InputStream;Lscala/Function2;)V
  #27 = Utf8               emptyStringArray
  #28 = Utf8               ()[Ljava/lang/String;
  #29 = NameAndType        #27:#28        // emptyStringArray:()[Ljava/lang/String;
  #30 = Methodref          #14.#29        // os/Internals$.emptyStringArray:()[Ljava/lang/String;
  #31 = Utf8               Code
  #32 = Utf8               MethodParameters
  #33 = Utf8               Signature
  #34 = Utf8               SourceFile
  #35 = Utf8               RuntimeVisibleAnnotations
  #36 = Utf8               ScalaSig
{
  public static void transfer(java.io.InputStream, java.io.OutputStream);
    descriptor: (Ljava/io/InputStream;Ljava/io/OutputStream;)V
    flags: (0x0009) ACC_PUBLIC, ACC_STATIC
    Code:
      stack=3, locals=2, args_size=2
         0: getstatic     #18                 // Field os/Internals$.MODULE$:Los/Internals$;
         3: aload_0
         4: aload_1
         5: invokevirtual #20                 // Method os/Internals$.transfer:(Ljava/io/InputStream;Ljava/io/OutputStream;)V
         8: return
    MethodParameters:
      Name                           Flags
      src                            final
      dest                           final

  public static void transfer0(java.io.InputStream, scala.Function2<byte[], java.lang.Object, scala.runtime.BoxedUnit>);
    descriptor: (Ljava/io/InputStream;Lscala/Function2;)V
    flags: (0x0009) ACC_PUBLIC, ACC_STATIC
    Code:
      stack=3, locals=2, args_size=2
         0: getstatic     #18                 // Field os/Internals$.MODULE$:Los/Internals$;
         3: aload_0
         4: aload_1
         5: invokevirtual #26                 // Method os/Internals$.transfer0:(Ljava/io/InputStream;Lscala/Function2;)V
         8: return
    Signature: #23                          // (Ljava/io/InputStream;Lscala/Function2<[BLjava/lang/Object;Lscala/runtime/BoxedUnit;>;)V
    MethodParameters:
      Name                           Flags
      src                            final
      sink                           final

  public static java.lang.String[] emptyStringArray();
    descriptor: ()[Ljava/lang/String;
    flags: (0x0009) ACC_PUBLIC, ACC_STATIC
    Code:
      stack=1, locals=0, args_size=0
         0: getstatic     #18                 // Field os/Internals$.MODULE$:Los/Internals$;
         3: invokevirtual #30                 // Method os/Internals$.emptyStringArray:()[Ljava/lang/String;
         6: areturn
}
SourceFile: "Internals.scala"
RuntimeVisibleAnnotations:
  0: #6(#7=s#8)
    scala.reflect.ScalaSignature(
      bytes="\u0006\u0005-;Qa\u0002\u0005\t\u0002-1Q!\u0004\u0005\t\u00029AQ!F\u0001\u0005\u0002YAqaF\u0001C\u0002\u0013\u0005\u0001\u0004\u0003\u0004(\u0003\u0001\u0006I!\u0007\u0005\u0006Q\u0005!\t!\u000b\u0005\u0006\u0007\u0006!\t\u0001R\u0001\n\u0013:$XM\u001d8bYNT\u0011!C\u0001\u0003_N\u001c\u0001\u0001\u0005\u0002\r\u00035\t\u0001BA\u0005J]R,\'O\\1mgN\u0011\u0011a\u0004\t\u0003!Mi\u0011!\u0005\u0006\u0002%\u0005)1oY1mC&\u0011A#\u0005\u0002\u0007\u0003:L(+\u001a4\u0002\rqJg.\u001b;?)\u0005Y\u0011\u0001E3naRL8\u000b\u001e:j]\u001e\f%O]1z+\u0005I\u0002c\u0001\t\u001b9%\u00111$\u0005\u0002\u0006\u0003J\u0014\u0018-\u001f\t\u0003;\u0011r!A\b\u0012\u0011\u0005}\tR\"\u0001\u0011\u000b\u0005\u0005R\u0011A\u0002\u001fs_>$h(\u0003\u0002$#\u00051\u0001K]3eK\u001aL!!\n\u0014\u0003\rM#(/\u001b8h\u0015\t\u0019\u0013#A\tf[B$\u0018p\u0015;sS:<\u0017I\u001d:bs\u0002\n\u0011\u0002\u001e:b]N4WM\u001d\u0019\u0015\u0007)js\u0007\u0005\u0002\u0011W%\u0011A&\u0005\u0002\u0005+:LG\u000fC\u0003/\u000b\u0001\u0007q&A\u0002te\u000e\u0004\"\u0001M\u001b\u000e\u0003ER!AM\u001a\u0002\u0005%|\'\"\u0001\u001b\u0002\t)\fg/Y\u0005\u0003mE\u00121\"\u00138qkR\u001cFO]3b[\")\u0001(\u0002a\u0001s\u0005!1/\u001b8l!\u0015\u0001\"\b\u0010!+\u0013\tY\u0014CA\u0005Gk:\u001cG/[8oeA\u0019\u0001CG\u001f\u0011\u0005Aq\u0014BA \u0012\u0005\u0011\u0011\u0015\u0010^3\u0011\u0005A\t\u0015B\u0001\"\u0012\u0005\rIe\u000e^\u0001\tiJ\fgn\u001d4feR\u0019!&\u0012$\t\u000b92\u0001\u0019A\u0018\t\u000b\u001d3\u0001\u0019\u0001%\u0002\t\u0011,7\u000f\u001e\t\u0003a%K!AS\u0019\u0003\u0019=+H\u000f];u\'R\u0014X-Y7"
    )
  ScalaSig: length = 0x3 (unknown attribute)
   05 02 00
