Classfile /Users/mw/Projects/slang-braindump/.jar/jar11/assemble/slang-braindump/assemble/content/os/list.class
  Last modified May 29, 2022; size 1869 bytes
  SHA-256 checksum 68652b2a8003a0c906c546ee475b4219bfb23cf7492584b76bb0de6038208bc8
  Compiled from "ListOps.scala"
public final class os.list
  minor version: 0
  major version: 52
  flags: (0x0031) ACC_PUBLIC, ACC_FINAL, ACC_SUPER
  this_class: #2                          // os/list
  super_class: #4                         // java/lang/Object
  interfaces: 0, fields: 0, methods: 6, attributes: 4
Constant pool:
   #1 = Utf8               os/list
   #2 = Class              #1             // os/list
   #3 = Utf8               java/lang/Object
   #4 = Class              #3             // java/lang/Object
   #5 = Utf8               ListOps.scala
   #6 = Utf8               Lscala/reflect/ScalaSignature;
   #7 = Utf8               bytes
   #8 = Utf8               \u0006\u0005\u0001<QAC\u0006\t\u000291Q\u0001E\u0006\t\u0002EAQAK\u0001\u0005\u0002-BQ\u0001L\u0001\u0005\u00025Bq\u0001O\u0001\u0012\u0002\u0013\u0005\u0011\bC\u0003-\u0003\u0011\u0005AiB\u0003I\u0003!\u0005\u0011JB\u0003L\u0003!\u0005A\nC\u0003+\u000f\u0011\u0005A\u000bC\u0003-\u000f\u0011\u0005Q+\u0001\u0003mSN$(\"\u0001\u0007\u0002\u0005=\u001c8\u0001\u0001\t\u0003\u001f\u0005i\u0011a\u0003\u0002\u0005Y&\u001cHoE\u0002\u0002%a\u0001\"a\u0005\f\u000e\u0003QQ\u0011!F\u0001\u0006g\u000e\fG.Y\u0005\u0003/Q\u0011a!\u00118z%\u00164\u0007\u0003B\n\u001a7yI!A\u0007\u000b\u0003\u0013\u0019+hn\u0019;j_:\f\u0004CA\b\u001d\u0013\ti2B\u0001\u0003QCRD\u0007cA\u0010(79\u0011\u0001%\n\b\u0003C\u0011j\u0011A\t\u0006\u0003G5\ta\u0001\u0010:p_Rt\u0014\"A\u000b\n\u0005\u0019\"\u0012a\u00029bG.\fw-Z\u0005\u0003Q%\u0012!\"\u00138eKb,GmU3r\u0015\t1C#\u0001\u0004=S:LGO\u0010\u000b\u0002\u001d\u0005)\u0011\r\u001d9msR\u0019a&M\u001a\u0011\u0007My3$\u0003\u00021)\t)\u0011I\u001d:bs\")!g\u0001a\u00017\u0005\u00191O]2\t\u000fQ\u001a\u0001\u0013!a\u0001k\u0005!1o\u001c:u!\t\u0019b\'\u0003\u00028)\t9!i\\8mK\u0006t\u0017aD1qa2LH\u0005Z3gCVdG\u000f\n\u001a\u0016\u0003iR#!N\u001e,\u0003q\u0002\"!\u0010\"\u000e\u0003yR!a\u0010!\u0002\u0013Ut7\r[3dW\u0016$\'BA!\u0015\u0003)\tgN\\8uCRLwN\\\u0005\u0003\u0007z\u0012\u0011#\u001e8dQ\u0016\u001c7.\u001a3WCJL\u0017M\\2f)\t)u\tE\u0002GOmq!aE\u0013\t\u000bI*\u0001\u0019A\u000e\u0002\rM$(/Z1n!\tQu!D\u0001\u0002\u0005\u0019\u0019HO]3b[N\u0019qAE\'\u0011\tMI2D\u0014\t\u0004\u001fJ[R\"\u0001)\u000b\u0003E\u000bAaZ3os&\u00111\u000b\u0015\u0002\n\u000f\u0016tWM]1u_J$\u0012!\u0013\u000b\u0003-z\u00132a\u0016\nZ\r\u0011A\u0016\u0002\u0001,\u0003\u0019q\u0012XMZ5oK6,g\u000e\u001e \u0011\u0007ic6D\u0004\u0002\u00107&\u0011aeC\u0005\u0003\'vS!AJ\u0006\t\u000b}K\u0001\u0019A\u000e\u0002\u0007\u0005\u0014x\r
   #9 = Utf8               os/list$stream$
  #10 = Class              #9             // os/list$stream$
  #11 = Utf8               stream$
  #12 = Utf8               apply
  #13 = Utf8               (Los/Path;)Lscala/collection/immutable/IndexedSeq;
  #14 = Utf8               (Los/Path;)Lscala/collection/immutable/IndexedSeq<Los/Path;>;
  #15 = Utf8               src
  #16 = Utf8               os/list$
  #17 = Class              #16            // os/list$
  #18 = Utf8               MODULE$
  #19 = Utf8               Los/list$;
  #20 = NameAndType        #18:#19        // MODULE$:Los/list$;
  #21 = Fieldref           #17.#20        // os/list$.MODULE$:Los/list$;
  #22 = NameAndType        #12:#13        // apply:(Los/Path;)Lscala/collection/immutable/IndexedSeq;
  #23 = Methodref          #17.#22        // os/list$.apply:(Los/Path;)Lscala/collection/immutable/IndexedSeq;
  #24 = Utf8               apply$default$2
  #25 = Utf8               ()Z
  #26 = NameAndType        #24:#25        // apply$default$2:()Z
  #27 = Methodref          #17.#26        // os/list$.apply$default$2:()Z
  #28 = Utf8               (Los/Path;Z)[Los/Path;
  #29 = Utf8               sort
  #30 = NameAndType        #12:#28        // apply:(Los/Path;Z)[Los/Path;
  #31 = Methodref          #17.#30        // os/list$.apply:(Los/Path;Z)[Los/Path;
  #32 = Utf8               toString
  #33 = Utf8               ()Ljava/lang/String;
  #34 = NameAndType        #32:#33        // toString:()Ljava/lang/String;
  #35 = Methodref          #17.#34        // os/list$.toString:()Ljava/lang/String;
  #36 = Utf8               andThen
  #37 = Utf8               (Lscala/Function1;)Lscala/Function1;
  #38 = Utf8               <A:Ljava/lang/Object;>(Lscala/Function1<Lscala/collection/immutable/IndexedSeq<Los/Path;>;TA;>;)Lscala/Function1<Los/Path;TA;>;
  #39 = Utf8               g
  #40 = NameAndType        #36:#37        // andThen:(Lscala/Function1;)Lscala/Function1;
  #41 = Methodref          #17.#40        // os/list$.andThen:(Lscala/Function1;)Lscala/Function1;
  #42 = Utf8               compose
  #43 = Utf8               <A:Ljava/lang/Object;>(Lscala/Function1<TA;Los/Path;>;)Lscala/Function1<TA;Lscala/collection/immutable/IndexedSeq<Los/Path;>;>;
  #44 = NameAndType        #42:#37        // compose:(Lscala/Function1;)Lscala/Function1;
  #45 = Methodref          #17.#44        // os/list$.compose:(Lscala/Function1;)Lscala/Function1;
  #46 = Utf8               Code
  #47 = Utf8               Signature
  #48 = Utf8               MethodParameters
  #49 = Utf8               InnerClasses
  #50 = Utf8               SourceFile
  #51 = Utf8               RuntimeVisibleAnnotations
  #52 = Utf8               ScalaSig
{
  public static scala.collection.immutable.IndexedSeq<os.Path> apply(os.Path);
    descriptor: (Los/Path;)Lscala/collection/immutable/IndexedSeq;
    flags: (0x0009) ACC_PUBLIC, ACC_STATIC
    Code:
      stack=2, locals=1, args_size=1
         0: getstatic     #21                 // Field os/list$.MODULE$:Los/list$;
         3: aload_0
         4: invokevirtual #23                 // Method os/list$.apply:(Los/Path;)Lscala/collection/immutable/IndexedSeq;
         7: areturn
    Signature: #14                          // (Los/Path;)Lscala/collection/immutable/IndexedSeq<Los/Path;>;
    MethodParameters:
      Name                           Flags
      src                            final

  public static boolean apply$default$2();
    descriptor: ()Z
    flags: (0x0009) ACC_PUBLIC, ACC_STATIC
    Code:
      stack=1, locals=0, args_size=0
         0: getstatic     #21                 // Field os/list$.MODULE$:Los/list$;
         3: invokevirtual #27                 // Method os/list$.apply$default$2:()Z
         6: ireturn

  public static os.Path[] apply(os.Path, boolean);
    descriptor: (Los/Path;Z)[Los/Path;
    flags: (0x0009) ACC_PUBLIC, ACC_STATIC
    Code:
      stack=3, locals=2, args_size=2
         0: getstatic     #21                 // Field os/list$.MODULE$:Los/list$;
         3: aload_0
         4: iload_1
         5: invokevirtual #31                 // Method os/list$.apply:(Los/Path;Z)[Los/Path;
         8: areturn
    MethodParameters:
      Name                           Flags
      src                            final
      sort                           final

  public static java.lang.String toString();
    descriptor: ()Ljava/lang/String;
    flags: (0x0009) ACC_PUBLIC, ACC_STATIC
    Code:
      stack=1, locals=0, args_size=0
         0: getstatic     #21                 // Field os/list$.MODULE$:Los/list$;
         3: invokevirtual #35                 // Method os/list$.toString:()Ljava/lang/String;
         6: areturn

  public static <A extends java.lang.Object> scala.Function1<os.Path, A> andThen(scala.Function1<scala.collection.immutable.IndexedSeq<os.Path>, A>);
    descriptor: (Lscala/Function1;)Lscala/Function1;
    flags: (0x0009) ACC_PUBLIC, ACC_STATIC
    Code:
      stack=2, locals=1, args_size=1
         0: getstatic     #21                 // Field os/list$.MODULE$:Los/list$;
         3: aload_0
         4: invokevirtual #41                 // Method os/list$.andThen:(Lscala/Function1;)Lscala/Function1;
         7: areturn
    Signature: #38                          // <A:Ljava/lang/Object;>(Lscala/Function1<Lscala/collection/immutable/IndexedSeq<Los/Path;>;TA;>;)Lscala/Function1<Los/Path;TA;>;
    MethodParameters:
      Name                           Flags
      g                              final

  public static <A extends java.lang.Object> scala.Function1<A, scala.collection.immutable.IndexedSeq<os.Path>> compose(scala.Function1<A, os.Path>);
    descriptor: (Lscala/Function1;)Lscala/Function1;
    flags: (0x0009) ACC_PUBLIC, ACC_STATIC
    Code:
      stack=2, locals=1, args_size=1
         0: getstatic     #21                 // Field os/list$.MODULE$:Los/list$;
         3: aload_0
         4: invokevirtual #45                 // Method os/list$.compose:(Lscala/Function1;)Lscala/Function1;
         7: areturn
    Signature: #43                          // <A:Ljava/lang/Object;>(Lscala/Function1<TA;Los/Path;>;)Lscala/Function1<TA;Lscala/collection/immutable/IndexedSeq<Los/Path;>;>;
    MethodParameters:
      Name                           Flags
      g                              final
}
InnerClasses:
  public static #11= #10 of #2;           // stream$=class os/list$stream$ of class os/list
SourceFile: "ListOps.scala"
RuntimeVisibleAnnotations:
  0: #6(#7=s#8)
    scala.reflect.ScalaSignature(
      bytes="\u0006\u0005\u0001<QAC\u0006\t\u000291Q\u0001E\u0006\t\u0002EAQAK\u0001\u0005\u0002-BQ\u0001L\u0001\u0005\u00025Bq\u0001O\u0001\u0012\u0002\u0013\u0005\u0011\bC\u0003-\u0003\u0011\u0005AiB\u0003I\u0003!\u0005\u0011JB\u0003L\u0003!\u0005A\nC\u0003+\u000f\u0011\u0005A\u000bC\u0003-\u000f\u0011\u0005Q+\u0001\u0003mSN$(\"\u0001\u0007\u0002\u0005=\u001c8\u0001\u0001\t\u0003\u001f\u0005i\u0011a\u0003\u0002\u0005Y&\u001cHoE\u0002\u0002%a\u0001\"a\u0005\f\u000e\u0003QQ\u0011!F\u0001\u0006g\u000e\fG.Y\u0005\u0003/Q\u0011a!\u00118z%\u00164\u0007\u0003B\n\u001a7yI!A\u0007\u000b\u0003\u0013\u0019+hn\u0019;j_:\f\u0004CA\b\u001d\u0013\ti2B\u0001\u0003QCRD\u0007cA\u0010(79\u0011\u0001%\n\b\u0003C\u0011j\u0011A\t\u0006\u0003G5\ta\u0001\u0010:p_Rt\u0014\"A\u000b\n\u0005\u0019\"\u0012a\u00029bG.\fw-Z\u0005\u0003Q%\u0012!\"\u00138eKb,GmU3r\u0015\t1C#\u0001\u0004=S:LGO\u0010\u000b\u0002\u001d\u0005)\u0011\r\u001d9msR\u0019a&M\u001a\u0011\u0007My3$\u0003\u00021)\t)\u0011I\u001d:bs\")!g\u0001a\u00017\u0005\u00191O]2\t\u000fQ\u001a\u0001\u0013!a\u0001k\u0005!1o\u001c:u!\t\u0019b\'\u0003\u00028)\t9!i\\8mK\u0006t\u0017aD1qa2LH\u0005Z3gCVdG\u000f\n\u001a\u0016\u0003iR#!N\u001e,\u0003q\u0002\"!\u0010\"\u000e\u0003yR!a\u0010!\u0002\u0013Ut7\r[3dW\u0016$\'BA!\u0015\u0003)\tgN\\8uCRLwN\\\u0005\u0003\u0007z\u0012\u0011#\u001e8dQ\u0016\u001c7.\u001a3WCJL\u0017M\\2f)\t)u\tE\u0002GOmq!aE\u0013\t\u000bI*\u0001\u0019A\u000e\u0002\rM$(/Z1n!\tQu!D\u0001\u0002\u0005\u0019\u0019HO]3b[N\u0019qAE\'\u0011\tMI2D\u0014\t\u0004\u001fJ[R\"\u0001)\u000b\u0003E\u000bAaZ3os&\u00111\u000b\u0015\u0002\n\u000f\u0016tWM]1u_J$\u0012!\u0013\u000b\u0003-z\u00132a\u0016\nZ\r\u0011A\u0016\u0002\u0001,\u0003\u0019q\u0012XMZ5oK6,g\u000e\u001e \u0011\u0007ic6D\u0004\u0002\u00107&\u0011aeC\u0005\u0003\'vS!AJ\u0006\t\u000b}K\u0001\u0019A\u000e\u0002\u0007\u0005\u0014x\r"
    )
  ScalaSig: length = 0x3 (unknown attribute)
   05 02 00
