Classfile /Users/mw/Projects/slang-braindump/.jar/jar11/assemble/slang-braindump/assemble/content/os/PathChunk$ArrayPathChunk.class
  Last modified May 29, 2022; size 1716 bytes
  SHA-256 checksum 917b47604547cb1b38d129fca20871caf069d709654bbd2b7e5837a4c1a2f8cf
  Compiled from "Path.scala"
public class os.PathChunk$ArrayPathChunk<T extends java.lang.Object> extends java.lang.Object implements os.PathChunk
  minor version: 0
  major version: 52
  flags: (0x0021) ACC_PUBLIC, ACC_SUPER
  this_class: #2                          // os/PathChunk$ArrayPathChunk
  super_class: #5                         // java/lang/Object
  interfaces: 1, fields: 1, methods: 5, attributes: 5
Constant pool:
   #1 = Utf8               os/PathChunk$ArrayPathChunk
   #2 = Class              #1             // os/PathChunk$ArrayPathChunk
   #3 = Utf8               <T:Ljava/lang/Object;>Ljava/lang/Object;Los/PathChunk;
   #4 = Utf8               java/lang/Object
   #5 = Class              #4             // java/lang/Object
   #6 = Utf8               os/PathChunk
   #7 = Class              #6             // os/PathChunk
   #8 = Utf8               Path.scala
   #9 = Utf8               ArrayPathChunk
  #10 = Utf8               os/PathChunk$SeqPathChunk
  #11 = Class              #10            // os/PathChunk$SeqPathChunk
  #12 = Utf8               SeqPathChunk
  #13 = Utf8               inner
  #14 = Utf8               Los/PathChunk$SeqPathChunk;
  #15 = Utf8               Los/PathChunk$SeqPathChunk<TT;>;
  #16 = Utf8               ()Los/PathChunk$SeqPathChunk;
  #17 = Utf8               ()Los/PathChunk$SeqPathChunk<TT;>;
  #18 = NameAndType        #13:#14        // inner:Los/PathChunk$SeqPathChunk;
  #19 = Fieldref           #2.#18         // os/PathChunk$ArrayPathChunk.inner:Los/PathChunk$SeqPathChunk;
  #20 = Utf8               this
  #21 = Utf8               Los/PathChunk$ArrayPathChunk;
  #22 = Utf8               segments
  #23 = Utf8               ()Lscala/collection/immutable/Seq;
  #24 = Utf8               ()Lscala/collection/immutable/Seq<Ljava/lang/String;>;
  #25 = NameAndType        #13:#16        // inner:()Los/PathChunk$SeqPathChunk;
  #26 = Methodref          #2.#25         // os/PathChunk$ArrayPathChunk.inner:()Los/PathChunk$SeqPathChunk;
  #27 = NameAndType        #22:#23        // segments:()Lscala/collection/immutable/Seq;
  #28 = Methodref          #11.#27        // os/PathChunk$SeqPathChunk.segments:()Lscala/collection/immutable/Seq;
  #29 = Utf8               ups
  #30 = Utf8               ()I
  #31 = NameAndType        #29:#30        // ups:()I
  #32 = Methodref          #11.#31        // os/PathChunk$SeqPathChunk.ups:()I
  #33 = Utf8               toString
  #34 = Utf8               ()Ljava/lang/String;
  #35 = NameAndType        #33:#34        // toString:()Ljava/lang/String;
  #36 = Methodref          #11.#35        // os/PathChunk$SeqPathChunk.toString:()Ljava/lang/String;
  #37 = Utf8               <init>
  #38 = Utf8               (Ljava/lang/Object;Lscala/Function1;)V
  #39 = Utf8               (Ljava/lang/Object;Lscala/Function1<TT;Los/PathChunk;>;)V
  #40 = Utf8               a
  #41 = Utf8               f
  #42 = Utf8               ()V
  #43 = NameAndType        #37:#42        // "<init>":()V
  #44 = Methodref          #5.#43         // java/lang/Object."<init>":()V
  #45 = Utf8               os/PathChunk$
  #46 = Class              #45            // os/PathChunk$
  #47 = Utf8               MODULE$
  #48 = Utf8               Los/PathChunk$;
  #49 = NameAndType        #47:#48        // MODULE$:Los/PathChunk$;
  #50 = Fieldref           #46.#49        // os/PathChunk$.MODULE$:Los/PathChunk$;
  #51 = Utf8               scala/Predef$
  #52 = Class              #51            // scala/Predef$
  #53 = Utf8               Lscala/Predef$;
  #54 = NameAndType        #47:#53        // MODULE$:Lscala/Predef$;
  #55 = Fieldref           #52.#54        // scala/Predef$.MODULE$:Lscala/Predef$;
  #56 = Utf8               copyArrayToImmutableIndexedSeq
  #57 = Utf8               (Ljava/lang/Object;)Lscala/collection/immutable/IndexedSeq;
  #58 = NameAndType        #56:#57        // copyArrayToImmutableIndexedSeq:(Ljava/lang/Object;)Lscala/collection/immutable/IndexedSeq;
  #59 = Methodref          #52.#58        // scala/Predef$.copyArrayToImmutableIndexedSeq:(Ljava/lang/Object;)Lscala/collection/immutable/IndexedSeq;
  #60 = Utf8               (Lscala/collection/immutable/Seq;Lscala/Function1;)Los/PathChunk$SeqPathChunk;
  #61 = NameAndType        #12:#60        // SeqPathChunk:(Lscala/collection/immutable/Seq;Lscala/Function1;)Los/PathChunk$SeqPathChunk;
  #62 = Methodref          #46.#61        // os/PathChunk$.SeqPathChunk:(Lscala/collection/immutable/Seq;Lscala/Function1;)Los/PathChunk$SeqPathChunk;
  #63 = Utf8               Ljava/lang/Object;
  #64 = Utf8               Lscala/Function1;
  #65 = Utf8               Signature
  #66 = Utf8               Code
  #67 = Utf8               LineNumberTable
  #68 = Utf8               LocalVariableTable
  #69 = Utf8               MethodParameters
  #70 = Utf8               InnerClasses
  #71 = Utf8               SourceFile
  #72 = Utf8               ScalaInlineInfo
  #73 = Utf8               Scala
{
  private final os.PathChunk$SeqPathChunk<T> inner;
    descriptor: Los/PathChunk$SeqPathChunk;
    flags: (0x0012) ACC_PRIVATE, ACC_FINAL
    Signature: #15                          // Los/PathChunk$SeqPathChunk<TT;>;

  public os.PathChunk$SeqPathChunk<T> inner();
    descriptor: ()Los/PathChunk$SeqPathChunk;
    flags: (0x0001) ACC_PUBLIC
    Code:
      stack=1, locals=1, args_size=1
         0: aload_0
         1: getfield      #19                 // Field inner:Los/PathChunk$SeqPathChunk;
         4: areturn
      LineNumberTable:
        line 33: 0
      LocalVariableTable:
        Start  Length  Slot  Name   Signature
            0       5     0  this   Los/PathChunk$ArrayPathChunk;
    Signature: #17                          // ()Los/PathChunk$SeqPathChunk<TT;>;

  public scala.collection.immutable.Seq<java.lang.String> segments();
    descriptor: ()Lscala/collection/immutable/Seq;
    flags: (0x0001) ACC_PUBLIC
    Code:
      stack=1, locals=1, args_size=1
         0: aload_0
         1: invokevirtual #26                 // Method inner:()Los/PathChunk$SeqPathChunk;
         4: invokevirtual #28                 // Method os/PathChunk$SeqPathChunk.segments:()Lscala/collection/immutable/Seq;
         7: areturn
      LineNumberTable:
        line 34: 0
      LocalVariableTable:
        Start  Length  Slot  Name   Signature
            0       8     0  this   Los/PathChunk$ArrayPathChunk;
    Signature: #24                          // ()Lscala/collection/immutable/Seq<Ljava/lang/String;>;

  public int ups();
    descriptor: ()I
    flags: (0x0001) ACC_PUBLIC
    Code:
      stack=1, locals=1, args_size=1
         0: aload_0
         1: invokevirtual #26                 // Method inner:()Los/PathChunk$SeqPathChunk;
         4: invokevirtual #32                 // Method os/PathChunk$SeqPathChunk.ups:()I
         7: ireturn
      LineNumberTable:
        line 35: 0
      LocalVariableTable:
        Start  Length  Slot  Name   Signature
            0       8     0  this   Los/PathChunk$ArrayPathChunk;

  public java.lang.String toString();
    descriptor: ()Ljava/lang/String;
    flags: (0x0001) ACC_PUBLIC
    Code:
      stack=1, locals=1, args_size=1
         0: aload_0
         1: invokevirtual #26                 // Method inner:()Los/PathChunk$SeqPathChunk;
         4: invokevirtual #36                 // Method os/PathChunk$SeqPathChunk.toString:()Ljava/lang/String;
         7: areturn
      LineNumberTable:
        line 37: 0
      LocalVariableTable:
        Start  Length  Slot  Name   Signature
            0       8     0  this   Los/PathChunk$ArrayPathChunk;

  public os.PathChunk$ArrayPathChunk(java.lang.Object, scala.Function1<T, os.PathChunk>);
    descriptor: (Ljava/lang/Object;Lscala/Function1;)V
    flags: (0x0001) ACC_PUBLIC
    Code:
      stack=4, locals=3, args_size=3
         0: aload_0
         1: invokespecial #44                 // Method java/lang/Object."<init>":()V
         4: aload_0
         5: getstatic     #50                 // Field os/PathChunk$.MODULE$:Los/PathChunk$;
         8: getstatic     #55                 // Field scala/Predef$.MODULE$:Lscala/Predef$;
        11: aload_1
        12: invokevirtual #59                 // Method scala/Predef$.copyArrayToImmutableIndexedSeq:(Ljava/lang/Object;)Lscala/collection/immutable/IndexedSeq;
        15: aload_2
        16: invokevirtual #62                 // Method os/PathChunk$.SeqPathChunk:(Lscala/collection/immutable/Seq;Lscala/Function1;)Los/PathChunk$SeqPathChunk;
        19: putfield      #19                 // Field inner:Los/PathChunk$SeqPathChunk;
        22: return
      LineNumberTable:
        line 32: 0
        line 33: 4
        line 32: 22
      LocalVariableTable:
        Start  Length  Slot  Name   Signature
            0      23     0  this   Los/PathChunk$ArrayPathChunk;
            0      23     1     a   Ljava/lang/Object;
            0      23     2     f   Lscala/Function1;
    Signature: #39                          // (Ljava/lang/Object;Lscala/Function1<TT;Los/PathChunk;>;)V
    MethodParameters:
      Name                           Flags
      a                              final
      f                              final
}
InnerClasses:
  public static #9= #2 of #7;             // ArrayPathChunk=class os/PathChunk$ArrayPathChunk of class os/PathChunk
  public static #12= #11 of #7;           // SeqPathChunk=class os/PathChunk$SeqPathChunk of class os/PathChunk
Signature: #3                           // <T:Ljava/lang/Object;>Ljava/lang/Object;Los/PathChunk;
SourceFile: "Path.scala"
  ScalaInlineInfo: length = 0x1D (unknown attribute)
   01 00 00 05 00 25 00 26 00 00 0D 00 10 00 00 16
   00 17 00 00 21 00 22 00 00 1D 00 1E 00
  Scala: length = 0x0 (unknown attribute)

