Classfile /Users/mw/Projects/slang-braindump/.jar/jar11/assemble/slang-braindump/assemble/content/os/PathChunk.class
  Last modified May 29, 2022; size 3883 bytes
  SHA-256 checksum d072dc5039a284a864611b2d5d1f6864ec9820d98df10d9a7ca58dc3fb4d9eb6
  Compiled from "Path.scala"
public interface os.PathChunk
  minor version: 0
  major version: 52
  flags: (0x0601) ACC_PUBLIC, ACC_INTERFACE, ACC_ABSTRACT
  this_class: #2                          // os/PathChunk
  super_class: #4                         // java/lang/Object
  interfaces: 0, fields: 0, methods: 8, attributes: 5
Constant pool:
   #1 = Utf8               os/PathChunk
   #2 = Class              #1             // os/PathChunk
   #3 = Utf8               java/lang/Object
   #4 = Class              #3             // java/lang/Object
   #5 = Utf8               Path.scala
   #6 = Utf8               Lscala/reflect/ScalaSignature;
   #7 = Utf8               bytes
   #8 = Utf8               \u0006\u0005\u0005ehaB\u001f?!\u0003\r\n!\u0011\u0005\u0006\u0011\u00021\t!\u0013\u0005\u0006=\u00021\taX\u0004\u0006GzB\t\u0001\u001a\u0004\u0006{yB\tA\u001a\u0005\u0006O\u0012!\t\u0001\u001b\u0004\u0005S\u0012\t!\u000e\u0003\u0005m\r\t\u0005\t\u0015!\u0003n\u0011\u00159g\u0001\"\u0001q\u0011\u0015Ae\u0001\"\u0001u\u0011\u0015qf\u0001\"\u0001`\u0011\u0015Ah\u0001\"\u0011z\u0011\u001dQH!!A\u0005\u0004m4A! \u0003\u0002}\"AA.\u0004B\u0001B\u0003%q\u0010\u0003\u0004h\u001b\u0011\u0005\u0011Q\u0001\u0005\u0006\u00116!\t\u0001\u001e\u0005\u0006=6!\ta\u0018\u0005\u0006q6!\t%\u001f\u0005\n\u0003\u0017!\u0011\u0011!C\u0002\u0003\u001b1a!!\u0005\u0005\u0003\u0005M\u0001\"CA\u000b)\t\u0005\t\u0015!\u0003W\u0011\u00199G\u0003\"\u0001\u0002\u0018!1\u0001\n\u0006C\u0001\u0003;AQA\u0018\u000b\u0005\u0002}CQ\u0001\u001f\u000b\u0005BeD\u0011\"!\f\u0005\u0003\u0003%\u0019!a\f\u0007\r\u0005MB!AA\u001b\u0011)\t)b\u0007B\u0001B\u0003%\u0011q\u0007\u0005\u0007On!\t!!\u0010\t\r![B\u0011AA\u000f\u0011\u0015q6\u0004\"\u0001`\u0011\u0015A8\u0004\"\u0011z\u0011%\t\u0019\u0005BA\u0001\n\u0007\t)E\u0002\u0004\u0002J\u0011\t\u00111\n\u0005\u000b\u0003\u001f\u0012#\u0011!Q\u0001\n\u0005E\u0003BCA7E\t\u0005\t\u0015a\u0003\u0002p!1qM\tC\u0001\u0003kB\u0011\"a #\u0005\u0004%\t!!!\t\u0011\u0005-\'\u0005)A\u0005\u0003\u0007Ca\u0001\u0013\u0012\u0005\u0002\u0005u\u0001\"\u00020#\t\u0003y\u0006\"\u0002=#\t\u0003J\b\"CAg\t\u0005\u0005I1AAh\r\u0019\t)\tB\u0001\u0002\b\"Q\u0011q\n\u0017\u0003\u0002\u0003\u0006I!a#\t\u0015\u00055DF!A!\u0002\u0017\t\t\n\u0003\u0004hY\u0011\u0005\u00111\u0013\u0005\n\u0003;c\u0003\u0019!C\u0001\u0003?C\u0011\"a*-\u0001\u0004%\t!!+\t\u0011\u0005UF\u0006)Q\u0005\u0003CC\u0001\"a.-\u0001\u0004%\ta\u0018\u0005\n\u0003sc\u0003\u0019!C\u0001\u0003wCq!a0-A\u0003&\u0001\r\u0003\u0007\u000242\u0002\n\u0011aA!\u0002\u0013\t\t\r\u0003\u0005IY\t\u0007I\u0011AA\u000f\u0011!\t9\r\fQ\u0001\n\u0005}\u0001b\u00020-\u0005\u0004%\ta\u0018\u0005\b\u0003\u0013d\u0003\u0015!\u0003a\u0011\u0015AH\u0006\"\u0011z\u0011%\t\u0019\u000fBA\u0001\n\u0007\t)OA\u0005QCRD7\t[;oW*\tq(\u0001\u0002pg\u000e\u00011C\u0001\u0001C!\t\u0019e)D\u0001E\u0015\u0005)\u0015!B:dC2\f\u0017BA$E\u0005\u0019\te.\u001f*fM\u0006A1/Z4nK:$8/F\u0001K!\rY5K\u0016\b\u0003\u0019Fs!!\u0014)\u000e\u00039S!a\u0014!\u0002\rq\u0012xn\u001c;?\u0013\u0005)\u0015B\u0001*E\u0003\u001d\u0001\u0018mY6bO\u0016L!\u0001V+\u0003\u0007M+\u0017O\u0003\u0002S\tB\u0011qk\u0017\b\u00031f\u0003\"!\u0014#\n\u0005i#\u0015A\u0002)sK\u0012,g-\u0003\u0002];\n11\u000b\u001e:j]\u001eT!A\u0017#\u0002\u0007U\u00048/F\u0001a!\t\u0019\u0015-\u0003\u0002c\t\n\u0019\u0011J\u001c;\u0002\u0013A\u000bG\u000f[\"ik:\\\u0007CA3\u0005\u001b\u0005q4C\u0001\u0003C\u0003\u0019a\u0014N\\5u}Q\tAM\u0001\u0007SK2\u0004\u0016\r\u001e5DQVt7nE\u0002\u0007\u0005.\u0004\"!\u001a\u0001\u0002\u0003I\u0004\"!\u001a8\n\u0005=t$a\u0002*fYB\u000bG\u000f\u001b\u000b\u0003cN\u0004\"A\u001d\u0004\u000e\u0003\u0011AQ\u0001\u001c\u0005A\u00025,\u0012!\u001e\t\u0004\u0017Z4\u0016BA<V\u0005)Ie\u000eZ3yK\u0012\u001cV-]\u0001\ti>\u001cFO]5oOR\ta+\u0001\u0007SK2\u0004\u0016\r\u001e5DQVt7\u000e\u0006\u0002ry\")A\u000e\u0004a\u0001[\na1+\u001e2QCRD7\t[;oWN\u0019QBQ6\u0011\u0007\u0015\f\t!C\u0002\u0002\u0004y\u0012qaU;c!\u0006$\b\u000e\u0006\u0003\u0002\b\u0005%\u0001C\u0001:\u000e\u0011\u0015aw\u00021\u0001\u0000\u00031\u0019VO\u0019)bi\"\u001c\u0005.\u001e8l)\u0011\t9!a\u0004\t\u000b1\u001c\u0002\u0019A@\u0003\u001fM#(/\u001b8h!\u0006$\bn\u00115v].\u001c2\u0001\u0006\"l\u0003\u0005\u0019H\u0003BA\r\u00037\u0001\"A\u001d\u000b\t\r\u0005Ua\u00031\u0001W+\t\ty\u0002E\u0003\u0002\"\u0005-b+\u0004\u0002\u0002$)!\u0011QEA\u0014\u0003%IW.\\;uC\ndWMC\u0002\u0002*\u0011\u000b!bY8mY\u0016\u001cG/[8o\u0013\r!\u00161E\u0001\u0010\'R\u0014\u0018N\\4QCRD7\t[;oWR!\u0011\u0011DA\u0019\u0011\u0019\t)B\u0007a\u0001-\ny1+_7c_2\u0004\u0016\r\u001e5DQVt7nE\u0002\u001c\u0005.\u00042aQA\u001d\u0013\r\tY\u0004\u0012\u0002\u0007\'fl\'m\u001c7\u0015\t\u0005}\u0012\u0011\t\t\u0003enAq!!\u0006\u001e\u0001\u0004\t9$A\bTs6\u0014w\u000e\u001c)bi\"\u001c\u0005.\u001e8l)\u0011\ty$a\u0012\t\u000f\u0005U\u0011\u00051\u0001\u00028\tq\u0011I\u001d:bsB\u000bG\u000f[\"ik:\\W\u0003BA\'\u00037\u001a2A\t\"l\u0003\u0005\t\u0007#B\"\u0002T\u0005]\u0013bAA+\t\n)\u0011I\u001d:bsB!\u0011\u0011LA.\u0019\u0001!q!!\u0018#\u0005\u0004\tyFA\u0001U#\u0011\t\t\'a\u001a\u0011\u0007\r\u000b\u0019\'C\u0002\u0002f\u0011\u0013qAT8uQ&tw\rE\u0002D\u0003SJ1!a\u001bE\u0005\r\te._\u0001\u0002MB11)!\u001d\u0002X-L1!a\u001dE\u0005%1UO\\2uS>t\u0017\u0007\u0006\u0003\u0002x\u0005uD\u0003BA=\u0003w\u0002BA\u001d\u0012\u0002X!9\u0011QN\u0013A\u0004\u0005=\u0004bBA(K\u0001\u0007\u0011\u0011K\u0001\u0006S:tWM]\u000b\u0003\u0003\u0007\u0003BA\u001d\u0017\u0002X\ta1+Z9QCRD7\t[;oWV!\u0011\u0011RAH\'\ra#i\u001b\t\u0005\u0017N\u000bi\t\u0005\u0003\u0002Z\u0005=EaBA/Y\t\u0007\u0011q\f\t\u0007\u0007\u0006E\u0014QR6\u0015\t\u0005U\u00151\u0014\u000b\u0005\u0003/\u000bI\n\u0005\u0003sY\u00055\u0005bBA7_\u0001\u000f\u0011\u0011\u0013\u0005\b\u0003\u001fz\u0003\u0019AAF\u0003%\u0019XmZ7f]R\u001c\b\'\u0006\u0002\u0002\"B!\u0011\u0011EAR\u0015\u0011\t)+a\t\u0002\u00079KG.A\u0007tK\u001elWM\u001c;ta}#S-\u001d\u000b\u0005\u0003W\u000b\t\fE\u0002D\u0003[K1!a,E\u0005\u0011)f.\u001b;\t\u0013\u0005M\u0016\'!AA\u0002\u0005\u0005\u0016a\u0001=%c\u0005Q1/Z4nK:$8\u000f\r\u0011\u0002\tU\u00048\u000fM\u0001\tkB\u001c\bg\u0018\u0013fcR!\u00111VA_\u0011!\t\u0019\fNA\u0001\u0002\u0004\u0001\u0017!B;qgB\u0002\u0003CB\"\u0002D\u0006}\u0001-C\u0002\u0002F\u0012\u0013a\u0001V;qY\u0016\u0014\u0014!C:fO6,g\u000e^:!\u0003\u0011)\bo\u001d\u0011\u0002\r%tg.\u001a:!\u00039\t%O]1z!\u0006$\bn\u00115v].,B!!5\u0002ZR!\u00111[Ap)\u0011\t).a7\u0011\tI\u0014\u0013q\u001b\t\u0005\u00033\nI\u000eB\u0004\u0002^-\u0012\r!a\u0018\t\u000f\u000554\u0006q\u0001\u0002^B11)!\u001d\u0002X.Dq!a\u0014,\u0001\u0004\t\t\u000fE\u0003D\u0003\'\n9.\u0001\u0007TKF\u0004\u0016\r\u001e5DQVt7.\u0006\u0003\u0002h\u0006=H\u0003BAu\u0003k$B!a;\u0002rB!!\u000fLAw!\u0011\tI&a<\u0005\u000f\u0005uCH1\u0001\u0002`!9\u0011Q\u000e\u001fA\u0004\u0005M\bCB\"\u0002r\u000558\u000eC\u0004\u0002Pq\u0002\r!a>\u0011\t-\u001b\u0016Q\u001e
   #9 = Utf8               os/PathChunk$ArrayPathChunk
  #10 = Class              #9             // os/PathChunk$ArrayPathChunk
  #11 = Utf8               ArrayPathChunk
  #12 = Utf8               os/PathChunk$RelPathChunk
  #13 = Class              #12            // os/PathChunk$RelPathChunk
  #14 = Utf8               RelPathChunk
  #15 = Utf8               os/PathChunk$SeqPathChunk
  #16 = Class              #15            // os/PathChunk$SeqPathChunk
  #17 = Utf8               SeqPathChunk
  #18 = Utf8               os/PathChunk$StringPathChunk
  #19 = Class              #18            // os/PathChunk$StringPathChunk
  #20 = Utf8               StringPathChunk
  #21 = Utf8               os/PathChunk$SubPathChunk
  #22 = Class              #21            // os/PathChunk$SubPathChunk
  #23 = Utf8               SubPathChunk
  #24 = Utf8               os/PathChunk$SymbolPathChunk
  #25 = Class              #24            // os/PathChunk$SymbolPathChunk
  #26 = Utf8               SymbolPathChunk
  #27 = Utf8               (Lscala/collection/immutable/Seq;Lscala/Function1;)Los/PathChunk$SeqPathChunk;
  #28 = Utf8               <T:Ljava/lang/Object;>(Lscala/collection/immutable/Seq<TT;>;Lscala/Function1<TT;Los/PathChunk;>;)Los/PathChunk$SeqPathChunk<TT;>;
  #29 = Utf8               a
  #30 = Utf8               f
  #31 = Utf8               os/PathChunk$
  #32 = Class              #31            // os/PathChunk$
  #33 = Utf8               MODULE$
  #34 = Utf8               Los/PathChunk$;
  #35 = NameAndType        #33:#34        // MODULE$:Los/PathChunk$;
  #36 = Fieldref           #32.#35        // os/PathChunk$.MODULE$:Los/PathChunk$;
  #37 = NameAndType        #17:#27        // SeqPathChunk:(Lscala/collection/immutable/Seq;Lscala/Function1;)Los/PathChunk$SeqPathChunk;
  #38 = Methodref          #32.#37        // os/PathChunk$.SeqPathChunk:(Lscala/collection/immutable/Seq;Lscala/Function1;)Los/PathChunk$SeqPathChunk;
  #39 = Utf8               (Ljava/lang/Object;Lscala/Function1;)Los/PathChunk$ArrayPathChunk;
  #40 = Utf8               <T:Ljava/lang/Object;>(Ljava/lang/Object;Lscala/Function1<TT;Los/PathChunk;>;)Los/PathChunk$ArrayPathChunk<TT;>;
  #41 = NameAndType        #11:#39        // ArrayPathChunk:(Ljava/lang/Object;Lscala/Function1;)Los/PathChunk$ArrayPathChunk;
  #42 = Methodref          #32.#41        // os/PathChunk$.ArrayPathChunk:(Ljava/lang/Object;Lscala/Function1;)Los/PathChunk$ArrayPathChunk;
  #43 = Utf8               (Lscala/Symbol;)Los/PathChunk$SymbolPathChunk;
  #44 = Utf8               s
  #45 = NameAndType        #26:#43        // SymbolPathChunk:(Lscala/Symbol;)Los/PathChunk$SymbolPathChunk;
  #46 = Methodref          #32.#45        // os/PathChunk$.SymbolPathChunk:(Lscala/Symbol;)Los/PathChunk$SymbolPathChunk;
  #47 = Utf8               (Ljava/lang/String;)Los/PathChunk$StringPathChunk;
  #48 = NameAndType        #20:#47        // StringPathChunk:(Ljava/lang/String;)Los/PathChunk$StringPathChunk;
  #49 = Methodref          #32.#48        // os/PathChunk$.StringPathChunk:(Ljava/lang/String;)Los/PathChunk$StringPathChunk;
  #50 = Utf8               (Los/SubPath;)Los/PathChunk$SubPathChunk;
  #51 = Utf8               r
  #52 = NameAndType        #23:#50        // SubPathChunk:(Los/SubPath;)Los/PathChunk$SubPathChunk;
  #53 = Methodref          #32.#52        // os/PathChunk$.SubPathChunk:(Los/SubPath;)Los/PathChunk$SubPathChunk;
  #54 = Utf8               (Los/RelPath;)Los/PathChunk$RelPathChunk;
  #55 = NameAndType        #14:#54        // RelPathChunk:(Los/RelPath;)Los/PathChunk$RelPathChunk;
  #56 = Methodref          #32.#55        // os/PathChunk$.RelPathChunk:(Los/RelPath;)Los/PathChunk$RelPathChunk;
  #57 = Utf8               segments
  #58 = Utf8               ()Lscala/collection/immutable/Seq;
  #59 = Utf8               ()Lscala/collection/immutable/Seq<Ljava/lang/String;>;
  #60 = Utf8               ups
  #61 = Utf8               ()I
  #62 = Utf8               Code
  #63 = Utf8               Signature
  #64 = Utf8               MethodParameters
  #65 = Utf8               InnerClasses
  #66 = Utf8               SourceFile
  #67 = Utf8               RuntimeVisibleAnnotations
  #68 = Utf8               ScalaInlineInfo
  #69 = Utf8               ScalaSig
{
  public static <T extends java.lang.Object> os.PathChunk$SeqPathChunk<T> SeqPathChunk(scala.collection.immutable.Seq<T>, scala.Function1<T, os.PathChunk>);
    descriptor: (Lscala/collection/immutable/Seq;Lscala/Function1;)Los/PathChunk$SeqPathChunk;
    flags: (0x0009) ACC_PUBLIC, ACC_STATIC
    Code:
      stack=3, locals=2, args_size=2
         0: getstatic     #36                 // Field os/PathChunk$.MODULE$:Los/PathChunk$;
         3: aload_0
         4: aload_1
         5: invokevirtual #38                 // Method os/PathChunk$.SeqPathChunk:(Lscala/collection/immutable/Seq;Lscala/Function1;)Los/PathChunk$SeqPathChunk;
         8: areturn
    Signature: #28                          // <T:Ljava/lang/Object;>(Lscala/collection/immutable/Seq<TT;>;Lscala/Function1<TT;Los/PathChunk;>;)Los/PathChunk$SeqPathChunk<TT;>;
    MethodParameters:
      Name                           Flags
      a                              final
      f                              final

  public static <T extends java.lang.Object> os.PathChunk$ArrayPathChunk<T> ArrayPathChunk(java.lang.Object, scala.Function1<T, os.PathChunk>);
    descriptor: (Ljava/lang/Object;Lscala/Function1;)Los/PathChunk$ArrayPathChunk;
    flags: (0x0009) ACC_PUBLIC, ACC_STATIC
    Code:
      stack=3, locals=2, args_size=2
         0: getstatic     #36                 // Field os/PathChunk$.MODULE$:Los/PathChunk$;
         3: aload_0
         4: aload_1
         5: invokevirtual #42                 // Method os/PathChunk$.ArrayPathChunk:(Ljava/lang/Object;Lscala/Function1;)Los/PathChunk$ArrayPathChunk;
         8: areturn
    Signature: #40                          // <T:Ljava/lang/Object;>(Ljava/lang/Object;Lscala/Function1<TT;Los/PathChunk;>;)Los/PathChunk$ArrayPathChunk<TT;>;
    MethodParameters:
      Name                           Flags
      a                              final
      f                              final

  public static os.PathChunk$SymbolPathChunk SymbolPathChunk(scala.Symbol);
    descriptor: (Lscala/Symbol;)Los/PathChunk$SymbolPathChunk;
    flags: (0x0009) ACC_PUBLIC, ACC_STATIC
    Code:
      stack=2, locals=1, args_size=1
         0: getstatic     #36                 // Field os/PathChunk$.MODULE$:Los/PathChunk$;
         3: aload_0
         4: invokevirtual #46                 // Method os/PathChunk$.SymbolPathChunk:(Lscala/Symbol;)Los/PathChunk$SymbolPathChunk;
         7: areturn
    MethodParameters:
      Name                           Flags
      s                              final

  public static os.PathChunk$StringPathChunk StringPathChunk(java.lang.String);
    descriptor: (Ljava/lang/String;)Los/PathChunk$StringPathChunk;
    flags: (0x0009) ACC_PUBLIC, ACC_STATIC
    Code:
      stack=2, locals=1, args_size=1
         0: getstatic     #36                 // Field os/PathChunk$.MODULE$:Los/PathChunk$;
         3: aload_0
         4: invokevirtual #49                 // Method os/PathChunk$.StringPathChunk:(Ljava/lang/String;)Los/PathChunk$StringPathChunk;
         7: areturn
    MethodParameters:
      Name                           Flags
      s                              final

  public static os.PathChunk$SubPathChunk SubPathChunk(os.SubPath);
    descriptor: (Los/SubPath;)Los/PathChunk$SubPathChunk;
    flags: (0x0009) ACC_PUBLIC, ACC_STATIC
    Code:
      stack=2, locals=1, args_size=1
         0: getstatic     #36                 // Field os/PathChunk$.MODULE$:Los/PathChunk$;
         3: aload_0
         4: invokevirtual #53                 // Method os/PathChunk$.SubPathChunk:(Los/SubPath;)Los/PathChunk$SubPathChunk;
         7: areturn
    MethodParameters:
      Name                           Flags
      r                              final

  public static os.PathChunk$RelPathChunk RelPathChunk(os.RelPath);
    descriptor: (Los/RelPath;)Los/PathChunk$RelPathChunk;
    flags: (0x0009) ACC_PUBLIC, ACC_STATIC
    Code:
      stack=2, locals=1, args_size=1
         0: getstatic     #36                 // Field os/PathChunk$.MODULE$:Los/PathChunk$;
         3: aload_0
         4: invokevirtual #56                 // Method os/PathChunk$.RelPathChunk:(Los/RelPath;)Los/PathChunk$RelPathChunk;
         7: areturn
    MethodParameters:
      Name                           Flags
      r                              final

  public abstract scala.collection.immutable.Seq<java.lang.String> segments();
    descriptor: ()Lscala/collection/immutable/Seq;
    flags: (0x0401) ACC_PUBLIC, ACC_ABSTRACT
    Signature: #59                          // ()Lscala/collection/immutable/Seq<Ljava/lang/String;>;

  public abstract int ups();
    descriptor: ()I
    flags: (0x0401) ACC_PUBLIC, ACC_ABSTRACT
}
InnerClasses:
  public static #11= #10 of #2;           // ArrayPathChunk=class os/PathChunk$ArrayPathChunk of class os/PathChunk
  public static #14= #13 of #2;           // RelPathChunk=class os/PathChunk$RelPathChunk of class os/PathChunk
  public static #17= #16 of #2;           // SeqPathChunk=class os/PathChunk$SeqPathChunk of class os/PathChunk
  public static #20= #19 of #2;           // StringPathChunk=class os/PathChunk$StringPathChunk of class os/PathChunk
  public static #23= #22 of #2;           // SubPathChunk=class os/PathChunk$SubPathChunk of class os/PathChunk
  public static #26= #25 of #2;           // SymbolPathChunk=class os/PathChunk$SymbolPathChunk of class os/PathChunk
SourceFile: "Path.scala"
RuntimeVisibleAnnotations:
  0: #6(#7=s#8)
    scala.reflect.ScalaSignature(
      bytes="\u0006\u0005\u0005ehaB\u001f?!\u0003\r\n!\u0011\u0005\u0006\u0011\u00021\t!\u0013\u0005\u0006=\u00021\taX\u0004\u0006GzB\t\u0001\u001a\u0004\u0006{yB\tA\u001a\u0005\u0006O\u0012!\t\u0001\u001b\u0004\u0005S\u0012\t!\u000e\u0003\u0005m\r\t\u0005\t\u0015!\u0003n\u0011\u00159g\u0001\"\u0001q\u0011\u0015Ae\u0001\"\u0001u\u0011\u0015qf\u0001\"\u0001`\u0011\u0015Ah\u0001\"\u0011z\u0011\u001dQH!!A\u0005\u0004m4A! \u0003\u0002}\"AA.\u0004B\u0001B\u0003%q\u0010\u0003\u0004h\u001b\u0011\u0005\u0011Q\u0001\u0005\u0006\u00116!\t\u0001\u001e\u0005\u0006=6!\ta\u0018\u0005\u0006q6!\t%\u001f\u0005\n\u0003\u0017!\u0011\u0011!C\u0002\u0003\u001b1a!!\u0005\u0005\u0003\u0005M\u0001\"CA\u000b)\t\u0005\t\u0015!\u0003W\u0011\u00199G\u0003\"\u0001\u0002\u0018!1\u0001\n\u0006C\u0001\u0003;AQA\u0018\u000b\u0005\u0002}CQ\u0001\u001f\u000b\u0005BeD\u0011\"!\f\u0005\u0003\u0003%\u0019!a\f\u0007\r\u0005MB!AA\u001b\u0011)\t)b\u0007B\u0001B\u0003%\u0011q\u0007\u0005\u0007On!\t!!\u0010\t\r![B\u0011AA\u000f\u0011\u0015q6\u0004\"\u0001`\u0011\u0015A8\u0004\"\u0011z\u0011%\t\u0019\u0005BA\u0001\n\u0007\t)E\u0002\u0004\u0002J\u0011\t\u00111\n\u0005\u000b\u0003\u001f\u0012#\u0011!Q\u0001\n\u0005E\u0003BCA7E\t\u0005\t\u0015a\u0003\u0002p!1qM\tC\u0001\u0003kB\u0011\"a #\u0005\u0004%\t!!!\t\u0011\u0005-\'\u0005)A\u0005\u0003\u0007Ca\u0001\u0013\u0012\u0005\u0002\u0005u\u0001\"\u00020#\t\u0003y\u0006\"\u0002=#\t\u0003J\b\"CAg\t\u0005\u0005I1AAh\r\u0019\t)\tB\u0001\u0002\b\"Q\u0011q\n\u0017\u0003\u0002\u0003\u0006I!a#\t\u0015\u00055DF!A!\u0002\u0017\t\t\n\u0003\u0004hY\u0011\u0005\u00111\u0013\u0005\n\u0003;c\u0003\u0019!C\u0001\u0003?C\u0011\"a*-\u0001\u0004%\t!!+\t\u0011\u0005UF\u0006)Q\u0005\u0003CC\u0001\"a.-\u0001\u0004%\ta\u0018\u0005\n\u0003sc\u0003\u0019!C\u0001\u0003wCq!a0-A\u0003&\u0001\r\u0003\u0007\u000242\u0002\n\u0011aA!\u0002\u0013\t\t\r\u0003\u0005IY\t\u0007I\u0011AA\u000f\u0011!\t9\r\fQ\u0001\n\u0005}\u0001b\u00020-\u0005\u0004%\ta\u0018\u0005\b\u0003\u0013d\u0003\u0015!\u0003a\u0011\u0015AH\u0006\"\u0011z\u0011%\t\u0019\u000fBA\u0001\n\u0007\t)OA\u0005QCRD7\t[;oW*\tq(\u0001\u0002pg\u000e\u00011C\u0001\u0001C!\t\u0019e)D\u0001E\u0015\u0005)\u0015!B:dC2\f\u0017BA$E\u0005\u0019\te.\u001f*fM\u0006A1/Z4nK:$8/F\u0001K!\rY5K\u0016\b\u0003\u0019Fs!!\u0014)\u000e\u00039S!a\u0014!\u0002\rq\u0012xn\u001c;?\u0013\u0005)\u0015B\u0001*E\u0003\u001d\u0001\u0018mY6bO\u0016L!\u0001V+\u0003\u0007M+\u0017O\u0003\u0002S\tB\u0011qk\u0017\b\u00031f\u0003\"!\u0014#\n\u0005i#\u0015A\u0002)sK\u0012,g-\u0003\u0002];\n11\u000b\u001e:j]\u001eT!A\u0017#\u0002\u0007U\u00048/F\u0001a!\t\u0019\u0015-\u0003\u0002c\t\n\u0019\u0011J\u001c;\u0002\u0013A\u000bG\u000f[\"ik:\\\u0007CA3\u0005\u001b\u0005q4C\u0001\u0003C\u0003\u0019a\u0014N\\5u}Q\tAM\u0001\u0007SK2\u0004\u0016\r\u001e5DQVt7nE\u0002\u0007\u0005.\u0004\"!\u001a\u0001\u0002\u0003I\u0004\"!\u001a8\n\u0005=t$a\u0002*fYB\u000bG\u000f\u001b\u000b\u0003cN\u0004\"A\u001d\u0004\u000e\u0003\u0011AQ\u0001\u001c\u0005A\u00025,\u0012!\u001e\t\u0004\u0017Z4\u0016BA<V\u0005)Ie\u000eZ3yK\u0012\u001cV-]\u0001\ti>\u001cFO]5oOR\ta+\u0001\u0007SK2\u0004\u0016\r\u001e5DQVt7\u000e\u0006\u0002ry\")A\u000e\u0004a\u0001[\na1+\u001e2QCRD7\t[;oWN\u0019QBQ6\u0011\u0007\u0015\f\t!C\u0002\u0002\u0004y\u0012qaU;c!\u0006$\b\u000e\u0006\u0003\u0002\b\u0005%\u0001C\u0001:\u000e\u0011\u0015aw\u00021\u0001\u0000\u00031\u0019VO\u0019)bi\"\u001c\u0005.\u001e8l)\u0011\t9!a\u0004\t\u000b1\u001c\u0002\u0019A@\u0003\u001fM#(/\u001b8h!\u0006$\bn\u00115v].\u001c2\u0001\u0006\"l\u0003\u0005\u0019H\u0003BA\r\u00037\u0001\"A\u001d\u000b\t\r\u0005Ua\u00031\u0001W+\t\ty\u0002E\u0003\u0002\"\u0005-b+\u0004\u0002\u0002$)!\u0011QEA\u0014\u0003%IW.\\;uC\ndWMC\u0002\u0002*\u0011\u000b!bY8mY\u0016\u001cG/[8o\u0013\r!\u00161E\u0001\u0010\'R\u0014\u0018N\\4QCRD7\t[;oWR!\u0011\u0011DA\u0019\u0011\u0019\t)B\u0007a\u0001-\ny1+_7c_2\u0004\u0016\r\u001e5DQVt7nE\u0002\u001c\u0005.\u00042aQA\u001d\u0013\r\tY\u0004\u0012\u0002\u0007\'fl\'m\u001c7\u0015\t\u0005}\u0012\u0011\t\t\u0003enAq!!\u0006\u001e\u0001\u0004\t9$A\bTs6\u0014w\u000e\u001c)bi\"\u001c\u0005.\u001e8l)\u0011\ty$a\u0012\t\u000f\u0005U\u0011\u00051\u0001\u00028\tq\u0011I\u001d:bsB\u000bG\u000f[\"ik:\\W\u0003BA\'\u00037\u001a2A\t\"l\u0003\u0005\t\u0007#B\"\u0002T\u0005]\u0013bAA+\t\n)\u0011I\u001d:bsB!\u0011\u0011LA.\u0019\u0001!q!!\u0018#\u0005\u0004\tyFA\u0001U#\u0011\t\t\'a\u001a\u0011\u0007\r\u000b\u0019\'C\u0002\u0002f\u0011\u0013qAT8uQ&tw\rE\u0002D\u0003SJ1!a\u001bE\u0005\r\te._\u0001\u0002MB11)!\u001d\u0002X-L1!a\u001dE\u0005%1UO\\2uS>t\u0017\u0007\u0006\u0003\u0002x\u0005uD\u0003BA=\u0003w\u0002BA\u001d\u0012\u0002X!9\u0011QN\u0013A\u0004\u0005=\u0004bBA(K\u0001\u0007\u0011\u0011K\u0001\u0006S:tWM]\u000b\u0003\u0003\u0007\u0003BA\u001d\u0017\u0002X\ta1+Z9QCRD7\t[;oWV!\u0011\u0011RAH\'\ra#i\u001b\t\u0005\u0017N\u000bi\t\u0005\u0003\u0002Z\u0005=EaBA/Y\t\u0007\u0011q\f\t\u0007\u0007\u0006E\u0014QR6\u0015\t\u0005U\u00151\u0014\u000b\u0005\u0003/\u000bI\n\u0005\u0003sY\u00055\u0005bBA7_\u0001\u000f\u0011\u0011\u0013\u0005\b\u0003\u001fz\u0003\u0019AAF\u0003%\u0019XmZ7f]R\u001c\b\'\u0006\u0002\u0002\"B!\u0011\u0011EAR\u0015\u0011\t)+a\t\u0002\u00079KG.A\u0007tK\u001elWM\u001c;ta}#S-\u001d\u000b\u0005\u0003W\u000b\t\fE\u0002D\u0003[K1!a,E\u0005\u0011)f.\u001b;\t\u0013\u0005M\u0016\'!AA\u0002\u0005\u0005\u0016a\u0001=%c\u0005Q1/Z4nK:$8\u000f\r\u0011\u0002\tU\u00048\u000fM\u0001\tkB\u001c\bg\u0018\u0013fcR!\u00111VA_\u0011!\t\u0019\fNA\u0001\u0002\u0004\u0001\u0017!B;qgB\u0002\u0003CB\"\u0002D\u0006}\u0001-C\u0002\u0002F\u0012\u0013a\u0001V;qY\u0016\u0014\u0014!C:fO6,g\u000e^:!\u0003\u0011)\bo\u001d\u0011\u0002\r%tg.\u001a:!\u00039\t%O]1z!\u0006$\bn\u00115v].,B!!5\u0002ZR!\u00111[Ap)\u0011\t).a7\u0011\tI\u0014\u0013q\u001b\t\u0005\u00033\nI\u000eB\u0004\u0002^-\u0012\r!a\u0018\t\u000f\u000554\u0006q\u0001\u0002^B11)!\u001d\u0002X.Dq!a\u0014,\u0001\u0004\t\t\u000fE\u0003D\u0003\'\n9.\u0001\u0007TKF\u0004\u0016\r\u001e5DQVt7.\u0006\u0003\u0002h\u0006=H\u0003BAu\u0003k$B!a;\u0002rB!!\u000fLAw!\u0011\tI&a<\u0005\u000f\u0005uCH1\u0001\u0002`!9\u0011Q\u000e\u001fA\u0004\u0005M\bCB\"\u0002r\u000558\u000eC\u0004\u0002Pq\u0002\r!a>\u0011\t-\u001b\u0016Q\u001e"
    )
  ScalaInlineInfo: length = 0xE (unknown attribute)
   01 00 00 02 00 39 00 3A 00 00 3C 00 3D 00
  ScalaSig: length = 0x3 (unknown attribute)
   05 02 00
