Classfile /Users/mw/Projects/slang-braindump/.jar/jar11/assemble/slang-braindump/assemble/content/os/PathError$LastOnEmptyPath.class
  Last modified May 29, 2022; size 2284 bytes
  SHA-256 checksum 67df5cd096968e909901e0ddcc86e32a00ba804d247f4e16a454dfe55a395b24
  Compiled from "Path.scala"
public class os.PathError$LastOnEmptyPath extends java.lang.IllegalArgumentException implements scala.Product
  minor version: 0
  major version: 52
  flags: (0x0021) ACC_PUBLIC, ACC_SUPER
  this_class: #2                          // os/PathError$LastOnEmptyPath
  super_class: #4                         // java/lang/IllegalArgumentException
  interfaces: 1, fields: 0, methods: 11, attributes: 4
Constant pool:
   #1 = Utf8               os/PathError$LastOnEmptyPath
   #2 = Class              #1             // os/PathError$LastOnEmptyPath
   #3 = Utf8               java/lang/IllegalArgumentException
   #4 = Class              #3             // java/lang/IllegalArgumentException
   #5 = Utf8               scala/Product
   #6 = Class              #5             // scala/Product
   #7 = Utf8               Path.scala
   #8 = Utf8               os/PathError
   #9 = Class              #8             // os/PathError
  #10 = Utf8               LastOnEmptyPath
  #11 = Utf8               productElementNames
  #12 = Utf8               ()Lscala/collection/Iterator;
  #13 = Utf8               ()Lscala/collection/Iterator<Ljava/lang/String;>;
  #14 = Utf8               productElementNames$
  #15 = Utf8               (Lscala/Product;)Lscala/collection/Iterator;
  #16 = NameAndType        #14:#15        // productElementNames$:(Lscala/Product;)Lscala/collection/Iterator;
  #17 = InterfaceMethodref #6.#16         // scala/Product.productElementNames$:(Lscala/Product;)Lscala/collection/Iterator;
  #18 = Utf8               this
  #19 = Utf8               Los/PathError$LastOnEmptyPath;
  #20 = Utf8               copy
  #21 = Utf8               ()Los/PathError$LastOnEmptyPath;
  #22 = Utf8               <init>
  #23 = Utf8               ()V
  #24 = NameAndType        #22:#23        // "<init>":()V
  #25 = Methodref          #2.#24         // os/PathError$LastOnEmptyPath."<init>":()V
  #26 = Utf8               productPrefix
  #27 = Utf8               ()Ljava/lang/String;
  #28 = String             #10            // LastOnEmptyPath
  #29 = Utf8               productArity
  #30 = Utf8               ()I
  #31 = Utf8               productElement
  #32 = Utf8               (I)Ljava/lang/Object;
  #33 = Utf8               x$1
  #34 = Utf8               scala/runtime/Statics
  #35 = Class              #34            // scala/runtime/Statics
  #36 = Utf8               ioobe
  #37 = NameAndType        #36:#32        // ioobe:(I)Ljava/lang/Object;
  #38 = Methodref          #35.#37        // scala/runtime/Statics.ioobe:(I)Ljava/lang/Object;
  #39 = Utf8               I
  #40 = Utf8               java/lang/Object
  #41 = Class              #40            // java/lang/Object
  #42 = Utf8               productIterator
  #43 = Utf8               ()Lscala/collection/Iterator<Ljava/lang/Object;>;
  #44 = Utf8               scala/runtime/ScalaRunTime$
  #45 = Class              #44            // scala/runtime/ScalaRunTime$
  #46 = Utf8               MODULE$
  #47 = Utf8               Lscala/runtime/ScalaRunTime$;
  #48 = NameAndType        #46:#47        // MODULE$:Lscala/runtime/ScalaRunTime$;
  #49 = Fieldref           #45.#48        // scala/runtime/ScalaRunTime$.MODULE$:Lscala/runtime/ScalaRunTime$;
  #50 = Utf8               typedProductIterator
  #51 = NameAndType        #50:#15        // typedProductIterator:(Lscala/Product;)Lscala/collection/Iterator;
  #52 = Methodref          #45.#51        // scala/runtime/ScalaRunTime$.typedProductIterator:(Lscala/Product;)Lscala/collection/Iterator;
  #53 = Utf8               canEqual
  #54 = Utf8               (Ljava/lang/Object;)Z
  #55 = Utf8               Ljava/lang/Object;
  #56 = Utf8               productElementName
  #57 = Utf8               (I)Ljava/lang/String;
  #58 = Utf8               java/lang/String
  #59 = Class              #58            // java/lang/String
  #60 = Utf8               hashCode
  #61 = Utf8               _hashCode
  #62 = Utf8               (Lscala/Product;)I
  #63 = NameAndType        #61:#62        // _hashCode:(Lscala/Product;)I
  #64 = Methodref          #45.#63        // scala/runtime/ScalaRunTime$._hashCode:(Lscala/Product;)I
  #65 = Utf8               equals
  #66 = NameAndType        #53:#54        // canEqual:(Ljava/lang/Object;)Z
  #67 = Methodref          #2.#66         // os/PathError$LastOnEmptyPath.canEqual:(Ljava/lang/Object;)Z
  #68 = Utf8               empty path has no last segment
  #69 = String             #68            // empty path has no last segment
  #70 = Utf8               (Ljava/lang/String;)V
  #71 = NameAndType        #22:#70        // "<init>":(Ljava/lang/String;)V
  #72 = Methodref          #4.#71         // java/lang/IllegalArgumentException."<init>":(Ljava/lang/String;)V
  #73 = Utf8               $init$
  #74 = Utf8               (Lscala/Product;)V
  #75 = NameAndType        #73:#74        // $init$:(Lscala/Product;)V
  #76 = InterfaceMethodref #6.#75         // scala/Product.$init$:(Lscala/Product;)V
  #77 = Utf8               Code
  #78 = Utf8               LineNumberTable
  #79 = Utf8               LocalVariableTable
  #80 = Utf8               Signature
  #81 = Utf8               StackMapTable
  #82 = Utf8               MethodParameters
  #83 = Utf8               InnerClasses
  #84 = Utf8               SourceFile
  #85 = Utf8               ScalaInlineInfo
  #86 = Utf8               Scala
{
  public scala.collection.Iterator<java.lang.String> productElementNames();
    descriptor: ()Lscala/collection/Iterator;
    flags: (0x0001) ACC_PUBLIC
    Code:
      stack=1, locals=1, args_size=1
         0: aload_0
         1: invokestatic  #17                 // InterfaceMethod scala/Product.productElementNames$:(Lscala/Product;)Lscala/collection/Iterator;
         4: areturn
      LineNumberTable:
        line 219: 0
      LocalVariableTable:
        Start  Length  Slot  Name   Signature
            0       5     0  this   Los/PathError$LastOnEmptyPath;
    Signature: #13                          // ()Lscala/collection/Iterator<Ljava/lang/String;>;

  public os.PathError$LastOnEmptyPath copy();
    descriptor: ()Los/PathError$LastOnEmptyPath;
    flags: (0x0001) ACC_PUBLIC
    Code:
      stack=2, locals=1, args_size=1
         0: new           #2                  // class os/PathError$LastOnEmptyPath
         3: dup
         4: invokespecial #25                 // Method "<init>":()V
         7: areturn
      LineNumberTable:
        line 219: 0
      LocalVariableTable:
        Start  Length  Slot  Name   Signature
            0       8     0  this   Los/PathError$LastOnEmptyPath;

  public java.lang.String productPrefix();
    descriptor: ()Ljava/lang/String;
    flags: (0x0001) ACC_PUBLIC
    Code:
      stack=1, locals=1, args_size=1
         0: ldc           #28                 // String LastOnEmptyPath
         2: areturn
      LineNumberTable:
        line 219: 0
      LocalVariableTable:
        Start  Length  Slot  Name   Signature
            0       3     0  this   Los/PathError$LastOnEmptyPath;

  public int productArity();
    descriptor: ()I
    flags: (0x0001) ACC_PUBLIC
    Code:
      stack=1, locals=1, args_size=1
         0: iconst_0
         1: ireturn
      LineNumberTable:
        line 219: 0
      LocalVariableTable:
        Start  Length  Slot  Name   Signature
            0       2     0  this   Los/PathError$LastOnEmptyPath;

  public java.lang.Object productElement(int);
    descriptor: (I)Ljava/lang/Object;
    flags: (0x0001) ACC_PUBLIC
    Code:
      stack=1, locals=4, args_size=2
         0: iload_1
         1: istore_3
         2: iload_1
         3: invokestatic  #38                 // Method scala/runtime/Statics.ioobe:(I)Ljava/lang/Object;
         6: astore_2
         7: goto          10
        10: aload_2
        11: areturn
      StackMapTable: number_of_entries = 1
        frame_type = 253 /* append */
          offset_delta = 10
          locals = [ class java/lang/Object, int ]
      LineNumberTable:
        line 219: 0
      LocalVariableTable:
        Start  Length  Slot  Name   Signature
            0      12     0  this   Los/PathError$LastOnEmptyPath;
            0      12     1   x$1   I
    MethodParameters:
      Name                           Flags
      x$1                            final

  public scala.collection.Iterator<java.lang.Object> productIterator();
    descriptor: ()Lscala/collection/Iterator;
    flags: (0x0001) ACC_PUBLIC
    Code:
      stack=2, locals=1, args_size=1
         0: getstatic     #49                 // Field scala/runtime/ScalaRunTime$.MODULE$:Lscala/runtime/ScalaRunTime$;
         3: aload_0
         4: invokevirtual #52                 // Method scala/runtime/ScalaRunTime$.typedProductIterator:(Lscala/Product;)Lscala/collection/Iterator;
         7: areturn
      LineNumberTable:
        line 219: 0
      LocalVariableTable:
        Start  Length  Slot  Name   Signature
            0       8     0  this   Los/PathError$LastOnEmptyPath;
    Signature: #43                          // ()Lscala/collection/Iterator<Ljava/lang/Object;>;

  public boolean canEqual(java.lang.Object);
    descriptor: (Ljava/lang/Object;)Z
    flags: (0x0001) ACC_PUBLIC
    Code:
      stack=1, locals=2, args_size=2
         0: aload_1
         1: instanceof    #2                  // class os/PathError$LastOnEmptyPath
         4: ireturn
      LineNumberTable:
        line 219: 0
      LocalVariableTable:
        Start  Length  Slot  Name   Signature
            0       5     0  this   Los/PathError$LastOnEmptyPath;
            0       5     1   x$1   Ljava/lang/Object;
    MethodParameters:
      Name                           Flags
      x$1                            final

  public java.lang.String productElementName(int);
    descriptor: (I)Ljava/lang/String;
    flags: (0x0001) ACC_PUBLIC
    Code:
      stack=1, locals=4, args_size=2
         0: iload_1
         1: istore_3
         2: iload_1
         3: invokestatic  #38                 // Method scala/runtime/Statics.ioobe:(I)Ljava/lang/Object;
         6: checkcast     #59                 // class java/lang/String
         9: astore_2
        10: goto          13
        13: aload_2
        14: areturn
      StackMapTable: number_of_entries = 1
        frame_type = 253 /* append */
          offset_delta = 13
          locals = [ class java/lang/String, int ]
      LineNumberTable:
        line 219: 0
      LocalVariableTable:
        Start  Length  Slot  Name   Signature
            0      15     0  this   Los/PathError$LastOnEmptyPath;
            0      15     1   x$1   I
    MethodParameters:
      Name                           Flags
      x$1                            final

  public int hashCode();
    descriptor: ()I
    flags: (0x0001) ACC_PUBLIC
    Code:
      stack=2, locals=1, args_size=1
         0: getstatic     #49                 // Field scala/runtime/ScalaRunTime$.MODULE$:Lscala/runtime/ScalaRunTime$;
         3: aload_0
         4: invokevirtual #64                 // Method scala/runtime/ScalaRunTime$._hashCode:(Lscala/Product;)I
         7: ireturn
      LineNumberTable:
        line 219: 0
      LocalVariableTable:
        Start  Length  Slot  Name   Signature
            0       8     0  this   Los/PathError$LastOnEmptyPath;

  public boolean equals(java.lang.Object);
    descriptor: (Ljava/lang/Object;)Z
    flags: (0x0001) ACC_PUBLIC
    Code:
      stack=2, locals=4, args_size=2
         0: aload_1
         1: astore_3
         2: aload_3
         3: instanceof    #2                  // class os/PathError$LastOnEmptyPath
         6: ifeq          14
         9: iconst_1
        10: istore_2
        11: goto          22
        14: goto          17
        17: iconst_0
        18: istore_2
        19: goto          22
        22: iload_2
        23: ifeq          41
        26: aload_1
        27: checkcast     #2                  // class os/PathError$LastOnEmptyPath
        30: aload_0
        31: invokevirtual #67                 // Method canEqual:(Ljava/lang/Object;)Z
        34: ifeq          41
        37: iconst_1
        38: goto          42
        41: iconst_0
        42: ireturn
      StackMapTable: number_of_entries = 5
        frame_type = 253 /* append */
          offset_delta = 14
          locals = [ top, class java/lang/Object ]
        frame_type = 2 /* same */
        frame_type = 255 /* full_frame */
          offset_delta = 4
          locals = [ class os/PathError$LastOnEmptyPath, class java/lang/Object, int, class java/lang/Object ]
          stack = []
        frame_type = 18 /* same */
        frame_type = 64 /* same_locals_1_stack_item */
          stack = [ int ]
      LineNumberTable:
        line 219: 0
      LocalVariableTable:
        Start  Length  Slot  Name   Signature
            0      43     0  this   Los/PathError$LastOnEmptyPath;
            0      43     1   x$1   Ljava/lang/Object;
    MethodParameters:
      Name                           Flags
      x$1                            final

  public os.PathError$LastOnEmptyPath();
    descriptor: ()V
    flags: (0x0001) ACC_PUBLIC
    Code:
      stack=2, locals=1, args_size=1
         0: aload_0
         1: ldc           #69                 // String empty path has no last segment
         3: invokespecial #72                 // Method java/lang/IllegalArgumentException."<init>":(Ljava/lang/String;)V
         6: aload_0
         7: invokestatic  #76                 // InterfaceMethod scala/Product.$init$:(Lscala/Product;)V
        10: return
      LineNumberTable:
        line 220: 0
        line 219: 10
      LocalVariableTable:
        Start  Length  Slot  Name   Signature
            0      11     0  this   Los/PathError$LastOnEmptyPath;
}
InnerClasses:
  public static #10= #2 of #9;            // LastOnEmptyPath=class os/PathError$LastOnEmptyPath of class os/PathError
SourceFile: "Path.scala"
  ScalaInlineInfo: length = 0x3B (unknown attribute)
   01 00 00 0B 00 16 00 17 00 00 35 00 36 00 00 14
   00 15 00 00 41 00 36 00 00 3C 00 1E 00 00 1D 00
   1E 00 00 1F 00 20 00 00 38 00 39 00 00 0B 00 0C
   00 00 2A 00 0C 00 00 1A 00 1B 00
  Scala: length = 0x0 (unknown attribute)

