Classfile /Users/mw/Projects/slang-braindump/.jar/jar11/assemble/slang-braindump/assemble/content/os/PathError$LastOnEmptyPath$.class
  Last modified May 29, 2022; size 1412 bytes
  SHA-256 checksum f4d7348b1e5bf69690431aeaab8e5450374b25542a9a248022b99dabd7a5c035
  Compiled from "Path.scala"
public class os.PathError$LastOnEmptyPath$ extends scala.runtime.AbstractFunction0<os.PathError$LastOnEmptyPath> implements java.io.Serializable
  minor version: 0
  major version: 52
  flags: (0x0021) ACC_PUBLIC, ACC_SUPER
  this_class: #2                          // os/PathError$LastOnEmptyPath$
  super_class: #5                         // scala/runtime/AbstractFunction0
  interfaces: 1, fields: 1, methods: 7, attributes: 5
Constant pool:
   #1 = Utf8               os/PathError$LastOnEmptyPath$
   #2 = Class              #1             // os/PathError$LastOnEmptyPath$
   #3 = Utf8               Lscala/runtime/AbstractFunction0<Los/PathError$LastOnEmptyPath;>;Ljava/io/Serializable;
   #4 = Utf8               scala/runtime/AbstractFunction0
   #5 = Class              #4             // scala/runtime/AbstractFunction0
   #6 = Utf8               java/io/Serializable
   #7 = Class              #6             // java/io/Serializable
   #8 = Utf8               Path.scala
   #9 = Utf8               os/PathError$LastOnEmptyPath
  #10 = Class              #9             // os/PathError$LastOnEmptyPath
  #11 = Utf8               os/PathError
  #12 = Class              #11            // os/PathError
  #13 = Utf8               LastOnEmptyPath
  #14 = Utf8               LastOnEmptyPath$
  #15 = Utf8               MODULE$
  #16 = Utf8               Los/PathError$LastOnEmptyPath$;
  #17 = Utf8               <clinit>
  #18 = Utf8               ()V
  #19 = Utf8               <init>
  #20 = NameAndType        #19:#18        // "<init>":()V
  #21 = Methodref          #2.#20         // os/PathError$LastOnEmptyPath$."<init>":()V
  #22 = NameAndType        #15:#16        // MODULE$:Los/PathError$LastOnEmptyPath$;
  #23 = Fieldref           #2.#22         // os/PathError$LastOnEmptyPath$.MODULE$:Los/PathError$LastOnEmptyPath$;
  #24 = Utf8               toString
  #25 = Utf8               ()Ljava/lang/String;
  #26 = String             #13            // LastOnEmptyPath
  #27 = Utf8               this
  #28 = Utf8               apply
  #29 = Utf8               ()Los/PathError$LastOnEmptyPath;
  #30 = Methodref          #10.#20        // os/PathError$LastOnEmptyPath."<init>":()V
  #31 = Utf8               unapply
  #32 = Utf8               (Los/PathError$LastOnEmptyPath;)Z
  #33 = Utf8               x$0
  #34 = Utf8               Los/PathError$LastOnEmptyPath;
  #35 = Utf8               writeReplace
  #36 = Utf8               ()Ljava/lang/Object;
  #37 = Utf8               scala/runtime/ModuleSerializationProxy
  #38 = Class              #37            // scala/runtime/ModuleSerializationProxy
  #39 = Utf8               (Ljava/lang/Class;)V
  #40 = NameAndType        #19:#39        // "<init>":(Ljava/lang/Class;)V
  #41 = Methodref          #38.#40        // scala/runtime/ModuleSerializationProxy."<init>":(Ljava/lang/Class;)V
  #42 = NameAndType        #28:#29        // apply:()Los/PathError$LastOnEmptyPath;
  #43 = Methodref          #2.#42         // os/PathError$LastOnEmptyPath$.apply:()Los/PathError$LastOnEmptyPath;
  #44 = Methodref          #5.#20         // scala/runtime/AbstractFunction0."<init>":()V
  #45 = Utf8               Code
  #46 = Utf8               LineNumberTable
  #47 = Utf8               LocalVariableTable
  #48 = Utf8               StackMapTable
  #49 = Utf8               MethodParameters
  #50 = Utf8               InnerClasses
  #51 = Utf8               Signature
  #52 = Utf8               SourceFile
  #53 = Utf8               ScalaInlineInfo
  #54 = Utf8               Scala
{
  public static final os.PathError$LastOnEmptyPath$ MODULE$;
    descriptor: Los/PathError$LastOnEmptyPath$;
    flags: (0x0019) ACC_PUBLIC, ACC_STATIC, ACC_FINAL

  public static {};
    descriptor: ()V
    flags: (0x0009) ACC_PUBLIC, ACC_STATIC
    Code:
      stack=2, locals=0, args_size=0
         0: new           #2                  // class os/PathError$LastOnEmptyPath$
         3: dup
         4: invokespecial #21                 // Method "<init>":()V
         7: putstatic     #23                 // Field MODULE$:Los/PathError$LastOnEmptyPath$;
        10: return
      LineNumberTable:
        line 219: 0

  public final java.lang.String toString();
    descriptor: ()Ljava/lang/String;
    flags: (0x0011) ACC_PUBLIC, ACC_FINAL
    Code:
      stack=1, locals=1, args_size=1
         0: ldc           #26                 // String LastOnEmptyPath
         2: areturn
      LineNumberTable:
        line 219: 0
      LocalVariableTable:
        Start  Length  Slot  Name   Signature
            0       3     0  this   Los/PathError$LastOnEmptyPath$;

  public os.PathError$LastOnEmptyPath apply();
    descriptor: ()Los/PathError$LastOnEmptyPath;
    flags: (0x0001) ACC_PUBLIC
    Code:
      stack=2, locals=1, args_size=1
         0: new           #10                 // class os/PathError$LastOnEmptyPath
         3: dup
         4: invokespecial #30                 // Method os/PathError$LastOnEmptyPath."<init>":()V
         7: areturn
      LineNumberTable:
        line 219: 0
      LocalVariableTable:
        Start  Length  Slot  Name   Signature
            0       8     0  this   Los/PathError$LastOnEmptyPath$;

  public boolean unapply(os.PathError$LastOnEmptyPath);
    descriptor: (Los/PathError$LastOnEmptyPath;)Z
    flags: (0x0001) ACC_PUBLIC
    Code:
      stack=1, locals=2, args_size=2
         0: aload_1
         1: ifnonnull     8
         4: iconst_0
         5: goto          9
         8: iconst_1
         9: ireturn
      StackMapTable: number_of_entries = 2
        frame_type = 8 /* same */
        frame_type = 64 /* same_locals_1_stack_item */
          stack = [ int ]
      LineNumberTable:
        line 219: 0
      LocalVariableTable:
        Start  Length  Slot  Name   Signature
            0      10     0  this   Los/PathError$LastOnEmptyPath$;
            0      10     1   x$0   Los/PathError$LastOnEmptyPath;
    MethodParameters:
      Name                           Flags
      x$0                            final

  private java.lang.Object writeReplace();
    descriptor: ()Ljava/lang/Object;
    flags: (0x0002) ACC_PRIVATE
    Code:
      stack=3, locals=1, args_size=1
         0: new           #38                 // class scala/runtime/ModuleSerializationProxy
         3: dup
         4: ldc           #2                  // class os/PathError$LastOnEmptyPath$
         6: invokespecial #41                 // Method scala/runtime/ModuleSerializationProxy."<init>":(Ljava/lang/Class;)V
         9: areturn
      LineNumberTable:
        line 219: 0
      LocalVariableTable:
        Start  Length  Slot  Name   Signature
            0      10     0  this   Los/PathError$LastOnEmptyPath$;

  public java.lang.Object apply();
    descriptor: ()Ljava/lang/Object;
    flags: (0x1041) ACC_PUBLIC, ACC_BRIDGE, ACC_SYNTHETIC
    Code:
      stack=1, locals=1, args_size=1
         0: aload_0
         1: invokevirtual #43                 // Method apply:()Los/PathError$LastOnEmptyPath;
         4: areturn
      LineNumberTable:
        line 219: 0
      LocalVariableTable:
        Start  Length  Slot  Name   Signature
            0       5     0  this   Los/PathError$LastOnEmptyPath$;

  public os.PathError$LastOnEmptyPath$();
    descriptor: ()V
    flags: (0x0001) ACC_PUBLIC
    Code:
      stack=1, locals=1, args_size=1
         0: aload_0
         1: invokespecial #44                 // Method scala/runtime/AbstractFunction0."<init>":()V
         4: return
      LineNumberTable:
        line 219: 0
      LocalVariableTable:
        Start  Length  Slot  Name   Signature
            0       5     0  this   Los/PathError$LastOnEmptyPath$;
}
InnerClasses:
  public static #13= #10 of #12;          // LastOnEmptyPath=class os/PathError$LastOnEmptyPath of class os/PathError
  public static #14= #2 of #12;           // LastOnEmptyPath$=class os/PathError$LastOnEmptyPath$ of class os/PathError
Signature: #3                           // Lscala/runtime/AbstractFunction0<Los/PathError$LastOnEmptyPath;>;Ljava/io/Serializable;
SourceFile: "Path.scala"
  ScalaInlineInfo: length = 0x22 (unknown attribute)
   01 01 00 06 00 13 00 12 01 00 1C 00 24 01 00 1C
   00 1D 01 00 18 00 19 01 00 1F 00 20 01 00 23 00
   24 01
  Scala: length = 0x0 (unknown attribute)

