Classfile /Users/mw/Projects/slang-braindump/.jar/jar11/assemble/slang-braindump/assemble/content/os/PermSet.class
  Last modified May 29, 2022; size 8139 bytes
  SHA-256 checksum 10c8c80158fb03d28020326c1606380220860bdd449b6ac669cf99f575b5b08f
  Compiled from "Model.scala"
public class os.PermSet implements scala.Product,java.io.Serializable
  minor version: 0
  major version: 52
  flags: (0x0021) ACC_PUBLIC, ACC_SUPER
  this_class: #2                          // os/PermSet
  super_class: #4                         // java/lang/Object
  interfaces: 2, fields: 1, methods: 31, attributes: 5
Constant pool:
    #1 = Utf8               os/PermSet
    #2 = Class              #1            // os/PermSet
    #3 = Utf8               java/lang/Object
    #4 = Class              #3            // java/lang/Object
    #5 = Utf8               scala/Product
    #6 = Class              #5            // scala/Product
    #7 = Utf8               java/io/Serializable
    #8 = Class              #7            // java/io/Serializable
    #9 = Utf8               Model.scala
   #10 = Utf8               Lscala/reflect/ScalaSignature;
   #11 = Utf8               bytes
   #12 = Utf8               \u0006\u0005\u0005Mv!\u0002\u0012$\u0011\u00031c!\u0002\u0015$\u0011\u0003I\u0003\"\u0002\u001d\u0002\t\u0003I\u0004\"\u0002\u001e\u0002\t\u0007Y\u0004bBA1\u0003\u0011\r\u00111\r\u0005\b\u0003o\nA1AA=\u0011\u001d\ti(\u0001C\u0001\u0003\u007fBq!a!\u0002\t\u0003\t)\tC\u0004\u0002\u0010\u0006!\t!!%\t\u0013\u0005U\u0015!!A\u0005\u0002\u0006]\u0005\"CAN\u0003\u0005\u0005I\u0011QAO\u0011%\tI+AA\u0001\n\u0013\tYK\u0002\u0003)G\u0001k\u0004\u0002\u0003\'\r\u0005+\u0007I\u0011A\'\t\u0011Ec!\u0011#Q\u0001\n9CQ\u0001\u000f\u0007\u0005\u0002ICQ\u0001\u0016\u0007\u0005\u0002UCQ!\u001a\u0007\u0005\u0002\u0019DQ\u0001\u001b\u0007\u0005\u0002%DQ\u0001\u001c\u0007\u0005\u00025DQa\u001c\u0007\u0005\u0002ADQA\u001d\u0007\u0005\u0002MDQ\u0001\u001e\u0007\u0005\u0002UDQ\u0001 \u0007\u0005BuD\u0011\"!\u0003\r\u0003\u0003%\t!a\u0003\t\u0013\u0005=A\"%A\u0005\u0002\u0005E\u0001\"CA\u0014\u0019\u0005\u0005I\u0011IA\u0015\u0011!\tY\u0003DA\u0001\n\u0003i\u0005\"CA\u0017\u0019\u0005\u0005I\u0011AA\u0018\u0011%\tY\u0004DA\u0001\n\u0003\ni\u0004C\u0005\u0002L1\t\t\u0011\"\u0001\u0002N!I\u0011\u0011\u000b\u0007\u0002\u0002\u0013\u0005\u00131\u000b\u0005\t\u0003/b\u0011\u0011!C!g\"I\u0011\u0011\f\u0007\u0002\u0002\u0013\u0005\u00131L\u0001\b!\u0016\u0014XnU3u\u0015\u0005!\u0013AA8t\u0007\u0001\u0001\"aJ\u0001\u000e\u0003\r\u0012q\u0001U3s[N+GoE\u0002\u0002UA\u0002\"a\u000b\u0018\u000e\u00031R\u0011!L\u0001\u0006g\u000e\fG.Y\u0005\u0003_1\u0012a!\u00118z%\u00164\u0007CA\u00197\u001b\u0005\u0011$BA\u001a5\u0003\tIwNC\u00016\u0003\u0011Q\u0017M^1\n\u0005]\u0012$\u0001D*fe&\fG.\u001b>bE2,\u0017A\u0002\u001fj]&$h\bF\u0001\'\u0003\u001d1\'o\\7TKR$2\u0001PA0!\t9Cb\u0005\u0003\rUy\n\u0005CA\u0016@\u0013\t\u0001EFA\u0004Qe>$Wo\u0019;\u0011\u0005\tSeBA\"I\u001d\t!u)D\u0001F\u0015\t1U%\u0001\u0004=e>|GOP\u0005\u0002[%\u0011\u0011\nL\u0001\ba\u0006\u001c7.Y4f\u0013\t94J\u0003\u0002JY\u0005)a/\u00197vKV\ta\n\u0005\u0002,\u001f&\u0011\u0001\u000b\f\u0002\u0004\u0013:$\u0018A\u0002<bYV,\u0007\u0005\u0006\u0002=\'\")Aj\u0004a\u0001\u001d\u0006A1m\u001c8uC&t7\u000f\u0006\u0002W3B\u00111fV\u0005\u000312\u0012qAQ8pY\u0016\fg\u000eC\u0003[!\u0001\u00071,\u0001\u0003fY\u0016l\u0007C\u0001/d\u001b\u0005i&B\u00010`\u0003%\tG\u000f\u001e:jEV$XM\u0003\u0002aC\u0006!a-\u001b7f\u0015\t\u0011G\'A\u0002oS>L!\u0001Z/\u0003\'A{7/\u001b=GS2,\u0007+\u001a:nSN\u001c\u0018n\u001c8\u0002\u000b\u0011\u0002H.^:\u0015\u0005q:\u0007\"\u0002.\u0012\u0001\u0004Y\u0016A\u0003\u0013qYV\u001cH\u0005\u001d7vgR\u0011AH\u001b\u0005\u0006WJ\u0001\r\u0001P\u0001\u0006_RDWM]\u0001\u0007I5Lg.^:\u0015\u0005qr\u0007\"\u0002.\u0014\u0001\u0004Y\u0016\u0001\u0004\u0013nS:,8\u000fJ7j]V\u001cHC\u0001\u001fr\u0011\u0015YG\u00031\u0001=\u0003\u0015!x.\u00138u)\u0005q\u0015!\u0002;p\'\u0016$H#\u0001<\u0011\u0007]T8,D\u0001y\u0015\tIH\'\u0001\u0003vi&d\u0017BA>y\u0005\r\u0019V\r^\u0001\ti>\u001cFO]5oOR\ta\u0010E\u0002\u0000\u0003\u000bi!!!\u0001\u000b\u0007\u0005\rA\'\u0001\u0003mC:<\u0017\u0002BA\u0004\u0003\u0003\u0011aa\u0015;sS:<\u0017\u0001B2paf$2\u0001PA\u0007\u0011\u001da\u0005\u0004%AA\u00029\u000babY8qs\u0012\"WMZ1vYR$\u0013\'\u0006\u0002\u0002\u0014)\u001aa*!\u0006,\u0005\u0005]\u0001\u0003BA\r\u0003Gi!!a\u0007\u000b\t\u0005u\u0011qD\u0001\nk:\u001c\u0007.Z2lK\u0012T1!!\t-\u0003)\tgN\\8uCRLwN\\\u0005\u0005\u0003K\tYBA\tv]\u000eDWmY6fIZ\u000b\'/[1oG\u0016\fQ\u0002\u001d:pIV\u001cG\u000f\u0015:fM&DX#\u0001@\u0002\u0019A\u0014x\u000eZ;di\u0006\u0013\u0018\u000e^=\u0002\u001dA\u0014x\u000eZ;di\u0016cW-\\3oiR!\u0011\u0011GA\u001c!\rY\u00131G\u0005\u0004\u0003ka#aA!os\"A\u0011\u0011\b\u000f\u0002\u0002\u0003\u0007a*A\u0002yIE\nq\u0002\u001d:pIV\u001cG/\u0013;fe\u0006$xN]\u000b\u0003\u0003\u007f\u0001b!!\u0011\u0002H\u0005ERBAA\"\u0015\r\t)\u0005L\u0001\u000bG>dG.Z2uS>t\u0017\u0002BA%\u0003\u0007\u0012\u0001\"\u0013;fe\u0006$xN]\u0001\tG\u0006tW)];bYR\u0019a+a\u0014\t\u0013\u0005eb$!AA\u0002\u0005E\u0012A\u00059s_\u0012,8\r^#mK6,g\u000e\u001e(b[\u0016$2A`A+\u0011!\tIdHA\u0001\u0002\u0004q\u0015\u0001\u00035bg\"\u001cu\u000eZ3\u0002\r\u0015\fX/\u00197t)\r1\u0016Q\f\u0005\n\u0003s\t\u0013\u0011!a\u0001\u0003cAQ\u0001T\u0002A\u0002Y\f!B\u001a:p[N#(/\u001b8h)\ra\u0014Q\r\u0005\b\u0003O\"\u0001\u0019AA5\u0003\r\t\'o\u001a\t\u0005\u0003W\n\u0019H\u0004\u0003\u0002n\u0005=\u0004C\u0001#-\u0013\r\t\t\bL\u0001\u0007!J,G-\u001a4\n\t\u0005\u001d\u0011Q\u000f\u0006\u0004\u0003cb\u0013a\u00024s_6Le\u000e\u001e\u000b\u0004y\u0005m\u0004\"\u0002\'\u0006\u0001\u0004q\u0015A\u00039fe6$v.T1tWR\u0019a*!!\t\u000bi3\u0001\u0019A.\u0002\u0015A,\'/\u001c+p\u0007\"\f\'\u000f\u0006\u0003\u0002\b\u00065\u0005cA\u0016\u0002\n&\u0019\u00111\u0012\u0017\u0003\t\rC\u0017M\u001d\u0005\u00065\u001e\u0001\raW\u0001\ra\u0016\u0014X\u000eV8PM\u001a\u001cX\r\u001e\u000b\u0004\u001d\u0006M\u0005\"\u0002.\t\u0001\u0004Y\u0016!B1qa2LHc\u0001\u001f\u0002\u001a\")A*\u0003a\u0001\u001d\u00069QO\\1qa2LH\u0003BAP\u0003K\u0003BaKAQ\u001d&\u0019\u00111\u0015\u0017\u0003\r=\u0003H/[8o\u0011!\t9KCA\u0001\u0002\u0004a\u0014a\u0001=%a\u0005aqO]5uKJ+\u0007\u000f\\1dKR\u0011\u0011Q\u0016\t\u0004\u007f\u0006=\u0016\u0002BAY\u0003\u0003\u0011aa\u00142kK\u000e$\b
   #13 = Utf8               scala/reflect/ManifestFactory$CharManifest
   #14 = Class              #13           // scala/reflect/ManifestFactory$CharManifest
   #15 = Utf8               scala/reflect/ManifestFactory
   #16 = Class              #15           // scala/reflect/ManifestFactory
   #17 = Utf8               CharManifest
   #18 = Utf8               value
   #19 = Utf8               I
   #20 = Utf8               unapply
   #21 = Utf8               (Los/PermSet;)Lscala/Option;
   #22 = Utf8               (Los/PermSet;)Lscala/Option<Ljava/lang/Object;>;
   #23 = Utf8               x$0
   #24 = Utf8               os/PermSet$
   #25 = Class              #24           // os/PermSet$
   #26 = Utf8               MODULE$
   #27 = Utf8               Los/PermSet$;
   #28 = NameAndType        #26:#27       // MODULE$:Los/PermSet$;
   #29 = Fieldref           #25.#28       // os/PermSet$.MODULE$:Los/PermSet$;
   #30 = NameAndType        #20:#21       // unapply:(Los/PermSet;)Lscala/Option;
   #31 = Methodref          #25.#30       // os/PermSet$.unapply:(Los/PermSet;)Lscala/Option;
   #32 = Utf8               apply
   #33 = Utf8               (I)Los/PermSet;
   #34 = NameAndType        #32:#33       // apply:(I)Los/PermSet;
   #35 = Methodref          #25.#34       // os/PermSet$.apply:(I)Los/PermSet;
   #36 = Utf8               permToOffset
   #37 = Utf8               (Ljava/nio/file/attribute/PosixFilePermission;)I
   #38 = Utf8               elem
   #39 = NameAndType        #36:#37       // permToOffset:(Ljava/nio/file/attribute/PosixFilePermission;)I
   #40 = Methodref          #25.#39       // os/PermSet$.permToOffset:(Ljava/nio/file/attribute/PosixFilePermission;)I
   #41 = Utf8               permToChar
   #42 = Utf8               (Ljava/nio/file/attribute/PosixFilePermission;)C
   #43 = NameAndType        #41:#42       // permToChar:(Ljava/nio/file/attribute/PosixFilePermission;)C
   #44 = Methodref          #25.#43       // os/PermSet$.permToChar:(Ljava/nio/file/attribute/PosixFilePermission;)C
   #45 = Utf8               permToMask
   #46 = NameAndType        #45:#37       // permToMask:(Ljava/nio/file/attribute/PosixFilePermission;)I
   #47 = Methodref          #25.#46       // os/PermSet$.permToMask:(Ljava/nio/file/attribute/PosixFilePermission;)I
   #48 = Utf8               fromInt
   #49 = NameAndType        #48:#33       // fromInt:(I)Los/PermSet;
   #50 = Methodref          #25.#49       // os/PermSet$.fromInt:(I)Los/PermSet;
   #51 = Utf8               fromString
   #52 = Utf8               (Ljava/lang/String;)Los/PermSet;
   #53 = Utf8               arg
   #54 = NameAndType        #51:#52       // fromString:(Ljava/lang/String;)Los/PermSet;
   #55 = Methodref          #25.#54       // os/PermSet$.fromString:(Ljava/lang/String;)Los/PermSet;
   #56 = Utf8               fromSet
   #57 = Utf8               (Ljava/util/Set;)Los/PermSet;
   #58 = Utf8               (Ljava/util/Set<Ljava/nio/file/attribute/PosixFilePermission;>;)Los/PermSet;
   #59 = NameAndType        #56:#57       // fromSet:(Ljava/util/Set;)Los/PermSet;
   #60 = Methodref          #25.#59       // os/PermSet$.fromSet:(Ljava/util/Set;)Los/PermSet;
   #61 = Utf8               productElementNames
   #62 = Utf8               ()Lscala/collection/Iterator;
   #63 = Utf8               ()Lscala/collection/Iterator<Ljava/lang/String;>;
   #64 = Utf8               productElementNames$
   #65 = Utf8               (Lscala/Product;)Lscala/collection/Iterator;
   #66 = NameAndType        #64:#65       // productElementNames$:(Lscala/Product;)Lscala/collection/Iterator;
   #67 = InterfaceMethodref #6.#66        // scala/Product.productElementNames$:(Lscala/Product;)Lscala/collection/Iterator;
   #68 = Utf8               this
   #69 = Utf8               Los/PermSet;
   #70 = Utf8               ()I
   #71 = NameAndType        #18:#19       // value:I
   #72 = Fieldref           #2.#71        // os/PermSet.value:I
   #73 = Utf8               contains
   #74 = Utf8               (Ljava/nio/file/attribute/PosixFilePermission;)Z
   #75 = NameAndType        #18:#70       // value:()I
   #76 = Methodref          #2.#75        // os/PermSet.value:()I
   #77 = Utf8               Ljava/nio/file/attribute/PosixFilePermission;
   #78 = Utf8               $plus
   #79 = Utf8               (Ljava/nio/file/attribute/PosixFilePermission;)Los/PermSet;
   #80 = Utf8               <init>
   #81 = Utf8               (I)V
   #82 = NameAndType        #80:#81       // "<init>":(I)V
   #83 = Methodref          #2.#82        // os/PermSet."<init>":(I)V
   #84 = Utf8               $plus$plus
   #85 = Utf8               (Los/PermSet;)Los/PermSet;
   #86 = Utf8               other
   #87 = Utf8               $minus
   #88 = Utf8               $minus$minus
   #89 = Utf8               toInt
   #90 = Utf8               toSet
   #91 = Utf8               ()Ljava/util/Set;
   #92 = Utf8               ()Ljava/util/Set<Ljava/nio/file/attribute/PosixFilePermission;>;
   #93 = Utf8               java/util/HashSet
   #94 = Class              #93           // java/util/HashSet
   #95 = Utf8               ()V
   #96 = NameAndType        #80:#95       // "<init>":()V
   #97 = Methodref          #94.#96       // java/util/HashSet."<init>":()V
   #98 = Utf8               java/nio/file/attribute/PosixFilePermission
   #99 = Class              #98           // java/nio/file/attribute/PosixFilePermission
  #100 = Utf8               OWNER_READ
  #101 = NameAndType        #100:#77      // OWNER_READ:Ljava/nio/file/attribute/PosixFilePermission;
  #102 = Fieldref           #99.#101      // java/nio/file/attribute/PosixFilePermission.OWNER_READ:Ljava/nio/file/attribute/PosixFilePermission;
  #103 = Utf8               add$3
  #104 = Utf8               (Ljava/nio/file/attribute/PosixFilePermission;Ljava/util/HashSet;)Ljava/lang/Object;
  #105 = NameAndType        #103:#104     // add$3:(Ljava/nio/file/attribute/PosixFilePermission;Ljava/util/HashSet;)Ljava/lang/Object;
  #106 = Methodref          #2.#105       // os/PermSet.add$3:(Ljava/nio/file/attribute/PosixFilePermission;Ljava/util/HashSet;)Ljava/lang/Object;
  #107 = Utf8               OWNER_WRITE
  #108 = NameAndType        #107:#77      // OWNER_WRITE:Ljava/nio/file/attribute/PosixFilePermission;
  #109 = Fieldref           #99.#108      // java/nio/file/attribute/PosixFilePermission.OWNER_WRITE:Ljava/nio/file/attribute/PosixFilePermission;
  #110 = Utf8               OWNER_EXECUTE
  #111 = NameAndType        #110:#77      // OWNER_EXECUTE:Ljava/nio/file/attribute/PosixFilePermission;
  #112 = Fieldref           #99.#111      // java/nio/file/attribute/PosixFilePermission.OWNER_EXECUTE:Ljava/nio/file/attribute/PosixFilePermission;
  #113 = Utf8               GROUP_READ
  #114 = NameAndType        #113:#77      // GROUP_READ:Ljava/nio/file/attribute/PosixFilePermission;
  #115 = Fieldref           #99.#114      // java/nio/file/attribute/PosixFilePermission.GROUP_READ:Ljava/nio/file/attribute/PosixFilePermission;
  #116 = Utf8               GROUP_WRITE
  #117 = NameAndType        #116:#77      // GROUP_WRITE:Ljava/nio/file/attribute/PosixFilePermission;
  #118 = Fieldref           #99.#117      // java/nio/file/attribute/PosixFilePermission.GROUP_WRITE:Ljava/nio/file/attribute/PosixFilePermission;
  #119 = Utf8               GROUP_EXECUTE
  #120 = NameAndType        #119:#77      // GROUP_EXECUTE:Ljava/nio/file/attribute/PosixFilePermission;
  #121 = Fieldref           #99.#120      // java/nio/file/attribute/PosixFilePermission.GROUP_EXECUTE:Ljava/nio/file/attribute/PosixFilePermission;
  #122 = Utf8               OTHERS_READ
  #123 = NameAndType        #122:#77      // OTHERS_READ:Ljava/nio/file/attribute/PosixFilePermission;
  #124 = Fieldref           #99.#123      // java/nio/file/attribute/PosixFilePermission.OTHERS_READ:Ljava/nio/file/attribute/PosixFilePermission;
  #125 = Utf8               OTHERS_WRITE
  #126 = NameAndType        #125:#77      // OTHERS_WRITE:Ljava/nio/file/attribute/PosixFilePermission;
  #127 = Fieldref           #99.#126      // java/nio/file/attribute/PosixFilePermission.OTHERS_WRITE:Ljava/nio/file/attribute/PosixFilePermission;
  #128 = Utf8               OTHERS_EXECUTE
  #129 = NameAndType        #128:#77      // OTHERS_EXECUTE:Ljava/nio/file/attribute/PosixFilePermission;
  #130 = Fieldref           #99.#129      // java/nio/file/attribute/PosixFilePermission.OTHERS_EXECUTE:Ljava/nio/file/attribute/PosixFilePermission;
  #131 = Utf8               perms
  #132 = Utf8               Ljava/util/HashSet;
  #133 = Utf8               toString
  #134 = Utf8               ()Ljava/lang/String;
  #135 = Utf8               java/lang/String
  #136 = Class              #135          // java/lang/String
  #137 = Utf8               scala/Array$
  #138 = Class              #137          // scala/Array$
  #139 = Utf8               Lscala/Array$;
  #140 = NameAndType        #26:#139      // MODULE$:Lscala/Array$;
  #141 = Fieldref           #138.#140     // scala/Array$.MODULE$:Lscala/Array$;
  #142 = Utf8               scala/runtime/ScalaRunTime$
  #143 = Class              #142          // scala/runtime/ScalaRunTime$
  #144 = Utf8               Lscala/runtime/ScalaRunTime$;
  #145 = NameAndType        #26:#144      // MODULE$:Lscala/runtime/ScalaRunTime$;
  #146 = Fieldref           #143.#145     // scala/runtime/ScalaRunTime$.MODULE$:Lscala/runtime/ScalaRunTime$;
  #147 = Utf8               add$4
  #148 = NameAndType        #147:#42      // add$4:(Ljava/nio/file/attribute/PosixFilePermission;)C
  #149 = Methodref          #2.#148       // os/PermSet.add$4:(Ljava/nio/file/attribute/PosixFilePermission;)C
  #150 = Utf8               wrapCharArray
  #151 = Utf8               ([C)Lscala/collection/immutable/ArraySeq;
  #152 = NameAndType        #150:#151     // wrapCharArray:([C)Lscala/collection/immutable/ArraySeq;
  #153 = Methodref          #143.#152     // scala/runtime/ScalaRunTime$.wrapCharArray:([C)Lscala/collection/immutable/ArraySeq;
  #154 = Utf8               scala/reflect/ClassTag$
  #155 = Class              #154          // scala/reflect/ClassTag$
  #156 = Utf8               Lscala/reflect/ClassTag$;
  #157 = NameAndType        #26:#156      // MODULE$:Lscala/reflect/ClassTag$;
  #158 = Fieldref           #155.#157     // scala/reflect/ClassTag$.MODULE$:Lscala/reflect/ClassTag$;
  #159 = Utf8               Char
  #160 = Utf8               ()Lscala/reflect/ManifestFactory$CharManifest;
  #161 = NameAndType        #159:#160     // Char:()Lscala/reflect/ManifestFactory$CharManifest;
  #162 = Methodref          #155.#161     // scala/reflect/ClassTag$.Char:()Lscala/reflect/ManifestFactory$CharManifest;
  #163 = Utf8               (Lscala/collection/immutable/Seq;Lscala/reflect/ClassTag;)Ljava/lang/Object;
  #164 = NameAndType        #32:#163      // apply:(Lscala/collection/immutable/Seq;Lscala/reflect/ClassTag;)Ljava/lang/Object;
  #165 = Methodref          #138.#164     // scala/Array$.apply:(Lscala/collection/immutable/Seq;Lscala/reflect/ClassTag;)Ljava/lang/Object;
  #166 = Utf8               [C
  #167 = Class              #166          // "[C"
  #168 = Utf8               ([C)V
  #169 = NameAndType        #80:#168      // "<init>":([C)V
  #170 = Methodref          #136.#169     // java/lang/String."<init>":([C)V
  #171 = Utf8               copy
  #172 = Utf8               copy$default$1
  #173 = Utf8               productPrefix
  #174 = Utf8               PermSet
  #175 = String             #174          // PermSet
  #176 = Utf8               productArity
  #177 = Utf8               productElement
  #178 = Utf8               (I)Ljava/lang/Object;
  #179 = Utf8               x$1
  #180 = Utf8               scala/runtime/BoxesRunTime
  #181 = Class              #180          // scala/runtime/BoxesRunTime
  #182 = Utf8               boxToInteger
  #183 = Utf8               (I)Ljava/lang/Integer;
  #184 = NameAndType        #182:#183     // boxToInteger:(I)Ljava/lang/Integer;
  #185 = Methodref          #181.#184     // scala/runtime/BoxesRunTime.boxToInteger:(I)Ljava/lang/Integer;
  #186 = Utf8               scala/runtime/Statics
  #187 = Class              #186          // scala/runtime/Statics
  #188 = Utf8               ioobe
  #189 = NameAndType        #188:#178     // ioobe:(I)Ljava/lang/Object;
  #190 = Methodref          #187.#189     // scala/runtime/Statics.ioobe:(I)Ljava/lang/Object;
  #191 = Utf8               productIterator
  #192 = Utf8               ()Lscala/collection/Iterator<Ljava/lang/Object;>;
  #193 = Utf8               typedProductIterator
  #194 = NameAndType        #193:#65      // typedProductIterator:(Lscala/Product;)Lscala/collection/Iterator;
  #195 = Methodref          #143.#194     // scala/runtime/ScalaRunTime$.typedProductIterator:(Lscala/Product;)Lscala/collection/Iterator;
  #196 = Utf8               canEqual
  #197 = Utf8               (Ljava/lang/Object;)Z
  #198 = Utf8               Ljava/lang/Object;
  #199 = Utf8               productElementName
  #200 = Utf8               (I)Ljava/lang/String;
  #201 = String             #18           // value
  #202 = Utf8               hashCode
  #203 = Integer            -889275714
  #204 = NameAndType        #173:#134     // productPrefix:()Ljava/lang/String;
  #205 = Methodref          #2.#204       // os/PermSet.productPrefix:()Ljava/lang/String;
  #206 = NameAndType        #202:#70      // hashCode:()I
  #207 = Methodref          #136.#206     // java/lang/String.hashCode:()I
  #208 = Utf8               mix
  #209 = Utf8               (II)I
  #210 = NameAndType        #208:#209     // mix:(II)I
  #211 = Methodref          #187.#210     // scala/runtime/Statics.mix:(II)I
  #212 = Utf8               finalizeHash
  #213 = NameAndType        #212:#209     // finalizeHash:(II)I
  #214 = Methodref          #187.#213     // scala/runtime/Statics.finalizeHash:(II)I
  #215 = Utf8               equals
  #216 = NameAndType        #196:#197     // canEqual:(Ljava/lang/Object;)Z
  #217 = Methodref          #2.#216       // os/PermSet.canEqual:(Ljava/lang/Object;)Z
  #218 = Utf8               perm
  #219 = Utf8               perms$2
  #220 = Utf8               add
  #221 = NameAndType        #220:#197     // add:(Ljava/lang/Object;)Z
  #222 = Methodref          #94.#221      // java/util/HashSet.add:(Ljava/lang/Object;)Z
  #223 = Utf8               boxToBoolean
  #224 = Utf8               (Z)Ljava/lang/Boolean;
  #225 = NameAndType        #223:#224     // boxToBoolean:(Z)Ljava/lang/Boolean;
  #226 = Methodref          #181.#225     // scala/runtime/BoxesRunTime.boxToBoolean:(Z)Ljava/lang/Boolean;
  #227 = Utf8               scala/runtime/BoxedUnit
  #228 = Class              #227          // scala/runtime/BoxedUnit
  #229 = Utf8               UNIT
  #230 = Utf8               Lscala/runtime/BoxedUnit;
  #231 = NameAndType        #229:#230     // UNIT:Lscala/runtime/BoxedUnit;
  #232 = Fieldref           #228.#231     // scala/runtime/BoxedUnit.UNIT:Lscala/runtime/BoxedUnit;
  #233 = Utf8               c
  #234 = Utf8               C
  #235 = Methodref          #4.#96        // java/lang/Object."<init>":()V
  #236 = Utf8               $init$
  #237 = Utf8               (Lscala/Product;)V
  #238 = NameAndType        #236:#237     // $init$:(Lscala/Product;)V
  #239 = InterfaceMethodref #6.#238       // scala/Product.$init$:(Lscala/Product;)V
  #240 = Utf8               Code
  #241 = Utf8               Signature
  #242 = Utf8               MethodParameters
  #243 = Utf8               LineNumberTable
  #244 = Utf8               LocalVariableTable
  #245 = Utf8               StackMapTable
  #246 = Utf8               InnerClasses
  #247 = Utf8               SourceFile
  #248 = Utf8               RuntimeVisibleAnnotations
  #249 = Utf8               ScalaInlineInfo
  #250 = Utf8               ScalaSig
{
  private final int value;
    descriptor: I
    flags: (0x0012) ACC_PRIVATE, ACC_FINAL

  public static scala.Option<java.lang.Object> unapply(os.PermSet);
    descriptor: (Los/PermSet;)Lscala/Option;
    flags: (0x0009) ACC_PUBLIC, ACC_STATIC
    Code:
      stack=2, locals=1, args_size=1
         0: getstatic     #29                 // Field os/PermSet$.MODULE$:Los/PermSet$;
         3: aload_0
         4: invokevirtual #31                 // Method os/PermSet$.unapply:(Los/PermSet;)Lscala/Option;
         7: areturn
    Signature: #22                          // (Los/PermSet;)Lscala/Option<Ljava/lang/Object;>;
    MethodParameters:
      Name                           Flags
      x$0                            final

  public static os.PermSet apply(int);
    descriptor: (I)Los/PermSet;
    flags: (0x0009) ACC_PUBLIC, ACC_STATIC
    Code:
      stack=2, locals=1, args_size=1
         0: getstatic     #29                 // Field os/PermSet$.MODULE$:Los/PermSet$;
         3: iload_0
         4: invokevirtual #35                 // Method os/PermSet$.apply:(I)Los/PermSet;
         7: areturn
    MethodParameters:
      Name                           Flags
      value                          final

  public static int permToOffset(java.nio.file.attribute.PosixFilePermission);
    descriptor: (Ljava/nio/file/attribute/PosixFilePermission;)I
    flags: (0x0009) ACC_PUBLIC, ACC_STATIC
    Code:
      stack=2, locals=1, args_size=1
         0: getstatic     #29                 // Field os/PermSet$.MODULE$:Los/PermSet$;
         3: aload_0
         4: invokevirtual #40                 // Method os/PermSet$.permToOffset:(Ljava/nio/file/attribute/PosixFilePermission;)I
         7: ireturn
    MethodParameters:
      Name                           Flags
      elem                           final

  public static char permToChar(java.nio.file.attribute.PosixFilePermission);
    descriptor: (Ljava/nio/file/attribute/PosixFilePermission;)C
    flags: (0x0009) ACC_PUBLIC, ACC_STATIC
    Code:
      stack=2, locals=1, args_size=1
         0: getstatic     #29                 // Field os/PermSet$.MODULE$:Los/PermSet$;
         3: aload_0
         4: invokevirtual #44                 // Method os/PermSet$.permToChar:(Ljava/nio/file/attribute/PosixFilePermission;)C
         7: ireturn
    MethodParameters:
      Name                           Flags
      elem                           final

  public static int permToMask(java.nio.file.attribute.PosixFilePermission);
    descriptor: (Ljava/nio/file/attribute/PosixFilePermission;)I
    flags: (0x0009) ACC_PUBLIC, ACC_STATIC
    Code:
      stack=2, locals=1, args_size=1
         0: getstatic     #29                 // Field os/PermSet$.MODULE$:Los/PermSet$;
         3: aload_0
         4: invokevirtual #47                 // Method os/PermSet$.permToMask:(Ljava/nio/file/attribute/PosixFilePermission;)I
         7: ireturn
    MethodParameters:
      Name                           Flags
      elem                           final

  public static os.PermSet fromInt(int);
    descriptor: (I)Los/PermSet;
    flags: (0x0009) ACC_PUBLIC, ACC_STATIC
    Code:
      stack=2, locals=1, args_size=1
         0: getstatic     #29                 // Field os/PermSet$.MODULE$:Los/PermSet$;
         3: iload_0
         4: invokevirtual #50                 // Method os/PermSet$.fromInt:(I)Los/PermSet;
         7: areturn
    MethodParameters:
      Name                           Flags
      value                          final

  public static os.PermSet fromString(java.lang.String);
    descriptor: (Ljava/lang/String;)Los/PermSet;
    flags: (0x0009) ACC_PUBLIC, ACC_STATIC
    Code:
      stack=2, locals=1, args_size=1
         0: getstatic     #29                 // Field os/PermSet$.MODULE$:Los/PermSet$;
         3: aload_0
         4: invokevirtual #55                 // Method os/PermSet$.fromString:(Ljava/lang/String;)Los/PermSet;
         7: areturn
    MethodParameters:
      Name                           Flags
      arg                            final

  public static os.PermSet fromSet(java.util.Set<java.nio.file.attribute.PosixFilePermission>);
    descriptor: (Ljava/util/Set;)Los/PermSet;
    flags: (0x0009) ACC_PUBLIC, ACC_STATIC
    Code:
      stack=2, locals=1, args_size=1
         0: getstatic     #29                 // Field os/PermSet$.MODULE$:Los/PermSet$;
         3: aload_0
         4: invokevirtual #60                 // Method os/PermSet$.fromSet:(Ljava/util/Set;)Los/PermSet;
         7: areturn
    Signature: #58                          // (Ljava/util/Set<Ljava/nio/file/attribute/PosixFilePermission;>;)Los/PermSet;
    MethodParameters:
      Name                           Flags
      value                          final

  public scala.collection.Iterator<java.lang.String> productElementNames();
    descriptor: ()Lscala/collection/Iterator;
    flags: (0x0001) ACC_PUBLIC
    Code:
      stack=1, locals=1, args_size=1
         0: aload_0
         1: invokestatic  #67                 // InterfaceMethod scala/Product.productElementNames$:(Lscala/Product;)Lscala/collection/Iterator;
         4: areturn
      LineNumberTable:
        line 109: 0
      LocalVariableTable:
        Start  Length  Slot  Name   Signature
            0       5     0  this   Los/PermSet;
    Signature: #63                          // ()Lscala/collection/Iterator<Ljava/lang/String;>;

  public int value();
    descriptor: ()I
    flags: (0x0001) ACC_PUBLIC
    Code:
      stack=1, locals=1, args_size=1
         0: aload_0
         1: getfield      #72                 // Field value:I
         4: ireturn
      LineNumberTable:
        line 109: 0
      LocalVariableTable:
        Start  Length  Slot  Name   Signature
            0       5     0  this   Los/PermSet;

  public boolean contains(java.nio.file.attribute.PosixFilePermission);
    descriptor: (Ljava/nio/file/attribute/PosixFilePermission;)Z
    flags: (0x0001) ACC_PUBLIC
    Code:
      stack=2, locals=2, args_size=2
         0: getstatic     #29                 // Field os/PermSet$.MODULE$:Los/PermSet$;
         3: aload_1
         4: invokevirtual #47                 // Method os/PermSet$.permToMask:(Ljava/nio/file/attribute/PosixFilePermission;)I
         7: aload_0
         8: invokevirtual #76                 // Method value:()I
        11: iand
        12: iconst_0
        13: if_icmpeq     20
        16: iconst_1
        17: goto          21
        20: iconst_0
        21: ireturn
      StackMapTable: number_of_entries = 2
        frame_type = 20 /* same */
        frame_type = 64 /* same_locals_1_stack_item */
          stack = [ int ]
      LineNumberTable:
        line 110: 0
      LocalVariableTable:
        Start  Length  Slot  Name   Signature
            0      22     0  this   Los/PermSet;
            0      22     1  elem   Ljava/nio/file/attribute/PosixFilePermission;
    MethodParameters:
      Name                           Flags
      elem                           final

  public os.PermSet $plus(java.nio.file.attribute.PosixFilePermission);
    descriptor: (Ljava/nio/file/attribute/PosixFilePermission;)Los/PermSet;
    flags: (0x0001) ACC_PUBLIC
    Code:
      stack=5, locals=2, args_size=2
         0: new           #2                  // class os/PermSet
         3: dup
         4: aload_0
         5: invokevirtual #76                 // Method value:()I
         8: getstatic     #29                 // Field os/PermSet$.MODULE$:Los/PermSet$;
        11: aload_1
        12: invokevirtual #47                 // Method os/PermSet$.permToMask:(Ljava/nio/file/attribute/PosixFilePermission;)I
        15: ior
        16: invokespecial #83                 // Method "<init>":(I)V
        19: areturn
      LineNumberTable:
        line 111: 0
      LocalVariableTable:
        Start  Length  Slot  Name   Signature
            0      20     0  this   Los/PermSet;
            0      20     1  elem   Ljava/nio/file/attribute/PosixFilePermission;
    MethodParameters:
      Name                           Flags
      elem                           final

  public os.PermSet $plus$plus(os.PermSet);
    descriptor: (Los/PermSet;)Los/PermSet;
    flags: (0x0001) ACC_PUBLIC
    Code:
      stack=4, locals=2, args_size=2
         0: new           #2                  // class os/PermSet
         3: dup
         4: aload_0
         5: invokevirtual #76                 // Method value:()I
         8: aload_1
         9: invokevirtual #76                 // Method value:()I
        12: ior
        13: invokespecial #83                 // Method "<init>":(I)V
        16: areturn
      LineNumberTable:
        line 112: 0
      LocalVariableTable:
        Start  Length  Slot  Name   Signature
            0      17     0  this   Los/PermSet;
            0      17     1 other   Los/PermSet;
    MethodParameters:
      Name                           Flags
      other                          final

  public os.PermSet $minus(java.nio.file.attribute.PosixFilePermission);
    descriptor: (Ljava/nio/file/attribute/PosixFilePermission;)Los/PermSet;
    flags: (0x0001) ACC_PUBLIC
    Code:
      stack=5, locals=2, args_size=2
         0: new           #2                  // class os/PermSet
         3: dup
         4: aload_0
         5: invokevirtual #76                 // Method value:()I
         8: getstatic     #29                 // Field os/PermSet$.MODULE$:Los/PermSet$;
        11: aload_1
        12: invokevirtual #47                 // Method os/PermSet$.permToMask:(Ljava/nio/file/attribute/PosixFilePermission;)I
        15: iconst_m1
        16: ixor
        17: iand
        18: invokespecial #83                 // Method "<init>":(I)V
        21: areturn
      LineNumberTable:
        line 114: 0
      LocalVariableTable:
        Start  Length  Slot  Name   Signature
            0      22     0  this   Los/PermSet;
            0      22     1  elem   Ljava/nio/file/attribute/PosixFilePermission;
    MethodParameters:
      Name                           Flags
      elem                           final

  public os.PermSet $minus$minus(os.PermSet);
    descriptor: (Los/PermSet;)Los/PermSet;
    flags: (0x0001) ACC_PUBLIC
    Code:
      stack=5, locals=2, args_size=2
         0: new           #2                  // class os/PermSet
         3: dup
         4: aload_0
         5: invokevirtual #76                 // Method value:()I
         8: aload_1
         9: invokevirtual #76                 // Method value:()I
        12: iconst_m1
        13: ixor
        14: iand
        15: invokespecial #83                 // Method "<init>":(I)V
        18: areturn
      LineNumberTable:
        line 115: 0
      LocalVariableTable:
        Start  Length  Slot  Name   Signature
            0      19     0  this   Los/PermSet;
            0      19     1 other   Los/PermSet;
    MethodParameters:
      Name                           Flags
      other                          final

  public int toInt();
    descriptor: ()I
    flags: (0x0001) ACC_PUBLIC
    Code:
      stack=1, locals=1, args_size=1
         0: aload_0
         1: invokevirtual #76                 // Method value:()I
         4: ireturn
      LineNumberTable:
        line 117: 0
      LocalVariableTable:
        Start  Length  Slot  Name   Signature
            0       5     0  this   Los/PermSet;

  public java.util.Set<java.nio.file.attribute.PosixFilePermission> toSet();
    descriptor: ()Ljava/util/Set;
    flags: (0x0001) ACC_PUBLIC
    Code:
      stack=3, locals=2, args_size=1
         0: new           #94                 // class java/util/HashSet
         3: dup
         4: invokespecial #97                 // Method java/util/HashSet."<init>":()V
         7: astore_1
         8: aload_0
         9: getstatic     #102                // Field java/nio/file/attribute/PosixFilePermission.OWNER_READ:Ljava/nio/file/attribute/PosixFilePermission;
        12: aload_1
        13: invokespecial #106                // Method add$3:(Ljava/nio/file/attribute/PosixFilePermission;Ljava/util/HashSet;)Ljava/lang/Object;
        16: pop
        17: aload_0
        18: getstatic     #109                // Field java/nio/file/attribute/PosixFilePermission.OWNER_WRITE:Ljava/nio/file/attribute/PosixFilePermission;
        21: aload_1
        22: invokespecial #106                // Method add$3:(Ljava/nio/file/attribute/PosixFilePermission;Ljava/util/HashSet;)Ljava/lang/Object;
        25: pop
        26: aload_0
        27: getstatic     #112                // Field java/nio/file/attribute/PosixFilePermission.OWNER_EXECUTE:Ljava/nio/file/attribute/PosixFilePermission;
        30: aload_1
        31: invokespecial #106                // Method add$3:(Ljava/nio/file/attribute/PosixFilePermission;Ljava/util/HashSet;)Ljava/lang/Object;
        34: pop
        35: aload_0
        36: getstatic     #115                // Field java/nio/file/attribute/PosixFilePermission.GROUP_READ:Ljava/nio/file/attribute/PosixFilePermission;
        39: aload_1
        40: invokespecial #106                // Method add$3:(Ljava/nio/file/attribute/PosixFilePermission;Ljava/util/HashSet;)Ljava/lang/Object;
        43: pop
        44: aload_0
        45: getstatic     #118                // Field java/nio/file/attribute/PosixFilePermission.GROUP_WRITE:Ljava/nio/file/attribute/PosixFilePermission;
        48: aload_1
        49: invokespecial #106                // Method add$3:(Ljava/nio/file/attribute/PosixFilePermission;Ljava/util/HashSet;)Ljava/lang/Object;
        52: pop
        53: aload_0
        54: getstatic     #121                // Field java/nio/file/attribute/PosixFilePermission.GROUP_EXECUTE:Ljava/nio/file/attribute/PosixFilePermission;
        57: aload_1
        58: invokespecial #106                // Method add$3:(Ljava/nio/file/attribute/PosixFilePermission;Ljava/util/HashSet;)Ljava/lang/Object;
        61: pop
        62: aload_0
        63: getstatic     #124                // Field java/nio/file/attribute/PosixFilePermission.OTHERS_READ:Ljava/nio/file/attribute/PosixFilePermission;
        66: aload_1
        67: invokespecial #106                // Method add$3:(Ljava/nio/file/attribute/PosixFilePermission;Ljava/util/HashSet;)Ljava/lang/Object;
        70: pop
        71: aload_0
        72: getstatic     #127                // Field java/nio/file/attribute/PosixFilePermission.OTHERS_WRITE:Ljava/nio/file/attribute/PosixFilePermission;
        75: aload_1
        76: invokespecial #106                // Method add$3:(Ljava/nio/file/attribute/PosixFilePermission;Ljava/util/HashSet;)Ljava/lang/Object;
        79: pop
        80: aload_0
        81: getstatic     #130                // Field java/nio/file/attribute/PosixFilePermission.OTHERS_EXECUTE:Ljava/nio/file/attribute/PosixFilePermission;
        84: aload_1
        85: invokespecial #106                // Method add$3:(Ljava/nio/file/attribute/PosixFilePermission;Ljava/util/HashSet;)Ljava/lang/Object;
        88: pop
        89: aload_1
        90: areturn
      LineNumberTable:
        line 121: 0
        line 125: 8
        line 126: 17
        line 127: 26
        line 128: 35
        line 129: 44
        line 130: 53
        line 131: 62
        line 132: 71
        line 133: 80
        line 134: 89
      LocalVariableTable:
        Start  Length  Slot  Name   Signature
            8      82     1 perms   Ljava/util/HashSet;
            0      91     0  this   Los/PermSet;
    Signature: #92                          // ()Ljava/util/Set<Ljava/nio/file/attribute/PosixFilePermission;>;

  public java.lang.String toString();
    descriptor: ()Ljava/lang/String;
    flags: (0x0001) ACC_PUBLIC
    Code:
      stack=9, locals=1, args_size=1
         0: new           #136                // class java/lang/String
         3: dup
         4: getstatic     #141                // Field scala/Array$.MODULE$:Lscala/Array$;
         7: getstatic     #146                // Field scala/runtime/ScalaRunTime$.MODULE$:Lscala/runtime/ScalaRunTime$;
        10: bipush        9
        12: newarray       char
        14: dup
        15: iconst_0
        16: aload_0
        17: getstatic     #102                // Field java/nio/file/attribute/PosixFilePermission.OWNER_READ:Ljava/nio/file/attribute/PosixFilePermission;
        20: invokespecial #149                // Method add$4:(Ljava/nio/file/attribute/PosixFilePermission;)C
        23: castore
        24: dup
        25: iconst_1
        26: aload_0
        27: getstatic     #109                // Field java/nio/file/attribute/PosixFilePermission.OWNER_WRITE:Ljava/nio/file/attribute/PosixFilePermission;
        30: invokespecial #149                // Method add$4:(Ljava/nio/file/attribute/PosixFilePermission;)C
        33: castore
        34: dup
        35: iconst_2
        36: aload_0
        37: getstatic     #112                // Field java/nio/file/attribute/PosixFilePermission.OWNER_EXECUTE:Ljava/nio/file/attribute/PosixFilePermission;
        40: invokespecial #149                // Method add$4:(Ljava/nio/file/attribute/PosixFilePermission;)C
        43: castore
        44: dup
        45: iconst_3
        46: aload_0
        47: getstatic     #115                // Field java/nio/file/attribute/PosixFilePermission.GROUP_READ:Ljava/nio/file/attribute/PosixFilePermission;
        50: invokespecial #149                // Method add$4:(Ljava/nio/file/attribute/PosixFilePermission;)C
        53: castore
        54: dup
        55: iconst_4
        56: aload_0
        57: getstatic     #118                // Field java/nio/file/attribute/PosixFilePermission.GROUP_WRITE:Ljava/nio/file/attribute/PosixFilePermission;
        60: invokespecial #149                // Method add$4:(Ljava/nio/file/attribute/PosixFilePermission;)C
        63: castore
        64: dup
        65: iconst_5
        66: aload_0
        67: getstatic     #121                // Field java/nio/file/attribute/PosixFilePermission.GROUP_EXECUTE:Ljava/nio/file/attribute/PosixFilePermission;
        70: invokespecial #149                // Method add$4:(Ljava/nio/file/attribute/PosixFilePermission;)C
        73: castore
        74: dup
        75: bipush        6
        77: aload_0
        78: getstatic     #124                // Field java/nio/file/attribute/PosixFilePermission.OTHERS_READ:Ljava/nio/file/attribute/PosixFilePermission;
        81: invokespecial #149                // Method add$4:(Ljava/nio/file/attribute/PosixFilePermission;)C
        84: castore
        85: dup
        86: bipush        7
        88: aload_0
        89: getstatic     #127                // Field java/nio/file/attribute/PosixFilePermission.OTHERS_WRITE:Ljava/nio/file/attribute/PosixFilePermission;
        92: invokespecial #149                // Method add$4:(Ljava/nio/file/attribute/PosixFilePermission;)C
        95: castore
        96: dup
        97: bipush        8
        99: aload_0
       100: getstatic     #130                // Field java/nio/file/attribute/PosixFilePermission.OTHERS_EXECUTE:Ljava/nio/file/attribute/PosixFilePermission;
       103: invokespecial #149                // Method add$4:(Ljava/nio/file/attribute/PosixFilePermission;)C
       106: castore
       107: invokevirtual #153                // Method scala/runtime/ScalaRunTime$.wrapCharArray:([C)Lscala/collection/immutable/ArraySeq;
       110: getstatic     #158                // Field scala/reflect/ClassTag$.MODULE$:Lscala/reflect/ClassTag$;
       113: invokevirtual #162                // Method scala/reflect/ClassTag$.Char:()Lscala/reflect/ManifestFactory$CharManifest;
       116: invokevirtual #165                // Method scala/Array$.apply:(Lscala/collection/immutable/Seq;Lscala/reflect/ClassTag;)Ljava/lang/Object;
       119: checkcast     #167                // class "[C"
       122: invokespecial #170                // Method java/lang/String."<init>":([C)V
       125: areturn
      LineNumberTable:
        line 143: 0
        line 144: 4
        line 145: 16
        line 146: 26
        line 147: 36
        line 148: 46
        line 149: 56
        line 150: 66
        line 151: 77
        line 152: 88
        line 153: 99
        line 144: 110
      LocalVariableTable:
        Start  Length  Slot  Name   Signature
            0     126     0  this   Los/PermSet;

  public os.PermSet copy(int);
    descriptor: (I)Los/PermSet;
    flags: (0x0001) ACC_PUBLIC
    Code:
      stack=3, locals=2, args_size=2
         0: new           #2                  // class os/PermSet
         3: dup
         4: iload_1
         5: invokespecial #83                 // Method "<init>":(I)V
         8: areturn
      LineNumberTable:
        line 109: 0
      LocalVariableTable:
        Start  Length  Slot  Name   Signature
            0       9     0  this   Los/PermSet;
            0       9     1 value   I
    MethodParameters:
      Name                           Flags
      value                          final

  public int copy$default$1();
    descriptor: ()I
    flags: (0x0001) ACC_PUBLIC
    Code:
      stack=1, locals=1, args_size=1
         0: aload_0
         1: invokevirtual #76                 // Method value:()I
         4: ireturn
      LineNumberTable:
        line 109: 0
      LocalVariableTable:
        Start  Length  Slot  Name   Signature
            0       5     0  this   Los/PermSet;

  public java.lang.String productPrefix();
    descriptor: ()Ljava/lang/String;
    flags: (0x0001) ACC_PUBLIC
    Code:
      stack=1, locals=1, args_size=1
         0: ldc           #175                // String PermSet
         2: areturn
      LineNumberTable:
        line 109: 0
      LocalVariableTable:
        Start  Length  Slot  Name   Signature
            0       3     0  this   Los/PermSet;

  public int productArity();
    descriptor: ()I
    flags: (0x0001) ACC_PUBLIC
    Code:
      stack=1, locals=1, args_size=1
         0: iconst_1
         1: ireturn
      LineNumberTable:
        line 109: 0
      LocalVariableTable:
        Start  Length  Slot  Name   Signature
            0       2     0  this   Los/PermSet;

  public java.lang.Object productElement(int);
    descriptor: (I)Ljava/lang/Object;
    flags: (0x0001) ACC_PUBLIC
    Code:
      stack=1, locals=3, args_size=2
         0: iload_1
         1: istore_2
         2: iload_2
         3: tableswitch   { // 0 to 0
                       0: 20
                 default: 30
            }
        20: aload_0
        21: invokevirtual #76                 // Method value:()I
        24: invokestatic  #185                // Method scala/runtime/BoxesRunTime.boxToInteger:(I)Ljava/lang/Integer;
        27: goto          37
        30: iload_1
        31: invokestatic  #190                // Method scala/runtime/Statics.ioobe:(I)Ljava/lang/Object;
        34: goto          37
        37: areturn
      StackMapTable: number_of_entries = 3
        frame_type = 252 /* append */
          offset_delta = 20
          locals = [ int ]
        frame_type = 9 /* same */
        frame_type = 70 /* same_locals_1_stack_item */
          stack = [ class java/lang/Object ]
      LineNumberTable:
        line 109: 0
      LocalVariableTable:
        Start  Length  Slot  Name   Signature
            0      38     0  this   Los/PermSet;
            0      38     1   x$1   I
    MethodParameters:
      Name                           Flags
      x$1                            final

  public scala.collection.Iterator<java.lang.Object> productIterator();
    descriptor: ()Lscala/collection/Iterator;
    flags: (0x0001) ACC_PUBLIC
    Code:
      stack=2, locals=1, args_size=1
         0: getstatic     #146                // Field scala/runtime/ScalaRunTime$.MODULE$:Lscala/runtime/ScalaRunTime$;
         3: aload_0
         4: invokevirtual #195                // Method scala/runtime/ScalaRunTime$.typedProductIterator:(Lscala/Product;)Lscala/collection/Iterator;
         7: areturn
      LineNumberTable:
        line 109: 0
      LocalVariableTable:
        Start  Length  Slot  Name   Signature
            0       8     0  this   Los/PermSet;
    Signature: #192                         // ()Lscala/collection/Iterator<Ljava/lang/Object;>;

  public boolean canEqual(java.lang.Object);
    descriptor: (Ljava/lang/Object;)Z
    flags: (0x0001) ACC_PUBLIC
    Code:
      stack=1, locals=2, args_size=2
         0: aload_1
         1: instanceof    #2                  // class os/PermSet
         4: ireturn
      LineNumberTable:
        line 109: 0
      LocalVariableTable:
        Start  Length  Slot  Name   Signature
            0       5     0  this   Los/PermSet;
            0       5     1   x$1   Ljava/lang/Object;
    MethodParameters:
      Name                           Flags
      x$1                            final

  public java.lang.String productElementName(int);
    descriptor: (I)Ljava/lang/String;
    flags: (0x0001) ACC_PUBLIC
    Code:
      stack=1, locals=3, args_size=2
         0: iload_1
         1: istore_2
         2: iload_2
         3: tableswitch   { // 0 to 0
                       0: 20
                 default: 25
            }
        20: ldc           #201                // String value
        22: goto          35
        25: iload_1
        26: invokestatic  #190                // Method scala/runtime/Statics.ioobe:(I)Ljava/lang/Object;
        29: checkcast     #136                // class java/lang/String
        32: goto          35
        35: areturn
      StackMapTable: number_of_entries = 3
        frame_type = 252 /* append */
          offset_delta = 20
          locals = [ int ]
        frame_type = 4 /* same */
        frame_type = 73 /* same_locals_1_stack_item */
          stack = [ class java/lang/String ]
      LineNumberTable:
        line 109: 0
      LocalVariableTable:
        Start  Length  Slot  Name   Signature
            0      36     0  this   Los/PermSet;
            0      36     1   x$1   I
    MethodParameters:
      Name                           Flags
      x$1                            final

  public int hashCode();
    descriptor: ()I
    flags: (0x0001) ACC_PUBLIC
    Code:
      stack=2, locals=2, args_size=1
         0: ldc           #203                // int -889275714
         2: istore_1
         3: iload_1
         4: aload_0
         5: invokevirtual #205                // Method productPrefix:()Ljava/lang/String;
         8: invokevirtual #207                // Method java/lang/String.hashCode:()I
        11: invokestatic  #211                // Method scala/runtime/Statics.mix:(II)I
        14: istore_1
        15: iload_1
        16: aload_0
        17: invokevirtual #76                 // Method value:()I
        20: invokestatic  #211                // Method scala/runtime/Statics.mix:(II)I
        23: istore_1
        24: iload_1
        25: iconst_1
        26: invokestatic  #214                // Method scala/runtime/Statics.finalizeHash:(II)I
        29: ireturn
      LineNumberTable:
        line 109: 0
      LocalVariableTable:
        Start  Length  Slot  Name   Signature
            0      30     0  this   Los/PermSet;

  public boolean equals(java.lang.Object);
    descriptor: (Ljava/lang/Object;)Z
    flags: (0x0001) ACC_PUBLIC
    Code:
      stack=2, locals=5, args_size=2
         0: aload_0
         1: aload_1
         2: if_acmpeq     66
         5: aload_1
         6: astore_3
         7: aload_3
         8: instanceof    #2                  // class os/PermSet
        11: ifeq          19
        14: iconst_1
        15: istore_2
        16: goto          27
        19: goto          22
        22: iconst_0
        23: istore_2
        24: goto          27
        27: iload_2
        28: ifeq          70
        31: aload_1
        32: checkcast     #2                  // class os/PermSet
        35: astore        4
        37: aload_0
        38: invokevirtual #76                 // Method value:()I
        41: aload         4
        43: invokevirtual #76                 // Method value:()I
        46: if_icmpne     62
        49: aload         4
        51: aload_0
        52: invokevirtual #217                // Method canEqual:(Ljava/lang/Object;)Z
        55: ifeq          62
        58: iconst_1
        59: goto          63
        62: iconst_0
        63: ifeq          70
        66: iconst_1
        67: goto          71
        70: iconst_0
        71: ireturn
      StackMapTable: number_of_entries = 8
        frame_type = 253 /* append */
          offset_delta = 19
          locals = [ top, class java/lang/Object ]
        frame_type = 2 /* same */
        frame_type = 255 /* full_frame */
          offset_delta = 4
          locals = [ class os/PermSet, class java/lang/Object, int, class java/lang/Object ]
          stack = []
        frame_type = 252 /* append */
          offset_delta = 34
          locals = [ class os/PermSet ]
        frame_type = 64 /* same_locals_1_stack_item */
          stack = [ int ]
        frame_type = 248 /* chop */
          offset_delta = 2
        frame_type = 253 /* append */
          offset_delta = 3
          locals = [ int, class java/lang/Object ]
        frame_type = 255 /* full_frame */
          offset_delta = 0
          locals = [ class os/PermSet, class java/lang/Object ]
          stack = [ int ]
      LineNumberTable:
        line 109: 0
      LocalVariableTable:
        Start  Length  Slot  Name   Signature
            0      72     0  this   Los/PermSet;
            0      72     1   x$1   Ljava/lang/Object;
    MethodParameters:
      Name                           Flags
      x$1                            final

  private final java.lang.Object add$3(java.nio.file.attribute.PosixFilePermission, java.util.HashSet);
    descriptor: (Ljava/nio/file/attribute/PosixFilePermission;Ljava/util/HashSet;)Ljava/lang/Object;
    flags: (0x0012) ACC_PRIVATE, ACC_FINAL
    Code:
      stack=3, locals=3, args_size=3
         0: aload_0
         1: invokevirtual #76                 // Method value:()I
         4: getstatic     #29                 // Field os/PermSet$.MODULE$:Los/PermSet$;
         7: aload_1
         8: invokevirtual #47                 // Method os/PermSet$.permToMask:(Ljava/nio/file/attribute/PosixFilePermission;)I
        11: iand
        12: iconst_0
        13: if_icmpeq     27
        16: aload_2
        17: aload_1
        18: invokevirtual #222                // Method java/util/HashSet.add:(Ljava/lang/Object;)Z
        21: invokestatic  #226                // Method scala/runtime/BoxesRunTime.boxToBoolean:(Z)Ljava/lang/Boolean;
        24: goto          30
        27: getstatic     #232                // Field scala/runtime/BoxedUnit.UNIT:Lscala/runtime/BoxedUnit;
        30: areturn
      StackMapTable: number_of_entries = 2
        frame_type = 27 /* same */
        frame_type = 66 /* same_locals_1_stack_item */
          stack = [ class java/lang/Object ]
      LineNumberTable:
        line 123: 0
      LocalVariableTable:
        Start  Length  Slot  Name   Signature
            0      31     0  this   Los/PermSet;
            0      31     1  perm   Ljava/nio/file/attribute/PosixFilePermission;
            0      31     2 perms$2   Ljava/util/HashSet;
    MethodParameters:
      Name                           Flags
      perm                           final
      perms$2                        final

  private final char add$4(java.nio.file.attribute.PosixFilePermission);
    descriptor: (Ljava/nio/file/attribute/PosixFilePermission;)C
    flags: (0x0012) ACC_PRIVATE, ACC_FINAL
    Code:
      stack=2, locals=3, args_size=2
         0: getstatic     #29                 // Field os/PermSet$.MODULE$:Los/PermSet$;
         3: aload_1
         4: invokevirtual #44                 // Method os/PermSet$.permToChar:(Ljava/nio/file/attribute/PosixFilePermission;)C
         7: istore_2
         8: getstatic     #29                 // Field os/PermSet$.MODULE$:Los/PermSet$;
        11: aload_1
        12: invokevirtual #47                 // Method os/PermSet$.permToMask:(Ljava/nio/file/attribute/PosixFilePermission;)I
        15: aload_0
        16: invokevirtual #76                 // Method value:()I
        19: iand
        20: iconst_0
        21: if_icmpeq     28
        24: iload_2
        25: goto          30
        28: bipush        45
        30: ireturn
      StackMapTable: number_of_entries = 2
        frame_type = 252 /* append */
          offset_delta = 28
          locals = [ int ]
        frame_type = 65 /* same_locals_1_stack_item */
          stack = [ int ]
      LineNumberTable:
        line 140: 0
        line 141: 8
      LocalVariableTable:
        Start  Length  Slot  Name   Signature
            8      22     2     c   C
            0      31     0  this   Los/PermSet;
            0      31     1  perm   Ljava/nio/file/attribute/PosixFilePermission;
    MethodParameters:
      Name                           Flags
      perm                           final

  public os.PermSet(int);
    descriptor: (I)V
    flags: (0x0001) ACC_PUBLIC
    Code:
      stack=2, locals=2, args_size=2
         0: aload_0
         1: iload_1
         2: putfield      #72                 // Field value:I
         5: aload_0
         6: invokespecial #235                // Method java/lang/Object."<init>":()V
         9: aload_0
        10: invokestatic  #239                // InterfaceMethod scala/Product.$init$:(Lscala/Product;)V
        13: return
      LineNumberTable:
        line 109: 0
      LocalVariableTable:
        Start  Length  Slot  Name   Signature
            0      14     0  this   Los/PermSet;
            0      14     1 value   I
    MethodParameters:
      Name                           Flags
      value                          final
}
InnerClasses:
  public static final #17= #14 of #16;    // CharManifest=class scala/reflect/ManifestFactory$CharManifest of class scala/reflect/ManifestFactory
SourceFile: "Model.scala"
RuntimeVisibleAnnotations:
  0: #10(#11=s#12)
    scala.reflect.ScalaSignature(
      bytes="\u0006\u0005\u0005Mv!\u0002\u0012$\u0011\u00031c!\u0002\u0015$\u0011\u0003I\u0003\"\u0002\u001d\u0002\t\u0003I\u0004\"\u0002\u001e\u0002\t\u0007Y\u0004bBA1\u0003\u0011\r\u00111\r\u0005\b\u0003o\nA1AA=\u0011\u001d\ti(\u0001C\u0001\u0003\u007fBq!a!\u0002\t\u0003\t)\tC\u0004\u0002\u0010\u0006!\t!!%\t\u0013\u0005U\u0015!!A\u0005\u0002\u0006]\u0005\"CAN\u0003\u0005\u0005I\u0011QAO\u0011%\tI+AA\u0001\n\u0013\tYK\u0002\u0003)G\u0001k\u0004\u0002\u0003\'\r\u0005+\u0007I\u0011A\'\t\u0011Ec!\u0011#Q\u0001\n9CQ\u0001\u000f\u0007\u0005\u0002ICQ\u0001\u0016\u0007\u0005\u0002UCQ!\u001a\u0007\u0005\u0002\u0019DQ\u0001\u001b\u0007\u0005\u0002%DQ\u0001\u001c\u0007\u0005\u00025DQa\u001c\u0007\u0005\u0002ADQA\u001d\u0007\u0005\u0002MDQ\u0001\u001e\u0007\u0005\u0002UDQ\u0001 \u0007\u0005BuD\u0011\"!\u0003\r\u0003\u0003%\t!a\u0003\t\u0013\u0005=A\"%A\u0005\u0002\u0005E\u0001\"CA\u0014\u0019\u0005\u0005I\u0011IA\u0015\u0011!\tY\u0003DA\u0001\n\u0003i\u0005\"CA\u0017\u0019\u0005\u0005I\u0011AA\u0018\u0011%\tY\u0004DA\u0001\n\u0003\ni\u0004C\u0005\u0002L1\t\t\u0011\"\u0001\u0002N!I\u0011\u0011\u000b\u0007\u0002\u0002\u0013\u0005\u00131\u000b\u0005\t\u0003/b\u0011\u0011!C!g\"I\u0011\u0011\f\u0007\u0002\u0002\u0013\u0005\u00131L\u0001\b!\u0016\u0014XnU3u\u0015\u0005!\u0013AA8t\u0007\u0001\u0001\"aJ\u0001\u000e\u0003\r\u0012q\u0001U3s[N+GoE\u0002\u0002UA\u0002\"a\u000b\u0018\u000e\u00031R\u0011!L\u0001\u0006g\u000e\fG.Y\u0005\u0003_1\u0012a!\u00118z%\u00164\u0007CA\u00197\u001b\u0005\u0011$BA\u001a5\u0003\tIwNC\u00016\u0003\u0011Q\u0017M^1\n\u0005]\u0012$\u0001D*fe&\fG.\u001b>bE2,\u0017A\u0002\u001fj]&$h\bF\u0001\'\u0003\u001d1\'o\\7TKR$2\u0001PA0!\t9Cb\u0005\u0003\rUy\n\u0005CA\u0016@\u0013\t\u0001EFA\u0004Qe>$Wo\u0019;\u0011\u0005\tSeBA\"I\u001d\t!u)D\u0001F\u0015\t1U%\u0001\u0004=e>|GOP\u0005\u0002[%\u0011\u0011\nL\u0001\ba\u0006\u001c7.Y4f\u0013\t94J\u0003\u0002JY\u0005)a/\u00197vKV\ta\n\u0005\u0002,\u001f&\u0011\u0001\u000b\f\u0002\u0004\u0013:$\u0018A\u0002<bYV,\u0007\u0005\u0006\u0002=\'\")Aj\u0004a\u0001\u001d\u0006A1m\u001c8uC&t7\u000f\u0006\u0002W3B\u00111fV\u0005\u000312\u0012qAQ8pY\u0016\fg\u000eC\u0003[!\u0001\u00071,\u0001\u0003fY\u0016l\u0007C\u0001/d\u001b\u0005i&B\u00010`\u0003%\tG\u000f\u001e:jEV$XM\u0003\u0002aC\u0006!a-\u001b7f\u0015\t\u0011G\'A\u0002oS>L!\u0001Z/\u0003\'A{7/\u001b=GS2,\u0007+\u001a:nSN\u001c\u0018n\u001c8\u0002\u000b\u0011\u0002H.^:\u0015\u0005q:\u0007\"\u0002.\u0012\u0001\u0004Y\u0016A\u0003\u0013qYV\u001cH\u0005\u001d7vgR\u0011AH\u001b\u0005\u0006WJ\u0001\r\u0001P\u0001\u0006_RDWM]\u0001\u0007I5Lg.^:\u0015\u0005qr\u0007\"\u0002.\u0014\u0001\u0004Y\u0016\u0001\u0004\u0013nS:,8\u000fJ7j]V\u001cHC\u0001\u001fr\u0011\u0015YG\u00031\u0001=\u0003\u0015!x.\u00138u)\u0005q\u0015!\u0002;p\'\u0016$H#\u0001<\u0011\u0007]T8,D\u0001y\u0015\tIH\'\u0001\u0003vi&d\u0017BA>y\u0005\r\u0019V\r^\u0001\ti>\u001cFO]5oOR\ta\u0010E\u0002\u0000\u0003\u000bi!!!\u0001\u000b\u0007\u0005\rA\'\u0001\u0003mC:<\u0017\u0002BA\u0004\u0003\u0003\u0011aa\u0015;sS:<\u0017\u0001B2paf$2\u0001PA\u0007\u0011\u001da\u0005\u0004%AA\u00029\u000babY8qs\u0012\"WMZ1vYR$\u0013\'\u0006\u0002\u0002\u0014)\u001aa*!\u0006,\u0005\u0005]\u0001\u0003BA\r\u0003Gi!!a\u0007\u000b\t\u0005u\u0011qD\u0001\nk:\u001c\u0007.Z2lK\u0012T1!!\t-\u0003)\tgN\\8uCRLwN\\\u0005\u0005\u0003K\tYBA\tv]\u000eDWmY6fIZ\u000b\'/[1oG\u0016\fQ\u0002\u001d:pIV\u001cG\u000f\u0015:fM&DX#\u0001@\u0002\u0019A\u0014x\u000eZ;di\u0006\u0013\u0018\u000e^=\u0002\u001dA\u0014x\u000eZ;di\u0016cW-\\3oiR!\u0011\u0011GA\u001c!\rY\u00131G\u0005\u0004\u0003ka#aA!os\"A\u0011\u0011\b\u000f\u0002\u0002\u0003\u0007a*A\u0002yIE\nq\u0002\u001d:pIV\u001cG/\u0013;fe\u0006$xN]\u000b\u0003\u0003\u007f\u0001b!!\u0011\u0002H\u0005ERBAA\"\u0015\r\t)\u0005L\u0001\u000bG>dG.Z2uS>t\u0017\u0002BA%\u0003\u0007\u0012\u0001\"\u0013;fe\u0006$xN]\u0001\tG\u0006tW)];bYR\u0019a+a\u0014\t\u0013\u0005eb$!AA\u0002\u0005E\u0012A\u00059s_\u0012,8\r^#mK6,g\u000e\u001e(b[\u0016$2A`A+\u0011!\tIdHA\u0001\u0002\u0004q\u0015\u0001\u00035bg\"\u001cu\u000eZ3\u0002\r\u0015\fX/\u00197t)\r1\u0016Q\f\u0005\n\u0003s\t\u0013\u0011!a\u0001\u0003cAQ\u0001T\u0002A\u0002Y\f!B\u001a:p[N#(/\u001b8h)\ra\u0014Q\r\u0005\b\u0003O\"\u0001\u0019AA5\u0003\r\t\'o\u001a\t\u0005\u0003W\n\u0019H\u0004\u0003\u0002n\u0005=\u0004C\u0001#-\u0013\r\t\t\bL\u0001\u0007!J,G-\u001a4\n\t\u0005\u001d\u0011Q\u000f\u0006\u0004\u0003cb\u0013a\u00024s_6Le\u000e\u001e\u000b\u0004y\u0005m\u0004\"\u0002\'\u0006\u0001\u0004q\u0015A\u00039fe6$v.T1tWR\u0019a*!!\t\u000bi3\u0001\u0019A.\u0002\u0015A,\'/\u001c+p\u0007\"\f\'\u000f\u0006\u0003\u0002\b\u00065\u0005cA\u0016\u0002\n&\u0019\u00111\u0012\u0017\u0003\t\rC\u0017M\u001d\u0005\u00065\u001e\u0001\raW\u0001\ra\u0016\u0014X\u000eV8PM\u001a\u001cX\r\u001e\u000b\u0004\u001d\u0006M\u0005\"\u0002.\t\u0001\u0004Y\u0016!B1qa2LHc\u0001\u001f\u0002\u001a\")A*\u0003a\u0001\u001d\u00069QO\\1qa2LH\u0003BAP\u0003K\u0003BaKAQ\u001d&\u0019\u00111\u0015\u0017\u0003\r=\u0003H/[8o\u0011!\t9KCA\u0001\u0002\u0004a\u0014a\u0001=%a\u0005aqO]5uKJ+\u0007\u000f\\1dKR\u0011\u0011Q\u0016\t\u0004\u007f\u0006=\u0016\u0002BAY\u0003\u0003\u0011aa\u00142kK\u000e$\b"
    )
  ScalaInlineInfo: length = 0x77 (unknown attribute)
   01 00 00 17 00 57 00 4F 00 00 58 00 55 00 00 4E
   00 4F 00 00 54 00 55 00 00 50 00 51 00 00 67 00
   68 01 00 93 00 2A 01 00 C4 00 C5 00 00 49 00 4A
   00 00 AB 00 21 00 00 AC 00 46 00 00 D7 00 C5 00
   00 CA 00 46 00 00 B0 00 46 00 00 B1 00 B2 00 00
   C7 00 C8 00 00 3D 00 3E 00 00 BF 00 3E 00 00 AD
   00 86 00 00 59 00 46 00 00 5A 00 5B 00 00 85 00
   86 00 00 12 00 46 00
  ScalaSig: length = 0x3 (unknown attribute)
   05 02 00
