Classfile /Users/mw/Projects/slang-braindump/.jar/jar11/assemble/slang-braindump/assemble/content/os/perms.class
  Last modified May 29, 2022; size 1548 bytes
  SHA-256 checksum d23bf5a5005857840238cb0380a9e4cb8ee3e4eac2dd00227292e6fb1fb13be9
  Compiled from "PermsOps.scala"
public final class os.perms
  minor version: 0
  major version: 52
  flags: (0x0031) ACC_PUBLIC, ACC_FINAL, ACC_SUPER
  this_class: #2                          // os/perms
  super_class: #4                         // java/lang/Object
  interfaces: 0, fields: 0, methods: 6, attributes: 4
Constant pool:
   #1 = Utf8               os/perms
   #2 = Class              #1             // os/perms
   #3 = Utf8               java/lang/Object
   #4 = Class              #3             // java/lang/Object
   #5 = Utf8               PermsOps.scala
   #6 = Utf8               Lscala/reflect/ScalaSignature;
   #7 = Utf8               bytes
   #8 = Utf8               \u0006\u0005\u001d;QAC\u0006\t\u000291Q\u0001E\u0006\t\u0002EAQ!I\u0001\u0005\u0002\tBQaI\u0001\u0005\u0002\u0011BQaI\u0001\u0005\u0002\u001dBqAL\u0001\u0012\u0002\u0013\u0005qfB\u0003;\u0003!\u00051HB\u0003>\u0003!\u0005a\bC\u0003\"\u000f\u0011\u0005q\bC\u0003$\u000f\u0011\u0005\u0001)A\u0003qKJl7OC\u0001\r\u0003\ty7o\u0001\u0001\u0011\u0005=\tQ\"A\u0006\u0003\u000bA,\'/\\:\u0014\u0007\u0005\u0011\u0002\u0004\u0005\u0002\u0014-5\tACC\u0001\u0016\u0003\u0015\u00198-\u00197b\u0013\t9BC\u0001\u0004B]f\u0014VM\u001a\t\u0005\'eYb$\u0003\u0002\u001b)\tIa)\u001e8di&|g.\r\t\u0003\u001fqI!!H\u0006\u0003\tA\u000bG\u000f\u001b\t\u0003\u001f}I!\u0001I\u0006\u0003\u000fA+\'/\\*fi\u00061A(\u001b8jiz\"\u0012AD\u0001\u0006CB\u0004H.\u001f\u000b\u0003=\u0015BQAJ\u0002A\u0002m\t\u0011\u0001\u001d\u000b\u0004=!J\u0003\"\u0002\u0014\u0005\u0001\u0004Y\u0002b\u0002\u0016\u0005!\u0003\u0005\raK\u0001\fM>dGn\\<MS:\\7\u000f\u0005\u0002\u0014Y%\u0011Q\u0006\u0006\u0002\b\u0005>|G.Z1o\u0003=\t\u0007\u000f\u001d7zI\u0011,g-Y;mi\u0012\u0012T#\u0001\u0019+\u0005-\n4&\u0001\u001a\u0011\u0005MBT\"\u0001\u001b\u000b\u0005U2\u0014!C;oG\",7m[3e\u0015\t9D#\u0001\u0006b]:|G/\u0019;j_:L!!\u000f\u001b\u0003#Ut7\r[3dW\u0016$g+\u0019:jC:\u001cW-A\u0002tKR\u0004\"\u0001P\u0004\u000e\u0003\u0005\u00111a]3u\'\t9!\u0003F\u0001<)\r\tE)\u0012\t\u0003\'\tK!a\u0011\u000b\u0003\tUs\u0017\u000e\u001e\u0005\u0006M%\u0001\ra\u0007\u0005\u0006\r&\u0001\rAH\u0001\u0005CJ<\'\u0007
   #9 = Utf8               os/perms$set$
  #10 = Class              #9             // os/perms$set$
  #11 = Utf8               set$
  #12 = Utf8               apply$default$2
  #13 = Utf8               ()Z
  #14 = Utf8               os/perms$
  #15 = Class              #14            // os/perms$
  #16 = Utf8               MODULE$
  #17 = Utf8               Los/perms$;
  #18 = NameAndType        #16:#17        // MODULE$:Los/perms$;
  #19 = Fieldref           #15.#18        // os/perms$.MODULE$:Los/perms$;
  #20 = NameAndType        #12:#13        // apply$default$2:()Z
  #21 = Methodref          #15.#20        // os/perms$.apply$default$2:()Z
  #22 = Utf8               apply
  #23 = Utf8               (Los/Path;Z)Los/PermSet;
  #24 = Utf8               p
  #25 = Utf8               followLinks
  #26 = NameAndType        #22:#23        // apply:(Los/Path;Z)Los/PermSet;
  #27 = Methodref          #15.#26        // os/perms$.apply:(Los/Path;Z)Los/PermSet;
  #28 = Utf8               (Los/Path;)Los/PermSet;
  #29 = NameAndType        #22:#28        // apply:(Los/Path;)Los/PermSet;
  #30 = Methodref          #15.#29        // os/perms$.apply:(Los/Path;)Los/PermSet;
  #31 = Utf8               toString
  #32 = Utf8               ()Ljava/lang/String;
  #33 = NameAndType        #31:#32        // toString:()Ljava/lang/String;
  #34 = Methodref          #15.#33        // os/perms$.toString:()Ljava/lang/String;
  #35 = Utf8               andThen
  #36 = Utf8               (Lscala/Function1;)Lscala/Function1;
  #37 = Utf8               <A:Ljava/lang/Object;>(Lscala/Function1<Los/PermSet;TA;>;)Lscala/Function1<Los/Path;TA;>;
  #38 = Utf8               g
  #39 = NameAndType        #35:#36        // andThen:(Lscala/Function1;)Lscala/Function1;
  #40 = Methodref          #15.#39        // os/perms$.andThen:(Lscala/Function1;)Lscala/Function1;
  #41 = Utf8               compose
  #42 = Utf8               <A:Ljava/lang/Object;>(Lscala/Function1<TA;Los/Path;>;)Lscala/Function1<TA;Los/PermSet;>;
  #43 = NameAndType        #41:#36        // compose:(Lscala/Function1;)Lscala/Function1;
  #44 = Methodref          #15.#43        // os/perms$.compose:(Lscala/Function1;)Lscala/Function1;
  #45 = Utf8               Code
  #46 = Utf8               MethodParameters
  #47 = Utf8               Signature
  #48 = Utf8               InnerClasses
  #49 = Utf8               SourceFile
  #50 = Utf8               RuntimeVisibleAnnotations
  #51 = Utf8               ScalaSig
{
  public static boolean apply$default$2();
    descriptor: ()Z
    flags: (0x0009) ACC_PUBLIC, ACC_STATIC
    Code:
      stack=1, locals=0, args_size=0
         0: getstatic     #19                 // Field os/perms$.MODULE$:Los/perms$;
         3: invokevirtual #21                 // Method os/perms$.apply$default$2:()Z
         6: ireturn

  public static os.PermSet apply(os.Path, boolean);
    descriptor: (Los/Path;Z)Los/PermSet;
    flags: (0x0009) ACC_PUBLIC, ACC_STATIC
    Code:
      stack=3, locals=2, args_size=2
         0: getstatic     #19                 // Field os/perms$.MODULE$:Los/perms$;
         3: aload_0
         4: iload_1
         5: invokevirtual #27                 // Method os/perms$.apply:(Los/Path;Z)Los/PermSet;
         8: areturn
    MethodParameters:
      Name                           Flags
      p                              final
      followLinks                    final

  public static os.PermSet apply(os.Path);
    descriptor: (Los/Path;)Los/PermSet;
    flags: (0x0009) ACC_PUBLIC, ACC_STATIC
    Code:
      stack=2, locals=1, args_size=1
         0: getstatic     #19                 // Field os/perms$.MODULE$:Los/perms$;
         3: aload_0
         4: invokevirtual #30                 // Method os/perms$.apply:(Los/Path;)Los/PermSet;
         7: areturn
    MethodParameters:
      Name                           Flags
      p                              final

  public static java.lang.String toString();
    descriptor: ()Ljava/lang/String;
    flags: (0x0009) ACC_PUBLIC, ACC_STATIC
    Code:
      stack=1, locals=0, args_size=0
         0: getstatic     #19                 // Field os/perms$.MODULE$:Los/perms$;
         3: invokevirtual #34                 // Method os/perms$.toString:()Ljava/lang/String;
         6: areturn

  public static <A extends java.lang.Object> scala.Function1<os.Path, A> andThen(scala.Function1<os.PermSet, A>);
    descriptor: (Lscala/Function1;)Lscala/Function1;
    flags: (0x0009) ACC_PUBLIC, ACC_STATIC
    Code:
      stack=2, locals=1, args_size=1
         0: getstatic     #19                 // Field os/perms$.MODULE$:Los/perms$;
         3: aload_0
         4: invokevirtual #40                 // Method os/perms$.andThen:(Lscala/Function1;)Lscala/Function1;
         7: areturn
    Signature: #37                          // <A:Ljava/lang/Object;>(Lscala/Function1<Los/PermSet;TA;>;)Lscala/Function1<Los/Path;TA;>;
    MethodParameters:
      Name                           Flags
      g                              final

  public static <A extends java.lang.Object> scala.Function1<A, os.PermSet> compose(scala.Function1<A, os.Path>);
    descriptor: (Lscala/Function1;)Lscala/Function1;
    flags: (0x0009) ACC_PUBLIC, ACC_STATIC
    Code:
      stack=2, locals=1, args_size=1
         0: getstatic     #19                 // Field os/perms$.MODULE$:Los/perms$;
         3: aload_0
         4: invokevirtual #44                 // Method os/perms$.compose:(Lscala/Function1;)Lscala/Function1;
         7: areturn
    Signature: #42                          // <A:Ljava/lang/Object;>(Lscala/Function1<TA;Los/Path;>;)Lscala/Function1<TA;Los/PermSet;>;
    MethodParameters:
      Name                           Flags
      g                              final
}
InnerClasses:
  public static #11= #10 of #2;           // set$=class os/perms$set$ of class os/perms
SourceFile: "PermsOps.scala"
RuntimeVisibleAnnotations:
  0: #6(#7=s#8)
    scala.reflect.ScalaSignature(
      bytes="\u0006\u0005\u001d;QAC\u0006\t\u000291Q\u0001E\u0006\t\u0002EAQ!I\u0001\u0005\u0002\tBQaI\u0001\u0005\u0002\u0011BQaI\u0001\u0005\u0002\u001dBqAL\u0001\u0012\u0002\u0013\u0005qfB\u0003;\u0003!\u00051HB\u0003>\u0003!\u0005a\bC\u0003\"\u000f\u0011\u0005q\bC\u0003$\u000f\u0011\u0005\u0001)A\u0003qKJl7OC\u0001\r\u0003\ty7o\u0001\u0001\u0011\u0005=\tQ\"A\u0006\u0003\u000bA,\'/\\:\u0014\u0007\u0005\u0011\u0002\u0004\u0005\u0002\u0014-5\tACC\u0001\u0016\u0003\u0015\u00198-\u00197b\u0013\t9BC\u0001\u0004B]f\u0014VM\u001a\t\u0005\'eYb$\u0003\u0002\u001b)\tIa)\u001e8di&|g.\r\t\u0003\u001fqI!!H\u0006\u0003\tA\u000bG\u000f\u001b\t\u0003\u001f}I!\u0001I\u0006\u0003\u000fA+\'/\\*fi\u00061A(\u001b8jiz\"\u0012AD\u0001\u0006CB\u0004H.\u001f\u000b\u0003=\u0015BQAJ\u0002A\u0002m\t\u0011\u0001\u001d\u000b\u0004=!J\u0003\"\u0002\u0014\u0005\u0001\u0004Y\u0002b\u0002\u0016\u0005!\u0003\u0005\raK\u0001\fM>dGn\\<MS:\\7\u000f\u0005\u0002\u0014Y%\u0011Q\u0006\u0006\u0002\b\u0005>|G.Z1o\u0003=\t\u0007\u000f\u001d7zI\u0011,g-Y;mi\u0012\u0012T#\u0001\u0019+\u0005-\n4&\u0001\u001a\u0011\u0005MBT\"\u0001\u001b\u000b\u0005U2\u0014!C;oG\",7m[3e\u0015\t9D#\u0001\u0006b]:|G/\u0019;j_:L!!\u000f\u001b\u0003#Ut7\r[3dW\u0016$g+\u0019:jC:\u001cW-A\u0002tKR\u0004\"\u0001P\u0004\u000e\u0003\u0005\u00111a]3u\'\t9!\u0003F\u0001<)\r\tE)\u0012\t\u0003\'\tK!a\u0011\u000b\u0003\tUs\u0017\u000e\u001e\u0005\u0006M%\u0001\ra\u0007\u0005\u0006\r&\u0001\rAH\u0001\u0005CJ<\'\u0007"
    )
  ScalaSig: length = 0x3 (unknown attribute)
   05 02 00
