Classfile /Users/mw/Projects/slang-braindump/.jar/jar11/assemble/slang-braindump/assemble/content/os/Pipe.class
  Last modified May 29, 2022; size 1509 bytes
  SHA-256 checksum 77ab0c85b0a1ef9edac15e9b79dbecaba6ed68dcc9c438019d548d20a6a2042f
  Compiled from "SubProcess.scala"
public final class os.Pipe
  minor version: 0
  major version: 52
  flags: (0x0031) ACC_PUBLIC, ACC_FINAL, ACC_SUPER
  this_class: #2                          // os/Pipe
  super_class: #4                         // java/lang/Object
  interfaces: 0, fields: 0, methods: 4, attributes: 4
Constant pool:
   #1 = Utf8               os/Pipe
   #2 = Class              #1             // os/Pipe
   #3 = Utf8               java/lang/Object
   #4 = Class              #3             // java/lang/Object
   #5 = Utf8               SubProcess.scala
   #6 = Utf8               Lscala/reflect/ScalaSignature;
   #7 = Utf8               bytes
   #8 = Utf8               \u0006\u0005\u0011;Qa\u0002\u0005\t\u0002-1Q!\u0004\u0005\t\u00029AQaG\u0001\u0005\u0002qAQ!H\u0001\u0005\u0002yAQaK\u0001\u0005\u0002yAQ\u0001L\u0001\u0005\u00025BQ!P\u0001\u0005\u0002y\nA\u0001U5qK*\t\u0011\"\u0001\u0002pg\u000e\u0001\u0001C\u0001\u0007\u0002\u001b\u0005A!\u0001\u0002)ja\u0016\u001cB!A\b\u00161A\u0011\u0001cE\u0007\u0002#)\t!#A\u0003tG\u0006d\u0017-\u0003\u0002\u0015#\t1\u0011I\\=SK\u001a\u0004\"\u0001\u0004\f\n\u0005]A!\u0001\u0004)s_\u000e,7o]%oaV$\bC\u0001\u0007\u001a\u0013\tQ\u0002BA\u0007Qe>\u001cWm]:PkR\u0004X\u000f^\u0001\u0007y%t\u0017\u000e\u001e \u0015\u0003-\t!B]3eSJ,7\r\u001e+p+\u0005y\u0002C\u0001\u0011)\u001d\t\tc%D\u0001#\u0015\t\u0019C%\u0001\u0003mC:<\'\"A\u0013\u0002\t)\fg/Y\u0005\u0003O\t\na\u0002\u0015:pG\u0016\u001c8OQ;jY\u0012,\'/\u0003\u0002*U\tA!+\u001a3je\u0016\u001cGO\u0003\u0002(E\u0005a!/\u001a3je\u0016\u001cGO\u0012:p[\u0006a\u0001O]8dKN\u001c\u0018J\u001c9viR\u0011a&\r\t\u0003!=R!\u0001M\t\u0002\t9{g.\u001a\u0005\u0007e\u0015!\t\u0019A\u001a\u0002\u000bM$H-\u001b8\u0011\u0007A!d\'\u0003\u00026#\tAAHY=oC6,g\b\u0005\u00028u9\u0011A\u0002O\u0005\u0003s!\t!bU;c!J|7-Z:t\u0013\tYDHA\u0006J]B,Ho\u0015;sK\u0006l\'BA\u001d\t\u00035\u0001(o\\2fgN|U\u000f\u001e9viR\u0011af\u0010\u0005\u0007e\u0019!\t\u0019\u0001!\u0011\u0007A!\u0014\t\u0005\u00028\u0005&\u00111\t\u0010\u0002\r\u001fV$\b/\u001e;TiJ,\u0017-\u001c
   #9 = Utf8               java/lang/ProcessBuilder$Redirect
  #10 = Class              #9             // java/lang/ProcessBuilder$Redirect
  #11 = Utf8               java/lang/ProcessBuilder
  #12 = Class              #11            // java/lang/ProcessBuilder
  #13 = Utf8               Redirect
  #14 = Utf8               os/SubProcess$InputStream
  #15 = Class              #14            // os/SubProcess$InputStream
  #16 = Utf8               os/SubProcess
  #17 = Class              #16            // os/SubProcess
  #18 = Utf8               InputStream
  #19 = Utf8               os/SubProcess$OutputStream
  #20 = Class              #19            // os/SubProcess$OutputStream
  #21 = Utf8               OutputStream
  #22 = Utf8               processOutput
  #23 = Utf8               (Lscala/Function0;)Lscala/None$;
  #24 = Utf8               (Lscala/Function0<Los/SubProcess$OutputStream;>;)Lscala/None$;
  #25 = Utf8               stdin
  #26 = Utf8               os/Pipe$
  #27 = Class              #26            // os/Pipe$
  #28 = Utf8               MODULE$
  #29 = Utf8               Los/Pipe$;
  #30 = NameAndType        #28:#29        // MODULE$:Los/Pipe$;
  #31 = Fieldref           #27.#30        // os/Pipe$.MODULE$:Los/Pipe$;
  #32 = NameAndType        #22:#23        // processOutput:(Lscala/Function0;)Lscala/None$;
  #33 = Methodref          #27.#32        // os/Pipe$.processOutput:(Lscala/Function0;)Lscala/None$;
  #34 = Utf8               processInput
  #35 = Utf8               (Lscala/Function0<Los/SubProcess$InputStream;>;)Lscala/None$;
  #36 = NameAndType        #34:#23        // processInput:(Lscala/Function0;)Lscala/None$;
  #37 = Methodref          #27.#36        // os/Pipe$.processInput:(Lscala/Function0;)Lscala/None$;
  #38 = Utf8               redirectFrom
  #39 = Utf8               ()Ljava/lang/ProcessBuilder$Redirect;
  #40 = NameAndType        #38:#39        // redirectFrom:()Ljava/lang/ProcessBuilder$Redirect;
  #41 = Methodref          #27.#40        // os/Pipe$.redirectFrom:()Ljava/lang/ProcessBuilder$Redirect;
  #42 = Utf8               redirectTo
  #43 = NameAndType        #42:#39        // redirectTo:()Ljava/lang/ProcessBuilder$Redirect;
  #44 = Methodref          #27.#43        // os/Pipe$.redirectTo:()Ljava/lang/ProcessBuilder$Redirect;
  #45 = Utf8               Code
  #46 = Utf8               Signature
  #47 = Utf8               MethodParameters
  #48 = Utf8               InnerClasses
  #49 = Utf8               SourceFile
  #50 = Utf8               RuntimeVisibleAnnotations
  #51 = Utf8               ScalaSig
{
  public static scala.None$ processOutput(scala.Function0<os.SubProcess$OutputStream>);
    descriptor: (Lscala/Function0;)Lscala/None$;
    flags: (0x0009) ACC_PUBLIC, ACC_STATIC
    Code:
      stack=2, locals=1, args_size=1
         0: getstatic     #31                 // Field os/Pipe$.MODULE$:Los/Pipe$;
         3: aload_0
         4: invokevirtual #33                 // Method os/Pipe$.processOutput:(Lscala/Function0;)Lscala/None$;
         7: areturn
    Signature: #24                          // (Lscala/Function0<Los/SubProcess$OutputStream;>;)Lscala/None$;
    MethodParameters:
      Name                           Flags
      stdin                          final

  public static scala.None$ processInput(scala.Function0<os.SubProcess$InputStream>);
    descriptor: (Lscala/Function0;)Lscala/None$;
    flags: (0x0009) ACC_PUBLIC, ACC_STATIC
    Code:
      stack=2, locals=1, args_size=1
         0: getstatic     #31                 // Field os/Pipe$.MODULE$:Los/Pipe$;
         3: aload_0
         4: invokevirtual #37                 // Method os/Pipe$.processInput:(Lscala/Function0;)Lscala/None$;
         7: areturn
    Signature: #35                          // (Lscala/Function0<Los/SubProcess$InputStream;>;)Lscala/None$;
    MethodParameters:
      Name                           Flags
      stdin                          final

  public static java.lang.ProcessBuilder$Redirect redirectFrom();
    descriptor: ()Ljava/lang/ProcessBuilder$Redirect;
    flags: (0x0009) ACC_PUBLIC, ACC_STATIC
    Code:
      stack=1, locals=0, args_size=0
         0: getstatic     #31                 // Field os/Pipe$.MODULE$:Los/Pipe$;
         3: invokevirtual #41                 // Method os/Pipe$.redirectFrom:()Ljava/lang/ProcessBuilder$Redirect;
         6: areturn

  public static java.lang.ProcessBuilder$Redirect redirectTo();
    descriptor: ()Ljava/lang/ProcessBuilder$Redirect;
    flags: (0x0009) ACC_PUBLIC, ACC_STATIC
    Code:
      stack=1, locals=0, args_size=0
         0: getstatic     #31                 // Field os/Pipe$.MODULE$:Los/Pipe$;
         3: invokevirtual #44                 // Method os/Pipe$.redirectTo:()Ljava/lang/ProcessBuilder$Redirect;
         6: areturn
}
InnerClasses:
  public static abstract #13= #10 of #12; // Redirect=class java/lang/ProcessBuilder$Redirect of class java/lang/ProcessBuilder
  public static #18= #15 of #17;          // InputStream=class os/SubProcess$InputStream of class os/SubProcess
  public static #21= #20 of #17;          // OutputStream=class os/SubProcess$OutputStream of class os/SubProcess
SourceFile: "SubProcess.scala"
RuntimeVisibleAnnotations:
  0: #6(#7=s#8)
    scala.reflect.ScalaSignature(
      bytes="\u0006\u0005\u0011;Qa\u0002\u0005\t\u0002-1Q!\u0004\u0005\t\u00029AQaG\u0001\u0005\u0002qAQ!H\u0001\u0005\u0002yAQaK\u0001\u0005\u0002yAQ\u0001L\u0001\u0005\u00025BQ!P\u0001\u0005\u0002y\nA\u0001U5qK*\t\u0011\"\u0001\u0002pg\u000e\u0001\u0001C\u0001\u0007\u0002\u001b\u0005A!\u0001\u0002)ja\u0016\u001cB!A\b\u00161A\u0011\u0001cE\u0007\u0002#)\t!#A\u0003tG\u0006d\u0017-\u0003\u0002\u0015#\t1\u0011I\\=SK\u001a\u0004\"\u0001\u0004\f\n\u0005]A!\u0001\u0004)s_\u000e,7o]%oaV$\bC\u0001\u0007\u001a\u0013\tQ\u0002BA\u0007Qe>\u001cWm]:PkR\u0004X\u000f^\u0001\u0007y%t\u0017\u000e\u001e \u0015\u0003-\t!B]3eSJ,7\r\u001e+p+\u0005y\u0002C\u0001\u0011)\u001d\t\tc%D\u0001#\u0015\t\u0019C%\u0001\u0003mC:<\'\"A\u0013\u0002\t)\fg/Y\u0005\u0003O\t\na\u0002\u0015:pG\u0016\u001c8OQ;jY\u0012,\'/\u0003\u0002*U\tA!+\u001a3je\u0016\u001cGO\u0003\u0002(E\u0005a!/\u001a3je\u0016\u001cGO\u0012:p[\u0006a\u0001O]8dKN\u001c\u0018J\u001c9viR\u0011a&\r\t\u0003!=R!\u0001M\t\u0002\t9{g.\u001a\u0005\u0007e\u0015!\t\u0019A\u001a\u0002\u000bM$H-\u001b8\u0011\u0007A!d\'\u0003\u00026#\tAAHY=oC6,g\b\u0005\u00028u9\u0011A\u0002O\u0005\u0003s!\t!bU;c!J|7-Z:t\u0013\tYDHA\u0006J]B,Ho\u0015;sK\u0006l\'BA\u001d\t\u00035\u0001(o\\2fgN|U\u000f\u001e9viR\u0011af\u0010\u0005\u0007e\u0019!\t\u0019\u0001!\u0011\u0007A!\u0014\t\u0005\u00028\u0005&\u00111\t\u0010\u0002\r\u001fV$\b/\u001e;TiJ,\u0017-\u001c"
    )
  ScalaSig: length = 0x3 (unknown attribute)
   05 02 00
