Classfile /Users/mw/Projects/slang-braindump/.jar/jar11/assemble/slang-braindump/assemble/content/os/PosixStatInfo.class
  Last modified May 29, 2022; size 5270 bytes
  SHA-256 checksum a3c01d574c776565f35cdf43d7fbe388f99fdb8fdcf02693d4b191e23af132b2
  Compiled from "Model.scala"
public class os.PosixStatInfo implements scala.Product,java.io.Serializable
  minor version: 0
  major version: 52
  flags: (0x0021) ACC_PUBLIC, ACC_SUPER
  this_class: #2                          // os/PosixStatInfo
  super_class: #4                         // java/lang/Object
  interfaces: 2, fields: 2, methods: 19, attributes: 4
Constant pool:
    #1 = Utf8               os/PosixStatInfo
    #2 = Class              #1            // os/PosixStatInfo
    #3 = Utf8               java/lang/Object
    #4 = Class              #3            // java/lang/Object
    #5 = Utf8               scala/Product
    #6 = Class              #5            // scala/Product
    #7 = Utf8               java/io/Serializable
    #8 = Class              #7            // java/io/Serializable
    #9 = Utf8               Model.scala
   #10 = Utf8               Lscala/reflect/ScalaSignature;
   #11 = Utf8               bytes
   #12 = Utf8               \u0006\u0005\u0005\u0005d\u0001B\r\u001b\u0001vA\u0001b\r\u0001\u0003\u0016\u0004%\t\u0001\u000e\u0005\t\u0003\u0002\u0011\t\u0012)A\u0005k!A!\t\u0001BK\u0002\u0013\u00051\t\u0003\u0005I\u0001\tE\t\u0015!\u0003E\u0011\u0015I\u0005\u0001\"\u0001K\u0011\u001dq\u0005!!A\u0005\u0002=CqA\u0015\u0001\u0012\u0002\u0013\u00051\u000bC\u0004_\u0001E\u0005I\u0011A0\t\u000f\u0005\u0004\u0011\u0011!C!E\"9\u0011\u000eAA\u0001\n\u0003Q\u0007b\u00028\u0001\u0003\u0003%\ta\u001c\u0005\bk\u0002\t\t\u0011\"\u0011w\u0011\u001di\b!!A\u0005\u0002yD\u0011\"a\u0002\u0001\u0003\u0003%\t%!\u0003\t\u0013\u00055\u0001!!A\u0005B\u0005=\u0001\"CA\t\u0001\u0005\u0005I\u0011IA\n\u0011%\t)\u0002AA\u0001\n\u0003\n9bB\u0004\u0002\u001ciA\t!!\b\u0007\reQ\u0002\u0012AA\u0010\u0011\u0019I5\u0003\"\u0001\u0002,!9\u0011QF\n\u0005\u0002\u0005=\u0002\"CA\u001e\'\u0005\u0005I\u0011QA\u001f\u0011%\t\u0019eEA\u0001\n\u0003\u000b)\u0005C\u0005\u0002XM\t\t\u0011\"\u0003\u0002Z\ti\u0001k\\:jqN#\u0018\r^%oM>T\u0011aG\u0001\u0003_N\u001c\u0001a\u0005\u0003\u0001=\u0011:\u0003CA\u0010#\u001b\u0005\u0001#\"A\u0011\u0002\u000bM\u001c\u0017\r\\1\n\u0005\r\u0002#AB!osJ+g\r\u0005\u0002 K%\u0011a\u0005\t\u0002\b!J|G-^2u!\tA\u0003G\u0004\u0002*]9\u0011!&L\u0007\u0002W)\u0011A\u0006H\u0001\u0007yI|w\u000e\u001e \n\u0003\u0005J!a\f\u0011\u0002\u000fA\f7m[1hK&\u0011\u0011G\r\u0002\r\'\u0016\u0014\u0018.\u00197ju\u0006\u0014G.\u001a\u0006\u0003_\u0001\nQa\\<oKJ,\u0012!\u000e\t\u0003m}j\u0011a\u000e\u0006\u0003qe\n\u0011\"\u0019;ue&\u0014W\u000f^3\u000b\u0005iZ\u0014\u0001\u00024jY\u0016T!\u0001P\u001f\u0002\u00079LwNC\u0001?\u0003\u0011Q\u0017M^1\n\u0005\u0001;$!D+tKJ\u0004&/\u001b8dSB\fG.\u0001\u0004po:,\'\u000fI\u0001\fa\u0016\u0014X.[:tS>t7/F\u0001E!\t)e)D\u0001\u001b\u0013\t9%DA\u0004QKJl7+\u001a;\u0002\u0019A,\'/\\5tg&|gn\u001d\u0011\u0002\rqJg.\u001b;?)\rYE*\u0014\t\u0003\u000b\u0002AQaM\u0003A\u0002UBQAQ\u0003A\u0002\u0011\u000bAaY8qsR\u00191\nU)\t\u000fM2\u0001\u0013!a\u0001k!9!I\u0002I\u0001\u0002\u0004!\u0015AD2paf$C-\u001a4bk2$H%M\u000b\u0002)*\u0012Q\'V\u0016\u0002-B\u0011q\u000bX\u0007\u00021*\u0011\u0011LW\u0001\nk:\u001c\u0007.Z2lK\u0012T!a\u0017\u0011\u0002\u0015\u0005tgn\u001c;bi&|g.\u0003\u0002^1\n\tRO\\2iK\u000e\\W\r\u001a,be&\fgnY3\u0002\u001d\r|\u0007/\u001f\u0013eK\u001a\fW\u000f\u001c;%eU\t\u0001M\u000b\u0002E+\u0006i\u0001O]8ek\u000e$\bK]3gSb,\u0012a\u0019\t\u0003I\u001el\u0011!\u001a\u0006\u0003Mv\nA\u0001\\1oO&\u0011\u0001.\u001a\u0002\u0007\'R\u0014\u0018N\\4\u0002\u0019A\u0014x\u000eZ;di\u0006\u0013\u0018\u000e^=\u0016\u0003-\u0004\"a\b7\n\u00055\u0004#aA%oi\u0006q\u0001O]8ek\u000e$X\t\\3nK:$HC\u00019t!\ty\u0012/\u0003\u0002sA\t\u0019\u0011I\\=\t\u000fQ\\\u0011\u0011!a\u0001W\u0006\u0019\u0001\u0010J\u0019\u0002\u001fA\u0014x\u000eZ;di&#XM]1u_J,\u0012a\u001e\t\u0004qn\u0004X\"A=\u000b\u0005i\u0004\u0013AC2pY2,7\r^5p]&\u0011A0\u001f\u0002\t\u0013R,\'/\u0019;pe\u0006A1-\u00198FcV\fG\u000eF\u0002\u0000\u0003\u000b\u00012aHA\u0001\u0013\r\t\u0019\u0001\t\u0002\b\u0005>|G.Z1o\u0011\u001d!X\"!AA\u0002A\f!\u0003\u001d:pIV\u001cG/\u00127f[\u0016tGOT1nKR\u00191-a\u0003\t\u000fQt\u0011\u0011!a\u0001W\u0006A\u0001.Y:i\u0007>$W\rF\u0001l\u0003!!xn\u0015;sS:<G#A2\u0002\r\u0015\fX/\u00197t)\ry\u0018\u0011\u0004\u0005\biF\t\t\u00111\u0001q\u00035\u0001vn]5y\'R\fG/\u00138g_B\u0011QiE\n\u0005\'y\t\t\u0003\u0005\u0003\u0002$\u0005%RBAA\u0013\u0015\r\t9#P\u0001\u0003S>L1!MA\u0013)\t\ti\"\u0001\u0003nC.,GcA&\u00022!9\u00111G\u000bA\u0002\u0005U\u0012A\u00039pg&D\u0018\t\u001e;sgB\u0019a\'a\u000e\n\u0007\u0005erGA\nQ_NL\u0007PR5mK\u0006#HO]5ckR,7/A\u0003baBd\u0017\u0010F\u0003L\u0003\u007f\t\t\u0005C\u00034-\u0001\u0007Q\u0007C\u0003C-\u0001\u0007A)A\u0004v]\u0006\u0004\b\u000f\\=\u0015\t\u0005\u001d\u00131\u000b\t\u0006?\u0005%\u0013QJ\u0005\u0004\u0003\u0017\u0002#AB(qi&|g\u000eE\u0003 \u0003\u001f*D)C\u0002\u0002R\u0001\u0012a\u0001V;qY\u0016\u0014\u0004\u0002CA+/\u0005\u0005\t\u0019A&\u0002\u0007a$\u0003\'\u0001\u0007xe&$XMU3qY\u0006\u001cW\r\u0006\u0002\u0002\\A\u0019A-!\u0018\n\u0007\u0005}SM\u0001\u0004PE*,7\r\u001e
   #13 = Utf8               owner
   #14 = Utf8               Ljava/nio/file/attribute/UserPrincipal;
   #15 = Utf8               permissions
   #16 = Utf8               Los/PermSet;
   #17 = Utf8               unapply
   #18 = Utf8               (Los/PosixStatInfo;)Lscala/Option;
   #19 = Utf8               (Los/PosixStatInfo;)Lscala/Option<Lscala/Tuple2<Ljava/nio/file/attribute/UserPrincipal;Los/PermSet;>;>;
   #20 = Utf8               x$0
   #21 = Utf8               os/PosixStatInfo$
   #22 = Class              #21           // os/PosixStatInfo$
   #23 = Utf8               MODULE$
   #24 = Utf8               Los/PosixStatInfo$;
   #25 = NameAndType        #23:#24       // MODULE$:Los/PosixStatInfo$;
   #26 = Fieldref           #22.#25       // os/PosixStatInfo$.MODULE$:Los/PosixStatInfo$;
   #27 = NameAndType        #17:#18       // unapply:(Los/PosixStatInfo;)Lscala/Option;
   #28 = Methodref          #22.#27       // os/PosixStatInfo$.unapply:(Los/PosixStatInfo;)Lscala/Option;
   #29 = Utf8               apply
   #30 = Utf8               (Ljava/nio/file/attribute/UserPrincipal;Los/PermSet;)Los/PosixStatInfo;
   #31 = NameAndType        #29:#30       // apply:(Ljava/nio/file/attribute/UserPrincipal;Los/PermSet;)Los/PosixStatInfo;
   #32 = Methodref          #22.#31       // os/PosixStatInfo$.apply:(Ljava/nio/file/attribute/UserPrincipal;Los/PermSet;)Los/PosixStatInfo;
   #33 = Utf8               make
   #34 = Utf8               (Ljava/nio/file/attribute/PosixFileAttributes;)Los/PosixStatInfo;
   #35 = Utf8               posixAttrs
   #36 = NameAndType        #33:#34       // make:(Ljava/nio/file/attribute/PosixFileAttributes;)Los/PosixStatInfo;
   #37 = Methodref          #22.#36       // os/PosixStatInfo$.make:(Ljava/nio/file/attribute/PosixFileAttributes;)Los/PosixStatInfo;
   #38 = Utf8               productElementNames
   #39 = Utf8               ()Lscala/collection/Iterator;
   #40 = Utf8               ()Lscala/collection/Iterator<Ljava/lang/String;>;
   #41 = Utf8               productElementNames$
   #42 = Utf8               (Lscala/Product;)Lscala/collection/Iterator;
   #43 = NameAndType        #41:#42       // productElementNames$:(Lscala/Product;)Lscala/collection/Iterator;
   #44 = InterfaceMethodref #6.#43        // scala/Product.productElementNames$:(Lscala/Product;)Lscala/collection/Iterator;
   #45 = Utf8               this
   #46 = Utf8               Los/PosixStatInfo;
   #47 = Utf8               ()Ljava/nio/file/attribute/UserPrincipal;
   #48 = NameAndType        #13:#14       // owner:Ljava/nio/file/attribute/UserPrincipal;
   #49 = Fieldref           #2.#48        // os/PosixStatInfo.owner:Ljava/nio/file/attribute/UserPrincipal;
   #50 = Utf8               ()Los/PermSet;
   #51 = NameAndType        #15:#16       // permissions:Los/PermSet;
   #52 = Fieldref           #2.#51        // os/PosixStatInfo.permissions:Los/PermSet;
   #53 = Utf8               copy
   #54 = Utf8               <init>
   #55 = Utf8               (Ljava/nio/file/attribute/UserPrincipal;Los/PermSet;)V
   #56 = NameAndType        #54:#55       // "<init>":(Ljava/nio/file/attribute/UserPrincipal;Los/PermSet;)V
   #57 = Methodref          #2.#56        // os/PosixStatInfo."<init>":(Ljava/nio/file/attribute/UserPrincipal;Los/PermSet;)V
   #58 = Utf8               copy$default$1
   #59 = NameAndType        #13:#47       // owner:()Ljava/nio/file/attribute/UserPrincipal;
   #60 = Methodref          #2.#59        // os/PosixStatInfo.owner:()Ljava/nio/file/attribute/UserPrincipal;
   #61 = Utf8               copy$default$2
   #62 = NameAndType        #15:#50       // permissions:()Los/PermSet;
   #63 = Methodref          #2.#62        // os/PosixStatInfo.permissions:()Los/PermSet;
   #64 = Utf8               productPrefix
   #65 = Utf8               ()Ljava/lang/String;
   #66 = Utf8               PosixStatInfo
   #67 = String             #66           // PosixStatInfo
   #68 = Utf8               productArity
   #69 = Utf8               ()I
   #70 = Utf8               productElement
   #71 = Utf8               (I)Ljava/lang/Object;
   #72 = Utf8               x$1
   #73 = Utf8               scala/runtime/Statics
   #74 = Class              #73           // scala/runtime/Statics
   #75 = Utf8               ioobe
   #76 = NameAndType        #75:#71       // ioobe:(I)Ljava/lang/Object;
   #77 = Methodref          #74.#76       // scala/runtime/Statics.ioobe:(I)Ljava/lang/Object;
   #78 = Utf8               I
   #79 = Utf8               productIterator
   #80 = Utf8               ()Lscala/collection/Iterator<Ljava/lang/Object;>;
   #81 = Utf8               scala/runtime/ScalaRunTime$
   #82 = Class              #81           // scala/runtime/ScalaRunTime$
   #83 = Utf8               Lscala/runtime/ScalaRunTime$;
   #84 = NameAndType        #23:#83       // MODULE$:Lscala/runtime/ScalaRunTime$;
   #85 = Fieldref           #82.#84       // scala/runtime/ScalaRunTime$.MODULE$:Lscala/runtime/ScalaRunTime$;
   #86 = Utf8               typedProductIterator
   #87 = NameAndType        #86:#42       // typedProductIterator:(Lscala/Product;)Lscala/collection/Iterator;
   #88 = Methodref          #82.#87       // scala/runtime/ScalaRunTime$.typedProductIterator:(Lscala/Product;)Lscala/collection/Iterator;
   #89 = Utf8               canEqual
   #90 = Utf8               (Ljava/lang/Object;)Z
   #91 = Utf8               Ljava/lang/Object;
   #92 = Utf8               productElementName
   #93 = Utf8               (I)Ljava/lang/String;
   #94 = String             #13           // owner
   #95 = String             #15           // permissions
   #96 = Utf8               java/lang/String
   #97 = Class              #96           // java/lang/String
   #98 = Utf8               hashCode
   #99 = Utf8               _hashCode
  #100 = Utf8               (Lscala/Product;)I
  #101 = NameAndType        #99:#100      // _hashCode:(Lscala/Product;)I
  #102 = Methodref          #82.#101      // scala/runtime/ScalaRunTime$._hashCode:(Lscala/Product;)I
  #103 = Utf8               toString
  #104 = Utf8               _toString
  #105 = Utf8               (Lscala/Product;)Ljava/lang/String;
  #106 = NameAndType        #104:#105     // _toString:(Lscala/Product;)Ljava/lang/String;
  #107 = Methodref          #82.#106      // scala/runtime/ScalaRunTime$._toString:(Lscala/Product;)Ljava/lang/String;
  #108 = Utf8               equals
  #109 = NameAndType        #108:#90      // equals:(Ljava/lang/Object;)Z
  #110 = Methodref          #4.#109       // java/lang/Object.equals:(Ljava/lang/Object;)Z
  #111 = NameAndType        #89:#90       // canEqual:(Ljava/lang/Object;)Z
  #112 = Methodref          #2.#111       // os/PosixStatInfo.canEqual:(Ljava/lang/Object;)Z
  #113 = Utf8               java/nio/file/attribute/UserPrincipal
  #114 = Class              #113          // java/nio/file/attribute/UserPrincipal
  #115 = Utf8               os/PermSet
  #116 = Class              #115          // os/PermSet
  #117 = Utf8               ()V
  #118 = NameAndType        #54:#117      // "<init>":()V
  #119 = Methodref          #4.#118       // java/lang/Object."<init>":()V
  #120 = Utf8               $init$
  #121 = Utf8               (Lscala/Product;)V
  #122 = NameAndType        #120:#121     // $init$:(Lscala/Product;)V
  #123 = InterfaceMethodref #6.#122       // scala/Product.$init$:(Lscala/Product;)V
  #124 = Utf8               Code
  #125 = Utf8               Signature
  #126 = Utf8               MethodParameters
  #127 = Utf8               LineNumberTable
  #128 = Utf8               LocalVariableTable
  #129 = Utf8               StackMapTable
  #130 = Utf8               SourceFile
  #131 = Utf8               RuntimeVisibleAnnotations
  #132 = Utf8               ScalaInlineInfo
  #133 = Utf8               ScalaSig
{
  private final java.nio.file.attribute.UserPrincipal owner;
    descriptor: Ljava/nio/file/attribute/UserPrincipal;
    flags: (0x0012) ACC_PRIVATE, ACC_FINAL

  private final os.PermSet permissions;
    descriptor: Los/PermSet;
    flags: (0x0012) ACC_PRIVATE, ACC_FINAL

  public static scala.Option<scala.Tuple2<java.nio.file.attribute.UserPrincipal, os.PermSet>> unapply(os.PosixStatInfo);
    descriptor: (Los/PosixStatInfo;)Lscala/Option;
    flags: (0x0009) ACC_PUBLIC, ACC_STATIC
    Code:
      stack=2, locals=1, args_size=1
         0: getstatic     #26                 // Field os/PosixStatInfo$.MODULE$:Los/PosixStatInfo$;
         3: aload_0
         4: invokevirtual #28                 // Method os/PosixStatInfo$.unapply:(Los/PosixStatInfo;)Lscala/Option;
         7: areturn
    Signature: #19                          // (Los/PosixStatInfo;)Lscala/Option<Lscala/Tuple2<Ljava/nio/file/attribute/UserPrincipal;Los/PermSet;>;>;
    MethodParameters:
      Name                           Flags
      x$0                            final

  public static os.PosixStatInfo apply(java.nio.file.attribute.UserPrincipal, os.PermSet);
    descriptor: (Ljava/nio/file/attribute/UserPrincipal;Los/PermSet;)Los/PosixStatInfo;
    flags: (0x0009) ACC_PUBLIC, ACC_STATIC
    Code:
      stack=3, locals=2, args_size=2
         0: getstatic     #26                 // Field os/PosixStatInfo$.MODULE$:Los/PosixStatInfo$;
         3: aload_0
         4: aload_1
         5: invokevirtual #32                 // Method os/PosixStatInfo$.apply:(Ljava/nio/file/attribute/UserPrincipal;Los/PermSet;)Los/PosixStatInfo;
         8: areturn
    MethodParameters:
      Name                           Flags
      owner                          final
      permissions                    final

  public static os.PosixStatInfo make(java.nio.file.attribute.PosixFileAttributes);
    descriptor: (Ljava/nio/file/attribute/PosixFileAttributes;)Los/PosixStatInfo;
    flags: (0x0009) ACC_PUBLIC, ACC_STATIC
    Code:
      stack=2, locals=1, args_size=1
         0: getstatic     #26                 // Field os/PosixStatInfo$.MODULE$:Los/PosixStatInfo$;
         3: aload_0
         4: invokevirtual #37                 // Method os/PosixStatInfo$.make:(Ljava/nio/file/attribute/PosixFileAttributes;)Los/PosixStatInfo;
         7: areturn
    MethodParameters:
      Name                           Flags
      posixAttrs                     final

  public scala.collection.Iterator<java.lang.String> productElementNames();
    descriptor: ()Lscala/collection/Iterator;
    flags: (0x0001) ACC_PUBLIC
    Code:
      stack=1, locals=1, args_size=1
         0: aload_0
         1: invokestatic  #44                 // InterfaceMethod scala/Product.productElementNames$:(Lscala/Product;)Lscala/collection/Iterator;
         4: areturn
      LineNumberTable:
        line 258: 0
      LocalVariableTable:
        Start  Length  Slot  Name   Signature
            0       5     0  this   Los/PosixStatInfo;
    Signature: #40                          // ()Lscala/collection/Iterator<Ljava/lang/String;>;

  public java.nio.file.attribute.UserPrincipal owner();
    descriptor: ()Ljava/nio/file/attribute/UserPrincipal;
    flags: (0x0001) ACC_PUBLIC
    Code:
      stack=1, locals=1, args_size=1
         0: aload_0
         1: getfield      #49                 // Field owner:Ljava/nio/file/attribute/UserPrincipal;
         4: areturn
      LineNumberTable:
        line 258: 0
      LocalVariableTable:
        Start  Length  Slot  Name   Signature
            0       5     0  this   Los/PosixStatInfo;

  public os.PermSet permissions();
    descriptor: ()Los/PermSet;
    flags: (0x0001) ACC_PUBLIC
    Code:
      stack=1, locals=1, args_size=1
         0: aload_0
         1: getfield      #52                 // Field permissions:Los/PermSet;
         4: areturn
      LineNumberTable:
        line 258: 0
      LocalVariableTable:
        Start  Length  Slot  Name   Signature
            0       5     0  this   Los/PosixStatInfo;

  public os.PosixStatInfo copy(java.nio.file.attribute.UserPrincipal, os.PermSet);
    descriptor: (Ljava/nio/file/attribute/UserPrincipal;Los/PermSet;)Los/PosixStatInfo;
    flags: (0x0001) ACC_PUBLIC
    Code:
      stack=4, locals=3, args_size=3
         0: new           #2                  // class os/PosixStatInfo
         3: dup
         4: aload_1
         5: aload_2
         6: invokespecial #57                 // Method "<init>":(Ljava/nio/file/attribute/UserPrincipal;Los/PermSet;)V
         9: areturn
      LineNumberTable:
        line 258: 0
      LocalVariableTable:
        Start  Length  Slot  Name   Signature
            0      10     0  this   Los/PosixStatInfo;
            0      10     1 owner   Ljava/nio/file/attribute/UserPrincipal;
            0      10     2 permissions   Los/PermSet;
    MethodParameters:
      Name                           Flags
      owner                          final
      permissions                    final

  public java.nio.file.attribute.UserPrincipal copy$default$1();
    descriptor: ()Ljava/nio/file/attribute/UserPrincipal;
    flags: (0x0001) ACC_PUBLIC
    Code:
      stack=1, locals=1, args_size=1
         0: aload_0
         1: invokevirtual #60                 // Method owner:()Ljava/nio/file/attribute/UserPrincipal;
         4: areturn
      LineNumberTable:
        line 258: 0
      LocalVariableTable:
        Start  Length  Slot  Name   Signature
            0       5     0  this   Los/PosixStatInfo;

  public os.PermSet copy$default$2();
    descriptor: ()Los/PermSet;
    flags: (0x0001) ACC_PUBLIC
    Code:
      stack=1, locals=1, args_size=1
         0: aload_0
         1: invokevirtual #63                 // Method permissions:()Los/PermSet;
         4: areturn
      LineNumberTable:
        line 258: 0
      LocalVariableTable:
        Start  Length  Slot  Name   Signature
            0       5     0  this   Los/PosixStatInfo;

  public java.lang.String productPrefix();
    descriptor: ()Ljava/lang/String;
    flags: (0x0001) ACC_PUBLIC
    Code:
      stack=1, locals=1, args_size=1
         0: ldc           #67                 // String PosixStatInfo
         2: areturn
      LineNumberTable:
        line 258: 0
      LocalVariableTable:
        Start  Length  Slot  Name   Signature
            0       3     0  this   Los/PosixStatInfo;

  public int productArity();
    descriptor: ()I
    flags: (0x0001) ACC_PUBLIC
    Code:
      stack=1, locals=1, args_size=1
         0: iconst_2
         1: ireturn
      LineNumberTable:
        line 258: 0
      LocalVariableTable:
        Start  Length  Slot  Name   Signature
            0       2     0  this   Los/PosixStatInfo;

  public java.lang.Object productElement(int);
    descriptor: (I)Ljava/lang/Object;
    flags: (0x0001) ACC_PUBLIC
    Code:
      stack=1, locals=3, args_size=2
         0: iload_1
         1: istore_2
         2: iload_2
         3: tableswitch   { // 0 to 1
                       0: 24
                       1: 31
                 default: 38
            }
        24: aload_0
        25: invokevirtual #60                 // Method owner:()Ljava/nio/file/attribute/UserPrincipal;
        28: goto          45
        31: aload_0
        32: invokevirtual #63                 // Method permissions:()Los/PermSet;
        35: goto          45
        38: iload_1
        39: invokestatic  #77                 // Method scala/runtime/Statics.ioobe:(I)Ljava/lang/Object;
        42: goto          45
        45: areturn
      StackMapTable: number_of_entries = 4
        frame_type = 252 /* append */
          offset_delta = 24
          locals = [ int ]
        frame_type = 6 /* same */
        frame_type = 6 /* same */
        frame_type = 70 /* same_locals_1_stack_item */
          stack = [ class java/lang/Object ]
      LineNumberTable:
        line 258: 0
      LocalVariableTable:
        Start  Length  Slot  Name   Signature
            0      46     0  this   Los/PosixStatInfo;
            0      46     1   x$1   I
    MethodParameters:
      Name                           Flags
      x$1                            final

  public scala.collection.Iterator<java.lang.Object> productIterator();
    descriptor: ()Lscala/collection/Iterator;
    flags: (0x0001) ACC_PUBLIC
    Code:
      stack=2, locals=1, args_size=1
         0: getstatic     #85                 // Field scala/runtime/ScalaRunTime$.MODULE$:Lscala/runtime/ScalaRunTime$;
         3: aload_0
         4: invokevirtual #88                 // Method scala/runtime/ScalaRunTime$.typedProductIterator:(Lscala/Product;)Lscala/collection/Iterator;
         7: areturn
      LineNumberTable:
        line 258: 0
      LocalVariableTable:
        Start  Length  Slot  Name   Signature
            0       8     0  this   Los/PosixStatInfo;
    Signature: #80                          // ()Lscala/collection/Iterator<Ljava/lang/Object;>;

  public boolean canEqual(java.lang.Object);
    descriptor: (Ljava/lang/Object;)Z
    flags: (0x0001) ACC_PUBLIC
    Code:
      stack=1, locals=2, args_size=2
         0: aload_1
         1: instanceof    #2                  // class os/PosixStatInfo
         4: ireturn
      LineNumberTable:
        line 258: 0
      LocalVariableTable:
        Start  Length  Slot  Name   Signature
            0       5     0  this   Los/PosixStatInfo;
            0       5     1   x$1   Ljava/lang/Object;
    MethodParameters:
      Name                           Flags
      x$1                            final

  public java.lang.String productElementName(int);
    descriptor: (I)Ljava/lang/String;
    flags: (0x0001) ACC_PUBLIC
    Code:
      stack=1, locals=3, args_size=2
         0: iload_1
         1: istore_2
         2: iload_2
         3: tableswitch   { // 0 to 1
                       0: 24
                       1: 29
                 default: 34
            }
        24: ldc           #94                 // String owner
        26: goto          44
        29: ldc           #95                 // String permissions
        31: goto          44
        34: iload_1
        35: invokestatic  #77                 // Method scala/runtime/Statics.ioobe:(I)Ljava/lang/Object;
        38: checkcast     #97                 // class java/lang/String
        41: goto          44
        44: areturn
      StackMapTable: number_of_entries = 4
        frame_type = 252 /* append */
          offset_delta = 24
          locals = [ int ]
        frame_type = 4 /* same */
        frame_type = 4 /* same */
        frame_type = 73 /* same_locals_1_stack_item */
          stack = [ class java/lang/String ]
      LineNumberTable:
        line 258: 0
      LocalVariableTable:
        Start  Length  Slot  Name   Signature
            0      45     0  this   Los/PosixStatInfo;
            0      45     1   x$1   I
    MethodParameters:
      Name                           Flags
      x$1                            final

  public int hashCode();
    descriptor: ()I
    flags: (0x0001) ACC_PUBLIC
    Code:
      stack=2, locals=1, args_size=1
         0: getstatic     #85                 // Field scala/runtime/ScalaRunTime$.MODULE$:Lscala/runtime/ScalaRunTime$;
         3: aload_0
         4: invokevirtual #102                // Method scala/runtime/ScalaRunTime$._hashCode:(Lscala/Product;)I
         7: ireturn
      LineNumberTable:
        line 258: 0
      LocalVariableTable:
        Start  Length  Slot  Name   Signature
            0       8     0  this   Los/PosixStatInfo;

  public java.lang.String toString();
    descriptor: ()Ljava/lang/String;
    flags: (0x0001) ACC_PUBLIC
    Code:
      stack=2, locals=1, args_size=1
         0: getstatic     #85                 // Field scala/runtime/ScalaRunTime$.MODULE$:Lscala/runtime/ScalaRunTime$;
         3: aload_0
         4: invokevirtual #107                // Method scala/runtime/ScalaRunTime$._toString:(Lscala/Product;)Ljava/lang/String;
         7: areturn
      LineNumberTable:
        line 258: 0
      LocalVariableTable:
        Start  Length  Slot  Name   Signature
            0       8     0  this   Los/PosixStatInfo;

  public boolean equals(java.lang.Object);
    descriptor: (Ljava/lang/Object;)Z
    flags: (0x0001) ACC_PUBLIC
    Code:
      stack=2, locals=7, args_size=2
         0: aload_0
         1: aload_1
         2: if_acmpeq     118
         5: aload_1
         6: astore_3
         7: aload_3
         8: instanceof    #2                  // class os/PosixStatInfo
        11: ifeq          19
        14: iconst_1
        15: istore_2
        16: goto          27
        19: goto          22
        22: iconst_0
        23: istore_2
        24: goto          27
        27: iload_2
        28: ifeq          122
        31: aload_1
        32: checkcast     #2                  // class os/PosixStatInfo
        35: astore        4
        37: aload_0
        38: invokevirtual #60                 // Method owner:()Ljava/nio/file/attribute/UserPrincipal;
        41: aload         4
        43: invokevirtual #60                 // Method owner:()Ljava/nio/file/attribute/UserPrincipal;
        46: astore        5
        48: dup
        49: ifnonnull     61
        52: pop
        53: aload         5
        55: ifnull        69
        58: goto          114
        61: aload         5
        63: invokevirtual #110                // Method java/lang/Object.equals:(Ljava/lang/Object;)Z
        66: ifeq          114
        69: aload_0
        70: invokevirtual #63                 // Method permissions:()Los/PermSet;
        73: aload         4
        75: invokevirtual #63                 // Method permissions:()Los/PermSet;
        78: astore        6
        80: dup
        81: ifnonnull     93
        84: pop
        85: aload         6
        87: ifnull        101
        90: goto          114
        93: aload         6
        95: invokevirtual #110                // Method java/lang/Object.equals:(Ljava/lang/Object;)Z
        98: ifeq          114
       101: aload         4
       103: aload_0
       104: invokevirtual #112                // Method canEqual:(Ljava/lang/Object;)Z
       107: ifeq          114
       110: iconst_1
       111: goto          115
       114: iconst_0
       115: ifeq          122
       118: iconst_1
       119: goto          123
       122: iconst_0
       123: ireturn
      StackMapTable: number_of_entries = 12
        frame_type = 253 /* append */
          offset_delta = 19
          locals = [ top, class java/lang/Object ]
        frame_type = 2 /* same */
        frame_type = 255 /* full_frame */
          offset_delta = 4
          locals = [ class os/PosixStatInfo, class java/lang/Object, int, class java/lang/Object ]
          stack = []
        frame_type = 255 /* full_frame */
          offset_delta = 33
          locals = [ class os/PosixStatInfo, class java/lang/Object, int, class java/lang/Object, class os/PosixStatInfo, class java/nio/file/attribute/UserPrincipal ]
          stack = [ class java/nio/file/attribute/UserPrincipal ]
        frame_type = 7 /* same */
        frame_type = 255 /* full_frame */
          offset_delta = 23
          locals = [ class os/PosixStatInfo, class java/lang/Object, int, class java/lang/Object, class os/PosixStatInfo, class java/nio/file/attribute/UserPrincipal, class os/PermSet ]
          stack = [ class os/PermSet ]
        frame_type = 7 /* same */
        frame_type = 250 /* chop */
          offset_delta = 12
        frame_type = 64 /* same_locals_1_stack_item */
          stack = [ int ]
        frame_type = 255 /* full_frame */
          offset_delta = 2
          locals = [ class os/PosixStatInfo, class java/lang/Object ]
          stack = []
        frame_type = 253 /* append */
          offset_delta = 3
          locals = [ int, class java/lang/Object ]
        frame_type = 255 /* full_frame */
          offset_delta = 0
          locals = [ class os/PosixStatInfo, class java/lang/Object ]
          stack = [ int ]
      LineNumberTable:
        line 258: 0
      LocalVariableTable:
        Start  Length  Slot  Name   Signature
            0     124     0  this   Los/PosixStatInfo;
            0     124     1   x$1   Ljava/lang/Object;
    MethodParameters:
      Name                           Flags
      x$1                            final

  public os.PosixStatInfo(java.nio.file.attribute.UserPrincipal, os.PermSet);
    descriptor: (Ljava/nio/file/attribute/UserPrincipal;Los/PermSet;)V
    flags: (0x0001) ACC_PUBLIC
    Code:
      stack=2, locals=3, args_size=3
         0: aload_0
         1: aload_1
         2: putfield      #49                 // Field owner:Ljava/nio/file/attribute/UserPrincipal;
         5: aload_0
         6: aload_2
         7: putfield      #52                 // Field permissions:Los/PermSet;
        10: aload_0
        11: invokespecial #119                // Method java/lang/Object."<init>":()V
        14: aload_0
        15: invokestatic  #123                // InterfaceMethod scala/Product.$init$:(Lscala/Product;)V
        18: return
      LineNumberTable:
        line 258: 0
      LocalVariableTable:
        Start  Length  Slot  Name   Signature
            0      19     0  this   Los/PosixStatInfo;
            0      19     1 owner   Ljava/nio/file/attribute/UserPrincipal;
            0      19     2 permissions   Los/PermSet;
    MethodParameters:
      Name                           Flags
      owner                          final
      permissions                    final
}
SourceFile: "Model.scala"
RuntimeVisibleAnnotations:
  0: #10(#11=s#12)
    scala.reflect.ScalaSignature(
      bytes="\u0006\u0005\u0005\u0005d\u0001B\r\u001b\u0001vA\u0001b\r\u0001\u0003\u0016\u0004%\t\u0001\u000e\u0005\t\u0003\u0002\u0011\t\u0012)A\u0005k!A!\t\u0001BK\u0002\u0013\u00051\t\u0003\u0005I\u0001\tE\t\u0015!\u0003E\u0011\u0015I\u0005\u0001\"\u0001K\u0011\u001dq\u0005!!A\u0005\u0002=CqA\u0015\u0001\u0012\u0002\u0013\u00051\u000bC\u0004_\u0001E\u0005I\u0011A0\t\u000f\u0005\u0004\u0011\u0011!C!E\"9\u0011\u000eAA\u0001\n\u0003Q\u0007b\u00028\u0001\u0003\u0003%\ta\u001c\u0005\bk\u0002\t\t\u0011\"\u0011w\u0011\u001di\b!!A\u0005\u0002yD\u0011\"a\u0002\u0001\u0003\u0003%\t%!\u0003\t\u0013\u00055\u0001!!A\u0005B\u0005=\u0001\"CA\t\u0001\u0005\u0005I\u0011IA\n\u0011%\t)\u0002AA\u0001\n\u0003\n9bB\u0004\u0002\u001ciA\t!!\b\u0007\reQ\u0002\u0012AA\u0010\u0011\u0019I5\u0003\"\u0001\u0002,!9\u0011QF\n\u0005\u0002\u0005=\u0002\"CA\u001e\'\u0005\u0005I\u0011QA\u001f\u0011%\t\u0019eEA\u0001\n\u0003\u000b)\u0005C\u0005\u0002XM\t\t\u0011\"\u0003\u0002Z\ti\u0001k\\:jqN#\u0018\r^%oM>T\u0011aG\u0001\u0003_N\u001c\u0001a\u0005\u0003\u0001=\u0011:\u0003CA\u0010#\u001b\u0005\u0001#\"A\u0011\u0002\u000bM\u001c\u0017\r\\1\n\u0005\r\u0002#AB!osJ+g\r\u0005\u0002 K%\u0011a\u0005\t\u0002\b!J|G-^2u!\tA\u0003G\u0004\u0002*]9\u0011!&L\u0007\u0002W)\u0011A\u0006H\u0001\u0007yI|w\u000e\u001e \n\u0003\u0005J!a\f\u0011\u0002\u000fA\f7m[1hK&\u0011\u0011G\r\u0002\r\'\u0016\u0014\u0018.\u00197ju\u0006\u0014G.\u001a\u0006\u0003_\u0001\nQa\\<oKJ,\u0012!\u000e\t\u0003m}j\u0011a\u000e\u0006\u0003qe\n\u0011\"\u0019;ue&\u0014W\u000f^3\u000b\u0005iZ\u0014\u0001\u00024jY\u0016T!\u0001P\u001f\u0002\u00079LwNC\u0001?\u0003\u0011Q\u0017M^1\n\u0005\u0001;$!D+tKJ\u0004&/\u001b8dSB\fG.\u0001\u0004po:,\'\u000fI\u0001\fa\u0016\u0014X.[:tS>t7/F\u0001E!\t)e)D\u0001\u001b\u0013\t9%DA\u0004QKJl7+\u001a;\u0002\u0019A,\'/\\5tg&|gn\u001d\u0011\u0002\rqJg.\u001b;?)\rYE*\u0014\t\u0003\u000b\u0002AQaM\u0003A\u0002UBQAQ\u0003A\u0002\u0011\u000bAaY8qsR\u00191\nU)\t\u000fM2\u0001\u0013!a\u0001k!9!I\u0002I\u0001\u0002\u0004!\u0015AD2paf$C-\u001a4bk2$H%M\u000b\u0002)*\u0012Q\'V\u0016\u0002-B\u0011q\u000bX\u0007\u00021*\u0011\u0011LW\u0001\nk:\u001c\u0007.Z2lK\u0012T!a\u0017\u0011\u0002\u0015\u0005tgn\u001c;bi&|g.\u0003\u0002^1\n\tRO\\2iK\u000e\\W\r\u001a,be&\fgnY3\u0002\u001d\r|\u0007/\u001f\u0013eK\u001a\fW\u000f\u001c;%eU\t\u0001M\u000b\u0002E+\u0006i\u0001O]8ek\u000e$\bK]3gSb,\u0012a\u0019\t\u0003I\u001el\u0011!\u001a\u0006\u0003Mv\nA\u0001\\1oO&\u0011\u0001.\u001a\u0002\u0007\'R\u0014\u0018N\\4\u0002\u0019A\u0014x\u000eZ;di\u0006\u0013\u0018\u000e^=\u0016\u0003-\u0004\"a\b7\n\u00055\u0004#aA%oi\u0006q\u0001O]8ek\u000e$X\t\\3nK:$HC\u00019t!\ty\u0012/\u0003\u0002sA\t\u0019\u0011I\\=\t\u000fQ\\\u0011\u0011!a\u0001W\u0006\u0019\u0001\u0010J\u0019\u0002\u001fA\u0014x\u000eZ;di&#XM]1u_J,\u0012a\u001e\t\u0004qn\u0004X\"A=\u000b\u0005i\u0004\u0013AC2pY2,7\r^5p]&\u0011A0\u001f\u0002\t\u0013R,\'/\u0019;pe\u0006A1-\u00198FcV\fG\u000eF\u0002\u0000\u0003\u000b\u00012aHA\u0001\u0013\r\t\u0019\u0001\t\u0002\b\u0005>|G.Z1o\u0011\u001d!X\"!AA\u0002A\f!\u0003\u001d:pIV\u001cG/\u00127f[\u0016tGOT1nKR\u00191-a\u0003\t\u000fQt\u0011\u0011!a\u0001W\u0006A\u0001.Y:i\u0007>$W\rF\u0001l\u0003!!xn\u0015;sS:<G#A2\u0002\r\u0015\fX/\u00197t)\ry\u0018\u0011\u0004\u0005\biF\t\t\u00111\u0001q\u00035\u0001vn]5y\'R\fG/\u00138g_B\u0011QiE\n\u0005\'y\t\t\u0003\u0005\u0003\u0002$\u0005%RBAA\u0013\u0015\r\t9#P\u0001\u0003S>L1!MA\u0013)\t\ti\"\u0001\u0003nC.,GcA&\u00022!9\u00111G\u000bA\u0002\u0005U\u0012A\u00039pg&D\u0018\t\u001e;sgB\u0019a\'a\u000e\n\u0007\u0005erGA\nQ_NL\u0007PR5mK\u0006#HO]5ckR,7/A\u0003baBd\u0017\u0010F\u0003L\u0003\u007f\t\t\u0005C\u00034-\u0001\u0007Q\u0007C\u0003C-\u0001\u0007A)A\u0004v]\u0006\u0004\b\u000f\\=\u0015\t\u0005\u001d\u00131\u000b\t\u0006?\u0005%\u0013QJ\u0005\u0004\u0003\u0017\u0002#AB(qi&|g\u000eE\u0003 \u0003\u001f*D)C\u0002\u0002R\u0001\u0012a\u0001V;qY\u0016\u0014\u0004\u0002CA+/\u0005\u0005\t\u0019A&\u0002\u0007a$\u0003\'\u0001\u0007xe&$XMU3qY\u0006\u001cW\r\u0006\u0002\u0002\\A\u0019A-!\u0018\n\u0007\u0005}SM\u0001\u0004PE*,7\r\u001e"
    )
  ScalaInlineInfo: length = 0x54 (unknown attribute)
   01 00 00 10 00 36 00 37 00 00 59 00 5A 00 00 35
   00 1E 00 00 3A 00 2F 00 00 3D 00 32 00 00 6C 00
   5A 00 00 62 00 45 00 00 0D 00 2F 00 00 0F 00 32
   00 00 44 00 45 00 00 46 00 47 00 00 5C 00 5D 00
   00 26 00 27 00 00 4F 00 27 00 00 40 00 41 00 00
   67 00 41 00
  ScalaSig: length = 0x3 (unknown attribute)
   05 02 00
