Classfile /Users/mw/Projects/slang-braindump/.jar/jar11/assemble/slang-braindump/assemble/content/os/ProcessInput$.class
  Last modified May 29, 2022; size 1193 bytes
  SHA-256 checksum ca24d67548d300d1bd40f47658aeab60efe8888870c61a8d4ae6c3715a2e96e6
  Compiled from "SubProcess.scala"
public final class os.ProcessInput$
  minor version: 0
  major version: 52
  flags: (0x0031) ACC_PUBLIC, ACC_FINAL, ACC_SUPER
  this_class: #2                          // os/ProcessInput$
  super_class: #4                         // java/lang/Object
  interfaces: 0, fields: 1, methods: 4, attributes: 4
Constant pool:
   #1 = Utf8               os/ProcessInput$
   #2 = Class              #1             // os/ProcessInput$
   #3 = Utf8               java/lang/Object
   #4 = Class              #3             // java/lang/Object
   #5 = Utf8               SubProcess.scala
   #6 = Utf8               os/ProcessInput$SourceInput
   #7 = Class              #6             // os/ProcessInput$SourceInput
   #8 = Utf8               os/ProcessInput
   #9 = Class              #8             // os/ProcessInput
  #10 = Utf8               SourceInput
  #11 = Utf8               MODULE$
  #12 = Utf8               Los/ProcessInput$;
  #13 = Utf8               <clinit>
  #14 = Utf8               ()V
  #15 = Utf8               <init>
  #16 = NameAndType        #15:#14        // "<init>":()V
  #17 = Methodref          #2.#16         // os/ProcessInput$."<init>":()V
  #18 = NameAndType        #11:#12        // MODULE$:Los/ProcessInput$;
  #19 = Fieldref           #2.#18         // os/ProcessInput$.MODULE$:Los/ProcessInput$;
  #20 = Utf8               makeSourceInput
  #21 = Utf8               (Ljava/lang/Object;Lscala/Function1;)Los/ProcessInput;
  #22 = Utf8               <T:Ljava/lang/Object;>(TT;Lscala/Function1<TT;Los/Source;>;)Los/ProcessInput;
  #23 = Utf8               r
  #24 = Utf8               f
  #25 = Utf8               scala/Function1
  #26 = Class              #25            // scala/Function1
  #27 = Utf8               apply
  #28 = Utf8               (Ljava/lang/Object;)Ljava/lang/Object;
  #29 = NameAndType        #27:#28        // apply:(Ljava/lang/Object;)Ljava/lang/Object;
  #30 = InterfaceMethodref #26.#29        // scala/Function1.apply:(Ljava/lang/Object;)Ljava/lang/Object;
  #31 = Utf8               os/Source
  #32 = Class              #31            // os/Source
  #33 = Utf8               (Los/Source;)V
  #34 = NameAndType        #15:#33        // "<init>":(Los/Source;)V
  #35 = Methodref          #7.#34         // os/ProcessInput$SourceInput."<init>":(Los/Source;)V
  #36 = Utf8               this
  #37 = Utf8               Ljava/lang/Object;
  #38 = Utf8               Lscala/Function1;
  #39 = Utf8               makePathRedirect
  #40 = Utf8               (Los/Path;)Los/ProcessInput;
  #41 = Utf8               p
  #42 = Utf8               os/PathRedirect
  #43 = Class              #42            // os/PathRedirect
  #44 = Utf8               (Los/Path;)V
  #45 = NameAndType        #15:#44        // "<init>":(Los/Path;)V
  #46 = Methodref          #43.#45        // os/PathRedirect."<init>":(Los/Path;)V
  #47 = Utf8               Los/Path;
  #48 = Methodref          #4.#16         // java/lang/Object."<init>":()V
  #49 = Utf8               Code
  #50 = Utf8               LineNumberTable
  #51 = Utf8               LocalVariableTable
  #52 = Utf8               Signature
  #53 = Utf8               MethodParameters
  #54 = Utf8               InnerClasses
  #55 = Utf8               SourceFile
  #56 = Utf8               ScalaInlineInfo
  #57 = Utf8               Scala
{
  public static final os.ProcessInput$ MODULE$;
    descriptor: Los/ProcessInput$;
    flags: (0x0019) ACC_PUBLIC, ACC_STATIC, ACC_FINAL

  public static {};
    descriptor: ()V
    flags: (0x0009) ACC_PUBLIC, ACC_STATIC
    Code:
      stack=2, locals=0, args_size=0
         0: new           #2                  // class os/ProcessInput$
         3: dup
         4: invokespecial #17                 // Method "<init>":()V
         7: putstatic     #19                 // Field MODULE$:Los/ProcessInput$;
        10: return
      LineNumberTable:
        line 177: 0

  public <T extends java.lang.Object> os.ProcessInput makeSourceInput(T, scala.Function1<T, os.Source>);
    descriptor: (Ljava/lang/Object;Lscala/Function1;)Los/ProcessInput;
    flags: (0x0001) ACC_PUBLIC
    Code:
      stack=4, locals=3, args_size=3
         0: new           #7                  // class os/ProcessInput$SourceInput
         3: dup
         4: aload_2
         5: aload_1
         6: invokeinterface #30,  2           // InterfaceMethod scala/Function1.apply:(Ljava/lang/Object;)Ljava/lang/Object;
        11: checkcast     #32                 // class os/Source
        14: invokespecial #35                 // Method os/ProcessInput$SourceInput."<init>":(Los/Source;)V
        17: areturn
      LineNumberTable:
        line 178: 0
      LocalVariableTable:
        Start  Length  Slot  Name   Signature
            0      18     0  this   Los/ProcessInput$;
            0      18     1     r   Ljava/lang/Object;
            0      18     2     f   Lscala/Function1;
    Signature: #22                          // <T:Ljava/lang/Object;>(TT;Lscala/Function1<TT;Los/Source;>;)Los/ProcessInput;
    MethodParameters:
      Name                           Flags
      r                              final
      f                              final

  public os.ProcessInput makePathRedirect(os.Path);
    descriptor: (Los/Path;)Los/ProcessInput;
    flags: (0x0001) ACC_PUBLIC
    Code:
      stack=3, locals=2, args_size=2
         0: new           #43                 // class os/PathRedirect
         3: dup
         4: aload_1
         5: invokespecial #46                 // Method os/PathRedirect."<init>":(Los/Path;)V
         8: areturn
      LineNumberTable:
        line 179: 0
      LocalVariableTable:
        Start  Length  Slot  Name   Signature
            0       9     0  this   Los/ProcessInput$;
            0       9     1     p   Los/Path;
    MethodParameters:
      Name                           Flags
      p                              final

  private os.ProcessInput$();
    descriptor: ()V
    flags: (0x0002) ACC_PRIVATE
    Code:
      stack=1, locals=1, args_size=1
         0: aload_0
         1: invokespecial #48                 // Method java/lang/Object."<init>":()V
         4: return
      LineNumberTable:
        line 196: 0
        line 177: 4
      LocalVariableTable:
        Start  Length  Slot  Name   Signature
            0       5     0  this   Los/ProcessInput$;
}
InnerClasses:
  public static #10= #7 of #9;            // SourceInput=class os/ProcessInput$SourceInput of class os/ProcessInput
SourceFile: "SubProcess.scala"
  ScalaInlineInfo: length = 0x13 (unknown attribute)
   01 01 00 03 00 0F 00 0E 01 00 27 00 28 01 00 14
   00 15 01
  Scala: length = 0x0 (unknown attribute)

