Classfile /Users/mw/Projects/slang-braindump/.jar/jar11/assemble/slang-braindump/assemble/content/os/RelPath.class
  Last modified May 29, 2022; size 10073 bytes
  SHA-256 checksum 0efa980dcf7091909ba954d338f7e11d63b894824548559f14d35c3bb67d5953
  Compiled from "Path.scala"
public class os.RelPath implements os.FilePath,os.BasePathImpl,os.SegmentedPath
  minor version: 0
  major version: 52
  flags: (0x0021) ACC_PUBLIC, ACC_SUPER
  this_class: #2                          // os/RelPath
  super_class: #4                         // java/lang/Object
  interfaces: 3, fields: 3, methods: 31, attributes: 6
Constant pool:
    #1 = Utf8               os/RelPath
    #2 = Class              #1            // os/RelPath
    #3 = Utf8               java/lang/Object
    #4 = Class              #3            // java/lang/Object
    #5 = Utf8               os/FilePath
    #6 = Class              #5            // os/FilePath
    #7 = Utf8               os/BasePathImpl
    #8 = Class              #7            // os/BasePathImpl
    #9 = Utf8               os/SegmentedPath
   #10 = Class              #9            // os/SegmentedPath
   #11 = Utf8               Path.scala
   #12 = Utf8               Lscala/reflect/ScalaSignature;
   #13 = Utf8               bytes
   #14 = Utf8               \u0006\u0005\u0005ud\u0001\u0002\u0010 \u0001\tB\u0001b\r\u0001\u0003\u0002\u0003\u0006I\u0001\u000e\u0005\t\u0005\u0002\u0011)\u0019!C\u0001\u0007\"Aq\t\u0001B\u0001B\u0003%A\t\u0003\u0004I\u0001\u0011\u0005q$\u0013\u0005\u0006\u001b\u0002!\tA\u0014\u0005\b%\u0002\u0011\r\u0011\"\u0001T\u0011\u0019i\u0006\u0001)A\u0005)\u0016!a\f\u0001\u0001K\u0011\u0019y\u0006\u0001)C\tA\")q\r\u0001C\u0001Q\")1\u000e\u0001C\u0001Y\")!\u000f\u0001C!g\")A\u000f\u0001C!k\")a\u000f\u0001C!o\")Q\u0010\u0001C\u0001}\"9\u00111\u0003\u0001\u0005\u0002\u0005U\u0001bBA\u000f\u0001\u0011\u0005\u0011qD\u0004\b\u0003_y\u0002\u0012AA\u0019\r\u0019qr\u0004#\u0001\u00024!1\u0001j\u0005C\u0001\u0003kAq!a\u000e\u0014\t\u0003\tI\u0004C\u0004\u00028M!\t!a\u0017\t\u0013\u0005\u00054C1A\u0005\u0004\u0005\r\u0004\u0002CA6\'\u0001\u0006I!!\u001a\t\u0013\u000554C1A\u0005\u0002\u0005=\u0004bBA9\'\u0001\u0006IA\u0013\u0005\n\u0003g\u001a\"\u0019!C\u0001\u0003_Bq!!\u001e\u0014A\u0003%!\nC\u0004\u0002xM!\u0019!!\u001f\u0003\u000fI+G\u000eU1uQ*\t\u0001%\u0001\u0002pg\u000e\u00011#\u0002\u0001$S5\u0002\u0004C\u0001\u0013(\u001b\u0005)#\"\u0001\u0014\u0002\u000bM\u001c\u0017\r\\1\n\u0005!*#AB!osJ+g\r\u0005\u0002+W5\tq$\u0003\u0002-?\tAa)\u001b7f!\u0006$\b\u000e\u0005\u0002+]%\u0011qf\b\u0002\r\u0005\u0006\u001cX\rU1uQ&k\u0007\u000f\u001c\t\u0003UEJ!AM\u0010\u0003\u001bM+w-\\3oi\u0016$\u0007+\u0019;i\u0003%\u0019XmZ7f]R\u001c\b\u0007E\u0002%k]J!AN\u0013\u0003\u000b\u0005\u0013(/Y=\u0011\u0005azdBA\u001d>!\tQT%D\u0001<\u0015\ta\u0014%\u0001\u0004=e>|GOP\u0005\u0003}\u0015\na\u0001\u0015:fI\u00164\u0017B\u0001!B\u0005\u0019\u0019FO]5oO*\u0011a(J\u0001\u0004kB\u001cX#\u0001#\u0011\u0005\u0011*\u0015B\u0001$&\u0005\rIe\u000e^\u0001\u0005kB\u001c\b%\u0001\u0004=S:LGO\u0010\u000b\u0004\u0015.c\u0005C\u0001\u0016\u0001\u0011\u0015\u0019D\u00011\u00015\u0011\u0015\u0011E\u00011\u0001E\u0003\u001da\u0017m\u001d;PaR,\u0012a\u0014\t\u0004IA;\u0014BA)&\u0005\u0019y\u0005\u000f^5p]\u0006A1/Z4nK:$8/F\u0001U!\r)&l\u000e\b\u0003-bs!AO,\n\u0003\u0019J!!W\u0013\u0002\u000fA\f7m[1hK&\u00111\f\u0018\u0002\u000b\u0013:$W\r_3e\'\u0016\f(BA-&\u0003%\u0019XmZ7f]R\u001c\bE\u0001\u0005UQ&\u001cH+\u001f9f\u0003\u0011i\u0017m[3\u0015\u0007)\u000bg\rC\u0003c\u0013\u0001\u00071-A\u0001q!\r)FmN\u0005\u0003Kr\u00131aU3r\u0011\u0015\u0011\u0015\u00021\u0001E\u0003)\u0011X\r\\1uSZ,Gk\u001c\u000b\u0003\u0015&DQA\u001b\u0006A\u0002)\u000bAAY1tK\u0006Q1\u000f^1siN<\u0016\u000e\u001e5\u0015\u00055\u0004\bC\u0001\u0013o\u0013\tyWEA\u0004C_>dW-\u00198\t\u000bE\\\u0001\u0019\u0001&\u0002\rQ\f\'oZ3u\u0003!!xn\u0015;sS:<G#A\u001c\u0002\u0011!\f7\u000f[\"pI\u0016$\u0012\u0001R\u0001\u0007KF,\u0018\r\\:\u0015\u00055D\b\"B=\u000f\u0001\u0004Q\u0018!A8\u0011\u0005\u0011Z\u0018B\u0001?&\u0005\r\te._\u0001\u0006i>t\u0015jT\u000b\u0002\u007fB!\u0011\u0011AA\b\u001b\t\t\u0019A\u0003\u0003\u0002\u0006\u0005\u001d\u0011\u0001\u00024jY\u0016TA!!\u0003\u0002\f\u0005\u0019a.[8\u000b\u0005\u00055\u0011\u0001\u00026bm\u0006LA!!\u0005\u0002\u0004\t!\u0001+\u0019;i\u0003%\t7oU;c!\u0006$\b.\u0006\u0002\u0002\u0018A\u0019!&!\u0007\n\u0007\u0005mqDA\u0004Tk\n\u0004\u0016\r\u001e5\u0002\u0017I,7o\u001c7wK\u001a\u0013x.\u001c\u000b\u0005\u0003C\t9\u0003\u0005\u0003\u0002$\u00055b\u0002BA\u0013\u0003Oa\u0001\u0001\u0003\u0004k#\u0001\u0007\u0011\u0011\u0006\t\u0004U\u0005-\u0012bAA\t?%\u0019a,a\u000b\u0002\u000fI+G\u000eU1uQB\u0011!fE\n\u0003\'\r\"\"!!\r\u0002\u000b\u0005\u0004\b\u000f\\=\u0016\t\u0005m\u00121\n\u000b\u0005\u0003{\t9\u0006F\u0002K\u0003\u007fA\u0011\"!\u0011\u0016\u0003\u0003\u0005\u001d!a\u0011\u0002\u0015\u00154\u0018\u000eZ3oG\u0016$#\u0007E\u0003+\u0003\u000b\nI%C\u0002\u0002H}\u0011q\u0002U1uQ\u000e{gN^3si&\u0014G.\u001a\t\u0005\u0003K\tY\u0005B\u0004\u0002NU\u0011\r!a\u0014\u0003\u0003Q\u000b2!!\u0015{!\r!\u00131K\u0005\u0004\u0003+*#a\u0002(pi\"Lgn\u001a\u0005\b\u00033*\u0002\u0019AA%\u0003\t1\u0007\u0007F\u0003K\u0003;\ny\u0006C\u00034-\u0001\u0007A\u000bC\u0003C-\u0001\u0007A)A\bsK2\u0004\u0016\r\u001e5Pe\u0012,\'/\u001b8h+\t\t)\u0007\u0005\u0003V\u0003OR\u0015bAA59\nAqJ\u001d3fe&tw-\u0001\tsK2\u0004\u0016\r\u001e5Pe\u0012,\'/\u001b8hA\u0005\u0011Q\u000f]\u000b\u0002\u0015\u0006\u0019Q\u000f\u001d\u0011\u0002\u0007I,G.\u0001\u0003sK2\u0004\u0013AC*vEJ+G\u000eU1uQR\u0019!*a\u001f\t\r\tl\u0002\u0019AA\f\u0001
   #15 = Utf8               java/lang/invoke/MethodHandles$Lookup
   #16 = Class              #15           // java/lang/invoke/MethodHandles$Lookup
   #17 = Utf8               java/lang/invoke/MethodHandles
   #18 = Class              #17           // java/lang/invoke/MethodHandles
   #19 = Utf8               Lookup
   #20 = Utf8               os/PathChunk$RelPathChunk
   #21 = Class              #20           // os/PathChunk$RelPathChunk
   #22 = Utf8               os/PathChunk
   #23 = Class              #22           // os/PathChunk
   #24 = Utf8               RelPathChunk
   #25 = Utf8               os/PathError$NoRelativePath
   #26 = Class              #25           // os/PathError$NoRelativePath
   #27 = Utf8               os/PathError
   #28 = Class              #27           // os/PathError
   #29 = Utf8               NoRelativePath
   #30 = Utf8               scala/collection/mutable/ArraySeq$ofRef
   #31 = Class              #30           // scala/collection/mutable/ArraySeq$ofRef
   #32 = Utf8               scala/collection/mutable/ArraySeq
   #33 = Class              #32           // scala/collection/mutable/ArraySeq
   #34 = Utf8               ofRef
   #35 = Utf8               segments0
   #36 = Utf8               [Ljava/lang/String;
   #37 = Utf8               ups
   #38 = Utf8               I
   #39 = Utf8               segments
   #40 = Utf8               Lscala/collection/immutable/IndexedSeq;
   #41 = Utf8               Lscala/collection/immutable/IndexedSeq<Ljava/lang/String;>;
   #42 = Utf8               SubRelPath
   #43 = Utf8               (Los/SubPath;)Los/RelPath;
   #44 = Utf8               p
   #45 = Utf8               os/RelPath$
   #46 = Class              #45           // os/RelPath$
   #47 = Utf8               MODULE$
   #48 = Utf8               Los/RelPath$;
   #49 = NameAndType        #47:#48       // MODULE$:Los/RelPath$;
   #50 = Fieldref           #46.#49       // os/RelPath$.MODULE$:Los/RelPath$;
   #51 = NameAndType        #42:#43       // SubRelPath:(Los/SubPath;)Los/RelPath;
   #52 = Methodref          #46.#51       // os/RelPath$.SubRelPath:(Los/SubPath;)Los/RelPath;
   #53 = Utf8               rel
   #54 = Utf8               ()Los/RelPath;
   #55 = NameAndType        #53:#54       // rel:()Los/RelPath;
   #56 = Methodref          #46.#55       // os/RelPath$.rel:()Los/RelPath;
   #57 = Utf8               up
   #58 = NameAndType        #57:#54       // up:()Los/RelPath;
   #59 = Methodref          #46.#58       // os/RelPath$.up:()Los/RelPath;
   #60 = Utf8               relPathOrdering
   #61 = Utf8               ()Lscala/math/Ordering;
   #62 = Utf8               ()Lscala/math/Ordering<Los/RelPath;>;
   #63 = NameAndType        #60:#61       // relPathOrdering:()Lscala/math/Ordering;
   #64 = Methodref          #46.#63       // os/RelPath$.relPathOrdering:()Lscala/math/Ordering;
   #65 = Utf8               apply
   #66 = Utf8               (Lscala/collection/immutable/IndexedSeq;I)Los/RelPath;
   #67 = Utf8               (Lscala/collection/immutable/IndexedSeq<Ljava/lang/String;>;I)Los/RelPath;
   #68 = NameAndType        #65:#66       // apply:(Lscala/collection/immutable/IndexedSeq;I)Los/RelPath;
   #69 = Methodref          #46.#68       // os/RelPath$.apply:(Lscala/collection/immutable/IndexedSeq;I)Los/RelPath;
   #70 = Utf8               (Ljava/lang/Object;Los/PathConvertible;)Los/RelPath;
   #71 = Utf8               <T:Ljava/lang/Object;>(TT;Los/PathConvertible<TT;>;)Los/RelPath;
   #72 = Utf8               f0
   #73 = Utf8               evidence$2
   #74 = NameAndType        #65:#70       // apply:(Ljava/lang/Object;Los/PathConvertible;)Los/RelPath;
   #75 = Methodref          #46.#74       // os/RelPath$.apply:(Ljava/lang/Object;Los/PathConvertible;)Los/RelPath;
   #76 = Utf8               $div
   #77 = Utf8               (Los/PathChunk;)Los/BasePath;
   #78 = Utf8               chunk
   #79 = Utf8               $div$
   #80 = Utf8               (Los/SegmentedPath;Los/PathChunk;)Los/BasePath;
   #81 = NameAndType        #79:#80       // $div$:(Los/SegmentedPath;Los/PathChunk;)Los/BasePath;
   #82 = InterfaceMethodref #10.#81       // os/SegmentedPath.$div$:(Los/SegmentedPath;Los/PathChunk;)Los/BasePath;
   #83 = Utf8               this
   #84 = Utf8               Los/RelPath;
   #85 = Utf8               Los/PathChunk;
   #86 = Utf8               endsWith
   #87 = Utf8               (Los/RelPath;)Z
   #88 = Utf8               target
   #89 = Utf8               endsWith$
   #90 = Utf8               (Los/SegmentedPath;Los/RelPath;)Z
   #91 = NameAndType        #89:#90       // endsWith$:(Los/SegmentedPath;Los/RelPath;)Z
   #92 = InterfaceMethodref #10.#91       // os/SegmentedPath.endsWith$:(Los/SegmentedPath;Los/RelPath;)Z
   #93 = Utf8               ext
   #94 = Utf8               ()Ljava/lang/String;
   #95 = Utf8               ext$
   #96 = Utf8               (Los/BasePathImpl;)Ljava/lang/String;
   #97 = NameAndType        #95:#96       // ext$:(Los/BasePathImpl;)Ljava/lang/String;
   #98 = InterfaceMethodref #8.#97        // os/BasePathImpl.ext$:(Los/BasePathImpl;)Ljava/lang/String;
   #99 = Utf8               baseName
  #100 = Utf8               baseName$
  #101 = NameAndType        #100:#96      // baseName$:(Los/BasePathImpl;)Ljava/lang/String;
  #102 = InterfaceMethodref #8.#101       // os/BasePathImpl.baseName$:(Los/BasePathImpl;)Ljava/lang/String;
  #103 = Utf8               last
  #104 = Utf8               last$
  #105 = NameAndType        #104:#96      // last$:(Los/BasePathImpl;)Ljava/lang/String;
  #106 = InterfaceMethodref #8.#105       // os/BasePathImpl.last$:(Los/BasePathImpl;)Ljava/lang/String;
  #107 = Utf8               subRelativeTo
  #108 = Utf8               (Los/BasePath;)Los/SubPath;
  #109 = Utf8               os/BasePath
  #110 = Class              #109          // os/BasePath
  #111 = Utf8               subRelativeTo$
  #112 = Utf8               (Los/BasePath;Los/BasePath;)Los/SubPath;
  #113 = NameAndType        #111:#112     // subRelativeTo$:(Los/BasePath;Los/BasePath;)Los/SubPath;
  #114 = InterfaceMethodref #110.#113     // os/BasePath.subRelativeTo$:(Los/BasePath;Los/BasePath;)Los/SubPath;
  #115 = Utf8               Los/BasePath;
  #116 = Utf8               ()I
  #117 = NameAndType        #37:#38       // ups:I
  #118 = Fieldref           #2.#117       // os/RelPath.ups:I
  #119 = Utf8               lastOpt
  #120 = Utf8               ()Lscala/Option;
  #121 = Utf8               ()Lscala/Option<Ljava/lang/String;>;
  #122 = Utf8               ()Lscala/collection/immutable/IndexedSeq;
  #123 = NameAndType        #39:#122      // segments:()Lscala/collection/immutable/IndexedSeq;
  #124 = Methodref          #2.#123       // os/RelPath.segments:()Lscala/collection/immutable/IndexedSeq;
  #125 = Utf8               scala/collection/immutable/IndexedSeq
  #126 = Class              #125          // scala/collection/immutable/IndexedSeq
  #127 = Utf8               lastOption
  #128 = NameAndType        #127:#120     // lastOption:()Lscala/Option;
  #129 = InterfaceMethodref #126.#128     // scala/collection/immutable/IndexedSeq.lastOption:()Lscala/Option;
  #130 = Utf8               ()Lscala/collection/immutable/IndexedSeq<Ljava/lang/String;>;
  #131 = NameAndType        #39:#40       // segments:Lscala/collection/immutable/IndexedSeq;
  #132 = Fieldref           #2.#131       // os/RelPath.segments:Lscala/collection/immutable/IndexedSeq;
  #133 = Utf8               make
  #134 = Utf8               (Lscala/collection/immutable/Seq;I)Los/RelPath;
  #135 = Utf8               (Lscala/collection/immutable/Seq<Ljava/lang/String;>;I)Los/RelPath;
  #136 = Utf8               scala/reflect/ClassTag$
  #137 = Class              #136          // scala/reflect/ClassTag$
  #138 = Utf8               Lscala/reflect/ClassTag$;
  #139 = NameAndType        #47:#138      // MODULE$:Lscala/reflect/ClassTag$;
  #140 = Fieldref           #137.#139     // scala/reflect/ClassTag$.MODULE$:Lscala/reflect/ClassTag$;
  #141 = Utf8               java/lang/String
  #142 = Class              #141          // java/lang/String
  #143 = Utf8               (Ljava/lang/Class;)Lscala/reflect/ClassTag;
  #144 = NameAndType        #65:#143      // apply:(Ljava/lang/Class;)Lscala/reflect/ClassTag;
  #145 = Methodref          #137.#144     // scala/reflect/ClassTag$.apply:(Ljava/lang/Class;)Lscala/reflect/ClassTag;
  #146 = Utf8               scala/collection/immutable/Seq
  #147 = Class              #146          // scala/collection/immutable/Seq
  #148 = Utf8               toArray
  #149 = Utf8               (Lscala/reflect/ClassTag;)Ljava/lang/Object;
  #150 = NameAndType        #148:#149     // toArray:(Lscala/reflect/ClassTag;)Ljava/lang/Object;
  #151 = InterfaceMethodref #147.#150     // scala/collection/immutable/Seq.toArray:(Lscala/reflect/ClassTag;)Ljava/lang/Object;
  #152 = Class              #36           // "[Ljava/lang/String;"
  #153 = NameAndType        #37:#116      // ups:()I
  #154 = Methodref          #2.#153       // os/RelPath.ups:()I
  #155 = Utf8               <init>
  #156 = Utf8               ([Ljava/lang/String;I)V
  #157 = NameAndType        #155:#156     // "<init>":([Ljava/lang/String;I)V
  #158 = Methodref          #2.#157       // os/RelPath."<init>":([Ljava/lang/String;I)V
  #159 = Utf8               Lscala/collection/immutable/Seq;
  #160 = Utf8               relativeTo
  #161 = Utf8               (Los/RelPath;)Los/RelPath;
  #162 = Utf8               base
  #163 = NameAndType        #35:#36       // segments0:[Ljava/lang/String;
  #164 = Fieldref           #2.#163       // os/RelPath.segments0:[Ljava/lang/String;
  #165 = Utf8               length
  #166 = NameAndType        #165:#116     // length:()I
  #167 = InterfaceMethodref #126.#166     // scala/collection/immutable/IndexedSeq.length:()I
  #168 = Utf8               os/SubPath$
  #169 = Class              #168          // os/SubPath$
  #170 = Utf8               Los/SubPath$;
  #171 = NameAndType        #47:#170      // MODULE$:Los/SubPath$;
  #172 = Fieldref           #169.#171     // os/SubPath$.MODULE$:Los/SubPath$;
  #173 = Utf8               relativeTo0
  #174 = Utf8               ([Ljava/lang/String;Lscala/collection/immutable/IndexedSeq;)Los/RelPath;
  #175 = NameAndType        #173:#174     // relativeTo0:([Ljava/lang/String;Lscala/collection/immutable/IndexedSeq;)Los/RelPath;
  #176 = Methodref          #169.#175     // os/SubPath$.relativeTo0:([Ljava/lang/String;Lscala/collection/immutable/IndexedSeq;)Los/RelPath;
  #177 = Utf8               (Los/RelPath;Los/RelPath;)V
  #178 = NameAndType        #155:#177     // "<init>":(Los/RelPath;Los/RelPath;)V
  #179 = Methodref          #26.#178      // os/PathError$NoRelativePath."<init>":(Los/RelPath;Los/RelPath;)V
  #180 = Utf8               startsWith
  #181 = Utf8               scala/Predef$
  #182 = Class              #181          // scala/Predef$
  #183 = Utf8               Lscala/Predef$;
  #184 = NameAndType        #47:#183      // MODULE$:Lscala/Predef$;
  #185 = Fieldref           #182.#184     // scala/Predef$.MODULE$:Lscala/Predef$;
  #186 = Utf8               [Ljava/lang/Object;
  #187 = Class              #186          // "[Ljava/lang/Object;"
  #188 = Utf8               refArrayOps
  #189 = Utf8               ([Ljava/lang/Object;)Ljava/lang/Object;
  #190 = NameAndType        #188:#189     // refArrayOps:([Ljava/lang/Object;)Ljava/lang/Object;
  #191 = Methodref          #182.#190     // scala/Predef$.refArrayOps:([Ljava/lang/Object;)Ljava/lang/Object;
  #192 = Utf8               scala/collection/ArrayOps$
  #193 = Class              #192          // scala/collection/ArrayOps$
  #194 = Utf8               Lscala/collection/ArrayOps$;
  #195 = NameAndType        #47:#194      // MODULE$:Lscala/collection/ArrayOps$;
  #196 = Fieldref           #193.#195     // scala/collection/ArrayOps$.MODULE$:Lscala/collection/ArrayOps$;
  #197 = Utf8               startsWith$default$2$extension
  #198 = Utf8               (Ljava/lang/Object;)I
  #199 = NameAndType        #197:#198     // startsWith$default$2$extension:(Ljava/lang/Object;)I
  #200 = Methodref          #193.#199     // scala/collection/ArrayOps$.startsWith$default$2$extension:(Ljava/lang/Object;)I
  #201 = Utf8               startsWith$extension
  #202 = Utf8               (Ljava/lang/Object;Lscala/collection/IterableOnce;I)Z
  #203 = NameAndType        #201:#202     // startsWith$extension:(Ljava/lang/Object;Lscala/collection/IterableOnce;I)Z
  #204 = Methodref          #193.#203     // scala/collection/ArrayOps$.startsWith$extension:(Ljava/lang/Object;Lscala/collection/IterableOnce;I)Z
  #205 = Utf8               qual$1
  #206 = Utf8               Ljava/lang/Object;
  #207 = Utf8               x$1
  #208 = Utf8               x$2
  #209 = Utf8               toString
  #210 = Utf8               scala/package$
  #211 = Class              #210          // scala/package$
  #212 = Utf8               Lscala/package$;
  #213 = NameAndType        #47:#212      // MODULE$:Lscala/package$;
  #214 = Fieldref           #211.#213     // scala/package$.MODULE$:Lscala/package$;
  #215 = Utf8               Seq
  #216 = Utf8               ()Lscala/collection/immutable/Seq$;
  #217 = NameAndType        #215:#216     // Seq:()Lscala/collection/immutable/Seq$;
  #218 = Methodref          #211.#217     // scala/package$.Seq:()Lscala/collection/immutable/Seq$;
  #219 = Utf8               ()Ljava/lang/Object;
  #220 = MethodType         #219          //  ()Ljava/lang/Object;
  #221 = Utf8               $anonfun$toString$1
  #222 = NameAndType        #221:#94      // $anonfun$toString$1:()Ljava/lang/String;
  #223 = Methodref          #2.#222       // os/RelPath.$anonfun$toString$1:()Ljava/lang/String;
  #224 = MethodHandle       6:#223        // REF_invokeStatic os/RelPath.$anonfun$toString$1:()Ljava/lang/String;
  #225 = MethodType         #94           //  ()Ljava/lang/String;
  #226 = Integer            5
  #227 = Integer            1
  #228 = Utf8               java/lang/invoke/LambdaMetafactory
  #229 = Class              #228          // java/lang/invoke/LambdaMetafactory
  #230 = Utf8               altMetafactory
  #231 = Utf8               (Ljava/lang/invoke/MethodHandles$Lookup;Ljava/lang/String;Ljava/lang/invoke/MethodType;[Ljava/lang/Object;)Ljava/lang/invoke/CallSite;
  #232 = NameAndType        #230:#231     // altMetafactory:(Ljava/lang/invoke/MethodHandles$Lookup;Ljava/lang/String;Ljava/lang/invoke/MethodType;[Ljava/lang/Object;)Ljava/lang/invoke/CallSite;
  #233 = Methodref          #229.#232     // java/lang/invoke/LambdaMetafactory.altMetafactory:(Ljava/lang/invoke/MethodHandles$Lookup;Ljava/lang/String;Ljava/lang/invoke/MethodType;[Ljava/lang/Object;)Ljava/lang/invoke/CallSite;
  #234 = MethodHandle       6:#233        // REF_invokeStatic java/lang/invoke/LambdaMetafactory.altMetafactory:(Ljava/lang/invoke/MethodHandles$Lookup;Ljava/lang/String;Ljava/lang/invoke/MethodType;[Ljava/lang/Object;)Ljava/lang/invoke/CallSite;
  #235 = Utf8               ()Lscala/Function0;
  #236 = NameAndType        #65:#235      // apply:()Lscala/Function0;
  #237 = InvokeDynamic      #0:#236       // #0:apply:()Lscala/Function0;
  #238 = Utf8               scala/collection/immutable/Seq$
  #239 = Class              #238          // scala/collection/immutable/Seq$
  #240 = Utf8               fill
  #241 = Utf8               (ILscala/Function0;)Ljava/lang/Object;
  #242 = NameAndType        #240:#241     // fill:(ILscala/Function0;)Ljava/lang/Object;
  #243 = Methodref          #239.#242     // scala/collection/immutable/Seq$.fill:(ILscala/Function0;)Ljava/lang/Object;
  #244 = Utf8               scala/collection/IterableOps
  #245 = Class              #244          // scala/collection/IterableOps
  #246 = Utf8               wrapRefArray
  #247 = Utf8               ([Ljava/lang/Object;)Lscala/collection/mutable/ArraySeq$ofRef;
  #248 = NameAndType        #246:#247     // wrapRefArray:([Ljava/lang/Object;)Lscala/collection/mutable/ArraySeq$ofRef;
  #249 = Methodref          #182.#248     // scala/Predef$.wrapRefArray:([Ljava/lang/Object;)Lscala/collection/mutable/ArraySeq$ofRef;
  #250 = Utf8               $plus$plus
  #251 = Utf8               (Lscala/collection/IterableOnce;)Ljava/lang/Object;
  #252 = NameAndType        #250:#251     // $plus$plus:(Lscala/collection/IterableOnce;)Ljava/lang/Object;
  #253 = InterfaceMethodref #245.#252     // scala/collection/IterableOps.$plus$plus:(Lscala/collection/IterableOnce;)Ljava/lang/Object;
  #254 = Utf8               scala/collection/IterableOnceOps
  #255 = Class              #254          // scala/collection/IterableOnceOps
  #256 = Utf8               /
  #257 = String             #256          // /
  #258 = Utf8               mkString
  #259 = Utf8               (Ljava/lang/String;)Ljava/lang/String;
  #260 = NameAndType        #258:#259     // mkString:(Ljava/lang/String;)Ljava/lang/String;
  #261 = InterfaceMethodref #255.#260     // scala/collection/IterableOnceOps.mkString:(Ljava/lang/String;)Ljava/lang/String;
  #262 = Utf8               hashCode
  #263 = Utf8               scala/collection/Seq
  #264 = Class              #263          // scala/collection/Seq
  #265 = NameAndType        #262:#116     // hashCode:()I
  #266 = InterfaceMethodref #264.#265     // scala/collection/Seq.hashCode:()I
  #267 = Utf8               scala/runtime/BoxesRunTime
  #268 = Class              #267          // scala/runtime/BoxesRunTime
  #269 = Utf8               boxToInteger
  #270 = Utf8               (I)Ljava/lang/Integer;
  #271 = NameAndType        #269:#270     // boxToInteger:(I)Ljava/lang/Integer;
  #272 = Methodref          #268.#271     // scala/runtime/BoxesRunTime.boxToInteger:(I)Ljava/lang/Integer;
  #273 = Methodref          #4.#265       // java/lang/Object.hashCode:()I
  #274 = Utf8               equals
  #275 = Utf8               (Ljava/lang/Object;)Z
  #276 = Utf8               o
  #277 = NameAndType        #274:#275     // equals:(Ljava/lang/Object;)Z
  #278 = Methodref          #4.#277       // java/lang/Object.equals:(Ljava/lang/Object;)Z
  #279 = Utf8               os/SubPath
  #280 = Class              #279          // os/SubPath
  #281 = Methodref          #280.#123     // os/SubPath.segments:()Lscala/collection/immutable/IndexedSeq;
  #282 = Utf8               toNIO
  #283 = Utf8               ()Ljava/nio/file/Path;
  #284 = NameAndType        #209:#94      // toString:()Ljava/lang/String;
  #285 = Methodref          #2.#284       // os/RelPath.toString:()Ljava/lang/String;
  #286 = Utf8               java/nio/file/Paths
  #287 = Class              #286          // java/nio/file/Paths
  #288 = Utf8               get
  #289 = Utf8               (Ljava/lang/String;[Ljava/lang/String;)Ljava/nio/file/Path;
  #290 = NameAndType        #288:#289     // get:(Ljava/lang/String;[Ljava/lang/String;)Ljava/nio/file/Path;
  #291 = Methodref          #287.#290     // java/nio/file/Paths.get:(Ljava/lang/String;[Ljava/lang/String;)Ljava/nio/file/Path;
  #292 = Utf8               asSubPath
  #293 = Utf8               ()Los/SubPath;
  #294 = Utf8               require
  #295 = Utf8               (Z)V
  #296 = NameAndType        #294:#295     // require:(Z)V
  #297 = Methodref          #182.#296     // scala/Predef$.require:(Z)V
  #298 = Utf8               ([Ljava/lang/String;)V
  #299 = NameAndType        #155:#298     // "<init>":([Ljava/lang/String;)V
  #300 = Methodref          #280.#299     // os/SubPath."<init>":([Ljava/lang/String;)V
  #301 = Utf8               resolveFrom
  #302 = Utf8               (Los/Path;)Los/Path;
  #303 = Utf8               os/PathChunk$
  #304 = Class              #303          // os/PathChunk$
  #305 = Utf8               Los/PathChunk$;
  #306 = NameAndType        #47:#305      // MODULE$:Los/PathChunk$;
  #307 = Fieldref           #304.#306     // os/PathChunk$.MODULE$:Los/PathChunk$;
  #308 = Utf8               (Los/RelPath;)Los/PathChunk$RelPathChunk;
  #309 = NameAndType        #24:#308      // RelPathChunk:(Los/RelPath;)Los/PathChunk$RelPathChunk;
  #310 = Methodref          #304.#309     // os/PathChunk$.RelPathChunk:(Los/RelPath;)Los/PathChunk$RelPathChunk;
  #311 = Utf8               os/Path
  #312 = Class              #311          // os/Path
  #313 = Utf8               (Los/PathChunk;)Los/Path;
  #314 = NameAndType        #76:#313      // $div:(Los/PathChunk;)Los/Path;
  #315 = Methodref          #312.#314     // os/Path.$div:(Los/PathChunk;)Los/Path;
  #316 = Utf8               Los/Path;
  #317 = Utf8               (Los/BasePath;)Z
  #318 = NameAndType        #180:#87      // startsWith:(Los/RelPath;)Z
  #319 = Methodref          #2.#318       // os/RelPath.startsWith:(Los/RelPath;)Z
  #320 = Utf8               (Los/BasePath;)Los/RelPath;
  #321 = NameAndType        #160:#161     // relativeTo:(Los/RelPath;)Los/RelPath;
  #322 = Methodref          #2.#321       // os/RelPath.relativeTo:(Los/RelPath;)Los/RelPath;
  #323 = Utf8               (Lscala/collection/immutable/Seq;I)Los/BasePath;
  #324 = NameAndType        #133:#134     // make:(Lscala/collection/immutable/Seq;I)Los/RelPath;
  #325 = Methodref          #2.#324       // os/RelPath.make:(Lscala/collection/immutable/Seq;I)Los/RelPath;
  #326 = Utf8               ()Lscala/collection/IterableOnce;
  #327 = Utf8               ..
  #328 = String             #327          // ..
  #329 = Utf8               ()V
  #330 = NameAndType        #155:#329     // "<init>":()V
  #331 = Methodref          #4.#330       // java/lang/Object."<init>":()V
  #332 = Utf8               $init$
  #333 = Utf8               (Los/BasePath;)V
  #334 = NameAndType        #332:#333     // $init$:(Los/BasePath;)V
  #335 = InterfaceMethodref #110.#334     // os/BasePath.$init$:(Los/BasePath;)V
  #336 = Utf8               (Los/BasePathImpl;)V
  #337 = NameAndType        #332:#336     // $init$:(Los/BasePathImpl;)V
  #338 = InterfaceMethodref #8.#337       // os/BasePathImpl.$init$:(Los/BasePathImpl;)V
  #339 = Utf8               (Los/SegmentedPath;)V
  #340 = NameAndType        #332:#339     // $init$:(Los/SegmentedPath;)V
  #341 = InterfaceMethodref #10.#340      // os/SegmentedPath.$init$:(Los/SegmentedPath;)V
  #342 = Utf8               copyArrayToImmutableIndexedSeq
  #343 = Utf8               (Ljava/lang/Object;)Lscala/collection/immutable/IndexedSeq;
  #344 = NameAndType        #342:#343     // copyArrayToImmutableIndexedSeq:(Ljava/lang/Object;)Lscala/collection/immutable/IndexedSeq;
  #345 = Methodref          #182.#344     // scala/Predef$.copyArrayToImmutableIndexedSeq:(Ljava/lang/Object;)Lscala/collection/immutable/IndexedSeq;
  #346 = Utf8               $deserializeLambda$
  #347 = Utf8               (Ljava/lang/invoke/SerializedLambda;)Ljava/lang/Object;
  #348 = Utf8               scala/runtime/LambdaDeserialize
  #349 = Class              #348          // scala/runtime/LambdaDeserialize
  #350 = Utf8               bootstrap
  #351 = Utf8               (Ljava/lang/invoke/MethodHandles$Lookup;Ljava/lang/String;Ljava/lang/invoke/MethodType;[Ljava/lang/invoke/MethodHandle;)Ljava/lang/invoke/CallSite;
  #352 = NameAndType        #350:#351     // bootstrap:(Ljava/lang/invoke/MethodHandles$Lookup;Ljava/lang/String;Ljava/lang/invoke/MethodType;[Ljava/lang/invoke/MethodHandle;)Ljava/lang/invoke/CallSite;
  #353 = Methodref          #349.#352     // scala/runtime/LambdaDeserialize.bootstrap:(Ljava/lang/invoke/MethodHandles$Lookup;Ljava/lang/String;Ljava/lang/invoke/MethodType;[Ljava/lang/invoke/MethodHandle;)Ljava/lang/invoke/CallSite;
  #354 = MethodHandle       6:#353        // REF_invokeStatic scala/runtime/LambdaDeserialize.bootstrap:(Ljava/lang/invoke/MethodHandles$Lookup;Ljava/lang/String;Ljava/lang/invoke/MethodType;[Ljava/lang/invoke/MethodHandle;)Ljava/lang/invoke/CallSite;
  #355 = Utf8               lambdaDeserialize
  #356 = NameAndType        #355:#347     // lambdaDeserialize:(Ljava/lang/invoke/SerializedLambda;)Ljava/lang/Object;
  #357 = InvokeDynamic      #1:#356       // #1:lambdaDeserialize:(Ljava/lang/invoke/SerializedLambda;)Ljava/lang/Object;
  #358 = Utf8               Signature
  #359 = Utf8               Code
  #360 = Utf8               MethodParameters
  #361 = Utf8               LineNumberTable
  #362 = Utf8               LocalVariableTable
  #363 = Utf8               StackMapTable
  #364 = Utf8               InnerClasses
  #365 = Utf8               SourceFile
  #366 = Utf8               RuntimeVisibleAnnotations
  #367 = Utf8               BootstrapMethods
  #368 = Utf8               ScalaInlineInfo
  #369 = Utf8               ScalaSig
{
  private final java.lang.String[] segments0;
    descriptor: [Ljava/lang/String;
    flags: (0x0012) ACC_PRIVATE, ACC_FINAL

  private final int ups;
    descriptor: I
    flags: (0x0012) ACC_PRIVATE, ACC_FINAL

  private final scala.collection.immutable.IndexedSeq<java.lang.String> segments;
    descriptor: Lscala/collection/immutable/IndexedSeq;
    flags: (0x0012) ACC_PRIVATE, ACC_FINAL
    Signature: #41                          // Lscala/collection/immutable/IndexedSeq<Ljava/lang/String;>;

  public static os.RelPath SubRelPath(os.SubPath);
    descriptor: (Los/SubPath;)Los/RelPath;
    flags: (0x0009) ACC_PUBLIC, ACC_STATIC
    Code:
      stack=2, locals=1, args_size=1
         0: getstatic     #50                 // Field os/RelPath$.MODULE$:Los/RelPath$;
         3: aload_0
         4: invokevirtual #52                 // Method os/RelPath$.SubRelPath:(Los/SubPath;)Los/RelPath;
         7: areturn
    MethodParameters:
      Name                           Flags
      p                              final

  public static os.RelPath rel();
    descriptor: ()Los/RelPath;
    flags: (0x0009) ACC_PUBLIC, ACC_STATIC
    Code:
      stack=1, locals=0, args_size=0
         0: getstatic     #50                 // Field os/RelPath$.MODULE$:Los/RelPath$;
         3: invokevirtual #56                 // Method os/RelPath$.rel:()Los/RelPath;
         6: areturn

  public static os.RelPath up();
    descriptor: ()Los/RelPath;
    flags: (0x0009) ACC_PUBLIC, ACC_STATIC
    Code:
      stack=1, locals=0, args_size=0
         0: getstatic     #50                 // Field os/RelPath$.MODULE$:Los/RelPath$;
         3: invokevirtual #59                 // Method os/RelPath$.up:()Los/RelPath;
         6: areturn

  public static scala.math.Ordering<os.RelPath> relPathOrdering();
    descriptor: ()Lscala/math/Ordering;
    flags: (0x0009) ACC_PUBLIC, ACC_STATIC
    Code:
      stack=1, locals=0, args_size=0
         0: getstatic     #50                 // Field os/RelPath$.MODULE$:Los/RelPath$;
         3: invokevirtual #64                 // Method os/RelPath$.relPathOrdering:()Lscala/math/Ordering;
         6: areturn
    Signature: #62                          // ()Lscala/math/Ordering<Los/RelPath;>;

  public static os.RelPath apply(scala.collection.immutable.IndexedSeq<java.lang.String>, int);
    descriptor: (Lscala/collection/immutable/IndexedSeq;I)Los/RelPath;
    flags: (0x0009) ACC_PUBLIC, ACC_STATIC
    Code:
      stack=3, locals=2, args_size=2
         0: getstatic     #50                 // Field os/RelPath$.MODULE$:Los/RelPath$;
         3: aload_0
         4: iload_1
         5: invokevirtual #69                 // Method os/RelPath$.apply:(Lscala/collection/immutable/IndexedSeq;I)Los/RelPath;
         8: areturn
    Signature: #67                          // (Lscala/collection/immutable/IndexedSeq<Ljava/lang/String;>;I)Los/RelPath;
    MethodParameters:
      Name                           Flags
      segments0                      final
      ups                            final

  public static <T extends java.lang.Object> os.RelPath apply(T, os.PathConvertible<T>);
    descriptor: (Ljava/lang/Object;Los/PathConvertible;)Los/RelPath;
    flags: (0x0009) ACC_PUBLIC, ACC_STATIC
    Code:
      stack=3, locals=2, args_size=2
         0: getstatic     #50                 // Field os/RelPath$.MODULE$:Los/RelPath$;
         3: aload_0
         4: aload_1
         5: invokevirtual #75                 // Method os/RelPath$.apply:(Ljava/lang/Object;Los/PathConvertible;)Los/RelPath;
         8: areturn
    Signature: #71                          // <T:Ljava/lang/Object;>(TT;Los/PathConvertible<TT;>;)Los/RelPath;
    MethodParameters:
      Name                           Flags
      f0                             final
      evidence$2                     final

  public os.BasePath $div(os.PathChunk);
    descriptor: (Los/PathChunk;)Los/BasePath;
    flags: (0x0001) ACC_PUBLIC
    Code:
      stack=2, locals=2, args_size=2
         0: aload_0
         1: aload_1
         2: invokestatic  #82                 // InterfaceMethod os/SegmentedPath.$div$:(Los/SegmentedPath;Los/PathChunk;)Los/BasePath;
         5: areturn
      LineNumberTable:
        line 250: 0
      LocalVariableTable:
        Start  Length  Slot  Name   Signature
            0       6     0  this   Los/RelPath;
            0       6     1 chunk   Los/PathChunk;
    MethodParameters:
      Name                           Flags
      chunk                          final

  public boolean endsWith(os.RelPath);
    descriptor: (Los/RelPath;)Z
    flags: (0x0001) ACC_PUBLIC
    Code:
      stack=2, locals=2, args_size=2
         0: aload_0
         1: aload_1
         2: invokestatic  #92                 // InterfaceMethod os/SegmentedPath.endsWith$:(Los/SegmentedPath;Los/RelPath;)Z
         5: ireturn
      LineNumberTable:
        line 250: 0
      LocalVariableTable:
        Start  Length  Slot  Name   Signature
            0       6     0  this   Los/RelPath;
            0       6     1 target   Los/RelPath;
    MethodParameters:
      Name                           Flags
      target                         final

  public java.lang.String ext();
    descriptor: ()Ljava/lang/String;
    flags: (0x0001) ACC_PUBLIC
    Code:
      stack=1, locals=1, args_size=1
         0: aload_0
         1: invokestatic  #98                 // InterfaceMethod os/BasePathImpl.ext$:(Los/BasePathImpl;)Ljava/lang/String;
         4: areturn
      LineNumberTable:
        line 250: 0
      LocalVariableTable:
        Start  Length  Slot  Name   Signature
            0       5     0  this   Los/RelPath;

  public java.lang.String baseName();
    descriptor: ()Ljava/lang/String;
    flags: (0x0001) ACC_PUBLIC
    Code:
      stack=1, locals=1, args_size=1
         0: aload_0
         1: invokestatic  #102                // InterfaceMethod os/BasePathImpl.baseName$:(Los/BasePathImpl;)Ljava/lang/String;
         4: areturn
      LineNumberTable:
        line 250: 0
      LocalVariableTable:
        Start  Length  Slot  Name   Signature
            0       5     0  this   Los/RelPath;

  public java.lang.String last();
    descriptor: ()Ljava/lang/String;
    flags: (0x0001) ACC_PUBLIC
    Code:
      stack=1, locals=1, args_size=1
         0: aload_0
         1: invokestatic  #106                // InterfaceMethod os/BasePathImpl.last$:(Los/BasePathImpl;)Ljava/lang/String;
         4: areturn
      LineNumberTable:
        line 250: 0
      LocalVariableTable:
        Start  Length  Slot  Name   Signature
            0       5     0  this   Los/RelPath;

  public os.SubPath subRelativeTo(os.BasePath);
    descriptor: (Los/BasePath;)Los/SubPath;
    flags: (0x0001) ACC_PUBLIC
    Code:
      stack=2, locals=2, args_size=2
         0: aload_0
         1: aload_1
         2: invokestatic  #114                // InterfaceMethod os/BasePath.subRelativeTo$:(Los/BasePath;Los/BasePath;)Los/SubPath;
         5: areturn
      LineNumberTable:
        line 250: 0
      LocalVariableTable:
        Start  Length  Slot  Name   Signature
            0       6     0  this   Los/RelPath;
            0       6     1 target   Los/BasePath;
    MethodParameters:
      Name                           Flags
      target                         final

  public int ups();
    descriptor: ()I
    flags: (0x0001) ACC_PUBLIC
    Code:
      stack=1, locals=1, args_size=1
         0: aload_0
         1: getfield      #118                // Field ups:I
         4: ireturn
      LineNumberTable:
        line 250: 0
      LocalVariableTable:
        Start  Length  Slot  Name   Signature
            0       5     0  this   Los/RelPath;

  public scala.Option<java.lang.String> lastOpt();
    descriptor: ()Lscala/Option;
    flags: (0x0001) ACC_PUBLIC
    Code:
      stack=1, locals=1, args_size=1
         0: aload_0
         1: invokevirtual #124                // Method segments:()Lscala/collection/immutable/IndexedSeq;
         4: invokeinterface #129,  1          // InterfaceMethod scala/collection/immutable/IndexedSeq.lastOption:()Lscala/Option;
         9: areturn
      LineNumberTable:
        line 252: 0
      LocalVariableTable:
        Start  Length  Slot  Name   Signature
            0      10     0  this   Los/RelPath;
    Signature: #121                         // ()Lscala/Option<Ljava/lang/String;>;

  public scala.collection.immutable.IndexedSeq<java.lang.String> segments();
    descriptor: ()Lscala/collection/immutable/IndexedSeq;
    flags: (0x0001) ACC_PUBLIC
    Code:
      stack=1, locals=1, args_size=1
         0: aload_0
         1: getfield      #132                // Field segments:Lscala/collection/immutable/IndexedSeq;
         4: areturn
      LineNumberTable:
        line 253: 0
      LocalVariableTable:
        Start  Length  Slot  Name   Signature
            0       5     0  this   Los/RelPath;
    Signature: #130                         // ()Lscala/collection/immutable/IndexedSeq<Ljava/lang/String;>;

  public os.RelPath make(scala.collection.immutable.Seq<java.lang.String>, int);
    descriptor: (Lscala/collection/immutable/Seq;I)Los/RelPath;
    flags: (0x0001) ACC_PUBLIC
    Code:
      stack=5, locals=3, args_size=3
         0: new           #2                  // class os/RelPath
         3: dup
         4: aload_1
         5: getstatic     #140                // Field scala/reflect/ClassTag$.MODULE$:Lscala/reflect/ClassTag$;
         8: ldc           #142                // class java/lang/String
        10: invokevirtual #145                // Method scala/reflect/ClassTag$.apply:(Ljava/lang/Class;)Lscala/reflect/ClassTag;
        13: invokeinterface #151,  2          // InterfaceMethod scala/collection/immutable/Seq.toArray:(Lscala/reflect/ClassTag;)Ljava/lang/Object;
        18: checkcast     #152                // class "[Ljava/lang/String;"
        21: iload_2
        22: aload_0
        23: invokevirtual #154                // Method ups:()I
        26: iadd
        27: invokespecial #158                // Method "<init>":([Ljava/lang/String;I)V
        30: areturn
      LineNumberTable:
        line 257: 0
      LocalVariableTable:
        Start  Length  Slot  Name   Signature
            0      31     0  this   Los/RelPath;
            0      31     1     p   Lscala/collection/immutable/Seq;
            0      31     2   ups   I
    Signature: #135                         // (Lscala/collection/immutable/Seq<Ljava/lang/String;>;I)Los/RelPath;
    MethodParameters:
      Name                           Flags
      p                              final
      ups                            final

  public os.RelPath relativeTo(os.RelPath);
    descriptor: (Los/RelPath;)Los/RelPath;
    flags: (0x0001) ACC_PUBLIC
    Code:
      stack=5, locals=2, args_size=2
         0: aload_1
         1: invokevirtual #154                // Method ups:()I
         4: aload_0
         5: invokevirtual #154                // Method ups:()I
         8: if_icmpge     39
        11: new           #2                  // class os/RelPath
        14: dup
        15: aload_0
        16: getfield      #164                // Field segments0:[Ljava/lang/String;
        19: aload_0
        20: invokevirtual #154                // Method ups:()I
        23: aload_1
        24: invokevirtual #124                // Method segments:()Lscala/collection/immutable/IndexedSeq;
        27: invokeinterface #167,  1          // InterfaceMethod scala/collection/immutable/IndexedSeq.length:()I
        32: iadd
        33: invokespecial #158                // Method "<init>":([Ljava/lang/String;I)V
        36: goto          77
        39: aload_1
        40: invokevirtual #154                // Method ups:()I
        43: aload_0
        44: invokevirtual #154                // Method ups:()I
        47: if_icmpne     67
        50: getstatic     #172                // Field os/SubPath$.MODULE$:Los/SubPath$;
        53: aload_0
        54: getfield      #164                // Field segments0:[Ljava/lang/String;
        57: aload_1
        58: invokevirtual #124                // Method segments:()Lscala/collection/immutable/IndexedSeq;
        61: invokevirtual #176                // Method os/SubPath$.relativeTo0:([Ljava/lang/String;Lscala/collection/immutable/IndexedSeq;)Los/RelPath;
        64: goto          77
        67: new           #26                 // class os/PathError$NoRelativePath
        70: dup
        71: aload_0
        72: aload_1
        73: invokespecial #179                // Method os/PathError$NoRelativePath."<init>":(Los/RelPath;Los/RelPath;)V
        76: athrow
        77: areturn
      StackMapTable: number_of_entries = 3
        frame_type = 39 /* same */
        frame_type = 27 /* same */
        frame_type = 73 /* same_locals_1_stack_item */
          stack = [ class os/RelPath ]
      LineNumberTable:
        line 261: 0
        line 262: 39
        line 263: 67
      LocalVariableTable:
        Start  Length  Slot  Name   Signature
            0      78     0  this   Los/RelPath;
            0      78     1  base   Los/RelPath;
    MethodParameters:
      Name                           Flags
      base                           final

  public boolean startsWith(os.RelPath);
    descriptor: (Los/RelPath;)Z
    flags: (0x0001) ACC_PUBLIC
    Code:
      stack=4, locals=5, args_size=2
         0: getstatic     #185                // Field scala/Predef$.MODULE$:Lscala/Predef$;
         3: aload_0
         4: getfield      #164                // Field segments0:[Ljava/lang/String;
         7: checkcast     #187                // class "[Ljava/lang/Object;"
        10: invokevirtual #191                // Method scala/Predef$.refArrayOps:([Ljava/lang/Object;)Ljava/lang/Object;
        13: astore_2
        14: aload_1
        15: invokevirtual #124                // Method segments:()Lscala/collection/immutable/IndexedSeq;
        18: astore_3
        19: getstatic     #196                // Field scala/collection/ArrayOps$.MODULE$:Lscala/collection/ArrayOps$;
        22: aload_2
        23: invokevirtual #200                // Method scala/collection/ArrayOps$.startsWith$default$2$extension:(Ljava/lang/Object;)I
        26: istore        4
        28: getstatic     #196                // Field scala/collection/ArrayOps$.MODULE$:Lscala/collection/ArrayOps$;
        31: aload_2
        32: aload_3
        33: iload         4
        35: invokevirtual #204                // Method scala/collection/ArrayOps$.startsWith$extension:(Ljava/lang/Object;Lscala/collection/IterableOnce;I)Z
        38: ifeq          56
        41: aload_0
        42: invokevirtual #154                // Method ups:()I
        45: aload_1
        46: invokevirtual #154                // Method ups:()I
        49: if_icmpne     56
        52: iconst_1
        53: goto          57
        56: iconst_0
        57: ireturn
      StackMapTable: number_of_entries = 2
        frame_type = 254 /* append */
          offset_delta = 56
          locals = [ class java/lang/Object, class scala/collection/immutable/IndexedSeq, int ]
        frame_type = 64 /* same_locals_1_stack_item */
          stack = [ int ]
      LineNumberTable:
        line 267: 0
      LocalVariableTable:
        Start  Length  Slot  Name   Signature
           14      24     2 qual$1   Ljava/lang/Object;
           19      19     3   x$1   Lscala/collection/immutable/IndexedSeq;
           28      10     4   x$2   I
            0      58     0  this   Los/RelPath;
            0      58     1 target   Los/RelPath;
    MethodParameters:
      Name                           Flags
      target                         final

  public java.lang.String toString();
    descriptor: ()Ljava/lang/String;
    flags: (0x0001) ACC_PUBLIC
    Code:
      stack=3, locals=1, args_size=1
         0: getstatic     #214                // Field scala/package$.MODULE$:Lscala/package$;
         3: invokevirtual #218                // Method scala/package$.Seq:()Lscala/collection/immutable/Seq$;
         6: aload_0
         7: invokevirtual #154                // Method ups:()I
        10: invokedynamic #237,  0            // InvokeDynamic #0:apply:()Lscala/Function0;
        15: invokevirtual #243                // Method scala/collection/immutable/Seq$.fill:(ILscala/Function0;)Ljava/lang/Object;
        18: checkcast     #245                // class scala/collection/IterableOps
        21: getstatic     #185                // Field scala/Predef$.MODULE$:Lscala/Predef$;
        24: aload_0
        25: getfield      #164                // Field segments0:[Ljava/lang/String;
        28: checkcast     #187                // class "[Ljava/lang/Object;"
        31: invokevirtual #249                // Method scala/Predef$.wrapRefArray:([Ljava/lang/Object;)Lscala/collection/mutable/ArraySeq$ofRef;
        34: invokeinterface #253,  2          // InterfaceMethod scala/collection/IterableOps.$plus$plus:(Lscala/collection/IterableOnce;)Ljava/lang/Object;
        39: checkcast     #255                // class scala/collection/IterableOnceOps
        42: ldc_w         #257                // String /
        45: invokeinterface #261,  2          // InterfaceMethod scala/collection/IterableOnceOps.mkString:(Ljava/lang/String;)Ljava/lang/String;
        50: areturn
      LineNumberTable:
        line 270: 0
      LocalVariableTable:
        Start  Length  Slot  Name   Signature
            0      51     0  this   Los/RelPath;

  public int hashCode();
    descriptor: ()I
    flags: (0x0001) ACC_PUBLIC
    Code:
      stack=2, locals=1, args_size=1
         0: aload_0
         1: invokevirtual #124                // Method segments:()Lscala/collection/immutable/IndexedSeq;
         4: invokeinterface #266,  1          // InterfaceMethod scala/collection/Seq.hashCode:()I
         9: aload_0
        10: invokevirtual #154                // Method ups:()I
        13: invokestatic  #272                // Method scala/runtime/BoxesRunTime.boxToInteger:(I)Ljava/lang/Integer;
        16: invokevirtual #273                // Method java/lang/Object.hashCode:()I
        19: iadd
        20: ireturn
      LineNumberTable:
        line 271: 0
      LocalVariableTable:
        Start  Length  Slot  Name   Signature
            0      21     0  this   Los/RelPath;

  public boolean equals(java.lang.Object);
    descriptor: (Ljava/lang/Object;)Z
    flags: (0x0001) ACC_PUBLIC
    Code:
      stack=2, locals=8, args_size=2
         0: aload_1
         1: astore_3
         2: aload_3
         3: instanceof    #2                  // class os/RelPath
         6: ifeq          68
         9: aload_3
        10: checkcast     #2                  // class os/RelPath
        13: astore        4
        15: aload_0
        16: invokevirtual #124                // Method segments:()Lscala/collection/immutable/IndexedSeq;
        19: aload         4
        21: invokevirtual #124                // Method segments:()Lscala/collection/immutable/IndexedSeq;
        24: astore        5
        26: dup
        27: ifnonnull     39
        30: pop
        31: aload         5
        33: ifnull        47
        36: goto          63
        39: aload         5
        41: invokevirtual #278                // Method java/lang/Object.equals:(Ljava/lang/Object;)Z
        44: ifeq          63
        47: aload         4
        49: invokevirtual #154                // Method ups:()I
        52: aload_0
        53: invokevirtual #154                // Method ups:()I
        56: if_icmpne     63
        59: iconst_1
        60: goto          64
        63: iconst_0
        64: istore_2
        65: goto          141
        68: goto          71
        71: aload_3
        72: instanceof    #280                // class os/SubPath
        75: ifeq          133
        78: aload_3
        79: checkcast     #280                // class os/SubPath
        82: astore        6
        84: aload_0
        85: invokevirtual #124                // Method segments:()Lscala/collection/immutable/IndexedSeq;
        88: aload         6
        90: invokevirtual #281                // Method os/SubPath.segments:()Lscala/collection/immutable/IndexedSeq;
        93: astore        7
        95: dup
        96: ifnonnull     108
        99: pop
       100: aload         7
       102: ifnull        116
       105: goto          128
       108: aload         7
       110: invokevirtual #278                // Method java/lang/Object.equals:(Ljava/lang/Object;)Z
       113: ifeq          128
       116: aload_0
       117: invokevirtual #154                // Method ups:()I
       120: iconst_0
       121: if_icmpne     128
       124: iconst_1
       125: goto          129
       128: iconst_0
       129: istore_2
       130: goto          141
       133: goto          136
       136: iconst_0
       137: istore_2
       138: goto          141
       141: iload_2
       142: ireturn
      StackMapTable: number_of_entries = 13
        frame_type = 255 /* full_frame */
          offset_delta = 39
          locals = [ class os/RelPath, class java/lang/Object, top, class java/lang/Object, class os/RelPath, class scala/collection/immutable/IndexedSeq ]
          stack = [ class scala/collection/immutable/IndexedSeq ]
        frame_type = 7 /* same */
        frame_type = 15 /* same */
        frame_type = 64 /* same_locals_1_stack_item */
          stack = [ int ]
        frame_type = 249 /* chop */
          offset_delta = 3
        frame_type = 2 /* same */
        frame_type = 255 /* full_frame */
          offset_delta = 36
          locals = [ class os/RelPath, class java/lang/Object, top, class java/lang/Object, top, top, class os/SubPath, class scala/collection/immutable/IndexedSeq ]
          stack = [ class scala/collection/immutable/IndexedSeq ]
        frame_type = 7 /* same */
        frame_type = 11 /* same */
        frame_type = 64 /* same_locals_1_stack_item */
          stack = [ int ]
        frame_type = 255 /* full_frame */
          offset_delta = 3
          locals = [ class os/RelPath, class java/lang/Object, top, class java/lang/Object ]
          stack = []
        frame_type = 2 /* same */
        frame_type = 255 /* full_frame */
          offset_delta = 4
          locals = [ class os/RelPath, class java/lang/Object, int, class java/lang/Object ]
          stack = []
      LineNumberTable:
        line 272: 0
        line 273: 2
        line 274: 71
        line 275: 136
        line 272: 141
      LocalVariableTable:
        Start  Length  Slot  Name   Signature
            0     143     0  this   Los/RelPath;
            0     143     1     o   Ljava/lang/Object;
    MethodParameters:
      Name                           Flags
      o                              final

  public java.nio.file.Path toNIO();
    descriptor: ()Ljava/nio/file/Path;
    flags: (0x0001) ACC_PUBLIC
    Code:
      stack=2, locals=1, args_size=1
         0: aload_0
         1: invokevirtual #285                // Method toString:()Ljava/lang/String;
         4: iconst_0
         5: anewarray     #142                // class java/lang/String
         8: invokestatic  #291                // Method java/nio/file/Paths.get:(Ljava/lang/String;[Ljava/lang/String;)Ljava/nio/file/Path;
        11: areturn
      LineNumberTable:
        line 278: 0
      LocalVariableTable:
        Start  Length  Slot  Name   Signature
            0      12     0  this   Los/RelPath;

  public os.SubPath asSubPath();
    descriptor: ()Los/SubPath;
    flags: (0x0001) ACC_PUBLIC
    Code:
      stack=3, locals=1, args_size=1
         0: getstatic     #185                // Field scala/Predef$.MODULE$:Lscala/Predef$;
         3: aload_0
         4: invokevirtual #154                // Method ups:()I
         7: iconst_0
         8: if_icmpne     15
        11: iconst_1
        12: goto          16
        15: iconst_0
        16: invokevirtual #297                // Method scala/Predef$.require:(Z)V
        19: new           #280                // class os/SubPath
        22: dup
        23: aload_0
        24: getfield      #164                // Field segments0:[Ljava/lang/String;
        27: invokespecial #300                // Method os/SubPath."<init>":([Ljava/lang/String;)V
        30: areturn
      StackMapTable: number_of_entries = 2
        frame_type = 79 /* same_locals_1_stack_item */
          stack = [ class scala/Predef$ ]
        frame_type = 255 /* full_frame */
          offset_delta = 0
          locals = [ class os/RelPath ]
          stack = [ class scala/Predef$, int ]
      LineNumberTable:
        line 281: 0
        line 282: 19
      LocalVariableTable:
        Start  Length  Slot  Name   Signature
            0      31     0  this   Los/RelPath;

  public os.Path resolveFrom(os.Path);
    descriptor: (Los/Path;)Los/Path;
    flags: (0x0001) ACC_PUBLIC
    Code:
      stack=3, locals=2, args_size=2
         0: aload_1
         1: getstatic     #307                // Field os/PathChunk$.MODULE$:Los/PathChunk$;
         4: aload_0
         5: invokevirtual #310                // Method os/PathChunk$.RelPathChunk:(Los/RelPath;)Los/PathChunk$RelPathChunk;
         8: invokevirtual #315                // Method os/Path.$div:(Los/PathChunk;)Los/Path;
        11: areturn
      LineNumberTable:
        line 285: 0
      LocalVariableTable:
        Start  Length  Slot  Name   Signature
            0      12     0  this   Los/RelPath;
            0      12     1  base   Los/Path;
    MethodParameters:
      Name                           Flags
      base                           final

  public boolean startsWith(os.BasePath);
    descriptor: (Los/BasePath;)Z
    flags: (0x1041) ACC_PUBLIC, ACC_BRIDGE, ACC_SYNTHETIC
    Code:
      stack=2, locals=2, args_size=2
         0: aload_0
         1: aload_1
         2: checkcast     #2                  // class os/RelPath
         5: invokevirtual #319                // Method startsWith:(Los/RelPath;)Z
         8: ireturn
      LineNumberTable:
        line 250: 0
      LocalVariableTable:
        Start  Length  Slot  Name   Signature
            0       9     0  this   Los/RelPath;
            0       9     1 target   Los/BasePath;
    MethodParameters:
      Name                           Flags
      target                         final

  public os.RelPath relativeTo(os.BasePath);
    descriptor: (Los/BasePath;)Los/RelPath;
    flags: (0x1041) ACC_PUBLIC, ACC_BRIDGE, ACC_SYNTHETIC
    Code:
      stack=2, locals=2, args_size=2
         0: aload_0
         1: aload_1
         2: checkcast     #2                  // class os/RelPath
         5: invokevirtual #322                // Method relativeTo:(Los/RelPath;)Los/RelPath;
         8: areturn
      LineNumberTable:
        line 250: 0
      LocalVariableTable:
        Start  Length  Slot  Name   Signature
            0       9     0  this   Los/RelPath;
            0       9     1 target   Los/BasePath;
    MethodParameters:
      Name                           Flags
      target                         final

  public os.BasePath make(scala.collection.immutable.Seq, int);
    descriptor: (Lscala/collection/immutable/Seq;I)Los/BasePath;
    flags: (0x1041) ACC_PUBLIC, ACC_BRIDGE, ACC_SYNTHETIC
    Code:
      stack=3, locals=3, args_size=3
         0: aload_0
         1: aload_1
         2: iload_2
         3: invokevirtual #325                // Method make:(Lscala/collection/immutable/Seq;I)Los/RelPath;
         6: areturn
      LineNumberTable:
        line 250: 0
      LocalVariableTable:
        Start  Length  Slot  Name   Signature
            0       7     0  this   Los/RelPath;
            0       7     1     p   Lscala/collection/immutable/Seq;
            0       7     2   ups   I
    MethodParameters:
      Name                           Flags
      p                              final
      ups                            final

  public scala.collection.IterableOnce segments();
    descriptor: ()Lscala/collection/IterableOnce;
    flags: (0x1041) ACC_PUBLIC, ACC_BRIDGE, ACC_SYNTHETIC
    Code:
      stack=1, locals=1, args_size=1
         0: aload_0
         1: invokevirtual #124                // Method segments:()Lscala/collection/immutable/IndexedSeq;
         4: areturn
      LineNumberTable:
        line 250: 0
      LocalVariableTable:
        Start  Length  Slot  Name   Signature
            0       5     0  this   Los/RelPath;

  public static final java.lang.String $anonfun$toString$1();
    descriptor: ()Ljava/lang/String;
    flags: (0x1019) ACC_PUBLIC, ACC_STATIC, ACC_FINAL, ACC_SYNTHETIC
    Code:
      stack=1, locals=0, args_size=0
         0: ldc_w         #328                // String ..
         3: areturn
      LineNumberTable:
        line 270: 0

  public os.RelPath(java.lang.String[], int);
    descriptor: ([Ljava/lang/String;I)V
    flags: (0x0001) ACC_PUBLIC
    Code:
      stack=3, locals=3, args_size=3
         0: aload_0
         1: aload_1
         2: putfield      #164                // Field segments0:[Ljava/lang/String;
         5: aload_0
         6: iload_2
         7: putfield      #118                // Field ups:I
        10: aload_0
        11: invokespecial #331                // Method java/lang/Object."<init>":()V
        14: aload_0
        15: invokestatic  #335                // InterfaceMethod os/BasePath.$init$:(Los/BasePath;)V
        18: aload_0
        19: invokestatic  #338                // InterfaceMethod os/BasePathImpl.$init$:(Los/BasePathImpl;)V
        22: aload_0
        23: invokestatic  #341                // InterfaceMethod os/SegmentedPath.$init$:(Los/SegmentedPath;)V
        26: aload_0
        27: getstatic     #185                // Field scala/Predef$.MODULE$:Lscala/Predef$;
        30: aload_1
        31: invokevirtual #345                // Method scala/Predef$.copyArrayToImmutableIndexedSeq:(Ljava/lang/Object;)Lscala/collection/immutable/IndexedSeq;
        34: putfield      #132                // Field segments:Lscala/collection/immutable/IndexedSeq;
        37: getstatic     #185                // Field scala/Predef$.MODULE$:Lscala/Predef$;
        40: iload_2
        41: iconst_0
        42: if_icmplt     49
        45: iconst_1
        46: goto          50
        49: iconst_0
        50: invokevirtual #297                // Method scala/Predef$.require:(Z)V
        53: return
      StackMapTable: number_of_entries = 2
        frame_type = 255 /* full_frame */
          offset_delta = 49
          locals = [ class os/RelPath, class "[Ljava/lang/String;", int ]
          stack = [ class scala/Predef$ ]
        frame_type = 255 /* full_frame */
          offset_delta = 0
          locals = [ class os/RelPath, class "[Ljava/lang/String;", int ]
          stack = [ class scala/Predef$, int ]
      LineNumberTable:
        line 250: 0
        line 251: 10
        line 253: 26
        line 255: 37
        line 250: 53
      LocalVariableTable:
        Start  Length  Slot  Name   Signature
            0      54     0  this   Los/RelPath;
            0      54     1 segments0   [Ljava/lang/String;
            0      54     2   ups   I
    MethodParameters:
      Name                           Flags
      segments0                      final
      ups                            final

  private static java.lang.Object $deserializeLambda$(java.lang.invoke.SerializedLambda);
    descriptor: (Ljava/lang/invoke/SerializedLambda;)Ljava/lang/Object;
    flags: (0x100a) ACC_PRIVATE, ACC_STATIC, ACC_SYNTHETIC
    Code:
      stack=1, locals=1, args_size=1
         0: aload_0
         1: invokedynamic #357,  0            // InvokeDynamic #1:lambdaDeserialize:(Ljava/lang/invoke/SerializedLambda;)Ljava/lang/Object;
         6: areturn
}
InnerClasses:
  public static final #19= #16 of #18;    // Lookup=class java/lang/invoke/MethodHandles$Lookup of class java/lang/invoke/MethodHandles
  public static #24= #21 of #23;          // RelPathChunk=class os/PathChunk$RelPathChunk of class os/PathChunk
  public static #29= #26 of #28;          // NoRelativePath=class os/PathError$NoRelativePath of class os/PathError
  public static final #34= #31 of #33;    // ofRef=class scala/collection/mutable/ArraySeq$ofRef of class scala/collection/mutable/ArraySeq
SourceFile: "Path.scala"
RuntimeVisibleAnnotations:
  0: #12(#13=s#14)
    scala.reflect.ScalaSignature(
      bytes="\u0006\u0005\u0005ud\u0001\u0002\u0010 \u0001\tB\u0001b\r\u0001\u0003\u0002\u0003\u0006I\u0001\u000e\u0005\t\u0005\u0002\u0011)\u0019!C\u0001\u0007\"Aq\t\u0001B\u0001B\u0003%A\t\u0003\u0004I\u0001\u0011\u0005q$\u0013\u0005\u0006\u001b\u0002!\tA\u0014\u0005\b%\u0002\u0011\r\u0011\"\u0001T\u0011\u0019i\u0006\u0001)A\u0005)\u0016!a\f\u0001\u0001K\u0011\u0019y\u0006\u0001)C\tA\")q\r\u0001C\u0001Q\")1\u000e\u0001C\u0001Y\")!\u000f\u0001C!g\")A\u000f\u0001C!k\")a\u000f\u0001C!o\")Q\u0010\u0001C\u0001}\"9\u00111\u0003\u0001\u0005\u0002\u0005U\u0001bBA\u000f\u0001\u0011\u0005\u0011qD\u0004\b\u0003_y\u0002\u0012AA\u0019\r\u0019qr\u0004#\u0001\u00024!1\u0001j\u0005C\u0001\u0003kAq!a\u000e\u0014\t\u0003\tI\u0004C\u0004\u00028M!\t!a\u0017\t\u0013\u0005\u00054C1A\u0005\u0004\u0005\r\u0004\u0002CA6\'\u0001\u0006I!!\u001a\t\u0013\u000554C1A\u0005\u0002\u0005=\u0004bBA9\'\u0001\u0006IA\u0013\u0005\n\u0003g\u001a\"\u0019!C\u0001\u0003_Bq!!\u001e\u0014A\u0003%!\nC\u0004\u0002xM!\u0019!!\u001f\u0003\u000fI+G\u000eU1uQ*\t\u0001%\u0001\u0002pg\u000e\u00011#\u0002\u0001$S5\u0002\u0004C\u0001\u0013(\u001b\u0005)#\"\u0001\u0014\u0002\u000bM\u001c\u0017\r\\1\n\u0005!*#AB!osJ+g\r\u0005\u0002+W5\tq$\u0003\u0002-?\tAa)\u001b7f!\u0006$\b\u000e\u0005\u0002+]%\u0011qf\b\u0002\r\u0005\u0006\u001cX\rU1uQ&k\u0007\u000f\u001c\t\u0003UEJ!AM\u0010\u0003\u001bM+w-\\3oi\u0016$\u0007+\u0019;i\u0003%\u0019XmZ7f]R\u001c\b\u0007E\u0002%k]J!AN\u0013\u0003\u000b\u0005\u0013(/Y=\u0011\u0005azdBA\u001d>!\tQT%D\u0001<\u0015\ta\u0014%\u0001\u0004=e>|GOP\u0005\u0003}\u0015\na\u0001\u0015:fI\u00164\u0017B\u0001!B\u0005\u0019\u0019FO]5oO*\u0011a(J\u0001\u0004kB\u001cX#\u0001#\u0011\u0005\u0011*\u0015B\u0001$&\u0005\rIe\u000e^\u0001\u0005kB\u001c\b%\u0001\u0004=S:LGO\u0010\u000b\u0004\u0015.c\u0005C\u0001\u0016\u0001\u0011\u0015\u0019D\u00011\u00015\u0011\u0015\u0011E\u00011\u0001E\u0003\u001da\u0017m\u001d;PaR,\u0012a\u0014\t\u0004IA;\u0014BA)&\u0005\u0019y\u0005\u000f^5p]\u0006A1/Z4nK:$8/F\u0001U!\r)&l\u000e\b\u0003-bs!AO,\n\u0003\u0019J!!W\u0013\u0002\u000fA\f7m[1hK&\u00111\f\u0018\u0002\u000b\u0013:$W\r_3e\'\u0016\f(BA-&\u0003%\u0019XmZ7f]R\u001c\bE\u0001\u0005UQ&\u001cH+\u001f9f\u0003\u0011i\u0017m[3\u0015\u0007)\u000bg\rC\u0003c\u0013\u0001\u00071-A\u0001q!\r)FmN\u0005\u0003Kr\u00131aU3r\u0011\u0015\u0011\u0015\u00021\u0001E\u0003)\u0011X\r\\1uSZ,Gk\u001c\u000b\u0003\u0015&DQA\u001b\u0006A\u0002)\u000bAAY1tK\u0006Q1\u000f^1siN<\u0016\u000e\u001e5\u0015\u00055\u0004\bC\u0001\u0013o\u0013\tyWEA\u0004C_>dW-\u00198\t\u000bE\\\u0001\u0019\u0001&\u0002\rQ\f\'oZ3u\u0003!!xn\u0015;sS:<G#A\u001c\u0002\u0011!\f7\u000f[\"pI\u0016$\u0012\u0001R\u0001\u0007KF,\u0018\r\\:\u0015\u00055D\b\"B=\u000f\u0001\u0004Q\u0018!A8\u0011\u0005\u0011Z\u0018B\u0001?&\u0005\r\te._\u0001\u0006i>t\u0015jT\u000b\u0002\u007fB!\u0011\u0011AA\b\u001b\t\t\u0019A\u0003\u0003\u0002\u0006\u0005\u001d\u0011\u0001\u00024jY\u0016TA!!\u0003\u0002\f\u0005\u0019a.[8\u000b\u0005\u00055\u0011\u0001\u00026bm\u0006LA!!\u0005\u0002\u0004\t!\u0001+\u0019;i\u0003%\t7oU;c!\u0006$\b.\u0006\u0002\u0002\u0018A\u0019!&!\u0007\n\u0007\u0005mqDA\u0004Tk\n\u0004\u0016\r\u001e5\u0002\u0017I,7o\u001c7wK\u001a\u0013x.\u001c\u000b\u0005\u0003C\t9\u0003\u0005\u0003\u0002$\u00055b\u0002BA\u0013\u0003Oa\u0001\u0001\u0003\u0004k#\u0001\u0007\u0011\u0011\u0006\t\u0004U\u0005-\u0012bAA\t?%\u0019a,a\u000b\u0002\u000fI+G\u000eU1uQB\u0011!fE\n\u0003\'\r\"\"!!\r\u0002\u000b\u0005\u0004\b\u000f\\=\u0016\t\u0005m\u00121\n\u000b\u0005\u0003{\t9\u0006F\u0002K\u0003\u007fA\u0011\"!\u0011\u0016\u0003\u0003\u0005\u001d!a\u0011\u0002\u0015\u00154\u0018\u000eZ3oG\u0016$#\u0007E\u0003+\u0003\u000b\nI%C\u0002\u0002H}\u0011q\u0002U1uQ\u000e{gN^3si&\u0014G.\u001a\t\u0005\u0003K\tY\u0005B\u0004\u0002NU\u0011\r!a\u0014\u0003\u0003Q\u000b2!!\u0015{!\r!\u00131K\u0005\u0004\u0003+*#a\u0002(pi\"Lgn\u001a\u0005\b\u00033*\u0002\u0019AA%\u0003\t1\u0007\u0007F\u0003K\u0003;\ny\u0006C\u00034-\u0001\u0007A\u000bC\u0003C-\u0001\u0007A)A\bsK2\u0004\u0016\r\u001e5Pe\u0012,\'/\u001b8h+\t\t)\u0007\u0005\u0003V\u0003OR\u0015bAA59\nAqJ\u001d3fe&tw-\u0001\tsK2\u0004\u0016\r\u001e5Pe\u0012,\'/\u001b8hA\u0005\u0011Q\u000f]\u000b\u0002\u0015\u0006\u0019Q\u000f\u001d\u0011\u0002\u0007I,G.\u0001\u0003sK2\u0004\u0013AC*vEJ+G\u000eU1uQR\u0019!*a\u001f\t\r\tl\u0002\u0019AA\f\u0001"
    )
BootstrapMethods:
  0: #234 REF_invokeStatic java/lang/invoke/LambdaMetafactory.altMetafactory:(Ljava/lang/invoke/MethodHandles$Lookup;Ljava/lang/String;Ljava/lang/invoke/MethodType;[Ljava/lang/Object;)Ljava/lang/invoke/CallSite;
    Method arguments:
      #220 ()Ljava/lang/Object;
      #224 REF_invokeStatic os/RelPath.$anonfun$toString$1:()Ljava/lang/String;
      #225 ()Ljava/lang/String;
      #226 5
      #227 1
      #225 ()Ljava/lang/String;
  1: #354 REF_invokeStatic scala/runtime/LambdaDeserialize.bootstrap:(Ljava/lang/invoke/MethodHandles$Lookup;Ljava/lang/String;Ljava/lang/invoke/MethodType;[Ljava/lang/invoke/MethodHandle;)Ljava/lang/invoke/CallSite;
    Method arguments:
      #224 REF_invokeStatic os/RelPath.$anonfun$toString$1:()Ljava/lang/String;
  ScalaInlineInfo: length = 0x7C (unknown attribute)
   01 00 00 18 00 DD 00 5E 01 00 4C 00 4D 00 00 9B
   00 9C 00 01 24 01 25 00 00 63 00 5E 00 00 56 00
   57 00 01 12 01 13 00 00 5D 00 5E 00 01 06 00 74
   00 00 67 00 5E 00 00 77 00 78 00 00 85 01 43 00
   00 85 00 86 00 00 A0 01 40 00 00 A0 00 A1 00 01
   2D 01 2E 00 00 27 01 46 00 00 27 00 7A 00 00 B4
   01 3D 00 00 B4 00 57 00 00 6B 00 6C 00 01 1A 01
   1B 00 00 D1 00 5E 00 00 25 00 74 00
  ScalaSig: length = 0x3 (unknown attribute)
   05 02 00
