Classfile /Users/mw/Projects/slang-braindump/.jar/jar11/assemble/slang-braindump/assemble/content/os/SeekableSource$ChannelSource.class
  Last modified May 29, 2022; size 2417 bytes
  SHA-256 checksum 8a1e3f5c6a8b1e24873b1db26045336c6c48c34f4ad911b14f485f62cff69a9e
  Compiled from "Source.scala"
public class os.SeekableSource$ChannelSource implements os.SeekableSource
  minor version: 0
  major version: 52
  flags: (0x0021) ACC_PUBLIC, ACC_SUPER
  this_class: #2                          // os/SeekableSource$ChannelSource
  super_class: #4                         // java/lang/Object
  interfaces: 1, fields: 1, methods: 9, attributes: 4
Constant pool:
    #1 = Utf8               os/SeekableSource$ChannelSource
    #2 = Class              #1            // os/SeekableSource$ChannelSource
    #3 = Utf8               java/lang/Object
    #4 = Class              #3            // java/lang/Object
    #5 = Utf8               os/SeekableSource
    #6 = Class              #5            // os/SeekableSource
    #7 = Utf8               Source.scala
    #8 = Utf8               ChannelSource
    #9 = Utf8               cn
   #10 = Utf8               Ljava/nio/channels/SeekableByteChannel;
   #11 = Utf8               getChannel
   #12 = Utf8               ()Ljava/nio/channels/SeekableByteChannel;
   #13 = Utf8               getChannel$
   #14 = Utf8               (Los/SeekableSource;)Ljava/nio/channels/SeekableByteChannel;
   #15 = NameAndType        #13:#14       // getChannel$:(Los/SeekableSource;)Ljava/nio/channels/SeekableByteChannel;
   #16 = InterfaceMethodref #6.#15        // os/SeekableSource.getChannel$:(Los/SeekableSource;)Ljava/nio/channels/SeekableByteChannel;
   #17 = Utf8               this
   #18 = Utf8               Los/SeekableSource$ChannelSource;
   #19 = Utf8               httpContentType
   #20 = Utf8               ()Lscala/Some;
   #21 = Utf8               ()Lscala/Some<Ljava/lang/String;>;
   #22 = Utf8               os/Source
   #23 = Class              #22           // os/Source
   #24 = Utf8               httpContentType$
   #25 = Utf8               (Los/Source;)Lscala/Some;
   #26 = NameAndType        #24:#25       // httpContentType$:(Los/Source;)Lscala/Some;
   #27 = InterfaceMethodref #23.#26       // os/Source.httpContentType$:(Los/Source;)Lscala/Some;
   #28 = Utf8               writeBytesTo
   #29 = Utf8               (Ljava/io/OutputStream;)V
   #30 = Utf8               out
   #31 = Utf8               writeBytesTo$
   #32 = Utf8               (Los/Source;Ljava/io/OutputStream;)V
   #33 = NameAndType        #31:#32       // writeBytesTo$:(Los/Source;Ljava/io/OutputStream;)V
   #34 = InterfaceMethodref #23.#33       // os/Source.writeBytesTo$:(Los/Source;Ljava/io/OutputStream;)V
   #35 = Utf8               Ljava/io/OutputStream;
   #36 = Utf8               (Ljava/nio/channels/WritableByteChannel;)Ljava/lang/Object;
   #37 = Utf8               (Los/Source;Ljava/nio/channels/WritableByteChannel;)Ljava/lang/Object;
   #38 = NameAndType        #31:#37       // writeBytesTo$:(Los/Source;Ljava/nio/channels/WritableByteChannel;)Ljava/lang/Object;
   #39 = InterfaceMethodref #23.#38       // os/Source.writeBytesTo$:(Los/Source;Ljava/nio/channels/WritableByteChannel;)Ljava/lang/Object;
   #40 = Utf8               Ljava/nio/channels/WritableByteChannel;
   #41 = Utf8               contentLength
   #42 = Utf8               ()Lscala/Option;
   #43 = Utf8               ()Lscala/Option<Ljava/lang/Object;>;
   #44 = Utf8               geny/Writable
   #45 = Class              #44           // geny/Writable
   #46 = Utf8               contentLength$
   #47 = Utf8               (Lgeny/Writable;)Lscala/Option;
   #48 = NameAndType        #46:#47       // contentLength$:(Lgeny/Writable;)Lscala/Option;
   #49 = InterfaceMethodref #45.#48       // geny/Writable.contentLength$:(Lgeny/Writable;)Lscala/Option;
   #50 = Utf8               getHandle
   #51 = Utf8               ()Lscala/util/Right;
   #52 = Utf8               ()Lscala/util/Right<Lscala/runtime/Nothing$;Ljava/nio/channels/SeekableByteChannel;>;
   #53 = Utf8               scala/package$
   #54 = Class              #53           // scala/package$
   #55 = Utf8               MODULE$
   #56 = Utf8               Lscala/package$;
   #57 = NameAndType        #55:#56       // MODULE$:Lscala/package$;
   #58 = Fieldref           #54.#57       // scala/package$.MODULE$:Lscala/package$;
   #59 = Utf8               Right
   #60 = Utf8               ()Lscala/util/Right$;
   #61 = NameAndType        #59:#60       // Right:()Lscala/util/Right$;
   #62 = Methodref          #54.#61       // scala/package$.Right:()Lscala/util/Right$;
   #63 = NameAndType        #9:#10        // cn:Ljava/nio/channels/SeekableByteChannel;
   #64 = Fieldref           #2.#63        // os/SeekableSource$ChannelSource.cn:Ljava/nio/channels/SeekableByteChannel;
   #65 = Utf8               scala/util/Right$
   #66 = Class              #65           // scala/util/Right$
   #67 = Utf8               apply
   #68 = Utf8               (Ljava/lang/Object;)Lscala/util/Right;
   #69 = NameAndType        #67:#68       // apply:(Ljava/lang/Object;)Lscala/util/Right;
   #70 = Methodref          #66.#69       // scala/util/Right$.apply:(Ljava/lang/Object;)Lscala/util/Right;
   #71 = NameAndType        #19:#20       // httpContentType:()Lscala/Some;
   #72 = Methodref          #2.#71        // os/SeekableSource$ChannelSource.httpContentType:()Lscala/Some;
   #73 = Utf8               ()Lscala/util/Either;
   #74 = NameAndType        #50:#51       // getHandle:()Lscala/util/Right;
   #75 = Methodref          #2.#74        // os/SeekableSource$ChannelSource.getHandle:()Lscala/util/Right;
   #76 = Utf8               <init>
   #77 = Utf8               (Ljava/nio/channels/SeekableByteChannel;)V
   #78 = Utf8               ()V
   #79 = NameAndType        #76:#78       // "<init>":()V
   #80 = Methodref          #4.#79        // java/lang/Object."<init>":()V
   #81 = Utf8               $init$
   #82 = Utf8               (Lgeny/Writable;)V
   #83 = NameAndType        #81:#82       // $init$:(Lgeny/Writable;)V
   #84 = InterfaceMethodref #45.#83       // geny/Writable.$init$:(Lgeny/Writable;)V
   #85 = Utf8               (Los/Source;)V
   #86 = NameAndType        #81:#85       // $init$:(Los/Source;)V
   #87 = InterfaceMethodref #23.#86       // os/Source.$init$:(Los/Source;)V
   #88 = Utf8               (Los/SeekableSource;)V
   #89 = NameAndType        #81:#88       // $init$:(Los/SeekableSource;)V
   #90 = InterfaceMethodref #6.#89        // os/SeekableSource.$init$:(Los/SeekableSource;)V
   #91 = Utf8               Code
   #92 = Utf8               LineNumberTable
   #93 = Utf8               LocalVariableTable
   #94 = Utf8               Signature
   #95 = Utf8               MethodParameters
   #96 = Utf8               InnerClasses
   #97 = Utf8               SourceFile
   #98 = Utf8               ScalaInlineInfo
   #99 = Utf8               Scala
{
  private final java.nio.channels.SeekableByteChannel cn;
    descriptor: Ljava/nio/channels/SeekableByteChannel;
    flags: (0x0012) ACC_PRIVATE, ACC_FINAL

  public java.nio.channels.SeekableByteChannel getChannel();
    descriptor: ()Ljava/nio/channels/SeekableByteChannel;
    flags: (0x0001) ACC_PUBLIC
    Code:
      stack=1, locals=1, args_size=1
         0: aload_0
         1: invokestatic  #16                 // InterfaceMethod os/SeekableSource.getChannel$:(Los/SeekableSource;)Ljava/nio/channels/SeekableByteChannel;
         4: areturn
      LineNumberTable:
        line 111: 0
      LocalVariableTable:
        Start  Length  Slot  Name   Signature
            0       5     0  this   Los/SeekableSource$ChannelSource;

  public scala.Some<java.lang.String> httpContentType();
    descriptor: ()Lscala/Some;
    flags: (0x0001) ACC_PUBLIC
    Code:
      stack=1, locals=1, args_size=1
         0: aload_0
         1: invokestatic  #27                 // InterfaceMethod os/Source.httpContentType$:(Los/Source;)Lscala/Some;
         4: areturn
      LineNumberTable:
        line 111: 0
      LocalVariableTable:
        Start  Length  Slot  Name   Signature
            0       5     0  this   Los/SeekableSource$ChannelSource;
    Signature: #21                          // ()Lscala/Some<Ljava/lang/String;>;

  public void writeBytesTo(java.io.OutputStream);
    descriptor: (Ljava/io/OutputStream;)V
    flags: (0x0001) ACC_PUBLIC
    Code:
      stack=2, locals=2, args_size=2
         0: aload_0
         1: aload_1
         2: invokestatic  #34                 // InterfaceMethod os/Source.writeBytesTo$:(Los/Source;Ljava/io/OutputStream;)V
         5: return
      LineNumberTable:
        line 111: 0
      LocalVariableTable:
        Start  Length  Slot  Name   Signature
            0       6     0  this   Los/SeekableSource$ChannelSource;
            0       6     1   out   Ljava/io/OutputStream;
    MethodParameters:
      Name                           Flags
      out                            final

  public java.lang.Object writeBytesTo(java.nio.channels.WritableByteChannel);
    descriptor: (Ljava/nio/channels/WritableByteChannel;)Ljava/lang/Object;
    flags: (0x0001) ACC_PUBLIC
    Code:
      stack=2, locals=2, args_size=2
         0: aload_0
         1: aload_1
         2: invokestatic  #39                 // InterfaceMethod os/Source.writeBytesTo$:(Los/Source;Ljava/nio/channels/WritableByteChannel;)Ljava/lang/Object;
         5: areturn
      LineNumberTable:
        line 111: 0
      LocalVariableTable:
        Start  Length  Slot  Name   Signature
            0       6     0  this   Los/SeekableSource$ChannelSource;
            0       6     1   out   Ljava/nio/channels/WritableByteChannel;
    MethodParameters:
      Name                           Flags
      out                            final

  public scala.Option<java.lang.Object> contentLength();
    descriptor: ()Lscala/Option;
    flags: (0x0001) ACC_PUBLIC
    Code:
      stack=1, locals=1, args_size=1
         0: aload_0
         1: invokestatic  #49                 // InterfaceMethod geny/Writable.contentLength$:(Lgeny/Writable;)Lscala/Option;
         4: areturn
      LineNumberTable:
        line 111: 0
      LocalVariableTable:
        Start  Length  Slot  Name   Signature
            0       5     0  this   Los/SeekableSource$ChannelSource;
    Signature: #43                          // ()Lscala/Option<Ljava/lang/Object;>;

  public scala.util.Right<scala.runtime.Nothing$, java.nio.channels.SeekableByteChannel> getHandle();
    descriptor: ()Lscala/util/Right;
    flags: (0x0001) ACC_PUBLIC
    Code:
      stack=2, locals=1, args_size=1
         0: getstatic     #58                 // Field scala/package$.MODULE$:Lscala/package$;
         3: invokevirtual #62                 // Method scala/package$.Right:()Lscala/util/Right$;
         6: aload_0
         7: getfield      #64                 // Field cn:Ljava/nio/channels/SeekableByteChannel;
        10: invokevirtual #70                 // Method scala/util/Right$.apply:(Ljava/lang/Object;)Lscala/util/Right;
        13: areturn
      LineNumberTable:
        line 112: 0
      LocalVariableTable:
        Start  Length  Slot  Name   Signature
            0      14     0  this   Los/SeekableSource$ChannelSource;
    Signature: #52                          // ()Lscala/util/Right<Lscala/runtime/Nothing$;Ljava/nio/channels/SeekableByteChannel;>;

  public scala.Option httpContentType();
    descriptor: ()Lscala/Option;
    flags: (0x1041) ACC_PUBLIC, ACC_BRIDGE, ACC_SYNTHETIC
    Code:
      stack=1, locals=1, args_size=1
         0: aload_0
         1: invokevirtual #72                 // Method httpContentType:()Lscala/Some;
         4: areturn
      LineNumberTable:
        line 111: 0
      LocalVariableTable:
        Start  Length  Slot  Name   Signature
            0       5     0  this   Los/SeekableSource$ChannelSource;

  public scala.util.Either getHandle();
    descriptor: ()Lscala/util/Either;
    flags: (0x1041) ACC_PUBLIC, ACC_BRIDGE, ACC_SYNTHETIC
    Code:
      stack=1, locals=1, args_size=1
         0: aload_0
         1: invokevirtual #75                 // Method getHandle:()Lscala/util/Right;
         4: areturn
      LineNumberTable:
        line 111: 0
      LocalVariableTable:
        Start  Length  Slot  Name   Signature
            0       5     0  this   Los/SeekableSource$ChannelSource;

  public os.SeekableSource$ChannelSource(java.nio.channels.SeekableByteChannel);
    descriptor: (Ljava/nio/channels/SeekableByteChannel;)V
    flags: (0x0001) ACC_PUBLIC
    Code:
      stack=2, locals=2, args_size=2
         0: aload_0
         1: aload_1
         2: putfield      #64                 // Field cn:Ljava/nio/channels/SeekableByteChannel;
         5: aload_0
         6: invokespecial #80                 // Method java/lang/Object."<init>":()V
         9: aload_0
        10: invokestatic  #84                 // InterfaceMethod geny/Writable.$init$:(Lgeny/Writable;)V
        13: aload_0
        14: invokestatic  #87                 // InterfaceMethod os/Source.$init$:(Los/Source;)V
        17: aload_0
        18: invokestatic  #90                 // InterfaceMethod os/SeekableSource.$init$:(Los/SeekableSource;)V
        21: return
      LineNumberTable:
        line 111: 0
      LocalVariableTable:
        Start  Length  Slot  Name   Signature
            0      22     0  this   Los/SeekableSource$ChannelSource;
            0      22     1    cn   Ljava/nio/channels/SeekableByteChannel;
    MethodParameters:
      Name                           Flags
      cn                             final
}
InnerClasses:
  public static #8= #2 of #6;             // ChannelSource=class os/SeekableSource$ChannelSource of class os/SeekableSource
SourceFile: "Source.scala"
  ScalaInlineInfo: length = 0x31 (unknown attribute)
   01 00 00 09 00 4C 00 4D 00 00 29 00 2A 00 00 0B
   00 0C 00 00 32 00 49 00 00 32 00 33 00 00 13 00
   2A 00 00 13 00 14 00 00 1C 00 1D 00 00 1C 00 24
   00
  Scala: length = 0x0 (unknown attribute)

