Classfile /Users/mw/Projects/slang-braindump/.jar/jar11/assemble/slang-braindump/assemble/content/os/Shellable$.class
  Last modified May 29, 2022; size 5726 bytes
  SHA-256 checksum bb289a2e94f882353d30250108d5a32fb70c2902917b956e772d43d73198b9f7
  Compiled from "Model.scala"
public final class os.Shellable$ implements java.io.Serializable
  minor version: 0
  major version: 52
  flags: (0x0031) ACC_PUBLIC, ACC_FINAL, ACC_SUPER
  this_class: #2                          // os/Shellable$
  super_class: #4                         // java/lang/Object
  interfaces: 1, fields: 1, methods: 15, attributes: 5
Constant pool:
    #1 = Utf8               os/Shellable$
    #2 = Class              #1            // os/Shellable$
    #3 = Utf8               java/lang/Object
    #4 = Class              #3            // java/lang/Object
    #5 = Utf8               java/io/Serializable
    #6 = Class              #5            // java/io/Serializable
    #7 = Utf8               Model.scala
    #8 = Utf8               java/lang/invoke/MethodHandles$Lookup
    #9 = Class              #8            // java/lang/invoke/MethodHandles$Lookup
   #10 = Utf8               java/lang/invoke/MethodHandles
   #11 = Class              #10           // java/lang/invoke/MethodHandles
   #12 = Utf8               Lookup
   #13 = Utf8               MODULE$
   #14 = Utf8               Los/Shellable$;
   #15 = Utf8               <clinit>
   #16 = Utf8               ()V
   #17 = Utf8               <init>
   #18 = NameAndType        #17:#16       // "<init>":()V
   #19 = Methodref          #2.#18        // os/Shellable$."<init>":()V
   #20 = NameAndType        #13:#14       // MODULE$:Los/Shellable$;
   #21 = Fieldref           #2.#20        // os/Shellable$.MODULE$:Los/Shellable$;
   #22 = Utf8               StringShellable
   #23 = Utf8               (Ljava/lang/String;)Los/Shellable;
   #24 = Utf8               s
   #25 = Utf8               os/Shellable
   #26 = Class              #25           // os/Shellable
   #27 = Utf8               scala/package$
   #28 = Class              #27           // scala/package$
   #29 = Utf8               Lscala/package$;
   #30 = NameAndType        #13:#29       // MODULE$:Lscala/package$;
   #31 = Fieldref           #28.#30       // scala/package$.MODULE$:Lscala/package$;
   #32 = Utf8               Seq
   #33 = Utf8               ()Lscala/collection/immutable/Seq$;
   #34 = NameAndType        #32:#33       // Seq:()Lscala/collection/immutable/Seq$;
   #35 = Methodref          #28.#34       // scala/package$.Seq:()Lscala/collection/immutable/Seq$;
   #36 = Utf8               scala/runtime/ScalaRunTime$
   #37 = Class              #36           // scala/runtime/ScalaRunTime$
   #38 = Utf8               Lscala/runtime/ScalaRunTime$;
   #39 = NameAndType        #13:#38       // MODULE$:Lscala/runtime/ScalaRunTime$;
   #40 = Fieldref           #37.#39       // scala/runtime/ScalaRunTime$.MODULE$:Lscala/runtime/ScalaRunTime$;
   #41 = Utf8               java/lang/String
   #42 = Class              #41           // java/lang/String
   #43 = Utf8               [Ljava/lang/Object;
   #44 = Class              #43           // "[Ljava/lang/Object;"
   #45 = Utf8               wrapRefArray
   #46 = Utf8               ([Ljava/lang/Object;)Lscala/collection/immutable/ArraySeq;
   #47 = NameAndType        #45:#46       // wrapRefArray:([Ljava/lang/Object;)Lscala/collection/immutable/ArraySeq;
   #48 = Methodref          #37.#47       // scala/runtime/ScalaRunTime$.wrapRefArray:([Ljava/lang/Object;)Lscala/collection/immutable/ArraySeq;
   #49 = Utf8               scala/collection/immutable/Seq$
   #50 = Class              #49           // scala/collection/immutable/Seq$
   #51 = Utf8               apply
   #52 = Utf8               (Lscala/collection/immutable/Seq;)Lscala/collection/SeqOps;
   #53 = NameAndType        #51:#52       // apply:(Lscala/collection/immutable/Seq;)Lscala/collection/SeqOps;
   #54 = Methodref          #50.#53       // scala/collection/immutable/Seq$.apply:(Lscala/collection/immutable/Seq;)Lscala/collection/SeqOps;
   #55 = Utf8               scala/collection/immutable/Seq
   #56 = Class              #55           // scala/collection/immutable/Seq
   #57 = Utf8               (Lscala/collection/immutable/Seq;)V
   #58 = NameAndType        #17:#57       // "<init>":(Lscala/collection/immutable/Seq;)V
   #59 = Methodref          #26.#58       // os/Shellable."<init>":(Lscala/collection/immutable/Seq;)V
   #60 = Utf8               this
   #61 = Utf8               Ljava/lang/String;
   #62 = Utf8               SymbolShellable
   #63 = Utf8               (Lscala/Symbol;)Los/Shellable;
   #64 = Utf8               scala/Symbol
   #65 = Class              #64           // scala/Symbol
   #66 = Utf8               name
   #67 = Utf8               ()Ljava/lang/String;
   #68 = NameAndType        #66:#67       // name:()Ljava/lang/String;
   #69 = Methodref          #65.#68       // scala/Symbol.name:()Ljava/lang/String;
   #70 = Utf8               Lscala/Symbol;
   #71 = Utf8               PathShellable
   #72 = Utf8               (Los/Path;)Los/Shellable;
   #73 = Utf8               os/Path
   #74 = Class              #73           // os/Path
   #75 = Utf8               toString
   #76 = NameAndType        #75:#67       // toString:()Ljava/lang/String;
   #77 = Methodref          #74.#76       // os/Path.toString:()Ljava/lang/String;
   #78 = Utf8               Los/Path;
   #79 = Utf8               RelPathShellable
   #80 = Utf8               (Los/RelPath;)Los/Shellable;
   #81 = Utf8               os/RelPath
   #82 = Class              #81           // os/RelPath
   #83 = Methodref          #82.#76       // os/RelPath.toString:()Ljava/lang/String;
   #84 = Utf8               Los/RelPath;
   #85 = Utf8               NumericShellable
   #86 = Utf8               (Ljava/lang/Object;Lscala/math/Numeric;)Los/Shellable;
   #87 = Utf8               <T:Ljava/lang/Object;>(TT;Lscala/math/Numeric<TT;>;)Los/Shellable;
   #88 = Utf8               evidence$1
   #89 = Methodref          #4.#76        // java/lang/Object.toString:()Ljava/lang/String;
   #90 = Utf8               Ljava/lang/Object;
   #91 = Utf8               Lscala/math/Numeric;
   #92 = Utf8               IterableShellable
   #93 = Utf8               (Lscala/collection/Iterable;Lscala/Function1;)Los/Shellable;
   #94 = Utf8               <T:Ljava/lang/Object;>(Lscala/collection/Iterable<TT;>;Lscala/Function1<TT;Los/Shellable;>;)Los/Shellable;
   #95 = Utf8               f
   #96 = Utf8               scala/collection/Iterable
   #97 = Class              #96           // scala/collection/Iterable
   #98 = Utf8               toSeq
   #99 = Utf8               ()Lscala/collection/immutable/Seq;
  #100 = NameAndType        #98:#99       // toSeq:()Lscala/collection/immutable/Seq;
  #101 = InterfaceMethodref #97.#100      // scala/collection/Iterable.toSeq:()Lscala/collection/immutable/Seq;
  #102 = Utf8               (Ljava/lang/Object;)Ljava/lang/Object;
  #103 = MethodType         #102          //  (Ljava/lang/Object;)Ljava/lang/Object;
  #104 = Utf8               $anonfun$IterableShellable$1
  #105 = Utf8               (Lscala/Function1;Ljava/lang/Object;)Lscala/collection/immutable/Seq;
  #106 = NameAndType        #104:#105     // $anonfun$IterableShellable$1:(Lscala/Function1;Ljava/lang/Object;)Lscala/collection/immutable/Seq;
  #107 = Methodref          #2.#106       // os/Shellable$.$anonfun$IterableShellable$1:(Lscala/Function1;Ljava/lang/Object;)Lscala/collection/immutable/Seq;
  #108 = MethodHandle       6:#107        // REF_invokeStatic os/Shellable$.$anonfun$IterableShellable$1:(Lscala/Function1;Ljava/lang/Object;)Lscala/collection/immutable/Seq;
  #109 = Utf8               (Ljava/lang/Object;)Lscala/collection/immutable/Seq;
  #110 = MethodType         #109          //  (Ljava/lang/Object;)Lscala/collection/immutable/Seq;
  #111 = Integer            5
  #112 = Integer            1
  #113 = Utf8               java/lang/invoke/LambdaMetafactory
  #114 = Class              #113          // java/lang/invoke/LambdaMetafactory
  #115 = Utf8               altMetafactory
  #116 = Utf8               (Ljava/lang/invoke/MethodHandles$Lookup;Ljava/lang/String;Ljava/lang/invoke/MethodType;[Ljava/lang/Object;)Ljava/lang/invoke/CallSite;
  #117 = NameAndType        #115:#116     // altMetafactory:(Ljava/lang/invoke/MethodHandles$Lookup;Ljava/lang/String;Ljava/lang/invoke/MethodType;[Ljava/lang/Object;)Ljava/lang/invoke/CallSite;
  #118 = Methodref          #114.#117     // java/lang/invoke/LambdaMetafactory.altMetafactory:(Ljava/lang/invoke/MethodHandles$Lookup;Ljava/lang/String;Ljava/lang/invoke/MethodType;[Ljava/lang/Object;)Ljava/lang/invoke/CallSite;
  #119 = MethodHandle       6:#118        // REF_invokeStatic java/lang/invoke/LambdaMetafactory.altMetafactory:(Ljava/lang/invoke/MethodHandles$Lookup;Ljava/lang/String;Ljava/lang/invoke/MethodType;[Ljava/lang/Object;)Ljava/lang/invoke/CallSite;
  #120 = Utf8               (Lscala/Function1;)Lscala/Function1;
  #121 = NameAndType        #51:#120      // apply:(Lscala/Function1;)Lscala/Function1;
  #122 = InvokeDynamic      #0:#121       // #0:apply:(Lscala/Function1;)Lscala/Function1;
  #123 = Utf8               flatMap
  #124 = Utf8               (Lscala/Function1;)Ljava/lang/Object;
  #125 = NameAndType        #123:#124     // flatMap:(Lscala/Function1;)Ljava/lang/Object;
  #126 = InterfaceMethodref #56.#125      // scala/collection/immutable/Seq.flatMap:(Lscala/Function1;)Ljava/lang/Object;
  #127 = Utf8               Lscala/collection/Iterable;
  #128 = Utf8               Lscala/Function1;
  #129 = Utf8               ArrayShellable
  #130 = Utf8               (Ljava/lang/Object;Lscala/Function1;)Los/Shellable;
  #131 = Utf8               <T:Ljava/lang/Object;>(Ljava/lang/Object;Lscala/Function1<TT;Los/Shellable;>;)Los/Shellable;
  #132 = Utf8               scala/Predef$
  #133 = Class              #132          // scala/Predef$
  #134 = Utf8               Lscala/Predef$;
  #135 = NameAndType        #13:#134      // MODULE$:Lscala/Predef$;
  #136 = Fieldref           #133.#135     // scala/Predef$.MODULE$:Lscala/Predef$;
  #137 = Utf8               scala/collection/ArrayOps$
  #138 = Class              #137          // scala/collection/ArrayOps$
  #139 = Utf8               Lscala/collection/ArrayOps$;
  #140 = NameAndType        #13:#139      // MODULE$:Lscala/collection/ArrayOps$;
  #141 = Fieldref           #138.#140     // scala/collection/ArrayOps$.MODULE$:Lscala/collection/ArrayOps$;
  #142 = Utf8               genericArrayOps
  #143 = NameAndType        #142:#102     // genericArrayOps:(Ljava/lang/Object;)Ljava/lang/Object;
  #144 = Methodref          #133.#143     // scala/Predef$.genericArrayOps:(Ljava/lang/Object;)Ljava/lang/Object;
  #145 = Utf8               $anonfun$ArrayShellable$1
  #146 = NameAndType        #145:#105     // $anonfun$ArrayShellable$1:(Lscala/Function1;Ljava/lang/Object;)Lscala/collection/immutable/Seq;
  #147 = Methodref          #2.#146       // os/Shellable$.$anonfun$ArrayShellable$1:(Lscala/Function1;Ljava/lang/Object;)Lscala/collection/immutable/Seq;
  #148 = MethodHandle       6:#147        // REF_invokeStatic os/Shellable$.$anonfun$ArrayShellable$1:(Lscala/Function1;Ljava/lang/Object;)Lscala/collection/immutable/Seq;
  #149 = InvokeDynamic      #1:#121       // #1:apply:(Lscala/Function1;)Lscala/Function1;
  #150 = Utf8               scala/reflect/ClassTag$
  #151 = Class              #150          // scala/reflect/ClassTag$
  #152 = Utf8               Lscala/reflect/ClassTag$;
  #153 = NameAndType        #13:#152      // MODULE$:Lscala/reflect/ClassTag$;
  #154 = Fieldref           #151.#153     // scala/reflect/ClassTag$.MODULE$:Lscala/reflect/ClassTag$;
  #155 = Utf8               (Ljava/lang/Class;)Lscala/reflect/ClassTag;
  #156 = NameAndType        #51:#155      // apply:(Ljava/lang/Class;)Lscala/reflect/ClassTag;
  #157 = Methodref          #151.#156     // scala/reflect/ClassTag$.apply:(Ljava/lang/Class;)Lscala/reflect/ClassTag;
  #158 = Utf8               flatMap$extension
  #159 = Utf8               (Ljava/lang/Object;Lscala/Function1;Lscala/reflect/ClassTag;)Ljava/lang/Object;
  #160 = NameAndType        #158:#159     // flatMap$extension:(Ljava/lang/Object;Lscala/Function1;Lscala/reflect/ClassTag;)Ljava/lang/Object;
  #161 = Methodref          #138.#160     // scala/collection/ArrayOps$.flatMap$extension:(Ljava/lang/Object;Lscala/Function1;Lscala/reflect/ClassTag;)Ljava/lang/Object;
  #162 = Utf8               copyArrayToImmutableIndexedSeq
  #163 = Utf8               (Ljava/lang/Object;)Lscala/collection/immutable/IndexedSeq;
  #164 = NameAndType        #162:#163     // copyArrayToImmutableIndexedSeq:(Ljava/lang/Object;)Lscala/collection/immutable/IndexedSeq;
  #165 = Methodref          #133.#164     // scala/Predef$.copyArrayToImmutableIndexedSeq:(Ljava/lang/Object;)Lscala/collection/immutable/IndexedSeq;
  #166 = Utf8               (Lscala/collection/immutable/Seq;)Los/Shellable;
  #167 = Utf8               (Lscala/collection/immutable/Seq<Ljava/lang/String;>;)Los/Shellable;
  #168 = Utf8               value
  #169 = Utf8               Lscala/collection/immutable/Seq;
  #170 = Utf8               unapply
  #171 = Utf8               (Los/Shellable;)Lscala/Option;
  #172 = Utf8               (Los/Shellable;)Lscala/Option<Lscala/collection/immutable/Seq<Ljava/lang/String;>;>;
  #173 = Utf8               x$0
  #174 = Utf8               scala/None$
  #175 = Class              #174          // scala/None$
  #176 = Utf8               Lscala/None$;
  #177 = NameAndType        #13:#176      // MODULE$:Lscala/None$;
  #178 = Fieldref           #175.#177     // scala/None$.MODULE$:Lscala/None$;
  #179 = Utf8               scala/Some
  #180 = Class              #179          // scala/Some
  #181 = NameAndType        #168:#99      // value:()Lscala/collection/immutable/Seq;
  #182 = Methodref          #26.#181      // os/Shellable.value:()Lscala/collection/immutable/Seq;
  #183 = Utf8               (Ljava/lang/Object;)V
  #184 = NameAndType        #17:#183      // "<init>":(Ljava/lang/Object;)V
  #185 = Methodref          #180.#184     // scala/Some."<init>":(Ljava/lang/Object;)V
  #186 = Utf8               Los/Shellable;
  #187 = Utf8               scala/Option
  #188 = Class              #187          // scala/Option
  #189 = Utf8               writeReplace
  #190 = Utf8               ()Ljava/lang/Object;
  #191 = Utf8               scala/runtime/ModuleSerializationProxy
  #192 = Class              #191          // scala/runtime/ModuleSerializationProxy
  #193 = Utf8               (Ljava/lang/Class;)V
  #194 = NameAndType        #17:#193      // "<init>":(Ljava/lang/Class;)V
  #195 = Methodref          #192.#194     // scala/runtime/ModuleSerializationProxy."<init>":(Ljava/lang/Class;)V
  #196 = Utf8               f$1
  #197 = Utf8               x$2
  #198 = Utf8               scala/Function1
  #199 = Class              #198          // scala/Function1
  #200 = NameAndType        #51:#102      // apply:(Ljava/lang/Object;)Ljava/lang/Object;
  #201 = InterfaceMethodref #199.#200     // scala/Function1.apply:(Ljava/lang/Object;)Ljava/lang/Object;
  #202 = Utf8               f$2
  #203 = Utf8               x$3
  #204 = Methodref          #4.#18        // java/lang/Object."<init>":()V
  #205 = Utf8               $deserializeLambda$
  #206 = Utf8               (Ljava/lang/invoke/SerializedLambda;)Ljava/lang/Object;
  #207 = Utf8               scala/runtime/LambdaDeserialize
  #208 = Class              #207          // scala/runtime/LambdaDeserialize
  #209 = Utf8               bootstrap
  #210 = Utf8               (Ljava/lang/invoke/MethodHandles$Lookup;Ljava/lang/String;Ljava/lang/invoke/MethodType;[Ljava/lang/invoke/MethodHandle;)Ljava/lang/invoke/CallSite;
  #211 = NameAndType        #209:#210     // bootstrap:(Ljava/lang/invoke/MethodHandles$Lookup;Ljava/lang/String;Ljava/lang/invoke/MethodType;[Ljava/lang/invoke/MethodHandle;)Ljava/lang/invoke/CallSite;
  #212 = Methodref          #208.#211     // scala/runtime/LambdaDeserialize.bootstrap:(Ljava/lang/invoke/MethodHandles$Lookup;Ljava/lang/String;Ljava/lang/invoke/MethodType;[Ljava/lang/invoke/MethodHandle;)Ljava/lang/invoke/CallSite;
  #213 = MethodHandle       6:#212        // REF_invokeStatic scala/runtime/LambdaDeserialize.bootstrap:(Ljava/lang/invoke/MethodHandles$Lookup;Ljava/lang/String;Ljava/lang/invoke/MethodType;[Ljava/lang/invoke/MethodHandle;)Ljava/lang/invoke/CallSite;
  #214 = Utf8               lambdaDeserialize
  #215 = NameAndType        #214:#206     // lambdaDeserialize:(Ljava/lang/invoke/SerializedLambda;)Ljava/lang/Object;
  #216 = InvokeDynamic      #2:#215       // #2:lambdaDeserialize:(Ljava/lang/invoke/SerializedLambda;)Ljava/lang/Object;
  #217 = Utf8               Code
  #218 = Utf8               LineNumberTable
  #219 = Utf8               LocalVariableTable
  #220 = Utf8               MethodParameters
  #221 = Utf8               Signature
  #222 = Utf8               StackMapTable
  #223 = Utf8               InnerClasses
  #224 = Utf8               SourceFile
  #225 = Utf8               BootstrapMethods
  #226 = Utf8               ScalaInlineInfo
  #227 = Utf8               Scala
{
  public static final os.Shellable$ MODULE$;
    descriptor: Los/Shellable$;
    flags: (0x0019) ACC_PUBLIC, ACC_STATIC, ACC_FINAL

  public static {};
    descriptor: ()V
    flags: (0x0009) ACC_PUBLIC, ACC_STATIC
    Code:
      stack=2, locals=0, args_size=0
         0: new           #2                  // class os/Shellable$
         3: dup
         4: invokespecial #19                 // Method "<init>":()V
         7: putstatic     #21                 // Field MODULE$:Los/Shellable$;
        10: return
      LineNumberTable:
        line 210: 0

  public os.Shellable StringShellable(java.lang.String);
    descriptor: (Ljava/lang/String;)Los/Shellable;
    flags: (0x0001) ACC_PUBLIC
    Code:
      stack=8, locals=2, args_size=2
         0: new           #26                 // class os/Shellable
         3: dup
         4: getstatic     #31                 // Field scala/package$.MODULE$:Lscala/package$;
         7: invokevirtual #35                 // Method scala/package$.Seq:()Lscala/collection/immutable/Seq$;
        10: getstatic     #40                 // Field scala/runtime/ScalaRunTime$.MODULE$:Lscala/runtime/ScalaRunTime$;
        13: iconst_1
        14: anewarray     #42                 // class java/lang/String
        17: dup
        18: iconst_0
        19: aload_1
        20: aastore
        21: checkcast     #44                 // class "[Ljava/lang/Object;"
        24: invokevirtual #48                 // Method scala/runtime/ScalaRunTime$.wrapRefArray:([Ljava/lang/Object;)Lscala/collection/immutable/ArraySeq;
        27: invokevirtual #54                 // Method scala/collection/immutable/Seq$.apply:(Lscala/collection/immutable/Seq;)Lscala/collection/SeqOps;
        30: checkcast     #56                 // class scala/collection/immutable/Seq
        33: invokespecial #59                 // Method os/Shellable."<init>":(Lscala/collection/immutable/Seq;)V
        36: areturn
      LineNumberTable:
        line 211: 0
      LocalVariableTable:
        Start  Length  Slot  Name   Signature
            0      37     0  this   Los/Shellable$;
            0      37     1     s   Ljava/lang/String;
    MethodParameters:
      Name                           Flags
      s                              final

  public os.Shellable SymbolShellable(scala.Symbol);
    descriptor: (Lscala/Symbol;)Los/Shellable;
    flags: (0x0001) ACC_PUBLIC
    Code:
      stack=8, locals=2, args_size=2
         0: new           #26                 // class os/Shellable
         3: dup
         4: getstatic     #31                 // Field scala/package$.MODULE$:Lscala/package$;
         7: invokevirtual #35                 // Method scala/package$.Seq:()Lscala/collection/immutable/Seq$;
        10: getstatic     #40                 // Field scala/runtime/ScalaRunTime$.MODULE$:Lscala/runtime/ScalaRunTime$;
        13: iconst_1
        14: anewarray     #42                 // class java/lang/String
        17: dup
        18: iconst_0
        19: aload_1
        20: invokevirtual #69                 // Method scala/Symbol.name:()Ljava/lang/String;
        23: aastore
        24: checkcast     #44                 // class "[Ljava/lang/Object;"
        27: invokevirtual #48                 // Method scala/runtime/ScalaRunTime$.wrapRefArray:([Ljava/lang/Object;)Lscala/collection/immutable/ArraySeq;
        30: invokevirtual #54                 // Method scala/collection/immutable/Seq$.apply:(Lscala/collection/immutable/Seq;)Lscala/collection/SeqOps;
        33: checkcast     #56                 // class scala/collection/immutable/Seq
        36: invokespecial #59                 // Method os/Shellable."<init>":(Lscala/collection/immutable/Seq;)V
        39: areturn
      LineNumberTable:
        line 213: 0
      LocalVariableTable:
        Start  Length  Slot  Name   Signature
            0      40     0  this   Los/Shellable$;
            0      40     1     s   Lscala/Symbol;
    MethodParameters:
      Name                           Flags
      s                              final

  public os.Shellable PathShellable(os.Path);
    descriptor: (Los/Path;)Los/Shellable;
    flags: (0x0001) ACC_PUBLIC
    Code:
      stack=8, locals=2, args_size=2
         0: new           #26                 // class os/Shellable
         3: dup
         4: getstatic     #31                 // Field scala/package$.MODULE$:Lscala/package$;
         7: invokevirtual #35                 // Method scala/package$.Seq:()Lscala/collection/immutable/Seq$;
        10: getstatic     #40                 // Field scala/runtime/ScalaRunTime$.MODULE$:Lscala/runtime/ScalaRunTime$;
        13: iconst_1
        14: anewarray     #42                 // class java/lang/String
        17: dup
        18: iconst_0
        19: aload_1
        20: invokevirtual #77                 // Method os/Path.toString:()Ljava/lang/String;
        23: aastore
        24: checkcast     #44                 // class "[Ljava/lang/Object;"
        27: invokevirtual #48                 // Method scala/runtime/ScalaRunTime$.wrapRefArray:([Ljava/lang/Object;)Lscala/collection/immutable/ArraySeq;
        30: invokevirtual #54                 // Method scala/collection/immutable/Seq$.apply:(Lscala/collection/immutable/Seq;)Lscala/collection/SeqOps;
        33: checkcast     #56                 // class scala/collection/immutable/Seq
        36: invokespecial #59                 // Method os/Shellable."<init>":(Lscala/collection/immutable/Seq;)V
        39: areturn
      LineNumberTable:
        line 214: 0
      LocalVariableTable:
        Start  Length  Slot  Name   Signature
            0      40     0  this   Los/Shellable$;
            0      40     1     s   Los/Path;
    MethodParameters:
      Name                           Flags
      s                              final

  public os.Shellable RelPathShellable(os.RelPath);
    descriptor: (Los/RelPath;)Los/Shellable;
    flags: (0x0001) ACC_PUBLIC
    Code:
      stack=8, locals=2, args_size=2
         0: new           #26                 // class os/Shellable
         3: dup
         4: getstatic     #31                 // Field scala/package$.MODULE$:Lscala/package$;
         7: invokevirtual #35                 // Method scala/package$.Seq:()Lscala/collection/immutable/Seq$;
        10: getstatic     #40                 // Field scala/runtime/ScalaRunTime$.MODULE$:Lscala/runtime/ScalaRunTime$;
        13: iconst_1
        14: anewarray     #42                 // class java/lang/String
        17: dup
        18: iconst_0
        19: aload_1
        20: invokevirtual #83                 // Method os/RelPath.toString:()Ljava/lang/String;
        23: aastore
        24: checkcast     #44                 // class "[Ljava/lang/Object;"
        27: invokevirtual #48                 // Method scala/runtime/ScalaRunTime$.wrapRefArray:([Ljava/lang/Object;)Lscala/collection/immutable/ArraySeq;
        30: invokevirtual #54                 // Method scala/collection/immutable/Seq$.apply:(Lscala/collection/immutable/Seq;)Lscala/collection/SeqOps;
        33: checkcast     #56                 // class scala/collection/immutable/Seq
        36: invokespecial #59                 // Method os/Shellable."<init>":(Lscala/collection/immutable/Seq;)V
        39: areturn
      LineNumberTable:
        line 215: 0
      LocalVariableTable:
        Start  Length  Slot  Name   Signature
            0      40     0  this   Los/Shellable$;
            0      40     1     s   Los/RelPath;
    MethodParameters:
      Name                           Flags
      s                              final

  public <T extends java.lang.Object> os.Shellable NumericShellable(T, scala.math.Numeric<T>);
    descriptor: (Ljava/lang/Object;Lscala/math/Numeric;)Los/Shellable;
    flags: (0x0001) ACC_PUBLIC
    Code:
      stack=8, locals=3, args_size=3
         0: new           #26                 // class os/Shellable
         3: dup
         4: getstatic     #31                 // Field scala/package$.MODULE$:Lscala/package$;
         7: invokevirtual #35                 // Method scala/package$.Seq:()Lscala/collection/immutable/Seq$;
        10: getstatic     #40                 // Field scala/runtime/ScalaRunTime$.MODULE$:Lscala/runtime/ScalaRunTime$;
        13: iconst_1
        14: anewarray     #42                 // class java/lang/String
        17: dup
        18: iconst_0
        19: aload_1
        20: invokevirtual #89                 // Method java/lang/Object.toString:()Ljava/lang/String;
        23: aastore
        24: checkcast     #44                 // class "[Ljava/lang/Object;"
        27: invokevirtual #48                 // Method scala/runtime/ScalaRunTime$.wrapRefArray:([Ljava/lang/Object;)Lscala/collection/immutable/ArraySeq;
        30: invokevirtual #54                 // Method scala/collection/immutable/Seq$.apply:(Lscala/collection/immutable/Seq;)Lscala/collection/SeqOps;
        33: checkcast     #56                 // class scala/collection/immutable/Seq
        36: invokespecial #59                 // Method os/Shellable."<init>":(Lscala/collection/immutable/Seq;)V
        39: areturn
      LineNumberTable:
        line 216: 0
      LocalVariableTable:
        Start  Length  Slot  Name   Signature
            0      40     0  this   Los/Shellable$;
            0      40     1     s   Ljava/lang/Object;
            0      40     2 evidence$1   Lscala/math/Numeric;
    Signature: #87                          // <T:Ljava/lang/Object;>(TT;Lscala/math/Numeric<TT;>;)Los/Shellable;
    MethodParameters:
      Name                           Flags
      s                              final
      evidence$1                     final

  public <T extends java.lang.Object> os.Shellable IterableShellable(scala.collection.Iterable<T>, scala.Function1<T, os.Shellable>);
    descriptor: (Lscala/collection/Iterable;Lscala/Function1;)Los/Shellable;
    flags: (0x0001) ACC_PUBLIC
    Code:
      stack=4, locals=3, args_size=3
         0: new           #26                 // class os/Shellable
         3: dup
         4: aload_1
         5: invokeinterface #101,  1          // InterfaceMethod scala/collection/Iterable.toSeq:()Lscala/collection/immutable/Seq;
        10: aload_2
        11: invokedynamic #122,  0            // InvokeDynamic #0:apply:(Lscala/Function1;)Lscala/Function1;
        16: invokeinterface #126,  2          // InterfaceMethod scala/collection/immutable/Seq.flatMap:(Lscala/Function1;)Ljava/lang/Object;
        21: checkcast     #56                 // class scala/collection/immutable/Seq
        24: invokespecial #59                 // Method os/Shellable."<init>":(Lscala/collection/immutable/Seq;)V
        27: areturn
      LineNumberTable:
        line 219: 0
      LocalVariableTable:
        Start  Length  Slot  Name   Signature
            0      28     0  this   Los/Shellable$;
            0      28     1     s   Lscala/collection/Iterable;
            0      28     2     f   Lscala/Function1;
    Signature: #94                          // <T:Ljava/lang/Object;>(Lscala/collection/Iterable<TT;>;Lscala/Function1<TT;Los/Shellable;>;)Los/Shellable;
    MethodParameters:
      Name                           Flags
      s                              final
      f                              final

  public <T extends java.lang.Object> os.Shellable ArrayShellable(java.lang.Object, scala.Function1<T, os.Shellable>);
    descriptor: (Ljava/lang/Object;Lscala/Function1;)Los/Shellable;
    flags: (0x0001) ACC_PUBLIC
    Code:
      stack=8, locals=3, args_size=3
         0: new           #26                 // class os/Shellable
         3: dup
         4: getstatic     #136                // Field scala/Predef$.MODULE$:Lscala/Predef$;
         7: getstatic     #141                // Field scala/collection/ArrayOps$.MODULE$:Lscala/collection/ArrayOps$;
        10: getstatic     #136                // Field scala/Predef$.MODULE$:Lscala/Predef$;
        13: aload_1
        14: invokevirtual #144                // Method scala/Predef$.genericArrayOps:(Ljava/lang/Object;)Ljava/lang/Object;
        17: aload_2
        18: invokedynamic #149,  0            // InvokeDynamic #1:apply:(Lscala/Function1;)Lscala/Function1;
        23: getstatic     #154                // Field scala/reflect/ClassTag$.MODULE$:Lscala/reflect/ClassTag$;
        26: ldc           #42                 // class java/lang/String
        28: invokevirtual #157                // Method scala/reflect/ClassTag$.apply:(Ljava/lang/Class;)Lscala/reflect/ClassTag;
        31: invokevirtual #161                // Method scala/collection/ArrayOps$.flatMap$extension:(Ljava/lang/Object;Lscala/Function1;Lscala/reflect/ClassTag;)Ljava/lang/Object;
        34: invokevirtual #165                // Method scala/Predef$.copyArrayToImmutableIndexedSeq:(Ljava/lang/Object;)Lscala/collection/immutable/IndexedSeq;
        37: invokespecial #59                 // Method os/Shellable."<init>":(Lscala/collection/immutable/Seq;)V
        40: areturn
      LineNumberTable:
        line 222: 0
      LocalVariableTable:
        Start  Length  Slot  Name   Signature
            0      41     0  this   Los/Shellable$;
            0      41     1     s   Ljava/lang/Object;
            0      41     2     f   Lscala/Function1;
    Signature: #131                         // <T:Ljava/lang/Object;>(Ljava/lang/Object;Lscala/Function1<TT;Los/Shellable;>;)Los/Shellable;
    MethodParameters:
      Name                           Flags
      s                              final
      f                              final

  public os.Shellable apply(scala.collection.immutable.Seq<java.lang.String>);
    descriptor: (Lscala/collection/immutable/Seq;)Los/Shellable;
    flags: (0x0001) ACC_PUBLIC
    Code:
      stack=3, locals=2, args_size=2
         0: new           #26                 // class os/Shellable
         3: dup
         4: aload_1
         5: invokespecial #59                 // Method os/Shellable."<init>":(Lscala/collection/immutable/Seq;)V
         8: areturn
      LineNumberTable:
        line 209: 0
      LocalVariableTable:
        Start  Length  Slot  Name   Signature
            0       9     0  this   Los/Shellable$;
            0       9     1 value   Lscala/collection/immutable/Seq;
    Signature: #167                         // (Lscala/collection/immutable/Seq<Ljava/lang/String;>;)Los/Shellable;
    MethodParameters:
      Name                           Flags
      value                          final

  public scala.Option<scala.collection.immutable.Seq<java.lang.String>> unapply(os.Shellable);
    descriptor: (Los/Shellable;)Lscala/Option;
    flags: (0x0001) ACC_PUBLIC
    Code:
      stack=3, locals=2, args_size=2
         0: aload_1
         1: ifnonnull     10
         4: getstatic     #178                // Field scala/None$.MODULE$:Lscala/None$;
         7: goto          21
        10: new           #180                // class scala/Some
        13: dup
        14: aload_1
        15: invokevirtual #182                // Method os/Shellable.value:()Lscala/collection/immutable/Seq;
        18: invokespecial #185                // Method scala/Some."<init>":(Ljava/lang/Object;)V
        21: areturn
      StackMapTable: number_of_entries = 2
        frame_type = 10 /* same */
        frame_type = 74 /* same_locals_1_stack_item */
          stack = [ class scala/Option ]
      LineNumberTable:
        line 209: 0
      LocalVariableTable:
        Start  Length  Slot  Name   Signature
            0      22     0  this   Los/Shellable$;
            0      22     1   x$0   Los/Shellable;
    Signature: #172                         // (Los/Shellable;)Lscala/Option<Lscala/collection/immutable/Seq<Ljava/lang/String;>;>;
    MethodParameters:
      Name                           Flags
      x$0                            final

  private java.lang.Object writeReplace();
    descriptor: ()Ljava/lang/Object;
    flags: (0x0002) ACC_PRIVATE
    Code:
      stack=3, locals=1, args_size=1
         0: new           #192                // class scala/runtime/ModuleSerializationProxy
         3: dup
         4: ldc           #2                  // class os/Shellable$
         6: invokespecial #195                // Method scala/runtime/ModuleSerializationProxy."<init>":(Ljava/lang/Class;)V
         9: areturn
      LineNumberTable:
        line 210: 0
      LocalVariableTable:
        Start  Length  Slot  Name   Signature
            0      10     0  this   Los/Shellable$;

  public static final scala.collection.immutable.Seq $anonfun$IterableShellable$1(scala.Function1, java.lang.Object);
    descriptor: (Lscala/Function1;Ljava/lang/Object;)Lscala/collection/immutable/Seq;
    flags: (0x1019) ACC_PUBLIC, ACC_STATIC, ACC_FINAL, ACC_SYNTHETIC
    Code:
      stack=2, locals=2, args_size=2
         0: aload_0
         1: aload_1
         2: invokeinterface #201,  2          // InterfaceMethod scala/Function1.apply:(Ljava/lang/Object;)Ljava/lang/Object;
         7: checkcast     #26                 // class os/Shellable
        10: invokevirtual #182                // Method os/Shellable.value:()Lscala/collection/immutable/Seq;
        13: areturn
      LineNumberTable:
        line 219: 0
      LocalVariableTable:
        Start  Length  Slot  Name   Signature
            0      14     0   f$1   Lscala/Function1;
            0      14     1   x$2   Ljava/lang/Object;
    MethodParameters:
      Name                           Flags
      f$1                            final
      x$2                            final

  public static final scala.collection.immutable.Seq $anonfun$ArrayShellable$1(scala.Function1, java.lang.Object);
    descriptor: (Lscala/Function1;Ljava/lang/Object;)Lscala/collection/immutable/Seq;
    flags: (0x1019) ACC_PUBLIC, ACC_STATIC, ACC_FINAL, ACC_SYNTHETIC
    Code:
      stack=2, locals=2, args_size=2
         0: aload_0
         1: aload_1
         2: invokeinterface #201,  2          // InterfaceMethod scala/Function1.apply:(Ljava/lang/Object;)Ljava/lang/Object;
         7: checkcast     #26                 // class os/Shellable
        10: invokevirtual #182                // Method os/Shellable.value:()Lscala/collection/immutable/Seq;
        13: areturn
      LineNumberTable:
        line 222: 0
      LocalVariableTable:
        Start  Length  Slot  Name   Signature
            0      14     0   f$2   Lscala/Function1;
            0      14     1   x$3   Ljava/lang/Object;
    MethodParameters:
      Name                           Flags
      f$2                            final
      x$3                            final

  private os.Shellable$();
    descriptor: ()V
    flags: (0x0002) ACC_PRIVATE
    Code:
      stack=1, locals=1, args_size=1
         0: aload_0
         1: invokespecial #204                // Method java/lang/Object."<init>":()V
         4: return
      LineNumberTable:
        line 232: 0
        line 210: 4
      LocalVariableTable:
        Start  Length  Slot  Name   Signature
            0       5     0  this   Los/Shellable$;

  private static java.lang.Object $deserializeLambda$(java.lang.invoke.SerializedLambda);
    descriptor: (Ljava/lang/invoke/SerializedLambda;)Ljava/lang/Object;
    flags: (0x100a) ACC_PRIVATE, ACC_STATIC, ACC_SYNTHETIC
    Code:
      stack=1, locals=1, args_size=1
         0: aload_0
         1: invokedynamic #216,  0            // InvokeDynamic #2:lambdaDeserialize:(Ljava/lang/invoke/SerializedLambda;)Ljava/lang/Object;
         6: areturn
}
InnerClasses:
  public static final #12= #9 of #11;     // Lookup=class java/lang/invoke/MethodHandles$Lookup of class java/lang/invoke/MethodHandles
SourceFile: "Model.scala"
BootstrapMethods:
  0: #119 REF_invokeStatic java/lang/invoke/LambdaMetafactory.altMetafactory:(Ljava/lang/invoke/MethodHandles$Lookup;Ljava/lang/String;Ljava/lang/invoke/MethodType;[Ljava/lang/Object;)Ljava/lang/invoke/CallSite;
    Method arguments:
      #103 (Ljava/lang/Object;)Ljava/lang/Object;
      #108 REF_invokeStatic os/Shellable$.$anonfun$IterableShellable$1:(Lscala/Function1;Ljava/lang/Object;)Lscala/collection/immutable/Seq;
      #110 (Ljava/lang/Object;)Lscala/collection/immutable/Seq;
      #111 5
      #112 1
      #110 (Ljava/lang/Object;)Lscala/collection/immutable/Seq;
  1: #119 REF_invokeStatic java/lang/invoke/LambdaMetafactory.altMetafactory:(Ljava/lang/invoke/MethodHandles$Lookup;Ljava/lang/String;Ljava/lang/invoke/MethodType;[Ljava/lang/Object;)Ljava/lang/invoke/CallSite;
    Method arguments:
      #103 (Ljava/lang/Object;)Ljava/lang/Object;
      #148 REF_invokeStatic os/Shellable$.$anonfun$ArrayShellable$1:(Lscala/Function1;Ljava/lang/Object;)Lscala/collection/immutable/Seq;
      #110 (Ljava/lang/Object;)Lscala/collection/immutable/Seq;
      #111 5
      #112 1
      #110 (Ljava/lang/Object;)Lscala/collection/immutable/Seq;
  2: #213 REF_invokeStatic scala/runtime/LambdaDeserialize.bootstrap:(Ljava/lang/invoke/MethodHandles$Lookup;Ljava/lang/String;Ljava/lang/invoke/MethodType;[Ljava/lang/invoke/MethodHandle;)Ljava/lang/invoke/CallSite;
    Method arguments:
      #148 REF_invokeStatic os/Shellable$.$anonfun$ArrayShellable$1:(Lscala/Function1;Ljava/lang/Object;)Lscala/collection/immutable/Seq;
      #108 REF_invokeStatic os/Shellable$.$anonfun$IterableShellable$1:(Lscala/Function1;Ljava/lang/Object;)Lscala/collection/immutable/Seq;
  ScalaInlineInfo: length = 0x45 (unknown attribute)
   01 01 00 0D 00 91 00 69 01 00 68 00 69 01 00 11
   00 10 01 00 81 00 82 01 00 5C 00 5D 01 00 55 00
   56 01 00 47 00 48 01 00 4F 00 50 01 00 16 00 17
   01 00 3E 00 3F 01 00 33 00 A6 01 00 AA 00 AB 01
   00 BD 00 BE 01
  Scala: length = 0x0 (unknown attribute)

