Classfile /Users/mw/Projects/slang-braindump/.jar/jar11/assemble/slang-braindump/assemble/content/os/SubProcess$InputStream.class
  Last modified May 29, 2022; size 3606 bytes
  SHA-256 checksum a1f36353e24daa960a00c67302d61beed4eff0f823fa1605b05a6fc31cede391
  Compiled from "SubProcess.scala"
public class os.SubProcess$InputStream extends java.io.OutputStream implements java.io.DataOutput
  minor version: 0
  major version: 52
  flags: (0x0021) ACC_PUBLIC, ACC_SUPER
  this_class: #2                          // os/SubProcess$InputStream
  super_class: #4                         // java/io/OutputStream
  interfaces: 1, fields: 3, methods: 23, attributes: 4
Constant pool:
    #1 = Utf8               os/SubProcess$InputStream
    #2 = Class              #1            // os/SubProcess$InputStream
    #3 = Utf8               java/io/OutputStream
    #4 = Class              #3            // java/io/OutputStream
    #5 = Utf8               java/io/DataOutput
    #6 = Class              #5            // java/io/DataOutput
    #7 = Utf8               SubProcess.scala
    #8 = Utf8               os/SubProcess
    #9 = Class              #8            // os/SubProcess
   #10 = Utf8               InputStream
   #11 = Utf8               wrapped
   #12 = Utf8               Ljava/io/OutputStream;
   #13 = Utf8               data
   #14 = Utf8               Ljava/io/DataOutputStream;
   #15 = Utf8               buffered
   #16 = Utf8               Ljava/io/BufferedWriter;
   #17 = Utf8               ()Ljava/io/OutputStream;
   #18 = NameAndType        #11:#12       // wrapped:Ljava/io/OutputStream;
   #19 = Fieldref           #2.#18        // os/SubProcess$InputStream.wrapped:Ljava/io/OutputStream;
   #20 = Utf8               this
   #21 = Utf8               Los/SubProcess$InputStream;
   #22 = Utf8               ()Ljava/io/DataOutputStream;
   #23 = NameAndType        #13:#14       // data:Ljava/io/DataOutputStream;
   #24 = Fieldref           #2.#23        // os/SubProcess$InputStream.data:Ljava/io/DataOutputStream;
   #25 = Utf8               ()Ljava/io/BufferedWriter;
   #26 = NameAndType        #15:#16       // buffered:Ljava/io/BufferedWriter;
   #27 = Fieldref           #2.#26        // os/SubProcess$InputStream.buffered:Ljava/io/BufferedWriter;
   #28 = Utf8               write
   #29 = Utf8               (I)V
   #30 = Utf8               b
   #31 = NameAndType        #11:#17       // wrapped:()Ljava/io/OutputStream;
   #32 = Methodref          #2.#31        // os/SubProcess$InputStream.wrapped:()Ljava/io/OutputStream;
   #33 = NameAndType        #28:#29       // write:(I)V
   #34 = Methodref          #4.#33        // java/io/OutputStream.write:(I)V
   #35 = Utf8               I
   #36 = Utf8               ([B)V
   #37 = NameAndType        #28:#36       // write:([B)V
   #38 = Methodref          #4.#37        // java/io/OutputStream.write:([B)V
   #39 = Utf8               [B
   #40 = Utf8               ([BII)V
   #41 = Utf8               off
   #42 = Utf8               len
   #43 = NameAndType        #28:#40       // write:([BII)V
   #44 = Methodref          #4.#43        // java/io/OutputStream.write:([BII)V
   #45 = Utf8               writeBoolean
   #46 = Utf8               (Z)V
   #47 = Utf8               v
   #48 = NameAndType        #13:#22       // data:()Ljava/io/DataOutputStream;
   #49 = Methodref          #2.#48        // os/SubProcess$InputStream.data:()Ljava/io/DataOutputStream;
   #50 = Utf8               java/io/DataOutputStream
   #51 = Class              #50           // java/io/DataOutputStream
   #52 = NameAndType        #45:#46       // writeBoolean:(Z)V
   #53 = Methodref          #51.#52       // java/io/DataOutputStream.writeBoolean:(Z)V
   #54 = Utf8               Z
   #55 = Utf8               writeByte
   #56 = NameAndType        #55:#29       // writeByte:(I)V
   #57 = Methodref          #51.#56       // java/io/DataOutputStream.writeByte:(I)V
   #58 = Utf8               writeShort
   #59 = NameAndType        #58:#29       // writeShort:(I)V
   #60 = Methodref          #51.#59       // java/io/DataOutputStream.writeShort:(I)V
   #61 = Utf8               writeChar
   #62 = NameAndType        #61:#29       // writeChar:(I)V
   #63 = Methodref          #51.#62       // java/io/DataOutputStream.writeChar:(I)V
   #64 = Utf8               writeInt
   #65 = NameAndType        #64:#29       // writeInt:(I)V
   #66 = Methodref          #51.#65       // java/io/DataOutputStream.writeInt:(I)V
   #67 = Utf8               writeLong
   #68 = Utf8               (J)V
   #69 = NameAndType        #67:#68       // writeLong:(J)V
   #70 = Methodref          #51.#69       // java/io/DataOutputStream.writeLong:(J)V
   #71 = Utf8               J
   #72 = Utf8               writeFloat
   #73 = Utf8               (F)V
   #74 = NameAndType        #72:#73       // writeFloat:(F)V
   #75 = Methodref          #51.#74       // java/io/DataOutputStream.writeFloat:(F)V
   #76 = Utf8               F
   #77 = Utf8               writeDouble
   #78 = Utf8               (D)V
   #79 = NameAndType        #77:#78       // writeDouble:(D)V
   #80 = Methodref          #51.#79       // java/io/DataOutputStream.writeDouble:(D)V
   #81 = Utf8               D
   #82 = Utf8               writeBytes
   #83 = Utf8               (Ljava/lang/String;)V
   #84 = Utf8               s
   #85 = NameAndType        #82:#83       // writeBytes:(Ljava/lang/String;)V
   #86 = Methodref          #51.#85       // java/io/DataOutputStream.writeBytes:(Ljava/lang/String;)V
   #87 = Utf8               Ljava/lang/String;
   #88 = Utf8               writeChars
   #89 = NameAndType        #88:#83       // writeChars:(Ljava/lang/String;)V
   #90 = Methodref          #51.#89       // java/io/DataOutputStream.writeChars:(Ljava/lang/String;)V
   #91 = Utf8               writeUTF
   #92 = NameAndType        #91:#83       // writeUTF:(Ljava/lang/String;)V
   #93 = Methodref          #51.#92       // java/io/DataOutputStream.writeUTF:(Ljava/lang/String;)V
   #94 = Utf8               writeLine
   #95 = NameAndType        #15:#25       // buffered:()Ljava/io/BufferedWriter;
   #96 = Methodref          #2.#95        // os/SubProcess$InputStream.buffered:()Ljava/io/BufferedWriter;
   #97 = Utf8               java/lang/StringBuilder
   #98 = Class              #97           // java/lang/StringBuilder
   #99 = Integer            1
  #100 = Utf8               <init>
  #101 = NameAndType        #100:#29      // "<init>":(I)V
  #102 = Methodref          #98.#101      // java/lang/StringBuilder."<init>":(I)V
  #103 = Utf8               append
  #104 = Utf8               (Ljava/lang/String;)Ljava/lang/StringBuilder;
  #105 = NameAndType        #103:#104     // append:(Ljava/lang/String;)Ljava/lang/StringBuilder;
  #106 = Methodref          #98.#105      // java/lang/StringBuilder.append:(Ljava/lang/String;)Ljava/lang/StringBuilder;
  #107 = Utf8               \n
  #108 = String             #107          // \n
  #109 = Utf8               toString
  #110 = Utf8               ()Ljava/lang/String;
  #111 = NameAndType        #109:#110     // toString:()Ljava/lang/String;
  #112 = Methodref          #98.#111      // java/lang/StringBuilder.toString:()Ljava/lang/String;
  #113 = Utf8               java/io/BufferedWriter
  #114 = Class              #113          // java/io/BufferedWriter
  #115 = NameAndType        #28:#83       // write:(Ljava/lang/String;)V
  #116 = Methodref          #114.#115     // java/io/BufferedWriter.write:(Ljava/lang/String;)V
  #117 = Utf8               ([C)V
  #118 = NameAndType        #28:#117      // write:([C)V
  #119 = Methodref          #114.#118     // java/io/BufferedWriter.write:([C)V
  #120 = Utf8               [C
  #121 = Utf8               flush
  #122 = Utf8               ()V
  #123 = NameAndType        #121:#122     // flush:()V
  #124 = Methodref          #51.#123      // java/io/DataOutputStream.flush:()V
  #125 = Methodref          #114.#123     // java/io/BufferedWriter.flush:()V
  #126 = Methodref          #4.#123       // java/io/OutputStream.flush:()V
  #127 = Utf8               close
  #128 = NameAndType        #127:#122     // close:()V
  #129 = Methodref          #4.#128       // java/io/OutputStream.close:()V
  #130 = Utf8               (Ljava/io/OutputStream;)V
  #131 = NameAndType        #100:#122     // "<init>":()V
  #132 = Methodref          #4.#131       // java/io/OutputStream."<init>":()V
  #133 = NameAndType        #100:#130     // "<init>":(Ljava/io/OutputStream;)V
  #134 = Methodref          #51.#133      // java/io/DataOutputStream."<init>":(Ljava/io/OutputStream;)V
  #135 = Utf8               java/io/OutputStreamWriter
  #136 = Class              #135          // java/io/OutputStreamWriter
  #137 = Methodref          #136.#133     // java/io/OutputStreamWriter."<init>":(Ljava/io/OutputStream;)V
  #138 = Utf8               (Ljava/io/Writer;)V
  #139 = NameAndType        #100:#138     // "<init>":(Ljava/io/Writer;)V
  #140 = Methodref          #114.#139     // java/io/BufferedWriter."<init>":(Ljava/io/Writer;)V
  #141 = Utf8               Code
  #142 = Utf8               LineNumberTable
  #143 = Utf8               LocalVariableTable
  #144 = Utf8               MethodParameters
  #145 = Utf8               InnerClasses
  #146 = Utf8               SourceFile
  #147 = Utf8               ScalaInlineInfo
  #148 = Utf8               Scala
{
  private final java.io.OutputStream wrapped;
    descriptor: Ljava/io/OutputStream;
    flags: (0x0012) ACC_PRIVATE, ACC_FINAL

  private final java.io.DataOutputStream data;
    descriptor: Ljava/io/DataOutputStream;
    flags: (0x0012) ACC_PRIVATE, ACC_FINAL

  private final java.io.BufferedWriter buffered;
    descriptor: Ljava/io/BufferedWriter;
    flags: (0x0012) ACC_PRIVATE, ACC_FINAL

  public java.io.OutputStream wrapped();
    descriptor: ()Ljava/io/OutputStream;
    flags: (0x0001) ACC_PUBLIC
    Code:
      stack=1, locals=1, args_size=1
         0: aload_0
         1: getfield      #19                 // Field wrapped:Ljava/io/OutputStream;
         4: areturn
      LineNumberTable:
        line 89: 0
      LocalVariableTable:
        Start  Length  Slot  Name   Signature
            0       5     0  this   Los/SubProcess$InputStream;

  public java.io.DataOutputStream data();
    descriptor: ()Ljava/io/DataOutputStream;
    flags: (0x0001) ACC_PUBLIC
    Code:
      stack=1, locals=1, args_size=1
         0: aload_0
         1: getfield      #24                 // Field data:Ljava/io/DataOutputStream;
         4: areturn
      LineNumberTable:
        line 91: 0
      LocalVariableTable:
        Start  Length  Slot  Name   Signature
            0       5     0  this   Los/SubProcess$InputStream;

  public java.io.BufferedWriter buffered();
    descriptor: ()Ljava/io/BufferedWriter;
    flags: (0x0001) ACC_PUBLIC
    Code:
      stack=1, locals=1, args_size=1
         0: aload_0
         1: getfield      #27                 // Field buffered:Ljava/io/BufferedWriter;
         4: areturn
      LineNumberTable:
        line 92: 0
      LocalVariableTable:
        Start  Length  Slot  Name   Signature
            0       5     0  this   Los/SubProcess$InputStream;

  public void write(int);
    descriptor: (I)V
    flags: (0x0001) ACC_PUBLIC
    Code:
      stack=2, locals=2, args_size=2
         0: aload_0
         1: invokevirtual #32                 // Method wrapped:()Ljava/io/OutputStream;
         4: iload_1
         5: invokevirtual #34                 // Method java/io/OutputStream.write:(I)V
         8: return
      LineNumberTable:
        line 94: 0
      LocalVariableTable:
        Start  Length  Slot  Name   Signature
            0       9     0  this   Los/SubProcess$InputStream;
            0       9     1     b   I
    MethodParameters:
      Name                           Flags
      b                              final

  public void write(byte[]);
    descriptor: ([B)V
    flags: (0x0001) ACC_PUBLIC
    Code:
      stack=2, locals=2, args_size=2
         0: aload_0
         1: invokevirtual #32                 // Method wrapped:()Ljava/io/OutputStream;
         4: aload_1
         5: invokevirtual #38                 // Method java/io/OutputStream.write:([B)V
         8: return
      LineNumberTable:
        line 95: 0
      LocalVariableTable:
        Start  Length  Slot  Name   Signature
            0       9     0  this   Los/SubProcess$InputStream;
            0       9     1     b   [B
    MethodParameters:
      Name                           Flags
      b                              final

  public void write(byte[], int, int);
    descriptor: ([BII)V
    flags: (0x0001) ACC_PUBLIC
    Code:
      stack=4, locals=4, args_size=4
         0: aload_0
         1: invokevirtual #32                 // Method wrapped:()Ljava/io/OutputStream;
         4: aload_1
         5: iload_2
         6: iload_3
         7: invokevirtual #44                 // Method java/io/OutputStream.write:([BII)V
        10: return
      LineNumberTable:
        line 96: 0
      LocalVariableTable:
        Start  Length  Slot  Name   Signature
            0      11     0  this   Los/SubProcess$InputStream;
            0      11     1     b   [B
            0      11     2   off   I
            0      11     3   len   I
    MethodParameters:
      Name                           Flags
      b                              final
      off                            final
      len                            final

  public void writeBoolean(boolean);
    descriptor: (Z)V
    flags: (0x0001) ACC_PUBLIC
    Code:
      stack=2, locals=2, args_size=2
         0: aload_0
         1: invokevirtual #49                 // Method data:()Ljava/io/DataOutputStream;
         4: iload_1
         5: invokevirtual #53                 // Method java/io/DataOutputStream.writeBoolean:(Z)V
         8: return
      LineNumberTable:
        line 98: 0
      LocalVariableTable:
        Start  Length  Slot  Name   Signature
            0       9     0  this   Los/SubProcess$InputStream;
            0       9     1     v   Z
    MethodParameters:
      Name                           Flags
      v                              final

  public void writeByte(int);
    descriptor: (I)V
    flags: (0x0001) ACC_PUBLIC
    Code:
      stack=2, locals=2, args_size=2
         0: aload_0
         1: invokevirtual #49                 // Method data:()Ljava/io/DataOutputStream;
         4: iload_1
         5: invokevirtual #57                 // Method java/io/DataOutputStream.writeByte:(I)V
         8: return
      LineNumberTable:
        line 99: 0
      LocalVariableTable:
        Start  Length  Slot  Name   Signature
            0       9     0  this   Los/SubProcess$InputStream;
            0       9     1     v   I
    MethodParameters:
      Name                           Flags
      v                              final

  public void writeShort(int);
    descriptor: (I)V
    flags: (0x0001) ACC_PUBLIC
    Code:
      stack=2, locals=2, args_size=2
         0: aload_0
         1: invokevirtual #49                 // Method data:()Ljava/io/DataOutputStream;
         4: iload_1
         5: invokevirtual #60                 // Method java/io/DataOutputStream.writeShort:(I)V
         8: return
      LineNumberTable:
        line 100: 0
      LocalVariableTable:
        Start  Length  Slot  Name   Signature
            0       9     0  this   Los/SubProcess$InputStream;
            0       9     1     v   I
    MethodParameters:
      Name                           Flags
      v                              final

  public void writeChar(int);
    descriptor: (I)V
    flags: (0x0001) ACC_PUBLIC
    Code:
      stack=2, locals=2, args_size=2
         0: aload_0
         1: invokevirtual #49                 // Method data:()Ljava/io/DataOutputStream;
         4: iload_1
         5: invokevirtual #63                 // Method java/io/DataOutputStream.writeChar:(I)V
         8: return
      LineNumberTable:
        line 101: 0
      LocalVariableTable:
        Start  Length  Slot  Name   Signature
            0       9     0  this   Los/SubProcess$InputStream;
            0       9     1     v   I
    MethodParameters:
      Name                           Flags
      v                              final

  public void writeInt(int);
    descriptor: (I)V
    flags: (0x0001) ACC_PUBLIC
    Code:
      stack=2, locals=2, args_size=2
         0: aload_0
         1: invokevirtual #49                 // Method data:()Ljava/io/DataOutputStream;
         4: iload_1
         5: invokevirtual #66                 // Method java/io/DataOutputStream.writeInt:(I)V
         8: return
      LineNumberTable:
        line 102: 0
      LocalVariableTable:
        Start  Length  Slot  Name   Signature
            0       9     0  this   Los/SubProcess$InputStream;
            0       9     1     v   I
    MethodParameters:
      Name                           Flags
      v                              final

  public void writeLong(long);
    descriptor: (J)V
    flags: (0x0001) ACC_PUBLIC
    Code:
      stack=3, locals=3, args_size=2
         0: aload_0
         1: invokevirtual #49                 // Method data:()Ljava/io/DataOutputStream;
         4: lload_1
         5: invokevirtual #70                 // Method java/io/DataOutputStream.writeLong:(J)V
         8: return
      LineNumberTable:
        line 103: 0
      LocalVariableTable:
        Start  Length  Slot  Name   Signature
            0       9     0  this   Los/SubProcess$InputStream;
            0       9     1     v   J
    MethodParameters:
      Name                           Flags
      v                              final

  public void writeFloat(float);
    descriptor: (F)V
    flags: (0x0001) ACC_PUBLIC
    Code:
      stack=2, locals=2, args_size=2
         0: aload_0
         1: invokevirtual #49                 // Method data:()Ljava/io/DataOutputStream;
         4: fload_1
         5: invokevirtual #75                 // Method java/io/DataOutputStream.writeFloat:(F)V
         8: return
      LineNumberTable:
        line 104: 0
      LocalVariableTable:
        Start  Length  Slot  Name   Signature
            0       9     0  this   Los/SubProcess$InputStream;
            0       9     1     v   F
    MethodParameters:
      Name                           Flags
      v                              final

  public void writeDouble(double);
    descriptor: (D)V
    flags: (0x0001) ACC_PUBLIC
    Code:
      stack=3, locals=3, args_size=2
         0: aload_0
         1: invokevirtual #49                 // Method data:()Ljava/io/DataOutputStream;
         4: dload_1
         5: invokevirtual #80                 // Method java/io/DataOutputStream.writeDouble:(D)V
         8: return
      LineNumberTable:
        line 105: 0
      LocalVariableTable:
        Start  Length  Slot  Name   Signature
            0       9     0  this   Los/SubProcess$InputStream;
            0       9     1     v   D
    MethodParameters:
      Name                           Flags
      v                              final

  public void writeBytes(java.lang.String);
    descriptor: (Ljava/lang/String;)V
    flags: (0x0001) ACC_PUBLIC
    Code:
      stack=2, locals=2, args_size=2
         0: aload_0
         1: invokevirtual #49                 // Method data:()Ljava/io/DataOutputStream;
         4: aload_1
         5: invokevirtual #86                 // Method java/io/DataOutputStream.writeBytes:(Ljava/lang/String;)V
         8: return
      LineNumberTable:
        line 106: 0
      LocalVariableTable:
        Start  Length  Slot  Name   Signature
            0       9     0  this   Los/SubProcess$InputStream;
            0       9     1     s   Ljava/lang/String;
    MethodParameters:
      Name                           Flags
      s                              final

  public void writeChars(java.lang.String);
    descriptor: (Ljava/lang/String;)V
    flags: (0x0001) ACC_PUBLIC
    Code:
      stack=2, locals=2, args_size=2
         0: aload_0
         1: invokevirtual #49                 // Method data:()Ljava/io/DataOutputStream;
         4: aload_1
         5: invokevirtual #90                 // Method java/io/DataOutputStream.writeChars:(Ljava/lang/String;)V
         8: return
      LineNumberTable:
        line 107: 0
      LocalVariableTable:
        Start  Length  Slot  Name   Signature
            0       9     0  this   Los/SubProcess$InputStream;
            0       9     1     s   Ljava/lang/String;
    MethodParameters:
      Name                           Flags
      s                              final

  public void writeUTF(java.lang.String);
    descriptor: (Ljava/lang/String;)V
    flags: (0x0001) ACC_PUBLIC
    Code:
      stack=2, locals=2, args_size=2
         0: aload_0
         1: invokevirtual #49                 // Method data:()Ljava/io/DataOutputStream;
         4: aload_1
         5: invokevirtual #93                 // Method java/io/DataOutputStream.writeUTF:(Ljava/lang/String;)V
         8: return
      LineNumberTable:
        line 108: 0
      LocalVariableTable:
        Start  Length  Slot  Name   Signature
            0       9     0  this   Los/SubProcess$InputStream;
            0       9     1     s   Ljava/lang/String;
    MethodParameters:
      Name                           Flags
      s                              final

  public void writeLine(java.lang.String);
    descriptor: (Ljava/lang/String;)V
    flags: (0x0001) ACC_PUBLIC
    Code:
      stack=4, locals=2, args_size=2
         0: aload_0
         1: invokevirtual #96                 // Method buffered:()Ljava/io/BufferedWriter;
         4: new           #98                 // class java/lang/StringBuilder
         7: dup
         8: ldc           #99                 // int 1
        10: invokespecial #102                // Method java/lang/StringBuilder."<init>":(I)V
        13: aload_1
        14: invokevirtual #106                // Method java/lang/StringBuilder.append:(Ljava/lang/String;)Ljava/lang/StringBuilder;
        17: ldc           #108                // String \n
        19: invokevirtual #106                // Method java/lang/StringBuilder.append:(Ljava/lang/String;)Ljava/lang/StringBuilder;
        22: invokevirtual #112                // Method java/lang/StringBuilder.toString:()Ljava/lang/String;
        25: invokevirtual #116                // Method java/io/BufferedWriter.write:(Ljava/lang/String;)V
        28: return
      LineNumberTable:
        line 110: 0
      LocalVariableTable:
        Start  Length  Slot  Name   Signature
            0      29     0  this   Los/SubProcess$InputStream;
            0      29     1     s   Ljava/lang/String;
    MethodParameters:
      Name                           Flags
      s                              final

  public void write(java.lang.String);
    descriptor: (Ljava/lang/String;)V
    flags: (0x0001) ACC_PUBLIC
    Code:
      stack=2, locals=2, args_size=2
         0: aload_0
         1: invokevirtual #96                 // Method buffered:()Ljava/io/BufferedWriter;
         4: aload_1
         5: invokevirtual #116                // Method java/io/BufferedWriter.write:(Ljava/lang/String;)V
         8: return
      LineNumberTable:
        line 111: 0
      LocalVariableTable:
        Start  Length  Slot  Name   Signature
            0       9     0  this   Los/SubProcess$InputStream;
            0       9     1     s   Ljava/lang/String;
    MethodParameters:
      Name                           Flags
      s                              final

  public void write(char[]);
    descriptor: ([C)V
    flags: (0x0001) ACC_PUBLIC
    Code:
      stack=2, locals=2, args_size=2
         0: aload_0
         1: invokevirtual #96                 // Method buffered:()Ljava/io/BufferedWriter;
         4: aload_1
         5: invokevirtual #119                // Method java/io/BufferedWriter.write:([C)V
         8: return
      LineNumberTable:
        line 112: 0
      LocalVariableTable:
        Start  Length  Slot  Name   Signature
            0       9     0  this   Los/SubProcess$InputStream;
            0       9     1     s   [C
    MethodParameters:
      Name                           Flags
      s                              final

  public void flush();
    descriptor: ()V
    flags: (0x0001) ACC_PUBLIC
    Code:
      stack=1, locals=1, args_size=1
         0: aload_0
         1: invokevirtual #49                 // Method data:()Ljava/io/DataOutputStream;
         4: invokevirtual #124                // Method java/io/DataOutputStream.flush:()V
         7: aload_0
         8: invokevirtual #96                 // Method buffered:()Ljava/io/BufferedWriter;
        11: invokevirtual #125                // Method java/io/BufferedWriter.flush:()V
        14: aload_0
        15: invokevirtual #32                 // Method wrapped:()Ljava/io/OutputStream;
        18: invokevirtual #126                // Method java/io/OutputStream.flush:()V
        21: return
      LineNumberTable:
        line 115: 0
        line 116: 7
        line 117: 14
      LocalVariableTable:
        Start  Length  Slot  Name   Signature
            0      22     0  this   Los/SubProcess$InputStream;

  public void close();
    descriptor: ()V
    flags: (0x0001) ACC_PUBLIC
    Code:
      stack=1, locals=1, args_size=1
         0: aload_0
         1: invokevirtual #32                 // Method wrapped:()Ljava/io/OutputStream;
         4: invokevirtual #129                // Method java/io/OutputStream.close:()V
         7: return
      LineNumberTable:
        line 119: 0
      LocalVariableTable:
        Start  Length  Slot  Name   Signature
            0       8     0  this   Los/SubProcess$InputStream;

  public os.SubProcess$InputStream(java.io.OutputStream);
    descriptor: (Ljava/io/OutputStream;)V
    flags: (0x0001) ACC_PUBLIC
    Code:
      stack=6, locals=2, args_size=2
         0: aload_0
         1: aload_1
         2: putfield      #19                 // Field wrapped:Ljava/io/OutputStream;
         5: aload_0
         6: invokespecial #132                // Method java/io/OutputStream."<init>":()V
         9: aload_0
        10: new           #51                 // class java/io/DataOutputStream
        13: dup
        14: aload_1
        15: invokespecial #134                // Method java/io/DataOutputStream."<init>":(Ljava/io/OutputStream;)V
        18: putfield      #24                 // Field data:Ljava/io/DataOutputStream;
        21: aload_0
        22: new           #114                // class java/io/BufferedWriter
        25: dup
        26: new           #136                // class java/io/OutputStreamWriter
        29: dup
        30: aload_1
        31: invokespecial #137                // Method java/io/OutputStreamWriter."<init>":(Ljava/io/OutputStream;)V
        34: invokespecial #140                // Method java/io/BufferedWriter."<init>":(Ljava/io/Writer;)V
        37: putfield      #27                 // Field buffered:Ljava/io/BufferedWriter;
        40: return
      LineNumberTable:
        line 89: 0
        line 90: 5
        line 91: 9
        line 92: 21
        line 89: 40
      LocalVariableTable:
        Start  Length  Slot  Name   Signature
            0      41     0  this   Los/SubProcess$InputStream;
            0      41     1 wrapped   Ljava/io/OutputStream;
    MethodParameters:
      Name                           Flags
      wrapped                        final
}
InnerClasses:
  public static #10= #2 of #9;            // InputStream=class os/SubProcess$InputStream of class os/SubProcess
SourceFile: "SubProcess.scala"
  ScalaInlineInfo: length = 0x77 (unknown attribute)
   01 00 00 17 00 64 00 82 00 00 0F 00 19 00 00 7F
   00 7A 00 00 0D 00 16 00 00 79 00 7A 00 00 0B 00
   11 00 00 1C 00 1D 00 00 1C 00 53 00 00 1C 00 24
   00 00 1C 00 28 00 00 1C 00 75 00 00 2D 00 2E 00
   00 37 00 1D 00 00 52 00 53 00 00 3D 00 1D 00 00
   58 00 53 00 00 4D 00 4E 00 00 48 00 49 00 00 40
   00 1D 00 00 5E 00 53 00 00 43 00 44 00 00 3A 00
   1D 00 00 5B 00 53 00
  Scala: length = 0x0 (unknown attribute)

