Classfile /Users/mw/Projects/slang-braindump/.jar/jar11/assemble/slang-braindump/assemble/content/os/SubPath.class
  Last modified May 29, 2022; size 8012 bytes
  SHA-256 checksum 93dbfc3dfe2975207036bd70040e46a83e5eac6e2afa8f2cc68a4946bcb3f6f6
  Compiled from "Path.scala"
public class os.SubPath implements os.FilePath,os.BasePathImpl,os.SegmentedPath
  minor version: 0
  major version: 52
  flags: (0x0021) ACC_PUBLIC, ACC_SUPER
  this_class: #2                          // os/SubPath
  super_class: #4                         // java/lang/Object
  interfaces: 3, fields: 2, methods: 26, attributes: 5
Constant pool:
    #1 = Utf8               os/SubPath
    #2 = Class              #1            // os/SubPath
    #3 = Utf8               java/lang/Object
    #4 = Class              #3            // java/lang/Object
    #5 = Utf8               os/FilePath
    #6 = Class              #5            // os/FilePath
    #7 = Utf8               os/BasePathImpl
    #8 = Class              #7            // os/BasePathImpl
    #9 = Utf8               os/SegmentedPath
   #10 = Class              #9            // os/SegmentedPath
   #11 = Utf8               Path.scala
   #12 = Utf8               Lscala/reflect/ScalaSignature;
   #13 = Utf8               bytes
   #14 = Utf8               \u0006\u0005\u0005-d\u0001\u0002\u000e\u001c\u0001yA\u0001b\f\u0001\u0003\u0006\u0004%\t\u0001\r\u0005\t\u007f\u0001\u0011\t\u0011)A\u0005c!1\u0001\t\u0001C\u00017\u0005CQ\u0001\u0012\u0001\u0005\u0002\u0015Cq!\u0013\u0001C\u0002\u0013\u0005!\n\u0003\u0004U\u0001\u0001\u0006IaS\u0003\u0005+\u0002\u0001!\t\u0003\u0004W\u0001\u0001&\tb\u0016\u0005\u0006E\u0002!\ta\u0019\u0005\u0006S\u0002!\tA\u001b\u0005\u0006a\u0002!\t%\u001d\u0005\u0006e\u0002!\te\u001d\u0005\u0006i\u0002!\t%\u001e\u0005\u0006w\u0002!\t\u0001 \u0005\b\u0003\u001f\u0001A\u0011AA\t\u000f\u001d\t\tc\u0007E\u0001\u0003G1aAG\u000e\t\u0002\u0005\u0015\u0002B\u0002!\u0012\t\u0003\t9\u0003\u0003\u0005\u0002*E!\taGA\u0016\u0011\u001d\t\t$\u0005C\u0001\u0003gAq!!\r\u0012\t\u0003\t)\u0006C\u0005\u0002ZE\u0011\r\u0011b\u0001\u0002\\!A\u00111M\t!\u0002\u0013\ti\u0006C\u0005\u0002fE\u0011\r\u0011\"\u0001\u0002h!9\u0011\u0011N\t!\u0002\u0013\u0011%aB*vEB\u000bG\u000f\u001b\u0006\u00029\u0005\u0011qn]\u0002\u0001\'\u0015\u0001q$J\u0015-!\t\u00013%D\u0001\"\u0015\u0005\u0011\u0013!B:dC2\f\u0017B\u0001\u0013\"\u0005\u0019\te.\u001f*fMB\u0011aeJ\u0007\u00027%\u0011\u0001f\u0007\u0002\t\r&dW\rU1uQB\u0011aEK\u0005\u0003Wm\u0011ABQ1tKB\u000bG\u000f[%na2\u0004\"AJ\u0017\n\u00059Z\"!D*fO6,g\u000e^3e!\u0006$\b.A\u0005tK\u001elWM\u001c;taU\t\u0011\u0007E\u0002!eQJ!aM\u0011\u0003\u000b\u0005\u0013(/Y=\u0011\u0005UbdB\u0001\u001c;!\t9\u0014%D\u00019\u0015\tIT$\u0001\u0004=e>|GOP\u0005\u0003w\u0005\na\u0001\u0015:fI\u00164\u0017BA\u001f?\u0005\u0019\u0019FO]5oO*\u00111(I\u0001\u000bg\u0016<W.\u001a8ugB\u0002\u0013A\u0002\u001fj]&$h\b\u0006\u0002C\u0007B\u0011a\u0005\u0001\u0005\u0006_\r\u0001\r!M\u0001\bY\u0006\u001cHo\u00149u+\u00051\u0005c\u0001\u0011Hi%\u0011\u0001*\t\u0002\u0007\u001fB$\u0018n\u001c8\u0002\u0011M,w-\\3oiN,\u0012a\u0013\t\u0004\u0019F#dBA\'P\u001d\t9d*C\u0001#\u0013\t\u0001\u0016%A\u0004qC\u000e\\\u0017mZ3\n\u0005I\u001b&AC%oI\u0016DX\rZ*fc*\u0011\u0001+I\u0001\ng\u0016<W.\u001a8ug\u0002\u0012\u0001\u0002\u00165jgRK\b/Z\u0001\u0005[\u0006\\W\rF\u0002C1vCQ!\u0017\u0005A\u0002i\u000b\u0011\u0001\u001d\t\u0004\u0019n#\u0014B\u0001/T\u0005\r\u0019V-\u001d\u0005\u0006=\"\u0001\raX\u0001\u0004kB\u001c\bC\u0001\u0011a\u0013\t\t\u0017EA\u0002J]R\f!B]3mCRLg/\u001a+p)\t!w\r\u0005\u0002\'K&\u0011am\u0007\u0002\b%\u0016d\u0007+\u0019;i\u0011\u0015A\u0017\u00021\u0001C\u0003\u0011\u0011\u0017m]3\u0002\u0015M$\u0018M\u001d;t/&$\b\u000e\u0006\u0002l]B\u0011\u0001\u0005\\\u0005\u0003[\u0006\u0012qAQ8pY\u0016\fg\u000eC\u0003p\u0015\u0001\u0007!)\u0001\u0004uCJ<W\r^\u0001\ti>\u001cFO]5oOR\tA\'\u0001\u0005iCND7i\u001c3f)\u0005y\u0016AB3rk\u0006d7\u000f\u0006\u0002lm\")q/\u0004a\u0001q\u0006\tq\u000e\u0005\u0002!s&\u0011!0\t\u0002\u0004\u0003:L\u0018!\u0002;p\u001d&{U#A?\u0011\u0007y\fY!D\u0001\u0000\u0015\u0011\t\t!a\u0001\u0002\t\u0019LG.\u001a\u0006\u0005\u0003\u000b\t9!A\u0002oS>T!!!\u0003\u0002\t)\fg/Y\u0005\u0004\u0003\u001by(\u0001\u0002)bi\"\f1B]3t_24XM\u0012:p[R!\u00111CA\r!\u0011\t)\"a\b\u000f\t\u0005]\u0011\u0011\u0004\u0007\u0001\u0011\u0019Aw\u00021\u0001\u0002\u001cA\u0019a%!\b\n\u0007\u000551$C\u0002V\u0003;\tqaU;c!\u0006$\b\u000e\u0005\u0002\'#M\u0011\u0011c\b\u000b\u0003\u0003G\t1B]3mCRLg/\u001a+paQ)A-!\f\u00020!)qf\u0005a\u0001c!)\u0011j\u0005a\u0001\u0017\u0006)\u0011\r\u001d9msV!\u0011QGA#)\u0011\t9$!\u0015\u0015\u0007\t\u000bI\u0004C\u0005\u0002<Q\t\t\u0011q\u0001\u0002>\u0005QQM^5eK:\u001cW\rJ\u001a\u0011\u000b\u0019\ny$a\u0011\n\u0007\u0005\u00053DA\bQCRD7i\u001c8wKJ$\u0018N\u00197f!\u0011\t9\"!\u0012\u0005\u000f\u0005\u001dCC1\u0001\u0002J\t\tA+E\u0002\u0002La\u00042\u0001IA\'\u0013\r\ty%\t\u0002\b\u001d>$\b.\u001b8h\u0011\u001d\t\u0019\u0006\u0006a\u0001\u0003\u0007\n!A\u001a\u0019\u0015\u0007\t\u000b9\u0006C\u00030+\u0001\u00071*A\btk\n\u0004\u0016\r\u001e5Pe\u0012,\'/\u001b8h+\t\ti\u0006\u0005\u0003M\u0003?\u0012\u0015bAA1\'\nAqJ\u001d3fe&tw-\u0001\ttk\n\u0004\u0016\r\u001e5Pe\u0012,\'/\u001b8hA\u0005\u00191/\u001e2\u0016\u0003\t\u000bAa];cA\u0001
   #15 = Utf8               os/PathChunk$SubPathChunk
   #16 = Class              #15           // os/PathChunk$SubPathChunk
   #17 = Utf8               os/PathChunk
   #18 = Class              #17           // os/PathChunk
   #19 = Utf8               SubPathChunk
   #20 = Utf8               scala/collection/mutable/ArraySeq$ofRef
   #21 = Class              #20           // scala/collection/mutable/ArraySeq$ofRef
   #22 = Utf8               scala/collection/mutable/ArraySeq
   #23 = Class              #22           // scala/collection/mutable/ArraySeq
   #24 = Utf8               ofRef
   #25 = Utf8               segments0
   #26 = Utf8               [Ljava/lang/String;
   #27 = Utf8               segments
   #28 = Utf8               Lscala/collection/immutable/IndexedSeq;
   #29 = Utf8               Lscala/collection/immutable/IndexedSeq<Ljava/lang/String;>;
   #30 = Utf8               sub
   #31 = Utf8               ()Los/SubPath;
   #32 = Utf8               os/SubPath$
   #33 = Class              #32           // os/SubPath$
   #34 = Utf8               MODULE$
   #35 = Utf8               Los/SubPath$;
   #36 = NameAndType        #34:#35       // MODULE$:Los/SubPath$;
   #37 = Fieldref           #33.#36       // os/SubPath$.MODULE$:Los/SubPath$;
   #38 = NameAndType        #30:#31       // sub:()Los/SubPath;
   #39 = Methodref          #33.#38       // os/SubPath$.sub:()Los/SubPath;
   #40 = Utf8               subPathOrdering
   #41 = Utf8               ()Lscala/math/Ordering;
   #42 = Utf8               ()Lscala/math/Ordering<Los/SubPath;>;
   #43 = NameAndType        #40:#41       // subPathOrdering:()Lscala/math/Ordering;
   #44 = Methodref          #33.#43       // os/SubPath$.subPathOrdering:()Lscala/math/Ordering;
   #45 = Utf8               apply
   #46 = Utf8               (Lscala/collection/immutable/IndexedSeq;)Los/SubPath;
   #47 = Utf8               (Lscala/collection/immutable/IndexedSeq<Ljava/lang/String;>;)Los/SubPath;
   #48 = NameAndType        #45:#46       // apply:(Lscala/collection/immutable/IndexedSeq;)Los/SubPath;
   #49 = Methodref          #33.#48       // os/SubPath$.apply:(Lscala/collection/immutable/IndexedSeq;)Los/SubPath;
   #50 = Utf8               (Ljava/lang/Object;Los/PathConvertible;)Los/SubPath;
   #51 = Utf8               <T:Ljava/lang/Object;>(TT;Los/PathConvertible<TT;>;)Los/SubPath;
   #52 = Utf8               f0
   #53 = Utf8               evidence$3
   #54 = NameAndType        #45:#50       // apply:(Ljava/lang/Object;Los/PathConvertible;)Los/SubPath;
   #55 = Methodref          #33.#54       // os/SubPath$.apply:(Ljava/lang/Object;Los/PathConvertible;)Los/SubPath;
   #56 = Utf8               $div
   #57 = Utf8               (Los/PathChunk;)Los/BasePath;
   #58 = Utf8               chunk
   #59 = Utf8               $div$
   #60 = Utf8               (Los/SegmentedPath;Los/PathChunk;)Los/BasePath;
   #61 = NameAndType        #59:#60       // $div$:(Los/SegmentedPath;Los/PathChunk;)Los/BasePath;
   #62 = InterfaceMethodref #10.#61       // os/SegmentedPath.$div$:(Los/SegmentedPath;Los/PathChunk;)Los/BasePath;
   #63 = Utf8               this
   #64 = Utf8               Los/SubPath;
   #65 = Utf8               Los/PathChunk;
   #66 = Utf8               endsWith
   #67 = Utf8               (Los/RelPath;)Z
   #68 = Utf8               target
   #69 = Utf8               endsWith$
   #70 = Utf8               (Los/SegmentedPath;Los/RelPath;)Z
   #71 = NameAndType        #69:#70       // endsWith$:(Los/SegmentedPath;Los/RelPath;)Z
   #72 = InterfaceMethodref #10.#71       // os/SegmentedPath.endsWith$:(Los/SegmentedPath;Los/RelPath;)Z
   #73 = Utf8               Los/RelPath;
   #74 = Utf8               ext
   #75 = Utf8               ()Ljava/lang/String;
   #76 = Utf8               ext$
   #77 = Utf8               (Los/BasePathImpl;)Ljava/lang/String;
   #78 = NameAndType        #76:#77       // ext$:(Los/BasePathImpl;)Ljava/lang/String;
   #79 = InterfaceMethodref #8.#78        // os/BasePathImpl.ext$:(Los/BasePathImpl;)Ljava/lang/String;
   #80 = Utf8               baseName
   #81 = Utf8               baseName$
   #82 = NameAndType        #81:#77       // baseName$:(Los/BasePathImpl;)Ljava/lang/String;
   #83 = InterfaceMethodref #8.#82        // os/BasePathImpl.baseName$:(Los/BasePathImpl;)Ljava/lang/String;
   #84 = Utf8               last
   #85 = Utf8               last$
   #86 = NameAndType        #85:#77       // last$:(Los/BasePathImpl;)Ljava/lang/String;
   #87 = InterfaceMethodref #8.#86        // os/BasePathImpl.last$:(Los/BasePathImpl;)Ljava/lang/String;
   #88 = Utf8               subRelativeTo
   #89 = Utf8               (Los/BasePath;)Los/SubPath;
   #90 = Utf8               os/BasePath
   #91 = Class              #90           // os/BasePath
   #92 = Utf8               subRelativeTo$
   #93 = Utf8               (Los/BasePath;Los/BasePath;)Los/SubPath;
   #94 = NameAndType        #92:#93       // subRelativeTo$:(Los/BasePath;Los/BasePath;)Los/SubPath;
   #95 = InterfaceMethodref #91.#94       // os/BasePath.subRelativeTo$:(Los/BasePath;Los/BasePath;)Los/SubPath;
   #96 = Utf8               Los/BasePath;
   #97 = Utf8               ()[Ljava/lang/String;
   #98 = NameAndType        #25:#26       // segments0:[Ljava/lang/String;
   #99 = Fieldref           #2.#98        // os/SubPath.segments0:[Ljava/lang/String;
  #100 = Utf8               lastOpt
  #101 = Utf8               ()Lscala/Option;
  #102 = Utf8               ()Lscala/Option<Ljava/lang/String;>;
  #103 = Utf8               ()Lscala/collection/immutable/IndexedSeq;
  #104 = NameAndType        #27:#103      // segments:()Lscala/collection/immutable/IndexedSeq;
  #105 = Methodref          #2.#104       // os/SubPath.segments:()Lscala/collection/immutable/IndexedSeq;
  #106 = Utf8               scala/collection/immutable/IndexedSeq
  #107 = Class              #106          // scala/collection/immutable/IndexedSeq
  #108 = Utf8               lastOption
  #109 = NameAndType        #108:#101     // lastOption:()Lscala/Option;
  #110 = InterfaceMethodref #107.#109     // scala/collection/immutable/IndexedSeq.lastOption:()Lscala/Option;
  #111 = Utf8               ()Lscala/collection/immutable/IndexedSeq<Ljava/lang/String;>;
  #112 = NameAndType        #27:#28       // segments:Lscala/collection/immutable/IndexedSeq;
  #113 = Fieldref           #2.#112       // os/SubPath.segments:Lscala/collection/immutable/IndexedSeq;
  #114 = Utf8               make
  #115 = Utf8               (Lscala/collection/immutable/Seq;I)Los/SubPath;
  #116 = Utf8               (Lscala/collection/immutable/Seq<Ljava/lang/String;>;I)Los/SubPath;
  #117 = Utf8               p
  #118 = Utf8               ups
  #119 = Utf8               scala/Predef$
  #120 = Class              #119          // scala/Predef$
  #121 = Utf8               Lscala/Predef$;
  #122 = NameAndType        #34:#121      // MODULE$:Lscala/Predef$;
  #123 = Fieldref           #120.#122     // scala/Predef$.MODULE$:Lscala/Predef$;
  #124 = Utf8               require
  #125 = Utf8               (Z)V
  #126 = NameAndType        #124:#125     // require:(Z)V
  #127 = Methodref          #120.#126     // scala/Predef$.require:(Z)V
  #128 = Utf8               scala/reflect/ClassTag$
  #129 = Class              #128          // scala/reflect/ClassTag$
  #130 = Utf8               Lscala/reflect/ClassTag$;
  #131 = NameAndType        #34:#130      // MODULE$:Lscala/reflect/ClassTag$;
  #132 = Fieldref           #129.#131     // scala/reflect/ClassTag$.MODULE$:Lscala/reflect/ClassTag$;
  #133 = Utf8               java/lang/String
  #134 = Class              #133          // java/lang/String
  #135 = Utf8               (Ljava/lang/Class;)Lscala/reflect/ClassTag;
  #136 = NameAndType        #45:#135      // apply:(Ljava/lang/Class;)Lscala/reflect/ClassTag;
  #137 = Methodref          #129.#136     // scala/reflect/ClassTag$.apply:(Ljava/lang/Class;)Lscala/reflect/ClassTag;
  #138 = Utf8               scala/collection/immutable/Seq
  #139 = Class              #138          // scala/collection/immutable/Seq
  #140 = Utf8               toArray
  #141 = Utf8               (Lscala/reflect/ClassTag;)Ljava/lang/Object;
  #142 = NameAndType        #140:#141     // toArray:(Lscala/reflect/ClassTag;)Ljava/lang/Object;
  #143 = InterfaceMethodref #139.#142     // scala/collection/immutable/Seq.toArray:(Lscala/reflect/ClassTag;)Ljava/lang/Object;
  #144 = Class              #26           // "[Ljava/lang/String;"
  #145 = Utf8               <init>
  #146 = Utf8               ([Ljava/lang/String;)V
  #147 = NameAndType        #145:#146     // "<init>":([Ljava/lang/String;)V
  #148 = Methodref          #2.#147       // os/SubPath."<init>":([Ljava/lang/String;)V
  #149 = Utf8               Lscala/collection/immutable/Seq;
  #150 = Utf8               I
  #151 = Utf8               relativeTo
  #152 = Utf8               (Los/SubPath;)Los/RelPath;
  #153 = Utf8               base
  #154 = NameAndType        #25:#97       // segments0:()[Ljava/lang/String;
  #155 = Methodref          #2.#154       // os/SubPath.segments0:()[Ljava/lang/String;
  #156 = Utf8               copyArrayToImmutableIndexedSeq
  #157 = Utf8               (Ljava/lang/Object;)Lscala/collection/immutable/IndexedSeq;
  #158 = NameAndType        #156:#157     // copyArrayToImmutableIndexedSeq:(Ljava/lang/Object;)Lscala/collection/immutable/IndexedSeq;
  #159 = Methodref          #120.#158     // scala/Predef$.copyArrayToImmutableIndexedSeq:(Ljava/lang/Object;)Lscala/collection/immutable/IndexedSeq;
  #160 = Utf8               relativeTo0
  #161 = Utf8               ([Ljava/lang/String;Lscala/collection/immutable/IndexedSeq;)Los/RelPath;
  #162 = NameAndType        #160:#161     // relativeTo0:([Ljava/lang/String;Lscala/collection/immutable/IndexedSeq;)Los/RelPath;
  #163 = Methodref          #33.#162      // os/SubPath$.relativeTo0:([Ljava/lang/String;Lscala/collection/immutable/IndexedSeq;)Los/RelPath;
  #164 = Utf8               startsWith
  #165 = Utf8               (Los/SubPath;)Z
  #166 = Utf8               [Ljava/lang/Object;
  #167 = Class              #166          // "[Ljava/lang/Object;"
  #168 = Utf8               refArrayOps
  #169 = Utf8               ([Ljava/lang/Object;)Ljava/lang/Object;
  #170 = NameAndType        #168:#169     // refArrayOps:([Ljava/lang/Object;)Ljava/lang/Object;
  #171 = Methodref          #120.#170     // scala/Predef$.refArrayOps:([Ljava/lang/Object;)Ljava/lang/Object;
  #172 = Utf8               scala/collection/ArrayOps$
  #173 = Class              #172          // scala/collection/ArrayOps$
  #174 = Utf8               Lscala/collection/ArrayOps$;
  #175 = NameAndType        #34:#174      // MODULE$:Lscala/collection/ArrayOps$;
  #176 = Fieldref           #173.#175     // scala/collection/ArrayOps$.MODULE$:Lscala/collection/ArrayOps$;
  #177 = Utf8               startsWith$default$2$extension
  #178 = Utf8               (Ljava/lang/Object;)I
  #179 = NameAndType        #177:#178     // startsWith$default$2$extension:(Ljava/lang/Object;)I
  #180 = Methodref          #173.#179     // scala/collection/ArrayOps$.startsWith$default$2$extension:(Ljava/lang/Object;)I
  #181 = Utf8               startsWith$extension
  #182 = Utf8               (Ljava/lang/Object;Lscala/collection/IterableOnce;I)Z
  #183 = NameAndType        #181:#182     // startsWith$extension:(Ljava/lang/Object;Lscala/collection/IterableOnce;I)Z
  #184 = Methodref          #173.#183     // scala/collection/ArrayOps$.startsWith$extension:(Ljava/lang/Object;Lscala/collection/IterableOnce;I)Z
  #185 = Utf8               qual$1
  #186 = Utf8               Ljava/lang/Object;
  #187 = Utf8               x$1
  #188 = Utf8               x$2
  #189 = Utf8               toString
  #190 = Utf8               wrapRefArray
  #191 = Utf8               ([Ljava/lang/Object;)Lscala/collection/mutable/ArraySeq$ofRef;
  #192 = NameAndType        #190:#191     // wrapRefArray:([Ljava/lang/Object;)Lscala/collection/mutable/ArraySeq$ofRef;
  #193 = Methodref          #120.#192     // scala/Predef$.wrapRefArray:([Ljava/lang/Object;)Lscala/collection/mutable/ArraySeq$ofRef;
  #194 = Utf8               /
  #195 = String             #194          // /
  #196 = Utf8               mkString
  #197 = Utf8               (Ljava/lang/String;)Ljava/lang/String;
  #198 = NameAndType        #196:#197     // mkString:(Ljava/lang/String;)Ljava/lang/String;
  #199 = Methodref          #21.#198      // scala/collection/mutable/ArraySeq$ofRef.mkString:(Ljava/lang/String;)Ljava/lang/String;
  #200 = Utf8               hashCode
  #201 = Utf8               ()I
  #202 = Utf8               scala/collection/Seq
  #203 = Class              #202          // scala/collection/Seq
  #204 = NameAndType        #200:#201     // hashCode:()I
  #205 = InterfaceMethodref #203.#204     // scala/collection/Seq.hashCode:()I
  #206 = Utf8               equals
  #207 = Utf8               (Ljava/lang/Object;)Z
  #208 = Utf8               o
  #209 = NameAndType        #206:#207     // equals:(Ljava/lang/Object;)Z
  #210 = Methodref          #4.#209       // java/lang/Object.equals:(Ljava/lang/Object;)Z
  #211 = Utf8               os/RelPath
  #212 = Class              #211          // os/RelPath
  #213 = Methodref          #212.#104     // os/RelPath.segments:()Lscala/collection/immutable/IndexedSeq;
  #214 = NameAndType        #118:#201     // ups:()I
  #215 = Methodref          #212.#214     // os/RelPath.ups:()I
  #216 = Utf8               toNIO
  #217 = Utf8               ()Ljava/nio/file/Path;
  #218 = NameAndType        #189:#75      // toString:()Ljava/lang/String;
  #219 = Methodref          #2.#218       // os/SubPath.toString:()Ljava/lang/String;
  #220 = Utf8               java/nio/file/Paths
  #221 = Class              #220          // java/nio/file/Paths
  #222 = Utf8               get
  #223 = Utf8               (Ljava/lang/String;[Ljava/lang/String;)Ljava/nio/file/Path;
  #224 = NameAndType        #222:#223     // get:(Ljava/lang/String;[Ljava/lang/String;)Ljava/nio/file/Path;
  #225 = Methodref          #221.#224     // java/nio/file/Paths.get:(Ljava/lang/String;[Ljava/lang/String;)Ljava/nio/file/Path;
  #226 = Utf8               resolveFrom
  #227 = Utf8               (Los/Path;)Los/Path;
  #228 = Utf8               os/PathChunk$
  #229 = Class              #228          // os/PathChunk$
  #230 = Utf8               Los/PathChunk$;
  #231 = NameAndType        #34:#230      // MODULE$:Los/PathChunk$;
  #232 = Fieldref           #229.#231     // os/PathChunk$.MODULE$:Los/PathChunk$;
  #233 = Utf8               (Los/SubPath;)Los/PathChunk$SubPathChunk;
  #234 = NameAndType        #19:#233      // SubPathChunk:(Los/SubPath;)Los/PathChunk$SubPathChunk;
  #235 = Methodref          #229.#234     // os/PathChunk$.SubPathChunk:(Los/SubPath;)Los/PathChunk$SubPathChunk;
  #236 = Utf8               os/Path
  #237 = Class              #236          // os/Path
  #238 = Utf8               (Los/PathChunk;)Los/Path;
  #239 = NameAndType        #56:#238      // $div:(Los/PathChunk;)Los/Path;
  #240 = Methodref          #237.#239     // os/Path.$div:(Los/PathChunk;)Los/Path;
  #241 = Utf8               Los/Path;
  #242 = Utf8               (Los/BasePath;)Z
  #243 = NameAndType        #164:#165     // startsWith:(Los/SubPath;)Z
  #244 = Methodref          #2.#243       // os/SubPath.startsWith:(Los/SubPath;)Z
  #245 = Utf8               (Los/BasePath;)Los/RelPath;
  #246 = NameAndType        #151:#152     // relativeTo:(Los/SubPath;)Los/RelPath;
  #247 = Methodref          #2.#246       // os/SubPath.relativeTo:(Los/SubPath;)Los/RelPath;
  #248 = Utf8               (Lscala/collection/immutable/Seq;I)Los/BasePath;
  #249 = NameAndType        #114:#115     // make:(Lscala/collection/immutable/Seq;I)Los/SubPath;
  #250 = Methodref          #2.#249       // os/SubPath.make:(Lscala/collection/immutable/Seq;I)Los/SubPath;
  #251 = Utf8               ()Lscala/collection/IterableOnce;
  #252 = Utf8               ()V
  #253 = NameAndType        #145:#252     // "<init>":()V
  #254 = Methodref          #4.#253       // java/lang/Object."<init>":()V
  #255 = Utf8               $init$
  #256 = Utf8               (Los/BasePath;)V
  #257 = NameAndType        #255:#256     // $init$:(Los/BasePath;)V
  #258 = InterfaceMethodref #91.#257      // os/BasePath.$init$:(Los/BasePath;)V
  #259 = Utf8               (Los/BasePathImpl;)V
  #260 = NameAndType        #255:#259     // $init$:(Los/BasePathImpl;)V
  #261 = InterfaceMethodref #8.#260       // os/BasePathImpl.$init$:(Los/BasePathImpl;)V
  #262 = Utf8               (Los/SegmentedPath;)V
  #263 = NameAndType        #255:#262     // $init$:(Los/SegmentedPath;)V
  #264 = InterfaceMethodref #10.#263      // os/SegmentedPath.$init$:(Los/SegmentedPath;)V
  #265 = Utf8               Signature
  #266 = Utf8               Code
  #267 = Utf8               MethodParameters
  #268 = Utf8               LineNumberTable
  #269 = Utf8               LocalVariableTable
  #270 = Utf8               StackMapTable
  #271 = Utf8               InnerClasses
  #272 = Utf8               SourceFile
  #273 = Utf8               RuntimeVisibleAnnotations
  #274 = Utf8               ScalaInlineInfo
  #275 = Utf8               ScalaSig
{
  private final java.lang.String[] segments0;
    descriptor: [Ljava/lang/String;
    flags: (0x0012) ACC_PRIVATE, ACC_FINAL

  private final scala.collection.immutable.IndexedSeq<java.lang.String> segments;
    descriptor: Lscala/collection/immutable/IndexedSeq;
    flags: (0x0012) ACC_PRIVATE, ACC_FINAL
    Signature: #29                          // Lscala/collection/immutable/IndexedSeq<Ljava/lang/String;>;

  public static os.SubPath sub();
    descriptor: ()Los/SubPath;
    flags: (0x0009) ACC_PUBLIC, ACC_STATIC
    Code:
      stack=1, locals=0, args_size=0
         0: getstatic     #37                 // Field os/SubPath$.MODULE$:Los/SubPath$;
         3: invokevirtual #39                 // Method os/SubPath$.sub:()Los/SubPath;
         6: areturn

  public static scala.math.Ordering<os.SubPath> subPathOrdering();
    descriptor: ()Lscala/math/Ordering;
    flags: (0x0009) ACC_PUBLIC, ACC_STATIC
    Code:
      stack=1, locals=0, args_size=0
         0: getstatic     #37                 // Field os/SubPath$.MODULE$:Los/SubPath$;
         3: invokevirtual #44                 // Method os/SubPath$.subPathOrdering:()Lscala/math/Ordering;
         6: areturn
    Signature: #42                          // ()Lscala/math/Ordering<Los/SubPath;>;

  public static os.SubPath apply(scala.collection.immutable.IndexedSeq<java.lang.String>);
    descriptor: (Lscala/collection/immutable/IndexedSeq;)Los/SubPath;
    flags: (0x0009) ACC_PUBLIC, ACC_STATIC
    Code:
      stack=2, locals=1, args_size=1
         0: getstatic     #37                 // Field os/SubPath$.MODULE$:Los/SubPath$;
         3: aload_0
         4: invokevirtual #49                 // Method os/SubPath$.apply:(Lscala/collection/immutable/IndexedSeq;)Los/SubPath;
         7: areturn
    Signature: #47                          // (Lscala/collection/immutable/IndexedSeq<Ljava/lang/String;>;)Los/SubPath;
    MethodParameters:
      Name                           Flags
      segments0                      final

  public static <T extends java.lang.Object> os.SubPath apply(T, os.PathConvertible<T>);
    descriptor: (Ljava/lang/Object;Los/PathConvertible;)Los/SubPath;
    flags: (0x0009) ACC_PUBLIC, ACC_STATIC
    Code:
      stack=3, locals=2, args_size=2
         0: getstatic     #37                 // Field os/SubPath$.MODULE$:Los/SubPath$;
         3: aload_0
         4: aload_1
         5: invokevirtual #55                 // Method os/SubPath$.apply:(Ljava/lang/Object;Los/PathConvertible;)Los/SubPath;
         8: areturn
    Signature: #51                          // <T:Ljava/lang/Object;>(TT;Los/PathConvertible<TT;>;)Los/SubPath;
    MethodParameters:
      Name                           Flags
      f0                             final
      evidence$3                     final

  public os.BasePath $div(os.PathChunk);
    descriptor: (Los/PathChunk;)Los/BasePath;
    flags: (0x0001) ACC_PUBLIC
    Code:
      stack=2, locals=2, args_size=2
         0: aload_0
         1: aload_1
         2: invokestatic  #62                 // InterfaceMethod os/SegmentedPath.$div$:(Los/SegmentedPath;Los/PathChunk;)Los/BasePath;
         5: areturn
      LineNumberTable:
        line 316: 0
      LocalVariableTable:
        Start  Length  Slot  Name   Signature
            0       6     0  this   Los/SubPath;
            0       6     1 chunk   Los/PathChunk;
    MethodParameters:
      Name                           Flags
      chunk                          final

  public boolean endsWith(os.RelPath);
    descriptor: (Los/RelPath;)Z
    flags: (0x0001) ACC_PUBLIC
    Code:
      stack=2, locals=2, args_size=2
         0: aload_0
         1: aload_1
         2: invokestatic  #72                 // InterfaceMethod os/SegmentedPath.endsWith$:(Los/SegmentedPath;Los/RelPath;)Z
         5: ireturn
      LineNumberTable:
        line 316: 0
      LocalVariableTable:
        Start  Length  Slot  Name   Signature
            0       6     0  this   Los/SubPath;
            0       6     1 target   Los/RelPath;
    MethodParameters:
      Name                           Flags
      target                         final

  public java.lang.String ext();
    descriptor: ()Ljava/lang/String;
    flags: (0x0001) ACC_PUBLIC
    Code:
      stack=1, locals=1, args_size=1
         0: aload_0
         1: invokestatic  #79                 // InterfaceMethod os/BasePathImpl.ext$:(Los/BasePathImpl;)Ljava/lang/String;
         4: areturn
      LineNumberTable:
        line 316: 0
      LocalVariableTable:
        Start  Length  Slot  Name   Signature
            0       5     0  this   Los/SubPath;

  public java.lang.String baseName();
    descriptor: ()Ljava/lang/String;
    flags: (0x0001) ACC_PUBLIC
    Code:
      stack=1, locals=1, args_size=1
         0: aload_0
         1: invokestatic  #83                 // InterfaceMethod os/BasePathImpl.baseName$:(Los/BasePathImpl;)Ljava/lang/String;
         4: areturn
      LineNumberTable:
        line 316: 0
      LocalVariableTable:
        Start  Length  Slot  Name   Signature
            0       5     0  this   Los/SubPath;

  public java.lang.String last();
    descriptor: ()Ljava/lang/String;
    flags: (0x0001) ACC_PUBLIC
    Code:
      stack=1, locals=1, args_size=1
         0: aload_0
         1: invokestatic  #87                 // InterfaceMethod os/BasePathImpl.last$:(Los/BasePathImpl;)Ljava/lang/String;
         4: areturn
      LineNumberTable:
        line 316: 0
      LocalVariableTable:
        Start  Length  Slot  Name   Signature
            0       5     0  this   Los/SubPath;

  public os.SubPath subRelativeTo(os.BasePath);
    descriptor: (Los/BasePath;)Los/SubPath;
    flags: (0x0001) ACC_PUBLIC
    Code:
      stack=2, locals=2, args_size=2
         0: aload_0
         1: aload_1
         2: invokestatic  #95                 // InterfaceMethod os/BasePath.subRelativeTo$:(Los/BasePath;Los/BasePath;)Los/SubPath;
         5: areturn
      LineNumberTable:
        line 316: 0
      LocalVariableTable:
        Start  Length  Slot  Name   Signature
            0       6     0  this   Los/SubPath;
            0       6     1 target   Los/BasePath;
    MethodParameters:
      Name                           Flags
      target                         final

  public java.lang.String[] segments0();
    descriptor: ()[Ljava/lang/String;
    flags: (0x0001) ACC_PUBLIC
    Code:
      stack=1, locals=1, args_size=1
         0: aload_0
         1: getfield      #99                 // Field segments0:[Ljava/lang/String;
         4: areturn
      LineNumberTable:
        line 316: 0
      LocalVariableTable:
        Start  Length  Slot  Name   Signature
            0       5     0  this   Los/SubPath;

  public scala.Option<java.lang.String> lastOpt();
    descriptor: ()Lscala/Option;
    flags: (0x0001) ACC_PUBLIC
    Code:
      stack=1, locals=1, args_size=1
         0: aload_0
         1: invokevirtual #105                // Method segments:()Lscala/collection/immutable/IndexedSeq;
         4: invokeinterface #110,  1          // InterfaceMethod scala/collection/immutable/IndexedSeq.lastOption:()Lscala/Option;
         9: areturn
      LineNumberTable:
        line 318: 0
      LocalVariableTable:
        Start  Length  Slot  Name   Signature
            0      10     0  this   Los/SubPath;
    Signature: #102                         // ()Lscala/Option<Ljava/lang/String;>;

  public scala.collection.immutable.IndexedSeq<java.lang.String> segments();
    descriptor: ()Lscala/collection/immutable/IndexedSeq;
    flags: (0x0001) ACC_PUBLIC
    Code:
      stack=1, locals=1, args_size=1
         0: aload_0
         1: getfield      #113                // Field segments:Lscala/collection/immutable/IndexedSeq;
         4: areturn
      LineNumberTable:
        line 319: 0
      LocalVariableTable:
        Start  Length  Slot  Name   Signature
            0       5     0  this   Los/SubPath;
    Signature: #111                         // ()Lscala/collection/immutable/IndexedSeq<Ljava/lang/String;>;

  public os.SubPath make(scala.collection.immutable.Seq<java.lang.String>, int);
    descriptor: (Lscala/collection/immutable/Seq;I)Los/SubPath;
    flags: (0x0001) ACC_PUBLIC
    Code:
      stack=5, locals=3, args_size=3
         0: getstatic     #123                // Field scala/Predef$.MODULE$:Lscala/Predef$;
         3: iload_2
         4: iconst_0
         5: if_icmpne     12
         8: iconst_1
         9: goto          13
        12: iconst_0
        13: invokevirtual #127                // Method scala/Predef$.require:(Z)V
        16: new           #2                  // class os/SubPath
        19: dup
        20: aload_1
        21: getstatic     #132                // Field scala/reflect/ClassTag$.MODULE$:Lscala/reflect/ClassTag$;
        24: ldc           #134                // class java/lang/String
        26: invokevirtual #137                // Method scala/reflect/ClassTag$.apply:(Ljava/lang/Class;)Lscala/reflect/ClassTag;
        29: invokeinterface #143,  2          // InterfaceMethod scala/collection/immutable/Seq.toArray:(Lscala/reflect/ClassTag;)Ljava/lang/Object;
        34: checkcast     #144                // class "[Ljava/lang/String;"
        37: invokespecial #148                // Method "<init>":([Ljava/lang/String;)V
        40: areturn
      StackMapTable: number_of_entries = 2
        frame_type = 76 /* same_locals_1_stack_item */
          stack = [ class scala/Predef$ ]
        frame_type = 255 /* full_frame */
          offset_delta = 0
          locals = [ class os/SubPath, class scala/collection/immutable/Seq, int ]
          stack = [ class scala/Predef$, int ]
      LineNumberTable:
        line 322: 0
        line 323: 16
      LocalVariableTable:
        Start  Length  Slot  Name   Signature
            0      41     0  this   Los/SubPath;
            0      41     1     p   Lscala/collection/immutable/Seq;
            0      41     2   ups   I
    Signature: #116                         // (Lscala/collection/immutable/Seq<Ljava/lang/String;>;I)Los/SubPath;
    MethodParameters:
      Name                           Flags
      p                              final
      ups                            final

  public os.RelPath relativeTo(os.SubPath);
    descriptor: (Los/SubPath;)Los/RelPath;
    flags: (0x0001) ACC_PUBLIC
    Code:
      stack=4, locals=2, args_size=2
         0: getstatic     #37                 // Field os/SubPath$.MODULE$:Los/SubPath$;
         3: aload_0
         4: invokevirtual #155                // Method segments0:()[Ljava/lang/String;
         7: getstatic     #123                // Field scala/Predef$.MODULE$:Lscala/Predef$;
        10: aload_1
        11: invokevirtual #155                // Method segments0:()[Ljava/lang/String;
        14: invokevirtual #159                // Method scala/Predef$.copyArrayToImmutableIndexedSeq:(Ljava/lang/Object;)Lscala/collection/immutable/IndexedSeq;
        17: invokevirtual #163                // Method os/SubPath$.relativeTo0:([Ljava/lang/String;Lscala/collection/immutable/IndexedSeq;)Los/RelPath;
        20: areturn
      LineNumberTable:
        line 326: 0
      LocalVariableTable:
        Start  Length  Slot  Name   Signature
            0      21     0  this   Los/SubPath;
            0      21     1  base   Los/SubPath;
    MethodParameters:
      Name                           Flags
      base                           final

  public boolean startsWith(os.SubPath);
    descriptor: (Los/SubPath;)Z
    flags: (0x0001) ACC_PUBLIC
    Code:
      stack=4, locals=5, args_size=2
         0: getstatic     #123                // Field scala/Predef$.MODULE$:Lscala/Predef$;
         3: aload_0
         4: invokevirtual #155                // Method segments0:()[Ljava/lang/String;
         7: checkcast     #167                // class "[Ljava/lang/Object;"
        10: invokevirtual #171                // Method scala/Predef$.refArrayOps:([Ljava/lang/Object;)Ljava/lang/Object;
        13: astore_2
        14: aload_1
        15: invokevirtual #105                // Method segments:()Lscala/collection/immutable/IndexedSeq;
        18: astore_3
        19: getstatic     #176                // Field scala/collection/ArrayOps$.MODULE$:Lscala/collection/ArrayOps$;
        22: aload_2
        23: invokevirtual #180                // Method scala/collection/ArrayOps$.startsWith$default$2$extension:(Ljava/lang/Object;)I
        26: istore        4
        28: getstatic     #176                // Field scala/collection/ArrayOps$.MODULE$:Lscala/collection/ArrayOps$;
        31: aload_2
        32: aload_3
        33: iload         4
        35: invokevirtual #184                // Method scala/collection/ArrayOps$.startsWith$extension:(Ljava/lang/Object;Lscala/collection/IterableOnce;I)Z
        38: ireturn
      LineNumberTable:
        line 328: 0
      LocalVariableTable:
        Start  Length  Slot  Name   Signature
           14      24     2 qual$1   Ljava/lang/Object;
           19      19     3   x$1   Lscala/collection/immutable/IndexedSeq;
           28      10     4   x$2   I
            0      39     0  this   Los/SubPath;
            0      39     1 target   Los/SubPath;
    MethodParameters:
      Name                           Flags
      target                         final

  public java.lang.String toString();
    descriptor: ()Ljava/lang/String;
    flags: (0x0001) ACC_PUBLIC
    Code:
      stack=2, locals=1, args_size=1
         0: getstatic     #123                // Field scala/Predef$.MODULE$:Lscala/Predef$;
         3: aload_0
         4: invokevirtual #155                // Method segments0:()[Ljava/lang/String;
         7: checkcast     #167                // class "[Ljava/lang/Object;"
        10: invokevirtual #193                // Method scala/Predef$.wrapRefArray:([Ljava/lang/Object;)Lscala/collection/mutable/ArraySeq$ofRef;
        13: ldc           #195                // String /
        15: invokevirtual #199                // Method scala/collection/mutable/ArraySeq$ofRef.mkString:(Ljava/lang/String;)Ljava/lang/String;
        18: areturn
      LineNumberTable:
        line 330: 0
      LocalVariableTable:
        Start  Length  Slot  Name   Signature
            0      19     0  this   Los/SubPath;

  public int hashCode();
    descriptor: ()I
    flags: (0x0001) ACC_PUBLIC
    Code:
      stack=1, locals=1, args_size=1
         0: aload_0
         1: invokevirtual #105                // Method segments:()Lscala/collection/immutable/IndexedSeq;
         4: invokeinterface #205,  1          // InterfaceMethod scala/collection/Seq.hashCode:()I
         9: ireturn
      LineNumberTable:
        line 331: 0
      LocalVariableTable:
        Start  Length  Slot  Name   Signature
            0      10     0  this   Los/SubPath;

  public boolean equals(java.lang.Object);
    descriptor: (Ljava/lang/Object;)Z
    flags: (0x0001) ACC_PUBLIC
    Code:
      stack=2, locals=8, args_size=2
         0: aload_1
         1: astore_3
         2: aload_3
         3: instanceof    #2                  // class os/SubPath
         6: ifeq          56
         9: aload_3
        10: checkcast     #2                  // class os/SubPath
        13: astore        4
        15: aload_0
        16: invokevirtual #105                // Method segments:()Lscala/collection/immutable/IndexedSeq;
        19: aload         4
        21: invokevirtual #105                // Method segments:()Lscala/collection/immutable/IndexedSeq;
        24: astore        5
        26: dup
        27: ifnonnull     39
        30: pop
        31: aload         5
        33: ifnull        47
        36: goto          51
        39: aload         5
        41: invokevirtual #210                // Method java/lang/Object.equals:(Ljava/lang/Object;)Z
        44: ifeq          51
        47: iconst_1
        48: goto          52
        51: iconst_0
        52: istore_2
        53: goto          130
        56: goto          59
        59: aload_3
        60: instanceof    #212                // class os/RelPath
        63: ifeq          122
        66: aload_3
        67: checkcast     #212                // class os/RelPath
        70: astore        6
        72: aload_0
        73: invokevirtual #105                // Method segments:()Lscala/collection/immutable/IndexedSeq;
        76: aload         6
        78: invokevirtual #213                // Method os/RelPath.segments:()Lscala/collection/immutable/IndexedSeq;
        81: astore        7
        83: dup
        84: ifnonnull     96
        87: pop
        88: aload         7
        90: ifnull        104
        93: goto          117
        96: aload         7
        98: invokevirtual #210                // Method java/lang/Object.equals:(Ljava/lang/Object;)Z
       101: ifeq          117
       104: aload         6
       106: invokevirtual #215                // Method os/RelPath.ups:()I
       109: iconst_0
       110: if_icmpne     117
       113: iconst_1
       114: goto          118
       117: iconst_0
       118: istore_2
       119: goto          130
       122: goto          125
       125: iconst_0
       126: istore_2
       127: goto          130
       130: iload_2
       131: ireturn
      StackMapTable: number_of_entries = 13
        frame_type = 255 /* full_frame */
          offset_delta = 39
          locals = [ class os/SubPath, class java/lang/Object, top, class java/lang/Object, class os/SubPath, class scala/collection/immutable/IndexedSeq ]
          stack = [ class scala/collection/immutable/IndexedSeq ]
        frame_type = 7 /* same */
        frame_type = 3 /* same */
        frame_type = 64 /* same_locals_1_stack_item */
          stack = [ int ]
        frame_type = 249 /* chop */
          offset_delta = 3
        frame_type = 2 /* same */
        frame_type = 255 /* full_frame */
          offset_delta = 36
          locals = [ class os/SubPath, class java/lang/Object, top, class java/lang/Object, top, top, class os/RelPath, class scala/collection/immutable/IndexedSeq ]
          stack = [ class scala/collection/immutable/IndexedSeq ]
        frame_type = 7 /* same */
        frame_type = 12 /* same */
        frame_type = 64 /* same_locals_1_stack_item */
          stack = [ int ]
        frame_type = 255 /* full_frame */
          offset_delta = 3
          locals = [ class os/SubPath, class java/lang/Object, top, class java/lang/Object ]
          stack = []
        frame_type = 2 /* same */
        frame_type = 255 /* full_frame */
          offset_delta = 4
          locals = [ class os/SubPath, class java/lang/Object, int, class java/lang/Object ]
          stack = []
      LineNumberTable:
        line 332: 0
        line 333: 2
        line 334: 59
        line 335: 125
        line 332: 130
      LocalVariableTable:
        Start  Length  Slot  Name   Signature
            0     132     0  this   Los/SubPath;
            0     132     1     o   Ljava/lang/Object;
    MethodParameters:
      Name                           Flags
      o                              final

  public java.nio.file.Path toNIO();
    descriptor: ()Ljava/nio/file/Path;
    flags: (0x0001) ACC_PUBLIC
    Code:
      stack=2, locals=1, args_size=1
         0: aload_0
         1: invokevirtual #219                // Method toString:()Ljava/lang/String;
         4: iconst_0
         5: anewarray     #134                // class java/lang/String
         8: invokestatic  #225                // Method java/nio/file/Paths.get:(Ljava/lang/String;[Ljava/lang/String;)Ljava/nio/file/Path;
        11: areturn
      LineNumberTable:
        line 338: 0
      LocalVariableTable:
        Start  Length  Slot  Name   Signature
            0      12     0  this   Los/SubPath;

  public os.Path resolveFrom(os.Path);
    descriptor: (Los/Path;)Los/Path;
    flags: (0x0001) ACC_PUBLIC
    Code:
      stack=3, locals=2, args_size=2
         0: aload_1
         1: getstatic     #232                // Field os/PathChunk$.MODULE$:Los/PathChunk$;
         4: aload_0
         5: invokevirtual #235                // Method os/PathChunk$.SubPathChunk:(Los/SubPath;)Los/PathChunk$SubPathChunk;
         8: invokevirtual #240                // Method os/Path.$div:(Los/PathChunk;)Los/Path;
        11: areturn
      LineNumberTable:
        line 340: 0
      LocalVariableTable:
        Start  Length  Slot  Name   Signature
            0      12     0  this   Los/SubPath;
            0      12     1  base   Los/Path;
    MethodParameters:
      Name                           Flags
      base                           final

  public boolean startsWith(os.BasePath);
    descriptor: (Los/BasePath;)Z
    flags: (0x1041) ACC_PUBLIC, ACC_BRIDGE, ACC_SYNTHETIC
    Code:
      stack=2, locals=2, args_size=2
         0: aload_0
         1: aload_1
         2: checkcast     #2                  // class os/SubPath
         5: invokevirtual #244                // Method startsWith:(Los/SubPath;)Z
         8: ireturn
      LineNumberTable:
        line 316: 0
      LocalVariableTable:
        Start  Length  Slot  Name   Signature
            0       9     0  this   Los/SubPath;
            0       9     1 target   Los/BasePath;
    MethodParameters:
      Name                           Flags
      target                         final

  public os.RelPath relativeTo(os.BasePath);
    descriptor: (Los/BasePath;)Los/RelPath;
    flags: (0x1041) ACC_PUBLIC, ACC_BRIDGE, ACC_SYNTHETIC
    Code:
      stack=2, locals=2, args_size=2
         0: aload_0
         1: aload_1
         2: checkcast     #2                  // class os/SubPath
         5: invokevirtual #247                // Method relativeTo:(Los/SubPath;)Los/RelPath;
         8: areturn
      LineNumberTable:
        line 316: 0
      LocalVariableTable:
        Start  Length  Slot  Name   Signature
            0       9     0  this   Los/SubPath;
            0       9     1 target   Los/BasePath;
    MethodParameters:
      Name                           Flags
      target                         final

  public os.BasePath make(scala.collection.immutable.Seq, int);
    descriptor: (Lscala/collection/immutable/Seq;I)Los/BasePath;
    flags: (0x1041) ACC_PUBLIC, ACC_BRIDGE, ACC_SYNTHETIC
    Code:
      stack=3, locals=3, args_size=3
         0: aload_0
         1: aload_1
         2: iload_2
         3: invokevirtual #250                // Method make:(Lscala/collection/immutable/Seq;I)Los/SubPath;
         6: areturn
      LineNumberTable:
        line 316: 0
      LocalVariableTable:
        Start  Length  Slot  Name   Signature
            0       7     0  this   Los/SubPath;
            0       7     1     p   Lscala/collection/immutable/Seq;
            0       7     2   ups   I
    MethodParameters:
      Name                           Flags
      p                              final
      ups                            final

  public scala.collection.IterableOnce segments();
    descriptor: ()Lscala/collection/IterableOnce;
    flags: (0x1041) ACC_PUBLIC, ACC_BRIDGE, ACC_SYNTHETIC
    Code:
      stack=1, locals=1, args_size=1
         0: aload_0
         1: invokevirtual #105                // Method segments:()Lscala/collection/immutable/IndexedSeq;
         4: areturn
      LineNumberTable:
        line 316: 0
      LocalVariableTable:
        Start  Length  Slot  Name   Signature
            0       5     0  this   Los/SubPath;

  public os.SubPath(java.lang.String[]);
    descriptor: ([Ljava/lang/String;)V
    flags: (0x0001) ACC_PUBLIC
    Code:
      stack=3, locals=2, args_size=2
         0: aload_0
         1: aload_1
         2: putfield      #99                 // Field segments0:[Ljava/lang/String;
         5: aload_0
         6: invokespecial #254                // Method java/lang/Object."<init>":()V
         9: aload_0
        10: invokestatic  #258                // InterfaceMethod os/BasePath.$init$:(Los/BasePath;)V
        13: aload_0
        14: invokestatic  #261                // InterfaceMethod os/BasePathImpl.$init$:(Los/BasePathImpl;)V
        17: aload_0
        18: invokestatic  #264                // InterfaceMethod os/SegmentedPath.$init$:(Los/SegmentedPath;)V
        21: aload_0
        22: getstatic     #123                // Field scala/Predef$.MODULE$:Lscala/Predef$;
        25: aload_1
        26: invokevirtual #159                // Method scala/Predef$.copyArrayToImmutableIndexedSeq:(Ljava/lang/Object;)Lscala/collection/immutable/IndexedSeq;
        29: putfield      #113                // Field segments:Lscala/collection/immutable/IndexedSeq;
        32: return
      LineNumberTable:
        line 316: 0
        line 317: 5
        line 319: 21
        line 316: 32
      LocalVariableTable:
        Start  Length  Slot  Name   Signature
            0      33     0  this   Los/SubPath;
            0      33     1 segments0   [Ljava/lang/String;
    MethodParameters:
      Name                           Flags
      segments0                      final
}
InnerClasses:
  public static #19= #16 of #18;          // SubPathChunk=class os/PathChunk$SubPathChunk of class os/PathChunk
  public static final #24= #21 of #23;    // ofRef=class scala/collection/mutable/ArraySeq$ofRef of class scala/collection/mutable/ArraySeq
SourceFile: "Path.scala"
RuntimeVisibleAnnotations:
  0: #12(#13=s#14)
    scala.reflect.ScalaSignature(
      bytes="\u0006\u0005\u0005-d\u0001\u0002\u000e\u001c\u0001yA\u0001b\f\u0001\u0003\u0006\u0004%\t\u0001\r\u0005\t\u007f\u0001\u0011\t\u0011)A\u0005c!1\u0001\t\u0001C\u00017\u0005CQ\u0001\u0012\u0001\u0005\u0002\u0015Cq!\u0013\u0001C\u0002\u0013\u0005!\n\u0003\u0004U\u0001\u0001\u0006IaS\u0003\u0005+\u0002\u0001!\t\u0003\u0004W\u0001\u0001&\tb\u0016\u0005\u0006E\u0002!\ta\u0019\u0005\u0006S\u0002!\tA\u001b\u0005\u0006a\u0002!\t%\u001d\u0005\u0006e\u0002!\te\u001d\u0005\u0006i\u0002!\t%\u001e\u0005\u0006w\u0002!\t\u0001 \u0005\b\u0003\u001f\u0001A\u0011AA\t\u000f\u001d\t\tc\u0007E\u0001\u0003G1aAG\u000e\t\u0002\u0005\u0015\u0002B\u0002!\u0012\t\u0003\t9\u0003\u0003\u0005\u0002*E!\taGA\u0016\u0011\u001d\t\t$\u0005C\u0001\u0003gAq!!\r\u0012\t\u0003\t)\u0006C\u0005\u0002ZE\u0011\r\u0011b\u0001\u0002\\!A\u00111M\t!\u0002\u0013\ti\u0006C\u0005\u0002fE\u0011\r\u0011\"\u0001\u0002h!9\u0011\u0011N\t!\u0002\u0013\u0011%aB*vEB\u000bG\u000f\u001b\u0006\u00029\u0005\u0011qn]\u0002\u0001\'\u0015\u0001q$J\u0015-!\t\u00013%D\u0001\"\u0015\u0005\u0011\u0013!B:dC2\f\u0017B\u0001\u0013\"\u0005\u0019\te.\u001f*fMB\u0011aeJ\u0007\u00027%\u0011\u0001f\u0007\u0002\t\r&dW\rU1uQB\u0011aEK\u0005\u0003Wm\u0011ABQ1tKB\u000bG\u000f[%na2\u0004\"AJ\u0017\n\u00059Z\"!D*fO6,g\u000e^3e!\u0006$\b.A\u0005tK\u001elWM\u001c;taU\t\u0011\u0007E\u0002!eQJ!aM\u0011\u0003\u000b\u0005\u0013(/Y=\u0011\u0005UbdB\u0001\u001c;!\t9\u0014%D\u00019\u0015\tIT$\u0001\u0004=e>|GOP\u0005\u0003w\u0005\na\u0001\u0015:fI\u00164\u0017BA\u001f?\u0005\u0019\u0019FO]5oO*\u00111(I\u0001\u000bg\u0016<W.\u001a8ugB\u0002\u0013A\u0002\u001fj]&$h\b\u0006\u0002C\u0007B\u0011a\u0005\u0001\u0005\u0006_\r\u0001\r!M\u0001\bY\u0006\u001cHo\u00149u+\u00051\u0005c\u0001\u0011Hi%\u0011\u0001*\t\u0002\u0007\u001fB$\u0018n\u001c8\u0002\u0011M,w-\\3oiN,\u0012a\u0013\t\u0004\u0019F#dBA\'P\u001d\t9d*C\u0001#\u0013\t\u0001\u0016%A\u0004qC\u000e\\\u0017mZ3\n\u0005I\u001b&AC%oI\u0016DX\rZ*fc*\u0011\u0001+I\u0001\ng\u0016<W.\u001a8ug\u0002\u0012\u0001\u0002\u00165jgRK\b/Z\u0001\u0005[\u0006\\W\rF\u0002C1vCQ!\u0017\u0005A\u0002i\u000b\u0011\u0001\u001d\t\u0004\u0019n#\u0014B\u0001/T\u0005\r\u0019V-\u001d\u0005\u0006=\"\u0001\raX\u0001\u0004kB\u001c\bC\u0001\u0011a\u0013\t\t\u0017EA\u0002J]R\f!B]3mCRLg/\u001a+p)\t!w\r\u0005\u0002\'K&\u0011am\u0007\u0002\b%\u0016d\u0007+\u0019;i\u0011\u0015A\u0017\u00021\u0001C\u0003\u0011\u0011\u0017m]3\u0002\u0015M$\u0018M\u001d;t/&$\b\u000e\u0006\u0002l]B\u0011\u0001\u0005\\\u0005\u0003[\u0006\u0012qAQ8pY\u0016\fg\u000eC\u0003p\u0015\u0001\u0007!)\u0001\u0004uCJ<W\r^\u0001\ti>\u001cFO]5oOR\tA\'\u0001\u0005iCND7i\u001c3f)\u0005y\u0016AB3rk\u0006d7\u000f\u0006\u0002lm\")q/\u0004a\u0001q\u0006\tq\u000e\u0005\u0002!s&\u0011!0\t\u0002\u0004\u0003:L\u0018!\u0002;p\u001d&{U#A?\u0011\u0007y\fY!D\u0001\u0000\u0015\u0011\t\t!a\u0001\u0002\t\u0019LG.\u001a\u0006\u0005\u0003\u000b\t9!A\u0002oS>T!!!\u0003\u0002\t)\fg/Y\u0005\u0004\u0003\u001by(\u0001\u0002)bi\"\f1B]3t_24XM\u0012:p[R!\u00111CA\r!\u0011\t)\"a\b\u000f\t\u0005]\u0011\u0011\u0004\u0007\u0001\u0011\u0019Aw\u00021\u0001\u0002\u001cA\u0019a%!\b\n\u0007\u000551$C\u0002V\u0003;\tqaU;c!\u0006$\b\u000e\u0005\u0002\'#M\u0011\u0011c\b\u000b\u0003\u0003G\t1B]3mCRLg/\u001a+paQ)A-!\f\u00020!)qf\u0005a\u0001c!)\u0011j\u0005a\u0001\u0017\u0006)\u0011\r\u001d9msV!\u0011QGA#)\u0011\t9$!\u0015\u0015\u0007\t\u000bI\u0004C\u0005\u0002<Q\t\t\u0011q\u0001\u0002>\u0005QQM^5eK:\u001cW\rJ\u001a\u0011\u000b\u0019\ny$a\u0011\n\u0007\u0005\u00053DA\bQCRD7i\u001c8wKJ$\u0018N\u00197f!\u0011\t9\"!\u0012\u0005\u000f\u0005\u001dCC1\u0001\u0002J\t\tA+E\u0002\u0002La\u00042\u0001IA\'\u0013\r\ty%\t\u0002\b\u001d>$\b.\u001b8h\u0011\u001d\t\u0019\u0006\u0006a\u0001\u0003\u0007\n!A\u001a\u0019\u0015\u0007\t\u000b9\u0006C\u00030+\u0001\u00071*A\btk\n\u0004\u0016\r\u001e5Pe\u0012,\'/\u001b8h+\t\ti\u0006\u0005\u0003M\u0003?\u0012\u0015bAA1\'\nAqJ\u001d3fe&tw-\u0001\ttk\n\u0004\u0016\r\u001e5Pe\u0012,\'/\u001b8hA\u0005\u00191/\u001e2\u0016\u0003\t\u000bAa];cA\u0001"
    )
  ScalaInlineInfo: length = 0x72 (unknown attribute)
   01 00 00 16 00 38 00 39 00 00 91 00 92 00 00 50
   00 4B 00 00 42 00 43 00 00 CE 00 CF 00 00 4A 00
   4B 00 00 C8 00 C9 00 00 54 00 4B 00 00 64 00 65
   00 00 72 00 F8 00 00 72 00 73 00 00 97 00 F5 00
   00 97 00 98 00 00 E2 00 E3 00 00 1B 00 FB 00 00
   1B 00 67 00 00 19 00 61 00 00 A4 00 F2 00 00 A4
   00 A5 00 00 58 00 59 00 00 D8 00 D9 00 00 BD 00
   4B 00
  ScalaSig: length = 0x3 (unknown attribute)
   05 02 00
