Classfile /Users/mw/Projects/slang-braindump/.jar/jar11/assemble/slang-braindump/assemble/content/os/symlink$.class
  Last modified May 29, 2022; size 2402 bytes
  SHA-256 checksum 3a063b43402869cdb758523d9378ca11b8151e00448a73413f1a7ac1b4fd7eb6
  Compiled from "FileOps.scala"
public final class os.symlink$
  minor version: 0
  major version: 52
  flags: (0x0031) ACC_PUBLIC, ACC_FINAL, ACC_SUPER
  this_class: #2                          // os/symlink$
  super_class: #4                         // java/lang/Object
  interfaces: 0, fields: 1, methods: 4, attributes: 3
Constant pool:
    #1 = Utf8               os/symlink$
    #2 = Class              #1            // os/symlink$
    #3 = Utf8               java/lang/Object
    #4 = Class              #3            // java/lang/Object
    #5 = Utf8               FileOps.scala
    #6 = Utf8               MODULE$
    #7 = Utf8               Los/symlink$;
    #8 = Utf8               <clinit>
    #9 = Utf8               ()V
   #10 = Utf8               <init>
   #11 = NameAndType        #10:#9        // "<init>":()V
   #12 = Methodref          #2.#11        // os/symlink$."<init>":()V
   #13 = NameAndType        #6:#7         // MODULE$:Los/symlink$;
   #14 = Fieldref           #2.#13        // os/symlink$.MODULE$:Los/symlink$;
   #15 = Utf8               apply
   #16 = Utf8               (Los/Path;Los/FilePath;Los/PermSet;)V
   #17 = Utf8               link
   #18 = Utf8               dest
   #19 = Utf8               perms
   #20 = Utf8               scala/Array$
   #21 = Class              #20           // scala/Array$
   #22 = Utf8               Lscala/Array$;
   #23 = NameAndType        #6:#22        // MODULE$:Lscala/Array$;
   #24 = Fieldref           #21.#23       // scala/Array$.MODULE$:Lscala/Array$;
   #25 = Utf8               scala/collection/immutable/Nil$
   #26 = Class              #25           // scala/collection/immutable/Nil$
   #27 = Utf8               Lscala/collection/immutable/Nil$;
   #28 = NameAndType        #6:#27        // MODULE$:Lscala/collection/immutable/Nil$;
   #29 = Fieldref           #26.#28       // scala/collection/immutable/Nil$.MODULE$:Lscala/collection/immutable/Nil$;
   #30 = Utf8               scala/reflect/ClassTag$
   #31 = Class              #30           // scala/reflect/ClassTag$
   #32 = Utf8               Lscala/reflect/ClassTag$;
   #33 = NameAndType        #6:#32        // MODULE$:Lscala/reflect/ClassTag$;
   #34 = Fieldref           #31.#33       // scala/reflect/ClassTag$.MODULE$:Lscala/reflect/ClassTag$;
   #35 = Utf8               java/nio/file/attribute/FileAttribute
   #36 = Class              #35           // java/nio/file/attribute/FileAttribute
   #37 = Utf8               (Ljava/lang/Class;)Lscala/reflect/ClassTag;
   #38 = NameAndType        #15:#37       // apply:(Ljava/lang/Class;)Lscala/reflect/ClassTag;
   #39 = Methodref          #31.#38       // scala/reflect/ClassTag$.apply:(Ljava/lang/Class;)Lscala/reflect/ClassTag;
   #40 = Utf8               (Lscala/collection/immutable/Seq;Lscala/reflect/ClassTag;)Ljava/lang/Object;
   #41 = NameAndType        #15:#40       // apply:(Lscala/collection/immutable/Seq;Lscala/reflect/ClassTag;)Ljava/lang/Object;
   #42 = Methodref          #21.#41       // scala/Array$.apply:(Lscala/collection/immutable/Seq;Lscala/reflect/ClassTag;)Ljava/lang/Object;
   #43 = Utf8               [Ljava/nio/file/attribute/FileAttribute;
   #44 = Class              #43           // "[Ljava/nio/file/attribute/FileAttribute;"
   #45 = Utf8               os/PermSet
   #46 = Class              #45           // os/PermSet
   #47 = Utf8               toSet
   #48 = Utf8               ()Ljava/util/Set;
   #49 = NameAndType        #47:#48       // toSet:()Ljava/util/Set;
   #50 = Methodref          #46.#49       // os/PermSet.toSet:()Ljava/util/Set;
   #51 = Utf8               java/nio/file/attribute/PosixFilePermissions
   #52 = Class              #51           // java/nio/file/attribute/PosixFilePermissions
   #53 = Utf8               asFileAttribute
   #54 = Utf8               (Ljava/util/Set;)Ljava/nio/file/attribute/FileAttribute;
   #55 = NameAndType        #53:#54       // asFileAttribute:(Ljava/util/Set;)Ljava/nio/file/attribute/FileAttribute;
   #56 = Methodref          #52.#55       // java/nio/file/attribute/PosixFilePermissions.asFileAttribute:(Ljava/util/Set;)Ljava/nio/file/attribute/FileAttribute;
   #57 = Utf8               [Ljava/lang/Object;
   #58 = Class              #57           // "[Ljava/lang/Object;"
   #59 = Utf8               os/Path
   #60 = Class              #59           // os/Path
   #61 = Utf8               toNIO
   #62 = Utf8               ()Ljava/nio/file/Path;
   #63 = NameAndType        #61:#62       // toNIO:()Ljava/nio/file/Path;
   #64 = Methodref          #60.#63       // os/Path.toNIO:()Ljava/nio/file/Path;
   #65 = Utf8               os/RelPath
   #66 = Class              #65           // os/RelPath
   #67 = Utf8               segments
   #68 = Utf8               ()Lscala/collection/immutable/IndexedSeq;
   #69 = NameAndType        #67:#68       // segments:()Lscala/collection/immutable/IndexedSeq;
   #70 = Methodref          #66.#69       // os/RelPath.segments:()Lscala/collection/immutable/IndexedSeq;
   #71 = Utf8               scala/collection/immutable/IndexedSeq
   #72 = Class              #71           // scala/collection/immutable/IndexedSeq
   #73 = Utf8               isEmpty
   #74 = Utf8               ()Z
   #75 = NameAndType        #73:#74       // isEmpty:()Z
   #76 = InterfaceMethodref #72.#75       // scala/collection/immutable/IndexedSeq.isEmpty:()Z
   #77 = Utf8               ups
   #78 = Utf8               ()I
   #79 = NameAndType        #77:#78       // ups:()I
   #80 = Methodref          #66.#79       // os/RelPath.ups:()I
   #81 = Utf8               .
   #82 = String             #81           // .
   #83 = Utf8               java/lang/String
   #84 = Class              #83           // java/lang/String
   #85 = Utf8               java/nio/file/Paths
   #86 = Class              #85           // java/nio/file/Paths
   #87 = Utf8               get
   #88 = Utf8               (Ljava/lang/String;[Ljava/lang/String;)Ljava/nio/file/Path;
   #89 = NameAndType        #87:#88       // get:(Ljava/lang/String;[Ljava/lang/String;)Ljava/nio/file/Path;
   #90 = Methodref          #86.#89       // java/nio/file/Paths.get:(Ljava/lang/String;[Ljava/lang/String;)Ljava/nio/file/Path;
   #91 = Utf8               os/SubPath
   #92 = Class              #91           // os/SubPath
   #93 = Methodref          #92.#69       // os/SubPath.segments:()Lscala/collection/immutable/IndexedSeq;
   #94 = Utf8               os/FilePath
   #95 = Class              #94           // os/FilePath
   #96 = InterfaceMethodref #95.#63       // os/FilePath.toNIO:()Ljava/nio/file/Path;
   #97 = Utf8               java/nio/file/Files
   #98 = Class              #97           // java/nio/file/Files
   #99 = Utf8               createSymbolicLink
  #100 = Utf8               (Ljava/nio/file/Path;Ljava/nio/file/Path;[Ljava/nio/file/attribute/FileAttribute;)Ljava/nio/file/Path;
  #101 = NameAndType        #99:#100      // createSymbolicLink:(Ljava/nio/file/Path;Ljava/nio/file/Path;[Ljava/nio/file/attribute/FileAttribute;)Ljava/nio/file/Path;
  #102 = Methodref          #98.#101      // java/nio/file/Files.createSymbolicLink:(Ljava/nio/file/Path;Ljava/nio/file/Path;[Ljava/nio/file/attribute/FileAttribute;)Ljava/nio/file/Path;
  #103 = Utf8               permArray
  #104 = Utf8               this
  #105 = Utf8               Los/Path;
  #106 = Utf8               Los/FilePath;
  #107 = Utf8               Los/PermSet;
  #108 = Utf8               java/nio/file/Path
  #109 = Class              #108          // java/nio/file/Path
  #110 = Utf8               apply$default$3
  #111 = Utf8               ()Los/PermSet;
  #112 = Methodref          #4.#11        // java/lang/Object."<init>":()V
  #113 = Utf8               Code
  #114 = Utf8               LineNumberTable
  #115 = Utf8               StackMapTable
  #116 = Utf8               LocalVariableTable
  #117 = Utf8               MethodParameters
  #118 = Utf8               SourceFile
  #119 = Utf8               ScalaInlineInfo
  #120 = Utf8               Scala
{
  public static final os.symlink$ MODULE$;
    descriptor: Los/symlink$;
    flags: (0x0019) ACC_PUBLIC, ACC_STATIC, ACC_FINAL

  public static {};
    descriptor: ()V
    flags: (0x0009) ACC_PUBLIC, ACC_STATIC
    Code:
      stack=2, locals=0, args_size=0
         0: new           #2                  // class os/symlink$
         3: dup
         4: invokespecial #12                 // Method "<init>":()V
         7: putstatic     #14                 // Field MODULE$:Los/symlink$;
        10: return
      LineNumberTable:
        line 332: 0

  public void apply(os.Path, os.FilePath, os.PermSet);
    descriptor: (Los/Path;Los/FilePath;Los/PermSet;)V
    flags: (0x0001) ACC_PUBLIC
    Code:
      stack=4, locals=9, args_size=4
         0: aload_3
         1: ifnonnull     27
         4: getstatic     #24                 // Field scala/Array$.MODULE$:Lscala/Array$;
         7: getstatic     #29                 // Field scala/collection/immutable/Nil$.MODULE$:Lscala/collection/immutable/Nil$;
        10: getstatic     #34                 // Field scala/reflect/ClassTag$.MODULE$:Lscala/reflect/ClassTag$;
        13: ldc           #36                 // class java/nio/file/attribute/FileAttribute
        15: invokevirtual #39                 // Method scala/reflect/ClassTag$.apply:(Ljava/lang/Class;)Lscala/reflect/ClassTag;
        18: invokevirtual #42                 // Method scala/Array$.apply:(Lscala/collection/immutable/Seq;Lscala/reflect/ClassTag;)Ljava/lang/Object;
        21: checkcast     #44                 // class "[Ljava/nio/file/attribute/FileAttribute;"
        24: goto          47
        27: iconst_1
        28: anewarray     #36                 // class java/nio/file/attribute/FileAttribute
        31: dup
        32: iconst_0
        33: aload_3
        34: invokevirtual #50                 // Method os/PermSet.toSet:()Ljava/util/Set;
        37: invokestatic  #56                 // Method java/nio/file/attribute/PosixFilePermissions.asFileAttribute:(Ljava/util/Set;)Ljava/nio/file/attribute/FileAttribute;
        40: aastore
        41: checkcast     #58                 // class "[Ljava/lang/Object;"
        44: checkcast     #44                 // class "[Ljava/nio/file/attribute/FileAttribute;"
        47: astore        5
        49: aload_1
        50: invokevirtual #64                 // Method os/Path.toNIO:()Ljava/nio/file/Path;
        53: aload_2
        54: astore        6
        56: aload         6
        58: instanceof    #66                 // class os/RelPath
        61: ifeq          110
        64: aload         6
        66: checkcast     #66                 // class os/RelPath
        69: astore        7
        71: aload         7
        73: invokevirtual #70                 // Method os/RelPath.segments:()Lscala/collection/immutable/IndexedSeq;
        76: invokeinterface #76,  1           // InterfaceMethod scala/collection/immutable/IndexedSeq.isEmpty:()Z
        81: ifeq          107
        84: aload         7
        86: invokevirtual #80                 // Method os/RelPath.ups:()I
        89: iconst_0
        90: if_icmpne     107
        93: ldc           #82                 // String .
        95: iconst_0
        96: anewarray     #84                 // class java/lang/String
        99: invokestatic  #90                 // Method java/nio/file/Paths.get:(Ljava/lang/String;[Ljava/lang/String;)Ljava/nio/file/Path;
       102: astore        4
       104: goto          172
       107: goto          113
       110: goto          113
       113: aload         6
       115: instanceof    #92                 // class os/SubPath
       118: ifeq          158
       121: aload         6
       123: checkcast     #92                 // class os/SubPath
       126: astore        8
       128: aload         8
       130: invokevirtual #93                 // Method os/SubPath.segments:()Lscala/collection/immutable/IndexedSeq;
       133: invokeinterface #76,  1           // InterfaceMethod scala/collection/immutable/IndexedSeq.isEmpty:()Z
       138: ifeq          155
       141: ldc           #82                 // String .
       143: iconst_0
       144: anewarray     #84                 // class java/lang/String
       147: invokestatic  #90                 // Method java/nio/file/Paths.get:(Ljava/lang/String;[Ljava/lang/String;)Ljava/nio/file/Path;
       150: astore        4
       152: goto          172
       155: goto          161
       158: goto          161
       161: aload_2
       162: invokeinterface #96,  1           // InterfaceMethod os/FilePath.toNIO:()Ljava/nio/file/Path;
       167: astore        4
       169: goto          172
       172: aload         4
       174: aload         5
       176: invokestatic  #102                // Method java/nio/file/Files.createSymbolicLink:(Ljava/nio/file/Path;Ljava/nio/file/Path;[Ljava/nio/file/attribute/FileAttribute;)Ljava/nio/file/Path;
       179: pop
       180: return
      StackMapTable: number_of_entries = 9
        frame_type = 27 /* same */
        frame_type = 83 /* same_locals_1_stack_item */
          stack = [ class "[Ljava/nio/file/attribute/FileAttribute;" ]
        frame_type = 255 /* full_frame */
          offset_delta = 59
          locals = [ class os/symlink$, class os/Path, class os/FilePath, class os/PermSet, top, class "[Ljava/nio/file/attribute/FileAttribute;", class os/FilePath, class os/RelPath ]
          stack = [ class java/nio/file/Path ]
        frame_type = 255 /* full_frame */
          offset_delta = 2
          locals = [ class os/symlink$, class os/Path, class os/FilePath, class os/PermSet, top, class "[Ljava/nio/file/attribute/FileAttribute;", class os/FilePath ]
          stack = [ class java/nio/file/Path ]
        frame_type = 66 /* same_locals_1_stack_item */
          stack = [ class java/nio/file/Path ]
        frame_type = 255 /* full_frame */
          offset_delta = 41
          locals = [ class os/symlink$, class os/Path, class os/FilePath, class os/PermSet, top, class "[Ljava/nio/file/attribute/FileAttribute;", class os/FilePath, top, class os/SubPath ]
          stack = [ class java/nio/file/Path ]
        frame_type = 255 /* full_frame */
          offset_delta = 2
          locals = [ class os/symlink$, class os/Path, class os/FilePath, class os/PermSet, top, class "[Ljava/nio/file/attribute/FileAttribute;", class os/FilePath ]
          stack = [ class java/nio/file/Path ]
        frame_type = 66 /* same_locals_1_stack_item */
          stack = [ class java/nio/file/Path ]
        frame_type = 255 /* full_frame */
          offset_delta = 10
          locals = [ class os/symlink$, class os/Path, class os/FilePath, class os/PermSet, class java/nio/file/Path, class "[Ljava/nio/file/attribute/FileAttribute;", class os/FilePath ]
          stack = [ class java/nio/file/Path ]
      LineNumberTable:
        line 335: 0
        line 336: 27
        line 339: 49
        line 340: 53
        line 343: 56
        line 344: 113
        line 345: 161
        line 340: 172
        line 347: 174
        line 338: 180
      LocalVariableTable:
        Start  Length  Slot  Name   Signature
           49     131     5 permArray   [Ljava/nio/file/attribute/FileAttribute;
            0     181     0  this   Los/symlink$;
            0     181     1  link   Los/Path;
            0     181     2  dest   Los/FilePath;
            0     181     3 perms   Los/PermSet;
    MethodParameters:
      Name                           Flags
      link                           final
      dest                           final
      perms                          final

  public os.PermSet apply$default$3();
    descriptor: ()Los/PermSet;
    flags: (0x0001) ACC_PUBLIC
    Code:
      stack=1, locals=1, args_size=1
         0: aconst_null
         1: areturn
      LineNumberTable:
        line 333: 0
      LocalVariableTable:
        Start  Length  Slot  Name   Signature
            0       2     0  this   Los/symlink$;

  private os.symlink$();
    descriptor: ()V
    flags: (0x0002) ACC_PRIVATE
    Code:
      stack=1, locals=1, args_size=1
         0: aload_0
         1: invokespecial #112                // Method java/lang/Object."<init>":()V
         4: return
      LineNumberTable:
        line 358: 0
        line 332: 4
      LocalVariableTable:
        Start  Length  Slot  Name   Signature
            0       5     0  this   Los/symlink$;
}
SourceFile: "FileOps.scala"
  ScalaInlineInfo: length = 0x13 (unknown attribute)
   01 01 00 03 00 0A 00 09 01 00 0F 00 10 01 00 6E
   00 6F 01
  Scala: length = 0x0 (unknown attribute)

