Classfile /Users/mw/Projects/slang-braindump/.jar/jar11/assemble/slang-braindump/assemble/content/os/temp.class
  Last modified May 29, 2022; size 2163 bytes
  SHA-256 checksum 3fae4968c5bc444edd22583aa96bb1e6d761a0e143946474d450e815c6b46e19
  Compiled from "TempOps.scala"
public final class os.temp
  minor version: 0
  major version: 52
  flags: (0x0031) ACC_PUBLIC, ACC_FINAL, ACC_SUPER
  this_class: #2                          // os/temp
  super_class: #4                         // java/lang/Object
  interfaces: 0, fields: 0, methods: 12, attributes: 3
Constant pool:
   #1 = Utf8               os/temp
   #2 = Class              #1             // os/temp
   #3 = Utf8               java/lang/Object
   #4 = Class              #3             // java/lang/Object
   #5 = Utf8               TempOps.scala
   #6 = Utf8               Lscala/reflect/ScalaSignature;
   #7 = Utf8               bytes
   #8 = Utf8               \u0006\u0005\u0019<Qa\u0004\t\t\u0002M1Q!\u0006\t\t\u0002YAQ!H\u0001\u0005\u0002yAQaH\u0001\u0005\u0002\u0001Bq\u0001R\u0001\u0012\u0002\u0013\u0005Q\tC\u0004Q\u0003E\u0005I\u0011A)\t\u000fM\u000b\u0011\u0013!C\u0001)\"9a+AI\u0001\n\u0003!\u0006bB,\u0002#\u0003%\t\u0001\u0017\u0005\b5\u0006\t\n\u0011\"\u0001\\\u0011\u0015Q\u0013\u0001\"\u0001^\u0011\u001d\u0011\u0017!%A\u0005\u0002ECqaY\u0001\u0012\u0002\u0013\u0005A\u000bC\u0004e\u0003E\u0005I\u0011\u0001-\t\u000f\u0015\f\u0011\u0013!C\u00017\u0006!A/Z7q\u0015\u0005\t\u0012AA8t\u0007\u0001\u0001\"\u0001F\u0001\u000e\u0003A\u0011A\u0001^3naN\u0011\u0011a\u0006\t\u00031mi\u0011!\u0007\u0006\u00025\u0005)1oY1mC&\u0011A$\u0007\u0002\u0007\u0003:L(+\u001a4\u0002\rqJg.\u001b;?)\u0005\u0019\u0012!B1qa2LHcB\u0011%S-B$h\u0010\t\u0003)\tJ!a\t\t\u0003\tA\u000bG\u000f\u001b\u0005\bK\r\u0001\n\u00111\u0001\'\u0003!\u0019wN\u001c;f]R\u001c\bC\u0001\u000b(\u0013\tA\u0003C\u0001\u0004T_V\u00148-\u001a\u0005\bU\r\u0001\n\u00111\u0001\"\u0003\r!\u0017N\u001d\u0005\bY\r\u0001\n\u00111\u0001.\u0003\u0019\u0001(/\u001a4jqB\u0011a&\u000e\b\u0003_M\u0002\"\u0001M\r\u000e\u0003ER!A\r\n\u0002\rq\u0012xn\u001c;?\u0013\t!\u0014$\u0001\u0004Qe\u0016$WMZ\u0005\u0003m]\u0012aa\u0015;sS:<\'B\u0001\u001b\u001a\u0011\u001dI4\u0001%AA\u00025\naa];gM&D\bbB\u001e\u0004!\u0003\u0005\r\u0001P\u0001\rI\u0016dW\r^3P]\u0016C\u0018\u000e\u001e\t\u00031uJ!AP\r\u0003\u000f\t{w\u000e\\3b]\"9\u0001i\u0001I\u0001\u0002\u0004\t\u0015!\u00029fe6\u001c\bC\u0001\u000bC\u0013\t\u0019\u0005CA\u0004QKJl7+\u001a;\u0002\u001f\u0005\u0004\b\u000f\\=%I\u00164\u0017-\u001e7uIE*\u0012A\u0012\u0016\u0003M\u001d[\u0013\u0001\u0013\t\u0003\u0013:k\u0011A\u0013\u0006\u0003\u00172\u000b\u0011\"\u001e8dQ\u0016\u001c7.\u001a3\u000b\u00055K\u0012AC1o]>$\u0018\r^5p]&\u0011qJ\u0013\u0002\u0012k:\u001c\u0007.Z2lK\u00124\u0016M]5b]\u000e,\u0017aD1qa2LH\u0005Z3gCVdG\u000f\n\u001a\u0016\u0003IS#!I$\u0002\u001f\u0005\u0004\b\u000f\\=%I\u00164\u0017-\u001e7uIM*\u0012!\u0016\u0016\u0003[\u001d\u000bq\"\u00199qYf$C-\u001a4bk2$H\u0005N\u0001\u0010CB\u0004H.\u001f\u0013eK\u001a\fW\u000f\u001c;%kU\t\u0011L\u000b\u0002=\u000f\u0006y\u0011\r\u001d9ms\u0012\"WMZ1vYR$c\'F\u0001]U\t\tu\tF\u0003\"=~\u0003\u0017\rC\u0004+\u0015A\u0005\t\u0019A\u0011\t\u000f1R\u0001\u0013!a\u0001[!91H\u0003I\u0001\u0002\u0004a\u0004b\u0002!\u000b!\u0003\u0005\r!Q\u0001\u000eI&\u0014H\u0005Z3gCVdG\u000fJ\u0019\u0002\u001b\u0011L\'\u000f\n3fM\u0006,H\u000e\u001e\u00133\u00035!\u0017N\u001d\u0013eK\u001a\fW\u000f\u001c;%g\u0005iA-\u001b:%I\u00164\u0017-\u001e7uIQ\u0002
   #9 = Utf8               dir$default$4
  #10 = Utf8               ()Los/PermSet;
  #11 = Utf8               os/temp$
  #12 = Class              #11            // os/temp$
  #13 = Utf8               MODULE$
  #14 = Utf8               Los/temp$;
  #15 = NameAndType        #13:#14        // MODULE$:Los/temp$;
  #16 = Fieldref           #12.#15        // os/temp$.MODULE$:Los/temp$;
  #17 = NameAndType        #9:#10         // dir$default$4:()Los/PermSet;
  #18 = Methodref          #12.#17        // os/temp$.dir$default$4:()Los/PermSet;
  #19 = Utf8               dir$default$3
  #20 = Utf8               ()Z
  #21 = NameAndType        #19:#20        // dir$default$3:()Z
  #22 = Methodref          #12.#21        // os/temp$.dir$default$3:()Z
  #23 = Utf8               dir$default$2
  #24 = Utf8               ()Ljava/lang/String;
  #25 = NameAndType        #23:#24        // dir$default$2:()Ljava/lang/String;
  #26 = Methodref          #12.#25        // os/temp$.dir$default$2:()Ljava/lang/String;
  #27 = Utf8               dir$default$1
  #28 = Utf8               ()Los/Path;
  #29 = NameAndType        #27:#28        // dir$default$1:()Los/Path;
  #30 = Methodref          #12.#29        // os/temp$.dir$default$1:()Los/Path;
  #31 = Utf8               dir
  #32 = Utf8               (Los/Path;Ljava/lang/String;ZLos/PermSet;)Los/Path;
  #33 = Utf8               prefix
  #34 = Utf8               deleteOnExit
  #35 = Utf8               perms
  #36 = NameAndType        #31:#32        // dir:(Los/Path;Ljava/lang/String;ZLos/PermSet;)Los/Path;
  #37 = Methodref          #12.#36        // os/temp$.dir:(Los/Path;Ljava/lang/String;ZLos/PermSet;)Los/Path;
  #38 = Utf8               apply$default$6
  #39 = NameAndType        #38:#10        // apply$default$6:()Los/PermSet;
  #40 = Methodref          #12.#39        // os/temp$.apply$default$6:()Los/PermSet;
  #41 = Utf8               apply$default$5
  #42 = NameAndType        #41:#20        // apply$default$5:()Z
  #43 = Methodref          #12.#42        // os/temp$.apply$default$5:()Z
  #44 = Utf8               apply$default$4
  #45 = NameAndType        #44:#24        // apply$default$4:()Ljava/lang/String;
  #46 = Methodref          #12.#45        // os/temp$.apply$default$4:()Ljava/lang/String;
  #47 = Utf8               apply$default$3
  #48 = NameAndType        #47:#24        // apply$default$3:()Ljava/lang/String;
  #49 = Methodref          #12.#48        // os/temp$.apply$default$3:()Ljava/lang/String;
  #50 = Utf8               apply$default$2
  #51 = NameAndType        #50:#28        // apply$default$2:()Los/Path;
  #52 = Methodref          #12.#51        // os/temp$.apply$default$2:()Los/Path;
  #53 = Utf8               apply$default$1
  #54 = Utf8               ()Los/Source;
  #55 = NameAndType        #53:#54        // apply$default$1:()Los/Source;
  #56 = Methodref          #12.#55        // os/temp$.apply$default$1:()Los/Source;
  #57 = Utf8               apply
  #58 = Utf8               (Los/Source;Los/Path;Ljava/lang/String;Ljava/lang/String;ZLos/PermSet;)Los/Path;
  #59 = Utf8               contents
  #60 = Utf8               suffix
  #61 = NameAndType        #57:#58        // apply:(Los/Source;Los/Path;Ljava/lang/String;Ljava/lang/String;ZLos/PermSet;)Los/Path;
  #62 = Methodref          #12.#61        // os/temp$.apply:(Los/Source;Los/Path;Ljava/lang/String;Ljava/lang/String;ZLos/PermSet;)Los/Path;
  #63 = Utf8               Code
  #64 = Utf8               MethodParameters
  #65 = Utf8               SourceFile
  #66 = Utf8               RuntimeVisibleAnnotations
  #67 = Utf8               ScalaSig
{
  public static os.PermSet dir$default$4();
    descriptor: ()Los/PermSet;
    flags: (0x0009) ACC_PUBLIC, ACC_STATIC
    Code:
      stack=1, locals=0, args_size=0
         0: getstatic     #16                 // Field os/temp$.MODULE$:Los/temp$;
         3: invokevirtual #18                 // Method os/temp$.dir$default$4:()Los/PermSet;
         6: areturn

  public static boolean dir$default$3();
    descriptor: ()Z
    flags: (0x0009) ACC_PUBLIC, ACC_STATIC
    Code:
      stack=1, locals=0, args_size=0
         0: getstatic     #16                 // Field os/temp$.MODULE$:Los/temp$;
         3: invokevirtual #22                 // Method os/temp$.dir$default$3:()Z
         6: ireturn

  public static java.lang.String dir$default$2();
    descriptor: ()Ljava/lang/String;
    flags: (0x0009) ACC_PUBLIC, ACC_STATIC
    Code:
      stack=1, locals=0, args_size=0
         0: getstatic     #16                 // Field os/temp$.MODULE$:Los/temp$;
         3: invokevirtual #26                 // Method os/temp$.dir$default$2:()Ljava/lang/String;
         6: areturn

  public static os.Path dir$default$1();
    descriptor: ()Los/Path;
    flags: (0x0009) ACC_PUBLIC, ACC_STATIC
    Code:
      stack=1, locals=0, args_size=0
         0: getstatic     #16                 // Field os/temp$.MODULE$:Los/temp$;
         3: invokevirtual #30                 // Method os/temp$.dir$default$1:()Los/Path;
         6: areturn

  public static os.Path dir(os.Path, java.lang.String, boolean, os.PermSet);
    descriptor: (Los/Path;Ljava/lang/String;ZLos/PermSet;)Los/Path;
    flags: (0x0009) ACC_PUBLIC, ACC_STATIC
    Code:
      stack=5, locals=4, args_size=4
         0: getstatic     #16                 // Field os/temp$.MODULE$:Los/temp$;
         3: aload_0
         4: aload_1
         5: iload_2
         6: aload_3
         7: invokevirtual #37                 // Method os/temp$.dir:(Los/Path;Ljava/lang/String;ZLos/PermSet;)Los/Path;
        10: areturn
    MethodParameters:
      Name                           Flags
      dir                            final
      prefix                         final
      deleteOnExit                   final
      perms                          final

  public static os.PermSet apply$default$6();
    descriptor: ()Los/PermSet;
    flags: (0x0009) ACC_PUBLIC, ACC_STATIC
    Code:
      stack=1, locals=0, args_size=0
         0: getstatic     #16                 // Field os/temp$.MODULE$:Los/temp$;
         3: invokevirtual #40                 // Method os/temp$.apply$default$6:()Los/PermSet;
         6: areturn

  public static boolean apply$default$5();
    descriptor: ()Z
    flags: (0x0009) ACC_PUBLIC, ACC_STATIC
    Code:
      stack=1, locals=0, args_size=0
         0: getstatic     #16                 // Field os/temp$.MODULE$:Los/temp$;
         3: invokevirtual #43                 // Method os/temp$.apply$default$5:()Z
         6: ireturn

  public static java.lang.String apply$default$4();
    descriptor: ()Ljava/lang/String;
    flags: (0x0009) ACC_PUBLIC, ACC_STATIC
    Code:
      stack=1, locals=0, args_size=0
         0: getstatic     #16                 // Field os/temp$.MODULE$:Los/temp$;
         3: invokevirtual #46                 // Method os/temp$.apply$default$4:()Ljava/lang/String;
         6: areturn

  public static java.lang.String apply$default$3();
    descriptor: ()Ljava/lang/String;
    flags: (0x0009) ACC_PUBLIC, ACC_STATIC
    Code:
      stack=1, locals=0, args_size=0
         0: getstatic     #16                 // Field os/temp$.MODULE$:Los/temp$;
         3: invokevirtual #49                 // Method os/temp$.apply$default$3:()Ljava/lang/String;
         6: areturn

  public static os.Path apply$default$2();
    descriptor: ()Los/Path;
    flags: (0x0009) ACC_PUBLIC, ACC_STATIC
    Code:
      stack=1, locals=0, args_size=0
         0: getstatic     #16                 // Field os/temp$.MODULE$:Los/temp$;
         3: invokevirtual #52                 // Method os/temp$.apply$default$2:()Los/Path;
         6: areturn

  public static os.Source apply$default$1();
    descriptor: ()Los/Source;
    flags: (0x0009) ACC_PUBLIC, ACC_STATIC
    Code:
      stack=1, locals=0, args_size=0
         0: getstatic     #16                 // Field os/temp$.MODULE$:Los/temp$;
         3: invokevirtual #56                 // Method os/temp$.apply$default$1:()Los/Source;
         6: areturn

  public static os.Path apply(os.Source, os.Path, java.lang.String, java.lang.String, boolean, os.PermSet);
    descriptor: (Los/Source;Los/Path;Ljava/lang/String;Ljava/lang/String;ZLos/PermSet;)Los/Path;
    flags: (0x0009) ACC_PUBLIC, ACC_STATIC
    Code:
      stack=7, locals=6, args_size=6
         0: getstatic     #16                 // Field os/temp$.MODULE$:Los/temp$;
         3: aload_0
         4: aload_1
         5: aload_2
         6: aload_3
         7: iload         4
         9: aload         5
        11: invokevirtual #62                 // Method os/temp$.apply:(Los/Source;Los/Path;Ljava/lang/String;Ljava/lang/String;ZLos/PermSet;)Los/Path;
        14: areturn
    MethodParameters:
      Name                           Flags
      contents                       final
      dir                            final
      prefix                         final
      suffix                         final
      deleteOnExit                   final
      perms                          final
}
SourceFile: "TempOps.scala"
RuntimeVisibleAnnotations:
  0: #6(#7=s#8)
    scala.reflect.ScalaSignature(
      bytes="\u0006\u0005\u0019<Qa\u0004\t\t\u0002M1Q!\u0006\t\t\u0002YAQ!H\u0001\u0005\u0002yAQaH\u0001\u0005\u0002\u0001Bq\u0001R\u0001\u0012\u0002\u0013\u0005Q\tC\u0004Q\u0003E\u0005I\u0011A)\t\u000fM\u000b\u0011\u0013!C\u0001)\"9a+AI\u0001\n\u0003!\u0006bB,\u0002#\u0003%\t\u0001\u0017\u0005\b5\u0006\t\n\u0011\"\u0001\\\u0011\u0015Q\u0013\u0001\"\u0001^\u0011\u001d\u0011\u0017!%A\u0005\u0002ECqaY\u0001\u0012\u0002\u0013\u0005A\u000bC\u0004e\u0003E\u0005I\u0011\u0001-\t\u000f\u0015\f\u0011\u0013!C\u00017\u0006!A/Z7q\u0015\u0005\t\u0012AA8t\u0007\u0001\u0001\"\u0001F\u0001\u000e\u0003A\u0011A\u0001^3naN\u0011\u0011a\u0006\t\u00031mi\u0011!\u0007\u0006\u00025\u0005)1oY1mC&\u0011A$\u0007\u0002\u0007\u0003:L(+\u001a4\u0002\rqJg.\u001b;?)\u0005\u0019\u0012!B1qa2LHcB\u0011%S-B$h\u0010\t\u0003)\tJ!a\t\t\u0003\tA\u000bG\u000f\u001b\u0005\bK\r\u0001\n\u00111\u0001\'\u0003!\u0019wN\u001c;f]R\u001c\bC\u0001\u000b(\u0013\tA\u0003C\u0001\u0004T_V\u00148-\u001a\u0005\bU\r\u0001\n\u00111\u0001\"\u0003\r!\u0017N\u001d\u0005\bY\r\u0001\n\u00111\u0001.\u0003\u0019\u0001(/\u001a4jqB\u0011a&\u000e\b\u0003_M\u0002\"\u0001M\r\u000e\u0003ER!A\r\n\u0002\rq\u0012xn\u001c;?\u0013\t!\u0014$\u0001\u0004Qe\u0016$WMZ\u0005\u0003m]\u0012aa\u0015;sS:<\'B\u0001\u001b\u001a\u0011\u001dI4\u0001%AA\u00025\naa];gM&D\bbB\u001e\u0004!\u0003\u0005\r\u0001P\u0001\rI\u0016dW\r^3P]\u0016C\u0018\u000e\u001e\t\u00031uJ!AP\r\u0003\u000f\t{w\u000e\\3b]\"9\u0001i\u0001I\u0001\u0002\u0004\t\u0015!\u00029fe6\u001c\bC\u0001\u000bC\u0013\t\u0019\u0005CA\u0004QKJl7+\u001a;\u0002\u001f\u0005\u0004\b\u000f\\=%I\u00164\u0017-\u001e7uIE*\u0012A\u0012\u0016\u0003M\u001d[\u0013\u0001\u0013\t\u0003\u0013:k\u0011A\u0013\u0006\u0003\u00172\u000b\u0011\"\u001e8dQ\u0016\u001c7.\u001a3\u000b\u00055K\u0012AC1o]>$\u0018\r^5p]&\u0011qJ\u0013\u0002\u0012k:\u001c\u0007.Z2lK\u00124\u0016M]5b]\u000e,\u0017aD1qa2LH\u0005Z3gCVdG\u000f\n\u001a\u0016\u0003IS#!I$\u0002\u001f\u0005\u0004\b\u000f\\=%I\u00164\u0017-\u001e7uIM*\u0012!\u0016\u0016\u0003[\u001d\u000bq\"\u00199qYf$C-\u001a4bk2$H\u0005N\u0001\u0010CB\u0004H.\u001f\u0013eK\u001a\fW\u000f\u001c;%kU\t\u0011L\u000b\u0002=\u000f\u0006y\u0011\r\u001d9ms\u0012\"WMZ1vYR$c\'F\u0001]U\t\tu\tF\u0003\"=~\u0003\u0017\rC\u0004+\u0015A\u0005\t\u0019A\u0011\t\u000f1R\u0001\u0013!a\u0001[!91H\u0003I\u0001\u0002\u0004a\u0004b\u0002!\u000b!\u0003\u0005\r!Q\u0001\u000eI&\u0014H\u0005Z3gCVdG\u000fJ\u0019\u0002\u001b\u0011L\'\u000f\n3fM\u0006,H\u000e\u001e\u00133\u00035!\u0017N\u001d\u0013eK\u001a\fW\u000f\u001c;%g\u0005iA-\u001b:%I\u00164\u0017-\u001e7uIQ\u0002"
    )
  ScalaSig: length = 0x3 (unknown attribute)
   05 02 00
