Classfile /Users/mw/Projects/slang-braindump/.jar/jar11/assemble/slang-braindump/assemble/content/os/walk$stream$.class
  Last modified May 29, 2022; size 6249 bytes
  SHA-256 checksum 2ef584590cc2c920f73d22ccc7de4e2ea0fb830f85640a7f97da8400632bb602
  Compiled from "ListOps.scala"
public class os.walk$stream$
  minor version: 0
  major version: 52
  flags: (0x0021) ACC_PUBLIC, ACC_SUPER
  this_class: #2                          // os/walk$stream$
  super_class: #4                         // java/lang/Object
  interfaces: 0, fields: 1, methods: 22, attributes: 5
Constant pool:
    #1 = Utf8               os/walk$stream$
    #2 = Class              #1            // os/walk$stream$
    #3 = Utf8               java/lang/Object
    #4 = Class              #3            // java/lang/Object
    #5 = Utf8               ListOps.scala
    #6 = Utf8               java/lang/invoke/MethodHandles$Lookup
    #7 = Class              #6            // java/lang/invoke/MethodHandles$Lookup
    #8 = Utf8               java/lang/invoke/MethodHandles
    #9 = Class              #8            // java/lang/invoke/MethodHandles
   #10 = Utf8               Lookup
   #11 = Utf8               os/walk
   #12 = Class              #11           // os/walk
   #13 = Utf8               stream$
   #14 = Utf8               os/walk$stream$$anon$2
   #15 = Class              #14           // os/walk$stream$$anon$2
   #16 = Utf8               MODULE$
   #17 = Utf8               Los/walk$stream$;
   #18 = Utf8               <clinit>
   #19 = Utf8               ()V
   #20 = Utf8               <init>
   #21 = NameAndType        #20:#19       // "<init>":()V
   #22 = Methodref          #2.#21        // os/walk$stream$."<init>":()V
   #23 = NameAndType        #16:#17       // MODULE$:Los/walk$stream$;
   #24 = Fieldref           #2.#23        // os/walk$stream$.MODULE$:Los/walk$stream$;
   #25 = Utf8               apply
   #26 = Utf8               (Los/Path;Lscala/Function1;ZZIZ)Lgeny/Generator;
   #27 = Utf8               (Los/Path;Lscala/Function1<Los/Path;Ljava/lang/Object;>;ZZIZ)Lgeny/Generator<Los/Path;>;
   #28 = Utf8               path
   #29 = Utf8               skip
   #30 = Utf8               preOrder
   #31 = Utf8               followLinks
   #32 = Utf8               maxDepth
   #33 = Utf8               includeTarget
   #34 = Utf8               (Ljava/lang/Object;Ljava/lang/Object;)Ljava/lang/Object;
   #35 = MethodType         #34           //  (Ljava/lang/Object;Ljava/lang/Object;)Ljava/lang/Object;
   #36 = Utf8               $anonfun$apply$1$adapted
   #37 = Utf8               (Lscala/Function1;Los/Path;Los/StatInfo;)Ljava/lang/Object;
   #38 = NameAndType        #36:#37       // $anonfun$apply$1$adapted:(Lscala/Function1;Los/Path;Los/StatInfo;)Ljava/lang/Object;
   #39 = Methodref          #2.#38        // os/walk$stream$.$anonfun$apply$1$adapted:(Lscala/Function1;Los/Path;Los/StatInfo;)Ljava/lang/Object;
   #40 = MethodHandle       6:#39         // REF_invokeStatic os/walk$stream$.$anonfun$apply$1$adapted:(Lscala/Function1;Los/Path;Los/StatInfo;)Ljava/lang/Object;
   #41 = Utf8               (Los/Path;Los/StatInfo;)Ljava/lang/Object;
   #42 = MethodType         #41           //  (Los/Path;Los/StatInfo;)Ljava/lang/Object;
   #43 = Integer            5
   #44 = Integer            1
   #45 = Utf8               java/lang/invoke/LambdaMetafactory
   #46 = Class              #45           // java/lang/invoke/LambdaMetafactory
   #47 = Utf8               altMetafactory
   #48 = Utf8               (Ljava/lang/invoke/MethodHandles$Lookup;Ljava/lang/String;Ljava/lang/invoke/MethodType;[Ljava/lang/Object;)Ljava/lang/invoke/CallSite;
   #49 = NameAndType        #47:#48       // altMetafactory:(Ljava/lang/invoke/MethodHandles$Lookup;Ljava/lang/String;Ljava/lang/invoke/MethodType;[Ljava/lang/Object;)Ljava/lang/invoke/CallSite;
   #50 = Methodref          #46.#49       // java/lang/invoke/LambdaMetafactory.altMetafactory:(Ljava/lang/invoke/MethodHandles$Lookup;Ljava/lang/String;Ljava/lang/invoke/MethodType;[Ljava/lang/Object;)Ljava/lang/invoke/CallSite;
   #51 = MethodHandle       6:#50         // REF_invokeStatic java/lang/invoke/LambdaMetafactory.altMetafactory:(Ljava/lang/invoke/MethodHandles$Lookup;Ljava/lang/String;Ljava/lang/invoke/MethodType;[Ljava/lang/Object;)Ljava/lang/invoke/CallSite;
   #52 = Utf8               (Lscala/Function1;)Lscala/Function2;
   #53 = NameAndType        #25:#52       // apply:(Lscala/Function1;)Lscala/Function2;
   #54 = InvokeDynamic      #0:#53        // #0:apply:(Lscala/Function1;)Lscala/Function2;
   #55 = Utf8               attrs
   #56 = Utf8               (Los/Path;Lscala/Function2;ZZIZ)Lgeny/Generator;
   #57 = NameAndType        #55:#56       // attrs:(Los/Path;Lscala/Function2;ZZIZ)Lgeny/Generator;
   #58 = Methodref          #2.#57        // os/walk$stream$.attrs:(Los/Path;Lscala/Function2;ZZIZ)Lgeny/Generator;
   #59 = Utf8               (Ljava/lang/Object;)Ljava/lang/Object;
   #60 = MethodType         #59           //  (Ljava/lang/Object;)Ljava/lang/Object;
   #61 = Utf8               $anonfun$apply$2
   #62 = Utf8               (Lscala/Tuple2;)Los/Path;
   #63 = NameAndType        #61:#62       // $anonfun$apply$2:(Lscala/Tuple2;)Los/Path;
   #64 = Methodref          #2.#63        // os/walk$stream$.$anonfun$apply$2:(Lscala/Tuple2;)Los/Path;
   #65 = MethodHandle       6:#64         // REF_invokeStatic os/walk$stream$.$anonfun$apply$2:(Lscala/Tuple2;)Los/Path;
   #66 = MethodType         #62           //  (Lscala/Tuple2;)Los/Path;
   #67 = Utf8               ()Lscala/Function1;
   #68 = NameAndType        #25:#67       // apply:()Lscala/Function1;
   #69 = InvokeDynamic      #1:#68        // #1:apply:()Lscala/Function1;
   #70 = Utf8               geny/Generator
   #71 = Class              #70           // geny/Generator
   #72 = Utf8               map
   #73 = Utf8               (Lscala/Function1;)Lgeny/Generator;
   #74 = NameAndType        #72:#73       // map:(Lscala/Function1;)Lgeny/Generator;
   #75 = InterfaceMethodref #71.#74       // geny/Generator.map:(Lscala/Function1;)Lgeny/Generator;
   #76 = Utf8               this
   #77 = Utf8               Los/Path;
   #78 = Utf8               Lscala/Function1;
   #79 = Utf8               Z
   #80 = Utf8               I
   #81 = Utf8               apply$default$2
   #82 = Utf8               ()Lscala/Function1<Los/Path;Ljava/lang/Object;>;
   #83 = Utf8               $anonfun$apply$default$2$2$adapted
   #84 = Utf8               (Los/Path;)Ljava/lang/Object;
   #85 = NameAndType        #83:#84       // $anonfun$apply$default$2$2$adapted:(Los/Path;)Ljava/lang/Object;
   #86 = Methodref          #2.#85        // os/walk$stream$.$anonfun$apply$default$2$2$adapted:(Los/Path;)Ljava/lang/Object;
   #87 = MethodHandle       6:#86         // REF_invokeStatic os/walk$stream$.$anonfun$apply$default$2$2$adapted:(Los/Path;)Ljava/lang/Object;
   #88 = MethodType         #84           //  (Los/Path;)Ljava/lang/Object;
   #89 = InvokeDynamic      #2:#68        // #2:apply:()Lscala/Function1;
   #90 = Utf8               apply$default$3
   #91 = Utf8               ()Z
   #92 = Utf8               apply$default$4
   #93 = Utf8               apply$default$5
   #94 = Utf8               ()I
   #95 = Integer            2147483647
   #96 = Utf8               apply$default$6
   #97 = Utf8               (Los/Path;Lscala/Function2<Los/Path;Los/StatInfo;Ljava/lang/Object;>;ZZIZ)Lgeny/Generator<Lscala/Tuple2<Los/Path;Los/StatInfo;>;>;
   #98 = Utf8               scala/Array$
   #99 = Class              #98           // scala/Array$
  #100 = Utf8               Lscala/Array$;
  #101 = NameAndType        #16:#100      // MODULE$:Lscala/Array$;
  #102 = Fieldref           #99.#101      // scala/Array$.MODULE$:Lscala/Array$;
  #103 = Utf8               scala/collection/immutable/Nil$
  #104 = Class              #103          // scala/collection/immutable/Nil$
  #105 = Utf8               Lscala/collection/immutable/Nil$;
  #106 = NameAndType        #16:#105      // MODULE$:Lscala/collection/immutable/Nil$;
  #107 = Fieldref           #104.#106     // scala/collection/immutable/Nil$.MODULE$:Lscala/collection/immutable/Nil$;
  #108 = Utf8               scala/reflect/ClassTag$
  #109 = Class              #108          // scala/reflect/ClassTag$
  #110 = Utf8               Lscala/reflect/ClassTag$;
  #111 = NameAndType        #16:#110      // MODULE$:Lscala/reflect/ClassTag$;
  #112 = Fieldref           #109.#111     // scala/reflect/ClassTag$.MODULE$:Lscala/reflect/ClassTag$;
  #113 = Utf8               java/nio/file/LinkOption
  #114 = Class              #113          // java/nio/file/LinkOption
  #115 = Utf8               (Ljava/lang/Class;)Lscala/reflect/ClassTag;
  #116 = NameAndType        #25:#115      // apply:(Ljava/lang/Class;)Lscala/reflect/ClassTag;
  #117 = Methodref          #109.#116     // scala/reflect/ClassTag$.apply:(Ljava/lang/Class;)Lscala/reflect/ClassTag;
  #118 = Utf8               (Lscala/collection/immutable/Seq;Lscala/reflect/ClassTag;)Ljava/lang/Object;
  #119 = NameAndType        #25:#118      // apply:(Lscala/collection/immutable/Seq;Lscala/reflect/ClassTag;)Ljava/lang/Object;
  #120 = Methodref          #99.#119      // scala/Array$.apply:(Lscala/collection/immutable/Seq;Lscala/reflect/ClassTag;)Ljava/lang/Object;
  #121 = Utf8               [Ljava/nio/file/LinkOption;
  #122 = Class              #121          // "[Ljava/nio/file/LinkOption;"
  #123 = Utf8               NOFOLLOW_LINKS
  #124 = Utf8               Ljava/nio/file/LinkOption;
  #125 = NameAndType        #123:#124     // NOFOLLOW_LINKS:Ljava/nio/file/LinkOption;
  #126 = Fieldref           #114.#125     // java/nio/file/LinkOption.NOFOLLOW_LINKS:Ljava/nio/file/LinkOption;
  #127 = Utf8               [Ljava/lang/Object;
  #128 = Class              #127          // "[Ljava/lang/Object;"
  #129 = Utf8               java/util/HashSet
  #130 = Class              #129          // java/util/HashSet
  #131 = Methodref          #130.#21      // java/util/HashSet."<init>":()V
  #132 = Utf8               java/nio/file/FileVisitOption
  #133 = Class              #132          // java/nio/file/FileVisitOption
  #134 = Utf8               FOLLOW_LINKS
  #135 = Utf8               Ljava/nio/file/FileVisitOption;
  #136 = NameAndType        #134:#135     // FOLLOW_LINKS:Ljava/nio/file/FileVisitOption;
  #137 = Fieldref           #133.#136     // java/nio/file/FileVisitOption.FOLLOW_LINKS:Ljava/nio/file/FileVisitOption;
  #138 = Utf8               add
  #139 = Utf8               (Ljava/lang/Object;)Z
  #140 = NameAndType        #138:#139     // add:(Ljava/lang/Object;)Z
  #141 = Methodref          #130.#140     // java/util/HashSet.add:(Ljava/lang/Object;)Z
  #142 = Utf8               scala/runtime/BoxesRunTime
  #143 = Class              #142          // scala/runtime/BoxesRunTime
  #144 = Utf8               boxToBoolean
  #145 = Utf8               (Z)Ljava/lang/Boolean;
  #146 = NameAndType        #144:#145     // boxToBoolean:(Z)Ljava/lang/Boolean;
  #147 = Methodref          #143.#146     // scala/runtime/BoxesRunTime.boxToBoolean:(Z)Ljava/lang/Boolean;
  #148 = Utf8               scala/runtime/BoxedUnit
  #149 = Class              #148          // scala/runtime/BoxedUnit
  #150 = Utf8               UNIT
  #151 = Utf8               Lscala/runtime/BoxedUnit;
  #152 = NameAndType        #150:#151     // UNIT:Lscala/runtime/BoxedUnit;
  #153 = Fieldref           #149.#152     // scala/runtime/BoxedUnit.UNIT:Lscala/runtime/BoxedUnit;
  #154 = Utf8               os/Path
  #155 = Class              #154          // os/Path
  #156 = Utf8               wrapped
  #157 = Utf8               ()Ljava/nio/file/Path;
  #158 = NameAndType        #156:#157     // wrapped:()Ljava/nio/file/Path;
  #159 = Methodref          #155.#158     // os/Path.wrapped:()Ljava/nio/file/Path;
  #160 = Utf8               java/nio/file/Files
  #161 = Class              #160          // java/nio/file/Files
  #162 = Utf8               exists
  #163 = Utf8               (Ljava/nio/file/Path;[Ljava/nio/file/LinkOption;)Z
  #164 = NameAndType        #162:#163     // exists:(Ljava/nio/file/Path;[Ljava/nio/file/LinkOption;)Z
  #165 = Methodref          #161.#164     // java/nio/file/Files.exists:(Ljava/nio/file/Path;[Ljava/nio/file/LinkOption;)Z
  #166 = Utf8               java/nio/file/NoSuchFileException
  #167 = Class              #166          // java/nio/file/NoSuchFileException
  #168 = Utf8               toString
  #169 = Utf8               ()Ljava/lang/String;
  #170 = NameAndType        #168:#169     // toString:()Ljava/lang/String;
  #171 = Methodref          #4.#170       // java/lang/Object.toString:()Ljava/lang/String;
  #172 = Utf8               (Ljava/lang/String;)V
  #173 = NameAndType        #20:#172      // "<init>":(Ljava/lang/String;)V
  #174 = Methodref          #167.#173     // java/nio/file/NoSuchFileException."<init>":(Ljava/lang/String;)V
  #175 = Utf8               (ZZLos/Path;Ljava/nio/file/Path;Ljava/util/HashSet;ILscala/Function2;)V
  #176 = NameAndType        #20:#175      // "<init>":(ZZLos/Path;Ljava/nio/file/Path;Ljava/util/HashSet;ILscala/Function2;)V
  #177 = Methodref          #15.#176      // os/walk$stream$$anon$2."<init>":(ZZLos/Path;Ljava/nio/file/Path;Ljava/util/HashSet;ILscala/Function2;)V
  #178 = Utf8               opts0
  #179 = Utf8               opts
  #180 = Utf8               Ljava/util/HashSet;
  #181 = Utf8               pathNIO
  #182 = Utf8               Ljava/nio/file/Path;
  #183 = Utf8               Lscala/Function2;
  #184 = Utf8               java/nio/file/Path
  #185 = Class              #184          // java/nio/file/Path
  #186 = Utf8               attrs$default$2
  #187 = Utf8               ()Lscala/Function2;
  #188 = Utf8               ()Lscala/Function2<Los/Path;Los/StatInfo;Ljava/lang/Object;>;
  #189 = Utf8               $anonfun$attrs$default$2$2$adapted
  #190 = NameAndType        #189:#41      // $anonfun$attrs$default$2$2$adapted:(Los/Path;Los/StatInfo;)Ljava/lang/Object;
  #191 = Methodref          #2.#190       // os/walk$stream$.$anonfun$attrs$default$2$2$adapted:(Los/Path;Los/StatInfo;)Ljava/lang/Object;
  #192 = MethodHandle       6:#191        // REF_invokeStatic os/walk$stream$.$anonfun$attrs$default$2$2$adapted:(Los/Path;Los/StatInfo;)Ljava/lang/Object;
  #193 = NameAndType        #25:#187      // apply:()Lscala/Function2;
  #194 = InvokeDynamic      #3:#193       // #3:apply:()Lscala/Function2;
  #195 = Utf8               attrs$default$3
  #196 = Utf8               attrs$default$4
  #197 = Utf8               attrs$default$5
  #198 = Utf8               attrs$default$6
  #199 = Utf8               $anonfun$apply$1
  #200 = Utf8               (Lscala/Function1;Los/Path;Los/StatInfo;)Z
  #201 = Utf8               skip$1
  #202 = Utf8               p
  #203 = Utf8               x$5
  #204 = Utf8               scala/Function1
  #205 = Class              #204          // scala/Function1
  #206 = NameAndType        #25:#59       // apply:(Ljava/lang/Object;)Ljava/lang/Object;
  #207 = InterfaceMethodref #205.#206     // scala/Function1.apply:(Ljava/lang/Object;)Ljava/lang/Object;
  #208 = Utf8               unboxToBoolean
  #209 = NameAndType        #208:#139     // unboxToBoolean:(Ljava/lang/Object;)Z
  #210 = Methodref          #143.#209     // scala/runtime/BoxesRunTime.unboxToBoolean:(Ljava/lang/Object;)Z
  #211 = Utf8               Los/StatInfo;
  #212 = Utf8               x$6
  #213 = Utf8               scala/Tuple2
  #214 = Class              #213          // scala/Tuple2
  #215 = Utf8               _1
  #216 = Utf8               ()Ljava/lang/Object;
  #217 = NameAndType        #215:#216     // _1:()Ljava/lang/Object;
  #218 = Methodref          #214.#217     // scala/Tuple2._1:()Ljava/lang/Object;
  #219 = Utf8               Lscala/Tuple2;
  #220 = Utf8               $anonfun$apply$default$2$2
  #221 = Utf8               (Los/Path;)Z
  #222 = Utf8               x$4
  #223 = Utf8               $anonfun$attrs$default$2$2
  #224 = Utf8               (Los/Path;Los/StatInfo;)Z
  #225 = Utf8               x$7
  #226 = Utf8               x$8
  #227 = Methodref          #4.#21        // java/lang/Object."<init>":()V
  #228 = NameAndType        #199:#200     // $anonfun$apply$1:(Lscala/Function1;Los/Path;Los/StatInfo;)Z
  #229 = Methodref          #2.#228       // os/walk$stream$.$anonfun$apply$1:(Lscala/Function1;Los/Path;Los/StatInfo;)Z
  #230 = NameAndType        #220:#221     // $anonfun$apply$default$2$2:(Los/Path;)Z
  #231 = Methodref          #2.#230       // os/walk$stream$.$anonfun$apply$default$2$2:(Los/Path;)Z
  #232 = NameAndType        #223:#224     // $anonfun$attrs$default$2$2:(Los/Path;Los/StatInfo;)Z
  #233 = Methodref          #2.#232       // os/walk$stream$.$anonfun$attrs$default$2$2:(Los/Path;Los/StatInfo;)Z
  #234 = Utf8               $deserializeLambda$
  #235 = Utf8               (Ljava/lang/invoke/SerializedLambda;)Ljava/lang/Object;
  #236 = Utf8               scala/runtime/LambdaDeserialize
  #237 = Class              #236          // scala/runtime/LambdaDeserialize
  #238 = Utf8               bootstrap
  #239 = Utf8               (Ljava/lang/invoke/MethodHandles$Lookup;Ljava/lang/String;Ljava/lang/invoke/MethodType;[Ljava/lang/invoke/MethodHandle;)Ljava/lang/invoke/CallSite;
  #240 = NameAndType        #238:#239     // bootstrap:(Ljava/lang/invoke/MethodHandles$Lookup;Ljava/lang/String;Ljava/lang/invoke/MethodType;[Ljava/lang/invoke/MethodHandle;)Ljava/lang/invoke/CallSite;
  #241 = Methodref          #237.#240     // scala/runtime/LambdaDeserialize.bootstrap:(Ljava/lang/invoke/MethodHandles$Lookup;Ljava/lang/String;Ljava/lang/invoke/MethodType;[Ljava/lang/invoke/MethodHandle;)Ljava/lang/invoke/CallSite;
  #242 = MethodHandle       6:#241        // REF_invokeStatic scala/runtime/LambdaDeserialize.bootstrap:(Ljava/lang/invoke/MethodHandles$Lookup;Ljava/lang/String;Ljava/lang/invoke/MethodType;[Ljava/lang/invoke/MethodHandle;)Ljava/lang/invoke/CallSite;
  #243 = Utf8               lambdaDeserialize
  #244 = NameAndType        #243:#235     // lambdaDeserialize:(Ljava/lang/invoke/SerializedLambda;)Ljava/lang/Object;
  #245 = InvokeDynamic      #4:#244       // #4:lambdaDeserialize:(Ljava/lang/invoke/SerializedLambda;)Ljava/lang/Object;
  #246 = Utf8               Code
  #247 = Utf8               LineNumberTable
  #248 = Utf8               LocalVariableTable
  #249 = Utf8               Signature
  #250 = Utf8               MethodParameters
  #251 = Utf8               StackMapTable
  #252 = Utf8               InnerClasses
  #253 = Utf8               SourceFile
  #254 = Utf8               BootstrapMethods
  #255 = Utf8               ScalaInlineInfo
  #256 = Utf8               Scala
{
  public static final os.walk$stream$ MODULE$;
    descriptor: Los/walk$stream$;
    flags: (0x0019) ACC_PUBLIC, ACC_STATIC, ACC_FINAL

  public static {};
    descriptor: ()V
    flags: (0x0009) ACC_PUBLIC, ACC_STATIC
    Code:
      stack=2, locals=0, args_size=0
         0: new           #2                  // class os/walk$stream$
         3: dup
         4: invokespecial #22                 // Method "<init>":()V
         7: putstatic     #24                 // Field MODULE$:Los/walk$stream$;
        10: return
      LineNumberTable:
        line 128: 0

  public geny.Generator<os.Path> apply(os.Path, scala.Function1<os.Path, java.lang.Object>, boolean, boolean, int, boolean);
    descriptor: (Los/Path;Lscala/Function1;ZZIZ)Lgeny/Generator;
    flags: (0x0001) ACC_PUBLIC
    Code:
      stack=7, locals=7, args_size=7
         0: aload_0
         1: aload_1
         2: aload_2
         3: invokedynamic #54,  0             // InvokeDynamic #0:apply:(Lscala/Function1;)Lscala/Function2;
         8: iload_3
         9: iload         4
        11: iload         5
        13: iload         6
        15: invokevirtual #58                 // Method attrs:(Los/Path;Lscala/Function2;ZZIZ)Lgeny/Generator;
        18: invokedynamic #69,  0             // InvokeDynamic #1:apply:()Lscala/Function1;
        23: invokeinterface #75,  2           // InterfaceMethod geny/Generator.map:(Lscala/Function1;)Lgeny/Generator;
        28: areturn
      LineNumberTable:
        line 159: 0
      LocalVariableTable:
        Start  Length  Slot  Name   Signature
            0      29     0  this   Los/walk$stream$;
            0      29     1  path   Los/Path;
            0      29     2  skip   Lscala/Function1;
            0      29     3 preOrder   Z
            0      29     4 followLinks   Z
            0      29     5 maxDepth   I
            0      29     6 includeTarget   Z
    Signature: #27                          // (Los/Path;Lscala/Function1<Los/Path;Ljava/lang/Object;>;ZZIZ)Lgeny/Generator<Los/Path;>;
    MethodParameters:
      Name                           Flags
      path                           final
      skip                           final
      preOrder                       final
      followLinks                    final
      maxDepth                       final
      includeTarget                  final

  public scala.Function1<os.Path, java.lang.Object> apply$default$2();
    descriptor: ()Lscala/Function1;
    flags: (0x0001) ACC_PUBLIC
    Code:
      stack=1, locals=1, args_size=1
         0: invokedynamic #89,  0             // InvokeDynamic #2:apply:()Lscala/Function1;
         5: areturn
      LineNumberTable:
        line 153: 0
      LocalVariableTable:
        Start  Length  Slot  Name   Signature
            0       6     0  this   Los/walk$stream$;
    Signature: #82                          // ()Lscala/Function1<Los/Path;Ljava/lang/Object;>;

  public boolean apply$default$3();
    descriptor: ()Z
    flags: (0x0001) ACC_PUBLIC
    Code:
      stack=1, locals=1, args_size=1
         0: iconst_1
         1: ireturn
      LineNumberTable:
        line 154: 0
      LocalVariableTable:
        Start  Length  Slot  Name   Signature
            0       2     0  this   Los/walk$stream$;

  public boolean apply$default$4();
    descriptor: ()Z
    flags: (0x0001) ACC_PUBLIC
    Code:
      stack=1, locals=1, args_size=1
         0: iconst_0
         1: ireturn
      LineNumberTable:
        line 155: 0
      LocalVariableTable:
        Start  Length  Slot  Name   Signature
            0       2     0  this   Los/walk$stream$;

  public int apply$default$5();
    descriptor: ()I
    flags: (0x0001) ACC_PUBLIC
    Code:
      stack=1, locals=1, args_size=1
         0: ldc           #95                 // int 2147483647
         2: ireturn
      LineNumberTable:
        line 156: 0
      LocalVariableTable:
        Start  Length  Slot  Name   Signature
            0       3     0  this   Los/walk$stream$;

  public boolean apply$default$6();
    descriptor: ()Z
    flags: (0x0001) ACC_PUBLIC
    Code:
      stack=1, locals=1, args_size=1
         0: iconst_0
         1: ireturn
      LineNumberTable:
        line 157: 0
      LocalVariableTable:
        Start  Length  Slot  Name   Signature
            0       2     0  this   Los/walk$stream$;

  public geny.Generator<scala.Tuple2<os.Path, os.StatInfo>> attrs(os.Path, scala.Function2<os.Path, os.StatInfo, java.lang.Object>, boolean, boolean, int, boolean);
    descriptor: (Los/Path;Lscala/Function2;ZZIZ)Lgeny/Generator;
    flags: (0x0001) ACC_PUBLIC
    Code:
      stack=9, locals=10, args_size=7
         0: iload         4
         2: ifeq          28
         5: getstatic     #102                // Field scala/Array$.MODULE$:Lscala/Array$;
         8: getstatic     #107                // Field scala/collection/immutable/Nil$.MODULE$:Lscala/collection/immutable/Nil$;
        11: getstatic     #112                // Field scala/reflect/ClassTag$.MODULE$:Lscala/reflect/ClassTag$;
        14: ldc           #114                // class java/nio/file/LinkOption
        16: invokevirtual #117                // Method scala/reflect/ClassTag$.apply:(Ljava/lang/Class;)Lscala/reflect/ClassTag;
        19: invokevirtual #120                // Method scala/Array$.apply:(Lscala/collection/immutable/Seq;Lscala/reflect/ClassTag;)Ljava/lang/Object;
        22: checkcast     #122                // class "[Ljava/nio/file/LinkOption;"
        25: goto          44
        28: iconst_1
        29: anewarray     #114                // class java/nio/file/LinkOption
        32: dup
        33: iconst_0
        34: getstatic     #126                // Field java/nio/file/LinkOption.NOFOLLOW_LINKS:Ljava/nio/file/LinkOption;
        37: aastore
        38: checkcast     #128                // class "[Ljava/lang/Object;"
        41: checkcast     #122                // class "[Ljava/nio/file/LinkOption;"
        44: astore        7
        46: new           #130                // class java/util/HashSet
        49: dup
        50: invokespecial #131                // Method java/util/HashSet."<init>":()V
        53: astore        8
        55: iload         4
        57: ifeq          74
        60: aload         8
        62: getstatic     #137                // Field java/nio/file/FileVisitOption.FOLLOW_LINKS:Ljava/nio/file/FileVisitOption;
        65: invokevirtual #141                // Method java/util/HashSet.add:(Ljava/lang/Object;)Z
        68: invokestatic  #147                // Method scala/runtime/BoxesRunTime.boxToBoolean:(Z)Ljava/lang/Boolean;
        71: goto          77
        74: getstatic     #153                // Field scala/runtime/BoxedUnit.UNIT:Lscala/runtime/BoxedUnit;
        77: pop
        78: aload_1
        79: invokevirtual #159                // Method os/Path.wrapped:()Ljava/nio/file/Path;
        82: astore        9
        84: aload         9
        86: aload         7
        88: invokestatic  #165                // Method java/nio/file/Files.exists:(Ljava/nio/file/Path;[Ljava/nio/file/LinkOption;)Z
        91: ifne          107
        94: new           #167                // class java/nio/file/NoSuchFileException
        97: dup
        98: aload         9
       100: invokevirtual #171                // Method java/lang/Object.toString:()Ljava/lang/String;
       103: invokespecial #174                // Method java/nio/file/NoSuchFileException."<init>":(Ljava/lang/String;)V
       106: athrow
       107: new           #15                 // class os/walk$stream$$anon$2
       110: dup
       111: iload         6
       113: iload_3
       114: aload_1
       115: aload         9
       117: aload         8
       119: iload         5
       121: aload_2
       122: invokespecial #177                // Method os/walk$stream$$anon$2."<init>":(ZZLos/Path;Ljava/nio/file/Path;Ljava/util/HashSet;ILscala/Function2;)V
       125: areturn
      StackMapTable: number_of_entries = 5
        frame_type = 28 /* same */
        frame_type = 79 /* same_locals_1_stack_item */
          stack = [ class "[Ljava/nio/file/LinkOption;" ]
        frame_type = 253 /* append */
          offset_delta = 29
          locals = [ class "[Ljava/nio/file/LinkOption;", class java/util/HashSet ]
        frame_type = 66 /* same_locals_1_stack_item */
          stack = [ class java/lang/Object ]
        frame_type = 252 /* append */
          offset_delta = 29
          locals = [ class java/nio/file/Path ]
      LineNumberTable:
        line 191: 0
        line 192: 46
        line 193: 55
        line 194: 78
        line 195: 84
        line 196: 94
        line 198: 107
      LocalVariableTable:
        Start  Length  Slot  Name   Signature
           46      79     7 opts0   [Ljava/nio/file/LinkOption;
           55      70     8  opts   Ljava/util/HashSet;
           84      41     9 pathNIO   Ljava/nio/file/Path;
            0     126     0  this   Los/walk$stream$;
            0     126     1  path   Los/Path;
            0     126     2  skip   Lscala/Function2;
            0     126     3 preOrder   Z
            0     126     4 followLinks   Z
            0     126     5 maxDepth   I
            0     126     6 includeTarget   Z
    Signature: #97                          // (Los/Path;Lscala/Function2<Los/Path;Los/StatInfo;Ljava/lang/Object;>;ZZIZ)Lgeny/Generator<Lscala/Tuple2<Los/Path;Los/StatInfo;>;>;
    MethodParameters:
      Name                           Flags
      path                           final
      skip                           final
      preOrder                       final
      followLinks                    final
      maxDepth                       final
      includeTarget                  final

  public scala.Function2<os.Path, os.StatInfo, java.lang.Object> attrs$default$2();
    descriptor: ()Lscala/Function2;
    flags: (0x0001) ACC_PUBLIC
    Code:
      stack=1, locals=1, args_size=1
         0: invokedynamic #194,  0            // InvokeDynamic #3:apply:()Lscala/Function2;
         5: areturn
      LineNumberTable:
        line 185: 0
      LocalVariableTable:
        Start  Length  Slot  Name   Signature
            0       6     0  this   Los/walk$stream$;
    Signature: #188                         // ()Lscala/Function2<Los/Path;Los/StatInfo;Ljava/lang/Object;>;

  public boolean attrs$default$3();
    descriptor: ()Z
    flags: (0x0001) ACC_PUBLIC
    Code:
      stack=1, locals=1, args_size=1
         0: iconst_1
         1: ireturn
      LineNumberTable:
        line 186: 0
      LocalVariableTable:
        Start  Length  Slot  Name   Signature
            0       2     0  this   Los/walk$stream$;

  public boolean attrs$default$4();
    descriptor: ()Z
    flags: (0x0001) ACC_PUBLIC
    Code:
      stack=1, locals=1, args_size=1
         0: iconst_0
         1: ireturn
      LineNumberTable:
        line 187: 0
      LocalVariableTable:
        Start  Length  Slot  Name   Signature
            0       2     0  this   Los/walk$stream$;

  public int attrs$default$5();
    descriptor: ()I
    flags: (0x0001) ACC_PUBLIC
    Code:
      stack=1, locals=1, args_size=1
         0: ldc           #95                 // int 2147483647
         2: ireturn
      LineNumberTable:
        line 188: 0
      LocalVariableTable:
        Start  Length  Slot  Name   Signature
            0       3     0  this   Los/walk$stream$;

  public boolean attrs$default$6();
    descriptor: ()Z
    flags: (0x0001) ACC_PUBLIC
    Code:
      stack=1, locals=1, args_size=1
         0: iconst_0
         1: ireturn
      LineNumberTable:
        line 189: 0
      LocalVariableTable:
        Start  Length  Slot  Name   Signature
            0       2     0  this   Los/walk$stream$;

  public static final boolean $anonfun$apply$1(scala.Function1, os.Path, os.StatInfo);
    descriptor: (Lscala/Function1;Los/Path;Los/StatInfo;)Z
    flags: (0x1019) ACC_PUBLIC, ACC_STATIC, ACC_FINAL, ACC_SYNTHETIC
    Code:
      stack=2, locals=3, args_size=3
         0: aload_0
         1: aload_1
         2: invokeinterface #207,  2          // InterfaceMethod scala/Function1.apply:(Ljava/lang/Object;)Ljava/lang/Object;
         7: invokestatic  #210                // Method scala/runtime/BoxesRunTime.unboxToBoolean:(Ljava/lang/Object;)Z
        10: ireturn
      LineNumberTable:
        line 159: 0
      LocalVariableTable:
        Start  Length  Slot  Name   Signature
            0      11     0 skip$1   Lscala/Function1;
            0      11     1     p   Los/Path;
            0      11     2   x$5   Los/StatInfo;
    MethodParameters:
      Name                           Flags
      skip$1                         final
      p                              final
      x$5                            final

  public static final os.Path $anonfun$apply$2(scala.Tuple2);
    descriptor: (Lscala/Tuple2;)Los/Path;
    flags: (0x1019) ACC_PUBLIC, ACC_STATIC, ACC_FINAL, ACC_SYNTHETIC
    Code:
      stack=1, locals=1, args_size=1
         0: aload_0
         1: invokevirtual #218                // Method scala/Tuple2._1:()Ljava/lang/Object;
         4: checkcast     #155                // class os/Path
         7: areturn
      LineNumberTable:
        line 159: 0
      LocalVariableTable:
        Start  Length  Slot  Name   Signature
            0       8     0   x$6   Lscala/Tuple2;
    MethodParameters:
      Name                           Flags
      x$6                            final

  public static final boolean $anonfun$apply$default$2$2(os.Path);
    descriptor: (Los/Path;)Z
    flags: (0x1019) ACC_PUBLIC, ACC_STATIC, ACC_FINAL, ACC_SYNTHETIC
    Code:
      stack=1, locals=1, args_size=1
         0: iconst_0
         1: ireturn
      LineNumberTable:
        line 153: 0
      LocalVariableTable:
        Start  Length  Slot  Name   Signature
            0       2     0   x$4   Los/Path;
    MethodParameters:
      Name                           Flags
      x$4                            final

  public static final boolean $anonfun$attrs$default$2$2(os.Path, os.StatInfo);
    descriptor: (Los/Path;Los/StatInfo;)Z
    flags: (0x1019) ACC_PUBLIC, ACC_STATIC, ACC_FINAL, ACC_SYNTHETIC
    Code:
      stack=1, locals=2, args_size=2
         0: iconst_0
         1: ireturn
      LineNumberTable:
        line 185: 0
      LocalVariableTable:
        Start  Length  Slot  Name   Signature
            0       2     0   x$7   Los/Path;
            0       2     1   x$8   Los/StatInfo;
    MethodParameters:
      Name                           Flags
      x$7                            final
      x$8                            final

  public os.walk$stream$();
    descriptor: ()V
    flags: (0x0001) ACC_PUBLIC
    Code:
      stack=1, locals=1, args_size=1
         0: aload_0
         1: invokespecial #227                // Method java/lang/Object."<init>":()V
         4: return
      LineNumberTable:
        line 288: 0
        line 128: 4
      LocalVariableTable:
        Start  Length  Slot  Name   Signature
            0       5     0  this   Los/walk$stream$;

  public static final java.lang.Object $anonfun$apply$1$adapted(scala.Function1, os.Path, os.StatInfo);
    descriptor: (Lscala/Function1;Los/Path;Los/StatInfo;)Ljava/lang/Object;
    flags: (0x1019) ACC_PUBLIC, ACC_STATIC, ACC_FINAL, ACC_SYNTHETIC
    Code:
      stack=3, locals=3, args_size=3
         0: aload_0
         1: aload_1
         2: aload_2
         3: invokestatic  #229                // Method $anonfun$apply$1:(Lscala/Function1;Los/Path;Los/StatInfo;)Z
         6: invokestatic  #147                // Method scala/runtime/BoxesRunTime.boxToBoolean:(Z)Ljava/lang/Boolean;
         9: areturn
      LineNumberTable:
        line 159: 0
      LocalVariableTable:
        Start  Length  Slot  Name   Signature
            0      10     0 skip$1   Lscala/Function1;
            0      10     1     p   Los/Path;
            0      10     2   x$5   Los/StatInfo;
    MethodParameters:
      Name                           Flags
      skip$1                         final
      p                              final
      x$5                            final

  public static final java.lang.Object $anonfun$apply$default$2$2$adapted(os.Path);
    descriptor: (Los/Path;)Ljava/lang/Object;
    flags: (0x1019) ACC_PUBLIC, ACC_STATIC, ACC_FINAL, ACC_SYNTHETIC
    Code:
      stack=1, locals=1, args_size=1
         0: aload_0
         1: invokestatic  #231                // Method $anonfun$apply$default$2$2:(Los/Path;)Z
         4: invokestatic  #147                // Method scala/runtime/BoxesRunTime.boxToBoolean:(Z)Ljava/lang/Boolean;
         7: areturn
      LineNumberTable:
        line 153: 0
      LocalVariableTable:
        Start  Length  Slot  Name   Signature
            0       8     0   x$4   Los/Path;
    MethodParameters:
      Name                           Flags
      x$4                            final

  public static final java.lang.Object $anonfun$attrs$default$2$2$adapted(os.Path, os.StatInfo);
    descriptor: (Los/Path;Los/StatInfo;)Ljava/lang/Object;
    flags: (0x1019) ACC_PUBLIC, ACC_STATIC, ACC_FINAL, ACC_SYNTHETIC
    Code:
      stack=2, locals=2, args_size=2
         0: aload_0
         1: aload_1
         2: invokestatic  #233                // Method $anonfun$attrs$default$2$2:(Los/Path;Los/StatInfo;)Z
         5: invokestatic  #147                // Method scala/runtime/BoxesRunTime.boxToBoolean:(Z)Ljava/lang/Boolean;
         8: areturn
      LineNumberTable:
        line 185: 0
      LocalVariableTable:
        Start  Length  Slot  Name   Signature
            0       9     0   x$7   Los/Path;
            0       9     1   x$8   Los/StatInfo;
    MethodParameters:
      Name                           Flags
      x$7                            final
      x$8                            final

  private static java.lang.Object $deserializeLambda$(java.lang.invoke.SerializedLambda);
    descriptor: (Ljava/lang/invoke/SerializedLambda;)Ljava/lang/Object;
    flags: (0x100a) ACC_PRIVATE, ACC_STATIC, ACC_SYNTHETIC
    Code:
      stack=1, locals=1, args_size=1
         0: aload_0
         1: invokedynamic #245,  0            // InvokeDynamic #4:lambdaDeserialize:(Ljava/lang/invoke/SerializedLambda;)Ljava/lang/Object;
         6: areturn
}
InnerClasses:
  public static final #10= #7 of #9;      // Lookup=class java/lang/invoke/MethodHandles$Lookup of class java/lang/invoke/MethodHandles
  public static #13= #2 of #12;           // stream$=class os/walk$stream$ of class os/walk
  public final #15;                       // class os/walk$stream$$anon$2
SourceFile: "ListOps.scala"
BootstrapMethods:
  0: #51 REF_invokeStatic java/lang/invoke/LambdaMetafactory.altMetafactory:(Ljava/lang/invoke/MethodHandles$Lookup;Ljava/lang/String;Ljava/lang/invoke/MethodType;[Ljava/lang/Object;)Ljava/lang/invoke/CallSite;
    Method arguments:
      #35 (Ljava/lang/Object;Ljava/lang/Object;)Ljava/lang/Object;
      #40 REF_invokeStatic os/walk$stream$.$anonfun$apply$1$adapted:(Lscala/Function1;Los/Path;Los/StatInfo;)Ljava/lang/Object;
      #42 (Los/Path;Los/StatInfo;)Ljava/lang/Object;
      #43 5
      #44 1
      #42 (Los/Path;Los/StatInfo;)Ljava/lang/Object;
  1: #51 REF_invokeStatic java/lang/invoke/LambdaMetafactory.altMetafactory:(Ljava/lang/invoke/MethodHandles$Lookup;Ljava/lang/String;Ljava/lang/invoke/MethodType;[Ljava/lang/Object;)Ljava/lang/invoke/CallSite;
    Method arguments:
      #60 (Ljava/lang/Object;)Ljava/lang/Object;
      #65 REF_invokeStatic os/walk$stream$.$anonfun$apply$2:(Lscala/Tuple2;)Los/Path;
      #66 (Lscala/Tuple2;)Los/Path;
      #43 5
      #44 1
      #66 (Lscala/Tuple2;)Los/Path;
  2: #51 REF_invokeStatic java/lang/invoke/LambdaMetafactory.altMetafactory:(Ljava/lang/invoke/MethodHandles$Lookup;Ljava/lang/String;Ljava/lang/invoke/MethodType;[Ljava/lang/Object;)Ljava/lang/invoke/CallSite;
    Method arguments:
      #60 (Ljava/lang/Object;)Ljava/lang/Object;
      #87 REF_invokeStatic os/walk$stream$.$anonfun$apply$default$2$2$adapted:(Los/Path;)Ljava/lang/Object;
      #88 (Los/Path;)Ljava/lang/Object;
      #43 5
      #44 1
      #88 (Los/Path;)Ljava/lang/Object;
  3: #51 REF_invokeStatic java/lang/invoke/LambdaMetafactory.altMetafactory:(Ljava/lang/invoke/MethodHandles$Lookup;Ljava/lang/String;Ljava/lang/invoke/MethodType;[Ljava/lang/Object;)Ljava/lang/invoke/CallSite;
    Method arguments:
      #35 (Ljava/lang/Object;Ljava/lang/Object;)Ljava/lang/Object;
      #192 REF_invokeStatic os/walk$stream$.$anonfun$attrs$default$2$2$adapted:(Los/Path;Los/StatInfo;)Ljava/lang/Object;
      #42 (Los/Path;Los/StatInfo;)Ljava/lang/Object;
      #43 5
      #44 1
      #42 (Los/Path;Los/StatInfo;)Ljava/lang/Object;
  4: #242 REF_invokeStatic scala/runtime/LambdaDeserialize.bootstrap:(Ljava/lang/invoke/MethodHandles$Lookup;Ljava/lang/String;Ljava/lang/invoke/MethodType;[Ljava/lang/invoke/MethodHandle;)Ljava/lang/invoke/CallSite;
    Method arguments:
      #40 REF_invokeStatic os/walk$stream$.$anonfun$apply$1$adapted:(Lscala/Function1;Los/Path;Los/StatInfo;)Ljava/lang/Object;
      #65 REF_invokeStatic os/walk$stream$.$anonfun$apply$2:(Lscala/Tuple2;)Los/Path;
      #87 REF_invokeStatic os/walk$stream$.$anonfun$apply$default$2$2$adapted:(Los/Path;)Ljava/lang/Object;
      #192 REF_invokeStatic os/walk$stream$.$anonfun$attrs$default$2$2$adapted:(Los/Path;Los/StatInfo;)Ljava/lang/Object;
  ScalaInlineInfo: length = 0x68 (unknown attribute)
   01 01 00 14 00 C7 00 C8 01 00 24 00 25 01 00 3D
   00 3E 01 00 DC 00 DD 01 00 53 00 54 01 00 DF 00
   E0 01 00 BD 00 29 01 00 14 00 13 01 00 19 00 1A
   01 00 51 00 43 01 00 5A 00 5B 01 00 5C 00 5B 01
   00 5D 00 5E 01 00 60 00 5B 01 00 37 00 38 01 00
   BA 00 BB 01 00 C3 00 5B 01 00 C4 00 5B 01 00 C5
   00 5E 01 00 C6 00 5B 01
  Scala: length = 0x0 (unknown attribute)

