Classfile /Users/mw/Projects/slang-braindump/.jar/jar11/assemble/slang-braindump/assemble/content/os/WritableLowPri$$anon$3$$anon$4.class
  Last modified May 29, 2022; size 3273 bytes
  SHA-256 checksum 93d3bec060b38a03c4a4299a2bc770262ac13357ef8319be9ca8044ba086fc94
  Compiled from "Source.scala"
public final class os.WritableLowPri$$anon$3$$anon$4 implements geny.Writable
  minor version: 0
  major version: 52
  flags: (0x0031) ACC_PUBLIC, ACC_FINAL, ACC_SUPER
  this_class: #2                          // os/WritableLowPri$$anon$3$$anon$4
  super_class: #4                         // java/lang/Object
  interfaces: 1, fields: 1, methods: 7, attributes: 6
Constant pool:
    #1 = Utf8               os/WritableLowPri$$anon$3$$anon$4
    #2 = Class              #1            // os/WritableLowPri$$anon$3$$anon$4
    #3 = Utf8               java/lang/Object
    #4 = Class              #3            // java/lang/Object
    #5 = Utf8               geny/Writable
    #6 = Class              #5            // geny/Writable
    #7 = Utf8               Source.scala
    #8 = Utf8               os/WritableLowPri$$anon$3
    #9 = Class              #8            // os/WritableLowPri$$anon$3
   #10 = Utf8               getHandle
   #11 = Utf8               ()Lscala/util/Left;
   #12 = NameAndType        #10:#11       // getHandle:()Lscala/util/Left;
   #13 = Utf8               java/lang/invoke/MethodHandles$Lookup
   #14 = Class              #13           // java/lang/invoke/MethodHandles$Lookup
   #15 = Utf8               java/lang/invoke/MethodHandles
   #16 = Class              #15           // java/lang/invoke/MethodHandles
   #17 = Utf8               Lookup
   #18 = Utf8               $outer
   #19 = Utf8               Los/WritableLowPri$$anon$3;
   #20 = Utf8               httpContentType
   #21 = Utf8               ()Lscala/Option;
   #22 = Utf8               ()Lscala/Option<Ljava/lang/String;>;
   #23 = Utf8               httpContentType$
   #24 = Utf8               (Lgeny/Writable;)Lscala/Option;
   #25 = NameAndType        #23:#24       // httpContentType$:(Lgeny/Writable;)Lscala/Option;
   #26 = InterfaceMethodref #6.#25        // geny/Writable.httpContentType$:(Lgeny/Writable;)Lscala/Option;
   #27 = Utf8               this
   #28 = Utf8               Los/WritableLowPri$$anon$3$$anon$4;
   #29 = Utf8               contentLength
   #30 = Utf8               ()Lscala/Option<Ljava/lang/Object;>;
   #31 = Utf8               contentLength$
   #32 = NameAndType        #31:#24       // contentLength$:(Lgeny/Writable;)Lscala/Option;
   #33 = InterfaceMethodref #6.#32        // geny/Writable.contentLength$:(Lgeny/Writable;)Lscala/Option;
   #34 = Utf8               writeBytesTo
   #35 = Utf8               (Ljava/io/OutputStream;)V
   #36 = Utf8               out
   #37 = Utf8               scala/collection/IterableOnceExtensionMethods$
   #38 = Class              #37           // scala/collection/IterableOnceExtensionMethods$
   #39 = Utf8               MODULE$
   #40 = Utf8               Lscala/collection/IterableOnceExtensionMethods$;
   #41 = NameAndType        #39:#40       // MODULE$:Lscala/collection/IterableOnceExtensionMethods$;
   #42 = Fieldref           #38.#41       // scala/collection/IterableOnceExtensionMethods$.MODULE$:Lscala/collection/IterableOnceExtensionMethods$;
   #43 = Utf8               scala/collection/IterableOnce$
   #44 = Class              #43           // scala/collection/IterableOnce$
   #45 = Utf8               Lscala/collection/IterableOnce$;
   #46 = NameAndType        #39:#45       // MODULE$:Lscala/collection/IterableOnce$;
   #47 = Fieldref           #44.#46       // scala/collection/IterableOnce$.MODULE$:Lscala/collection/IterableOnce$;
   #48 = NameAndType        #18:#19       // $outer:Los/WritableLowPri$$anon$3;
   #49 = Fieldref           #2.#48        // os/WritableLowPri$$anon$3$$anon$4.$outer:Los/WritableLowPri$$anon$3;
   #50 = Utf8               traversable$1
   #51 = Utf8               Lscala/collection/IterableOnce;
   #52 = NameAndType        #50:#51       // traversable$1:Lscala/collection/IterableOnce;
   #53 = Fieldref           #9.#52        // os/WritableLowPri$$anon$3.traversable$1:Lscala/collection/IterableOnce;
   #54 = Utf8               iterableOnceExtensionMethods
   #55 = Utf8               (Lscala/collection/IterableOnce;)Lscala/collection/IterableOnce;
   #56 = NameAndType        #54:#55       // iterableOnceExtensionMethods:(Lscala/collection/IterableOnce;)Lscala/collection/IterableOnce;
   #57 = Methodref          #44.#56       // scala/collection/IterableOnce$.iterableOnceExtensionMethods:(Lscala/collection/IterableOnce;)Lscala/collection/IterableOnce;
   #58 = Utf8               (Ljava/lang/Object;)Ljava/lang/Object;
   #59 = MethodType         #58           //  (Ljava/lang/Object;)Ljava/lang/Object;
   #60 = Utf8               $anonfun$writeBytesTo$2$adapted
   #61 = Utf8               (Los/WritableLowPri$$anon$3$$anon$4;Ljava/io/OutputStream;Ljava/lang/Object;)Ljava/lang/Object;
   #62 = NameAndType        #60:#61       // $anonfun$writeBytesTo$2$adapted:(Los/WritableLowPri$$anon$3$$anon$4;Ljava/io/OutputStream;Ljava/lang/Object;)Ljava/lang/Object;
   #63 = Methodref          #2.#62        // os/WritableLowPri$$anon$3$$anon$4.$anonfun$writeBytesTo$2$adapted:(Los/WritableLowPri$$anon$3$$anon$4;Ljava/io/OutputStream;Ljava/lang/Object;)Ljava/lang/Object;
   #64 = MethodHandle       6:#63         // REF_invokeStatic os/WritableLowPri$$anon$3$$anon$4.$anonfun$writeBytesTo$2$adapted:(Los/WritableLowPri$$anon$3$$anon$4;Ljava/io/OutputStream;Ljava/lang/Object;)Ljava/lang/Object;
   #65 = Integer            1
   #66 = Utf8               java/lang/invoke/LambdaMetafactory
   #67 = Class              #66           // java/lang/invoke/LambdaMetafactory
   #68 = Utf8               altMetafactory
   #69 = Utf8               (Ljava/lang/invoke/MethodHandles$Lookup;Ljava/lang/String;Ljava/lang/invoke/MethodType;[Ljava/lang/Object;)Ljava/lang/invoke/CallSite;
   #70 = NameAndType        #68:#69       // altMetafactory:(Ljava/lang/invoke/MethodHandles$Lookup;Ljava/lang/String;Ljava/lang/invoke/MethodType;[Ljava/lang/Object;)Ljava/lang/invoke/CallSite;
   #71 = Methodref          #67.#70       // java/lang/invoke/LambdaMetafactory.altMetafactory:(Ljava/lang/invoke/MethodHandles$Lookup;Ljava/lang/String;Ljava/lang/invoke/MethodType;[Ljava/lang/Object;)Ljava/lang/invoke/CallSite;
   #72 = MethodHandle       6:#71         // REF_invokeStatic java/lang/invoke/LambdaMetafactory.altMetafactory:(Ljava/lang/invoke/MethodHandles$Lookup;Ljava/lang/String;Ljava/lang/invoke/MethodType;[Ljava/lang/Object;)Ljava/lang/invoke/CallSite;
   #73 = Utf8               apply
   #74 = Utf8               (Los/WritableLowPri$$anon$3$$anon$4;Ljava/io/OutputStream;)Lscala/Function1;
   #75 = NameAndType        #73:#74       // apply:(Los/WritableLowPri$$anon$3$$anon$4;Ljava/io/OutputStream;)Lscala/Function1;
   #76 = InvokeDynamic      #0:#75        // #0:apply:(Los/WritableLowPri$$anon$3$$anon$4;Ljava/io/OutputStream;)Lscala/Function1;
   #77 = Utf8               foreach$extension
   #78 = Utf8               (Lscala/collection/IterableOnce;Lscala/Function1;)V
   #79 = NameAndType        #77:#78       // foreach$extension:(Lscala/collection/IterableOnce;Lscala/Function1;)V
   #80 = Methodref          #38.#79       // scala/collection/IterableOnceExtensionMethods$.foreach$extension:(Lscala/collection/IterableOnce;Lscala/Function1;)V
   #81 = Utf8               Ljava/io/OutputStream;
   #82 = Utf8               $anonfun$writeBytesTo$2
   #83 = Utf8               (Los/WritableLowPri$$anon$3$$anon$4;Ljava/io/OutputStream;Ljava/lang/Object;)V
   #84 = Utf8               $this
   #85 = Utf8               out$2
   #86 = Utf8               x
   #87 = Utf8               f0$2
   #88 = Utf8               Lscala/Function1;
   #89 = NameAndType        #87:#88       // f0$2:Lscala/Function1;
   #90 = Fieldref           #9.#89        // os/WritableLowPri$$anon$3.f0$2:Lscala/Function1;
   #91 = Utf8               scala/Function1
   #92 = Class              #91           // scala/Function1
   #93 = NameAndType        #73:#58       // apply:(Ljava/lang/Object;)Ljava/lang/Object;
   #94 = InterfaceMethodref #92.#93       // scala/Function1.apply:(Ljava/lang/Object;)Ljava/lang/Object;
   #95 = NameAndType        #34:#35       // writeBytesTo:(Ljava/io/OutputStream;)V
   #96 = InterfaceMethodref #6.#95        // geny/Writable.writeBytesTo:(Ljava/io/OutputStream;)V
   #97 = Utf8               Ljava/lang/Object;
   #98 = Utf8               <init>
   #99 = Utf8               (Los/WritableLowPri$$anon$3;)V
  #100 = Utf8               ()V
  #101 = NameAndType        #98:#100      // "<init>":()V
  #102 = Methodref          #4.#101       // java/lang/Object."<init>":()V
  #103 = Utf8               $init$
  #104 = Utf8               (Lgeny/Writable;)V
  #105 = NameAndType        #103:#104     // $init$:(Lgeny/Writable;)V
  #106 = InterfaceMethodref #6.#105       // geny/Writable.$init$:(Lgeny/Writable;)V
  #107 = NameAndType        #82:#83       // $anonfun$writeBytesTo$2:(Los/WritableLowPri$$anon$3$$anon$4;Ljava/io/OutputStream;Ljava/lang/Object;)V
  #108 = Methodref          #2.#107       // os/WritableLowPri$$anon$3$$anon$4.$anonfun$writeBytesTo$2:(Los/WritableLowPri$$anon$3$$anon$4;Ljava/io/OutputStream;Ljava/lang/Object;)V
  #109 = Utf8               scala/runtime/BoxedUnit
  #110 = Class              #109          // scala/runtime/BoxedUnit
  #111 = Utf8               UNIT
  #112 = Utf8               Lscala/runtime/BoxedUnit;
  #113 = NameAndType        #111:#112     // UNIT:Lscala/runtime/BoxedUnit;
  #114 = Fieldref           #110.#113     // scala/runtime/BoxedUnit.UNIT:Lscala/runtime/BoxedUnit;
  #115 = Utf8               $deserializeLambda$
  #116 = Utf8               (Ljava/lang/invoke/SerializedLambda;)Ljava/lang/Object;
  #117 = Utf8               scala/runtime/LambdaDeserialize
  #118 = Class              #117          // scala/runtime/LambdaDeserialize
  #119 = Utf8               bootstrap
  #120 = Utf8               (Ljava/lang/invoke/MethodHandles$Lookup;Ljava/lang/String;Ljava/lang/invoke/MethodType;[Ljava/lang/invoke/MethodHandle;)Ljava/lang/invoke/CallSite;
  #121 = NameAndType        #119:#120     // bootstrap:(Ljava/lang/invoke/MethodHandles$Lookup;Ljava/lang/String;Ljava/lang/invoke/MethodType;[Ljava/lang/invoke/MethodHandle;)Ljava/lang/invoke/CallSite;
  #122 = Methodref          #118.#121     // scala/runtime/LambdaDeserialize.bootstrap:(Ljava/lang/invoke/MethodHandles$Lookup;Ljava/lang/String;Ljava/lang/invoke/MethodType;[Ljava/lang/invoke/MethodHandle;)Ljava/lang/invoke/CallSite;
  #123 = MethodHandle       6:#122        // REF_invokeStatic scala/runtime/LambdaDeserialize.bootstrap:(Ljava/lang/invoke/MethodHandles$Lookup;Ljava/lang/String;Ljava/lang/invoke/MethodType;[Ljava/lang/invoke/MethodHandle;)Ljava/lang/invoke/CallSite;
  #124 = Utf8               lambdaDeserialize
  #125 = NameAndType        #124:#116     // lambdaDeserialize:(Ljava/lang/invoke/SerializedLambda;)Ljava/lang/Object;
  #126 = InvokeDynamic      #1:#125       // #1:lambdaDeserialize:(Ljava/lang/invoke/SerializedLambda;)Ljava/lang/Object;
  #127 = Utf8               Code
  #128 = Utf8               LineNumberTable
  #129 = Utf8               LocalVariableTable
  #130 = Utf8               Signature
  #131 = Utf8               MethodParameters
  #132 = Utf8               StackMapTable
  #133 = Utf8               InnerClasses
  #134 = Utf8               EnclosingMethod
  #135 = Utf8               SourceFile
  #136 = Utf8               BootstrapMethods
  #137 = Utf8               ScalaInlineInfo
  #138 = Utf8               Scala
{
  private final os.WritableLowPri$$anon$3 $outer;
    descriptor: Los/WritableLowPri$$anon$3;
    flags: (0x1012) ACC_PRIVATE, ACC_FINAL, ACC_SYNTHETIC

  public scala.Option<java.lang.String> httpContentType();
    descriptor: ()Lscala/Option;
    flags: (0x0001) ACC_PUBLIC
    Code:
      stack=1, locals=1, args_size=1
         0: aload_0
         1: invokestatic  #26                 // InterfaceMethod geny/Writable.httpContentType$:(Lgeny/Writable;)Lscala/Option;
         4: areturn
      LineNumberTable:
        line 92: 0
      LocalVariableTable:
        Start  Length  Slot  Name   Signature
            0       5     0  this   Los/WritableLowPri$$anon$3$$anon$4;
    Signature: #22                          // ()Lscala/Option<Ljava/lang/String;>;

  public scala.Option<java.lang.Object> contentLength();
    descriptor: ()Lscala/Option;
    flags: (0x0001) ACC_PUBLIC
    Code:
      stack=1, locals=1, args_size=1
         0: aload_0
         1: invokestatic  #33                 // InterfaceMethod geny/Writable.contentLength$:(Lgeny/Writable;)Lscala/Option;
         4: areturn
      LineNumberTable:
        line 92: 0
      LocalVariableTable:
        Start  Length  Slot  Name   Signature
            0       5     0  this   Los/WritableLowPri$$anon$3$$anon$4;
    Signature: #30                          // ()Lscala/Option<Ljava/lang/Object;>;

  public void writeBytesTo(java.io.OutputStream);
    descriptor: (Ljava/io/OutputStream;)V
    flags: (0x0001) ACC_PUBLIC
    Code:
      stack=4, locals=2, args_size=2
         0: getstatic     #42                 // Field scala/collection/IterableOnceExtensionMethods$.MODULE$:Lscala/collection/IterableOnceExtensionMethods$;
         3: getstatic     #47                 // Field scala/collection/IterableOnce$.MODULE$:Lscala/collection/IterableOnce$;
         6: aload_0
         7: getfield      #49                 // Field $outer:Los/WritableLowPri$$anon$3;
        10: getfield      #53                 // Field os/WritableLowPri$$anon$3.traversable$1:Lscala/collection/IterableOnce;
        13: invokevirtual #57                 // Method scala/collection/IterableOnce$.iterableOnceExtensionMethods:(Lscala/collection/IterableOnce;)Lscala/collection/IterableOnce;
        16: aload_0
        17: aload_1
        18: invokedynamic #76,  0             // InvokeDynamic #0:apply:(Los/WritableLowPri$$anon$3$$anon$4;Ljava/io/OutputStream;)Lscala/Function1;
        23: invokevirtual #80                 // Method scala/collection/IterableOnceExtensionMethods$.foreach$extension:(Lscala/collection/IterableOnce;Lscala/Function1;)V
        26: return
      LineNumberTable:
        line 94: 3
      LocalVariableTable:
        Start  Length  Slot  Name   Signature
            0      27     0  this   Los/WritableLowPri$$anon$3$$anon$4;
            0      27     1   out   Ljava/io/OutputStream;
    MethodParameters:
      Name                           Flags
      out                            final

  public static final void $anonfun$writeBytesTo$2(os.WritableLowPri$$anon$3$$anon$4, java.io.OutputStream, java.lang.Object);
    descriptor: (Los/WritableLowPri$$anon$3$$anon$4;Ljava/io/OutputStream;Ljava/lang/Object;)V
    flags: (0x1019) ACC_PUBLIC, ACC_STATIC, ACC_FINAL, ACC_SYNTHETIC
    Code:
      stack=2, locals=3, args_size=3
         0: aload_0
         1: getfield      #49                 // Field $outer:Los/WritableLowPri$$anon$3;
         4: getfield      #90                 // Field os/WritableLowPri$$anon$3.f0$2:Lscala/Function1;
         7: aload_2
         8: invokeinterface #94,  2           // InterfaceMethod scala/Function1.apply:(Ljava/lang/Object;)Ljava/lang/Object;
        13: checkcast     #6                  // class geny/Writable
        16: aload_1
        17: invokeinterface #96,  2           // InterfaceMethod geny/Writable.writeBytesTo:(Ljava/io/OutputStream;)V
        22: return
      LineNumberTable:
        line 94: 0
      LocalVariableTable:
        Start  Length  Slot  Name   Signature
            0      23     0 $this   Los/WritableLowPri$$anon$3$$anon$4;
            0      23     1 out$2   Ljava/io/OutputStream;
            0      23     2     x   Ljava/lang/Object;
    MethodParameters:
      Name                           Flags
      $this                          final synthetic
      out$2                          final
      x                              final

  public os.WritableLowPri$$anon$3$$anon$4(os.WritableLowPri$$anon$3);
    descriptor: (Los/WritableLowPri$$anon$3;)V
    flags: (0x0001) ACC_PUBLIC
    Code:
      stack=2, locals=2, args_size=2
         0: aload_1
         1: ifnonnull     6
         4: aconst_null
         5: athrow
         6: aload_0
         7: aload_1
         8: putfield      #49                 // Field $outer:Los/WritableLowPri$$anon$3;
        11: aload_0
        12: invokespecial #102                // Method java/lang/Object."<init>":()V
        15: aload_0
        16: invokestatic  #106                // InterfaceMethod geny/Writable.$init$:(Lgeny/Writable;)V
        19: return
      StackMapTable: number_of_entries = 1
        frame_type = 6 /* same */
      LineNumberTable:
        line 92: 0
      LocalVariableTable:
        Start  Length  Slot  Name   Signature
            0      20     0  this   Los/WritableLowPri$$anon$3$$anon$4;
            0      20     1 $outer   Los/WritableLowPri$$anon$3;
    MethodParameters:
      Name                           Flags
      $outer                         final synthetic

  public static final java.lang.Object $anonfun$writeBytesTo$2$adapted(os.WritableLowPri$$anon$3$$anon$4, java.io.OutputStream, java.lang.Object);
    descriptor: (Los/WritableLowPri$$anon$3$$anon$4;Ljava/io/OutputStream;Ljava/lang/Object;)Ljava/lang/Object;
    flags: (0x1019) ACC_PUBLIC, ACC_STATIC, ACC_FINAL, ACC_SYNTHETIC
    Code:
      stack=3, locals=3, args_size=3
         0: aload_0
         1: aload_1
         2: aload_2
         3: invokestatic  #108                // Method $anonfun$writeBytesTo$2:(Los/WritableLowPri$$anon$3$$anon$4;Ljava/io/OutputStream;Ljava/lang/Object;)V
         6: getstatic     #114                // Field scala/runtime/BoxedUnit.UNIT:Lscala/runtime/BoxedUnit;
         9: areturn
      LineNumberTable:
        line 94: 0
      LocalVariableTable:
        Start  Length  Slot  Name   Signature
            0      10     0 $this   Los/WritableLowPri$$anon$3$$anon$4;
            0      10     1 out$2   Ljava/io/OutputStream;
            0      10     2     x   Ljava/lang/Object;
    MethodParameters:
      Name                           Flags
      $this                          final
      out$2                          final
      x                              final

  private static java.lang.Object $deserializeLambda$(java.lang.invoke.SerializedLambda);
    descriptor: (Ljava/lang/invoke/SerializedLambda;)Ljava/lang/Object;
    flags: (0x100a) ACC_PRIVATE, ACC_STATIC, ACC_SYNTHETIC
    Code:
      stack=1, locals=1, args_size=1
         0: aload_0
         1: invokedynamic #126,  0            // InvokeDynamic #1:lambdaDeserialize:(Ljava/lang/invoke/SerializedLambda;)Ljava/lang/Object;
         6: areturn
}
InnerClasses:
  public static final #17= #14 of #16;    // Lookup=class java/lang/invoke/MethodHandles$Lookup of class java/lang/invoke/MethodHandles
  public final #9;                        // class os/WritableLowPri$$anon$3
  public final #2;                        // class os/WritableLowPri$$anon$3$$anon$4
EnclosingMethod: #9.#12                 // os.WritableLowPri$$anon$3.getHandle
SourceFile: "Source.scala"
BootstrapMethods:
  0: #72 REF_invokeStatic java/lang/invoke/LambdaMetafactory.altMetafactory:(Ljava/lang/invoke/MethodHandles$Lookup;Ljava/lang/String;Ljava/lang/invoke/MethodType;[Ljava/lang/Object;)Ljava/lang/invoke/CallSite;
    Method arguments:
      #59 (Ljava/lang/Object;)Ljava/lang/Object;
      #64 REF_invokeStatic os/WritableLowPri$$anon$3$$anon$4.$anonfun$writeBytesTo$2$adapted:(Los/WritableLowPri$$anon$3$$anon$4;Ljava/io/OutputStream;Ljava/lang/Object;)Ljava/lang/Object;
      #59 (Ljava/lang/Object;)Ljava/lang/Object;
      #65 1
  1: #123 REF_invokeStatic scala/runtime/LambdaDeserialize.bootstrap:(Ljava/lang/invoke/MethodHandles$Lookup;Ljava/lang/String;Ljava/lang/invoke/MethodType;[Ljava/lang/invoke/MethodHandle;)Ljava/lang/invoke/CallSite;
    Method arguments:
      #64 REF_invokeStatic os/WritableLowPri$$anon$3$$anon$4.$anonfun$writeBytesTo$2$adapted:(Los/WritableLowPri$$anon$3$$anon$4;Ljava/io/OutputStream;Ljava/lang/Object;)Ljava/lang/Object;
  ScalaInlineInfo: length = 0x22 (unknown attribute)
   01 01 00 06 00 52 00 53 01 00 3C 00 3D 01 00 62
   00 63 01 00 1D 00 15 01 00 14 00 15 01 00 22 00
   23 01
  Scala: length = 0x0 (unknown attribute)

