Classfile /Users/mw/Projects/slang-braindump/.jar/jar8/assemble/slang-braindump/assemble/content/coursier/util/shaded/org/jsoup/helper/HttpConnection$Response.class
  Last modified May 29, 2022; size 21922 bytes
  SHA-256 checksum 0bffe70a212d38fcfe01a68a98c1d428af296ef1c4e12e72b2f8e76983383b33
  Compiled from "HttpConnection.java"
public class coursier.util.shaded.org.jsoup.helper.HttpConnection$Response extends coursier.util.shaded.org.jsoup.helper.HttpConnection$Base<coursier.util.shaded.org.jsoup.Connection$Response> implements coursier.util.shaded.org.jsoup.Connection$Response
  minor version: 0
  major version: 51
  flags: (0x0021) ACC_PUBLIC, ACC_SUPER
  this_class: #2                          // coursier/util/shaded/org/jsoup/helper/HttpConnection$Response
  super_class: #5                         // coursier/util/shaded/org/jsoup/helper/HttpConnection$Base
  interfaces: 1, fields: 14, methods: 44, attributes: 3
Constant pool:
    #1 = Utf8               coursier/util/shaded/org/jsoup/helper/HttpConnection$Response
    #2 = Class              #1            // coursier/util/shaded/org/jsoup/helper/HttpConnection$Response
    #3 = Utf8               Lcoursier/util/shaded/org/jsoup/helper/HttpConnection$Base<Lcoursier/util/shaded/org/jsoup/Connection$Response;>;Lcoursier/util/shaded/org/jsoup/Connection$Response;
    #4 = Utf8               coursier/util/shaded/org/jsoup/helper/HttpConnection$Base
    #5 = Class              #4            // coursier/util/shaded/org/jsoup/helper/HttpConnection$Base
    #6 = Utf8               coursier/util/shaded/org/jsoup/Connection$Response
    #7 = Class              #6            // coursier/util/shaded/org/jsoup/Connection$Response
    #8 = Utf8               HttpConnection.java
    #9 = Utf8               coursier/util/shaded/org/jsoup/helper/HttpConnection
   #10 = Class              #9            // coursier/util/shaded/org/jsoup/helper/HttpConnection
   #11 = Utf8               Base
   #12 = Utf8               coursier/util/shaded/org/jsoup/helper/HttpConnection$1
   #13 = Class              #12           // coursier/util/shaded/org/jsoup/helper/HttpConnection$1
   #14 = Utf8               Response
   #15 = Utf8               coursier/util/shaded/org/jsoup/Connection$Request
   #16 = Class              #15           // coursier/util/shaded/org/jsoup/Connection$Request
   #17 = Utf8               coursier/util/shaded/org/jsoup/Connection
   #18 = Class              #17           // coursier/util/shaded/org/jsoup/Connection
   #19 = Utf8               Request
   #20 = Utf8               coursier/util/shaded/org/jsoup/Connection$Method
   #21 = Class              #20           // coursier/util/shaded/org/jsoup/Connection$Method
   #22 = Utf8               Method
   #23 = Utf8               coursier/util/shaded/org/jsoup/Connection$Base
   #24 = Class              #23           // coursier/util/shaded/org/jsoup/Connection$Base
   #25 = Utf8               java/util/Map$Entry
   #26 = Class              #25           // java/util/Map$Entry
   #27 = Utf8               java/util/Map
   #28 = Class              #27           // java/util/Map
   #29 = Utf8               Entry
   #30 = Utf8               coursier/util/shaded/org/jsoup/helper/HttpConnection$Request
   #31 = Class              #30           // coursier/util/shaded/org/jsoup/helper/HttpConnection$Request
   #32 = Utf8               coursier/util/shaded/org/jsoup/nodes/Document$OutputSettings
   #33 = Class              #32           // coursier/util/shaded/org/jsoup/nodes/Document$OutputSettings
   #34 = Utf8               coursier/util/shaded/org/jsoup/nodes/Document
   #35 = Class              #34           // coursier/util/shaded/org/jsoup/nodes/Document
   #36 = Utf8               OutputSettings
   #37 = Utf8               coursier/util/shaded/org/jsoup/Connection$KeyVal
   #38 = Class              #37           // coursier/util/shaded/org/jsoup/Connection$KeyVal
   #39 = Utf8               KeyVal
   #40 = Utf8               MAX_REDIRECTS
   #41 = Utf8               I
   #42 = Integer            20
   #43 = Utf8               LOCATION
   #44 = Utf8               Ljava/lang/String;
   #45 = Utf8               Location
   #46 = String             #45           // Location
   #47 = Utf8               statusCode
   #48 = Utf8               statusMessage
   #49 = Utf8               byteData
   #50 = Utf8               Ljava/nio/ByteBuffer;
   #51 = Utf8               bodyStream
   #52 = Utf8               Ljava/io/InputStream;
   #53 = Utf8               conn
   #54 = Utf8               Ljava/net/HttpURLConnection;
   #55 = Utf8               charset
   #56 = Utf8               contentType
   #57 = Utf8               executed
   #58 = Utf8               Z
   #59 = Utf8               inputStreamRead
   #60 = Utf8               numRedirects
   #61 = Utf8               req
   #62 = Utf8               Lcoursier/util/shaded/org/jsoup/Connection$Request;
   #63 = Utf8               xmlContentTypeRxp
   #64 = Utf8               Ljava/util/regex/Pattern;
   #65 = Utf8               <init>
   #66 = Utf8               ()V
   #67 = Utf8               (Lcoursier/util/shaded/org/jsoup/helper/HttpConnection$1;)V
   #68 = NameAndType        #65:#67       // "<init>":(Lcoursier/util/shaded/org/jsoup/helper/HttpConnection$1;)V
   #69 = Methodref          #5.#68        // coursier/util/shaded/org/jsoup/helper/HttpConnection$Base."<init>":(Lcoursier/util/shaded/org/jsoup/helper/HttpConnection$1;)V
   #70 = NameAndType        #57:#58       // executed:Z
   #71 = Fieldref           #2.#70        // coursier/util/shaded/org/jsoup/helper/HttpConnection$Response.executed:Z
   #72 = NameAndType        #59:#58       // inputStreamRead:Z
   #73 = Fieldref           #2.#72        // coursier/util/shaded/org/jsoup/helper/HttpConnection$Response.inputStreamRead:Z
   #74 = NameAndType        #60:#41       // numRedirects:I
   #75 = Fieldref           #2.#74        // coursier/util/shaded/org/jsoup/helper/HttpConnection$Response.numRedirects:I
   #76 = Utf8               this
   #77 = Utf8               Lcoursier/util/shaded/org/jsoup/helper/HttpConnection$Response;
   #78 = Utf8               (Lcoursier/util/shaded/org/jsoup/helper/HttpConnection$Response;)V
   #79 = Utf8               java/io/IOException
   #80 = Class              #79           // java/io/IOException
   #81 = Utf8               Too many redirects occurred trying to load URL %s
   #82 = String             #81           // Too many redirects occurred trying to load URL %s
   #83 = Utf8               java/lang/Object
   #84 = Class              #83           // java/lang/Object
   #85 = Utf8               url
   #86 = Utf8               ()Ljava/net/URL;
   #87 = NameAndType        #85:#86       // url:()Ljava/net/URL;
   #88 = Methodref          #2.#87        // coursier/util/shaded/org/jsoup/helper/HttpConnection$Response.url:()Ljava/net/URL;
   #89 = Utf8               java/lang/String
   #90 = Class              #89           // java/lang/String
   #91 = Utf8               format
   #92 = Utf8               (Ljava/lang/String;[Ljava/lang/Object;)Ljava/lang/String;
   #93 = NameAndType        #91:#92       // format:(Ljava/lang/String;[Ljava/lang/Object;)Ljava/lang/String;
   #94 = Methodref          #90.#93       // java/lang/String.format:(Ljava/lang/String;[Ljava/lang/Object;)Ljava/lang/String;
   #95 = Utf8               (Ljava/lang/String;)V
   #96 = NameAndType        #65:#95       // "<init>":(Ljava/lang/String;)V
   #97 = Methodref          #80.#96       // java/io/IOException."<init>":(Ljava/lang/String;)V
   #98 = Utf8               previousResponse
   #99 = Utf8               execute
  #100 = Utf8               (Lcoursier/util/shaded/org/jsoup/Connection$Request;)Lcoursier/util/shaded/org/jsoup/helper/HttpConnection$Response;
  #101 = Utf8               (Lcoursier/util/shaded/org/jsoup/Connection$Request;Lcoursier/util/shaded/org/jsoup/helper/HttpConnection$Response;)Lcoursier/util/shaded/org/jsoup/helper/HttpConnection$Response;
  #102 = NameAndType        #99:#101      // execute:(Lcoursier/util/shaded/org/jsoup/Connection$Request;Lcoursier/util/shaded/org/jsoup/helper/HttpConnection$Response;)Lcoursier/util/shaded/org/jsoup/helper/HttpConnection$Response;
  #103 = Methodref          #2.#102       // coursier/util/shaded/org/jsoup/helper/HttpConnection$Response.execute:(Lcoursier/util/shaded/org/jsoup/Connection$Request;Lcoursier/util/shaded/org/jsoup/helper/HttpConnection$Response;)Lcoursier/util/shaded/org/jsoup/helper/HttpConnection$Response;
  #104 = Utf8               Request must not be null
  #105 = String             #104          // Request must not be null
  #106 = Utf8               coursier/util/shaded/org/jsoup/helper/Validate
  #107 = Class              #106          // coursier/util/shaded/org/jsoup/helper/Validate
  #108 = Utf8               notNull
  #109 = Utf8               (Ljava/lang/Object;Ljava/lang/String;)V
  #110 = NameAndType        #108:#109     // notNull:(Ljava/lang/Object;Ljava/lang/String;)V
  #111 = Methodref          #107.#110     // coursier/util/shaded/org/jsoup/helper/Validate.notNull:(Ljava/lang/Object;Ljava/lang/String;)V
  #112 = InterfaceMethodref #16.#87       // coursier/util/shaded/org/jsoup/Connection$Request.url:()Ljava/net/URL;
  #113 = Utf8               URL must be specified to connect
  #114 = String             #113          // URL must be specified to connect
  #115 = Utf8               java/net/URL
  #116 = Class              #115          // java/net/URL
  #117 = Utf8               getProtocol
  #118 = Utf8               ()Ljava/lang/String;
  #119 = NameAndType        #117:#118     // getProtocol:()Ljava/lang/String;
  #120 = Methodref          #116.#119     // java/net/URL.getProtocol:()Ljava/lang/String;
  #121 = Utf8               http
  #122 = String             #121          // http
  #123 = Utf8               equals
  #124 = Utf8               (Ljava/lang/Object;)Z
  #125 = NameAndType        #123:#124     // equals:(Ljava/lang/Object;)Z
  #126 = Methodref          #90.#125      // java/lang/String.equals:(Ljava/lang/Object;)Z
  #127 = Utf8               https
  #128 = String             #127          // https
  #129 = Utf8               java/net/MalformedURLException
  #130 = Class              #129          // java/net/MalformedURLException
  #131 = Utf8               Only http & https protocols supported
  #132 = String             #131          // Only http & https protocols supported
  #133 = Methodref          #130.#96      // java/net/MalformedURLException."<init>":(Ljava/lang/String;)V
  #134 = Utf8               method
  #135 = Utf8               ()Lcoursier/util/shaded/org/jsoup/Connection$Method;
  #136 = NameAndType        #134:#135     // method:()Lcoursier/util/shaded/org/jsoup/Connection$Method;
  #137 = InterfaceMethodref #16.#136      // coursier/util/shaded/org/jsoup/Connection$Request.method:()Lcoursier/util/shaded/org/jsoup/Connection$Method;
  #138 = Utf8               hasBody
  #139 = Utf8               ()Z
  #140 = NameAndType        #138:#139     // hasBody:()Z
  #141 = Methodref          #21.#140      // coursier/util/shaded/org/jsoup/Connection$Method.hasBody:()Z
  #142 = Utf8               requestBody
  #143 = NameAndType        #142:#118     // requestBody:()Ljava/lang/String;
  #144 = InterfaceMethodref #16.#143      // coursier/util/shaded/org/jsoup/Connection$Request.requestBody:()Ljava/lang/String;
  #145 = Utf8               java/lang/StringBuilder
  #146 = Class              #145          // java/lang/StringBuilder
  #147 = NameAndType        #65:#66       // "<init>":()V
  #148 = Methodref          #146.#147     // java/lang/StringBuilder."<init>":()V
  #149 = Utf8               Cannot set a request body for HTTP method
  #150 = String             #149          // Cannot set a request body for HTTP method
  #151 = Utf8               append
  #152 = Utf8               (Ljava/lang/String;)Ljava/lang/StringBuilder;
  #153 = NameAndType        #151:#152     // append:(Ljava/lang/String;)Ljava/lang/StringBuilder;
  #154 = Methodref          #146.#153     // java/lang/StringBuilder.append:(Ljava/lang/String;)Ljava/lang/StringBuilder;
  #155 = Utf8               (Ljava/lang/Object;)Ljava/lang/StringBuilder;
  #156 = NameAndType        #151:#155     // append:(Ljava/lang/Object;)Ljava/lang/StringBuilder;
  #157 = Methodref          #146.#156     // java/lang/StringBuilder.append:(Ljava/lang/Object;)Ljava/lang/StringBuilder;
  #158 = Utf8               toString
  #159 = NameAndType        #158:#118     // toString:()Ljava/lang/String;
  #160 = Methodref          #146.#159     // java/lang/StringBuilder.toString:()Ljava/lang/String;
  #161 = Utf8               isFalse
  #162 = Utf8               (ZLjava/lang/String;)V
  #163 = NameAndType        #161:#162     // isFalse:(ZLjava/lang/String;)V
  #164 = Methodref          #107.#163     // coursier/util/shaded/org/jsoup/helper/Validate.isFalse:(ZLjava/lang/String;)V
  #165 = Utf8               data
  #166 = Utf8               ()Ljava/util/Collection;
  #167 = NameAndType        #165:#166     // data:()Ljava/util/Collection;
  #168 = InterfaceMethodref #16.#167      // coursier/util/shaded/org/jsoup/Connection$Request.data:()Ljava/util/Collection;
  #169 = Utf8               java/util/Collection
  #170 = Class              #169          // java/util/Collection
  #171 = Utf8               size
  #172 = Utf8               ()I
  #173 = NameAndType        #171:#172     // size:()I
  #174 = InterfaceMethodref #170.#173     // java/util/Collection.size:()I
  #175 = Utf8               serialiseRequestUrl
  #176 = Utf8               (Lcoursier/util/shaded/org/jsoup/Connection$Request;)V
  #177 = NameAndType        #175:#176     // serialiseRequestUrl:(Lcoursier/util/shaded/org/jsoup/Connection$Request;)V
  #178 = Methodref          #2.#177       // coursier/util/shaded/org/jsoup/helper/HttpConnection$Response.serialiseRequestUrl:(Lcoursier/util/shaded/org/jsoup/Connection$Request;)V
  #179 = Utf8               setOutputContentType
  #180 = Utf8               (Lcoursier/util/shaded/org/jsoup/Connection$Request;)Ljava/lang/String;
  #181 = NameAndType        #179:#180     // setOutputContentType:(Lcoursier/util/shaded/org/jsoup/Connection$Request;)Ljava/lang/String;
  #182 = Methodref          #2.#181       // coursier/util/shaded/org/jsoup/helper/HttpConnection$Response.setOutputContentType:(Lcoursier/util/shaded/org/jsoup/Connection$Request;)Ljava/lang/String;
  #183 = Utf8               java/lang/System
  #184 = Class              #183          // java/lang/System
  #185 = Utf8               nanoTime
  #186 = Utf8               ()J
  #187 = NameAndType        #185:#186     // nanoTime:()J
  #188 = Methodref          #184.#187     // java/lang/System.nanoTime:()J
  #189 = Utf8               createConnection
  #190 = Utf8               (Lcoursier/util/shaded/org/jsoup/Connection$Request;)Ljava/net/HttpURLConnection;
  #191 = NameAndType        #189:#190     // createConnection:(Lcoursier/util/shaded/org/jsoup/Connection$Request;)Ljava/net/HttpURLConnection;
  #192 = Methodref          #2.#191       // coursier/util/shaded/org/jsoup/helper/HttpConnection$Response.createConnection:(Lcoursier/util/shaded/org/jsoup/Connection$Request;)Ljava/net/HttpURLConnection;
  #193 = Utf8               java/net/HttpURLConnection
  #194 = Class              #193          // java/net/HttpURLConnection
  #195 = Utf8               connect
  #196 = NameAndType        #195:#66      // connect:()V
  #197 = Methodref          #194.#196     // java/net/HttpURLConnection.connect:()V
  #198 = Utf8               getDoOutput
  #199 = NameAndType        #198:#139     // getDoOutput:()Z
  #200 = Methodref          #194.#199     // java/net/HttpURLConnection.getDoOutput:()Z
  #201 = Utf8               getOutputStream
  #202 = Utf8               ()Ljava/io/OutputStream;
  #203 = NameAndType        #201:#202     // getOutputStream:()Ljava/io/OutputStream;
  #204 = Methodref          #194.#203     // java/net/HttpURLConnection.getOutputStream:()Ljava/io/OutputStream;
  #205 = Utf8               writePost
  #206 = Utf8               (Lcoursier/util/shaded/org/jsoup/Connection$Request;Ljava/io/OutputStream;Ljava/lang/String;)V
  #207 = NameAndType        #205:#206     // writePost:(Lcoursier/util/shaded/org/jsoup/Connection$Request;Ljava/io/OutputStream;Ljava/lang/String;)V
  #208 = Methodref          #2.#207       // coursier/util/shaded/org/jsoup/helper/HttpConnection$Response.writePost:(Lcoursier/util/shaded/org/jsoup/Connection$Request;Ljava/io/OutputStream;Ljava/lang/String;)V
  #209 = Utf8               getResponseCode
  #210 = NameAndType        #209:#172     // getResponseCode:()I
  #211 = Methodref          #194.#210     // java/net/HttpURLConnection.getResponseCode:()I
  #212 = NameAndType        #65:#78       // "<init>":(Lcoursier/util/shaded/org/jsoup/helper/HttpConnection$Response;)V
  #213 = Methodref          #2.#212       // coursier/util/shaded/org/jsoup/helper/HttpConnection$Response."<init>":(Lcoursier/util/shaded/org/jsoup/helper/HttpConnection$Response;)V
  #214 = Utf8               setupFromConnection
  #215 = Utf8               (Ljava/net/HttpURLConnection;Lcoursier/util/shaded/org/jsoup/helper/HttpConnection$Response;)V
  #216 = NameAndType        #214:#215     // setupFromConnection:(Ljava/net/HttpURLConnection;Lcoursier/util/shaded/org/jsoup/helper/HttpConnection$Response;)V
  #217 = Methodref          #2.#216       // coursier/util/shaded/org/jsoup/helper/HttpConnection$Response.setupFromConnection:(Ljava/net/HttpURLConnection;Lcoursier/util/shaded/org/jsoup/helper/HttpConnection$Response;)V
  #218 = NameAndType        #61:#62       // req:Lcoursier/util/shaded/org/jsoup/Connection$Request;
  #219 = Fieldref           #2.#218       // coursier/util/shaded/org/jsoup/helper/HttpConnection$Response.req:Lcoursier/util/shaded/org/jsoup/Connection$Request;
  #220 = Utf8               hasHeader
  #221 = Utf8               (Ljava/lang/String;)Z
  #222 = NameAndType        #220:#221     // hasHeader:(Ljava/lang/String;)Z
  #223 = Methodref          #2.#222       // coursier/util/shaded/org/jsoup/helper/HttpConnection$Response.hasHeader:(Ljava/lang/String;)Z
  #224 = Utf8               followRedirects
  #225 = NameAndType        #224:#139     // followRedirects:()Z
  #226 = InterfaceMethodref #16.#225      // coursier/util/shaded/org/jsoup/Connection$Request.followRedirects:()Z
  #227 = Utf8               GET
  #228 = Utf8               Lcoursier/util/shaded/org/jsoup/Connection$Method;
  #229 = NameAndType        #227:#228     // GET:Lcoursier/util/shaded/org/jsoup/Connection$Method;
  #230 = Fieldref           #21.#229      // coursier/util/shaded/org/jsoup/Connection$Method.GET:Lcoursier/util/shaded/org/jsoup/Connection$Method;
  #231 = Utf8               (Lcoursier/util/shaded/org/jsoup/Connection$Method;)Lcoursier/util/shaded/org/jsoup/Connection$Base;
  #232 = NameAndType        #134:#231     // method:(Lcoursier/util/shaded/org/jsoup/Connection$Method;)Lcoursier/util/shaded/org/jsoup/Connection$Base;
  #233 = InterfaceMethodref #16.#232      // coursier/util/shaded/org/jsoup/Connection$Request.method:(Lcoursier/util/shaded/org/jsoup/Connection$Method;)Lcoursier/util/shaded/org/jsoup/Connection$Base;
  #234 = Utf8               clear
  #235 = NameAndType        #234:#66      // clear:()V
  #236 = InterfaceMethodref #170.#235     // java/util/Collection.clear:()V
  #237 = Utf8               (Ljava/lang/String;)Lcoursier/util/shaded/org/jsoup/Connection$Request;
  #238 = NameAndType        #142:#237     // requestBody:(Ljava/lang/String;)Lcoursier/util/shaded/org/jsoup/Connection$Request;
  #239 = InterfaceMethodref #16.#238      // coursier/util/shaded/org/jsoup/Connection$Request.requestBody:(Ljava/lang/String;)Lcoursier/util/shaded/org/jsoup/Connection$Request;
  #240 = Utf8               Content-Type
  #241 = String             #240          // Content-Type
  #242 = Utf8               removeHeader
  #243 = Utf8               (Ljava/lang/String;)Lcoursier/util/shaded/org/jsoup/Connection$Base;
  #244 = NameAndType        #242:#243     // removeHeader:(Ljava/lang/String;)Lcoursier/util/shaded/org/jsoup/Connection$Base;
  #245 = InterfaceMethodref #16.#244      // coursier/util/shaded/org/jsoup/Connection$Request.removeHeader:(Ljava/lang/String;)Lcoursier/util/shaded/org/jsoup/Connection$Base;
  #246 = Utf8               header
  #247 = Utf8               (Ljava/lang/String;)Ljava/lang/String;
  #248 = NameAndType        #246:#247     // header:(Ljava/lang/String;)Ljava/lang/String;
  #249 = Methodref          #2.#248       // coursier/util/shaded/org/jsoup/helper/HttpConnection$Response.header:(Ljava/lang/String;)Ljava/lang/String;
  #250 = Utf8               http:/
  #251 = String             #250          // http:/
  #252 = Utf8               startsWith
  #253 = NameAndType        #252:#221     // startsWith:(Ljava/lang/String;)Z
  #254 = Methodref          #90.#253      // java/lang/String.startsWith:(Ljava/lang/String;)Z
  #255 = Utf8               charAt
  #256 = Utf8               (I)C
  #257 = NameAndType        #255:#256     // charAt:(I)C
  #258 = Methodref          #90.#257      // java/lang/String.charAt:(I)C
  #259 = Utf8               substring
  #260 = Utf8               (I)Ljava/lang/String;
  #261 = NameAndType        #259:#260     // substring:(I)Ljava/lang/String;
  #262 = Methodref          #90.#261      // java/lang/String.substring:(I)Ljava/lang/String;
  #263 = Utf8               coursier/util/shaded/org/jsoup/internal/StringUtil
  #264 = Class              #263          // coursier/util/shaded/org/jsoup/internal/StringUtil
  #265 = Utf8               resolve
  #266 = Utf8               (Ljava/net/URL;Ljava/lang/String;)Ljava/net/URL;
  #267 = NameAndType        #265:#266     // resolve:(Ljava/net/URL;Ljava/lang/String;)Ljava/net/URL;
  #268 = Methodref          #264.#267     // coursier/util/shaded/org/jsoup/internal/StringUtil.resolve:(Ljava/net/URL;Ljava/lang/String;)Ljava/net/URL;
  #269 = Utf8               encodeUrl
  #270 = Utf8               (Ljava/net/URL;)Ljava/net/URL;
  #271 = NameAndType        #269:#270     // encodeUrl:(Ljava/net/URL;)Ljava/net/URL;
  #272 = Methodref          #10.#271      // coursier/util/shaded/org/jsoup/helper/HttpConnection.encodeUrl:(Ljava/net/URL;)Ljava/net/URL;
  #273 = Utf8               (Ljava/net/URL;)Lcoursier/util/shaded/org/jsoup/Connection$Base;
  #274 = NameAndType        #85:#273      // url:(Ljava/net/URL;)Lcoursier/util/shaded/org/jsoup/Connection$Base;
  #275 = InterfaceMethodref #16.#274      // coursier/util/shaded/org/jsoup/Connection$Request.url:(Ljava/net/URL;)Lcoursier/util/shaded/org/jsoup/Connection$Base;
  #276 = Utf8               cookies
  #277 = Utf8               Ljava/util/Map;
  #278 = NameAndType        #276:#277     // cookies:Ljava/util/Map;
  #279 = Fieldref           #2.#278       // coursier/util/shaded/org/jsoup/helper/HttpConnection$Response.cookies:Ljava/util/Map;
  #280 = Utf8               entrySet
  #281 = Utf8               ()Ljava/util/Set;
  #282 = NameAndType        #280:#281     // entrySet:()Ljava/util/Set;
  #283 = InterfaceMethodref #28.#282      // java/util/Map.entrySet:()Ljava/util/Set;
  #284 = Utf8               java/util/Set
  #285 = Class              #284          // java/util/Set
  #286 = Utf8               iterator
  #287 = Utf8               ()Ljava/util/Iterator;
  #288 = NameAndType        #286:#287     // iterator:()Ljava/util/Iterator;
  #289 = InterfaceMethodref #285.#288     // java/util/Set.iterator:()Ljava/util/Iterator;
  #290 = Utf8               java/util/Iterator
  #291 = Class              #290          // java/util/Iterator
  #292 = Utf8               hasNext
  #293 = NameAndType        #292:#139     // hasNext:()Z
  #294 = InterfaceMethodref #291.#293     // java/util/Iterator.hasNext:()Z
  #295 = Utf8               next
  #296 = Utf8               ()Ljava/lang/Object;
  #297 = NameAndType        #295:#296     // next:()Ljava/lang/Object;
  #298 = InterfaceMethodref #291.#297     // java/util/Iterator.next:()Ljava/lang/Object;
  #299 = Utf8               getKey
  #300 = NameAndType        #299:#296     // getKey:()Ljava/lang/Object;
  #301 = InterfaceMethodref #26.#300      // java/util/Map$Entry.getKey:()Ljava/lang/Object;
  #302 = Utf8               getValue
  #303 = NameAndType        #302:#296     // getValue:()Ljava/lang/Object;
  #304 = InterfaceMethodref #26.#303      // java/util/Map$Entry.getValue:()Ljava/lang/Object;
  #305 = Utf8               cookie
  #306 = Utf8               (Ljava/lang/String;Ljava/lang/String;)Lcoursier/util/shaded/org/jsoup/Connection$Base;
  #307 = NameAndType        #305:#306     // cookie:(Ljava/lang/String;Ljava/lang/String;)Lcoursier/util/shaded/org/jsoup/Connection$Base;
  #308 = InterfaceMethodref #16.#307      // coursier/util/shaded/org/jsoup/Connection$Request.cookie:(Ljava/lang/String;Ljava/lang/String;)Lcoursier/util/shaded/org/jsoup/Connection$Base;
  #309 = Utf8               ignoreHttpErrors
  #310 = NameAndType        #309:#139     // ignoreHttpErrors:()Z
  #311 = InterfaceMethodref #16.#310      // coursier/util/shaded/org/jsoup/Connection$Request.ignoreHttpErrors:()Z
  #312 = Utf8               coursier/util/shaded/org/jsoup/HttpStatusException
  #313 = Class              #312          // coursier/util/shaded/org/jsoup/HttpStatusException
  #314 = Utf8               HTTP error fetching URL
  #315 = String             #314          // HTTP error fetching URL
  #316 = Methodref          #116.#159     // java/net/URL.toString:()Ljava/lang/String;
  #317 = Utf8               (Ljava/lang/String;ILjava/lang/String;)V
  #318 = NameAndType        #65:#317      // "<init>":(Ljava/lang/String;ILjava/lang/String;)V
  #319 = Methodref          #313.#318     // coursier/util/shaded/org/jsoup/HttpStatusException."<init>":(Ljava/lang/String;ILjava/lang/String;)V
  #320 = NameAndType        #56:#118      // contentType:()Ljava/lang/String;
  #321 = Methodref          #2.#320       // coursier/util/shaded/org/jsoup/helper/HttpConnection$Response.contentType:()Ljava/lang/String;
  #322 = Utf8               ignoreContentType
  #323 = NameAndType        #322:#139     // ignoreContentType:()Z
  #324 = InterfaceMethodref #16.#323      // coursier/util/shaded/org/jsoup/Connection$Request.ignoreContentType:()Z
  #325 = Utf8               text/
  #326 = String             #325          // text/
  #327 = NameAndType        #63:#64       // xmlContentTypeRxp:Ljava/util/regex/Pattern;
  #328 = Fieldref           #2.#327       // coursier/util/shaded/org/jsoup/helper/HttpConnection$Response.xmlContentTypeRxp:Ljava/util/regex/Pattern;
  #329 = Utf8               java/util/regex/Pattern
  #330 = Class              #329          // java/util/regex/Pattern
  #331 = Utf8               matcher
  #332 = Utf8               (Ljava/lang/CharSequence;)Ljava/util/regex/Matcher;
  #333 = NameAndType        #331:#332     // matcher:(Ljava/lang/CharSequence;)Ljava/util/regex/Matcher;
  #334 = Methodref          #330.#333     // java/util/regex/Pattern.matcher:(Ljava/lang/CharSequence;)Ljava/util/regex/Matcher;
  #335 = Utf8               java/util/regex/Matcher
  #336 = Class              #335          // java/util/regex/Matcher
  #337 = Utf8               matches
  #338 = NameAndType        #337:#139     // matches:()Z
  #339 = Methodref          #336.#338     // java/util/regex/Matcher.matches:()Z
  #340 = Utf8               coursier/util/shaded/org/jsoup/UnsupportedMimeTypeException
  #341 = Class              #340          // coursier/util/shaded/org/jsoup/UnsupportedMimeTypeException
  #342 = Utf8               Unhandled content type. Must be text/*, application/xml, or application/*+xml
  #343 = String             #342          // Unhandled content type. Must be text/*, application/xml, or application/*+xml
  #344 = Utf8               (Ljava/lang/String;Ljava/lang/String;Ljava/lang/String;)V
  #345 = NameAndType        #65:#344      // "<init>":(Ljava/lang/String;Ljava/lang/String;Ljava/lang/String;)V
  #346 = Methodref          #341.#345     // coursier/util/shaded/org/jsoup/UnsupportedMimeTypeException."<init>":(Ljava/lang/String;Ljava/lang/String;Ljava/lang/String;)V
  #347 = Utf8               access$100
  #348 = Utf8               (Lcoursier/util/shaded/org/jsoup/helper/HttpConnection$Request;)Z
  #349 = NameAndType        #347:#348     // access$100:(Lcoursier/util/shaded/org/jsoup/helper/HttpConnection$Request;)Z
  #350 = Methodref          #31.#349      // coursier/util/shaded/org/jsoup/helper/HttpConnection$Request.access$100:(Lcoursier/util/shaded/org/jsoup/helper/HttpConnection$Request;)Z
  #351 = Utf8               coursier/util/shaded/org/jsoup/parser/Parser
  #352 = Class              #351          // coursier/util/shaded/org/jsoup/parser/Parser
  #353 = Utf8               xmlParser
  #354 = Utf8               ()Lcoursier/util/shaded/org/jsoup/parser/Parser;
  #355 = NameAndType        #353:#354     // xmlParser:()Lcoursier/util/shaded/org/jsoup/parser/Parser;
  #356 = Methodref          #352.#355     // coursier/util/shaded/org/jsoup/parser/Parser.xmlParser:()Lcoursier/util/shaded/org/jsoup/parser/Parser;
  #357 = Utf8               parser
  #358 = Utf8               (Lcoursier/util/shaded/org/jsoup/parser/Parser;)Lcoursier/util/shaded/org/jsoup/Connection$Request;
  #359 = NameAndType        #357:#358     // parser:(Lcoursier/util/shaded/org/jsoup/parser/Parser;)Lcoursier/util/shaded/org/jsoup/Connection$Request;
  #360 = InterfaceMethodref #16.#359      // coursier/util/shaded/org/jsoup/Connection$Request.parser:(Lcoursier/util/shaded/org/jsoup/parser/Parser;)Lcoursier/util/shaded/org/jsoup/Connection$Request;
  #361 = NameAndType        #56:#44       // contentType:Ljava/lang/String;
  #362 = Fieldref           #2.#361       // coursier/util/shaded/org/jsoup/helper/HttpConnection$Response.contentType:Ljava/lang/String;
  #363 = Utf8               coursier/util/shaded/org/jsoup/helper/DataUtil
  #364 = Class              #363          // coursier/util/shaded/org/jsoup/helper/DataUtil
  #365 = Utf8               getCharsetFromContentType
  #366 = NameAndType        #365:#247     // getCharsetFromContentType:(Ljava/lang/String;)Ljava/lang/String;
  #367 = Methodref          #364.#366     // coursier/util/shaded/org/jsoup/helper/DataUtil.getCharsetFromContentType:(Ljava/lang/String;)Ljava/lang/String;
  #368 = NameAndType        #55:#44       // charset:Ljava/lang/String;
  #369 = Fieldref           #2.#368       // coursier/util/shaded/org/jsoup/helper/HttpConnection$Response.charset:Ljava/lang/String;
  #370 = Utf8               getContentLength
  #371 = NameAndType        #370:#172     // getContentLength:()I
  #372 = Methodref          #194.#371     // java/net/HttpURLConnection.getContentLength:()I
  #373 = Utf8               HEAD
  #374 = NameAndType        #373:#228     // HEAD:Lcoursier/util/shaded/org/jsoup/Connection$Method;
  #375 = Fieldref           #21.#374      // coursier/util/shaded/org/jsoup/Connection$Method.HEAD:Lcoursier/util/shaded/org/jsoup/Connection$Method;
  #376 = NameAndType        #51:#52       // bodyStream:Ljava/io/InputStream;
  #377 = Fieldref           #2.#376       // coursier/util/shaded/org/jsoup/helper/HttpConnection$Response.bodyStream:Ljava/io/InputStream;
  #378 = Utf8               getErrorStream
  #379 = Utf8               ()Ljava/io/InputStream;
  #380 = NameAndType        #378:#379     // getErrorStream:()Ljava/io/InputStream;
  #381 = Methodref          #194.#380     // java/net/HttpURLConnection.getErrorStream:()Ljava/io/InputStream;
  #382 = Utf8               getInputStream
  #383 = NameAndType        #382:#379     // getInputStream:()Ljava/io/InputStream;
  #384 = Methodref          #194.#383     // java/net/HttpURLConnection.getInputStream:()Ljava/io/InputStream;
  #385 = Utf8               java/io/InputStream
  #386 = Class              #385          // java/io/InputStream
  #387 = Utf8               Content-Encoding
  #388 = String             #387          // Content-Encoding
  #389 = Utf8               gzip
  #390 = String             #389          // gzip
  #391 = Utf8               hasHeaderWithValue
  #392 = Utf8               (Ljava/lang/String;Ljava/lang/String;)Z
  #393 = NameAndType        #391:#392     // hasHeaderWithValue:(Ljava/lang/String;Ljava/lang/String;)Z
  #394 = Methodref          #2.#393       // coursier/util/shaded/org/jsoup/helper/HttpConnection$Response.hasHeaderWithValue:(Ljava/lang/String;Ljava/lang/String;)Z
  #395 = Utf8               java/util/zip/GZIPInputStream
  #396 = Class              #395          // java/util/zip/GZIPInputStream
  #397 = Utf8               (Ljava/io/InputStream;)V
  #398 = NameAndType        #65:#397      // "<init>":(Ljava/io/InputStream;)V
  #399 = Methodref          #396.#398     // java/util/zip/GZIPInputStream."<init>":(Ljava/io/InputStream;)V
  #400 = Utf8               deflate
  #401 = String             #400          // deflate
  #402 = Utf8               java/util/zip/InflaterInputStream
  #403 = Class              #402          // java/util/zip/InflaterInputStream
  #404 = Utf8               java/util/zip/Inflater
  #405 = Class              #404          // java/util/zip/Inflater
  #406 = Utf8               (Z)V
  #407 = NameAndType        #65:#406      // "<init>":(Z)V
  #408 = Methodref          #405.#407     // java/util/zip/Inflater."<init>":(Z)V
  #409 = Utf8               (Ljava/io/InputStream;Ljava/util/zip/Inflater;)V
  #410 = NameAndType        #65:#409      // "<init>":(Ljava/io/InputStream;Ljava/util/zip/Inflater;)V
  #411 = Methodref          #403.#410     // java/util/zip/InflaterInputStream."<init>":(Ljava/io/InputStream;Ljava/util/zip/Inflater;)V
  #412 = Integer            32768
  #413 = Utf8               maxBodySize
  #414 = NameAndType        #413:#172     // maxBodySize:()I
  #415 = InterfaceMethodref #16.#414      // coursier/util/shaded/org/jsoup/Connection$Request.maxBodySize:()I
  #416 = Utf8               coursier/util/shaded/org/jsoup/internal/ConstrainableInputStream
  #417 = Class              #416          // coursier/util/shaded/org/jsoup/internal/ConstrainableInputStream
  #418 = Utf8               wrap
  #419 = Utf8               (Ljava/io/InputStream;II)Lcoursier/util/shaded/org/jsoup/internal/ConstrainableInputStream;
  #420 = NameAndType        #418:#419     // wrap:(Ljava/io/InputStream;II)Lcoursier/util/shaded/org/jsoup/internal/ConstrainableInputStream;
  #421 = Methodref          #417.#420     // coursier/util/shaded/org/jsoup/internal/ConstrainableInputStream.wrap:(Ljava/io/InputStream;II)Lcoursier/util/shaded/org/jsoup/internal/ConstrainableInputStream;
  #422 = Utf8               timeout
  #423 = NameAndType        #422:#172     // timeout:()I
  #424 = InterfaceMethodref #16.#423      // coursier/util/shaded/org/jsoup/Connection$Request.timeout:()I
  #425 = Utf8               (JJ)Lcoursier/util/shaded/org/jsoup/internal/ConstrainableInputStream;
  #426 = NameAndType        #422:#425     // timeout:(JJ)Lcoursier/util/shaded/org/jsoup/internal/ConstrainableInputStream;
  #427 = Methodref          #417.#426     // coursier/util/shaded/org/jsoup/internal/ConstrainableInputStream.timeout:(JJ)Lcoursier/util/shaded/org/jsoup/internal/ConstrainableInputStream;
  #428 = Utf8               emptyByteBuffer
  #429 = Utf8               ()Ljava/nio/ByteBuffer;
  #430 = NameAndType        #428:#429     // emptyByteBuffer:()Ljava/nio/ByteBuffer;
  #431 = Methodref          #364.#430     // coursier/util/shaded/org/jsoup/helper/DataUtil.emptyByteBuffer:()Ljava/nio/ByteBuffer;
  #432 = NameAndType        #49:#50       // byteData:Ljava/nio/ByteBuffer;
  #433 = Fieldref           #2.#432       // coursier/util/shaded/org/jsoup/helper/HttpConnection$Response.byteData:Ljava/nio/ByteBuffer;
  #434 = Utf8               safeClose
  #435 = NameAndType        #434:#66      // safeClose:()V
  #436 = Methodref          #2.#435       // coursier/util/shaded/org/jsoup/helper/HttpConnection$Response.safeClose:()V
  #437 = Utf8               Ljava/util/Map$Entry<Ljava/lang/String;Ljava/lang/String;>;
  #438 = Utf8               Ljava/util/Map$Entry;
  #439 = Utf8               location
  #440 = Utf8               redir
  #441 = Utf8               Ljava/net/URL;
  #442 = Utf8               status
  #443 = Utf8               e
  #444 = Utf8               Ljava/io/IOException;
  #445 = Utf8               protocol
  #446 = Utf8               methodHasBody
  #447 = Utf8               hasRequestBody
  #448 = Utf8               mimeBoundary
  #449 = Utf8               startTime
  #450 = Utf8               J
  #451 = Utf8               res
  #452 = NameAndType        #47:#41       // statusCode:I
  #453 = Fieldref           #2.#452       // coursier/util/shaded/org/jsoup/helper/HttpConnection$Response.statusCode:I
  #454 = NameAndType        #48:#44       // statusMessage:Ljava/lang/String;
  #455 = Fieldref           #2.#454       // coursier/util/shaded/org/jsoup/helper/HttpConnection$Response.statusMessage:Ljava/lang/String;
  #456 = Utf8               (Ljava/lang/String;)Lcoursier/util/shaded/org/jsoup/helper/HttpConnection$Response;
  #457 = Utf8               parse
  #458 = Utf8               ()Lcoursier/util/shaded/org/jsoup/nodes/Document;
  #459 = Utf8               Request must be executed (with .execute(), .get(), or .post() before parsing response
  #460 = String             #459          // Request must be executed (with .execute(), .get(), or .post() before parsing response
  #461 = Utf8               isTrue
  #462 = NameAndType        #461:#162     // isTrue:(ZLjava/lang/String;)V
  #463 = Methodref          #107.#462     // coursier/util/shaded/org/jsoup/helper/Validate.isTrue:(ZLjava/lang/String;)V
  #464 = Utf8               java/io/ByteArrayInputStream
  #465 = Class              #464          // java/io/ByteArrayInputStream
  #466 = Utf8               java/nio/ByteBuffer
  #467 = Class              #466          // java/nio/ByteBuffer
  #468 = Utf8               array
  #469 = Utf8               ()[B
  #470 = NameAndType        #468:#469     // array:()[B
  #471 = Methodref          #467.#470     // java/nio/ByteBuffer.array:()[B
  #472 = Utf8               ([B)V
  #473 = NameAndType        #65:#472      // "<init>":([B)V
  #474 = Methodref          #465.#473     // java/io/ByteArrayInputStream."<init>":([B)V
  #475 = Utf8               Input stream already read and parsed, cannot re-read.
  #476 = String             #475          // Input stream already read and parsed, cannot re-read.
  #477 = NameAndType        #85:#441      // url:Ljava/net/URL;
  #478 = Fieldref           #2.#477       // coursier/util/shaded/org/jsoup/helper/HttpConnection$Response.url:Ljava/net/URL;
  #479 = Utf8               toExternalForm
  #480 = NameAndType        #479:#118     // toExternalForm:()Ljava/lang/String;
  #481 = Methodref          #116.#480     // java/net/URL.toExternalForm:()Ljava/lang/String;
  #482 = NameAndType        #357:#354     // parser:()Lcoursier/util/shaded/org/jsoup/parser/Parser;
  #483 = InterfaceMethodref #16.#482      // coursier/util/shaded/org/jsoup/Connection$Request.parser:()Lcoursier/util/shaded/org/jsoup/parser/Parser;
  #484 = Utf8               parseInputStream
  #485 = Utf8               (Ljava/io/InputStream;Ljava/lang/String;Ljava/lang/String;Lcoursier/util/shaded/org/jsoup/parser/Parser;)Lcoursier/util/shaded/org/jsoup/nodes/Document;
  #486 = NameAndType        #484:#485     // parseInputStream:(Ljava/io/InputStream;Ljava/lang/String;Ljava/lang/String;Lcoursier/util/shaded/org/jsoup/parser/Parser;)Lcoursier/util/shaded/org/jsoup/nodes/Document;
  #487 = Methodref          #364.#486     // coursier/util/shaded/org/jsoup/helper/DataUtil.parseInputStream:(Ljava/io/InputStream;Ljava/lang/String;Ljava/lang/String;Lcoursier/util/shaded/org/jsoup/parser/Parser;)Lcoursier/util/shaded/org/jsoup/nodes/Document;
  #488 = Utf8               outputSettings
  #489 = Utf8               ()Lcoursier/util/shaded/org/jsoup/nodes/Document$OutputSettings;
  #490 = NameAndType        #488:#489     // outputSettings:()Lcoursier/util/shaded/org/jsoup/nodes/Document$OutputSettings;
  #491 = Methodref          #35.#490      // coursier/util/shaded/org/jsoup/nodes/Document.outputSettings:()Lcoursier/util/shaded/org/jsoup/nodes/Document$OutputSettings;
  #492 = Utf8               ()Ljava/nio/charset/Charset;
  #493 = NameAndType        #55:#492      // charset:()Ljava/nio/charset/Charset;
  #494 = Methodref          #33.#493      // coursier/util/shaded/org/jsoup/nodes/Document$OutputSettings.charset:()Ljava/nio/charset/Charset;
  #495 = Utf8               java/nio/charset/Charset
  #496 = Class              #495          // java/nio/charset/Charset
  #497 = Utf8               name
  #498 = NameAndType        #497:#118     // name:()Ljava/lang/String;
  #499 = Methodref          #496.#498     // java/nio/charset/Charset.name:()Ljava/lang/String;
  #500 = Utf8               doc
  #501 = Utf8               Lcoursier/util/shaded/org/jsoup/nodes/Document;
  #502 = Utf8               prepareByteData
  #503 = Utf8               Request must be executed (with .execute(), .get(), or .post() before getting response body
  #504 = String             #503          // Request must be executed (with .execute(), .get(), or .post() before getting response body
  #505 = Utf8               Request has already been read (with .parse())
  #506 = String             #505          // Request has already been read (with .parse())
  #507 = Utf8               readToByteBuffer
  #508 = Utf8               (Ljava/io/InputStream;I)Ljava/nio/ByteBuffer;
  #509 = NameAndType        #507:#508     // readToByteBuffer:(Ljava/io/InputStream;I)Ljava/nio/ByteBuffer;
  #510 = Methodref          #364.#509     // coursier/util/shaded/org/jsoup/helper/DataUtil.readToByteBuffer:(Ljava/io/InputStream;I)Ljava/nio/ByteBuffer;
  #511 = Utf8               coursier/util/shaded/org/jsoup/UncheckedIOException
  #512 = Class              #511          // coursier/util/shaded/org/jsoup/UncheckedIOException
  #513 = Utf8               (Ljava/io/IOException;)V
  #514 = NameAndType        #65:#513      // "<init>":(Ljava/io/IOException;)V
  #515 = Methodref          #512.#514     // coursier/util/shaded/org/jsoup/UncheckedIOException."<init>":(Ljava/io/IOException;)V
  #516 = Utf8               java/lang/Throwable
  #517 = Class              #516          // java/lang/Throwable
  #518 = Utf8               body
  #519 = NameAndType        #502:#66      // prepareByteData:()V
  #520 = Methodref          #2.#519       // coursier/util/shaded/org/jsoup/helper/HttpConnection$Response.prepareByteData:()V
  #521 = Utf8               UTF-8
  #522 = String             #521          // UTF-8
  #523 = Utf8               forName
  #524 = Utf8               (Ljava/lang/String;)Ljava/nio/charset/Charset;
  #525 = NameAndType        #523:#524     // forName:(Ljava/lang/String;)Ljava/nio/charset/Charset;
  #526 = Methodref          #496.#525     // java/nio/charset/Charset.forName:(Ljava/lang/String;)Ljava/nio/charset/Charset;
  #527 = Utf8               decode
  #528 = Utf8               (Ljava/nio/ByteBuffer;)Ljava/nio/CharBuffer;
  #529 = NameAndType        #527:#528     // decode:(Ljava/nio/ByteBuffer;)Ljava/nio/CharBuffer;
  #530 = Methodref          #496.#529     // java/nio/charset/Charset.decode:(Ljava/nio/ByteBuffer;)Ljava/nio/CharBuffer;
  #531 = Utf8               java/nio/CharBuffer
  #532 = Class              #531          // java/nio/CharBuffer
  #533 = Methodref          #532.#159     // java/nio/CharBuffer.toString:()Ljava/lang/String;
  #534 = Utf8               java/nio/Buffer
  #535 = Class              #534          // java/nio/Buffer
  #536 = Utf8               rewind
  #537 = Utf8               ()Ljava/nio/Buffer;
  #538 = NameAndType        #536:#537     // rewind:()Ljava/nio/Buffer;
  #539 = Methodref          #535.#538     // java/nio/Buffer.rewind:()Ljava/nio/Buffer;
  #540 = Utf8               bodyAsBytes
  #541 = Utf8               bufferUp
  #542 = Utf8               ()Lcoursier/util/shaded/org/jsoup/Connection$Response;
  #543 = Utf8               ()Ljava/io/BufferedInputStream;
  #544 = Utf8               Request has already been read
  #545 = String             #544          // Request has already been read
  #546 = Utf8               proxy
  #547 = Utf8               ()Ljava/net/Proxy;
  #548 = NameAndType        #546:#547     // proxy:()Ljava/net/Proxy;
  #549 = InterfaceMethodref #16.#548      // coursier/util/shaded/org/jsoup/Connection$Request.proxy:()Ljava/net/Proxy;
  #550 = Utf8               openConnection
  #551 = Utf8               ()Ljava/net/URLConnection;
  #552 = NameAndType        #550:#551     // openConnection:()Ljava/net/URLConnection;
  #553 = Methodref          #116.#552     // java/net/URL.openConnection:()Ljava/net/URLConnection;
  #554 = Utf8               (Ljava/net/Proxy;)Ljava/net/URLConnection;
  #555 = NameAndType        #550:#554     // openConnection:(Ljava/net/Proxy;)Ljava/net/URLConnection;
  #556 = Methodref          #116.#555     // java/net/URL.openConnection:(Ljava/net/Proxy;)Ljava/net/URLConnection;
  #557 = Utf8               java/net/URLConnection
  #558 = Class              #557          // java/net/URLConnection
  #559 = Methodref          #21.#498      // coursier/util/shaded/org/jsoup/Connection$Method.name:()Ljava/lang/String;
  #560 = Utf8               setRequestMethod
  #561 = NameAndType        #560:#95      // setRequestMethod:(Ljava/lang/String;)V
  #562 = Methodref          #194.#561     // java/net/HttpURLConnection.setRequestMethod:(Ljava/lang/String;)V
  #563 = Utf8               setInstanceFollowRedirects
  #564 = NameAndType        #563:#406     // setInstanceFollowRedirects:(Z)V
  #565 = Methodref          #194.#564     // java/net/HttpURLConnection.setInstanceFollowRedirects:(Z)V
  #566 = Utf8               setConnectTimeout
  #567 = Utf8               (I)V
  #568 = NameAndType        #566:#567     // setConnectTimeout:(I)V
  #569 = Methodref          #194.#568     // java/net/HttpURLConnection.setConnectTimeout:(I)V
  #570 = Utf8               setReadTimeout
  #571 = NameAndType        #570:#567     // setReadTimeout:(I)V
  #572 = Methodref          #194.#571     // java/net/HttpURLConnection.setReadTimeout:(I)V
  #573 = Utf8               sslSocketFactory
  #574 = Utf8               ()Ljavax/net/ssl/SSLSocketFactory;
  #575 = NameAndType        #573:#574     // sslSocketFactory:()Ljavax/net/ssl/SSLSocketFactory;
  #576 = InterfaceMethodref #16.#575      // coursier/util/shaded/org/jsoup/Connection$Request.sslSocketFactory:()Ljavax/net/ssl/SSLSocketFactory;
  #577 = Utf8               javax/net/ssl/HttpsURLConnection
  #578 = Class              #577          // javax/net/ssl/HttpsURLConnection
  #579 = Utf8               setSSLSocketFactory
  #580 = Utf8               (Ljavax/net/ssl/SSLSocketFactory;)V
  #581 = NameAndType        #579:#580     // setSSLSocketFactory:(Ljavax/net/ssl/SSLSocketFactory;)V
  #582 = Methodref          #578.#581     // javax/net/ssl/HttpsURLConnection.setSSLSocketFactory:(Ljavax/net/ssl/SSLSocketFactory;)V
  #583 = Utf8               setDoOutput
  #584 = NameAndType        #583:#406     // setDoOutput:(Z)V
  #585 = Methodref          #194.#584     // java/net/HttpURLConnection.setDoOutput:(Z)V
  #586 = Utf8               ()Ljava/util/Map;
  #587 = NameAndType        #276:#586     // cookies:()Ljava/util/Map;
  #588 = InterfaceMethodref #16.#587      // coursier/util/shaded/org/jsoup/Connection$Request.cookies:()Ljava/util/Map;
  #589 = InterfaceMethodref #28.#173      // java/util/Map.size:()I
  #590 = Utf8               Cookie
  #591 = String             #590          // Cookie
  #592 = Utf8               getRequestCookieString
  #593 = NameAndType        #592:#180     // getRequestCookieString:(Lcoursier/util/shaded/org/jsoup/Connection$Request;)Ljava/lang/String;
  #594 = Methodref          #2.#593       // coursier/util/shaded/org/jsoup/helper/HttpConnection$Response.getRequestCookieString:(Lcoursier/util/shaded/org/jsoup/Connection$Request;)Ljava/lang/String;
  #595 = Utf8               addRequestProperty
  #596 = Utf8               (Ljava/lang/String;Ljava/lang/String;)V
  #597 = NameAndType        #595:#596     // addRequestProperty:(Ljava/lang/String;Ljava/lang/String;)V
  #598 = Methodref          #194.#597     // java/net/HttpURLConnection.addRequestProperty:(Ljava/lang/String;Ljava/lang/String;)V
  #599 = Utf8               multiHeaders
  #600 = NameAndType        #599:#586     // multiHeaders:()Ljava/util/Map;
  #601 = InterfaceMethodref #16.#600      // coursier/util/shaded/org/jsoup/Connection$Request.multiHeaders:()Ljava/util/Map;
  #602 = Utf8               java/util/List
  #603 = Class              #602          // java/util/List
  #604 = InterfaceMethodref #603.#288     // java/util/List.iterator:()Ljava/util/Iterator;
  #605 = Utf8               value
  #606 = Utf8               Ljava/util/Map$Entry<Ljava/lang/String;Ljava/util/List<Ljava/lang/String;>;>;
  #607 = Utf8               close
  #608 = NameAndType        #607:#66      // close:()V
  #609 = Methodref          #386.#608     // java/io/InputStream.close:()V
  #610 = NameAndType        #53:#54       // conn:Ljava/net/HttpURLConnection;
  #611 = Fieldref           #2.#610       // coursier/util/shaded/org/jsoup/helper/HttpConnection$Response.conn:Ljava/net/HttpURLConnection;
  #612 = Utf8               disconnect
  #613 = NameAndType        #612:#66      // disconnect:()V
  #614 = Methodref          #194.#613     // java/net/HttpURLConnection.disconnect:()V
  #615 = Utf8               getRequestMethod
  #616 = NameAndType        #615:#118     // getRequestMethod:()Ljava/lang/String;
  #617 = Methodref          #194.#616     // java/net/HttpURLConnection.getRequestMethod:()Ljava/lang/String;
  #618 = Utf8               valueOf
  #619 = Utf8               (Ljava/lang/String;)Lcoursier/util/shaded/org/jsoup/Connection$Method;
  #620 = NameAndType        #618:#619     // valueOf:(Ljava/lang/String;)Lcoursier/util/shaded/org/jsoup/Connection$Method;
  #621 = Methodref          #21.#620      // coursier/util/shaded/org/jsoup/Connection$Method.valueOf:(Ljava/lang/String;)Lcoursier/util/shaded/org/jsoup/Connection$Method;
  #622 = NameAndType        #134:#228     // method:Lcoursier/util/shaded/org/jsoup/Connection$Method;
  #623 = Fieldref           #2.#622       // coursier/util/shaded/org/jsoup/helper/HttpConnection$Response.method:Lcoursier/util/shaded/org/jsoup/Connection$Method;
  #624 = Utf8               getURL
  #625 = NameAndType        #624:#86      // getURL:()Ljava/net/URL;
  #626 = Methodref          #194.#625     // java/net/HttpURLConnection.getURL:()Ljava/net/URL;
  #627 = Utf8               getResponseMessage
  #628 = NameAndType        #627:#118     // getResponseMessage:()Ljava/lang/String;
  #629 = Methodref          #194.#628     // java/net/HttpURLConnection.getResponseMessage:()Ljava/lang/String;
  #630 = Utf8               getContentType
  #631 = NameAndType        #630:#118     // getContentType:()Ljava/lang/String;
  #632 = Methodref          #194.#631     // java/net/HttpURLConnection.getContentType:()Ljava/lang/String;
  #633 = Utf8               createHeaderMap
  #634 = Utf8               (Ljava/net/HttpURLConnection;)Ljava/util/LinkedHashMap;
  #635 = NameAndType        #633:#634     // createHeaderMap:(Ljava/net/HttpURLConnection;)Ljava/util/LinkedHashMap;
  #636 = Methodref          #2.#635       // coursier/util/shaded/org/jsoup/helper/HttpConnection$Response.createHeaderMap:(Ljava/net/HttpURLConnection;)Ljava/util/LinkedHashMap;
  #637 = Utf8               processResponseHeaders
  #638 = Utf8               (Ljava/util/Map;)V
  #639 = NameAndType        #637:#638     // processResponseHeaders:(Ljava/util/Map;)V
  #640 = Methodref          #2.#639       // coursier/util/shaded/org/jsoup/helper/HttpConnection$Response.processResponseHeaders:(Ljava/util/Map;)V
  #641 = Methodref          #2.#587       // coursier/util/shaded/org/jsoup/helper/HttpConnection$Response.cookies:()Ljava/util/Map;
  #642 = Utf8               hasCookie
  #643 = NameAndType        #642:#221     // hasCookie:(Ljava/lang/String;)Z
  #644 = Methodref          #2.#643       // coursier/util/shaded/org/jsoup/helper/HttpConnection$Response.hasCookie:(Ljava/lang/String;)Z
  #645 = Methodref          #2.#307       // coursier/util/shaded/org/jsoup/helper/HttpConnection$Response.cookie:(Ljava/lang/String;Ljava/lang/String;)Lcoursier/util/shaded/org/jsoup/Connection$Base;
  #646 = Utf8               prevCookie
  #647 = Utf8               resHeaders
  #648 = Utf8               Ljava/util/Map<Ljava/lang/String;Ljava/util/List<Ljava/lang/String;>;>;
  #649 = Utf8               (Ljava/net/HttpURLConnection;)Ljava/util/LinkedHashMap<Ljava/lang/String;Ljava/util/List<Ljava/lang/String;>;>;
  #650 = Utf8               java/util/LinkedHashMap
  #651 = Class              #650          // java/util/LinkedHashMap
  #652 = Methodref          #651.#147     // java/util/LinkedHashMap."<init>":()V
  #653 = Utf8               getHeaderFieldKey
  #654 = NameAndType        #653:#260     // getHeaderFieldKey:(I)Ljava/lang/String;
  #655 = Methodref          #194.#654     // java/net/HttpURLConnection.getHeaderFieldKey:(I)Ljava/lang/String;
  #656 = Utf8               getHeaderField
  #657 = NameAndType        #656:#260     // getHeaderField:(I)Ljava/lang/String;
  #658 = Methodref          #194.#657     // java/net/HttpURLConnection.getHeaderField:(I)Ljava/lang/String;
  #659 = Utf8               containsKey
  #660 = NameAndType        #659:#124     // containsKey:(Ljava/lang/Object;)Z
  #661 = Methodref          #651.#660     // java/util/LinkedHashMap.containsKey:(Ljava/lang/Object;)Z
  #662 = Utf8               get
  #663 = Utf8               (Ljava/lang/Object;)Ljava/lang/Object;
  #664 = NameAndType        #662:#663     // get:(Ljava/lang/Object;)Ljava/lang/Object;
  #665 = Methodref          #651.#664     // java/util/LinkedHashMap.get:(Ljava/lang/Object;)Ljava/lang/Object;
  #666 = Utf8               add
  #667 = NameAndType        #666:#124     // add:(Ljava/lang/Object;)Z
  #668 = InterfaceMethodref #603.#667     // java/util/List.add:(Ljava/lang/Object;)Z
  #669 = Utf8               java/util/ArrayList
  #670 = Class              #669          // java/util/ArrayList
  #671 = Methodref          #670.#147     // java/util/ArrayList."<init>":()V
  #672 = Methodref          #670.#667     // java/util/ArrayList.add:(Ljava/lang/Object;)Z
  #673 = Utf8               put
  #674 = Utf8               (Ljava/lang/Object;Ljava/lang/Object;)Ljava/lang/Object;
  #675 = NameAndType        #673:#674     // put:(Ljava/lang/Object;Ljava/lang/Object;)Ljava/lang/Object;
  #676 = Methodref          #651.#675     // java/util/LinkedHashMap.put:(Ljava/lang/Object;Ljava/lang/Object;)Ljava/lang/Object;
  #677 = Utf8               vals
  #678 = Utf8               Ljava/util/ArrayList<Ljava/lang/String;>;
  #679 = Utf8               Ljava/util/ArrayList;
  #680 = Utf8               key
  #681 = Utf8               val
  #682 = Utf8               headers
  #683 = Utf8               Ljava/util/LinkedHashMap<Ljava/lang/String;Ljava/util/List<Ljava/lang/String;>;>;
  #684 = Utf8               Ljava/util/LinkedHashMap;
  #685 = Utf8               i
  #686 = Utf8               (Ljava/util/Map<Ljava/lang/String;Ljava/util/List<Ljava/lang/String;>;>;)V
  #687 = Utf8               Set-Cookie
  #688 = String             #687          // Set-Cookie
  #689 = Utf8               equalsIgnoreCase
  #690 = NameAndType        #689:#221     // equalsIgnoreCase:(Ljava/lang/String;)Z
  #691 = Methodref          #90.#690      // java/lang/String.equalsIgnoreCase:(Ljava/lang/String;)Z
  #692 = Utf8               coursier/util/shaded/org/jsoup/parser/TokenQueue
  #693 = Class              #692          // coursier/util/shaded/org/jsoup/parser/TokenQueue
  #694 = Methodref          #693.#96      // coursier/util/shaded/org/jsoup/parser/TokenQueue."<init>":(Ljava/lang/String;)V
  #695 = Utf8               =
  #696 = String             #695          // =
  #697 = Utf8               chompTo
  #698 = NameAndType        #697:#247     // chompTo:(Ljava/lang/String;)Ljava/lang/String;
  #699 = Methodref          #693.#698     // coursier/util/shaded/org/jsoup/parser/TokenQueue.chompTo:(Ljava/lang/String;)Ljava/lang/String;
  #700 = Utf8               trim
  #701 = NameAndType        #700:#118     // trim:()Ljava/lang/String;
  #702 = Methodref          #90.#701      // java/lang/String.trim:()Ljava/lang/String;
  #703 = Utf8               ;
  #704 = String             #703          // ;
  #705 = Utf8               consumeTo
  #706 = NameAndType        #705:#247     // consumeTo:(Ljava/lang/String;)Ljava/lang/String;
  #707 = Methodref          #693.#706     // coursier/util/shaded/org/jsoup/parser/TokenQueue.consumeTo:(Ljava/lang/String;)Ljava/lang/String;
  #708 = Utf8               length
  #709 = NameAndType        #708:#172     // length:()I
  #710 = Methodref          #90.#709      // java/lang/String.length:()I
  #711 = Utf8               addHeader
  #712 = NameAndType        #711:#306     // addHeader:(Ljava/lang/String;Ljava/lang/String;)Lcoursier/util/shaded/org/jsoup/Connection$Base;
  #713 = Methodref          #2.#712       // coursier/util/shaded/org/jsoup/helper/HttpConnection$Response.addHeader:(Ljava/lang/String;Ljava/lang/String;)Lcoursier/util/shaded/org/jsoup/Connection$Base;
  #714 = Utf8               cd
  #715 = Utf8               Lcoursier/util/shaded/org/jsoup/parser/TokenQueue;
  #716 = Utf8               cookieName
  #717 = Utf8               cookieVal
  #718 = Utf8               values
  #719 = Utf8               Ljava/util/List<Ljava/lang/String;>;
  #720 = Utf8               Ljava/util/List;
  #721 = Utf8               entry
  #722 = InterfaceMethodref #16.#222      // coursier/util/shaded/org/jsoup/Connection$Request.hasHeader:(Ljava/lang/String;)Z
  #723 = InterfaceMethodref #16.#248      // coursier/util/shaded/org/jsoup/Connection$Request.header:(Ljava/lang/String;)Ljava/lang/String;
  #724 = Utf8               multipart/form-data
  #725 = String             #724          // multipart/form-data
  #726 = Utf8               contains
  #727 = Utf8               (Ljava/lang/CharSequence;)Z
  #728 = NameAndType        #726:#727     // contains:(Ljava/lang/CharSequence;)Z
  #729 = Methodref          #90.#728      // java/lang/String.contains:(Ljava/lang/CharSequence;)Z
  #730 = Utf8               boundary
  #731 = String             #730          // boundary
  #732 = NameAndType        #448:#118     // mimeBoundary:()Ljava/lang/String;
  #733 = Methodref          #364.#732     // coursier/util/shaded/org/jsoup/helper/DataUtil.mimeBoundary:()Ljava/lang/String;
  #734 = Utf8               multipart/form-data; boundary=
  #735 = String             #734          // multipart/form-data; boundary=
  #736 = NameAndType        #246:#306     // header:(Ljava/lang/String;Ljava/lang/String;)Lcoursier/util/shaded/org/jsoup/Connection$Base;
  #737 = InterfaceMethodref #16.#736      // coursier/util/shaded/org/jsoup/Connection$Request.header:(Ljava/lang/String;Ljava/lang/String;)Lcoursier/util/shaded/org/jsoup/Connection$Base;
  #738 = Utf8               access$200
  #739 = Utf8               (Lcoursier/util/shaded/org/jsoup/Connection$Request;)Z
  #740 = NameAndType        #738:#739     // access$200:(Lcoursier/util/shaded/org/jsoup/Connection$Request;)Z
  #741 = Methodref          #10.#740      // coursier/util/shaded/org/jsoup/helper/HttpConnection.access$200:(Lcoursier/util/shaded/org/jsoup/Connection$Request;)Z
  #742 = Utf8               application/x-www-form-urlencoded; charset=
  #743 = String             #742          // application/x-www-form-urlencoded; charset=
  #744 = Utf8               postDataCharset
  #745 = NameAndType        #744:#118     // postDataCharset:()Ljava/lang/String;
  #746 = InterfaceMethodref #16.#745      // coursier/util/shaded/org/jsoup/Connection$Request.postDataCharset:()Ljava/lang/String;
  #747 = Utf8               bound
  #748 = Utf8               java/io/BufferedWriter
  #749 = Class              #748          // java/io/BufferedWriter
  #750 = Utf8               java/io/OutputStreamWriter
  #751 = Class              #750          // java/io/OutputStreamWriter
  #752 = Utf8               (Ljava/io/OutputStream;Ljava/lang/String;)V
  #753 = NameAndType        #65:#752      // "<init>":(Ljava/io/OutputStream;Ljava/lang/String;)V
  #754 = Methodref          #751.#753     // java/io/OutputStreamWriter."<init>":(Ljava/io/OutputStream;Ljava/lang/String;)V
  #755 = Utf8               (Ljava/io/Writer;)V
  #756 = NameAndType        #65:#755      // "<init>":(Ljava/io/Writer;)V
  #757 = Methodref          #749.#756     // java/io/BufferedWriter."<init>":(Ljava/io/Writer;)V
  #758 = InterfaceMethodref #170.#288     // java/util/Collection.iterator:()Ljava/util/Iterator;
  #759 = Utf8               --
  #760 = String             #759          // --
  #761 = Utf8               write
  #762 = NameAndType        #761:#95      // write:(Ljava/lang/String;)V
  #763 = Methodref          #749.#762     // java/io/BufferedWriter.write:(Ljava/lang/String;)V
  #764 = Utf8               \r\n
  #765 = String             #764          // \r\n
  #766 = Utf8               Content-Disposition: form-data; name=\"
  #767 = String             #766          // Content-Disposition: form-data; name=\"
  #768 = NameAndType        #680:#118     // key:()Ljava/lang/String;
  #769 = InterfaceMethodref #38.#768      // coursier/util/shaded/org/jsoup/Connection$KeyVal.key:()Ljava/lang/String;
  #770 = Utf8               access$300
  #771 = NameAndType        #770:#247     // access$300:(Ljava/lang/String;)Ljava/lang/String;
  #772 = Methodref          #10.#771      // coursier/util/shaded/org/jsoup/helper/HttpConnection.access$300:(Ljava/lang/String;)Ljava/lang/String;
  #773 = Utf8               \"
  #774 = String             #773          // \"
  #775 = Utf8               hasInputStream
  #776 = NameAndType        #775:#139     // hasInputStream:()Z
  #777 = InterfaceMethodref #38.#776      // coursier/util/shaded/org/jsoup/Connection$KeyVal.hasInputStream:()Z
  #778 = Utf8               ; filename=\"
  #779 = String             #778          // ; filename=\"
  #780 = NameAndType        #605:#118     // value:()Ljava/lang/String;
  #781 = InterfaceMethodref #38.#780      // coursier/util/shaded/org/jsoup/Connection$KeyVal.value:()Ljava/lang/String;
  #782 = Utf8               \"\r\nContent-Type:
  #783 = String             #782          // \"\r\nContent-Type:
  #784 = InterfaceMethodref #38.#320      // coursier/util/shaded/org/jsoup/Connection$KeyVal.contentType:()Ljava/lang/String;
  #785 = Utf8               java/io/OutputStream
  #786 = Class              #785          // java/io/OutputStream
  #787 = Utf8               application/octet-stream
  #788 = String             #787          // application/octet-stream
  #789 = Utf8               \r\n\r\n
  #790 = String             #789          // \r\n\r\n
  #791 = Utf8               flush
  #792 = NameAndType        #791:#66      // flush:()V
  #793 = Methodref          #749.#792     // java/io/BufferedWriter.flush:()V
  #794 = Utf8               inputStream
  #795 = NameAndType        #794:#379     // inputStream:()Ljava/io/InputStream;
  #796 = InterfaceMethodref #38.#795      // coursier/util/shaded/org/jsoup/Connection$KeyVal.inputStream:()Ljava/io/InputStream;
  #797 = Utf8               crossStreams
  #798 = Utf8               (Ljava/io/InputStream;Ljava/io/OutputStream;)V
  #799 = NameAndType        #797:#798     // crossStreams:(Ljava/io/InputStream;Ljava/io/OutputStream;)V
  #800 = Methodref          #364.#799     // coursier/util/shaded/org/jsoup/helper/DataUtil.crossStreams:(Ljava/io/InputStream;Ljava/io/OutputStream;)V
  #801 = Methodref          #786.#792     // java/io/OutputStream.flush:()V
  #802 = Utf8               (C)Ljava/io/Writer;
  #803 = NameAndType        #151:#802     // append:(C)Ljava/io/Writer;
  #804 = Methodref          #749.#803     // java/io/BufferedWriter.append:(C)Ljava/io/Writer;
  #805 = Utf8               java/net/URLEncoder
  #806 = Class              #805          // java/net/URLEncoder
  #807 = Utf8               encode
  #808 = Utf8               (Ljava/lang/String;Ljava/lang/String;)Ljava/lang/String;
  #809 = NameAndType        #807:#808     // encode:(Ljava/lang/String;Ljava/lang/String;)Ljava/lang/String;
  #810 = Methodref          #806.#809     // java/net/URLEncoder.encode:(Ljava/lang/String;Ljava/lang/String;)Ljava/lang/String;
  #811 = NameAndType        #761:#567     // write:(I)V
  #812 = Methodref          #749.#811     // java/io/BufferedWriter.write:(I)V
  #813 = Methodref          #749.#608     // java/io/BufferedWriter.close:()V
  #814 = Utf8               keyVal
  #815 = Utf8               Lcoursier/util/shaded/org/jsoup/Connection$KeyVal;
  #816 = Utf8               first
  #817 = Utf8               outputStream
  #818 = Utf8               Ljava/io/OutputStream;
  #819 = Utf8               Ljava/util/Collection<Lcoursier/util/shaded/org/jsoup/Connection$KeyVal;>;
  #820 = Utf8               Ljava/util/Collection;
  #821 = Utf8               w
  #822 = Utf8               Ljava/io/BufferedWriter;
  #823 = Utf8               borrowBuilder
  #824 = Utf8               ()Ljava/lang/StringBuilder;
  #825 = NameAndType        #823:#824     // borrowBuilder:()Ljava/lang/StringBuilder;
  #826 = Methodref          #264.#825     // coursier/util/shaded/org/jsoup/internal/StringUtil.borrowBuilder:()Ljava/lang/StringBuilder;
  #827 = Utf8               ;
  #828 = String             #827          // ;
  #829 = Utf8               (C)Ljava/lang/StringBuilder;
  #830 = NameAndType        #151:#829     // append:(C)Ljava/lang/StringBuilder;
  #831 = Methodref          #146.#830     // java/lang/StringBuilder.append:(C)Ljava/lang/StringBuilder;
  #832 = Utf8               releaseBuilder
  #833 = Utf8               (Ljava/lang/StringBuilder;)Ljava/lang/String;
  #834 = NameAndType        #832:#833     // releaseBuilder:(Ljava/lang/StringBuilder;)Ljava/lang/String;
  #835 = Methodref          #264.#834     // coursier/util/shaded/org/jsoup/internal/StringUtil.releaseBuilder:(Ljava/lang/StringBuilder;)Ljava/lang/String;
  #836 = Utf8               sb
  #837 = Utf8               Ljava/lang/StringBuilder;
  #838 = Utf8               ://
  #839 = String             #838          // ://
  #840 = Utf8               getAuthority
  #841 = NameAndType        #840:#118     // getAuthority:()Ljava/lang/String;
  #842 = Methodref          #116.#841     // java/net/URL.getAuthority:()Ljava/lang/String;
  #843 = Utf8               getPath
  #844 = NameAndType        #843:#118     // getPath:()Ljava/lang/String;
  #845 = Methodref          #116.#844     // java/net/URL.getPath:()Ljava/lang/String;
  #846 = Utf8               ?
  #847 = String             #846          // ?
  #848 = Utf8               getQuery
  #849 = NameAndType        #848:#118     // getQuery:()Ljava/lang/String;
  #850 = Methodref          #116.#849     // java/net/URL.getQuery:()Ljava/lang/String;
  #851 = Utf8               InputStream data not supported in URL query string.
  #852 = String             #851          // InputStream data not supported in URL query string.
  #853 = Methodref          #116.#96      // java/net/URL."<init>":(Ljava/lang/String;)V
  #854 = Utf8               in
  #855 = Methodref          #5.#587       // coursier/util/shaded/org/jsoup/helper/HttpConnection$Base.cookies:()Ljava/util/Map;
  #856 = Utf8               removeCookie
  #857 = NameAndType        #856:#243     // removeCookie:(Ljava/lang/String;)Lcoursier/util/shaded/org/jsoup/Connection$Base;
  #858 = Methodref          #5.#857       // coursier/util/shaded/org/jsoup/helper/HttpConnection$Base.removeCookie:(Ljava/lang/String;)Lcoursier/util/shaded/org/jsoup/Connection$Base;
  #859 = Methodref          #5.#643       // coursier/util/shaded/org/jsoup/helper/HttpConnection$Base.hasCookie:(Ljava/lang/String;)Z
  #860 = Methodref          #5.#307       // coursier/util/shaded/org/jsoup/helper/HttpConnection$Base.cookie:(Ljava/lang/String;Ljava/lang/String;)Lcoursier/util/shaded/org/jsoup/Connection$Base;
  #861 = NameAndType        #305:#247     // cookie:(Ljava/lang/String;)Ljava/lang/String;
  #862 = Methodref          #5.#861       // coursier/util/shaded/org/jsoup/helper/HttpConnection$Base.cookie:(Ljava/lang/String;)Ljava/lang/String;
  #863 = Methodref          #5.#600       // coursier/util/shaded/org/jsoup/helper/HttpConnection$Base.multiHeaders:()Ljava/util/Map;
  #864 = NameAndType        #682:#586     // headers:()Ljava/util/Map;
  #865 = Methodref          #5.#864       // coursier/util/shaded/org/jsoup/helper/HttpConnection$Base.headers:()Ljava/util/Map;
  #866 = Methodref          #5.#244       // coursier/util/shaded/org/jsoup/helper/HttpConnection$Base.removeHeader:(Ljava/lang/String;)Lcoursier/util/shaded/org/jsoup/Connection$Base;
  #867 = Methodref          #5.#393       // coursier/util/shaded/org/jsoup/helper/HttpConnection$Base.hasHeaderWithValue:(Ljava/lang/String;Ljava/lang/String;)Z
  #868 = Methodref          #5.#222       // coursier/util/shaded/org/jsoup/helper/HttpConnection$Base.hasHeader:(Ljava/lang/String;)Z
  #869 = Methodref          #5.#736       // coursier/util/shaded/org/jsoup/helper/HttpConnection$Base.header:(Ljava/lang/String;Ljava/lang/String;)Lcoursier/util/shaded/org/jsoup/Connection$Base;
  #870 = Utf8               (Ljava/lang/String;)Ljava/util/List;
  #871 = NameAndType        #682:#870     // headers:(Ljava/lang/String;)Ljava/util/List;
  #872 = Methodref          #5.#871       // coursier/util/shaded/org/jsoup/helper/HttpConnection$Base.headers:(Ljava/lang/String;)Ljava/util/List;
  #873 = Methodref          #5.#712       // coursier/util/shaded/org/jsoup/helper/HttpConnection$Base.addHeader:(Ljava/lang/String;Ljava/lang/String;)Lcoursier/util/shaded/org/jsoup/Connection$Base;
  #874 = Methodref          #5.#248       // coursier/util/shaded/org/jsoup/helper/HttpConnection$Base.header:(Ljava/lang/String;)Ljava/lang/String;
  #875 = Methodref          #5.#232       // coursier/util/shaded/org/jsoup/helper/HttpConnection$Base.method:(Lcoursier/util/shaded/org/jsoup/Connection$Method;)Lcoursier/util/shaded/org/jsoup/Connection$Base;
  #876 = Methodref          #5.#136       // coursier/util/shaded/org/jsoup/helper/HttpConnection$Base.method:()Lcoursier/util/shaded/org/jsoup/Connection$Method;
  #877 = Methodref          #5.#274       // coursier/util/shaded/org/jsoup/helper/HttpConnection$Base.url:(Ljava/net/URL;)Lcoursier/util/shaded/org/jsoup/Connection$Base;
  #878 = Methodref          #5.#87        // coursier/util/shaded/org/jsoup/helper/HttpConnection$Base.url:()Ljava/net/URL;
  #879 = Utf8               (Ljava/lang/String;)Lcoursier/util/shaded/org/jsoup/Connection$Response;
  #880 = NameAndType        #55:#456      // charset:(Ljava/lang/String;)Lcoursier/util/shaded/org/jsoup/helper/HttpConnection$Response;
  #881 = Methodref          #2.#880       // coursier/util/shaded/org/jsoup/helper/HttpConnection$Response.charset:(Ljava/lang/String;)Lcoursier/util/shaded/org/jsoup/helper/HttpConnection$Response;
  #882 = Utf8               <clinit>
  #883 = Utf8               (application|text)/\\w*\\+?xml.*
  #884 = String             #883          // (application|text)/\\w*\\+?xml.*
  #885 = Utf8               compile
  #886 = Utf8               (Ljava/lang/String;)Ljava/util/regex/Pattern;
  #887 = NameAndType        #885:#886     // compile:(Ljava/lang/String;)Ljava/util/regex/Pattern;
  #888 = Methodref          #330.#887     // java/util/regex/Pattern.compile:(Ljava/lang/String;)Ljava/util/regex/Pattern;
  #889 = Utf8               ConstantValue
  #890 = Utf8               Code
  #891 = Utf8               LineNumberTable
  #892 = Utf8               LocalVariableTable
  #893 = Utf8               StackMapTable
  #894 = Utf8               Exceptions
  #895 = Utf8               LocalVariableTypeTable
  #896 = Utf8               Signature
  #897 = Utf8               InnerClasses
  #898 = Utf8               SourceFile
{
  private static final int MAX_REDIRECTS;
    descriptor: I
    flags: (0x001a) ACC_PRIVATE, ACC_STATIC, ACC_FINAL
    ConstantValue: int 20

  private static final java.lang.String LOCATION;
    descriptor: Ljava/lang/String;
    flags: (0x001a) ACC_PRIVATE, ACC_STATIC, ACC_FINAL
    ConstantValue: String Location

  private int statusCode;
    descriptor: I
    flags: (0x0002) ACC_PRIVATE

  private java.lang.String statusMessage;
    descriptor: Ljava/lang/String;
    flags: (0x0002) ACC_PRIVATE

  private java.nio.ByteBuffer byteData;
    descriptor: Ljava/nio/ByteBuffer;
    flags: (0x0002) ACC_PRIVATE

  private java.io.InputStream bodyStream;
    descriptor: Ljava/io/InputStream;
    flags: (0x0002) ACC_PRIVATE

  private java.net.HttpURLConnection conn;
    descriptor: Ljava/net/HttpURLConnection;
    flags: (0x0002) ACC_PRIVATE

  private java.lang.String charset;
    descriptor: Ljava/lang/String;
    flags: (0x0002) ACC_PRIVATE

  private java.lang.String contentType;
    descriptor: Ljava/lang/String;
    flags: (0x0002) ACC_PRIVATE

  private boolean executed;
    descriptor: Z
    flags: (0x0002) ACC_PRIVATE

  private boolean inputStreamRead;
    descriptor: Z
    flags: (0x0002) ACC_PRIVATE

  private int numRedirects;
    descriptor: I
    flags: (0x0002) ACC_PRIVATE

  private coursier.util.shaded.org.jsoup.Connection$Request req;
    descriptor: Lcoursier/util/shaded/org/jsoup/Connection$Request;
    flags: (0x0002) ACC_PRIVATE

  private static final java.util.regex.Pattern xmlContentTypeRxp;
    descriptor: Ljava/util/regex/Pattern;
    flags: (0x001a) ACC_PRIVATE, ACC_STATIC, ACC_FINAL

  coursier.util.shaded.org.jsoup.helper.HttpConnection$Response();
    descriptor: ()V
    flags: (0x0000)
    Code:
      stack=2, locals=1, args_size=1
         0: aload_0
         1: aconst_null
         2: invokespecial #69                 // Method coursier/util/shaded/org/jsoup/helper/HttpConnection$Base."<init>":(Lcoursier/util/shaded/org/jsoup/helper/HttpConnection$1;)V
         5: aload_0
         6: iconst_0
         7: putfield      #71                 // Field executed:Z
        10: aload_0
        11: iconst_0
        12: putfield      #73                 // Field inputStreamRead:Z
        15: aload_0
        16: iconst_0
        17: putfield      #75                 // Field numRedirects:I
        20: return
      LineNumberTable:
        line 694: 0
        line 683: 5
        line 684: 10
        line 685: 15
        line 695: 20
      LocalVariableTable:
        Start  Length  Slot  Name   Signature
            0      21     0  this   Lcoursier/util/shaded/org/jsoup/helper/HttpConnection$Response;

  private coursier.util.shaded.org.jsoup.helper.HttpConnection$Response(coursier.util.shaded.org.jsoup.helper.HttpConnection$Response) throws java.io.IOException;
    descriptor: (Lcoursier/util/shaded/org/jsoup/helper/HttpConnection$Response;)V
    flags: (0x0002) ACC_PRIVATE
    Code:
      stack=7, locals=2, args_size=2
         0: aload_0
         1: aconst_null
         2: invokespecial #69                 // Method coursier/util/shaded/org/jsoup/helper/HttpConnection$Base."<init>":(Lcoursier/util/shaded/org/jsoup/helper/HttpConnection$1;)V
         5: aload_0
         6: iconst_0
         7: putfield      #71                 // Field executed:Z
        10: aload_0
        11: iconst_0
        12: putfield      #73                 // Field inputStreamRead:Z
        15: aload_0
        16: iconst_0
        17: putfield      #75                 // Field numRedirects:I
        20: aload_1
        21: ifnull        67
        24: aload_0
        25: aload_1
        26: getfield      #75                 // Field numRedirects:I
        29: iconst_1
        30: iadd
        31: putfield      #75                 // Field numRedirects:I
        34: aload_0
        35: getfield      #75                 // Field numRedirects:I
        38: bipush        20
        40: if_icmplt     67
        43: new           #80                 // class java/io/IOException
        46: dup
        47: ldc           #82                 // String Too many redirects occurred trying to load URL %s
        49: iconst_1
        50: anewarray     #84                 // class java/lang/Object
        53: dup
        54: iconst_0
        55: aload_1
        56: invokevirtual #88                 // Method url:()Ljava/net/URL;
        59: aastore
        60: invokestatic  #94                 // Method java/lang/String.format:(Ljava/lang/String;[Ljava/lang/Object;)Ljava/lang/String;
        63: invokespecial #97                 // Method java/io/IOException."<init>":(Ljava/lang/String;)V
        66: athrow
        67: return
      StackMapTable: number_of_entries = 1
        frame_type = 255 /* full_frame */
          offset_delta = 67
          locals = [ class coursier/util/shaded/org/jsoup/helper/HttpConnection$Response, class coursier/util/shaded/org/jsoup/helper/HttpConnection$Response ]
          stack = []
      LineNumberTable:
        line 698: 0
        line 683: 5
        line 684: 10
        line 685: 15
        line 699: 20
        line 700: 24
        line 701: 34
        line 702: 43
        line 704: 67
      LocalVariableTable:
        Start  Length  Slot  Name   Signature
            0      68     0  this   Lcoursier/util/shaded/org/jsoup/helper/HttpConnection$Response;
            0      68     1 previousResponse   Lcoursier/util/shaded/org/jsoup/helper/HttpConnection$Response;
    Exceptions:
      throws java.io.IOException

  static coursier.util.shaded.org.jsoup.helper.HttpConnection$Response execute(coursier.util.shaded.org.jsoup.Connection$Request) throws java.io.IOException;
    descriptor: (Lcoursier/util/shaded/org/jsoup/Connection$Request;)Lcoursier/util/shaded/org/jsoup/helper/HttpConnection$Response;
    flags: (0x0008) ACC_STATIC
    Code:
      stack=2, locals=1, args_size=1
         0: aload_0
         1: aconst_null
         2: invokestatic  #103                // Method execute:(Lcoursier/util/shaded/org/jsoup/Connection$Request;Lcoursier/util/shaded/org/jsoup/helper/HttpConnection$Response;)Lcoursier/util/shaded/org/jsoup/helper/HttpConnection$Response;
         5: areturn
      LineNumberTable:
        line 707: 0
      LocalVariableTable:
        Start  Length  Slot  Name   Signature
            0       6     0   req   Lcoursier/util/shaded/org/jsoup/Connection$Request;
    Exceptions:
      throws java.io.IOException

  static coursier.util.shaded.org.jsoup.helper.HttpConnection$Response execute(coursier.util.shaded.org.jsoup.Connection$Request, coursier.util.shaded.org.jsoup.helper.HttpConnection$Response) throws java.io.IOException;
    descriptor: (Lcoursier/util/shaded/org/jsoup/Connection$Request;Lcoursier/util/shaded/org/jsoup/helper/HttpConnection$Response;)Lcoursier/util/shaded/org/jsoup/helper/HttpConnection$Response;
    flags: (0x0008) ACC_STATIC
    Code:
      stack=7, locals=15, args_size=2
         0: aload_0
         1: ldc           #105                // String Request must not be null
         3: invokestatic  #111                // Method coursier/util/shaded/org/jsoup/helper/Validate.notNull:(Ljava/lang/Object;Ljava/lang/String;)V
         6: aload_0
         7: invokeinterface #112,  1          // InterfaceMethod coursier/util/shaded/org/jsoup/Connection$Request.url:()Ljava/net/URL;
        12: ldc           #114                // String URL must be specified to connect
        14: invokestatic  #111                // Method coursier/util/shaded/org/jsoup/helper/Validate.notNull:(Ljava/lang/Object;Ljava/lang/String;)V
        17: aload_0
        18: invokeinterface #112,  1          // InterfaceMethod coursier/util/shaded/org/jsoup/Connection$Request.url:()Ljava/net/URL;
        23: invokevirtual #120                // Method java/net/URL.getProtocol:()Ljava/lang/String;
        26: astore_2
        27: aload_2
        28: ldc           #122                // String http
        30: invokevirtual #126                // Method java/lang/String.equals:(Ljava/lang/Object;)Z
        33: ifne          55
        36: aload_2
        37: ldc           #128                // String https
        39: invokevirtual #126                // Method java/lang/String.equals:(Ljava/lang/Object;)Z
        42: ifne          55
        45: new           #130                // class java/net/MalformedURLException
        48: dup
        49: ldc           #132                // String Only http & https protocols supported
        51: invokespecial #133                // Method java/net/MalformedURLException."<init>":(Ljava/lang/String;)V
        54: athrow
        55: aload_0
        56: invokeinterface #137,  1          // InterfaceMethod coursier/util/shaded/org/jsoup/Connection$Request.method:()Lcoursier/util/shaded/org/jsoup/Connection$Method;
        61: invokevirtual #141                // Method coursier/util/shaded/org/jsoup/Connection$Method.hasBody:()Z
        64: istore_3
        65: aload_0
        66: invokeinterface #144,  1          // InterfaceMethod coursier/util/shaded/org/jsoup/Connection$Request.requestBody:()Ljava/lang/String;
        71: ifnull        78
        74: iconst_1
        75: goto          79
        78: iconst_0
        79: istore        4
        81: iload_3
        82: ifne          114
        85: iload         4
        87: new           #146                // class java/lang/StringBuilder
        90: dup
        91: invokespecial #148                // Method java/lang/StringBuilder."<init>":()V
        94: ldc           #150                // String Cannot set a request body for HTTP method
        96: invokevirtual #154                // Method java/lang/StringBuilder.append:(Ljava/lang/String;)Ljava/lang/StringBuilder;
        99: aload_0
       100: invokeinterface #137,  1          // InterfaceMethod coursier/util/shaded/org/jsoup/Connection$Request.method:()Lcoursier/util/shaded/org/jsoup/Connection$Method;
       105: invokevirtual #157                // Method java/lang/StringBuilder.append:(Ljava/lang/Object;)Ljava/lang/StringBuilder;
       108: invokevirtual #160                // Method java/lang/StringBuilder.toString:()Ljava/lang/String;
       111: invokestatic  #164                // Method coursier/util/shaded/org/jsoup/helper/Validate.isFalse:(ZLjava/lang/String;)V
       114: aconst_null
       115: astore        5
       117: aload_0
       118: invokeinterface #168,  1          // InterfaceMethod coursier/util/shaded/org/jsoup/Connection$Request.data:()Ljava/util/Collection;
       123: invokeinterface #174,  1          // InterfaceMethod java/util/Collection.size:()I
       128: ifle          147
       131: iload_3
       132: ifeq          140
       135: iload         4
       137: ifeq          147
       140: aload_0
       141: invokestatic  #178                // Method serialiseRequestUrl:(Lcoursier/util/shaded/org/jsoup/Connection$Request;)V
       144: goto          157
       147: iload_3
       148: ifeq          157
       151: aload_0
       152: invokestatic  #182                // Method setOutputContentType:(Lcoursier/util/shaded/org/jsoup/Connection$Request;)Ljava/lang/String;
       155: astore        5
       157: invokestatic  #188                // Method java/lang/System.nanoTime:()J
       160: lstore        6
       162: aload_0
       163: invokestatic  #192                // Method createConnection:(Lcoursier/util/shaded/org/jsoup/Connection$Request;)Ljava/net/HttpURLConnection;
       166: astore        8
       168: aconst_null
       169: astore        9
       171: aload         8
       173: invokevirtual #197                // Method java/net/HttpURLConnection.connect:()V
       176: aload         8
       178: invokevirtual #200                // Method java/net/HttpURLConnection.getDoOutput:()Z
       181: ifeq          195
       184: aload_0
       185: aload         8
       187: invokevirtual #204                // Method java/net/HttpURLConnection.getOutputStream:()Ljava/io/OutputStream;
       190: aload         5
       192: invokestatic  #208                // Method writePost:(Lcoursier/util/shaded/org/jsoup/Connection$Request;Ljava/io/OutputStream;Ljava/lang/String;)V
       195: aload         8
       197: invokevirtual #211                // Method java/net/HttpURLConnection.getResponseCode:()I
       200: istore        10
       202: new           #2                  // class coursier/util/shaded/org/jsoup/helper/HttpConnection$Response
       205: dup
       206: aload_1
       207: invokespecial #213                // Method "<init>":(Lcoursier/util/shaded/org/jsoup/helper/HttpConnection$Response;)V
       210: astore        9
       212: aload         9
       214: aload         8
       216: aload_1
       217: invokespecial #217                // Method setupFromConnection:(Ljava/net/HttpURLConnection;Lcoursier/util/shaded/org/jsoup/helper/HttpConnection$Response;)V
       220: aload         9
       222: aload_0
       223: putfield      #219                // Field req:Lcoursier/util/shaded/org/jsoup/Connection$Request;
       226: aload         9
       228: ldc           #46                 // String Location
       230: invokevirtual #223                // Method hasHeader:(Ljava/lang/String;)Z
       233: ifeq          432
       236: aload_0
       237: invokeinterface #226,  1          // InterfaceMethod coursier/util/shaded/org/jsoup/Connection$Request.followRedirects:()Z
       242: ifeq          432
       245: iload         10
       247: sipush        307
       250: if_icmpeq     291
       253: aload_0
       254: getstatic     #230                // Field coursier/util/shaded/org/jsoup/Connection$Method.GET:Lcoursier/util/shaded/org/jsoup/Connection$Method;
       257: invokeinterface #233,  2          // InterfaceMethod coursier/util/shaded/org/jsoup/Connection$Request.method:(Lcoursier/util/shaded/org/jsoup/Connection$Method;)Lcoursier/util/shaded/org/jsoup/Connection$Base;
       262: pop
       263: aload_0
       264: invokeinterface #168,  1          // InterfaceMethod coursier/util/shaded/org/jsoup/Connection$Request.data:()Ljava/util/Collection;
       269: invokeinterface #236,  1          // InterfaceMethod java/util/Collection.clear:()V
       274: aload_0
       275: aconst_null
       276: invokeinterface #239,  2          // InterfaceMethod coursier/util/shaded/org/jsoup/Connection$Request.requestBody:(Ljava/lang/String;)Lcoursier/util/shaded/org/jsoup/Connection$Request;
       281: pop
       282: aload_0
       283: ldc           #241                // String Content-Type
       285: invokeinterface #245,  2          // InterfaceMethod coursier/util/shaded/org/jsoup/Connection$Request.removeHeader:(Ljava/lang/String;)Lcoursier/util/shaded/org/jsoup/Connection$Base;
       290: pop
       291: aload         9
       293: ldc           #46                 // String Location
       295: invokevirtual #249                // Method header:(Ljava/lang/String;)Ljava/lang/String;
       298: astore        11
       300: aload         11
       302: ldc           #251                // String http:/
       304: invokevirtual #254                // Method java/lang/String.startsWith:(Ljava/lang/String;)Z
       307: ifeq          331
       310: aload         11
       312: bipush        6
       314: invokevirtual #258                // Method java/lang/String.charAt:(I)C
       317: bipush        47
       319: if_icmpeq     331
       322: aload         11
       324: bipush        6
       326: invokevirtual #262                // Method java/lang/String.substring:(I)Ljava/lang/String;
       329: astore        11
       331: aload_0
       332: invokeinterface #112,  1          // InterfaceMethod coursier/util/shaded/org/jsoup/Connection$Request.url:()Ljava/net/URL;
       337: aload         11
       339: invokestatic  #268                // Method coursier/util/shaded/org/jsoup/internal/StringUtil.resolve:(Ljava/net/URL;Ljava/lang/String;)Ljava/net/URL;
       342: astore        12
       344: aload_0
       345: aload         12
       347: invokestatic  #272                // Method coursier/util/shaded/org/jsoup/helper/HttpConnection.encodeUrl:(Ljava/net/URL;)Ljava/net/URL;
       350: invokeinterface #275,  2          // InterfaceMethod coursier/util/shaded/org/jsoup/Connection$Request.url:(Ljava/net/URL;)Lcoursier/util/shaded/org/jsoup/Connection$Base;
       355: pop
       356: aload         9
       358: getfield      #279                // Field cookies:Ljava/util/Map;
       361: invokeinterface #283,  1          // InterfaceMethod java/util/Map.entrySet:()Ljava/util/Set;
       366: invokeinterface #289,  1          // InterfaceMethod java/util/Set.iterator:()Ljava/util/Iterator;
       371: astore        13
       373: aload         13
       375: invokeinterface #294,  1          // InterfaceMethod java/util/Iterator.hasNext:()Z
       380: ifeq          425
       383: aload         13
       385: invokeinterface #298,  1          // InterfaceMethod java/util/Iterator.next:()Ljava/lang/Object;
       390: checkcast     #26                 // class java/util/Map$Entry
       393: astore        14
       395: aload_0
       396: aload         14
       398: invokeinterface #301,  1          // InterfaceMethod java/util/Map$Entry.getKey:()Ljava/lang/Object;
       403: checkcast     #90                 // class java/lang/String
       406: aload         14
       408: invokeinterface #304,  1          // InterfaceMethod java/util/Map$Entry.getValue:()Ljava/lang/Object;
       413: checkcast     #90                 // class java/lang/String
       416: invokeinterface #308,  3          // InterfaceMethod coursier/util/shaded/org/jsoup/Connection$Request.cookie:(Ljava/lang/String;Ljava/lang/String;)Lcoursier/util/shaded/org/jsoup/Connection$Base;
       421: pop
       422: goto          373
       425: aload_0
       426: aload         9
       428: invokestatic  #103                // Method execute:(Lcoursier/util/shaded/org/jsoup/Connection$Request;Lcoursier/util/shaded/org/jsoup/helper/HttpConnection$Response;)Lcoursier/util/shaded/org/jsoup/helper/HttpConnection$Response;
       431: areturn
       432: iload         10
       434: sipush        200
       437: if_icmplt     448
       440: iload         10
       442: sipush        400
       445: if_icmplt     479
       448: aload_0
       449: invokeinterface #311,  1          // InterfaceMethod coursier/util/shaded/org/jsoup/Connection$Request.ignoreHttpErrors:()Z
       454: ifne          479
       457: new           #313                // class coursier/util/shaded/org/jsoup/HttpStatusException
       460: dup
       461: ldc_w         #315                // String HTTP error fetching URL
       464: iload         10
       466: aload_0
       467: invokeinterface #112,  1          // InterfaceMethod coursier/util/shaded/org/jsoup/Connection$Request.url:()Ljava/net/URL;
       472: invokevirtual #316                // Method java/net/URL.toString:()Ljava/lang/String;
       475: invokespecial #319                // Method coursier/util/shaded/org/jsoup/HttpStatusException."<init>":(Ljava/lang/String;ILjava/lang/String;)V
       478: athrow
       479: aload         9
       481: invokevirtual #321                // Method contentType:()Ljava/lang/String;
       484: astore        11
       486: aload         11
       488: ifnull        547
       491: aload_0
       492: invokeinterface #324,  1          // InterfaceMethod coursier/util/shaded/org/jsoup/Connection$Request.ignoreContentType:()Z
       497: ifne          547
       500: aload         11
       502: ldc_w         #326                // String text/
       505: invokevirtual #254                // Method java/lang/String.startsWith:(Ljava/lang/String;)Z
       508: ifne          547
       511: getstatic     #328                // Field xmlContentTypeRxp:Ljava/util/regex/Pattern;
       514: aload         11
       516: invokevirtual #334                // Method java/util/regex/Pattern.matcher:(Ljava/lang/CharSequence;)Ljava/util/regex/Matcher;
       519: invokevirtual #339                // Method java/util/regex/Matcher.matches:()Z
       522: ifne          547
       525: new           #341                // class coursier/util/shaded/org/jsoup/UnsupportedMimeTypeException
       528: dup
       529: ldc_w         #343                // String Unhandled content type. Must be text/*, application/xml, or application/*+xml
       532: aload         11
       534: aload_0
       535: invokeinterface #112,  1          // InterfaceMethod coursier/util/shaded/org/jsoup/Connection$Request.url:()Ljava/net/URL;
       540: invokevirtual #316                // Method java/net/URL.toString:()Ljava/lang/String;
       543: invokespecial #346                // Method coursier/util/shaded/org/jsoup/UnsupportedMimeTypeException."<init>":(Ljava/lang/String;Ljava/lang/String;Ljava/lang/String;)V
       546: athrow
       547: aload         11
       549: ifnull        593
       552: getstatic     #328                // Field xmlContentTypeRxp:Ljava/util/regex/Pattern;
       555: aload         11
       557: invokevirtual #334                // Method java/util/regex/Pattern.matcher:(Ljava/lang/CharSequence;)Ljava/util/regex/Matcher;
       560: invokevirtual #339                // Method java/util/regex/Matcher.matches:()Z
       563: ifeq          593
       566: aload_0
       567: instanceof    #31                 // class coursier/util/shaded/org/jsoup/helper/HttpConnection$Request
       570: ifeq          593
       573: aload_0
       574: checkcast     #31                 // class coursier/util/shaded/org/jsoup/helper/HttpConnection$Request
       577: invokestatic  #350                // Method coursier/util/shaded/org/jsoup/helper/HttpConnection$Request.access$100:(Lcoursier/util/shaded/org/jsoup/helper/HttpConnection$Request;)Z
       580: ifne          593
       583: aload_0
       584: invokestatic  #356                // Method coursier/util/shaded/org/jsoup/parser/Parser.xmlParser:()Lcoursier/util/shaded/org/jsoup/parser/Parser;
       587: invokeinterface #360,  2          // InterfaceMethod coursier/util/shaded/org/jsoup/Connection$Request.parser:(Lcoursier/util/shaded/org/jsoup/parser/Parser;)Lcoursier/util/shaded/org/jsoup/Connection$Request;
       592: pop
       593: aload         9
       595: aload         9
       597: getfield      #362                // Field contentType:Ljava/lang/String;
       600: invokestatic  #367                // Method coursier/util/shaded/org/jsoup/helper/DataUtil.getCharsetFromContentType:(Ljava/lang/String;)Ljava/lang/String;
       603: putfield      #369                // Field charset:Ljava/lang/String;
       606: aload         8
       608: invokevirtual #372                // Method java/net/HttpURLConnection.getContentLength:()I
       611: ifeq          768
       614: aload_0
       615: invokeinterface #137,  1          // InterfaceMethod coursier/util/shaded/org/jsoup/Connection$Request.method:()Lcoursier/util/shaded/org/jsoup/Connection$Method;
       620: getstatic     #375                // Field coursier/util/shaded/org/jsoup/Connection$Method.HEAD:Lcoursier/util/shaded/org/jsoup/Connection$Method;
       623: if_acmpeq     768
       626: aload         9
       628: aconst_null
       629: putfield      #377                // Field bodyStream:Ljava/io/InputStream;
       632: aload         9
       634: aload         8
       636: invokevirtual #381                // Method java/net/HttpURLConnection.getErrorStream:()Ljava/io/InputStream;
       639: ifnull        650
       642: aload         8
       644: invokevirtual #381                // Method java/net/HttpURLConnection.getErrorStream:()Ljava/io/InputStream;
       647: goto          655
       650: aload         8
       652: invokevirtual #384                // Method java/net/HttpURLConnection.getInputStream:()Ljava/io/InputStream;
       655: putfield      #377                // Field bodyStream:Ljava/io/InputStream;
       658: aload         9
       660: ldc_w         #388                // String Content-Encoding
       663: ldc_w         #390                // String gzip
       666: invokevirtual #394                // Method hasHeaderWithValue:(Ljava/lang/String;Ljava/lang/String;)Z
       669: ifeq          692
       672: aload         9
       674: new           #396                // class java/util/zip/GZIPInputStream
       677: dup
       678: aload         9
       680: getfield      #377                // Field bodyStream:Ljava/io/InputStream;
       683: invokespecial #399                // Method java/util/zip/GZIPInputStream."<init>":(Ljava/io/InputStream;)V
       686: putfield      #377                // Field bodyStream:Ljava/io/InputStream;
       689: goto          731
       692: aload         9
       694: ldc_w         #388                // String Content-Encoding
       697: ldc_w         #401                // String deflate
       700: invokevirtual #394                // Method hasHeaderWithValue:(Ljava/lang/String;Ljava/lang/String;)Z
       703: ifeq          731
       706: aload         9
       708: new           #403                // class java/util/zip/InflaterInputStream
       711: dup
       712: aload         9
       714: getfield      #377                // Field bodyStream:Ljava/io/InputStream;
       717: new           #405                // class java/util/zip/Inflater
       720: dup
       721: iconst_1
       722: invokespecial #408                // Method java/util/zip/Inflater."<init>":(Z)V
       725: invokespecial #411                // Method java/util/zip/InflaterInputStream."<init>":(Ljava/io/InputStream;Ljava/util/zip/Inflater;)V
       728: putfield      #377                // Field bodyStream:Ljava/io/InputStream;
       731: aload         9
       733: aload         9
       735: getfield      #377                // Field bodyStream:Ljava/io/InputStream;
       738: ldc_w         #412                // int 32768
       741: aload_0
       742: invokeinterface #415,  1          // InterfaceMethod coursier/util/shaded/org/jsoup/Connection$Request.maxBodySize:()I
       747: invokestatic  #421                // Method coursier/util/shaded/org/jsoup/internal/ConstrainableInputStream.wrap:(Ljava/io/InputStream;II)Lcoursier/util/shaded/org/jsoup/internal/ConstrainableInputStream;
       750: lload         6
       752: aload_0
       753: invokeinterface #424,  1          // InterfaceMethod coursier/util/shaded/org/jsoup/Connection$Request.timeout:()I
       758: i2l
       759: invokevirtual #427                // Method coursier/util/shaded/org/jsoup/internal/ConstrainableInputStream.timeout:(JJ)Lcoursier/util/shaded/org/jsoup/internal/ConstrainableInputStream;
       762: putfield      #377                // Field bodyStream:Ljava/io/InputStream;
       765: goto          776
       768: aload         9
       770: invokestatic  #431                // Method coursier/util/shaded/org/jsoup/helper/DataUtil.emptyByteBuffer:()Ljava/nio/ByteBuffer;
       773: putfield      #433                // Field byteData:Ljava/nio/ByteBuffer;
       776: goto          794
       779: astore        10
       781: aload         9
       783: ifnull        791
       786: aload         9
       788: invokespecial #436                // Method safeClose:()V
       791: aload         10
       793: athrow
       794: aload         9
       796: iconst_1
       797: putfield      #71                 // Field executed:Z
       800: aload         9
       802: areturn
      Exception table:
         from    to  target type
           171   431   779   Class java/io/IOException
           432   776   779   Class java/io/IOException
      StackMapTable: number_of_entries = 26
        frame_type = 252 /* append */
          offset_delta = 55
          locals = [ class java/lang/String ]
        frame_type = 252 /* append */
          offset_delta = 22
          locals = [ int ]
        frame_type = 64 /* same_locals_1_stack_item */
          stack = [ int ]
        frame_type = 252 /* append */
          offset_delta = 34
          locals = [ int ]
        frame_type = 252 /* append */
          offset_delta = 25
          locals = [ class java/lang/String ]
        frame_type = 6 /* same */
        frame_type = 9 /* same */
        frame_type = 254 /* append */
          offset_delta = 37
          locals = [ long, class java/net/HttpURLConnection, class coursier/util/shaded/org/jsoup/helper/HttpConnection$Response ]
        frame_type = 252 /* append */
          offset_delta = 95
          locals = [ int ]
        frame_type = 252 /* append */
          offset_delta = 39
          locals = [ class java/lang/String ]
        frame_type = 253 /* append */
          offset_delta = 41
          locals = [ class java/net/URL, class java/util/Iterator ]
        frame_type = 250 /* chop */
          offset_delta = 51
        frame_type = 249 /* chop */
          offset_delta = 6
        frame_type = 15 /* same */
        frame_type = 30 /* same */
        frame_type = 252 /* append */
          offset_delta = 67
          locals = [ class java/lang/String ]
        frame_type = 45 /* same */
        frame_type = 120 /* same_locals_1_stack_item */
          stack = [ class coursier/util/shaded/org/jsoup/helper/HttpConnection$Response ]
        frame_type = 255 /* full_frame */
          offset_delta = 4
          locals = [ class coursier/util/shaded/org/jsoup/Connection$Request, class coursier/util/shaded/org/jsoup/helper/HttpConnection$Response, class java/lang/String, int, int, class java/lang/String, long, class java/net/HttpURLConnection, class coursier/util/shaded/org/jsoup/helper/HttpConnection$Response, int, class java/lang/String ]
          stack = [ class coursier/util/shaded/org/jsoup/helper/HttpConnection$Response, class java/io/InputStream ]
        frame_type = 36 /* same */
        frame_type = 38 /* same */
        frame_type = 36 /* same */
        frame_type = 249 /* chop */
          offset_delta = 7
        frame_type = 66 /* same_locals_1_stack_item */
          stack = [ class java/io/IOException ]
        frame_type = 252 /* append */
          offset_delta = 11
          locals = [ class java/io/IOException ]
        frame_type = 250 /* chop */
          offset_delta = 2
      LineNumberTable:
        line 711: 0
        line 712: 6
        line 713: 17
        line 714: 27
        line 715: 45
        line 716: 55
        line 717: 65
        line 718: 81
        line 719: 85
        line 722: 114
        line 723: 117
        line 724: 140
        line 725: 147
        line 726: 151
        line 728: 157
        line 729: 162
        line 730: 168
        line 732: 171
        line 733: 176
        line 734: 184
        line 736: 195
        line 737: 202
        line 738: 212
        line 739: 220
        line 742: 226
        line 743: 245
        line 744: 253
        line 745: 263
        line 746: 274
        line 747: 282
        line 750: 291
        line 751: 300
        line 752: 322
        line 753: 331
        line 754: 344
        line 756: 356
        line 757: 395
        line 758: 422
        line 759: 425
        line 761: 432
        line 762: 457
        line 765: 479
        line 766: 486
        line 767: 492
        line 768: 505
        line 769: 516
        line 771: 525
        line 772: 535
        line 775: 547
        line 777: 566
        line 778: 583
        line 782: 593
        line 783: 606
        line 784: 626
        line 785: 632
        line 786: 658
        line 787: 672
        line 788: 692
        line 789: 706
        line 791: 731
        line 792: 742
        line 793: 753
        line 796: 768
        line 801: 776
        line 798: 779
        line 799: 781
        line 800: 791
        line 803: 794
        line 804: 800
      LocalVariableTable:
        Start  Length  Slot  Name   Signature
          395      27    14 cookie   Ljava/util/Map$Entry;
          300     132    11 location   Ljava/lang/String;
          344      88    12 redir   Ljava/net/URL;
          202     574    10 status   I
          486     290    11 contentType   Ljava/lang/String;
          781      13    10     e   Ljava/io/IOException;
            0     803     0   req   Lcoursier/util/shaded/org/jsoup/Connection$Request;
            0     803     1 previousResponse   Lcoursier/util/shaded/org/jsoup/helper/HttpConnection$Response;
           27     776     2 protocol   Ljava/lang/String;
           65     738     3 methodHasBody   Z
           81     722     4 hasRequestBody   Z
          117     686     5 mimeBoundary   Ljava/lang/String;
          162     641     6 startTime   J
          168     635     8  conn   Ljava/net/HttpURLConnection;
          171     632     9   res   Lcoursier/util/shaded/org/jsoup/helper/HttpConnection$Response;
      LocalVariableTypeTable:
        Start  Length  Slot  Name   Signature
          395      27    14 cookie   Ljava/util/Map$Entry<Ljava/lang/String;Ljava/lang/String;>;
    Exceptions:
      throws java.io.IOException

  public int statusCode();
    descriptor: ()I
    flags: (0x0001) ACC_PUBLIC
    Code:
      stack=1, locals=1, args_size=1
         0: aload_0
         1: getfield      #453                // Field statusCode:I
         4: ireturn
      LineNumberTable:
        line 808: 0
      LocalVariableTable:
        Start  Length  Slot  Name   Signature
            0       5     0  this   Lcoursier/util/shaded/org/jsoup/helper/HttpConnection$Response;

  public java.lang.String statusMessage();
    descriptor: ()Ljava/lang/String;
    flags: (0x0001) ACC_PUBLIC
    Code:
      stack=1, locals=1, args_size=1
         0: aload_0
         1: getfield      #455                // Field statusMessage:Ljava/lang/String;
         4: areturn
      LineNumberTable:
        line 812: 0
      LocalVariableTable:
        Start  Length  Slot  Name   Signature
            0       5     0  this   Lcoursier/util/shaded/org/jsoup/helper/HttpConnection$Response;

  public java.lang.String charset();
    descriptor: ()Ljava/lang/String;
    flags: (0x0001) ACC_PUBLIC
    Code:
      stack=1, locals=1, args_size=1
         0: aload_0
         1: getfield      #369                // Field charset:Ljava/lang/String;
         4: areturn
      LineNumberTable:
        line 816: 0
      LocalVariableTable:
        Start  Length  Slot  Name   Signature
            0       5     0  this   Lcoursier/util/shaded/org/jsoup/helper/HttpConnection$Response;

  public coursier.util.shaded.org.jsoup.helper.HttpConnection$Response charset(java.lang.String);
    descriptor: (Ljava/lang/String;)Lcoursier/util/shaded/org/jsoup/helper/HttpConnection$Response;
    flags: (0x0001) ACC_PUBLIC
    Code:
      stack=2, locals=2, args_size=2
         0: aload_0
         1: aload_1
         2: putfield      #369                // Field charset:Ljava/lang/String;
         5: aload_0
         6: areturn
      LineNumberTable:
        line 820: 0
        line 821: 5
      LocalVariableTable:
        Start  Length  Slot  Name   Signature
            0       7     0  this   Lcoursier/util/shaded/org/jsoup/helper/HttpConnection$Response;
            0       7     1 charset   Ljava/lang/String;

  public java.lang.String contentType();
    descriptor: ()Ljava/lang/String;
    flags: (0x0001) ACC_PUBLIC
    Code:
      stack=1, locals=1, args_size=1
         0: aload_0
         1: getfield      #362                // Field contentType:Ljava/lang/String;
         4: areturn
      LineNumberTable:
        line 825: 0
      LocalVariableTable:
        Start  Length  Slot  Name   Signature
            0       5     0  this   Lcoursier/util/shaded/org/jsoup/helper/HttpConnection$Response;

  public coursier.util.shaded.org.jsoup.nodes.Document parse() throws java.io.IOException;
    descriptor: ()Lcoursier/util/shaded/org/jsoup/nodes/Document;
    flags: (0x0001) ACC_PUBLIC
    Code:
      stack=4, locals=2, args_size=1
         0: aload_0
         1: getfield      #71                 // Field executed:Z
         4: ldc_w         #460                // String Request must be executed (with .execute(), .get(), or .post() before parsing response
         7: invokestatic  #463                // Method coursier/util/shaded/org/jsoup/helper/Validate.isTrue:(ZLjava/lang/String;)V
        10: aload_0
        11: getfield      #433                // Field byteData:Ljava/nio/ByteBuffer;
        14: ifnull        40
        17: aload_0
        18: new           #465                // class java/io/ByteArrayInputStream
        21: dup
        22: aload_0
        23: getfield      #433                // Field byteData:Ljava/nio/ByteBuffer;
        26: invokevirtual #471                // Method java/nio/ByteBuffer.array:()[B
        29: invokespecial #474                // Method java/io/ByteArrayInputStream."<init>":([B)V
        32: putfield      #377                // Field bodyStream:Ljava/io/InputStream;
        35: aload_0
        36: iconst_0
        37: putfield      #73                 // Field inputStreamRead:Z
        40: aload_0
        41: getfield      #73                 // Field inputStreamRead:Z
        44: ldc_w         #476                // String Input stream already read and parsed, cannot re-read.
        47: invokestatic  #164                // Method coursier/util/shaded/org/jsoup/helper/Validate.isFalse:(ZLjava/lang/String;)V
        50: aload_0
        51: getfield      #377                // Field bodyStream:Ljava/io/InputStream;
        54: aload_0
        55: getfield      #369                // Field charset:Ljava/lang/String;
        58: aload_0
        59: getfield      #478                // Field url:Ljava/net/URL;
        62: invokevirtual #481                // Method java/net/URL.toExternalForm:()Ljava/lang/String;
        65: aload_0
        66: getfield      #219                // Field req:Lcoursier/util/shaded/org/jsoup/Connection$Request;
        69: invokeinterface #483,  1          // InterfaceMethod coursier/util/shaded/org/jsoup/Connection$Request.parser:()Lcoursier/util/shaded/org/jsoup/parser/Parser;
        74: invokestatic  #487                // Method coursier/util/shaded/org/jsoup/helper/DataUtil.parseInputStream:(Ljava/io/InputStream;Ljava/lang/String;Ljava/lang/String;Lcoursier/util/shaded/org/jsoup/parser/Parser;)Lcoursier/util/shaded/org/jsoup/nodes/Document;
        77: astore_1
        78: aload_0
        79: aload_1
        80: invokevirtual #491                // Method coursier/util/shaded/org/jsoup/nodes/Document.outputSettings:()Lcoursier/util/shaded/org/jsoup/nodes/Document$OutputSettings;
        83: invokevirtual #494                // Method coursier/util/shaded/org/jsoup/nodes/Document$OutputSettings.charset:()Ljava/nio/charset/Charset;
        86: invokevirtual #499                // Method java/nio/charset/Charset.name:()Ljava/lang/String;
        89: putfield      #369                // Field charset:Ljava/lang/String;
        92: aload_0
        93: iconst_1
        94: putfield      #73                 // Field inputStreamRead:Z
        97: aload_0
        98: invokespecial #436                // Method safeClose:()V
       101: aload_1
       102: areturn
      StackMapTable: number_of_entries = 1
        frame_type = 40 /* same */
      LineNumberTable:
        line 829: 0
        line 830: 10
        line 831: 17
        line 832: 35
        line 834: 40
        line 835: 50
        line 836: 78
        line 837: 92
        line 838: 97
        line 839: 101
      LocalVariableTable:
        Start  Length  Slot  Name   Signature
            0     103     0  this   Lcoursier/util/shaded/org/jsoup/helper/HttpConnection$Response;
           78      25     1   doc   Lcoursier/util/shaded/org/jsoup/nodes/Document;
    Exceptions:
      throws java.io.IOException

  private void prepareByteData();
    descriptor: ()V
    flags: (0x0002) ACC_PRIVATE
    Code:
      stack=3, locals=3, args_size=1
         0: aload_0
         1: getfield      #71                 // Field executed:Z
         4: ldc_w         #504                // String Request must be executed (with .execute(), .get(), or .post() before getting response body
         7: invokestatic  #463                // Method coursier/util/shaded/org/jsoup/helper/Validate.isTrue:(ZLjava/lang/String;)V
        10: aload_0
        11: getfield      #433                // Field byteData:Ljava/nio/ByteBuffer;
        14: ifnonnull     81
        17: aload_0
        18: getfield      #73                 // Field inputStreamRead:Z
        21: ldc_w         #506                // String Request has already been read (with .parse())
        24: invokestatic  #164                // Method coursier/util/shaded/org/jsoup/helper/Validate.isFalse:(ZLjava/lang/String;)V
        27: aload_0
        28: aload_0
        29: getfield      #377                // Field bodyStream:Ljava/io/InputStream;
        32: aload_0
        33: getfield      #219                // Field req:Lcoursier/util/shaded/org/jsoup/Connection$Request;
        36: invokeinterface #415,  1          // InterfaceMethod coursier/util/shaded/org/jsoup/Connection$Request.maxBodySize:()I
        41: invokestatic  #510                // Method coursier/util/shaded/org/jsoup/helper/DataUtil.readToByteBuffer:(Ljava/io/InputStream;I)Ljava/nio/ByteBuffer;
        44: putfield      #433                // Field byteData:Ljava/nio/ByteBuffer;
        47: aload_0
        48: iconst_1
        49: putfield      #73                 // Field inputStreamRead:Z
        52: aload_0
        53: invokespecial #436                // Method safeClose:()V
        56: goto          81
        59: astore_1
        60: new           #512                // class coursier/util/shaded/org/jsoup/UncheckedIOException
        63: dup
        64: aload_1
        65: invokespecial #515                // Method coursier/util/shaded/org/jsoup/UncheckedIOException."<init>":(Ljava/io/IOException;)V
        68: athrow
        69: astore_2
        70: aload_0
        71: iconst_1
        72: putfield      #73                 // Field inputStreamRead:Z
        75: aload_0
        76: invokespecial #436                // Method safeClose:()V
        79: aload_2
        80: athrow
        81: return
      Exception table:
         from    to  target type
            27    47    59   Class java/io/IOException
            27    47    69   any
            59    70    69   any
      StackMapTable: number_of_entries = 3
        frame_type = 123 /* same_locals_1_stack_item */
          stack = [ class java/io/IOException ]
        frame_type = 73 /* same_locals_1_stack_item */
          stack = [ class java/lang/Throwable ]
        frame_type = 11 /* same */
      LineNumberTable:
        line 843: 0
        line 844: 10
        line 845: 17
        line 847: 27
        line 851: 47
        line 852: 52
        line 853: 56
        line 848: 59
        line 849: 60
        line 851: 69
        line 852: 75
        line 853: 79
        line 855: 81
      LocalVariableTable:
        Start  Length  Slot  Name   Signature
           60       9     1     e   Ljava/io/IOException;
            0      82     0  this   Lcoursier/util/shaded/org/jsoup/helper/HttpConnection$Response;

  public java.lang.String body();
    descriptor: ()Ljava/lang/String;
    flags: (0x0001) ACC_PUBLIC
    Code:
      stack=2, locals=2, args_size=1
         0: aload_0
         1: invokespecial #520                // Method prepareByteData:()V
         4: aload_0
         5: getfield      #369                // Field charset:Ljava/lang/String;
         8: ifnonnull     31
        11: ldc_w         #522                // String UTF-8
        14: invokestatic  #526                // Method java/nio/charset/Charset.forName:(Ljava/lang/String;)Ljava/nio/charset/Charset;
        17: aload_0
        18: getfield      #433                // Field byteData:Ljava/nio/ByteBuffer;
        21: invokevirtual #530                // Method java/nio/charset/Charset.decode:(Ljava/nio/ByteBuffer;)Ljava/nio/CharBuffer;
        24: invokevirtual #533                // Method java/nio/CharBuffer.toString:()Ljava/lang/String;
        27: astore_1
        28: goto          49
        31: aload_0
        32: getfield      #369                // Field charset:Ljava/lang/String;
        35: invokestatic  #526                // Method java/nio/charset/Charset.forName:(Ljava/lang/String;)Ljava/nio/charset/Charset;
        38: aload_0
        39: getfield      #433                // Field byteData:Ljava/nio/ByteBuffer;
        42: invokevirtual #530                // Method java/nio/charset/Charset.decode:(Ljava/nio/ByteBuffer;)Ljava/nio/CharBuffer;
        45: invokevirtual #533                // Method java/nio/CharBuffer.toString:()Ljava/lang/String;
        48: astore_1
        49: aload_0
        50: getfield      #433                // Field byteData:Ljava/nio/ByteBuffer;
        53: invokevirtual #539                // Method java/nio/Buffer.rewind:()Ljava/nio/Buffer;
        56: pop
        57: aload_1
        58: areturn
      StackMapTable: number_of_entries = 2
        frame_type = 31 /* same */
        frame_type = 252 /* append */
          offset_delta = 17
          locals = [ class java/lang/String ]
      LineNumberTable:
        line 858: 0
        line 861: 4
        line 862: 11
        line 864: 31
        line 865: 49
        line 866: 57
      LocalVariableTable:
        Start  Length  Slot  Name   Signature
           28       3     1  body   Ljava/lang/String;
            0      59     0  this   Lcoursier/util/shaded/org/jsoup/helper/HttpConnection$Response;
           49      10     1  body   Ljava/lang/String;

  public byte[] bodyAsBytes();
    descriptor: ()[B
    flags: (0x0001) ACC_PUBLIC
    Code:
      stack=1, locals=1, args_size=1
         0: aload_0
         1: invokespecial #520                // Method prepareByteData:()V
         4: aload_0
         5: getfield      #433                // Field byteData:Ljava/nio/ByteBuffer;
         8: invokevirtual #471                // Method java/nio/ByteBuffer.array:()[B
        11: areturn
      LineNumberTable:
        line 870: 0
        line 871: 4
      LocalVariableTable:
        Start  Length  Slot  Name   Signature
            0      12     0  this   Lcoursier/util/shaded/org/jsoup/helper/HttpConnection$Response;

  public coursier.util.shaded.org.jsoup.Connection$Response bufferUp();
    descriptor: ()Lcoursier/util/shaded/org/jsoup/Connection$Response;
    flags: (0x0001) ACC_PUBLIC
    Code:
      stack=1, locals=1, args_size=1
         0: aload_0
         1: invokespecial #520                // Method prepareByteData:()V
         4: aload_0
         5: areturn
      LineNumberTable:
        line 876: 0
        line 877: 4
      LocalVariableTable:
        Start  Length  Slot  Name   Signature
            0       6     0  this   Lcoursier/util/shaded/org/jsoup/helper/HttpConnection$Response;

  public java.io.BufferedInputStream bodyStream();
    descriptor: ()Ljava/io/BufferedInputStream;
    flags: (0x0001) ACC_PUBLIC
    Code:
      stack=3, locals=1, args_size=1
         0: aload_0
         1: getfield      #71                 // Field executed:Z
         4: ldc_w         #504                // String Request must be executed (with .execute(), .get(), or .post() before getting response body
         7: invokestatic  #463                // Method coursier/util/shaded/org/jsoup/helper/Validate.isTrue:(ZLjava/lang/String;)V
        10: aload_0
        11: getfield      #73                 // Field inputStreamRead:Z
        14: ldc_w         #545                // String Request has already been read
        17: invokestatic  #164                // Method coursier/util/shaded/org/jsoup/helper/Validate.isFalse:(ZLjava/lang/String;)V
        20: aload_0
        21: iconst_1
        22: putfield      #73                 // Field inputStreamRead:Z
        25: aload_0
        26: getfield      #377                // Field bodyStream:Ljava/io/InputStream;
        29: ldc_w         #412                // int 32768
        32: aload_0
        33: getfield      #219                // Field req:Lcoursier/util/shaded/org/jsoup/Connection$Request;
        36: invokeinterface #415,  1          // InterfaceMethod coursier/util/shaded/org/jsoup/Connection$Request.maxBodySize:()I
        41: invokestatic  #421                // Method coursier/util/shaded/org/jsoup/internal/ConstrainableInputStream.wrap:(Ljava/io/InputStream;II)Lcoursier/util/shaded/org/jsoup/internal/ConstrainableInputStream;
        44: areturn
      LineNumberTable:
        line 882: 0
        line 883: 10
        line 884: 20
        line 885: 25
      LocalVariableTable:
        Start  Length  Slot  Name   Signature
            0      45     0  this   Lcoursier/util/shaded/org/jsoup/helper/HttpConnection$Response;

  private static java.net.HttpURLConnection createConnection(coursier.util.shaded.org.jsoup.Connection$Request) throws java.io.IOException;
    descriptor: (Lcoursier/util/shaded/org/jsoup/Connection$Request;)Ljava/net/HttpURLConnection;
    flags: (0x000a) ACC_PRIVATE, ACC_STATIC
    Code:
      stack=3, locals=6, args_size=1
         0: aload_0
         1: invokeinterface #549,  1          // InterfaceMethod coursier/util/shaded/org/jsoup/Connection$Request.proxy:()Ljava/net/Proxy;
         6: ifnonnull     21
         9: aload_0
        10: invokeinterface #112,  1          // InterfaceMethod coursier/util/shaded/org/jsoup/Connection$Request.url:()Ljava/net/URL;
        15: invokevirtual #553                // Method java/net/URL.openConnection:()Ljava/net/URLConnection;
        18: goto          36
        21: aload_0
        22: invokeinterface #112,  1          // InterfaceMethod coursier/util/shaded/org/jsoup/Connection$Request.url:()Ljava/net/URL;
        27: aload_0
        28: invokeinterface #549,  1          // InterfaceMethod coursier/util/shaded/org/jsoup/Connection$Request.proxy:()Ljava/net/Proxy;
        33: invokevirtual #556                // Method java/net/URL.openConnection:(Ljava/net/Proxy;)Ljava/net/URLConnection;
        36: checkcast     #194                // class java/net/HttpURLConnection
        39: astore_1
        40: aload_1
        41: aload_0
        42: invokeinterface #137,  1          // InterfaceMethod coursier/util/shaded/org/jsoup/Connection$Request.method:()Lcoursier/util/shaded/org/jsoup/Connection$Method;
        47: invokevirtual #559                // Method coursier/util/shaded/org/jsoup/Connection$Method.name:()Ljava/lang/String;
        50: invokevirtual #562                // Method java/net/HttpURLConnection.setRequestMethod:(Ljava/lang/String;)V
        53: aload_1
        54: iconst_0
        55: invokevirtual #565                // Method java/net/HttpURLConnection.setInstanceFollowRedirects:(Z)V
        58: aload_1
        59: aload_0
        60: invokeinterface #424,  1          // InterfaceMethod coursier/util/shaded/org/jsoup/Connection$Request.timeout:()I
        65: invokevirtual #569                // Method java/net/HttpURLConnection.setConnectTimeout:(I)V
        68: aload_1
        69: aload_0
        70: invokeinterface #424,  1          // InterfaceMethod coursier/util/shaded/org/jsoup/Connection$Request.timeout:()I
        75: iconst_2
        76: idiv
        77: invokevirtual #572                // Method java/net/HttpURLConnection.setReadTimeout:(I)V
        80: aload_0
        81: invokeinterface #576,  1          // InterfaceMethod coursier/util/shaded/org/jsoup/Connection$Request.sslSocketFactory:()Ljavax/net/ssl/SSLSocketFactory;
        86: ifnull        109
        89: aload_1
        90: instanceof    #578                // class javax/net/ssl/HttpsURLConnection
        93: ifeq          109
        96: aload_1
        97: checkcast     #578                // class javax/net/ssl/HttpsURLConnection
       100: aload_0
       101: invokeinterface #576,  1          // InterfaceMethod coursier/util/shaded/org/jsoup/Connection$Request.sslSocketFactory:()Ljavax/net/ssl/SSLSocketFactory;
       106: invokevirtual #582                // Method javax/net/ssl/HttpsURLConnection.setSSLSocketFactory:(Ljavax/net/ssl/SSLSocketFactory;)V
       109: aload_0
       110: invokeinterface #137,  1          // InterfaceMethod coursier/util/shaded/org/jsoup/Connection$Request.method:()Lcoursier/util/shaded/org/jsoup/Connection$Method;
       115: invokevirtual #141                // Method coursier/util/shaded/org/jsoup/Connection$Method.hasBody:()Z
       118: ifeq          126
       121: aload_1
       122: iconst_1
       123: invokevirtual #585                // Method java/net/HttpURLConnection.setDoOutput:(Z)V
       126: aload_0
       127: invokeinterface #588,  1          // InterfaceMethod coursier/util/shaded/org/jsoup/Connection$Request.cookies:()Ljava/util/Map;
       132: invokeinterface #589,  1          // InterfaceMethod java/util/Map.size:()I
       137: ifle          151
       140: aload_1
       141: ldc_w         #591                // String Cookie
       144: aload_0
       145: invokestatic  #594                // Method getRequestCookieString:(Lcoursier/util/shaded/org/jsoup/Connection$Request;)Ljava/lang/String;
       148: invokevirtual #598                // Method java/net/HttpURLConnection.addRequestProperty:(Ljava/lang/String;Ljava/lang/String;)V
       151: aload_0
       152: invokeinterface #601,  1          // InterfaceMethod coursier/util/shaded/org/jsoup/Connection$Request.multiHeaders:()Ljava/util/Map;
       157: invokeinterface #283,  1          // InterfaceMethod java/util/Map.entrySet:()Ljava/util/Set;
       162: invokeinterface #289,  1          // InterfaceMethod java/util/Set.iterator:()Ljava/util/Iterator;
       167: astore_2
       168: aload_2
       169: invokeinterface #294,  1          // InterfaceMethod java/util/Iterator.hasNext:()Z
       174: ifeq          246
       177: aload_2
       178: invokeinterface #298,  1          // InterfaceMethod java/util/Iterator.next:()Ljava/lang/Object;
       183: checkcast     #26                 // class java/util/Map$Entry
       186: astore_3
       187: aload_3
       188: invokeinterface #304,  1          // InterfaceMethod java/util/Map$Entry.getValue:()Ljava/lang/Object;
       193: checkcast     #603                // class java/util/List
       196: invokeinterface #604,  1          // InterfaceMethod java/util/List.iterator:()Ljava/util/Iterator;
       201: astore        4
       203: aload         4
       205: invokeinterface #294,  1          // InterfaceMethod java/util/Iterator.hasNext:()Z
       210: ifeq          243
       213: aload         4
       215: invokeinterface #298,  1          // InterfaceMethod java/util/Iterator.next:()Ljava/lang/Object;
       220: checkcast     #90                 // class java/lang/String
       223: astore        5
       225: aload_1
       226: aload_3
       227: invokeinterface #301,  1          // InterfaceMethod java/util/Map$Entry.getKey:()Ljava/lang/Object;
       232: checkcast     #90                 // class java/lang/String
       235: aload         5
       237: invokevirtual #598                // Method java/net/HttpURLConnection.addRequestProperty:(Ljava/lang/String;Ljava/lang/String;)V
       240: goto          203
       243: goto          168
       246: aload_1
       247: areturn
      StackMapTable: number_of_entries = 9
        frame_type = 21 /* same */
        frame_type = 78 /* same_locals_1_stack_item */
          stack = [ class java/net/URLConnection ]
        frame_type = 252 /* append */
          offset_delta = 72
          locals = [ class java/net/HttpURLConnection ]
        frame_type = 16 /* same */
        frame_type = 24 /* same */
        frame_type = 252 /* append */
          offset_delta = 16
          locals = [ class java/util/Iterator ]
        frame_type = 253 /* append */
          offset_delta = 34
          locals = [ class java/util/Map$Entry, class java/util/Iterator ]
        frame_type = 249 /* chop */
          offset_delta = 39
        frame_type = 250 /* chop */
          offset_delta = 2
      LineNumberTable:
        line 891: 0
        line 892: 9
        line 893: 21
        line 896: 40
        line 897: 53
        line 898: 58
        line 899: 68
        line 901: 80
        line 902: 96
        line 903: 109
        line 904: 121
        line 905: 126
        line 906: 140
        line 907: 151
        line 908: 187
        line 909: 225
        line 910: 240
        line 911: 243
        line 912: 246
      LocalVariableTable:
        Start  Length  Slot  Name   Signature
          225      15     5 value   Ljava/lang/String;
          187      56     3 header   Ljava/util/Map$Entry;
            0     248     0   req   Lcoursier/util/shaded/org/jsoup/Connection$Request;
           40     208     1  conn   Ljava/net/HttpURLConnection;
      LocalVariableTypeTable:
        Start  Length  Slot  Name   Signature
          187      56     3 header   Ljava/util/Map$Entry<Ljava/lang/String;Ljava/util/List<Ljava/lang/String;>;>;
    Exceptions:
      throws java.io.IOException

  private void safeClose();
    descriptor: ()V
    flags: (0x0002) ACC_PRIVATE
    Code:
      stack=2, locals=3, args_size=1
         0: aload_0
         1: getfield      #377                // Field bodyStream:Ljava/io/InputStream;
         4: ifnull        39
         7: aload_0
         8: getfield      #377                // Field bodyStream:Ljava/io/InputStream;
        11: invokevirtual #609                // Method java/io/InputStream.close:()V
        14: aload_0
        15: aconst_null
        16: putfield      #377                // Field bodyStream:Ljava/io/InputStream;
        19: goto          39
        22: astore_1
        23: aload_0
        24: aconst_null
        25: putfield      #377                // Field bodyStream:Ljava/io/InputStream;
        28: goto          39
        31: astore_2
        32: aload_0
        33: aconst_null
        34: putfield      #377                // Field bodyStream:Ljava/io/InputStream;
        37: aload_2
        38: athrow
        39: aload_0
        40: getfield      #611                // Field conn:Ljava/net/HttpURLConnection;
        43: ifnull        58
        46: aload_0
        47: getfield      #611                // Field conn:Ljava/net/HttpURLConnection;
        50: invokevirtual #614                // Method java/net/HttpURLConnection.disconnect:()V
        53: aload_0
        54: aconst_null
        55: putfield      #611                // Field conn:Ljava/net/HttpURLConnection;
        58: return
      Exception table:
         from    to  target type
             7    14    22   Class java/io/IOException
             7    14    31   any
      StackMapTable: number_of_entries = 4
        frame_type = 86 /* same_locals_1_stack_item */
          stack = [ class java/io/IOException ]
        frame_type = 72 /* same_locals_1_stack_item */
          stack = [ class java/lang/Throwable ]
        frame_type = 7 /* same */
        frame_type = 18 /* same */
      LineNumberTable:
        line 920: 0
        line 922: 7
        line 926: 14
        line 927: 19
        line 923: 22
        line 926: 23
        line 927: 28
        line 926: 31
        line 927: 37
        line 929: 39
        line 930: 46
        line 931: 53
        line 933: 58
      LocalVariableTable:
        Start  Length  Slot  Name   Signature
            0      59     0  this   Lcoursier/util/shaded/org/jsoup/helper/HttpConnection$Response;

  private void setupFromConnection(java.net.HttpURLConnection, coursier.util.shaded.org.jsoup.helper.HttpConnection$Response) throws java.io.IOException;
    descriptor: (Ljava/net/HttpURLConnection;Lcoursier/util/shaded/org/jsoup/helper/HttpConnection$Response;)V
    flags: (0x0002) ACC_PRIVATE
    Code:
      stack=3, locals=6, args_size=3
         0: aload_0
         1: aload_1
         2: putfield      #611                // Field conn:Ljava/net/HttpURLConnection;
         5: aload_0
         6: aload_1
         7: invokevirtual #617                // Method java/net/HttpURLConnection.getRequestMethod:()Ljava/lang/String;
        10: invokestatic  #621                // Method coursier/util/shaded/org/jsoup/Connection$Method.valueOf:(Ljava/lang/String;)Lcoursier/util/shaded/org/jsoup/Connection$Method;
        13: putfield      #623                // Field method:Lcoursier/util/shaded/org/jsoup/Connection$Method;
        16: aload_0
        17: aload_1
        18: invokevirtual #626                // Method java/net/HttpURLConnection.getURL:()Ljava/net/URL;
        21: putfield      #478                // Field url:Ljava/net/URL;
        24: aload_0
        25: aload_1
        26: invokevirtual #211                // Method java/net/HttpURLConnection.getResponseCode:()I
        29: putfield      #453                // Field statusCode:I
        32: aload_0
        33: aload_1
        34: invokevirtual #629                // Method java/net/HttpURLConnection.getResponseMessage:()Ljava/lang/String;
        37: putfield      #455                // Field statusMessage:Ljava/lang/String;
        40: aload_0
        41: aload_1
        42: invokevirtual #632                // Method java/net/HttpURLConnection.getContentType:()Ljava/lang/String;
        45: putfield      #362                // Field contentType:Ljava/lang/String;
        48: aload_1
        49: invokestatic  #636                // Method createHeaderMap:(Ljava/net/HttpURLConnection;)Ljava/util/LinkedHashMap;
        52: astore_3
        53: aload_0
        54: aload_3
        55: invokevirtual #640                // Method processResponseHeaders:(Ljava/util/Map;)V
        58: aload_2
        59: ifnull        149
        62: aload_2
        63: invokevirtual #641                // Method cookies:()Ljava/util/Map;
        66: invokeinterface #283,  1          // InterfaceMethod java/util/Map.entrySet:()Ljava/util/Set;
        71: invokeinterface #289,  1          // InterfaceMethod java/util/Set.iterator:()Ljava/util/Iterator;
        76: astore        4
        78: aload         4
        80: invokeinterface #294,  1          // InterfaceMethod java/util/Iterator.hasNext:()Z
        85: ifeq          145
        88: aload         4
        90: invokeinterface #298,  1          // InterfaceMethod java/util/Iterator.next:()Ljava/lang/Object;
        95: checkcast     #26                 // class java/util/Map$Entry
        98: astore        5
       100: aload_0
       101: aload         5
       103: invokeinterface #301,  1          // InterfaceMethod java/util/Map$Entry.getKey:()Ljava/lang/Object;
       108: checkcast     #90                 // class java/lang/String
       111: invokevirtual #644                // Method hasCookie:(Ljava/lang/String;)Z
       114: ifne          142
       117: aload_0
       118: aload         5
       120: invokeinterface #301,  1          // InterfaceMethod java/util/Map$Entry.getKey:()Ljava/lang/Object;
       125: checkcast     #90                 // class java/lang/String
       128: aload         5
       130: invokeinterface #304,  1          // InterfaceMethod java/util/Map$Entry.getValue:()Ljava/lang/Object;
       135: checkcast     #90                 // class java/lang/String
       138: invokevirtual #645                // Method cookie:(Ljava/lang/String;Ljava/lang/String;)Lcoursier/util/shaded/org/jsoup/Connection$Base;
       141: pop
       142: goto          78
       145: aload_2
       146: invokespecial #436                // Method safeClose:()V
       149: return
      StackMapTable: number_of_entries = 4
        frame_type = 253 /* append */
          offset_delta = 78
          locals = [ class java/util/Map, class java/util/Iterator ]
        frame_type = 63 /* same */
        frame_type = 250 /* chop */
          offset_delta = 2
        frame_type = 3 /* same */
      LineNumberTable:
        line 937: 0
        line 938: 5
        line 939: 16
        line 940: 24
        line 941: 32
        line 942: 40
        line 944: 48
        line 945: 53
        line 948: 58
        line 949: 62
        line 950: 100
        line 951: 117
        line 952: 142
        line 953: 145
        line 955: 149
      LocalVariableTable:
        Start  Length  Slot  Name   Signature
          100      42     5 prevCookie   Ljava/util/Map$Entry;
            0     150     0  this   Lcoursier/util/shaded/org/jsoup/helper/HttpConnection$Response;
            0     150     1  conn   Ljava/net/HttpURLConnection;
            0     150     2 previousResponse   Lcoursier/util/shaded/org/jsoup/helper/HttpConnection$Response;
           53      97     3 resHeaders   Ljava/util/Map;
      LocalVariableTypeTable:
        Start  Length  Slot  Name   Signature
          100      42     5 prevCookie   Ljava/util/Map$Entry<Ljava/lang/String;Ljava/lang/String;>;
           53      97     3 resHeaders   Ljava/util/Map<Ljava/lang/String;Ljava/util/List<Ljava/lang/String;>;>;
    Exceptions:
      throws java.io.IOException

  private static java.util.LinkedHashMap<java.lang.String, java.util.List<java.lang.String>> createHeaderMap(java.net.HttpURLConnection);
    descriptor: (Ljava/net/HttpURLConnection;)Ljava/util/LinkedHashMap;
    flags: (0x000a) ACC_PRIVATE, ACC_STATIC
    Code:
      stack=3, locals=6, args_size=1
         0: new           #651                // class java/util/LinkedHashMap
         3: dup
         4: invokespecial #652                // Method java/util/LinkedHashMap."<init>":()V
         7: astore_1
         8: iconst_0
         9: istore_2
        10: aload_0
        11: iload_2
        12: invokevirtual #655                // Method java/net/HttpURLConnection.getHeaderFieldKey:(I)Ljava/lang/String;
        15: astore_3
        16: aload_0
        17: iload_2
        18: invokevirtual #658                // Method java/net/HttpURLConnection.getHeaderField:(I)Ljava/lang/String;
        21: astore        4
        23: aload_3
        24: ifnonnull     35
        27: aload         4
        29: ifnonnull     35
        32: goto          105
        35: iinc          2, 1
        38: aload_3
        39: ifnull        10
        42: aload         4
        44: ifnonnull     50
        47: goto          10
        50: aload_1
        51: aload_3
        52: invokevirtual #661                // Method java/util/LinkedHashMap.containsKey:(Ljava/lang/Object;)Z
        55: ifeq          77
        58: aload_1
        59: aload_3
        60: invokevirtual #665                // Method java/util/LinkedHashMap.get:(Ljava/lang/Object;)Ljava/lang/Object;
        63: checkcast     #603                // class java/util/List
        66: aload         4
        68: invokeinterface #668,  2          // InterfaceMethod java/util/List.add:(Ljava/lang/Object;)Z
        73: pop
        74: goto          102
        77: new           #670                // class java/util/ArrayList
        80: dup
        81: invokespecial #671                // Method java/util/ArrayList."<init>":()V
        84: astore        5
        86: aload         5
        88: aload         4
        90: invokevirtual #672                // Method java/util/ArrayList.add:(Ljava/lang/Object;)Z
        93: pop
        94: aload_1
        95: aload_3
        96: aload         5
        98: invokevirtual #676                // Method java/util/LinkedHashMap.put:(Ljava/lang/Object;Ljava/lang/Object;)Ljava/lang/Object;
       101: pop
       102: goto          10
       105: aload_1
       106: areturn
      StackMapTable: number_of_entries = 6
        frame_type = 253 /* append */
          offset_delta = 10
          locals = [ class java/util/LinkedHashMap, int ]
        frame_type = 253 /* append */
          offset_delta = 24
          locals = [ class java/lang/String, class java/lang/String ]
        frame_type = 14 /* same */
        frame_type = 26 /* same */
        frame_type = 249 /* chop */
          offset_delta = 24
        frame_type = 2 /* same */
      LineNumberTable:
        line 959: 0
        line 960: 8
        line 962: 10
        line 963: 16
        line 964: 23
        line 965: 32
        line 966: 35
        line 967: 38
        line 968: 47
        line 970: 50
        line 971: 58
        line 973: 77
        line 974: 86
        line 975: 94
        line 977: 102
        line 978: 105
      LocalVariableTable:
        Start  Length  Slot  Name   Signature
           86      16     5  vals   Ljava/util/ArrayList;
           16      86     3   key   Ljava/lang/String;
           23      79     4   val   Ljava/lang/String;
            0     107     0  conn   Ljava/net/HttpURLConnection;
            8      99     1 headers   Ljava/util/LinkedHashMap;
           10      97     2     i   I
      LocalVariableTypeTable:
        Start  Length  Slot  Name   Signature
           86      16     5  vals   Ljava/util/ArrayList<Ljava/lang/String;>;
            8      99     1 headers   Ljava/util/LinkedHashMap<Ljava/lang/String;Ljava/util/List<Ljava/lang/String;>;>;
    Signature: #649                         // (Ljava/net/HttpURLConnection;)Ljava/util/LinkedHashMap<Ljava/lang/String;Ljava/util/List<Ljava/lang/String;>;>;

  void processResponseHeaders(java.util.Map<java.lang.String, java.util.List<java.lang.String>>);
    descriptor: (Ljava/util/Map;)V
    flags: (0x0000)
    Code:
      stack=3, locals=11, args_size=2
         0: aload_1
         1: invokeinterface #283,  1          // InterfaceMethod java/util/Map.entrySet:()Ljava/util/Set;
         6: invokeinterface #289,  1          // InterfaceMethod java/util/Set.iterator:()Ljava/util/Iterator;
        11: astore_2
        12: aload_2
        13: invokeinterface #294,  1          // InterfaceMethod java/util/Iterator.hasNext:()Z
        18: ifeq          214
        21: aload_2
        22: invokeinterface #298,  1          // InterfaceMethod java/util/Iterator.next:()Ljava/lang/Object;
        27: checkcast     #26                 // class java/util/Map$Entry
        30: astore_3
        31: aload_3
        32: invokeinterface #301,  1          // InterfaceMethod java/util/Map$Entry.getKey:()Ljava/lang/Object;
        37: checkcast     #90                 // class java/lang/String
        40: astore        4
        42: aload         4
        44: ifnonnull     50
        47: goto          12
        50: aload_3
        51: invokeinterface #304,  1          // InterfaceMethod java/util/Map$Entry.getValue:()Ljava/lang/Object;
        56: checkcast     #603                // class java/util/List
        59: astore        5
        61: aload         4
        63: ldc_w         #688                // String Set-Cookie
        66: invokevirtual #691                // Method java/lang/String.equalsIgnoreCase:(Ljava/lang/String;)Z
        69: ifeq          168
        72: aload         5
        74: invokeinterface #604,  1          // InterfaceMethod java/util/List.iterator:()Ljava/util/Iterator;
        79: astore        6
        81: aload         6
        83: invokeinterface #294,  1          // InterfaceMethod java/util/Iterator.hasNext:()Z
        88: ifeq          168
        91: aload         6
        93: invokeinterface #298,  1          // InterfaceMethod java/util/Iterator.next:()Ljava/lang/Object;
        98: checkcast     #90                 // class java/lang/String
       101: astore        7
       103: aload         7
       105: ifnonnull     111
       108: goto          81
       111: new           #693                // class coursier/util/shaded/org/jsoup/parser/TokenQueue
       114: dup
       115: aload         7
       117: invokespecial #694                // Method coursier/util/shaded/org/jsoup/parser/TokenQueue."<init>":(Ljava/lang/String;)V
       120: astore        8
       122: aload         8
       124: ldc_w         #696                // String =
       127: invokevirtual #699                // Method coursier/util/shaded/org/jsoup/parser/TokenQueue.chompTo:(Ljava/lang/String;)Ljava/lang/String;
       130: invokevirtual #702                // Method java/lang/String.trim:()Ljava/lang/String;
       133: astore        9
       135: aload         8
       137: ldc_w         #704                // String ;
       140: invokevirtual #707                // Method coursier/util/shaded/org/jsoup/parser/TokenQueue.consumeTo:(Ljava/lang/String;)Ljava/lang/String;
       143: invokevirtual #702                // Method java/lang/String.trim:()Ljava/lang/String;
       146: astore        10
       148: aload         9
       150: invokevirtual #710                // Method java/lang/String.length:()I
       153: ifle          165
       156: aload_0
       157: aload         9
       159: aload         10
       161: invokevirtual #645                // Method cookie:(Ljava/lang/String;Ljava/lang/String;)Lcoursier/util/shaded/org/jsoup/Connection$Base;
       164: pop
       165: goto          81
       168: aload         5
       170: invokeinterface #604,  1          // InterfaceMethod java/util/List.iterator:()Ljava/util/Iterator;
       175: astore        6
       177: aload         6
       179: invokeinterface #294,  1          // InterfaceMethod java/util/Iterator.hasNext:()Z
       184: ifeq          211
       187: aload         6
       189: invokeinterface #298,  1          // InterfaceMethod java/util/Iterator.next:()Ljava/lang/Object;
       194: checkcast     #90                 // class java/lang/String
       197: astore        7
       199: aload_0
       200: aload         4
       202: aload         7
       204: invokevirtual #713                // Method addHeader:(Ljava/lang/String;Ljava/lang/String;)Lcoursier/util/shaded/org/jsoup/Connection$Base;
       207: pop
       208: goto          177
       211: goto          12
       214: return
      StackMapTable: number_of_entries = 9
        frame_type = 252 /* append */
          offset_delta = 12
          locals = [ class java/util/Iterator ]
        frame_type = 253 /* append */
          offset_delta = 37
          locals = [ class java/util/Map$Entry, class java/lang/String ]
        frame_type = 253 /* append */
          offset_delta = 30
          locals = [ class java/util/List, class java/util/Iterator ]
        frame_type = 252 /* append */
          offset_delta = 29
          locals = [ class java/lang/String ]
        frame_type = 250 /* chop */
          offset_delta = 53
        frame_type = 250 /* chop */
          offset_delta = 2
        frame_type = 252 /* append */
          offset_delta = 8
          locals = [ class java/util/Iterator ]
        frame_type = 255 /* full_frame */
          offset_delta = 33
          locals = [ class coursier/util/shaded/org/jsoup/helper/HttpConnection$Response, class java/util/Map, class java/util/Iterator ]
          stack = []
        frame_type = 250 /* chop */
          offset_delta = 2
      LineNumberTable:
        line 982: 0
        line 983: 31
        line 984: 42
        line 985: 47
        line 987: 50
        line 988: 61
        line 989: 72
        line 990: 103
        line 991: 108
        line 992: 111
        line 993: 122
        line 994: 135
        line 997: 148
        line 998: 156
        line 999: 165
        line 1001: 168
        line 1002: 199
        line 1003: 208
        line 1004: 211
        line 1005: 214
      LocalVariableTable:
        Start  Length  Slot  Name   Signature
          122      43     8    cd   Lcoursier/util/shaded/org/jsoup/parser/TokenQueue;
          135      30     9 cookieName   Ljava/lang/String;
          148      17    10 cookieVal   Ljava/lang/String;
          103      62     7 value   Ljava/lang/String;
          199       9     7 value   Ljava/lang/String;
           42     169     4  name   Ljava/lang/String;
           61     150     5 values   Ljava/util/List;
           31     180     3 entry   Ljava/util/Map$Entry;
            0     215     0  this   Lcoursier/util/shaded/org/jsoup/helper/HttpConnection$Response;
            0     215     1 resHeaders   Ljava/util/Map;
      LocalVariableTypeTable:
        Start  Length  Slot  Name   Signature
           61     150     5 values   Ljava/util/List<Ljava/lang/String;>;
           31     180     3 entry   Ljava/util/Map$Entry<Ljava/lang/String;Ljava/util/List<Ljava/lang/String;>;>;
            0     215     1 resHeaders   Ljava/util/Map<Ljava/lang/String;Ljava/util/List<Ljava/lang/String;>;>;
    Signature: #686                         // (Ljava/util/Map<Ljava/lang/String;Ljava/util/List<Ljava/lang/String;>;>;)V

  private static java.lang.String setOutputContentType(coursier.util.shaded.org.jsoup.Connection$Request);
    descriptor: (Lcoursier/util/shaded/org/jsoup/Connection$Request;)Ljava/lang/String;
    flags: (0x000a) ACC_PRIVATE, ACC_STATIC
    Code:
      stack=4, locals=2, args_size=1
         0: aconst_null
         1: astore_1
         2: aload_0
         3: ldc           #241                // String Content-Type
         5: invokeinterface #722,  2          // InterfaceMethod coursier/util/shaded/org/jsoup/Connection$Request.hasHeader:(Ljava/lang/String;)Z
        10: ifeq          83
        13: aload_0
        14: ldc           #241                // String Content-Type
        16: invokeinterface #723,  2          // InterfaceMethod coursier/util/shaded/org/jsoup/Connection$Request.header:(Ljava/lang/String;)Ljava/lang/String;
        21: ldc_w         #725                // String multipart/form-data
        24: invokevirtual #729                // Method java/lang/String.contains:(Ljava/lang/CharSequence;)Z
        27: ifeq          160
        30: aload_0
        31: ldc           #241                // String Content-Type
        33: invokeinterface #723,  2          // InterfaceMethod coursier/util/shaded/org/jsoup/Connection$Request.header:(Ljava/lang/String;)Ljava/lang/String;
        38: ldc_w         #731                // String boundary
        41: invokevirtual #729                // Method java/lang/String.contains:(Ljava/lang/CharSequence;)Z
        44: ifne          160
        47: invokestatic  #733                // Method coursier/util/shaded/org/jsoup/helper/DataUtil.mimeBoundary:()Ljava/lang/String;
        50: astore_1
        51: aload_0
        52: ldc           #241                // String Content-Type
        54: new           #146                // class java/lang/StringBuilder
        57: dup
        58: invokespecial #148                // Method java/lang/StringBuilder."<init>":()V
        61: ldc_w         #735                // String multipart/form-data; boundary=
        64: invokevirtual #154                // Method java/lang/StringBuilder.append:(Ljava/lang/String;)Ljava/lang/StringBuilder;
        67: aload_1
        68: invokevirtual #154                // Method java/lang/StringBuilder.append:(Ljava/lang/String;)Ljava/lang/StringBuilder;
        71: invokevirtual #160                // Method java/lang/StringBuilder.toString:()Ljava/lang/String;
        74: invokeinterface #737,  3          // InterfaceMethod coursier/util/shaded/org/jsoup/Connection$Request.header:(Ljava/lang/String;Ljava/lang/String;)Lcoursier/util/shaded/org/jsoup/Connection$Base;
        79: pop
        80: goto          160
        83: aload_0
        84: invokestatic  #741                // Method coursier/util/shaded/org/jsoup/helper/HttpConnection.access$200:(Lcoursier/util/shaded/org/jsoup/Connection$Request;)Z
        87: ifeq          126
        90: invokestatic  #733                // Method coursier/util/shaded/org/jsoup/helper/DataUtil.mimeBoundary:()Ljava/lang/String;
        93: astore_1
        94: aload_0
        95: ldc           #241                // String Content-Type
        97: new           #146                // class java/lang/StringBuilder
       100: dup
       101: invokespecial #148                // Method java/lang/StringBuilder."<init>":()V
       104: ldc_w         #735                // String multipart/form-data; boundary=
       107: invokevirtual #154                // Method java/lang/StringBuilder.append:(Ljava/lang/String;)Ljava/lang/StringBuilder;
       110: aload_1
       111: invokevirtual #154                // Method java/lang/StringBuilder.append:(Ljava/lang/String;)Ljava/lang/StringBuilder;
       114: invokevirtual #160                // Method java/lang/StringBuilder.toString:()Ljava/lang/String;
       117: invokeinterface #737,  3          // InterfaceMethod coursier/util/shaded/org/jsoup/Connection$Request.header:(Ljava/lang/String;Ljava/lang/String;)Lcoursier/util/shaded/org/jsoup/Connection$Base;
       122: pop
       123: goto          160
       126: aload_0
       127: ldc           #241                // String Content-Type
       129: new           #146                // class java/lang/StringBuilder
       132: dup
       133: invokespecial #148                // Method java/lang/StringBuilder."<init>":()V
       136: ldc_w         #743                // String application/x-www-form-urlencoded; charset=
       139: invokevirtual #154                // Method java/lang/StringBuilder.append:(Ljava/lang/String;)Ljava/lang/StringBuilder;
       142: aload_0
       143: invokeinterface #746,  1          // InterfaceMethod coursier/util/shaded/org/jsoup/Connection$Request.postDataCharset:()Ljava/lang/String;
       148: invokevirtual #154                // Method java/lang/StringBuilder.append:(Ljava/lang/String;)Ljava/lang/StringBuilder;
       151: invokevirtual #160                // Method java/lang/StringBuilder.toString:()Ljava/lang/String;
       154: invokeinterface #737,  3          // InterfaceMethod coursier/util/shaded/org/jsoup/Connection$Request.header:(Ljava/lang/String;Ljava/lang/String;)Lcoursier/util/shaded/org/jsoup/Connection$Base;
       159: pop
       160: aload_1
       161: areturn
      StackMapTable: number_of_entries = 3
        frame_type = 252 /* append */
          offset_delta = 83
          locals = [ class java/lang/String ]
        frame_type = 42 /* same */
        frame_type = 33 /* same */
      LineNumberTable:
        line 1008: 0
        line 1009: 2
        line 1014: 13
        line 1015: 33
        line 1016: 47
        line 1017: 51
        line 1021: 83
        line 1022: 90
        line 1023: 94
        line 1025: 126
        line 1027: 160
      LocalVariableTable:
        Start  Length  Slot  Name   Signature
            0     162     0   req   Lcoursier/util/shaded/org/jsoup/Connection$Request;
            2     160     1 bound   Ljava/lang/String;

  private static void writePost(coursier.util.shaded.org.jsoup.Connection$Request, java.io.OutputStream, java.lang.String) throws java.io.IOException;
    descriptor: (Lcoursier/util/shaded/org/jsoup/Connection$Request;Ljava/io/OutputStream;Ljava/lang/String;)V
    flags: (0x000a) ACC_PRIVATE, ACC_STATIC
    Code:
      stack=6, locals=8, args_size=3
         0: aload_0
         1: invokeinterface #168,  1          // InterfaceMethod coursier/util/shaded/org/jsoup/Connection$Request.data:()Ljava/util/Collection;
         6: astore_3
         7: new           #749                // class java/io/BufferedWriter
        10: dup
        11: new           #751                // class java/io/OutputStreamWriter
        14: dup
        15: aload_1
        16: aload_0
        17: invokeinterface #746,  1          // InterfaceMethod coursier/util/shaded/org/jsoup/Connection$Request.postDataCharset:()Ljava/lang/String;
        22: invokespecial #754                // Method java/io/OutputStreamWriter."<init>":(Ljava/io/OutputStream;Ljava/lang/String;)V
        25: invokespecial #757                // Method java/io/BufferedWriter."<init>":(Ljava/io/Writer;)V
        28: astore        4
        30: aload_2
        31: ifnull        273
        34: aload_3
        35: invokeinterface #758,  1          // InterfaceMethod java/util/Collection.iterator:()Ljava/util/Iterator;
        40: astore        5
        42: aload         5
        44: invokeinterface #294,  1          // InterfaceMethod java/util/Iterator.hasNext:()Z
        49: ifeq          248
        52: aload         5
        54: invokeinterface #298,  1          // InterfaceMethod java/util/Iterator.next:()Ljava/lang/Object;
        59: checkcast     #38                 // class coursier/util/shaded/org/jsoup/Connection$KeyVal
        62: astore        6
        64: aload         4
        66: ldc_w         #760                // String --
        69: invokevirtual #763                // Method java/io/BufferedWriter.write:(Ljava/lang/String;)V
        72: aload         4
        74: aload_2
        75: invokevirtual #763                // Method java/io/BufferedWriter.write:(Ljava/lang/String;)V
        78: aload         4
        80: ldc_w         #765                // String \r\n
        83: invokevirtual #763                // Method java/io/BufferedWriter.write:(Ljava/lang/String;)V
        86: aload         4
        88: ldc_w         #767                // String Content-Disposition: form-data; name=\"
        91: invokevirtual #763                // Method java/io/BufferedWriter.write:(Ljava/lang/String;)V
        94: aload         4
        96: aload         6
        98: invokeinterface #769,  1          // InterfaceMethod coursier/util/shaded/org/jsoup/Connection$KeyVal.key:()Ljava/lang/String;
       103: invokestatic  #772                // Method coursier/util/shaded/org/jsoup/helper/HttpConnection.access$300:(Ljava/lang/String;)Ljava/lang/String;
       106: invokevirtual #763                // Method java/io/BufferedWriter.write:(Ljava/lang/String;)V
       109: aload         4
       111: ldc_w         #774                // String \"
       114: invokevirtual #763                // Method java/io/BufferedWriter.write:(Ljava/lang/String;)V
       117: aload         6
       119: invokeinterface #777,  1          // InterfaceMethod coursier/util/shaded/org/jsoup/Connection$KeyVal.hasInputStream:()Z
       124: ifeq          217
       127: aload         4
       129: ldc_w         #779                // String ; filename=\"
       132: invokevirtual #763                // Method java/io/BufferedWriter.write:(Ljava/lang/String;)V
       135: aload         4
       137: aload         6
       139: invokeinterface #781,  1          // InterfaceMethod coursier/util/shaded/org/jsoup/Connection$KeyVal.value:()Ljava/lang/String;
       144: invokestatic  #772                // Method coursier/util/shaded/org/jsoup/helper/HttpConnection.access$300:(Ljava/lang/String;)Ljava/lang/String;
       147: invokevirtual #763                // Method java/io/BufferedWriter.write:(Ljava/lang/String;)V
       150: aload         4
       152: ldc_w         #783                // String \"\r\nContent-Type:
       155: invokevirtual #763                // Method java/io/BufferedWriter.write:(Ljava/lang/String;)V
       158: aload         4
       160: aload         6
       162: invokeinterface #784,  1          // InterfaceMethod coursier/util/shaded/org/jsoup/Connection$KeyVal.contentType:()Ljava/lang/String;
       167: ifnull        180
       170: aload         6
       172: invokeinterface #784,  1          // InterfaceMethod coursier/util/shaded/org/jsoup/Connection$KeyVal.contentType:()Ljava/lang/String;
       177: goto          183
       180: ldc_w         #788                // String application/octet-stream
       183: invokevirtual #763                // Method java/io/BufferedWriter.write:(Ljava/lang/String;)V
       186: aload         4
       188: ldc_w         #790                // String \r\n\r\n
       191: invokevirtual #763                // Method java/io/BufferedWriter.write:(Ljava/lang/String;)V
       194: aload         4
       196: invokevirtual #793                // Method java/io/BufferedWriter.flush:()V
       199: aload         6
       201: invokeinterface #796,  1          // InterfaceMethod coursier/util/shaded/org/jsoup/Connection$KeyVal.inputStream:()Ljava/io/InputStream;
       206: aload_1
       207: invokestatic  #800                // Method coursier/util/shaded/org/jsoup/helper/DataUtil.crossStreams:(Ljava/io/InputStream;Ljava/io/OutputStream;)V
       210: aload_1
       211: invokevirtual #801                // Method java/io/OutputStream.flush:()V
       214: goto          237
       217: aload         4
       219: ldc_w         #790                // String \r\n\r\n
       222: invokevirtual #763                // Method java/io/BufferedWriter.write:(Ljava/lang/String;)V
       225: aload         4
       227: aload         6
       229: invokeinterface #781,  1          // InterfaceMethod coursier/util/shaded/org/jsoup/Connection$KeyVal.value:()Ljava/lang/String;
       234: invokevirtual #763                // Method java/io/BufferedWriter.write:(Ljava/lang/String;)V
       237: aload         4
       239: ldc_w         #765                // String \r\n
       242: invokevirtual #763                // Method java/io/BufferedWriter.write:(Ljava/lang/String;)V
       245: goto          42
       248: aload         4
       250: ldc_w         #760                // String --
       253: invokevirtual #763                // Method java/io/BufferedWriter.write:(Ljava/lang/String;)V
       256: aload         4
       258: aload_2
       259: invokevirtual #763                // Method java/io/BufferedWriter.write:(Ljava/lang/String;)V
       262: aload         4
       264: ldc_w         #760                // String --
       267: invokevirtual #763                // Method java/io/BufferedWriter.write:(Ljava/lang/String;)V
       270: goto          400
       273: aload_0
       274: invokeinterface #144,  1          // InterfaceMethod coursier/util/shaded/org/jsoup/Connection$Request.requestBody:()Ljava/lang/String;
       279: ifnull        296
       282: aload         4
       284: aload_0
       285: invokeinterface #144,  1          // InterfaceMethod coursier/util/shaded/org/jsoup/Connection$Request.requestBody:()Ljava/lang/String;
       290: invokevirtual #763                // Method java/io/BufferedWriter.write:(Ljava/lang/String;)V
       293: goto          400
       296: iconst_1
       297: istore        5
       299: aload_3
       300: invokeinterface #758,  1          // InterfaceMethod java/util/Collection.iterator:()Ljava/util/Iterator;
       305: astore        6
       307: aload         6
       309: invokeinterface #294,  1          // InterfaceMethod java/util/Iterator.hasNext:()Z
       314: ifeq          400
       317: aload         6
       319: invokeinterface #298,  1          // InterfaceMethod java/util/Iterator.next:()Ljava/lang/Object;
       324: checkcast     #38                 // class coursier/util/shaded/org/jsoup/Connection$KeyVal
       327: astore        7
       329: iload         5
       331: ifne          345
       334: aload         4
       336: bipush        38
       338: invokevirtual #804                // Method java/io/BufferedWriter.append:(C)Ljava/io/Writer;
       341: pop
       342: goto          348
       345: iconst_0
       346: istore        5
       348: aload         4
       350: aload         7
       352: invokeinterface #769,  1          // InterfaceMethod coursier/util/shaded/org/jsoup/Connection$KeyVal.key:()Ljava/lang/String;
       357: aload_0
       358: invokeinterface #746,  1          // InterfaceMethod coursier/util/shaded/org/jsoup/Connection$Request.postDataCharset:()Ljava/lang/String;
       363: invokestatic  #810                // Method java/net/URLEncoder.encode:(Ljava/lang/String;Ljava/lang/String;)Ljava/lang/String;
       366: invokevirtual #763                // Method java/io/BufferedWriter.write:(Ljava/lang/String;)V
       369: aload         4
       371: bipush        61
       373: invokevirtual #812                // Method java/io/BufferedWriter.write:(I)V
       376: aload         4
       378: aload         7
       380: invokeinterface #781,  1          // InterfaceMethod coursier/util/shaded/org/jsoup/Connection$KeyVal.value:()Ljava/lang/String;
       385: aload_0
       386: invokeinterface #746,  1          // InterfaceMethod coursier/util/shaded/org/jsoup/Connection$Request.postDataCharset:()Ljava/lang/String;
       391: invokestatic  #810                // Method java/net/URLEncoder.encode:(Ljava/lang/String;Ljava/lang/String;)Ljava/lang/String;
       394: invokevirtual #763                // Method java/io/BufferedWriter.write:(Ljava/lang/String;)V
       397: goto          307
       400: aload         4
       402: invokevirtual #813                // Method java/io/BufferedWriter.close:()V
       405: return
      StackMapTable: number_of_entries = 12
        frame_type = 254 /* append */
          offset_delta = 42
          locals = [ class java/util/Collection, class java/io/BufferedWriter, class java/util/Iterator ]
        frame_type = 255 /* full_frame */
          offset_delta = 137
          locals = [ class coursier/util/shaded/org/jsoup/Connection$Request, class java/io/OutputStream, class java/lang/String, class java/util/Collection, class java/io/BufferedWriter, class java/util/Iterator, class coursier/util/shaded/org/jsoup/Connection$KeyVal ]
          stack = [ class java/io/BufferedWriter ]
        frame_type = 255 /* full_frame */
          offset_delta = 2
          locals = [ class coursier/util/shaded/org/jsoup/Connection$Request, class java/io/OutputStream, class java/lang/String, class java/util/Collection, class java/io/BufferedWriter, class java/util/Iterator, class coursier/util/shaded/org/jsoup/Connection$KeyVal ]
          stack = [ class java/io/BufferedWriter, class java/lang/String ]
        frame_type = 33 /* same */
        frame_type = 19 /* same */
        frame_type = 249 /* chop */
          offset_delta = 10
        frame_type = 24 /* same */
        frame_type = 22 /* same */
        frame_type = 253 /* append */
          offset_delta = 10
          locals = [ int, class java/util/Iterator ]
        frame_type = 252 /* append */
          offset_delta = 37
          locals = [ class coursier/util/shaded/org/jsoup/Connection$KeyVal ]
        frame_type = 2 /* same */
        frame_type = 248 /* chop */
          offset_delta = 51
      LineNumberTable:
        line 1031: 0
        line 1032: 7
        line 1034: 30
        line 1036: 34
        line 1037: 64
        line 1038: 72
        line 1039: 78
        line 1040: 86
        line 1041: 94
        line 1042: 109
        line 1043: 117
        line 1044: 127
        line 1045: 135
        line 1046: 150
        line 1047: 158
        line 1048: 186
        line 1049: 194
        line 1050: 199
        line 1051: 210
        line 1053: 217
        line 1054: 225
        line 1056: 237
        line 1057: 245
        line 1058: 248
        line 1059: 256
        line 1060: 262
        line 1061: 273
        line 1063: 282
        line 1067: 296
        line 1068: 299
        line 1069: 329
        line 1070: 334
        line 1072: 345
        line 1074: 348
        line 1075: 369
        line 1076: 376
        line 1077: 397
        line 1079: 400
        line 1080: 405
      LocalVariableTable:
        Start  Length  Slot  Name   Signature
           64     181     6 keyVal   Lcoursier/util/shaded/org/jsoup/Connection$KeyVal;
          329      68     7 keyVal   Lcoursier/util/shaded/org/jsoup/Connection$KeyVal;
          299     101     5 first   Z
            0     406     0   req   Lcoursier/util/shaded/org/jsoup/Connection$Request;
            0     406     1 outputStream   Ljava/io/OutputStream;
            0     406     2 bound   Ljava/lang/String;
            7     399     3  data   Ljava/util/Collection;
           30     376     4     w   Ljava/io/BufferedWriter;
      LocalVariableTypeTable:
        Start  Length  Slot  Name   Signature
            7     399     3  data   Ljava/util/Collection<Lcoursier/util/shaded/org/jsoup/Connection$KeyVal;>;
    Exceptions:
      throws java.io.IOException

  private static java.lang.String getRequestCookieString(coursier.util.shaded.org.jsoup.Connection$Request);
    descriptor: (Lcoursier/util/shaded/org/jsoup/Connection$Request;)Ljava/lang/String;
    flags: (0x000a) ACC_PRIVATE, ACC_STATIC
    Code:
      stack=2, locals=5, args_size=1
         0: invokestatic  #826                // Method coursier/util/shaded/org/jsoup/internal/StringUtil.borrowBuilder:()Ljava/lang/StringBuilder;
         3: astore_1
         4: iconst_1
         5: istore_2
         6: aload_0
         7: invokeinterface #588,  1          // InterfaceMethod coursier/util/shaded/org/jsoup/Connection$Request.cookies:()Ljava/util/Map;
        12: invokeinterface #283,  1          // InterfaceMethod java/util/Map.entrySet:()Ljava/util/Set;
        17: invokeinterface #289,  1          // InterfaceMethod java/util/Set.iterator:()Ljava/util/Iterator;
        22: astore_3
        23: aload_3
        24: invokeinterface #294,  1          // InterfaceMethod java/util/Iterator.hasNext:()Z
        29: ifeq          96
        32: aload_3
        33: invokeinterface #298,  1          // InterfaceMethod java/util/Iterator.next:()Ljava/lang/Object;
        38: checkcast     #26                 // class java/util/Map$Entry
        41: astore        4
        43: iload_2
        44: ifne          58
        47: aload_1
        48: ldc_w         #828                // String ;
        51: invokevirtual #154                // Method java/lang/StringBuilder.append:(Ljava/lang/String;)Ljava/lang/StringBuilder;
        54: pop
        55: goto          60
        58: iconst_0
        59: istore_2
        60: aload_1
        61: aload         4
        63: invokeinterface #301,  1          // InterfaceMethod java/util/Map$Entry.getKey:()Ljava/lang/Object;
        68: checkcast     #90                 // class java/lang/String
        71: invokevirtual #154                // Method java/lang/StringBuilder.append:(Ljava/lang/String;)Ljava/lang/StringBuilder;
        74: bipush        61
        76: invokevirtual #831                // Method java/lang/StringBuilder.append:(C)Ljava/lang/StringBuilder;
        79: aload         4
        81: invokeinterface #304,  1          // InterfaceMethod java/util/Map$Entry.getValue:()Ljava/lang/Object;
        86: checkcast     #90                 // class java/lang/String
        89: invokevirtual #154                // Method java/lang/StringBuilder.append:(Ljava/lang/String;)Ljava/lang/StringBuilder;
        92: pop
        93: goto          23
        96: aload_1
        97: invokestatic  #835                // Method coursier/util/shaded/org/jsoup/internal/StringUtil.releaseBuilder:(Ljava/lang/StringBuilder;)Ljava/lang/String;
       100: areturn
      StackMapTable: number_of_entries = 4
        frame_type = 254 /* append */
          offset_delta = 23
          locals = [ class java/lang/StringBuilder, int, class java/util/Iterator ]
        frame_type = 252 /* append */
          offset_delta = 34
          locals = [ class java/util/Map$Entry ]
        frame_type = 1 /* same */
        frame_type = 249 /* chop */
          offset_delta = 35
      LineNumberTable:
        line 1083: 0
        line 1084: 4
        line 1085: 6
        line 1086: 43
        line 1087: 47
        line 1089: 58
        line 1090: 60
        line 1092: 93
        line 1093: 96
      LocalVariableTable:
        Start  Length  Slot  Name   Signature
           43      50     4 cookie   Ljava/util/Map$Entry;
            0     101     0   req   Lcoursier/util/shaded/org/jsoup/Connection$Request;
            4      97     1    sb   Ljava/lang/StringBuilder;
            6      95     2 first   Z
      LocalVariableTypeTable:
        Start  Length  Slot  Name   Signature
           43      50     4 cookie   Ljava/util/Map$Entry<Ljava/lang/String;Ljava/lang/String;>;

  private static void serialiseRequestUrl(coursier.util.shaded.org.jsoup.Connection$Request) throws java.io.IOException;
    descriptor: (Lcoursier/util/shaded/org/jsoup/Connection$Request;)V
    flags: (0x000a) ACC_PRIVATE, ACC_STATIC
    Code:
      stack=4, locals=6, args_size=1
         0: aload_0
         1: invokeinterface #112,  1          // InterfaceMethod coursier/util/shaded/org/jsoup/Connection$Request.url:()Ljava/net/URL;
         6: astore_1
         7: invokestatic  #826                // Method coursier/util/shaded/org/jsoup/internal/StringUtil.borrowBuilder:()Ljava/lang/StringBuilder;
        10: astore_2
        11: iconst_1
        12: istore_3
        13: aload_2
        14: aload_1
        15: invokevirtual #120                // Method java/net/URL.getProtocol:()Ljava/lang/String;
        18: invokevirtual #154                // Method java/lang/StringBuilder.append:(Ljava/lang/String;)Ljava/lang/StringBuilder;
        21: ldc_w         #839                // String ://
        24: invokevirtual #154                // Method java/lang/StringBuilder.append:(Ljava/lang/String;)Ljava/lang/StringBuilder;
        27: aload_1
        28: invokevirtual #842                // Method java/net/URL.getAuthority:()Ljava/lang/String;
        31: invokevirtual #154                // Method java/lang/StringBuilder.append:(Ljava/lang/String;)Ljava/lang/StringBuilder;
        34: aload_1
        35: invokevirtual #845                // Method java/net/URL.getPath:()Ljava/lang/String;
        38: invokevirtual #154                // Method java/lang/StringBuilder.append:(Ljava/lang/String;)Ljava/lang/StringBuilder;
        41: ldc_w         #847                // String ?
        44: invokevirtual #154                // Method java/lang/StringBuilder.append:(Ljava/lang/String;)Ljava/lang/StringBuilder;
        47: pop
        48: aload_1
        49: invokevirtual #850                // Method java/net/URL.getQuery:()Ljava/lang/String;
        52: ifnull        66
        55: aload_2
        56: aload_1
        57: invokevirtual #850                // Method java/net/URL.getQuery:()Ljava/lang/String;
        60: invokevirtual #154                // Method java/lang/StringBuilder.append:(Ljava/lang/String;)Ljava/lang/StringBuilder;
        63: pop
        64: iconst_0
        65: istore_3
        66: aload_0
        67: invokeinterface #168,  1          // InterfaceMethod coursier/util/shaded/org/jsoup/Connection$Request.data:()Ljava/util/Collection;
        72: invokeinterface #758,  1          // InterfaceMethod java/util/Collection.iterator:()Ljava/util/Iterator;
        77: astore        4
        79: aload         4
        81: invokeinterface #294,  1          // InterfaceMethod java/util/Iterator.hasNext:()Z
        86: ifeq          172
        89: aload         4
        91: invokeinterface #298,  1          // InterfaceMethod java/util/Iterator.next:()Ljava/lang/Object;
        96: checkcast     #38                 // class coursier/util/shaded/org/jsoup/Connection$KeyVal
        99: astore        5
       101: aload         5
       103: invokeinterface #777,  1          // InterfaceMethod coursier/util/shaded/org/jsoup/Connection$KeyVal.hasInputStream:()Z
       108: ldc_w         #852                // String InputStream data not supported in URL query string.
       111: invokestatic  #164                // Method coursier/util/shaded/org/jsoup/helper/Validate.isFalse:(ZLjava/lang/String;)V
       114: iload_3
       115: ifne          128
       118: aload_2
       119: bipush        38
       121: invokevirtual #831                // Method java/lang/StringBuilder.append:(C)Ljava/lang/StringBuilder;
       124: pop
       125: goto          130
       128: iconst_0
       129: istore_3
       130: aload_2
       131: aload         5
       133: invokeinterface #769,  1          // InterfaceMethod coursier/util/shaded/org/jsoup/Connection$KeyVal.key:()Ljava/lang/String;
       138: ldc_w         #522                // String UTF-8
       141: invokestatic  #810                // Method java/net/URLEncoder.encode:(Ljava/lang/String;Ljava/lang/String;)Ljava/lang/String;
       144: invokevirtual #154                // Method java/lang/StringBuilder.append:(Ljava/lang/String;)Ljava/lang/StringBuilder;
       147: bipush        61
       149: invokevirtual #831                // Method java/lang/StringBuilder.append:(C)Ljava/lang/StringBuilder;
       152: aload         5
       154: invokeinterface #781,  1          // InterfaceMethod coursier/util/shaded/org/jsoup/Connection$KeyVal.value:()Ljava/lang/String;
       159: ldc_w         #522                // String UTF-8
       162: invokestatic  #810                // Method java/net/URLEncoder.encode:(Ljava/lang/String;Ljava/lang/String;)Ljava/lang/String;
       165: invokevirtual #154                // Method java/lang/StringBuilder.append:(Ljava/lang/String;)Ljava/lang/StringBuilder;
       168: pop
       169: goto          79
       172: aload_0
       173: new           #116                // class java/net/URL
       176: dup
       177: aload_2
       178: invokestatic  #835                // Method coursier/util/shaded/org/jsoup/internal/StringUtil.releaseBuilder:(Ljava/lang/StringBuilder;)Ljava/lang/String;
       181: invokespecial #853                // Method java/net/URL."<init>":(Ljava/lang/String;)V
       184: invokeinterface #275,  2          // InterfaceMethod coursier/util/shaded/org/jsoup/Connection$Request.url:(Ljava/net/URL;)Lcoursier/util/shaded/org/jsoup/Connection$Base;
       189: pop
       190: aload_0
       191: invokeinterface #168,  1          // InterfaceMethod coursier/util/shaded/org/jsoup/Connection$Request.data:()Ljava/util/Collection;
       196: invokeinterface #236,  1          // InterfaceMethod java/util/Collection.clear:()V
       201: return
      StackMapTable: number_of_entries = 5
        frame_type = 254 /* append */
          offset_delta = 66
          locals = [ class java/net/URL, class java/lang/StringBuilder, int ]
        frame_type = 252 /* append */
          offset_delta = 12
          locals = [ class java/util/Iterator ]
        frame_type = 252 /* append */
          offset_delta = 48
          locals = [ class coursier/util/shaded/org/jsoup/Connection$KeyVal ]
        frame_type = 1 /* same */
        frame_type = 249 /* chop */
          offset_delta = 41
      LineNumberTable:
        line 1098: 0
        line 1099: 7
        line 1100: 11
        line 1102: 13
        line 1103: 15
        line 1104: 24
        line 1105: 28
        line 1106: 35
        line 1107: 44
        line 1108: 48
        line 1109: 55
        line 1110: 64
        line 1112: 66
        line 1113: 101
        line 1114: 114
        line 1115: 118
        line 1117: 128
        line 1118: 130
        line 1119: 133
        line 1120: 149
        line 1121: 154
        line 1122: 169
        line 1123: 172
        line 1124: 190
        line 1125: 201
      LocalVariableTable:
        Start  Length  Slot  Name   Signature
          101      68     5 keyVal   Lcoursier/util/shaded/org/jsoup/Connection$KeyVal;
            0     202     0   req   Lcoursier/util/shaded/org/jsoup/Connection$Request;
            7     195     1    in   Ljava/net/URL;
           11     191     2   url   Ljava/lang/StringBuilder;
           13     189     3 first   Z
    Exceptions:
      throws java.io.IOException

  public java.util.Map cookies();
    descriptor: ()Ljava/util/Map;
    flags: (0x1041) ACC_PUBLIC, ACC_BRIDGE, ACC_SYNTHETIC
    Code:
      stack=1, locals=1, args_size=1
         0: aload_0
         1: invokespecial #855                // Method coursier/util/shaded/org/jsoup/helper/HttpConnection$Base.cookies:()Ljava/util/Map;
         4: areturn
      LineNumberTable:
        line 673: 0
      LocalVariableTable:
        Start  Length  Slot  Name   Signature
            0       5     0  this   Lcoursier/util/shaded/org/jsoup/helper/HttpConnection$Response;

  public coursier.util.shaded.org.jsoup.Connection$Base removeCookie(java.lang.String);
    descriptor: (Ljava/lang/String;)Lcoursier/util/shaded/org/jsoup/Connection$Base;
    flags: (0x1041) ACC_PUBLIC, ACC_BRIDGE, ACC_SYNTHETIC
    Code:
      stack=2, locals=2, args_size=2
         0: aload_0
         1: aload_1
         2: invokespecial #858                // Method coursier/util/shaded/org/jsoup/helper/HttpConnection$Base.removeCookie:(Ljava/lang/String;)Lcoursier/util/shaded/org/jsoup/Connection$Base;
         5: areturn
      LineNumberTable:
        line 673: 0
      LocalVariableTable:
        Start  Length  Slot  Name   Signature
            0       6     0  this   Lcoursier/util/shaded/org/jsoup/helper/HttpConnection$Response;

  public boolean hasCookie(java.lang.String);
    descriptor: (Ljava/lang/String;)Z
    flags: (0x1041) ACC_PUBLIC, ACC_BRIDGE, ACC_SYNTHETIC
    Code:
      stack=2, locals=2, args_size=2
         0: aload_0
         1: aload_1
         2: invokespecial #859                // Method coursier/util/shaded/org/jsoup/helper/HttpConnection$Base.hasCookie:(Ljava/lang/String;)Z
         5: ireturn
      LineNumberTable:
        line 673: 0
      LocalVariableTable:
        Start  Length  Slot  Name   Signature
            0       6     0  this   Lcoursier/util/shaded/org/jsoup/helper/HttpConnection$Response;

  public coursier.util.shaded.org.jsoup.Connection$Base cookie(java.lang.String, java.lang.String);
    descriptor: (Ljava/lang/String;Ljava/lang/String;)Lcoursier/util/shaded/org/jsoup/Connection$Base;
    flags: (0x1041) ACC_PUBLIC, ACC_BRIDGE, ACC_SYNTHETIC
    Code:
      stack=3, locals=3, args_size=3
         0: aload_0
         1: aload_1
         2: aload_2
         3: invokespecial #860                // Method coursier/util/shaded/org/jsoup/helper/HttpConnection$Base.cookie:(Ljava/lang/String;Ljava/lang/String;)Lcoursier/util/shaded/org/jsoup/Connection$Base;
         6: areturn
      LineNumberTable:
        line 673: 0
      LocalVariableTable:
        Start  Length  Slot  Name   Signature
            0       7     0  this   Lcoursier/util/shaded/org/jsoup/helper/HttpConnection$Response;

  public java.lang.String cookie(java.lang.String);
    descriptor: (Ljava/lang/String;)Ljava/lang/String;
    flags: (0x1041) ACC_PUBLIC, ACC_BRIDGE, ACC_SYNTHETIC
    Code:
      stack=2, locals=2, args_size=2
         0: aload_0
         1: aload_1
         2: invokespecial #862                // Method coursier/util/shaded/org/jsoup/helper/HttpConnection$Base.cookie:(Ljava/lang/String;)Ljava/lang/String;
         5: areturn
      LineNumberTable:
        line 673: 0
      LocalVariableTable:
        Start  Length  Slot  Name   Signature
            0       6     0  this   Lcoursier/util/shaded/org/jsoup/helper/HttpConnection$Response;

  public java.util.Map multiHeaders();
    descriptor: ()Ljava/util/Map;
    flags: (0x1041) ACC_PUBLIC, ACC_BRIDGE, ACC_SYNTHETIC
    Code:
      stack=1, locals=1, args_size=1
         0: aload_0
         1: invokespecial #863                // Method coursier/util/shaded/org/jsoup/helper/HttpConnection$Base.multiHeaders:()Ljava/util/Map;
         4: areturn
      LineNumberTable:
        line 673: 0
      LocalVariableTable:
        Start  Length  Slot  Name   Signature
            0       5     0  this   Lcoursier/util/shaded/org/jsoup/helper/HttpConnection$Response;

  public java.util.Map headers();
    descriptor: ()Ljava/util/Map;
    flags: (0x1041) ACC_PUBLIC, ACC_BRIDGE, ACC_SYNTHETIC
    Code:
      stack=1, locals=1, args_size=1
         0: aload_0
         1: invokespecial #865                // Method coursier/util/shaded/org/jsoup/helper/HttpConnection$Base.headers:()Ljava/util/Map;
         4: areturn
      LineNumberTable:
        line 673: 0
      LocalVariableTable:
        Start  Length  Slot  Name   Signature
            0       5     0  this   Lcoursier/util/shaded/org/jsoup/helper/HttpConnection$Response;

  public coursier.util.shaded.org.jsoup.Connection$Base removeHeader(java.lang.String);
    descriptor: (Ljava/lang/String;)Lcoursier/util/shaded/org/jsoup/Connection$Base;
    flags: (0x1041) ACC_PUBLIC, ACC_BRIDGE, ACC_SYNTHETIC
    Code:
      stack=2, locals=2, args_size=2
         0: aload_0
         1: aload_1
         2: invokespecial #866                // Method coursier/util/shaded/org/jsoup/helper/HttpConnection$Base.removeHeader:(Ljava/lang/String;)Lcoursier/util/shaded/org/jsoup/Connection$Base;
         5: areturn
      LineNumberTable:
        line 673: 0
      LocalVariableTable:
        Start  Length  Slot  Name   Signature
            0       6     0  this   Lcoursier/util/shaded/org/jsoup/helper/HttpConnection$Response;

  public boolean hasHeaderWithValue(java.lang.String, java.lang.String);
    descriptor: (Ljava/lang/String;Ljava/lang/String;)Z
    flags: (0x1041) ACC_PUBLIC, ACC_BRIDGE, ACC_SYNTHETIC
    Code:
      stack=3, locals=3, args_size=3
         0: aload_0
         1: aload_1
         2: aload_2
         3: invokespecial #867                // Method coursier/util/shaded/org/jsoup/helper/HttpConnection$Base.hasHeaderWithValue:(Ljava/lang/String;Ljava/lang/String;)Z
         6: ireturn
      LineNumberTable:
        line 673: 0
      LocalVariableTable:
        Start  Length  Slot  Name   Signature
            0       7     0  this   Lcoursier/util/shaded/org/jsoup/helper/HttpConnection$Response;

  public boolean hasHeader(java.lang.String);
    descriptor: (Ljava/lang/String;)Z
    flags: (0x1041) ACC_PUBLIC, ACC_BRIDGE, ACC_SYNTHETIC
    Code:
      stack=2, locals=2, args_size=2
         0: aload_0
         1: aload_1
         2: invokespecial #868                // Method coursier/util/shaded/org/jsoup/helper/HttpConnection$Base.hasHeader:(Ljava/lang/String;)Z
         5: ireturn
      LineNumberTable:
        line 673: 0
      LocalVariableTable:
        Start  Length  Slot  Name   Signature
            0       6     0  this   Lcoursier/util/shaded/org/jsoup/helper/HttpConnection$Response;

  public coursier.util.shaded.org.jsoup.Connection$Base header(java.lang.String, java.lang.String);
    descriptor: (Ljava/lang/String;Ljava/lang/String;)Lcoursier/util/shaded/org/jsoup/Connection$Base;
    flags: (0x1041) ACC_PUBLIC, ACC_BRIDGE, ACC_SYNTHETIC
    Code:
      stack=3, locals=3, args_size=3
         0: aload_0
         1: aload_1
         2: aload_2
         3: invokespecial #869                // Method coursier/util/shaded/org/jsoup/helper/HttpConnection$Base.header:(Ljava/lang/String;Ljava/lang/String;)Lcoursier/util/shaded/org/jsoup/Connection$Base;
         6: areturn
      LineNumberTable:
        line 673: 0
      LocalVariableTable:
        Start  Length  Slot  Name   Signature
            0       7     0  this   Lcoursier/util/shaded/org/jsoup/helper/HttpConnection$Response;

  public java.util.List headers(java.lang.String);
    descriptor: (Ljava/lang/String;)Ljava/util/List;
    flags: (0x1041) ACC_PUBLIC, ACC_BRIDGE, ACC_SYNTHETIC
    Code:
      stack=2, locals=2, args_size=2
         0: aload_0
         1: aload_1
         2: invokespecial #872                // Method coursier/util/shaded/org/jsoup/helper/HttpConnection$Base.headers:(Ljava/lang/String;)Ljava/util/List;
         5: areturn
      LineNumberTable:
        line 673: 0
      LocalVariableTable:
        Start  Length  Slot  Name   Signature
            0       6     0  this   Lcoursier/util/shaded/org/jsoup/helper/HttpConnection$Response;

  public coursier.util.shaded.org.jsoup.Connection$Base addHeader(java.lang.String, java.lang.String);
    descriptor: (Ljava/lang/String;Ljava/lang/String;)Lcoursier/util/shaded/org/jsoup/Connection$Base;
    flags: (0x1041) ACC_PUBLIC, ACC_BRIDGE, ACC_SYNTHETIC
    Code:
      stack=3, locals=3, args_size=3
         0: aload_0
         1: aload_1
         2: aload_2
         3: invokespecial #873                // Method coursier/util/shaded/org/jsoup/helper/HttpConnection$Base.addHeader:(Ljava/lang/String;Ljava/lang/String;)Lcoursier/util/shaded/org/jsoup/Connection$Base;
         6: areturn
      LineNumberTable:
        line 673: 0
      LocalVariableTable:
        Start  Length  Slot  Name   Signature
            0       7     0  this   Lcoursier/util/shaded/org/jsoup/helper/HttpConnection$Response;

  public java.lang.String header(java.lang.String);
    descriptor: (Ljava/lang/String;)Ljava/lang/String;
    flags: (0x1041) ACC_PUBLIC, ACC_BRIDGE, ACC_SYNTHETIC
    Code:
      stack=2, locals=2, args_size=2
         0: aload_0
         1: aload_1
         2: invokespecial #874                // Method coursier/util/shaded/org/jsoup/helper/HttpConnection$Base.header:(Ljava/lang/String;)Ljava/lang/String;
         5: areturn
      LineNumberTable:
        line 673: 0
      LocalVariableTable:
        Start  Length  Slot  Name   Signature
            0       6     0  this   Lcoursier/util/shaded/org/jsoup/helper/HttpConnection$Response;

  public coursier.util.shaded.org.jsoup.Connection$Base method(coursier.util.shaded.org.jsoup.Connection$Method);
    descriptor: (Lcoursier/util/shaded/org/jsoup/Connection$Method;)Lcoursier/util/shaded/org/jsoup/Connection$Base;
    flags: (0x1041) ACC_PUBLIC, ACC_BRIDGE, ACC_SYNTHETIC
    Code:
      stack=2, locals=2, args_size=2
         0: aload_0
         1: aload_1
         2: invokespecial #875                // Method coursier/util/shaded/org/jsoup/helper/HttpConnection$Base.method:(Lcoursier/util/shaded/org/jsoup/Connection$Method;)Lcoursier/util/shaded/org/jsoup/Connection$Base;
         5: areturn
      LineNumberTable:
        line 673: 0
      LocalVariableTable:
        Start  Length  Slot  Name   Signature
            0       6     0  this   Lcoursier/util/shaded/org/jsoup/helper/HttpConnection$Response;

  public coursier.util.shaded.org.jsoup.Connection$Method method();
    descriptor: ()Lcoursier/util/shaded/org/jsoup/Connection$Method;
    flags: (0x1041) ACC_PUBLIC, ACC_BRIDGE, ACC_SYNTHETIC
    Code:
      stack=1, locals=1, args_size=1
         0: aload_0
         1: invokespecial #876                // Method coursier/util/shaded/org/jsoup/helper/HttpConnection$Base.method:()Lcoursier/util/shaded/org/jsoup/Connection$Method;
         4: areturn
      LineNumberTable:
        line 673: 0
      LocalVariableTable:
        Start  Length  Slot  Name   Signature
            0       5     0  this   Lcoursier/util/shaded/org/jsoup/helper/HttpConnection$Response;

  public coursier.util.shaded.org.jsoup.Connection$Base url(java.net.URL);
    descriptor: (Ljava/net/URL;)Lcoursier/util/shaded/org/jsoup/Connection$Base;
    flags: (0x1041) ACC_PUBLIC, ACC_BRIDGE, ACC_SYNTHETIC
    Code:
      stack=2, locals=2, args_size=2
         0: aload_0
         1: aload_1
         2: invokespecial #877                // Method coursier/util/shaded/org/jsoup/helper/HttpConnection$Base.url:(Ljava/net/URL;)Lcoursier/util/shaded/org/jsoup/Connection$Base;
         5: areturn
      LineNumberTable:
        line 673: 0
      LocalVariableTable:
        Start  Length  Slot  Name   Signature
            0       6     0  this   Lcoursier/util/shaded/org/jsoup/helper/HttpConnection$Response;

  public java.net.URL url();
    descriptor: ()Ljava/net/URL;
    flags: (0x1041) ACC_PUBLIC, ACC_BRIDGE, ACC_SYNTHETIC
    Code:
      stack=1, locals=1, args_size=1
         0: aload_0
         1: invokespecial #878                // Method coursier/util/shaded/org/jsoup/helper/HttpConnection$Base.url:()Ljava/net/URL;
         4: areturn
      LineNumberTable:
        line 673: 0
      LocalVariableTable:
        Start  Length  Slot  Name   Signature
            0       5     0  this   Lcoursier/util/shaded/org/jsoup/helper/HttpConnection$Response;

  public coursier.util.shaded.org.jsoup.Connection$Response charset(java.lang.String);
    descriptor: (Ljava/lang/String;)Lcoursier/util/shaded/org/jsoup/Connection$Response;
    flags: (0x1041) ACC_PUBLIC, ACC_BRIDGE, ACC_SYNTHETIC
    Code:
      stack=2, locals=2, args_size=2
         0: aload_0
         1: aload_1
         2: invokevirtual #881                // Method charset:(Ljava/lang/String;)Lcoursier/util/shaded/org/jsoup/helper/HttpConnection$Response;
         5: areturn
      LineNumberTable:
        line 673: 0
      LocalVariableTable:
        Start  Length  Slot  Name   Signature
            0       6     0  this   Lcoursier/util/shaded/org/jsoup/helper/HttpConnection$Response;

  static {};
    descriptor: ()V
    flags: (0x0008) ACC_STATIC
    Code:
      stack=1, locals=0, args_size=0
         0: ldc_w         #884                // String (application|text)/\\w*\\+?xml.*
         3: invokestatic  #888                // Method java/util/regex/Pattern.compile:(Ljava/lang/String;)Ljava/util/regex/Pattern;
         6: putstatic     #328                // Field xmlContentTypeRxp:Ljava/util/regex/Pattern;
         9: return
      LineNumberTable:
        line 691: 0
}
InnerClasses:
  private static abstract #11= #5 of #10; // Base=class coursier/util/shaded/org/jsoup/helper/HttpConnection$Base of class coursier/util/shaded/org/jsoup/helper/HttpConnection
  static #13;                             // class coursier/util/shaded/org/jsoup/helper/HttpConnection$1
  public static #14= #2 of #10;           // Response=class coursier/util/shaded/org/jsoup/helper/HttpConnection$Response of class coursier/util/shaded/org/jsoup/helper/HttpConnection
  public static #19= #16 of #18;          // Request=class coursier/util/shaded/org/jsoup/Connection$Request of class coursier/util/shaded/org/jsoup/Connection
  public static final #22= #21 of #18;    // Method=class coursier/util/shaded/org/jsoup/Connection$Method of class coursier/util/shaded/org/jsoup/Connection
  public static #11= #24 of #18;          // Base=class coursier/util/shaded/org/jsoup/Connection$Base of class coursier/util/shaded/org/jsoup/Connection
  public static #29= #26 of #28;          // Entry=class java/util/Map$Entry of class java/util/Map
  public static #19= #31 of #10;          // Request=class coursier/util/shaded/org/jsoup/helper/HttpConnection$Request of class coursier/util/shaded/org/jsoup/helper/HttpConnection
  public static #36= #33 of #35;          // OutputSettings=class coursier/util/shaded/org/jsoup/nodes/Document$OutputSettings of class coursier/util/shaded/org/jsoup/nodes/Document
  public static #39= #38 of #18;          // KeyVal=class coursier/util/shaded/org/jsoup/Connection$KeyVal of class coursier/util/shaded/org/jsoup/Connection
  public static #14= #7 of #18;           // Response=class coursier/util/shaded/org/jsoup/Connection$Response of class coursier/util/shaded/org/jsoup/Connection
Signature: #3                           // Lcoursier/util/shaded/org/jsoup/helper/HttpConnection$Base<Lcoursier/util/shaded/org/jsoup/Connection$Response;>;Lcoursier/util/shaded/org/jsoup/Connection$Response;
SourceFile: "HttpConnection.java"
