Classfile /Users/mw/Projects/slang-braindump/.jar/jar8/assemble/slang-braindump/assemble/content/scala/collection/convert/impl/BitSetStepper$.class
  Last modified May 29, 2022; size 1207 bytes
  SHA-256 checksum 892ac5c6d3a351e28d35bf5ac1743723224df9904b3624f2ae9b99115831e3ba
  Compiled from "BitSetStepper.scala"
public final class scala.collection.convert.impl.BitSetStepper$
  minor version: 0
  major version: 52
  flags: (0x0031) ACC_PUBLIC, ACC_FINAL, ACC_SUPER
  this_class: #2                          // scala/collection/convert/impl/BitSetStepper$
  super_class: #4                         // java/lang/Object
  interfaces: 0, fields: 1, methods: 3, attributes: 3
Constant pool:
   #1 = Utf8               scala/collection/convert/impl/BitSetStepper$
   #2 = Class              #1             // scala/collection/convert/impl/BitSetStepper$
   #3 = Utf8               java/lang/Object
   #4 = Class              #3             // java/lang/Object
   #5 = Utf8               BitSetStepper.scala
   #6 = Utf8               MODULE$
   #7 = Utf8               Lscala/collection/convert/impl/BitSetStepper$;
   #8 = Utf8               <clinit>
   #9 = Utf8               ()V
  #10 = Utf8               <init>
  #11 = NameAndType        #10:#9         // "<init>":()V
  #12 = Methodref          #2.#11         // scala/collection/convert/impl/BitSetStepper$."<init>":()V
  #13 = NameAndType        #6:#7          // MODULE$:Lscala/collection/convert/impl/BitSetStepper$;
  #14 = Fieldref           #2.#13         // scala/collection/convert/impl/BitSetStepper$.MODULE$:Lscala/collection/convert/impl/BitSetStepper$;
  #15 = Utf8               from
  #16 = Utf8               (Lscala/collection/BitSetOps;)Lscala/collection/IntStepper;
  #17 = Utf8               (Lscala/collection/BitSetOps<*>;)Lscala/collection/IntStepper;
  #18 = Utf8               bs
  #19 = Utf8               scala/collection/convert/impl/BitSetStepper
  #20 = Class              #19            // scala/collection/convert/impl/BitSetStepper
  #21 = Utf8               scala/collection/BitSetOps
  #22 = Class              #21            // scala/collection/BitSetOps
  #23 = Utf8               nwords
  #24 = Utf8               ()I
  #25 = NameAndType        #23:#24        // nwords:()I
  #26 = InterfaceMethodref #22.#25        // scala/collection/BitSetOps.nwords:()I
  #27 = Long               -1l
  #29 = Utf8               word
  #30 = Utf8               (I)J
  #31 = NameAndType        #29:#30        // word:(I)J
  #32 = InterfaceMethodref #22.#31        // scala/collection/BitSetOps.word:(I)J
  #33 = Utf8               (Lscala/collection/BitSetOps;JJIII)V
  #34 = NameAndType        #10:#33        // "<init>":(Lscala/collection/BitSetOps;JJIII)V
  #35 = Methodref          #20.#34        // scala/collection/convert/impl/BitSetStepper."<init>":(Lscala/collection/BitSetOps;JJIII)V
  #36 = Utf8               this
  #37 = Utf8               Lscala/collection/BitSetOps;
  #38 = Methodref          #4.#11         // java/lang/Object."<init>":()V
  #39 = Utf8               Code
  #40 = Utf8               LineNumberTable
  #41 = Utf8               StackMapTable
  #42 = Utf8               LocalVariableTable
  #43 = Utf8               Signature
  #44 = Utf8               MethodParameters
  #45 = Utf8               SourceFile
  #46 = Utf8               ScalaInlineInfo
  #47 = Utf8               Scala
{
  public static final scala.collection.convert.impl.BitSetStepper$ MODULE$;
    descriptor: Lscala/collection/convert/impl/BitSetStepper$;
    flags: (0x0019) ACC_PUBLIC, ACC_STATIC, ACC_FINAL

  public static {};
    descriptor: ()V
    flags: (0x0009) ACC_PUBLIC, ACC_STATIC
    Code:
      stack=2, locals=0, args_size=0
         0: new           #2                  // class scala/collection/convert/impl/BitSetStepper$
         3: dup
         4: invokespecial #12                 // Method "<init>":()V
         7: putstatic     #14                 // Field MODULE$:Lscala/collection/convert/impl/BitSetStepper$;
        10: return
      LineNumberTable:
        line 108: 0

  public scala.collection.IntStepper from(scala.collection.BitSetOps<?>);
    descriptor: (Lscala/collection/BitSetOps;)Lscala/collection/IntStepper;
    flags: (0x0001) ACC_PUBLIC
    Code:
      stack=10, locals=2, args_size=2
         0: new           #20                 // class scala/collection/convert/impl/BitSetStepper
         3: dup
         4: aload_1
         5: invokeinterface #26,  1           // InterfaceMethod scala/collection/BitSetOps.nwords:()I
        10: iconst_2
        11: if_icmpgt     18
        14: aconst_null
        15: goto          19
        18: aload_1
        19: aload_1
        20: invokeinterface #26,  1           // InterfaceMethod scala/collection/BitSetOps.nwords:()I
        25: iconst_0
        26: if_icmpgt     35
        29: ldc2_w        #27                 // long -1l
        32: goto          42
        35: aload_1
        36: iconst_0
        37: invokeinterface #32,  2           // InterfaceMethod scala/collection/BitSetOps.word:(I)J
        42: aload_1
        43: invokeinterface #26,  1           // InterfaceMethod scala/collection/BitSetOps.nwords:()I
        48: iconst_1
        49: if_icmpgt     58
        52: ldc2_w        #27                 // long -1l
        55: goto          65
        58: aload_1
        59: iconst_1
        60: invokeinterface #32,  2           // InterfaceMethod scala/collection/BitSetOps.word:(I)J
        65: iconst_0
        66: aload_1
        67: invokeinterface #26,  1           // InterfaceMethod scala/collection/BitSetOps.nwords:()I
        72: bipush        64
        74: imul
        75: iconst_0
        76: invokespecial #35                 // Method scala/collection/convert/impl/BitSetStepper."<init>":(Lscala/collection/BitSetOps;JJIII)V
        79: areturn
      StackMapTable: number_of_entries = 6
        frame_type = 255 /* full_frame */
          offset_delta = 18
          locals = [ class scala/collection/convert/impl/BitSetStepper$, class scala/collection/BitSetOps ]
          stack = [ uninitialized 0, uninitialized 0 ]
        frame_type = 255 /* full_frame */
          offset_delta = 0
          locals = [ class scala/collection/convert/impl/BitSetStepper$, class scala/collection/BitSetOps ]
          stack = [ uninitialized 0, uninitialized 0, class scala/collection/BitSetOps ]
        frame_type = 255 /* full_frame */
          offset_delta = 15
          locals = [ class scala/collection/convert/impl/BitSetStepper$, class scala/collection/BitSetOps ]
          stack = [ uninitialized 0, uninitialized 0, class scala/collection/BitSetOps ]
        frame_type = 255 /* full_frame */
          offset_delta = 6
          locals = [ class scala/collection/convert/impl/BitSetStepper$, class scala/collection/BitSetOps ]
          stack = [ uninitialized 0, uninitialized 0, class scala/collection/BitSetOps, long ]
        frame_type = 255 /* full_frame */
          offset_delta = 15
          locals = [ class scala/collection/convert/impl/BitSetStepper$, class scala/collection/BitSetOps ]
          stack = [ uninitialized 0, uninitialized 0, class scala/collection/BitSetOps, long ]
        frame_type = 255 /* full_frame */
          offset_delta = 6
          locals = [ class scala/collection/convert/impl/BitSetStepper$, class scala/collection/BitSetOps ]
          stack = [ uninitialized 0, uninitialized 0, class scala/collection/BitSetOps, long, long ]
      LineNumberTable:
        line 110: 0
        line 111: 4
        line 112: 19
        line 113: 42
        line 114: 65
        line 115: 66
        line 116: 75
      LocalVariableTable:
        Start  Length  Slot  Name   Signature
            0      80     0  this   Lscala/collection/convert/impl/BitSetStepper$;
            0      80     1    bs   Lscala/collection/BitSetOps;
    Signature: #17                          // (Lscala/collection/BitSetOps<*>;)Lscala/collection/IntStepper;
    MethodParameters:
      Name                           Flags
      bs                             final

  private scala.collection.convert.impl.BitSetStepper$();
    descriptor: ()V
    flags: (0x0002) ACC_PRIVATE
    Code:
      stack=1, locals=1, args_size=1
         0: aload_0
         1: invokespecial #38                 // Method java/lang/Object."<init>":()V
         4: return
      LineNumberTable:
        line 108: 0
      LocalVariableTable:
        Start  Length  Slot  Name   Signature
            0       5     0  this   Lscala/collection/convert/impl/BitSetStepper$;
}
SourceFile: "BitSetStepper.scala"
  ScalaInlineInfo: length = 0xE (unknown attribute)
   01 01 00 02 00 0A 00 09 01 00 0F 00 10 01
  Scala: length = 0x0 (unknown attribute)

