Classfile /Users/mw/Projects/slang-braindump/.jar/jar8/assemble/slang-braindump/assemble/content/scala/collection/convert/impl/LongIteratorStepper.class
  Last modified May 29, 2022; size 6464 bytes
  SHA-256 checksum b87a064f2df11418417473299a884a8bd4ecf0a4dc3df10f230f99b03c63c302
  Compiled from "IteratorStepper.scala"
public class scala.collection.convert.impl.LongIteratorStepper extends scala.collection.convert.impl.IteratorStepperBase<java.lang.Object, scala.collection.LongStepper, scala.collection.convert.impl.LongIteratorStepper> implements scala.collection.LongStepper
  minor version: 0
  major version: 52
  flags: (0x0021) ACC_PUBLIC, ACC_SUPER
  this_class: #2                          // scala/collection/convert/impl/LongIteratorStepper
  super_class: #5                         // scala/collection/convert/impl/IteratorStepperBase
  interfaces: 1, fields: 0, methods: 24, attributes: 6
Constant pool:
    #1 = Utf8               scala/collection/convert/impl/LongIteratorStepper
    #2 = Class              #1            // scala/collection/convert/impl/LongIteratorStepper
    #3 = Utf8               Lscala/collection/convert/impl/IteratorStepperBase<Ljava/lang/Object;Lscala/collection/LongStepper;Lscala/collection/convert/impl/LongIteratorStepper;>;Lscala/collection/LongStepper;
    #4 = Utf8               scala/collection/convert/impl/IteratorStepperBase
    #5 = Class              #4            // scala/collection/convert/impl/IteratorStepperBase
    #6 = Utf8               scala/collection/LongStepper
    #7 = Class              #6            // scala/collection/LongStepper
    #8 = Utf8               IteratorStepper.scala
    #9 = Utf8               Lscala/reflect/ScalaSignature;
   #10 = Utf8               bytes
   #11 = Utf8               \u0006\u0005Y2QAB\u0004\u0001\u0017=A\u0011\"\b\u0001\u0003\u0002\u0003\u0006IaH\u0016\t\u000b5\u0002A\u0011\u0001\u0018\t\u000bA\u0002A\u0011C\u0019\t\u000bI\u0002A\u0011A\u001a\t\u000bQ\u0002A\u0011A\u001b\u0003\'1{gnZ%uKJ\fGo\u001c:Ti\u0016\u0004\b/\u001a:\u000b\u0005!I\u0011\u0001B5na2T!AC\u0006\u0002\u000f\r|gN^3si*\u0011A\"D\u0001\u000bG>dG.Z2uS>t\'\"\u0001\b\u0002\u000bM\u001c\u0017\r\\1\u0014\u0007\u0001\u0001\u0002\u0004E\u0003\u0012%QAB$D\u0001\b\u0013\t\u0019rAA\nJi\u0016\u0014\u0018\r^8s\'R,\u0007\u000f]3s\u0005\u0006\u001cX\r\u0005\u0002\u0016-5\tQ\"\u0003\u0002\u0018\u001b\t!Aj\u001c8h!\tI\"$D\u0001\f\u0013\tY2BA\u0006M_:<7\u000b^3qa\u0016\u0014\bCA\t\u0001\u0003-yVO\u001c3fe2L\u0018N\\4\u0004\u0001A\u0019\u0001\u0005\u000b\u000b\u000f\u0005\u00052cB\u0001\u0012&\u001b\u0005\u0019#B\u0001\u0013\u001f\u0003\u0019a$o\\8u}%\ta\"\u0003\u0002(\u001b\u00059\u0001/Y2lC\u001e,\u0017BA\u0015+\u0005!IE/\u001a:bi>\u0014(BA\u0014\u000e\u0013\ta##\u0001\u0006v]\u0012,\'\u000f\\=j]\u001e\fa\u0001P5oSRtDC\u0001\u000f0\u0011\u0015i\"\u00011\u0001 \u0003%\u0019X-\\5dY>tW\rF\u0001\u001d\u0003!qW\r\u001f;Ti\u0016\u0004H#\u0001\u000b\u0002\u0011Q\u0014\u0018p\u00159mSR$\u0012\u0001\u0007
   #12 = Utf8               java/util/PrimitiveIterator$OfLong
   #13 = Class              #12           // java/util/PrimitiveIterator$OfLong
   #14 = Utf8               java/util/PrimitiveIterator
   #15 = Class              #14           // java/util/PrimitiveIterator
   #16 = Utf8               OfLong
   #17 = Utf8               java/util/Spliterator$OfLong
   #18 = Class              #17           // java/util/Spliterator$OfLong
   #19 = Utf8               java/util/Spliterator
   #20 = Class              #19           // java/util/Spliterator
   #21 = Utf8               spliterator
   #22 = Utf8               ()Ljava/util/Spliterator$OfLong;
   #23 = Utf8               <B:Ljava/lang/Object;>()Ljava/util/Spliterator$OfLong;
   #24 = Utf8               spliterator$
   #25 = Utf8               (Lscala/collection/LongStepper;)Ljava/util/Spliterator$OfLong;
   #26 = NameAndType        #24:#25       // spliterator$:(Lscala/collection/LongStepper;)Ljava/util/Spliterator$OfLong;
   #27 = InterfaceMethodref #7.#26        // scala/collection/LongStepper.spliterator$:(Lscala/collection/LongStepper;)Ljava/util/Spliterator$OfLong;
   #28 = Utf8               this
   #29 = Utf8               Lscala/collection/convert/impl/LongIteratorStepper;
   #30 = Utf8               javaIterator
   #31 = Utf8               ()Ljava/util/PrimitiveIterator$OfLong;
   #32 = Utf8               <B:Ljava/lang/Object;>()Ljava/util/PrimitiveIterator$OfLong;
   #33 = Utf8               javaIterator$
   #34 = Utf8               (Lscala/collection/LongStepper;)Ljava/util/PrimitiveIterator$OfLong;
   #35 = NameAndType        #33:#34       // javaIterator$:(Lscala/collection/LongStepper;)Ljava/util/PrimitiveIterator$OfLong;
   #36 = InterfaceMethodref #7.#35        // scala/collection/LongStepper.javaIterator$:(Lscala/collection/LongStepper;)Ljava/util/PrimitiveIterator$OfLong;
   #37 = Utf8               spliterator$mcJ$sp
   #38 = Utf8               ()Ljava/util/Spliterator;
   #39 = Utf8               <B:Ljava/lang/Object;>()Ljava/util/Spliterator<*>;
   #40 = Utf8               spliterator$mcJ$sp$
   #41 = Utf8               (Lscala/collection/LongStepper;)Ljava/util/Spliterator;
   #42 = NameAndType        #40:#41       // spliterator$mcJ$sp$:(Lscala/collection/LongStepper;)Ljava/util/Spliterator;
   #43 = InterfaceMethodref #7.#42        // scala/collection/LongStepper.spliterator$mcJ$sp$:(Lscala/collection/LongStepper;)Ljava/util/Spliterator;
   #44 = Utf8               javaIterator$mcJ$sp
   #45 = Utf8               ()Ljava/util/Iterator;
   #46 = Utf8               <B:Ljava/lang/Object;>()Ljava/util/Iterator<*>;
   #47 = Utf8               javaIterator$mcJ$sp$
   #48 = Utf8               (Lscala/collection/LongStepper;)Ljava/util/Iterator;
   #49 = NameAndType        #47:#48       // javaIterator$mcJ$sp$:(Lscala/collection/LongStepper;)Ljava/util/Iterator;
   #50 = InterfaceMethodref #7.#49        // scala/collection/LongStepper.javaIterator$mcJ$sp$:(Lscala/collection/LongStepper;)Ljava/util/Iterator;
   #51 = Utf8               nextStep$mcD$sp
   #52 = Utf8               ()D
   #53 = Utf8               scala/collection/Stepper
   #54 = Class              #53           // scala/collection/Stepper
   #55 = Utf8               nextStep$mcD$sp$
   #56 = Utf8               (Lscala/collection/Stepper;)D
   #57 = NameAndType        #55:#56       // nextStep$mcD$sp$:(Lscala/collection/Stepper;)D
   #58 = InterfaceMethodref #54.#57       // scala/collection/Stepper.nextStep$mcD$sp$:(Lscala/collection/Stepper;)D
   #59 = Utf8               nextStep$mcI$sp
   #60 = Utf8               ()I
   #61 = Utf8               nextStep$mcI$sp$
   #62 = Utf8               (Lscala/collection/Stepper;)I
   #63 = NameAndType        #61:#62       // nextStep$mcI$sp$:(Lscala/collection/Stepper;)I
   #64 = InterfaceMethodref #54.#63       // scala/collection/Stepper.nextStep$mcI$sp$:(Lscala/collection/Stepper;)I
   #65 = Utf8               trySplit$mcD$sp
   #66 = Utf8               ()Lscala/collection/Stepper;
   #67 = Utf8               ()Lscala/collection/Stepper<Ljava/lang/Object;>;
   #68 = Utf8               trySplit$mcD$sp$
   #69 = Utf8               (Lscala/collection/Stepper;)Lscala/collection/Stepper;
   #70 = NameAndType        #68:#69       // trySplit$mcD$sp$:(Lscala/collection/Stepper;)Lscala/collection/Stepper;
   #71 = InterfaceMethodref #54.#70       // scala/collection/Stepper.trySplit$mcD$sp$:(Lscala/collection/Stepper;)Lscala/collection/Stepper;
   #72 = Utf8               trySplit$mcI$sp
   #73 = Utf8               trySplit$mcI$sp$
   #74 = NameAndType        #73:#69       // trySplit$mcI$sp$:(Lscala/collection/Stepper;)Lscala/collection/Stepper;
   #75 = InterfaceMethodref #54.#74       // scala/collection/Stepper.trySplit$mcI$sp$:(Lscala/collection/Stepper;)Lscala/collection/Stepper;
   #76 = Utf8               trySplit$mcJ$sp
   #77 = Utf8               trySplit$mcJ$sp$
   #78 = NameAndType        #77:#69       // trySplit$mcJ$sp$:(Lscala/collection/Stepper;)Lscala/collection/Stepper;
   #79 = InterfaceMethodref #54.#78       // scala/collection/Stepper.trySplit$mcJ$sp$:(Lscala/collection/Stepper;)Lscala/collection/Stepper;
   #80 = Utf8               spliterator$mcD$sp
   #81 = Utf8               spliterator$mcD$sp$
   #82 = Utf8               (Lscala/collection/Stepper;)Ljava/util/Spliterator;
   #83 = NameAndType        #81:#82       // spliterator$mcD$sp$:(Lscala/collection/Stepper;)Ljava/util/Spliterator;
   #84 = InterfaceMethodref #54.#83       // scala/collection/Stepper.spliterator$mcD$sp$:(Lscala/collection/Stepper;)Ljava/util/Spliterator;
   #85 = Utf8               spliterator$mcI$sp
   #86 = Utf8               spliterator$mcI$sp$
   #87 = NameAndType        #86:#82       // spliterator$mcI$sp$:(Lscala/collection/Stepper;)Ljava/util/Spliterator;
   #88 = InterfaceMethodref #54.#87       // scala/collection/Stepper.spliterator$mcI$sp$:(Lscala/collection/Stepper;)Ljava/util/Spliterator;
   #89 = Utf8               javaIterator$mcD$sp
   #90 = Utf8               javaIterator$mcD$sp$
   #91 = Utf8               (Lscala/collection/Stepper;)Ljava/util/Iterator;
   #92 = NameAndType        #90:#91       // javaIterator$mcD$sp$:(Lscala/collection/Stepper;)Ljava/util/Iterator;
   #93 = InterfaceMethodref #54.#92       // scala/collection/Stepper.javaIterator$mcD$sp$:(Lscala/collection/Stepper;)Ljava/util/Iterator;
   #94 = Utf8               javaIterator$mcI$sp
   #95 = Utf8               javaIterator$mcI$sp$
   #96 = NameAndType        #95:#91       // javaIterator$mcI$sp$:(Lscala/collection/Stepper;)Ljava/util/Iterator;
   #97 = InterfaceMethodref #54.#96       // scala/collection/Stepper.javaIterator$mcI$sp$:(Lscala/collection/Stepper;)Ljava/util/Iterator;
   #98 = Utf8               iterator
   #99 = Utf8               ()Lscala/collection/Iterator;
  #100 = Utf8               ()Lscala/collection/Iterator<Ljava/lang/Object;>;
  #101 = Utf8               iterator$
  #102 = Utf8               (Lscala/collection/Stepper;)Lscala/collection/Iterator;
  #103 = NameAndType        #101:#102     // iterator$:(Lscala/collection/Stepper;)Lscala/collection/Iterator;
  #104 = InterfaceMethodref #54.#103      // scala/collection/Stepper.iterator$:(Lscala/collection/Stepper;)Lscala/collection/Iterator;
  #105 = Utf8               semiclone
  #106 = Utf8               ()Lscala/collection/convert/impl/LongIteratorStepper;
  #107 = Utf8               <init>
  #108 = Utf8               (Lscala/collection/Iterator;)V
  #109 = NameAndType        #107:#108     // "<init>":(Lscala/collection/Iterator;)V
  #110 = Methodref          #2.#109       // scala/collection/convert/impl/LongIteratorStepper."<init>":(Lscala/collection/Iterator;)V
  #111 = Utf8               nextStep
  #112 = Utf8               ()J
  #113 = Utf8               nextStep$mcJ$sp
  #114 = NameAndType        #113:#112     // nextStep$mcJ$sp:()J
  #115 = Methodref          #2.#114       // scala/collection/convert/impl/LongIteratorStepper.nextStep$mcJ$sp:()J
  #116 = Utf8               trySplit
  #117 = Utf8               ()Lscala/collection/LongStepper;
  #118 = Utf8               proxied
  #119 = NameAndType        #118:#66      // proxied:()Lscala/collection/Stepper;
  #120 = Methodref          #2.#119       // scala/collection/convert/impl/LongIteratorStepper.proxied:()Lscala/collection/Stepper;
  #121 = NameAndType        #116:#117     // trySplit:()Lscala/collection/LongStepper;
  #122 = InterfaceMethodref #7.#121       // scala/collection/LongStepper.trySplit:()Lscala/collection/LongStepper;
  #123 = Utf8               scala/jdk/LongAccumulator
  #124 = Class              #123          // scala/jdk/LongAccumulator
  #125 = Utf8               ()V
  #126 = NameAndType        #107:#125     // "<init>":()V
  #127 = Methodref          #124.#126     // scala/jdk/LongAccumulator."<init>":()V
  #128 = Utf8               nextChunkSize
  #129 = NameAndType        #128:#60      // nextChunkSize:()I
  #130 = Methodref          #2.#129       // scala/collection/convert/impl/LongIteratorStepper.nextChunkSize:()I
  #131 = Utf8               underlying
  #132 = NameAndType        #131:#99      // underlying:()Lscala/collection/Iterator;
  #133 = Methodref          #2.#132       // scala/collection/convert/impl/LongIteratorStepper.underlying:()Lscala/collection/Iterator;
  #134 = Utf8               scala/collection/Iterator
  #135 = Class              #134          // scala/collection/Iterator
  #136 = Utf8               hasNext
  #137 = Utf8               ()Z
  #138 = NameAndType        #136:#137     // hasNext:()Z
  #139 = InterfaceMethodref #135.#138     // scala/collection/Iterator.hasNext:()Z
  #140 = Utf8               next
  #141 = Utf8               ()Ljava/lang/Object;
  #142 = NameAndType        #140:#141     // next:()Ljava/lang/Object;
  #143 = InterfaceMethodref #135.#142     // scala/collection/Iterator.next:()Ljava/lang/Object;
  #144 = Utf8               scala/runtime/BoxesRunTime
  #145 = Class              #144          // scala/runtime/BoxesRunTime
  #146 = Utf8               unboxToLong
  #147 = Utf8               (Ljava/lang/Object;)J
  #148 = NameAndType        #146:#147     // unboxToLong:(Ljava/lang/Object;)J
  #149 = Methodref          #145.#148     // scala/runtime/BoxesRunTime.unboxToLong:(Ljava/lang/Object;)J
  #150 = Utf8               addOne
  #151 = Utf8               (J)Lscala/jdk/LongAccumulator;
  #152 = NameAndType        #150:#151     // addOne:(J)Lscala/jdk/LongAccumulator;
  #153 = Methodref          #124.#152     // scala/jdk/LongAccumulator.addOne:(J)Lscala/jdk/LongAccumulator;
  #154 = Utf8               scala/collection/StepperShape$
  #155 = Class              #154          // scala/collection/StepperShape$
  #156 = Utf8               MODULE$
  #157 = Utf8               Lscala/collection/StepperShape$;
  #158 = NameAndType        #156:#157     // MODULE$:Lscala/collection/StepperShape$;
  #159 = Fieldref           #155.#158     // scala/collection/StepperShape$.MODULE$:Lscala/collection/StepperShape$;
  #160 = Utf8               longStepperShape
  #161 = Utf8               ()Lscala/collection/StepperShape;
  #162 = NameAndType        #160:#161     // longStepperShape:()Lscala/collection/StepperShape;
  #163 = Methodref          #155.#162     // scala/collection/StepperShape$.longStepperShape:()Lscala/collection/StepperShape;
  #164 = Utf8               scala/jdk/Accumulator
  #165 = Class              #164          // scala/jdk/Accumulator
  #166 = Utf8               efficientStepper
  #167 = Utf8               (Lscala/collection/StepperShape;)Lscala/collection/Stepper;
  #168 = NameAndType        #166:#167     // efficientStepper:(Lscala/collection/StepperShape;)Lscala/collection/Stepper;
  #169 = Methodref          #165.#168     // scala/jdk/Accumulator.efficientStepper:(Lscala/collection/StepperShape;)Lscala/collection/Stepper;
  #170 = Utf8               proxied_$eq
  #171 = Utf8               (Lscala/collection/Stepper;)V
  #172 = NameAndType        #170:#171     // proxied_$eq:(Lscala/collection/Stepper;)V
  #173 = Methodref          #2.#172       // scala/collection/convert/impl/LongIteratorStepper.proxied_$eq:(Lscala/collection/Stepper;)V
  #174 = NameAndType        #105:#106     // semiclone:()Lscala/collection/convert/impl/LongIteratorStepper;
  #175 = Methodref          #2.#174       // scala/collection/convert/impl/LongIteratorStepper.semiclone:()Lscala/collection/convert/impl/LongIteratorStepper;
  #176 = Integer            1073741824
  #177 = Utf8               nextChunkSize_$eq
  #178 = Utf8               (I)V
  #179 = NameAndType        #177:#178     // nextChunkSize_$eq:(I)V
  #180 = Methodref          #2.#179       // scala/collection/convert/impl/LongIteratorStepper.nextChunkSize_$eq:(I)V
  #181 = Utf8               ans
  #182 = Utf8               acc
  #183 = Utf8               Lscala/jdk/LongAccumulator;
  #184 = Utf8               i
  #185 = Utf8               I
  #186 = Utf8               n
  #187 = Utf8               $plus$eq_elem
  #188 = Utf8               Ljava/lang/Object;
  #189 = Utf8               stepper_shape
  #190 = Utf8               Lscala/collection/StepperShape;
  #191 = InterfaceMethodref #54.#114      // scala/collection/Stepper.nextStep$mcJ$sp:()J
  #192 = NameAndType        #30:#31       // javaIterator:()Ljava/util/PrimitiveIterator$OfLong;
  #193 = Methodref          #2.#192       // scala/collection/convert/impl/LongIteratorStepper.javaIterator:()Ljava/util/PrimitiveIterator$OfLong;
  #194 = NameAndType        #21:#22       // spliterator:()Ljava/util/Spliterator$OfLong;
  #195 = Methodref          #2.#194       // scala/collection/convert/impl/LongIteratorStepper.spliterator:()Ljava/util/Spliterator$OfLong;
  #196 = Methodref          #2.#121       // scala/collection/convert/impl/LongIteratorStepper.trySplit:()Lscala/collection/LongStepper;
  #197 = NameAndType        #111:#112     // nextStep:()J
  #198 = Methodref          #2.#197       // scala/collection/convert/impl/LongIteratorStepper.nextStep:()J
  #199 = Utf8               boxToLong
  #200 = Utf8               (J)Ljava/lang/Long;
  #201 = NameAndType        #199:#200     // boxToLong:(J)Ljava/lang/Long;
  #202 = Methodref          #145.#201     // scala/runtime/BoxesRunTime.boxToLong:(J)Ljava/lang/Long;
  #203 = Utf8               (Lscala/collection/Iterator<Ljava/lang/Object;>;)V
  #204 = Utf8               _underlying
  #205 = Methodref          #5.#109       // scala/collection/convert/impl/IteratorStepperBase."<init>":(Lscala/collection/Iterator;)V
  #206 = Utf8               Lscala/collection/Iterator;
  #207 = Utf8               Code
  #208 = Utf8               LineNumberTable
  #209 = Utf8               LocalVariableTable
  #210 = Utf8               Signature
  #211 = Utf8               StackMapTable
  #212 = Utf8               MethodParameters
  #213 = Utf8               InnerClasses
  #214 = Utf8               SourceFile
  #215 = Utf8               RuntimeVisibleAnnotations
  #216 = Utf8               ScalaInlineInfo
  #217 = Utf8               ScalaSig
{
  public <B extends java.lang.Object> java.util.Spliterator$OfLong spliterator();
    descriptor: ()Ljava/util/Spliterator$OfLong;
    flags: (0x0001) ACC_PUBLIC
    Code:
      stack=1, locals=1, args_size=1
         0: aload_0
         1: invokestatic  #27                 // InterfaceMethod scala/collection/LongStepper.spliterator$:(Lscala/collection/LongStepper;)Ljava/util/Spliterator$OfLong;
         4: areturn
      LineNumberTable:
        line 96: 0
      LocalVariableTable:
        Start  Length  Slot  Name   Signature
            0       5     0  this   Lscala/collection/convert/impl/LongIteratorStepper;
    Signature: #23                          // <B:Ljava/lang/Object;>()Ljava/util/Spliterator$OfLong;

  public <B extends java.lang.Object> java.util.PrimitiveIterator$OfLong javaIterator();
    descriptor: ()Ljava/util/PrimitiveIterator$OfLong;
    flags: (0x0001) ACC_PUBLIC
    Code:
      stack=1, locals=1, args_size=1
         0: aload_0
         1: invokestatic  #36                 // InterfaceMethod scala/collection/LongStepper.javaIterator$:(Lscala/collection/LongStepper;)Ljava/util/PrimitiveIterator$OfLong;
         4: areturn
      LineNumberTable:
        line 96: 0
      LocalVariableTable:
        Start  Length  Slot  Name   Signature
            0       5     0  this   Lscala/collection/convert/impl/LongIteratorStepper;
    Signature: #32                          // <B:Ljava/lang/Object;>()Ljava/util/PrimitiveIterator$OfLong;

  public <B extends java.lang.Object> java.util.Spliterator<?> spliterator$mcJ$sp();
    descriptor: ()Ljava/util/Spliterator;
    flags: (0x0001) ACC_PUBLIC
    Code:
      stack=1, locals=1, args_size=1
         0: aload_0
         1: invokestatic  #43                 // InterfaceMethod scala/collection/LongStepper.spliterator$mcJ$sp$:(Lscala/collection/LongStepper;)Ljava/util/Spliterator;
         4: areturn
      LineNumberTable:
        line 96: 0
      LocalVariableTable:
        Start  Length  Slot  Name   Signature
            0       5     0  this   Lscala/collection/convert/impl/LongIteratorStepper;
    Signature: #39                          // <B:Ljava/lang/Object;>()Ljava/util/Spliterator<*>;

  public <B extends java.lang.Object> java.util.Iterator<?> javaIterator$mcJ$sp();
    descriptor: ()Ljava/util/Iterator;
    flags: (0x0001) ACC_PUBLIC
    Code:
      stack=1, locals=1, args_size=1
         0: aload_0
         1: invokestatic  #50                 // InterfaceMethod scala/collection/LongStepper.javaIterator$mcJ$sp$:(Lscala/collection/LongStepper;)Ljava/util/Iterator;
         4: areturn
      LineNumberTable:
        line 96: 0
      LocalVariableTable:
        Start  Length  Slot  Name   Signature
            0       5     0  this   Lscala/collection/convert/impl/LongIteratorStepper;
    Signature: #46                          // <B:Ljava/lang/Object;>()Ljava/util/Iterator<*>;

  public double nextStep$mcD$sp();
    descriptor: ()D
    flags: (0x0001) ACC_PUBLIC
    Code:
      stack=2, locals=1, args_size=1
         0: aload_0
         1: invokestatic  #58                 // InterfaceMethod scala/collection/Stepper.nextStep$mcD$sp$:(Lscala/collection/Stepper;)D
         4: dreturn
      LineNumberTable:
        line 96: 0
      LocalVariableTable:
        Start  Length  Slot  Name   Signature
            0       5     0  this   Lscala/collection/convert/impl/LongIteratorStepper;

  public int nextStep$mcI$sp();
    descriptor: ()I
    flags: (0x0001) ACC_PUBLIC
    Code:
      stack=1, locals=1, args_size=1
         0: aload_0
         1: invokestatic  #64                 // InterfaceMethod scala/collection/Stepper.nextStep$mcI$sp$:(Lscala/collection/Stepper;)I
         4: ireturn
      LineNumberTable:
        line 96: 0
      LocalVariableTable:
        Start  Length  Slot  Name   Signature
            0       5     0  this   Lscala/collection/convert/impl/LongIteratorStepper;

  public scala.collection.Stepper<java.lang.Object> trySplit$mcD$sp();
    descriptor: ()Lscala/collection/Stepper;
    flags: (0x0001) ACC_PUBLIC
    Code:
      stack=1, locals=1, args_size=1
         0: aload_0
         1: invokestatic  #71                 // InterfaceMethod scala/collection/Stepper.trySplit$mcD$sp$:(Lscala/collection/Stepper;)Lscala/collection/Stepper;
         4: areturn
      LineNumberTable:
        line 96: 0
      LocalVariableTable:
        Start  Length  Slot  Name   Signature
            0       5     0  this   Lscala/collection/convert/impl/LongIteratorStepper;
    Signature: #67                          // ()Lscala/collection/Stepper<Ljava/lang/Object;>;

  public scala.collection.Stepper<java.lang.Object> trySplit$mcI$sp();
    descriptor: ()Lscala/collection/Stepper;
    flags: (0x0001) ACC_PUBLIC
    Code:
      stack=1, locals=1, args_size=1
         0: aload_0
         1: invokestatic  #75                 // InterfaceMethod scala/collection/Stepper.trySplit$mcI$sp$:(Lscala/collection/Stepper;)Lscala/collection/Stepper;
         4: areturn
      LineNumberTable:
        line 96: 0
      LocalVariableTable:
        Start  Length  Slot  Name   Signature
            0       5     0  this   Lscala/collection/convert/impl/LongIteratorStepper;
    Signature: #67                          // ()Lscala/collection/Stepper<Ljava/lang/Object;>;

  public scala.collection.Stepper<java.lang.Object> trySplit$mcJ$sp();
    descriptor: ()Lscala/collection/Stepper;
    flags: (0x0001) ACC_PUBLIC
    Code:
      stack=1, locals=1, args_size=1
         0: aload_0
         1: invokestatic  #79                 // InterfaceMethod scala/collection/Stepper.trySplit$mcJ$sp$:(Lscala/collection/Stepper;)Lscala/collection/Stepper;
         4: areturn
      LineNumberTable:
        line 96: 0
      LocalVariableTable:
        Start  Length  Slot  Name   Signature
            0       5     0  this   Lscala/collection/convert/impl/LongIteratorStepper;
    Signature: #67                          // ()Lscala/collection/Stepper<Ljava/lang/Object;>;

  public <B extends java.lang.Object> java.util.Spliterator<?> spliterator$mcD$sp();
    descriptor: ()Ljava/util/Spliterator;
    flags: (0x0001) ACC_PUBLIC
    Code:
      stack=1, locals=1, args_size=1
         0: aload_0
         1: invokestatic  #84                 // InterfaceMethod scala/collection/Stepper.spliterator$mcD$sp$:(Lscala/collection/Stepper;)Ljava/util/Spliterator;
         4: areturn
      LineNumberTable:
        line 96: 0
      LocalVariableTable:
        Start  Length  Slot  Name   Signature
            0       5     0  this   Lscala/collection/convert/impl/LongIteratorStepper;
    Signature: #39                          // <B:Ljava/lang/Object;>()Ljava/util/Spliterator<*>;

  public <B extends java.lang.Object> java.util.Spliterator<?> spliterator$mcI$sp();
    descriptor: ()Ljava/util/Spliterator;
    flags: (0x0001) ACC_PUBLIC
    Code:
      stack=1, locals=1, args_size=1
         0: aload_0
         1: invokestatic  #88                 // InterfaceMethod scala/collection/Stepper.spliterator$mcI$sp$:(Lscala/collection/Stepper;)Ljava/util/Spliterator;
         4: areturn
      LineNumberTable:
        line 96: 0
      LocalVariableTable:
        Start  Length  Slot  Name   Signature
            0       5     0  this   Lscala/collection/convert/impl/LongIteratorStepper;
    Signature: #39                          // <B:Ljava/lang/Object;>()Ljava/util/Spliterator<*>;

  public <B extends java.lang.Object> java.util.Iterator<?> javaIterator$mcD$sp();
    descriptor: ()Ljava/util/Iterator;
    flags: (0x0001) ACC_PUBLIC
    Code:
      stack=1, locals=1, args_size=1
         0: aload_0
         1: invokestatic  #93                 // InterfaceMethod scala/collection/Stepper.javaIterator$mcD$sp$:(Lscala/collection/Stepper;)Ljava/util/Iterator;
         4: areturn
      LineNumberTable:
        line 96: 0
      LocalVariableTable:
        Start  Length  Slot  Name   Signature
            0       5     0  this   Lscala/collection/convert/impl/LongIteratorStepper;
    Signature: #46                          // <B:Ljava/lang/Object;>()Ljava/util/Iterator<*>;

  public <B extends java.lang.Object> java.util.Iterator<?> javaIterator$mcI$sp();
    descriptor: ()Ljava/util/Iterator;
    flags: (0x0001) ACC_PUBLIC
    Code:
      stack=1, locals=1, args_size=1
         0: aload_0
         1: invokestatic  #97                 // InterfaceMethod scala/collection/Stepper.javaIterator$mcI$sp$:(Lscala/collection/Stepper;)Ljava/util/Iterator;
         4: areturn
      LineNumberTable:
        line 96: 0
      LocalVariableTable:
        Start  Length  Slot  Name   Signature
            0       5     0  this   Lscala/collection/convert/impl/LongIteratorStepper;
    Signature: #46                          // <B:Ljava/lang/Object;>()Ljava/util/Iterator<*>;

  public scala.collection.Iterator<java.lang.Object> iterator();
    descriptor: ()Lscala/collection/Iterator;
    flags: (0x0001) ACC_PUBLIC
    Code:
      stack=1, locals=1, args_size=1
         0: aload_0
         1: invokestatic  #104                // InterfaceMethod scala/collection/Stepper.iterator$:(Lscala/collection/Stepper;)Lscala/collection/Iterator;
         4: areturn
      LineNumberTable:
        line 96: 0
      LocalVariableTable:
        Start  Length  Slot  Name   Signature
            0       5     0  this   Lscala/collection/convert/impl/LongIteratorStepper;
    Signature: #100                         // ()Lscala/collection/Iterator<Ljava/lang/Object;>;

  public scala.collection.convert.impl.LongIteratorStepper semiclone();
    descriptor: ()Lscala/collection/convert/impl/LongIteratorStepper;
    flags: (0x0001) ACC_PUBLIC
    Code:
      stack=3, locals=1, args_size=1
         0: new           #2                  // class scala/collection/convert/impl/LongIteratorStepper
         3: dup
         4: aconst_null
         5: invokespecial #110                // Method "<init>":(Lscala/collection/Iterator;)V
         8: areturn
      LineNumberTable:
        line 99: 0
      LocalVariableTable:
        Start  Length  Slot  Name   Signature
            0       9     0  this   Lscala/collection/convert/impl/LongIteratorStepper;

  public long nextStep();
    descriptor: ()J
    flags: (0x0001) ACC_PUBLIC
    Code:
      stack=2, locals=1, args_size=1
         0: aload_0
         1: invokevirtual #115                // Method nextStep$mcJ$sp:()J
         4: lreturn
      LineNumberTable:
        line 101: 0
      LocalVariableTable:
        Start  Length  Slot  Name   Signature
            0       5     0  this   Lscala/collection/convert/impl/LongIteratorStepper;

  public scala.collection.LongStepper trySplit();
    descriptor: ()Lscala/collection/LongStepper;
    flags: (0x0001) ACC_PUBLIC
    Code:
      stack=3, locals=8, args_size=1
         0: aload_0
         1: invokevirtual #120                // Method proxied:()Lscala/collection/Stepper;
         4: ifnull        20
         7: aload_0
         8: invokevirtual #120                // Method proxied:()Lscala/collection/Stepper;
        11: checkcast     #7                  // class scala/collection/LongStepper
        14: invokeinterface #122,  1          // InterfaceMethod scala/collection/LongStepper.trySplit:()Lscala/collection/LongStepper;
        19: areturn
        20: new           #124                // class scala/jdk/LongAccumulator
        23: dup
        24: invokespecial #127                // Method scala/jdk/LongAccumulator."<init>":()V
        27: astore_1
        28: iconst_0
        29: istore_2
        30: aload_0
        31: invokevirtual #130                // Method nextChunkSize:()I
        34: bipush        -4
        36: iand
        37: istore_3
        38: iload_2
        39: iload_3
        40: if_icmpge     85
        43: aload_0
        44: invokevirtual #133                // Method underlying:()Lscala/collection/Iterator;
        47: invokeinterface #139,  1          // InterfaceMethod scala/collection/Iterator.hasNext:()Z
        52: ifeq          85
        55: aload_0
        56: invokevirtual #133                // Method underlying:()Lscala/collection/Iterator;
        59: invokeinterface #143,  1          // InterfaceMethod scala/collection/Iterator.next:()Ljava/lang/Object;
        64: astore        5
        66: aload_1
        67: aload         5
        69: invokestatic  #149                // Method scala/runtime/BoxesRunTime.unboxToLong:(Ljava/lang/Object;)J
        72: invokevirtual #153                // Method scala/jdk/LongAccumulator.addOne:(J)Lscala/jdk/LongAccumulator;
        75: pop
        76: aconst_null
        77: astore        5
        79: iinc          2, 1
        82: goto          38
        85: iload_2
        86: iload_3
        87: if_icmplt     102
        90: aload_0
        91: invokevirtual #133                // Method underlying:()Lscala/collection/Iterator;
        94: invokeinterface #139,  1          // InterfaceMethod scala/collection/Iterator.hasNext:()Z
        99: ifne          136
       102: aload_0
       103: getstatic     #159                // Field scala/collection/StepperShape$.MODULE$:Lscala/collection/StepperShape$;
       106: invokevirtual #163                // Method scala/collection/StepperShape$.longStepperShape:()Lscala/collection/StepperShape;
       109: astore        6
       111: aload_1
       112: aload         6
       114: invokevirtual #169                // Method scala/jdk/Accumulator.efficientStepper:(Lscala/collection/StepperShape;)Lscala/collection/Stepper;
       117: aconst_null
       118: astore        6
       120: invokevirtual #173                // Method proxied_$eq:(Lscala/collection/Stepper;)V
       123: aload_0
       124: invokevirtual #120                // Method proxied:()Lscala/collection/Stepper;
       127: checkcast     #7                  // class scala/collection/LongStepper
       130: invokeinterface #122,  1          // InterfaceMethod scala/collection/LongStepper.trySplit:()Lscala/collection/LongStepper;
       135: areturn
       136: aload_0
       137: invokevirtual #175                // Method semiclone:()Lscala/collection/convert/impl/LongIteratorStepper;
       140: astore        4
       142: aload         4
       144: getstatic     #159                // Field scala/collection/StepperShape$.MODULE$:Lscala/collection/StepperShape$;
       147: invokevirtual #163                // Method scala/collection/StepperShape$.longStepperShape:()Lscala/collection/StepperShape;
       150: astore        7
       152: aload_1
       153: aload         7
       155: invokevirtual #169                // Method scala/jdk/Accumulator.efficientStepper:(Lscala/collection/StepperShape;)Lscala/collection/Stepper;
       158: aconst_null
       159: astore        7
       161: invokevirtual #173                // Method proxied_$eq:(Lscala/collection/Stepper;)V
       164: aload_0
       165: aload_0
       166: invokevirtual #130                // Method nextChunkSize:()I
       169: iconst_3
       170: iand
       171: iconst_3
       172: if_icmpne     191
       175: iload_3
       176: ldc           #176                // int 1073741824
       178: if_icmpge     187
       181: iload_3
       182: iconst_2
       183: imul
       184: goto          197
       187: iload_3
       188: goto          197
       191: aload_0
       192: invokevirtual #130                // Method nextChunkSize:()I
       195: iconst_1
       196: iadd
       197: invokevirtual #180                // Method nextChunkSize_$eq:(I)V
       200: aload         4
       202: areturn
      StackMapTable: number_of_entries = 8
        frame_type = 20 /* same */
        frame_type = 254 /* append */
          offset_delta = 17
          locals = [ class scala/jdk/LongAccumulator, int, int ]
        frame_type = 46 /* same */
        frame_type = 16 /* same */
        frame_type = 33 /* same */
        frame_type = 255 /* full_frame */
          offset_delta = 50
          locals = [ class scala/collection/convert/impl/LongIteratorStepper, class scala/jdk/LongAccumulator, int, int, class scala/collection/convert/impl/LongIteratorStepper, top, top, null ]
          stack = [ class scala/collection/convert/impl/LongIteratorStepper ]
        frame_type = 67 /* same_locals_1_stack_item */
          stack = [ class scala/collection/convert/impl/LongIteratorStepper ]
        frame_type = 255 /* full_frame */
          offset_delta = 5
          locals = [ class scala/collection/convert/impl/LongIteratorStepper, class scala/jdk/LongAccumulator, int, int, class scala/collection/convert/impl/LongIteratorStepper, top, top, null ]
          stack = [ class scala/collection/convert/impl/LongIteratorStepper, int ]
      LineNumberTable:
        line 103: 0
        line 104: 20
        line 105: 28
        line 106: 30
        line 107: 38
        line 108: 85
        line 109: 102
        line 110: 123
        line 113: 136
        line 114: 142
        line 115: 164
        line 116: 200
      LocalVariableTable:
        Start  Length  Slot  Name   Signature
          142      60     4   ans   Lscala/collection/convert/impl/LongIteratorStepper;
           28     174     1   acc   Lscala/jdk/LongAccumulator;
           30     172     2     i   I
           38     164     3     n   I
            0     203     0  this   Lscala/collection/convert/impl/LongIteratorStepper;
           66      10     5 $plus$eq_elem   Ljava/lang/Object;
          111       6     6 stepper_shape   Lscala/collection/StepperShape;
          152       6     7 stepper_shape   Lscala/collection/StepperShape;

  public long nextStep$mcJ$sp();
    descriptor: ()J
    flags: (0x0001) ACC_PUBLIC
    Code:
      stack=2, locals=1, args_size=1
         0: aload_0
         1: invokevirtual #120                // Method proxied:()Lscala/collection/Stepper;
         4: ifnull        17
         7: aload_0
         8: invokevirtual #120                // Method proxied:()Lscala/collection/Stepper;
        11: invokeinterface #191,  1          // InterfaceMethod scala/collection/Stepper.nextStep$mcJ$sp:()J
        16: lreturn
        17: aload_0
        18: invokevirtual #133                // Method underlying:()Lscala/collection/Iterator;
        21: invokeinterface #143,  1          // InterfaceMethod scala/collection/Iterator.next:()Ljava/lang/Object;
        26: invokestatic  #149                // Method scala/runtime/BoxesRunTime.unboxToLong:(Ljava/lang/Object;)J
        29: lreturn
      StackMapTable: number_of_entries = 1
        frame_type = 17 /* same */
      LineNumberTable:
        line 101: 0
      LocalVariableTable:
        Start  Length  Slot  Name   Signature
            0      30     0  this   Lscala/collection/convert/impl/LongIteratorStepper;

  public java.util.Iterator javaIterator();
    descriptor: ()Ljava/util/Iterator;
    flags: (0x1041) ACC_PUBLIC, ACC_BRIDGE, ACC_SYNTHETIC
    Code:
      stack=1, locals=1, args_size=1
         0: aload_0
         1: invokevirtual #193                // Method javaIterator:()Ljava/util/PrimitiveIterator$OfLong;
         4: areturn
      LineNumberTable:
        line 96: 0
      LocalVariableTable:
        Start  Length  Slot  Name   Signature
            0       5     0  this   Lscala/collection/convert/impl/LongIteratorStepper;

  public java.util.Spliterator spliterator();
    descriptor: ()Ljava/util/Spliterator;
    flags: (0x1041) ACC_PUBLIC, ACC_BRIDGE, ACC_SYNTHETIC
    Code:
      stack=1, locals=1, args_size=1
         0: aload_0
         1: invokevirtual #195                // Method spliterator:()Ljava/util/Spliterator$OfLong;
         4: areturn
      LineNumberTable:
        line 96: 0
      LocalVariableTable:
        Start  Length  Slot  Name   Signature
            0       5     0  this   Lscala/collection/convert/impl/LongIteratorStepper;

  public scala.collection.Stepper trySplit();
    descriptor: ()Lscala/collection/Stepper;
    flags: (0x1041) ACC_PUBLIC, ACC_BRIDGE, ACC_SYNTHETIC
    Code:
      stack=1, locals=1, args_size=1
         0: aload_0
         1: invokevirtual #196                // Method trySplit:()Lscala/collection/LongStepper;
         4: areturn
      LineNumberTable:
        line 96: 0
      LocalVariableTable:
        Start  Length  Slot  Name   Signature
            0       5     0  this   Lscala/collection/convert/impl/LongIteratorStepper;

  public java.lang.Object nextStep();
    descriptor: ()Ljava/lang/Object;
    flags: (0x1041) ACC_PUBLIC, ACC_BRIDGE, ACC_SYNTHETIC
    Code:
      stack=2, locals=1, args_size=1
         0: aload_0
         1: invokevirtual #198                // Method nextStep:()J
         4: invokestatic  #202                // Method scala/runtime/BoxesRunTime.boxToLong:(J)Ljava/lang/Long;
         7: areturn
      LineNumberTable:
        line 96: 0
      LocalVariableTable:
        Start  Length  Slot  Name   Signature
            0       8     0  this   Lscala/collection/convert/impl/LongIteratorStepper;

  public scala.collection.Stepper semiclone();
    descriptor: ()Lscala/collection/Stepper;
    flags: (0x1041) ACC_PUBLIC, ACC_BRIDGE, ACC_SYNTHETIC
    Code:
      stack=1, locals=1, args_size=1
         0: aload_0
         1: invokevirtual #175                // Method semiclone:()Lscala/collection/convert/impl/LongIteratorStepper;
         4: areturn
      LineNumberTable:
        line 96: 0
      LocalVariableTable:
        Start  Length  Slot  Name   Signature
            0       5     0  this   Lscala/collection/convert/impl/LongIteratorStepper;

  public scala.collection.convert.impl.LongIteratorStepper(scala.collection.Iterator<java.lang.Object>);
    descriptor: (Lscala/collection/Iterator;)V
    flags: (0x0001) ACC_PUBLIC
    Code:
      stack=2, locals=2, args_size=2
         0: aload_0
         1: aload_1
         2: invokespecial #205                // Method scala/collection/convert/impl/IteratorStepperBase."<init>":(Lscala/collection/Iterator;)V
         5: return
      LineNumberTable:
        line 97: 0
      LocalVariableTable:
        Start  Length  Slot  Name   Signature
            0       6     0  this   Lscala/collection/convert/impl/LongIteratorStepper;
            0       6     1 _underlying   Lscala/collection/Iterator;
    Signature: #203                         // (Lscala/collection/Iterator<Ljava/lang/Object;>;)V
    MethodParameters:
      Name                           Flags
      _underlying                    final
}
InnerClasses:
  public static #16= #13 of #15;          // OfLong=class java/util/PrimitiveIterator$OfLong of class java/util/PrimitiveIterator
  public static #16= #18 of #20;          // OfLong=class java/util/Spliterator$OfLong of class java/util/Spliterator
Signature: #3                           // Lscala/collection/convert/impl/IteratorStepperBase<Ljava/lang/Object;Lscala/collection/LongStepper;Lscala/collection/convert/impl/LongIteratorStepper;>;Lscala/collection/LongStepper;
SourceFile: "IteratorStepper.scala"
RuntimeVisibleAnnotations:
  0: #9(#10=s#11)
    scala.reflect.ScalaSignature(
      bytes="\u0006\u0005Y2QAB\u0004\u0001\u0017=A\u0011\"\b\u0001\u0003\u0002\u0003\u0006IaH\u0016\t\u000b5\u0002A\u0011\u0001\u0018\t\u000bA\u0002A\u0011C\u0019\t\u000bI\u0002A\u0011A\u001a\t\u000bQ\u0002A\u0011A\u001b\u0003\'1{gnZ%uKJ\fGo\u001c:Ti\u0016\u0004\b/\u001a:\u000b\u0005!I\u0011\u0001B5na2T!AC\u0006\u0002\u000f\r|gN^3si*\u0011A\"D\u0001\u000bG>dG.Z2uS>t\'\"\u0001\b\u0002\u000bM\u001c\u0017\r\\1\u0014\u0007\u0001\u0001\u0002\u0004E\u0003\u0012%QAB$D\u0001\b\u0013\t\u0019rAA\nJi\u0016\u0014\u0018\r^8s\'R,\u0007\u000f]3s\u0005\u0006\u001cX\r\u0005\u0002\u0016-5\tQ\"\u0003\u0002\u0018\u001b\t!Aj\u001c8h!\tI\"$D\u0001\f\u0013\tY2BA\u0006M_:<7\u000b^3qa\u0016\u0014\bCA\t\u0001\u0003-yVO\u001c3fe2L\u0018N\\4\u0004\u0001A\u0019\u0001\u0005\u000b\u000b\u000f\u0005\u00052cB\u0001\u0012&\u001b\u0005\u0019#B\u0001\u0013\u001f\u0003\u0019a$o\\8u}%\ta\"\u0003\u0002(\u001b\u00059\u0001/Y2lC\u001e,\u0017BA\u0015+\u0005!IE/\u001a:bi>\u0014(BA\u0014\u000e\u0013\ta##\u0001\u0006v]\u0012,\'\u000f\\=j]\u001e\fa\u0001P5oSRtDC\u0001\u000f0\u0011\u0015i\"\u00011\u0001 \u0003%\u0019X-\\5dY>tW\rF\u0001\u001d\u0003!qW\r\u001f;Ti\u0016\u0004H#\u0001\u000b\u0002\u0011Q\u0014\u0018p\u00159mSR$\u0012\u0001\u0007"
    )
  ScalaInlineInfo: length = 0x7C (unknown attribute)
   01 00 00 18 00 6B 00 6C 00 00 62 00 63 00 00 1E
   00 2D 00 00 1E 00 1F 00 00 59 00 2D 00 00 5E 00
   2D 00 00 2C 00 2D 00 00 6F 00 70 00 00 6F 00 8D
   00 00 33 00 34 00 00 3B 00 3C 00 00 71 00 70 00
   00 69 00 42 00 00 69 00 6A 00 00 15 00 16 00 00
   15 00 26 00 00 50 00 26 00 00 55 00 26 00 00 25
   00 26 00 00 74 00 75 00 00 74 00 42 00 00 41 00
   42 00 00 48 00 42 00 00 4C 00 42 00
  ScalaSig: length = 0x3 (unknown attribute)
   05 02 00
