Classfile /Users/mw/Projects/slang-braindump/.jar/jar11/assemble/slang-braindump/assemble/content/scala/compat/java8/functionConverterImpls/AsJavaIntPredicate.class
  Last modified May 29, 2022; size 1767 bytes
  SHA-256 checksum 6e6454f5f303b88ad64188fa66a392534adcb7d5ffbf1b84fd3d20c3a8698f8b
  Compiled from "FunctionConverters.scala"
public class scala.compat.java8.functionConverterImpls.AsJavaIntPredicate implements java.util.function.IntPredicate
  minor version: 0
  major version: 52
  flags: (0x0021) ACC_PUBLIC, ACC_SUPER
  this_class: #2                          // scala/compat/java8/functionConverterImpls/AsJavaIntPredicate
  super_class: #4                         // java/lang/Object
  interfaces: 1, fields: 1, methods: 5, attributes: 4
Constant pool:
   #1 = Utf8               scala/compat/java8/functionConverterImpls/AsJavaIntPredicate
   #2 = Class              #1             // scala/compat/java8/functionConverterImpls/AsJavaIntPredicate
   #3 = Utf8               java/lang/Object
   #4 = Class              #3             // java/lang/Object
   #5 = Utf8               java/util/function/IntPredicate
   #6 = Class              #5             // java/util/function/IntPredicate
   #7 = Utf8               FunctionConverters.scala
   #8 = Utf8               Lscala/reflect/ScalaSignature;
   #9 = Utf8               bytes
  #10 = Utf8               \u0006\u0005M2A\u0001B\u0003\u0001\u001d!Aq\u0004\u0001B\u0001B\u0003%\u0001\u0005C\u0003+\u0001\u0011\u00051\u0006C\u00030\u0001\u0011\u0005\u0001G\u0001\nBg*\u000bg/Y%oiB\u0013X\rZ5dCR,\'B\u0001\u0004\b\u0003Y1WO\\2uS>t7i\u001c8wKJ$XM]%na2\u001c(B\u0001\u0005\n\u0003\u0015Q\u0017M^19\u0015\tQ1\"\u0001\u0004d_6\u0004\u0018\r\u001e\u0006\u0002\u0019\u0005)1oY1mC\u000e\u00011c\u0001\u0001\u0010/A\u0011\u0001#F\u0007\u0002#)\u0011!cE\u0001\u0005Y\u0006twMC\u0001\u0015\u0003\u0011Q\u0017M^1\n\u0005Y\t\"AB(cU\u0016\u001cG\u000f\u0005\u0002\u0019;5\t\u0011D\u0003\u0002\u001b7\u0005Aa-\u001e8di&|gN\u0003\u0002\u001d\'\u0005!Q\u000f^5m\u0013\tq\u0012D\u0001\u0007J]R\u0004&/\u001a3jG\u0006$X-\u0001\u0002tMB!\u0011E\t\u0013(\u001b\u0005Y\u0011BA\u0012\f\u0005%1UO\\2uS>t\u0017\u0007\u0005\u0002\"K%\u0011ae\u0003\u0002\u0004\u0013:$\bCA\u0011)\u0013\tI3BA\u0004C_>dW-\u00198\u0002\rqJg.\u001b;?)\tac\u0006\u0005\u0002.\u00015\tQ\u0001C\u0003 \u0005\u0001\u0007\u0001%\u0001\u0003uKN$HCA\u00142\u0011\u0015\u00114\u00011\u0001%\u0003\tA\u0018\u0007
  #11 = Utf8               sf
  #12 = Utf8               Lscala/Function1;
  #13 = Utf8               Lscala/Function1<Ljava/lang/Object;Ljava/lang/Object;>;
  #14 = Utf8               and
  #15 = Utf8               (Ljava/util/function/IntPredicate;)Ljava/util/function/IntPredicate;
  #16 = Utf8               x$1
  #17 = NameAndType        #14:#15        // and:(Ljava/util/function/IntPredicate;)Ljava/util/function/IntPredicate;
  #18 = InterfaceMethodref #6.#17         // java/util/function/IntPredicate.and:(Ljava/util/function/IntPredicate;)Ljava/util/function/IntPredicate;
  #19 = Utf8               this
  #20 = Utf8               Lscala/compat/java8/functionConverterImpls/AsJavaIntPredicate;
  #21 = Utf8               Ljava/util/function/IntPredicate;
  #22 = Utf8               negate
  #23 = Utf8               ()Ljava/util/function/IntPredicate;
  #24 = NameAndType        #22:#23        // negate:()Ljava/util/function/IntPredicate;
  #25 = InterfaceMethodref #6.#24         // java/util/function/IntPredicate.negate:()Ljava/util/function/IntPredicate;
  #26 = Utf8               or
  #27 = NameAndType        #26:#15        // or:(Ljava/util/function/IntPredicate;)Ljava/util/function/IntPredicate;
  #28 = InterfaceMethodref #6.#27         // java/util/function/IntPredicate.or:(Ljava/util/function/IntPredicate;)Ljava/util/function/IntPredicate;
  #29 = Utf8               test
  #30 = Utf8               (I)Z
  #31 = Utf8               x1
  #32 = NameAndType        #11:#12        // sf:Lscala/Function1;
  #33 = Fieldref           #2.#32         // scala/compat/java8/functionConverterImpls/AsJavaIntPredicate.sf:Lscala/Function1;
  #34 = Utf8               scala/Function1
  #35 = Class              #34            // scala/Function1
  #36 = Utf8               apply$mcZI$sp
  #37 = NameAndType        #36:#30        // apply$mcZI$sp:(I)Z
  #38 = InterfaceMethodref #35.#37        // scala/Function1.apply$mcZI$sp:(I)Z
  #39 = Utf8               I
  #40 = Utf8               <init>
  #41 = Utf8               (Lscala/Function1;)V
  #42 = Utf8               (Lscala/Function1<Ljava/lang/Object;Ljava/lang/Object;>;)V
  #43 = Utf8               ()V
  #44 = NameAndType        #40:#43        // "<init>":()V
  #45 = Methodref          #4.#44         // java/lang/Object."<init>":()V
  #46 = Utf8               Signature
  #47 = Utf8               Code
  #48 = Utf8               LineNumberTable
  #49 = Utf8               LocalVariableTable
  #50 = Utf8               MethodParameters
  #51 = Utf8               SourceFile
  #52 = Utf8               RuntimeVisibleAnnotations
  #53 = Utf8               ScalaInlineInfo
  #54 = Utf8               ScalaSig
{
  private final scala.Function1<java.lang.Object, java.lang.Object> sf;
    descriptor: Lscala/Function1;
    flags: (0x0012) ACC_PRIVATE, ACC_FINAL
    Signature: #13                          // Lscala/Function1<Ljava/lang/Object;Ljava/lang/Object;>;

  public java.util.function.IntPredicate and(java.util.function.IntPredicate);
    descriptor: (Ljava/util/function/IntPredicate;)Ljava/util/function/IntPredicate;
    flags: (0x0001) ACC_PUBLIC
    Code:
      stack=2, locals=2, args_size=2
         0: aload_0
         1: aload_1
         2: invokespecial #18                 // InterfaceMethod java/util/function/IntPredicate.and:(Ljava/util/function/IntPredicate;)Ljava/util/function/IntPredicate;
         5: areturn
      LineNumberTable:
        line 326: 0
      LocalVariableTable:
        Start  Length  Slot  Name   Signature
            0       6     0  this   Lscala/compat/java8/functionConverterImpls/AsJavaIntPredicate;
            0       6     1   x$1   Ljava/util/function/IntPredicate;
    MethodParameters:
      Name                           Flags
      x$1                            final

  public java.util.function.IntPredicate negate();
    descriptor: ()Ljava/util/function/IntPredicate;
    flags: (0x0001) ACC_PUBLIC
    Code:
      stack=1, locals=1, args_size=1
         0: aload_0
         1: invokespecial #25                 // InterfaceMethod java/util/function/IntPredicate.negate:()Ljava/util/function/IntPredicate;
         4: areturn
      LineNumberTable:
        line 326: 0
      LocalVariableTable:
        Start  Length  Slot  Name   Signature
            0       5     0  this   Lscala/compat/java8/functionConverterImpls/AsJavaIntPredicate;

  public java.util.function.IntPredicate or(java.util.function.IntPredicate);
    descriptor: (Ljava/util/function/IntPredicate;)Ljava/util/function/IntPredicate;
    flags: (0x0001) ACC_PUBLIC
    Code:
      stack=2, locals=2, args_size=2
         0: aload_0
         1: aload_1
         2: invokespecial #28                 // InterfaceMethod java/util/function/IntPredicate.or:(Ljava/util/function/IntPredicate;)Ljava/util/function/IntPredicate;
         5: areturn
      LineNumberTable:
        line 326: 0
      LocalVariableTable:
        Start  Length  Slot  Name   Signature
            0       6     0  this   Lscala/compat/java8/functionConverterImpls/AsJavaIntPredicate;
            0       6     1   x$1   Ljava/util/function/IntPredicate;
    MethodParameters:
      Name                           Flags
      x$1                            final

  public boolean test(int);
    descriptor: (I)Z
    flags: (0x0001) ACC_PUBLIC
    Code:
      stack=2, locals=2, args_size=2
         0: aload_0
         1: getfield      #33                 // Field sf:Lscala/Function1;
         4: iload_1
         5: invokeinterface #38,  2           // InterfaceMethod scala/Function1.apply$mcZI$sp:(I)Z
        10: ireturn
      LineNumberTable:
        line 327: 0
      LocalVariableTable:
        Start  Length  Slot  Name   Signature
            0      11     0  this   Lscala/compat/java8/functionConverterImpls/AsJavaIntPredicate;
            0      11     1    x1   I
    MethodParameters:
      Name                           Flags
      x1                             final

  public scala.compat.java8.functionConverterImpls.AsJavaIntPredicate(scala.Function1<java.lang.Object, java.lang.Object>);
    descriptor: (Lscala/Function1;)V
    flags: (0x0001) ACC_PUBLIC
    Code:
      stack=2, locals=2, args_size=2
         0: aload_0
         1: aload_1
         2: putfield      #33                 // Field sf:Lscala/Function1;
         5: aload_0
         6: invokespecial #45                 // Method java/lang/Object."<init>":()V
         9: return
      LineNumberTable:
        line 326: 0
      LocalVariableTable:
        Start  Length  Slot  Name   Signature
            0      10     0  this   Lscala/compat/java8/functionConverterImpls/AsJavaIntPredicate;
            0      10     1    sf   Lscala/Function1;
    Signature: #42                          // (Lscala/Function1<Ljava/lang/Object;Ljava/lang/Object;>;)V
    MethodParameters:
      Name                           Flags
      sf                             final
}
SourceFile: "FunctionConverters.scala"
RuntimeVisibleAnnotations:
  0: #8(#9=s#10)
    scala.reflect.ScalaSignature(
      bytes="\u0006\u0005M2A\u0001B\u0003\u0001\u001d!Aq\u0004\u0001B\u0001B\u0003%\u0001\u0005C\u0003+\u0001\u0011\u00051\u0006C\u00030\u0001\u0011\u0005\u0001G\u0001\nBg*\u000bg/Y%oiB\u0013X\rZ5dCR,\'B\u0001\u0004\b\u0003Y1WO\\2uS>t7i\u001c8wKJ$XM]%na2\u001c(B\u0001\u0005\n\u0003\u0015Q\u0017M^19\u0015\tQ1\"\u0001\u0004d_6\u0004\u0018\r\u001e\u0006\u0002\u0019\u0005)1oY1mC\u000e\u00011c\u0001\u0001\u0010/A\u0011\u0001#F\u0007\u0002#)\u0011!cE\u0001\u0005Y\u0006twMC\u0001\u0015\u0003\u0011Q\u0017M^1\n\u0005Y\t\"AB(cU\u0016\u001cG\u000f\u0005\u0002\u0019;5\t\u0011D\u0003\u0002\u001b7\u0005Aa-\u001e8di&|gN\u0003\u0002\u001d\'\u0005!Q\u000f^5m\u0013\tq\u0012D\u0001\u0007J]R\u0004&/\u001a3jG\u0006$X-\u0001\u0002tMB!\u0011E\t\u0013(\u001b\u0005Y\u0011BA\u0012\f\u0005%1UO\\2uS>t\u0017\u0007\u0005\u0002\"K%\u0011ae\u0003\u0002\u0004\u0013:$\bCA\u0011)\u0013\tI3BA\u0004C_>dW-\u00198\u0002\rqJg.\u001b;?)\tac\u0006\u0005\u0002.\u00015\tQ\u0001C\u0003 \u0005\u0001\u0007\u0001%\u0001\u0003uKN$HCA\u00142\u0011\u0015\u00114\u00011\u0001%\u0003\tA\u0018\u0007"
    )
  ScalaInlineInfo: length = 0x1D (unknown attribute)
   01 00 00 05 00 28 00 29 00 00 0E 00 0F 00 00 16
   00 17 00 00 1A 00 0F 00 00 1D 00 1E 00
  ScalaSig: length = 0x3 (unknown attribute)
   05 02 00
