Classfile /Users/mw/Projects/slang-braindump/.jar/jar11/assemble/slang-braindump/assemble/content/scala/compat/java8/functionConverterImpls/AsJavaLongFunction.class
  Last modified May 29, 2022; size 1569 bytes
  SHA-256 checksum 219e292e61b63083f82bcd98d43dbfed0545760b17647863ca81b90b3abc838b
  Compiled from "FunctionConverters.scala"
public class scala.compat.java8.functionConverterImpls.AsJavaLongFunction<R extends java.lang.Object> extends java.lang.Object implements java.util.function.LongFunction<R>
  minor version: 0
  major version: 52
  flags: (0x0021) ACC_PUBLIC, ACC_SUPER
  this_class: #2                          // scala/compat/java8/functionConverterImpls/AsJavaLongFunction
  super_class: #5                         // java/lang/Object
  interfaces: 1, fields: 1, methods: 2, attributes: 5
Constant pool:
   #1 = Utf8               scala/compat/java8/functionConverterImpls/AsJavaLongFunction
   #2 = Class              #1             // scala/compat/java8/functionConverterImpls/AsJavaLongFunction
   #3 = Utf8               <R:Ljava/lang/Object;>Ljava/lang/Object;Ljava/util/function/LongFunction<TR;>;
   #4 = Utf8               java/lang/Object
   #5 = Class              #4             // java/lang/Object
   #6 = Utf8               java/util/function/LongFunction
   #7 = Class              #6             // java/util/function/LongFunction
   #8 = Utf8               FunctionConverters.scala
   #9 = Utf8               Lscala/reflect/ScalaSignature;
  #10 = Utf8               bytes
  #11 = Utf8               \u0006\u0005q2A\u0001B\u0003\u0001\u001d!AA\u0006\u0001B\u0001B\u0003%Q\u0006C\u00034\u0001\u0011\u0005A\u0007C\u00039\u0001\u0011\u0005\u0011H\u0001\nBg*\u000bg/\u0019\'p]\u001e4UO\\2uS>t\'B\u0001\u0004\b\u0003Y1WO\\2uS>t7i\u001c8wKJ$XM]%na2\u001c(B\u0001\u0005\n\u0003\u0015Q\u0017M^19\u0015\tQ1\"\u0001\u0004d_6\u0004\u0018\r\u001e\u0006\u0002\u0019\u0005)1oY1mC\u000e\u0001QCA\b#\'\r\u0001\u0001\u0003\u0007\t\u0003#Yi\u0011A\u0005\u0006\u0003\'Q\tA\u0001\\1oO*\tQ#\u0001\u0003kCZ\f\u0017BA\f\u0013\u0005\u0019y%M[3diB\u0019\u0011D\b\u0011\u000e\u0003iQ!a\u0007\u000f\u0002\u0011\u0019,hn\u0019;j_:T!!\b\u000b\u0002\tU$\u0018\u000e\\\u0005\u0003?i\u0011A\u0002T8oO\u001a+hn\u0019;j_:\u0004\"!\t\u0012\r\u0001\u0011)1\u0005\u0001b\u0001I\t\t!+\u0005\u0002&SA\u0011aeJ\u0007\u0002\u0017%\u0011\u0001f\u0003\u0002\b\u001d>$\b.\u001b8h!\t1#&\u0003\u0002,\u0017\t\u0019\u0011I\\=\u0002\u0005M4\u0007\u0003\u0002\u0014/a\u0001J!aL\u0006\u0003\u0013\u0019+hn\u0019;j_:\f\u0004C\u0001\u00142\u0013\t\u00114B\u0001\u0003M_:<\u0017A\u0002\u001fj]&$h\b\u0006\u00026oA\u0019a\u0007\u0001\u0011\u000e\u0003\u0015AQ\u0001\f\u0002A\u00025\nQ!\u00199qYf$\"\u0001\t\u001e\t\u000bm\u001a\u0001\u0019\u0001\u0019\u0002\u0005a\f\u0004
  #12 = Utf8               sf
  #13 = Utf8               Lscala/Function1;
  #14 = Utf8               Lscala/Function1<Ljava/lang/Object;TR;>;
  #15 = Utf8               apply
  #16 = Utf8               (J)Ljava/lang/Object;
  #17 = Utf8               (J)TR;
  #18 = Utf8               x1
  #19 = NameAndType        #12:#13        // sf:Lscala/Function1;
  #20 = Fieldref           #2.#19         // scala/compat/java8/functionConverterImpls/AsJavaLongFunction.sf:Lscala/Function1;
  #21 = Utf8               scala/runtime/BoxesRunTime
  #22 = Class              #21            // scala/runtime/BoxesRunTime
  #23 = Utf8               boxToLong
  #24 = Utf8               (J)Ljava/lang/Long;
  #25 = NameAndType        #23:#24        // boxToLong:(J)Ljava/lang/Long;
  #26 = Methodref          #22.#25        // scala/runtime/BoxesRunTime.boxToLong:(J)Ljava/lang/Long;
  #27 = Utf8               scala/Function1
  #28 = Class              #27            // scala/Function1
  #29 = Utf8               (Ljava/lang/Object;)Ljava/lang/Object;
  #30 = NameAndType        #15:#29        // apply:(Ljava/lang/Object;)Ljava/lang/Object;
  #31 = InterfaceMethodref #28.#30        // scala/Function1.apply:(Ljava/lang/Object;)Ljava/lang/Object;
  #32 = Utf8               this
  #33 = Utf8               Lscala/compat/java8/functionConverterImpls/AsJavaLongFunction;
  #34 = Utf8               J
  #35 = Utf8               <init>
  #36 = Utf8               (Lscala/Function1;)V
  #37 = Utf8               (Lscala/Function1<Ljava/lang/Object;TR;>;)V
  #38 = Utf8               ()V
  #39 = NameAndType        #35:#38        // "<init>":()V
  #40 = Methodref          #5.#39         // java/lang/Object."<init>":()V
  #41 = Utf8               Signature
  #42 = Utf8               Code
  #43 = Utf8               LineNumberTable
  #44 = Utf8               LocalVariableTable
  #45 = Utf8               MethodParameters
  #46 = Utf8               SourceFile
  #47 = Utf8               RuntimeVisibleAnnotations
  #48 = Utf8               ScalaInlineInfo
  #49 = Utf8               ScalaSig
{
  private final scala.Function1<java.lang.Object, R> sf;
    descriptor: Lscala/Function1;
    flags: (0x0012) ACC_PRIVATE, ACC_FINAL
    Signature: #14                          // Lscala/Function1<Ljava/lang/Object;TR;>;

  public R apply(long);
    descriptor: (J)Ljava/lang/Object;
    flags: (0x0001) ACC_PUBLIC
    Code:
      stack=3, locals=3, args_size=2
         0: aload_0
         1: getfield      #20                 // Field sf:Lscala/Function1;
         4: lload_1
         5: invokestatic  #26                 // Method scala/runtime/BoxesRunTime.boxToLong:(J)Ljava/lang/Long;
         8: invokeinterface #31,  2           // InterfaceMethod scala/Function1.apply:(Ljava/lang/Object;)Ljava/lang/Object;
        13: areturn
      LineNumberTable:
        line 446: 0
      LocalVariableTable:
        Start  Length  Slot  Name   Signature
            0      14     0  this   Lscala/compat/java8/functionConverterImpls/AsJavaLongFunction;
            0      14     1    x1   J
    Signature: #17                          // (J)TR;
    MethodParameters:
      Name                           Flags
      x1                             final

  public scala.compat.java8.functionConverterImpls.AsJavaLongFunction(scala.Function1<java.lang.Object, R>);
    descriptor: (Lscala/Function1;)V
    flags: (0x0001) ACC_PUBLIC
    Code:
      stack=2, locals=2, args_size=2
         0: aload_0
         1: aload_1
         2: putfield      #20                 // Field sf:Lscala/Function1;
         5: aload_0
         6: invokespecial #40                 // Method java/lang/Object."<init>":()V
         9: return
      LineNumberTable:
        line 445: 0
      LocalVariableTable:
        Start  Length  Slot  Name   Signature
            0      10     0  this   Lscala/compat/java8/functionConverterImpls/AsJavaLongFunction;
            0      10     1    sf   Lscala/Function1;
    Signature: #37                          // (Lscala/Function1<Ljava/lang/Object;TR;>;)V
    MethodParameters:
      Name                           Flags
      sf                             final
}
Signature: #3                           // <R:Ljava/lang/Object;>Ljava/lang/Object;Ljava/util/function/LongFunction<TR;>;
SourceFile: "FunctionConverters.scala"
RuntimeVisibleAnnotations:
  0: #9(#10=s#11)
    scala.reflect.ScalaSignature(
      bytes="\u0006\u0005q2A\u0001B\u0003\u0001\u001d!AA\u0006\u0001B\u0001B\u0003%Q\u0006C\u00034\u0001\u0011\u0005A\u0007C\u00039\u0001\u0011\u0005\u0011H\u0001\nBg*\u000bg/\u0019\'p]\u001e4UO\\2uS>t\'B\u0001\u0004\b\u0003Y1WO\\2uS>t7i\u001c8wKJ$XM]%na2\u001c(B\u0001\u0005\n\u0003\u0015Q\u0017M^19\u0015\tQ1\"\u0001\u0004d_6\u0004\u0018\r\u001e\u0006\u0002\u0019\u0005)1oY1mC\u000e\u0001QCA\b#\'\r\u0001\u0001\u0003\u0007\t\u0003#Yi\u0011A\u0005\u0006\u0003\'Q\tA\u0001\\1oO*\tQ#\u0001\u0003kCZ\f\u0017BA\f\u0013\u0005\u0019y%M[3diB\u0019\u0011D\b\u0011\u000e\u0003iQ!a\u0007\u000f\u0002\u0011\u0019,hn\u0019;j_:T!!\b\u000b\u0002\tU$\u0018\u000e\\\u0005\u0003?i\u0011A\u0002T8oO\u001a+hn\u0019;j_:\u0004\"!\t\u0012\r\u0001\u0011)1\u0005\u0001b\u0001I\t\t!+\u0005\u0002&SA\u0011aeJ\u0007\u0002\u0017%\u0011\u0001f\u0003\u0002\b\u001d>$\b.\u001b8h!\t1#&\u0003\u0002,\u0017\t\u0019\u0011I\\=\u0002\u0005M4\u0007\u0003\u0002\u0014/a\u0001J!aL\u0006\u0003\u0013\u0019+hn\u0019;j_:\f\u0004C\u0001\u00142\u0013\t\u00114B\u0001\u0003M_:<\u0017A\u0002\u001fj]&$h\b\u0006\u00026oA\u0019a\u0007\u0001\u0011\u000e\u0003\u0015AQ\u0001\f\u0002A\u00025\nQ!\u00199qYf$\"\u0001\t\u001e\t\u000bm\u001a\u0001\u0019\u0001\u0019\u0002\u0005a\f\u0004"
    )
  ScalaInlineInfo: length = 0xE (unknown attribute)
   01 00 00 02 00 23 00 24 00 00 0F 00 10 00
  ScalaSig: length = 0x3 (unknown attribute)
   05 02 00
