Classfile /Users/mw/Projects/slang-braindump/.jar/jar11/assemble/slang-braindump/assemble/content/scala/compat/java8/functionConverterImpls/AsJavaFunction.class
  Last modified May 29, 2022; size 1995 bytes
  SHA-256 checksum 23330bcedf6142c47b533e7da1bd4d684298a63906cb99dd7d0ee86975470203
  Compiled from "FunctionConverters.scala"
public class scala.compat.java8.functionConverterImpls.AsJavaFunction<T extends java.lang.Object, R extends java.lang.Object> extends java.lang.Object implements java.util.function.Function<T, R>
  minor version: 0
  major version: 52
  flags: (0x0021) ACC_PUBLIC, ACC_SUPER
  this_class: #2                          // scala/compat/java8/functionConverterImpls/AsJavaFunction
  super_class: #5                         // java/lang/Object
  interfaces: 1, fields: 1, methods: 4, attributes: 5
Constant pool:
   #1 = Utf8               scala/compat/java8/functionConverterImpls/AsJavaFunction
   #2 = Class              #1             // scala/compat/java8/functionConverterImpls/AsJavaFunction
   #3 = Utf8               <T:Ljava/lang/Object;R:Ljava/lang/Object;>Ljava/lang/Object;Ljava/util/function/Function<TT;TR;>;
   #4 = Utf8               java/lang/Object
   #5 = Class              #4             // java/lang/Object
   #6 = Utf8               java/util/function/Function
   #7 = Class              #6             // java/util/function/Function
   #8 = Utf8               FunctionConverters.scala
   #9 = Utf8               Lscala/reflect/ScalaSignature;
  #10 = Utf8               bytes
  #11 = Utf8               \u0006\u0005q2A\u0001B\u0003\u0001\u001d!Aq\u0006\u0001B\u0001B\u0003%\u0001\u0007C\u00034\u0001\u0011\u0005A\u0007C\u00039\u0001\u0011\u0005\u0011H\u0001\bBg*\u000bg/\u0019$v]\u000e$\u0018n\u001c8\u000b\u0005\u00199\u0011A\u00064v]\u000e$\u0018n\u001c8D_:4XM\u001d;fe&k\u0007\u000f\\:\u000b\u0005!I\u0011!\u00026bm\u0006D$B\u0001\u0006\f\u0003\u0019\u0019w.\u001c9bi*\tA\"A\u0003tG\u0006d\u0017m\u0001\u0001\u0016\u0007=\u0011SfE\u0002\u0001!a\u0001\"!\u0005\f\u000e\u0003IQ!a\u0005\u000b\u0002\t1\fgn\u001a\u0006\u0002+\u0005!!.\u0019<b\u0013\t9\"C\u0001\u0004PE*,7\r\u001e\t\u00053y\u0001C&D\u0001\u001b\u0015\tYB$\u0001\u0005gk:\u001cG/[8o\u0015\tiB#\u0001\u0003vi&d\u0017BA\u0010\u001b\u0005!1UO\\2uS>t\u0007CA\u0011#\u0019\u0001!Qa\t\u0001C\u0002\u0011\u0012\u0011\u0001V\t\u0003K%\u0002\"AJ\u0014\u000e\u0003-I!\u0001K\u0006\u0003\u000f9{G\u000f[5oOB\u0011aEK\u0005\u0003W-\u00111!\u00118z!\t\tS\u0006B\u0003/\u0001\t\u0007AEA\u0001S\u0003\t\u0019h\r\u0005\u0003\'c\u0001b\u0013B\u0001\u001a\f\u0005%1UO\\2uS>t\u0017\'\u0001\u0004=S:LGO\u0010\u000b\u0003k]\u0002BA\u000e\u0001!Y5\tQ\u0001C\u00030\u0005\u0001\u0007\u0001\'A\u0003baBd\u0017\u0010\u0006\u0002-u!)1h\u0001a\u0001A\u0005\u0011\u00010\r
  #12 = Utf8               sf
  #13 = Utf8               Lscala/Function1;
  #14 = Utf8               Lscala/Function1<TT;TR;>;
  #15 = Utf8               compose
  #16 = Utf8               (Ljava/util/function/Function;)Ljava/util/function/Function;
  #17 = Utf8               <V:Ljava/lang/Object;>(Ljava/util/function/Function<-TV;+TT;>;)Ljava/util/function/Function<TV;TR;>;
  #18 = Utf8               x$1
  #19 = NameAndType        #15:#16        // compose:(Ljava/util/function/Function;)Ljava/util/function/Function;
  #20 = InterfaceMethodref #7.#19         // java/util/function/Function.compose:(Ljava/util/function/Function;)Ljava/util/function/Function;
  #21 = Utf8               this
  #22 = Utf8               Lscala/compat/java8/functionConverterImpls/AsJavaFunction;
  #23 = Utf8               Ljava/util/function/Function;
  #24 = Utf8               andThen
  #25 = Utf8               <V:Ljava/lang/Object;>(Ljava/util/function/Function<-TR;+TV;>;)Ljava/util/function/Function<TT;TV;>;
  #26 = NameAndType        #24:#16        // andThen:(Ljava/util/function/Function;)Ljava/util/function/Function;
  #27 = InterfaceMethodref #7.#26         // java/util/function/Function.andThen:(Ljava/util/function/Function;)Ljava/util/function/Function;
  #28 = Utf8               apply
  #29 = Utf8               (Ljava/lang/Object;)Ljava/lang/Object;
  #30 = Utf8               (TT;)TR;
  #31 = Utf8               x1
  #32 = NameAndType        #12:#13        // sf:Lscala/Function1;
  #33 = Fieldref           #2.#32         // scala/compat/java8/functionConverterImpls/AsJavaFunction.sf:Lscala/Function1;
  #34 = Utf8               scala/Function1
  #35 = Class              #34            // scala/Function1
  #36 = NameAndType        #28:#29        // apply:(Ljava/lang/Object;)Ljava/lang/Object;
  #37 = InterfaceMethodref #35.#36        // scala/Function1.apply:(Ljava/lang/Object;)Ljava/lang/Object;
  #38 = Utf8               Ljava/lang/Object;
  #39 = Utf8               <init>
  #40 = Utf8               (Lscala/Function1;)V
  #41 = Utf8               (Lscala/Function1<TT;TR;>;)V
  #42 = Utf8               ()V
  #43 = NameAndType        #39:#42        // "<init>":()V
  #44 = Methodref          #5.#43         // java/lang/Object."<init>":()V
  #45 = Utf8               Signature
  #46 = Utf8               Code
  #47 = Utf8               LineNumberTable
  #48 = Utf8               LocalVariableTable
  #49 = Utf8               MethodParameters
  #50 = Utf8               SourceFile
  #51 = Utf8               RuntimeVisibleAnnotations
  #52 = Utf8               ScalaInlineInfo
  #53 = Utf8               ScalaSig
{
  private final scala.Function1<T, R> sf;
    descriptor: Lscala/Function1;
    flags: (0x0012) ACC_PRIVATE, ACC_FINAL
    Signature: #14                          // Lscala/Function1<TT;TR;>;

  public <V extends java.lang.Object> java.util.function.Function<V, R> compose(java.util.function.Function<? super V, ? extends T>);
    descriptor: (Ljava/util/function/Function;)Ljava/util/function/Function;
    flags: (0x0001) ACC_PUBLIC
    Code:
      stack=2, locals=2, args_size=2
         0: aload_0
         1: aload_1
         2: invokespecial #20                 // InterfaceMethod java/util/function/Function.compose:(Ljava/util/function/Function;)Ljava/util/function/Function;
         5: areturn
      LineNumberTable:
        line 258: 0
      LocalVariableTable:
        Start  Length  Slot  Name   Signature
            0       6     0  this   Lscala/compat/java8/functionConverterImpls/AsJavaFunction;
            0       6     1   x$1   Ljava/util/function/Function;
    Signature: #17                          // <V:Ljava/lang/Object;>(Ljava/util/function/Function<-TV;+TT;>;)Ljava/util/function/Function<TV;TR;>;
    MethodParameters:
      Name                           Flags
      x$1                            final

  public <V extends java.lang.Object> java.util.function.Function<T, V> andThen(java.util.function.Function<? super R, ? extends V>);
    descriptor: (Ljava/util/function/Function;)Ljava/util/function/Function;
    flags: (0x0001) ACC_PUBLIC
    Code:
      stack=2, locals=2, args_size=2
         0: aload_0
         1: aload_1
         2: invokespecial #27                 // InterfaceMethod java/util/function/Function.andThen:(Ljava/util/function/Function;)Ljava/util/function/Function;
         5: areturn
      LineNumberTable:
        line 258: 0
      LocalVariableTable:
        Start  Length  Slot  Name   Signature
            0       6     0  this   Lscala/compat/java8/functionConverterImpls/AsJavaFunction;
            0       6     1   x$1   Ljava/util/function/Function;
    Signature: #25                          // <V:Ljava/lang/Object;>(Ljava/util/function/Function<-TR;+TV;>;)Ljava/util/function/Function<TT;TV;>;
    MethodParameters:
      Name                           Flags
      x$1                            final

  public R apply(T);
    descriptor: (Ljava/lang/Object;)Ljava/lang/Object;
    flags: (0x0001) ACC_PUBLIC
    Code:
      stack=2, locals=2, args_size=2
         0: aload_0
         1: getfield      #33                 // Field sf:Lscala/Function1;
         4: aload_1
         5: invokeinterface #37,  2           // InterfaceMethod scala/Function1.apply:(Ljava/lang/Object;)Ljava/lang/Object;
        10: areturn
      LineNumberTable:
        line 259: 0
      LocalVariableTable:
        Start  Length  Slot  Name   Signature
            0      11     0  this   Lscala/compat/java8/functionConverterImpls/AsJavaFunction;
            0      11     1    x1   Ljava/lang/Object;
    Signature: #30                          // (TT;)TR;
    MethodParameters:
      Name                           Flags
      x1                             final

  public scala.compat.java8.functionConverterImpls.AsJavaFunction(scala.Function1<T, R>);
    descriptor: (Lscala/Function1;)V
    flags: (0x0001) ACC_PUBLIC
    Code:
      stack=2, locals=2, args_size=2
         0: aload_0
         1: aload_1
         2: putfield      #33                 // Field sf:Lscala/Function1;
         5: aload_0
         6: invokespecial #44                 // Method java/lang/Object."<init>":()V
         9: return
      LineNumberTable:
        line 258: 0
      LocalVariableTable:
        Start  Length  Slot  Name   Signature
            0      10     0  this   Lscala/compat/java8/functionConverterImpls/AsJavaFunction;
            0      10     1    sf   Lscala/Function1;
    Signature: #41                          // (Lscala/Function1<TT;TR;>;)V
    MethodParameters:
      Name                           Flags
      sf                             final
}
Signature: #3                           // <T:Ljava/lang/Object;R:Ljava/lang/Object;>Ljava/lang/Object;Ljava/util/function/Function<TT;TR;>;
SourceFile: "FunctionConverters.scala"
RuntimeVisibleAnnotations:
  0: #9(#10=s#11)
    scala.reflect.ScalaSignature(
      bytes="\u0006\u0005q2A\u0001B\u0003\u0001\u001d!Aq\u0006\u0001B\u0001B\u0003%\u0001\u0007C\u00034\u0001\u0011\u0005A\u0007C\u00039\u0001\u0011\u0005\u0011H\u0001\bBg*\u000bg/\u0019$v]\u000e$\u0018n\u001c8\u000b\u0005\u00199\u0011A\u00064v]\u000e$\u0018n\u001c8D_:4XM\u001d;fe&k\u0007\u000f\\:\u000b\u0005!I\u0011!\u00026bm\u0006D$B\u0001\u0006\f\u0003\u0019\u0019w.\u001c9bi*\tA\"A\u0003tG\u0006d\u0017m\u0001\u0001\u0016\u0007=\u0011SfE\u0002\u0001!a\u0001\"!\u0005\f\u000e\u0003IQ!a\u0005\u000b\u0002\t1\fgn\u001a\u0006\u0002+\u0005!!.\u0019<b\u0013\t9\"C\u0001\u0004PE*,7\r\u001e\t\u00053y\u0001C&D\u0001\u001b\u0015\tYB$\u0001\u0005gk:\u001cG/[8o\u0015\tiB#\u0001\u0003vi&d\u0017BA\u0010\u001b\u0005!1UO\\2uS>t\u0007CA\u0011#\u0019\u0001!Qa\t\u0001C\u0002\u0011\u0012\u0011\u0001V\t\u0003K%\u0002\"AJ\u0014\u000e\u0003-I!\u0001K\u0006\u0003\u000f9{G\u000f[5oOB\u0011aEK\u0005\u0003W-\u00111!\u00118z!\t\tS\u0006B\u0003/\u0001\t\u0007AEA\u0001S\u0003\t\u0019h\r\u0005\u0003\'c\u0001b\u0013B\u0001\u001a\f\u0005%1UO\\2uS>t\u0017\'\u0001\u0004=S:LGO\u0010\u000b\u0003k]\u0002BA\u000e\u0001!Y5\tQ\u0001C\u00030\u0005\u0001\u0007\u0001\'A\u0003baBd\u0017\u0010\u0006\u0002-u!)1h\u0001a\u0001A\u0005\u0011\u00010\r"
    )
  ScalaInlineInfo: length = 0x18 (unknown attribute)
   01 00 00 04 00 27 00 28 00 00 18 00 10 00 00 1C
   00 1D 00 00 0F 00 10 00
  ScalaSig: length = 0x3 (unknown attribute)
   05 02 00
