Classfile /Users/mw/Projects/slang-braindump/.jar/jar11/assemble/slang-braindump/assemble/content/scala/compat/java8/functionConverterImpls/RichFunction1AsDoubleFunction.class
  Last modified May 29, 2022; size 3419 bytes
  SHA-256 checksum ea5e22f96963ccc0e98ebcb486d46ae9588940a5954d10881821eb7e3c742cab
  Compiled from "FunctionConverters.scala"
public final class scala.compat.java8.functionConverterImpls.RichFunction1AsDoubleFunction<R extends java.lang.Object> extends java.lang.Object
  minor version: 0
  major version: 52
  flags: (0x0031) ACC_PUBLIC, ACC_FINAL, ACC_SUPER
  this_class: #2                          // scala/compat/java8/functionConverterImpls/RichFunction1AsDoubleFunction
  super_class: #5                         // java/lang/Object
  interfaces: 0, fields: 1, methods: 8, attributes: 5
Constant pool:
   #1 = Utf8               scala/compat/java8/functionConverterImpls/RichFunction1AsDoubleFunction
   #2 = Class              #1             // scala/compat/java8/functionConverterImpls/RichFunction1AsDoubleFunction
   #3 = Utf8               <R:Ljava/lang/Object;>Ljava/lang/Object;
   #4 = Utf8               java/lang/Object
   #5 = Class              #4             // java/lang/Object
   #6 = Utf8               FunctionConverters.scala
   #7 = Utf8               Lscala/reflect/ScalaSignature;
   #8 = Utf8               bytes
   #9 = Utf8               \u0006\u0005Q4A!\u0004\b\u0003/!aQ\u0004\u0001C\u0001\u0002\u000b\u0015)\u0019!C\u0005=!I\u0001\u0007\u0001B\u0003\u0002\u0003\u0006Ia\b\u0005\u0006c\u0001!\tA\r\u0005\u0006o\u0001!\t\u0001\u000f\u0005\b\u000f\u0002\t\t\u0011\"\u0011I\u0011\u001da\u0005!!A\u0005B5;qa\u0015\b\u0002\u0002#\u0005AKB\u0004\u000e\u001d\u0005\u0005\t\u0012A+\t\u000bEBA\u0011A-\t\u000biCAQA.\t\u000f\u0011D\u0011\u0011!C\u0003K\"91\u000eCA\u0001\n\u000ba\'!\b*jG\"4UO\\2uS>t\u0017\'Q:E_V\u0014G.\u001a$v]\u000e$\u0018n\u001c8\u000b\u0005=\u0001\u0012A\u00064v]\u000e$\u0018n\u001c8D_:4XM\u001d;fe&k\u0007\u000f\\:\u000b\u0005E\u0011\u0012!\u00026bm\u0006D$BA\n\u0015\u0003\u0019\u0019w.\u001c9bi*\tQ#A\u0003tG\u0006d\u0017m\u0001\u0001\u0016\u0005a93C\u0001\u0001\u001a!\tQ2$D\u0001\u0015\u0013\taBC\u0001\u0004B]f4\u0016\r\\\u0001Tg\u000e\fG.\u0019\u0013d_6\u0004\u0018\r\u001e\u0013kCZ\f\u0007\b\n4v]\u000e$\u0018n\u001c8D_:4XM\u001d;fe&k\u0007\u000f\\:%%&\u001c\u0007NR;oGRLwN\\\u0019Bg\u0012{WO\u00197f\rVt7\r^5p]\u0012\"SO\u001c3fe2L\u0018N\\4\u0016\u0003}\u0001BA\u0007\u0011#K%\u0011\u0011\u0005\u0006\u0002\n\rVt7\r^5p]F\u0002\"AG\u0012\n\u0005\u0011\"\"A\u0002#pk\ndW\r\u0005\u0002\'O1\u0001A!\u0002\u0015\u0001\u0005\u0004I#!\u0001*\u0012\u0005)j\u0003C\u0001\u000e,\u0013\taCCA\u0004O_RD\u0017N\\4\u0011\u0005iq\u0013BA\u0018\u0015\u0005\r\te._\u0001Ug\u000e\fG.\u0019\u0013d_6\u0004\u0018\r\u001e\u0013kCZ\f\u0007\b\n4v]\u000e$\u0018n\u001c8D_:4XM\u001d;fe&k\u0007\u000f\\:%%&\u001c\u0007NR;oGRLwN\\\u0019Bg\u0012{WO\u00197f\rVt7\r^5p]\u0012\"SO\u001c3fe2L\u0018N\\4!\u0003\u0019a\u0014N\\5u}Q\u00111\'\u000e\t\u0004i\u0001)S\"\u0001\b\t\u000bY\u001a\u0001\u0019A\u0010\u0002\u0015UtG-\u001a:ms&tw-\u0001\u0004bg*\u000bg/Y\u000b\u0002sA\u0019!(Q\u0013\u000e\u0003mR!\u0001P\u001f\u0002\u0011\u0019,hn\u0019;j_:T!AP \u0002\tU$\u0018\u000e\u001c\u0006\u0002\u0001\u0006!!.\u0019<b\u0013\t\u00115H\u0001\bE_V\u0014G.\u001a$v]\u000e$\u0018n\u001c8)\u0005\u0011!\u0005C\u0001\u000eF\u0013\t1EC\u0001\u0004j]2Lg.Z\u0001\tQ\u0006\u001c\bnQ8eKR\t\u0011\n\u0005\u0002\u001b\u0015&\u00111\n\u0006\u0002\u0004\u0013:$\u0018AB3rk\u0006d7\u000f\u0006\u0002O#B\u0011!dT\u0005\u0003!R\u0011qAQ8pY\u0016\fg\u000eC\u0004S\r\u0005\u0005\t\u0019A\u0017\u0002\u0007a$\u0013\'A\u000fSS\u000eDg)\u001e8di&|g.M!t\t>,(\r\\3Gk:\u001cG/[8o!\t!\u0004b\u0005\u0002\t-B\u0011!dV\u0005\u00031R\u0011a!\u00118z%\u00164G#\u0001+\u0002!\u0005\u001c(*\u0019<bI\u0015DH/\u001a8tS>tWC\u0001/`)\ti\u0006\rE\u0002;\u0003z\u0003\"AJ0\u0005\u000b!R!\u0019A\u0015\t\u000b\u0005T\u0001\u0019\u00012\u0002\u000b\u0011\"\b.[:\u0011\u0007Q\u0002a\f\u000b\u0002\u000b\t\u0006\u0011\u0002.Y:i\u0007>$W\rJ3yi\u0016t7/[8o+\t1\'\u000e\u0006\u0002IO\")\u0011m\u0003a\u0001QB\u0019A\u0007A5\u0011\u0005\u0019RG!\u0002\u0015\f\u0005\u0004I\u0013\u0001E3rk\u0006d7\u000fJ3yi\u0016t7/[8o+\ti7\u000f\u0006\u0002oaR\u0011aj\u001c\u0005\b%2\t\t\u00111\u0001.\u0011\u0015\tG\u00021\u0001r!\r!\u0004A\u001d\t\u0003MM$Q\u0001\u000b\u0007C\u0002%\u0002
  #10 = Utf8               scala$compat$java8$functionConverterImpls$RichFunction1AsDoubleFunction$$underlying
  #11 = Utf8               Lscala/Function1;
  #12 = Utf8               Lscala/Function1<Ljava/lang/Object;TR;>;
  #13 = Utf8               equals$extension
  #14 = Utf8               (Lscala/Function1;Ljava/lang/Object;)Z
  #15 = Utf8               <R:Ljava/lang/Object;>(Lscala/Function1<Ljava/lang/Object;TR;>;Ljava/lang/Object;)Z
  #16 = Utf8               $this
  #17 = Utf8               x$1
  #18 = Utf8               scala/compat/java8/functionConverterImpls/RichFunction1AsDoubleFunction$
  #19 = Class              #18            // scala/compat/java8/functionConverterImpls/RichFunction1AsDoubleFunction$
  #20 = Utf8               MODULE$
  #21 = Utf8               Lscala/compat/java8/functionConverterImpls/RichFunction1AsDoubleFunction$;
  #22 = NameAndType        #20:#21        // MODULE$:Lscala/compat/java8/functionConverterImpls/RichFunction1AsDoubleFunction$;
  #23 = Fieldref           #19.#22        // scala/compat/java8/functionConverterImpls/RichFunction1AsDoubleFunction$.MODULE$:Lscala/compat/java8/functionConverterImpls/RichFunction1AsDoubleFunction$;
  #24 = NameAndType        #13:#14        // equals$extension:(Lscala/Function1;Ljava/lang/Object;)Z
  #25 = Methodref          #19.#24        // scala/compat/java8/functionConverterImpls/RichFunction1AsDoubleFunction$.equals$extension:(Lscala/Function1;Ljava/lang/Object;)Z
  #26 = Utf8               Ljava/lang/Object;
  #27 = Utf8               hashCode$extension
  #28 = Utf8               (Lscala/Function1;)I
  #29 = Utf8               <R:Ljava/lang/Object;>(Lscala/Function1<Ljava/lang/Object;TR;>;)I
  #30 = NameAndType        #27:#28        // hashCode$extension:(Lscala/Function1;)I
  #31 = Methodref          #19.#30        // scala/compat/java8/functionConverterImpls/RichFunction1AsDoubleFunction$.hashCode$extension:(Lscala/Function1;)I
  #32 = Utf8               asJava$extension
  #33 = Utf8               (Lscala/Function1;)Ljava/util/function/DoubleFunction;
  #34 = Utf8               <R:Ljava/lang/Object;>(Lscala/Function1<Ljava/lang/Object;TR;>;)Ljava/util/function/DoubleFunction<TR;>;
  #35 = NameAndType        #32:#33        // asJava$extension:(Lscala/Function1;)Ljava/util/function/DoubleFunction;
  #36 = Methodref          #19.#35        // scala/compat/java8/functionConverterImpls/RichFunction1AsDoubleFunction$.asJava$extension:(Lscala/Function1;)Ljava/util/function/DoubleFunction;
  #37 = Utf8               ()Lscala/Function1;
  #38 = Utf8               ()Lscala/Function1<Ljava/lang/Object;TR;>;
  #39 = NameAndType        #10:#11        // scala$compat$java8$functionConverterImpls$RichFunction1AsDoubleFunction$$underlying:Lscala/Function1;
  #40 = Fieldref           #2.#39         // scala/compat/java8/functionConverterImpls/RichFunction1AsDoubleFunction.scala$compat$java8$functionConverterImpls$RichFunction1AsDoubleFunction$$underlying:Lscala/Function1;
  #41 = Utf8               this
  #42 = Utf8               Lscala/compat/java8/functionConverterImpls/RichFunction1AsDoubleFunction;
  #43 = Utf8               asJava
  #44 = Utf8               ()Ljava/util/function/DoubleFunction;
  #45 = Utf8               ()Ljava/util/function/DoubleFunction<TR;>;
  #46 = NameAndType        #10:#37        // scala$compat$java8$functionConverterImpls$RichFunction1AsDoubleFunction$$underlying:()Lscala/Function1;
  #47 = Methodref          #2.#46         // scala/compat/java8/functionConverterImpls/RichFunction1AsDoubleFunction.scala$compat$java8$functionConverterImpls$RichFunction1AsDoubleFunction$$underlying:()Lscala/Function1;
  #48 = Utf8               hashCode
  #49 = Utf8               ()I
  #50 = Utf8               equals
  #51 = Utf8               (Ljava/lang/Object;)Z
  #52 = Utf8               <init>
  #53 = Utf8               (Lscala/Function1;)V
  #54 = Utf8               (Lscala/Function1<Ljava/lang/Object;TR;>;)V
  #55 = Utf8               underlying
  #56 = Utf8               ()V
  #57 = NameAndType        #52:#56        // "<init>":()V
  #58 = Methodref          #5.#57         // java/lang/Object."<init>":()V
  #59 = Utf8               Signature
  #60 = Utf8               Code
  #61 = Utf8               LocalVariableTable
  #62 = Utf8               MethodParameters
  #63 = Utf8               LineNumberTable
  #64 = Utf8               SourceFile
  #65 = Utf8               RuntimeVisibleAnnotations
  #66 = Utf8               ScalaInlineInfo
  #67 = Utf8               ScalaSig
{
  private final scala.Function1<java.lang.Object, R> scala$compat$java8$functionConverterImpls$RichFunction1AsDoubleFunction$$underlying;
    descriptor: Lscala/Function1;
    flags: (0x0012) ACC_PRIVATE, ACC_FINAL
    Signature: #12                          // Lscala/Function1<Ljava/lang/Object;TR;>;

  public static <R extends java.lang.Object> boolean equals$extension(scala.Function1<java.lang.Object, R>, java.lang.Object);
    descriptor: (Lscala/Function1;Ljava/lang/Object;)Z
    flags: (0x0009) ACC_PUBLIC, ACC_STATIC
    Code:
      stack=3, locals=2, args_size=2
         0: getstatic     #23                 // Field scala/compat/java8/functionConverterImpls/RichFunction1AsDoubleFunction$.MODULE$:Lscala/compat/java8/functionConverterImpls/RichFunction1AsDoubleFunction$;
         3: aload_0
         4: aload_1
         5: invokevirtual #25                 // Method scala/compat/java8/functionConverterImpls/RichFunction1AsDoubleFunction$.equals$extension:(Lscala/Function1;Ljava/lang/Object;)Z
         8: ireturn
      LocalVariableTable:
        Start  Length  Slot  Name   Signature
            0       9     0 $this   Lscala/Function1;
            0       9     1   x$1   Ljava/lang/Object;
    Signature: #15                          // <R:Ljava/lang/Object;>(Lscala/Function1<Ljava/lang/Object;TR;>;Ljava/lang/Object;)Z
    MethodParameters:
      Name                           Flags
      $this                          final
      x$1                            final

  public static <R extends java.lang.Object> int hashCode$extension(scala.Function1<java.lang.Object, R>);
    descriptor: (Lscala/Function1;)I
    flags: (0x0009) ACC_PUBLIC, ACC_STATIC
    Code:
      stack=2, locals=1, args_size=1
         0: getstatic     #23                 // Field scala/compat/java8/functionConverterImpls/RichFunction1AsDoubleFunction$.MODULE$:Lscala/compat/java8/functionConverterImpls/RichFunction1AsDoubleFunction$;
         3: aload_0
         4: invokevirtual #31                 // Method scala/compat/java8/functionConverterImpls/RichFunction1AsDoubleFunction$.hashCode$extension:(Lscala/Function1;)I
         7: ireturn
      LocalVariableTable:
        Start  Length  Slot  Name   Signature
            0       8     0 $this   Lscala/Function1;
    Signature: #29                          // <R:Ljava/lang/Object;>(Lscala/Function1<Ljava/lang/Object;TR;>;)I
    MethodParameters:
      Name                           Flags
      $this                          final

  public static <R extends java.lang.Object> java.util.function.DoubleFunction<R> asJava$extension(scala.Function1<java.lang.Object, R>);
    descriptor: (Lscala/Function1;)Ljava/util/function/DoubleFunction;
    flags: (0x0009) ACC_PUBLIC, ACC_STATIC
    Code:
      stack=2, locals=1, args_size=1
         0: getstatic     #23                 // Field scala/compat/java8/functionConverterImpls/RichFunction1AsDoubleFunction$.MODULE$:Lscala/compat/java8/functionConverterImpls/RichFunction1AsDoubleFunction$;
         3: aload_0
         4: invokevirtual #36                 // Method scala/compat/java8/functionConverterImpls/RichFunction1AsDoubleFunction$.asJava$extension:(Lscala/Function1;)Ljava/util/function/DoubleFunction;
         7: areturn
      LocalVariableTable:
        Start  Length  Slot  Name   Signature
            0       8     0 $this   Lscala/Function1;
    Signature: #34                          // <R:Ljava/lang/Object;>(Lscala/Function1<Ljava/lang/Object;TR;>;)Ljava/util/function/DoubleFunction<TR;>;
    MethodParameters:
      Name                           Flags
      $this                          final

  public scala.Function1<java.lang.Object, R> scala$compat$java8$functionConverterImpls$RichFunction1AsDoubleFunction$$underlying();
    descriptor: ()Lscala/Function1;
    flags: (0x0001) ACC_PUBLIC
    Code:
      stack=1, locals=1, args_size=1
         0: aload_0
         1: getfield      #40                 // Field scala$compat$java8$functionConverterImpls$RichFunction1AsDoubleFunction$$underlying:Lscala/Function1;
         4: areturn
      LineNumberTable:
        line 160: 0
      LocalVariableTable:
        Start  Length  Slot  Name   Signature
            0       5     0  this   Lscala/compat/java8/functionConverterImpls/RichFunction1AsDoubleFunction;
    Signature: #38                          // ()Lscala/Function1<Ljava/lang/Object;TR;>;

  public java.util.function.DoubleFunction<R> asJava();
    descriptor: ()Ljava/util/function/DoubleFunction;
    flags: (0x0001) ACC_PUBLIC
    Code:
      stack=2, locals=1, args_size=1
         0: getstatic     #23                 // Field scala/compat/java8/functionConverterImpls/RichFunction1AsDoubleFunction$.MODULE$:Lscala/compat/java8/functionConverterImpls/RichFunction1AsDoubleFunction$;
         3: aload_0
         4: invokevirtual #47                 // Method scala$compat$java8$functionConverterImpls$RichFunction1AsDoubleFunction$$underlying:()Lscala/Function1;
         7: invokevirtual #36                 // Method scala/compat/java8/functionConverterImpls/RichFunction1AsDoubleFunction$.asJava$extension:(Lscala/Function1;)Ljava/util/function/DoubleFunction;
        10: areturn
      LineNumberTable:
        line 161: 0
      LocalVariableTable:
        Start  Length  Slot  Name   Signature
            0      11     0  this   Lscala/compat/java8/functionConverterImpls/RichFunction1AsDoubleFunction;
    Signature: #45                          // ()Ljava/util/function/DoubleFunction<TR;>;

  public int hashCode();
    descriptor: ()I
    flags: (0x0001) ACC_PUBLIC
    Code:
      stack=2, locals=1, args_size=1
         0: getstatic     #23                 // Field scala/compat/java8/functionConverterImpls/RichFunction1AsDoubleFunction$.MODULE$:Lscala/compat/java8/functionConverterImpls/RichFunction1AsDoubleFunction$;
         3: aload_0
         4: invokevirtual #47                 // Method scala$compat$java8$functionConverterImpls$RichFunction1AsDoubleFunction$$underlying:()Lscala/Function1;
         7: invokevirtual #31                 // Method scala/compat/java8/functionConverterImpls/RichFunction1AsDoubleFunction$.hashCode$extension:(Lscala/Function1;)I
        10: ireturn
      LineNumberTable:
        line 160: 0
      LocalVariableTable:
        Start  Length  Slot  Name   Signature
            0      11     0  this   Lscala/compat/java8/functionConverterImpls/RichFunction1AsDoubleFunction;

  public boolean equals(java.lang.Object);
    descriptor: (Ljava/lang/Object;)Z
    flags: (0x0001) ACC_PUBLIC
    Code:
      stack=3, locals=2, args_size=2
         0: getstatic     #23                 // Field scala/compat/java8/functionConverterImpls/RichFunction1AsDoubleFunction$.MODULE$:Lscala/compat/java8/functionConverterImpls/RichFunction1AsDoubleFunction$;
         3: aload_0
         4: invokevirtual #47                 // Method scala$compat$java8$functionConverterImpls$RichFunction1AsDoubleFunction$$underlying:()Lscala/Function1;
         7: aload_1
         8: invokevirtual #25                 // Method scala/compat/java8/functionConverterImpls/RichFunction1AsDoubleFunction$.equals$extension:(Lscala/Function1;Ljava/lang/Object;)Z
        11: ireturn
      LineNumberTable:
        line 160: 0
      LocalVariableTable:
        Start  Length  Slot  Name   Signature
            0      12     0  this   Lscala/compat/java8/functionConverterImpls/RichFunction1AsDoubleFunction;
            0      12     1   x$1   Ljava/lang/Object;
    MethodParameters:
      Name                           Flags
      x$1                            final

  public scala.compat.java8.functionConverterImpls.RichFunction1AsDoubleFunction(scala.Function1<java.lang.Object, R>);
    descriptor: (Lscala/Function1;)V
    flags: (0x0001) ACC_PUBLIC
    Code:
      stack=2, locals=2, args_size=2
         0: aload_0
         1: aload_1
         2: putfield      #40                 // Field scala$compat$java8$functionConverterImpls$RichFunction1AsDoubleFunction$$underlying:Lscala/Function1;
         5: aload_0
         6: invokespecial #58                 // Method java/lang/Object."<init>":()V
         9: return
      LineNumberTable:
        line 160: 0
      LocalVariableTable:
        Start  Length  Slot  Name   Signature
            0      10     0  this   Lscala/compat/java8/functionConverterImpls/RichFunction1AsDoubleFunction;
            0      10     1 underlying   Lscala/Function1;
    Signature: #54                          // (Lscala/Function1<Ljava/lang/Object;TR;>;)V
    MethodParameters:
      Name                           Flags
      underlying                     final
}
Signature: #3                           // <R:Ljava/lang/Object;>Ljava/lang/Object;
SourceFile: "FunctionConverters.scala"
RuntimeVisibleAnnotations:
  0: #7(#8=s#9)
    scala.reflect.ScalaSignature(
      bytes="\u0006\u0005Q4A!\u0004\b\u0003/!aQ\u0004\u0001C\u0001\u0002\u000b\u0015)\u0019!C\u0005=!I\u0001\u0007\u0001B\u0003\u0002\u0003\u0006Ia\b\u0005\u0006c\u0001!\tA\r\u0005\u0006o\u0001!\t\u0001\u000f\u0005\b\u000f\u0002\t\t\u0011\"\u0011I\u0011\u001da\u0005!!A\u0005B5;qa\u0015\b\u0002\u0002#\u0005AKB\u0004\u000e\u001d\u0005\u0005\t\u0012A+\t\u000bEBA\u0011A-\t\u000biCAQA.\t\u000f\u0011D\u0011\u0011!C\u0003K\"91\u000eCA\u0001\n\u000ba\'!\b*jG\"4UO\\2uS>t\u0017\'Q:E_V\u0014G.\u001a$v]\u000e$\u0018n\u001c8\u000b\u0005=\u0001\u0012A\u00064v]\u000e$\u0018n\u001c8D_:4XM\u001d;fe&k\u0007\u000f\\:\u000b\u0005E\u0011\u0012!\u00026bm\u0006D$BA\n\u0015\u0003\u0019\u0019w.\u001c9bi*\tQ#A\u0003tG\u0006d\u0017m\u0001\u0001\u0016\u0005a93C\u0001\u0001\u001a!\tQ2$D\u0001\u0015\u0013\taBC\u0001\u0004B]f4\u0016\r\\\u0001Tg\u000e\fG.\u0019\u0013d_6\u0004\u0018\r\u001e\u0013kCZ\f\u0007\b\n4v]\u000e$\u0018n\u001c8D_:4XM\u001d;fe&k\u0007\u000f\\:%%&\u001c\u0007NR;oGRLwN\\\u0019Bg\u0012{WO\u00197f\rVt7\r^5p]\u0012\"SO\u001c3fe2L\u0018N\\4\u0016\u0003}\u0001BA\u0007\u0011#K%\u0011\u0011\u0005\u0006\u0002\n\rVt7\r^5p]F\u0002\"AG\u0012\n\u0005\u0011\"\"A\u0002#pk\ndW\r\u0005\u0002\'O1\u0001A!\u0002\u0015\u0001\u0005\u0004I#!\u0001*\u0012\u0005)j\u0003C\u0001\u000e,\u0013\taCCA\u0004O_RD\u0017N\\4\u0011\u0005iq\u0013BA\u0018\u0015\u0005\r\te._\u0001Ug\u000e\fG.\u0019\u0013d_6\u0004\u0018\r\u001e\u0013kCZ\f\u0007\b\n4v]\u000e$\u0018n\u001c8D_:4XM\u001d;fe&k\u0007\u000f\\:%%&\u001c\u0007NR;oGRLwN\\\u0019Bg\u0012{WO\u00197f\rVt7\r^5p]\u0012\"SO\u001c3fe2L\u0018N\\4!\u0003\u0019a\u0014N\\5u}Q\u00111\'\u000e\t\u0004i\u0001)S\"\u0001\b\t\u000bY\u001a\u0001\u0019A\u0010\u0002\u0015UtG-\u001a:ms&tw-\u0001\u0004bg*\u000bg/Y\u000b\u0002sA\u0019!(Q\u0013\u000e\u0003mR!\u0001P\u001f\u0002\u0011\u0019,hn\u0019;j_:T!AP \u0002\tU$\u0018\u000e\u001c\u0006\u0002\u0001\u0006!!.\u0019<b\u0013\t\u00115H\u0001\bE_V\u0014G.\u001a$v]\u000e$\u0018n\u001c8)\u0005\u0011!\u0005C\u0001\u000eF\u0013\t1EC\u0001\u0004j]2Lg.Z\u0001\tQ\u0006\u001c\bnQ8eKR\t\u0011\n\u0005\u0002\u001b\u0015&\u00111\n\u0006\u0002\u0004\u0013:$\u0018AB3rk\u0006d7\u000f\u0006\u0002O#B\u0011!dT\u0005\u0003!R\u0011qAQ8pY\u0016\fg\u000eC\u0004S\r\u0005\u0005\t\u0019A\u0017\u0002\u0007a$\u0013\'A\u000fSS\u000eDg)\u001e8di&|g.M!t\t>,(\r\\3Gk:\u001cG/[8o!\t!\u0004b\u0005\u0002\t-B\u0011!dV\u0005\u00031R\u0011a!\u00118z%\u00164G#\u0001+\u0002!\u0005\u001c(*\u0019<bI\u0015DH/\u001a8tS>tWC\u0001/`)\ti\u0006\rE\u0002;\u0003z\u0003\"AJ0\u0005\u000b!R!\u0019A\u0015\t\u000b\u0005T\u0001\u0019\u00012\u0002\u000b\u0011\"\b.[:\u0011\u0007Q\u0002a\f\u000b\u0002\u000b\t\u0006\u0011\u0002.Y:i\u0007>$W\rJ3yi\u0016t7/[8o+\t1\'\u000e\u0006\u0002IO\")\u0011m\u0003a\u0001QB\u0019A\u0007A5\u0011\u0005\u0019RG!\u0002\u0015\f\u0005\u0004I\u0013\u0001E3rk\u0006d7\u000fJ3yi\u0016t7/[8o+\ti7\u000f\u0006\u0002oaR\u0011aj\u001c\u0005\b%2\t\t\u00111\u0001.\u0011\u0015\tG\u00021\u0001r!\r!\u0004A\u001d\t\u0003MM$Q\u0001\u000b\u0007C\u0002%\u0002"
    )
  ScalaInlineInfo: length = 0x1D (unknown attribute)
   01 01 00 05 00 34 00 35 01 00 2B 00 2C 05 00 32
   00 33 01 00 30 00 31 01 00 0A 00 25 01
  ScalaSig: length = 0x3 (unknown attribute)
   05 02 00
