Classfile /Users/mw/Projects/slang-braindump/.jar/jar11/assemble/slang-braindump/assemble/content/scala/compat/java8/functionConverterImpls/RichFunction1AsToLongFunction.class
  Last modified May 29, 2022; size 3417 bytes
  SHA-256 checksum e9ceca1515d81b57cfa0d75ede64d1f18a147dc4ceca3aa2732175f2816f4c25
  Compiled from "FunctionConverters.scala"
public final class scala.compat.java8.functionConverterImpls.RichFunction1AsToLongFunction<T extends java.lang.Object> extends java.lang.Object
  minor version: 0
  major version: 52
  flags: (0x0031) ACC_PUBLIC, ACC_FINAL, ACC_SUPER
  this_class: #2                          // scala/compat/java8/functionConverterImpls/RichFunction1AsToLongFunction
  super_class: #5                         // java/lang/Object
  interfaces: 0, fields: 1, methods: 8, attributes: 5
Constant pool:
   #1 = Utf8               scala/compat/java8/functionConverterImpls/RichFunction1AsToLongFunction
   #2 = Class              #1             // scala/compat/java8/functionConverterImpls/RichFunction1AsToLongFunction
   #3 = Utf8               <T:Ljava/lang/Object;>Ljava/lang/Object;
   #4 = Utf8               java/lang/Object
   #5 = Class              #4             // java/lang/Object
   #6 = Utf8               FunctionConverters.scala
   #7 = Utf8               Lscala/reflect/ScalaSignature;
   #8 = Utf8               bytes
   #9 = Utf8               \u0006\u0005Q4A!\u0004\b\u0003/!aQ\u0004\u0001C\u0001\u0002\u000b\u0015)\u0019!C\u0005=!I\u0001\u0007\u0001B\u0003\u0002\u0003\u0006Ia\b\u0005\u0006c\u0001!\tA\r\u0005\u0006o\u0001!\t\u0001\u000f\u0005\b\u000f\u0002\t\t\u0011\"\u0011I\u0011\u001da\u0005!!A\u0005B5;qa\u0015\b\u0002\u0002#\u0005AKB\u0004\u000e\u001d\u0005\u0005\t\u0012A+\t\u000bEBA\u0011A-\t\u000biCAQA.\t\u000f\u0011D\u0011\u0011!C\u0003K\"91\u000eCA\u0001\n\u000ba\'!\b*jG\"4UO\\2uS>t\u0017\'Q:U_2{gn\u001a$v]\u000e$\u0018n\u001c8\u000b\u0005=\u0001\u0012A\u00064v]\u000e$\u0018n\u001c8D_:4XM\u001d;fe&k\u0007\u000f\\:\u000b\u0005E\u0011\u0012!\u00026bm\u0006D$BA\n\u0015\u0003\u0019\u0019w.\u001c9bi*\tQ#A\u0003tG\u0006d\u0017m\u0001\u0001\u0016\u0005a!3C\u0001\u0001\u001a!\tQ2$D\u0001\u0015\u0013\taBC\u0001\u0004B]f4\u0016\r\\\u0001Tg\u000e\fG.\u0019\u0013d_6\u0004\u0018\r\u001e\u0013kCZ\f\u0007\b\n4v]\u000e$\u0018n\u001c8D_:4XM\u001d;fe&k\u0007\u000f\\:%%&\u001c\u0007NR;oGRLwN\\\u0019BgR{Gj\u001c8h\rVt7\r^5p]\u0012\"SO\u001c3fe2L\u0018N\\4\u0016\u0003}\u0001BA\u0007\u0011#[%\u0011\u0011\u0005\u0006\u0002\n\rVt7\r^5p]F\u0002\"a\t\u0013\r\u0001\u0011)Q\u0005\u0001b\u0001M\t\tA+\u0005\u0002(UA\u0011!\u0004K\u0005\u0003SQ\u0011qAT8uQ&tw\r\u0005\u0002\u001bW%\u0011A\u0006\u0006\u0002\u0004\u0003:L\bC\u0001\u000e/\u0013\tyCC\u0001\u0003M_:<\u0017\u0001V:dC2\fGeY8na\u0006$HE[1wCb\"c-\u001e8di&|gnQ8om\u0016\u0014H/\u001a:J[Bd7\u000f\n*jG\"4UO\\2uS>t\u0017\'Q:U_2{gn\u001a$v]\u000e$\u0018n\u001c8%IUtG-\u001a:ms&tw\rI\u0001\u0007y%t\u0017\u000e\u001e \u0015\u0005M*\u0004c\u0001\u001b\u0001E5\ta\u0002C\u00037\u0007\u0001\u0007q$\u0001\u0006v]\u0012,\'\u000f\\=j]\u001e\fa!Y:KCZ\fW#A\u001d\u0011\u0007i\n%%D\u0001<\u0015\taT(\u0001\u0005gk:\u001cG/[8o\u0015\tqt(\u0001\u0003vi&d\'\"\u0001!\u0002\t)\fg/Y\u0005\u0003\u0005n\u0012a\u0002V8M_:<g)\u001e8di&|g\u000e\u000b\u0002\u0005\tB\u0011!$R\u0005\u0003\rR\u0011a!\u001b8mS:,\u0017\u0001\u00035bg\"\u001cu\u000eZ3\u0015\u0003%\u0003\"A\u0007&\n\u0005-#\"aA%oi\u00061Q-];bYN$\"AT)\u0011\u0005iy\u0015B\u0001)\u0015\u0005\u001d\u0011un\u001c7fC:DqA\u0015\u0004\u0002\u0002\u0003\u0007!&A\u0002yIE\nQDU5dQ\u001a+hn\u0019;j_:\f\u0014i\u001d+p\u0019>twMR;oGRLwN\u001c\t\u0003i!\u0019\"\u0001\u0003,\u0011\u0005i9\u0016B\u0001-\u0015\u0005\u0019\te.\u001f*fMR\tA+\u0001\tbg*\u000bg/\u0019\u0013fqR,gn]5p]V\u0011Al\u0018\u000b\u0003;\u0002\u00042AO!_!\t\u0019s\fB\u0003&\u0015\t\u0007a\u0005C\u0003b\u0015\u0001\u0007!-A\u0003%i\"L7\u000fE\u00025\u0001yC#A\u0003#\u0002%!\f7\u000f[\"pI\u0016$S\r\u001f;f]NLwN\\\u000b\u0003M*$\"\u0001S4\t\u000b\u0005\\\u0001\u0019\u00015\u0011\u0007Q\u0002\u0011\u000e\u0005\u0002$U\u0012)Qe\u0003b\u0001M\u0005\u0001R-];bYN$S\r\u001f;f]NLwN\\\u000b\u0003[N$\"A\u001c9\u0015\u00059{\u0007b\u0002*\r\u0003\u0003\u0005\rA\u000b\u0005\u0006C2\u0001\r!\u001d\t\u0004i\u0001\u0011\bCA\u0012t\t\u0015)CB1\u0001\'\u0001
  #10 = Utf8               scala$compat$java8$functionConverterImpls$RichFunction1AsToLongFunction$$underlying
  #11 = Utf8               Lscala/Function1;
  #12 = Utf8               Lscala/Function1<TT;Ljava/lang/Object;>;
  #13 = Utf8               equals$extension
  #14 = Utf8               (Lscala/Function1;Ljava/lang/Object;)Z
  #15 = Utf8               <T:Ljava/lang/Object;>(Lscala/Function1<TT;Ljava/lang/Object;>;Ljava/lang/Object;)Z
  #16 = Utf8               $this
  #17 = Utf8               x$1
  #18 = Utf8               scala/compat/java8/functionConverterImpls/RichFunction1AsToLongFunction$
  #19 = Class              #18            // scala/compat/java8/functionConverterImpls/RichFunction1AsToLongFunction$
  #20 = Utf8               MODULE$
  #21 = Utf8               Lscala/compat/java8/functionConverterImpls/RichFunction1AsToLongFunction$;
  #22 = NameAndType        #20:#21        // MODULE$:Lscala/compat/java8/functionConverterImpls/RichFunction1AsToLongFunction$;
  #23 = Fieldref           #19.#22        // scala/compat/java8/functionConverterImpls/RichFunction1AsToLongFunction$.MODULE$:Lscala/compat/java8/functionConverterImpls/RichFunction1AsToLongFunction$;
  #24 = NameAndType        #13:#14        // equals$extension:(Lscala/Function1;Ljava/lang/Object;)Z
  #25 = Methodref          #19.#24        // scala/compat/java8/functionConverterImpls/RichFunction1AsToLongFunction$.equals$extension:(Lscala/Function1;Ljava/lang/Object;)Z
  #26 = Utf8               Ljava/lang/Object;
  #27 = Utf8               hashCode$extension
  #28 = Utf8               (Lscala/Function1;)I
  #29 = Utf8               <T:Ljava/lang/Object;>(Lscala/Function1<TT;Ljava/lang/Object;>;)I
  #30 = NameAndType        #27:#28        // hashCode$extension:(Lscala/Function1;)I
  #31 = Methodref          #19.#30        // scala/compat/java8/functionConverterImpls/RichFunction1AsToLongFunction$.hashCode$extension:(Lscala/Function1;)I
  #32 = Utf8               asJava$extension
  #33 = Utf8               (Lscala/Function1;)Ljava/util/function/ToLongFunction;
  #34 = Utf8               <T:Ljava/lang/Object;>(Lscala/Function1<TT;Ljava/lang/Object;>;)Ljava/util/function/ToLongFunction<TT;>;
  #35 = NameAndType        #32:#33        // asJava$extension:(Lscala/Function1;)Ljava/util/function/ToLongFunction;
  #36 = Methodref          #19.#35        // scala/compat/java8/functionConverterImpls/RichFunction1AsToLongFunction$.asJava$extension:(Lscala/Function1;)Ljava/util/function/ToLongFunction;
  #37 = Utf8               ()Lscala/Function1;
  #38 = Utf8               ()Lscala/Function1<TT;Ljava/lang/Object;>;
  #39 = NameAndType        #10:#11        // scala$compat$java8$functionConverterImpls$RichFunction1AsToLongFunction$$underlying:Lscala/Function1;
  #40 = Fieldref           #2.#39         // scala/compat/java8/functionConverterImpls/RichFunction1AsToLongFunction.scala$compat$java8$functionConverterImpls$RichFunction1AsToLongFunction$$underlying:Lscala/Function1;
  #41 = Utf8               this
  #42 = Utf8               Lscala/compat/java8/functionConverterImpls/RichFunction1AsToLongFunction;
  #43 = Utf8               asJava
  #44 = Utf8               ()Ljava/util/function/ToLongFunction;
  #45 = Utf8               ()Ljava/util/function/ToLongFunction<TT;>;
  #46 = NameAndType        #10:#37        // scala$compat$java8$functionConverterImpls$RichFunction1AsToLongFunction$$underlying:()Lscala/Function1;
  #47 = Methodref          #2.#46         // scala/compat/java8/functionConverterImpls/RichFunction1AsToLongFunction.scala$compat$java8$functionConverterImpls$RichFunction1AsToLongFunction$$underlying:()Lscala/Function1;
  #48 = Utf8               hashCode
  #49 = Utf8               ()I
  #50 = Utf8               equals
  #51 = Utf8               (Ljava/lang/Object;)Z
  #52 = Utf8               <init>
  #53 = Utf8               (Lscala/Function1;)V
  #54 = Utf8               (Lscala/Function1<TT;Ljava/lang/Object;>;)V
  #55 = Utf8               underlying
  #56 = Utf8               ()V
  #57 = NameAndType        #52:#56        // "<init>":()V
  #58 = Methodref          #5.#57         // java/lang/Object."<init>":()V
  #59 = Utf8               Signature
  #60 = Utf8               Code
  #61 = Utf8               LocalVariableTable
  #62 = Utf8               MethodParameters
  #63 = Utf8               LineNumberTable
  #64 = Utf8               SourceFile
  #65 = Utf8               RuntimeVisibleAnnotations
  #66 = Utf8               ScalaInlineInfo
  #67 = Utf8               ScalaSig
{
  private final scala.Function1<T, java.lang.Object> scala$compat$java8$functionConverterImpls$RichFunction1AsToLongFunction$$underlying;
    descriptor: Lscala/Function1;
    flags: (0x0012) ACC_PRIVATE, ACC_FINAL
    Signature: #12                          // Lscala/Function1<TT;Ljava/lang/Object;>;

  public static <T extends java.lang.Object> boolean equals$extension(scala.Function1<T, java.lang.Object>, java.lang.Object);
    descriptor: (Lscala/Function1;Ljava/lang/Object;)Z
    flags: (0x0009) ACC_PUBLIC, ACC_STATIC
    Code:
      stack=3, locals=2, args_size=2
         0: getstatic     #23                 // Field scala/compat/java8/functionConverterImpls/RichFunction1AsToLongFunction$.MODULE$:Lscala/compat/java8/functionConverterImpls/RichFunction1AsToLongFunction$;
         3: aload_0
         4: aload_1
         5: invokevirtual #25                 // Method scala/compat/java8/functionConverterImpls/RichFunction1AsToLongFunction$.equals$extension:(Lscala/Function1;Ljava/lang/Object;)Z
         8: ireturn
      LocalVariableTable:
        Start  Length  Slot  Name   Signature
            0       9     0 $this   Lscala/Function1;
            0       9     1   x$1   Ljava/lang/Object;
    Signature: #15                          // <T:Ljava/lang/Object;>(Lscala/Function1<TT;Ljava/lang/Object;>;Ljava/lang/Object;)Z
    MethodParameters:
      Name                           Flags
      $this                          final
      x$1                            final

  public static <T extends java.lang.Object> int hashCode$extension(scala.Function1<T, java.lang.Object>);
    descriptor: (Lscala/Function1;)I
    flags: (0x0009) ACC_PUBLIC, ACC_STATIC
    Code:
      stack=2, locals=1, args_size=1
         0: getstatic     #23                 // Field scala/compat/java8/functionConverterImpls/RichFunction1AsToLongFunction$.MODULE$:Lscala/compat/java8/functionConverterImpls/RichFunction1AsToLongFunction$;
         3: aload_0
         4: invokevirtual #31                 // Method scala/compat/java8/functionConverterImpls/RichFunction1AsToLongFunction$.hashCode$extension:(Lscala/Function1;)I
         7: ireturn
      LocalVariableTable:
        Start  Length  Slot  Name   Signature
            0       8     0 $this   Lscala/Function1;
    Signature: #29                          // <T:Ljava/lang/Object;>(Lscala/Function1<TT;Ljava/lang/Object;>;)I
    MethodParameters:
      Name                           Flags
      $this                          final

  public static <T extends java.lang.Object> java.util.function.ToLongFunction<T> asJava$extension(scala.Function1<T, java.lang.Object>);
    descriptor: (Lscala/Function1;)Ljava/util/function/ToLongFunction;
    flags: (0x0009) ACC_PUBLIC, ACC_STATIC
    Code:
      stack=2, locals=1, args_size=1
         0: getstatic     #23                 // Field scala/compat/java8/functionConverterImpls/RichFunction1AsToLongFunction$.MODULE$:Lscala/compat/java8/functionConverterImpls/RichFunction1AsToLongFunction$;
         3: aload_0
         4: invokevirtual #36                 // Method scala/compat/java8/functionConverterImpls/RichFunction1AsToLongFunction$.asJava$extension:(Lscala/Function1;)Ljava/util/function/ToLongFunction;
         7: areturn
      LocalVariableTable:
        Start  Length  Slot  Name   Signature
            0       8     0 $this   Lscala/Function1;
    Signature: #34                          // <T:Ljava/lang/Object;>(Lscala/Function1<TT;Ljava/lang/Object;>;)Ljava/util/function/ToLongFunction<TT;>;
    MethodParameters:
      Name                           Flags
      $this                          final

  public scala.Function1<T, java.lang.Object> scala$compat$java8$functionConverterImpls$RichFunction1AsToLongFunction$$underlying();
    descriptor: ()Lscala/Function1;
    flags: (0x0001) ACC_PUBLIC
    Code:
      stack=1, locals=1, args_size=1
         0: aload_0
         1: getfield      #40                 // Field scala$compat$java8$functionConverterImpls$RichFunction1AsToLongFunction$$underlying:Lscala/Function1;
         4: areturn
      LineNumberTable:
        line 721: 0
      LocalVariableTable:
        Start  Length  Slot  Name   Signature
            0       5     0  this   Lscala/compat/java8/functionConverterImpls/RichFunction1AsToLongFunction;
    Signature: #38                          // ()Lscala/Function1<TT;Ljava/lang/Object;>;

  public java.util.function.ToLongFunction<T> asJava();
    descriptor: ()Ljava/util/function/ToLongFunction;
    flags: (0x0001) ACC_PUBLIC
    Code:
      stack=2, locals=1, args_size=1
         0: getstatic     #23                 // Field scala/compat/java8/functionConverterImpls/RichFunction1AsToLongFunction$.MODULE$:Lscala/compat/java8/functionConverterImpls/RichFunction1AsToLongFunction$;
         3: aload_0
         4: invokevirtual #47                 // Method scala$compat$java8$functionConverterImpls$RichFunction1AsToLongFunction$$underlying:()Lscala/Function1;
         7: invokevirtual #36                 // Method scala/compat/java8/functionConverterImpls/RichFunction1AsToLongFunction$.asJava$extension:(Lscala/Function1;)Ljava/util/function/ToLongFunction;
        10: areturn
      LineNumberTable:
        line 722: 0
      LocalVariableTable:
        Start  Length  Slot  Name   Signature
            0      11     0  this   Lscala/compat/java8/functionConverterImpls/RichFunction1AsToLongFunction;
    Signature: #45                          // ()Ljava/util/function/ToLongFunction<TT;>;

  public int hashCode();
    descriptor: ()I
    flags: (0x0001) ACC_PUBLIC
    Code:
      stack=2, locals=1, args_size=1
         0: getstatic     #23                 // Field scala/compat/java8/functionConverterImpls/RichFunction1AsToLongFunction$.MODULE$:Lscala/compat/java8/functionConverterImpls/RichFunction1AsToLongFunction$;
         3: aload_0
         4: invokevirtual #47                 // Method scala$compat$java8$functionConverterImpls$RichFunction1AsToLongFunction$$underlying:()Lscala/Function1;
         7: invokevirtual #31                 // Method scala/compat/java8/functionConverterImpls/RichFunction1AsToLongFunction$.hashCode$extension:(Lscala/Function1;)I
        10: ireturn
      LineNumberTable:
        line 721: 0
      LocalVariableTable:
        Start  Length  Slot  Name   Signature
            0      11     0  this   Lscala/compat/java8/functionConverterImpls/RichFunction1AsToLongFunction;

  public boolean equals(java.lang.Object);
    descriptor: (Ljava/lang/Object;)Z
    flags: (0x0001) ACC_PUBLIC
    Code:
      stack=3, locals=2, args_size=2
         0: getstatic     #23                 // Field scala/compat/java8/functionConverterImpls/RichFunction1AsToLongFunction$.MODULE$:Lscala/compat/java8/functionConverterImpls/RichFunction1AsToLongFunction$;
         3: aload_0
         4: invokevirtual #47                 // Method scala$compat$java8$functionConverterImpls$RichFunction1AsToLongFunction$$underlying:()Lscala/Function1;
         7: aload_1
         8: invokevirtual #25                 // Method scala/compat/java8/functionConverterImpls/RichFunction1AsToLongFunction$.equals$extension:(Lscala/Function1;Ljava/lang/Object;)Z
        11: ireturn
      LineNumberTable:
        line 721: 0
      LocalVariableTable:
        Start  Length  Slot  Name   Signature
            0      12     0  this   Lscala/compat/java8/functionConverterImpls/RichFunction1AsToLongFunction;
            0      12     1   x$1   Ljava/lang/Object;
    MethodParameters:
      Name                           Flags
      x$1                            final

  public scala.compat.java8.functionConverterImpls.RichFunction1AsToLongFunction(scala.Function1<T, java.lang.Object>);
    descriptor: (Lscala/Function1;)V
    flags: (0x0001) ACC_PUBLIC
    Code:
      stack=2, locals=2, args_size=2
         0: aload_0
         1: aload_1
         2: putfield      #40                 // Field scala$compat$java8$functionConverterImpls$RichFunction1AsToLongFunction$$underlying:Lscala/Function1;
         5: aload_0
         6: invokespecial #58                 // Method java/lang/Object."<init>":()V
         9: return
      LineNumberTable:
        line 721: 0
      LocalVariableTable:
        Start  Length  Slot  Name   Signature
            0      10     0  this   Lscala/compat/java8/functionConverterImpls/RichFunction1AsToLongFunction;
            0      10     1 underlying   Lscala/Function1;
    Signature: #54                          // (Lscala/Function1<TT;Ljava/lang/Object;>;)V
    MethodParameters:
      Name                           Flags
      underlying                     final
}
Signature: #3                           // <T:Ljava/lang/Object;>Ljava/lang/Object;
SourceFile: "FunctionConverters.scala"
RuntimeVisibleAnnotations:
  0: #7(#8=s#9)
    scala.reflect.ScalaSignature(
      bytes="\u0006\u0005Q4A!\u0004\b\u0003/!aQ\u0004\u0001C\u0001\u0002\u000b\u0015)\u0019!C\u0005=!I\u0001\u0007\u0001B\u0003\u0002\u0003\u0006Ia\b\u0005\u0006c\u0001!\tA\r\u0005\u0006o\u0001!\t\u0001\u000f\u0005\b\u000f\u0002\t\t\u0011\"\u0011I\u0011\u001da\u0005!!A\u0005B5;qa\u0015\b\u0002\u0002#\u0005AKB\u0004\u000e\u001d\u0005\u0005\t\u0012A+\t\u000bEBA\u0011A-\t\u000biCAQA.\t\u000f\u0011D\u0011\u0011!C\u0003K\"91\u000eCA\u0001\n\u000ba\'!\b*jG\"4UO\\2uS>t\u0017\'Q:U_2{gn\u001a$v]\u000e$\u0018n\u001c8\u000b\u0005=\u0001\u0012A\u00064v]\u000e$\u0018n\u001c8D_:4XM\u001d;fe&k\u0007\u000f\\:\u000b\u0005E\u0011\u0012!\u00026bm\u0006D$BA\n\u0015\u0003\u0019\u0019w.\u001c9bi*\tQ#A\u0003tG\u0006d\u0017m\u0001\u0001\u0016\u0005a!3C\u0001\u0001\u001a!\tQ2$D\u0001\u0015\u0013\taBC\u0001\u0004B]f4\u0016\r\\\u0001Tg\u000e\fG.\u0019\u0013d_6\u0004\u0018\r\u001e\u0013kCZ\f\u0007\b\n4v]\u000e$\u0018n\u001c8D_:4XM\u001d;fe&k\u0007\u000f\\:%%&\u001c\u0007NR;oGRLwN\\\u0019BgR{Gj\u001c8h\rVt7\r^5p]\u0012\"SO\u001c3fe2L\u0018N\\4\u0016\u0003}\u0001BA\u0007\u0011#[%\u0011\u0011\u0005\u0006\u0002\n\rVt7\r^5p]F\u0002\"a\t\u0013\r\u0001\u0011)Q\u0005\u0001b\u0001M\t\tA+\u0005\u0002(UA\u0011!\u0004K\u0005\u0003SQ\u0011qAT8uQ&tw\r\u0005\u0002\u001bW%\u0011A\u0006\u0006\u0002\u0004\u0003:L\bC\u0001\u000e/\u0013\tyCC\u0001\u0003M_:<\u0017\u0001V:dC2\fGeY8na\u0006$HE[1wCb\"c-\u001e8di&|gnQ8om\u0016\u0014H/\u001a:J[Bd7\u000f\n*jG\"4UO\\2uS>t\u0017\'Q:U_2{gn\u001a$v]\u000e$\u0018n\u001c8%IUtG-\u001a:ms&tw\rI\u0001\u0007y%t\u0017\u000e\u001e \u0015\u0005M*\u0004c\u0001\u001b\u0001E5\ta\u0002C\u00037\u0007\u0001\u0007q$\u0001\u0006v]\u0012,\'\u000f\\=j]\u001e\fa!Y:KCZ\fW#A\u001d\u0011\u0007i\n%%D\u0001<\u0015\taT(\u0001\u0005gk:\u001cG/[8o\u0015\tqt(\u0001\u0003vi&d\'\"\u0001!\u0002\t)\fg/Y\u0005\u0003\u0005n\u0012a\u0002V8M_:<g)\u001e8di&|g\u000e\u000b\u0002\u0005\tB\u0011!$R\u0005\u0003\rR\u0011a!\u001b8mS:,\u0017\u0001\u00035bg\"\u001cu\u000eZ3\u0015\u0003%\u0003\"A\u0007&\n\u0005-#\"aA%oi\u00061Q-];bYN$\"AT)\u0011\u0005iy\u0015B\u0001)\u0015\u0005\u001d\u0011un\u001c7fC:DqA\u0015\u0004\u0002\u0002\u0003\u0007!&A\u0002yIE\nQDU5dQ\u001a+hn\u0019;j_:\f\u0014i\u001d+p\u0019>twMR;oGRLwN\u001c\t\u0003i!\u0019\"\u0001\u0003,\u0011\u0005i9\u0016B\u0001-\u0015\u0005\u0019\te.\u001f*fMR\tA+\u0001\tbg*\u000bg/\u0019\u0013fqR,gn]5p]V\u0011Al\u0018\u000b\u0003;\u0002\u00042AO!_!\t\u0019s\fB\u0003&\u0015\t\u0007a\u0005C\u0003b\u0015\u0001\u0007!-A\u0003%i\"L7\u000fE\u00025\u0001yC#A\u0003#\u0002%!\f7\u000f[\"pI\u0016$S\r\u001f;f]NLwN\\\u000b\u0003M*$\"\u0001S4\t\u000b\u0005\\\u0001\u0019\u00015\u0011\u0007Q\u0002\u0011\u000e\u0005\u0002$U\u0012)Qe\u0003b\u0001M\u0005\u0001R-];bYN$S\r\u001f;f]NLwN\\\u000b\u0003[N$\"A\u001c9\u0015\u00059{\u0007b\u0002*\r\u0003\u0003\u0005\rA\u000b\u0005\u0006C2\u0001\r!\u001d\t\u0004i\u0001\u0011\bCA\u0012t\t\u0015)CB1\u0001\'\u0001"
    )
  ScalaInlineInfo: length = 0x1D (unknown attribute)
   01 01 00 05 00 34 00 35 01 00 2B 00 2C 05 00 32
   00 33 01 00 30 00 31 01 00 0A 00 25 01
  ScalaSig: length = 0x3 (unknown attribute)
   05 02 00
