Classfile /Users/mw/Projects/slang-braindump/.jar/jar11/assemble/slang-braindump/assemble/content/scala/compat/java8/functionConverterImpls/RichLongFunctionAsFunction1.class
  Last modified May 29, 2022; size 3449 bytes
  SHA-256 checksum dd79c2e71b90a2f4237c401c8defc1d2466e3cb22a414f6cecfd713ab27a1124
  Compiled from "FunctionConverters.scala"
public final class scala.compat.java8.functionConverterImpls.RichLongFunctionAsFunction1<R extends java.lang.Object> extends java.lang.Object
  minor version: 0
  major version: 52
  flags: (0x0031) ACC_PUBLIC, ACC_FINAL, ACC_SUPER
  this_class: #2                          // scala/compat/java8/functionConverterImpls/RichLongFunctionAsFunction1
  super_class: #5                         // java/lang/Object
  interfaces: 0, fields: 1, methods: 8, attributes: 5
Constant pool:
   #1 = Utf8               scala/compat/java8/functionConverterImpls/RichLongFunctionAsFunction1
   #2 = Class              #1             // scala/compat/java8/functionConverterImpls/RichLongFunctionAsFunction1
   #3 = Utf8               <R:Ljava/lang/Object;>Ljava/lang/Object;
   #4 = Utf8               java/lang/Object
   #5 = Class              #4             // java/lang/Object
   #6 = Utf8               FunctionConverters.scala
   #7 = Utf8               Lscala/reflect/ScalaSignature;
   #8 = Utf8               bytes
   #9 = Utf8               \u0006\u0005Q4A!\u0004\b\u0003/!aQ\u0004\u0001C\u0001\u0002\u000b\u0015)\u0019!C\u0005=!IA\u0007\u0001B\u0003\u0002\u0003\u0006Ia\b\u0005\u0006k\u0001!\tA\u000e\u0005\u0006w\u0001!\t\u0001\u0010\u0005\b\u000f\u0002\t\t\u0011\"\u0011I\u0011\u001da\u0005!!A\u0005B5;qa\u0015\b\u0002\u0002#\u0005AKB\u0004\u000e\u001d\u0005\u0005\t\u0012A+\t\u000bUBA\u0011A-\t\u000biCAQA.\t\u000f\u0011D\u0011\u0011!C\u0003K\"91\u000eCA\u0001\n\u000ba\'a\u0007*jG\"duN\\4Gk:\u001cG/[8o\u0003N4UO\\2uS>t\u0017G\u0003\u0002\u0010!\u00051b-\u001e8di&|gnQ8om\u0016\u0014H/\u001a:J[Bd7O\u0003\u0002\u0012%\u0005)!.\u0019<bq)\u00111\u0003F\u0001\u0007G>l\u0007/\u0019;\u000b\u0003U\tQa]2bY\u0006\u001c\u0001!\u0006\u0002\u0019WM\u0011\u0001!\u0007\t\u00035mi\u0011\u0001F\u0005\u00039Q\u0011a!\u00118z-\u0006d\u0017!U:dC2\fGeY8na\u0006$HE[1wCb\"c-\u001e8di&|gnQ8om\u0016\u0014H/\u001a:J[Bd7\u000f\n*jG\"duN\\4Gk:\u001cG/[8o\u0003N4UO\\2uS>t\u0017\u0007\n\u0013v]\u0012,\'\u000f\\=j]\u001e,\u0012a\b\t\u0004A\u001dJS\"A\u0011\u000b\u0005\t\u001a\u0013\u0001\u00034v]\u000e$\u0018n\u001c8\u000b\u0005\u0011*\u0013\u0001B;uS2T\u0011AJ\u0001\u0005U\u00064\u0018-\u0003\u0002)C\taAj\u001c8h\rVt7\r^5p]B\u0011!f\u000b\u0007\u0001\t\u0015a\u0003A1\u0001.\u0005\u0005\u0011\u0016C\u0001\u00182!\tQr&\u0003\u00021)\t9aj\u001c;iS:<\u0007C\u0001\u000e3\u0013\t\u0019DCA\u0002B]f\f!k]2bY\u0006$3m\\7qCR$#.\u0019<bq\u00112WO\\2uS>t7i\u001c8wKJ$XM]%na2\u001cHEU5dQ2{gn\u001a$v]\u000e$\u0018n\u001c8Bg\u001a+hn\u0019;j_:\fD\u0005J;oI\u0016\u0014H._5oO\u0002\na\u0001P5oSRtDCA\u001c:!\rA\u0004!K\u0007\u0002\u001d!)!h\u0001a\u0001?\u0005QQO\u001c3fe2L\u0018N\\4\u0002\u000f\u0005\u001c8kY1mCV\tQ\b\u0005\u0003\u001b}\u0001K\u0013BA \u0015\u0005%1UO\\2uS>t\u0017\u0007\u0005\u0002\u001b\u0003&\u0011!\t\u0006\u0002\u0005\u0019>tw\r\u000b\u0002\u0005\tB\u0011!$R\u0005\u0003\rR\u0011a!\u001b8mS:,\u0017\u0001\u00035bg\"\u001cu\u000eZ3\u0015\u0003%\u0003\"A\u0007&\n\u0005-#\"aA%oi\u00061Q-];bYN$\"AT)\u0011\u0005iy\u0015B\u0001)\u0015\u0005\u001d\u0011un\u001c7fC:DqA\u0015\u0004\u0002\u0002\u0003\u0007\u0011\'A\u0002yIE\n1DU5dQ2{gn\u001a$v]\u000e$\u0018n\u001c8Bg\u001a+hn\u0019;j_:\f\u0004C\u0001\u001d\t\'\tAa\u000b\u0005\u0002\u001b/&\u0011\u0001\f\u0006\u0002\u0007\u0003:L(+\u001a4\u0015\u0003Q\u000b\u0011#Y:TG\u0006d\u0017\rJ3yi\u0016t7/[8o+\tav\f\u0006\u0002^AB!!D\u0010!_!\tQs\fB\u0003-\u0015\t\u0007Q\u0006C\u0003b\u0015\u0001\u0007!-A\u0003%i\"L7\u000fE\u00029\u0001yC#A\u0003#\u0002%!\f7\u000f[\"pI\u0016$S\r\u001f;f]NLwN\\\u000b\u0003M*$\"\u0001S4\t\u000b\u0005\\\u0001\u0019\u00015\u0011\u0007a\u0002\u0011\u000e\u0005\u0002+U\u0012)Af\u0003b\u0001[\u0005\u0001R-];bYN$S\r\u001f;f]NLwN\\\u000b\u0003[N$\"A\u001c9\u0015\u00059{\u0007b\u0002*\r\u0003\u0003\u0005\r!\r\u0005\u0006C2\u0001\r!\u001d\t\u0004q\u0001\u0011\bC\u0001\u0016t\t\u0015aCB1\u0001.\u0001
  #10 = Utf8               scala$compat$java8$functionConverterImpls$RichLongFunctionAsFunction1$$underlying
  #11 = Utf8               Ljava/util/function/LongFunction;
  #12 = Utf8               Ljava/util/function/LongFunction<TR;>;
  #13 = Utf8               equals$extension
  #14 = Utf8               (Ljava/util/function/LongFunction;Ljava/lang/Object;)Z
  #15 = Utf8               <R:Ljava/lang/Object;>(Ljava/util/function/LongFunction<TR;>;Ljava/lang/Object;)Z
  #16 = Utf8               $this
  #17 = Utf8               x$1
  #18 = Utf8               scala/compat/java8/functionConverterImpls/RichLongFunctionAsFunction1$
  #19 = Class              #18            // scala/compat/java8/functionConverterImpls/RichLongFunctionAsFunction1$
  #20 = Utf8               MODULE$
  #21 = Utf8               Lscala/compat/java8/functionConverterImpls/RichLongFunctionAsFunction1$;
  #22 = NameAndType        #20:#21        // MODULE$:Lscala/compat/java8/functionConverterImpls/RichLongFunctionAsFunction1$;
  #23 = Fieldref           #19.#22        // scala/compat/java8/functionConverterImpls/RichLongFunctionAsFunction1$.MODULE$:Lscala/compat/java8/functionConverterImpls/RichLongFunctionAsFunction1$;
  #24 = NameAndType        #13:#14        // equals$extension:(Ljava/util/function/LongFunction;Ljava/lang/Object;)Z
  #25 = Methodref          #19.#24        // scala/compat/java8/functionConverterImpls/RichLongFunctionAsFunction1$.equals$extension:(Ljava/util/function/LongFunction;Ljava/lang/Object;)Z
  #26 = Utf8               Ljava/lang/Object;
  #27 = Utf8               hashCode$extension
  #28 = Utf8               (Ljava/util/function/LongFunction;)I
  #29 = Utf8               <R:Ljava/lang/Object;>(Ljava/util/function/LongFunction<TR;>;)I
  #30 = NameAndType        #27:#28        // hashCode$extension:(Ljava/util/function/LongFunction;)I
  #31 = Methodref          #19.#30        // scala/compat/java8/functionConverterImpls/RichLongFunctionAsFunction1$.hashCode$extension:(Ljava/util/function/LongFunction;)I
  #32 = Utf8               asScala$extension
  #33 = Utf8               (Ljava/util/function/LongFunction;)Lscala/Function1;
  #34 = Utf8               <R:Ljava/lang/Object;>(Ljava/util/function/LongFunction<TR;>;)Lscala/Function1<Ljava/lang/Object;TR;>;
  #35 = NameAndType        #32:#33        // asScala$extension:(Ljava/util/function/LongFunction;)Lscala/Function1;
  #36 = Methodref          #19.#35        // scala/compat/java8/functionConverterImpls/RichLongFunctionAsFunction1$.asScala$extension:(Ljava/util/function/LongFunction;)Lscala/Function1;
  #37 = Utf8               ()Ljava/util/function/LongFunction;
  #38 = Utf8               ()Ljava/util/function/LongFunction<TR;>;
  #39 = NameAndType        #10:#11        // scala$compat$java8$functionConverterImpls$RichLongFunctionAsFunction1$$underlying:Ljava/util/function/LongFunction;
  #40 = Fieldref           #2.#39         // scala/compat/java8/functionConverterImpls/RichLongFunctionAsFunction1.scala$compat$java8$functionConverterImpls$RichLongFunctionAsFunction1$$underlying:Ljava/util/function/LongFunction;
  #41 = Utf8               this
  #42 = Utf8               Lscala/compat/java8/functionConverterImpls/RichLongFunctionAsFunction1;
  #43 = Utf8               asScala
  #44 = Utf8               ()Lscala/Function1;
  #45 = Utf8               ()Lscala/Function1<Ljava/lang/Object;TR;>;
  #46 = NameAndType        #10:#37        // scala$compat$java8$functionConverterImpls$RichLongFunctionAsFunction1$$underlying:()Ljava/util/function/LongFunction;
  #47 = Methodref          #2.#46         // scala/compat/java8/functionConverterImpls/RichLongFunctionAsFunction1.scala$compat$java8$functionConverterImpls$RichLongFunctionAsFunction1$$underlying:()Ljava/util/function/LongFunction;
  #48 = Utf8               hashCode
  #49 = Utf8               ()I
  #50 = Utf8               equals
  #51 = Utf8               (Ljava/lang/Object;)Z
  #52 = Utf8               <init>
  #53 = Utf8               (Ljava/util/function/LongFunction;)V
  #54 = Utf8               (Ljava/util/function/LongFunction<TR;>;)V
  #55 = Utf8               underlying
  #56 = Utf8               ()V
  #57 = NameAndType        #52:#56        // "<init>":()V
  #58 = Methodref          #5.#57         // java/lang/Object."<init>":()V
  #59 = Utf8               Signature
  #60 = Utf8               Code
  #61 = Utf8               LocalVariableTable
  #62 = Utf8               MethodParameters
  #63 = Utf8               LineNumberTable
  #64 = Utf8               SourceFile
  #65 = Utf8               RuntimeVisibleAnnotations
  #66 = Utf8               ScalaInlineInfo
  #67 = Utf8               ScalaSig
{
  private final java.util.function.LongFunction<R> scala$compat$java8$functionConverterImpls$RichLongFunctionAsFunction1$$underlying;
    descriptor: Ljava/util/function/LongFunction;
    flags: (0x0012) ACC_PRIVATE, ACC_FINAL
    Signature: #12                          // Ljava/util/function/LongFunction<TR;>;

  public static <R extends java.lang.Object> boolean equals$extension(java.util.function.LongFunction<R>, java.lang.Object);
    descriptor: (Ljava/util/function/LongFunction;Ljava/lang/Object;)Z
    flags: (0x0009) ACC_PUBLIC, ACC_STATIC
    Code:
      stack=3, locals=2, args_size=2
         0: getstatic     #23                 // Field scala/compat/java8/functionConverterImpls/RichLongFunctionAsFunction1$.MODULE$:Lscala/compat/java8/functionConverterImpls/RichLongFunctionAsFunction1$;
         3: aload_0
         4: aload_1
         5: invokevirtual #25                 // Method scala/compat/java8/functionConverterImpls/RichLongFunctionAsFunction1$.equals$extension:(Ljava/util/function/LongFunction;Ljava/lang/Object;)Z
         8: ireturn
      LocalVariableTable:
        Start  Length  Slot  Name   Signature
            0       9     0 $this   Ljava/util/function/LongFunction;
            0       9     1   x$1   Ljava/lang/Object;
    Signature: #15                          // <R:Ljava/lang/Object;>(Ljava/util/function/LongFunction<TR;>;Ljava/lang/Object;)Z
    MethodParameters:
      Name                           Flags
      $this                          final
      x$1                            final

  public static <R extends java.lang.Object> int hashCode$extension(java.util.function.LongFunction<R>);
    descriptor: (Ljava/util/function/LongFunction;)I
    flags: (0x0009) ACC_PUBLIC, ACC_STATIC
    Code:
      stack=2, locals=1, args_size=1
         0: getstatic     #23                 // Field scala/compat/java8/functionConverterImpls/RichLongFunctionAsFunction1$.MODULE$:Lscala/compat/java8/functionConverterImpls/RichLongFunctionAsFunction1$;
         3: aload_0
         4: invokevirtual #31                 // Method scala/compat/java8/functionConverterImpls/RichLongFunctionAsFunction1$.hashCode$extension:(Ljava/util/function/LongFunction;)I
         7: ireturn
      LocalVariableTable:
        Start  Length  Slot  Name   Signature
            0       8     0 $this   Ljava/util/function/LongFunction;
    Signature: #29                          // <R:Ljava/lang/Object;>(Ljava/util/function/LongFunction<TR;>;)I
    MethodParameters:
      Name                           Flags
      $this                          final

  public static <R extends java.lang.Object> scala.Function1<java.lang.Object, R> asScala$extension(java.util.function.LongFunction<R>);
    descriptor: (Ljava/util/function/LongFunction;)Lscala/Function1;
    flags: (0x0009) ACC_PUBLIC, ACC_STATIC
    Code:
      stack=2, locals=1, args_size=1
         0: getstatic     #23                 // Field scala/compat/java8/functionConverterImpls/RichLongFunctionAsFunction1$.MODULE$:Lscala/compat/java8/functionConverterImpls/RichLongFunctionAsFunction1$;
         3: aload_0
         4: invokevirtual #36                 // Method scala/compat/java8/functionConverterImpls/RichLongFunctionAsFunction1$.asScala$extension:(Ljava/util/function/LongFunction;)Lscala/Function1;
         7: areturn
      LocalVariableTable:
        Start  Length  Slot  Name   Signature
            0       8     0 $this   Ljava/util/function/LongFunction;
    Signature: #34                          // <R:Ljava/lang/Object;>(Ljava/util/function/LongFunction<TR;>;)Lscala/Function1<Ljava/lang/Object;TR;>;
    MethodParameters:
      Name                           Flags
      $this                          final

  public java.util.function.LongFunction<R> scala$compat$java8$functionConverterImpls$RichLongFunctionAsFunction1$$underlying();
    descriptor: ()Ljava/util/function/LongFunction;
    flags: (0x0001) ACC_PUBLIC
    Code:
      stack=1, locals=1, args_size=1
         0: aload_0
         1: getfield      #40                 // Field scala$compat$java8$functionConverterImpls$RichLongFunctionAsFunction1$$underlying:Ljava/util/function/LongFunction;
         4: areturn
      LineNumberTable:
        line 441: 0
      LocalVariableTable:
        Start  Length  Slot  Name   Signature
            0       5     0  this   Lscala/compat/java8/functionConverterImpls/RichLongFunctionAsFunction1;
    Signature: #38                          // ()Ljava/util/function/LongFunction<TR;>;

  public scala.Function1<java.lang.Object, R> asScala();
    descriptor: ()Lscala/Function1;
    flags: (0x0001) ACC_PUBLIC
    Code:
      stack=2, locals=1, args_size=1
         0: getstatic     #23                 // Field scala/compat/java8/functionConverterImpls/RichLongFunctionAsFunction1$.MODULE$:Lscala/compat/java8/functionConverterImpls/RichLongFunctionAsFunction1$;
         3: aload_0
         4: invokevirtual #47                 // Method scala$compat$java8$functionConverterImpls$RichLongFunctionAsFunction1$$underlying:()Ljava/util/function/LongFunction;
         7: invokevirtual #36                 // Method scala/compat/java8/functionConverterImpls/RichLongFunctionAsFunction1$.asScala$extension:(Ljava/util/function/LongFunction;)Lscala/Function1;
        10: areturn
      LineNumberTable:
        line 442: 0
      LocalVariableTable:
        Start  Length  Slot  Name   Signature
            0      11     0  this   Lscala/compat/java8/functionConverterImpls/RichLongFunctionAsFunction1;
    Signature: #45                          // ()Lscala/Function1<Ljava/lang/Object;TR;>;

  public int hashCode();
    descriptor: ()I
    flags: (0x0001) ACC_PUBLIC
    Code:
      stack=2, locals=1, args_size=1
         0: getstatic     #23                 // Field scala/compat/java8/functionConverterImpls/RichLongFunctionAsFunction1$.MODULE$:Lscala/compat/java8/functionConverterImpls/RichLongFunctionAsFunction1$;
         3: aload_0
         4: invokevirtual #47                 // Method scala$compat$java8$functionConverterImpls$RichLongFunctionAsFunction1$$underlying:()Ljava/util/function/LongFunction;
         7: invokevirtual #31                 // Method scala/compat/java8/functionConverterImpls/RichLongFunctionAsFunction1$.hashCode$extension:(Ljava/util/function/LongFunction;)I
        10: ireturn
      LineNumberTable:
        line 441: 0
      LocalVariableTable:
        Start  Length  Slot  Name   Signature
            0      11     0  this   Lscala/compat/java8/functionConverterImpls/RichLongFunctionAsFunction1;

  public boolean equals(java.lang.Object);
    descriptor: (Ljava/lang/Object;)Z
    flags: (0x0001) ACC_PUBLIC
    Code:
      stack=3, locals=2, args_size=2
         0: getstatic     #23                 // Field scala/compat/java8/functionConverterImpls/RichLongFunctionAsFunction1$.MODULE$:Lscala/compat/java8/functionConverterImpls/RichLongFunctionAsFunction1$;
         3: aload_0
         4: invokevirtual #47                 // Method scala$compat$java8$functionConverterImpls$RichLongFunctionAsFunction1$$underlying:()Ljava/util/function/LongFunction;
         7: aload_1
         8: invokevirtual #25                 // Method scala/compat/java8/functionConverterImpls/RichLongFunctionAsFunction1$.equals$extension:(Ljava/util/function/LongFunction;Ljava/lang/Object;)Z
        11: ireturn
      LineNumberTable:
        line 441: 0
      LocalVariableTable:
        Start  Length  Slot  Name   Signature
            0      12     0  this   Lscala/compat/java8/functionConverterImpls/RichLongFunctionAsFunction1;
            0      12     1   x$1   Ljava/lang/Object;
    MethodParameters:
      Name                           Flags
      x$1                            final

  public scala.compat.java8.functionConverterImpls.RichLongFunctionAsFunction1(java.util.function.LongFunction<R>);
    descriptor: (Ljava/util/function/LongFunction;)V
    flags: (0x0001) ACC_PUBLIC
    Code:
      stack=2, locals=2, args_size=2
         0: aload_0
         1: aload_1
         2: putfield      #40                 // Field scala$compat$java8$functionConverterImpls$RichLongFunctionAsFunction1$$underlying:Ljava/util/function/LongFunction;
         5: aload_0
         6: invokespecial #58                 // Method java/lang/Object."<init>":()V
         9: return
      LineNumberTable:
        line 441: 0
      LocalVariableTable:
        Start  Length  Slot  Name   Signature
            0      10     0  this   Lscala/compat/java8/functionConverterImpls/RichLongFunctionAsFunction1;
            0      10     1 underlying   Ljava/util/function/LongFunction;
    Signature: #54                          // (Ljava/util/function/LongFunction<TR;>;)V
    MethodParameters:
      Name                           Flags
      underlying                     final
}
Signature: #3                           // <R:Ljava/lang/Object;>Ljava/lang/Object;
SourceFile: "FunctionConverters.scala"
RuntimeVisibleAnnotations:
  0: #7(#8=s#9)
    scala.reflect.ScalaSignature(
      bytes="\u0006\u0005Q4A!\u0004\b\u0003/!aQ\u0004\u0001C\u0001\u0002\u000b\u0015)\u0019!C\u0005=!IA\u0007\u0001B\u0003\u0002\u0003\u0006Ia\b\u0005\u0006k\u0001!\tA\u000e\u0005\u0006w\u0001!\t\u0001\u0010\u0005\b\u000f\u0002\t\t\u0011\"\u0011I\u0011\u001da\u0005!!A\u0005B5;qa\u0015\b\u0002\u0002#\u0005AKB\u0004\u000e\u001d\u0005\u0005\t\u0012A+\t\u000bUBA\u0011A-\t\u000biCAQA.\t\u000f\u0011D\u0011\u0011!C\u0003K\"91\u000eCA\u0001\n\u000ba\'a\u0007*jG\"duN\\4Gk:\u001cG/[8o\u0003N4UO\\2uS>t\u0017G\u0003\u0002\u0010!\u00051b-\u001e8di&|gnQ8om\u0016\u0014H/\u001a:J[Bd7O\u0003\u0002\u0012%\u0005)!.\u0019<bq)\u00111\u0003F\u0001\u0007G>l\u0007/\u0019;\u000b\u0003U\tQa]2bY\u0006\u001c\u0001!\u0006\u0002\u0019WM\u0011\u0001!\u0007\t\u00035mi\u0011\u0001F\u0005\u00039Q\u0011a!\u00118z-\u0006d\u0017!U:dC2\fGeY8na\u0006$HE[1wCb\"c-\u001e8di&|gnQ8om\u0016\u0014H/\u001a:J[Bd7\u000f\n*jG\"duN\\4Gk:\u001cG/[8o\u0003N4UO\\2uS>t\u0017\u0007\n\u0013v]\u0012,\'\u000f\\=j]\u001e,\u0012a\b\t\u0004A\u001dJS\"A\u0011\u000b\u0005\t\u001a\u0013\u0001\u00034v]\u000e$\u0018n\u001c8\u000b\u0005\u0011*\u0013\u0001B;uS2T\u0011AJ\u0001\u0005U\u00064\u0018-\u0003\u0002)C\taAj\u001c8h\rVt7\r^5p]B\u0011!f\u000b\u0007\u0001\t\u0015a\u0003A1\u0001.\u0005\u0005\u0011\u0016C\u0001\u00182!\tQr&\u0003\u00021)\t9aj\u001c;iS:<\u0007C\u0001\u000e3\u0013\t\u0019DCA\u0002B]f\f!k]2bY\u0006$3m\\7qCR$#.\u0019<bq\u00112WO\\2uS>t7i\u001c8wKJ$XM]%na2\u001cHEU5dQ2{gn\u001a$v]\u000e$\u0018n\u001c8Bg\u001a+hn\u0019;j_:\fD\u0005J;oI\u0016\u0014H._5oO\u0002\na\u0001P5oSRtDCA\u001c:!\rA\u0004!K\u0007\u0002\u001d!)!h\u0001a\u0001?\u0005QQO\u001c3fe2L\u0018N\\4\u0002\u000f\u0005\u001c8kY1mCV\tQ\b\u0005\u0003\u001b}\u0001K\u0013BA \u0015\u0005%1UO\\2uS>t\u0017\u0007\u0005\u0002\u001b\u0003&\u0011!\t\u0006\u0002\u0005\u0019>tw\r\u000b\u0002\u0005\tB\u0011!$R\u0005\u0003\rR\u0011a!\u001b8mS:,\u0017\u0001\u00035bg\"\u001cu\u000eZ3\u0015\u0003%\u0003\"A\u0007&\n\u0005-#\"aA%oi\u00061Q-];bYN$\"AT)\u0011\u0005iy\u0015B\u0001)\u0015\u0005\u001d\u0011un\u001c7fC:DqA\u0015\u0004\u0002\u0002\u0003\u0007\u0011\'A\u0002yIE\n1DU5dQ2{gn\u001a$v]\u000e$\u0018n\u001c8Bg\u001a+hn\u0019;j_:\f\u0004C\u0001\u001d\t\'\tAa\u000b\u0005\u0002\u001b/&\u0011\u0001\f\u0006\u0002\u0007\u0003:L(+\u001a4\u0015\u0003Q\u000b\u0011#Y:TG\u0006d\u0017\rJ3yi\u0016t7/[8o+\tav\f\u0006\u0002^AB!!D\u0010!_!\tQs\fB\u0003-\u0015\t\u0007Q\u0006C\u0003b\u0015\u0001\u0007!-A\u0003%i\"L7\u000fE\u00029\u0001yC#A\u0003#\u0002%!\f7\u000f[\"pI\u0016$S\r\u001f;f]NLwN\\\u000b\u0003M*$\"\u0001S4\t\u000b\u0005\\\u0001\u0019\u00015\u0011\u0007a\u0002\u0011\u000e\u0005\u0002+U\u0012)Af\u0003b\u0001[\u0005\u0001R-];bYN$S\r\u001f;f]NLwN\\\u000b\u0003[N$\"A\u001c9\u0015\u00059{\u0007b\u0002*\r\u0003\u0003\u0005\r!\r\u0005\u0006C2\u0001\r!\u001d\t\u0004q\u0001\u0011\bC\u0001\u0016t\t\u0015aCB1\u0001.\u0001"
    )
  ScalaInlineInfo: length = 0x1D (unknown attribute)
   01 01 00 05 00 34 00 35 01 00 2B 00 2C 05 00 32
   00 33 01 00 30 00 31 01 00 0A 00 25 01
  ScalaSig: length = 0x3 (unknown attribute)
   05 02 00
