Classfile /Users/mw/Projects/slang-braindump/.jar/jar11/assemble/slang-braindump/assemble/content/scala/compat/java8/functionConverterImpls/RichToDoubleBiFunctionAsFunction2.class
  Last modified May 29, 2022; size 3757 bytes
  SHA-256 checksum db772396d5f8764c992f3d5e3296c9f73f787efb29680f57f37a609273669fe6
  Compiled from "FunctionConverters.scala"
public final class scala.compat.java8.functionConverterImpls.RichToDoubleBiFunctionAsFunction2<T extends java.lang.Object, U extends java.lang.Object> extends java.lang.Object
  minor version: 0
  major version: 52
  flags: (0x0031) ACC_PUBLIC, ACC_FINAL, ACC_SUPER
  this_class: #2                          // scala/compat/java8/functionConverterImpls/RichToDoubleBiFunctionAsFunction2
  super_class: #5                         // java/lang/Object
  interfaces: 0, fields: 1, methods: 8, attributes: 5
Constant pool:
   #1 = Utf8               scala/compat/java8/functionConverterImpls/RichToDoubleBiFunctionAsFunction2
   #2 = Class              #1             // scala/compat/java8/functionConverterImpls/RichToDoubleBiFunctionAsFunction2
   #3 = Utf8               <T:Ljava/lang/Object;U:Ljava/lang/Object;>Ljava/lang/Object;
   #4 = Utf8               java/lang/Object
   #5 = Class              #4             // java/lang/Object
   #6 = Utf8               FunctionConverters.scala
   #7 = Utf8               Lscala/reflect/ScalaSignature;
   #8 = Utf8               bytes
   #9 = Utf8               \u0006\u0005u4A!\u0004\b\u0003/!aQ\u0004\u0001C\u0001\u0002\u000b\u0015)\u0019!C\u0005=!Iq\u0007\u0001B\u0003\u0002\u0003\u0006Ia\b\u0005\u0006q\u0001!\t!\u000f\u0005\u0006}\u0001!\ta\u0010\u0005\b\u0015\u0002\t\t\u0011\"\u0011L\u0011\u001dy\u0005!!A\u0005BA;qA\u0016\b\u0002\u0002#\u0005qKB\u0004\u000e\u001d\u0005\u0005\t\u0012\u0001-\t\u000baBA\u0011\u0001/\t\u000buCAQ\u00010\t\u000f%D\u0011\u0011!C\u0003U\"9!\u000fCA\u0001\n\u000b\u0019(!\t*jG\"$v\u000eR8vE2,\')\u001b$v]\u000e$\u0018n\u001c8Bg\u001a+hn\u0019;j_:\u0014$BA\b\u0011\u0003Y1WO\\2uS>t7i\u001c8wKJ$XM]%na2\u001c(BA\t\u0013\u0003\u0015Q\u0017M^19\u0015\t\u0019B#\u0001\u0004d_6\u0004\u0018\r\u001e\u0006\u0002+\u0005)1oY1mC\u000e\u0001Qc\u0001\r,kM\u0011\u0001!\u0007\t\u00035mi\u0011\u0001F\u0005\u00039Q\u0011a!\u00118z-\u0006d\u0017aV:dC2\fGeY8na\u0006$HE[1wCb\"c-\u001e8di&|gnQ8om\u0016\u0014H/\u001a:J[Bd7\u000f\n*jG\"$v\u000eR8vE2,\')\u001b$v]\u000e$\u0018n\u001c8Bg\u001a+hn\u0019;j_:\u0014D\u0005J;oI\u0016\u0014H._5oOV\tq\u0004\u0005\u0003!O%\"T\"A\u0011\u000b\u0005\t\u001a\u0013\u0001\u00034v]\u000e$\u0018n\u001c8\u000b\u0005\u0011*\u0013\u0001B;uS2T\u0011AJ\u0001\u0005U\u00064\u0018-\u0003\u0002)C\t\u0011Bk\u001c#pk\ndWMQ5Gk:\u001cG/[8o!\tQ3\u0006\u0004\u0001\u0005\u000b1\u0002!\u0019A\u0017\u0003\u0003Q\u000b\"AL\u0019\u0011\u0005iy\u0013B\u0001\u0019\u0015\u0005\u001dqu\u000e\u001e5j]\u001e\u0004\"A\u0007\u001a\n\u0005M\"\"aA!osB\u0011!&\u000e\u0003\u0006m\u0001\u0011\r!\f\u0002\u0002+\u0006A6oY1mC\u0012\u001aw.\u001c9bi\u0012R\u0017M^19I\u0019,hn\u0019;j_:\u001cuN\u001c<feR,\'/S7qYN$#+[2i)>$u.\u001e2mK\nKg)\u001e8di&|g.Q:Gk:\u001cG/[8oe\u0011\"SO\u001c3fe2L\u0018N\\4!\u0003\u0019a\u0014N\\5u}Q\u0011!\b\u0010\t\u0005w\u0001IC\'D\u0001\u000f\u0011\u0015i4\u00011\u0001 \u0003))h\u000eZ3sYfLgnZ\u0001\bCN\u001c6-\u00197b+\u0005\u0001\u0005#\u0002\u000eBSQ\u001a\u0015B\u0001\"\u0015\u0005%1UO\\2uS>t\'\u0007\u0005\u0002\u001b\t&\u0011Q\t\u0006\u0002\u0007\t>,(\r\\3)\u0005\u00119\u0005C\u0001\u000eI\u0013\tIEC\u0001\u0004j]2Lg.Z\u0001\tQ\u0006\u001c\bnQ8eKR\tA\n\u0005\u0002\u001b\u001b&\u0011a\n\u0006\u0002\u0004\u0013:$\u0018AB3rk\u0006d7\u000f\u0006\u0002R)B\u0011!DU\u0005\u0003\'R\u0011qAQ8pY\u0016\fg\u000eC\u0004V\r\u0005\u0005\t\u0019A\u0019\u0002\u0007a$\u0013\'A\u0011SS\u000eDGk\u001c#pk\ndWMQ5Gk:\u001cG/[8o\u0003N4UO\\2uS>t\'\u0007\u0005\u0002<\u0011M\u0011\u0001\"\u0017\t\u00035iK!a\u0017\u000b\u0003\r\u0005s\u0017PU3g)\u00059\u0016!E1t\'\u000e\fG.\u0019\u0013fqR,gn]5p]V\u0019qL\u00193\u0015\u0005\u0001,\u0007#\u0002\u000eBC\u000e\u001c\u0005C\u0001\u0016c\t\u0015a#B1\u0001.!\tQC\rB\u00037\u0015\t\u0007Q\u0006C\u0003g\u0015\u0001\u0007q-A\u0003%i\"L7\u000f\u0005\u0003<\u0001\u0005\u001c\u0007F\u0001\u0006H\u0003IA\u0017m\u001d5D_\u0012,G%\u001a=uK:\u001c\u0018n\u001c8\u0016\u0007-|\u0017\u000f\u0006\u0002LY\")am\u0003a\u0001[B!1\b\u00018q!\tQs\u000eB\u0003-\u0017\t\u0007Q\u0006\u0005\u0002+c\u0012)ag\u0003b\u0001[\u0005\u0001R-];bYN$S\r\u001f;f]NLwN\\\u000b\u0004ijdHCA;x)\t\tf\u000fC\u0004V\u0019\u0005\u0005\t\u0019A\u0019\t\u000b\u0019d\u0001\u0019\u0001=\u0011\tm\u0002\u0011p\u001f\t\u0003Ui$Q\u0001\f\u0007C\u00025\u0002\"A\u000b?\u0005\u000bYb!\u0019A\u0017
  #10 = Utf8               scala$compat$java8$functionConverterImpls$RichToDoubleBiFunctionAsFunction2$$underlying
  #11 = Utf8               Ljava/util/function/ToDoubleBiFunction;
  #12 = Utf8               Ljava/util/function/ToDoubleBiFunction<TT;TU;>;
  #13 = Utf8               equals$extension
  #14 = Utf8               (Ljava/util/function/ToDoubleBiFunction;Ljava/lang/Object;)Z
  #15 = Utf8               <T:Ljava/lang/Object;U:Ljava/lang/Object;>(Ljava/util/function/ToDoubleBiFunction<TT;TU;>;Ljava/lang/Object;)Z
  #16 = Utf8               $this
  #17 = Utf8               x$1
  #18 = Utf8               scala/compat/java8/functionConverterImpls/RichToDoubleBiFunctionAsFunction2$
  #19 = Class              #18            // scala/compat/java8/functionConverterImpls/RichToDoubleBiFunctionAsFunction2$
  #20 = Utf8               MODULE$
  #21 = Utf8               Lscala/compat/java8/functionConverterImpls/RichToDoubleBiFunctionAsFunction2$;
  #22 = NameAndType        #20:#21        // MODULE$:Lscala/compat/java8/functionConverterImpls/RichToDoubleBiFunctionAsFunction2$;
  #23 = Fieldref           #19.#22        // scala/compat/java8/functionConverterImpls/RichToDoubleBiFunctionAsFunction2$.MODULE$:Lscala/compat/java8/functionConverterImpls/RichToDoubleBiFunctionAsFunction2$;
  #24 = NameAndType        #13:#14        // equals$extension:(Ljava/util/function/ToDoubleBiFunction;Ljava/lang/Object;)Z
  #25 = Methodref          #19.#24        // scala/compat/java8/functionConverterImpls/RichToDoubleBiFunctionAsFunction2$.equals$extension:(Ljava/util/function/ToDoubleBiFunction;Ljava/lang/Object;)Z
  #26 = Utf8               Ljava/lang/Object;
  #27 = Utf8               hashCode$extension
  #28 = Utf8               (Ljava/util/function/ToDoubleBiFunction;)I
  #29 = Utf8               <T:Ljava/lang/Object;U:Ljava/lang/Object;>(Ljava/util/function/ToDoubleBiFunction<TT;TU;>;)I
  #30 = NameAndType        #27:#28        // hashCode$extension:(Ljava/util/function/ToDoubleBiFunction;)I
  #31 = Methodref          #19.#30        // scala/compat/java8/functionConverterImpls/RichToDoubleBiFunctionAsFunction2$.hashCode$extension:(Ljava/util/function/ToDoubleBiFunction;)I
  #32 = Utf8               asScala$extension
  #33 = Utf8               (Ljava/util/function/ToDoubleBiFunction;)Lscala/Function2;
  #34 = Utf8               <T:Ljava/lang/Object;U:Ljava/lang/Object;>(Ljava/util/function/ToDoubleBiFunction<TT;TU;>;)Lscala/Function2<TT;TU;Ljava/lang/Object;>;
  #35 = NameAndType        #32:#33        // asScala$extension:(Ljava/util/function/ToDoubleBiFunction;)Lscala/Function2;
  #36 = Methodref          #19.#35        // scala/compat/java8/functionConverterImpls/RichToDoubleBiFunctionAsFunction2$.asScala$extension:(Ljava/util/function/ToDoubleBiFunction;)Lscala/Function2;
  #37 = Utf8               ()Ljava/util/function/ToDoubleBiFunction;
  #38 = Utf8               ()Ljava/util/function/ToDoubleBiFunction<TT;TU;>;
  #39 = NameAndType        #10:#11        // scala$compat$java8$functionConverterImpls$RichToDoubleBiFunctionAsFunction2$$underlying:Ljava/util/function/ToDoubleBiFunction;
  #40 = Fieldref           #2.#39         // scala/compat/java8/functionConverterImpls/RichToDoubleBiFunctionAsFunction2.scala$compat$java8$functionConverterImpls$RichToDoubleBiFunctionAsFunction2$$underlying:Ljava/util/function/ToDoubleBiFunction;
  #41 = Utf8               this
  #42 = Utf8               Lscala/compat/java8/functionConverterImpls/RichToDoubleBiFunctionAsFunction2;
  #43 = Utf8               asScala
  #44 = Utf8               ()Lscala/Function2;
  #45 = Utf8               ()Lscala/Function2<TT;TU;Ljava/lang/Object;>;
  #46 = NameAndType        #10:#37        // scala$compat$java8$functionConverterImpls$RichToDoubleBiFunctionAsFunction2$$underlying:()Ljava/util/function/ToDoubleBiFunction;
  #47 = Methodref          #2.#46         // scala/compat/java8/functionConverterImpls/RichToDoubleBiFunctionAsFunction2.scala$compat$java8$functionConverterImpls$RichToDoubleBiFunctionAsFunction2$$underlying:()Ljava/util/function/ToDoubleBiFunction;
  #48 = Utf8               hashCode
  #49 = Utf8               ()I
  #50 = Utf8               equals
  #51 = Utf8               (Ljava/lang/Object;)Z
  #52 = Utf8               <init>
  #53 = Utf8               (Ljava/util/function/ToDoubleBiFunction;)V
  #54 = Utf8               (Ljava/util/function/ToDoubleBiFunction<TT;TU;>;)V
  #55 = Utf8               underlying
  #56 = Utf8               ()V
  #57 = NameAndType        #52:#56        // "<init>":()V
  #58 = Methodref          #5.#57         // java/lang/Object."<init>":()V
  #59 = Utf8               Signature
  #60 = Utf8               Code
  #61 = Utf8               LocalVariableTable
  #62 = Utf8               MethodParameters
  #63 = Utf8               LineNumberTable
  #64 = Utf8               SourceFile
  #65 = Utf8               RuntimeVisibleAnnotations
  #66 = Utf8               ScalaInlineInfo
  #67 = Utf8               ScalaSig
{
  private final java.util.function.ToDoubleBiFunction<T, U> scala$compat$java8$functionConverterImpls$RichToDoubleBiFunctionAsFunction2$$underlying;
    descriptor: Ljava/util/function/ToDoubleBiFunction;
    flags: (0x0012) ACC_PRIVATE, ACC_FINAL
    Signature: #12                          // Ljava/util/function/ToDoubleBiFunction<TT;TU;>;

  public static <T extends java.lang.Object, U extends java.lang.Object> boolean equals$extension(java.util.function.ToDoubleBiFunction<T, U>, java.lang.Object);
    descriptor: (Ljava/util/function/ToDoubleBiFunction;Ljava/lang/Object;)Z
    flags: (0x0009) ACC_PUBLIC, ACC_STATIC
    Code:
      stack=3, locals=2, args_size=2
         0: getstatic     #23                 // Field scala/compat/java8/functionConverterImpls/RichToDoubleBiFunctionAsFunction2$.MODULE$:Lscala/compat/java8/functionConverterImpls/RichToDoubleBiFunctionAsFunction2$;
         3: aload_0
         4: aload_1
         5: invokevirtual #25                 // Method scala/compat/java8/functionConverterImpls/RichToDoubleBiFunctionAsFunction2$.equals$extension:(Ljava/util/function/ToDoubleBiFunction;Ljava/lang/Object;)Z
         8: ireturn
      LocalVariableTable:
        Start  Length  Slot  Name   Signature
            0       9     0 $this   Ljava/util/function/ToDoubleBiFunction;
            0       9     1   x$1   Ljava/lang/Object;
    Signature: #15                          // <T:Ljava/lang/Object;U:Ljava/lang/Object;>(Ljava/util/function/ToDoubleBiFunction<TT;TU;>;Ljava/lang/Object;)Z
    MethodParameters:
      Name                           Flags
      $this                          final
      x$1                            final

  public static <T extends java.lang.Object, U extends java.lang.Object> int hashCode$extension(java.util.function.ToDoubleBiFunction<T, U>);
    descriptor: (Ljava/util/function/ToDoubleBiFunction;)I
    flags: (0x0009) ACC_PUBLIC, ACC_STATIC
    Code:
      stack=2, locals=1, args_size=1
         0: getstatic     #23                 // Field scala/compat/java8/functionConverterImpls/RichToDoubleBiFunctionAsFunction2$.MODULE$:Lscala/compat/java8/functionConverterImpls/RichToDoubleBiFunctionAsFunction2$;
         3: aload_0
         4: invokevirtual #31                 // Method scala/compat/java8/functionConverterImpls/RichToDoubleBiFunctionAsFunction2$.hashCode$extension:(Ljava/util/function/ToDoubleBiFunction;)I
         7: ireturn
      LocalVariableTable:
        Start  Length  Slot  Name   Signature
            0       8     0 $this   Ljava/util/function/ToDoubleBiFunction;
    Signature: #29                          // <T:Ljava/lang/Object;U:Ljava/lang/Object;>(Ljava/util/function/ToDoubleBiFunction<TT;TU;>;)I
    MethodParameters:
      Name                           Flags
      $this                          final

  public static <T extends java.lang.Object, U extends java.lang.Object> scala.Function2<T, U, java.lang.Object> asScala$extension(java.util.function.ToDoubleBiFunction<T, U>);
    descriptor: (Ljava/util/function/ToDoubleBiFunction;)Lscala/Function2;
    flags: (0x0009) ACC_PUBLIC, ACC_STATIC
    Code:
      stack=2, locals=1, args_size=1
         0: getstatic     #23                 // Field scala/compat/java8/functionConverterImpls/RichToDoubleBiFunctionAsFunction2$.MODULE$:Lscala/compat/java8/functionConverterImpls/RichToDoubleBiFunctionAsFunction2$;
         3: aload_0
         4: invokevirtual #36                 // Method scala/compat/java8/functionConverterImpls/RichToDoubleBiFunctionAsFunction2$.asScala$extension:(Ljava/util/function/ToDoubleBiFunction;)Lscala/Function2;
         7: areturn
      LocalVariableTable:
        Start  Length  Slot  Name   Signature
            0       8     0 $this   Ljava/util/function/ToDoubleBiFunction;
    Signature: #34                          // <T:Ljava/lang/Object;U:Ljava/lang/Object;>(Ljava/util/function/ToDoubleBiFunction<TT;TU;>;)Lscala/Function2<TT;TU;Ljava/lang/Object;>;
    MethodParameters:
      Name                           Flags
      $this                          final

  public java.util.function.ToDoubleBiFunction<T, U> scala$compat$java8$functionConverterImpls$RichToDoubleBiFunctionAsFunction2$$underlying();
    descriptor: ()Ljava/util/function/ToDoubleBiFunction;
    flags: (0x0001) ACC_PUBLIC
    Code:
      stack=1, locals=1, args_size=1
         0: aload_0
         1: getfield      #40                 // Field scala$compat$java8$functionConverterImpls$RichToDoubleBiFunctionAsFunction2$$underlying:Ljava/util/function/ToDoubleBiFunction;
         4: areturn
      LineNumberTable:
        line 628: 0
      LocalVariableTable:
        Start  Length  Slot  Name   Signature
            0       5     0  this   Lscala/compat/java8/functionConverterImpls/RichToDoubleBiFunctionAsFunction2;
    Signature: #38                          // ()Ljava/util/function/ToDoubleBiFunction<TT;TU;>;

  public scala.Function2<T, U, java.lang.Object> asScala();
    descriptor: ()Lscala/Function2;
    flags: (0x0001) ACC_PUBLIC
    Code:
      stack=2, locals=1, args_size=1
         0: getstatic     #23                 // Field scala/compat/java8/functionConverterImpls/RichToDoubleBiFunctionAsFunction2$.MODULE$:Lscala/compat/java8/functionConverterImpls/RichToDoubleBiFunctionAsFunction2$;
         3: aload_0
         4: invokevirtual #47                 // Method scala$compat$java8$functionConverterImpls$RichToDoubleBiFunctionAsFunction2$$underlying:()Ljava/util/function/ToDoubleBiFunction;
         7: invokevirtual #36                 // Method scala/compat/java8/functionConverterImpls/RichToDoubleBiFunctionAsFunction2$.asScala$extension:(Ljava/util/function/ToDoubleBiFunction;)Lscala/Function2;
        10: areturn
      LineNumberTable:
        line 629: 0
      LocalVariableTable:
        Start  Length  Slot  Name   Signature
            0      11     0  this   Lscala/compat/java8/functionConverterImpls/RichToDoubleBiFunctionAsFunction2;
    Signature: #45                          // ()Lscala/Function2<TT;TU;Ljava/lang/Object;>;

  public int hashCode();
    descriptor: ()I
    flags: (0x0001) ACC_PUBLIC
    Code:
      stack=2, locals=1, args_size=1
         0: getstatic     #23                 // Field scala/compat/java8/functionConverterImpls/RichToDoubleBiFunctionAsFunction2$.MODULE$:Lscala/compat/java8/functionConverterImpls/RichToDoubleBiFunctionAsFunction2$;
         3: aload_0
         4: invokevirtual #47                 // Method scala$compat$java8$functionConverterImpls$RichToDoubleBiFunctionAsFunction2$$underlying:()Ljava/util/function/ToDoubleBiFunction;
         7: invokevirtual #31                 // Method scala/compat/java8/functionConverterImpls/RichToDoubleBiFunctionAsFunction2$.hashCode$extension:(Ljava/util/function/ToDoubleBiFunction;)I
        10: ireturn
      LineNumberTable:
        line 628: 0
      LocalVariableTable:
        Start  Length  Slot  Name   Signature
            0      11     0  this   Lscala/compat/java8/functionConverterImpls/RichToDoubleBiFunctionAsFunction2;

  public boolean equals(java.lang.Object);
    descriptor: (Ljava/lang/Object;)Z
    flags: (0x0001) ACC_PUBLIC
    Code:
      stack=3, locals=2, args_size=2
         0: getstatic     #23                 // Field scala/compat/java8/functionConverterImpls/RichToDoubleBiFunctionAsFunction2$.MODULE$:Lscala/compat/java8/functionConverterImpls/RichToDoubleBiFunctionAsFunction2$;
         3: aload_0
         4: invokevirtual #47                 // Method scala$compat$java8$functionConverterImpls$RichToDoubleBiFunctionAsFunction2$$underlying:()Ljava/util/function/ToDoubleBiFunction;
         7: aload_1
         8: invokevirtual #25                 // Method scala/compat/java8/functionConverterImpls/RichToDoubleBiFunctionAsFunction2$.equals$extension:(Ljava/util/function/ToDoubleBiFunction;Ljava/lang/Object;)Z
        11: ireturn
      LineNumberTable:
        line 628: 0
      LocalVariableTable:
        Start  Length  Slot  Name   Signature
            0      12     0  this   Lscala/compat/java8/functionConverterImpls/RichToDoubleBiFunctionAsFunction2;
            0      12     1   x$1   Ljava/lang/Object;
    MethodParameters:
      Name                           Flags
      x$1                            final

  public scala.compat.java8.functionConverterImpls.RichToDoubleBiFunctionAsFunction2(java.util.function.ToDoubleBiFunction<T, U>);
    descriptor: (Ljava/util/function/ToDoubleBiFunction;)V
    flags: (0x0001) ACC_PUBLIC
    Code:
      stack=2, locals=2, args_size=2
         0: aload_0
         1: aload_1
         2: putfield      #40                 // Field scala$compat$java8$functionConverterImpls$RichToDoubleBiFunctionAsFunction2$$underlying:Ljava/util/function/ToDoubleBiFunction;
         5: aload_0
         6: invokespecial #58                 // Method java/lang/Object."<init>":()V
         9: return
      LineNumberTable:
        line 628: 0
      LocalVariableTable:
        Start  Length  Slot  Name   Signature
            0      10     0  this   Lscala/compat/java8/functionConverterImpls/RichToDoubleBiFunctionAsFunction2;
            0      10     1 underlying   Ljava/util/function/ToDoubleBiFunction;
    Signature: #54                          // (Ljava/util/function/ToDoubleBiFunction<TT;TU;>;)V
    MethodParameters:
      Name                           Flags
      underlying                     final
}
Signature: #3                           // <T:Ljava/lang/Object;U:Ljava/lang/Object;>Ljava/lang/Object;
SourceFile: "FunctionConverters.scala"
RuntimeVisibleAnnotations:
  0: #7(#8=s#9)
    scala.reflect.ScalaSignature(
      bytes="\u0006\u0005u4A!\u0004\b\u0003/!aQ\u0004\u0001C\u0001\u0002\u000b\u0015)\u0019!C\u0005=!Iq\u0007\u0001B\u0003\u0002\u0003\u0006Ia\b\u0005\u0006q\u0001!\t!\u000f\u0005\u0006}\u0001!\ta\u0010\u0005\b\u0015\u0002\t\t\u0011\"\u0011L\u0011\u001dy\u0005!!A\u0005BA;qA\u0016\b\u0002\u0002#\u0005qKB\u0004\u000e\u001d\u0005\u0005\t\u0012\u0001-\t\u000baBA\u0011\u0001/\t\u000buCAQ\u00010\t\u000f%D\u0011\u0011!C\u0003U\"9!\u000fCA\u0001\n\u000b\u0019(!\t*jG\"$v\u000eR8vE2,\')\u001b$v]\u000e$\u0018n\u001c8Bg\u001a+hn\u0019;j_:\u0014$BA\b\u0011\u0003Y1WO\\2uS>t7i\u001c8wKJ$XM]%na2\u001c(BA\t\u0013\u0003\u0015Q\u0017M^19\u0015\t\u0019B#\u0001\u0004d_6\u0004\u0018\r\u001e\u0006\u0002+\u0005)1oY1mC\u000e\u0001Qc\u0001\r,kM\u0011\u0001!\u0007\t\u00035mi\u0011\u0001F\u0005\u00039Q\u0011a!\u00118z-\u0006d\u0017aV:dC2\fGeY8na\u0006$HE[1wCb\"c-\u001e8di&|gnQ8om\u0016\u0014H/\u001a:J[Bd7\u000f\n*jG\"$v\u000eR8vE2,\')\u001b$v]\u000e$\u0018n\u001c8Bg\u001a+hn\u0019;j_:\u0014D\u0005J;oI\u0016\u0014H._5oOV\tq\u0004\u0005\u0003!O%\"T\"A\u0011\u000b\u0005\t\u001a\u0013\u0001\u00034v]\u000e$\u0018n\u001c8\u000b\u0005\u0011*\u0013\u0001B;uS2T\u0011AJ\u0001\u0005U\u00064\u0018-\u0003\u0002)C\t\u0011Bk\u001c#pk\ndWMQ5Gk:\u001cG/[8o!\tQ3\u0006\u0004\u0001\u0005\u000b1\u0002!\u0019A\u0017\u0003\u0003Q\u000b\"AL\u0019\u0011\u0005iy\u0013B\u0001\u0019\u0015\u0005\u001dqu\u000e\u001e5j]\u001e\u0004\"A\u0007\u001a\n\u0005M\"\"aA!osB\u0011!&\u000e\u0003\u0006m\u0001\u0011\r!\f\u0002\u0002+\u0006A6oY1mC\u0012\u001aw.\u001c9bi\u0012R\u0017M^19I\u0019,hn\u0019;j_:\u001cuN\u001c<feR,\'/S7qYN$#+[2i)>$u.\u001e2mK\nKg)\u001e8di&|g.Q:Gk:\u001cG/[8oe\u0011\"SO\u001c3fe2L\u0018N\\4!\u0003\u0019a\u0014N\\5u}Q\u0011!\b\u0010\t\u0005w\u0001IC\'D\u0001\u000f\u0011\u0015i4\u00011\u0001 \u0003))h\u000eZ3sYfLgnZ\u0001\bCN\u001c6-\u00197b+\u0005\u0001\u0005#\u0002\u000eBSQ\u001a\u0015B\u0001\"\u0015\u0005%1UO\\2uS>t\'\u0007\u0005\u0002\u001b\t&\u0011Q\t\u0006\u0002\u0007\t>,(\r\\3)\u0005\u00119\u0005C\u0001\u000eI\u0013\tIEC\u0001\u0004j]2Lg.Z\u0001\tQ\u0006\u001c\bnQ8eKR\tA\n\u0005\u0002\u001b\u001b&\u0011a\n\u0006\u0002\u0004\u0013:$\u0018AB3rk\u0006d7\u000f\u0006\u0002R)B\u0011!DU\u0005\u0003\'R\u0011qAQ8pY\u0016\fg\u000eC\u0004V\r\u0005\u0005\t\u0019A\u0019\u0002\u0007a$\u0013\'A\u0011SS\u000eDGk\u001c#pk\ndWMQ5Gk:\u001cG/[8o\u0003N4UO\\2uS>t\'\u0007\u0005\u0002<\u0011M\u0011\u0001\"\u0017\t\u00035iK!a\u0017\u000b\u0003\r\u0005s\u0017PU3g)\u00059\u0016!E1t\'\u000e\fG.\u0019\u0013fqR,gn]5p]V\u0019qL\u00193\u0015\u0005\u0001,\u0007#\u0002\u000eBC\u000e\u001c\u0005C\u0001\u0016c\t\u0015a#B1\u0001.!\tQC\rB\u00037\u0015\t\u0007Q\u0006C\u0003g\u0015\u0001\u0007q-A\u0003%i\"L7\u000f\u0005\u0003<\u0001\u0005\u001c\u0007F\u0001\u0006H\u0003IA\u0017m\u001d5D_\u0012,G%\u001a=uK:\u001c\u0018n\u001c8\u0016\u0007-|\u0017\u000f\u0006\u0002LY\")am\u0003a\u0001[B!1\b\u00018q!\tQs\u000eB\u0003-\u0017\t\u0007Q\u0006\u0005\u0002+c\u0012)ag\u0003b\u0001[\u0005\u0001R-];bYN$S\r\u001f;f]NLwN\\\u000b\u0004ijdHCA;x)\t\tf\u000fC\u0004V\u0019\u0005\u0005\t\u0019A\u0019\t\u000b\u0019d\u0001\u0019\u0001=\u0011\tm\u0002\u0011p\u001f\t\u0003Ui$Q\u0001\f\u0007C\u00025\u0002\"A\u000b?\u0005\u000bYb!\u0019A\u0017"
    )
  ScalaInlineInfo: length = 0x1D (unknown attribute)
   01 01 00 05 00 34 00 35 01 00 2B 00 2C 05 00 32
   00 33 01 00 30 00 31 01 00 0A 00 25 01
  ScalaSig: length = 0x3 (unknown attribute)
   05 02 00
