Classfile /Users/mw/Projects/slang-braindump/.jar/jar11/assemble/slang-braindump/assemble/content/scala/compat/java8/functionConverterImpls/RichFunction1AsDoublePredicate.class
  Last modified May 29, 2022; size 2964 bytes
  SHA-256 checksum 9f1621cdaed0a98b08806ac1354780437e2413a1adc8cd37346406919468dee3
  Compiled from "FunctionConverters.scala"
public final class scala.compat.java8.functionConverterImpls.RichFunction1AsDoublePredicate
  minor version: 0
  major version: 52
  flags: (0x0031) ACC_PUBLIC, ACC_FINAL, ACC_SUPER
  this_class: #2                          // scala/compat/java8/functionConverterImpls/RichFunction1AsDoublePredicate
  super_class: #4                         // java/lang/Object
  interfaces: 0, fields: 1, methods: 8, attributes: 4
Constant pool:
   #1 = Utf8               scala/compat/java8/functionConverterImpls/RichFunction1AsDoublePredicate
   #2 = Class              #1             // scala/compat/java8/functionConverterImpls/RichFunction1AsDoublePredicate
   #3 = Utf8               java/lang/Object
   #4 = Class              #3             // java/lang/Object
   #5 = Utf8               FunctionConverters.scala
   #6 = Utf8               Lscala/reflect/ScalaSignature;
   #7 = Utf8               bytes
   #8 = Utf8               \u0006\u0005y3A!\u0004\b\u0003/!aA\u0004\u0001C\u0001\u0002\u000b\u0015)\u0019!C\u0005;!Iq\u0005\u0001B\u0003\u0002\u0003\u0006IA\b\u0005\u0006Q\u0001!\t!\u000b\u0005\u0006]\u0001!\ta\f\u0005\b}\u0001\t\t\u0011\"\u0011@\u0011\u001d\u0019\u0005!!A\u0005B\u0011;qA\u0013\b\u0002\u0002#\u00051JB\u0004\u000e\u001d\u0005\u0005\t\u0012\u0001\'\t\u000b!BA\u0011\u0001)\t\u000bECAQ\u0001*\t\u000fYC\u0011\u0011!C\u0003/\"9\u0011\fCA\u0001\n\u000bQ&A\b*jG\"4UO\\2uS>t\u0017\'Q:E_V\u0014G.\u001a)sK\u0012L7-\u0019;f\u0015\ty\u0001#\u0001\fgk:\u001cG/[8o\u0007>tg/\u001a:uKJLU\u000e\u001d7t\u0015\t\t\"#A\u0003kCZ\f\u0007H\u0003\u0002\u0014)\u000511m\\7qCRT\u0011!F\u0001\u0006g\u000e\fG.Y\u0002\u0001\'\t\u0001\u0001\u0004\u0005\u0002\u001a55\tA#\u0003\u0002\u001c)\t1\u0011I\\=WC2\fAk]2bY\u0006$3m\\7qCR$#.\u0019<bq\u00112WO\\2uS>t7i\u001c8wKJ$XM]%na2\u001cHEU5dQ\u001a+hn\u0019;j_:\f\u0014i\u001d#pk\ndW\r\u0015:fI&\u001c\u0017\r^3%IUtG-\u001a:ms&tw-F\u0001\u001f!\u0011Ir$\t\u0013\n\u0005\u0001\"\"!\u0003$v]\u000e$\u0018n\u001c82!\tI\"%\u0003\u0002$)\t1Ai\\;cY\u0016\u0004\"!G\u0013\n\u0005\u0019\"\"a\u0002\"p_2,\u0017M\\\u0001Vg\u000e\fG.\u0019\u0013d_6\u0004\u0018\r\u001e\u0013kCZ\f\u0007\b\n4v]\u000e$\u0018n\u001c8D_:4XM\u001d;fe&k\u0007\u000f\\:%%&\u001c\u0007NR;oGRLwN\\\u0019Bg\u0012{WO\u00197f!J,G-[2bi\u0016$C%\u001e8eKJd\u00170\u001b8hA\u00051A(\u001b8jiz\"\"A\u000b\u0017\u0011\u0005-\u0002Q\"\u0001\b\t\u000b5\u001a\u0001\u0019\u0001\u0010\u0002\u0015UtG-\u001a:ms&tw-\u0001\u0004bg*\u000bg/Y\u000b\u0002aA\u0011\u0011\u0007O\u0007\u0002e)\u00111\u0007N\u0001\tMVt7\r^5p]*\u0011QGN\u0001\u0005kRLGNC\u00018\u0003\u0011Q\u0017M^1\n\u0005e\u0012$a\u0004#pk\ndW\r\u0015:fI&\u001c\u0017\r^3)\u0005\u0011Y\u0004CA\r=\u0013\tiDC\u0001\u0004j]2Lg.Z\u0001\tQ\u0006\u001c\bnQ8eKR\t\u0001\t\u0005\u0002\u001a\u0003&\u0011!\t\u0006\u0002\u0004\u0013:$\u0018AB3rk\u0006d7\u000f\u0006\u0002%\u000b\"9aIBA\u0001\u0002\u00049\u0015a\u0001=%cA\u0011\u0011\u0004S\u0005\u0003\u0013R\u00111!\u00118z\u0003y\u0011\u0016n\u00195Gk:\u001cG/[8oc\u0005\u001bHi\\;cY\u0016\u0004&/\u001a3jG\u0006$X\r\u0005\u0002,\u0011M\u0011\u0001\"\u0014\t\u000339K!a\u0014\u000b\u0003\r\u0005s\u0017PU3g)\u0005Y\u0015\u0001E1t\u0015\u00064\u0018\rJ3yi\u0016t7/[8o)\t\u00014\u000bC\u0003U\u0015\u0001\u0007!&A\u0003%i\"L7\u000f\u000b\u0002\u000bw\u0005\u0011\u0002.Y:i\u0007>$W\rJ3yi\u0016t7/[8o)\ty\u0004\fC\u0003U\u0017\u0001\u0007!&\u0001\tfcV\fGn\u001d\u0013fqR,gn]5p]R\u00111,\u0018\u000b\u0003IqCqA\u0012\u0007\u0002\u0002\u0003\u0007q\tC\u0003U\u0019\u0001\u0007!\u0006
   #9 = Utf8               scala$compat$java8$functionConverterImpls$RichFunction1AsDoublePredicate$$underlying
  #10 = Utf8               Lscala/Function1;
  #11 = Utf8               Lscala/Function1<Ljava/lang/Object;Ljava/lang/Object;>;
  #12 = Utf8               equals$extension
  #13 = Utf8               (Lscala/Function1;Ljava/lang/Object;)Z
  #14 = Utf8               $this
  #15 = Utf8               x$1
  #16 = Utf8               scala/compat/java8/functionConverterImpls/RichFunction1AsDoublePredicate$
  #17 = Class              #16            // scala/compat/java8/functionConverterImpls/RichFunction1AsDoublePredicate$
  #18 = Utf8               MODULE$
  #19 = Utf8               Lscala/compat/java8/functionConverterImpls/RichFunction1AsDoublePredicate$;
  #20 = NameAndType        #18:#19        // MODULE$:Lscala/compat/java8/functionConverterImpls/RichFunction1AsDoublePredicate$;
  #21 = Fieldref           #17.#20        // scala/compat/java8/functionConverterImpls/RichFunction1AsDoublePredicate$.MODULE$:Lscala/compat/java8/functionConverterImpls/RichFunction1AsDoublePredicate$;
  #22 = NameAndType        #12:#13        // equals$extension:(Lscala/Function1;Ljava/lang/Object;)Z
  #23 = Methodref          #17.#22        // scala/compat/java8/functionConverterImpls/RichFunction1AsDoublePredicate$.equals$extension:(Lscala/Function1;Ljava/lang/Object;)Z
  #24 = Utf8               Ljava/lang/Object;
  #25 = Utf8               hashCode$extension
  #26 = Utf8               (Lscala/Function1;)I
  #27 = NameAndType        #25:#26        // hashCode$extension:(Lscala/Function1;)I
  #28 = Methodref          #17.#27        // scala/compat/java8/functionConverterImpls/RichFunction1AsDoublePredicate$.hashCode$extension:(Lscala/Function1;)I
  #29 = Utf8               asJava$extension
  #30 = Utf8               (Lscala/Function1;)Ljava/util/function/DoublePredicate;
  #31 = NameAndType        #29:#30        // asJava$extension:(Lscala/Function1;)Ljava/util/function/DoublePredicate;
  #32 = Methodref          #17.#31        // scala/compat/java8/functionConverterImpls/RichFunction1AsDoublePredicate$.asJava$extension:(Lscala/Function1;)Ljava/util/function/DoublePredicate;
  #33 = Utf8               ()Lscala/Function1;
  #34 = Utf8               ()Lscala/Function1<Ljava/lang/Object;Ljava/lang/Object;>;
  #35 = NameAndType        #9:#10         // scala$compat$java8$functionConverterImpls$RichFunction1AsDoublePredicate$$underlying:Lscala/Function1;
  #36 = Fieldref           #2.#35         // scala/compat/java8/functionConverterImpls/RichFunction1AsDoublePredicate.scala$compat$java8$functionConverterImpls$RichFunction1AsDoublePredicate$$underlying:Lscala/Function1;
  #37 = Utf8               this
  #38 = Utf8               Lscala/compat/java8/functionConverterImpls/RichFunction1AsDoublePredicate;
  #39 = Utf8               asJava
  #40 = Utf8               ()Ljava/util/function/DoublePredicate;
  #41 = NameAndType        #9:#33         // scala$compat$java8$functionConverterImpls$RichFunction1AsDoublePredicate$$underlying:()Lscala/Function1;
  #42 = Methodref          #2.#41         // scala/compat/java8/functionConverterImpls/RichFunction1AsDoublePredicate.scala$compat$java8$functionConverterImpls$RichFunction1AsDoublePredicate$$underlying:()Lscala/Function1;
  #43 = Utf8               hashCode
  #44 = Utf8               ()I
  #45 = Utf8               equals
  #46 = Utf8               (Ljava/lang/Object;)Z
  #47 = Utf8               <init>
  #48 = Utf8               (Lscala/Function1;)V
  #49 = Utf8               (Lscala/Function1<Ljava/lang/Object;Ljava/lang/Object;>;)V
  #50 = Utf8               underlying
  #51 = Utf8               ()V
  #52 = NameAndType        #47:#51        // "<init>":()V
  #53 = Methodref          #4.#52         // java/lang/Object."<init>":()V
  #54 = Utf8               Signature
  #55 = Utf8               Code
  #56 = Utf8               LocalVariableTable
  #57 = Utf8               MethodParameters
  #58 = Utf8               LineNumberTable
  #59 = Utf8               SourceFile
  #60 = Utf8               RuntimeVisibleAnnotations
  #61 = Utf8               ScalaInlineInfo
  #62 = Utf8               ScalaSig
{
  private final scala.Function1<java.lang.Object, java.lang.Object> scala$compat$java8$functionConverterImpls$RichFunction1AsDoublePredicate$$underlying;
    descriptor: Lscala/Function1;
    flags: (0x0012) ACC_PRIVATE, ACC_FINAL
    Signature: #11                          // Lscala/Function1<Ljava/lang/Object;Ljava/lang/Object;>;

  public static boolean equals$extension(scala.Function1, java.lang.Object);
    descriptor: (Lscala/Function1;Ljava/lang/Object;)Z
    flags: (0x0009) ACC_PUBLIC, ACC_STATIC
    Code:
      stack=3, locals=2, args_size=2
         0: getstatic     #21                 // Field scala/compat/java8/functionConverterImpls/RichFunction1AsDoublePredicate$.MODULE$:Lscala/compat/java8/functionConverterImpls/RichFunction1AsDoublePredicate$;
         3: aload_0
         4: aload_1
         5: invokevirtual #23                 // Method scala/compat/java8/functionConverterImpls/RichFunction1AsDoublePredicate$.equals$extension:(Lscala/Function1;Ljava/lang/Object;)Z
         8: ireturn
      LocalVariableTable:
        Start  Length  Slot  Name   Signature
            0       9     0 $this   Lscala/Function1;
            0       9     1   x$1   Ljava/lang/Object;
    MethodParameters:
      Name                           Flags
      $this                          final
      x$1                            final

  public static int hashCode$extension(scala.Function1);
    descriptor: (Lscala/Function1;)I
    flags: (0x0009) ACC_PUBLIC, ACC_STATIC
    Code:
      stack=2, locals=1, args_size=1
         0: getstatic     #21                 // Field scala/compat/java8/functionConverterImpls/RichFunction1AsDoublePredicate$.MODULE$:Lscala/compat/java8/functionConverterImpls/RichFunction1AsDoublePredicate$;
         3: aload_0
         4: invokevirtual #28                 // Method scala/compat/java8/functionConverterImpls/RichFunction1AsDoublePredicate$.hashCode$extension:(Lscala/Function1;)I
         7: ireturn
      LocalVariableTable:
        Start  Length  Slot  Name   Signature
            0       8     0 $this   Lscala/Function1;
    MethodParameters:
      Name                           Flags
      $this                          final

  public static java.util.function.DoublePredicate asJava$extension(scala.Function1);
    descriptor: (Lscala/Function1;)Ljava/util/function/DoublePredicate;
    flags: (0x0009) ACC_PUBLIC, ACC_STATIC
    Code:
      stack=2, locals=1, args_size=1
         0: getstatic     #21                 // Field scala/compat/java8/functionConverterImpls/RichFunction1AsDoublePredicate$.MODULE$:Lscala/compat/java8/functionConverterImpls/RichFunction1AsDoublePredicate$;
         3: aload_0
         4: invokevirtual #32                 // Method scala/compat/java8/functionConverterImpls/RichFunction1AsDoublePredicate$.asJava$extension:(Lscala/Function1;)Ljava/util/function/DoublePredicate;
         7: areturn
      LocalVariableTable:
        Start  Length  Slot  Name   Signature
            0       8     0 $this   Lscala/Function1;
    MethodParameters:
      Name                           Flags
      $this                          final

  public scala.Function1<java.lang.Object, java.lang.Object> scala$compat$java8$functionConverterImpls$RichFunction1AsDoublePredicate$$underlying();
    descriptor: ()Lscala/Function1;
    flags: (0x0001) ACC_PUBLIC
    Code:
      stack=1, locals=1, args_size=1
         0: aload_0
         1: getfield      #36                 // Field scala$compat$java8$functionConverterImpls$RichFunction1AsDoublePredicate$$underlying:Lscala/Function1;
         4: areturn
      LineNumberTable:
        line 177: 0
      LocalVariableTable:
        Start  Length  Slot  Name   Signature
            0       5     0  this   Lscala/compat/java8/functionConverterImpls/RichFunction1AsDoublePredicate;
    Signature: #34                          // ()Lscala/Function1<Ljava/lang/Object;Ljava/lang/Object;>;

  public java.util.function.DoublePredicate asJava();
    descriptor: ()Ljava/util/function/DoublePredicate;
    flags: (0x0001) ACC_PUBLIC
    Code:
      stack=2, locals=1, args_size=1
         0: getstatic     #21                 // Field scala/compat/java8/functionConverterImpls/RichFunction1AsDoublePredicate$.MODULE$:Lscala/compat/java8/functionConverterImpls/RichFunction1AsDoublePredicate$;
         3: aload_0
         4: invokevirtual #42                 // Method scala$compat$java8$functionConverterImpls$RichFunction1AsDoublePredicate$$underlying:()Lscala/Function1;
         7: invokevirtual #32                 // Method scala/compat/java8/functionConverterImpls/RichFunction1AsDoublePredicate$.asJava$extension:(Lscala/Function1;)Ljava/util/function/DoublePredicate;
        10: areturn
      LineNumberTable:
        line 178: 0
      LocalVariableTable:
        Start  Length  Slot  Name   Signature
            0      11     0  this   Lscala/compat/java8/functionConverterImpls/RichFunction1AsDoublePredicate;

  public int hashCode();
    descriptor: ()I
    flags: (0x0001) ACC_PUBLIC
    Code:
      stack=2, locals=1, args_size=1
         0: getstatic     #21                 // Field scala/compat/java8/functionConverterImpls/RichFunction1AsDoublePredicate$.MODULE$:Lscala/compat/java8/functionConverterImpls/RichFunction1AsDoublePredicate$;
         3: aload_0
         4: invokevirtual #42                 // Method scala$compat$java8$functionConverterImpls$RichFunction1AsDoublePredicate$$underlying:()Lscala/Function1;
         7: invokevirtual #28                 // Method scala/compat/java8/functionConverterImpls/RichFunction1AsDoublePredicate$.hashCode$extension:(Lscala/Function1;)I
        10: ireturn
      LineNumberTable:
        line 177: 0
      LocalVariableTable:
        Start  Length  Slot  Name   Signature
            0      11     0  this   Lscala/compat/java8/functionConverterImpls/RichFunction1AsDoublePredicate;

  public boolean equals(java.lang.Object);
    descriptor: (Ljava/lang/Object;)Z
    flags: (0x0001) ACC_PUBLIC
    Code:
      stack=3, locals=2, args_size=2
         0: getstatic     #21                 // Field scala/compat/java8/functionConverterImpls/RichFunction1AsDoublePredicate$.MODULE$:Lscala/compat/java8/functionConverterImpls/RichFunction1AsDoublePredicate$;
         3: aload_0
         4: invokevirtual #42                 // Method scala$compat$java8$functionConverterImpls$RichFunction1AsDoublePredicate$$underlying:()Lscala/Function1;
         7: aload_1
         8: invokevirtual #23                 // Method scala/compat/java8/functionConverterImpls/RichFunction1AsDoublePredicate$.equals$extension:(Lscala/Function1;Ljava/lang/Object;)Z
        11: ireturn
      LineNumberTable:
        line 177: 0
      LocalVariableTable:
        Start  Length  Slot  Name   Signature
            0      12     0  this   Lscala/compat/java8/functionConverterImpls/RichFunction1AsDoublePredicate;
            0      12     1   x$1   Ljava/lang/Object;
    MethodParameters:
      Name                           Flags
      x$1                            final

  public scala.compat.java8.functionConverterImpls.RichFunction1AsDoublePredicate(scala.Function1<java.lang.Object, java.lang.Object>);
    descriptor: (Lscala/Function1;)V
    flags: (0x0001) ACC_PUBLIC
    Code:
      stack=2, locals=2, args_size=2
         0: aload_0
         1: aload_1
         2: putfield      #36                 // Field scala$compat$java8$functionConverterImpls$RichFunction1AsDoublePredicate$$underlying:Lscala/Function1;
         5: aload_0
         6: invokespecial #53                 // Method java/lang/Object."<init>":()V
         9: return
      LineNumberTable:
        line 177: 0
      LocalVariableTable:
        Start  Length  Slot  Name   Signature
            0      10     0  this   Lscala/compat/java8/functionConverterImpls/RichFunction1AsDoublePredicate;
            0      10     1 underlying   Lscala/Function1;
    Signature: #49                          // (Lscala/Function1<Ljava/lang/Object;Ljava/lang/Object;>;)V
    MethodParameters:
      Name                           Flags
      underlying                     final
}
SourceFile: "FunctionConverters.scala"
RuntimeVisibleAnnotations:
  0: #6(#7=s#8)
    scala.reflect.ScalaSignature(
      bytes="\u0006\u0005y3A!\u0004\b\u0003/!aA\u0004\u0001C\u0001\u0002\u000b\u0015)\u0019!C\u0005;!Iq\u0005\u0001B\u0003\u0002\u0003\u0006IA\b\u0005\u0006Q\u0001!\t!\u000b\u0005\u0006]\u0001!\ta\f\u0005\b}\u0001\t\t\u0011\"\u0011@\u0011\u001d\u0019\u0005!!A\u0005B\u0011;qA\u0013\b\u0002\u0002#\u00051JB\u0004\u000e\u001d\u0005\u0005\t\u0012\u0001\'\t\u000b!BA\u0011\u0001)\t\u000bECAQ\u0001*\t\u000fYC\u0011\u0011!C\u0003/\"9\u0011\fCA\u0001\n\u000bQ&A\b*jG\"4UO\\2uS>t\u0017\'Q:E_V\u0014G.\u001a)sK\u0012L7-\u0019;f\u0015\ty\u0001#\u0001\fgk:\u001cG/[8o\u0007>tg/\u001a:uKJLU\u000e\u001d7t\u0015\t\t\"#A\u0003kCZ\f\u0007H\u0003\u0002\u0014)\u000511m\\7qCRT\u0011!F\u0001\u0006g\u000e\fG.Y\u0002\u0001\'\t\u0001\u0001\u0004\u0005\u0002\u001a55\tA#\u0003\u0002\u001c)\t1\u0011I\\=WC2\fAk]2bY\u0006$3m\\7qCR$#.\u0019<bq\u00112WO\\2uS>t7i\u001c8wKJ$XM]%na2\u001cHEU5dQ\u001a+hn\u0019;j_:\f\u0014i\u001d#pk\ndW\r\u0015:fI&\u001c\u0017\r^3%IUtG-\u001a:ms&tw-F\u0001\u001f!\u0011Ir$\t\u0013\n\u0005\u0001\"\"!\u0003$v]\u000e$\u0018n\u001c82!\tI\"%\u0003\u0002$)\t1Ai\\;cY\u0016\u0004\"!G\u0013\n\u0005\u0019\"\"a\u0002\"p_2,\u0017M\\\u0001Vg\u000e\fG.\u0019\u0013d_6\u0004\u0018\r\u001e\u0013kCZ\f\u0007\b\n4v]\u000e$\u0018n\u001c8D_:4XM\u001d;fe&k\u0007\u000f\\:%%&\u001c\u0007NR;oGRLwN\\\u0019Bg\u0012{WO\u00197f!J,G-[2bi\u0016$C%\u001e8eKJd\u00170\u001b8hA\u00051A(\u001b8jiz\"\"A\u000b\u0017\u0011\u0005-\u0002Q\"\u0001\b\t\u000b5\u001a\u0001\u0019\u0001\u0010\u0002\u0015UtG-\u001a:ms&tw-\u0001\u0004bg*\u000bg/Y\u000b\u0002aA\u0011\u0011\u0007O\u0007\u0002e)\u00111\u0007N\u0001\tMVt7\r^5p]*\u0011QGN\u0001\u0005kRLGNC\u00018\u0003\u0011Q\u0017M^1\n\u0005e\u0012$a\u0004#pk\ndW\r\u0015:fI&\u001c\u0017\r^3)\u0005\u0011Y\u0004CA\r=\u0013\tiDC\u0001\u0004j]2Lg.Z\u0001\tQ\u0006\u001c\bnQ8eKR\t\u0001\t\u0005\u0002\u001a\u0003&\u0011!\t\u0006\u0002\u0004\u0013:$\u0018AB3rk\u0006d7\u000f\u0006\u0002%\u000b\"9aIBA\u0001\u0002\u00049\u0015a\u0001=%cA\u0011\u0011\u0004S\u0005\u0003\u0013R\u00111!\u00118z\u0003y\u0011\u0016n\u00195Gk:\u001cG/[8oc\u0005\u001bHi\\;cY\u0016\u0004&/\u001a3jG\u0006$X\r\u0005\u0002,\u0011M\u0011\u0001\"\u0014\t\u000339K!a\u0014\u000b\u0003\r\u0005s\u0017PU3g)\u0005Y\u0015\u0001E1t\u0015\u00064\u0018\rJ3yi\u0016t7/[8o)\t\u00014\u000bC\u0003U\u0015\u0001\u0007!&A\u0003%i\"L7\u000f\u000b\u0002\u000bw\u0005\u0011\u0002.Y:i\u0007>$W\rJ3yi\u0016t7/[8o)\ty\u0004\fC\u0003U\u0017\u0001\u0007!&\u0001\tfcV\fGn\u001d\u0013fqR,gn]5p]R\u00111,\u0018\u000b\u0003IqCqA\u0012\u0007\u0002\u0002\u0003\u0007q\tC\u0003U\u0019\u0001\u0007!\u0006"
    )
  ScalaInlineInfo: length = 0x1D (unknown attribute)
   01 01 00 05 00 2F 00 30 01 00 27 00 28 05 00 2D
   00 2E 01 00 2B 00 2C 01 00 09 00 21 01
  ScalaSig: length = 0x3 (unknown attribute)
   05 02 00
