Classfile /Users/mw/Projects/slang-braindump/.jar/jar11/assemble/slang-braindump/assemble/content/dk/brics/automaton/MinimizationOperations$StateListNode.class
  Last modified May 29, 2022; size 1137 bytes
  SHA-256 checksum 3b73d0acad13cd8c177152b4cdc3d6953173dedcdcc8c2d2b1bbac47850f78c7
  Compiled from "MinimizationOperations.java"
class dk.brics.automaton.MinimizationOperations$StateListNode
  minor version: 0
  major version: 52
  flags: (0x0020) ACC_SUPER
  this_class: #9                          // dk/brics/automaton/MinimizationOperations$StateListNode
  super_class: #10                        // java/lang/Object
  interfaces: 0, fields: 4, methods: 2, attributes: 2
Constant pool:
   #1 = Methodref          #10.#32        // java/lang/Object."<init>":()V
   #2 = Fieldref           #9.#33         // dk/brics/automaton/MinimizationOperations$StateListNode.q:Ldk/brics/automaton/State;
   #3 = Fieldref           #9.#34         // dk/brics/automaton/MinimizationOperations$StateListNode.sl:Ldk/brics/automaton/MinimizationOperations$StateList;
   #4 = Fieldref           #19.#35        // dk/brics/automaton/MinimizationOperations$StateList.size:I
   #5 = Fieldref           #19.#36        // dk/brics/automaton/MinimizationOperations$StateList.last:Ldk/brics/automaton/MinimizationOperations$StateListNode;
   #6 = Fieldref           #19.#37        // dk/brics/automaton/MinimizationOperations$StateList.first:Ldk/brics/automaton/MinimizationOperations$StateListNode;
   #7 = Fieldref           #9.#38         // dk/brics/automaton/MinimizationOperations$StateListNode.next:Ldk/brics/automaton/MinimizationOperations$StateListNode;
   #8 = Fieldref           #9.#39         // dk/brics/automaton/MinimizationOperations$StateListNode.prev:Ldk/brics/automaton/MinimizationOperations$StateListNode;
   #9 = Class              #41            // dk/brics/automaton/MinimizationOperations$StateListNode
  #10 = Class              #42            // java/lang/Object
  #11 = Utf8               q
  #12 = Utf8               Ldk/brics/automaton/State;
  #13 = Utf8               next
  #14 = Utf8               StateListNode
  #15 = Utf8               InnerClasses
  #16 = Utf8               Ldk/brics/automaton/MinimizationOperations$StateListNode;
  #17 = Utf8               prev
  #18 = Utf8               sl
  #19 = Class              #43            // dk/brics/automaton/MinimizationOperations$StateList
  #20 = Utf8               StateList
  #21 = Utf8               Ldk/brics/automaton/MinimizationOperations$StateList;
  #22 = Utf8               <init>
  #23 = Utf8               (Ldk/brics/automaton/State;Ldk/brics/automaton/MinimizationOperations$StateList;)V
  #24 = Utf8               Code
  #25 = Utf8               LineNumberTable
  #26 = Utf8               StackMapTable
  #27 = Class              #44            // dk/brics/automaton/State
  #28 = Utf8               remove
  #29 = Utf8               ()V
  #30 = Utf8               SourceFile
  #31 = Utf8               MinimizationOperations.java
  #32 = NameAndType        #22:#29        // "<init>":()V
  #33 = NameAndType        #11:#12        // q:Ldk/brics/automaton/State;
  #34 = NameAndType        #18:#21        // sl:Ldk/brics/automaton/MinimizationOperations$StateList;
  #35 = NameAndType        #45:#46        // size:I
  #36 = NameAndType        #47:#16        // last:Ldk/brics/automaton/MinimizationOperations$StateListNode;
  #37 = NameAndType        #48:#16        // first:Ldk/brics/automaton/MinimizationOperations$StateListNode;
  #38 = NameAndType        #13:#16        // next:Ldk/brics/automaton/MinimizationOperations$StateListNode;
  #39 = NameAndType        #17:#16        // prev:Ldk/brics/automaton/MinimizationOperations$StateListNode;
  #40 = Class              #49            // dk/brics/automaton/MinimizationOperations
  #41 = Utf8               dk/brics/automaton/MinimizationOperations$StateListNode
  #42 = Utf8               java/lang/Object
  #43 = Utf8               dk/brics/automaton/MinimizationOperations$StateList
  #44 = Utf8               dk/brics/automaton/State
  #45 = Utf8               size
  #46 = Utf8               I
  #47 = Utf8               last
  #48 = Utf8               first
  #49 = Utf8               dk/brics/automaton/MinimizationOperations
{
  dk.brics.automaton.State q;
    descriptor: Ldk/brics/automaton/State;
    flags: (0x0000)

  dk.brics.automaton.MinimizationOperations$StateListNode next;
    descriptor: Ldk/brics/automaton/MinimizationOperations$StateListNode;
    flags: (0x0000)

  dk.brics.automaton.MinimizationOperations$StateListNode prev;
    descriptor: Ldk/brics/automaton/MinimizationOperations$StateListNode;
    flags: (0x0000)

  dk.brics.automaton.MinimizationOperations$StateList sl;
    descriptor: Ldk/brics/automaton/MinimizationOperations$StateList;
    flags: (0x0000)

  dk.brics.automaton.MinimizationOperations$StateListNode(dk.brics.automaton.State, dk.brics.automaton.MinimizationOperations$StateList);
    descriptor: (Ldk/brics/automaton/State;Ldk/brics/automaton/MinimizationOperations$StateList;)V
    flags: (0x0000)
    Code:
      stack=4, locals=3, args_size=3
         0: aload_0
         1: invokespecial #1                  // Method java/lang/Object."<init>":()V
         4: aload_0
         5: aload_1
         6: putfield      #2                  // Field q:Ldk/brics/automaton/State;
         9: aload_0
        10: aload_2
        11: putfield      #3                  // Field sl:Ldk/brics/automaton/MinimizationOperations$StateList;
        14: aload_2
        15: dup
        16: getfield      #4                  // Field dk/brics/automaton/MinimizationOperations$StateList.size:I
        19: dup_x1
        20: iconst_1
        21: iadd
        22: putfield      #4                  // Field dk/brics/automaton/MinimizationOperations$StateList.size:I
        25: ifne          41
        28: aload_2
        29: aload_2
        30: aload_0
        31: dup_x1
        32: putfield      #5                  // Field dk/brics/automaton/MinimizationOperations$StateList.last:Ldk/brics/automaton/MinimizationOperations$StateListNode;
        35: putfield      #6                  // Field dk/brics/automaton/MinimizationOperations$StateList.first:Ldk/brics/automaton/MinimizationOperations$StateListNode;
        38: goto          62
        41: aload_2
        42: getfield      #5                  // Field dk/brics/automaton/MinimizationOperations$StateList.last:Ldk/brics/automaton/MinimizationOperations$StateListNode;
        45: aload_0
        46: putfield      #7                  // Field next:Ldk/brics/automaton/MinimizationOperations$StateListNode;
        49: aload_0
        50: aload_2
        51: getfield      #5                  // Field dk/brics/automaton/MinimizationOperations$StateList.last:Ldk/brics/automaton/MinimizationOperations$StateListNode;
        54: putfield      #8                  // Field prev:Ldk/brics/automaton/MinimizationOperations$StateListNode;
        57: aload_2
        58: aload_0
        59: putfield      #5                  // Field dk/brics/automaton/MinimizationOperations$StateList.last:Ldk/brics/automaton/MinimizationOperations$StateListNode;
        62: return
      LineNumberTable:
        line 548: 0
        line 549: 4
        line 550: 9
        line 551: 14
        line 552: 28
        line 554: 41
        line 555: 49
        line 556: 57
        line 558: 62
      StackMapTable: number_of_entries = 2
        frame_type = 255 /* full_frame */
          offset_delta = 41
          locals = [ class dk/brics/automaton/MinimizationOperations$StateListNode, class dk/brics/automaton/State, class dk/brics/automaton/MinimizationOperations$StateList ]
          stack = []
        frame_type = 20 /* same */

  void remove();
    descriptor: ()V
    flags: (0x0000)
    Code:
      stack=3, locals=1, args_size=1
         0: aload_0
         1: getfield      #3                  // Field sl:Ldk/brics/automaton/MinimizationOperations$StateList;
         4: dup
         5: getfield      #4                  // Field dk/brics/automaton/MinimizationOperations$StateList.size:I
         8: iconst_1
         9: isub
        10: putfield      #4                  // Field dk/brics/automaton/MinimizationOperations$StateList.size:I
        13: aload_0
        14: getfield      #3                  // Field sl:Ldk/brics/automaton/MinimizationOperations$StateList;
        17: getfield      #6                  // Field dk/brics/automaton/MinimizationOperations$StateList.first:Ldk/brics/automaton/MinimizationOperations$StateListNode;
        20: aload_0
        21: if_acmpne     38
        24: aload_0
        25: getfield      #3                  // Field sl:Ldk/brics/automaton/MinimizationOperations$StateList;
        28: aload_0
        29: getfield      #7                  // Field next:Ldk/brics/automaton/MinimizationOperations$StateListNode;
        32: putfield      #6                  // Field dk/brics/automaton/MinimizationOperations$StateList.first:Ldk/brics/automaton/MinimizationOperations$StateListNode;
        35: goto          49
        38: aload_0
        39: getfield      #8                  // Field prev:Ldk/brics/automaton/MinimizationOperations$StateListNode;
        42: aload_0
        43: getfield      #7                  // Field next:Ldk/brics/automaton/MinimizationOperations$StateListNode;
        46: putfield      #7                  // Field next:Ldk/brics/automaton/MinimizationOperations$StateListNode;
        49: aload_0
        50: getfield      #3                  // Field sl:Ldk/brics/automaton/MinimizationOperations$StateList;
        53: getfield      #5                  // Field dk/brics/automaton/MinimizationOperations$StateList.last:Ldk/brics/automaton/MinimizationOperations$StateListNode;
        56: aload_0
        57: if_acmpne     74
        60: aload_0
        61: getfield      #3                  // Field sl:Ldk/brics/automaton/MinimizationOperations$StateList;
        64: aload_0
        65: getfield      #8                  // Field prev:Ldk/brics/automaton/MinimizationOperations$StateListNode;
        68: putfield      #5                  // Field dk/brics/automaton/MinimizationOperations$StateList.last:Ldk/brics/automaton/MinimizationOperations$StateListNode;
        71: goto          85
        74: aload_0
        75: getfield      #7                  // Field next:Ldk/brics/automaton/MinimizationOperations$StateListNode;
        78: aload_0
        79: getfield      #8                  // Field prev:Ldk/brics/automaton/MinimizationOperations$StateListNode;
        82: putfield      #8                  // Field prev:Ldk/brics/automaton/MinimizationOperations$StateListNode;
        85: return
      LineNumberTable:
        line 561: 0
        line 562: 13
        line 563: 24
        line 565: 38
        line 566: 49
        line 567: 60
        line 569: 74
        line 570: 85
      StackMapTable: number_of_entries = 4
        frame_type = 38 /* same */
        frame_type = 10 /* same */
        frame_type = 24 /* same */
        frame_type = 10 /* same */
}
SourceFile: "MinimizationOperations.java"
InnerClasses:
  static #14= #9 of #40;                  // StateListNode=class dk/brics/automaton/MinimizationOperations$StateListNode of class dk/brics/automaton/MinimizationOperations
  static #20= #19 of #40;                 // StateList=class dk/brics/automaton/MinimizationOperations$StateList of class dk/brics/automaton/MinimizationOperations
