Classfile /Users/mw/Projects/slang-braindump/.jar/jar11/assemble/slang-braindump/assemble/content/dk/brics/automaton/SpecialOperations.class
  Last modified May 29, 2022; size 12505 bytes
  SHA-256 checksum 3e6371b6d7b2b2169c9213736740a897e5ea48284b1d11f755e75315534ecd41
  Compiled from "SpecialOperations.java"
public final class dk.brics.automaton.SpecialOperations
  minor version: 0
  major version: 52
  flags: (0x0031) ACC_PUBLIC, ACC_FINAL, ACC_SUPER
  this_class: #102                        // dk/brics/automaton/SpecialOperations
  super_class: #103                       // java/lang/Object
  interfaces: 0, fields: 0, methods: 24, attributes: 1
Constant pool:
    #1 = Methodref          #103.#159     // java/lang/Object."<init>":()V
    #2 = Class              #160          // java/util/HashMap
    #3 = Methodref          #2.#159       // java/util/HashMap."<init>":()V
    #4 = Methodref          #35.#161      // dk/brics/automaton/Automaton.getStates:()Ljava/util/Set;
    #5 = Methodref          #35.#162      // dk/brics/automaton/Automaton.getAcceptStates:()Ljava/util/Set;
    #6 = InterfaceMethodref #22.#163      // java/util/Set.iterator:()Ljava/util/Iterator;
    #7 = InterfaceMethodref #111.#164     // java/util/Iterator.hasNext:()Z
    #8 = InterfaceMethodref #111.#165     // java/util/Iterator.next:()Ljava/lang/Object;
    #9 = Class              #166          // dk/brics/automaton/State
   #10 = Class              #167          // java/util/HashSet
   #11 = Methodref          #10.#159      // java/util/HashSet."<init>":()V
   #12 = Methodref          #2.#168       // java/util/HashMap.put:(Ljava/lang/Object;Ljava/lang/Object;)Ljava/lang/Object;
   #13 = Fieldref           #9.#169       // dk/brics/automaton/State.accept:Z
   #14 = Methodref          #9.#170       // dk/brics/automaton/State.getTransitions:()Ljava/util/Set;
   #15 = Class              #171          // dk/brics/automaton/Transition
   #16 = Fieldref           #15.#172      // dk/brics/automaton/Transition.to:Ldk/brics/automaton/State;
   #17 = Methodref          #2.#173       // java/util/HashMap.get:(Ljava/lang/Object;)Ljava/lang/Object;
   #18 = Fieldref           #15.#174      // dk/brics/automaton/Transition.min:I
   #19 = Fieldref           #15.#175      // dk/brics/automaton/Transition.max:I
   #20 = Methodref          #15.#176      // dk/brics/automaton/Transition."<init>":(IILdk/brics/automaton/State;)V
   #21 = Methodref          #10.#177      // java/util/HashSet.add:(Ljava/lang/Object;)Z
   #22 = Class              #178          // java/util/Set
   #23 = Fieldref           #9.#179       // dk/brics/automaton/State.transitions:Ljava/util/Set;
   #24 = Fieldref           #35.#180      // dk/brics/automaton/Automaton.initial:Ldk/brics/automaton/State;
   #25 = Methodref          #9.#159       // dk/brics/automaton/State."<init>":()V
   #26 = Methodref          #9.#181       // dk/brics/automaton/State.addEpsilon:(Ldk/brics/automaton/State;)V
   #27 = Fieldref           #35.#182      // dk/brics/automaton/Automaton.deterministic:Z
   #28 = Methodref          #35.#183      // dk/brics/automaton/Automaton.cloneExpanded:()Ldk/brics/automaton/Automaton;
   #29 = Methodref          #35.#184      // dk/brics/automaton/Automaton.determinize:()V
   #30 = Methodref          #102.#185     // dk/brics/automaton/SpecialOperations.acceptToAccept:(Ldk/brics/automaton/Automaton;)V
   #31 = Methodref          #102.#186     // dk/brics/automaton/SpecialOperations.reverse:(Ldk/brics/automaton/Automaton;)Ljava/util/Set;
   #32 = Methodref          #35.#187      // dk/brics/automaton/Automaton.intersection:(Ldk/brics/automaton/Automaton;)Ldk/brics/automaton/Automaton;
   #33 = Methodref          #188.#189     // dk/brics/automaton/BasicAutomata.makeEmptyString:()Ldk/brics/automaton/Automaton;
   #34 = Methodref          #35.#190      // dk/brics/automaton/Automaton.minus:(Ldk/brics/automaton/Automaton;)Ldk/brics/automaton/Automaton;
   #35 = Class              #191          // dk/brics/automaton/Automaton
   #36 = Methodref          #35.#159      // dk/brics/automaton/Automaton."<init>":()V
   #37 = Methodref          #35.#192      // dk/brics/automaton/Automaton.isSingleton:()Z
   #38 = Fieldref           #35.#193      // dk/brics/automaton/Automaton.singleton:Ljava/lang/String;
   #39 = Methodref          #194.#195     // dk/brics/automaton/StringUnionOperations.cpCount:(Ljava/lang/String;)I
   #40 = Methodref          #194.#196     // dk/brics/automaton/StringUnionOperations.cpAt:(Ljava/lang/String;I)I
   #41 = Methodref          #15.#197      // dk/brics/automaton/Transition."<init>":(ILdk/brics/automaton/State;)V
   #42 = InterfaceMethodref #22.#177      // java/util/Set.add:(Ljava/lang/Object;)Z
   #43 = Methodref          #35.#198      // dk/brics/automaton/Automaton.removeDeadTransitions:()V
   #44 = Methodref          #35.#199      // dk/brics/automaton/Automaton.cloneExpandedIfRequired:()Ldk/brics/automaton/Automaton;
   #45 = Methodref          #102.#200     // dk/brics/automaton/SpecialOperations.addSetTransitions:(Ldk/brics/automaton/State;Ljava/lang/String;Ldk/brics/automaton/State;)V
   #46 = Methodref          #9.#201       // dk/brics/automaton/State.step:(I)Ldk/brics/automaton/State;
   #47 = Methodref          #35.#202      // dk/brics/automaton/Automaton.checkMinimizeAlways:()V
   #48 = InterfaceMethodref #127.#203     // java/util/Map.isEmpty:()Z
   #49 = Methodref          #35.#204      // dk/brics/automaton/Automaton.cloneIfRequired:()Ldk/brics/automaton/Automaton;
   #50 = Class              #205          // java/util/TreeSet
   #51 = InterfaceMethodref #127.#206     // java/util/Map.keySet:()Ljava/util/Set;
   #52 = Methodref          #50.#207      // java/util/TreeSet."<init>":(Ljava/util/Collection;)V
   #53 = InterfaceMethodref #22.#208      // java/util/Set.size:()I
   #54 = Class              #209          // java/lang/Integer
   #55 = Methodref          #54.#210      // java/lang/Integer.intValue:()I
   #56 = Methodref          #9.#211       // dk/brics/automaton/State.resetTransitions:()V
   #57 = Methodref          #102.#212     // dk/brics/automaton/SpecialOperations.findIndex:(I[I)I
   #58 = Fieldref           #15.#213      // dk/brics/automaton/Transition.MAX_VALUE:I
   #59 = Methodref          #54.#214      // java/lang/Integer.valueOf:(I)Ljava/lang/Integer;
   #60 = InterfaceMethodref #127.#173     // java/util/Map.get:(Ljava/lang/Object;)Ljava/lang/Object;
   #61 = Methodref          #133.#215     // java/lang/String.length:()I
   #62 = Class              #216          // dk/brics/automaton/StatePair
   #63 = Methodref          #62.#217      // dk/brics/automaton/StatePair."<init>":(Ldk/brics/automaton/State;Ldk/brics/automaton/State;)V
   #64 = Methodref          #35.#218      // dk/brics/automaton/Automaton.addEpsilons:(Ljava/util/Collection;)V
   #65 = Class              #219          // java/lang/Character
   #66 = InterfaceMethodref #22.#220      // java/util/Set.toArray:([Ljava/lang/Object;)[Ljava/lang/Object;
   #67 = Class              #221          // "[Ljava/lang/Character;"
   #68 = Methodref          #65.#222      // java/lang/Character.charValue:()C
   #69 = Methodref          #223.#224     // java/util/Arrays.sort:([I)V
   #70 = Methodref          #133.#225     // java/lang/String.charAt:(I)C
   #71 = Integer            57343
   #72 = Integer            63744
   #73 = Methodref          #223.#226     // java/util/Arrays.binarySearch:([II)I
   #74 = Methodref          #188.#227     // dk/brics/automaton/BasicAutomata.makeEmpty:()Ldk/brics/automaton/Automaton;
   #75 = Integer            57344
   #76 = Integer            63743
   #77 = Methodref          #35.#228      // dk/brics/automaton/Automaton.reduce:()V
   #78 = Methodref          #102.#229     // dk/brics/automaton/SpecialOperations.isFinite:(Ldk/brics/automaton/State;Ljava/util/HashSet;Ljava/util/HashSet;)Z
   #79 = Methodref          #10.#230      // java/util/HashSet.contains:(Ljava/lang/Object;)Z
   #80 = Methodref          #10.#231      // java/util/HashSet.remove:(Ljava/lang/Object;)Z
   #81 = Class              #232          // java/lang/StringBuilder
   #82 = Methodref          #81.#159      // java/lang/StringBuilder."<init>":()V
   #83 = Methodref          #102.#233     // dk/brics/automaton/SpecialOperations.getStrings:(Ldk/brics/automaton/State;Ljava/util/Set;Ljava/lang/StringBuilder;I)V
   #84 = Methodref          #81.#234      // java/lang/StringBuilder.toString:()Ljava/lang/String;
   #85 = Integer            65535
   #86 = String             #235          // \\u{
   #87 = Methodref          #81.#236      // java/lang/StringBuilder.append:(Ljava/lang/String;)Ljava/lang/StringBuilder;
   #88 = Methodref          #54.#237      // java/lang/Integer.toHexString:(I)Ljava/lang/String;
   #89 = Methodref          #133.#238     // java/lang/String.toUpperCase:()Ljava/lang/String;
   #90 = Methodref          #81.#239      // java/lang/StringBuilder.append:(C)Ljava/lang/StringBuilder;
   #91 = Methodref          #81.#215      // java/lang/StringBuilder.length:()I
   #92 = Methodref          #81.#240      // java/lang/StringBuilder.deleteCharAt:(I)Ljava/lang/StringBuilder;
   #93 = Methodref          #102.#241     // dk/brics/automaton/SpecialOperations.getFiniteStrings:(Ldk/brics/automaton/State;Ljava/util/HashSet;Ljava/util/HashSet;Ljava/lang/StringBuilder;I)Z
   #94 = Methodref          #81.#242      // java/lang/StringBuilder.append:(I)Ljava/lang/StringBuilder;
   #95 = Methodref          #10.#208      // java/util/HashSet.size:()I
   #96 = Methodref          #9.#243       // dk/brics/automaton/State.setAccept:(Z)V
   #97 = Methodref          #35.#244      // dk/brics/automaton/Automaton.clearHashCode:()V
   #98 = InterfaceMethodref #127.#168     // java/util/Map.put:(Ljava/lang/Object;Ljava/lang/Object;)Ljava/lang/Object;
   #99 = Fieldref           #188.#245     // dk/brics/automaton/BasicAutomata.ws:Ldk/brics/automaton/Automaton;
  #100 = Methodref          #35.#246      // dk/brics/automaton/Automaton.subst:(Ljava/util/Map;)Ldk/brics/automaton/Automaton;
  #101 = Methodref          #35.#247      // dk/brics/automaton/Automaton.concatenate:(Ldk/brics/automaton/Automaton;)Ldk/brics/automaton/Automaton;
  #102 = Class              #248          // dk/brics/automaton/SpecialOperations
  #103 = Class              #249          // java/lang/Object
  #104 = Utf8               <init>
  #105 = Utf8               ()V
  #106 = Utf8               Code
  #107 = Utf8               LineNumberTable
  #108 = Utf8               reverse
  #109 = Utf8               (Ldk/brics/automaton/Automaton;)Ljava/util/Set;
  #110 = Utf8               StackMapTable
  #111 = Class              #250          // java/util/Iterator
  #112 = Utf8               Signature
  #113 = Utf8               (Ldk/brics/automaton/Automaton;)Ljava/util/Set<Ldk/brics/automaton/State;>;
  #114 = Utf8               overlap
  #115 = Utf8               (Ldk/brics/automaton/Automaton;Ldk/brics/automaton/Automaton;)Ldk/brics/automaton/Automaton;
  #116 = Utf8               acceptToAccept
  #117 = Utf8               (Ldk/brics/automaton/Automaton;)V
  #118 = Utf8               singleChars
  #119 = Utf8               (Ldk/brics/automaton/Automaton;)Ldk/brics/automaton/Automaton;
  #120 = Utf8               trim
  #121 = Utf8               (Ldk/brics/automaton/Automaton;Ljava/lang/String;I)Ldk/brics/automaton/Automaton;
  #122 = Utf8               addSetTransitions
  #123 = Utf8               (Ldk/brics/automaton/State;Ljava/lang/String;Ldk/brics/automaton/State;)V
  #124 = Utf8               compress
  #125 = Utf8               subst
  #126 = Utf8               (Ldk/brics/automaton/Automaton;Ljava/util/Map;)Ldk/brics/automaton/Automaton;
  #127 = Class              #251          // java/util/Map
  #128 = Class              #252          // "[I"
  #129 = Utf8               (Ldk/brics/automaton/Automaton;Ljava/util/Map<Ljava/lang/Integer;Ljava/util/Set<Ljava/lang/Integer;>;>;)Ldk/brics/automaton/Automaton;
  #130 = Utf8               findIndex
  #131 = Utf8               (I[I)I
  #132 = Utf8               (Ldk/brics/automaton/Automaton;ILjava/lang/String;)Ldk/brics/automaton/Automaton;
  #133 = Class              #253          // java/lang/String
  #134 = Utf8               homomorph
  #135 = Utf8               (Ldk/brics/automaton/Automaton;[I[I)Ldk/brics/automaton/Automaton;
  #136 = Utf8               projectChars
  #137 = Utf8               (Ldk/brics/automaton/Automaton;Ljava/util/Set;)Ldk/brics/automaton/Automaton;
  #138 = Utf8               (Ldk/brics/automaton/Automaton;Ljava/util/Set<Ljava/lang/Character;>;)Ldk/brics/automaton/Automaton;
  #139 = Utf8               isFinite
  #140 = Utf8               (Ldk/brics/automaton/Automaton;)Z
  #141 = Utf8               (Ldk/brics/automaton/State;Ljava/util/HashSet;Ljava/util/HashSet;)Z
  #142 = Utf8               (Ldk/brics/automaton/State;Ljava/util/HashSet<Ldk/brics/automaton/State;>;Ljava/util/HashSet<Ldk/brics/automaton/State;>;)Z
  #143 = Utf8               getStrings
  #144 = Utf8               (Ldk/brics/automaton/Automaton;I)Ljava/util/Set;
  #145 = Utf8               (Ldk/brics/automaton/Automaton;I)Ljava/util/Set<Ljava/lang/String;>;
  #146 = Utf8               (Ldk/brics/automaton/State;Ljava/util/Set;Ljava/lang/StringBuilder;I)V
  #147 = Utf8               (Ldk/brics/automaton/State;Ljava/util/Set<Ljava/lang/String;>;Ljava/lang/StringBuilder;I)V
  #148 = Utf8               getFiniteStrings
  #149 = Utf8               (Ldk/brics/automaton/Automaton;)Ljava/util/Set<Ljava/lang/String;>;
  #150 = Utf8               (Ldk/brics/automaton/State;Ljava/util/HashSet;Ljava/util/HashSet;Ljava/lang/StringBuilder;I)Z
  #151 = Utf8               (Ldk/brics/automaton/State;Ljava/util/HashSet<Ldk/brics/automaton/State;>;Ljava/util/HashSet<Ljava/lang/String;>;Ljava/lang/StringBuilder;I)Z
  #152 = Utf8               getCommonPrefix
  #153 = Utf8               (Ldk/brics/automaton/Automaton;)Ljava/lang/String;
  #154 = Utf8               prefixClose
  #155 = Utf8               hexCases
  #156 = Utf8               replaceWhitespace
  #157 = Utf8               SourceFile
  #158 = Utf8               SpecialOperations.java
  #159 = NameAndType        #104:#105     // "<init>":()V
  #160 = Utf8               java/util/HashMap
  #161 = NameAndType        #254:#255     // getStates:()Ljava/util/Set;
  #162 = NameAndType        #256:#255     // getAcceptStates:()Ljava/util/Set;
  #163 = NameAndType        #257:#258     // iterator:()Ljava/util/Iterator;
  #164 = NameAndType        #259:#260     // hasNext:()Z
  #165 = NameAndType        #261:#262     // next:()Ljava/lang/Object;
  #166 = Utf8               dk/brics/automaton/State
  #167 = Utf8               java/util/HashSet
  #168 = NameAndType        #263:#264     // put:(Ljava/lang/Object;Ljava/lang/Object;)Ljava/lang/Object;
  #169 = NameAndType        #265:#266     // accept:Z
  #170 = NameAndType        #267:#255     // getTransitions:()Ljava/util/Set;
  #171 = Utf8               dk/brics/automaton/Transition
  #172 = NameAndType        #268:#269     // to:Ldk/brics/automaton/State;
  #173 = NameAndType        #270:#271     // get:(Ljava/lang/Object;)Ljava/lang/Object;
  #174 = NameAndType        #272:#273     // min:I
  #175 = NameAndType        #274:#273     // max:I
  #176 = NameAndType        #104:#275     // "<init>":(IILdk/brics/automaton/State;)V
  #177 = NameAndType        #276:#277     // add:(Ljava/lang/Object;)Z
  #178 = Utf8               java/util/Set
  #179 = NameAndType        #278:#279     // transitions:Ljava/util/Set;
  #180 = NameAndType        #280:#269     // initial:Ldk/brics/automaton/State;
  #181 = NameAndType        #281:#282     // addEpsilon:(Ldk/brics/automaton/State;)V
  #182 = NameAndType        #283:#266     // deterministic:Z
  #183 = NameAndType        #284:#285     // cloneExpanded:()Ldk/brics/automaton/Automaton;
  #184 = NameAndType        #286:#105     // determinize:()V
  #185 = NameAndType        #116:#117     // acceptToAccept:(Ldk/brics/automaton/Automaton;)V
  #186 = NameAndType        #108:#109     // reverse:(Ldk/brics/automaton/Automaton;)Ljava/util/Set;
  #187 = NameAndType        #287:#119     // intersection:(Ldk/brics/automaton/Automaton;)Ldk/brics/automaton/Automaton;
  #188 = Class              #288          // dk/brics/automaton/BasicAutomata
  #189 = NameAndType        #289:#285     // makeEmptyString:()Ldk/brics/automaton/Automaton;
  #190 = NameAndType        #290:#119     // minus:(Ldk/brics/automaton/Automaton;)Ldk/brics/automaton/Automaton;
  #191 = Utf8               dk/brics/automaton/Automaton
  #192 = NameAndType        #291:#260     // isSingleton:()Z
  #193 = NameAndType        #292:#293     // singleton:Ljava/lang/String;
  #194 = Class              #294          // dk/brics/automaton/StringUnionOperations
  #195 = NameAndType        #295:#296     // cpCount:(Ljava/lang/String;)I
  #196 = NameAndType        #297:#298     // cpAt:(Ljava/lang/String;I)I
  #197 = NameAndType        #104:#299     // "<init>":(ILdk/brics/automaton/State;)V
  #198 = NameAndType        #300:#105     // removeDeadTransitions:()V
  #199 = NameAndType        #301:#285     // cloneExpandedIfRequired:()Ldk/brics/automaton/Automaton;
  #200 = NameAndType        #122:#123     // addSetTransitions:(Ldk/brics/automaton/State;Ljava/lang/String;Ldk/brics/automaton/State;)V
  #201 = NameAndType        #302:#303     // step:(I)Ldk/brics/automaton/State;
  #202 = NameAndType        #304:#105     // checkMinimizeAlways:()V
  #203 = NameAndType        #305:#260     // isEmpty:()Z
  #204 = NameAndType        #306:#285     // cloneIfRequired:()Ldk/brics/automaton/Automaton;
  #205 = Utf8               java/util/TreeSet
  #206 = NameAndType        #307:#255     // keySet:()Ljava/util/Set;
  #207 = NameAndType        #104:#308     // "<init>":(Ljava/util/Collection;)V
  #208 = NameAndType        #309:#310     // size:()I
  #209 = Utf8               java/lang/Integer
  #210 = NameAndType        #311:#310     // intValue:()I
  #211 = NameAndType        #312:#105     // resetTransitions:()V
  #212 = NameAndType        #130:#131     // findIndex:(I[I)I
  #213 = NameAndType        #313:#273     // MAX_VALUE:I
  #214 = NameAndType        #314:#315     // valueOf:(I)Ljava/lang/Integer;
  #215 = NameAndType        #316:#310     // length:()I
  #216 = Utf8               dk/brics/automaton/StatePair
  #217 = NameAndType        #104:#317     // "<init>":(Ldk/brics/automaton/State;Ldk/brics/automaton/State;)V
  #218 = NameAndType        #318:#308     // addEpsilons:(Ljava/util/Collection;)V
  #219 = Utf8               java/lang/Character
  #220 = NameAndType        #319:#320     // toArray:([Ljava/lang/Object;)[Ljava/lang/Object;
  #221 = Utf8               [Ljava/lang/Character;
  #222 = NameAndType        #321:#322     // charValue:()C
  #223 = Class              #323          // java/util/Arrays
  #224 = NameAndType        #324:#325     // sort:([I)V
  #225 = NameAndType        #326:#327     // charAt:(I)C
  #226 = NameAndType        #328:#329     // binarySearch:([II)I
  #227 = NameAndType        #330:#285     // makeEmpty:()Ldk/brics/automaton/Automaton;
  #228 = NameAndType        #331:#105     // reduce:()V
  #229 = NameAndType        #139:#141     // isFinite:(Ldk/brics/automaton/State;Ljava/util/HashSet;Ljava/util/HashSet;)Z
  #230 = NameAndType        #332:#277     // contains:(Ljava/lang/Object;)Z
  #231 = NameAndType        #333:#277     // remove:(Ljava/lang/Object;)Z
  #232 = Utf8               java/lang/StringBuilder
  #233 = NameAndType        #143:#146     // getStrings:(Ldk/brics/automaton/State;Ljava/util/Set;Ljava/lang/StringBuilder;I)V
  #234 = NameAndType        #334:#335     // toString:()Ljava/lang/String;
  #235 = Utf8               \\u{
  #236 = NameAndType        #336:#337     // append:(Ljava/lang/String;)Ljava/lang/StringBuilder;
  #237 = NameAndType        #338:#339     // toHexString:(I)Ljava/lang/String;
  #238 = NameAndType        #340:#335     // toUpperCase:()Ljava/lang/String;
  #239 = NameAndType        #336:#341     // append:(C)Ljava/lang/StringBuilder;
  #240 = NameAndType        #342:#343     // deleteCharAt:(I)Ljava/lang/StringBuilder;
  #241 = NameAndType        #148:#150     // getFiniteStrings:(Ldk/brics/automaton/State;Ljava/util/HashSet;Ljava/util/HashSet;Ljava/lang/StringBuilder;I)Z
  #242 = NameAndType        #336:#343     // append:(I)Ljava/lang/StringBuilder;
  #243 = NameAndType        #344:#345     // setAccept:(Z)V
  #244 = NameAndType        #346:#105     // clearHashCode:()V
  #245 = NameAndType        #347:#348     // ws:Ldk/brics/automaton/Automaton;
  #246 = NameAndType        #125:#349     // subst:(Ljava/util/Map;)Ldk/brics/automaton/Automaton;
  #247 = NameAndType        #350:#119     // concatenate:(Ldk/brics/automaton/Automaton;)Ldk/brics/automaton/Automaton;
  #248 = Utf8               dk/brics/automaton/SpecialOperations
  #249 = Utf8               java/lang/Object
  #250 = Utf8               java/util/Iterator
  #251 = Utf8               java/util/Map
  #252 = Utf8               [I
  #253 = Utf8               java/lang/String
  #254 = Utf8               getStates
  #255 = Utf8               ()Ljava/util/Set;
  #256 = Utf8               getAcceptStates
  #257 = Utf8               iterator
  #258 = Utf8               ()Ljava/util/Iterator;
  #259 = Utf8               hasNext
  #260 = Utf8               ()Z
  #261 = Utf8               next
  #262 = Utf8               ()Ljava/lang/Object;
  #263 = Utf8               put
  #264 = Utf8               (Ljava/lang/Object;Ljava/lang/Object;)Ljava/lang/Object;
  #265 = Utf8               accept
  #266 = Utf8               Z
  #267 = Utf8               getTransitions
  #268 = Utf8               to
  #269 = Utf8               Ldk/brics/automaton/State;
  #270 = Utf8               get
  #271 = Utf8               (Ljava/lang/Object;)Ljava/lang/Object;
  #272 = Utf8               min
  #273 = Utf8               I
  #274 = Utf8               max
  #275 = Utf8               (IILdk/brics/automaton/State;)V
  #276 = Utf8               add
  #277 = Utf8               (Ljava/lang/Object;)Z
  #278 = Utf8               transitions
  #279 = Utf8               Ljava/util/Set;
  #280 = Utf8               initial
  #281 = Utf8               addEpsilon
  #282 = Utf8               (Ldk/brics/automaton/State;)V
  #283 = Utf8               deterministic
  #284 = Utf8               cloneExpanded
  #285 = Utf8               ()Ldk/brics/automaton/Automaton;
  #286 = Utf8               determinize
  #287 = Utf8               intersection
  #288 = Utf8               dk/brics/automaton/BasicAutomata
  #289 = Utf8               makeEmptyString
  #290 = Utf8               minus
  #291 = Utf8               isSingleton
  #292 = Utf8               singleton
  #293 = Utf8               Ljava/lang/String;
  #294 = Utf8               dk/brics/automaton/StringUnionOperations
  #295 = Utf8               cpCount
  #296 = Utf8               (Ljava/lang/String;)I
  #297 = Utf8               cpAt
  #298 = Utf8               (Ljava/lang/String;I)I
  #299 = Utf8               (ILdk/brics/automaton/State;)V
  #300 = Utf8               removeDeadTransitions
  #301 = Utf8               cloneExpandedIfRequired
  #302 = Utf8               step
  #303 = Utf8               (I)Ldk/brics/automaton/State;
  #304 = Utf8               checkMinimizeAlways
  #305 = Utf8               isEmpty
  #306 = Utf8               cloneIfRequired
  #307 = Utf8               keySet
  #308 = Utf8               (Ljava/util/Collection;)V
  #309 = Utf8               size
  #310 = Utf8               ()I
  #311 = Utf8               intValue
  #312 = Utf8               resetTransitions
  #313 = Utf8               MAX_VALUE
  #314 = Utf8               valueOf
  #315 = Utf8               (I)Ljava/lang/Integer;
  #316 = Utf8               length
  #317 = Utf8               (Ldk/brics/automaton/State;Ldk/brics/automaton/State;)V
  #318 = Utf8               addEpsilons
  #319 = Utf8               toArray
  #320 = Utf8               ([Ljava/lang/Object;)[Ljava/lang/Object;
  #321 = Utf8               charValue
  #322 = Utf8               ()C
  #323 = Utf8               java/util/Arrays
  #324 = Utf8               sort
  #325 = Utf8               ([I)V
  #326 = Utf8               charAt
  #327 = Utf8               (I)C
  #328 = Utf8               binarySearch
  #329 = Utf8               ([II)I
  #330 = Utf8               makeEmpty
  #331 = Utf8               reduce
  #332 = Utf8               contains
  #333 = Utf8               remove
  #334 = Utf8               toString
  #335 = Utf8               ()Ljava/lang/String;
  #336 = Utf8               append
  #337 = Utf8               (Ljava/lang/String;)Ljava/lang/StringBuilder;
  #338 = Utf8               toHexString
  #339 = Utf8               (I)Ljava/lang/String;
  #340 = Utf8               toUpperCase
  #341 = Utf8               (C)Ljava/lang/StringBuilder;
  #342 = Utf8               deleteCharAt
  #343 = Utf8               (I)Ljava/lang/StringBuilder;
  #344 = Utf8               setAccept
  #345 = Utf8               (Z)V
  #346 = Utf8               clearHashCode
  #347 = Utf8               ws
  #348 = Utf8               Ldk/brics/automaton/Automaton;
  #349 = Utf8               (Ljava/util/Map;)Ldk/brics/automaton/Automaton;
  #350 = Utf8               concatenate
{
  private dk.brics.automaton.SpecialOperations();
    descriptor: ()V
    flags: (0x0002) ACC_PRIVATE
    Code:
      stack=1, locals=1, args_size=1
         0: aload_0
         1: invokespecial #1                  // Method java/lang/Object."<init>":()V
         4: return
      LineNumberTable:
        line 47: 0

  public static java.util.Set<dk.brics.automaton.State> reverse(dk.brics.automaton.Automaton);
    descriptor: (Ldk/brics/automaton/Automaton;)Ljava/util/Set;
    flags: (0x0009) ACC_PUBLIC, ACC_STATIC
    Code:
      stack=6, locals=8, args_size=1
         0: new           #2                  // class java/util/HashMap
         3: dup
         4: invokespecial #3                  // Method java/util/HashMap."<init>":()V
         7: astore_1
         8: aload_0
         9: invokevirtual #4                  // Method dk/brics/automaton/Automaton.getStates:()Ljava/util/Set;
        12: astore_2
        13: aload_0
        14: invokevirtual #5                  // Method dk/brics/automaton/Automaton.getAcceptStates:()Ljava/util/Set;
        17: astore_3
        18: aload_2
        19: invokeinterface #6,  1            // InterfaceMethod java/util/Set.iterator:()Ljava/util/Iterator;
        24: astore        4
        26: aload         4
        28: invokeinterface #7,  1            // InterfaceMethod java/util/Iterator.hasNext:()Z
        33: ifeq          71
        36: aload         4
        38: invokeinterface #8,  1            // InterfaceMethod java/util/Iterator.next:()Ljava/lang/Object;
        43: checkcast     #9                  // class dk/brics/automaton/State
        46: astore        5
        48: aload_1
        49: aload         5
        51: new           #10                 // class java/util/HashSet
        54: dup
        55: invokespecial #11                 // Method java/util/HashSet."<init>":()V
        58: invokevirtual #12                 // Method java/util/HashMap.put:(Ljava/lang/Object;Ljava/lang/Object;)Ljava/lang/Object;
        61: pop
        62: aload         5
        64: iconst_0
        65: putfield      #13                 // Field dk/brics/automaton/State.accept:Z
        68: goto          26
        71: aload_2
        72: invokeinterface #6,  1            // InterfaceMethod java/util/Set.iterator:()Ljava/util/Iterator;
        77: astore        4
        79: aload         4
        81: invokeinterface #7,  1            // InterfaceMethod java/util/Iterator.hasNext:()Z
        86: ifeq          176
        89: aload         4
        91: invokeinterface #8,  1            // InterfaceMethod java/util/Iterator.next:()Ljava/lang/Object;
        96: checkcast     #9                  // class dk/brics/automaton/State
        99: astore        5
       101: aload         5
       103: invokevirtual #14                 // Method dk/brics/automaton/State.getTransitions:()Ljava/util/Set;
       106: invokeinterface #6,  1            // InterfaceMethod java/util/Set.iterator:()Ljava/util/Iterator;
       111: astore        6
       113: aload         6
       115: invokeinterface #7,  1            // InterfaceMethod java/util/Iterator.hasNext:()Z
       120: ifeq          173
       123: aload         6
       125: invokeinterface #8,  1            // InterfaceMethod java/util/Iterator.next:()Ljava/lang/Object;
       130: checkcast     #15                 // class dk/brics/automaton/Transition
       133: astore        7
       135: aload_1
       136: aload         7
       138: getfield      #16                 // Field dk/brics/automaton/Transition.to:Ldk/brics/automaton/State;
       141: invokevirtual #17                 // Method java/util/HashMap.get:(Ljava/lang/Object;)Ljava/lang/Object;
       144: checkcast     #10                 // class java/util/HashSet
       147: new           #15                 // class dk/brics/automaton/Transition
       150: dup
       151: aload         7
       153: getfield      #18                 // Field dk/brics/automaton/Transition.min:I
       156: aload         7
       158: getfield      #19                 // Field dk/brics/automaton/Transition.max:I
       161: aload         5
       163: invokespecial #20                 // Method dk/brics/automaton/Transition."<init>":(IILdk/brics/automaton/State;)V
       166: invokevirtual #21                 // Method java/util/HashSet.add:(Ljava/lang/Object;)Z
       169: pop
       170: goto          113
       173: goto          79
       176: aload_2
       177: invokeinterface #6,  1            // InterfaceMethod java/util/Set.iterator:()Ljava/util/Iterator;
       182: astore        4
       184: aload         4
       186: invokeinterface #7,  1            // InterfaceMethod java/util/Iterator.hasNext:()Z
       191: ifeq          223
       194: aload         4
       196: invokeinterface #8,  1            // InterfaceMethod java/util/Iterator.next:()Ljava/lang/Object;
       201: checkcast     #9                  // class dk/brics/automaton/State
       204: astore        5
       206: aload         5
       208: aload_1
       209: aload         5
       211: invokevirtual #17                 // Method java/util/HashMap.get:(Ljava/lang/Object;)Ljava/lang/Object;
       214: checkcast     #22                 // class java/util/Set
       217: putfield      #23                 // Field dk/brics/automaton/State.transitions:Ljava/util/Set;
       220: goto          184
       223: aload_0
       224: getfield      #24                 // Field dk/brics/automaton/Automaton.initial:Ldk/brics/automaton/State;
       227: iconst_1
       228: putfield      #13                 // Field dk/brics/automaton/State.accept:Z
       231: aload_0
       232: new           #9                  // class dk/brics/automaton/State
       235: dup
       236: invokespecial #25                 // Method dk/brics/automaton/State."<init>":()V
       239: putfield      #24                 // Field dk/brics/automaton/Automaton.initial:Ldk/brics/automaton/State;
       242: aload_3
       243: invokeinterface #6,  1            // InterfaceMethod java/util/Set.iterator:()Ljava/util/Iterator;
       248: astore        4
       250: aload         4
       252: invokeinterface #7,  1            // InterfaceMethod java/util/Iterator.hasNext:()Z
       257: ifeq          284
       260: aload         4
       262: invokeinterface #8,  1            // InterfaceMethod java/util/Iterator.next:()Ljava/lang/Object;
       267: checkcast     #9                  // class dk/brics/automaton/State
       270: astore        5
       272: aload_0
       273: getfield      #24                 // Field dk/brics/automaton/Automaton.initial:Ldk/brics/automaton/State;
       276: aload         5
       278: invokevirtual #26                 // Method dk/brics/automaton/State.addEpsilon:(Ldk/brics/automaton/State;)V
       281: goto          250
       284: aload_0
       285: iconst_0
       286: putfield      #27                 // Field dk/brics/automaton/Automaton.deterministic:Z
       289: aload_3
       290: areturn
      LineNumberTable:
        line 55: 0
        line 56: 8
        line 57: 13
        line 58: 18
        line 59: 48
        line 60: 62
        line 61: 68
        line 62: 71
        line 63: 101
        line 64: 135
        line 63: 173
        line 65: 176
        line 66: 206
        line 68: 223
        line 69: 231
        line 70: 242
        line 71: 272
        line 72: 284
        line 73: 289
      StackMapTable: number_of_entries = 10
        frame_type = 255 /* full_frame */
          offset_delta = 26
          locals = [ class dk/brics/automaton/Automaton, class java/util/HashMap, class java/util/Set, class java/util/Set, class java/util/Iterator ]
          stack = []
        frame_type = 250 /* chop */
          offset_delta = 44
        frame_type = 252 /* append */
          offset_delta = 7
          locals = [ class java/util/Iterator ]
        frame_type = 253 /* append */
          offset_delta = 33
          locals = [ class dk/brics/automaton/State, class java/util/Iterator ]
        frame_type = 249 /* chop */
          offset_delta = 59
        frame_type = 250 /* chop */
          offset_delta = 2
        frame_type = 252 /* append */
          offset_delta = 7
          locals = [ class java/util/Iterator ]
        frame_type = 250 /* chop */
          offset_delta = 38
        frame_type = 252 /* append */
          offset_delta = 26
          locals = [ class java/util/Iterator ]
        frame_type = 250 /* chop */
          offset_delta = 33
    Signature: #113                         // (Ldk/brics/automaton/Automaton;)Ljava/util/Set<Ldk/brics/automaton/State;>;

  public static dk.brics.automaton.Automaton overlap(dk.brics.automaton.Automaton, dk.brics.automaton.Automaton);
    descriptor: (Ldk/brics/automaton/Automaton;Ldk/brics/automaton/Automaton;)Ldk/brics/automaton/Automaton;
    flags: (0x0009) ACC_PUBLIC, ACC_STATIC
    Code:
      stack=2, locals=4, args_size=2
         0: aload_0
         1: invokevirtual #28                 // Method dk/brics/automaton/Automaton.cloneExpanded:()Ldk/brics/automaton/Automaton;
         4: astore_2
         5: aload_2
         6: invokevirtual #29                 // Method dk/brics/automaton/Automaton.determinize:()V
         9: aload_2
        10: invokestatic  #30                 // Method acceptToAccept:(Ldk/brics/automaton/Automaton;)V
        13: aload_1
        14: invokevirtual #28                 // Method dk/brics/automaton/Automaton.cloneExpanded:()Ldk/brics/automaton/Automaton;
        17: astore_3
        18: aload_3
        19: invokestatic  #31                 // Method reverse:(Ldk/brics/automaton/Automaton;)Ljava/util/Set;
        22: pop
        23: aload_3
        24: invokevirtual #29                 // Method dk/brics/automaton/Automaton.determinize:()V
        27: aload_3
        28: invokestatic  #30                 // Method acceptToAccept:(Ldk/brics/automaton/Automaton;)V
        31: aload_3
        32: invokestatic  #31                 // Method reverse:(Ldk/brics/automaton/Automaton;)Ljava/util/Set;
        35: pop
        36: aload_3
        37: invokevirtual #29                 // Method dk/brics/automaton/Automaton.determinize:()V
        40: aload_2
        41: aload_3
        42: invokevirtual #32                 // Method dk/brics/automaton/Automaton.intersection:(Ldk/brics/automaton/Automaton;)Ldk/brics/automaton/Automaton;
        45: invokestatic  #33                 // Method dk/brics/automaton/BasicAutomata.makeEmptyString:()Ldk/brics/automaton/Automaton;
        48: invokevirtual #34                 // Method dk/brics/automaton/Automaton.minus:(Ldk/brics/automaton/Automaton;)Ldk/brics/automaton/Automaton;
        51: areturn
      LineNumberTable:
        line 82: 0
        line 83: 5
        line 84: 9
        line 85: 13
        line 86: 18
        line 87: 23
        line 88: 27
        line 89: 31
        line 90: 36
        line 91: 40

  private static void acceptToAccept(dk.brics.automaton.Automaton);
    descriptor: (Ldk/brics/automaton/Automaton;)V
    flags: (0x000a) ACC_PRIVATE, ACC_STATIC
    Code:
      stack=2, locals=4, args_size=1
         0: new           #9                  // class dk/brics/automaton/State
         3: dup
         4: invokespecial #25                 // Method dk/brics/automaton/State."<init>":()V
         7: astore_1
         8: aload_0
         9: invokevirtual #5                  // Method dk/brics/automaton/Automaton.getAcceptStates:()Ljava/util/Set;
        12: invokeinterface #6,  1            // InterfaceMethod java/util/Set.iterator:()Ljava/util/Iterator;
        17: astore_2
        18: aload_2
        19: invokeinterface #7,  1            // InterfaceMethod java/util/Iterator.hasNext:()Z
        24: ifeq          45
        27: aload_2
        28: invokeinterface #8,  1            // InterfaceMethod java/util/Iterator.next:()Ljava/lang/Object;
        33: checkcast     #9                  // class dk/brics/automaton/State
        36: astore_3
        37: aload_1
        38: aload_3
        39: invokevirtual #26                 // Method dk/brics/automaton/State.addEpsilon:(Ldk/brics/automaton/State;)V
        42: goto          18
        45: aload_0
        46: aload_1
        47: putfield      #24                 // Field dk/brics/automaton/Automaton.initial:Ldk/brics/automaton/State;
        50: aload_0
        51: iconst_0
        52: putfield      #27                 // Field dk/brics/automaton/Automaton.deterministic:Z
        55: return
      LineNumberTable:
        line 95: 0
        line 96: 8
        line 97: 37
        line 98: 45
        line 99: 50
        line 100: 55
      StackMapTable: number_of_entries = 2
        frame_type = 253 /* append */
          offset_delta = 18
          locals = [ class dk/brics/automaton/State, class java/util/Iterator ]
        frame_type = 250 /* chop */
          offset_delta = 26

  public static dk.brics.automaton.Automaton singleChars(dk.brics.automaton.Automaton);
    descriptor: (Ldk/brics/automaton/Automaton;)Ldk/brics/automaton/Automaton;
    flags: (0x0009) ACC_PUBLIC, ACC_STATIC
    Code:
      stack=6, locals=8, args_size=1
         0: new           #35                 // class dk/brics/automaton/Automaton
         3: dup
         4: invokespecial #36                 // Method dk/brics/automaton/Automaton."<init>":()V
         7: astore_1
         8: new           #9                  // class dk/brics/automaton/State
        11: dup
        12: invokespecial #25                 // Method dk/brics/automaton/State."<init>":()V
        15: astore_2
        16: aload_1
        17: aload_2
        18: putfield      #24                 // Field dk/brics/automaton/Automaton.initial:Ldk/brics/automaton/State;
        21: new           #9                  // class dk/brics/automaton/State
        24: dup
        25: invokespecial #25                 // Method dk/brics/automaton/State."<init>":()V
        28: astore_3
        29: aload_3
        30: iconst_1
        31: putfield      #13                 // Field dk/brics/automaton/State.accept:Z
        34: aload_0
        35: invokevirtual #37                 // Method dk/brics/automaton/Automaton.isSingleton:()Z
        38: ifeq          96
        41: aload_0
        42: getfield      #38                 // Field dk/brics/automaton/Automaton.singleton:Ljava/lang/String;
        45: invokestatic  #39                 // Method dk/brics/automaton/StringUnionOperations.cpCount:(Ljava/lang/String;)I
        48: istore        4
        50: iconst_0
        51: istore        5
        53: iload         5
        55: iload         4
        57: if_icmpge     93
        60: aload_2
        61: getfield      #23                 // Field dk/brics/automaton/State.transitions:Ljava/util/Set;
        64: new           #15                 // class dk/brics/automaton/Transition
        67: dup
        68: aload_0
        69: getfield      #38                 // Field dk/brics/automaton/Automaton.singleton:Ljava/lang/String;
        72: iload         5
        74: invokestatic  #40                 // Method dk/brics/automaton/StringUnionOperations.cpAt:(Ljava/lang/String;I)I
        77: aload_3
        78: invokespecial #41                 // Method dk/brics/automaton/Transition."<init>":(ILdk/brics/automaton/State;)V
        81: invokeinterface #42,  2           // InterfaceMethod java/util/Set.add:(Ljava/lang/Object;)Z
        86: pop
        87: iinc          5, 1
        90: goto          53
        93: goto          197
        96: aload_0
        97: invokevirtual #4                  // Method dk/brics/automaton/Automaton.getStates:()Ljava/util/Set;
       100: invokeinterface #6,  1            // InterfaceMethod java/util/Set.iterator:()Ljava/util/Iterator;
       105: astore        4
       107: aload         4
       109: invokeinterface #7,  1            // InterfaceMethod java/util/Iterator.hasNext:()Z
       114: ifeq          197
       117: aload         4
       119: invokeinterface #8,  1            // InterfaceMethod java/util/Iterator.next:()Ljava/lang/Object;
       124: checkcast     #9                  // class dk/brics/automaton/State
       127: astore        5
       129: aload         5
       131: getfield      #23                 // Field dk/brics/automaton/State.transitions:Ljava/util/Set;
       134: invokeinterface #6,  1            // InterfaceMethod java/util/Set.iterator:()Ljava/util/Iterator;
       139: astore        6
       141: aload         6
       143: invokeinterface #7,  1            // InterfaceMethod java/util/Iterator.hasNext:()Z
       148: ifeq          194
       151: aload         6
       153: invokeinterface #8,  1            // InterfaceMethod java/util/Iterator.next:()Ljava/lang/Object;
       158: checkcast     #15                 // class dk/brics/automaton/Transition
       161: astore        7
       163: aload_2
       164: getfield      #23                 // Field dk/brics/automaton/State.transitions:Ljava/util/Set;
       167: new           #15                 // class dk/brics/automaton/Transition
       170: dup
       171: aload         7
       173: getfield      #18                 // Field dk/brics/automaton/Transition.min:I
       176: aload         7
       178: getfield      #19                 // Field dk/brics/automaton/Transition.max:I
       181: aload_3
       182: invokespecial #20                 // Method dk/brics/automaton/Transition."<init>":(IILdk/brics/automaton/State;)V
       185: invokeinterface #42,  2           // InterfaceMethod java/util/Set.add:(Ljava/lang/Object;)Z
       190: pop
       191: goto          141
       194: goto          107
       197: aload_1
       198: iconst_1
       199: putfield      #27                 // Field dk/brics/automaton/Automaton.deterministic:Z
       202: aload_1
       203: invokevirtual #43                 // Method dk/brics/automaton/Automaton.removeDeadTransitions:()V
       206: aload_1
       207: areturn
      LineNumberTable:
        line 108: 0
        line 109: 8
        line 110: 16
        line 111: 21
        line 112: 29
        line 113: 34
        line 114: 41
        line 115: 50
        line 116: 60
        line 115: 87
        line 117: 93
        line 118: 96
        line 119: 129
        line 120: 163
        line 119: 194
        line 121: 197
        line 122: 202
        line 123: 206
      StackMapTable: number_of_entries = 7
        frame_type = 255 /* full_frame */
          offset_delta = 53
          locals = [ class dk/brics/automaton/Automaton, class dk/brics/automaton/Automaton, class dk/brics/automaton/State, class dk/brics/automaton/State, int, int ]
          stack = []
        frame_type = 249 /* chop */
          offset_delta = 39
        frame_type = 2 /* same */
        frame_type = 252 /* append */
          offset_delta = 10
          locals = [ class java/util/Iterator ]
        frame_type = 253 /* append */
          offset_delta = 33
          locals = [ class dk/brics/automaton/State, class java/util/Iterator ]
        frame_type = 249 /* chop */
          offset_delta = 52
        frame_type = 250 /* chop */
          offset_delta = 2

  public static dk.brics.automaton.Automaton trim(dk.brics.automaton.Automaton, java.lang.String, int);
    descriptor: (Ldk/brics/automaton/Automaton;Ljava/lang/String;I)Ldk/brics/automaton/Automaton;
    flags: (0x0009) ACC_PUBLIC, ACC_STATIC
    Code:
      stack=3, locals=8, args_size=3
         0: aload_0
         1: invokevirtual #44                 // Method dk/brics/automaton/Automaton.cloneExpandedIfRequired:()Ldk/brics/automaton/Automaton;
         4: astore_0
         5: new           #9                  // class dk/brics/automaton/State
         8: dup
         9: invokespecial #25                 // Method dk/brics/automaton/State."<init>":()V
        12: astore_3
        13: aload_3
        14: aload_1
        15: aload_3
        16: invokestatic  #45                 // Method addSetTransitions:(Ldk/brics/automaton/State;Ljava/lang/String;Ldk/brics/automaton/State;)V
        19: aload_3
        20: iconst_1
        21: putfield      #13                 // Field dk/brics/automaton/State.accept:Z
        24: aload_0
        25: invokevirtual #4                  // Method dk/brics/automaton/Automaton.getStates:()Ljava/util/Set;
        28: invokeinterface #6,  1            // InterfaceMethod java/util/Set.iterator:()Ljava/util/Iterator;
        33: astore        4
        35: aload         4
        37: invokeinterface #7,  1            // InterfaceMethod java/util/Iterator.hasNext:()Z
        42: ifeq          119
        45: aload         4
        47: invokeinterface #8,  1            // InterfaceMethod java/util/Iterator.next:()Ljava/lang/Object;
        52: checkcast     #9                  // class dk/brics/automaton/State
        55: astore        5
        57: aload         5
        59: iload_2
        60: invokevirtual #46                 // Method dk/brics/automaton/State.step:(I)Ldk/brics/automaton/State;
        63: astore        6
        65: aload         6
        67: ifnull        102
        70: new           #9                  // class dk/brics/automaton/State
        73: dup
        74: invokespecial #25                 // Method dk/brics/automaton/State."<init>":()V
        77: astore        7
        79: aload         7
        81: aload_1
        82: aload         7
        84: invokestatic  #45                 // Method addSetTransitions:(Ldk/brics/automaton/State;Ljava/lang/String;Ldk/brics/automaton/State;)V
        87: aload         5
        89: aload_1
        90: aload         7
        92: invokestatic  #45                 // Method addSetTransitions:(Ldk/brics/automaton/State;Ljava/lang/String;Ldk/brics/automaton/State;)V
        95: aload         7
        97: aload         6
        99: invokevirtual #26                 // Method dk/brics/automaton/State.addEpsilon:(Ldk/brics/automaton/State;)V
       102: aload         5
       104: getfield      #13                 // Field dk/brics/automaton/State.accept:Z
       107: ifeq          116
       110: aload         5
       112: aload_3
       113: invokevirtual #26                 // Method dk/brics/automaton/State.addEpsilon:(Ldk/brics/automaton/State;)V
       116: goto          35
       119: new           #9                  // class dk/brics/automaton/State
       122: dup
       123: invokespecial #25                 // Method dk/brics/automaton/State."<init>":()V
       126: astore        4
       128: aload         4
       130: aload_1
       131: aload         4
       133: invokestatic  #45                 // Method addSetTransitions:(Ldk/brics/automaton/State;Ljava/lang/String;Ldk/brics/automaton/State;)V
       136: aload         4
       138: aload_0
       139: getfield      #24                 // Field dk/brics/automaton/Automaton.initial:Ldk/brics/automaton/State;
       142: invokevirtual #26                 // Method dk/brics/automaton/State.addEpsilon:(Ldk/brics/automaton/State;)V
       145: aload_0
       146: aload         4
       148: putfield      #24                 // Field dk/brics/automaton/Automaton.initial:Ldk/brics/automaton/State;
       151: aload_0
       152: iconst_0
       153: putfield      #27                 // Field dk/brics/automaton/Automaton.deterministic:Z
       156: aload_0
       157: invokevirtual #43                 // Method dk/brics/automaton/Automaton.removeDeadTransitions:()V
       160: aload_0
       161: invokevirtual #47                 // Method dk/brics/automaton/Automaton.checkMinimizeAlways:()V
       164: aload_0
       165: areturn
      LineNumberTable:
        line 137: 0
        line 138: 5
        line 139: 13
        line 140: 19
        line 141: 24
        line 142: 57
        line 143: 65
        line 145: 70
        line 146: 79
        line 147: 87
        line 148: 95
        line 151: 102
        line 152: 110
        line 153: 116
        line 155: 119
        line 156: 128
        line 157: 136
        line 158: 145
        line 159: 151
        line 160: 156
        line 161: 160
        line 162: 164
      StackMapTable: number_of_entries = 4
        frame_type = 253 /* append */
          offset_delta = 35
          locals = [ class dk/brics/automaton/State, class java/util/Iterator ]
        frame_type = 253 /* append */
          offset_delta = 66
          locals = [ class dk/brics/automaton/State, class dk/brics/automaton/State ]
        frame_type = 249 /* chop */
          offset_delta = 13
        frame_type = 250 /* chop */
          offset_delta = 2

  private static void addSetTransitions(dk.brics.automaton.State, java.lang.String, dk.brics.automaton.State);
    descriptor: (Ldk/brics/automaton/State;Ljava/lang/String;Ldk/brics/automaton/State;)V
    flags: (0x000a) ACC_PRIVATE, ACC_STATIC
    Code:
      stack=5, locals=5, args_size=3
         0: aload_1
         1: invokestatic  #39                 // Method dk/brics/automaton/StringUnionOperations.cpCount:(Ljava/lang/String;)I
         4: istore_3
         5: iconst_0
         6: istore        4
         8: iload         4
        10: iload_3
        11: if_icmpge     44
        14: aload_0
        15: getfield      #23                 // Field dk/brics/automaton/State.transitions:Ljava/util/Set;
        18: new           #15                 // class dk/brics/automaton/Transition
        21: dup
        22: aload_1
        23: iload         4
        25: invokestatic  #40                 // Method dk/brics/automaton/StringUnionOperations.cpAt:(Ljava/lang/String;I)I
        28: aload_2
        29: invokespecial #41                 // Method dk/brics/automaton/Transition."<init>":(ILdk/brics/automaton/State;)V
        32: invokeinterface #42,  2           // InterfaceMethod java/util/Set.add:(Ljava/lang/Object;)Z
        37: pop
        38: iinc          4, 1
        41: goto          8
        44: return
      LineNumberTable:
        line 166: 0
        line 167: 5
        line 168: 14
        line 167: 38
        line 169: 44
      StackMapTable: number_of_entries = 2
        frame_type = 253 /* append */
          offset_delta = 8
          locals = [ int, int ]
        frame_type = 250 /* chop */
          offset_delta = 35

  public static dk.brics.automaton.Automaton compress(dk.brics.automaton.Automaton, java.lang.String, int);
    descriptor: (Ldk/brics/automaton/Automaton;Ljava/lang/String;I)Ldk/brics/automaton/Automaton;
    flags: (0x0009) ACC_PUBLIC, ACC_STATIC
    Code:
      stack=3, locals=7, args_size=3
         0: aload_0
         1: invokevirtual #44                 // Method dk/brics/automaton/Automaton.cloneExpandedIfRequired:()Ldk/brics/automaton/Automaton;
         4: astore_0
         5: aload_0
         6: invokevirtual #4                  // Method dk/brics/automaton/Automaton.getStates:()Ljava/util/Set;
         9: invokeinterface #6,  1            // InterfaceMethod java/util/Set.iterator:()Ljava/util/Iterator;
        14: astore_3
        15: aload_3
        16: invokeinterface #7,  1            // InterfaceMethod java/util/Iterator.hasNext:()Z
        21: ifeq          83
        24: aload_3
        25: invokeinterface #8,  1            // InterfaceMethod java/util/Iterator.next:()Ljava/lang/Object;
        30: checkcast     #9                  // class dk/brics/automaton/State
        33: astore        4
        35: aload         4
        37: iload_2
        38: invokevirtual #46                 // Method dk/brics/automaton/State.step:(I)Ldk/brics/automaton/State;
        41: astore        5
        43: aload         5
        45: ifnull        80
        48: new           #9                  // class dk/brics/automaton/State
        51: dup
        52: invokespecial #25                 // Method dk/brics/automaton/State."<init>":()V
        55: astore        6
        57: aload         6
        59: aload_1
        60: aload         6
        62: invokestatic  #45                 // Method addSetTransitions:(Ldk/brics/automaton/State;Ljava/lang/String;Ldk/brics/automaton/State;)V
        65: aload         4
        67: aload_1
        68: aload         6
        70: invokestatic  #45                 // Method addSetTransitions:(Ldk/brics/automaton/State;Ljava/lang/String;Ldk/brics/automaton/State;)V
        73: aload         6
        75: aload         5
        77: invokevirtual #26                 // Method dk/brics/automaton/State.addEpsilon:(Ldk/brics/automaton/State;)V
        80: goto          15
        83: aload_0
        84: iconst_0
        85: putfield      #27                 // Field dk/brics/automaton/Automaton.deterministic:Z
        88: aload_0
        89: invokevirtual #43                 // Method dk/brics/automaton/Automaton.removeDeadTransitions:()V
        92: aload_0
        93: invokevirtual #47                 // Method dk/brics/automaton/Automaton.checkMinimizeAlways:()V
        96: aload_0
        97: areturn
      LineNumberTable:
        line 180: 0
        line 181: 5
        line 182: 35
        line 183: 43
        line 185: 48
        line 186: 57
        line 187: 65
        line 188: 73
        line 190: 80
        line 192: 83
        line 193: 88
        line 194: 92
        line 195: 96
      StackMapTable: number_of_entries = 3
        frame_type = 252 /* append */
          offset_delta = 15
          locals = [ class java/util/Iterator ]
        frame_type = 251 /* same_frame_extended */
          offset_delta = 64
        frame_type = 250 /* chop */
          offset_delta = 2

  public static dk.brics.automaton.Automaton subst(dk.brics.automaton.Automaton, java.util.Map<java.lang.Integer, java.util.Set<java.lang.Integer>>);
    descriptor: (Ldk/brics/automaton/Automaton;Ljava/util/Map;)Ldk/brics/automaton/Automaton;
    flags: (0x0009) ACC_PUBLIC, ACC_STATIC
    Code:
      stack=6, locals=13, args_size=2
         0: aload_1
         1: invokeinterface #48,  1           // InterfaceMethod java/util/Map.isEmpty:()Z
         6: ifeq          14
         9: aload_0
        10: invokevirtual #49                 // Method dk/brics/automaton/Automaton.cloneIfRequired:()Ldk/brics/automaton/Automaton;
        13: areturn
        14: new           #50                 // class java/util/TreeSet
        17: dup
        18: aload_1
        19: invokeinterface #51,  1           // InterfaceMethod java/util/Map.keySet:()Ljava/util/Set;
        24: invokespecial #52                 // Method java/util/TreeSet."<init>":(Ljava/util/Collection;)V
        27: astore_2
        28: aload_2
        29: invokeinterface #53,  1           // InterfaceMethod java/util/Set.size:()I
        34: newarray       int
        36: astore_3
        37: iconst_0
        38: istore        4
        40: aload_2
        41: invokeinterface #6,  1            // InterfaceMethod java/util/Set.iterator:()Ljava/util/Iterator;
        46: astore        5
        48: aload         5
        50: invokeinterface #7,  1            // InterfaceMethod java/util/Iterator.hasNext:()Z
        55: ifeq          85
        58: aload         5
        60: invokeinterface #8,  1            // InterfaceMethod java/util/Iterator.next:()Ljava/lang/Object;
        65: checkcast     #54                 // class java/lang/Integer
        68: invokevirtual #55                 // Method java/lang/Integer.intValue:()I
        71: istore        6
        73: aload_3
        74: iload         4
        76: iinc          4, 1
        79: iload         6
        81: iastore
        82: goto          48
        85: aload_0
        86: invokevirtual #44                 // Method dk/brics/automaton/Automaton.cloneExpandedIfRequired:()Ldk/brics/automaton/Automaton;
        89: astore_0
        90: aload_0
        91: invokevirtual #4                  // Method dk/brics/automaton/Automaton.getStates:()Ljava/util/Set;
        94: invokeinterface #6,  1            // InterfaceMethod java/util/Set.iterator:()Ljava/util/Iterator;
        99: astore        5
       101: aload         5
       103: invokeinterface #7,  1            // InterfaceMethod java/util/Iterator.hasNext:()Z
       108: ifeq          533
       111: aload         5
       113: invokeinterface #8,  1            // InterfaceMethod java/util/Iterator.next:()Ljava/lang/Object;
       118: checkcast     #9                  // class dk/brics/automaton/State
       121: astore        6
       123: aload         6
       125: getfield      #23                 // Field dk/brics/automaton/State.transitions:Ljava/util/Set;
       128: astore        7
       130: aload         6
       132: invokevirtual #56                 // Method dk/brics/automaton/State.resetTransitions:()V
       135: aload         7
       137: invokeinterface #6,  1            // InterfaceMethod java/util/Set.iterator:()Ljava/util/Iterator;
       142: astore        8
       144: aload         8
       146: invokeinterface #7,  1            // InterfaceMethod java/util/Iterator.hasNext:()Z
       151: ifeq          530
       154: aload         8
       156: invokeinterface #8,  1            // InterfaceMethod java/util/Iterator.next:()Ljava/lang/Object;
       161: checkcast     #15                 // class dk/brics/automaton/Transition
       164: astore        9
       166: aload         9
       168: getfield      #18                 // Field dk/brics/automaton/Transition.min:I
       171: aload_3
       172: invokestatic  #57                 // Method findIndex:(I[I)I
       175: istore        10
       177: aload         9
       179: getfield      #18                 // Field dk/brics/automaton/Transition.min:I
       182: aload         9
       184: getfield      #19                 // Field dk/brics/automaton/Transition.max:I
       187: if_icmpgt     527
       190: aload_3
       191: iload         10
       193: iaload
       194: aload         9
       196: getfield      #18                 // Field dk/brics/automaton/Transition.min:I
       199: if_icmple     282
       202: aload_3
       203: iload         10
       205: iaload
       206: iconst_1
       207: isub
       208: istore        11
       210: aload         9
       212: getfield      #19                 // Field dk/brics/automaton/Transition.max:I
       215: iload         11
       217: if_icmpge     227
       220: aload         9
       222: getfield      #19                 // Field dk/brics/automaton/Transition.max:I
       225: istore        11
       227: aload         6
       229: getfield      #23                 // Field dk/brics/automaton/State.transitions:Ljava/util/Set;
       232: new           #15                 // class dk/brics/automaton/Transition
       235: dup
       236: aload         9
       238: getfield      #18                 // Field dk/brics/automaton/Transition.min:I
       241: iload         11
       243: aload         9
       245: getfield      #16                 // Field dk/brics/automaton/Transition.to:Ldk/brics/automaton/State;
       248: invokespecial #20                 // Method dk/brics/automaton/Transition."<init>":(IILdk/brics/automaton/State;)V
       251: invokeinterface #42,  2           // InterfaceMethod java/util/Set.add:(Ljava/lang/Object;)Z
       256: pop
       257: iload         11
       259: iconst_1
       260: iadd
       261: getstatic     #58                 // Field dk/brics/automaton/Transition.MAX_VALUE:I
       264: if_icmple     270
       267: goto          527
       270: aload         9
       272: iload         11
       274: iconst_1
       275: iadd
       276: putfield      #18                 // Field dk/brics/automaton/Transition.min:I
       279: goto          177
       282: aload_3
       283: iload         10
       285: iaload
       286: aload         9
       288: getfield      #18                 // Field dk/brics/automaton/Transition.min:I
       291: if_icmpge     394
       294: iload         10
       296: iconst_1
       297: iadd
       298: aload_3
       299: arraylength
       300: if_icmpge     317
       303: aload_3
       304: iinc          10, 1
       307: iload         10
       309: iaload
       310: iconst_1
       311: isub
       312: istore        11
       314: goto          322
       317: getstatic     #58                 // Field dk/brics/automaton/Transition.MAX_VALUE:I
       320: istore        11
       322: aload         9
       324: getfield      #19                 // Field dk/brics/automaton/Transition.max:I
       327: iload         11
       329: if_icmpge     339
       332: aload         9
       334: getfield      #19                 // Field dk/brics/automaton/Transition.max:I
       337: istore        11
       339: aload         6
       341: getfield      #23                 // Field dk/brics/automaton/State.transitions:Ljava/util/Set;
       344: new           #15                 // class dk/brics/automaton/Transition
       347: dup
       348: aload         9
       350: getfield      #18                 // Field dk/brics/automaton/Transition.min:I
       353: iload         11
       355: aload         9
       357: getfield      #16                 // Field dk/brics/automaton/Transition.to:Ldk/brics/automaton/State;
       360: invokespecial #20                 // Method dk/brics/automaton/Transition."<init>":(IILdk/brics/automaton/State;)V
       363: invokeinterface #42,  2           // InterfaceMethod java/util/Set.add:(Ljava/lang/Object;)Z
       368: pop
       369: iload         11
       371: iconst_1
       372: iadd
       373: getstatic     #58                 // Field dk/brics/automaton/Transition.MAX_VALUE:I
       376: if_icmple     382
       379: goto          527
       382: aload         9
       384: iload         11
       386: iconst_1
       387: iadd
       388: putfield      #18                 // Field dk/brics/automaton/Transition.min:I
       391: goto          177
       394: aload_1
       395: aload         9
       397: getfield      #18                 // Field dk/brics/automaton/Transition.min:I
       400: invokestatic  #59                 // Method java/lang/Integer.valueOf:(I)Ljava/lang/Integer;
       403: invokeinterface #60,  2           // InterfaceMethod java/util/Map.get:(Ljava/lang/Object;)Ljava/lang/Object;
       408: checkcast     #22                 // class java/util/Set
       411: invokeinterface #6,  1            // InterfaceMethod java/util/Set.iterator:()Ljava/util/Iterator;
       416: astore        11
       418: aload         11
       420: invokeinterface #7,  1            // InterfaceMethod java/util/Iterator.hasNext:()Z
       425: ifeq          471
       428: aload         11
       430: invokeinterface #8,  1            // InterfaceMethod java/util/Iterator.next:()Ljava/lang/Object;
       435: checkcast     #54                 // class java/lang/Integer
       438: invokevirtual #55                 // Method java/lang/Integer.intValue:()I
       441: istore        12
       443: aload         6
       445: getfield      #23                 // Field dk/brics/automaton/State.transitions:Ljava/util/Set;
       448: new           #15                 // class dk/brics/automaton/Transition
       451: dup
       452: iload         12
       454: aload         9
       456: getfield      #16                 // Field dk/brics/automaton/Transition.to:Ldk/brics/automaton/State;
       459: invokespecial #41                 // Method dk/brics/automaton/Transition."<init>":(ILdk/brics/automaton/State;)V
       462: invokeinterface #42,  2           // InterfaceMethod java/util/Set.add:(Ljava/lang/Object;)Z
       467: pop
       468: goto          418
       471: aload         9
       473: getfield      #18                 // Field dk/brics/automaton/Transition.min:I
       476: iconst_1
       477: iadd
       478: getstatic     #58                 // Field dk/brics/automaton/Transition.MAX_VALUE:I
       481: if_icmple     487
       484: goto          527
       487: aload         9
       489: dup
       490: getfield      #18                 // Field dk/brics/automaton/Transition.min:I
       493: iconst_1
       494: iadd
       495: putfield      #18                 // Field dk/brics/automaton/Transition.min:I
       498: iload         10
       500: iconst_1
       501: iadd
       502: aload_3
       503: arraylength
       504: if_icmpge     177
       507: aload_3
       508: iload         10
       510: iconst_1
       511: iadd
       512: iaload
       513: aload         9
       515: getfield      #18                 // Field dk/brics/automaton/Transition.min:I
       518: if_icmpne     177
       521: iinc          10, 1
       524: goto          177
       527: goto          144
       530: goto          101
       533: aload_0
       534: iconst_0
       535: putfield      #27                 // Field dk/brics/automaton/Automaton.deterministic:Z
       538: aload_0
       539: invokevirtual #43                 // Method dk/brics/automaton/Automaton.removeDeadTransitions:()V
       542: aload_0
       543: invokevirtual #47                 // Method dk/brics/automaton/Automaton.checkMinimizeAlways:()V
       546: aload_0
       547: areturn
      LineNumberTable:
        line 208: 0
        line 209: 9
        line 210: 14
        line 211: 28
        line 212: 37
        line 213: 40
        line 214: 73
        line 215: 85
        line 216: 90
        line 217: 123
        line 218: 130
        line 219: 135
        line 220: 166
        line 221: 177
        line 222: 190
        line 223: 202
        line 224: 210
        line 225: 220
        line 226: 227
        line 227: 257
        line 228: 267
        line 229: 270
        line 230: 279
        line 232: 294
        line 233: 303
        line 235: 317
        line 236: 322
        line 237: 332
        line 238: 339
        line 239: 369
        line 240: 379
        line 241: 382
        line 242: 391
        line 243: 394
        line 244: 443
        line 245: 471
        line 246: 484
        line 247: 487
        line 248: 498
        line 249: 521
        line 252: 527
        line 253: 530
        line 254: 533
        line 255: 538
        line 256: 542
        line 257: 546
      StackMapTable: number_of_entries = 20
        frame_type = 14 /* same */
        frame_type = 255 /* full_frame */
          offset_delta = 33
          locals = [ class dk/brics/automaton/Automaton, class java/util/Map, class java/util/Set, class "[I", int, class java/util/Iterator ]
          stack = []
        frame_type = 250 /* chop */
          offset_delta = 36
        frame_type = 252 /* append */
          offset_delta = 15
          locals = [ class java/util/Iterator ]
        frame_type = 254 /* append */
          offset_delta = 42
          locals = [ class dk/brics/automaton/State, class java/util/Set, class java/util/Iterator ]
        frame_type = 253 /* append */
          offset_delta = 32
          locals = [ class dk/brics/automaton/Transition, int ]
        frame_type = 252 /* append */
          offset_delta = 49
          locals = [ int ]
        frame_type = 42 /* same */
        frame_type = 250 /* chop */
          offset_delta = 11
        frame_type = 34 /* same */
        frame_type = 252 /* append */
          offset_delta = 4
          locals = [ int ]
        frame_type = 16 /* same */
        frame_type = 42 /* same */
        frame_type = 250 /* chop */
          offset_delta = 11
        frame_type = 252 /* append */
          offset_delta = 23
          locals = [ class java/util/Iterator ]
        frame_type = 250 /* chop */
          offset_delta = 52
        frame_type = 15 /* same */
        frame_type = 249 /* chop */
          offset_delta = 39
        frame_type = 248 /* chop */
          offset_delta = 2
        frame_type = 250 /* chop */
          offset_delta = 2
    Signature: #129                         // (Ldk/brics/automaton/Automaton;Ljava/util/Map<Ljava/lang/Integer;Ljava/util/Set<Ljava/lang/Integer;>;>;)Ldk/brics/automaton/Automaton;

  static int findIndex(int, int[]);
    descriptor: (I[I)I
    flags: (0x0008) ACC_STATIC
    Code:
      stack=2, locals=5, args_size=2
         0: iconst_0
         1: istore_2
         2: aload_1
         3: arraylength
         4: istore_3
         5: iload_3
         6: iload_2
         7: isub
         8: iconst_1
         9: if_icmple     53
        12: iload_2
        13: iload_3
        14: iadd
        15: iconst_1
        16: iushr
        17: istore        4
        19: aload_1
        20: iload         4
        22: iaload
        23: iload_0
        24: if_icmple     33
        27: iload         4
        29: istore_3
        30: goto          50
        33: aload_1
        34: iload         4
        36: iaload
        37: iload_0
        38: if_icmpge     47
        41: iload         4
        43: istore_2
        44: goto          50
        47: iload         4
        49: ireturn
        50: goto          5
        53: iload_2
        54: ireturn
      LineNumberTable:
        line 265: 0
        line 266: 2
        line 267: 5
        line 268: 12
        line 269: 19
        line 270: 27
        line 271: 33
        line 272: 41
        line 274: 47
        line 275: 50
        line 276: 53
      StackMapTable: number_of_entries = 5
        frame_type = 253 /* append */
          offset_delta = 5
          locals = [ int, int ]
        frame_type = 252 /* append */
          offset_delta = 27
          locals = [ int ]
        frame_type = 13 /* same */
        frame_type = 250 /* chop */
          offset_delta = 2
        frame_type = 2 /* same */

  public static dk.brics.automaton.Automaton subst(dk.brics.automaton.Automaton, int, java.lang.String);
    descriptor: (Ldk/brics/automaton/Automaton;ILjava/lang/String;)Ldk/brics/automaton/Automaton;
    flags: (0x0009) ACC_PUBLIC, ACC_STATIC
    Code:
      stack=6, locals=13, args_size=3
         0: aload_0
         1: invokevirtual #44                 // Method dk/brics/automaton/Automaton.cloneExpandedIfRequired:()Ldk/brics/automaton/Automaton;
         4: astore_0
         5: new           #10                 // class java/util/HashSet
         8: dup
         9: invokespecial #11                 // Method java/util/HashSet."<init>":()V
        12: astore_3
        13: aload_0
        14: invokevirtual #4                  // Method dk/brics/automaton/Automaton.getStates:()Ljava/util/Set;
        17: invokeinterface #6,  1            // InterfaceMethod java/util/Set.iterator:()Ljava/util/Iterator;
        22: astore        4
        24: aload         4
        26: invokeinterface #7,  1            // InterfaceMethod java/util/Iterator.hasNext:()Z
        31: ifeq          326
        34: aload         4
        36: invokeinterface #8,  1            // InterfaceMethod java/util/Iterator.next:()Ljava/lang/Object;
        41: checkcast     #9                  // class dk/brics/automaton/State
        44: astore        5
        46: aload         5
        48: getfield      #23                 // Field dk/brics/automaton/State.transitions:Ljava/util/Set;
        51: astore        6
        53: aload         5
        55: invokevirtual #56                 // Method dk/brics/automaton/State.resetTransitions:()V
        58: aload         6
        60: invokeinterface #6,  1            // InterfaceMethod java/util/Set.iterator:()Ljava/util/Iterator;
        65: astore        7
        67: aload         7
        69: invokeinterface #7,  1            // InterfaceMethod java/util/Iterator.hasNext:()Z
        74: ifeq          323
        77: aload         7
        79: invokeinterface #8,  1            // InterfaceMethod java/util/Iterator.next:()Ljava/lang/Object;
        84: checkcast     #15                 // class dk/brics/automaton/Transition
        87: astore        8
        89: aload         8
        91: getfield      #19                 // Field dk/brics/automaton/Transition.max:I
        94: iload_1
        95: if_icmplt     107
        98: aload         8
       100: getfield      #18                 // Field dk/brics/automaton/Transition.min:I
       103: iload_1
       104: if_icmple     123
       107: aload         5
       109: getfield      #23                 // Field dk/brics/automaton/State.transitions:Ljava/util/Set;
       112: aload         8
       114: invokeinterface #42,  2           // InterfaceMethod java/util/Set.add:(Ljava/lang/Object;)Z
       119: pop
       120: goto          320
       123: aload         8
       125: getfield      #18                 // Field dk/brics/automaton/Transition.min:I
       128: iload_1
       129: if_icmpge     163
       132: aload         5
       134: getfield      #23                 // Field dk/brics/automaton/State.transitions:Ljava/util/Set;
       137: new           #15                 // class dk/brics/automaton/Transition
       140: dup
       141: aload         8
       143: getfield      #18                 // Field dk/brics/automaton/Transition.min:I
       146: iload_1
       147: iconst_1
       148: isub
       149: aload         8
       151: getfield      #16                 // Field dk/brics/automaton/Transition.to:Ldk/brics/automaton/State;
       154: invokespecial #20                 // Method dk/brics/automaton/Transition."<init>":(IILdk/brics/automaton/State;)V
       157: invokeinterface #42,  2           // InterfaceMethod java/util/Set.add:(Ljava/lang/Object;)Z
       162: pop
       163: aload         8
       165: getfield      #19                 // Field dk/brics/automaton/Transition.max:I
       168: iload_1
       169: if_icmple     203
       172: aload         5
       174: getfield      #23                 // Field dk/brics/automaton/State.transitions:Ljava/util/Set;
       177: new           #15                 // class dk/brics/automaton/Transition
       180: dup
       181: iload_1
       182: iconst_1
       183: iadd
       184: aload         8
       186: getfield      #19                 // Field dk/brics/automaton/Transition.max:I
       189: aload         8
       191: getfield      #16                 // Field dk/brics/automaton/Transition.to:Ldk/brics/automaton/State;
       194: invokespecial #20                 // Method dk/brics/automaton/Transition."<init>":(IILdk/brics/automaton/State;)V
       197: invokeinterface #42,  2           // InterfaceMethod java/util/Set.add:(Ljava/lang/Object;)Z
       202: pop
       203: aload_2
       204: invokevirtual #61                 // Method java/lang/String.length:()I
       207: ifne          234
       210: aload_3
       211: new           #62                 // class dk/brics/automaton/StatePair
       214: dup
       215: aload         5
       217: aload         8
       219: getfield      #16                 // Field dk/brics/automaton/Transition.to:Ldk/brics/automaton/State;
       222: invokespecial #63                 // Method dk/brics/automaton/StatePair."<init>":(Ldk/brics/automaton/State;Ldk/brics/automaton/State;)V
       225: invokeinterface #42,  2           // InterfaceMethod java/util/Set.add:(Ljava/lang/Object;)Z
       230: pop
       231: goto          320
       234: aload         5
       236: astore        9
       238: aload_2
       239: invokestatic  #39                 // Method dk/brics/automaton/StringUnionOperations.cpCount:(Ljava/lang/String;)I
       242: istore        10
       244: iconst_0
       245: istore        11
       247: iload         11
       249: iload         10
       251: if_icmpge     320
       254: iload         11
       256: iconst_1
       257: iadd
       258: aload_2
       259: invokevirtual #61                 // Method java/lang/String.length:()I
       262: if_icmpne     275
       265: aload         8
       267: getfield      #16                 // Field dk/brics/automaton/Transition.to:Ldk/brics/automaton/State;
       270: astore        12
       272: goto          284
       275: new           #9                  // class dk/brics/automaton/State
       278: dup
       279: invokespecial #25                 // Method dk/brics/automaton/State."<init>":()V
       282: astore        12
       284: aload         9
       286: getfield      #23                 // Field dk/brics/automaton/State.transitions:Ljava/util/Set;
       289: new           #15                 // class dk/brics/automaton/Transition
       292: dup
       293: aload_2
       294: iload         11
       296: invokestatic  #40                 // Method dk/brics/automaton/StringUnionOperations.cpAt:(Ljava/lang/String;I)I
       299: aload         12
       301: invokespecial #41                 // Method dk/brics/automaton/Transition."<init>":(ILdk/brics/automaton/State;)V
       304: invokeinterface #42,  2           // InterfaceMethod java/util/Set.add:(Ljava/lang/Object;)Z
       309: pop
       310: aload         12
       312: astore        9
       314: iinc          11, 1
       317: goto          247
       320: goto          67
       323: goto          24
       326: aload_0
       327: aload_3
       328: invokevirtual #64                 // Method dk/brics/automaton/Automaton.addEpsilons:(Ljava/util/Collection;)V
       331: aload_0
       332: iconst_0
       333: putfield      #27                 // Field dk/brics/automaton/Automaton.deterministic:Z
       336: aload_0
       337: invokevirtual #43                 // Method dk/brics/automaton/Automaton.removeDeadTransitions:()V
       340: aload_0
       341: invokevirtual #47                 // Method dk/brics/automaton/Automaton.checkMinimizeAlways:()V
       344: aload_0
       345: areturn
      LineNumberTable:
        line 286: 0
        line 287: 5
        line 288: 13
        line 289: 46
        line 290: 53
        line 291: 58
        line 292: 89
        line 293: 107
        line 295: 123
        line 296: 132
        line 297: 163
        line 298: 172
        line 299: 203
        line 300: 210
        line 302: 234
        line 303: 238
        line 304: 244
        line 306: 254
        line 307: 265
        line 309: 275
        line 310: 284
        line 311: 310
        line 304: 314
        line 292: 320
        line 315: 323
        line 316: 326
        line 317: 331
        line 318: 336
        line 319: 340
        line 320: 344
      StackMapTable: number_of_entries = 13
        frame_type = 253 /* append */
          offset_delta = 24
          locals = [ class java/util/Set, class java/util/Iterator ]
        frame_type = 254 /* append */
          offset_delta = 42
          locals = [ class dk/brics/automaton/State, class java/util/Set, class java/util/Iterator ]
        frame_type = 252 /* append */
          offset_delta = 39
          locals = [ class dk/brics/automaton/Transition ]
        frame_type = 15 /* same */
        frame_type = 39 /* same */
        frame_type = 39 /* same */
        frame_type = 30 /* same */
        frame_type = 254 /* append */
          offset_delta = 12
          locals = [ class dk/brics/automaton/State, int, int ]
        frame_type = 27 /* same */
        frame_type = 252 /* append */
          offset_delta = 8
          locals = [ class dk/brics/automaton/State ]
        frame_type = 255 /* full_frame */
          offset_delta = 35
          locals = [ class dk/brics/automaton/Automaton, int, class java/lang/String, class java/util/Set, class java/util/Iterator, class dk/brics/automaton/State, class java/util/Set, class java/util/Iterator ]
          stack = []
        frame_type = 248 /* chop */
          offset_delta = 2
        frame_type = 250 /* chop */
          offset_delta = 2

  public static dk.brics.automaton.Automaton homomorph(dk.brics.automaton.Automaton, int[], int[]);
    descriptor: (Ldk/brics/automaton/Automaton;[I[I)Ldk/brics/automaton/Automaton;
    flags: (0x0009) ACC_PUBLIC, ACC_STATIC
    Code:
      stack=6, locals=13, args_size=3
         0: aload_0
         1: invokevirtual #44                 // Method dk/brics/automaton/Automaton.cloneExpandedIfRequired:()Ldk/brics/automaton/Automaton;
         4: astore_0
         5: aload_0
         6: invokevirtual #4                  // Method dk/brics/automaton/Automaton.getStates:()Ljava/util/Set;
         9: invokeinterface #6,  1            // InterfaceMethod java/util/Set.iterator:()Ljava/util/Iterator;
        14: astore_3
        15: aload_3
        16: invokeinterface #7,  1            // InterfaceMethod java/util/Iterator.hasNext:()Z
        21: ifeq          224
        24: aload_3
        25: invokeinterface #8,  1            // InterfaceMethod java/util/Iterator.next:()Ljava/lang/Object;
        30: checkcast     #9                  // class dk/brics/automaton/State
        33: astore        4
        35: aload         4
        37: getfield      #23                 // Field dk/brics/automaton/State.transitions:Ljava/util/Set;
        40: astore        5
        42: aload         4
        44: invokevirtual #56                 // Method dk/brics/automaton/State.resetTransitions:()V
        47: aload         5
        49: invokeinterface #6,  1            // InterfaceMethod java/util/Set.iterator:()Ljava/util/Iterator;
        54: astore        6
        56: aload         6
        58: invokeinterface #7,  1            // InterfaceMethod java/util/Iterator.hasNext:()Z
        63: ifeq          221
        66: aload         6
        68: invokeinterface #8,  1            // InterfaceMethod java/util/Iterator.next:()Ljava/lang/Object;
        73: checkcast     #15                 // class dk/brics/automaton/Transition
        76: astore        7
        78: aload         7
        80: getfield      #18                 // Field dk/brics/automaton/Transition.min:I
        83: istore        8
        85: iload         8
        87: aload         7
        89: getfield      #19                 // Field dk/brics/automaton/Transition.max:I
        92: if_icmpgt     218
        95: iload         8
        97: aload_1
        98: invokestatic  #57                 // Method findIndex:(I[I)I
       101: istore        9
       103: aload_2
       104: iload         9
       106: iaload
       107: iload         8
       109: iadd
       110: aload_1
       111: iload         9
       113: iaload
       114: isub
       115: istore        10
       117: iload         9
       119: iconst_1
       120: iadd
       121: aload_1
       122: arraylength
       123: if_icmpne     132
       126: getstatic     #58                 // Field dk/brics/automaton/Transition.MAX_VALUE:I
       129: goto          140
       132: aload_1
       133: iload         9
       135: iconst_1
       136: iadd
       137: iaload
       138: iconst_1
       139: isub
       140: istore        11
       142: iload         11
       144: aload         7
       146: getfield      #19                 // Field dk/brics/automaton/Transition.max:I
       149: if_icmpge     164
       152: iload         11
       154: iconst_1
       155: iadd
       156: iload         8
       158: isub
       159: istore        12
       161: goto          176
       164: aload         7
       166: getfield      #19                 // Field dk/brics/automaton/Transition.max:I
       169: iconst_1
       170: iadd
       171: iload         8
       173: isub
       174: istore        12
       176: aload         4
       178: getfield      #23                 // Field dk/brics/automaton/State.transitions:Ljava/util/Set;
       181: new           #15                 // class dk/brics/automaton/Transition
       184: dup
       185: iload         10
       187: iload         10
       189: iload         12
       191: iadd
       192: iconst_1
       193: isub
       194: aload         7
       196: getfield      #16                 // Field dk/brics/automaton/Transition.to:Ldk/brics/automaton/State;
       199: invokespecial #20                 // Method dk/brics/automaton/Transition."<init>":(IILdk/brics/automaton/State;)V
       202: invokeinterface #42,  2           // InterfaceMethod java/util/Set.add:(Ljava/lang/Object;)Z
       207: pop
       208: iload         8
       210: iload         12
       212: iadd
       213: istore        8
       215: goto          85
       218: goto          56
       221: goto          15
       224: aload_0
       225: iconst_0
       226: putfield      #27                 // Field dk/brics/automaton/Automaton.deterministic:Z
       229: aload_0
       230: invokevirtual #43                 // Method dk/brics/automaton/Automaton.removeDeadTransitions:()V
       233: aload_0
       234: invokevirtual #47                 // Method dk/brics/automaton/Automaton.checkMinimizeAlways:()V
       237: aload_0
       238: areturn
      LineNumberTable:
        line 336: 0
        line 337: 5
        line 338: 35
        line 339: 42
        line 340: 47
        line 341: 78
        line 342: 85
        line 343: 95
        line 344: 103
        line 345: 117
        line 347: 142
        line 348: 152
        line 350: 164
        line 351: 176
        line 352: 208
        line 353: 215
        line 354: 218
        line 355: 221
        line 356: 224
        line 357: 229
        line 358: 233
        line 359: 237
      StackMapTable: number_of_entries = 10
        frame_type = 252 /* append */
          offset_delta = 15
          locals = [ class java/util/Iterator ]
        frame_type = 254 /* append */
          offset_delta = 40
          locals = [ class dk/brics/automaton/State, class java/util/Set, class java/util/Iterator ]
        frame_type = 253 /* append */
          offset_delta = 28
          locals = [ class dk/brics/automaton/Transition, int ]
        frame_type = 253 /* append */
          offset_delta = 46
          locals = [ int, int ]
        frame_type = 71 /* same_locals_1_stack_item */
          stack = [ int ]
        frame_type = 252 /* append */
          offset_delta = 23
          locals = [ int ]
        frame_type = 252 /* append */
          offset_delta = 11
          locals = [ int ]
        frame_type = 255 /* full_frame */
          offset_delta = 41
          locals = [ class dk/brics/automaton/Automaton, class "[I", class "[I", class java/util/Iterator, class dk/brics/automaton/State, class java/util/Set, class java/util/Iterator ]
          stack = []
        frame_type = 248 /* chop */
          offset_delta = 2
        frame_type = 250 /* chop */
          offset_delta = 2

  public static dk.brics.automaton.Automaton projectChars(dk.brics.automaton.Automaton, java.util.Set<java.lang.Character>);
    descriptor: (Ldk/brics/automaton/Automaton;Ljava/util/Set;)Ldk/brics/automaton/Automaton;
    flags: (0x0009) ACC_PUBLIC, ACC_STATIC
    Code:
      stack=6, locals=15, args_size=2
         0: aload_1
         1: aload_1
         2: invokeinterface #53,  1           // InterfaceMethod java/util/Set.size:()I
         7: anewarray     #65                 // class java/lang/Character
        10: invokeinterface #66,  2           // InterfaceMethod java/util/Set.toArray:([Ljava/lang/Object;)[Ljava/lang/Object;
        15: checkcast     #67                 // class "[Ljava/lang/Character;"
        18: astore_2
        19: aload_2
        20: arraylength
        21: newarray       int
        23: astore_3
        24: iconst_0
        25: istore        4
        27: iconst_0
        28: istore        5
        30: iload         5
        32: aload_2
        33: arraylength
        34: if_icmpge     67
        37: aload_2
        38: iload         5
        40: aaload
        41: ifnonnull     50
        44: iconst_1
        45: istore        4
        47: goto          61
        50: aload_3
        51: iload         5
        53: aload_2
        54: iload         5
        56: aaload
        57: invokevirtual #68                 // Method java/lang/Character.charValue:()C
        60: iastore
        61: iinc          5, 1
        64: goto          30
        67: aload_3
        68: invokestatic  #69                 // Method java/util/Arrays.sort:([I)V
        71: aload_0
        72: invokevirtual #37                 // Method dk/brics/automaton/Automaton.isSingleton:()Z
        75: ifeq          147
        78: iconst_0
        79: istore        5
        81: iload         5
        83: aload_0
        84: getfield      #38                 // Field dk/brics/automaton/Automaton.singleton:Ljava/lang/String;
        87: invokevirtual #61                 // Method java/lang/String.length:()I
        90: if_icmpge     142
        93: aload_0
        94: getfield      #38                 // Field dk/brics/automaton/Automaton.singleton:Ljava/lang/String;
        97: iload         5
        99: invokevirtual #70                 // Method java/lang/String.charAt:(I)C
       102: istore        6
       104: iload         4
       106: ifeq          123
       109: iload         6
       111: ldc           #71                 // int 57343
       113: if_icmple     136
       116: iload         6
       118: ldc           #72                 // int 63744
       120: if_icmpge     136
       123: aload_3
       124: iload         6
       126: invokestatic  #73                 // Method java/util/Arrays.binarySearch:([II)I
       129: ifge          136
       132: invokestatic  #74                 // Method dk/brics/automaton/BasicAutomata.makeEmpty:()Ldk/brics/automaton/Automaton;
       135: areturn
       136: iinc          5, 1
       139: goto          81
       142: aload_0
       143: invokevirtual #49                 // Method dk/brics/automaton/Automaton.cloneIfRequired:()Ldk/brics/automaton/Automaton;
       146: areturn
       147: new           #10                 // class java/util/HashSet
       150: dup
       151: invokespecial #11                 // Method java/util/HashSet."<init>":()V
       154: astore        5
       156: aload_0
       157: invokevirtual #44                 // Method dk/brics/automaton/Automaton.cloneExpandedIfRequired:()Ldk/brics/automaton/Automaton;
       160: astore_0
       161: aload_0
       162: invokevirtual #4                  // Method dk/brics/automaton/Automaton.getStates:()Ljava/util/Set;
       165: invokeinterface #6,  1            // InterfaceMethod java/util/Set.iterator:()Ljava/util/Iterator;
       170: astore        6
       172: aload         6
       174: invokeinterface #7,  1            // InterfaceMethod java/util/Iterator.hasNext:()Z
       179: ifeq          581
       182: aload         6
       184: invokeinterface #8,  1            // InterfaceMethod java/util/Iterator.next:()Ljava/lang/Object;
       189: checkcast     #9                  // class dk/brics/automaton/State
       192: astore        7
       194: new           #10                 // class java/util/HashSet
       197: dup
       198: invokespecial #11                 // Method java/util/HashSet."<init>":()V
       201: astore        8
       203: aload         7
       205: getfield      #23                 // Field dk/brics/automaton/State.transitions:Ljava/util/Set;
       208: invokeinterface #6,  1            // InterfaceMethod java/util/Set.iterator:()Ljava/util/Iterator;
       213: astore        9
       215: aload         9
       217: invokeinterface #7,  1            // InterfaceMethod java/util/Iterator.hasNext:()Z
       222: ifeq          571
       225: aload         9
       227: invokeinterface #8,  1            // InterfaceMethod java/util/Iterator.next:()Ljava/lang/Object;
       232: checkcast     #15                 // class dk/brics/automaton/Transition
       235: astore        10
       237: iconst_0
       238: istore        11
       240: aload         10
       242: getfield      #18                 // Field dk/brics/automaton/Transition.min:I
       245: ldc           #72                 // int 63744
       247: if_icmpge     406
       250: aload         10
       252: getfield      #19                 // Field dk/brics/automaton/Transition.max:I
       255: ldc           #71                 // int 57343
       257: if_icmple     406
       260: aload_3
       261: aload         10
       263: getfield      #18                 // Field dk/brics/automaton/Transition.min:I
       266: ldc           #75                 // int 57344
       268: if_icmple     279
       271: aload         10
       273: getfield      #18                 // Field dk/brics/automaton/Transition.min:I
       276: goto          281
       279: ldc           #75                 // int 57344
       281: invokestatic  #73                 // Method java/util/Arrays.binarySearch:([II)I
       284: istore        12
       286: iload         12
       288: ifge          301
       291: iload         12
       293: ineg
       294: iconst_1
       295: isub
       296: istore        12
       298: iconst_1
       299: istore        11
       301: aload_3
       302: aload         10
       304: getfield      #19                 // Field dk/brics/automaton/Transition.max:I
       307: ldc           #76                 // int 63743
       309: if_icmpge     320
       312: aload         10
       314: getfield      #19                 // Field dk/brics/automaton/Transition.max:I
       317: goto          322
       320: ldc           #76                 // int 63743
       322: invokestatic  #73                 // Method java/util/Arrays.binarySearch:([II)I
       325: istore        13
       327: iload         13
       329: ifge          342
       332: iload         13
       334: ineg
       335: iconst_2
       336: isub
       337: istore        13
       339: iconst_1
       340: istore        11
       342: iload         12
       344: istore        14
       346: iload         14
       348: iload         13
       350: if_icmpgt     406
       353: aload         8
       355: new           #15                 // class dk/brics/automaton/Transition
       358: dup
       359: aload_3
       360: iload         14
       362: iaload
       363: aload         10
       365: getfield      #16                 // Field dk/brics/automaton/Transition.to:Ldk/brics/automaton/State;
       368: invokespecial #41                 // Method dk/brics/automaton/Transition."<init>":(ILdk/brics/automaton/State;)V
       371: invokevirtual #21                 // Method java/util/HashSet.add:(Ljava/lang/Object;)Z
       374: pop
       375: iload         14
       377: iload         12
       379: if_icmple     400
       382: aload_3
       383: iload         14
       385: iconst_1
       386: isub
       387: iaload
       388: iconst_1
       389: iadd
       390: aload_3
       391: iload         14
       393: iaload
       394: if_icmpeq     400
       397: iconst_1
       398: istore        11
       400: iinc          14, 1
       403: goto          346
       406: iload         4
       408: ifeq          520
       411: aload         10
       413: getfield      #18                 // Field dk/brics/automaton/Transition.min:I
       416: ldc           #71                 // int 57343
       418: if_icmpgt     464
       421: aload         8
       423: new           #15                 // class dk/brics/automaton/Transition
       426: dup
       427: aload         10
       429: getfield      #18                 // Field dk/brics/automaton/Transition.min:I
       432: aload         10
       434: getfield      #19                 // Field dk/brics/automaton/Transition.max:I
       437: ldc           #71                 // int 57343
       439: if_icmpge     450
       442: aload         10
       444: getfield      #19                 // Field dk/brics/automaton/Transition.max:I
       447: goto          452
       450: ldc           #71                 // int 57343
       452: aload         10
       454: getfield      #16                 // Field dk/brics/automaton/Transition.to:Ldk/brics/automaton/State;
       457: invokespecial #20                 // Method dk/brics/automaton/Transition."<init>":(IILdk/brics/automaton/State;)V
       460: invokevirtual #21                 // Method java/util/HashSet.add:(Ljava/lang/Object;)Z
       463: pop
       464: aload         10
       466: getfield      #19                 // Field dk/brics/automaton/Transition.max:I
       469: ldc           #72                 // int 63744
       471: if_icmplt     543
       474: aload         8
       476: new           #15                 // class dk/brics/automaton/Transition
       479: dup
       480: aload         10
       482: getfield      #18                 // Field dk/brics/automaton/Transition.min:I
       485: ldc           #72                 // int 63744
       487: if_icmple     498
       490: aload         10
       492: getfield      #18                 // Field dk/brics/automaton/Transition.min:I
       495: goto          500
       498: ldc           #72                 // int 63744
       500: aload         10
       502: getfield      #19                 // Field dk/brics/automaton/Transition.max:I
       505: aload         10
       507: getfield      #16                 // Field dk/brics/automaton/Transition.to:Ldk/brics/automaton/State;
       510: invokespecial #20                 // Method dk/brics/automaton/Transition."<init>":(IILdk/brics/automaton/State;)V
       513: invokevirtual #21                 // Method java/util/HashSet.add:(Ljava/lang/Object;)Z
       516: pop
       517: goto          543
       520: aload         10
       522: getfield      #18                 // Field dk/brics/automaton/Transition.min:I
       525: ldc           #71                 // int 57343
       527: if_icmple     540
       530: aload         10
       532: getfield      #19                 // Field dk/brics/automaton/Transition.max:I
       535: ldc           #72                 // int 63744
       537: if_icmplt     543
       540: iconst_1
       541: istore        11
       543: iload         11
       545: ifeq          568
       548: aload         5
       550: new           #62                 // class dk/brics/automaton/StatePair
       553: dup
       554: aload         7
       556: aload         10
       558: getfield      #16                 // Field dk/brics/automaton/Transition.to:Ldk/brics/automaton/State;
       561: invokespecial #63                 // Method dk/brics/automaton/StatePair."<init>":(Ldk/brics/automaton/State;Ldk/brics/automaton/State;)V
       564: invokevirtual #21                 // Method java/util/HashSet.add:(Ljava/lang/Object;)Z
       567: pop
       568: goto          215
       571: aload         7
       573: aload         8
       575: putfield      #23                 // Field dk/brics/automaton/State.transitions:Ljava/util/Set;
       578: goto          172
       581: aload_0
       582: invokevirtual #77                 // Method dk/brics/automaton/Automaton.reduce:()V
       585: aload_0
       586: aload         5
       588: invokevirtual #64                 // Method dk/brics/automaton/Automaton.addEpsilons:(Ljava/util/Collection;)V
       591: aload_0
       592: invokevirtual #43                 // Method dk/brics/automaton/Automaton.removeDeadTransitions:()V
       595: aload_0
       596: invokevirtual #47                 // Method dk/brics/automaton/Automaton.checkMinimizeAlways:()V
       599: aload_0
       600: areturn
      LineNumberTable:
        line 372: 0
        line 373: 19
        line 374: 24
        line 375: 27
        line 376: 37
        line 377: 44
        line 379: 50
        line 375: 61
        line 380: 67
        line 381: 71
        line 382: 78
        line 383: 93
        line 384: 104
        line 385: 132
        line 382: 136
        line 387: 142
        line 389: 147
        line 390: 156
        line 391: 161
        line 392: 194
        line 393: 203
        line 394: 237
        line 395: 240
        line 396: 260
        line 397: 286
        line 398: 291
        line 399: 298
        line 401: 301
        line 402: 327
        line 403: 332
        line 404: 339
        line 406: 342
        line 407: 353
        line 408: 375
        line 409: 397
        line 406: 400
        line 412: 406
        line 413: 411
        line 414: 421
        line 415: 464
        line 416: 474
        line 417: 520
        line 418: 540
        line 419: 543
        line 420: 548
        line 421: 568
        line 422: 571
        line 423: 578
        line 424: 581
        line 425: 585
        line 426: 591
        line 427: 595
        line 428: 599
      StackMapTable: number_of_entries = 31
        frame_type = 255 /* full_frame */
          offset_delta = 30
          locals = [ class dk/brics/automaton/Automaton, class java/util/Set, class "[Ljava/lang/Character;", class "[I", int, int ]
          stack = []
        frame_type = 19 /* same */
        frame_type = 10 /* same */
        frame_type = 250 /* chop */
          offset_delta = 5
        frame_type = 252 /* append */
          offset_delta = 13
          locals = [ int ]
        frame_type = 252 /* append */
          offset_delta = 41
          locals = [ int ]
        frame_type = 250 /* chop */
          offset_delta = 12
        frame_type = 250 /* chop */
          offset_delta = 5
        frame_type = 4 /* same */
        frame_type = 253 /* append */
          offset_delta = 24
          locals = [ class java/util/HashSet, class java/util/Iterator ]
        frame_type = 254 /* append */
          offset_delta = 42
          locals = [ class dk/brics/automaton/State, class java/util/HashSet, class java/util/Iterator ]
        frame_type = 255 /* full_frame */
          offset_delta = 63
          locals = [ class dk/brics/automaton/Automaton, class java/util/Set, class "[Ljava/lang/Character;", class "[I", int, class java/util/HashSet, class java/util/Iterator, class dk/brics/automaton/State, class java/util/HashSet, class java/util/Iterator, class dk/brics/automaton/Transition, int ]
          stack = [ class "[I" ]
        frame_type = 255 /* full_frame */
          offset_delta = 1
          locals = [ class dk/brics/automaton/Automaton, class java/util/Set, class "[Ljava/lang/Character;", class "[I", int, class java/util/HashSet, class java/util/Iterator, class dk/brics/automaton/State, class java/util/HashSet, class java/util/Iterator, class dk/brics/automaton/Transition, int ]
          stack = [ class "[I", int ]
        frame_type = 252 /* append */
          offset_delta = 19
          locals = [ int ]
        frame_type = 82 /* same_locals_1_stack_item */
          stack = [ class "[I" ]
        frame_type = 255 /* full_frame */
          offset_delta = 1
          locals = [ class dk/brics/automaton/Automaton, class java/util/Set, class "[Ljava/lang/Character;", class "[I", int, class java/util/HashSet, class java/util/Iterator, class dk/brics/automaton/State, class java/util/HashSet, class java/util/Iterator, class dk/brics/automaton/Transition, int, int ]
          stack = [ class "[I", int ]
        frame_type = 252 /* append */
          offset_delta = 19
          locals = [ int ]
        frame_type = 252 /* append */
          offset_delta = 3
          locals = [ int ]
        frame_type = 53 /* same */
        frame_type = 248 /* chop */
          offset_delta = 5
        frame_type = 255 /* full_frame */
          offset_delta = 43
          locals = [ class dk/brics/automaton/Automaton, class java/util/Set, class "[Ljava/lang/Character;", class "[I", int, class java/util/HashSet, class java/util/Iterator, class dk/brics/automaton/State, class java/util/HashSet, class java/util/Iterator, class dk/brics/automaton/Transition, int ]
          stack = [ class java/util/HashSet, uninitialized 423, uninitialized 423, int ]
        frame_type = 255 /* full_frame */
          offset_delta = 1
          locals = [ class dk/brics/automaton/Automaton, class java/util/Set, class "[Ljava/lang/Character;", class "[I", int, class java/util/HashSet, class java/util/Iterator, class dk/brics/automaton/State, class java/util/HashSet, class java/util/Iterator, class dk/brics/automaton/Transition, int ]
          stack = [ class java/util/HashSet, uninitialized 423, uninitialized 423, int, int ]
        frame_type = 11 /* same */
        frame_type = 255 /* full_frame */
          offset_delta = 33
          locals = [ class dk/brics/automaton/Automaton, class java/util/Set, class "[Ljava/lang/Character;", class "[I", int, class java/util/HashSet, class java/util/Iterator, class dk/brics/automaton/State, class java/util/HashSet, class java/util/Iterator, class dk/brics/automaton/Transition, int ]
          stack = [ class java/util/HashSet, uninitialized 476, uninitialized 476 ]
        frame_type = 255 /* full_frame */
          offset_delta = 1
          locals = [ class dk/brics/automaton/Automaton, class java/util/Set, class "[Ljava/lang/Character;", class "[I", int, class java/util/HashSet, class java/util/Iterator, class dk/brics/automaton/State, class java/util/HashSet, class java/util/Iterator, class dk/brics/automaton/Transition, int ]
          stack = [ class java/util/HashSet, uninitialized 476, uninitialized 476, int ]
        frame_type = 19 /* same */
        frame_type = 19 /* same */
        frame_type = 2 /* same */
        frame_type = 249 /* chop */
          offset_delta = 24
        frame_type = 250 /* chop */
          offset_delta = 2
        frame_type = 248 /* chop */
          offset_delta = 9
    Signature: #138                         // (Ldk/brics/automaton/Automaton;Ljava/util/Set<Ljava/lang/Character;>;)Ldk/brics/automaton/Automaton;

  public static boolean isFinite(dk.brics.automaton.Automaton);
    descriptor: (Ldk/brics/automaton/Automaton;)Z
    flags: (0x0009) ACC_PUBLIC, ACC_STATIC
    Code:
      stack=4, locals=1, args_size=1
         0: aload_0
         1: invokevirtual #37                 // Method dk/brics/automaton/Automaton.isSingleton:()Z
         4: ifeq          9
         7: iconst_1
         8: ireturn
         9: aload_0
        10: getfield      #24                 // Field dk/brics/automaton/Automaton.initial:Ldk/brics/automaton/State;
        13: new           #10                 // class java/util/HashSet
        16: dup
        17: invokespecial #11                 // Method java/util/HashSet."<init>":()V
        20: new           #10                 // class java/util/HashSet
        23: dup
        24: invokespecial #11                 // Method java/util/HashSet."<init>":()V
        27: invokestatic  #78                 // Method isFinite:(Ldk/brics/automaton/State;Ljava/util/HashSet;Ljava/util/HashSet;)Z
        30: ireturn
      LineNumberTable:
        line 436: 0
        line 437: 7
        line 438: 9
      StackMapTable: number_of_entries = 1
        frame_type = 9 /* same */

  private static boolean isFinite(dk.brics.automaton.State, java.util.HashSet<dk.brics.automaton.State>, java.util.HashSet<dk.brics.automaton.State>);
    descriptor: (Ldk/brics/automaton/State;Ljava/util/HashSet;Ljava/util/HashSet;)Z
    flags: (0x000a) ACC_PRIVATE, ACC_STATIC
    Code:
      stack=3, locals=5, args_size=3
         0: aload_1
         1: aload_0
         2: invokevirtual #21                 // Method java/util/HashSet.add:(Ljava/lang/Object;)Z
         5: pop
         6: aload_0
         7: getfield      #23                 // Field dk/brics/automaton/State.transitions:Ljava/util/Set;
        10: invokeinterface #6,  1            // InterfaceMethod java/util/Set.iterator:()Ljava/util/Iterator;
        15: astore_3
        16: aload_3
        17: invokeinterface #7,  1            // InterfaceMethod java/util/Iterator.hasNext:()Z
        22: ifeq          78
        25: aload_3
        26: invokeinterface #8,  1            // InterfaceMethod java/util/Iterator.next:()Ljava/lang/Object;
        31: checkcast     #15                 // class dk/brics/automaton/Transition
        34: astore        4
        36: aload_1
        37: aload         4
        39: getfield      #16                 // Field dk/brics/automaton/Transition.to:Ldk/brics/automaton/State;
        42: invokevirtual #79                 // Method java/util/HashSet.contains:(Ljava/lang/Object;)Z
        45: ifne          73
        48: aload_2
        49: aload         4
        51: getfield      #16                 // Field dk/brics/automaton/Transition.to:Ldk/brics/automaton/State;
        54: invokevirtual #79                 // Method java/util/HashSet.contains:(Ljava/lang/Object;)Z
        57: ifne          75
        60: aload         4
        62: getfield      #16                 // Field dk/brics/automaton/Transition.to:Ldk/brics/automaton/State;
        65: aload_1
        66: aload_2
        67: invokestatic  #78                 // Method isFinite:(Ldk/brics/automaton/State;Ljava/util/HashSet;Ljava/util/HashSet;)Z
        70: ifne          75
        73: iconst_0
        74: ireturn
        75: goto          16
        78: aload_1
        79: aload_0
        80: invokevirtual #80                 // Method java/util/HashSet.remove:(Ljava/lang/Object;)Z
        83: pop
        84: aload_2
        85: aload_0
        86: invokevirtual #21                 // Method java/util/HashSet.add:(Ljava/lang/Object;)Z
        89: pop
        90: iconst_1
        91: ireturn
      LineNumberTable:
        line 446: 0
        line 447: 6
        line 448: 36
        line 449: 73
        line 448: 75
        line 450: 78
        line 451: 84
        line 452: 90
      StackMapTable: number_of_entries = 4
        frame_type = 252 /* append */
          offset_delta = 16
          locals = [ class java/util/Iterator ]
        frame_type = 252 /* append */
          offset_delta = 56
          locals = [ class dk/brics/automaton/Transition ]
        frame_type = 250 /* chop */
          offset_delta = 1
        frame_type = 250 /* chop */
          offset_delta = 2
    Signature: #142                         // (Ldk/brics/automaton/State;Ljava/util/HashSet<Ldk/brics/automaton/State;>;Ljava/util/HashSet<Ldk/brics/automaton/State;>;)Z

  public static java.util.Set<java.lang.String> getStrings(dk.brics.automaton.Automaton, int);
    descriptor: (Ldk/brics/automaton/Automaton;I)Ljava/util/Set;
    flags: (0x0009) ACC_PUBLIC, ACC_STATIC
    Code:
      stack=4, locals=3, args_size=2
         0: new           #10                 // class java/util/HashSet
         3: dup
         4: invokespecial #11                 // Method java/util/HashSet."<init>":()V
         7: astore_2
         8: aload_0
         9: invokevirtual #37                 // Method dk/brics/automaton/Automaton.isSingleton:()Z
        12: ifeq          38
        15: aload_0
        16: getfield      #38                 // Field dk/brics/automaton/Automaton.singleton:Ljava/lang/String;
        19: invokevirtual #61                 // Method java/lang/String.length:()I
        22: iload_1
        23: if_icmpne     38
        26: aload_2
        27: aload_0
        28: getfield      #38                 // Field dk/brics/automaton/Automaton.singleton:Ljava/lang/String;
        31: invokevirtual #21                 // Method java/util/HashSet.add:(Ljava/lang/Object;)Z
        34: pop
        35: goto          58
        38: iload_1
        39: iflt          58
        42: aload_0
        43: getfield      #24                 // Field dk/brics/automaton/Automaton.initial:Ldk/brics/automaton/State;
        46: aload_2
        47: new           #81                 // class java/lang/StringBuilder
        50: dup
        51: invokespecial #82                 // Method java/lang/StringBuilder."<init>":()V
        54: iload_1
        55: invokestatic  #83                 // Method getStrings:(Ldk/brics/automaton/State;Ljava/util/Set;Ljava/lang/StringBuilder;I)V
        58: aload_2
        59: areturn
      LineNumberTable:
        line 459: 0
        line 460: 8
        line 461: 26
        line 462: 38
        line 463: 42
        line 464: 58
      StackMapTable: number_of_entries = 2
        frame_type = 252 /* append */
          offset_delta = 38
          locals = [ class java/util/HashSet ]
        frame_type = 19 /* same */
    Signature: #145                         // (Ldk/brics/automaton/Automaton;I)Ljava/util/Set<Ljava/lang/String;>;

  private static void getStrings(dk.brics.automaton.State, java.util.Set<java.lang.String>, java.lang.StringBuilder, int);
    descriptor: (Ldk/brics/automaton/State;Ljava/util/Set;Ljava/lang/StringBuilder;I)V
    flags: (0x000a) ACC_PRIVATE, ACC_STATIC
    Code:
      stack=5, locals=7, args_size=4
         0: iload_3
         1: ifne          25
         4: aload_0
         5: getfield      #13                 // Field dk/brics/automaton/State.accept:Z
         8: ifeq          153
        11: aload_1
        12: aload_2
        13: invokevirtual #84                 // Method java/lang/StringBuilder.toString:()Ljava/lang/String;
        16: invokeinterface #42,  2           // InterfaceMethod java/util/Set.add:(Ljava/lang/Object;)Z
        21: pop
        22: goto          153
        25: aload_0
        26: getfield      #23                 // Field dk/brics/automaton/State.transitions:Ljava/util/Set;
        29: invokeinterface #6,  1            // InterfaceMethod java/util/Set.iterator:()Ljava/util/Iterator;
        34: astore        4
        36: aload         4
        38: invokeinterface #7,  1            // InterfaceMethod java/util/Iterator.hasNext:()Z
        43: ifeq          153
        46: aload         4
        48: invokeinterface #8,  1            // InterfaceMethod java/util/Iterator.next:()Ljava/lang/Object;
        53: checkcast     #15                 // class dk/brics/automaton/Transition
        56: astore        5
        58: aload         5
        60: getfield      #18                 // Field dk/brics/automaton/Transition.min:I
        63: istore        6
        65: iload         6
        67: aload         5
        69: getfield      #19                 // Field dk/brics/automaton/Transition.max:I
        72: if_icmpgt     150
        75: iload         6
        77: ldc           #85                 // int 65535
        79: if_icmple     112
        82: aload_2
        83: ldc           #86                 // String \\u{
        85: invokevirtual #87                 // Method java/lang/StringBuilder.append:(Ljava/lang/String;)Ljava/lang/StringBuilder;
        88: pop
        89: aload_2
        90: iload         6
        92: invokestatic  #88                 // Method java/lang/Integer.toHexString:(I)Ljava/lang/String;
        95: invokevirtual #89                 // Method java/lang/String.toUpperCase:()Ljava/lang/String;
        98: invokevirtual #87                 // Method java/lang/StringBuilder.append:(Ljava/lang/String;)Ljava/lang/StringBuilder;
       101: pop
       102: aload_2
       103: bipush        125
       105: invokevirtual #90                 // Method java/lang/StringBuilder.append:(C)Ljava/lang/StringBuilder;
       108: pop
       109: goto          120
       112: aload_2
       113: iload         6
       115: i2c
       116: invokevirtual #90                 // Method java/lang/StringBuilder.append:(C)Ljava/lang/StringBuilder;
       119: pop
       120: aload         5
       122: getfield      #16                 // Field dk/brics/automaton/Transition.to:Ldk/brics/automaton/State;
       125: aload_1
       126: aload_2
       127: iload_3
       128: iconst_1
       129: isub
       130: invokestatic  #83                 // Method getStrings:(Ldk/brics/automaton/State;Ljava/util/Set;Ljava/lang/StringBuilder;I)V
       133: aload_2
       134: aload_2
       135: invokevirtual #91                 // Method java/lang/StringBuilder.length:()I
       138: iconst_1
       139: isub
       140: invokevirtual #92                 // Method java/lang/StringBuilder.deleteCharAt:(I)Ljava/lang/StringBuilder;
       143: pop
       144: iinc          6, 1
       147: goto          65
       150: goto          36
       153: return
      LineNumberTable:
        line 468: 0
        line 469: 4
        line 470: 11
        line 472: 25
        line 473: 58
        line 474: 75
        line 475: 82
        line 476: 89
        line 477: 102
        line 479: 112
        line 481: 120
        line 482: 133
        line 473: 144
        line 484: 153
      StackMapTable: number_of_entries = 7
        frame_type = 25 /* same */
        frame_type = 252 /* append */
          offset_delta = 10
          locals = [ class java/util/Iterator ]
        frame_type = 253 /* append */
          offset_delta = 28
          locals = [ class dk/brics/automaton/Transition, int ]
        frame_type = 46 /* same */
        frame_type = 7 /* same */
        frame_type = 249 /* chop */
          offset_delta = 29
        frame_type = 250 /* chop */
          offset_delta = 2
    Signature: #147                         // (Ldk/brics/automaton/State;Ljava/util/Set<Ljava/lang/String;>;Ljava/lang/StringBuilder;I)V

  public static java.util.Set<java.lang.String> getFiniteStrings(dk.brics.automaton.Automaton);
    descriptor: (Ldk/brics/automaton/Automaton;)Ljava/util/Set;
    flags: (0x0009) ACC_PUBLIC, ACC_STATIC
    Code:
      stack=5, locals=2, args_size=1
         0: new           #10                 // class java/util/HashSet
         3: dup
         4: invokespecial #11                 // Method java/util/HashSet."<init>":()V
         7: astore_1
         8: aload_0
         9: invokevirtual #37                 // Method dk/brics/automaton/Automaton.isSingleton:()Z
        12: ifeq          27
        15: aload_1
        16: aload_0
        17: getfield      #38                 // Field dk/brics/automaton/Automaton.singleton:Ljava/lang/String;
        20: invokevirtual #21                 // Method java/util/HashSet.add:(Ljava/lang/Object;)Z
        23: pop
        24: goto          55
        27: aload_0
        28: getfield      #24                 // Field dk/brics/automaton/Automaton.initial:Ldk/brics/automaton/State;
        31: new           #10                 // class java/util/HashSet
        34: dup
        35: invokespecial #11                 // Method java/util/HashSet."<init>":()V
        38: aload_1
        39: new           #81                 // class java/lang/StringBuilder
        42: dup
        43: invokespecial #82                 // Method java/lang/StringBuilder."<init>":()V
        46: iconst_m1
        47: invokestatic  #93                 // Method getFiniteStrings:(Ldk/brics/automaton/State;Ljava/util/HashSet;Ljava/util/HashSet;Ljava/lang/StringBuilder;I)Z
        50: ifne          55
        53: aconst_null
        54: areturn
        55: aload_1
        56: areturn
      LineNumberTable:
        line 491: 0
        line 492: 8
        line 493: 15
        line 494: 27
        line 495: 53
        line 496: 55
      StackMapTable: number_of_entries = 2
        frame_type = 252 /* append */
          offset_delta = 27
          locals = [ class java/util/HashSet ]
        frame_type = 27 /* same */
    Signature: #149                         // (Ldk/brics/automaton/Automaton;)Ljava/util/Set<Ljava/lang/String;>;

  public static java.util.Set<java.lang.String> getFiniteStrings(dk.brics.automaton.Automaton, int);
    descriptor: (Ldk/brics/automaton/Automaton;I)Ljava/util/Set;
    flags: (0x0009) ACC_PUBLIC, ACC_STATIC
    Code:
      stack=5, locals=3, args_size=2
         0: new           #10                 // class java/util/HashSet
         3: dup
         4: invokespecial #11                 // Method java/util/HashSet."<init>":()V
         7: astore_2
         8: aload_0
         9: invokevirtual #37                 // Method dk/brics/automaton/Automaton.isSingleton:()Z
        12: ifeq          33
        15: iload_1
        16: ifle          31
        19: aload_2
        20: aload_0
        21: getfield      #38                 // Field dk/brics/automaton/Automaton.singleton:Ljava/lang/String;
        24: invokevirtual #21                 // Method java/util/HashSet.add:(Ljava/lang/Object;)Z
        27: pop
        28: goto          61
        31: aconst_null
        32: areturn
        33: aload_0
        34: getfield      #24                 // Field dk/brics/automaton/Automaton.initial:Ldk/brics/automaton/State;
        37: new           #10                 // class java/util/HashSet
        40: dup
        41: invokespecial #11                 // Method java/util/HashSet."<init>":()V
        44: aload_2
        45: new           #81                 // class java/lang/StringBuilder
        48: dup
        49: invokespecial #82                 // Method java/lang/StringBuilder."<init>":()V
        52: iload_1
        53: invokestatic  #93                 // Method getFiniteStrings:(Ldk/brics/automaton/State;Ljava/util/HashSet;Ljava/util/HashSet;Ljava/lang/StringBuilder;I)Z
        56: ifne          61
        59: aconst_null
        60: areturn
        61: aload_2
        62: areturn
      LineNumberTable:
        line 506: 0
        line 507: 8
        line 508: 15
        line 509: 19
        line 511: 31
        line 512: 33
        line 513: 59
        line 514: 61
      StackMapTable: number_of_entries = 3
        frame_type = 252 /* append */
          offset_delta = 31
          locals = [ class java/util/HashSet ]
        frame_type = 1 /* same */
        frame_type = 27 /* same */
    Signature: #145                         // (Ldk/brics/automaton/Automaton;I)Ljava/util/Set<Ljava/lang/String;>;

  private static boolean getFiniteStrings(dk.brics.automaton.State, java.util.HashSet<dk.brics.automaton.State>, java.util.HashSet<java.lang.String>, java.lang.StringBuilder, int);
    descriptor: (Ldk/brics/automaton/State;Ljava/util/HashSet;Ljava/util/HashSet;Ljava/lang/StringBuilder;I)Z
    flags: (0x000a) ACC_PRIVATE, ACC_STATIC
    Code:
      stack=5, locals=8, args_size=5
         0: aload_1
         1: aload_0
         2: invokevirtual #21                 // Method java/util/HashSet.add:(Ljava/lang/Object;)Z
         5: pop
         6: aload_0
         7: getfield      #23                 // Field dk/brics/automaton/State.transitions:Ljava/util/Set;
        10: invokeinterface #6,  1            // InterfaceMethod java/util/Set.iterator:()Ljava/util/Iterator;
        15: astore        5
        17: aload         5
        19: invokeinterface #7,  1            // InterfaceMethod java/util/Iterator.hasNext:()Z
        24: ifeq          188
        27: aload         5
        29: invokeinterface #8,  1            // InterfaceMethod java/util/Iterator.next:()Ljava/lang/Object;
        34: checkcast     #15                 // class dk/brics/automaton/Transition
        37: astore        6
        39: aload_1
        40: aload         6
        42: getfield      #16                 // Field dk/brics/automaton/Transition.to:Ldk/brics/automaton/State;
        45: invokevirtual #79                 // Method java/util/HashSet.contains:(Ljava/lang/Object;)Z
        48: ifeq          53
        51: iconst_0
        52: ireturn
        53: aload         6
        55: getfield      #18                 // Field dk/brics/automaton/Transition.min:I
        58: istore        7
        60: iload         7
        62: aload         6
        64: getfield      #19                 // Field dk/brics/automaton/Transition.max:I
        67: if_icmpgt     185
        70: iload         7
        72: ldc           #85                 // int 65535
        74: if_icmple     107
        77: aload_3
        78: ldc           #86                 // String \\u{
        80: invokevirtual #87                 // Method java/lang/StringBuilder.append:(Ljava/lang/String;)Ljava/lang/StringBuilder;
        83: pop
        84: aload_3
        85: iload         7
        87: invokestatic  #88                 // Method java/lang/Integer.toHexString:(I)Ljava/lang/String;
        90: invokevirtual #89                 // Method java/lang/String.toUpperCase:()Ljava/lang/String;
        93: invokevirtual #87                 // Method java/lang/StringBuilder.append:(Ljava/lang/String;)Ljava/lang/StringBuilder;
        96: pop
        97: aload_3
        98: bipush        125
       100: invokevirtual #90                 // Method java/lang/StringBuilder.append:(C)Ljava/lang/StringBuilder;
       103: pop
       104: goto          114
       107: aload_3
       108: iload         7
       110: invokevirtual #94                 // Method java/lang/StringBuilder.append:(I)Ljava/lang/StringBuilder;
       113: pop
       114: aload         6
       116: getfield      #16                 // Field dk/brics/automaton/Transition.to:Ldk/brics/automaton/State;
       119: getfield      #13                 // Field dk/brics/automaton/State.accept:Z
       122: ifeq          150
       125: aload_2
       126: aload_3
       127: invokevirtual #84                 // Method java/lang/StringBuilder.toString:()Ljava/lang/String;
       130: invokevirtual #21                 // Method java/util/HashSet.add:(Ljava/lang/Object;)Z
       133: pop
       134: iload         4
       136: iflt          150
       139: aload_2
       140: invokevirtual #95                 // Method java/util/HashSet.size:()I
       143: iload         4
       145: if_icmple     150
       148: iconst_0
       149: ireturn
       150: aload         6
       152: getfield      #16                 // Field dk/brics/automaton/Transition.to:Ldk/brics/automaton/State;
       155: aload_1
       156: aload_2
       157: aload_3
       158: iload         4
       160: invokestatic  #93                 // Method getFiniteStrings:(Ldk/brics/automaton/State;Ljava/util/HashSet;Ljava/util/HashSet;Ljava/lang/StringBuilder;I)Z
       163: ifne          168
       166: iconst_0
       167: ireturn
       168: aload_3
       169: aload_3
       170: invokevirtual #91                 // Method java/lang/StringBuilder.length:()I
       173: iconst_1
       174: isub
       175: invokevirtual #92                 // Method java/lang/StringBuilder.deleteCharAt:(I)Ljava/lang/StringBuilder;
       178: pop
       179: iinc          7, 1
       182: goto          60
       185: goto          17
       188: aload_1
       189: aload_0
       190: invokevirtual #80                 // Method java/util/HashSet.remove:(Ljava/lang/Object;)Z
       193: pop
       194: iconst_1
       195: ireturn
      LineNumberTable:
        line 522: 0
        line 523: 6
        line 524: 39
        line 525: 51
        line 526: 53
        line 527: 70
        line 528: 77
        line 529: 84
        line 530: 97
        line 532: 107
        line 534: 114
        line 535: 125
        line 536: 134
        line 537: 148
        line 539: 150
        line 540: 166
        line 541: 168
        line 526: 179
        line 543: 185
        line 544: 188
        line 545: 194
      StackMapTable: number_of_entries = 9
        frame_type = 252 /* append */
          offset_delta = 17
          locals = [ class java/util/Iterator ]
        frame_type = 252 /* append */
          offset_delta = 35
          locals = [ class dk/brics/automaton/Transition ]
        frame_type = 252 /* append */
          offset_delta = 6
          locals = [ int ]
        frame_type = 46 /* same */
        frame_type = 6 /* same */
        frame_type = 35 /* same */
        frame_type = 17 /* same */
        frame_type = 249 /* chop */
          offset_delta = 16
        frame_type = 250 /* chop */
          offset_delta = 2
    Signature: #151                         // (Ldk/brics/automaton/State;Ljava/util/HashSet<Ldk/brics/automaton/State;>;Ljava/util/HashSet<Ljava/lang/String;>;Ljava/lang/StringBuilder;I)Z

  public static java.lang.String getCommonPrefix(dk.brics.automaton.Automaton);
    descriptor: (Ldk/brics/automaton/Automaton;)Ljava/lang/String;
    flags: (0x0009) ACC_PUBLIC, ACC_STATIC
    Code:
      stack=2, locals=6, args_size=1
         0: aload_0
         1: invokevirtual #37                 // Method dk/brics/automaton/Automaton.isSingleton:()Z
         4: ifeq          12
         7: aload_0
         8: getfield      #38                 // Field dk/brics/automaton/Automaton.singleton:Ljava/lang/String;
        11: areturn
        12: new           #81                 // class java/lang/StringBuilder
        15: dup
        16: invokespecial #82                 // Method java/lang/StringBuilder."<init>":()V
        19: astore_1
        20: new           #10                 // class java/util/HashSet
        23: dup
        24: invokespecial #11                 // Method java/util/HashSet."<init>":()V
        27: astore_2
        28: aload_0
        29: getfield      #24                 // Field dk/brics/automaton/Automaton.initial:Ldk/brics/automaton/State;
        32: astore_3
        33: iconst_1
        34: istore        4
        36: aload_2
        37: aload_3
        38: invokevirtual #21                 // Method java/util/HashSet.add:(Ljava/lang/Object;)Z
        41: pop
        42: aload_3
        43: getfield      #13                 // Field dk/brics/automaton/State.accept:Z
        46: ifne          125
        49: aload_3
        50: getfield      #23                 // Field dk/brics/automaton/State.transitions:Ljava/util/Set;
        53: invokeinterface #53,  1           // InterfaceMethod java/util/Set.size:()I
        58: iconst_1
        59: if_icmpne     125
        62: aload_3
        63: getfield      #23                 // Field dk/brics/automaton/State.transitions:Ljava/util/Set;
        66: invokeinterface #6,  1            // InterfaceMethod java/util/Set.iterator:()Ljava/util/Iterator;
        71: invokeinterface #8,  1            // InterfaceMethod java/util/Iterator.next:()Ljava/lang/Object;
        76: checkcast     #15                 // class dk/brics/automaton/Transition
        79: astore        5
        81: aload         5
        83: getfield      #18                 // Field dk/brics/automaton/Transition.min:I
        86: aload         5
        88: getfield      #19                 // Field dk/brics/automaton/Transition.max:I
        91: if_icmpne     125
        94: aload_2
        95: aload         5
        97: getfield      #16                 // Field dk/brics/automaton/Transition.to:Ldk/brics/automaton/State;
       100: invokevirtual #79                 // Method java/util/HashSet.contains:(Ljava/lang/Object;)Z
       103: ifne          125
       106: aload_1
       107: aload         5
       109: getfield      #18                 // Field dk/brics/automaton/Transition.min:I
       112: invokevirtual #94                 // Method java/lang/StringBuilder.append:(I)Ljava/lang/StringBuilder;
       115: pop
       116: aload         5
       118: getfield      #16                 // Field dk/brics/automaton/Transition.to:Ldk/brics/automaton/State;
       121: astore_3
       122: iconst_0
       123: istore        4
       125: iload         4
       127: ifeq          33
       130: aload_1
       131: invokevirtual #84                 // Method java/lang/StringBuilder.toString:()Ljava/lang/String;
       134: areturn
      LineNumberTable:
        line 554: 0
        line 555: 7
        line 556: 12
        line 557: 20
        line 558: 28
        line 561: 33
        line 562: 36
        line 563: 42
        line 564: 62
        line 565: 81
        line 566: 106
        line 567: 116
        line 568: 122
        line 571: 125
        line 572: 130
      StackMapTable: number_of_entries = 3
        frame_type = 12 /* same */
        frame_type = 254 /* append */
          offset_delta = 20
          locals = [ class java/lang/StringBuilder, class java/util/HashSet, class dk/brics/automaton/State ]
        frame_type = 252 /* append */
          offset_delta = 91
          locals = [ int ]

  public static void prefixClose(dk.brics.automaton.Automaton);
    descriptor: (Ldk/brics/automaton/Automaton;)V
    flags: (0x0009) ACC_PUBLIC, ACC_STATIC
    Code:
      stack=2, locals=3, args_size=1
         0: aload_0
         1: invokevirtual #4                  // Method dk/brics/automaton/Automaton.getStates:()Ljava/util/Set;
         4: invokeinterface #6,  1            // InterfaceMethod java/util/Set.iterator:()Ljava/util/Iterator;
         9: astore_1
        10: aload_1
        11: invokeinterface #7,  1            // InterfaceMethod java/util/Iterator.hasNext:()Z
        16: ifeq          37
        19: aload_1
        20: invokeinterface #8,  1            // InterfaceMethod java/util/Iterator.next:()Ljava/lang/Object;
        25: checkcast     #9                  // class dk/brics/automaton/State
        28: astore_2
        29: aload_2
        30: iconst_1
        31: invokevirtual #96                 // Method dk/brics/automaton/State.setAccept:(Z)V
        34: goto          10
        37: aload_0
        38: invokevirtual #97                 // Method dk/brics/automaton/Automaton.clearHashCode:()V
        41: aload_0
        42: invokevirtual #47                 // Method dk/brics/automaton/Automaton.checkMinimizeAlways:()V
        45: return
      LineNumberTable:
        line 579: 0
        line 580: 29
        line 581: 37
        line 582: 41
        line 583: 45
      StackMapTable: number_of_entries = 2
        frame_type = 252 /* append */
          offset_delta = 10
          locals = [ class java/util/Iterator ]
        frame_type = 250 /* chop */
          offset_delta = 26

  public static dk.brics.automaton.Automaton hexCases(dk.brics.automaton.Automaton);
    descriptor: (Ldk/brics/automaton/Automaton;)Ldk/brics/automaton/Automaton;
    flags: (0x0009) ACC_PUBLIC, ACC_STATIC
    Code:
      stack=3, locals=5, args_size=1
         0: new           #2                  // class java/util/HashMap
         3: dup
         4: invokespecial #3                  // Method java/util/HashMap."<init>":()V
         7: astore_1
         8: bipush        97
        10: istore_2
        11: bipush        65
        13: istore_3
        14: iload_2
        15: bipush        102
        17: if_icmpgt     88
        20: new           #10                 // class java/util/HashSet
        23: dup
        24: invokespecial #11                 // Method java/util/HashSet."<init>":()V
        27: astore        4
        29: aload         4
        31: iload_2
        32: invokestatic  #59                 // Method java/lang/Integer.valueOf:(I)Ljava/lang/Integer;
        35: invokeinterface #42,  2           // InterfaceMethod java/util/Set.add:(Ljava/lang/Object;)Z
        40: pop
        41: aload         4
        43: iload_3
        44: invokestatic  #59                 // Method java/lang/Integer.valueOf:(I)Ljava/lang/Integer;
        47: invokeinterface #42,  2           // InterfaceMethod java/util/Set.add:(Ljava/lang/Object;)Z
        52: pop
        53: aload_1
        54: iload_2
        55: invokestatic  #59                 // Method java/lang/Integer.valueOf:(I)Ljava/lang/Integer;
        58: aload         4
        60: invokeinterface #98,  3           // InterfaceMethod java/util/Map.put:(Ljava/lang/Object;Ljava/lang/Object;)Ljava/lang/Object;
        65: pop
        66: aload_1
        67: iload_3
        68: invokestatic  #59                 // Method java/lang/Integer.valueOf:(I)Ljava/lang/Integer;
        71: aload         4
        73: invokeinterface #98,  3           // InterfaceMethod java/util/Map.put:(Ljava/lang/Object;Ljava/lang/Object;)Ljava/lang/Object;
        78: pop
        79: iinc          2, 1
        82: iinc          3, 1
        85: goto          14
        88: getstatic     #99                 // Field dk/brics/automaton/BasicAutomata.ws:Ldk/brics/automaton/Automaton;
        91: astore_2
        92: aload_2
        93: aload_0
        94: aload_1
        95: invokevirtual #100                // Method dk/brics/automaton/Automaton.subst:(Ljava/util/Map;)Ldk/brics/automaton/Automaton;
        98: invokevirtual #101                // Method dk/brics/automaton/Automaton.concatenate:(Ldk/brics/automaton/Automaton;)Ldk/brics/automaton/Automaton;
       101: aload_2
       102: invokevirtual #101                // Method dk/brics/automaton/Automaton.concatenate:(Ldk/brics/automaton/Automaton;)Ldk/brics/automaton/Automaton;
       105: areturn
      LineNumberTable:
        line 592: 0
        line 593: 8
        line 594: 20
        line 595: 29
        line 596: 41
        line 597: 53
        line 598: 66
        line 593: 79
        line 600: 88
        line 601: 92
      StackMapTable: number_of_entries = 2
        frame_type = 254 /* append */
          offset_delta = 14
          locals = [ class java/util/Map, int, int ]
        frame_type = 249 /* chop */
          offset_delta = 73

  public static dk.brics.automaton.Automaton replaceWhitespace(dk.brics.automaton.Automaton);
    descriptor: (Ldk/brics/automaton/Automaton;)Ldk/brics/automaton/Automaton;
    flags: (0x0009) ACC_PUBLIC, ACC_STATIC
    Code:
      stack=3, locals=3, args_size=1
         0: new           #2                  // class java/util/HashMap
         3: dup
         4: invokespecial #3                  // Method java/util/HashMap."<init>":()V
         7: astore_1
         8: new           #10                 // class java/util/HashSet
        11: dup
        12: invokespecial #11                 // Method java/util/HashSet."<init>":()V
        15: astore_2
        16: aload_2
        17: bipush        32
        19: invokestatic  #59                 // Method java/lang/Integer.valueOf:(I)Ljava/lang/Integer;
        22: invokeinterface #42,  2           // InterfaceMethod java/util/Set.add:(Ljava/lang/Object;)Z
        27: pop
        28: aload_2
        29: bipush        9
        31: invokestatic  #59                 // Method java/lang/Integer.valueOf:(I)Ljava/lang/Integer;
        34: invokeinterface #42,  2           // InterfaceMethod java/util/Set.add:(Ljava/lang/Object;)Z
        39: pop
        40: aload_2
        41: bipush        10
        43: invokestatic  #59                 // Method java/lang/Integer.valueOf:(I)Ljava/lang/Integer;
        46: invokeinterface #42,  2           // InterfaceMethod java/util/Set.add:(Ljava/lang/Object;)Z
        51: pop
        52: aload_2
        53: bipush        13
        55: invokestatic  #59                 // Method java/lang/Integer.valueOf:(I)Ljava/lang/Integer;
        58: invokeinterface #42,  2           // InterfaceMethod java/util/Set.add:(Ljava/lang/Object;)Z
        63: pop
        64: aload_1
        65: bipush        32
        67: invokestatic  #59                 // Method java/lang/Integer.valueOf:(I)Ljava/lang/Integer;
        70: aload_2
        71: invokeinterface #98,  3           // InterfaceMethod java/util/Map.put:(Ljava/lang/Object;Ljava/lang/Object;)Ljava/lang/Object;
        76: pop
        77: aload_0
        78: aload_1
        79: invokevirtual #100                // Method dk/brics/automaton/Automaton.subst:(Ljava/util/Map;)Ldk/brics/automaton/Automaton;
        82: areturn
      LineNumberTable:
        line 611: 0
        line 612: 8
        line 613: 16
        line 614: 28
        line 615: 40
        line 616: 52
        line 617: 64
        line 618: 77
}
SourceFile: "SpecialOperations.java"
