Classfile /Users/mw/Projects/slang-braindump/.jar/jar11/assemble/slang-braindump/assemble/content/scala/$less$colon$less$$anon$1.class
  Last modified May 29, 2022; size 3266 bytes
  SHA-256 checksum 296e71a2e925982f4dd9ee5e979ad1e5c04fda586cb8f775bc39b3f047f75c90
  Compiled from "typeConstraints.scala"
public final class scala.$less$colon$less$$anon$1 extends scala.$eq$colon$eq<java.lang.Object, java.lang.Object>
  minor version: 0
  major version: 52
  flags: (0x0031) ACC_PUBLIC, ACC_FINAL, ACC_SUPER
  this_class: #2                          // scala/$less$colon$less$$anon$1
  super_class: #5                         // scala/$eq$colon$eq
  interfaces: 0, fields: 0, methods: 18, attributes: 6
Constant pool:
   #1 = Utf8               scala/$less$colon$less$$anon$1
   #2 = Class              #1             // scala/$less$colon$less$$anon$1
   #3 = Utf8               Lscala/$eq$colon$eq<Ljava/lang/Object;Ljava/lang/Object;>;
   #4 = Utf8               scala/$eq$colon$eq
   #5 = Class              #4             // scala/$eq$colon$eq
   #6 = Utf8               typeConstraints.scala
   #7 = Utf8               scala/$less$colon$less$
   #8 = Class              #7             // scala/$less$colon$less$
   #9 = Utf8               substituteBoth
  #10 = Utf8               (Ljava/lang/Object;)Ljava/lang/Object;
  #11 = Utf8               <F:Ljava/lang/Object;>(TF;)TF;
  #12 = Utf8               ftf
  #13 = Utf8               this
  #14 = Utf8               Lscala/$less$colon$less$$anon$1;
  #15 = Utf8               Ljava/lang/Object;
  #16 = Utf8               substituteCo
  #17 = Utf8               ff
  #18 = Utf8               substituteContra
  #19 = Utf8               apply
  #20 = Utf8               x
  #21 = Utf8               flip
  #22 = Utf8               ()Lscala/$less$colon$less$$anon$1;
  #23 = Utf8               compose
  #24 = Utf8               (Lscala/Function1;)Lscala/Function1;
  #25 = Utf8               <C:Ljava/lang/Object;>(Lscala/Function1<TC;Ljava/lang/Object;>;)Lscala/Function1<TC;Ljava/lang/Object;>;
  #26 = Utf8               r
  #27 = Utf8               Lscala/Function1;
  #28 = Utf8               (Lscala/$less$colon$less;)Lscala/$less$colon$less;
  #29 = Utf8               <C:Ljava/lang/Object;>(Lscala/$less$colon$less<TC;Ljava/lang/Object;>;)Lscala/$less$colon$less<TC;Ljava/lang/Object;>;
  #30 = Utf8               Lscala/$less$colon$less;
  #31 = Utf8               (Lscala/$eq$colon$eq;)Lscala/$eq$colon$eq;
  #32 = Utf8               <C:Ljava/lang/Object;>(Lscala/$eq$colon$eq<TC;Ljava/lang/Object;>;)Lscala/$eq$colon$eq<TC;Ljava/lang/Object;>;
  #33 = Utf8               Lscala/$eq$colon$eq;
  #34 = Utf8               andThen
  #35 = Utf8               <C:Ljava/lang/Object;>(Lscala/Function1<Ljava/lang/Object;TC;>;)Lscala/Function1<Ljava/lang/Object;TC;>;
  #36 = Utf8               <C:Ljava/lang/Object;>(Lscala/$less$colon$less<Ljava/lang/Object;TC;>;)Lscala/$less$colon$less<Ljava/lang/Object;TC;>;
  #37 = Utf8               <C:Ljava/lang/Object;>(Lscala/$eq$colon$eq<Ljava/lang/Object;TC;>;)Lscala/$eq$colon$eq<Ljava/lang/Object;TC;>;
  #38 = Utf8               liftCo
  #39 = Utf8               ()Lscala/$eq$colon$eq;
  #40 = Utf8               <F:Ljava/lang/Object;>()Lscala/$eq$colon$eq<TF;TF;>;
  #41 = Utf8               liftContra
  #42 = Utf8               toString
  #43 = Utf8               ()Ljava/lang/String;
  #44 = Utf8               generalized constraint
  #45 = String             #44            // generalized constraint
  #46 = Utf8               ()Lscala/$less$colon$less;
  #47 = NameAndType        #41:#39        // liftContra:()Lscala/$eq$colon$eq;
  #48 = Methodref          #2.#47         // scala/$less$colon$less$$anon$1.liftContra:()Lscala/$eq$colon$eq;
  #49 = NameAndType        #38:#39        // liftCo:()Lscala/$eq$colon$eq;
  #50 = Methodref          #2.#49         // scala/$less$colon$less$$anon$1.liftCo:()Lscala/$eq$colon$eq;
  #51 = NameAndType        #21:#22        // flip:()Lscala/$less$colon$less$$anon$1;
  #52 = Methodref          #2.#51         // scala/$less$colon$less$$anon$1.flip:()Lscala/$less$colon$less$$anon$1;
  #53 = Utf8               <init>
  #54 = Utf8               ()V
  #55 = NameAndType        #53:#54        // "<init>":()V
  #56 = Methodref          #5.#55         // scala/$eq$colon$eq."<init>":()V
  #57 = Utf8               Code
  #58 = Utf8               LineNumberTable
  #59 = Utf8               LocalVariableTable
  #60 = Utf8               Signature
  #61 = Utf8               MethodParameters
  #62 = Utf8               InnerClasses
  #63 = Utf8               EnclosingMethod
  #64 = Utf8               SourceFile
  #65 = Utf8               ScalaInlineInfo
  #66 = Utf8               Scala
{
  public <F extends java.lang.Object> F substituteBoth(F);
    descriptor: (Ljava/lang/Object;)Ljava/lang/Object;
    flags: (0x0001) ACC_PUBLIC
    Code:
      stack=1, locals=2, args_size=2
         0: aload_1
         1: areturn
      LineNumberTable:
        line 149: 0
      LocalVariableTable:
        Start  Length  Slot  Name   Signature
            0       2     0  this   Lscala/$less$colon$less$$anon$1;
            0       2     1   ftf   Ljava/lang/Object;
    Signature: #11                          // <F:Ljava/lang/Object;>(TF;)TF;
    MethodParameters:
      Name                           Flags
      ftf                            final

  public <F extends java.lang.Object> F substituteCo(F);
    descriptor: (Ljava/lang/Object;)Ljava/lang/Object;
    flags: (0x0001) ACC_PUBLIC
    Code:
      stack=1, locals=2, args_size=2
         0: aload_1
         1: areturn
      LineNumberTable:
        line 150: 0
      LocalVariableTable:
        Start  Length  Slot  Name   Signature
            0       2     0  this   Lscala/$less$colon$less$$anon$1;
            0       2     1    ff   Ljava/lang/Object;
    Signature: #11                          // <F:Ljava/lang/Object;>(TF;)TF;
    MethodParameters:
      Name                           Flags
      ff                             final

  public <F extends java.lang.Object> F substituteContra(F);
    descriptor: (Ljava/lang/Object;)Ljava/lang/Object;
    flags: (0x0001) ACC_PUBLIC
    Code:
      stack=1, locals=2, args_size=2
         0: aload_1
         1: areturn
      LineNumberTable:
        line 151: 0
      LocalVariableTable:
        Start  Length  Slot  Name   Signature
            0       2     0  this   Lscala/$less$colon$less$$anon$1;
            0       2     1    ff   Ljava/lang/Object;
    Signature: #11                          // <F:Ljava/lang/Object;>(TF;)TF;
    MethodParameters:
      Name                           Flags
      ff                             final

  public java.lang.Object apply(java.lang.Object);
    descriptor: (Ljava/lang/Object;)Ljava/lang/Object;
    flags: (0x0001) ACC_PUBLIC
    Code:
      stack=1, locals=2, args_size=2
         0: aload_1
         1: areturn
      LineNumberTable:
        line 152: 0
      LocalVariableTable:
        Start  Length  Slot  Name   Signature
            0       2     0  this   Lscala/$less$colon$less$$anon$1;
            0       2     1     x   Ljava/lang/Object;
    MethodParameters:
      Name                           Flags
      x                              final

  public scala.$less$colon$less$$anon$1 flip();
    descriptor: ()Lscala/$less$colon$less$$anon$1;
    flags: (0x0001) ACC_PUBLIC
    Code:
      stack=1, locals=1, args_size=1
         0: aload_0
         1: areturn
      LineNumberTable:
        line 153: 0
      LocalVariableTable:
        Start  Length  Slot  Name   Signature
            0       2     0  this   Lscala/$less$colon$less$$anon$1;

  public <C extends java.lang.Object> scala.Function1<C, java.lang.Object> compose(scala.Function1<C, java.lang.Object>);
    descriptor: (Lscala/Function1;)Lscala/Function1;
    flags: (0x0001) ACC_PUBLIC
    Code:
      stack=1, locals=2, args_size=2
         0: aload_1
         1: areturn
      LineNumberTable:
        line 154: 0
      LocalVariableTable:
        Start  Length  Slot  Name   Signature
            0       2     0  this   Lscala/$less$colon$less$$anon$1;
            0       2     1     r   Lscala/Function1;
    Signature: #25                          // <C:Ljava/lang/Object;>(Lscala/Function1<TC;Ljava/lang/Object;>;)Lscala/Function1<TC;Ljava/lang/Object;>;
    MethodParameters:
      Name                           Flags
      r                              final

  public <C extends java.lang.Object> scala.$less$colon$less<C, java.lang.Object> compose(scala.$less$colon$less<C, java.lang.Object>);
    descriptor: (Lscala/$less$colon$less;)Lscala/$less$colon$less;
    flags: (0x0001) ACC_PUBLIC
    Code:
      stack=1, locals=2, args_size=2
         0: aload_1
         1: areturn
      LineNumberTable:
        line 155: 0
      LocalVariableTable:
        Start  Length  Slot  Name   Signature
            0       2     0  this   Lscala/$less$colon$less$$anon$1;
            0       2     1     r   Lscala/$less$colon$less;
    Signature: #29                          // <C:Ljava/lang/Object;>(Lscala/$less$colon$less<TC;Ljava/lang/Object;>;)Lscala/$less$colon$less<TC;Ljava/lang/Object;>;
    MethodParameters:
      Name                           Flags
      r                              final

  public <C extends java.lang.Object> scala.$eq$colon$eq<C, java.lang.Object> compose(scala.$eq$colon$eq<C, java.lang.Object>);
    descriptor: (Lscala/$eq$colon$eq;)Lscala/$eq$colon$eq;
    flags: (0x0001) ACC_PUBLIC
    Code:
      stack=1, locals=2, args_size=2
         0: aload_1
         1: areturn
      LineNumberTable:
        line 156: 0
      LocalVariableTable:
        Start  Length  Slot  Name   Signature
            0       2     0  this   Lscala/$less$colon$less$$anon$1;
            0       2     1     r   Lscala/$eq$colon$eq;
    Signature: #32                          // <C:Ljava/lang/Object;>(Lscala/$eq$colon$eq<TC;Ljava/lang/Object;>;)Lscala/$eq$colon$eq<TC;Ljava/lang/Object;>;
    MethodParameters:
      Name                           Flags
      r                              final

  public <C extends java.lang.Object> scala.Function1<java.lang.Object, C> andThen(scala.Function1<java.lang.Object, C>);
    descriptor: (Lscala/Function1;)Lscala/Function1;
    flags: (0x0001) ACC_PUBLIC
    Code:
      stack=1, locals=2, args_size=2
         0: aload_1
         1: areturn
      LineNumberTable:
        line 157: 0
      LocalVariableTable:
        Start  Length  Slot  Name   Signature
            0       2     0  this   Lscala/$less$colon$less$$anon$1;
            0       2     1     r   Lscala/Function1;
    Signature: #35                          // <C:Ljava/lang/Object;>(Lscala/Function1<Ljava/lang/Object;TC;>;)Lscala/Function1<Ljava/lang/Object;TC;>;
    MethodParameters:
      Name                           Flags
      r                              final

  public <C extends java.lang.Object> scala.$less$colon$less<java.lang.Object, C> andThen(scala.$less$colon$less<java.lang.Object, C>);
    descriptor: (Lscala/$less$colon$less;)Lscala/$less$colon$less;
    flags: (0x0001) ACC_PUBLIC
    Code:
      stack=1, locals=2, args_size=2
         0: aload_1
         1: areturn
      LineNumberTable:
        line 158: 0
      LocalVariableTable:
        Start  Length  Slot  Name   Signature
            0       2     0  this   Lscala/$less$colon$less$$anon$1;
            0       2     1     r   Lscala/$less$colon$less;
    Signature: #36                          // <C:Ljava/lang/Object;>(Lscala/$less$colon$less<Ljava/lang/Object;TC;>;)Lscala/$less$colon$less<Ljava/lang/Object;TC;>;
    MethodParameters:
      Name                           Flags
      r                              final

  public <C extends java.lang.Object> scala.$eq$colon$eq<java.lang.Object, C> andThen(scala.$eq$colon$eq<java.lang.Object, C>);
    descriptor: (Lscala/$eq$colon$eq;)Lscala/$eq$colon$eq;
    flags: (0x0001) ACC_PUBLIC
    Code:
      stack=1, locals=2, args_size=2
         0: aload_1
         1: areturn
      LineNumberTable:
        line 159: 0
      LocalVariableTable:
        Start  Length  Slot  Name   Signature
            0       2     0  this   Lscala/$less$colon$less$$anon$1;
            0       2     1     r   Lscala/$eq$colon$eq;
    Signature: #37                          // <C:Ljava/lang/Object;>(Lscala/$eq$colon$eq<Ljava/lang/Object;TC;>;)Lscala/$eq$colon$eq<Ljava/lang/Object;TC;>;
    MethodParameters:
      Name                           Flags
      r                              final

  public <F extends java.lang.Object> scala.$eq$colon$eq<F, F> liftCo();
    descriptor: ()Lscala/$eq$colon$eq;
    flags: (0x0001) ACC_PUBLIC
    Code:
      stack=1, locals=1, args_size=1
         0: aload_0
         1: areturn
      LineNumberTable:
        line 160: 0
      LocalVariableTable:
        Start  Length  Slot  Name   Signature
            0       2     0  this   Lscala/$less$colon$less$$anon$1;
    Signature: #40                          // <F:Ljava/lang/Object;>()Lscala/$eq$colon$eq<TF;TF;>;

  public <F extends java.lang.Object> scala.$eq$colon$eq<F, F> liftContra();
    descriptor: ()Lscala/$eq$colon$eq;
    flags: (0x0001) ACC_PUBLIC
    Code:
      stack=1, locals=1, args_size=1
         0: aload_0
         1: areturn
      LineNumberTable:
        line 161: 0
      LocalVariableTable:
        Start  Length  Slot  Name   Signature
            0       2     0  this   Lscala/$less$colon$less$$anon$1;
    Signature: #40                          // <F:Ljava/lang/Object;>()Lscala/$eq$colon$eq<TF;TF;>;

  public java.lang.String toString();
    descriptor: ()Ljava/lang/String;
    flags: (0x0001) ACC_PUBLIC
    Code:
      stack=1, locals=1, args_size=1
         0: ldc           #45                 // String generalized constraint
         2: areturn
      LineNumberTable:
        line 162: 0
      LocalVariableTable:
        Start  Length  Slot  Name   Signature
            0       3     0  this   Lscala/$less$colon$less$$anon$1;

  public scala.$less$colon$less liftContra();
    descriptor: ()Lscala/$less$colon$less;
    flags: (0x1041) ACC_PUBLIC, ACC_BRIDGE, ACC_SYNTHETIC
    Code:
      stack=1, locals=1, args_size=1
         0: aload_0
         1: invokevirtual #48                 // Method liftContra:()Lscala/$eq$colon$eq;
         4: areturn
      LineNumberTable:
        line 148: 0
      LocalVariableTable:
        Start  Length  Slot  Name   Signature
            0       5     0  this   Lscala/$less$colon$less$$anon$1;

  public scala.$less$colon$less liftCo();
    descriptor: ()Lscala/$less$colon$less;
    flags: (0x1041) ACC_PUBLIC, ACC_BRIDGE, ACC_SYNTHETIC
    Code:
      stack=1, locals=1, args_size=1
         0: aload_0
         1: invokevirtual #50                 // Method liftCo:()Lscala/$eq$colon$eq;
         4: areturn
      LineNumberTable:
        line 148: 0
      LocalVariableTable:
        Start  Length  Slot  Name   Signature
            0       5     0  this   Lscala/$less$colon$less$$anon$1;

  public scala.$eq$colon$eq flip();
    descriptor: ()Lscala/$eq$colon$eq;
    flags: (0x1041) ACC_PUBLIC, ACC_BRIDGE, ACC_SYNTHETIC
    Code:
      stack=1, locals=1, args_size=1
         0: aload_0
         1: invokevirtual #52                 // Method flip:()Lscala/$less$colon$less$$anon$1;
         4: areturn
      LineNumberTable:
        line 148: 0
      LocalVariableTable:
        Start  Length  Slot  Name   Signature
            0       5     0  this   Lscala/$less$colon$less$$anon$1;

  public scala.$less$colon$less$$anon$1();
    descriptor: ()V
    flags: (0x0001) ACC_PUBLIC
    Code:
      stack=1, locals=1, args_size=1
         0: aload_0
         1: invokespecial #56                 // Method scala/$eq$colon$eq."<init>":()V
         4: return
      LineNumberTable:
        line 148: 0
      LocalVariableTable:
        Start  Length  Slot  Name   Signature
            0       5     0  this   Lscala/$less$colon$less$$anon$1;
}
InnerClasses:
  public final #2;                        // class scala/$less$colon$less$$anon$1
EnclosingMethod: #8.#0                  // scala.$less$colon$less$
Signature: #3                           // Lscala/$eq$colon$eq<Ljava/lang/Object;Ljava/lang/Object;>;
SourceFile: "typeConstraints.scala"
  ScalaInlineInfo: length = 0x5E (unknown attribute)
   01 01 00 12 00 35 00 36 01 00 22 00 1F 01 00 22
   00 1C 01 00 22 00 18 01 00 13 00 0A 01 00 17 00
   1F 01 00 17 00 1C 01 00 17 00 18 01 00 15 00 27
   01 00 15 00 16 01 00 26 00 27 01 00 26 00 2E 01
   00 29 00 27 01 00 29 00 2E 01 00 09 00 0A 01 00
   10 00 0A 01 00 12 00 0A 01 00 2A 00 2B 01
  Scala: length = 0x0 (unknown attribute)

