Classfile /Users/mw/Projects/slang-braindump/.jar/jar11/assemble/slang-braindump/assemble/content/scala/Array$UnapplySeqWrapper.class
  Last modified May 29, 2022; size 2404 bytes
  SHA-256 checksum e6990c65f2e4f3689102abe3b218f60fbf7d67ddf20b966db68b4e25a9328169
  Compiled from "Array.scala"
public final class scala.Array$UnapplySeqWrapper<T extends java.lang.Object> extends java.lang.Object
  minor version: 0
  major version: 52
  flags: (0x0031) ACC_PUBLIC, ACC_FINAL, ACC_SUPER
  this_class: #2                          // scala/Array$UnapplySeqWrapper
  super_class: #5                         // java/lang/Object
  interfaces: 0, fields: 1, methods: 10, attributes: 5
Constant pool:
   #1 = Utf8               scala/Array$UnapplySeqWrapper
   #2 = Class              #1             // scala/Array$UnapplySeqWrapper
   #3 = Utf8               <T:Ljava/lang/Object;>Ljava/lang/Object;
   #4 = Utf8               java/lang/Object
   #5 = Class              #4             // java/lang/Object
   #6 = Utf8               Array.scala
   #7 = Utf8               scala/Array
   #8 = Class              #7             // scala/Array
   #9 = Utf8               UnapplySeqWrapper
  #10 = Utf8               scala/Array$UnapplySeqWrapper$
  #11 = Class              #10            // scala/Array$UnapplySeqWrapper$
  #12 = Utf8               UnapplySeqWrapper$
  #13 = Utf8               scala$Array$UnapplySeqWrapper$$a
  #14 = Utf8               Ljava/lang/Object;
  #15 = Utf8               ()Ljava/lang/Object;
  #16 = NameAndType        #13:#14        // scala$Array$UnapplySeqWrapper$$a:Ljava/lang/Object;
  #17 = Fieldref           #2.#16         // scala/Array$UnapplySeqWrapper.scala$Array$UnapplySeqWrapper$$a:Ljava/lang/Object;
  #18 = Utf8               this
  #19 = Utf8               Lscala/Array$UnapplySeqWrapper;
  #20 = Utf8               isEmpty
  #21 = Utf8               ()Z
  #22 = Utf8               MODULE$
  #23 = Utf8               Lscala/Array$UnapplySeqWrapper$;
  #24 = NameAndType        #22:#23        // MODULE$:Lscala/Array$UnapplySeqWrapper$;
  #25 = Fieldref           #11.#24        // scala/Array$UnapplySeqWrapper$.MODULE$:Lscala/Array$UnapplySeqWrapper$;
  #26 = NameAndType        #13:#15        // scala$Array$UnapplySeqWrapper$$a:()Ljava/lang/Object;
  #27 = Methodref          #2.#26         // scala/Array$UnapplySeqWrapper.scala$Array$UnapplySeqWrapper$$a:()Ljava/lang/Object;
  #28 = Utf8               get
  #29 = Utf8               lengthCompare
  #30 = Utf8               (I)I
  #31 = Utf8               len
  #32 = Utf8               lengthCompare$extension
  #33 = Utf8               (Ljava/lang/Object;I)I
  #34 = NameAndType        #32:#33        // lengthCompare$extension:(Ljava/lang/Object;I)I
  #35 = Methodref          #11.#34        // scala/Array$UnapplySeqWrapper$.lengthCompare$extension:(Ljava/lang/Object;I)I
  #36 = Utf8               I
  #37 = Utf8               apply
  #38 = Utf8               (I)Ljava/lang/Object;
  #39 = Utf8               (I)TT;
  #40 = Utf8               i
  #41 = Utf8               scala/runtime/ScalaRunTime$
  #42 = Class              #41            // scala/runtime/ScalaRunTime$
  #43 = Utf8               Lscala/runtime/ScalaRunTime$;
  #44 = NameAndType        #22:#43        // MODULE$:Lscala/runtime/ScalaRunTime$;
  #45 = Fieldref           #42.#44        // scala/runtime/ScalaRunTime$.MODULE$:Lscala/runtime/ScalaRunTime$;
  #46 = Utf8               array_apply
  #47 = Utf8               (Ljava/lang/Object;I)Ljava/lang/Object;
  #48 = NameAndType        #46:#47        // array_apply:(Ljava/lang/Object;I)Ljava/lang/Object;
  #49 = Methodref          #42.#48        // scala/runtime/ScalaRunTime$.array_apply:(Ljava/lang/Object;I)Ljava/lang/Object;
  #50 = Utf8               apply$extension_$this
  #51 = Utf8               drop
  #52 = Utf8               (I)Lscala/collection/immutable/Seq;
  #53 = Utf8               (I)Lscala/collection/immutable/Seq<TT;>;
  #54 = Utf8               n
  #55 = Utf8               drop$extension
  #56 = Utf8               (Ljava/lang/Object;I)Lscala/collection/immutable/Seq;
  #57 = NameAndType        #55:#56        // drop$extension:(Ljava/lang/Object;I)Lscala/collection/immutable/Seq;
  #58 = Methodref          #11.#57        // scala/Array$UnapplySeqWrapper$.drop$extension:(Ljava/lang/Object;I)Lscala/collection/immutable/Seq;
  #59 = Utf8               toSeq
  #60 = Utf8               ()Lscala/collection/immutable/Seq;
  #61 = Utf8               ()Lscala/collection/immutable/Seq<TT;>;
  #62 = Utf8               toSeq$extension
  #63 = Utf8               (Ljava/lang/Object;)Lscala/collection/immutable/Seq;
  #64 = NameAndType        #62:#63        // toSeq$extension:(Ljava/lang/Object;)Lscala/collection/immutable/Seq;
  #65 = Methodref          #11.#64        // scala/Array$UnapplySeqWrapper$.toSeq$extension:(Ljava/lang/Object;)Lscala/collection/immutable/Seq;
  #66 = Utf8               hashCode
  #67 = Utf8               ()I
  #68 = NameAndType        #66:#67        // hashCode:()I
  #69 = Methodref          #5.#68         // java/lang/Object.hashCode:()I
  #70 = Utf8               equals
  #71 = Utf8               (Ljava/lang/Object;)Z
  #72 = Utf8               x$1
  #73 = Utf8               equals$extension
  #74 = Utf8               (Ljava/lang/Object;Ljava/lang/Object;)Z
  #75 = NameAndType        #73:#74        // equals$extension:(Ljava/lang/Object;Ljava/lang/Object;)Z
  #76 = Methodref          #11.#75        // scala/Array$UnapplySeqWrapper$.equals$extension:(Ljava/lang/Object;Ljava/lang/Object;)Z
  #77 = Utf8               <init>
  #78 = Utf8               (Ljava/lang/Object;)V
  #79 = Utf8               a
  #80 = Utf8               ()V
  #81 = NameAndType        #77:#80        // "<init>":()V
  #82 = Methodref          #5.#81         // java/lang/Object."<init>":()V
  #83 = Utf8               Signature
  #84 = Utf8               Code
  #85 = Utf8               LineNumberTable
  #86 = Utf8               LocalVariableTable
  #87 = Utf8               MethodParameters
  #88 = Utf8               InnerClasses
  #89 = Utf8               SourceFile
  #90 = Utf8               ScalaInlineInfo
  #91 = Utf8               Scala
{
  private final java.lang.Object scala$Array$UnapplySeqWrapper$$a;
    descriptor: Ljava/lang/Object;
    flags: (0x0012) ACC_PRIVATE, ACC_FINAL
    Signature: #14                          // Ljava/lang/Object;

  public java.lang.Object scala$Array$UnapplySeqWrapper$$a();
    descriptor: ()Ljava/lang/Object;
    flags: (0x0001) ACC_PUBLIC
    Code:
      stack=1, locals=1, args_size=1
         0: aload_0
         1: getfield      #17                 // Field scala$Array$UnapplySeqWrapper$$a:Ljava/lang/Object;
         4: areturn
      LineNumberTable:
        line 579: 0
      LocalVariableTable:
        Start  Length  Slot  Name   Signature
            0       5     0  this   Lscala/Array$UnapplySeqWrapper;
    Signature: #15                          // ()Ljava/lang/Object;

  public boolean isEmpty();
    descriptor: ()Z
    flags: (0x0001) ACC_PUBLIC
    Code:
      stack=1, locals=1, args_size=1
         0: getstatic     #25                 // Field scala/Array$UnapplySeqWrapper$.MODULE$:Lscala/Array$UnapplySeqWrapper$;
         3: pop
         4: aload_0
         5: invokevirtual #27                 // Method scala$Array$UnapplySeqWrapper$$a:()Ljava/lang/Object;
         8: pop
         9: iconst_0
        10: ireturn
      LineNumberTable:
        line 580: 0
        line 580: 9
        line 580: 10
      LocalVariableTable:
        Start  Length  Slot  Name   Signature
            0      11     0  this   Lscala/Array$UnapplySeqWrapper;

  public java.lang.Object get();
    descriptor: ()Ljava/lang/Object;
    flags: (0x0001) ACC_PUBLIC
    Code:
      stack=1, locals=1, args_size=1
         0: getstatic     #25                 // Field scala/Array$UnapplySeqWrapper$.MODULE$:Lscala/Array$UnapplySeqWrapper$;
         3: pop
         4: aload_0
         5: invokevirtual #27                 // Method scala$Array$UnapplySeqWrapper$$a:()Ljava/lang/Object;
         8: areturn
      LineNumberTable:
        line 581: 0
        line 581: 8
      LocalVariableTable:
        Start  Length  Slot  Name   Signature
            0       9     0  this   Lscala/Array$UnapplySeqWrapper;
    Signature: #15                          // ()Ljava/lang/Object;

  public int lengthCompare(int);
    descriptor: (I)I
    flags: (0x0001) ACC_PUBLIC
    Code:
      stack=3, locals=2, args_size=2
         0: getstatic     #25                 // Field scala/Array$UnapplySeqWrapper$.MODULE$:Lscala/Array$UnapplySeqWrapper$;
         3: aload_0
         4: invokevirtual #27                 // Method scala$Array$UnapplySeqWrapper$$a:()Ljava/lang/Object;
         7: iload_1
         8: invokevirtual #35                 // Method scala/Array$UnapplySeqWrapper$.lengthCompare$extension:(Ljava/lang/Object;I)I
        11: ireturn
      LineNumberTable:
        line 582: 0
      LocalVariableTable:
        Start  Length  Slot  Name   Signature
            0      12     0  this   Lscala/Array$UnapplySeqWrapper;
            0      12     1   len   I
    MethodParameters:
      Name                           Flags
      len                            final

  public T apply(int);
    descriptor: (I)Ljava/lang/Object;
    flags: (0x0001) ACC_PUBLIC
    Code:
      stack=3, locals=3, args_size=2
         0: getstatic     #25                 // Field scala/Array$UnapplySeqWrapper$.MODULE$:Lscala/Array$UnapplySeqWrapper$;
         3: pop
         4: aload_0
         5: invokevirtual #27                 // Method scala$Array$UnapplySeqWrapper$$a:()Ljava/lang/Object;
         8: astore_2
         9: getstatic     #45                 // Field scala/runtime/ScalaRunTime$.MODULE$:Lscala/runtime/ScalaRunTime$;
        12: aload_2
        13: iload_1
        14: invokevirtual #49                 // Method scala/runtime/ScalaRunTime$.array_apply:(Ljava/lang/Object;I)Ljava/lang/Object;
        17: areturn
      LineNumberTable:
        line 583: 0
        line 583: 9
        line 583: 17
      LocalVariableTable:
        Start  Length  Slot  Name   Signature
            0      18     0  this   Lscala/Array$UnapplySeqWrapper;
            0      18     1     i   I
            9       8     2 apply$extension_$this   Ljava/lang/Object;
    Signature: #39                          // (I)TT;
    MethodParameters:
      Name                           Flags
      i                              final

  public scala.collection.immutable.Seq<T> drop(int);
    descriptor: (I)Lscala/collection/immutable/Seq;
    flags: (0x0001) ACC_PUBLIC
    Code:
      stack=3, locals=2, args_size=2
         0: getstatic     #25                 // Field scala/Array$UnapplySeqWrapper$.MODULE$:Lscala/Array$UnapplySeqWrapper$;
         3: aload_0
         4: invokevirtual #27                 // Method scala$Array$UnapplySeqWrapper$$a:()Ljava/lang/Object;
         7: iload_1
         8: invokevirtual #58                 // Method scala/Array$UnapplySeqWrapper$.drop$extension:(Ljava/lang/Object;I)Lscala/collection/immutable/Seq;
        11: areturn
      LineNumberTable:
        line 584: 0
      LocalVariableTable:
        Start  Length  Slot  Name   Signature
            0      12     0  this   Lscala/Array$UnapplySeqWrapper;
            0      12     1     n   I
    Signature: #53                          // (I)Lscala/collection/immutable/Seq<TT;>;
    MethodParameters:
      Name                           Flags
      n                              final

  public scala.collection.immutable.Seq<T> toSeq();
    descriptor: ()Lscala/collection/immutable/Seq;
    flags: (0x0001) ACC_PUBLIC
    Code:
      stack=2, locals=1, args_size=1
         0: getstatic     #25                 // Field scala/Array$UnapplySeqWrapper$.MODULE$:Lscala/Array$UnapplySeqWrapper$;
         3: aload_0
         4: invokevirtual #27                 // Method scala$Array$UnapplySeqWrapper$$a:()Ljava/lang/Object;
         7: invokevirtual #65                 // Method scala/Array$UnapplySeqWrapper$.toSeq$extension:(Ljava/lang/Object;)Lscala/collection/immutable/Seq;
        10: areturn
      LineNumberTable:
        line 585: 0
      LocalVariableTable:
        Start  Length  Slot  Name   Signature
            0      11     0  this   Lscala/Array$UnapplySeqWrapper;
    Signature: #61                          // ()Lscala/collection/immutable/Seq<TT;>;

  public int hashCode();
    descriptor: ()I
    flags: (0x0001) ACC_PUBLIC
    Code:
      stack=1, locals=1, args_size=1
         0: getstatic     #25                 // Field scala/Array$UnapplySeqWrapper$.MODULE$:Lscala/Array$UnapplySeqWrapper$;
         3: pop
         4: aload_0
         5: invokevirtual #27                 // Method scala$Array$UnapplySeqWrapper$$a:()Ljava/lang/Object;
         8: invokevirtual #69                 // Method java/lang/Object.hashCode:()I
        11: ireturn
      LineNumberTable:
        line 579: 0
        line 579: 8
        line 579: 11
      LocalVariableTable:
        Start  Length  Slot  Name   Signature
            0      12     0  this   Lscala/Array$UnapplySeqWrapper;

  public boolean equals(java.lang.Object);
    descriptor: (Ljava/lang/Object;)Z
    flags: (0x0001) ACC_PUBLIC
    Code:
      stack=3, locals=2, args_size=2
         0: getstatic     #25                 // Field scala/Array$UnapplySeqWrapper$.MODULE$:Lscala/Array$UnapplySeqWrapper$;
         3: aload_0
         4: invokevirtual #27                 // Method scala$Array$UnapplySeqWrapper$$a:()Ljava/lang/Object;
         7: aload_1
         8: invokevirtual #76                 // Method scala/Array$UnapplySeqWrapper$.equals$extension:(Ljava/lang/Object;Ljava/lang/Object;)Z
        11: ireturn
      LineNumberTable:
        line 579: 0
      LocalVariableTable:
        Start  Length  Slot  Name   Signature
            0      12     0  this   Lscala/Array$UnapplySeqWrapper;
            0      12     1   x$1   Ljava/lang/Object;
    MethodParameters:
      Name                           Flags
      x$1                            final

  public scala.Array$UnapplySeqWrapper(java.lang.Object);
    descriptor: (Ljava/lang/Object;)V
    flags: (0x0001) ACC_PUBLIC
    Code:
      stack=2, locals=2, args_size=2
         0: aload_0
         1: aload_1
         2: putfield      #17                 // Field scala$Array$UnapplySeqWrapper$$a:Ljava/lang/Object;
         5: aload_0
         6: invokespecial #82                 // Method java/lang/Object."<init>":()V
         9: return
      LineNumberTable:
        line 579: 0
      LocalVariableTable:
        Start  Length  Slot  Name   Signature
            0      10     0  this   Lscala/Array$UnapplySeqWrapper;
            0      10     1     a   Ljava/lang/Object;
    Signature: #78                          // (Ljava/lang/Object;)V
    MethodParameters:
      Name                           Flags
      a                              final
}
InnerClasses:
  public static final #9= #2 of #8;       // UnapplySeqWrapper=class scala/Array$UnapplySeqWrapper of class scala/Array
  public static #12= #11 of #8;           // UnapplySeqWrapper$=class scala/Array$UnapplySeqWrapper$ of class scala/Array
Signature: #3                           // <T:Ljava/lang/Object;>Ljava/lang/Object;
SourceFile: "Array.scala"
  ScalaInlineInfo: length = 0x36 (unknown attribute)
   01 01 00 0A 00 4D 00 4E 01 00 25 00 26 01 00 33
   00 34 01 00 46 00 47 01 00 1C 00 0F 01 00 42 00
   43 01 00 14 00 15 01 00 1D 00 1E 01 00 0D 00 0F
   01 00 3B 00 3C 01
  Scala: length = 0x0 (unknown attribute)

