Classfile /Users/mw/Projects/slang-braindump/.jar/jar11/assemble/slang-braindump/assemble/content/scala/deprecated$.class
  Last modified May 29, 2022; size 627 bytes
  SHA-256 checksum b8da7f4adf3218e0b34be457e20eda82fbdeeea3cf59f9654db9579bb898f253
  Compiled from "deprecated.scala"
public final class scala.deprecated$
  minor version: 0
  major version: 52
  flags: (0x0031) ACC_PUBLIC, ACC_FINAL, ACC_SUPER
  this_class: #2                          // scala/deprecated$
  super_class: #4                         // java/lang/Object
  interfaces: 0, fields: 1, methods: 4, attributes: 3
Constant pool:
   #1 = Utf8               scala/deprecated$
   #2 = Class              #1             // scala/deprecated$
   #3 = Utf8               java/lang/Object
   #4 = Class              #3             // java/lang/Object
   #5 = Utf8               deprecated.scala
   #6 = Utf8               MODULE$
   #7 = Utf8               Lscala/deprecated$;
   #8 = Utf8               <clinit>
   #9 = Utf8               ()V
  #10 = Utf8               <init>
  #11 = NameAndType        #10:#9         // "<init>":()V
  #12 = Methodref          #2.#11         // scala/deprecated$."<init>":()V
  #13 = NameAndType        #6:#7          // MODULE$:Lscala/deprecated$;
  #14 = Fieldref           #2.#13         // scala/deprecated$.MODULE$:Lscala/deprecated$;
  #15 = Utf8               $lessinit$greater$default$1
  #16 = Utf8               ()Ljava/lang/String;
  #17 = Utf8
  #18 = String             #17            //
  #19 = Utf8               this
  #20 = Utf8               $lessinit$greater$default$2
  #21 = Methodref          #4.#11         // java/lang/Object."<init>":()V
  #22 = Utf8               Code
  #23 = Utf8               LineNumberTable
  #24 = Utf8               LocalVariableTable
  #25 = Utf8               SourceFile
  #26 = Utf8               ScalaInlineInfo
  #27 = Utf8               Scala
{
  public static final scala.deprecated$ MODULE$;
    descriptor: Lscala/deprecated$;
    flags: (0x0019) ACC_PUBLIC, ACC_STATIC, ACC_FINAL

  public static {};
    descriptor: ()V
    flags: (0x0009) ACC_PUBLIC, ACC_STATIC
    Code:
      stack=2, locals=0, args_size=0
         0: new           #2                  // class scala/deprecated$
         3: dup
         4: invokespecial #12                 // Method "<init>":()V
         7: putstatic     #14                 // Field MODULE$:Lscala/deprecated$;
        10: return
      LineNumberTable:
        line 61: 0

  public java.lang.String $lessinit$greater$default$1();
    descriptor: ()Ljava/lang/String;
    flags: (0x0001) ACC_PUBLIC
    Code:
      stack=1, locals=1, args_size=1
         0: ldc           #18                 // String
         2: areturn
      LineNumberTable:
        line 61: 0
      LocalVariableTable:
        Start  Length  Slot  Name   Signature
            0       3     0  this   Lscala/deprecated$;

  public java.lang.String $lessinit$greater$default$2();
    descriptor: ()Ljava/lang/String;
    flags: (0x0001) ACC_PUBLIC
    Code:
      stack=1, locals=1, args_size=1
         0: ldc           #18                 // String
         2: areturn
      LineNumberTable:
        line 61: 0
      LocalVariableTable:
        Start  Length  Slot  Name   Signature
            0       3     0  this   Lscala/deprecated$;

  private scala.deprecated$();
    descriptor: ()V
    flags: (0x0002) ACC_PRIVATE
    Code:
      stack=1, locals=1, args_size=1
         0: aload_0
         1: invokespecial #21                 // Method java/lang/Object."<init>":()V
         4: return
      LineNumberTable:
        line 61: 0
      LocalVariableTable:
        Start  Length  Slot  Name   Signature
            0       5     0  this   Lscala/deprecated$;
}
SourceFile: "deprecated.scala"
  ScalaInlineInfo: length = 0x13 (unknown attribute)
   01 01 00 03 00 0F 00 10 01 00 14 00 10 01 00 0A
   00 09 01
  Scala: length = 0x0 (unknown attribute)

