Classfile /Users/mw/Projects/slang-braindump/.jar/jar11/assemble/slang-braindump/assemble/content/scala/deprecatedOverriding.class
  Last modified May 29, 2022; size 1637 bytes
  SHA-256 checksum f231400ad435ebd9f31e427fa9570723420fec7867e2e7c593c2063d79192d42
  Compiled from "deprecatedOverriding.scala"
public class scala.deprecatedOverriding extends scala.annotation.Annotation implements scala.annotation.ConstantAnnotation
  minor version: 0
  major version: 52
  flags: (0x0021) ACC_PUBLIC, ACC_SUPER
  this_class: #2                          // scala/deprecatedOverriding
  super_class: #4                         // scala/annotation/Annotation
  interfaces: 1, fields: 0, methods: 3, attributes: 4
Constant pool:
   #1 = Utf8               scala/deprecatedOverriding
   #2 = Class              #1             // scala/deprecatedOverriding
   #3 = Utf8               scala/annotation/Annotation
   #4 = Class              #3             // scala/annotation/Annotation
   #5 = Utf8               scala/annotation/ConstantAnnotation
   #6 = Class              #5             // scala/annotation/ConstantAnnotation
   #7 = Utf8               deprecatedOverriding.scala
   #8 = Utf8               Lscala/reflect/ScalaSignature;
   #9 = Utf8               bytes
  #10 = Utf8               \u0006\u0005]3A!\u0003\u0006\u0001\u001b!Aq\u0003\u0001B\u0001B\u0003%\u0001\u0004\u0003\u0005$\u0001\t\u0005\t\u0015!\u0003\u0019\u0011\u0015!\u0003\u0001\"\u0001&\u000f\u001d)%\"!A\t\u0002\u00193q!\u0003\u0006\u0002\u0002#\u0005q\tC\u0003%\u000b\u0011\u00051\nC\u0004M\u000bE\u0005I\u0011A\'\t\u000fY+\u0011\u0013!C\u0001\u001b\n!B-\u001a9sK\u000e\fG/\u001a3Pm\u0016\u0014(/\u001b3j]\u001eT\u0011aC\u0001\u0006g\u000e\fG.Y\u0002\u0001\'\r\u0001a\u0002\u0006\t\u0003\u001fIi\u0011\u0001\u0005\u0006\u0003#)\t!\"\u00198o_R\fG/[8o\u0013\t\u0019\u0002C\u0001\u0006B]:|G/\u0019;j_:\u0004\"aD\u000b\n\u0005Y\u0001\"AE\"p]N$\u0018M\u001c;B]:|G/\u0019;j_:\fq!\\3tg\u0006<W\r\u0005\u0002\u001aA9\u0011!D\b\t\u00037)i\u0011\u0001\b\u0006\u0003;1\ta\u0001\u0010:p_Rt\u0014BA\u0010\u000b\u0003\u0019\u0001&/\u001a3fM&\u0011\u0011E\t\u0002\u0007\'R\u0014\u0018N\\4\u000b\u0005}Q\u0011!B:j]\u000e,\u0017A\u0002\u001fj]&$h\bF\u0002\'Q%\u0002\"a\n\u0001\u000e\u0003)AqaF\u0002\u0011\u0002\u0003\u0007\u0001\u0004C\u0004$\u0007A\u0005\t\u0019\u0001\r)\r\u0001YsCL\u00121!\t9C&\u0003\u0002.\u0015\t)B-\u001a9sK\u000e\fG/\u001a3J]\",\'/\u001b;b]\u000e,\u0017%A\u0018\u0002OM\u001b\u0007.\u001a3vY\u0016$\u0007EZ8sA\t,\u0017N\\4!M&t\u0017\r\u001c\u0011j]\u0002\"\b.\u001a\u0011gkR,(/Z\u0011\u0002c\u00051!GL\u00194]AB#\u0001A\u001a\u0011\u0005Q:T\"A\u001b\u000b\u0005Y\u0002\u0012\u0001B7fi\u0006L!\u0001O\u001b\u0003\u0015\t,\u0017M\\*fiR,\'\u000f\u000b\u0002\u0001uA\u0011AgO\u0005\u0003yU\u0012!BY3b]\u001e+G\u000f^3sQ\t\u0001a\b\u0005\u00025\u007f%\u0011\u0001)\u000e\u0002\u0007g\u0016$H/\u001a:)\u0005\u0001\u0011\u0005C\u0001\u001bD\u0013\t!UG\u0001\u0004hKR$XM]\u0001\u0015I\u0016\u0004(/Z2bi\u0016$wJ^3se&$\u0017N\\4\u0011\u0005\u001d*1CA\u0003I!\t9\u0013*\u0003\u0002K\u0015\t1\u0011I\\=SK\u001a$\u0012AR\u0001\u001cI1,7o]5oSR$sM]3bi\u0016\u0014H\u0005Z3gCVdG\u000fJ\u0019\u0016\u00039S#\u0001G(,\u0003A\u0003\"!\u0015+\u000e\u0003IS!a\u0015\t\u0002\u0013Ut7\r[3dW\u0016$\u0017BA+S\u0005E)hn\u00195fG.,GMV1sS\u0006t7-Z\u0001\u001cI1,7o]5oSR$sM]3bi\u0016\u0014H\u0005Z3gCVdG\u000f\n\u001a
  #11 = Utf8               $lessinit$greater$default$2
  #12 = Utf8               ()Ljava/lang/String;
  #13 = Utf8               scala/deprecatedOverriding$
  #14 = Class              #13            // scala/deprecatedOverriding$
  #15 = Utf8               MODULE$
  #16 = Utf8               Lscala/deprecatedOverriding$;
  #17 = NameAndType        #15:#16        // MODULE$:Lscala/deprecatedOverriding$;
  #18 = Fieldref           #14.#17        // scala/deprecatedOverriding$.MODULE$:Lscala/deprecatedOverriding$;
  #19 = Utf8
  #20 = String             #19            //
  #21 = Utf8               $lessinit$greater$default$1
  #22 = Utf8               <init>
  #23 = Utf8               (Ljava/lang/String;Ljava/lang/String;)V
  #24 = Utf8               message
  #25 = Utf8               since
  #26 = Utf8               ()V
  #27 = NameAndType        #22:#26        // "<init>":()V
  #28 = Methodref          #4.#27         // scala/annotation/Annotation."<init>":()V
  #29 = Utf8               this
  #30 = Utf8               Lscala/deprecatedOverriding;
  #31 = Utf8               Ljava/lang/String;
  #32 = Utf8               Code
  #33 = Utf8               LineNumberTable
  #34 = Utf8               LocalVariableTable
  #35 = Utf8               MethodParameters
  #36 = Utf8               SourceFile
  #37 = Utf8               RuntimeVisibleAnnotations
  #38 = Utf8               ScalaInlineInfo
  #39 = Utf8               ScalaSig
{
  public static java.lang.String $lessinit$greater$default$2();
    descriptor: ()Ljava/lang/String;
    flags: (0x0009) ACC_PUBLIC, ACC_STATIC
    Code:
      stack=1, locals=0, args_size=0
         0: getstatic     #18                 // Field scala/deprecatedOverriding$.MODULE$:Lscala/deprecatedOverriding$;
         3: pop
         4: ldc           #20                 // String
         6: areturn
      LineNumberTable:
        line 52: 4

  public static java.lang.String $lessinit$greater$default$1();
    descriptor: ()Ljava/lang/String;
    flags: (0x0009) ACC_PUBLIC, ACC_STATIC
    Code:
      stack=1, locals=0, args_size=0
         0: getstatic     #18                 // Field scala/deprecatedOverriding$.MODULE$:Lscala/deprecatedOverriding$;
         3: pop
         4: ldc           #20                 // String
         6: areturn
      LineNumberTable:
        line 52: 4

  public scala.deprecatedOverriding(java.lang.String, java.lang.String);
    descriptor: (Ljava/lang/String;Ljava/lang/String;)V
    flags: (0x0001) ACC_PUBLIC
    Code:
      stack=1, locals=3, args_size=3
         0: aload_0
         1: invokespecial #28                 // Method scala/annotation/Annotation."<init>":()V
         4: return
      LineNumberTable:
        line 52: 0
      LocalVariableTable:
        Start  Length  Slot  Name   Signature
            0       5     0  this   Lscala/deprecatedOverriding;
            0       5     1 message   Ljava/lang/String;
            0       5     2 since   Ljava/lang/String;
    MethodParameters:
      Name                           Flags
      message                        final
      since                          final
}
SourceFile: "deprecatedOverriding.scala"
RuntimeVisibleAnnotations:
  0: #8(#9=s#10)
    scala.reflect.ScalaSignature(
      bytes="\u0006\u0005]3A!\u0003\u0006\u0001\u001b!Aq\u0003\u0001B\u0001B\u0003%\u0001\u0004\u0003\u0005$\u0001\t\u0005\t\u0015!\u0003\u0019\u0011\u0015!\u0003\u0001\"\u0001&\u000f\u001d)%\"!A\t\u0002\u00193q!\u0003\u0006\u0002\u0002#\u0005q\tC\u0003%\u000b\u0011\u00051\nC\u0004M\u000bE\u0005I\u0011A\'\t\u000fY+\u0011\u0013!C\u0001\u001b\n!B-\u001a9sK\u000e\fG/\u001a3Pm\u0016\u0014(/\u001b3j]\u001eT\u0011aC\u0001\u0006g\u000e\fG.Y\u0002\u0001\'\r\u0001a\u0002\u0006\t\u0003\u001fIi\u0011\u0001\u0005\u0006\u0003#)\t!\"\u00198o_R\fG/[8o\u0013\t\u0019\u0002C\u0001\u0006B]:|G/\u0019;j_:\u0004\"aD\u000b\n\u0005Y\u0001\"AE\"p]N$\u0018M\u001c;B]:|G/\u0019;j_:\fq!\\3tg\u0006<W\r\u0005\u0002\u001aA9\u0011!D\b\t\u00037)i\u0011\u0001\b\u0006\u0003;1\ta\u0001\u0010:p_Rt\u0014BA\u0010\u000b\u0003\u0019\u0001&/\u001a3fM&\u0011\u0011E\t\u0002\u0007\'R\u0014\u0018N\\4\u000b\u0005}Q\u0011!B:j]\u000e,\u0017A\u0002\u001fj]&$h\bF\u0002\'Q%\u0002\"a\n\u0001\u000e\u0003)AqaF\u0002\u0011\u0002\u0003\u0007\u0001\u0004C\u0004$\u0007A\u0005\t\u0019\u0001\r)\r\u0001YsCL\u00121!\t9C&\u0003\u0002.\u0015\t)B-\u001a9sK\u000e\fG/\u001a3J]\",\'/\u001b;b]\u000e,\u0017%A\u0018\u0002OM\u001b\u0007.\u001a3vY\u0016$\u0007EZ8sA\t,\u0017N\\4!M&t\u0017\r\u001c\u0011j]\u0002\"\b.\u001a\u0011gkR,(/Z\u0011\u0002c\u00051!GL\u00194]AB#\u0001A\u001a\u0011\u0005Q:T\"A\u001b\u000b\u0005Y\u0002\u0012\u0001B7fi\u0006L!\u0001O\u001b\u0003\u0015\t,\u0017M\\*fiR,\'\u000f\u000b\u0002\u0001uA\u0011AgO\u0005\u0003yU\u0012!BY3b]\u001e+G\u000f^3sQ\t\u0001a\b\u0005\u00025\u007f%\u0011\u0001)\u000e\u0002\u0007g\u0016$H/\u001a:)\u0005\u0001\u0011\u0005C\u0001\u001bD\u0013\t!UG\u0001\u0004hKR$XM]\u0001\u0015I\u0016\u0004(/Z2bi\u0016$wJ^3se&$\u0017N\\4\u0011\u0005\u001d*1CA\u0003I!\t9\u0013*\u0003\u0002K\u0015\t1\u0011I\\=SK\u001a$\u0012AR\u0001\u001cI1,7o]5oSR$sM]3bi\u0016\u0014H\u0005Z3gCVdG\u000fJ\u0019\u0016\u00039S#\u0001G(,\u0003A\u0003\"!\u0015+\u000e\u0003IS!a\u0015\t\u0002\u0013Ut7\r[3dW\u0016$\u0017BA+S\u0005E)hn\u00195fG.,GMV1sS\u0006t7-Z\u0001\u001cI1,7o]5oSR$sM]3bi\u0016\u0014H\u0005Z3gCVdG\u000f\n\u001a"
    )
  ScalaInlineInfo: length = 0x9 (unknown attribute)
   01 00 00 01 00 16 00 17 00
  ScalaSig: length = 0x3 (unknown attribute)
   05 02 00
