Classfile /Users/mw/Projects/slang-braindump/.jar/jar11/assemble/slang-braindump/assemble/content/scala/Function1$.class
  Last modified May 29, 2022; size 734 bytes
  SHA-256 checksum 5cdba2185dbb119b5d9d696d98d2e31201efc0f4ca11a50982e56d444562d447
  Compiled from "Function1.scala"
public final class scala.Function1$
  minor version: 0
  major version: 52
  flags: (0x0031) ACC_PUBLIC, ACC_FINAL, ACC_SUPER
  this_class: #2                          // scala/Function1$
  super_class: #4                         // java/lang/Object
  interfaces: 0, fields: 1, methods: 3, attributes: 3
Constant pool:
   #1 = Utf8               scala/Function1$
   #2 = Class              #1             // scala/Function1$
   #3 = Utf8               java/lang/Object
   #4 = Class              #3             // java/lang/Object
   #5 = Utf8               Function1.scala
   #6 = Utf8               MODULE$
   #7 = Utf8               Lscala/Function1$;
   #8 = Utf8               <clinit>
   #9 = Utf8               ()V
  #10 = Utf8               <init>
  #11 = NameAndType        #10:#9         // "<init>":()V
  #12 = Methodref          #2.#11         // scala/Function1$."<init>":()V
  #13 = NameAndType        #6:#7          // MODULE$:Lscala/Function1$;
  #14 = Fieldref           #2.#13         // scala/Function1$.MODULE$:Lscala/Function1$;
  #15 = Utf8               UnliftOps
  #16 = Utf8               (Lscala/Function1;)Lscala/Function1;
  #17 = Utf8               <A:Ljava/lang/Object;B:Ljava/lang/Object;>(Lscala/Function1<TA;Lscala/Option<TB;>;>;)Lscala/Function1<TA;Lscala/Option<TB;>;>;
  #18 = Utf8               f
  #19 = Utf8               this
  #20 = Utf8               Lscala/Function1;
  #21 = Methodref          #4.#11         // java/lang/Object."<init>":()V
  #22 = Utf8               Code
  #23 = Utf8               LineNumberTable
  #24 = Utf8               LocalVariableTable
  #25 = Utf8               Signature
  #26 = Utf8               MethodParameters
  #27 = Utf8               SourceFile
  #28 = Utf8               ScalaInlineInfo
  #29 = Utf8               Scala
{
  public static final scala.Function1$ MODULE$;
    descriptor: Lscala/Function1$;
    flags: (0x0019) ACC_PUBLIC, ACC_STATIC, ACC_FINAL

  public static {};
    descriptor: ()V
    flags: (0x0009) ACC_PUBLIC, ACC_STATIC
    Code:
      stack=2, locals=0, args_size=0
         0: new           #2                  // class scala/Function1$
         3: dup
         4: invokespecial #12                 // Method "<init>":()V
         7: putstatic     #14                 // Field MODULE$:Lscala/Function1$;
        10: return
      LineNumberTable:
        line 18: 0

  public final <A extends java.lang.Object, B extends java.lang.Object> scala.Function1<A, scala.Option<B>> UnliftOps(scala.Function1<A, scala.Option<B>>);
    descriptor: (Lscala/Function1;)Lscala/Function1;
    flags: (0x0011) ACC_PUBLIC, ACC_FINAL
    Code:
      stack=1, locals=2, args_size=2
         0: aload_1
         1: areturn
      LineNumberTable:
        line 20: 0
      LocalVariableTable:
        Start  Length  Slot  Name   Signature
            0       2     0  this   Lscala/Function1$;
            0       2     1     f   Lscala/Function1;
    Signature: #17                          // <A:Ljava/lang/Object;B:Ljava/lang/Object;>(Lscala/Function1<TA;Lscala/Option<TB;>;>;)Lscala/Function1<TA;Lscala/Option<TB;>;>;
    MethodParameters:
      Name                           Flags
      f                              final

  private scala.Function1$();
    descriptor: ()V
    flags: (0x0002) ACC_PRIVATE
    Code:
      stack=1, locals=1, args_size=1
         0: aload_0
         1: invokespecial #21                 // Method java/lang/Object."<init>":()V
         4: return
      LineNumberTable:
        line 18: 0
      LocalVariableTable:
        Start  Length  Slot  Name   Signature
            0       5     0  this   Lscala/Function1$;
}
SourceFile: "Function1.scala"
  ScalaInlineInfo: length = 0xE (unknown attribute)
   01 01 00 02 00 0A 00 09 01 00 0F 00 10 01
  Scala: length = 0x0 (unknown attribute)

