Classfile /Users/mw/Projects/slang-braindump/.jar/jar11/assemble/slang-braindump/assemble/content/scala/Function12.class
  Last modified May 29, 2022; size 6117 bytes
  SHA-256 checksum 18243152efef17883b1d78bc66a1b48a253b2ddc3ceab77cad5679e0b8bf837b
  Compiled from "Function12.scala"
public interface scala.Function12<T1 extends java.lang.Object, T2 extends java.lang.Object, T3 extends java.lang.Object, T4 extends java.lang.Object, T5 extends java.lang.Object, T6 extends java.lang.Object, T7 extends java.lang.Object, T8 extends java.lang.Object, T9 extends java.lang.Object, T10 extends java.lang.Object, T11 extends java.lang.Object, T12 extends java.lang.Object, R extends java.lang.Object>
  minor version: 0
  major version: 52
  flags: (0x0601) ACC_PUBLIC, ACC_INTERFACE, ACC_ABSTRACT
  this_class: #2                          // scala/Function12
  super_class: #5                         // java/lang/Object
  interfaces: 0, fields: 0, methods: 12, attributes: 7
Constant pool:
    #1 = Utf8               scala/Function12
    #2 = Class              #1            // scala/Function12
    #3 = Utf8               <T1:Ljava/lang/Object;T2:Ljava/lang/Object;T3:Ljava/lang/Object;T4:Ljava/lang/Object;T5:Ljava/lang/Object;T6:Ljava/lang/Object;T7:Ljava/lang/Object;T8:Ljava/lang/Object;T9:Ljava/lang/Object;T10:Ljava/lang/Object;T11:Ljava/lang/Object;T12:Ljava/lang/Object;R:Ljava/lang/Object;>Ljava/lang/Object;
    #4 = Utf8               java/lang/Object
    #5 = Class              #4            // java/lang/Object
    #6 = Utf8               Function12.scala
    #7 = Utf8               Lscala/reflect/ScalaSignature;
    #8 = Utf8               bytes
    #9 = Utf8               \u0006\u0005\u0005Maa\u0002\u0004\b!\u0003\r\tA\u0003\u0005\u0006!\u0001!\t!\u0005\u0005\u0006+\u00011\tA\u0006\u0005\u0006=\u0002!\ta\u0018\u0005\u0006k\u0002!\tA\u001e\u0005\u0006y\u0002!\t% \u0002\u000b\rVt7\r^5p]F\u0012$\"\u0001\u0005\u0002\u000bM\u001c\u0017\r\\1\u0004\u0001Uq1\"\n\u00160ier4\tS\'S/rK2C\u0001\u0001\r!\tia\"D\u0001\b\u0013\tyqA\u0001\u0004B]f\u0014VMZ\u0001\u0007I%t\u0017\u000e\u001e\u0013\u0015\u0003I\u0001\"!D\n\n\u0005Q9!\u0001B+oSR\fQ!\u00199qYf$Rb\u0006\u0012(YE24\bQ#K\u001fRK\u0006C\u0001\r\u001a\u0019\u0001!aA\u0007\u0001\u0005\u0006\u0004Y\"!\u0001*\u0012\u0005qy\u0002CA\u0007\u001e\u0013\tqrAA\u0004O_RD\u0017N\\4\u0011\u00055\u0001\u0013BA\u0011\b\u0005\r\te.\u001f\u0005\u0006G\t\u0001\r\u0001J\u0001\u0003mF\u0002\"\u0001G\u0013\u0005\r\u0019\u0002\u0001R1\u0001\u001c\u0005\t!\u0016\u0007C\u0003)\u0005\u0001\u0007\u0011&\u0001\u0002weA\u0011\u0001D\u000b\u0003\u0007W\u0001A)\u0019A\u000e\u0003\u0005Q\u0013\u0004\"B\u0017\u0003\u0001\u0004q\u0013A\u0001<4!\tAr\u0006\u0002\u00041\u0001!\u0015\ra\u0007\u0002\u0003)NBQA\r\u0002A\u0002M\n!A\u001e\u001b\u0011\u0005a!DAB\u001b\u0001\u0011\u000b\u00071D\u0001\u0002Ui!)qG\u0001a\u0001q\u0005\u0011a/\u000e\t\u00031e\"aA\u000f\u0001\t\u0006\u0004Y\"A\u0001+6\u0011\u0015a$\u00011\u0001>\u0003\t1h\u0007\u0005\u0002\u0019}\u00111q\b\u0001EC\u0002m\u0011!\u0001\u0016\u001c\t\u000b\u0005\u0013\u0001\u0019\u0001\"\u0002\u0005Y<\u0004C\u0001\rD\t\u0019!\u0005\u0001#b\u00017\t\u0011Ak\u000e\u0005\u0006\r\n\u0001\raR\u0001\u0003mb\u0002\"\u0001\u0007%\u0005\r%\u0003\u0001R1\u0001\u001c\u0005\t!\u0006\bC\u0003L\u0005\u0001\u0007A*\u0001\u0002wsA\u0011\u0001$\u0014\u0003\u0007\u001d\u0002A)\u0019A\u000e\u0003\u0005QK\u0004\"\u0002)\u0003\u0001\u0004\t\u0016a\u0001<2aA\u0011\u0001D\u0015\u0003\u0007\'\u0002A)\u0019A\u000e\u0003\u0007Q\u000b\u0004\u0007C\u0003V\u0005\u0001\u0007a+A\u0002wcE\u0002\"\u0001G,\u0005\ra\u0003\u0001R1\u0001\u001c\u0005\r!\u0016\'\r\u0005\u00065\n\u0001\raW\u0001\u0004mF\u0012\u0004C\u0001\r]\t\u0019i\u0006\u0001#b\u00017\t\u0019A+\r\u001a\u0002\u000f\r,(O]5fIV\t\u0001\r\u0005\u0003\u000eC\u0012\u001a\u0017B\u00012\b\u0005%1UO\\2uS>t\u0017\u0007\u0005\u0003\u000eC&\"\u0007\u0003B\u0007b]\u0015\u0004B!D14MB!Q\"\u0019\u001dh!\u0011i\u0011-\u00105\u0011\t5\t\')\u001b\t\u0005\u001b\u0005<%\u000e\u0005\u0003\u000eC2[\u0007\u0003B\u0007b#2\u0004B!D1W[B!Q\"Y.\u0018Q\t\u0019q\u000e\u0005\u0002qg6\t\u0011O\u0003\u0002s\u000f\u0005Q\u0011M\u001c8pi\u0006$\u0018n\u001c8\n\u0005Q\f(!D;ogB,7-[1mSj,G-\u0001\u0004ukBdW\rZ\u000b\u0002oB!Q\"\u0019=\u0018!9i\u0011\u0010J\u0015/gaj$i\u0012\'R-nK!A_\u0004\u0003\u000fQ+\b\u000f\\32e!\u0012Aa\\\u0001\ti>\u001cFO]5oOR\ta\u0010E\u0002\u0000\u0003\u001bqA!!\u0001\u0002\nA\u0019\u00111A\u0004\u000e\u0005\u0005\u0015!bAA\u0004\u0013\u00051AH]8pizJ1!a\u0003\b\u0003\u0019\u0001&/\u001a3fM&!\u0011qBA\t\u0005\u0019\u0019FO]5oO*\u0019\u00111B\u0004
   #10 = Utf8               java/lang/invoke/MethodHandles$Lookup
   #11 = Class              #10           // java/lang/invoke/MethodHandles$Lookup
   #12 = Utf8               java/lang/invoke/MethodHandles
   #13 = Class              #12           // java/lang/invoke/MethodHandles
   #14 = Utf8               Lookup
   #15 = Utf8               apply
   #16 = Utf8               (Ljava/lang/Object;Ljava/lang/Object;Ljava/lang/Object;Ljava/lang/Object;Ljava/lang/Object;Ljava/lang/Object;Ljava/lang/Object;Ljava/lang/Object;Ljava/lang/Object;Ljava/lang/Object;Ljava/lang/Object;Ljava/lang/Object;)Ljava/lang/Object;
   #17 = Utf8               (TT1;TT2;TT3;TT4;TT5;TT6;TT7;TT8;TT9;TT10;TT11;TT12;)TR;
   #18 = Utf8               v1
   #19 = Utf8               v2
   #20 = Utf8               v3
   #21 = Utf8               v4
   #22 = Utf8               v5
   #23 = Utf8               v6
   #24 = Utf8               v7
   #25 = Utf8               v8
   #26 = Utf8               v9
   #27 = Utf8               v10
   #28 = Utf8               v11
   #29 = Utf8               v12
   #30 = Utf8               curried$
   #31 = Utf8               (Lscala/Function12;)Lscala/Function1;
   #32 = Utf8               $this
   #33 = Utf8               curried
   #34 = Utf8               ()Lscala/Function1;
   #35 = NameAndType        #33:#34       // curried:()Lscala/Function1;
   #36 = InterfaceMethodref #2.#35        // scala/Function12.curried:()Lscala/Function1;
   #37 = Utf8               Lscala/Function12;
   #38 = Utf8               ()Lscala/Function1<TT1;Lscala/Function1<TT2;Lscala/Function1<TT3;Lscala/Function1<TT4;Lscala/Function1<TT5;Lscala/Function1<TT6;Lscala/Function1<TT7;Lscala/Function1<TT8;Lscala/Function1<TT9;Lscala/Function1<TT10;Lscala/Function1<TT11;Lscala/Function1<TT12;TR;>;>;>;>;>;>;>;>;>;>;>;>;
   #39 = Utf8               (Ljava/lang/Object;)Ljava/lang/Object;
   #40 = MethodType         #39           //  (Ljava/lang/Object;)Ljava/lang/Object;
   #41 = Utf8               $anonfun$curried$1
   #42 = Utf8               (Lscala/Function12;Ljava/lang/Object;)Lscala/Function1;
   #43 = NameAndType        #41:#42       // $anonfun$curried$1:(Lscala/Function12;Ljava/lang/Object;)Lscala/Function1;
   #44 = InterfaceMethodref #2.#43        // scala/Function12.$anonfun$curried$1:(Lscala/Function12;Ljava/lang/Object;)Lscala/Function1;
   #45 = MethodHandle       6:#44         // REF_invokeStatic scala/Function12.$anonfun$curried$1:(Lscala/Function12;Ljava/lang/Object;)Lscala/Function1;
   #46 = Utf8               (Ljava/lang/Object;)Lscala/Function1;
   #47 = MethodType         #46           //  (Ljava/lang/Object;)Lscala/Function1;
   #48 = Integer            5
   #49 = Integer            1
   #50 = Utf8               java/lang/invoke/LambdaMetafactory
   #51 = Class              #50           // java/lang/invoke/LambdaMetafactory
   #52 = Utf8               altMetafactory
   #53 = Utf8               (Ljava/lang/invoke/MethodHandles$Lookup;Ljava/lang/String;Ljava/lang/invoke/MethodType;[Ljava/lang/Object;)Ljava/lang/invoke/CallSite;
   #54 = NameAndType        #52:#53       // altMetafactory:(Ljava/lang/invoke/MethodHandles$Lookup;Ljava/lang/String;Ljava/lang/invoke/MethodType;[Ljava/lang/Object;)Ljava/lang/invoke/CallSite;
   #55 = Methodref          #51.#54       // java/lang/invoke/LambdaMetafactory.altMetafactory:(Ljava/lang/invoke/MethodHandles$Lookup;Ljava/lang/String;Ljava/lang/invoke/MethodType;[Ljava/lang/Object;)Ljava/lang/invoke/CallSite;
   #56 = MethodHandle       6:#55         // REF_invokeStatic java/lang/invoke/LambdaMetafactory.altMetafactory:(Ljava/lang/invoke/MethodHandles$Lookup;Ljava/lang/String;Ljava/lang/invoke/MethodType;[Ljava/lang/Object;)Ljava/lang/invoke/CallSite;
   #57 = NameAndType        #15:#31       // apply:(Lscala/Function12;)Lscala/Function1;
   #58 = InvokeDynamic      #0:#57        // #0:apply:(Lscala/Function12;)Lscala/Function1;
   #59 = Utf8               this
   #60 = Utf8               tupled$
   #61 = Utf8               tupled
   #62 = NameAndType        #61:#34       // tupled:()Lscala/Function1;
   #63 = InterfaceMethodref #2.#62        // scala/Function12.tupled:()Lscala/Function1;
   #64 = Utf8               ()Lscala/Function1<Lscala/Tuple12<TT1;TT2;TT3;TT4;TT5;TT6;TT7;TT8;TT9;TT10;TT11;TT12;>;TR;>;
   #65 = Utf8               $anonfun$tupled$1
   #66 = Utf8               (Lscala/Function12;Lscala/Tuple12;)Ljava/lang/Object;
   #67 = NameAndType        #65:#66       // $anonfun$tupled$1:(Lscala/Function12;Lscala/Tuple12;)Ljava/lang/Object;
   #68 = InterfaceMethodref #2.#67        // scala/Function12.$anonfun$tupled$1:(Lscala/Function12;Lscala/Tuple12;)Ljava/lang/Object;
   #69 = MethodHandle       6:#68         // REF_invokeStatic scala/Function12.$anonfun$tupled$1:(Lscala/Function12;Lscala/Tuple12;)Ljava/lang/Object;
   #70 = Utf8               (Lscala/Tuple12;)Ljava/lang/Object;
   #71 = MethodType         #70           //  (Lscala/Tuple12;)Ljava/lang/Object;
   #72 = InvokeDynamic      #1:#57        // #1:apply:(Lscala/Function12;)Lscala/Function1;
   #73 = Utf8               toString$
   #74 = Utf8               (Lscala/Function12;)Ljava/lang/String;
   #75 = Utf8               toString
   #76 = Utf8               ()Ljava/lang/String;
   #77 = NameAndType        #75:#76       // toString:()Ljava/lang/String;
   #78 = InterfaceMethodref #2.#77        // scala/Function12.toString:()Ljava/lang/String;
   #79 = Utf8               <function12>
   #80 = String             #79           // <function12>
   #81 = Utf8               $anonfun$curried$2
   #82 = Utf8               (Lscala/Function12;Ljava/lang/Object;Ljava/lang/Object;Ljava/lang/Object;Ljava/lang/Object;Ljava/lang/Object;Ljava/lang/Object;Ljava/lang/Object;Ljava/lang/Object;Ljava/lang/Object;Ljava/lang/Object;Ljava/lang/Object;Ljava/lang/Object;)Ljava/lang/Object;
   #83 = Utf8               x1$1
   #84 = Utf8               x2
   #85 = Utf8               x3
   #86 = Utf8               x4
   #87 = Utf8               x5
   #88 = Utf8               x6
   #89 = Utf8               x7
   #90 = Utf8               x8
   #91 = Utf8               x9
   #92 = Utf8               x10
   #93 = Utf8               x11
   #94 = Utf8               x12
   #95 = NameAndType        #15:#16       // apply:(Ljava/lang/Object;Ljava/lang/Object;Ljava/lang/Object;Ljava/lang/Object;Ljava/lang/Object;Ljava/lang/Object;Ljava/lang/Object;Ljava/lang/Object;Ljava/lang/Object;Ljava/lang/Object;Ljava/lang/Object;Ljava/lang/Object;)Ljava/lang/Object;
   #96 = InterfaceMethodref #2.#95        // scala/Function12.apply:(Ljava/lang/Object;Ljava/lang/Object;Ljava/lang/Object;Ljava/lang/Object;Ljava/lang/Object;Ljava/lang/Object;Ljava/lang/Object;Ljava/lang/Object;Ljava/lang/Object;Ljava/lang/Object;Ljava/lang/Object;Ljava/lang/Object;)Ljava/lang/Object;
   #97 = Utf8               Ljava/lang/Object;
   #98 = Utf8               x1
   #99 = Utf8               (Ljava/lang/Object;Ljava/lang/Object;Ljava/lang/Object;Ljava/lang/Object;Ljava/lang/Object;Ljava/lang/Object;Ljava/lang/Object;Ljava/lang/Object;Ljava/lang/Object;Ljava/lang/Object;Ljava/lang/Object;)Ljava/lang/Object;
  #100 = MethodType         #99           //  (Ljava/lang/Object;Ljava/lang/Object;Ljava/lang/Object;Ljava/lang/Object;Ljava/lang/Object;Ljava/lang/Object;Ljava/lang/Object;Ljava/lang/Object;Ljava/lang/Object;Ljava/lang/Object;Ljava/lang/Object;)Ljava/lang/Object;
  #101 = NameAndType        #81:#82       // $anonfun$curried$2:(Lscala/Function12;Ljava/lang/Object;Ljava/lang/Object;Ljava/lang/Object;Ljava/lang/Object;Ljava/lang/Object;Ljava/lang/Object;Ljava/lang/Object;Ljava/lang/Object;Ljava/lang/Object;Ljava/lang/Object;Ljava/lang/Object;Ljava/lang/Object;)Ljava/lang/Object;
  #102 = InterfaceMethodref #2.#101       // scala/Function12.$anonfun$curried$2:(Lscala/Function12;Ljava/lang/Object;Ljava/lang/Object;Ljava/lang/Object;Ljava/lang/Object;Ljava/lang/Object;Ljava/lang/Object;Ljava/lang/Object;Ljava/lang/Object;Ljava/lang/Object;Ljava/lang/Object;Ljava/lang/Object;Ljava/lang/Object;)Ljava/lang/Object;
  #103 = MethodHandle       6:#102        // REF_invokeStatic scala/Function12.$anonfun$curried$2:(Lscala/Function12;Ljava/lang/Object;Ljava/lang/Object;Ljava/lang/Object;Ljava/lang/Object;Ljava/lang/Object;Ljava/lang/Object;Ljava/lang/Object;Ljava/lang/Object;Ljava/lang/Object;Ljava/lang/Object;Ljava/lang/Object;Ljava/lang/Object;)Ljava/lang/Object;
  #104 = Utf8               (Lscala/Function12;Ljava/lang/Object;)Lscala/Function11;
  #105 = NameAndType        #15:#104      // apply:(Lscala/Function12;Ljava/lang/Object;)Lscala/Function11;
  #106 = InvokeDynamic      #2:#105       // #2:apply:(Lscala/Function12;Ljava/lang/Object;)Lscala/Function11;
  #107 = Utf8               scala/Function11
  #108 = Class              #107          // scala/Function11
  #109 = InterfaceMethodref #108.#35      // scala/Function11.curried:()Lscala/Function1;
  #110 = Utf8               x0$1
  #111 = Utf8               scala/Tuple12
  #112 = Class              #111          // scala/Tuple12
  #113 = Utf8               _1
  #114 = Utf8               ()Ljava/lang/Object;
  #115 = NameAndType        #113:#114     // _1:()Ljava/lang/Object;
  #116 = Methodref          #112.#115     // scala/Tuple12._1:()Ljava/lang/Object;
  #117 = Utf8               _2
  #118 = NameAndType        #117:#114     // _2:()Ljava/lang/Object;
  #119 = Methodref          #112.#118     // scala/Tuple12._2:()Ljava/lang/Object;
  #120 = Utf8               _3
  #121 = NameAndType        #120:#114     // _3:()Ljava/lang/Object;
  #122 = Methodref          #112.#121     // scala/Tuple12._3:()Ljava/lang/Object;
  #123 = Utf8               _4
  #124 = NameAndType        #123:#114     // _4:()Ljava/lang/Object;
  #125 = Methodref          #112.#124     // scala/Tuple12._4:()Ljava/lang/Object;
  #126 = Utf8               _5
  #127 = NameAndType        #126:#114     // _5:()Ljava/lang/Object;
  #128 = Methodref          #112.#127     // scala/Tuple12._5:()Ljava/lang/Object;
  #129 = Utf8               _6
  #130 = NameAndType        #129:#114     // _6:()Ljava/lang/Object;
  #131 = Methodref          #112.#130     // scala/Tuple12._6:()Ljava/lang/Object;
  #132 = Utf8               _7
  #133 = NameAndType        #132:#114     // _7:()Ljava/lang/Object;
  #134 = Methodref          #112.#133     // scala/Tuple12._7:()Ljava/lang/Object;
  #135 = Utf8               _8
  #136 = NameAndType        #135:#114     // _8:()Ljava/lang/Object;
  #137 = Methodref          #112.#136     // scala/Tuple12._8:()Ljava/lang/Object;
  #138 = Utf8               _9
  #139 = NameAndType        #138:#114     // _9:()Ljava/lang/Object;
  #140 = Methodref          #112.#139     // scala/Tuple12._9:()Ljava/lang/Object;
  #141 = Utf8               _10
  #142 = NameAndType        #141:#114     // _10:()Ljava/lang/Object;
  #143 = Methodref          #112.#142     // scala/Tuple12._10:()Ljava/lang/Object;
  #144 = Utf8               _11
  #145 = NameAndType        #144:#114     // _11:()Ljava/lang/Object;
  #146 = Methodref          #112.#145     // scala/Tuple12._11:()Ljava/lang/Object;
  #147 = Utf8               _12
  #148 = NameAndType        #147:#114     // _12:()Ljava/lang/Object;
  #149 = Methodref          #112.#148     // scala/Tuple12._12:()Ljava/lang/Object;
  #150 = Utf8               scala/MatchError
  #151 = Class              #150          // scala/MatchError
  #152 = Utf8               <init>
  #153 = Utf8               (Ljava/lang/Object;)V
  #154 = NameAndType        #152:#153     // "<init>":(Ljava/lang/Object;)V
  #155 = Methodref          #151.#154     // scala/MatchError."<init>":(Ljava/lang/Object;)V
  #156 = Utf8               Lscala/Tuple12;
  #157 = Utf8               $init$
  #158 = Utf8               (Lscala/Function12;)V
  #159 = Utf8               $deserializeLambda$
  #160 = Utf8               (Ljava/lang/invoke/SerializedLambda;)Ljava/lang/Object;
  #161 = Utf8               scala/runtime/LambdaDeserialize
  #162 = Class              #161          // scala/runtime/LambdaDeserialize
  #163 = Utf8               bootstrap
  #164 = Utf8               (Ljava/lang/invoke/MethodHandles$Lookup;Ljava/lang/String;Ljava/lang/invoke/MethodType;[Ljava/lang/invoke/MethodHandle;)Ljava/lang/invoke/CallSite;
  #165 = NameAndType        #163:#164     // bootstrap:(Ljava/lang/invoke/MethodHandles$Lookup;Ljava/lang/String;Ljava/lang/invoke/MethodType;[Ljava/lang/invoke/MethodHandle;)Ljava/lang/invoke/CallSite;
  #166 = Methodref          #162.#165     // scala/runtime/LambdaDeserialize.bootstrap:(Ljava/lang/invoke/MethodHandles$Lookup;Ljava/lang/String;Ljava/lang/invoke/MethodType;[Ljava/lang/invoke/MethodHandle;)Ljava/lang/invoke/CallSite;
  #167 = MethodHandle       6:#166        // REF_invokeStatic scala/runtime/LambdaDeserialize.bootstrap:(Ljava/lang/invoke/MethodHandles$Lookup;Ljava/lang/String;Ljava/lang/invoke/MethodType;[Ljava/lang/invoke/MethodHandle;)Ljava/lang/invoke/CallSite;
  #168 = Utf8               lambdaDeserialize
  #169 = NameAndType        #168:#160     // lambdaDeserialize:(Ljava/lang/invoke/SerializedLambda;)Ljava/lang/Object;
  #170 = InvokeDynamic      #3:#169       // #3:lambdaDeserialize:(Ljava/lang/invoke/SerializedLambda;)Ljava/lang/Object;
  #171 = Utf8               Signature
  #172 = Utf8               MethodParameters
  #173 = Utf8               Code
  #174 = Utf8               LineNumberTable
  #175 = Utf8               LocalVariableTable
  #176 = Utf8               StackMapTable
  #177 = Utf8               InnerClasses
  #178 = Utf8               SourceFile
  #179 = Utf8               RuntimeVisibleAnnotations
  #180 = Utf8               BootstrapMethods
  #181 = Utf8               ScalaInlineInfo
  #182 = Utf8               ScalaSig
{
  public abstract R apply(T1, T2, T3, T4, T5, T6, T7, T8, T9, T10, T11, T12);
    descriptor: (Ljava/lang/Object;Ljava/lang/Object;Ljava/lang/Object;Ljava/lang/Object;Ljava/lang/Object;Ljava/lang/Object;Ljava/lang/Object;Ljava/lang/Object;Ljava/lang/Object;Ljava/lang/Object;Ljava/lang/Object;Ljava/lang/Object;)Ljava/lang/Object;
    flags: (0x0401) ACC_PUBLIC, ACC_ABSTRACT
    Signature: #17                          // (TT1;TT2;TT3;TT4;TT5;TT6;TT7;TT8;TT9;TT10;TT11;TT12;)TR;
    MethodParameters:
      Name                           Flags
      v1                             final
      v2                             final
      v3                             final
      v4                             final
      v5                             final
      v6                             final
      v7                             final
      v8                             final
      v9                             final
      v10                            final
      v11                            final
      v12                            final

  public static scala.Function1 curried$(scala.Function12);
    descriptor: (Lscala/Function12;)Lscala/Function1;
    flags: (0x1009) ACC_PUBLIC, ACC_STATIC, ACC_SYNTHETIC
    Code:
      stack=1, locals=1, args_size=1
         0: aload_0
         1: invokespecial #36                 // InterfaceMethod curried:()Lscala/Function1;
         4: areturn
      LineNumberTable:
        line 30: 0
      LocalVariableTable:
        Start  Length  Slot  Name   Signature
            0       5     0 $this   Lscala/Function12;
    MethodParameters:
      Name                           Flags
      $this                          final synthetic

  public default scala.Function1<T1, scala.Function1<T2, scala.Function1<T3, scala.Function1<T4, scala.Function1<T5, scala.Function1<T6, scala.Function1<T7, scala.Function1<T8, scala.Function1<T9, scala.Function1<T10, scala.Function1<T11, scala.Function1<T12, R>>>>>>>>>>>> curried();
    descriptor: ()Lscala/Function1;
    flags: (0x0001) ACC_PUBLIC
    Code:
      stack=1, locals=1, args_size=1
         0: aload_0
         1: invokedynamic #58,  0             // InvokeDynamic #0:apply:(Lscala/Function12;)Lscala/Function1;
         6: areturn
      LineNumberTable:
        line 31: 0
      LocalVariableTable:
        Start  Length  Slot  Name   Signature
            0       7     0  this   Lscala/Function12;
    Signature: #38                          // ()Lscala/Function1<TT1;Lscala/Function1<TT2;Lscala/Function1<TT3;Lscala/Function1<TT4;Lscala/Function1<TT5;Lscala/Function1<TT6;Lscala/Function1<TT7;Lscala/Function1<TT8;Lscala/Function1<TT9;Lscala/Function1<TT10;Lscala/Function1<TT11;Lscala/Function1<TT12;TR;>;>;>;>;>;>;>;>;>;>;>;>;

  public static scala.Function1 tupled$(scala.Function12);
    descriptor: (Lscala/Function12;)Lscala/Function1;
    flags: (0x1009) ACC_PUBLIC, ACC_STATIC, ACC_SYNTHETIC
    Code:
      stack=1, locals=1, args_size=1
         0: aload_0
         1: invokespecial #63                 // InterfaceMethod tupled:()Lscala/Function1;
         4: areturn
      LineNumberTable:
        line 39: 0
      LocalVariableTable:
        Start  Length  Slot  Name   Signature
            0       5     0 $this   Lscala/Function12;
    MethodParameters:
      Name                           Flags
      $this                          final synthetic

  public default scala.Function1<scala.Tuple12<T1, T2, T3, T4, T5, T6, T7, T8, T9, T10, T11, T12>, R> tupled();
    descriptor: ()Lscala/Function1;
    flags: (0x0001) ACC_PUBLIC
    Code:
      stack=1, locals=1, args_size=1
         0: aload_0
         1: invokedynamic #72,  0             // InvokeDynamic #1:apply:(Lscala/Function12;)Lscala/Function1;
         6: areturn
      LineNumberTable:
        line 39: 0
      LocalVariableTable:
        Start  Length  Slot  Name   Signature
            0       7     0  this   Lscala/Function12;
    Signature: #64                          // ()Lscala/Function1<Lscala/Tuple12<TT1;TT2;TT3;TT4;TT5;TT6;TT7;TT8;TT9;TT10;TT11;TT12;>;TR;>;

  public static java.lang.String toString$(scala.Function12);
    descriptor: (Lscala/Function12;)Ljava/lang/String;
    flags: (0x1009) ACC_PUBLIC, ACC_STATIC, ACC_SYNTHETIC
    Code:
      stack=1, locals=1, args_size=1
         0: aload_0
         1: invokespecial #78                 // InterfaceMethod toString:()Ljava/lang/String;
         4: areturn
      LineNumberTable:
        line 42: 0
      LocalVariableTable:
        Start  Length  Slot  Name   Signature
            0       5     0 $this   Lscala/Function12;
    MethodParameters:
      Name                           Flags
      $this                          final synthetic

  public default java.lang.String toString();
    descriptor: ()Ljava/lang/String;
    flags: (0x0001) ACC_PUBLIC
    Code:
      stack=1, locals=1, args_size=1
         0: ldc           #80                 // String <function12>
         2: areturn
      LineNumberTable:
        line 42: 0
      LocalVariableTable:
        Start  Length  Slot  Name   Signature
            0       3     0  this   Lscala/Function12;

  public static java.lang.Object $anonfun$curried$2(scala.Function12, java.lang.Object, java.lang.Object, java.lang.Object, java.lang.Object, java.lang.Object, java.lang.Object, java.lang.Object, java.lang.Object, java.lang.Object, java.lang.Object, java.lang.Object, java.lang.Object);
    descriptor: (Lscala/Function12;Ljava/lang/Object;Ljava/lang/Object;Ljava/lang/Object;Ljava/lang/Object;Ljava/lang/Object;Ljava/lang/Object;Ljava/lang/Object;Ljava/lang/Object;Ljava/lang/Object;Ljava/lang/Object;Ljava/lang/Object;Ljava/lang/Object;)Ljava/lang/Object;
    flags: (0x1009) ACC_PUBLIC, ACC_STATIC, ACC_SYNTHETIC
    Code:
      stack=13, locals=13, args_size=13
         0: aload_0
         1: aload_1
         2: aload_2
         3: aload_3
         4: aload         4
         6: aload         5
         8: aload         6
        10: aload         7
        12: aload         8
        14: aload         9
        16: aload         10
        18: aload         11
        20: aload         12
        22: invokeinterface #96,  13          // InterfaceMethod apply:(Ljava/lang/Object;Ljava/lang/Object;Ljava/lang/Object;Ljava/lang/Object;Ljava/lang/Object;Ljava/lang/Object;Ljava/lang/Object;Ljava/lang/Object;Ljava/lang/Object;Ljava/lang/Object;Ljava/lang/Object;Ljava/lang/Object;)Ljava/lang/Object;
        27: areturn
      LineNumberTable:
        line 31: 0
      LocalVariableTable:
        Start  Length  Slot  Name   Signature
            0      28     0 $this   Lscala/Function12;
            0      28     1  x1$1   Ljava/lang/Object;
            0      28     2    x2   Ljava/lang/Object;
            0      28     3    x3   Ljava/lang/Object;
            0      28     4    x4   Ljava/lang/Object;
            0      28     5    x5   Ljava/lang/Object;
            0      28     6    x6   Ljava/lang/Object;
            0      28     7    x7   Ljava/lang/Object;
            0      28     8    x8   Ljava/lang/Object;
            0      28     9    x9   Ljava/lang/Object;
            0      28    10   x10   Ljava/lang/Object;
            0      28    11   x11   Ljava/lang/Object;
            0      28    12   x12   Ljava/lang/Object;
    MethodParameters:
      Name                           Flags
      $this                          final synthetic
      x1$1                           final
      x2                             final
      x3                             final
      x4                             final
      x5                             final
      x6                             final
      x7                             final
      x8                             final
      x9                             final
      x10                            final
      x11                            final
      x12                            final

  public static scala.Function1 $anonfun$curried$1(scala.Function12, java.lang.Object);
    descriptor: (Lscala/Function12;Ljava/lang/Object;)Lscala/Function1;
    flags: (0x1009) ACC_PUBLIC, ACC_STATIC, ACC_SYNTHETIC
    Code:
      stack=2, locals=2, args_size=2
         0: aload_0
         1: aload_1
         2: invokedynamic #106,  0            // InvokeDynamic #2:apply:(Lscala/Function12;Ljava/lang/Object;)Lscala/Function11;
         7: invokeinterface #109,  1          // InterfaceMethod scala/Function11.curried:()Lscala/Function1;
        12: areturn
      LineNumberTable:
        line 31: 0
      LocalVariableTable:
        Start  Length  Slot  Name   Signature
            0      13     0 $this   Lscala/Function12;
            0      13     1    x1   Ljava/lang/Object;
    MethodParameters:
      Name                           Flags
      $this                          final synthetic
      x1                             final

  public static java.lang.Object $anonfun$tupled$1(scala.Function12, scala.Tuple12);
    descriptor: (Lscala/Function12;Lscala/Tuple12;)Ljava/lang/Object;
    flags: (0x1009) ACC_PUBLIC, ACC_STATIC, ACC_SYNTHETIC
    Code:
      stack=13, locals=15, args_size=2
         0: aload_1
         1: ifnull        108
         4: aload_1
         5: invokevirtual #116                // Method scala/Tuple12._1:()Ljava/lang/Object;
         8: astore_3
         9: aload_1
        10: invokevirtual #119                // Method scala/Tuple12._2:()Ljava/lang/Object;
        13: astore        4
        15: aload_1
        16: invokevirtual #122                // Method scala/Tuple12._3:()Ljava/lang/Object;
        19: astore        5
        21: aload_1
        22: invokevirtual #125                // Method scala/Tuple12._4:()Ljava/lang/Object;
        25: astore        6
        27: aload_1
        28: invokevirtual #128                // Method scala/Tuple12._5:()Ljava/lang/Object;
        31: astore        7
        33: aload_1
        34: invokevirtual #131                // Method scala/Tuple12._6:()Ljava/lang/Object;
        37: astore        8
        39: aload_1
        40: invokevirtual #134                // Method scala/Tuple12._7:()Ljava/lang/Object;
        43: astore        9
        45: aload_1
        46: invokevirtual #137                // Method scala/Tuple12._8:()Ljava/lang/Object;
        49: astore        10
        51: aload_1
        52: invokevirtual #140                // Method scala/Tuple12._9:()Ljava/lang/Object;
        55: astore        11
        57: aload_1
        58: invokevirtual #143                // Method scala/Tuple12._10:()Ljava/lang/Object;
        61: astore        12
        63: aload_1
        64: invokevirtual #146                // Method scala/Tuple12._11:()Ljava/lang/Object;
        67: astore        13
        69: aload_1
        70: invokevirtual #149                // Method scala/Tuple12._12:()Ljava/lang/Object;
        73: astore        14
        75: aload_0
        76: aload_3
        77: aload         4
        79: aload         5
        81: aload         6
        83: aload         7
        85: aload         8
        87: aload         9
        89: aload         10
        91: aload         11
        93: aload         12
        95: aload         13
        97: aload         14
        99: invokeinterface #96,  13          // InterfaceMethod apply:(Ljava/lang/Object;Ljava/lang/Object;Ljava/lang/Object;Ljava/lang/Object;Ljava/lang/Object;Ljava/lang/Object;Ljava/lang/Object;Ljava/lang/Object;Ljava/lang/Object;Ljava/lang/Object;Ljava/lang/Object;Ljava/lang/Object;)Ljava/lang/Object;
       104: astore_2
       105: goto          117
       108: new           #151                // class scala/MatchError
       111: dup
       112: aconst_null
       113: invokespecial #155                // Method scala/MatchError."<init>":(Ljava/lang/Object;)V
       116: athrow
       117: aload_2
       118: areturn
      StackMapTable: number_of_entries = 2
        frame_type = 251 /* same_frame_extended */
          offset_delta = 108
        frame_type = 255 /* full_frame */
          offset_delta = 8
          locals = [ class scala/Function12, class scala/Tuple12, class java/lang/Object, class java/lang/Object, class java/lang/Object, class java/lang/Object, class java/lang/Object, class java/lang/Object, class java/lang/Object, class java/lang/Object, class java/lang/Object, class java/lang/Object, class java/lang/Object, class java/lang/Object, class java/lang/Object ]
          stack = []
      LineNumberTable:
        line 40: 0
        line 39: 108
      LocalVariableTable:
        Start  Length  Slot  Name   Signature
            9      99     3    x1   Ljava/lang/Object;
           15      93     4    x2   Ljava/lang/Object;
           21      87     5    x3   Ljava/lang/Object;
           27      81     6    x4   Ljava/lang/Object;
           33      75     7    x5   Ljava/lang/Object;
           39      69     8    x6   Ljava/lang/Object;
           45      63     9    x7   Ljava/lang/Object;
           51      57    10    x8   Ljava/lang/Object;
           57      51    11    x9   Ljava/lang/Object;
           63      45    12   x10   Ljava/lang/Object;
           69      39    13   x11   Ljava/lang/Object;
           75      33    14   x12   Ljava/lang/Object;
            0     119     0 $this   Lscala/Function12;
            0     119     1  x0$1   Lscala/Tuple12;
    MethodParameters:
      Name                           Flags
      $this                          final synthetic
      x0$1                           final

  public static void $init$(scala.Function12);
    descriptor: (Lscala/Function12;)V
    flags: (0x0009) ACC_PUBLIC, ACC_STATIC
    Code:
      stack=0, locals=1, args_size=1
         0: return
      LineNumberTable:
        line 21: 0
      LocalVariableTable:
        Start  Length  Slot  Name   Signature
            0       1     0 $this   Lscala/Function12;
    MethodParameters:
      Name                           Flags
      $this                          final synthetic

  private static java.lang.Object $deserializeLambda$(java.lang.invoke.SerializedLambda);
    descriptor: (Ljava/lang/invoke/SerializedLambda;)Ljava/lang/Object;
    flags: (0x100a) ACC_PRIVATE, ACC_STATIC, ACC_SYNTHETIC
    Code:
      stack=1, locals=1, args_size=1
         0: aload_0
         1: invokedynamic #170,  0            // InvokeDynamic #3:lambdaDeserialize:(Ljava/lang/invoke/SerializedLambda;)Ljava/lang/Object;
         6: areturn
}
InnerClasses:
  public static final #14= #11 of #13;    // Lookup=class java/lang/invoke/MethodHandles$Lookup of class java/lang/invoke/MethodHandles
Signature: #3                           // <T1:Ljava/lang/Object;T2:Ljava/lang/Object;T3:Ljava/lang/Object;T4:Ljava/lang/Object;T5:Ljava/lang/Object;T6:Ljava/lang/Object;T7:Ljava/lang/Object;T8:Ljava/lang/Object;T9:Ljava/lang/Object;T10:Ljava/lang/Object;T11:Ljava/lang/Object;T12:Ljava/lang/Object;R:Ljava/lang/Object;>Ljava/lang/Object;
SourceFile: "Function12.scala"
RuntimeVisibleAnnotations:
  0: #7(#8=s#9)
    scala.reflect.ScalaSignature(
      bytes="\u0006\u0005\u0005Maa\u0002\u0004\b!\u0003\r\tA\u0003\u0005\u0006!\u0001!\t!\u0005\u0005\u0006+\u00011\tA\u0006\u0005\u0006=\u0002!\ta\u0018\u0005\u0006k\u0002!\tA\u001e\u0005\u0006y\u0002!\t% \u0002\u000b\rVt7\r^5p]F\u0012$\"\u0001\u0005\u0002\u000bM\u001c\u0017\r\\1\u0004\u0001Uq1\"\n\u00160ier4\tS\'S/rK2C\u0001\u0001\r!\tia\"D\u0001\b\u0013\tyqA\u0001\u0004B]f\u0014VMZ\u0001\u0007I%t\u0017\u000e\u001e\u0013\u0015\u0003I\u0001\"!D\n\n\u0005Q9!\u0001B+oSR\fQ!\u00199qYf$Rb\u0006\u0012(YE24\bQ#K\u001fRK\u0006C\u0001\r\u001a\u0019\u0001!aA\u0007\u0001\u0005\u0006\u0004Y\"!\u0001*\u0012\u0005qy\u0002CA\u0007\u001e\u0013\tqrAA\u0004O_RD\u0017N\\4\u0011\u00055\u0001\u0013BA\u0011\b\u0005\r\te.\u001f\u0005\u0006G\t\u0001\r\u0001J\u0001\u0003mF\u0002\"\u0001G\u0013\u0005\r\u0019\u0002\u0001R1\u0001\u001c\u0005\t!\u0016\u0007C\u0003)\u0005\u0001\u0007\u0011&\u0001\u0002weA\u0011\u0001D\u000b\u0003\u0007W\u0001A)\u0019A\u000e\u0003\u0005Q\u0013\u0004\"B\u0017\u0003\u0001\u0004q\u0013A\u0001<4!\tAr\u0006\u0002\u00041\u0001!\u0015\ra\u0007\u0002\u0003)NBQA\r\u0002A\u0002M\n!A\u001e\u001b\u0011\u0005a!DAB\u001b\u0001\u0011\u000b\u00071D\u0001\u0002Ui!)qG\u0001a\u0001q\u0005\u0011a/\u000e\t\u00031e\"aA\u000f\u0001\t\u0006\u0004Y\"A\u0001+6\u0011\u0015a$\u00011\u0001>\u0003\t1h\u0007\u0005\u0002\u0019}\u00111q\b\u0001EC\u0002m\u0011!\u0001\u0016\u001c\t\u000b\u0005\u0013\u0001\u0019\u0001\"\u0002\u0005Y<\u0004C\u0001\rD\t\u0019!\u0005\u0001#b\u00017\t\u0011Ak\u000e\u0005\u0006\r\n\u0001\raR\u0001\u0003mb\u0002\"\u0001\u0007%\u0005\r%\u0003\u0001R1\u0001\u001c\u0005\t!\u0006\bC\u0003L\u0005\u0001\u0007A*\u0001\u0002wsA\u0011\u0001$\u0014\u0003\u0007\u001d\u0002A)\u0019A\u000e\u0003\u0005QK\u0004\"\u0002)\u0003\u0001\u0004\t\u0016a\u0001<2aA\u0011\u0001D\u0015\u0003\u0007\'\u0002A)\u0019A\u000e\u0003\u0007Q\u000b\u0004\u0007C\u0003V\u0005\u0001\u0007a+A\u0002wcE\u0002\"\u0001G,\u0005\ra\u0003\u0001R1\u0001\u001c\u0005\r!\u0016\'\r\u0005\u00065\n\u0001\raW\u0001\u0004mF\u0012\u0004C\u0001\r]\t\u0019i\u0006\u0001#b\u00017\t\u0019A+\r\u001a\u0002\u000f\r,(O]5fIV\t\u0001\r\u0005\u0003\u000eC\u0012\u001a\u0017B\u00012\b\u0005%1UO\\2uS>t\u0017\u0007\u0005\u0003\u000eC&\"\u0007\u0003B\u0007b]\u0015\u0004B!D14MB!Q\"\u0019\u001dh!\u0011i\u0011-\u00105\u0011\t5\t\')\u001b\t\u0005\u001b\u0005<%\u000e\u0005\u0003\u000eC2[\u0007\u0003B\u0007b#2\u0004B!D1W[B!Q\"Y.\u0018Q\t\u0019q\u000e\u0005\u0002qg6\t\u0011O\u0003\u0002s\u000f\u0005Q\u0011M\u001c8pi\u0006$\u0018n\u001c8\n\u0005Q\f(!D;ogB,7-[1mSj,G-\u0001\u0004ukBdW\rZ\u000b\u0002oB!Q\"\u0019=\u0018!9i\u0011\u0010J\u0015/gaj$i\u0012\'R-nK!A_\u0004\u0003\u000fQ+\b\u000f\\32e!\u0012Aa\\\u0001\ti>\u001cFO]5oOR\ta\u0010E\u0002\u0000\u0003\u001bqA!!\u0001\u0002\nA\u0019\u00111A\u0004\u000e\u0005\u0005\u0015!bAA\u0004\u0013\u00051AH]8pizJ1!a\u0003\b\u0003\u0019\u0001&/\u001a3fM&!\u0011qBA\t\u0005\u0019\u0019FO]5oO*\u0019\u00111B\u0004"
    )
BootstrapMethods:
  0: #56 REF_invokeStatic java/lang/invoke/LambdaMetafactory.altMetafactory:(Ljava/lang/invoke/MethodHandles$Lookup;Ljava/lang/String;Ljava/lang/invoke/MethodType;[Ljava/lang/Object;)Ljava/lang/invoke/CallSite;
    Method arguments:
      #40 (Ljava/lang/Object;)Ljava/lang/Object;
      #45 REF_invokeStatic scala/Function12.$anonfun$curried$1:(Lscala/Function12;Ljava/lang/Object;)Lscala/Function1;
      #47 (Ljava/lang/Object;)Lscala/Function1;
      #48 5
      #49 1
      #47 (Ljava/lang/Object;)Lscala/Function1;
  1: #56 REF_invokeStatic java/lang/invoke/LambdaMetafactory.altMetafactory:(Ljava/lang/invoke/MethodHandles$Lookup;Ljava/lang/String;Ljava/lang/invoke/MethodType;[Ljava/lang/Object;)Ljava/lang/invoke/CallSite;
    Method arguments:
      #40 (Ljava/lang/Object;)Ljava/lang/Object;
      #69 REF_invokeStatic scala/Function12.$anonfun$tupled$1:(Lscala/Function12;Lscala/Tuple12;)Ljava/lang/Object;
      #71 (Lscala/Tuple12;)Ljava/lang/Object;
      #48 5
      #49 1
      #71 (Lscala/Tuple12;)Ljava/lang/Object;
  2: #56 REF_invokeStatic java/lang/invoke/LambdaMetafactory.altMetafactory:(Ljava/lang/invoke/MethodHandles$Lookup;Ljava/lang/String;Ljava/lang/invoke/MethodType;[Ljava/lang/Object;)Ljava/lang/invoke/CallSite;
    Method arguments:
      #100 (Ljava/lang/Object;Ljava/lang/Object;Ljava/lang/Object;Ljava/lang/Object;Ljava/lang/Object;Ljava/lang/Object;Ljava/lang/Object;Ljava/lang/Object;Ljava/lang/Object;Ljava/lang/Object;Ljava/lang/Object;)Ljava/lang/Object;
      #103 REF_invokeStatic scala/Function12.$anonfun$curried$2:(Lscala/Function12;Ljava/lang/Object;Ljava/lang/Object;Ljava/lang/Object;Ljava/lang/Object;Ljava/lang/Object;Ljava/lang/Object;Ljava/lang/Object;Ljava/lang/Object;Ljava/lang/Object;Ljava/lang/Object;Ljava/lang/Object;Ljava/lang/Object;)Ljava/lang/Object;
      #100 (Ljava/lang/Object;Ljava/lang/Object;Ljava/lang/Object;Ljava/lang/Object;Ljava/lang/Object;Ljava/lang/Object;Ljava/lang/Object;Ljava/lang/Object;Ljava/lang/Object;Ljava/lang/Object;Ljava/lang/Object;)Ljava/lang/Object;
      #49 1
  3: #167 REF_invokeStatic scala/runtime/LambdaDeserialize.bootstrap:(Ljava/lang/invoke/MethodHandles$Lookup;Ljava/lang/String;Ljava/lang/invoke/MethodType;[Ljava/lang/invoke/MethodHandle;)Ljava/lang/invoke/CallSite;
    Method arguments:
      #45 REF_invokeStatic scala/Function12.$anonfun$curried$1:(Lscala/Function12;Ljava/lang/Object;)Lscala/Function1;
      #103 REF_invokeStatic scala/Function12.$anonfun$curried$2:(Lscala/Function12;Ljava/lang/Object;Ljava/lang/Object;Ljava/lang/Object;Ljava/lang/Object;Ljava/lang/Object;Ljava/lang/Object;Ljava/lang/Object;Ljava/lang/Object;Ljava/lang/Object;Ljava/lang/Object;Ljava/lang/Object;Ljava/lang/Object;)Ljava/lang/Object;
      #69 REF_invokeStatic scala/Function12.$anonfun$tupled$1:(Lscala/Function12;Lscala/Tuple12;)Ljava/lang/Object;
  ScalaInlineInfo: length = 0x3F (unknown attribute)
   01 04 00 0F 00 10 00 0B 00 29 00 2A 01 00 51 00
   52 01 00 41 00 42 01 00 9D 00 9E 01 00 0F 00 10
   00 00 21 00 22 00 00 1E 00 1F 01 00 4B 00 4C 00
   00 49 00 4A 01 00 3D 00 22 00 00 3C 00 1F 01
  ScalaSig: length = 0x3 (unknown attribute)
   05 02 00
