Classfile /Users/mw/Projects/slang-braindump/.jar/jar11/assemble/slang-braindump/assemble/content/scala/Long$.class
  Last modified May 29, 2022; size 1254 bytes
  SHA-256 checksum 8a7f92129b6c4de8e69e3e3d9d9cab64d223a480e1965eb41f0d6b25523a00b5
  Compiled from "Long.scala"
public final class scala.Long$ implements scala.AnyValCompanion
  minor version: 0
  major version: 52
  flags: (0x0031) ACC_PUBLIC, ACC_FINAL, ACC_SUPER
  this_class: #2                          // scala/Long$
  super_class: #4                         // java/lang/Object
  interfaces: 1, fields: 1, methods: 9, attributes: 3
Constant pool:
   #1 = Utf8               scala/Long$
   #2 = Class              #1             // scala/Long$
   #3 = Utf8               java/lang/Object
   #4 = Class              #3             // java/lang/Object
   #5 = Utf8               scala/AnyValCompanion
   #6 = Class              #5             // scala/AnyValCompanion
   #7 = Utf8               Long.scala
   #8 = Utf8               MODULE$
   #9 = Utf8               Lscala/Long$;
  #10 = Utf8               <clinit>
  #11 = Utf8               ()V
  #12 = Utf8               <init>
  #13 = NameAndType        #12:#11        // "<init>":()V
  #14 = Methodref          #2.#13         // scala/Long$."<init>":()V
  #15 = NameAndType        #8:#9          // MODULE$:Lscala/Long$;
  #16 = Fieldref           #2.#15         // scala/Long$.MODULE$:Lscala/Long$;
  #17 = Utf8               MinValue
  #18 = Utf8               ()J
  #19 = Long               -9223372036854775808l
  #21 = Utf8               this
  #22 = Utf8               MaxValue
  #23 = Long               9223372036854775807l
  #25 = Utf8               box
  #26 = Utf8               (J)Ljava/lang/Long;
  #27 = Utf8               x
  #28 = Utf8               scala/NotImplementedError
  #29 = Class              #28            // scala/NotImplementedError
  #30 = Methodref          #29.#13        // scala/NotImplementedError."<init>":()V
  #31 = Utf8               J
  #32 = Utf8               unbox
  #33 = Utf8               (Ljava/lang/Object;)J
  #34 = Utf8               Ljava/lang/Object;
  #35 = Utf8               toString
  #36 = Utf8               ()Ljava/lang/String;
  #37 = Utf8               object scala.Long
  #38 = String             #37            // object scala.Long
  #39 = Utf8               long2float
  #40 = Utf8               (J)F
  #41 = Utf8               long2double
  #42 = Utf8               (J)D
  #43 = Methodref          #4.#13         // java/lang/Object."<init>":()V
  #44 = Utf8               Code
  #45 = Utf8               LineNumberTable
  #46 = Utf8               LocalVariableTable
  #47 = Utf8               MethodParameters
  #48 = Utf8               Deprecated
  #49 = Utf8               SourceFile
  #50 = Utf8               ScalaInlineInfo
  #51 = Utf8               Scala
{
  public static final scala.Long$ MODULE$;
    descriptor: Lscala/Long$;
    flags: (0x0019) ACC_PUBLIC, ACC_STATIC, ACC_FINAL

  public static {};
    descriptor: ()V
    flags: (0x0009) ACC_PUBLIC, ACC_STATIC
    Code:
      stack=2, locals=0, args_size=0
         0: new           #2                  // class scala/Long$
         3: dup
         4: invokespecial #14                 // Method "<init>":()V
         7: putstatic     #16                 // Field MODULE$:Lscala/Long$;
        10: return
      LineNumberTable:
        line 446: 0

  public final long MinValue();
    descriptor: ()J
    flags: (0x0011) ACC_PUBLIC, ACC_FINAL
    Code:
      stack=2, locals=1, args_size=1
         0: ldc2_w        #19                 // long -9223372036854775808l
         3: lreturn
      LocalVariableTable:
        Start  Length  Slot  Name   Signature
            0       4     0  this   Lscala/Long$;

  public final long MaxValue();
    descriptor: ()J
    flags: (0x0011) ACC_PUBLIC, ACC_FINAL
    Code:
      stack=2, locals=1, args_size=1
         0: ldc2_w        #23                 // long 9223372036854775807l
         3: lreturn
      LocalVariableTable:
        Start  Length  Slot  Name   Signature
            0       4     0  this   Lscala/Long$;

  public java.lang.Long box(long);
    descriptor: (J)Ljava/lang/Long;
    flags: (0x0001) ACC_PUBLIC
    Code:
      stack=2, locals=3, args_size=2
         0: new           #29                 // class scala/NotImplementedError
         3: dup
         4: invokespecial #30                 // Method scala/NotImplementedError."<init>":()V
         7: athrow
      LineNumberTable:
        line 460: 0
      LocalVariableTable:
        Start  Length  Slot  Name   Signature
            0       8     0  this   Lscala/Long$;
            0       8     1     x   J
    MethodParameters:
      Name                           Flags
      x                              final

  public long unbox(java.lang.Object);
    descriptor: (Ljava/lang/Object;)J
    flags: (0x0001) ACC_PUBLIC
    Code:
      stack=2, locals=2, args_size=2
         0: new           #29                 // class scala/NotImplementedError
         3: dup
         4: invokespecial #30                 // Method scala/NotImplementedError."<init>":()V
         7: athrow
      LineNumberTable:
        line 472: 0
      LocalVariableTable:
        Start  Length  Slot  Name   Signature
            0       8     0  this   Lscala/Long$;
            0       8     1     x   Ljava/lang/Object;
    MethodParameters:
      Name                           Flags
      x                              final

  public java.lang.String toString();
    descriptor: ()Ljava/lang/String;
    flags: (0x0001) ACC_PUBLIC
    Code:
      stack=1, locals=1, args_size=1
         0: ldc           #38                 // String object scala.Long
         2: areturn
      LineNumberTable:
        line 475: 0
      LocalVariableTable:
        Start  Length  Slot  Name   Signature
            0       3     0  this   Lscala/Long$;

  public float long2float(long);
    descriptor: (J)F
    flags: (0x0001) ACC_PUBLIC
    Code:
      stack=2, locals=3, args_size=2
         0: lload_1
         1: l2f
         2: freturn
      LineNumberTable:
        line 479: 0
      LocalVariableTable:
        Start  Length  Slot  Name   Signature
            0       3     0  this   Lscala/Long$;
            0       3     1     x   J
    Deprecated: true
    MethodParameters:
      Name                           Flags
      x                              final

  public double long2double(long);
    descriptor: (J)D
    flags: (0x0001) ACC_PUBLIC
    Code:
      stack=2, locals=3, args_size=2
         0: lload_1
         1: l2d
         2: dreturn
      LineNumberTable:
        line 481: 0
      LocalVariableTable:
        Start  Length  Slot  Name   Signature
            0       3     0  this   Lscala/Long$;
            0       3     1     x   J
    Deprecated: true
    MethodParameters:
      Name                           Flags
      x                              final

  private scala.Long$();
    descriptor: ()V
    flags: (0x0002) ACC_PRIVATE
    Code:
      stack=1, locals=1, args_size=1
         0: aload_0
         1: invokespecial #43                 // Method java/lang/Object."<init>":()V
         4: return
      LineNumberTable:
        line 446: 0
      LocalVariableTable:
        Start  Length  Slot  Name   Signature
            0       5     0  this   Lscala/Long$;
}
SourceFile: "Long.scala"
  ScalaInlineInfo: length = 0x2C (unknown attribute)
   01 01 00 08 00 0C 00 0B 01 00 16 00 12 01 00 11
   00 12 01 00 19 00 1A 01 00 29 00 2A 01 00 27 00
   28 01 00 23 00 24 01 00 20 00 21 01
  Scala: length = 0x0 (unknown attribute)

