Classfile /Users/mw/Projects/slang-braindump/.jar/jar11/assemble/slang-braindump/assemble/content/scala/Option$.class
  Last modified May 29, 2022; size 2256 bytes
  SHA-256 checksum 089a71cf88b054a89687faadb91128a574f1ade48a457e063e77896a1b15435e
  Compiled from "Option.scala"
public final class scala.Option$ implements java.io.Serializable
  minor version: 0
  major version: 52
  flags: (0x0031) ACC_PUBLIC, ACC_FINAL, ACC_SUPER
  this_class: #2                          // scala/Option$
  super_class: #4                         // java/lang/Object
  interfaces: 1, fields: 1, methods: 8, attributes: 4
Constant pool:
   #1 = Utf8               scala/Option$
   #2 = Class              #1             // scala/Option$
   #3 = Utf8               java/lang/Object
   #4 = Class              #3             // java/lang/Object
   #5 = Utf8               java/io/Serializable
   #6 = Class              #5             // java/io/Serializable
   #7 = Utf8               Option.scala
   #8 = Utf8               scala/collection/Iterable$$anon$1
   #9 = Class              #8             // scala/collection/Iterable$$anon$1
  #10 = Utf8               MODULE$
  #11 = Utf8               Lscala/Option$;
  #12 = Utf8               <clinit>
  #13 = Utf8               ()V
  #14 = Utf8               <init>
  #15 = NameAndType        #14:#13        // "<init>":()V
  #16 = Methodref          #2.#15         // scala/Option$."<init>":()V
  #17 = NameAndType        #10:#11        // MODULE$:Lscala/Option$;
  #18 = Fieldref           #2.#17         // scala/Option$.MODULE$:Lscala/Option$;
  #19 = Utf8               option2Iterable
  #20 = Utf8               (Lscala/Option;)Lscala/collection/Iterable;
  #21 = Utf8               <A:Ljava/lang/Object;>(Lscala/Option<TA;>;)Lscala/collection/Iterable<TA;>;
  #22 = Utf8               xo
  #23 = Utf8               scala/Option
  #24 = Class              #23            // scala/Option
  #25 = Utf8               isEmpty
  #26 = Utf8               ()Z
  #27 = NameAndType        #25:#26        // isEmpty:()Z
  #28 = Methodref          #24.#27        // scala/Option.isEmpty:()Z
  #29 = Utf8               scala/package$
  #30 = Class              #29            // scala/package$
  #31 = Utf8               Lscala/package$;
  #32 = NameAndType        #10:#31        // MODULE$:Lscala/package$;
  #33 = Fieldref           #30.#32        // scala/package$.MODULE$:Lscala/package$;
  #34 = Utf8               Iterable
  #35 = Utf8               ()Lscala/collection/Iterable$;
  #36 = NameAndType        #34:#35        // Iterable:()Lscala/collection/Iterable$;
  #37 = Methodref          #30.#36        // scala/package$.Iterable:()Lscala/collection/Iterable$;
  #38 = Utf8               scala/collection/Iterable$
  #39 = Class              #38            // scala/collection/Iterable$
  #40 = Utf8               empty
  #41 = Utf8               ()Ljava/lang/Object;
  #42 = NameAndType        #40:#41        // empty:()Ljava/lang/Object;
  #43 = Methodref          #39.#42        // scala/collection/Iterable$.empty:()Ljava/lang/Object;
  #44 = Utf8               scala/collection/Iterable
  #45 = Class              #44            // scala/collection/Iterable
  #46 = Utf8               get
  #47 = NameAndType        #46:#41        // get:()Ljava/lang/Object;
  #48 = Methodref          #24.#47        // scala/Option.get:()Ljava/lang/Object;
  #49 = Utf8               (Ljava/lang/Object;)V
  #50 = NameAndType        #14:#49        // "<init>":(Ljava/lang/Object;)V
  #51 = Methodref          #9.#50         // scala/collection/Iterable$$anon$1."<init>":(Ljava/lang/Object;)V
  #52 = Utf8               this
  #53 = Utf8               Lscala/Option;
  #54 = Utf8               single_a
  #55 = Utf8               Ljava/lang/Object;
  #56 = Utf8               apply
  #57 = Utf8               (Ljava/lang/Object;)Lscala/Option;
  #58 = Utf8               <A:Ljava/lang/Object;>(TA;)Lscala/Option<TA;>;
  #59 = Utf8               x
  #60 = Utf8               scala/None$
  #61 = Class              #60            // scala/None$
  #62 = Utf8               Lscala/None$;
  #63 = NameAndType        #10:#62        // MODULE$:Lscala/None$;
  #64 = Fieldref           #61.#63        // scala/None$.MODULE$:Lscala/None$;
  #65 = Utf8               scala/Some
  #66 = Class              #65            // scala/Some
  #67 = Methodref          #66.#50        // scala/Some."<init>":(Ljava/lang/Object;)V
  #68 = Utf8               ()Lscala/Option;
  #69 = Utf8               <A:Ljava/lang/Object;>()Lscala/Option<TA;>;
  #70 = Utf8               when
  #71 = Utf8               (ZLscala/Function0;)Lscala/Option;
  #72 = Utf8               <A:Ljava/lang/Object;>(ZLscala/Function0<TA;>;)Lscala/Option<TA;>;
  #73 = Utf8               cond
  #74 = Utf8               a
  #75 = Utf8               scala/Function0
  #76 = Class              #75            // scala/Function0
  #77 = NameAndType        #56:#41        // apply:()Ljava/lang/Object;
  #78 = InterfaceMethodref #76.#77        // scala/Function0.apply:()Ljava/lang/Object;
  #79 = Utf8               Z
  #80 = Utf8               Lscala/Function0;
  #81 = Utf8               unless
  #82 = Utf8               writeReplace
  #83 = Utf8               scala/runtime/ModuleSerializationProxy
  #84 = Class              #83            // scala/runtime/ModuleSerializationProxy
  #85 = Utf8               (Ljava/lang/Class;)V
  #86 = NameAndType        #14:#85        // "<init>":(Ljava/lang/Class;)V
  #87 = Methodref          #84.#86        // scala/runtime/ModuleSerializationProxy."<init>":(Ljava/lang/Class;)V
  #88 = Methodref          #4.#15         // java/lang/Object."<init>":()V
  #89 = Utf8               Code
  #90 = Utf8               LineNumberTable
  #91 = Utf8               StackMapTable
  #92 = Utf8               LocalVariableTable
  #93 = Utf8               Signature
  #94 = Utf8               MethodParameters
  #95 = Utf8               InnerClasses
  #96 = Utf8               SourceFile
  #97 = Utf8               ScalaInlineInfo
  #98 = Utf8               Scala
{
  public static final scala.Option$ MODULE$;
    descriptor: Lscala/Option$;
    flags: (0x0019) ACC_PUBLIC, ACC_STATIC, ACC_FINAL

  public static {};
    descriptor: ()V
    flags: (0x0009) ACC_PUBLIC, ACC_STATIC
    Code:
      stack=2, locals=0, args_size=0
         0: new           #2                  // class scala/Option$
         3: dup
         4: invokespecial #16                 // Method "<init>":()V
         7: putstatic     #18                 // Field MODULE$:Lscala/Option$;
        10: return
      LineNumberTable:
        line 15: 0

  public <A extends java.lang.Object> scala.collection.Iterable<A> option2Iterable(scala.Option<A>);
    descriptor: (Lscala/Option;)Lscala/collection/Iterable;
    flags: (0x0001) ACC_PUBLIC
    Code:
      stack=3, locals=3, args_size=2
         0: aload_1
         1: invokevirtual #28                 // Method scala/Option.isEmpty:()Z
         4: ifeq          20
         7: getstatic     #33                 // Field scala/package$.MODULE$:Lscala/package$;
        10: invokevirtual #37                 // Method scala/package$.Iterable:()Lscala/collection/Iterable$;
        13: invokevirtual #43                 // Method scala/collection/Iterable$.empty:()Ljava/lang/Object;
        16: checkcast     #45                 // class scala/collection/Iterable
        19: areturn
        20: getstatic     #33                 // Field scala/package$.MODULE$:Lscala/package$;
        23: invokevirtual #37                 // Method scala/package$.Iterable:()Lscala/collection/Iterable$;
        26: aload_1
        27: invokevirtual #48                 // Method scala/Option.get:()Ljava/lang/Object;
        30: astore_2
        31: ifnonnull     36
        34: aconst_null
        35: athrow
        36: new           #9                  // class scala/collection/Iterable$$anon$1
        39: dup
        40: aload_2
        41: invokespecial #51                 // Method scala/collection/Iterable$$anon$1."<init>":(Ljava/lang/Object;)V
        44: areturn
      StackMapTable: number_of_entries = 2
        frame_type = 20 /* same */
        frame_type = 252 /* append */
          offset_delta = 15
          locals = [ class java/lang/Object ]
      LineNumberTable:
        line 21: 0
      LocalVariableTable:
        Start  Length  Slot  Name   Signature
            0      45     0  this   Lscala/Option$;
            0      45     1    xo   Lscala/Option;
           36       8     2 single_a   Ljava/lang/Object;
    Signature: #21                          // <A:Ljava/lang/Object;>(Lscala/Option<TA;>;)Lscala/collection/Iterable<TA;>;
    MethodParameters:
      Name                           Flags
      xo                             final

  public <A extends java.lang.Object> scala.Option<A> apply(A);
    descriptor: (Ljava/lang/Object;)Lscala/Option;
    flags: (0x0001) ACC_PUBLIC
    Code:
      stack=3, locals=2, args_size=2
         0: aload_1
         1: ifnonnull     8
         4: getstatic     #64                 // Field scala/None$.MODULE$:Lscala/None$;
         7: areturn
         8: new           #66                 // class scala/Some
        11: dup
        12: aload_1
        13: invokespecial #67                 // Method scala/Some."<init>":(Ljava/lang/Object;)V
        16: areturn
      StackMapTable: number_of_entries = 1
        frame_type = 8 /* same */
      LineNumberTable:
        line 29: 0
      LocalVariableTable:
        Start  Length  Slot  Name   Signature
            0      17     0  this   Lscala/Option$;
            0      17     1     x   Ljava/lang/Object;
    Signature: #58                          // <A:Ljava/lang/Object;>(TA;)Lscala/Option<TA;>;
    MethodParameters:
      Name                           Flags
      x                              final

  public <A extends java.lang.Object> scala.Option<A> empty();
    descriptor: ()Lscala/Option;
    flags: (0x0001) ACC_PUBLIC
    Code:
      stack=1, locals=1, args_size=1
         0: getstatic     #64                 // Field scala/None$.MODULE$:Lscala/None$;
         3: areturn
      LineNumberTable:
        line 34: 0
      LocalVariableTable:
        Start  Length  Slot  Name   Signature
            0       4     0  this   Lscala/Option$;
    Signature: #69                          // <A:Ljava/lang/Object;>()Lscala/Option<TA;>;

  public <A extends java.lang.Object> scala.Option<A> when(boolean, scala.Function0<A>);
    descriptor: (ZLscala/Function0;)Lscala/Option;
    flags: (0x0001) ACC_PUBLIC
    Code:
      stack=3, locals=3, args_size=3
         0: iload_1
         1: ifeq          18
         4: new           #66                 // class scala/Some
         7: dup
         8: aload_2
         9: invokeinterface #78,  1           // InterfaceMethod scala/Function0.apply:()Ljava/lang/Object;
        14: invokespecial #67                 // Method scala/Some."<init>":(Ljava/lang/Object;)V
        17: areturn
        18: getstatic     #64                 // Field scala/None$.MODULE$:Lscala/None$;
        21: areturn
      StackMapTable: number_of_entries = 1
        frame_type = 18 /* same */
      LineNumberTable:
        line 41: 0
      LocalVariableTable:
        Start  Length  Slot  Name   Signature
            0      22     0  this   Lscala/Option$;
            0      22     1  cond   Z
            0      22     2     a   Lscala/Function0;
    Signature: #72                          // <A:Ljava/lang/Object;>(ZLscala/Function0<TA;>;)Lscala/Option<TA;>;
    MethodParameters:
      Name                           Flags
      cond                           final
      a                              final

  public <A extends java.lang.Object> scala.Option<A> unless(boolean, scala.Function0<A>);
    descriptor: (ZLscala/Function0;)Lscala/Option;
    flags: (0x0001) ACC_PUBLIC
    Code:
      stack=3, locals=3, args_size=3
         0: iload_1
         1: ifne          8
         4: iconst_1
         5: goto          9
         8: iconst_0
         9: ifeq          26
        12: new           #66                 // class scala/Some
        15: dup
        16: aload_2
        17: invokeinterface #78,  1           // InterfaceMethod scala/Function0.apply:()Ljava/lang/Object;
        22: invokespecial #67                 // Method scala/Some."<init>":(Ljava/lang/Object;)V
        25: areturn
        26: getstatic     #64                 // Field scala/None$.MODULE$:Lscala/None$;
        29: areturn
      StackMapTable: number_of_entries = 3
        frame_type = 8 /* same */
        frame_type = 64 /* same_locals_1_stack_item */
          stack = [ int ]
        frame_type = 16 /* same */
      LineNumberTable:
        line 47: 0
        line 41: 9
        line 47: 29
      LocalVariableTable:
        Start  Length  Slot  Name   Signature
            0      30     0  this   Lscala/Option$;
            0      30     1  cond   Z
            0      30     2     a   Lscala/Function0;
    Signature: #72                          // <A:Ljava/lang/Object;>(ZLscala/Function0<TA;>;)Lscala/Option<TA;>;
    MethodParameters:
      Name                           Flags
      cond                           final
      a                              final

  private java.lang.Object writeReplace();
    descriptor: ()Ljava/lang/Object;
    flags: (0x0002) ACC_PRIVATE
    Code:
      stack=3, locals=1, args_size=1
         0: new           #84                 // class scala/runtime/ModuleSerializationProxy
         3: dup
         4: ldc           #2                  // class scala/Option$
         6: invokespecial #87                 // Method scala/runtime/ModuleSerializationProxy."<init>":(Ljava/lang/Class;)V
         9: areturn
      LineNumberTable:
        line 15: 0
      LocalVariableTable:
        Start  Length  Slot  Name   Signature
            0      10     0  this   Lscala/Option$;

  private scala.Option$();
    descriptor: ()V
    flags: (0x0002) ACC_PRIVATE
    Code:
      stack=1, locals=1, args_size=1
         0: aload_0
         1: invokespecial #88                 // Method java/lang/Object."<init>":()V
         4: return
      LineNumberTable:
        line 15: 0
      LocalVariableTable:
        Start  Length  Slot  Name   Signature
            0       5     0  this   Lscala/Option$;
}
InnerClasses:
  public final #9;                        // class scala/collection/Iterable$$anon$1
SourceFile: "Option.scala"
  ScalaInlineInfo: length = 0x27 (unknown attribute)
   01 01 00 07 00 0E 00 0D 01 00 38 00 39 01 00 28
   00 44 01 00 13 00 14 01 00 51 00 47 05 00 46 00
   47 01 00 52 00 29 01
  Scala: length = 0x0 (unknown attribute)

