Classfile /Users/mw/Projects/slang-braindump/.jar/jar11/assemble/slang-braindump/assemble/content/scala/Predef$StringFormat$.class
  Last modified May 29, 2022; size 1907 bytes
  SHA-256 checksum 925afdc202c7cac5ece0ef0d37cfb6b98ecca24dd09f789d6a3556a95991b722
  Compiled from "Predef.scala"
public class scala.Predef$StringFormat$
  minor version: 0
  major version: 52
  flags: (0x0021) ACC_PUBLIC, ACC_SUPER
  this_class: #2                          // scala/Predef$StringFormat$
  super_class: #4                         // java/lang/Object
  interfaces: 0, fields: 1, methods: 5, attributes: 4
Constant pool:
   #1 = Utf8               scala/Predef$StringFormat$
   #2 = Class              #1             // scala/Predef$StringFormat$
   #3 = Utf8               java/lang/Object
   #4 = Class              #3             // java/lang/Object
   #5 = Utf8               Predef.scala
   #6 = Utf8               scala/Predef$StringFormat
   #7 = Class              #6             // scala/Predef$StringFormat
   #8 = Utf8               scala/Predef
   #9 = Class              #8             // scala/Predef
  #10 = Utf8               StringFormat
  #11 = Utf8               StringFormat$
  #12 = Utf8               MODULE$
  #13 = Utf8               Lscala/Predef$StringFormat$;
  #14 = Utf8               <clinit>
  #15 = Utf8               ()V
  #16 = Utf8               <init>
  #17 = NameAndType        #16:#15        // "<init>":()V
  #18 = Methodref          #2.#17         // scala/Predef$StringFormat$."<init>":()V
  #19 = NameAndType        #12:#13        // MODULE$:Lscala/Predef$StringFormat$;
  #20 = Fieldref           #2.#19         // scala/Predef$StringFormat$.MODULE$:Lscala/Predef$StringFormat$;
  #21 = Utf8               formatted$extension
  #22 = Utf8               (Ljava/lang/Object;Ljava/lang/String;)Ljava/lang/String;
  #23 = Utf8               <A:Ljava/lang/Object;>(TA;Ljava/lang/String;)Ljava/lang/String;
  #24 = Utf8               $this
  #25 = Utf8               fmtstr
  #26 = Utf8               scala/collection/StringOps$
  #27 = Class              #26            // scala/collection/StringOps$
  #28 = Utf8               Lscala/collection/StringOps$;
  #29 = NameAndType        #12:#28        // MODULE$:Lscala/collection/StringOps$;
  #30 = Fieldref           #27.#29        // scala/collection/StringOps$.MODULE$:Lscala/collection/StringOps$;
  #31 = Utf8               scala/runtime/ScalaRunTime$
  #32 = Class              #31            // scala/runtime/ScalaRunTime$
  #33 = Utf8               Lscala/runtime/ScalaRunTime$;
  #34 = NameAndType        #12:#33        // MODULE$:Lscala/runtime/ScalaRunTime$;
  #35 = Fieldref           #32.#34        // scala/runtime/ScalaRunTime$.MODULE$:Lscala/runtime/ScalaRunTime$;
  #36 = Utf8               genericWrapArray
  #37 = Utf8               (Ljava/lang/Object;)Lscala/collection/immutable/ArraySeq;
  #38 = NameAndType        #36:#37        // genericWrapArray:(Ljava/lang/Object;)Lscala/collection/immutable/ArraySeq;
  #39 = Methodref          #32.#38        // scala/runtime/ScalaRunTime$.genericWrapArray:(Ljava/lang/Object;)Lscala/collection/immutable/ArraySeq;
  #40 = Utf8               format$extension
  #41 = Utf8               (Ljava/lang/String;Lscala/collection/immutable/Seq;)Ljava/lang/String;
  #42 = NameAndType        #40:#41        // format$extension:(Ljava/lang/String;Lscala/collection/immutable/Seq;)Ljava/lang/String;
  #43 = Methodref          #27.#42        // scala/collection/StringOps$.format$extension:(Ljava/lang/String;Lscala/collection/immutable/Seq;)Ljava/lang/String;
  #44 = Utf8               this
  #45 = Utf8               Ljava/lang/Object;
  #46 = Utf8               Ljava/lang/String;
  #47 = Utf8               hashCode$extension
  #48 = Utf8               (Ljava/lang/Object;)I
  #49 = Utf8               <A:Ljava/lang/Object;>(TA;)I
  #50 = Utf8               hashCode
  #51 = Utf8               ()I
  #52 = NameAndType        #50:#51        // hashCode:()I
  #53 = Methodref          #4.#52         // java/lang/Object.hashCode:()I
  #54 = Utf8               equals$extension
  #55 = Utf8               (Ljava/lang/Object;Ljava/lang/Object;)Z
  #56 = Utf8               <A:Ljava/lang/Object;>(TA;Ljava/lang/Object;)Z
  #57 = Utf8               x$1
  #58 = Utf8               scala$Predef$StringFormat$$self
  #59 = Utf8               ()Ljava/lang/Object;
  #60 = NameAndType        #58:#59        // scala$Predef$StringFormat$$self:()Ljava/lang/Object;
  #61 = Methodref          #7.#60         // scala/Predef$StringFormat.scala$Predef$StringFormat$$self:()Ljava/lang/Object;
  #62 = Utf8               scala/runtime/BoxesRunTime
  #63 = Class              #62            // scala/runtime/BoxesRunTime
  #64 = Utf8               equals
  #65 = NameAndType        #64:#55        // equals:(Ljava/lang/Object;Ljava/lang/Object;)Z
  #66 = Methodref          #63.#65        // scala/runtime/BoxesRunTime.equals:(Ljava/lang/Object;Ljava/lang/Object;)Z
  #67 = Methodref          #4.#17         // java/lang/Object."<init>":()V
  #68 = Utf8               Code
  #69 = Utf8               LineNumberTable
  #70 = Utf8               LocalVariableTable
  #71 = Utf8               Signature
  #72 = Utf8               Deprecated
  #73 = Utf8               MethodParameters
  #74 = Utf8               StackMapTable
  #75 = Utf8               InnerClasses
  #76 = Utf8               SourceFile
  #77 = Utf8               ScalaInlineInfo
  #78 = Utf8               Scala
{
  public static final scala.Predef$StringFormat$ MODULE$;
    descriptor: Lscala/Predef$StringFormat$;
    flags: (0x0019) ACC_PUBLIC, ACC_STATIC, ACC_FINAL

  public static {};
    descriptor: ()V
    flags: (0x0009) ACC_PUBLIC, ACC_STATIC
    Code:
      stack=2, locals=0, args_size=0
         0: new           #2                  // class scala/Predef$StringFormat$
         3: dup
         4: invokespecial #18                 // Method "<init>":()V
         7: putstatic     #20                 // Field MODULE$:Lscala/Predef$StringFormat$;
        10: return
      LineNumberTable:
        line 364: 0

  public final <A extends java.lang.Object> java.lang.String formatted$extension(A, java.lang.String);
    descriptor: (Ljava/lang/Object;Ljava/lang/String;)Ljava/lang/String;
    flags: (0x0011) ACC_PUBLIC, ACC_FINAL
    Code:
      stack=7, locals=3, args_size=3
         0: getstatic     #30                 // Field scala/collection/StringOps$.MODULE$:Lscala/collection/StringOps$;
         3: aload_2
         4: getstatic     #35                 // Field scala/runtime/ScalaRunTime$.MODULE$:Lscala/runtime/ScalaRunTime$;
         7: iconst_1
         8: anewarray     #4                  // class java/lang/Object
        11: dup
        12: iconst_0
        13: aload_1
        14: aastore
        15: invokevirtual #39                 // Method scala/runtime/ScalaRunTime$.genericWrapArray:(Ljava/lang/Object;)Lscala/collection/immutable/ArraySeq;
        18: invokevirtual #43                 // Method scala/collection/StringOps$.format$extension:(Ljava/lang/String;Lscala/collection/immutable/Seq;)Ljava/lang/String;
        21: areturn
      LineNumberTable:
        line 406: 3
        line 370: 3
      LocalVariableTable:
        Start  Length  Slot  Name   Signature
            0      22     0  this   Lscala/Predef$StringFormat$;
            0      22     1 $this   Ljava/lang/Object;
            0      22     2 fmtstr   Ljava/lang/String;
    Signature: #23                          // <A:Ljava/lang/Object;>(TA;Ljava/lang/String;)Ljava/lang/String;
    Deprecated: true
    MethodParameters:
      Name                           Flags
      $this                          final
      fmtstr                         final

  public final <A extends java.lang.Object> int hashCode$extension(A);
    descriptor: (Ljava/lang/Object;)I
    flags: (0x0011) ACC_PUBLIC, ACC_FINAL
    Code:
      stack=1, locals=2, args_size=2
         0: aload_1
         1: invokevirtual #53                 // Method java/lang/Object.hashCode:()I
         4: ireturn
      LineNumberTable:
        line 364: 0
      LocalVariableTable:
        Start  Length  Slot  Name   Signature
            0       5     0  this   Lscala/Predef$StringFormat$;
            0       5     1 $this   Ljava/lang/Object;
    Signature: #49                          // <A:Ljava/lang/Object;>(TA;)I
    MethodParameters:
      Name                           Flags
      $this                          final

  public final <A extends java.lang.Object> boolean equals$extension(A, java.lang.Object);
    descriptor: (Ljava/lang/Object;Ljava/lang/Object;)Z
    flags: (0x0011) ACC_PUBLIC, ACC_FINAL
    Code:
      stack=2, locals=5, args_size=3
         0: aload_2
         1: instanceof    #7                  // class scala/Predef$StringFormat
         4: ifeq          12
         7: iconst_1
         8: istore_3
         9: goto          14
        12: iconst_0
        13: istore_3
        14: iload_3
        15: ifeq          54
        18: aload_2
        19: ifnonnull     26
        22: aconst_null
        23: goto          33
        26: aload_2
        27: checkcast     #7                  // class scala/Predef$StringFormat
        30: invokevirtual #61                 // Method scala/Predef$StringFormat.scala$Predef$StringFormat$$self:()Ljava/lang/Object;
        33: astore        4
        35: aload_1
        36: aload         4
        38: invokestatic  #66                 // Method scala/runtime/BoxesRunTime.equals:(Ljava/lang/Object;Ljava/lang/Object;)Z
        41: ifeq          48
        44: iconst_1
        45: goto          49
        48: iconst_0
        49: ifeq          54
        52: iconst_1
        53: ireturn
        54: iconst_0
        55: ireturn
      StackMapTable: number_of_entries = 7
        frame_type = 12 /* same */
        frame_type = 252 /* append */
          offset_delta = 1
          locals = [ int ]
        frame_type = 11 /* same */
        frame_type = 70 /* same_locals_1_stack_item */
          stack = [ class java/lang/Object ]
        frame_type = 252 /* append */
          offset_delta = 14
          locals = [ class java/lang/Object ]
        frame_type = 64 /* same_locals_1_stack_item */
          stack = [ int ]
        frame_type = 250 /* chop */
          offset_delta = 4
      LineNumberTable:
        line 364: 0
      LocalVariableTable:
        Start  Length  Slot  Name   Signature
            0      56     0  this   Lscala/Predef$StringFormat$;
            0      56     1 $this   Ljava/lang/Object;
            0      56     2   x$1   Ljava/lang/Object;
    Signature: #56                          // <A:Ljava/lang/Object;>(TA;Ljava/lang/Object;)Z
    MethodParameters:
      Name                           Flags
      $this                          final
      x$1                            final

  public scala.Predef$StringFormat$();
    descriptor: ()V
    flags: (0x0001) ACC_PUBLIC
    Code:
      stack=1, locals=1, args_size=1
         0: aload_0
         1: invokespecial #67                 // Method java/lang/Object."<init>":()V
         4: return
      LineNumberTable:
        line 364: 0
      LocalVariableTable:
        Start  Length  Slot  Name   Signature
            0       5     0  this   Lscala/Predef$StringFormat$;
}
InnerClasses:
  public static final #10= #7 of #9;      // StringFormat=class scala/Predef$StringFormat of class scala/Predef
  public static #11= #2 of #9;            // StringFormat$=class scala/Predef$StringFormat$ of class scala/Predef
SourceFile: "Predef.scala"
  ScalaInlineInfo: length = 0x18 (unknown attribute)
   01 01 00 04 00 10 00 0F 01 00 36 00 37 01 00 15
   00 16 05 00 2F 00 30 01
  Scala: length = 0x0 (unknown attribute)

