Classfile /Users/mw/Projects/slang-braindump/.jar/jar11/assemble/slang-braindump/assemble/content/scala/Product10.class
  Last modified May 29, 2022; size 3910 bytes
  SHA-256 checksum b4e072657d387424cd268db4389c28882cb84d29b3075cca73ea46f792f93694
  Compiled from "Product10.scala"
public interface scala.Product10<T1 extends java.lang.Object, T2 extends java.lang.Object, T3 extends java.lang.Object, T4 extends java.lang.Object, T5 extends java.lang.Object, T6 extends java.lang.Object, T7 extends java.lang.Object, T8 extends java.lang.Object, T9 extends java.lang.Object, T10 extends java.lang.Object> extends scala.Product
  minor version: 0
  major version: 52
  flags: (0x0601) ACC_PUBLIC, ACC_INTERFACE, ACC_ABSTRACT
  this_class: #2                          // scala/Product10
  super_class: #5                         // java/lang/Object
  interfaces: 1, fields: 0, methods: 16, attributes: 5
Constant pool:
    #1 = Utf8               scala/Product10
    #2 = Class              #1            // scala/Product10
    #3 = Utf8               <T1:Ljava/lang/Object;T2:Ljava/lang/Object;T3:Ljava/lang/Object;T4:Ljava/lang/Object;T5:Ljava/lang/Object;T6:Ljava/lang/Object;T7:Ljava/lang/Object;T8:Ljava/lang/Object;T9:Ljava/lang/Object;T10:Ljava/lang/Object;>Ljava/lang/Object;Lscala/Product;
    #4 = Utf8               java/lang/Object
    #5 = Class              #4            // java/lang/Object
    #6 = Utf8               scala/Product
    #7 = Class              #6            // scala/Product
    #8 = Utf8               Product10.scala
    #9 = Utf8               Lscala/reflect/ScalaSignature;
   #10 = Utf8               bytes
   #11 = Utf8               \u0006\u0005\u0005-r!\u0002\n\u0014\u0011\u00031b!\u0002\r\u0014\u0011\u0003I\u0002\"B\u000f\u0002\t\u0003q\u0002\"B\u0010\u0002\t\u0003\u0001ca\u0002\r\u0014!\u0003\r\tA\n\u0005\u0006]\u0011!\ta\f\u0005\u0006g\u0011!\t\u0005\u000e\u0005\u0006q\u0011!\t%\u000f\u0005\u0006\u0011\u00121\t!\u0013\u0005\u0006%\u00121\ta\u0015\u0005\u0006/\u00121\t\u0001\u0017\u0005\u00069\u00121\t!\u0018\u0005\u0006C\u00121\tA\u0019\u0005\u0006M\u00121\ta\u001a\u0005\u0006W\u00121\t\u0001\u001c\u0005\u0006a\u00121\t!\u001d\u0005\u0006k\u00121\tA\u001e\u0005\u0006u\u00121\ta_\u0001\n!J|G-^2ucAR\u0011\u0001F\u0001\u0006g\u000e\fG.Y\u0002\u0001!\t9\u0012!D\u0001\u0014\u0005%\u0001&o\u001c3vGR\f\u0004g\u0005\u0002\u00025A\u0011qcG\u0005\u00039M\u0011a!\u00118z%\u00164\u0017A\u0002\u001fj]&$h\bF\u0001\u0017\u0003\u001d)h.\u00199qYf,R#IA\u0001\u0003\u000b\tI!!\u0004\u0002\u0012\u0005U\u0011\u0011DA\u000f\u0003C\t)\u0003F\u0002#\u0003O\u00012aF\u0012&\u0013\t!3C\u0001\u0004PaRLwN\u001c\t\u0016/\u0011y\u00181AA\u0004\u0003\u0017\ty!a\u0005\u0002\u0018\u0005m\u0011qDA\u0012+-9C*\u0016.`I&t7\u000f_?\u0014\u0007\u0011A3\u0006\u0005\u0002\u0018S%\u0011!f\u0005\u0002\u0004\u0003:L\bCA\f-\u0013\ti3CA\u0004Qe>$Wo\u0019;\u0002\r\u0011Jg.\u001b;%)\u0005\u0001\u0004CA\f2\u0013\t\u00114C\u0001\u0003V]&$\u0018\u0001\u00049s_\u0012,8\r^!sSRLX#A\u001b\u0011\u0005]1\u0014BA\u001c\u0014\u0005\rIe\u000e^\u0001\u000faJ|G-^2u\u000b2,W.\u001a8u)\tA#\bC\u0003<\u000f\u0001\u0007Q\'A\u0001oQ\r9Qh\u0012\t\u0004/y\u0002\u0015BA \u0014\u0005\u0019!\bN]8xgB\u0011\u0011\t\u0012\b\u0003/\tK!aQ\n\u0002\u000fA\f7m[1hK&\u0011QI\u0012\u0002\u001a\u0013:$W\r_(vi>3\'i\\;oIN,\u0005pY3qi&|gN\u0003\u0002D\'\r\n\u0001)\u0001\u0002`cU\t!\n\u0005\u0002L\u00192\u0001AAB\'\u0005\t\u000b\u0007aJ\u0001\u0002UcE\u0011q\n\u000b\t\u0003/AK!!U\n\u0003\u000f9{G\u000f[5oO\u0006\u0011qLM\u000b\u0002)B\u00111*\u0016\u0003\u0007-\u0012!)\u0019\u0001(\u0003\u0005Q\u0013\u0014AA04+\u0005I\u0006CA&[\t\u0019YF\u0001\"b\u0001\u001d\n\u0011AkM\u0001\u0003?R*\u0012A\u0018\t\u0003\u0017~#a\u0001\u0019\u0003\u0005\u0006\u0004q%A\u0001+5\u0003\tyV\'F\u0001d!\tYE\r\u0002\u0004f\t\u0011\u0015\rA\u0014\u0002\u0003)V\n!a\u0018\u001c\u0016\u0003!\u0004\"aS5\u0005\r)$AQ1\u0001O\u0005\t!f\'\u0001\u0002`oU\tQ\u000e\u0005\u0002L]\u00121q\u000e\u0002CC\u00029\u0013!\u0001V\u001c\u0002\u0005}CT#\u0001:\u0011\u0005-\u001bHA\u0002;\u0005\t\u000b\u0007aJ\u0001\u0002Uq\u0005\u0011q,O\u000b\u0002oB\u00111\n\u001f\u0003\u0007s\u0012!)\u0019\u0001(\u0003\u0005QK\u0014aA02aU\tA\u0010\u0005\u0002L{\u00121a\u0010\u0002CC\u00029\u00131\u0001V\u00191!\rY\u0015\u0011\u0001\u0003\u0006\u001b\u000e\u0011\rA\u0014\t\u0004\u0017\u0006\u0015A!\u0002,\u0004\u0005\u0004q\u0005cA&\u0002\n\u0011)1l\u0001b\u0001\u001dB\u00191*!\u0004\u0005\u000b\u0001\u001c!\u0019\u0001(\u0011\u0007-\u000b\t\u0002B\u0003f\u0007\t\u0007a\nE\u0002L\u0003+!QA[\u0002C\u00029\u00032aSA\r\t\u0015y7A1\u0001O!\rY\u0015Q\u0004\u0003\u0006i\u000e\u0011\rA\u0014\t\u0004\u0017\u0006\u0005B!B=\u0004\u0005\u0004q\u0005cA&\u0002&\u0011)ap\u0001b\u0001\u001d\"1\u0011\u0011F\u0002A\u0002\u0015\n\u0011\u0001\u001f
   #12 = Utf8               unapply
   #13 = Utf8               (Lscala/Product10;)Lscala/Option;
   #14 = Utf8               <T1:Ljava/lang/Object;T2:Ljava/lang/Object;T3:Ljava/lang/Object;T4:Ljava/lang/Object;T5:Ljava/lang/Object;T6:Ljava/lang/Object;T7:Ljava/lang/Object;T8:Ljava/lang/Object;T9:Ljava/lang/Object;T10:Ljava/lang/Object;>(Lscala/Product10<TT1;TT2;TT3;TT4;TT5;TT6;TT7;TT8;TT9;TT10;>;)Lscala/Option<Lscala/Product10<TT1;TT2;TT3;TT4;TT5;TT6;TT7;TT8;TT9;TT10;>;>;
   #15 = Utf8               x
   #16 = Utf8               scala/Product10$
   #17 = Class              #16           // scala/Product10$
   #18 = Utf8               MODULE$
   #19 = Utf8               Lscala/Product10$;
   #20 = NameAndType        #18:#19       // MODULE$:Lscala/Product10$;
   #21 = Fieldref           #17.#20       // scala/Product10$.MODULE$:Lscala/Product10$;
   #22 = Utf8               scala/Some
   #23 = Class              #22           // scala/Some
   #24 = Utf8               <init>
   #25 = Utf8               (Ljava/lang/Object;)V
   #26 = NameAndType        #24:#25       // "<init>":(Ljava/lang/Object;)V
   #27 = Methodref          #23.#26       // scala/Some."<init>":(Ljava/lang/Object;)V
   #28 = Utf8               Lscala/Product10;
   #29 = Utf8               productArity$
   #30 = Utf8               (Lscala/Product10;)I
   #31 = Utf8               $this
   #32 = Utf8               productArity
   #33 = Utf8               ()I
   #34 = NameAndType        #32:#33       // productArity:()I
   #35 = InterfaceMethodref #2.#34        // scala/Product10.productArity:()I
   #36 = Utf8               this
   #37 = Utf8               productElement$
   #38 = Utf8               (Lscala/Product10;I)Ljava/lang/Object;
   #39 = Utf8               n
   #40 = Utf8               productElement
   #41 = Utf8               (I)Ljava/lang/Object;
   #42 = NameAndType        #40:#41       // productElement:(I)Ljava/lang/Object;
   #43 = InterfaceMethodref #2.#42        // scala/Product10.productElement:(I)Ljava/lang/Object;
   #44 = Utf8               I
   #45 = Utf8               java/lang/IndexOutOfBoundsException
   #46 = Class              #45           // java/lang/IndexOutOfBoundsException
   #47 = Utf8               _1
   #48 = Utf8               ()Ljava/lang/Object;
   #49 = NameAndType        #47:#48       // _1:()Ljava/lang/Object;
   #50 = InterfaceMethodref #2.#49        // scala/Product10._1:()Ljava/lang/Object;
   #51 = Utf8               _2
   #52 = NameAndType        #51:#48       // _2:()Ljava/lang/Object;
   #53 = InterfaceMethodref #2.#52        // scala/Product10._2:()Ljava/lang/Object;
   #54 = Utf8               _3
   #55 = NameAndType        #54:#48       // _3:()Ljava/lang/Object;
   #56 = InterfaceMethodref #2.#55        // scala/Product10._3:()Ljava/lang/Object;
   #57 = Utf8               _4
   #58 = NameAndType        #57:#48       // _4:()Ljava/lang/Object;
   #59 = InterfaceMethodref #2.#58        // scala/Product10._4:()Ljava/lang/Object;
   #60 = Utf8               _5
   #61 = NameAndType        #60:#48       // _5:()Ljava/lang/Object;
   #62 = InterfaceMethodref #2.#61        // scala/Product10._5:()Ljava/lang/Object;
   #63 = Utf8               _6
   #64 = NameAndType        #63:#48       // _6:()Ljava/lang/Object;
   #65 = InterfaceMethodref #2.#64        // scala/Product10._6:()Ljava/lang/Object;
   #66 = Utf8               _7
   #67 = NameAndType        #66:#48       // _7:()Ljava/lang/Object;
   #68 = InterfaceMethodref #2.#67        // scala/Product10._7:()Ljava/lang/Object;
   #69 = Utf8               _8
   #70 = NameAndType        #69:#48       // _8:()Ljava/lang/Object;
   #71 = InterfaceMethodref #2.#70        // scala/Product10._8:()Ljava/lang/Object;
   #72 = Utf8               _9
   #73 = NameAndType        #72:#48       // _9:()Ljava/lang/Object;
   #74 = InterfaceMethodref #2.#73        // scala/Product10._9:()Ljava/lang/Object;
   #75 = Utf8               _10
   #76 = NameAndType        #75:#48       // _10:()Ljava/lang/Object;
   #77 = InterfaceMethodref #2.#76        // scala/Product10._10:()Ljava/lang/Object;
   #78 = Utf8               java/lang/StringBuilder
   #79 = Class              #78           // java/lang/StringBuilder
   #80 = Integer            32
   #81 = Utf8               (I)V
   #82 = NameAndType        #24:#81       // "<init>":(I)V
   #83 = Methodref          #79.#82       // java/lang/StringBuilder."<init>":(I)V
   #84 = Utf8               append
   #85 = Utf8               (I)Ljava/lang/StringBuilder;
   #86 = NameAndType        #84:#85       // append:(I)Ljava/lang/StringBuilder;
   #87 = Methodref          #79.#86       // java/lang/StringBuilder.append:(I)Ljava/lang/StringBuilder;
   #88 = Utf8                is out of bounds (min 0, max 9)
   #89 = String             #88           //  is out of bounds (min 0, max 9)
   #90 = Utf8               (Ljava/lang/String;)Ljava/lang/StringBuilder;
   #91 = NameAndType        #84:#90       // append:(Ljava/lang/String;)Ljava/lang/StringBuilder;
   #92 = Methodref          #79.#91       // java/lang/StringBuilder.append:(Ljava/lang/String;)Ljava/lang/StringBuilder;
   #93 = Utf8               toString
   #94 = Utf8               ()Ljava/lang/String;
   #95 = NameAndType        #93:#94       // toString:()Ljava/lang/String;
   #96 = Methodref          #79.#95       // java/lang/StringBuilder.toString:()Ljava/lang/String;
   #97 = Utf8               (Ljava/lang/String;)V
   #98 = NameAndType        #24:#97       // "<init>":(Ljava/lang/String;)V
   #99 = Methodref          #46.#98       // java/lang/IndexOutOfBoundsException."<init>":(Ljava/lang/String;)V
  #100 = Utf8               ()TT1;
  #101 = Utf8               ()TT2;
  #102 = Utf8               ()TT3;
  #103 = Utf8               ()TT4;
  #104 = Utf8               ()TT5;
  #105 = Utf8               ()TT6;
  #106 = Utf8               ()TT7;
  #107 = Utf8               ()TT8;
  #108 = Utf8               ()TT9;
  #109 = Utf8               ()TT10;
  #110 = Utf8               $init$
  #111 = Utf8               (Lscala/Product10;)V
  #112 = Utf8               Code
  #113 = Utf8               LineNumberTable
  #114 = Utf8               LocalVariableTable
  #115 = Utf8               Signature
  #116 = Utf8               MethodParameters
  #117 = Utf8               StackMapTable
  #118 = Utf8               Exceptions
  #119 = Utf8               SourceFile
  #120 = Utf8               RuntimeVisibleAnnotations
  #121 = Utf8               ScalaInlineInfo
  #122 = Utf8               ScalaSig
{
  public static <T1 extends java.lang.Object, T2 extends java.lang.Object, T3 extends java.lang.Object, T4 extends java.lang.Object, T5 extends java.lang.Object, T6 extends java.lang.Object, T7 extends java.lang.Object, T8 extends java.lang.Object, T9 extends java.lang.Object, T10 extends java.lang.Object> scala.Option<scala.Product10<T1, T2, T3, T4, T5, T6, T7, T8, T9, T10>> unapply(scala.Product10<T1, T2, T3, T4, T5, T6, T7, T8, T9, T10>);
    descriptor: (Lscala/Product10;)Lscala/Option;
    flags: (0x0009) ACC_PUBLIC, ACC_STATIC
    Code:
      stack=3, locals=1, args_size=1
         0: getstatic     #21                 // Field scala/Product10$.MODULE$:Lscala/Product10$;
         3: pop
         4: new           #23                 // class scala/Some
         7: dup
         8: aload_0
         9: invokespecial #27                 // Method scala/Some."<init>":(Ljava/lang/Object;)V
        12: areturn
      LineNumberTable:
        line 19: 4
      LocalVariableTable:
        Start  Length  Slot  Name   Signature
            0      13     0     x   Lscala/Product10;
    Signature: #14                          // <T1:Ljava/lang/Object;T2:Ljava/lang/Object;T3:Ljava/lang/Object;T4:Ljava/lang/Object;T5:Ljava/lang/Object;T6:Ljava/lang/Object;T7:Ljava/lang/Object;T8:Ljava/lang/Object;T9:Ljava/lang/Object;T10:Ljava/lang/Object;>(Lscala/Product10<TT1;TT2;TT3;TT4;TT5;TT6;TT7;TT8;TT9;TT10;>;)Lscala/Option<Lscala/Product10<TT1;TT2;TT3;TT4;TT5;TT6;TT7;TT8;TT9;TT10;>;>;
    MethodParameters:
      Name                           Flags
      x                              final

  public static int productArity$(scala.Product10);
    descriptor: (Lscala/Product10;)I
    flags: (0x1009) ACC_PUBLIC, ACC_STATIC, ACC_SYNTHETIC
    Code:
      stack=1, locals=1, args_size=1
         0: aload_0
         1: invokespecial #35                 // InterfaceMethod productArity:()I
         4: ireturn
      LineNumberTable:
        line 28: 0
      LocalVariableTable:
        Start  Length  Slot  Name   Signature
            0       5     0 $this   Lscala/Product10;
    MethodParameters:
      Name                           Flags
      $this                          final synthetic

  public default int productArity();
    descriptor: ()I
    flags: (0x0001) ACC_PUBLIC
    Code:
      stack=1, locals=1, args_size=1
         0: bipush        10
         2: ireturn
      LineNumberTable:
        line 28: 0
      LocalVariableTable:
        Start  Length  Slot  Name   Signature
            0       3     0  this   Lscala/Product10;

  public static java.lang.Object productElement$(scala.Product10, int);
    descriptor: (Lscala/Product10;I)Ljava/lang/Object;
    flags: (0x1009) ACC_PUBLIC, ACC_STATIC, ACC_SYNTHETIC
    Code:
      stack=2, locals=2, args_size=2
         0: aload_0
         1: iload_1
         2: invokespecial #43                 // InterfaceMethod productElement:(I)Ljava/lang/Object;
         5: areturn
      LineNumberTable:
        line 40: 0
      LocalVariableTable:
        Start  Length  Slot  Name   Signature
            0       6     0 $this   Lscala/Product10;
            0       6     1     n   I
    MethodParameters:
      Name                           Flags
      $this                          final synthetic
      n                              final

  public default java.lang.Object productElement(int) throws java.lang.IndexOutOfBoundsException;
    descriptor: (I)Ljava/lang/Object;
    flags: (0x0001) ACC_PUBLIC
    Code:
      stack=5, locals=2, args_size=2
         0: iload_1
         1: tableswitch   { // 0 to 9
                       0: 56
                       1: 63
                       2: 70
                       3: 77
                       4: 84
                       5: 91
                       6: 98
                       7: 105
                       8: 112
                       9: 119
                 default: 126
            }
        56: aload_0
        57: invokeinterface #50,  1           // InterfaceMethod _1:()Ljava/lang/Object;
        62: areturn
        63: aload_0
        64: invokeinterface #53,  1           // InterfaceMethod _2:()Ljava/lang/Object;
        69: areturn
        70: aload_0
        71: invokeinterface #56,  1           // InterfaceMethod _3:()Ljava/lang/Object;
        76: areturn
        77: aload_0
        78: invokeinterface #59,  1           // InterfaceMethod _4:()Ljava/lang/Object;
        83: areturn
        84: aload_0
        85: invokeinterface #62,  1           // InterfaceMethod _5:()Ljava/lang/Object;
        90: areturn
        91: aload_0
        92: invokeinterface #65,  1           // InterfaceMethod _6:()Ljava/lang/Object;
        97: areturn
        98: aload_0
        99: invokeinterface #68,  1           // InterfaceMethod _7:()Ljava/lang/Object;
       104: areturn
       105: aload_0
       106: invokeinterface #71,  1           // InterfaceMethod _8:()Ljava/lang/Object;
       111: areturn
       112: aload_0
       113: invokeinterface #74,  1           // InterfaceMethod _9:()Ljava/lang/Object;
       118: areturn
       119: aload_0
       120: invokeinterface #77,  1           // InterfaceMethod _10:()Ljava/lang/Object;
       125: areturn
       126: new           #46                 // class java/lang/IndexOutOfBoundsException
       129: dup
       130: new           #79                 // class java/lang/StringBuilder
       133: dup
       134: ldc           #80                 // int 32
       136: invokespecial #83                 // Method java/lang/StringBuilder."<init>":(I)V
       139: iload_1
       140: invokevirtual #87                 // Method java/lang/StringBuilder.append:(I)Ljava/lang/StringBuilder;
       143: ldc           #89                 // String  is out of bounds (min 0, max 9)
       145: invokevirtual #92                 // Method java/lang/StringBuilder.append:(Ljava/lang/String;)Ljava/lang/StringBuilder;
       148: invokevirtual #96                 // Method java/lang/StringBuilder.toString:()Ljava/lang/String;
       151: invokespecial #99                 // Method java/lang/IndexOutOfBoundsException."<init>":(Ljava/lang/String;)V
       154: athrow
      StackMapTable: number_of_entries = 11
        frame_type = 56 /* same */
        frame_type = 6 /* same */
        frame_type = 6 /* same */
        frame_type = 6 /* same */
        frame_type = 6 /* same */
        frame_type = 6 /* same */
        frame_type = 6 /* same */
        frame_type = 6 /* same */
        frame_type = 6 /* same */
        frame_type = 6 /* same */
        frame_type = 6 /* same */
      LineNumberTable:
        line 40: 0
        line 41: 56
        line 42: 63
        line 43: 70
        line 44: 77
        line 45: 84
        line 46: 91
        line 47: 98
        line 48: 105
        line 49: 112
        line 50: 119
        line 51: 126
      LocalVariableTable:
        Start  Length  Slot  Name   Signature
            0     155     0  this   Lscala/Product10;
            0     155     1     n   I
    Exceptions:
      throws java.lang.IndexOutOfBoundsException
    MethodParameters:
      Name                           Flags
      n                              final

  public abstract T1 _1();
    descriptor: ()Ljava/lang/Object;
    flags: (0x0401) ACC_PUBLIC, ACC_ABSTRACT
    Signature: #100                         // ()TT1;

  public abstract T2 _2();
    descriptor: ()Ljava/lang/Object;
    flags: (0x0401) ACC_PUBLIC, ACC_ABSTRACT
    Signature: #101                         // ()TT2;

  public abstract T3 _3();
    descriptor: ()Ljava/lang/Object;
    flags: (0x0401) ACC_PUBLIC, ACC_ABSTRACT
    Signature: #102                         // ()TT3;

  public abstract T4 _4();
    descriptor: ()Ljava/lang/Object;
    flags: (0x0401) ACC_PUBLIC, ACC_ABSTRACT
    Signature: #103                         // ()TT4;

  public abstract T5 _5();
    descriptor: ()Ljava/lang/Object;
    flags: (0x0401) ACC_PUBLIC, ACC_ABSTRACT
    Signature: #104                         // ()TT5;

  public abstract T6 _6();
    descriptor: ()Ljava/lang/Object;
    flags: (0x0401) ACC_PUBLIC, ACC_ABSTRACT
    Signature: #105                         // ()TT6;

  public abstract T7 _7();
    descriptor: ()Ljava/lang/Object;
    flags: (0x0401) ACC_PUBLIC, ACC_ABSTRACT
    Signature: #106                         // ()TT7;

  public abstract T8 _8();
    descriptor: ()Ljava/lang/Object;
    flags: (0x0401) ACC_PUBLIC, ACC_ABSTRACT
    Signature: #107                         // ()TT8;

  public abstract T9 _9();
    descriptor: ()Ljava/lang/Object;
    flags: (0x0401) ACC_PUBLIC, ACC_ABSTRACT
    Signature: #108                         // ()TT9;

  public abstract T10 _10();
    descriptor: ()Ljava/lang/Object;
    flags: (0x0401) ACC_PUBLIC, ACC_ABSTRACT
    Signature: #109                         // ()TT10;

  public static void $init$(scala.Product10);
    descriptor: (Lscala/Product10;)V
    flags: (0x0009) ACC_PUBLIC, ACC_STATIC
    Code:
      stack=0, locals=1, args_size=1
         0: return
      LineNumberTable:
        line 24: 0
      LocalVariableTable:
        Start  Length  Slot  Name   Signature
            0       1     0 $this   Lscala/Product10;
    MethodParameters:
      Name                           Flags
      $this                          final synthetic
}
Signature: #3                           // <T1:Ljava/lang/Object;T2:Ljava/lang/Object;T3:Ljava/lang/Object;T4:Ljava/lang/Object;T5:Ljava/lang/Object;T6:Ljava/lang/Object;T7:Ljava/lang/Object;T8:Ljava/lang/Object;T9:Ljava/lang/Object;T10:Ljava/lang/Object;>Ljava/lang/Object;Lscala/Product;
SourceFile: "Product10.scala"
RuntimeVisibleAnnotations:
  0: #9(#10=s#11)
    scala.reflect.ScalaSignature(
      bytes="\u0006\u0005\u0005-r!\u0002\n\u0014\u0011\u00031b!\u0002\r\u0014\u0011\u0003I\u0002\"B\u000f\u0002\t\u0003q\u0002\"B\u0010\u0002\t\u0003\u0001ca\u0002\r\u0014!\u0003\r\tA\n\u0005\u0006]\u0011!\ta\f\u0005\u0006g\u0011!\t\u0005\u000e\u0005\u0006q\u0011!\t%\u000f\u0005\u0006\u0011\u00121\t!\u0013\u0005\u0006%\u00121\ta\u0015\u0005\u0006/\u00121\t\u0001\u0017\u0005\u00069\u00121\t!\u0018\u0005\u0006C\u00121\tA\u0019\u0005\u0006M\u00121\ta\u001a\u0005\u0006W\u00121\t\u0001\u001c\u0005\u0006a\u00121\t!\u001d\u0005\u0006k\u00121\tA\u001e\u0005\u0006u\u00121\ta_\u0001\n!J|G-^2ucAR\u0011\u0001F\u0001\u0006g\u000e\fG.Y\u0002\u0001!\t9\u0012!D\u0001\u0014\u0005%\u0001&o\u001c3vGR\f\u0004g\u0005\u0002\u00025A\u0011qcG\u0005\u00039M\u0011a!\u00118z%\u00164\u0017A\u0002\u001fj]&$h\bF\u0001\u0017\u0003\u001d)h.\u00199qYf,R#IA\u0001\u0003\u000b\tI!!\u0004\u0002\u0012\u0005U\u0011\u0011DA\u000f\u0003C\t)\u0003F\u0002#\u0003O\u00012aF\u0012&\u0013\t!3C\u0001\u0004PaRLwN\u001c\t\u0016/\u0011y\u00181AA\u0004\u0003\u0017\ty!a\u0005\u0002\u0018\u0005m\u0011qDA\u0012+-9C*\u0016.`I&t7\u000f_?\u0014\u0007\u0011A3\u0006\u0005\u0002\u0018S%\u0011!f\u0005\u0002\u0004\u0003:L\bCA\f-\u0013\ti3CA\u0004Qe>$Wo\u0019;\u0002\r\u0011Jg.\u001b;%)\u0005\u0001\u0004CA\f2\u0013\t\u00114C\u0001\u0003V]&$\u0018\u0001\u00049s_\u0012,8\r^!sSRLX#A\u001b\u0011\u0005]1\u0014BA\u001c\u0014\u0005\rIe\u000e^\u0001\u000faJ|G-^2u\u000b2,W.\u001a8u)\tA#\bC\u0003<\u000f\u0001\u0007Q\'A\u0001oQ\r9Qh\u0012\t\u0004/y\u0002\u0015BA \u0014\u0005\u0019!\bN]8xgB\u0011\u0011\t\u0012\b\u0003/\tK!aQ\n\u0002\u000fA\f7m[1hK&\u0011QI\u0012\u0002\u001a\u0013:$W\r_(vi>3\'i\\;oIN,\u0005pY3qi&|gN\u0003\u0002D\'\r\n\u0001)\u0001\u0002`cU\t!\n\u0005\u0002L\u00192\u0001AAB\'\u0005\t\u000b\u0007aJ\u0001\u0002UcE\u0011q\n\u000b\t\u0003/AK!!U\n\u0003\u000f9{G\u000f[5oO\u0006\u0011qLM\u000b\u0002)B\u00111*\u0016\u0003\u0007-\u0012!)\u0019\u0001(\u0003\u0005Q\u0013\u0014AA04+\u0005I\u0006CA&[\t\u0019YF\u0001\"b\u0001\u001d\n\u0011AkM\u0001\u0003?R*\u0012A\u0018\t\u0003\u0017~#a\u0001\u0019\u0003\u0005\u0006\u0004q%A\u0001+5\u0003\tyV\'F\u0001d!\tYE\r\u0002\u0004f\t\u0011\u0015\rA\u0014\u0002\u0003)V\n!a\u0018\u001c\u0016\u0003!\u0004\"aS5\u0005\r)$AQ1\u0001O\u0005\t!f\'\u0001\u0002`oU\tQ\u000e\u0005\u0002L]\u00121q\u000e\u0002CC\u00029\u0013!\u0001V\u001c\u0002\u0005}CT#\u0001:\u0011\u0005-\u001bHA\u0002;\u0005\t\u000b\u0007aJ\u0001\u0002Uq\u0005\u0011q,O\u000b\u0002oB\u00111\n\u001f\u0003\u0007s\u0012!)\u0019\u0001(\u0003\u0005QK\u0014aA02aU\tA\u0010\u0005\u0002L{\u00121a\u0010\u0002CC\u00029\u00131\u0001V\u00191!\rY\u0015\u0011\u0001\u0003\u0006\u001b\u000e\u0011\rA\u0014\t\u0004\u0017\u0006\u0015A!\u0002,\u0004\u0005\u0004q\u0005cA&\u0002\n\u0011)1l\u0001b\u0001\u001dB\u00191*!\u0004\u0005\u000b\u0001\u001c!\u0019\u0001(\u0011\u0007-\u000b\t\u0002B\u0003f\u0007\t\u0007a\nE\u0002L\u0003+!QA[\u0002C\u00029\u00032aSA\r\t\u0015y7A1\u0001O!\rY\u0015Q\u0004\u0003\u0006i\u000e\u0011\rA\u0014\t\u0004\u0017\u0006\u0005B!B=\u0004\u0005\u0004q\u0005cA&\u0002&\u0011)ap\u0001b\u0001\u001d\"1\u0011\u0011F\u0002A\u0002\u0015\n\u0011\u0001\u001f"
    )
  ScalaInlineInfo: length = 0x4F (unknown attribute)
   01 00 00 0F 00 6E 00 6F 01 00 2F 00 30 00 00 4B
   00 30 00 00 33 00 30 00 00 36 00 30 00 00 39 00
   30 00 00 3C 00 30 00 00 3F 00 30 00 00 42 00 30
   00 00 45 00 30 00 00 48 00 30 00 00 20 00 21 00
   00 1D 00 1E 01 00 28 00 29 00 00 25 00 26 01
  ScalaSig: length = 0x3 (unknown attribute)
   05 02 00
