Classfile /Users/mw/Projects/slang-braindump/.jar/jar11/assemble/slang-braindump/assemble/content/scala/Product16.class
  Last modified May 29, 2022; size 5008 bytes
  SHA-256 checksum c10cb262b9fb5609b680e7a56908ca5276942dee68f5b28e303f5a4ecd2729fc
  Compiled from "Product16.scala"
public interface scala.Product16<T1 extends java.lang.Object, T2 extends java.lang.Object, T3 extends java.lang.Object, T4 extends java.lang.Object, T5 extends java.lang.Object, T6 extends java.lang.Object, T7 extends java.lang.Object, T8 extends java.lang.Object, T9 extends java.lang.Object, T10 extends java.lang.Object, T11 extends java.lang.Object, T12 extends java.lang.Object, T13 extends java.lang.Object, T14 extends java.lang.Object, T15 extends java.lang.Object, T16 extends java.lang.Object> extends scala.Product
  minor version: 0
  major version: 52
  flags: (0x0601) ACC_PUBLIC, ACC_INTERFACE, ACC_ABSTRACT
  this_class: #2                          // scala/Product16
  super_class: #5                         // java/lang/Object
  interfaces: 1, fields: 0, methods: 22, attributes: 5
Constant pool:
    #1 = Utf8               scala/Product16
    #2 = Class              #1            // scala/Product16
    #3 = Utf8               <T1:Ljava/lang/Object;T2:Ljava/lang/Object;T3:Ljava/lang/Object;T4:Ljava/lang/Object;T5:Ljava/lang/Object;T6:Ljava/lang/Object;T7:Ljava/lang/Object;T8:Ljava/lang/Object;T9:Ljava/lang/Object;T10:Ljava/lang/Object;T11:Ljava/lang/Object;T12:Ljava/lang/Object;T13:Ljava/lang/Object;T14:Ljava/lang/Object;T15:Ljava/lang/Object;T16:Ljava/lang/Object;>Ljava/lang/Object;Lscala/Product;
    #4 = Utf8               java/lang/Object
    #5 = Class              #4            // java/lang/Object
    #6 = Utf8               scala/Product
    #7 = Class              #6            // scala/Product
    #8 = Utf8               Product16.scala
    #9 = Utf8               Lscala/reflect/ScalaSignature;
   #10 = Utf8               bytes
   #11 = Utf8               \u0006\u0005\u0005-u!\u0002\r\u001a\u0011\u0003ab!\u0002\u0010\u001a\u0011\u0003y\u0002\"B\u0012\u0002\t\u0003!\u0003\"B\u0013\u0002\t\u00031ca\u0002\u0010\u001a!\u0003\r\t\u0001\f\u0005\u0006i\u0011!\t!\u000e\u0005\u0006s\u0011!\tE\u000f\u0005\u0006}\u0011!\te\u0010\u0005\u0006\u001d\u00121\ta\u0014\u0005\u00061\u00121\t!\u0017\u0005\u0006;\u00121\tA\u0018\u0005\u0006E\u00121\ta\u0019\u0005\u0006O\u00121\t\u0001\u001b\u0005\u0006Y\u00121\t!\u001c\u0005\u0006c\u00121\tA\u001d\u0005\u0006m\u00121\ta\u001e\u0005\u0006w\u00121\t\u0001 \u0005\b\u0003\u0003!a\u0011AA\u0002\u0011\u001d\tY\u0001\u0002D\u0001\u0003\u001bAq!!\u0006\u0005\r\u0003\t9\u0002C\u0004\u0002 \u00111\t!!\t\t\u000f\u0005%BA\"\u0001\u0002,!9\u00111\u0007\u0003\u0007\u0002\u0005U\u0002bBA\u001f\t\u0019\u0005\u0011qH\u0001\n!J|G-^2ucYR\u0011AG\u0001\u0006g\u000e\fG.Y\u0002\u0001!\ti\u0012!D\u0001\u001a\u0005%\u0001&o\u001c3vGR\fdg\u0005\u0002\u0002AA\u0011Q$I\u0005\u0003Ee\u0011a!\u00118z%\u00164\u0017A\u0002\u001fj]&$h\bF\u0001\u001d\u0003\u001d)h.\u00199qYf,\u0012eJA%\u0003\u001b\n\t&!\u0016\u0002Z\u0005u\u0013\u0011MA3\u0003S\ni\'!\u001d\u0002v\u0005e\u0014QPAA\u0003\u000b#2\u0001KAD!\ri\u0012fK\u0005\u0003Ue\u0011aa\u00149uS>t\u0007CI\u000f\u0005\u0003\u000f\nY%a\u0014\u0002T\u0005]\u00131LA0\u0003G\n9\'a\u001b\u0002p\u0005M\u0014qOA>\u0003\u007f\n\u0019)\u0006\r.%n\u0003WM[8usz\f9!!\u0005\u0002\u001c\u0005\u0015\u0012qFA\u001d\u0003\u0007\u001a2\u0001\u0002\u00182!\tir&\u0003\u000213\t\u0019\u0011I\\=\u0011\u0005u\u0011\u0014BA\u001a\u001a\u0005\u001d\u0001&o\u001c3vGR\fa\u0001J5oSR$C#\u0001\u001c\u0011\u0005u9\u0014B\u0001\u001d\u001a\u0005\u0011)f.\u001b;\u0002\u0019A\u0014x\u000eZ;di\u0006\u0013\u0018\u000e^=\u0016\u0003m\u0002\"!\b\u001f\n\u0005uJ\"aA%oi\u0006q\u0001O]8ek\u000e$X\t\\3nK:$HC\u0001\u0018A\u0011\u0015\tu\u00011\u0001<\u0003\u0005q\u0007fA\u0004D\u001bB\u0019Q\u0004\u0012$\n\u0005\u0015K\"A\u0002;ie><8\u000f\u0005\u0002H\u0015:\u0011Q\u0004S\u0005\u0003\u0013f\tq\u0001]1dW\u0006<W-\u0003\u0002L\u0019\nI\u0012J\u001c3fq>+Ho\u00144C_VtGm]#yG\u0016\u0004H/[8o\u0015\tI\u0015dI\u0001G\u0003\ty\u0016\'F\u0001Q!\t\t&\u000b\u0004\u0001\u0005\rM#AQ1\u0001U\u0005\t!\u0016\'\u0005\u0002V]A\u0011QDV\u0005\u0003/f\u0011qAT8uQ&tw-\u0001\u0002`eU\t!\f\u0005\u0002R7\u00121A\f\u0002CC\u0002Q\u0013!\u0001\u0016\u001a\u0002\u0005}\u001bT#A0\u0011\u0005E\u0003GAB1\u0005\t\u000b\u0007AK\u0001\u0002Ug\u0005\u0011q\fN\u000b\u0002IB\u0011\u0011+\u001a\u0003\u0007M\u0012!)\u0019\u0001+\u0003\u0005Q#\u0014AA06+\u0005I\u0007CA)k\t\u0019YG\u0001\"b\u0001)\n\u0011A+N\u0001\u0003?Z*\u0012A\u001c\t\u0003#>$a\u0001\u001d\u0003\u0005\u0006\u0004!&A\u0001+7\u0003\tyv\'F\u0001t!\t\tF\u000f\u0002\u0004v\t\u0011\u0015\r\u0001\u0016\u0002\u0003)^\n!a\u0018\u001d\u0016\u0003a\u0004\"!U=\u0005\ri$AQ1\u0001U\u0005\t!\u0006(\u0001\u0002`sU\tQ\u0010\u0005\u0002R}\u00121q\u0010\u0002CC\u0002Q\u0013!\u0001V\u001d\u0002\u0007}\u000b\u0004\'\u0006\u0002\u0002\u0006A\u0019\u0011+a\u0002\u0005\u000f\u0005%A\u0001\"b\u0001)\n\u0019A+\r\u0019\u0002\u0007}\u000b\u0014\'\u0006\u0002\u0002\u0010A\u0019\u0011+!\u0005\u0005\u000f\u0005MA\u0001\"b\u0001)\n\u0019A+M\u0019\u0002\u0007}\u000b$\'\u0006\u0002\u0002\u001aA\u0019\u0011+a\u0007\u0005\u000f\u0005uA\u0001\"b\u0001)\n\u0019A+\r\u001a\u0002\u0007}\u000b4\'\u0006\u0002\u0002$A\u0019\u0011+!\n\u0005\u000f\u0005\u001dB\u0001\"b\u0001)\n\u0019A+M\u001a\u0002\u0007}\u000bD\'\u0006\u0002\u0002.A\u0019\u0011+a\f\u0005\u000f\u0005EB\u0001\"b\u0001)\n\u0019A+\r\u001b\u0002\u0007}\u000bT\'\u0006\u0002\u00028A\u0019\u0011+!\u000f\u0005\u000f\u0005mB\u0001\"b\u0001)\n\u0019A+M\u001b\u0002\u0007}\u000bd\'\u0006\u0002\u0002BA\u0019\u0011+a\u0011\u0005\u000f\u0005\u0015C\u0001\"b\u0001)\n\u0019A+\r\u001c\u0011\u0007E\u000bI\u0005B\u0003T\u0007\t\u0007A\u000bE\u0002R\u0003\u001b\"Q\u0001X\u0002C\u0002Q\u00032!UA)\t\u0015\t7A1\u0001U!\r\t\u0016Q\u000b\u0003\u0006M\u000e\u0011\r\u0001\u0016\t\u0004#\u0006eC!B6\u0004\u0005\u0004!\u0006cA)\u0002^\u0011)\u0001o\u0001b\u0001)B\u0019\u0011+!\u0019\u0005\u000bU\u001c!\u0019\u0001+\u0011\u0007E\u000b)\u0007B\u0003{\u0007\t\u0007A\u000bE\u0002R\u0003S\"Qa`\u0002C\u0002Q\u00032!UA7\t\u0019\tIa\u0001b\u0001)B\u0019\u0011+!\u001d\u0005\r\u0005M1A1\u0001U!\r\t\u0016Q\u000f\u0003\u0007\u0003;\u0019!\u0019\u0001+\u0011\u0007E\u000bI\b\u0002\u0004\u0002(\r\u0011\r\u0001\u0016\t\u0004#\u0006uDABA\u0019\u0007\t\u0007A\u000bE\u0002R\u0003\u0003#a!a\u000f\u0004\u0005\u0004!\u0006cA)\u0002\u0006\u00121\u0011QI\u0002C\u0002QCa!!#\u0004\u0001\u0004Y\u0013!\u0001=
   #12 = Utf8               unapply
   #13 = Utf8               (Lscala/Product16;)Lscala/Option;
   #14 = Utf8               <T1:Ljava/lang/Object;T2:Ljava/lang/Object;T3:Ljava/lang/Object;T4:Ljava/lang/Object;T5:Ljava/lang/Object;T6:Ljava/lang/Object;T7:Ljava/lang/Object;T8:Ljava/lang/Object;T9:Ljava/lang/Object;T10:Ljava/lang/Object;T11:Ljava/lang/Object;T12:Ljava/lang/Object;T13:Ljava/lang/Object;T14:Ljava/lang/Object;T15:Ljava/lang/Object;T16:Ljava/lang/Object;>(Lscala/Product16<TT1;TT2;TT3;TT4;TT5;TT6;TT7;TT8;TT9;TT10;TT11;TT12;TT13;TT14;TT15;TT16;>;)Lscala/Option<Lscala/Product16<TT1;TT2;TT3;TT4;TT5;TT6;TT7;TT8;TT9;TT10;TT11;TT12;TT13;TT14;TT15;TT16;>;>;
   #15 = Utf8               x
   #16 = Utf8               scala/Product16$
   #17 = Class              #16           // scala/Product16$
   #18 = Utf8               MODULE$
   #19 = Utf8               Lscala/Product16$;
   #20 = NameAndType        #18:#19       // MODULE$:Lscala/Product16$;
   #21 = Fieldref           #17.#20       // scala/Product16$.MODULE$:Lscala/Product16$;
   #22 = Utf8               scala/Some
   #23 = Class              #22           // scala/Some
   #24 = Utf8               <init>
   #25 = Utf8               (Ljava/lang/Object;)V
   #26 = NameAndType        #24:#25       // "<init>":(Ljava/lang/Object;)V
   #27 = Methodref          #23.#26       // scala/Some."<init>":(Ljava/lang/Object;)V
   #28 = Utf8               Lscala/Product16;
   #29 = Utf8               productArity$
   #30 = Utf8               (Lscala/Product16;)I
   #31 = Utf8               $this
   #32 = Utf8               productArity
   #33 = Utf8               ()I
   #34 = NameAndType        #32:#33       // productArity:()I
   #35 = InterfaceMethodref #2.#34        // scala/Product16.productArity:()I
   #36 = Utf8               this
   #37 = Utf8               productElement$
   #38 = Utf8               (Lscala/Product16;I)Ljava/lang/Object;
   #39 = Utf8               n
   #40 = Utf8               productElement
   #41 = Utf8               (I)Ljava/lang/Object;
   #42 = NameAndType        #40:#41       // productElement:(I)Ljava/lang/Object;
   #43 = InterfaceMethodref #2.#42        // scala/Product16.productElement:(I)Ljava/lang/Object;
   #44 = Utf8               I
   #45 = Utf8               java/lang/IndexOutOfBoundsException
   #46 = Class              #45           // java/lang/IndexOutOfBoundsException
   #47 = Utf8               _1
   #48 = Utf8               ()Ljava/lang/Object;
   #49 = NameAndType        #47:#48       // _1:()Ljava/lang/Object;
   #50 = InterfaceMethodref #2.#49        // scala/Product16._1:()Ljava/lang/Object;
   #51 = Utf8               _2
   #52 = NameAndType        #51:#48       // _2:()Ljava/lang/Object;
   #53 = InterfaceMethodref #2.#52        // scala/Product16._2:()Ljava/lang/Object;
   #54 = Utf8               _3
   #55 = NameAndType        #54:#48       // _3:()Ljava/lang/Object;
   #56 = InterfaceMethodref #2.#55        // scala/Product16._3:()Ljava/lang/Object;
   #57 = Utf8               _4
   #58 = NameAndType        #57:#48       // _4:()Ljava/lang/Object;
   #59 = InterfaceMethodref #2.#58        // scala/Product16._4:()Ljava/lang/Object;
   #60 = Utf8               _5
   #61 = NameAndType        #60:#48       // _5:()Ljava/lang/Object;
   #62 = InterfaceMethodref #2.#61        // scala/Product16._5:()Ljava/lang/Object;
   #63 = Utf8               _6
   #64 = NameAndType        #63:#48       // _6:()Ljava/lang/Object;
   #65 = InterfaceMethodref #2.#64        // scala/Product16._6:()Ljava/lang/Object;
   #66 = Utf8               _7
   #67 = NameAndType        #66:#48       // _7:()Ljava/lang/Object;
   #68 = InterfaceMethodref #2.#67        // scala/Product16._7:()Ljava/lang/Object;
   #69 = Utf8               _8
   #70 = NameAndType        #69:#48       // _8:()Ljava/lang/Object;
   #71 = InterfaceMethodref #2.#70        // scala/Product16._8:()Ljava/lang/Object;
   #72 = Utf8               _9
   #73 = NameAndType        #72:#48       // _9:()Ljava/lang/Object;
   #74 = InterfaceMethodref #2.#73        // scala/Product16._9:()Ljava/lang/Object;
   #75 = Utf8               _10
   #76 = NameAndType        #75:#48       // _10:()Ljava/lang/Object;
   #77 = InterfaceMethodref #2.#76        // scala/Product16._10:()Ljava/lang/Object;
   #78 = Utf8               _11
   #79 = NameAndType        #78:#48       // _11:()Ljava/lang/Object;
   #80 = InterfaceMethodref #2.#79        // scala/Product16._11:()Ljava/lang/Object;
   #81 = Utf8               _12
   #82 = NameAndType        #81:#48       // _12:()Ljava/lang/Object;
   #83 = InterfaceMethodref #2.#82        // scala/Product16._12:()Ljava/lang/Object;
   #84 = Utf8               _13
   #85 = NameAndType        #84:#48       // _13:()Ljava/lang/Object;
   #86 = InterfaceMethodref #2.#85        // scala/Product16._13:()Ljava/lang/Object;
   #87 = Utf8               _14
   #88 = NameAndType        #87:#48       // _14:()Ljava/lang/Object;
   #89 = InterfaceMethodref #2.#88        // scala/Product16._14:()Ljava/lang/Object;
   #90 = Utf8               _15
   #91 = NameAndType        #90:#48       // _15:()Ljava/lang/Object;
   #92 = InterfaceMethodref #2.#91        // scala/Product16._15:()Ljava/lang/Object;
   #93 = Utf8               _16
   #94 = NameAndType        #93:#48       // _16:()Ljava/lang/Object;
   #95 = InterfaceMethodref #2.#94        // scala/Product16._16:()Ljava/lang/Object;
   #96 = Utf8               java/lang/StringBuilder
   #97 = Class              #96           // java/lang/StringBuilder
   #98 = Integer            33
   #99 = Utf8               (I)V
  #100 = NameAndType        #24:#99       // "<init>":(I)V
  #101 = Methodref          #97.#100      // java/lang/StringBuilder."<init>":(I)V
  #102 = Utf8               append
  #103 = Utf8               (I)Ljava/lang/StringBuilder;
  #104 = NameAndType        #102:#103     // append:(I)Ljava/lang/StringBuilder;
  #105 = Methodref          #97.#104      // java/lang/StringBuilder.append:(I)Ljava/lang/StringBuilder;
  #106 = Utf8                is out of bounds (min 0, max 15)
  #107 = String             #106          //  is out of bounds (min 0, max 15)
  #108 = Utf8               (Ljava/lang/String;)Ljava/lang/StringBuilder;
  #109 = NameAndType        #102:#108     // append:(Ljava/lang/String;)Ljava/lang/StringBuilder;
  #110 = Methodref          #97.#109      // java/lang/StringBuilder.append:(Ljava/lang/String;)Ljava/lang/StringBuilder;
  #111 = Utf8               toString
  #112 = Utf8               ()Ljava/lang/String;
  #113 = NameAndType        #111:#112     // toString:()Ljava/lang/String;
  #114 = Methodref          #97.#113      // java/lang/StringBuilder.toString:()Ljava/lang/String;
  #115 = Utf8               (Ljava/lang/String;)V
  #116 = NameAndType        #24:#115      // "<init>":(Ljava/lang/String;)V
  #117 = Methodref          #46.#116      // java/lang/IndexOutOfBoundsException."<init>":(Ljava/lang/String;)V
  #118 = Utf8               ()TT1;
  #119 = Utf8               ()TT2;
  #120 = Utf8               ()TT3;
  #121 = Utf8               ()TT4;
  #122 = Utf8               ()TT5;
  #123 = Utf8               ()TT6;
  #124 = Utf8               ()TT7;
  #125 = Utf8               ()TT8;
  #126 = Utf8               ()TT9;
  #127 = Utf8               ()TT10;
  #128 = Utf8               ()TT11;
  #129 = Utf8               ()TT12;
  #130 = Utf8               ()TT13;
  #131 = Utf8               ()TT14;
  #132 = Utf8               ()TT15;
  #133 = Utf8               ()TT16;
  #134 = Utf8               $init$
  #135 = Utf8               (Lscala/Product16;)V
  #136 = Utf8               Code
  #137 = Utf8               LineNumberTable
  #138 = Utf8               LocalVariableTable
  #139 = Utf8               Signature
  #140 = Utf8               MethodParameters
  #141 = Utf8               StackMapTable
  #142 = Utf8               Exceptions
  #143 = Utf8               SourceFile
  #144 = Utf8               RuntimeVisibleAnnotations
  #145 = Utf8               ScalaInlineInfo
  #146 = Utf8               ScalaSig
{
  public static <T1 extends java.lang.Object, T2 extends java.lang.Object, T3 extends java.lang.Object, T4 extends java.lang.Object, T5 extends java.lang.Object, T6 extends java.lang.Object, T7 extends java.lang.Object, T8 extends java.lang.Object, T9 extends java.lang.Object, T10 extends java.lang.Object, T11 extends java.lang.Object, T12 extends java.lang.Object, T13 extends java.lang.Object, T14 extends java.lang.Object, T15 extends java.lang.Object, T16 extends java.lang.Object> scala.Option<scala.Product16<T1, T2, T3, T4, T5, T6, T7, T8, T9, T10, T11, T12, T13, T14, T15, T16>> unapply(scala.Product16<T1, T2, T3, T4, T5, T6, T7, T8, T9, T10, T11, T12, T13, T14, T15, T16>);
    descriptor: (Lscala/Product16;)Lscala/Option;
    flags: (0x0009) ACC_PUBLIC, ACC_STATIC
    Code:
      stack=3, locals=1, args_size=1
         0: getstatic     #21                 // Field scala/Product16$.MODULE$:Lscala/Product16$;
         3: pop
         4: new           #23                 // class scala/Some
         7: dup
         8: aload_0
         9: invokespecial #27                 // Method scala/Some."<init>":(Ljava/lang/Object;)V
        12: areturn
      LineNumberTable:
        line 19: 4
      LocalVariableTable:
        Start  Length  Slot  Name   Signature
            0      13     0     x   Lscala/Product16;
    Signature: #14                          // <T1:Ljava/lang/Object;T2:Ljava/lang/Object;T3:Ljava/lang/Object;T4:Ljava/lang/Object;T5:Ljava/lang/Object;T6:Ljava/lang/Object;T7:Ljava/lang/Object;T8:Ljava/lang/Object;T9:Ljava/lang/Object;T10:Ljava/lang/Object;T11:Ljava/lang/Object;T12:Ljava/lang/Object;T13:Ljava/lang/Object;T14:Ljava/lang/Object;T15:Ljava/lang/Object;T16:Ljava/lang/Object;>(Lscala/Product16<TT1;TT2;TT3;TT4;TT5;TT6;TT7;TT8;TT9;TT10;TT11;TT12;TT13;TT14;TT15;TT16;>;)Lscala/Option<Lscala/Product16<TT1;TT2;TT3;TT4;TT5;TT6;TT7;TT8;TT9;TT10;TT11;TT12;TT13;TT14;TT15;TT16;>;>;
    MethodParameters:
      Name                           Flags
      x                              final

  public static int productArity$(scala.Product16);
    descriptor: (Lscala/Product16;)I
    flags: (0x1009) ACC_PUBLIC, ACC_STATIC, ACC_SYNTHETIC
    Code:
      stack=1, locals=1, args_size=1
         0: aload_0
         1: invokespecial #35                 // InterfaceMethod productArity:()I
         4: ireturn
      LineNumberTable:
        line 28: 0
      LocalVariableTable:
        Start  Length  Slot  Name   Signature
            0       5     0 $this   Lscala/Product16;
    MethodParameters:
      Name                           Flags
      $this                          final synthetic

  public default int productArity();
    descriptor: ()I
    flags: (0x0001) ACC_PUBLIC
    Code:
      stack=1, locals=1, args_size=1
         0: bipush        16
         2: ireturn
      LineNumberTable:
        line 28: 0
      LocalVariableTable:
        Start  Length  Slot  Name   Signature
            0       3     0  this   Lscala/Product16;

  public static java.lang.Object productElement$(scala.Product16, int);
    descriptor: (Lscala/Product16;I)Ljava/lang/Object;
    flags: (0x1009) ACC_PUBLIC, ACC_STATIC, ACC_SYNTHETIC
    Code:
      stack=2, locals=2, args_size=2
         0: aload_0
         1: iload_1
         2: invokespecial #43                 // InterfaceMethod productElement:(I)Ljava/lang/Object;
         5: areturn
      LineNumberTable:
        line 40: 0
      LocalVariableTable:
        Start  Length  Slot  Name   Signature
            0       6     0 $this   Lscala/Product16;
            0       6     1     n   I
    MethodParameters:
      Name                           Flags
      $this                          final synthetic
      n                              final

  public default java.lang.Object productElement(int) throws java.lang.IndexOutOfBoundsException;
    descriptor: (I)Ljava/lang/Object;
    flags: (0x0001) ACC_PUBLIC
    Code:
      stack=5, locals=2, args_size=2
         0: iload_1
         1: tableswitch   { // 0 to 15
                       0: 80
                       1: 87
                       2: 94
                       3: 101
                       4: 108
                       5: 115
                       6: 122
                       7: 129
                       8: 136
                       9: 143
                      10: 150
                      11: 157
                      12: 164
                      13: 171
                      14: 178
                      15: 185
                 default: 192
            }
        80: aload_0
        81: invokeinterface #50,  1           // InterfaceMethod _1:()Ljava/lang/Object;
        86: areturn
        87: aload_0
        88: invokeinterface #53,  1           // InterfaceMethod _2:()Ljava/lang/Object;
        93: areturn
        94: aload_0
        95: invokeinterface #56,  1           // InterfaceMethod _3:()Ljava/lang/Object;
       100: areturn
       101: aload_0
       102: invokeinterface #59,  1           // InterfaceMethod _4:()Ljava/lang/Object;
       107: areturn
       108: aload_0
       109: invokeinterface #62,  1           // InterfaceMethod _5:()Ljava/lang/Object;
       114: areturn
       115: aload_0
       116: invokeinterface #65,  1           // InterfaceMethod _6:()Ljava/lang/Object;
       121: areturn
       122: aload_0
       123: invokeinterface #68,  1           // InterfaceMethod _7:()Ljava/lang/Object;
       128: areturn
       129: aload_0
       130: invokeinterface #71,  1           // InterfaceMethod _8:()Ljava/lang/Object;
       135: areturn
       136: aload_0
       137: invokeinterface #74,  1           // InterfaceMethod _9:()Ljava/lang/Object;
       142: areturn
       143: aload_0
       144: invokeinterface #77,  1           // InterfaceMethod _10:()Ljava/lang/Object;
       149: areturn
       150: aload_0
       151: invokeinterface #80,  1           // InterfaceMethod _11:()Ljava/lang/Object;
       156: areturn
       157: aload_0
       158: invokeinterface #83,  1           // InterfaceMethod _12:()Ljava/lang/Object;
       163: areturn
       164: aload_0
       165: invokeinterface #86,  1           // InterfaceMethod _13:()Ljava/lang/Object;
       170: areturn
       171: aload_0
       172: invokeinterface #89,  1           // InterfaceMethod _14:()Ljava/lang/Object;
       177: areturn
       178: aload_0
       179: invokeinterface #92,  1           // InterfaceMethod _15:()Ljava/lang/Object;
       184: areturn
       185: aload_0
       186: invokeinterface #95,  1           // InterfaceMethod _16:()Ljava/lang/Object;
       191: areturn
       192: new           #46                 // class java/lang/IndexOutOfBoundsException
       195: dup
       196: new           #97                 // class java/lang/StringBuilder
       199: dup
       200: ldc           #98                 // int 33
       202: invokespecial #101                // Method java/lang/StringBuilder."<init>":(I)V
       205: iload_1
       206: invokevirtual #105                // Method java/lang/StringBuilder.append:(I)Ljava/lang/StringBuilder;
       209: ldc           #107                // String  is out of bounds (min 0, max 15)
       211: invokevirtual #110                // Method java/lang/StringBuilder.append:(Ljava/lang/String;)Ljava/lang/StringBuilder;
       214: invokevirtual #114                // Method java/lang/StringBuilder.toString:()Ljava/lang/String;
       217: invokespecial #117                // Method java/lang/IndexOutOfBoundsException."<init>":(Ljava/lang/String;)V
       220: athrow
      StackMapTable: number_of_entries = 17
        frame_type = 251 /* same_frame_extended */
          offset_delta = 80
        frame_type = 6 /* same */
        frame_type = 6 /* same */
        frame_type = 6 /* same */
        frame_type = 6 /* same */
        frame_type = 6 /* same */
        frame_type = 6 /* same */
        frame_type = 6 /* same */
        frame_type = 6 /* same */
        frame_type = 6 /* same */
        frame_type = 6 /* same */
        frame_type = 6 /* same */
        frame_type = 6 /* same */
        frame_type = 6 /* same */
        frame_type = 6 /* same */
        frame_type = 6 /* same */
        frame_type = 6 /* same */
      LineNumberTable:
        line 40: 0
        line 41: 80
        line 42: 87
        line 43: 94
        line 44: 101
        line 45: 108
        line 46: 115
        line 47: 122
        line 48: 129
        line 49: 136
        line 50: 143
        line 51: 150
        line 52: 157
        line 53: 164
        line 54: 171
        line 55: 178
        line 56: 185
        line 57: 192
      LocalVariableTable:
        Start  Length  Slot  Name   Signature
            0     221     0  this   Lscala/Product16;
            0     221     1     n   I
    Exceptions:
      throws java.lang.IndexOutOfBoundsException
    MethodParameters:
      Name                           Flags
      n                              final

  public abstract T1 _1();
    descriptor: ()Ljava/lang/Object;
    flags: (0x0401) ACC_PUBLIC, ACC_ABSTRACT
    Signature: #118                         // ()TT1;

  public abstract T2 _2();
    descriptor: ()Ljava/lang/Object;
    flags: (0x0401) ACC_PUBLIC, ACC_ABSTRACT
    Signature: #119                         // ()TT2;

  public abstract T3 _3();
    descriptor: ()Ljava/lang/Object;
    flags: (0x0401) ACC_PUBLIC, ACC_ABSTRACT
    Signature: #120                         // ()TT3;

  public abstract T4 _4();
    descriptor: ()Ljava/lang/Object;
    flags: (0x0401) ACC_PUBLIC, ACC_ABSTRACT
    Signature: #121                         // ()TT4;

  public abstract T5 _5();
    descriptor: ()Ljava/lang/Object;
    flags: (0x0401) ACC_PUBLIC, ACC_ABSTRACT
    Signature: #122                         // ()TT5;

  public abstract T6 _6();
    descriptor: ()Ljava/lang/Object;
    flags: (0x0401) ACC_PUBLIC, ACC_ABSTRACT
    Signature: #123                         // ()TT6;

  public abstract T7 _7();
    descriptor: ()Ljava/lang/Object;
    flags: (0x0401) ACC_PUBLIC, ACC_ABSTRACT
    Signature: #124                         // ()TT7;

  public abstract T8 _8();
    descriptor: ()Ljava/lang/Object;
    flags: (0x0401) ACC_PUBLIC, ACC_ABSTRACT
    Signature: #125                         // ()TT8;

  public abstract T9 _9();
    descriptor: ()Ljava/lang/Object;
    flags: (0x0401) ACC_PUBLIC, ACC_ABSTRACT
    Signature: #126                         // ()TT9;

  public abstract T10 _10();
    descriptor: ()Ljava/lang/Object;
    flags: (0x0401) ACC_PUBLIC, ACC_ABSTRACT
    Signature: #127                         // ()TT10;

  public abstract T11 _11();
    descriptor: ()Ljava/lang/Object;
    flags: (0x0401) ACC_PUBLIC, ACC_ABSTRACT
    Signature: #128                         // ()TT11;

  public abstract T12 _12();
    descriptor: ()Ljava/lang/Object;
    flags: (0x0401) ACC_PUBLIC, ACC_ABSTRACT
    Signature: #129                         // ()TT12;

  public abstract T13 _13();
    descriptor: ()Ljava/lang/Object;
    flags: (0x0401) ACC_PUBLIC, ACC_ABSTRACT
    Signature: #130                         // ()TT13;

  public abstract T14 _14();
    descriptor: ()Ljava/lang/Object;
    flags: (0x0401) ACC_PUBLIC, ACC_ABSTRACT
    Signature: #131                         // ()TT14;

  public abstract T15 _15();
    descriptor: ()Ljava/lang/Object;
    flags: (0x0401) ACC_PUBLIC, ACC_ABSTRACT
    Signature: #132                         // ()TT15;

  public abstract T16 _16();
    descriptor: ()Ljava/lang/Object;
    flags: (0x0401) ACC_PUBLIC, ACC_ABSTRACT
    Signature: #133                         // ()TT16;

  public static void $init$(scala.Product16);
    descriptor: (Lscala/Product16;)V
    flags: (0x0009) ACC_PUBLIC, ACC_STATIC
    Code:
      stack=0, locals=1, args_size=1
         0: return
      LineNumberTable:
        line 24: 0
      LocalVariableTable:
        Start  Length  Slot  Name   Signature
            0       1     0 $this   Lscala/Product16;
    MethodParameters:
      Name                           Flags
      $this                          final synthetic
}
Signature: #3                           // <T1:Ljava/lang/Object;T2:Ljava/lang/Object;T3:Ljava/lang/Object;T4:Ljava/lang/Object;T5:Ljava/lang/Object;T6:Ljava/lang/Object;T7:Ljava/lang/Object;T8:Ljava/lang/Object;T9:Ljava/lang/Object;T10:Ljava/lang/Object;T11:Ljava/lang/Object;T12:Ljava/lang/Object;T13:Ljava/lang/Object;T14:Ljava/lang/Object;T15:Ljava/lang/Object;T16:Ljava/lang/Object;>Ljava/lang/Object;Lscala/Product;
SourceFile: "Product16.scala"
RuntimeVisibleAnnotations:
  0: #9(#10=s#11)
    scala.reflect.ScalaSignature(
      bytes="\u0006\u0005\u0005-u!\u0002\r\u001a\u0011\u0003ab!\u0002\u0010\u001a\u0011\u0003y\u0002\"B\u0012\u0002\t\u0003!\u0003\"B\u0013\u0002\t\u00031ca\u0002\u0010\u001a!\u0003\r\t\u0001\f\u0005\u0006i\u0011!\t!\u000e\u0005\u0006s\u0011!\tE\u000f\u0005\u0006}\u0011!\te\u0010\u0005\u0006\u001d\u00121\ta\u0014\u0005\u00061\u00121\t!\u0017\u0005\u0006;\u00121\tA\u0018\u0005\u0006E\u00121\ta\u0019\u0005\u0006O\u00121\t\u0001\u001b\u0005\u0006Y\u00121\t!\u001c\u0005\u0006c\u00121\tA\u001d\u0005\u0006m\u00121\ta\u001e\u0005\u0006w\u00121\t\u0001 \u0005\b\u0003\u0003!a\u0011AA\u0002\u0011\u001d\tY\u0001\u0002D\u0001\u0003\u001bAq!!\u0006\u0005\r\u0003\t9\u0002C\u0004\u0002 \u00111\t!!\t\t\u000f\u0005%BA\"\u0001\u0002,!9\u00111\u0007\u0003\u0007\u0002\u0005U\u0002bBA\u001f\t\u0019\u0005\u0011qH\u0001\n!J|G-^2ucYR\u0011AG\u0001\u0006g\u000e\fG.Y\u0002\u0001!\ti\u0012!D\u0001\u001a\u0005%\u0001&o\u001c3vGR\fdg\u0005\u0002\u0002AA\u0011Q$I\u0005\u0003Ee\u0011a!\u00118z%\u00164\u0017A\u0002\u001fj]&$h\bF\u0001\u001d\u0003\u001d)h.\u00199qYf,\u0012eJA%\u0003\u001b\n\t&!\u0016\u0002Z\u0005u\u0013\u0011MA3\u0003S\ni\'!\u001d\u0002v\u0005e\u0014QPAA\u0003\u000b#2\u0001KAD!\ri\u0012fK\u0005\u0003Ue\u0011aa\u00149uS>t\u0007CI\u000f\u0005\u0003\u000f\nY%a\u0014\u0002T\u0005]\u00131LA0\u0003G\n9\'a\u001b\u0002p\u0005M\u0014qOA>\u0003\u007f\n\u0019)\u0006\r.%n\u0003WM[8usz\f9!!\u0005\u0002\u001c\u0005\u0015\u0012qFA\u001d\u0003\u0007\u001a2\u0001\u0002\u00182!\tir&\u0003\u000213\t\u0019\u0011I\\=\u0011\u0005u\u0011\u0014BA\u001a\u001a\u0005\u001d\u0001&o\u001c3vGR\fa\u0001J5oSR$C#\u0001\u001c\u0011\u0005u9\u0014B\u0001\u001d\u001a\u0005\u0011)f.\u001b;\u0002\u0019A\u0014x\u000eZ;di\u0006\u0013\u0018\u000e^=\u0016\u0003m\u0002\"!\b\u001f\n\u0005uJ\"aA%oi\u0006q\u0001O]8ek\u000e$X\t\\3nK:$HC\u0001\u0018A\u0011\u0015\tu\u00011\u0001<\u0003\u0005q\u0007fA\u0004D\u001bB\u0019Q\u0004\u0012$\n\u0005\u0015K\"A\u0002;ie><8\u000f\u0005\u0002H\u0015:\u0011Q\u0004S\u0005\u0003\u0013f\tq\u0001]1dW\u0006<W-\u0003\u0002L\u0019\nI\u0012J\u001c3fq>+Ho\u00144C_VtGm]#yG\u0016\u0004H/[8o\u0015\tI\u0015dI\u0001G\u0003\ty\u0016\'F\u0001Q!\t\t&\u000b\u0004\u0001\u0005\rM#AQ1\u0001U\u0005\t!\u0016\'\u0005\u0002V]A\u0011QDV\u0005\u0003/f\u0011qAT8uQ&tw-\u0001\u0002`eU\t!\f\u0005\u0002R7\u00121A\f\u0002CC\u0002Q\u0013!\u0001\u0016\u001a\u0002\u0005}\u001bT#A0\u0011\u0005E\u0003GAB1\u0005\t\u000b\u0007AK\u0001\u0002Ug\u0005\u0011q\fN\u000b\u0002IB\u0011\u0011+\u001a\u0003\u0007M\u0012!)\u0019\u0001+\u0003\u0005Q#\u0014AA06+\u0005I\u0007CA)k\t\u0019YG\u0001\"b\u0001)\n\u0011A+N\u0001\u0003?Z*\u0012A\u001c\t\u0003#>$a\u0001\u001d\u0003\u0005\u0006\u0004!&A\u0001+7\u0003\tyv\'F\u0001t!\t\tF\u000f\u0002\u0004v\t\u0011\u0015\r\u0001\u0016\u0002\u0003)^\n!a\u0018\u001d\u0016\u0003a\u0004\"!U=\u0005\ri$AQ1\u0001U\u0005\t!\u0006(\u0001\u0002`sU\tQ\u0010\u0005\u0002R}\u00121q\u0010\u0002CC\u0002Q\u0013!\u0001V\u001d\u0002\u0007}\u000b\u0004\'\u0006\u0002\u0002\u0006A\u0019\u0011+a\u0002\u0005\u000f\u0005%A\u0001\"b\u0001)\n\u0019A+\r\u0019\u0002\u0007}\u000b\u0014\'\u0006\u0002\u0002\u0010A\u0019\u0011+!\u0005\u0005\u000f\u0005MA\u0001\"b\u0001)\n\u0019A+M\u0019\u0002\u0007}\u000b$\'\u0006\u0002\u0002\u001aA\u0019\u0011+a\u0007\u0005\u000f\u0005uA\u0001\"b\u0001)\n\u0019A+\r\u001a\u0002\u0007}\u000b4\'\u0006\u0002\u0002$A\u0019\u0011+!\n\u0005\u000f\u0005\u001dB\u0001\"b\u0001)\n\u0019A+M\u001a\u0002\u0007}\u000bD\'\u0006\u0002\u0002.A\u0019\u0011+a\f\u0005\u000f\u0005EB\u0001\"b\u0001)\n\u0019A+\r\u001b\u0002\u0007}\u000bT\'\u0006\u0002\u00028A\u0019\u0011+!\u000f\u0005\u000f\u0005mB\u0001\"b\u0001)\n\u0019A+M\u001b\u0002\u0007}\u000bd\'\u0006\u0002\u0002BA\u0019\u0011+a\u0011\u0005\u000f\u0005\u0015C\u0001\"b\u0001)\n\u0019A+\r\u001c\u0011\u0007E\u000bI\u0005B\u0003T\u0007\t\u0007A\u000bE\u0002R\u0003\u001b\"Q\u0001X\u0002C\u0002Q\u00032!UA)\t\u0015\t7A1\u0001U!\r\t\u0016Q\u000b\u0003\u0006M\u000e\u0011\r\u0001\u0016\t\u0004#\u0006eC!B6\u0004\u0005\u0004!\u0006cA)\u0002^\u0011)\u0001o\u0001b\u0001)B\u0019\u0011+!\u0019\u0005\u000bU\u001c!\u0019\u0001+\u0011\u0007E\u000b)\u0007B\u0003{\u0007\t\u0007A\u000bE\u0002R\u0003S\"Qa`\u0002C\u0002Q\u00032!UA7\t\u0019\tIa\u0001b\u0001)B\u0019\u0011+!\u001d\u0005\r\u0005M1A1\u0001U!\r\t\u0016Q\u000f\u0003\u0007\u0003;\u0019!\u0019\u0001+\u0011\u0007E\u000bI\b\u0002\u0004\u0002(\r\u0011\r\u0001\u0016\t\u0004#\u0006uDABA\u0019\u0007\t\u0007A\u000bE\u0002R\u0003\u0003#a!a\u000f\u0004\u0005\u0004!\u0006cA)\u0002\u0006\u00121\u0011QI\u0002C\u0002QCa!!#\u0004\u0001\u0004Y\u0013!\u0001="
    )
  ScalaInlineInfo: length = 0x6D (unknown attribute)
   01 00 00 15 00 86 00 87 01 00 2F 00 30 00 00 4B
   00 30 00 00 4E 00 30 00 00 51 00 30 00 00 54 00
   30 00 00 57 00 30 00 00 5A 00 30 00 00 5D 00 30
   00 00 33 00 30 00 00 36 00 30 00 00 39 00 30 00
   00 3C 00 30 00 00 3F 00 30 00 00 42 00 30 00 00
   45 00 30 00 00 48 00 30 00 00 20 00 21 00 00 1D
   00 1E 01 00 28 00 29 00 00 25 00 26 01
  ScalaSig: length = 0x3 (unknown attribute)
   05 02 00
