Classfile /Users/mw/Projects/slang-braindump/.jar/jar11/assemble/slang-braindump/assemble/content/scala/ScalaReflectionException.class
  Last modified May 29, 2022; size 5741 bytes
  SHA-256 checksum 2caea6545a170cc670d03bba34d6d985620d1c51ccb6c783086aa0bf6948a748
  Compiled from "package.scala"
public class scala.ScalaReflectionException extends java.lang.Exception implements scala.Product
  minor version: 0
  major version: 52
  flags: (0x0021) ACC_PUBLIC, ACC_SUPER
  this_class: #2                          // scala/ScalaReflectionException
  super_class: #4                         // java/lang/Exception
  interfaces: 1, fields: 1, methods: 18, attributes: 6
Constant pool:
    #1 = Utf8               scala/ScalaReflectionException
    #2 = Class              #1            // scala/ScalaReflectionException
    #3 = Utf8               java/lang/Exception
    #4 = Class              #3            // java/lang/Exception
    #5 = Utf8               scala/Product
    #6 = Class              #5            // scala/Product
    #7 = Utf8               package.scala
    #8 = Utf8               Lscala/reflect/ScalaSignature;
    #9 = Utf8               bytes
   #10 = Utf8               \u0006\u0005\u0005=b\u0001B\u000b\u0017\u0001fA\u0001B\f\u0001\u0003\u0016\u0004%\ta\f\u0005\tq\u0001\u0011\t\u0012)A\u0005a!)\u0011\b\u0001C\u0001u!9Q\bAA\u0001\n\u0003q\u0004b\u0002!\u0001#\u0003%\t!\u0011\u0005\b\u0019\u0002\t\t\u0011\"\u0011N\u0011\u001d)\u0006!!A\u0005\u0002YCqA\u0017\u0001\u0002\u0002\u0013\u00051\fC\u0004b\u0001\u0005\u0005I\u0011\t2\t\u000f%\u0004\u0011\u0011!C\u0001U\"9q\u000eAA\u0001\n\u0003\u0002\bb\u0002:\u0001\u0003\u0003%\te\u001d\u0005\bi\u0002\t\t\u0011\"\u0011v\u000f\u001d9h#!A\t\u0002a4q!\u0006\f\u0002\u0002#\u0005\u0011\u0010\u0003\u0004:\u001f\u0011\u0005\u00111\u0002\u0005\n\u0003\u001by\u0011\u0011!C#\u0003\u001fA\u0011\"!\u0005\u0010\u0003\u0003%\t)a\u0005\t\u0013\u0005]q\"!A\u0005\u0002\u0006e\u0001\"CA\u0013\u001f\u0005\u0005I\u0011BA\u0014\u0005a\u00196-\u00197b%\u00164G.Z2uS>tW\t_2faRLwN\u001c\u0006\u0002/\u0005)1oY1mC\u000e\u00011\u0003\u0002\u0001\u001bE\u0015\u0002\"aG\u0010\u000f\u0005qiR\"\u0001\f\n\u0005y1\u0012a\u00029bG.\fw-Z\u0005\u0003A\u0005\u0012\u0011\"\u0012=dKB$\u0018n\u001c8\u000b\u0005y1\u0002C\u0001\u000f$\u0013\t!cCA\u0004Qe>$Wo\u0019;\u0011\u0005\u0019bcBA\u0014\u001e\u001d\tA3&D\u0001*\u0015\tQ\u0003$\u0001\u0004=e>|GOP\u0005\u0002/%\u0011Q&\t\u0002\r\'\u0016\u0014\u0018.\u00197ju\u0006\u0014G.Z\u0001\u0004[N<W#\u0001\u0019\u0011\u0005E*dB\u0001\u001a4!\tAc#\u0003\u00025-\u00051\u0001K]3eK\u001aL!AN\u001c\u0003\rM#(/\u001b8h\u0015\t!d#\u0001\u0003ng\u001e\u0004\u0013A\u0002\u001fj]&$h\b\u0006\u0002<yA\u0011A\u0004\u0001\u0005\u0006]\r\u0001\r\u0001M\u0001\u0005G>\u0004\u0018\u0010\u0006\u0002<\u007f!9a\u0006\u0002I\u0001\u0002\u0004\u0001\u0014AD2paf$C-\u001a4bk2$H%M\u000b\u0002\u0005*\u0012\u0001gQ\u0016\u0002\tB\u0011QIS\u0007\u0002\r*\u0011q\tS\u0001\nk:\u001c\u0007.Z2lK\u0012T!!\u0013\f\u0002\u0015\u0005tgn\u001c;bi&|g.\u0003\u0002L\r\n\tRO\\2iK\u000e\\W\r\u001a,be&\fgnY3\u0002\u001bA\u0014x\u000eZ;diB\u0013XMZ5y+\u0005q\u0005CA(U\u001b\u0005\u0001&BA)S\u0003\u0011a\u0017M\\4\u000b\u0003M\u000bAA[1wC&\u0011a\u0007U\u0001\raJ|G-^2u\u0003JLG/_\u000b\u0002/B\u0011A\u0004W\u0005\u00033Z\u00111!\u00138u\u00039\u0001(o\u001c3vGR,E.Z7f]R$\"\u0001X0\u0011\u0005qi\u0016B\u00010\u0017\u0005\r\te.\u001f\u0005\bA\"\t\t\u00111\u0001X\u0003\rAH%M\u0001\u0010aJ|G-^2u\u0013R,\'/\u0019;peV\t1\rE\u0002eOrk\u0011!\u001a\u0006\u0003MZ\t!bY8mY\u0016\u001cG/[8o\u0013\tAWM\u0001\u0005Ji\u0016\u0014\u0018\r^8s\u0003!\u0019\u0017M\\#rk\u0006dGCA6o!\taB.\u0003\u0002n-\t9!i\\8mK\u0006t\u0007b\u00021\u000b\u0003\u0003\u0005\r\u0001X\u0001\u0013aJ|G-^2u\u000b2,W.\u001a8u\u001d\u0006lW\r\u0006\u0002Oc\"9\u0001mCA\u0001\u0002\u00049\u0016\u0001\u00035bg\"\u001cu\u000eZ3\u0015\u0003]\u000ba!Z9vC2\u001cHCA6w\u0011\u001d\u0001W\"!AA\u0002q\u000b\u0001dU2bY\u0006\u0014VM\u001a7fGRLwN\\#yG\u0016\u0004H/[8o!\tarb\u0005\u0003\u0010u\u0006\u0005\u0001\u0003B>\u007famj\u0011\u0001 \u0006\u0003{Z\tqA];oi&lW-\u0003\u0002\u0000y\n\t\u0012IY:ue\u0006\u001cGOR;oGRLwN\\\u0019\u0011\t\u0005\r\u0011\u0011B\u0007\u0003\u0003\u000bQ1!a\u0002S\u0003\tIw.C\u0002.\u0003\u000b!\u0012\u0001_\u0001\ti>\u001cFO]5oOR\ta*A\u0003baBd\u0017\u0010F\u0002<\u0003+AQA\f\nA\u0002A\nq!\u001e8baBd\u0017\u0010\u0006\u0003\u0002\u001c\u0005\u0005\u0002\u0003\u0002\u000f\u0002\u001eAJ1!a\b\u0017\u0005\u0019y\u0005\u000f^5p]\"A\u00111E\n\u0002\u0002\u0003\u00071(A\u0002yIA\nAb\u001e:ji\u0016\u0014V\r\u001d7bG\u0016$\"!!\u000b\u0011\u0007=\u000bY#C\u0002\u0002.A\u0013aa\u00142kK\u000e$\b
   #11 = Utf8               java/lang/invoke/MethodHandles$Lookup
   #12 = Class              #11           // java/lang/invoke/MethodHandles$Lookup
   #13 = Utf8               java/lang/invoke/MethodHandles
   #14 = Class              #13           // java/lang/invoke/MethodHandles
   #15 = Utf8               Lookup
   #16 = Utf8               scala/runtime/ScalaRunTime$$anon$1
   #17 = Class              #16           // scala/runtime/ScalaRunTime$$anon$1
   #18 = Utf8               msg
   #19 = Utf8               Ljava/lang/String;
   #20 = Utf8               unapply
   #21 = Utf8               (Lscala/ScalaReflectionException;)Lscala/Option;
   #22 = Utf8               (Lscala/ScalaReflectionException;)Lscala/Option<Ljava/lang/String;>;
   #23 = Utf8               x$0
   #24 = Utf8               scala/ScalaReflectionException$
   #25 = Class              #24           // scala/ScalaReflectionException$
   #26 = Utf8               MODULE$
   #27 = Utf8               Lscala/ScalaReflectionException$;
   #28 = NameAndType        #26:#27       // MODULE$:Lscala/ScalaReflectionException$;
   #29 = Fieldref           #25.#28       // scala/ScalaReflectionException$.MODULE$:Lscala/ScalaReflectionException$;
   #30 = NameAndType        #20:#21       // unapply:(Lscala/ScalaReflectionException;)Lscala/Option;
   #31 = Methodref          #25.#30       // scala/ScalaReflectionException$.unapply:(Lscala/ScalaReflectionException;)Lscala/Option;
   #32 = Utf8               Lscala/ScalaReflectionException;
   #33 = Utf8               apply
   #34 = Utf8               (Ljava/lang/String;)Lscala/ScalaReflectionException;
   #35 = Utf8               <init>
   #36 = Utf8               (Ljava/lang/String;)V
   #37 = NameAndType        #35:#36       // "<init>":(Ljava/lang/String;)V
   #38 = Methodref          #2.#37        // scala/ScalaReflectionException."<init>":(Ljava/lang/String;)V
   #39 = Utf8               andThen
   #40 = Utf8               (Lscala/Function1;)Lscala/Function1;
   #41 = Utf8               <A$:Ljava/lang/Object;>(Lscala/Function1<Lscala/ScalaReflectionException;TA$;>;)Lscala/Function1<Ljava/lang/String;TA$;>;
   #42 = Utf8               g
   #43 = Utf8               (Ljava/lang/Object;)Ljava/lang/Object;
   #44 = MethodType         #43           //  (Ljava/lang/Object;)Ljava/lang/Object;
   #45 = Utf8               scala/Function1
   #46 = Class              #45           // scala/Function1
   #47 = Utf8               $anonfun$andThen$1
   #48 = Utf8               (Lscala/Function1;Lscala/Function1;Ljava/lang/Object;)Ljava/lang/Object;
   #49 = NameAndType        #47:#48       // $anonfun$andThen$1:(Lscala/Function1;Lscala/Function1;Ljava/lang/Object;)Ljava/lang/Object;
   #50 = InterfaceMethodref #46.#49       // scala/Function1.$anonfun$andThen$1:(Lscala/Function1;Lscala/Function1;Ljava/lang/Object;)Ljava/lang/Object;
   #51 = MethodHandle       6:#50         // REF_invokeStatic scala/Function1.$anonfun$andThen$1:(Lscala/Function1;Lscala/Function1;Ljava/lang/Object;)Ljava/lang/Object;
   #52 = Integer            1
   #53 = Utf8               java/lang/invoke/LambdaMetafactory
   #54 = Class              #53           // java/lang/invoke/LambdaMetafactory
   #55 = Utf8               altMetafactory
   #56 = Utf8               (Ljava/lang/invoke/MethodHandles$Lookup;Ljava/lang/String;Ljava/lang/invoke/MethodType;[Ljava/lang/Object;)Ljava/lang/invoke/CallSite;
   #57 = NameAndType        #55:#56       // altMetafactory:(Ljava/lang/invoke/MethodHandles$Lookup;Ljava/lang/String;Ljava/lang/invoke/MethodType;[Ljava/lang/Object;)Ljava/lang/invoke/CallSite;
   #58 = Methodref          #54.#57       // java/lang/invoke/LambdaMetafactory.altMetafactory:(Ljava/lang/invoke/MethodHandles$Lookup;Ljava/lang/String;Ljava/lang/invoke/MethodType;[Ljava/lang/Object;)Ljava/lang/invoke/CallSite;
   #59 = MethodHandle       6:#58         // REF_invokeStatic java/lang/invoke/LambdaMetafactory.altMetafactory:(Ljava/lang/invoke/MethodHandles$Lookup;Ljava/lang/String;Ljava/lang/invoke/MethodType;[Ljava/lang/Object;)Ljava/lang/invoke/CallSite;
   #60 = Utf8               (Lscala/Function1;Lscala/Function1;)Lscala/Function1;
   #61 = NameAndType        #33:#60       // apply:(Lscala/Function1;Lscala/Function1;)Lscala/Function1;
   #62 = InvokeDynamic      #0:#61        // #0:apply:(Lscala/Function1;Lscala/Function1;)Lscala/Function1;
   #63 = Utf8               Lscala/Function1;
   #64 = Utf8               compose
   #65 = Utf8               <A$:Ljava/lang/Object;>(Lscala/Function1<TA$;Ljava/lang/String;>;)Lscala/Function1<TA$;Lscala/ScalaReflectionException;>;
   #66 = Utf8               $anonfun$compose$1
   #67 = NameAndType        #66:#48       // $anonfun$compose$1:(Lscala/Function1;Lscala/Function1;Ljava/lang/Object;)Ljava/lang/Object;
   #68 = InterfaceMethodref #46.#67       // scala/Function1.$anonfun$compose$1:(Lscala/Function1;Lscala/Function1;Ljava/lang/Object;)Ljava/lang/Object;
   #69 = MethodHandle       6:#68         // REF_invokeStatic scala/Function1.$anonfun$compose$1:(Lscala/Function1;Lscala/Function1;Ljava/lang/Object;)Ljava/lang/Object;
   #70 = InvokeDynamic      #1:#61        // #1:apply:(Lscala/Function1;Lscala/Function1;)Lscala/Function1;
   #71 = Utf8               productElementNames
   #72 = Utf8               ()Lscala/collection/Iterator;
   #73 = Utf8               ()Lscala/collection/Iterator<Ljava/lang/String;>;
   #74 = Utf8               productElementNames$
   #75 = Utf8               (Lscala/Product;)Lscala/collection/Iterator;
   #76 = NameAndType        #74:#75       // productElementNames$:(Lscala/Product;)Lscala/collection/Iterator;
   #77 = InterfaceMethodref #6.#76        // scala/Product.productElementNames$:(Lscala/Product;)Lscala/collection/Iterator;
   #78 = Utf8               this
   #79 = Utf8               ()Ljava/lang/String;
   #80 = NameAndType        #18:#19       // msg:Ljava/lang/String;
   #81 = Fieldref           #2.#80        // scala/ScalaReflectionException.msg:Ljava/lang/String;
   #82 = Utf8               copy
   #83 = Utf8               copy$default$1
   #84 = NameAndType        #18:#79       // msg:()Ljava/lang/String;
   #85 = Methodref          #2.#84        // scala/ScalaReflectionException.msg:()Ljava/lang/String;
   #86 = Utf8               productPrefix
   #87 = Utf8               ScalaReflectionException
   #88 = String             #87           // ScalaReflectionException
   #89 = Utf8               productArity
   #90 = Utf8               ()I
   #91 = Utf8               productElement
   #92 = Utf8               (I)Ljava/lang/Object;
   #93 = Utf8               x$1
   #94 = Utf8               scala/runtime/Statics
   #95 = Class              #94           // scala/runtime/Statics
   #96 = Utf8               ioobe
   #97 = NameAndType        #96:#92       // ioobe:(I)Ljava/lang/Object;
   #98 = Methodref          #95.#97       // scala/runtime/Statics.ioobe:(I)Ljava/lang/Object;
   #99 = Utf8               I
  #100 = Utf8               productIterator
  #101 = Utf8               ()Lscala/collection/Iterator<Ljava/lang/Object;>;
  #102 = Utf8               (Lscala/Product;)V
  #103 = NameAndType        #35:#102      // "<init>":(Lscala/Product;)V
  #104 = Methodref          #17.#103      // scala/runtime/ScalaRunTime$$anon$1."<init>":(Lscala/Product;)V
  #105 = Utf8               canEqual
  #106 = Utf8               (Ljava/lang/Object;)Z
  #107 = Utf8               Ljava/lang/Object;
  #108 = Utf8               productElementName
  #109 = Utf8               (I)Ljava/lang/String;
  #110 = String             #18           // msg
  #111 = Utf8               java/lang/String
  #112 = Class              #111          // java/lang/String
  #113 = Utf8               hashCode
  #114 = Utf8               scala/util/hashing/MurmurHash3$
  #115 = Class              #114          // scala/util/hashing/MurmurHash3$
  #116 = Utf8               Lscala/util/hashing/MurmurHash3$;
  #117 = NameAndType        #26:#116      // MODULE$:Lscala/util/hashing/MurmurHash3$;
  #118 = Fieldref           #115.#117     // scala/util/hashing/MurmurHash3$.MODULE$:Lscala/util/hashing/MurmurHash3$;
  #119 = Utf8               productHash
  #120 = Utf8               (Lscala/Product;)I
  #121 = NameAndType        #119:#120     // productHash:(Lscala/Product;)I
  #122 = Methodref          #115.#121     // scala/util/hashing/MurmurHash3$.productHash:(Lscala/Product;)I
  #123 = Utf8               equals
  #124 = Utf8               java/lang/Object
  #125 = Class              #124          // java/lang/Object
  #126 = NameAndType        #123:#106     // equals:(Ljava/lang/Object;)Z
  #127 = Methodref          #125.#126     // java/lang/Object.equals:(Ljava/lang/Object;)Z
  #128 = NameAndType        #105:#106     // canEqual:(Ljava/lang/Object;)Z
  #129 = Methodref          #2.#128       // scala/ScalaReflectionException.canEqual:(Ljava/lang/Object;)Z
  #130 = Methodref          #4.#37        // java/lang/Exception."<init>":(Ljava/lang/String;)V
  #131 = Utf8               $deserializeLambda$
  #132 = Utf8               (Ljava/lang/invoke/SerializedLambda;)Ljava/lang/Object;
  #133 = Utf8               scala/runtime/LambdaDeserialize
  #134 = Class              #133          // scala/runtime/LambdaDeserialize
  #135 = Utf8               bootstrap
  #136 = Utf8               (Ljava/lang/invoke/MethodHandles$Lookup;Ljava/lang/String;Ljava/lang/invoke/MethodType;[Ljava/lang/invoke/MethodHandle;)Ljava/lang/invoke/CallSite;
  #137 = NameAndType        #135:#136     // bootstrap:(Ljava/lang/invoke/MethodHandles$Lookup;Ljava/lang/String;Ljava/lang/invoke/MethodType;[Ljava/lang/invoke/MethodHandle;)Ljava/lang/invoke/CallSite;
  #138 = Methodref          #134.#137     // scala/runtime/LambdaDeserialize.bootstrap:(Ljava/lang/invoke/MethodHandles$Lookup;Ljava/lang/String;Ljava/lang/invoke/MethodType;[Ljava/lang/invoke/MethodHandle;)Ljava/lang/invoke/CallSite;
  #139 = MethodHandle       6:#138        // REF_invokeStatic scala/runtime/LambdaDeserialize.bootstrap:(Ljava/lang/invoke/MethodHandles$Lookup;Ljava/lang/String;Ljava/lang/invoke/MethodType;[Ljava/lang/invoke/MethodHandle;)Ljava/lang/invoke/CallSite;
  #140 = Utf8               lambdaDeserialize
  #141 = NameAndType        #140:#132     // lambdaDeserialize:(Ljava/lang/invoke/SerializedLambda;)Ljava/lang/Object;
  #142 = InvokeDynamic      #2:#141       // #2:lambdaDeserialize:(Ljava/lang/invoke/SerializedLambda;)Ljava/lang/Object;
  #143 = Utf8               Code
  #144 = Utf8               LocalVariableTable
  #145 = Utf8               Signature
  #146 = Utf8               MethodParameters
  #147 = Utf8               LineNumberTable
  #148 = Utf8               StackMapTable
  #149 = Utf8               InnerClasses
  #150 = Utf8               SourceFile
  #151 = Utf8               RuntimeVisibleAnnotations
  #152 = Utf8               BootstrapMethods
  #153 = Utf8               ScalaInlineInfo
  #154 = Utf8               ScalaSig
{
  private final java.lang.String msg;
    descriptor: Ljava/lang/String;
    flags: (0x0012) ACC_PRIVATE, ACC_FINAL

  public static scala.Option<java.lang.String> unapply(scala.ScalaReflectionException);
    descriptor: (Lscala/ScalaReflectionException;)Lscala/Option;
    flags: (0x0009) ACC_PUBLIC, ACC_STATIC
    Code:
      stack=2, locals=1, args_size=1
         0: getstatic     #29                 // Field scala/ScalaReflectionException$.MODULE$:Lscala/ScalaReflectionException$;
         3: aload_0
         4: invokevirtual #31                 // Method scala/ScalaReflectionException$.unapply:(Lscala/ScalaReflectionException;)Lscala/Option;
         7: areturn
      LocalVariableTable:
        Start  Length  Slot  Name   Signature
            0       8     0   x$0   Lscala/ScalaReflectionException;
    Signature: #22                          // (Lscala/ScalaReflectionException;)Lscala/Option<Ljava/lang/String;>;
    MethodParameters:
      Name                           Flags
      x$0                            final

  public static scala.ScalaReflectionException apply(java.lang.String);
    descriptor: (Ljava/lang/String;)Lscala/ScalaReflectionException;
    flags: (0x0009) ACC_PUBLIC, ACC_STATIC
    Code:
      stack=3, locals=1, args_size=1
         0: getstatic     #29                 // Field scala/ScalaReflectionException$.MODULE$:Lscala/ScalaReflectionException$;
         3: pop
         4: new           #2                  // class scala/ScalaReflectionException
         7: dup
         8: aload_0
         9: invokespecial #38                 // Method "<init>":(Ljava/lang/String;)V
        12: areturn
      LineNumberTable:
        line 76: 4
      LocalVariableTable:
        Start  Length  Slot  Name   Signature
            0      13     0   msg   Ljava/lang/String;
    MethodParameters:
      Name                           Flags
      msg                            final

  public static <A$ extends java.lang.Object> scala.Function1<java.lang.String, A$> andThen(scala.Function1<scala.ScalaReflectionException, A$>);
    descriptor: (Lscala/Function1;)Lscala/Function1;
    flags: (0x0009) ACC_PUBLIC, ACC_STATIC
    Code:
      stack=2, locals=1, args_size=1
         0: getstatic     #29                 // Field scala/ScalaReflectionException$.MODULE$:Lscala/ScalaReflectionException$;
         3: aload_0
         4: invokedynamic #62,  0             // InvokeDynamic #0:apply:(Lscala/Function1;Lscala/Function1;)Lscala/Function1;
         9: areturn
      LocalVariableTable:
        Start  Length  Slot  Name   Signature
            0      10     0     g   Lscala/Function1;
    Signature: #41                          // <A$:Ljava/lang/Object;>(Lscala/Function1<Lscala/ScalaReflectionException;TA$;>;)Lscala/Function1<Ljava/lang/String;TA$;>;
    MethodParameters:
      Name                           Flags
      g                              final

  public static <A$ extends java.lang.Object> scala.Function1<A$, scala.ScalaReflectionException> compose(scala.Function1<A$, java.lang.String>);
    descriptor: (Lscala/Function1;)Lscala/Function1;
    flags: (0x0009) ACC_PUBLIC, ACC_STATIC
    Code:
      stack=2, locals=1, args_size=1
         0: getstatic     #29                 // Field scala/ScalaReflectionException$.MODULE$:Lscala/ScalaReflectionException$;
         3: aload_0
         4: invokedynamic #70,  0             // InvokeDynamic #1:apply:(Lscala/Function1;Lscala/Function1;)Lscala/Function1;
         9: areturn
      LocalVariableTable:
        Start  Length  Slot  Name   Signature
            0      10     0     g   Lscala/Function1;
    Signature: #65                          // <A$:Ljava/lang/Object;>(Lscala/Function1<TA$;Ljava/lang/String;>;)Lscala/Function1<TA$;Lscala/ScalaReflectionException;>;
    MethodParameters:
      Name                           Flags
      g                              final

  public scala.collection.Iterator<java.lang.String> productElementNames();
    descriptor: ()Lscala/collection/Iterator;
    flags: (0x0001) ACC_PUBLIC
    Code:
      stack=1, locals=1, args_size=1
         0: aload_0
         1: invokestatic  #77                 // InterfaceMethod scala/Product.productElementNames$:(Lscala/Product;)Lscala/collection/Iterator;
         4: areturn
      LineNumberTable:
        line 76: 0
      LocalVariableTable:
        Start  Length  Slot  Name   Signature
            0       5     0  this   Lscala/ScalaReflectionException;
    Signature: #73                          // ()Lscala/collection/Iterator<Ljava/lang/String;>;

  public java.lang.String msg();
    descriptor: ()Ljava/lang/String;
    flags: (0x0001) ACC_PUBLIC
    Code:
      stack=1, locals=1, args_size=1
         0: aload_0
         1: getfield      #81                 // Field msg:Ljava/lang/String;
         4: areturn
      LineNumberTable:
        line 76: 0
      LocalVariableTable:
        Start  Length  Slot  Name   Signature
            0       5     0  this   Lscala/ScalaReflectionException;

  public scala.ScalaReflectionException copy(java.lang.String);
    descriptor: (Ljava/lang/String;)Lscala/ScalaReflectionException;
    flags: (0x0001) ACC_PUBLIC
    Code:
      stack=3, locals=2, args_size=2
         0: new           #2                  // class scala/ScalaReflectionException
         3: dup
         4: aload_1
         5: invokespecial #38                 // Method "<init>":(Ljava/lang/String;)V
         8: areturn
      LineNumberTable:
        line 76: 0
      LocalVariableTable:
        Start  Length  Slot  Name   Signature
            0       9     0  this   Lscala/ScalaReflectionException;
            0       9     1   msg   Ljava/lang/String;
    MethodParameters:
      Name                           Flags
      msg                            final

  public java.lang.String copy$default$1();
    descriptor: ()Ljava/lang/String;
    flags: (0x0001) ACC_PUBLIC
    Code:
      stack=1, locals=1, args_size=1
         0: aload_0
         1: invokevirtual #85                 // Method msg:()Ljava/lang/String;
         4: areturn
      LineNumberTable:
        line 76: 0
      LocalVariableTable:
        Start  Length  Slot  Name   Signature
            0       5     0  this   Lscala/ScalaReflectionException;

  public java.lang.String productPrefix();
    descriptor: ()Ljava/lang/String;
    flags: (0x0001) ACC_PUBLIC
    Code:
      stack=1, locals=1, args_size=1
         0: ldc           #88                 // String ScalaReflectionException
         2: areturn
      LineNumberTable:
        line 76: 0
      LocalVariableTable:
        Start  Length  Slot  Name   Signature
            0       3     0  this   Lscala/ScalaReflectionException;

  public int productArity();
    descriptor: ()I
    flags: (0x0001) ACC_PUBLIC
    Code:
      stack=1, locals=1, args_size=1
         0: iconst_1
         1: ireturn
      LineNumberTable:
        line 76: 0
      LocalVariableTable:
        Start  Length  Slot  Name   Signature
            0       2     0  this   Lscala/ScalaReflectionException;

  public java.lang.Object productElement(int);
    descriptor: (I)Ljava/lang/Object;
    flags: (0x0001) ACC_PUBLIC
    Code:
      stack=1, locals=2, args_size=2
         0: iload_1
         1: tableswitch   { // 0 to 0
                       0: 20
                 default: 25
            }
        20: aload_0
        21: invokevirtual #85                 // Method msg:()Ljava/lang/String;
        24: areturn
        25: iload_1
        26: invokestatic  #98                 // Method scala/runtime/Statics.ioobe:(I)Ljava/lang/Object;
        29: areturn
      StackMapTable: number_of_entries = 2
        frame_type = 20 /* same */
        frame_type = 4 /* same */
      LineNumberTable:
        line 76: 0
      LocalVariableTable:
        Start  Length  Slot  Name   Signature
            0      30     0  this   Lscala/ScalaReflectionException;
            0      30     1   x$1   I
    MethodParameters:
      Name                           Flags
      x$1                            final

  public scala.collection.Iterator<java.lang.Object> productIterator();
    descriptor: ()Lscala/collection/Iterator;
    flags: (0x0001) ACC_PUBLIC
    Code:
      stack=3, locals=1, args_size=1
         0: new           #17                 // class scala/runtime/ScalaRunTime$$anon$1
         3: dup
         4: aload_0
         5: invokespecial #104                // Method scala/runtime/ScalaRunTime$$anon$1."<init>":(Lscala/Product;)V
         8: areturn
      LineNumberTable:
        line 76: 0
      LocalVariableTable:
        Start  Length  Slot  Name   Signature
            0       9     0  this   Lscala/ScalaReflectionException;
    Signature: #101                         // ()Lscala/collection/Iterator<Ljava/lang/Object;>;

  public boolean canEqual(java.lang.Object);
    descriptor: (Ljava/lang/Object;)Z
    flags: (0x0001) ACC_PUBLIC
    Code:
      stack=1, locals=2, args_size=2
         0: aload_1
         1: instanceof    #2                  // class scala/ScalaReflectionException
         4: ireturn
      LineNumberTable:
        line 76: 0
      LocalVariableTable:
        Start  Length  Slot  Name   Signature
            0       5     0  this   Lscala/ScalaReflectionException;
            0       5     1   x$1   Ljava/lang/Object;
    MethodParameters:
      Name                           Flags
      x$1                            final

  public java.lang.String productElementName(int);
    descriptor: (I)Ljava/lang/String;
    flags: (0x0001) ACC_PUBLIC
    Code:
      stack=1, locals=2, args_size=2
         0: iload_1
         1: tableswitch   { // 0 to 0
                       0: 20
                 default: 23
            }
        20: ldc           #110                // String msg
        22: areturn
        23: iload_1
        24: invokestatic  #98                 // Method scala/runtime/Statics.ioobe:(I)Ljava/lang/Object;
        27: checkcast     #112                // class java/lang/String
        30: areturn
      StackMapTable: number_of_entries = 2
        frame_type = 20 /* same */
        frame_type = 2 /* same */
      LineNumberTable:
        line 76: 0
      LocalVariableTable:
        Start  Length  Slot  Name   Signature
            0      31     0  this   Lscala/ScalaReflectionException;
            0      31     1   x$1   I
    MethodParameters:
      Name                           Flags
      x$1                            final

  public int hashCode();
    descriptor: ()I
    flags: (0x0001) ACC_PUBLIC
    Code:
      stack=2, locals=1, args_size=1
         0: getstatic     #118                // Field scala/util/hashing/MurmurHash3$.MODULE$:Lscala/util/hashing/MurmurHash3$;
         3: aload_0
         4: invokevirtual #122                // Method scala/util/hashing/MurmurHash3$.productHash:(Lscala/Product;)I
         7: ireturn
      LineNumberTable:
        line 76: 0
      LocalVariableTable:
        Start  Length  Slot  Name   Signature
            0       8     0  this   Lscala/ScalaReflectionException;

  public boolean equals(java.lang.Object);
    descriptor: (Ljava/lang/Object;)Z
    flags: (0x0001) ACC_PUBLIC
    Code:
      stack=2, locals=5, args_size=2
         0: aload_0
         1: aload_1
         2: if_acmpeq     75
         5: aload_1
         6: instanceof    #2                  // class scala/ScalaReflectionException
         9: ifeq          17
        12: iconst_1
        13: istore_2
        14: goto          19
        17: iconst_0
        18: istore_2
        19: iload_2
        20: ifeq          77
        23: aload_1
        24: checkcast     #2                  // class scala/ScalaReflectionException
        27: astore_3
        28: aload_0
        29: invokevirtual #85                 // Method msg:()Ljava/lang/String;
        32: aload_3
        33: invokevirtual #85                 // Method msg:()Ljava/lang/String;
        36: astore        4
        38: dup
        39: ifnonnull     51
        42: pop
        43: aload         4
        45: ifnull        59
        48: goto          71
        51: aload         4
        53: invokevirtual #127                // Method java/lang/Object.equals:(Ljava/lang/Object;)Z
        56: ifeq          71
        59: aload_3
        60: aload_0
        61: invokevirtual #129                // Method canEqual:(Ljava/lang/Object;)Z
        64: ifeq          71
        67: iconst_1
        68: goto          72
        71: iconst_0
        72: ifeq          77
        75: iconst_1
        76: ireturn
        77: iconst_0
        78: ireturn
      StackMapTable: number_of_entries = 8
        frame_type = 17 /* same */
        frame_type = 252 /* append */
          offset_delta = 1
          locals = [ int ]
        frame_type = 255 /* full_frame */
          offset_delta = 31
          locals = [ class scala/ScalaReflectionException, class java/lang/Object, int, class scala/ScalaReflectionException, class java/lang/String ]
          stack = [ class java/lang/String ]
        frame_type = 7 /* same */
        frame_type = 11 /* same */
        frame_type = 64 /* same_locals_1_stack_item */
          stack = [ int ]
        frame_type = 248 /* chop */
          offset_delta = 2
        frame_type = 252 /* append */
          offset_delta = 1
          locals = [ int ]
      LineNumberTable:
        line 76: 0
      LocalVariableTable:
        Start  Length  Slot  Name   Signature
            0      79     0  this   Lscala/ScalaReflectionException;
            0      79     1   x$1   Ljava/lang/Object;
    MethodParameters:
      Name                           Flags
      x$1                            final

  public scala.ScalaReflectionException(java.lang.String);
    descriptor: (Ljava/lang/String;)V
    flags: (0x0001) ACC_PUBLIC
    Code:
      stack=2, locals=2, args_size=2
         0: aload_0
         1: aload_1
         2: putfield      #81                 // Field msg:Ljava/lang/String;
         5: aload_0
         6: aload_1
         7: invokespecial #130                // Method java/lang/Exception."<init>":(Ljava/lang/String;)V
        10: return
      LineNumberTable:
        line 76: 0
      LocalVariableTable:
        Start  Length  Slot  Name   Signature
            0      11     0  this   Lscala/ScalaReflectionException;
            0      11     1   msg   Ljava/lang/String;
    MethodParameters:
      Name                           Flags
      msg                            final

  private static java.lang.Object $deserializeLambda$(java.lang.invoke.SerializedLambda);
    descriptor: (Ljava/lang/invoke/SerializedLambda;)Ljava/lang/Object;
    flags: (0x100a) ACC_PRIVATE, ACC_STATIC, ACC_SYNTHETIC
    Code:
      stack=1, locals=1, args_size=1
         0: aload_0
         1: invokedynamic #142,  0            // InvokeDynamic #2:lambdaDeserialize:(Ljava/lang/invoke/SerializedLambda;)Ljava/lang/Object;
         6: areturn
}
InnerClasses:
  public static final #15= #12 of #14;    // Lookup=class java/lang/invoke/MethodHandles$Lookup of class java/lang/invoke/MethodHandles
  public final #17;                       // class scala/runtime/ScalaRunTime$$anon$1
SourceFile: "package.scala"
RuntimeVisibleAnnotations:
  0: #8(#9=s#10)
    scala.reflect.ScalaSignature(
      bytes="\u0006\u0005\u0005=b\u0001B\u000b\u0017\u0001fA\u0001B\f\u0001\u0003\u0016\u0004%\ta\f\u0005\tq\u0001\u0011\t\u0012)A\u0005a!)\u0011\b\u0001C\u0001u!9Q\bAA\u0001\n\u0003q\u0004b\u0002!\u0001#\u0003%\t!\u0011\u0005\b\u0019\u0002\t\t\u0011\"\u0011N\u0011\u001d)\u0006!!A\u0005\u0002YCqA\u0017\u0001\u0002\u0002\u0013\u00051\fC\u0004b\u0001\u0005\u0005I\u0011\t2\t\u000f%\u0004\u0011\u0011!C\u0001U\"9q\u000eAA\u0001\n\u0003\u0002\bb\u0002:\u0001\u0003\u0003%\te\u001d\u0005\bi\u0002\t\t\u0011\"\u0011v\u000f\u001d9h#!A\t\u0002a4q!\u0006\f\u0002\u0002#\u0005\u0011\u0010\u0003\u0004:\u001f\u0011\u0005\u00111\u0002\u0005\n\u0003\u001by\u0011\u0011!C#\u0003\u001fA\u0011\"!\u0005\u0010\u0003\u0003%\t)a\u0005\t\u0013\u0005]q\"!A\u0005\u0002\u0006e\u0001\"CA\u0013\u001f\u0005\u0005I\u0011BA\u0014\u0005a\u00196-\u00197b%\u00164G.Z2uS>tW\t_2faRLwN\u001c\u0006\u0002/\u0005)1oY1mC\u000e\u00011\u0003\u0002\u0001\u001bE\u0015\u0002\"aG\u0010\u000f\u0005qiR\"\u0001\f\n\u0005y1\u0012a\u00029bG.\fw-Z\u0005\u0003A\u0005\u0012\u0011\"\u0012=dKB$\u0018n\u001c8\u000b\u0005y1\u0002C\u0001\u000f$\u0013\t!cCA\u0004Qe>$Wo\u0019;\u0011\u0005\u0019bcBA\u0014\u001e\u001d\tA3&D\u0001*\u0015\tQ\u0003$\u0001\u0004=e>|GOP\u0005\u0002/%\u0011Q&\t\u0002\r\'\u0016\u0014\u0018.\u00197ju\u0006\u0014G.Z\u0001\u0004[N<W#\u0001\u0019\u0011\u0005E*dB\u0001\u001a4!\tAc#\u0003\u00025-\u00051\u0001K]3eK\u001aL!AN\u001c\u0003\rM#(/\u001b8h\u0015\t!d#\u0001\u0003ng\u001e\u0004\u0013A\u0002\u001fj]&$h\b\u0006\u0002<yA\u0011A\u0004\u0001\u0005\u0006]\r\u0001\r\u0001M\u0001\u0005G>\u0004\u0018\u0010\u0006\u0002<\u007f!9a\u0006\u0002I\u0001\u0002\u0004\u0001\u0014AD2paf$C-\u001a4bk2$H%M\u000b\u0002\u0005*\u0012\u0001gQ\u0016\u0002\tB\u0011QIS\u0007\u0002\r*\u0011q\tS\u0001\nk:\u001c\u0007.Z2lK\u0012T!!\u0013\f\u0002\u0015\u0005tgn\u001c;bi&|g.\u0003\u0002L\r\n\tRO\\2iK\u000e\\W\r\u001a,be&\fgnY3\u0002\u001bA\u0014x\u000eZ;diB\u0013XMZ5y+\u0005q\u0005CA(U\u001b\u0005\u0001&BA)S\u0003\u0011a\u0017M\\4\u000b\u0003M\u000bAA[1wC&\u0011a\u0007U\u0001\raJ|G-^2u\u0003JLG/_\u000b\u0002/B\u0011A\u0004W\u0005\u00033Z\u00111!\u00138u\u00039\u0001(o\u001c3vGR,E.Z7f]R$\"\u0001X0\u0011\u0005qi\u0016B\u00010\u0017\u0005\r\te.\u001f\u0005\bA\"\t\t\u00111\u0001X\u0003\rAH%M\u0001\u0010aJ|G-^2u\u0013R,\'/\u0019;peV\t1\rE\u0002eOrk\u0011!\u001a\u0006\u0003MZ\t!bY8mY\u0016\u001cG/[8o\u0013\tAWM\u0001\u0005Ji\u0016\u0014\u0018\r^8s\u0003!\u0019\u0017M\\#rk\u0006dGCA6o!\taB.\u0003\u0002n-\t9!i\\8mK\u0006t\u0007b\u00021\u000b\u0003\u0003\u0005\r\u0001X\u0001\u0013aJ|G-^2u\u000b2,W.\u001a8u\u001d\u0006lW\r\u0006\u0002Oc\"9\u0001mCA\u0001\u0002\u00049\u0016\u0001\u00035bg\"\u001cu\u000eZ3\u0015\u0003]\u000ba!Z9vC2\u001cHCA6w\u0011\u001d\u0001W\"!AA\u0002q\u000b\u0001dU2bY\u0006\u0014VM\u001a7fGRLwN\\#yG\u0016\u0004H/[8o!\tarb\u0005\u0003\u0010u\u0006\u0005\u0001\u0003B>\u007famj\u0011\u0001 \u0006\u0003{Z\tqA];oi&lW-\u0003\u0002\u0000y\n\t\u0012IY:ue\u0006\u001cGOR;oGRLwN\\\u0019\u0011\t\u0005\r\u0011\u0011B\u0007\u0003\u0003\u000bQ1!a\u0002S\u0003\tIw.C\u0002.\u0003\u000b!\u0012\u0001_\u0001\ti>\u001cFO]5oOR\ta*A\u0003baBd\u0017\u0010F\u0002<\u0003+AQA\f\nA\u0002A\nq!\u001e8baBd\u0017\u0010\u0006\u0003\u0002\u001c\u0005\u0005\u0002\u0003\u0002\u000f\u0002\u001eAJ1!a\b\u0017\u0005\u0019y\u0005\u000f^5p]\"A\u00111E\n\u0002\u0002\u0003\u00071(A\u0002yIA\nAb\u001e:ji\u0016\u0014V\r\u001d7bG\u0016$\"!!\u000b\u0011\u0007=\u000bY#C\u0002\u0002.A\u0013aa\u00142kK\u000e$\b"
    )
BootstrapMethods:
  0: #59 REF_invokeStatic java/lang/invoke/LambdaMetafactory.altMetafactory:(Ljava/lang/invoke/MethodHandles$Lookup;Ljava/lang/String;Ljava/lang/invoke/MethodType;[Ljava/lang/Object;)Ljava/lang/invoke/CallSite;
    Method arguments:
      #44 (Ljava/lang/Object;)Ljava/lang/Object;
      #51 REF_invokeStatic scala/Function1.$anonfun$andThen$1:(Lscala/Function1;Lscala/Function1;Ljava/lang/Object;)Ljava/lang/Object;
      #44 (Ljava/lang/Object;)Ljava/lang/Object;
      #52 1
  1: #59 REF_invokeStatic java/lang/invoke/LambdaMetafactory.altMetafactory:(Ljava/lang/invoke/MethodHandles$Lookup;Ljava/lang/String;Ljava/lang/invoke/MethodType;[Ljava/lang/Object;)Ljava/lang/invoke/CallSite;
    Method arguments:
      #44 (Ljava/lang/Object;)Ljava/lang/Object;
      #69 REF_invokeStatic scala/Function1.$anonfun$compose$1:(Lscala/Function1;Lscala/Function1;Ljava/lang/Object;)Ljava/lang/Object;
      #44 (Ljava/lang/Object;)Ljava/lang/Object;
      #52 1
  2: #139 REF_invokeStatic scala/runtime/LambdaDeserialize.bootstrap:(Ljava/lang/invoke/MethodHandles$Lookup;Ljava/lang/String;Ljava/lang/invoke/MethodType;[Ljava/lang/invoke/MethodHandle;)Ljava/lang/invoke/CallSite;
    Method arguments:
      #51 REF_invokeStatic scala/Function1.$anonfun$andThen$1:(Lscala/Function1;Lscala/Function1;Ljava/lang/Object;)Ljava/lang/Object;
      #69 REF_invokeStatic scala/Function1.$anonfun$compose$1:(Lscala/Function1;Lscala/Function1;Ljava/lang/Object;)Ljava/lang/Object;
  ScalaInlineInfo: length = 0x45 (unknown attribute)
   01 00 00 0D 00 23 00 24 00 00 69 00 6A 00 00 52
   00 22 00 00 53 00 4F 00 00 7B 00 6A 00 00 71 00
   5A 00 00 12 00 4F 00 00 59 00 5A 00 00 5B 00 5C
   00 00 6C 00 6D 00 00 47 00 48 00 00 64 00 48 00
   00 56 00 4F 00
  ScalaSig: length = 0x3 (unknown attribute)
   05 02 00
