Classfile /Users/mw/Projects/slang-braindump/.jar/jar11/assemble/slang-braindump/assemble/content/scala/Specializable$Group.class
  Last modified May 29, 2022; size 682 bytes
  SHA-256 checksum f0dcab6749820193bf1ebe2f56f6954f0a466f78c1d6ba22b48fcfa1041e1834
  Compiled from "Specializable.scala"
public class scala.Specializable$Group<T extends java.lang.Object> extends java.lang.Object implements scala.Specializable$SpecializedGroup
  minor version: 0
  major version: 52
  flags: (0x0021) ACC_PUBLIC, ACC_SUPER
  this_class: #2                          // scala/Specializable$Group
  super_class: #5                         // java/lang/Object
  interfaces: 1, fields: 0, methods: 1, attributes: 5
Constant pool:
   #1 = Utf8               scala/Specializable$Group
   #2 = Class              #1             // scala/Specializable$Group
   #3 = Utf8               <T:Ljava/lang/Object;>Ljava/lang/Object;Lscala/Specializable$SpecializedGroup;
   #4 = Utf8               java/lang/Object
   #5 = Class              #4             // java/lang/Object
   #6 = Utf8               scala/Specializable$SpecializedGroup
   #7 = Class              #6             // scala/Specializable$SpecializedGroup
   #8 = Utf8               Specializable.scala
   #9 = Utf8               scala/Specializable
  #10 = Class              #9             // scala/Specializable
  #11 = Utf8               Group
  #12 = Utf8               SpecializedGroup
  #13 = Utf8               <init>
  #14 = Utf8               (Ljava/lang/Object;)V
  #15 = Utf8               (TT;)V
  #16 = Utf8               value
  #17 = Utf8               ()V
  #18 = NameAndType        #13:#17        // "<init>":()V
  #19 = Methodref          #5.#18         // java/lang/Object."<init>":()V
  #20 = Utf8               this
  #21 = Utf8               Lscala/Specializable$Group;
  #22 = Utf8               Ljava/lang/Object;
  #23 = Utf8               Code
  #24 = Utf8               LineNumberTable
  #25 = Utf8               LocalVariableTable
  #26 = Utf8               Signature
  #27 = Utf8               MethodParameters
  #28 = Utf8               InnerClasses
  #29 = Utf8               SourceFile
  #30 = Utf8               ScalaInlineInfo
  #31 = Utf8               Scala
{
  public scala.Specializable$Group(T);
    descriptor: (Ljava/lang/Object;)V
    flags: (0x0001) ACC_PUBLIC
    Code:
      stack=1, locals=2, args_size=2
         0: aload_0
         1: invokespecial #19                 // Method java/lang/Object."<init>":()V
         4: return
      LineNumberTable:
        line 25: 0
      LocalVariableTable:
        Start  Length  Slot  Name   Signature
            0       5     0  this   Lscala/Specializable$Group;
            0       5     1 value   Ljava/lang/Object;
    Signature: #15                          // (TT;)V
    MethodParameters:
      Name                           Flags
      value                          final
}
InnerClasses:
  public static #11= #2 of #10;           // Group=class scala/Specializable$Group of class scala/Specializable
  public static #12= #7 of #10;           // SpecializedGroup=class scala/Specializable$SpecializedGroup of class scala/Specializable
Signature: #3                           // <T:Ljava/lang/Object;>Ljava/lang/Object;Lscala/Specializable$SpecializedGroup;
SourceFile: "Specializable.scala"
  ScalaInlineInfo: length = 0x9 (unknown attribute)
   01 00 00 01 00 0D 00 0E 00
  Scala: length = 0x0 (unknown attribute)

