Classfile /Users/mw/Projects/slang-braindump/.jar/jar11/assemble/slang-braindump/assemble/content/scala/Tuple3.class
  Last modified May 29, 2022; size 6481 bytes
  SHA-256 checksum 7ef9fe45918c2fed0512993b374d4ccd6e060ad972512b7e64672f2b7623e326
  Compiled from "Tuple3.scala"
public final class scala.Tuple3<T1 extends java.lang.Object, T2 extends java.lang.Object, T3 extends java.lang.Object> extends java.lang.Object implements scala.Product3<T1, T2, T3>, java.io.Serializable
  minor version: 0
  major version: 52
  flags: (0x0031) ACC_PUBLIC, ACC_FINAL, ACC_SUPER
  this_class: #2                          // scala/Tuple3
  super_class: #5                         // java/lang/Object
  interfaces: 2, fields: 3, methods: 20, attributes: 6
Constant pool:
    #1 = Utf8               scala/Tuple3
    #2 = Class              #1            // scala/Tuple3
    #3 = Utf8               <T1:Ljava/lang/Object;T2:Ljava/lang/Object;T3:Ljava/lang/Object;>Ljava/lang/Object;Lscala/Product3<TT1;TT2;TT3;>;Ljava/io/Serializable;
    #4 = Utf8               java/lang/Object
    #5 = Class              #4            // java/lang/Object
    #6 = Utf8               scala/Product3
    #7 = Class              #6            // scala/Product3
    #8 = Utf8               java/io/Serializable
    #9 = Class              #8            // java/io/Serializable
   #10 = Utf8               Tuple3.scala
   #11 = Utf8               Lscala/reflect/ScalaSignature;
   #12 = Utf8               bytes
   #13 = Utf8               \u0006\u0005\u0005Mf\u0001\u0002\u000e\u001c\u0005zA\u0001b\u0012\u0001\u0003\u0016\u0004%\t\u0001\u0013\u0005\t\u0013\u0002\u0011\t\u0012)A\u0005O!A!\n\u0001BK\u0002\u0013\u00051\n\u0003\u0005M\u0001\tE\t\u0015!\u00033\u0011!i\u0005A!f\u0001\n\u0003q\u0005\u0002C(\u0001\u0005#\u0005\u000b\u0011B\u001b\t\u000bA\u0003A\u0011A)\t\u000bY\u0003A\u0011I,\t\u000f\u0001\u0004\u0011\u0011!C\u0001C\"9Q\u000eAI\u0001\n\u0003q\u0007bB?\u0001#\u0003%\tA \u0005\n\u0003\u0013\u0001\u0011\u0013!C\u0001\u0003\u0017A\u0011\"a\u0006\u0001\u0003\u0003%\t%!\u0007\t\u0013\u0005%\u0002!!A\u0005B\u0005-\u0002\"CA\u001d\u0001\u0005\u0005I\u0011AA\u001e\u0011%\t9\u0005AA\u0001\n\u0003\nI\u0005C\u0005\u0002T\u0001\t\t\u0011\"\u0011\u0002V!I\u0011q\u000b\u0001\u0002\u0002\u0013\u0005\u0013\u0011L\u0004\n\u0003;Z\u0012\u0011!E\u0001\u0003?2\u0001BG\u000e\u0002\u0002#\u0005\u0011\u0011\r\u0005\u0007!R!\t!!\u001c\t\u0011Y#\u0012\u0011!C#\u0003_B\u0011\"!\u001d\u0015\u0003\u0003%\t)a\u001d\t\u0013\u0005-E#!A\u0005\u0002\u00065\u0005\"CAU)\u0005\u0005I\u0011BAV\u0005\u0019!V\u000f\u001d7fg)\tA$A\u0003tG\u0006d\u0017m\u0001\u0001\u0016\t}I3GN\n\u0006\u0001\u0001\"\u0003h\u000f\t\u0003C\tj\u0011aG\u0005\u0003Gm\u0011a!\u00118z%\u00164\u0007#B\u0011&OI*\u0014B\u0001\u0014\u001c\u0005!\u0001&o\u001c3vGR\u001c\u0004C\u0001\u0015*\u0019\u0001!aA\u000b\u0001\u0005\u0006\u0004Y#A\u0001+2#\tas\u0006\u0005\u0002\"[%\u0011af\u0007\u0002\b\u001d>$\b.\u001b8h!\t\t\u0003\'\u0003\u000227\t\u0019\u0011I\\=\u0011\u0005!\u001aDA\u0002\u001b\u0001\t\u000b\u00071F\u0001\u0002UeA\u0011\u0001F\u000e\u0003\u0007o\u0001!)\u0019A\u0016\u0003\u0005Q\u001b\u0004CA\u0011:\u0013\tQ4DA\u0004Qe>$Wo\u0019;\u0011\u0005q\"eBA\u001fC\u001d\tq\u0014)D\u0001@\u0015\t\u0001U$\u0001\u0004=e>|GOP\u0005\u00029%\u00111iG\u0001\ba\u0006\u001c7.Y4f\u0013\t)eI\u0001\u0007TKJL\u0017\r\\5{C\ndWM\u0003\u0002D7\u0005\u0011q,M\u000b\u0002O\u0005\u0019q,\r\u0011\u0002\u0005}\u0013T#\u0001\u001a\u0002\u0007}\u0013\u0004%\u0001\u0002`gU\tQ\'A\u0002`g\u0001\na\u0001P5oSRtD\u0003\u0002*T)V\u0003R!\t\u0001(eUBQaR\u0004A\u0002\u001dBQAS\u0004A\u0002IBQ!T\u0004A\u0002U\n\u0001\u0002^8TiJLgn\u001a\u000b\u00021B\u0011\u0011,\u0018\b\u00035n\u0003\"AP\u000e\n\u0005q[\u0012A\u0002)sK\u0012,g-\u0003\u0002_?\n11\u000b\u001e:j]\u001eT!\u0001X\u000e\u0002\t\r|\u0007/_\u000b\u0005E\u0016<\u0017\u000e\u0006\u0003dU.d\u0007#B\u0011\u0001I\u001aD\u0007C\u0001\u0015f\t\u0015Q\u0013B1\u0001,!\tAs\rB\u00035\u0013\t\u00071\u0006\u0005\u0002)S\u0012)q\'\u0003b\u0001W!9q)\u0003I\u0001\u0002\u0004!\u0007b\u0002&\n!\u0003\u0005\rA\u001a\u0005\b\u001b&\u0001\n\u00111\u0001i\u00039\u0019w\u000e]=%I\u00164\u0017-\u001e7uIE*Ba\u001c>|yV\t\u0001O\u000b\u0002(c.\n!\u000f\u0005\u0002tq6\tAO\u0003\u0002vm\u0006IQO\\2iK\u000e\\W\r\u001a\u0006\u0003on\t!\"\u00198o_R\fG/[8o\u0013\tIHOA\tv]\u000eDWmY6fIZ\u000b\'/[1oG\u0016$QA\u000b\u0006C\u0002-\"Q\u0001\u000e\u0006C\u0002-\"Qa\u000e\u0006C\u0002-\nabY8qs\u0012\"WMZ1vYR$#\'F\u0004\u0000\u0003\u0007\t)!a\u0002\u0016\u0005\u0005\u0005!F\u0001\u001ar\t\u0015Q3B1\u0001,\t\u0015!4B1\u0001,\t\u001594B1\u0001,\u00039\u0019w\u000e]=%I\u00164\u0017-\u001e7uIM*\u0002\"!\u0004\u0002\u0012\u0005M\u0011QC\u000b\u0003\u0003\u001fQ#!N9\u0005\u000b)b!\u0019A\u0016\u0005\u000bQb!\u0019A\u0016\u0005\u000b]b!\u0019A\u0016\u0002\u001bA\u0014x\u000eZ;diB\u0013XMZ5y+\t\tY\u0002\u0005\u0003\u0002\u001e\u0005\u001dRBAA\u0010\u0015\u0011\t\t#a\t\u0002\t1\fgn\u001a\u0006\u0003\u0003K\tAA[1wC&\u0019a,a\b\u0002\u001fA\u0014x\u000eZ;di&#XM]1u_J,\"!!\f\u0011\u000b\u0005=\u0012QG\u0018\u000e\u0005\u0005E\"bAA\u001a7\u0005Q1m\u001c7mK\u000e$\u0018n\u001c8\n\t\u0005]\u0012\u0011\u0007\u0002\t\u0013R,\'/\u0019;pe\u0006A1-\u00198FcV\fG\u000e\u0006\u0003\u0002>\u0005\r\u0003cA\u0011\u0002@%\u0019\u0011\u0011I\u000e\u0003\u000f\t{w\u000e\\3b]\"A\u0011QI\b\u0002\u0002\u0003\u0007q&A\u0002yIE\n!\u0003\u001d:pIV\u001cG/\u00127f[\u0016tGOT1nKR!\u00111DA&\u0011%\t)\u0005EA\u0001\u0002\u0004\ti\u0005E\u0002\"\u0003\u001fJ1!!\u0015\u001c\u0005\rIe\u000e^\u0001\tQ\u0006\u001c\bnQ8eKR\u0011\u0011QJ\u0001\u0007KF,\u0018\r\\:\u0015\t\u0005u\u00121\f\u0005\t\u0003\u000b\u0012\u0012\u0011!a\u0001_\u00051A+\u001e9mKN\u0002\"!\t\u000b\u0014\tQ\u0001\u00131\r\t\u0005\u0003K\nY\'\u0004\u0002\u0002h)!\u0011\u0011NA\u0012\u0003\tIw.C\u0002F\u0003O\"\"!a\u0018\u0015\u0005\u0005m\u0011!B1qa2LX\u0003CA;\u0003w\ny(a!\u0015\u0011\u0005]\u0014QQAD\u0003\u0013\u0003\u0002\"\t\u0001\u0002z\u0005u\u0014\u0011\u0011\t\u0004Q\u0005mD!\u0002\u0016\u0018\u0005\u0004Y\u0003c\u0001\u0015\u0002\u0000\u0011)Ag\u0006b\u0001WA\u0019\u0001&a!\u0005\u000b]:\"\u0019A\u0016\t\r\u001d;\u0002\u0019AA=\u0011\u0019Qu\u00031\u0001\u0002~!1Qj\u0006a\u0001\u0003\u0003\u000bq!\u001e8baBd\u00170\u0006\u0005\u0002\u0010\u0006m\u0015qTAR)\u0011\t\t*!*\u0011\u000b\u0005\n\u0019*a&\n\u0007\u0005U5D\u0001\u0004PaRLwN\u001c\t\tC\u0001\tI*!(\u0002\"B\u0019\u0001&a\'\u0005\u000b)B\"\u0019A\u0016\u0011\u0007!\ny\nB\u000351\t\u00071\u0006E\u0002)\u0003G#Qa\u000e\rC\u0002-B\u0011\"a*\u0019\u0003\u0003\u0005\r!a&\u0002\u0007a$\u0003\'\u0001\u0007xe&$XMU3qY\u0006\u001cW\r\u0006\u0002\u0002.B!\u0011QDAX\u0013\u0011\t\t,a\b\u0003\r=\u0013\'.Z2u\u0001
   #14 = Utf8               scala/runtime/ScalaRunTime$$anon$1
   #15 = Class              #14           // scala/runtime/ScalaRunTime$$anon$1
   #16 = Utf8               _1
   #17 = Utf8               Ljava/lang/Object;
   #18 = Utf8               TT1;
   #19 = Utf8               _2
   #20 = Utf8               TT2;
   #21 = Utf8               _3
   #22 = Utf8               TT3;
   #23 = Utf8               unapply
   #24 = Utf8               (Lscala/Tuple3;)Lscala/Option;
   #25 = Utf8               <T1:Ljava/lang/Object;T2:Ljava/lang/Object;T3:Ljava/lang/Object;>(Lscala/Tuple3<TT1;TT2;TT3;>;)Lscala/Option<Lscala/Tuple3<TT1;TT2;TT3;>;>;
   #26 = Utf8               x$0
   #27 = Utf8               scala/Tuple3$
   #28 = Class              #27           // scala/Tuple3$
   #29 = Utf8               MODULE$
   #30 = Utf8               Lscala/Tuple3$;
   #31 = NameAndType        #29:#30       // MODULE$:Lscala/Tuple3$;
   #32 = Fieldref           #28.#31       // scala/Tuple3$.MODULE$:Lscala/Tuple3$;
   #33 = NameAndType        #23:#24       // unapply:(Lscala/Tuple3;)Lscala/Option;
   #34 = Methodref          #28.#33       // scala/Tuple3$.unapply:(Lscala/Tuple3;)Lscala/Option;
   #35 = Utf8               Lscala/Tuple3;
   #36 = Utf8               apply
   #37 = Utf8               (Ljava/lang/Object;Ljava/lang/Object;Ljava/lang/Object;)Lscala/Tuple3;
   #38 = Utf8               <T1:Ljava/lang/Object;T2:Ljava/lang/Object;T3:Ljava/lang/Object;>(TT1;TT2;TT3;)Lscala/Tuple3<TT1;TT2;TT3;>;
   #39 = Utf8               <init>
   #40 = Utf8               (Ljava/lang/Object;Ljava/lang/Object;Ljava/lang/Object;)V
   #41 = NameAndType        #39:#40       // "<init>":(Ljava/lang/Object;Ljava/lang/Object;Ljava/lang/Object;)V
   #42 = Methodref          #2.#41        // scala/Tuple3."<init>":(Ljava/lang/Object;Ljava/lang/Object;Ljava/lang/Object;)V
   #43 = Utf8               productArity
   #44 = Utf8               ()I
   #45 = Utf8               productArity$
   #46 = Utf8               (Lscala/Product3;)I
   #47 = NameAndType        #45:#46       // productArity$:(Lscala/Product3;)I
   #48 = InterfaceMethodref #7.#47        // scala/Product3.productArity$:(Lscala/Product3;)I
   #49 = Utf8               this
   #50 = Utf8               productElement
   #51 = Utf8               (I)Ljava/lang/Object;
   #52 = Utf8               java/lang/IndexOutOfBoundsException
   #53 = Class              #52           // java/lang/IndexOutOfBoundsException
   #54 = Utf8               n
   #55 = Utf8               productElement$
   #56 = Utf8               (Lscala/Product3;I)Ljava/lang/Object;
   #57 = NameAndType        #55:#56       // productElement$:(Lscala/Product3;I)Ljava/lang/Object;
   #58 = InterfaceMethodref #7.#57        // scala/Product3.productElement$:(Lscala/Product3;I)Ljava/lang/Object;
   #59 = Utf8               I
   #60 = Utf8               productElementNames
   #61 = Utf8               ()Lscala/collection/Iterator;
   #62 = Utf8               ()Lscala/collection/Iterator<Ljava/lang/String;>;
   #63 = Utf8               scala/Product
   #64 = Class              #63           // scala/Product
   #65 = Utf8               productElementNames$
   #66 = Utf8               (Lscala/Product;)Lscala/collection/Iterator;
   #67 = NameAndType        #65:#66       // productElementNames$:(Lscala/Product;)Lscala/collection/Iterator;
   #68 = InterfaceMethodref #64.#67       // scala/Product.productElementNames$:(Lscala/Product;)Lscala/collection/Iterator;
   #69 = Utf8               ()Ljava/lang/Object;
   #70 = Utf8               ()TT1;
   #71 = NameAndType        #16:#17       // _1:Ljava/lang/Object;
   #72 = Fieldref           #2.#71        // scala/Tuple3._1:Ljava/lang/Object;
   #73 = Utf8               ()TT2;
   #74 = NameAndType        #19:#17       // _2:Ljava/lang/Object;
   #75 = Fieldref           #2.#74        // scala/Tuple3._2:Ljava/lang/Object;
   #76 = Utf8               ()TT3;
   #77 = NameAndType        #21:#17       // _3:Ljava/lang/Object;
   #78 = Fieldref           #2.#77        // scala/Tuple3._3:Ljava/lang/Object;
   #79 = Utf8               toString
   #80 = Utf8               ()Ljava/lang/String;
   #81 = Utf8               java/lang/StringBuilder
   #82 = Class              #81           // java/lang/StringBuilder
   #83 = Integer            4
   #84 = Utf8               (I)V
   #85 = NameAndType        #39:#84       // "<init>":(I)V
   #86 = Methodref          #82.#85       // java/lang/StringBuilder."<init>":(I)V
   #87 = Utf8               (
   #88 = String             #87           // (
   #89 = Utf8               append
   #90 = Utf8               (Ljava/lang/String;)Ljava/lang/StringBuilder;
   #91 = NameAndType        #89:#90       // append:(Ljava/lang/String;)Ljava/lang/StringBuilder;
   #92 = Methodref          #82.#91       // java/lang/StringBuilder.append:(Ljava/lang/String;)Ljava/lang/StringBuilder;
   #93 = NameAndType        #16:#69       // _1:()Ljava/lang/Object;
   #94 = Methodref          #2.#93        // scala/Tuple3._1:()Ljava/lang/Object;
   #95 = Utf8               (Ljava/lang/Object;)Ljava/lang/StringBuilder;
   #96 = NameAndType        #89:#95       // append:(Ljava/lang/Object;)Ljava/lang/StringBuilder;
   #97 = Methodref          #82.#96       // java/lang/StringBuilder.append:(Ljava/lang/Object;)Ljava/lang/StringBuilder;
   #98 = Utf8               ,
   #99 = String             #98           // ,
  #100 = NameAndType        #19:#69       // _2:()Ljava/lang/Object;
  #101 = Methodref          #2.#100       // scala/Tuple3._2:()Ljava/lang/Object;
  #102 = NameAndType        #21:#69       // _3:()Ljava/lang/Object;
  #103 = Methodref          #2.#102       // scala/Tuple3._3:()Ljava/lang/Object;
  #104 = Utf8               )
  #105 = String             #104          // )
  #106 = NameAndType        #79:#80       // toString:()Ljava/lang/String;
  #107 = Methodref          #82.#106      // java/lang/StringBuilder.toString:()Ljava/lang/String;
  #108 = Utf8               copy
  #109 = Utf8               copy$default$1
  #110 = Utf8               <T1:Ljava/lang/Object;T2:Ljava/lang/Object;T3:Ljava/lang/Object;>()TT1;
  #111 = Utf8               copy$default$2
  #112 = Utf8               <T1:Ljava/lang/Object;T2:Ljava/lang/Object;T3:Ljava/lang/Object;>()TT2;
  #113 = Utf8               copy$default$3
  #114 = Utf8               <T1:Ljava/lang/Object;T2:Ljava/lang/Object;T3:Ljava/lang/Object;>()TT3;
  #115 = Utf8               productPrefix
  #116 = Utf8               Tuple3
  #117 = String             #116          // Tuple3
  #118 = Utf8               productIterator
  #119 = Utf8               ()Lscala/collection/Iterator<Ljava/lang/Object;>;
  #120 = Utf8               (Lscala/Product;)V
  #121 = NameAndType        #39:#120      // "<init>":(Lscala/Product;)V
  #122 = Methodref          #15.#121      // scala/runtime/ScalaRunTime$$anon$1."<init>":(Lscala/Product;)V
  #123 = Utf8               canEqual
  #124 = Utf8               (Ljava/lang/Object;)Z
  #125 = Utf8               x$1
  #126 = Utf8               productElementName
  #127 = Utf8               (I)Ljava/lang/String;
  #128 = String             #16           // _1
  #129 = String             #19           // _2
  #130 = String             #21           // _3
  #131 = Utf8               scala/runtime/Statics
  #132 = Class              #131          // scala/runtime/Statics
  #133 = Utf8               ioobe
  #134 = NameAndType        #133:#51      // ioobe:(I)Ljava/lang/Object;
  #135 = Methodref          #132.#134     // scala/runtime/Statics.ioobe:(I)Ljava/lang/Object;
  #136 = Utf8               java/lang/String
  #137 = Class              #136          // java/lang/String
  #138 = Utf8               hashCode
  #139 = Utf8               scala/util/hashing/MurmurHash3$
  #140 = Class              #139          // scala/util/hashing/MurmurHash3$
  #141 = Utf8               Lscala/util/hashing/MurmurHash3$;
  #142 = NameAndType        #29:#141      // MODULE$:Lscala/util/hashing/MurmurHash3$;
  #143 = Fieldref           #140.#142     // scala/util/hashing/MurmurHash3$.MODULE$:Lscala/util/hashing/MurmurHash3$;
  #144 = Utf8               productHash
  #145 = Utf8               (Lscala/Product;)I
  #146 = NameAndType        #144:#145     // productHash:(Lscala/Product;)I
  #147 = Methodref          #140.#146     // scala/util/hashing/MurmurHash3$.productHash:(Lscala/Product;)I
  #148 = Utf8               equals
  #149 = Utf8               scala/runtime/BoxesRunTime
  #150 = Class              #149          // scala/runtime/BoxesRunTime
  #151 = Utf8               (Ljava/lang/Object;Ljava/lang/Object;)Z
  #152 = NameAndType        #148:#151     // equals:(Ljava/lang/Object;Ljava/lang/Object;)Z
  #153 = Methodref          #150.#152     // scala/runtime/BoxesRunTime.equals:(Ljava/lang/Object;Ljava/lang/Object;)Z
  #154 = Utf8               (TT1;TT2;TT3;)V
  #155 = Utf8               ()V
  #156 = NameAndType        #39:#155      // "<init>":()V
  #157 = Methodref          #5.#156       // java/lang/Object."<init>":()V
  #158 = Utf8               Signature
  #159 = Utf8               Code
  #160 = Utf8               LocalVariableTable
  #161 = Utf8               MethodParameters
  #162 = Utf8               LineNumberTable
  #163 = Utf8               Exceptions
  #164 = Utf8               StackMapTable
  #165 = Utf8               InnerClasses
  #166 = Utf8               SourceFile
  #167 = Utf8               RuntimeVisibleAnnotations
  #168 = Utf8               ScalaInlineInfo
  #169 = Utf8               ScalaSig
{
  private final T1 _1;
    descriptor: Ljava/lang/Object;
    flags: (0x0012) ACC_PRIVATE, ACC_FINAL
    Signature: #18                          // TT1;

  private final T2 _2;
    descriptor: Ljava/lang/Object;
    flags: (0x0012) ACC_PRIVATE, ACC_FINAL
    Signature: #20                          // TT2;

  private final T3 _3;
    descriptor: Ljava/lang/Object;
    flags: (0x0012) ACC_PRIVATE, ACC_FINAL
    Signature: #22                          // TT3;

  public static <T1 extends java.lang.Object, T2 extends java.lang.Object, T3 extends java.lang.Object> scala.Option<scala.Tuple3<T1, T2, T3>> unapply(scala.Tuple3<T1, T2, T3>);
    descriptor: (Lscala/Tuple3;)Lscala/Option;
    flags: (0x0009) ACC_PUBLIC, ACC_STATIC
    Code:
      stack=2, locals=1, args_size=1
         0: getstatic     #32                 // Field scala/Tuple3$.MODULE$:Lscala/Tuple3$;
         3: aload_0
         4: invokevirtual #34                 // Method scala/Tuple3$.unapply:(Lscala/Tuple3;)Lscala/Option;
         7: areturn
      LocalVariableTable:
        Start  Length  Slot  Name   Signature
            0       8     0   x$0   Lscala/Tuple3;
    Signature: #25                          // <T1:Ljava/lang/Object;T2:Ljava/lang/Object;T3:Ljava/lang/Object;>(Lscala/Tuple3<TT1;TT2;TT3;>;)Lscala/Option<Lscala/Tuple3<TT1;TT2;TT3;>;>;
    MethodParameters:
      Name                           Flags
      x$0                            final

  public static <T1 extends java.lang.Object, T2 extends java.lang.Object, T3 extends java.lang.Object> scala.Tuple3<T1, T2, T3> apply(T1, T2, T3);
    descriptor: (Ljava/lang/Object;Ljava/lang/Object;Ljava/lang/Object;)Lscala/Tuple3;
    flags: (0x0009) ACC_PUBLIC, ACC_STATIC
    Code:
      stack=5, locals=3, args_size=3
         0: getstatic     #32                 // Field scala/Tuple3$.MODULE$:Lscala/Tuple3$;
         3: pop
         4: new           #2                  // class scala/Tuple3
         7: dup
         8: aload_0
         9: aload_1
        10: aload_2
        11: invokespecial #42                 // Method "<init>":(Ljava/lang/Object;Ljava/lang/Object;Ljava/lang/Object;)V
        14: areturn
      LineNumberTable:
        line 25: 4
      LocalVariableTable:
        Start  Length  Slot  Name   Signature
            0      15     0    _1   Ljava/lang/Object;
            0      15     1    _2   Ljava/lang/Object;
            0      15     2    _3   Ljava/lang/Object;
    Signature: #38                          // <T1:Ljava/lang/Object;T2:Ljava/lang/Object;T3:Ljava/lang/Object;>(TT1;TT2;TT3;)Lscala/Tuple3<TT1;TT2;TT3;>;
    MethodParameters:
      Name                           Flags
      _1                             final
      _2                             final
      _3                             final

  public int productArity();
    descriptor: ()I
    flags: (0x0001) ACC_PUBLIC
    Code:
      stack=1, locals=1, args_size=1
         0: aload_0
         1: invokestatic  #48                 // InterfaceMethod scala/Product3.productArity$:(Lscala/Product3;)I
         4: ireturn
      LineNumberTable:
        line 25: 0
      LocalVariableTable:
        Start  Length  Slot  Name   Signature
            0       5     0  this   Lscala/Tuple3;

  public java.lang.Object productElement(int) throws java.lang.IndexOutOfBoundsException;
    descriptor: (I)Ljava/lang/Object;
    flags: (0x0001) ACC_PUBLIC
    Code:
      stack=2, locals=2, args_size=2
         0: aload_0
         1: iload_1
         2: invokestatic  #58                 // InterfaceMethod scala/Product3.productElement$:(Lscala/Product3;I)Ljava/lang/Object;
         5: areturn
      LineNumberTable:
        line 25: 0
      LocalVariableTable:
        Start  Length  Slot  Name   Signature
            0       6     0  this   Lscala/Tuple3;
            0       6     1     n   I
    Exceptions:
      throws java.lang.IndexOutOfBoundsException
    MethodParameters:
      Name                           Flags
      n                              final

  public scala.collection.Iterator<java.lang.String> productElementNames();
    descriptor: ()Lscala/collection/Iterator;
    flags: (0x0001) ACC_PUBLIC
    Code:
      stack=1, locals=1, args_size=1
         0: aload_0
         1: invokestatic  #68                 // InterfaceMethod scala/Product.productElementNames$:(Lscala/Product;)Lscala/collection/Iterator;
         4: areturn
      LineNumberTable:
        line 25: 0
      LocalVariableTable:
        Start  Length  Slot  Name   Signature
            0       5     0  this   Lscala/Tuple3;
    Signature: #62                          // ()Lscala/collection/Iterator<Ljava/lang/String;>;

  public T1 _1();
    descriptor: ()Ljava/lang/Object;
    flags: (0x0001) ACC_PUBLIC
    Code:
      stack=1, locals=1, args_size=1
         0: aload_0
         1: getfield      #72                 // Field _1:Ljava/lang/Object;
         4: areturn
      LineNumberTable:
        line 25: 0
      LocalVariableTable:
        Start  Length  Slot  Name   Signature
            0       5     0  this   Lscala/Tuple3;
    Signature: #70                          // ()TT1;

  public T2 _2();
    descriptor: ()Ljava/lang/Object;
    flags: (0x0001) ACC_PUBLIC
    Code:
      stack=1, locals=1, args_size=1
         0: aload_0
         1: getfield      #75                 // Field _2:Ljava/lang/Object;
         4: areturn
      LineNumberTable:
        line 25: 0
      LocalVariableTable:
        Start  Length  Slot  Name   Signature
            0       5     0  this   Lscala/Tuple3;
    Signature: #73                          // ()TT2;

  public T3 _3();
    descriptor: ()Ljava/lang/Object;
    flags: (0x0001) ACC_PUBLIC
    Code:
      stack=1, locals=1, args_size=1
         0: aload_0
         1: getfield      #78                 // Field _3:Ljava/lang/Object;
         4: areturn
      LineNumberTable:
        line 25: 0
      LocalVariableTable:
        Start  Length  Slot  Name   Signature
            0       5     0  this   Lscala/Tuple3;
    Signature: #76                          // ()TT3;

  public java.lang.String toString();
    descriptor: ()Ljava/lang/String;
    flags: (0x0001) ACC_PUBLIC
    Code:
      stack=3, locals=1, args_size=1
         0: new           #82                 // class java/lang/StringBuilder
         3: dup
         4: ldc           #83                 // int 4
         6: invokespecial #86                 // Method java/lang/StringBuilder."<init>":(I)V
         9: ldc           #88                 // String (
        11: invokevirtual #92                 // Method java/lang/StringBuilder.append:(Ljava/lang/String;)Ljava/lang/StringBuilder;
        14: aload_0
        15: invokevirtual #94                 // Method _1:()Ljava/lang/Object;
        18: invokevirtual #97                 // Method java/lang/StringBuilder.append:(Ljava/lang/Object;)Ljava/lang/StringBuilder;
        21: ldc           #99                 // String ,
        23: invokevirtual #92                 // Method java/lang/StringBuilder.append:(Ljava/lang/String;)Ljava/lang/StringBuilder;
        26: aload_0
        27: invokevirtual #101                // Method _2:()Ljava/lang/Object;
        30: invokevirtual #97                 // Method java/lang/StringBuilder.append:(Ljava/lang/Object;)Ljava/lang/StringBuilder;
        33: ldc           #99                 // String ,
        35: invokevirtual #92                 // Method java/lang/StringBuilder.append:(Ljava/lang/String;)Ljava/lang/StringBuilder;
        38: aload_0
        39: invokevirtual #103                // Method _3:()Ljava/lang/Object;
        42: invokevirtual #97                 // Method java/lang/StringBuilder.append:(Ljava/lang/Object;)Ljava/lang/StringBuilder;
        45: ldc           #105                // String )
        47: invokevirtual #92                 // Method java/lang/StringBuilder.append:(Ljava/lang/String;)Ljava/lang/StringBuilder;
        50: invokevirtual #107                // Method java/lang/StringBuilder.toString:()Ljava/lang/String;
        53: areturn
      LineNumberTable:
        line 28: 0
      LocalVariableTable:
        Start  Length  Slot  Name   Signature
            0      54     0  this   Lscala/Tuple3;

  public <T1 extends java.lang.Object, T2 extends java.lang.Object, T3 extends java.lang.Object> scala.Tuple3<T1, T2, T3> copy(T1, T2, T3);
    descriptor: (Ljava/lang/Object;Ljava/lang/Object;Ljava/lang/Object;)Lscala/Tuple3;
    flags: (0x0001) ACC_PUBLIC
    Code:
      stack=5, locals=4, args_size=4
         0: new           #2                  // class scala/Tuple3
         3: dup
         4: aload_1
         5: aload_2
         6: aload_3
         7: invokespecial #42                 // Method "<init>":(Ljava/lang/Object;Ljava/lang/Object;Ljava/lang/Object;)V
        10: areturn
      LineNumberTable:
        line 25: 0
      LocalVariableTable:
        Start  Length  Slot  Name   Signature
            0      11     0  this   Lscala/Tuple3;
            0      11     1    _1   Ljava/lang/Object;
            0      11     2    _2   Ljava/lang/Object;
            0      11     3    _3   Ljava/lang/Object;
    Signature: #38                          // <T1:Ljava/lang/Object;T2:Ljava/lang/Object;T3:Ljava/lang/Object;>(TT1;TT2;TT3;)Lscala/Tuple3<TT1;TT2;TT3;>;
    MethodParameters:
      Name                           Flags
      _1                             final
      _2                             final
      _3                             final

  public <T1 extends java.lang.Object, T2 extends java.lang.Object, T3 extends java.lang.Object> T1 copy$default$1();
    descriptor: ()Ljava/lang/Object;
    flags: (0x0001) ACC_PUBLIC
    Code:
      stack=1, locals=1, args_size=1
         0: aload_0
         1: invokevirtual #94                 // Method _1:()Ljava/lang/Object;
         4: areturn
      LineNumberTable:
        line 25: 0
      LocalVariableTable:
        Start  Length  Slot  Name   Signature
            0       5     0  this   Lscala/Tuple3;
    Signature: #110                         // <T1:Ljava/lang/Object;T2:Ljava/lang/Object;T3:Ljava/lang/Object;>()TT1;

  public <T1 extends java.lang.Object, T2 extends java.lang.Object, T3 extends java.lang.Object> T2 copy$default$2();
    descriptor: ()Ljava/lang/Object;
    flags: (0x0001) ACC_PUBLIC
    Code:
      stack=1, locals=1, args_size=1
         0: aload_0
         1: invokevirtual #101                // Method _2:()Ljava/lang/Object;
         4: areturn
      LineNumberTable:
        line 25: 0
      LocalVariableTable:
        Start  Length  Slot  Name   Signature
            0       5     0  this   Lscala/Tuple3;
    Signature: #112                         // <T1:Ljava/lang/Object;T2:Ljava/lang/Object;T3:Ljava/lang/Object;>()TT2;

  public <T1 extends java.lang.Object, T2 extends java.lang.Object, T3 extends java.lang.Object> T3 copy$default$3();
    descriptor: ()Ljava/lang/Object;
    flags: (0x0001) ACC_PUBLIC
    Code:
      stack=1, locals=1, args_size=1
         0: aload_0
         1: invokevirtual #103                // Method _3:()Ljava/lang/Object;
         4: areturn
      LineNumberTable:
        line 25: 0
      LocalVariableTable:
        Start  Length  Slot  Name   Signature
            0       5     0  this   Lscala/Tuple3;
    Signature: #114                         // <T1:Ljava/lang/Object;T2:Ljava/lang/Object;T3:Ljava/lang/Object;>()TT3;

  public java.lang.String productPrefix();
    descriptor: ()Ljava/lang/String;
    flags: (0x0001) ACC_PUBLIC
    Code:
      stack=1, locals=1, args_size=1
         0: ldc           #117                // String Tuple3
         2: areturn
      LineNumberTable:
        line 25: 0
      LocalVariableTable:
        Start  Length  Slot  Name   Signature
            0       3     0  this   Lscala/Tuple3;

  public scala.collection.Iterator<java.lang.Object> productIterator();
    descriptor: ()Lscala/collection/Iterator;
    flags: (0x0001) ACC_PUBLIC
    Code:
      stack=3, locals=1, args_size=1
         0: new           #15                 // class scala/runtime/ScalaRunTime$$anon$1
         3: dup
         4: aload_0
         5: invokespecial #122                // Method scala/runtime/ScalaRunTime$$anon$1."<init>":(Lscala/Product;)V
         8: areturn
      LineNumberTable:
        line 25: 0
      LocalVariableTable:
        Start  Length  Slot  Name   Signature
            0       9     0  this   Lscala/Tuple3;
    Signature: #119                         // ()Lscala/collection/Iterator<Ljava/lang/Object;>;

  public boolean canEqual(java.lang.Object);
    descriptor: (Ljava/lang/Object;)Z
    flags: (0x0001) ACC_PUBLIC
    Code:
      stack=1, locals=2, args_size=2
         0: aload_1
         1: instanceof    #2                  // class scala/Tuple3
         4: ireturn
      LineNumberTable:
        line 25: 0
      LocalVariableTable:
        Start  Length  Slot  Name   Signature
            0       5     0  this   Lscala/Tuple3;
            0       5     1   x$1   Ljava/lang/Object;
    MethodParameters:
      Name                           Flags
      x$1                            final

  public java.lang.String productElementName(int);
    descriptor: (I)Ljava/lang/String;
    flags: (0x0001) ACC_PUBLIC
    Code:
      stack=1, locals=2, args_size=2
         0: iload_1
         1: tableswitch   { // 0 to 2
                       0: 28
                       1: 31
                       2: 34
                 default: 37
            }
        28: ldc           #128                // String _1
        30: areturn
        31: ldc           #129                // String _2
        33: areturn
        34: ldc           #130                // String _3
        36: areturn
        37: iload_1
        38: invokestatic  #135                // Method scala/runtime/Statics.ioobe:(I)Ljava/lang/Object;
        41: checkcast     #137                // class java/lang/String
        44: areturn
      StackMapTable: number_of_entries = 4
        frame_type = 28 /* same */
        frame_type = 2 /* same */
        frame_type = 2 /* same */
        frame_type = 2 /* same */
      LineNumberTable:
        line 25: 0
      LocalVariableTable:
        Start  Length  Slot  Name   Signature
            0      45     0  this   Lscala/Tuple3;
            0      45     1   x$1   I
    MethodParameters:
      Name                           Flags
      x$1                            final

  public int hashCode();
    descriptor: ()I
    flags: (0x0001) ACC_PUBLIC
    Code:
      stack=2, locals=1, args_size=1
         0: getstatic     #143                // Field scala/util/hashing/MurmurHash3$.MODULE$:Lscala/util/hashing/MurmurHash3$;
         3: aload_0
         4: invokevirtual #147                // Method scala/util/hashing/MurmurHash3$.productHash:(Lscala/Product;)I
         7: ireturn
      LineNumberTable:
        line 25: 0
      LocalVariableTable:
        Start  Length  Slot  Name   Signature
            0       8     0  this   Lscala/Tuple3;

  public boolean equals(java.lang.Object);
    descriptor: (Ljava/lang/Object;)Z
    flags: (0x0001) ACC_PUBLIC
    Code:
      stack=2, locals=4, args_size=2
         0: aload_0
         1: aload_1
         2: if_acmpeq     78
         5: aload_1
         6: instanceof    #2                  // class scala/Tuple3
         9: ifeq          17
        12: iconst_1
        13: istore_2
        14: goto          19
        17: iconst_0
        18: istore_2
        19: iload_2
        20: ifeq          80
        23: aload_1
        24: checkcast     #2                  // class scala/Tuple3
        27: astore_3
        28: aload_0
        29: invokevirtual #94                 // Method _1:()Ljava/lang/Object;
        32: aload_3
        33: invokevirtual #94                 // Method _1:()Ljava/lang/Object;
        36: invokestatic  #153                // Method scala/runtime/BoxesRunTime.equals:(Ljava/lang/Object;Ljava/lang/Object;)Z
        39: ifeq          74
        42: aload_0
        43: invokevirtual #101                // Method _2:()Ljava/lang/Object;
        46: aload_3
        47: invokevirtual #101                // Method _2:()Ljava/lang/Object;
        50: invokestatic  #153                // Method scala/runtime/BoxesRunTime.equals:(Ljava/lang/Object;Ljava/lang/Object;)Z
        53: ifeq          74
        56: aload_0
        57: invokevirtual #103                // Method _3:()Ljava/lang/Object;
        60: aload_3
        61: invokevirtual #103                // Method _3:()Ljava/lang/Object;
        64: invokestatic  #153                // Method scala/runtime/BoxesRunTime.equals:(Ljava/lang/Object;Ljava/lang/Object;)Z
        67: ifeq          74
        70: iconst_1
        71: goto          75
        74: iconst_0
        75: ifeq          80
        78: iconst_1
        79: ireturn
        80: iconst_0
        81: ireturn
      StackMapTable: number_of_entries = 6
        frame_type = 17 /* same */
        frame_type = 252 /* append */
          offset_delta = 1
          locals = [ int ]
        frame_type = 252 /* append */
          offset_delta = 54
          locals = [ class scala/Tuple3 ]
        frame_type = 64 /* same_locals_1_stack_item */
          stack = [ int ]
        frame_type = 249 /* chop */
          offset_delta = 2
        frame_type = 252 /* append */
          offset_delta = 1
          locals = [ int ]
      LineNumberTable:
        line 25: 0
      LocalVariableTable:
        Start  Length  Slot  Name   Signature
            0      82     0  this   Lscala/Tuple3;
            0      82     1   x$1   Ljava/lang/Object;
    MethodParameters:
      Name                           Flags
      x$1                            final

  public scala.Tuple3(T1, T2, T3);
    descriptor: (Ljava/lang/Object;Ljava/lang/Object;Ljava/lang/Object;)V
    flags: (0x0001) ACC_PUBLIC
    Code:
      stack=2, locals=4, args_size=4
         0: aload_0
         1: aload_1
         2: putfield      #72                 // Field _1:Ljava/lang/Object;
         5: aload_0
         6: aload_2
         7: putfield      #75                 // Field _2:Ljava/lang/Object;
        10: aload_0
        11: aload_3
        12: putfield      #78                 // Field _3:Ljava/lang/Object;
        15: aload_0
        16: invokespecial #157                // Method java/lang/Object."<init>":()V
        19: return
      LineNumberTable:
        line 25: 0
        line 26: 15
      LocalVariableTable:
        Start  Length  Slot  Name   Signature
            0      20     0  this   Lscala/Tuple3;
            0      20     1    _1   Ljava/lang/Object;
            0      20     2    _2   Ljava/lang/Object;
            0      20     3    _3   Ljava/lang/Object;
    Signature: #154                         // (TT1;TT2;TT3;)V
    MethodParameters:
      Name                           Flags
      _1                             final
      _2                             final
      _3                             final
}
InnerClasses:
  public final #15;                       // class scala/runtime/ScalaRunTime$$anon$1
Signature: #3                           // <T1:Ljava/lang/Object;T2:Ljava/lang/Object;T3:Ljava/lang/Object;>Ljava/lang/Object;Lscala/Product3<TT1;TT2;TT3;>;Ljava/io/Serializable;
SourceFile: "Tuple3.scala"
RuntimeVisibleAnnotations:
  0: #11(#12=s#13)
    scala.reflect.ScalaSignature(
      bytes="\u0006\u0005\u0005Mf\u0001\u0002\u000e\u001c\u0005zA\u0001b\u0012\u0001\u0003\u0016\u0004%\t\u0001\u0013\u0005\t\u0013\u0002\u0011\t\u0012)A\u0005O!A!\n\u0001BK\u0002\u0013\u00051\n\u0003\u0005M\u0001\tE\t\u0015!\u00033\u0011!i\u0005A!f\u0001\n\u0003q\u0005\u0002C(\u0001\u0005#\u0005\u000b\u0011B\u001b\t\u000bA\u0003A\u0011A)\t\u000bY\u0003A\u0011I,\t\u000f\u0001\u0004\u0011\u0011!C\u0001C\"9Q\u000eAI\u0001\n\u0003q\u0007bB?\u0001#\u0003%\tA \u0005\n\u0003\u0013\u0001\u0011\u0013!C\u0001\u0003\u0017A\u0011\"a\u0006\u0001\u0003\u0003%\t%!\u0007\t\u0013\u0005%\u0002!!A\u0005B\u0005-\u0002\"CA\u001d\u0001\u0005\u0005I\u0011AA\u001e\u0011%\t9\u0005AA\u0001\n\u0003\nI\u0005C\u0005\u0002T\u0001\t\t\u0011\"\u0011\u0002V!I\u0011q\u000b\u0001\u0002\u0002\u0013\u0005\u0013\u0011L\u0004\n\u0003;Z\u0012\u0011!E\u0001\u0003?2\u0001BG\u000e\u0002\u0002#\u0005\u0011\u0011\r\u0005\u0007!R!\t!!\u001c\t\u0011Y#\u0012\u0011!C#\u0003_B\u0011\"!\u001d\u0015\u0003\u0003%\t)a\u001d\t\u0013\u0005-E#!A\u0005\u0002\u00065\u0005\"CAU)\u0005\u0005I\u0011BAV\u0005\u0019!V\u000f\u001d7fg)\tA$A\u0003tG\u0006d\u0017m\u0001\u0001\u0016\t}I3GN\n\u0006\u0001\u0001\"\u0003h\u000f\t\u0003C\tj\u0011aG\u0005\u0003Gm\u0011a!\u00118z%\u00164\u0007#B\u0011&OI*\u0014B\u0001\u0014\u001c\u0005!\u0001&o\u001c3vGR\u001c\u0004C\u0001\u0015*\u0019\u0001!aA\u000b\u0001\u0005\u0006\u0004Y#A\u0001+2#\tas\u0006\u0005\u0002\"[%\u0011af\u0007\u0002\b\u001d>$\b.\u001b8h!\t\t\u0003\'\u0003\u000227\t\u0019\u0011I\\=\u0011\u0005!\u001aDA\u0002\u001b\u0001\t\u000b\u00071F\u0001\u0002UeA\u0011\u0001F\u000e\u0003\u0007o\u0001!)\u0019A\u0016\u0003\u0005Q\u001b\u0004CA\u0011:\u0013\tQ4DA\u0004Qe>$Wo\u0019;\u0011\u0005q\"eBA\u001fC\u001d\tq\u0014)D\u0001@\u0015\t\u0001U$\u0001\u0004=e>|GOP\u0005\u00029%\u00111iG\u0001\ba\u0006\u001c7.Y4f\u0013\t)eI\u0001\u0007TKJL\u0017\r\\5{C\ndWM\u0003\u0002D7\u0005\u0011q,M\u000b\u0002O\u0005\u0019q,\r\u0011\u0002\u0005}\u0013T#\u0001\u001a\u0002\u0007}\u0013\u0004%\u0001\u0002`gU\tQ\'A\u0002`g\u0001\na\u0001P5oSRtD\u0003\u0002*T)V\u0003R!\t\u0001(eUBQaR\u0004A\u0002\u001dBQAS\u0004A\u0002IBQ!T\u0004A\u0002U\n\u0001\u0002^8TiJLgn\u001a\u000b\u00021B\u0011\u0011,\u0018\b\u00035n\u0003\"AP\u000e\n\u0005q[\u0012A\u0002)sK\u0012,g-\u0003\u0002_?\n11\u000b\u001e:j]\u001eT!\u0001X\u000e\u0002\t\r|\u0007/_\u000b\u0005E\u0016<\u0017\u000e\u0006\u0003dU.d\u0007#B\u0011\u0001I\u001aD\u0007C\u0001\u0015f\t\u0015Q\u0013B1\u0001,!\tAs\rB\u00035\u0013\t\u00071\u0006\u0005\u0002)S\u0012)q\'\u0003b\u0001W!9q)\u0003I\u0001\u0002\u0004!\u0007b\u0002&\n!\u0003\u0005\rA\u001a\u0005\b\u001b&\u0001\n\u00111\u0001i\u00039\u0019w\u000e]=%I\u00164\u0017-\u001e7uIE*Ba\u001c>|yV\t\u0001O\u000b\u0002(c.\n!\u000f\u0005\u0002tq6\tAO\u0003\u0002vm\u0006IQO\\2iK\u000e\\W\r\u001a\u0006\u0003on\t!\"\u00198o_R\fG/[8o\u0013\tIHOA\tv]\u000eDWmY6fIZ\u000b\'/[1oG\u0016$QA\u000b\u0006C\u0002-\"Q\u0001\u000e\u0006C\u0002-\"Qa\u000e\u0006C\u0002-\nabY8qs\u0012\"WMZ1vYR$#\'F\u0004\u0000\u0003\u0007\t)!a\u0002\u0016\u0005\u0005\u0005!F\u0001\u001ar\t\u0015Q3B1\u0001,\t\u0015!4B1\u0001,\t\u001594B1\u0001,\u00039\u0019w\u000e]=%I\u00164\u0017-\u001e7uIM*\u0002\"!\u0004\u0002\u0012\u0005M\u0011QC\u000b\u0003\u0003\u001fQ#!N9\u0005\u000b)b!\u0019A\u0016\u0005\u000bQb!\u0019A\u0016\u0005\u000b]b!\u0019A\u0016\u0002\u001bA\u0014x\u000eZ;diB\u0013XMZ5y+\t\tY\u0002\u0005\u0003\u0002\u001e\u0005\u001dRBAA\u0010\u0015\u0011\t\t#a\t\u0002\t1\fgn\u001a\u0006\u0003\u0003K\tAA[1wC&\u0019a,a\b\u0002\u001fA\u0014x\u000eZ;di&#XM]1u_J,\"!!\f\u0011\u000b\u0005=\u0012QG\u0018\u000e\u0005\u0005E\"bAA\u001a7\u0005Q1m\u001c7mK\u000e$\u0018n\u001c8\n\t\u0005]\u0012\u0011\u0007\u0002\t\u0013R,\'/\u0019;pe\u0006A1-\u00198FcV\fG\u000e\u0006\u0003\u0002>\u0005\r\u0003cA\u0011\u0002@%\u0019\u0011\u0011I\u000e\u0003\u000f\t{w\u000e\\3b]\"A\u0011QI\b\u0002\u0002\u0003\u0007q&A\u0002yIE\n!\u0003\u001d:pIV\u001cG/\u00127f[\u0016tGOT1nKR!\u00111DA&\u0011%\t)\u0005EA\u0001\u0002\u0004\ti\u0005E\u0002\"\u0003\u001fJ1!!\u0015\u001c\u0005\rIe\u000e^\u0001\tQ\u0006\u001c\bnQ8eKR\u0011\u0011QJ\u0001\u0007KF,\u0018\r\\:\u0015\t\u0005u\u00121\f\u0005\t\u0003\u000b\u0012\u0012\u0011!a\u0001_\u00051A+\u001e9mKN\u0002\"!\t\u000b\u0014\tQ\u0001\u00131\r\t\u0005\u0003K\nY\'\u0004\u0002\u0002h)!\u0011\u0011NA\u0012\u0003\tIw.C\u0002F\u0003O\"\"!a\u0018\u0015\u0005\u0005m\u0011!B1qa2LX\u0003CA;\u0003w\ny(a!\u0015\u0011\u0005]\u0014QQAD\u0003\u0013\u0003\u0002\"\t\u0001\u0002z\u0005u\u0014\u0011\u0011\t\u0004Q\u0005mD!\u0002\u0016\u0018\u0005\u0004Y\u0003c\u0001\u0015\u0002\u0000\u0011)Ag\u0006b\u0001WA\u0019\u0001&a!\u0005\u000b]:\"\u0019A\u0016\t\r\u001d;\u0002\u0019AA=\u0011\u0019Qu\u00031\u0001\u0002~!1Qj\u0006a\u0001\u0003\u0003\u000bq!\u001e8baBd\u00170\u0006\u0005\u0002\u0010\u0006m\u0015qTAR)\u0011\t\t*!*\u0011\u000b\u0005\n\u0019*a&\n\u0007\u0005U5D\u0001\u0004PaRLwN\u001c\t\tC\u0001\tI*!(\u0002\"B\u0019\u0001&a\'\u0005\u000b)B\"\u0019A\u0016\u0011\u0007!\ny\nB\u000351\t\u00071\u0006E\u0002)\u0003G#Qa\u000e\rC\u0002-B\u0011\"a*\u0019\u0003\u0003\u0005\r!a&\u0002\u0007a$\u0003\'\u0001\u0007xe&$XMU3qY\u0006\u001cW\r\u0006\u0002\u0002.B!\u0011QDAX\u0013\u0011\t\t,a\b\u0003\r=\u0013\'.Z2u\u0001"
    )
  ScalaInlineInfo: length = 0x5E (unknown attribute)
   01 01 00 12 00 27 00 28 01 00 10 00 45 01 00 13
   00 45 01 00 15 00 45 01 00 7B 00 7C 01 00 6C 00
   25 01 00 6D 00 45 01 00 6F 00 45 01 00 71 00 45
   01 00 94 00 7C 01 00 8A 00 2C 01 00 2B 00 2C 01
   00 32 00 33 01 00 7E 00 7F 01 00 3C 00 3D 01 00
   76 00 3D 01 00 73 00 50 01 00 4F 00 50 01
  ScalaSig: length = 0x3 (unknown attribute)
   05 02 00
