Classfile /Users/mw/Projects/slang-braindump/.jar/jar11/assemble/slang-braindump/assemble/content/scala/Tuple19.class
  Last modified May 29, 2022; size 28664 bytes
  SHA-256 checksum 88384dfb04b070d3cfe4060d610229aba1440b827828c1ae8d013e405c0072b5
  Compiled from "Tuple19.scala"
public final class scala.Tuple19<T1 extends java.lang.Object, T2 extends java.lang.Object, T3 extends java.lang.Object, T4 extends java.lang.Object, T5 extends java.lang.Object, T6 extends java.lang.Object, T7 extends java.lang.Object, T8 extends java.lang.Object, T9 extends java.lang.Object, T10 extends java.lang.Object, T11 extends java.lang.Object, T12 extends java.lang.Object, T13 extends java.lang.Object, T14 extends java.lang.Object, T15 extends java.lang.Object, T16 extends java.lang.Object, T17 extends java.lang.Object, T18 extends java.lang.Object, T19 extends java.lang.Object> extends java.lang.Object implements scala.Product19<T1, T2, T3, T4, T5, T6, T7, T8, T9, T10, T11, T12, T13, T14, T15, T16, T17, T18, T19>, java.io.Serializable
  minor version: 0
  major version: 52
  flags: (0x0031) ACC_PUBLIC, ACC_FINAL, ACC_SUPER
  this_class: #2                          // scala/Tuple19
  super_class: #5                         // java/lang/Object
  interfaces: 2, fields: 19, methods: 52, attributes: 6
Constant pool:
    #1 = Utf8               scala/Tuple19
    #2 = Class              #1            // scala/Tuple19
    #3 = Utf8               <T1:Ljava/lang/Object;T2:Ljava/lang/Object;T3:Ljava/lang/Object;T4:Ljava/lang/Object;T5:Ljava/lang/Object;T6:Ljava/lang/Object;T7:Ljava/lang/Object;T8:Ljava/lang/Object;T9:Ljava/lang/Object;T10:Ljava/lang/Object;T11:Ljava/lang/Object;T12:Ljava/lang/Object;T13:Ljava/lang/Object;T14:Ljava/lang/Object;T15:Ljava/lang/Object;T16:Ljava/lang/Object;T17:Ljava/lang/Object;T18:Ljava/lang/Object;T19:Ljava/lang/Object;>Ljava/lang/Object;Lscala/Product19<TT1;TT2;TT3;TT4;TT5;TT6;TT7;TT8;TT9;TT10;TT11;TT12;TT13;TT14;TT15;TT16;TT17;TT18;TT19;>;Ljava/io/Serializable;
    #4 = Utf8               java/lang/Object
    #5 = Class              #4            // java/lang/Object
    #6 = Utf8               scala/Product19
    #7 = Class              #6            // scala/Product19
    #8 = Utf8               java/io/Serializable
    #9 = Class              #8            // java/io/Serializable
   #10 = Utf8               Tuple19.scala
   #11 = Utf8               Lscala/reflect/ScalaSignature;
   #12 = Utf8               bytes
   #13 = Utf8               \u0006\u0005\u001dMb\u0001\u0002&L\u0005:C!\"a\u0014\u0001\u0005+\u0007I\u0011AA)\u0011%\t\u0019\u0006\u0001B\tB\u0003%q\u000b\u0003\u0006\u0002V\u0001\u0011)\u001a!C\u0001\u0003/B\u0011\"!\u0017\u0001\u0005#\u0005\u000b\u0011\u00022\t\u0015\u0005m\u0003A!f\u0001\n\u0003\ti\u0006C\u0005\u0002`\u0001\u0011\t\u0012)A\u0005K\"Q\u0011\u0011\r\u0001\u0003\u0016\u0004%\t!a\u0019\t\u0013\u0005\u0015\u0004A!E!\u0002\u0013A\u0007BCA4\u0001\tU\r\u0011\"\u0001\u0002j!I\u00111\u000e\u0001\u0003\u0012\u0003\u0006Ia\u001b\u0005\u000b\u0003[\u0002!Q3A\u0005\u0002\u0005=\u0004\"CA9\u0001\tE\t\u0015!\u0003o\u0011)\t\u0019\b\u0001BK\u0002\u0013\u0005\u0011Q\u000f\u0005\n\u0003o\u0002!\u0011#Q\u0001\nED!\"!\u001f\u0001\u0005+\u0007I\u0011AA>\u0011%\ti\b\u0001B\tB\u0003%A\u000f\u0003\u0006\u0002\u0000\u0001\u0011)\u001a!C\u0001\u0003\u0003C\u0011\"a!\u0001\u0005#\u0005\u000b\u0011B<\t\u0015\u0005\u0015\u0005A!f\u0001\n\u0003\t9\tC\u0005\u0002\n\u0002\u0011\t\u0012)A\u0005u\"Q\u00111\u0012\u0001\u0003\u0016\u0004%\t!!$\t\u0013\u0005=\u0005A!E!\u0002\u0013i\bBCAI\u0001\tU\r\u0011\"\u0001\u0002\u0014\"Q\u0011Q\u0013\u0001\u0003\u0012\u0003\u0006I!!\u0001\t\u0015\u0005]\u0005A!f\u0001\n\u0003\tI\n\u0003\u0006\u0002\u001c\u0002\u0011\t\u0012)A\u0005\u0003\u000fA!\"!(\u0001\u0005+\u0007I\u0011AAP\u0011)\t\t\u000b\u0001B\tB\u0003%\u0011Q\u0002\u0005\u000b\u0003G\u0003!Q3A\u0005\u0002\u0005\u0015\u0006BCAT\u0001\tE\t\u0015!\u0003\u0002\u0014!Q\u0011\u0011\u0016\u0001\u0003\u0016\u0004%\t!a+\t\u0015\u00055\u0006A!E!\u0002\u0013\tI\u0002\u0003\u0006\u00020\u0002\u0011)\u001a!C\u0001\u0003cC!\"a-\u0001\u0005#\u0005\u000b\u0011BA\u0010\u0011)\t)\f\u0001BK\u0002\u0013\u0005\u0011q\u0017\u0005\u000b\u0003s\u0003!\u0011#Q\u0001\n\u0005\u0015\u0002BCA^\u0001\tU\r\u0011\"\u0001\u0002>\"Q\u0011q\u0018\u0001\u0003\u0012\u0003\u0006I!a\u000b\t\u000f\u0005\u0005\u0007\u0001\"\u0001\u0002D\"9\u0011Q\u001e\u0001\u0005B\u0005=\b\"\u0003B\u0001\u0001\u0005\u0005I\u0011\u0001B\u0002\u0011%\u0011Y\bAI\u0001\n\u0003\u0011i\bC\u0005\u0003<\u0002\t\n\u0011\"\u0001\u0003>\"I!\u0011\u001e\u0001\u0012\u0002\u0013\u0005!1\u001e\u0005\n\u0007/\u0001\u0011\u0013!C\u0001\u00073A\u0011b!\u0012\u0001#\u0003%\taa\u0012\t\u0013\rM\u0004!%A\u0005\u0002\rU\u0004\"CBQ\u0001E\u0005I\u0011ABR\u0011%\u0019y\rAI\u0001\n\u0003\u0019\t\u000eC\u0005\u0004~\u0002\t\n\u0011\"\u0001\u0004\u0000\"IA1\u0006\u0001\u0012\u0002\u0013\u0005AQ\u0006\u0005\n\t3\u0002\u0011\u0013!C\u0001\t7B\u0011\u0002b\"\u0001#\u0003%\t\u0001\"#\t\u0013\u0011U\u0006!%A\u0005\u0002\u0011]\u0006\"\u0003Cr\u0001E\u0005I\u0011\u0001Cs\u0011%)\t\u0002AI\u0001\n\u0003)\u0019\u0002C\u0005\u0006@\u0001\t\n\u0011\"\u0001\u0006B!IQQ\u000e\u0001\u0012\u0002\u0013\u0005Qq\u000e\u0005\n\u000b7\u0003\u0011\u0013!C\u0001\u000b;C\u0011\"\"3\u0001#\u0003%\t!b3\t\u0013\u0015]\b!!A\u0005B\u0015e\b\"\u0003D\u0005\u0001\u0005\u0005I\u0011\tD\u0006\u0011%1I\u0002AA\u0001\n\u00031Y\u0002C\u0005\u0007(\u0001\t\t\u0011\"\u0011\u0007*!Ia1\u0007\u0001\u0002\u0002\u0013\u0005cQ\u0007\u0005\n\ro\u0001\u0011\u0011!C!\rs9\u0011B\"\u0010L\u0003\u0003E\tAb\u0010\u0007\u0011)[\u0015\u0011!E\u0001\r\u0003Bq!!1E\t\u00031i\u0005C\u0005\u0002n\u0012\u000b\t\u0011\"\u0012\u0007P!Ia\u0011\u000b#\u0002\u0002\u0013\u0005e1\u000b\u0005\n\r\u0017$\u0015\u0011!CA\r\u001bD\u0011b\"\u000bE\u0003\u0003%Iab\u000b\u0003\u000fQ+\b\u000f\\32s)\tA*A\u0003tG\u0006d\u0017m\u0001\u0001\u00169=K6MZ5m_J,\bp\u001f@\u0002\u0004\u0005%\u0011qBA\u000b\u00037\t\t#a\n\u0002.M9\u0001\u0001\u0015+\u00022\u0005]\u0002CA)S\u001b\u0005Y\u0015BA*L\u0005\u0019\te.\u001f*fMBi\u0012+V,cK\"\\g.\u001d;xuv\f\t!a\u0002\u0002\u000e\u0005M\u0011\u0011DA\u0010\u0003K\tY#\u0003\u0002W\u0017\nI\u0001K]8ek\u000e$\u0018\'\u000f\t\u00031fc\u0001\u0001\u0002\u0004[\u0001\u0011\u0015\ra\u0017\u0002\u0003)F\n\"\u0001X0\u0011\u0005Ek\u0016B\u00010L\u0005\u001dqu\u000e\u001e5j]\u001e\u0004\"!\u00151\n\u0005\u0005\\%aA!osB\u0011\u0001l\u0019\u0003\u0007I\u0002!)\u0019A.\u0003\u0005Q\u0013\u0004C\u0001-g\t\u00199\u0007\u0001\"b\u00017\n\u0011Ak\r\t\u00031&$aA\u001b\u0001\u0005\u0006\u0004Y&A\u0001+5!\tAF\u000e\u0002\u0004n\u0001\u0011\u0015\ra\u0017\u0002\u0003)V\u0002\"\u0001W8\u0005\rA\u0004AQ1\u0001\\\u0005\t!f\u0007\u0005\u0002Ye\u001211\u000f\u0001CC\u0002m\u0013!\u0001V\u001c\u0011\u0005a+HA\u0002<\u0001\t\u000b\u00071L\u0001\u0002UqA\u0011\u0001\f\u001f\u0003\u0007s\u0002!)\u0019A.\u0003\u0005QK\u0004C\u0001-|\t\u0019a\b\u0001\"b\u00017\n\u0019A+\r\u0019\u0011\u0005asHAB@\u0001\t\u000b\u00071LA\u0002UcE\u00022\u0001WA\u0002\t\u001d\t)\u0001\u0001CC\u0002m\u00131\u0001V\u00193!\rA\u0016\u0011\u0002\u0003\b\u0003\u0017\u0001AQ1\u0001\\\u0005\r!\u0016g\r\t\u00041\u0006=AaBA\t\u0001\u0011\u0015\ra\u0017\u0002\u0004)F\"\u0004c\u0001-\u0002\u0016\u00119\u0011q\u0003\u0001\u0005\u0006\u0004Y&a\u0001+2kA\u0019\u0001,a\u0007\u0005\u000f\u0005u\u0001\u0001\"b\u00017\n\u0019A+\r\u001c\u0011\u0007a\u000b\t\u0003B\u0004\u0002$\u0001!)\u0019A.\u0003\u0007Q\u000bt\u0007E\u0002Y\u0003O!q!!\u000b\u0001\t\u000b\u00071LA\u0002Uca\u00022\u0001WA\u0017\t\u001d\ty\u0003\u0001CC\u0002m\u00131\u0001V\u0019:!\r\t\u00161G\u0005\u0004\u0003kY%a\u0002)s_\u0012,8\r\u001e\t\u0005\u0003s\tIE\u0004\u0003\u0002<\u0005\u0015c\u0002BA\u001f\u0003\u0007j!!a\u0010\u000b\u0007\u0005\u0005S*\u0001\u0004=e>|GOP\u0005\u0002\u0019&\u0019\u0011qI&\u0002\u000fA\f7m[1hK&!\u00111JA\'\u00051\u0019VM]5bY&T\u0018M\u00197f\u0015\r\t9eS\u0001\u0003?F*\u0012aV\u0001\u0004?F\u0002\u0013AA03+\u0005\u0011\u0017aA03A\u0005\u0011qlM\u000b\u0002K\u0006\u0019ql\r\u0011\u0002\u0005}#T#\u00015\u0002\u0007}#\u0004%\u0001\u0002`kU\t1.A\u0002`k\u0001\n!a\u0018\u001c\u0016\u00039\f1a\u0018\u001c!\u0003\tyv\'F\u0001r\u0003\ryv\u0007I\u0001\u0003?b*\u0012\u0001^\u0001\u0004?b\u0002\u0013AA0:+\u00059\u0018aA0:A\u0005\u0019q,\r\u0019\u0016\u0003i\fAaX\u00191A\u0005\u0019q,M\u0019\u0016\u0003u\fAaX\u00192A\u0005\u0019q,\r\u001a\u0016\u0005\u0005\u0005\u0011\u0001B02e\u0001\n1aX\u00194+\t\t9!\u0001\u0003`cM\u0002\u0013aA02iU\u0011\u0011QB\u0001\u0005?F\"\u0004%A\u0002`cU*\"!a\u0005\u0002\t}\u000bT\u0007I\u0001\u0004?F2TCAA\r\u0003\u0011y\u0016G\u000e\u0011\u0002\u0007}\u000bt\'\u0006\u0002\u0002 \u0005!q,M\u001c!\u0003\ry\u0016\u0007O\u000b\u0003\u0003K\tAaX\u00199A\u0005\u0019q,M\u001d\u0016\u0005\u0005-\u0012\u0001B02s\u0001\na\u0001P5oSRtD\u0003KAc\u0003\u000f\fI-a3\u0002N\u0006=\u0017\u0011[Aj\u0003+\f9.!7\u0002\\\u0006u\u0017q\\Aq\u0003G\f)/a:\u0002j\u0006-\b#H)\u0001/\n,\u0007n\u001b8ri^TX0!\u0001\u0002\b\u00055\u00111CA\r\u0003?\t)#a\u000b\t\r\u0005=s\u00051\u0001X\u0011\u0019\t)f\na\u0001E\"1\u00111L\u0014A\u0002\u0015Da!!\u0019(\u0001\u0004A\u0007BBA4O\u0001\u00071\u000e\u0003\u0004\u0002n\u001d\u0002\rA\u001c\u0005\u0007\u0003g:\u0003\u0019A9\t\r\u0005et\u00051\u0001u\u0011\u0019\tyh\na\u0001o\"1\u0011QQ\u0014A\u0002iDa!a#(\u0001\u0004i\bbBAIO\u0001\u0007\u0011\u0011\u0001\u0005\b\u0003/;\u0003\u0019AA\u0004\u0011\u001d\tij\na\u0001\u0003\u001bAq!a)(\u0001\u0004\t\u0019\u0002C\u0004\u0002*\u001e\u0002\r!!\u0007\t\u000f\u0005=v\u00051\u0001\u0002 !9\u0011QW\u0014A\u0002\u0005\u0015\u0002bBA^O\u0001\u0007\u00111F\u0001\ti>\u001cFO]5oOR\u0011\u0011\u0011\u001f\t\u0005\u0003g\fYP\u0004\u0003\u0002v\u0006]\bcAA\u001f\u0017&\u0019\u0011\u0011`&\u0002\rA\u0013X\rZ3g\u0013\u0011\ti0a@\u0003\rM#(/\u001b8h\u0015\r\tIpS\u0001\u0005G>\u0004\u00180\u0006\u0015\u0003\u0006\t-!q\u0002B\n\u0005/\u0011YBa\b\u0003$\t\u001d\"1\u0006B\u0018\u0005g\u00119Da\u000f\u0003@\t\r#q\tB&\u0005\u001f\u0012\u0019\u0006\u0006\u0015\u0003\b\tU#q\u000bB-\u00057\u0012iFa\u0018\u0003b\t\r$Q\rB4\u0005S\u0012YG!\u001c\u0003p\tE$1\u000fB;\u0005o\u0012I\b\u0005\u0015R\u0001\t%!Q\u0002B\t\u0005+\u0011IB!\b\u0003\"\t\u0015\"\u0011\u0006B\u0017\u0005c\u0011)D!\u000f\u0003>\t\u0005#Q\tB%\u0005\u001b\u0012\t\u0006E\u0002Y\u0005\u0017!QAW\u0015C\u0002m\u00032\u0001\u0017B\b\t\u0015!\u0017F1\u0001\\!\rA&1\u0003\u0003\u0006O&\u0012\ra\u0017\t\u00041\n]A!\u00026*\u0005\u0004Y\u0006c\u0001-\u0003\u001c\u0011)Q.\u000bb\u00017B\u0019\u0001La\b\u0005\u000bAL#\u0019A.\u0011\u0007a\u0013\u0019\u0003B\u0003tS\t\u00071\fE\u0002Y\u0005O!QA^\u0015C\u0002m\u00032\u0001\u0017B\u0016\t\u0015I\u0018F1\u0001\\!\rA&q\u0006\u0003\u0006y&\u0012\ra\u0017\t\u00041\nMB!B@*\u0005\u0004Y\u0006c\u0001-\u00038\u00111\u0011QA\u0015C\u0002m\u00032\u0001\u0017B\u001e\t\u0019\tY!\u000bb\u00017B\u0019\u0001La\u0010\u0005\r\u0005E\u0011F1\u0001\\!\rA&1\t\u0003\u0007\u0003/I#\u0019A.\u0011\u0007a\u00139\u0005\u0002\u0004\u0002\u001e%\u0012\ra\u0017\t\u00041\n-CABA\u0012S\t\u00071\fE\u0002Y\u0005\u001f\"a!!\u000b*\u0005\u0004Y\u0006c\u0001-\u0003T\u00111\u0011qF\u0015C\u0002mC\u0011\"a\u0014*!\u0003\u0005\rA!\u0003\t\u0013\u0005U\u0013\u0006%AA\u0002\t5\u0001\"CA.SA\u0005\t\u0019\u0001B\t\u0011%\t\t\'\u000bI\u0001\u0002\u0004\u0011)\u0002C\u0005\u0002h%\u0002\n\u00111\u0001\u0003\u001a!I\u0011QN\u0015\u0011\u0002\u0003\u0007!Q\u0004\u0005\n\u0003gJ\u0003\u0013!a\u0001\u0005CA\u0011\"!\u001f*!\u0003\u0005\rA!\n\t\u0013\u0005}\u0014\u0006%AA\u0002\t%\u0002\"CACSA\u0005\t\u0019\u0001B\u0017\u0011%\tY)\u000bI\u0001\u0002\u0004\u0011\t\u0004C\u0005\u0002\u0012&\u0002\n\u00111\u0001\u00036!I\u0011qS\u0015\u0011\u0002\u0003\u0007!\u0011\b\u0005\n\u0003;K\u0003\u0013!a\u0001\u0005{A\u0011\"a)*!\u0003\u0005\rA!\u0011\t\u0013\u0005%\u0016\u0006%AA\u0002\t\u0015\u0003\"CAXSA\u0005\t\u0019\u0001B%\u0011%\t),\u000bI\u0001\u0002\u0004\u0011i\u0005C\u0005\u0002<&\u0002\n\u00111\u0001\u0003R\u0005q1m\u001c9zI\u0011,g-Y;mi\u0012\nT\u0003\u000bB@\u0005+\u00139J!\'\u0003\u001c\nu%q\u0014BQ\u0005G\u0013)Ka*\u0003*\n-&Q\u0016BX\u0005c\u0013\u0019L!.\u00038\neVC\u0001BAU\r9&1Q\u0016\u0003\u0005\u000b\u0003BAa\"\u0003\u00126\u0011!\u0011\u0012\u0006\u0005\u0005\u0017\u0013i)A\u0005v]\u000eDWmY6fI*\u0019!qR&\u0002\u0015\u0005tgn\u001c;bi&|g.\u0003\u0003\u0003\u0014\n%%!E;oG\",7m[3e-\u0006\u0014\u0018.\u00198dK\u0012)!L\u000bb\u00017\u0012)AM\u000bb\u00017\u0012)qM\u000bb\u00017\u0012)!N\u000bb\u00017\u0012)QN\u000bb\u00017\u0012)\u0001O\u000bb\u00017\u0012)1O\u000bb\u00017\u0012)aO\u000bb\u00017\u0012)\u0011P\u000bb\u00017\u0012)AP\u000bb\u00017\u0012)qP\u000bb\u00017\u00121\u0011Q\u0001\u0016C\u0002m#a!a\u0003+\u0005\u0004YFABA\tU\t\u00071\f\u0002\u0004\u0002\u0018)\u0012\ra\u0017\u0003\u0007\u0003;Q#\u0019A.\u0005\r\u0005\r\"F1\u0001\\\t\u0019\tIC\u000bb\u00017\u00121\u0011q\u0006\u0016C\u0002m\u000babY8qs\u0012\"WMZ1vYR$#\'\u0006\u0015\u0003@\n\r\'Q\u0019Bd\u0005\u0013\u0014YM!4\u0003P\nE\'1\u001bBk\u0005/\u0014INa7\u0003^\n}\'\u0011\u001dBr\u0005K\u00149/\u0006\u0002\u0003B*\u001a!Ma!\u0005\u000bi[#\u0019A.\u0005\u000b\u0011\\#\u0019A.\u0005\u000b\u001d\\#\u0019A.\u0005\u000b)\\#\u0019A.\u0005\u000b5\\#\u0019A.\u0005\u000bA\\#\u0019A.\u0005\u000bM\\#\u0019A.\u0005\u000bY\\#\u0019A.\u0005\u000be\\#\u0019A.\u0005\u000bq\\#\u0019A.\u0005\u000b}\\#\u0019A.\u0005\r\u0005\u00151F1\u0001\\\t\u0019\tYa\u000bb\u00017\u00121\u0011\u0011C\u0016C\u0002m#a!a\u0006,\u0005\u0004YFABA\u000fW\t\u00071\f\u0002\u0004\u0002$-\u0012\ra\u0017\u0003\u0007\u0003SY#\u0019A.\u0005\r\u0005=2F1\u0001\\\u00039\u0019w\u000e]=%I\u00164\u0017-\u001e7uIM*\u0002F!<\u0003r\nM(Q\u001fB|\u0005s\u0014YP!@\u0003\u0000\u000e\u000511AB\u0003\u0007\u000f\u0019Iaa\u0003\u0004\u000e\r=1\u0011CB\n\u0007+)\"Aa<+\u0007\u0015\u0014\u0019\tB\u0003[Y\t\u00071\fB\u0003eY\t\u00071\fB\u0003hY\t\u00071\fB\u0003kY\t\u00071\fB\u0003nY\t\u00071\fB\u0003qY\t\u00071\fB\u0003tY\t\u00071\fB\u0003wY\t\u00071\fB\u0003zY\t\u00071\fB\u0003}Y\t\u00071\fB\u0003\u0000Y\t\u00071\f\u0002\u0004\u0002\u00061\u0012\ra\u0017\u0003\u0007\u0003\u0017a#\u0019A.\u0005\r\u0005EAF1\u0001\\\t\u0019\t9\u0002\fb\u00017\u00121\u0011Q\u0004\u0017C\u0002m#a!a\t-\u0005\u0004YFABA\u0015Y\t\u00071\f\u0002\u0004\u000201\u0012\raW\u0001\u000fG>\u0004\u0018\u0010\n3fM\u0006,H\u000e\u001e\u00135+!\u001aYba\b\u0004\"\r\r2QEB\u0014\u0007S\u0019Yc!\f\u00040\rE21GB\u001b\u0007o\u0019Ida\u000f\u0004>\r}2\u0011IB\"+\t\u0019iBK\u0002i\u0005\u0007#QAW\u0017C\u0002m#Q\u0001Z\u0017C\u0002m#QaZ\u0017C\u0002m#QA[\u0017C\u0002m#Q!\\\u0017C\u0002m#Q\u0001]\u0017C\u0002m#Qa]\u0017C\u0002m#QA^\u0017C\u0002m#Q!_\u0017C\u0002m#Q\u0001`\u0017C\u0002m#Qa`\u0017C\u0002m#a!!\u0002.\u0005\u0004YFABA\u0006[\t\u00071\f\u0002\u0004\u0002\u00125\u0012\ra\u0017\u0003\u0007\u0003/i#\u0019A.\u0005\r\u0005uQF1\u0001\\\t\u0019\t\u0019#\fb\u00017\u00121\u0011\u0011F\u0017C\u0002m#a!a\f.\u0005\u0004Y\u0016AD2paf$C-\u001a4bk2$H%N\u000b)\u0007\u0013\u001aiea\u0014\u0004R\rM3QKB,\u00073\u001aYf!\u0018\u0004`\r\u000541MB3\u0007O\u001aIga\u001b\u0004n\r=4\u0011O\u000b\u0003\u0007\u0017R3a\u001bBB\t\u0015QfF1\u0001\\\t\u0015!gF1\u0001\\\t\u00159gF1\u0001\\\t\u0015QgF1\u0001\\\t\u0015igF1\u0001\\\t\u0015\u0001hF1\u0001\\\t\u0015\u0019hF1\u0001\\\t\u00151hF1\u0001\\\t\u0015IhF1\u0001\\\t\u0015ahF1\u0001\\\t\u0015yhF1\u0001\\\t\u0019\t)A\fb\u00017\u00121\u00111\u0002\u0018C\u0002m#a!!\u0005/\u0005\u0004YFABA\f]\t\u00071\f\u0002\u0004\u0002\u001e9\u0012\ra\u0017\u0003\u0007\u0003Gq#\u0019A.\u0005\r\u0005%bF1\u0001\\\t\u0019\tyC\fb\u00017\u0006q1m\u001c9zI\u0011,g-Y;mi\u00122T\u0003KB<\u0007w\u001aiha \u0004\u0002\u000e\r5QQBD\u0007\u0013\u001bYi!$\u0004\u0010\u000eE51SBK\u0007/\u001bIja\'\u0004\u001e\u000e}UCAB=U\rq\'1\u0011\u0003\u00065>\u0012\ra\u0017\u0003\u0006I>\u0012\ra\u0017\u0003\u0006O>\u0012\ra\u0017\u0003\u0006U>\u0012\ra\u0017\u0003\u0006[>\u0012\ra\u0017\u0003\u0006a>\u0012\ra\u0017\u0003\u0006g>\u0012\ra\u0017\u0003\u0006m>\u0012\ra\u0017\u0003\u0006s>\u0012\ra\u0017\u0003\u0006y>\u0012\ra\u0017\u0003\u0006\u007f>\u0012\ra\u0017\u0003\u0007\u0003\u000by#\u0019A.\u0005\r\u0005-qF1\u0001\\\t\u0019\t\tb\fb\u00017\u00121\u0011qC\u0018C\u0002m#a!!\b0\u0005\u0004YFABA\u0012_\t\u00071\f\u0002\u0004\u0002*=\u0012\ra\u0017\u0003\u0007\u0003_y#\u0019A.\u0002\u001d\r|\u0007/\u001f\u0013eK\u001a\fW\u000f\u001c;%oUA3QUBU\u0007W\u001bika,\u00042\u000eM6QWB\\\u0007s\u001bYl!0\u0004@\u000e\u000571YBc\u0007\u000f\u001cIma3\u0004NV\u00111q\u0015\u0016\u0004c\n\rE!\u0002.1\u0005\u0004YF!\u000231\u0005\u0004YF!B41\u0005\u0004YF!\u000261\u0005\u0004YF!B71\u0005\u0004YF!\u000291\u0005\u0004YF!B:1\u0005\u0004YF!\u0002<1\u0005\u0004YF!B=1\u0005\u0004YF!\u0002?1\u0005\u0004YF!B@1\u0005\u0004YFABA\u0003a\t\u00071\f\u0002\u0004\u0002\fA\u0012\ra\u0017\u0003\u0007\u0003#\u0001$\u0019A.\u0005\r\u0005]\u0001G1\u0001\\\t\u0019\ti\u0002\rb\u00017\u00121\u00111\u0005\u0019C\u0002m#a!!\u000b1\u0005\u0004YFABA\u0018a\t\u00071,\u0001\bd_BLH\u0005Z3gCVdG\u000f\n\u001d\u0016Q\rM7q[Bm\u00077\u001cina8\u0004b\u000e\r8Q]Bt\u0007S\u001cYo!<\u0004p\u000eE81_B{\u0007o\u001cIpa?\u0016\u0005\rU\'f\u0001;\u0003\u0004\u0012)!,\rb\u00017\u0012)A-\rb\u00017\u0012)q-\rb\u00017\u0012)!.\rb\u00017\u0012)Q.\rb\u00017\u0012)\u0001/\rb\u00017\u0012)1/\rb\u00017\u0012)a/\rb\u00017\u0012)\u00110\rb\u00017\u0012)A0\rb\u00017\u0012)q0\rb\u00017\u00121\u0011QA\u0019C\u0002m#a!a\u00032\u0005\u0004YFABA\tc\t\u00071\f\u0002\u0004\u0002\u0018E\u0012\ra\u0017\u0003\u0007\u0003;\t$\u0019A.\u0005\r\u0005\r\u0012G1\u0001\\\t\u0019\tI#\rb\u00017\u00121\u0011qF\u0019C\u0002m\u000babY8qs\u0012\"WMZ1vYR$\u0013(\u0006\u0015\u0005\u0002\u0011\u0015Aq\u0001C\u0005\t\u0017!i\u0001b\u0004\u0005\u0012\u0011MAQ\u0003C\f\t3!Y\u0002\"\b\u0005 \u0011\u0005B1\u0005C\u0013\tO!I#\u0006\u0002\u0005\u0004)\u001aqOa!\u0005\u000bi\u0013$\u0019A.\u0005\u000b\u0011\u0014$\u0019A.\u0005\u000b\u001d\u0014$\u0019A.\u0005\u000b)\u0014$\u0019A.\u0005\u000b5\u0014$\u0019A.\u0005\u000bA\u0014$\u0019A.\u0005\u000bM\u0014$\u0019A.\u0005\u000bY\u0014$\u0019A.\u0005\u000be\u0014$\u0019A.\u0005\u000bq\u0014$\u0019A.\u0005\u000b}\u0014$\u0019A.\u0005\r\u0005\u0015!G1\u0001\\\t\u0019\tYA\rb\u00017\u00121\u0011\u0011\u0003\u001aC\u0002m#a!a\u00063\u0005\u0004YFABA\u000fe\t\u00071\f\u0002\u0004\u0002$I\u0012\ra\u0017\u0003\u0007\u0003S\u0011$\u0019A.\u0005\r\u0005=\"G1\u0001\\\u0003=\u0019w\u000e]=%I\u00164\u0017-\u001e7uIE\u0002T\u0003\u000bC\u0018\tg!)\u0004b\u000e\u0005:\u0011mBQ\bC \t\u0003\"\u0019\u0005\"\u0012\u0005H\u0011%C1\nC\'\t\u001f\"\t\u0006b\u0015\u0005V\u0011]SC\u0001C\u0019U\rQ(1\u0011\u0003\u00065N\u0012\ra\u0017\u0003\u0006IN\u0012\ra\u0017\u0003\u0006ON\u0012\ra\u0017\u0003\u0006UN\u0012\ra\u0017\u0003\u0006[N\u0012\ra\u0017\u0003\u0006aN\u0012\ra\u0017\u0003\u0006gN\u0012\ra\u0017\u0003\u0006mN\u0012\ra\u0017\u0003\u0006sN\u0012\ra\u0017\u0003\u0006yN\u0012\ra\u0017\u0003\u0006\u007fN\u0012\ra\u0017\u0003\u0007\u0003\u000b\u0019$\u0019A.\u0005\r\u0005-1G1\u0001\\\t\u0019\t\tb\rb\u00017\u00121\u0011qC\u001aC\u0002m#a!!\b4\u0005\u0004YFABA\u0012g\t\u00071\f\u0002\u0004\u0002*M\u0012\ra\u0017\u0003\u0007\u0003_\u0019$\u0019A.\u0002\u001f\r|\u0007/\u001f\u0013eK\u001a\fW\u000f\u001c;%cE*\u0002\u0006\"\u0018\u0005b\u0011\rDQ\rC4\tS\"Y\u0007\"\u001c\u0005p\u0011ED1\u000fC;\to\"I\bb\u001f\u0005~\u0011}D\u0011\u0011CB\t\u000b+\"\u0001b\u0018+\u0007u\u0014\u0019\tB\u0003[i\t\u00071\fB\u0003ei\t\u00071\fB\u0003hi\t\u00071\fB\u0003ki\t\u00071\fB\u0003ni\t\u00071\fB\u0003qi\t\u00071\fB\u0003ti\t\u00071\fB\u0003wi\t\u00071\fB\u0003zi\t\u00071\fB\u0003}i\t\u00071\fB\u0003\u0000i\t\u00071\f\u0002\u0004\u0002\u0006Q\u0012\ra\u0017\u0003\u0007\u0003\u0017!$\u0019A.\u0005\r\u0005EAG1\u0001\\\t\u0019\t9\u0002\u000eb\u00017\u00121\u0011Q\u0004\u001bC\u0002m#a!a\t5\u0005\u0004YFABA\u0015i\t\u00071\f\u0002\u0004\u00020Q\u0012\raW\u0001\u0010G>\u0004\u0018\u0010\n3fM\u0006,H\u000e\u001e\u00132eUAC1\u0012CH\t##\u0019\n\"&\u0005\u0018\u0012eE1\u0014CO\t?#\t\u000bb)\u0005&\u0012\u001dF\u0011\u0016CV\t[#y\u000b\"-\u00054V\u0011AQ\u0012\u0016\u0005\u0003\u0003\u0011\u0019\tB\u0003[k\t\u00071\fB\u0003ek\t\u00071\fB\u0003hk\t\u00071\fB\u0003kk\t\u00071\fB\u0003nk\t\u00071\fB\u0003qk\t\u00071\fB\u0003tk\t\u00071\fB\u0003wk\t\u00071\fB\u0003zk\t\u00071\fB\u0003}k\t\u00071\fB\u0003\u0000k\t\u00071\f\u0002\u0004\u0002\u0006U\u0012\ra\u0017\u0003\u0007\u0003\u0017)$\u0019A.\u0005\r\u0005EQG1\u0001\\\t\u0019\t9\"\u000eb\u00017\u00121\u0011QD\u001bC\u0002m#a!a\t6\u0005\u0004YFABA\u0015k\t\u00071\f\u0002\u0004\u00020U\u0012\raW\u0001\u0010G>\u0004\u0018\u0010\n3fM\u0006,H\u000e\u001e\u00132gUAC\u0011\u0018C_\t\u007f#\t\rb1\u0005F\u0012\u001dG\u0011\u001aCf\t\u001b$y\r\"5\u0005T\u0012UGq\u001bCm\t7$i\u000eb8\u0005bV\u0011A1\u0018\u0016\u0005\u0003\u000f\u0011\u0019\tB\u0003[m\t\u00071\fB\u0003em\t\u00071\fB\u0003hm\t\u00071\fB\u0003km\t\u00071\fB\u0003nm\t\u00071\fB\u0003qm\t\u00071\fB\u0003tm\t\u00071\fB\u0003wm\t\u00071\fB\u0003zm\t\u00071\fB\u0003}m\t\u00071\fB\u0003\u0000m\t\u00071\f\u0002\u0004\u0002\u0006Y\u0012\ra\u0017\u0003\u0007\u0003\u00171$\u0019A.\u0005\r\u0005EaG1\u0001\\\t\u0019\t9B\u000eb\u00017\u00121\u0011Q\u0004\u001cC\u0002m#a!a\t7\u0005\u0004YFABA\u0015m\t\u00071\f\u0002\u0004\u00020Y\u0012\raW\u0001\u0010G>\u0004\u0018\u0010\n3fM\u0006,H\u000e\u001e\u00132iUACq\u001dCv\t[$y\u000f\"=\u0005t\u0012UHq\u001fC}\tw$i\u0010b@\u0006\u0002\u0015\rQQAC\u0004\u000b\u0013)Y!\"\u0004\u0006\u0010U\u0011A\u0011\u001e\u0016\u0005\u0003\u001b\u0011\u0019\tB\u0003[o\t\u00071\fB\u0003eo\t\u00071\fB\u0003ho\t\u00071\fB\u0003ko\t\u00071\fB\u0003no\t\u00071\fB\u0003qo\t\u00071\fB\u0003to\t\u00071\fB\u0003wo\t\u00071\fB\u0003zo\t\u00071\fB\u0003}o\t\u00071\fB\u0003\u0000o\t\u00071\f\u0002\u0004\u0002\u0006]\u0012\ra\u0017\u0003\u0007\u0003\u00179$\u0019A.\u0005\r\u0005EqG1\u0001\\\t\u0019\t9b\u000eb\u00017\u00121\u0011QD\u001cC\u0002m#a!a\t8\u0005\u0004YFABA\u0015o\t\u00071\f\u0002\u0004\u00020]\u0012\raW\u0001\u0010G>\u0004\u0018\u0010\n3fM\u0006,H\u000e\u001e\u00132kUASQCC\r\u000b7)i\"b\b\u0006\"\u0015\rRQEC\u0014\u000bS)Y#\"\f\u00060\u0015ER1GC\u001b\u000bo)I$b\u000f\u0006>U\u0011Qq\u0003\u0016\u0005\u0003\'\u0011\u0019\tB\u0003[q\t\u00071\fB\u0003eq\t\u00071\fB\u0003hq\t\u00071\fB\u0003kq\t\u00071\fB\u0003nq\t\u00071\fB\u0003qq\t\u00071\fB\u0003tq\t\u00071\fB\u0003wq\t\u00071\fB\u0003zq\t\u00071\fB\u0003}q\t\u00071\fB\u0003\u0000q\t\u00071\f\u0002\u0004\u0002\u0006a\u0012\ra\u0017\u0003\u0007\u0003\u0017A$\u0019A.\u0005\r\u0005E\u0001H1\u0001\\\t\u0019\t9\u0002\u000fb\u00017\u00121\u0011Q\u0004\u001dC\u0002m#a!a\t9\u0005\u0004YFABA\u0015q\t\u00071\f\u0002\u0004\u00020a\u0012\raW\u0001\u0010G>\u0004\u0018\u0010\n3fM\u0006,H\u000e\u001e\u00132mUAS1IC$\u000b\u0013*Y%\"\u0014\u0006P\u0015ES1KC+\u000b/*I&b\u0017\u0006^\u0015}S\u0011MC2\u000bK*9\'\"\u001b\u0006lU\u0011QQ\t\u0016\u0005\u00033\u0011\u0019\tB\u0003[s\t\u00071\fB\u0003es\t\u00071\fB\u0003hs\t\u00071\fB\u0003ks\t\u00071\fB\u0003ns\t\u00071\fB\u0003qs\t\u00071\fB\u0003ts\t\u00071\fB\u0003ws\t\u00071\fB\u0003zs\t\u00071\fB\u0003}s\t\u00071\fB\u0003\u0000s\t\u00071\f\u0002\u0004\u0002\u0006e\u0012\ra\u0017\u0003\u0007\u0003\u0017I$\u0019A.\u0005\r\u0005E\u0011H1\u0001\\\t\u0019\t9\"\u000fb\u00017\u00121\u0011QD\u001dC\u0002m#a!a\t:\u0005\u0004YFABA\u0015s\t\u00071\f\u0002\u0004\u00020e\u0012\raW\u0001\u0010G>\u0004\u0018\u0010\n3fM\u0006,H\u000e\u001e\u00132oUAS\u0011OC;\u000bo*I(b\u001f\u0006~\u0015}T\u0011QCB\u000b\u000b+9)\"#\u0006\f\u00165UqRCI\u000b\'+)*b&\u0006\u001aV\u0011Q1\u000f\u0016\u0005\u0003?\u0011\u0019\tB\u0003[u\t\u00071\fB\u0003eu\t\u00071\fB\u0003hu\t\u00071\fB\u0003ku\t\u00071\fB\u0003nu\t\u00071\fB\u0003qu\t\u00071\fB\u0003tu\t\u00071\fB\u0003wu\t\u00071\fB\u0003zu\t\u00071\fB\u0003}u\t\u00071\fB\u0003\u0000u\t\u00071\f\u0002\u0004\u0002\u0006i\u0012\ra\u0017\u0003\u0007\u0003\u0017Q$\u0019A.\u0005\r\u0005E!H1\u0001\\\t\u0019\t9B\u000fb\u00017\u00121\u0011Q\u0004\u001eC\u0002m#a!a\t;\u0005\u0004YFABA\u0015u\t\u00071\f\u0002\u0004\u00020i\u0012\raW\u0001\u0010G>\u0004\u0018\u0010\n3fM\u0006,H\u000e\u001e\u00132qUASqTCR\u000bK+9+\"+\u0006,\u00165VqVCY\u000bg+),b.\u0006:\u0016mVQXC`\u000b\u0003,\u0019-\"2\u0006HV\u0011Q\u0011\u0015\u0016\u0005\u0003K\u0011\u0019\tB\u0003[w\t\u00071\fB\u0003ew\t\u00071\fB\u0003hw\t\u00071\fB\u0003kw\t\u00071\fB\u0003nw\t\u00071\fB\u0003qw\t\u00071\fB\u0003tw\t\u00071\fB\u0003ww\t\u00071\fB\u0003zw\t\u00071\fB\u0003}w\t\u00071\fB\u0003\u0000w\t\u00071\f\u0002\u0004\u0002\u0006m\u0012\ra\u0017\u0003\u0007\u0003\u0017Y$\u0019A.\u0005\r\u0005E1H1\u0001\\\t\u0019\t9b\u000fb\u00017\u00121\u0011QD\u001eC\u0002m#a!a\t<\u0005\u0004YFABA\u0015w\t\u00071\f\u0002\u0004\u00020m\u0012\raW\u0001\u0010G>\u0004\u0018\u0010\n3fM\u0006,H\u000e\u001e\u00132sUASQZCi\u000b\',).b6\u0006Z\u0016mWQ\\Cp\u000bC,\u0019/\":\u0006h\u0016%X1^Cw\u000b_,\t0b=\u0006vV\u0011Qq\u001a\u0016\u0005\u0003W\u0011\u0019\tB\u0003[y\t\u00071\fB\u0003ey\t\u00071\fB\u0003hy\t\u00071\fB\u0003ky\t\u00071\fB\u0003ny\t\u00071\fB\u0003qy\t\u00071\fB\u0003ty\t\u00071\fB\u0003wy\t\u00071\fB\u0003zy\t\u00071\fB\u0003}y\t\u00071\fB\u0003\u0000y\t\u00071\f\u0002\u0004\u0002\u0006q\u0012\ra\u0017\u0003\u0007\u0003\u0017a$\u0019A.\u0005\r\u0005EAH1\u0001\\\t\u0019\t9\u0002\u0010b\u00017\u00121\u0011Q\u0004\u001fC\u0002m#a!a\t=\u0005\u0004YFABA\u0015y\t\u00071\f\u0002\u0004\u00020q\u0012\raW\u0001\u000eaJ|G-^2u!J,g-\u001b=\u0016\u0005\u0015m\b\u0003BC\u007f\r\u000fi!!b@\u000b\t\u0019\u0005a1A\u0001\u0005Y\u0006twM\u0003\u0002\u0007\u0006\u0005!!.\u0019<b\u0013\u0011\ti0b@\u0002\u001fA\u0014x\u000eZ;di&#XM]1u_J,\"A\"\u0004\u0011\u000b\u0019=aQC0\u000e\u0005\u0019E!b\u0001D\n\u0017\u0006Q1m\u001c7mK\u000e$\u0018n\u001c8\n\t\u0019]a\u0011\u0003\u0002\t\u0013R,\'/\u0019;pe\u0006A1-\u00198FcV\fG\u000e\u0006\u0003\u0007\u001e\u0019\r\u0002cA)\u0007 %\u0019a\u0011E&\u0003\u000f\t{w\u000e\\3b]\"AaQE \u0002\u0002\u0003\u0007q,A\u0002yIE\n!\u0003\u001d:pIV\u001cG/\u00127f[\u0016tGOT1nKR!Q1 D\u0016\u0011%1)\u0003QA\u0001\u0002\u00041i\u0003E\u0002R\r_I1A\"\rL\u0005\rIe\u000e^\u0001\tQ\u0006\u001c\bnQ8eKR\u0011aQF\u0001\u0007KF,\u0018\r\\:\u0015\t\u0019ua1\b\u0005\t\rK\u0011\u0015\u0011!a\u0001?\u00069A+\u001e9mKFJ\u0004CA)E\'\u0011!\u0005Kb\u0011\u0011\t\u0019\u0015c1J\u0007\u0003\r\u000fRAA\"\u0013\u0007\u0004\u0005\u0011\u0011n\\\u0005\u0005\u0003\u001729\u0005\u0006\u0002\u0007@Q\u0011Q1`\u0001\u0006CB\u0004H._\u000b)\r+2YFb\u0018\u0007d\u0019\u001dd1\u000eD8\rg29Hb\u001f\u0007\u0000\u0019\req\u0011DF\r\u001f3\u0019Jb&\u0007\u001c\u001a}e1\u0015\u000b)\r/2)Kb*\u0007*\u001a-fQ\u0016DX\rc3\u0019L\".\u00078\u001aef1\u0018D_\r\u007f3\tMb1\u0007F\u001a\u001dg\u0011\u001a\t)#\u00021IF\"\u0018\u0007b\u0019\u0015d\u0011\u000eD7\rc2)H\"\u001f\u0007~\u0019\u0005eQ\u0011DE\r\u001b3\tJ\"&\u0007\u001a\u001aue\u0011\u0015\t\u00041\u001amC!\u0002.H\u0005\u0004Y\u0006c\u0001-\u0007`\u0011)Am\u0012b\u00017B\u0019\u0001Lb\u0019\u0005\u000b\u001d<%\u0019A.\u0011\u0007a39\u0007B\u0003k\u000f\n\u00071\fE\u0002Y\rW\"Q!\\$C\u0002m\u00032\u0001\u0017D8\t\u0015\u0001xI1\u0001\\!\rAf1\u000f\u0003\u0006g\u001e\u0013\ra\u0017\t\u00041\u001a]D!\u0002<H\u0005\u0004Y\u0006c\u0001-\u0007|\u0011)\u0011p\u0012b\u00017B\u0019\u0001Lb \u0005\u000bq<%\u0019A.\u0011\u0007a3\u0019\tB\u0003\u0000\u000f\n\u00071\fE\u0002Y\r\u000f#a!!\u0002H\u0005\u0004Y\u0006c\u0001-\u0007\f\u00121\u00111B$C\u0002m\u00032\u0001\u0017DH\t\u0019\t\tb\u0012b\u00017B\u0019\u0001Lb%\u0005\r\u0005]qI1\u0001\\!\rAfq\u0013\u0003\u0007\u0003;9%\u0019A.\u0011\u0007a3Y\n\u0002\u0004\u0002$\u001d\u0013\ra\u0017\t\u00041\u001a}EABA\u0015\u000f\n\u00071\fE\u0002Y\rG#a!a\fH\u0005\u0004Y\u0006bBA(\u000f\u0002\u0007a\u0011\f\u0005\b\u0003+:\u0005\u0019\u0001D/\u0011\u001d\tYf\u0012a\u0001\rCBq!!\u0019H\u0001\u00041)\u0007C\u0004\u0002h\u001d\u0003\rA\"\u001b\t\u000f\u00055t\t1\u0001\u0007n!9\u00111O$A\u0002\u0019E\u0004bBA=\u000f\u0002\u0007aQ\u000f\u0005\b\u0003\u007f:\u0005\u0019\u0001D=\u0011\u001d\t)i\u0012a\u0001\r{Bq!a#H\u0001\u00041\t\tC\u0004\u0002\u0012\u001e\u0003\rA\"\"\t\u000f\u0005]u\t1\u0001\u0007\n\"9\u0011QT$A\u0002\u00195\u0005bBAR\u000f\u0002\u0007a\u0011\u0013\u0005\b\u0003S;\u0005\u0019\u0001DK\u0011\u001d\tyk\u0012a\u0001\r3Cq!!.H\u0001\u00041i\nC\u0004\u0002<\u001e\u0003\rA\")\u0002\u000fUt\u0017\r\u001d9msVAcq\u001aDn\r?4\u0019Ob:\u0007l\u001a=h1\u001fD|\rw4ypb\u0001\b\b\u001d-qqBD\n\u000f/9Ybb\b\b$Q!a\u0011[D\u0013!\u0015\tf1\u001bDl\u0013\r1)n\u0013\u0002\u0007\u001fB$\u0018n\u001c8\u0011QE\u0003a\u0011\u001cDo\rC4)O\";\u0007n\u001aEhQ\u001fD}\r{<\ta\"\u0002\b\n\u001d5q\u0011CD\u000b\u000f39ib\"\t\u0011\u0007a3Y\u000eB\u0003[\u0011\n\u00071\fE\u0002Y\r?$Q\u0001\u001a%C\u0002m\u00032\u0001\u0017Dr\t\u00159\u0007J1\u0001\\!\rAfq\u001d\u0003\u0006U\"\u0013\ra\u0017\t\u00041\u001a-H!B7I\u0005\u0004Y\u0006c\u0001-\u0007p\u0012)\u0001\u000f\u0013b\u00017B\u0019\u0001Lb=\u0005\u000bMD%\u0019A.\u0011\u0007a39\u0010B\u0003w\u0011\n\u00071\fE\u0002Y\rw$Q!\u001f%C\u0002m\u00032\u0001\u0017D\u0000\t\u0015a\bJ1\u0001\\!\rAv1\u0001\u0003\u0006\u007f\"\u0013\ra\u0017\t\u00041\u001e\u001dAABA\u0003\u0011\n\u00071\fE\u0002Y\u000f\u0017!a!a\u0003I\u0005\u0004Y\u0006c\u0001-\b\u0010\u00111\u0011\u0011\u0003%C\u0002m\u00032\u0001WD\n\t\u0019\t9\u0002\u0013b\u00017B\u0019\u0001lb\u0006\u0005\r\u0005u\u0001J1\u0001\\!\rAv1\u0004\u0003\u0007\u0003GA%\u0019A.\u0011\u0007a;y\u0002\u0002\u0004\u0002*!\u0013\ra\u0017\t\u00041\u001e\rBABA\u0018\u0011\n\u00071\fC\u0005\b(!\u000b\t\u00111\u0001\u0007X\u0006\u0019\u0001\u0010\n\u0019\u0002\u0019]\u0014\u0018\u000e^3SKBd\u0017mY3\u0015\u0005\u001d5\u0002\u0003BC\u007f\u000f_IAa\"\r\u0006\u0000\n1qJ\u00196fGR\u0004
   #14 = Utf8               scala/runtime/ScalaRunTime$$anon$1
   #15 = Class              #14           // scala/runtime/ScalaRunTime$$anon$1
   #16 = Utf8               _1
   #17 = Utf8               Ljava/lang/Object;
   #18 = Utf8               TT1;
   #19 = Utf8               _2
   #20 = Utf8               TT2;
   #21 = Utf8               _3
   #22 = Utf8               TT3;
   #23 = Utf8               _4
   #24 = Utf8               TT4;
   #25 = Utf8               _5
   #26 = Utf8               TT5;
   #27 = Utf8               _6
   #28 = Utf8               TT6;
   #29 = Utf8               _7
   #30 = Utf8               TT7;
   #31 = Utf8               _8
   #32 = Utf8               TT8;
   #33 = Utf8               _9
   #34 = Utf8               TT9;
   #35 = Utf8               _10
   #36 = Utf8               TT10;
   #37 = Utf8               _11
   #38 = Utf8               TT11;
   #39 = Utf8               _12
   #40 = Utf8               TT12;
   #41 = Utf8               _13
   #42 = Utf8               TT13;
   #43 = Utf8               _14
   #44 = Utf8               TT14;
   #45 = Utf8               _15
   #46 = Utf8               TT15;
   #47 = Utf8               _16
   #48 = Utf8               TT16;
   #49 = Utf8               _17
   #50 = Utf8               TT17;
   #51 = Utf8               _18
   #52 = Utf8               TT18;
   #53 = Utf8               _19
   #54 = Utf8               TT19;
   #55 = Utf8               unapply
   #56 = Utf8               (Lscala/Tuple19;)Lscala/Option;
   #57 = Utf8               <T1:Ljava/lang/Object;T2:Ljava/lang/Object;T3:Ljava/lang/Object;T4:Ljava/lang/Object;T5:Ljava/lang/Object;T6:Ljava/lang/Object;T7:Ljava/lang/Object;T8:Ljava/lang/Object;T9:Ljava/lang/Object;T10:Ljava/lang/Object;T11:Ljava/lang/Object;T12:Ljava/lang/Object;T13:Ljava/lang/Object;T14:Ljava/lang/Object;T15:Ljava/lang/Object;T16:Ljava/lang/Object;T17:Ljava/lang/Object;T18:Ljava/lang/Object;T19:Ljava/lang/Object;>(Lscala/Tuple19<TT1;TT2;TT3;TT4;TT5;TT6;TT7;TT8;TT9;TT10;TT11;TT12;TT13;TT14;TT15;TT16;TT17;TT18;TT19;>;)Lscala/Option<Lscala/Tuple19<TT1;TT2;TT3;TT4;TT5;TT6;TT7;TT8;TT9;TT10;TT11;TT12;TT13;TT14;TT15;TT16;TT17;TT18;TT19;>;>;
   #58 = Utf8               x$0
   #59 = Utf8               scala/Tuple19$
   #60 = Class              #59           // scala/Tuple19$
   #61 = Utf8               MODULE$
   #62 = Utf8               Lscala/Tuple19$;
   #63 = NameAndType        #61:#62       // MODULE$:Lscala/Tuple19$;
   #64 = Fieldref           #60.#63       // scala/Tuple19$.MODULE$:Lscala/Tuple19$;
   #65 = NameAndType        #55:#56       // unapply:(Lscala/Tuple19;)Lscala/Option;
   #66 = Methodref          #60.#65       // scala/Tuple19$.unapply:(Lscala/Tuple19;)Lscala/Option;
   #67 = Utf8               Lscala/Tuple19;
   #68 = Utf8               apply
   #69 = Utf8               (Ljava/lang/Object;Ljava/lang/Object;Ljava/lang/Object;Ljava/lang/Object;Ljava/lang/Object;Ljava/lang/Object;Ljava/lang/Object;Ljava/lang/Object;Ljava/lang/Object;Ljava/lang/Object;Ljava/lang/Object;Ljava/lang/Object;Ljava/lang/Object;Ljava/lang/Object;Ljava/lang/Object;Ljava/lang/Object;Ljava/lang/Object;Ljava/lang/Object;Ljava/lang/Object;)Lscala/Tuple19;
   #70 = Utf8               <T1:Ljava/lang/Object;T2:Ljava/lang/Object;T3:Ljava/lang/Object;T4:Ljava/lang/Object;T5:Ljava/lang/Object;T6:Ljava/lang/Object;T7:Ljava/lang/Object;T8:Ljava/lang/Object;T9:Ljava/lang/Object;T10:Ljava/lang/Object;T11:Ljava/lang/Object;T12:Ljava/lang/Object;T13:Ljava/lang/Object;T14:Ljava/lang/Object;T15:Ljava/lang/Object;T16:Ljava/lang/Object;T17:Ljava/lang/Object;T18:Ljava/lang/Object;T19:Ljava/lang/Object;>(TT1;TT2;TT3;TT4;TT5;TT6;TT7;TT8;TT9;TT10;TT11;TT12;TT13;TT14;TT15;TT16;TT17;TT18;TT19;)Lscala/Tuple19<TT1;TT2;TT3;TT4;TT5;TT6;TT7;TT8;TT9;TT10;TT11;TT12;TT13;TT14;TT15;TT16;TT17;TT18;TT19;>;
   #71 = Utf8               <init>
   #72 = Utf8               (Ljava/lang/Object;Ljava/lang/Object;Ljava/lang/Object;Ljava/lang/Object;Ljava/lang/Object;Ljava/lang/Object;Ljava/lang/Object;Ljava/lang/Object;Ljava/lang/Object;Ljava/lang/Object;Ljava/lang/Object;Ljava/lang/Object;Ljava/lang/Object;Ljava/lang/Object;Ljava/lang/Object;Ljava/lang/Object;Ljava/lang/Object;Ljava/lang/Object;Ljava/lang/Object;)V
   #73 = NameAndType        #71:#72       // "<init>":(Ljava/lang/Object;Ljava/lang/Object;Ljava/lang/Object;Ljava/lang/Object;Ljava/lang/Object;Ljava/lang/Object;Ljava/lang/Object;Ljava/lang/Object;Ljava/lang/Object;Ljava/lang/Object;Ljava/lang/Object;Ljava/lang/Object;Ljava/lang/Object;Ljava/lang/Object;Ljava/lang/Object;Ljava/lang/Object;Ljava/lang/Object;Ljava/lang/Object;Ljava/lang/Object;)V
   #74 = Methodref          #2.#73        // scala/Tuple19."<init>":(Ljava/lang/Object;Ljava/lang/Object;Ljava/lang/Object;Ljava/lang/Object;Ljava/lang/Object;Ljava/lang/Object;Ljava/lang/Object;Ljava/lang/Object;Ljava/lang/Object;Ljava/lang/Object;Ljava/lang/Object;Ljava/lang/Object;Ljava/lang/Object;Ljava/lang/Object;Ljava/lang/Object;Ljava/lang/Object;Ljava/lang/Object;Ljava/lang/Object;Ljava/lang/Object;)V
   #75 = Utf8               productArity
   #76 = Utf8               ()I
   #77 = Utf8               productArity$
   #78 = Utf8               (Lscala/Product19;)I
   #79 = NameAndType        #77:#78       // productArity$:(Lscala/Product19;)I
   #80 = InterfaceMethodref #7.#79        // scala/Product19.productArity$:(Lscala/Product19;)I
   #81 = Utf8               this
   #82 = Utf8               productElement
   #83 = Utf8               (I)Ljava/lang/Object;
   #84 = Utf8               java/lang/IndexOutOfBoundsException
   #85 = Class              #84           // java/lang/IndexOutOfBoundsException
   #86 = Utf8               n
   #87 = Utf8               productElement$
   #88 = Utf8               (Lscala/Product19;I)Ljava/lang/Object;
   #89 = NameAndType        #87:#88       // productElement$:(Lscala/Product19;I)Ljava/lang/Object;
   #90 = InterfaceMethodref #7.#89        // scala/Product19.productElement$:(Lscala/Product19;I)Ljava/lang/Object;
   #91 = Utf8               I
   #92 = Utf8               productElementNames
   #93 = Utf8               ()Lscala/collection/Iterator;
   #94 = Utf8               ()Lscala/collection/Iterator<Ljava/lang/String;>;
   #95 = Utf8               scala/Product
   #96 = Class              #95           // scala/Product
   #97 = Utf8               productElementNames$
   #98 = Utf8               (Lscala/Product;)Lscala/collection/Iterator;
   #99 = NameAndType        #97:#98       // productElementNames$:(Lscala/Product;)Lscala/collection/Iterator;
  #100 = InterfaceMethodref #96.#99       // scala/Product.productElementNames$:(Lscala/Product;)Lscala/collection/Iterator;
  #101 = Utf8               ()Ljava/lang/Object;
  #102 = Utf8               ()TT1;
  #103 = NameAndType        #16:#17       // _1:Ljava/lang/Object;
  #104 = Fieldref           #2.#103       // scala/Tuple19._1:Ljava/lang/Object;
  #105 = Utf8               ()TT2;
  #106 = NameAndType        #19:#17       // _2:Ljava/lang/Object;
  #107 = Fieldref           #2.#106       // scala/Tuple19._2:Ljava/lang/Object;
  #108 = Utf8               ()TT3;
  #109 = NameAndType        #21:#17       // _3:Ljava/lang/Object;
  #110 = Fieldref           #2.#109       // scala/Tuple19._3:Ljava/lang/Object;
  #111 = Utf8               ()TT4;
  #112 = NameAndType        #23:#17       // _4:Ljava/lang/Object;
  #113 = Fieldref           #2.#112       // scala/Tuple19._4:Ljava/lang/Object;
  #114 = Utf8               ()TT5;
  #115 = NameAndType        #25:#17       // _5:Ljava/lang/Object;
  #116 = Fieldref           #2.#115       // scala/Tuple19._5:Ljava/lang/Object;
  #117 = Utf8               ()TT6;
  #118 = NameAndType        #27:#17       // _6:Ljava/lang/Object;
  #119 = Fieldref           #2.#118       // scala/Tuple19._6:Ljava/lang/Object;
  #120 = Utf8               ()TT7;
  #121 = NameAndType        #29:#17       // _7:Ljava/lang/Object;
  #122 = Fieldref           #2.#121       // scala/Tuple19._7:Ljava/lang/Object;
  #123 = Utf8               ()TT8;
  #124 = NameAndType        #31:#17       // _8:Ljava/lang/Object;
  #125 = Fieldref           #2.#124       // scala/Tuple19._8:Ljava/lang/Object;
  #126 = Utf8               ()TT9;
  #127 = NameAndType        #33:#17       // _9:Ljava/lang/Object;
  #128 = Fieldref           #2.#127       // scala/Tuple19._9:Ljava/lang/Object;
  #129 = Utf8               ()TT10;
  #130 = NameAndType        #35:#17       // _10:Ljava/lang/Object;
  #131 = Fieldref           #2.#130       // scala/Tuple19._10:Ljava/lang/Object;
  #132 = Utf8               ()TT11;
  #133 = NameAndType        #37:#17       // _11:Ljava/lang/Object;
  #134 = Fieldref           #2.#133       // scala/Tuple19._11:Ljava/lang/Object;
  #135 = Utf8               ()TT12;
  #136 = NameAndType        #39:#17       // _12:Ljava/lang/Object;
  #137 = Fieldref           #2.#136       // scala/Tuple19._12:Ljava/lang/Object;
  #138 = Utf8               ()TT13;
  #139 = NameAndType        #41:#17       // _13:Ljava/lang/Object;
  #140 = Fieldref           #2.#139       // scala/Tuple19._13:Ljava/lang/Object;
  #141 = Utf8               ()TT14;
  #142 = NameAndType        #43:#17       // _14:Ljava/lang/Object;
  #143 = Fieldref           #2.#142       // scala/Tuple19._14:Ljava/lang/Object;
  #144 = Utf8               ()TT15;
  #145 = NameAndType        #45:#17       // _15:Ljava/lang/Object;
  #146 = Fieldref           #2.#145       // scala/Tuple19._15:Ljava/lang/Object;
  #147 = Utf8               ()TT16;
  #148 = NameAndType        #47:#17       // _16:Ljava/lang/Object;
  #149 = Fieldref           #2.#148       // scala/Tuple19._16:Ljava/lang/Object;
  #150 = Utf8               ()TT17;
  #151 = NameAndType        #49:#17       // _17:Ljava/lang/Object;
  #152 = Fieldref           #2.#151       // scala/Tuple19._17:Ljava/lang/Object;
  #153 = Utf8               ()TT18;
  #154 = NameAndType        #51:#17       // _18:Ljava/lang/Object;
  #155 = Fieldref           #2.#154       // scala/Tuple19._18:Ljava/lang/Object;
  #156 = Utf8               ()TT19;
  #157 = NameAndType        #53:#17       // _19:Ljava/lang/Object;
  #158 = Fieldref           #2.#157       // scala/Tuple19._19:Ljava/lang/Object;
  #159 = Utf8               toString
  #160 = Utf8               ()Ljava/lang/String;
  #161 = Utf8               java/lang/StringBuilder
  #162 = Class              #161          // java/lang/StringBuilder
  #163 = Integer            20
  #164 = Utf8               (I)V
  #165 = NameAndType        #71:#164      // "<init>":(I)V
  #166 = Methodref          #162.#165     // java/lang/StringBuilder."<init>":(I)V
  #167 = Utf8               (
  #168 = String             #167          // (
  #169 = Utf8               append
  #170 = Utf8               (Ljava/lang/String;)Ljava/lang/StringBuilder;
  #171 = NameAndType        #169:#170     // append:(Ljava/lang/String;)Ljava/lang/StringBuilder;
  #172 = Methodref          #162.#171     // java/lang/StringBuilder.append:(Ljava/lang/String;)Ljava/lang/StringBuilder;
  #173 = NameAndType        #16:#101      // _1:()Ljava/lang/Object;
  #174 = Methodref          #2.#173       // scala/Tuple19._1:()Ljava/lang/Object;
  #175 = Utf8               (Ljava/lang/Object;)Ljava/lang/StringBuilder;
  #176 = NameAndType        #169:#175     // append:(Ljava/lang/Object;)Ljava/lang/StringBuilder;
  #177 = Methodref          #162.#176     // java/lang/StringBuilder.append:(Ljava/lang/Object;)Ljava/lang/StringBuilder;
  #178 = Utf8               ,
  #179 = String             #178          // ,
  #180 = NameAndType        #19:#101      // _2:()Ljava/lang/Object;
  #181 = Methodref          #2.#180       // scala/Tuple19._2:()Ljava/lang/Object;
  #182 = NameAndType        #21:#101      // _3:()Ljava/lang/Object;
  #183 = Methodref          #2.#182       // scala/Tuple19._3:()Ljava/lang/Object;
  #184 = NameAndType        #23:#101      // _4:()Ljava/lang/Object;
  #185 = Methodref          #2.#184       // scala/Tuple19._4:()Ljava/lang/Object;
  #186 = NameAndType        #25:#101      // _5:()Ljava/lang/Object;
  #187 = Methodref          #2.#186       // scala/Tuple19._5:()Ljava/lang/Object;
  #188 = NameAndType        #27:#101      // _6:()Ljava/lang/Object;
  #189 = Methodref          #2.#188       // scala/Tuple19._6:()Ljava/lang/Object;
  #190 = NameAndType        #29:#101      // _7:()Ljava/lang/Object;
  #191 = Methodref          #2.#190       // scala/Tuple19._7:()Ljava/lang/Object;
  #192 = NameAndType        #31:#101      // _8:()Ljava/lang/Object;
  #193 = Methodref          #2.#192       // scala/Tuple19._8:()Ljava/lang/Object;
  #194 = NameAndType        #33:#101      // _9:()Ljava/lang/Object;
  #195 = Methodref          #2.#194       // scala/Tuple19._9:()Ljava/lang/Object;
  #196 = NameAndType        #35:#101      // _10:()Ljava/lang/Object;
  #197 = Methodref          #2.#196       // scala/Tuple19._10:()Ljava/lang/Object;
  #198 = NameAndType        #37:#101      // _11:()Ljava/lang/Object;
  #199 = Methodref          #2.#198       // scala/Tuple19._11:()Ljava/lang/Object;
  #200 = NameAndType        #39:#101      // _12:()Ljava/lang/Object;
  #201 = Methodref          #2.#200       // scala/Tuple19._12:()Ljava/lang/Object;
  #202 = NameAndType        #41:#101      // _13:()Ljava/lang/Object;
  #203 = Methodref          #2.#202       // scala/Tuple19._13:()Ljava/lang/Object;
  #204 = NameAndType        #43:#101      // _14:()Ljava/lang/Object;
  #205 = Methodref          #2.#204       // scala/Tuple19._14:()Ljava/lang/Object;
  #206 = NameAndType        #45:#101      // _15:()Ljava/lang/Object;
  #207 = Methodref          #2.#206       // scala/Tuple19._15:()Ljava/lang/Object;
  #208 = NameAndType        #47:#101      // _16:()Ljava/lang/Object;
  #209 = Methodref          #2.#208       // scala/Tuple19._16:()Ljava/lang/Object;
  #210 = NameAndType        #49:#101      // _17:()Ljava/lang/Object;
  #211 = Methodref          #2.#210       // scala/Tuple19._17:()Ljava/lang/Object;
  #212 = NameAndType        #51:#101      // _18:()Ljava/lang/Object;
  #213 = Methodref          #2.#212       // scala/Tuple19._18:()Ljava/lang/Object;
  #214 = NameAndType        #53:#101      // _19:()Ljava/lang/Object;
  #215 = Methodref          #2.#214       // scala/Tuple19._19:()Ljava/lang/Object;
  #216 = Utf8               )
  #217 = String             #216          // )
  #218 = NameAndType        #159:#160     // toString:()Ljava/lang/String;
  #219 = Methodref          #162.#218     // java/lang/StringBuilder.toString:()Ljava/lang/String;
  #220 = Utf8               copy
  #221 = Utf8               copy$default$1
  #222 = Utf8               <T1:Ljava/lang/Object;T2:Ljava/lang/Object;T3:Ljava/lang/Object;T4:Ljava/lang/Object;T5:Ljava/lang/Object;T6:Ljava/lang/Object;T7:Ljava/lang/Object;T8:Ljava/lang/Object;T9:Ljava/lang/Object;T10:Ljava/lang/Object;T11:Ljava/lang/Object;T12:Ljava/lang/Object;T13:Ljava/lang/Object;T14:Ljava/lang/Object;T15:Ljava/lang/Object;T16:Ljava/lang/Object;T17:Ljava/lang/Object;T18:Ljava/lang/Object;T19:Ljava/lang/Object;>()TT1;
  #223 = Utf8               copy$default$10
  #224 = Utf8               <T1:Ljava/lang/Object;T2:Ljava/lang/Object;T3:Ljava/lang/Object;T4:Ljava/lang/Object;T5:Ljava/lang/Object;T6:Ljava/lang/Object;T7:Ljava/lang/Object;T8:Ljava/lang/Object;T9:Ljava/lang/Object;T10:Ljava/lang/Object;T11:Ljava/lang/Object;T12:Ljava/lang/Object;T13:Ljava/lang/Object;T14:Ljava/lang/Object;T15:Ljava/lang/Object;T16:Ljava/lang/Object;T17:Ljava/lang/Object;T18:Ljava/lang/Object;T19:Ljava/lang/Object;>()TT10;
  #225 = Utf8               copy$default$11
  #226 = Utf8               <T1:Ljava/lang/Object;T2:Ljava/lang/Object;T3:Ljava/lang/Object;T4:Ljava/lang/Object;T5:Ljava/lang/Object;T6:Ljava/lang/Object;T7:Ljava/lang/Object;T8:Ljava/lang/Object;T9:Ljava/lang/Object;T10:Ljava/lang/Object;T11:Ljava/lang/Object;T12:Ljava/lang/Object;T13:Ljava/lang/Object;T14:Ljava/lang/Object;T15:Ljava/lang/Object;T16:Ljava/lang/Object;T17:Ljava/lang/Object;T18:Ljava/lang/Object;T19:Ljava/lang/Object;>()TT11;
  #227 = Utf8               copy$default$12
  #228 = Utf8               <T1:Ljava/lang/Object;T2:Ljava/lang/Object;T3:Ljava/lang/Object;T4:Ljava/lang/Object;T5:Ljava/lang/Object;T6:Ljava/lang/Object;T7:Ljava/lang/Object;T8:Ljava/lang/Object;T9:Ljava/lang/Object;T10:Ljava/lang/Object;T11:Ljava/lang/Object;T12:Ljava/lang/Object;T13:Ljava/lang/Object;T14:Ljava/lang/Object;T15:Ljava/lang/Object;T16:Ljava/lang/Object;T17:Ljava/lang/Object;T18:Ljava/lang/Object;T19:Ljava/lang/Object;>()TT12;
  #229 = Utf8               copy$default$13
  #230 = Utf8               <T1:Ljava/lang/Object;T2:Ljava/lang/Object;T3:Ljava/lang/Object;T4:Ljava/lang/Object;T5:Ljava/lang/Object;T6:Ljava/lang/Object;T7:Ljava/lang/Object;T8:Ljava/lang/Object;T9:Ljava/lang/Object;T10:Ljava/lang/Object;T11:Ljava/lang/Object;T12:Ljava/lang/Object;T13:Ljava/lang/Object;T14:Ljava/lang/Object;T15:Ljava/lang/Object;T16:Ljava/lang/Object;T17:Ljava/lang/Object;T18:Ljava/lang/Object;T19:Ljava/lang/Object;>()TT13;
  #231 = Utf8               copy$default$14
  #232 = Utf8               <T1:Ljava/lang/Object;T2:Ljava/lang/Object;T3:Ljava/lang/Object;T4:Ljava/lang/Object;T5:Ljava/lang/Object;T6:Ljava/lang/Object;T7:Ljava/lang/Object;T8:Ljava/lang/Object;T9:Ljava/lang/Object;T10:Ljava/lang/Object;T11:Ljava/lang/Object;T12:Ljava/lang/Object;T13:Ljava/lang/Object;T14:Ljava/lang/Object;T15:Ljava/lang/Object;T16:Ljava/lang/Object;T17:Ljava/lang/Object;T18:Ljava/lang/Object;T19:Ljava/lang/Object;>()TT14;
  #233 = Utf8               copy$default$15
  #234 = Utf8               <T1:Ljava/lang/Object;T2:Ljava/lang/Object;T3:Ljava/lang/Object;T4:Ljava/lang/Object;T5:Ljava/lang/Object;T6:Ljava/lang/Object;T7:Ljava/lang/Object;T8:Ljava/lang/Object;T9:Ljava/lang/Object;T10:Ljava/lang/Object;T11:Ljava/lang/Object;T12:Ljava/lang/Object;T13:Ljava/lang/Object;T14:Ljava/lang/Object;T15:Ljava/lang/Object;T16:Ljava/lang/Object;T17:Ljava/lang/Object;T18:Ljava/lang/Object;T19:Ljava/lang/Object;>()TT15;
  #235 = Utf8               copy$default$16
  #236 = Utf8               <T1:Ljava/lang/Object;T2:Ljava/lang/Object;T3:Ljava/lang/Object;T4:Ljava/lang/Object;T5:Ljava/lang/Object;T6:Ljava/lang/Object;T7:Ljava/lang/Object;T8:Ljava/lang/Object;T9:Ljava/lang/Object;T10:Ljava/lang/Object;T11:Ljava/lang/Object;T12:Ljava/lang/Object;T13:Ljava/lang/Object;T14:Ljava/lang/Object;T15:Ljava/lang/Object;T16:Ljava/lang/Object;T17:Ljava/lang/Object;T18:Ljava/lang/Object;T19:Ljava/lang/Object;>()TT16;
  #237 = Utf8               copy$default$17
  #238 = Utf8               <T1:Ljava/lang/Object;T2:Ljava/lang/Object;T3:Ljava/lang/Object;T4:Ljava/lang/Object;T5:Ljava/lang/Object;T6:Ljava/lang/Object;T7:Ljava/lang/Object;T8:Ljava/lang/Object;T9:Ljava/lang/Object;T10:Ljava/lang/Object;T11:Ljava/lang/Object;T12:Ljava/lang/Object;T13:Ljava/lang/Object;T14:Ljava/lang/Object;T15:Ljava/lang/Object;T16:Ljava/lang/Object;T17:Ljava/lang/Object;T18:Ljava/lang/Object;T19:Ljava/lang/Object;>()TT17;
  #239 = Utf8               copy$default$18
  #240 = Utf8               <T1:Ljava/lang/Object;T2:Ljava/lang/Object;T3:Ljava/lang/Object;T4:Ljava/lang/Object;T5:Ljava/lang/Object;T6:Ljava/lang/Object;T7:Ljava/lang/Object;T8:Ljava/lang/Object;T9:Ljava/lang/Object;T10:Ljava/lang/Object;T11:Ljava/lang/Object;T12:Ljava/lang/Object;T13:Ljava/lang/Object;T14:Ljava/lang/Object;T15:Ljava/lang/Object;T16:Ljava/lang/Object;T17:Ljava/lang/Object;T18:Ljava/lang/Object;T19:Ljava/lang/Object;>()TT18;
  #241 = Utf8               copy$default$19
  #242 = Utf8               <T1:Ljava/lang/Object;T2:Ljava/lang/Object;T3:Ljava/lang/Object;T4:Ljava/lang/Object;T5:Ljava/lang/Object;T6:Ljava/lang/Object;T7:Ljava/lang/Object;T8:Ljava/lang/Object;T9:Ljava/lang/Object;T10:Ljava/lang/Object;T11:Ljava/lang/Object;T12:Ljava/lang/Object;T13:Ljava/lang/Object;T14:Ljava/lang/Object;T15:Ljava/lang/Object;T16:Ljava/lang/Object;T17:Ljava/lang/Object;T18:Ljava/lang/Object;T19:Ljava/lang/Object;>()TT19;
  #243 = Utf8               copy$default$2
  #244 = Utf8               <T1:Ljava/lang/Object;T2:Ljava/lang/Object;T3:Ljava/lang/Object;T4:Ljava/lang/Object;T5:Ljava/lang/Object;T6:Ljava/lang/Object;T7:Ljava/lang/Object;T8:Ljava/lang/Object;T9:Ljava/lang/Object;T10:Ljava/lang/Object;T11:Ljava/lang/Object;T12:Ljava/lang/Object;T13:Ljava/lang/Object;T14:Ljava/lang/Object;T15:Ljava/lang/Object;T16:Ljava/lang/Object;T17:Ljava/lang/Object;T18:Ljava/lang/Object;T19:Ljava/lang/Object;>()TT2;
  #245 = Utf8               copy$default$3
  #246 = Utf8               <T1:Ljava/lang/Object;T2:Ljava/lang/Object;T3:Ljava/lang/Object;T4:Ljava/lang/Object;T5:Ljava/lang/Object;T6:Ljava/lang/Object;T7:Ljava/lang/Object;T8:Ljava/lang/Object;T9:Ljava/lang/Object;T10:Ljava/lang/Object;T11:Ljava/lang/Object;T12:Ljava/lang/Object;T13:Ljava/lang/Object;T14:Ljava/lang/Object;T15:Ljava/lang/Object;T16:Ljava/lang/Object;T17:Ljava/lang/Object;T18:Ljava/lang/Object;T19:Ljava/lang/Object;>()TT3;
  #247 = Utf8               copy$default$4
  #248 = Utf8               <T1:Ljava/lang/Object;T2:Ljava/lang/Object;T3:Ljava/lang/Object;T4:Ljava/lang/Object;T5:Ljava/lang/Object;T6:Ljava/lang/Object;T7:Ljava/lang/Object;T8:Ljava/lang/Object;T9:Ljava/lang/Object;T10:Ljava/lang/Object;T11:Ljava/lang/Object;T12:Ljava/lang/Object;T13:Ljava/lang/Object;T14:Ljava/lang/Object;T15:Ljava/lang/Object;T16:Ljava/lang/Object;T17:Ljava/lang/Object;T18:Ljava/lang/Object;T19:Ljava/lang/Object;>()TT4;
  #249 = Utf8               copy$default$5
  #250 = Utf8               <T1:Ljava/lang/Object;T2:Ljava/lang/Object;T3:Ljava/lang/Object;T4:Ljava/lang/Object;T5:Ljava/lang/Object;T6:Ljava/lang/Object;T7:Ljava/lang/Object;T8:Ljava/lang/Object;T9:Ljava/lang/Object;T10:Ljava/lang/Object;T11:Ljava/lang/Object;T12:Ljava/lang/Object;T13:Ljava/lang/Object;T14:Ljava/lang/Object;T15:Ljava/lang/Object;T16:Ljava/lang/Object;T17:Ljava/lang/Object;T18:Ljava/lang/Object;T19:Ljava/lang/Object;>()TT5;
  #251 = Utf8               copy$default$6
  #252 = Utf8               <T1:Ljava/lang/Object;T2:Ljava/lang/Object;T3:Ljava/lang/Object;T4:Ljava/lang/Object;T5:Ljava/lang/Object;T6:Ljava/lang/Object;T7:Ljava/lang/Object;T8:Ljava/lang/Object;T9:Ljava/lang/Object;T10:Ljava/lang/Object;T11:Ljava/lang/Object;T12:Ljava/lang/Object;T13:Ljava/lang/Object;T14:Ljava/lang/Object;T15:Ljava/lang/Object;T16:Ljava/lang/Object;T17:Ljava/lang/Object;T18:Ljava/lang/Object;T19:Ljava/lang/Object;>()TT6;
  #253 = Utf8               copy$default$7
  #254 = Utf8               <T1:Ljava/lang/Object;T2:Ljava/lang/Object;T3:Ljava/lang/Object;T4:Ljava/lang/Object;T5:Ljava/lang/Object;T6:Ljava/lang/Object;T7:Ljava/lang/Object;T8:Ljava/lang/Object;T9:Ljava/lang/Object;T10:Ljava/lang/Object;T11:Ljava/lang/Object;T12:Ljava/lang/Object;T13:Ljava/lang/Object;T14:Ljava/lang/Object;T15:Ljava/lang/Object;T16:Ljava/lang/Object;T17:Ljava/lang/Object;T18:Ljava/lang/Object;T19:Ljava/lang/Object;>()TT7;
  #255 = Utf8               copy$default$8
  #256 = Utf8               <T1:Ljava/lang/Object;T2:Ljava/lang/Object;T3:Ljava/lang/Object;T4:Ljava/lang/Object;T5:Ljava/lang/Object;T6:Ljava/lang/Object;T7:Ljava/lang/Object;T8:Ljava/lang/Object;T9:Ljava/lang/Object;T10:Ljava/lang/Object;T11:Ljava/lang/Object;T12:Ljava/lang/Object;T13:Ljava/lang/Object;T14:Ljava/lang/Object;T15:Ljava/lang/Object;T16:Ljava/lang/Object;T17:Ljava/lang/Object;T18:Ljava/lang/Object;T19:Ljava/lang/Object;>()TT8;
  #257 = Utf8               copy$default$9
  #258 = Utf8               <T1:Ljava/lang/Object;T2:Ljava/lang/Object;T3:Ljava/lang/Object;T4:Ljava/lang/Object;T5:Ljava/lang/Object;T6:Ljava/lang/Object;T7:Ljava/lang/Object;T8:Ljava/lang/Object;T9:Ljava/lang/Object;T10:Ljava/lang/Object;T11:Ljava/lang/Object;T12:Ljava/lang/Object;T13:Ljava/lang/Object;T14:Ljava/lang/Object;T15:Ljava/lang/Object;T16:Ljava/lang/Object;T17:Ljava/lang/Object;T18:Ljava/lang/Object;T19:Ljava/lang/Object;>()TT9;
  #259 = Utf8               productPrefix
  #260 = Utf8               Tuple19
  #261 = String             #260          // Tuple19
  #262 = Utf8               productIterator
  #263 = Utf8               ()Lscala/collection/Iterator<Ljava/lang/Object;>;
  #264 = Utf8               (Lscala/Product;)V
  #265 = NameAndType        #71:#264      // "<init>":(Lscala/Product;)V
  #266 = Methodref          #15.#265      // scala/runtime/ScalaRunTime$$anon$1."<init>":(Lscala/Product;)V
  #267 = Utf8               canEqual
  #268 = Utf8               (Ljava/lang/Object;)Z
  #269 = Utf8               x$1
  #270 = Utf8               productElementName
  #271 = Utf8               (I)Ljava/lang/String;
  #272 = String             #16           // _1
  #273 = String             #19           // _2
  #274 = String             #21           // _3
  #275 = String             #23           // _4
  #276 = String             #25           // _5
  #277 = String             #27           // _6
  #278 = String             #29           // _7
  #279 = String             #31           // _8
  #280 = String             #33           // _9
  #281 = String             #35           // _10
  #282 = String             #37           // _11
  #283 = String             #39           // _12
  #284 = String             #41           // _13
  #285 = String             #43           // _14
  #286 = String             #45           // _15
  #287 = String             #47           // _16
  #288 = String             #49           // _17
  #289 = String             #51           // _18
  #290 = String             #53           // _19
  #291 = Utf8               scala/runtime/Statics
  #292 = Class              #291          // scala/runtime/Statics
  #293 = Utf8               ioobe
  #294 = NameAndType        #293:#83      // ioobe:(I)Ljava/lang/Object;
  #295 = Methodref          #292.#294     // scala/runtime/Statics.ioobe:(I)Ljava/lang/Object;
  #296 = Utf8               java/lang/String
  #297 = Class              #296          // java/lang/String
  #298 = Utf8               hashCode
  #299 = Utf8               scala/util/hashing/MurmurHash3$
  #300 = Class              #299          // scala/util/hashing/MurmurHash3$
  #301 = Utf8               Lscala/util/hashing/MurmurHash3$;
  #302 = NameAndType        #61:#301      // MODULE$:Lscala/util/hashing/MurmurHash3$;
  #303 = Fieldref           #300.#302     // scala/util/hashing/MurmurHash3$.MODULE$:Lscala/util/hashing/MurmurHash3$;
  #304 = Utf8               productHash
  #305 = Utf8               (Lscala/Product;)I
  #306 = NameAndType        #304:#305     // productHash:(Lscala/Product;)I
  #307 = Methodref          #300.#306     // scala/util/hashing/MurmurHash3$.productHash:(Lscala/Product;)I
  #308 = Utf8               equals
  #309 = Utf8               scala/runtime/BoxesRunTime
  #310 = Class              #309          // scala/runtime/BoxesRunTime
  #311 = Utf8               (Ljava/lang/Object;Ljava/lang/Object;)Z
  #312 = NameAndType        #308:#311     // equals:(Ljava/lang/Object;Ljava/lang/Object;)Z
  #313 = Methodref          #310.#312     // scala/runtime/BoxesRunTime.equals:(Ljava/lang/Object;Ljava/lang/Object;)Z
  #314 = Utf8               (TT1;TT2;TT3;TT4;TT5;TT6;TT7;TT8;TT9;TT10;TT11;TT12;TT13;TT14;TT15;TT16;TT17;TT18;TT19;)V
  #315 = Utf8               ()V
  #316 = NameAndType        #71:#315      // "<init>":()V
  #317 = Methodref          #5.#316       // java/lang/Object."<init>":()V
  #318 = Utf8               Signature
  #319 = Utf8               Code
  #320 = Utf8               LocalVariableTable
  #321 = Utf8               MethodParameters
  #322 = Utf8               LineNumberTable
  #323 = Utf8               Exceptions
  #324 = Utf8               StackMapTable
  #325 = Utf8               InnerClasses
  #326 = Utf8               SourceFile
  #327 = Utf8               RuntimeVisibleAnnotations
  #328 = Utf8               ScalaInlineInfo
  #329 = Utf8               ScalaSig
{
  private final T1 _1;
    descriptor: Ljava/lang/Object;
    flags: (0x0012) ACC_PRIVATE, ACC_FINAL
    Signature: #18                          // TT1;

  private final T2 _2;
    descriptor: Ljava/lang/Object;
    flags: (0x0012) ACC_PRIVATE, ACC_FINAL
    Signature: #20                          // TT2;

  private final T3 _3;
    descriptor: Ljava/lang/Object;
    flags: (0x0012) ACC_PRIVATE, ACC_FINAL
    Signature: #22                          // TT3;

  private final T4 _4;
    descriptor: Ljava/lang/Object;
    flags: (0x0012) ACC_PRIVATE, ACC_FINAL
    Signature: #24                          // TT4;

  private final T5 _5;
    descriptor: Ljava/lang/Object;
    flags: (0x0012) ACC_PRIVATE, ACC_FINAL
    Signature: #26                          // TT5;

  private final T6 _6;
    descriptor: Ljava/lang/Object;
    flags: (0x0012) ACC_PRIVATE, ACC_FINAL
    Signature: #28                          // TT6;

  private final T7 _7;
    descriptor: Ljava/lang/Object;
    flags: (0x0012) ACC_PRIVATE, ACC_FINAL
    Signature: #30                          // TT7;

  private final T8 _8;
    descriptor: Ljava/lang/Object;
    flags: (0x0012) ACC_PRIVATE, ACC_FINAL
    Signature: #32                          // TT8;

  private final T9 _9;
    descriptor: Ljava/lang/Object;
    flags: (0x0012) ACC_PRIVATE, ACC_FINAL
    Signature: #34                          // TT9;

  private final T10 _10;
    descriptor: Ljava/lang/Object;
    flags: (0x0012) ACC_PRIVATE, ACC_FINAL
    Signature: #36                          // TT10;

  private final T11 _11;
    descriptor: Ljava/lang/Object;
    flags: (0x0012) ACC_PRIVATE, ACC_FINAL
    Signature: #38                          // TT11;

  private final T12 _12;
    descriptor: Ljava/lang/Object;
    flags: (0x0012) ACC_PRIVATE, ACC_FINAL
    Signature: #40                          // TT12;

  private final T13 _13;
    descriptor: Ljava/lang/Object;
    flags: (0x0012) ACC_PRIVATE, ACC_FINAL
    Signature: #42                          // TT13;

  private final T14 _14;
    descriptor: Ljava/lang/Object;
    flags: (0x0012) ACC_PRIVATE, ACC_FINAL
    Signature: #44                          // TT14;

  private final T15 _15;
    descriptor: Ljava/lang/Object;
    flags: (0x0012) ACC_PRIVATE, ACC_FINAL
    Signature: #46                          // TT15;

  private final T16 _16;
    descriptor: Ljava/lang/Object;
    flags: (0x0012) ACC_PRIVATE, ACC_FINAL
    Signature: #48                          // TT16;

  private final T17 _17;
    descriptor: Ljava/lang/Object;
    flags: (0x0012) ACC_PRIVATE, ACC_FINAL
    Signature: #50                          // TT17;

  private final T18 _18;
    descriptor: Ljava/lang/Object;
    flags: (0x0012) ACC_PRIVATE, ACC_FINAL
    Signature: #52                          // TT18;

  private final T19 _19;
    descriptor: Ljava/lang/Object;
    flags: (0x0012) ACC_PRIVATE, ACC_FINAL
    Signature: #54                          // TT19;

  public static <T1 extends java.lang.Object, T2 extends java.lang.Object, T3 extends java.lang.Object, T4 extends java.lang.Object, T5 extends java.lang.Object, T6 extends java.lang.Object, T7 extends java.lang.Object, T8 extends java.lang.Object, T9 extends java.lang.Object, T10 extends java.lang.Object, T11 extends java.lang.Object, T12 extends java.lang.Object, T13 extends java.lang.Object, T14 extends java.lang.Object, T15 extends java.lang.Object, T16 extends java.lang.Object, T17 extends java.lang.Object, T18 extends java.lang.Object, T19 extends java.lang.Object> scala.Option<scala.Tuple19<T1, T2, T3, T4, T5, T6, T7, T8, T9, T10, T11, T12, T13, T14, T15, T16, T17, T18, T19>> unapply(scala.Tuple19<T1, T2, T3, T4, T5, T6, T7, T8, T9, T10, T11, T12, T13, T14, T15, T16, T17, T18, T19>);
    descriptor: (Lscala/Tuple19;)Lscala/Option;
    flags: (0x0009) ACC_PUBLIC, ACC_STATIC
    Code:
      stack=2, locals=1, args_size=1
         0: getstatic     #64                 // Field scala/Tuple19$.MODULE$:Lscala/Tuple19$;
         3: aload_0
         4: invokevirtual #66                 // Method scala/Tuple19$.unapply:(Lscala/Tuple19;)Lscala/Option;
         7: areturn
      LocalVariableTable:
        Start  Length  Slot  Name   Signature
            0       8     0   x$0   Lscala/Tuple19;
    Signature: #57                          // <T1:Ljava/lang/Object;T2:Ljava/lang/Object;T3:Ljava/lang/Object;T4:Ljava/lang/Object;T5:Ljava/lang/Object;T6:Ljava/lang/Object;T7:Ljava/lang/Object;T8:Ljava/lang/Object;T9:Ljava/lang/Object;T10:Ljava/lang/Object;T11:Ljava/lang/Object;T12:Ljava/lang/Object;T13:Ljava/lang/Object;T14:Ljava/lang/Object;T15:Ljava/lang/Object;T16:Ljava/lang/Object;T17:Ljava/lang/Object;T18:Ljava/lang/Object;T19:Ljava/lang/Object;>(Lscala/Tuple19<TT1;TT2;TT3;TT4;TT5;TT6;TT7;TT8;TT9;TT10;TT11;TT12;TT13;TT14;TT15;TT16;TT17;TT18;TT19;>;)Lscala/Option<Lscala/Tuple19<TT1;TT2;TT3;TT4;TT5;TT6;TT7;TT8;TT9;TT10;TT11;TT12;TT13;TT14;TT15;TT16;TT17;TT18;TT19;>;>;
    MethodParameters:
      Name                           Flags
      x$0                            final

  public static <T1 extends java.lang.Object, T2 extends java.lang.Object, T3 extends java.lang.Object, T4 extends java.lang.Object, T5 extends java.lang.Object, T6 extends java.lang.Object, T7 extends java.lang.Object, T8 extends java.lang.Object, T9 extends java.lang.Object, T10 extends java.lang.Object, T11 extends java.lang.Object, T12 extends java.lang.Object, T13 extends java.lang.Object, T14 extends java.lang.Object, T15 extends java.lang.Object, T16 extends java.lang.Object, T17 extends java.lang.Object, T18 extends java.lang.Object, T19 extends java.lang.Object> scala.Tuple19<T1, T2, T3, T4, T5, T6, T7, T8, T9, T10, T11, T12, T13, T14, T15, T16, T17, T18, T19> apply(T1, T2, T3, T4, T5, T6, T7, T8, T9, T10, T11, T12, T13, T14, T15, T16, T17, T18, T19);
    descriptor: (Ljava/lang/Object;Ljava/lang/Object;Ljava/lang/Object;Ljava/lang/Object;Ljava/lang/Object;Ljava/lang/Object;Ljava/lang/Object;Ljava/lang/Object;Ljava/lang/Object;Ljava/lang/Object;Ljava/lang/Object;Ljava/lang/Object;Ljava/lang/Object;Ljava/lang/Object;Ljava/lang/Object;Ljava/lang/Object;Ljava/lang/Object;Ljava/lang/Object;Ljava/lang/Object;)Lscala/Tuple19;
    flags: (0x0009) ACC_PUBLIC, ACC_STATIC
    Code:
      stack=21, locals=19, args_size=19
         0: getstatic     #64                 // Field scala/Tuple19$.MODULE$:Lscala/Tuple19$;
         3: pop
         4: new           #2                  // class scala/Tuple19
         7: dup
         8: aload_0
         9: aload_1
        10: aload_2
        11: aload_3
        12: aload         4
        14: aload         5
        16: aload         6
        18: aload         7
        20: aload         8
        22: aload         9
        24: aload         10
        26: aload         11
        28: aload         12
        30: aload         13
        32: aload         14
        34: aload         15
        36: aload         16
        38: aload         17
        40: aload         18
        42: invokespecial #74                 // Method "<init>":(Ljava/lang/Object;Ljava/lang/Object;Ljava/lang/Object;Ljava/lang/Object;Ljava/lang/Object;Ljava/lang/Object;Ljava/lang/Object;Ljava/lang/Object;Ljava/lang/Object;Ljava/lang/Object;Ljava/lang/Object;Ljava/lang/Object;Ljava/lang/Object;Ljava/lang/Object;Ljava/lang/Object;Ljava/lang/Object;Ljava/lang/Object;Ljava/lang/Object;Ljava/lang/Object;)V
        45: areturn
      LineNumberTable:
        line 41: 4
      LocalVariableTable:
        Start  Length  Slot  Name   Signature
            0      46     0    _1   Ljava/lang/Object;
            0      46     1    _2   Ljava/lang/Object;
            0      46     2    _3   Ljava/lang/Object;
            0      46     3    _4   Ljava/lang/Object;
            0      46     4    _5   Ljava/lang/Object;
            0      46     5    _6   Ljava/lang/Object;
            0      46     6    _7   Ljava/lang/Object;
            0      46     7    _8   Ljava/lang/Object;
            0      46     8    _9   Ljava/lang/Object;
            0      46     9   _10   Ljava/lang/Object;
            0      46    10   _11   Ljava/lang/Object;
            0      46    11   _12   Ljava/lang/Object;
            0      46    12   _13   Ljava/lang/Object;
            0      46    13   _14   Ljava/lang/Object;
            0      46    14   _15   Ljava/lang/Object;
            0      46    15   _16   Ljava/lang/Object;
            0      46    16   _17   Ljava/lang/Object;
            0      46    17   _18   Ljava/lang/Object;
            0      46    18   _19   Ljava/lang/Object;
    Signature: #70                          // <T1:Ljava/lang/Object;T2:Ljava/lang/Object;T3:Ljava/lang/Object;T4:Ljava/lang/Object;T5:Ljava/lang/Object;T6:Ljava/lang/Object;T7:Ljava/lang/Object;T8:Ljava/lang/Object;T9:Ljava/lang/Object;T10:Ljava/lang/Object;T11:Ljava/lang/Object;T12:Ljava/lang/Object;T13:Ljava/lang/Object;T14:Ljava/lang/Object;T15:Ljava/lang/Object;T16:Ljava/lang/Object;T17:Ljava/lang/Object;T18:Ljava/lang/Object;T19:Ljava/lang/Object;>(TT1;TT2;TT3;TT4;TT5;TT6;TT7;TT8;TT9;TT10;TT11;TT12;TT13;TT14;TT15;TT16;TT17;TT18;TT19;)Lscala/Tuple19<TT1;TT2;TT3;TT4;TT5;TT6;TT7;TT8;TT9;TT10;TT11;TT12;TT13;TT14;TT15;TT16;TT17;TT18;TT19;>;
    MethodParameters:
      Name                           Flags
      _1                             final
      _2                             final
      _3                             final
      _4                             final
      _5                             final
      _6                             final
      _7                             final
      _8                             final
      _9                             final
      _10                            final
      _11                            final
      _12                            final
      _13                            final
      _14                            final
      _15                            final
      _16                            final
      _17                            final
      _18                            final
      _19                            final

  public int productArity();
    descriptor: ()I
    flags: (0x0001) ACC_PUBLIC
    Code:
      stack=1, locals=1, args_size=1
         0: aload_0
         1: invokestatic  #80                 // InterfaceMethod scala/Product19.productArity$:(Lscala/Product19;)I
         4: ireturn
      LineNumberTable:
        line 41: 0
      LocalVariableTable:
        Start  Length  Slot  Name   Signature
            0       5     0  this   Lscala/Tuple19;

  public java.lang.Object productElement(int) throws java.lang.IndexOutOfBoundsException;
    descriptor: (I)Ljava/lang/Object;
    flags: (0x0001) ACC_PUBLIC
    Code:
      stack=2, locals=2, args_size=2
         0: aload_0
         1: iload_1
         2: invokestatic  #90                 // InterfaceMethod scala/Product19.productElement$:(Lscala/Product19;I)Ljava/lang/Object;
         5: areturn
      LineNumberTable:
        line 41: 0
      LocalVariableTable:
        Start  Length  Slot  Name   Signature
            0       6     0  this   Lscala/Tuple19;
            0       6     1     n   I
    Exceptions:
      throws java.lang.IndexOutOfBoundsException
    MethodParameters:
      Name                           Flags
      n                              final

  public scala.collection.Iterator<java.lang.String> productElementNames();
    descriptor: ()Lscala/collection/Iterator;
    flags: (0x0001) ACC_PUBLIC
    Code:
      stack=1, locals=1, args_size=1
         0: aload_0
         1: invokestatic  #100                // InterfaceMethod scala/Product.productElementNames$:(Lscala/Product;)Lscala/collection/Iterator;
         4: areturn
      LineNumberTable:
        line 41: 0
      LocalVariableTable:
        Start  Length  Slot  Name   Signature
            0       5     0  this   Lscala/Tuple19;
    Signature: #94                          // ()Lscala/collection/Iterator<Ljava/lang/String;>;

  public T1 _1();
    descriptor: ()Ljava/lang/Object;
    flags: (0x0001) ACC_PUBLIC
    Code:
      stack=1, locals=1, args_size=1
         0: aload_0
         1: getfield      #104                // Field _1:Ljava/lang/Object;
         4: areturn
      LineNumberTable:
        line 41: 0
      LocalVariableTable:
        Start  Length  Slot  Name   Signature
            0       5     0  this   Lscala/Tuple19;
    Signature: #102                         // ()TT1;

  public T2 _2();
    descriptor: ()Ljava/lang/Object;
    flags: (0x0001) ACC_PUBLIC
    Code:
      stack=1, locals=1, args_size=1
         0: aload_0
         1: getfield      #107                // Field _2:Ljava/lang/Object;
         4: areturn
      LineNumberTable:
        line 41: 0
      LocalVariableTable:
        Start  Length  Slot  Name   Signature
            0       5     0  this   Lscala/Tuple19;
    Signature: #105                         // ()TT2;

  public T3 _3();
    descriptor: ()Ljava/lang/Object;
    flags: (0x0001) ACC_PUBLIC
    Code:
      stack=1, locals=1, args_size=1
         0: aload_0
         1: getfield      #110                // Field _3:Ljava/lang/Object;
         4: areturn
      LineNumberTable:
        line 41: 0
      LocalVariableTable:
        Start  Length  Slot  Name   Signature
            0       5     0  this   Lscala/Tuple19;
    Signature: #108                         // ()TT3;

  public T4 _4();
    descriptor: ()Ljava/lang/Object;
    flags: (0x0001) ACC_PUBLIC
    Code:
      stack=1, locals=1, args_size=1
         0: aload_0
         1: getfield      #113                // Field _4:Ljava/lang/Object;
         4: areturn
      LineNumberTable:
        line 41: 0
      LocalVariableTable:
        Start  Length  Slot  Name   Signature
            0       5     0  this   Lscala/Tuple19;
    Signature: #111                         // ()TT4;

  public T5 _5();
    descriptor: ()Ljava/lang/Object;
    flags: (0x0001) ACC_PUBLIC
    Code:
      stack=1, locals=1, args_size=1
         0: aload_0
         1: getfield      #116                // Field _5:Ljava/lang/Object;
         4: areturn
      LineNumberTable:
        line 41: 0
      LocalVariableTable:
        Start  Length  Slot  Name   Signature
            0       5     0  this   Lscala/Tuple19;
    Signature: #114                         // ()TT5;

  public T6 _6();
    descriptor: ()Ljava/lang/Object;
    flags: (0x0001) ACC_PUBLIC
    Code:
      stack=1, locals=1, args_size=1
         0: aload_0
         1: getfield      #119                // Field _6:Ljava/lang/Object;
         4: areturn
      LineNumberTable:
        line 41: 0
      LocalVariableTable:
        Start  Length  Slot  Name   Signature
            0       5     0  this   Lscala/Tuple19;
    Signature: #117                         // ()TT6;

  public T7 _7();
    descriptor: ()Ljava/lang/Object;
    flags: (0x0001) ACC_PUBLIC
    Code:
      stack=1, locals=1, args_size=1
         0: aload_0
         1: getfield      #122                // Field _7:Ljava/lang/Object;
         4: areturn
      LineNumberTable:
        line 41: 0
      LocalVariableTable:
        Start  Length  Slot  Name   Signature
            0       5     0  this   Lscala/Tuple19;
    Signature: #120                         // ()TT7;

  public T8 _8();
    descriptor: ()Ljava/lang/Object;
    flags: (0x0001) ACC_PUBLIC
    Code:
      stack=1, locals=1, args_size=1
         0: aload_0
         1: getfield      #125                // Field _8:Ljava/lang/Object;
         4: areturn
      LineNumberTable:
        line 41: 0
      LocalVariableTable:
        Start  Length  Slot  Name   Signature
            0       5     0  this   Lscala/Tuple19;
    Signature: #123                         // ()TT8;

  public T9 _9();
    descriptor: ()Ljava/lang/Object;
    flags: (0x0001) ACC_PUBLIC
    Code:
      stack=1, locals=1, args_size=1
         0: aload_0
         1: getfield      #128                // Field _9:Ljava/lang/Object;
         4: areturn
      LineNumberTable:
        line 41: 0
      LocalVariableTable:
        Start  Length  Slot  Name   Signature
            0       5     0  this   Lscala/Tuple19;
    Signature: #126                         // ()TT9;

  public T10 _10();
    descriptor: ()Ljava/lang/Object;
    flags: (0x0001) ACC_PUBLIC
    Code:
      stack=1, locals=1, args_size=1
         0: aload_0
         1: getfield      #131                // Field _10:Ljava/lang/Object;
         4: areturn
      LineNumberTable:
        line 41: 0
      LocalVariableTable:
        Start  Length  Slot  Name   Signature
            0       5     0  this   Lscala/Tuple19;
    Signature: #129                         // ()TT10;

  public T11 _11();
    descriptor: ()Ljava/lang/Object;
    flags: (0x0001) ACC_PUBLIC
    Code:
      stack=1, locals=1, args_size=1
         0: aload_0
         1: getfield      #134                // Field _11:Ljava/lang/Object;
         4: areturn
      LineNumberTable:
        line 41: 0
      LocalVariableTable:
        Start  Length  Slot  Name   Signature
            0       5     0  this   Lscala/Tuple19;
    Signature: #132                         // ()TT11;

  public T12 _12();
    descriptor: ()Ljava/lang/Object;
    flags: (0x0001) ACC_PUBLIC
    Code:
      stack=1, locals=1, args_size=1
         0: aload_0
         1: getfield      #137                // Field _12:Ljava/lang/Object;
         4: areturn
      LineNumberTable:
        line 41: 0
      LocalVariableTable:
        Start  Length  Slot  Name   Signature
            0       5     0  this   Lscala/Tuple19;
    Signature: #135                         // ()TT12;

  public T13 _13();
    descriptor: ()Ljava/lang/Object;
    flags: (0x0001) ACC_PUBLIC
    Code:
      stack=1, locals=1, args_size=1
         0: aload_0
         1: getfield      #140                // Field _13:Ljava/lang/Object;
         4: areturn
      LineNumberTable:
        line 41: 0
      LocalVariableTable:
        Start  Length  Slot  Name   Signature
            0       5     0  this   Lscala/Tuple19;
    Signature: #138                         // ()TT13;

  public T14 _14();
    descriptor: ()Ljava/lang/Object;
    flags: (0x0001) ACC_PUBLIC
    Code:
      stack=1, locals=1, args_size=1
         0: aload_0
         1: getfield      #143                // Field _14:Ljava/lang/Object;
         4: areturn
      LineNumberTable:
        line 41: 0
      LocalVariableTable:
        Start  Length  Slot  Name   Signature
            0       5     0  this   Lscala/Tuple19;
    Signature: #141                         // ()TT14;

  public T15 _15();
    descriptor: ()Ljava/lang/Object;
    flags: (0x0001) ACC_PUBLIC
    Code:
      stack=1, locals=1, args_size=1
         0: aload_0
         1: getfield      #146                // Field _15:Ljava/lang/Object;
         4: areturn
      LineNumberTable:
        line 41: 0
      LocalVariableTable:
        Start  Length  Slot  Name   Signature
            0       5     0  this   Lscala/Tuple19;
    Signature: #144                         // ()TT15;

  public T16 _16();
    descriptor: ()Ljava/lang/Object;
    flags: (0x0001) ACC_PUBLIC
    Code:
      stack=1, locals=1, args_size=1
         0: aload_0
         1: getfield      #149                // Field _16:Ljava/lang/Object;
         4: areturn
      LineNumberTable:
        line 41: 0
      LocalVariableTable:
        Start  Length  Slot  Name   Signature
            0       5     0  this   Lscala/Tuple19;
    Signature: #147                         // ()TT16;

  public T17 _17();
    descriptor: ()Ljava/lang/Object;
    flags: (0x0001) ACC_PUBLIC
    Code:
      stack=1, locals=1, args_size=1
         0: aload_0
         1: getfield      #152                // Field _17:Ljava/lang/Object;
         4: areturn
      LineNumberTable:
        line 41: 0
      LocalVariableTable:
        Start  Length  Slot  Name   Signature
            0       5     0  this   Lscala/Tuple19;
    Signature: #150                         // ()TT17;

  public T18 _18();
    descriptor: ()Ljava/lang/Object;
    flags: (0x0001) ACC_PUBLIC
    Code:
      stack=1, locals=1, args_size=1
         0: aload_0
         1: getfield      #155                // Field _18:Ljava/lang/Object;
         4: areturn
      LineNumberTable:
        line 41: 0
      LocalVariableTable:
        Start  Length  Slot  Name   Signature
            0       5     0  this   Lscala/Tuple19;
    Signature: #153                         // ()TT18;

  public T19 _19();
    descriptor: ()Ljava/lang/Object;
    flags: (0x0001) ACC_PUBLIC
    Code:
      stack=1, locals=1, args_size=1
         0: aload_0
         1: getfield      #158                // Field _19:Ljava/lang/Object;
         4: areturn
      LineNumberTable:
        line 41: 0
      LocalVariableTable:
        Start  Length  Slot  Name   Signature
            0       5     0  this   Lscala/Tuple19;
    Signature: #156                         // ()TT19;

  public java.lang.String toString();
    descriptor: ()Ljava/lang/String;
    flags: (0x0001) ACC_PUBLIC
    Code:
      stack=3, locals=1, args_size=1
         0: new           #162                // class java/lang/StringBuilder
         3: dup
         4: ldc           #163                // int 20
         6: invokespecial #166                // Method java/lang/StringBuilder."<init>":(I)V
         9: ldc           #168                // String (
        11: invokevirtual #172                // Method java/lang/StringBuilder.append:(Ljava/lang/String;)Ljava/lang/StringBuilder;
        14: aload_0
        15: invokevirtual #174                // Method _1:()Ljava/lang/Object;
        18: invokevirtual #177                // Method java/lang/StringBuilder.append:(Ljava/lang/Object;)Ljava/lang/StringBuilder;
        21: ldc           #179                // String ,
        23: invokevirtual #172                // Method java/lang/StringBuilder.append:(Ljava/lang/String;)Ljava/lang/StringBuilder;
        26: aload_0
        27: invokevirtual #181                // Method _2:()Ljava/lang/Object;
        30: invokevirtual #177                // Method java/lang/StringBuilder.append:(Ljava/lang/Object;)Ljava/lang/StringBuilder;
        33: ldc           #179                // String ,
        35: invokevirtual #172                // Method java/lang/StringBuilder.append:(Ljava/lang/String;)Ljava/lang/StringBuilder;
        38: aload_0
        39: invokevirtual #183                // Method _3:()Ljava/lang/Object;
        42: invokevirtual #177                // Method java/lang/StringBuilder.append:(Ljava/lang/Object;)Ljava/lang/StringBuilder;
        45: ldc           #179                // String ,
        47: invokevirtual #172                // Method java/lang/StringBuilder.append:(Ljava/lang/String;)Ljava/lang/StringBuilder;
        50: aload_0
        51: invokevirtual #185                // Method _4:()Ljava/lang/Object;
        54: invokevirtual #177                // Method java/lang/StringBuilder.append:(Ljava/lang/Object;)Ljava/lang/StringBuilder;
        57: ldc           #179                // String ,
        59: invokevirtual #172                // Method java/lang/StringBuilder.append:(Ljava/lang/String;)Ljava/lang/StringBuilder;
        62: aload_0
        63: invokevirtual #187                // Method _5:()Ljava/lang/Object;
        66: invokevirtual #177                // Method java/lang/StringBuilder.append:(Ljava/lang/Object;)Ljava/lang/StringBuilder;
        69: ldc           #179                // String ,
        71: invokevirtual #172                // Method java/lang/StringBuilder.append:(Ljava/lang/String;)Ljava/lang/StringBuilder;
        74: aload_0
        75: invokevirtual #189                // Method _6:()Ljava/lang/Object;
        78: invokevirtual #177                // Method java/lang/StringBuilder.append:(Ljava/lang/Object;)Ljava/lang/StringBuilder;
        81: ldc           #179                // String ,
        83: invokevirtual #172                // Method java/lang/StringBuilder.append:(Ljava/lang/String;)Ljava/lang/StringBuilder;
        86: aload_0
        87: invokevirtual #191                // Method _7:()Ljava/lang/Object;
        90: invokevirtual #177                // Method java/lang/StringBuilder.append:(Ljava/lang/Object;)Ljava/lang/StringBuilder;
        93: ldc           #179                // String ,
        95: invokevirtual #172                // Method java/lang/StringBuilder.append:(Ljava/lang/String;)Ljava/lang/StringBuilder;
        98: aload_0
        99: invokevirtual #193                // Method _8:()Ljava/lang/Object;
       102: invokevirtual #177                // Method java/lang/StringBuilder.append:(Ljava/lang/Object;)Ljava/lang/StringBuilder;
       105: ldc           #179                // String ,
       107: invokevirtual #172                // Method java/lang/StringBuilder.append:(Ljava/lang/String;)Ljava/lang/StringBuilder;
       110: aload_0
       111: invokevirtual #195                // Method _9:()Ljava/lang/Object;
       114: invokevirtual #177                // Method java/lang/StringBuilder.append:(Ljava/lang/Object;)Ljava/lang/StringBuilder;
       117: ldc           #179                // String ,
       119: invokevirtual #172                // Method java/lang/StringBuilder.append:(Ljava/lang/String;)Ljava/lang/StringBuilder;
       122: aload_0
       123: invokevirtual #197                // Method _10:()Ljava/lang/Object;
       126: invokevirtual #177                // Method java/lang/StringBuilder.append:(Ljava/lang/Object;)Ljava/lang/StringBuilder;
       129: ldc           #179                // String ,
       131: invokevirtual #172                // Method java/lang/StringBuilder.append:(Ljava/lang/String;)Ljava/lang/StringBuilder;
       134: aload_0
       135: invokevirtual #199                // Method _11:()Ljava/lang/Object;
       138: invokevirtual #177                // Method java/lang/StringBuilder.append:(Ljava/lang/Object;)Ljava/lang/StringBuilder;
       141: ldc           #179                // String ,
       143: invokevirtual #172                // Method java/lang/StringBuilder.append:(Ljava/lang/String;)Ljava/lang/StringBuilder;
       146: aload_0
       147: invokevirtual #201                // Method _12:()Ljava/lang/Object;
       150: invokevirtual #177                // Method java/lang/StringBuilder.append:(Ljava/lang/Object;)Ljava/lang/StringBuilder;
       153: ldc           #179                // String ,
       155: invokevirtual #172                // Method java/lang/StringBuilder.append:(Ljava/lang/String;)Ljava/lang/StringBuilder;
       158: aload_0
       159: invokevirtual #203                // Method _13:()Ljava/lang/Object;
       162: invokevirtual #177                // Method java/lang/StringBuilder.append:(Ljava/lang/Object;)Ljava/lang/StringBuilder;
       165: ldc           #179                // String ,
       167: invokevirtual #172                // Method java/lang/StringBuilder.append:(Ljava/lang/String;)Ljava/lang/StringBuilder;
       170: aload_0
       171: invokevirtual #205                // Method _14:()Ljava/lang/Object;
       174: invokevirtual #177                // Method java/lang/StringBuilder.append:(Ljava/lang/Object;)Ljava/lang/StringBuilder;
       177: ldc           #179                // String ,
       179: invokevirtual #172                // Method java/lang/StringBuilder.append:(Ljava/lang/String;)Ljava/lang/StringBuilder;
       182: aload_0
       183: invokevirtual #207                // Method _15:()Ljava/lang/Object;
       186: invokevirtual #177                // Method java/lang/StringBuilder.append:(Ljava/lang/Object;)Ljava/lang/StringBuilder;
       189: ldc           #179                // String ,
       191: invokevirtual #172                // Method java/lang/StringBuilder.append:(Ljava/lang/String;)Ljava/lang/StringBuilder;
       194: aload_0
       195: invokevirtual #209                // Method _16:()Ljava/lang/Object;
       198: invokevirtual #177                // Method java/lang/StringBuilder.append:(Ljava/lang/Object;)Ljava/lang/StringBuilder;
       201: ldc           #179                // String ,
       203: invokevirtual #172                // Method java/lang/StringBuilder.append:(Ljava/lang/String;)Ljava/lang/StringBuilder;
       206: aload_0
       207: invokevirtual #211                // Method _17:()Ljava/lang/Object;
       210: invokevirtual #177                // Method java/lang/StringBuilder.append:(Ljava/lang/Object;)Ljava/lang/StringBuilder;
       213: ldc           #179                // String ,
       215: invokevirtual #172                // Method java/lang/StringBuilder.append:(Ljava/lang/String;)Ljava/lang/StringBuilder;
       218: aload_0
       219: invokevirtual #213                // Method _18:()Ljava/lang/Object;
       222: invokevirtual #177                // Method java/lang/StringBuilder.append:(Ljava/lang/Object;)Ljava/lang/StringBuilder;
       225: ldc           #179                // String ,
       227: invokevirtual #172                // Method java/lang/StringBuilder.append:(Ljava/lang/String;)Ljava/lang/StringBuilder;
       230: aload_0
       231: invokevirtual #215                // Method _19:()Ljava/lang/Object;
       234: invokevirtual #177                // Method java/lang/StringBuilder.append:(Ljava/lang/Object;)Ljava/lang/StringBuilder;
       237: ldc           #217                // String )
       239: invokevirtual #172                // Method java/lang/StringBuilder.append:(Ljava/lang/String;)Ljava/lang/StringBuilder;
       242: invokevirtual #219                // Method java/lang/StringBuilder.toString:()Ljava/lang/String;
       245: areturn
      LineNumberTable:
        line 45: 0
        line 44: 9
        line 45: 117
      LocalVariableTable:
        Start  Length  Slot  Name   Signature
            0     246     0  this   Lscala/Tuple19;

  public <T1 extends java.lang.Object, T2 extends java.lang.Object, T3 extends java.lang.Object, T4 extends java.lang.Object, T5 extends java.lang.Object, T6 extends java.lang.Object, T7 extends java.lang.Object, T8 extends java.lang.Object, T9 extends java.lang.Object, T10 extends java.lang.Object, T11 extends java.lang.Object, T12 extends java.lang.Object, T13 extends java.lang.Object, T14 extends java.lang.Object, T15 extends java.lang.Object, T16 extends java.lang.Object, T17 extends java.lang.Object, T18 extends java.lang.Object, T19 extends java.lang.Object> scala.Tuple19<T1, T2, T3, T4, T5, T6, T7, T8, T9, T10, T11, T12, T13, T14, T15, T16, T17, T18, T19> copy(T1, T2, T3, T4, T5, T6, T7, T8, T9, T10, T11, T12, T13, T14, T15, T16, T17, T18, T19);
    descriptor: (Ljava/lang/Object;Ljava/lang/Object;Ljava/lang/Object;Ljava/lang/Object;Ljava/lang/Object;Ljava/lang/Object;Ljava/lang/Object;Ljava/lang/Object;Ljava/lang/Object;Ljava/lang/Object;Ljava/lang/Object;Ljava/lang/Object;Ljava/lang/Object;Ljava/lang/Object;Ljava/lang/Object;Ljava/lang/Object;Ljava/lang/Object;Ljava/lang/Object;Ljava/lang/Object;)Lscala/Tuple19;
    flags: (0x0001) ACC_PUBLIC
    Code:
      stack=21, locals=20, args_size=20
         0: new           #2                  // class scala/Tuple19
         3: dup
         4: aload_1
         5: aload_2
         6: aload_3
         7: aload         4
         9: aload         5
        11: aload         6
        13: aload         7
        15: aload         8
        17: aload         9
        19: aload         10
        21: aload         11
        23: aload         12
        25: aload         13
        27: aload         14
        29: aload         15
        31: aload         16
        33: aload         17
        35: aload         18
        37: aload         19
        39: invokespecial #74                 // Method "<init>":(Ljava/lang/Object;Ljava/lang/Object;Ljava/lang/Object;Ljava/lang/Object;Ljava/lang/Object;Ljava/lang/Object;Ljava/lang/Object;Ljava/lang/Object;Ljava/lang/Object;Ljava/lang/Object;Ljava/lang/Object;Ljava/lang/Object;Ljava/lang/Object;Ljava/lang/Object;Ljava/lang/Object;Ljava/lang/Object;Ljava/lang/Object;Ljava/lang/Object;Ljava/lang/Object;)V
        42: areturn
      LineNumberTable:
        line 41: 0
      LocalVariableTable:
        Start  Length  Slot  Name   Signature
            0      43     0  this   Lscala/Tuple19;
            0      43     1    _1   Ljava/lang/Object;
            0      43     2    _2   Ljava/lang/Object;
            0      43     3    _3   Ljava/lang/Object;
            0      43     4    _4   Ljava/lang/Object;
            0      43     5    _5   Ljava/lang/Object;
            0      43     6    _6   Ljava/lang/Object;
            0      43     7    _7   Ljava/lang/Object;
            0      43     8    _8   Ljava/lang/Object;
            0      43     9    _9   Ljava/lang/Object;
            0      43    10   _10   Ljava/lang/Object;
            0      43    11   _11   Ljava/lang/Object;
            0      43    12   _12   Ljava/lang/Object;
            0      43    13   _13   Ljava/lang/Object;
            0      43    14   _14   Ljava/lang/Object;
            0      43    15   _15   Ljava/lang/Object;
            0      43    16   _16   Ljava/lang/Object;
            0      43    17   _17   Ljava/lang/Object;
            0      43    18   _18   Ljava/lang/Object;
            0      43    19   _19   Ljava/lang/Object;
    Signature: #70                          // <T1:Ljava/lang/Object;T2:Ljava/lang/Object;T3:Ljava/lang/Object;T4:Ljava/lang/Object;T5:Ljava/lang/Object;T6:Ljava/lang/Object;T7:Ljava/lang/Object;T8:Ljava/lang/Object;T9:Ljava/lang/Object;T10:Ljava/lang/Object;T11:Ljava/lang/Object;T12:Ljava/lang/Object;T13:Ljava/lang/Object;T14:Ljava/lang/Object;T15:Ljava/lang/Object;T16:Ljava/lang/Object;T17:Ljava/lang/Object;T18:Ljava/lang/Object;T19:Ljava/lang/Object;>(TT1;TT2;TT3;TT4;TT5;TT6;TT7;TT8;TT9;TT10;TT11;TT12;TT13;TT14;TT15;TT16;TT17;TT18;TT19;)Lscala/Tuple19<TT1;TT2;TT3;TT4;TT5;TT6;TT7;TT8;TT9;TT10;TT11;TT12;TT13;TT14;TT15;TT16;TT17;TT18;TT19;>;
    MethodParameters:
      Name                           Flags
      _1                             final
      _2                             final
      _3                             final
      _4                             final
      _5                             final
      _6                             final
      _7                             final
      _8                             final
      _9                             final
      _10                            final
      _11                            final
      _12                            final
      _13                            final
      _14                            final
      _15                            final
      _16                            final
      _17                            final
      _18                            final
      _19                            final

  public <T1 extends java.lang.Object, T2 extends java.lang.Object, T3 extends java.lang.Object, T4 extends java.lang.Object, T5 extends java.lang.Object, T6 extends java.lang.Object, T7 extends java.lang.Object, T8 extends java.lang.Object, T9 extends java.lang.Object, T10 extends java.lang.Object, T11 extends java.lang.Object, T12 extends java.lang.Object, T13 extends java.lang.Object, T14 extends java.lang.Object, T15 extends java.lang.Object, T16 extends java.lang.Object, T17 extends java.lang.Object, T18 extends java.lang.Object, T19 extends java.lang.Object> T1 copy$default$1();
    descriptor: ()Ljava/lang/Object;
    flags: (0x0001) ACC_PUBLIC
    Code:
      stack=1, locals=1, args_size=1
         0: aload_0
         1: invokevirtual #174                // Method _1:()Ljava/lang/Object;
         4: areturn
      LineNumberTable:
        line 41: 0
      LocalVariableTable:
        Start  Length  Slot  Name   Signature
            0       5     0  this   Lscala/Tuple19;
    Signature: #222                         // <T1:Ljava/lang/Object;T2:Ljava/lang/Object;T3:Ljava/lang/Object;T4:Ljava/lang/Object;T5:Ljava/lang/Object;T6:Ljava/lang/Object;T7:Ljava/lang/Object;T8:Ljava/lang/Object;T9:Ljava/lang/Object;T10:Ljava/lang/Object;T11:Ljava/lang/Object;T12:Ljava/lang/Object;T13:Ljava/lang/Object;T14:Ljava/lang/Object;T15:Ljava/lang/Object;T16:Ljava/lang/Object;T17:Ljava/lang/Object;T18:Ljava/lang/Object;T19:Ljava/lang/Object;>()TT1;

  public <T1 extends java.lang.Object, T2 extends java.lang.Object, T3 extends java.lang.Object, T4 extends java.lang.Object, T5 extends java.lang.Object, T6 extends java.lang.Object, T7 extends java.lang.Object, T8 extends java.lang.Object, T9 extends java.lang.Object, T10 extends java.lang.Object, T11 extends java.lang.Object, T12 extends java.lang.Object, T13 extends java.lang.Object, T14 extends java.lang.Object, T15 extends java.lang.Object, T16 extends java.lang.Object, T17 extends java.lang.Object, T18 extends java.lang.Object, T19 extends java.lang.Object> T10 copy$default$10();
    descriptor: ()Ljava/lang/Object;
    flags: (0x0001) ACC_PUBLIC
    Code:
      stack=1, locals=1, args_size=1
         0: aload_0
         1: invokevirtual #197                // Method _10:()Ljava/lang/Object;
         4: areturn
      LineNumberTable:
        line 41: 0
      LocalVariableTable:
        Start  Length  Slot  Name   Signature
            0       5     0  this   Lscala/Tuple19;
    Signature: #224                         // <T1:Ljava/lang/Object;T2:Ljava/lang/Object;T3:Ljava/lang/Object;T4:Ljava/lang/Object;T5:Ljava/lang/Object;T6:Ljava/lang/Object;T7:Ljava/lang/Object;T8:Ljava/lang/Object;T9:Ljava/lang/Object;T10:Ljava/lang/Object;T11:Ljava/lang/Object;T12:Ljava/lang/Object;T13:Ljava/lang/Object;T14:Ljava/lang/Object;T15:Ljava/lang/Object;T16:Ljava/lang/Object;T17:Ljava/lang/Object;T18:Ljava/lang/Object;T19:Ljava/lang/Object;>()TT10;

  public <T1 extends java.lang.Object, T2 extends java.lang.Object, T3 extends java.lang.Object, T4 extends java.lang.Object, T5 extends java.lang.Object, T6 extends java.lang.Object, T7 extends java.lang.Object, T8 extends java.lang.Object, T9 extends java.lang.Object, T10 extends java.lang.Object, T11 extends java.lang.Object, T12 extends java.lang.Object, T13 extends java.lang.Object, T14 extends java.lang.Object, T15 extends java.lang.Object, T16 extends java.lang.Object, T17 extends java.lang.Object, T18 extends java.lang.Object, T19 extends java.lang.Object> T11 copy$default$11();
    descriptor: ()Ljava/lang/Object;
    flags: (0x0001) ACC_PUBLIC
    Code:
      stack=1, locals=1, args_size=1
         0: aload_0
         1: invokevirtual #199                // Method _11:()Ljava/lang/Object;
         4: areturn
      LineNumberTable:
        line 41: 0
      LocalVariableTable:
        Start  Length  Slot  Name   Signature
            0       5     0  this   Lscala/Tuple19;
    Signature: #226                         // <T1:Ljava/lang/Object;T2:Ljava/lang/Object;T3:Ljava/lang/Object;T4:Ljava/lang/Object;T5:Ljava/lang/Object;T6:Ljava/lang/Object;T7:Ljava/lang/Object;T8:Ljava/lang/Object;T9:Ljava/lang/Object;T10:Ljava/lang/Object;T11:Ljava/lang/Object;T12:Ljava/lang/Object;T13:Ljava/lang/Object;T14:Ljava/lang/Object;T15:Ljava/lang/Object;T16:Ljava/lang/Object;T17:Ljava/lang/Object;T18:Ljava/lang/Object;T19:Ljava/lang/Object;>()TT11;

  public <T1 extends java.lang.Object, T2 extends java.lang.Object, T3 extends java.lang.Object, T4 extends java.lang.Object, T5 extends java.lang.Object, T6 extends java.lang.Object, T7 extends java.lang.Object, T8 extends java.lang.Object, T9 extends java.lang.Object, T10 extends java.lang.Object, T11 extends java.lang.Object, T12 extends java.lang.Object, T13 extends java.lang.Object, T14 extends java.lang.Object, T15 extends java.lang.Object, T16 extends java.lang.Object, T17 extends java.lang.Object, T18 extends java.lang.Object, T19 extends java.lang.Object> T12 copy$default$12();
    descriptor: ()Ljava/lang/Object;
    flags: (0x0001) ACC_PUBLIC
    Code:
      stack=1, locals=1, args_size=1
         0: aload_0
         1: invokevirtual #201                // Method _12:()Ljava/lang/Object;
         4: areturn
      LineNumberTable:
        line 41: 0
      LocalVariableTable:
        Start  Length  Slot  Name   Signature
            0       5     0  this   Lscala/Tuple19;
    Signature: #228                         // <T1:Ljava/lang/Object;T2:Ljava/lang/Object;T3:Ljava/lang/Object;T4:Ljava/lang/Object;T5:Ljava/lang/Object;T6:Ljava/lang/Object;T7:Ljava/lang/Object;T8:Ljava/lang/Object;T9:Ljava/lang/Object;T10:Ljava/lang/Object;T11:Ljava/lang/Object;T12:Ljava/lang/Object;T13:Ljava/lang/Object;T14:Ljava/lang/Object;T15:Ljava/lang/Object;T16:Ljava/lang/Object;T17:Ljava/lang/Object;T18:Ljava/lang/Object;T19:Ljava/lang/Object;>()TT12;

  public <T1 extends java.lang.Object, T2 extends java.lang.Object, T3 extends java.lang.Object, T4 extends java.lang.Object, T5 extends java.lang.Object, T6 extends java.lang.Object, T7 extends java.lang.Object, T8 extends java.lang.Object, T9 extends java.lang.Object, T10 extends java.lang.Object, T11 extends java.lang.Object, T12 extends java.lang.Object, T13 extends java.lang.Object, T14 extends java.lang.Object, T15 extends java.lang.Object, T16 extends java.lang.Object, T17 extends java.lang.Object, T18 extends java.lang.Object, T19 extends java.lang.Object> T13 copy$default$13();
    descriptor: ()Ljava/lang/Object;
    flags: (0x0001) ACC_PUBLIC
    Code:
      stack=1, locals=1, args_size=1
         0: aload_0
         1: invokevirtual #203                // Method _13:()Ljava/lang/Object;
         4: areturn
      LineNumberTable:
        line 41: 0
      LocalVariableTable:
        Start  Length  Slot  Name   Signature
            0       5     0  this   Lscala/Tuple19;
    Signature: #230                         // <T1:Ljava/lang/Object;T2:Ljava/lang/Object;T3:Ljava/lang/Object;T4:Ljava/lang/Object;T5:Ljava/lang/Object;T6:Ljava/lang/Object;T7:Ljava/lang/Object;T8:Ljava/lang/Object;T9:Ljava/lang/Object;T10:Ljava/lang/Object;T11:Ljava/lang/Object;T12:Ljava/lang/Object;T13:Ljava/lang/Object;T14:Ljava/lang/Object;T15:Ljava/lang/Object;T16:Ljava/lang/Object;T17:Ljava/lang/Object;T18:Ljava/lang/Object;T19:Ljava/lang/Object;>()TT13;

  public <T1 extends java.lang.Object, T2 extends java.lang.Object, T3 extends java.lang.Object, T4 extends java.lang.Object, T5 extends java.lang.Object, T6 extends java.lang.Object, T7 extends java.lang.Object, T8 extends java.lang.Object, T9 extends java.lang.Object, T10 extends java.lang.Object, T11 extends java.lang.Object, T12 extends java.lang.Object, T13 extends java.lang.Object, T14 extends java.lang.Object, T15 extends java.lang.Object, T16 extends java.lang.Object, T17 extends java.lang.Object, T18 extends java.lang.Object, T19 extends java.lang.Object> T14 copy$default$14();
    descriptor: ()Ljava/lang/Object;
    flags: (0x0001) ACC_PUBLIC
    Code:
      stack=1, locals=1, args_size=1
         0: aload_0
         1: invokevirtual #205                // Method _14:()Ljava/lang/Object;
         4: areturn
      LineNumberTable:
        line 41: 0
      LocalVariableTable:
        Start  Length  Slot  Name   Signature
            0       5     0  this   Lscala/Tuple19;
    Signature: #232                         // <T1:Ljava/lang/Object;T2:Ljava/lang/Object;T3:Ljava/lang/Object;T4:Ljava/lang/Object;T5:Ljava/lang/Object;T6:Ljava/lang/Object;T7:Ljava/lang/Object;T8:Ljava/lang/Object;T9:Ljava/lang/Object;T10:Ljava/lang/Object;T11:Ljava/lang/Object;T12:Ljava/lang/Object;T13:Ljava/lang/Object;T14:Ljava/lang/Object;T15:Ljava/lang/Object;T16:Ljava/lang/Object;T17:Ljava/lang/Object;T18:Ljava/lang/Object;T19:Ljava/lang/Object;>()TT14;

  public <T1 extends java.lang.Object, T2 extends java.lang.Object, T3 extends java.lang.Object, T4 extends java.lang.Object, T5 extends java.lang.Object, T6 extends java.lang.Object, T7 extends java.lang.Object, T8 extends java.lang.Object, T9 extends java.lang.Object, T10 extends java.lang.Object, T11 extends java.lang.Object, T12 extends java.lang.Object, T13 extends java.lang.Object, T14 extends java.lang.Object, T15 extends java.lang.Object, T16 extends java.lang.Object, T17 extends java.lang.Object, T18 extends java.lang.Object, T19 extends java.lang.Object> T15 copy$default$15();
    descriptor: ()Ljava/lang/Object;
    flags: (0x0001) ACC_PUBLIC
    Code:
      stack=1, locals=1, args_size=1
         0: aload_0
         1: invokevirtual #207                // Method _15:()Ljava/lang/Object;
         4: areturn
      LineNumberTable:
        line 41: 0
      LocalVariableTable:
        Start  Length  Slot  Name   Signature
            0       5     0  this   Lscala/Tuple19;
    Signature: #234                         // <T1:Ljava/lang/Object;T2:Ljava/lang/Object;T3:Ljava/lang/Object;T4:Ljava/lang/Object;T5:Ljava/lang/Object;T6:Ljava/lang/Object;T7:Ljava/lang/Object;T8:Ljava/lang/Object;T9:Ljava/lang/Object;T10:Ljava/lang/Object;T11:Ljava/lang/Object;T12:Ljava/lang/Object;T13:Ljava/lang/Object;T14:Ljava/lang/Object;T15:Ljava/lang/Object;T16:Ljava/lang/Object;T17:Ljava/lang/Object;T18:Ljava/lang/Object;T19:Ljava/lang/Object;>()TT15;

  public <T1 extends java.lang.Object, T2 extends java.lang.Object, T3 extends java.lang.Object, T4 extends java.lang.Object, T5 extends java.lang.Object, T6 extends java.lang.Object, T7 extends java.lang.Object, T8 extends java.lang.Object, T9 extends java.lang.Object, T10 extends java.lang.Object, T11 extends java.lang.Object, T12 extends java.lang.Object, T13 extends java.lang.Object, T14 extends java.lang.Object, T15 extends java.lang.Object, T16 extends java.lang.Object, T17 extends java.lang.Object, T18 extends java.lang.Object, T19 extends java.lang.Object> T16 copy$default$16();
    descriptor: ()Ljava/lang/Object;
    flags: (0x0001) ACC_PUBLIC
    Code:
      stack=1, locals=1, args_size=1
         0: aload_0
         1: invokevirtual #209                // Method _16:()Ljava/lang/Object;
         4: areturn
      LineNumberTable:
        line 41: 0
      LocalVariableTable:
        Start  Length  Slot  Name   Signature
            0       5     0  this   Lscala/Tuple19;
    Signature: #236                         // <T1:Ljava/lang/Object;T2:Ljava/lang/Object;T3:Ljava/lang/Object;T4:Ljava/lang/Object;T5:Ljava/lang/Object;T6:Ljava/lang/Object;T7:Ljava/lang/Object;T8:Ljava/lang/Object;T9:Ljava/lang/Object;T10:Ljava/lang/Object;T11:Ljava/lang/Object;T12:Ljava/lang/Object;T13:Ljava/lang/Object;T14:Ljava/lang/Object;T15:Ljava/lang/Object;T16:Ljava/lang/Object;T17:Ljava/lang/Object;T18:Ljava/lang/Object;T19:Ljava/lang/Object;>()TT16;

  public <T1 extends java.lang.Object, T2 extends java.lang.Object, T3 extends java.lang.Object, T4 extends java.lang.Object, T5 extends java.lang.Object, T6 extends java.lang.Object, T7 extends java.lang.Object, T8 extends java.lang.Object, T9 extends java.lang.Object, T10 extends java.lang.Object, T11 extends java.lang.Object, T12 extends java.lang.Object, T13 extends java.lang.Object, T14 extends java.lang.Object, T15 extends java.lang.Object, T16 extends java.lang.Object, T17 extends java.lang.Object, T18 extends java.lang.Object, T19 extends java.lang.Object> T17 copy$default$17();
    descriptor: ()Ljava/lang/Object;
    flags: (0x0001) ACC_PUBLIC
    Code:
      stack=1, locals=1, args_size=1
         0: aload_0
         1: invokevirtual #211                // Method _17:()Ljava/lang/Object;
         4: areturn
      LineNumberTable:
        line 41: 0
      LocalVariableTable:
        Start  Length  Slot  Name   Signature
            0       5     0  this   Lscala/Tuple19;
    Signature: #238                         // <T1:Ljava/lang/Object;T2:Ljava/lang/Object;T3:Ljava/lang/Object;T4:Ljava/lang/Object;T5:Ljava/lang/Object;T6:Ljava/lang/Object;T7:Ljava/lang/Object;T8:Ljava/lang/Object;T9:Ljava/lang/Object;T10:Ljava/lang/Object;T11:Ljava/lang/Object;T12:Ljava/lang/Object;T13:Ljava/lang/Object;T14:Ljava/lang/Object;T15:Ljava/lang/Object;T16:Ljava/lang/Object;T17:Ljava/lang/Object;T18:Ljava/lang/Object;T19:Ljava/lang/Object;>()TT17;

  public <T1 extends java.lang.Object, T2 extends java.lang.Object, T3 extends java.lang.Object, T4 extends java.lang.Object, T5 extends java.lang.Object, T6 extends java.lang.Object, T7 extends java.lang.Object, T8 extends java.lang.Object, T9 extends java.lang.Object, T10 extends java.lang.Object, T11 extends java.lang.Object, T12 extends java.lang.Object, T13 extends java.lang.Object, T14 extends java.lang.Object, T15 extends java.lang.Object, T16 extends java.lang.Object, T17 extends java.lang.Object, T18 extends java.lang.Object, T19 extends java.lang.Object> T18 copy$default$18();
    descriptor: ()Ljava/lang/Object;
    flags: (0x0001) ACC_PUBLIC
    Code:
      stack=1, locals=1, args_size=1
         0: aload_0
         1: invokevirtual #213                // Method _18:()Ljava/lang/Object;
         4: areturn
      LineNumberTable:
        line 41: 0
      LocalVariableTable:
        Start  Length  Slot  Name   Signature
            0       5     0  this   Lscala/Tuple19;
    Signature: #240                         // <T1:Ljava/lang/Object;T2:Ljava/lang/Object;T3:Ljava/lang/Object;T4:Ljava/lang/Object;T5:Ljava/lang/Object;T6:Ljava/lang/Object;T7:Ljava/lang/Object;T8:Ljava/lang/Object;T9:Ljava/lang/Object;T10:Ljava/lang/Object;T11:Ljava/lang/Object;T12:Ljava/lang/Object;T13:Ljava/lang/Object;T14:Ljava/lang/Object;T15:Ljava/lang/Object;T16:Ljava/lang/Object;T17:Ljava/lang/Object;T18:Ljava/lang/Object;T19:Ljava/lang/Object;>()TT18;

  public <T1 extends java.lang.Object, T2 extends java.lang.Object, T3 extends java.lang.Object, T4 extends java.lang.Object, T5 extends java.lang.Object, T6 extends java.lang.Object, T7 extends java.lang.Object, T8 extends java.lang.Object, T9 extends java.lang.Object, T10 extends java.lang.Object, T11 extends java.lang.Object, T12 extends java.lang.Object, T13 extends java.lang.Object, T14 extends java.lang.Object, T15 extends java.lang.Object, T16 extends java.lang.Object, T17 extends java.lang.Object, T18 extends java.lang.Object, T19 extends java.lang.Object> T19 copy$default$19();
    descriptor: ()Ljava/lang/Object;
    flags: (0x0001) ACC_PUBLIC
    Code:
      stack=1, locals=1, args_size=1
         0: aload_0
         1: invokevirtual #215                // Method _19:()Ljava/lang/Object;
         4: areturn
      LineNumberTable:
        line 41: 0
      LocalVariableTable:
        Start  Length  Slot  Name   Signature
            0       5     0  this   Lscala/Tuple19;
    Signature: #242                         // <T1:Ljava/lang/Object;T2:Ljava/lang/Object;T3:Ljava/lang/Object;T4:Ljava/lang/Object;T5:Ljava/lang/Object;T6:Ljava/lang/Object;T7:Ljava/lang/Object;T8:Ljava/lang/Object;T9:Ljava/lang/Object;T10:Ljava/lang/Object;T11:Ljava/lang/Object;T12:Ljava/lang/Object;T13:Ljava/lang/Object;T14:Ljava/lang/Object;T15:Ljava/lang/Object;T16:Ljava/lang/Object;T17:Ljava/lang/Object;T18:Ljava/lang/Object;T19:Ljava/lang/Object;>()TT19;

  public <T1 extends java.lang.Object, T2 extends java.lang.Object, T3 extends java.lang.Object, T4 extends java.lang.Object, T5 extends java.lang.Object, T6 extends java.lang.Object, T7 extends java.lang.Object, T8 extends java.lang.Object, T9 extends java.lang.Object, T10 extends java.lang.Object, T11 extends java.lang.Object, T12 extends java.lang.Object, T13 extends java.lang.Object, T14 extends java.lang.Object, T15 extends java.lang.Object, T16 extends java.lang.Object, T17 extends java.lang.Object, T18 extends java.lang.Object, T19 extends java.lang.Object> T2 copy$default$2();
    descriptor: ()Ljava/lang/Object;
    flags: (0x0001) ACC_PUBLIC
    Code:
      stack=1, locals=1, args_size=1
         0: aload_0
         1: invokevirtual #181                // Method _2:()Ljava/lang/Object;
         4: areturn
      LineNumberTable:
        line 41: 0
      LocalVariableTable:
        Start  Length  Slot  Name   Signature
            0       5     0  this   Lscala/Tuple19;
    Signature: #244                         // <T1:Ljava/lang/Object;T2:Ljava/lang/Object;T3:Ljava/lang/Object;T4:Ljava/lang/Object;T5:Ljava/lang/Object;T6:Ljava/lang/Object;T7:Ljava/lang/Object;T8:Ljava/lang/Object;T9:Ljava/lang/Object;T10:Ljava/lang/Object;T11:Ljava/lang/Object;T12:Ljava/lang/Object;T13:Ljava/lang/Object;T14:Ljava/lang/Object;T15:Ljava/lang/Object;T16:Ljava/lang/Object;T17:Ljava/lang/Object;T18:Ljava/lang/Object;T19:Ljava/lang/Object;>()TT2;

  public <T1 extends java.lang.Object, T2 extends java.lang.Object, T3 extends java.lang.Object, T4 extends java.lang.Object, T5 extends java.lang.Object, T6 extends java.lang.Object, T7 extends java.lang.Object, T8 extends java.lang.Object, T9 extends java.lang.Object, T10 extends java.lang.Object, T11 extends java.lang.Object, T12 extends java.lang.Object, T13 extends java.lang.Object, T14 extends java.lang.Object, T15 extends java.lang.Object, T16 extends java.lang.Object, T17 extends java.lang.Object, T18 extends java.lang.Object, T19 extends java.lang.Object> T3 copy$default$3();
    descriptor: ()Ljava/lang/Object;
    flags: (0x0001) ACC_PUBLIC
    Code:
      stack=1, locals=1, args_size=1
         0: aload_0
         1: invokevirtual #183                // Method _3:()Ljava/lang/Object;
         4: areturn
      LineNumberTable:
        line 41: 0
      LocalVariableTable:
        Start  Length  Slot  Name   Signature
            0       5     0  this   Lscala/Tuple19;
    Signature: #246                         // <T1:Ljava/lang/Object;T2:Ljava/lang/Object;T3:Ljava/lang/Object;T4:Ljava/lang/Object;T5:Ljava/lang/Object;T6:Ljava/lang/Object;T7:Ljava/lang/Object;T8:Ljava/lang/Object;T9:Ljava/lang/Object;T10:Ljava/lang/Object;T11:Ljava/lang/Object;T12:Ljava/lang/Object;T13:Ljava/lang/Object;T14:Ljava/lang/Object;T15:Ljava/lang/Object;T16:Ljava/lang/Object;T17:Ljava/lang/Object;T18:Ljava/lang/Object;T19:Ljava/lang/Object;>()TT3;

  public <T1 extends java.lang.Object, T2 extends java.lang.Object, T3 extends java.lang.Object, T4 extends java.lang.Object, T5 extends java.lang.Object, T6 extends java.lang.Object, T7 extends java.lang.Object, T8 extends java.lang.Object, T9 extends java.lang.Object, T10 extends java.lang.Object, T11 extends java.lang.Object, T12 extends java.lang.Object, T13 extends java.lang.Object, T14 extends java.lang.Object, T15 extends java.lang.Object, T16 extends java.lang.Object, T17 extends java.lang.Object, T18 extends java.lang.Object, T19 extends java.lang.Object> T4 copy$default$4();
    descriptor: ()Ljava/lang/Object;
    flags: (0x0001) ACC_PUBLIC
    Code:
      stack=1, locals=1, args_size=1
         0: aload_0
         1: invokevirtual #185                // Method _4:()Ljava/lang/Object;
         4: areturn
      LineNumberTable:
        line 41: 0
      LocalVariableTable:
        Start  Length  Slot  Name   Signature
            0       5     0  this   Lscala/Tuple19;
    Signature: #248                         // <T1:Ljava/lang/Object;T2:Ljava/lang/Object;T3:Ljava/lang/Object;T4:Ljava/lang/Object;T5:Ljava/lang/Object;T6:Ljava/lang/Object;T7:Ljava/lang/Object;T8:Ljava/lang/Object;T9:Ljava/lang/Object;T10:Ljava/lang/Object;T11:Ljava/lang/Object;T12:Ljava/lang/Object;T13:Ljava/lang/Object;T14:Ljava/lang/Object;T15:Ljava/lang/Object;T16:Ljava/lang/Object;T17:Ljava/lang/Object;T18:Ljava/lang/Object;T19:Ljava/lang/Object;>()TT4;

  public <T1 extends java.lang.Object, T2 extends java.lang.Object, T3 extends java.lang.Object, T4 extends java.lang.Object, T5 extends java.lang.Object, T6 extends java.lang.Object, T7 extends java.lang.Object, T8 extends java.lang.Object, T9 extends java.lang.Object, T10 extends java.lang.Object, T11 extends java.lang.Object, T12 extends java.lang.Object, T13 extends java.lang.Object, T14 extends java.lang.Object, T15 extends java.lang.Object, T16 extends java.lang.Object, T17 extends java.lang.Object, T18 extends java.lang.Object, T19 extends java.lang.Object> T5 copy$default$5();
    descriptor: ()Ljava/lang/Object;
    flags: (0x0001) ACC_PUBLIC
    Code:
      stack=1, locals=1, args_size=1
         0: aload_0
         1: invokevirtual #187                // Method _5:()Ljava/lang/Object;
         4: areturn
      LineNumberTable:
        line 41: 0
      LocalVariableTable:
        Start  Length  Slot  Name   Signature
            0       5     0  this   Lscala/Tuple19;
    Signature: #250                         // <T1:Ljava/lang/Object;T2:Ljava/lang/Object;T3:Ljava/lang/Object;T4:Ljava/lang/Object;T5:Ljava/lang/Object;T6:Ljava/lang/Object;T7:Ljava/lang/Object;T8:Ljava/lang/Object;T9:Ljava/lang/Object;T10:Ljava/lang/Object;T11:Ljava/lang/Object;T12:Ljava/lang/Object;T13:Ljava/lang/Object;T14:Ljava/lang/Object;T15:Ljava/lang/Object;T16:Ljava/lang/Object;T17:Ljava/lang/Object;T18:Ljava/lang/Object;T19:Ljava/lang/Object;>()TT5;

  public <T1 extends java.lang.Object, T2 extends java.lang.Object, T3 extends java.lang.Object, T4 extends java.lang.Object, T5 extends java.lang.Object, T6 extends java.lang.Object, T7 extends java.lang.Object, T8 extends java.lang.Object, T9 extends java.lang.Object, T10 extends java.lang.Object, T11 extends java.lang.Object, T12 extends java.lang.Object, T13 extends java.lang.Object, T14 extends java.lang.Object, T15 extends java.lang.Object, T16 extends java.lang.Object, T17 extends java.lang.Object, T18 extends java.lang.Object, T19 extends java.lang.Object> T6 copy$default$6();
    descriptor: ()Ljava/lang/Object;
    flags: (0x0001) ACC_PUBLIC
    Code:
      stack=1, locals=1, args_size=1
         0: aload_0
         1: invokevirtual #189                // Method _6:()Ljava/lang/Object;
         4: areturn
      LineNumberTable:
        line 41: 0
      LocalVariableTable:
        Start  Length  Slot  Name   Signature
            0       5     0  this   Lscala/Tuple19;
    Signature: #252                         // <T1:Ljava/lang/Object;T2:Ljava/lang/Object;T3:Ljava/lang/Object;T4:Ljava/lang/Object;T5:Ljava/lang/Object;T6:Ljava/lang/Object;T7:Ljava/lang/Object;T8:Ljava/lang/Object;T9:Ljava/lang/Object;T10:Ljava/lang/Object;T11:Ljava/lang/Object;T12:Ljava/lang/Object;T13:Ljava/lang/Object;T14:Ljava/lang/Object;T15:Ljava/lang/Object;T16:Ljava/lang/Object;T17:Ljava/lang/Object;T18:Ljava/lang/Object;T19:Ljava/lang/Object;>()TT6;

  public <T1 extends java.lang.Object, T2 extends java.lang.Object, T3 extends java.lang.Object, T4 extends java.lang.Object, T5 extends java.lang.Object, T6 extends java.lang.Object, T7 extends java.lang.Object, T8 extends java.lang.Object, T9 extends java.lang.Object, T10 extends java.lang.Object, T11 extends java.lang.Object, T12 extends java.lang.Object, T13 extends java.lang.Object, T14 extends java.lang.Object, T15 extends java.lang.Object, T16 extends java.lang.Object, T17 extends java.lang.Object, T18 extends java.lang.Object, T19 extends java.lang.Object> T7 copy$default$7();
    descriptor: ()Ljava/lang/Object;
    flags: (0x0001) ACC_PUBLIC
    Code:
      stack=1, locals=1, args_size=1
         0: aload_0
         1: invokevirtual #191                // Method _7:()Ljava/lang/Object;
         4: areturn
      LineNumberTable:
        line 41: 0
      LocalVariableTable:
        Start  Length  Slot  Name   Signature
            0       5     0  this   Lscala/Tuple19;
    Signature: #254                         // <T1:Ljava/lang/Object;T2:Ljava/lang/Object;T3:Ljava/lang/Object;T4:Ljava/lang/Object;T5:Ljava/lang/Object;T6:Ljava/lang/Object;T7:Ljava/lang/Object;T8:Ljava/lang/Object;T9:Ljava/lang/Object;T10:Ljava/lang/Object;T11:Ljava/lang/Object;T12:Ljava/lang/Object;T13:Ljava/lang/Object;T14:Ljava/lang/Object;T15:Ljava/lang/Object;T16:Ljava/lang/Object;T17:Ljava/lang/Object;T18:Ljava/lang/Object;T19:Ljava/lang/Object;>()TT7;

  public <T1 extends java.lang.Object, T2 extends java.lang.Object, T3 extends java.lang.Object, T4 extends java.lang.Object, T5 extends java.lang.Object, T6 extends java.lang.Object, T7 extends java.lang.Object, T8 extends java.lang.Object, T9 extends java.lang.Object, T10 extends java.lang.Object, T11 extends java.lang.Object, T12 extends java.lang.Object, T13 extends java.lang.Object, T14 extends java.lang.Object, T15 extends java.lang.Object, T16 extends java.lang.Object, T17 extends java.lang.Object, T18 extends java.lang.Object, T19 extends java.lang.Object> T8 copy$default$8();
    descriptor: ()Ljava/lang/Object;
    flags: (0x0001) ACC_PUBLIC
    Code:
      stack=1, locals=1, args_size=1
         0: aload_0
         1: invokevirtual #193                // Method _8:()Ljava/lang/Object;
         4: areturn
      LineNumberTable:
        line 41: 0
      LocalVariableTable:
        Start  Length  Slot  Name   Signature
            0       5     0  this   Lscala/Tuple19;
    Signature: #256                         // <T1:Ljava/lang/Object;T2:Ljava/lang/Object;T3:Ljava/lang/Object;T4:Ljava/lang/Object;T5:Ljava/lang/Object;T6:Ljava/lang/Object;T7:Ljava/lang/Object;T8:Ljava/lang/Object;T9:Ljava/lang/Object;T10:Ljava/lang/Object;T11:Ljava/lang/Object;T12:Ljava/lang/Object;T13:Ljava/lang/Object;T14:Ljava/lang/Object;T15:Ljava/lang/Object;T16:Ljava/lang/Object;T17:Ljava/lang/Object;T18:Ljava/lang/Object;T19:Ljava/lang/Object;>()TT8;

  public <T1 extends java.lang.Object, T2 extends java.lang.Object, T3 extends java.lang.Object, T4 extends java.lang.Object, T5 extends java.lang.Object, T6 extends java.lang.Object, T7 extends java.lang.Object, T8 extends java.lang.Object, T9 extends java.lang.Object, T10 extends java.lang.Object, T11 extends java.lang.Object, T12 extends java.lang.Object, T13 extends java.lang.Object, T14 extends java.lang.Object, T15 extends java.lang.Object, T16 extends java.lang.Object, T17 extends java.lang.Object, T18 extends java.lang.Object, T19 extends java.lang.Object> T9 copy$default$9();
    descriptor: ()Ljava/lang/Object;
    flags: (0x0001) ACC_PUBLIC
    Code:
      stack=1, locals=1, args_size=1
         0: aload_0
         1: invokevirtual #195                // Method _9:()Ljava/lang/Object;
         4: areturn
      LineNumberTable:
        line 41: 0
      LocalVariableTable:
        Start  Length  Slot  Name   Signature
            0       5     0  this   Lscala/Tuple19;
    Signature: #258                         // <T1:Ljava/lang/Object;T2:Ljava/lang/Object;T3:Ljava/lang/Object;T4:Ljava/lang/Object;T5:Ljava/lang/Object;T6:Ljava/lang/Object;T7:Ljava/lang/Object;T8:Ljava/lang/Object;T9:Ljava/lang/Object;T10:Ljava/lang/Object;T11:Ljava/lang/Object;T12:Ljava/lang/Object;T13:Ljava/lang/Object;T14:Ljava/lang/Object;T15:Ljava/lang/Object;T16:Ljava/lang/Object;T17:Ljava/lang/Object;T18:Ljava/lang/Object;T19:Ljava/lang/Object;>()TT9;

  public java.lang.String productPrefix();
    descriptor: ()Ljava/lang/String;
    flags: (0x0001) ACC_PUBLIC
    Code:
      stack=1, locals=1, args_size=1
         0: ldc_w         #261                // String Tuple19
         3: areturn
      LineNumberTable:
        line 41: 0
      LocalVariableTable:
        Start  Length  Slot  Name   Signature
            0       4     0  this   Lscala/Tuple19;

  public scala.collection.Iterator<java.lang.Object> productIterator();
    descriptor: ()Lscala/collection/Iterator;
    flags: (0x0001) ACC_PUBLIC
    Code:
      stack=3, locals=1, args_size=1
         0: new           #15                 // class scala/runtime/ScalaRunTime$$anon$1
         3: dup
         4: aload_0
         5: invokespecial #266                // Method scala/runtime/ScalaRunTime$$anon$1."<init>":(Lscala/Product;)V
         8: areturn
      LineNumberTable:
        line 41: 0
      LocalVariableTable:
        Start  Length  Slot  Name   Signature
            0       9     0  this   Lscala/Tuple19;
    Signature: #263                         // ()Lscala/collection/Iterator<Ljava/lang/Object;>;

  public boolean canEqual(java.lang.Object);
    descriptor: (Ljava/lang/Object;)Z
    flags: (0x0001) ACC_PUBLIC
    Code:
      stack=1, locals=2, args_size=2
         0: aload_1
         1: instanceof    #2                  // class scala/Tuple19
         4: ireturn
      LineNumberTable:
        line 41: 0
      LocalVariableTable:
        Start  Length  Slot  Name   Signature
            0       5     0  this   Lscala/Tuple19;
            0       5     1   x$1   Ljava/lang/Object;
    MethodParameters:
      Name                           Flags
      x$1                            final

  public java.lang.String productElementName(int);
    descriptor: (I)Ljava/lang/String;
    flags: (0x0001) ACC_PUBLIC
    Code:
      stack=1, locals=2, args_size=2
         0: iload_1
         1: tableswitch   { // 0 to 18
                       0: 92
                       1: 96
                       2: 100
                       3: 104
                       4: 108
                       5: 112
                       6: 116
                       7: 120
                       8: 124
                       9: 128
                      10: 132
                      11: 136
                      12: 140
                      13: 144
                      14: 148
                      15: 152
                      16: 156
                      17: 160
                      18: 164
                 default: 168
            }
        92: ldc_w         #272                // String _1
        95: areturn
        96: ldc_w         #273                // String _2
        99: areturn
       100: ldc_w         #274                // String _3
       103: areturn
       104: ldc_w         #275                // String _4
       107: areturn
       108: ldc_w         #276                // String _5
       111: areturn
       112: ldc_w         #277                // String _6
       115: areturn
       116: ldc_w         #278                // String _7
       119: areturn
       120: ldc_w         #279                // String _8
       123: areturn
       124: ldc_w         #280                // String _9
       127: areturn
       128: ldc_w         #281                // String _10
       131: areturn
       132: ldc_w         #282                // String _11
       135: areturn
       136: ldc_w         #283                // String _12
       139: areturn
       140: ldc_w         #284                // String _13
       143: areturn
       144: ldc_w         #285                // String _14
       147: areturn
       148: ldc_w         #286                // String _15
       151: areturn
       152: ldc_w         #287                // String _16
       155: areturn
       156: ldc_w         #288                // String _17
       159: areturn
       160: ldc_w         #289                // String _18
       163: areturn
       164: ldc_w         #290                // String _19
       167: areturn
       168: iload_1
       169: invokestatic  #295                // Method scala/runtime/Statics.ioobe:(I)Ljava/lang/Object;
       172: checkcast     #297                // class java/lang/String
       175: areturn
      StackMapTable: number_of_entries = 20
        frame_type = 251 /* same_frame_extended */
          offset_delta = 92
        frame_type = 3 /* same */
        frame_type = 3 /* same */
        frame_type = 3 /* same */
        frame_type = 3 /* same */
        frame_type = 3 /* same */
        frame_type = 3 /* same */
        frame_type = 3 /* same */
        frame_type = 3 /* same */
        frame_type = 3 /* same */
        frame_type = 3 /* same */
        frame_type = 3 /* same */
        frame_type = 3 /* same */
        frame_type = 3 /* same */
        frame_type = 3 /* same */
        frame_type = 3 /* same */
        frame_type = 3 /* same */
        frame_type = 3 /* same */
        frame_type = 3 /* same */
        frame_type = 3 /* same */
      LineNumberTable:
        line 41: 0
      LocalVariableTable:
        Start  Length  Slot  Name   Signature
            0     176     0  this   Lscala/Tuple19;
            0     176     1   x$1   I
    MethodParameters:
      Name                           Flags
      x$1                            final

  public int hashCode();
    descriptor: ()I
    flags: (0x0001) ACC_PUBLIC
    Code:
      stack=2, locals=1, args_size=1
         0: getstatic     #303                // Field scala/util/hashing/MurmurHash3$.MODULE$:Lscala/util/hashing/MurmurHash3$;
         3: aload_0
         4: invokevirtual #307                // Method scala/util/hashing/MurmurHash3$.productHash:(Lscala/Product;)I
         7: ireturn
      LineNumberTable:
        line 41: 0
      LocalVariableTable:
        Start  Length  Slot  Name   Signature
            0       8     0  this   Lscala/Tuple19;

  public boolean equals(java.lang.Object);
    descriptor: (Ljava/lang/Object;)Z
    flags: (0x0001) ACC_PUBLIC
    Code:
      stack=2, locals=4, args_size=2
         0: aload_0
         1: aload_1
         2: if_acmpeq     302
         5: aload_1
         6: instanceof    #2                  // class scala/Tuple19
         9: ifeq          17
        12: iconst_1
        13: istore_2
        14: goto          19
        17: iconst_0
        18: istore_2
        19: iload_2
        20: ifeq          304
        23: aload_1
        24: checkcast     #2                  // class scala/Tuple19
        27: astore_3
        28: aload_0
        29: invokevirtual #174                // Method _1:()Ljava/lang/Object;
        32: aload_3
        33: invokevirtual #174                // Method _1:()Ljava/lang/Object;
        36: invokestatic  #313                // Method scala/runtime/BoxesRunTime.equals:(Ljava/lang/Object;Ljava/lang/Object;)Z
        39: ifeq          298
        42: aload_0
        43: invokevirtual #181                // Method _2:()Ljava/lang/Object;
        46: aload_3
        47: invokevirtual #181                // Method _2:()Ljava/lang/Object;
        50: invokestatic  #313                // Method scala/runtime/BoxesRunTime.equals:(Ljava/lang/Object;Ljava/lang/Object;)Z
        53: ifeq          298
        56: aload_0
        57: invokevirtual #183                // Method _3:()Ljava/lang/Object;
        60: aload_3
        61: invokevirtual #183                // Method _3:()Ljava/lang/Object;
        64: invokestatic  #313                // Method scala/runtime/BoxesRunTime.equals:(Ljava/lang/Object;Ljava/lang/Object;)Z
        67: ifeq          298
        70: aload_0
        71: invokevirtual #185                // Method _4:()Ljava/lang/Object;
        74: aload_3
        75: invokevirtual #185                // Method _4:()Ljava/lang/Object;
        78: invokestatic  #313                // Method scala/runtime/BoxesRunTime.equals:(Ljava/lang/Object;Ljava/lang/Object;)Z
        81: ifeq          298
        84: aload_0
        85: invokevirtual #187                // Method _5:()Ljava/lang/Object;
        88: aload_3
        89: invokevirtual #187                // Method _5:()Ljava/lang/Object;
        92: invokestatic  #313                // Method scala/runtime/BoxesRunTime.equals:(Ljava/lang/Object;Ljava/lang/Object;)Z
        95: ifeq          298
        98: aload_0
        99: invokevirtual #189                // Method _6:()Ljava/lang/Object;
       102: aload_3
       103: invokevirtual #189                // Method _6:()Ljava/lang/Object;
       106: invokestatic  #313                // Method scala/runtime/BoxesRunTime.equals:(Ljava/lang/Object;Ljava/lang/Object;)Z
       109: ifeq          298
       112: aload_0
       113: invokevirtual #191                // Method _7:()Ljava/lang/Object;
       116: aload_3
       117: invokevirtual #191                // Method _7:()Ljava/lang/Object;
       120: invokestatic  #313                // Method scala/runtime/BoxesRunTime.equals:(Ljava/lang/Object;Ljava/lang/Object;)Z
       123: ifeq          298
       126: aload_0
       127: invokevirtual #193                // Method _8:()Ljava/lang/Object;
       130: aload_3
       131: invokevirtual #193                // Method _8:()Ljava/lang/Object;
       134: invokestatic  #313                // Method scala/runtime/BoxesRunTime.equals:(Ljava/lang/Object;Ljava/lang/Object;)Z
       137: ifeq          298
       140: aload_0
       141: invokevirtual #195                // Method _9:()Ljava/lang/Object;
       144: aload_3
       145: invokevirtual #195                // Method _9:()Ljava/lang/Object;
       148: invokestatic  #313                // Method scala/runtime/BoxesRunTime.equals:(Ljava/lang/Object;Ljava/lang/Object;)Z
       151: ifeq          298
       154: aload_0
       155: invokevirtual #197                // Method _10:()Ljava/lang/Object;
       158: aload_3
       159: invokevirtual #197                // Method _10:()Ljava/lang/Object;
       162: invokestatic  #313                // Method scala/runtime/BoxesRunTime.equals:(Ljava/lang/Object;Ljava/lang/Object;)Z
       165: ifeq          298
       168: aload_0
       169: invokevirtual #199                // Method _11:()Ljava/lang/Object;
       172: aload_3
       173: invokevirtual #199                // Method _11:()Ljava/lang/Object;
       176: invokestatic  #313                // Method scala/runtime/BoxesRunTime.equals:(Ljava/lang/Object;Ljava/lang/Object;)Z
       179: ifeq          298
       182: aload_0
       183: invokevirtual #201                // Method _12:()Ljava/lang/Object;
       186: aload_3
       187: invokevirtual #201                // Method _12:()Ljava/lang/Object;
       190: invokestatic  #313                // Method scala/runtime/BoxesRunTime.equals:(Ljava/lang/Object;Ljava/lang/Object;)Z
       193: ifeq          298
       196: aload_0
       197: invokevirtual #203                // Method _13:()Ljava/lang/Object;
       200: aload_3
       201: invokevirtual #203                // Method _13:()Ljava/lang/Object;
       204: invokestatic  #313                // Method scala/runtime/BoxesRunTime.equals:(Ljava/lang/Object;Ljava/lang/Object;)Z
       207: ifeq          298
       210: aload_0
       211: invokevirtual #205                // Method _14:()Ljava/lang/Object;
       214: aload_3
       215: invokevirtual #205                // Method _14:()Ljava/lang/Object;
       218: invokestatic  #313                // Method scala/runtime/BoxesRunTime.equals:(Ljava/lang/Object;Ljava/lang/Object;)Z
       221: ifeq          298
       224: aload_0
       225: invokevirtual #207                // Method _15:()Ljava/lang/Object;
       228: aload_3
       229: invokevirtual #207                // Method _15:()Ljava/lang/Object;
       232: invokestatic  #313                // Method scala/runtime/BoxesRunTime.equals:(Ljava/lang/Object;Ljava/lang/Object;)Z
       235: ifeq          298
       238: aload_0
       239: invokevirtual #209                // Method _16:()Ljava/lang/Object;
       242: aload_3
       243: invokevirtual #209                // Method _16:()Ljava/lang/Object;
       246: invokestatic  #313                // Method scala/runtime/BoxesRunTime.equals:(Ljava/lang/Object;Ljava/lang/Object;)Z
       249: ifeq          298
       252: aload_0
       253: invokevirtual #211                // Method _17:()Ljava/lang/Object;
       256: aload_3
       257: invokevirtual #211                // Method _17:()Ljava/lang/Object;
       260: invokestatic  #313                // Method scala/runtime/BoxesRunTime.equals:(Ljava/lang/Object;Ljava/lang/Object;)Z
       263: ifeq          298
       266: aload_0
       267: invokevirtual #213                // Method _18:()Ljava/lang/Object;
       270: aload_3
       271: invokevirtual #213                // Method _18:()Ljava/lang/Object;
       274: invokestatic  #313                // Method scala/runtime/BoxesRunTime.equals:(Ljava/lang/Object;Ljava/lang/Object;)Z
       277: ifeq          298
       280: aload_0
       281: invokevirtual #215                // Method _19:()Ljava/lang/Object;
       284: aload_3
       285: invokevirtual #215                // Method _19:()Ljava/lang/Object;
       288: invokestatic  #313                // Method scala/runtime/BoxesRunTime.equals:(Ljava/lang/Object;Ljava/lang/Object;)Z
       291: ifeq          298
       294: iconst_1
       295: goto          299
       298: iconst_0
       299: ifeq          304
       302: iconst_1
       303: ireturn
       304: iconst_0
       305: ireturn
      StackMapTable: number_of_entries = 6
        frame_type = 17 /* same */
        frame_type = 252 /* append */
          offset_delta = 1
          locals = [ int ]
        frame_type = 252 /* append */
          offset_delta = 278
          locals = [ class scala/Tuple19 ]
        frame_type = 64 /* same_locals_1_stack_item */
          stack = [ int ]
        frame_type = 249 /* chop */
          offset_delta = 2
        frame_type = 252 /* append */
          offset_delta = 1
          locals = [ int ]
      LineNumberTable:
        line 41: 0
      LocalVariableTable:
        Start  Length  Slot  Name   Signature
            0     306     0  this   Lscala/Tuple19;
            0     306     1   x$1   Ljava/lang/Object;
    MethodParameters:
      Name                           Flags
      x$1                            final

  public scala.Tuple19(T1, T2, T3, T4, T5, T6, T7, T8, T9, T10, T11, T12, T13, T14, T15, T16, T17, T18, T19);
    descriptor: (Ljava/lang/Object;Ljava/lang/Object;Ljava/lang/Object;Ljava/lang/Object;Ljava/lang/Object;Ljava/lang/Object;Ljava/lang/Object;Ljava/lang/Object;Ljava/lang/Object;Ljava/lang/Object;Ljava/lang/Object;Ljava/lang/Object;Ljava/lang/Object;Ljava/lang/Object;Ljava/lang/Object;Ljava/lang/Object;Ljava/lang/Object;Ljava/lang/Object;Ljava/lang/Object;)V
    flags: (0x0001) ACC_PUBLIC
    Code:
      stack=2, locals=20, args_size=20
         0: aload_0
         1: aload_1
         2: putfield      #104                // Field _1:Ljava/lang/Object;
         5: aload_0
         6: aload_2
         7: putfield      #107                // Field _2:Ljava/lang/Object;
        10: aload_0
        11: aload_3
        12: putfield      #110                // Field _3:Ljava/lang/Object;
        15: aload_0
        16: aload         4
        18: putfield      #113                // Field _4:Ljava/lang/Object;
        21: aload_0
        22: aload         5
        24: putfield      #116                // Field _5:Ljava/lang/Object;
        27: aload_0
        28: aload         6
        30: putfield      #119                // Field _6:Ljava/lang/Object;
        33: aload_0
        34: aload         7
        36: putfield      #122                // Field _7:Ljava/lang/Object;
        39: aload_0
        40: aload         8
        42: putfield      #125                // Field _8:Ljava/lang/Object;
        45: aload_0
        46: aload         9
        48: putfield      #128                // Field _9:Ljava/lang/Object;
        51: aload_0
        52: aload         10
        54: putfield      #131                // Field _10:Ljava/lang/Object;
        57: aload_0
        58: aload         11
        60: putfield      #134                // Field _11:Ljava/lang/Object;
        63: aload_0
        64: aload         12
        66: putfield      #137                // Field _12:Ljava/lang/Object;
        69: aload_0
        70: aload         13
        72: putfield      #140                // Field _13:Ljava/lang/Object;
        75: aload_0
        76: aload         14
        78: putfield      #143                // Field _14:Ljava/lang/Object;
        81: aload_0
        82: aload         15
        84: putfield      #146                // Field _15:Ljava/lang/Object;
        87: aload_0
        88: aload         16
        90: putfield      #149                // Field _16:Ljava/lang/Object;
        93: aload_0
        94: aload         17
        96: putfield      #152                // Field _17:Ljava/lang/Object;
        99: aload_0
       100: aload         18
       102: putfield      #155                // Field _18:Ljava/lang/Object;
       105: aload_0
       106: aload         19
       108: putfield      #158                // Field _19:Ljava/lang/Object;
       111: aload_0
       112: invokespecial #317                // Method java/lang/Object."<init>":()V
       115: return
      LineNumberTable:
        line 41: 0
        line 42: 111
      LocalVariableTable:
        Start  Length  Slot  Name   Signature
            0     116     0  this   Lscala/Tuple19;
            0     116     1    _1   Ljava/lang/Object;
            0     116     2    _2   Ljava/lang/Object;
            0     116     3    _3   Ljava/lang/Object;
            0     116     4    _4   Ljava/lang/Object;
            0     116     5    _5   Ljava/lang/Object;
            0     116     6    _6   Ljava/lang/Object;
            0     116     7    _7   Ljava/lang/Object;
            0     116     8    _8   Ljava/lang/Object;
            0     116     9    _9   Ljava/lang/Object;
            0     116    10   _10   Ljava/lang/Object;
            0     116    11   _11   Ljava/lang/Object;
            0     116    12   _12   Ljava/lang/Object;
            0     116    13   _13   Ljava/lang/Object;
            0     116    14   _14   Ljava/lang/Object;
            0     116    15   _15   Ljava/lang/Object;
            0     116    16   _16   Ljava/lang/Object;
            0     116    17   _17   Ljava/lang/Object;
            0     116    18   _18   Ljava/lang/Object;
            0     116    19   _19   Ljava/lang/Object;
    Signature: #314                         // (TT1;TT2;TT3;TT4;TT5;TT6;TT7;TT8;TT9;TT10;TT11;TT12;TT13;TT14;TT15;TT16;TT17;TT18;TT19;)V
    MethodParameters:
      Name                           Flags
      _1                             final
      _2                             final
      _3                             final
      _4                             final
      _5                             final
      _6                             final
      _7                             final
      _8                             final
      _9                             final
      _10                            final
      _11                            final
      _12                            final
      _13                            final
      _14                            final
      _15                            final
      _16                            final
      _17                            final
      _18                            final
      _19                            final
}
InnerClasses:
  public final #15;                       // class scala/runtime/ScalaRunTime$$anon$1
Signature: #3                           // <T1:Ljava/lang/Object;T2:Ljava/lang/Object;T3:Ljava/lang/Object;T4:Ljava/lang/Object;T5:Ljava/lang/Object;T6:Ljava/lang/Object;T7:Ljava/lang/Object;T8:Ljava/lang/Object;T9:Ljava/lang/Object;T10:Ljava/lang/Object;T11:Ljava/lang/Object;T12:Ljava/lang/Object;T13:Ljava/lang/Object;T14:Ljava/lang/Object;T15:Ljava/lang/Object;T16:Ljava/lang/Object;T17:Ljava/lang/Object;T18:Ljava/lang/Object;T19:Ljava/lang/Object;>Ljava/lang/Object;Lscala/Product19<TT1;TT2;TT3;TT4;TT5;TT6;TT7;TT8;TT9;TT10;TT11;TT12;TT13;TT14;TT15;TT16;TT17;TT18;TT19;>;Ljava/io/Serializable;
SourceFile: "Tuple19.scala"
RuntimeVisibleAnnotations:
  0: #11(#12=s#13)
    scala.reflect.ScalaSignature(
      bytes="\u0006\u0005\u001dMb\u0001\u0002&L\u0005:C!\"a\u0014\u0001\u0005+\u0007I\u0011AA)\u0011%\t\u0019\u0006\u0001B\tB\u0003%q\u000b\u0003\u0006\u0002V\u0001\u0011)\u001a!C\u0001\u0003/B\u0011\"!\u0017\u0001\u0005#\u0005\u000b\u0011\u00022\t\u0015\u0005m\u0003A!f\u0001\n\u0003\ti\u0006C\u0005\u0002`\u0001\u0011\t\u0012)A\u0005K\"Q\u0011\u0011\r\u0001\u0003\u0016\u0004%\t!a\u0019\t\u0013\u0005\u0015\u0004A!E!\u0002\u0013A\u0007BCA4\u0001\tU\r\u0011\"\u0001\u0002j!I\u00111\u000e\u0001\u0003\u0012\u0003\u0006Ia\u001b\u0005\u000b\u0003[\u0002!Q3A\u0005\u0002\u0005=\u0004\"CA9\u0001\tE\t\u0015!\u0003o\u0011)\t\u0019\b\u0001BK\u0002\u0013\u0005\u0011Q\u000f\u0005\n\u0003o\u0002!\u0011#Q\u0001\nED!\"!\u001f\u0001\u0005+\u0007I\u0011AA>\u0011%\ti\b\u0001B\tB\u0003%A\u000f\u0003\u0006\u0002\u0000\u0001\u0011)\u001a!C\u0001\u0003\u0003C\u0011\"a!\u0001\u0005#\u0005\u000b\u0011B<\t\u0015\u0005\u0015\u0005A!f\u0001\n\u0003\t9\tC\u0005\u0002\n\u0002\u0011\t\u0012)A\u0005u\"Q\u00111\u0012\u0001\u0003\u0016\u0004%\t!!$\t\u0013\u0005=\u0005A!E!\u0002\u0013i\bBCAI\u0001\tU\r\u0011\"\u0001\u0002\u0014\"Q\u0011Q\u0013\u0001\u0003\u0012\u0003\u0006I!!\u0001\t\u0015\u0005]\u0005A!f\u0001\n\u0003\tI\n\u0003\u0006\u0002\u001c\u0002\u0011\t\u0012)A\u0005\u0003\u000fA!\"!(\u0001\u0005+\u0007I\u0011AAP\u0011)\t\t\u000b\u0001B\tB\u0003%\u0011Q\u0002\u0005\u000b\u0003G\u0003!Q3A\u0005\u0002\u0005\u0015\u0006BCAT\u0001\tE\t\u0015!\u0003\u0002\u0014!Q\u0011\u0011\u0016\u0001\u0003\u0016\u0004%\t!a+\t\u0015\u00055\u0006A!E!\u0002\u0013\tI\u0002\u0003\u0006\u00020\u0002\u0011)\u001a!C\u0001\u0003cC!\"a-\u0001\u0005#\u0005\u000b\u0011BA\u0010\u0011)\t)\f\u0001BK\u0002\u0013\u0005\u0011q\u0017\u0005\u000b\u0003s\u0003!\u0011#Q\u0001\n\u0005\u0015\u0002BCA^\u0001\tU\r\u0011\"\u0001\u0002>\"Q\u0011q\u0018\u0001\u0003\u0012\u0003\u0006I!a\u000b\t\u000f\u0005\u0005\u0007\u0001\"\u0001\u0002D\"9\u0011Q\u001e\u0001\u0005B\u0005=\b\"\u0003B\u0001\u0001\u0005\u0005I\u0011\u0001B\u0002\u0011%\u0011Y\bAI\u0001\n\u0003\u0011i\bC\u0005\u0003<\u0002\t\n\u0011\"\u0001\u0003>\"I!\u0011\u001e\u0001\u0012\u0002\u0013\u0005!1\u001e\u0005\n\u0007/\u0001\u0011\u0013!C\u0001\u00073A\u0011b!\u0012\u0001#\u0003%\taa\u0012\t\u0013\rM\u0004!%A\u0005\u0002\rU\u0004\"CBQ\u0001E\u0005I\u0011ABR\u0011%\u0019y\rAI\u0001\n\u0003\u0019\t\u000eC\u0005\u0004~\u0002\t\n\u0011\"\u0001\u0004\u0000\"IA1\u0006\u0001\u0012\u0002\u0013\u0005AQ\u0006\u0005\n\t3\u0002\u0011\u0013!C\u0001\t7B\u0011\u0002b\"\u0001#\u0003%\t\u0001\"#\t\u0013\u0011U\u0006!%A\u0005\u0002\u0011]\u0006\"\u0003Cr\u0001E\u0005I\u0011\u0001Cs\u0011%)\t\u0002AI\u0001\n\u0003)\u0019\u0002C\u0005\u0006@\u0001\t\n\u0011\"\u0001\u0006B!IQQ\u000e\u0001\u0012\u0002\u0013\u0005Qq\u000e\u0005\n\u000b7\u0003\u0011\u0013!C\u0001\u000b;C\u0011\"\"3\u0001#\u0003%\t!b3\t\u0013\u0015]\b!!A\u0005B\u0015e\b\"\u0003D\u0005\u0001\u0005\u0005I\u0011\tD\u0006\u0011%1I\u0002AA\u0001\n\u00031Y\u0002C\u0005\u0007(\u0001\t\t\u0011\"\u0011\u0007*!Ia1\u0007\u0001\u0002\u0002\u0013\u0005cQ\u0007\u0005\n\ro\u0001\u0011\u0011!C!\rs9\u0011B\"\u0010L\u0003\u0003E\tAb\u0010\u0007\u0011)[\u0015\u0011!E\u0001\r\u0003Bq!!1E\t\u00031i\u0005C\u0005\u0002n\u0012\u000b\t\u0011\"\u0012\u0007P!Ia\u0011\u000b#\u0002\u0002\u0013\u0005e1\u000b\u0005\n\r\u0017$\u0015\u0011!CA\r\u001bD\u0011b\"\u000bE\u0003\u0003%Iab\u000b\u0003\u000fQ+\b\u000f\\32s)\tA*A\u0003tG\u0006d\u0017m\u0001\u0001\u00169=K6MZ5m_J,\bp\u001f@\u0002\u0004\u0005%\u0011qBA\u000b\u00037\t\t#a\n\u0002.M9\u0001\u0001\u0015+\u00022\u0005]\u0002CA)S\u001b\u0005Y\u0015BA*L\u0005\u0019\te.\u001f*fMBi\u0012+V,cK\"\\g.\u001d;xuv\f\t!a\u0002\u0002\u000e\u0005M\u0011\u0011DA\u0010\u0003K\tY#\u0003\u0002W\u0017\nI\u0001K]8ek\u000e$\u0018\'\u000f\t\u00031fc\u0001\u0001\u0002\u0004[\u0001\u0011\u0015\ra\u0017\u0002\u0003)F\n\"\u0001X0\u0011\u0005Ek\u0016B\u00010L\u0005\u001dqu\u000e\u001e5j]\u001e\u0004\"!\u00151\n\u0005\u0005\\%aA!osB\u0011\u0001l\u0019\u0003\u0007I\u0002!)\u0019A.\u0003\u0005Q\u0013\u0004C\u0001-g\t\u00199\u0007\u0001\"b\u00017\n\u0011Ak\r\t\u00031&$aA\u001b\u0001\u0005\u0006\u0004Y&A\u0001+5!\tAF\u000e\u0002\u0004n\u0001\u0011\u0015\ra\u0017\u0002\u0003)V\u0002\"\u0001W8\u0005\rA\u0004AQ1\u0001\\\u0005\t!f\u0007\u0005\u0002Ye\u001211\u000f\u0001CC\u0002m\u0013!\u0001V\u001c\u0011\u0005a+HA\u0002<\u0001\t\u000b\u00071L\u0001\u0002UqA\u0011\u0001\f\u001f\u0003\u0007s\u0002!)\u0019A.\u0003\u0005QK\u0004C\u0001-|\t\u0019a\b\u0001\"b\u00017\n\u0019A+\r\u0019\u0011\u0005asHAB@\u0001\t\u000b\u00071LA\u0002UcE\u00022\u0001WA\u0002\t\u001d\t)\u0001\u0001CC\u0002m\u00131\u0001V\u00193!\rA\u0016\u0011\u0002\u0003\b\u0003\u0017\u0001AQ1\u0001\\\u0005\r!\u0016g\r\t\u00041\u0006=AaBA\t\u0001\u0011\u0015\ra\u0017\u0002\u0004)F\"\u0004c\u0001-\u0002\u0016\u00119\u0011q\u0003\u0001\u0005\u0006\u0004Y&a\u0001+2kA\u0019\u0001,a\u0007\u0005\u000f\u0005u\u0001\u0001\"b\u00017\n\u0019A+\r\u001c\u0011\u0007a\u000b\t\u0003B\u0004\u0002$\u0001!)\u0019A.\u0003\u0007Q\u000bt\u0007E\u0002Y\u0003O!q!!\u000b\u0001\t\u000b\u00071LA\u0002Uca\u00022\u0001WA\u0017\t\u001d\ty\u0003\u0001CC\u0002m\u00131\u0001V\u0019:!\r\t\u00161G\u0005\u0004\u0003kY%a\u0002)s_\u0012,8\r\u001e\t\u0005\u0003s\tIE\u0004\u0003\u0002<\u0005\u0015c\u0002BA\u001f\u0003\u0007j!!a\u0010\u000b\u0007\u0005\u0005S*\u0001\u0004=e>|GOP\u0005\u0002\u0019&\u0019\u0011qI&\u0002\u000fA\f7m[1hK&!\u00111JA\'\u00051\u0019VM]5bY&T\u0018M\u00197f\u0015\r\t9eS\u0001\u0003?F*\u0012aV\u0001\u0004?F\u0002\u0013AA03+\u0005\u0011\u0017aA03A\u0005\u0011qlM\u000b\u0002K\u0006\u0019ql\r\u0011\u0002\u0005}#T#\u00015\u0002\u0007}#\u0004%\u0001\u0002`kU\t1.A\u0002`k\u0001\n!a\u0018\u001c\u0016\u00039\f1a\u0018\u001c!\u0003\tyv\'F\u0001r\u0003\ryv\u0007I\u0001\u0003?b*\u0012\u0001^\u0001\u0004?b\u0002\u0013AA0:+\u00059\u0018aA0:A\u0005\u0019q,\r\u0019\u0016\u0003i\fAaX\u00191A\u0005\u0019q,M\u0019\u0016\u0003u\fAaX\u00192A\u0005\u0019q,\r\u001a\u0016\u0005\u0005\u0005\u0011\u0001B02e\u0001\n1aX\u00194+\t\t9!\u0001\u0003`cM\u0002\u0013aA02iU\u0011\u0011QB\u0001\u0005?F\"\u0004%A\u0002`cU*\"!a\u0005\u0002\t}\u000bT\u0007I\u0001\u0004?F2TCAA\r\u0003\u0011y\u0016G\u000e\u0011\u0002\u0007}\u000bt\'\u0006\u0002\u0002 \u0005!q,M\u001c!\u0003\ry\u0016\u0007O\u000b\u0003\u0003K\tAaX\u00199A\u0005\u0019q,M\u001d\u0016\u0005\u0005-\u0012\u0001B02s\u0001\na\u0001P5oSRtD\u0003KAc\u0003\u000f\fI-a3\u0002N\u0006=\u0017\u0011[Aj\u0003+\f9.!7\u0002\\\u0006u\u0017q\\Aq\u0003G\f)/a:\u0002j\u0006-\b#H)\u0001/\n,\u0007n\u001b8ri^TX0!\u0001\u0002\b\u00055\u00111CA\r\u0003?\t)#a\u000b\t\r\u0005=s\u00051\u0001X\u0011\u0019\t)f\na\u0001E\"1\u00111L\u0014A\u0002\u0015Da!!\u0019(\u0001\u0004A\u0007BBA4O\u0001\u00071\u000e\u0003\u0004\u0002n\u001d\u0002\rA\u001c\u0005\u0007\u0003g:\u0003\u0019A9\t\r\u0005et\u00051\u0001u\u0011\u0019\tyh\na\u0001o\"1\u0011QQ\u0014A\u0002iDa!a#(\u0001\u0004i\bbBAIO\u0001\u0007\u0011\u0011\u0001\u0005\b\u0003/;\u0003\u0019AA\u0004\u0011\u001d\tij\na\u0001\u0003\u001bAq!a)(\u0001\u0004\t\u0019\u0002C\u0004\u0002*\u001e\u0002\r!!\u0007\t\u000f\u0005=v\u00051\u0001\u0002 !9\u0011QW\u0014A\u0002\u0005\u0015\u0002bBA^O\u0001\u0007\u00111F\u0001\ti>\u001cFO]5oOR\u0011\u0011\u0011\u001f\t\u0005\u0003g\fYP\u0004\u0003\u0002v\u0006]\bcAA\u001f\u0017&\u0019\u0011\u0011`&\u0002\rA\u0013X\rZ3g\u0013\u0011\ti0a@\u0003\rM#(/\u001b8h\u0015\r\tIpS\u0001\u0005G>\u0004\u00180\u0006\u0015\u0003\u0006\t-!q\u0002B\n\u0005/\u0011YBa\b\u0003$\t\u001d\"1\u0006B\u0018\u0005g\u00119Da\u000f\u0003@\t\r#q\tB&\u0005\u001f\u0012\u0019\u0006\u0006\u0015\u0003\b\tU#q\u000bB-\u00057\u0012iFa\u0018\u0003b\t\r$Q\rB4\u0005S\u0012YG!\u001c\u0003p\tE$1\u000fB;\u0005o\u0012I\b\u0005\u0015R\u0001\t%!Q\u0002B\t\u0005+\u0011IB!\b\u0003\"\t\u0015\"\u0011\u0006B\u0017\u0005c\u0011)D!\u000f\u0003>\t\u0005#Q\tB%\u0005\u001b\u0012\t\u0006E\u0002Y\u0005\u0017!QAW\u0015C\u0002m\u00032\u0001\u0017B\b\t\u0015!\u0017F1\u0001\\!\rA&1\u0003\u0003\u0006O&\u0012\ra\u0017\t\u00041\n]A!\u00026*\u0005\u0004Y\u0006c\u0001-\u0003\u001c\u0011)Q.\u000bb\u00017B\u0019\u0001La\b\u0005\u000bAL#\u0019A.\u0011\u0007a\u0013\u0019\u0003B\u0003tS\t\u00071\fE\u0002Y\u0005O!QA^\u0015C\u0002m\u00032\u0001\u0017B\u0016\t\u0015I\u0018F1\u0001\\!\rA&q\u0006\u0003\u0006y&\u0012\ra\u0017\t\u00041\nMB!B@*\u0005\u0004Y\u0006c\u0001-\u00038\u00111\u0011QA\u0015C\u0002m\u00032\u0001\u0017B\u001e\t\u0019\tY!\u000bb\u00017B\u0019\u0001La\u0010\u0005\r\u0005E\u0011F1\u0001\\!\rA&1\t\u0003\u0007\u0003/I#\u0019A.\u0011\u0007a\u00139\u0005\u0002\u0004\u0002\u001e%\u0012\ra\u0017\t\u00041\n-CABA\u0012S\t\u00071\fE\u0002Y\u0005\u001f\"a!!\u000b*\u0005\u0004Y\u0006c\u0001-\u0003T\u00111\u0011qF\u0015C\u0002mC\u0011\"a\u0014*!\u0003\u0005\rA!\u0003\t\u0013\u0005U\u0013\u0006%AA\u0002\t5\u0001\"CA.SA\u0005\t\u0019\u0001B\t\u0011%\t\t\'\u000bI\u0001\u0002\u0004\u0011)\u0002C\u0005\u0002h%\u0002\n\u00111\u0001\u0003\u001a!I\u0011QN\u0015\u0011\u0002\u0003\u0007!Q\u0004\u0005\n\u0003gJ\u0003\u0013!a\u0001\u0005CA\u0011\"!\u001f*!\u0003\u0005\rA!\n\t\u0013\u0005}\u0014\u0006%AA\u0002\t%\u0002\"CACSA\u0005\t\u0019\u0001B\u0017\u0011%\tY)\u000bI\u0001\u0002\u0004\u0011\t\u0004C\u0005\u0002\u0012&\u0002\n\u00111\u0001\u00036!I\u0011qS\u0015\u0011\u0002\u0003\u0007!\u0011\b\u0005\n\u0003;K\u0003\u0013!a\u0001\u0005{A\u0011\"a)*!\u0003\u0005\rA!\u0011\t\u0013\u0005%\u0016\u0006%AA\u0002\t\u0015\u0003\"CAXSA\u0005\t\u0019\u0001B%\u0011%\t),\u000bI\u0001\u0002\u0004\u0011i\u0005C\u0005\u0002<&\u0002\n\u00111\u0001\u0003R\u0005q1m\u001c9zI\u0011,g-Y;mi\u0012\nT\u0003\u000bB@\u0005+\u00139J!\'\u0003\u001c\nu%q\u0014BQ\u0005G\u0013)Ka*\u0003*\n-&Q\u0016BX\u0005c\u0013\u0019L!.\u00038\neVC\u0001BAU\r9&1Q\u0016\u0003\u0005\u000b\u0003BAa\"\u0003\u00126\u0011!\u0011\u0012\u0006\u0005\u0005\u0017\u0013i)A\u0005v]\u000eDWmY6fI*\u0019!qR&\u0002\u0015\u0005tgn\u001c;bi&|g.\u0003\u0003\u0003\u0014\n%%!E;oG\",7m[3e-\u0006\u0014\u0018.\u00198dK\u0012)!L\u000bb\u00017\u0012)AM\u000bb\u00017\u0012)qM\u000bb\u00017\u0012)!N\u000bb\u00017\u0012)QN\u000bb\u00017\u0012)\u0001O\u000bb\u00017\u0012)1O\u000bb\u00017\u0012)aO\u000bb\u00017\u0012)\u0011P\u000bb\u00017\u0012)AP\u000bb\u00017\u0012)qP\u000bb\u00017\u00121\u0011Q\u0001\u0016C\u0002m#a!a\u0003+\u0005\u0004YFABA\tU\t\u00071\f\u0002\u0004\u0002\u0018)\u0012\ra\u0017\u0003\u0007\u0003;Q#\u0019A.\u0005\r\u0005\r\"F1\u0001\\\t\u0019\tIC\u000bb\u00017\u00121\u0011q\u0006\u0016C\u0002m\u000babY8qs\u0012\"WMZ1vYR$#\'\u0006\u0015\u0003@\n\r\'Q\u0019Bd\u0005\u0013\u0014YM!4\u0003P\nE\'1\u001bBk\u0005/\u0014INa7\u0003^\n}\'\u0011\u001dBr\u0005K\u00149/\u0006\u0002\u0003B*\u001a!Ma!\u0005\u000bi[#\u0019A.\u0005\u000b\u0011\\#\u0019A.\u0005\u000b\u001d\\#\u0019A.\u0005\u000b)\\#\u0019A.\u0005\u000b5\\#\u0019A.\u0005\u000bA\\#\u0019A.\u0005\u000bM\\#\u0019A.\u0005\u000bY\\#\u0019A.\u0005\u000be\\#\u0019A.\u0005\u000bq\\#\u0019A.\u0005\u000b}\\#\u0019A.\u0005\r\u0005\u00151F1\u0001\\\t\u0019\tYa\u000bb\u00017\u00121\u0011\u0011C\u0016C\u0002m#a!a\u0006,\u0005\u0004YFABA\u000fW\t\u00071\f\u0002\u0004\u0002$-\u0012\ra\u0017\u0003\u0007\u0003SY#\u0019A.\u0005\r\u0005=2F1\u0001\\\u00039\u0019w\u000e]=%I\u00164\u0017-\u001e7uIM*\u0002F!<\u0003r\nM(Q\u001fB|\u0005s\u0014YP!@\u0003\u0000\u000e\u000511AB\u0003\u0007\u000f\u0019Iaa\u0003\u0004\u000e\r=1\u0011CB\n\u0007+)\"Aa<+\u0007\u0015\u0014\u0019\tB\u0003[Y\t\u00071\fB\u0003eY\t\u00071\fB\u0003hY\t\u00071\fB\u0003kY\t\u00071\fB\u0003nY\t\u00071\fB\u0003qY\t\u00071\fB\u0003tY\t\u00071\fB\u0003wY\t\u00071\fB\u0003zY\t\u00071\fB\u0003}Y\t\u00071\fB\u0003\u0000Y\t\u00071\f\u0002\u0004\u0002\u00061\u0012\ra\u0017\u0003\u0007\u0003\u0017a#\u0019A.\u0005\r\u0005EAF1\u0001\\\t\u0019\t9\u0002\fb\u00017\u00121\u0011Q\u0004\u0017C\u0002m#a!a\t-\u0005\u0004YFABA\u0015Y\t\u00071\f\u0002\u0004\u000201\u0012\raW\u0001\u000fG>\u0004\u0018\u0010\n3fM\u0006,H\u000e\u001e\u00135+!\u001aYba\b\u0004\"\r\r2QEB\u0014\u0007S\u0019Yc!\f\u00040\rE21GB\u001b\u0007o\u0019Ida\u000f\u0004>\r}2\u0011IB\"+\t\u0019iBK\u0002i\u0005\u0007#QAW\u0017C\u0002m#Q\u0001Z\u0017C\u0002m#QaZ\u0017C\u0002m#QA[\u0017C\u0002m#Q!\\\u0017C\u0002m#Q\u0001]\u0017C\u0002m#Qa]\u0017C\u0002m#QA^\u0017C\u0002m#Q!_\u0017C\u0002m#Q\u0001`\u0017C\u0002m#Qa`\u0017C\u0002m#a!!\u0002.\u0005\u0004YFABA\u0006[\t\u00071\f\u0002\u0004\u0002\u00125\u0012\ra\u0017\u0003\u0007\u0003/i#\u0019A.\u0005\r\u0005uQF1\u0001\\\t\u0019\t\u0019#\fb\u00017\u00121\u0011\u0011F\u0017C\u0002m#a!a\f.\u0005\u0004Y\u0016AD2paf$C-\u001a4bk2$H%N\u000b)\u0007\u0013\u001aiea\u0014\u0004R\rM3QKB,\u00073\u001aYf!\u0018\u0004`\r\u000541MB3\u0007O\u001aIga\u001b\u0004n\r=4\u0011O\u000b\u0003\u0007\u0017R3a\u001bBB\t\u0015QfF1\u0001\\\t\u0015!gF1\u0001\\\t\u00159gF1\u0001\\\t\u0015QgF1\u0001\\\t\u0015igF1\u0001\\\t\u0015\u0001hF1\u0001\\\t\u0015\u0019hF1\u0001\\\t\u00151hF1\u0001\\\t\u0015IhF1\u0001\\\t\u0015ahF1\u0001\\\t\u0015yhF1\u0001\\\t\u0019\t)A\fb\u00017\u00121\u00111\u0002\u0018C\u0002m#a!!\u0005/\u0005\u0004YFABA\f]\t\u00071\f\u0002\u0004\u0002\u001e9\u0012\ra\u0017\u0003\u0007\u0003Gq#\u0019A.\u0005\r\u0005%bF1\u0001\\\t\u0019\tyC\fb\u00017\u0006q1m\u001c9zI\u0011,g-Y;mi\u00122T\u0003KB<\u0007w\u001aiha \u0004\u0002\u000e\r5QQBD\u0007\u0013\u001bYi!$\u0004\u0010\u000eE51SBK\u0007/\u001bIja\'\u0004\u001e\u000e}UCAB=U\rq\'1\u0011\u0003\u00065>\u0012\ra\u0017\u0003\u0006I>\u0012\ra\u0017\u0003\u0006O>\u0012\ra\u0017\u0003\u0006U>\u0012\ra\u0017\u0003\u0006[>\u0012\ra\u0017\u0003\u0006a>\u0012\ra\u0017\u0003\u0006g>\u0012\ra\u0017\u0003\u0006m>\u0012\ra\u0017\u0003\u0006s>\u0012\ra\u0017\u0003\u0006y>\u0012\ra\u0017\u0003\u0006\u007f>\u0012\ra\u0017\u0003\u0007\u0003\u000by#\u0019A.\u0005\r\u0005-qF1\u0001\\\t\u0019\t\tb\fb\u00017\u00121\u0011qC\u0018C\u0002m#a!!\b0\u0005\u0004YFABA\u0012_\t\u00071\f\u0002\u0004\u0002*=\u0012\ra\u0017\u0003\u0007\u0003_y#\u0019A.\u0002\u001d\r|\u0007/\u001f\u0013eK\u001a\fW\u000f\u001c;%oUA3QUBU\u0007W\u001bika,\u00042\u000eM6QWB\\\u0007s\u001bYl!0\u0004@\u000e\u000571YBc\u0007\u000f\u001cIma3\u0004NV\u00111q\u0015\u0016\u0004c\n\rE!\u0002.1\u0005\u0004YF!\u000231\u0005\u0004YF!B41\u0005\u0004YF!\u000261\u0005\u0004YF!B71\u0005\u0004YF!\u000291\u0005\u0004YF!B:1\u0005\u0004YF!\u0002<1\u0005\u0004YF!B=1\u0005\u0004YF!\u0002?1\u0005\u0004YF!B@1\u0005\u0004YFABA\u0003a\t\u00071\f\u0002\u0004\u0002\fA\u0012\ra\u0017\u0003\u0007\u0003#\u0001$\u0019A.\u0005\r\u0005]\u0001G1\u0001\\\t\u0019\ti\u0002\rb\u00017\u00121\u00111\u0005\u0019C\u0002m#a!!\u000b1\u0005\u0004YFABA\u0018a\t\u00071,\u0001\bd_BLH\u0005Z3gCVdG\u000f\n\u001d\u0016Q\rM7q[Bm\u00077\u001cina8\u0004b\u000e\r8Q]Bt\u0007S\u001cYo!<\u0004p\u000eE81_B{\u0007o\u001cIpa?\u0016\u0005\rU\'f\u0001;\u0003\u0004\u0012)!,\rb\u00017\u0012)A-\rb\u00017\u0012)q-\rb\u00017\u0012)!.\rb\u00017\u0012)Q.\rb\u00017\u0012)\u0001/\rb\u00017\u0012)1/\rb\u00017\u0012)a/\rb\u00017\u0012)\u00110\rb\u00017\u0012)A0\rb\u00017\u0012)q0\rb\u00017\u00121\u0011QA\u0019C\u0002m#a!a\u00032\u0005\u0004YFABA\tc\t\u00071\f\u0002\u0004\u0002\u0018E\u0012\ra\u0017\u0003\u0007\u0003;\t$\u0019A.\u0005\r\u0005\r\u0012G1\u0001\\\t\u0019\tI#\rb\u00017\u00121\u0011qF\u0019C\u0002m\u000babY8qs\u0012\"WMZ1vYR$\u0013(\u0006\u0015\u0005\u0002\u0011\u0015Aq\u0001C\u0005\t\u0017!i\u0001b\u0004\u0005\u0012\u0011MAQ\u0003C\f\t3!Y\u0002\"\b\u0005 \u0011\u0005B1\u0005C\u0013\tO!I#\u0006\u0002\u0005\u0004)\u001aqOa!\u0005\u000bi\u0013$\u0019A.\u0005\u000b\u0011\u0014$\u0019A.\u0005\u000b\u001d\u0014$\u0019A.\u0005\u000b)\u0014$\u0019A.\u0005\u000b5\u0014$\u0019A.\u0005\u000bA\u0014$\u0019A.\u0005\u000bM\u0014$\u0019A.\u0005\u000bY\u0014$\u0019A.\u0005\u000be\u0014$\u0019A.\u0005\u000bq\u0014$\u0019A.\u0005\u000b}\u0014$\u0019A.\u0005\r\u0005\u0015!G1\u0001\\\t\u0019\tYA\rb\u00017\u00121\u0011\u0011\u0003\u001aC\u0002m#a!a\u00063\u0005\u0004YFABA\u000fe\t\u00071\f\u0002\u0004\u0002$I\u0012\ra\u0017\u0003\u0007\u0003S\u0011$\u0019A.\u0005\r\u0005=\"G1\u0001\\\u0003=\u0019w\u000e]=%I\u00164\u0017-\u001e7uIE\u0002T\u0003\u000bC\u0018\tg!)\u0004b\u000e\u0005:\u0011mBQ\bC \t\u0003\"\u0019\u0005\"\u0012\u0005H\u0011%C1\nC\'\t\u001f\"\t\u0006b\u0015\u0005V\u0011]SC\u0001C\u0019U\rQ(1\u0011\u0003\u00065N\u0012\ra\u0017\u0003\u0006IN\u0012\ra\u0017\u0003\u0006ON\u0012\ra\u0017\u0003\u0006UN\u0012\ra\u0017\u0003\u0006[N\u0012\ra\u0017\u0003\u0006aN\u0012\ra\u0017\u0003\u0006gN\u0012\ra\u0017\u0003\u0006mN\u0012\ra\u0017\u0003\u0006sN\u0012\ra\u0017\u0003\u0006yN\u0012\ra\u0017\u0003\u0006\u007fN\u0012\ra\u0017\u0003\u0007\u0003\u000b\u0019$\u0019A.\u0005\r\u0005-1G1\u0001\\\t\u0019\t\tb\rb\u00017\u00121\u0011qC\u001aC\u0002m#a!!\b4\u0005\u0004YFABA\u0012g\t\u00071\f\u0002\u0004\u0002*M\u0012\ra\u0017\u0003\u0007\u0003_\u0019$\u0019A.\u0002\u001f\r|\u0007/\u001f\u0013eK\u001a\fW\u000f\u001c;%cE*\u0002\u0006\"\u0018\u0005b\u0011\rDQ\rC4\tS\"Y\u0007\"\u001c\u0005p\u0011ED1\u000fC;\to\"I\bb\u001f\u0005~\u0011}D\u0011\u0011CB\t\u000b+\"\u0001b\u0018+\u0007u\u0014\u0019\tB\u0003[i\t\u00071\fB\u0003ei\t\u00071\fB\u0003hi\t\u00071\fB\u0003ki\t\u00071\fB\u0003ni\t\u00071\fB\u0003qi\t\u00071\fB\u0003ti\t\u00071\fB\u0003wi\t\u00071\fB\u0003zi\t\u00071\fB\u0003}i\t\u00071\fB\u0003\u0000i\t\u00071\f\u0002\u0004\u0002\u0006Q\u0012\ra\u0017\u0003\u0007\u0003\u0017!$\u0019A.\u0005\r\u0005EAG1\u0001\\\t\u0019\t9\u0002\u000eb\u00017\u00121\u0011Q\u0004\u001bC\u0002m#a!a\t5\u0005\u0004YFABA\u0015i\t\u00071\f\u0002\u0004\u00020Q\u0012\raW\u0001\u0010G>\u0004\u0018\u0010\n3fM\u0006,H\u000e\u001e\u00132eUAC1\u0012CH\t##\u0019\n\"&\u0005\u0018\u0012eE1\u0014CO\t?#\t\u000bb)\u0005&\u0012\u001dF\u0011\u0016CV\t[#y\u000b\"-\u00054V\u0011AQ\u0012\u0016\u0005\u0003\u0003\u0011\u0019\tB\u0003[k\t\u00071\fB\u0003ek\t\u00071\fB\u0003hk\t\u00071\fB\u0003kk\t\u00071\fB\u0003nk\t\u00071\fB\u0003qk\t\u00071\fB\u0003tk\t\u00071\fB\u0003wk\t\u00071\fB\u0003zk\t\u00071\fB\u0003}k\t\u00071\fB\u0003\u0000k\t\u00071\f\u0002\u0004\u0002\u0006U\u0012\ra\u0017\u0003\u0007\u0003\u0017)$\u0019A.\u0005\r\u0005EQG1\u0001\\\t\u0019\t9\"\u000eb\u00017\u00121\u0011QD\u001bC\u0002m#a!a\t6\u0005\u0004YFABA\u0015k\t\u00071\f\u0002\u0004\u00020U\u0012\raW\u0001\u0010G>\u0004\u0018\u0010\n3fM\u0006,H\u000e\u001e\u00132gUAC\u0011\u0018C_\t\u007f#\t\rb1\u0005F\u0012\u001dG\u0011\u001aCf\t\u001b$y\r\"5\u0005T\u0012UGq\u001bCm\t7$i\u000eb8\u0005bV\u0011A1\u0018\u0016\u0005\u0003\u000f\u0011\u0019\tB\u0003[m\t\u00071\fB\u0003em\t\u00071\fB\u0003hm\t\u00071\fB\u0003km\t\u00071\fB\u0003nm\t\u00071\fB\u0003qm\t\u00071\fB\u0003tm\t\u00071\fB\u0003wm\t\u00071\fB\u0003zm\t\u00071\fB\u0003}m\t\u00071\fB\u0003\u0000m\t\u00071\f\u0002\u0004\u0002\u0006Y\u0012\ra\u0017\u0003\u0007\u0003\u00171$\u0019A.\u0005\r\u0005EaG1\u0001\\\t\u0019\t9B\u000eb\u00017\u00121\u0011Q\u0004\u001cC\u0002m#a!a\t7\u0005\u0004YFABA\u0015m\t\u00071\f\u0002\u0004\u00020Y\u0012\raW\u0001\u0010G>\u0004\u0018\u0010\n3fM\u0006,H\u000e\u001e\u00132iUACq\u001dCv\t[$y\u000f\"=\u0005t\u0012UHq\u001fC}\tw$i\u0010b@\u0006\u0002\u0015\rQQAC\u0004\u000b\u0013)Y!\"\u0004\u0006\u0010U\u0011A\u0011\u001e\u0016\u0005\u0003\u001b\u0011\u0019\tB\u0003[o\t\u00071\fB\u0003eo\t\u00071\fB\u0003ho\t\u00071\fB\u0003ko\t\u00071\fB\u0003no\t\u00071\fB\u0003qo\t\u00071\fB\u0003to\t\u00071\fB\u0003wo\t\u00071\fB\u0003zo\t\u00071\fB\u0003}o\t\u00071\fB\u0003\u0000o\t\u00071\f\u0002\u0004\u0002\u0006]\u0012\ra\u0017\u0003\u0007\u0003\u00179$\u0019A.\u0005\r\u0005EqG1\u0001\\\t\u0019\t9b\u000eb\u00017\u00121\u0011QD\u001cC\u0002m#a!a\t8\u0005\u0004YFABA\u0015o\t\u00071\f\u0002\u0004\u00020]\u0012\raW\u0001\u0010G>\u0004\u0018\u0010\n3fM\u0006,H\u000e\u001e\u00132kUASQCC\r\u000b7)i\"b\b\u0006\"\u0015\rRQEC\u0014\u000bS)Y#\"\f\u00060\u0015ER1GC\u001b\u000bo)I$b\u000f\u0006>U\u0011Qq\u0003\u0016\u0005\u0003\'\u0011\u0019\tB\u0003[q\t\u00071\fB\u0003eq\t\u00071\fB\u0003hq\t\u00071\fB\u0003kq\t\u00071\fB\u0003nq\t\u00071\fB\u0003qq\t\u00071\fB\u0003tq\t\u00071\fB\u0003wq\t\u00071\fB\u0003zq\t\u00071\fB\u0003}q\t\u00071\fB\u0003\u0000q\t\u00071\f\u0002\u0004\u0002\u0006a\u0012\ra\u0017\u0003\u0007\u0003\u0017A$\u0019A.\u0005\r\u0005E\u0001H1\u0001\\\t\u0019\t9\u0002\u000fb\u00017\u00121\u0011Q\u0004\u001dC\u0002m#a!a\t9\u0005\u0004YFABA\u0015q\t\u00071\f\u0002\u0004\u00020a\u0012\raW\u0001\u0010G>\u0004\u0018\u0010\n3fM\u0006,H\u000e\u001e\u00132mUAS1IC$\u000b\u0013*Y%\"\u0014\u0006P\u0015ES1KC+\u000b/*I&b\u0017\u0006^\u0015}S\u0011MC2\u000bK*9\'\"\u001b\u0006lU\u0011QQ\t\u0016\u0005\u00033\u0011\u0019\tB\u0003[s\t\u00071\fB\u0003es\t\u00071\fB\u0003hs\t\u00071\fB\u0003ks\t\u00071\fB\u0003ns\t\u00071\fB\u0003qs\t\u00071\fB\u0003ts\t\u00071\fB\u0003ws\t\u00071\fB\u0003zs\t\u00071\fB\u0003}s\t\u00071\fB\u0003\u0000s\t\u00071\f\u0002\u0004\u0002\u0006e\u0012\ra\u0017\u0003\u0007\u0003\u0017I$\u0019A.\u0005\r\u0005E\u0011H1\u0001\\\t\u0019\t9\"\u000fb\u00017\u00121\u0011QD\u001dC\u0002m#a!a\t:\u0005\u0004YFABA\u0015s\t\u00071\f\u0002\u0004\u00020e\u0012\raW\u0001\u0010G>\u0004\u0018\u0010\n3fM\u0006,H\u000e\u001e\u00132oUAS\u0011OC;\u000bo*I(b\u001f\u0006~\u0015}T\u0011QCB\u000b\u000b+9)\"#\u0006\f\u00165UqRCI\u000b\'+)*b&\u0006\u001aV\u0011Q1\u000f\u0016\u0005\u0003?\u0011\u0019\tB\u0003[u\t\u00071\fB\u0003eu\t\u00071\fB\u0003hu\t\u00071\fB\u0003ku\t\u00071\fB\u0003nu\t\u00071\fB\u0003qu\t\u00071\fB\u0003tu\t\u00071\fB\u0003wu\t\u00071\fB\u0003zu\t\u00071\fB\u0003}u\t\u00071\fB\u0003\u0000u\t\u00071\f\u0002\u0004\u0002\u0006i\u0012\ra\u0017\u0003\u0007\u0003\u0017Q$\u0019A.\u0005\r\u0005E!H1\u0001\\\t\u0019\t9B\u000fb\u00017\u00121\u0011Q\u0004\u001eC\u0002m#a!a\t;\u0005\u0004YFABA\u0015u\t\u00071\f\u0002\u0004\u00020i\u0012\raW\u0001\u0010G>\u0004\u0018\u0010\n3fM\u0006,H\u000e\u001e\u00132qUASqTCR\u000bK+9+\"+\u0006,\u00165VqVCY\u000bg+),b.\u0006:\u0016mVQXC`\u000b\u0003,\u0019-\"2\u0006HV\u0011Q\u0011\u0015\u0016\u0005\u0003K\u0011\u0019\tB\u0003[w\t\u00071\fB\u0003ew\t\u00071\fB\u0003hw\t\u00071\fB\u0003kw\t\u00071\fB\u0003nw\t\u00071\fB\u0003qw\t\u00071\fB\u0003tw\t\u00071\fB\u0003ww\t\u00071\fB\u0003zw\t\u00071\fB\u0003}w\t\u00071\fB\u0003\u0000w\t\u00071\f\u0002\u0004\u0002\u0006m\u0012\ra\u0017\u0003\u0007\u0003\u0017Y$\u0019A.\u0005\r\u0005E1H1\u0001\\\t\u0019\t9b\u000fb\u00017\u00121\u0011QD\u001eC\u0002m#a!a\t<\u0005\u0004YFABA\u0015w\t\u00071\f\u0002\u0004\u00020m\u0012\raW\u0001\u0010G>\u0004\u0018\u0010\n3fM\u0006,H\u000e\u001e\u00132sUASQZCi\u000b\',).b6\u0006Z\u0016mWQ\\Cp\u000bC,\u0019/\":\u0006h\u0016%X1^Cw\u000b_,\t0b=\u0006vV\u0011Qq\u001a\u0016\u0005\u0003W\u0011\u0019\tB\u0003[y\t\u00071\fB\u0003ey\t\u00071\fB\u0003hy\t\u00071\fB\u0003ky\t\u00071\fB\u0003ny\t\u00071\fB\u0003qy\t\u00071\fB\u0003ty\t\u00071\fB\u0003wy\t\u00071\fB\u0003zy\t\u00071\fB\u0003}y\t\u00071\fB\u0003\u0000y\t\u00071\f\u0002\u0004\u0002\u0006q\u0012\ra\u0017\u0003\u0007\u0003\u0017a$\u0019A.\u0005\r\u0005EAH1\u0001\\\t\u0019\t9\u0002\u0010b\u00017\u00121\u0011Q\u0004\u001fC\u0002m#a!a\t=\u0005\u0004YFABA\u0015y\t\u00071\f\u0002\u0004\u00020q\u0012\raW\u0001\u000eaJ|G-^2u!J,g-\u001b=\u0016\u0005\u0015m\b\u0003BC\u007f\r\u000fi!!b@\u000b\t\u0019\u0005a1A\u0001\u0005Y\u0006twM\u0003\u0002\u0007\u0006\u0005!!.\u0019<b\u0013\u0011\ti0b@\u0002\u001fA\u0014x\u000eZ;di&#XM]1u_J,\"A\"\u0004\u0011\u000b\u0019=aQC0\u000e\u0005\u0019E!b\u0001D\n\u0017\u0006Q1m\u001c7mK\u000e$\u0018n\u001c8\n\t\u0019]a\u0011\u0003\u0002\t\u0013R,\'/\u0019;pe\u0006A1-\u00198FcV\fG\u000e\u0006\u0003\u0007\u001e\u0019\r\u0002cA)\u0007 %\u0019a\u0011E&\u0003\u000f\t{w\u000e\\3b]\"AaQE \u0002\u0002\u0003\u0007q,A\u0002yIE\n!\u0003\u001d:pIV\u001cG/\u00127f[\u0016tGOT1nKR!Q1 D\u0016\u0011%1)\u0003QA\u0001\u0002\u00041i\u0003E\u0002R\r_I1A\"\rL\u0005\rIe\u000e^\u0001\tQ\u0006\u001c\bnQ8eKR\u0011aQF\u0001\u0007KF,\u0018\r\\:\u0015\t\u0019ua1\b\u0005\t\rK\u0011\u0015\u0011!a\u0001?\u00069A+\u001e9mKFJ\u0004CA)E\'\u0011!\u0005Kb\u0011\u0011\t\u0019\u0015c1J\u0007\u0003\r\u000fRAA\"\u0013\u0007\u0004\u0005\u0011\u0011n\\\u0005\u0005\u0003\u001729\u0005\u0006\u0002\u0007@Q\u0011Q1`\u0001\u0006CB\u0004H._\u000b)\r+2YFb\u0018\u0007d\u0019\u001dd1\u000eD8\rg29Hb\u001f\u0007\u0000\u0019\req\u0011DF\r\u001f3\u0019Jb&\u0007\u001c\u001a}e1\u0015\u000b)\r/2)Kb*\u0007*\u001a-fQ\u0016DX\rc3\u0019L\".\u00078\u001aef1\u0018D_\r\u007f3\tMb1\u0007F\u001a\u001dg\u0011\u001a\t)#\u00021IF\"\u0018\u0007b\u0019\u0015d\u0011\u000eD7\rc2)H\"\u001f\u0007~\u0019\u0005eQ\u0011DE\r\u001b3\tJ\"&\u0007\u001a\u001aue\u0011\u0015\t\u00041\u001amC!\u0002.H\u0005\u0004Y\u0006c\u0001-\u0007`\u0011)Am\u0012b\u00017B\u0019\u0001Lb\u0019\u0005\u000b\u001d<%\u0019A.\u0011\u0007a39\u0007B\u0003k\u000f\n\u00071\fE\u0002Y\rW\"Q!\\$C\u0002m\u00032\u0001\u0017D8\t\u0015\u0001xI1\u0001\\!\rAf1\u000f\u0003\u0006g\u001e\u0013\ra\u0017\t\u00041\u001a]D!\u0002<H\u0005\u0004Y\u0006c\u0001-\u0007|\u0011)\u0011p\u0012b\u00017B\u0019\u0001Lb \u0005\u000bq<%\u0019A.\u0011\u0007a3\u0019\tB\u0003\u0000\u000f\n\u00071\fE\u0002Y\r\u000f#a!!\u0002H\u0005\u0004Y\u0006c\u0001-\u0007\f\u00121\u00111B$C\u0002m\u00032\u0001\u0017DH\t\u0019\t\tb\u0012b\u00017B\u0019\u0001Lb%\u0005\r\u0005]qI1\u0001\\!\rAfq\u0013\u0003\u0007\u0003;9%\u0019A.\u0011\u0007a3Y\n\u0002\u0004\u0002$\u001d\u0013\ra\u0017\t\u00041\u001a}EABA\u0015\u000f\n\u00071\fE\u0002Y\rG#a!a\fH\u0005\u0004Y\u0006bBA(\u000f\u0002\u0007a\u0011\f\u0005\b\u0003+:\u0005\u0019\u0001D/\u0011\u001d\tYf\u0012a\u0001\rCBq!!\u0019H\u0001\u00041)\u0007C\u0004\u0002h\u001d\u0003\rA\"\u001b\t\u000f\u00055t\t1\u0001\u0007n!9\u00111O$A\u0002\u0019E\u0004bBA=\u000f\u0002\u0007aQ\u000f\u0005\b\u0003\u007f:\u0005\u0019\u0001D=\u0011\u001d\t)i\u0012a\u0001\r{Bq!a#H\u0001\u00041\t\tC\u0004\u0002\u0012\u001e\u0003\rA\"\"\t\u000f\u0005]u\t1\u0001\u0007\n\"9\u0011QT$A\u0002\u00195\u0005bBAR\u000f\u0002\u0007a\u0011\u0013\u0005\b\u0003S;\u0005\u0019\u0001DK\u0011\u001d\tyk\u0012a\u0001\r3Cq!!.H\u0001\u00041i\nC\u0004\u0002<\u001e\u0003\rA\")\u0002\u000fUt\u0017\r\u001d9msVAcq\u001aDn\r?4\u0019Ob:\u0007l\u001a=h1\u001fD|\rw4ypb\u0001\b\b\u001d-qqBD\n\u000f/9Ybb\b\b$Q!a\u0011[D\u0013!\u0015\tf1\u001bDl\u0013\r1)n\u0013\u0002\u0007\u001fB$\u0018n\u001c8\u0011QE\u0003a\u0011\u001cDo\rC4)O\";\u0007n\u001aEhQ\u001fD}\r{<\ta\"\u0002\b\n\u001d5q\u0011CD\u000b\u000f39ib\"\t\u0011\u0007a3Y\u000eB\u0003[\u0011\n\u00071\fE\u0002Y\r?$Q\u0001\u001a%C\u0002m\u00032\u0001\u0017Dr\t\u00159\u0007J1\u0001\\!\rAfq\u001d\u0003\u0006U\"\u0013\ra\u0017\t\u00041\u001a-H!B7I\u0005\u0004Y\u0006c\u0001-\u0007p\u0012)\u0001\u000f\u0013b\u00017B\u0019\u0001Lb=\u0005\u000bMD%\u0019A.\u0011\u0007a39\u0010B\u0003w\u0011\n\u00071\fE\u0002Y\rw$Q!\u001f%C\u0002m\u00032\u0001\u0017D\u0000\t\u0015a\bJ1\u0001\\!\rAv1\u0001\u0003\u0006\u007f\"\u0013\ra\u0017\t\u00041\u001e\u001dAABA\u0003\u0011\n\u00071\fE\u0002Y\u000f\u0017!a!a\u0003I\u0005\u0004Y\u0006c\u0001-\b\u0010\u00111\u0011\u0011\u0003%C\u0002m\u00032\u0001WD\n\t\u0019\t9\u0002\u0013b\u00017B\u0019\u0001lb\u0006\u0005\r\u0005u\u0001J1\u0001\\!\rAv1\u0004\u0003\u0007\u0003GA%\u0019A.\u0011\u0007a;y\u0002\u0002\u0004\u0002*!\u0013\ra\u0017\t\u00041\u001e\rBABA\u0018\u0011\n\u00071\fC\u0005\b(!\u000b\t\u00111\u0001\u0007X\u0006\u0019\u0001\u0010\n\u0019\u0002\u0019]\u0014\u0018\u000e^3SKBd\u0017mY3\u0015\u0005\u001d5\u0002\u0003BC\u007f\u000f_IAa\"\r\u0006\u0000\n1qJ\u00196fGR\u0004"
    )
  ScalaInlineInfo: length = 0xFE (unknown attribute)
   01 01 00 32 00 47 00 48 01 00 10 00 65 01 00 23
   00 65 01 00 25 00 65 01 00 27 00 65 01 00 29 00
   65 01 00 2B 00 65 01 00 2D 00 65 01 00 2F 00 65
   01 00 31 00 65 01 00 33 00 65 01 00 35 00 65 01
   00 13 00 65 01 00 15 00 65 01 00 17 00 65 01 00
   19 00 65 01 00 1B 00 65 01 00 1D 00 65 01 00 1F
   00 65 01 00 21 00 65 01 01 0B 01 0C 01 00 DC 00
   45 01 00 DD 00 65 01 00 DF 00 65 01 00 E1 00 65
   01 00 E3 00 65 01 00 E5 00 65 01 00 E7 00 65 01
   00 E9 00 65 01 00 EB 00 65 01 00 ED 00 65 01 00
   EF 00 65 01 00 F1 00 65 01 00 F3 00 65 01 00 F5
   00 65 01 00 F7 00 65 01 00 F9 00 65 01 00 FB 00
   65 01 00 FD 00 65 01 00 FF 00 65 01 01 01 00 65
   01 01 34 01 0C 01 01 2A 00 4C 01 00 4B 00 4C 01
   00 52 00 53 01 01 0E 01 0F 01 00 5C 00 5D 01 01
   06 00 5D 01 01 03 00 A0 01 00 9F 00 A0 01
  ScalaSig: length = 0x3 (unknown attribute)
   05 02 00
