Classfile /Users/mw/Projects/slang-braindump/.jar/jar11/assemble/slang-braindump/assemble/content/scala/Tuple11.class
  Last modified May 29, 2022; size 15300 bytes
  SHA-256 checksum e7c55ebc527a265907a40862b92a96350c5c172501ac2a9cb3269c76adb1ad88
  Compiled from "Tuple11.scala"
public final class scala.Tuple11<T1 extends java.lang.Object, T2 extends java.lang.Object, T3 extends java.lang.Object, T4 extends java.lang.Object, T5 extends java.lang.Object, T6 extends java.lang.Object, T7 extends java.lang.Object, T8 extends java.lang.Object, T9 extends java.lang.Object, T10 extends java.lang.Object, T11 extends java.lang.Object> extends java.lang.Object implements scala.Product11<T1, T2, T3, T4, T5, T6, T7, T8, T9, T10, T11>, java.io.Serializable
  minor version: 0
  major version: 52
  flags: (0x0031) ACC_PUBLIC, ACC_FINAL, ACC_SUPER
  this_class: #2                          // scala/Tuple11
  super_class: #5                         // java/lang/Object
  interfaces: 2, fields: 11, methods: 36, attributes: 6
Constant pool:
    #1 = Utf8               scala/Tuple11
    #2 = Class              #1            // scala/Tuple11
    #3 = Utf8               <T1:Ljava/lang/Object;T2:Ljava/lang/Object;T3:Ljava/lang/Object;T4:Ljava/lang/Object;T5:Ljava/lang/Object;T6:Ljava/lang/Object;T7:Ljava/lang/Object;T8:Ljava/lang/Object;T9:Ljava/lang/Object;T10:Ljava/lang/Object;T11:Ljava/lang/Object;>Ljava/lang/Object;Lscala/Product11<TT1;TT2;TT3;TT4;TT5;TT6;TT7;TT8;TT9;TT10;TT11;>;Ljava/io/Serializable;
    #4 = Utf8               java/lang/Object
    #5 = Class              #4            // java/lang/Object
    #6 = Utf8               scala/Product11
    #7 = Class              #6            // scala/Product11
    #8 = Utf8               java/io/Serializable
    #9 = Class              #8            // java/io/Serializable
   #10 = Utf8               Tuple11.scala
   #11 = Utf8               Lscala/reflect/ScalaSignature;
   #12 = Utf8               bytes
   #13 = Utf8               \u0006\u0005\rMh\u0001\u0002\u001a4\u0005ZB\u0001b\u001e\u0001\u0003\u0016\u0004%\t\u0001\u001f\u0005\ts\u0002\u0011\t\u0012)A\u0005\u007f!A!\u0010\u0001BK\u0002\u0013\u00051\u0010\u0003\u0005}\u0001\tE\t\u0015!\u0003K\u0011!i\bA!f\u0001\n\u0003q\b\u0002C@\u0001\u0005#\u0005\u000b\u0011B\'\t\u0015\u0005\u0005\u0001A!f\u0001\n\u0003\t\u0019\u0001C\u0005\u0002\u0006\u0001\u0011\t\u0012)A\u0005!\"Q\u0011q\u0001\u0001\u0003\u0016\u0004%\t!!\u0003\t\u0013\u0005-\u0001A!E!\u0002\u0013\u0019\u0006BCA\u0007\u0001\tU\r\u0011\"\u0001\u0002\u0010!I\u0011\u0011\u0003\u0001\u0003\u0012\u0003\u0006IA\u0016\u0005\u000b\u0003\'\u0001!Q3A\u0005\u0002\u0005U\u0001\"CA\f\u0001\tE\t\u0015!\u0003Z\u0011)\tI\u0002\u0001BK\u0002\u0013\u0005\u00111\u0004\u0005\n\u0003;\u0001!\u0011#Q\u0001\nqC!\"a\b\u0001\u0005+\u0007I\u0011AA\u0011\u0011%\t\u0019\u0003\u0001B\tB\u0003%q\f\u0003\u0006\u0002&\u0001\u0011)\u001a!C\u0001\u0003OA\u0011\"!\u000b\u0001\u0005#\u0005\u000b\u0011\u00022\t\u0015\u0005-\u0002A!f\u0001\n\u0003\ti\u0003C\u0005\u00020\u0001\u0011\t\u0012)A\u0005K\"9\u0011\u0011\u0007\u0001\u0005\u0002\u0005M\u0002bBA\'\u0001\u0011\u0005\u0013q\n\u0005\n\u0003C\u0002\u0011\u0011!C\u0001\u0003GB\u0011\"a+\u0001#\u0003%\t!!,\t\u0013\u0005m\u0007!%A\u0005\u0002\u0005u\u0007\"CA}\u0001E\u0005I\u0011AA~\u0011%\u00119\u0002AI\u0001\n\u0003\u0011I\u0002C\u0005\u00036\u0001\t\n\u0011\"\u0001\u00038!I!1\u000b\u0001\u0012\u0002\u0013\u0005!Q\u000b\u0005\n\u0005c\u0002\u0011\u0013!C\u0001\u0005gB\u0011Ba$\u0001#\u0003%\tA!%\t\u0013\t5\u0006!%A\u0005\u0002\t=\u0006\"\u0003Bf\u0001E\u0005I\u0011\u0001Bg\u0011%\u0011I\u000fAI\u0001\n\u0003\u0011Y\u000fC\u0005\u0004\b\u0001\t\t\u0011\"\u0011\u0004\n!I1\u0011\u0004\u0001\u0002\u0002\u0013\u000531\u0004\u0005\n\u0007S\u0001\u0011\u0011!C\u0001\u0007WA\u0011ba\u000e\u0001\u0003\u0003%\te!\u000f\t\u0013\r\r\u0003!!A\u0005B\r\u0015\u0003\"CB$\u0001\u0005\u0005I\u0011IB%\u000f%\u0019ieMA\u0001\u0012\u0003\u0019yE\u0002\u00053g\u0005\u0005\t\u0012AB)\u0011\u001d\t\t\u0004\fC\u0001\u0007;B\u0011\"!\u0014-\u0003\u0003%)ea\u0018\t\u0013\r\u0005D&!A\u0005\u0002\u000e\r\u0004\"CBVY\u0005\u0005I\u0011QBW\u0011%\u0019I\u000fLA\u0001\n\u0013\u0019YOA\u0004UkBdW-M\u0019\u000b\u0003Q\nQa]2bY\u0006\u001c\u0001!\u0006\u00078\u0003.s\u0015\u000bV,[;\u0002\u001cgmE\u0003\u0001qqB7\u000e\u0005\u0002:u5\t1\'\u0003\u0002<g\t1\u0011I\\=SK\u001a\u0004R\"O\u001f@\u00156\u00036KV-]?\n,\u0017B\u0001 4\u0005%\u0001&o\u001c3vGR\f\u0014\u0007\u0005\u0002A\u00032\u0001AA\u0002\"\u0001\t\u000b\u00071I\u0001\u0002UcE\u0011Ai\u0012\t\u0003s\u0015K!AR\u001a\u0003\u000f9{G\u000f[5oOB\u0011\u0011\bS\u0005\u0003\u0013N\u00121!\u00118z!\t\u00015\n\u0002\u0004M\u0001\u0011\u0015\ra\u0011\u0002\u0003)J\u0002\"\u0001\u0011(\u0005\r=\u0003AQ1\u0001D\u0005\t!6\u0007\u0005\u0002A#\u00121!\u000b\u0001CC\u0002\r\u0013!\u0001\u0016\u001b\u0011\u0005\u0001#FAB+\u0001\t\u000b\u00071I\u0001\u0002UkA\u0011\u0001i\u0016\u0003\u00071\u0002!)\u0019A\"\u0003\u0005Q3\u0004C\u0001![\t\u0019Y\u0006\u0001\"b\u0001\u0007\n\u0011Ak\u000e\t\u0003\u0001v#aA\u0018\u0001\u0005\u0006\u0004\u0019%A\u0001+9!\t\u0001\u0005\r\u0002\u0004b\u0001\u0011\u0015\ra\u0011\u0002\u0003)f\u0002\"\u0001Q2\u0005\r\u0011\u0004AQ1\u0001D\u0005\r!\u0016\u0007\r\t\u0003\u0001\u001a$aa\u001a\u0001\u0005\u0006\u0004\u0019%a\u0001+2cA\u0011\u0011([\u0005\u0003UN\u0012q\u0001\u0015:pIV\u001cG\u000f\u0005\u0002mi:\u0011QN\u001d\b\u0003]Fl\u0011a\u001c\u0006\u0003aV\na\u0001\u0010:p_Rt\u0014\"\u0001\u001b\n\u0005M\u001c\u0014a\u00029bG.\fw-Z\u0005\u0003kZ\u0014AbU3sS\u0006d\u0017N_1cY\u0016T!a]\u001a\u0002\u0005}\u000bT#A \u0002\u0007}\u000b\u0004%\u0001\u0002`eU\t!*A\u0002`e\u0001\n!aX\u001a\u0016\u00035\u000b1aX\u001a!\u0003\tyF\'F\u0001Q\u0003\ryF\u0007I\u0001\u0003?V*\u0012aU\u0001\u0004?V\u0002\u0013AA07+\u00051\u0016aA07A\u0005\u0011qlN\u000b\u00023\u0006\u0019ql\u000e\u0011\u0002\u0005}CT#\u0001/\u0002\u0007}C\u0004%\u0001\u0002`sU\tq,A\u0002`s\u0001\n1aX\u00191+\u0005\u0011\u0017\u0001B02a\u0001\n1aX\u00192+\u0005)\u0017\u0001B02c\u0001\na\u0001P5oSRtD\u0003GA\u001b\u0003o\tI$a\u000f\u0002>\u0005}\u0012\u0011IA\"\u0003\u000b\n9%!\u0013\u0002LAi\u0011\bA K\u001bB\u001bf+\u0017/`E\u0016DQa^\fA\u0002}BQA_\fA\u0002)CQ!`\fA\u00025Ca!!\u0001\u0018\u0001\u0004\u0001\u0006BBA\u0004/\u0001\u00071\u000b\u0003\u0004\u0002\u000e]\u0001\rA\u0016\u0005\u0007\u0003\'9\u0002\u0019A-\t\r\u0005eq\u00031\u0001]\u0011\u0019\tyb\u0006a\u0001?\"1\u0011QE\fA\u0002\tDa!a\u000b\u0018\u0001\u0004)\u0017\u0001\u0003;p\'R\u0014\u0018N\\4\u0015\u0005\u0005E\u0003\u0003BA*\u00037rA!!\u0016\u0002XA\u0011anM\u0005\u0004\u00033\u001a\u0014A\u0002)sK\u0012,g-\u0003\u0003\u0002^\u0005}#AB*ue&twMC\u0002\u0002ZM\nAaY8qsVA\u0012QMA6\u0003_\n\u0019(a\u001e\u0002|\u0005}\u00141QAD\u0003\u0017\u000by)a%\u00151\u0005\u001d\u0014QSAL\u00033\u000bY*!(\u0002 \u0006\u0005\u00161UAS\u0003O\u000bI\u000b\u0005\r:\u0001\u0005%\u0014QNA9\u0003k\nI(! \u0002\u0002\u0006\u0015\u0015\u0011RAG\u0003#\u00032\u0001QA6\t\u0015\u0011\u0015D1\u0001D!\r\u0001\u0015q\u000e\u0003\u0006\u0019f\u0011\ra\u0011\t\u0004\u0001\u0006MD!B(\u001a\u0005\u0004\u0019\u0005c\u0001!\u0002x\u0011)!+\u0007b\u0001\u0007B\u0019\u0001)a\u001f\u0005\u000bUK\"\u0019A\"\u0011\u0007\u0001\u000by\bB\u0003Y3\t\u00071\tE\u0002A\u0003\u0007#QaW\rC\u0002\r\u00032\u0001QAD\t\u0015q\u0016D1\u0001D!\r\u0001\u00151\u0012\u0003\u0006Cf\u0011\ra\u0011\t\u0004\u0001\u0006=E!\u00023\u001a\u0005\u0004\u0019\u0005c\u0001!\u0002\u0014\u0012)q-\u0007b\u0001\u0007\"Aq/\u0007I\u0001\u0002\u0004\tI\u0007\u0003\u0005{3A\u0005\t\u0019AA7\u0011!i\u0018\u0004%AA\u0002\u0005E\u0004\"CA\u00013A\u0005\t\u0019AA;\u0011%\t9!\u0007I\u0001\u0002\u0004\tI\bC\u0005\u0002\u000ee\u0001\n\u00111\u0001\u0002~!I\u00111C\r\u0011\u0002\u0003\u0007\u0011\u0011\u0011\u0005\n\u00033I\u0002\u0013!a\u0001\u0003\u000bC\u0011\"a\b\u001a!\u0003\u0005\r!!#\t\u0013\u0005\u0015\u0012\u0004%AA\u0002\u00055\u0005\"CA\u00163A\u0005\t\u0019AAI\u00039\u0019w\u000e]=%I\u00164\u0017-\u001e7uIE*\u0002$a,\u0002F\u0006\u001d\u0017\u0011ZAf\u0003\u001b\fy-!5\u0002T\u0006U\u0017q[Am+\t\t\tLK\u0002@\u0003g[#!!.\u0011\t\u0005]\u0016\u0011Y\u0007\u0003\u0003sSA!a/\u0002>\u0006IQO\\2iK\u000e\\W\r\u001a\u0006\u0004\u0003\u007f\u001b\u0014AC1o]>$\u0018\r^5p]&!\u00111YA]\u0005E)hn\u00195fG.,GMV1sS\u0006t7-\u001a\u0003\u0006\u0005j\u0011\ra\u0011\u0003\u0006\u0019j\u0011\ra\u0011\u0003\u0006\u001fj\u0011\ra\u0011\u0003\u0006%j\u0011\ra\u0011\u0003\u0006+j\u0011\ra\u0011\u0003\u00061j\u0011\ra\u0011\u0003\u00067j\u0011\ra\u0011\u0003\u0006=j\u0011\ra\u0011\u0003\u0006Cj\u0011\ra\u0011\u0003\u0006Ij\u0011\ra\u0011\u0003\u0006Oj\u0011\raQ\u0001\u000fG>\u0004\u0018\u0010\n3fM\u0006,H\u000e\u001e\u00133+a\ty.a9\u0002f\u0006\u001d\u0018\u0011^Av\u0003[\fy/!=\u0002t\u0006U\u0018q_\u000b\u0003\u0003CT3ASAZ\t\u0015\u00115D1\u0001D\t\u0015a5D1\u0001D\t\u0015y5D1\u0001D\t\u0015\u00116D1\u0001D\t\u0015)6D1\u0001D\t\u0015A6D1\u0001D\t\u0015Y6D1\u0001D\t\u0015q6D1\u0001D\t\u0015\t7D1\u0001D\t\u0015!7D1\u0001D\t\u001597D1\u0001D\u00039\u0019w\u000e]=%I\u00164\u0017-\u001e7uIM*\u0002$!@\u0003\u0002\t\r!Q\u0001B\u0004\u0005\u0013\u0011YA!\u0004\u0003\u0010\tE!1\u0003B\u000b+\t\tyPK\u0002N\u0003g#QA\u0011\u000fC\u0002\r#Q\u0001\u0014\u000fC\u0002\r#Qa\u0014\u000fC\u0002\r#QA\u0015\u000fC\u0002\r#Q!\u0016\u000fC\u0002\r#Q\u0001\u0017\u000fC\u0002\r#Qa\u0017\u000fC\u0002\r#QA\u0018\u000fC\u0002\r#Q!\u0019\u000fC\u0002\r#Q\u0001\u001a\u000fC\u0002\r#Qa\u001a\u000fC\u0002\r\u000babY8qs\u0012\"WMZ1vYR$C\'\u0006\r\u0003\u001c\t}!\u0011\u0005B\u0012\u0005K\u00119C!\u000b\u0003,\t5\"q\u0006B\u0019\u0005g)\"A!\b+\u0007A\u000b\u0019\fB\u0003C;\t\u00071\tB\u0003M;\t\u00071\tB\u0003P;\t\u00071\tB\u0003S;\t\u00071\tB\u0003V;\t\u00071\tB\u0003Y;\t\u00071\tB\u0003\\;\t\u00071\tB\u0003_;\t\u00071\tB\u0003b;\t\u00071\tB\u0003e;\t\u00071\tB\u0003h;\t\u00071)\u0001\bd_BLH\u0005Z3gCVdG\u000fJ\u001b\u00161\te\"Q\bB \u0005\u0003\u0012\u0019E!\u0012\u0003H\t%#1\nB\'\u0005\u001f\u0012\t&\u0006\u0002\u0003<)\u001a1+a-\u0005\u000b\ts\"\u0019A\"\u0005\u000b1s\"\u0019A\"\u0005\u000b=s\"\u0019A\"\u0005\u000bIs\"\u0019A\"\u0005\u000bUs\"\u0019A\"\u0005\u000bas\"\u0019A\"\u0005\u000bms\"\u0019A\"\u0005\u000bys\"\u0019A\"\u0005\u000b\u0005t\"\u0019A\"\u0005\u000b\u0011t\"\u0019A\"\u0005\u000b\u001dt\"\u0019A\"\u0002\u001d\r|\u0007/\u001f\u0013eK\u001a\fW\u000f\u001c;%mUA\"q\u000bB.\u0005;\u0012yF!\u0019\u0003d\t\u0015$q\rB5\u0005W\u0012iGa\u001c\u0016\u0005\te#f\u0001,\u00024\u0012)!i\bb\u0001\u0007\u0012)Aj\bb\u0001\u0007\u0012)qj\bb\u0001\u0007\u0012)!k\bb\u0001\u0007\u0012)Qk\bb\u0001\u0007\u0012)\u0001l\bb\u0001\u0007\u0012)1l\bb\u0001\u0007\u0012)al\bb\u0001\u0007\u0012)\u0011m\bb\u0001\u0007\u0012)Am\bb\u0001\u0007\u0012)qm\bb\u0001\u0007\u0006q1m\u001c9zI\u0011,g-Y;mi\u0012:T\u0003\u0007B;\u0005s\u0012YH! \u0003\u0000\t\u0005%1\u0011BC\u0005\u000f\u0013IIa#\u0003\u000eV\u0011!q\u000f\u0016\u00043\u0006MF!\u0002\"!\u0005\u0004\u0019E!\u0002\'!\u0005\u0004\u0019E!B(!\u0005\u0004\u0019E!\u0002*!\u0005\u0004\u0019E!B+!\u0005\u0004\u0019E!\u0002-!\u0005\u0004\u0019E!B.!\u0005\u0004\u0019E!\u00020!\u0005\u0004\u0019E!B1!\u0005\u0004\u0019E!\u00023!\u0005\u0004\u0019E!B4!\u0005\u0004\u0019\u0015AD2paf$C-\u001a4bk2$H\u0005O\u000b\u0019\u0005\'\u00139J!\'\u0003\u001c\nu%q\u0014BQ\u0005G\u0013)Ka*\u0003*\n-VC\u0001BKU\ra\u00161\u0017\u0003\u0006\u0005\u0006\u0012\ra\u0011\u0003\u0006\u0019\u0006\u0012\ra\u0011\u0003\u0006\u001f\u0006\u0012\ra\u0011\u0003\u0006%\u0006\u0012\ra\u0011\u0003\u0006+\u0006\u0012\ra\u0011\u0003\u00061\u0006\u0012\ra\u0011\u0003\u00067\u0006\u0012\ra\u0011\u0003\u0006=\u0006\u0012\ra\u0011\u0003\u0006C\u0006\u0012\ra\u0011\u0003\u0006I\u0006\u0012\ra\u0011\u0003\u0006O\u0006\u0012\raQ\u0001\u000fG>\u0004\u0018\u0010\n3fM\u0006,H\u000e\u001e\u0013:+a\u0011\tL!.\u00038\ne&1\u0018B_\u0005\u007f\u0013\tMa1\u0003F\n\u001d\'\u0011Z\u000b\u0003\u0005gS3aXAZ\t\u0015\u0011%E1\u0001D\t\u0015a%E1\u0001D\t\u0015y%E1\u0001D\t\u0015\u0011&E1\u0001D\t\u0015)&E1\u0001D\t\u0015A&E1\u0001D\t\u0015Y&E1\u0001D\t\u0015q&E1\u0001D\t\u0015\t\'E1\u0001D\t\u0015!\'E1\u0001D\t\u00159\'E1\u0001D\u0003=\u0019w\u000e]=%I\u00164\u0017-\u001e7uIE\u0002T\u0003\u0007Bh\u0005\'\u0014)Na6\u0003Z\nm\'Q\u001cBp\u0005C\u0014\u0019O!:\u0003hV\u0011!\u0011\u001b\u0016\u0004E\u0006MF!\u0002\"$\u0005\u0004\u0019E!\u0002\'$\u0005\u0004\u0019E!B($\u0005\u0004\u0019E!\u0002*$\u0005\u0004\u0019E!B+$\u0005\u0004\u0019E!\u0002-$\u0005\u0004\u0019E!B.$\u0005\u0004\u0019E!\u00020$\u0005\u0004\u0019E!B1$\u0005\u0004\u0019E!\u00023$\u0005\u0004\u0019E!B4$\u0005\u0004\u0019\u0015aD2paf$C-\u001a4bk2$H%M\u0019\u00161\t5(\u0011\u001fBz\u0005k\u00149P!?\u0003|\nu(q`B\u0001\u0007\u0007\u0019)!\u0006\u0002\u0003p*\u001aQ-a-\u0005\u000b\t##\u0019A\"\u0005\u000b1##\u0019A\"\u0005\u000b=##\u0019A\"\u0005\u000bI##\u0019A\"\u0005\u000bU##\u0019A\"\u0005\u000ba##\u0019A\"\u0005\u000bm##\u0019A\"\u0005\u000by##\u0019A\"\u0005\u000b\u0005$#\u0019A\"\u0005\u000b\u0011$#\u0019A\"\u0005\u000b\u001d$#\u0019A\"\u0002\u001bA\u0014x\u000eZ;diB\u0013XMZ5y+\t\u0019Y\u0001\u0005\u0003\u0004\u000e\r]QBAB\b\u0015\u0011\u0019\tba\u0005\u0002\t1\fgn\u001a\u0006\u0003\u0007+\tAA[1wC&!\u0011QLB\b\u0003=\u0001(o\u001c3vGRLE/\u001a:bi>\u0014XCAB\u000f!\u0015\u0019yb!\nH\u001b\t\u0019\tCC\u0002\u0004$M\n!bY8mY\u0016\u001cG/[8o\u0013\u0011\u00199c!\t\u0003\u0011%#XM]1u_J\f\u0001bY1o\u000bF,\u0018\r\u001c\u000b\u0005\u0007[\u0019\u0019\u0004E\u0002:\u0007_I1a!\r4\u0005\u001d\u0011un\u001c7fC:D\u0001b!\u000e(\u0003\u0003\u0005\raR\u0001\u0004q\u0012\n\u0014A\u00059s_\u0012,8\r^#mK6,g\u000e\u001e(b[\u0016$Baa\u0003\u0004<!I1Q\u0007\u0015\u0002\u0002\u0003\u00071Q\b\t\u0004s\r}\u0012bAB!g\t\u0019\u0011J\u001c;\u0002\u0011!\f7\u000f[\"pI\u0016$\"a!\u0010\u0002\r\u0015\fX/\u00197t)\u0011\u0019ica\u0013\t\u0011\rU\"&!AA\u0002\u001d\u000bq\u0001V;qY\u0016\f\u0014\u0007\u0005\u0002:YM!A\u0006OB*!\u0011\u0019)fa\u0017\u000e\u0005\r]#\u0002BB-\u0007\'\t!![8\n\u0007U\u001c9\u0006\u0006\u0002\u0004PQ\u001111B\u0001\u0006CB\u0004H._\u000b\u0019\u0007K\u001aYga\u001c\u0004t\r]41PB@\u0007\u0007\u001b9ia#\u0004\u0010\u000eME\u0003GB4\u0007+\u001b9j!\'\u0004\u001c\u000eu5qTBQ\u0007G\u001b)ka*\u0004*BA\u0012\bAB5\u0007[\u001a\th!\u001e\u0004z\ru4\u0011QBC\u0007\u0013\u001bii!%\u0011\u0007\u0001\u001bY\u0007B\u0003C_\t\u00071\tE\u0002A\u0007_\"Q\u0001T\u0018C\u0002\r\u00032\u0001QB:\t\u0015yuF1\u0001D!\r\u00015q\u000f\u0003\u0006%>\u0012\ra\u0011\t\u0004\u0001\u000emD!B+0\u0005\u0004\u0019\u0005c\u0001!\u0004\u0000\u0011)\u0001l\fb\u0001\u0007B\u0019\u0001ia!\u0005\u000bm{#\u0019A\"\u0011\u0007\u0001\u001b9\tB\u0003__\t\u00071\tE\u0002A\u0007\u0017#Q!Y\u0018C\u0002\r\u00032\u0001QBH\t\u0015!wF1\u0001D!\r\u000151\u0013\u0003\u0006O>\u0012\ra\u0011\u0005\u0007o>\u0002\ra!\u001b\t\ri|\u0003\u0019AB7\u0011\u0019ix\u00061\u0001\u0004r!9\u0011\u0011A\u0018A\u0002\rU\u0004bBA\u0004_\u0001\u00071\u0011\u0010\u0005\b\u0003\u001by\u0003\u0019AB?\u0011\u001d\t\u0019b\fa\u0001\u0007\u0003Cq!!\u00070\u0001\u0004\u0019)\tC\u0004\u0002 =\u0002\ra!#\t\u000f\u0005\u0015r\u00061\u0001\u0004\u000e\"9\u00111F\u0018A\u0002\rE\u0015aB;oCB\u0004H._\u000b\u0019\u0007_\u001bYla0\u0004D\u000e\u001d71ZBh\u0007\'\u001c9na7\u0004`\u000e\rH\u0003BBY\u0007K\u0004R!OBZ\u0007oK1a!.4\u0005\u0019y\u0005\u000f^5p]BA\u0012\bAB]\u0007{\u001b\tm!2\u0004J\u000e57\u0011[Bk\u00073\u001cin!9\u0011\u0007\u0001\u001bY\fB\u0003Ca\t\u00071\tE\u0002A\u0007\u007f#Q\u0001\u0014\u0019C\u0002\r\u00032\u0001QBb\t\u0015y\u0005G1\u0001D!\r\u00015q\u0019\u0003\u0006%B\u0012\ra\u0011\t\u0004\u0001\u000e-G!B+1\u0005\u0004\u0019\u0005c\u0001!\u0004P\u0012)\u0001\f\rb\u0001\u0007B\u0019\u0001ia5\u0005\u000bm\u0003$\u0019A\"\u0011\u0007\u0001\u001b9\u000eB\u0003_a\t\u00071\tE\u0002A\u00077$Q!\u0019\u0019C\u0002\r\u00032\u0001QBp\t\u0015!\u0007G1\u0001D!\r\u000151\u001d\u0003\u0006OB\u0012\ra\u0011\u0005\n\u0007O\u0004\u0014\u0011!a\u0001\u0007o\u000b1\u0001\u001f\u00131\u000319(/\u001b;f%\u0016\u0004H.Y2f)\t\u0019i\u000f\u0005\u0003\u0004\u000e\r=\u0018\u0002BBy\u0007\u001f\u0011aa\u00142kK\u000e$\b
   #14 = Utf8               scala/runtime/ScalaRunTime$$anon$1
   #15 = Class              #14           // scala/runtime/ScalaRunTime$$anon$1
   #16 = Utf8               _1
   #17 = Utf8               Ljava/lang/Object;
   #18 = Utf8               TT1;
   #19 = Utf8               _2
   #20 = Utf8               TT2;
   #21 = Utf8               _3
   #22 = Utf8               TT3;
   #23 = Utf8               _4
   #24 = Utf8               TT4;
   #25 = Utf8               _5
   #26 = Utf8               TT5;
   #27 = Utf8               _6
   #28 = Utf8               TT6;
   #29 = Utf8               _7
   #30 = Utf8               TT7;
   #31 = Utf8               _8
   #32 = Utf8               TT8;
   #33 = Utf8               _9
   #34 = Utf8               TT9;
   #35 = Utf8               _10
   #36 = Utf8               TT10;
   #37 = Utf8               _11
   #38 = Utf8               TT11;
   #39 = Utf8               unapply
   #40 = Utf8               (Lscala/Tuple11;)Lscala/Option;
   #41 = Utf8               <T1:Ljava/lang/Object;T2:Ljava/lang/Object;T3:Ljava/lang/Object;T4:Ljava/lang/Object;T5:Ljava/lang/Object;T6:Ljava/lang/Object;T7:Ljava/lang/Object;T8:Ljava/lang/Object;T9:Ljava/lang/Object;T10:Ljava/lang/Object;T11:Ljava/lang/Object;>(Lscala/Tuple11<TT1;TT2;TT3;TT4;TT5;TT6;TT7;TT8;TT9;TT10;TT11;>;)Lscala/Option<Lscala/Tuple11<TT1;TT2;TT3;TT4;TT5;TT6;TT7;TT8;TT9;TT10;TT11;>;>;
   #42 = Utf8               x$0
   #43 = Utf8               scala/Tuple11$
   #44 = Class              #43           // scala/Tuple11$
   #45 = Utf8               MODULE$
   #46 = Utf8               Lscala/Tuple11$;
   #47 = NameAndType        #45:#46       // MODULE$:Lscala/Tuple11$;
   #48 = Fieldref           #44.#47       // scala/Tuple11$.MODULE$:Lscala/Tuple11$;
   #49 = NameAndType        #39:#40       // unapply:(Lscala/Tuple11;)Lscala/Option;
   #50 = Methodref          #44.#49       // scala/Tuple11$.unapply:(Lscala/Tuple11;)Lscala/Option;
   #51 = Utf8               Lscala/Tuple11;
   #52 = Utf8               apply
   #53 = Utf8               (Ljava/lang/Object;Ljava/lang/Object;Ljava/lang/Object;Ljava/lang/Object;Ljava/lang/Object;Ljava/lang/Object;Ljava/lang/Object;Ljava/lang/Object;Ljava/lang/Object;Ljava/lang/Object;Ljava/lang/Object;)Lscala/Tuple11;
   #54 = Utf8               <T1:Ljava/lang/Object;T2:Ljava/lang/Object;T3:Ljava/lang/Object;T4:Ljava/lang/Object;T5:Ljava/lang/Object;T6:Ljava/lang/Object;T7:Ljava/lang/Object;T8:Ljava/lang/Object;T9:Ljava/lang/Object;T10:Ljava/lang/Object;T11:Ljava/lang/Object;>(TT1;TT2;TT3;TT4;TT5;TT6;TT7;TT8;TT9;TT10;TT11;)Lscala/Tuple11<TT1;TT2;TT3;TT4;TT5;TT6;TT7;TT8;TT9;TT10;TT11;>;
   #55 = Utf8               <init>
   #56 = Utf8               (Ljava/lang/Object;Ljava/lang/Object;Ljava/lang/Object;Ljava/lang/Object;Ljava/lang/Object;Ljava/lang/Object;Ljava/lang/Object;Ljava/lang/Object;Ljava/lang/Object;Ljava/lang/Object;Ljava/lang/Object;)V
   #57 = NameAndType        #55:#56       // "<init>":(Ljava/lang/Object;Ljava/lang/Object;Ljava/lang/Object;Ljava/lang/Object;Ljava/lang/Object;Ljava/lang/Object;Ljava/lang/Object;Ljava/lang/Object;Ljava/lang/Object;Ljava/lang/Object;Ljava/lang/Object;)V
   #58 = Methodref          #2.#57        // scala/Tuple11."<init>":(Ljava/lang/Object;Ljava/lang/Object;Ljava/lang/Object;Ljava/lang/Object;Ljava/lang/Object;Ljava/lang/Object;Ljava/lang/Object;Ljava/lang/Object;Ljava/lang/Object;Ljava/lang/Object;Ljava/lang/Object;)V
   #59 = Utf8               productArity
   #60 = Utf8               ()I
   #61 = Utf8               productArity$
   #62 = Utf8               (Lscala/Product11;)I
   #63 = NameAndType        #61:#62       // productArity$:(Lscala/Product11;)I
   #64 = InterfaceMethodref #7.#63        // scala/Product11.productArity$:(Lscala/Product11;)I
   #65 = Utf8               this
   #66 = Utf8               productElement
   #67 = Utf8               (I)Ljava/lang/Object;
   #68 = Utf8               java/lang/IndexOutOfBoundsException
   #69 = Class              #68           // java/lang/IndexOutOfBoundsException
   #70 = Utf8               n
   #71 = Utf8               productElement$
   #72 = Utf8               (Lscala/Product11;I)Ljava/lang/Object;
   #73 = NameAndType        #71:#72       // productElement$:(Lscala/Product11;I)Ljava/lang/Object;
   #74 = InterfaceMethodref #7.#73        // scala/Product11.productElement$:(Lscala/Product11;I)Ljava/lang/Object;
   #75 = Utf8               I
   #76 = Utf8               productElementNames
   #77 = Utf8               ()Lscala/collection/Iterator;
   #78 = Utf8               ()Lscala/collection/Iterator<Ljava/lang/String;>;
   #79 = Utf8               scala/Product
   #80 = Class              #79           // scala/Product
   #81 = Utf8               productElementNames$
   #82 = Utf8               (Lscala/Product;)Lscala/collection/Iterator;
   #83 = NameAndType        #81:#82       // productElementNames$:(Lscala/Product;)Lscala/collection/Iterator;
   #84 = InterfaceMethodref #80.#83       // scala/Product.productElementNames$:(Lscala/Product;)Lscala/collection/Iterator;
   #85 = Utf8               ()Ljava/lang/Object;
   #86 = Utf8               ()TT1;
   #87 = NameAndType        #16:#17       // _1:Ljava/lang/Object;
   #88 = Fieldref           #2.#87        // scala/Tuple11._1:Ljava/lang/Object;
   #89 = Utf8               ()TT2;
   #90 = NameAndType        #19:#17       // _2:Ljava/lang/Object;
   #91 = Fieldref           #2.#90        // scala/Tuple11._2:Ljava/lang/Object;
   #92 = Utf8               ()TT3;
   #93 = NameAndType        #21:#17       // _3:Ljava/lang/Object;
   #94 = Fieldref           #2.#93        // scala/Tuple11._3:Ljava/lang/Object;
   #95 = Utf8               ()TT4;
   #96 = NameAndType        #23:#17       // _4:Ljava/lang/Object;
   #97 = Fieldref           #2.#96        // scala/Tuple11._4:Ljava/lang/Object;
   #98 = Utf8               ()TT5;
   #99 = NameAndType        #25:#17       // _5:Ljava/lang/Object;
  #100 = Fieldref           #2.#99        // scala/Tuple11._5:Ljava/lang/Object;
  #101 = Utf8               ()TT6;
  #102 = NameAndType        #27:#17       // _6:Ljava/lang/Object;
  #103 = Fieldref           #2.#102       // scala/Tuple11._6:Ljava/lang/Object;
  #104 = Utf8               ()TT7;
  #105 = NameAndType        #29:#17       // _7:Ljava/lang/Object;
  #106 = Fieldref           #2.#105       // scala/Tuple11._7:Ljava/lang/Object;
  #107 = Utf8               ()TT8;
  #108 = NameAndType        #31:#17       // _8:Ljava/lang/Object;
  #109 = Fieldref           #2.#108       // scala/Tuple11._8:Ljava/lang/Object;
  #110 = Utf8               ()TT9;
  #111 = NameAndType        #33:#17       // _9:Ljava/lang/Object;
  #112 = Fieldref           #2.#111       // scala/Tuple11._9:Ljava/lang/Object;
  #113 = Utf8               ()TT10;
  #114 = NameAndType        #35:#17       // _10:Ljava/lang/Object;
  #115 = Fieldref           #2.#114       // scala/Tuple11._10:Ljava/lang/Object;
  #116 = Utf8               ()TT11;
  #117 = NameAndType        #37:#17       // _11:Ljava/lang/Object;
  #118 = Fieldref           #2.#117       // scala/Tuple11._11:Ljava/lang/Object;
  #119 = Utf8               toString
  #120 = Utf8               ()Ljava/lang/String;
  #121 = Utf8               java/lang/StringBuilder
  #122 = Class              #121          // java/lang/StringBuilder
  #123 = Integer            12
  #124 = Utf8               (I)V
  #125 = NameAndType        #55:#124      // "<init>":(I)V
  #126 = Methodref          #122.#125     // java/lang/StringBuilder."<init>":(I)V
  #127 = Utf8               (
  #128 = String             #127          // (
  #129 = Utf8               append
  #130 = Utf8               (Ljava/lang/String;)Ljava/lang/StringBuilder;
  #131 = NameAndType        #129:#130     // append:(Ljava/lang/String;)Ljava/lang/StringBuilder;
  #132 = Methodref          #122.#131     // java/lang/StringBuilder.append:(Ljava/lang/String;)Ljava/lang/StringBuilder;
  #133 = NameAndType        #16:#85       // _1:()Ljava/lang/Object;
  #134 = Methodref          #2.#133       // scala/Tuple11._1:()Ljava/lang/Object;
  #135 = Utf8               (Ljava/lang/Object;)Ljava/lang/StringBuilder;
  #136 = NameAndType        #129:#135     // append:(Ljava/lang/Object;)Ljava/lang/StringBuilder;
  #137 = Methodref          #122.#136     // java/lang/StringBuilder.append:(Ljava/lang/Object;)Ljava/lang/StringBuilder;
  #138 = Utf8               ,
  #139 = String             #138          // ,
  #140 = NameAndType        #19:#85       // _2:()Ljava/lang/Object;
  #141 = Methodref          #2.#140       // scala/Tuple11._2:()Ljava/lang/Object;
  #142 = NameAndType        #21:#85       // _3:()Ljava/lang/Object;
  #143 = Methodref          #2.#142       // scala/Tuple11._3:()Ljava/lang/Object;
  #144 = NameAndType        #23:#85       // _4:()Ljava/lang/Object;
  #145 = Methodref          #2.#144       // scala/Tuple11._4:()Ljava/lang/Object;
  #146 = NameAndType        #25:#85       // _5:()Ljava/lang/Object;
  #147 = Methodref          #2.#146       // scala/Tuple11._5:()Ljava/lang/Object;
  #148 = NameAndType        #27:#85       // _6:()Ljava/lang/Object;
  #149 = Methodref          #2.#148       // scala/Tuple11._6:()Ljava/lang/Object;
  #150 = NameAndType        #29:#85       // _7:()Ljava/lang/Object;
  #151 = Methodref          #2.#150       // scala/Tuple11._7:()Ljava/lang/Object;
  #152 = NameAndType        #31:#85       // _8:()Ljava/lang/Object;
  #153 = Methodref          #2.#152       // scala/Tuple11._8:()Ljava/lang/Object;
  #154 = NameAndType        #33:#85       // _9:()Ljava/lang/Object;
  #155 = Methodref          #2.#154       // scala/Tuple11._9:()Ljava/lang/Object;
  #156 = NameAndType        #35:#85       // _10:()Ljava/lang/Object;
  #157 = Methodref          #2.#156       // scala/Tuple11._10:()Ljava/lang/Object;
  #158 = NameAndType        #37:#85       // _11:()Ljava/lang/Object;
  #159 = Methodref          #2.#158       // scala/Tuple11._11:()Ljava/lang/Object;
  #160 = Utf8               )
  #161 = String             #160          // )
  #162 = NameAndType        #119:#120     // toString:()Ljava/lang/String;
  #163 = Methodref          #122.#162     // java/lang/StringBuilder.toString:()Ljava/lang/String;
  #164 = Utf8               copy
  #165 = Utf8               copy$default$1
  #166 = Utf8               <T1:Ljava/lang/Object;T2:Ljava/lang/Object;T3:Ljava/lang/Object;T4:Ljava/lang/Object;T5:Ljava/lang/Object;T6:Ljava/lang/Object;T7:Ljava/lang/Object;T8:Ljava/lang/Object;T9:Ljava/lang/Object;T10:Ljava/lang/Object;T11:Ljava/lang/Object;>()TT1;
  #167 = Utf8               copy$default$10
  #168 = Utf8               <T1:Ljava/lang/Object;T2:Ljava/lang/Object;T3:Ljava/lang/Object;T4:Ljava/lang/Object;T5:Ljava/lang/Object;T6:Ljava/lang/Object;T7:Ljava/lang/Object;T8:Ljava/lang/Object;T9:Ljava/lang/Object;T10:Ljava/lang/Object;T11:Ljava/lang/Object;>()TT10;
  #169 = Utf8               copy$default$11
  #170 = Utf8               <T1:Ljava/lang/Object;T2:Ljava/lang/Object;T3:Ljava/lang/Object;T4:Ljava/lang/Object;T5:Ljava/lang/Object;T6:Ljava/lang/Object;T7:Ljava/lang/Object;T8:Ljava/lang/Object;T9:Ljava/lang/Object;T10:Ljava/lang/Object;T11:Ljava/lang/Object;>()TT11;
  #171 = Utf8               copy$default$2
  #172 = Utf8               <T1:Ljava/lang/Object;T2:Ljava/lang/Object;T3:Ljava/lang/Object;T4:Ljava/lang/Object;T5:Ljava/lang/Object;T6:Ljava/lang/Object;T7:Ljava/lang/Object;T8:Ljava/lang/Object;T9:Ljava/lang/Object;T10:Ljava/lang/Object;T11:Ljava/lang/Object;>()TT2;
  #173 = Utf8               copy$default$3
  #174 = Utf8               <T1:Ljava/lang/Object;T2:Ljava/lang/Object;T3:Ljava/lang/Object;T4:Ljava/lang/Object;T5:Ljava/lang/Object;T6:Ljava/lang/Object;T7:Ljava/lang/Object;T8:Ljava/lang/Object;T9:Ljava/lang/Object;T10:Ljava/lang/Object;T11:Ljava/lang/Object;>()TT3;
  #175 = Utf8               copy$default$4
  #176 = Utf8               <T1:Ljava/lang/Object;T2:Ljava/lang/Object;T3:Ljava/lang/Object;T4:Ljava/lang/Object;T5:Ljava/lang/Object;T6:Ljava/lang/Object;T7:Ljava/lang/Object;T8:Ljava/lang/Object;T9:Ljava/lang/Object;T10:Ljava/lang/Object;T11:Ljava/lang/Object;>()TT4;
  #177 = Utf8               copy$default$5
  #178 = Utf8               <T1:Ljava/lang/Object;T2:Ljava/lang/Object;T3:Ljava/lang/Object;T4:Ljava/lang/Object;T5:Ljava/lang/Object;T6:Ljava/lang/Object;T7:Ljava/lang/Object;T8:Ljava/lang/Object;T9:Ljava/lang/Object;T10:Ljava/lang/Object;T11:Ljava/lang/Object;>()TT5;
  #179 = Utf8               copy$default$6
  #180 = Utf8               <T1:Ljava/lang/Object;T2:Ljava/lang/Object;T3:Ljava/lang/Object;T4:Ljava/lang/Object;T5:Ljava/lang/Object;T6:Ljava/lang/Object;T7:Ljava/lang/Object;T8:Ljava/lang/Object;T9:Ljava/lang/Object;T10:Ljava/lang/Object;T11:Ljava/lang/Object;>()TT6;
  #181 = Utf8               copy$default$7
  #182 = Utf8               <T1:Ljava/lang/Object;T2:Ljava/lang/Object;T3:Ljava/lang/Object;T4:Ljava/lang/Object;T5:Ljava/lang/Object;T6:Ljava/lang/Object;T7:Ljava/lang/Object;T8:Ljava/lang/Object;T9:Ljava/lang/Object;T10:Ljava/lang/Object;T11:Ljava/lang/Object;>()TT7;
  #183 = Utf8               copy$default$8
  #184 = Utf8               <T1:Ljava/lang/Object;T2:Ljava/lang/Object;T3:Ljava/lang/Object;T4:Ljava/lang/Object;T5:Ljava/lang/Object;T6:Ljava/lang/Object;T7:Ljava/lang/Object;T8:Ljava/lang/Object;T9:Ljava/lang/Object;T10:Ljava/lang/Object;T11:Ljava/lang/Object;>()TT8;
  #185 = Utf8               copy$default$9
  #186 = Utf8               <T1:Ljava/lang/Object;T2:Ljava/lang/Object;T3:Ljava/lang/Object;T4:Ljava/lang/Object;T5:Ljava/lang/Object;T6:Ljava/lang/Object;T7:Ljava/lang/Object;T8:Ljava/lang/Object;T9:Ljava/lang/Object;T10:Ljava/lang/Object;T11:Ljava/lang/Object;>()TT9;
  #187 = Utf8               productPrefix
  #188 = Utf8               Tuple11
  #189 = String             #188          // Tuple11
  #190 = Utf8               productIterator
  #191 = Utf8               ()Lscala/collection/Iterator<Ljava/lang/Object;>;
  #192 = Utf8               (Lscala/Product;)V
  #193 = NameAndType        #55:#192      // "<init>":(Lscala/Product;)V
  #194 = Methodref          #15.#193      // scala/runtime/ScalaRunTime$$anon$1."<init>":(Lscala/Product;)V
  #195 = Utf8               canEqual
  #196 = Utf8               (Ljava/lang/Object;)Z
  #197 = Utf8               x$1
  #198 = Utf8               productElementName
  #199 = Utf8               (I)Ljava/lang/String;
  #200 = String             #16           // _1
  #201 = String             #19           // _2
  #202 = String             #21           // _3
  #203 = String             #23           // _4
  #204 = String             #25           // _5
  #205 = String             #27           // _6
  #206 = String             #29           // _7
  #207 = String             #31           // _8
  #208 = String             #33           // _9
  #209 = String             #35           // _10
  #210 = String             #37           // _11
  #211 = Utf8               scala/runtime/Statics
  #212 = Class              #211          // scala/runtime/Statics
  #213 = Utf8               ioobe
  #214 = NameAndType        #213:#67      // ioobe:(I)Ljava/lang/Object;
  #215 = Methodref          #212.#214     // scala/runtime/Statics.ioobe:(I)Ljava/lang/Object;
  #216 = Utf8               java/lang/String
  #217 = Class              #216          // java/lang/String
  #218 = Utf8               hashCode
  #219 = Utf8               scala/util/hashing/MurmurHash3$
  #220 = Class              #219          // scala/util/hashing/MurmurHash3$
  #221 = Utf8               Lscala/util/hashing/MurmurHash3$;
  #222 = NameAndType        #45:#221      // MODULE$:Lscala/util/hashing/MurmurHash3$;
  #223 = Fieldref           #220.#222     // scala/util/hashing/MurmurHash3$.MODULE$:Lscala/util/hashing/MurmurHash3$;
  #224 = Utf8               productHash
  #225 = Utf8               (Lscala/Product;)I
  #226 = NameAndType        #224:#225     // productHash:(Lscala/Product;)I
  #227 = Methodref          #220.#226     // scala/util/hashing/MurmurHash3$.productHash:(Lscala/Product;)I
  #228 = Utf8               equals
  #229 = Utf8               scala/runtime/BoxesRunTime
  #230 = Class              #229          // scala/runtime/BoxesRunTime
  #231 = Utf8               (Ljava/lang/Object;Ljava/lang/Object;)Z
  #232 = NameAndType        #228:#231     // equals:(Ljava/lang/Object;Ljava/lang/Object;)Z
  #233 = Methodref          #230.#232     // scala/runtime/BoxesRunTime.equals:(Ljava/lang/Object;Ljava/lang/Object;)Z
  #234 = Utf8               (TT1;TT2;TT3;TT4;TT5;TT6;TT7;TT8;TT9;TT10;TT11;)V
  #235 = Utf8               ()V
  #236 = NameAndType        #55:#235      // "<init>":()V
  #237 = Methodref          #5.#236       // java/lang/Object."<init>":()V
  #238 = Utf8               Signature
  #239 = Utf8               Code
  #240 = Utf8               LocalVariableTable
  #241 = Utf8               MethodParameters
  #242 = Utf8               LineNumberTable
  #243 = Utf8               Exceptions
  #244 = Utf8               StackMapTable
  #245 = Utf8               InnerClasses
  #246 = Utf8               SourceFile
  #247 = Utf8               RuntimeVisibleAnnotations
  #248 = Utf8               ScalaInlineInfo
  #249 = Utf8               ScalaSig
{
  private final T1 _1;
    descriptor: Ljava/lang/Object;
    flags: (0x0012) ACC_PRIVATE, ACC_FINAL
    Signature: #18                          // TT1;

  private final T2 _2;
    descriptor: Ljava/lang/Object;
    flags: (0x0012) ACC_PRIVATE, ACC_FINAL
    Signature: #20                          // TT2;

  private final T3 _3;
    descriptor: Ljava/lang/Object;
    flags: (0x0012) ACC_PRIVATE, ACC_FINAL
    Signature: #22                          // TT3;

  private final T4 _4;
    descriptor: Ljava/lang/Object;
    flags: (0x0012) ACC_PRIVATE, ACC_FINAL
    Signature: #24                          // TT4;

  private final T5 _5;
    descriptor: Ljava/lang/Object;
    flags: (0x0012) ACC_PRIVATE, ACC_FINAL
    Signature: #26                          // TT5;

  private final T6 _6;
    descriptor: Ljava/lang/Object;
    flags: (0x0012) ACC_PRIVATE, ACC_FINAL
    Signature: #28                          // TT6;

  private final T7 _7;
    descriptor: Ljava/lang/Object;
    flags: (0x0012) ACC_PRIVATE, ACC_FINAL
    Signature: #30                          // TT7;

  private final T8 _8;
    descriptor: Ljava/lang/Object;
    flags: (0x0012) ACC_PRIVATE, ACC_FINAL
    Signature: #32                          // TT8;

  private final T9 _9;
    descriptor: Ljava/lang/Object;
    flags: (0x0012) ACC_PRIVATE, ACC_FINAL
    Signature: #34                          // TT9;

  private final T10 _10;
    descriptor: Ljava/lang/Object;
    flags: (0x0012) ACC_PRIVATE, ACC_FINAL
    Signature: #36                          // TT10;

  private final T11 _11;
    descriptor: Ljava/lang/Object;
    flags: (0x0012) ACC_PRIVATE, ACC_FINAL
    Signature: #38                          // TT11;

  public static <T1 extends java.lang.Object, T2 extends java.lang.Object, T3 extends java.lang.Object, T4 extends java.lang.Object, T5 extends java.lang.Object, T6 extends java.lang.Object, T7 extends java.lang.Object, T8 extends java.lang.Object, T9 extends java.lang.Object, T10 extends java.lang.Object, T11 extends java.lang.Object> scala.Option<scala.Tuple11<T1, T2, T3, T4, T5, T6, T7, T8, T9, T10, T11>> unapply(scala.Tuple11<T1, T2, T3, T4, T5, T6, T7, T8, T9, T10, T11>);
    descriptor: (Lscala/Tuple11;)Lscala/Option;
    flags: (0x0009) ACC_PUBLIC, ACC_STATIC
    Code:
      stack=2, locals=1, args_size=1
         0: getstatic     #48                 // Field scala/Tuple11$.MODULE$:Lscala/Tuple11$;
         3: aload_0
         4: invokevirtual #50                 // Method scala/Tuple11$.unapply:(Lscala/Tuple11;)Lscala/Option;
         7: areturn
      LocalVariableTable:
        Start  Length  Slot  Name   Signature
            0       8     0   x$0   Lscala/Tuple11;
    Signature: #41                          // <T1:Ljava/lang/Object;T2:Ljava/lang/Object;T3:Ljava/lang/Object;T4:Ljava/lang/Object;T5:Ljava/lang/Object;T6:Ljava/lang/Object;T7:Ljava/lang/Object;T8:Ljava/lang/Object;T9:Ljava/lang/Object;T10:Ljava/lang/Object;T11:Ljava/lang/Object;>(Lscala/Tuple11<TT1;TT2;TT3;TT4;TT5;TT6;TT7;TT8;TT9;TT10;TT11;>;)Lscala/Option<Lscala/Tuple11<TT1;TT2;TT3;TT4;TT5;TT6;TT7;TT8;TT9;TT10;TT11;>;>;
    MethodParameters:
      Name                           Flags
      x$0                            final

  public static <T1 extends java.lang.Object, T2 extends java.lang.Object, T3 extends java.lang.Object, T4 extends java.lang.Object, T5 extends java.lang.Object, T6 extends java.lang.Object, T7 extends java.lang.Object, T8 extends java.lang.Object, T9 extends java.lang.Object, T10 extends java.lang.Object, T11 extends java.lang.Object> scala.Tuple11<T1, T2, T3, T4, T5, T6, T7, T8, T9, T10, T11> apply(T1, T2, T3, T4, T5, T6, T7, T8, T9, T10, T11);
    descriptor: (Ljava/lang/Object;Ljava/lang/Object;Ljava/lang/Object;Ljava/lang/Object;Ljava/lang/Object;Ljava/lang/Object;Ljava/lang/Object;Ljava/lang/Object;Ljava/lang/Object;Ljava/lang/Object;Ljava/lang/Object;)Lscala/Tuple11;
    flags: (0x0009) ACC_PUBLIC, ACC_STATIC
    Code:
      stack=13, locals=11, args_size=11
         0: getstatic     #48                 // Field scala/Tuple11$.MODULE$:Lscala/Tuple11$;
         3: pop
         4: new           #2                  // class scala/Tuple11
         7: dup
         8: aload_0
         9: aload_1
        10: aload_2
        11: aload_3
        12: aload         4
        14: aload         5
        16: aload         6
        18: aload         7
        20: aload         8
        22: aload         9
        24: aload         10
        26: invokespecial #58                 // Method "<init>":(Ljava/lang/Object;Ljava/lang/Object;Ljava/lang/Object;Ljava/lang/Object;Ljava/lang/Object;Ljava/lang/Object;Ljava/lang/Object;Ljava/lang/Object;Ljava/lang/Object;Ljava/lang/Object;Ljava/lang/Object;)V
        29: areturn
      LineNumberTable:
        line 33: 4
      LocalVariableTable:
        Start  Length  Slot  Name   Signature
            0      30     0    _1   Ljava/lang/Object;
            0      30     1    _2   Ljava/lang/Object;
            0      30     2    _3   Ljava/lang/Object;
            0      30     3    _4   Ljava/lang/Object;
            0      30     4    _5   Ljava/lang/Object;
            0      30     5    _6   Ljava/lang/Object;
            0      30     6    _7   Ljava/lang/Object;
            0      30     7    _8   Ljava/lang/Object;
            0      30     8    _9   Ljava/lang/Object;
            0      30     9   _10   Ljava/lang/Object;
            0      30    10   _11   Ljava/lang/Object;
    Signature: #54                          // <T1:Ljava/lang/Object;T2:Ljava/lang/Object;T3:Ljava/lang/Object;T4:Ljava/lang/Object;T5:Ljava/lang/Object;T6:Ljava/lang/Object;T7:Ljava/lang/Object;T8:Ljava/lang/Object;T9:Ljava/lang/Object;T10:Ljava/lang/Object;T11:Ljava/lang/Object;>(TT1;TT2;TT3;TT4;TT5;TT6;TT7;TT8;TT9;TT10;TT11;)Lscala/Tuple11<TT1;TT2;TT3;TT4;TT5;TT6;TT7;TT8;TT9;TT10;TT11;>;
    MethodParameters:
      Name                           Flags
      _1                             final
      _2                             final
      _3                             final
      _4                             final
      _5                             final
      _6                             final
      _7                             final
      _8                             final
      _9                             final
      _10                            final
      _11                            final

  public int productArity();
    descriptor: ()I
    flags: (0x0001) ACC_PUBLIC
    Code:
      stack=1, locals=1, args_size=1
         0: aload_0
         1: invokestatic  #64                 // InterfaceMethod scala/Product11.productArity$:(Lscala/Product11;)I
         4: ireturn
      LineNumberTable:
        line 33: 0
      LocalVariableTable:
        Start  Length  Slot  Name   Signature
            0       5     0  this   Lscala/Tuple11;

  public java.lang.Object productElement(int) throws java.lang.IndexOutOfBoundsException;
    descriptor: (I)Ljava/lang/Object;
    flags: (0x0001) ACC_PUBLIC
    Code:
      stack=2, locals=2, args_size=2
         0: aload_0
         1: iload_1
         2: invokestatic  #74                 // InterfaceMethod scala/Product11.productElement$:(Lscala/Product11;I)Ljava/lang/Object;
         5: areturn
      LineNumberTable:
        line 33: 0
      LocalVariableTable:
        Start  Length  Slot  Name   Signature
            0       6     0  this   Lscala/Tuple11;
            0       6     1     n   I
    Exceptions:
      throws java.lang.IndexOutOfBoundsException
    MethodParameters:
      Name                           Flags
      n                              final

  public scala.collection.Iterator<java.lang.String> productElementNames();
    descriptor: ()Lscala/collection/Iterator;
    flags: (0x0001) ACC_PUBLIC
    Code:
      stack=1, locals=1, args_size=1
         0: aload_0
         1: invokestatic  #84                 // InterfaceMethod scala/Product.productElementNames$:(Lscala/Product;)Lscala/collection/Iterator;
         4: areturn
      LineNumberTable:
        line 33: 0
      LocalVariableTable:
        Start  Length  Slot  Name   Signature
            0       5     0  this   Lscala/Tuple11;
    Signature: #78                          // ()Lscala/collection/Iterator<Ljava/lang/String;>;

  public T1 _1();
    descriptor: ()Ljava/lang/Object;
    flags: (0x0001) ACC_PUBLIC
    Code:
      stack=1, locals=1, args_size=1
         0: aload_0
         1: getfield      #88                 // Field _1:Ljava/lang/Object;
         4: areturn
      LineNumberTable:
        line 33: 0
      LocalVariableTable:
        Start  Length  Slot  Name   Signature
            0       5     0  this   Lscala/Tuple11;
    Signature: #86                          // ()TT1;

  public T2 _2();
    descriptor: ()Ljava/lang/Object;
    flags: (0x0001) ACC_PUBLIC
    Code:
      stack=1, locals=1, args_size=1
         0: aload_0
         1: getfield      #91                 // Field _2:Ljava/lang/Object;
         4: areturn
      LineNumberTable:
        line 33: 0
      LocalVariableTable:
        Start  Length  Slot  Name   Signature
            0       5     0  this   Lscala/Tuple11;
    Signature: #89                          // ()TT2;

  public T3 _3();
    descriptor: ()Ljava/lang/Object;
    flags: (0x0001) ACC_PUBLIC
    Code:
      stack=1, locals=1, args_size=1
         0: aload_0
         1: getfield      #94                 // Field _3:Ljava/lang/Object;
         4: areturn
      LineNumberTable:
        line 33: 0
      LocalVariableTable:
        Start  Length  Slot  Name   Signature
            0       5     0  this   Lscala/Tuple11;
    Signature: #92                          // ()TT3;

  public T4 _4();
    descriptor: ()Ljava/lang/Object;
    flags: (0x0001) ACC_PUBLIC
    Code:
      stack=1, locals=1, args_size=1
         0: aload_0
         1: getfield      #97                 // Field _4:Ljava/lang/Object;
         4: areturn
      LineNumberTable:
        line 33: 0
      LocalVariableTable:
        Start  Length  Slot  Name   Signature
            0       5     0  this   Lscala/Tuple11;
    Signature: #95                          // ()TT4;

  public T5 _5();
    descriptor: ()Ljava/lang/Object;
    flags: (0x0001) ACC_PUBLIC
    Code:
      stack=1, locals=1, args_size=1
         0: aload_0
         1: getfield      #100                // Field _5:Ljava/lang/Object;
         4: areturn
      LineNumberTable:
        line 33: 0
      LocalVariableTable:
        Start  Length  Slot  Name   Signature
            0       5     0  this   Lscala/Tuple11;
    Signature: #98                          // ()TT5;

  public T6 _6();
    descriptor: ()Ljava/lang/Object;
    flags: (0x0001) ACC_PUBLIC
    Code:
      stack=1, locals=1, args_size=1
         0: aload_0
         1: getfield      #103                // Field _6:Ljava/lang/Object;
         4: areturn
      LineNumberTable:
        line 33: 0
      LocalVariableTable:
        Start  Length  Slot  Name   Signature
            0       5     0  this   Lscala/Tuple11;
    Signature: #101                         // ()TT6;

  public T7 _7();
    descriptor: ()Ljava/lang/Object;
    flags: (0x0001) ACC_PUBLIC
    Code:
      stack=1, locals=1, args_size=1
         0: aload_0
         1: getfield      #106                // Field _7:Ljava/lang/Object;
         4: areturn
      LineNumberTable:
        line 33: 0
      LocalVariableTable:
        Start  Length  Slot  Name   Signature
            0       5     0  this   Lscala/Tuple11;
    Signature: #104                         // ()TT7;

  public T8 _8();
    descriptor: ()Ljava/lang/Object;
    flags: (0x0001) ACC_PUBLIC
    Code:
      stack=1, locals=1, args_size=1
         0: aload_0
         1: getfield      #109                // Field _8:Ljava/lang/Object;
         4: areturn
      LineNumberTable:
        line 33: 0
      LocalVariableTable:
        Start  Length  Slot  Name   Signature
            0       5     0  this   Lscala/Tuple11;
    Signature: #107                         // ()TT8;

  public T9 _9();
    descriptor: ()Ljava/lang/Object;
    flags: (0x0001) ACC_PUBLIC
    Code:
      stack=1, locals=1, args_size=1
         0: aload_0
         1: getfield      #112                // Field _9:Ljava/lang/Object;
         4: areturn
      LineNumberTable:
        line 33: 0
      LocalVariableTable:
        Start  Length  Slot  Name   Signature
            0       5     0  this   Lscala/Tuple11;
    Signature: #110                         // ()TT9;

  public T10 _10();
    descriptor: ()Ljava/lang/Object;
    flags: (0x0001) ACC_PUBLIC
    Code:
      stack=1, locals=1, args_size=1
         0: aload_0
         1: getfield      #115                // Field _10:Ljava/lang/Object;
         4: areturn
      LineNumberTable:
        line 33: 0
      LocalVariableTable:
        Start  Length  Slot  Name   Signature
            0       5     0  this   Lscala/Tuple11;
    Signature: #113                         // ()TT10;

  public T11 _11();
    descriptor: ()Ljava/lang/Object;
    flags: (0x0001) ACC_PUBLIC
    Code:
      stack=1, locals=1, args_size=1
         0: aload_0
         1: getfield      #118                // Field _11:Ljava/lang/Object;
         4: areturn
      LineNumberTable:
        line 33: 0
      LocalVariableTable:
        Start  Length  Slot  Name   Signature
            0       5     0  this   Lscala/Tuple11;
    Signature: #116                         // ()TT11;

  public java.lang.String toString();
    descriptor: ()Ljava/lang/String;
    flags: (0x0001) ACC_PUBLIC
    Code:
      stack=3, locals=1, args_size=1
         0: new           #122                // class java/lang/StringBuilder
         3: dup
         4: ldc           #123                // int 12
         6: invokespecial #126                // Method java/lang/StringBuilder."<init>":(I)V
         9: ldc           #128                // String (
        11: invokevirtual #132                // Method java/lang/StringBuilder.append:(Ljava/lang/String;)Ljava/lang/StringBuilder;
        14: aload_0
        15: invokevirtual #134                // Method _1:()Ljava/lang/Object;
        18: invokevirtual #137                // Method java/lang/StringBuilder.append:(Ljava/lang/Object;)Ljava/lang/StringBuilder;
        21: ldc           #139                // String ,
        23: invokevirtual #132                // Method java/lang/StringBuilder.append:(Ljava/lang/String;)Ljava/lang/StringBuilder;
        26: aload_0
        27: invokevirtual #141                // Method _2:()Ljava/lang/Object;
        30: invokevirtual #137                // Method java/lang/StringBuilder.append:(Ljava/lang/Object;)Ljava/lang/StringBuilder;
        33: ldc           #139                // String ,
        35: invokevirtual #132                // Method java/lang/StringBuilder.append:(Ljava/lang/String;)Ljava/lang/StringBuilder;
        38: aload_0
        39: invokevirtual #143                // Method _3:()Ljava/lang/Object;
        42: invokevirtual #137                // Method java/lang/StringBuilder.append:(Ljava/lang/Object;)Ljava/lang/StringBuilder;
        45: ldc           #139                // String ,
        47: invokevirtual #132                // Method java/lang/StringBuilder.append:(Ljava/lang/String;)Ljava/lang/StringBuilder;
        50: aload_0
        51: invokevirtual #145                // Method _4:()Ljava/lang/Object;
        54: invokevirtual #137                // Method java/lang/StringBuilder.append:(Ljava/lang/Object;)Ljava/lang/StringBuilder;
        57: ldc           #139                // String ,
        59: invokevirtual #132                // Method java/lang/StringBuilder.append:(Ljava/lang/String;)Ljava/lang/StringBuilder;
        62: aload_0
        63: invokevirtual #147                // Method _5:()Ljava/lang/Object;
        66: invokevirtual #137                // Method java/lang/StringBuilder.append:(Ljava/lang/Object;)Ljava/lang/StringBuilder;
        69: ldc           #139                // String ,
        71: invokevirtual #132                // Method java/lang/StringBuilder.append:(Ljava/lang/String;)Ljava/lang/StringBuilder;
        74: aload_0
        75: invokevirtual #149                // Method _6:()Ljava/lang/Object;
        78: invokevirtual #137                // Method java/lang/StringBuilder.append:(Ljava/lang/Object;)Ljava/lang/StringBuilder;
        81: ldc           #139                // String ,
        83: invokevirtual #132                // Method java/lang/StringBuilder.append:(Ljava/lang/String;)Ljava/lang/StringBuilder;
        86: aload_0
        87: invokevirtual #151                // Method _7:()Ljava/lang/Object;
        90: invokevirtual #137                // Method java/lang/StringBuilder.append:(Ljava/lang/Object;)Ljava/lang/StringBuilder;
        93: ldc           #139                // String ,
        95: invokevirtual #132                // Method java/lang/StringBuilder.append:(Ljava/lang/String;)Ljava/lang/StringBuilder;
        98: aload_0
        99: invokevirtual #153                // Method _8:()Ljava/lang/Object;
       102: invokevirtual #137                // Method java/lang/StringBuilder.append:(Ljava/lang/Object;)Ljava/lang/StringBuilder;
       105: ldc           #139                // String ,
       107: invokevirtual #132                // Method java/lang/StringBuilder.append:(Ljava/lang/String;)Ljava/lang/StringBuilder;
       110: aload_0
       111: invokevirtual #155                // Method _9:()Ljava/lang/Object;
       114: invokevirtual #137                // Method java/lang/StringBuilder.append:(Ljava/lang/Object;)Ljava/lang/StringBuilder;
       117: ldc           #139                // String ,
       119: invokevirtual #132                // Method java/lang/StringBuilder.append:(Ljava/lang/String;)Ljava/lang/StringBuilder;
       122: aload_0
       123: invokevirtual #157                // Method _10:()Ljava/lang/Object;
       126: invokevirtual #137                // Method java/lang/StringBuilder.append:(Ljava/lang/Object;)Ljava/lang/StringBuilder;
       129: ldc           #139                // String ,
       131: invokevirtual #132                // Method java/lang/StringBuilder.append:(Ljava/lang/String;)Ljava/lang/StringBuilder;
       134: aload_0
       135: invokevirtual #159                // Method _11:()Ljava/lang/Object;
       138: invokevirtual #137                // Method java/lang/StringBuilder.append:(Ljava/lang/Object;)Ljava/lang/StringBuilder;
       141: ldc           #161                // String )
       143: invokevirtual #132                // Method java/lang/StringBuilder.append:(Ljava/lang/String;)Ljava/lang/StringBuilder;
       146: invokevirtual #163                // Method java/lang/StringBuilder.toString:()Ljava/lang/String;
       149: areturn
      LineNumberTable:
        line 36: 0
      LocalVariableTable:
        Start  Length  Slot  Name   Signature
            0     150     0  this   Lscala/Tuple11;

  public <T1 extends java.lang.Object, T2 extends java.lang.Object, T3 extends java.lang.Object, T4 extends java.lang.Object, T5 extends java.lang.Object, T6 extends java.lang.Object, T7 extends java.lang.Object, T8 extends java.lang.Object, T9 extends java.lang.Object, T10 extends java.lang.Object, T11 extends java.lang.Object> scala.Tuple11<T1, T2, T3, T4, T5, T6, T7, T8, T9, T10, T11> copy(T1, T2, T3, T4, T5, T6, T7, T8, T9, T10, T11);
    descriptor: (Ljava/lang/Object;Ljava/lang/Object;Ljava/lang/Object;Ljava/lang/Object;Ljava/lang/Object;Ljava/lang/Object;Ljava/lang/Object;Ljava/lang/Object;Ljava/lang/Object;Ljava/lang/Object;Ljava/lang/Object;)Lscala/Tuple11;
    flags: (0x0001) ACC_PUBLIC
    Code:
      stack=13, locals=12, args_size=12
         0: new           #2                  // class scala/Tuple11
         3: dup
         4: aload_1
         5: aload_2
         6: aload_3
         7: aload         4
         9: aload         5
        11: aload         6
        13: aload         7
        15: aload         8
        17: aload         9
        19: aload         10
        21: aload         11
        23: invokespecial #58                 // Method "<init>":(Ljava/lang/Object;Ljava/lang/Object;Ljava/lang/Object;Ljava/lang/Object;Ljava/lang/Object;Ljava/lang/Object;Ljava/lang/Object;Ljava/lang/Object;Ljava/lang/Object;Ljava/lang/Object;Ljava/lang/Object;)V
        26: areturn
      LineNumberTable:
        line 33: 0
      LocalVariableTable:
        Start  Length  Slot  Name   Signature
            0      27     0  this   Lscala/Tuple11;
            0      27     1    _1   Ljava/lang/Object;
            0      27     2    _2   Ljava/lang/Object;
            0      27     3    _3   Ljava/lang/Object;
            0      27     4    _4   Ljava/lang/Object;
            0      27     5    _5   Ljava/lang/Object;
            0      27     6    _6   Ljava/lang/Object;
            0      27     7    _7   Ljava/lang/Object;
            0      27     8    _8   Ljava/lang/Object;
            0      27     9    _9   Ljava/lang/Object;
            0      27    10   _10   Ljava/lang/Object;
            0      27    11   _11   Ljava/lang/Object;
    Signature: #54                          // <T1:Ljava/lang/Object;T2:Ljava/lang/Object;T3:Ljava/lang/Object;T4:Ljava/lang/Object;T5:Ljava/lang/Object;T6:Ljava/lang/Object;T7:Ljava/lang/Object;T8:Ljava/lang/Object;T9:Ljava/lang/Object;T10:Ljava/lang/Object;T11:Ljava/lang/Object;>(TT1;TT2;TT3;TT4;TT5;TT6;TT7;TT8;TT9;TT10;TT11;)Lscala/Tuple11<TT1;TT2;TT3;TT4;TT5;TT6;TT7;TT8;TT9;TT10;TT11;>;
    MethodParameters:
      Name                           Flags
      _1                             final
      _2                             final
      _3                             final
      _4                             final
      _5                             final
      _6                             final
      _7                             final
      _8                             final
      _9                             final
      _10                            final
      _11                            final

  public <T1 extends java.lang.Object, T2 extends java.lang.Object, T3 extends java.lang.Object, T4 extends java.lang.Object, T5 extends java.lang.Object, T6 extends java.lang.Object, T7 extends java.lang.Object, T8 extends java.lang.Object, T9 extends java.lang.Object, T10 extends java.lang.Object, T11 extends java.lang.Object> T1 copy$default$1();
    descriptor: ()Ljava/lang/Object;
    flags: (0x0001) ACC_PUBLIC
    Code:
      stack=1, locals=1, args_size=1
         0: aload_0
         1: invokevirtual #134                // Method _1:()Ljava/lang/Object;
         4: areturn
      LineNumberTable:
        line 33: 0
      LocalVariableTable:
        Start  Length  Slot  Name   Signature
            0       5     0  this   Lscala/Tuple11;
    Signature: #166                         // <T1:Ljava/lang/Object;T2:Ljava/lang/Object;T3:Ljava/lang/Object;T4:Ljava/lang/Object;T5:Ljava/lang/Object;T6:Ljava/lang/Object;T7:Ljava/lang/Object;T8:Ljava/lang/Object;T9:Ljava/lang/Object;T10:Ljava/lang/Object;T11:Ljava/lang/Object;>()TT1;

  public <T1 extends java.lang.Object, T2 extends java.lang.Object, T3 extends java.lang.Object, T4 extends java.lang.Object, T5 extends java.lang.Object, T6 extends java.lang.Object, T7 extends java.lang.Object, T8 extends java.lang.Object, T9 extends java.lang.Object, T10 extends java.lang.Object, T11 extends java.lang.Object> T10 copy$default$10();
    descriptor: ()Ljava/lang/Object;
    flags: (0x0001) ACC_PUBLIC
    Code:
      stack=1, locals=1, args_size=1
         0: aload_0
         1: invokevirtual #157                // Method _10:()Ljava/lang/Object;
         4: areturn
      LineNumberTable:
        line 33: 0
      LocalVariableTable:
        Start  Length  Slot  Name   Signature
            0       5     0  this   Lscala/Tuple11;
    Signature: #168                         // <T1:Ljava/lang/Object;T2:Ljava/lang/Object;T3:Ljava/lang/Object;T4:Ljava/lang/Object;T5:Ljava/lang/Object;T6:Ljava/lang/Object;T7:Ljava/lang/Object;T8:Ljava/lang/Object;T9:Ljava/lang/Object;T10:Ljava/lang/Object;T11:Ljava/lang/Object;>()TT10;

  public <T1 extends java.lang.Object, T2 extends java.lang.Object, T3 extends java.lang.Object, T4 extends java.lang.Object, T5 extends java.lang.Object, T6 extends java.lang.Object, T7 extends java.lang.Object, T8 extends java.lang.Object, T9 extends java.lang.Object, T10 extends java.lang.Object, T11 extends java.lang.Object> T11 copy$default$11();
    descriptor: ()Ljava/lang/Object;
    flags: (0x0001) ACC_PUBLIC
    Code:
      stack=1, locals=1, args_size=1
         0: aload_0
         1: invokevirtual #159                // Method _11:()Ljava/lang/Object;
         4: areturn
      LineNumberTable:
        line 33: 0
      LocalVariableTable:
        Start  Length  Slot  Name   Signature
            0       5     0  this   Lscala/Tuple11;
    Signature: #170                         // <T1:Ljava/lang/Object;T2:Ljava/lang/Object;T3:Ljava/lang/Object;T4:Ljava/lang/Object;T5:Ljava/lang/Object;T6:Ljava/lang/Object;T7:Ljava/lang/Object;T8:Ljava/lang/Object;T9:Ljava/lang/Object;T10:Ljava/lang/Object;T11:Ljava/lang/Object;>()TT11;

  public <T1 extends java.lang.Object, T2 extends java.lang.Object, T3 extends java.lang.Object, T4 extends java.lang.Object, T5 extends java.lang.Object, T6 extends java.lang.Object, T7 extends java.lang.Object, T8 extends java.lang.Object, T9 extends java.lang.Object, T10 extends java.lang.Object, T11 extends java.lang.Object> T2 copy$default$2();
    descriptor: ()Ljava/lang/Object;
    flags: (0x0001) ACC_PUBLIC
    Code:
      stack=1, locals=1, args_size=1
         0: aload_0
         1: invokevirtual #141                // Method _2:()Ljava/lang/Object;
         4: areturn
      LineNumberTable:
        line 33: 0
      LocalVariableTable:
        Start  Length  Slot  Name   Signature
            0       5     0  this   Lscala/Tuple11;
    Signature: #172                         // <T1:Ljava/lang/Object;T2:Ljava/lang/Object;T3:Ljava/lang/Object;T4:Ljava/lang/Object;T5:Ljava/lang/Object;T6:Ljava/lang/Object;T7:Ljava/lang/Object;T8:Ljava/lang/Object;T9:Ljava/lang/Object;T10:Ljava/lang/Object;T11:Ljava/lang/Object;>()TT2;

  public <T1 extends java.lang.Object, T2 extends java.lang.Object, T3 extends java.lang.Object, T4 extends java.lang.Object, T5 extends java.lang.Object, T6 extends java.lang.Object, T7 extends java.lang.Object, T8 extends java.lang.Object, T9 extends java.lang.Object, T10 extends java.lang.Object, T11 extends java.lang.Object> T3 copy$default$3();
    descriptor: ()Ljava/lang/Object;
    flags: (0x0001) ACC_PUBLIC
    Code:
      stack=1, locals=1, args_size=1
         0: aload_0
         1: invokevirtual #143                // Method _3:()Ljava/lang/Object;
         4: areturn
      LineNumberTable:
        line 33: 0
      LocalVariableTable:
        Start  Length  Slot  Name   Signature
            0       5     0  this   Lscala/Tuple11;
    Signature: #174                         // <T1:Ljava/lang/Object;T2:Ljava/lang/Object;T3:Ljava/lang/Object;T4:Ljava/lang/Object;T5:Ljava/lang/Object;T6:Ljava/lang/Object;T7:Ljava/lang/Object;T8:Ljava/lang/Object;T9:Ljava/lang/Object;T10:Ljava/lang/Object;T11:Ljava/lang/Object;>()TT3;

  public <T1 extends java.lang.Object, T2 extends java.lang.Object, T3 extends java.lang.Object, T4 extends java.lang.Object, T5 extends java.lang.Object, T6 extends java.lang.Object, T7 extends java.lang.Object, T8 extends java.lang.Object, T9 extends java.lang.Object, T10 extends java.lang.Object, T11 extends java.lang.Object> T4 copy$default$4();
    descriptor: ()Ljava/lang/Object;
    flags: (0x0001) ACC_PUBLIC
    Code:
      stack=1, locals=1, args_size=1
         0: aload_0
         1: invokevirtual #145                // Method _4:()Ljava/lang/Object;
         4: areturn
      LineNumberTable:
        line 33: 0
      LocalVariableTable:
        Start  Length  Slot  Name   Signature
            0       5     0  this   Lscala/Tuple11;
    Signature: #176                         // <T1:Ljava/lang/Object;T2:Ljava/lang/Object;T3:Ljava/lang/Object;T4:Ljava/lang/Object;T5:Ljava/lang/Object;T6:Ljava/lang/Object;T7:Ljava/lang/Object;T8:Ljava/lang/Object;T9:Ljava/lang/Object;T10:Ljava/lang/Object;T11:Ljava/lang/Object;>()TT4;

  public <T1 extends java.lang.Object, T2 extends java.lang.Object, T3 extends java.lang.Object, T4 extends java.lang.Object, T5 extends java.lang.Object, T6 extends java.lang.Object, T7 extends java.lang.Object, T8 extends java.lang.Object, T9 extends java.lang.Object, T10 extends java.lang.Object, T11 extends java.lang.Object> T5 copy$default$5();
    descriptor: ()Ljava/lang/Object;
    flags: (0x0001) ACC_PUBLIC
    Code:
      stack=1, locals=1, args_size=1
         0: aload_0
         1: invokevirtual #147                // Method _5:()Ljava/lang/Object;
         4: areturn
      LineNumberTable:
        line 33: 0
      LocalVariableTable:
        Start  Length  Slot  Name   Signature
            0       5     0  this   Lscala/Tuple11;
    Signature: #178                         // <T1:Ljava/lang/Object;T2:Ljava/lang/Object;T3:Ljava/lang/Object;T4:Ljava/lang/Object;T5:Ljava/lang/Object;T6:Ljava/lang/Object;T7:Ljava/lang/Object;T8:Ljava/lang/Object;T9:Ljava/lang/Object;T10:Ljava/lang/Object;T11:Ljava/lang/Object;>()TT5;

  public <T1 extends java.lang.Object, T2 extends java.lang.Object, T3 extends java.lang.Object, T4 extends java.lang.Object, T5 extends java.lang.Object, T6 extends java.lang.Object, T7 extends java.lang.Object, T8 extends java.lang.Object, T9 extends java.lang.Object, T10 extends java.lang.Object, T11 extends java.lang.Object> T6 copy$default$6();
    descriptor: ()Ljava/lang/Object;
    flags: (0x0001) ACC_PUBLIC
    Code:
      stack=1, locals=1, args_size=1
         0: aload_0
         1: invokevirtual #149                // Method _6:()Ljava/lang/Object;
         4: areturn
      LineNumberTable:
        line 33: 0
      LocalVariableTable:
        Start  Length  Slot  Name   Signature
            0       5     0  this   Lscala/Tuple11;
    Signature: #180                         // <T1:Ljava/lang/Object;T2:Ljava/lang/Object;T3:Ljava/lang/Object;T4:Ljava/lang/Object;T5:Ljava/lang/Object;T6:Ljava/lang/Object;T7:Ljava/lang/Object;T8:Ljava/lang/Object;T9:Ljava/lang/Object;T10:Ljava/lang/Object;T11:Ljava/lang/Object;>()TT6;

  public <T1 extends java.lang.Object, T2 extends java.lang.Object, T3 extends java.lang.Object, T4 extends java.lang.Object, T5 extends java.lang.Object, T6 extends java.lang.Object, T7 extends java.lang.Object, T8 extends java.lang.Object, T9 extends java.lang.Object, T10 extends java.lang.Object, T11 extends java.lang.Object> T7 copy$default$7();
    descriptor: ()Ljava/lang/Object;
    flags: (0x0001) ACC_PUBLIC
    Code:
      stack=1, locals=1, args_size=1
         0: aload_0
         1: invokevirtual #151                // Method _7:()Ljava/lang/Object;
         4: areturn
      LineNumberTable:
        line 33: 0
      LocalVariableTable:
        Start  Length  Slot  Name   Signature
            0       5     0  this   Lscala/Tuple11;
    Signature: #182                         // <T1:Ljava/lang/Object;T2:Ljava/lang/Object;T3:Ljava/lang/Object;T4:Ljava/lang/Object;T5:Ljava/lang/Object;T6:Ljava/lang/Object;T7:Ljava/lang/Object;T8:Ljava/lang/Object;T9:Ljava/lang/Object;T10:Ljava/lang/Object;T11:Ljava/lang/Object;>()TT7;

  public <T1 extends java.lang.Object, T2 extends java.lang.Object, T3 extends java.lang.Object, T4 extends java.lang.Object, T5 extends java.lang.Object, T6 extends java.lang.Object, T7 extends java.lang.Object, T8 extends java.lang.Object, T9 extends java.lang.Object, T10 extends java.lang.Object, T11 extends java.lang.Object> T8 copy$default$8();
    descriptor: ()Ljava/lang/Object;
    flags: (0x0001) ACC_PUBLIC
    Code:
      stack=1, locals=1, args_size=1
         0: aload_0
         1: invokevirtual #153                // Method _8:()Ljava/lang/Object;
         4: areturn
      LineNumberTable:
        line 33: 0
      LocalVariableTable:
        Start  Length  Slot  Name   Signature
            0       5     0  this   Lscala/Tuple11;
    Signature: #184                         // <T1:Ljava/lang/Object;T2:Ljava/lang/Object;T3:Ljava/lang/Object;T4:Ljava/lang/Object;T5:Ljava/lang/Object;T6:Ljava/lang/Object;T7:Ljava/lang/Object;T8:Ljava/lang/Object;T9:Ljava/lang/Object;T10:Ljava/lang/Object;T11:Ljava/lang/Object;>()TT8;

  public <T1 extends java.lang.Object, T2 extends java.lang.Object, T3 extends java.lang.Object, T4 extends java.lang.Object, T5 extends java.lang.Object, T6 extends java.lang.Object, T7 extends java.lang.Object, T8 extends java.lang.Object, T9 extends java.lang.Object, T10 extends java.lang.Object, T11 extends java.lang.Object> T9 copy$default$9();
    descriptor: ()Ljava/lang/Object;
    flags: (0x0001) ACC_PUBLIC
    Code:
      stack=1, locals=1, args_size=1
         0: aload_0
         1: invokevirtual #155                // Method _9:()Ljava/lang/Object;
         4: areturn
      LineNumberTable:
        line 33: 0
      LocalVariableTable:
        Start  Length  Slot  Name   Signature
            0       5     0  this   Lscala/Tuple11;
    Signature: #186                         // <T1:Ljava/lang/Object;T2:Ljava/lang/Object;T3:Ljava/lang/Object;T4:Ljava/lang/Object;T5:Ljava/lang/Object;T6:Ljava/lang/Object;T7:Ljava/lang/Object;T8:Ljava/lang/Object;T9:Ljava/lang/Object;T10:Ljava/lang/Object;T11:Ljava/lang/Object;>()TT9;

  public java.lang.String productPrefix();
    descriptor: ()Ljava/lang/String;
    flags: (0x0001) ACC_PUBLIC
    Code:
      stack=1, locals=1, args_size=1
         0: ldc           #189                // String Tuple11
         2: areturn
      LineNumberTable:
        line 33: 0
      LocalVariableTable:
        Start  Length  Slot  Name   Signature
            0       3     0  this   Lscala/Tuple11;

  public scala.collection.Iterator<java.lang.Object> productIterator();
    descriptor: ()Lscala/collection/Iterator;
    flags: (0x0001) ACC_PUBLIC
    Code:
      stack=3, locals=1, args_size=1
         0: new           #15                 // class scala/runtime/ScalaRunTime$$anon$1
         3: dup
         4: aload_0
         5: invokespecial #194                // Method scala/runtime/ScalaRunTime$$anon$1."<init>":(Lscala/Product;)V
         8: areturn
      LineNumberTable:
        line 33: 0
      LocalVariableTable:
        Start  Length  Slot  Name   Signature
            0       9     0  this   Lscala/Tuple11;
    Signature: #191                         // ()Lscala/collection/Iterator<Ljava/lang/Object;>;

  public boolean canEqual(java.lang.Object);
    descriptor: (Ljava/lang/Object;)Z
    flags: (0x0001) ACC_PUBLIC
    Code:
      stack=1, locals=2, args_size=2
         0: aload_1
         1: instanceof    #2                  // class scala/Tuple11
         4: ireturn
      LineNumberTable:
        line 33: 0
      LocalVariableTable:
        Start  Length  Slot  Name   Signature
            0       5     0  this   Lscala/Tuple11;
            0       5     1   x$1   Ljava/lang/Object;
    MethodParameters:
      Name                           Flags
      x$1                            final

  public java.lang.String productElementName(int);
    descriptor: (I)Ljava/lang/String;
    flags: (0x0001) ACC_PUBLIC
    Code:
      stack=1, locals=2, args_size=2
         0: iload_1
         1: tableswitch   { // 0 to 10
                       0: 60
                       1: 63
                       2: 66
                       3: 69
                       4: 72
                       5: 75
                       6: 78
                       7: 81
                       8: 84
                       9: 87
                      10: 90
                 default: 93
            }
        60: ldc           #200                // String _1
        62: areturn
        63: ldc           #201                // String _2
        65: areturn
        66: ldc           #202                // String _3
        68: areturn
        69: ldc           #203                // String _4
        71: areturn
        72: ldc           #204                // String _5
        74: areturn
        75: ldc           #205                // String _6
        77: areturn
        78: ldc           #206                // String _7
        80: areturn
        81: ldc           #207                // String _8
        83: areturn
        84: ldc           #208                // String _9
        86: areturn
        87: ldc           #209                // String _10
        89: areturn
        90: ldc           #210                // String _11
        92: areturn
        93: iload_1
        94: invokestatic  #215                // Method scala/runtime/Statics.ioobe:(I)Ljava/lang/Object;
        97: checkcast     #217                // class java/lang/String
       100: areturn
      StackMapTable: number_of_entries = 12
        frame_type = 60 /* same */
        frame_type = 2 /* same */
        frame_type = 2 /* same */
        frame_type = 2 /* same */
        frame_type = 2 /* same */
        frame_type = 2 /* same */
        frame_type = 2 /* same */
        frame_type = 2 /* same */
        frame_type = 2 /* same */
        frame_type = 2 /* same */
        frame_type = 2 /* same */
        frame_type = 2 /* same */
      LineNumberTable:
        line 33: 0
      LocalVariableTable:
        Start  Length  Slot  Name   Signature
            0     101     0  this   Lscala/Tuple11;
            0     101     1   x$1   I
    MethodParameters:
      Name                           Flags
      x$1                            final

  public int hashCode();
    descriptor: ()I
    flags: (0x0001) ACC_PUBLIC
    Code:
      stack=2, locals=1, args_size=1
         0: getstatic     #223                // Field scala/util/hashing/MurmurHash3$.MODULE$:Lscala/util/hashing/MurmurHash3$;
         3: aload_0
         4: invokevirtual #227                // Method scala/util/hashing/MurmurHash3$.productHash:(Lscala/Product;)I
         7: ireturn
      LineNumberTable:
        line 33: 0
      LocalVariableTable:
        Start  Length  Slot  Name   Signature
            0       8     0  this   Lscala/Tuple11;

  public boolean equals(java.lang.Object);
    descriptor: (Ljava/lang/Object;)Z
    flags: (0x0001) ACC_PUBLIC
    Code:
      stack=2, locals=4, args_size=2
         0: aload_0
         1: aload_1
         2: if_acmpeq     190
         5: aload_1
         6: instanceof    #2                  // class scala/Tuple11
         9: ifeq          17
        12: iconst_1
        13: istore_2
        14: goto          19
        17: iconst_0
        18: istore_2
        19: iload_2
        20: ifeq          192
        23: aload_1
        24: checkcast     #2                  // class scala/Tuple11
        27: astore_3
        28: aload_0
        29: invokevirtual #134                // Method _1:()Ljava/lang/Object;
        32: aload_3
        33: invokevirtual #134                // Method _1:()Ljava/lang/Object;
        36: invokestatic  #233                // Method scala/runtime/BoxesRunTime.equals:(Ljava/lang/Object;Ljava/lang/Object;)Z
        39: ifeq          186
        42: aload_0
        43: invokevirtual #141                // Method _2:()Ljava/lang/Object;
        46: aload_3
        47: invokevirtual #141                // Method _2:()Ljava/lang/Object;
        50: invokestatic  #233                // Method scala/runtime/BoxesRunTime.equals:(Ljava/lang/Object;Ljava/lang/Object;)Z
        53: ifeq          186
        56: aload_0
        57: invokevirtual #143                // Method _3:()Ljava/lang/Object;
        60: aload_3
        61: invokevirtual #143                // Method _3:()Ljava/lang/Object;
        64: invokestatic  #233                // Method scala/runtime/BoxesRunTime.equals:(Ljava/lang/Object;Ljava/lang/Object;)Z
        67: ifeq          186
        70: aload_0
        71: invokevirtual #145                // Method _4:()Ljava/lang/Object;
        74: aload_3
        75: invokevirtual #145                // Method _4:()Ljava/lang/Object;
        78: invokestatic  #233                // Method scala/runtime/BoxesRunTime.equals:(Ljava/lang/Object;Ljava/lang/Object;)Z
        81: ifeq          186
        84: aload_0
        85: invokevirtual #147                // Method _5:()Ljava/lang/Object;
        88: aload_3
        89: invokevirtual #147                // Method _5:()Ljava/lang/Object;
        92: invokestatic  #233                // Method scala/runtime/BoxesRunTime.equals:(Ljava/lang/Object;Ljava/lang/Object;)Z
        95: ifeq          186
        98: aload_0
        99: invokevirtual #149                // Method _6:()Ljava/lang/Object;
       102: aload_3
       103: invokevirtual #149                // Method _6:()Ljava/lang/Object;
       106: invokestatic  #233                // Method scala/runtime/BoxesRunTime.equals:(Ljava/lang/Object;Ljava/lang/Object;)Z
       109: ifeq          186
       112: aload_0
       113: invokevirtual #151                // Method _7:()Ljava/lang/Object;
       116: aload_3
       117: invokevirtual #151                // Method _7:()Ljava/lang/Object;
       120: invokestatic  #233                // Method scala/runtime/BoxesRunTime.equals:(Ljava/lang/Object;Ljava/lang/Object;)Z
       123: ifeq          186
       126: aload_0
       127: invokevirtual #153                // Method _8:()Ljava/lang/Object;
       130: aload_3
       131: invokevirtual #153                // Method _8:()Ljava/lang/Object;
       134: invokestatic  #233                // Method scala/runtime/BoxesRunTime.equals:(Ljava/lang/Object;Ljava/lang/Object;)Z
       137: ifeq          186
       140: aload_0
       141: invokevirtual #155                // Method _9:()Ljava/lang/Object;
       144: aload_3
       145: invokevirtual #155                // Method _9:()Ljava/lang/Object;
       148: invokestatic  #233                // Method scala/runtime/BoxesRunTime.equals:(Ljava/lang/Object;Ljava/lang/Object;)Z
       151: ifeq          186
       154: aload_0
       155: invokevirtual #157                // Method _10:()Ljava/lang/Object;
       158: aload_3
       159: invokevirtual #157                // Method _10:()Ljava/lang/Object;
       162: invokestatic  #233                // Method scala/runtime/BoxesRunTime.equals:(Ljava/lang/Object;Ljava/lang/Object;)Z
       165: ifeq          186
       168: aload_0
       169: invokevirtual #159                // Method _11:()Ljava/lang/Object;
       172: aload_3
       173: invokevirtual #159                // Method _11:()Ljava/lang/Object;
       176: invokestatic  #233                // Method scala/runtime/BoxesRunTime.equals:(Ljava/lang/Object;Ljava/lang/Object;)Z
       179: ifeq          186
       182: iconst_1
       183: goto          187
       186: iconst_0
       187: ifeq          192
       190: iconst_1
       191: ireturn
       192: iconst_0
       193: ireturn
      StackMapTable: number_of_entries = 6
        frame_type = 17 /* same */
        frame_type = 252 /* append */
          offset_delta = 1
          locals = [ int ]
        frame_type = 252 /* append */
          offset_delta = 166
          locals = [ class scala/Tuple11 ]
        frame_type = 64 /* same_locals_1_stack_item */
          stack = [ int ]
        frame_type = 249 /* chop */
          offset_delta = 2
        frame_type = 252 /* append */
          offset_delta = 1
          locals = [ int ]
      LineNumberTable:
        line 33: 0
      LocalVariableTable:
        Start  Length  Slot  Name   Signature
            0     194     0  this   Lscala/Tuple11;
            0     194     1   x$1   Ljava/lang/Object;
    MethodParameters:
      Name                           Flags
      x$1                            final

  public scala.Tuple11(T1, T2, T3, T4, T5, T6, T7, T8, T9, T10, T11);
    descriptor: (Ljava/lang/Object;Ljava/lang/Object;Ljava/lang/Object;Ljava/lang/Object;Ljava/lang/Object;Ljava/lang/Object;Ljava/lang/Object;Ljava/lang/Object;Ljava/lang/Object;Ljava/lang/Object;Ljava/lang/Object;)V
    flags: (0x0001) ACC_PUBLIC
    Code:
      stack=2, locals=12, args_size=12
         0: aload_0
         1: aload_1
         2: putfield      #88                 // Field _1:Ljava/lang/Object;
         5: aload_0
         6: aload_2
         7: putfield      #91                 // Field _2:Ljava/lang/Object;
        10: aload_0
        11: aload_3
        12: putfield      #94                 // Field _3:Ljava/lang/Object;
        15: aload_0
        16: aload         4
        18: putfield      #97                 // Field _4:Ljava/lang/Object;
        21: aload_0
        22: aload         5
        24: putfield      #100                // Field _5:Ljava/lang/Object;
        27: aload_0
        28: aload         6
        30: putfield      #103                // Field _6:Ljava/lang/Object;
        33: aload_0
        34: aload         7
        36: putfield      #106                // Field _7:Ljava/lang/Object;
        39: aload_0
        40: aload         8
        42: putfield      #109                // Field _8:Ljava/lang/Object;
        45: aload_0
        46: aload         9
        48: putfield      #112                // Field _9:Ljava/lang/Object;
        51: aload_0
        52: aload         10
        54: putfield      #115                // Field _10:Ljava/lang/Object;
        57: aload_0
        58: aload         11
        60: putfield      #118                // Field _11:Ljava/lang/Object;
        63: aload_0
        64: invokespecial #237                // Method java/lang/Object."<init>":()V
        67: return
      LineNumberTable:
        line 33: 0
        line 34: 63
      LocalVariableTable:
        Start  Length  Slot  Name   Signature
            0      68     0  this   Lscala/Tuple11;
            0      68     1    _1   Ljava/lang/Object;
            0      68     2    _2   Ljava/lang/Object;
            0      68     3    _3   Ljava/lang/Object;
            0      68     4    _4   Ljava/lang/Object;
            0      68     5    _5   Ljava/lang/Object;
            0      68     6    _6   Ljava/lang/Object;
            0      68     7    _7   Ljava/lang/Object;
            0      68     8    _8   Ljava/lang/Object;
            0      68     9    _9   Ljava/lang/Object;
            0      68    10   _10   Ljava/lang/Object;
            0      68    11   _11   Ljava/lang/Object;
    Signature: #234                         // (TT1;TT2;TT3;TT4;TT5;TT6;TT7;TT8;TT9;TT10;TT11;)V
    MethodParameters:
      Name                           Flags
      _1                             final
      _2                             final
      _3                             final
      _4                             final
      _5                             final
      _6                             final
      _7                             final
      _8                             final
      _9                             final
      _10                            final
      _11                            final
}
InnerClasses:
  public final #15;                       // class scala/runtime/ScalaRunTime$$anon$1
Signature: #3                           // <T1:Ljava/lang/Object;T2:Ljava/lang/Object;T3:Ljava/lang/Object;T4:Ljava/lang/Object;T5:Ljava/lang/Object;T6:Ljava/lang/Object;T7:Ljava/lang/Object;T8:Ljava/lang/Object;T9:Ljava/lang/Object;T10:Ljava/lang/Object;T11:Ljava/lang/Object;>Ljava/lang/Object;Lscala/Product11<TT1;TT2;TT3;TT4;TT5;TT6;TT7;TT8;TT9;TT10;TT11;>;Ljava/io/Serializable;
SourceFile: "Tuple11.scala"
RuntimeVisibleAnnotations:
  0: #11(#12=s#13)
    scala.reflect.ScalaSignature(
      bytes="\u0006\u0005\rMh\u0001\u0002\u001a4\u0005ZB\u0001b\u001e\u0001\u0003\u0016\u0004%\t\u0001\u001f\u0005\ts\u0002\u0011\t\u0012)A\u0005\u007f!A!\u0010\u0001BK\u0002\u0013\u00051\u0010\u0003\u0005}\u0001\tE\t\u0015!\u0003K\u0011!i\bA!f\u0001\n\u0003q\b\u0002C@\u0001\u0005#\u0005\u000b\u0011B\'\t\u0015\u0005\u0005\u0001A!f\u0001\n\u0003\t\u0019\u0001C\u0005\u0002\u0006\u0001\u0011\t\u0012)A\u0005!\"Q\u0011q\u0001\u0001\u0003\u0016\u0004%\t!!\u0003\t\u0013\u0005-\u0001A!E!\u0002\u0013\u0019\u0006BCA\u0007\u0001\tU\r\u0011\"\u0001\u0002\u0010!I\u0011\u0011\u0003\u0001\u0003\u0012\u0003\u0006IA\u0016\u0005\u000b\u0003\'\u0001!Q3A\u0005\u0002\u0005U\u0001\"CA\f\u0001\tE\t\u0015!\u0003Z\u0011)\tI\u0002\u0001BK\u0002\u0013\u0005\u00111\u0004\u0005\n\u0003;\u0001!\u0011#Q\u0001\nqC!\"a\b\u0001\u0005+\u0007I\u0011AA\u0011\u0011%\t\u0019\u0003\u0001B\tB\u0003%q\f\u0003\u0006\u0002&\u0001\u0011)\u001a!C\u0001\u0003OA\u0011\"!\u000b\u0001\u0005#\u0005\u000b\u0011\u00022\t\u0015\u0005-\u0002A!f\u0001\n\u0003\ti\u0003C\u0005\u00020\u0001\u0011\t\u0012)A\u0005K\"9\u0011\u0011\u0007\u0001\u0005\u0002\u0005M\u0002bBA\'\u0001\u0011\u0005\u0013q\n\u0005\n\u0003C\u0002\u0011\u0011!C\u0001\u0003GB\u0011\"a+\u0001#\u0003%\t!!,\t\u0013\u0005m\u0007!%A\u0005\u0002\u0005u\u0007\"CA}\u0001E\u0005I\u0011AA~\u0011%\u00119\u0002AI\u0001\n\u0003\u0011I\u0002C\u0005\u00036\u0001\t\n\u0011\"\u0001\u00038!I!1\u000b\u0001\u0012\u0002\u0013\u0005!Q\u000b\u0005\n\u0005c\u0002\u0011\u0013!C\u0001\u0005gB\u0011Ba$\u0001#\u0003%\tA!%\t\u0013\t5\u0006!%A\u0005\u0002\t=\u0006\"\u0003Bf\u0001E\u0005I\u0011\u0001Bg\u0011%\u0011I\u000fAI\u0001\n\u0003\u0011Y\u000fC\u0005\u0004\b\u0001\t\t\u0011\"\u0011\u0004\n!I1\u0011\u0004\u0001\u0002\u0002\u0013\u000531\u0004\u0005\n\u0007S\u0001\u0011\u0011!C\u0001\u0007WA\u0011ba\u000e\u0001\u0003\u0003%\te!\u000f\t\u0013\r\r\u0003!!A\u0005B\r\u0015\u0003\"CB$\u0001\u0005\u0005I\u0011IB%\u000f%\u0019ieMA\u0001\u0012\u0003\u0019yE\u0002\u00053g\u0005\u0005\t\u0012AB)\u0011\u001d\t\t\u0004\fC\u0001\u0007;B\u0011\"!\u0014-\u0003\u0003%)ea\u0018\t\u0013\r\u0005D&!A\u0005\u0002\u000e\r\u0004\"CBVY\u0005\u0005I\u0011QBW\u0011%\u0019I\u000fLA\u0001\n\u0013\u0019YOA\u0004UkBdW-M\u0019\u000b\u0003Q\nQa]2bY\u0006\u001c\u0001!\u0006\u00078\u0003.s\u0015\u000bV,[;\u0002\u001cgmE\u0003\u0001qqB7\u000e\u0005\u0002:u5\t1\'\u0003\u0002<g\t1\u0011I\\=SK\u001a\u0004R\"O\u001f@\u00156\u00036KV-]?\n,\u0017B\u0001 4\u0005%\u0001&o\u001c3vGR\f\u0014\u0007\u0005\u0002A\u00032\u0001AA\u0002\"\u0001\t\u000b\u00071I\u0001\u0002UcE\u0011Ai\u0012\t\u0003s\u0015K!AR\u001a\u0003\u000f9{G\u000f[5oOB\u0011\u0011\bS\u0005\u0003\u0013N\u00121!\u00118z!\t\u00015\n\u0002\u0004M\u0001\u0011\u0015\ra\u0011\u0002\u0003)J\u0002\"\u0001\u0011(\u0005\r=\u0003AQ1\u0001D\u0005\t!6\u0007\u0005\u0002A#\u00121!\u000b\u0001CC\u0002\r\u0013!\u0001\u0016\u001b\u0011\u0005\u0001#FAB+\u0001\t\u000b\u00071I\u0001\u0002UkA\u0011\u0001i\u0016\u0003\u00071\u0002!)\u0019A\"\u0003\u0005Q3\u0004C\u0001![\t\u0019Y\u0006\u0001\"b\u0001\u0007\n\u0011Ak\u000e\t\u0003\u0001v#aA\u0018\u0001\u0005\u0006\u0004\u0019%A\u0001+9!\t\u0001\u0005\r\u0002\u0004b\u0001\u0011\u0015\ra\u0011\u0002\u0003)f\u0002\"\u0001Q2\u0005\r\u0011\u0004AQ1\u0001D\u0005\r!\u0016\u0007\r\t\u0003\u0001\u001a$aa\u001a\u0001\u0005\u0006\u0004\u0019%a\u0001+2cA\u0011\u0011([\u0005\u0003UN\u0012q\u0001\u0015:pIV\u001cG\u000f\u0005\u0002mi:\u0011QN\u001d\b\u0003]Fl\u0011a\u001c\u0006\u0003aV\na\u0001\u0010:p_Rt\u0014\"\u0001\u001b\n\u0005M\u001c\u0014a\u00029bG.\fw-Z\u0005\u0003kZ\u0014AbU3sS\u0006d\u0017N_1cY\u0016T!a]\u001a\u0002\u0005}\u000bT#A \u0002\u0007}\u000b\u0004%\u0001\u0002`eU\t!*A\u0002`e\u0001\n!aX\u001a\u0016\u00035\u000b1aX\u001a!\u0003\tyF\'F\u0001Q\u0003\ryF\u0007I\u0001\u0003?V*\u0012aU\u0001\u0004?V\u0002\u0013AA07+\u00051\u0016aA07A\u0005\u0011qlN\u000b\u00023\u0006\u0019ql\u000e\u0011\u0002\u0005}CT#\u0001/\u0002\u0007}C\u0004%\u0001\u0002`sU\tq,A\u0002`s\u0001\n1aX\u00191+\u0005\u0011\u0017\u0001B02a\u0001\n1aX\u00192+\u0005)\u0017\u0001B02c\u0001\na\u0001P5oSRtD\u0003GA\u001b\u0003o\tI$a\u000f\u0002>\u0005}\u0012\u0011IA\"\u0003\u000b\n9%!\u0013\u0002LAi\u0011\bA K\u001bB\u001bf+\u0017/`E\u0016DQa^\fA\u0002}BQA_\fA\u0002)CQ!`\fA\u00025Ca!!\u0001\u0018\u0001\u0004\u0001\u0006BBA\u0004/\u0001\u00071\u000b\u0003\u0004\u0002\u000e]\u0001\rA\u0016\u0005\u0007\u0003\'9\u0002\u0019A-\t\r\u0005eq\u00031\u0001]\u0011\u0019\tyb\u0006a\u0001?\"1\u0011QE\fA\u0002\tDa!a\u000b\u0018\u0001\u0004)\u0017\u0001\u0003;p\'R\u0014\u0018N\\4\u0015\u0005\u0005E\u0003\u0003BA*\u00037rA!!\u0016\u0002XA\u0011anM\u0005\u0004\u00033\u001a\u0014A\u0002)sK\u0012,g-\u0003\u0003\u0002^\u0005}#AB*ue&twMC\u0002\u0002ZM\nAaY8qsVA\u0012QMA6\u0003_\n\u0019(a\u001e\u0002|\u0005}\u00141QAD\u0003\u0017\u000by)a%\u00151\u0005\u001d\u0014QSAL\u00033\u000bY*!(\u0002 \u0006\u0005\u00161UAS\u0003O\u000bI\u000b\u0005\r:\u0001\u0005%\u0014QNA9\u0003k\nI(! \u0002\u0002\u0006\u0015\u0015\u0011RAG\u0003#\u00032\u0001QA6\t\u0015\u0011\u0015D1\u0001D!\r\u0001\u0015q\u000e\u0003\u0006\u0019f\u0011\ra\u0011\t\u0004\u0001\u0006MD!B(\u001a\u0005\u0004\u0019\u0005c\u0001!\u0002x\u0011)!+\u0007b\u0001\u0007B\u0019\u0001)a\u001f\u0005\u000bUK\"\u0019A\"\u0011\u0007\u0001\u000by\bB\u0003Y3\t\u00071\tE\u0002A\u0003\u0007#QaW\rC\u0002\r\u00032\u0001QAD\t\u0015q\u0016D1\u0001D!\r\u0001\u00151\u0012\u0003\u0006Cf\u0011\ra\u0011\t\u0004\u0001\u0006=E!\u00023\u001a\u0005\u0004\u0019\u0005c\u0001!\u0002\u0014\u0012)q-\u0007b\u0001\u0007\"Aq/\u0007I\u0001\u0002\u0004\tI\u0007\u0003\u0005{3A\u0005\t\u0019AA7\u0011!i\u0018\u0004%AA\u0002\u0005E\u0004\"CA\u00013A\u0005\t\u0019AA;\u0011%\t9!\u0007I\u0001\u0002\u0004\tI\bC\u0005\u0002\u000ee\u0001\n\u00111\u0001\u0002~!I\u00111C\r\u0011\u0002\u0003\u0007\u0011\u0011\u0011\u0005\n\u00033I\u0002\u0013!a\u0001\u0003\u000bC\u0011\"a\b\u001a!\u0003\u0005\r!!#\t\u0013\u0005\u0015\u0012\u0004%AA\u0002\u00055\u0005\"CA\u00163A\u0005\t\u0019AAI\u00039\u0019w\u000e]=%I\u00164\u0017-\u001e7uIE*\u0002$a,\u0002F\u0006\u001d\u0017\u0011ZAf\u0003\u001b\fy-!5\u0002T\u0006U\u0017q[Am+\t\t\tLK\u0002@\u0003g[#!!.\u0011\t\u0005]\u0016\u0011Y\u0007\u0003\u0003sSA!a/\u0002>\u0006IQO\\2iK\u000e\\W\r\u001a\u0006\u0004\u0003\u007f\u001b\u0014AC1o]>$\u0018\r^5p]&!\u00111YA]\u0005E)hn\u00195fG.,GMV1sS\u0006t7-\u001a\u0003\u0006\u0005j\u0011\ra\u0011\u0003\u0006\u0019j\u0011\ra\u0011\u0003\u0006\u001fj\u0011\ra\u0011\u0003\u0006%j\u0011\ra\u0011\u0003\u0006+j\u0011\ra\u0011\u0003\u00061j\u0011\ra\u0011\u0003\u00067j\u0011\ra\u0011\u0003\u0006=j\u0011\ra\u0011\u0003\u0006Cj\u0011\ra\u0011\u0003\u0006Ij\u0011\ra\u0011\u0003\u0006Oj\u0011\raQ\u0001\u000fG>\u0004\u0018\u0010\n3fM\u0006,H\u000e\u001e\u00133+a\ty.a9\u0002f\u0006\u001d\u0018\u0011^Av\u0003[\fy/!=\u0002t\u0006U\u0018q_\u000b\u0003\u0003CT3ASAZ\t\u0015\u00115D1\u0001D\t\u0015a5D1\u0001D\t\u0015y5D1\u0001D\t\u0015\u00116D1\u0001D\t\u0015)6D1\u0001D\t\u0015A6D1\u0001D\t\u0015Y6D1\u0001D\t\u0015q6D1\u0001D\t\u0015\t7D1\u0001D\t\u0015!7D1\u0001D\t\u001597D1\u0001D\u00039\u0019w\u000e]=%I\u00164\u0017-\u001e7uIM*\u0002$!@\u0003\u0002\t\r!Q\u0001B\u0004\u0005\u0013\u0011YA!\u0004\u0003\u0010\tE!1\u0003B\u000b+\t\tyPK\u0002N\u0003g#QA\u0011\u000fC\u0002\r#Q\u0001\u0014\u000fC\u0002\r#Qa\u0014\u000fC\u0002\r#QA\u0015\u000fC\u0002\r#Q!\u0016\u000fC\u0002\r#Q\u0001\u0017\u000fC\u0002\r#Qa\u0017\u000fC\u0002\r#QA\u0018\u000fC\u0002\r#Q!\u0019\u000fC\u0002\r#Q\u0001\u001a\u000fC\u0002\r#Qa\u001a\u000fC\u0002\r\u000babY8qs\u0012\"WMZ1vYR$C\'\u0006\r\u0003\u001c\t}!\u0011\u0005B\u0012\u0005K\u00119C!\u000b\u0003,\t5\"q\u0006B\u0019\u0005g)\"A!\b+\u0007A\u000b\u0019\fB\u0003C;\t\u00071\tB\u0003M;\t\u00071\tB\u0003P;\t\u00071\tB\u0003S;\t\u00071\tB\u0003V;\t\u00071\tB\u0003Y;\t\u00071\tB\u0003\\;\t\u00071\tB\u0003_;\t\u00071\tB\u0003b;\t\u00071\tB\u0003e;\t\u00071\tB\u0003h;\t\u00071)\u0001\bd_BLH\u0005Z3gCVdG\u000fJ\u001b\u00161\te\"Q\bB \u0005\u0003\u0012\u0019E!\u0012\u0003H\t%#1\nB\'\u0005\u001f\u0012\t&\u0006\u0002\u0003<)\u001a1+a-\u0005\u000b\ts\"\u0019A\"\u0005\u000b1s\"\u0019A\"\u0005\u000b=s\"\u0019A\"\u0005\u000bIs\"\u0019A\"\u0005\u000bUs\"\u0019A\"\u0005\u000bas\"\u0019A\"\u0005\u000bms\"\u0019A\"\u0005\u000bys\"\u0019A\"\u0005\u000b\u0005t\"\u0019A\"\u0005\u000b\u0011t\"\u0019A\"\u0005\u000b\u001dt\"\u0019A\"\u0002\u001d\r|\u0007/\u001f\u0013eK\u001a\fW\u000f\u001c;%mUA\"q\u000bB.\u0005;\u0012yF!\u0019\u0003d\t\u0015$q\rB5\u0005W\u0012iGa\u001c\u0016\u0005\te#f\u0001,\u00024\u0012)!i\bb\u0001\u0007\u0012)Aj\bb\u0001\u0007\u0012)qj\bb\u0001\u0007\u0012)!k\bb\u0001\u0007\u0012)Qk\bb\u0001\u0007\u0012)\u0001l\bb\u0001\u0007\u0012)1l\bb\u0001\u0007\u0012)al\bb\u0001\u0007\u0012)\u0011m\bb\u0001\u0007\u0012)Am\bb\u0001\u0007\u0012)qm\bb\u0001\u0007\u0006q1m\u001c9zI\u0011,g-Y;mi\u0012:T\u0003\u0007B;\u0005s\u0012YH! \u0003\u0000\t\u0005%1\u0011BC\u0005\u000f\u0013IIa#\u0003\u000eV\u0011!q\u000f\u0016\u00043\u0006MF!\u0002\"!\u0005\u0004\u0019E!\u0002\'!\u0005\u0004\u0019E!B(!\u0005\u0004\u0019E!\u0002*!\u0005\u0004\u0019E!B+!\u0005\u0004\u0019E!\u0002-!\u0005\u0004\u0019E!B.!\u0005\u0004\u0019E!\u00020!\u0005\u0004\u0019E!B1!\u0005\u0004\u0019E!\u00023!\u0005\u0004\u0019E!B4!\u0005\u0004\u0019\u0015AD2paf$C-\u001a4bk2$H\u0005O\u000b\u0019\u0005\'\u00139J!\'\u0003\u001c\nu%q\u0014BQ\u0005G\u0013)Ka*\u0003*\n-VC\u0001BKU\ra\u00161\u0017\u0003\u0006\u0005\u0006\u0012\ra\u0011\u0003\u0006\u0019\u0006\u0012\ra\u0011\u0003\u0006\u001f\u0006\u0012\ra\u0011\u0003\u0006%\u0006\u0012\ra\u0011\u0003\u0006+\u0006\u0012\ra\u0011\u0003\u00061\u0006\u0012\ra\u0011\u0003\u00067\u0006\u0012\ra\u0011\u0003\u0006=\u0006\u0012\ra\u0011\u0003\u0006C\u0006\u0012\ra\u0011\u0003\u0006I\u0006\u0012\ra\u0011\u0003\u0006O\u0006\u0012\raQ\u0001\u000fG>\u0004\u0018\u0010\n3fM\u0006,H\u000e\u001e\u0013:+a\u0011\tL!.\u00038\ne&1\u0018B_\u0005\u007f\u0013\tMa1\u0003F\n\u001d\'\u0011Z\u000b\u0003\u0005gS3aXAZ\t\u0015\u0011%E1\u0001D\t\u0015a%E1\u0001D\t\u0015y%E1\u0001D\t\u0015\u0011&E1\u0001D\t\u0015)&E1\u0001D\t\u0015A&E1\u0001D\t\u0015Y&E1\u0001D\t\u0015q&E1\u0001D\t\u0015\t\'E1\u0001D\t\u0015!\'E1\u0001D\t\u00159\'E1\u0001D\u0003=\u0019w\u000e]=%I\u00164\u0017-\u001e7uIE\u0002T\u0003\u0007Bh\u0005\'\u0014)Na6\u0003Z\nm\'Q\u001cBp\u0005C\u0014\u0019O!:\u0003hV\u0011!\u0011\u001b\u0016\u0004E\u0006MF!\u0002\"$\u0005\u0004\u0019E!\u0002\'$\u0005\u0004\u0019E!B($\u0005\u0004\u0019E!\u0002*$\u0005\u0004\u0019E!B+$\u0005\u0004\u0019E!\u0002-$\u0005\u0004\u0019E!B.$\u0005\u0004\u0019E!\u00020$\u0005\u0004\u0019E!B1$\u0005\u0004\u0019E!\u00023$\u0005\u0004\u0019E!B4$\u0005\u0004\u0019\u0015aD2paf$C-\u001a4bk2$H%M\u0019\u00161\t5(\u0011\u001fBz\u0005k\u00149P!?\u0003|\nu(q`B\u0001\u0007\u0007\u0019)!\u0006\u0002\u0003p*\u001aQ-a-\u0005\u000b\t##\u0019A\"\u0005\u000b1##\u0019A\"\u0005\u000b=##\u0019A\"\u0005\u000bI##\u0019A\"\u0005\u000bU##\u0019A\"\u0005\u000ba##\u0019A\"\u0005\u000bm##\u0019A\"\u0005\u000by##\u0019A\"\u0005\u000b\u0005$#\u0019A\"\u0005\u000b\u0011$#\u0019A\"\u0005\u000b\u001d$#\u0019A\"\u0002\u001bA\u0014x\u000eZ;diB\u0013XMZ5y+\t\u0019Y\u0001\u0005\u0003\u0004\u000e\r]QBAB\b\u0015\u0011\u0019\tba\u0005\u0002\t1\fgn\u001a\u0006\u0003\u0007+\tAA[1wC&!\u0011QLB\b\u0003=\u0001(o\u001c3vGRLE/\u001a:bi>\u0014XCAB\u000f!\u0015\u0019yb!\nH\u001b\t\u0019\tCC\u0002\u0004$M\n!bY8mY\u0016\u001cG/[8o\u0013\u0011\u00199c!\t\u0003\u0011%#XM]1u_J\f\u0001bY1o\u000bF,\u0018\r\u001c\u000b\u0005\u0007[\u0019\u0019\u0004E\u0002:\u0007_I1a!\r4\u0005\u001d\u0011un\u001c7fC:D\u0001b!\u000e(\u0003\u0003\u0005\raR\u0001\u0004q\u0012\n\u0014A\u00059s_\u0012,8\r^#mK6,g\u000e\u001e(b[\u0016$Baa\u0003\u0004<!I1Q\u0007\u0015\u0002\u0002\u0003\u00071Q\b\t\u0004s\r}\u0012bAB!g\t\u0019\u0011J\u001c;\u0002\u0011!\f7\u000f[\"pI\u0016$\"a!\u0010\u0002\r\u0015\fX/\u00197t)\u0011\u0019ica\u0013\t\u0011\rU\"&!AA\u0002\u001d\u000bq\u0001V;qY\u0016\f\u0014\u0007\u0005\u0002:YM!A\u0006OB*!\u0011\u0019)fa\u0017\u000e\u0005\r]#\u0002BB-\u0007\'\t!![8\n\u0007U\u001c9\u0006\u0006\u0002\u0004PQ\u001111B\u0001\u0006CB\u0004H._\u000b\u0019\u0007K\u001aYga\u001c\u0004t\r]41PB@\u0007\u0007\u001b9ia#\u0004\u0010\u000eME\u0003GB4\u0007+\u001b9j!\'\u0004\u001c\u000eu5qTBQ\u0007G\u001b)ka*\u0004*BA\u0012\bAB5\u0007[\u001a\th!\u001e\u0004z\ru4\u0011QBC\u0007\u0013\u001bii!%\u0011\u0007\u0001\u001bY\u0007B\u0003C_\t\u00071\tE\u0002A\u0007_\"Q\u0001T\u0018C\u0002\r\u00032\u0001QB:\t\u0015yuF1\u0001D!\r\u00015q\u000f\u0003\u0006%>\u0012\ra\u0011\t\u0004\u0001\u000emD!B+0\u0005\u0004\u0019\u0005c\u0001!\u0004\u0000\u0011)\u0001l\fb\u0001\u0007B\u0019\u0001ia!\u0005\u000bm{#\u0019A\"\u0011\u0007\u0001\u001b9\tB\u0003__\t\u00071\tE\u0002A\u0007\u0017#Q!Y\u0018C\u0002\r\u00032\u0001QBH\t\u0015!wF1\u0001D!\r\u000151\u0013\u0003\u0006O>\u0012\ra\u0011\u0005\u0007o>\u0002\ra!\u001b\t\ri|\u0003\u0019AB7\u0011\u0019ix\u00061\u0001\u0004r!9\u0011\u0011A\u0018A\u0002\rU\u0004bBA\u0004_\u0001\u00071\u0011\u0010\u0005\b\u0003\u001by\u0003\u0019AB?\u0011\u001d\t\u0019b\fa\u0001\u0007\u0003Cq!!\u00070\u0001\u0004\u0019)\tC\u0004\u0002 =\u0002\ra!#\t\u000f\u0005\u0015r\u00061\u0001\u0004\u000e\"9\u00111F\u0018A\u0002\rE\u0015aB;oCB\u0004H._\u000b\u0019\u0007_\u001bYla0\u0004D\u000e\u001d71ZBh\u0007\'\u001c9na7\u0004`\u000e\rH\u0003BBY\u0007K\u0004R!OBZ\u0007oK1a!.4\u0005\u0019y\u0005\u000f^5p]BA\u0012\bAB]\u0007{\u001b\tm!2\u0004J\u000e57\u0011[Bk\u00073\u001cin!9\u0011\u0007\u0001\u001bY\fB\u0003Ca\t\u00071\tE\u0002A\u0007\u007f#Q\u0001\u0014\u0019C\u0002\r\u00032\u0001QBb\t\u0015y\u0005G1\u0001D!\r\u00015q\u0019\u0003\u0006%B\u0012\ra\u0011\t\u0004\u0001\u000e-G!B+1\u0005\u0004\u0019\u0005c\u0001!\u0004P\u0012)\u0001\f\rb\u0001\u0007B\u0019\u0001ia5\u0005\u000bm\u0003$\u0019A\"\u0011\u0007\u0001\u001b9\u000eB\u0003_a\t\u00071\tE\u0002A\u00077$Q!\u0019\u0019C\u0002\r\u00032\u0001QBp\t\u0015!\u0007G1\u0001D!\r\u000151\u001d\u0003\u0006OB\u0012\ra\u0011\u0005\n\u0007O\u0004\u0014\u0011!a\u0001\u0007o\u000b1\u0001\u001f\u00131\u000319(/\u001b;f%\u0016\u0004H.Y2f)\t\u0019i\u000f\u0005\u0003\u0004\u000e\r=\u0018\u0002BBy\u0007\u001f\u0011aa\u00142kK\u000e$\b"
    )
  ScalaInlineInfo: length = 0xAE (unknown attribute)
   01 01 00 22 00 37 00 38 01 00 10 00 55 01 00 23
   00 55 01 00 25 00 55 01 00 13 00 55 01 00 15 00
   55 01 00 17 00 55 01 00 19 00 55 01 00 1B 00 55
   01 00 1D 00 55 01 00 1F 00 55 01 00 21 00 55 01
   00 C3 00 C4 01 00 A4 00 35 01 00 A5 00 55 01 00
   A7 00 55 01 00 A9 00 55 01 00 AB 00 55 01 00 AD
   00 55 01 00 AF 00 55 01 00 B1 00 55 01 00 B3 00
   55 01 00 B5 00 55 01 00 B7 00 55 01 00 B9 00 55
   01 00 E4 00 C4 01 00 DA 00 3C 01 00 3B 00 3C 01
   00 42 00 43 01 00 C6 00 C7 01 00 4C 00 4D 01 00
   BE 00 4D 01 00 BB 00 78 01 00 77 00 78 01
  ScalaSig: length = 0x3 (unknown attribute)
   05 02 00
