Classfile /Users/mw/Projects/slang-braindump/.jar/jar11/assemble/slang-braindump/assemble/content/scala/UninitializedFieldError.class
  Last modified May 29, 2022; size 5955 bytes
  SHA-256 checksum f3e38321d6d6eb23d5148754201d05e4f25f41dfeff168755c78f3b31a55aff3
  Compiled from "UninitializedFieldError.scala"
public final class scala.UninitializedFieldError extends java.lang.RuntimeException implements scala.Product
  minor version: 0
  major version: 52
  flags: (0x0031) ACC_PUBLIC, ACC_FINAL, ACC_SUPER
  this_class: #2                          // scala/UninitializedFieldError
  super_class: #4                         // java/lang/RuntimeException
  interfaces: 1, fields: 1, methods: 19, attributes: 6
Constant pool:
    #1 = Utf8               scala/UninitializedFieldError
    #2 = Class              #1            // scala/UninitializedFieldError
    #3 = Utf8               java/lang/RuntimeException
    #4 = Class              #3            // java/lang/RuntimeException
    #5 = Utf8               scala/Product
    #6 = Class              #5            // scala/Product
    #7 = Utf8               UninitializedFieldError.scala
    #8 = Utf8               Lscala/reflect/ScalaSignature;
    #9 = Utf8               bytes
   #10 = Utf8               \u0006\u0005\u0005]b\u0001\u0002\f\u0018\u0005jA\u0001b\f\u0001\u0003\u0016\u0004%\t\u0001\r\u0005\ts\u0001\u0011\t\u0012)A\u0005c!)!\b\u0001C\u0001w!)!\b\u0001C\u0001}!9A\tAA\u0001\n\u0003)\u0005bB$\u0001#\u0003%\t\u0001\u0013\u0005\b\'\u0002\t\t\u0011\"\u0011U\u0011\u001da\u0006!!A\u0005\u0002uCq!\u0019\u0001\u0002\u0002\u0013\u0005!\rC\u0004f\u0001\u0005\u0005I\u0011\t4\t\u000f5\u0004\u0011\u0011!C\u0001]\"91\u000fAA\u0001\n\u0003\"\bb\u0002<\u0001\u0003\u0003%\te\u001e\u0005\bq\u0002\t\t\u0011\"\u0011z\u000f\u001dYx#!A\t\u0002q4qAF\f\u0002\u0002#\u0005Q\u0010\u0003\u0004;!\u0011\u0005\u00111\u0003\u0005\n\u0003+\u0001\u0012\u0011!C#\u0003/A\u0011\"!\u0007\u0011\u0003\u0003%\t)a\u0007\t\u0013\u0005}\u0001#!A\u0005\u0002\u0006\u0005\u0002\"CA\u0017!\u0005\u0005I\u0011BA\u0018\u0005])f.\u001b8ji&\fG.\u001b>fI\u001aKW\r\u001c3FeJ|\'OC\u0001\u0019\u0003\u0015\u00198-\u00197b\u0007\u0001\u0019B\u0001A\u000e$MA\u0011A\u0004\t\b\u0003;yi\u0011aF\u0005\u0003?]\tq\u0001]1dW\u0006<W-\u0003\u0002\"E\t\u0001\"+\u001e8uS6,W\t_2faRLwN\u001c\u0006\u0003?]\u0001\"!\b\u0013\n\u0005\u0015:\"a\u0002)s_\u0012,8\r\u001e\t\u0003O5r!\u0001\u000b\u0010\u000f\u0005%bS\"\u0001\u0016\u000b\u0005-J\u0012A\u0002\u001fs_>$h(C\u0001\u0019\u0013\tq#E\u0001\u0007TKJL\u0017\r\\5{C\ndW-A\u0002ng\u001e,\u0012!\r\t\u0003eYr!a\r\u001b\u0011\u0005%:\u0012BA\u001b\u0018\u0003\u0019\u0001&/\u001a3fM&\u0011q\u0007\u000f\u0002\u0007\'R\u0014\u0018N\\4\u000b\u0005U:\u0012\u0001B7tO\u0002\na\u0001P5oSRtDC\u0001\u001f>!\ti\u0002\u0001C\u00030\u0007\u0001\u0007\u0011\u0007\u0006\u0002=\u007f!)\u0001\t\u0002a\u0001\u0003\u0006\u0019qN\u00196\u0011\u0005u\u0011\u0015BA\"\u0018\u0005\r\te._\u0001\u0005G>\u0004\u0018\u0010\u0006\u0002=\r\"9q&\u0002I\u0001\u0002\u0004\t\u0014AD2paf$C-\u001a4bk2$H%M\u000b\u0002\u0013*\u0012\u0011GS\u0016\u0002\u0017B\u0011A*U\u0007\u0002\u001b*\u0011ajT\u0001\nk:\u001c\u0007.Z2lK\u0012T!\u0001U\f\u0002\u0015\u0005tgn\u001c;bi&|g.\u0003\u0002S\u001b\n\tRO\\2iK\u000e\\W\r\u001a,be&\fgnY3\u0002\u001bA\u0014x\u000eZ;diB\u0013XMZ5y+\u0005)\u0006C\u0001,\\\u001b\u00059&B\u0001-Z\u0003\u0011a\u0017M\\4\u000b\u0003i\u000bAA[1wC&\u0011qgV\u0001\raJ|G-^2u\u0003JLG/_\u000b\u0002=B\u0011QdX\u0005\u0003A^\u00111!\u00138u\u00039\u0001(o\u001c3vGR,E.Z7f]R$\"!Q2\t\u000f\u0011L\u0011\u0011!a\u0001=\u0006\u0019\u0001\u0010J\u0019\u0002\u001fA\u0014x\u000eZ;di&#XM]1u_J,\u0012a\u001a\t\u0004Q.\fU\"A5\u000b\u0005)<\u0012AC2pY2,7\r^5p]&\u0011A.\u001b\u0002\t\u0013R,\'/\u0019;pe\u0006A1-\u00198FcV\fG\u000e\u0006\u0002peB\u0011Q\u0004]\u0005\u0003c^\u0011qAQ8pY\u0016\fg\u000eC\u0004e\u0017\u0005\u0005\t\u0019A!\u0002%A\u0014x\u000eZ;di\u0016cW-\\3oi:\u000bW.\u001a\u000b\u0003+VDq\u0001\u001a\u0007\u0002\u0002\u0003\u0007a,\u0001\u0005iCND7i\u001c3f)\u0005q\u0016AB3rk\u0006d7\u000f\u0006\u0002pu\"9AMDA\u0001\u0002\u0004\t\u0015aF+oS:LG/[1mSj,GMR5fY\u0012,%O]8s!\ti\u0002c\u0005\u0003\u0011}\u0006%\u0001#B@\u0002\u0006EbTBAA\u0001\u0015\r\t\u0019aF\u0001\beVtG/[7f\u0013\u0011\t9!!\u0001\u0003#\u0005\u00137\u000f\u001e:bGR4UO\\2uS>t\u0017\u0007\u0005\u0003\u0002\f\u0005EQBAA\u0007\u0015\r\ty!W\u0001\u0003S>L1ALA\u0007)\u0005a\u0018\u0001\u0003;p\'R\u0014\u0018N\\4\u0015\u0003U\u000bQ!\u00199qYf$2\u0001PA\u000f\u0011\u0015y3\u00031\u00012\u0003\u001d)h.\u00199qYf$B!a\t\u0002*A!Q$!\n2\u0013\r\t9c\u0006\u0002\u0007\u001fB$\u0018n\u001c8\t\u0011\u0005-B#!AA\u0002q\n1\u0001\u001f\u00131\u000319(/\u001b;f%\u0016\u0004H.Y2f)\t\t\t\u0004E\u0002W\u0003gI1!!\u000eX\u0005\u0019y%M[3di\u0002
   #11 = Utf8               java/lang/invoke/MethodHandles$Lookup
   #12 = Class              #11           // java/lang/invoke/MethodHandles$Lookup
   #13 = Utf8               java/lang/invoke/MethodHandles
   #14 = Class              #13           // java/lang/invoke/MethodHandles
   #15 = Utf8               Lookup
   #16 = Utf8               scala/runtime/ScalaRunTime$$anon$1
   #17 = Class              #16           // scala/runtime/ScalaRunTime$$anon$1
   #18 = Utf8               msg
   #19 = Utf8               Ljava/lang/String;
   #20 = Utf8               unapply
   #21 = Utf8               (Lscala/UninitializedFieldError;)Lscala/Option;
   #22 = Utf8               (Lscala/UninitializedFieldError;)Lscala/Option<Ljava/lang/String;>;
   #23 = Utf8               x$0
   #24 = Utf8               scala/UninitializedFieldError$
   #25 = Class              #24           // scala/UninitializedFieldError$
   #26 = Utf8               MODULE$
   #27 = Utf8               Lscala/UninitializedFieldError$;
   #28 = NameAndType        #26:#27       // MODULE$:Lscala/UninitializedFieldError$;
   #29 = Fieldref           #25.#28       // scala/UninitializedFieldError$.MODULE$:Lscala/UninitializedFieldError$;
   #30 = NameAndType        #20:#21       // unapply:(Lscala/UninitializedFieldError;)Lscala/Option;
   #31 = Methodref          #25.#30       // scala/UninitializedFieldError$.unapply:(Lscala/UninitializedFieldError;)Lscala/Option;
   #32 = Utf8               Lscala/UninitializedFieldError;
   #33 = Utf8               apply
   #34 = Utf8               (Ljava/lang/String;)Lscala/UninitializedFieldError;
   #35 = Utf8               <init>
   #36 = Utf8               (Ljava/lang/String;)V
   #37 = NameAndType        #35:#36       // "<init>":(Ljava/lang/String;)V
   #38 = Methodref          #2.#37        // scala/UninitializedFieldError."<init>":(Ljava/lang/String;)V
   #39 = Utf8               andThen
   #40 = Utf8               (Lscala/Function1;)Lscala/Function1;
   #41 = Utf8               <A$:Ljava/lang/Object;>(Lscala/Function1<Lscala/UninitializedFieldError;TA$;>;)Lscala/Function1<Ljava/lang/String;TA$;>;
   #42 = Utf8               g
   #43 = Utf8               (Ljava/lang/Object;)Ljava/lang/Object;
   #44 = MethodType         #43           //  (Ljava/lang/Object;)Ljava/lang/Object;
   #45 = Utf8               scala/Function1
   #46 = Class              #45           // scala/Function1
   #47 = Utf8               $anonfun$andThen$1
   #48 = Utf8               (Lscala/Function1;Lscala/Function1;Ljava/lang/Object;)Ljava/lang/Object;
   #49 = NameAndType        #47:#48       // $anonfun$andThen$1:(Lscala/Function1;Lscala/Function1;Ljava/lang/Object;)Ljava/lang/Object;
   #50 = InterfaceMethodref #46.#49       // scala/Function1.$anonfun$andThen$1:(Lscala/Function1;Lscala/Function1;Ljava/lang/Object;)Ljava/lang/Object;
   #51 = MethodHandle       6:#50         // REF_invokeStatic scala/Function1.$anonfun$andThen$1:(Lscala/Function1;Lscala/Function1;Ljava/lang/Object;)Ljava/lang/Object;
   #52 = Integer            1
   #53 = Utf8               java/lang/invoke/LambdaMetafactory
   #54 = Class              #53           // java/lang/invoke/LambdaMetafactory
   #55 = Utf8               altMetafactory
   #56 = Utf8               (Ljava/lang/invoke/MethodHandles$Lookup;Ljava/lang/String;Ljava/lang/invoke/MethodType;[Ljava/lang/Object;)Ljava/lang/invoke/CallSite;
   #57 = NameAndType        #55:#56       // altMetafactory:(Ljava/lang/invoke/MethodHandles$Lookup;Ljava/lang/String;Ljava/lang/invoke/MethodType;[Ljava/lang/Object;)Ljava/lang/invoke/CallSite;
   #58 = Methodref          #54.#57       // java/lang/invoke/LambdaMetafactory.altMetafactory:(Ljava/lang/invoke/MethodHandles$Lookup;Ljava/lang/String;Ljava/lang/invoke/MethodType;[Ljava/lang/Object;)Ljava/lang/invoke/CallSite;
   #59 = MethodHandle       6:#58         // REF_invokeStatic java/lang/invoke/LambdaMetafactory.altMetafactory:(Ljava/lang/invoke/MethodHandles$Lookup;Ljava/lang/String;Ljava/lang/invoke/MethodType;[Ljava/lang/Object;)Ljava/lang/invoke/CallSite;
   #60 = Utf8               (Lscala/Function1;Lscala/Function1;)Lscala/Function1;
   #61 = NameAndType        #33:#60       // apply:(Lscala/Function1;Lscala/Function1;)Lscala/Function1;
   #62 = InvokeDynamic      #0:#61        // #0:apply:(Lscala/Function1;Lscala/Function1;)Lscala/Function1;
   #63 = Utf8               Lscala/Function1;
   #64 = Utf8               compose
   #65 = Utf8               <A$:Ljava/lang/Object;>(Lscala/Function1<TA$;Ljava/lang/String;>;)Lscala/Function1<TA$;Lscala/UninitializedFieldError;>;
   #66 = Utf8               $anonfun$compose$1
   #67 = NameAndType        #66:#48       // $anonfun$compose$1:(Lscala/Function1;Lscala/Function1;Ljava/lang/Object;)Ljava/lang/Object;
   #68 = InterfaceMethodref #46.#67       // scala/Function1.$anonfun$compose$1:(Lscala/Function1;Lscala/Function1;Ljava/lang/Object;)Ljava/lang/Object;
   #69 = MethodHandle       6:#68         // REF_invokeStatic scala/Function1.$anonfun$compose$1:(Lscala/Function1;Lscala/Function1;Ljava/lang/Object;)Ljava/lang/Object;
   #70 = InvokeDynamic      #1:#61        // #1:apply:(Lscala/Function1;Lscala/Function1;)Lscala/Function1;
   #71 = Utf8               productElementNames
   #72 = Utf8               ()Lscala/collection/Iterator;
   #73 = Utf8               ()Lscala/collection/Iterator<Ljava/lang/String;>;
   #74 = Utf8               productElementNames$
   #75 = Utf8               (Lscala/Product;)Lscala/collection/Iterator;
   #76 = NameAndType        #74:#75       // productElementNames$:(Lscala/Product;)Lscala/collection/Iterator;
   #77 = InterfaceMethodref #6.#76        // scala/Product.productElementNames$:(Lscala/Product;)Lscala/collection/Iterator;
   #78 = Utf8               this
   #79 = Utf8               ()Ljava/lang/String;
   #80 = NameAndType        #18:#19       // msg:Ljava/lang/String;
   #81 = Fieldref           #2.#80        // scala/UninitializedFieldError.msg:Ljava/lang/String;
   #82 = Utf8               copy
   #83 = Utf8               copy$default$1
   #84 = NameAndType        #18:#79       // msg:()Ljava/lang/String;
   #85 = Methodref          #2.#84        // scala/UninitializedFieldError.msg:()Ljava/lang/String;
   #86 = Utf8               productPrefix
   #87 = Utf8               UninitializedFieldError
   #88 = String             #87           // UninitializedFieldError
   #89 = Utf8               productArity
   #90 = Utf8               ()I
   #91 = Utf8               productElement
   #92 = Utf8               (I)Ljava/lang/Object;
   #93 = Utf8               x$1
   #94 = Utf8               scala/runtime/Statics
   #95 = Class              #94           // scala/runtime/Statics
   #96 = Utf8               ioobe
   #97 = NameAndType        #96:#92       // ioobe:(I)Ljava/lang/Object;
   #98 = Methodref          #95.#97       // scala/runtime/Statics.ioobe:(I)Ljava/lang/Object;
   #99 = Utf8               I
  #100 = Utf8               productIterator
  #101 = Utf8               ()Lscala/collection/Iterator<Ljava/lang/Object;>;
  #102 = Utf8               (Lscala/Product;)V
  #103 = NameAndType        #35:#102      // "<init>":(Lscala/Product;)V
  #104 = Methodref          #17.#103      // scala/runtime/ScalaRunTime$$anon$1."<init>":(Lscala/Product;)V
  #105 = Utf8               canEqual
  #106 = Utf8               (Ljava/lang/Object;)Z
  #107 = Utf8               Ljava/lang/Object;
  #108 = Utf8               productElementName
  #109 = Utf8               (I)Ljava/lang/String;
  #110 = String             #18           // msg
  #111 = Utf8               java/lang/String
  #112 = Class              #111          // java/lang/String
  #113 = Utf8               hashCode
  #114 = Utf8               scala/util/hashing/MurmurHash3$
  #115 = Class              #114          // scala/util/hashing/MurmurHash3$
  #116 = Utf8               Lscala/util/hashing/MurmurHash3$;
  #117 = NameAndType        #26:#116      // MODULE$:Lscala/util/hashing/MurmurHash3$;
  #118 = Fieldref           #115.#117     // scala/util/hashing/MurmurHash3$.MODULE$:Lscala/util/hashing/MurmurHash3$;
  #119 = Utf8               productHash
  #120 = Utf8               (Lscala/Product;)I
  #121 = NameAndType        #119:#120     // productHash:(Lscala/Product;)I
  #122 = Methodref          #115.#121     // scala/util/hashing/MurmurHash3$.productHash:(Lscala/Product;)I
  #123 = Utf8               equals
  #124 = Utf8               java/lang/Object
  #125 = Class              #124          // java/lang/Object
  #126 = NameAndType        #123:#106     // equals:(Ljava/lang/Object;)Z
  #127 = Methodref          #125.#126     // java/lang/Object.equals:(Ljava/lang/Object;)Z
  #128 = Methodref          #4.#37        // java/lang/RuntimeException."<init>":(Ljava/lang/String;)V
  #129 = Utf8               (Ljava/lang/Object;)V
  #130 = Utf8               obj
  #131 = Utf8               valueOf
  #132 = Utf8               (Ljava/lang/Object;)Ljava/lang/String;
  #133 = NameAndType        #131:#132     // valueOf:(Ljava/lang/Object;)Ljava/lang/String;
  #134 = Methodref          #112.#133     // java/lang/String.valueOf:(Ljava/lang/Object;)Ljava/lang/String;
  #135 = Utf8               $deserializeLambda$
  #136 = Utf8               (Ljava/lang/invoke/SerializedLambda;)Ljava/lang/Object;
  #137 = Utf8               scala/runtime/LambdaDeserialize
  #138 = Class              #137          // scala/runtime/LambdaDeserialize
  #139 = Utf8               bootstrap
  #140 = Utf8               (Ljava/lang/invoke/MethodHandles$Lookup;Ljava/lang/String;Ljava/lang/invoke/MethodType;[Ljava/lang/invoke/MethodHandle;)Ljava/lang/invoke/CallSite;
  #141 = NameAndType        #139:#140     // bootstrap:(Ljava/lang/invoke/MethodHandles$Lookup;Ljava/lang/String;Ljava/lang/invoke/MethodType;[Ljava/lang/invoke/MethodHandle;)Ljava/lang/invoke/CallSite;
  #142 = Methodref          #138.#141     // scala/runtime/LambdaDeserialize.bootstrap:(Ljava/lang/invoke/MethodHandles$Lookup;Ljava/lang/String;Ljava/lang/invoke/MethodType;[Ljava/lang/invoke/MethodHandle;)Ljava/lang/invoke/CallSite;
  #143 = MethodHandle       6:#142        // REF_invokeStatic scala/runtime/LambdaDeserialize.bootstrap:(Ljava/lang/invoke/MethodHandles$Lookup;Ljava/lang/String;Ljava/lang/invoke/MethodType;[Ljava/lang/invoke/MethodHandle;)Ljava/lang/invoke/CallSite;
  #144 = Utf8               lambdaDeserialize
  #145 = NameAndType        #144:#136     // lambdaDeserialize:(Ljava/lang/invoke/SerializedLambda;)Ljava/lang/Object;
  #146 = InvokeDynamic      #2:#145       // #2:lambdaDeserialize:(Ljava/lang/invoke/SerializedLambda;)Ljava/lang/Object;
  #147 = Utf8               Code
  #148 = Utf8               LocalVariableTable
  #149 = Utf8               Signature
  #150 = Utf8               MethodParameters
  #151 = Utf8               LineNumberTable
  #152 = Utf8               StackMapTable
  #153 = Utf8               InnerClasses
  #154 = Utf8               SourceFile
  #155 = Utf8               RuntimeVisibleAnnotations
  #156 = Utf8               BootstrapMethods
  #157 = Utf8               ScalaInlineInfo
  #158 = Utf8               ScalaSig
{
  private final java.lang.String msg;
    descriptor: Ljava/lang/String;
    flags: (0x0012) ACC_PRIVATE, ACC_FINAL

  public static scala.Option<java.lang.String> unapply(scala.UninitializedFieldError);
    descriptor: (Lscala/UninitializedFieldError;)Lscala/Option;
    flags: (0x0009) ACC_PUBLIC, ACC_STATIC
    Code:
      stack=2, locals=1, args_size=1
         0: getstatic     #29                 // Field scala/UninitializedFieldError$.MODULE$:Lscala/UninitializedFieldError$;
         3: aload_0
         4: invokevirtual #31                 // Method scala/UninitializedFieldError$.unapply:(Lscala/UninitializedFieldError;)Lscala/Option;
         7: areturn
      LocalVariableTable:
        Start  Length  Slot  Name   Signature
            0       8     0   x$0   Lscala/UninitializedFieldError;
    Signature: #22                          // (Lscala/UninitializedFieldError;)Lscala/Option<Ljava/lang/String;>;
    MethodParameters:
      Name                           Flags
      x$0                            final

  public static scala.UninitializedFieldError apply(java.lang.String);
    descriptor: (Ljava/lang/String;)Lscala/UninitializedFieldError;
    flags: (0x0009) ACC_PUBLIC, ACC_STATIC
    Code:
      stack=3, locals=1, args_size=1
         0: getstatic     #29                 // Field scala/UninitializedFieldError$.MODULE$:Lscala/UninitializedFieldError$;
         3: pop
         4: new           #2                  // class scala/UninitializedFieldError
         7: dup
         8: aload_0
         9: invokespecial #38                 // Method "<init>":(Ljava/lang/String;)V
        12: areturn
      LineNumberTable:
        line 21: 4
      LocalVariableTable:
        Start  Length  Slot  Name   Signature
            0      13     0   msg   Ljava/lang/String;
    MethodParameters:
      Name                           Flags
      msg                            final

  public static <A$ extends java.lang.Object> scala.Function1<java.lang.String, A$> andThen(scala.Function1<scala.UninitializedFieldError, A$>);
    descriptor: (Lscala/Function1;)Lscala/Function1;
    flags: (0x0009) ACC_PUBLIC, ACC_STATIC
    Code:
      stack=2, locals=1, args_size=1
         0: getstatic     #29                 // Field scala/UninitializedFieldError$.MODULE$:Lscala/UninitializedFieldError$;
         3: aload_0
         4: invokedynamic #62,  0             // InvokeDynamic #0:apply:(Lscala/Function1;Lscala/Function1;)Lscala/Function1;
         9: areturn
      LocalVariableTable:
        Start  Length  Slot  Name   Signature
            0      10     0     g   Lscala/Function1;
    Signature: #41                          // <A$:Ljava/lang/Object;>(Lscala/Function1<Lscala/UninitializedFieldError;TA$;>;)Lscala/Function1<Ljava/lang/String;TA$;>;
    MethodParameters:
      Name                           Flags
      g                              final

  public static <A$ extends java.lang.Object> scala.Function1<A$, scala.UninitializedFieldError> compose(scala.Function1<A$, java.lang.String>);
    descriptor: (Lscala/Function1;)Lscala/Function1;
    flags: (0x0009) ACC_PUBLIC, ACC_STATIC
    Code:
      stack=2, locals=1, args_size=1
         0: getstatic     #29                 // Field scala/UninitializedFieldError$.MODULE$:Lscala/UninitializedFieldError$;
         3: aload_0
         4: invokedynamic #70,  0             // InvokeDynamic #1:apply:(Lscala/Function1;Lscala/Function1;)Lscala/Function1;
         9: areturn
      LocalVariableTable:
        Start  Length  Slot  Name   Signature
            0      10     0     g   Lscala/Function1;
    Signature: #65                          // <A$:Ljava/lang/Object;>(Lscala/Function1<TA$;Ljava/lang/String;>;)Lscala/Function1<TA$;Lscala/UninitializedFieldError;>;
    MethodParameters:
      Name                           Flags
      g                              final

  public scala.collection.Iterator<java.lang.String> productElementNames();
    descriptor: ()Lscala/collection/Iterator;
    flags: (0x0001) ACC_PUBLIC
    Code:
      stack=1, locals=1, args_size=1
         0: aload_0
         1: invokestatic  #77                 // InterfaceMethod scala/Product.productElementNames$:(Lscala/Product;)Lscala/collection/Iterator;
         4: areturn
      LineNumberTable:
        line 21: 0
      LocalVariableTable:
        Start  Length  Slot  Name   Signature
            0       5     0  this   Lscala/UninitializedFieldError;
    Signature: #73                          // ()Lscala/collection/Iterator<Ljava/lang/String;>;

  public java.lang.String msg();
    descriptor: ()Ljava/lang/String;
    flags: (0x0001) ACC_PUBLIC
    Code:
      stack=1, locals=1, args_size=1
         0: aload_0
         1: getfield      #81                 // Field msg:Ljava/lang/String;
         4: areturn
      LineNumberTable:
        line 21: 0
      LocalVariableTable:
        Start  Length  Slot  Name   Signature
            0       5     0  this   Lscala/UninitializedFieldError;

  public scala.UninitializedFieldError copy(java.lang.String);
    descriptor: (Ljava/lang/String;)Lscala/UninitializedFieldError;
    flags: (0x0001) ACC_PUBLIC
    Code:
      stack=3, locals=2, args_size=2
         0: new           #2                  // class scala/UninitializedFieldError
         3: dup
         4: aload_1
         5: invokespecial #38                 // Method "<init>":(Ljava/lang/String;)V
         8: areturn
      LineNumberTable:
        line 21: 0
      LocalVariableTable:
        Start  Length  Slot  Name   Signature
            0       9     0  this   Lscala/UninitializedFieldError;
            0       9     1   msg   Ljava/lang/String;
    MethodParameters:
      Name                           Flags
      msg                            final

  public java.lang.String copy$default$1();
    descriptor: ()Ljava/lang/String;
    flags: (0x0001) ACC_PUBLIC
    Code:
      stack=1, locals=1, args_size=1
         0: aload_0
         1: invokevirtual #85                 // Method msg:()Ljava/lang/String;
         4: areturn
      LineNumberTable:
        line 21: 0
      LocalVariableTable:
        Start  Length  Slot  Name   Signature
            0       5     0  this   Lscala/UninitializedFieldError;

  public java.lang.String productPrefix();
    descriptor: ()Ljava/lang/String;
    flags: (0x0001) ACC_PUBLIC
    Code:
      stack=1, locals=1, args_size=1
         0: ldc           #88                 // String UninitializedFieldError
         2: areturn
      LineNumberTable:
        line 21: 0
      LocalVariableTable:
        Start  Length  Slot  Name   Signature
            0       3     0  this   Lscala/UninitializedFieldError;

  public int productArity();
    descriptor: ()I
    flags: (0x0001) ACC_PUBLIC
    Code:
      stack=1, locals=1, args_size=1
         0: iconst_1
         1: ireturn
      LineNumberTable:
        line 21: 0
      LocalVariableTable:
        Start  Length  Slot  Name   Signature
            0       2     0  this   Lscala/UninitializedFieldError;

  public java.lang.Object productElement(int);
    descriptor: (I)Ljava/lang/Object;
    flags: (0x0001) ACC_PUBLIC
    Code:
      stack=1, locals=2, args_size=2
         0: iload_1
         1: tableswitch   { // 0 to 0
                       0: 20
                 default: 25
            }
        20: aload_0
        21: invokevirtual #85                 // Method msg:()Ljava/lang/String;
        24: areturn
        25: iload_1
        26: invokestatic  #98                 // Method scala/runtime/Statics.ioobe:(I)Ljava/lang/Object;
        29: areturn
      StackMapTable: number_of_entries = 2
        frame_type = 20 /* same */
        frame_type = 4 /* same */
      LineNumberTable:
        line 21: 0
      LocalVariableTable:
        Start  Length  Slot  Name   Signature
            0      30     0  this   Lscala/UninitializedFieldError;
            0      30     1   x$1   I
    MethodParameters:
      Name                           Flags
      x$1                            final

  public scala.collection.Iterator<java.lang.Object> productIterator();
    descriptor: ()Lscala/collection/Iterator;
    flags: (0x0001) ACC_PUBLIC
    Code:
      stack=3, locals=1, args_size=1
         0: new           #17                 // class scala/runtime/ScalaRunTime$$anon$1
         3: dup
         4: aload_0
         5: invokespecial #104                // Method scala/runtime/ScalaRunTime$$anon$1."<init>":(Lscala/Product;)V
         8: areturn
      LineNumberTable:
        line 21: 0
      LocalVariableTable:
        Start  Length  Slot  Name   Signature
            0       9     0  this   Lscala/UninitializedFieldError;
    Signature: #101                         // ()Lscala/collection/Iterator<Ljava/lang/Object;>;

  public boolean canEqual(java.lang.Object);
    descriptor: (Ljava/lang/Object;)Z
    flags: (0x0001) ACC_PUBLIC
    Code:
      stack=1, locals=2, args_size=2
         0: aload_1
         1: instanceof    #2                  // class scala/UninitializedFieldError
         4: ireturn
      LineNumberTable:
        line 21: 0
      LocalVariableTable:
        Start  Length  Slot  Name   Signature
            0       5     0  this   Lscala/UninitializedFieldError;
            0       5     1   x$1   Ljava/lang/Object;
    MethodParameters:
      Name                           Flags
      x$1                            final

  public java.lang.String productElementName(int);
    descriptor: (I)Ljava/lang/String;
    flags: (0x0001) ACC_PUBLIC
    Code:
      stack=1, locals=2, args_size=2
         0: iload_1
         1: tableswitch   { // 0 to 0
                       0: 20
                 default: 23
            }
        20: ldc           #110                // String msg
        22: areturn
        23: iload_1
        24: invokestatic  #98                 // Method scala/runtime/Statics.ioobe:(I)Ljava/lang/Object;
        27: checkcast     #112                // class java/lang/String
        30: areturn
      StackMapTable: number_of_entries = 2
        frame_type = 20 /* same */
        frame_type = 2 /* same */
      LineNumberTable:
        line 21: 0
      LocalVariableTable:
        Start  Length  Slot  Name   Signature
            0      31     0  this   Lscala/UninitializedFieldError;
            0      31     1   x$1   I
    MethodParameters:
      Name                           Flags
      x$1                            final

  public int hashCode();
    descriptor: ()I
    flags: (0x0001) ACC_PUBLIC
    Code:
      stack=2, locals=1, args_size=1
         0: getstatic     #118                // Field scala/util/hashing/MurmurHash3$.MODULE$:Lscala/util/hashing/MurmurHash3$;
         3: aload_0
         4: invokevirtual #122                // Method scala/util/hashing/MurmurHash3$.productHash:(Lscala/Product;)I
         7: ireturn
      LineNumberTable:
        line 21: 0
      LocalVariableTable:
        Start  Length  Slot  Name   Signature
            0       8     0  this   Lscala/UninitializedFieldError;

  public boolean equals(java.lang.Object);
    descriptor: (Ljava/lang/Object;)Z
    flags: (0x0001) ACC_PUBLIC
    Code:
      stack=2, locals=5, args_size=2
         0: aload_0
         1: aload_1
         2: if_acmpeq     67
         5: aload_1
         6: instanceof    #2                  // class scala/UninitializedFieldError
         9: ifeq          17
        12: iconst_1
        13: istore_2
        14: goto          19
        17: iconst_0
        18: istore_2
        19: iload_2
        20: ifeq          69
        23: aload_1
        24: checkcast     #2                  // class scala/UninitializedFieldError
        27: astore_3
        28: aload_0
        29: invokevirtual #85                 // Method msg:()Ljava/lang/String;
        32: aload_3
        33: invokevirtual #85                 // Method msg:()Ljava/lang/String;
        36: astore        4
        38: dup
        39: ifnonnull     51
        42: pop
        43: aload         4
        45: ifnull        59
        48: goto          63
        51: aload         4
        53: invokevirtual #127                // Method java/lang/Object.equals:(Ljava/lang/Object;)Z
        56: ifeq          63
        59: iconst_1
        60: goto          64
        63: iconst_0
        64: ifeq          69
        67: iconst_1
        68: ireturn
        69: iconst_0
        70: ireturn
      StackMapTable: number_of_entries = 8
        frame_type = 17 /* same */
        frame_type = 252 /* append */
          offset_delta = 1
          locals = [ int ]
        frame_type = 255 /* full_frame */
          offset_delta = 31
          locals = [ class scala/UninitializedFieldError, class java/lang/Object, int, class scala/UninitializedFieldError, class java/lang/String ]
          stack = [ class java/lang/String ]
        frame_type = 7 /* same */
        frame_type = 3 /* same */
        frame_type = 64 /* same_locals_1_stack_item */
          stack = [ int ]
        frame_type = 248 /* chop */
          offset_delta = 2
        frame_type = 252 /* append */
          offset_delta = 1
          locals = [ int ]
      LineNumberTable:
        line 21: 0
      LocalVariableTable:
        Start  Length  Slot  Name   Signature
            0      71     0  this   Lscala/UninitializedFieldError;
            0      71     1   x$1   Ljava/lang/Object;
    MethodParameters:
      Name                           Flags
      x$1                            final

  public scala.UninitializedFieldError(java.lang.String);
    descriptor: (Ljava/lang/String;)V
    flags: (0x0001) ACC_PUBLIC
    Code:
      stack=2, locals=2, args_size=2
         0: aload_0
         1: aload_1
         2: putfield      #81                 // Field msg:Ljava/lang/String;
         5: aload_0
         6: aload_1
         7: invokespecial #128                // Method java/lang/RuntimeException."<init>":(Ljava/lang/String;)V
        10: return
      LineNumberTable:
        line 21: 0
      LocalVariableTable:
        Start  Length  Slot  Name   Signature
            0      11     0  this   Lscala/UninitializedFieldError;
            0      11     1   msg   Ljava/lang/String;
    MethodParameters:
      Name                           Flags
      msg                            final

  public scala.UninitializedFieldError(java.lang.Object);
    descriptor: (Ljava/lang/Object;)V
    flags: (0x0001) ACC_PUBLIC
    Code:
      stack=2, locals=2, args_size=2
         0: aload_0
         1: aload_1
         2: invokestatic  #134                // Method java/lang/String.valueOf:(Ljava/lang/Object;)Ljava/lang/String;
         5: invokespecial #38                 // Method "<init>":(Ljava/lang/String;)V
         8: return
      LineNumberTable:
        line 22: 0
      LocalVariableTable:
        Start  Length  Slot  Name   Signature
            0       9     0  this   Lscala/UninitializedFieldError;
            0       9     1   obj   Ljava/lang/Object;
    MethodParameters:
      Name                           Flags
      obj                            final

  private static java.lang.Object $deserializeLambda$(java.lang.invoke.SerializedLambda);
    descriptor: (Ljava/lang/invoke/SerializedLambda;)Ljava/lang/Object;
    flags: (0x100a) ACC_PRIVATE, ACC_STATIC, ACC_SYNTHETIC
    Code:
      stack=1, locals=1, args_size=1
         0: aload_0
         1: invokedynamic #146,  0            // InvokeDynamic #2:lambdaDeserialize:(Ljava/lang/invoke/SerializedLambda;)Ljava/lang/Object;
         6: areturn
}
InnerClasses:
  public static final #15= #12 of #14;    // Lookup=class java/lang/invoke/MethodHandles$Lookup of class java/lang/invoke/MethodHandles
  public final #17;                       // class scala/runtime/ScalaRunTime$$anon$1
SourceFile: "UninitializedFieldError.scala"
RuntimeVisibleAnnotations:
  0: #8(#9=s#10)
    scala.reflect.ScalaSignature(
      bytes="\u0006\u0005\u0005]b\u0001\u0002\f\u0018\u0005jA\u0001b\f\u0001\u0003\u0016\u0004%\t\u0001\r\u0005\ts\u0001\u0011\t\u0012)A\u0005c!)!\b\u0001C\u0001w!)!\b\u0001C\u0001}!9A\tAA\u0001\n\u0003)\u0005bB$\u0001#\u0003%\t\u0001\u0013\u0005\b\'\u0002\t\t\u0011\"\u0011U\u0011\u001da\u0006!!A\u0005\u0002uCq!\u0019\u0001\u0002\u0002\u0013\u0005!\rC\u0004f\u0001\u0005\u0005I\u0011\t4\t\u000f5\u0004\u0011\u0011!C\u0001]\"91\u000fAA\u0001\n\u0003\"\bb\u0002<\u0001\u0003\u0003%\te\u001e\u0005\bq\u0002\t\t\u0011\"\u0011z\u000f\u001dYx#!A\t\u0002q4qAF\f\u0002\u0002#\u0005Q\u0010\u0003\u0004;!\u0011\u0005\u00111\u0003\u0005\n\u0003+\u0001\u0012\u0011!C#\u0003/A\u0011\"!\u0007\u0011\u0003\u0003%\t)a\u0007\t\u0013\u0005}\u0001#!A\u0005\u0002\u0006\u0005\u0002\"CA\u0017!\u0005\u0005I\u0011BA\u0018\u0005])f.\u001b8ji&\fG.\u001b>fI\u001aKW\r\u001c3FeJ|\'OC\u0001\u0019\u0003\u0015\u00198-\u00197b\u0007\u0001\u0019B\u0001A\u000e$MA\u0011A\u0004\t\b\u0003;yi\u0011aF\u0005\u0003?]\tq\u0001]1dW\u0006<W-\u0003\u0002\"E\t\u0001\"+\u001e8uS6,W\t_2faRLwN\u001c\u0006\u0003?]\u0001\"!\b\u0013\n\u0005\u0015:\"a\u0002)s_\u0012,8\r\u001e\t\u0003O5r!\u0001\u000b\u0010\u000f\u0005%bS\"\u0001\u0016\u000b\u0005-J\u0012A\u0002\u001fs_>$h(C\u0001\u0019\u0013\tq#E\u0001\u0007TKJL\u0017\r\\5{C\ndW-A\u0002ng\u001e,\u0012!\r\t\u0003eYr!a\r\u001b\u0011\u0005%:\u0012BA\u001b\u0018\u0003\u0019\u0001&/\u001a3fM&\u0011q\u0007\u000f\u0002\u0007\'R\u0014\u0018N\\4\u000b\u0005U:\u0012\u0001B7tO\u0002\na\u0001P5oSRtDC\u0001\u001f>!\ti\u0002\u0001C\u00030\u0007\u0001\u0007\u0011\u0007\u0006\u0002=\u007f!)\u0001\t\u0002a\u0001\u0003\u0006\u0019qN\u00196\u0011\u0005u\u0011\u0015BA\"\u0018\u0005\r\te._\u0001\u0005G>\u0004\u0018\u0010\u0006\u0002=\r\"9q&\u0002I\u0001\u0002\u0004\t\u0014AD2paf$C-\u001a4bk2$H%M\u000b\u0002\u0013*\u0012\u0011GS\u0016\u0002\u0017B\u0011A*U\u0007\u0002\u001b*\u0011ajT\u0001\nk:\u001c\u0007.Z2lK\u0012T!\u0001U\f\u0002\u0015\u0005tgn\u001c;bi&|g.\u0003\u0002S\u001b\n\tRO\\2iK\u000e\\W\r\u001a,be&\fgnY3\u0002\u001bA\u0014x\u000eZ;diB\u0013XMZ5y+\u0005)\u0006C\u0001,\\\u001b\u00059&B\u0001-Z\u0003\u0011a\u0017M\\4\u000b\u0003i\u000bAA[1wC&\u0011qgV\u0001\raJ|G-^2u\u0003JLG/_\u000b\u0002=B\u0011QdX\u0005\u0003A^\u00111!\u00138u\u00039\u0001(o\u001c3vGR,E.Z7f]R$\"!Q2\t\u000f\u0011L\u0011\u0011!a\u0001=\u0006\u0019\u0001\u0010J\u0019\u0002\u001fA\u0014x\u000eZ;di&#XM]1u_J,\u0012a\u001a\t\u0004Q.\fU\"A5\u000b\u0005)<\u0012AC2pY2,7\r^5p]&\u0011A.\u001b\u0002\t\u0013R,\'/\u0019;pe\u0006A1-\u00198FcV\fG\u000e\u0006\u0002peB\u0011Q\u0004]\u0005\u0003c^\u0011qAQ8pY\u0016\fg\u000eC\u0004e\u0017\u0005\u0005\t\u0019A!\u0002%A\u0014x\u000eZ;di\u0016cW-\\3oi:\u000bW.\u001a\u000b\u0003+VDq\u0001\u001a\u0007\u0002\u0002\u0003\u0007a,\u0001\u0005iCND7i\u001c3f)\u0005q\u0016AB3rk\u0006d7\u000f\u0006\u0002pu\"9AMDA\u0001\u0002\u0004\t\u0015aF+oS:LG/[1mSj,GMR5fY\u0012,%O]8s!\ti\u0002c\u0005\u0003\u0011}\u0006%\u0001#B@\u0002\u0006EbTBAA\u0001\u0015\r\t\u0019aF\u0001\beVtG/[7f\u0013\u0011\t9!!\u0001\u0003#\u0005\u00137\u000f\u001e:bGR4UO\\2uS>t\u0017\u0007\u0005\u0003\u0002\f\u0005EQBAA\u0007\u0015\r\ty!W\u0001\u0003S>L1ALA\u0007)\u0005a\u0018\u0001\u0003;p\'R\u0014\u0018N\\4\u0015\u0003U\u000bQ!\u00199qYf$2\u0001PA\u000f\u0011\u0015y3\u00031\u00012\u0003\u001d)h.\u00199qYf$B!a\t\u0002*A!Q$!\n2\u0013\r\t9c\u0006\u0002\u0007\u001fB$\u0018n\u001c8\t\u0011\u0005-B#!AA\u0002q\n1\u0001\u001f\u00131\u000319(/\u001b;f%\u0016\u0004H.Y2f)\t\t\t\u0004E\u0002W\u0003gI1!!\u000eX\u0005\u0019y%M[3di\u0002"
    )
BootstrapMethods:
  0: #59 REF_invokeStatic java/lang/invoke/LambdaMetafactory.altMetafactory:(Ljava/lang/invoke/MethodHandles$Lookup;Ljava/lang/String;Ljava/lang/invoke/MethodType;[Ljava/lang/Object;)Ljava/lang/invoke/CallSite;
    Method arguments:
      #44 (Ljava/lang/Object;)Ljava/lang/Object;
      #51 REF_invokeStatic scala/Function1.$anonfun$andThen$1:(Lscala/Function1;Lscala/Function1;Ljava/lang/Object;)Ljava/lang/Object;
      #44 (Ljava/lang/Object;)Ljava/lang/Object;
      #52 1
  1: #59 REF_invokeStatic java/lang/invoke/LambdaMetafactory.altMetafactory:(Ljava/lang/invoke/MethodHandles$Lookup;Ljava/lang/String;Ljava/lang/invoke/MethodType;[Ljava/lang/Object;)Ljava/lang/invoke/CallSite;
    Method arguments:
      #44 (Ljava/lang/Object;)Ljava/lang/Object;
      #69 REF_invokeStatic scala/Function1.$anonfun$compose$1:(Lscala/Function1;Lscala/Function1;Ljava/lang/Object;)Ljava/lang/Object;
      #44 (Ljava/lang/Object;)Ljava/lang/Object;
      #52 1
  2: #143 REF_invokeStatic scala/runtime/LambdaDeserialize.bootstrap:(Ljava/lang/invoke/MethodHandles$Lookup;Ljava/lang/String;Ljava/lang/invoke/MethodType;[Ljava/lang/invoke/MethodHandle;)Ljava/lang/invoke/CallSite;
    Method arguments:
      #51 REF_invokeStatic scala/Function1.$anonfun$andThen$1:(Lscala/Function1;Lscala/Function1;Ljava/lang/Object;)Ljava/lang/Object;
      #69 REF_invokeStatic scala/Function1.$anonfun$compose$1:(Lscala/Function1;Lscala/Function1;Ljava/lang/Object;)Ljava/lang/Object;
  ScalaInlineInfo: length = 0x4A (unknown attribute)
   01 01 00 0E 00 23 00 81 01 00 23 00 24 01 00 69
   00 6A 01 00 52 00 22 01 00 53 00 4F 01 00 7B 00
   6A 01 00 71 00 5A 01 00 12 00 4F 01 00 59 00 5A
   01 00 5B 00 5C 01 00 6C 00 6D 01 00 47 00 48 01
   00 64 00 48 01 00 56 00 4F 01
  ScalaSig: length = 0x3 (unknown attribute)
   05 02 00
