Classfile /Users/mw/Projects/slang-braindump/.jar/jar11/assemble/slang-braindump/assemble/content/shapeless/syntax/SingletonOps.class
  Last modified May 29, 2022; size 1966 bytes
  SHA-256 checksum 4442227ffd2010614a779fd875962fa87e07b8048e03bda4289c1f81c89bc4c0
  Compiled from "singletons.scala"
public interface shapeless.syntax.SingletonOps
  minor version: 0
  major version: 52
  flags: (0x0601) ACC_PUBLIC, ACC_INTERFACE, ACC_ABSTRACT
  this_class: #2                          // shapeless/syntax/SingletonOps
  super_class: #4                         // java/lang/Object
  interfaces: 0, fields: 0, methods: 6, attributes: 5
Constant pool:
   #1 = Utf8               shapeless/syntax/SingletonOps
   #2 = Class              #1             // shapeless/syntax/SingletonOps
   #3 = Utf8               java/lang/Object
   #4 = Class              #3             // java/lang/Object
   #5 = Utf8               singletons.scala
   #6 = Utf8               Lscala/reflect/ScalaSignature;
   #7 = Utf8               bytes
   #8 = Utf8               \u0006\u0005\u00053qAB\u0004\u0011\u0002\u0007\u0005A\u0002C\u0003\u0014\u0001\u0011\u0005A\u0003B\u0003\u0019\u0001\t\u0005\u0011\u0004C\u0004!\u0001\t\u0007i\u0011A\u0011\t\u000b1\u0002A\u0011A\u0017\t\u000bE\u0002A\u0011\u0001\u001a\u0003\u0019MKgn\u001a7fi>tw\n]:\u000b\u0005!I\u0011AB:z]R\f\u0007PC\u0001\u000b\u0003%\u0019\b.\u00199fY\u0016\u001c8o\u0001\u0001\u0014\u0005\u0001i\u0001C\u0001\b\u0012\u001b\u0005y!\"\u0001\t\u0002\u000bM\u001c\u0017\r\\1\n\u0005Iy!AB!osJ+g-\u0001\u0004%S:LG\u000f\n\u000b\u0002+A\u0011aBF\u0005\u0003/=\u0011A!\u00168ji\n\tA+\u0005\u0002\u001b;A\u0011abG\u0005\u00039=\u0011qAT8uQ&tw\r\u0005\u0002\u000f=%\u0011qd\u0004\u0002\u0004\u0003:L\u0018aB<ji:,7o]\u000b\u0002EA\u00191e\n\u0016\u000f\u0005\u0011*S\"A\u0005\n\u0005\u0019J\u0011aB,ji:,7o]\u0005\u0003Q%\u00121!Q;y\u0015\t1\u0013\u0002\u0005\u0002,\u00055\t\u0001!\u0001\u0004oCJ\u0014xn^\u000b\u0002]I\u0011qF\u000b\u0004\u0005a\u0001\u0001aF\u0001\u0007=e\u00164\u0017N\\3nK:$h(\u0001\f%[&tWo\u001d\u0013he\u0016\fG/\u001a:%OJ,\u0017\r^3s+\t\u0019T\b\u0006\u00025\u007fA!Q\u0007\u000f\u0016<\u001d\t!c\'\u0003\u00028\u0013\u0005AA.\u00192fY2,G-\u0003\u0002:u\tIa)[3mIRK\b/\u001a\u0006\u0003o%\u0001\"\u0001P\u001f\r\u0001\u0011)a(\u0002b\u00013\t\ta\u000bC\u0003A\u000b\u0001\u00071(A\u0001w\u0001
   #9 = Utf8               shapeless/labelled$FieldBuilder
  #10 = Class              #9             // shapeless/labelled$FieldBuilder
  #11 = Utf8               shapeless/labelled
  #12 = Class              #11            // shapeless/labelled
  #13 = Utf8               FieldBuilder
  #14 = Utf8               witness
  #15 = Utf8               ()Lshapeless/Witness;
  #16 = Utf8               narrow$
  #17 = Utf8               (Lshapeless/syntax/SingletonOps;)Ljava/lang/Object;
  #18 = Utf8               $this
  #19 = Utf8               narrow
  #20 = Utf8               ()Ljava/lang/Object;
  #21 = NameAndType        #19:#20        // narrow:()Ljava/lang/Object;
  #22 = InterfaceMethodref #2.#21         // shapeless/syntax/SingletonOps.narrow:()Ljava/lang/Object;
  #23 = Utf8               Lshapeless/syntax/SingletonOps;
  #24 = NameAndType        #14:#15        // witness:()Lshapeless/Witness;
  #25 = InterfaceMethodref #2.#24         // shapeless/syntax/SingletonOps.witness:()Lshapeless/Witness;
  #26 = Utf8               shapeless/Witness
  #27 = Class              #26            // shapeless/Witness
  #28 = Utf8               value
  #29 = NameAndType        #28:#20        // value:()Ljava/lang/Object;
  #30 = InterfaceMethodref #27.#29        // shapeless/Witness.value:()Ljava/lang/Object;
  #31 = Utf8               this
  #32 = Utf8               $minus$greater$greater$
  #33 = Utf8               (Lshapeless/syntax/SingletonOps;Ljava/lang/Object;)Ljava/lang/Object;
  #34 = Utf8               v
  #35 = Utf8               $minus$greater$greater
  #36 = Utf8               (Ljava/lang/Object;)Ljava/lang/Object;
  #37 = NameAndType        #35:#36        // $minus$greater$greater:(Ljava/lang/Object;)Ljava/lang/Object;
  #38 = InterfaceMethodref #2.#37         // shapeless/syntax/SingletonOps.$minus$greater$greater:(Ljava/lang/Object;)Ljava/lang/Object;
  #39 = Utf8               Ljava/lang/Object;
  #40 = Utf8               <V:Ljava/lang/Object;>(TV;)TV;
  #41 = Utf8               shapeless/labelled$
  #42 = Class              #41            // shapeless/labelled$
  #43 = Utf8               MODULE$
  #44 = Utf8               Lshapeless/labelled$;
  #45 = NameAndType        #43:#44        // MODULE$:Lshapeless/labelled$;
  #46 = Fieldref           #42.#45        // shapeless/labelled$.MODULE$:Lshapeless/labelled$;
  #47 = Utf8               field
  #48 = Utf8               ()Lshapeless/labelled$FieldBuilder;
  #49 = NameAndType        #47:#48        // field:()Lshapeless/labelled$FieldBuilder;
  #50 = Methodref          #42.#49        // shapeless/labelled$.field:()Lshapeless/labelled$FieldBuilder;
  #51 = Utf8               apply
  #52 = NameAndType        #51:#36        // apply:(Ljava/lang/Object;)Ljava/lang/Object;
  #53 = Methodref          #10.#52        // shapeless/labelled$FieldBuilder.apply:(Ljava/lang/Object;)Ljava/lang/Object;
  #54 = Utf8               $init$
  #55 = Utf8               (Lshapeless/syntax/SingletonOps;)V
  #56 = Utf8               Code
  #57 = Utf8               LineNumberTable
  #58 = Utf8               LocalVariableTable
  #59 = Utf8               MethodParameters
  #60 = Utf8               Signature
  #61 = Utf8               InnerClasses
  #62 = Utf8               SourceFile
  #63 = Utf8               RuntimeVisibleAnnotations
  #64 = Utf8               ScalaInlineInfo
  #65 = Utf8               ScalaSig
{
  public abstract shapeless.Witness witness();
    descriptor: ()Lshapeless/Witness;
    flags: (0x0401) ACC_PUBLIC, ACC_ABSTRACT

  public static java.lang.Object narrow$(shapeless.syntax.SingletonOps);
    descriptor: (Lshapeless/syntax/SingletonOps;)Ljava/lang/Object;
    flags: (0x1009) ACC_PUBLIC, ACC_STATIC, ACC_SYNTHETIC
    Code:
      stack=1, locals=1, args_size=1
         0: aload_0
         1: invokespecial #22                 // InterfaceMethod narrow:()Ljava/lang/Object;
         4: areturn
      LineNumberTable:
        line 42: 0
      LocalVariableTable:
        Start  Length  Slot  Name   Signature
            0       5     0 $this   Lshapeless/syntax/SingletonOps;
    MethodParameters:
      Name                           Flags
      $this                          final synthetic

  public default java.lang.Object narrow();
    descriptor: ()Ljava/lang/Object;
    flags: (0x0001) ACC_PUBLIC
    Code:
      stack=1, locals=1, args_size=1
         0: aload_0
         1: invokeinterface #25,  1           // InterfaceMethod witness:()Lshapeless/Witness;
         6: invokeinterface #30,  1           // InterfaceMethod shapeless/Witness.value:()Ljava/lang/Object;
        11: areturn
      LineNumberTable:
        line 42: 0
      LocalVariableTable:
        Start  Length  Slot  Name   Signature
            0      12     0  this   Lshapeless/syntax/SingletonOps;

  public static java.lang.Object $minus$greater$greater$(shapeless.syntax.SingletonOps, java.lang.Object);
    descriptor: (Lshapeless/syntax/SingletonOps;Ljava/lang/Object;)Ljava/lang/Object;
    flags: (0x1009) ACC_PUBLIC, ACC_STATIC, ACC_SYNTHETIC
    Code:
      stack=2, locals=2, args_size=2
         0: aload_0
         1: aload_1
         2: invokespecial #38                 // InterfaceMethod $minus$greater$greater:(Ljava/lang/Object;)Ljava/lang/Object;
         5: areturn
      LineNumberTable:
        line 47: 0
      LocalVariableTable:
        Start  Length  Slot  Name   Signature
            0       6     0 $this   Lshapeless/syntax/SingletonOps;
            0       6     1     v   Ljava/lang/Object;
    MethodParameters:
      Name                           Flags
      $this                          final synthetic
      v                              final

  public default <V extends java.lang.Object> V $minus$greater$greater(V);
    descriptor: (Ljava/lang/Object;)Ljava/lang/Object;
    flags: (0x0001) ACC_PUBLIC
    Code:
      stack=2, locals=2, args_size=2
         0: getstatic     #46                 // Field shapeless/labelled$.MODULE$:Lshapeless/labelled$;
         3: invokevirtual #50                 // Method shapeless/labelled$.field:()Lshapeless/labelled$FieldBuilder;
         6: aload_1
         7: invokevirtual #53                 // Method shapeless/labelled$FieldBuilder.apply:(Ljava/lang/Object;)Ljava/lang/Object;
        10: areturn
      LineNumberTable:
        line 47: 0
      LocalVariableTable:
        Start  Length  Slot  Name   Signature
            0      11     0  this   Lshapeless/syntax/SingletonOps;
            0      11     1     v   Ljava/lang/Object;
    Signature: #40                          // <V:Ljava/lang/Object;>(TV;)TV;
    MethodParameters:
      Name                           Flags
      v                              final

  public static void $init$(shapeless.syntax.SingletonOps);
    descriptor: (Lshapeless/syntax/SingletonOps;)V
    flags: (0x0009) ACC_PUBLIC, ACC_STATIC
    Code:
      stack=0, locals=1, args_size=1
         0: return
      LineNumberTable:
        line 29: 0
      LocalVariableTable:
        Start  Length  Slot  Name   Signature
            0       1     0 $this   Lshapeless/syntax/SingletonOps;
    MethodParameters:
      Name                           Flags
      $this                          final synthetic
}
InnerClasses:
  public static #13= #10 of #12;          // FieldBuilder=class shapeless/labelled$FieldBuilder of class shapeless/labelled
SourceFile: "singletons.scala"
RuntimeVisibleAnnotations:
  0: #6(#7=s#8)
    scala.reflect.ScalaSignature(
      bytes="\u0006\u0005\u00053qAB\u0004\u0011\u0002\u0007\u0005A\u0002C\u0003\u0014\u0001\u0011\u0005A\u0003B\u0003\u0019\u0001\t\u0005\u0011\u0004C\u0004!\u0001\t\u0007i\u0011A\u0011\t\u000b1\u0002A\u0011A\u0017\t\u000bE\u0002A\u0011\u0001\u001a\u0003\u0019MKgn\u001a7fi>tw\n]:\u000b\u0005!I\u0011AB:z]R\f\u0007PC\u0001\u000b\u0003%\u0019\b.\u00199fY\u0016\u001c8o\u0001\u0001\u0014\u0005\u0001i\u0001C\u0001\b\u0012\u001b\u0005y!\"\u0001\t\u0002\u000bM\u001c\u0017\r\\1\n\u0005Iy!AB!osJ+g-\u0001\u0004%S:LG\u000f\n\u000b\u0002+A\u0011aBF\u0005\u0003/=\u0011A!\u00168ji\n\tA+\u0005\u0002\u001b;A\u0011abG\u0005\u00039=\u0011qAT8uQ&tw\r\u0005\u0002\u000f=%\u0011qd\u0004\u0002\u0004\u0003:L\u0018aB<ji:,7o]\u000b\u0002EA\u00191e\n\u0016\u000f\u0005\u0011*S\"A\u0005\n\u0005\u0019J\u0011aB,ji:,7o]\u0005\u0003Q%\u00121!Q;y\u0015\t1\u0013\u0002\u0005\u0002,\u00055\t\u0001!\u0001\u0004oCJ\u0014xn^\u000b\u0002]I\u0011qF\u000b\u0004\u0005a\u0001\u0001aF\u0001\u0007=e\u00164\u0017N\\3nK:$h(\u0001\f%[&tWo\u001d\u0013he\u0016\fG/\u001a:%OJ,\u0017\r^3s+\t\u0019T\b\u0006\u00025\u007fA!Q\u0007\u000f\u0016<\u001d\t!c\'\u0003\u00028\u0013\u0005AA.\u00192fY2,G-\u0003\u0002:u\tIa)[3mIRK\b/\u001a\u0006\u0003o%\u0001\"\u0001P\u001f\r\u0001\u0011)a(\u0002b\u00013\t\ta\u000bC\u0003A\u000b\u0001\u00071(A\u0001w\u0001"
    )
  ScalaInlineInfo: length = 0x22 (unknown attribute)
   01 00 00 06 00 36 00 37 01 00 20 00 21 01 00 23
   00 24 00 00 10 00 11 01 00 13 00 14 00 00 0E 00
   0F 00
  ScalaSig: length = 0x3 (unknown attribute)
   05 02 00
