Classfile /Users/mw/Projects/slang-braindump/.jar/jar11/assemble/slang-braindump/assemble/content/shapeless/syntax/unwrapped.class
  Last modified May 29, 2022; size 1669 bytes
  SHA-256 checksum 6f72f1d33271d620b8e58390ecde6175ecacbd5f6c0a34192df8138b17972bf2
  Compiled from "unwrapped.scala"
public final class shapeless.syntax.unwrapped
  minor version: 0
  major version: 52
  flags: (0x0031) ACC_PUBLIC, ACC_FINAL, ACC_SUPER
  this_class: #2                          // shapeless/syntax/unwrapped
  super_class: #4                         // java/lang/Object
  interfaces: 0, fields: 0, methods: 1, attributes: 4
Constant pool:
   #1 = Utf8               shapeless/syntax/unwrapped
   #2 = Class              #1             // shapeless/syntax/unwrapped
   #3 = Utf8               java/lang/Object
   #4 = Class              #3             // java/lang/Object
   #5 = Utf8               unwrapped.scala
   #6 = Utf8               Lscala/reflect/ScalaSignature;
   #7 = Utf8               bytes
   #8 = Utf8               \u0006\u0005\u0005%r!B\n\u0015\u0011\u0003Ib!B\u000e\u0015\u0011\u0003a\u0002\"B\u0012\u0002\t\u0003!c\u0001B\u0013\u0002\u0007\u0019B\u0001bK\u0002\u0003\u0006\u0004%\t\u0001\f\u0005\tq\r\u0011\t\u0011)A\u0005[!)1e\u0001C\u0001s!)Qh\u0001C\u0001}!)Qj\u0001C\u0001\u001d\"9QkAA\u0001\n\u00032\u0006b\u0002.\u0004\u0003\u0003%\te\u0017\u0005\bC\u0006\t\t\u0011b\u0001c\u000f\u001d\t\u0017!!A\t\u0002!4q!J\u0001\u0002\u0002#\u0005\u0011\u000eC\u0003$\u001b\u0011\u0005!\u000eC\u0003l\u001b\u0011\u0015A\u000eC\u0003y\u001b\u0011\u0015\u0011\u0010C\u0005\u0002\n5\t\t\u0011\"\u0002\u0002\f!I\u0011qC\u0007\u0002\u0002\u0013\u0015\u0011\u0011D\u0001\nk:<(/\u00199qK\u0012T!!\u0006\f\u0002\rMLh\u000e^1y\u0015\u00059\u0012!C:iCB,G.Z:t\u0007\u0001\u0001\"AG\u0001\u000e\u0003Q\u0011\u0011\"\u001e8xe\u0006\u0004\b/\u001a3\u0014\u0005\u0005i\u0002C\u0001\u0010\"\u001b\u0005y\"\"\u0001\u0011\u0002\u000bM\u001c\u0017\r\\1\n\u0005\tz\"AB!osJ+g-\u0001\u0004=S:LGO\u0010\u000b\u00023\tyQK\\<sCB\u0004X\rZ*z]R\f\u00070\u0006\u0002(_M\u00111\u0001\u000b\t\u0003=%J!AK\u0010\u0003\r\u0005s\u0017PV1m\u0003\u0005!X#A\u0017\u0011\u00059zC\u0002\u0001\u0003\u0006a\r\u0011\r!\r\u0002\u0002)F\u0011!\'\u000e\t\u0003=MJ!\u0001N\u0010\u0003\u000f9{G\u000f[5oOB\u0011aDN\u0005\u0003o}\u00111!\u00118z\u0003\t!\b\u0005\u0006\u0002;yA\u00191hA\u0017\u000e\u0003\u0005AQa\u000b\u0004A\u00025\na!\u001e8xe\u0006\u0004XCA B)\t\u00015\t\u0005\u0002/\u0003\u0012)!i\u0002b\u0001c\t\tQ\u000bC\u0003E\u000f\u0001\u000fQ)\u0001\u0002voB!aIS\u0017A\u001d\t9\u0005*D\u0001\u0017\u0013\tIe#A\u0005V]^\u0014\u0018\r\u001d9fI&\u00111\n\u0014\u0002\u0004\u0003VD(BA%\u0017\u0003\u00119(/\u00199\u0016\u0005=\u000bFC\u0001)T!\tq\u0013\u000bB\u0003S\u0011\t\u0007\u0011GA\u0001X\u0011\u0015!\u0005\u0002q\u0001U!\u00111%\nU\u0017\u0002\u0011!\f7\u000f[\"pI\u0016$\u0012a\u0016\t\u0003=aK!!W\u0010\u0003\u0007%sG/\u0001\u0004fcV\fGn\u001d\u000b\u00039~\u0003\"AH/\n\u0005y{\"a\u0002\"p_2,\u0017M\u001c\u0005\bA*\t\t\u00111\u00016\u0003\rAH%M\u0001\u0010+:<(/\u00199qK\u0012\u001c\u0016P\u001c;bqV\u00111M\u001a\u000b\u0003I\u001e\u00042aO\u0002f!\tqc\rB\u00031\u0017\t\u0007\u0011\u0007C\u0003,\u0017\u0001\u0007Q\r\u0005\u0002<\u001bM\u0011Q\"\b\u000b\u0002Q\u0006\u0001RO\\<sCB$S\r\u001f;f]NLwN\\\u000b\u0004[B$HC\u00018v)\ty\u0017\u000f\u0005\u0002/a\u0012)!i\u0004b\u0001c!)Ai\u0004a\u0002eB!aIS:p!\tqC\u000fB\u00031\u001f\t\u0007\u0011\u0007C\u0003w\u001f\u0001\u0007q/A\u0003%i\"L7\u000fE\u0002<\u0007M\fab\u001e:ba\u0012*\u0007\u0010^3og&|g.\u0006\u0003{{\u0006\rAcA>\u0002\u0006Q\u0011AP \t\u0003]u$QA\u0015\tC\u0002EBQ\u0001\u0012\tA\u0004}\u0004RA\u0012&}\u0003\u0003\u00012ALA\u0002\t\u0015\u0001\u0004C1\u00012\u0011\u00191\b\u00031\u0001\u0002\bA!1hAA\u0001\u0003IA\u0017m\u001d5D_\u0012,G%\u001a=uK:\u001c\u0018n\u001c8\u0016\t\u00055\u0011Q\u0003\u000b\u0004-\u0006=\u0001B\u0002<\u0012\u0001\u0004\t\t\u0002\u0005\u0003<\u0007\u0005M\u0001c\u0001\u0018\u0002\u0016\u0011)\u0001\'\u0005b\u0001c\u0005\u0001R-];bYN$S\r\u001f;f]NLwN\\\u000b\u0005\u00037\t9\u0003\u0006\u0003\u0002\u001e\u0005\u0005Bc\u0001/\u0002 !9\u0001MEA\u0001\u0002\u0004)\u0004B\u0002<\u0013\u0001\u0004\t\u0019\u0003\u0005\u0003<\u0007\u0005\u0015\u0002c\u0001\u0018\u0002(\u0011)\u0001G\u0005b\u0001c\u0001
   #9 = Utf8               shapeless/syntax/unwrapped$UnwrappedSyntax
  #10 = Class              #9             // shapeless/syntax/unwrapped$UnwrappedSyntax
  #11 = Utf8               UnwrappedSyntax
  #12 = Utf8               shapeless/syntax/unwrapped$UnwrappedSyntax$
  #13 = Class              #12            // shapeless/syntax/unwrapped$UnwrappedSyntax$
  #14 = Utf8               UnwrappedSyntax$
  #15 = Utf8               (Ljava/lang/Object;)Ljava/lang/Object;
  #16 = Utf8               t
  #17 = Utf8               shapeless/syntax/unwrapped$
  #18 = Class              #17            // shapeless/syntax/unwrapped$
  #19 = Utf8               MODULE$
  #20 = Utf8               Lshapeless/syntax/unwrapped$;
  #21 = NameAndType        #19:#20        // MODULE$:Lshapeless/syntax/unwrapped$;
  #22 = Fieldref           #18.#21        // shapeless/syntax/unwrapped$.MODULE$:Lshapeless/syntax/unwrapped$;
  #23 = NameAndType        #11:#15        // UnwrappedSyntax:(Ljava/lang/Object;)Ljava/lang/Object;
  #24 = Methodref          #18.#23        // shapeless/syntax/unwrapped$.UnwrappedSyntax:(Ljava/lang/Object;)Ljava/lang/Object;
  #25 = Utf8               Code
  #26 = Utf8               MethodParameters
  #27 = Utf8               InnerClasses
  #28 = Utf8               SourceFile
  #29 = Utf8               RuntimeVisibleAnnotations
  #30 = Utf8               ScalaSig
{
  public static java.lang.Object UnwrappedSyntax(java.lang.Object);
    descriptor: (Ljava/lang/Object;)Ljava/lang/Object;
    flags: (0x0009) ACC_PUBLIC, ACC_STATIC
    Code:
      stack=2, locals=1, args_size=1
         0: getstatic     #22                 // Field shapeless/syntax/unwrapped$.MODULE$:Lshapeless/syntax/unwrapped$;
         3: aload_0
         4: invokevirtual #24                 // Method shapeless/syntax/unwrapped$.UnwrappedSyntax:(Ljava/lang/Object;)Ljava/lang/Object;
         7: areturn
    MethodParameters:
      Name                           Flags
      t                              final
}
InnerClasses:
  public static final #11= #10 of #2;     // UnwrappedSyntax=class shapeless/syntax/unwrapped$UnwrappedSyntax of class shapeless/syntax/unwrapped
  public static #14= #13 of #2;           // UnwrappedSyntax$=class shapeless/syntax/unwrapped$UnwrappedSyntax$ of class shapeless/syntax/unwrapped
SourceFile: "unwrapped.scala"
RuntimeVisibleAnnotations:
  0: #6(#7=s#8)
    scala.reflect.ScalaSignature(
      bytes="\u0006\u0005\u0005%r!B\n\u0015\u0011\u0003Ib!B\u000e\u0015\u0011\u0003a\u0002\"B\u0012\u0002\t\u0003!c\u0001B\u0013\u0002\u0007\u0019B\u0001bK\u0002\u0003\u0006\u0004%\t\u0001\f\u0005\tq\r\u0011\t\u0011)A\u0005[!)1e\u0001C\u0001s!)Qh\u0001C\u0001}!)Qj\u0001C\u0001\u001d\"9QkAA\u0001\n\u00032\u0006b\u0002.\u0004\u0003\u0003%\te\u0017\u0005\bC\u0006\t\t\u0011b\u0001c\u000f\u001d\t\u0017!!A\t\u0002!4q!J\u0001\u0002\u0002#\u0005\u0011\u000eC\u0003$\u001b\u0011\u0005!\u000eC\u0003l\u001b\u0011\u0015A\u000eC\u0003y\u001b\u0011\u0015\u0011\u0010C\u0005\u0002\n5\t\t\u0011\"\u0002\u0002\f!I\u0011qC\u0007\u0002\u0002\u0013\u0015\u0011\u0011D\u0001\nk:<(/\u00199qK\u0012T!!\u0006\f\u0002\rMLh\u000e^1y\u0015\u00059\u0012!C:iCB,G.Z:t\u0007\u0001\u0001\"AG\u0001\u000e\u0003Q\u0011\u0011\"\u001e8xe\u0006\u0004\b/\u001a3\u0014\u0005\u0005i\u0002C\u0001\u0010\"\u001b\u0005y\"\"\u0001\u0011\u0002\u000bM\u001c\u0017\r\\1\n\u0005\tz\"AB!osJ+g-\u0001\u0004=S:LGO\u0010\u000b\u00023\tyQK\\<sCB\u0004X\rZ*z]R\f\u00070\u0006\u0002(_M\u00111\u0001\u000b\t\u0003=%J!AK\u0010\u0003\r\u0005s\u0017PV1m\u0003\u0005!X#A\u0017\u0011\u00059zC\u0002\u0001\u0003\u0006a\r\u0011\r!\r\u0002\u0002)F\u0011!\'\u000e\t\u0003=MJ!\u0001N\u0010\u0003\u000f9{G\u000f[5oOB\u0011aDN\u0005\u0003o}\u00111!\u00118z\u0003\t!\b\u0005\u0006\u0002;yA\u00191hA\u0017\u000e\u0003\u0005AQa\u000b\u0004A\u00025\na!\u001e8xe\u0006\u0004XCA B)\t\u00015\t\u0005\u0002/\u0003\u0012)!i\u0002b\u0001c\t\tQ\u000bC\u0003E\u000f\u0001\u000fQ)\u0001\u0002voB!aIS\u0017A\u001d\t9\u0005*D\u0001\u0017\u0013\tIe#A\u0005V]^\u0014\u0018\r\u001d9fI&\u00111\n\u0014\u0002\u0004\u0003VD(BA%\u0017\u0003\u00119(/\u00199\u0016\u0005=\u000bFC\u0001)T!\tq\u0013\u000bB\u0003S\u0011\t\u0007\u0011GA\u0001X\u0011\u0015!\u0005\u0002q\u0001U!\u00111%\nU\u0017\u0002\u0011!\f7\u000f[\"pI\u0016$\u0012a\u0016\t\u0003=aK!!W\u0010\u0003\u0007%sG/\u0001\u0004fcV\fGn\u001d\u000b\u00039~\u0003\"AH/\n\u0005y{\"a\u0002\"p_2,\u0017M\u001c\u0005\bA*\t\t\u00111\u00016\u0003\rAH%M\u0001\u0010+:<(/\u00199qK\u0012\u001c\u0016P\u001c;bqV\u00111M\u001a\u000b\u0003I\u001e\u00042aO\u0002f!\tqc\rB\u00031\u0017\t\u0007\u0011\u0007C\u0003,\u0017\u0001\u0007Q\r\u0005\u0002<\u001bM\u0011Q\"\b\u000b\u0002Q\u0006\u0001RO\\<sCB$S\r\u001f;f]NLwN\\\u000b\u0004[B$HC\u00018v)\ty\u0017\u000f\u0005\u0002/a\u0012)!i\u0004b\u0001c!)Ai\u0004a\u0002eB!aIS:p!\tqC\u000fB\u00031\u001f\t\u0007\u0011\u0007C\u0003w\u001f\u0001\u0007q/A\u0003%i\"L7\u000fE\u0002<\u0007M\fab\u001e:ba\u0012*\u0007\u0010^3og&|g.\u0006\u0003{{\u0006\rAcA>\u0002\u0006Q\u0011AP \t\u0003]u$QA\u0015\tC\u0002EBQ\u0001\u0012\tA\u0004}\u0004RA\u0012&}\u0003\u0003\u00012ALA\u0002\t\u0015\u0001\u0004C1\u00012\u0011\u00191\b\u00031\u0001\u0002\bA!1hAA\u0001\u0003IA\u0017m\u001d5D_\u0012,G%\u001a=uK:\u001c\u0018n\u001c8\u0016\t\u00055\u0011Q\u0003\u000b\u0004-\u0006=\u0001B\u0002<\u0012\u0001\u0004\t\t\u0002\u0005\u0003<\u0007\u0005M\u0001c\u0001\u0018\u0002\u0016\u0011)\u0001\'\u0005b\u0001c\u0005\u0001R-];bYN$S\r\u001f;f]NLwN\\\u000b\u0005\u00037\t9\u0003\u0006\u0003\u0002\u001e\u0005\u0005Bc\u0001/\u0002 !9\u0001MEA\u0001\u0002\u0004)\u0004B\u0002<\u0013\u0001\u0004\t\u0019\u0003\u0005\u0003<\u0007\u0005\u0015\u0002c\u0001\u0018\u0002(\u0011)\u0001G\u0005b\u0001c\u0001"
    )
  ScalaSig: length = 0x3 (unknown attribute)
   05 02 00
