Classfile /Users/mw/Projects/slang-braindump/.jar/jar11/assemble/slang-braindump/assemble/content/coursier/core/shaded/fastparse/CharPredicates$.class
  Last modified May 29, 2022; size 1811 bytes
  SHA-256 checksum bef96493188f853ac61c776da74b2bc8e5622a8b47518ac1d58c878c8724280d
  Compiled from "CharPredicates.scala"
public final class coursier.core.shaded.fastparse.CharPredicates$
  minor version: 0
  major version: 52
  flags: (0x0031) ACC_PUBLIC, ACC_FINAL, ACC_SUPER
  this_class: #2                          // coursier/core/shaded/fastparse/CharPredicates$
  super_class: #4                         // java/lang/Object
  interfaces: 0, fields: 1, methods: 9, attributes: 4
Constant pool:
   #1 = Utf8               coursier/core/shaded/fastparse/CharPredicates$
   #2 = Class              #1             // coursier/core/shaded/fastparse/CharPredicates$
   #3 = Utf8               java/lang/Object
   #4 = Class              #3             // java/lang/Object
   #5 = Utf8               CharPredicates.scala
   #6 = Utf8               java/lang/Character$UnicodeBlock
   #7 = Class              #6             // java/lang/Character$UnicodeBlock
   #8 = Utf8               java/lang/Character
   #9 = Class              #8             // java/lang/Character
  #10 = Utf8               UnicodeBlock
  #11 = Utf8               MODULE$
  #12 = Utf8               Lcoursier/core/shaded/fastparse/CharPredicates$;
  #13 = Utf8               <clinit>
  #14 = Utf8               ()V
  #15 = Utf8               <init>
  #16 = NameAndType        #15:#14        // "<init>":()V
  #17 = Methodref          #2.#16         // coursier/core/shaded/fastparse/CharPredicates$."<init>":()V
  #18 = NameAndType        #11:#12        // MODULE$:Lcoursier/core/shaded/fastparse/CharPredicates$;
  #19 = Fieldref           #2.#18         // coursier/core/shaded/fastparse/CharPredicates$.MODULE$:Lcoursier/core/shaded/fastparse/CharPredicates$;
  #20 = Utf8               isMathSymbol
  #21 = Utf8               (C)Z
  #22 = Utf8               c
  #23 = Utf8               getType
  #24 = Utf8               (C)I
  #25 = NameAndType        #23:#24        // getType:(C)I
  #26 = Methodref          #9.#25         // java/lang/Character.getType:(C)I
  #27 = Utf8               this
  #28 = Utf8               C
  #29 = Utf8               isOtherSymbol
  #30 = Utf8               isLetter
  #31 = Utf8               isPrintableChar
  #32 = Utf8               of
  #33 = Utf8               (C)Ljava/lang/Character$UnicodeBlock;
  #34 = NameAndType        #32:#33        // of:(C)Ljava/lang/Character$UnicodeBlock;
  #35 = Methodref          #7.#34         // java/lang/Character$UnicodeBlock.of:(C)Ljava/lang/Character$UnicodeBlock;
  #36 = Utf8               isISOControl
  #37 = NameAndType        #36:#21        // isISOControl:(C)Z
  #38 = Methodref          #9.#37         // java/lang/Character.isISOControl:(C)Z
  #39 = Utf8               isSurrogate
  #40 = NameAndType        #39:#21        // isSurrogate:(C)Z
  #41 = Methodref          #9.#40         // java/lang/Character.isSurrogate:(C)Z
  #42 = Utf8               SPECIALS
  #43 = Utf8               Ljava/lang/Character$UnicodeBlock;
  #44 = NameAndType        #42:#43        // SPECIALS:Ljava/lang/Character$UnicodeBlock;
  #45 = Fieldref           #7.#44         // java/lang/Character$UnicodeBlock.SPECIALS:Ljava/lang/Character$UnicodeBlock;
  #46 = Utf8               equals
  #47 = Utf8               (Ljava/lang/Object;)Z
  #48 = NameAndType        #46:#47        // equals:(Ljava/lang/Object;)Z
  #49 = Methodref          #4.#48         // java/lang/Object.equals:(Ljava/lang/Object;)Z
  #50 = Utf8               block
  #51 = Utf8               isDigit
  #52 = NameAndType        #51:#21        // isDigit:(C)Z
  #53 = Methodref          #9.#52         // java/lang/Character.isDigit:(C)Z
  #54 = Utf8               isLower
  #55 = Utf8               isLowerCase
  #56 = NameAndType        #55:#21        // isLowerCase:(C)Z
  #57 = Methodref          #9.#56         // java/lang/Character.isLowerCase:(C)Z
  #58 = Utf8               isUpper
  #59 = Utf8               isUpperCase
  #60 = NameAndType        #59:#21        // isUpperCase:(C)Z
  #61 = Methodref          #9.#60         // java/lang/Character.isUpperCase:(C)Z
  #62 = Methodref          #4.#16         // java/lang/Object."<init>":()V
  #63 = Utf8               Code
  #64 = Utf8               LineNumberTable
  #65 = Utf8               StackMapTable
  #66 = Utf8               LocalVariableTable
  #67 = Utf8               MethodParameters
  #68 = Utf8               InnerClasses
  #69 = Utf8               SourceFile
  #70 = Utf8               ScalaInlineInfo
  #71 = Utf8               Scala
{
  public static final coursier.core.shaded.fastparse.CharPredicates$ MODULE$;
    descriptor: Lcoursier/core/shaded/fastparse/CharPredicates$;
    flags: (0x0019) ACC_PUBLIC, ACC_STATIC, ACC_FINAL

  public static {};
    descriptor: ()V
    flags: (0x0009) ACC_PUBLIC, ACC_STATIC
    Code:
      stack=2, locals=0, args_size=0
         0: new           #2                  // class coursier/core/shaded/fastparse/CharPredicates$
         3: dup
         4: invokespecial #17                 // Method "<init>":()V
         7: putstatic     #19                 // Field MODULE$:Lcoursier/core/shaded/fastparse/CharPredicates$;
        10: return
      LineNumberTable:
        line 12: 0

  public boolean isMathSymbol(char);
    descriptor: (C)Z
    flags: (0x0001) ACC_PUBLIC
    Code:
      stack=2, locals=2, args_size=2
         0: iload_1
         1: invokestatic  #26                 // Method java/lang/Character.getType:(C)I
         4: bipush        25
         6: if_icmpne     13
         9: iconst_1
        10: goto          14
        13: iconst_0
        14: ireturn
      StackMapTable: number_of_entries = 2
        frame_type = 13 /* same */
        frame_type = 64 /* same_locals_1_stack_item */
          stack = [ int ]
      LineNumberTable:
        line 14: 0
      LocalVariableTable:
        Start  Length  Slot  Name   Signature
            0      15     0  this   Lcoursier/core/shaded/fastparse/CharPredicates$;
            0      15     1     c   C
    MethodParameters:
      Name                           Flags
      c                              final

  public boolean isOtherSymbol(char);
    descriptor: (C)Z
    flags: (0x0001) ACC_PUBLIC
    Code:
      stack=2, locals=2, args_size=2
         0: iload_1
         1: invokestatic  #26                 // Method java/lang/Character.getType:(C)I
         4: bipush        28
         6: if_icmpne     13
         9: iconst_1
        10: goto          14
        13: iconst_0
        14: ireturn
      StackMapTable: number_of_entries = 2
        frame_type = 13 /* same */
        frame_type = 64 /* same_locals_1_stack_item */
          stack = [ int ]
      LineNumberTable:
        line 15: 0
      LocalVariableTable:
        Start  Length  Slot  Name   Signature
            0      15     0  this   Lcoursier/core/shaded/fastparse/CharPredicates$;
            0      15     1     c   C
    MethodParameters:
      Name                           Flags
      c                              final

  public boolean isLetter(char);
    descriptor: (C)Z
    flags: (0x0001) ACC_PUBLIC
    Code:
      stack=2, locals=2, args_size=2
         0: bipush        62
         2: iload_1
         3: invokestatic  #26                 // Method java/lang/Character.getType:(C)I
         6: ishr
         7: iconst_1
         8: iand
         9: iconst_0
        10: if_icmpeq     17
        13: iconst_1
        14: goto          18
        17: iconst_0
        18: ireturn
      StackMapTable: number_of_entries = 2
        frame_type = 17 /* same */
        frame_type = 64 /* same_locals_1_stack_item */
          stack = [ int ]
      LineNumberTable:
        line 20: 0
        line 21: 2
      LocalVariableTable:
        Start  Length  Slot  Name   Signature
            0      19     0  this   Lcoursier/core/shaded/fastparse/CharPredicates$;
            0      19     1     c   C
    MethodParameters:
      Name                           Flags
      c                              final

  public boolean isPrintableChar(char);
    descriptor: (C)Z
    flags: (0x0001) ACC_PUBLIC
    Code:
      stack=2, locals=4, args_size=2
         0: iload_1
         1: invokestatic  #35                 // Method java/lang/Character$UnicodeBlock.of:(C)Ljava/lang/Character$UnicodeBlock;
         4: astore_2
         5: iload_1
         6: invokestatic  #38                 // Method java/lang/Character.isISOControl:(C)Z
         9: ifne          51
        12: iload_1
        13: invokestatic  #41                 // Method java/lang/Character.isSurrogate:(C)Z
        16: ifne          51
        19: aload_2
        20: ifnull        51
        23: aload_2
        24: getstatic     #45                 // Field java/lang/Character$UnicodeBlock.SPECIALS:Ljava/lang/Character$UnicodeBlock;
        27: astore_3
        28: dup
        29: ifnonnull     40
        32: pop
        33: aload_3
        34: ifnull        51
        37: goto          47
        40: aload_3
        41: invokevirtual #49                 // Method java/lang/Object.equals:(Ljava/lang/Object;)Z
        44: ifne          51
        47: iconst_1
        48: goto          52
        51: iconst_0
        52: ireturn
      StackMapTable: number_of_entries = 4
        frame_type = 255 /* full_frame */
          offset_delta = 40
          locals = [ class coursier/core/shaded/fastparse/CharPredicates$, int, class java/lang/Character$UnicodeBlock, class java/lang/Character$UnicodeBlock ]
          stack = [ class java/lang/Character$UnicodeBlock ]
        frame_type = 6 /* same */
        frame_type = 250 /* chop */
          offset_delta = 3
        frame_type = 64 /* same_locals_1_stack_item */
          stack = [ int ]
      LineNumberTable:
        line 25: 0
        line 26: 5
        line 27: 12
        line 28: 19
        line 29: 23
      LocalVariableTable:
        Start  Length  Slot  Name   Signature
            4      48     2 block   Ljava/lang/Character$UnicodeBlock;
            0      53     0  this   Lcoursier/core/shaded/fastparse/CharPredicates$;
            0      53     1     c   C
    MethodParameters:
      Name                           Flags
      c                              final

  public boolean isDigit(char);
    descriptor: (C)Z
    flags: (0x0001) ACC_PUBLIC
    Code:
      stack=1, locals=2, args_size=2
         0: iload_1
         1: invokestatic  #53                 // Method java/lang/Character.isDigit:(C)Z
         4: ireturn
      LineNumberTable:
        line 31: 0
      LocalVariableTable:
        Start  Length  Slot  Name   Signature
            0       5     0  this   Lcoursier/core/shaded/fastparse/CharPredicates$;
            0       5     1     c   C
    MethodParameters:
      Name                           Flags
      c                              final

  public boolean isLower(char);
    descriptor: (C)Z
    flags: (0x0001) ACC_PUBLIC
    Code:
      stack=1, locals=2, args_size=2
         0: iload_1
         1: invokestatic  #57                 // Method java/lang/Character.isLowerCase:(C)Z
         4: ireturn
      LineNumberTable:
        line 32: 0
      LocalVariableTable:
        Start  Length  Slot  Name   Signature
            0       5     0  this   Lcoursier/core/shaded/fastparse/CharPredicates$;
            0       5     1     c   C
    MethodParameters:
      Name                           Flags
      c                              final

  public boolean isUpper(char);
    descriptor: (C)Z
    flags: (0x0001) ACC_PUBLIC
    Code:
      stack=1, locals=2, args_size=2
         0: iload_1
         1: invokestatic  #61                 // Method java/lang/Character.isUpperCase:(C)Z
         4: ireturn
      LineNumberTable:
        line 33: 0
      LocalVariableTable:
        Start  Length  Slot  Name   Signature
            0       5     0  this   Lcoursier/core/shaded/fastparse/CharPredicates$;
            0       5     1     c   C
    MethodParameters:
      Name                           Flags
      c                              final

  private coursier.core.shaded.fastparse.CharPredicates$();
    descriptor: ()V
    flags: (0x0002) ACC_PRIVATE
    Code:
      stack=1, locals=1, args_size=1
         0: aload_0
         1: invokespecial #62                 // Method java/lang/Object."<init>":()V
         4: return
      LineNumberTable:
        line 34: 0
        line 12: 4
      LocalVariableTable:
        Start  Length  Slot  Name   Signature
            0       5     0  this   Lcoursier/core/shaded/fastparse/CharPredicates$;
}
InnerClasses:
  public static final #10= #7 of #9;      // UnicodeBlock=class java/lang/Character$UnicodeBlock of class java/lang/Character
SourceFile: "CharPredicates.scala"
  ScalaInlineInfo: length = 0x2C (unknown attribute)
   01 01 00 08 00 0F 00 0E 01 00 33 00 15 01 00 1E
   00 15 01 00 36 00 15 01 00 14 00 15 01 00 1D 00
   15 01 00 1F 00 15 01 00 3A 00 15 01
  Scala: length = 0x0 (unknown attribute)

