Classfile /Users/mw/Projects/slang-braindump/.jar/jar11/assemble/slang-braindump/assemble/content/coursier/core/shaded/fastparse/Implicits$Repeater$UnitRepeater$.class
  Last modified May 29, 2022; size 1758 bytes
  SHA-256 checksum 240688684190ea1e87e89fa5e302135a560c8b6f46cebe2cda5391b437b46d38
  Compiled from "Implicits.scala"
public class coursier.core.shaded.fastparse.Implicits$Repeater$UnitRepeater$ extends java.lang.Object implements coursier.core.shaded.fastparse.Implicits$Repeater<scala.runtime.BoxedUnit, scala.runtime.BoxedUnit>
  minor version: 0
  major version: 52
  flags: (0x0021) ACC_PUBLIC, ACC_SUPER
  this_class: #2                          // coursier/core/shaded/fastparse/Implicits$Repeater$UnitRepeater$
  super_class: #5                         // java/lang/Object
  interfaces: 1, fields: 1, methods: 8, attributes: 5
Constant pool:
   #1 = Utf8               coursier/core/shaded/fastparse/Implicits$Repeater$UnitRepeater$
   #2 = Class              #1             // coursier/core/shaded/fastparse/Implicits$Repeater$UnitRepeater$
   #3 = Utf8               Ljava/lang/Object;Lcoursier/core/shaded/fastparse/Implicits$Repeater<Lscala/runtime/BoxedUnit;Lscala/runtime/BoxedUnit;>;
   #4 = Utf8               java/lang/Object
   #5 = Class              #4             // java/lang/Object
   #6 = Utf8               coursier/core/shaded/fastparse/Implicits$Repeater
   #7 = Class              #6             // coursier/core/shaded/fastparse/Implicits$Repeater
   #8 = Utf8               Implicits.scala
   #9 = Utf8               coursier/core/shaded/fastparse/Implicits
  #10 = Class              #9             // coursier/core/shaded/fastparse/Implicits
  #11 = Utf8               Repeater
  #12 = Utf8               coursier/core/shaded/fastparse/Implicits$Repeater$
  #13 = Class              #12            // coursier/core/shaded/fastparse/Implicits$Repeater$
  #14 = Utf8
  #15 = Utf8               MODULE$
  #16 = Utf8               Lcoursier/core/shaded/fastparse/Implicits$Repeater$UnitRepeater$;
  #17 = Utf8               <clinit>
  #18 = Utf8               ()V
  #19 = Utf8               <init>
  #20 = NameAndType        #19:#18        // "<init>":()V
  #21 = Methodref          #2.#20         // coursier/core/shaded/fastparse/Implicits$Repeater$UnitRepeater$."<init>":()V
  #22 = NameAndType        #15:#16        // MODULE$:Lcoursier/core/shaded/fastparse/Implicits$Repeater$UnitRepeater$;
  #23 = Fieldref           #2.#22         // coursier/core/shaded/fastparse/Implicits$Repeater$UnitRepeater$.MODULE$:Lcoursier/core/shaded/fastparse/Implicits$Repeater$UnitRepeater$;
  #24 = Utf8               initial
  #25 = Utf8               this
  #26 = Utf8               accumulate
  #27 = Utf8               (Lscala/runtime/BoxedUnit;Lscala/runtime/BoxedUnit;)V
  #28 = Utf8               t
  #29 = Utf8               acc
  #30 = Utf8               Lscala/runtime/BoxedUnit;
  #31 = Utf8               result
  #32 = Utf8               (Lscala/runtime/BoxedUnit;)V
  #33 = Utf8               (Ljava/lang/Object;)Ljava/lang/Object;
  #34 = Utf8               scala/runtime/BoxedUnit
  #35 = Class              #34            // scala/runtime/BoxedUnit
  #36 = NameAndType        #31:#32        // result:(Lscala/runtime/BoxedUnit;)V
  #37 = Methodref          #2.#36         // coursier/core/shaded/fastparse/Implicits$Repeater$UnitRepeater$.result:(Lscala/runtime/BoxedUnit;)V
  #38 = Utf8               UNIT
  #39 = NameAndType        #38:#30        // UNIT:Lscala/runtime/BoxedUnit;
  #40 = Fieldref           #35.#39        // scala/runtime/BoxedUnit.UNIT:Lscala/runtime/BoxedUnit;
  #41 = Utf8               Ljava/lang/Object;
  #42 = Utf8               (Ljava/lang/Object;Ljava/lang/Object;)V
  #43 = NameAndType        #26:#27        // accumulate:(Lscala/runtime/BoxedUnit;Lscala/runtime/BoxedUnit;)V
  #44 = Methodref          #2.#43         // coursier/core/shaded/fastparse/Implicits$Repeater$UnitRepeater$.accumulate:(Lscala/runtime/BoxedUnit;Lscala/runtime/BoxedUnit;)V
  #45 = Utf8               ()Ljava/lang/Object;
  #46 = NameAndType        #24:#18        // initial:()V
  #47 = Methodref          #2.#46         // coursier/core/shaded/fastparse/Implicits$Repeater$UnitRepeater$.initial:()V
  #48 = Methodref          #5.#20         // java/lang/Object."<init>":()V
  #49 = Utf8               Code
  #50 = Utf8               LineNumberTable
  #51 = Utf8               LocalVariableTable
  #52 = Utf8               MethodParameters
  #53 = Utf8               InnerClasses
  #54 = Utf8               Signature
  #55 = Utf8               SourceFile
  #56 = Utf8               ScalaInlineInfo
  #57 = Utf8               Scala
{
  public static final coursier.core.shaded.fastparse.Implicits$Repeater$UnitRepeater$ MODULE$;
    descriptor: Lcoursier/core/shaded/fastparse/Implicits$Repeater$UnitRepeater$;
    flags: (0x0019) ACC_PUBLIC, ACC_STATIC, ACC_FINAL

  public static {};
    descriptor: ()V
    flags: (0x0009) ACC_PUBLIC, ACC_STATIC
    Code:
      stack=2, locals=0, args_size=0
         0: new           #2                  // class coursier/core/shaded/fastparse/Implicits$Repeater$UnitRepeater$
         3: dup
         4: invokespecial #21                 // Method "<init>":()V
         7: putstatic     #23                 // Field MODULE$:Lcoursier/core/shaded/fastparse/Implicits$Repeater$UnitRepeater$;
        10: return
      LineNumberTable:
        line 41: 0

  public void initial();
    descriptor: ()V
    flags: (0x0001) ACC_PUBLIC
    Code:
      stack=0, locals=1, args_size=1
         0: return
      LineNumberTable:
        line 43: 0
      LocalVariableTable:
        Start  Length  Slot  Name   Signature
            0       1     0  this   Lcoursier/core/shaded/fastparse/Implicits$Repeater$UnitRepeater$;

  public void accumulate(scala.runtime.BoxedUnit, scala.runtime.BoxedUnit);
    descriptor: (Lscala/runtime/BoxedUnit;Lscala/runtime/BoxedUnit;)V
    flags: (0x0001) ACC_PUBLIC
    Code:
      stack=0, locals=3, args_size=3
         0: return
      LineNumberTable:
        line 44: 0
      LocalVariableTable:
        Start  Length  Slot  Name   Signature
            0       1     0  this   Lcoursier/core/shaded/fastparse/Implicits$Repeater$UnitRepeater$;
            0       1     1     t   Lscala/runtime/BoxedUnit;
            0       1     2   acc   Lscala/runtime/BoxedUnit;
    MethodParameters:
      Name                           Flags
      t                              final
      acc                            final

  public void result(scala.runtime.BoxedUnit);
    descriptor: (Lscala/runtime/BoxedUnit;)V
    flags: (0x0001) ACC_PUBLIC
    Code:
      stack=0, locals=2, args_size=2
         0: return
      LineNumberTable:
        line 45: 0
      LocalVariableTable:
        Start  Length  Slot  Name   Signature
            0       1     0  this   Lcoursier/core/shaded/fastparse/Implicits$Repeater$UnitRepeater$;
            0       1     1   acc   Lscala/runtime/BoxedUnit;
    MethodParameters:
      Name                           Flags
      acc                            final

  public java.lang.Object result(java.lang.Object);
    descriptor: (Ljava/lang/Object;)Ljava/lang/Object;
    flags: (0x1041) ACC_PUBLIC, ACC_BRIDGE, ACC_SYNTHETIC
    Code:
      stack=2, locals=2, args_size=2
         0: aload_0
         1: aload_1
         2: checkcast     #35                 // class scala/runtime/BoxedUnit
         5: invokevirtual #37                 // Method result:(Lscala/runtime/BoxedUnit;)V
         8: getstatic     #40                 // Field scala/runtime/BoxedUnit.UNIT:Lscala/runtime/BoxedUnit;
        11: areturn
      LineNumberTable:
        line 41: 0
      LocalVariableTable:
        Start  Length  Slot  Name   Signature
            0      12     0  this   Lcoursier/core/shaded/fastparse/Implicits$Repeater$UnitRepeater$;
            0      12     1   acc   Ljava/lang/Object;
    MethodParameters:
      Name                           Flags
      acc                            final

  public void accumulate(java.lang.Object, java.lang.Object);
    descriptor: (Ljava/lang/Object;Ljava/lang/Object;)V
    flags: (0x1041) ACC_PUBLIC, ACC_BRIDGE, ACC_SYNTHETIC
    Code:
      stack=3, locals=3, args_size=3
         0: aload_0
         1: aload_1
         2: checkcast     #35                 // class scala/runtime/BoxedUnit
         5: aload_2
         6: checkcast     #35                 // class scala/runtime/BoxedUnit
         9: invokevirtual #44                 // Method accumulate:(Lscala/runtime/BoxedUnit;Lscala/runtime/BoxedUnit;)V
        12: return
      LineNumberTable:
        line 41: 0
      LocalVariableTable:
        Start  Length  Slot  Name   Signature
            0      13     0  this   Lcoursier/core/shaded/fastparse/Implicits$Repeater$UnitRepeater$;
            0      13     1     t   Ljava/lang/Object;
            0      13     2   acc   Ljava/lang/Object;
    MethodParameters:
      Name                           Flags
      t                              final
      acc                            final

  public java.lang.Object initial();
    descriptor: ()Ljava/lang/Object;
    flags: (0x1041) ACC_PUBLIC, ACC_BRIDGE, ACC_SYNTHETIC
    Code:
      stack=1, locals=1, args_size=1
         0: aload_0
         1: invokevirtual #47                 // Method initial:()V
         4: getstatic     #40                 // Field scala/runtime/BoxedUnit.UNIT:Lscala/runtime/BoxedUnit;
         7: areturn
      LineNumberTable:
        line 41: 0
      LocalVariableTable:
        Start  Length  Slot  Name   Signature
            0       8     0  this   Lcoursier/core/shaded/fastparse/Implicits$Repeater$UnitRepeater$;

  public coursier.core.shaded.fastparse.Implicits$Repeater$UnitRepeater$();
    descriptor: ()V
    flags: (0x0001) ACC_PUBLIC
    Code:
      stack=1, locals=1, args_size=1
         0: aload_0
         1: invokespecial #48                 // Method java/lang/Object."<init>":()V
         4: return
      LineNumberTable:
        line 41: 0
      LocalVariableTable:
        Start  Length  Slot  Name   Signature
            0       5     0  this   Lcoursier/core/shaded/fastparse/Implicits$Repeater$UnitRepeater$;
}
InnerClasses:
  public static #11= #7 of #10;           // Repeater=class coursier/core/shaded/fastparse/Implicits$Repeater of class coursier/core/shaded/fastparse/Implicits
  public static #14= #13 of #10;          // =class coursier/core/shaded/fastparse/Implicits$Repeater$ of class coursier/core/shaded/fastparse/Implicits
  public static #14= #2 of #13;           // =class coursier/core/shaded/fastparse/Implicits$Repeater$UnitRepeater$ of class coursier/core/shaded/fastparse/Implicits$Repeater$
Signature: #3                           // Ljava/lang/Object;Lcoursier/core/shaded/fastparse/Implicits$Repeater<Lscala/runtime/BoxedUnit;Lscala/runtime/BoxedUnit;>;
SourceFile: "Implicits.scala"
  ScalaInlineInfo: length = 0x27 (unknown attribute)
   01 01 00 07 00 14 00 13 01 00 1B 00 2B 01 00 1B
   00 1C 01 00 19 00 2E 01 00 19 00 13 01 00 20 00
   22 01 00 20 00 21 01
  Scala: length = 0x0 (unknown attribute)

