Classfile /Users/mw/Projects/slang-braindump/.jar/jar11/assemble/slang-braindump/assemble/content/coursier/core/shaded/fastparse/Implicits$Repeater$.class
  Last modified May 29, 2022; size 1971 bytes
  SHA-256 checksum 250d2b839078f9c72bb1f368508429ca23f1e2762b68008aadf85d9be00c473d
  Compiled from "Implicits.scala"
public class coursier.core.shaded.fastparse.Implicits$Repeater$ implements coursier.core.shaded.fastparse.Implicits$LowPriRepeater
  minor version: 0
  major version: 52
  flags: (0x0021) ACC_PUBLIC, ACC_SUPER
  this_class: #2                          // coursier/core/shaded/fastparse/Implicits$Repeater$
  super_class: #4                         // java/lang/Object
  interfaces: 1, fields: 2, methods: 5, attributes: 4
Constant pool:
   #1 = Utf8               coursier/core/shaded/fastparse/Implicits$Repeater$
   #2 = Class              #1             // coursier/core/shaded/fastparse/Implicits$Repeater$
   #3 = Utf8               java/lang/Object
   #4 = Class              #3             // java/lang/Object
   #5 = Utf8               coursier/core/shaded/fastparse/Implicits$LowPriRepeater
   #6 = Class              #5             // coursier/core/shaded/fastparse/Implicits$LowPriRepeater
   #7 = Utf8               Implicits.scala
   #8 = Utf8               coursier/core/shaded/fastparse/Implicits
   #9 = Class              #8             // coursier/core/shaded/fastparse/Implicits
  #10 = Utf8               LowPriRepeater
  #11 = Utf8               coursier/core/shaded/fastparse/Implicits$LowPriRepeater$GenericRepeatedImplicit0$
  #12 = Class              #11            // coursier/core/shaded/fastparse/Implicits$LowPriRepeater$GenericRepeatedImplicit0$
  #13 = Utf8
  #14 = Utf8               coursier/core/shaded/fastparse/Implicits$Repeater
  #15 = Class              #14            // coursier/core/shaded/fastparse/Implicits$Repeater
  #16 = Utf8               Repeater
  #17 = Utf8               coursier/core/shaded/fastparse/Implicits$Repeater$UnitRepeater$
  #18 = Class              #17            // coursier/core/shaded/fastparse/Implicits$Repeater$UnitRepeater$
  #19 = Utf8               MODULE$
  #20 = Utf8               Lcoursier/core/shaded/fastparse/Implicits$Repeater$;
  #21 = Utf8               GenericRepeatedImplicit0$module
  #22 = Utf8               Lcoursier/core/shaded/fastparse/Implicits$LowPriRepeater$GenericRepeatedImplicit0$;
  #23 = Utf8               <clinit>
  #24 = Utf8               ()V
  #25 = Utf8               <init>
  #26 = NameAndType        #25:#24        // "<init>":()V
  #27 = Methodref          #2.#26         // coursier/core/shaded/fastparse/Implicits$Repeater$."<init>":()V
  #28 = NameAndType        #19:#20        // MODULE$:Lcoursier/core/shaded/fastparse/Implicits$Repeater$;
  #29 = Fieldref           #2.#28         // coursier/core/shaded/fastparse/Implicits$Repeater$.MODULE$:Lcoursier/core/shaded/fastparse/Implicits$Repeater$;
  #30 = Utf8               $init$
  #31 = Utf8               (Lcoursier/core/shaded/fastparse/Implicits$LowPriRepeater;)V
  #32 = NameAndType        #30:#31        // $init$:(Lcoursier/core/shaded/fastparse/Implicits$LowPriRepeater;)V
  #33 = InterfaceMethodref #6.#32         // coursier/core/shaded/fastparse/Implicits$LowPriRepeater.$init$:(Lcoursier/core/shaded/fastparse/Implicits$LowPriRepeater;)V
  #34 = Utf8               GenericRepeaterImplicit
  #35 = Utf8               ()Lcoursier/core/shaded/fastparse/Implicits$Repeater;
  #36 = Utf8               <T:Ljava/lang/Object;>()Lcoursier/core/shaded/fastparse/Implicits$Repeater<TT;Lscala/collection/immutable/Seq<TT;>;>;
  #37 = Utf8               GenericRepeaterImplicit$
  #38 = Utf8               (Lcoursier/core/shaded/fastparse/Implicits$LowPriRepeater;)Lcoursier/core/shaded/fastparse/Implicits$Repeater;
  #39 = NameAndType        #37:#38        // GenericRepeaterImplicit$:(Lcoursier/core/shaded/fastparse/Implicits$LowPriRepeater;)Lcoursier/core/shaded/fastparse/Implicits$Repeater;
  #40 = InterfaceMethodref #6.#39         // coursier/core/shaded/fastparse/Implicits$LowPriRepeater.GenericRepeaterImplicit$:(Lcoursier/core/shaded/fastparse/Implicits$LowPriRepeater;)Lcoursier/core/shaded/fastparse/Implicits$Repeater;
  #41 = Utf8               this
  #42 = Utf8               GenericRepeatedImplicit0
  #43 = Utf8               ()Lcoursier/core/shaded/fastparse/Implicits$LowPriRepeater$GenericRepeatedImplicit0$;
  #44 = NameAndType        #21:#22        // GenericRepeatedImplicit0$module:Lcoursier/core/shaded/fastparse/Implicits$LowPriRepeater$GenericRepeatedImplicit0$;
  #45 = Fieldref           #2.#44         // coursier/core/shaded/fastparse/Implicits$Repeater$.GenericRepeatedImplicit0$module:Lcoursier/core/shaded/fastparse/Implicits$LowPriRepeater$GenericRepeatedImplicit0$;
  #46 = Utf8               GenericRepeatedImplicit0$lzycompute$1
  #47 = NameAndType        #46:#24        // GenericRepeatedImplicit0$lzycompute$1:()V
  #48 = Methodref          #2.#47         // coursier/core/shaded/fastparse/Implicits$Repeater$.GenericRepeatedImplicit0$lzycompute$1:()V
  #49 = NameAndType        #25:#31        // "<init>":(Lcoursier/core/shaded/fastparse/Implicits$LowPriRepeater;)V
  #50 = Methodref          #12.#49        // coursier/core/shaded/fastparse/Implicits$LowPriRepeater$GenericRepeatedImplicit0$."<init>":(Lcoursier/core/shaded/fastparse/Implicits$LowPriRepeater;)V
  #51 = Utf8               java/lang/Throwable
  #52 = Class              #51            // java/lang/Throwable
  #53 = Methodref          #4.#26         // java/lang/Object."<init>":()V
  #54 = Utf8               Code
  #55 = Utf8               LineNumberTable
  #56 = Utf8               LocalVariableTable
  #57 = Utf8               Signature
  #58 = Utf8               StackMapTable
  #59 = Utf8               InnerClasses
  #60 = Utf8               SourceFile
  #61 = Utf8               ScalaInlineInfo
  #62 = Utf8               Scala
{
  public static final coursier.core.shaded.fastparse.Implicits$Repeater$ MODULE$;
    descriptor: Lcoursier/core/shaded/fastparse/Implicits$Repeater$;
    flags: (0x0019) ACC_PUBLIC, ACC_STATIC, ACC_FINAL

  private static volatile coursier.core.shaded.fastparse.Implicits$LowPriRepeater$GenericRepeatedImplicit0$ GenericRepeatedImplicit0$module;
    descriptor: Lcoursier/core/shaded/fastparse/Implicits$LowPriRepeater$GenericRepeatedImplicit0$;
    flags: (0x004a) ACC_PRIVATE, ACC_STATIC, ACC_VOLATILE

  public static {};
    descriptor: ()V
    flags: (0x0009) ACC_PUBLIC, ACC_STATIC
    Code:
      stack=2, locals=0, args_size=0
         0: new           #2                  // class coursier/core/shaded/fastparse/Implicits$Repeater$
         3: dup
         4: invokespecial #27                 // Method "<init>":()V
         7: putstatic     #29                 // Field MODULE$:Lcoursier/core/shaded/fastparse/Implicits$Repeater$;
        10: getstatic     #29                 // Field MODULE$:Lcoursier/core/shaded/fastparse/Implicits$Repeater$;
        13: invokestatic  #33                 // InterfaceMethod coursier/core/shaded/fastparse/Implicits$LowPriRepeater.$init$:(Lcoursier/core/shaded/fastparse/Implicits$LowPriRepeater;)V
        16: return
      LineNumberTable:
        line 40: 0

  public <T extends java.lang.Object> coursier.core.shaded.fastparse.Implicits$Repeater<T, scala.collection.immutable.Seq<T>> GenericRepeaterImplicit();
    descriptor: ()Lcoursier/core/shaded/fastparse/Implicits$Repeater;
    flags: (0x0001) ACC_PUBLIC
    Code:
      stack=1, locals=1, args_size=1
         0: aload_0
         1: invokestatic  #40                 // InterfaceMethod coursier/core/shaded/fastparse/Implicits$LowPriRepeater.GenericRepeaterImplicit$:(Lcoursier/core/shaded/fastparse/Implicits$LowPriRepeater;)Lcoursier/core/shaded/fastparse/Implicits$Repeater;
         4: areturn
      LineNumberTable:
        line 40: 0
      LocalVariableTable:
        Start  Length  Slot  Name   Signature
            0       5     0  this   Lcoursier/core/shaded/fastparse/Implicits$Repeater$;
    Signature: #36                          // <T:Ljava/lang/Object;>()Lcoursier/core/shaded/fastparse/Implicits$Repeater<TT;Lscala/collection/immutable/Seq<TT;>;>;

  public coursier.core.shaded.fastparse.Implicits$LowPriRepeater$GenericRepeatedImplicit0$ GenericRepeatedImplicit0();
    descriptor: ()Lcoursier/core/shaded/fastparse/Implicits$LowPriRepeater$GenericRepeatedImplicit0$;
    flags: (0x0001) ACC_PUBLIC
    Code:
      stack=1, locals=1, args_size=1
         0: getstatic     #45                 // Field GenericRepeatedImplicit0$module:Lcoursier/core/shaded/fastparse/Implicits$LowPriRepeater$GenericRepeatedImplicit0$;
         3: ifnonnull     10
         6: aload_0
         7: invokespecial #48                 // Method GenericRepeatedImplicit0$lzycompute$1:()V
        10: getstatic     #45                 // Field GenericRepeatedImplicit0$module:Lcoursier/core/shaded/fastparse/Implicits$LowPriRepeater$GenericRepeatedImplicit0$;
        13: areturn
      StackMapTable: number_of_entries = 1
        frame_type = 10 /* same */
      LineNumberTable:
        line 40: 0
      LocalVariableTable:
        Start  Length  Slot  Name   Signature
            0      14     0  this   Lcoursier/core/shaded/fastparse/Implicits$Repeater$;

  private final void GenericRepeatedImplicit0$lzycompute$1();
    descriptor: ()V
    flags: (0x0012) ACC_PRIVATE, ACC_FINAL
    Code:
      stack=3, locals=2, args_size=1
         0: aload_0
         1: dup
         2: astore_1
         3: monitorenter
         4: getstatic     #45                 // Field GenericRepeatedImplicit0$module:Lcoursier/core/shaded/fastparse/Implicits$LowPriRepeater$GenericRepeatedImplicit0$;
         7: ifnonnull     21
        10: new           #12                 // class coursier/core/shaded/fastparse/Implicits$LowPriRepeater$GenericRepeatedImplicit0$
        13: dup
        14: aload_0
        15: invokespecial #50                 // Method coursier/core/shaded/fastparse/Implicits$LowPriRepeater$GenericRepeatedImplicit0$."<init>":(Lcoursier/core/shaded/fastparse/Implicits$LowPriRepeater;)V
        18: putstatic     #45                 // Field GenericRepeatedImplicit0$module:Lcoursier/core/shaded/fastparse/Implicits$LowPriRepeater$GenericRepeatedImplicit0$;
        21: aload_1
        22: monitorexit
        23: goto          29
        26: aload_1
        27: monitorexit
        28: athrow
        29: return
      Exception table:
         from    to  target type
             4    21    26   any
      StackMapTable: number_of_entries = 3
        frame_type = 252 /* append */
          offset_delta = 21
          locals = [ class coursier/core/shaded/fastparse/Implicits$Repeater$ ]
        frame_type = 68 /* same_locals_1_stack_item */
          stack = [ class java/lang/Throwable ]
        frame_type = 2 /* same */
      LineNumberTable:
        line 40: 0
      LocalVariableTable:
        Start  Length  Slot  Name   Signature
            0      30     0  this   Lcoursier/core/shaded/fastparse/Implicits$Repeater$;

  public coursier.core.shaded.fastparse.Implicits$Repeater$();
    descriptor: ()V
    flags: (0x0001) ACC_PUBLIC
    Code:
      stack=1, locals=1, args_size=1
         0: aload_0
         1: invokespecial #53                 // Method java/lang/Object."<init>":()V
         4: return
      LineNumberTable:
        line 40: 0
      LocalVariableTable:
        Start  Length  Slot  Name   Signature
            0       5     0  this   Lcoursier/core/shaded/fastparse/Implicits$Repeater$;
}
InnerClasses:
  public static #10= #6 of #9;            // LowPriRepeater=class coursier/core/shaded/fastparse/Implicits$LowPriRepeater of class coursier/core/shaded/fastparse/Implicits
  public #13= #12 of #6;                  // =class coursier/core/shaded/fastparse/Implicits$LowPriRepeater$GenericRepeatedImplicit0$ of class coursier/core/shaded/fastparse/Implicits$LowPriRepeater
  public static #16= #15 of #9;           // Repeater=class coursier/core/shaded/fastparse/Implicits$Repeater of class coursier/core/shaded/fastparse/Implicits
  public static #13= #2 of #9;            // =class coursier/core/shaded/fastparse/Implicits$Repeater$ of class coursier/core/shaded/fastparse/Implicits
  public static #13= #18 of #2;           // =class coursier/core/shaded/fastparse/Implicits$Repeater$UnitRepeater$ of class coursier/core/shaded/fastparse/Implicits$Repeater$
SourceFile: "Implicits.scala"
  ScalaInlineInfo: length = 0x18 (unknown attribute)
   01 01 00 04 00 1B 00 1A 01 00 2C 00 2D 01 00 30
   00 1A 01 00 24 00 25 01
  Scala: length = 0x0 (unknown attribute)

