Classfile /Users/mw/Projects/slang-braindump/.jar/jar11/assemble/slang-braindump/assemble/content/coursier/core/shaded/fastparse/Implicits$Sequencer$NarySequencer.class
  Last modified May 29, 2022; size 1263 bytes
  SHA-256 checksum 90458f8ec270d79101032b2e4c69eb19793668de06810a4656f29d996929f5cb
  Compiled from "Implicits.scala"
public class coursier.core.shaded.fastparse.Implicits$Sequencer$NarySequencer<T extends java.lang.Object, V extends java.lang.Object, R extends java.lang.Object> extends java.lang.Object implements coursier.core.shaded.fastparse.Implicits$Sequencer<T, V, R>
  minor version: 0
  major version: 52
  flags: (0x0021) ACC_PUBLIC, ACC_SUPER
  this_class: #2                          // coursier/core/shaded/fastparse/Implicits$Sequencer$NarySequencer
  super_class: #5                         // java/lang/Object
  interfaces: 1, fields: 1, methods: 2, attributes: 5
Constant pool:
   #1 = Utf8               coursier/core/shaded/fastparse/Implicits$Sequencer$NarySequencer
   #2 = Class              #1             // coursier/core/shaded/fastparse/Implicits$Sequencer$NarySequencer
   #3 = Utf8               <T:Ljava/lang/Object;V:Ljava/lang/Object;R:Ljava/lang/Object;>Ljava/lang/Object;Lcoursier/core/shaded/fastparse/Implicits$Sequencer<TT;TV;TR;>;
   #4 = Utf8               java/lang/Object
   #5 = Class              #4             // java/lang/Object
   #6 = Utf8               coursier/core/shaded/fastparse/Implicits$Sequencer
   #7 = Class              #6             // coursier/core/shaded/fastparse/Implicits$Sequencer
   #8 = Utf8               Implicits.scala
   #9 = Utf8               coursier/core/shaded/fastparse/Implicits
  #10 = Class              #9             // coursier/core/shaded/fastparse/Implicits
  #11 = Utf8               Sequencer
  #12 = Utf8               coursier/core/shaded/fastparse/Implicits$Sequencer$
  #13 = Class              #12            // coursier/core/shaded/fastparse/Implicits$Sequencer$
  #14 = Utf8
  #15 = Utf8               NarySequencer
  #16 = Utf8               f
  #17 = Utf8               Lscala/Function2;
  #18 = Utf8               Lscala/Function2<TT;TV;TR;>;
  #19 = Utf8               apply
  #20 = Utf8               (Ljava/lang/Object;Ljava/lang/Object;)Ljava/lang/Object;
  #21 = Utf8               (TT;TV;)TR;
  #22 = Utf8               t
  #23 = Utf8               v
  #24 = NameAndType        #16:#17        // f:Lscala/Function2;
  #25 = Fieldref           #2.#24         // coursier/core/shaded/fastparse/Implicits$Sequencer$NarySequencer.f:Lscala/Function2;
  #26 = Utf8               scala/Function2
  #27 = Class              #26            // scala/Function2
  #28 = NameAndType        #19:#20        // apply:(Ljava/lang/Object;Ljava/lang/Object;)Ljava/lang/Object;
  #29 = InterfaceMethodref #27.#28        // scala/Function2.apply:(Ljava/lang/Object;Ljava/lang/Object;)Ljava/lang/Object;
  #30 = Utf8               this
  #31 = Utf8               Lcoursier/core/shaded/fastparse/Implicits$Sequencer$NarySequencer;
  #32 = Utf8               Ljava/lang/Object;
  #33 = Utf8               <init>
  #34 = Utf8               (Lscala/Function2;)V
  #35 = Utf8               (Lscala/Function2<TT;TV;TR;>;)V
  #36 = Utf8               ()V
  #37 = NameAndType        #33:#36        // "<init>":()V
  #38 = Methodref          #5.#37         // java/lang/Object."<init>":()V
  #39 = Utf8               Signature
  #40 = Utf8               Code
  #41 = Utf8               LineNumberTable
  #42 = Utf8               LocalVariableTable
  #43 = Utf8               MethodParameters
  #44 = Utf8               InnerClasses
  #45 = Utf8               SourceFile
  #46 = Utf8               ScalaInlineInfo
  #47 = Utf8               Scala
{
  private final scala.Function2<T, V, R> f;
    descriptor: Lscala/Function2;
    flags: (0x0012) ACC_PRIVATE, ACC_FINAL
    Signature: #18                          // Lscala/Function2<TT;TV;TR;>;

  public R apply(T, V);
    descriptor: (Ljava/lang/Object;Ljava/lang/Object;)Ljava/lang/Object;
    flags: (0x0001) ACC_PUBLIC
    Code:
      stack=3, locals=3, args_size=3
         0: aload_0
         1: getfield      #25                 // Field f:Lscala/Function2;
         4: aload_1
         5: aload_2
         6: invokeinterface #29,  3           // InterfaceMethod scala/Function2.apply:(Ljava/lang/Object;Ljava/lang/Object;)Ljava/lang/Object;
        11: areturn
      LineNumberTable:
        line 18: 0
      LocalVariableTable:
        Start  Length  Slot  Name   Signature
            0      12     0  this   Lcoursier/core/shaded/fastparse/Implicits$Sequencer$NarySequencer;
            0      12     1     t   Ljava/lang/Object;
            0      12     2     v   Ljava/lang/Object;
    Signature: #21                          // (TT;TV;)TR;
    MethodParameters:
      Name                           Flags
      t                              final
      v                              final

  public coursier.core.shaded.fastparse.Implicits$Sequencer$NarySequencer(scala.Function2<T, V, R>);
    descriptor: (Lscala/Function2;)V
    flags: (0x0001) ACC_PUBLIC
    Code:
      stack=2, locals=2, args_size=2
         0: aload_0
         1: aload_1
         2: putfield      #25                 // Field f:Lscala/Function2;
         5: aload_0
         6: invokespecial #38                 // Method java/lang/Object."<init>":()V
         9: return
      LineNumberTable:
        line 17: 0
      LocalVariableTable:
        Start  Length  Slot  Name   Signature
            0      10     0  this   Lcoursier/core/shaded/fastparse/Implicits$Sequencer$NarySequencer;
            0      10     1     f   Lscala/Function2;
    Signature: #35                          // (Lscala/Function2<TT;TV;TR;>;)V
    MethodParameters:
      Name                           Flags
      f                              final
}
InnerClasses:
  public static #11= #7 of #10;           // Sequencer=class coursier/core/shaded/fastparse/Implicits$Sequencer of class coursier/core/shaded/fastparse/Implicits
  public static #14= #13 of #10;          // =class coursier/core/shaded/fastparse/Implicits$Sequencer$ of class coursier/core/shaded/fastparse/Implicits
  public static #15= #2 of #13;           // NarySequencer=class coursier/core/shaded/fastparse/Implicits$Sequencer$NarySequencer of class coursier/core/shaded/fastparse/Implicits$Sequencer$
Signature: #3                           // <T:Ljava/lang/Object;V:Ljava/lang/Object;R:Ljava/lang/Object;>Ljava/lang/Object;Lcoursier/core/shaded/fastparse/Implicits$Sequencer<TT;TV;TR;>;
SourceFile: "Implicits.scala"
  ScalaInlineInfo: length = 0xE (unknown attribute)
   01 00 00 02 00 21 00 22 00 00 13 00 14 00
  Scala: length = 0x0 (unknown attribute)

