Classfile /Users/mw/Projects/slang-braindump/.jar/jar11/assemble/slang-braindump/assemble/content/coursier/core/shaded/fastparse/package$EagerOps.class
  Last modified May 29, 2022; size 1613 bytes
  SHA-256 checksum 9641be470ce93b3fc8512f6e8d6753c6cf1807ac79399bc9ae44f5ef42a55479
  Compiled from "package.scala"
public final class coursier.core.shaded.fastparse.package$EagerOps<T extends java.lang.Object> extends java.lang.Object
  minor version: 0
  major version: 52
  flags: (0x0031) ACC_PUBLIC, ACC_FINAL, ACC_SUPER
  this_class: #2                          // coursier/core/shaded/fastparse/package$EagerOps
  super_class: #5                         // java/lang/Object
  interfaces: 0, fields: 1, methods: 4, attributes: 5
Constant pool:
   #1 = Utf8               coursier/core/shaded/fastparse/package$EagerOps
   #2 = Class              #1             // coursier/core/shaded/fastparse/package$EagerOps
   #3 = Utf8               <T:Ljava/lang/Object;>Ljava/lang/Object;
   #4 = Utf8               java/lang/Object
   #5 = Class              #4             // java/lang/Object
   #6 = Utf8               package.scala
   #7 = Utf8               coursier/core/shaded/fastparse/package
   #8 = Class              #7             // coursier/core/shaded/fastparse/package
   #9 = Utf8               EagerOps
  #10 = Utf8               coursier/core/shaded/fastparse/package$EagerOps$
  #11 = Class              #10            // coursier/core/shaded/fastparse/package$EagerOps$
  #12 = Utf8
  #13 = Utf8               parse0
  #14 = Utf8               Lcoursier/core/shaded/fastparse/ParsingRun;
  #15 = Utf8               Lcoursier/core/shaded/fastparse/ParsingRun<TT;>;
  #16 = Utf8               ()Lcoursier/core/shaded/fastparse/ParsingRun;
  #17 = Utf8               ()Lcoursier/core/shaded/fastparse/ParsingRun<TT;>;
  #18 = NameAndType        #13:#14        // parse0:Lcoursier/core/shaded/fastparse/ParsingRun;
  #19 = Fieldref           #2.#18         // coursier/core/shaded/fastparse/package$EagerOps.parse0:Lcoursier/core/shaded/fastparse/ParsingRun;
  #20 = Utf8               this
  #21 = Utf8               Lcoursier/core/shaded/fastparse/package$EagerOps;
  #22 = Utf8               hashCode
  #23 = Utf8               ()I
  #24 = Utf8               MODULE$
  #25 = Utf8               Lcoursier/core/shaded/fastparse/package$EagerOps$;
  #26 = NameAndType        #24:#25        // MODULE$:Lcoursier/core/shaded/fastparse/package$EagerOps$;
  #27 = Fieldref           #11.#26        // coursier/core/shaded/fastparse/package$EagerOps$.MODULE$:Lcoursier/core/shaded/fastparse/package$EagerOps$;
  #28 = NameAndType        #13:#16        // parse0:()Lcoursier/core/shaded/fastparse/ParsingRun;
  #29 = Methodref          #2.#28         // coursier/core/shaded/fastparse/package$EagerOps.parse0:()Lcoursier/core/shaded/fastparse/ParsingRun;
  #30 = Utf8               hashCode$extension
  #31 = Utf8               (Lcoursier/core/shaded/fastparse/ParsingRun;)I
  #32 = NameAndType        #30:#31        // hashCode$extension:(Lcoursier/core/shaded/fastparse/ParsingRun;)I
  #33 = Methodref          #11.#32        // coursier/core/shaded/fastparse/package$EagerOps$.hashCode$extension:(Lcoursier/core/shaded/fastparse/ParsingRun;)I
  #34 = Utf8               equals
  #35 = Utf8               (Ljava/lang/Object;)Z
  #36 = Utf8               x$1
  #37 = Utf8               equals$extension
  #38 = Utf8               (Lcoursier/core/shaded/fastparse/ParsingRun;Ljava/lang/Object;)Z
  #39 = NameAndType        #37:#38        // equals$extension:(Lcoursier/core/shaded/fastparse/ParsingRun;Ljava/lang/Object;)Z
  #40 = Methodref          #11.#39        // coursier/core/shaded/fastparse/package$EagerOps$.equals$extension:(Lcoursier/core/shaded/fastparse/ParsingRun;Ljava/lang/Object;)Z
  #41 = Utf8               Ljava/lang/Object;
  #42 = Utf8               <init>
  #43 = Utf8               (Lcoursier/core/shaded/fastparse/ParsingRun;)V
  #44 = Utf8               (Lcoursier/core/shaded/fastparse/ParsingRun<TT;>;)V
  #45 = Utf8               ()V
  #46 = NameAndType        #42:#45        // "<init>":()V
  #47 = Methodref          #5.#46         // java/lang/Object."<init>":()V
  #48 = Utf8               Signature
  #49 = Utf8               Code
  #50 = Utf8               LineNumberTable
  #51 = Utf8               LocalVariableTable
  #52 = Utf8               MethodParameters
  #53 = Utf8               InnerClasses
  #54 = Utf8               SourceFile
  #55 = Utf8               ScalaInlineInfo
  #56 = Utf8               Scala
{
  private final coursier.core.shaded.fastparse.ParsingRun<T> parse0;
    descriptor: Lcoursier/core/shaded/fastparse/ParsingRun;
    flags: (0x0012) ACC_PRIVATE, ACC_FINAL
    Signature: #15                          // Lcoursier/core/shaded/fastparse/ParsingRun<TT;>;

  public coursier.core.shaded.fastparse.ParsingRun<T> parse0();
    descriptor: ()Lcoursier/core/shaded/fastparse/ParsingRun;
    flags: (0x0001) ACC_PUBLIC
    Code:
      stack=1, locals=1, args_size=1
         0: aload_0
         1: getfield      #19                 // Field parse0:Lcoursier/core/shaded/fastparse/ParsingRun;
         4: areturn
      LineNumberTable:
        line 119: 0
      LocalVariableTable:
        Start  Length  Slot  Name   Signature
            0       5     0  this   Lcoursier/core/shaded/fastparse/package$EagerOps;
    Signature: #17                          // ()Lcoursier/core/shaded/fastparse/ParsingRun<TT;>;

  public int hashCode();
    descriptor: ()I
    flags: (0x0001) ACC_PUBLIC
    Code:
      stack=2, locals=1, args_size=1
         0: getstatic     #27                 // Field coursier/core/shaded/fastparse/package$EagerOps$.MODULE$:Lcoursier/core/shaded/fastparse/package$EagerOps$;
         3: aload_0
         4: invokevirtual #29                 // Method parse0:()Lcoursier/core/shaded/fastparse/ParsingRun;
         7: invokevirtual #33                 // Method coursier/core/shaded/fastparse/package$EagerOps$.hashCode$extension:(Lcoursier/core/shaded/fastparse/ParsingRun;)I
        10: ireturn
      LineNumberTable:
        line 119: 0
      LocalVariableTable:
        Start  Length  Slot  Name   Signature
            0      11     0  this   Lcoursier/core/shaded/fastparse/package$EagerOps;

  public boolean equals(java.lang.Object);
    descriptor: (Ljava/lang/Object;)Z
    flags: (0x0001) ACC_PUBLIC
    Code:
      stack=3, locals=2, args_size=2
         0: getstatic     #27                 // Field coursier/core/shaded/fastparse/package$EagerOps$.MODULE$:Lcoursier/core/shaded/fastparse/package$EagerOps$;
         3: aload_0
         4: invokevirtual #29                 // Method parse0:()Lcoursier/core/shaded/fastparse/ParsingRun;
         7: aload_1
         8: invokevirtual #40                 // Method coursier/core/shaded/fastparse/package$EagerOps$.equals$extension:(Lcoursier/core/shaded/fastparse/ParsingRun;Ljava/lang/Object;)Z
        11: ireturn
      LineNumberTable:
        line 119: 0
      LocalVariableTable:
        Start  Length  Slot  Name   Signature
            0      12     0  this   Lcoursier/core/shaded/fastparse/package$EagerOps;
            0      12     1   x$1   Ljava/lang/Object;
    MethodParameters:
      Name                           Flags
      x$1                            final

  public coursier.core.shaded.fastparse.package$EagerOps(coursier.core.shaded.fastparse.ParsingRun<T>);
    descriptor: (Lcoursier/core/shaded/fastparse/ParsingRun;)V
    flags: (0x0001) ACC_PUBLIC
    Code:
      stack=2, locals=2, args_size=2
         0: aload_0
         1: aload_1
         2: putfield      #19                 // Field parse0:Lcoursier/core/shaded/fastparse/ParsingRun;
         5: aload_0
         6: invokespecial #47                 // Method java/lang/Object."<init>":()V
         9: return
      LineNumberTable:
        line 119: 0
      LocalVariableTable:
        Start  Length  Slot  Name   Signature
            0      10     0  this   Lcoursier/core/shaded/fastparse/package$EagerOps;
            0      10     1 parse0   Lcoursier/core/shaded/fastparse/ParsingRun;
    Signature: #44                          // (Lcoursier/core/shaded/fastparse/ParsingRun<TT;>;)V
    MethodParameters:
      Name                           Flags
      parse0                         final
}
InnerClasses:
  public static final #9= #2 of #8;       // EagerOps=class coursier/core/shaded/fastparse/package$EagerOps of class coursier/core/shaded/fastparse/package
  public static #12= #11 of #8;           // =class coursier/core/shaded/fastparse/package$EagerOps$ of class coursier/core/shaded/fastparse/package
Signature: #3                           // <T:Ljava/lang/Object;>Ljava/lang/Object;
SourceFile: "package.scala"
  ScalaInlineInfo: length = 0x54 (unknown attribute)
   01 01 00 10 00 38 00 39 01 00 3A 00 3B 01 00 3C
   00 39 01 00 3D 00 3E 01 00 3F 00 40 01 00 41 00
   40 01 00 42 00 43 01 00 44 00 43 01 00 2A 00 2B
   01 00 22 00 23 01 00 45 00 46 01 00 47 00 48 01
   00 49 00 4A 01 00 16 00 17 01 00 4B 00 4A 01 00
   0D 00 10 01
  Scala: length = 0x0 (unknown attribute)

