Classfile /Users/mw/Projects/slang-braindump/.jar/jar11/assemble/slang-braindump/assemble/content/coursier/core/shaded/fastparse/Parsed.class
  Last modified May 29, 2022; size 7156 bytes
  SHA-256 checksum 81c83b047e40025ae55c438f73d848ce51c9894e545442209f24323eae52e171
  Compiled from "Parsed.scala"
public abstract class coursier.core.shaded.fastparse.Parsed<T extends java.lang.Object> extends java.lang.Object
  minor version: 0
  major version: 52
  flags: (0x0421) ACC_PUBLIC, ACC_SUPER, ACC_ABSTRACT
  this_class: #2                          // coursier/core/shaded/fastparse/Parsed
  super_class: #5                         // java/lang/Object
  interfaces: 0, fields: 1, methods: 5, attributes: 6
Constant pool:
   #1 = Utf8               coursier/core/shaded/fastparse/Parsed
   #2 = Class              #1             // coursier/core/shaded/fastparse/Parsed
   #3 = Utf8               <T:Ljava/lang/Object;>Ljava/lang/Object;
   #4 = Utf8               java/lang/Object
   #5 = Class              #4             // java/lang/Object
   #6 = Utf8               Parsed.scala
   #7 = Utf8               Lscala/reflect/ScalaSignature;
   #8 = Utf8               bytes
   #9 = Utf8               \u0006\u0005\u0011=b!\u0002;v\u0003CA\bBCA\u0001\u0001\t\u0015\r\u0011\"\u0001\u0002\u0004!Q\u00111\u0002\u0001\u0003\u0002\u0003\u0006I!!\u0002\t\u000f\u00055\u0001\u0001\"\u0001\u0002\u0010!9\u0011Q\u0006\u0001\u0007\u0002\u0005=\u0002bBA^\u0001\u0019\u0005A\u0011F\u0004\b\u0003G*\b\u0012AA3\r\u0019!X\u000f#\u0001\u0002h!9\u0011QB\u0004\u0005\u0002\u0005%\u0004bBA6\u000f\u0011\u0005\u0011Q\u000e\u0004\u0007\u0003\u0003;!)a!\t\u0015\u0005\u0015&B!f\u0001\n\u0003\t9\u000b\u0003\u0006\u0002**\u0011\t\u0012)A\u0005\u0003\u0013C!\"a+\u000b\u0005+\u0007I\u0011AAW\u0011)\tyK\u0003B\tB\u0003%\u0011\u0011\f\u0005\b\u0003\u001bQA\u0011AAY\u0011\u001d\tYL\u0003C\u0001\u0003{Cq!!\f\u000b\t\u0003\ty\fC\u0004\u0003\n*!\tEa#\t\u0013\t](\"!A\u0005\u0002\r]\u0003\"CB\u0001\u0015E\u0005I\u0011AB3\u0011%\u00199ACI\u0001\n\u0003\u0019i\u0007C\u0005\u0004\u0010)\t\t\u0011\"\u0011\u0003\u0010\"I1\u0011\u0003\u0006\u0002\u0002\u0013\u0005\u0011Q\u0016\u0005\n\u0007\'Q\u0011\u0011!C\u0001\u0007kB\u0011ba\u0007\u000b\u0003\u0003%\te!\b\t\u0013\r-\"\"!A\u0005\u0002\re\u0004\"CB\u0019\u0015\u0005\u0005I\u0011IB?\u0011%\u00199DCA\u0001\n\u0003\u001aI\u0004C\u0005\u0004>)\t\t\u0011\"\u0011\u0004\u0002\u001eI1QQ\u0004\u0002\u0002#\u00051q\u0011\u0004\n\u0003\u0003;\u0011\u0011!E\u0001\u0007\u0013Cq!!\u0004 \t\u0003\u0019)\nC\u0005\u0003\n~\t\t\u0011\"\u0012\u0004<!I1qS\u0010\u0002\u0002\u0013\u00055\u0011\u0014\u0005\n\u0007O{\u0012\u0011!CA\u0007SC\u0011ba0 \u0003\u0003%Ia!1\u0007\r\t]sA\u0001B-\u0011)\u0011i&\nBC\u0002\u0013\u0005!q\f\u0005\u000b\u0005C*#\u0011!Q\u0001\n\u0005\r\u0003BCAVK\t\u0015\r\u0011\"\u0001\u0002.\"Q\u0011qV\u0013\u0003\u0002\u0003\u0006I!!\u0017\t\u0015\t\rTE!b\u0001\n\u0003\u0011)\u0007\u0003\u0006\u0003h\u0015\u0012\t\u0011)A\u0005\u0003\u0017Dq!!\u0004&\t\u0003\u0011I\u0007C\u0004\u0002<\u0016\"\tA!\u001d\t\u000f\u00055R\u0005\"\u0001\u0003t!9!\u0011R\u0013\u0005B\t-\u0005b\u0002BGK\u0011\u0005!q\u0012\u0005\b\u0005?+C\u0011\u0001BH\u0011\u001d\u0011\t+\nC\u0001\u0005GC\u0011B!+&#\u0003%\tAa+\b\u000f\r%w\u0001#\u0001\u0004L\u001a9!qK\u0004\t\u0002\r5\u0007bBA\u0007k\u0011\u00051q\u001a\u0005\b\u0007/+D\u0011ABi\u0011\u001d\u00199+\u000eC\u0001\u00073Dqaa:6\t\u0003\u0019I\u000fC\u0004\u0004rV\"\taa=\t\u000f\reX\u0007\"\u0001\u0004|\u001a1\u0011QZ\u0004\u0001\u0003\u001fD!\"!5=\u0005\u000b\u0007I\u0011AAj\u0011)\tY\u000e\u0010B\u0001B\u0003%\u0011Q\u001b\u0005\u000b\u0003;d$Q1A\u0005\u0002\u00055\u0006BCApy\t\u0005\t\u0015!\u0003\u0002Z!Q\u00111\u0016\u001f\u0003\u0006\u0004%\t!!,\t\u0015\u0005=FH!A!\u0002\u0013\tI\u0006\u0003\u0006\u0002br\u0012)\u0019!C\u0001\u0003GD!\"!>=\u0005\u0003\u0005\u000b\u0011BAs\u0011)\u0011\t\u0001\u0010BC\u0002\u0013\u0005!1\u0001\u0005\u000b\u0005#a$\u0011!Q\u0001\n\t\u0015\u0001bBA\u0007y\u0011\u0005!1\u0003\u0005\b\u0005caD\u0011\u0001B\u001a\u0011\u001d\u0011\t\u000b\u0010C\u0001\u0007\u001fB\u0011B!+=#\u0003%\tAa+\b\u000f\u0011\u0005q\u0001#\u0001\u0005\u0004\u00199!qG\u0004\t\u0002\u0011\u0015\u0001bBA\u0007\u0019\u0012\u0005Aq\u0001\u0005\b\u0003WbE\u0011\u0001C\u0005\u0011%\u00199\nTA\u0001\n\u0003#)\u0002C\u0005\u0004(2\u000b\t\u0011\"!\u0005\u001e!I1q\u0018\'\u0002\u0002\u0013%1\u0011\u0019\u0004\u0007\u0005o9\u0001I!\u000f\t\u0015\tm\"K!f\u0001\n\u0003\u0011i\u0004\u0003\u0006\u0003LI\u0013\t\u0012)A\u0005\u0005\u007fA!B!\u0014S\u0005+\u0007I\u0011\u0001B\u001f\u0011)\u0011yE\u0015B\tB\u0003%!q\b\u0005\u000b\u0005#\u0012&Q3A\u0005\u0002\tM\u0003B\u0003Ba%\nE\t\u0015!\u0003\u0003V!9\u0011Q\u0002*\u0005\u0002\t\r\u0007b\u0002B/%\u0012\u0005!q\f\u0005\b\u0003W\u0013F\u0011AAW\u0011\u001d\t\tN\u0015C\u0001\u0003\'DqA!\u0001S\t\u0003\u0011\u0019\u0001C\u0004\u0003LJ#\tAa\u0018\t\u000f\t5\'\u000b\"\u0001\u0003`!9!\u0011\u0015*\u0005\u0002\t=\u0005b\u0002BG%\u0012\u0005!q\u0012\u0005\b\u0005_\u0014F\u0011\u0001BH\u0011\u001d\u0011\tP\u0015C\u0001\u0005\u001fCqAa(S\t\u0003\u0011y\tC\u0004\u0003tJ#\tAa$\t\u000f\tU(\u000b\"\u0001\u0003\u0010\"I!q\u001f*\u0002\u0002\u0013\u0005!\u0011 \u0005\n\u0007\u0003\u0011\u0016\u0013!C\u0001\u0007\u0007A\u0011ba\u0002S#\u0003%\taa\u0001\t\u0013\r%!+%A\u0005\u0002\r-\u0001\"CB\b%\u0006\u0005I\u0011\tBH\u0011%\u0019\tBUA\u0001\n\u0003\ti\u000bC\u0005\u0004\u0014I\u000b\t\u0011\"\u0001\u0004\u0016!I11\u0004*\u0002\u0002\u0013\u00053Q\u0004\u0005\n\u0007W\u0011\u0016\u0011!C\u0001\u0007[A\u0011b!\rS\u0003\u0003%\tea\r\t\u0013\r]\"+!A\u0005B\re\u0002\"\u0003BE%\u0006\u0005I\u0011IB\u001e\u0011%\u0019iDUA\u0001\n\u0003\u001ayD\u0001\u0004QCJ\u001cX\r\u001a\u0006\u0002m\u0006Ia-Y:ua\u0006\u00148/Z\u0002\u0001+\rI\u0018\u0011D\n\u0003\u0001i\u0004\"a\u001f@\u000e\u0003qT\u0011!`\u0001\u0006g\u000e\fG.Y\u0005\u0003\u007fr\u0014a!\u00118z%\u00164\u0017!C5t\'V\u001c7-Z:t+\t\t)\u0001E\u0002|\u0003\u000fI1!!\u0003}\u0005\u001d\u0011un\u001c7fC:\f!\"[:Tk\u000e\u001cWm]:!\u0003\u0019a\u0014N\\5u}Q!\u0011\u0011CA\u0016!\u0015\t\u0019\u0002AA\u000b\u001b\u0005)\b\u0003BA\f\u00033a\u0001\u0001\u0002\u0005\u0002\u001c\u0001!)\u0019AA\u000f\u0005\u0005!\u0016\u0003BA\u0010\u0003K\u00012a_A\u0011\u0013\r\t\u0019\u0003 \u0002\b\u001d>$\b.\u001b8h!\rY\u0018qE\u0005\u0004\u0003Sa(aA!os\"9\u0011\u0011A\u0002A\u0002\u0005\u0015\u0011\u0001\u00024pY\u0012,B!!\r\u00026Q1\u00111GA\u001d\tK\u0001B!a\u0006\u00026\u00119\u0011q\u0007\u0003C\u0002\u0005u!!\u0001,\t\u000f\u0005mB\u00011\u0001\u0002>\u0005IqN\u001c$bS2,(/\u001a\t\fw\u0006}\u00121IA-\u0003?\n\u0019$C\u0002\u0002Bq\u0014\u0011BR;oGRLwN\\\u001a\u0011\t\u0005\u0015\u00131\u000b\b\u0005\u0003\u000f\ny\u0005E\u0002\u0002Jql!!a\u0013\u000b\u0007\u00055s/\u0001\u0004=e>|GOP\u0005\u0004\u0003#b\u0018A\u0002)sK\u0012,g-\u0003\u0003\u0002V\u0005]#AB*ue&twMC\u0002\u0002Rq\u00042a_A.\u0013\r\ti\u0006 \u0002\u0004\u0013:$\bcAA1y9\u0019\u00111\u0003\u0004\u0002\rA\u000b\'o]3e!\r\t\u0019bB\n\u0003\u000fi$\"!!\u001a\u0002\u001d\u0019\u0014x.\u001c)beNLgn\u001a*v]V!\u0011qNA;)\u0011\t\t(a\u001e\u0011\u000b\u0005M\u0001!a\u001d\u0011\t\u0005]\u0011Q\u000f\u0003\b\u00037I!\u0019AA\u000f\u0011\u001d\tI(\u0003a\u0001\u0003w\n\u0011\u0001\u001d\t\u0007\u0003\'\ti(a\u001d\n\u0007\u0005}TO\u0001\u0006QCJ\u001c\u0018N\\4Sk:\u0014qaU;dG\u0016\u001c8/\u0006\u0003\u0002\u0006\u0006-5c\u0002\u0006\u0002\b\u00065\u00151\u0013\t\u0006\u0003\'\u0001\u0011\u0011\u0012\t\u0005\u0003/\tY\t\u0002\u0005\u0002\u001c)!)\u0019AA\u000f!\rY\u0018qR\u0005\u0004\u0003#c(a\u0002)s_\u0012,8\r\u001e\t\u0005\u0003+\u000byJ\u0004\u0003\u0002\u0018\u0006me\u0002BA%\u00033K\u0011!`\u0005\u0004\u0003;c\u0018a\u00029bG.\fw-Z\u0005\u0005\u0003C\u000b\u0019K\u0001\u0007TKJL\u0017\r\\5{C\ndWMC\u0002\u0002\u001er\fQA^1mk\u0016,\"!!#\u0002\rY\fG.^3!\u0003\u0015Ig\u000eZ3y+\t\tI&\u0001\u0004j]\u0012,\u0007\u0010\t\u000b\u0007\u0003g\u000b9,!/\u0011\u000b\u0005U&\"!#\u000e\u0003\u001dAq!!*\u0010\u0001\u0004\tI\tC\u0004\u0002,>\u0001\r!!\u0017\u0002\u0007\u001d,G/\u0006\u0002\u00024V!\u0011\u0011YAc)\u0019\t\u0019-a2\u0004TA!\u0011qCAc\t\u001d\t9$\u0005b\u0001\u0003;Aq!a\u000f\u0012\u0001\u0004\tI\rE\u0006|\u0003\u007f\t\u0019%!\u0017\u0002L\u0006\r\u0007cAA[y\t)Q\t\u001f;sCN\u0011AH_\u0001\u0006S:\u0004X\u000f^\u000b\u0003\u0003+\u0004B!a\u0005\u0002X&\u0019\u0011\u0011\\;\u0003\u0017A\u000b\'o]3s\u0013:\u0004X\u000f^\u0001\u0007S:\u0004X\u000f\u001e\u0011\u0002\u0015M$\u0018M\u001d;J]\u0012,\u00070A\u0006ti\u0006\u0014H/\u00138eKb\u0004\u0013AD8sS\u001eLg.\u00197QCJ\u001cXM]\u000b\u0003\u0003K\u0004ra_At\u0003W\f90C\u0002\u0002jr\u0014\u0011BR;oGRLwN\\\u00191\t\u00055\u0018\u0011\u001f\t\u0007\u0003\'\ti(a<\u0011\t\u0005]\u0011\u0011\u001f\u0003\f\u0003g$\u0015\u0011!A\u0001\u0006\u0003\tiBA\u0002`IE\nqb\u001c:jO&t\u0017\r\u001c)beN,\'\u000f\t\u0019\u0005\u0003s\fi\u0010\u0005\u0004\u0002\u0014\u0005u\u00141 \t\u0005\u0003/\ti\u0010B\u0006\u0002\u0000\u0012\u000b\t\u0011!A\u0003\u0002\u0005u!aA0%e\u0005)1\u000f^1dWV\u0011!Q\u0001\t\u0007\u0003+\u00139Aa\u0003\n\t\t%\u00111\u0015\u0002\u0005\u0019&\u001cH\u000fE\u0004|\u0005\u001b\t\u0019%!\u0017\n\u0007\t=AP\u0001\u0004UkBdWMM\u0001\u0007gR\f7m\u001b\u0011\u0015\u0019\u0005-\'Q\u0003B\f\u00053\u0011YBa\f\t\u000f\u0005Ew\t1\u0001\u0002V\"9\u0011Q\\$A\u0002\u0005e\u0003bBAV\u000f\u0002\u0007\u0011\u0011\f\u0005\b\u0003C<\u0005\u0019\u0001B\u000f!\u001dY\u0018q\u001dB\u0010\u0005O\u0001DA!\t\u0003&A1\u00111CA?\u0005G\u0001B!a\u0006\u0003&\u0011a\u00111\u001fB\u000e\u0003\u0003\u0005\tQ!\u0001\u0002\u001eA\"!\u0011\u0006B\u0017!\u0019\t\u0019\"! \u0003,A!\u0011q\u0003B\u0017\t1\tyPa\u0007\u0002\u0002\u0003\u0005)\u0011AA\u000f\u0011\u001d\u0011\ta\u0012a\u0001\u0005\u000b\ta\u0001\u001e:bG\u0016$WC\u0001B\u001b!\r\t)L\u0015\u0002\u000e)J\f7-\u001a3GC&dWO]3\u0014\rIS\u0018QRAJ\u0003%!XM]7j]\u0006d7/\u0006\u0002\u0003@A!!\u0011\tB$\u001b\t\u0011\u0019EC\u0002\u0003FU\f\u0001\"\u001b8uKJt\u0017\r\\\u0005\u0005\u0005\u0013\u0012\u0019E\u0001\u0003Ng\u001e\u001c\u0018A\u0003;fe6Lg.\u00197tA\u00051qM]8vaN\fqa\u001a:pkB\u001c\b%A\u0004gC&dWO]3\u0016\u0005\tU\u0003cAA[K\t9a)Y5mkJ,7cA\u0013\u0003\\A)\u00111\u0003\u0001\u0002 \u0005)A.\u00192fYV\u0011\u00111I\u0001\u0007Y\u0006\u0014W\r\u001c\u0011\u0002\u000b\u0015DHO]1\u0016\u0005\u0005-\u0017AB3yiJ\f\u0007\u0005\u0006\u0005\u0003V\t-$Q\u000eB8\u0011\u001d\u0011i\u0006\fa\u0001\u0003\u0007Bq!a+-\u0001\u0004\tI\u0006C\u0004\u0003d1\u0002\r!a3\u0016\u0005\u0005}Q\u0003\u0002B;\u0005s\"bAa\u001e\u0003|\t}\u0004\u0003BA\f\u0005s\"q!a\u000e/\u0005\u0004\ti\u0002C\u0004\u0002<9\u0002\rA! \u0011\u0017m\fy$a\u0011\u0002Z\u0005-\'q\u000f\u0005\b\u0005\u0003s\u0003\u0019\u0001BB\u0003%ygnU;dG\u0016\u001c8\u000fE\u0005|\u0005\u000b\u000by\"!\u0017\u0003x%\u0019!q\u0011?\u0003\u0013\u0019+hn\u0019;j_:\u0014\u0014\u0001\u0003;p\'R\u0014\u0018N\\4\u0015\u0005\u0005\r\u0013aA7tOV\u0011!\u0011\u0013\t\u0005\u0005\'\u0013i*\u0004\u0002\u0003\u0016*!!q\u0013BM\u0003\u0011a\u0017M\\4\u000b\u0005\tm\u0015\u0001\u00026bm\u0006LA!!\u0016\u0003\u0016\u00069An\u001c8h\u001bN<\u0017!\u0002;sC\u000e,G\u0003\u0002B\u001b\u0005KC\u0011Ba*3!\u0003\u0005\r!!\u0002\u0002\u001b\u0015t\u0017M\u00197f\u0019><w-\u001b8h\u0003=!(/Y2fI\u0011,g-Y;mi\u0012\nTC\u0001BWU\u0011\t)Aa,,\u0005\tE\u0006\u0003\u0002BZ\u0005{k!A!.\u000b\t\t]&\u0011X\u0001\nk:\u001c\u0007.Z2lK\u0012T1Aa/}\u0003)\tgN\\8uCRLwN\\\u0005\u0005\u0005\u007f\u0013)LA\tv]\u000eDWmY6fIZ\u000b\'/[1oG\u0016\f\u0001BZ1jYV\u0014X\r\t\u000b\t\u0005k\u0011)Ma2\u0003J\"9!1H-A\u0002\t}\u0002b\u0002B\'3\u0002\u0007!q\b\u0005\b\u0005#J\u0006\u0019\u0001B+\u0003]!XM]7j]\u0006d\u0017iZ4sK\u001e\fG/Z*ue&tw-\u0001\u000bhe>,\b/Q4he\u0016<\u0017\r^3TiJLgn\u001a\u0015\bA\nE\'q\u001bBn!\rY(1[\u0005\u0004\u0005+d(A\u00033faJ,7-\u0019;fI\u0006\u0012!\u0011\\\u0001\u0011+N,\u0007EL7tO\u0002Jgn\u001d;fC\u0012\f\u0014bIA\"\u0005;\u0014)Oa8\n\t\t}\'\u0011]\u0001\u001cI1,7o]5oSR$sM]3bi\u0016\u0014H\u0005Z3gCVdG\u000f\n\u001a\u000b\u0007\t\rH0\u0001\u0006eKB\u0014XmY1uK\u0012\f\u0014b\tBt\u0005S\u0014YOa9\u000f\u0007m\u0014I/C\u0002\u0003dr\fTAI>}\u0005[\u0014Qa]2bY\u0006\fA\u0002^3s[&t\u0017\r\\:Ng\u001e\fA\"Y4he\u0016<\u0017\r^3Ng\u001e\f\u0001\u0003\\8oOR+\'/\\5oC2\u001cXj]4\u0002!1|gnZ!hOJ,w-\u0019;f\u001bN<\u0017\u0001B2paf$\u0002B!\u000e\u0003|\nu(q \u0005\n\u0005w9\u0007\u0013!a\u0001\u0005\u007fA\u0011B!\u0014h!\u0003\u0005\rAa\u0010\t\u0013\tEs\r%AA\u0002\tU\u0013AD2paf$C-\u001a4bk2$H%M\u000b\u0003\u0007\u000bQCAa\u0010\u00030\u0006q1m\u001c9zI\u0011,g-Y;mi\u0012\u0012\u0014AD2paf$C-\u001a4bk2$HeM\u000b\u0003\u0007\u001bQCA!\u0016\u00030\u0006i\u0001O]8ek\u000e$\bK]3gSb\fA\u0002\u001d:pIV\u001cG/\u0011:jif\fa\u0002\u001d:pIV\u001cG/\u00127f[\u0016tG\u000f\u0006\u0003\u0002&\r]\u0001\"CB\r[\u0006\u0005\t\u0019AA-\u0003\rAH%M\u0001\u0010aJ|G-^2u\u0013R,\'/\u0019;peV\u00111q\u0004\t\u0007\u0007C\u00199#!\n\u000e\u0005\r\r\"bAB\u0013y\u0006Q1m\u001c7mK\u000e$\u0018n\u001c8\n\t\r%21\u0005\u0002\t\u0013R,\'/\u0019;pe\u0006A1-\u00198FcV\fG\u000e\u0006\u0003\u0002\u0006\r=\u0002\"CB\r_\u0006\u0005\t\u0019AA\u0013\u0003I\u0001(o\u001c3vGR,E.Z7f]Rt\u0015-\\3\u0015\t\tE5Q\u0007\u0005\n\u00073\u0001\u0018\u0011!a\u0001\u00033\n\u0001\u0002[1tQ\u000e{G-\u001a\u000b\u0003\u00033\"\"A!%\u0002\r\u0015\fX/\u00197t)\u0011\t)a!\u0011\t\u0013\re1/!AA\u0002\u0005\u0015\u0002f\u0002%\u0003R\u000e\u00153\u0011J\u0011\u0003\u0007\u000f\n!#V:fA9\"(/Y2fA%t7\u000f^3bIFJ1%a\u0011\u0003^\u000e-#q\\\u0019\nG\t\u001d(\u0011^B\'\u0005G\fTAI>}\u0005[$BA!\u000e\u0004R!I!qU%\u0011\u0002\u0003\u0007\u0011Q\u0001\u0005\b\u0005\u0003\u000b\u0002\u0019AB+!%Y(QQAE\u00033\n\u0019-\u0006\u0003\u0004Z\r}CCBB.\u0007C\u001a\u0019\u0007E\u0003\u00026*\u0019i\u0006\u0005\u0003\u0002\u0018\r}CaBA\u000e\'\t\u0007\u0011Q\u0004\u0005\n\u0003K\u001b\u0002\u0013!a\u0001\u0007;B\u0011\"a+\u0014!\u0003\u0005\r!!\u0017\u0016\t\r\u001d41N\u000b\u0003\u0007SRC!!#\u00030\u00129\u00111\u0004\u000bC\u0002\u0005uQ\u0003BB8\u0007g*\"a!\u001d+\t\u0005e#q\u0016\u0003\b\u00037)\"\u0019AA\u000f)\u0011\t)ca\u001e\t\u0013\re\u0001$!AA\u0002\u0005eC\u0003BA\u0003\u0007wB\u0011b!\u0007\u001b\u0003\u0003\u0005\r!!\n\u0015\t\tE5q\u0010\u0005\n\u00073Y\u0012\u0011!a\u0001\u00033\"B!!\u0002\u0004\u0004\"I1\u0011D\u000f\u0002\u0002\u0003\u0007\u0011QE\u0001\b\'V\u001c7-Z:t!\r\t)lH\n\u0005?i\u001cY\t\u0005\u0003\u0004\u000e\u000eMUBABH\u0015\u0011\u0019\tJ!\'\u0002\u0005%|\u0017\u0002BAQ\u0007\u001f#\"aa\"\u0002\u000b\u0005\u0004\b\u000f\\=\u0016\t\rm5\u0011\u0015\u000b\u0007\u0007;\u001b\u0019k!*\u0011\u000b\u0005U&ba(\u0011\t\u0005]1\u0011\u0015\u0003\b\u00037\u0011#\u0019AA\u000f\u0011\u001d\t)K\ta\u0001\u0007?Cq!a+#\u0001\u0004\tI&A\u0004v]\u0006\u0004\b\u000f\\=\u0016\t\r-6q\u0017\u000b\u0005\u0007[\u001bI\fE\u0003|\u0007_\u001b\u0019,C\u0002\u00042r\u0014aa\u00149uS>t\u0007cB>\u0003\u000e\rU\u0016\u0011\f\t\u0005\u0003/\u00199\fB\u0004\u0002\u001c\r\u0012\r!!\b\t\u0013\rm6%!AA\u0002\ru\u0016a\u0001=%aA)\u0011Q\u0017\u0006\u00046\u0006aqO]5uKJ+\u0007\u000f\\1dKR\u001111\u0019\t\u0005\u0005\'\u001b)-\u0003\u0003\u0004H\nU%AB(cU\u0016\u001cG/A\u0004GC&dWO]3\u0011\u0007\u0005UVg\u0005\u00026uR\u001111\u001a\u000b\t\u0005+\u001a\u0019n!6\u0004X\"9!QL\u001cA\u0002\u0005\r\u0003bBAVo\u0001\u0007\u0011\u0011\f\u0005\b\u0005G:\u0004\u0019AAf)\u0011\u0019Yna9\u0011\u000bm\u001cyk!8\u0011\u0013m\u001cy.a\u0011\u0002Z\u0005-\u0017bABqy\n1A+\u001e9mKNBqa!:9\u0001\u0004\u0011)&A\u0001y\u0003%1wN]7bi6\u001bx\r\u0006\u0005\u0003\u0012\u000e-8Q^Bx\u0011\u001d\t\t.\u000fa\u0001\u0003+DqA!\u0001:\u0001\u0004\u0011)\u0001C\u0004\u0002,f\u0002\r!!\u0017\u0002\u0017\u0019|\'/\\1u\'R\f7m\u001b\u000b\u0007\u0003\u0007\u001a)pa>\t\u000f\u0005E\'\b1\u0001\u0002V\"9!\u0011\u0001\u001eA\u0002\t\u0015\u0011A\u00044pe6\fG\u000f\u0016:bS2Lgn\u001a\u000b\u0007\u0005#\u001bipa@\t\u000f\u0005E7\b1\u0001\u0002V\"9\u00111V\u001eA\u0002\u0005e\u0013!\u0004+sC\u000e,GMR1jYV\u0014X\rE\u0002\u000262\u001bB\u0001\u0014>\u0004\fR\u0011A1A\u000b\u0005\t\u0017!\u0019\u0002\u0006\u0003\u00036\u00115\u0001bBA=\u001d\u0002\u0007Aq\u0002\t\u0007\u0003\'\ti\b\"\u0005\u0011\t\u0005]A1\u0003\u0003\b\u00037q%\u0019AA\u000f)!\u0011)\u0004b\u0006\u0005\u001a\u0011m\u0001b\u0002B\u001e\u001f\u0002\u0007!q\b\u0005\b\u0005\u001bz\u0005\u0019\u0001B \u0011\u001d\u0011\tf\u0014a\u0001\u0005+\"B\u0001b\b\u0005$A)1pa,\u0005\"AI1pa8\u0003@\t}\"Q\u000b\u0005\n\u0007w\u0003\u0016\u0011!a\u0001\u0005kAqA!!\u0005\u0001\u0004!9\u0003E\u0005|\u0005\u000b\u000b)\"!\u0017\u00024U\u0011A1\u0006\t\u0006\u0003CR\u0011QC\u0015\u0004\u0001\u0015R\u0001
  #10 = Utf8               coursier/core/shaded/fastparse/Parsed$Extra
  #11 = Class              #10            // coursier/core/shaded/fastparse/Parsed$Extra
  #12 = Utf8               Extra
  #13 = Utf8               coursier/core/shaded/fastparse/Parsed$Failure
  #14 = Class              #13            // coursier/core/shaded/fastparse/Parsed$Failure
  #15 = Utf8               Failure
  #16 = Utf8               coursier/core/shaded/fastparse/Parsed$Failure$
  #17 = Class              #16            // coursier/core/shaded/fastparse/Parsed$Failure$
  #18 = Utf8
  #19 = Utf8               coursier/core/shaded/fastparse/Parsed$Success
  #20 = Class              #19            // coursier/core/shaded/fastparse/Parsed$Success
  #21 = Utf8               Success
  #22 = Utf8               coursier/core/shaded/fastparse/Parsed$Success$
  #23 = Class              #22            // coursier/core/shaded/fastparse/Parsed$Success$
  #24 = Utf8               coursier/core/shaded/fastparse/Parsed$TracedFailure
  #25 = Class              #24            // coursier/core/shaded/fastparse/Parsed$TracedFailure
  #26 = Utf8               TracedFailure
  #27 = Utf8               coursier/core/shaded/fastparse/Parsed$TracedFailure$
  #28 = Class              #27            // coursier/core/shaded/fastparse/Parsed$TracedFailure$
  #29 = Utf8               isSuccess
  #30 = Utf8               Z
  #31 = Utf8               fromParsingRun
  #32 = Utf8               (Lcoursier/core/shaded/fastparse/ParsingRun;)Lcoursier/core/shaded/fastparse/Parsed;
  #33 = Utf8               <T:Ljava/lang/Object;>(Lcoursier/core/shaded/fastparse/ParsingRun<TT;>;)Lcoursier/core/shaded/fastparse/Parsed<TT;>;
  #34 = Utf8               p
  #35 = Utf8               coursier/core/shaded/fastparse/Parsed$
  #36 = Class              #35            // coursier/core/shaded/fastparse/Parsed$
  #37 = Utf8               MODULE$
  #38 = Utf8               Lcoursier/core/shaded/fastparse/Parsed$;
  #39 = NameAndType        #37:#38        // MODULE$:Lcoursier/core/shaded/fastparse/Parsed$;
  #40 = Fieldref           #36.#39        // coursier/core/shaded/fastparse/Parsed$.MODULE$:Lcoursier/core/shaded/fastparse/Parsed$;
  #41 = NameAndType        #31:#32        // fromParsingRun:(Lcoursier/core/shaded/fastparse/ParsingRun;)Lcoursier/core/shaded/fastparse/Parsed;
  #42 = Methodref          #36.#41        // coursier/core/shaded/fastparse/Parsed$.fromParsingRun:(Lcoursier/core/shaded/fastparse/ParsingRun;)Lcoursier/core/shaded/fastparse/Parsed;
  #43 = Utf8               ()Z
  #44 = NameAndType        #29:#30        // isSuccess:Z
  #45 = Fieldref           #2.#44         // coursier/core/shaded/fastparse/Parsed.isSuccess:Z
  #46 = Utf8               this
  #47 = Utf8               Lcoursier/core/shaded/fastparse/Parsed;
  #48 = Utf8               fold
  #49 = Utf8               (Lscala/Function3;Lscala/Function2;)Ljava/lang/Object;
  #50 = Utf8               <V:Ljava/lang/Object;>(Lscala/Function3<Ljava/lang/String;Ljava/lang/Object;Lcoursier/core/shaded/fastparse/Parsed$Extra;TV;>;Lscala/Function2<TT;Ljava/lang/Object;TV;>;)TV;
  #51 = Utf8               onFailure
  #52 = Utf8               onSuccess
  #53 = Utf8               get
  #54 = Utf8               ()Lcoursier/core/shaded/fastparse/Parsed$Success;
  #55 = Utf8               ()Lcoursier/core/shaded/fastparse/Parsed$Success<TT;>;
  #56 = Utf8               <init>
  #57 = Utf8               (Z)V
  #58 = Utf8               ()V
  #59 = NameAndType        #56:#58        // "<init>":()V
  #60 = Methodref          #5.#59         // java/lang/Object."<init>":()V
  #61 = Utf8               Code
  #62 = Utf8               Signature
  #63 = Utf8               MethodParameters
  #64 = Utf8               LineNumberTable
  #65 = Utf8               LocalVariableTable
  #66 = Utf8               InnerClasses
  #67 = Utf8               SourceFile
  #68 = Utf8               RuntimeVisibleAnnotations
  #69 = Utf8               ScalaInlineInfo
  #70 = Utf8               ScalaSig
{
  private final boolean isSuccess;
    descriptor: Z
    flags: (0x0012) ACC_PRIVATE, ACC_FINAL

  public static <T extends java.lang.Object> coursier.core.shaded.fastparse.Parsed<T> fromParsingRun(coursier.core.shaded.fastparse.ParsingRun<T>);
    descriptor: (Lcoursier/core/shaded/fastparse/ParsingRun;)Lcoursier/core/shaded/fastparse/Parsed;
    flags: (0x0009) ACC_PUBLIC, ACC_STATIC
    Code:
      stack=2, locals=1, args_size=1
         0: getstatic     #40                 // Field coursier/core/shaded/fastparse/Parsed$.MODULE$:Lcoursier/core/shaded/fastparse/Parsed$;
         3: aload_0
         4: invokevirtual #42                 // Method coursier/core/shaded/fastparse/Parsed$.fromParsingRun:(Lcoursier/core/shaded/fastparse/ParsingRun;)Lcoursier/core/shaded/fastparse/Parsed;
         7: areturn
    Signature: #33                          // <T:Ljava/lang/Object;>(Lcoursier/core/shaded/fastparse/ParsingRun<TT;>;)Lcoursier/core/shaded/fastparse/Parsed<TT;>;
    MethodParameters:
      Name                           Flags
      p                              final

  public boolean isSuccess();
    descriptor: ()Z
    flags: (0x0001) ACC_PUBLIC
    Code:
      stack=1, locals=1, args_size=1
         0: aload_0
         1: getfield      #45                 // Field isSuccess:Z
         4: ireturn
      LineNumberTable:
        line 14: 0
      LocalVariableTable:
        Start  Length  Slot  Name   Signature
            0       5     0  this   Lcoursier/core/shaded/fastparse/Parsed;

  public abstract <V extends java.lang.Object> V fold(scala.Function3<java.lang.String, java.lang.Object, coursier.core.shaded.fastparse.Parsed$Extra, V>, scala.Function2<T, java.lang.Object, V>);
    descriptor: (Lscala/Function3;Lscala/Function2;)Ljava/lang/Object;
    flags: (0x0401) ACC_PUBLIC, ACC_ABSTRACT
    Signature: #50                          // <V:Ljava/lang/Object;>(Lscala/Function3<Ljava/lang/String;Ljava/lang/Object;Lcoursier/core/shaded/fastparse/Parsed$Extra;TV;>;Lscala/Function2<TT;Ljava/lang/Object;TV;>;)TV;
    MethodParameters:
      Name                           Flags
      onFailure                      final
      onSuccess                      final

  public abstract coursier.core.shaded.fastparse.Parsed$Success<T> get();
    descriptor: ()Lcoursier/core/shaded/fastparse/Parsed$Success;
    flags: (0x0401) ACC_PUBLIC, ACC_ABSTRACT
    Signature: #55                          // ()Lcoursier/core/shaded/fastparse/Parsed$Success<TT;>;

  public coursier.core.shaded.fastparse.Parsed(boolean);
    descriptor: (Z)V
    flags: (0x0001) ACC_PUBLIC
    Code:
      stack=2, locals=2, args_size=2
         0: aload_0
         1: iload_1
         2: putfield      #45                 // Field isSuccess:Z
         5: aload_0
         6: invokespecial #60                 // Method java/lang/Object."<init>":()V
         9: return
      LineNumberTable:
        line 14: 0
        line 19: 5
        line 14: 9
      LocalVariableTable:
        Start  Length  Slot  Name   Signature
            0      10     0  this   Lcoursier/core/shaded/fastparse/Parsed;
            0      10     1 isSuccess   Z
    MethodParameters:
      Name                           Flags
      isSuccess                      final
}
InnerClasses:
  public static #12= #11 of #2;           // Extra=class coursier/core/shaded/fastparse/Parsed$Extra of class coursier/core/shaded/fastparse/Parsed
  public static final #15= #14 of #2;     // Failure=class coursier/core/shaded/fastparse/Parsed$Failure of class coursier/core/shaded/fastparse/Parsed
  public static #18= #17 of #2;           // =class coursier/core/shaded/fastparse/Parsed$Failure$ of class coursier/core/shaded/fastparse/Parsed
  public static final #21= #20 of #2;     // Success=class coursier/core/shaded/fastparse/Parsed$Success of class coursier/core/shaded/fastparse/Parsed
  public static #18= #23 of #2;           // =class coursier/core/shaded/fastparse/Parsed$Success$ of class coursier/core/shaded/fastparse/Parsed
  public static #26= #25 of #2;           // TracedFailure=class coursier/core/shaded/fastparse/Parsed$TracedFailure of class coursier/core/shaded/fastparse/Parsed
  public static #18= #28 of #2;           // =class coursier/core/shaded/fastparse/Parsed$TracedFailure$ of class coursier/core/shaded/fastparse/Parsed
Signature: #3                           // <T:Ljava/lang/Object;>Ljava/lang/Object;
SourceFile: "Parsed.scala"
RuntimeVisibleAnnotations:
  0: #7(#8=s#9)
    scala.reflect.ScalaSignature(
      bytes="\u0006\u0005\u0011=b!\u0002;v\u0003CA\bBCA\u0001\u0001\t\u0015\r\u0011\"\u0001\u0002\u0004!Q\u00111\u0002\u0001\u0003\u0002\u0003\u0006I!!\u0002\t\u000f\u00055\u0001\u0001\"\u0001\u0002\u0010!9\u0011Q\u0006\u0001\u0007\u0002\u0005=\u0002bBA^\u0001\u0019\u0005A\u0011F\u0004\b\u0003G*\b\u0012AA3\r\u0019!X\u000f#\u0001\u0002h!9\u0011QB\u0004\u0005\u0002\u0005%\u0004bBA6\u000f\u0011\u0005\u0011Q\u000e\u0004\u0007\u0003\u0003;!)a!\t\u0015\u0005\u0015&B!f\u0001\n\u0003\t9\u000b\u0003\u0006\u0002**\u0011\t\u0012)A\u0005\u0003\u0013C!\"a+\u000b\u0005+\u0007I\u0011AAW\u0011)\tyK\u0003B\tB\u0003%\u0011\u0011\f\u0005\b\u0003\u001bQA\u0011AAY\u0011\u001d\tYL\u0003C\u0001\u0003{Cq!!\f\u000b\t\u0003\ty\fC\u0004\u0003\n*!\tEa#\t\u0013\t](\"!A\u0005\u0002\r]\u0003\"CB\u0001\u0015E\u0005I\u0011AB3\u0011%\u00199ACI\u0001\n\u0003\u0019i\u0007C\u0005\u0004\u0010)\t\t\u0011\"\u0011\u0003\u0010\"I1\u0011\u0003\u0006\u0002\u0002\u0013\u0005\u0011Q\u0016\u0005\n\u0007\'Q\u0011\u0011!C\u0001\u0007kB\u0011ba\u0007\u000b\u0003\u0003%\te!\b\t\u0013\r-\"\"!A\u0005\u0002\re\u0004\"CB\u0019\u0015\u0005\u0005I\u0011IB?\u0011%\u00199DCA\u0001\n\u0003\u001aI\u0004C\u0005\u0004>)\t\t\u0011\"\u0011\u0004\u0002\u001eI1QQ\u0004\u0002\u0002#\u00051q\u0011\u0004\n\u0003\u0003;\u0011\u0011!E\u0001\u0007\u0013Cq!!\u0004 \t\u0003\u0019)\nC\u0005\u0003\n~\t\t\u0011\"\u0012\u0004<!I1qS\u0010\u0002\u0002\u0013\u00055\u0011\u0014\u0005\n\u0007O{\u0012\u0011!CA\u0007SC\u0011ba0 \u0003\u0003%Ia!1\u0007\r\t]sA\u0001B-\u0011)\u0011i&\nBC\u0002\u0013\u0005!q\f\u0005\u000b\u0005C*#\u0011!Q\u0001\n\u0005\r\u0003BCAVK\t\u0015\r\u0011\"\u0001\u0002.\"Q\u0011qV\u0013\u0003\u0002\u0003\u0006I!!\u0017\t\u0015\t\rTE!b\u0001\n\u0003\u0011)\u0007\u0003\u0006\u0003h\u0015\u0012\t\u0011)A\u0005\u0003\u0017Dq!!\u0004&\t\u0003\u0011I\u0007C\u0004\u0002<\u0016\"\tA!\u001d\t\u000f\u00055R\u0005\"\u0001\u0003t!9!\u0011R\u0013\u0005B\t-\u0005b\u0002BGK\u0011\u0005!q\u0012\u0005\b\u0005?+C\u0011\u0001BH\u0011\u001d\u0011\t+\nC\u0001\u0005GC\u0011B!+&#\u0003%\tAa+\b\u000f\r%w\u0001#\u0001\u0004L\u001a9!qK\u0004\t\u0002\r5\u0007bBA\u0007k\u0011\u00051q\u001a\u0005\b\u0007/+D\u0011ABi\u0011\u001d\u00199+\u000eC\u0001\u00073Dqaa:6\t\u0003\u0019I\u000fC\u0004\u0004rV\"\taa=\t\u000f\reX\u0007\"\u0001\u0004|\u001a1\u0011QZ\u0004\u0001\u0003\u001fD!\"!5=\u0005\u000b\u0007I\u0011AAj\u0011)\tY\u000e\u0010B\u0001B\u0003%\u0011Q\u001b\u0005\u000b\u0003;d$Q1A\u0005\u0002\u00055\u0006BCApy\t\u0005\t\u0015!\u0003\u0002Z!Q\u00111\u0016\u001f\u0003\u0006\u0004%\t!!,\t\u0015\u0005=FH!A!\u0002\u0013\tI\u0006\u0003\u0006\u0002br\u0012)\u0019!C\u0001\u0003GD!\"!>=\u0005\u0003\u0005\u000b\u0011BAs\u0011)\u0011\t\u0001\u0010BC\u0002\u0013\u0005!1\u0001\u0005\u000b\u0005#a$\u0011!Q\u0001\n\t\u0015\u0001bBA\u0007y\u0011\u0005!1\u0003\u0005\b\u0005caD\u0011\u0001B\u001a\u0011\u001d\u0011\t\u000b\u0010C\u0001\u0007\u001fB\u0011B!+=#\u0003%\tAa+\b\u000f\u0011\u0005q\u0001#\u0001\u0005\u0004\u00199!qG\u0004\t\u0002\u0011\u0015\u0001bBA\u0007\u0019\u0012\u0005Aq\u0001\u0005\b\u0003WbE\u0011\u0001C\u0005\u0011%\u00199\nTA\u0001\n\u0003#)\u0002C\u0005\u0004(2\u000b\t\u0011\"!\u0005\u001e!I1q\u0018\'\u0002\u0002\u0013%1\u0011\u0019\u0004\u0007\u0005o9\u0001I!\u000f\t\u0015\tm\"K!f\u0001\n\u0003\u0011i\u0004\u0003\u0006\u0003LI\u0013\t\u0012)A\u0005\u0005\u007fA!B!\u0014S\u0005+\u0007I\u0011\u0001B\u001f\u0011)\u0011yE\u0015B\tB\u0003%!q\b\u0005\u000b\u0005#\u0012&Q3A\u0005\u0002\tM\u0003B\u0003Ba%\nE\t\u0015!\u0003\u0003V!9\u0011Q\u0002*\u0005\u0002\t\r\u0007b\u0002B/%\u0012\u0005!q\f\u0005\b\u0003W\u0013F\u0011AAW\u0011\u001d\t\tN\u0015C\u0001\u0003\'DqA!\u0001S\t\u0003\u0011\u0019\u0001C\u0004\u0003LJ#\tAa\u0018\t\u000f\t5\'\u000b\"\u0001\u0003`!9!\u0011\u0015*\u0005\u0002\t=\u0005b\u0002BG%\u0012\u0005!q\u0012\u0005\b\u0005_\u0014F\u0011\u0001BH\u0011\u001d\u0011\tP\u0015C\u0001\u0005\u001fCqAa(S\t\u0003\u0011y\tC\u0004\u0003tJ#\tAa$\t\u000f\tU(\u000b\"\u0001\u0003\u0010\"I!q\u001f*\u0002\u0002\u0013\u0005!\u0011 \u0005\n\u0007\u0003\u0011\u0016\u0013!C\u0001\u0007\u0007A\u0011ba\u0002S#\u0003%\taa\u0001\t\u0013\r%!+%A\u0005\u0002\r-\u0001\"CB\b%\u0006\u0005I\u0011\tBH\u0011%\u0019\tBUA\u0001\n\u0003\ti\u000bC\u0005\u0004\u0014I\u000b\t\u0011\"\u0001\u0004\u0016!I11\u0004*\u0002\u0002\u0013\u00053Q\u0004\u0005\n\u0007W\u0011\u0016\u0011!C\u0001\u0007[A\u0011b!\rS\u0003\u0003%\tea\r\t\u0013\r]\"+!A\u0005B\re\u0002\"\u0003BE%\u0006\u0005I\u0011IB\u001e\u0011%\u0019iDUA\u0001\n\u0003\u001ayD\u0001\u0004QCJ\u001cX\r\u001a\u0006\u0002m\u0006Ia-Y:ua\u0006\u00148/Z\u0002\u0001+\rI\u0018\u0011D\n\u0003\u0001i\u0004\"a\u001f@\u000e\u0003qT\u0011!`\u0001\u0006g\u000e\fG.Y\u0005\u0003\u007fr\u0014a!\u00118z%\u00164\u0017!C5t\'V\u001c7-Z:t+\t\t)\u0001E\u0002|\u0003\u000fI1!!\u0003}\u0005\u001d\u0011un\u001c7fC:\f!\"[:Tk\u000e\u001cWm]:!\u0003\u0019a\u0014N\\5u}Q!\u0011\u0011CA\u0016!\u0015\t\u0019\u0002AA\u000b\u001b\u0005)\b\u0003BA\f\u00033a\u0001\u0001\u0002\u0005\u0002\u001c\u0001!)\u0019AA\u000f\u0005\u0005!\u0016\u0003BA\u0010\u0003K\u00012a_A\u0011\u0013\r\t\u0019\u0003 \u0002\b\u001d>$\b.\u001b8h!\rY\u0018qE\u0005\u0004\u0003Sa(aA!os\"9\u0011\u0011A\u0002A\u0002\u0005\u0015\u0011\u0001\u00024pY\u0012,B!!\r\u00026Q1\u00111GA\u001d\tK\u0001B!a\u0006\u00026\u00119\u0011q\u0007\u0003C\u0002\u0005u!!\u0001,\t\u000f\u0005mB\u00011\u0001\u0002>\u0005IqN\u001c$bS2,(/\u001a\t\fw\u0006}\u00121IA-\u0003?\n\u0019$C\u0002\u0002Bq\u0014\u0011BR;oGRLwN\\\u001a\u0011\t\u0005\u0015\u00131\u000b\b\u0005\u0003\u000f\ny\u0005E\u0002\u0002Jql!!a\u0013\u000b\u0007\u00055s/\u0001\u0004=e>|GOP\u0005\u0004\u0003#b\u0018A\u0002)sK\u0012,g-\u0003\u0003\u0002V\u0005]#AB*ue&twMC\u0002\u0002Rq\u00042a_A.\u0013\r\ti\u0006 \u0002\u0004\u0013:$\bcAA1y9\u0019\u00111\u0003\u0004\u0002\rA\u000b\'o]3e!\r\t\u0019bB\n\u0003\u000fi$\"!!\u001a\u0002\u001d\u0019\u0014x.\u001c)beNLgn\u001a*v]V!\u0011qNA;)\u0011\t\t(a\u001e\u0011\u000b\u0005M\u0001!a\u001d\u0011\t\u0005]\u0011Q\u000f\u0003\b\u00037I!\u0019AA\u000f\u0011\u001d\tI(\u0003a\u0001\u0003w\n\u0011\u0001\u001d\t\u0007\u0003\'\ti(a\u001d\n\u0007\u0005}TO\u0001\u0006QCJ\u001c\u0018N\\4Sk:\u0014qaU;dG\u0016\u001c8/\u0006\u0003\u0002\u0006\u0006-5c\u0002\u0006\u0002\b\u00065\u00151\u0013\t\u0006\u0003\'\u0001\u0011\u0011\u0012\t\u0005\u0003/\tY\t\u0002\u0005\u0002\u001c)!)\u0019AA\u000f!\rY\u0018qR\u0005\u0004\u0003#c(a\u0002)s_\u0012,8\r\u001e\t\u0005\u0003+\u000byJ\u0004\u0003\u0002\u0018\u0006me\u0002BA%\u00033K\u0011!`\u0005\u0004\u0003;c\u0018a\u00029bG.\fw-Z\u0005\u0005\u0003C\u000b\u0019K\u0001\u0007TKJL\u0017\r\\5{C\ndWMC\u0002\u0002\u001er\fQA^1mk\u0016,\"!!#\u0002\rY\fG.^3!\u0003\u0015Ig\u000eZ3y+\t\tI&\u0001\u0004j]\u0012,\u0007\u0010\t\u000b\u0007\u0003g\u000b9,!/\u0011\u000b\u0005U&\"!#\u000e\u0003\u001dAq!!*\u0010\u0001\u0004\tI\tC\u0004\u0002,>\u0001\r!!\u0017\u0002\u0007\u001d,G/\u0006\u0002\u00024V!\u0011\u0011YAc)\u0019\t\u0019-a2\u0004TA!\u0011qCAc\t\u001d\t9$\u0005b\u0001\u0003;Aq!a\u000f\u0012\u0001\u0004\tI\rE\u0006|\u0003\u007f\t\u0019%!\u0017\u0002L\u0006\r\u0007cAA[y\t)Q\t\u001f;sCN\u0011AH_\u0001\u0006S:\u0004X\u000f^\u000b\u0003\u0003+\u0004B!a\u0005\u0002X&\u0019\u0011\u0011\\;\u0003\u0017A\u000b\'o]3s\u0013:\u0004X\u000f^\u0001\u0007S:\u0004X\u000f\u001e\u0011\u0002\u0015M$\u0018M\u001d;J]\u0012,\u00070A\u0006ti\u0006\u0014H/\u00138eKb\u0004\u0013AD8sS\u001eLg.\u00197QCJ\u001cXM]\u000b\u0003\u0003K\u0004ra_At\u0003W\f90C\u0002\u0002jr\u0014\u0011BR;oGRLwN\\\u00191\t\u00055\u0018\u0011\u001f\t\u0007\u0003\'\ti(a<\u0011\t\u0005]\u0011\u0011\u001f\u0003\f\u0003g$\u0015\u0011!A\u0001\u0006\u0003\tiBA\u0002`IE\nqb\u001c:jO&t\u0017\r\u001c)beN,\'\u000f\t\u0019\u0005\u0003s\fi\u0010\u0005\u0004\u0002\u0014\u0005u\u00141 \t\u0005\u0003/\ti\u0010B\u0006\u0002\u0000\u0012\u000b\t\u0011!A\u0003\u0002\u0005u!aA0%e\u0005)1\u000f^1dWV\u0011!Q\u0001\t\u0007\u0003+\u00139Aa\u0003\n\t\t%\u00111\u0015\u0002\u0005\u0019&\u001cH\u000fE\u0004|\u0005\u001b\t\u0019%!\u0017\n\u0007\t=AP\u0001\u0004UkBdWMM\u0001\u0007gR\f7m\u001b\u0011\u0015\u0019\u0005-\'Q\u0003B\f\u00053\u0011YBa\f\t\u000f\u0005Ew\t1\u0001\u0002V\"9\u0011Q\\$A\u0002\u0005e\u0003bBAV\u000f\u0002\u0007\u0011\u0011\f\u0005\b\u0003C<\u0005\u0019\u0001B\u000f!\u001dY\u0018q\u001dB\u0010\u0005O\u0001DA!\t\u0003&A1\u00111CA?\u0005G\u0001B!a\u0006\u0003&\u0011a\u00111\u001fB\u000e\u0003\u0003\u0005\tQ!\u0001\u0002\u001eA\"!\u0011\u0006B\u0017!\u0019\t\u0019\"! \u0003,A!\u0011q\u0003B\u0017\t1\tyPa\u0007\u0002\u0002\u0003\u0005)\u0011AA\u000f\u0011\u001d\u0011\ta\u0012a\u0001\u0005\u000b\ta\u0001\u001e:bG\u0016$WC\u0001B\u001b!\r\t)L\u0015\u0002\u000e)J\f7-\u001a3GC&dWO]3\u0014\rIS\u0018QRAJ\u0003%!XM]7j]\u0006d7/\u0006\u0002\u0003@A!!\u0011\tB$\u001b\t\u0011\u0019EC\u0002\u0003FU\f\u0001\"\u001b8uKJt\u0017\r\\\u0005\u0005\u0005\u0013\u0012\u0019E\u0001\u0003Ng\u001e\u001c\u0018A\u0003;fe6Lg.\u00197tA\u00051qM]8vaN\fqa\u001a:pkB\u001c\b%A\u0004gC&dWO]3\u0016\u0005\tU\u0003cAA[K\t9a)Y5mkJ,7cA\u0013\u0003\\A)\u00111\u0003\u0001\u0002 \u0005)A.\u00192fYV\u0011\u00111I\u0001\u0007Y\u0006\u0014W\r\u001c\u0011\u0002\u000b\u0015DHO]1\u0016\u0005\u0005-\u0017AB3yiJ\f\u0007\u0005\u0006\u0005\u0003V\t-$Q\u000eB8\u0011\u001d\u0011i\u0006\fa\u0001\u0003\u0007Bq!a+-\u0001\u0004\tI\u0006C\u0004\u0003d1\u0002\r!a3\u0016\u0005\u0005}Q\u0003\u0002B;\u0005s\"bAa\u001e\u0003|\t}\u0004\u0003BA\f\u0005s\"q!a\u000e/\u0005\u0004\ti\u0002C\u0004\u0002<9\u0002\rA! \u0011\u0017m\fy$a\u0011\u0002Z\u0005-\'q\u000f\u0005\b\u0005\u0003s\u0003\u0019\u0001BB\u0003%ygnU;dG\u0016\u001c8\u000fE\u0005|\u0005\u000b\u000by\"!\u0017\u0003x%\u0019!q\u0011?\u0003\u0013\u0019+hn\u0019;j_:\u0014\u0014\u0001\u0003;p\'R\u0014\u0018N\\4\u0015\u0005\u0005\r\u0013aA7tOV\u0011!\u0011\u0013\t\u0005\u0005\'\u0013i*\u0004\u0002\u0003\u0016*!!q\u0013BM\u0003\u0011a\u0017M\\4\u000b\u0005\tm\u0015\u0001\u00026bm\u0006LA!!\u0016\u0003\u0016\u00069An\u001c8h\u001bN<\u0017!\u0002;sC\u000e,G\u0003\u0002B\u001b\u0005KC\u0011Ba*3!\u0003\u0005\r!!\u0002\u0002\u001b\u0015t\u0017M\u00197f\u0019><w-\u001b8h\u0003=!(/Y2fI\u0011,g-Y;mi\u0012\nTC\u0001BWU\u0011\t)Aa,,\u0005\tE\u0006\u0003\u0002BZ\u0005{k!A!.\u000b\t\t]&\u0011X\u0001\nk:\u001c\u0007.Z2lK\u0012T1Aa/}\u0003)\tgN\\8uCRLwN\\\u0005\u0005\u0005\u007f\u0013)LA\tv]\u000eDWmY6fIZ\u000b\'/[1oG\u0016\f\u0001BZ1jYV\u0014X\r\t\u000b\t\u0005k\u0011)Ma2\u0003J\"9!1H-A\u0002\t}\u0002b\u0002B\'3\u0002\u0007!q\b\u0005\b\u0005#J\u0006\u0019\u0001B+\u0003]!XM]7j]\u0006d\u0017iZ4sK\u001e\fG/Z*ue&tw-\u0001\u000bhe>,\b/Q4he\u0016<\u0017\r^3TiJLgn\u001a\u0015\bA\nE\'q\u001bBn!\rY(1[\u0005\u0004\u0005+d(A\u00033faJ,7-\u0019;fI\u0006\u0012!\u0011\\\u0001\u0011+N,\u0007EL7tO\u0002Jgn\u001d;fC\u0012\f\u0014bIA\"\u0005;\u0014)Oa8\n\t\t}\'\u0011]\u0001\u001cI1,7o]5oSR$sM]3bi\u0016\u0014H\u0005Z3gCVdG\u000f\n\u001a\u000b\u0007\t\rH0\u0001\u0006eKB\u0014XmY1uK\u0012\f\u0014b\tBt\u0005S\u0014YOa9\u000f\u0007m\u0014I/C\u0002\u0003dr\fTAI>}\u0005[\u0014Qa]2bY\u0006\fA\u0002^3s[&t\u0017\r\\:Ng\u001e\fA\"Y4he\u0016<\u0017\r^3Ng\u001e\f\u0001\u0003\\8oOR+\'/\\5oC2\u001cXj]4\u0002!1|gnZ!hOJ,w-\u0019;f\u001bN<\u0017\u0001B2paf$\u0002B!\u000e\u0003|\nu(q \u0005\n\u0005w9\u0007\u0013!a\u0001\u0005\u007fA\u0011B!\u0014h!\u0003\u0005\rAa\u0010\t\u0013\tEs\r%AA\u0002\tU\u0013AD2paf$C-\u001a4bk2$H%M\u000b\u0003\u0007\u000bQCAa\u0010\u00030\u0006q1m\u001c9zI\u0011,g-Y;mi\u0012\u0012\u0014AD2paf$C-\u001a4bk2$HeM\u000b\u0003\u0007\u001bQCA!\u0016\u00030\u0006i\u0001O]8ek\u000e$\bK]3gSb\fA\u0002\u001d:pIV\u001cG/\u0011:jif\fa\u0002\u001d:pIV\u001cG/\u00127f[\u0016tG\u000f\u0006\u0003\u0002&\r]\u0001\"CB\r[\u0006\u0005\t\u0019AA-\u0003\rAH%M\u0001\u0010aJ|G-^2u\u0013R,\'/\u0019;peV\u00111q\u0004\t\u0007\u0007C\u00199#!\n\u000e\u0005\r\r\"bAB\u0013y\u0006Q1m\u001c7mK\u000e$\u0018n\u001c8\n\t\r%21\u0005\u0002\t\u0013R,\'/\u0019;pe\u0006A1-\u00198FcV\fG\u000e\u0006\u0003\u0002\u0006\r=\u0002\"CB\r_\u0006\u0005\t\u0019AA\u0013\u0003I\u0001(o\u001c3vGR,E.Z7f]Rt\u0015-\\3\u0015\t\tE5Q\u0007\u0005\n\u00073\u0001\u0018\u0011!a\u0001\u00033\n\u0001\u0002[1tQ\u000e{G-\u001a\u000b\u0003\u00033\"\"A!%\u0002\r\u0015\fX/\u00197t)\u0011\t)a!\u0011\t\u0013\re1/!AA\u0002\u0005\u0015\u0002f\u0002%\u0003R\u000e\u00153\u0011J\u0011\u0003\u0007\u000f\n!#V:fA9\"(/Y2fA%t7\u000f^3bIFJ1%a\u0011\u0003^\u000e-#q\\\u0019\nG\t\u001d(\u0011^B\'\u0005G\fTAI>}\u0005[$BA!\u000e\u0004R!I!qU%\u0011\u0002\u0003\u0007\u0011Q\u0001\u0005\b\u0005\u0003\u000b\u0002\u0019AB+!%Y(QQAE\u00033\n\u0019-\u0006\u0003\u0004Z\r}CCBB.\u0007C\u001a\u0019\u0007E\u0003\u00026*\u0019i\u0006\u0005\u0003\u0002\u0018\r}CaBA\u000e\'\t\u0007\u0011Q\u0004\u0005\n\u0003K\u001b\u0002\u0013!a\u0001\u0007;B\u0011\"a+\u0014!\u0003\u0005\r!!\u0017\u0016\t\r\u001d41N\u000b\u0003\u0007SRC!!#\u00030\u00129\u00111\u0004\u000bC\u0002\u0005uQ\u0003BB8\u0007g*\"a!\u001d+\t\u0005e#q\u0016\u0003\b\u00037)\"\u0019AA\u000f)\u0011\t)ca\u001e\t\u0013\re\u0001$!AA\u0002\u0005eC\u0003BA\u0003\u0007wB\u0011b!\u0007\u001b\u0003\u0003\u0005\r!!\n\u0015\t\tE5q\u0010\u0005\n\u00073Y\u0012\u0011!a\u0001\u00033\"B!!\u0002\u0004\u0004\"I1\u0011D\u000f\u0002\u0002\u0003\u0007\u0011QE\u0001\b\'V\u001c7-Z:t!\r\t)lH\n\u0005?i\u001cY\t\u0005\u0003\u0004\u000e\u000eMUBABH\u0015\u0011\u0019\tJ!\'\u0002\u0005%|\u0017\u0002BAQ\u0007\u001f#\"aa\"\u0002\u000b\u0005\u0004\b\u000f\\=\u0016\t\rm5\u0011\u0015\u000b\u0007\u0007;\u001b\u0019k!*\u0011\u000b\u0005U&ba(\u0011\t\u0005]1\u0011\u0015\u0003\b\u00037\u0011#\u0019AA\u000f\u0011\u001d\t)K\ta\u0001\u0007?Cq!a+#\u0001\u0004\tI&A\u0004v]\u0006\u0004\b\u000f\\=\u0016\t\r-6q\u0017\u000b\u0005\u0007[\u001bI\fE\u0003|\u0007_\u001b\u0019,C\u0002\u00042r\u0014aa\u00149uS>t\u0007cB>\u0003\u000e\rU\u0016\u0011\f\t\u0005\u0003/\u00199\fB\u0004\u0002\u001c\r\u0012\r!!\b\t\u0013\rm6%!AA\u0002\ru\u0016a\u0001=%aA)\u0011Q\u0017\u0006\u00046\u0006aqO]5uKJ+\u0007\u000f\\1dKR\u001111\u0019\t\u0005\u0005\'\u001b)-\u0003\u0003\u0004H\nU%AB(cU\u0016\u001cG/A\u0004GC&dWO]3\u0011\u0007\u0005UVg\u0005\u00026uR\u001111\u001a\u000b\t\u0005+\u001a\u0019n!6\u0004X\"9!QL\u001cA\u0002\u0005\r\u0003bBAVo\u0001\u0007\u0011\u0011\f\u0005\b\u0005G:\u0004\u0019AAf)\u0011\u0019Yna9\u0011\u000bm\u001cyk!8\u0011\u0013m\u001cy.a\u0011\u0002Z\u0005-\u0017bABqy\n1A+\u001e9mKNBqa!:9\u0001\u0004\u0011)&A\u0001y\u0003%1wN]7bi6\u001bx\r\u0006\u0005\u0003\u0012\u000e-8Q^Bx\u0011\u001d\t\t.\u000fa\u0001\u0003+DqA!\u0001:\u0001\u0004\u0011)\u0001C\u0004\u0002,f\u0002\r!!\u0017\u0002\u0017\u0019|\'/\\1u\'R\f7m\u001b\u000b\u0007\u0003\u0007\u001a)pa>\t\u000f\u0005E\'\b1\u0001\u0002V\"9!\u0011\u0001\u001eA\u0002\t\u0015\u0011A\u00044pe6\fG\u000f\u0016:bS2Lgn\u001a\u000b\u0007\u0005#\u001bipa@\t\u000f\u0005E7\b1\u0001\u0002V\"9\u00111V\u001eA\u0002\u0005e\u0013!\u0004+sC\u000e,GMR1jYV\u0014X\rE\u0002\u000262\u001bB\u0001\u0014>\u0004\fR\u0011A1A\u000b\u0005\t\u0017!\u0019\u0002\u0006\u0003\u00036\u00115\u0001bBA=\u001d\u0002\u0007Aq\u0002\t\u0007\u0003\'\ti\b\"\u0005\u0011\t\u0005]A1\u0003\u0003\b\u00037q%\u0019AA\u000f)!\u0011)\u0004b\u0006\u0005\u001a\u0011m\u0001b\u0002B\u001e\u001f\u0002\u0007!q\b\u0005\b\u0005\u001bz\u0005\u0019\u0001B \u0011\u001d\u0011\tf\u0014a\u0001\u0005+\"B\u0001b\b\u0005$A)1pa,\u0005\"AI1pa8\u0003@\t}\"Q\u000b\u0005\n\u0007w\u0003\u0016\u0011!a\u0001\u0005kAqA!!\u0005\u0001\u0004!9\u0003E\u0005|\u0005\u000b\u000b)\"!\u0017\u00024U\u0011A1\u0006\t\u0006\u0003CR\u0011QC\u0015\u0004\u0001\u0015R\u0001"
    )
  ScalaInlineInfo: length = 0x18 (unknown attribute)
   01 00 00 04 00 3A 00 3B 01 00 32 00 33 00 00 37
   00 38 00 00 1F 00 2D 01
  ScalaSig: length = 0x3 (unknown attribute)
   05 02 00
