Classfile /Users/mw/Projects/slang-braindump/.jar/jar11/assemble/slang-braindump/assemble/content/coursier/core/shaded/fastparse/ParserInputSourceLowPri.class
  Last modified May 29, 2022; size 3548 bytes
  SHA-256 checksum 659da069aca8f7473c2e5c0b33715fb50d2bca0b4a6cfc9b3e01ca28c4b94a20
  Compiled from "ParserInput.scala"
public interface coursier.core.shaded.fastparse.ParserInputSourceLowPri
  minor version: 0
  major version: 52
  flags: (0x0601) ACC_PUBLIC, ACC_INTERFACE, ACC_ABSTRACT
  this_class: #2                          // coursier/core/shaded/fastparse/ParserInputSourceLowPri
  super_class: #4                         // java/lang/Object
  interfaces: 0, fields: 0, methods: 4, attributes: 5
Constant pool:
   #1 = Utf8               coursier/core/shaded/fastparse/ParserInputSourceLowPri
   #2 = Class              #1             // coursier/core/shaded/fastparse/ParserInputSourceLowPri
   #3 = Utf8               java/lang/Object
   #4 = Class              #3             // java/lang/Object
   #5 = Utf8               ParserInput.scala
   #6 = Utf8               Lscala/reflect/ScalaSignature;
   #7 = Utf8               bytes
   #8 = Utf8               \u0006\u0005\u0005eea\u0002\u000f\u001e!\u0003\r\t\u0001\t\u0005\u0006O\u0001!\t\u0001\u000b\u0005\u0006Y\u0001!\u0019!\f\u0004\u0005e\u0001\u00015\u0007\u0003\u0005H\u0007\tU\r\u0011\"\u0001I\u0011!y5A!E!\u0002\u0013I\u0005\u0002\u0003)\u0004\u0005+\u0007I\u0011A)\t\u0011U\u001b!\u0011#Q\u0001\nICQAV\u0002\u0005\u0002]CQAW\u0002\u0005\u0002mCq\u0001]\u0002\u0002\u0002\u0013\u0005\u0011\u000fC\u0004u\u0007E\u0005I\u0011A;\t\u0013\u0005\u00051!%A\u0005\u0002\u0005\r\u0001\"CA\u0004\u0007\u0005\u0005I\u0011IA\u0005\u0011!\tYbAA\u0001\n\u0003\t\u0006\"CA\u000f\u0007\u0005\u0005I\u0011AA\u0010\u0011%\t)cAA\u0001\n\u0003\n9\u0003C\u0005\u00026\r\t\t\u0011\"\u0001\u00028!I\u0011\u0011I\u0002\u0002\u0002\u0013\u0005\u00131\t\u0005\n\u0003\u000f\u001a\u0011\u0011!C!\u0003\u0013B\u0011\"a\u0013\u0004\u0003\u0003%\t%!\u0014\t\u0013\u0005=3!!A\u0005B\u0005Es!CA0\u0001\u0005\u0005\t\u0012AA1\r!\u0011\u0004!!A\t\u0002\u0005\r\u0004B\u0002,\u0018\t\u0003\tY\bC\u0005\u0002L]\t\t\u0011\"\u0012\u0002N!I\u0011QP\f\u0002\u0002\u0013\u0005\u0015q\u0010\u0005\n\u0003\u000b;\u0012\u0011!CA\u0003\u000f\u0013q\u0003U1sg\u0016\u0014\u0018J\u001c9viN{WO]2f\u0019><\bK]5\u000b\u0003y\t\u0011BZ1tiB\f\'o]3\u0004\u0001M\u0011\u0001!\t\t\u0003E\u0015j\u0011a\t\u0006\u0002I\u0005)1oY1mC&\u0011ae\t\u0002\u0007\u0003:L(+\u001a4\u0002\r\u0011Jg.\u001b;%)\u0005I\u0003C\u0001\u0012+\u0013\tY3E\u0001\u0003V]&$\u0018\u0001\u00044s_6\u0014V-\u00193bE2,Wc\u0001\u0018\u0002\\Q\u0019q&!\u0018\u0015\u0007A\n)\u0006\u0005\u00022\u00075\t\u0001A\u0001\u0007Ge>l\'+Z1eC\ndWmE\u0003\u0004CQB4\b\u0005\u00026m5\tQ$\u0003\u00028;\t\t\u0002+\u0019:tKJLe\u000e];u\'>,(oY3\u0011\u0005\tJ\u0014B\u0001\u001e$\u0005\u001d\u0001&o\u001c3vGR\u0004\"\u0001\u0010#\u000f\u0005u\u0012eB\u0001 B\u001b\u0005y$B\u0001! \u0003\u0019a$o\\8u}%\tA%\u0003\u0002DG\u00059\u0001/Y2lC\u001e,\u0017BA#G\u00051\u0019VM]5bY&T\u0018M\u00197f\u0015\t\u00195%A\u0001t+\u0005I\u0005C\u0001&N\u001b\u0005Y%\"\u0001\'\u0002\t\u001d,g._\u0005\u0003\u001d.\u0013\u0001BU3bI\u0006\u0014G.Z\u0001\u0003g\u0002\n!BY;gM\u0016\u00148+\u001b>f+\u0005\u0011\u0006C\u0001\u0012T\u0013\t!6EA\u0002J]R\f1BY;gM\u0016\u00148+\u001b>fA\u00051A(\u001b8jiz\"2\u0001\r-Z\u0011\u00159\u0005\u00021\u0001J\u0011\u0015\u0001\u0006\u00021\u0001S\u00031\u0001\u0018M]:f)\"\u0014x.^4i+\tav\f\u0006\u0002^QB\u0011al\u0018\u0007\u0001\t\u0015\u0001\u0017B1\u0001b\u0005\u0005!\u0016C\u00012f!\t\u00113-\u0003\u0002eG\t9aj\u001c;iS:<\u0007C\u0001\u0012g\u0013\t97EA\u0002B]fDQ![\u0005A\u0002)\f\u0011A\u001a\t\u0005E-lW,\u0003\u0002mG\tIa)\u001e8di&|g.\r\t\u0003k9L!a\\\u000f\u0003\u0017A\u000b\'o]3s\u0013:\u0004X\u000f^\u0001\u0005G>\u0004\u0018\u0010F\u00021eNDqa\u0012\u0006\u0011\u0002\u0003\u0007\u0011\nC\u0004Q\u0015A\u0005\t\u0019\u0001*\u0002\u001d\r|\u0007/\u001f\u0013eK\u001a\fW\u000f\u001c;%cU\taO\u000b\u0002Jo.\n\u0001\u0010\u0005\u0002z}6\t!P\u0003\u0002|y\u0006IQO\\2iK\u000e\\W\r\u001a\u0006\u0003{\u000e\n!\"\u00198o_R\fG/[8o\u0013\ty(PA\tv]\u000eDWmY6fIZ\u000b\'/[1oG\u0016\fabY8qs\u0012\"WMZ1vYR$#\'\u0006\u0002\u0002\u0006)\u0012!k^\u0001\u000eaJ|G-^2u!J,g-\u001b=\u0016\u0005\u0005-\u0001\u0003BA\u0007\u0003/i!!a\u0004\u000b\t\u0005E\u00111C\u0001\u0005Y\u0006twM\u0003\u0002\u0002\u0016\u0005!!.\u0019<b\u0013\u0011\tI\"a\u0004\u0003\rM#(/\u001b8h\u00031\u0001(o\u001c3vGR\f%/\u001b;z\u00039\u0001(o\u001c3vGR,E.Z7f]R$2!ZA\u0011\u0011!\t\u0019cDA\u0001\u0002\u0004\u0011\u0016a\u0001=%c\u0005y\u0001O]8ek\u000e$\u0018\n^3sCR|\'/\u0006\u0002\u0002*A)\u00111FA\u0019K6\u0011\u0011Q\u0006\u0006\u0004\u0003_\u0019\u0013AC2pY2,7\r^5p]&!\u00111GA\u0017\u0005!IE/\u001a:bi>\u0014\u0018\u0001C2b]\u0016\u000bX/\u00197\u0015\t\u0005e\u0012q\b\t\u0004E\u0005m\u0012bAA\u001fG\t9!i\\8mK\u0006t\u0007\u0002CA\u0012#\u0005\u0005\t\u0019A3\u0002%A\u0014x\u000eZ;di\u0016cW-\\3oi:\u000bW.\u001a\u000b\u0005\u0003\u0017\t)\u0005\u0003\u0005\u0002$I\t\t\u00111\u0001S\u0003!A\u0017m\u001d5D_\u0012,G#\u0001*\u0002\u0011Q|7\u000b\u001e:j]\u001e$\"!a\u0003\u0002\r\u0015\fX/\u00197t)\u0011\tI$a\u0015\t\u0011\u0005\rR#!AA\u0002\u0015Da!\u001b\u0002A\u0004\u0005]\u0003#\u0002\u0012l\u00033J\u0005c\u00010\u0002\\\u0011)\u0001M\u0001b\u0001C\"1qI\u0001a\u0001\u00033\nAB\u0012:p[J+\u0017\rZ1cY\u0016\u0004\"!M\f\u0014\u000b]\t)\'!\u001d\u0011\u000f\u0005\u001d\u0014QN%Sa5\u0011\u0011\u0011\u000e\u0006\u0004\u0003W\u001a\u0013a\u0002:v]RLW.Z\u0005\u0005\u0003_\nIGA\tBEN$(/Y2u\rVt7\r^5p]J\u0002B!a\u001d\u0002z5\u0011\u0011Q\u000f\u0006\u0005\u0003o\n\u0019\"\u0001\u0002j_&\u0019Q)!\u001e\u0015\u0005\u0005\u0005\u0014!B1qa2LH#\u0002\u0019\u0002\u0002\u0006\r\u0005\"B$\u001b\u0001\u0004I\u0005\"\u0002)\u001b\u0001\u0004\u0011\u0016aB;oCB\u0004H.\u001f\u000b\u0005\u0003\u0013\u000b)\nE\u0003#\u0003\u0017\u000by)C\u0002\u0002\u000e\u000e\u0012aa\u00149uS>t\u0007#\u0002\u0012\u0002\u0012&\u0013\u0016bAAJG\t1A+\u001e9mKJB\u0001\"a&\u001c\u0003\u0003\u0005\r\u0001M\u0001\u0004q\u0012\u0002\u0004
   #9 = Utf8               coursier/core/shaded/fastparse/ParserInputSourceLowPri$FromReadable
  #10 = Class              #9             // coursier/core/shaded/fastparse/ParserInputSourceLowPri$FromReadable
  #11 = Utf8               FromReadable
  #12 = Utf8               coursier/core/shaded/fastparse/ParserInputSourceLowPri$FromReadable$
  #13 = Class              #12            // coursier/core/shaded/fastparse/ParserInputSourceLowPri$FromReadable$
  #14 = Utf8
  #15 = Utf8               ()Lcoursier/core/shaded/fastparse/ParserInputSourceLowPri$FromReadable$;
  #16 = Utf8               fromReadable$
  #17 = Utf8               (Lcoursier/core/shaded/fastparse/ParserInputSourceLowPri;Ljava/lang/Object;Lscala/Function1;)Lcoursier/core/shaded/fastparse/ParserInputSourceLowPri$FromReadable;
  #18 = Utf8               $this
  #19 = Utf8               s
  #20 = Utf8               f
  #21 = Utf8               fromReadable
  #22 = Utf8               (Ljava/lang/Object;Lscala/Function1;)Lcoursier/core/shaded/fastparse/ParserInputSourceLowPri$FromReadable;
  #23 = NameAndType        #21:#22        // fromReadable:(Ljava/lang/Object;Lscala/Function1;)Lcoursier/core/shaded/fastparse/ParserInputSourceLowPri$FromReadable;
  #24 = InterfaceMethodref #2.#23         // coursier/core/shaded/fastparse/ParserInputSourceLowPri.fromReadable:(Ljava/lang/Object;Lscala/Function1;)Lcoursier/core/shaded/fastparse/ParserInputSourceLowPri$FromReadable;
  #25 = Utf8               Lcoursier/core/shaded/fastparse/ParserInputSourceLowPri;
  #26 = Utf8               Ljava/lang/Object;
  #27 = Utf8               Lscala/Function1;
  #28 = Utf8               <T:Ljava/lang/Object;>(TT;Lscala/Function1<TT;Lcoursier/core/shaded/geny/Readable;>;)Lcoursier/core/shaded/fastparse/ParserInputSourceLowPri$FromReadable;
  #29 = Utf8               scala/Function1
  #30 = Class              #29            // scala/Function1
  #31 = Utf8               apply
  #32 = Utf8               (Ljava/lang/Object;)Ljava/lang/Object;
  #33 = NameAndType        #31:#32        // apply:(Ljava/lang/Object;)Ljava/lang/Object;
  #34 = InterfaceMethodref #30.#33        // scala/Function1.apply:(Ljava/lang/Object;)Ljava/lang/Object;
  #35 = Utf8               coursier/core/shaded/geny/Readable
  #36 = Class              #35            // coursier/core/shaded/geny/Readable
  #37 = Utf8               <init>
  #38 = Utf8               (Lcoursier/core/shaded/fastparse/ParserInputSourceLowPri;Lcoursier/core/shaded/geny/Readable;I)V
  #39 = NameAndType        #37:#38        // "<init>":(Lcoursier/core/shaded/fastparse/ParserInputSourceLowPri;Lcoursier/core/shaded/geny/Readable;I)V
  #40 = Methodref          #10.#39        // coursier/core/shaded/fastparse/ParserInputSourceLowPri$FromReadable."<init>":(Lcoursier/core/shaded/fastparse/ParserInputSourceLowPri;Lcoursier/core/shaded/geny/Readable;I)V
  #41 = Utf8               this
  #42 = Utf8               $init$
  #43 = Utf8               (Lcoursier/core/shaded/fastparse/ParserInputSourceLowPri;)V
  #44 = Utf8               Code
  #45 = Utf8               LineNumberTable
  #46 = Utf8               LocalVariableTable
  #47 = Utf8               MethodParameters
  #48 = Utf8               Signature
  #49 = Utf8               InnerClasses
  #50 = Utf8               SourceFile
  #51 = Utf8               RuntimeVisibleAnnotations
  #52 = Utf8               ScalaInlineInfo
  #53 = Utf8               ScalaSig
{
  public abstract coursier.core.shaded.fastparse.ParserInputSourceLowPri$FromReadable$ FromReadable();
    descriptor: ()Lcoursier/core/shaded/fastparse/ParserInputSourceLowPri$FromReadable$;
    flags: (0x0401) ACC_PUBLIC, ACC_ABSTRACT

  public static coursier.core.shaded.fastparse.ParserInputSourceLowPri$FromReadable fromReadable$(coursier.core.shaded.fastparse.ParserInputSourceLowPri, java.lang.Object, scala.Function1);
    descriptor: (Lcoursier/core/shaded/fastparse/ParserInputSourceLowPri;Ljava/lang/Object;Lscala/Function1;)Lcoursier/core/shaded/fastparse/ParserInputSourceLowPri$FromReadable;
    flags: (0x1009) ACC_PUBLIC, ACC_STATIC, ACC_SYNTHETIC
    Code:
      stack=3, locals=3, args_size=3
         0: aload_0
         1: aload_1
         2: aload_2
         3: invokespecial #24                 // InterfaceMethod fromReadable:(Ljava/lang/Object;Lscala/Function1;)Lcoursier/core/shaded/fastparse/ParserInputSourceLowPri$FromReadable;
         6: areturn
      LineNumberTable:
        line 31: 0
      LocalVariableTable:
        Start  Length  Slot  Name   Signature
            0       7     0 $this   Lcoursier/core/shaded/fastparse/ParserInputSourceLowPri;
            0       7     1     s   Ljava/lang/Object;
            0       7     2     f   Lscala/Function1;
    MethodParameters:
      Name                           Flags
      $this                          final synthetic
      s                              final
      f                              final

  public default <T extends java.lang.Object> coursier.core.shaded.fastparse.ParserInputSourceLowPri$FromReadable fromReadable(T, scala.Function1<T, coursier.core.shaded.geny.Readable>);
    descriptor: (Ljava/lang/Object;Lscala/Function1;)Lcoursier/core/shaded/fastparse/ParserInputSourceLowPri$FromReadable;
    flags: (0x0001) ACC_PUBLIC
    Code:
      stack=5, locals=3, args_size=3
         0: new           #10                 // class coursier/core/shaded/fastparse/ParserInputSourceLowPri$FromReadable
         3: dup
         4: aload_0
         5: aload_2
         6: aload_1
         7: invokeinterface #34,  2           // InterfaceMethod scala/Function1.apply:(Ljava/lang/Object;)Ljava/lang/Object;
        12: checkcast     #36                 // class coursier/core/shaded/geny/Readable
        15: sipush        4096
        18: invokespecial #40                 // Method coursier/core/shaded/fastparse/ParserInputSourceLowPri$FromReadable."<init>":(Lcoursier/core/shaded/fastparse/ParserInputSourceLowPri;Lcoursier/core/shaded/geny/Readable;I)V
        21: areturn
      LineNumberTable:
        line 31: 0
        line 32: 5
        line 46: 15
      LocalVariableTable:
        Start  Length  Slot  Name   Signature
            0      22     0  this   Lcoursier/core/shaded/fastparse/ParserInputSourceLowPri;
            0      22     1     s   Ljava/lang/Object;
            0      22     2     f   Lscala/Function1;
    Signature: #28                          // <T:Ljava/lang/Object;>(TT;Lscala/Function1<TT;Lcoursier/core/shaded/geny/Readable;>;)Lcoursier/core/shaded/fastparse/ParserInputSourceLowPri$FromReadable;
    MethodParameters:
      Name                           Flags
      s                              final
      f                              final

  public static void $init$(coursier.core.shaded.fastparse.ParserInputSourceLowPri);
    descriptor: (Lcoursier/core/shaded/fastparse/ParserInputSourceLowPri;)V
    flags: (0x0009) ACC_PUBLIC, ACC_STATIC
    Code:
      stack=0, locals=1, args_size=1
         0: return
      LineNumberTable:
        line 29: 0
      LocalVariableTable:
        Start  Length  Slot  Name   Signature
            0       1     0 $this   Lcoursier/core/shaded/fastparse/ParserInputSourceLowPri;
    MethodParameters:
      Name                           Flags
      $this                          final synthetic
}
InnerClasses:
  public #11= #10 of #2;                  // FromReadable=class coursier/core/shaded/fastparse/ParserInputSourceLowPri$FromReadable of class coursier/core/shaded/fastparse/ParserInputSourceLowPri
  public #14= #13 of #2;                  // =class coursier/core/shaded/fastparse/ParserInputSourceLowPri$FromReadable$ of class coursier/core/shaded/fastparse/ParserInputSourceLowPri
SourceFile: "ParserInput.scala"
RuntimeVisibleAnnotations:
  0: #6(#7=s#8)
    scala.reflect.ScalaSignature(
      bytes="\u0006\u0005\u0005eea\u0002\u000f\u001e!\u0003\r\t\u0001\t\u0005\u0006O\u0001!\t\u0001\u000b\u0005\u0006Y\u0001!\u0019!\f\u0004\u0005e\u0001\u00015\u0007\u0003\u0005H\u0007\tU\r\u0011\"\u0001I\u0011!y5A!E!\u0002\u0013I\u0005\u0002\u0003)\u0004\u0005+\u0007I\u0011A)\t\u0011U\u001b!\u0011#Q\u0001\nICQAV\u0002\u0005\u0002]CQAW\u0002\u0005\u0002mCq\u0001]\u0002\u0002\u0002\u0013\u0005\u0011\u000fC\u0004u\u0007E\u0005I\u0011A;\t\u0013\u0005\u00051!%A\u0005\u0002\u0005\r\u0001\"CA\u0004\u0007\u0005\u0005I\u0011IA\u0005\u0011!\tYbAA\u0001\n\u0003\t\u0006\"CA\u000f\u0007\u0005\u0005I\u0011AA\u0010\u0011%\t)cAA\u0001\n\u0003\n9\u0003C\u0005\u00026\r\t\t\u0011\"\u0001\u00028!I\u0011\u0011I\u0002\u0002\u0002\u0013\u0005\u00131\t\u0005\n\u0003\u000f\u001a\u0011\u0011!C!\u0003\u0013B\u0011\"a\u0013\u0004\u0003\u0003%\t%!\u0014\t\u0013\u0005=3!!A\u0005B\u0005Es!CA0\u0001\u0005\u0005\t\u0012AA1\r!\u0011\u0004!!A\t\u0002\u0005\r\u0004B\u0002,\u0018\t\u0003\tY\bC\u0005\u0002L]\t\t\u0011\"\u0012\u0002N!I\u0011QP\f\u0002\u0002\u0013\u0005\u0015q\u0010\u0005\n\u0003\u000b;\u0012\u0011!CA\u0003\u000f\u0013q\u0003U1sg\u0016\u0014\u0018J\u001c9viN{WO]2f\u0019><\bK]5\u000b\u0003y\t\u0011BZ1tiB\f\'o]3\u0004\u0001M\u0011\u0001!\t\t\u0003E\u0015j\u0011a\t\u0006\u0002I\u0005)1oY1mC&\u0011ae\t\u0002\u0007\u0003:L(+\u001a4\u0002\r\u0011Jg.\u001b;%)\u0005I\u0003C\u0001\u0012+\u0013\tY3E\u0001\u0003V]&$\u0018\u0001\u00044s_6\u0014V-\u00193bE2,Wc\u0001\u0018\u0002\\Q\u0019q&!\u0018\u0015\u0007A\n)\u0006\u0005\u00022\u00075\t\u0001A\u0001\u0007Ge>l\'+Z1eC\ndWmE\u0003\u0004CQB4\b\u0005\u00026m5\tQ$\u0003\u00028;\t\t\u0002+\u0019:tKJLe\u000e];u\'>,(oY3\u0011\u0005\tJ\u0014B\u0001\u001e$\u0005\u001d\u0001&o\u001c3vGR\u0004\"\u0001\u0010#\u000f\u0005u\u0012eB\u0001 B\u001b\u0005y$B\u0001! \u0003\u0019a$o\\8u}%\tA%\u0003\u0002DG\u00059\u0001/Y2lC\u001e,\u0017BA#G\u00051\u0019VM]5bY&T\u0018M\u00197f\u0015\t\u00195%A\u0001t+\u0005I\u0005C\u0001&N\u001b\u0005Y%\"\u0001\'\u0002\t\u001d,g._\u0005\u0003\u001d.\u0013\u0001BU3bI\u0006\u0014G.Z\u0001\u0003g\u0002\n!BY;gM\u0016\u00148+\u001b>f+\u0005\u0011\u0006C\u0001\u0012T\u0013\t!6EA\u0002J]R\f1BY;gM\u0016\u00148+\u001b>fA\u00051A(\u001b8jiz\"2\u0001\r-Z\u0011\u00159\u0005\u00021\u0001J\u0011\u0015\u0001\u0006\u00021\u0001S\u00031\u0001\u0018M]:f)\"\u0014x.^4i+\tav\f\u0006\u0002^QB\u0011al\u0018\u0007\u0001\t\u0015\u0001\u0017B1\u0001b\u0005\u0005!\u0016C\u00012f!\t\u00113-\u0003\u0002eG\t9aj\u001c;iS:<\u0007C\u0001\u0012g\u0013\t97EA\u0002B]fDQ![\u0005A\u0002)\f\u0011A\u001a\t\u0005E-lW,\u0003\u0002mG\tIa)\u001e8di&|g.\r\t\u0003k9L!a\\\u000f\u0003\u0017A\u000b\'o]3s\u0013:\u0004X\u000f^\u0001\u0005G>\u0004\u0018\u0010F\u00021eNDqa\u0012\u0006\u0011\u0002\u0003\u0007\u0011\nC\u0004Q\u0015A\u0005\t\u0019\u0001*\u0002\u001d\r|\u0007/\u001f\u0013eK\u001a\fW\u000f\u001c;%cU\taO\u000b\u0002Jo.\n\u0001\u0010\u0005\u0002z}6\t!P\u0003\u0002|y\u0006IQO\\2iK\u000e\\W\r\u001a\u0006\u0003{\u000e\n!\"\u00198o_R\fG/[8o\u0013\ty(PA\tv]\u000eDWmY6fIZ\u000b\'/[1oG\u0016\fabY8qs\u0012\"WMZ1vYR$#\'\u0006\u0002\u0002\u0006)\u0012!k^\u0001\u000eaJ|G-^2u!J,g-\u001b=\u0016\u0005\u0005-\u0001\u0003BA\u0007\u0003/i!!a\u0004\u000b\t\u0005E\u00111C\u0001\u0005Y\u0006twM\u0003\u0002\u0002\u0016\u0005!!.\u0019<b\u0013\u0011\tI\"a\u0004\u0003\rM#(/\u001b8h\u00031\u0001(o\u001c3vGR\f%/\u001b;z\u00039\u0001(o\u001c3vGR,E.Z7f]R$2!ZA\u0011\u0011!\t\u0019cDA\u0001\u0002\u0004\u0011\u0016a\u0001=%c\u0005y\u0001O]8ek\u000e$\u0018\n^3sCR|\'/\u0006\u0002\u0002*A)\u00111FA\u0019K6\u0011\u0011Q\u0006\u0006\u0004\u0003_\u0019\u0013AC2pY2,7\r^5p]&!\u00111GA\u0017\u0005!IE/\u001a:bi>\u0014\u0018\u0001C2b]\u0016\u000bX/\u00197\u0015\t\u0005e\u0012q\b\t\u0004E\u0005m\u0012bAA\u001fG\t9!i\\8mK\u0006t\u0007\u0002CA\u0012#\u0005\u0005\t\u0019A3\u0002%A\u0014x\u000eZ;di\u0016cW-\\3oi:\u000bW.\u001a\u000b\u0005\u0003\u0017\t)\u0005\u0003\u0005\u0002$I\t\t\u00111\u0001S\u0003!A\u0017m\u001d5D_\u0012,G#\u0001*\u0002\u0011Q|7\u000b\u001e:j]\u001e$\"!a\u0003\u0002\r\u0015\fX/\u00197t)\u0011\tI$a\u0015\t\u0011\u0005\rR#!AA\u0002\u0015Da!\u001b\u0002A\u0004\u0005]\u0003#\u0002\u0012l\u00033J\u0005c\u00010\u0002\\\u0011)\u0001M\u0001b\u0001C\"1qI\u0001a\u0001\u00033\nAB\u0012:p[J+\u0017\rZ1cY\u0016\u0004\"!M\f\u0014\u000b]\t)\'!\u001d\u0011\u000f\u0005\u001d\u0014QN%Sa5\u0011\u0011\u0011\u000e\u0006\u0004\u0003W\u001a\u0013a\u0002:v]RLW.Z\u0005\u0005\u0003_\nIGA\tBEN$(/Y2u\rVt7\r^5p]J\u0002B!a\u001d\u0002z5\u0011\u0011Q\u000f\u0006\u0005\u0003o\n\u0019\"\u0001\u0002j_&\u0019Q)!\u001e\u0015\u0005\u0005\u0005\u0014!B1qa2LH#\u0002\u0019\u0002\u0002\u0006\r\u0005\"B$\u001b\u0001\u0004I\u0005\"\u0002)\u001b\u0001\u0004\u0011\u0016aB;oCB\u0004H.\u001f\u000b\u0005\u0003\u0013\u000b)\nE\u0003#\u0003\u0017\u000by)C\u0002\u0002\u000e\u000e\u0012aa\u00149uS>t\u0007#\u0002\u0012\u0002\u0012&\u0013\u0016bAAJG\t1A+\u001e9mKJB\u0001\"a&\u001c\u0003\u0003\u0005\r\u0001M\u0001\u0004q\u0012\u0002\u0004"
    )
  ScalaInlineInfo: length = 0x18 (unknown attribute)
   01 00 00 04 00 2A 00 2B 01 00 0B 00 0F 00 00 15
   00 16 00 00 10 00 11 01
  ScalaSig: length = 0x3 (unknown attribute)
   05 02 00
