Classfile /Users/mw/Projects/slang-braindump/.jar/jar11/assemble/slang-braindump/assemble/content/coursier/core/shaded/fastparse/ParserInputSourceLowPri$FromReadable.class
  Last modified May 29, 2022; size 5772 bytes
  SHA-256 checksum e69b1f1840e55c1ca6dec2767ca7565ef0479cb894b1bf44e57ca0746508889a
  Compiled from "ParserInput.scala"
public class coursier.core.shaded.fastparse.ParserInputSourceLowPri$FromReadable implements coursier.core.shaded.fastparse.ParserInputSource,scala.Product,java.io.Serializable
  minor version: 0
  major version: 52
  flags: (0x0021) ACC_PUBLIC, ACC_SUPER
  this_class: #2                          // coursier/core/shaded/fastparse/ParserInputSourceLowPri$FromReadable
  super_class: #4                         // java/lang/Object
  interfaces: 3, fields: 3, methods: 20, attributes: 5
Constant pool:
    #1 = Utf8               coursier/core/shaded/fastparse/ParserInputSourceLowPri$FromReadable
    #2 = Class              #1            // coursier/core/shaded/fastparse/ParserInputSourceLowPri$FromReadable
    #3 = Utf8               java/lang/Object
    #4 = Class              #3            // java/lang/Object
    #5 = Utf8               coursier/core/shaded/fastparse/ParserInputSource
    #6 = Class              #5            // coursier/core/shaded/fastparse/ParserInputSource
    #7 = Utf8               scala/Product
    #8 = Class              #7            // scala/Product
    #9 = Utf8               java/io/Serializable
   #10 = Class              #9            // java/io/Serializable
   #11 = Utf8               ParserInput.scala
   #12 = Utf8               coursier/core/shaded/fastparse/ParserInputSourceLowPri
   #13 = Class              #12           // coursier/core/shaded/fastparse/ParserInputSourceLowPri
   #14 = Utf8               FromReadable
   #15 = Utf8               java/lang/invoke/MethodHandles$Lookup
   #16 = Class              #15           // java/lang/invoke/MethodHandles$Lookup
   #17 = Utf8               java/lang/invoke/MethodHandles
   #18 = Class              #17           // java/lang/invoke/MethodHandles
   #19 = Utf8               Lookup
   #20 = Utf8               s
   #21 = Utf8               Lcoursier/core/shaded/geny/Readable;
   #22 = Utf8               bufferSize
   #23 = Utf8               I
   #24 = Utf8               $outer
   #25 = Utf8               Lcoursier/core/shaded/fastparse/ParserInputSourceLowPri;
   #26 = Utf8               productElementNames
   #27 = Utf8               ()Lscala/collection/Iterator;
   #28 = Utf8               ()Lscala/collection/Iterator<Ljava/lang/String;>;
   #29 = Utf8               productElementNames$
   #30 = Utf8               (Lscala/Product;)Lscala/collection/Iterator;
   #31 = NameAndType        #29:#30       // productElementNames$:(Lscala/Product;)Lscala/collection/Iterator;
   #32 = InterfaceMethodref #8.#31        // scala/Product.productElementNames$:(Lscala/Product;)Lscala/collection/Iterator;
   #33 = Utf8               this
   #34 = Utf8               Lcoursier/core/shaded/fastparse/ParserInputSourceLowPri$FromReadable;
   #35 = Utf8               ()Lcoursier/core/shaded/geny/Readable;
   #36 = NameAndType        #20:#21       // s:Lcoursier/core/shaded/geny/Readable;
   #37 = Fieldref           #2.#36        // coursier/core/shaded/fastparse/ParserInputSourceLowPri$FromReadable.s:Lcoursier/core/shaded/geny/Readable;
   #38 = Utf8               ()I
   #39 = NameAndType        #22:#23       // bufferSize:I
   #40 = Fieldref           #2.#39        // coursier/core/shaded/fastparse/ParserInputSourceLowPri$FromReadable.bufferSize:I
   #41 = Utf8               parseThrough
   #42 = Utf8               (Lscala/Function1;)Ljava/lang/Object;
   #43 = Utf8               <T:Ljava/lang/Object;>(Lscala/Function1<Lcoursier/core/shaded/fastparse/ParserInput;TT;>;)TT;
   #44 = Utf8               f
   #45 = NameAndType        #20:#35       // s:()Lcoursier/core/shaded/geny/Readable;
   #46 = Methodref          #2.#45        // coursier/core/shaded/fastparse/ParserInputSourceLowPri$FromReadable.s:()Lcoursier/core/shaded/geny/Readable;
   #47 = Utf8               (Ljava/lang/Object;)Ljava/lang/Object;
   #48 = MethodType         #47           //  (Ljava/lang/Object;)Ljava/lang/Object;
   #49 = Utf8               $anonfun$parseThrough$1
   #50 = Utf8               (Lcoursier/core/shaded/fastparse/ParserInputSourceLowPri$FromReadable;Lscala/Function1;Ljava/io/InputStream;)Ljava/lang/Object;
   #51 = NameAndType        #49:#50       // $anonfun$parseThrough$1:(Lcoursier/core/shaded/fastparse/ParserInputSourceLowPri$FromReadable;Lscala/Function1;Ljava/io/InputStream;)Ljava/lang/Object;
   #52 = Methodref          #2.#51        // coursier/core/shaded/fastparse/ParserInputSourceLowPri$FromReadable.$anonfun$parseThrough$1:(Lcoursier/core/shaded/fastparse/ParserInputSourceLowPri$FromReadable;Lscala/Function1;Ljava/io/InputStream;)Ljava/lang/Object;
   #53 = MethodHandle       6:#52         // REF_invokeStatic coursier/core/shaded/fastparse/ParserInputSourceLowPri$FromReadable.$anonfun$parseThrough$1:(Lcoursier/core/shaded/fastparse/ParserInputSourceLowPri$FromReadable;Lscala/Function1;Ljava/io/InputStream;)Ljava/lang/Object;
   #54 = Utf8               (Ljava/io/InputStream;)Ljava/lang/Object;
   #55 = MethodType         #54           //  (Ljava/io/InputStream;)Ljava/lang/Object;
   #56 = Integer            5
   #57 = Integer            1
   #58 = Utf8               java/lang/invoke/LambdaMetafactory
   #59 = Class              #58           // java/lang/invoke/LambdaMetafactory
   #60 = Utf8               altMetafactory
   #61 = Utf8               (Ljava/lang/invoke/MethodHandles$Lookup;Ljava/lang/String;Ljava/lang/invoke/MethodType;[Ljava/lang/Object;)Ljava/lang/invoke/CallSite;
   #62 = NameAndType        #60:#61       // altMetafactory:(Ljava/lang/invoke/MethodHandles$Lookup;Ljava/lang/String;Ljava/lang/invoke/MethodType;[Ljava/lang/Object;)Ljava/lang/invoke/CallSite;
   #63 = Methodref          #59.#62       // java/lang/invoke/LambdaMetafactory.altMetafactory:(Ljava/lang/invoke/MethodHandles$Lookup;Ljava/lang/String;Ljava/lang/invoke/MethodType;[Ljava/lang/Object;)Ljava/lang/invoke/CallSite;
   #64 = MethodHandle       6:#63         // REF_invokeStatic java/lang/invoke/LambdaMetafactory.altMetafactory:(Ljava/lang/invoke/MethodHandles$Lookup;Ljava/lang/String;Ljava/lang/invoke/MethodType;[Ljava/lang/Object;)Ljava/lang/invoke/CallSite;
   #65 = Utf8               apply
   #66 = Utf8               (Lcoursier/core/shaded/fastparse/ParserInputSourceLowPri$FromReadable;Lscala/Function1;)Lscala/Function1;
   #67 = NameAndType        #65:#66       // apply:(Lcoursier/core/shaded/fastparse/ParserInputSourceLowPri$FromReadable;Lscala/Function1;)Lscala/Function1;
   #68 = InvokeDynamic      #0:#67        // #0:apply:(Lcoursier/core/shaded/fastparse/ParserInputSourceLowPri$FromReadable;Lscala/Function1;)Lscala/Function1;
   #69 = Utf8               coursier/core/shaded/geny/Readable
   #70 = Class              #69           // coursier/core/shaded/geny/Readable
   #71 = Utf8               readBytesThrough
   #72 = NameAndType        #71:#42       // readBytesThrough:(Lscala/Function1;)Ljava/lang/Object;
   #73 = InterfaceMethodref #70.#72       // coursier/core/shaded/geny/Readable.readBytesThrough:(Lscala/Function1;)Ljava/lang/Object;
   #74 = Utf8               Lscala/Function1;
   #75 = Utf8               copy
   #76 = Utf8               (Lcoursier/core/shaded/geny/Readable;I)Lcoursier/core/shaded/fastparse/ParserInputSourceLowPri$FromReadable;
   #77 = Utf8               fastparse$ParserInputSourceLowPri$FromReadable$$$outer
   #78 = Utf8               ()Lcoursier/core/shaded/fastparse/ParserInputSourceLowPri;
   #79 = NameAndType        #77:#78       // fastparse$ParserInputSourceLowPri$FromReadable$$$outer:()Lcoursier/core/shaded/fastparse/ParserInputSourceLowPri;
   #80 = Methodref          #2.#79        // coursier/core/shaded/fastparse/ParserInputSourceLowPri$FromReadable.fastparse$ParserInputSourceLowPri$FromReadable$$$outer:()Lcoursier/core/shaded/fastparse/ParserInputSourceLowPri;
   #81 = Utf8               <init>
   #82 = Utf8               (Lcoursier/core/shaded/fastparse/ParserInputSourceLowPri;Lcoursier/core/shaded/geny/Readable;I)V
   #83 = NameAndType        #81:#82       // "<init>":(Lcoursier/core/shaded/fastparse/ParserInputSourceLowPri;Lcoursier/core/shaded/geny/Readable;I)V
   #84 = Methodref          #2.#83        // coursier/core/shaded/fastparse/ParserInputSourceLowPri$FromReadable."<init>":(Lcoursier/core/shaded/fastparse/ParserInputSourceLowPri;Lcoursier/core/shaded/geny/Readable;I)V
   #85 = Utf8               copy$default$1
   #86 = Utf8               copy$default$2
   #87 = NameAndType        #22:#38       // bufferSize:()I
   #88 = Methodref          #2.#87        // coursier/core/shaded/fastparse/ParserInputSourceLowPri$FromReadable.bufferSize:()I
   #89 = Utf8               productPrefix
   #90 = Utf8               ()Ljava/lang/String;
   #91 = String             #14           // FromReadable
   #92 = Utf8               productArity
   #93 = Utf8               productElement
   #94 = Utf8               (I)Ljava/lang/Object;
   #95 = Utf8               x$1
   #96 = Utf8               scala/runtime/BoxesRunTime
   #97 = Class              #96           // scala/runtime/BoxesRunTime
   #98 = Utf8               boxToInteger
   #99 = Utf8               (I)Ljava/lang/Integer;
  #100 = NameAndType        #98:#99       // boxToInteger:(I)Ljava/lang/Integer;
  #101 = Methodref          #97.#100      // scala/runtime/BoxesRunTime.boxToInteger:(I)Ljava/lang/Integer;
  #102 = Utf8               scala/runtime/Statics
  #103 = Class              #102          // scala/runtime/Statics
  #104 = Utf8               ioobe
  #105 = NameAndType        #104:#94      // ioobe:(I)Ljava/lang/Object;
  #106 = Methodref          #103.#105     // scala/runtime/Statics.ioobe:(I)Ljava/lang/Object;
  #107 = Utf8               productIterator
  #108 = Utf8               ()Lscala/collection/Iterator<Ljava/lang/Object;>;
  #109 = Utf8               scala/runtime/ScalaRunTime$
  #110 = Class              #109          // scala/runtime/ScalaRunTime$
  #111 = Utf8               MODULE$
  #112 = Utf8               Lscala/runtime/ScalaRunTime$;
  #113 = NameAndType        #111:#112     // MODULE$:Lscala/runtime/ScalaRunTime$;
  #114 = Fieldref           #110.#113     // scala/runtime/ScalaRunTime$.MODULE$:Lscala/runtime/ScalaRunTime$;
  #115 = Utf8               typedProductIterator
  #116 = NameAndType        #115:#30      // typedProductIterator:(Lscala/Product;)Lscala/collection/Iterator;
  #117 = Methodref          #110.#116     // scala/runtime/ScalaRunTime$.typedProductIterator:(Lscala/Product;)Lscala/collection/Iterator;
  #118 = Utf8               canEqual
  #119 = Utf8               (Ljava/lang/Object;)Z
  #120 = Utf8               Ljava/lang/Object;
  #121 = Utf8               productElementName
  #122 = Utf8               (I)Ljava/lang/String;
  #123 = String             #20           // s
  #124 = String             #22           // bufferSize
  #125 = Utf8               java/lang/String
  #126 = Class              #125          // java/lang/String
  #127 = Utf8               hashCode
  #128 = Integer            -889275714
  #129 = NameAndType        #89:#90       // productPrefix:()Ljava/lang/String;
  #130 = Methodref          #2.#129       // coursier/core/shaded/fastparse/ParserInputSourceLowPri$FromReadable.productPrefix:()Ljava/lang/String;
  #131 = NameAndType        #127:#38      // hashCode:()I
  #132 = Methodref          #126.#131     // java/lang/String.hashCode:()I
  #133 = Utf8               mix
  #134 = Utf8               (II)I
  #135 = NameAndType        #133:#134     // mix:(II)I
  #136 = Methodref          #103.#135     // scala/runtime/Statics.mix:(II)I
  #137 = Utf8               anyHash
  #138 = Utf8               (Ljava/lang/Object;)I
  #139 = NameAndType        #137:#138     // anyHash:(Ljava/lang/Object;)I
  #140 = Methodref          #103.#139     // scala/runtime/Statics.anyHash:(Ljava/lang/Object;)I
  #141 = Utf8               finalizeHash
  #142 = NameAndType        #141:#134     // finalizeHash:(II)I
  #143 = Methodref          #103.#142     // scala/runtime/Statics.finalizeHash:(II)I
  #144 = Utf8               toString
  #145 = Utf8               _toString
  #146 = Utf8               (Lscala/Product;)Ljava/lang/String;
  #147 = NameAndType        #145:#146     // _toString:(Lscala/Product;)Ljava/lang/String;
  #148 = Methodref          #110.#147     // scala/runtime/ScalaRunTime$._toString:(Lscala/Product;)Ljava/lang/String;
  #149 = Utf8               equals
  #150 = NameAndType        #149:#119     // equals:(Ljava/lang/Object;)Z
  #151 = Methodref          #4.#150       // java/lang/Object.equals:(Ljava/lang/Object;)Z
  #152 = NameAndType        #118:#119     // canEqual:(Ljava/lang/Object;)Z
  #153 = Methodref          #2.#152       // coursier/core/shaded/fastparse/ParserInputSourceLowPri$FromReadable.canEqual:(Ljava/lang/Object;)Z
  #154 = NameAndType        #24:#25       // $outer:Lcoursier/core/shaded/fastparse/ParserInputSourceLowPri;
  #155 = Fieldref           #2.#154       // coursier/core/shaded/fastparse/ParserInputSourceLowPri$FromReadable.$outer:Lcoursier/core/shaded/fastparse/ParserInputSourceLowPri;
  #156 = Utf8               $this
  #157 = Utf8               f$1
  #158 = Utf8               is
  #159 = Utf8               coursier/core/shaded/fastparse/ReaderParserInput
  #160 = Class              #159          // coursier/core/shaded/fastparse/ReaderParserInput
  #161 = Utf8               java/io/InputStreamReader
  #162 = Class              #161          // java/io/InputStreamReader
  #163 = Utf8               (Ljava/io/InputStream;)V
  #164 = NameAndType        #81:#163      // "<init>":(Ljava/io/InputStream;)V
  #165 = Methodref          #162.#164     // java/io/InputStreamReader."<init>":(Ljava/io/InputStream;)V
  #166 = Utf8               (Ljava/io/Reader;I)V
  #167 = NameAndType        #81:#166      // "<init>":(Ljava/io/Reader;I)V
  #168 = Methodref          #160.#167     // coursier/core/shaded/fastparse/ReaderParserInput."<init>":(Ljava/io/Reader;I)V
  #169 = Utf8               scala/Function1
  #170 = Class              #169          // scala/Function1
  #171 = NameAndType        #65:#47       // apply:(Ljava/lang/Object;)Ljava/lang/Object;
  #172 = InterfaceMethodref #170.#171     // scala/Function1.apply:(Ljava/lang/Object;)Ljava/lang/Object;
  #173 = Utf8               Ljava/io/InputStream;
  #174 = Utf8               ()V
  #175 = NameAndType        #81:#174      // "<init>":()V
  #176 = Methodref          #4.#175       // java/lang/Object."<init>":()V
  #177 = Utf8               $init$
  #178 = Utf8               (Lscala/Product;)V
  #179 = NameAndType        #177:#178     // $init$:(Lscala/Product;)V
  #180 = InterfaceMethodref #8.#179       // scala/Product.$init$:(Lscala/Product;)V
  #181 = Utf8               $deserializeLambda$
  #182 = Utf8               (Ljava/lang/invoke/SerializedLambda;)Ljava/lang/Object;
  #183 = Utf8               scala/runtime/LambdaDeserialize
  #184 = Class              #183          // scala/runtime/LambdaDeserialize
  #185 = Utf8               bootstrap
  #186 = Utf8               (Ljava/lang/invoke/MethodHandles$Lookup;Ljava/lang/String;Ljava/lang/invoke/MethodType;[Ljava/lang/invoke/MethodHandle;)Ljava/lang/invoke/CallSite;
  #187 = NameAndType        #185:#186     // bootstrap:(Ljava/lang/invoke/MethodHandles$Lookup;Ljava/lang/String;Ljava/lang/invoke/MethodType;[Ljava/lang/invoke/MethodHandle;)Ljava/lang/invoke/CallSite;
  #188 = Methodref          #184.#187     // scala/runtime/LambdaDeserialize.bootstrap:(Ljava/lang/invoke/MethodHandles$Lookup;Ljava/lang/String;Ljava/lang/invoke/MethodType;[Ljava/lang/invoke/MethodHandle;)Ljava/lang/invoke/CallSite;
  #189 = MethodHandle       6:#188        // REF_invokeStatic scala/runtime/LambdaDeserialize.bootstrap:(Ljava/lang/invoke/MethodHandles$Lookup;Ljava/lang/String;Ljava/lang/invoke/MethodType;[Ljava/lang/invoke/MethodHandle;)Ljava/lang/invoke/CallSite;
  #190 = Utf8               lambdaDeserialize
  #191 = NameAndType        #190:#182     // lambdaDeserialize:(Ljava/lang/invoke/SerializedLambda;)Ljava/lang/Object;
  #192 = InvokeDynamic      #1:#191       // #1:lambdaDeserialize:(Ljava/lang/invoke/SerializedLambda;)Ljava/lang/Object;
  #193 = Utf8               Code
  #194 = Utf8               LineNumberTable
  #195 = Utf8               LocalVariableTable
  #196 = Utf8               Signature
  #197 = Utf8               MethodParameters
  #198 = Utf8               StackMapTable
  #199 = Utf8               InnerClasses
  #200 = Utf8               SourceFile
  #201 = Utf8               BootstrapMethods
  #202 = Utf8               ScalaInlineInfo
  #203 = Utf8               Scala
{
  private final coursier.core.shaded.geny.Readable s;
    descriptor: Lcoursier/core/shaded/geny/Readable;
    flags: (0x0012) ACC_PRIVATE, ACC_FINAL

  private final int bufferSize;
    descriptor: I
    flags: (0x0012) ACC_PRIVATE, ACC_FINAL

  public final coursier.core.shaded.fastparse.ParserInputSourceLowPri $outer;
    descriptor: Lcoursier/core/shaded/fastparse/ParserInputSourceLowPri;
    flags: (0x1011) ACC_PUBLIC, ACC_FINAL, ACC_SYNTHETIC

  public scala.collection.Iterator<java.lang.String> productElementNames();
    descriptor: ()Lscala/collection/Iterator;
    flags: (0x0001) ACC_PUBLIC
    Code:
      stack=1, locals=1, args_size=1
         0: aload_0
         1: invokestatic  #32                 // InterfaceMethod scala/Product.productElementNames$:(Lscala/Product;)Lscala/collection/Iterator;
         4: areturn
      LineNumberTable:
        line 48: 0
      LocalVariableTable:
        Start  Length  Slot  Name   Signature
            0       5     0  this   Lcoursier/core/shaded/fastparse/ParserInputSourceLowPri$FromReadable;
    Signature: #28                          // ()Lscala/collection/Iterator<Ljava/lang/String;>;

  public coursier.core.shaded.geny.Readable s();
    descriptor: ()Lcoursier/core/shaded/geny/Readable;
    flags: (0x0001) ACC_PUBLIC
    Code:
      stack=1, locals=1, args_size=1
         0: aload_0
         1: getfield      #37                 // Field s:Lcoursier/core/shaded/geny/Readable;
         4: areturn
      LineNumberTable:
        line 48: 0
      LocalVariableTable:
        Start  Length  Slot  Name   Signature
            0       5     0  this   Lcoursier/core/shaded/fastparse/ParserInputSourceLowPri$FromReadable;

  public int bufferSize();
    descriptor: ()I
    flags: (0x0001) ACC_PUBLIC
    Code:
      stack=1, locals=1, args_size=1
         0: aload_0
         1: getfield      #40                 // Field bufferSize:I
         4: ireturn
      LineNumberTable:
        line 48: 0
      LocalVariableTable:
        Start  Length  Slot  Name   Signature
            0       5     0  this   Lcoursier/core/shaded/fastparse/ParserInputSourceLowPri$FromReadable;

  public <T extends java.lang.Object> T parseThrough(scala.Function1<coursier.core.shaded.fastparse.ParserInput, T>);
    descriptor: (Lscala/Function1;)Ljava/lang/Object;
    flags: (0x0001) ACC_PUBLIC
    Code:
      stack=3, locals=2, args_size=2
         0: aload_0
         1: invokevirtual #46                 // Method s:()Lcoursier/core/shaded/geny/Readable;
         4: aload_0
         5: aload_1
         6: invokedynamic #68,  0             // InvokeDynamic #0:apply:(Lcoursier/core/shaded/fastparse/ParserInputSourceLowPri$FromReadable;Lscala/Function1;)Lscala/Function1;
        11: invokeinterface #73,  2           // InterfaceMethod coursier/core/shaded/geny/Readable.readBytesThrough:(Lscala/Function1;)Ljava/lang/Object;
        16: areturn
      LineNumberTable:
        line 50: 0
      LocalVariableTable:
        Start  Length  Slot  Name   Signature
            0      17     0  this   Lcoursier/core/shaded/fastparse/ParserInputSourceLowPri$FromReadable;
            0      17     1     f   Lscala/Function1;
    Signature: #43                          // <T:Ljava/lang/Object;>(Lscala/Function1<Lcoursier/core/shaded/fastparse/ParserInput;TT;>;)TT;
    MethodParameters:
      Name                           Flags
      f                              final

  public coursier.core.shaded.fastparse.ParserInputSourceLowPri$FromReadable copy(coursier.core.shaded.geny.Readable, int);
    descriptor: (Lcoursier/core/shaded/geny/Readable;I)Lcoursier/core/shaded/fastparse/ParserInputSourceLowPri$FromReadable;
    flags: (0x0001) ACC_PUBLIC
    Code:
      stack=5, locals=3, args_size=3
         0: new           #2                  // class coursier/core/shaded/fastparse/ParserInputSourceLowPri$FromReadable
         3: dup
         4: aload_0
         5: invokevirtual #80                 // Method fastparse$ParserInputSourceLowPri$FromReadable$$$outer:()Lcoursier/core/shaded/fastparse/ParserInputSourceLowPri;
         8: aload_1
         9: iload_2
        10: invokespecial #84                 // Method "<init>":(Lcoursier/core/shaded/fastparse/ParserInputSourceLowPri;Lcoursier/core/shaded/geny/Readable;I)V
        13: areturn
      LineNumberTable:
        line 48: 0
      LocalVariableTable:
        Start  Length  Slot  Name   Signature
            0      14     0  this   Lcoursier/core/shaded/fastparse/ParserInputSourceLowPri$FromReadable;
            0      14     1     s   Lcoursier/core/shaded/geny/Readable;
            0      14     2 bufferSize   I
    MethodParameters:
      Name                           Flags
      s                              final
      bufferSize                     final

  public coursier.core.shaded.geny.Readable copy$default$1();
    descriptor: ()Lcoursier/core/shaded/geny/Readable;
    flags: (0x0001) ACC_PUBLIC
    Code:
      stack=1, locals=1, args_size=1
         0: aload_0
         1: invokevirtual #46                 // Method s:()Lcoursier/core/shaded/geny/Readable;
         4: areturn
      LineNumberTable:
        line 48: 0
      LocalVariableTable:
        Start  Length  Slot  Name   Signature
            0       5     0  this   Lcoursier/core/shaded/fastparse/ParserInputSourceLowPri$FromReadable;

  public int copy$default$2();
    descriptor: ()I
    flags: (0x0001) ACC_PUBLIC
    Code:
      stack=1, locals=1, args_size=1
         0: aload_0
         1: invokevirtual #88                 // Method bufferSize:()I
         4: ireturn
      LineNumberTable:
        line 48: 0
      LocalVariableTable:
        Start  Length  Slot  Name   Signature
            0       5     0  this   Lcoursier/core/shaded/fastparse/ParserInputSourceLowPri$FromReadable;

  public java.lang.String productPrefix();
    descriptor: ()Ljava/lang/String;
    flags: (0x0001) ACC_PUBLIC
    Code:
      stack=1, locals=1, args_size=1
         0: ldc           #91                 // String FromReadable
         2: areturn
      LineNumberTable:
        line 48: 0
      LocalVariableTable:
        Start  Length  Slot  Name   Signature
            0       3     0  this   Lcoursier/core/shaded/fastparse/ParserInputSourceLowPri$FromReadable;

  public int productArity();
    descriptor: ()I
    flags: (0x0001) ACC_PUBLIC
    Code:
      stack=1, locals=1, args_size=1
         0: iconst_2
         1: ireturn
      LineNumberTable:
        line 48: 0
      LocalVariableTable:
        Start  Length  Slot  Name   Signature
            0       2     0  this   Lcoursier/core/shaded/fastparse/ParserInputSourceLowPri$FromReadable;

  public java.lang.Object productElement(int);
    descriptor: (I)Ljava/lang/Object;
    flags: (0x0001) ACC_PUBLIC
    Code:
      stack=1, locals=3, args_size=2
         0: iload_1
         1: istore_2
         2: iload_2
         3: tableswitch   { // 0 to 1
                       0: 24
                       1: 31
                 default: 41
            }
        24: aload_0
        25: invokevirtual #46                 // Method s:()Lcoursier/core/shaded/geny/Readable;
        28: goto          48
        31: aload_0
        32: invokevirtual #88                 // Method bufferSize:()I
        35: invokestatic  #101                // Method scala/runtime/BoxesRunTime.boxToInteger:(I)Ljava/lang/Integer;
        38: goto          48
        41: iload_1
        42: invokestatic  #106                // Method scala/runtime/Statics.ioobe:(I)Ljava/lang/Object;
        45: goto          48
        48: areturn
      StackMapTable: number_of_entries = 4
        frame_type = 252 /* append */
          offset_delta = 24
          locals = [ int ]
        frame_type = 6 /* same */
        frame_type = 9 /* same */
        frame_type = 70 /* same_locals_1_stack_item */
          stack = [ class java/lang/Object ]
      LineNumberTable:
        line 48: 0
      LocalVariableTable:
        Start  Length  Slot  Name   Signature
            0      49     0  this   Lcoursier/core/shaded/fastparse/ParserInputSourceLowPri$FromReadable;
            0      49     1   x$1   I
    MethodParameters:
      Name                           Flags
      x$1                            final

  public scala.collection.Iterator<java.lang.Object> productIterator();
    descriptor: ()Lscala/collection/Iterator;
    flags: (0x0001) ACC_PUBLIC
    Code:
      stack=2, locals=1, args_size=1
         0: getstatic     #114                // Field scala/runtime/ScalaRunTime$.MODULE$:Lscala/runtime/ScalaRunTime$;
         3: aload_0
         4: invokevirtual #117                // Method scala/runtime/ScalaRunTime$.typedProductIterator:(Lscala/Product;)Lscala/collection/Iterator;
         7: areturn
      LineNumberTable:
        line 48: 0
      LocalVariableTable:
        Start  Length  Slot  Name   Signature
            0       8     0  this   Lcoursier/core/shaded/fastparse/ParserInputSourceLowPri$FromReadable;
    Signature: #108                         // ()Lscala/collection/Iterator<Ljava/lang/Object;>;

  public boolean canEqual(java.lang.Object);
    descriptor: (Ljava/lang/Object;)Z
    flags: (0x0001) ACC_PUBLIC
    Code:
      stack=1, locals=2, args_size=2
         0: aload_1
         1: instanceof    #2                  // class coursier/core/shaded/fastparse/ParserInputSourceLowPri$FromReadable
         4: ireturn
      LineNumberTable:
        line 48: 0
      LocalVariableTable:
        Start  Length  Slot  Name   Signature
            0       5     0  this   Lcoursier/core/shaded/fastparse/ParserInputSourceLowPri$FromReadable;
            0       5     1   x$1   Ljava/lang/Object;
    MethodParameters:
      Name                           Flags
      x$1                            final

  public java.lang.String productElementName(int);
    descriptor: (I)Ljava/lang/String;
    flags: (0x0001) ACC_PUBLIC
    Code:
      stack=1, locals=3, args_size=2
         0: iload_1
         1: istore_2
         2: iload_2
         3: tableswitch   { // 0 to 1
                       0: 24
                       1: 29
                 default: 34
            }
        24: ldc           #123                // String s
        26: goto          44
        29: ldc           #124                // String bufferSize
        31: goto          44
        34: iload_1
        35: invokestatic  #106                // Method scala/runtime/Statics.ioobe:(I)Ljava/lang/Object;
        38: checkcast     #126                // class java/lang/String
        41: goto          44
        44: areturn
      StackMapTable: number_of_entries = 4
        frame_type = 252 /* append */
          offset_delta = 24
          locals = [ int ]
        frame_type = 4 /* same */
        frame_type = 4 /* same */
        frame_type = 73 /* same_locals_1_stack_item */
          stack = [ class java/lang/String ]
      LineNumberTable:
        line 48: 0
      LocalVariableTable:
        Start  Length  Slot  Name   Signature
            0      45     0  this   Lcoursier/core/shaded/fastparse/ParserInputSourceLowPri$FromReadable;
            0      45     1   x$1   I
    MethodParameters:
      Name                           Flags
      x$1                            final

  public int hashCode();
    descriptor: ()I
    flags: (0x0001) ACC_PUBLIC
    Code:
      stack=2, locals=2, args_size=1
         0: ldc           #128                // int -889275714
         2: istore_1
         3: iload_1
         4: aload_0
         5: invokevirtual #130                // Method productPrefix:()Ljava/lang/String;
         8: invokevirtual #132                // Method java/lang/String.hashCode:()I
        11: invokestatic  #136                // Method scala/runtime/Statics.mix:(II)I
        14: istore_1
        15: iload_1
        16: aload_0
        17: invokevirtual #46                 // Method s:()Lcoursier/core/shaded/geny/Readable;
        20: invokestatic  #140                // Method scala/runtime/Statics.anyHash:(Ljava/lang/Object;)I
        23: invokestatic  #136                // Method scala/runtime/Statics.mix:(II)I
        26: istore_1
        27: iload_1
        28: aload_0
        29: invokevirtual #88                 // Method bufferSize:()I
        32: invokestatic  #136                // Method scala/runtime/Statics.mix:(II)I
        35: istore_1
        36: iload_1
        37: iconst_2
        38: invokestatic  #143                // Method scala/runtime/Statics.finalizeHash:(II)I
        41: ireturn
      LineNumberTable:
        line 48: 0
      LocalVariableTable:
        Start  Length  Slot  Name   Signature
            0      42     0  this   Lcoursier/core/shaded/fastparse/ParserInputSourceLowPri$FromReadable;

  public java.lang.String toString();
    descriptor: ()Ljava/lang/String;
    flags: (0x0001) ACC_PUBLIC
    Code:
      stack=2, locals=1, args_size=1
         0: getstatic     #114                // Field scala/runtime/ScalaRunTime$.MODULE$:Lscala/runtime/ScalaRunTime$;
         3: aload_0
         4: invokevirtual #148                // Method scala/runtime/ScalaRunTime$._toString:(Lscala/Product;)Ljava/lang/String;
         7: areturn
      LineNumberTable:
        line 48: 0
      LocalVariableTable:
        Start  Length  Slot  Name   Signature
            0       8     0  this   Lcoursier/core/shaded/fastparse/ParserInputSourceLowPri$FromReadable;

  public boolean equals(java.lang.Object);
    descriptor: (Ljava/lang/Object;)Z
    flags: (0x0001) ACC_PUBLIC
    Code:
      stack=2, locals=6, args_size=2
         0: aload_0
         1: aload_1
         2: if_acmpeq     112
         5: aload_1
         6: astore_3
         7: aload_3
         8: instanceof    #2                  // class coursier/core/shaded/fastparse/ParserInputSourceLowPri$FromReadable
        11: ifeq          33
        14: aload_3
        15: checkcast     #2                  // class coursier/core/shaded/fastparse/ParserInputSourceLowPri$FromReadable
        18: invokevirtual #80                 // Method fastparse$ParserInputSourceLowPri$FromReadable$$$outer:()Lcoursier/core/shaded/fastparse/ParserInputSourceLowPri;
        21: aload_0
        22: invokevirtual #80                 // Method fastparse$ParserInputSourceLowPri$FromReadable$$$outer:()Lcoursier/core/shaded/fastparse/ParserInputSourceLowPri;
        25: if_acmpne     33
        28: iconst_1
        29: istore_2
        30: goto          41
        33: goto          36
        36: iconst_0
        37: istore_2
        38: goto          41
        41: iload_2
        42: ifeq          116
        45: aload_1
        46: checkcast     #2                  // class coursier/core/shaded/fastparse/ParserInputSourceLowPri$FromReadable
        49: astore        4
        51: aload_0
        52: invokevirtual #88                 // Method bufferSize:()I
        55: aload         4
        57: invokevirtual #88                 // Method bufferSize:()I
        60: if_icmpne     108
        63: aload_0
        64: invokevirtual #46                 // Method s:()Lcoursier/core/shaded/geny/Readable;
        67: aload         4
        69: invokevirtual #46                 // Method s:()Lcoursier/core/shaded/geny/Readable;
        72: astore        5
        74: dup
        75: ifnonnull     87
        78: pop
        79: aload         5
        81: ifnull        95
        84: goto          108
        87: aload         5
        89: invokevirtual #151                // Method java/lang/Object.equals:(Ljava/lang/Object;)Z
        92: ifeq          108
        95: aload         4
        97: aload_0
        98: invokevirtual #153                // Method canEqual:(Ljava/lang/Object;)Z
       101: ifeq          108
       104: iconst_1
       105: goto          109
       108: iconst_0
       109: ifeq          116
       112: iconst_1
       113: goto          117
       116: iconst_0
       117: ireturn
      StackMapTable: number_of_entries = 10
        frame_type = 253 /* append */
          offset_delta = 33
          locals = [ top, class java/lang/Object ]
        frame_type = 2 /* same */
        frame_type = 255 /* full_frame */
          offset_delta = 4
          locals = [ class coursier/core/shaded/fastparse/ParserInputSourceLowPri$FromReadable, class java/lang/Object, int, class java/lang/Object ]
          stack = []
        frame_type = 255 /* full_frame */
          offset_delta = 45
          locals = [ class coursier/core/shaded/fastparse/ParserInputSourceLowPri$FromReadable, class java/lang/Object, int, class java/lang/Object, class coursier/core/shaded/fastparse/ParserInputSourceLowPri$FromReadable, class coursier/core/shaded/geny/Readable ]
          stack = [ class coursier/core/shaded/geny/Readable ]
        frame_type = 7 /* same */
        frame_type = 250 /* chop */
          offset_delta = 12
        frame_type = 64 /* same_locals_1_stack_item */
          stack = [ int ]
        frame_type = 248 /* chop */
          offset_delta = 2
        frame_type = 253 /* append */
          offset_delta = 3
          locals = [ int, class java/lang/Object ]
        frame_type = 255 /* full_frame */
          offset_delta = 0
          locals = [ class coursier/core/shaded/fastparse/ParserInputSourceLowPri$FromReadable, class java/lang/Object ]
          stack = [ int ]
      LineNumberTable:
        line 48: 0
      LocalVariableTable:
        Start  Length  Slot  Name   Signature
            0     118     0  this   Lcoursier/core/shaded/fastparse/ParserInputSourceLowPri$FromReadable;
            0     118     1   x$1   Ljava/lang/Object;
    MethodParameters:
      Name                           Flags
      x$1                            final

  public coursier.core.shaded.fastparse.ParserInputSourceLowPri fastparse$ParserInputSourceLowPri$FromReadable$$$outer();
    descriptor: ()Lcoursier/core/shaded/fastparse/ParserInputSourceLowPri;
    flags: (0x1001) ACC_PUBLIC, ACC_SYNTHETIC
    Code:
      stack=1, locals=1, args_size=1
         0: aload_0
         1: getfield      #155                // Field $outer:Lcoursier/core/shaded/fastparse/ParserInputSourceLowPri;
         4: areturn
      LineNumberTable:
        line 48: 0
      LocalVariableTable:
        Start  Length  Slot  Name   Signature
            0       5     0  this   Lcoursier/core/shaded/fastparse/ParserInputSourceLowPri$FromReadable;

  public static final java.lang.Object $anonfun$parseThrough$1(coursier.core.shaded.fastparse.ParserInputSourceLowPri$FromReadable, scala.Function1, java.io.InputStream);
    descriptor: (Lcoursier/core/shaded/fastparse/ParserInputSourceLowPri$FromReadable;Lscala/Function1;Ljava/io/InputStream;)Ljava/lang/Object;
    flags: (0x1019) ACC_PUBLIC, ACC_STATIC, ACC_FINAL, ACC_SYNTHETIC
    Code:
      stack=6, locals=3, args_size=3
         0: aload_1
         1: new           #160                // class coursier/core/shaded/fastparse/ReaderParserInput
         4: dup
         5: new           #162                // class java/io/InputStreamReader
         8: dup
         9: aload_2
        10: invokespecial #165                // Method java/io/InputStreamReader."<init>":(Ljava/io/InputStream;)V
        13: aload_0
        14: invokevirtual #88                 // Method bufferSize:()I
        17: invokespecial #168                // Method coursier/core/shaded/fastparse/ReaderParserInput."<init>":(Ljava/io/Reader;I)V
        20: invokeinterface #172,  2          // InterfaceMethod scala/Function1.apply:(Ljava/lang/Object;)Ljava/lang/Object;
        25: areturn
      LineNumberTable:
        line 50: 0
      LocalVariableTable:
        Start  Length  Slot  Name   Signature
            0      26     0 $this   Lcoursier/core/shaded/fastparse/ParserInputSourceLowPri$FromReadable;
            0      26     1   f$1   Lscala/Function1;
            0      26     2    is   Ljava/io/InputStream;
    MethodParameters:
      Name                           Flags
      $this                          final synthetic
      f$1                            final
      is                             final

  public coursier.core.shaded.fastparse.ParserInputSourceLowPri$FromReadable(coursier.core.shaded.fastparse.ParserInputSourceLowPri, coursier.core.shaded.geny.Readable, int);
    descriptor: (Lcoursier/core/shaded/fastparse/ParserInputSourceLowPri;Lcoursier/core/shaded/geny/Readable;I)V
    flags: (0x0001) ACC_PUBLIC
    Code:
      stack=2, locals=4, args_size=4
         0: aload_0
         1: aload_2
         2: putfield      #37                 // Field s:Lcoursier/core/shaded/geny/Readable;
         5: aload_0
         6: iload_3
         7: putfield      #40                 // Field bufferSize:I
        10: aload_1
        11: ifnonnull     16
        14: aconst_null
        15: athrow
        16: aload_0
        17: aload_1
        18: putfield      #155                // Field $outer:Lcoursier/core/shaded/fastparse/ParserInputSourceLowPri;
        21: aload_0
        22: invokespecial #176                // Method java/lang/Object."<init>":()V
        25: aload_0
        26: invokestatic  #180                // InterfaceMethod scala/Product.$init$:(Lscala/Product;)V
        29: return
      StackMapTable: number_of_entries = 1
        frame_type = 16 /* same */
      LineNumberTable:
        line 48: 0
      LocalVariableTable:
        Start  Length  Slot  Name   Signature
            0      30     0  this   Lcoursier/core/shaded/fastparse/ParserInputSourceLowPri$FromReadable;
            0      30     1 $outer   Lcoursier/core/shaded/fastparse/ParserInputSourceLowPri;
            0      30     2     s   Lcoursier/core/shaded/geny/Readable;
            0      30     3 bufferSize   I
    MethodParameters:
      Name                           Flags
      $outer                         final synthetic
      s                              final
      bufferSize                     final

  private static java.lang.Object $deserializeLambda$(java.lang.invoke.SerializedLambda);
    descriptor: (Ljava/lang/invoke/SerializedLambda;)Ljava/lang/Object;
    flags: (0x100a) ACC_PRIVATE, ACC_STATIC, ACC_SYNTHETIC
    Code:
      stack=1, locals=1, args_size=1
         0: aload_0
         1: invokedynamic #192,  0            // InvokeDynamic #1:lambdaDeserialize:(Ljava/lang/invoke/SerializedLambda;)Ljava/lang/Object;
         6: areturn
}
InnerClasses:
  public #14= #2 of #13;                  // FromReadable=class coursier/core/shaded/fastparse/ParserInputSourceLowPri$FromReadable of class coursier/core/shaded/fastparse/ParserInputSourceLowPri
  public static final #19= #16 of #18;    // Lookup=class java/lang/invoke/MethodHandles$Lookup of class java/lang/invoke/MethodHandles
SourceFile: "ParserInput.scala"
BootstrapMethods:
  0: #64 REF_invokeStatic java/lang/invoke/LambdaMetafactory.altMetafactory:(Ljava/lang/invoke/MethodHandles$Lookup;Ljava/lang/String;Ljava/lang/invoke/MethodType;[Ljava/lang/Object;)Ljava/lang/invoke/CallSite;
    Method arguments:
      #48 (Ljava/lang/Object;)Ljava/lang/Object;
      #53 REF_invokeStatic coursier/core/shaded/fastparse/ParserInputSourceLowPri$FromReadable.$anonfun$parseThrough$1:(Lcoursier/core/shaded/fastparse/ParserInputSourceLowPri$FromReadable;Lscala/Function1;Ljava/io/InputStream;)Ljava/lang/Object;
      #55 (Ljava/io/InputStream;)Ljava/lang/Object;
      #56 5
      #57 1
      #55 (Ljava/io/InputStream;)Ljava/lang/Object;
  1: #189 REF_invokeStatic scala/runtime/LambdaDeserialize.bootstrap:(Ljava/lang/invoke/MethodHandles$Lookup;Ljava/lang/String;Ljava/lang/invoke/MethodType;[Ljava/lang/invoke/MethodHandle;)Ljava/lang/invoke/CallSite;
    Method arguments:
      #53 REF_invokeStatic coursier/core/shaded/fastparse/ParserInputSourceLowPri$FromReadable.$anonfun$parseThrough$1:(Lcoursier/core/shaded/fastparse/ParserInputSourceLowPri$FromReadable;Lscala/Function1;Ljava/io/InputStream;)Ljava/lang/Object;
  ScalaInlineInfo: length = 0x63 (unknown attribute)
   01 00 00 13 00 31 00 32 01 00 51 00 52 00 00 16
   00 26 00 00 76 00 77 00 00 4B 00 4C 00 00 55 00
   23 00 00 56 00 26 00 00 95 00 77 00 00 4D 00 4E
   00 00 7F 00 26 00 00 29 00 2A 00 00 5C 00 26 00
   00 5D 00 5E 00 00 79 00 7A 00 00 1A 00 1B 00 00
   6B 00 1B 00 00 59 00 5A 00 00 14 00 23 00 00 90
   00 5A 00
  Scala: length = 0x0 (unknown attribute)

