Classfile /Users/mw/Projects/slang-braindump/.jar/jar11/assemble/slang-braindump/assemble/content/coursier/core/shaded/fastparse/ScalaWhitespace$.class
  Last modified May 29, 2022; size 4822 bytes
  SHA-256 checksum 04441f6922deddfe478830fb75f1383307a3eeb2ce4581a7ba6e76a5c70051c0
  Compiled from "Whitespace.scala"
public final class coursier.core.shaded.fastparse.ScalaWhitespace$
  minor version: 0
  major version: 52
  flags: (0x0031) ACC_PUBLIC, ACC_FINAL, ACC_SUPER
  this_class: #2                          // coursier/core/shaded/fastparse/ScalaWhitespace$
  super_class: #4                         // java/lang/Object
  interfaces: 0, fields: 2, methods: 7, attributes: 5
Constant pool:
    #1 = Utf8               coursier/core/shaded/fastparse/ScalaWhitespace$
    #2 = Class              #1            // coursier/core/shaded/fastparse/ScalaWhitespace$
    #3 = Utf8               java/lang/Object
    #4 = Class              #3            // java/lang/Object
    #5 = Utf8               Whitespace.scala
    #6 = Utf8               java/lang/invoke/MethodHandles$Lookup
    #7 = Class              #6            // java/lang/invoke/MethodHandles$Lookup
    #8 = Utf8               java/lang/invoke/MethodHandles
    #9 = Class              #8            // java/lang/invoke/MethodHandles
   #10 = Utf8               Lookup
   #11 = Utf8               MODULE$
   #12 = Utf8               Lcoursier/core/shaded/fastparse/ScalaWhitespace$;
   #13 = Utf8               whitespace
   #14 = Utf8               Lscala/Function1;
   #15 = Utf8               Lscala/Function1<Lcoursier/core/shaded/fastparse/ParsingRun<*>;Lcoursier/core/shaded/fastparse/ParsingRun<Lscala/runtime/BoxedUnit;>;>;
   #16 = Utf8               <clinit>
   #17 = Utf8               ()V
   #18 = Utf8               <init>
   #19 = NameAndType        #18:#17       // "<init>":()V
   #20 = Methodref          #2.#19        // coursier/core/shaded/fastparse/ScalaWhitespace$."<init>":()V
   #21 = NameAndType        #11:#12       // MODULE$:Lcoursier/core/shaded/fastparse/ScalaWhitespace$;
   #22 = Fieldref           #2.#21        // coursier/core/shaded/fastparse/ScalaWhitespace$.MODULE$:Lcoursier/core/shaded/fastparse/ScalaWhitespace$;
   #23 = Utf8               (Ljava/lang/Object;)Ljava/lang/Object;
   #24 = MethodType         #23           //  (Ljava/lang/Object;)Ljava/lang/Object;
   #25 = Utf8               $anonfun$whitespace$8
   #26 = Utf8               (Lcoursier/core/shaded/fastparse/ScalaWhitespace$;Lcoursier/core/shaded/fastparse/ParsingRun;)Lcoursier/core/shaded/fastparse/ParsingRun;
   #27 = NameAndType        #25:#26       // $anonfun$whitespace$8:(Lcoursier/core/shaded/fastparse/ScalaWhitespace$;Lcoursier/core/shaded/fastparse/ParsingRun;)Lcoursier/core/shaded/fastparse/ParsingRun;
   #28 = Methodref          #2.#27        // coursier/core/shaded/fastparse/ScalaWhitespace$.$anonfun$whitespace$8:(Lcoursier/core/shaded/fastparse/ScalaWhitespace$;Lcoursier/core/shaded/fastparse/ParsingRun;)Lcoursier/core/shaded/fastparse/ParsingRun;
   #29 = MethodHandle       6:#28         // REF_invokeStatic coursier/core/shaded/fastparse/ScalaWhitespace$.$anonfun$whitespace$8:(Lcoursier/core/shaded/fastparse/ScalaWhitespace$;Lcoursier/core/shaded/fastparse/ParsingRun;)Lcoursier/core/shaded/fastparse/ParsingRun;
   #30 = Utf8               (Lcoursier/core/shaded/fastparse/ParsingRun;)Lcoursier/core/shaded/fastparse/ParsingRun;
   #31 = MethodType         #30           //  (Lcoursier/core/shaded/fastparse/ParsingRun;)Lcoursier/core/shaded/fastparse/ParsingRun;
   #32 = Integer            5
   #33 = Integer            1
   #34 = Utf8               java/lang/invoke/LambdaMetafactory
   #35 = Class              #34           // java/lang/invoke/LambdaMetafactory
   #36 = Utf8               altMetafactory
   #37 = Utf8               (Ljava/lang/invoke/MethodHandles$Lookup;Ljava/lang/String;Ljava/lang/invoke/MethodType;[Ljava/lang/Object;)Ljava/lang/invoke/CallSite;
   #38 = NameAndType        #36:#37       // altMetafactory:(Ljava/lang/invoke/MethodHandles$Lookup;Ljava/lang/String;Ljava/lang/invoke/MethodType;[Ljava/lang/Object;)Ljava/lang/invoke/CallSite;
   #39 = Methodref          #35.#38       // java/lang/invoke/LambdaMetafactory.altMetafactory:(Ljava/lang/invoke/MethodHandles$Lookup;Ljava/lang/String;Ljava/lang/invoke/MethodType;[Ljava/lang/Object;)Ljava/lang/invoke/CallSite;
   #40 = MethodHandle       6:#39         // REF_invokeStatic java/lang/invoke/LambdaMetafactory.altMetafactory:(Ljava/lang/invoke/MethodHandles$Lookup;Ljava/lang/String;Ljava/lang/invoke/MethodType;[Ljava/lang/Object;)Ljava/lang/invoke/CallSite;
   #41 = Utf8               apply
   #42 = Utf8               (Lcoursier/core/shaded/fastparse/ScalaWhitespace$;)Lscala/Function1;
   #43 = NameAndType        #41:#42       // apply:(Lcoursier/core/shaded/fastparse/ScalaWhitespace$;)Lscala/Function1;
   #44 = InvokeDynamic      #0:#43        // #0:apply:(Lcoursier/core/shaded/fastparse/ScalaWhitespace$;)Lscala/Function1;
   #45 = NameAndType        #13:#14       // whitespace:Lscala/Function1;
   #46 = Fieldref           #2.#45        // coursier/core/shaded/fastparse/ScalaWhitespace$.whitespace:Lscala/Function1;
   #47 = Utf8               ()Lscala/Function1;
   #48 = Utf8               ()Lscala/Function1<Lcoursier/core/shaded/fastparse/ParsingRun<*>;Lcoursier/core/shaded/fastparse/ParsingRun<Lscala/runtime/BoxedUnit;>;>;
   #49 = Utf8               this
   #50 = Utf8               $anonfun$whitespace$9
   #51 = Utf8               ()Ljava/lang/String;
   #52 = Utf8               coursier/core/shaded/fastparse/internal/Util$
   #53 = Class              #52           // coursier/core/shaded/fastparse/internal/Util$
   #54 = Utf8               Lcoursier/core/shaded/fastparse/internal/Util$;
   #55 = NameAndType        #11:#54       // MODULE$:Lcoursier/core/shaded/fastparse/internal/Util$;
   #56 = Fieldref           #53.#55       // coursier/core/shaded/fastparse/internal/Util$.MODULE$:Lcoursier/core/shaded/fastparse/internal/Util$;
   #57 = Utf8               scala/Predef$
   #58 = Class              #57           // scala/Predef$
   #59 = Utf8               Lscala/Predef$;
   #60 = NameAndType        #11:#59       // MODULE$:Lscala/Predef$;
   #61 = Fieldref           #58.#60       // scala/Predef$.MODULE$:Lscala/Predef$;
   #62 = Utf8               */
   #63 = String             #62           // */
   #64 = Utf8               wrapString
   #65 = Utf8               (Ljava/lang/String;)Lscala/collection/immutable/WrappedString;
   #66 = NameAndType        #64:#65       // wrapString:(Ljava/lang/String;)Lscala/collection/immutable/WrappedString;
   #67 = Methodref          #58.#66       // scala/Predef$.wrapString:(Ljava/lang/String;)Lscala/collection/immutable/WrappedString;
   #68 = Utf8               literalize$default$2
   #69 = Utf8               ()Z
   #70 = NameAndType        #68:#69       // literalize$default$2:()Z
   #71 = Methodref          #53.#70       // coursier/core/shaded/fastparse/internal/Util$.literalize$default$2:()Z
   #72 = Utf8               literalize
   #73 = Utf8               (Lscala/collection/immutable/IndexedSeq;Z)Ljava/lang/String;
   #74 = NameAndType        #72:#73       // literalize:(Lscala/collection/immutable/IndexedSeq;Z)Ljava/lang/String;
   #75 = Methodref          #53.#74       // coursier/core/shaded/fastparse/internal/Util$.literalize:(Lscala/collection/immutable/IndexedSeq;Z)Ljava/lang/String;
   #76 = Utf8               rec$4
   #77 = Utf8               (IIILcoursier/core/shaded/fastparse/ParserInput;Lcoursier/core/shaded/fastparse/ParsingRun;I)Lcoursier/core/shaded/fastparse/ParsingRun;
   #78 = Utf8               current
   #79 = Utf8               state
   #80 = Utf8               nesting
   #81 = Utf8               input$4
   #82 = Utf8               ctx$4
   #83 = Utf8               startIndex$3
   #84 = Utf8               coursier/core/shaded/fastparse/ParserInput
   #85 = Class              #84           // coursier/core/shaded/fastparse/ParserInput
   #86 = Utf8               isReachable
   #87 = Utf8               (I)Z
   #88 = NameAndType        #86:#87       // isReachable:(I)Z
   #89 = Methodref          #85.#88       // coursier/core/shaded/fastparse/ParserInput.isReachable:(I)Z
   #90 = Utf8               coursier/core/shaded/fastparse/ParsingRun
   #91 = Class              #90           // coursier/core/shaded/fastparse/ParsingRun
   #92 = Utf8               freshSuccessUnit
   #93 = Utf8               (I)Lcoursier/core/shaded/fastparse/ParsingRun;
   #94 = NameAndType        #92:#93       // freshSuccessUnit:(I)Lcoursier/core/shaded/fastparse/ParsingRun;
   #95 = Methodref          #91.#94       // coursier/core/shaded/fastparse/ParsingRun.freshSuccessUnit:(I)Lcoursier/core/shaded/fastparse/ParsingRun;
   #96 = Utf8               cut_$eq
   #97 = Utf8               (Z)V
   #98 = NameAndType        #96:#97       // cut_$eq:(Z)V
   #99 = Methodref          #91.#98       // coursier/core/shaded/fastparse/ParsingRun.cut_$eq:(Z)V
  #100 = Utf8               freshFailure
  #101 = NameAndType        #100:#93      // freshFailure:(I)Lcoursier/core/shaded/fastparse/ParsingRun;
  #102 = Methodref          #91.#101      // coursier/core/shaded/fastparse/ParsingRun.freshFailure:(I)Lcoursier/core/shaded/fastparse/ParsingRun;
  #103 = Utf8               verboseFailures
  #104 = NameAndType        #103:#69      // verboseFailures:()Z
  #105 = Methodref          #91.#104      // coursier/core/shaded/fastparse/ParsingRun.verboseFailures:()Z
  #106 = Utf8               ()Ljava/lang/Object;
  #107 = MethodType         #106          //  ()Ljava/lang/Object;
  #108 = NameAndType        #50:#51       // $anonfun$whitespace$9:()Ljava/lang/String;
  #109 = Methodref          #2.#108       // coursier/core/shaded/fastparse/ScalaWhitespace$.$anonfun$whitespace$9:()Ljava/lang/String;
  #110 = MethodHandle       6:#109        // REF_invokeStatic coursier/core/shaded/fastparse/ScalaWhitespace$.$anonfun$whitespace$9:()Ljava/lang/String;
  #111 = MethodType         #51           //  ()Ljava/lang/String;
  #112 = Utf8               ()Lscala/Function0;
  #113 = NameAndType        #41:#112      // apply:()Lscala/Function0;
  #114 = InvokeDynamic      #1:#113       // #1:apply:()Lscala/Function0;
  #115 = Utf8               setMsg
  #116 = Utf8               (ILscala/Function0;)V
  #117 = NameAndType        #115:#116     // setMsg:(ILscala/Function0;)V
  #118 = Methodref          #91.#117      // coursier/core/shaded/fastparse/ParsingRun.setMsg:(ILscala/Function0;)V
  #119 = Utf8               (I)C
  #120 = NameAndType        #41:#119      // apply:(I)C
  #121 = Methodref          #85.#120      // coursier/core/shaded/fastparse/ParserInput.apply:(I)C
  #122 = Utf8               scala/MatchError
  #123 = Class              #122          // scala/MatchError
  #124 = Utf8               scala/runtime/BoxesRunTime
  #125 = Class              #124          // scala/runtime/BoxesRunTime
  #126 = Utf8               boxToInteger
  #127 = Utf8               (I)Ljava/lang/Integer;
  #128 = NameAndType        #126:#127     // boxToInteger:(I)Ljava/lang/Integer;
  #129 = Methodref          #125.#128     // scala/runtime/BoxesRunTime.boxToInteger:(I)Ljava/lang/Integer;
  #130 = Utf8               (Ljava/lang/Object;)V
  #131 = NameAndType        #18:#130      // "<init>":(Ljava/lang/Object;)V
  #132 = Methodref          #123.#131     // scala/MatchError."<init>":(Ljava/lang/Object;)V
  #133 = Utf8               res
  #134 = Utf8               Lcoursier/core/shaded/fastparse/ParsingRun;
  #135 = Utf8               currentChar
  #136 = Utf8               C
  #137 = Utf8               I
  #138 = Utf8               Lcoursier/core/shaded/fastparse/ParserInput;
  #139 = Utf8               $this
  #140 = Utf8               ctx
  #141 = Utf8               input
  #142 = Utf8               ()Lcoursier/core/shaded/fastparse/ParserInput;
  #143 = NameAndType        #141:#142     // input:()Lcoursier/core/shaded/fastparse/ParserInput;
  #144 = Methodref          #91.#143      // coursier/core/shaded/fastparse/ParsingRun.input:()Lcoursier/core/shaded/fastparse/ParserInput;
  #145 = Utf8               index
  #146 = Utf8               ()I
  #147 = NameAndType        #145:#146     // index:()I
  #148 = Methodref          #91.#147      // coursier/core/shaded/fastparse/ParsingRun.index:()I
  #149 = NameAndType        #76:#77       // rec$4:(IIILcoursier/core/shaded/fastparse/ParserInput;Lcoursier/core/shaded/fastparse/ParsingRun;I)Lcoursier/core/shaded/fastparse/ParsingRun;
  #150 = Methodref          #2.#149       // coursier/core/shaded/fastparse/ScalaWhitespace$.rec$4:(IIILcoursier/core/shaded/fastparse/ParserInput;Lcoursier/core/shaded/fastparse/ParsingRun;I)Lcoursier/core/shaded/fastparse/ParsingRun;
  #151 = Utf8               startIndex
  #152 = Methodref          #4.#19        // java/lang/Object."<init>":()V
  #153 = Utf8               $deserializeLambda$
  #154 = Utf8               (Ljava/lang/invoke/SerializedLambda;)Ljava/lang/Object;
  #155 = Utf8               scala/runtime/LambdaDeserialize
  #156 = Class              #155          // scala/runtime/LambdaDeserialize
  #157 = Utf8               bootstrap
  #158 = Utf8               (Ljava/lang/invoke/MethodHandles$Lookup;Ljava/lang/String;Ljava/lang/invoke/MethodType;[Ljava/lang/invoke/MethodHandle;)Ljava/lang/invoke/CallSite;
  #159 = NameAndType        #157:#158     // bootstrap:(Ljava/lang/invoke/MethodHandles$Lookup;Ljava/lang/String;Ljava/lang/invoke/MethodType;[Ljava/lang/invoke/MethodHandle;)Ljava/lang/invoke/CallSite;
  #160 = Methodref          #156.#159     // scala/runtime/LambdaDeserialize.bootstrap:(Ljava/lang/invoke/MethodHandles$Lookup;Ljava/lang/String;Ljava/lang/invoke/MethodType;[Ljava/lang/invoke/MethodHandle;)Ljava/lang/invoke/CallSite;
  #161 = MethodHandle       6:#160        // REF_invokeStatic scala/runtime/LambdaDeserialize.bootstrap:(Ljava/lang/invoke/MethodHandles$Lookup;Ljava/lang/String;Ljava/lang/invoke/MethodType;[Ljava/lang/invoke/MethodHandle;)Ljava/lang/invoke/CallSite;
  #162 = Utf8               lambdaDeserialize
  #163 = NameAndType        #162:#154     // lambdaDeserialize:(Ljava/lang/invoke/SerializedLambda;)Ljava/lang/Object;
  #164 = InvokeDynamic      #2:#163       // #2:lambdaDeserialize:(Ljava/lang/invoke/SerializedLambda;)Ljava/lang/Object;
  #165 = Utf8               Signature
  #166 = Utf8               Code
  #167 = Utf8               LineNumberTable
  #168 = Utf8               LocalVariableTable
  #169 = Utf8               StackMapTable
  #170 = Utf8               MethodParameters
  #171 = Utf8               InnerClasses
  #172 = Utf8               SourceFile
  #173 = Utf8               BootstrapMethods
  #174 = Utf8               ScalaInlineInfo
  #175 = Utf8               Scala
{
  public static final coursier.core.shaded.fastparse.ScalaWhitespace$ MODULE$;
    descriptor: Lcoursier/core/shaded/fastparse/ScalaWhitespace$;
    flags: (0x0019) ACC_PUBLIC, ACC_STATIC, ACC_FINAL

  private static final scala.Function1<coursier.core.shaded.fastparse.ParsingRun<?>, coursier.core.shaded.fastparse.ParsingRun<scala.runtime.BoxedUnit>> whitespace;
    descriptor: Lscala/Function1;
    flags: (0x001a) ACC_PRIVATE, ACC_STATIC, ACC_FINAL
    Signature: #15                          // Lscala/Function1<Lcoursier/core/shaded/fastparse/ParsingRun<*>;Lcoursier/core/shaded/fastparse/ParsingRun<Lscala/runtime/BoxedUnit;>;>;

  public static {};
    descriptor: ()V
    flags: (0x0009) ACC_PUBLIC, ACC_STATIC
    Code:
      stack=2, locals=0, args_size=0
         0: new           #2                  // class coursier/core/shaded/fastparse/ScalaWhitespace$
         3: dup
         4: invokespecial #20                 // Method "<init>":()V
         7: putstatic     #22                 // Field MODULE$:Lcoursier/core/shaded/fastparse/ScalaWhitespace$;
        10: getstatic     #22                 // Field MODULE$:Lcoursier/core/shaded/fastparse/ScalaWhitespace$;
        13: invokedynamic #44,  0             // InvokeDynamic #0:apply:(Lcoursier/core/shaded/fastparse/ScalaWhitespace$;)Lscala/Function1;
        18: putstatic     #46                 // Field whitespace:Lscala/Function1;
        21: return
      LineNumberTable:
        line 180: 0
        line 181: 10
        line 180: 21

  public scala.Function1<coursier.core.shaded.fastparse.ParsingRun<?>, coursier.core.shaded.fastparse.ParsingRun<scala.runtime.BoxedUnit>> whitespace();
    descriptor: ()Lscala/Function1;
    flags: (0x0001) ACC_PUBLIC
    Code:
      stack=1, locals=1, args_size=1
         0: getstatic     #46                 // Field whitespace:Lscala/Function1;
         3: areturn
      LineNumberTable:
        line 181: 0
      LocalVariableTable:
        Start  Length  Slot  Name   Signature
            0       4     0  this   Lcoursier/core/shaded/fastparse/ScalaWhitespace$;
    Signature: #48                          // ()Lscala/Function1<Lcoursier/core/shaded/fastparse/ParsingRun<*>;Lcoursier/core/shaded/fastparse/ParsingRun<Lscala/runtime/BoxedUnit;>;>;

  public static final java.lang.String $anonfun$whitespace$9();
    descriptor: ()Ljava/lang/String;
    flags: (0x1019) ACC_PUBLIC, ACC_STATIC, ACC_FINAL, ACC_SYNTHETIC
    Code:
      stack=3, locals=0, args_size=0
         0: getstatic     #56                 // Field coursier/core/shaded/fastparse/internal/Util$.MODULE$:Lcoursier/core/shaded/fastparse/internal/Util$;
         3: getstatic     #61                 // Field scala/Predef$.MODULE$:Lscala/Predef$;
         6: ldc           #63                 // String */
         8: invokevirtual #67                 // Method scala/Predef$.wrapString:(Ljava/lang/String;)Lscala/collection/immutable/WrappedString;
        11: getstatic     #56                 // Field coursier/core/shaded/fastparse/internal/Util$.MODULE$:Lcoursier/core/shaded/fastparse/internal/Util$;
        14: invokevirtual #71                 // Method coursier/core/shaded/fastparse/internal/Util$.literalize$default$2:()Z
        17: invokevirtual #75                 // Method coursier/core/shaded/fastparse/internal/Util$.literalize:(Lscala/collection/immutable/IndexedSeq;Z)Ljava/lang/String;
        20: areturn
      LineNumberTable:
        line 191: 0

  private final coursier.core.shaded.fastparse.ParsingRun rec$4(int, int, int, coursier.core.shaded.fastparse.ParserInput, coursier.core.shaded.fastparse.ParsingRun, int);
    descriptor: (IIILcoursier/core/shaded/fastparse/ParserInput;Lcoursier/core/shaded/fastparse/ParsingRun;I)Lcoursier/core/shaded/fastparse/ParsingRun;
    flags: (0x0012) ACC_PRIVATE, ACC_FINAL
    Code:
      stack=4, locals=15, args_size=7
         0: aload         4
         2: iload_1
         3: invokevirtual #89                 // Method coursier/core/shaded/fastparse/ParserInput.isReachable:(I)Z
         6: ifne          91
         9: iload_2
        10: iconst_0
        11: if_icmpeq     19
        14: iload_2
        15: iconst_1
        16: if_icmpne     28
        19: aload         5
        21: iload_1
        22: invokevirtual #95                 // Method coursier/core/shaded/fastparse/ParsingRun.freshSuccessUnit:(I)Lcoursier/core/shaded/fastparse/ParsingRun;
        25: goto          88
        28: iload_2
        29: iconst_2
        30: if_icmpne     49
        33: iload_3
        34: iconst_0
        35: if_icmpne     49
        38: aload         5
        40: iload_1
        41: iconst_1
        42: isub
        43: invokevirtual #95                 // Method coursier/core/shaded/fastparse/ParsingRun.freshSuccessUnit:(I)Lcoursier/core/shaded/fastparse/ParsingRun;
        46: goto          88
        49: aload         5
        51: iconst_1
        52: invokevirtual #99                 // Method coursier/core/shaded/fastparse/ParsingRun.cut_$eq:(Z)V
        55: aload         5
        57: iload_1
        58: invokevirtual #102                // Method coursier/core/shaded/fastparse/ParsingRun.freshFailure:(I)Lcoursier/core/shaded/fastparse/ParsingRun;
        61: astore        8
        63: aload         5
        65: invokevirtual #105                // Method coursier/core/shaded/fastparse/ParsingRun.verboseFailures:()Z
        68: ifeq          86
        71: aload         5
        73: iload         6
        75: invokedynamic #114,  0            // InvokeDynamic #1:apply:()Lscala/Function0;
        80: invokevirtual #118                // Method coursier/core/shaded/fastparse/ParsingRun.setMsg:(ILscala/Function0;)V
        83: goto          86
        86: aload         8
        88: goto          509
        91: aload         4
        93: iload_1
        94: invokevirtual #121                // Method coursier/core/shaded/fastparse/ParserInput.apply:(I)C
        97: istore        9
        99: iload_2
       100: istore        10
       102: iload         10
       104: tableswitch   { // 0 to 4
                       0: 140
                       1: 230
                       2: 252
                       3: 357
                       4: 421
                 default: 496
            }
       140: iload         9
       142: istore        11
       144: iload         11
       146: lookupswitch  { // 5
                       9: 196
                      10: 196
                      13: 196
                      32: 196
                      47: 207
                 default: 218
            }
       196: iload_1
       197: iconst_1
       198: iadd
       199: iload_2
       200: iconst_0
       201: istore_3
       202: istore_2
       203: istore_1
       204: goto          0
       207: iload_1
       208: iconst_1
       209: iadd
       210: iconst_2
       211: iconst_0
       212: istore_3
       213: istore_2
       214: istore_1
       215: goto          0
       218: aload         5
       220: iload_1
       221: invokevirtual #95                 // Method coursier/core/shaded/fastparse/ParsingRun.freshSuccessUnit:(I)Lcoursier/core/shaded/fastparse/ParsingRun;
       224: goto          227
       227: goto          509
       230: iload_1
       231: iconst_1
       232: iadd
       233: iload         9
       235: bipush        10
       237: if_icmpne     244
       240: iconst_0
       241: goto          245
       244: iload_2
       245: iconst_0
       246: istore_3
       247: istore_2
       248: istore_1
       249: goto          0
       252: iload         9
       254: istore        12
       256: iload         12
       258: lookupswitch  { // 2
                      42: 311
                      47: 284
                 default: 324
            }
       284: iload_3
       285: iconst_0
       286: if_icmpne     300
       289: iload_1
       290: iconst_1
       291: iadd
       292: iconst_1
       293: iconst_0
       294: istore_3
       295: istore_2
       296: istore_1
       297: goto          0
       300: iload_1
       301: iconst_1
       302: iadd
       303: iconst_2
       304: iload_3
       305: istore_3
       306: istore_2
       307: istore_1
       308: goto          0
       311: iload_1
       312: iconst_1
       313: iadd
       314: iconst_3
       315: iload_3
       316: iconst_1
       317: iadd
       318: istore_3
       319: istore_2
       320: istore_1
       321: goto          0
       324: iload_3
       325: iconst_0
       326: if_icmpne     340
       329: aload         5
       331: iload_1
       332: iconst_1
       333: isub
       334: invokevirtual #95                 // Method coursier/core/shaded/fastparse/ParsingRun.freshSuccessUnit:(I)Lcoursier/core/shaded/fastparse/ParsingRun;
       337: goto          351
       340: iload_1
       341: iconst_1
       342: iadd
       343: iconst_3
       344: iload_3
       345: istore_3
       346: istore_2
       347: istore_1
       348: goto          0
       351: goto          354
       354: goto          509
       357: iload         9
       359: istore        13
       361: iload         13
       363: lookupswitch  { // 2
                      42: 399
                      47: 388
                 default: 410
            }
       388: iload_1
       389: iconst_1
       390: iadd
       391: iconst_2
       392: iload_3
       393: istore_3
       394: istore_2
       395: istore_1
       396: goto          0
       399: iload_1
       400: iconst_1
       401: iadd
       402: iconst_4
       403: iload_3
       404: istore_3
       405: istore_2
       406: istore_1
       407: goto          0
       410: iload_1
       411: iconst_1
       412: iadd
       413: iload_2
       414: iload_3
       415: istore_3
       416: istore_2
       417: istore_1
       418: goto          0
       421: iload         9
       423: istore        14
       425: iload         14
       427: lookupswitch  { // 2
                      42: 474
                      47: 452
                 default: 485
            }
       452: iload_1
       453: iconst_1
       454: iadd
       455: iload_3
       456: iconst_1
       457: if_icmpne     464
       460: iconst_0
       461: goto          465
       464: iconst_3
       465: iload_3
       466: iconst_1
       467: isub
       468: istore_3
       469: istore_2
       470: istore_1
       471: goto          0
       474: iload_1
       475: iconst_1
       476: iadd
       477: iconst_4
       478: iload_3
       479: istore_3
       480: istore_2
       481: istore_1
       482: goto          0
       485: iload_1
       486: iconst_1
       487: iadd
       488: iconst_3
       489: iload_3
       490: istore_3
       491: istore_2
       492: istore_1
       493: goto          0
       496: new           #123                // class scala/MatchError
       499: dup
       500: iload         10
       502: invokestatic  #129                // Method scala/runtime/BoxesRunTime.boxToInteger:(I)Ljava/lang/Integer;
       505: invokespecial #132                // Method scala/MatchError."<init>":(Ljava/lang/Object;)V
       508: athrow
       509: areturn
      StackMapTable: number_of_entries = 35
        frame_type = 0 /* same */
        frame_type = 18 /* same */
        frame_type = 8 /* same */
        frame_type = 20 /* same */
        frame_type = 253 /* append */
          offset_delta = 36
          locals = [ top, class coursier/core/shaded/fastparse/ParsingRun ]
        frame_type = 255 /* full_frame */
          offset_delta = 1
          locals = [ class coursier/core/shaded/fastparse/ScalaWhitespace$, int, int, int, class coursier/core/shaded/fastparse/ParserInput, class coursier/core/shaded/fastparse/ParsingRun, int ]
          stack = [ class coursier/core/shaded/fastparse/ParsingRun ]
        frame_type = 2 /* same */
        frame_type = 255 /* full_frame */
          offset_delta = 48
          locals = [ class coursier/core/shaded/fastparse/ScalaWhitespace$, int, int, int, class coursier/core/shaded/fastparse/ParserInput, class coursier/core/shaded/fastparse/ParsingRun, int, top, top, int, int ]
          stack = []
        frame_type = 252 /* append */
          offset_delta = 55
          locals = [ int ]
        frame_type = 10 /* same */
        frame_type = 10 /* same */
        frame_type = 72 /* same_locals_1_stack_item */
          stack = [ class coursier/core/shaded/fastparse/ParsingRun ]
        frame_type = 250 /* chop */
          offset_delta = 2
        frame_type = 77 /* same_locals_1_stack_item */
          stack = [ int ]
        frame_type = 255 /* full_frame */
          offset_delta = 0
          locals = [ class coursier/core/shaded/fastparse/ScalaWhitespace$, int, int, int, class coursier/core/shaded/fastparse/ParserInput, class coursier/core/shaded/fastparse/ParsingRun, int, top, top, int, int ]
          stack = [ int, int ]
        frame_type = 6 /* same */
        frame_type = 253 /* append */
          offset_delta = 31
          locals = [ top, int ]
        frame_type = 15 /* same */
        frame_type = 10 /* same */
        frame_type = 12 /* same */
        frame_type = 15 /* same */
        frame_type = 74 /* same_locals_1_stack_item */
          stack = [ class coursier/core/shaded/fastparse/ParsingRun ]
        frame_type = 66 /* same_locals_1_stack_item */
          stack = [ class coursier/core/shaded/fastparse/ParsingRun ]
        frame_type = 249 /* chop */
          offset_delta = 2
        frame_type = 254 /* append */
          offset_delta = 30
          locals = [ top, top, int ]
        frame_type = 10 /* same */
        frame_type = 10 /* same */
        frame_type = 248 /* chop */
          offset_delta = 10
        frame_type = 255 /* full_frame */
          offset_delta = 30
          locals = [ class coursier/core/shaded/fastparse/ScalaWhitespace$, int, int, int, class coursier/core/shaded/fastparse/ParserInput, class coursier/core/shaded/fastparse/ParsingRun, int, top, top, int, int, top, top, top, int ]
          stack = []
        frame_type = 75 /* same_locals_1_stack_item */
          stack = [ int ]
        frame_type = 255 /* full_frame */
          offset_delta = 0
          locals = [ class coursier/core/shaded/fastparse/ScalaWhitespace$, int, int, int, class coursier/core/shaded/fastparse/ParserInput, class coursier/core/shaded/fastparse/ParsingRun, int, top, top, int, int, top, top, top, int ]
          stack = [ int, int ]
        frame_type = 8 /* same */
        frame_type = 10 /* same */
        frame_type = 255 /* full_frame */
          offset_delta = 10
          locals = [ class coursier/core/shaded/fastparse/ScalaWhitespace$, int, int, int, class coursier/core/shaded/fastparse/ParserInput, class coursier/core/shaded/fastparse/ParsingRun, int, top, top, int, int ]
          stack = []
        frame_type = 255 /* full_frame */
          offset_delta = 12
          locals = [ class coursier/core/shaded/fastparse/ScalaWhitespace$, int, int, int, class coursier/core/shaded/fastparse/ParserInput, class coursier/core/shaded/fastparse/ParsingRun, int ]
          stack = [ class coursier/core/shaded/fastparse/ParsingRun ]
      LineNumberTable:
        line 185: 0
        line 186: 9
        line 187: 28
        line 189: 49
        line 190: 55
        line 191: 63
        line 192: 86
        line 195: 91
        line 196: 99
        line 198: 140
        line 199: 196
        line 200: 207
        line 201: 218
        line 203: 230
        line 205: 252
        line 207: 284
        line 208: 300
        line 209: 311
        line 211: 324
        line 212: 340
        line 215: 357
        line 216: 388
        line 217: 399
        line 218: 410
        line 221: 421
        line 222: 452
        line 223: 474
        line 224: 485
        line 196: 496
      LocalVariableTable:
        Start  Length  Slot  Name   Signature
           61      27     8   res   Lcoursier/core/shaded/fastparse/ParsingRun;
           97     412     9 currentChar   C
            0     510     0  this   Lcoursier/core/shaded/fastparse/ScalaWhitespace$;
            0     510     1 current   I
            0     510     2 state   I
            0     510     3 nesting   I
            0     510     4 input$4   Lcoursier/core/shaded/fastparse/ParserInput;
            0     510     5 ctx$4   Lcoursier/core/shaded/fastparse/ParsingRun;
            0     510     6 startIndex$3   I
    MethodParameters:
      Name                           Flags
      current                        final
      state                          final
      nesting                        final
      input$4                        final
      ctx$4                          final
      startIndex$3                   final

  public static final coursier.core.shaded.fastparse.ParsingRun $anonfun$whitespace$8(coursier.core.shaded.fastparse.ScalaWhitespace$, coursier.core.shaded.fastparse.ParsingRun);
    descriptor: (Lcoursier/core/shaded/fastparse/ScalaWhitespace$;Lcoursier/core/shaded/fastparse/ParsingRun;)Lcoursier/core/shaded/fastparse/ParsingRun;
    flags: (0x1019) ACC_PUBLIC, ACC_STATIC, ACC_FINAL, ACC_SYNTHETIC
    Code:
      stack=7, locals=4, args_size=2
         0: aload_1
         1: invokevirtual #144                // Method coursier/core/shaded/fastparse/ParsingRun.input:()Lcoursier/core/shaded/fastparse/ParserInput;
         4: astore_2
         5: aload_1
         6: invokevirtual #148                // Method coursier/core/shaded/fastparse/ParsingRun.index:()I
         9: istore_3
        10: aload_0
        11: aload_1
        12: invokevirtual #148                // Method coursier/core/shaded/fastparse/ParsingRun.index:()I
        15: iconst_0
        16: iconst_0
        17: aload_2
        18: aload_1
        19: iload_3
        20: invokespecial #150                // Method rec$4:(IIILcoursier/core/shaded/fastparse/ParserInput;Lcoursier/core/shaded/fastparse/ParsingRun;I)Lcoursier/core/shaded/fastparse/ParsingRun;
        23: areturn
      LineNumberTable:
        line 182: 0
        line 183: 5
        line 229: 10
      LocalVariableTable:
        Start  Length  Slot  Name   Signature
            4      19     2 input   Lcoursier/core/shaded/fastparse/ParserInput;
            9      14     3 startIndex   I
            0      24     0 $this   Lcoursier/core/shaded/fastparse/ScalaWhitespace$;
            0      24     1   ctx   Lcoursier/core/shaded/fastparse/ParsingRun;
    MethodParameters:
      Name                           Flags
      $this                          final synthetic
      ctx                            final

  private coursier.core.shaded.fastparse.ScalaWhitespace$();
    descriptor: ()V
    flags: (0x0002) ACC_PRIVATE
    Code:
      stack=1, locals=1, args_size=1
         0: aload_0
         1: invokespecial #152                // Method java/lang/Object."<init>":()V
         4: return
      LineNumberTable:
        line 233: 0
        line 180: 4
      LocalVariableTable:
        Start  Length  Slot  Name   Signature
            0       5     0  this   Lcoursier/core/shaded/fastparse/ScalaWhitespace$;

  private static java.lang.Object $deserializeLambda$(java.lang.invoke.SerializedLambda);
    descriptor: (Ljava/lang/invoke/SerializedLambda;)Ljava/lang/Object;
    flags: (0x100a) ACC_PRIVATE, ACC_STATIC, ACC_SYNTHETIC
    Code:
      stack=1, locals=1, args_size=1
         0: aload_0
         1: invokedynamic #164,  0            // InvokeDynamic #2:lambdaDeserialize:(Ljava/lang/invoke/SerializedLambda;)Ljava/lang/Object;
         6: areturn
}
InnerClasses:
  public static final #10= #7 of #9;      // Lookup=class java/lang/invoke/MethodHandles$Lookup of class java/lang/invoke/MethodHandles
SourceFile: "Whitespace.scala"
BootstrapMethods:
  0: #40 REF_invokeStatic java/lang/invoke/LambdaMetafactory.altMetafactory:(Ljava/lang/invoke/MethodHandles$Lookup;Ljava/lang/String;Ljava/lang/invoke/MethodType;[Ljava/lang/Object;)Ljava/lang/invoke/CallSite;
    Method arguments:
      #24 (Ljava/lang/Object;)Ljava/lang/Object;
      #29 REF_invokeStatic coursier/core/shaded/fastparse/ScalaWhitespace$.$anonfun$whitespace$8:(Lcoursier/core/shaded/fastparse/ScalaWhitespace$;Lcoursier/core/shaded/fastparse/ParsingRun;)Lcoursier/core/shaded/fastparse/ParsingRun;
      #31 (Lcoursier/core/shaded/fastparse/ParsingRun;)Lcoursier/core/shaded/fastparse/ParsingRun;
      #32 5
      #33 1
      #31 (Lcoursier/core/shaded/fastparse/ParsingRun;)Lcoursier/core/shaded/fastparse/ParsingRun;
  1: #40 REF_invokeStatic java/lang/invoke/LambdaMetafactory.altMetafactory:(Ljava/lang/invoke/MethodHandles$Lookup;Ljava/lang/String;Ljava/lang/invoke/MethodType;[Ljava/lang/Object;)Ljava/lang/invoke/CallSite;
    Method arguments:
      #107 ()Ljava/lang/Object;
      #110 REF_invokeStatic coursier/core/shaded/fastparse/ScalaWhitespace$.$anonfun$whitespace$9:()Ljava/lang/String;
      #111 ()Ljava/lang/String;
      #32 5
      #33 1
      #111 ()Ljava/lang/String;
  2: #161 REF_invokeStatic scala/runtime/LambdaDeserialize.bootstrap:(Ljava/lang/invoke/MethodHandles$Lookup;Ljava/lang/String;Ljava/lang/invoke/MethodType;[Ljava/lang/invoke/MethodHandle;)Ljava/lang/invoke/CallSite;
    Method arguments:
      #29 REF_invokeStatic coursier/core/shaded/fastparse/ScalaWhitespace$.$anonfun$whitespace$8:(Lcoursier/core/shaded/fastparse/ScalaWhitespace$;Lcoursier/core/shaded/fastparse/ParsingRun;)Lcoursier/core/shaded/fastparse/ParsingRun;
      #110 REF_invokeStatic coursier/core/shaded/fastparse/ScalaWhitespace$.$anonfun$whitespace$9:()Ljava/lang/String;
  ScalaInlineInfo: length = 0x1D (unknown attribute)
   01 01 00 05 00 19 00 1A 01 00 32 00 33 01 00 12
   00 11 01 00 4C 00 4D 01 00 0D 00 2F 01
  Scala: length = 0x0 (unknown attribute)

