Classfile /Users/mw/Projects/slang-braindump/.jar/jar11/assemble/slang-braindump/assemble/content/coursier/core/shaded/fastparse/SingleLineWhitespace.class
  Last modified May 29, 2022; size 1014 bytes
  SHA-256 checksum 6f44cb1fa947b0591d3aa5d2360287c2dd8dc19d30da99d0a21ebae20906760d
  Compiled from "Whitespace.scala"
public final class coursier.core.shaded.fastparse.SingleLineWhitespace
  minor version: 0
  major version: 52
  flags: (0x0031) ACC_PUBLIC, ACC_FINAL, ACC_SUPER
  this_class: #2                          // coursier/core/shaded/fastparse/SingleLineWhitespace
  super_class: #4                         // java/lang/Object
  interfaces: 0, fields: 0, methods: 1, attributes: 3
Constant pool:
   #1 = Utf8               coursier/core/shaded/fastparse/SingleLineWhitespace
   #2 = Class              #1             // coursier/core/shaded/fastparse/SingleLineWhitespace
   #3 = Utf8               java/lang/Object
   #4 = Class              #3             // java/lang/Object
   #5 = Utf8               Whitespace.scala
   #6 = Utf8               Lscala/reflect/ScalaSignature;
   #7 = Utf8               bytes
   #8 = Utf8               \u0006\u0005M:Q!\u0002\u0004\t\u0002%1Qa\u0003\u0004\t\u00021AQaE\u0001\u0005\u0002QAq!F\u0001C\u0002\u0013\ra\u0003\u0003\u0004\'\u0003\u0001\u0006IaF\u0001\u0015\'&tw\r\\3MS:,w\u000b[5uKN\u0004\u0018mY3\u000b\u0003\u001d\t\u0011BZ1tiB\f\'o]3\u0004\u0001A\u0011!\"A\u0007\u0002\r\t!2+\u001b8hY\u0016d\u0015N\\3XQ&$Xm\u001d9bG\u0016\u001c\"!A\u0007\u0011\u00059\tR\"A\b\u000b\u0003A\tQa]2bY\u0006L!AE\b\u0003\r\u0005s\u0017PU3g\u0003\u0019a\u0014N\\5u}Q\t\u0011\"\u0001\u0006xQ&$Xm\u001d9bG\u0016,\u0012a\u0006\t\u0005\u001daQr&\u0003\u0002\u001a\u001f\tIa)\u001e8di&|g.\r\u0019\u00037\u0001\u00022A\u0003\u000f\u001f\u0013\tibA\u0001\u0006QCJ\u001c\u0018N\\4Sk:\u0004\"a\b\u0011\r\u0001\u0011I\u0011EIA\u0001\u0002\u0003\u0015\t\u0001\u000b\u0002\u0004?\u0012\u001a\u0004\"B\u0012%\u0001\bQ\u0012aA2uq\"9Q\u0005BA\u0001\u0002\u00039\u0013\u0001\u0003\u0013b]>tg-\u001e8\u0002\u0017]D\u0017\u000e^3ta\u0006\u001cW\rI\u0006\u0001#\tIC\u0006\u0005\u0002\u000fU%\u00111f\u0004\u0002\b\u001d>$\b.\u001b8h!\tqQ&\u0003\u0002/\u001f\t\u0019\u0011I\\=\u0011\u0007)a\u0002\u0007\u0005\u0002\u000fc%\u0011!g\u0004\u0002\u0005+:LG\u000f
   #9 = Utf8               whitespace
  #10 = Utf8               ()Lscala/Function1;
  #11 = Utf8               ()Lscala/Function1<Lcoursier/core/shaded/fastparse/ParsingRun<*>;Lcoursier/core/shaded/fastparse/ParsingRun<Lscala/runtime/BoxedUnit;>;>;
  #12 = Utf8               coursier/core/shaded/fastparse/SingleLineWhitespace$
  #13 = Class              #12            // coursier/core/shaded/fastparse/SingleLineWhitespace$
  #14 = Utf8               MODULE$
  #15 = Utf8               Lcoursier/core/shaded/fastparse/SingleLineWhitespace$;
  #16 = NameAndType        #14:#15        // MODULE$:Lcoursier/core/shaded/fastparse/SingleLineWhitespace$;
  #17 = Fieldref           #13.#16        // coursier/core/shaded/fastparse/SingleLineWhitespace$.MODULE$:Lcoursier/core/shaded/fastparse/SingleLineWhitespace$;
  #18 = NameAndType        #9:#10         // whitespace:()Lscala/Function1;
  #19 = Methodref          #13.#18        // coursier/core/shaded/fastparse/SingleLineWhitespace$.whitespace:()Lscala/Function1;
  #20 = Utf8               Code
  #21 = Utf8               Signature
  #22 = Utf8               SourceFile
  #23 = Utf8               RuntimeVisibleAnnotations
  #24 = Utf8               ScalaSig
{
  public static scala.Function1<coursier.core.shaded.fastparse.ParsingRun<?>, coursier.core.shaded.fastparse.ParsingRun<scala.runtime.BoxedUnit>> whitespace();
    descriptor: ()Lscala/Function1;
    flags: (0x0009) ACC_PUBLIC, ACC_STATIC
    Code:
      stack=1, locals=0, args_size=0
         0: getstatic     #17                 // Field coursier/core/shaded/fastparse/SingleLineWhitespace$.MODULE$:Lcoursier/core/shaded/fastparse/SingleLineWhitespace$;
         3: invokevirtual #19                 // Method coursier/core/shaded/fastparse/SingleLineWhitespace$.whitespace:()Lscala/Function1;
         6: areturn
    Signature: #11                          // ()Lscala/Function1<Lcoursier/core/shaded/fastparse/ParsingRun<*>;Lcoursier/core/shaded/fastparse/ParsingRun<Lscala/runtime/BoxedUnit;>;>;
}
SourceFile: "Whitespace.scala"
RuntimeVisibleAnnotations:
  0: #6(#7=s#8)
    scala.reflect.ScalaSignature(
      bytes="\u0006\u0005M:Q!\u0002\u0004\t\u0002%1Qa\u0003\u0004\t\u00021AQaE\u0001\u0005\u0002QAq!F\u0001C\u0002\u0013\ra\u0003\u0003\u0004\'\u0003\u0001\u0006IaF\u0001\u0015\'&tw\r\\3MS:,w\u000b[5uKN\u0004\u0018mY3\u000b\u0003\u001d\t\u0011BZ1tiB\f\'o]3\u0004\u0001A\u0011!\"A\u0007\u0002\r\t!2+\u001b8hY\u0016d\u0015N\\3XQ&$Xm\u001d9bG\u0016\u001c\"!A\u0007\u0011\u00059\tR\"A\b\u000b\u0003A\tQa]2bY\u0006L!AE\b\u0003\r\u0005s\u0017PU3g\u0003\u0019a\u0014N\\5u}Q\t\u0011\"\u0001\u0006xQ&$Xm\u001d9bG\u0016,\u0012a\u0006\t\u0005\u001daQr&\u0003\u0002\u001a\u001f\tIa)\u001e8di&|g.\r\u0019\u00037\u0001\u00022A\u0003\u000f\u001f\u0013\tibA\u0001\u0006QCJ\u001c\u0018N\\4Sk:\u0004\"a\b\u0011\r\u0001\u0011I\u0011EIA\u0001\u0002\u0003\u0015\t\u0001\u000b\u0002\u0004?\u0012\u001a\u0004\"B\u0012%\u0001\bQ\u0012aA2uq\"9Q\u0005BA\u0001\u0002\u00039\u0013\u0001\u0003\u0013b]>tg-\u001e8\u0002\u0017]D\u0017\u000e^3ta\u0006\u001cW\rI\u0006\u0001#\tIC\u0006\u0005\u0002\u000fU%\u00111f\u0004\u0002\b\u001d>$\b.\u001b8h!\tqQ&\u0003\u0002/\u001f\t\u0019\u0011I\\=\u0011\u0007)a\u0002\u0007\u0005\u0002\u000fc%\u0011!g\u0004\u0002\u0005+:LG\u000f"
    )
  ScalaSig: length = 0x3 (unknown attribute)
   05 02 00
