Classfile /Users/mw/Projects/slang-braindump/.jar/jar8/assemble/slang-braindump/assemble/content/scala/xml/dtd/AttListDecl.class
  Last modified May 29, 2022; size 6535 bytes
  SHA-256 checksum 0636dbd51203e4caa733df9df59ff63dba9bb2cbf311bc950cc9108af53523fc
  Compiled from "Decl.scala"
public class scala.xml.dtd.AttListDecl extends scala.xml.dtd.MarkupDecl implements scala.Product,java.io.Serializable
  minor version: 0
  major version: 52
  flags: (0x0021) ACC_PUBLIC, ACC_SUPER
  this_class: #2                          // scala/xml/dtd/AttListDecl
  super_class: #4                         // scala/xml/dtd/MarkupDecl
  interfaces: 2, fields: 2, methods: 20, attributes: 4
Constant pool:
    #1 = Utf8               scala/xml/dtd/AttListDecl
    #2 = Class              #1            // scala/xml/dtd/AttListDecl
    #3 = Utf8               scala/xml/dtd/MarkupDecl
    #4 = Class              #3            // scala/xml/dtd/MarkupDecl
    #5 = Utf8               scala/Product
    #6 = Class              #5            // scala/Product
    #7 = Utf8               java/io/Serializable
    #8 = Class              #7            // java/io/Serializable
    #9 = Utf8               Decl.scala
   #10 = Utf8               Lscala/reflect/ScalaSignature;
   #11 = Utf8               bytes
   #12 = Utf8               \u0006\u0005\u0005Md\u0001B\r\u001b\u0001\u0006B\u0001B\u000e\u0001\u0003\u0016\u0004%\ta\u000e\u0005\t\u0001\u0002\u0011\t\u0012)A\u0005q!A\u0011\t\u0001BK\u0002\u0013\u0005!\t\u0003\u0005K\u0001\tE\t\u0015!\u0003D\u0011\u0015Y\u0005\u0001\"\u0001M\u0011\u0015\u0001\u0006\u0001\"\u0011R\u0011\u001d9\u0006!!A\u0005\u0002aCqa\u0017\u0001\u0012\u0002\u0013\u0005A\fC\u0004h\u0001E\u0005I\u0011\u00015\t\u000f)\u0004\u0011\u0011!C!W\"91\u000fAA\u0001\n\u0003!\bb\u0002=\u0001\u0003\u0003%\t!\u001f\u0005\t\u007f\u0002\t\t\u0011\"\u0011\u0002\u0002!I\u0011q\u0002\u0001\u0002\u0002\u0013\u0005\u0011\u0011\u0003\u0005\n\u00037\u0001\u0011\u0011!C!\u0003;A\u0011\"!\t\u0001\u0003\u0003%\t%a\t\t\u0013\u0005\u0015\u0002!!A\u0005B\u0005\u001dr!CA\u00165\u0005\u0005\t\u0012AA\u0017\r!I\"$!A\t\u0002\u0005=\u0002BB&\u0014\t\u0003\t9\u0005C\u0005\u0002JM\t\t\u0011\"\u0012\u0002L!I\u0011QJ\n\u0002\u0002\u0013\u0005\u0015q\n\u0005\n\u0003+\u001a\u0012\u0011!CA\u0003/B\u0011\"!\u001b\u0014\u0003\u0003%I!a\u001b\u0003\u0017\u0005#H\u000fT5ti\u0012+7\r\u001c\u0006\u00037q\t1\u0001\u001a;e\u0015\tib$A\u0002y[2T\u0011aH\u0001\u0006g\u000e\fG.Y\u0002\u0001\'\u0011\u0001!E\n\u0016\u0011\u0005\r\"S\"\u0001\u000e\n\u0005\u0015R\"AC\'be.,\b\u000fR3dYB\u0011q\u0005K\u0007\u0002=%\u0011\u0011F\b\u0002\b!J|G-^2u!\tY3G\u0004\u0002-c9\u0011Q\u0006M\u0007\u0002])\u0011q\u0006I\u0001\u0007yI|w\u000e\u001e \n\u0003}I!A\r\u0010\u0002\u000fA\f7m[1hK&\u0011A\'\u000e\u0002\r\'\u0016\u0014\u0018.\u00197ju\u0006\u0014G.\u001a\u0006\u0003ey\tAA\\1nKV\t\u0001\b\u0005\u0002:{9\u0011!h\u000f\t\u0003[yI!\u0001\u0010\u0010\u0002\rA\u0013X\rZ3g\u0013\tqtH\u0001\u0004TiJLgn\u001a\u0006\u0003yy\tQA\\1nK\u0002\nQ!\u0019;ueN,\u0012a\u0011\t\u0004\t\u0016;eBA\u00142\u0013\t1UG\u0001\u0003MSN$\bCA\u0012I\u0013\tI%D\u0001\u0005BiR\u0014H)Z2m\u0003\u0019\tG\u000f\u001e:tA\u00051A(\u001b8jiz\"2!\u0014(P!\t\u0019\u0003\u0001C\u00037\u000b\u0001\u0007\u0001\bC\u0003B\u000b\u0001\u00071)A\u0006ck&dGm\u0015;sS:<GC\u0001*V!\t!5+\u0003\u0002Uk\ti1\u000b\u001e:j]\u001e\u0014U/\u001b7eKJDQA\u0016\u0004A\u0002I\u000b!a\u001d2\u0002\t\r|\u0007/\u001f\u000b\u0004\u001bfS\u0006b\u0002\u001c\b!\u0003\u0005\r\u0001\u000f\u0005\b\u0003\u001e\u0001\n\u00111\u0001D\u00039\u0019w\u000e]=%I\u00164\u0017-\u001e7uIE*\u0012!\u0018\u0016\u0003qy[\u0013a\u0018\t\u0003A\u0016l\u0011!\u0019\u0006\u0003E\u000e\f\u0011\"\u001e8dQ\u0016\u001c7.\u001a3\u000b\u0005\u0011t\u0012AC1o]>$\u0018\r^5p]&\u0011a-\u0019\u0002\u0012k:\u001c\u0007.Z2lK\u00124\u0016M]5b]\u000e,\u0017AD2paf$C-\u001a4bk2$HEM\u000b\u0002S*\u00121IX\u0001\u000eaJ|G-^2u!J,g-\u001b=\u0016\u00031\u0004\"!\u001c:\u000e\u00039T!a\u001c9\u0002\t1\fgn\u001a\u0006\u0002c\u0006!!.\u0019<b\u0013\tqd.\u0001\u0007qe>$Wo\u0019;Be&$\u00180F\u0001v!\t9c/\u0003\u0002x=\t\u0019\u0011J\u001c;\u0002\u001dA\u0014x\u000eZ;di\u0016cW-\\3oiR\u0011!0 \t\u0003OmL!\u0001 \u0010\u0003\u0007\u0005s\u0017\u0010C\u0004\u007f\u0019\u0005\u0005\t\u0019A;\u0002\u0007a$\u0013\'A\bqe>$Wo\u0019;Ji\u0016\u0014\u0018\r^8s+\t\t\u0019\u0001E\u0003\u0002\u0006\u0005-!0\u0004\u0002\u0002\b)\u0019\u0011\u0011\u0002\u0010\u0002\u0015\r|G\u000e\\3di&|g.\u0003\u0003\u0002\u000e\u0005\u001d!\u0001C%uKJ\fGo\u001c:\u0002\u0011\r\fg.R9vC2$B!a\u0005\u0002\u001aA\u0019q%!\u0006\n\u0007\u0005]aDA\u0004C_>dW-\u00198\t\u000fyt\u0011\u0011!a\u0001u\u0006\u0011\u0002O]8ek\u000e$X\t\\3nK:$h*Y7f)\ra\u0017q\u0004\u0005\b}>\t\t\u00111\u0001v\u0003!A\u0017m\u001d5D_\u0012,G#A;\u0002\r\u0015\fX/\u00197t)\u0011\t\u0019\"!\u000b\t\u000fy\f\u0012\u0011!a\u0001u\u0006Y\u0011\t\u001e;MSN$H)Z2m!\t\u00193cE\u0003\u0014\u0003c\ti\u0004E\u0004\u00024\u0005e\u0002hQ\'\u000e\u0005\u0005U\"bAA\u001c=\u00059!/\u001e8uS6,\u0017\u0002BA\u001e\u0003k\u0011\u0011#\u00112tiJ\f7\r\u001e$v]\u000e$\u0018n\u001c83!\u0011\ty$!\u0012\u000e\u0005\u0005\u0005#bAA\"a\u0006\u0011\u0011n\\\u0005\u0004i\u0005\u0005CCAA\u0017\u0003!!xn\u0015;sS:<G#\u00017\u0002\u000b\u0005\u0004\b\u000f\\=\u0015\u000b5\u000b\t&a\u0015\t\u000bY2\u0002\u0019\u0001\u001d\t\u000b\u00053\u0002\u0019A\"\u0002\u000fUt\u0017\r\u001d9msR!\u0011\u0011LA3!\u00159\u00131LA0\u0013\r\tiF\b\u0002\u0007\u001fB$\u0018n\u001c8\u0011\u000b\u001d\n\t\u0007O\"\n\u0007\u0005\rdD\u0001\u0004UkBdWM\r\u0005\t\u0003O:\u0012\u0011!a\u0001\u001b\u0006\u0019\u0001\u0010\n\u0019\u0002\u0019]\u0014\u0018\u000e^3SKBd\u0017mY3\u0015\u0005\u00055\u0004cA7\u0002p%\u0019\u0011\u0011\u000f8\u0003\r=\u0013\'.Z2u\u0001
   #13 = Utf8               name
   #14 = Utf8               Ljava/lang/String;
   #15 = Utf8               attrs
   #16 = Utf8               Lscala/collection/immutable/List;
   #17 = Utf8               Lscala/collection/immutable/List<Lscala/xml/dtd/AttrDecl;>;
   #18 = Utf8               unapply
   #19 = Utf8               (Lscala/xml/dtd/AttListDecl;)Lscala/Option;
   #20 = Utf8               (Lscala/xml/dtd/AttListDecl;)Lscala/Option<Lscala/Tuple2<Ljava/lang/String;Lscala/collection/immutable/List<Lscala/xml/dtd/AttrDecl;>;>;>;
   #21 = Utf8               x$0
   #22 = Utf8               scala/xml/dtd/AttListDecl$
   #23 = Class              #22           // scala/xml/dtd/AttListDecl$
   #24 = Utf8               MODULE$
   #25 = Utf8               Lscala/xml/dtd/AttListDecl$;
   #26 = NameAndType        #24:#25       // MODULE$:Lscala/xml/dtd/AttListDecl$;
   #27 = Fieldref           #23.#26       // scala/xml/dtd/AttListDecl$.MODULE$:Lscala/xml/dtd/AttListDecl$;
   #28 = NameAndType        #18:#19       // unapply:(Lscala/xml/dtd/AttListDecl;)Lscala/Option;
   #29 = Methodref          #23.#28       // scala/xml/dtd/AttListDecl$.unapply:(Lscala/xml/dtd/AttListDecl;)Lscala/Option;
   #30 = Utf8               Lscala/xml/dtd/AttListDecl;
   #31 = Utf8               apply
   #32 = Utf8               (Ljava/lang/String;Lscala/collection/immutable/List;)Lscala/xml/dtd/AttListDecl;
   #33 = Utf8               (Ljava/lang/String;Lscala/collection/immutable/List<Lscala/xml/dtd/AttrDecl;>;)Lscala/xml/dtd/AttListDecl;
   #34 = NameAndType        #31:#32       // apply:(Ljava/lang/String;Lscala/collection/immutable/List;)Lscala/xml/dtd/AttListDecl;
   #35 = Methodref          #23.#34       // scala/xml/dtd/AttListDecl$.apply:(Ljava/lang/String;Lscala/collection/immutable/List;)Lscala/xml/dtd/AttListDecl;
   #36 = Utf8               tupled
   #37 = Utf8               ()Lscala/Function1;
   #38 = Utf8               ()Lscala/Function1<Lscala/Tuple2<Ljava/lang/String;Lscala/collection/immutable/List<Lscala/xml/dtd/AttrDecl;>;>;Lscala/xml/dtd/AttListDecl;>;
   #39 = NameAndType        #36:#37       // tupled:()Lscala/Function1;
   #40 = Methodref          #23.#39       // scala/xml/dtd/AttListDecl$.tupled:()Lscala/Function1;
   #41 = Utf8               curried
   #42 = Utf8               ()Lscala/Function1<Ljava/lang/String;Lscala/Function1<Lscala/collection/immutable/List<Lscala/xml/dtd/AttrDecl;>;Lscala/xml/dtd/AttListDecl;>;>;
   #43 = NameAndType        #41:#37       // curried:()Lscala/Function1;
   #44 = Methodref          #23.#43       // scala/xml/dtd/AttListDecl$.curried:()Lscala/Function1;
   #45 = Utf8               productElementNames
   #46 = Utf8               ()Lscala/collection/Iterator;
   #47 = Utf8               ()Lscala/collection/Iterator<Ljava/lang/String;>;
   #48 = Utf8               productElementNames$
   #49 = Utf8               (Lscala/Product;)Lscala/collection/Iterator;
   #50 = NameAndType        #48:#49       // productElementNames$:(Lscala/Product;)Lscala/collection/Iterator;
   #51 = InterfaceMethodref #6.#50        // scala/Product.productElementNames$:(Lscala/Product;)Lscala/collection/Iterator;
   #52 = Utf8               this
   #53 = Utf8               ()Ljava/lang/String;
   #54 = NameAndType        #13:#14       // name:Ljava/lang/String;
   #55 = Fieldref           #2.#54        // scala/xml/dtd/AttListDecl.name:Ljava/lang/String;
   #56 = Utf8               ()Lscala/collection/immutable/List;
   #57 = Utf8               ()Lscala/collection/immutable/List<Lscala/xml/dtd/AttrDecl;>;
   #58 = NameAndType        #15:#16       // attrs:Lscala/collection/immutable/List;
   #59 = Fieldref           #2.#58        // scala/xml/dtd/AttListDecl.attrs:Lscala/collection/immutable/List;
   #60 = Utf8               buildString
   #61 = Utf8               (Lscala/collection/mutable/StringBuilder;)Lscala/collection/mutable/StringBuilder;
   #62 = Utf8               sb
   #63 = Utf8               <!ATTLIST
   #64 = String             #63           // <!ATTLIST
   #65 = Utf8               scala/collection/mutable/StringBuilder
   #66 = Class              #65           // scala/collection/mutable/StringBuilder
   #67 = Utf8               append
   #68 = Utf8               (Ljava/lang/String;)Lscala/collection/mutable/StringBuilder;
   #69 = NameAndType        #67:#68       // append:(Ljava/lang/String;)Lscala/collection/mutable/StringBuilder;
   #70 = Methodref          #66.#69       // scala/collection/mutable/StringBuilder.append:(Ljava/lang/String;)Lscala/collection/mutable/StringBuilder;
   #71 = NameAndType        #13:#53       // name:()Ljava/lang/String;
   #72 = Methodref          #2.#71        // scala/xml/dtd/AttListDecl.name:()Ljava/lang/String;
   #73 = Utf8               (C)Lscala/collection/mutable/StringBuilder;
   #74 = NameAndType        #67:#73       // append:(C)Lscala/collection/mutable/StringBuilder;
   #75 = Methodref          #66.#74       // scala/collection/mutable/StringBuilder.append:(C)Lscala/collection/mutable/StringBuilder;
   #76 = NameAndType        #15:#56       // attrs:()Lscala/collection/immutable/List;
   #77 = Methodref          #2.#76        // scala/xml/dtd/AttListDecl.attrs:()Lscala/collection/immutable/List;
   #78 = Utf8
   #79 = String             #78           //
   #80 = Utf8               \n
   #81 = String             #80           // \n
   #82 = Utf8               >
   #83 = String             #82           // >
   #84 = Utf8               scala/collection/immutable/List
   #85 = Class              #84           // scala/collection/immutable/List
   #86 = Utf8               mkString
   #87 = Utf8               (Ljava/lang/String;Ljava/lang/String;Ljava/lang/String;)Ljava/lang/String;
   #88 = NameAndType        #86:#87       // mkString:(Ljava/lang/String;Ljava/lang/String;Ljava/lang/String;)Ljava/lang/String;
   #89 = Methodref          #85.#88       // scala/collection/immutable/List.mkString:(Ljava/lang/String;Ljava/lang/String;Ljava/lang/String;)Ljava/lang/String;
   #90 = Utf8               Lscala/collection/mutable/StringBuilder;
   #91 = Utf8               copy
   #92 = Utf8               <init>
   #93 = Utf8               (Ljava/lang/String;Lscala/collection/immutable/List;)V
   #94 = NameAndType        #92:#93       // "<init>":(Ljava/lang/String;Lscala/collection/immutable/List;)V
   #95 = Methodref          #2.#94        // scala/xml/dtd/AttListDecl."<init>":(Ljava/lang/String;Lscala/collection/immutable/List;)V
   #96 = Utf8               copy$default$1
   #97 = Utf8               copy$default$2
   #98 = Utf8               productPrefix
   #99 = Utf8               AttListDecl
  #100 = String             #99           // AttListDecl
  #101 = Utf8               productArity
  #102 = Utf8               ()I
  #103 = Utf8               productElement
  #104 = Utf8               (I)Ljava/lang/Object;
  #105 = Utf8               x$1
  #106 = Utf8               scala/runtime/Statics
  #107 = Class              #106          // scala/runtime/Statics
  #108 = Utf8               ioobe
  #109 = NameAndType        #108:#104     // ioobe:(I)Ljava/lang/Object;
  #110 = Methodref          #107.#109     // scala/runtime/Statics.ioobe:(I)Ljava/lang/Object;
  #111 = Utf8               I
  #112 = Utf8               java/lang/Object
  #113 = Class              #112          // java/lang/Object
  #114 = Utf8               productIterator
  #115 = Utf8               ()Lscala/collection/Iterator<Ljava/lang/Object;>;
  #116 = Utf8               scala/runtime/ScalaRunTime$
  #117 = Class              #116          // scala/runtime/ScalaRunTime$
  #118 = Utf8               Lscala/runtime/ScalaRunTime$;
  #119 = NameAndType        #24:#118      // MODULE$:Lscala/runtime/ScalaRunTime$;
  #120 = Fieldref           #117.#119     // scala/runtime/ScalaRunTime$.MODULE$:Lscala/runtime/ScalaRunTime$;
  #121 = Utf8               typedProductIterator
  #122 = NameAndType        #121:#49      // typedProductIterator:(Lscala/Product;)Lscala/collection/Iterator;
  #123 = Methodref          #117.#122     // scala/runtime/ScalaRunTime$.typedProductIterator:(Lscala/Product;)Lscala/collection/Iterator;
  #124 = Utf8               canEqual
  #125 = Utf8               (Ljava/lang/Object;)Z
  #126 = Utf8               Ljava/lang/Object;
  #127 = Utf8               productElementName
  #128 = Utf8               (I)Ljava/lang/String;
  #129 = String             #13           // name
  #130 = String             #15           // attrs
  #131 = Utf8               java/lang/String
  #132 = Class              #131          // java/lang/String
  #133 = Utf8               hashCode
  #134 = Utf8               _hashCode
  #135 = Utf8               (Lscala/Product;)I
  #136 = NameAndType        #134:#135     // _hashCode:(Lscala/Product;)I
  #137 = Methodref          #117.#136     // scala/runtime/ScalaRunTime$._hashCode:(Lscala/Product;)I
  #138 = Utf8               equals
  #139 = NameAndType        #138:#125     // equals:(Ljava/lang/Object;)Z
  #140 = Methodref          #113.#139     // java/lang/Object.equals:(Ljava/lang/Object;)Z
  #141 = NameAndType        #124:#125     // canEqual:(Ljava/lang/Object;)Z
  #142 = Methodref          #2.#141       // scala/xml/dtd/AttListDecl.canEqual:(Ljava/lang/Object;)Z
  #143 = Utf8               (Ljava/lang/String;Lscala/collection/immutable/List<Lscala/xml/dtd/AttrDecl;>;)V
  #144 = Utf8               ()V
  #145 = NameAndType        #92:#144      // "<init>":()V
  #146 = Methodref          #4.#145       // scala/xml/dtd/MarkupDecl."<init>":()V
  #147 = Utf8               $init$
  #148 = Utf8               (Lscala/Product;)V
  #149 = NameAndType        #147:#148     // $init$:(Lscala/Product;)V
  #150 = InterfaceMethodref #6.#149       // scala/Product.$init$:(Lscala/Product;)V
  #151 = Utf8               Signature
  #152 = Utf8               Code
  #153 = Utf8               LocalVariableTable
  #154 = Utf8               MethodParameters
  #155 = Utf8               LineNumberTable
  #156 = Utf8               StackMapTable
  #157 = Utf8               SourceFile
  #158 = Utf8               RuntimeVisibleAnnotations
  #159 = Utf8               ScalaInlineInfo
  #160 = Utf8               ScalaSig
{
  private final java.lang.String name;
    descriptor: Ljava/lang/String;
    flags: (0x0012) ACC_PRIVATE, ACC_FINAL

  private final scala.collection.immutable.List<scala.xml.dtd.AttrDecl> attrs;
    descriptor: Lscala/collection/immutable/List;
    flags: (0x0012) ACC_PRIVATE, ACC_FINAL
    Signature: #17                          // Lscala/collection/immutable/List<Lscala/xml/dtd/AttrDecl;>;

  public static scala.Option<scala.Tuple2<java.lang.String, scala.collection.immutable.List<scala.xml.dtd.AttrDecl>>> unapply(scala.xml.dtd.AttListDecl);
    descriptor: (Lscala/xml/dtd/AttListDecl;)Lscala/Option;
    flags: (0x0009) ACC_PUBLIC, ACC_STATIC
    Code:
      stack=2, locals=1, args_size=1
         0: getstatic     #27                 // Field scala/xml/dtd/AttListDecl$.MODULE$:Lscala/xml/dtd/AttListDecl$;
         3: aload_0
         4: invokevirtual #29                 // Method scala/xml/dtd/AttListDecl$.unapply:(Lscala/xml/dtd/AttListDecl;)Lscala/Option;
         7: areturn
      LocalVariableTable:
        Start  Length  Slot  Name   Signature
            0       8     0   x$0   Lscala/xml/dtd/AttListDecl;
    Signature: #20                          // (Lscala/xml/dtd/AttListDecl;)Lscala/Option<Lscala/Tuple2<Ljava/lang/String;Lscala/collection/immutable/List<Lscala/xml/dtd/AttrDecl;>;>;>;
    MethodParameters:
      Name                           Flags
      x$0                            final

  public static scala.xml.dtd.AttListDecl apply(java.lang.String, scala.collection.immutable.List<scala.xml.dtd.AttrDecl>);
    descriptor: (Ljava/lang/String;Lscala/collection/immutable/List;)Lscala/xml/dtd/AttListDecl;
    flags: (0x0009) ACC_PUBLIC, ACC_STATIC
    Code:
      stack=3, locals=2, args_size=2
         0: getstatic     #27                 // Field scala/xml/dtd/AttListDecl$.MODULE$:Lscala/xml/dtd/AttListDecl$;
         3: aload_0
         4: aload_1
         5: invokevirtual #35                 // Method scala/xml/dtd/AttListDecl$.apply:(Ljava/lang/String;Lscala/collection/immutable/List;)Lscala/xml/dtd/AttListDecl;
         8: areturn
      LocalVariableTable:
        Start  Length  Slot  Name   Signature
            0       9     0  name   Ljava/lang/String;
            0       9     1 attrs   Lscala/collection/immutable/List;
    Signature: #33                          // (Ljava/lang/String;Lscala/collection/immutable/List<Lscala/xml/dtd/AttrDecl;>;)Lscala/xml/dtd/AttListDecl;
    MethodParameters:
      Name                           Flags
      name                           final
      attrs                          final

  public static scala.Function1<scala.Tuple2<java.lang.String, scala.collection.immutable.List<scala.xml.dtd.AttrDecl>>, scala.xml.dtd.AttListDecl> tupled();
    descriptor: ()Lscala/Function1;
    flags: (0x0009) ACC_PUBLIC, ACC_STATIC
    Code:
      stack=1, locals=0, args_size=0
         0: getstatic     #27                 // Field scala/xml/dtd/AttListDecl$.MODULE$:Lscala/xml/dtd/AttListDecl$;
         3: invokevirtual #40                 // Method scala/xml/dtd/AttListDecl$.tupled:()Lscala/Function1;
         6: areturn
    Signature: #38                          // ()Lscala/Function1<Lscala/Tuple2<Ljava/lang/String;Lscala/collection/immutable/List<Lscala/xml/dtd/AttrDecl;>;>;Lscala/xml/dtd/AttListDecl;>;

  public static scala.Function1<java.lang.String, scala.Function1<scala.collection.immutable.List<scala.xml.dtd.AttrDecl>, scala.xml.dtd.AttListDecl>> curried();
    descriptor: ()Lscala/Function1;
    flags: (0x0009) ACC_PUBLIC, ACC_STATIC
    Code:
      stack=1, locals=0, args_size=0
         0: getstatic     #27                 // Field scala/xml/dtd/AttListDecl$.MODULE$:Lscala/xml/dtd/AttListDecl$;
         3: invokevirtual #44                 // Method scala/xml/dtd/AttListDecl$.curried:()Lscala/Function1;
         6: areturn
    Signature: #42                          // ()Lscala/Function1<Ljava/lang/String;Lscala/Function1<Lscala/collection/immutable/List<Lscala/xml/dtd/AttrDecl;>;Lscala/xml/dtd/AttListDecl;>;>;

  public scala.collection.Iterator<java.lang.String> productElementNames();
    descriptor: ()Lscala/collection/Iterator;
    flags: (0x0001) ACC_PUBLIC
    Code:
      stack=1, locals=1, args_size=1
         0: aload_0
         1: invokestatic  #51                 // InterfaceMethod scala/Product.productElementNames$:(Lscala/Product;)Lscala/collection/Iterator;
         4: areturn
      LineNumberTable:
        line 50: 0
      LocalVariableTable:
        Start  Length  Slot  Name   Signature
            0       5     0  this   Lscala/xml/dtd/AttListDecl;
    Signature: #47                          // ()Lscala/collection/Iterator<Ljava/lang/String;>;

  public java.lang.String name();
    descriptor: ()Ljava/lang/String;
    flags: (0x0001) ACC_PUBLIC
    Code:
      stack=1, locals=1, args_size=1
         0: aload_0
         1: getfield      #55                 // Field name:Ljava/lang/String;
         4: areturn
      LineNumberTable:
        line 50: 0
      LocalVariableTable:
        Start  Length  Slot  Name   Signature
            0       5     0  this   Lscala/xml/dtd/AttListDecl;

  public scala.collection.immutable.List<scala.xml.dtd.AttrDecl> attrs();
    descriptor: ()Lscala/collection/immutable/List;
    flags: (0x0001) ACC_PUBLIC
    Code:
      stack=1, locals=1, args_size=1
         0: aload_0
         1: getfield      #59                 // Field attrs:Lscala/collection/immutable/List;
         4: areturn
      LineNumberTable:
        line 50: 0
      LocalVariableTable:
        Start  Length  Slot  Name   Signature
            0       5     0  this   Lscala/xml/dtd/AttListDecl;
    Signature: #57                          // ()Lscala/collection/immutable/List<Lscala/xml/dtd/AttrDecl;>;

  public scala.collection.mutable.StringBuilder buildString(scala.collection.mutable.StringBuilder);
    descriptor: (Lscala/collection/mutable/StringBuilder;)Lscala/collection/mutable/StringBuilder;
    flags: (0x0001) ACC_PUBLIC
    Code:
      stack=5, locals=2, args_size=2
         0: aload_1
         1: ldc           #64                 // String <!ATTLIST
         3: invokevirtual #70                 // Method scala/collection/mutable/StringBuilder.append:(Ljava/lang/String;)Lscala/collection/mutable/StringBuilder;
         6: aload_0
         7: invokevirtual #72                 // Method name:()Ljava/lang/String;
        10: invokevirtual #70                 // Method scala/collection/mutable/StringBuilder.append:(Ljava/lang/String;)Lscala/collection/mutable/StringBuilder;
        13: bipush        10
        15: invokevirtual #75                 // Method scala/collection/mutable/StringBuilder.append:(C)Lscala/collection/mutable/StringBuilder;
        18: aload_0
        19: invokevirtual #77                 // Method attrs:()Lscala/collection/immutable/List;
        22: ldc           #79                 // String
        24: ldc           #81                 // String \n
        26: ldc           #83                 // String >
        28: invokevirtual #89                 // Method scala/collection/immutable/List.mkString:(Ljava/lang/String;Ljava/lang/String;Ljava/lang/String;)Ljava/lang/String;
        31: invokevirtual #70                 // Method scala/collection/mutable/StringBuilder.append:(Ljava/lang/String;)Lscala/collection/mutable/StringBuilder;
        34: areturn
      LineNumberTable:
        line 53: 0
      LocalVariableTable:
        Start  Length  Slot  Name   Signature
            0      35     0  this   Lscala/xml/dtd/AttListDecl;
            0      35     1    sb   Lscala/collection/mutable/StringBuilder;
    MethodParameters:
      Name                           Flags
      sb                             final

  public scala.xml.dtd.AttListDecl copy(java.lang.String, scala.collection.immutable.List<scala.xml.dtd.AttrDecl>);
    descriptor: (Ljava/lang/String;Lscala/collection/immutable/List;)Lscala/xml/dtd/AttListDecl;
    flags: (0x0001) ACC_PUBLIC
    Code:
      stack=4, locals=3, args_size=3
         0: new           #2                  // class scala/xml/dtd/AttListDecl
         3: dup
         4: aload_1
         5: aload_2
         6: invokespecial #95                 // Method "<init>":(Ljava/lang/String;Lscala/collection/immutable/List;)V
         9: areturn
      LineNumberTable:
        line 50: 0
      LocalVariableTable:
        Start  Length  Slot  Name   Signature
            0      10     0  this   Lscala/xml/dtd/AttListDecl;
            0      10     1  name   Ljava/lang/String;
            0      10     2 attrs   Lscala/collection/immutable/List;
    Signature: #33                          // (Ljava/lang/String;Lscala/collection/immutable/List<Lscala/xml/dtd/AttrDecl;>;)Lscala/xml/dtd/AttListDecl;
    MethodParameters:
      Name                           Flags
      name                           final
      attrs                          final

  public java.lang.String copy$default$1();
    descriptor: ()Ljava/lang/String;
    flags: (0x0001) ACC_PUBLIC
    Code:
      stack=1, locals=1, args_size=1
         0: aload_0
         1: invokevirtual #72                 // Method name:()Ljava/lang/String;
         4: areturn
      LineNumberTable:
        line 50: 0
      LocalVariableTable:
        Start  Length  Slot  Name   Signature
            0       5     0  this   Lscala/xml/dtd/AttListDecl;

  public scala.collection.immutable.List<scala.xml.dtd.AttrDecl> copy$default$2();
    descriptor: ()Lscala/collection/immutable/List;
    flags: (0x0001) ACC_PUBLIC
    Code:
      stack=1, locals=1, args_size=1
         0: aload_0
         1: invokevirtual #77                 // Method attrs:()Lscala/collection/immutable/List;
         4: areturn
      LineNumberTable:
        line 50: 0
      LocalVariableTable:
        Start  Length  Slot  Name   Signature
            0       5     0  this   Lscala/xml/dtd/AttListDecl;
    Signature: #57                          // ()Lscala/collection/immutable/List<Lscala/xml/dtd/AttrDecl;>;

  public java.lang.String productPrefix();
    descriptor: ()Ljava/lang/String;
    flags: (0x0001) ACC_PUBLIC
    Code:
      stack=1, locals=1, args_size=1
         0: ldc           #100                // String AttListDecl
         2: areturn
      LineNumberTable:
        line 50: 0
      LocalVariableTable:
        Start  Length  Slot  Name   Signature
            0       3     0  this   Lscala/xml/dtd/AttListDecl;

  public int productArity();
    descriptor: ()I
    flags: (0x0001) ACC_PUBLIC
    Code:
      stack=1, locals=1, args_size=1
         0: iconst_2
         1: ireturn
      LineNumberTable:
        line 50: 0
      LocalVariableTable:
        Start  Length  Slot  Name   Signature
            0       2     0  this   Lscala/xml/dtd/AttListDecl;

  public java.lang.Object productElement(int);
    descriptor: (I)Ljava/lang/Object;
    flags: (0x0001) ACC_PUBLIC
    Code:
      stack=1, locals=3, args_size=2
         0: iload_1
         1: istore_2
         2: iload_2
         3: tableswitch   { // 0 to 1
                       0: 24
                       1: 31
                 default: 38
            }
        24: aload_0
        25: invokevirtual #72                 // Method name:()Ljava/lang/String;
        28: goto          45
        31: aload_0
        32: invokevirtual #77                 // Method attrs:()Lscala/collection/immutable/List;
        35: goto          45
        38: iload_1
        39: invokestatic  #110                // Method scala/runtime/Statics.ioobe:(I)Ljava/lang/Object;
        42: goto          45
        45: areturn
      StackMapTable: number_of_entries = 4
        frame_type = 252 /* append */
          offset_delta = 24
          locals = [ int ]
        frame_type = 6 /* same */
        frame_type = 6 /* same */
        frame_type = 70 /* same_locals_1_stack_item */
          stack = [ class java/lang/Object ]
      LineNumberTable:
        line 50: 0
      LocalVariableTable:
        Start  Length  Slot  Name   Signature
            0      46     0  this   Lscala/xml/dtd/AttListDecl;
            0      46     1   x$1   I
    MethodParameters:
      Name                           Flags
      x$1                            final

  public scala.collection.Iterator<java.lang.Object> productIterator();
    descriptor: ()Lscala/collection/Iterator;
    flags: (0x0001) ACC_PUBLIC
    Code:
      stack=2, locals=1, args_size=1
         0: getstatic     #120                // Field scala/runtime/ScalaRunTime$.MODULE$:Lscala/runtime/ScalaRunTime$;
         3: aload_0
         4: invokevirtual #123                // Method scala/runtime/ScalaRunTime$.typedProductIterator:(Lscala/Product;)Lscala/collection/Iterator;
         7: areturn
      LineNumberTable:
        line 50: 0
      LocalVariableTable:
        Start  Length  Slot  Name   Signature
            0       8     0  this   Lscala/xml/dtd/AttListDecl;
    Signature: #115                         // ()Lscala/collection/Iterator<Ljava/lang/Object;>;

  public boolean canEqual(java.lang.Object);
    descriptor: (Ljava/lang/Object;)Z
    flags: (0x0001) ACC_PUBLIC
    Code:
      stack=1, locals=2, args_size=2
         0: aload_1
         1: instanceof    #2                  // class scala/xml/dtd/AttListDecl
         4: ireturn
      LineNumberTable:
        line 50: 0
      LocalVariableTable:
        Start  Length  Slot  Name   Signature
            0       5     0  this   Lscala/xml/dtd/AttListDecl;
            0       5     1   x$1   Ljava/lang/Object;
    MethodParameters:
      Name                           Flags
      x$1                            final

  public java.lang.String productElementName(int);
    descriptor: (I)Ljava/lang/String;
    flags: (0x0001) ACC_PUBLIC
    Code:
      stack=1, locals=3, args_size=2
         0: iload_1
         1: istore_2
         2: iload_2
         3: tableswitch   { // 0 to 1
                       0: 24
                       1: 29
                 default: 34
            }
        24: ldc           #129                // String name
        26: goto          44
        29: ldc           #130                // String attrs
        31: goto          44
        34: iload_1
        35: invokestatic  #110                // Method scala/runtime/Statics.ioobe:(I)Ljava/lang/Object;
        38: checkcast     #132                // class java/lang/String
        41: goto          44
        44: areturn
      StackMapTable: number_of_entries = 4
        frame_type = 252 /* append */
          offset_delta = 24
          locals = [ int ]
        frame_type = 4 /* same */
        frame_type = 4 /* same */
        frame_type = 73 /* same_locals_1_stack_item */
          stack = [ class java/lang/String ]
      LineNumberTable:
        line 50: 0
      LocalVariableTable:
        Start  Length  Slot  Name   Signature
            0      45     0  this   Lscala/xml/dtd/AttListDecl;
            0      45     1   x$1   I
    MethodParameters:
      Name                           Flags
      x$1                            final

  public int hashCode();
    descriptor: ()I
    flags: (0x0001) ACC_PUBLIC
    Code:
      stack=2, locals=1, args_size=1
         0: getstatic     #120                // Field scala/runtime/ScalaRunTime$.MODULE$:Lscala/runtime/ScalaRunTime$;
         3: aload_0
         4: invokevirtual #137                // Method scala/runtime/ScalaRunTime$._hashCode:(Lscala/Product;)I
         7: ireturn
      LineNumberTable:
        line 50: 0
      LocalVariableTable:
        Start  Length  Slot  Name   Signature
            0       8     0  this   Lscala/xml/dtd/AttListDecl;

  public boolean equals(java.lang.Object);
    descriptor: (Ljava/lang/Object;)Z
    flags: (0x0001) ACC_PUBLIC
    Code:
      stack=2, locals=7, args_size=2
         0: aload_0
         1: aload_1
         2: if_acmpeq     118
         5: aload_1
         6: astore_3
         7: aload_3
         8: instanceof    #2                  // class scala/xml/dtd/AttListDecl
        11: ifeq          19
        14: iconst_1
        15: istore_2
        16: goto          27
        19: goto          22
        22: iconst_0
        23: istore_2
        24: goto          27
        27: iload_2
        28: ifeq          122
        31: aload_1
        32: checkcast     #2                  // class scala/xml/dtd/AttListDecl
        35: astore        4
        37: aload_0
        38: invokevirtual #72                 // Method name:()Ljava/lang/String;
        41: aload         4
        43: invokevirtual #72                 // Method name:()Ljava/lang/String;
        46: astore        5
        48: dup
        49: ifnonnull     61
        52: pop
        53: aload         5
        55: ifnull        69
        58: goto          114
        61: aload         5
        63: invokevirtual #140                // Method java/lang/Object.equals:(Ljava/lang/Object;)Z
        66: ifeq          114
        69: aload_0
        70: invokevirtual #77                 // Method attrs:()Lscala/collection/immutable/List;
        73: aload         4
        75: invokevirtual #77                 // Method attrs:()Lscala/collection/immutable/List;
        78: astore        6
        80: dup
        81: ifnonnull     93
        84: pop
        85: aload         6
        87: ifnull        101
        90: goto          114
        93: aload         6
        95: invokevirtual #140                // Method java/lang/Object.equals:(Ljava/lang/Object;)Z
        98: ifeq          114
       101: aload         4
       103: aload_0
       104: invokevirtual #142                // Method canEqual:(Ljava/lang/Object;)Z
       107: ifeq          114
       110: iconst_1
       111: goto          115
       114: iconst_0
       115: ifeq          122
       118: iconst_1
       119: goto          123
       122: iconst_0
       123: ireturn
      StackMapTable: number_of_entries = 12
        frame_type = 253 /* append */
          offset_delta = 19
          locals = [ top, class java/lang/Object ]
        frame_type = 2 /* same */
        frame_type = 255 /* full_frame */
          offset_delta = 4
          locals = [ class scala/xml/dtd/AttListDecl, class java/lang/Object, int, class java/lang/Object ]
          stack = []
        frame_type = 255 /* full_frame */
          offset_delta = 33
          locals = [ class scala/xml/dtd/AttListDecl, class java/lang/Object, int, class java/lang/Object, class scala/xml/dtd/AttListDecl, class java/lang/String ]
          stack = [ class java/lang/String ]
        frame_type = 7 /* same */
        frame_type = 255 /* full_frame */
          offset_delta = 23
          locals = [ class scala/xml/dtd/AttListDecl, class java/lang/Object, int, class java/lang/Object, class scala/xml/dtd/AttListDecl, class java/lang/String, class scala/collection/immutable/List ]
          stack = [ class scala/collection/immutable/List ]
        frame_type = 7 /* same */
        frame_type = 250 /* chop */
          offset_delta = 12
        frame_type = 64 /* same_locals_1_stack_item */
          stack = [ int ]
        frame_type = 255 /* full_frame */
          offset_delta = 2
          locals = [ class scala/xml/dtd/AttListDecl, class java/lang/Object ]
          stack = []
        frame_type = 253 /* append */
          offset_delta = 3
          locals = [ int, class java/lang/Object ]
        frame_type = 255 /* full_frame */
          offset_delta = 0
          locals = [ class scala/xml/dtd/AttListDecl, class java/lang/Object ]
          stack = [ int ]
      LineNumberTable:
        line 50: 0
      LocalVariableTable:
        Start  Length  Slot  Name   Signature
            0     124     0  this   Lscala/xml/dtd/AttListDecl;
            0     124     1   x$1   Ljava/lang/Object;
    MethodParameters:
      Name                           Flags
      x$1                            final

  public scala.xml.dtd.AttListDecl(java.lang.String, scala.collection.immutable.List<scala.xml.dtd.AttrDecl>);
    descriptor: (Ljava/lang/String;Lscala/collection/immutable/List;)V
    flags: (0x0001) ACC_PUBLIC
    Code:
      stack=2, locals=3, args_size=3
         0: aload_0
         1: aload_1
         2: putfield      #55                 // Field name:Ljava/lang/String;
         5: aload_0
         6: aload_2
         7: putfield      #59                 // Field attrs:Lscala/collection/immutable/List;
        10: aload_0
        11: invokespecial #146                // Method scala/xml/dtd/MarkupDecl."<init>":()V
        14: aload_0
        15: invokestatic  #150                // InterfaceMethod scala/Product.$init$:(Lscala/Product;)V
        18: return
      LineNumberTable:
        line 50: 0
        line 51: 10
        line 50: 18
      LocalVariableTable:
        Start  Length  Slot  Name   Signature
            0      19     0  this   Lscala/xml/dtd/AttListDecl;
            0      19     1  name   Ljava/lang/String;
            0      19     2 attrs   Lscala/collection/immutable/List;
    Signature: #143                         // (Ljava/lang/String;Lscala/collection/immutable/List<Lscala/xml/dtd/AttrDecl;>;)V
    MethodParameters:
      Name                           Flags
      name                           final
      attrs                          final
}
SourceFile: "Decl.scala"
RuntimeVisibleAnnotations:
  0: #10(#11=s#12)
    scala.reflect.ScalaSignature(
      bytes="\u0006\u0005\u0005Md\u0001B\r\u001b\u0001\u0006B\u0001B\u000e\u0001\u0003\u0016\u0004%\ta\u000e\u0005\t\u0001\u0002\u0011\t\u0012)A\u0005q!A\u0011\t\u0001BK\u0002\u0013\u0005!\t\u0003\u0005K\u0001\tE\t\u0015!\u0003D\u0011\u0015Y\u0005\u0001\"\u0001M\u0011\u0015\u0001\u0006\u0001\"\u0011R\u0011\u001d9\u0006!!A\u0005\u0002aCqa\u0017\u0001\u0012\u0002\u0013\u0005A\fC\u0004h\u0001E\u0005I\u0011\u00015\t\u000f)\u0004\u0011\u0011!C!W\"91\u000fAA\u0001\n\u0003!\bb\u0002=\u0001\u0003\u0003%\t!\u001f\u0005\t\u007f\u0002\t\t\u0011\"\u0011\u0002\u0002!I\u0011q\u0002\u0001\u0002\u0002\u0013\u0005\u0011\u0011\u0003\u0005\n\u00037\u0001\u0011\u0011!C!\u0003;A\u0011\"!\t\u0001\u0003\u0003%\t%a\t\t\u0013\u0005\u0015\u0002!!A\u0005B\u0005\u001dr!CA\u00165\u0005\u0005\t\u0012AA\u0017\r!I\"$!A\t\u0002\u0005=\u0002BB&\u0014\t\u0003\t9\u0005C\u0005\u0002JM\t\t\u0011\"\u0012\u0002L!I\u0011QJ\n\u0002\u0002\u0013\u0005\u0015q\n\u0005\n\u0003+\u001a\u0012\u0011!CA\u0003/B\u0011\"!\u001b\u0014\u0003\u0003%I!a\u001b\u0003\u0017\u0005#H\u000fT5ti\u0012+7\r\u001c\u0006\u00037q\t1\u0001\u001a;e\u0015\tib$A\u0002y[2T\u0011aH\u0001\u0006g\u000e\fG.Y\u0002\u0001\'\u0011\u0001!E\n\u0016\u0011\u0005\r\"S\"\u0001\u000e\n\u0005\u0015R\"AC\'be.,\b\u000fR3dYB\u0011q\u0005K\u0007\u0002=%\u0011\u0011F\b\u0002\b!J|G-^2u!\tY3G\u0004\u0002-c9\u0011Q\u0006M\u0007\u0002])\u0011q\u0006I\u0001\u0007yI|w\u000e\u001e \n\u0003}I!A\r\u0010\u0002\u000fA\f7m[1hK&\u0011A\'\u000e\u0002\r\'\u0016\u0014\u0018.\u00197ju\u0006\u0014G.\u001a\u0006\u0003ey\tAA\\1nKV\t\u0001\b\u0005\u0002:{9\u0011!h\u000f\t\u0003[yI!\u0001\u0010\u0010\u0002\rA\u0013X\rZ3g\u0013\tqtH\u0001\u0004TiJLgn\u001a\u0006\u0003yy\tQA\\1nK\u0002\nQ!\u0019;ueN,\u0012a\u0011\t\u0004\t\u0016;eBA\u00142\u0013\t1UG\u0001\u0003MSN$\bCA\u0012I\u0013\tI%D\u0001\u0005BiR\u0014H)Z2m\u0003\u0019\tG\u000f\u001e:tA\u00051A(\u001b8jiz\"2!\u0014(P!\t\u0019\u0003\u0001C\u00037\u000b\u0001\u0007\u0001\bC\u0003B\u000b\u0001\u00071)A\u0006ck&dGm\u0015;sS:<GC\u0001*V!\t!5+\u0003\u0002Uk\ti1\u000b\u001e:j]\u001e\u0014U/\u001b7eKJDQA\u0016\u0004A\u0002I\u000b!a\u001d2\u0002\t\r|\u0007/\u001f\u000b\u0004\u001bfS\u0006b\u0002\u001c\b!\u0003\u0005\r\u0001\u000f\u0005\b\u0003\u001e\u0001\n\u00111\u0001D\u00039\u0019w\u000e]=%I\u00164\u0017-\u001e7uIE*\u0012!\u0018\u0016\u0003qy[\u0013a\u0018\t\u0003A\u0016l\u0011!\u0019\u0006\u0003E\u000e\f\u0011\"\u001e8dQ\u0016\u001c7.\u001a3\u000b\u0005\u0011t\u0012AC1o]>$\u0018\r^5p]&\u0011a-\u0019\u0002\u0012k:\u001c\u0007.Z2lK\u00124\u0016M]5b]\u000e,\u0017AD2paf$C-\u001a4bk2$HEM\u000b\u0002S*\u00121IX\u0001\u000eaJ|G-^2u!J,g-\u001b=\u0016\u00031\u0004\"!\u001c:\u000e\u00039T!a\u001c9\u0002\t1\fgn\u001a\u0006\u0002c\u0006!!.\u0019<b\u0013\tqd.\u0001\u0007qe>$Wo\u0019;Be&$\u00180F\u0001v!\t9c/\u0003\u0002x=\t\u0019\u0011J\u001c;\u0002\u001dA\u0014x\u000eZ;di\u0016cW-\\3oiR\u0011!0 \t\u0003OmL!\u0001 \u0010\u0003\u0007\u0005s\u0017\u0010C\u0004\u007f\u0019\u0005\u0005\t\u0019A;\u0002\u0007a$\u0013\'A\bqe>$Wo\u0019;Ji\u0016\u0014\u0018\r^8s+\t\t\u0019\u0001E\u0003\u0002\u0006\u0005-!0\u0004\u0002\u0002\b)\u0019\u0011\u0011\u0002\u0010\u0002\u0015\r|G\u000e\\3di&|g.\u0003\u0003\u0002\u000e\u0005\u001d!\u0001C%uKJ\fGo\u001c:\u0002\u0011\r\fg.R9vC2$B!a\u0005\u0002\u001aA\u0019q%!\u0006\n\u0007\u0005]aDA\u0004C_>dW-\u00198\t\u000fyt\u0011\u0011!a\u0001u\u0006\u0011\u0002O]8ek\u000e$X\t\\3nK:$h*Y7f)\ra\u0017q\u0004\u0005\b}>\t\t\u00111\u0001v\u0003!A\u0017m\u001d5D_\u0012,G#A;\u0002\r\u0015\fX/\u00197t)\u0011\t\u0019\"!\u000b\t\u000fy\f\u0012\u0011!a\u0001u\u0006Y\u0011\t\u001e;MSN$H)Z2m!\t\u00193cE\u0003\u0014\u0003c\ti\u0004E\u0004\u00024\u0005e\u0002hQ\'\u000e\u0005\u0005U\"bAA\u001c=\u00059!/\u001e8uS6,\u0017\u0002BA\u001e\u0003k\u0011\u0011#\u00112tiJ\f7\r\u001e$v]\u000e$\u0018n\u001c83!\u0011\ty$!\u0012\u000e\u0005\u0005\u0005#bAA\"a\u0006\u0011\u0011n\\\u0005\u0004i\u0005\u0005CCAA\u0017\u0003!!xn\u0015;sS:<G#\u00017\u0002\u000b\u0005\u0004\b\u000f\\=\u0015\u000b5\u000b\t&a\u0015\t\u000bY2\u0002\u0019\u0001\u001d\t\u000b\u00053\u0002\u0019A\"\u0002\u000fUt\u0017\r\u001d9msR!\u0011\u0011LA3!\u00159\u00131LA0\u0013\r\tiF\b\u0002\u0007\u001fB$\u0018n\u001c8\u0011\u000b\u001d\n\t\u0007O\"\n\u0007\u0005\rdD\u0001\u0004UkBdWM\r\u0005\t\u0003O:\u0012\u0011!a\u0001\u001b\u0006\u0019\u0001\u0010\n\u0019\u0002\u0019]\u0014\u0018\u000e^3SKBd\u0017mY3\u0015\u0005\u00055\u0004cA7\u0002p%\u0019\u0011\u0011\u000f8\u0003\r=\u0013\'.Z2u\u0001"
    )
  ScalaInlineInfo: length = 0x54 (unknown attribute)
   01 00 00 10 00 5C 00 5D 00 00 0F 00 38 00 00 3C
   00 3D 00 00 7C 00 7D 00 00 5B 00 20 00 00 60 00
   35 00 00 61 00 38 00 00 8A 00 7D 00 00 85 00 66
   00 00 0D 00 35 00 00 65 00 66 00 00 67 00 68 00
   00 7F 00 80 00 00 2D 00 2E 00 00 72 00 2E 00 00
   62 00 35 00
  ScalaSig: length = 0x3 (unknown attribute)
   05 02 00
