Classfile /Users/mw/Projects/slang-braindump/.jar/jar8/assemble/slang-braindump/assemble/content/scala/xml/dtd/DocType$.class
  Last modified May 29, 2022; size 2246 bytes
  SHA-256 checksum 0579ff1e3b0cd1e3161455dd34095fb9d905d19191edfc6ab5d9fd993c739e21
  Compiled from "DocType.scala"
public final class scala.xml.dtd.DocType$ implements java.io.Serializable
  minor version: 0
  major version: 52
  flags: (0x0031) ACC_PUBLIC, ACC_FINAL, ACC_SUPER
  this_class: #2                          // scala/xml/dtd/DocType$
  super_class: #4                         // java/lang/Object
  interfaces: 1, fields: 1, methods: 6, attributes: 3
Constant pool:
   #1 = Utf8               scala/xml/dtd/DocType$
   #2 = Class              #1             // scala/xml/dtd/DocType$
   #3 = Utf8               java/lang/Object
   #4 = Class              #3             // java/lang/Object
   #5 = Utf8               java/io/Serializable
   #6 = Class              #5             // java/io/Serializable
   #7 = Utf8               DocType.scala
   #8 = Utf8               MODULE$
   #9 = Utf8               Lscala/xml/dtd/DocType$;
  #10 = Utf8               <clinit>
  #11 = Utf8               ()V
  #12 = Utf8               <init>
  #13 = NameAndType        #12:#11        // "<init>":()V
  #14 = Methodref          #2.#13         // scala/xml/dtd/DocType$."<init>":()V
  #15 = NameAndType        #8:#9          // MODULE$:Lscala/xml/dtd/DocType$;
  #16 = Fieldref           #2.#15         // scala/xml/dtd/DocType$.MODULE$:Lscala/xml/dtd/DocType$;
  #17 = Utf8               apply
  #18 = Utf8               (Ljava/lang/String;)Lscala/xml/dtd/DocType;
  #19 = Utf8               name
  #20 = Utf8               scala/xml/dtd/DocType
  #21 = Class              #20            // scala/xml/dtd/DocType
  #22 = Utf8               scala/xml/dtd/NoExternalID$
  #23 = Class              #22            // scala/xml/dtd/NoExternalID$
  #24 = Utf8               Lscala/xml/dtd/NoExternalID$;
  #25 = NameAndType        #8:#24         // MODULE$:Lscala/xml/dtd/NoExternalID$;
  #26 = Fieldref           #23.#25        // scala/xml/dtd/NoExternalID$.MODULE$:Lscala/xml/dtd/NoExternalID$;
  #27 = Utf8               scala/package$
  #28 = Class              #27            // scala/package$
  #29 = Utf8               Lscala/package$;
  #30 = NameAndType        #8:#29         // MODULE$:Lscala/package$;
  #31 = Fieldref           #28.#30        // scala/package$.MODULE$:Lscala/package$;
  #32 = Utf8               Nil
  #33 = Utf8               ()Lscala/collection/immutable/Nil$;
  #34 = NameAndType        #32:#33        // Nil:()Lscala/collection/immutable/Nil$;
  #35 = Methodref          #28.#34        // scala/package$.Nil:()Lscala/collection/immutable/Nil$;
  #36 = Utf8               (Ljava/lang/String;Lscala/xml/dtd/ExternalID;Lscala/collection/Seq;)V
  #37 = NameAndType        #12:#36        // "<init>":(Ljava/lang/String;Lscala/xml/dtd/ExternalID;Lscala/collection/Seq;)V
  #38 = Methodref          #21.#37        // scala/xml/dtd/DocType."<init>":(Ljava/lang/String;Lscala/xml/dtd/ExternalID;Lscala/collection/Seq;)V
  #39 = Utf8               this
  #40 = Utf8               Ljava/lang/String;
  #41 = Utf8               (Ljava/lang/String;Lscala/xml/dtd/ExternalID;Lscala/collection/Seq;)Lscala/xml/dtd/DocType;
  #42 = Utf8               (Ljava/lang/String;Lscala/xml/dtd/ExternalID;Lscala/collection/Seq<Lscala/xml/dtd/Decl;>;)Lscala/xml/dtd/DocType;
  #43 = Utf8               extID
  #44 = Utf8               intSubset
  #45 = Utf8               Lscala/xml/dtd/ExternalID;
  #46 = Utf8               Lscala/collection/Seq;
  #47 = Utf8               unapply
  #48 = Utf8               (Lscala/xml/dtd/DocType;)Lscala/Option;
  #49 = Utf8               (Lscala/xml/dtd/DocType;)Lscala/Option<Lscala/Tuple3<Ljava/lang/String;Lscala/xml/dtd/ExternalID;Lscala/collection/Seq<Lscala/xml/dtd/Decl;>;>;>;
  #50 = Utf8               x$0
  #51 = Utf8               scala/None$
  #52 = Class              #51            // scala/None$
  #53 = Utf8               Lscala/None$;
  #54 = NameAndType        #8:#53         // MODULE$:Lscala/None$;
  #55 = Fieldref           #52.#54        // scala/None$.MODULE$:Lscala/None$;
  #56 = Utf8               scala/Some
  #57 = Class              #56            // scala/Some
  #58 = Utf8               scala/Tuple3
  #59 = Class              #58            // scala/Tuple3
  #60 = Utf8               ()Ljava/lang/String;
  #61 = NameAndType        #19:#60        // name:()Ljava/lang/String;
  #62 = Methodref          #21.#61        // scala/xml/dtd/DocType.name:()Ljava/lang/String;
  #63 = Utf8               ()Lscala/xml/dtd/ExternalID;
  #64 = NameAndType        #43:#63        // extID:()Lscala/xml/dtd/ExternalID;
  #65 = Methodref          #21.#64        // scala/xml/dtd/DocType.extID:()Lscala/xml/dtd/ExternalID;
  #66 = Utf8               ()Lscala/collection/Seq;
  #67 = NameAndType        #44:#66        // intSubset:()Lscala/collection/Seq;
  #68 = Methodref          #21.#67        // scala/xml/dtd/DocType.intSubset:()Lscala/collection/Seq;
  #69 = Utf8               (Ljava/lang/Object;Ljava/lang/Object;Ljava/lang/Object;)V
  #70 = NameAndType        #12:#69        // "<init>":(Ljava/lang/Object;Ljava/lang/Object;Ljava/lang/Object;)V
  #71 = Methodref          #59.#70        // scala/Tuple3."<init>":(Ljava/lang/Object;Ljava/lang/Object;Ljava/lang/Object;)V
  #72 = Utf8               (Ljava/lang/Object;)V
  #73 = NameAndType        #12:#72        // "<init>":(Ljava/lang/Object;)V
  #74 = Methodref          #57.#73        // scala/Some."<init>":(Ljava/lang/Object;)V
  #75 = Utf8               Lscala/xml/dtd/DocType;
  #76 = Utf8               scala/Option
  #77 = Class              #76            // scala/Option
  #78 = Utf8               writeReplace
  #79 = Utf8               ()Ljava/lang/Object;
  #80 = Utf8               scala/runtime/ModuleSerializationProxy
  #81 = Class              #80            // scala/runtime/ModuleSerializationProxy
  #82 = Utf8               (Ljava/lang/Class;)V
  #83 = NameAndType        #12:#82        // "<init>":(Ljava/lang/Class;)V
  #84 = Methodref          #81.#83        // scala/runtime/ModuleSerializationProxy."<init>":(Ljava/lang/Class;)V
  #85 = Methodref          #4.#13         // java/lang/Object."<init>":()V
  #86 = Utf8               Code
  #87 = Utf8               LineNumberTable
  #88 = Utf8               LocalVariableTable
  #89 = Utf8               MethodParameters
  #90 = Utf8               Signature
  #91 = Utf8               StackMapTable
  #92 = Utf8               SourceFile
  #93 = Utf8               ScalaInlineInfo
  #94 = Utf8               Scala
{
  public static final scala.xml.dtd.DocType$ MODULE$;
    descriptor: Lscala/xml/dtd/DocType$;
    flags: (0x0019) ACC_PUBLIC, ACC_STATIC, ACC_FINAL

  public static {};
    descriptor: ()V
    flags: (0x0009) ACC_PUBLIC, ACC_STATIC
    Code:
      stack=2, locals=0, args_size=0
         0: new           #2                  // class scala/xml/dtd/DocType$
         3: dup
         4: invokespecial #14                 // Method "<init>":()V
         7: putstatic     #16                 // Field MODULE$:Lscala/xml/dtd/DocType$;
        10: return
      LineNumberTable:
        line 42: 0

  public scala.xml.dtd.DocType apply(java.lang.String);
    descriptor: (Ljava/lang/String;)Lscala/xml/dtd/DocType;
    flags: (0x0001) ACC_PUBLIC
    Code:
      stack=5, locals=2, args_size=2
         0: new           #21                 // class scala/xml/dtd/DocType
         3: dup
         4: aload_1
         5: getstatic     #26                 // Field scala/xml/dtd/NoExternalID$.MODULE$:Lscala/xml/dtd/NoExternalID$;
         8: getstatic     #31                 // Field scala/package$.MODULE$:Lscala/package$;
        11: invokevirtual #35                 // Method scala/package$.Nil:()Lscala/collection/immutable/Nil$;
        14: invokespecial #38                 // Method scala/xml/dtd/DocType."<init>":(Ljava/lang/String;Lscala/xml/dtd/ExternalID;Lscala/collection/Seq;)V
        17: areturn
      LineNumberTable:
        line 44: 0
      LocalVariableTable:
        Start  Length  Slot  Name   Signature
            0      18     0  this   Lscala/xml/dtd/DocType$;
            0      18     1  name   Ljava/lang/String;
    MethodParameters:
      Name                           Flags
      name                           final

  public scala.xml.dtd.DocType apply(java.lang.String, scala.xml.dtd.ExternalID, scala.collection.Seq<scala.xml.dtd.Decl>);
    descriptor: (Ljava/lang/String;Lscala/xml/dtd/ExternalID;Lscala/collection/Seq;)Lscala/xml/dtd/DocType;
    flags: (0x0001) ACC_PUBLIC
    Code:
      stack=5, locals=4, args_size=4
         0: new           #21                 // class scala/xml/dtd/DocType
         3: dup
         4: aload_1
         5: aload_2
         6: aload_3
         7: invokespecial #38                 // Method scala/xml/dtd/DocType."<init>":(Ljava/lang/String;Lscala/xml/dtd/ExternalID;Lscala/collection/Seq;)V
        10: areturn
      LineNumberTable:
        line 28: 0
      LocalVariableTable:
        Start  Length  Slot  Name   Signature
            0      11     0  this   Lscala/xml/dtd/DocType$;
            0      11     1  name   Ljava/lang/String;
            0      11     2 extID   Lscala/xml/dtd/ExternalID;
            0      11     3 intSubset   Lscala/collection/Seq;
    Signature: #42                          // (Ljava/lang/String;Lscala/xml/dtd/ExternalID;Lscala/collection/Seq<Lscala/xml/dtd/Decl;>;)Lscala/xml/dtd/DocType;
    MethodParameters:
      Name                           Flags
      name                           final
      extID                          final
      intSubset                      final

  public scala.Option<scala.Tuple3<java.lang.String, scala.xml.dtd.ExternalID, scala.collection.Seq<scala.xml.dtd.Decl>>> unapply(scala.xml.dtd.DocType);
    descriptor: (Lscala/xml/dtd/DocType;)Lscala/Option;
    flags: (0x0001) ACC_PUBLIC
    Code:
      stack=7, locals=2, args_size=2
         0: aload_1
         1: ifnonnull     10
         4: getstatic     #55                 // Field scala/None$.MODULE$:Lscala/None$;
         7: goto          36
        10: new           #57                 // class scala/Some
        13: dup
        14: new           #59                 // class scala/Tuple3
        17: dup
        18: aload_1
        19: invokevirtual #62                 // Method scala/xml/dtd/DocType.name:()Ljava/lang/String;
        22: aload_1
        23: invokevirtual #65                 // Method scala/xml/dtd/DocType.extID:()Lscala/xml/dtd/ExternalID;
        26: aload_1
        27: invokevirtual #68                 // Method scala/xml/dtd/DocType.intSubset:()Lscala/collection/Seq;
        30: invokespecial #71                 // Method scala/Tuple3."<init>":(Ljava/lang/Object;Ljava/lang/Object;Ljava/lang/Object;)V
        33: invokespecial #74                 // Method scala/Some."<init>":(Ljava/lang/Object;)V
        36: areturn
      StackMapTable: number_of_entries = 2
        frame_type = 10 /* same */
        frame_type = 89 /* same_locals_1_stack_item */
          stack = [ class scala/Option ]
      LineNumberTable:
        line 28: 0
      LocalVariableTable:
        Start  Length  Slot  Name   Signature
            0      37     0  this   Lscala/xml/dtd/DocType$;
            0      37     1   x$0   Lscala/xml/dtd/DocType;
    Signature: #49                          // (Lscala/xml/dtd/DocType;)Lscala/Option<Lscala/Tuple3<Ljava/lang/String;Lscala/xml/dtd/ExternalID;Lscala/collection/Seq<Lscala/xml/dtd/Decl;>;>;>;
    MethodParameters:
      Name                           Flags
      x$0                            final

  private java.lang.Object writeReplace();
    descriptor: ()Ljava/lang/Object;
    flags: (0x0002) ACC_PRIVATE
    Code:
      stack=3, locals=1, args_size=1
         0: new           #81                 // class scala/runtime/ModuleSerializationProxy
         3: dup
         4: ldc           #2                  // class scala/xml/dtd/DocType$
         6: invokespecial #84                 // Method scala/runtime/ModuleSerializationProxy."<init>":(Ljava/lang/Class;)V
         9: areturn
      LineNumberTable:
        line 42: 0
      LocalVariableTable:
        Start  Length  Slot  Name   Signature
            0      10     0  this   Lscala/xml/dtd/DocType$;

  private scala.xml.dtd.DocType$();
    descriptor: ()V
    flags: (0x0002) ACC_PRIVATE
    Code:
      stack=1, locals=1, args_size=1
         0: aload_0
         1: invokespecial #85                 // Method java/lang/Object."<init>":()V
         4: return
      LineNumberTable:
        line 45: 0
        line 42: 4
      LocalVariableTable:
        Start  Length  Slot  Name   Signature
            0       5     0  this   Lscala/xml/dtd/DocType$;
}
SourceFile: "DocType.scala"
  ScalaInlineInfo: length = 0x1D (unknown attribute)
   01 01 00 05 00 0C 00 0B 01 00 11 00 12 01 00 11
   00 29 01 00 2F 00 30 01 00 4E 00 4F 01
  Scala: length = 0x0 (unknown attribute)

