Classfile /Users/mw/Projects/slang-braindump/.jar/jar8/assemble/slang-braindump/assemble/content/scala/xml/dtd/DTD.class
  Last modified May 29, 2022; size 6062 bytes
  SHA-256 checksum 6bdcce11229757371cbb1305500cd47955f7f5dfb3f3fe65f573ed57b8a97bf0
  Compiled from "DTD.scala"
public abstract class scala.xml.dtd.DTD
  minor version: 0
  major version: 52
  flags: (0x0421) ACC_PUBLIC, ACC_SUPER, ACC_ABSTRACT
  this_class: #2                          // scala/xml/dtd/DTD
  super_class: #4                         // java/lang/Object
  interfaces: 0, fields: 5, methods: 16, attributes: 6
Constant pool:
    #1 = Utf8               scala/xml/dtd/DTD
    #2 = Class              #1            // scala/xml/dtd/DTD
    #3 = Utf8               java/lang/Object
    #4 = Class              #3            // java/lang/Object
    #5 = Utf8               DTD.scala
    #6 = Utf8               Lscala/reflect/ScalaSignature;
    #7 = Utf8               bytes
    #8 = Utf8               \u0006\u0005\u0005\u0005a!\u0002\u000b\u0016\u0003\u0003a\u0002\"B\u0011\u0001\t\u0003\u0011\u0003bB\u0013\u0001\u0001\u0004%\tA\n\u0005\bU\u0001\u0001\r\u0011\"\u0001,\u0011\u0019\t\u0004\u0001)Q\u0005O!9!\u0007\u0001a\u0001\n\u0003\u0019\u0004b\u0002 \u0001\u0001\u0004%\ta\u0010\u0005\u0007\u0003\u0002\u0001\u000b\u0015\u0002\u001b\t\u000b\t\u0003A\u0011A\"\t\u000b5\u0003A\u0011\u0001(\t\u000fM\u0003\u0001\u0019!C\u0001)\"9\u0011\u000e\u0001a\u0001\n\u0003Q\u0007B\u00027\u0001A\u0003&Q\u000bC\u0004n\u0001\u0001\u0007I\u0011\u00018\t\u000fM\u0004\u0001\u0019!C\u0001i\"1a\u000f\u0001Q!\n=Dqa\u001e\u0001A\u0002\u0013\u0005\u0001\u0010C\u0004{\u0001\u0001\u0007I\u0011A>\t\ru\u0004\u0001\u0015)\u0003z\u0011\u0015q\b\u0001\"\u0011\u0000\u0005\r!E\u000b\u0012\u0006\u0003-]\t1\u0001\u001a;e\u0015\tA\u0012$A\u0002y[2T\u0011AG\u0001\u0006g\u000e\fG.Y\u0002\u0001\'\t\u0001Q\u0004\u0005\u0002\u001f?5\t\u0011$\u0003\u0002!3\t1\u0011I\\=SK\u001a\fa\u0001P5oSRtD#A\u0012\u0011\u0005\u0011\u0002Q\"A\u000b\u0002\u0015\u0015DH/\u001a:oC2LE)F\u0001(!\t!\u0003&\u0003\u0002*+\tQQ\t\u001f;fe:\fG.\u0013#\u0002\u001d\u0015DH/\u001a:oC2LEi\u0018\u0013fcR\u0011Af\f\t\u0003=5J!AL\r\u0003\tUs\u0017\u000e\u001e\u0005\ba\r\t\t\u00111\u0001(\u0003\rAH%M\u0001\fKb$XM\u001d8bY&#\u0005%A\u0003eK\u000ed7/F\u00015!\r)\u0004h\u000f\b\u0003=YJ!aN\r\u0002\u000fA\f7m[1hK&\u0011\u0011H\u000f\u0002\u0005\u0019&\u001cHO\u0003\u000283A\u0011A\u0005P\u0005\u0003{U\u0011A\u0001R3dY\u0006IA-Z2mg~#S-\u001d\u000b\u0003Y\u0001Cq\u0001\r\u0004\u0002\u0002\u0003\u0007A\'\u0001\u0004eK\u000ed7\u000fI\u0001\n]>$\u0018\r^5p]N,\u0012\u0001\u0012\t\u0004\u000b\"SU\"\u0001$\u000b\u0005\u001dK\u0012AC2pY2,7\r^5p]&\u0011\u0011J\u0012\u0002\u0004\'\u0016\f\bC\u0001\u0013L\u0013\taUC\u0001\u0007O_R\fG/[8o\t\u0016\u001cG.\u0001\tv]B\f\'o]3e\u000b:$\u0018\u000e^5fgV\tq\nE\u0002F\u0011B\u0003\"\u0001J)\n\u0005I+\"AC#oi&$\u0018\u0010R3dY\u0006!Q\r\\3n+\u0005)\u0006\u0003\u0002,Z7\u001al\u0011a\u0016\u0006\u00031\u001a\u000bq!\\;uC\ndW-\u0003\u0002[/\n\u0019Q*\u00199\u0011\u0005q\u001bgBA/b!\tq\u0016$D\u0001`\u0015\t\u00017$\u0001\u0004=e>|GOP\u0005\u0003Ef\ta\u0001\u0015:fI\u00164\u0017B\u00013f\u0005\u0019\u0019FO]5oO*\u0011!-\u0007\t\u0003I\u001dL!\u0001[\u000b\u0003\u0011\u0015cW-\u001c#fG2\f\u0001\"\u001a7f[~#S-\u001d\u000b\u0003Y-Dq\u0001M\u0006\u0002\u0002\u0003\u0007Q+A\u0003fY\u0016l\u0007%\u0001\u0003biR\u0014X#A8\u0011\tYK6\f\u001d\t\u0003IEL!A]\u000b\u0003\u0017\u0005#H\u000fT5ti\u0012+7\r\\\u0001\tCR$(o\u0018\u0013fcR\u0011A&\u001e\u0005\ba9\t\t\u00111\u0001p\u0003\u0015\tG\u000f\u001e:!\u0003\r)g\u000e^\u000b\u0002sB!a+W.Q\u0003\u001d)g\u000e^0%KF$\"\u0001\f?\t\u000fA\n\u0012\u0011!a\u0001s\u0006!QM\u001c;!\u0003!!xn\u0015;sS:<G#A.
    #9 = Utf8               java/lang/invoke/MethodHandles$Lookup
   #10 = Class              #9            // java/lang/invoke/MethodHandles$Lookup
   #11 = Utf8               java/lang/invoke/MethodHandles
   #12 = Class              #11           // java/lang/invoke/MethodHandles
   #13 = Utf8               Lookup
   #14 = Utf8               externalID
   #15 = Utf8               Lscala/xml/dtd/ExternalID;
   #16 = Utf8               decls
   #17 = Utf8               Lscala/collection/immutable/List;
   #18 = Utf8               Lscala/collection/immutable/List<Lscala/xml/dtd/Decl;>;
   #19 = Utf8               elem
   #20 = Utf8               Lscala/collection/mutable/Map;
   #21 = Utf8               Lscala/collection/mutable/Map<Ljava/lang/String;Lscala/xml/dtd/ElemDecl;>;
   #22 = Utf8               attr
   #23 = Utf8               Lscala/collection/mutable/Map<Ljava/lang/String;Lscala/xml/dtd/AttListDecl;>;
   #24 = Utf8               ent
   #25 = Utf8               Lscala/collection/mutable/Map<Ljava/lang/String;Lscala/xml/dtd/EntityDecl;>;
   #26 = Utf8               ()Lscala/xml/dtd/ExternalID;
   #27 = NameAndType        #14:#15       // externalID:Lscala/xml/dtd/ExternalID;
   #28 = Fieldref           #2.#27        // scala/xml/dtd/DTD.externalID:Lscala/xml/dtd/ExternalID;
   #29 = Utf8               this
   #30 = Utf8               Lscala/xml/dtd/DTD;
   #31 = Utf8               externalID_$eq
   #32 = Utf8               (Lscala/xml/dtd/ExternalID;)V
   #33 = Utf8               x$1
   #34 = Utf8               ()Lscala/collection/immutable/List;
   #35 = Utf8               ()Lscala/collection/immutable/List<Lscala/xml/dtd/Decl;>;
   #36 = NameAndType        #16:#17       // decls:Lscala/collection/immutable/List;
   #37 = Fieldref           #2.#36        // scala/xml/dtd/DTD.decls:Lscala/collection/immutable/List;
   #38 = Utf8               decls_$eq
   #39 = Utf8               (Lscala/collection/immutable/List;)V
   #40 = Utf8               (Lscala/collection/immutable/List<Lscala/xml/dtd/Decl;>;)V
   #41 = Utf8               notations
   #42 = Utf8               ()Lscala/collection/Seq;
   #43 = Utf8               ()Lscala/collection/Seq<Lscala/xml/dtd/NotationDecl;>;
   #44 = Utf8               scala/package$
   #45 = Class              #44           // scala/package$
   #46 = Utf8               MODULE$
   #47 = Utf8               Lscala/package$;
   #48 = NameAndType        #46:#47       // MODULE$:Lscala/package$;
   #49 = Fieldref           #45.#48       // scala/package$.MODULE$:Lscala/package$;
   #50 = Utf8               Nil
   #51 = Utf8               ()Lscala/collection/immutable/Nil$;
   #52 = NameAndType        #50:#51       // Nil:()Lscala/collection/immutable/Nil$;
   #53 = Methodref          #45.#52       // scala/package$.Nil:()Lscala/collection/immutable/Nil$;
   #54 = Utf8               unparsedEntities
   #55 = Utf8               ()Lscala/collection/Seq<Lscala/xml/dtd/EntityDecl;>;
   #56 = Utf8               ()Lscala/collection/mutable/Map;
   #57 = Utf8               ()Lscala/collection/mutable/Map<Ljava/lang/String;Lscala/xml/dtd/ElemDecl;>;
   #58 = NameAndType        #19:#20       // elem:Lscala/collection/mutable/Map;
   #59 = Fieldref           #2.#58        // scala/xml/dtd/DTD.elem:Lscala/collection/mutable/Map;
   #60 = Utf8               elem_$eq
   #61 = Utf8               (Lscala/collection/mutable/Map;)V
   #62 = Utf8               (Lscala/collection/mutable/Map<Ljava/lang/String;Lscala/xml/dtd/ElemDecl;>;)V
   #63 = Utf8               ()Lscala/collection/mutable/Map<Ljava/lang/String;Lscala/xml/dtd/AttListDecl;>;
   #64 = NameAndType        #22:#20       // attr:Lscala/collection/mutable/Map;
   #65 = Fieldref           #2.#64        // scala/xml/dtd/DTD.attr:Lscala/collection/mutable/Map;
   #66 = Utf8               attr_$eq
   #67 = Utf8               (Lscala/collection/mutable/Map<Ljava/lang/String;Lscala/xml/dtd/AttListDecl;>;)V
   #68 = Utf8               ()Lscala/collection/mutable/Map<Ljava/lang/String;Lscala/xml/dtd/EntityDecl;>;
   #69 = NameAndType        #24:#20       // ent:Lscala/collection/mutable/Map;
   #70 = Fieldref           #2.#69        // scala/xml/dtd/DTD.ent:Lscala/collection/mutable/Map;
   #71 = Utf8               ent_$eq
   #72 = Utf8               (Lscala/collection/mutable/Map<Ljava/lang/String;Lscala/xml/dtd/EntityDecl;>;)V
   #73 = Utf8               toString
   #74 = Utf8               ()Ljava/lang/String;
   #75 = Utf8               scala/collection/StringOps$
   #76 = Class              #75           // scala/collection/StringOps$
   #77 = Utf8               Lscala/collection/StringOps$;
   #78 = NameAndType        #46:#77       // MODULE$:Lscala/collection/StringOps$;
   #79 = Fieldref           #76.#78       // scala/collection/StringOps$.MODULE$:Lscala/collection/StringOps$;
   #80 = Utf8               scala/Predef$
   #81 = Class              #80           // scala/Predef$
   #82 = Utf8               Lscala/Predef$;
   #83 = NameAndType        #46:#82       // MODULE$:Lscala/Predef$;
   #84 = Fieldref           #81.#83       // scala/Predef$.MODULE$:Lscala/Predef$;
   #85 = Utf8               DTD [\n%s%s]
   #86 = String             #85           // DTD [\n%s%s]
   #87 = Utf8               augmentString
   #88 = Utf8               (Ljava/lang/String;)Ljava/lang/String;
   #89 = NameAndType        #87:#88       // augmentString:(Ljava/lang/String;)Ljava/lang/String;
   #90 = Methodref          #81.#89       // scala/Predef$.augmentString:(Ljava/lang/String;)Ljava/lang/String;
   #91 = Utf8               scala/runtime/ScalaRunTime$
   #92 = Class              #91           // scala/runtime/ScalaRunTime$
   #93 = Utf8               Lscala/runtime/ScalaRunTime$;
   #94 = NameAndType        #46:#93       // MODULE$:Lscala/runtime/ScalaRunTime$;
   #95 = Fieldref           #92.#94       // scala/runtime/ScalaRunTime$.MODULE$:Lscala/runtime/ScalaRunTime$;
   #96 = Utf8               scala/Option$
   #97 = Class              #96           // scala/Option$
   #98 = Utf8               Lscala/Option$;
   #99 = NameAndType        #46:#98       // MODULE$:Lscala/Option$;
  #100 = Fieldref           #97.#99       // scala/Option$.MODULE$:Lscala/Option$;
  #101 = NameAndType        #14:#26       // externalID:()Lscala/xml/dtd/ExternalID;
  #102 = Methodref          #2.#101       // scala/xml/dtd/DTD.externalID:()Lscala/xml/dtd/ExternalID;
  #103 = Utf8               apply
  #104 = Utf8               (Ljava/lang/Object;)Lscala/Option;
  #105 = NameAndType        #103:#104     // apply:(Ljava/lang/Object;)Lscala/Option;
  #106 = Methodref          #97.#105      // scala/Option$.apply:(Ljava/lang/Object;)Lscala/Option;
  #107 = Utf8               ()Ljava/lang/Object;
  #108 = MethodType         #107          //  ()Ljava/lang/Object;
  #109 = Utf8               $anonfun$toString$1
  #110 = NameAndType        #109:#74      // $anonfun$toString$1:()Ljava/lang/String;
  #111 = Methodref          #2.#110       // scala/xml/dtd/DTD.$anonfun$toString$1:()Ljava/lang/String;
  #112 = MethodHandle       6:#111        // REF_invokeStatic scala/xml/dtd/DTD.$anonfun$toString$1:()Ljava/lang/String;
  #113 = MethodType         #74           //  ()Ljava/lang/String;
  #114 = Integer            5
  #115 = Integer            1
  #116 = Utf8               java/lang/invoke/LambdaMetafactory
  #117 = Class              #116          // java/lang/invoke/LambdaMetafactory
  #118 = Utf8               altMetafactory
  #119 = Utf8               (Ljava/lang/invoke/MethodHandles$Lookup;Ljava/lang/String;Ljava/lang/invoke/MethodType;[Ljava/lang/Object;)Ljava/lang/invoke/CallSite;
  #120 = NameAndType        #118:#119     // altMetafactory:(Ljava/lang/invoke/MethodHandles$Lookup;Ljava/lang/String;Ljava/lang/invoke/MethodType;[Ljava/lang/Object;)Ljava/lang/invoke/CallSite;
  #121 = Methodref          #117.#120     // java/lang/invoke/LambdaMetafactory.altMetafactory:(Ljava/lang/invoke/MethodHandles$Lookup;Ljava/lang/String;Ljava/lang/invoke/MethodType;[Ljava/lang/Object;)Ljava/lang/invoke/CallSite;
  #122 = MethodHandle       6:#121        // REF_invokeStatic java/lang/invoke/LambdaMetafactory.altMetafactory:(Ljava/lang/invoke/MethodHandles$Lookup;Ljava/lang/String;Ljava/lang/invoke/MethodType;[Ljava/lang/Object;)Ljava/lang/invoke/CallSite;
  #123 = Utf8               ()Lscala/Function0;
  #124 = NameAndType        #103:#123     // apply:()Lscala/Function0;
  #125 = InvokeDynamic      #0:#124       // #0:apply:()Lscala/Function0;
  #126 = Utf8               scala/Option
  #127 = Class              #126          // scala/Option
  #128 = Utf8               getOrElse
  #129 = Utf8               (Lscala/Function0;)Ljava/lang/Object;
  #130 = NameAndType        #128:#129     // getOrElse:(Lscala/Function0;)Ljava/lang/Object;
  #131 = Methodref          #127.#130     // scala/Option.getOrElse:(Lscala/Function0;)Ljava/lang/Object;
  #132 = NameAndType        #16:#34       // decls:()Lscala/collection/immutable/List;
  #133 = Methodref          #2.#132       // scala/xml/dtd/DTD.decls:()Lscala/collection/immutable/List;
  #134 = Utf8
  #135 = String             #134          //
  #136 = Utf8               \n
  #137 = String             #136          // \n
  #138 = Utf8               scala/collection/immutable/List
  #139 = Class              #138          // scala/collection/immutable/List
  #140 = Utf8               mkString
  #141 = Utf8               (Ljava/lang/String;Ljava/lang/String;Ljava/lang/String;)Ljava/lang/String;
  #142 = NameAndType        #140:#141     // mkString:(Ljava/lang/String;Ljava/lang/String;Ljava/lang/String;)Ljava/lang/String;
  #143 = Methodref          #139.#142     // scala/collection/immutable/List.mkString:(Ljava/lang/String;Ljava/lang/String;Ljava/lang/String;)Ljava/lang/String;
  #144 = Utf8               genericWrapArray
  #145 = Utf8               (Ljava/lang/Object;)Lscala/collection/immutable/ArraySeq;
  #146 = NameAndType        #144:#145     // genericWrapArray:(Ljava/lang/Object;)Lscala/collection/immutable/ArraySeq;
  #147 = Methodref          #92.#146      // scala/runtime/ScalaRunTime$.genericWrapArray:(Ljava/lang/Object;)Lscala/collection/immutable/ArraySeq;
  #148 = Utf8               format$extension
  #149 = Utf8               (Ljava/lang/String;Lscala/collection/immutable/Seq;)Ljava/lang/String;
  #150 = NameAndType        #148:#149     // format$extension:(Ljava/lang/String;Lscala/collection/immutable/Seq;)Ljava/lang/String;
  #151 = Methodref          #76.#150      // scala/collection/StringOps$.format$extension:(Ljava/lang/String;Lscala/collection/immutable/Seq;)Ljava/lang/String;
  #152 = Utf8               <init>
  #153 = Utf8               ()V
  #154 = NameAndType        #152:#153     // "<init>":()V
  #155 = Methodref          #4.#154       // java/lang/Object."<init>":()V
  #156 = Utf8               scala/collection/mutable/HashMap
  #157 = Class              #156          // scala/collection/mutable/HashMap
  #158 = Methodref          #157.#154     // scala/collection/mutable/HashMap."<init>":()V
  #159 = Utf8               $deserializeLambda$
  #160 = Utf8               (Ljava/lang/invoke/SerializedLambda;)Ljava/lang/Object;
  #161 = Utf8               scala/runtime/LambdaDeserialize
  #162 = Class              #161          // scala/runtime/LambdaDeserialize
  #163 = Utf8               bootstrap
  #164 = Utf8               (Ljava/lang/invoke/MethodHandles$Lookup;Ljava/lang/String;Ljava/lang/invoke/MethodType;[Ljava/lang/invoke/MethodHandle;)Ljava/lang/invoke/CallSite;
  #165 = NameAndType        #163:#164     // bootstrap:(Ljava/lang/invoke/MethodHandles$Lookup;Ljava/lang/String;Ljava/lang/invoke/MethodType;[Ljava/lang/invoke/MethodHandle;)Ljava/lang/invoke/CallSite;
  #166 = Methodref          #162.#165     // scala/runtime/LambdaDeserialize.bootstrap:(Ljava/lang/invoke/MethodHandles$Lookup;Ljava/lang/String;Ljava/lang/invoke/MethodType;[Ljava/lang/invoke/MethodHandle;)Ljava/lang/invoke/CallSite;
  #167 = MethodHandle       6:#166        // REF_invokeStatic scala/runtime/LambdaDeserialize.bootstrap:(Ljava/lang/invoke/MethodHandles$Lookup;Ljava/lang/String;Ljava/lang/invoke/MethodType;[Ljava/lang/invoke/MethodHandle;)Ljava/lang/invoke/CallSite;
  #168 = Utf8               lambdaDeserialize
  #169 = NameAndType        #168:#160     // lambdaDeserialize:(Ljava/lang/invoke/SerializedLambda;)Ljava/lang/Object;
  #170 = InvokeDynamic      #1:#169       // #1:lambdaDeserialize:(Ljava/lang/invoke/SerializedLambda;)Ljava/lang/Object;
  #171 = Utf8               Signature
  #172 = Utf8               Code
  #173 = Utf8               LineNumberTable
  #174 = Utf8               LocalVariableTable
  #175 = Utf8               MethodParameters
  #176 = Utf8               InnerClasses
  #177 = Utf8               SourceFile
  #178 = Utf8               RuntimeVisibleAnnotations
  #179 = Utf8               BootstrapMethods
  #180 = Utf8               ScalaInlineInfo
  #181 = Utf8               ScalaSig
{
  private scala.xml.dtd.ExternalID externalID;
    descriptor: Lscala/xml/dtd/ExternalID;
    flags: (0x0002) ACC_PRIVATE

  private scala.collection.immutable.List<scala.xml.dtd.Decl> decls;
    descriptor: Lscala/collection/immutable/List;
    flags: (0x0002) ACC_PRIVATE
    Signature: #18                          // Lscala/collection/immutable/List<Lscala/xml/dtd/Decl;>;

  private scala.collection.mutable.Map<java.lang.String, scala.xml.dtd.ElemDecl> elem;
    descriptor: Lscala/collection/mutable/Map;
    flags: (0x0002) ACC_PRIVATE
    Signature: #21                          // Lscala/collection/mutable/Map<Ljava/lang/String;Lscala/xml/dtd/ElemDecl;>;

  private scala.collection.mutable.Map<java.lang.String, scala.xml.dtd.AttListDecl> attr;
    descriptor: Lscala/collection/mutable/Map;
    flags: (0x0002) ACC_PRIVATE
    Signature: #23                          // Lscala/collection/mutable/Map<Ljava/lang/String;Lscala/xml/dtd/AttListDecl;>;

  private scala.collection.mutable.Map<java.lang.String, scala.xml.dtd.EntityDecl> ent;
    descriptor: Lscala/collection/mutable/Map;
    flags: (0x0002) ACC_PRIVATE
    Signature: #25                          // Lscala/collection/mutable/Map<Ljava/lang/String;Lscala/xml/dtd/EntityDecl;>;

  public scala.xml.dtd.ExternalID externalID();
    descriptor: ()Lscala/xml/dtd/ExternalID;
    flags: (0x0001) ACC_PUBLIC
    Code:
      stack=1, locals=1, args_size=1
         0: aload_0
         1: getfield      #28                 // Field externalID:Lscala/xml/dtd/ExternalID;
         4: areturn
      LineNumberTable:
        line 26: 0
      LocalVariableTable:
        Start  Length  Slot  Name   Signature
            0       5     0  this   Lscala/xml/dtd/DTD;

  public void externalID_$eq(scala.xml.dtd.ExternalID);
    descriptor: (Lscala/xml/dtd/ExternalID;)V
    flags: (0x0001) ACC_PUBLIC
    Code:
      stack=2, locals=2, args_size=2
         0: aload_0
         1: aload_1
         2: putfield      #28                 // Field externalID:Lscala/xml/dtd/ExternalID;
         5: return
      LineNumberTable:
        line 26: 0
      LocalVariableTable:
        Start  Length  Slot  Name   Signature
            0       6     0  this   Lscala/xml/dtd/DTD;
            0       6     1   x$1   Lscala/xml/dtd/ExternalID;
    MethodParameters:
      Name                           Flags
      x$1                            final

  public scala.collection.immutable.List<scala.xml.dtd.Decl> decls();
    descriptor: ()Lscala/collection/immutable/List;
    flags: (0x0001) ACC_PUBLIC
    Code:
      stack=1, locals=1, args_size=1
         0: aload_0
         1: getfield      #37                 // Field decls:Lscala/collection/immutable/List;
         4: areturn
      LineNumberTable:
        line 27: 0
      LocalVariableTable:
        Start  Length  Slot  Name   Signature
            0       5     0  this   Lscala/xml/dtd/DTD;
    Signature: #35                          // ()Lscala/collection/immutable/List<Lscala/xml/dtd/Decl;>;

  public void decls_$eq(scala.collection.immutable.List<scala.xml.dtd.Decl>);
    descriptor: (Lscala/collection/immutable/List;)V
    flags: (0x0001) ACC_PUBLIC
    Code:
      stack=2, locals=2, args_size=2
         0: aload_0
         1: aload_1
         2: putfield      #37                 // Field decls:Lscala/collection/immutable/List;
         5: return
      LineNumberTable:
        line 27: 0
      LocalVariableTable:
        Start  Length  Slot  Name   Signature
            0       6     0  this   Lscala/xml/dtd/DTD;
            0       6     1   x$1   Lscala/collection/immutable/List;
    Signature: #40                          // (Lscala/collection/immutable/List<Lscala/xml/dtd/Decl;>;)V
    MethodParameters:
      Name                           Flags
      x$1                            final

  public scala.collection.Seq<scala.xml.dtd.NotationDecl> notations();
    descriptor: ()Lscala/collection/Seq;
    flags: (0x0001) ACC_PUBLIC
    Code:
      stack=1, locals=1, args_size=1
         0: getstatic     #49                 // Field scala/package$.MODULE$:Lscala/package$;
         3: invokevirtual #53                 // Method scala/package$.Nil:()Lscala/collection/immutable/Nil$;
         6: areturn
      LineNumberTable:
        line 28: 0
      LocalVariableTable:
        Start  Length  Slot  Name   Signature
            0       7     0  this   Lscala/xml/dtd/DTD;
    Signature: #43                          // ()Lscala/collection/Seq<Lscala/xml/dtd/NotationDecl;>;

  public scala.collection.Seq<scala.xml.dtd.EntityDecl> unparsedEntities();
    descriptor: ()Lscala/collection/Seq;
    flags: (0x0001) ACC_PUBLIC
    Code:
      stack=1, locals=1, args_size=1
         0: getstatic     #49                 // Field scala/package$.MODULE$:Lscala/package$;
         3: invokevirtual #53                 // Method scala/package$.Nil:()Lscala/collection/immutable/Nil$;
         6: areturn
      LineNumberTable:
        line 29: 0
      LocalVariableTable:
        Start  Length  Slot  Name   Signature
            0       7     0  this   Lscala/xml/dtd/DTD;
    Signature: #55                          // ()Lscala/collection/Seq<Lscala/xml/dtd/EntityDecl;>;

  public scala.collection.mutable.Map<java.lang.String, scala.xml.dtd.ElemDecl> elem();
    descriptor: ()Lscala/collection/mutable/Map;
    flags: (0x0001) ACC_PUBLIC
    Code:
      stack=1, locals=1, args_size=1
         0: aload_0
         1: getfield      #59                 // Field elem:Lscala/collection/mutable/Map;
         4: areturn
      LineNumberTable:
        line 31: 0
      LocalVariableTable:
        Start  Length  Slot  Name   Signature
            0       5     0  this   Lscala/xml/dtd/DTD;
    Signature: #57                          // ()Lscala/collection/mutable/Map<Ljava/lang/String;Lscala/xml/dtd/ElemDecl;>;

  public void elem_$eq(scala.collection.mutable.Map<java.lang.String, scala.xml.dtd.ElemDecl>);
    descriptor: (Lscala/collection/mutable/Map;)V
    flags: (0x0001) ACC_PUBLIC
    Code:
      stack=2, locals=2, args_size=2
         0: aload_0
         1: aload_1
         2: putfield      #59                 // Field elem:Lscala/collection/mutable/Map;
         5: return
      LineNumberTable:
        line 31: 0
      LocalVariableTable:
        Start  Length  Slot  Name   Signature
            0       6     0  this   Lscala/xml/dtd/DTD;
            0       6     1   x$1   Lscala/collection/mutable/Map;
    Signature: #62                          // (Lscala/collection/mutable/Map<Ljava/lang/String;Lscala/xml/dtd/ElemDecl;>;)V
    MethodParameters:
      Name                           Flags
      x$1                            final

  public scala.collection.mutable.Map<java.lang.String, scala.xml.dtd.AttListDecl> attr();
    descriptor: ()Lscala/collection/mutable/Map;
    flags: (0x0001) ACC_PUBLIC
    Code:
      stack=1, locals=1, args_size=1
         0: aload_0
         1: getfield      #65                 // Field attr:Lscala/collection/mutable/Map;
         4: areturn
      LineNumberTable:
        line 32: 0
      LocalVariableTable:
        Start  Length  Slot  Name   Signature
            0       5     0  this   Lscala/xml/dtd/DTD;
    Signature: #63                          // ()Lscala/collection/mutable/Map<Ljava/lang/String;Lscala/xml/dtd/AttListDecl;>;

  public void attr_$eq(scala.collection.mutable.Map<java.lang.String, scala.xml.dtd.AttListDecl>);
    descriptor: (Lscala/collection/mutable/Map;)V
    flags: (0x0001) ACC_PUBLIC
    Code:
      stack=2, locals=2, args_size=2
         0: aload_0
         1: aload_1
         2: putfield      #65                 // Field attr:Lscala/collection/mutable/Map;
         5: return
      LineNumberTable:
        line 32: 0
      LocalVariableTable:
        Start  Length  Slot  Name   Signature
            0       6     0  this   Lscala/xml/dtd/DTD;
            0       6     1   x$1   Lscala/collection/mutable/Map;
    Signature: #67                          // (Lscala/collection/mutable/Map<Ljava/lang/String;Lscala/xml/dtd/AttListDecl;>;)V
    MethodParameters:
      Name                           Flags
      x$1                            final

  public scala.collection.mutable.Map<java.lang.String, scala.xml.dtd.EntityDecl> ent();
    descriptor: ()Lscala/collection/mutable/Map;
    flags: (0x0001) ACC_PUBLIC
    Code:
      stack=1, locals=1, args_size=1
         0: aload_0
         1: getfield      #70                 // Field ent:Lscala/collection/mutable/Map;
         4: areturn
      LineNumberTable:
        line 33: 0
      LocalVariableTable:
        Start  Length  Slot  Name   Signature
            0       5     0  this   Lscala/xml/dtd/DTD;
    Signature: #68                          // ()Lscala/collection/mutable/Map<Ljava/lang/String;Lscala/xml/dtd/EntityDecl;>;

  public void ent_$eq(scala.collection.mutable.Map<java.lang.String, scala.xml.dtd.EntityDecl>);
    descriptor: (Lscala/collection/mutable/Map;)V
    flags: (0x0001) ACC_PUBLIC
    Code:
      stack=2, locals=2, args_size=2
         0: aload_0
         1: aload_1
         2: putfield      #70                 // Field ent:Lscala/collection/mutable/Map;
         5: return
      LineNumberTable:
        line 33: 0
      LocalVariableTable:
        Start  Length  Slot  Name   Signature
            0       6     0  this   Lscala/xml/dtd/DTD;
            0       6     1   x$1   Lscala/collection/mutable/Map;
    Signature: #72                          // (Lscala/collection/mutable/Map<Ljava/lang/String;Lscala/xml/dtd/EntityDecl;>;)V
    MethodParameters:
      Name                           Flags
      x$1                            final

  public java.lang.String toString();
    descriptor: ()Ljava/lang/String;
    flags: (0x0001) ACC_PUBLIC
    Code:
      stack=10, locals=1, args_size=1
         0: getstatic     #79                 // Field scala/collection/StringOps$.MODULE$:Lscala/collection/StringOps$;
         3: getstatic     #84                 // Field scala/Predef$.MODULE$:Lscala/Predef$;
         6: ldc           #86                 // String DTD [\n%s%s]
         8: invokevirtual #90                 // Method scala/Predef$.augmentString:(Ljava/lang/String;)Ljava/lang/String;
        11: getstatic     #95                 // Field scala/runtime/ScalaRunTime$.MODULE$:Lscala/runtime/ScalaRunTime$;
        14: iconst_2
        15: anewarray     #4                  // class java/lang/Object
        18: dup
        19: iconst_0
        20: getstatic     #100                // Field scala/Option$.MODULE$:Lscala/Option$;
        23: aload_0
        24: invokevirtual #102                // Method externalID:()Lscala/xml/dtd/ExternalID;
        27: invokevirtual #106                // Method scala/Option$.apply:(Ljava/lang/Object;)Lscala/Option;
        30: invokedynamic #125,  0            // InvokeDynamic #0:apply:()Lscala/Function0;
        35: invokevirtual #131                // Method scala/Option.getOrElse:(Lscala/Function0;)Ljava/lang/Object;
        38: aastore
        39: dup
        40: iconst_1
        41: aload_0
        42: invokevirtual #133                // Method decls:()Lscala/collection/immutable/List;
        45: ldc           #135                // String
        47: ldc           #137                // String \n
        49: ldc           #137                // String \n
        51: invokevirtual #143                // Method scala/collection/immutable/List.mkString:(Ljava/lang/String;Ljava/lang/String;Ljava/lang/String;)Ljava/lang/String;
        54: aastore
        55: invokevirtual #147                // Method scala/runtime/ScalaRunTime$.genericWrapArray:(Ljava/lang/Object;)Lscala/collection/immutable/ArraySeq;
        58: invokevirtual #151                // Method scala/collection/StringOps$.format$extension:(Ljava/lang/String;Lscala/collection/immutable/Seq;)Ljava/lang/String;
        61: areturn
      LineNumberTable:
        line 36: 3
        line 37: 20
        line 38: 41
      LocalVariableTable:
        Start  Length  Slot  Name   Signature
            0      62     0  this   Lscala/xml/dtd/DTD;

  public static final java.lang.String $anonfun$toString$1();
    descriptor: ()Ljava/lang/String;
    flags: (0x1019) ACC_PUBLIC, ACC_STATIC, ACC_FINAL, ACC_SYNTHETIC
    Code:
      stack=1, locals=0, args_size=0
         0: ldc           #135                // String
         2: areturn
      LineNumberTable:
        line 37: 0

  public scala.xml.dtd.DTD();
    descriptor: ()V
    flags: (0x0001) ACC_PUBLIC
    Code:
      stack=3, locals=1, args_size=1
         0: aload_0
         1: invokespecial #155                // Method java/lang/Object."<init>":()V
         4: aload_0
         5: aconst_null
         6: putfield      #28                 // Field externalID:Lscala/xml/dtd/ExternalID;
         9: aload_0
        10: getstatic     #49                 // Field scala/package$.MODULE$:Lscala/package$;
        13: invokevirtual #53                 // Method scala/package$.Nil:()Lscala/collection/immutable/Nil$;
        16: putfield      #37                 // Field decls:Lscala/collection/immutable/List;
        19: aload_0
        20: new           #157                // class scala/collection/mutable/HashMap
        23: dup
        24: invokespecial #158                // Method scala/collection/mutable/HashMap."<init>":()V
        27: putfield      #59                 // Field elem:Lscala/collection/mutable/Map;
        30: aload_0
        31: new           #157                // class scala/collection/mutable/HashMap
        34: dup
        35: invokespecial #158                // Method scala/collection/mutable/HashMap."<init>":()V
        38: putfield      #65                 // Field attr:Lscala/collection/mutable/Map;
        41: aload_0
        42: new           #157                // class scala/collection/mutable/HashMap
        45: dup
        46: invokespecial #158                // Method scala/collection/mutable/HashMap."<init>":()V
        49: putfield      #70                 // Field ent:Lscala/collection/mutable/Map;
        52: return
      LineNumberTable:
        line 40: 0
        line 26: 4
        line 27: 9
        line 31: 19
        line 32: 30
        line 33: 41
        line 25: 52
      LocalVariableTable:
        Start  Length  Slot  Name   Signature
            0      53     0  this   Lscala/xml/dtd/DTD;

  private static java.lang.Object $deserializeLambda$(java.lang.invoke.SerializedLambda);
    descriptor: (Ljava/lang/invoke/SerializedLambda;)Ljava/lang/Object;
    flags: (0x100a) ACC_PRIVATE, ACC_STATIC, ACC_SYNTHETIC
    Code:
      stack=1, locals=1, args_size=1
         0: aload_0
         1: invokedynamic #170,  0            // InvokeDynamic #1:lambdaDeserialize:(Ljava/lang/invoke/SerializedLambda;)Ljava/lang/Object;
         6: areturn
}
InnerClasses:
  public static final #13= #10 of #12;    // Lookup=class java/lang/invoke/MethodHandles$Lookup of class java/lang/invoke/MethodHandles
SourceFile: "DTD.scala"
RuntimeVisibleAnnotations:
  0: #6(#7=s#8)
    scala.reflect.ScalaSignature(
      bytes="\u0006\u0005\u0005\u0005a!\u0002\u000b\u0016\u0003\u0003a\u0002\"B\u0011\u0001\t\u0003\u0011\u0003bB\u0013\u0001\u0001\u0004%\tA\n\u0005\bU\u0001\u0001\r\u0011\"\u0001,\u0011\u0019\t\u0004\u0001)Q\u0005O!9!\u0007\u0001a\u0001\n\u0003\u0019\u0004b\u0002 \u0001\u0001\u0004%\ta\u0010\u0005\u0007\u0003\u0002\u0001\u000b\u0015\u0002\u001b\t\u000b\t\u0003A\u0011A\"\t\u000b5\u0003A\u0011\u0001(\t\u000fM\u0003\u0001\u0019!C\u0001)\"9\u0011\u000e\u0001a\u0001\n\u0003Q\u0007B\u00027\u0001A\u0003&Q\u000bC\u0004n\u0001\u0001\u0007I\u0011\u00018\t\u000fM\u0004\u0001\u0019!C\u0001i\"1a\u000f\u0001Q!\n=Dqa\u001e\u0001A\u0002\u0013\u0005\u0001\u0010C\u0004{\u0001\u0001\u0007I\u0011A>\t\ru\u0004\u0001\u0015)\u0003z\u0011\u0015q\b\u0001\"\u0011\u0000\u0005\r!E\u000b\u0012\u0006\u0003-]\t1\u0001\u001a;e\u0015\tA\u0012$A\u0002y[2T\u0011AG\u0001\u0006g\u000e\fG.Y\u0002\u0001\'\t\u0001Q\u0004\u0005\u0002\u001f?5\t\u0011$\u0003\u0002!3\t1\u0011I\\=SK\u001a\fa\u0001P5oSRtD#A\u0012\u0011\u0005\u0011\u0002Q\"A\u000b\u0002\u0015\u0015DH/\u001a:oC2LE)F\u0001(!\t!\u0003&\u0003\u0002*+\tQQ\t\u001f;fe:\fG.\u0013#\u0002\u001d\u0015DH/\u001a:oC2LEi\u0018\u0013fcR\u0011Af\f\t\u0003=5J!AL\r\u0003\tUs\u0017\u000e\u001e\u0005\ba\r\t\t\u00111\u0001(\u0003\rAH%M\u0001\fKb$XM\u001d8bY&#\u0005%A\u0003eK\u000ed7/F\u00015!\r)\u0004h\u000f\b\u0003=YJ!aN\r\u0002\u000fA\f7m[1hK&\u0011\u0011H\u000f\u0002\u0005\u0019&\u001cHO\u0003\u000283A\u0011A\u0005P\u0005\u0003{U\u0011A\u0001R3dY\u0006IA-Z2mg~#S-\u001d\u000b\u0003Y\u0001Cq\u0001\r\u0004\u0002\u0002\u0003\u0007A\'\u0001\u0004eK\u000ed7\u000fI\u0001\n]>$\u0018\r^5p]N,\u0012\u0001\u0012\t\u0004\u000b\"SU\"\u0001$\u000b\u0005\u001dK\u0012AC2pY2,7\r^5p]&\u0011\u0011J\u0012\u0002\u0004\'\u0016\f\bC\u0001\u0013L\u0013\taUC\u0001\u0007O_R\fG/[8o\t\u0016\u001cG.\u0001\tv]B\f\'o]3e\u000b:$\u0018\u000e^5fgV\tq\nE\u0002F\u0011B\u0003\"\u0001J)\n\u0005I+\"AC#oi&$\u0018\u0010R3dY\u0006!Q\r\\3n+\u0005)\u0006\u0003\u0002,Z7\u001al\u0011a\u0016\u0006\u00031\u001a\u000bq!\\;uC\ndW-\u0003\u0002[/\n\u0019Q*\u00199\u0011\u0005q\u001bgBA/b!\tq\u0016$D\u0001`\u0015\t\u00017$\u0001\u0004=e>|GOP\u0005\u0003Ef\ta\u0001\u0015:fI\u00164\u0017B\u00013f\u0005\u0019\u0019FO]5oO*\u0011!-\u0007\t\u0003I\u001dL!\u0001[\u000b\u0003\u0011\u0015cW-\u001c#fG2\f\u0001\"\u001a7f[~#S-\u001d\u000b\u0003Y-Dq\u0001M\u0006\u0002\u0002\u0003\u0007Q+A\u0003fY\u0016l\u0007%\u0001\u0003biR\u0014X#A8\u0011\tYK6\f\u001d\t\u0003IEL!A]\u000b\u0003\u0017\u0005#H\u000fT5ti\u0012+7\r\\\u0001\tCR$(o\u0018\u0013fcR\u0011A&\u001e\u0005\ba9\t\t\u00111\u0001p\u0003\u0015\tG\u000f\u001e:!\u0003\r)g\u000e^\u000b\u0002sB!a+W.Q\u0003\u001d)g\u000e^0%KF$\"\u0001\f?\t\u000fA\n\u0012\u0011!a\u0001s\u0006!QM\u001c;!\u0003!!xn\u0015;sS:<G#A."
    )
BootstrapMethods:
  0: #122 REF_invokeStatic java/lang/invoke/LambdaMetafactory.altMetafactory:(Ljava/lang/invoke/MethodHandles$Lookup;Ljava/lang/String;Ljava/lang/invoke/MethodType;[Ljava/lang/Object;)Ljava/lang/invoke/CallSite;
    Method arguments:
      #108 ()Ljava/lang/Object;
      #112 REF_invokeStatic scala/xml/dtd/DTD.$anonfun$toString$1:()Ljava/lang/String;
      #113 ()Ljava/lang/String;
      #114 5
      #115 1
      #113 ()Ljava/lang/String;
  1: #167 REF_invokeStatic scala/runtime/LambdaDeserialize.bootstrap:(Ljava/lang/invoke/MethodHandles$Lookup;Ljava/lang/String;Ljava/lang/invoke/MethodType;[Ljava/lang/invoke/MethodHandle;)Ljava/lang/invoke/CallSite;
    Method arguments:
      #112 REF_invokeStatic scala/xml/dtd/DTD.$anonfun$toString$1:()Ljava/lang/String;
  ScalaInlineInfo: length = 0x4F (unknown attribute)
   01 00 00 0F 00 6D 00 4A 01 00 98 00 99 00 00 16
   00 38 00 00 42 00 3D 00 00 10 00 22 00 00 26 00
   27 00 00 13 00 38 00 00 3C 00 3D 00 00 18 00 38
   00 00 47 00 3D 00 00 0E 00 1A 00 00 1F 00 20 00
   00 29 00 2A 00 00 49 00 4A 00 00 36 00 2A 00
  ScalaSig: length = 0x3 (unknown attribute)
   05 02 00
