Classfile /Users/mw/Projects/slang-braindump/.jar/jar8/assemble/slang-braindump/assemble/content/scala/xml/dtd/MakeValidationException.class
  Last modified May 29, 2022; size 2122 bytes
  SHA-256 checksum c1ac379f8756df66b077c37e7e6cd31441c2ece4fb44f4c8effca2e2e23a1764
  Compiled from "ValidationException.scala"
public final class scala.xml.dtd.MakeValidationException
  minor version: 0
  major version: 52
  flags: (0x0031) ACC_PUBLIC, ACC_FINAL, ACC_SUPER
  this_class: #2                          // scala/xml/dtd/MakeValidationException
  super_class: #4                         // java/lang/Object
  interfaces: 0, fields: 0, methods: 6, attributes: 3
Constant pool:
   #1 = Utf8               scala/xml/dtd/MakeValidationException
   #2 = Class              #1             // scala/xml/dtd/MakeValidationException
   #3 = Utf8               java/lang/Object
   #4 = Class              #3             // java/lang/Object
   #5 = Utf8               ValidationException.scala
   #6 = Utf8               Lscala/reflect/ScalaSignature;
   #7 = Utf8               bytes
   #8 = Utf8               \u0006\u0005\u0019;Q!\u0003\u0006\t\u0002E1Qa\u0005\u0006\t\u0002QAQ!G\u0001\u0005\u0002iAQaG\u0001\u0005\u0002qAQ!M\u0001\u0005\u0002IBQaM\u0001\u0005\u0002QBQaN\u0001\u0005\u0002aBQaO\u0001\u0005\u0002qBQaO\u0001\u0005\u0002\t\u000bq#T1lKZ\u000bG.\u001b3bi&|g.\u0012=dKB$\u0018n\u001c8\u000b\u0005-a\u0011a\u00013uI*\u0011QBD\u0001\u0004q6d\'\"A\b\u0002\u000bM\u001c\u0017\r\\1\u0004\u0001A\u0011!#A\u0007\u0002\u0015\t9R*Y6f-\u0006d\u0017\u000eZ1uS>tW\t_2faRLwN\\\n\u0003\u0003U\u0001\"AF\f\u000e\u00039I!\u0001\u0007\b\u0003\r\u0005s\u0017PU3g\u0003\u0019a\u0014N\\5u}Q\t\u0011#\u0001\nge>lg)\u001b=fI\u0006#HO]5ckR,G\u0003B\u000f![=\u0002\"A\u0005\u0010\n\u0005}Q!a\u0005,bY&$\u0017\r^5p]\u0016C8-\u001a9uS>t\u0007\"B\u0011\u0004\u0001\u0004\u0011\u0013!A6\u0011\u0005\rRcB\u0001\u0013)!\t)c\"D\u0001\'\u0015\t9\u0003#\u0001\u0004=e>|GOP\u0005\u0003S9\ta\u0001\u0015:fI\u00164\u0017BA\u0016-\u0005\u0019\u0019FO]5oO*\u0011\u0011F\u0004\u0005\u0006]\r\u0001\rAI\u0001\u0006m\u0006dW/\u001a\u0005\u0006a\r\u0001\rAI\u0001\u0007C\u000e$X/\u00197\u0002\'\u0019\u0014x.\u001c(p]\u0016k\u0007\u000f^=FY\u0016lWM\u001c;\u0015\u0003u\tAC\u001a:p[VsG-\u001a4j]\u0016$W\t\\3nK:$HCA\u000f6\u0011\u00151T\u00011\u0001#\u0003\u0015a\u0017MY3m\u0003Y1\'o\\7V]\u0012,g-\u001b8fI\u0006#HO]5ckR,GCA\u000f:\u0011\u0015Qd\u00011\u0001#\u0003\rYW-_\u0001\u0015MJ|W.T5tg&tw-\u0011;ue&\u0014W\u000f^3\u0015\u0005ui\u0004\"\u0002 \b\u0001\u0004y\u0014aB1mY.+\u0017p\u001d\t\u0004G\u0001\u0013\u0013BA!-\u0005\r\u0019V\r\u001e\u000b\u0004;\r#\u0005\"\u0002\u001e\t\u0001\u0004\u0011\u0003\"B#\t\u0001\u0004\u0011\u0013a\u0001;qK\u0002
   #9 = Utf8               fromMissingAttribute
  #10 = Utf8               (Ljava/lang/String;Ljava/lang/String;)Lscala/xml/dtd/ValidationException;
  #11 = Utf8               key
  #12 = Utf8               tpe
  #13 = Utf8               scala/xml/dtd/MakeValidationException$
  #14 = Class              #13            // scala/xml/dtd/MakeValidationException$
  #15 = Utf8               MODULE$
  #16 = Utf8               Lscala/xml/dtd/MakeValidationException$;
  #17 = NameAndType        #15:#16        // MODULE$:Lscala/xml/dtd/MakeValidationException$;
  #18 = Fieldref           #14.#17        // scala/xml/dtd/MakeValidationException$.MODULE$:Lscala/xml/dtd/MakeValidationException$;
  #19 = NameAndType        #9:#10         // fromMissingAttribute:(Ljava/lang/String;Ljava/lang/String;)Lscala/xml/dtd/ValidationException;
  #20 = Methodref          #14.#19        // scala/xml/dtd/MakeValidationException$.fromMissingAttribute:(Ljava/lang/String;Ljava/lang/String;)Lscala/xml/dtd/ValidationException;
  #21 = Utf8               Ljava/lang/String;
  #22 = Utf8               (Lscala/collection/immutable/Set;)Lscala/xml/dtd/ValidationException;
  #23 = Utf8               (Lscala/collection/immutable/Set<Ljava/lang/String;>;)Lscala/xml/dtd/ValidationException;
  #24 = Utf8               allKeys
  #25 = NameAndType        #9:#22         // fromMissingAttribute:(Lscala/collection/immutable/Set;)Lscala/xml/dtd/ValidationException;
  #26 = Methodref          #14.#25        // scala/xml/dtd/MakeValidationException$.fromMissingAttribute:(Lscala/collection/immutable/Set;)Lscala/xml/dtd/ValidationException;
  #27 = Utf8               Lscala/collection/immutable/Set;
  #28 = Utf8               fromUndefinedAttribute
  #29 = Utf8               (Ljava/lang/String;)Lscala/xml/dtd/ValidationException;
  #30 = NameAndType        #28:#29        // fromUndefinedAttribute:(Ljava/lang/String;)Lscala/xml/dtd/ValidationException;
  #31 = Methodref          #14.#30        // scala/xml/dtd/MakeValidationException$.fromUndefinedAttribute:(Ljava/lang/String;)Lscala/xml/dtd/ValidationException;
  #32 = Utf8               fromUndefinedElement
  #33 = Utf8               label
  #34 = NameAndType        #32:#29        // fromUndefinedElement:(Ljava/lang/String;)Lscala/xml/dtd/ValidationException;
  #35 = Methodref          #14.#34        // scala/xml/dtd/MakeValidationException$.fromUndefinedElement:(Ljava/lang/String;)Lscala/xml/dtd/ValidationException;
  #36 = Utf8               fromNonEmptyElement
  #37 = Utf8               ()Lscala/xml/dtd/ValidationException;
  #38 = NameAndType        #36:#37        // fromNonEmptyElement:()Lscala/xml/dtd/ValidationException;
  #39 = Methodref          #14.#38        // scala/xml/dtd/MakeValidationException$.fromNonEmptyElement:()Lscala/xml/dtd/ValidationException;
  #40 = Utf8               fromFixedAttribute
  #41 = Utf8               (Ljava/lang/String;Ljava/lang/String;Ljava/lang/String;)Lscala/xml/dtd/ValidationException;
  #42 = Utf8               k
  #43 = Utf8               value
  #44 = Utf8               actual
  #45 = NameAndType        #40:#41        // fromFixedAttribute:(Ljava/lang/String;Ljava/lang/String;Ljava/lang/String;)Lscala/xml/dtd/ValidationException;
  #46 = Methodref          #14.#45        // scala/xml/dtd/MakeValidationException$.fromFixedAttribute:(Ljava/lang/String;Ljava/lang/String;Ljava/lang/String;)Lscala/xml/dtd/ValidationException;
  #47 = Utf8               Code
  #48 = Utf8               LocalVariableTable
  #49 = Utf8               MethodParameters
  #50 = Utf8               Signature
  #51 = Utf8               SourceFile
  #52 = Utf8               RuntimeVisibleAnnotations
  #53 = Utf8               ScalaSig
{
  public static scala.xml.dtd.ValidationException fromMissingAttribute(java.lang.String, java.lang.String);
    descriptor: (Ljava/lang/String;Ljava/lang/String;)Lscala/xml/dtd/ValidationException;
    flags: (0x0009) ACC_PUBLIC, ACC_STATIC
    Code:
      stack=3, locals=2, args_size=2
         0: getstatic     #18                 // Field scala/xml/dtd/MakeValidationException$.MODULE$:Lscala/xml/dtd/MakeValidationException$;
         3: aload_0
         4: aload_1
         5: invokevirtual #20                 // Method scala/xml/dtd/MakeValidationException$.fromMissingAttribute:(Ljava/lang/String;Ljava/lang/String;)Lscala/xml/dtd/ValidationException;
         8: areturn
      LocalVariableTable:
        Start  Length  Slot  Name   Signature
            0       9     0   key   Ljava/lang/String;
            0       9     1   tpe   Ljava/lang/String;
    MethodParameters:
      Name                           Flags
      key                            final
      tpe                            final

  public static scala.xml.dtd.ValidationException fromMissingAttribute(scala.collection.immutable.Set<java.lang.String>);
    descriptor: (Lscala/collection/immutable/Set;)Lscala/xml/dtd/ValidationException;
    flags: (0x0009) ACC_PUBLIC, ACC_STATIC
    Code:
      stack=2, locals=1, args_size=1
         0: getstatic     #18                 // Field scala/xml/dtd/MakeValidationException$.MODULE$:Lscala/xml/dtd/MakeValidationException$;
         3: aload_0
         4: invokevirtual #26                 // Method scala/xml/dtd/MakeValidationException$.fromMissingAttribute:(Lscala/collection/immutable/Set;)Lscala/xml/dtd/ValidationException;
         7: areturn
      LocalVariableTable:
        Start  Length  Slot  Name   Signature
            0       8     0 allKeys   Lscala/collection/immutable/Set;
    Signature: #23                          // (Lscala/collection/immutable/Set<Ljava/lang/String;>;)Lscala/xml/dtd/ValidationException;
    MethodParameters:
      Name                           Flags
      allKeys                        final

  public static scala.xml.dtd.ValidationException fromUndefinedAttribute(java.lang.String);
    descriptor: (Ljava/lang/String;)Lscala/xml/dtd/ValidationException;
    flags: (0x0009) ACC_PUBLIC, ACC_STATIC
    Code:
      stack=2, locals=1, args_size=1
         0: getstatic     #18                 // Field scala/xml/dtd/MakeValidationException$.MODULE$:Lscala/xml/dtd/MakeValidationException$;
         3: aload_0
         4: invokevirtual #31                 // Method scala/xml/dtd/MakeValidationException$.fromUndefinedAttribute:(Ljava/lang/String;)Lscala/xml/dtd/ValidationException;
         7: areturn
      LocalVariableTable:
        Start  Length  Slot  Name   Signature
            0       8     0   key   Ljava/lang/String;
    MethodParameters:
      Name                           Flags
      key                            final

  public static scala.xml.dtd.ValidationException fromUndefinedElement(java.lang.String);
    descriptor: (Ljava/lang/String;)Lscala/xml/dtd/ValidationException;
    flags: (0x0009) ACC_PUBLIC, ACC_STATIC
    Code:
      stack=2, locals=1, args_size=1
         0: getstatic     #18                 // Field scala/xml/dtd/MakeValidationException$.MODULE$:Lscala/xml/dtd/MakeValidationException$;
         3: aload_0
         4: invokevirtual #35                 // Method scala/xml/dtd/MakeValidationException$.fromUndefinedElement:(Ljava/lang/String;)Lscala/xml/dtd/ValidationException;
         7: areturn
      LocalVariableTable:
        Start  Length  Slot  Name   Signature
            0       8     0 label   Ljava/lang/String;
    MethodParameters:
      Name                           Flags
      label                          final

  public static scala.xml.dtd.ValidationException fromNonEmptyElement();
    descriptor: ()Lscala/xml/dtd/ValidationException;
    flags: (0x0009) ACC_PUBLIC, ACC_STATIC
    Code:
      stack=1, locals=0, args_size=0
         0: getstatic     #18                 // Field scala/xml/dtd/MakeValidationException$.MODULE$:Lscala/xml/dtd/MakeValidationException$;
         3: invokevirtual #39                 // Method scala/xml/dtd/MakeValidationException$.fromNonEmptyElement:()Lscala/xml/dtd/ValidationException;
         6: areturn

  public static scala.xml.dtd.ValidationException fromFixedAttribute(java.lang.String, java.lang.String, java.lang.String);
    descriptor: (Ljava/lang/String;Ljava/lang/String;Ljava/lang/String;)Lscala/xml/dtd/ValidationException;
    flags: (0x0009) ACC_PUBLIC, ACC_STATIC
    Code:
      stack=4, locals=3, args_size=3
         0: getstatic     #18                 // Field scala/xml/dtd/MakeValidationException$.MODULE$:Lscala/xml/dtd/MakeValidationException$;
         3: aload_0
         4: aload_1
         5: aload_2
         6: invokevirtual #46                 // Method scala/xml/dtd/MakeValidationException$.fromFixedAttribute:(Ljava/lang/String;Ljava/lang/String;Ljava/lang/String;)Lscala/xml/dtd/ValidationException;
         9: areturn
      LocalVariableTable:
        Start  Length  Slot  Name   Signature
            0      10     0     k   Ljava/lang/String;
            0      10     1 value   Ljava/lang/String;
            0      10     2 actual   Ljava/lang/String;
    MethodParameters:
      Name                           Flags
      k                              final
      value                          final
      actual                         final
}
SourceFile: "ValidationException.scala"
RuntimeVisibleAnnotations:
  0: #6(#7=s#8)
    scala.reflect.ScalaSignature(
      bytes="\u0006\u0005\u0019;Q!\u0003\u0006\t\u0002E1Qa\u0005\u0006\t\u0002QAQ!G\u0001\u0005\u0002iAQaG\u0001\u0005\u0002qAQ!M\u0001\u0005\u0002IBQaM\u0001\u0005\u0002QBQaN\u0001\u0005\u0002aBQaO\u0001\u0005\u0002qBQaO\u0001\u0005\u0002\t\u000bq#T1lKZ\u000bG.\u001b3bi&|g.\u0012=dKB$\u0018n\u001c8\u000b\u0005-a\u0011a\u00013uI*\u0011QBD\u0001\u0004q6d\'\"A\b\u0002\u000bM\u001c\u0017\r\\1\u0004\u0001A\u0011!#A\u0007\u0002\u0015\t9R*Y6f-\u0006d\u0017\u000eZ1uS>tW\t_2faRLwN\\\n\u0003\u0003U\u0001\"AF\f\u000e\u00039I!\u0001\u0007\b\u0003\r\u0005s\u0017PU3g\u0003\u0019a\u0014N\\5u}Q\t\u0011#\u0001\nge>lg)\u001b=fI\u0006#HO]5ckR,G\u0003B\u000f![=\u0002\"A\u0005\u0010\n\u0005}Q!a\u0005,bY&$\u0017\r^5p]\u0016C8-\u001a9uS>t\u0007\"B\u0011\u0004\u0001\u0004\u0011\u0013!A6\u0011\u0005\rRcB\u0001\u0013)!\t)c\"D\u0001\'\u0015\t9\u0003#\u0001\u0004=e>|GOP\u0005\u0003S9\ta\u0001\u0015:fI\u00164\u0017BA\u0016-\u0005\u0019\u0019FO]5oO*\u0011\u0011F\u0004\u0005\u0006]\r\u0001\rAI\u0001\u0006m\u0006dW/\u001a\u0005\u0006a\r\u0001\rAI\u0001\u0007C\u000e$X/\u00197\u0002\'\u0019\u0014x.\u001c(p]\u0016k\u0007\u000f^=FY\u0016lWM\u001c;\u0015\u0003u\tAC\u001a:p[VsG-\u001a4j]\u0016$W\t\\3nK:$HCA\u000f6\u0011\u00151T\u00011\u0001#\u0003\u0015a\u0017MY3m\u0003Y1\'o\\7V]\u0012,g-\u001b8fI\u0006#HO]5ckR,GCA\u000f:\u0011\u0015Qd\u00011\u0001#\u0003\rYW-_\u0001\u0015MJ|W.T5tg&tw-\u0011;ue&\u0014W\u000f^3\u0015\u0005ui\u0004\"\u0002 \b\u0001\u0004y\u0014aB1mY.+\u0017p\u001d\t\u0004G\u0001\u0013\u0013BA!-\u0005\r\u0019V\r\u001e\u000b\u0004;\r#\u0005\"\u0002\u001e\t\u0001\u0004\u0011\u0003\"B#\t\u0001\u0004\u0011\u0013a\u0001;qK\u0002"
    )
  ScalaSig: length = 0x3 (unknown attribute)
   05 02 00
