Classfile /Users/mw/Projects/slang-braindump/.jar/jar8/assemble/slang-braindump/assemble/content/scala/xml/dtd/MIXED.class
  Last modified May 29, 2022; size 6404 bytes
  SHA-256 checksum 91e57f12105ba37de5087900155c176e2a954803da72835027267efad9a010f4
  Compiled from "ContentModel.scala"
public class scala.xml.dtd.MIXED extends scala.xml.dtd.DFAContentModel implements scala.Product,java.io.Serializable
  minor version: 0
  major version: 52
  flags: (0x0021) ACC_PUBLIC, ACC_SUPER
  this_class: #2                          // scala/xml/dtd/MIXED
  super_class: #4                         // scala/xml/dtd/DFAContentModel
  interfaces: 2, fields: 1, methods: 18, attributes: 5
Constant pool:
    #1 = Utf8               scala/xml/dtd/MIXED
    #2 = Class              #1            // scala/xml/dtd/MIXED
    #3 = Utf8               scala/xml/dtd/DFAContentModel
    #4 = Class              #3            // scala/xml/dtd/DFAContentModel
    #5 = Utf8               scala/Product
    #6 = Class              #5            // scala/Product
    #7 = Utf8               java/io/Serializable
    #8 = Class              #7            // java/io/Serializable
    #9 = Utf8               ContentModel.scala
   #10 = Utf8               Lscala/reflect/ScalaSignature;
   #11 = Utf8               bytes
   #12 = Utf8               \u0006\u0005\u0005=c\u0001\u0002\f\u0018\u0001zA\u0001b\r\u0001\u0003\u0016\u0004%\t\u0001\u000e\u0005\t\u007f\u0001\u0011\t\u0012)A\u0005k!)\u0001\t\u0001C\u0001\u0003\")A\t\u0001C!\u000b\"9A\nAA\u0001\n\u0003i\u0005bB(\u0001#\u0003%\t\u0001\u0015\u0005\b7\u0002\t\t\u0011\"\u0011]\u0011\u001d)\u0007!!A\u0005\u0002\u0019DqA\u001b\u0001\u0002\u0002\u0013\u00051\u000eC\u0004r\u0001\u0005\u0005I\u0011\t:\t\u000fe\u0004\u0011\u0011!C\u0001u\"Aq\u0010AA\u0001\n\u0003\n\t\u0001C\u0005\u0002\u0006\u0001\t\t\u0011\"\u0011\u0002\b!I\u0011\u0011\u0002\u0001\u0002\u0002\u0013\u0005\u00131B\u0004\n\u0003\u001f9\u0012\u0011!E\u0001\u0003#1\u0001BF\f\u0002\u0002#\u0005\u00111\u0003\u0005\u0007\u0001B!\t!a\u000b\t\u0013\u00055\u0002#!A\u0005F\u0005=\u0002\"CA\u0019!\u0005\u0005I\u0011QA\u001a\u0011%\t9\u0004EA\u0001\n\u0003\u000bI\u0004C\u0005\u0002FA\t\t\u0011\"\u0003\u0002H\t)Q*\u0013-F\t*\u0011\u0001$G\u0001\u0004IR$\'B\u0001\u000e\u001c\u0003\rAX\u000e\u001c\u0006\u00029\u0005)1oY1mC\u000e\u00011\u0003\u0002\u0001 G\u001d\u0002\"\u0001I\u0011\u000e\u0003]I!AI\f\u0003\u001f\u00113\u0015iQ8oi\u0016tG/T8eK2\u0004\"\u0001J\u0013\u000e\u0003mI!AJ\u000e\u0003\u000fA\u0013x\u000eZ;diB\u0011\u0001\u0006\r\b\u0003S9r!AK\u0017\u000e\u0003-R!\u0001L\u000f\u0002\rq\u0012xn\u001c;?\u0013\u0005a\u0012BA\u0018\u001c\u0003\u001d\u0001\u0018mY6bO\u0016L!!\r\u001a\u0003\u0019M+\'/[1mSj\f\'\r\\3\u000b\u0005=Z\u0012!\u0001:\u0016\u0003U\u0002\"AN\u001d\u000f\u0005\u0001:\u0014B\u0001\u001d\u0018\u00031\u0019uN\u001c;f]Rlu\u000eZ3m\u0013\tQ4H\u0001\u0004SK\u001e,\u0005\u0010]\u0005\u0003yu\u0012AAQ1tK*\u0011ahF\u0001\u0005S6\u0004H.\u0001\u0002sA\u00051A(\u001b8jiz\"\"AQ\"\u0011\u0005\u0001\u0002\u0001\"B\u001a\u0004\u0001\u0004)\u0014a\u00032vS2$7\u000b\u001e:j]\u001e$\"A\u0012&\u0011\u0005\u001dCeB\u0001\u0013/\u0013\tI%GA\u0007TiJLgn\u001a\"vS2$WM\u001d\u0005\u0006\u0017\u0012\u0001\rAR\u0001\u0003g\n\fAaY8qsR\u0011!I\u0014\u0005\bg\u0015\u0001\n\u00111\u00016\u00039\u0019w\u000e]=%I\u00164\u0017-\u001e7uIE*\u0012!\u0015\u0016\u0003kI[\u0013a\u0015\t\u0003)fk\u0011!\u0016\u0006\u0003-^\u000b\u0011\"\u001e8dQ\u0016\u001c7.\u001a3\u000b\u0005a[\u0012AC1o]>$\u0018\r^5p]&\u0011!,\u0016\u0002\u0012k:\u001c\u0007.Z2lK\u00124\u0016M]5b]\u000e,\u0017!\u00049s_\u0012,8\r\u001e)sK\u001aL\u00070F\u0001^!\tq6-D\u0001`\u0015\t\u0001\u0017-\u0001\u0003mC:<\'\"\u00012\u0002\t)\fg/Y\u0005\u0003I~\u0013aa\u0015;sS:<\u0017\u0001\u00049s_\u0012,8\r^!sSRLX#A4\u0011\u0005\u0011B\u0017BA5\u001c\u0005\rIe\u000e^\u0001\u000faJ|G-^2u\u000b2,W.\u001a8u)\taw\u000e\u0005\u0002%[&\u0011an\u0007\u0002\u0004\u0003:L\bb\u00029\n\u0003\u0003\u0005\raZ\u0001\u0004q\u0012\n\u0014a\u00049s_\u0012,8\r^%uKJ\fGo\u001c:\u0016\u0003M\u00042\u0001^<m\u001b\u0005)(B\u0001<\u001c\u0003)\u0019w\u000e\u001c7fGRLwN\\\u0005\u0003qV\u0014\u0001\"\u0013;fe\u0006$xN]\u0001\tG\u0006tW)];bYR\u00111P \t\u0003IqL!!`\u000e\u0003\u000f\t{w\u000e\\3b]\"9\u0001oCA\u0001\u0002\u0004a\u0017A\u00059s_\u0012,8\r^#mK6,g\u000e\u001e(b[\u0016$2!XA\u0002\u0011\u001d\u0001H\"!AA\u0002\u001d\f\u0001\u0002[1tQ\u000e{G-\u001a\u000b\u0002O\u00061Q-];bYN$2a_A\u0007\u0011\u001d\u0001h\"!AA\u00021\fQ!T%Y\u000b\u0012\u0003\"\u0001\t\t\u0014\u000bA\t)\"!\t\u0011\r\u0005]\u0011QD\u001bC\u001b\t\tIBC\u0002\u0002\u001cm\tqA];oi&lW-\u0003\u0003\u0002 \u0005e!!E!cgR\u0014\u0018m\u0019;Gk:\u001cG/[8ocA!\u00111EA\u0015\u001b\t\t)CC\u0002\u0002(\u0005\f!![8\n\u0007E\n)\u0003\u0006\u0002\u0002\u0012\u0005AAo\\*ue&tw\rF\u0001^\u0003\u0015\t\u0007\u000f\u001d7z)\r\u0011\u0015Q\u0007\u0005\u0006gM\u0001\r!N\u0001\bk:\f\u0007\u000f\u001d7z)\u0011\tY$!\u0011\u0011\t\u0011\ni$N\u0005\u0004\u0003\u007fY\"AB(qi&|g\u000e\u0003\u0005\u0002DQ\t\t\u00111\u0001C\u0003\rAH\u0005M\u0001\roJLG/\u001a*fa2\f7-\u001a\u000b\u0003\u0003\u0013\u00022AXA&\u0013\r\tie\u0018\u0002\u0007\u001f\nTWm\u0019;
   #13 = Utf8               scala/xml/dtd/impl/Base$Alt
   #14 = Class              #13           // scala/xml/dtd/impl/Base$Alt
   #15 = Utf8               scala/xml/dtd/impl/Base
   #16 = Class              #15           // scala/xml/dtd/impl/Base
   #17 = Utf8               Alt
   #18 = Utf8               scala/xml/dtd/impl/Base$Alt$
   #19 = Class              #18           // scala/xml/dtd/impl/Base$Alt$
   #20 = Utf8               Alt$
   #21 = Utf8               scala/xml/dtd/impl/Base$RegExp
   #22 = Class              #21           // scala/xml/dtd/impl/Base$RegExp
   #23 = Utf8               RegExp
   #24 = Utf8               r
   #25 = Utf8               Lscala/xml/dtd/impl/Base$RegExp;
   #26 = Utf8               unapply
   #27 = Utf8               (Lscala/xml/dtd/MIXED;)Lscala/Option;
   #28 = Utf8               (Lscala/xml/dtd/MIXED;)Lscala/Option<Lscala/xml/dtd/impl/Base$RegExp;>;
   #29 = Utf8               x$0
   #30 = Utf8               scala/xml/dtd/MIXED$
   #31 = Class              #30           // scala/xml/dtd/MIXED$
   #32 = Utf8               MODULE$
   #33 = Utf8               Lscala/xml/dtd/MIXED$;
   #34 = NameAndType        #32:#33       // MODULE$:Lscala/xml/dtd/MIXED$;
   #35 = Fieldref           #31.#34       // scala/xml/dtd/MIXED$.MODULE$:Lscala/xml/dtd/MIXED$;
   #36 = NameAndType        #26:#27       // unapply:(Lscala/xml/dtd/MIXED;)Lscala/Option;
   #37 = Methodref          #31.#36       // scala/xml/dtd/MIXED$.unapply:(Lscala/xml/dtd/MIXED;)Lscala/Option;
   #38 = Utf8               Lscala/xml/dtd/MIXED;
   #39 = Utf8               apply
   #40 = Utf8               (Lscala/xml/dtd/impl/Base$RegExp;)Lscala/xml/dtd/MIXED;
   #41 = NameAndType        #39:#40       // apply:(Lscala/xml/dtd/impl/Base$RegExp;)Lscala/xml/dtd/MIXED;
   #42 = Methodref          #31.#41       // scala/xml/dtd/MIXED$.apply:(Lscala/xml/dtd/impl/Base$RegExp;)Lscala/xml/dtd/MIXED;
   #43 = Utf8               andThen
   #44 = Utf8               (Lscala/Function1;)Lscala/Function1;
   #45 = Utf8               <A$:Ljava/lang/Object;>(Lscala/Function1<Lscala/xml/dtd/MIXED;TA$;>;)Lscala/Function1<Lscala/xml/dtd/impl/Base$RegExp;TA$;>;
   #46 = Utf8               g
   #47 = NameAndType        #43:#44       // andThen:(Lscala/Function1;)Lscala/Function1;
   #48 = Methodref          #31.#47       // scala/xml/dtd/MIXED$.andThen:(Lscala/Function1;)Lscala/Function1;
   #49 = Utf8               Lscala/Function1;
   #50 = Utf8               compose
   #51 = Utf8               <A$:Ljava/lang/Object;>(Lscala/Function1<TA$;Lscala/xml/dtd/impl/Base$RegExp;>;)Lscala/Function1<TA$;Lscala/xml/dtd/MIXED;>;
   #52 = NameAndType        #50:#44       // compose:(Lscala/Function1;)Lscala/Function1;
   #53 = Methodref          #31.#52       // scala/xml/dtd/MIXED$.compose:(Lscala/Function1;)Lscala/Function1;
   #54 = Utf8               productElementNames
   #55 = Utf8               ()Lscala/collection/Iterator;
   #56 = Utf8               ()Lscala/collection/Iterator<Ljava/lang/String;>;
   #57 = Utf8               productElementNames$
   #58 = Utf8               (Lscala/Product;)Lscala/collection/Iterator;
   #59 = NameAndType        #57:#58       // productElementNames$:(Lscala/Product;)Lscala/collection/Iterator;
   #60 = InterfaceMethodref #6.#59        // scala/Product.productElementNames$:(Lscala/Product;)Lscala/collection/Iterator;
   #61 = Utf8               this
   #62 = Utf8               ()Lscala/xml/dtd/impl/Base$RegExp;
   #63 = NameAndType        #24:#25       // r:Lscala/xml/dtd/impl/Base$RegExp;
   #64 = Fieldref           #2.#63        // scala/xml/dtd/MIXED.r:Lscala/xml/dtd/impl/Base$RegExp;
   #65 = Utf8               buildString
   #66 = Utf8               (Lscala/collection/mutable/StringBuilder;)Lscala/collection/mutable/StringBuilder;
   #67 = Utf8               sb
   #68 = NameAndType        #24:#62       // r:()Lscala/xml/dtd/impl/Base$RegExp;
   #69 = Methodref          #2.#68        // scala/xml/dtd/MIXED.r:()Lscala/xml/dtd/impl/Base$RegExp;
   #70 = Utf8               scala/xml/dtd/ContentModel$
   #71 = Class              #70           // scala/xml/dtd/ContentModel$
   #72 = Utf8               Lscala/xml/dtd/ContentModel$;
   #73 = NameAndType        #32:#72       // MODULE$:Lscala/xml/dtd/ContentModel$;
   #74 = Fieldref           #71.#73       // scala/xml/dtd/ContentModel$.MODULE$:Lscala/xml/dtd/ContentModel$;
   #75 = Utf8               ()Lscala/xml/dtd/impl/Base$Alt$;
   #76 = NameAndType        #17:#75       // Alt:()Lscala/xml/dtd/impl/Base$Alt$;
   #77 = Methodref          #71.#76       // scala/xml/dtd/ContentModel$.Alt:()Lscala/xml/dtd/impl/Base$Alt$;
   #78 = Utf8               unapplySeq
   #79 = Utf8               (Lscala/xml/dtd/impl/Base$Alt;)Lscala/Some;
   #80 = NameAndType        #78:#79       // unapplySeq:(Lscala/xml/dtd/impl/Base$Alt;)Lscala/Some;
   #81 = Methodref          #19.#80       // scala/xml/dtd/impl/Base$Alt$.unapplySeq:(Lscala/xml/dtd/impl/Base$Alt;)Lscala/Some;
   #82 = Utf8               scala/Some
   #83 = Class              #82           // scala/Some
   #84 = Utf8               isEmpty
   #85 = Utf8               ()Z
   #86 = NameAndType        #84:#85       // isEmpty:()Z
   #87 = Methodref          #83.#86       // scala/Some.isEmpty:()Z
   #88 = Utf8               get
   #89 = Utf8               ()Ljava/lang/Object;
   #90 = NameAndType        #88:#89       // get:()Ljava/lang/Object;
   #91 = Methodref          #83.#90       // scala/Some.get:()Ljava/lang/Object;
   #92 = Utf8               scala/collection/immutable/Seq
   #93 = Class              #92           // scala/collection/immutable/Seq
   #94 = Utf8               drop
   #95 = Utf8               (I)Ljava/lang/Object;
   #96 = NameAndType        #94:#95       // drop:(I)Ljava/lang/Object;
   #97 = InterfaceMethodref #93.#96       // scala/collection/immutable/Seq.drop:(I)Ljava/lang/Object;
   #98 = Utf8               (Lscala/collection/immutable/Seq;)Lscala/xml/dtd/impl/Base$Alt;
   #99 = NameAndType        #39:#98       // apply:(Lscala/collection/immutable/Seq;)Lscala/xml/dtd/impl/Base$Alt;
  #100 = Methodref          #19.#99       // scala/xml/dtd/impl/Base$Alt$.apply:(Lscala/collection/immutable/Seq;)Lscala/xml/dtd/impl/Base$Alt;
  #101 = Utf8               scala/MatchError
  #102 = Class              #101          // scala/MatchError
  #103 = Utf8               <init>
  #104 = Utf8               (Ljava/lang/Object;)V
  #105 = NameAndType        #103:#104     // "<init>":(Ljava/lang/Object;)V
  #106 = Methodref          #102.#105     // scala/MatchError."<init>":(Ljava/lang/Object;)V
  #107 = Utf8               (#PCDATA|
  #108 = String             #107          // (#PCDATA|
  #109 = Utf8               scala/collection/mutable/StringBuilder
  #110 = Class              #109          // scala/collection/mutable/StringBuilder
  #111 = Utf8               append
  #112 = Utf8               (Ljava/lang/String;)Lscala/collection/mutable/StringBuilder;
  #113 = NameAndType        #111:#112     // append:(Ljava/lang/String;)Lscala/collection/mutable/StringBuilder;
  #114 = Methodref          #110.#113     // scala/collection/mutable/StringBuilder.append:(Ljava/lang/String;)Lscala/collection/mutable/StringBuilder;
  #115 = Utf8               (Lscala/xml/dtd/impl/Base$RegExp;Lscala/collection/mutable/StringBuilder;)Lscala/collection/mutable/StringBuilder;
  #116 = NameAndType        #65:#115      // buildString:(Lscala/xml/dtd/impl/Base$RegExp;Lscala/collection/mutable/StringBuilder;)Lscala/collection/mutable/StringBuilder;
  #117 = Methodref          #71.#116      // scala/xml/dtd/ContentModel$.buildString:(Lscala/xml/dtd/impl/Base$RegExp;Lscala/collection/mutable/StringBuilder;)Lscala/collection/mutable/StringBuilder;
  #118 = Utf8               )*
  #119 = String             #118          // )*
  #120 = Utf8               rs
  #121 = Utf8               Lscala/collection/immutable/Seq;
  #122 = Utf8               newAlt
  #123 = Utf8               Lscala/xml/dtd/impl/Base$Alt;
  #124 = Utf8               Lscala/collection/mutable/StringBuilder;
  #125 = Utf8               copy
  #126 = Utf8               (Lscala/xml/dtd/impl/Base$RegExp;)V
  #127 = NameAndType        #103:#126     // "<init>":(Lscala/xml/dtd/impl/Base$RegExp;)V
  #128 = Methodref          #2.#127       // scala/xml/dtd/MIXED."<init>":(Lscala/xml/dtd/impl/Base$RegExp;)V
  #129 = Utf8               copy$default$1
  #130 = Utf8               productPrefix
  #131 = Utf8               ()Ljava/lang/String;
  #132 = Utf8               MIXED
  #133 = String             #132          // MIXED
  #134 = Utf8               productArity
  #135 = Utf8               ()I
  #136 = Utf8               productElement
  #137 = Utf8               x$1
  #138 = Utf8               scala/runtime/Statics
  #139 = Class              #138          // scala/runtime/Statics
  #140 = Utf8               ioobe
  #141 = NameAndType        #140:#95      // ioobe:(I)Ljava/lang/Object;
  #142 = Methodref          #139.#141     // scala/runtime/Statics.ioobe:(I)Ljava/lang/Object;
  #143 = Utf8               I
  #144 = Utf8               java/lang/Object
  #145 = Class              #144          // java/lang/Object
  #146 = Utf8               productIterator
  #147 = Utf8               ()Lscala/collection/Iterator<Ljava/lang/Object;>;
  #148 = Utf8               scala/runtime/ScalaRunTime$
  #149 = Class              #148          // scala/runtime/ScalaRunTime$
  #150 = Utf8               Lscala/runtime/ScalaRunTime$;
  #151 = NameAndType        #32:#150      // MODULE$:Lscala/runtime/ScalaRunTime$;
  #152 = Fieldref           #149.#151     // scala/runtime/ScalaRunTime$.MODULE$:Lscala/runtime/ScalaRunTime$;
  #153 = Utf8               typedProductIterator
  #154 = NameAndType        #153:#58      // typedProductIterator:(Lscala/Product;)Lscala/collection/Iterator;
  #155 = Methodref          #149.#154     // scala/runtime/ScalaRunTime$.typedProductIterator:(Lscala/Product;)Lscala/collection/Iterator;
  #156 = Utf8               canEqual
  #157 = Utf8               (Ljava/lang/Object;)Z
  #158 = Utf8               Ljava/lang/Object;
  #159 = Utf8               productElementName
  #160 = Utf8               (I)Ljava/lang/String;
  #161 = String             #24           // r
  #162 = Utf8               java/lang/String
  #163 = Class              #162          // java/lang/String
  #164 = Utf8               hashCode
  #165 = Utf8               _hashCode
  #166 = Utf8               (Lscala/Product;)I
  #167 = NameAndType        #165:#166     // _hashCode:(Lscala/Product;)I
  #168 = Methodref          #149.#167     // scala/runtime/ScalaRunTime$._hashCode:(Lscala/Product;)I
  #169 = Utf8               equals
  #170 = NameAndType        #169:#157     // equals:(Ljava/lang/Object;)Z
  #171 = Methodref          #145.#170     // java/lang/Object.equals:(Ljava/lang/Object;)Z
  #172 = NameAndType        #156:#157     // canEqual:(Ljava/lang/Object;)Z
  #173 = Methodref          #2.#172       // scala/xml/dtd/MIXED.canEqual:(Ljava/lang/Object;)Z
  #174 = Utf8               ()V
  #175 = NameAndType        #103:#174     // "<init>":()V
  #176 = Methodref          #4.#175       // scala/xml/dtd/DFAContentModel."<init>":()V
  #177 = Utf8               $init$
  #178 = Utf8               (Lscala/Product;)V
  #179 = NameAndType        #177:#178     // $init$:(Lscala/Product;)V
  #180 = InterfaceMethodref #6.#179       // scala/Product.$init$:(Lscala/Product;)V
  #181 = Utf8               Code
  #182 = Utf8               LocalVariableTable
  #183 = Utf8               Signature
  #184 = Utf8               MethodParameters
  #185 = Utf8               LineNumberTable
  #186 = Utf8               StackMapTable
  #187 = Utf8               InnerClasses
  #188 = Utf8               SourceFile
  #189 = Utf8               RuntimeVisibleAnnotations
  #190 = Utf8               ScalaInlineInfo
  #191 = Utf8               ScalaSig
{
  private final scala.xml.dtd.impl.Base$RegExp r;
    descriptor: Lscala/xml/dtd/impl/Base$RegExp;
    flags: (0x0012) ACC_PRIVATE, ACC_FINAL

  public static scala.Option<scala.xml.dtd.impl.Base$RegExp> unapply(scala.xml.dtd.MIXED);
    descriptor: (Lscala/xml/dtd/MIXED;)Lscala/Option;
    flags: (0x0009) ACC_PUBLIC, ACC_STATIC
    Code:
      stack=2, locals=1, args_size=1
         0: getstatic     #35                 // Field scala/xml/dtd/MIXED$.MODULE$:Lscala/xml/dtd/MIXED$;
         3: aload_0
         4: invokevirtual #37                 // Method scala/xml/dtd/MIXED$.unapply:(Lscala/xml/dtd/MIXED;)Lscala/Option;
         7: areturn
      LocalVariableTable:
        Start  Length  Slot  Name   Signature
            0       8     0   x$0   Lscala/xml/dtd/MIXED;
    Signature: #28                          // (Lscala/xml/dtd/MIXED;)Lscala/Option<Lscala/xml/dtd/impl/Base$RegExp;>;
    MethodParameters:
      Name                           Flags
      x$0                            final

  public static scala.xml.dtd.MIXED apply(scala.xml.dtd.impl.Base$RegExp);
    descriptor: (Lscala/xml/dtd/impl/Base$RegExp;)Lscala/xml/dtd/MIXED;
    flags: (0x0009) ACC_PUBLIC, ACC_STATIC
    Code:
      stack=2, locals=1, args_size=1
         0: getstatic     #35                 // Field scala/xml/dtd/MIXED$.MODULE$:Lscala/xml/dtd/MIXED$;
         3: aload_0
         4: invokevirtual #42                 // Method scala/xml/dtd/MIXED$.apply:(Lscala/xml/dtd/impl/Base$RegExp;)Lscala/xml/dtd/MIXED;
         7: areturn
      LocalVariableTable:
        Start  Length  Slot  Name   Signature
            0       8     0     r   Lscala/xml/dtd/impl/Base$RegExp;
    MethodParameters:
      Name                           Flags
      r                              final

  public static <A$ extends java.lang.Object> scala.Function1<scala.xml.dtd.impl.Base$RegExp, A$> andThen(scala.Function1<scala.xml.dtd.MIXED, A$>);
    descriptor: (Lscala/Function1;)Lscala/Function1;
    flags: (0x0009) ACC_PUBLIC, ACC_STATIC
    Code:
      stack=2, locals=1, args_size=1
         0: getstatic     #35                 // Field scala/xml/dtd/MIXED$.MODULE$:Lscala/xml/dtd/MIXED$;
         3: aload_0
         4: invokevirtual #48                 // Method scala/xml/dtd/MIXED$.andThen:(Lscala/Function1;)Lscala/Function1;
         7: areturn
      LocalVariableTable:
        Start  Length  Slot  Name   Signature
            0       8     0     g   Lscala/Function1;
    Signature: #45                          // <A$:Ljava/lang/Object;>(Lscala/Function1<Lscala/xml/dtd/MIXED;TA$;>;)Lscala/Function1<Lscala/xml/dtd/impl/Base$RegExp;TA$;>;
    MethodParameters:
      Name                           Flags
      g                              final

  public static <A$ extends java.lang.Object> scala.Function1<A$, scala.xml.dtd.MIXED> compose(scala.Function1<A$, scala.xml.dtd.impl.Base$RegExp>);
    descriptor: (Lscala/Function1;)Lscala/Function1;
    flags: (0x0009) ACC_PUBLIC, ACC_STATIC
    Code:
      stack=2, locals=1, args_size=1
         0: getstatic     #35                 // Field scala/xml/dtd/MIXED$.MODULE$:Lscala/xml/dtd/MIXED$;
         3: aload_0
         4: invokevirtual #53                 // Method scala/xml/dtd/MIXED$.compose:(Lscala/Function1;)Lscala/Function1;
         7: areturn
      LocalVariableTable:
        Start  Length  Slot  Name   Signature
            0       8     0     g   Lscala/Function1;
    Signature: #51                          // <A$:Ljava/lang/Object;>(Lscala/Function1<TA$;Lscala/xml/dtd/impl/Base$RegExp;>;)Lscala/Function1<TA$;Lscala/xml/dtd/MIXED;>;
    MethodParameters:
      Name                           Flags
      g                              final

  public scala.collection.Iterator<java.lang.String> productElementNames();
    descriptor: ()Lscala/collection/Iterator;
    flags: (0x0001) ACC_PUBLIC
    Code:
      stack=1, locals=1, args_size=1
         0: aload_0
         1: invokestatic  #60                 // InterfaceMethod scala/Product.productElementNames$:(Lscala/Product;)Lscala/collection/Iterator;
         4: areturn
      LineNumberTable:
        line 117: 0
      LocalVariableTable:
        Start  Length  Slot  Name   Signature
            0       5     0  this   Lscala/xml/dtd/MIXED;
    Signature: #56                          // ()Lscala/collection/Iterator<Ljava/lang/String;>;

  public scala.xml.dtd.impl.Base$RegExp r();
    descriptor: ()Lscala/xml/dtd/impl/Base$RegExp;
    flags: (0x0001) ACC_PUBLIC
    Code:
      stack=1, locals=1, args_size=1
         0: aload_0
         1: getfield      #64                 // Field r:Lscala/xml/dtd/impl/Base$RegExp;
         4: areturn
      LineNumberTable:
        line 117: 0
      LocalVariableTable:
        Start  Length  Slot  Name   Signature
            0       5     0  this   Lscala/xml/dtd/MIXED;

  public scala.collection.mutable.StringBuilder buildString(scala.collection.mutable.StringBuilder);
    descriptor: (Lscala/collection/mutable/StringBuilder;)Lscala/collection/mutable/StringBuilder;
    flags: (0x0001) ACC_PUBLIC
    Code:
      stack=3, locals=8, args_size=2
         0: aload_0
         1: invokevirtual #69                 // Method r:()Lscala/xml/dtd/impl/Base$RegExp;
         4: astore        4
         6: aload         4
         8: instanceof    #14                 // class scala/xml/dtd/impl/Base$Alt
        11: ifeq          79
        14: aload         4
        16: checkcast     #14                 // class scala/xml/dtd/impl/Base$Alt
        19: astore        5
        21: getstatic     #74                 // Field scala/xml/dtd/ContentModel$.MODULE$:Lscala/xml/dtd/ContentModel$;
        24: invokevirtual #77                 // Method scala/xml/dtd/ContentModel$.Alt:()Lscala/xml/dtd/impl/Base$Alt$;
        27: aload         5
        29: invokevirtual #81                 // Method scala/xml/dtd/impl/Base$Alt$.unapplySeq:(Lscala/xml/dtd/impl/Base$Alt;)Lscala/Some;
        32: astore        6
        34: aload         6
        36: invokevirtual #87                 // Method scala/Some.isEmpty:()Z
        39: ifne          76
        42: aload         6
        44: invokevirtual #91                 // Method scala/Some.get:()Ljava/lang/Object;
        47: checkcast     #93                 // class scala/collection/immutable/Seq
        50: astore        7
        52: getstatic     #74                 // Field scala/xml/dtd/ContentModel$.MODULE$:Lscala/xml/dtd/ContentModel$;
        55: invokevirtual #77                 // Method scala/xml/dtd/ContentModel$.Alt:()Lscala/xml/dtd/impl/Base$Alt$;
        58: aload         7
        60: iconst_1
        61: invokeinterface #97,  2           // InterfaceMethod scala/collection/immutable/Seq.drop:(I)Ljava/lang/Object;
        66: checkcast     #93                 // class scala/collection/immutable/Seq
        69: invokevirtual #100                // Method scala/xml/dtd/impl/Base$Alt$.apply:(Lscala/collection/immutable/Seq;)Lscala/xml/dtd/impl/Base$Alt;
        72: astore_2
        73: goto          92
        76: goto          82
        79: goto          82
        82: new           #102                // class scala/MatchError
        85: dup
        86: aload         4
        88: invokespecial #106                // Method scala/MatchError."<init>":(Ljava/lang/Object;)V
        91: athrow
        92: aload_2
        93: astore_3
        94: aload_1
        95: ldc           #108                // String (#PCDATA|
        97: invokevirtual #114                // Method scala/collection/mutable/StringBuilder.append:(Ljava/lang/String;)Lscala/collection/mutable/StringBuilder;
       100: pop
       101: getstatic     #74                 // Field scala/xml/dtd/ContentModel$.MODULE$:Lscala/xml/dtd/ContentModel$;
       104: aload_3
       105: aload_1
       106: invokevirtual #117                // Method scala/xml/dtd/ContentModel$.buildString:(Lscala/xml/dtd/impl/Base$RegExp;Lscala/collection/mutable/StringBuilder;)Lscala/collection/mutable/StringBuilder;
       109: pop
       110: aload_1
       111: ldc           #119                // String )*
       113: invokevirtual #114                // Method scala/collection/mutable/StringBuilder.append:(Ljava/lang/String;)Lscala/collection/mutable/StringBuilder;
       116: areturn
      StackMapTable: number_of_entries = 4
        frame_type = 255 /* full_frame */
          offset_delta = 76
          locals = [ class scala/xml/dtd/MIXED, class scala/collection/mutable/StringBuilder, top, top, class scala/xml/dtd/impl/Base$RegExp, class scala/xml/dtd/impl/Base$Alt, class scala/Some ]
          stack = []
        frame_type = 249 /* chop */
          offset_delta = 2
        frame_type = 2 /* same */
        frame_type = 255 /* full_frame */
          offset_delta = 9
          locals = [ class scala/xml/dtd/MIXED, class scala/collection/mutable/StringBuilder, class scala/xml/dtd/impl/Base$Alt, top, class scala/xml/dtd/impl/Base$RegExp, class scala/xml/dtd/impl/Base$Alt, class scala/Some, class scala/collection/immutable/Seq ]
          stack = []
      LineNumberTable:
        line 121: 0
        line 123: 94
        line 124: 101
        line 125: 110
      LocalVariableTable:
        Start  Length  Slot  Name   Signature
           52      24     7    rs   Lscala/collection/immutable/Seq;
           94      22     3 newAlt   Lscala/xml/dtd/impl/Base$Alt;
            0     117     0  this   Lscala/xml/dtd/MIXED;
            0     117     1    sb   Lscala/collection/mutable/StringBuilder;
    MethodParameters:
      Name                           Flags
      sb                             final

  public scala.xml.dtd.MIXED copy(scala.xml.dtd.impl.Base$RegExp);
    descriptor: (Lscala/xml/dtd/impl/Base$RegExp;)Lscala/xml/dtd/MIXED;
    flags: (0x0001) ACC_PUBLIC
    Code:
      stack=3, locals=2, args_size=2
         0: new           #2                  // class scala/xml/dtd/MIXED
         3: dup
         4: aload_1
         5: invokespecial #128                // Method "<init>":(Lscala/xml/dtd/impl/Base$RegExp;)V
         8: areturn
      LineNumberTable:
        line 117: 0
      LocalVariableTable:
        Start  Length  Slot  Name   Signature
            0       9     0  this   Lscala/xml/dtd/MIXED;
            0       9     1     r   Lscala/xml/dtd/impl/Base$RegExp;
    MethodParameters:
      Name                           Flags
      r                              final

  public scala.xml.dtd.impl.Base$RegExp copy$default$1();
    descriptor: ()Lscala/xml/dtd/impl/Base$RegExp;
    flags: (0x0001) ACC_PUBLIC
    Code:
      stack=1, locals=1, args_size=1
         0: aload_0
         1: invokevirtual #69                 // Method r:()Lscala/xml/dtd/impl/Base$RegExp;
         4: areturn
      LineNumberTable:
        line 117: 0
      LocalVariableTable:
        Start  Length  Slot  Name   Signature
            0       5     0  this   Lscala/xml/dtd/MIXED;

  public java.lang.String productPrefix();
    descriptor: ()Ljava/lang/String;
    flags: (0x0001) ACC_PUBLIC
    Code:
      stack=1, locals=1, args_size=1
         0: ldc           #133                // String MIXED
         2: areturn
      LineNumberTable:
        line 117: 0
      LocalVariableTable:
        Start  Length  Slot  Name   Signature
            0       3     0  this   Lscala/xml/dtd/MIXED;

  public int productArity();
    descriptor: ()I
    flags: (0x0001) ACC_PUBLIC
    Code:
      stack=1, locals=1, args_size=1
         0: iconst_1
         1: ireturn
      LineNumberTable:
        line 117: 0
      LocalVariableTable:
        Start  Length  Slot  Name   Signature
            0       2     0  this   Lscala/xml/dtd/MIXED;

  public java.lang.Object productElement(int);
    descriptor: (I)Ljava/lang/Object;
    flags: (0x0001) ACC_PUBLIC
    Code:
      stack=1, locals=3, args_size=2
         0: iload_1
         1: istore_2
         2: iload_2
         3: tableswitch   { // 0 to 0
                       0: 20
                 default: 27
            }
        20: aload_0
        21: invokevirtual #69                 // Method r:()Lscala/xml/dtd/impl/Base$RegExp;
        24: goto          34
        27: iload_1
        28: invokestatic  #142                // Method scala/runtime/Statics.ioobe:(I)Ljava/lang/Object;
        31: goto          34
        34: areturn
      StackMapTable: number_of_entries = 3
        frame_type = 252 /* append */
          offset_delta = 20
          locals = [ int ]
        frame_type = 6 /* same */
        frame_type = 70 /* same_locals_1_stack_item */
          stack = [ class java/lang/Object ]
      LineNumberTable:
        line 117: 0
      LocalVariableTable:
        Start  Length  Slot  Name   Signature
            0      35     0  this   Lscala/xml/dtd/MIXED;
            0      35     1   x$1   I
    MethodParameters:
      Name                           Flags
      x$1                            final

  public scala.collection.Iterator<java.lang.Object> productIterator();
    descriptor: ()Lscala/collection/Iterator;
    flags: (0x0001) ACC_PUBLIC
    Code:
      stack=2, locals=1, args_size=1
         0: getstatic     #152                // Field scala/runtime/ScalaRunTime$.MODULE$:Lscala/runtime/ScalaRunTime$;
         3: aload_0
         4: invokevirtual #155                // Method scala/runtime/ScalaRunTime$.typedProductIterator:(Lscala/Product;)Lscala/collection/Iterator;
         7: areturn
      LineNumberTable:
        line 117: 0
      LocalVariableTable:
        Start  Length  Slot  Name   Signature
            0       8     0  this   Lscala/xml/dtd/MIXED;
    Signature: #147                         // ()Lscala/collection/Iterator<Ljava/lang/Object;>;

  public boolean canEqual(java.lang.Object);
    descriptor: (Ljava/lang/Object;)Z
    flags: (0x0001) ACC_PUBLIC
    Code:
      stack=1, locals=2, args_size=2
         0: aload_1
         1: instanceof    #2                  // class scala/xml/dtd/MIXED
         4: ireturn
      LineNumberTable:
        line 117: 0
      LocalVariableTable:
        Start  Length  Slot  Name   Signature
            0       5     0  this   Lscala/xml/dtd/MIXED;
            0       5     1   x$1   Ljava/lang/Object;
    MethodParameters:
      Name                           Flags
      x$1                            final

  public java.lang.String productElementName(int);
    descriptor: (I)Ljava/lang/String;
    flags: (0x0001) ACC_PUBLIC
    Code:
      stack=1, locals=3, args_size=2
         0: iload_1
         1: istore_2
         2: iload_2
         3: tableswitch   { // 0 to 0
                       0: 20
                 default: 25
            }
        20: ldc           #161                // String r
        22: goto          35
        25: iload_1
        26: invokestatic  #142                // Method scala/runtime/Statics.ioobe:(I)Ljava/lang/Object;
        29: checkcast     #163                // class java/lang/String
        32: goto          35
        35: areturn
      StackMapTable: number_of_entries = 3
        frame_type = 252 /* append */
          offset_delta = 20
          locals = [ int ]
        frame_type = 4 /* same */
        frame_type = 73 /* same_locals_1_stack_item */
          stack = [ class java/lang/String ]
      LineNumberTable:
        line 117: 0
      LocalVariableTable:
        Start  Length  Slot  Name   Signature
            0      36     0  this   Lscala/xml/dtd/MIXED;
            0      36     1   x$1   I
    MethodParameters:
      Name                           Flags
      x$1                            final

  public int hashCode();
    descriptor: ()I
    flags: (0x0001) ACC_PUBLIC
    Code:
      stack=2, locals=1, args_size=1
         0: getstatic     #152                // Field scala/runtime/ScalaRunTime$.MODULE$:Lscala/runtime/ScalaRunTime$;
         3: aload_0
         4: invokevirtual #168                // Method scala/runtime/ScalaRunTime$._hashCode:(Lscala/Product;)I
         7: ireturn
      LineNumberTable:
        line 117: 0
      LocalVariableTable:
        Start  Length  Slot  Name   Signature
            0       8     0  this   Lscala/xml/dtd/MIXED;

  public boolean equals(java.lang.Object);
    descriptor: (Ljava/lang/Object;)Z
    flags: (0x0001) ACC_PUBLIC
    Code:
      stack=2, locals=6, args_size=2
         0: aload_0
         1: aload_1
         2: if_acmpeq     86
         5: aload_1
         6: astore_3
         7: aload_3
         8: instanceof    #2                  // class scala/xml/dtd/MIXED
        11: ifeq          19
        14: iconst_1
        15: istore_2
        16: goto          27
        19: goto          22
        22: iconst_0
        23: istore_2
        24: goto          27
        27: iload_2
        28: ifeq          90
        31: aload_1
        32: checkcast     #2                  // class scala/xml/dtd/MIXED
        35: astore        4
        37: aload_0
        38: invokevirtual #69                 // Method r:()Lscala/xml/dtd/impl/Base$RegExp;
        41: aload         4
        43: invokevirtual #69                 // Method r:()Lscala/xml/dtd/impl/Base$RegExp;
        46: astore        5
        48: dup
        49: ifnonnull     61
        52: pop
        53: aload         5
        55: ifnull        69
        58: goto          82
        61: aload         5
        63: invokevirtual #171                // Method java/lang/Object.equals:(Ljava/lang/Object;)Z
        66: ifeq          82
        69: aload         4
        71: aload_0
        72: invokevirtual #173                // Method canEqual:(Ljava/lang/Object;)Z
        75: ifeq          82
        78: iconst_1
        79: goto          83
        82: iconst_0
        83: ifeq          90
        86: iconst_1
        87: goto          91
        90: iconst_0
        91: ireturn
      StackMapTable: number_of_entries = 10
        frame_type = 253 /* append */
          offset_delta = 19
          locals = [ top, class java/lang/Object ]
        frame_type = 2 /* same */
        frame_type = 255 /* full_frame */
          offset_delta = 4
          locals = [ class scala/xml/dtd/MIXED, class java/lang/Object, int, class java/lang/Object ]
          stack = []
        frame_type = 255 /* full_frame */
          offset_delta = 33
          locals = [ class scala/xml/dtd/MIXED, class java/lang/Object, int, class java/lang/Object, class scala/xml/dtd/MIXED, class scala/xml/dtd/impl/Base$RegExp ]
          stack = [ class scala/xml/dtd/impl/Base$RegExp ]
        frame_type = 7 /* same */
        frame_type = 12 /* same */
        frame_type = 64 /* same_locals_1_stack_item */
          stack = [ int ]
        frame_type = 255 /* full_frame */
          offset_delta = 2
          locals = [ class scala/xml/dtd/MIXED, class java/lang/Object ]
          stack = []
        frame_type = 253 /* append */
          offset_delta = 3
          locals = [ int, class java/lang/Object ]
        frame_type = 255 /* full_frame */
          offset_delta = 0
          locals = [ class scala/xml/dtd/MIXED, class java/lang/Object ]
          stack = [ int ]
      LineNumberTable:
        line 117: 0
      LocalVariableTable:
        Start  Length  Slot  Name   Signature
            0      92     0  this   Lscala/xml/dtd/MIXED;
            0      92     1   x$1   Ljava/lang/Object;
    MethodParameters:
      Name                           Flags
      x$1                            final

  public scala.xml.dtd.MIXED(scala.xml.dtd.impl.Base$RegExp);
    descriptor: (Lscala/xml/dtd/impl/Base$RegExp;)V
    flags: (0x0001) ACC_PUBLIC
    Code:
      stack=2, locals=2, args_size=2
         0: aload_0
         1: aload_1
         2: putfield      #64                 // Field r:Lscala/xml/dtd/impl/Base$RegExp;
         5: aload_0
         6: invokespecial #176                // Method scala/xml/dtd/DFAContentModel."<init>":()V
         9: aload_0
        10: invokestatic  #180                // InterfaceMethod scala/Product.$init$:(Lscala/Product;)V
        13: return
      LineNumberTable:
        line 117: 0
      LocalVariableTable:
        Start  Length  Slot  Name   Signature
            0      14     0  this   Lscala/xml/dtd/MIXED;
            0      14     1     r   Lscala/xml/dtd/impl/Base$RegExp;
    MethodParameters:
      Name                           Flags
      r                              final
}
InnerClasses:
  public #17= #14 of #16;                 // Alt=class scala/xml/dtd/impl/Base$Alt of class scala/xml/dtd/impl/Base
  public #20= #19 of #16;                 // Alt$=class scala/xml/dtd/impl/Base$Alt$ of class scala/xml/dtd/impl/Base
  public abstract #23= #22 of #16;        // RegExp=class scala/xml/dtd/impl/Base$RegExp of class scala/xml/dtd/impl/Base
SourceFile: "ContentModel.scala"
RuntimeVisibleAnnotations:
  0: #10(#11=s#12)
    scala.reflect.ScalaSignature(
      bytes="\u0006\u0005\u0005=c\u0001\u0002\f\u0018\u0001zA\u0001b\r\u0001\u0003\u0016\u0004%\t\u0001\u000e\u0005\t\u007f\u0001\u0011\t\u0012)A\u0005k!)\u0001\t\u0001C\u0001\u0003\")A\t\u0001C!\u000b\"9A\nAA\u0001\n\u0003i\u0005bB(\u0001#\u0003%\t\u0001\u0015\u0005\b7\u0002\t\t\u0011\"\u0011]\u0011\u001d)\u0007!!A\u0005\u0002\u0019DqA\u001b\u0001\u0002\u0002\u0013\u00051\u000eC\u0004r\u0001\u0005\u0005I\u0011\t:\t\u000fe\u0004\u0011\u0011!C\u0001u\"Aq\u0010AA\u0001\n\u0003\n\t\u0001C\u0005\u0002\u0006\u0001\t\t\u0011\"\u0011\u0002\b!I\u0011\u0011\u0002\u0001\u0002\u0002\u0013\u0005\u00131B\u0004\n\u0003\u001f9\u0012\u0011!E\u0001\u0003#1\u0001BF\f\u0002\u0002#\u0005\u00111\u0003\u0005\u0007\u0001B!\t!a\u000b\t\u0013\u00055\u0002#!A\u0005F\u0005=\u0002\"CA\u0019!\u0005\u0005I\u0011QA\u001a\u0011%\t9\u0004EA\u0001\n\u0003\u000bI\u0004C\u0005\u0002FA\t\t\u0011\"\u0003\u0002H\t)Q*\u0013-F\t*\u0011\u0001$G\u0001\u0004IR$\'B\u0001\u000e\u001c\u0003\rAX\u000e\u001c\u0006\u00029\u0005)1oY1mC\u000e\u00011\u0003\u0002\u0001 G\u001d\u0002\"\u0001I\u0011\u000e\u0003]I!AI\f\u0003\u001f\u00113\u0015iQ8oi\u0016tG/T8eK2\u0004\"\u0001J\u0013\u000e\u0003mI!AJ\u000e\u0003\u000fA\u0013x\u000eZ;diB\u0011\u0001\u0006\r\b\u0003S9r!AK\u0017\u000e\u0003-R!\u0001L\u000f\u0002\rq\u0012xn\u001c;?\u0013\u0005a\u0012BA\u0018\u001c\u0003\u001d\u0001\u0018mY6bO\u0016L!!\r\u001a\u0003\u0019M+\'/[1mSj\f\'\r\\3\u000b\u0005=Z\u0012!\u0001:\u0016\u0003U\u0002\"AN\u001d\u000f\u0005\u0001:\u0014B\u0001\u001d\u0018\u00031\u0019uN\u001c;f]Rlu\u000eZ3m\u0013\tQ4H\u0001\u0004SK\u001e,\u0005\u0010]\u0005\u0003yu\u0012AAQ1tK*\u0011ahF\u0001\u0005S6\u0004H.\u0001\u0002sA\u00051A(\u001b8jiz\"\"AQ\"\u0011\u0005\u0001\u0002\u0001\"B\u001a\u0004\u0001\u0004)\u0014a\u00032vS2$7\u000b\u001e:j]\u001e$\"A\u0012&\u0011\u0005\u001dCeB\u0001\u0013/\u0013\tI%GA\u0007TiJLgn\u001a\"vS2$WM\u001d\u0005\u0006\u0017\u0012\u0001\rAR\u0001\u0003g\n\fAaY8qsR\u0011!I\u0014\u0005\bg\u0015\u0001\n\u00111\u00016\u00039\u0019w\u000e]=%I\u00164\u0017-\u001e7uIE*\u0012!\u0015\u0016\u0003kI[\u0013a\u0015\t\u0003)fk\u0011!\u0016\u0006\u0003-^\u000b\u0011\"\u001e8dQ\u0016\u001c7.\u001a3\u000b\u0005a[\u0012AC1o]>$\u0018\r^5p]&\u0011!,\u0016\u0002\u0012k:\u001c\u0007.Z2lK\u00124\u0016M]5b]\u000e,\u0017!\u00049s_\u0012,8\r\u001e)sK\u001aL\u00070F\u0001^!\tq6-D\u0001`\u0015\t\u0001\u0017-\u0001\u0003mC:<\'\"\u00012\u0002\t)\fg/Y\u0005\u0003I~\u0013aa\u0015;sS:<\u0017\u0001\u00049s_\u0012,8\r^!sSRLX#A4\u0011\u0005\u0011B\u0017BA5\u001c\u0005\rIe\u000e^\u0001\u000faJ|G-^2u\u000b2,W.\u001a8u)\taw\u000e\u0005\u0002%[&\u0011an\u0007\u0002\u0004\u0003:L\bb\u00029\n\u0003\u0003\u0005\raZ\u0001\u0004q\u0012\n\u0014a\u00049s_\u0012,8\r^%uKJ\fGo\u001c:\u0016\u0003M\u00042\u0001^<m\u001b\u0005)(B\u0001<\u001c\u0003)\u0019w\u000e\u001c7fGRLwN\\\u0005\u0003qV\u0014\u0001\"\u0013;fe\u0006$xN]\u0001\tG\u0006tW)];bYR\u00111P \t\u0003IqL!!`\u000e\u0003\u000f\t{w\u000e\\3b]\"9\u0001oCA\u0001\u0002\u0004a\u0017A\u00059s_\u0012,8\r^#mK6,g\u000e\u001e(b[\u0016$2!XA\u0002\u0011\u001d\u0001H\"!AA\u0002\u001d\f\u0001\u0002[1tQ\u000e{G-\u001a\u000b\u0002O\u00061Q-];bYN$2a_A\u0007\u0011\u001d\u0001h\"!AA\u00021\fQ!T%Y\u000b\u0012\u0003\"\u0001\t\t\u0014\u000bA\t)\"!\t\u0011\r\u0005]\u0011QD\u001bC\u001b\t\tIBC\u0002\u0002\u001cm\tqA];oi&lW-\u0003\u0003\u0002 \u0005e!!E!cgR\u0014\u0018m\u0019;Gk:\u001cG/[8ocA!\u00111EA\u0015\u001b\t\t)CC\u0002\u0002(\u0005\f!![8\n\u0007E\n)\u0003\u0006\u0002\u0002\u0012\u0005AAo\\*ue&tw\rF\u0001^\u0003\u0015\t\u0007\u000f\u001d7z)\r\u0011\u0015Q\u0007\u0005\u0006gM\u0001\r!N\u0001\bk:\f\u0007\u000f\u001d7z)\u0011\tY$!\u0011\u0011\t\u0011\ni$N\u0005\u0004\u0003\u007fY\"AB(qi&|g\u000e\u0003\u0005\u0002DQ\t\t\u00111\u0001C\u0003\rAH\u0005M\u0001\roJLG/\u001a*fa2\f7-\u001a\u000b\u0003\u0003\u0013\u00022AXA&\u0013\r\tie\u0018\u0002\u0007\u001f\nTWm\u0019;"
    )
  ScalaInlineInfo: length = 0x4A (unknown attribute)
   01 00 00 0E 00 67 00 7E 00 00 41 00 42 00 00 9C
   00 9D 00 00 7D 00 28 00 00 81 00 3E 00 00 A9 00
   9D 00 00 A4 00 87 00 00 86 00 87 00 00 88 00 5F
   00 00 9F 00 A0 00 00 36 00 37 00 00 92 00 37 00
   00 82 00 83 00 00 18 00 3E 00
  ScalaSig: length = 0x3 (unknown attribute)
   05 02 00
