Classfile /Users/mw/Projects/slang-braindump/.jar/jar8/assemble/slang-braindump/assemble/content/scala/xml/dtd/NoExternalID.class
  Last modified May 29, 2022; size 2385 bytes
  SHA-256 checksum e4240850bf410b10a4392a5748a488fb28b7ca1d963214a9a116bf5cd11ddd25
  Compiled from "ExternalID.scala"
public final class scala.xml.dtd.NoExternalID
  minor version: 0
  major version: 52
  flags: (0x0031) ACC_PUBLIC, ACC_FINAL, ACC_SUPER
  this_class: #2                          // scala/xml/dtd/NoExternalID
  super_class: #4                         // java/lang/Object
  interfaces: 0, fields: 0, methods: 16, attributes: 3
Constant pool:
   #1 = Utf8               scala/xml/dtd/NoExternalID
   #2 = Class              #1             // scala/xml/dtd/NoExternalID
   #3 = Utf8               java/lang/Object
   #4 = Class              #3             // java/lang/Object
   #5 = Utf8               ExternalID.scala
   #6 = Utf8               Lscala/reflect/ScalaSignature;
   #7 = Utf8               bytes
   #8 = Utf8               \u0006\u00051:Q\u0001C\u0005\t\u0002A1QAE\u0005\t\u0002MAQaF\u0001\u0005\u0002aAq!G\u0001C\u0002\u0013\u0005!\u0004\u0003\u0004 \u0003\u0001\u0006Ia\u0007\u0005\bA\u0005\u0011\r\u0011\"\u0001\u001b\u0011\u0019\t\u0013\u0001)A\u00057!)!%\u0001C!G\u0005aaj\\#yi\u0016\u0014h.\u00197J\t*\u0011!bC\u0001\u0004IR$\'B\u0001\u0007\u000e\u0003\rAX\u000e\u001c\u0006\u0002\u001d\u0005)1oY1mC\u000e\u0001\u0001CA\t\u0002\u001b\u0005I!\u0001\u0004(p\u000bb$XM\u001d8bY&#5CA\u0001\u0015!\t\tR#\u0003\u0002\u0017\u0013\tQQ\t\u001f;fe:\fG.\u0013#\u0002\rqJg.\u001b;?)\u0005\u0001\u0012\u0001\u00039vE2L7-\u00133\u0016\u0003m\u0001\"\u0001H\u000f\u000e\u00035I!AH\u0007\u0003\t9+H\u000e\\\u0001\naV\u0014G.[2JI\u0002\n\u0001b]=ti\u0016l\u0017\nZ\u0001\ngf\u001cH/Z7JI\u0002\n\u0001\u0002^8TiJLgn\u001a\u000b\u0002IA\u0011QEK\u0007\u0002M)\u0011q\u0005K\u0001\u0005Y\u0006twMC\u0001*\u0003\u0011Q\u0017M^1\n\u0005-2#AB*ue&tw\r
   #9 = Utf8               toString
  #10 = Utf8               ()Ljava/lang/String;
  #11 = Utf8               scala/xml/dtd/NoExternalID$
  #12 = Class              #11            // scala/xml/dtd/NoExternalID$
  #13 = Utf8               MODULE$
  #14 = Utf8               Lscala/xml/dtd/NoExternalID$;
  #15 = NameAndType        #13:#14        // MODULE$:Lscala/xml/dtd/NoExternalID$;
  #16 = Fieldref           #12.#15        // scala/xml/dtd/NoExternalID$.MODULE$:Lscala/xml/dtd/NoExternalID$;
  #17 = NameAndType        #9:#10         // toString:()Ljava/lang/String;
  #18 = Methodref          #12.#17        // scala/xml/dtd/NoExternalID$.toString:()Ljava/lang/String;
  #19 = Utf8               systemId
  #20 = Utf8               ()Lscala/runtime/Null$;
  #21 = NameAndType        #19:#20        // systemId:()Lscala/runtime/Null$;
  #22 = Methodref          #12.#21        // scala/xml/dtd/NoExternalID$.systemId:()Lscala/runtime/Null$;
  #23 = Utf8               publicId
  #24 = NameAndType        #23:#20        // publicId:()Lscala/runtime/Null$;
  #25 = Methodref          #12.#24        // scala/xml/dtd/NoExternalID$.publicId:()Lscala/runtime/Null$;
  #26 = Utf8               buildString
  #27 = Utf8               (Lscala/collection/mutable/StringBuilder;)Lscala/collection/mutable/StringBuilder;
  #28 = Utf8               sb
  #29 = NameAndType        #26:#27        // buildString:(Lscala/collection/mutable/StringBuilder;)Lscala/collection/mutable/StringBuilder;
  #30 = Methodref          #12.#29        // scala/xml/dtd/NoExternalID$.buildString:(Lscala/collection/mutable/StringBuilder;)Lscala/collection/mutable/StringBuilder;
  #31 = Utf8               Lscala/collection/mutable/StringBuilder;
  #32 = Utf8               quoted
  #33 = Utf8               (Ljava/lang/String;)Ljava/lang/String;
  #34 = Utf8               s
  #35 = NameAndType        #32:#33        // quoted:(Ljava/lang/String;)Ljava/lang/String;
  #36 = Methodref          #12.#35        // scala/xml/dtd/NoExternalID$.quoted:(Ljava/lang/String;)Ljava/lang/String;
  #37 = Utf8               Ljava/lang/String;
  #38 = Utf8               checkPubID
  #39 = Utf8               (Ljava/lang/String;)Z
  #40 = NameAndType        #38:#39        // checkPubID:(Ljava/lang/String;)Z
  #41 = Methodref          #12.#40        // scala/xml/dtd/NoExternalID$.checkPubID:(Ljava/lang/String;)Z
  #42 = Utf8               checkSysID
  #43 = NameAndType        #42:#39        // checkSysID:(Ljava/lang/String;)Z
  #44 = Methodref          #12.#43        // scala/xml/dtd/NoExternalID$.checkSysID:(Ljava/lang/String;)Z
  #45 = Utf8               isValidIANAEncoding
  #46 = Utf8               (Lscala/collection/Seq;)Z
  #47 = Utf8               (Lscala/collection/Seq<Ljava/lang/Object;>;)Z
  #48 = Utf8               ianaEncoding
  #49 = NameAndType        #45:#46        // isValidIANAEncoding:(Lscala/collection/Seq;)Z
  #50 = Methodref          #12.#49        // scala/xml/dtd/NoExternalID$.isValidIANAEncoding:(Lscala/collection/Seq;)Z
  #51 = Utf8               Lscala/collection/Seq;
  #52 = Utf8               isPubIDChar
  #53 = Utf8               (C)Z
  #54 = Utf8               ch
  #55 = NameAndType        #52:#53        // isPubIDChar:(C)Z
  #56 = Methodref          #12.#55        // scala/xml/dtd/NoExternalID$.isPubIDChar:(C)Z
  #57 = Utf8               C
  #58 = Utf8               isName
  #59 = NameAndType        #58:#39        // isName:(Ljava/lang/String;)Z
  #60 = Methodref          #12.#59        // scala/xml/dtd/NoExternalID$.isName:(Ljava/lang/String;)Z
  #61 = Utf8               isNameStart
  #62 = NameAndType        #61:#53        // isNameStart:(C)Z
  #63 = Methodref          #12.#62        // scala/xml/dtd/NoExternalID$.isNameStart:(C)Z
  #64 = Utf8               isNameChar
  #65 = NameAndType        #64:#53        // isNameChar:(C)Z
  #66 = Methodref          #12.#65        // scala/xml/dtd/NoExternalID$.isNameChar:(C)Z
  #67 = Utf8               isAlphaDigit
  #68 = Utf8               c
  #69 = NameAndType        #67:#53        // isAlphaDigit:(C)Z
  #70 = Methodref          #12.#69        // scala/xml/dtd/NoExternalID$.isAlphaDigit:(C)Z
  #71 = Utf8               isAlpha
  #72 = NameAndType        #71:#53        // isAlpha:(C)Z
  #73 = Methodref          #12.#72        // scala/xml/dtd/NoExternalID$.isAlpha:(C)Z
  #74 = Utf8               isSpace
  #75 = Utf8               cs
  #76 = NameAndType        #74:#46        // isSpace:(Lscala/collection/Seq;)Z
  #77 = Methodref          #12.#76        // scala/xml/dtd/NoExternalID$.isSpace:(Lscala/collection/Seq;)Z
  #78 = NameAndType        #74:#53        // isSpace:(C)Z
  #79 = Methodref          #12.#78        // scala/xml/dtd/NoExternalID$.isSpace:(C)Z
  #80 = Utf8               Code
  #81 = Utf8               LocalVariableTable
  #82 = Utf8               MethodParameters
  #83 = Utf8               Signature
  #84 = Utf8               SourceFile
  #85 = Utf8               RuntimeVisibleAnnotations
  #86 = Utf8               ScalaSig
{
  public static java.lang.String toString();
    descriptor: ()Ljava/lang/String;
    flags: (0x0009) ACC_PUBLIC, ACC_STATIC
    Code:
      stack=1, locals=0, args_size=0
         0: getstatic     #16                 // Field scala/xml/dtd/NoExternalID$.MODULE$:Lscala/xml/dtd/NoExternalID$;
         3: invokevirtual #18                 // Method scala/xml/dtd/NoExternalID$.toString:()Ljava/lang/String;
         6: areturn

  public static scala.runtime.Null$ systemId();
    descriptor: ()Lscala/runtime/Null$;
    flags: (0x0009) ACC_PUBLIC, ACC_STATIC
    Code:
      stack=1, locals=0, args_size=0
         0: getstatic     #16                 // Field scala/xml/dtd/NoExternalID$.MODULE$:Lscala/xml/dtd/NoExternalID$;
         3: invokevirtual #22                 // Method scala/xml/dtd/NoExternalID$.systemId:()Lscala/runtime/Null$;
         6: areturn

  public static scala.runtime.Null$ publicId();
    descriptor: ()Lscala/runtime/Null$;
    flags: (0x0009) ACC_PUBLIC, ACC_STATIC
    Code:
      stack=1, locals=0, args_size=0
         0: getstatic     #16                 // Field scala/xml/dtd/NoExternalID$.MODULE$:Lscala/xml/dtd/NoExternalID$;
         3: invokevirtual #25                 // Method scala/xml/dtd/NoExternalID$.publicId:()Lscala/runtime/Null$;
         6: areturn

  public static scala.collection.mutable.StringBuilder buildString(scala.collection.mutable.StringBuilder);
    descriptor: (Lscala/collection/mutable/StringBuilder;)Lscala/collection/mutable/StringBuilder;
    flags: (0x0009) ACC_PUBLIC, ACC_STATIC
    Code:
      stack=2, locals=1, args_size=1
         0: getstatic     #16                 // Field scala/xml/dtd/NoExternalID$.MODULE$:Lscala/xml/dtd/NoExternalID$;
         3: aload_0
         4: invokevirtual #30                 // Method scala/xml/dtd/NoExternalID$.buildString:(Lscala/collection/mutable/StringBuilder;)Lscala/collection/mutable/StringBuilder;
         7: areturn
      LocalVariableTable:
        Start  Length  Slot  Name   Signature
            0       8     0    sb   Lscala/collection/mutable/StringBuilder;
    MethodParameters:
      Name                           Flags
      sb                             final

  public static java.lang.String quoted(java.lang.String);
    descriptor: (Ljava/lang/String;)Ljava/lang/String;
    flags: (0x0009) ACC_PUBLIC, ACC_STATIC
    Code:
      stack=2, locals=1, args_size=1
         0: getstatic     #16                 // Field scala/xml/dtd/NoExternalID$.MODULE$:Lscala/xml/dtd/NoExternalID$;
         3: aload_0
         4: invokevirtual #36                 // Method scala/xml/dtd/NoExternalID$.quoted:(Ljava/lang/String;)Ljava/lang/String;
         7: areturn
      LocalVariableTable:
        Start  Length  Slot  Name   Signature
            0       8     0     s   Ljava/lang/String;
    MethodParameters:
      Name                           Flags
      s                              final

  public static boolean checkPubID(java.lang.String);
    descriptor: (Ljava/lang/String;)Z
    flags: (0x0009) ACC_PUBLIC, ACC_STATIC
    Code:
      stack=2, locals=1, args_size=1
         0: getstatic     #16                 // Field scala/xml/dtd/NoExternalID$.MODULE$:Lscala/xml/dtd/NoExternalID$;
         3: aload_0
         4: invokevirtual #41                 // Method scala/xml/dtd/NoExternalID$.checkPubID:(Ljava/lang/String;)Z
         7: ireturn
      LocalVariableTable:
        Start  Length  Slot  Name   Signature
            0       8     0     s   Ljava/lang/String;
    MethodParameters:
      Name                           Flags
      s                              final

  public static boolean checkSysID(java.lang.String);
    descriptor: (Ljava/lang/String;)Z
    flags: (0x0009) ACC_PUBLIC, ACC_STATIC
    Code:
      stack=2, locals=1, args_size=1
         0: getstatic     #16                 // Field scala/xml/dtd/NoExternalID$.MODULE$:Lscala/xml/dtd/NoExternalID$;
         3: aload_0
         4: invokevirtual #44                 // Method scala/xml/dtd/NoExternalID$.checkSysID:(Ljava/lang/String;)Z
         7: ireturn
      LocalVariableTable:
        Start  Length  Slot  Name   Signature
            0       8     0     s   Ljava/lang/String;
    MethodParameters:
      Name                           Flags
      s                              final

  public static boolean isValidIANAEncoding(scala.collection.Seq<java.lang.Object>);
    descriptor: (Lscala/collection/Seq;)Z
    flags: (0x0009) ACC_PUBLIC, ACC_STATIC
    Code:
      stack=2, locals=1, args_size=1
         0: getstatic     #16                 // Field scala/xml/dtd/NoExternalID$.MODULE$:Lscala/xml/dtd/NoExternalID$;
         3: aload_0
         4: invokevirtual #50                 // Method scala/xml/dtd/NoExternalID$.isValidIANAEncoding:(Lscala/collection/Seq;)Z
         7: ireturn
      LocalVariableTable:
        Start  Length  Slot  Name   Signature
            0       8     0 ianaEncoding   Lscala/collection/Seq;
    Signature: #47                          // (Lscala/collection/Seq<Ljava/lang/Object;>;)Z
    MethodParameters:
      Name                           Flags
      ianaEncoding                   final

  public static boolean isPubIDChar(char);
    descriptor: (C)Z
    flags: (0x0009) ACC_PUBLIC, ACC_STATIC
    Code:
      stack=2, locals=1, args_size=1
         0: getstatic     #16                 // Field scala/xml/dtd/NoExternalID$.MODULE$:Lscala/xml/dtd/NoExternalID$;
         3: iload_0
         4: invokevirtual #56                 // Method scala/xml/dtd/NoExternalID$.isPubIDChar:(C)Z
         7: ireturn
      LocalVariableTable:
        Start  Length  Slot  Name   Signature
            0       8     0    ch   C
    MethodParameters:
      Name                           Flags
      ch                             final

  public static boolean isName(java.lang.String);
    descriptor: (Ljava/lang/String;)Z
    flags: (0x0009) ACC_PUBLIC, ACC_STATIC
    Code:
      stack=2, locals=1, args_size=1
         0: getstatic     #16                 // Field scala/xml/dtd/NoExternalID$.MODULE$:Lscala/xml/dtd/NoExternalID$;
         3: aload_0
         4: invokevirtual #60                 // Method scala/xml/dtd/NoExternalID$.isName:(Ljava/lang/String;)Z
         7: ireturn
      LocalVariableTable:
        Start  Length  Slot  Name   Signature
            0       8     0     s   Ljava/lang/String;
    MethodParameters:
      Name                           Flags
      s                              final

  public static boolean isNameStart(char);
    descriptor: (C)Z
    flags: (0x0009) ACC_PUBLIC, ACC_STATIC
    Code:
      stack=2, locals=1, args_size=1
         0: getstatic     #16                 // Field scala/xml/dtd/NoExternalID$.MODULE$:Lscala/xml/dtd/NoExternalID$;
         3: iload_0
         4: invokevirtual #63                 // Method scala/xml/dtd/NoExternalID$.isNameStart:(C)Z
         7: ireturn
      LocalVariableTable:
        Start  Length  Slot  Name   Signature
            0       8     0    ch   C
    MethodParameters:
      Name                           Flags
      ch                             final

  public static boolean isNameChar(char);
    descriptor: (C)Z
    flags: (0x0009) ACC_PUBLIC, ACC_STATIC
    Code:
      stack=2, locals=1, args_size=1
         0: getstatic     #16                 // Field scala/xml/dtd/NoExternalID$.MODULE$:Lscala/xml/dtd/NoExternalID$;
         3: iload_0
         4: invokevirtual #66                 // Method scala/xml/dtd/NoExternalID$.isNameChar:(C)Z
         7: ireturn
      LocalVariableTable:
        Start  Length  Slot  Name   Signature
            0       8     0    ch   C
    MethodParameters:
      Name                           Flags
      ch                             final

  public static boolean isAlphaDigit(char);
    descriptor: (C)Z
    flags: (0x0009) ACC_PUBLIC, ACC_STATIC
    Code:
      stack=2, locals=1, args_size=1
         0: getstatic     #16                 // Field scala/xml/dtd/NoExternalID$.MODULE$:Lscala/xml/dtd/NoExternalID$;
         3: iload_0
         4: invokevirtual #70                 // Method scala/xml/dtd/NoExternalID$.isAlphaDigit:(C)Z
         7: ireturn
      LocalVariableTable:
        Start  Length  Slot  Name   Signature
            0       8     0     c   C
    MethodParameters:
      Name                           Flags
      c                              final

  public static boolean isAlpha(char);
    descriptor: (C)Z
    flags: (0x0009) ACC_PUBLIC, ACC_STATIC
    Code:
      stack=2, locals=1, args_size=1
         0: getstatic     #16                 // Field scala/xml/dtd/NoExternalID$.MODULE$:Lscala/xml/dtd/NoExternalID$;
         3: iload_0
         4: invokevirtual #73                 // Method scala/xml/dtd/NoExternalID$.isAlpha:(C)Z
         7: ireturn
      LocalVariableTable:
        Start  Length  Slot  Name   Signature
            0       8     0     c   C
    MethodParameters:
      Name                           Flags
      c                              final

  public static boolean isSpace(scala.collection.Seq<java.lang.Object>);
    descriptor: (Lscala/collection/Seq;)Z
    flags: (0x0009) ACC_PUBLIC, ACC_STATIC
    Code:
      stack=2, locals=1, args_size=1
         0: getstatic     #16                 // Field scala/xml/dtd/NoExternalID$.MODULE$:Lscala/xml/dtd/NoExternalID$;
         3: aload_0
         4: invokevirtual #77                 // Method scala/xml/dtd/NoExternalID$.isSpace:(Lscala/collection/Seq;)Z
         7: ireturn
      LocalVariableTable:
        Start  Length  Slot  Name   Signature
            0       8     0    cs   Lscala/collection/Seq;
    Signature: #47                          // (Lscala/collection/Seq<Ljava/lang/Object;>;)Z
    MethodParameters:
      Name                           Flags
      cs                             final

  public static boolean isSpace(char);
    descriptor: (C)Z
    flags: (0x0009) ACC_PUBLIC, ACC_STATIC
    Code:
      stack=2, locals=1, args_size=1
         0: getstatic     #16                 // Field scala/xml/dtd/NoExternalID$.MODULE$:Lscala/xml/dtd/NoExternalID$;
         3: iload_0
         4: invokevirtual #79                 // Method scala/xml/dtd/NoExternalID$.isSpace:(C)Z
         7: ireturn
      LocalVariableTable:
        Start  Length  Slot  Name   Signature
            0       8     0    ch   C
    MethodParameters:
      Name                           Flags
      ch                             final
}
SourceFile: "ExternalID.scala"
RuntimeVisibleAnnotations:
  0: #6(#7=s#8)
    scala.reflect.ScalaSignature(
      bytes="\u0006\u00051:Q\u0001C\u0005\t\u0002A1QAE\u0005\t\u0002MAQaF\u0001\u0005\u0002aAq!G\u0001C\u0002\u0013\u0005!\u0004\u0003\u0004 \u0003\u0001\u0006Ia\u0007\u0005\bA\u0005\u0011\r\u0011\"\u0001\u001b\u0011\u0019\t\u0013\u0001)A\u00057!)!%\u0001C!G\u0005aaj\\#yi\u0016\u0014h.\u00197J\t*\u0011!bC\u0001\u0004IR$\'B\u0001\u0007\u000e\u0003\rAX\u000e\u001c\u0006\u0002\u001d\u0005)1oY1mC\u000e\u0001\u0001CA\t\u0002\u001b\u0005I!\u0001\u0004(p\u000bb$XM\u001d8bY&#5CA\u0001\u0015!\t\tR#\u0003\u0002\u0017\u0013\tQQ\t\u001f;fe:\fG.\u0013#\u0002\rqJg.\u001b;?)\u0005\u0001\u0012\u0001\u00039vE2L7-\u00133\u0016\u0003m\u0001\"\u0001H\u000f\u000e\u00035I!AH\u0007\u0003\t9+H\u000e\\\u0001\naV\u0014G.[2JI\u0002\n\u0001b]=ti\u0016l\u0017\nZ\u0001\ngf\u001cH/Z7JI\u0002\n\u0001\u0002^8TiJLgn\u001a\u000b\u0002IA\u0011QEK\u0007\u0002M)\u0011q\u0005K\u0001\u0005Y\u0006twMC\u0001*\u0003\u0011Q\u0017M^1\n\u0005-2#AB*ue&tw\r"
    )
  ScalaSig: length = 0x3 (unknown attribute)
   05 02 00
