Classfile /Users/mw/Projects/slang-braindump/.jar/jar8/assemble/slang-braindump/assemble/content/scala/xml/dtd/ParsedEntityDecl.class
  Last modified May 29, 2022; size 5957 bytes
  SHA-256 checksum d5ffed393c6770c8fe07a9c7bef3d2f9161c6114ae462308d1dfccaab66b8a2f
  Compiled from "Decl.scala"
public class scala.xml.dtd.ParsedEntityDecl extends scala.xml.dtd.EntityDecl implements scala.Product,java.io.Serializable
  minor version: 0
  major version: 52
  flags: (0x0021) ACC_PUBLIC, ACC_SUPER
  this_class: #2                          // scala/xml/dtd/ParsedEntityDecl
  super_class: #4                         // scala/xml/dtd/EntityDecl
  interfaces: 2, fields: 2, methods: 20, attributes: 4
Constant pool:
    #1 = Utf8               scala/xml/dtd/ParsedEntityDecl
    #2 = Class              #1            // scala/xml/dtd/ParsedEntityDecl
    #3 = Utf8               scala/xml/dtd/EntityDecl
    #4 = Class              #3            // scala/xml/dtd/EntityDecl
    #5 = Utf8               scala/Product
    #6 = Class              #5            // scala/Product
    #7 = Utf8               java/io/Serializable
    #8 = Class              #7            // java/io/Serializable
    #9 = Utf8               Decl.scala
   #10 = Utf8               Lscala/reflect/ScalaSignature;
   #11 = Utf8               bytes
   #12 = Utf8               \u0006\u0005\u00055d\u0001B\r\u001b\u0001\u0006B\u0001B\u000e\u0001\u0003\u0016\u0004%\ta\u000e\u0005\t\u0001\u0002\u0011\t\u0012)A\u0005q!A\u0011\t\u0001BK\u0002\u0013\u0005!\t\u0003\u0005G\u0001\tE\t\u0015!\u0003D\u0011\u00159\u0005\u0001\"\u0001I\u0011\u0015a\u0005\u0001\"\u0011N\u0011\u001d!\u0006!!A\u0005\u0002UCq\u0001\u0017\u0001\u0012\u0002\u0013\u0005\u0011\fC\u0004e\u0001E\u0005I\u0011A3\t\u000f\u001d\u0004\u0011\u0011!C!Q\"9\u0001\u000fAA\u0001\n\u0003\t\bbB;\u0001\u0003\u0003%\tA\u001e\u0005\by\u0002\t\t\u0011\"\u0011~\u0011%\tI\u0001AA\u0001\n\u0003\tY\u0001C\u0005\u0002\u0016\u0001\t\t\u0011\"\u0011\u0002\u0018!I\u00111\u0004\u0001\u0002\u0002\u0013\u0005\u0013Q\u0004\u0005\n\u0003?\u0001\u0011\u0011!C!\u0003C9\u0011\"!\n\u001b\u0003\u0003E\t!a\n\u0007\u0011eQ\u0012\u0011!E\u0001\u0003SAaaR\n\u0005\u0002\u0005\u0005\u0003\"CA\"\'\u0005\u0005IQIA#\u0011%\t9eEA\u0001\n\u0003\u000bI\u0005C\u0005\u0002PM\t\t\u0011\"!\u0002R!I\u00111M\n\u0002\u0002\u0013%\u0011Q\r\u0002\u0011!\u0006\u00148/\u001a3F]RLG/\u001f#fG2T!a\u0007\u000f\u0002\u0007\u0011$HM\u0003\u0002\u001e=\u0005\u0019\u00010\u001c7\u000b\u0003}\tQa]2bY\u0006\u001c\u0001a\u0005\u0003\u0001E\u0019R\u0003CA\u0012%\u001b\u0005Q\u0012BA\u0013\u001b\u0005))e\u000e^5us\u0012+7\r\u001c\t\u0003O!j\u0011AH\u0005\u0003Sy\u0011q\u0001\u0015:pIV\u001cG\u000f\u0005\u0002,g9\u0011A&\r\b\u0003[Aj\u0011A\f\u0006\u0003_\u0001\na\u0001\u0010:p_Rt\u0014\"A\u0010\n\u0005Ir\u0012a\u00029bG.\fw-Z\u0005\u0003iU\u0012AbU3sS\u0006d\u0017N_1cY\u0016T!A\r\u0010\u0002\t9\fW.Z\u000b\u0002qA\u0011\u0011(\u0010\b\u0003um\u0002\"!\f\u0010\n\u0005qr\u0012A\u0002)sK\u0012,g-\u0003\u0002?\u007f\t11\u000b\u001e:j]\u001eT!\u0001\u0010\u0010\u0002\u000b9\fW.\u001a\u0011\u0002\r\u0015tG\u000fZ3g+\u0005\u0019\u0005CA\u0012E\u0013\t)%DA\u0005F]RLG/\u001f#fM\u00069QM\u001c;eK\u001a\u0004\u0013A\u0002\u001fj]&$h\bF\u0002J\u0015.\u0003\"a\t\u0001\t\u000bY*\u0001\u0019\u0001\u001d\t\u000b\u0005+\u0001\u0019A\"\u0002\u0017\t,\u0018\u000e\u001c3TiJLgn\u001a\u000b\u0003\u001dJ\u0003\"a\u0014)\u000f\u0005\u001d\n\u0014BA)6\u00055\u0019FO]5oO\n+\u0018\u000e\u001c3fe\")1K\u0002a\u0001\u001d\u0006\u00111OY\u0001\u0005G>\u0004\u0018\u0010F\u0002J-^CqAN\u0004\u0011\u0002\u0003\u0007\u0001\bC\u0004B\u000fA\u0005\t\u0019A\"\u0002\u001d\r|\u0007/\u001f\u0013eK\u001a\fW\u000f\u001c;%cU\t!L\u000b\u000297.\nA\f\u0005\u0002^E6\taL\u0003\u0002`A\u0006IQO\\2iK\u000e\\W\r\u001a\u0006\u0003Cz\t!\"\u00198o_R\fG/[8o\u0013\t\u0019gLA\tv]\u000eDWmY6fIZ\u000b\'/[1oG\u0016\fabY8qs\u0012\"WMZ1vYR$#\'F\u0001gU\t\u00195,A\u0007qe>$Wo\u0019;Qe\u00164\u0017\u000e_\u000b\u0002SB\u0011!n\\\u0007\u0002W*\u0011A.\\\u0001\u0005Y\u0006twMC\u0001o\u0003\u0011Q\u0017M^1\n\u0005yZ\u0017\u0001\u00049s_\u0012,8\r^!sSRLX#\u0001:\u0011\u0005\u001d\u001a\u0018B\u0001;\u001f\u0005\rIe\u000e^\u0001\u000faJ|G-^2u\u000b2,W.\u001a8u)\t9(\u0010\u0005\u0002(q&\u0011\u0011P\b\u0002\u0004\u0003:L\bbB>\r\u0003\u0003\u0005\rA]\u0001\u0004q\u0012\n\u0014a\u00049s_\u0012,8\r^%uKJ\fGo\u001c:\u0016\u0003y\u0004Ba`A\u0003o6\u0011\u0011\u0011\u0001\u0006\u0004\u0003\u0007q\u0012AC2pY2,7\r^5p]&!\u0011qAA\u0001\u0005!IE/\u001a:bi>\u0014\u0018\u0001C2b]\u0016\u000bX/\u00197\u0015\t\u00055\u00111\u0003\t\u0004O\u0005=\u0011bAA\t=\t9!i\\8mK\u0006t\u0007bB>\u000f\u0003\u0003\u0005\ra^\u0001\u0013aJ|G-^2u\u000b2,W.\u001a8u\u001d\u0006lW\rF\u0002j\u00033Aqa_\b\u0002\u0002\u0003\u0007!/\u0001\u0005iCND7i\u001c3f)\u0005\u0011\u0018AB3rk\u0006d7\u000f\u0006\u0003\u0002\u000e\u0005\r\u0002bB>\u0012\u0003\u0003\u0005\ra^\u0001\u0011!\u0006\u00148/\u001a3F]RLG/\u001f#fG2\u0004\"aI\n\u0014\u000bM\tY#a\u000e\u0011\u000f\u00055\u00121\u0007\u001dD\u00136\u0011\u0011q\u0006\u0006\u0004\u0003cq\u0012a\u0002:v]RLW.Z\u0005\u0005\u0003k\tyCA\tBEN$(/Y2u\rVt7\r^5p]J\u0002B!!\u000f\u0002@5\u0011\u00111\b\u0006\u0004\u0003{i\u0017AA5p\u0013\r!\u00141\b\u000b\u0003\u0003O\t\u0001\u0002^8TiJLgn\u001a\u000b\u0002S\u0006)\u0011\r\u001d9msR)\u0011*a\u0013\u0002N!)aG\u0006a\u0001q!)\u0011I\u0006a\u0001\u0007\u00069QO\\1qa2LH\u0003BA*\u0003?\u0002RaJA+\u00033J1!a\u0016\u001f\u0005\u0019y\u0005\u000f^5p]B)q%a\u00179\u0007&\u0019\u0011Q\f\u0010\u0003\rQ+\b\u000f\\33\u0011!\t\tgFA\u0001\u0002\u0004I\u0015a\u0001=%a\u0005aqO]5uKJ+\u0007\u000f\\1dKR\u0011\u0011q\r\t\u0004U\u0006%\u0014bAA6W\n1qJ\u00196fGR\u0004
   #13 = Utf8               name
   #14 = Utf8               Ljava/lang/String;
   #15 = Utf8               entdef
   #16 = Utf8               Lscala/xml/dtd/EntityDef;
   #17 = Utf8               unapply
   #18 = Utf8               (Lscala/xml/dtd/ParsedEntityDecl;)Lscala/Option;
   #19 = Utf8               (Lscala/xml/dtd/ParsedEntityDecl;)Lscala/Option<Lscala/Tuple2<Ljava/lang/String;Lscala/xml/dtd/EntityDef;>;>;
   #20 = Utf8               x$0
   #21 = Utf8               scala/xml/dtd/ParsedEntityDecl$
   #22 = Class              #21           // scala/xml/dtd/ParsedEntityDecl$
   #23 = Utf8               MODULE$
   #24 = Utf8               Lscala/xml/dtd/ParsedEntityDecl$;
   #25 = NameAndType        #23:#24       // MODULE$:Lscala/xml/dtd/ParsedEntityDecl$;
   #26 = Fieldref           #22.#25       // scala/xml/dtd/ParsedEntityDecl$.MODULE$:Lscala/xml/dtd/ParsedEntityDecl$;
   #27 = NameAndType        #17:#18       // unapply:(Lscala/xml/dtd/ParsedEntityDecl;)Lscala/Option;
   #28 = Methodref          #22.#27       // scala/xml/dtd/ParsedEntityDecl$.unapply:(Lscala/xml/dtd/ParsedEntityDecl;)Lscala/Option;
   #29 = Utf8               Lscala/xml/dtd/ParsedEntityDecl;
   #30 = Utf8               apply
   #31 = Utf8               (Ljava/lang/String;Lscala/xml/dtd/EntityDef;)Lscala/xml/dtd/ParsedEntityDecl;
   #32 = NameAndType        #30:#31       // apply:(Ljava/lang/String;Lscala/xml/dtd/EntityDef;)Lscala/xml/dtd/ParsedEntityDecl;
   #33 = Methodref          #22.#32       // scala/xml/dtd/ParsedEntityDecl$.apply:(Ljava/lang/String;Lscala/xml/dtd/EntityDef;)Lscala/xml/dtd/ParsedEntityDecl;
   #34 = Utf8               tupled
   #35 = Utf8               ()Lscala/Function1;
   #36 = Utf8               ()Lscala/Function1<Lscala/Tuple2<Ljava/lang/String;Lscala/xml/dtd/EntityDef;>;Lscala/xml/dtd/ParsedEntityDecl;>;
   #37 = NameAndType        #34:#35       // tupled:()Lscala/Function1;
   #38 = Methodref          #22.#37       // scala/xml/dtd/ParsedEntityDecl$.tupled:()Lscala/Function1;
   #39 = Utf8               curried
   #40 = Utf8               ()Lscala/Function1<Ljava/lang/String;Lscala/Function1<Lscala/xml/dtd/EntityDef;Lscala/xml/dtd/ParsedEntityDecl;>;>;
   #41 = NameAndType        #39:#35       // curried:()Lscala/Function1;
   #42 = Methodref          #22.#41       // scala/xml/dtd/ParsedEntityDecl$.curried:()Lscala/Function1;
   #43 = Utf8               productElementNames
   #44 = Utf8               ()Lscala/collection/Iterator;
   #45 = Utf8               ()Lscala/collection/Iterator<Ljava/lang/String;>;
   #46 = Utf8               productElementNames$
   #47 = Utf8               (Lscala/Product;)Lscala/collection/Iterator;
   #48 = NameAndType        #46:#47       // productElementNames$:(Lscala/Product;)Lscala/collection/Iterator;
   #49 = InterfaceMethodref #6.#48        // scala/Product.productElementNames$:(Lscala/Product;)Lscala/collection/Iterator;
   #50 = Utf8               this
   #51 = Utf8               ()Ljava/lang/String;
   #52 = NameAndType        #13:#14       // name:Ljava/lang/String;
   #53 = Fieldref           #2.#52        // scala/xml/dtd/ParsedEntityDecl.name:Ljava/lang/String;
   #54 = Utf8               ()Lscala/xml/dtd/EntityDef;
   #55 = NameAndType        #15:#16       // entdef:Lscala/xml/dtd/EntityDef;
   #56 = Fieldref           #2.#55        // scala/xml/dtd/ParsedEntityDecl.entdef:Lscala/xml/dtd/EntityDef;
   #57 = Utf8               buildString
   #58 = Utf8               (Lscala/collection/mutable/StringBuilder;)Lscala/collection/mutable/StringBuilder;
   #59 = Utf8               sb
   #60 = Utf8               <!ENTITY
   #61 = String             #60           // <!ENTITY
   #62 = Utf8               scala/collection/mutable/StringBuilder
   #63 = Class              #62           // scala/collection/mutable/StringBuilder
   #64 = Utf8               append
   #65 = Utf8               (Ljava/lang/String;)Lscala/collection/mutable/StringBuilder;
   #66 = NameAndType        #64:#65       // append:(Ljava/lang/String;)Lscala/collection/mutable/StringBuilder;
   #67 = Methodref          #63.#66       // scala/collection/mutable/StringBuilder.append:(Ljava/lang/String;)Lscala/collection/mutable/StringBuilder;
   #68 = NameAndType        #13:#51       // name:()Ljava/lang/String;
   #69 = Methodref          #2.#68        // scala/xml/dtd/ParsedEntityDecl.name:()Ljava/lang/String;
   #70 = Utf8               (C)Lscala/collection/mutable/StringBuilder;
   #71 = NameAndType        #64:#70       // append:(C)Lscala/collection/mutable/StringBuilder;
   #72 = Methodref          #63.#71       // scala/collection/mutable/StringBuilder.append:(C)Lscala/collection/mutable/StringBuilder;
   #73 = NameAndType        #15:#54       // entdef:()Lscala/xml/dtd/EntityDef;
   #74 = Methodref          #2.#73        // scala/xml/dtd/ParsedEntityDecl.entdef:()Lscala/xml/dtd/EntityDef;
   #75 = Utf8               scala/xml/dtd/EntityDef
   #76 = Class              #75           // scala/xml/dtd/EntityDef
   #77 = NameAndType        #57:#58       // buildString:(Lscala/collection/mutable/StringBuilder;)Lscala/collection/mutable/StringBuilder;
   #78 = Methodref          #76.#77       // scala/xml/dtd/EntityDef.buildString:(Lscala/collection/mutable/StringBuilder;)Lscala/collection/mutable/StringBuilder;
   #79 = Utf8               Lscala/collection/mutable/StringBuilder;
   #80 = Utf8               copy
   #81 = Utf8               <init>
   #82 = Utf8               (Ljava/lang/String;Lscala/xml/dtd/EntityDef;)V
   #83 = NameAndType        #81:#82       // "<init>":(Ljava/lang/String;Lscala/xml/dtd/EntityDef;)V
   #84 = Methodref          #2.#83        // scala/xml/dtd/ParsedEntityDecl."<init>":(Ljava/lang/String;Lscala/xml/dtd/EntityDef;)V
   #85 = Utf8               copy$default$1
   #86 = Utf8               copy$default$2
   #87 = Utf8               productPrefix
   #88 = Utf8               ParsedEntityDecl
   #89 = String             #88           // ParsedEntityDecl
   #90 = Utf8               productArity
   #91 = Utf8               ()I
   #92 = Utf8               productElement
   #93 = Utf8               (I)Ljava/lang/Object;
   #94 = Utf8               x$1
   #95 = Utf8               scala/runtime/Statics
   #96 = Class              #95           // scala/runtime/Statics
   #97 = Utf8               ioobe
   #98 = NameAndType        #97:#93       // ioobe:(I)Ljava/lang/Object;
   #99 = Methodref          #96.#98       // scala/runtime/Statics.ioobe:(I)Ljava/lang/Object;
  #100 = Utf8               I
  #101 = Utf8               java/lang/Object
  #102 = Class              #101          // java/lang/Object
  #103 = Utf8               productIterator
  #104 = Utf8               ()Lscala/collection/Iterator<Ljava/lang/Object;>;
  #105 = Utf8               scala/runtime/ScalaRunTime$
  #106 = Class              #105          // scala/runtime/ScalaRunTime$
  #107 = Utf8               Lscala/runtime/ScalaRunTime$;
  #108 = NameAndType        #23:#107      // MODULE$:Lscala/runtime/ScalaRunTime$;
  #109 = Fieldref           #106.#108     // scala/runtime/ScalaRunTime$.MODULE$:Lscala/runtime/ScalaRunTime$;
  #110 = Utf8               typedProductIterator
  #111 = NameAndType        #110:#47      // typedProductIterator:(Lscala/Product;)Lscala/collection/Iterator;
  #112 = Methodref          #106.#111     // scala/runtime/ScalaRunTime$.typedProductIterator:(Lscala/Product;)Lscala/collection/Iterator;
  #113 = Utf8               canEqual
  #114 = Utf8               (Ljava/lang/Object;)Z
  #115 = Utf8               Ljava/lang/Object;
  #116 = Utf8               productElementName
  #117 = Utf8               (I)Ljava/lang/String;
  #118 = String             #13           // name
  #119 = String             #15           // entdef
  #120 = Utf8               java/lang/String
  #121 = Class              #120          // java/lang/String
  #122 = Utf8               hashCode
  #123 = Utf8               _hashCode
  #124 = Utf8               (Lscala/Product;)I
  #125 = NameAndType        #123:#124     // _hashCode:(Lscala/Product;)I
  #126 = Methodref          #106.#125     // scala/runtime/ScalaRunTime$._hashCode:(Lscala/Product;)I
  #127 = Utf8               equals
  #128 = NameAndType        #127:#114     // equals:(Ljava/lang/Object;)Z
  #129 = Methodref          #102.#128     // java/lang/Object.equals:(Ljava/lang/Object;)Z
  #130 = NameAndType        #113:#114     // canEqual:(Ljava/lang/Object;)Z
  #131 = Methodref          #2.#130       // scala/xml/dtd/ParsedEntityDecl.canEqual:(Ljava/lang/Object;)Z
  #132 = Utf8               ()V
  #133 = NameAndType        #81:#132      // "<init>":()V
  #134 = Methodref          #4.#133       // scala/xml/dtd/EntityDecl."<init>":()V
  #135 = Utf8               $init$
  #136 = Utf8               (Lscala/Product;)V
  #137 = NameAndType        #135:#136     // $init$:(Lscala/Product;)V
  #138 = InterfaceMethodref #6.#137       // scala/Product.$init$:(Lscala/Product;)V
  #139 = Utf8               Code
  #140 = Utf8               LocalVariableTable
  #141 = Utf8               Signature
  #142 = Utf8               MethodParameters
  #143 = Utf8               LineNumberTable
  #144 = Utf8               StackMapTable
  #145 = Utf8               SourceFile
  #146 = Utf8               RuntimeVisibleAnnotations
  #147 = Utf8               ScalaInlineInfo
  #148 = Utf8               ScalaSig
{
  private final java.lang.String name;
    descriptor: Ljava/lang/String;
    flags: (0x0012) ACC_PRIVATE, ACC_FINAL

  private final scala.xml.dtd.EntityDef entdef;
    descriptor: Lscala/xml/dtd/EntityDef;
    flags: (0x0012) ACC_PRIVATE, ACC_FINAL

  public static scala.Option<scala.Tuple2<java.lang.String, scala.xml.dtd.EntityDef>> unapply(scala.xml.dtd.ParsedEntityDecl);
    descriptor: (Lscala/xml/dtd/ParsedEntityDecl;)Lscala/Option;
    flags: (0x0009) ACC_PUBLIC, ACC_STATIC
    Code:
      stack=2, locals=1, args_size=1
         0: getstatic     #26                 // Field scala/xml/dtd/ParsedEntityDecl$.MODULE$:Lscala/xml/dtd/ParsedEntityDecl$;
         3: aload_0
         4: invokevirtual #28                 // Method scala/xml/dtd/ParsedEntityDecl$.unapply:(Lscala/xml/dtd/ParsedEntityDecl;)Lscala/Option;
         7: areturn
      LocalVariableTable:
        Start  Length  Slot  Name   Signature
            0       8     0   x$0   Lscala/xml/dtd/ParsedEntityDecl;
    Signature: #19                          // (Lscala/xml/dtd/ParsedEntityDecl;)Lscala/Option<Lscala/Tuple2<Ljava/lang/String;Lscala/xml/dtd/EntityDef;>;>;
    MethodParameters:
      Name                           Flags
      x$0                            final

  public static scala.xml.dtd.ParsedEntityDecl apply(java.lang.String, scala.xml.dtd.EntityDef);
    descriptor: (Ljava/lang/String;Lscala/xml/dtd/EntityDef;)Lscala/xml/dtd/ParsedEntityDecl;
    flags: (0x0009) ACC_PUBLIC, ACC_STATIC
    Code:
      stack=3, locals=2, args_size=2
         0: getstatic     #26                 // Field scala/xml/dtd/ParsedEntityDecl$.MODULE$:Lscala/xml/dtd/ParsedEntityDecl$;
         3: aload_0
         4: aload_1
         5: invokevirtual #33                 // Method scala/xml/dtd/ParsedEntityDecl$.apply:(Ljava/lang/String;Lscala/xml/dtd/EntityDef;)Lscala/xml/dtd/ParsedEntityDecl;
         8: areturn
      LocalVariableTable:
        Start  Length  Slot  Name   Signature
            0       9     0  name   Ljava/lang/String;
            0       9     1 entdef   Lscala/xml/dtd/EntityDef;
    MethodParameters:
      Name                           Flags
      name                           final
      entdef                         final

  public static scala.Function1<scala.Tuple2<java.lang.String, scala.xml.dtd.EntityDef>, scala.xml.dtd.ParsedEntityDecl> tupled();
    descriptor: ()Lscala/Function1;
    flags: (0x0009) ACC_PUBLIC, ACC_STATIC
    Code:
      stack=1, locals=0, args_size=0
         0: getstatic     #26                 // Field scala/xml/dtd/ParsedEntityDecl$.MODULE$:Lscala/xml/dtd/ParsedEntityDecl$;
         3: invokevirtual #38                 // Method scala/xml/dtd/ParsedEntityDecl$.tupled:()Lscala/Function1;
         6: areturn
    Signature: #36                          // ()Lscala/Function1<Lscala/Tuple2<Ljava/lang/String;Lscala/xml/dtd/EntityDef;>;Lscala/xml/dtd/ParsedEntityDecl;>;

  public static scala.Function1<java.lang.String, scala.Function1<scala.xml.dtd.EntityDef, scala.xml.dtd.ParsedEntityDecl>> curried();
    descriptor: ()Lscala/Function1;
    flags: (0x0009) ACC_PUBLIC, ACC_STATIC
    Code:
      stack=1, locals=0, args_size=0
         0: getstatic     #26                 // Field scala/xml/dtd/ParsedEntityDecl$.MODULE$:Lscala/xml/dtd/ParsedEntityDecl$;
         3: invokevirtual #42                 // Method scala/xml/dtd/ParsedEntityDecl$.curried:()Lscala/Function1;
         6: areturn
    Signature: #40                          // ()Lscala/Function1<Ljava/lang/String;Lscala/Function1<Lscala/xml/dtd/EntityDef;Lscala/xml/dtd/ParsedEntityDecl;>;>;

  public scala.collection.Iterator<java.lang.String> productElementNames();
    descriptor: ()Lscala/collection/Iterator;
    flags: (0x0001) ACC_PUBLIC
    Code:
      stack=1, locals=1, args_size=1
         0: aload_0
         1: invokestatic  #49                 // InterfaceMethod scala/Product.productElementNames$:(Lscala/Product;)Lscala/collection/Iterator;
         4: areturn
      LineNumberTable:
        line 76: 0
      LocalVariableTable:
        Start  Length  Slot  Name   Signature
            0       5     0  this   Lscala/xml/dtd/ParsedEntityDecl;
    Signature: #45                          // ()Lscala/collection/Iterator<Ljava/lang/String;>;

  public java.lang.String name();
    descriptor: ()Ljava/lang/String;
    flags: (0x0001) ACC_PUBLIC
    Code:
      stack=1, locals=1, args_size=1
         0: aload_0
         1: getfield      #53                 // Field name:Ljava/lang/String;
         4: areturn
      LineNumberTable:
        line 76: 0
      LocalVariableTable:
        Start  Length  Slot  Name   Signature
            0       5     0  this   Lscala/xml/dtd/ParsedEntityDecl;

  public scala.xml.dtd.EntityDef entdef();
    descriptor: ()Lscala/xml/dtd/EntityDef;
    flags: (0x0001) ACC_PUBLIC
    Code:
      stack=1, locals=1, args_size=1
         0: aload_0
         1: getfield      #56                 // Field entdef:Lscala/xml/dtd/EntityDef;
         4: areturn
      LineNumberTable:
        line 76: 0
      LocalVariableTable:
        Start  Length  Slot  Name   Signature
            0       5     0  this   Lscala/xml/dtd/ParsedEntityDecl;

  public scala.collection.mutable.StringBuilder buildString(scala.collection.mutable.StringBuilder);
    descriptor: (Lscala/collection/mutable/StringBuilder;)Lscala/collection/mutable/StringBuilder;
    flags: (0x0001) ACC_PUBLIC
    Code:
      stack=2, locals=2, args_size=2
         0: aload_1
         1: ldc           #61                 // String <!ENTITY
         3: invokevirtual #67                 // Method scala/collection/mutable/StringBuilder.append:(Ljava/lang/String;)Lscala/collection/mutable/StringBuilder;
         6: aload_0
         7: invokevirtual #69                 // Method name:()Ljava/lang/String;
        10: invokevirtual #67                 // Method scala/collection/mutable/StringBuilder.append:(Ljava/lang/String;)Lscala/collection/mutable/StringBuilder;
        13: bipush        32
        15: invokevirtual #72                 // Method scala/collection/mutable/StringBuilder.append:(C)Lscala/collection/mutable/StringBuilder;
        18: pop
        19: aload_0
        20: invokevirtual #74                 // Method entdef:()Lscala/xml/dtd/EntityDef;
        23: aload_1
        24: invokevirtual #78                 // Method scala/xml/dtd/EntityDef.buildString:(Lscala/collection/mutable/StringBuilder;)Lscala/collection/mutable/StringBuilder;
        27: bipush        62
        29: invokevirtual #72                 // Method scala/collection/mutable/StringBuilder.append:(C)Lscala/collection/mutable/StringBuilder;
        32: areturn
      LineNumberTable:
        line 78: 0
        line 79: 19
      LocalVariableTable:
        Start  Length  Slot  Name   Signature
            0      33     0  this   Lscala/xml/dtd/ParsedEntityDecl;
            0      33     1    sb   Lscala/collection/mutable/StringBuilder;
    MethodParameters:
      Name                           Flags
      sb                             final

  public scala.xml.dtd.ParsedEntityDecl copy(java.lang.String, scala.xml.dtd.EntityDef);
    descriptor: (Ljava/lang/String;Lscala/xml/dtd/EntityDef;)Lscala/xml/dtd/ParsedEntityDecl;
    flags: (0x0001) ACC_PUBLIC
    Code:
      stack=4, locals=3, args_size=3
         0: new           #2                  // class scala/xml/dtd/ParsedEntityDecl
         3: dup
         4: aload_1
         5: aload_2
         6: invokespecial #84                 // Method "<init>":(Ljava/lang/String;Lscala/xml/dtd/EntityDef;)V
         9: areturn
      LineNumberTable:
        line 76: 0
      LocalVariableTable:
        Start  Length  Slot  Name   Signature
            0      10     0  this   Lscala/xml/dtd/ParsedEntityDecl;
            0      10     1  name   Ljava/lang/String;
            0      10     2 entdef   Lscala/xml/dtd/EntityDef;
    MethodParameters:
      Name                           Flags
      name                           final
      entdef                         final

  public java.lang.String copy$default$1();
    descriptor: ()Ljava/lang/String;
    flags: (0x0001) ACC_PUBLIC
    Code:
      stack=1, locals=1, args_size=1
         0: aload_0
         1: invokevirtual #69                 // Method name:()Ljava/lang/String;
         4: areturn
      LineNumberTable:
        line 76: 0
      LocalVariableTable:
        Start  Length  Slot  Name   Signature
            0       5     0  this   Lscala/xml/dtd/ParsedEntityDecl;

  public scala.xml.dtd.EntityDef copy$default$2();
    descriptor: ()Lscala/xml/dtd/EntityDef;
    flags: (0x0001) ACC_PUBLIC
    Code:
      stack=1, locals=1, args_size=1
         0: aload_0
         1: invokevirtual #74                 // Method entdef:()Lscala/xml/dtd/EntityDef;
         4: areturn
      LineNumberTable:
        line 76: 0
      LocalVariableTable:
        Start  Length  Slot  Name   Signature
            0       5     0  this   Lscala/xml/dtd/ParsedEntityDecl;

  public java.lang.String productPrefix();
    descriptor: ()Ljava/lang/String;
    flags: (0x0001) ACC_PUBLIC
    Code:
      stack=1, locals=1, args_size=1
         0: ldc           #89                 // String ParsedEntityDecl
         2: areturn
      LineNumberTable:
        line 76: 0
      LocalVariableTable:
        Start  Length  Slot  Name   Signature
            0       3     0  this   Lscala/xml/dtd/ParsedEntityDecl;

  public int productArity();
    descriptor: ()I
    flags: (0x0001) ACC_PUBLIC
    Code:
      stack=1, locals=1, args_size=1
         0: iconst_2
         1: ireturn
      LineNumberTable:
        line 76: 0
      LocalVariableTable:
        Start  Length  Slot  Name   Signature
            0       2     0  this   Lscala/xml/dtd/ParsedEntityDecl;

  public java.lang.Object productElement(int);
    descriptor: (I)Ljava/lang/Object;
    flags: (0x0001) ACC_PUBLIC
    Code:
      stack=1, locals=3, args_size=2
         0: iload_1
         1: istore_2
         2: iload_2
         3: tableswitch   { // 0 to 1
                       0: 24
                       1: 31
                 default: 38
            }
        24: aload_0
        25: invokevirtual #69                 // Method name:()Ljava/lang/String;
        28: goto          45
        31: aload_0
        32: invokevirtual #74                 // Method entdef:()Lscala/xml/dtd/EntityDef;
        35: goto          45
        38: iload_1
        39: invokestatic  #99                 // Method scala/runtime/Statics.ioobe:(I)Ljava/lang/Object;
        42: goto          45
        45: areturn
      StackMapTable: number_of_entries = 4
        frame_type = 252 /* append */
          offset_delta = 24
          locals = [ int ]
        frame_type = 6 /* same */
        frame_type = 6 /* same */
        frame_type = 70 /* same_locals_1_stack_item */
          stack = [ class java/lang/Object ]
      LineNumberTable:
        line 76: 0
      LocalVariableTable:
        Start  Length  Slot  Name   Signature
            0      46     0  this   Lscala/xml/dtd/ParsedEntityDecl;
            0      46     1   x$1   I
    MethodParameters:
      Name                           Flags
      x$1                            final

  public scala.collection.Iterator<java.lang.Object> productIterator();
    descriptor: ()Lscala/collection/Iterator;
    flags: (0x0001) ACC_PUBLIC
    Code:
      stack=2, locals=1, args_size=1
         0: getstatic     #109                // Field scala/runtime/ScalaRunTime$.MODULE$:Lscala/runtime/ScalaRunTime$;
         3: aload_0
         4: invokevirtual #112                // Method scala/runtime/ScalaRunTime$.typedProductIterator:(Lscala/Product;)Lscala/collection/Iterator;
         7: areturn
      LineNumberTable:
        line 76: 0
      LocalVariableTable:
        Start  Length  Slot  Name   Signature
            0       8     0  this   Lscala/xml/dtd/ParsedEntityDecl;
    Signature: #104                         // ()Lscala/collection/Iterator<Ljava/lang/Object;>;

  public boolean canEqual(java.lang.Object);
    descriptor: (Ljava/lang/Object;)Z
    flags: (0x0001) ACC_PUBLIC
    Code:
      stack=1, locals=2, args_size=2
         0: aload_1
         1: instanceof    #2                  // class scala/xml/dtd/ParsedEntityDecl
         4: ireturn
      LineNumberTable:
        line 76: 0
      LocalVariableTable:
        Start  Length  Slot  Name   Signature
            0       5     0  this   Lscala/xml/dtd/ParsedEntityDecl;
            0       5     1   x$1   Ljava/lang/Object;
    MethodParameters:
      Name                           Flags
      x$1                            final

  public java.lang.String productElementName(int);
    descriptor: (I)Ljava/lang/String;
    flags: (0x0001) ACC_PUBLIC
    Code:
      stack=1, locals=3, args_size=2
         0: iload_1
         1: istore_2
         2: iload_2
         3: tableswitch   { // 0 to 1
                       0: 24
                       1: 29
                 default: 34
            }
        24: ldc           #118                // String name
        26: goto          44
        29: ldc           #119                // String entdef
        31: goto          44
        34: iload_1
        35: invokestatic  #99                 // Method scala/runtime/Statics.ioobe:(I)Ljava/lang/Object;
        38: checkcast     #121                // class java/lang/String
        41: goto          44
        44: areturn
      StackMapTable: number_of_entries = 4
        frame_type = 252 /* append */
          offset_delta = 24
          locals = [ int ]
        frame_type = 4 /* same */
        frame_type = 4 /* same */
        frame_type = 73 /* same_locals_1_stack_item */
          stack = [ class java/lang/String ]
      LineNumberTable:
        line 76: 0
      LocalVariableTable:
        Start  Length  Slot  Name   Signature
            0      45     0  this   Lscala/xml/dtd/ParsedEntityDecl;
            0      45     1   x$1   I
    MethodParameters:
      Name                           Flags
      x$1                            final

  public int hashCode();
    descriptor: ()I
    flags: (0x0001) ACC_PUBLIC
    Code:
      stack=2, locals=1, args_size=1
         0: getstatic     #109                // Field scala/runtime/ScalaRunTime$.MODULE$:Lscala/runtime/ScalaRunTime$;
         3: aload_0
         4: invokevirtual #126                // Method scala/runtime/ScalaRunTime$._hashCode:(Lscala/Product;)I
         7: ireturn
      LineNumberTable:
        line 76: 0
      LocalVariableTable:
        Start  Length  Slot  Name   Signature
            0       8     0  this   Lscala/xml/dtd/ParsedEntityDecl;

  public boolean equals(java.lang.Object);
    descriptor: (Ljava/lang/Object;)Z
    flags: (0x0001) ACC_PUBLIC
    Code:
      stack=2, locals=7, args_size=2
         0: aload_0
         1: aload_1
         2: if_acmpeq     118
         5: aload_1
         6: astore_3
         7: aload_3
         8: instanceof    #2                  // class scala/xml/dtd/ParsedEntityDecl
        11: ifeq          19
        14: iconst_1
        15: istore_2
        16: goto          27
        19: goto          22
        22: iconst_0
        23: istore_2
        24: goto          27
        27: iload_2
        28: ifeq          122
        31: aload_1
        32: checkcast     #2                  // class scala/xml/dtd/ParsedEntityDecl
        35: astore        4
        37: aload_0
        38: invokevirtual #69                 // Method name:()Ljava/lang/String;
        41: aload         4
        43: invokevirtual #69                 // Method name:()Ljava/lang/String;
        46: astore        5
        48: dup
        49: ifnonnull     61
        52: pop
        53: aload         5
        55: ifnull        69
        58: goto          114
        61: aload         5
        63: invokevirtual #129                // Method java/lang/Object.equals:(Ljava/lang/Object;)Z
        66: ifeq          114
        69: aload_0
        70: invokevirtual #74                 // Method entdef:()Lscala/xml/dtd/EntityDef;
        73: aload         4
        75: invokevirtual #74                 // Method entdef:()Lscala/xml/dtd/EntityDef;
        78: astore        6
        80: dup
        81: ifnonnull     93
        84: pop
        85: aload         6
        87: ifnull        101
        90: goto          114
        93: aload         6
        95: invokevirtual #129                // Method java/lang/Object.equals:(Ljava/lang/Object;)Z
        98: ifeq          114
       101: aload         4
       103: aload_0
       104: invokevirtual #131                // Method canEqual:(Ljava/lang/Object;)Z
       107: ifeq          114
       110: iconst_1
       111: goto          115
       114: iconst_0
       115: ifeq          122
       118: iconst_1
       119: goto          123
       122: iconst_0
       123: ireturn
      StackMapTable: number_of_entries = 12
        frame_type = 253 /* append */
          offset_delta = 19
          locals = [ top, class java/lang/Object ]
        frame_type = 2 /* same */
        frame_type = 255 /* full_frame */
          offset_delta = 4
          locals = [ class scala/xml/dtd/ParsedEntityDecl, class java/lang/Object, int, class java/lang/Object ]
          stack = []
        frame_type = 255 /* full_frame */
          offset_delta = 33
          locals = [ class scala/xml/dtd/ParsedEntityDecl, class java/lang/Object, int, class java/lang/Object, class scala/xml/dtd/ParsedEntityDecl, class java/lang/String ]
          stack = [ class java/lang/String ]
        frame_type = 7 /* same */
        frame_type = 255 /* full_frame */
          offset_delta = 23
          locals = [ class scala/xml/dtd/ParsedEntityDecl, class java/lang/Object, int, class java/lang/Object, class scala/xml/dtd/ParsedEntityDecl, class java/lang/String, class scala/xml/dtd/EntityDef ]
          stack = [ class scala/xml/dtd/EntityDef ]
        frame_type = 7 /* same */
        frame_type = 250 /* chop */
          offset_delta = 12
        frame_type = 64 /* same_locals_1_stack_item */
          stack = [ int ]
        frame_type = 255 /* full_frame */
          offset_delta = 2
          locals = [ class scala/xml/dtd/ParsedEntityDecl, class java/lang/Object ]
          stack = []
        frame_type = 253 /* append */
          offset_delta = 3
          locals = [ int, class java/lang/Object ]
        frame_type = 255 /* full_frame */
          offset_delta = 0
          locals = [ class scala/xml/dtd/ParsedEntityDecl, class java/lang/Object ]
          stack = [ int ]
      LineNumberTable:
        line 76: 0
      LocalVariableTable:
        Start  Length  Slot  Name   Signature
            0     124     0  this   Lscala/xml/dtd/ParsedEntityDecl;
            0     124     1   x$1   Ljava/lang/Object;
    MethodParameters:
      Name                           Flags
      x$1                            final

  public scala.xml.dtd.ParsedEntityDecl(java.lang.String, scala.xml.dtd.EntityDef);
    descriptor: (Ljava/lang/String;Lscala/xml/dtd/EntityDef;)V
    flags: (0x0001) ACC_PUBLIC
    Code:
      stack=2, locals=3, args_size=3
         0: aload_0
         1: aload_1
         2: putfield      #53                 // Field name:Ljava/lang/String;
         5: aload_0
         6: aload_2
         7: putfield      #56                 // Field entdef:Lscala/xml/dtd/EntityDef;
        10: aload_0
        11: invokespecial #134                // Method scala/xml/dtd/EntityDecl."<init>":()V
        14: aload_0
        15: invokestatic  #138                // InterfaceMethod scala/Product.$init$:(Lscala/Product;)V
        18: return
      LineNumberTable:
        line 76: 0
      LocalVariableTable:
        Start  Length  Slot  Name   Signature
            0      19     0  this   Lscala/xml/dtd/ParsedEntityDecl;
            0      19     1  name   Ljava/lang/String;
            0      19     2 entdef   Lscala/xml/dtd/EntityDef;
    MethodParameters:
      Name                           Flags
      name                           final
      entdef                         final
}
SourceFile: "Decl.scala"
RuntimeVisibleAnnotations:
  0: #10(#11=s#12)
    scala.reflect.ScalaSignature(
      bytes="\u0006\u0005\u00055d\u0001B\r\u001b\u0001\u0006B\u0001B\u000e\u0001\u0003\u0016\u0004%\ta\u000e\u0005\t\u0001\u0002\u0011\t\u0012)A\u0005q!A\u0011\t\u0001BK\u0002\u0013\u0005!\t\u0003\u0005G\u0001\tE\t\u0015!\u0003D\u0011\u00159\u0005\u0001\"\u0001I\u0011\u0015a\u0005\u0001\"\u0011N\u0011\u001d!\u0006!!A\u0005\u0002UCq\u0001\u0017\u0001\u0012\u0002\u0013\u0005\u0011\fC\u0004e\u0001E\u0005I\u0011A3\t\u000f\u001d\u0004\u0011\u0011!C!Q\"9\u0001\u000fAA\u0001\n\u0003\t\bbB;\u0001\u0003\u0003%\tA\u001e\u0005\by\u0002\t\t\u0011\"\u0011~\u0011%\tI\u0001AA\u0001\n\u0003\tY\u0001C\u0005\u0002\u0016\u0001\t\t\u0011\"\u0011\u0002\u0018!I\u00111\u0004\u0001\u0002\u0002\u0013\u0005\u0013Q\u0004\u0005\n\u0003?\u0001\u0011\u0011!C!\u0003C9\u0011\"!\n\u001b\u0003\u0003E\t!a\n\u0007\u0011eQ\u0012\u0011!E\u0001\u0003SAaaR\n\u0005\u0002\u0005\u0005\u0003\"CA\"\'\u0005\u0005IQIA#\u0011%\t9eEA\u0001\n\u0003\u000bI\u0005C\u0005\u0002PM\t\t\u0011\"!\u0002R!I\u00111M\n\u0002\u0002\u0013%\u0011Q\r\u0002\u0011!\u0006\u00148/\u001a3F]RLG/\u001f#fG2T!a\u0007\u000f\u0002\u0007\u0011$HM\u0003\u0002\u001e=\u0005\u0019\u00010\u001c7\u000b\u0003}\tQa]2bY\u0006\u001c\u0001a\u0005\u0003\u0001E\u0019R\u0003CA\u0012%\u001b\u0005Q\u0012BA\u0013\u001b\u0005))e\u000e^5us\u0012+7\r\u001c\t\u0003O!j\u0011AH\u0005\u0003Sy\u0011q\u0001\u0015:pIV\u001cG\u000f\u0005\u0002,g9\u0011A&\r\b\u0003[Aj\u0011A\f\u0006\u0003_\u0001\na\u0001\u0010:p_Rt\u0014\"A\u0010\n\u0005Ir\u0012a\u00029bG.\fw-Z\u0005\u0003iU\u0012AbU3sS\u0006d\u0017N_1cY\u0016T!A\r\u0010\u0002\t9\fW.Z\u000b\u0002qA\u0011\u0011(\u0010\b\u0003um\u0002\"!\f\u0010\n\u0005qr\u0012A\u0002)sK\u0012,g-\u0003\u0002?\u007f\t11\u000b\u001e:j]\u001eT!\u0001\u0010\u0010\u0002\u000b9\fW.\u001a\u0011\u0002\r\u0015tG\u000fZ3g+\u0005\u0019\u0005CA\u0012E\u0013\t)%DA\u0005F]RLG/\u001f#fM\u00069QM\u001c;eK\u001a\u0004\u0013A\u0002\u001fj]&$h\bF\u0002J\u0015.\u0003\"a\t\u0001\t\u000bY*\u0001\u0019\u0001\u001d\t\u000b\u0005+\u0001\u0019A\"\u0002\u0017\t,\u0018\u000e\u001c3TiJLgn\u001a\u000b\u0003\u001dJ\u0003\"a\u0014)\u000f\u0005\u001d\n\u0014BA)6\u00055\u0019FO]5oO\n+\u0018\u000e\u001c3fe\")1K\u0002a\u0001\u001d\u0006\u00111OY\u0001\u0005G>\u0004\u0018\u0010F\u0002J-^CqAN\u0004\u0011\u0002\u0003\u0007\u0001\bC\u0004B\u000fA\u0005\t\u0019A\"\u0002\u001d\r|\u0007/\u001f\u0013eK\u001a\fW\u000f\u001c;%cU\t!L\u000b\u000297.\nA\f\u0005\u0002^E6\taL\u0003\u0002`A\u0006IQO\\2iK\u000e\\W\r\u001a\u0006\u0003Cz\t!\"\u00198o_R\fG/[8o\u0013\t\u0019gLA\tv]\u000eDWmY6fIZ\u000b\'/[1oG\u0016\fabY8qs\u0012\"WMZ1vYR$#\'F\u0001gU\t\u00195,A\u0007qe>$Wo\u0019;Qe\u00164\u0017\u000e_\u000b\u0002SB\u0011!n\\\u0007\u0002W*\u0011A.\\\u0001\u0005Y\u0006twMC\u0001o\u0003\u0011Q\u0017M^1\n\u0005yZ\u0017\u0001\u00049s_\u0012,8\r^!sSRLX#\u0001:\u0011\u0005\u001d\u001a\u0018B\u0001;\u001f\u0005\rIe\u000e^\u0001\u000faJ|G-^2u\u000b2,W.\u001a8u)\t9(\u0010\u0005\u0002(q&\u0011\u0011P\b\u0002\u0004\u0003:L\bbB>\r\u0003\u0003\u0005\rA]\u0001\u0004q\u0012\n\u0014a\u00049s_\u0012,8\r^%uKJ\fGo\u001c:\u0016\u0003y\u0004Ba`A\u0003o6\u0011\u0011\u0011\u0001\u0006\u0004\u0003\u0007q\u0012AC2pY2,7\r^5p]&!\u0011qAA\u0001\u0005!IE/\u001a:bi>\u0014\u0018\u0001C2b]\u0016\u000bX/\u00197\u0015\t\u00055\u00111\u0003\t\u0004O\u0005=\u0011bAA\t=\t9!i\\8mK\u0006t\u0007bB>\u000f\u0003\u0003\u0005\ra^\u0001\u0013aJ|G-^2u\u000b2,W.\u001a8u\u001d\u0006lW\rF\u0002j\u00033Aqa_\b\u0002\u0002\u0003\u0007!/\u0001\u0005iCND7i\u001c3f)\u0005\u0011\u0018AB3rk\u0006d7\u000f\u0006\u0003\u0002\u000e\u0005\r\u0002bB>\u0012\u0003\u0003\u0005\ra^\u0001\u0011!\u0006\u00148/\u001a3F]RLG/\u001f#fG2\u0004\"aI\n\u0014\u000bM\tY#a\u000e\u0011\u000f\u00055\u00121\u0007\u001dD\u00136\u0011\u0011q\u0006\u0006\u0004\u0003cq\u0012a\u0002:v]RLW.Z\u0005\u0005\u0003k\tyCA\tBEN$(/Y2u\rVt7\r^5p]J\u0002B!!\u000f\u0002@5\u0011\u00111\b\u0006\u0004\u0003{i\u0017AA5p\u0013\r!\u00141\b\u000b\u0003\u0003O\t\u0001\u0002^8TiJLgn\u001a\u000b\u0002S\u0006)\u0011\r\u001d9msR)\u0011*a\u0013\u0002N!)aG\u0006a\u0001q!)\u0011I\u0006a\u0001\u0007\u00069QO\\1qa2LH\u0003BA*\u0003?\u0002RaJA+\u00033J1!a\u0016\u001f\u0005\u0019y\u0005\u000f^5p]B)q%a\u00179\u0007&\u0019\u0011Q\f\u0010\u0003\rQ+\b\u000f\\33\u0011!\t\tgFA\u0001\u0002\u0004I\u0015a\u0001=%a\u0005aqO]5uKJ+\u0007\u000f\\1dKR\u0011\u0011q\r\t\u0004U\u0006%\u0014bAA6W\n1qJ\u00196fGR\u0004"
    )
  ScalaInlineInfo: length = 0x54 (unknown attribute)
   01 00 00 10 00 51 00 52 00 00 39 00 3A 00 00 71
   00 72 00 00 50 00 1F 00 00 55 00 33 00 00 56 00
   36 00 00 0F 00 36 00 00 7F 00 72 00 00 7A 00 5B
   00 00 0D 00 33 00 00 5A 00 5B 00 00 5C 00 5D 00
   00 74 00 75 00 00 2B 00 2C 00 00 67 00 2C 00 00
   57 00 33 00
  ScalaSig: length = 0x3 (unknown attribute)
   05 02 00
