Classfile /Users/mw/Projects/slang-braindump/.jar/jar8/assemble/slang-braindump/assemble/content/scala/xml/dtd/UnparsedEntityDecl$.class
  Last modified May 29, 2022; size 2361 bytes
  SHA-256 checksum c2c8815264ce5c1f068bf768a78c5cf3413a2a579af197c1d9583bc853e18c9b
  Compiled from "Decl.scala"
public final class scala.xml.dtd.UnparsedEntityDecl$ extends scala.runtime.AbstractFunction3<java.lang.String, scala.xml.dtd.ExternalID, java.lang.String, scala.xml.dtd.UnparsedEntityDecl> implements java.io.Serializable
  minor version: 0
  major version: 52
  flags: (0x0031) ACC_PUBLIC, ACC_FINAL, ACC_SUPER
  this_class: #2                          // scala/xml/dtd/UnparsedEntityDecl$
  super_class: #5                         // scala/runtime/AbstractFunction3
  interfaces: 1, fields: 1, methods: 7, attributes: 4
Constant pool:
   #1 = Utf8               scala/xml/dtd/UnparsedEntityDecl$
   #2 = Class              #1             // scala/xml/dtd/UnparsedEntityDecl$
   #3 = Utf8               Lscala/runtime/AbstractFunction3<Ljava/lang/String;Lscala/xml/dtd/ExternalID;Ljava/lang/String;Lscala/xml/dtd/UnparsedEntityDecl;>;Ljava/io/Serializable;
   #4 = Utf8               scala/runtime/AbstractFunction3
   #5 = Class              #4             // scala/runtime/AbstractFunction3
   #6 = Utf8               java/io/Serializable
   #7 = Class              #6             // java/io/Serializable
   #8 = Utf8               Decl.scala
   #9 = Utf8               MODULE$
  #10 = Utf8               Lscala/xml/dtd/UnparsedEntityDecl$;
  #11 = Utf8               <clinit>
  #12 = Utf8               ()V
  #13 = Utf8               <init>
  #14 = NameAndType        #13:#12        // "<init>":()V
  #15 = Methodref          #2.#14         // scala/xml/dtd/UnparsedEntityDecl$."<init>":()V
  #16 = NameAndType        #9:#10         // MODULE$:Lscala/xml/dtd/UnparsedEntityDecl$;
  #17 = Fieldref           #2.#16         // scala/xml/dtd/UnparsedEntityDecl$.MODULE$:Lscala/xml/dtd/UnparsedEntityDecl$;
  #18 = Utf8               toString
  #19 = Utf8               ()Ljava/lang/String;
  #20 = Utf8               UnparsedEntityDecl
  #21 = String             #20            // UnparsedEntityDecl
  #22 = Utf8               this
  #23 = Utf8               apply
  #24 = Utf8               (Ljava/lang/String;Lscala/xml/dtd/ExternalID;Ljava/lang/String;)Lscala/xml/dtd/UnparsedEntityDecl;
  #25 = Utf8               name
  #26 = Utf8               extID
  #27 = Utf8               notation
  #28 = Utf8               scala/xml/dtd/UnparsedEntityDecl
  #29 = Class              #28            // scala/xml/dtd/UnparsedEntityDecl
  #30 = Utf8               (Ljava/lang/String;Lscala/xml/dtd/ExternalID;Ljava/lang/String;)V
  #31 = NameAndType        #13:#30        // "<init>":(Ljava/lang/String;Lscala/xml/dtd/ExternalID;Ljava/lang/String;)V
  #32 = Methodref          #29.#31        // scala/xml/dtd/UnparsedEntityDecl."<init>":(Ljava/lang/String;Lscala/xml/dtd/ExternalID;Ljava/lang/String;)V
  #33 = Utf8               Ljava/lang/String;
  #34 = Utf8               Lscala/xml/dtd/ExternalID;
  #35 = Utf8               unapply
  #36 = Utf8               (Lscala/xml/dtd/UnparsedEntityDecl;)Lscala/Option;
  #37 = Utf8               (Lscala/xml/dtd/UnparsedEntityDecl;)Lscala/Option<Lscala/Tuple3<Ljava/lang/String;Lscala/xml/dtd/ExternalID;Ljava/lang/String;>;>;
  #38 = Utf8               x$0
  #39 = Utf8               scala/None$
  #40 = Class              #39            // scala/None$
  #41 = Utf8               Lscala/None$;
  #42 = NameAndType        #9:#41         // MODULE$:Lscala/None$;
  #43 = Fieldref           #40.#42        // scala/None$.MODULE$:Lscala/None$;
  #44 = Utf8               scala/Some
  #45 = Class              #44            // scala/Some
  #46 = Utf8               scala/Tuple3
  #47 = Class              #46            // scala/Tuple3
  #48 = NameAndType        #25:#19        // name:()Ljava/lang/String;
  #49 = Methodref          #29.#48        // scala/xml/dtd/UnparsedEntityDecl.name:()Ljava/lang/String;
  #50 = Utf8               ()Lscala/xml/dtd/ExternalID;
  #51 = NameAndType        #26:#50        // extID:()Lscala/xml/dtd/ExternalID;
  #52 = Methodref          #29.#51        // scala/xml/dtd/UnparsedEntityDecl.extID:()Lscala/xml/dtd/ExternalID;
  #53 = NameAndType        #27:#19        // notation:()Ljava/lang/String;
  #54 = Methodref          #29.#53        // scala/xml/dtd/UnparsedEntityDecl.notation:()Ljava/lang/String;
  #55 = Utf8               (Ljava/lang/Object;Ljava/lang/Object;Ljava/lang/Object;)V
  #56 = NameAndType        #13:#55        // "<init>":(Ljava/lang/Object;Ljava/lang/Object;Ljava/lang/Object;)V
  #57 = Methodref          #47.#56        // scala/Tuple3."<init>":(Ljava/lang/Object;Ljava/lang/Object;Ljava/lang/Object;)V
  #58 = Utf8               (Ljava/lang/Object;)V
  #59 = NameAndType        #13:#58        // "<init>":(Ljava/lang/Object;)V
  #60 = Methodref          #45.#59        // scala/Some."<init>":(Ljava/lang/Object;)V
  #61 = Utf8               Lscala/xml/dtd/UnparsedEntityDecl;
  #62 = Utf8               scala/Option
  #63 = Class              #62            // scala/Option
  #64 = Utf8               writeReplace
  #65 = Utf8               ()Ljava/lang/Object;
  #66 = Utf8               scala/runtime/ModuleSerializationProxy
  #67 = Class              #66            // scala/runtime/ModuleSerializationProxy
  #68 = Utf8               (Ljava/lang/Class;)V
  #69 = NameAndType        #13:#68        // "<init>":(Ljava/lang/Class;)V
  #70 = Methodref          #67.#69        // scala/runtime/ModuleSerializationProxy."<init>":(Ljava/lang/Class;)V
  #71 = Utf8               (Ljava/lang/Object;Ljava/lang/Object;Ljava/lang/Object;)Ljava/lang/Object;
  #72 = Utf8               v1
  #73 = Utf8               v2
  #74 = Utf8               v3
  #75 = Utf8               java/lang/String
  #76 = Class              #75            // java/lang/String
  #77 = Utf8               scala/xml/dtd/ExternalID
  #78 = Class              #77            // scala/xml/dtd/ExternalID
  #79 = NameAndType        #23:#24        // apply:(Ljava/lang/String;Lscala/xml/dtd/ExternalID;Ljava/lang/String;)Lscala/xml/dtd/UnparsedEntityDecl;
  #80 = Methodref          #2.#79         // scala/xml/dtd/UnparsedEntityDecl$.apply:(Ljava/lang/String;Lscala/xml/dtd/ExternalID;Ljava/lang/String;)Lscala/xml/dtd/UnparsedEntityDecl;
  #81 = Utf8               Ljava/lang/Object;
  #82 = Methodref          #5.#14         // scala/runtime/AbstractFunction3."<init>":()V
  #83 = Utf8               Code
  #84 = Utf8               LineNumberTable
  #85 = Utf8               LocalVariableTable
  #86 = Utf8               MethodParameters
  #87 = Utf8               StackMapTable
  #88 = Utf8               Signature
  #89 = Utf8               SourceFile
  #90 = Utf8               ScalaInlineInfo
  #91 = Utf8               Scala
{
  public static final scala.xml.dtd.UnparsedEntityDecl$ MODULE$;
    descriptor: Lscala/xml/dtd/UnparsedEntityDecl$;
    flags: (0x0019) ACC_PUBLIC, ACC_STATIC, ACC_FINAL

  public static {};
    descriptor: ()V
    flags: (0x0009) ACC_PUBLIC, ACC_STATIC
    Code:
      stack=2, locals=0, args_size=0
         0: new           #2                  // class scala/xml/dtd/UnparsedEntityDecl$
         3: dup
         4: invokespecial #15                 // Method "<init>":()V
         7: putstatic     #17                 // Field MODULE$:Lscala/xml/dtd/UnparsedEntityDecl$;
        10: return
      LineNumberTable:
        line 92: 0

  public final java.lang.String toString();
    descriptor: ()Ljava/lang/String;
    flags: (0x0011) ACC_PUBLIC, ACC_FINAL
    Code:
      stack=1, locals=1, args_size=1
         0: ldc           #21                 // String UnparsedEntityDecl
         2: areturn
      LineNumberTable:
        line 92: 0
      LocalVariableTable:
        Start  Length  Slot  Name   Signature
            0       3     0  this   Lscala/xml/dtd/UnparsedEntityDecl$;

  public scala.xml.dtd.UnparsedEntityDecl apply(java.lang.String, scala.xml.dtd.ExternalID, java.lang.String);
    descriptor: (Ljava/lang/String;Lscala/xml/dtd/ExternalID;Ljava/lang/String;)Lscala/xml/dtd/UnparsedEntityDecl;
    flags: (0x0001) ACC_PUBLIC
    Code:
      stack=5, locals=4, args_size=4
         0: new           #29                 // class scala/xml/dtd/UnparsedEntityDecl
         3: dup
         4: aload_1
         5: aload_2
         6: aload_3
         7: invokespecial #32                 // Method scala/xml/dtd/UnparsedEntityDecl."<init>":(Ljava/lang/String;Lscala/xml/dtd/ExternalID;Ljava/lang/String;)V
        10: areturn
      LineNumberTable:
        line 92: 0
      LocalVariableTable:
        Start  Length  Slot  Name   Signature
            0      11     0  this   Lscala/xml/dtd/UnparsedEntityDecl$;
            0      11     1  name   Ljava/lang/String;
            0      11     2 extID   Lscala/xml/dtd/ExternalID;
            0      11     3 notation   Ljava/lang/String;
    MethodParameters:
      Name                           Flags
      name                           final
      extID                          final
      notation                       final

  public scala.Option<scala.Tuple3<java.lang.String, scala.xml.dtd.ExternalID, java.lang.String>> unapply(scala.xml.dtd.UnparsedEntityDecl);
    descriptor: (Lscala/xml/dtd/UnparsedEntityDecl;)Lscala/Option;
    flags: (0x0001) ACC_PUBLIC
    Code:
      stack=7, locals=2, args_size=2
         0: aload_1
         1: ifnonnull     10
         4: getstatic     #43                 // Field scala/None$.MODULE$:Lscala/None$;
         7: goto          36
        10: new           #45                 // class scala/Some
        13: dup
        14: new           #47                 // class scala/Tuple3
        17: dup
        18: aload_1
        19: invokevirtual #49                 // Method scala/xml/dtd/UnparsedEntityDecl.name:()Ljava/lang/String;
        22: aload_1
        23: invokevirtual #52                 // Method scala/xml/dtd/UnparsedEntityDecl.extID:()Lscala/xml/dtd/ExternalID;
        26: aload_1
        27: invokevirtual #54                 // Method scala/xml/dtd/UnparsedEntityDecl.notation:()Ljava/lang/String;
        30: invokespecial #57                 // Method scala/Tuple3."<init>":(Ljava/lang/Object;Ljava/lang/Object;Ljava/lang/Object;)V
        33: invokespecial #60                 // Method scala/Some."<init>":(Ljava/lang/Object;)V
        36: areturn
      StackMapTable: number_of_entries = 2
        frame_type = 10 /* same */
        frame_type = 89 /* same_locals_1_stack_item */
          stack = [ class scala/Option ]
      LineNumberTable:
        line 92: 0
      LocalVariableTable:
        Start  Length  Slot  Name   Signature
            0      37     0  this   Lscala/xml/dtd/UnparsedEntityDecl$;
            0      37     1   x$0   Lscala/xml/dtd/UnparsedEntityDecl;
    Signature: #37                          // (Lscala/xml/dtd/UnparsedEntityDecl;)Lscala/Option<Lscala/Tuple3<Ljava/lang/String;Lscala/xml/dtd/ExternalID;Ljava/lang/String;>;>;
    MethodParameters:
      Name                           Flags
      x$0                            final

  private java.lang.Object writeReplace();
    descriptor: ()Ljava/lang/Object;
    flags: (0x0002) ACC_PRIVATE
    Code:
      stack=3, locals=1, args_size=1
         0: new           #67                 // class scala/runtime/ModuleSerializationProxy
         3: dup
         4: ldc           #2                  // class scala/xml/dtd/UnparsedEntityDecl$
         6: invokespecial #70                 // Method scala/runtime/ModuleSerializationProxy."<init>":(Ljava/lang/Class;)V
         9: areturn
      LineNumberTable:
        line 92: 0
      LocalVariableTable:
        Start  Length  Slot  Name   Signature
            0      10     0  this   Lscala/xml/dtd/UnparsedEntityDecl$;

  public java.lang.Object apply(java.lang.Object, java.lang.Object, java.lang.Object);
    descriptor: (Ljava/lang/Object;Ljava/lang/Object;Ljava/lang/Object;)Ljava/lang/Object;
    flags: (0x1041) ACC_PUBLIC, ACC_BRIDGE, ACC_SYNTHETIC
    Code:
      stack=4, locals=4, args_size=4
         0: aload_0
         1: aload_1
         2: checkcast     #76                 // class java/lang/String
         5: aload_2
         6: checkcast     #78                 // class scala/xml/dtd/ExternalID
         9: aload_3
        10: checkcast     #76                 // class java/lang/String
        13: invokevirtual #80                 // Method apply:(Ljava/lang/String;Lscala/xml/dtd/ExternalID;Ljava/lang/String;)Lscala/xml/dtd/UnparsedEntityDecl;
        16: areturn
      LineNumberTable:
        line 92: 0
      LocalVariableTable:
        Start  Length  Slot  Name   Signature
            0      17     0  this   Lscala/xml/dtd/UnparsedEntityDecl$;
            0      17     1    v1   Ljava/lang/Object;
            0      17     2    v2   Ljava/lang/Object;
            0      17     3    v3   Ljava/lang/Object;
    MethodParameters:
      Name                           Flags
      v1                             final
      v2                             final
      v3                             final

  private scala.xml.dtd.UnparsedEntityDecl$();
    descriptor: ()V
    flags: (0x0002) ACC_PRIVATE
    Code:
      stack=1, locals=1, args_size=1
         0: aload_0
         1: invokespecial #82                 // Method scala/runtime/AbstractFunction3."<init>":()V
         4: return
      LineNumberTable:
        line 92: 0
      LocalVariableTable:
        Start  Length  Slot  Name   Signature
            0       5     0  this   Lscala/xml/dtd/UnparsedEntityDecl$;
}
Signature: #3                           // Lscala/runtime/AbstractFunction3<Ljava/lang/String;Lscala/xml/dtd/ExternalID;Ljava/lang/String;Lscala/xml/dtd/UnparsedEntityDecl;>;Ljava/io/Serializable;
SourceFile: "Decl.scala"
  ScalaInlineInfo: length = 0x22 (unknown attribute)
   01 01 00 06 00 0D 00 0C 01 00 17 00 47 01 00 17
   00 18 01 00 12 00 13 01 00 23 00 24 01 00 40 00
   41 01
  Scala: length = 0x0 (unknown attribute)

