Classfile /Users/mw/Projects/slang-braindump/.jar/jar8/assemble/slang-braindump/assemble/content/scala/collection/parallel/FutureThreadPoolTasks$.class
  Last modified May 29, 2022; size 1215 bytes
  SHA-256 checksum 7b18714b48d90db9d57a7e15d4febc70051b642f098a43e118be4b4ddda8b097
  Compiled from "Tasks.scala"
public final class scala.collection.parallel.FutureThreadPoolTasks$
  minor version: 0
  major version: 52
  flags: (0x0031) ACC_PUBLIC, ACC_FINAL, ACC_SUPER
  this_class: #2                          // scala/collection/parallel/FutureThreadPoolTasks$
  super_class: #4                         // java/lang/Object
  interfaces: 0, fields: 4, methods: 5, attributes: 3
Constant pool:
   #1 = Utf8               scala/collection/parallel/FutureThreadPoolTasks$
   #2 = Class              #1             // scala/collection/parallel/FutureThreadPoolTasks$
   #3 = Utf8               java/lang/Object
   #4 = Class              #3             // java/lang/Object
   #5 = Utf8               Tasks.scala
   #6 = Utf8               MODULE$
   #7 = Utf8               Lscala/collection/parallel/FutureThreadPoolTasks$;
   #8 = Utf8               numCores
   #9 = Utf8               I
  #10 = Utf8               tcount
  #11 = Utf8               Ljava/util/concurrent/atomic/AtomicLong;
  #12 = Utf8               defaultThreadPool
  #13 = Utf8               Ljava/util/concurrent/ExecutorService;
  #14 = Utf8               <clinit>
  #15 = Utf8               ()V
  #16 = Utf8               <init>
  #17 = NameAndType        #16:#15        // "<init>":()V
  #18 = Methodref          #2.#17         // scala/collection/parallel/FutureThreadPoolTasks$."<init>":()V
  #19 = NameAndType        #6:#7          // MODULE$:Lscala/collection/parallel/FutureThreadPoolTasks$;
  #20 = Fieldref           #2.#19         // scala/collection/parallel/FutureThreadPoolTasks$.MODULE$:Lscala/collection/parallel/FutureThreadPoolTasks$;
  #21 = Utf8               java/lang/Runtime
  #22 = Class              #21            // java/lang/Runtime
  #23 = Utf8               getRuntime
  #24 = Utf8               ()Ljava/lang/Runtime;
  #25 = NameAndType        #23:#24        // getRuntime:()Ljava/lang/Runtime;
  #26 = Methodref          #22.#25        // java/lang/Runtime.getRuntime:()Ljava/lang/Runtime;
  #27 = Utf8               availableProcessors
  #28 = Utf8               ()I
  #29 = NameAndType        #27:#28        // availableProcessors:()I
  #30 = Methodref          #22.#29        // java/lang/Runtime.availableProcessors:()I
  #31 = NameAndType        #8:#9          // numCores:I
  #32 = Fieldref           #2.#31         // scala/collection/parallel/FutureThreadPoolTasks$.numCores:I
  #33 = Utf8               java/util/concurrent/atomic/AtomicLong
  #34 = Class              #33            // java/util/concurrent/atomic/AtomicLong
  #35 = Utf8               (J)V
  #36 = NameAndType        #16:#35        // "<init>":(J)V
  #37 = Methodref          #34.#36        // java/util/concurrent/atomic/AtomicLong."<init>":(J)V
  #38 = NameAndType        #10:#11        // tcount:Ljava/util/concurrent/atomic/AtomicLong;
  #39 = Fieldref           #2.#38         // scala/collection/parallel/FutureThreadPoolTasks$.tcount:Ljava/util/concurrent/atomic/AtomicLong;
  #40 = Utf8               java/util/concurrent/Executors
  #41 = Class              #40            // java/util/concurrent/Executors
  #42 = Utf8               newCachedThreadPool
  #43 = Utf8               ()Ljava/util/concurrent/ExecutorService;
  #44 = NameAndType        #42:#43        // newCachedThreadPool:()Ljava/util/concurrent/ExecutorService;
  #45 = Methodref          #41.#44        // java/util/concurrent/Executors.newCachedThreadPool:()Ljava/util/concurrent/ExecutorService;
  #46 = NameAndType        #12:#13        // defaultThreadPool:Ljava/util/concurrent/ExecutorService;
  #47 = Fieldref           #2.#46         // scala/collection/parallel/FutureThreadPoolTasks$.defaultThreadPool:Ljava/util/concurrent/ExecutorService;
  #48 = Utf8               this
  #49 = Utf8               ()Ljava/util/concurrent/atomic/AtomicLong;
  #50 = Methodref          #4.#17         // java/lang/Object."<init>":()V
  #51 = Utf8               Code
  #52 = Utf8               LineNumberTable
  #53 = Utf8               LocalVariableTable
  #54 = Utf8               SourceFile
  #55 = Utf8               ScalaInlineInfo
  #56 = Utf8               Scala
{
  public static final scala.collection.parallel.FutureThreadPoolTasks$ MODULE$;
    descriptor: Lscala/collection/parallel/FutureThreadPoolTasks$;
    flags: (0x0019) ACC_PUBLIC, ACC_STATIC, ACC_FINAL

  private static final int numCores;
    descriptor: I
    flags: (0x001a) ACC_PRIVATE, ACC_STATIC, ACC_FINAL

  private static final java.util.concurrent.atomic.AtomicLong tcount;
    descriptor: Ljava/util/concurrent/atomic/AtomicLong;
    flags: (0x001a) ACC_PRIVATE, ACC_STATIC, ACC_FINAL

  private static final java.util.concurrent.ExecutorService defaultThreadPool;
    descriptor: Ljava/util/concurrent/ExecutorService;
    flags: (0x001a) ACC_PRIVATE, ACC_STATIC, ACC_FINAL

  public static {};
    descriptor: ()V
    flags: (0x0009) ACC_PUBLIC, ACC_STATIC
    Code:
      stack=4, locals=0, args_size=0
         0: new           #2                  // class scala/collection/parallel/FutureThreadPoolTasks$
         3: dup
         4: invokespecial #18                 // Method "<init>":()V
         7: putstatic     #20                 // Field MODULE$:Lscala/collection/parallel/FutureThreadPoolTasks$;
        10: invokestatic  #26                 // Method java/lang/Runtime.getRuntime:()Ljava/lang/Runtime;
        13: invokevirtual #30                 // Method java/lang/Runtime.availableProcessors:()I
        16: putstatic     #32                 // Field numCores:I
        19: new           #34                 // class java/util/concurrent/atomic/AtomicLong
        22: dup
        23: lconst_0
        24: invokespecial #37                 // Method java/util/concurrent/atomic/AtomicLong."<init>":(J)V
        27: putstatic     #39                 // Field tcount:Ljava/util/concurrent/atomic/AtomicLong;
        30: invokestatic  #45                 // Method java/util/concurrent/Executors.newCachedThreadPool:()Ljava/util/concurrent/ExecutorService;
        33: putstatic     #47                 // Field defaultThreadPool:Ljava/util/concurrent/ExecutorService;
        36: return
      LineNumberTable:
        line 213: 0
        line 216: 10
        line 218: 19
        line 220: 30
        line 213: 36

  public int numCores();
    descriptor: ()I
    flags: (0x0001) ACC_PUBLIC
    Code:
      stack=1, locals=1, args_size=1
         0: getstatic     #32                 // Field numCores:I
         3: ireturn
      LineNumberTable:
        line 216: 0
      LocalVariableTable:
        Start  Length  Slot  Name   Signature
            0       4     0  this   Lscala/collection/parallel/FutureThreadPoolTasks$;

  public java.util.concurrent.atomic.AtomicLong tcount();
    descriptor: ()Ljava/util/concurrent/atomic/AtomicLong;
    flags: (0x0001) ACC_PUBLIC
    Code:
      stack=1, locals=1, args_size=1
         0: getstatic     #39                 // Field tcount:Ljava/util/concurrent/atomic/AtomicLong;
         3: areturn
      LineNumberTable:
        line 218: 0
      LocalVariableTable:
        Start  Length  Slot  Name   Signature
            0       4     0  this   Lscala/collection/parallel/FutureThreadPoolTasks$;

  public java.util.concurrent.ExecutorService defaultThreadPool();
    descriptor: ()Ljava/util/concurrent/ExecutorService;
    flags: (0x0001) ACC_PUBLIC
    Code:
      stack=1, locals=1, args_size=1
         0: getstatic     #47                 // Field defaultThreadPool:Ljava/util/concurrent/ExecutorService;
         3: areturn
      LineNumberTable:
        line 220: 0
      LocalVariableTable:
        Start  Length  Slot  Name   Signature
            0       4     0  this   Lscala/collection/parallel/FutureThreadPoolTasks$;

  private scala.collection.parallel.FutureThreadPoolTasks$();
    descriptor: ()V
    flags: (0x0002) ACC_PRIVATE
    Code:
      stack=1, locals=1, args_size=1
         0: aload_0
         1: invokespecial #50                 // Method java/lang/Object."<init>":()V
         4: return
      LineNumberTable:
        line 228: 0
        line 213: 4
      LocalVariableTable:
        Start  Length  Slot  Name   Signature
            0       5     0  this   Lscala/collection/parallel/FutureThreadPoolTasks$;
}
SourceFile: "Tasks.scala"
  ScalaInlineInfo: length = 0x18 (unknown attribute)
   01 01 00 04 00 10 00 0F 01 00 0C 00 2B 01 00 08
   00 1C 01 00 0A 00 31 01
  Scala: length = 0x0 (unknown attribute)

