Classfile /Users/mw/Projects/slang-braindump/.jar/jar8/assemble/slang-braindump/assemble/content/scala/collection/parallel/ParallelCollectionImplicits.class
  Last modified May 29, 2022; size 1129 bytes
  SHA-256 checksum 22873e026c07a20a8a77f26f477229619d7bbb01ec316a10327b37236497c07e
  Compiled from "package.scala"
public final class scala.collection.parallel.ParallelCollectionImplicits
  minor version: 0
  major version: 52
  flags: (0x0031) ACC_PUBLIC, ACC_FINAL, ACC_SUPER
  this_class: #2                          // scala/collection/parallel/ParallelCollectionImplicits
  super_class: #4                         // java/lang/Object
  interfaces: 0, fields: 0, methods: 1, attributes: 3
Constant pool:
   #1 = Utf8               scala/collection/parallel/ParallelCollectionImplicits
   #2 = Class              #1             // scala/collection/parallel/ParallelCollectionImplicits
   #3 = Utf8               java/lang/Object
   #4 = Class              #3             // java/lang/Object
   #5 = Utf8               package.scala
   #6 = Utf8               Lscala/reflect/ScalaSignature;
   #7 = Utf8               bytes
   #8 = Utf8               \u0006\u00055:a\u0001B\u0003\t\u0002\u001dYaAB\u0007\u0006\u0011\u00039a\u0002C\u0003\u0014\u0003\u0011\u0005Q\u0003C\u0003\u0017\u0003\u0011\rq#A\u000eQCJ\fG\u000e\\3m\u0007>dG.Z2uS>t\u0017*\u001c9mS\u000eLGo\u001d\u0006\u0003\r\u001d\t\u0001\u0002]1sC2dW\r\u001c\u0006\u0003\u0011%\t!bY8mY\u0016\u001cG/[8o\u0015\u0005Q\u0011!B:dC2\f\u0007C\u0001\u0007\u0002\u001b\u0005)!a\u0007)be\u0006dG.\u001a7D_2dWm\u0019;j_:LU\u000e\u001d7jG&$8o\u0005\u0002\u0002\u001fA\u0011\u0001#E\u0007\u0002\u0013%\u0011!#\u0003\u0002\u0007\u0003:L(+\u001a4\u0002\rqJg.\u001b;?\u0007\u0001!\u0012aC\u0001\u0010iJ\fg/\u001a:tC\ndWMM8qgV\u0011\u0001D\b\u000b\u00033\u001d\u00022\u0001\u0004\u000e\u001d\u0013\tYRA\u0001\bUe\u00064XM]:bE2,w\n]:\u0011\u0005uqB\u0002\u0001\u0003\u0006?\r\u0011\r\u0001\t\u0002\u0002)F\u0011\u0011\u0005\n\t\u0003!\tJ!aI\u0005\u0003\u000f9{G\u000f[5oOB\u0011\u0001#J\u0005\u0003M%\u00111!\u00118z\u0011\u0015A3\u00011\u0001*\u0003\u0005!\bc\u0001\u0016,95\tq!\u0003\u0002-\u000f\ta\u0011\n^3sC\ndWm\u00148dK\u0002
   #9 = Utf8               traversable2ops
  #10 = Utf8               (Lscala/collection/IterableOnce;)Lscala/collection/parallel/TraversableOps;
  #11 = Utf8               <T:Ljava/lang/Object;>(Lscala/collection/IterableOnce<TT;>;)Lscala/collection/parallel/TraversableOps<TT;>;
  #12 = Utf8               t
  #13 = Utf8               scala/collection/parallel/ParallelCollectionImplicits$
  #14 = Class              #13            // scala/collection/parallel/ParallelCollectionImplicits$
  #15 = Utf8               MODULE$
  #16 = Utf8               Lscala/collection/parallel/ParallelCollectionImplicits$;
  #17 = NameAndType        #15:#16        // MODULE$:Lscala/collection/parallel/ParallelCollectionImplicits$;
  #18 = Fieldref           #14.#17        // scala/collection/parallel/ParallelCollectionImplicits$.MODULE$:Lscala/collection/parallel/ParallelCollectionImplicits$;
  #19 = NameAndType        #9:#10         // traversable2ops:(Lscala/collection/IterableOnce;)Lscala/collection/parallel/TraversableOps;
  #20 = Methodref          #14.#19        // scala/collection/parallel/ParallelCollectionImplicits$.traversable2ops:(Lscala/collection/IterableOnce;)Lscala/collection/parallel/TraversableOps;
  #21 = Utf8               Lscala/collection/IterableOnce;
  #22 = Utf8               Code
  #23 = Utf8               LocalVariableTable
  #24 = Utf8               Signature
  #25 = Utf8               MethodParameters
  #26 = Utf8               SourceFile
  #27 = Utf8               RuntimeVisibleAnnotations
  #28 = Utf8               ScalaSig
{
  public static <T extends java.lang.Object> scala.collection.parallel.TraversableOps<T> traversable2ops(scala.collection.IterableOnce<T>);
    descriptor: (Lscala/collection/IterableOnce;)Lscala/collection/parallel/TraversableOps;
    flags: (0x0009) ACC_PUBLIC, ACC_STATIC
    Code:
      stack=2, locals=1, args_size=1
         0: getstatic     #18                 // Field scala/collection/parallel/ParallelCollectionImplicits$.MODULE$:Lscala/collection/parallel/ParallelCollectionImplicits$;
         3: aload_0
         4: invokevirtual #20                 // Method scala/collection/parallel/ParallelCollectionImplicits$.traversable2ops:(Lscala/collection/IterableOnce;)Lscala/collection/parallel/TraversableOps;
         7: areturn
      LocalVariableTable:
        Start  Length  Slot  Name   Signature
            0       8     0     t   Lscala/collection/IterableOnce;
    Signature: #11                          // <T:Ljava/lang/Object;>(Lscala/collection/IterableOnce<TT;>;)Lscala/collection/parallel/TraversableOps<TT;>;
    MethodParameters:
      Name                           Flags
      t                              final
}
SourceFile: "package.scala"
RuntimeVisibleAnnotations:
  0: #6(#7=s#8)
    scala.reflect.ScalaSignature(
      bytes="\u0006\u00055:a\u0001B\u0003\t\u0002\u001dYaAB\u0007\u0006\u0011\u00039a\u0002C\u0003\u0014\u0003\u0011\u0005Q\u0003C\u0003\u0017\u0003\u0011\rq#A\u000eQCJ\fG\u000e\\3m\u0007>dG.Z2uS>t\u0017*\u001c9mS\u000eLGo\u001d\u0006\u0003\r\u001d\t\u0001\u0002]1sC2dW\r\u001c\u0006\u0003\u0011%\t!bY8mY\u0016\u001cG/[8o\u0015\u0005Q\u0011!B:dC2\f\u0007C\u0001\u0007\u0002\u001b\u0005)!a\u0007)be\u0006dG.\u001a7D_2dWm\u0019;j_:LU\u000e\u001d7jG&$8o\u0005\u0002\u0002\u001fA\u0011\u0001#E\u0007\u0002\u0013%\u0011!#\u0003\u0002\u0007\u0003:L(+\u001a4\u0002\rqJg.\u001b;?\u0007\u0001!\u0012aC\u0001\u0010iJ\fg/\u001a:tC\ndWMM8qgV\u0011\u0001D\b\u000b\u00033\u001d\u00022\u0001\u0004\u000e\u001d\u0013\tYRA\u0001\bUe\u00064XM]:bE2,w\n]:\u0011\u0005uqB\u0002\u0001\u0003\u0006?\r\u0011\r\u0001\t\u0002\u0002)F\u0011\u0011\u0005\n\t\u0003!\tJ!aI\u0005\u0003\u000f9{G\u000f[5oOB\u0011\u0001#J\u0005\u0003M%\u00111!\u00118z\u0011\u0015A3\u00011\u0001*\u0003\u0005!\bc\u0001\u0016,95\tq!\u0003\u0002-\u000f\ta\u0011\n^3sC\ndWm\u00148dK\u0002"
    )
  ScalaSig: length = 0x3 (unknown attribute)
   05 02 00
