Classfile /Users/mw/Projects/slang-braindump/.jar/jar8/assemble/slang-braindump/assemble/content/scala/collection/parallel/ParallelCollectionImplicits$$anon$1.class
  Last modified May 29, 2022; size 2310 bytes
  SHA-256 checksum d2df4d90dbe389308fcd6d4f93924797b876df466d96ecda4af83a48b3a46c80
  Compiled from "package.scala"
public final class scala.collection.parallel.ParallelCollectionImplicits$$anon$1 extends java.lang.Object implements scala.collection.parallel.TraversableOps<T>
  minor version: 0
  major version: 52
  flags: (0x0031) ACC_PUBLIC, ACC_FINAL, ACC_SUPER
  this_class: #2                          // scala/collection/parallel/ParallelCollectionImplicits$$anon$1
  super_class: #5                         // java/lang/Object
  interfaces: 1, fields: 1, methods: 7, attributes: 6
Constant pool:
   #1 = Utf8               scala/collection/parallel/ParallelCollectionImplicits$$anon$1
   #2 = Class              #1             // scala/collection/parallel/ParallelCollectionImplicits$$anon$1
   #3 = Utf8               Ljava/lang/Object;Lscala/collection/parallel/TraversableOps<TT;>;
   #4 = Utf8               java/lang/Object
   #5 = Class              #4             // java/lang/Object
   #6 = Utf8               scala/collection/parallel/TraversableOps
   #7 = Class              #6             // scala/collection/parallel/TraversableOps
   #8 = Utf8               package.scala
   #9 = Utf8               scala/collection/parallel/ParallelCollectionImplicits$
  #10 = Class              #9             // scala/collection/parallel/ParallelCollectionImplicits$
  #11 = Utf8               traversable2ops
  #12 = Utf8               (Lscala/collection/IterableOnce;)Lscala/collection/parallel/TraversableOps;
  #13 = NameAndType        #11:#12        // traversable2ops:(Lscala/collection/IterableOnce;)Lscala/collection/parallel/TraversableOps;
  #14 = Utf8               scala/collection/parallel/ParallelCollectionImplicits$$anon$1$$anon$2
  #15 = Class              #14            // scala/collection/parallel/ParallelCollectionImplicits$$anon$1$$anon$2
  #16 = Utf8               scala/collection/parallel/TraversableOps$Otherwise
  #17 = Class              #16            // scala/collection/parallel/TraversableOps$Otherwise
  #18 = Utf8               Otherwise
  #19 = Utf8               t$1
  #20 = Utf8               Lscala/collection/IterableOnce;
  #21 = Utf8               isParallel
  #22 = Utf8               ()Z
  #23 = NameAndType        #19:#20        // t$1:Lscala/collection/IterableOnce;
  #24 = Fieldref           #2.#23         // scala/collection/parallel/ParallelCollectionImplicits$$anon$1.t$1:Lscala/collection/IterableOnce;
  #25 = Utf8               scala/collection/Parallel
  #26 = Class              #25            // scala/collection/Parallel
  #27 = Utf8               this
  #28 = Utf8               Lscala/collection/parallel/ParallelCollectionImplicits$$anon$1;
  #29 = Utf8               isParIterable
  #30 = Utf8               scala/collection/parallel/ParIterable
  #31 = Class              #30            // scala/collection/parallel/ParIterable
  #32 = Utf8               asParIterable
  #33 = Utf8               ()Lscala/collection/parallel/ParIterable;
  #34 = Utf8               ()Lscala/collection/parallel/ParIterable<TT;>;
  #35 = Utf8               isParSeq
  #36 = Utf8               scala/collection/parallel/ParSeq
  #37 = Class              #36            // scala/collection/parallel/ParSeq
  #38 = Utf8               asParSeq
  #39 = Utf8               ()Lscala/collection/parallel/ParSeq;
  #40 = Utf8               ()Lscala/collection/parallel/ParSeq<TT;>;
  #41 = Utf8               ifParSeq
  #42 = Utf8               (Lscala/Function1;)Lscala/collection/parallel/TraversableOps$Otherwise;
  #43 = Utf8               <R:Ljava/lang/Object;>(Lscala/Function1<Lscala/collection/parallel/ParSeq<TT;>;TR;>;)Lscala/collection/parallel/TraversableOps<TT;>.Otherwise<TR;>;
  #44 = Utf8               isbody
  #45 = Utf8               <init>
  #46 = Utf8               (Lscala/collection/parallel/ParallelCollectionImplicits$$anon$1;Lscala/Function1;)V
  #47 = NameAndType        #45:#46        // "<init>":(Lscala/collection/parallel/ParallelCollectionImplicits$$anon$1;Lscala/Function1;)V
  #48 = Methodref          #15.#47        // scala/collection/parallel/ParallelCollectionImplicits$$anon$1$$anon$2."<init>":(Lscala/collection/parallel/ParallelCollectionImplicits$$anon$1;Lscala/Function1;)V
  #49 = Utf8               Lscala/Function1;
  #50 = Utf8               (Lscala/collection/IterableOnce;)V
  #51 = Utf8               ()V
  #52 = NameAndType        #45:#51        // "<init>":()V
  #53 = Methodref          #5.#52         // java/lang/Object."<init>":()V
  #54 = Utf8               $init$
  #55 = Utf8               (Lscala/collection/parallel/TraversableOps;)V
  #56 = NameAndType        #54:#55        // $init$:(Lscala/collection/parallel/TraversableOps;)V
  #57 = InterfaceMethodref #7.#56         // scala/collection/parallel/TraversableOps.$init$:(Lscala/collection/parallel/TraversableOps;)V
  #58 = Utf8               Code
  #59 = Utf8               LineNumberTable
  #60 = Utf8               LocalVariableTable
  #61 = Utf8               Signature
  #62 = Utf8               MethodParameters
  #63 = Utf8               InnerClasses
  #64 = Utf8               EnclosingMethod
  #65 = Utf8               SourceFile
  #66 = Utf8               ScalaInlineInfo
  #67 = Utf8               Scala
{
  private final scala.collection.IterableOnce t$1;
    descriptor: Lscala/collection/IterableOnce;
    flags: (0x0012) ACC_PRIVATE, ACC_FINAL

  public boolean isParallel();
    descriptor: ()Z
    flags: (0x0001) ACC_PUBLIC
    Code:
      stack=1, locals=1, args_size=1
         0: aload_0
         1: getfield      #24                 // Field t$1:Lscala/collection/IterableOnce;
         4: instanceof    #26                 // class scala/collection/Parallel
         7: ireturn
      LineNumberTable:
        line 69: 0
      LocalVariableTable:
        Start  Length  Slot  Name   Signature
            0       8     0  this   Lscala/collection/parallel/ParallelCollectionImplicits$$anon$1;

  public boolean isParIterable();
    descriptor: ()Z
    flags: (0x0001) ACC_PUBLIC
    Code:
      stack=1, locals=1, args_size=1
         0: aload_0
         1: getfield      #24                 // Field t$1:Lscala/collection/IterableOnce;
         4: instanceof    #31                 // class scala/collection/parallel/ParIterable
         7: ireturn
      LineNumberTable:
        line 70: 0
      LocalVariableTable:
        Start  Length  Slot  Name   Signature
            0       8     0  this   Lscala/collection/parallel/ParallelCollectionImplicits$$anon$1;

  public scala.collection.parallel.ParIterable<T> asParIterable();
    descriptor: ()Lscala/collection/parallel/ParIterable;
    flags: (0x0001) ACC_PUBLIC
    Code:
      stack=1, locals=1, args_size=1
         0: aload_0
         1: getfield      #24                 // Field t$1:Lscala/collection/IterableOnce;
         4: checkcast     #31                 // class scala/collection/parallel/ParIterable
         7: areturn
      LineNumberTable:
        line 71: 0
      LocalVariableTable:
        Start  Length  Slot  Name   Signature
            0       8     0  this   Lscala/collection/parallel/ParallelCollectionImplicits$$anon$1;
    Signature: #34                          // ()Lscala/collection/parallel/ParIterable<TT;>;

  public boolean isParSeq();
    descriptor: ()Z
    flags: (0x0001) ACC_PUBLIC
    Code:
      stack=1, locals=1, args_size=1
         0: aload_0
         1: getfield      #24                 // Field t$1:Lscala/collection/IterableOnce;
         4: instanceof    #37                 // class scala/collection/parallel/ParSeq
         7: ireturn
      LineNumberTable:
        line 72: 0
      LocalVariableTable:
        Start  Length  Slot  Name   Signature
            0       8     0  this   Lscala/collection/parallel/ParallelCollectionImplicits$$anon$1;

  public scala.collection.parallel.ParSeq<T> asParSeq();
    descriptor: ()Lscala/collection/parallel/ParSeq;
    flags: (0x0001) ACC_PUBLIC
    Code:
      stack=1, locals=1, args_size=1
         0: aload_0
         1: getfield      #24                 // Field t$1:Lscala/collection/IterableOnce;
         4: checkcast     #37                 // class scala/collection/parallel/ParSeq
         7: areturn
      LineNumberTable:
        line 73: 0
      LocalVariableTable:
        Start  Length  Slot  Name   Signature
            0       8     0  this   Lscala/collection/parallel/ParallelCollectionImplicits$$anon$1;
    Signature: #40                          // ()Lscala/collection/parallel/ParSeq<TT;>;

  public <R extends java.lang.Object> scala.collection.parallel.TraversableOps<T>.Otherwise<R> ifParSeq(scala.Function1<scala.collection.parallel.ParSeq<T>, R>);
    descriptor: (Lscala/Function1;)Lscala/collection/parallel/TraversableOps$Otherwise;
    flags: (0x0001) ACC_PUBLIC
    Code:
      stack=4, locals=2, args_size=2
         0: new           #15                 // class scala/collection/parallel/ParallelCollectionImplicits$$anon$1$$anon$2
         3: dup
         4: aload_0
         5: aload_1
         6: invokespecial #48                 // Method scala/collection/parallel/ParallelCollectionImplicits$$anon$1$$anon$2."<init>":(Lscala/collection/parallel/ParallelCollectionImplicits$$anon$1;Lscala/Function1;)V
         9: areturn
      LineNumberTable:
        line 74: 0
      LocalVariableTable:
        Start  Length  Slot  Name   Signature
            0      10     0  this   Lscala/collection/parallel/ParallelCollectionImplicits$$anon$1;
            0      10     1 isbody   Lscala/Function1;
    Signature: #43                          // <R:Ljava/lang/Object;>(Lscala/Function1<Lscala/collection/parallel/ParSeq<TT;>;TR;>;)Lscala/collection/parallel/TraversableOps<TT;>.Otherwise<TR;>;
    MethodParameters:
      Name                           Flags
      isbody                         final

  public scala.collection.parallel.ParallelCollectionImplicits$$anon$1(scala.collection.IterableOnce);
    descriptor: (Lscala/collection/IterableOnce;)V
    flags: (0x0001) ACC_PUBLIC
    Code:
      stack=2, locals=2, args_size=2
         0: aload_0
         1: aload_1
         2: putfield      #24                 // Field t$1:Lscala/collection/IterableOnce;
         5: aload_0
         6: invokespecial #53                 // Method java/lang/Object."<init>":()V
         9: aload_0
        10: invokestatic  #57                 // InterfaceMethod scala/collection/parallel/TraversableOps.$init$:(Lscala/collection/parallel/TraversableOps;)V
        13: return
      LineNumberTable:
        line 68: 0
      LocalVariableTable:
        Start  Length  Slot  Name   Signature
            0      14     0  this   Lscala/collection/parallel/ParallelCollectionImplicits$$anon$1;
            0      14     1   t$1   Lscala/collection/IterableOnce;
    MethodParameters:
      Name                           Flags
      t$1                            final
}
InnerClasses:
  public final #2;                        // class scala/collection/parallel/ParallelCollectionImplicits$$anon$1
  public final #15;                       // class scala/collection/parallel/ParallelCollectionImplicits$$anon$1$$anon$2
  public #18= #17 of #7;                  // Otherwise=class scala/collection/parallel/TraversableOps$Otherwise of class scala/collection/parallel/TraversableOps
EnclosingMethod: #10.#13                // scala.collection.parallel.ParallelCollectionImplicits$.traversable2ops
Signature: #3                           // Ljava/lang/Object;Lscala/collection/parallel/TraversableOps<TT;>;
SourceFile: "package.scala"
  ScalaInlineInfo: length = 0x27 (unknown attribute)
   01 01 00 07 00 2D 00 32 01 00 20 00 21 01 00 26
   00 27 01 00 29 00 2A 01 00 1D 00 16 01 00 23 00
   16 01 00 15 00 16 01
  Scala: length = 0x0 (unknown attribute)

