Classfile /Users/mw/Projects/slang-braindump/.jar/jar8/assemble/slang-braindump/assemble/content/scala/collection/parallel/ParIterableLike$$anon$1.class
  Last modified May 29, 2022; size 4175 bytes
  SHA-256 checksum 46f0a2377b079f60dd0de716bd139d71de5aace91bfad92fd5744946e7dc22ab
  Compiled from "ParIterableLike.scala"
public final class scala.collection.parallel.ParIterableLike$$anon$1 extends java.lang.Object implements scala.collection.parallel.ParIterableLike<T, CC, Repr, Sequential>.TaskOps<R, Tp>
  minor version: 0
  major version: 52
  flags: (0x0031) ACC_PUBLIC, ACC_FINAL, ACC_SUPER
  this_class: #2                          // scala/collection/parallel/ParIterableLike$$anon$1
  super_class: #5                         // java/lang/Object
  interfaces: 1, fields: 2, methods: 5, attributes: 6
Constant pool:
   #1 = Utf8               scala/collection/parallel/ParIterableLike$$anon$1
   #2 = Class              #1             // scala/collection/parallel/ParIterableLike$$anon$1
   #3 = Utf8               Ljava/lang/Object;Lscala/collection/parallel/ParIterableLike<TT;TCC;TRepr;TSequential;>.TaskOps<TR;TTp;>;
   #4 = Utf8               java/lang/Object
   #5 = Class              #4             // java/lang/Object
   #6 = Utf8               scala/collection/parallel/ParIterableLike$TaskOps
   #7 = Class              #6             // scala/collection/parallel/ParIterableLike$TaskOps
   #8 = Utf8               ParIterableLike.scala
   #9 = Utf8               scala/collection/parallel/ParIterableLike
  #10 = Class              #9             // scala/collection/parallel/ParIterableLike
  #11 = Utf8               task2ops
  #12 = Utf8               (Lscala/collection/parallel/ParIterableLike$StrictSplitterCheckTask;)Lscala/collection/parallel/ParIterableLike$TaskOps;
  #13 = NameAndType        #11:#12        // task2ops:(Lscala/collection/parallel/ParIterableLike$StrictSplitterCheckTask;)Lscala/collection/parallel/ParIterableLike$TaskOps;
  #14 = Utf8               scala/collection/parallel/ParIterableLike$$anon$1$$anon$2
  #15 = Class              #14            // scala/collection/parallel/ParIterableLike$$anon$1$$anon$2
  #16 = Utf8               scala/collection/parallel/ParIterableLike$$anon$1$$anon$3
  #17 = Class              #16            // scala/collection/parallel/ParIterableLike$$anon$1$$anon$3
  #18 = Utf8               scala/collection/parallel/ParIterableLike$$anon$1$$anon$4
  #19 = Class              #18            // scala/collection/parallel/ParIterableLike$$anon$1$$anon$4
  #20 = Utf8               scala/collection/parallel/ParIterableLike$ParComposite
  #21 = Class              #20            // scala/collection/parallel/ParIterableLike$ParComposite
  #22 = Utf8               ParComposite
  #23 = Utf8               scala/collection/parallel/ParIterableLike$ResultMapping
  #24 = Class              #23            // scala/collection/parallel/ParIterableLike$ResultMapping
  #25 = Utf8               ResultMapping
  #26 = Utf8               scala/collection/parallel/ParIterableLike$SeqComposite
  #27 = Class              #26            // scala/collection/parallel/ParIterableLike$SeqComposite
  #28 = Utf8               SeqComposite
  #29 = Utf8               scala/collection/parallel/ParIterableLike$StrictSplitterCheckTask
  #30 = Class              #29            // scala/collection/parallel/ParIterableLike$StrictSplitterCheckTask
  #31 = Utf8               StrictSplitterCheckTask
  #32 = Utf8               TaskOps
  #33 = Utf8               $outer
  #34 = Utf8               Lscala/collection/parallel/ParIterableLike;
  #35 = Utf8               tsk$1
  #36 = Utf8               Lscala/collection/parallel/ParIterableLike$StrictSplitterCheckTask;
  #37 = Utf8               mapResult
  #38 = Utf8               (Lscala/Function1;)Lscala/collection/parallel/ParIterableLike$ResultMapping;
  #39 = Utf8               <R1:Ljava/lang/Object;>(Lscala/Function1<TR;TR1;>;)Lscala/collection/parallel/ParIterableLike<TT;TCC;TRepr;TSequential;>.ResultMapping<TR;TTp;TR1;>;
  #40 = Utf8               mapping
  #41 = Utf8               <init>
  #42 = Utf8               (Lscala/collection/parallel/ParIterableLike$$anon$1;Lscala/Function1;)V
  #43 = NameAndType        #41:#42        // "<init>":(Lscala/collection/parallel/ParIterableLike$$anon$1;Lscala/Function1;)V
  #44 = Methodref          #15.#43        // scala/collection/parallel/ParIterableLike$$anon$1$$anon$2."<init>":(Lscala/collection/parallel/ParIterableLike$$anon$1;Lscala/Function1;)V
  #45 = Utf8               this
  #46 = Utf8               Lscala/collection/parallel/ParIterableLike$$anon$1;
  #47 = Utf8               Lscala/Function1;
  #48 = Utf8               compose
  #49 = Utf8               (Lscala/collection/parallel/ParIterableLike$StrictSplitterCheckTask;Lscala/Function2;)Lscala/collection/parallel/ParIterableLike$SeqComposite;
  #50 = Utf8               <R3:Ljava/lang/Object;R2:Ljava/lang/Object;Tp2:Ljava/lang/Object;>(Lscala/collection/parallel/ParIterableLike<TT;TCC;TRepr;TSequential;>.StrictSplitterCheckTask<TR2;TTp2;>;Lscala/Function2<TR;TR2;TR3;>;)Lscala/collection/parallel/ParIterableLike<TT;TCC;TRepr;TSequential;>.SeqComposite<TR;TR2;TR3;Lscala/collection/parallel/ParIterableLike<TT;TCC;TRepr;TSequential;>.StrictSplitterCheckTask<TR;TTp;>;Lscala/collection/parallel/ParIterableLike<TT;TCC;TRepr;TSequential;>.StrictSplitterCheckTask<TR2;TTp2;>;>;
  #51 = Utf8               t2
  #52 = Utf8               resCombiner
  #53 = Utf8               (Lscala/collection/parallel/ParIterableLike$$anon$1;Lscala/collection/parallel/ParIterableLike$StrictSplitterCheckTask;Lscala/Function2;)V
  #54 = NameAndType        #41:#53        // "<init>":(Lscala/collection/parallel/ParIterableLike$$anon$1;Lscala/collection/parallel/ParIterableLike$StrictSplitterCheckTask;Lscala/Function2;)V
  #55 = Methodref          #17.#54        // scala/collection/parallel/ParIterableLike$$anon$1$$anon$3."<init>":(Lscala/collection/parallel/ParIterableLike$$anon$1;Lscala/collection/parallel/ParIterableLike$StrictSplitterCheckTask;Lscala/Function2;)V
  #56 = Utf8               Lscala/Function2;
  #57 = Utf8               parallel
  #58 = Utf8               (Lscala/collection/parallel/ParIterableLike$StrictSplitterCheckTask;Lscala/Function2;)Lscala/collection/parallel/ParIterableLike$ParComposite;
  #59 = Utf8               <R3:Ljava/lang/Object;R2:Ljava/lang/Object;Tp2:Ljava/lang/Object;>(Lscala/collection/parallel/ParIterableLike<TT;TCC;TRepr;TSequential;>.StrictSplitterCheckTask<TR2;TTp2;>;Lscala/Function2<TR;TR2;TR3;>;)Lscala/collection/parallel/ParIterableLike<TT;TCC;TRepr;TSequential;>.ParComposite<TR;TR2;TR3;Lscala/collection/parallel/ParIterableLike<TT;TCC;TRepr;TSequential;>.StrictSplitterCheckTask<TR;TTp;>;Lscala/collection/parallel/ParIterableLike<TT;TCC;TRepr;TSequential;>.StrictSplitterCheckTask<TR2;TTp2;>;>;
  #60 = Methodref          #19.#54        // scala/collection/parallel/ParIterableLike$$anon$1$$anon$4."<init>":(Lscala/collection/parallel/ParIterableLike$$anon$1;Lscala/collection/parallel/ParIterableLike$StrictSplitterCheckTask;Lscala/Function2;)V
  #61 = Utf8               scala$collection$parallel$ParIterableLike$$anon$$$outer
  #62 = Utf8               ()Lscala/collection/parallel/ParIterableLike;
  #63 = NameAndType        #33:#34        // $outer:Lscala/collection/parallel/ParIterableLike;
  #64 = Fieldref           #2.#63         // scala/collection/parallel/ParIterableLike$$anon$1.$outer:Lscala/collection/parallel/ParIterableLike;
  #65 = Utf8               (Lscala/collection/parallel/ParIterableLike;Lscala/collection/parallel/ParIterableLike$StrictSplitterCheckTask;)V
  #66 = NameAndType        #35:#36        // tsk$1:Lscala/collection/parallel/ParIterableLike$StrictSplitterCheckTask;
  #67 = Fieldref           #2.#66         // scala/collection/parallel/ParIterableLike$$anon$1.tsk$1:Lscala/collection/parallel/ParIterableLike$StrictSplitterCheckTask;
  #68 = Utf8               ()V
  #69 = NameAndType        #41:#68        // "<init>":()V
  #70 = Methodref          #5.#69         // java/lang/Object."<init>":()V
  #71 = Utf8               Signature
  #72 = Utf8               Code
  #73 = Utf8               LineNumberTable
  #74 = Utf8               LocalVariableTable
  #75 = Utf8               MethodParameters
  #76 = Utf8               StackMapTable
  #77 = Utf8               InnerClasses
  #78 = Utf8               EnclosingMethod
  #79 = Utf8               SourceFile
  #80 = Utf8               ScalaInlineInfo
  #81 = Utf8               Scala
{
  private final scala.collection.parallel.ParIterableLike $outer;
    descriptor: Lscala/collection/parallel/ParIterableLike;
    flags: (0x1012) ACC_PRIVATE, ACC_FINAL, ACC_SYNTHETIC

  public final scala.collection.parallel.ParIterableLike$StrictSplitterCheckTask tsk$1;
    descriptor: Lscala/collection/parallel/ParIterableLike$StrictSplitterCheckTask;
    flags: (0x0011) ACC_PUBLIC, ACC_FINAL
    Signature: #36                          // Lscala/collection/parallel/ParIterableLike$StrictSplitterCheckTask;

  public <R1 extends java.lang.Object> scala.collection.parallel.ParIterableLike<T, CC, Repr, Sequential>.ResultMapping<R, Tp, R1> mapResult(scala.Function1<R, R1>);
    descriptor: (Lscala/Function1;)Lscala/collection/parallel/ParIterableLike$ResultMapping;
    flags: (0x0001) ACC_PUBLIC
    Code:
      stack=4, locals=2, args_size=2
         0: new           #15                 // class scala/collection/parallel/ParIterableLike$$anon$1$$anon$2
         3: dup
         4: aload_0
         5: aload_1
         6: invokespecial #44                 // Method scala/collection/parallel/ParIterableLike$$anon$1$$anon$2."<init>":(Lscala/collection/parallel/ParIterableLike$$anon$1;Lscala/Function1;)V
         9: areturn
      LineNumberTable:
        line 299: 0
      LocalVariableTable:
        Start  Length  Slot  Name   Signature
            0      10     0  this   Lscala/collection/parallel/ParIterableLike$$anon$1;
            0      10     1 mapping   Lscala/Function1;
    Signature: #39                          // <R1:Ljava/lang/Object;>(Lscala/Function1<TR;TR1;>;)Lscala/collection/parallel/ParIterableLike<TT;TCC;TRepr;TSequential;>.ResultMapping<TR;TTp;TR1;>;
    MethodParameters:
      Name                           Flags
      mapping                        final

  public <R3 extends java.lang.Object, R2 extends java.lang.Object, Tp2 extends java.lang.Object> scala.collection.parallel.ParIterableLike<T, CC, Repr, Sequential>.SeqComposite<R, R2, R3, scala.collection.parallel.ParIterableLike<T, CC, Repr, Sequential>.StrictSplitterCheckTask<R, Tp>, scala.collection.parallel.ParIterableLike<T, CC, Repr, Sequential>.StrictSplitterCheckTask<R2, Tp2>> compose(scala.collection.parallel.ParIterableLike<T, CC, Repr, Sequential>.StrictSplitterCheckTask<R2, Tp2>, scala.Function2<R, R2, R3>);
    descriptor: (Lscala/collection/parallel/ParIterableLike$StrictSplitterCheckTask;Lscala/Function2;)Lscala/collection/parallel/ParIterableLike$SeqComposite;
    flags: (0x0001) ACC_PUBLIC
    Code:
      stack=5, locals=3, args_size=3
         0: new           #17                 // class scala/collection/parallel/ParIterableLike$$anon$1$$anon$3
         3: dup
         4: aload_0
         5: aload_1
         6: aload_2
         7: invokespecial #55                 // Method scala/collection/parallel/ParIterableLike$$anon$1$$anon$3."<init>":(Lscala/collection/parallel/ParIterableLike$$anon$1;Lscala/collection/parallel/ParIterableLike$StrictSplitterCheckTask;Lscala/Function2;)V
        10: areturn
      LineNumberTable:
        line 303: 0
      LocalVariableTable:
        Start  Length  Slot  Name   Signature
            0      11     0  this   Lscala/collection/parallel/ParIterableLike$$anon$1;
            0      11     1    t2   Lscala/collection/parallel/ParIterableLike$StrictSplitterCheckTask;
            0      11     2 resCombiner   Lscala/Function2;
    Signature: #50                          // <R3:Ljava/lang/Object;R2:Ljava/lang/Object;Tp2:Ljava/lang/Object;>(Lscala/collection/parallel/ParIterableLike<TT;TCC;TRepr;TSequential;>.StrictSplitterCheckTask<TR2;TTp2;>;Lscala/Function2<TR;TR2;TR3;>;)Lscala/collection/parallel/ParIterableLike<TT;TCC;TRepr;TSequential;>.SeqComposite<TR;TR2;TR3;Lscala/collection/parallel/ParIterableLike<TT;TCC;TRepr;TSequential;>.StrictSplitterCheckTask<TR;TTp;>;Lscala/collection/parallel/ParIterableLike<TT;TCC;TRepr;TSequential;>.StrictSplitterCheckTask<TR2;TTp2;>;>;
    MethodParameters:
      Name                           Flags
      t2                             final
      resCombiner                    final

  public <R3 extends java.lang.Object, R2 extends java.lang.Object, Tp2 extends java.lang.Object> scala.collection.parallel.ParIterableLike<T, CC, Repr, Sequential>.ParComposite<R, R2, R3, scala.collection.parallel.ParIterableLike<T, CC, Repr, Sequential>.StrictSplitterCheckTask<R, Tp>, scala.collection.parallel.ParIterableLike<T, CC, Repr, Sequential>.StrictSplitterCheckTask<R2, Tp2>> parallel(scala.collection.parallel.ParIterableLike<T, CC, Repr, Sequential>.StrictSplitterCheckTask<R2, Tp2>, scala.Function2<R, R2, R3>);
    descriptor: (Lscala/collection/parallel/ParIterableLike$StrictSplitterCheckTask;Lscala/Function2;)Lscala/collection/parallel/ParIterableLike$ParComposite;
    flags: (0x0001) ACC_PUBLIC
    Code:
      stack=5, locals=3, args_size=3
         0: new           #19                 // class scala/collection/parallel/ParIterableLike$$anon$1$$anon$4
         3: dup
         4: aload_0
         5: aload_1
         6: aload_2
         7: invokespecial #60                 // Method scala/collection/parallel/ParIterableLike$$anon$1$$anon$4."<init>":(Lscala/collection/parallel/ParIterableLike$$anon$1;Lscala/collection/parallel/ParIterableLike$StrictSplitterCheckTask;Lscala/Function2;)V
        10: areturn
      LineNumberTable:
        line 307: 0
      LocalVariableTable:
        Start  Length  Slot  Name   Signature
            0      11     0  this   Lscala/collection/parallel/ParIterableLike$$anon$1;
            0      11     1    t2   Lscala/collection/parallel/ParIterableLike$StrictSplitterCheckTask;
            0      11     2 resCombiner   Lscala/Function2;
    Signature: #59                          // <R3:Ljava/lang/Object;R2:Ljava/lang/Object;Tp2:Ljava/lang/Object;>(Lscala/collection/parallel/ParIterableLike<TT;TCC;TRepr;TSequential;>.StrictSplitterCheckTask<TR2;TTp2;>;Lscala/Function2<TR;TR2;TR3;>;)Lscala/collection/parallel/ParIterableLike<TT;TCC;TRepr;TSequential;>.ParComposite<TR;TR2;TR3;Lscala/collection/parallel/ParIterableLike<TT;TCC;TRepr;TSequential;>.StrictSplitterCheckTask<TR;TTp;>;Lscala/collection/parallel/ParIterableLike<TT;TCC;TRepr;TSequential;>.StrictSplitterCheckTask<TR2;TTp2;>;>;
    MethodParameters:
      Name                           Flags
      t2                             final
      resCombiner                    final

  public scala.collection.parallel.ParIterableLike scala$collection$parallel$ParIterableLike$$anon$$$outer();
    descriptor: ()Lscala/collection/parallel/ParIterableLike;
    flags: (0x1001) ACC_PUBLIC, ACC_SYNTHETIC
    Code:
      stack=1, locals=1, args_size=1
         0: aload_0
         1: getfield      #64                 // Field $outer:Lscala/collection/parallel/ParIterableLike;
         4: areturn
      LineNumberTable:
        line 298: 0
      LocalVariableTable:
        Start  Length  Slot  Name   Signature
            0       5     0  this   Lscala/collection/parallel/ParIterableLike$$anon$1;

  public scala.collection.parallel.ParIterableLike$$anon$1(scala.collection.parallel.ParIterableLike, scala.collection.parallel.ParIterableLike$StrictSplitterCheckTask);
    descriptor: (Lscala/collection/parallel/ParIterableLike;Lscala/collection/parallel/ParIterableLike$StrictSplitterCheckTask;)V
    flags: (0x0001) ACC_PUBLIC
    Code:
      stack=2, locals=3, args_size=3
         0: aload_1
         1: ifnonnull     6
         4: aconst_null
         5: athrow
         6: aload_0
         7: aload_1
         8: putfield      #64                 // Field $outer:Lscala/collection/parallel/ParIterableLike;
        11: aload_0
        12: aload_2
        13: putfield      #67                 // Field tsk$1:Lscala/collection/parallel/ParIterableLike$StrictSplitterCheckTask;
        16: aload_0
        17: invokespecial #70                 // Method java/lang/Object."<init>":()V
        20: return
      StackMapTable: number_of_entries = 1
        frame_type = 6 /* same */
      LineNumberTable:
        line 298: 0
      LocalVariableTable:
        Start  Length  Slot  Name   Signature
            0      21     0  this   Lscala/collection/parallel/ParIterableLike$$anon$1;
            0      21     1 $outer   Lscala/collection/parallel/ParIterableLike;
            0      21     2 tsk$1   Lscala/collection/parallel/ParIterableLike$StrictSplitterCheckTask;
    MethodParameters:
      Name                           Flags
      $outer                         final synthetic
      tsk$1                          final
}
InnerClasses:
  public final #2;                        // class scala/collection/parallel/ParIterableLike$$anon$1
  public final #15;                       // class scala/collection/parallel/ParIterableLike$$anon$1$$anon$2
  public final #17;                       // class scala/collection/parallel/ParIterableLike$$anon$1$$anon$3
  public final #19;                       // class scala/collection/parallel/ParIterableLike$$anon$1$$anon$4
  public abstract #22= #21 of #10;        // ParComposite=class scala/collection/parallel/ParIterableLike$ParComposite of class scala/collection/parallel/ParIterableLike
  public abstract #25= #24 of #10;        // ResultMapping=class scala/collection/parallel/ParIterableLike$ResultMapping of class scala/collection/parallel/ParIterableLike
  public abstract #28= #27 of #10;        // SeqComposite=class scala/collection/parallel/ParIterableLike$SeqComposite of class scala/collection/parallel/ParIterableLike
  public #31= #30 of #10;                 // StrictSplitterCheckTask=class scala/collection/parallel/ParIterableLike$StrictSplitterCheckTask of class scala/collection/parallel/ParIterableLike
  public #32= #7 of #10;                  // TaskOps=class scala/collection/parallel/ParIterableLike$TaskOps of class scala/collection/parallel/ParIterableLike
EnclosingMethod: #10.#13                // scala.collection.parallel.ParIterableLike.task2ops
Signature: #3                           // Ljava/lang/Object;Lscala/collection/parallel/ParIterableLike<TT;TCC;TRepr;TSequential;>.TaskOps<TR;TTp;>;
SourceFile: "ParIterableLike.scala"
  ScalaInlineInfo: length = 0x1D (unknown attribute)
   01 01 00 05 00 29 00 41 01 00 30 00 31 01 00 25
   00 26 01 00 39 00 3A 01 00 3D 00 3E 01
  Scala: length = 0x0 (unknown attribute)

