Classfile /Users/mw/Projects/slang-braindump/.jar/jar8/assemble/slang-braindump/assemble/content/scala/collection/parallel/ParIterableLike$$anon$1$$anon$2.class
  Last modified May 29, 2022; size 1747 bytes
  SHA-256 checksum fe312d246814b3849dcbcdbaca3b28a93ca84860f480655553e4ede46dc1c30d
  Compiled from "ParIterableLike.scala"
public final class scala.collection.parallel.ParIterableLike$$anon$1$$anon$2 extends scala.collection.parallel.ParIterableLike<T, CC, Repr, Sequential>.ResultMapping<R, Tp, R1>
  minor version: 0
  major version: 52
  flags: (0x0031) ACC_PUBLIC, ACC_FINAL, ACC_SUPER
  this_class: #2                          // scala/collection/parallel/ParIterableLike$$anon$1$$anon$2
  super_class: #5                         // scala/collection/parallel/ParIterableLike$ResultMapping
  interfaces: 0, fields: 1, methods: 2, attributes: 6
Constant pool:
   #1 = Utf8               scala/collection/parallel/ParIterableLike$$anon$1$$anon$2
   #2 = Class              #1             // scala/collection/parallel/ParIterableLike$$anon$1$$anon$2
   #3 = Utf8               Lscala/collection/parallel/ParIterableLike<TT;TCC;TRepr;TSequential;>.ResultMapping<TR;TTp;TR1;>;
   #4 = Utf8               scala/collection/parallel/ParIterableLike$ResultMapping
   #5 = Class              #4             // scala/collection/parallel/ParIterableLike$ResultMapping
   #6 = Utf8               ParIterableLike.scala
   #7 = Utf8               scala/collection/parallel/ParIterableLike$$anon$1
   #8 = Class              #7             // scala/collection/parallel/ParIterableLike$$anon$1
   #9 = Utf8               mapResult
  #10 = Utf8               (Lscala/Function1;)Lscala/collection/parallel/ParIterableLike$ResultMapping;
  #11 = NameAndType        #9:#10         // mapResult:(Lscala/Function1;)Lscala/collection/parallel/ParIterableLike$ResultMapping;
  #12 = Utf8               scala/collection/parallel/ParIterableLike
  #13 = Class              #12            // scala/collection/parallel/ParIterableLike
  #14 = Utf8               ResultMapping
  #15 = Utf8               scala/collection/parallel/ParIterableLike$StrictSplitterCheckTask
  #16 = Class              #15            // scala/collection/parallel/ParIterableLike$StrictSplitterCheckTask
  #17 = Utf8               StrictSplitterCheckTask
  #18 = Utf8               mapping$1
  #19 = Utf8               Lscala/Function1;
  #20 = Utf8               map
  #21 = Utf8               (Ljava/lang/Object;)Ljava/lang/Object;
  #22 = Utf8               (TR;)TR1;
  #23 = Utf8               r
  #24 = NameAndType        #18:#19        // mapping$1:Lscala/Function1;
  #25 = Fieldref           #2.#24         // scala/collection/parallel/ParIterableLike$$anon$1$$anon$2.mapping$1:Lscala/Function1;
  #26 = Utf8               scala/Function1
  #27 = Class              #26            // scala/Function1
  #28 = Utf8               apply
  #29 = NameAndType        #28:#21        // apply:(Ljava/lang/Object;)Ljava/lang/Object;
  #30 = InterfaceMethodref #27.#29        // scala/Function1.apply:(Ljava/lang/Object;)Ljava/lang/Object;
  #31 = Utf8               this
  #32 = Utf8               Lscala/collection/parallel/ParIterableLike$$anon$1$$anon$2;
  #33 = Utf8               Ljava/lang/Object;
  #34 = Utf8               <init>
  #35 = Utf8               (Lscala/collection/parallel/ParIterableLike$$anon$1;Lscala/Function1;)V
  #36 = Utf8               $outer
  #37 = Utf8               scala$collection$parallel$ParIterableLike$$anon$$$outer
  #38 = Utf8               ()Lscala/collection/parallel/ParIterableLike;
  #39 = NameAndType        #37:#38        // scala$collection$parallel$ParIterableLike$$anon$$$outer:()Lscala/collection/parallel/ParIterableLike;
  #40 = Methodref          #8.#39         // scala/collection/parallel/ParIterableLike$$anon$1.scala$collection$parallel$ParIterableLike$$anon$$$outer:()Lscala/collection/parallel/ParIterableLike;
  #41 = Utf8               tsk$1
  #42 = Utf8               Lscala/collection/parallel/ParIterableLike$StrictSplitterCheckTask;
  #43 = NameAndType        #41:#42        // tsk$1:Lscala/collection/parallel/ParIterableLike$StrictSplitterCheckTask;
  #44 = Fieldref           #8.#43         // scala/collection/parallel/ParIterableLike$$anon$1.tsk$1:Lscala/collection/parallel/ParIterableLike$StrictSplitterCheckTask;
  #45 = Utf8               (Lscala/collection/parallel/ParIterableLike;Lscala/collection/parallel/ParIterableLike$StrictSplitterCheckTask;)V
  #46 = NameAndType        #34:#45        // "<init>":(Lscala/collection/parallel/ParIterableLike;Lscala/collection/parallel/ParIterableLike$StrictSplitterCheckTask;)V
  #47 = Methodref          #5.#46         // scala/collection/parallel/ParIterableLike$ResultMapping."<init>":(Lscala/collection/parallel/ParIterableLike;Lscala/collection/parallel/ParIterableLike$StrictSplitterCheckTask;)V
  #48 = Utf8               Lscala/collection/parallel/ParIterableLike$$anon$1;
  #49 = Utf8               Code
  #50 = Utf8               LineNumberTable
  #51 = Utf8               LocalVariableTable
  #52 = Utf8               Signature
  #53 = Utf8               MethodParameters
  #54 = Utf8               InnerClasses
  #55 = Utf8               EnclosingMethod
  #56 = Utf8               SourceFile
  #57 = Utf8               ScalaInlineInfo
  #58 = Utf8               Scala
{
  private final scala.Function1 mapping$1;
    descriptor: Lscala/Function1;
    flags: (0x0012) ACC_PRIVATE, ACC_FINAL

  public R1 map(R);
    descriptor: (Ljava/lang/Object;)Ljava/lang/Object;
    flags: (0x0001) ACC_PUBLIC
    Code:
      stack=2, locals=2, args_size=2
         0: aload_0
         1: getfield      #25                 // Field mapping$1:Lscala/Function1;
         4: aload_1
         5: invokeinterface #30,  2           // InterfaceMethod scala/Function1.apply:(Ljava/lang/Object;)Ljava/lang/Object;
        10: areturn
      LineNumberTable:
        line 300: 0
      LocalVariableTable:
        Start  Length  Slot  Name   Signature
            0      11     0  this   Lscala/collection/parallel/ParIterableLike$$anon$1$$anon$2;
            0      11     1     r   Ljava/lang/Object;
    Signature: #22                          // (TR;)TR1;
    MethodParameters:
      Name                           Flags
      r                              final

  public scala.collection.parallel.ParIterableLike$$anon$1$$anon$2(scala.collection.parallel.ParIterableLike$$anon$1, scala.Function1);
    descriptor: (Lscala/collection/parallel/ParIterableLike$$anon$1;Lscala/Function1;)V
    flags: (0x0001) ACC_PUBLIC
    Code:
      stack=3, locals=3, args_size=3
         0: aload_0
         1: aload_2
         2: putfield      #25                 // Field mapping$1:Lscala/Function1;
         5: aload_0
         6: aload_1
         7: invokevirtual #40                 // Method scala/collection/parallel/ParIterableLike$$anon$1.scala$collection$parallel$ParIterableLike$$anon$$$outer:()Lscala/collection/parallel/ParIterableLike;
        10: aload_1
        11: getfield      #44                 // Field scala/collection/parallel/ParIterableLike$$anon$1.tsk$1:Lscala/collection/parallel/ParIterableLike$StrictSplitterCheckTask;
        14: invokespecial #47                 // Method scala/collection/parallel/ParIterableLike$ResultMapping."<init>":(Lscala/collection/parallel/ParIterableLike;Lscala/collection/parallel/ParIterableLike$StrictSplitterCheckTask;)V
        17: return
      LineNumberTable:
        line 299: 0
      LocalVariableTable:
        Start  Length  Slot  Name   Signature
            0      18     0  this   Lscala/collection/parallel/ParIterableLike$$anon$1$$anon$2;
            0      18     1 $outer   Lscala/collection/parallel/ParIterableLike$$anon$1;
            0      18     2 mapping$1   Lscala/Function1;
    MethodParameters:
      Name                           Flags
      $outer                         final synthetic
      mapping$1                      final
}
InnerClasses:
  public final #8;                        // class scala/collection/parallel/ParIterableLike$$anon$1
  public final #2;                        // class scala/collection/parallel/ParIterableLike$$anon$1$$anon$2
  public abstract #14= #5 of #13;         // ResultMapping=class scala/collection/parallel/ParIterableLike$ResultMapping of class scala/collection/parallel/ParIterableLike
  public #17= #16 of #13;                 // StrictSplitterCheckTask=class scala/collection/parallel/ParIterableLike$StrictSplitterCheckTask of class scala/collection/parallel/ParIterableLike
EnclosingMethod: #8.#11                 // scala.collection.parallel.ParIterableLike$$anon$1.mapResult
Signature: #3                           // Lscala/collection/parallel/ParIterableLike<TT;TCC;TRepr;TSequential;>.ResultMapping<TR;TTp;TR1;>;
SourceFile: "ParIterableLike.scala"
  ScalaInlineInfo: length = 0xE (unknown attribute)
   01 01 00 02 00 22 00 23 01 00 14 00 15 01
  Scala: length = 0x0 (unknown attribute)

