Classfile /Users/mw/Projects/slang-braindump/.jar/jar8/assemble/slang-braindump/assemble/content/scala/collection/parallel/ParIterableLike$$anon$7.class
  Last modified May 29, 2022; size 2357 bytes
  SHA-256 checksum c2e4d5d3f77af7cf1824e6e2eacde65935e223851d209f90bf3c3495989ef0d4
  Compiled from "ParIterableLike.scala"
public final class scala.collection.parallel.ParIterableLike$$anon$7 extends java.lang.Object implements scala.collection.parallel.ParIterableLike<T, CC, Repr, Sequential>.BuilderOps<Elem, To>
  minor version: 0
  major version: 52
  flags: (0x0031) ACC_PUBLIC, ACC_FINAL, ACC_SUPER
  this_class: #2                          // scala/collection/parallel/ParIterableLike$$anon$7
  super_class: #5                         // java/lang/Object
  interfaces: 1, fields: 2, methods: 5, attributes: 6
Constant pool:
   #1 = Utf8               scala/collection/parallel/ParIterableLike$$anon$7
   #2 = Class              #1             // scala/collection/parallel/ParIterableLike$$anon$7
   #3 = Utf8               Ljava/lang/Object;Lscala/collection/parallel/ParIterableLike<TT;TCC;TRepr;TSequential;>.BuilderOps<TElem;TTo;>;
   #4 = Utf8               java/lang/Object
   #5 = Class              #4             // java/lang/Object
   #6 = Utf8               scala/collection/parallel/ParIterableLike$BuilderOps
   #7 = Class              #6             // scala/collection/parallel/ParIterableLike$BuilderOps
   #8 = Utf8               ParIterableLike.scala
   #9 = Utf8               scala/collection/parallel/ParIterableLike
  #10 = Class              #9             // scala/collection/parallel/ParIterableLike
  #11 = Utf8               builder2ops
  #12 = Utf8               (Lscala/collection/mutable/Builder;)Lscala/collection/parallel/ParIterableLike$BuilderOps;
  #13 = NameAndType        #11:#12        // builder2ops:(Lscala/collection/mutable/Builder;)Lscala/collection/parallel/ParIterableLike$BuilderOps;
  #14 = Utf8               scala/collection/parallel/ParIterableLike$$anon$7$$anon$8
  #15 = Class              #14            // scala/collection/parallel/ParIterableLike$$anon$7$$anon$8
  #16 = Utf8               BuilderOps
  #17 = Utf8               scala/collection/parallel/ParIterableLike$BuilderOps$Otherwise
  #18 = Class              #17            // scala/collection/parallel/ParIterableLike$BuilderOps$Otherwise
  #19 = Utf8               Otherwise
  #20 = Utf8               $outer
  #21 = Utf8               Lscala/collection/parallel/ParIterableLike;
  #22 = Utf8               cb$1
  #23 = Utf8               Lscala/collection/mutable/Builder;
  #24 = Utf8               ifIs
  #25 = Utf8               (Lscala/Function1;)Lscala/collection/parallel/ParIterableLike$BuilderOps$Otherwise;
  #26 = Utf8               <Cmb:Ljava/lang/Object;>(Lscala/Function1<TCmb;Lscala/runtime/BoxedUnit;>;)Lscala/collection/parallel/ParIterableLike<TT;TCC;TRepr;TSequential;>.BuilderOps<TElem;TTo;>.Otherwise<TCmb;>;
  #27 = Utf8               isbody
  #28 = Utf8               <init>
  #29 = Utf8               (Lscala/collection/parallel/ParIterableLike$$anon$7;Lscala/Function1;)V
  #30 = NameAndType        #28:#29        // "<init>":(Lscala/collection/parallel/ParIterableLike$$anon$7;Lscala/Function1;)V
  #31 = Methodref          #15.#30        // scala/collection/parallel/ParIterableLike$$anon$7$$anon$8."<init>":(Lscala/collection/parallel/ParIterableLike$$anon$7;Lscala/Function1;)V
  #32 = Utf8               this
  #33 = Utf8               Lscala/collection/parallel/ParIterableLike$$anon$7;
  #34 = Utf8               Lscala/Function1;
  #35 = Utf8               isCombiner
  #36 = Utf8               ()Z
  #37 = NameAndType        #22:#23        // cb$1:Lscala/collection/mutable/Builder;
  #38 = Fieldref           #2.#37         // scala/collection/parallel/ParIterableLike$$anon$7.cb$1:Lscala/collection/mutable/Builder;
  #39 = Utf8               scala/collection/parallel/Combiner
  #40 = Class              #39            // scala/collection/parallel/Combiner
  #41 = Utf8               asCombiner
  #42 = Utf8               ()Lscala/collection/parallel/Combiner;
  #43 = Utf8               ()Lscala/collection/parallel/Combiner<TElem;TTo;>;
  #44 = Utf8               scala$collection$parallel$ParIterableLike$BuilderOps$$$outer
  #45 = Utf8               ()Lscala/collection/parallel/ParIterableLike;
  #46 = NameAndType        #20:#21        // $outer:Lscala/collection/parallel/ParIterableLike;
  #47 = Fieldref           #2.#46         // scala/collection/parallel/ParIterableLike$$anon$7.$outer:Lscala/collection/parallel/ParIterableLike;
  #48 = Utf8               (Lscala/collection/parallel/ParIterableLike;Lscala/collection/mutable/Builder;)V
  #49 = Utf8               ()V
  #50 = NameAndType        #28:#49        // "<init>":()V
  #51 = Methodref          #5.#50         // java/lang/Object."<init>":()V
  #52 = Utf8               $init$
  #53 = Utf8               (Lscala/collection/parallel/ParIterableLike$BuilderOps;)V
  #54 = NameAndType        #52:#53        // $init$:(Lscala/collection/parallel/ParIterableLike$BuilderOps;)V
  #55 = InterfaceMethodref #7.#54         // scala/collection/parallel/ParIterableLike$BuilderOps.$init$:(Lscala/collection/parallel/ParIterableLike$BuilderOps;)V
  #56 = Utf8               Code
  #57 = Utf8               LineNumberTable
  #58 = Utf8               LocalVariableTable
  #59 = Utf8               Signature
  #60 = Utf8               MethodParameters
  #61 = Utf8               StackMapTable
  #62 = Utf8               InnerClasses
  #63 = Utf8               EnclosingMethod
  #64 = Utf8               SourceFile
  #65 = Utf8               ScalaInlineInfo
  #66 = Utf8               Scala
{
  private final scala.collection.parallel.ParIterableLike $outer;
    descriptor: Lscala/collection/parallel/ParIterableLike;
    flags: (0x1012) ACC_PRIVATE, ACC_FINAL, ACC_SYNTHETIC

  public final scala.collection.mutable.Builder cb$1;
    descriptor: Lscala/collection/mutable/Builder;
    flags: (0x0011) ACC_PUBLIC, ACC_FINAL

  public <Cmb extends java.lang.Object> scala.collection.parallel.ParIterableLike<T, CC, Repr, Sequential>.BuilderOps<Elem, To>.Otherwise<Cmb> ifIs(scala.Function1<Cmb, scala.runtime.BoxedUnit>);
    descriptor: (Lscala/Function1;)Lscala/collection/parallel/ParIterableLike$BuilderOps$Otherwise;
    flags: (0x0001) ACC_PUBLIC
    Code:
      stack=4, locals=2, args_size=2
         0: new           #15                 // class scala/collection/parallel/ParIterableLike$$anon$7$$anon$8
         3: dup
         4: aload_0
         5: aload_1
         6: invokespecial #31                 // Method scala/collection/parallel/ParIterableLike$$anon$7$$anon$8."<init>":(Lscala/collection/parallel/ParIterableLike$$anon$7;Lscala/Function1;)V
         9: areturn
      LineNumberTable:
        line 326: 0
      LocalVariableTable:
        Start  Length  Slot  Name   Signature
            0      10     0  this   Lscala/collection/parallel/ParIterableLike$$anon$7;
            0      10     1 isbody   Lscala/Function1;
    Signature: #26                          // <Cmb:Ljava/lang/Object;>(Lscala/Function1<TCmb;Lscala/runtime/BoxedUnit;>;)Lscala/collection/parallel/ParIterableLike<TT;TCC;TRepr;TSequential;>.BuilderOps<TElem;TTo;>.Otherwise<TCmb;>;
    MethodParameters:
      Name                           Flags
      isbody                         final

  public boolean isCombiner();
    descriptor: ()Z
    flags: (0x0001) ACC_PUBLIC
    Code:
      stack=1, locals=1, args_size=1
         0: aload_0
         1: getfield      #38                 // Field cb$1:Lscala/collection/mutable/Builder;
         4: instanceof    #40                 // class scala/collection/parallel/Combiner
         7: ireturn
      LineNumberTable:
        line 331: 0
      LocalVariableTable:
        Start  Length  Slot  Name   Signature
            0       8     0  this   Lscala/collection/parallel/ParIterableLike$$anon$7;

  public scala.collection.parallel.Combiner<Elem, To> asCombiner();
    descriptor: ()Lscala/collection/parallel/Combiner;
    flags: (0x0001) ACC_PUBLIC
    Code:
      stack=1, locals=1, args_size=1
         0: aload_0
         1: getfield      #38                 // Field cb$1:Lscala/collection/mutable/Builder;
         4: checkcast     #40                 // class scala/collection/parallel/Combiner
         7: areturn
      LineNumberTable:
        line 332: 0
      LocalVariableTable:
        Start  Length  Slot  Name   Signature
            0       8     0  this   Lscala/collection/parallel/ParIterableLike$$anon$7;
    Signature: #43                          // ()Lscala/collection/parallel/Combiner<TElem;TTo;>;

  public scala.collection.parallel.ParIterableLike scala$collection$parallel$ParIterableLike$BuilderOps$$$outer();
    descriptor: ()Lscala/collection/parallel/ParIterableLike;
    flags: (0x1001) ACC_PUBLIC, ACC_SYNTHETIC
    Code:
      stack=1, locals=1, args_size=1
         0: aload_0
         1: getfield      #47                 // Field $outer:Lscala/collection/parallel/ParIterableLike;
         4: areturn
      LineNumberTable:
        line 325: 0
      LocalVariableTable:
        Start  Length  Slot  Name   Signature
            0       5     0  this   Lscala/collection/parallel/ParIterableLike$$anon$7;

  public scala.collection.parallel.ParIterableLike$$anon$7(scala.collection.parallel.ParIterableLike, scala.collection.mutable.Builder);
    descriptor: (Lscala/collection/parallel/ParIterableLike;Lscala/collection/mutable/Builder;)V
    flags: (0x0001) ACC_PUBLIC
    Code:
      stack=2, locals=3, args_size=3
         0: aload_1
         1: ifnonnull     6
         4: aconst_null
         5: athrow
         6: aload_0
         7: aload_1
         8: putfield      #47                 // Field $outer:Lscala/collection/parallel/ParIterableLike;
        11: aload_0
        12: aload_2
        13: putfield      #38                 // Field cb$1:Lscala/collection/mutable/Builder;
        16: aload_0
        17: invokespecial #51                 // Method java/lang/Object."<init>":()V
        20: aload_0
        21: invokestatic  #55                 // InterfaceMethod scala/collection/parallel/ParIterableLike$BuilderOps.$init$:(Lscala/collection/parallel/ParIterableLike$BuilderOps;)V
        24: return
      StackMapTable: number_of_entries = 1
        frame_type = 6 /* same */
      LineNumberTable:
        line 325: 0
      LocalVariableTable:
        Start  Length  Slot  Name   Signature
            0      25     0  this   Lscala/collection/parallel/ParIterableLike$$anon$7;
            0      25     1 $outer   Lscala/collection/parallel/ParIterableLike;
            0      25     2  cb$1   Lscala/collection/mutable/Builder;
    MethodParameters:
      Name                           Flags
      $outer                         final synthetic
      cb$1                           final
}
InnerClasses:
  public final #2;                        // class scala/collection/parallel/ParIterableLike$$anon$7
  public final #15;                       // class scala/collection/parallel/ParIterableLike$$anon$7$$anon$8
  public #16= #7 of #10;                  // BuilderOps=class scala/collection/parallel/ParIterableLike$BuilderOps of class scala/collection/parallel/ParIterableLike
  public #19= #18 of #7;                  // Otherwise=class scala/collection/parallel/ParIterableLike$BuilderOps$Otherwise of class scala/collection/parallel/ParIterableLike$BuilderOps
EnclosingMethod: #10.#13                // scala.collection.parallel.ParIterableLike.builder2ops
Signature: #3                           // Ljava/lang/Object;Lscala/collection/parallel/ParIterableLike<TT;TCC;TRepr;TSequential;>.BuilderOps<TElem;TTo;>;
SourceFile: "ParIterableLike.scala"
  ScalaInlineInfo: length = 0x1D (unknown attribute)
   01 01 00 05 00 1C 00 30 01 00 29 00 2A 01 00 18
   00 19 01 00 23 00 24 01 00 2C 00 2D 01
  Scala: length = 0x0 (unknown attribute)

