Classfile /Users/mw/Projects/slang-braindump/.jar/jar8/assemble/slang-braindump/assemble/content/scala/collection/parallel/ParMapLike.class
  Last modified May 29, 2022; size 23423 bytes
  SHA-256 checksum 64de4653954443a46306761e5b58a662df3f8481f80ad9f1b17453bf7d5f402d
  Compiled from "ParMapLike.scala"
public interface scala.collection.parallel.ParMapLike<K extends java.lang.Object, V extends java.lang.Object, CC extends scala.collection.parallel.ParMap<java.lang.Object, java.lang.Object>, Repr extends scala.collection.parallel.ParMapLike<K, V, scala.collection.parallel.ParMap, Repr, Sequential> & scala.collection.parallel.ParMap<K, V>, Sequential extends scala.collection.Map<K, V> & scala.collection.MapOps<K, V, scala.collection.Map, Sequential>> extends scala.collection.parallel.ParIterableLike<scala.Tuple2<K, V>, scala.collection.parallel.ParIterable, Repr, Sequential>, scala.Equals
  minor version: 0
  major version: 52
  flags: (0x0601) ACC_PUBLIC, ACC_INTERFACE, ACC_ABSTRACT
  this_class: #2                          // scala/collection/parallel/ParMapLike
  super_class: #5                         // java/lang/Object
  interfaces: 2, fields: 0, methods: 69, attributes: 7
Constant pool:
    #1 = Utf8               scala/collection/parallel/ParMapLike
    #2 = Class              #1            // scala/collection/parallel/ParMapLike
    #3 = Utf8               <K:Ljava/lang/Object;V:Ljava/lang/Object;CC::Lscala/collection/parallel/ParMap<Ljava/lang/Object;Ljava/lang/Object;>;Repr::Lscala/collection/parallel/ParMapLike<TK;TV;Lscala/collection/parallel/ParMap;TRepr;TSequential;>;:Lscala/collection/parallel/ParMap<TK;TV;>;Sequential::Lscala/collection/Map<TK;TV;>;:Lscala/collection/MapOps<TK;TV;Lscala/collection/Map;TSequential;>;>Ljava/lang/Object;Lscala/collection/parallel/ParIterableLike<Lscala/Tuple2<TK;TV;>;Lscala/collection/parallel/ParIterable;TRepr;TSequential;>;Lscala/Equals;
    #4 = Utf8               java/lang/Object
    #5 = Class              #4            // java/lang/Object
    #6 = Utf8               scala/collection/parallel/ParIterableLike
    #7 = Class              #6            // scala/collection/parallel/ParIterableLike
    #8 = Utf8               scala/Equals
    #9 = Class              #8            // scala/Equals
   #10 = Utf8               ParMapLike.scala
   #11 = Utf8               Lscala/reflect/ScalaSignature;
   #12 = Utf8               bytes
   #13 = Utf8               \u0006\u0005\t\u0005haB\u00181!\u0003\r\ta\u000e\u0005\u0006e\u0002!\ta\u001d\u0005\u0006o\u00021\t\u0001\u001f\u0005\u0006}\u0002!\ta \u0005\b\u0003\u0017\u0001A\u0011IA\u0007\u0011\u001d\t\t\u0002\u0001C!\u0003\'Aq!a\u0007\u0001\r\u0003\ti\u0002C\u0004\u0002H\u0001!\t!!\u0013\t\u000f\u0005e\u0003A\"\u0001\u0002\\!9\u0011q\f\u0001\u0007\u0002\u0005\u0005\u0004bBA9\u0001\u0011\u0005\u00111\u000f\u0005\b\u0003o\u0002a\u0011AA=\u0011\u001d\tY\b\u0001C\u0001\u0003{Bq!!!\u0001\t\u0003\t\u0019\tC\u0004\u0002\u0018\u0002!\t!!\'\t\u000f\u0005u\u0005\u0001\"\u0001\u0002 \"A\u00111\u0015\u0001!\n\u0013\t)\u000bC\u0004\u0002$\u0002!\t!a2\t\u0011\u0005%\u0007\u0001)C\u0005\u0003\u0017Dq!!3\u0001\t\u0003\t\tN\u0002\u0004\u0002T\u0002A\u0011Q\u001b\u0005\b\u0003;$B\u0011AAp\u0011\u001d\t9\n\u0006C\u0001\u0003KDq!!;\u0015\t\u0003\t9\rC\u0004\u0002\u001cQ!\t!a;\t\u000f\u0005eC\u0003\"\u0001\u0002r\"9\u0011Q\u001f\u000b\u0005\u0002\u0005]\bbBA})\u0011\u0005\u0013q\u001f\u0005\b\u0003w$B\u0011IA\u007f\u0011\u001d\u0011y\u0001\u0006C!\u0005#1aA!\u0007\u0001\u0011\tm\u0001bBAo=\u0011\u0005!q\u0004\u0005\b\u0003StB\u0011AAi\u0011\u001d\t)P\bC\u0001\u0003oDq!!?\u001f\t\u0003\n9\u0010C\u0004\u0002|z!\tEa\t\t\u000f\t=a\u0004\"\u0001\u00030!9!q\u0007\u0001\u0005\u0002\te\u0002b\u0002B\u001e\u0001\u0011\u0005!Q\b\u0005\b\u0005\u0003\u0002A\u0011\u0001B\"\u0011\u001d\u0011)\u0005\u0001C\u0001\u0005\u000fBqAa\u0014\u0001\t\u0003\u0011\t\u0006C\u0004\u0003b\u0001!\tAa\u0019\t\u000f\tm\u0004\u0001\"\u0001\u0003~!9!q\u0013\u0001\u0005\u0002\te\u0005b\u0002BZ\u0001\u0011\u0005!Q\u0017\u0005\b\u0005\u000b\u0004AQ\u0001Bd\u0005)\u0001\u0016M]\'ba2K7.\u001a\u0006\u0003cI\n\u0001\u0002]1sC2dW\r\u001c\u0006\u0003gQ\n!bY8mY\u0016\u001cG/[8o\u0015\u0005)\u0014!B:dC2\f7\u0001A\u000b\bq\u0019\u0003\u00161\u0005,b\'\u0011\u0001\u0011(P8\u0011\u0005iZT\"\u0001\u001b\n\u0005q\"$AB!osJ+g\r\u0005\u0004?\u007f\u0005\u0013V\u000bY\u0007\u0002a%\u0011\u0001\t\r\u0002\u0010!\u0006\u0014\u0018\n^3sC\ndW\rT5lKB!!H\u0011#P\u0013\t\u0019EG\u0001\u0004UkBdWM\r\t\u0003\u000b\u001ac\u0001\u0001B\u0003H\u0001\t\u0007\u0001JA\u0001L#\tIE\n\u0005\u0002;\u0015&\u00111\n\u000e\u0002\b\u001d>$\b.\u001b8h!\tQT*\u0003\u0002Oi\t\u0019\u0011I\\=\u0011\u0005\u0015\u0003FAB)\u0001\t\u000b\u0007\u0001JA\u0001W!\tq4+\u0003\u0002Ua\tY\u0001+\u0019:Ji\u0016\u0014\u0018M\u00197f!\t)e\u000b\u0002\u0004X\u0001\u0011\u0015\r\u0001\u0017\u0002\u0005%\u0016\u0004(/\u0005\u0002J3J\u0019!\f\u00188\u0007\tm\u0003\u0001!\u0017\u0002\ryI,g-\u001b8f[\u0016tGO\u0010\t\b}\u0001!u*X+a!\tqd,\u0003\u0002`a\t1\u0001+\u0019:NCB\u0004\"!R1\u0005\r\t\u0004AQ1\u0001d\u0005)\u0019V-];f]RL\u0017\r\\\t\u0003\u0013\u0012\u00142!\u001a4k\r\u0011Y\u0006\u0001\u00013\u0011\t\u001dDGiT\u0007\u0002e%\u0011\u0011N\r\u0002\u0004\u001b\u0006\u0004\bCB4l\t>k\u0007-\u0003\u0002me\t1Q*\u00199PaN\u0004\"a\u001a5\u0011\tyrFi\u0014\t\u0003uAL!!\u001d\u001b\u0003\r\u0015\u000bX/\u00197t\u0003\u0019!\u0013N\\5uIQ\tA\u000f\u0005\u0002;k&\u0011a\u000f\u000e\u0002\u0005+:LG/A\u0002hKR$\"!\u001f?\u0011\u0007iRx*\u0003\u0002|i\t1q\n\u001d;j_:DQ! \u0002A\u0002\u0011\u000b1a[3z\u0003!\u0019\u0017M\\#rk\u0006dG\u0003BA\u0001\u0003\u000f\u00012AOA\u0002\u0013\r\t)\u0001\u000e\u0002\b\u0005>|G.Z1o\u0011\u0019\tIa\u0001a\u0001\u0019\u0006!A\u000f[1u\u0003\u0019)\u0017/^1mgR!\u0011\u0011AA\b\u0011\u0019\tI\u0001\u0002a\u0001\u0019\u0006A\u0001.Y:i\u0007>$W\r\u0006\u0002\u0002\u0016A\u0019!(a\u0006\n\u0007\u0005eAGA\u0002J]R\fQ\u0001\n9mkN,B!a\b\u0002<Q!\u0011\u0011EA!!\u0019)\u00151\u0005#\u0002:\u0011A\u0011Q\u0005\u0001\u0005\u0006\u0004\t9C\u0001\u0002D\u0007V1\u0011\u0011FA\u0018\u0003k\t2!SA\u0016!\u0019qd,!\f\u00024A\u0019Q)a\f\u0005\u000f\u0005E\u00121\u0005b\u0001\u0011\n\t\u0001\fE\u0002F\u0003k!q!a\u000e\u0002$\t\u0007\u0001JA\u0001Z!\r)\u00151\b\u0003\b\u0003{1!\u0019AA \u0005\t1\u0016\'\u0005\u0002P\u0019\"9\u00111\t\u0004A\u0002\u0005\u0015\u0013AA6w!\u0015Q$\tRA\u001d\u0003\u001d)\b\u000fZ1uK\u0012,B!a\u0013\u0002RQ1\u0011QJA*\u0003+\u0002b!RA\u0012\t\u0006=\u0003cA#\u0002R\u00119\u0011QH\u0004C\u0002\u0005}\u0002\"B?\b\u0001\u0004!\u0005bBA,\u000f\u0001\u0007\u0011qJ\u0001\u0006m\u0006dW/Z\u0001\u0007I5Lg.^:\u0015\u0007U\u000bi\u0006C\u0003~\u0011\u0001\u0007A)\u0001\u0007nCB\u001cu.\u001c9b]&|g.\u0006\u0002\u0002dA1\u0011QMA6\u0003_j!!a\u001a\u000b\u0007\u0005%$\'A\u0004hK:,\'/[2\n\t\u00055\u0014q\r\u0002\u0017\u000f\u0016tWM]5d!\u0006\u0014X*\u00199D_6\u0004\u0018M\\5p]B\u0019Q)a\t\u0002\u000f\u0011,g-Y;miR\u0019q*!\u001e\t\u000buT\u0001\u0019\u0001#\u0002\u000b\u0015l\u0007\u000f^=\u0016\u0003U\u000bQ!\u00199qYf$2aTA@\u0011\u0015iH\u00021\u0001E\u0003%9W\r^(s\u000b2\u001cX-\u0006\u0003\u0002\u0006\u0006%ECBAD\u0003\u001b\u000by\tE\u0002F\u0003\u0013#q!a#\u000e\u0005\u0004\tyDA\u0001V\u0011\u0015iX\u00021\u0001E\u0011!\t\t(\u0004CA\u0002\u0005E\u0005#\u0002\u001e\u0002\u0014\u0006\u001d\u0015bAAKi\tAAHY=oC6,g(\u0001\u0005d_:$\u0018-\u001b8t)\u0011\t\t!a\'\t\u000but\u0001\u0019\u0001#\u0002\u0017%\u001cH)\u001a4j]\u0016$\u0017\t\u001e\u000b\u0005\u0003\u0003\t\t\u000bC\u0003~\u001f\u0001\u0007A)\u0001\u0007lKf\u001c\u0018\n^3sCR|\'\u000f\u0006\u0003\u0002(\u00065\u0006\u0003\u0002 \u0002*\u0012K1!a+1\u0005AIE/\u001a:bE2,7\u000b\u001d7jiR,\'\u000fC\u0004\u00020B\u0001\r!!-\u0002\u0003MTC!a-\u00026B!a(!+BW\t\t9\f\u0005\u0003\u0002:\u0006\rWBAA^\u0015\u0011\ti,a0\u0002\u0013Ut7\r[3dW\u0016$\'bAAai\u0005Q\u0011M\u001c8pi\u0006$\u0018n\u001c8\n\t\u0005\u0015\u00171\u0018\u0002\u0012k:\u001c\u0007.Z2lK\u00124\u0016M]5b]\u000e,WCAAT\u000391\u0018\r\\;fg&#XM]1u_J$B!!4\u0002PB!a(!+P\u0011\u001d\tyK\u0005a\u0001\u0003c+\"!!4\u0003\u001b\u0011+g-Y;mi.+\u0017pU3u\'\u0011!\u0012(a6\u0011\ty\nI\u000eR\u0005\u0004\u00037\u0004$A\u0002)beN+G/\u0001\u0004=S:LGO\u0010\u000b\u0003\u0003C\u00042!a9\u0015\u001b\u0005\u0001A\u0003BA\u0001\u0003ODQ! \fA\u0002\u0011\u000b\u0001b\u001d9mSR$XM\u001d\u000b\u0005\u0003/\fi\u000f\u0003\u0004\u0002pb\u0001\r\u0001R\u0001\u0005K2,W\u000e\u0006\u0003\u0002X\u0006M\bBBAx3\u0001\u0007A)\u0001\u0003tSj,WCAA\u000b\u0003%Ygn\\<o\'&TX-A\u0004g_J,\u0017m\u00195\u0016\t\u0005}(Q\u0002\u000b\u0004i\n\u0005\u0001b\u0002B\u00029\u0001\u0007!QA\u0001\u0002MB1!Ha\u0002E\u0005\u0017I1A!\u00035\u0005%1UO\\2uS>t\u0017\u0007E\u0002F\u0005\u001b!a!a#\u001d\u0005\u0004A\u0015aA:fcV\u0011!1\u0003\t\u0005O\nUA)C\u0002\u0003\u0018I\u00121aU3u\u0005U!UMZ1vYR4\u0016\r\\;fg&#XM]1cY\u0016\u001cBAH\u001d\u0003\u001eA\u0019ahU(\u0015\u0005\t\u0005\u0002cAAr=U!!Q\u0005B\u0017)\r!(q\u0005\u0005\b\u0005\u0007\u0019\u0003\u0019\u0001B\u0015!\u0019Q$qA(\u0003,A\u0019QI!\f\u0005\r\u0005-5E1\u0001I+\t\u0011\t\u0004\u0005\u0003h\u0005gy\u0015b\u0001B\u001be\tA\u0011\n^3sC\ndW-\u0001\u0004lKf\u001cV\r^\u000b\u0003\u0003/\fAa[3zgV\u0011!q\b\t\u0004}M#\u0015A\u0002<bYV,7/\u0006\u0002\u0003\u001e\u0005Qa-\u001b7uKJ\\U-_:\u0015\u00079\u0014I\u0005C\u0004\u0003L!\u0002\rA!\u0014\u0002\u0003A\u0004bA\u000fB\u0004\t\u0006\u0005\u0011!C7baZ\u000bG.^3t+\u0011\u0011\u0019F!\u0017\u0015\t\tU#Q\f\t\u0006}y#%q\u000b\t\u0004\u000b\neCA\u0002B.S\t\u0007\u0001JA\u0001T\u0011\u001d\u0011\u0019!\u000ba\u0001\u0005?\u0002bA\u000fB\u0004\u001f\n]\u0013aA7baV1!Q\rB6\u0005c\"BAa\u001a\u0003vA9Q)a\t\u0003j\t=\u0004cA#\u0003l\u00111!Q\u000e\u0016C\u0002!\u0013!a\u0013\u001a\u0011\u0007\u0015\u0013\t\b\u0002\u0004\u0003t)\u0012\r\u0001\u0013\u0002\u0003-JBqAa\u0001+\u0001\u0004\u00119\b\u0005\u0004;\u0005\u000f\t%\u0011\u0010\t\u0007u\t\u0013IGa\u001c\u0002\u000f\r|G\u000e\\3diV1!q\u0010BC\u0005\u0013#BA!!\u0003\fB9Q)a\t\u0003\u0004\n\u001d\u0005cA#\u0003\u0006\u00121!QN\u0016C\u0002!\u00032!\u0012BE\t\u0019\u0011\u0019h\u000bb\u0001\u0011\"9!QR\u0016A\u0002\t=\u0015A\u00019g!\u0019Q$\u0011S!\u0003\u0016&\u0019!1\u0013\u001b\u0003\u001fA\u000b\'\u000f^5bY\u001a+hn\u0019;j_:\u0004bA\u000f\"\u0003\u0004\n\u001d\u0015a\u00024mCRl\u0015\r]\u000b\u0007\u00057\u0013\tK!*\u0015\t\tu%q\u0015\t\b\u000b\u0006\r\"q\u0014BR!\r)%\u0011\u0015\u0003\u0007\u0005[b#\u0019\u0001%\u0011\u0007\u0015\u0013)\u000b\u0002\u0004\u0003t1\u0012\r\u0001\u0013\u0005\b\u0005\u0007a\u0003\u0019\u0001BU!\u0019Q$qA!\u0003,B)qM!,\u00032&\u0019!q\u0016\u001a\u0003\u0019%#XM]1cY\u0016|enY3\u0011\ri\u0012%q\u0014BR\u0003\u0019\u0019wN\\2biV!!q\u0017B_)\u0011\u0011ILa0\u0011\r\u0015\u000b\u0019\u0003\u0012B^!\r)%Q\u0018\u0003\b\u0005gj#\u0019AA \u0011\u001d\tI!\fa\u0001\u0005\u0003\u0004Ra\u001aBW\u0005\u0007\u0004RA\u000f\"E\u0005w\u000b!\u0002\n9mkN$\u0003\u000f\\;t+\u0011\u0011IMa4\u0015\t\t-\'\u0011\u001b\t\u0007\u000b\u0006\rBI!4\u0011\u0007\u0015\u0013y\rB\u0004\u0003t9\u0012\r!a\u0010\t\u000f\tMg\u00061\u0001\u0003V\u0006\u0011\u0001p\u001d\t\u0006O\n5&q\u001b\t\u0006u\t#%Q\u001a\u0015\u0004]\tm\u0007c\u0001\u001e\u0003^&\u0019!q\u001c\u001b\u0003\r%tG.\u001b8f\u0001
   #14 = Utf8               java/lang/invoke/MethodHandles$Lookup
   #15 = Class              #14           // java/lang/invoke/MethodHandles$Lookup
   #16 = Utf8               java/lang/invoke/MethodHandles
   #17 = Class              #16           // java/lang/invoke/MethodHandles
   #18 = Utf8               Lookup
   #19 = Utf8               scala/collection/parallel/ParIterableLike$Collect
   #20 = Class              #19           // scala/collection/parallel/ParIterableLike$Collect
   #21 = Utf8               Collect
   #22 = Utf8               scala/collection/parallel/ParIterableLike$Copy
   #23 = Class              #22           // scala/collection/parallel/ParIterableLike$Copy
   #24 = Utf8               Copy
   #25 = Utf8               scala/collection/parallel/ParIterableLike$FlatMap
   #26 = Class              #25           // scala/collection/parallel/ParIterableLike$FlatMap
   #27 = Utf8               FlatMap
   #28 = Utf8               scala/collection/parallel/ParIterableLike$Map
   #29 = Class              #28           // scala/collection/parallel/ParIterableLike$Map
   #30 = Utf8               Map
   #31 = Utf8               scala/collection/parallel/ParIterableLike$NonDivisible
   #32 = Class              #31           // scala/collection/parallel/ParIterableLike$NonDivisible
   #33 = Utf8               NonDivisible
   #34 = Utf8               scala/collection/parallel/ParIterableLike$ParComposite
   #35 = Class              #34           // scala/collection/parallel/ParIterableLike$ParComposite
   #36 = Utf8               ParComposite
   #37 = Utf8               scala/collection/parallel/ParIterableLike$ResultMapping
   #38 = Class              #37           // scala/collection/parallel/ParIterableLike$ResultMapping
   #39 = Utf8               ResultMapping
   #40 = Utf8               scala/collection/parallel/ParIterableLike$StrictSplitterCheckTask
   #41 = Class              #40           // scala/collection/parallel/ParIterableLike$StrictSplitterCheckTask
   #42 = Utf8               StrictSplitterCheckTask
   #43 = Utf8               scala/collection/parallel/ParIterableLike$TaskOps
   #44 = Class              #43           // scala/collection/parallel/ParIterableLike$TaskOps
   #45 = Utf8               TaskOps
   #46 = Utf8               scala/collection/parallel/ParMapLike$$anon$1
   #47 = Class              #46           // scala/collection/parallel/ParMapLike$$anon$1
   #48 = Utf8               scala/collection/parallel/ParMapLike$$anon$2
   #49 = Class              #48           // scala/collection/parallel/ParMapLike$$anon$2
   #50 = Utf8               scala/collection/parallel/ParMapLike$$anon$3
   #51 = Class              #50           // scala/collection/parallel/ParMapLike$$anon$3
   #52 = Utf8               scala/collection/parallel/ParMapLike$$anon$4
   #53 = Class              #52           // scala/collection/parallel/ParMapLike$$anon$4
   #54 = Utf8               scala/collection/parallel/ParMapLike$DefaultKeySet
   #55 = Class              #54           // scala/collection/parallel/ParMapLike$DefaultKeySet
   #56 = Utf8               DefaultKeySet
   #57 = Utf8               scala/collection/parallel/ParMapLike$DefaultValuesIterable
   #58 = Class              #57           // scala/collection/parallel/ParMapLike$DefaultValuesIterable
   #59 = Utf8               DefaultValuesIterable
   #60 = Utf8               get
   #61 = Utf8               (Ljava/lang/Object;)Lscala/Option;
   #62 = Utf8               (TK;)Lscala/Option<TV;>;
   #63 = Utf8               key
   #64 = Utf8               canEqual$
   #65 = Utf8               (Lscala/collection/parallel/ParMapLike;Ljava/lang/Object;)Z
   #66 = Utf8               $this
   #67 = Utf8               that
   #68 = Utf8               canEqual
   #69 = Utf8               (Ljava/lang/Object;)Z
   #70 = NameAndType        #68:#69       // canEqual:(Ljava/lang/Object;)Z
   #71 = InterfaceMethodref #2.#70        // scala/collection/parallel/ParMapLike.canEqual:(Ljava/lang/Object;)Z
   #72 = Utf8               Lscala/collection/parallel/ParMapLike;
   #73 = Utf8               Ljava/lang/Object;
   #74 = Utf8               this
   #75 = Utf8               equals$
   #76 = Utf8               equals
   #77 = NameAndType        #76:#69       // equals:(Ljava/lang/Object;)Z
   #78 = InterfaceMethodref #2.#77        // scala/collection/parallel/ParMapLike.equals:(Ljava/lang/Object;)Z
   #79 = Utf8               java/lang/ClassCastException
   #80 = Class              #79           // java/lang/ClassCastException
   #81 = Utf8               scala/collection/parallel/ParMap
   #82 = Class              #81           // scala/collection/parallel/ParMap
   #83 = InterfaceMethodref #82.#70       // scala/collection/parallel/ParMap.canEqual:(Ljava/lang/Object;)Z
   #84 = Utf8               size
   #85 = Utf8               ()I
   #86 = NameAndType        #84:#85       // size:()I
   #87 = InterfaceMethodref #2.#86        // scala/collection/parallel/ParMapLike.size:()I
   #88 = InterfaceMethodref #82.#86       // scala/collection/parallel/ParMap.size:()I
   #89 = Utf8               (Ljava/lang/Object;)Ljava/lang/Object;
   #90 = MethodType         #89           //  (Ljava/lang/Object;)Ljava/lang/Object;
   #91 = Utf8               $anonfun$equals$1$adapted
   #92 = Utf8               (Lscala/collection/parallel/ParMap;Lscala/Tuple2;)Ljava/lang/Object;
   #93 = NameAndType        #91:#92       // $anonfun$equals$1$adapted:(Lscala/collection/parallel/ParMap;Lscala/Tuple2;)Ljava/lang/Object;
   #94 = InterfaceMethodref #2.#93        // scala/collection/parallel/ParMapLike.$anonfun$equals$1$adapted:(Lscala/collection/parallel/ParMap;Lscala/Tuple2;)Ljava/lang/Object;
   #95 = MethodHandle       6:#94         // REF_invokeStatic scala/collection/parallel/ParMapLike.$anonfun$equals$1$adapted:(Lscala/collection/parallel/ParMap;Lscala/Tuple2;)Ljava/lang/Object;
   #96 = Utf8               (Lscala/Tuple2;)Ljava/lang/Object;
   #97 = MethodType         #96           //  (Lscala/Tuple2;)Ljava/lang/Object;
   #98 = Integer            5
   #99 = Integer            1
  #100 = Utf8               java/lang/invoke/LambdaMetafactory
  #101 = Class              #100          // java/lang/invoke/LambdaMetafactory
  #102 = Utf8               altMetafactory
  #103 = Utf8               (Ljava/lang/invoke/MethodHandles$Lookup;Ljava/lang/String;Ljava/lang/invoke/MethodType;[Ljava/lang/Object;)Ljava/lang/invoke/CallSite;
  #104 = NameAndType        #102:#103     // altMetafactory:(Ljava/lang/invoke/MethodHandles$Lookup;Ljava/lang/String;Ljava/lang/invoke/MethodType;[Ljava/lang/Object;)Ljava/lang/invoke/CallSite;
  #105 = Methodref          #101.#104     // java/lang/invoke/LambdaMetafactory.altMetafactory:(Ljava/lang/invoke/MethodHandles$Lookup;Ljava/lang/String;Ljava/lang/invoke/MethodType;[Ljava/lang/Object;)Ljava/lang/invoke/CallSite;
  #106 = MethodHandle       6:#105        // REF_invokeStatic java/lang/invoke/LambdaMetafactory.altMetafactory:(Ljava/lang/invoke/MethodHandles$Lookup;Ljava/lang/String;Ljava/lang/invoke/MethodType;[Ljava/lang/Object;)Ljava/lang/invoke/CallSite;
  #107 = Utf8               apply
  #108 = Utf8               (Lscala/collection/parallel/ParMap;)Lscala/Function1;
  #109 = NameAndType        #107:#108     // apply:(Lscala/collection/parallel/ParMap;)Lscala/Function1;
  #110 = InvokeDynamic      #0:#109       // #0:apply:(Lscala/collection/parallel/ParMap;)Lscala/Function1;
  #111 = Utf8               forall
  #112 = Utf8               (Lscala/Function1;)Z
  #113 = NameAndType        #111:#112     // forall:(Lscala/Function1;)Z
  #114 = InterfaceMethodref #2.#113       // scala/collection/parallel/ParMapLike.forall:(Lscala/Function1;)Z
  #115 = Utf8               ex
  #116 = Utf8               Ljava/lang/ClassCastException;
  #117 = Utf8               hashCode$
  #118 = Utf8               (Lscala/collection/parallel/ParMapLike;)I
  #119 = Utf8               hashCode
  #120 = NameAndType        #119:#85      // hashCode:()I
  #121 = InterfaceMethodref #2.#120       // scala/collection/parallel/ParMapLike.hashCode:()I
  #122 = Utf8               scala/util/hashing/MurmurHash3$
  #123 = Class              #122          // scala/util/hashing/MurmurHash3$
  #124 = Utf8               MODULE$
  #125 = Utf8               Lscala/util/hashing/MurmurHash3$;
  #126 = NameAndType        #124:#125     // MODULE$:Lscala/util/hashing/MurmurHash3$;
  #127 = Fieldref           #123.#126     // scala/util/hashing/MurmurHash3$.MODULE$:Lscala/util/hashing/MurmurHash3$;
  #128 = Utf8               ParMap
  #129 = String             #128          // ParMap
  #130 = Utf8               java/lang/String
  #131 = Class              #130          // java/lang/String
  #132 = Methodref          #131.#120     // java/lang/String.hashCode:()I
  #133 = Utf8               unorderedHash
  #134 = Utf8               (Lscala/collection/IterableOnce;I)I
  #135 = NameAndType        #133:#134     // unorderedHash:(Lscala/collection/IterableOnce;I)I
  #136 = Methodref          #123.#135     // scala/util/hashing/MurmurHash3$.unorderedHash:(Lscala/collection/IterableOnce;I)I
  #137 = Utf8               $plus
  #138 = Utf8               (Lscala/Tuple2;)Lscala/collection/parallel/ParMap;
  #139 = Utf8               <V1:Ljava/lang/Object;>(Lscala/Tuple2<TK;TV1;>;)TCC;
  #140 = Utf8               kv
  #141 = Utf8               updated$
  #142 = Utf8               (Lscala/collection/parallel/ParMapLike;Ljava/lang/Object;Ljava/lang/Object;)Lscala/collection/parallel/ParMap;
  #143 = Utf8               value
  #144 = Utf8               updated
  #145 = Utf8               (Ljava/lang/Object;Ljava/lang/Object;)Lscala/collection/parallel/ParMap;
  #146 = NameAndType        #144:#145     // updated:(Ljava/lang/Object;Ljava/lang/Object;)Lscala/collection/parallel/ParMap;
  #147 = InterfaceMethodref #2.#146       // scala/collection/parallel/ParMapLike.updated:(Ljava/lang/Object;Ljava/lang/Object;)Lscala/collection/parallel/ParMap;
  #148 = Utf8               <V1:Ljava/lang/Object;>(TK;TV1;)TCC;
  #149 = Utf8               scala/Tuple2
  #150 = Class              #149          // scala/Tuple2
  #151 = Utf8               <init>
  #152 = Utf8               (Ljava/lang/Object;Ljava/lang/Object;)V
  #153 = NameAndType        #151:#152     // "<init>":(Ljava/lang/Object;Ljava/lang/Object;)V
  #154 = Methodref          #150.#153     // scala/Tuple2."<init>":(Ljava/lang/Object;Ljava/lang/Object;)V
  #155 = NameAndType        #137:#138     // $plus:(Lscala/Tuple2;)Lscala/collection/parallel/ParMap;
  #156 = InterfaceMethodref #2.#155       // scala/collection/parallel/ParMapLike.$plus:(Lscala/Tuple2;)Lscala/collection/parallel/ParMap;
  #157 = Utf8               $minus
  #158 = Utf8               (Ljava/lang/Object;)Lscala/collection/parallel/ParMap;
  #159 = Utf8               (TK;)TRepr;
  #160 = Utf8               mapCompanion
  #161 = Utf8               ()Lscala/collection/generic/GenericParMapCompanion;
  #162 = Utf8               ()Lscala/collection/generic/GenericParMapCompanion<TCC;>;
  #163 = Utf8               default$
  #164 = Utf8               (Lscala/collection/parallel/ParMapLike;Ljava/lang/Object;)Ljava/lang/Object;
  #165 = Utf8               default
  #166 = NameAndType        #165:#89      // default:(Ljava/lang/Object;)Ljava/lang/Object;
  #167 = InterfaceMethodref #2.#166       // scala/collection/parallel/ParMapLike.default:(Ljava/lang/Object;)Ljava/lang/Object;
  #168 = Utf8               (TK;)TV;
  #169 = Utf8               java/util/NoSuchElementException
  #170 = Class              #169          // java/util/NoSuchElementException
  #171 = Utf8               java/lang/StringBuilder
  #172 = Class              #171          // java/lang/StringBuilder
  #173 = Integer            15
  #174 = Utf8               (I)V
  #175 = NameAndType        #151:#174     // "<init>":(I)V
  #176 = Methodref          #172.#175     // java/lang/StringBuilder."<init>":(I)V
  #177 = Utf8               key not found:
  #178 = String             #177          // key not found:
  #179 = Utf8               append
  #180 = Utf8               (Ljava/lang/String;)Ljava/lang/StringBuilder;
  #181 = NameAndType        #179:#180     // append:(Ljava/lang/String;)Ljava/lang/StringBuilder;
  #182 = Methodref          #172.#181     // java/lang/StringBuilder.append:(Ljava/lang/String;)Ljava/lang/StringBuilder;
  #183 = Utf8               (Ljava/lang/Object;)Ljava/lang/StringBuilder;
  #184 = NameAndType        #179:#183     // append:(Ljava/lang/Object;)Ljava/lang/StringBuilder;
  #185 = Methodref          #172.#184     // java/lang/StringBuilder.append:(Ljava/lang/Object;)Ljava/lang/StringBuilder;
  #186 = Utf8               toString
  #187 = Utf8               ()Ljava/lang/String;
  #188 = NameAndType        #186:#187     // toString:()Ljava/lang/String;
  #189 = Methodref          #172.#188     // java/lang/StringBuilder.toString:()Ljava/lang/String;
  #190 = Utf8               (Ljava/lang/String;)V
  #191 = NameAndType        #151:#190     // "<init>":(Ljava/lang/String;)V
  #192 = Methodref          #170.#191     // java/util/NoSuchElementException."<init>":(Ljava/lang/String;)V
  #193 = Utf8               empty
  #194 = Utf8               ()Lscala/collection/parallel/ParMap;
  #195 = Utf8               ()TRepr;
  #196 = Utf8               apply$
  #197 = NameAndType        #107:#89      // apply:(Ljava/lang/Object;)Ljava/lang/Object;
  #198 = InterfaceMethodref #2.#197       // scala/collection/parallel/ParMapLike.apply:(Ljava/lang/Object;)Ljava/lang/Object;
  #199 = NameAndType        #60:#61       // get:(Ljava/lang/Object;)Lscala/Option;
  #200 = InterfaceMethodref #2.#199       // scala/collection/parallel/ParMapLike.get:(Ljava/lang/Object;)Lscala/Option;
  #201 = Utf8               scala/Some
  #202 = Class              #201          // scala/Some
  #203 = Utf8               ()Ljava/lang/Object;
  #204 = NameAndType        #143:#203     // value:()Ljava/lang/Object;
  #205 = Methodref          #202.#204     // scala/Some.value:()Ljava/lang/Object;
  #206 = Utf8               scala/None$
  #207 = Class              #206          // scala/None$
  #208 = Utf8               Lscala/None$;
  #209 = NameAndType        #124:#208     // MODULE$:Lscala/None$;
  #210 = Fieldref           #207.#209     // scala/None$.MODULE$:Lscala/None$;
  #211 = Methodref          #5.#77        // java/lang/Object.equals:(Ljava/lang/Object;)Z
  #212 = Utf8               scala/MatchError
  #213 = Class              #212          // scala/MatchError
  #214 = Utf8               (Ljava/lang/Object;)V
  #215 = NameAndType        #151:#214     // "<init>":(Ljava/lang/Object;)V
  #216 = Methodref          #213.#215     // scala/MatchError."<init>":(Ljava/lang/Object;)V
  #217 = Utf8               v
  #218 = Utf8               scala/Option
  #219 = Class              #218          // scala/Option
  #220 = Utf8               getOrElse$
  #221 = Utf8               (Lscala/collection/parallel/ParMapLike;Ljava/lang/Object;Lscala/Function0;)Ljava/lang/Object;
  #222 = Utf8               getOrElse
  #223 = Utf8               (Ljava/lang/Object;Lscala/Function0;)Ljava/lang/Object;
  #224 = NameAndType        #222:#223     // getOrElse:(Ljava/lang/Object;Lscala/Function0;)Ljava/lang/Object;
  #225 = InterfaceMethodref #2.#224       // scala/collection/parallel/ParMapLike.getOrElse:(Ljava/lang/Object;Lscala/Function0;)Ljava/lang/Object;
  #226 = Utf8               Lscala/Function0;
  #227 = Utf8               <U:Ljava/lang/Object;>(TK;Lscala/Function0<TU;>;)TU;
  #228 = Utf8               scala/Function0
  #229 = Class              #228          // scala/Function0
  #230 = NameAndType        #107:#203     // apply:()Ljava/lang/Object;
  #231 = InterfaceMethodref #229.#230     // scala/Function0.apply:()Ljava/lang/Object;
  #232 = Utf8               contains$
  #233 = Utf8               contains
  #234 = NameAndType        #233:#69      // contains:(Ljava/lang/Object;)Z
  #235 = InterfaceMethodref #2.#234       // scala/collection/parallel/ParMapLike.contains:(Ljava/lang/Object;)Z
  #236 = Utf8               (TK;)Z
  #237 = Utf8               isDefined
  #238 = Utf8               ()Z
  #239 = NameAndType        #237:#238     // isDefined:()Z
  #240 = Methodref          #219.#239     // scala/Option.isDefined:()Z
  #241 = Utf8               isDefinedAt$
  #242 = Utf8               isDefinedAt
  #243 = NameAndType        #242:#69      // isDefinedAt:(Ljava/lang/Object;)Z
  #244 = InterfaceMethodref #2.#243       // scala/collection/parallel/ParMapLike.isDefinedAt:(Ljava/lang/Object;)Z
  #245 = Utf8               scala$collection$parallel$ParMapLike$$keysIterator$
  #246 = Utf8               (Lscala/collection/parallel/ParMapLike;Lscala/collection/parallel/IterableSplitter;)Lscala/collection/parallel/IterableSplitter;
  #247 = Utf8               s
  #248 = Utf8               scala$collection$parallel$ParMapLike$$keysIterator
  #249 = Utf8               (Lscala/collection/parallel/IterableSplitter;)Lscala/collection/parallel/IterableSplitter;
  #250 = NameAndType        #248:#249     // scala$collection$parallel$ParMapLike$$keysIterator:(Lscala/collection/parallel/IterableSplitter;)Lscala/collection/parallel/IterableSplitter;
  #251 = InterfaceMethodref #2.#250       // scala/collection/parallel/ParMapLike.scala$collection$parallel$ParMapLike$$keysIterator:(Lscala/collection/parallel/IterableSplitter;)Lscala/collection/parallel/IterableSplitter;
  #252 = Utf8               Lscala/collection/parallel/IterableSplitter;
  #253 = Utf8               (Lscala/collection/parallel/IterableSplitter<Lscala/Tuple2<TK;TV;>;>;)Lscala/collection/parallel/IterableSplitter<TK;>;
  #254 = Utf8               (Lscala/collection/parallel/ParMapLike;Lscala/collection/parallel/IterableSplitter;)V
  #255 = NameAndType        #151:#254     // "<init>":(Lscala/collection/parallel/ParMapLike;Lscala/collection/parallel/IterableSplitter;)V
  #256 = Methodref          #47.#255      // scala/collection/parallel/ParMapLike$$anon$1."<init>":(Lscala/collection/parallel/ParMapLike;Lscala/collection/parallel/IterableSplitter;)V
  #257 = Utf8               keysIterator$
  #258 = Utf8               (Lscala/collection/parallel/ParMapLike;)Lscala/collection/parallel/IterableSplitter;
  #259 = Utf8               keysIterator
  #260 = Utf8               ()Lscala/collection/parallel/IterableSplitter;
  #261 = NameAndType        #259:#260     // keysIterator:()Lscala/collection/parallel/IterableSplitter;
  #262 = InterfaceMethodref #2.#261       // scala/collection/parallel/ParMapLike.keysIterator:()Lscala/collection/parallel/IterableSplitter;
  #263 = Utf8               ()Lscala/collection/parallel/IterableSplitter<TK;>;
  #264 = Utf8               splitter
  #265 = NameAndType        #264:#260     // splitter:()Lscala/collection/parallel/IterableSplitter;
  #266 = InterfaceMethodref #2.#265       // scala/collection/parallel/ParMapLike.splitter:()Lscala/collection/parallel/IterableSplitter;
  #267 = Utf8               scala$collection$parallel$ParMapLike$$valuesIterator$
  #268 = Utf8               scala$collection$parallel$ParMapLike$$valuesIterator
  #269 = NameAndType        #268:#249     // scala$collection$parallel$ParMapLike$$valuesIterator:(Lscala/collection/parallel/IterableSplitter;)Lscala/collection/parallel/IterableSplitter;
  #270 = InterfaceMethodref #2.#269       // scala/collection/parallel/ParMapLike.scala$collection$parallel$ParMapLike$$valuesIterator:(Lscala/collection/parallel/IterableSplitter;)Lscala/collection/parallel/IterableSplitter;
  #271 = Utf8               (Lscala/collection/parallel/IterableSplitter<Lscala/Tuple2<TK;TV;>;>;)Lscala/collection/parallel/IterableSplitter<TV;>;
  #272 = Methodref          #49.#255      // scala/collection/parallel/ParMapLike$$anon$2."<init>":(Lscala/collection/parallel/ParMapLike;Lscala/collection/parallel/IterableSplitter;)V
  #273 = Utf8               valuesIterator$
  #274 = Utf8               valuesIterator
  #275 = NameAndType        #274:#260     // valuesIterator:()Lscala/collection/parallel/IterableSplitter;
  #276 = InterfaceMethodref #2.#275       // scala/collection/parallel/ParMapLike.valuesIterator:()Lscala/collection/parallel/IterableSplitter;
  #277 = Utf8               ()Lscala/collection/parallel/IterableSplitter<TV;>;
  #278 = Utf8               keySet$
  #279 = Utf8               (Lscala/collection/parallel/ParMapLike;)Lscala/collection/parallel/ParSet;
  #280 = Utf8               keySet
  #281 = Utf8               ()Lscala/collection/parallel/ParSet;
  #282 = NameAndType        #280:#281     // keySet:()Lscala/collection/parallel/ParSet;
  #283 = InterfaceMethodref #2.#282       // scala/collection/parallel/ParMapLike.keySet:()Lscala/collection/parallel/ParSet;
  #284 = Utf8               ()Lscala/collection/parallel/ParSet<TK;>;
  #285 = Utf8               (Lscala/collection/parallel/ParMapLike;)V
  #286 = NameAndType        #151:#285     // "<init>":(Lscala/collection/parallel/ParMapLike;)V
  #287 = Methodref          #55.#286      // scala/collection/parallel/ParMapLike$DefaultKeySet."<init>":(Lscala/collection/parallel/ParMapLike;)V
  #288 = Utf8               keys$
  #289 = Utf8               (Lscala/collection/parallel/ParMapLike;)Lscala/collection/parallel/ParIterable;
  #290 = Utf8               keys
  #291 = Utf8               ()Lscala/collection/parallel/ParIterable;
  #292 = NameAndType        #290:#291     // keys:()Lscala/collection/parallel/ParIterable;
  #293 = InterfaceMethodref #2.#292       // scala/collection/parallel/ParMapLike.keys:()Lscala/collection/parallel/ParIterable;
  #294 = Utf8               ()Lscala/collection/parallel/ParIterable<TK;>;
  #295 = Utf8               values$
  #296 = Utf8               values
  #297 = NameAndType        #296:#291     // values:()Lscala/collection/parallel/ParIterable;
  #298 = InterfaceMethodref #2.#297       // scala/collection/parallel/ParMapLike.values:()Lscala/collection/parallel/ParIterable;
  #299 = Utf8               ()Lscala/collection/parallel/ParIterable<TV;>;
  #300 = Methodref          #58.#286      // scala/collection/parallel/ParMapLike$DefaultValuesIterable."<init>":(Lscala/collection/parallel/ParMapLike;)V
  #301 = Utf8               filterKeys$
  #302 = Utf8               (Lscala/collection/parallel/ParMapLike;Lscala/Function1;)Lscala/collection/parallel/ParMap;
  #303 = Utf8               p
  #304 = Utf8               filterKeys
  #305 = Utf8               (Lscala/Function1;)Lscala/collection/parallel/ParMap;
  #306 = NameAndType        #304:#305     // filterKeys:(Lscala/Function1;)Lscala/collection/parallel/ParMap;
  #307 = InterfaceMethodref #2.#306       // scala/collection/parallel/ParMapLike.filterKeys:(Lscala/Function1;)Lscala/collection/parallel/ParMap;
  #308 = Utf8               Lscala/Function1;
  #309 = Utf8               (Lscala/Function1<TK;Ljava/lang/Object;>;)Lscala/collection/parallel/ParMap<TK;TV;>;
  #310 = Utf8               (Lscala/collection/parallel/ParMapLike;Lscala/Function1;)V
  #311 = NameAndType        #151:#310     // "<init>":(Lscala/collection/parallel/ParMapLike;Lscala/Function1;)V
  #312 = Methodref          #51.#311      // scala/collection/parallel/ParMapLike$$anon$3."<init>":(Lscala/collection/parallel/ParMapLike;Lscala/Function1;)V
  #313 = Utf8               mapValues$
  #314 = Utf8               f
  #315 = Utf8               mapValues
  #316 = NameAndType        #315:#305     // mapValues:(Lscala/Function1;)Lscala/collection/parallel/ParMap;
  #317 = InterfaceMethodref #2.#316       // scala/collection/parallel/ParMapLike.mapValues:(Lscala/Function1;)Lscala/collection/parallel/ParMap;
  #318 = Utf8               <S:Ljava/lang/Object;>(Lscala/Function1<TV;TS;>;)Lscala/collection/parallel/ParMap<TK;TS;>;
  #319 = Methodref          #53.#311      // scala/collection/parallel/ParMapLike$$anon$4."<init>":(Lscala/collection/parallel/ParMapLike;Lscala/Function1;)V
  #320 = Utf8               map$
  #321 = Utf8               map
  #322 = NameAndType        #321:#305     // map:(Lscala/Function1;)Lscala/collection/parallel/ParMap;
  #323 = InterfaceMethodref #2.#322       // scala/collection/parallel/ParMapLike.map:(Lscala/Function1;)Lscala/collection/parallel/ParMap;
  #324 = Utf8               <K2:Ljava/lang/Object;V2:Ljava/lang/Object;>(Lscala/Function1<Lscala/Tuple2<TK;TV;>;Lscala/Tuple2<TK2;TV2;>;>;)TCC;
  #325 = Utf8               tasksupport
  #326 = Utf8               ()Lscala/collection/parallel/TaskSupport;
  #327 = NameAndType        #325:#326     // tasksupport:()Lscala/collection/parallel/TaskSupport;
  #328 = InterfaceMethodref #2.#327       // scala/collection/parallel/ParMapLike.tasksupport:()Lscala/collection/parallel/TaskSupport;
  #329 = MethodType         #203          //  ()Ljava/lang/Object;
  #330 = Utf8               $anonfun$map$1
  #331 = Utf8               (Lscala/collection/parallel/ParMapLike;)Lscala/collection/parallel/Combiner;
  #332 = NameAndType        #330:#331     // $anonfun$map$1:(Lscala/collection/parallel/ParMapLike;)Lscala/collection/parallel/Combiner;
  #333 = InterfaceMethodref #2.#332       // scala/collection/parallel/ParMapLike.$anonfun$map$1:(Lscala/collection/parallel/ParMapLike;)Lscala/collection/parallel/Combiner;
  #334 = MethodHandle       6:#333        // REF_invokeStatic scala/collection/parallel/ParMapLike.$anonfun$map$1:(Lscala/collection/parallel/ParMapLike;)Lscala/collection/parallel/Combiner;
  #335 = Utf8               ()Lscala/collection/parallel/Combiner;
  #336 = MethodType         #335          //  ()Lscala/collection/parallel/Combiner;
  #337 = Utf8               (Lscala/collection/parallel/ParMapLike;)Lscala/Function0;
  #338 = NameAndType        #107:#337     // apply:(Lscala/collection/parallel/ParMapLike;)Lscala/Function0;
  #339 = InvokeDynamic      #1:#338       // #1:apply:(Lscala/collection/parallel/ParMapLike;)Lscala/Function0;
  #340 = Utf8               combinerFactory
  #341 = Utf8               (Lscala/Function0;)Lscala/collection/parallel/CombinerFactory;
  #342 = NameAndType        #340:#341     // combinerFactory:(Lscala/Function0;)Lscala/collection/parallel/CombinerFactory;
  #343 = InterfaceMethodref #2.#342       // scala/collection/parallel/ParMapLike.combinerFactory:(Lscala/Function0;)Lscala/collection/parallel/CombinerFactory;
  #344 = Utf8               (Lscala/collection/parallel/ParIterableLike;Lscala/Function1;Lscala/collection/parallel/CombinerFactory;Lscala/collection/parallel/IterableSplitter;)V
  #345 = NameAndType        #151:#344     // "<init>":(Lscala/collection/parallel/ParIterableLike;Lscala/Function1;Lscala/collection/parallel/CombinerFactory;Lscala/collection/parallel/IterableSplitter;)V
  #346 = Methodref          #29.#345      // scala/collection/parallel/ParIterableLike$Map."<init>":(Lscala/collection/parallel/ParIterableLike;Lscala/Function1;Lscala/collection/parallel/CombinerFactory;Lscala/collection/parallel/IterableSplitter;)V
  #347 = Utf8               task2ops
  #348 = Utf8               (Lscala/collection/parallel/ParIterableLike$StrictSplitterCheckTask;)Lscala/collection/parallel/ParIterableLike$TaskOps;
  #349 = NameAndType        #347:#348     // task2ops:(Lscala/collection/parallel/ParIterableLike$StrictSplitterCheckTask;)Lscala/collection/parallel/ParIterableLike$TaskOps;
  #350 = InterfaceMethodref #2.#349       // scala/collection/parallel/ParMapLike.task2ops:(Lscala/collection/parallel/ParIterableLike$StrictSplitterCheckTask;)Lscala/collection/parallel/ParIterableLike$TaskOps;
  #351 = Utf8               $anonfun$map$2
  #352 = Utf8               (Lscala/collection/parallel/Combiner;)Lscala/collection/parallel/ParMap;
  #353 = NameAndType        #351:#352     // $anonfun$map$2:(Lscala/collection/parallel/Combiner;)Lscala/collection/parallel/ParMap;
  #354 = InterfaceMethodref #2.#353       // scala/collection/parallel/ParMapLike.$anonfun$map$2:(Lscala/collection/parallel/Combiner;)Lscala/collection/parallel/ParMap;
  #355 = MethodHandle       6:#354        // REF_invokeStatic scala/collection/parallel/ParMapLike.$anonfun$map$2:(Lscala/collection/parallel/Combiner;)Lscala/collection/parallel/ParMap;
  #356 = MethodType         #352          //  (Lscala/collection/parallel/Combiner;)Lscala/collection/parallel/ParMap;
  #357 = Utf8               ()Lscala/Function1;
  #358 = NameAndType        #107:#357     // apply:()Lscala/Function1;
  #359 = InvokeDynamic      #2:#358       // #2:apply:()Lscala/Function1;
  #360 = Utf8               mapResult
  #361 = Utf8               (Lscala/Function1;)Lscala/collection/parallel/ParIterableLike$ResultMapping;
  #362 = NameAndType        #360:#361     // mapResult:(Lscala/Function1;)Lscala/collection/parallel/ParIterableLike$ResultMapping;
  #363 = InterfaceMethodref #44.#362      // scala/collection/parallel/ParIterableLike$TaskOps.mapResult:(Lscala/Function1;)Lscala/collection/parallel/ParIterableLike$ResultMapping;
  #364 = Utf8               scala/collection/parallel/TaskSupport
  #365 = Class              #364          // scala/collection/parallel/TaskSupport
  #366 = Utf8               executeAndWaitResult
  #367 = Utf8               (Lscala/collection/parallel/Task;)Ljava/lang/Object;
  #368 = NameAndType        #366:#367     // executeAndWaitResult:(Lscala/collection/parallel/Task;)Ljava/lang/Object;
  #369 = InterfaceMethodref #365.#368     // scala/collection/parallel/TaskSupport.executeAndWaitResult:(Lscala/collection/parallel/Task;)Ljava/lang/Object;
  #370 = Utf8               collect$
  #371 = Utf8               (Lscala/collection/parallel/ParMapLike;Lscala/PartialFunction;)Lscala/collection/parallel/ParMap;
  #372 = Utf8               pf
  #373 = Utf8               collect
  #374 = Utf8               (Lscala/PartialFunction;)Lscala/collection/parallel/ParMap;
  #375 = NameAndType        #373:#374     // collect:(Lscala/PartialFunction;)Lscala/collection/parallel/ParMap;
  #376 = InterfaceMethodref #2.#375       // scala/collection/parallel/ParMapLike.collect:(Lscala/PartialFunction;)Lscala/collection/parallel/ParMap;
  #377 = Utf8               Lscala/PartialFunction;
  #378 = Utf8               <K2:Ljava/lang/Object;V2:Ljava/lang/Object;>(Lscala/PartialFunction<Lscala/Tuple2<TK;TV;>;Lscala/Tuple2<TK2;TV2;>;>;)TCC;
  #379 = Utf8               $anonfun$collect$1
  #380 = NameAndType        #379:#331     // $anonfun$collect$1:(Lscala/collection/parallel/ParMapLike;)Lscala/collection/parallel/Combiner;
  #381 = InterfaceMethodref #2.#380       // scala/collection/parallel/ParMapLike.$anonfun$collect$1:(Lscala/collection/parallel/ParMapLike;)Lscala/collection/parallel/Combiner;
  #382 = MethodHandle       6:#381        // REF_invokeStatic scala/collection/parallel/ParMapLike.$anonfun$collect$1:(Lscala/collection/parallel/ParMapLike;)Lscala/collection/parallel/Combiner;
  #383 = InvokeDynamic      #3:#338       // #3:apply:(Lscala/collection/parallel/ParMapLike;)Lscala/Function0;
  #384 = Utf8               (Lscala/collection/parallel/ParIterableLike;Lscala/PartialFunction;Lscala/collection/parallel/CombinerFactory;Lscala/collection/parallel/IterableSplitter;)V
  #385 = NameAndType        #151:#384     // "<init>":(Lscala/collection/parallel/ParIterableLike;Lscala/PartialFunction;Lscala/collection/parallel/CombinerFactory;Lscala/collection/parallel/IterableSplitter;)V
  #386 = Methodref          #20.#385      // scala/collection/parallel/ParIterableLike$Collect."<init>":(Lscala/collection/parallel/ParIterableLike;Lscala/PartialFunction;Lscala/collection/parallel/CombinerFactory;Lscala/collection/parallel/IterableSplitter;)V
  #387 = Utf8               $anonfun$collect$2
  #388 = NameAndType        #387:#352     // $anonfun$collect$2:(Lscala/collection/parallel/Combiner;)Lscala/collection/parallel/ParMap;
  #389 = InterfaceMethodref #2.#388       // scala/collection/parallel/ParMapLike.$anonfun$collect$2:(Lscala/collection/parallel/Combiner;)Lscala/collection/parallel/ParMap;
  #390 = MethodHandle       6:#389        // REF_invokeStatic scala/collection/parallel/ParMapLike.$anonfun$collect$2:(Lscala/collection/parallel/Combiner;)Lscala/collection/parallel/ParMap;
  #391 = InvokeDynamic      #4:#358       // #4:apply:()Lscala/Function1;
  #392 = Utf8               flatMap$
  #393 = Utf8               flatMap
  #394 = NameAndType        #393:#305     // flatMap:(Lscala/Function1;)Lscala/collection/parallel/ParMap;
  #395 = InterfaceMethodref #2.#394       // scala/collection/parallel/ParMapLike.flatMap:(Lscala/Function1;)Lscala/collection/parallel/ParMap;
  #396 = Utf8               <K2:Ljava/lang/Object;V2:Ljava/lang/Object;>(Lscala/Function1<Lscala/Tuple2<TK;TV;>;Lscala/collection/IterableOnce<Lscala/Tuple2<TK2;TV2;>;>;>;)TCC;
  #397 = Utf8               $anonfun$flatMap$1
  #398 = NameAndType        #397:#331     // $anonfun$flatMap$1:(Lscala/collection/parallel/ParMapLike;)Lscala/collection/parallel/Combiner;
  #399 = InterfaceMethodref #2.#398       // scala/collection/parallel/ParMapLike.$anonfun$flatMap$1:(Lscala/collection/parallel/ParMapLike;)Lscala/collection/parallel/Combiner;
  #400 = MethodHandle       6:#399        // REF_invokeStatic scala/collection/parallel/ParMapLike.$anonfun$flatMap$1:(Lscala/collection/parallel/ParMapLike;)Lscala/collection/parallel/Combiner;
  #401 = InvokeDynamic      #5:#338       // #5:apply:(Lscala/collection/parallel/ParMapLike;)Lscala/Function0;
  #402 = Methodref          #26.#345      // scala/collection/parallel/ParIterableLike$FlatMap."<init>":(Lscala/collection/parallel/ParIterableLike;Lscala/Function1;Lscala/collection/parallel/CombinerFactory;Lscala/collection/parallel/IterableSplitter;)V
  #403 = Utf8               $anonfun$flatMap$2
  #404 = NameAndType        #403:#352     // $anonfun$flatMap$2:(Lscala/collection/parallel/Combiner;)Lscala/collection/parallel/ParMap;
  #405 = InterfaceMethodref #2.#404       // scala/collection/parallel/ParMapLike.$anonfun$flatMap$2:(Lscala/collection/parallel/Combiner;)Lscala/collection/parallel/ParMap;
  #406 = MethodHandle       6:#405        // REF_invokeStatic scala/collection/parallel/ParMapLike.$anonfun$flatMap$2:(Lscala/collection/parallel/Combiner;)Lscala/collection/parallel/ParMap;
  #407 = InvokeDynamic      #6:#358       // #6:apply:()Lscala/Function1;
  #408 = Utf8               concat$
  #409 = Utf8               (Lscala/collection/parallel/ParMapLike;Lscala/collection/IterableOnce;)Lscala/collection/parallel/ParMap;
  #410 = Utf8               concat
  #411 = Utf8               (Lscala/collection/IterableOnce;)Lscala/collection/parallel/ParMap;
  #412 = NameAndType        #410:#411     // concat:(Lscala/collection/IterableOnce;)Lscala/collection/parallel/ParMap;
  #413 = InterfaceMethodref #2.#412       // scala/collection/parallel/ParMapLike.concat:(Lscala/collection/IterableOnce;)Lscala/collection/parallel/ParMap;
  #414 = Utf8               Lscala/collection/IterableOnce;
  #415 = Utf8               <V2:Ljava/lang/Object;>(Lscala/collection/IterableOnce<Lscala/Tuple2<TK;TV2;>;>;)TCC;
  #416 = Utf8               scala/collection/parallel/ParIterable
  #417 = Class              #416          // scala/collection/parallel/ParIterable
  #418 = Utf8               $anonfun$concat$1
  #419 = NameAndType        #418:#331     // $anonfun$concat$1:(Lscala/collection/parallel/ParMapLike;)Lscala/collection/parallel/Combiner;
  #420 = InterfaceMethodref #2.#419       // scala/collection/parallel/ParMapLike.$anonfun$concat$1:(Lscala/collection/parallel/ParMapLike;)Lscala/collection/parallel/Combiner;
  #421 = MethodHandle       6:#420        // REF_invokeStatic scala/collection/parallel/ParMapLike.$anonfun$concat$1:(Lscala/collection/parallel/ParMapLike;)Lscala/collection/parallel/Combiner;
  #422 = InvokeDynamic      #7:#338       // #7:apply:(Lscala/collection/parallel/ParMapLike;)Lscala/Function0;
  #423 = Utf8               (Lscala/collection/parallel/ParIterableLike;Lscala/collection/parallel/CombinerFactory;Lscala/collection/parallel/IterableSplitter;)V
  #424 = NameAndType        #151:#423     // "<init>":(Lscala/collection/parallel/ParIterableLike;Lscala/collection/parallel/CombinerFactory;Lscala/collection/parallel/IterableSplitter;)V
  #425 = Methodref          #23.#424      // scala/collection/parallel/ParIterableLike$Copy."<init>":(Lscala/collection/parallel/ParIterableLike;Lscala/collection/parallel/CombinerFactory;Lscala/collection/parallel/IterableSplitter;)V
  #426 = Utf8               $anonfun$concat$2
  #427 = Utf8               (Lscala/collection/parallel/ParMapLike;Lscala/collection/parallel/ParIterable;Lscala/collection/parallel/CombinerFactory;)Lscala/collection/parallel/Combiner;
  #428 = NameAndType        #426:#427     // $anonfun$concat$2:(Lscala/collection/parallel/ParMapLike;Lscala/collection/parallel/ParIterable;Lscala/collection/parallel/CombinerFactory;)Lscala/collection/parallel/Combiner;
  #429 = InterfaceMethodref #2.#428       // scala/collection/parallel/ParMapLike.$anonfun$concat$2:(Lscala/collection/parallel/ParMapLike;Lscala/collection/parallel/ParIterable;Lscala/collection/parallel/CombinerFactory;)Lscala/collection/parallel/Combiner;
  #430 = MethodHandle       6:#429        // REF_invokeStatic scala/collection/parallel/ParMapLike.$anonfun$concat$2:(Lscala/collection/parallel/ParMapLike;Lscala/collection/parallel/ParIterable;Lscala/collection/parallel/CombinerFactory;)Lscala/collection/parallel/Combiner;
  #431 = Utf8               (Lscala/collection/parallel/ParMapLike;Lscala/collection/parallel/ParIterable;Lscala/collection/parallel/CombinerFactory;)Lscala/Function0;
  #432 = NameAndType        #107:#431     // apply:(Lscala/collection/parallel/ParMapLike;Lscala/collection/parallel/ParIterable;Lscala/collection/parallel/CombinerFactory;)Lscala/Function0;
  #433 = InvokeDynamic      #8:#432       // #8:apply:(Lscala/collection/parallel/ParMapLike;Lscala/collection/parallel/ParIterable;Lscala/collection/parallel/CombinerFactory;)Lscala/Function0;
  #434 = Utf8               wrap
  #435 = Utf8               (Lscala/Function0;)Lscala/collection/parallel/ParIterableLike$NonDivisible;
  #436 = NameAndType        #434:#435     // wrap:(Lscala/Function0;)Lscala/collection/parallel/ParIterableLike$NonDivisible;
  #437 = InterfaceMethodref #2.#436       // scala/collection/parallel/ParMapLike.wrap:(Lscala/Function0;)Lscala/collection/parallel/ParIterableLike$NonDivisible;
  #438 = Utf8               (Ljava/lang/Object;Ljava/lang/Object;)Ljava/lang/Object;
  #439 = MethodType         #438          //  (Ljava/lang/Object;Ljava/lang/Object;)Ljava/lang/Object;
  #440 = Utf8               $anonfun$concat$3
  #441 = Utf8               (Lscala/collection/parallel/Combiner;Lscala/collection/parallel/Combiner;)Lscala/collection/parallel/Combiner;
  #442 = NameAndType        #440:#441     // $anonfun$concat$3:(Lscala/collection/parallel/Combiner;Lscala/collection/parallel/Combiner;)Lscala/collection/parallel/Combiner;
  #443 = InterfaceMethodref #2.#442       // scala/collection/parallel/ParMapLike.$anonfun$concat$3:(Lscala/collection/parallel/Combiner;Lscala/collection/parallel/Combiner;)Lscala/collection/parallel/Combiner;
  #444 = MethodHandle       6:#443        // REF_invokeStatic scala/collection/parallel/ParMapLike.$anonfun$concat$3:(Lscala/collection/parallel/Combiner;Lscala/collection/parallel/Combiner;)Lscala/collection/parallel/Combiner;
  #445 = MethodType         #441          //  (Lscala/collection/parallel/Combiner;Lscala/collection/parallel/Combiner;)Lscala/collection/parallel/Combiner;
  #446 = Utf8               ()Lscala/Function2;
  #447 = NameAndType        #107:#446     // apply:()Lscala/Function2;
  #448 = InvokeDynamic      #9:#447       // #9:apply:()Lscala/Function2;
  #449 = Utf8               parallel
  #450 = Utf8               (Lscala/collection/parallel/ParIterableLike$StrictSplitterCheckTask;Lscala/Function2;)Lscala/collection/parallel/ParIterableLike$ParComposite;
  #451 = NameAndType        #449:#450     // parallel:(Lscala/collection/parallel/ParIterableLike$StrictSplitterCheckTask;Lscala/Function2;)Lscala/collection/parallel/ParIterableLike$ParComposite;
  #452 = InterfaceMethodref #44.#451      // scala/collection/parallel/ParIterableLike$TaskOps.parallel:(Lscala/collection/parallel/ParIterableLike$StrictSplitterCheckTask;Lscala/Function2;)Lscala/collection/parallel/ParIterableLike$ParComposite;
  #453 = Utf8               $anonfun$concat$4
  #454 = NameAndType        #453:#352     // $anonfun$concat$4:(Lscala/collection/parallel/Combiner;)Lscala/collection/parallel/ParMap;
  #455 = InterfaceMethodref #2.#454       // scala/collection/parallel/ParMapLike.$anonfun$concat$4:(Lscala/collection/parallel/Combiner;)Lscala/collection/parallel/ParMap;
  #456 = MethodHandle       6:#455        // REF_invokeStatic scala/collection/parallel/ParMapLike.$anonfun$concat$4:(Lscala/collection/parallel/Combiner;)Lscala/collection/parallel/ParMap;
  #457 = InvokeDynamic      #10:#358      // #10:apply:()Lscala/Function1;
  #458 = Utf8               $anonfun$concat$5
  #459 = NameAndType        #458:#331     // $anonfun$concat$5:(Lscala/collection/parallel/ParMapLike;)Lscala/collection/parallel/Combiner;
  #460 = InterfaceMethodref #2.#459       // scala/collection/parallel/ParMapLike.$anonfun$concat$5:(Lscala/collection/parallel/ParMapLike;)Lscala/collection/parallel/Combiner;
  #461 = MethodHandle       6:#460        // REF_invokeStatic scala/collection/parallel/ParMapLike.$anonfun$concat$5:(Lscala/collection/parallel/ParMapLike;)Lscala/collection/parallel/Combiner;
  #462 = InvokeDynamic      #11:#338      // #11:apply:(Lscala/collection/parallel/ParMapLike;)Lscala/Function0;
  #463 = Utf8               $anonfun$concat$6
  #464 = Utf8               (Lscala/collection/parallel/ParMapLike;Lscala/collection/IterableOnce;)Lscala/collection/parallel/Combiner;
  #465 = NameAndType        #463:#464     // $anonfun$concat$6:(Lscala/collection/parallel/ParMapLike;Lscala/collection/IterableOnce;)Lscala/collection/parallel/Combiner;
  #466 = InterfaceMethodref #2.#465       // scala/collection/parallel/ParMapLike.$anonfun$concat$6:(Lscala/collection/parallel/ParMapLike;Lscala/collection/IterableOnce;)Lscala/collection/parallel/Combiner;
  #467 = MethodHandle       6:#466        // REF_invokeStatic scala/collection/parallel/ParMapLike.$anonfun$concat$6:(Lscala/collection/parallel/ParMapLike;Lscala/collection/IterableOnce;)Lscala/collection/parallel/Combiner;
  #468 = Utf8               (Lscala/collection/parallel/ParMapLike;Lscala/collection/IterableOnce;)Lscala/Function0;
  #469 = NameAndType        #107:#468     // apply:(Lscala/collection/parallel/ParMapLike;Lscala/collection/IterableOnce;)Lscala/Function0;
  #470 = InvokeDynamic      #12:#469      // #12:apply:(Lscala/collection/parallel/ParMapLike;Lscala/collection/IterableOnce;)Lscala/Function0;
  #471 = Utf8               $anonfun$concat$7
  #472 = NameAndType        #471:#441     // $anonfun$concat$7:(Lscala/collection/parallel/Combiner;Lscala/collection/parallel/Combiner;)Lscala/collection/parallel/Combiner;
  #473 = InterfaceMethodref #2.#472       // scala/collection/parallel/ParMapLike.$anonfun$concat$7:(Lscala/collection/parallel/Combiner;Lscala/collection/parallel/Combiner;)Lscala/collection/parallel/Combiner;
  #474 = MethodHandle       6:#473        // REF_invokeStatic scala/collection/parallel/ParMapLike.$anonfun$concat$7:(Lscala/collection/parallel/Combiner;Lscala/collection/parallel/Combiner;)Lscala/collection/parallel/Combiner;
  #475 = InvokeDynamic      #13:#447      // #13:apply:()Lscala/Function2;
  #476 = Utf8               $anonfun$concat$8
  #477 = NameAndType        #476:#352     // $anonfun$concat$8:(Lscala/collection/parallel/Combiner;)Lscala/collection/parallel/ParMap;
  #478 = InterfaceMethodref #2.#477       // scala/collection/parallel/ParMapLike.$anonfun$concat$8:(Lscala/collection/parallel/Combiner;)Lscala/collection/parallel/ParMap;
  #479 = MethodHandle       6:#478        // REF_invokeStatic scala/collection/parallel/ParMapLike.$anonfun$concat$8:(Lscala/collection/parallel/Combiner;)Lscala/collection/parallel/ParMap;
  #480 = InvokeDynamic      #14:#358      // #14:apply:()Lscala/Function1;
  #481 = Utf8               cfactory
  #482 = Utf8               Lscala/collection/parallel/CombinerFactory;
  #483 = Utf8               copythis
  #484 = Utf8               Lscala/collection/parallel/ParIterableLike$Copy;
  #485 = Utf8               copythat
  #486 = Utf8               Lscala/collection/parallel/ParIterableLike$NonDivisible;
  #487 = Utf8               task
  #488 = Utf8               Lscala/collection/parallel/ParIterableLike$ResultMapping;
  #489 = Utf8               scala/collection/IterableOnce
  #490 = Class              #489          // scala/collection/IterableOnce
  #491 = Utf8               $plus$plus$
  #492 = Utf8               xs
  #493 = Utf8               $plus$plus
  #494 = NameAndType        #493:#411     // $plus$plus:(Lscala/collection/IterableOnce;)Lscala/collection/parallel/ParMap;
  #495 = InterfaceMethodref #2.#494       // scala/collection/parallel/ParMapLike.$plus$plus:(Lscala/collection/IterableOnce;)Lscala/collection/parallel/ParMap;
  #496 = Utf8               $anonfun$equals$1
  #497 = Utf8               (Lscala/collection/parallel/ParMap;Lscala/Tuple2;)Z
  #498 = Utf8               x2$1
  #499 = Utf8               x0$1
  #500 = Utf8               _1
  #501 = NameAndType        #500:#203     // _1:()Ljava/lang/Object;
  #502 = Methodref          #150.#501     // scala/Tuple2._1:()Ljava/lang/Object;
  #503 = Utf8               _2
  #504 = NameAndType        #503:#203     // _2:()Ljava/lang/Object;
  #505 = Methodref          #150.#504     // scala/Tuple2._2:()Ljava/lang/Object;
  #506 = InterfaceMethodref #82.#199      // scala/collection/parallel/ParMap.get:(Ljava/lang/Object;)Lscala/Option;
  #507 = Utf8               scala/runtime/BoxesRunTime
  #508 = Class              #507          // scala/runtime/BoxesRunTime
  #509 = Utf8               (Ljava/lang/Object;Ljava/lang/Object;)Z
  #510 = NameAndType        #76:#509      // equals:(Ljava/lang/Object;Ljava/lang/Object;)Z
  #511 = Methodref          #508.#510     // scala/runtime/BoxesRunTime.equals:(Ljava/lang/Object;Ljava/lang/Object;)Z
  #512 = Utf8               k
  #513 = Utf8               Lscala/collection/parallel/ParMap;
  #514 = Utf8               Lscala/Tuple2;
  #515 = NameAndType        #160:#161     // mapCompanion:()Lscala/collection/generic/GenericParMapCompanion;
  #516 = InterfaceMethodref #2.#515       // scala/collection/parallel/ParMapLike.mapCompanion:()Lscala/collection/generic/GenericParMapCompanion;
  #517 = Utf8               scala/collection/generic/GenericParMapCompanion
  #518 = Class              #517          // scala/collection/generic/GenericParMapCompanion
  #519 = Utf8               newCombiner
  #520 = NameAndType        #519:#335     // newCombiner:()Lscala/collection/parallel/Combiner;
  #521 = InterfaceMethodref #518.#520     // scala/collection/generic/GenericParMapCompanion.newCombiner:()Lscala/collection/parallel/Combiner;
  #522 = Utf8               x$8
  #523 = Utf8               scala/collection/parallel/Combiner
  #524 = Class              #523          // scala/collection/parallel/Combiner
  #525 = Utf8               resultWithTaskSupport
  #526 = NameAndType        #525:#203     // resultWithTaskSupport:()Ljava/lang/Object;
  #527 = InterfaceMethodref #524.#526     // scala/collection/parallel/Combiner.resultWithTaskSupport:()Ljava/lang/Object;
  #528 = Utf8               Lscala/collection/parallel/Combiner;
  #529 = Utf8               x$9
  #530 = Utf8               x$10
  #531 = Utf8               x2$2
  #532 = Utf8               cfactory$1
  #533 = InterfaceMethodref #417.#265     // scala/collection/parallel/ParIterable.splitter:()Lscala/collection/parallel/IterableSplitter;
  #534 = Utf8               othtask
  #535 = Utf8               Lscala/collection/parallel/ParIterable;
  #536 = Utf8               x$11
  #537 = Utf8               x$12
  #538 = Utf8               combine
  #539 = Utf8               (Lscala/collection/parallel/Combiner;)Lscala/collection/parallel/Combiner;
  #540 = NameAndType        #538:#539     // combine:(Lscala/collection/parallel/Combiner;)Lscala/collection/parallel/Combiner;
  #541 = InterfaceMethodref #524.#540     // scala/collection/parallel/Combiner.combine:(Lscala/collection/parallel/Combiner;)Lscala/collection/parallel/Combiner;
  #542 = Utf8               x$13
  #543 = Utf8               that$1
  #544 = Utf8               $plus$plus$eq
  #545 = Utf8               (Lscala/collection/IterableOnce;)Lscala/collection/mutable/Growable;
  #546 = NameAndType        #544:#545     // $plus$plus$eq:(Lscala/collection/IterableOnce;)Lscala/collection/mutable/Growable;
  #547 = InterfaceMethodref #524.#546     // scala/collection/parallel/Combiner.$plus$plus$eq:(Lscala/collection/IterableOnce;)Lscala/collection/mutable/Growable;
  #548 = Utf8               cb
  #549 = Utf8               x$14
  #550 = Utf8               x$15
  #551 = Utf8               x$16
  #552 = Utf8               $init$
  #553 = NameAndType        #496:#497     // $anonfun$equals$1:(Lscala/collection/parallel/ParMap;Lscala/Tuple2;)Z
  #554 = InterfaceMethodref #2.#553       // scala/collection/parallel/ParMapLike.$anonfun$equals$1:(Lscala/collection/parallel/ParMap;Lscala/Tuple2;)Z
  #555 = Utf8               boxToBoolean
  #556 = Utf8               (Z)Ljava/lang/Boolean;
  #557 = NameAndType        #555:#556     // boxToBoolean:(Z)Ljava/lang/Boolean;
  #558 = Methodref          #508.#557     // scala/runtime/BoxesRunTime.boxToBoolean:(Z)Ljava/lang/Boolean;
  #559 = Utf8               $deserializeLambda$
  #560 = Utf8               (Ljava/lang/invoke/SerializedLambda;)Ljava/lang/Object;
  #561 = Utf8               scala/runtime/LambdaDeserialize
  #562 = Class              #561          // scala/runtime/LambdaDeserialize
  #563 = Utf8               bootstrap
  #564 = Utf8               (Ljava/lang/invoke/MethodHandles$Lookup;Ljava/lang/String;Ljava/lang/invoke/MethodType;[Ljava/lang/invoke/MethodHandle;)Ljava/lang/invoke/CallSite;
  #565 = NameAndType        #563:#564     // bootstrap:(Ljava/lang/invoke/MethodHandles$Lookup;Ljava/lang/String;Ljava/lang/invoke/MethodType;[Ljava/lang/invoke/MethodHandle;)Ljava/lang/invoke/CallSite;
  #566 = Methodref          #562.#565     // scala/runtime/LambdaDeserialize.bootstrap:(Ljava/lang/invoke/MethodHandles$Lookup;Ljava/lang/String;Ljava/lang/invoke/MethodType;[Ljava/lang/invoke/MethodHandle;)Ljava/lang/invoke/CallSite;
  #567 = MethodHandle       6:#566        // REF_invokeStatic scala/runtime/LambdaDeserialize.bootstrap:(Ljava/lang/invoke/MethodHandles$Lookup;Ljava/lang/String;Ljava/lang/invoke/MethodType;[Ljava/lang/invoke/MethodHandle;)Ljava/lang/invoke/CallSite;
  #568 = Utf8               lambdaDeserialize
  #569 = NameAndType        #568:#560     // lambdaDeserialize:(Ljava/lang/invoke/SerializedLambda;)Ljava/lang/Object;
  #570 = InvokeDynamic      #15:#569      // #15:lambdaDeserialize:(Ljava/lang/invoke/SerializedLambda;)Ljava/lang/Object;
  #571 = Utf8               Signature
  #572 = Utf8               MethodParameters
  #573 = Utf8               Code
  #574 = Utf8               LineNumberTable
  #575 = Utf8               LocalVariableTable
  #576 = Utf8               StackMapTable
  #577 = Utf8               InnerClasses
  #578 = Utf8               SourceFile
  #579 = Utf8               RuntimeVisibleAnnotations
  #580 = Utf8               BootstrapMethods
  #581 = Utf8               ScalaInlineInfo
  #582 = Utf8               ScalaSig
{
  public abstract scala.Option<V> get(K);
    descriptor: (Ljava/lang/Object;)Lscala/Option;
    flags: (0x0401) ACC_PUBLIC, ACC_ABSTRACT
    Signature: #62                          // (TK;)Lscala/Option<TV;>;
    MethodParameters:
      Name                           Flags
      key                            final

  public static boolean canEqual$(scala.collection.parallel.ParMapLike, java.lang.Object);
    descriptor: (Lscala/collection/parallel/ParMapLike;Ljava/lang/Object;)Z
    flags: (0x1009) ACC_PUBLIC, ACC_STATIC, ACC_SYNTHETIC
    Code:
      stack=2, locals=2, args_size=2
         0: aload_0
         1: aload_1
         2: invokespecial #71                 // InterfaceMethod canEqual:(Ljava/lang/Object;)Z
         5: ireturn
      LineNumberTable:
        line 45: 0
      LocalVariableTable:
        Start  Length  Slot  Name   Signature
            0       6     0 $this   Lscala/collection/parallel/ParMapLike;
            0       6     1  that   Ljava/lang/Object;
    MethodParameters:
      Name                           Flags
      $this                          final synthetic
      that                           final

  public default boolean canEqual(java.lang.Object);
    descriptor: (Ljava/lang/Object;)Z
    flags: (0x0001) ACC_PUBLIC
    Code:
      stack=1, locals=2, args_size=2
         0: iconst_1
         1: ireturn
      LineNumberTable:
        line 45: 0
      LocalVariableTable:
        Start  Length  Slot  Name   Signature
            0       2     0  this   Lscala/collection/parallel/ParMapLike;
            0       2     1  that   Ljava/lang/Object;
    MethodParameters:
      Name                           Flags
      that                           final

  public static boolean equals$(scala.collection.parallel.ParMapLike, java.lang.Object);
    descriptor: (Lscala/collection/parallel/ParMapLike;Ljava/lang/Object;)Z
    flags: (0x1009) ACC_PUBLIC, ACC_STATIC, ACC_SYNTHETIC
    Code:
      stack=2, locals=2, args_size=2
         0: aload_0
         1: aload_1
         2: invokespecial #78                 // InterfaceMethod equals:(Ljava/lang/Object;)Z
         5: ireturn
      LineNumberTable:
        line 55: 0
      LocalVariableTable:
        Start  Length  Slot  Name   Signature
            0       6     0 $this   Lscala/collection/parallel/ParMapLike;
            0       6     1  that   Ljava/lang/Object;
    MethodParameters:
      Name                           Flags
      $this                          final synthetic
      that                           final

  public default boolean equals(java.lang.Object);
    descriptor: (Ljava/lang/Object;)Z
    flags: (0x0001) ACC_PUBLIC
    Code:
      stack=2, locals=6, args_size=2
         0: aload_1
         1: astore_3
         2: aload_3
         3: instanceof    #82                 // class scala/collection/parallel/ParMap
         6: ifeq          82
         9: aload_3
        10: checkcast     #82                 // class scala/collection/parallel/ParMap
        13: astore        4
        15: aload_0
        16: aload         4
        18: if_acmpeq     73
        21: aload         4
        23: aload_0
        24: invokeinterface #83,  2           // InterfaceMethod scala/collection/parallel/ParMap.canEqual:(Ljava/lang/Object;)Z
        29: ifeq          77
        32: aload_0
        33: invokeinterface #87,  1           // InterfaceMethod size:()I
        38: aload         4
        40: invokeinterface #88,  1           // InterfaceMethod scala/collection/parallel/ParMap.size:()I
        45: if_icmpne     77
        48: aload_0
        49: aload         4
        51: invokedynamic #110,  0            // InvokeDynamic #0:apply:(Lscala/collection/parallel/ParMap;)Lscala/Function1;
        56: invokeinterface #114,  2          // InterfaceMethod forall:(Lscala/Function1;)Z
        61: goto          70
        64: astore        5
        66: iconst_0
        67: goto          70
        70: ifeq          77
        73: iconst_1
        74: goto          78
        77: iconst_0
        78: istore_2
        79: goto          90
        82: goto          85
        85: iconst_0
        86: istore_2
        87: goto          90
        90: iload_2
        91: ireturn
      Exception table:
         from    to  target type
            48    61    64   Class java/lang/ClassCastException
      StackMapTable: number_of_entries = 8
        frame_type = 255 /* full_frame */
          offset_delta = 64
          locals = [ class scala/collection/parallel/ParMapLike, class java/lang/Object, top, class java/lang/Object, class scala/collection/parallel/ParMap ]
          stack = [ class java/lang/ClassCastException ]
        frame_type = 69 /* same_locals_1_stack_item */
          stack = [ int ]
        frame_type = 2 /* same */
        frame_type = 3 /* same */
        frame_type = 64 /* same_locals_1_stack_item */
          stack = [ int ]
        frame_type = 250 /* chop */
          offset_delta = 3
        frame_type = 2 /* same */
        frame_type = 255 /* full_frame */
          offset_delta = 4
          locals = [ class scala/collection/parallel/ParMapLike, class java/lang/Object, int, class java/lang/Object ]
          stack = []
      LineNumberTable:
        line 55: 0
        line 56: 2
        line 57: 15
        line 58: 21
        line 59: 32
        line 61: 48
        line 69: 66
        line 56: 82
        line 72: 85
        line 55: 90
      LocalVariableTable:
        Start  Length  Slot  Name   Signature
           64       3     5    ex   Ljava/lang/ClassCastException;
            0      92     0  this   Lscala/collection/parallel/ParMapLike;
            0      92     1  that   Ljava/lang/Object;
    MethodParameters:
      Name                           Flags
      that                           final

  public static int hashCode$(scala.collection.parallel.ParMapLike);
    descriptor: (Lscala/collection/parallel/ParMapLike;)I
    flags: (0x1009) ACC_PUBLIC, ACC_STATIC, ACC_SYNTHETIC
    Code:
      stack=1, locals=1, args_size=1
         0: aload_0
         1: invokespecial #121                // InterfaceMethod hashCode:()I
         4: ireturn
      LineNumberTable:
        line 77: 0
      LocalVariableTable:
        Start  Length  Slot  Name   Signature
            0       5     0 $this   Lscala/collection/parallel/ParMapLike;
    MethodParameters:
      Name                           Flags
      $this                          final synthetic

  public default int hashCode();
    descriptor: ()I
    flags: (0x0001) ACC_PUBLIC
    Code:
      stack=3, locals=1, args_size=1
         0: getstatic     #127                // Field scala/util/hashing/MurmurHash3$.MODULE$:Lscala/util/hashing/MurmurHash3$;
         3: aload_0
         4: ldc           #129                // String ParMap
         6: invokevirtual #132                // Method java/lang/String.hashCode:()I
         9: invokevirtual #136                // Method scala/util/hashing/MurmurHash3$.unorderedHash:(Lscala/collection/IterableOnce;I)I
        12: ireturn
      LineNumberTable:
        line 77: 0
      LocalVariableTable:
        Start  Length  Slot  Name   Signature
            0      13     0  this   Lscala/collection/parallel/ParMapLike;

  public abstract <V1 extends java.lang.Object> CC $plus(scala.Tuple2<K, V1>);
    descriptor: (Lscala/Tuple2;)Lscala/collection/parallel/ParMap;
    flags: (0x0401) ACC_PUBLIC, ACC_ABSTRACT
    Signature: #139                         // <V1:Ljava/lang/Object;>(Lscala/Tuple2<TK;TV1;>;)TCC;
    MethodParameters:
      Name                           Flags
      kv                             final

  public static scala.collection.parallel.ParMap updated$(scala.collection.parallel.ParMapLike, java.lang.Object, java.lang.Object);
    descriptor: (Lscala/collection/parallel/ParMapLike;Ljava/lang/Object;Ljava/lang/Object;)Lscala/collection/parallel/ParMap;
    flags: (0x1009) ACC_PUBLIC, ACC_STATIC, ACC_SYNTHETIC
    Code:
      stack=3, locals=3, args_size=3
         0: aload_0
         1: aload_1
         2: aload_2
         3: invokespecial #147                // InterfaceMethod updated:(Ljava/lang/Object;Ljava/lang/Object;)Lscala/collection/parallel/ParMap;
         6: areturn
      LineNumberTable:
        line 80: 0
      LocalVariableTable:
        Start  Length  Slot  Name   Signature
            0       7     0 $this   Lscala/collection/parallel/ParMapLike;
            0       7     1   key   Ljava/lang/Object;
            0       7     2 value   Ljava/lang/Object;
    MethodParameters:
      Name                           Flags
      $this                          final synthetic
      key                            final
      value                          final

  public default <V1 extends java.lang.Object> CC updated(K, V1);
    descriptor: (Ljava/lang/Object;Ljava/lang/Object;)Lscala/collection/parallel/ParMap;
    flags: (0x0001) ACC_PUBLIC
    Code:
      stack=5, locals=3, args_size=3
         0: aload_0
         1: new           #150                // class scala/Tuple2
         4: dup
         5: aload_1
         6: aload_2
         7: invokespecial #154                // Method scala/Tuple2."<init>":(Ljava/lang/Object;Ljava/lang/Object;)V
        10: invokeinterface #156,  2          // InterfaceMethod $plus:(Lscala/Tuple2;)Lscala/collection/parallel/ParMap;
        15: areturn
      LineNumberTable:
        line 80: 0
      LocalVariableTable:
        Start  Length  Slot  Name   Signature
            0      16     0  this   Lscala/collection/parallel/ParMapLike;
            0      16     1   key   Ljava/lang/Object;
            0      16     2 value   Ljava/lang/Object;
    Signature: #148                         // <V1:Ljava/lang/Object;>(TK;TV1;)TCC;
    MethodParameters:
      Name                           Flags
      key                            final
      value                          final

  public abstract Repr $minus(K);
    descriptor: (Ljava/lang/Object;)Lscala/collection/parallel/ParMap;
    flags: (0x0401) ACC_PUBLIC, ACC_ABSTRACT
    Signature: #159                         // (TK;)TRepr;
    MethodParameters:
      Name                           Flags
      key                            final

  public abstract scala.collection.generic.GenericParMapCompanion<CC> mapCompanion();
    descriptor: ()Lscala/collection/generic/GenericParMapCompanion;
    flags: (0x0401) ACC_PUBLIC, ACC_ABSTRACT
    Signature: #162                         // ()Lscala/collection/generic/GenericParMapCompanion<TCC;>;

  public static java.lang.Object default$(scala.collection.parallel.ParMapLike, java.lang.Object);
    descriptor: (Lscala/collection/parallel/ParMapLike;Ljava/lang/Object;)Ljava/lang/Object;
    flags: (0x1009) ACC_PUBLIC, ACC_STATIC, ACC_SYNTHETIC
    Code:
      stack=2, locals=2, args_size=2
         0: aload_0
         1: aload_1
         2: invokespecial #167                // InterfaceMethod default:(Ljava/lang/Object;)Ljava/lang/Object;
         5: areturn
      LineNumberTable:
        line 86: 0
      LocalVariableTable:
        Start  Length  Slot  Name   Signature
            0       6     0 $this   Lscala/collection/parallel/ParMapLike;
            0       6     1   key   Ljava/lang/Object;
    MethodParameters:
      Name                           Flags
      $this                          final synthetic
      key                            final

  public default V default(K);
    descriptor: (Ljava/lang/Object;)Ljava/lang/Object;
    flags: (0x0001) ACC_PUBLIC
    Code:
      stack=5, locals=2, args_size=2
         0: new           #170                // class java/util/NoSuchElementException
         3: dup
         4: new           #172                // class java/lang/StringBuilder
         7: dup
         8: ldc           #173                // int 15
        10: invokespecial #176                // Method java/lang/StringBuilder."<init>":(I)V
        13: ldc           #178                // String key not found:
        15: invokevirtual #182                // Method java/lang/StringBuilder.append:(Ljava/lang/String;)Ljava/lang/StringBuilder;
        18: aload_1
        19: invokevirtual #185                // Method java/lang/StringBuilder.append:(Ljava/lang/Object;)Ljava/lang/StringBuilder;
        22: invokevirtual #189                // Method java/lang/StringBuilder.toString:()Ljava/lang/String;
        25: invokespecial #192                // Method java/util/NoSuchElementException."<init>":(Ljava/lang/String;)V
        28: athrow
      LineNumberTable:
        line 86: 0
      LocalVariableTable:
        Start  Length  Slot  Name   Signature
            0      29     0  this   Lscala/collection/parallel/ParMapLike;
            0      29     1   key   Ljava/lang/Object;
    Signature: #168                         // (TK;)TV;
    MethodParameters:
      Name                           Flags
      key                            final

  public abstract Repr empty();
    descriptor: ()Lscala/collection/parallel/ParMap;
    flags: (0x0401) ACC_PUBLIC, ACC_ABSTRACT
    Signature: #195                         // ()TRepr;

  public static java.lang.Object apply$(scala.collection.parallel.ParMapLike, java.lang.Object);
    descriptor: (Lscala/collection/parallel/ParMapLike;Ljava/lang/Object;)Ljava/lang/Object;
    flags: (0x1009) ACC_PUBLIC, ACC_STATIC, ACC_SYNTHETIC
    Code:
      stack=2, locals=2, args_size=2
         0: aload_0
         1: aload_1
         2: invokespecial #198                // InterfaceMethod apply:(Ljava/lang/Object;)Ljava/lang/Object;
         5: areturn
      LineNumberTable:
        line 90: 0
      LocalVariableTable:
        Start  Length  Slot  Name   Signature
            0       6     0 $this   Lscala/collection/parallel/ParMapLike;
            0       6     1   key   Ljava/lang/Object;
    MethodParameters:
      Name                           Flags
      $this                          final synthetic
      key                            final

  public default V apply(K);
    descriptor: (Ljava/lang/Object;)Ljava/lang/Object;
    flags: (0x0001) ACC_PUBLIC
    Code:
      stack=3, locals=6, args_size=2
         0: aload_0
         1: aload_1
         2: invokeinterface #200,  2          // InterfaceMethod get:(Ljava/lang/Object;)Lscala/Option;
         7: astore_3
         8: aload_3
         9: instanceof    #202                // class scala/Some
        12: ifeq          34
        15: aload_3
        16: checkcast     #202                // class scala/Some
        19: astore        4
        21: aload         4
        23: invokevirtual #205                // Method scala/Some.value:()Ljava/lang/Object;
        26: astore        5
        28: aload         5
        30: astore_2
        31: goto          70
        34: goto          37
        37: getstatic     #210                // Field scala/None$.MODULE$:Lscala/None$;
        40: aload_3
        41: invokevirtual #211                // Method java/lang/Object.equals:(Ljava/lang/Object;)Z
        44: ifeq          58
        47: aload_0
        48: aload_1
        49: invokeinterface #167,  2          // InterfaceMethod default:(Ljava/lang/Object;)Ljava/lang/Object;
        54: astore_2
        55: goto          70
        58: goto          61
        61: new           #213                // class scala/MatchError
        64: dup
        65: aload_3
        66: invokespecial #216                // Method scala/MatchError."<init>":(Ljava/lang/Object;)V
        69: athrow
        70: aload_2
        71: areturn
      StackMapTable: number_of_entries = 5
        frame_type = 253 /* append */
          offset_delta = 34
          locals = [ top, class scala/Option ]
        frame_type = 2 /* same */
        frame_type = 20 /* same */
        frame_type = 2 /* same */
        frame_type = 255 /* full_frame */
          offset_delta = 8
          locals = [ class scala/collection/parallel/ParMapLike, class java/lang/Object, class java/lang/Object, class scala/Option ]
          stack = []
      LineNumberTable:
        line 90: 0
        line 91: 8
        line 92: 37
        line 90: 61
      LocalVariableTable:
        Start  Length  Slot  Name   Signature
           28       6     5     v   Ljava/lang/Object;
            0      72     0  this   Lscala/collection/parallel/ParMapLike;
            0      72     1   key   Ljava/lang/Object;
    Signature: #168                         // (TK;)TV;
    MethodParameters:
      Name                           Flags
      key                            final

  public static java.lang.Object getOrElse$(scala.collection.parallel.ParMapLike, java.lang.Object, scala.Function0);
    descriptor: (Lscala/collection/parallel/ParMapLike;Ljava/lang/Object;Lscala/Function0;)Ljava/lang/Object;
    flags: (0x1009) ACC_PUBLIC, ACC_STATIC, ACC_SYNTHETIC
    Code:
      stack=3, locals=3, args_size=3
         0: aload_0
         1: aload_1
         2: aload_2
         3: invokespecial #225                // InterfaceMethod getOrElse:(Ljava/lang/Object;Lscala/Function0;)Ljava/lang/Object;
         6: areturn
      LineNumberTable:
        line 95: 0
      LocalVariableTable:
        Start  Length  Slot  Name   Signature
            0       7     0 $this   Lscala/collection/parallel/ParMapLike;
            0       7     1   key   Ljava/lang/Object;
            0       7     2 default   Lscala/Function0;
    MethodParameters:
      Name                           Flags
      $this                          final synthetic
      key                            final
      default                        final

  public default <U extends java.lang.Object> U getOrElse(K, scala.Function0<U>);
    descriptor: (Ljava/lang/Object;Lscala/Function0;)Ljava/lang/Object;
    flags: (0x0001) ACC_PUBLIC
    Code:
      stack=3, locals=7, args_size=3
         0: aload_0
         1: aload_1
         2: invokeinterface #200,  2          // InterfaceMethod get:(Ljava/lang/Object;)Lscala/Option;
         7: astore        4
         9: aload         4
        11: instanceof    #202                // class scala/Some
        14: ifeq          37
        17: aload         4
        19: checkcast     #202                // class scala/Some
        22: astore        5
        24: aload         5
        26: invokevirtual #205                // Method scala/Some.value:()Ljava/lang/Object;
        29: astore        6
        31: aload         6
        33: astore_3
        34: goto          74
        37: goto          40
        40: getstatic     #210                // Field scala/None$.MODULE$:Lscala/None$;
        43: aload         4
        45: invokevirtual #211                // Method java/lang/Object.equals:(Ljava/lang/Object;)Z
        48: ifeq          61
        51: aload_2
        52: invokeinterface #231,  1          // InterfaceMethod scala/Function0.apply:()Ljava/lang/Object;
        57: astore_3
        58: goto          74
        61: goto          64
        64: new           #213                // class scala/MatchError
        67: dup
        68: aload         4
        70: invokespecial #216                // Method scala/MatchError."<init>":(Ljava/lang/Object;)V
        73: athrow
        74: aload_3
        75: areturn
      StackMapTable: number_of_entries = 5
        frame_type = 253 /* append */
          offset_delta = 37
          locals = [ top, class scala/Option ]
        frame_type = 2 /* same */
        frame_type = 20 /* same */
        frame_type = 2 /* same */
        frame_type = 255 /* full_frame */
          offset_delta = 9
          locals = [ class scala/collection/parallel/ParMapLike, class java/lang/Object, class scala/Function0, class java/lang/Object, class scala/Option ]
          stack = []
      LineNumberTable:
        line 95: 0
        line 96: 9
        line 97: 40
        line 95: 64
      LocalVariableTable:
        Start  Length  Slot  Name   Signature
           31       6     6     v   Ljava/lang/Object;
            0      76     0  this   Lscala/collection/parallel/ParMapLike;
            0      76     1   key   Ljava/lang/Object;
            0      76     2 default   Lscala/Function0;
    Signature: #227                         // <U:Ljava/lang/Object;>(TK;Lscala/Function0<TU;>;)TU;
    MethodParameters:
      Name                           Flags
      key                            final
      default                        final

  public static boolean contains$(scala.collection.parallel.ParMapLike, java.lang.Object);
    descriptor: (Lscala/collection/parallel/ParMapLike;Ljava/lang/Object;)Z
    flags: (0x1009) ACC_PUBLIC, ACC_STATIC, ACC_SYNTHETIC
    Code:
      stack=2, locals=2, args_size=2
         0: aload_0
         1: aload_1
         2: invokespecial #235                // InterfaceMethod contains:(Ljava/lang/Object;)Z
         5: ireturn
      LineNumberTable:
        line 100: 0
      LocalVariableTable:
        Start  Length  Slot  Name   Signature
            0       6     0 $this   Lscala/collection/parallel/ParMapLike;
            0       6     1   key   Ljava/lang/Object;
    MethodParameters:
      Name                           Flags
      $this                          final synthetic
      key                            final

  public default boolean contains(K);
    descriptor: (Ljava/lang/Object;)Z
    flags: (0x0001) ACC_PUBLIC
    Code:
      stack=2, locals=2, args_size=2
         0: aload_0
         1: aload_1
         2: invokeinterface #200,  2          // InterfaceMethod get:(Ljava/lang/Object;)Lscala/Option;
         7: invokevirtual #240                // Method scala/Option.isDefined:()Z
        10: ireturn
      LineNumberTable:
        line 100: 0
      LocalVariableTable:
        Start  Length  Slot  Name   Signature
            0      11     0  this   Lscala/collection/parallel/ParMapLike;
            0      11     1   key   Ljava/lang/Object;
    Signature: #236                         // (TK;)Z
    MethodParameters:
      Name                           Flags
      key                            final

  public static boolean isDefinedAt$(scala.collection.parallel.ParMapLike, java.lang.Object);
    descriptor: (Lscala/collection/parallel/ParMapLike;Ljava/lang/Object;)Z
    flags: (0x1009) ACC_PUBLIC, ACC_STATIC, ACC_SYNTHETIC
    Code:
      stack=2, locals=2, args_size=2
         0: aload_0
         1: aload_1
         2: invokespecial #244                // InterfaceMethod isDefinedAt:(Ljava/lang/Object;)Z
         5: ireturn
      LineNumberTable:
        line 102: 0
      LocalVariableTable:
        Start  Length  Slot  Name   Signature
            0       6     0 $this   Lscala/collection/parallel/ParMapLike;
            0       6     1   key   Ljava/lang/Object;
    MethodParameters:
      Name                           Flags
      $this                          final synthetic
      key                            final

  public default boolean isDefinedAt(K);
    descriptor: (Ljava/lang/Object;)Z
    flags: (0x0001) ACC_PUBLIC
    Code:
      stack=2, locals=2, args_size=2
         0: aload_0
         1: aload_1
         2: invokeinterface #235,  2          // InterfaceMethod contains:(Ljava/lang/Object;)Z
         7: ireturn
      LineNumberTable:
        line 102: 0
      LocalVariableTable:
        Start  Length  Slot  Name   Signature
            0       8     0  this   Lscala/collection/parallel/ParMapLike;
            0       8     1   key   Ljava/lang/Object;
    Signature: #236                         // (TK;)Z
    MethodParameters:
      Name                           Flags
      key                            final

  public static scala.collection.parallel.IterableSplitter scala$collection$parallel$ParMapLike$$keysIterator$(scala.collection.parallel.ParMapLike, scala.collection.parallel.IterableSplitter);
    descriptor: (Lscala/collection/parallel/ParMapLike;Lscala/collection/parallel/IterableSplitter;)Lscala/collection/parallel/IterableSplitter;
    flags: (0x1009) ACC_PUBLIC, ACC_STATIC, ACC_SYNTHETIC
    Code:
      stack=2, locals=2, args_size=2
         0: aload_0
         1: aload_1
         2: invokespecial #251                // InterfaceMethod scala$collection$parallel$ParMapLike$$keysIterator:(Lscala/collection/parallel/IterableSplitter;)Lscala/collection/parallel/IterableSplitter;
         5: areturn
      LineNumberTable:
        line 104: 0
      LocalVariableTable:
        Start  Length  Slot  Name   Signature
            0       6     0 $this   Lscala/collection/parallel/ParMapLike;
            0       6     1     s   Lscala/collection/parallel/IterableSplitter;
    MethodParameters:
      Name                           Flags
      $this                          final synthetic
      s                              final

  public default scala.collection.parallel.IterableSplitter<K> scala$collection$parallel$ParMapLike$$keysIterator(scala.collection.parallel.IterableSplitter<scala.Tuple2<K, V>>);
    descriptor: (Lscala/collection/parallel/IterableSplitter;)Lscala/collection/parallel/IterableSplitter;
    flags: (0x0001) ACC_PUBLIC
    Code:
      stack=4, locals=2, args_size=2
         0: new           #47                 // class scala/collection/parallel/ParMapLike$$anon$1
         3: dup
         4: aload_0
         5: aload_1
         6: invokespecial #256                // Method scala/collection/parallel/ParMapLike$$anon$1."<init>":(Lscala/collection/parallel/ParMapLike;Lscala/collection/parallel/IterableSplitter;)V
         9: areturn
      LineNumberTable:
        line 105: 0
      LocalVariableTable:
        Start  Length  Slot  Name   Signature
            0      10     0  this   Lscala/collection/parallel/ParMapLike;
            0      10     1     s   Lscala/collection/parallel/IterableSplitter;
    Signature: #253                         // (Lscala/collection/parallel/IterableSplitter<Lscala/Tuple2<TK;TV;>;>;)Lscala/collection/parallel/IterableSplitter<TK;>;
    MethodParameters:
      Name                           Flags
      s                              final

  public static scala.collection.parallel.IterableSplitter keysIterator$(scala.collection.parallel.ParMapLike);
    descriptor: (Lscala/collection/parallel/ParMapLike;)Lscala/collection/parallel/IterableSplitter;
    flags: (0x1009) ACC_PUBLIC, ACC_STATIC, ACC_SYNTHETIC
    Code:
      stack=1, locals=1, args_size=1
         0: aload_0
         1: invokespecial #262                // InterfaceMethod keysIterator:()Lscala/collection/parallel/IterableSplitter;
         4: areturn
      LineNumberTable:
        line 119: 0
      LocalVariableTable:
        Start  Length  Slot  Name   Signature
            0       5     0 $this   Lscala/collection/parallel/ParMapLike;
    MethodParameters:
      Name                           Flags
      $this                          final synthetic

  public default scala.collection.parallel.IterableSplitter<K> keysIterator();
    descriptor: ()Lscala/collection/parallel/IterableSplitter;
    flags: (0x0001) ACC_PUBLIC
    Code:
      stack=2, locals=1, args_size=1
         0: aload_0
         1: aload_0
         2: invokeinterface #266,  1          // InterfaceMethod splitter:()Lscala/collection/parallel/IterableSplitter;
         7: invokeinterface #251,  2          // InterfaceMethod scala$collection$parallel$ParMapLike$$keysIterator:(Lscala/collection/parallel/IterableSplitter;)Lscala/collection/parallel/IterableSplitter;
        12: areturn
      LineNumberTable:
        line 119: 0
      LocalVariableTable:
        Start  Length  Slot  Name   Signature
            0      13     0  this   Lscala/collection/parallel/ParMapLike;
    Signature: #263                         // ()Lscala/collection/parallel/IterableSplitter<TK;>;

  public static scala.collection.parallel.IterableSplitter scala$collection$parallel$ParMapLike$$valuesIterator$(scala.collection.parallel.ParMapLike, scala.collection.parallel.IterableSplitter);
    descriptor: (Lscala/collection/parallel/ParMapLike;Lscala/collection/parallel/IterableSplitter;)Lscala/collection/parallel/IterableSplitter;
    flags: (0x1009) ACC_PUBLIC, ACC_STATIC, ACC_SYNTHETIC
    Code:
      stack=2, locals=2, args_size=2
         0: aload_0
         1: aload_1
         2: invokespecial #270                // InterfaceMethod scala$collection$parallel$ParMapLike$$valuesIterator:(Lscala/collection/parallel/IterableSplitter;)Lscala/collection/parallel/IterableSplitter;
         5: areturn
      LineNumberTable:
        line 121: 0
      LocalVariableTable:
        Start  Length  Slot  Name   Signature
            0       6     0 $this   Lscala/collection/parallel/ParMapLike;
            0       6     1     s   Lscala/collection/parallel/IterableSplitter;
    MethodParameters:
      Name                           Flags
      $this                          final synthetic
      s                              final

  public default scala.collection.parallel.IterableSplitter<V> scala$collection$parallel$ParMapLike$$valuesIterator(scala.collection.parallel.IterableSplitter<scala.Tuple2<K, V>>);
    descriptor: (Lscala/collection/parallel/IterableSplitter;)Lscala/collection/parallel/IterableSplitter;
    flags: (0x0001) ACC_PUBLIC
    Code:
      stack=4, locals=2, args_size=2
         0: new           #49                 // class scala/collection/parallel/ParMapLike$$anon$2
         3: dup
         4: aload_0
         5: aload_1
         6: invokespecial #272                // Method scala/collection/parallel/ParMapLike$$anon$2."<init>":(Lscala/collection/parallel/ParMapLike;Lscala/collection/parallel/IterableSplitter;)V
         9: areturn
      LineNumberTable:
        line 122: 0
      LocalVariableTable:
        Start  Length  Slot  Name   Signature
            0      10     0  this   Lscala/collection/parallel/ParMapLike;
            0      10     1     s   Lscala/collection/parallel/IterableSplitter;
    Signature: #271                         // (Lscala/collection/parallel/IterableSplitter<Lscala/Tuple2<TK;TV;>;>;)Lscala/collection/parallel/IterableSplitter<TV;>;
    MethodParameters:
      Name                           Flags
      s                              final

  public static scala.collection.parallel.IterableSplitter valuesIterator$(scala.collection.parallel.ParMapLike);
    descriptor: (Lscala/collection/parallel/ParMapLike;)Lscala/collection/parallel/IterableSplitter;
    flags: (0x1009) ACC_PUBLIC, ACC_STATIC, ACC_SYNTHETIC
    Code:
      stack=1, locals=1, args_size=1
         0: aload_0
         1: invokespecial #276                // InterfaceMethod valuesIterator:()Lscala/collection/parallel/IterableSplitter;
         4: areturn
      LineNumberTable:
        line 136: 0
      LocalVariableTable:
        Start  Length  Slot  Name   Signature
            0       5     0 $this   Lscala/collection/parallel/ParMapLike;
    MethodParameters:
      Name                           Flags
      $this                          final synthetic

  public default scala.collection.parallel.IterableSplitter<V> valuesIterator();
    descriptor: ()Lscala/collection/parallel/IterableSplitter;
    flags: (0x0001) ACC_PUBLIC
    Code:
      stack=2, locals=1, args_size=1
         0: aload_0
         1: aload_0
         2: invokeinterface #266,  1          // InterfaceMethod splitter:()Lscala/collection/parallel/IterableSplitter;
         7: invokeinterface #270,  2          // InterfaceMethod scala$collection$parallel$ParMapLike$$valuesIterator:(Lscala/collection/parallel/IterableSplitter;)Lscala/collection/parallel/IterableSplitter;
        12: areturn
      LineNumberTable:
        line 136: 0
      LocalVariableTable:
        Start  Length  Slot  Name   Signature
            0      13     0  this   Lscala/collection/parallel/ParMapLike;
    Signature: #277                         // ()Lscala/collection/parallel/IterableSplitter<TV;>;

  public static scala.collection.parallel.ParSet keySet$(scala.collection.parallel.ParMapLike);
    descriptor: (Lscala/collection/parallel/ParMapLike;)Lscala/collection/parallel/ParSet;
    flags: (0x1009) ACC_PUBLIC, ACC_STATIC, ACC_SYNTHETIC
    Code:
      stack=1, locals=1, args_size=1
         0: aload_0
         1: invokespecial #283                // InterfaceMethod keySet:()Lscala/collection/parallel/ParSet;
         4: areturn
      LineNumberTable:
        line 159: 0
      LocalVariableTable:
        Start  Length  Slot  Name   Signature
            0       5     0 $this   Lscala/collection/parallel/ParMapLike;
    MethodParameters:
      Name                           Flags
      $this                          final synthetic

  public default scala.collection.parallel.ParSet<K> keySet();
    descriptor: ()Lscala/collection/parallel/ParSet;
    flags: (0x0001) ACC_PUBLIC
    Code:
      stack=3, locals=1, args_size=1
         0: new           #55                 // class scala/collection/parallel/ParMapLike$DefaultKeySet
         3: dup
         4: aload_0
         5: invokespecial #287                // Method scala/collection/parallel/ParMapLike$DefaultKeySet."<init>":(Lscala/collection/parallel/ParMapLike;)V
         8: areturn
      LineNumberTable:
        line 159: 0
      LocalVariableTable:
        Start  Length  Slot  Name   Signature
            0       9     0  this   Lscala/collection/parallel/ParMapLike;
    Signature: #284                         // ()Lscala/collection/parallel/ParSet<TK;>;

  public static scala.collection.parallel.ParIterable keys$(scala.collection.parallel.ParMapLike);
    descriptor: (Lscala/collection/parallel/ParMapLike;)Lscala/collection/parallel/ParIterable;
    flags: (0x1009) ACC_PUBLIC, ACC_STATIC, ACC_SYNTHETIC
    Code:
      stack=1, locals=1, args_size=1
         0: aload_0
         1: invokespecial #293                // InterfaceMethod keys:()Lscala/collection/parallel/ParIterable;
         4: areturn
      LineNumberTable:
        line 161: 0
      LocalVariableTable:
        Start  Length  Slot  Name   Signature
            0       5     0 $this   Lscala/collection/parallel/ParMapLike;
    MethodParameters:
      Name                           Flags
      $this                          final synthetic

  public default scala.collection.parallel.ParIterable<K> keys();
    descriptor: ()Lscala/collection/parallel/ParIterable;
    flags: (0x0001) ACC_PUBLIC
    Code:
      stack=1, locals=1, args_size=1
         0: aload_0
         1: invokeinterface #283,  1          // InterfaceMethod keySet:()Lscala/collection/parallel/ParSet;
         6: areturn
      LineNumberTable:
        line 161: 0
      LocalVariableTable:
        Start  Length  Slot  Name   Signature
            0       7     0  this   Lscala/collection/parallel/ParMapLike;
    Signature: #294                         // ()Lscala/collection/parallel/ParIterable<TK;>;

  public static scala.collection.parallel.ParIterable values$(scala.collection.parallel.ParMapLike);
    descriptor: (Lscala/collection/parallel/ParMapLike;)Lscala/collection/parallel/ParIterable;
    flags: (0x1009) ACC_PUBLIC, ACC_STATIC, ACC_SYNTHETIC
    Code:
      stack=1, locals=1, args_size=1
         0: aload_0
         1: invokespecial #298                // InterfaceMethod values:()Lscala/collection/parallel/ParIterable;
         4: areturn
      LineNumberTable:
        line 163: 0
      LocalVariableTable:
        Start  Length  Slot  Name   Signature
            0       5     0 $this   Lscala/collection/parallel/ParMapLike;
    MethodParameters:
      Name                           Flags
      $this                          final synthetic

  public default scala.collection.parallel.ParIterable<V> values();
    descriptor: ()Lscala/collection/parallel/ParIterable;
    flags: (0x0001) ACC_PUBLIC
    Code:
      stack=3, locals=1, args_size=1
         0: new           #58                 // class scala/collection/parallel/ParMapLike$DefaultValuesIterable
         3: dup
         4: aload_0
         5: invokespecial #300                // Method scala/collection/parallel/ParMapLike$DefaultValuesIterable."<init>":(Lscala/collection/parallel/ParMapLike;)V
         8: areturn
      LineNumberTable:
        line 163: 0
      LocalVariableTable:
        Start  Length  Slot  Name   Signature
            0       9     0  this   Lscala/collection/parallel/ParMapLike;
    Signature: #299                         // ()Lscala/collection/parallel/ParIterable<TV;>;

  public static scala.collection.parallel.ParMap filterKeys$(scala.collection.parallel.ParMapLike, scala.Function1);
    descriptor: (Lscala/collection/parallel/ParMapLike;Lscala/Function1;)Lscala/collection/parallel/ParMap;
    flags: (0x1009) ACC_PUBLIC, ACC_STATIC, ACC_SYNTHETIC
    Code:
      stack=2, locals=2, args_size=2
         0: aload_0
         1: aload_1
         2: invokespecial #307                // InterfaceMethod filterKeys:(Lscala/Function1;)Lscala/collection/parallel/ParMap;
         5: areturn
      LineNumberTable:
        line 165: 0
      LocalVariableTable:
        Start  Length  Slot  Name   Signature
            0       6     0 $this   Lscala/collection/parallel/ParMapLike;
            0       6     1     p   Lscala/Function1;
    MethodParameters:
      Name                           Flags
      $this                          final synthetic
      p                              final

  public default scala.collection.parallel.ParMap<K, V> filterKeys(scala.Function1<K, java.lang.Object>);
    descriptor: (Lscala/Function1;)Lscala/collection/parallel/ParMap;
    flags: (0x0001) ACC_PUBLIC
    Code:
      stack=4, locals=2, args_size=2
         0: new           #51                 // class scala/collection/parallel/ParMapLike$$anon$3
         3: dup
         4: aload_0
         5: aload_1
         6: invokespecial #312                // Method scala/collection/parallel/ParMapLike$$anon$3."<init>":(Lscala/collection/parallel/ParMapLike;Lscala/Function1;)V
         9: areturn
      LineNumberTable:
        line 165: 0
      LocalVariableTable:
        Start  Length  Slot  Name   Signature
            0      10     0  this   Lscala/collection/parallel/ParMapLike;
            0      10     1     p   Lscala/Function1;
    Signature: #309                         // (Lscala/Function1<TK;Ljava/lang/Object;>;)Lscala/collection/parallel/ParMap<TK;TV;>;
    MethodParameters:
      Name                           Flags
      p                              final

  public static scala.collection.parallel.ParMap mapValues$(scala.collection.parallel.ParMapLike, scala.Function1);
    descriptor: (Lscala/collection/parallel/ParMapLike;Lscala/Function1;)Lscala/collection/parallel/ParMap;
    flags: (0x1009) ACC_PUBLIC, ACC_STATIC, ACC_SYNTHETIC
    Code:
      stack=2, locals=2, args_size=2
         0: aload_0
         1: aload_1
         2: invokespecial #317                // InterfaceMethod mapValues:(Lscala/Function1;)Lscala/collection/parallel/ParMap;
         5: areturn
      LineNumberTable:
        line 178: 0
      LocalVariableTable:
        Start  Length  Slot  Name   Signature
            0       6     0 $this   Lscala/collection/parallel/ParMapLike;
            0       6     1     f   Lscala/Function1;
    MethodParameters:
      Name                           Flags
      $this                          final synthetic
      f                              final

  public default <S extends java.lang.Object> scala.collection.parallel.ParMap<K, S> mapValues(scala.Function1<V, S>);
    descriptor: (Lscala/Function1;)Lscala/collection/parallel/ParMap;
    flags: (0x0001) ACC_PUBLIC
    Code:
      stack=4, locals=2, args_size=2
         0: new           #53                 // class scala/collection/parallel/ParMapLike$$anon$4
         3: dup
         4: aload_0
         5: aload_1
         6: invokespecial #319                // Method scala/collection/parallel/ParMapLike$$anon$4."<init>":(Lscala/collection/parallel/ParMapLike;Lscala/Function1;)V
         9: areturn
      LineNumberTable:
        line 178: 0
      LocalVariableTable:
        Start  Length  Slot  Name   Signature
            0      10     0  this   Lscala/collection/parallel/ParMapLike;
            0      10     1     f   Lscala/Function1;
    Signature: #318                         // <S:Ljava/lang/Object;>(Lscala/Function1<TV;TS;>;)Lscala/collection/parallel/ParMap<TK;TS;>;
    MethodParameters:
      Name                           Flags
      f                              final

  public static scala.collection.parallel.ParMap map$(scala.collection.parallel.ParMapLike, scala.Function1);
    descriptor: (Lscala/collection/parallel/ParMapLike;Lscala/Function1;)Lscala/collection/parallel/ParMap;
    flags: (0x1009) ACC_PUBLIC, ACC_STATIC, ACC_SYNTHETIC
    Code:
      stack=2, locals=2, args_size=2
         0: aload_0
         1: aload_1
         2: invokespecial #323                // InterfaceMethod map:(Lscala/Function1;)Lscala/collection/parallel/ParMap;
         5: areturn
      LineNumberTable:
        line 199: 0
      LocalVariableTable:
        Start  Length  Slot  Name   Signature
            0       6     0 $this   Lscala/collection/parallel/ParMapLike;
            0       6     1     f   Lscala/Function1;
    MethodParameters:
      Name                           Flags
      $this                          final synthetic
      f                              final

  public default <K2 extends java.lang.Object, V2 extends java.lang.Object> CC map(scala.Function1<scala.Tuple2<K, V>, scala.Tuple2<K2, V2>>);
    descriptor: (Lscala/Function1;)Lscala/collection/parallel/ParMap;
    flags: (0x0001) ACC_PUBLIC
    Code:
      stack=8, locals=2, args_size=2
         0: aload_0
         1: invokeinterface #328,  1          // InterfaceMethod tasksupport:()Lscala/collection/parallel/TaskSupport;
         6: aload_0
         7: new           #29                 // class scala/collection/parallel/ParIterableLike$Map
        10: dup
        11: aload_0
        12: aload_1
        13: aload_0
        14: aload_0
        15: invokedynamic #339,  0            // InvokeDynamic #1:apply:(Lscala/collection/parallel/ParMapLike;)Lscala/Function0;
        20: invokeinterface #343,  2          // InterfaceMethod combinerFactory:(Lscala/Function0;)Lscala/collection/parallel/CombinerFactory;
        25: aload_0
        26: invokeinterface #266,  1          // InterfaceMethod splitter:()Lscala/collection/parallel/IterableSplitter;
        31: invokespecial #346                // Method scala/collection/parallel/ParIterableLike$Map."<init>":(Lscala/collection/parallel/ParIterableLike;Lscala/Function1;Lscala/collection/parallel/CombinerFactory;Lscala/collection/parallel/IterableSplitter;)V
        34: invokeinterface #350,  2          // InterfaceMethod task2ops:(Lscala/collection/parallel/ParIterableLike$StrictSplitterCheckTask;)Lscala/collection/parallel/ParIterableLike$TaskOps;
        39: invokedynamic #359,  0            // InvokeDynamic #2:apply:()Lscala/Function1;
        44: invokeinterface #363,  2          // InterfaceMethod scala/collection/parallel/ParIterableLike$TaskOps.mapResult:(Lscala/Function1;)Lscala/collection/parallel/ParIterableLike$ResultMapping;
        49: invokeinterface #369,  2          // InterfaceMethod scala/collection/parallel/TaskSupport.executeAndWaitResult:(Lscala/collection/parallel/Task;)Ljava/lang/Object;
        54: checkcast     #82                 // class scala/collection/parallel/ParMap
        57: areturn
      LineNumberTable:
        line 200: 0
        line 200: 6
        line 201: 12
        line 202: 13
        line 203: 25
        line 204: 39
      LocalVariableTable:
        Start  Length  Slot  Name   Signature
            0      58     0  this   Lscala/collection/parallel/ParMapLike;
            0      58     1     f   Lscala/Function1;
    Signature: #324                         // <K2:Ljava/lang/Object;V2:Ljava/lang/Object;>(Lscala/Function1<Lscala/Tuple2<TK;TV;>;Lscala/Tuple2<TK2;TV2;>;>;)TCC;
    MethodParameters:
      Name                           Flags
      f                              final

  public static scala.collection.parallel.ParMap collect$(scala.collection.parallel.ParMapLike, scala.PartialFunction);
    descriptor: (Lscala/collection/parallel/ParMapLike;Lscala/PartialFunction;)Lscala/collection/parallel/ParMap;
    flags: (0x1009) ACC_PUBLIC, ACC_STATIC, ACC_SYNTHETIC
    Code:
      stack=2, locals=2, args_size=2
         0: aload_0
         1: aload_1
         2: invokespecial #376                // InterfaceMethod collect:(Lscala/PartialFunction;)Lscala/collection/parallel/ParMap;
         5: areturn
      LineNumberTable:
        line 216: 0
      LocalVariableTable:
        Start  Length  Slot  Name   Signature
            0       6     0 $this   Lscala/collection/parallel/ParMapLike;
            0       6     1    pf   Lscala/PartialFunction;
    MethodParameters:
      Name                           Flags
      $this                          final synthetic
      pf                             final

  public default <K2 extends java.lang.Object, V2 extends java.lang.Object> CC collect(scala.PartialFunction<scala.Tuple2<K, V>, scala.Tuple2<K2, V2>>);
    descriptor: (Lscala/PartialFunction;)Lscala/collection/parallel/ParMap;
    flags: (0x0001) ACC_PUBLIC
    Code:
      stack=8, locals=2, args_size=2
         0: aload_0
         1: invokeinterface #328,  1          // InterfaceMethod tasksupport:()Lscala/collection/parallel/TaskSupport;
         6: aload_0
         7: new           #20                 // class scala/collection/parallel/ParIterableLike$Collect
        10: dup
        11: aload_0
        12: aload_1
        13: aload_0
        14: aload_0
        15: invokedynamic #383,  0            // InvokeDynamic #3:apply:(Lscala/collection/parallel/ParMapLike;)Lscala/Function0;
        20: invokeinterface #343,  2          // InterfaceMethod combinerFactory:(Lscala/Function0;)Lscala/collection/parallel/CombinerFactory;
        25: aload_0
        26: invokeinterface #266,  1          // InterfaceMethod splitter:()Lscala/collection/parallel/IterableSplitter;
        31: invokespecial #386                // Method scala/collection/parallel/ParIterableLike$Collect."<init>":(Lscala/collection/parallel/ParIterableLike;Lscala/PartialFunction;Lscala/collection/parallel/CombinerFactory;Lscala/collection/parallel/IterableSplitter;)V
        34: invokeinterface #350,  2          // InterfaceMethod task2ops:(Lscala/collection/parallel/ParIterableLike$StrictSplitterCheckTask;)Lscala/collection/parallel/ParIterableLike$TaskOps;
        39: invokedynamic #391,  0            // InvokeDynamic #4:apply:()Lscala/Function1;
        44: invokeinterface #363,  2          // InterfaceMethod scala/collection/parallel/ParIterableLike$TaskOps.mapResult:(Lscala/Function1;)Lscala/collection/parallel/ParIterableLike$ResultMapping;
        49: invokeinterface #369,  2          // InterfaceMethod scala/collection/parallel/TaskSupport.executeAndWaitResult:(Lscala/collection/parallel/Task;)Ljava/lang/Object;
        54: checkcast     #82                 // class scala/collection/parallel/ParMap
        57: areturn
      LineNumberTable:
        line 217: 0
        line 217: 6
        line 218: 12
        line 219: 13
        line 220: 25
        line 221: 39
      LocalVariableTable:
        Start  Length  Slot  Name   Signature
            0      58     0  this   Lscala/collection/parallel/ParMapLike;
            0      58     1    pf   Lscala/PartialFunction;
    Signature: #378                         // <K2:Ljava/lang/Object;V2:Ljava/lang/Object;>(Lscala/PartialFunction<Lscala/Tuple2<TK;TV;>;Lscala/Tuple2<TK2;TV2;>;>;)TCC;
    MethodParameters:
      Name                           Flags
      pf                             final

  public static scala.collection.parallel.ParMap flatMap$(scala.collection.parallel.ParMapLike, scala.Function1);
    descriptor: (Lscala/collection/parallel/ParMapLike;Lscala/Function1;)Lscala/collection/parallel/ParMap;
    flags: (0x1009) ACC_PUBLIC, ACC_STATIC, ACC_SYNTHETIC
    Code:
      stack=2, locals=2, args_size=2
         0: aload_0
         1: aload_1
         2: invokespecial #395                // InterfaceMethod flatMap:(Lscala/Function1;)Lscala/collection/parallel/ParMap;
         5: areturn
      LineNumberTable:
        line 230: 0
      LocalVariableTable:
        Start  Length  Slot  Name   Signature
            0       6     0 $this   Lscala/collection/parallel/ParMapLike;
            0       6     1     f   Lscala/Function1;
    MethodParameters:
      Name                           Flags
      $this                          final synthetic
      f                              final

  public default <K2 extends java.lang.Object, V2 extends java.lang.Object> CC flatMap(scala.Function1<scala.Tuple2<K, V>, scala.collection.IterableOnce<scala.Tuple2<K2, V2>>>);
    descriptor: (Lscala/Function1;)Lscala/collection/parallel/ParMap;
    flags: (0x0001) ACC_PUBLIC
    Code:
      stack=8, locals=2, args_size=2
         0: aload_0
         1: invokeinterface #328,  1          // InterfaceMethod tasksupport:()Lscala/collection/parallel/TaskSupport;
         6: aload_0
         7: new           #26                 // class scala/collection/parallel/ParIterableLike$FlatMap
        10: dup
        11: aload_0
        12: aload_1
        13: aload_0
        14: aload_0
        15: invokedynamic #401,  0            // InvokeDynamic #5:apply:(Lscala/collection/parallel/ParMapLike;)Lscala/Function0;
        20: invokeinterface #343,  2          // InterfaceMethod combinerFactory:(Lscala/Function0;)Lscala/collection/parallel/CombinerFactory;
        25: aload_0
        26: invokeinterface #266,  1          // InterfaceMethod splitter:()Lscala/collection/parallel/IterableSplitter;
        31: invokespecial #402                // Method scala/collection/parallel/ParIterableLike$FlatMap."<init>":(Lscala/collection/parallel/ParIterableLike;Lscala/Function1;Lscala/collection/parallel/CombinerFactory;Lscala/collection/parallel/IterableSplitter;)V
        34: invokeinterface #350,  2          // InterfaceMethod task2ops:(Lscala/collection/parallel/ParIterableLike$StrictSplitterCheckTask;)Lscala/collection/parallel/ParIterableLike$TaskOps;
        39: invokedynamic #407,  0            // InvokeDynamic #6:apply:()Lscala/Function1;
        44: invokeinterface #363,  2          // InterfaceMethod scala/collection/parallel/ParIterableLike$TaskOps.mapResult:(Lscala/Function1;)Lscala/collection/parallel/ParIterableLike$ResultMapping;
        49: invokeinterface #369,  2          // InterfaceMethod scala/collection/parallel/TaskSupport.executeAndWaitResult:(Lscala/collection/parallel/Task;)Ljava/lang/Object;
        54: checkcast     #82                 // class scala/collection/parallel/ParMap
        57: areturn
      LineNumberTable:
        line 231: 0
        line 231: 6
        line 232: 12
        line 233: 13
        line 234: 25
        line 235: 39
      LocalVariableTable:
        Start  Length  Slot  Name   Signature
            0      58     0  this   Lscala/collection/parallel/ParMapLike;
            0      58     1     f   Lscala/Function1;
    Signature: #396                         // <K2:Ljava/lang/Object;V2:Ljava/lang/Object;>(Lscala/Function1<Lscala/Tuple2<TK;TV;>;Lscala/collection/IterableOnce<Lscala/Tuple2<TK2;TV2;>;>;>;)TCC;
    MethodParameters:
      Name                           Flags
      f                              final

  public static scala.collection.parallel.ParMap concat$(scala.collection.parallel.ParMapLike, scala.collection.IterableOnce);
    descriptor: (Lscala/collection/parallel/ParMapLike;Lscala/collection/IterableOnce;)Lscala/collection/parallel/ParMap;
    flags: (0x1009) ACC_PUBLIC, ACC_STATIC, ACC_SYNTHETIC
    Code:
      stack=2, locals=2, args_size=2
         0: aload_0
         1: aload_1
         2: invokespecial #413                // InterfaceMethod concat:(Lscala/collection/IterableOnce;)Lscala/collection/parallel/ParMap;
         5: areturn
      LineNumberTable:
        line 245: 0
      LocalVariableTable:
        Start  Length  Slot  Name   Signature
            0       6     0 $this   Lscala/collection/parallel/ParMapLike;
            0       6     1  that   Lscala/collection/IterableOnce;
    MethodParameters:
      Name                           Flags
      $this                          final synthetic
      that                           final

  public default <V2 extends java.lang.Object> CC concat(scala.collection.IterableOnce<scala.Tuple2<K, V2>>);
    descriptor: (Lscala/collection/IterableOnce;)Lscala/collection/parallel/ParMap;
    flags: (0x0001) ACC_PUBLIC
    Code:
      stack=5, locals=11, args_size=2
         0: aload_1
         1: astore_3
         2: aload_3
         3: instanceof    #417                // class scala/collection/parallel/ParIterable
         6: ifeq          123
         9: aload_3
        10: checkcast     #417                // class scala/collection/parallel/ParIterable
        13: astore        4
        15: aload_0
        16: aload_0
        17: invokedynamic #422,  0            // InvokeDynamic #7:apply:(Lscala/collection/parallel/ParMapLike;)Lscala/Function0;
        22: invokeinterface #343,  2          // InterfaceMethod combinerFactory:(Lscala/Function0;)Lscala/collection/parallel/CombinerFactory;
        27: astore        5
        29: new           #23                 // class scala/collection/parallel/ParIterableLike$Copy
        32: dup
        33: aload_0
        34: aload         5
        36: aload_0
        37: invokeinterface #266,  1          // InterfaceMethod splitter:()Lscala/collection/parallel/IterableSplitter;
        42: invokespecial #425                // Method scala/collection/parallel/ParIterableLike$Copy."<init>":(Lscala/collection/parallel/ParIterableLike;Lscala/collection/parallel/CombinerFactory;Lscala/collection/parallel/IterableSplitter;)V
        45: astore        6
        47: aload_0
        48: aload_0
        49: aload         4
        51: aload         5
        53: invokedynamic #433,  0            // InvokeDynamic #8:apply:(Lscala/collection/parallel/ParMapLike;Lscala/collection/parallel/ParIterable;Lscala/collection/parallel/CombinerFactory;)Lscala/Function0;
        58: invokeinterface #437,  2          // InterfaceMethod wrap:(Lscala/Function0;)Lscala/collection/parallel/ParIterableLike$NonDivisible;
        63: astore        7
        65: aload_0
        66: aload_0
        67: aload         6
        69: invokeinterface #350,  2          // InterfaceMethod task2ops:(Lscala/collection/parallel/ParIterableLike$StrictSplitterCheckTask;)Lscala/collection/parallel/ParIterableLike$TaskOps;
        74: aload         7
        76: invokedynamic #448,  0            // InvokeDynamic #9:apply:()Lscala/Function2;
        81: invokeinterface #452,  3          // InterfaceMethod scala/collection/parallel/ParIterableLike$TaskOps.parallel:(Lscala/collection/parallel/ParIterableLike$StrictSplitterCheckTask;Lscala/Function2;)Lscala/collection/parallel/ParIterableLike$ParComposite;
        86: invokeinterface #350,  2          // InterfaceMethod task2ops:(Lscala/collection/parallel/ParIterableLike$StrictSplitterCheckTask;)Lscala/collection/parallel/ParIterableLike$TaskOps;
        91: invokedynamic #457,  0            // InvokeDynamic #10:apply:()Lscala/Function1;
        96: invokeinterface #363,  2          // InterfaceMethod scala/collection/parallel/ParIterableLike$TaskOps.mapResult:(Lscala/Function1;)Lscala/collection/parallel/ParIterableLike$ResultMapping;
       101: astore        8
       103: aload_0
       104: invokeinterface #328,  1          // InterfaceMethod tasksupport:()Lscala/collection/parallel/TaskSupport;
       109: aload         8
       111: invokeinterface #369,  2          // InterfaceMethod scala/collection/parallel/TaskSupport.executeAndWaitResult:(Lscala/collection/parallel/Task;)Ljava/lang/Object;
       116: checkcast     #82                 // class scala/collection/parallel/ParMap
       119: astore_2
       120: goto          223
       123: goto          126
       126: new           #23                 // class scala/collection/parallel/ParIterableLike$Copy
       129: dup
       130: aload_0
       131: aload_0
       132: aload_0
       133: invokedynamic #462,  0            // InvokeDynamic #11:apply:(Lscala/collection/parallel/ParMapLike;)Lscala/Function0;
       138: invokeinterface #343,  2          // InterfaceMethod combinerFactory:(Lscala/Function0;)Lscala/collection/parallel/CombinerFactory;
       143: aload_0
       144: invokeinterface #266,  1          // InterfaceMethod splitter:()Lscala/collection/parallel/IterableSplitter;
       149: invokespecial #425                // Method scala/collection/parallel/ParIterableLike$Copy."<init>":(Lscala/collection/parallel/ParIterableLike;Lscala/collection/parallel/CombinerFactory;Lscala/collection/parallel/IterableSplitter;)V
       152: astore        9
       154: aload_0
       155: aload_0
       156: aload_1
       157: invokedynamic #470,  0            // InvokeDynamic #12:apply:(Lscala/collection/parallel/ParMapLike;Lscala/collection/IterableOnce;)Lscala/Function0;
       162: invokeinterface #437,  2          // InterfaceMethod wrap:(Lscala/Function0;)Lscala/collection/parallel/ParIterableLike$NonDivisible;
       167: astore        10
       169: aload_0
       170: invokeinterface #328,  1          // InterfaceMethod tasksupport:()Lscala/collection/parallel/TaskSupport;
       175: aload_0
       176: aload_0
       177: aload         9
       179: invokeinterface #350,  2          // InterfaceMethod task2ops:(Lscala/collection/parallel/ParIterableLike$StrictSplitterCheckTask;)Lscala/collection/parallel/ParIterableLike$TaskOps;
       184: aload         10
       186: invokedynamic #475,  0            // InvokeDynamic #13:apply:()Lscala/Function2;
       191: invokeinterface #452,  3          // InterfaceMethod scala/collection/parallel/ParIterableLike$TaskOps.parallel:(Lscala/collection/parallel/ParIterableLike$StrictSplitterCheckTask;Lscala/Function2;)Lscala/collection/parallel/ParIterableLike$ParComposite;
       196: invokeinterface #350,  2          // InterfaceMethod task2ops:(Lscala/collection/parallel/ParIterableLike$StrictSplitterCheckTask;)Lscala/collection/parallel/ParIterableLike$TaskOps;
       201: invokedynamic #480,  0            // InvokeDynamic #14:apply:()Lscala/Function1;
       206: invokeinterface #363,  2          // InterfaceMethod scala/collection/parallel/ParIterableLike$TaskOps.mapResult:(Lscala/Function1;)Lscala/collection/parallel/ParIterableLike$ResultMapping;
       211: invokeinterface #369,  2          // InterfaceMethod scala/collection/parallel/TaskSupport.executeAndWaitResult:(Lscala/collection/parallel/Task;)Ljava/lang/Object;
       216: checkcast     #82                 // class scala/collection/parallel/ParMap
       219: astore_2
       220: goto          223
       223: aload_2
       224: areturn
      StackMapTable: number_of_entries = 3
        frame_type = 253 /* append */
          offset_delta = 123
          locals = [ top, class scala/collection/IterableOnce ]
        frame_type = 2 /* same */
        frame_type = 255 /* full_frame */
          offset_delta = 96
          locals = [ class scala/collection/parallel/ParMapLike, class scala/collection/IterableOnce, class scala/collection/parallel/ParMap, class scala/collection/IterableOnce ]
          stack = []
      LineNumberTable:
        line 245: 0
        line 246: 2
        line 248: 15
        line 249: 29
        line 250: 47
        line 254: 65
        line 255: 91
        line 257: 103
        line 246: 123
        line 260: 126
        line 261: 154
        line 266: 169
        line 245: 223
      LocalVariableTable:
        Start  Length  Slot  Name   Signature
           29      90     5 cfactory   Lscala/collection/parallel/CombinerFactory;
           47      72     6 copythis   Lscala/collection/parallel/ParIterableLike$Copy;
           65      54     7 copythat   Lscala/collection/parallel/ParIterableLike$NonDivisible;
          103      16     8  task   Lscala/collection/parallel/ParIterableLike$ResultMapping;
          154      65     9 copythis   Lscala/collection/parallel/ParIterableLike$Copy;
          169      50    10 copythat   Lscala/collection/parallel/ParIterableLike$NonDivisible;
            0     225     0  this   Lscala/collection/parallel/ParMapLike;
            0     225     1  that   Lscala/collection/IterableOnce;
    Signature: #415                         // <V2:Ljava/lang/Object;>(Lscala/collection/IterableOnce<Lscala/Tuple2<TK;TV2;>;>;)TCC;
    MethodParameters:
      Name                           Flags
      that                           final

  public static scala.collection.parallel.ParMap $plus$plus$(scala.collection.parallel.ParMapLike, scala.collection.IterableOnce);
    descriptor: (Lscala/collection/parallel/ParMapLike;Lscala/collection/IterableOnce;)Lscala/collection/parallel/ParMap;
    flags: (0x1009) ACC_PUBLIC, ACC_STATIC, ACC_SYNTHETIC
    Code:
      stack=2, locals=2, args_size=2
         0: aload_0
         1: aload_1
         2: invokespecial #495                // InterfaceMethod $plus$plus:(Lscala/collection/IterableOnce;)Lscala/collection/parallel/ParMap;
         5: areturn
      LineNumberTable:
        line 270: 0
      LocalVariableTable:
        Start  Length  Slot  Name   Signature
            0       6     0 $this   Lscala/collection/parallel/ParMapLike;
            0       6     1    xs   Lscala/collection/IterableOnce;
    MethodParameters:
      Name                           Flags
      $this                          final synthetic
      xs                             final

  public default <V2 extends java.lang.Object> CC $plus$plus(scala.collection.IterableOnce<scala.Tuple2<K, V2>>);
    descriptor: (Lscala/collection/IterableOnce;)Lscala/collection/parallel/ParMap;
    flags: (0x0001) ACC_PUBLIC
    Code:
      stack=2, locals=2, args_size=2
         0: aload_0
         1: aload_1
         2: invokeinterface #413,  2          // InterfaceMethod concat:(Lscala/collection/IterableOnce;)Lscala/collection/parallel/ParMap;
         7: areturn
      LineNumberTable:
        line 270: 0
      LocalVariableTable:
        Start  Length  Slot  Name   Signature
            0       8     0  this   Lscala/collection/parallel/ParMapLike;
            0       8     1    xs   Lscala/collection/IterableOnce;
    Signature: #415                         // <V2:Ljava/lang/Object;>(Lscala/collection/IterableOnce<Lscala/Tuple2<TK;TV2;>;>;)TCC;
    MethodParameters:
      Name                           Flags
      xs                             final

  public static boolean $anonfun$equals$1(scala.collection.parallel.ParMap, scala.Tuple2);
    descriptor: (Lscala/collection/parallel/ParMap;Lscala/Tuple2;)Z
    flags: (0x1009) ACC_PUBLIC, ACC_STATIC, ACC_SYNTHETIC
    Code:
      stack=3, locals=10, args_size=2
         0: aload_1
         1: astore        4
         3: aload         4
         5: ifnull        85
         8: aload         4
        10: invokevirtual #502                // Method scala/Tuple2._1:()Ljava/lang/Object;
        13: astore        5
        15: aload         4
        17: invokevirtual #505                // Method scala/Tuple2._2:()Ljava/lang/Object;
        20: astore        6
        22: aload_0
        23: aload         5
        25: invokeinterface #506,  2          // InterfaceMethod scala/collection/parallel/ParMap.get:(Ljava/lang/Object;)Lscala/Option;
        30: astore        7
        32: aload         7
        34: instanceof    #202                // class scala/Some
        37: ifeq          72
        40: aload         7
        42: checkcast     #202                // class scala/Some
        45: astore        8
        47: aload         8
        49: invokevirtual #205                // Method scala/Some.value:()Ljava/lang/Object;
        52: astore        9
        54: aload         6
        56: aload         9
        58: invokestatic  #511                // Method scala/runtime/BoxesRunTime.equals:(Ljava/lang/Object;Ljava/lang/Object;)Z
        61: ifeq          69
        64: iconst_1
        65: istore_3
        66: goto          80
        69: goto          75
        72: goto          75
        75: iconst_0
        76: istore_3
        77: goto          80
        80: iload_3
        81: istore_2
        82: goto          98
        85: goto          88
        88: new           #213                // class scala/MatchError
        91: dup
        92: aload         4
        94: invokespecial #216                // Method scala/MatchError."<init>":(Ljava/lang/Object;)V
        97: athrow
        98: iload_2
        99: ireturn
      StackMapTable: number_of_entries = 7
        frame_type = 255 /* full_frame */
          offset_delta = 69
          locals = [ class scala/collection/parallel/ParMap, class scala/Tuple2, top, top, class scala/Tuple2, class java/lang/Object, class java/lang/Object, class scala/Option, class scala/Some, class java/lang/Object ]
          stack = []
        frame_type = 249 /* chop */
          offset_delta = 2
        frame_type = 2 /* same */
        frame_type = 255 /* full_frame */
          offset_delta = 4
          locals = [ class scala/collection/parallel/ParMap, class scala/Tuple2, top, int, class scala/Tuple2, class java/lang/Object, class java/lang/Object, class scala/Option ]
          stack = []
        frame_type = 255 /* full_frame */
          offset_delta = 4
          locals = [ class scala/collection/parallel/ParMap, class scala/Tuple2, top, top, class scala/Tuple2 ]
          stack = []
        frame_type = 2 /* same */
        frame_type = 255 /* full_frame */
          offset_delta = 9
          locals = [ class scala/collection/parallel/ParMap, class scala/Tuple2, int, int, class scala/Tuple2, class java/lang/Object, class java/lang/Object, class scala/Option ]
          stack = []
      LineNumberTable:
        line 61: 0
        line 62: 3
        line 63: 32
        line 64: 64
        line 63: 69
        line 65: 75
        line 62: 80
        line 61: 88
      LocalVariableTable:
        Start  Length  Slot  Name   Signature
           15      70     5     k   Ljava/lang/Object;
           22      63     6     v   Ljava/lang/Object;
            0     100     0  x2$1   Lscala/collection/parallel/ParMap;
            0     100     1  x0$1   Lscala/Tuple2;
    MethodParameters:
      Name                           Flags
      x2$1                           final
      x0$1                           final

  public static scala.collection.parallel.Combiner $anonfun$map$1(scala.collection.parallel.ParMapLike);
    descriptor: (Lscala/collection/parallel/ParMapLike;)Lscala/collection/parallel/Combiner;
    flags: (0x1009) ACC_PUBLIC, ACC_STATIC, ACC_SYNTHETIC
    Code:
      stack=1, locals=1, args_size=1
         0: aload_0
         1: invokeinterface #516,  1          // InterfaceMethod mapCompanion:()Lscala/collection/generic/GenericParMapCompanion;
         6: invokeinterface #521,  1          // InterfaceMethod scala/collection/generic/GenericParMapCompanion.newCombiner:()Lscala/collection/parallel/Combiner;
        11: areturn
      LineNumberTable:
        line 202: 0
      LocalVariableTable:
        Start  Length  Slot  Name   Signature
            0      12     0 $this   Lscala/collection/parallel/ParMapLike;
    MethodParameters:
      Name                           Flags
      $this                          final synthetic

  public static scala.collection.parallel.ParMap $anonfun$map$2(scala.collection.parallel.Combiner);
    descriptor: (Lscala/collection/parallel/Combiner;)Lscala/collection/parallel/ParMap;
    flags: (0x1009) ACC_PUBLIC, ACC_STATIC, ACC_SYNTHETIC
    Code:
      stack=1, locals=1, args_size=1
         0: aload_0
         1: invokeinterface #527,  1          // InterfaceMethod scala/collection/parallel/Combiner.resultWithTaskSupport:()Ljava/lang/Object;
         6: checkcast     #82                 // class scala/collection/parallel/ParMap
         9: areturn
      LineNumberTable:
        line 204: 0
      LocalVariableTable:
        Start  Length  Slot  Name   Signature
            0      10     0   x$8   Lscala/collection/parallel/Combiner;
    MethodParameters:
      Name                           Flags
      x$8                            final

  public static scala.collection.parallel.Combiner $anonfun$collect$1(scala.collection.parallel.ParMapLike);
    descriptor: (Lscala/collection/parallel/ParMapLike;)Lscala/collection/parallel/Combiner;
    flags: (0x1009) ACC_PUBLIC, ACC_STATIC, ACC_SYNTHETIC
    Code:
      stack=1, locals=1, args_size=1
         0: aload_0
         1: invokeinterface #516,  1          // InterfaceMethod mapCompanion:()Lscala/collection/generic/GenericParMapCompanion;
         6: invokeinterface #521,  1          // InterfaceMethod scala/collection/generic/GenericParMapCompanion.newCombiner:()Lscala/collection/parallel/Combiner;
        11: areturn
      LineNumberTable:
        line 219: 0
      LocalVariableTable:
        Start  Length  Slot  Name   Signature
            0      12     0 $this   Lscala/collection/parallel/ParMapLike;
    MethodParameters:
      Name                           Flags
      $this                          final synthetic

  public static scala.collection.parallel.ParMap $anonfun$collect$2(scala.collection.parallel.Combiner);
    descriptor: (Lscala/collection/parallel/Combiner;)Lscala/collection/parallel/ParMap;
    flags: (0x1009) ACC_PUBLIC, ACC_STATIC, ACC_SYNTHETIC
    Code:
      stack=1, locals=1, args_size=1
         0: aload_0
         1: invokeinterface #527,  1          // InterfaceMethod scala/collection/parallel/Combiner.resultWithTaskSupport:()Ljava/lang/Object;
         6: checkcast     #82                 // class scala/collection/parallel/ParMap
         9: areturn
      LineNumberTable:
        line 221: 0
      LocalVariableTable:
        Start  Length  Slot  Name   Signature
            0      10     0   x$9   Lscala/collection/parallel/Combiner;
    MethodParameters:
      Name                           Flags
      x$9                            final

  public static scala.collection.parallel.Combiner $anonfun$flatMap$1(scala.collection.parallel.ParMapLike);
    descriptor: (Lscala/collection/parallel/ParMapLike;)Lscala/collection/parallel/Combiner;
    flags: (0x1009) ACC_PUBLIC, ACC_STATIC, ACC_SYNTHETIC
    Code:
      stack=1, locals=1, args_size=1
         0: aload_0
         1: invokeinterface #516,  1          // InterfaceMethod mapCompanion:()Lscala/collection/generic/GenericParMapCompanion;
         6: invokeinterface #521,  1          // InterfaceMethod scala/collection/generic/GenericParMapCompanion.newCombiner:()Lscala/collection/parallel/Combiner;
        11: areturn
      LineNumberTable:
        line 233: 0
      LocalVariableTable:
        Start  Length  Slot  Name   Signature
            0      12     0 $this   Lscala/collection/parallel/ParMapLike;
    MethodParameters:
      Name                           Flags
      $this                          final synthetic

  public static scala.collection.parallel.ParMap $anonfun$flatMap$2(scala.collection.parallel.Combiner);
    descriptor: (Lscala/collection/parallel/Combiner;)Lscala/collection/parallel/ParMap;
    flags: (0x1009) ACC_PUBLIC, ACC_STATIC, ACC_SYNTHETIC
    Code:
      stack=1, locals=1, args_size=1
         0: aload_0
         1: invokeinterface #527,  1          // InterfaceMethod scala/collection/parallel/Combiner.resultWithTaskSupport:()Ljava/lang/Object;
         6: checkcast     #82                 // class scala/collection/parallel/ParMap
         9: areturn
      LineNumberTable:
        line 235: 0
      LocalVariableTable:
        Start  Length  Slot  Name   Signature
            0      10     0  x$10   Lscala/collection/parallel/Combiner;
    MethodParameters:
      Name                           Flags
      x$10                           final

  public static scala.collection.parallel.Combiner $anonfun$concat$1(scala.collection.parallel.ParMapLike);
    descriptor: (Lscala/collection/parallel/ParMapLike;)Lscala/collection/parallel/Combiner;
    flags: (0x1009) ACC_PUBLIC, ACC_STATIC, ACC_SYNTHETIC
    Code:
      stack=1, locals=1, args_size=1
         0: aload_0
         1: invokeinterface #516,  1          // InterfaceMethod mapCompanion:()Lscala/collection/generic/GenericParMapCompanion;
         6: invokeinterface #521,  1          // InterfaceMethod scala/collection/generic/GenericParMapCompanion.newCombiner:()Lscala/collection/parallel/Combiner;
        11: areturn
      LineNumberTable:
        line 248: 0
      LocalVariableTable:
        Start  Length  Slot  Name   Signature
            0      12     0 $this   Lscala/collection/parallel/ParMapLike;
    MethodParameters:
      Name                           Flags
      $this                          final synthetic

  public static scala.collection.parallel.Combiner $anonfun$concat$2(scala.collection.parallel.ParMapLike, scala.collection.parallel.ParIterable, scala.collection.parallel.CombinerFactory);
    descriptor: (Lscala/collection/parallel/ParMapLike;Lscala/collection/parallel/ParIterable;Lscala/collection/parallel/CombinerFactory;)Lscala/collection/parallel/Combiner;
    flags: (0x1009) ACC_PUBLIC, ACC_STATIC, ACC_SYNTHETIC
    Code:
      stack=5, locals=4, args_size=3
         0: new           #23                 // class scala/collection/parallel/ParIterableLike$Copy
         3: dup
         4: aload_1
         5: aload_2
         6: aload_1
         7: invokeinterface #533,  1          // InterfaceMethod scala/collection/parallel/ParIterable.splitter:()Lscala/collection/parallel/IterableSplitter;
        12: invokespecial #425                // Method scala/collection/parallel/ParIterableLike$Copy."<init>":(Lscala/collection/parallel/ParIterableLike;Lscala/collection/parallel/CombinerFactory;Lscala/collection/parallel/IterableSplitter;)V
        15: astore_3
        16: aload_0
        17: invokeinterface #328,  1          // InterfaceMethod tasksupport:()Lscala/collection/parallel/TaskSupport;
        22: aload_3
        23: invokeinterface #369,  2          // InterfaceMethod scala/collection/parallel/TaskSupport.executeAndWaitResult:(Lscala/collection/parallel/Task;)Ljava/lang/Object;
        28: checkcast     #524                // class scala/collection/parallel/Combiner
        31: areturn
      LineNumberTable:
        line 251: 0
        line 252: 16
      LocalVariableTable:
        Start  Length  Slot  Name   Signature
           16      15     3 othtask   Lscala/collection/parallel/ParIterableLike$Copy;
            0      32     0 $this   Lscala/collection/parallel/ParMapLike;
            0      32     1  x2$2   Lscala/collection/parallel/ParIterable;
            0      32     2 cfactory$1   Lscala/collection/parallel/CombinerFactory;
    MethodParameters:
      Name                           Flags
      $this                          final synthetic
      x2$2                           final
      cfactory$1                     final

  public static scala.collection.parallel.Combiner $anonfun$concat$3(scala.collection.parallel.Combiner, scala.collection.parallel.Combiner);
    descriptor: (Lscala/collection/parallel/Combiner;Lscala/collection/parallel/Combiner;)Lscala/collection/parallel/Combiner;
    flags: (0x1009) ACC_PUBLIC, ACC_STATIC, ACC_SYNTHETIC
    Code:
      stack=2, locals=2, args_size=2
         0: aload_0
         1: aload_1
         2: invokeinterface #541,  2          // InterfaceMethod scala/collection/parallel/Combiner.combine:(Lscala/collection/parallel/Combiner;)Lscala/collection/parallel/Combiner;
         7: areturn
      LineNumberTable:
        line 254: 0
      LocalVariableTable:
        Start  Length  Slot  Name   Signature
            0       8     0  x$11   Lscala/collection/parallel/Combiner;
            0       8     1  x$12   Lscala/collection/parallel/Combiner;
    MethodParameters:
      Name                           Flags
      x$11                           final
      x$12                           final

  public static scala.collection.parallel.ParMap $anonfun$concat$4(scala.collection.parallel.Combiner);
    descriptor: (Lscala/collection/parallel/Combiner;)Lscala/collection/parallel/ParMap;
    flags: (0x1009) ACC_PUBLIC, ACC_STATIC, ACC_SYNTHETIC
    Code:
      stack=1, locals=1, args_size=1
         0: aload_0
         1: invokeinterface #527,  1          // InterfaceMethod scala/collection/parallel/Combiner.resultWithTaskSupport:()Ljava/lang/Object;
         6: checkcast     #82                 // class scala/collection/parallel/ParMap
         9: areturn
      LineNumberTable:
        line 255: 0
      LocalVariableTable:
        Start  Length  Slot  Name   Signature
            0      10     0  x$13   Lscala/collection/parallel/Combiner;
    MethodParameters:
      Name                           Flags
      x$13                           final

  public static scala.collection.parallel.Combiner $anonfun$concat$5(scala.collection.parallel.ParMapLike);
    descriptor: (Lscala/collection/parallel/ParMapLike;)Lscala/collection/parallel/Combiner;
    flags: (0x1009) ACC_PUBLIC, ACC_STATIC, ACC_SYNTHETIC
    Code:
      stack=1, locals=1, args_size=1
         0: aload_0
         1: invokeinterface #516,  1          // InterfaceMethod mapCompanion:()Lscala/collection/generic/GenericParMapCompanion;
         6: invokeinterface #521,  1          // InterfaceMethod scala/collection/generic/GenericParMapCompanion.newCombiner:()Lscala/collection/parallel/Combiner;
        11: areturn
      LineNumberTable:
        line 260: 0
      LocalVariableTable:
        Start  Length  Slot  Name   Signature
            0      12     0 $this   Lscala/collection/parallel/ParMapLike;
    MethodParameters:
      Name                           Flags
      $this                          final synthetic

  public static scala.collection.parallel.Combiner $anonfun$concat$6(scala.collection.parallel.ParMapLike, scala.collection.IterableOnce);
    descriptor: (Lscala/collection/parallel/ParMapLike;Lscala/collection/IterableOnce;)Lscala/collection/parallel/Combiner;
    flags: (0x1009) ACC_PUBLIC, ACC_STATIC, ACC_SYNTHETIC
    Code:
      stack=2, locals=3, args_size=2
         0: aload_0
         1: invokeinterface #516,  1          // InterfaceMethod mapCompanion:()Lscala/collection/generic/GenericParMapCompanion;
         6: invokeinterface #521,  1          // InterfaceMethod scala/collection/generic/GenericParMapCompanion.newCombiner:()Lscala/collection/parallel/Combiner;
        11: astore_2
        12: aload_2
        13: aload_1
        14: invokeinterface #547,  2          // InterfaceMethod scala/collection/parallel/Combiner.$plus$plus$eq:(Lscala/collection/IterableOnce;)Lscala/collection/mutable/Growable;
        19: pop
        20: aload_2
        21: areturn
      LineNumberTable:
        line 262: 0
        line 263: 12
        line 264: 20
      LocalVariableTable:
        Start  Length  Slot  Name   Signature
           12       9     2    cb   Lscala/collection/parallel/Combiner;
            0      22     0 $this   Lscala/collection/parallel/ParMapLike;
            0      22     1 that$1   Lscala/collection/IterableOnce;
    MethodParameters:
      Name                           Flags
      $this                          final synthetic
      that$1                         final

  public static scala.collection.parallel.Combiner $anonfun$concat$7(scala.collection.parallel.Combiner, scala.collection.parallel.Combiner);
    descriptor: (Lscala/collection/parallel/Combiner;Lscala/collection/parallel/Combiner;)Lscala/collection/parallel/Combiner;
    flags: (0x1009) ACC_PUBLIC, ACC_STATIC, ACC_SYNTHETIC
    Code:
      stack=2, locals=2, args_size=2
         0: aload_0
         1: aload_1
         2: invokeinterface #541,  2          // InterfaceMethod scala/collection/parallel/Combiner.combine:(Lscala/collection/parallel/Combiner;)Lscala/collection/parallel/Combiner;
         7: areturn
      LineNumberTable:
        line 266: 0
      LocalVariableTable:
        Start  Length  Slot  Name   Signature
            0       8     0  x$14   Lscala/collection/parallel/Combiner;
            0       8     1  x$15   Lscala/collection/parallel/Combiner;
    MethodParameters:
      Name                           Flags
      x$14                           final
      x$15                           final

  public static scala.collection.parallel.ParMap $anonfun$concat$8(scala.collection.parallel.Combiner);
    descriptor: (Lscala/collection/parallel/Combiner;)Lscala/collection/parallel/ParMap;
    flags: (0x1009) ACC_PUBLIC, ACC_STATIC, ACC_SYNTHETIC
    Code:
      stack=1, locals=1, args_size=1
         0: aload_0
         1: invokeinterface #527,  1          // InterfaceMethod scala/collection/parallel/Combiner.resultWithTaskSupport:()Ljava/lang/Object;
         6: checkcast     #82                 // class scala/collection/parallel/ParMap
         9: areturn
      LineNumberTable:
        line 266: 0
      LocalVariableTable:
        Start  Length  Slot  Name   Signature
            0      10     0  x$16   Lscala/collection/parallel/Combiner;
    MethodParameters:
      Name                           Flags
      x$16                           final

  public static void $init$(scala.collection.parallel.ParMapLike);
    descriptor: (Lscala/collection/parallel/ParMapLike;)V
    flags: (0x0009) ACC_PUBLIC, ACC_STATIC
    Code:
      stack=0, locals=1, args_size=1
         0: return
      LineNumberTable:
        line 37: 0
      LocalVariableTable:
        Start  Length  Slot  Name   Signature
            0       1     0 $this   Lscala/collection/parallel/ParMapLike;
    MethodParameters:
      Name                           Flags
      $this                          final synthetic

  public static java.lang.Object $anonfun$equals$1$adapted(scala.collection.parallel.ParMap, scala.Tuple2);
    descriptor: (Lscala/collection/parallel/ParMap;Lscala/Tuple2;)Ljava/lang/Object;
    flags: (0x1009) ACC_PUBLIC, ACC_STATIC, ACC_SYNTHETIC
    Code:
      stack=2, locals=2, args_size=2
         0: aload_0
         1: aload_1
         2: invokestatic  #554                // InterfaceMethod $anonfun$equals$1:(Lscala/collection/parallel/ParMap;Lscala/Tuple2;)Z
         5: invokestatic  #558                // Method scala/runtime/BoxesRunTime.boxToBoolean:(Z)Ljava/lang/Boolean;
         8: areturn
      LineNumberTable:
        line 61: 0
      LocalVariableTable:
        Start  Length  Slot  Name   Signature
            0       9     0  x2$1   Lscala/collection/parallel/ParMap;
            0       9     1  x0$1   Lscala/Tuple2;
    MethodParameters:
      Name                           Flags
      x2$1                           final
      x0$1                           final

  private static java.lang.Object $deserializeLambda$(java.lang.invoke.SerializedLambda);
    descriptor: (Ljava/lang/invoke/SerializedLambda;)Ljava/lang/Object;
    flags: (0x100a) ACC_PRIVATE, ACC_STATIC, ACC_SYNTHETIC
    Code:
      stack=1, locals=1, args_size=1
         0: aload_0
         1: invokedynamic #570,  0            // InvokeDynamic #15:lambdaDeserialize:(Ljava/lang/invoke/SerializedLambda;)Ljava/lang/Object;
         6: areturn
}
InnerClasses:
  public static final #18= #15 of #17;    // Lookup=class java/lang/invoke/MethodHandles$Lookup of class java/lang/invoke/MethodHandles
  public #21= #20 of #7;                  // Collect=class scala/collection/parallel/ParIterableLike$Collect of class scala/collection/parallel/ParIterableLike
  public #24= #23 of #7;                  // Copy=class scala/collection/parallel/ParIterableLike$Copy of class scala/collection/parallel/ParIterableLike
  public #27= #26 of #7;                  // FlatMap=class scala/collection/parallel/ParIterableLike$FlatMap of class scala/collection/parallel/ParIterableLike
  public #30= #29 of #7;                  // Map=class scala/collection/parallel/ParIterableLike$Map of class scala/collection/parallel/ParIterableLike
  public #33= #32 of #7;                  // NonDivisible=class scala/collection/parallel/ParIterableLike$NonDivisible of class scala/collection/parallel/ParIterableLike
  public abstract #36= #35 of #7;         // ParComposite=class scala/collection/parallel/ParIterableLike$ParComposite of class scala/collection/parallel/ParIterableLike
  public abstract #39= #38 of #7;         // ResultMapping=class scala/collection/parallel/ParIterableLike$ResultMapping of class scala/collection/parallel/ParIterableLike
  public #42= #41 of #7;                  // StrictSplitterCheckTask=class scala/collection/parallel/ParIterableLike$StrictSplitterCheckTask of class scala/collection/parallel/ParIterableLike
  public #45= #44 of #7;                  // TaskOps=class scala/collection/parallel/ParIterableLike$TaskOps of class scala/collection/parallel/ParIterableLike
  public final #47;                       // class scala/collection/parallel/ParMapLike$$anon$1
  public final #49;                       // class scala/collection/parallel/ParMapLike$$anon$2
  public final #51;                       // class scala/collection/parallel/ParMapLike$$anon$3
  public final #53;                       // class scala/collection/parallel/ParMapLike$$anon$4
  public #56= #55 of #2;                  // DefaultKeySet=class scala/collection/parallel/ParMapLike$DefaultKeySet of class scala/collection/parallel/ParMapLike
  public #59= #58 of #2;                  // DefaultValuesIterable=class scala/collection/parallel/ParMapLike$DefaultValuesIterable of class scala/collection/parallel/ParMapLike
Signature: #3                           // <K:Ljava/lang/Object;V:Ljava/lang/Object;CC::Lscala/collection/parallel/ParMap<Ljava/lang/Object;Ljava/lang/Object;>;Repr::Lscala/collection/parallel/ParMapLike<TK;TV;Lscala/collection/parallel/ParMap;TRepr;TSequential;>;:Lscala/collection/parallel/ParMap<TK;TV;>;Sequential::Lscala/collection/Map<TK;TV;>;:Lscala/collection/MapOps<TK;TV;Lscala/collection/Map;TSequential;>;>Ljava/lang/Object;Lscala/collection/parallel/ParIterableLike<Lscala/Tuple2<TK;TV;>;Lscala/collection/parallel/ParIterable;TRepr;TSequential;>;Lscala/Equals;
SourceFile: "ParMapLike.scala"
RuntimeVisibleAnnotations:
  0: #11(#12=s#13)
    scala.reflect.ScalaSignature(
      bytes="\u0006\u0005\t\u0005haB\u00181!\u0003\r\ta\u000e\u0005\u0006e\u0002!\ta\u001d\u0005\u0006o\u00021\t\u0001\u001f\u0005\u0006}\u0002!\ta \u0005\b\u0003\u0017\u0001A\u0011IA\u0007\u0011\u001d\t\t\u0002\u0001C!\u0003\'Aq!a\u0007\u0001\r\u0003\ti\u0002C\u0004\u0002H\u0001!\t!!\u0013\t\u000f\u0005e\u0003A\"\u0001\u0002\\!9\u0011q\f\u0001\u0007\u0002\u0005\u0005\u0004bBA9\u0001\u0011\u0005\u00111\u000f\u0005\b\u0003o\u0002a\u0011AA=\u0011\u001d\tY\b\u0001C\u0001\u0003{Bq!!!\u0001\t\u0003\t\u0019\tC\u0004\u0002\u0018\u0002!\t!!\'\t\u000f\u0005u\u0005\u0001\"\u0001\u0002 \"A\u00111\u0015\u0001!\n\u0013\t)\u000bC\u0004\u0002$\u0002!\t!a2\t\u0011\u0005%\u0007\u0001)C\u0005\u0003\u0017Dq!!3\u0001\t\u0003\t\tN\u0002\u0004\u0002T\u0002A\u0011Q\u001b\u0005\b\u0003;$B\u0011AAp\u0011\u001d\t9\n\u0006C\u0001\u0003KDq!!;\u0015\t\u0003\t9\rC\u0004\u0002\u001cQ!\t!a;\t\u000f\u0005eC\u0003\"\u0001\u0002r\"9\u0011Q\u001f\u000b\u0005\u0002\u0005]\bbBA})\u0011\u0005\u0013q\u001f\u0005\b\u0003w$B\u0011IA\u007f\u0011\u001d\u0011y\u0001\u0006C!\u0005#1aA!\u0007\u0001\u0011\tm\u0001bBAo=\u0011\u0005!q\u0004\u0005\b\u0003StB\u0011AAi\u0011\u001d\t)P\bC\u0001\u0003oDq!!?\u001f\t\u0003\n9\u0010C\u0004\u0002|z!\tEa\t\t\u000f\t=a\u0004\"\u0001\u00030!9!q\u0007\u0001\u0005\u0002\te\u0002b\u0002B\u001e\u0001\u0011\u0005!Q\b\u0005\b\u0005\u0003\u0002A\u0011\u0001B\"\u0011\u001d\u0011)\u0005\u0001C\u0001\u0005\u000fBqAa\u0014\u0001\t\u0003\u0011\t\u0006C\u0004\u0003b\u0001!\tAa\u0019\t\u000f\tm\u0004\u0001\"\u0001\u0003~!9!q\u0013\u0001\u0005\u0002\te\u0005b\u0002BZ\u0001\u0011\u0005!Q\u0017\u0005\b\u0005\u000b\u0004AQ\u0001Bd\u0005)\u0001\u0016M]\'ba2K7.\u001a\u0006\u0003cI\n\u0001\u0002]1sC2dW\r\u001c\u0006\u0003gQ\n!bY8mY\u0016\u001cG/[8o\u0015\u0005)\u0014!B:dC2\f7\u0001A\u000b\bq\u0019\u0003\u00161\u0005,b\'\u0011\u0001\u0011(P8\u0011\u0005iZT\"\u0001\u001b\n\u0005q\"$AB!osJ+g\r\u0005\u0004?\u007f\u0005\u0013V\u000bY\u0007\u0002a%\u0011\u0001\t\r\u0002\u0010!\u0006\u0014\u0018\n^3sC\ndW\rT5lKB!!H\u0011#P\u0013\t\u0019EG\u0001\u0004UkBdWM\r\t\u0003\u000b\u001ac\u0001\u0001B\u0003H\u0001\t\u0007\u0001JA\u0001L#\tIE\n\u0005\u0002;\u0015&\u00111\n\u000e\u0002\b\u001d>$\b.\u001b8h!\tQT*\u0003\u0002Oi\t\u0019\u0011I\\=\u0011\u0005\u0015\u0003FAB)\u0001\t\u000b\u0007\u0001JA\u0001W!\tq4+\u0003\u0002Ua\tY\u0001+\u0019:Ji\u0016\u0014\u0018M\u00197f!\t)e\u000b\u0002\u0004X\u0001\u0011\u0015\r\u0001\u0017\u0002\u0005%\u0016\u0004(/\u0005\u0002J3J\u0019!\f\u00188\u0007\tm\u0003\u0001!\u0017\u0002\ryI,g-\u001b8f[\u0016tGO\u0010\t\b}\u0001!u*X+a!\tqd,\u0003\u0002`a\t1\u0001+\u0019:NCB\u0004\"!R1\u0005\r\t\u0004AQ1\u0001d\u0005)\u0019V-];f]RL\u0017\r\\\t\u0003\u0013\u0012\u00142!\u001a4k\r\u0011Y\u0006\u0001\u00013\u0011\t\u001dDGiT\u0007\u0002e%\u0011\u0011N\r\u0002\u0004\u001b\u0006\u0004\bCB4l\t>k\u0007-\u0003\u0002me\t1Q*\u00199PaN\u0004\"a\u001a5\u0011\tyrFi\u0014\t\u0003uAL!!\u001d\u001b\u0003\r\u0015\u000bX/\u00197t\u0003\u0019!\u0013N\\5uIQ\tA\u000f\u0005\u0002;k&\u0011a\u000f\u000e\u0002\u0005+:LG/A\u0002hKR$\"!\u001f?\u0011\u0007iRx*\u0003\u0002|i\t1q\n\u001d;j_:DQ! \u0002A\u0002\u0011\u000b1a[3z\u0003!\u0019\u0017M\\#rk\u0006dG\u0003BA\u0001\u0003\u000f\u00012AOA\u0002\u0013\r\t)\u0001\u000e\u0002\b\u0005>|G.Z1o\u0011\u0019\tIa\u0001a\u0001\u0019\u0006!A\u000f[1u\u0003\u0019)\u0017/^1mgR!\u0011\u0011AA\b\u0011\u0019\tI\u0001\u0002a\u0001\u0019\u0006A\u0001.Y:i\u0007>$W\r\u0006\u0002\u0002\u0016A\u0019!(a\u0006\n\u0007\u0005eAGA\u0002J]R\fQ\u0001\n9mkN,B!a\b\u0002<Q!\u0011\u0011EA!!\u0019)\u00151\u0005#\u0002:\u0011A\u0011Q\u0005\u0001\u0005\u0006\u0004\t9C\u0001\u0002D\u0007V1\u0011\u0011FA\u0018\u0003k\t2!SA\u0016!\u0019qd,!\f\u00024A\u0019Q)a\f\u0005\u000f\u0005E\u00121\u0005b\u0001\u0011\n\t\u0001\fE\u0002F\u0003k!q!a\u000e\u0002$\t\u0007\u0001JA\u0001Z!\r)\u00151\b\u0003\b\u0003{1!\u0019AA \u0005\t1\u0016\'\u0005\u0002P\u0019\"9\u00111\t\u0004A\u0002\u0005\u0015\u0013AA6w!\u0015Q$\tRA\u001d\u0003\u001d)\b\u000fZ1uK\u0012,B!a\u0013\u0002RQ1\u0011QJA*\u0003+\u0002b!RA\u0012\t\u0006=\u0003cA#\u0002R\u00119\u0011QH\u0004C\u0002\u0005}\u0002\"B?\b\u0001\u0004!\u0005bBA,\u000f\u0001\u0007\u0011qJ\u0001\u0006m\u0006dW/Z\u0001\u0007I5Lg.^:\u0015\u0007U\u000bi\u0006C\u0003~\u0011\u0001\u0007A)\u0001\u0007nCB\u001cu.\u001c9b]&|g.\u0006\u0002\u0002dA1\u0011QMA6\u0003_j!!a\u001a\u000b\u0007\u0005%$\'A\u0004hK:,\'/[2\n\t\u00055\u0014q\r\u0002\u0017\u000f\u0016tWM]5d!\u0006\u0014X*\u00199D_6\u0004\u0018M\\5p]B\u0019Q)a\t\u0002\u000f\u0011,g-Y;miR\u0019q*!\u001e\t\u000buT\u0001\u0019\u0001#\u0002\u000b\u0015l\u0007\u000f^=\u0016\u0003U\u000bQ!\u00199qYf$2aTA@\u0011\u0015iH\u00021\u0001E\u0003%9W\r^(s\u000b2\u001cX-\u0006\u0003\u0002\u0006\u0006%ECBAD\u0003\u001b\u000by\tE\u0002F\u0003\u0013#q!a#\u000e\u0005\u0004\tyDA\u0001V\u0011\u0015iX\u00021\u0001E\u0011!\t\t(\u0004CA\u0002\u0005E\u0005#\u0002\u001e\u0002\u0014\u0006\u001d\u0015bAAKi\tAAHY=oC6,g(\u0001\u0005d_:$\u0018-\u001b8t)\u0011\t\t!a\'\t\u000but\u0001\u0019\u0001#\u0002\u0017%\u001cH)\u001a4j]\u0016$\u0017\t\u001e\u000b\u0005\u0003\u0003\t\t\u000bC\u0003~\u001f\u0001\u0007A)\u0001\u0007lKf\u001c\u0018\n^3sCR|\'\u000f\u0006\u0003\u0002(\u00065\u0006\u0003\u0002 \u0002*\u0012K1!a+1\u0005AIE/\u001a:bE2,7\u000b\u001d7jiR,\'\u000fC\u0004\u00020B\u0001\r!!-\u0002\u0003MTC!a-\u00026B!a(!+BW\t\t9\f\u0005\u0003\u0002:\u0006\rWBAA^\u0015\u0011\ti,a0\u0002\u0013Ut7\r[3dW\u0016$\'bAAai\u0005Q\u0011M\u001c8pi\u0006$\u0018n\u001c8\n\t\u0005\u0015\u00171\u0018\u0002\u0012k:\u001c\u0007.Z2lK\u00124\u0016M]5b]\u000e,WCAAT\u000391\u0018\r\\;fg&#XM]1u_J$B!!4\u0002PB!a(!+P\u0011\u001d\tyK\u0005a\u0001\u0003c+\"!!4\u0003\u001b\u0011+g-Y;mi.+\u0017pU3u\'\u0011!\u0012(a6\u0011\ty\nI\u000eR\u0005\u0004\u00037\u0004$A\u0002)beN+G/\u0001\u0004=S:LGO\u0010\u000b\u0003\u0003C\u00042!a9\u0015\u001b\u0005\u0001A\u0003BA\u0001\u0003ODQ! \fA\u0002\u0011\u000b\u0001b\u001d9mSR$XM\u001d\u000b\u0005\u0003/\fi\u000f\u0003\u0004\u0002pb\u0001\r\u0001R\u0001\u0005K2,W\u000e\u0006\u0003\u0002X\u0006M\bBBAx3\u0001\u0007A)\u0001\u0003tSj,WCAA\u000b\u0003%Ygn\\<o\'&TX-A\u0004g_J,\u0017m\u00195\u0016\t\u0005}(Q\u0002\u000b\u0004i\n\u0005\u0001b\u0002B\u00029\u0001\u0007!QA\u0001\u0002MB1!Ha\u0002E\u0005\u0017I1A!\u00035\u0005%1UO\\2uS>t\u0017\u0007E\u0002F\u0005\u001b!a!a#\u001d\u0005\u0004A\u0015aA:fcV\u0011!1\u0003\t\u0005O\nUA)C\u0002\u0003\u0018I\u00121aU3u\u0005U!UMZ1vYR4\u0016\r\\;fg&#XM]1cY\u0016\u001cBAH\u001d\u0003\u001eA\u0019ahU(\u0015\u0005\t\u0005\u0002cAAr=U!!Q\u0005B\u0017)\r!(q\u0005\u0005\b\u0005\u0007\u0019\u0003\u0019\u0001B\u0015!\u0019Q$qA(\u0003,A\u0019QI!\f\u0005\r\u0005-5E1\u0001I+\t\u0011\t\u0004\u0005\u0003h\u0005gy\u0015b\u0001B\u001be\tA\u0011\n^3sC\ndW-\u0001\u0004lKf\u001cV\r^\u000b\u0003\u0003/\fAa[3zgV\u0011!q\b\t\u0004}M#\u0015A\u0002<bYV,7/\u0006\u0002\u0003\u001e\u0005Qa-\u001b7uKJ\\U-_:\u0015\u00079\u0014I\u0005C\u0004\u0003L!\u0002\rA!\u0014\u0002\u0003A\u0004bA\u000fB\u0004\t\u0006\u0005\u0011!C7baZ\u000bG.^3t+\u0011\u0011\u0019F!\u0017\u0015\t\tU#Q\f\t\u0006}y#%q\u000b\t\u0004\u000b\neCA\u0002B.S\t\u0007\u0001JA\u0001T\u0011\u001d\u0011\u0019!\u000ba\u0001\u0005?\u0002bA\u000fB\u0004\u001f\n]\u0013aA7baV1!Q\rB6\u0005c\"BAa\u001a\u0003vA9Q)a\t\u0003j\t=\u0004cA#\u0003l\u00111!Q\u000e\u0016C\u0002!\u0013!a\u0013\u001a\u0011\u0007\u0015\u0013\t\b\u0002\u0004\u0003t)\u0012\r\u0001\u0013\u0002\u0003-JBqAa\u0001+\u0001\u0004\u00119\b\u0005\u0004;\u0005\u000f\t%\u0011\u0010\t\u0007u\t\u0013IGa\u001c\u0002\u000f\r|G\u000e\\3diV1!q\u0010BC\u0005\u0013#BA!!\u0003\fB9Q)a\t\u0003\u0004\n\u001d\u0005cA#\u0003\u0006\u00121!QN\u0016C\u0002!\u00032!\u0012BE\t\u0019\u0011\u0019h\u000bb\u0001\u0011\"9!QR\u0016A\u0002\t=\u0015A\u00019g!\u0019Q$\u0011S!\u0003\u0016&\u0019!1\u0013\u001b\u0003\u001fA\u000b\'\u000f^5bY\u001a+hn\u0019;j_:\u0004bA\u000f\"\u0003\u0004\n\u001d\u0015a\u00024mCRl\u0015\r]\u000b\u0007\u00057\u0013\tK!*\u0015\t\tu%q\u0015\t\b\u000b\u0006\r\"q\u0014BR!\r)%\u0011\u0015\u0003\u0007\u0005[b#\u0019\u0001%\u0011\u0007\u0015\u0013)\u000b\u0002\u0004\u0003t1\u0012\r\u0001\u0013\u0005\b\u0005\u0007a\u0003\u0019\u0001BU!\u0019Q$qA!\u0003,B)qM!,\u00032&\u0019!q\u0016\u001a\u0003\u0019%#XM]1cY\u0016|enY3\u0011\ri\u0012%q\u0014BR\u0003\u0019\u0019wN\\2biV!!q\u0017B_)\u0011\u0011ILa0\u0011\r\u0015\u000b\u0019\u0003\u0012B^!\r)%Q\u0018\u0003\b\u0005gj#\u0019AA \u0011\u001d\tI!\fa\u0001\u0005\u0003\u0004Ra\u001aBW\u0005\u0007\u0004RA\u000f\"E\u0005w\u000b!\u0002\n9mkN$\u0003\u000f\\;t+\u0011\u0011IMa4\u0015\t\t-\'\u0011\u001b\t\u0007\u000b\u0006\rBI!4\u0011\u0007\u0015\u0013y\rB\u0004\u0003t9\u0012\r!a\u0010\t\u000f\tMg\u00061\u0001\u0003V\u0006\u0011\u0001p\u001d\t\u0006O\n5&q\u001b\t\u0006u\t#%Q\u001a\u0015\u0004]\tm\u0007c\u0001\u001e\u0003^&\u0019!q\u001c\u001b\u0003\r%tG.\u001b8f\u0001"
    )
BootstrapMethods:
  0: #106 REF_invokeStatic java/lang/invoke/LambdaMetafactory.altMetafactory:(Ljava/lang/invoke/MethodHandles$Lookup;Ljava/lang/String;Ljava/lang/invoke/MethodType;[Ljava/lang/Object;)Ljava/lang/invoke/CallSite;
    Method arguments:
      #90 (Ljava/lang/Object;)Ljava/lang/Object;
      #95 REF_invokeStatic scala/collection/parallel/ParMapLike.$anonfun$equals$1$adapted:(Lscala/collection/parallel/ParMap;Lscala/Tuple2;)Ljava/lang/Object;
      #97 (Lscala/Tuple2;)Ljava/lang/Object;
      #98 5
      #99 1
      #97 (Lscala/Tuple2;)Ljava/lang/Object;
  1: #106 REF_invokeStatic java/lang/invoke/LambdaMetafactory.altMetafactory:(Ljava/lang/invoke/MethodHandles$Lookup;Ljava/lang/String;Ljava/lang/invoke/MethodType;[Ljava/lang/Object;)Ljava/lang/invoke/CallSite;
    Method arguments:
      #329 ()Ljava/lang/Object;
      #334 REF_invokeStatic scala/collection/parallel/ParMapLike.$anonfun$map$1:(Lscala/collection/parallel/ParMapLike;)Lscala/collection/parallel/Combiner;
      #336 ()Lscala/collection/parallel/Combiner;
      #98 5
      #99 1
      #336 ()Lscala/collection/parallel/Combiner;
  2: #106 REF_invokeStatic java/lang/invoke/LambdaMetafactory.altMetafactory:(Ljava/lang/invoke/MethodHandles$Lookup;Ljava/lang/String;Ljava/lang/invoke/MethodType;[Ljava/lang/Object;)Ljava/lang/invoke/CallSite;
    Method arguments:
      #90 (Ljava/lang/Object;)Ljava/lang/Object;
      #355 REF_invokeStatic scala/collection/parallel/ParMapLike.$anonfun$map$2:(Lscala/collection/parallel/Combiner;)Lscala/collection/parallel/ParMap;
      #356 (Lscala/collection/parallel/Combiner;)Lscala/collection/parallel/ParMap;
      #98 5
      #99 1
      #356 (Lscala/collection/parallel/Combiner;)Lscala/collection/parallel/ParMap;
  3: #106 REF_invokeStatic java/lang/invoke/LambdaMetafactory.altMetafactory:(Ljava/lang/invoke/MethodHandles$Lookup;Ljava/lang/String;Ljava/lang/invoke/MethodType;[Ljava/lang/Object;)Ljava/lang/invoke/CallSite;
    Method arguments:
      #329 ()Ljava/lang/Object;
      #382 REF_invokeStatic scala/collection/parallel/ParMapLike.$anonfun$collect$1:(Lscala/collection/parallel/ParMapLike;)Lscala/collection/parallel/Combiner;
      #336 ()Lscala/collection/parallel/Combiner;
      #98 5
      #99 1
      #336 ()Lscala/collection/parallel/Combiner;
  4: #106 REF_invokeStatic java/lang/invoke/LambdaMetafactory.altMetafactory:(Ljava/lang/invoke/MethodHandles$Lookup;Ljava/lang/String;Ljava/lang/invoke/MethodType;[Ljava/lang/Object;)Ljava/lang/invoke/CallSite;
    Method arguments:
      #90 (Ljava/lang/Object;)Ljava/lang/Object;
      #390 REF_invokeStatic scala/collection/parallel/ParMapLike.$anonfun$collect$2:(Lscala/collection/parallel/Combiner;)Lscala/collection/parallel/ParMap;
      #356 (Lscala/collection/parallel/Combiner;)Lscala/collection/parallel/ParMap;
      #98 5
      #99 1
      #356 (Lscala/collection/parallel/Combiner;)Lscala/collection/parallel/ParMap;
  5: #106 REF_invokeStatic java/lang/invoke/LambdaMetafactory.altMetafactory:(Ljava/lang/invoke/MethodHandles$Lookup;Ljava/lang/String;Ljava/lang/invoke/MethodType;[Ljava/lang/Object;)Ljava/lang/invoke/CallSite;
    Method arguments:
      #329 ()Ljava/lang/Object;
      #400 REF_invokeStatic scala/collection/parallel/ParMapLike.$anonfun$flatMap$1:(Lscala/collection/parallel/ParMapLike;)Lscala/collection/parallel/Combiner;
      #336 ()Lscala/collection/parallel/Combiner;
      #98 5
      #99 1
      #336 ()Lscala/collection/parallel/Combiner;
  6: #106 REF_invokeStatic java/lang/invoke/LambdaMetafactory.altMetafactory:(Ljava/lang/invoke/MethodHandles$Lookup;Ljava/lang/String;Ljava/lang/invoke/MethodType;[Ljava/lang/Object;)Ljava/lang/invoke/CallSite;
    Method arguments:
      #90 (Ljava/lang/Object;)Ljava/lang/Object;
      #406 REF_invokeStatic scala/collection/parallel/ParMapLike.$anonfun$flatMap$2:(Lscala/collection/parallel/Combiner;)Lscala/collection/parallel/ParMap;
      #356 (Lscala/collection/parallel/Combiner;)Lscala/collection/parallel/ParMap;
      #98 5
      #99 1
      #356 (Lscala/collection/parallel/Combiner;)Lscala/collection/parallel/ParMap;
  7: #106 REF_invokeStatic java/lang/invoke/LambdaMetafactory.altMetafactory:(Ljava/lang/invoke/MethodHandles$Lookup;Ljava/lang/String;Ljava/lang/invoke/MethodType;[Ljava/lang/Object;)Ljava/lang/invoke/CallSite;
    Method arguments:
      #329 ()Ljava/lang/Object;
      #421 REF_invokeStatic scala/collection/parallel/ParMapLike.$anonfun$concat$1:(Lscala/collection/parallel/ParMapLike;)Lscala/collection/parallel/Combiner;
      #336 ()Lscala/collection/parallel/Combiner;
      #98 5
      #99 1
      #336 ()Lscala/collection/parallel/Combiner;
  8: #106 REF_invokeStatic java/lang/invoke/LambdaMetafactory.altMetafactory:(Ljava/lang/invoke/MethodHandles$Lookup;Ljava/lang/String;Ljava/lang/invoke/MethodType;[Ljava/lang/Object;)Ljava/lang/invoke/CallSite;
    Method arguments:
      #329 ()Ljava/lang/Object;
      #430 REF_invokeStatic scala/collection/parallel/ParMapLike.$anonfun$concat$2:(Lscala/collection/parallel/ParMapLike;Lscala/collection/parallel/ParIterable;Lscala/collection/parallel/CombinerFactory;)Lscala/collection/parallel/Combiner;
      #336 ()Lscala/collection/parallel/Combiner;
      #98 5
      #99 1
      #336 ()Lscala/collection/parallel/Combiner;
  9: #106 REF_invokeStatic java/lang/invoke/LambdaMetafactory.altMetafactory:(Ljava/lang/invoke/MethodHandles$Lookup;Ljava/lang/String;Ljava/lang/invoke/MethodType;[Ljava/lang/Object;)Ljava/lang/invoke/CallSite;
    Method arguments:
      #439 (Ljava/lang/Object;Ljava/lang/Object;)Ljava/lang/Object;
      #444 REF_invokeStatic scala/collection/parallel/ParMapLike.$anonfun$concat$3:(Lscala/collection/parallel/Combiner;Lscala/collection/parallel/Combiner;)Lscala/collection/parallel/Combiner;
      #445 (Lscala/collection/parallel/Combiner;Lscala/collection/parallel/Combiner;)Lscala/collection/parallel/Combiner;
      #98 5
      #99 1
      #445 (Lscala/collection/parallel/Combiner;Lscala/collection/parallel/Combiner;)Lscala/collection/parallel/Combiner;
  10: #106 REF_invokeStatic java/lang/invoke/LambdaMetafactory.altMetafactory:(Ljava/lang/invoke/MethodHandles$Lookup;Ljava/lang/String;Ljava/lang/invoke/MethodType;[Ljava/lang/Object;)Ljava/lang/invoke/CallSite;
    Method arguments:
      #90 (Ljava/lang/Object;)Ljava/lang/Object;
      #456 REF_invokeStatic scala/collection/parallel/ParMapLike.$anonfun$concat$4:(Lscala/collection/parallel/Combiner;)Lscala/collection/parallel/ParMap;
      #356 (Lscala/collection/parallel/Combiner;)Lscala/collection/parallel/ParMap;
      #98 5
      #99 1
      #356 (Lscala/collection/parallel/Combiner;)Lscala/collection/parallel/ParMap;
  11: #106 REF_invokeStatic java/lang/invoke/LambdaMetafactory.altMetafactory:(Ljava/lang/invoke/MethodHandles$Lookup;Ljava/lang/String;Ljava/lang/invoke/MethodType;[Ljava/lang/Object;)Ljava/lang/invoke/CallSite;
    Method arguments:
      #329 ()Ljava/lang/Object;
      #461 REF_invokeStatic scala/collection/parallel/ParMapLike.$anonfun$concat$5:(Lscala/collection/parallel/ParMapLike;)Lscala/collection/parallel/Combiner;
      #336 ()Lscala/collection/parallel/Combiner;
      #98 5
      #99 1
      #336 ()Lscala/collection/parallel/Combiner;
  12: #106 REF_invokeStatic java/lang/invoke/LambdaMetafactory.altMetafactory:(Ljava/lang/invoke/MethodHandles$Lookup;Ljava/lang/String;Ljava/lang/invoke/MethodType;[Ljava/lang/Object;)Ljava/lang/invoke/CallSite;
    Method arguments:
      #329 ()Ljava/lang/Object;
      #467 REF_invokeStatic scala/collection/parallel/ParMapLike.$anonfun$concat$6:(Lscala/collection/parallel/ParMapLike;Lscala/collection/IterableOnce;)Lscala/collection/parallel/Combiner;
      #336 ()Lscala/collection/parallel/Combiner;
      #98 5
      #99 1
      #336 ()Lscala/collection/parallel/Combiner;
  13: #106 REF_invokeStatic java/lang/invoke/LambdaMetafactory.altMetafactory:(Ljava/lang/invoke/MethodHandles$Lookup;Ljava/lang/String;Ljava/lang/invoke/MethodType;[Ljava/lang/Object;)Ljava/lang/invoke/CallSite;
    Method arguments:
      #439 (Ljava/lang/Object;Ljava/lang/Object;)Ljava/lang/Object;
      #474 REF_invokeStatic scala/collection/parallel/ParMapLike.$anonfun$concat$7:(Lscala/collection/parallel/Combiner;Lscala/collection/parallel/Combiner;)Lscala/collection/parallel/Combiner;
      #445 (Lscala/collection/parallel/Combiner;Lscala/collection/parallel/Combiner;)Lscala/collection/parallel/Combiner;
      #98 5
      #99 1
      #445 (Lscala/collection/parallel/Combiner;Lscala/collection/parallel/Combiner;)Lscala/collection/parallel/Combiner;
  14: #106 REF_invokeStatic java/lang/invoke/LambdaMetafactory.altMetafactory:(Ljava/lang/invoke/MethodHandles$Lookup;Ljava/lang/String;Ljava/lang/invoke/MethodType;[Ljava/lang/Object;)Ljava/lang/invoke/CallSite;
    Method arguments:
      #90 (Ljava/lang/Object;)Ljava/lang/Object;
      #479 REF_invokeStatic scala/collection/parallel/ParMapLike.$anonfun$concat$8:(Lscala/collection/parallel/Combiner;)Lscala/collection/parallel/ParMap;
      #356 (Lscala/collection/parallel/Combiner;)Lscala/collection/parallel/ParMap;
      #98 5
      #99 1
      #356 (Lscala/collection/parallel/Combiner;)Lscala/collection/parallel/ParMap;
  15: #567 REF_invokeStatic scala/runtime/LambdaDeserialize.bootstrap:(Ljava/lang/invoke/MethodHandles$Lookup;Ljava/lang/String;Ljava/lang/invoke/MethodType;[Ljava/lang/invoke/MethodHandle;)Ljava/lang/invoke/CallSite;
    Method arguments:
      #382 REF_invokeStatic scala/collection/parallel/ParMapLike.$anonfun$collect$1:(Lscala/collection/parallel/ParMapLike;)Lscala/collection/parallel/Combiner;
      #390 REF_invokeStatic scala/collection/parallel/ParMapLike.$anonfun$collect$2:(Lscala/collection/parallel/Combiner;)Lscala/collection/parallel/ParMap;
      #421 REF_invokeStatic scala/collection/parallel/ParMapLike.$anonfun$concat$1:(Lscala/collection/parallel/ParMapLike;)Lscala/collection/parallel/Combiner;
      #430 REF_invokeStatic scala/collection/parallel/ParMapLike.$anonfun$concat$2:(Lscala/collection/parallel/ParMapLike;Lscala/collection/parallel/ParIterable;Lscala/collection/parallel/CombinerFactory;)Lscala/collection/parallel/Combiner;
      #444 REF_invokeStatic scala/collection/parallel/ParMapLike.$anonfun$concat$3:(Lscala/collection/parallel/Combiner;Lscala/collection/parallel/Combiner;)Lscala/collection/parallel/Combiner;
      #456 REF_invokeStatic scala/collection/parallel/ParMapLike.$anonfun$concat$4:(Lscala/collection/parallel/Combiner;)Lscala/collection/parallel/ParMap;
      #461 REF_invokeStatic scala/collection/parallel/ParMapLike.$anonfun$concat$5:(Lscala/collection/parallel/ParMapLike;)Lscala/collection/parallel/Combiner;
      #467 REF_invokeStatic scala/collection/parallel/ParMapLike.$anonfun$concat$6:(Lscala/collection/parallel/ParMapLike;Lscala/collection/IterableOnce;)Lscala/collection/parallel/Combiner;
      #474 REF_invokeStatic scala/collection/parallel/ParMapLike.$anonfun$concat$7:(Lscala/collection/parallel/Combiner;Lscala/collection/parallel/Combiner;)Lscala/collection/parallel/Combiner;
      #479 REF_invokeStatic scala/collection/parallel/ParMapLike.$anonfun$concat$8:(Lscala/collection/parallel/Combiner;)Lscala/collection/parallel/ParMap;
      #95 REF_invokeStatic scala/collection/parallel/ParMapLike.$anonfun$equals$1$adapted:(Lscala/collection/parallel/ParMap;Lscala/Tuple2;)Ljava/lang/Object;
      #400 REF_invokeStatic scala/collection/parallel/ParMapLike.$anonfun$flatMap$1:(Lscala/collection/parallel/ParMapLike;)Lscala/collection/parallel/Combiner;
      #406 REF_invokeStatic scala/collection/parallel/ParMapLike.$anonfun$flatMap$2:(Lscala/collection/parallel/Combiner;)Lscala/collection/parallel/ParMap;
      #334 REF_invokeStatic scala/collection/parallel/ParMapLike.$anonfun$map$1:(Lscala/collection/parallel/ParMapLike;)Lscala/collection/parallel/Combiner;
      #355 REF_invokeStatic scala/collection/parallel/ParMapLike.$anonfun$map$2:(Lscala/collection/parallel/Combiner;)Lscala/collection/parallel/ParMap;
  ScalaInlineInfo: length = 0x158 (unknown attribute)
   01 00 00 44 01 7B 01 4B 01 01 83 01 60 01 01 A2
   01 4B 01 01 AA 01 AB 01 01 B8 01 B9 01 01 C5 01
   60 01 01 CA 01 4B 01 01 CF 01 D0 01 01 D7 01 B9
   01 01 DC 01 60 01 01 F0 01 F1 01 00 5B 00 5C 01
   01 8D 01 4B 01 01 93 01 60 01 01 4A 01 4B 01 01
   5F 01 60 01 02 28 01 1D 01 00 9D 00 9E 00 00 89
   00 8A 00 01 ED 01 9B 05 01 EB 01 99 05 00 6B 00
   59 00 00 C4 00 A4 01 00 44 00 45 00 00 40 00 41
   01 01 75 01 76 00 01 72 01 73 01 01 9A 01 9B 00
   01 98 01 99 01 00 E9 00 45 00 00 E8 00 41 01 00
   A5 00 59 00 00 A3 00 A4 01 00 C1 00 C2 00 00 4C
   00 45 00 00 4B 00 41 01 01 30 01 31 00 01 2D 01
   2E 01 01 89 01 31 00 01 88 01 2E 01 00 3C 00 3D
   00 00 DE 00 DF 00 00 DC 00 DD 01 00 77 00 55 00
   00 75 00 76 01 00 F2 00 45 00 00 F1 00 41 01 01
   18 01 19 00 01 16 01 17 01 01 22 01 23 00 01 20
   01 21 01 01 03 01 04 00 01 01 01 02 01 01 41 01
   31 00 01 40 01 2E 01 00 A0 00 A1 00 01 3B 01 31
   00 01 39 01 2E 01 00 F8 00 F9 01 00 F5 00 F6 01
   01 0C 00 F9 01 01 0B 00 F6 01 00 90 00 91 00 00
   8D 00 8E 01 01 28 01 23 00 01 27 01 21 01 01 12
   01 04 00 01 11 01 02 01
  ScalaSig: length = 0x3 (unknown attribute)
   05 02 00
