Classfile /Users/mw/Projects/slang-braindump/.jar/jar8/assemble/slang-braindump/assemble/content/org/antlr/runtime/misc/DoubleKeyMap.class
  Last modified May 29, 2022; size 3045 bytes
  SHA-256 checksum a18aa16ed6237968dd960266e69f57dacbde2ebf5cbff26aa31368048d394e22
  Compiled from "DoubleKeyMap.java"
public class org.antlr.runtime.misc.DoubleKeyMap<Key1 extends java.lang.Object, Key2 extends java.lang.Object, Value extends java.lang.Object> extends java.lang.Object
  minor version: 0
  major version: 49
  flags: (0x0021) ACC_PUBLIC, ACC_SUPER
  this_class: #16                         // org/antlr/runtime/misc/DoubleKeyMap
  super_class: #17                        // java/lang/Object
  interfaces: 0, fields: 1, methods: 8, attributes: 2
Constant pool:
   #1 = Methodref          #17.#67        // java/lang/Object."<init>":()V
   #2 = Class              #68            // java/util/LinkedHashMap
   #3 = Methodref          #2.#67         // java/util/LinkedHashMap."<init>":()V
   #4 = Fieldref           #16.#69        // org/antlr/runtime/misc/DoubleKeyMap.data:Ljava/util/Map;
   #5 = InterfaceMethodref #6.#70         // java/util/Map.get:(Ljava/lang/Object;)Ljava/lang/Object;
   #6 = Class              #71            // java/util/Map
   #7 = InterfaceMethodref #6.#72         // java/util/Map.put:(Ljava/lang/Object;Ljava/lang/Object;)Ljava/lang/Object;
   #8 = InterfaceMethodref #6.#73         // java/util/Map.values:()Ljava/util/Collection;
   #9 = InterfaceMethodref #6.#74         // java/util/Map.keySet:()Ljava/util/Set;
  #10 = Class              #75            // java/util/HashSet
  #11 = Methodref          #10.#67        // java/util/HashSet."<init>":()V
  #12 = InterfaceMethodref #76.#77        // java/util/Collection.iterator:()Ljava/util/Iterator;
  #13 = InterfaceMethodref #78.#79        // java/util/Iterator.hasNext:()Z
  #14 = InterfaceMethodref #78.#80        // java/util/Iterator.next:()Ljava/lang/Object;
  #15 = InterfaceMethodref #81.#82        // java/util/Set.add:(Ljava/lang/Object;)Z
  #16 = Class              #83            // org/antlr/runtime/misc/DoubleKeyMap
  #17 = Class              #84            // java/lang/Object
  #18 = Utf8               data
  #19 = Utf8               Ljava/util/Map;
  #20 = Utf8               Signature
  #21 = Utf8               Ljava/util/Map<TKey1;Ljava/util/Map<TKey2;TValue;>;>;
  #22 = Utf8               <init>
  #23 = Utf8               ()V
  #24 = Utf8               Code
  #25 = Utf8               LineNumberTable
  #26 = Utf8               LocalVariableTable
  #27 = Utf8               this
  #28 = Utf8               Lorg/antlr/runtime/misc/DoubleKeyMap;
  #29 = Utf8               LocalVariableTypeTable
  #30 = Utf8               Lorg/antlr/runtime/misc/DoubleKeyMap<TKey1;TKey2;TValue;>;
  #31 = Utf8               put
  #32 = Utf8               (Ljava/lang/Object;Ljava/lang/Object;Ljava/lang/Object;)Ljava/lang/Object;
  #33 = Utf8               k1
  #34 = Utf8               Ljava/lang/Object;
  #35 = Utf8               k2
  #36 = Utf8               v
  #37 = Utf8               data2
  #38 = Utf8               prev
  #39 = Utf8               TKey1;
  #40 = Utf8               TKey2;
  #41 = Utf8               TValue;
  #42 = Utf8               Ljava/util/Map<TKey2;TValue;>;
  #43 = Utf8               (TKey1;TKey2;TValue;)TValue;
  #44 = Utf8               get
  #45 = Utf8               (Ljava/lang/Object;Ljava/lang/Object;)Ljava/lang/Object;
  #46 = Utf8               (TKey1;TKey2;)TValue;
  #47 = Utf8               (Ljava/lang/Object;)Ljava/util/Map;
  #48 = Utf8               (TKey1;)Ljava/util/Map<TKey2;TValue;>;
  #49 = Utf8               values
  #50 = Utf8               (Ljava/lang/Object;)Ljava/util/Collection;
  #51 = Utf8               (TKey1;)Ljava/util/Collection<TValue;>;
  #52 = Utf8               keySet
  #53 = Utf8               ()Ljava/util/Set;
  #54 = Utf8               ()Ljava/util/Set<TKey1;>;
  #55 = Utf8               (Ljava/lang/Object;)Ljava/util/Set;
  #56 = Utf8               (TKey1;)Ljava/util/Set<TKey2;>;
  #57 = Utf8               ()Ljava/util/Collection;
  #58 = Utf8               i$
  #59 = Utf8               Ljava/util/Iterator;
  #60 = Utf8               s
  #61 = Utf8               Ljava/util/Set;
  #62 = Utf8               Ljava/util/Set<TValue;>;
  #63 = Utf8               ()Ljava/util/Collection<TValue;>;
  #64 = Utf8               <Key1:Ljava/lang/Object;Key2:Ljava/lang/Object;Value:Ljava/lang/Object;>Ljava/lang/Object;
  #65 = Utf8               SourceFile
  #66 = Utf8               DoubleKeyMap.java
  #67 = NameAndType        #22:#23        // "<init>":()V
  #68 = Utf8               java/util/LinkedHashMap
  #69 = NameAndType        #18:#19        // data:Ljava/util/Map;
  #70 = NameAndType        #44:#85        // get:(Ljava/lang/Object;)Ljava/lang/Object;
  #71 = Utf8               java/util/Map
  #72 = NameAndType        #31:#45        // put:(Ljava/lang/Object;Ljava/lang/Object;)Ljava/lang/Object;
  #73 = NameAndType        #49:#57        // values:()Ljava/util/Collection;
  #74 = NameAndType        #52:#53        // keySet:()Ljava/util/Set;
  #75 = Utf8               java/util/HashSet
  #76 = Class              #86            // java/util/Collection
  #77 = NameAndType        #87:#88        // iterator:()Ljava/util/Iterator;
  #78 = Class              #89            // java/util/Iterator
  #79 = NameAndType        #90:#91        // hasNext:()Z
  #80 = NameAndType        #92:#93        // next:()Ljava/lang/Object;
  #81 = Class              #94            // java/util/Set
  #82 = NameAndType        #95:#96        // add:(Ljava/lang/Object;)Z
  #83 = Utf8               org/antlr/runtime/misc/DoubleKeyMap
  #84 = Utf8               java/lang/Object
  #85 = Utf8               (Ljava/lang/Object;)Ljava/lang/Object;
  #86 = Utf8               java/util/Collection
  #87 = Utf8               iterator
  #88 = Utf8               ()Ljava/util/Iterator;
  #89 = Utf8               java/util/Iterator
  #90 = Utf8               hasNext
  #91 = Utf8               ()Z
  #92 = Utf8               next
  #93 = Utf8               ()Ljava/lang/Object;
  #94 = Utf8               java/util/Set
  #95 = Utf8               add
  #96 = Utf8               (Ljava/lang/Object;)Z
{
  java.util.Map<Key1, java.util.Map<Key2, Value>> data;
    descriptor: Ljava/util/Map;
    flags: (0x0000)
    Signature: #21                          // Ljava/util/Map<TKey1;Ljava/util/Map<TKey2;TValue;>;>;

  public org.antlr.runtime.misc.DoubleKeyMap();
    descriptor: ()V
    flags: (0x0001) ACC_PUBLIC
    Code:
      stack=3, locals=1, args_size=1
         0: aload_0
         1: invokespecial #1                  // Method java/lang/Object."<init>":()V
         4: aload_0
         5: new           #2                  // class java/util/LinkedHashMap
         8: dup
         9: invokespecial #3                  // Method java/util/LinkedHashMap."<init>":()V
        12: putfield      #4                  // Field data:Ljava/util/Map;
        15: return
      LineNumberTable:
        line 9: 0
        line 10: 4
      LocalVariableTable:
        Start  Length  Slot  Name   Signature
            0      16     0  this   Lorg/antlr/runtime/misc/DoubleKeyMap;
      LocalVariableTypeTable:
        Start  Length  Slot  Name   Signature
            0      16     0  this   Lorg/antlr/runtime/misc/DoubleKeyMap<TKey1;TKey2;TValue;>;

  public Value put(Key1, Key2, Value);
    descriptor: (Ljava/lang/Object;Ljava/lang/Object;Ljava/lang/Object;)Ljava/lang/Object;
    flags: (0x0001) ACC_PUBLIC
    Code:
      stack=3, locals=6, args_size=4
         0: aload_0
         1: getfield      #4                  // Field data:Ljava/util/Map;
         4: aload_1
         5: invokeinterface #5,  2            // InterfaceMethod java/util/Map.get:(Ljava/lang/Object;)Ljava/lang/Object;
        10: checkcast     #6                  // class java/util/Map
        13: astore        4
        15: aconst_null
        16: astore        5
        18: aload         4
        20: ifnonnull     48
        23: new           #2                  // class java/util/LinkedHashMap
        26: dup
        27: invokespecial #3                  // Method java/util/LinkedHashMap."<init>":()V
        30: astore        4
        32: aload_0
        33: getfield      #4                  // Field data:Ljava/util/Map;
        36: aload_1
        37: aload         4
        39: invokeinterface #7,  3            // InterfaceMethod java/util/Map.put:(Ljava/lang/Object;Ljava/lang/Object;)Ljava/lang/Object;
        44: pop
        45: goto          58
        48: aload         4
        50: aload_2
        51: invokeinterface #5,  2            // InterfaceMethod java/util/Map.get:(Ljava/lang/Object;)Ljava/lang/Object;
        56: astore        5
        58: aload         4
        60: aload_2
        61: aload_3
        62: invokeinterface #7,  3            // InterfaceMethod java/util/Map.put:(Ljava/lang/Object;Ljava/lang/Object;)Ljava/lang/Object;
        67: pop
        68: aload         5
        70: areturn
      LineNumberTable:
        line 13: 0
        line 14: 15
        line 15: 18
        line 16: 23
        line 17: 32
        line 20: 48
        line 22: 58
        line 23: 68
      LocalVariableTable:
        Start  Length  Slot  Name   Signature
            0      71     0  this   Lorg/antlr/runtime/misc/DoubleKeyMap;
            0      71     1    k1   Ljava/lang/Object;
            0      71     2    k2   Ljava/lang/Object;
            0      71     3     v   Ljava/lang/Object;
           15      56     4 data2   Ljava/util/Map;
           18      53     5  prev   Ljava/lang/Object;
      LocalVariableTypeTable:
        Start  Length  Slot  Name   Signature
            0      71     0  this   Lorg/antlr/runtime/misc/DoubleKeyMap<TKey1;TKey2;TValue;>;
            0      71     1    k1   TKey1;
            0      71     2    k2   TKey2;
            0      71     3     v   TValue;
           15      56     4 data2   Ljava/util/Map<TKey2;TValue;>;
           18      53     5  prev   TValue;
    Signature: #43                          // (TKey1;TKey2;TValue;)TValue;

  public Value get(Key1, Key2);
    descriptor: (Ljava/lang/Object;Ljava/lang/Object;)Ljava/lang/Object;
    flags: (0x0001) ACC_PUBLIC
    Code:
      stack=2, locals=4, args_size=3
         0: aload_0
         1: getfield      #4                  // Field data:Ljava/util/Map;
         4: aload_1
         5: invokeinterface #5,  2            // InterfaceMethod java/util/Map.get:(Ljava/lang/Object;)Ljava/lang/Object;
        10: checkcast     #6                  // class java/util/Map
        13: astore_3
        14: aload_3
        15: ifnonnull     20
        18: aconst_null
        19: areturn
        20: aload_3
        21: aload_2
        22: invokeinterface #5,  2            // InterfaceMethod java/util/Map.get:(Ljava/lang/Object;)Ljava/lang/Object;
        27: areturn
      LineNumberTable:
        line 27: 0
        line 28: 14
        line 29: 20
      LocalVariableTable:
        Start  Length  Slot  Name   Signature
            0      28     0  this   Lorg/antlr/runtime/misc/DoubleKeyMap;
            0      28     1    k1   Ljava/lang/Object;
            0      28     2    k2   Ljava/lang/Object;
           14      14     3 data2   Ljava/util/Map;
      LocalVariableTypeTable:
        Start  Length  Slot  Name   Signature
            0      28     0  this   Lorg/antlr/runtime/misc/DoubleKeyMap<TKey1;TKey2;TValue;>;
            0      28     1    k1   TKey1;
            0      28     2    k2   TKey2;
           14      14     3 data2   Ljava/util/Map<TKey2;TValue;>;
    Signature: #46                          // (TKey1;TKey2;)TValue;

  public java.util.Map<Key2, Value> get(Key1);
    descriptor: (Ljava/lang/Object;)Ljava/util/Map;
    flags: (0x0001) ACC_PUBLIC
    Code:
      stack=2, locals=2, args_size=2
         0: aload_0
         1: getfield      #4                  // Field data:Ljava/util/Map;
         4: aload_1
         5: invokeinterface #5,  2            // InterfaceMethod java/util/Map.get:(Ljava/lang/Object;)Ljava/lang/Object;
        10: checkcast     #6                  // class java/util/Map
        13: areturn
      LineNumberTable:
        line 32: 0
      LocalVariableTable:
        Start  Length  Slot  Name   Signature
            0      14     0  this   Lorg/antlr/runtime/misc/DoubleKeyMap;
            0      14     1    k1   Ljava/lang/Object;
      LocalVariableTypeTable:
        Start  Length  Slot  Name   Signature
            0      14     0  this   Lorg/antlr/runtime/misc/DoubleKeyMap<TKey1;TKey2;TValue;>;
            0      14     1    k1   TKey1;
    Signature: #48                          // (TKey1;)Ljava/util/Map<TKey2;TValue;>;

  public java.util.Collection<Value> values(Key1);
    descriptor: (Ljava/lang/Object;)Ljava/util/Collection;
    flags: (0x0001) ACC_PUBLIC
    Code:
      stack=2, locals=3, args_size=2
         0: aload_0
         1: getfield      #4                  // Field data:Ljava/util/Map;
         4: aload_1
         5: invokeinterface #5,  2            // InterfaceMethod java/util/Map.get:(Ljava/lang/Object;)Ljava/lang/Object;
        10: checkcast     #6                  // class java/util/Map
        13: astore_2
        14: aload_2
        15: ifnonnull     20
        18: aconst_null
        19: areturn
        20: aload_2
        21: invokeinterface #8,  1            // InterfaceMethod java/util/Map.values:()Ljava/util/Collection;
        26: areturn
      LineNumberTable:
        line 36: 0
        line 37: 14
        line 38: 20
      LocalVariableTable:
        Start  Length  Slot  Name   Signature
            0      27     0  this   Lorg/antlr/runtime/misc/DoubleKeyMap;
            0      27     1    k1   Ljava/lang/Object;
           14      13     2 data2   Ljava/util/Map;
      LocalVariableTypeTable:
        Start  Length  Slot  Name   Signature
            0      27     0  this   Lorg/antlr/runtime/misc/DoubleKeyMap<TKey1;TKey2;TValue;>;
            0      27     1    k1   TKey1;
           14      13     2 data2   Ljava/util/Map<TKey2;TValue;>;
    Signature: #51                          // (TKey1;)Ljava/util/Collection<TValue;>;

  public java.util.Set<Key1> keySet();
    descriptor: ()Ljava/util/Set;
    flags: (0x0001) ACC_PUBLIC
    Code:
      stack=1, locals=1, args_size=1
         0: aload_0
         1: getfield      #4                  // Field data:Ljava/util/Map;
         4: invokeinterface #9,  1            // InterfaceMethod java/util/Map.keySet:()Ljava/util/Set;
         9: areturn
      LineNumberTable:
        line 43: 0
      LocalVariableTable:
        Start  Length  Slot  Name   Signature
            0      10     0  this   Lorg/antlr/runtime/misc/DoubleKeyMap;
      LocalVariableTypeTable:
        Start  Length  Slot  Name   Signature
            0      10     0  this   Lorg/antlr/runtime/misc/DoubleKeyMap<TKey1;TKey2;TValue;>;
    Signature: #54                          // ()Ljava/util/Set<TKey1;>;

  public java.util.Set<Key2> keySet(Key1);
    descriptor: (Ljava/lang/Object;)Ljava/util/Set;
    flags: (0x0001) ACC_PUBLIC
    Code:
      stack=2, locals=3, args_size=2
         0: aload_0
         1: getfield      #4                  // Field data:Ljava/util/Map;
         4: aload_1
         5: invokeinterface #5,  2            // InterfaceMethod java/util/Map.get:(Ljava/lang/Object;)Ljava/lang/Object;
        10: checkcast     #6                  // class java/util/Map
        13: astore_2
        14: aload_2
        15: ifnonnull     20
        18: aconst_null
        19: areturn
        20: aload_2
        21: invokeinterface #9,  1            // InterfaceMethod java/util/Map.keySet:()Ljava/util/Set;
        26: areturn
      LineNumberTable:
        line 48: 0
        line 49: 14
        line 50: 20
      LocalVariableTable:
        Start  Length  Slot  Name   Signature
            0      27     0  this   Lorg/antlr/runtime/misc/DoubleKeyMap;
            0      27     1    k1   Ljava/lang/Object;
           14      13     2 data2   Ljava/util/Map;
      LocalVariableTypeTable:
        Start  Length  Slot  Name   Signature
            0      27     0  this   Lorg/antlr/runtime/misc/DoubleKeyMap<TKey1;TKey2;TValue;>;
            0      27     1    k1   TKey1;
           14      13     2 data2   Ljava/util/Map<TKey2;TValue;>;
    Signature: #56                          // (TKey1;)Ljava/util/Set<TKey2;>;

  public java.util.Collection<Value> values();
    descriptor: ()Ljava/util/Collection;
    flags: (0x0001) ACC_PUBLIC
    Code:
      stack=2, locals=6, args_size=1
         0: new           #10                 // class java/util/HashSet
         3: dup
         4: invokespecial #11                 // Method java/util/HashSet."<init>":()V
         7: astore_1
         8: aload_0
         9: getfield      #4                  // Field data:Ljava/util/Map;
        12: invokeinterface #8,  1            // InterfaceMethod java/util/Map.values:()Ljava/util/Collection;
        17: invokeinterface #12,  1           // InterfaceMethod java/util/Collection.iterator:()Ljava/util/Iterator;
        22: astore_2
        23: aload_2
        24: invokeinterface #13,  1           // InterfaceMethod java/util/Iterator.hasNext:()Z
        29: ifeq          89
        32: aload_2
        33: invokeinterface #14,  1           // InterfaceMethod java/util/Iterator.next:()Ljava/lang/Object;
        38: checkcast     #6                  // class java/util/Map
        41: astore_3
        42: aload_3
        43: invokeinterface #8,  1            // InterfaceMethod java/util/Map.values:()Ljava/util/Collection;
        48: invokeinterface #12,  1           // InterfaceMethod java/util/Collection.iterator:()Ljava/util/Iterator;
        53: astore        4
        55: aload         4
        57: invokeinterface #13,  1           // InterfaceMethod java/util/Iterator.hasNext:()Z
        62: ifeq          86
        65: aload         4
        67: invokeinterface #14,  1           // InterfaceMethod java/util/Iterator.next:()Ljava/lang/Object;
        72: astore        5
        74: aload_1
        75: aload         5
        77: invokeinterface #15,  2           // InterfaceMethod java/util/Set.add:(Ljava/lang/Object;)Z
        82: pop
        83: goto          55
        86: goto          23
        89: aload_1
        90: areturn
      LineNumberTable:
        line 54: 0
        line 55: 8
        line 56: 42
        line 57: 74
        line 58: 83
        line 59: 86
        line 60: 89
      LocalVariableTable:
        Start  Length  Slot  Name   Signature
           74       9     5     v   Ljava/lang/Object;
           55      31     4    i$   Ljava/util/Iterator;
           42      44     3    k2   Ljava/util/Map;
           23      66     2    i$   Ljava/util/Iterator;
            0      91     0  this   Lorg/antlr/runtime/misc/DoubleKeyMap;
            8      83     1     s   Ljava/util/Set;
      LocalVariableTypeTable:
        Start  Length  Slot  Name   Signature
           74       9     5     v   TValue;
           42      44     3    k2   Ljava/util/Map<TKey2;TValue;>;
            0      91     0  this   Lorg/antlr/runtime/misc/DoubleKeyMap<TKey1;TKey2;TValue;>;
            8      83     1     s   Ljava/util/Set<TValue;>;
    Signature: #63                          // ()Ljava/util/Collection<TValue;>;
}
Signature: #64                          // <Key1:Ljava/lang/Object;Key2:Ljava/lang/Object;Value:Ljava/lang/Object;>Ljava/lang/Object;
SourceFile: "DoubleKeyMap.java"
