Classfile /Users/mw/Projects/slang-braindump/.jar/jar11/assemble/slang-braindump/assemble/content/coursier/maven/PomParser$$anon$2.class
  Last modified May 29, 2022; size 3782 bytes
  SHA-256 checksum a735ecfca5d4a8b8483e716364a519ada844fd494f05ae4b7187a9107ea49e28
  Compiled from "PomParser.scala"
public final class coursier.maven.PomParser$$anon$2 extends coursier.maven.PomParser$SectionHandler
  minor version: 0
  major version: 52
  flags: (0x0031) ACC_PUBLIC, ACC_FINAL, ACC_SUPER
  this_class: #2                          // coursier/maven/PomParser$$anon$2
  super_class: #4                         // coursier/maven/PomParser$SectionHandler
  interfaces: 0, fields: 1, methods: 3, attributes: 5
Constant pool:
    #1 = Utf8               coursier/maven/PomParser$$anon$2
    #2 = Class              #1            // coursier/maven/PomParser$$anon$2
    #3 = Utf8               coursier/maven/PomParser$SectionHandler
    #4 = Class              #3            // coursier/maven/PomParser$SectionHandler
    #5 = Utf8               PomParser.scala
    #6 = Utf8               coursier/maven/PomParser$
    #7 = Class              #6            // coursier/maven/PomParser$
    #8 = Utf8               profileHandlers
    #9 = Utf8               (Lscala/collection/immutable/List;Lscala/Function2;)Lscala/collection/immutable/Seq;
   #10 = NameAndType        #8:#9         // profileHandlers:(Lscala/collection/immutable/List;Lscala/Function2;)Lscala/collection/immutable/Seq;
   #11 = Utf8               coursier/core/Activation$Os
   #12 = Class              #11           // coursier/core/Activation$Os
   #13 = Utf8               coursier/core/Activation
   #14 = Class              #13           // coursier/core/Activation
   #15 = Utf8               Os
   #16 = Utf8               coursier/core/Activation$Os$
   #17 = Class              #16           // coursier/core/Activation$Os$
   #18 = Utf8
   #19 = Utf8               coursier/maven/PomParser
   #20 = Class              #19           // coursier/maven/PomParser
   #21 = Utf8               SectionHandler
   #22 = Utf8               coursier/maven/PomParser$State
   #23 = Class              #22           // coursier/maven/PomParser$State
   #24 = Utf8               State
   #25 = Utf8               add$1
   #26 = Utf8               Lscala/Function2;
   #27 = Utf8               start
   #28 = Utf8               (Lcoursier/maven/PomParser$State;)V
   #29 = Utf8               state
   #30 = String             #18           //
   #31 = Utf8               profileId_$eq
   #32 = Utf8               (Ljava/lang/String;)V
   #33 = NameAndType        #31:#32       // profileId_$eq:(Ljava/lang/String;)V
   #34 = Methodref          #23.#33       // coursier/maven/PomParser$State.profileId_$eq:(Ljava/lang/String;)V
   #35 = Utf8               scala/None$
   #36 = Class              #35           // scala/None$
   #37 = Utf8               MODULE$
   #38 = Utf8               Lscala/None$;
   #39 = NameAndType        #37:#38       // MODULE$:Lscala/None$;
   #40 = Fieldref           #36.#39       // scala/None$.MODULE$:Lscala/None$;
   #41 = Utf8               profileActiveByDefaultOpt_$eq
   #42 = Utf8               (Lscala/Option;)V
   #43 = NameAndType        #41:#42       // profileActiveByDefaultOpt_$eq:(Lscala/Option;)V
   #44 = Methodref          #23.#43       // coursier/maven/PomParser$State.profileActiveByDefaultOpt_$eq:(Lscala/Option;)V
   #45 = Utf8               profileDependencies
   #46 = Utf8               ()Lscala/collection/mutable/ListBuffer;
   #47 = NameAndType        #45:#46       // profileDependencies:()Lscala/collection/mutable/ListBuffer;
   #48 = Methodref          #23.#47       // coursier/maven/PomParser$State.profileDependencies:()Lscala/collection/mutable/ListBuffer;
   #49 = Utf8               scala/collection/mutable/ListBuffer
   #50 = Class              #49           // scala/collection/mutable/ListBuffer
   #51 = Utf8               clear
   #52 = Utf8               ()V
   #53 = NameAndType        #51:#52       // clear:()V
   #54 = Methodref          #50.#53       // scala/collection/mutable/ListBuffer.clear:()V
   #55 = Utf8               profileDependencyManagement
   #56 = NameAndType        #55:#46       // profileDependencyManagement:()Lscala/collection/mutable/ListBuffer;
   #57 = Methodref          #23.#56       // coursier/maven/PomParser$State.profileDependencyManagement:()Lscala/collection/mutable/ListBuffer;
   #58 = Utf8               scala/Predef$
   #59 = Class              #58           // scala/Predef$
   #60 = Utf8               Lscala/Predef$;
   #61 = NameAndType        #37:#60       // MODULE$:Lscala/Predef$;
   #62 = Fieldref           #59.#61       // scala/Predef$.MODULE$:Lscala/Predef$;
   #63 = Utf8               Map
   #64 = Utf8               ()Lscala/collection/immutable/Map$;
   #65 = NameAndType        #63:#64       // Map:()Lscala/collection/immutable/Map$;
   #66 = Methodref          #59.#65       // scala/Predef$.Map:()Lscala/collection/immutable/Map$;
   #67 = Utf8               scala/collection/immutable/Map$
   #68 = Class              #67           // scala/collection/immutable/Map$
   #69 = Utf8               empty
   #70 = Utf8               ()Lscala/collection/immutable/Map;
   #71 = NameAndType        #69:#70       // empty:()Lscala/collection/immutable/Map;
   #72 = Methodref          #68.#71       // scala/collection/immutable/Map$.empty:()Lscala/collection/immutable/Map;
   #73 = Utf8               profileProperties_$eq
   #74 = Utf8               (Lscala/collection/immutable/Map;)V
   #75 = NameAndType        #73:#74       // profileProperties_$eq:(Lscala/collection/immutable/Map;)V
   #76 = Methodref          #23.#75       // coursier/maven/PomParser$State.profileProperties_$eq:(Lscala/collection/immutable/Map;)V
   #77 = Utf8               profileActivationProperties
   #78 = NameAndType        #77:#46       // profileActivationProperties:()Lscala/collection/mutable/ListBuffer;
   #79 = Methodref          #23.#78       // coursier/maven/PomParser$State.profileActivationProperties:()Lscala/collection/mutable/ListBuffer;
   #80 = Utf8               profileActivationOsArchOpt_$eq
   #81 = NameAndType        #80:#42       // profileActivationOsArchOpt_$eq:(Lscala/Option;)V
   #82 = Methodref          #23.#81       // coursier/maven/PomParser$State.profileActivationOsArchOpt_$eq:(Lscala/Option;)V
   #83 = Utf8               profileActivationOsFamilyOpt_$eq
   #84 = NameAndType        #83:#42       // profileActivationOsFamilyOpt_$eq:(Lscala/Option;)V
   #85 = Methodref          #23.#84       // coursier/maven/PomParser$State.profileActivationOsFamilyOpt_$eq:(Lscala/Option;)V
   #86 = Utf8               profileActivationOsNameOpt_$eq
   #87 = NameAndType        #86:#42       // profileActivationOsNameOpt_$eq:(Lscala/Option;)V
   #88 = Methodref          #23.#87       // coursier/maven/PomParser$State.profileActivationOsNameOpt_$eq:(Lscala/Option;)V
   #89 = Utf8               profileActivationOsVersionOpt_$eq
   #90 = NameAndType        #89:#42       // profileActivationOsVersionOpt_$eq:(Lscala/Option;)V
   #91 = Methodref          #23.#90       // coursier/maven/PomParser$State.profileActivationOsVersionOpt_$eq:(Lscala/Option;)V
   #92 = Utf8               profileActivationJdkOpt_$eq
   #93 = NameAndType        #92:#42       // profileActivationJdkOpt_$eq:(Lscala/Option;)V
   #94 = Methodref          #23.#93       // coursier/maven/PomParser$State.profileActivationJdkOpt_$eq:(Lscala/Option;)V
   #95 = Utf8               this
   #96 = Utf8               Lcoursier/maven/PomParser$$anon$2;
   #97 = Utf8               Lcoursier/maven/PomParser$State;
   #98 = Utf8               end
   #99 = Utf8               coursier/core/Profile$
  #100 = Class              #99           // coursier/core/Profile$
  #101 = Utf8               Lcoursier/core/Profile$;
  #102 = NameAndType        #37:#101      // MODULE$:Lcoursier/core/Profile$;
  #103 = Fieldref           #100.#102     // coursier/core/Profile$.MODULE$:Lcoursier/core/Profile$;
  #104 = Utf8               profileId
  #105 = Utf8               ()Ljava/lang/String;
  #106 = NameAndType        #104:#105     // profileId:()Ljava/lang/String;
  #107 = Methodref          #23.#106      // coursier/maven/PomParser$State.profileId:()Ljava/lang/String;
  #108 = Utf8               profileActiveByDefaultOpt
  #109 = Utf8               ()Lscala/Option;
  #110 = NameAndType        #108:#109     // profileActiveByDefaultOpt:()Lscala/Option;
  #111 = Methodref          #23.#110      // coursier/maven/PomParser$State.profileActiveByDefaultOpt:()Lscala/Option;
  #112 = Utf8               coursier/core/Activation$
  #113 = Class              #112          // coursier/core/Activation$
  #114 = Utf8               Lcoursier/core/Activation$;
  #115 = NameAndType        #37:#114      // MODULE$:Lcoursier/core/Activation$;
  #116 = Fieldref           #113.#115     // coursier/core/Activation$.MODULE$:Lcoursier/core/Activation$;
  #117 = Utf8               toList
  #118 = Utf8               ()Lscala/collection/immutable/List;
  #119 = NameAndType        #117:#118     // toList:()Lscala/collection/immutable/List;
  #120 = Methodref          #50.#119      // scala/collection/mutable/ListBuffer.toList:()Lscala/collection/immutable/List;
  #121 = Utf8               Lcoursier/core/Activation$Os$;
  #122 = NameAndType        #37:#121      // MODULE$:Lcoursier/core/Activation$Os$;
  #123 = Fieldref           #17.#122      // coursier/core/Activation$Os$.MODULE$:Lcoursier/core/Activation$Os$;
  #124 = Utf8               profileActivationOsArchOpt
  #125 = NameAndType        #124:#109     // profileActivationOsArchOpt:()Lscala/Option;
  #126 = Methodref          #23.#125      // coursier/maven/PomParser$State.profileActivationOsArchOpt:()Lscala/Option;
  #127 = Utf8               scala/Option$
  #128 = Class              #127          // scala/Option$
  #129 = Utf8               Lscala/Option$;
  #130 = NameAndType        #37:#129      // MODULE$:Lscala/Option$;
  #131 = Fieldref           #128.#130     // scala/Option$.MODULE$:Lscala/Option$;
  #132 = Utf8               profileActivationOsFamilyOpt
  #133 = NameAndType        #132:#109     // profileActivationOsFamilyOpt:()Lscala/Option;
  #134 = Methodref          #23.#133      // coursier/maven/PomParser$State.profileActivationOsFamilyOpt:()Lscala/Option;
  #135 = Utf8               option2Iterable
  #136 = Utf8               (Lscala/Option;)Lscala/collection/Iterable;
  #137 = NameAndType        #135:#136     // option2Iterable:(Lscala/Option;)Lscala/collection/Iterable;
  #138 = Methodref          #128.#137     // scala/Option$.option2Iterable:(Lscala/Option;)Lscala/collection/Iterable;
  #139 = Utf8               scala/collection/Iterable
  #140 = Class              #139          // scala/collection/Iterable
  #141 = Utf8               toSet
  #142 = Utf8               ()Lscala/collection/immutable/Set;
  #143 = NameAndType        #141:#142     // toSet:()Lscala/collection/immutable/Set;
  #144 = InterfaceMethodref #140.#143     // scala/collection/Iterable.toSet:()Lscala/collection/immutable/Set;
  #145 = Utf8               profileActivationOsNameOpt
  #146 = NameAndType        #145:#109     // profileActivationOsNameOpt:()Lscala/Option;
  #147 = Methodref          #23.#146      // coursier/maven/PomParser$State.profileActivationOsNameOpt:()Lscala/Option;
  #148 = Utf8               profileActivationOsVersionOpt
  #149 = NameAndType        #148:#109     // profileActivationOsVersionOpt:()Lscala/Option;
  #150 = Methodref          #23.#149      // coursier/maven/PomParser$State.profileActivationOsVersionOpt:()Lscala/Option;
  #151 = Utf8               apply
  #152 = Utf8               (Lscala/Option;Lscala/collection/immutable/Set;Lscala/Option;Lscala/Option;)Lcoursier/core/Activation$Os;
  #153 = NameAndType        #151:#152     // apply:(Lscala/Option;Lscala/collection/immutable/Set;Lscala/Option;Lscala/Option;)Lcoursier/core/Activation$Os;
  #154 = Methodref          #17.#153      // coursier/core/Activation$Os$.apply:(Lscala/Option;Lscala/collection/immutable/Set;Lscala/Option;Lscala/Option;)Lcoursier/core/Activation$Os;
  #155 = Utf8               profileActivationJdkOpt
  #156 = NameAndType        #155:#109     // profileActivationJdkOpt:()Lscala/Option;
  #157 = Methodref          #23.#156      // coursier/maven/PomParser$State.profileActivationJdkOpt:()Lscala/Option;
  #158 = Utf8               (Lscala/collection/immutable/Seq;Lcoursier/core/Activation$Os;Lscala/Option;)Lcoursier/core/Activation;
  #159 = NameAndType        #151:#158     // apply:(Lscala/collection/immutable/Seq;Lcoursier/core/Activation$Os;Lscala/Option;)Lcoursier/core/Activation;
  #160 = Methodref          #113.#159     // coursier/core/Activation$.apply:(Lscala/collection/immutable/Seq;Lcoursier/core/Activation$Os;Lscala/Option;)Lcoursier/core/Activation;
  #161 = Utf8               profileProperties
  #162 = NameAndType        #161:#70      // profileProperties:()Lscala/collection/immutable/Map;
  #163 = Methodref          #23.#162      // coursier/maven/PomParser$State.profileProperties:()Lscala/collection/immutable/Map;
  #164 = Utf8               (Ljava/lang/String;Lscala/Option;Lcoursier/core/Activation;Lscala/collection/immutable/Seq;Lscala/collection/immutable/Seq;Lscala/collection/immutable/Map;)Lcoursier/core/Profile;
  #165 = NameAndType        #151:#164     // apply:(Ljava/lang/String;Lscala/Option;Lcoursier/core/Activation;Lscala/collection/immutable/Seq;Lscala/collection/immutable/Seq;Lscala/collection/immutable/Map;)Lcoursier/core/Profile;
  #166 = Methodref          #100.#165     // coursier/core/Profile$.apply:(Ljava/lang/String;Lscala/Option;Lcoursier/core/Activation;Lscala/collection/immutable/Seq;Lscala/collection/immutable/Seq;Lscala/collection/immutable/Map;)Lcoursier/core/Profile;
  #167 = NameAndType        #25:#26       // add$1:Lscala/Function2;
  #168 = Fieldref           #2.#167       // coursier/maven/PomParser$$anon$2.add$1:Lscala/Function2;
  #169 = Utf8               scala/Function2
  #170 = Class              #169          // scala/Function2
  #171 = Utf8               (Ljava/lang/Object;Ljava/lang/Object;)Ljava/lang/Object;
  #172 = NameAndType        #151:#171     // apply:(Ljava/lang/Object;Ljava/lang/Object;)Ljava/lang/Object;
  #173 = InterfaceMethodref #170.#172     // scala/Function2.apply:(Ljava/lang/Object;Ljava/lang/Object;)Ljava/lang/Object;
  #174 = Utf8               p
  #175 = Utf8               Lcoursier/core/Profile;
  #176 = Utf8               <init>
  #177 = Utf8               (Lscala/collection/immutable/List;Lscala/Function2;)V
  #178 = Utf8               prefix$1
  #179 = Utf8               (Lscala/collection/immutable/List;)V
  #180 = NameAndType        #176:#179     // "<init>":(Lscala/collection/immutable/List;)V
  #181 = Methodref          #4.#180       // coursier/maven/PomParser$SectionHandler."<init>":(Lscala/collection/immutable/List;)V
  #182 = Utf8               Lscala/collection/immutable/List;
  #183 = Utf8               Code
  #184 = Utf8               LineNumberTable
  #185 = Utf8               LocalVariableTable
  #186 = Utf8               MethodParameters
  #187 = Utf8               InnerClasses
  #188 = Utf8               EnclosingMethod
  #189 = Utf8               SourceFile
  #190 = Utf8               ScalaInlineInfo
  #191 = Utf8               Scala
{
  private final scala.Function2 add$1;
    descriptor: Lscala/Function2;
    flags: (0x0012) ACC_PRIVATE, ACC_FINAL

  public void start(coursier.maven.PomParser$State);
    descriptor: (Lcoursier/maven/PomParser$State;)V
    flags: (0x0001) ACC_PUBLIC
    Code:
      stack=2, locals=2, args_size=2
         0: aload_1
         1: ldc           #30                 // String
         3: invokevirtual #34                 // Method coursier/maven/PomParser$State.profileId_$eq:(Ljava/lang/String;)V
         6: aload_1
         7: getstatic     #40                 // Field scala/None$.MODULE$:Lscala/None$;
        10: invokevirtual #44                 // Method coursier/maven/PomParser$State.profileActiveByDefaultOpt_$eq:(Lscala/Option;)V
        13: aload_1
        14: invokevirtual #48                 // Method coursier/maven/PomParser$State.profileDependencies:()Lscala/collection/mutable/ListBuffer;
        17: invokevirtual #54                 // Method scala/collection/mutable/ListBuffer.clear:()V
        20: aload_1
        21: invokevirtual #57                 // Method coursier/maven/PomParser$State.profileDependencyManagement:()Lscala/collection/mutable/ListBuffer;
        24: invokevirtual #54                 // Method scala/collection/mutable/ListBuffer.clear:()V
        27: aload_1
        28: getstatic     #62                 // Field scala/Predef$.MODULE$:Lscala/Predef$;
        31: invokevirtual #66                 // Method scala/Predef$.Map:()Lscala/collection/immutable/Map$;
        34: invokevirtual #72                 // Method scala/collection/immutable/Map$.empty:()Lscala/collection/immutable/Map;
        37: invokevirtual #76                 // Method coursier/maven/PomParser$State.profileProperties_$eq:(Lscala/collection/immutable/Map;)V
        40: aload_1
        41: invokevirtual #79                 // Method coursier/maven/PomParser$State.profileActivationProperties:()Lscala/collection/mutable/ListBuffer;
        44: invokevirtual #54                 // Method scala/collection/mutable/ListBuffer.clear:()V
        47: aload_1
        48: getstatic     #40                 // Field scala/None$.MODULE$:Lscala/None$;
        51: invokevirtual #82                 // Method coursier/maven/PomParser$State.profileActivationOsArchOpt_$eq:(Lscala/Option;)V
        54: aload_1
        55: getstatic     #40                 // Field scala/None$.MODULE$:Lscala/None$;
        58: invokevirtual #85                 // Method coursier/maven/PomParser$State.profileActivationOsFamilyOpt_$eq:(Lscala/Option;)V
        61: aload_1
        62: getstatic     #40                 // Field scala/None$.MODULE$:Lscala/None$;
        65: invokevirtual #88                 // Method coursier/maven/PomParser$State.profileActivationOsNameOpt_$eq:(Lscala/Option;)V
        68: aload_1
        69: getstatic     #40                 // Field scala/None$.MODULE$:Lscala/None$;
        72: invokevirtual #91                 // Method coursier/maven/PomParser$State.profileActivationOsVersionOpt_$eq:(Lscala/Option;)V
        75: aload_1
        76: getstatic     #40                 // Field scala/None$.MODULE$:Lscala/None$;
        79: invokevirtual #94                 // Method coursier/maven/PomParser$State.profileActivationJdkOpt_$eq:(Lscala/Option;)V
        82: return
      LineNumberTable:
        line 372: 0
        line 373: 6
        line 374: 13
        line 375: 20
        line 376: 27
        line 377: 40
        line 378: 47
        line 379: 54
        line 380: 61
        line 381: 68
        line 382: 75
      LocalVariableTable:
        Start  Length  Slot  Name   Signature
            0      83     0  this   Lcoursier/maven/PomParser$$anon$2;
            0      83     1 state   Lcoursier/maven/PomParser$State;
    MethodParameters:
      Name                           Flags
      state                          final

  public void end(coursier.maven.PomParser$State);
    descriptor: (Lcoursier/maven/PomParser$State;)V
    flags: (0x0001) ACC_PUBLIC
    Code:
      stack=10, locals=3, args_size=2
         0: getstatic     #103                // Field coursier/core/Profile$.MODULE$:Lcoursier/core/Profile$;
         3: aload_1
         4: invokevirtual #107                // Method coursier/maven/PomParser$State.profileId:()Ljava/lang/String;
         7: aload_1
         8: invokevirtual #111                // Method coursier/maven/PomParser$State.profileActiveByDefaultOpt:()Lscala/Option;
        11: getstatic     #116                // Field coursier/core/Activation$.MODULE$:Lcoursier/core/Activation$;
        14: aload_1
        15: invokevirtual #79                 // Method coursier/maven/PomParser$State.profileActivationProperties:()Lscala/collection/mutable/ListBuffer;
        18: invokevirtual #120                // Method scala/collection/mutable/ListBuffer.toList:()Lscala/collection/immutable/List;
        21: getstatic     #123                // Field coursier/core/Activation$Os$.MODULE$:Lcoursier/core/Activation$Os$;
        24: aload_1
        25: invokevirtual #126                // Method coursier/maven/PomParser$State.profileActivationOsArchOpt:()Lscala/Option;
        28: getstatic     #131                // Field scala/Option$.MODULE$:Lscala/Option$;
        31: aload_1
        32: invokevirtual #134                // Method coursier/maven/PomParser$State.profileActivationOsFamilyOpt:()Lscala/Option;
        35: invokevirtual #138                // Method scala/Option$.option2Iterable:(Lscala/Option;)Lscala/collection/Iterable;
        38: invokeinterface #144,  1          // InterfaceMethod scala/collection/Iterable.toSet:()Lscala/collection/immutable/Set;
        43: aload_1
        44: invokevirtual #147                // Method coursier/maven/PomParser$State.profileActivationOsNameOpt:()Lscala/Option;
        47: aload_1
        48: invokevirtual #150                // Method coursier/maven/PomParser$State.profileActivationOsVersionOpt:()Lscala/Option;
        51: invokevirtual #154                // Method coursier/core/Activation$Os$.apply:(Lscala/Option;Lscala/collection/immutable/Set;Lscala/Option;Lscala/Option;)Lcoursier/core/Activation$Os;
        54: aload_1
        55: invokevirtual #157                // Method coursier/maven/PomParser$State.profileActivationJdkOpt:()Lscala/Option;
        58: invokevirtual #160                // Method coursier/core/Activation$.apply:(Lscala/collection/immutable/Seq;Lcoursier/core/Activation$Os;Lscala/Option;)Lcoursier/core/Activation;
        61: aload_1
        62: invokevirtual #48                 // Method coursier/maven/PomParser$State.profileDependencies:()Lscala/collection/mutable/ListBuffer;
        65: invokevirtual #120                // Method scala/collection/mutable/ListBuffer.toList:()Lscala/collection/immutable/List;
        68: aload_1
        69: invokevirtual #57                 // Method coursier/maven/PomParser$State.profileDependencyManagement:()Lscala/collection/mutable/ListBuffer;
        72: invokevirtual #120                // Method scala/collection/mutable/ListBuffer.toList:()Lscala/collection/immutable/List;
        75: aload_1
        76: invokevirtual #163                // Method coursier/maven/PomParser$State.profileProperties:()Lscala/collection/immutable/Map;
        79: invokevirtual #166                // Method coursier/core/Profile$.apply:(Ljava/lang/String;Lscala/Option;Lcoursier/core/Activation;Lscala/collection/immutable/Seq;Lscala/collection/immutable/Seq;Lscala/collection/immutable/Map;)Lcoursier/core/Profile;
        82: astore_2
        83: aload_0
        84: getfield      #168                // Field add$1:Lscala/Function2;
        87: aload_1
        88: aload_2
        89: invokeinterface #173,  3          // InterfaceMethod scala/Function2.apply:(Ljava/lang/Object;Ljava/lang/Object;)Ljava/lang/Object;
        94: pop
        95: return
      LineNumberTable:
        line 385: 0
        line 386: 3
        line 387: 7
        line 388: 11
        line 389: 14
        line 390: 21
        line 391: 24
        line 392: 28
        line 393: 43
        line 394: 47
        line 396: 54
        line 398: 61
        line 399: 68
        line 400: 75
        line 402: 83
      LocalVariableTable:
        Start  Length  Slot  Name   Signature
           83      12     2     p   Lcoursier/core/Profile;
            0      96     0  this   Lcoursier/maven/PomParser$$anon$2;
            0      96     1 state   Lcoursier/maven/PomParser$State;
    MethodParameters:
      Name                           Flags
      state                          final

  public coursier.maven.PomParser$$anon$2(scala.collection.immutable.List, scala.Function2);
    descriptor: (Lscala/collection/immutable/List;Lscala/Function2;)V
    flags: (0x0001) ACC_PUBLIC
    Code:
      stack=2, locals=3, args_size=3
         0: aload_0
         1: aload_2
         2: putfield      #168                // Field add$1:Lscala/Function2;
         5: aload_0
         6: aload_1
         7: invokespecial #181                // Method coursier/maven/PomParser$SectionHandler."<init>":(Lscala/collection/immutable/List;)V
        10: return
      LineNumberTable:
        line 368: 0
        line 370: 5
      LocalVariableTable:
        Start  Length  Slot  Name   Signature
            0      11     0  this   Lcoursier/maven/PomParser$$anon$2;
            0      11     1 prefix$1   Lscala/collection/immutable/List;
            0      11     2 add$1   Lscala/Function2;
    MethodParameters:
      Name                           Flags
      prefix$1                       final
      add$1                          final
}
InnerClasses:
  public static final #15= #12 of #14;    // Os=class coursier/core/Activation$Os of class coursier/core/Activation
  public static #18= #17 of #14;          // =class coursier/core/Activation$Os$ of class coursier/core/Activation
  public final #2;                        // class coursier/maven/PomParser$$anon$2
  public static abstract #21= #4 of #20;  // SectionHandler=class coursier/maven/PomParser$SectionHandler of class coursier/maven/PomParser
  public static final #24= #23 of #20;    // State=class coursier/maven/PomParser$State of class coursier/maven/PomParser
EnclosingMethod: #7.#10                 // coursier.maven.PomParser$.profileHandlers
SourceFile: "PomParser.scala"
  ScalaInlineInfo: length = 0x13 (unknown attribute)
   01 01 00 03 00 B1 00 B2 01 00 63 00 1C 01 00 1B
   00 1C 01
  Scala: length = 0x0 (unknown attribute)

