Classfile /Users/mw/Projects/slang-braindump/.jar/jar11/assemble/slang-braindump/assemble/content/coursier/maven/PomParser$CustomList.class
  Last modified May 29, 2022; size 1089 bytes
  SHA-256 checksum f9c15731542bfd79c6b44bc567b2c3ac5c244a68d9608817546a7d42b245c3bc
  Compiled from "PomParser.scala"
public abstract class coursier.maven.PomParser$CustomList<T extends java.lang.Object> extends java.lang.Object
  minor version: 0
  major version: 52
  flags: (0x0421) ACC_PUBLIC, ACC_SUPER, ACC_ABSTRACT
  this_class: #2                          // coursier/maven/PomParser$CustomList
  super_class: #5                         // java/lang/Object
  interfaces: 0, fields: 0, methods: 3, attributes: 5
Constant pool:
   #1 = Utf8               coursier/maven/PomParser$CustomList
   #2 = Class              #1             // coursier/maven/PomParser$CustomList
   #3 = Utf8               <T:Ljava/lang/Object;>Ljava/lang/Object;
   #4 = Utf8               java/lang/Object
   #5 = Class              #4             // java/lang/Object
   #6 = Utf8               PomParser.scala
   #7 = Utf8               coursier/maven/PomParser
   #8 = Class              #7             // coursier/maven/PomParser
   #9 = Utf8               CustomList
  #10 = Utf8               coursier/maven/PomParser$CustomList$
  #11 = Class              #10            // coursier/maven/PomParser$CustomList$
  #12 = Utf8
  #13 = Utf8               coursier/maven/PomParser$CustomList$Cons
  #14 = Class              #13            // coursier/maven/PomParser$CustomList$Cons
  #15 = Utf8               Cons
  #16 = Utf8               $colon$colon
  #17 = Utf8               (Ljava/lang/Object;)Lcoursier/maven/PomParser$CustomList;
  #18 = Utf8               <U:Ljava/lang/Object;>(TU;)Lcoursier/maven/PomParser$CustomList<TU;>;
  #19 = Utf8               elem
  #20 = Utf8               <init>
  #21 = Utf8               (Ljava/lang/Object;Lcoursier/maven/PomParser$CustomList;)V
  #22 = NameAndType        #20:#21        // "<init>":(Ljava/lang/Object;Lcoursier/maven/PomParser$CustomList;)V
  #23 = Methodref          #14.#22        // coursier/maven/PomParser$CustomList$Cons."<init>":(Ljava/lang/Object;Lcoursier/maven/PomParser$CustomList;)V
  #24 = Utf8               this
  #25 = Utf8               Lcoursier/maven/PomParser$CustomList;
  #26 = Utf8               Ljava/lang/Object;
  #27 = Utf8               tail
  #28 = Utf8               ()Lcoursier/maven/PomParser$CustomList;
  #29 = Utf8               ()Lcoursier/maven/PomParser$CustomList<TT;>;
  #30 = Utf8               ()V
  #31 = NameAndType        #20:#30        // "<init>":()V
  #32 = Methodref          #5.#31         // java/lang/Object."<init>":()V
  #33 = Utf8               Code
  #34 = Utf8               LineNumberTable
  #35 = Utf8               LocalVariableTable
  #36 = Utf8               Signature
  #37 = Utf8               MethodParameters
  #38 = Utf8               InnerClasses
  #39 = Utf8               SourceFile
  #40 = Utf8               ScalaInlineInfo
  #41 = Utf8               Scala
{
  public <U extends java.lang.Object> coursier.maven.PomParser$CustomList<U> $colon$colon(U);
    descriptor: (Ljava/lang/Object;)Lcoursier/maven/PomParser$CustomList;
    flags: (0x0001) ACC_PUBLIC
    Code:
      stack=4, locals=2, args_size=2
         0: new           #14                 // class coursier/maven/PomParser$CustomList$Cons
         3: dup
         4: aload_1
         5: aload_0
         6: invokespecial #23                 // Method coursier/maven/PomParser$CustomList$Cons."<init>":(Ljava/lang/Object;Lcoursier/maven/PomParser$CustomList;)V
         9: areturn
      LineNumberTable:
        line 67: 0
      LocalVariableTable:
        Start  Length  Slot  Name   Signature
            0      10     0  this   Lcoursier/maven/PomParser$CustomList;
            0      10     1  elem   Ljava/lang/Object;
    Signature: #18                          // <U:Ljava/lang/Object;>(TU;)Lcoursier/maven/PomParser$CustomList<TU;>;
    MethodParameters:
      Name                           Flags
      elem                           final

  public abstract coursier.maven.PomParser$CustomList<T> tail();
    descriptor: ()Lcoursier/maven/PomParser$CustomList;
    flags: (0x0401) ACC_PUBLIC, ACC_ABSTRACT
    Signature: #29                          // ()Lcoursier/maven/PomParser$CustomList<TT;>;

  public coursier.maven.PomParser$CustomList();
    descriptor: ()V
    flags: (0x0001) ACC_PUBLIC
    Code:
      stack=1, locals=1, args_size=1
         0: aload_0
         1: invokespecial #32                 // Method java/lang/Object."<init>":()V
         4: return
      LineNumberTable:
        line 71: 0
        line 65: 4
      LocalVariableTable:
        Start  Length  Slot  Name   Signature
            0       5     0  this   Lcoursier/maven/PomParser$CustomList;
}
InnerClasses:
  public static abstract #9= #2 of #8;    // CustomList=class coursier/maven/PomParser$CustomList of class coursier/maven/PomParser
  public static #12= #11 of #8;           // =class coursier/maven/PomParser$CustomList$ of class coursier/maven/PomParser
  public static final #15= #14 of #11;    // Cons=class coursier/maven/PomParser$CustomList$Cons of class coursier/maven/PomParser$CustomList$
Signature: #3                           // <T:Ljava/lang/Object;>Ljava/lang/Object;
SourceFile: "PomParser.scala"
  ScalaInlineInfo: length = 0x13 (unknown attribute)
   01 00 00 03 00 10 00 11 01 00 14 00 1E 01 00 1B
   00 1C 00
  Scala: length = 0x0 (unknown attribute)

