Classfile /Users/mw/Projects/slang-braindump/.jar/jar11/assemble/slang-braindump/assemble/content/org/scalatest/flatspec/FixtureAsyncFlatSpecLike$InAndIgnoreMethodsAfterTaggedAs.class
  Last modified May 29, 2022; size 3210 bytes
  SHA-256 checksum 063e460eb28ba5cb7fb9880a4c02e5891f893fef71b41f7828c5860bc7c0dba3
  Compiled from "FixtureAsyncFlatSpecLike.scala"
public final class org.scalatest.flatspec.FixtureAsyncFlatSpecLike$InAndIgnoreMethodsAfterTaggedAs
  minor version: 0
  major version: 52
  flags: (0x0031) ACC_PUBLIC, ACC_FINAL, ACC_SUPER
  this_class: #2                          // org/scalatest/flatspec/FixtureAsyncFlatSpecLike$InAndIgnoreMethodsAfterTaggedAs
  super_class: #4                         // java/lang/Object
  interfaces: 0, fields: 2, methods: 7, attributes: 4
Constant pool:
   #1 = Utf8               org/scalatest/flatspec/FixtureAsyncFlatSpecLike$InAndIgnoreMethodsAfterTaggedAs
   #2 = Class              #1             // org/scalatest/flatspec/FixtureAsyncFlatSpecLike$InAndIgnoreMethodsAfterTaggedAs
   #3 = Utf8               java/lang/Object
   #4 = Class              #3             // java/lang/Object
   #5 = Utf8               FixtureAsyncFlatSpecLike.scala
   #6 = Utf8               org/scalatest/flatspec/FixtureAsyncFlatSpecLike
   #7 = Class              #6             // org/scalatest/flatspec/FixtureAsyncFlatSpecLike
   #8 = Utf8               InAndIgnoreMethodsAfterTaggedAs
   #9 = Utf8               resultOfTaggedAsInvocation
  #10 = Utf8               Lorg/scalatest/verbs/ResultOfTaggedAsInvocation;
  #11 = Utf8               $outer
  #12 = Utf8               Lorg/scalatest/flatspec/FixtureAsyncFlatSpecLike;
  #13 = Utf8               inImpl
  #14 = Utf8               (Lscala/Function0;Lorg/scalactic/source/Position;)V
  #15 = Utf8               (Lscala/Function0<Lscala/concurrent/Future<Lorg/scalatest/compatible/Assertion;>;>;Lorg/scalactic/source/Position;)V
  #16 = Utf8               testFun
  #17 = Utf8               pos
  #18 = NameAndType        #11:#12        // $outer:Lorg/scalatest/flatspec/FixtureAsyncFlatSpecLike;
  #19 = Fieldref           #2.#18         // org/scalatest/flatspec/FixtureAsyncFlatSpecLike$InAndIgnoreMethodsAfterTaggedAs.$outer:Lorg/scalatest/flatspec/FixtureAsyncFlatSpecLike;
  #20 = Utf8               java/lang/StringBuilder
  #21 = Class              #20            // java/lang/StringBuilder
  #22 = Integer            1
  #23 = Utf8               <init>
  #24 = Utf8               (I)V
  #25 = NameAndType        #23:#24        // "<init>":(I)V
  #26 = Methodref          #21.#25        // java/lang/StringBuilder."<init>":(I)V
  #27 = NameAndType        #9:#10         // resultOfTaggedAsInvocation:Lorg/scalatest/verbs/ResultOfTaggedAsInvocation;
  #28 = Fieldref           #2.#27         // org/scalatest/flatspec/FixtureAsyncFlatSpecLike$InAndIgnoreMethodsAfterTaggedAs.resultOfTaggedAsInvocation:Lorg/scalatest/verbs/ResultOfTaggedAsInvocation;
  #29 = Utf8               org/scalatest/verbs/ResultOfTaggedAsInvocation
  #30 = Class              #29            // org/scalatest/verbs/ResultOfTaggedAsInvocation
  #31 = Utf8               verb
  #32 = Utf8               ()Ljava/lang/String;
  #33 = NameAndType        #31:#32        // verb:()Ljava/lang/String;
  #34 = Methodref          #30.#33        // org/scalatest/verbs/ResultOfTaggedAsInvocation.verb:()Ljava/lang/String;
  #35 = Utf8               java/lang/String
  #36 = Class              #35            // java/lang/String
  #37 = Utf8               trim
  #38 = NameAndType        #37:#32        // trim:()Ljava/lang/String;
  #39 = Methodref          #36.#38        // java/lang/String.trim:()Ljava/lang/String;
  #40 = Utf8               append
  #41 = Utf8               (Ljava/lang/String;)Ljava/lang/StringBuilder;
  #42 = NameAndType        #40:#41        // append:(Ljava/lang/String;)Ljava/lang/StringBuilder;
  #43 = Methodref          #21.#42        // java/lang/StringBuilder.append:(Ljava/lang/String;)Ljava/lang/StringBuilder;
  #44 = Utf8
  #45 = String             #44            //
  #46 = Utf8               rest
  #47 = NameAndType        #46:#32        // rest:()Ljava/lang/String;
  #48 = Methodref          #30.#47        // org/scalatest/verbs/ResultOfTaggedAsInvocation.rest:()Ljava/lang/String;
  #49 = Utf8               toString
  #50 = NameAndType        #49:#32        // toString:()Ljava/lang/String;
  #51 = Methodref          #21.#50        // java/lang/StringBuilder.toString:()Ljava/lang/String;
  #52 = Utf8               tags
  #53 = Utf8               ()Lscala/collection/immutable/List;
  #54 = NameAndType        #52:#53        // tags:()Lscala/collection/immutable/List;
  #55 = Methodref          #30.#54        // org/scalatest/verbs/ResultOfTaggedAsInvocation.tags:()Lscala/collection/immutable/List;
  #56 = Utf8               in
  #57 = String             #56            // in
  #58 = Utf8               org/scalatest/fixture/NoArgTestWrapper
  #59 = Class              #58            // org/scalatest/fixture/NoArgTestWrapper
  #60 = Utf8               (Lscala/Function0;)V
  #61 = NameAndType        #23:#60        // "<init>":(Lscala/Function0;)V
  #62 = Methodref          #59.#61        // org/scalatest/fixture/NoArgTestWrapper."<init>":(Lscala/Function0;)V
  #63 = Utf8               org$scalatest$flatspec$FixtureAsyncFlatSpecLike$$registerAsyncTestToRun
  #64 = Utf8               (Ljava/lang/String;Lscala/collection/immutable/List;Ljava/lang/String;Lscala/Function1;Lorg/scalactic/source/Position;)V
  #65 = NameAndType        #63:#64        // org$scalatest$flatspec$FixtureAsyncFlatSpecLike$$registerAsyncTestToRun:(Ljava/lang/String;Lscala/collection/immutable/List;Ljava/lang/String;Lscala/Function1;Lorg/scalactic/source/Position;)V
  #66 = InterfaceMethodref #7.#65         // org/scalatest/flatspec/FixtureAsyncFlatSpecLike.org$scalatest$flatspec$FixtureAsyncFlatSpecLike$$registerAsyncTestToRun:(Ljava/lang/String;Lscala/collection/immutable/List;Ljava/lang/String;Lscala/Function1;Lorg/scalactic/source/Position;)V
  #67 = Utf8               this
  #68 = Utf8               Lorg/scalatest/flatspec/FixtureAsyncFlatSpecLike$InAndIgnoreMethodsAfterTaggedAs;
  #69 = Utf8               Lscala/Function0;
  #70 = Utf8               Lorg/scalactic/source/Position;
  #71 = NameAndType        #13:#14        // inImpl:(Lscala/Function0;Lorg/scalactic/source/Position;)V
  #72 = Methodref          #2.#71         // org/scalatest/flatspec/FixtureAsyncFlatSpecLike$InAndIgnoreMethodsAfterTaggedAs.inImpl:(Lscala/Function0;Lorg/scalactic/source/Position;)V
  #73 = Utf8               ignoreImpl
  #74 = Utf8               org$scalatest$flatspec$FixtureAsyncFlatSpecLike$$registerAsyncTestToIgnore
  #75 = Utf8               (Ljava/lang/String;Lscala/collection/immutable/List;Lscala/Function1;Lorg/scalactic/source/Position;)V
  #76 = NameAndType        #74:#75        // org$scalatest$flatspec$FixtureAsyncFlatSpecLike$$registerAsyncTestToIgnore:(Ljava/lang/String;Lscala/collection/immutable/List;Lscala/Function1;Lorg/scalactic/source/Position;)V
  #77 = InterfaceMethodref #7.#76         // org/scalatest/flatspec/FixtureAsyncFlatSpecLike.org$scalatest$flatspec$FixtureAsyncFlatSpecLike$$registerAsyncTestToIgnore:(Ljava/lang/String;Lscala/collection/immutable/List;Lscala/Function1;Lorg/scalactic/source/Position;)V
  #78 = Utf8               ignore
  #79 = NameAndType        #73:#14        // ignoreImpl:(Lscala/Function0;Lorg/scalactic/source/Position;)V
  #80 = Methodref          #2.#79         // org/scalatest/flatspec/FixtureAsyncFlatSpecLike$InAndIgnoreMethodsAfterTaggedAs.ignoreImpl:(Lscala/Function0;Lorg/scalactic/source/Position;)V
  #81 = Utf8               (Lscala/Function1;Lorg/scalactic/source/Position;)V
  #82 = Utf8               (Lscala/Function1<Ljava/lang/Object;Lscala/concurrent/Future<Lorg/scalatest/compatible/Assertion;>;>;Lorg/scalactic/source/Position;)V
  #83 = Utf8               Lscala/Function1;
  #84 = Utf8               (Lorg/scalatest/flatspec/FixtureAsyncFlatSpecLike;Lorg/scalatest/verbs/ResultOfTaggedAsInvocation;)V
  #85 = Utf8               ()V
  #86 = NameAndType        #23:#85        // "<init>":()V
  #87 = Methodref          #4.#86         // java/lang/Object."<init>":()V
  #88 = Utf8               Code
  #89 = Utf8               LineNumberTable
  #90 = Utf8               LocalVariableTable
  #91 = Utf8               Signature
  #92 = Utf8               MethodParameters
  #93 = Utf8               StackMapTable
  #94 = Utf8               InnerClasses
  #95 = Utf8               SourceFile
  #96 = Utf8               ScalaInlineInfo
  #97 = Utf8               Scala
{
  private final org.scalatest.verbs.ResultOfTaggedAsInvocation resultOfTaggedAsInvocation;
    descriptor: Lorg/scalatest/verbs/ResultOfTaggedAsInvocation;
    flags: (0x0012) ACC_PRIVATE, ACC_FINAL

  private final org.scalatest.flatspec.FixtureAsyncFlatSpecLike $outer;
    descriptor: Lorg/scalatest/flatspec/FixtureAsyncFlatSpecLike;
    flags: (0x1012) ACC_PRIVATE, ACC_FINAL, ACC_SYNTHETIC

  private final void inImpl(scala.Function0<scala.concurrent.Future<org.scalatest.compatible.Assertion>>, org.scalactic.source.Position);
    descriptor: (Lscala/Function0;Lorg/scalactic/source/Position;)V
    flags: (0x0012) ACC_PRIVATE, ACC_FINAL
    Code:
      stack=7, locals=3, args_size=3
         0: aload_0
         1: getfield      #19                 // Field $outer:Lorg/scalatest/flatspec/FixtureAsyncFlatSpecLike;
         4: new           #21                 // class java/lang/StringBuilder
         7: dup
         8: ldc           #22                 // int 1
        10: invokespecial #26                 // Method java/lang/StringBuilder."<init>":(I)V
        13: aload_0
        14: getfield      #28                 // Field resultOfTaggedAsInvocation:Lorg/scalatest/verbs/ResultOfTaggedAsInvocation;
        17: invokevirtual #34                 // Method org/scalatest/verbs/ResultOfTaggedAsInvocation.verb:()Ljava/lang/String;
        20: invokevirtual #39                 // Method java/lang/String.trim:()Ljava/lang/String;
        23: invokevirtual #43                 // Method java/lang/StringBuilder.append:(Ljava/lang/String;)Ljava/lang/StringBuilder;
        26: ldc           #45                 // String
        28: invokevirtual #43                 // Method java/lang/StringBuilder.append:(Ljava/lang/String;)Ljava/lang/StringBuilder;
        31: aload_0
        32: getfield      #28                 // Field resultOfTaggedAsInvocation:Lorg/scalatest/verbs/ResultOfTaggedAsInvocation;
        35: invokevirtual #48                 // Method org/scalatest/verbs/ResultOfTaggedAsInvocation.rest:()Ljava/lang/String;
        38: invokevirtual #39                 // Method java/lang/String.trim:()Ljava/lang/String;
        41: invokevirtual #43                 // Method java/lang/StringBuilder.append:(Ljava/lang/String;)Ljava/lang/StringBuilder;
        44: invokevirtual #51                 // Method java/lang/StringBuilder.toString:()Ljava/lang/String;
        47: aload_0
        48: getfield      #28                 // Field resultOfTaggedAsInvocation:Lorg/scalatest/verbs/ResultOfTaggedAsInvocation;
        51: invokevirtual #55                 // Method org/scalatest/verbs/ResultOfTaggedAsInvocation.tags:()Lscala/collection/immutable/List;
        54: ldc           #57                 // String in
        56: new           #59                 // class org/scalatest/fixture/NoArgTestWrapper
        59: dup
        60: aload_1
        61: invokespecial #62                 // Method org/scalatest/fixture/NoArgTestWrapper."<init>":(Lscala/Function0;)V
        64: aload_2
        65: invokeinterface #66,  6           // InterfaceMethod org/scalatest/flatspec/FixtureAsyncFlatSpecLike.org$scalatest$flatspec$FixtureAsyncFlatSpecLike$$registerAsyncTestToRun:(Ljava/lang/String;Lscala/collection/immutable/List;Ljava/lang/String;Lscala/Function1;Lorg/scalactic/source/Position;)V
        70: return
      LineNumberTable:
        line 2083: 0
      LocalVariableTable:
        Start  Length  Slot  Name   Signature
            0      71     0  this   Lorg/scalatest/flatspec/FixtureAsyncFlatSpecLike$InAndIgnoreMethodsAfterTaggedAs;
            0      71     1 testFun   Lscala/Function0;
            0      71     2   pos   Lorg/scalactic/source/Position;
    Signature: #15                          // (Lscala/Function0<Lscala/concurrent/Future<Lorg/scalatest/compatible/Assertion;>;>;Lorg/scalactic/source/Position;)V
    MethodParameters:
      Name                           Flags
      testFun                        final
      pos                            final

  public void in(scala.Function0<scala.concurrent.Future<org.scalatest.compatible.Assertion>>, org.scalactic.source.Position);
    descriptor: (Lscala/Function0;Lorg/scalactic/source/Position;)V
    flags: (0x0001) ACC_PUBLIC
    Code:
      stack=3, locals=3, args_size=3
         0: aload_0
         1: aload_1
         2: aload_2
         3: invokespecial #72                 // Method inImpl:(Lscala/Function0;Lorg/scalactic/source/Position;)V
         6: return
      LineNumberTable:
        line 2107: 0
      LocalVariableTable:
        Start  Length  Slot  Name   Signature
            0       7     0  this   Lorg/scalatest/flatspec/FixtureAsyncFlatSpecLike$InAndIgnoreMethodsAfterTaggedAs;
            0       7     1 testFun   Lscala/Function0;
            0       7     2   pos   Lorg/scalactic/source/Position;
    Signature: #15                          // (Lscala/Function0<Lscala/concurrent/Future<Lorg/scalatest/compatible/Assertion;>;>;Lorg/scalactic/source/Position;)V
    MethodParameters:
      Name                           Flags
      testFun                        final
      pos                            final

  private final void ignoreImpl(scala.Function0<scala.concurrent.Future<org.scalatest.compatible.Assertion>>, org.scalactic.source.Position);
    descriptor: (Lscala/Function0;Lorg/scalactic/source/Position;)V
    flags: (0x0012) ACC_PRIVATE, ACC_FINAL
    Code:
      stack=6, locals=3, args_size=3
         0: aload_0
         1: getfield      #19                 // Field $outer:Lorg/scalatest/flatspec/FixtureAsyncFlatSpecLike;
         4: new           #21                 // class java/lang/StringBuilder
         7: dup
         8: ldc           #22                 // int 1
        10: invokespecial #26                 // Method java/lang/StringBuilder."<init>":(I)V
        13: aload_0
        14: getfield      #28                 // Field resultOfTaggedAsInvocation:Lorg/scalatest/verbs/ResultOfTaggedAsInvocation;
        17: invokevirtual #34                 // Method org/scalatest/verbs/ResultOfTaggedAsInvocation.verb:()Ljava/lang/String;
        20: invokevirtual #39                 // Method java/lang/String.trim:()Ljava/lang/String;
        23: invokevirtual #43                 // Method java/lang/StringBuilder.append:(Ljava/lang/String;)Ljava/lang/StringBuilder;
        26: ldc           #45                 // String
        28: invokevirtual #43                 // Method java/lang/StringBuilder.append:(Ljava/lang/String;)Ljava/lang/StringBuilder;
        31: aload_0
        32: getfield      #28                 // Field resultOfTaggedAsInvocation:Lorg/scalatest/verbs/ResultOfTaggedAsInvocation;
        35: invokevirtual #48                 // Method org/scalatest/verbs/ResultOfTaggedAsInvocation.rest:()Ljava/lang/String;
        38: invokevirtual #39                 // Method java/lang/String.trim:()Ljava/lang/String;
        41: invokevirtual #43                 // Method java/lang/StringBuilder.append:(Ljava/lang/String;)Ljava/lang/StringBuilder;
        44: invokevirtual #51                 // Method java/lang/StringBuilder.toString:()Ljava/lang/String;
        47: aload_0
        48: getfield      #28                 // Field resultOfTaggedAsInvocation:Lorg/scalatest/verbs/ResultOfTaggedAsInvocation;
        51: invokevirtual #55                 // Method org/scalatest/verbs/ResultOfTaggedAsInvocation.tags:()Lscala/collection/immutable/List;
        54: new           #59                 // class org/scalatest/fixture/NoArgTestWrapper
        57: dup
        58: aload_1
        59: invokespecial #62                 // Method org/scalatest/fixture/NoArgTestWrapper."<init>":(Lscala/Function0;)V
        62: aload_2
        63: invokeinterface #77,  5           // InterfaceMethod org/scalatest/flatspec/FixtureAsyncFlatSpecLike.org$scalatest$flatspec$FixtureAsyncFlatSpecLike$$registerAsyncTestToIgnore:(Ljava/lang/String;Lscala/collection/immutable/List;Lscala/Function1;Lorg/scalactic/source/Position;)V
        68: return
      LineNumberTable:
        line 2115: 0
      LocalVariableTable:
        Start  Length  Slot  Name   Signature
            0      69     0  this   Lorg/scalatest/flatspec/FixtureAsyncFlatSpecLike$InAndIgnoreMethodsAfterTaggedAs;
            0      69     1 testFun   Lscala/Function0;
            0      69     2   pos   Lorg/scalactic/source/Position;
    Signature: #15                          // (Lscala/Function0<Lscala/concurrent/Future<Lorg/scalatest/compatible/Assertion;>;>;Lorg/scalactic/source/Position;)V
    MethodParameters:
      Name                           Flags
      testFun                        final
      pos                            final

  public void ignore(scala.Function0<scala.concurrent.Future<org.scalatest.compatible.Assertion>>, org.scalactic.source.Position);
    descriptor: (Lscala/Function0;Lorg/scalactic/source/Position;)V
    flags: (0x0001) ACC_PUBLIC
    Code:
      stack=3, locals=3, args_size=3
         0: aload_0
         1: aload_1
         2: aload_2
         3: invokespecial #80                 // Method ignoreImpl:(Lscala/Function0;Lorg/scalactic/source/Position;)V
         6: return
      LineNumberTable:
        line 2141: 0
      LocalVariableTable:
        Start  Length  Slot  Name   Signature
            0       7     0  this   Lorg/scalatest/flatspec/FixtureAsyncFlatSpecLike$InAndIgnoreMethodsAfterTaggedAs;
            0       7     1 testFun   Lscala/Function0;
            0       7     2   pos   Lorg/scalactic/source/Position;
    Signature: #15                          // (Lscala/Function0<Lscala/concurrent/Future<Lorg/scalatest/compatible/Assertion;>;>;Lorg/scalactic/source/Position;)V
    MethodParameters:
      Name                           Flags
      testFun                        final
      pos                            final

  public void in(scala.Function1<java.lang.Object, scala.concurrent.Future<org.scalatest.compatible.Assertion>>, org.scalactic.source.Position);
    descriptor: (Lscala/Function1;Lorg/scalactic/source/Position;)V
    flags: (0x0001) ACC_PUBLIC
    Code:
      stack=6, locals=3, args_size=3
         0: aload_0
         1: getfield      #19                 // Field $outer:Lorg/scalatest/flatspec/FixtureAsyncFlatSpecLike;
         4: new           #21                 // class java/lang/StringBuilder
         7: dup
         8: ldc           #22                 // int 1
        10: invokespecial #26                 // Method java/lang/StringBuilder."<init>":(I)V
        13: aload_0
        14: getfield      #28                 // Field resultOfTaggedAsInvocation:Lorg/scalatest/verbs/ResultOfTaggedAsInvocation;
        17: invokevirtual #34                 // Method org/scalatest/verbs/ResultOfTaggedAsInvocation.verb:()Ljava/lang/String;
        20: invokevirtual #39                 // Method java/lang/String.trim:()Ljava/lang/String;
        23: invokevirtual #43                 // Method java/lang/StringBuilder.append:(Ljava/lang/String;)Ljava/lang/StringBuilder;
        26: ldc           #45                 // String
        28: invokevirtual #43                 // Method java/lang/StringBuilder.append:(Ljava/lang/String;)Ljava/lang/StringBuilder;
        31: aload_0
        32: getfield      #28                 // Field resultOfTaggedAsInvocation:Lorg/scalatest/verbs/ResultOfTaggedAsInvocation;
        35: invokevirtual #48                 // Method org/scalatest/verbs/ResultOfTaggedAsInvocation.rest:()Ljava/lang/String;
        38: invokevirtual #39                 // Method java/lang/String.trim:()Ljava/lang/String;
        41: invokevirtual #43                 // Method java/lang/StringBuilder.append:(Ljava/lang/String;)Ljava/lang/StringBuilder;
        44: invokevirtual #51                 // Method java/lang/StringBuilder.toString:()Ljava/lang/String;
        47: aload_0
        48: getfield      #28                 // Field resultOfTaggedAsInvocation:Lorg/scalatest/verbs/ResultOfTaggedAsInvocation;
        51: invokevirtual #55                 // Method org/scalatest/verbs/ResultOfTaggedAsInvocation.tags:()Lscala/collection/immutable/List;
        54: ldc           #57                 // String in
        56: aload_1
        57: aload_2
        58: invokeinterface #66,  6           // InterfaceMethod org/scalatest/flatspec/FixtureAsyncFlatSpecLike.org$scalatest$flatspec$FixtureAsyncFlatSpecLike$$registerAsyncTestToRun:(Ljava/lang/String;Lscala/collection/immutable/List;Ljava/lang/String;Lscala/Function1;Lorg/scalactic/source/Position;)V
        63: return
      LineNumberTable:
        line 2169: 0
      LocalVariableTable:
        Start  Length  Slot  Name   Signature
            0      64     0  this   Lorg/scalatest/flatspec/FixtureAsyncFlatSpecLike$InAndIgnoreMethodsAfterTaggedAs;
            0      64     1 testFun   Lscala/Function1;
            0      64     2   pos   Lorg/scalactic/source/Position;
    Signature: #82                          // (Lscala/Function1<Ljava/lang/Object;Lscala/concurrent/Future<Lorg/scalatest/compatible/Assertion;>;>;Lorg/scalactic/source/Position;)V
    MethodParameters:
      Name                           Flags
      testFun                        final
      pos                            final

  public void ignore(scala.Function1<java.lang.Object, scala.concurrent.Future<org.scalatest.compatible.Assertion>>, org.scalactic.source.Position);
    descriptor: (Lscala/Function1;Lorg/scalactic/source/Position;)V
    flags: (0x0001) ACC_PUBLIC
    Code:
      stack=5, locals=3, args_size=3
         0: aload_0
         1: getfield      #19                 // Field $outer:Lorg/scalatest/flatspec/FixtureAsyncFlatSpecLike;
         4: new           #21                 // class java/lang/StringBuilder
         7: dup
         8: ldc           #22                 // int 1
        10: invokespecial #26                 // Method java/lang/StringBuilder."<init>":(I)V
        13: aload_0
        14: getfield      #28                 // Field resultOfTaggedAsInvocation:Lorg/scalatest/verbs/ResultOfTaggedAsInvocation;
        17: invokevirtual #34                 // Method org/scalatest/verbs/ResultOfTaggedAsInvocation.verb:()Ljava/lang/String;
        20: invokevirtual #39                 // Method java/lang/String.trim:()Ljava/lang/String;
        23: invokevirtual #43                 // Method java/lang/StringBuilder.append:(Ljava/lang/String;)Ljava/lang/StringBuilder;
        26: ldc           #45                 // String
        28: invokevirtual #43                 // Method java/lang/StringBuilder.append:(Ljava/lang/String;)Ljava/lang/StringBuilder;
        31: aload_0
        32: getfield      #28                 // Field resultOfTaggedAsInvocation:Lorg/scalatest/verbs/ResultOfTaggedAsInvocation;
        35: invokevirtual #48                 // Method org/scalatest/verbs/ResultOfTaggedAsInvocation.rest:()Ljava/lang/String;
        38: invokevirtual #39                 // Method java/lang/String.trim:()Ljava/lang/String;
        41: invokevirtual #43                 // Method java/lang/StringBuilder.append:(Ljava/lang/String;)Ljava/lang/StringBuilder;
        44: invokevirtual #51                 // Method java/lang/StringBuilder.toString:()Ljava/lang/String;
        47: aload_0
        48: getfield      #28                 // Field resultOfTaggedAsInvocation:Lorg/scalatest/verbs/ResultOfTaggedAsInvocation;
        51: invokevirtual #55                 // Method org/scalatest/verbs/ResultOfTaggedAsInvocation.tags:()Lscala/collection/immutable/List;
        54: aload_1
        55: aload_2
        56: invokeinterface #77,  5           // InterfaceMethod org/scalatest/flatspec/FixtureAsyncFlatSpecLike.org$scalatest$flatspec$FixtureAsyncFlatSpecLike$$registerAsyncTestToIgnore:(Ljava/lang/String;Lscala/collection/immutable/List;Lscala/Function1;Lorg/scalactic/source/Position;)V
        61: return
      LineNumberTable:
        line 2199: 0
      LocalVariableTable:
        Start  Length  Slot  Name   Signature
            0      62     0  this   Lorg/scalatest/flatspec/FixtureAsyncFlatSpecLike$InAndIgnoreMethodsAfterTaggedAs;
            0      62     1 testFun   Lscala/Function1;
            0      62     2   pos   Lorg/scalactic/source/Position;
    Signature: #82                          // (Lscala/Function1<Ljava/lang/Object;Lscala/concurrent/Future<Lorg/scalatest/compatible/Assertion;>;>;Lorg/scalactic/source/Position;)V
    MethodParameters:
      Name                           Flags
      testFun                        final
      pos                            final

  public org.scalatest.flatspec.FixtureAsyncFlatSpecLike$InAndIgnoreMethodsAfterTaggedAs(org.scalatest.flatspec.FixtureAsyncFlatSpecLike, org.scalatest.verbs.ResultOfTaggedAsInvocation);
    descriptor: (Lorg/scalatest/flatspec/FixtureAsyncFlatSpecLike;Lorg/scalatest/verbs/ResultOfTaggedAsInvocation;)V
    flags: (0x0001) ACC_PUBLIC
    Code:
      stack=2, locals=3, args_size=3
         0: aload_0
         1: aload_2
         2: putfield      #28                 // Field resultOfTaggedAsInvocation:Lorg/scalatest/verbs/ResultOfTaggedAsInvocation;
         5: aload_1
         6: ifnonnull     11
         9: aconst_null
        10: athrow
        11: aload_0
        12: aload_1
        13: putfield      #19                 // Field $outer:Lorg/scalatest/flatspec/FixtureAsyncFlatSpecLike;
        16: aload_0
        17: invokespecial #87                 // Method java/lang/Object."<init>":()V
        20: return
      StackMapTable: number_of_entries = 1
        frame_type = 11 /* same */
      LineNumberTable:
        line 2076: 0
        line 2214: 16
        line 2076: 20
      LocalVariableTable:
        Start  Length  Slot  Name   Signature
            0      21     0  this   Lorg/scalatest/flatspec/FixtureAsyncFlatSpecLike$InAndIgnoreMethodsAfterTaggedAs;
            0      21     1 $outer   Lorg/scalatest/flatspec/FixtureAsyncFlatSpecLike;
            0      21     2 resultOfTaggedAsInvocation   Lorg/scalatest/verbs/ResultOfTaggedAsInvocation;
    MethodParameters:
      Name                           Flags
      $outer                         final synthetic
      resultOfTaggedAsInvocation     final
}
InnerClasses:
  public final #8= #2 of #7;              // InAndIgnoreMethodsAfterTaggedAs=class org/scalatest/flatspec/FixtureAsyncFlatSpecLike$InAndIgnoreMethodsAfterTaggedAs of class org/scalatest/flatspec/FixtureAsyncFlatSpecLike
SourceFile: "FixtureAsyncFlatSpecLike.scala"
  ScalaInlineInfo: length = 0x27 (unknown attribute)
   01 01 00 07 00 17 00 54 01 00 4E 00 0E 01 00 4E
   00 51 01 00 49 00 0E 01 00 38 00 0E 01 00 38 00
   51 01 00 0D 00 0E 01
  Scala: length = 0x0 (unknown attribute)

