Classfile /Users/mw/Projects/slang-braindump/.jar/jar11/assemble/slang-braindump/assemble/content/org/scalatest/flatspec/FixtureAnyFlatSpecLike.class
  Last modified May 29, 2022; size 30900 bytes
  SHA-256 checksum 18513c96936a2b16e8c5e015273f898696322b7415f0251b402de478c836fd7a
  Compiled from "FixtureAnyFlatSpecLike.scala"
public interface org.scalatest.flatspec.FixtureAnyFlatSpecLike extends org.scalatest.FixtureTestSuite,org.scalatest.FixtureTestRegistration,org.scalatest.verbs.ShouldVerb,org.scalatest.verbs.MustVerb,org.scalatest.verbs.CanVerb,org.scalatest.Informing,org.scalatest.Notifying,org.scalatest.Alerting,org.scalatest.Documenting
  minor version: 0
  major version: 52
  flags: (0x0601) ACC_PUBLIC, ACC_INTERFACE, ACC_ABSTRACT
  this_class: #2                          // org/scalatest/flatspec/FixtureAnyFlatSpecLike
  super_class: #4                         // java/lang/Object
  interfaces: 9, fields: 0, methods: 76, attributes: 6
Constant pool:
    #1 = Utf8               org/scalatest/flatspec/FixtureAnyFlatSpecLike
    #2 = Class              #1            // org/scalatest/flatspec/FixtureAnyFlatSpecLike
    #3 = Utf8               java/lang/Object
    #4 = Class              #3            // java/lang/Object
    #5 = Utf8               org/scalatest/FixtureTestSuite
    #6 = Class              #5            // org/scalatest/FixtureTestSuite
    #7 = Utf8               org/scalatest/FixtureTestRegistration
    #8 = Class              #7            // org/scalatest/FixtureTestRegistration
    #9 = Utf8               org/scalatest/verbs/ShouldVerb
   #10 = Class              #9            // org/scalatest/verbs/ShouldVerb
   #11 = Utf8               org/scalatest/verbs/MustVerb
   #12 = Class              #11           // org/scalatest/verbs/MustVerb
   #13 = Utf8               org/scalatest/verbs/CanVerb
   #14 = Class              #13           // org/scalatest/verbs/CanVerb
   #15 = Utf8               org/scalatest/Informing
   #16 = Class              #15           // org/scalatest/Informing
   #17 = Utf8               org/scalatest/Notifying
   #18 = Class              #17           // org/scalatest/Notifying
   #19 = Utf8               org/scalatest/Alerting
   #20 = Class              #19           // org/scalatest/Alerting
   #21 = Utf8               org/scalatest/Documenting
   #22 = Class              #21           // org/scalatest/Documenting
   #23 = Utf8               FixtureAnyFlatSpecLike.scala
   #24 = Utf8               Lorg/scalatest/Finders;
   #25 = Utf8               value
   #26 = Utf8               org.scalatest.finders.FlatSpecFinder
   #27 = Utf8               Lscala/reflect/ScalaSignature;
   #28 = Utf8               bytes
   #29 = Utf8               \u0006\u0005\u0019=aACA\u0010\u0003C\u0001\n1!\u0001\u00020!9\u00111\u0010\u0001\u0005\u0002\u0005u\u0004\"CAC\u0001\t\u0007IQBAD\u0011-\tY\n\u0001b\u0001\n\u0003\t)#!(\t\u000f\u0005=\u0006\u0001\"\u0005\u00022\"9\u0011\u0011\u0018\u0001\u0005\u0012\u0005m\u0006bBAb\u0001\u0011E\u0011Q\u0019\u0005\b\u0003\u001b\u0004A\u0011CAh\u0011\u001d\t9\u000e\u0001C\u0007\u00033DqA!\u000b\u0001\t\u000b\u0011Y\u0003C\u0004\u0003:\u0001!iAa\u000f\t\u000f\t\u001d\u0003\u0001\"\u0002\u0003J!9!q\u000b\u0001\u0005\n\te\u0003b\u0002B>\u0001\u0011%!Q\u0010\u0004\u0007\u0005#\u0003!Ba%\t\u000f\tUe\u0002\"\u0001\u0003\u0018\"9!1\u0014\b\u0005\u000e\tu\u0005b\u0002BS\u001d\u0011\u0005!q\u0015\u0005\n\u0005_\u0003!\u0019!C\t\u0005c3aAa-\u0001\u0015\tU\u0006B\u0003B\\\'\t\u0005\t\u0015!\u0003\u0003\u0006!Q!\u0011X\n\u0003\u0002\u0003\u0006IA!\u0002\t\u0015\tm6C!A!\u0002\u0013\u0011\t\u0007C\u0004\u0003\u0016N!\tA!0\t\u000f\t\u001d7\u0003\"\u0004\u0003J\"9!Q[\n\u0005\u0002\t]\u0007b\u0002Bk\'\u0011\u0005!q\u001c\u0005\b\u0005O\u001cB\u0011\u0001Bu\u0011\u001d\u00119p\u0005C\u0007\u0005sDqAa@\u0014\t\u0003\u0019\t\u0001C\u0004\u0003\u0000N!\ta!\u0003\u0007\r\rE\u0001ACB\n\u0011)\u00119l\bB\u0001B\u0003%!Q\u0001\u0005\u000b\u0005s{\"\u0011!Q\u0001\n\t\u0015\u0001b\u0002BK?\u0011\u00051Q\u0003\u0005\b\u0005\u000f|BQBB\u000f\u0011\u001d\u0011)n\bC\u0001\u0007GAqA!6 \t\u0003\u0019Y\u0003C\u0004\u0003h~!\taa\r\t\u000f\t]x\u0004\"\u0004\u0004<!9!q`\u0010\u0005\u0002\r\u0005\u0003b\u0002B\u0000?\u0011\u00051\u0011\n\u0005\b\u0007#zB\u0011AB*\r\u0019\u0019i\u0006\u0001\u0006\u0004`!9!QS\u0016\u0005\u0002\r\u0005\u0004bBB3W\u0011\u00051q\r\u0005\b\u0007[ZC\u0011AB8\u0011\u001d\u0019\u0019h\u000bC\u0001\u0007kBqa!\u001a,\t\u0003\u0019I\bC\u0004\u0004n-\"\ta!\"\t\u000f\rM4\u0006\"\u0001\u0004\n\"I1Q\u0012\u0001C\u0002\u0013E1q\u0012\u0004\u0007\u0007#\u0003!ba%\t\u0015\t]FG!A!\u0002\u0013\u0011)\u0001\u0003\u0006\u0003:R\u0012\t\u0011)A\u0005\u0005\u000bA!Ba/5\u0005\u0003\u0005\u000b\u0011\u0002B1\u0011\u001d\u0011)\n\u000eC\u0001\u0007+CqAa25\t\u001b\u0019y\nC\u0004\u0003VR\"\ta!*\t\u000f\tUG\u0007\"\u0001\u0004.\"9!q\u001d\u001b\u0005\u0002\rU\u0006b\u0002B|i\u001151Q\u0018\u0005\b\u0005\u007f$D\u0011ABb\u0011\u001d\u0011y\u0010\u000eC\u0001\u0007\u00174aaa5\u0001\u0015\rU\u0007B\u0003B\\\u0001\n\u0005\t\u0015!\u0003\u0003\u0006!Q!\u0011\u0018!\u0003\u0002\u0003\u0006IA!\u0002\t\u000f\tU\u0005\t\"\u0001\u0004X\"9!q\u0019!\u0005\u0002\r}\u0007b\u0002Bk\u0001\u0012\u00051Q\u001d\u0005\b\u0005+\u0004E\u0011ABw\u0011\u001d\u00119\u000f\u0011C\u0001\u0007kDqAa>A\t\u001b\u0019i\u0010C\u0004\u0003\u0000\u0002#\t\u0001b\u0001\t\u000f\t}\b\t\"\u0001\u0005\f!91\u0011\u000b!\u0005\u0002\u0011MaA\u0002C\r\u0001)!Y\u0002C\u0004\u0003\u00162#\t\u0001\"\b\t\u000f\r\u0015D\n\"\u0001\u0005\"!91Q\u000e\'\u0005\u0002\u0011\u0015\u0002bBB:\u0019\u0012\u0005A\u0011\u0006\u0005\b\u0007KbE\u0011\u0001C\u0017\u0011\u001d\u0019i\u0007\u0014C\u0001\tcAqaa\u001dM\t\u0003!)\u0004C\u0005\u0005:\u0001\u0011\r\u0011\"\u0005\u0005<\u00191AQ\b\u0001\u000b\t\u007fA!Ba.V\u0005\u0003\u0005\u000b\u0011\u0002B\u0003\u0011)\u0011I,\u0016B\u0001B\u0003%!Q\u0001\u0005\u000b\u0005w+&\u0011!Q\u0001\n\t\u0005\u0004b\u0002BK+\u0012\u0005A\u0011\t\u0005\b\u0005\u000f,FQ\u0002C&\u0011\u001d\u0011).\u0016C\u0001\t#BqA!6V\t\u0003!I\u0006C\u0004\u0003hV#\t\u0001\"\u0019\u0007\r\u0011%\u0004A\u0003C6\u0011)\u00119L\u0018B\u0001B\u0003%!Q\u0001\u0005\u000b\u0005ss&\u0011!Q\u0001\n\t\u0015\u0001b\u0002BK=\u0012\u0005AQ\u000e\u0005\b\u0005\u000ftFQ\u0002C;\u0011\u001d\u0011)N\u0018C\u0001\twBqA!6_\t\u0003!\u0019\tC\u0004\u0003hz#\t\u0001b#\t\u000f\rEc\f\"\u0001\u0005\u0014\u001a1A\u0011\u0014\u0001\u000b\t7CqA!&h\t\u0003!i\nC\u0004\u0004f\u001d$\t\u0001\")\t\u000f\r5t\r\"\u0001\u0005&\"911O4\u0005\u0002\u0011%\u0006\"\u0003B\u0000\u0001\t\u0007I\u0011\u0003CW\r\u0019!y\u000b\u0001\u0006\u00052\"QA1W7\u0003\u0002\u0003\u0006I\u0001\".\t\u000f\tUU\u000e\"\u0001\u0005<\"9!qY7\u0005\u000e\u0011\u0005\u0007b\u0002Bk[\u0012\u0005Aq\u0019\u0005\b\u0005olGQ\u0002Ch\u0011\u001d\u0011y0\u001cC\u0001\t+DqA!6n\t\u0003!i\u000eC\u0004\u0003\u00006$\t\u0001\":\t\u000f\u00115\b\u0001b\u0005\u0005p\u001a1A1\u001f\u0001\u000b\tkD!\u0002b>x\u0005\u0003\u0005\u000b\u0011\u0002C}\u0011\u001d\u0011)j\u001eC\u0001\t\u007fDqAa2x\t\u001b))\u0001C\u0004\u0003V^$\t!b\u0003\t\u000f\t]x\u000f\"\u0004\u0006\u0014!9!q`<\u0005\u0002\u0015e\u0001b\u0002Bko\u0012\u0005Q\u0011\u0005\u0005\b\u0005\u007f<H\u0011AC\u0015\u0011\u001d)\t\u0004\u0001C\n\u000bgA\u0011\"b\u000e\u0001\u0005\u0004%\u0019\"\"\u000f\t\u0013\u0015\u0005\u0003A1A\u0005\u0014\u0015\r\u0003bBC&\u0001\u0011%QQ\n\u0005\b\u000b3\u0002A\u0011BC.\u0011\u001d\u0011Y\f\u0001C!\u000bOBq!\"\u001e\u0001\t#*9\bC\u0004\u0006\u000e\u0002!\t&b$\t\u000f\u0015m\u0005\u0001\"\u0011\u0006\u001e\"9Qq\u0014\u0001\u0005B\u0015\u0005\u0006\"CCT\u0001\t\u0007I\u0011CCU\u0011%)Y\u000b\u0001b\u0001\n\u000b*i\u000bC\u0004\u0006D\u0002!\t%\"2\t\u0013\u0015e\u0007!%A\u0005\u0002\u0015m\u0007BDCy\u0001A\u0005\u0019\u0011!A\u0005\n\u0015MX\u0011 \u0002\u0017\r&DH/\u001e:f\u0003:Lh\t\\1u\'B,7\rT5lK*!\u00111EA\u0013\u0003!1G.\u0019;ta\u0016\u001c\'\u0002BA\u0014\u0003S\t\u0011b]2bY\u0006$Xm\u001d;\u000b\u0005\u0005-\u0012aA8sO\u000e\u00011#\u0006\u0001\u00022\u0005u\u0012QIA&\u0003/\ni&a\u0019\u0002j\u0005=\u0014Q\u000f\t\u0005\u0003g\tI$\u0004\u0002\u00026)\u0011\u0011qG\u0001\u0006g\u000e\fG.Y\u0005\u0005\u0003w\t)D\u0001\u0004B]f\u0014VM\u001a\t\u0005\u0003\u007f\t\t%\u0004\u0002\u0002&%!\u00111IA\u0013\u0005A1\u0015\u000e\u001f;ve\u0016$Vm\u001d;Tk&$X\r\u0005\u0003\u0002@\u0005\u001d\u0013\u0002BA%\u0003K\u0011qCR5yiV\u0014X\rV3tiJ+w-[:ue\u0006$\u0018n\u001c8\u0011\t\u00055\u00131K\u0007\u0003\u0003\u001fRA!!\u0015\u0002&\u0005)a/\u001a:cg&!\u0011QKA(\u0005)\u0019\u0006n\\;mIZ+\'O\u0019\t\u0005\u0003\u001b\nI&\u0003\u0003\u0002\\\u0005=#\u0001C\'vgR4VM\u001d2\u0011\t\u00055\u0013qL\u0005\u0005\u0003C\nyEA\u0004DC:4VM\u001d2\u0011\t\u0005}\u0012QM\u0005\u0005\u0003O\n)CA\u0005J]\u001a|\'/\\5oOB!\u0011qHA6\u0013\u0011\ti\'!\n\u0003\u00139{G/\u001b4zS:<\u0007\u0003BA \u0003cJA!a\u001d\u0002&\tA\u0011\t\\3si&tw\r\u0005\u0003\u0002@\u0005]\u0014\u0002BA=\u0003K\u00111\u0002R8dk6,g\u000e^5oO\u00061A%\u001b8ji\u0012\"\"!a \u0011\t\u0005M\u0012\u0011Q\u0005\u0005\u0003\u0007\u000b)D\u0001\u0003V]&$\u0018AB3oO&tW-\u0006\u0002\u0002\nB1\u0011qHAF\u0003\u001fKA!!$\u0002&\tia)\u001b=ukJ,WI\\4j]\u0016\u0004B!!%\u0002\u00146\t\u0001!\u0003\u0003\u0002\u0016\u0006]%\u0001\u0004$jqR,(/\u001a)be\u0006l\u0017\u0002BAM\u0003K\u0011ABR5yiV\u0014XmU;ji\u0016\fab]8ve\u000e,g)\u001b7f\u001d\u0006lW-\u0006\u0002\u0002 B!\u0011\u0011UAV\u001b\t\t\u0019K\u0003\u0003\u0002&\u0006\u001d\u0016\u0001\u00027b]\u001eT!!!+\u0002\t)\fg/Y\u0005\u0005\u0003[\u000b\u0019K\u0001\u0004TiJLgnZ\u0001\u0005S:4w.\u0006\u0002\u00024B!\u0011qHA[\u0013\u0011\t9,!\n\u0003\u0011%sgm\u001c:nKJ\fAA\\8uKV\u0011\u0011Q\u0018\t\u0005\u0003\u007f\ty,\u0003\u0003\u0002B\u0006\u0015\"\u0001\u0003(pi&4\u0017.\u001a:\u0002\u000b\u0005dWM\u001d;\u0016\u0005\u0005\u001d\u0007\u0003BA \u0003\u0013LA!a3\u0002&\t9\u0011\t\\3si\u0016\u0014\u0018AB7be.,\b/\u0006\u0002\u0002RB!\u0011qHAj\u0013\u0011\t).!\n\u0003\u0015\u0011{7-^7f]R,\'/\u0001\tsK\u001eL7\u000f^3s)\u0016\u001cH/S7qYR1\u00111\u001cB\u0001\u00053!b!a \u0002^\u00065\bbBAp\u0011\u0001\u0007\u0011\u0011]\u0001\bi\u0016\u001cHOR;o!!\t\u0019$a9\u0002\u0010\u0006\u001d\u0018\u0002BAs\u0003k\u0011\u0011BR;oGRLwN\\\u0019\u0011\t\u0005M\u0012\u0011^\u0005\u0005\u0003W\f)DA\u0002B]fDq!a<\t\u0001\u0004\t\t0A\u0002q_N\u0004B!a=\u0002~6\u0011\u0011Q\u001f\u0006\u0005\u0003o\fI0\u0001\u0004t_V\u00148-\u001a\u0006\u0005\u0003w\fI#A\u0005tG\u0006d\u0017m\u0019;jG&!\u0011q`A{\u0005!\u0001vn]5uS>t\u0007b\u0002B\u0002\u0011\u0001\u0007!QA\u0001\ti\u0016\u001cH\u000fV3yiB!!q\u0001B\u000b\u001d\u0011\u0011IA!\u0005\u0011\t\t-\u0011QG\u0007\u0003\u0005\u001bQAAa\u0004\u0002.\u00051AH]8pizJAAa\u0005\u00026\u00051\u0001K]3eK\u001aLA!!,\u0003\u0018)!!1CA\u001b\u0011\u001d\u0011Y\u0002\u0003a\u0001\u0005;\t\u0001\u0002^3tiR\u000bwm\u001d\t\u0007\u0003g\u0011yBa\t\n\t\t\u0005\u0012Q\u0007\u0002\u000byI,\u0007/Z1uK\u0012t\u0004\u0003BA \u0005KIAAa\n\u0002&\t\u0019A+Y4\u0002\u0019I,w-[:uKJ$Vm\u001d;\u0015\r\t5\"Q\u0007B\u001c)\u0011\u0011yCa\r\u0015\t\u0005}$\u0011\u0007\u0005\b\u0003_L\u00019AAy\u0011\u001d\ty.\u0003a\u0001\u0003CDqAa\u0001\n\u0001\u0004\u0011)\u0001C\u0004\u0003\u001c%\u0001\rA!\b\u0002/I,w-[:uKJLuM\\8sK\u0012$Vm\u001d;J[BdGC\u0002B\u001f\u0005\u0007\u0012)\u0005\u0006\u0004\u0002\u0000\t}\"\u0011\t\u0005\b\u0003?T\u0001\u0019AAq\u0011\u001d\tyO\u0003a\u0001\u0003cDqAa\u0001\u000b\u0001\u0004\u0011)\u0001C\u0004\u0003\u001c)\u0001\rA!\b\u0002\'I,w-[:uKJLuM\\8sK\u0012$Vm\u001d;\u0015\r\t-#1\u000bB+)\u0011\u0011iE!\u0015\u0015\t\u0005}$q\n\u0005\b\u0003_\\\u00019AAy\u0011\u001d\tyn\u0003a\u0001\u0003CDqAa\u0001\f\u0001\u0004\u0011)\u0001C\u0004\u0003\u001c-\u0001\rA!\b\u0002#I,w-[:uKJ$Vm\u001d;U_J+h\u000e\u0006\u0007\u0002\u0000\tm#q\fB:\u0005o\u0012I\bC\u0004\u0003^1\u0001\rA!\u0002\u0002\u0011M\u0004Xm\u0019+fqRDqAa\u0007\r\u0001\u0004\u0011\t\u0007\u0005\u0004\u0003d\t5$1\u0005\b\u0005\u0005K\u0012IG\u0004\u0003\u0003\f\t\u001d\u0014BAA\u001c\u0013\u0011\u0011Y\'!\u000e\u0002\u000fA\f7m[1hK&!!q\u000eB9\u0005\u0011a\u0015n\u001d;\u000b\t\t-\u0014Q\u0007\u0005\b\u0005kb\u0001\u0019\u0001B\u0003\u0003)iW\r\u001e5pI:\u000bW.\u001a\u0005\b\u0003?d\u0001\u0019AAq\u0011\u001d\ty\u000f\u0004a\u0001\u0003c\f\u0001D]3hSN$XM\u001d)f]\u0012Lgn\u001a+fgR$vNU;o)1\tyHa \u0003\u0002\n\r%Q\u0011BH\u0011\u001d\u0011i&\u0004a\u0001\u0005\u000bAqAa\u0007\u000e\u0001\u0004\u0011\t\u0007C\u0004\u0003v5\u0001\rA!\u0002\t\u000f\u0005}W\u00021\u0001\u0003\bBA\u00111GAr\u0003\u001f\u0013I\t\u0005\u0003\u0002@\t-\u0015\u0002\u0002BG\u0003K\u0011\u0001\u0003U3oI&twm\u0015;bi\u0016lWM\u001c;\t\u000f\u0005=X\u00021\u0001\u0002r\na!)\u001a5bm&|\'oV8sIN\u0019a\"!\r\u0002\rqJg.\u001b;?)\t\u0011I\nE\u0002\u0002\u0012:\taa\u001c4J[BdGCBA@\u0005?\u0013\u0019\u000bC\u0004\u0003\"B\u0001\rA!\u0002\u0002\u0017\u0011,7o\u0019:jaRLwN\u001c\u0005\b\u0003_\u0004\u0002\u0019AAy\u0003\tyg\r\u0006\u0003\u0003*\n5F\u0003BA@\u0005WCq!a<\u0012\u0001\b\t\t\u0010C\u0004\u0003\"F\u0001\rA!\u0002\u0002\u0011\t,\u0007.\u0019<j_J,\"A!\'\u0003)%#h+\u001a:c\'R\u0014\u0018N\\4UC\u001e<W\rZ!t\'\r\u0019\u0012\u0011G\u0001\u0005m\u0016\u0014(-\u0001\u0003oC6,\u0017\u0001\u0002;bON$\u0002Ba0\u0003B\n\r\'Q\u0019\t\u0004\u0003#\u001b\u0002b\u0002B\\/\u0001\u0007!Q\u0001\u0005\b\u0005s;\u0002\u0019\u0001B\u0003\u0011\u001d\u0011Yl\u0006a\u0001\u0005C\na!\u001b8J[BdGCBA@\u0005\u0017\u0014\u0019\u000eC\u0004\u0002`b\u0001\rA!4\u0011\r\u0005M\"qZAt\u0013\u0011\u0011\t.!\u000e\u0003\u0013\u0019+hn\u0019;j_:\u0004\u0004bBAx1\u0001\u0007\u0011\u0011_\u0001\u0003S:$BA!7\u0003^R!\u0011q\u0010Bn\u0011\u001d\ty/\u0007a\u0002\u0003cDq!a8\u001a\u0001\u0004\u0011i\r\u0006\u0003\u0003b\n\u0015H\u0003BA@\u0005GDq!a<\u001b\u0001\b\t\t\u0010C\u0004\u0002`j\u0001\r!!9\u0002\u0005%\u001cH\u0003\u0002Bv\u0005_$B!a \u0003n\"9\u0011q^\u000eA\u0004\u0005E\b\u0002CAp7\u0011\u0005\rA!=\u0011\r\u0005M\"1\u001fBE\u0013\u0011\u0011)0!\u000e\u0003\u0011q\u0012\u0017P\\1nKz\n!\"[4o_J,\u0017*\u001c9m)\u0019\tyHa?\u0003~\"9\u0011q\u001c\u000fA\u0002\t5\u0007bBAx9\u0001\u0007\u0011\u0011_\u0001\u0007S\u001etwN]3\u0015\t\r\r1q\u0001\u000b\u0005\u0003\u007f\u001a)\u0001C\u0004\u0002pv\u0001\u001d!!=\t\u000f\u0005}W\u00041\u0001\u0003NR!11BB\b)\u0011\tyh!\u0004\t\u000f\u0005=h\u0004q\u0001\u0002r\"9\u0011q\u001c\u0010A\u0002\u0005\u0005(\u0001D%u-\u0016\u0014(m\u0015;sS:<7cA\u0010\u00022Q11qCB\r\u00077\u00012!!% \u0011\u001d\u00119L\ta\u0001\u0005\u000bAqA!/#\u0001\u0004\u0011)\u0001\u0006\u0004\u0002\u0000\r}1\u0011\u0005\u0005\b\u0003?\u001c\u0003\u0019\u0001Bg\u0011\u001d\tyo\ta\u0001\u0003c$Ba!\n\u0004*Q!\u0011qPB\u0014\u0011\u001d\ty\u000f\na\u0002\u0003cDq!a8%\u0001\u0004\u0011i\r\u0006\u0003\u0004.\rEB\u0003BA@\u0007_Aq!a<&\u0001\b\t\t\u0010C\u0004\u0002`\u0016\u0002\r!!9\u0015\t\rU2\u0011\b\u000b\u0005\u0003\u007f\u001a9\u0004C\u0004\u0002p\u001a\u0002\u001d!!=\t\u0011\u0005}g\u0005\"a\u0001\u0005c$b!a \u0004>\r}\u0002bBApO\u0001\u0007!Q\u001a\u0005\b\u0003_<\u0003\u0019AAy)\u0011\u0019\u0019ea\u0012\u0015\t\u0005}4Q\t\u0005\b\u0003_D\u00039AAy\u0011\u001d\ty\u000e\u000ba\u0001\u0005\u001b$Baa\u0013\u0004PQ!\u0011qPB\'\u0011\u001d\ty/\u000ba\u0002\u0003cDq!a8*\u0001\u0004\t\t/\u0001\u0005uC\u001e<W\rZ!t)\u0019\u0011yl!\u0016\u0004Z!91q\u000b\u0016A\u0002\t\r\u0012\u0001\u00044jeN$H+Z:u)\u0006<\u0007bBB.U\u0001\u0007!QD\u0001\u000e_RDWM\u001d+fgR$\u0016mZ:\u0003\r%#xk\u001c:e\'\rY\u0013\u0011\u0007\u000b\u0003\u0007G\u00022!!%,\u0003\u0019\u0019\bn\\;mIR!1qCB5\u0011\u001d\u0019Y\'\fa\u0001\u0005\u000b\taa\u001d;sS:<\u0017\u0001B7vgR$Baa\u0006\u0004r!911\u000e\u0018A\u0002\t\u0015\u0011aA2b]R!1qCB<\u0011\u001d\u0019Yg\fa\u0001\u0005\u000b!Baa\u001f\u0004\u0002B!\u0011QJB?\u0013\u0011\u0019y(a\u0014\u0003\u0015\t+\u0007.\u0019<f/>\u0014H\rC\u0004\u0004\u0004B\u0002\raa\u001f\u0002\u0015\t,\u0007.\u0019<f/>\u0014H\r\u0006\u0003\u0004|\r\u001d\u0005bBBBc\u0001\u000711\u0010\u000b\u0005\u0007w\u001aY\tC\u0004\u0004\u0004J\u0002\raa\u001f\u0002\u0005%$XCAB2\u0005Y!\u0006.Z=WKJ\u00147\u000b\u001e:j]\u001e$\u0016mZ4fI\u0006\u001b8c\u0001\u001b\u00022QA1qSBM\u00077\u001bi\nE\u0002\u0002\u0012RBqAa.9\u0001\u0004\u0011)\u0001C\u0004\u0003:b\u0002\rA!\u0002\t\u000f\tm\u0006\b1\u0001\u0003bQ1\u0011qPBQ\u0007GCq!a8:\u0001\u0004\u0011i\rC\u0004\u0002pf\u0002\r!!=\u0015\t\r\u001d61\u0016\u000b\u0005\u0003\u007f\u001aI\u000bC\u0004\u0002pj\u0002\u001d!!=\t\u000f\u0005}\'\b1\u0001\u0003NR!1qVBZ)\u0011\tyh!-\t\u000f\u0005=8\bq\u0001\u0002r\"9\u0011q\\\u001eA\u0002\u0005\u0005H\u0003BB\\\u0007w#B!a \u0004:\"9\u0011q\u001e\u001fA\u0004\u0005E\b\u0002CApy\u0011\u0005\rA!=\u0015\r\u0005}4qXBa\u0011\u001d\ty.\u0010a\u0001\u0005\u001bDq!a<>\u0001\u0004\t\t\u0010\u0006\u0003\u0004F\u000e%G\u0003BA@\u0007\u000fDq!a<?\u0001\b\t\t\u0010C\u0004\u0002`z\u0002\rA!4\u0015\t\r57\u0011\u001b\u000b\u0005\u0003\u007f\u001ay\rC\u0004\u0002p~\u0002\u001d!!=\t\u000f\u0005}w\b1\u0001\u0002b\nqA\u000b[3z-\u0016\u0014(m\u0015;sS:<7c\u0001!\u00022Q11\u0011\\Bn\u0007;\u00042!!%A\u0011\u001d\u00119l\u0011a\u0001\u0005\u000bAqA!/D\u0001\u0004\u0011)\u0001\u0006\u0004\u0002\u0000\r\u000581\u001d\u0005\b\u0003?$\u0005\u0019\u0001Bg\u0011\u001d\ty\u000f\u0012a\u0001\u0003c$Baa:\u0004lR!\u0011qPBu\u0011\u001d\ty/\u0012a\u0002\u0003cDq!a8F\u0001\u0004\u0011i\r\u0006\u0003\u0004p\u000eMH\u0003BA@\u0007cDq!a<G\u0001\b\t\t\u0010C\u0004\u0002`\u001a\u0003\r!!9\u0015\t\r]81 \u000b\u0005\u0003\u007f\u001aI\u0010C\u0004\u0002p\u001e\u0003\u001d!!=\t\u0011\u0005}w\t\"a\u0001\u0005c$b!a \u0004\u0000\u0012\u0005\u0001bBAp\u0011\u0002\u0007!Q\u001a\u0005\b\u0003_D\u0005\u0019AAy)\u0011!)\u0001\"\u0003\u0015\t\u0005}Dq\u0001\u0005\b\u0003_L\u00059AAy\u0011\u001d\ty.\u0013a\u0001\u0005\u001b$B\u0001\"\u0004\u0005\u0012Q!\u0011q\u0010C\b\u0011\u001d\tyO\u0013a\u0002\u0003cDq!a8K\u0001\u0004\t\t\u000f\u0006\u0004\u0003@\u0012UAq\u0003\u0005\b\u0007/Z\u0005\u0019\u0001B\u0012\u0011\u001d\u0019Yf\u0013a\u0001\u0005;\u0011\u0001\u0002\u00165fs^{\'\u000fZ\n\u0004\u0019\u0006EBC\u0001C\u0010!\r\t\t\n\u0014\u000b\u0005\u0007/!\u0019\u0003C\u0004\u0004l9\u0003\rA!\u0002\u0015\t\r]Aq\u0005\u0005\b\u0007Wz\u0005\u0019\u0001B\u0003)\u0011\u00199\u0002b\u000b\t\u000f\r-\u0004\u000b1\u0001\u0003\u0006Q!11\u0010C\u0018\u0011\u001d\u0019\u0019)\u0015a\u0001\u0007w\"Baa\u001f\u00054!911\u0011*A\u0002\rmD\u0003BB>\toAqaa!T\u0001\u0004\u0019Y(\u0001\u0003uQ\u0016LXC\u0001C\u0010\u0005aIuM\\8sKZ+\'OY*ue&tw\rV1hO\u0016$\u0017i]\n\u0004+\u0006EB\u0003\u0003C\"\t\u000b\"9\u0005\"\u0013\u0011\u0007\u0005EU\u000bC\u0004\u00038f\u0003\rA!\u0002\t\u000f\te\u0016\f1\u0001\u0003\u0006!9!1X-A\u0002\t\u0005DCBA@\t\u001b\"y\u0005C\u0004\u0002`j\u0003\rA!4\t\u000f\u0005=(\f1\u0001\u0002rR!A1\u000bC,)\u0011\ty\b\"\u0016\t\u000f\u0005=8\fq\u0001\u0002r\"9\u0011q\\.A\u0002\t5G\u0003\u0002C.\t?\"B!a \u0005^!9\u0011q\u001e/A\u0004\u0005E\bbBAp9\u0002\u0007\u0011\u0011\u001d\u000b\u0005\tG\"9\u0007\u0006\u0003\u0002\u0000\u0011\u0015\u0004bBAx;\u0002\u000f\u0011\u0011\u001f\u0005\t\u0003?lF\u00111\u0001\u0003r\n\u0001\u0012j\u001a8pe\u00164VM\u001d2TiJLgnZ\n\u0004=\u0006EBC\u0002C8\tc\"\u0019\bE\u0002\u0002\u0012zCqAa.b\u0001\u0004\u0011)\u0001C\u0004\u0003:\u0006\u0004\rA!\u0002\u0015\r\u0005}Dq\u000fC=\u0011\u001d\tyN\u0019a\u0001\u0005\u001bDq!a<c\u0001\u0004\t\t\u0010\u0006\u0003\u0005~\u0011\u0005E\u0003BA@\t\u007fBq!a<d\u0001\b\t\t\u0010C\u0004\u0002`\u000e\u0004\rA!4\u0015\t\u0011\u0015E\u0011\u0012\u000b\u0005\u0003\u007f\"9\tC\u0004\u0002p\u0012\u0004\u001d!!=\t\u000f\u0005}G\r1\u0001\u0002bR!AQ\u0012CI)\u0011\ty\bb$\t\u000f\u0005=X\rq\u0001\u0002r\"A\u0011q\\3\u0005\u0002\u0004\u0011\t\u0010\u0006\u0004\u0005D\u0011UEq\u0013\u0005\b\u0007/2\u0007\u0019\u0001B\u0012\u0011\u001d\u0019YF\u001aa\u0001\u0005;\u0011!\"S4o_J,wk\u001c:e\'\r9\u0017\u0011\u0007\u000b\u0003\t?\u00032!!%h)\u0011!y\u0007b)\t\u000f\r-\u0014\u000e1\u0001\u0003\u0006Q!Aq\u000eCT\u0011\u001d\u0019YG\u001ba\u0001\u0005\u000b!B\u0001b\u001c\u0005,\"911N6A\u0002\t\u0015QC\u0001CP\u0005IIe.\u00118e\u0013\u001etwN]3NKRDw\u000eZ:\u0014\u00075\f\t$\u0001\u000esKN,H\u000e^(g\'R\u0014\u0018N\\4QCN\u001cX\r\u001a+p-\u0016\u0014(\r\u0005\u0003\u0002N\u0011]\u0016\u0002\u0002C]\u0003\u001f\u0012!DU3tk2$xJZ*ue&tw\rU1tg\u0016$Gk\u001c,fe\n$B\u0001\"0\u0005@B\u0019\u0011\u0011S7\t\u000f\u0011Mv\u000e1\u0001\u00056R1\u0011q\u0010Cb\t\u000bDq!a8q\u0001\u0004\u0011i\rC\u0004\u0002pB\u0004\r!!=\u0015\t\u0011%GQ\u001a\u000b\u0005\u0003\u007f\"Y\rC\u0004\u0002pF\u0004\u001d!!=\t\u000f\u0005}\u0017\u000f1\u0001\u0003NR1\u0011q\u0010Ci\t\'Dq!a8s\u0001\u0004\u0011i\rC\u0004\u0002pJ\u0004\r!!=\u0015\t\u0011]G1\u001c\u000b\u0005\u0003\u007f\"I\u000eC\u0004\u0002pN\u0004\u001d!!=\t\u000f\u0005}7\u000f1\u0001\u0003NR!Aq\u001cCr)\u0011\ty\b\"9\t\u000f\u0005=H\u000fq\u0001\u0002r\"9\u0011q\u001c;A\u0002\u0005\u0005H\u0003\u0002Ct\tW$B!a \u0005j\"9\u0011q^;A\u0004\u0005E\bbBApk\u0002\u0007\u0011\u0011]\u0001\u001cG>tg/\u001a:u)>Le.\u00118e\u0013\u001etwN]3NKRDw\u000eZ:\u0015\t\u0011uF\u0011\u001f\u0005\b\tg3\b\u0019\u0001C[\u0005}Ie.\u00118e\u0013\u001etwN]3NKRDw\u000eZ:BMR,\'\u000fV1hO\u0016$\u0017i]\n\u0004o\u0006E\u0012A\u0007:fgVdGo\u00144UC\u001e<W\rZ!t\u0013:4xnY1uS>t\u0007\u0003BA\'\twLA\u0001\"@\u0002P\tQ\"+Z:vYR|e\rV1hO\u0016$\u0017i]%om>\u001c\u0017\r^5p]R!Q\u0011AC\u0002!\r\t\tj\u001e\u0005\b\toL\b\u0019\u0001C})\u0019\ty(b\u0002\u0006\n!9\u0011q\u001c>A\u0002\t5\u0007bBAxu\u0002\u0007\u0011\u0011\u001f\u000b\u0005\u000b\u001b)\t\u0002\u0006\u0003\u0002\u0000\u0015=\u0001bBAxw\u0002\u000f\u0011\u0011\u001f\u0005\b\u0003?\\\b\u0019\u0001Bg)\u0019\ty(\"\u0006\u0006\u0018!9\u0011q\u001c?A\u0002\t5\u0007bBAxy\u0002\u0007\u0011\u0011\u001f\u000b\u0005\u000b7)y\u0002\u0006\u0003\u0002\u0000\u0015u\u0001bBAx{\u0002\u000f\u0011\u0011\u001f\u0005\b\u0003?l\b\u0019\u0001Bg)\u0011)\u0019#b\n\u0015\t\u0005}TQ\u0005\u0005\b\u0003_t\b9AAy\u0011\u001d\tyN a\u0001\u0003C$B!b\u000b\u00060Q!\u0011qPC\u0017\u0011\u001d\tyo a\u0002\u0003cDq!a8\u0000\u0001\u0004\t\t/\u0001\u0015d_:4XM\u001d;U_&s\u0017I\u001c3JO:|\'/Z\'fi\"|Gm]!gi\u0016\u0014H+Y4hK\u0012\f5\u000f\u0006\u0003\u0006\u0002\u0015U\u0002\u0002\u0003C|\u0003\u0003\u0001\r\u0001\"?\u0002CMDwN\u001d;iC:$G+Z:u%\u0016<\u0017n\u001d;sCRLwN\u001c$v]\u000e$\u0018n\u001c8\u0016\u0005\u0015m\u0002\u0003BA\'\u000b{IA!b\u0010\u0002P\tQ2\u000b\u001e:j]\u001e4VM\u001d2TiJLgnZ%om>\u001c\u0017\r^5p]\u000693\u000f[8si\"\fg\u000eZ*iCJ,G\rV3tiJ+w-[:ue\u0006$\u0018n\u001c8Gk:\u001cG/[8o+\t))\u0005\u0005\u0003\u0002N\u0015\u001d\u0013\u0002BC%\u0003\u001f\u0012ad\u0015;sS:<g+\u001a:c\u0005\u0016D\u0017M^3MS.,\u0017J\u001c<pG\u0006$\u0018n\u001c8\u0002)I,w-[:uKJ$Vm\u001d;U_&;gn\u001c:f)1\ty(b\u0014\u0006R\u0015MSQKC,\u0011!\u0011i&a\u0002A\u0002\t\u0015\u0001\u0002\u0003B\u000e\u0003\u000f\u0001\rA!\u0019\t\u0011\tU\u0014q\u0001a\u0001\u0005\u000bA\u0001\"a8\u0002\b\u0001\u0007\u0011\u0011\u001d\u0005\t\u0003_\f9\u00011\u0001\u0002r\u0006Y\"/Z4jgR,\'\u000fU3oI&tw\rV3tiR{\u0017j\u001a8pe\u0016$B\"a \u0006^\u0015}S\u0011MC2\u000bKB\u0001B!\u0018\u0002\n\u0001\u0007!Q\u0001\u0005\t\u00057\tI\u00011\u0001\u0003b!A!QOA\u0005\u0001\u0004\u0011)\u0001\u0003\u0005\u0002`\u0006%\u0001\u0019\u0001BD\u0011!\ty/!\u0003A\u0002\u0005EXCAC5!!\u00119!b\u001b\u0003\u0006\u0015=\u0014\u0002BC7\u0005/\u00111!T1q!\u0019\u00119!\"\u001d\u0003\u0006%!Q1\u000fB\f\u0005\r\u0019V\r^\u0001\beVtG+Z:u)\u0019)I(b \u0006\u0004B!\u0011qHC>\u0013\u0011)i(!\n\u0003\rM#\u0018\r^;t\u0011!)\t)!\u0004A\u0002\t\u0015\u0011\u0001\u0003;fgRt\u0015-\\3\t\u0011\u0015\u0015\u0015Q\u0002a\u0001\u000b\u000f\u000bA!\u0019:hgB!\u0011qHCE\u0013\u0011)Y)!\n\u0003\t\u0005\u0013xm]\u0001\teVtG+Z:ugR1Q\u0011PCI\u000b3C\u0001\"\"!\u0002\u0010\u0001\u0007Q1\u0013\t\u0007\u0003g))J!\u0002\n\t\u0015]\u0015Q\u0007\u0002\u0007\u001fB$\u0018n\u001c8\t\u0011\u0015\u0015\u0015q\u0002a\u0001\u000b\u000f\u000b\u0011\u0002^3ti:\u000bW.Z:\u0016\u0005\u0015=\u0014a\u0001:v]R1Q\u0011PCR\u000bKC\u0001\"\"!\u0002\u0014\u0001\u0007Q1\u0013\u0005\t\u000b\u000b\u000b\u0019\u00021\u0001\u0006\b\u00061!-\u001a5bm\u0016,\"aa\u001f\u0002\u0013M$\u0018\u0010\\3OC6,WC\u0001B\u0003Q1\t9\"\"-\u00068\u0016eVQXC`!\u0011\t\u0019$b-\n\t\u0015U\u0016Q\u0007\u0002\u000bI\u0016\u0004(/Z2bi\u0016$\u0017aB7fgN\fw-Z\u0011\u0003\u000bw\u000bA\u0010\u00165fAM$\u0018\u0010\\3OC6,\u0007\u0005\\5gK\u000eL8\r\\3![\u0016$\bn\u001c3!Q\u0006\u001c\bEY3f]\u0002\"W\r\u001d:fG\u0006$X\r\u001a\u0011b]\u0012\u0004s/\u001b7mA\t,\u0007E]3n_Z,G\rI5oA\u0005\u0004c-\u001e;ve\u0016\u0004c/\u001a:tS>t\u0007e\u001c4!\'\u000e\fG.\u0019+fgR\u0004s/\u001b;iA9|\u0007E]3qY\u0006\u001cW-\\3oi:\nQa]5oG\u0016\f#!\"1\u0002\u000bMr\u0013G\f\u0019\u0002\u0017Q,7\u000f\u001e#bi\u00064uN\u001d\u000b\u0007\u000b\u000f,i-b4\u0011\t\u0005}R\u0011Z\u0005\u0005\u000b\u0017\f)C\u0001\u0005UKN$H)\u0019;b\u0011!)\t)!\u0007A\u0002\t\u0015\u0001BCCi\u00033\u0001\n\u00111\u0001\u0006T\u0006aA\u000f[3D_:4\u0017nZ\'baB!\u0011qHCk\u0013\u0011)9.!\n\u0003\u0013\r{gNZ5h\u001b\u0006\u0004\u0018!\u0006;fgR$\u0015\r^1G_J$C-\u001a4bk2$HEM\u000b\u0003\u000b;TC!b5\u0006`.\u0012Q\u0011\u001d\t\u0005\u000bG,i/\u0004\u0002\u0006f*!Qq]Cu\u0003%)hn\u00195fG.,GM\u0003\u0003\u0006l\u0006U\u0012AC1o]>$\u0018\r^5p]&!Qq^Cs\u0005E)hn\u00195fG.,GMV1sS\u0006t7-Z\u0001\ngV\u0004XM\u001d\u0013sk:$b!\"\u001f\u0006v\u0016]\b\u0002CCA\u0003;\u0001\r!b%\t\u0011\u0015\u0015\u0015Q\u0004a\u0001\u000b\u000fKA!b(\u0006|&!QQ`A\u0013\u0005\u0015\u0019V/\u001b;fQ\u001d\u0001a\u0011\u0001D\u0004\r\u0013\u0001B!a\u0010\u0007\u0004%!aQAA\u0013\u0005\u001d1\u0015N\u001c3feN\fQA^1mk\u0016d#Ab\u0003\"\u0005\u00195\u0011\u0001J8sO:\u001a8-\u00197bi\u0016\u001cHO\f4j]\u0012,\'o\u001d\u0018GY\u0006$8\u000b]3d\r&tG-\u001a:
   #30 = Utf8               java/lang/invoke/MethodHandles$Lookup
   #31 = Class              #30           // java/lang/invoke/MethodHandles$Lookup
   #32 = Utf8               java/lang/invoke/MethodHandles
   #33 = Class              #32           // java/lang/invoke/MethodHandles
   #34 = Utf8               Lookup
   #35 = Utf8               org/scalatest/FixtureTestSuite$FixturelessTestFunAndConfigMap
   #36 = Class              #35           // org/scalatest/FixtureTestSuite$FixturelessTestFunAndConfigMap
   #37 = Utf8               FixturelessTestFunAndConfigMap
   #38 = Utf8               org/scalatest/FixtureTestSuite$OneArgTest
   #39 = Class              #38           // org/scalatest/FixtureTestSuite$OneArgTest
   #40 = Utf8               OneArgTest
   #41 = Utf8               org/scalatest/FixtureTestSuite$TestFunAndConfigMap
   #42 = Class              #41           // org/scalatest/FixtureTestSuite$TestFunAndConfigMap
   #43 = Utf8               TestFunAndConfigMap
   #44 = Utf8               org/scalatest/SuperEngine$Bundle
   #45 = Class              #44           // org/scalatest/SuperEngine$Bundle
   #46 = Utf8               org/scalatest/SuperEngine
   #47 = Class              #46           // org/scalatest/SuperEngine
   #48 = Utf8               Bundle
   #49 = Utf8               org/scalatest/SuperEngine$TestLeaf
   #50 = Class              #49           // org/scalatest/SuperEngine$TestLeaf
   #51 = Utf8               TestLeaf
   #52 = Utf8               org/scalatest/TestSuite$NoArgTest
   #53 = Class              #52           // org/scalatest/TestSuite$NoArgTest
   #54 = Utf8               org/scalatest/TestSuite
   #55 = Class              #54           // org/scalatest/TestSuite
   #56 = Utf8               NoArgTest
   #57 = Utf8               org/scalatest/flatspec/FixtureAnyFlatSpecLike$$anon$1
   #58 = Class              #57           // org/scalatest/flatspec/FixtureAnyFlatSpecLike$$anon$1
   #59 = Utf8               org/scalatest/flatspec/FixtureAnyFlatSpecLike$$anon$4
   #60 = Class              #59           // org/scalatest/flatspec/FixtureAnyFlatSpecLike$$anon$4
   #61 = Utf8               org/scalatest/flatspec/FixtureAnyFlatSpecLike$BehaviorWord
   #62 = Class              #61           // org/scalatest/flatspec/FixtureAnyFlatSpecLike$BehaviorWord
   #63 = Utf8               BehaviorWord
   #64 = Utf8               org/scalatest/flatspec/FixtureAnyFlatSpecLike$IgnoreVerbString
   #65 = Class              #64           // org/scalatest/flatspec/FixtureAnyFlatSpecLike$IgnoreVerbString
   #66 = Utf8               IgnoreVerbString
   #67 = Utf8               org/scalatest/flatspec/FixtureAnyFlatSpecLike$IgnoreVerbStringTaggedAs
   #68 = Class              #67           // org/scalatest/flatspec/FixtureAnyFlatSpecLike$IgnoreVerbStringTaggedAs
   #69 = Utf8               IgnoreVerbStringTaggedAs
   #70 = Utf8               org/scalatest/flatspec/FixtureAnyFlatSpecLike$IgnoreWord
   #71 = Class              #70           // org/scalatest/flatspec/FixtureAnyFlatSpecLike$IgnoreWord
   #72 = Utf8               IgnoreWord
   #73 = Utf8               org/scalatest/flatspec/FixtureAnyFlatSpecLike$InAndIgnoreMethods
   #74 = Class              #73           // org/scalatest/flatspec/FixtureAnyFlatSpecLike$InAndIgnoreMethods
   #75 = Utf8               InAndIgnoreMethods
   #76 = Utf8               org/scalatest/flatspec/FixtureAnyFlatSpecLike$InAndIgnoreMethodsAfterTaggedAs
   #77 = Class              #76           // org/scalatest/flatspec/FixtureAnyFlatSpecLike$InAndIgnoreMethodsAfterTaggedAs
   #78 = Utf8               InAndIgnoreMethodsAfterTaggedAs
   #79 = Utf8               org/scalatest/flatspec/FixtureAnyFlatSpecLike$ItVerbString
   #80 = Class              #79           // org/scalatest/flatspec/FixtureAnyFlatSpecLike$ItVerbString
   #81 = Utf8               ItVerbString
   #82 = Utf8               org/scalatest/flatspec/FixtureAnyFlatSpecLike$ItVerbStringTaggedAs
   #83 = Class              #82           // org/scalatest/flatspec/FixtureAnyFlatSpecLike$ItVerbStringTaggedAs
   #84 = Utf8               ItVerbStringTaggedAs
   #85 = Utf8               org/scalatest/flatspec/FixtureAnyFlatSpecLike$ItWord
   #86 = Class              #85           // org/scalatest/flatspec/FixtureAnyFlatSpecLike$ItWord
   #87 = Utf8               ItWord
   #88 = Utf8               org/scalatest/flatspec/FixtureAnyFlatSpecLike$TheyVerbString
   #89 = Class              #88           // org/scalatest/flatspec/FixtureAnyFlatSpecLike$TheyVerbString
   #90 = Utf8               TheyVerbString
   #91 = Utf8               org/scalatest/flatspec/FixtureAnyFlatSpecLike$TheyVerbStringTaggedAs
   #92 = Class              #91           // org/scalatest/flatspec/FixtureAnyFlatSpecLike$TheyVerbStringTaggedAs
   #93 = Utf8               TheyVerbStringTaggedAs
   #94 = Utf8               org/scalatest/flatspec/FixtureAnyFlatSpecLike$TheyWord
   #95 = Class              #94           // org/scalatest/flatspec/FixtureAnyFlatSpecLike$TheyWord
   #96 = Utf8               TheyWord
   #97 = Utf8               org$scalatest$flatspec$FixtureAnyFlatSpecLike$_setter_$org$scalatest$flatspec$FixtureAnyFlatSpecLike$$engine_$eq
   #98 = Utf8               (Lorg/scalatest/FixtureEngine;)V
   #99 = Utf8               (Lorg/scalatest/FixtureEngine<Ljava/lang/Object;>;)V
  #100 = Utf8               x$1
  #101 = Utf8               org$scalatest$flatspec$FixtureAnyFlatSpecLike$_setter_$sourceFileName_$eq
  #102 = Utf8               (Ljava/lang/String;)V
  #103 = Utf8               org$scalatest$flatspec$FixtureAnyFlatSpecLike$_setter_$behavior_$eq
  #104 = Utf8               (Lorg/scalatest/flatspec/FixtureAnyFlatSpecLike$BehaviorWord;)V
  #105 = Utf8               org$scalatest$flatspec$FixtureAnyFlatSpecLike$_setter_$it_$eq
  #106 = Utf8               (Lorg/scalatest/flatspec/FixtureAnyFlatSpecLike$ItWord;)V
  #107 = Utf8               org$scalatest$flatspec$FixtureAnyFlatSpecLike$_setter_$they_$eq
  #108 = Utf8               (Lorg/scalatest/flatspec/FixtureAnyFlatSpecLike$TheyWord;)V
  #109 = Utf8               org$scalatest$flatspec$FixtureAnyFlatSpecLike$_setter_$ignore_$eq
  #110 = Utf8               (Lorg/scalatest/flatspec/FixtureAnyFlatSpecLike$IgnoreWord;)V
  #111 = Utf8               org$scalatest$flatspec$FixtureAnyFlatSpecLike$_setter_$shorthandTestRegistrationFunction_$eq
  #112 = Utf8               (Lorg/scalatest/verbs/StringVerbStringInvocation;)V
  #113 = Utf8               org$scalatest$flatspec$FixtureAnyFlatSpecLike$_setter_$shorthandSharedTestRegistrationFunction_$eq
  #114 = Utf8               (Lorg/scalatest/verbs/StringVerbBehaveLikeInvocation;)V
  #115 = Utf8               org$scalatest$flatspec$FixtureAnyFlatSpecLike$_setter_$behave_$eq
  #116 = Utf8               (Lorg/scalatest/verbs/BehaveWord;)V
  #117 = Utf8               org$scalatest$flatspec$FixtureAnyFlatSpecLike$_setter_$styleName_$eq
  #118 = Utf8               org$scalatest$flatspec$FixtureAnyFlatSpecLike$$super$run
  #119 = Utf8               (Lscala/Option;Lorg/scalatest/Args;)Lorg/scalatest/Status;
  #120 = Utf8               testName
  #121 = Utf8               args
  #122 = Utf8               org$scalatest$flatspec$FixtureAnyFlatSpecLike$$engine
  #123 = Utf8               ()Lorg/scalatest/FixtureEngine;
  #124 = Utf8               ()Lorg/scalatest/FixtureEngine<Ljava/lang/Object;>;
  #125 = Utf8               sourceFileName
  #126 = Utf8               ()Ljava/lang/String;
  #127 = Utf8               info$
  #128 = Utf8               (Lorg/scalatest/flatspec/FixtureAnyFlatSpecLike;)Lorg/scalatest/Informer;
  #129 = Utf8               $this
  #130 = Utf8               info
  #131 = Utf8               ()Lorg/scalatest/Informer;
  #132 = NameAndType        #130:#131     // info:()Lorg/scalatest/Informer;
  #133 = InterfaceMethodref #2.#132       // org/scalatest/flatspec/FixtureAnyFlatSpecLike.info:()Lorg/scalatest/Informer;
  #134 = Utf8               Lorg/scalatest/flatspec/FixtureAnyFlatSpecLike;
  #135 = NameAndType        #122:#123     // org$scalatest$flatspec$FixtureAnyFlatSpecLike$$engine:()Lorg/scalatest/FixtureEngine;
  #136 = InterfaceMethodref #2.#135       // org/scalatest/flatspec/FixtureAnyFlatSpecLike.org$scalatest$flatspec$FixtureAnyFlatSpecLike$$engine:()Lorg/scalatest/FixtureEngine;
  #137 = Utf8               org/scalatest/FixtureEngine
  #138 = Class              #137          // org/scalatest/FixtureEngine
  #139 = Utf8               atomicInformer
  #140 = Utf8               ()Ljava/util/concurrent/atomic/AtomicReference;
  #141 = NameAndType        #139:#140     // atomicInformer:()Ljava/util/concurrent/atomic/AtomicReference;
  #142 = Methodref          #138.#141     // org/scalatest/FixtureEngine.atomicInformer:()Ljava/util/concurrent/atomic/AtomicReference;
  #143 = Utf8               java/util/concurrent/atomic/AtomicReference
  #144 = Class              #143          // java/util/concurrent/atomic/AtomicReference
  #145 = Utf8               get
  #146 = Utf8               ()Ljava/lang/Object;
  #147 = NameAndType        #145:#146     // get:()Ljava/lang/Object;
  #148 = Methodref          #144.#147     // java/util/concurrent/atomic/AtomicReference.get:()Ljava/lang/Object;
  #149 = Utf8               org/scalatest/Informer
  #150 = Class              #149          // org/scalatest/Informer
  #151 = Utf8               this
  #152 = Utf8               note$
  #153 = Utf8               (Lorg/scalatest/flatspec/FixtureAnyFlatSpecLike;)Lorg/scalatest/Notifier;
  #154 = Utf8               note
  #155 = Utf8               ()Lorg/scalatest/Notifier;
  #156 = NameAndType        #154:#155     // note:()Lorg/scalatest/Notifier;
  #157 = InterfaceMethodref #2.#156       // org/scalatest/flatspec/FixtureAnyFlatSpecLike.note:()Lorg/scalatest/Notifier;
  #158 = Utf8               atomicNotifier
  #159 = NameAndType        #158:#140     // atomicNotifier:()Ljava/util/concurrent/atomic/AtomicReference;
  #160 = Methodref          #138.#159     // org/scalatest/FixtureEngine.atomicNotifier:()Ljava/util/concurrent/atomic/AtomicReference;
  #161 = Utf8               org/scalatest/Notifier
  #162 = Class              #161          // org/scalatest/Notifier
  #163 = Utf8               alert$
  #164 = Utf8               (Lorg/scalatest/flatspec/FixtureAnyFlatSpecLike;)Lorg/scalatest/Alerter;
  #165 = Utf8               alert
  #166 = Utf8               ()Lorg/scalatest/Alerter;
  #167 = NameAndType        #165:#166     // alert:()Lorg/scalatest/Alerter;
  #168 = InterfaceMethodref #2.#167       // org/scalatest/flatspec/FixtureAnyFlatSpecLike.alert:()Lorg/scalatest/Alerter;
  #169 = Utf8               atomicAlerter
  #170 = NameAndType        #169:#140     // atomicAlerter:()Ljava/util/concurrent/atomic/AtomicReference;
  #171 = Methodref          #138.#170     // org/scalatest/FixtureEngine.atomicAlerter:()Ljava/util/concurrent/atomic/AtomicReference;
  #172 = Utf8               org/scalatest/Alerter
  #173 = Class              #172          // org/scalatest/Alerter
  #174 = Utf8               markup$
  #175 = Utf8               (Lorg/scalatest/flatspec/FixtureAnyFlatSpecLike;)Lorg/scalatest/Documenter;
  #176 = Utf8               markup
  #177 = Utf8               ()Lorg/scalatest/Documenter;
  #178 = NameAndType        #176:#177     // markup:()Lorg/scalatest/Documenter;
  #179 = InterfaceMethodref #2.#178       // org/scalatest/flatspec/FixtureAnyFlatSpecLike.markup:()Lorg/scalatest/Documenter;
  #180 = Utf8               atomicDocumenter
  #181 = NameAndType        #180:#140     // atomicDocumenter:()Ljava/util/concurrent/atomic/AtomicReference;
  #182 = Methodref          #138.#181     // org/scalatest/FixtureEngine.atomicDocumenter:()Ljava/util/concurrent/atomic/AtomicReference;
  #183 = Utf8               org/scalatest/Documenter
  #184 = Class              #183          // org/scalatest/Documenter
  #185 = Utf8               registerTestImpl
  #186 = Utf8               (Ljava/lang/String;Lscala/collection/immutable/Seq;Lscala/Function1;Lorg/scalactic/source/Position;)V
  #187 = Utf8               (Ljava/lang/String;Lscala/collection/immutable/Seq<Lorg/scalatest/Tag;>;Lscala/Function1<Ljava/lang/Object;Ljava/lang/Object;>;Lorg/scalactic/source/Position;)V
  #188 = Utf8               testText
  #189 = Utf8               testTags
  #190 = Utf8               testFun
  #191 = Utf8               pos
  #192 = Utf8               org/scalatest/fixture/Transformer
  #193 = Class              #192          // org/scalatest/fixture/Transformer
  #194 = Utf8               <init>
  #195 = Utf8               (Lscala/Function1;)V
  #196 = NameAndType        #194:#195     // "<init>":(Lscala/Function1;)V
  #197 = Methodref          #193.#196     // org/scalatest/fixture/Transformer."<init>":(Lscala/Function1;)V
  #198 = MethodType         #146          //  ()Ljava/lang/Object;
  #199 = Utf8               $anonfun$registerTestImpl$1
  #200 = NameAndType        #199:#126     // $anonfun$registerTestImpl$1:()Ljava/lang/String;
  #201 = InterfaceMethodref #2.#200       // org/scalatest/flatspec/FixtureAnyFlatSpecLike.$anonfun$registerTestImpl$1:()Ljava/lang/String;
  #202 = MethodHandle       6:#201        // REF_invokeStatic org/scalatest/flatspec/FixtureAnyFlatSpecLike.$anonfun$registerTestImpl$1:()Ljava/lang/String;
  #203 = MethodType         #126          //  ()Ljava/lang/String;
  #204 = Integer            5
  #205 = Integer            1
  #206 = Utf8               java/lang/invoke/LambdaMetafactory
  #207 = Class              #206          // java/lang/invoke/LambdaMetafactory
  #208 = Utf8               altMetafactory
  #209 = Utf8               (Ljava/lang/invoke/MethodHandles$Lookup;Ljava/lang/String;Ljava/lang/invoke/MethodType;[Ljava/lang/Object;)Ljava/lang/invoke/CallSite;
  #210 = NameAndType        #208:#209     // altMetafactory:(Ljava/lang/invoke/MethodHandles$Lookup;Ljava/lang/String;Ljava/lang/invoke/MethodType;[Ljava/lang/Object;)Ljava/lang/invoke/CallSite;
  #211 = Methodref          #207.#210     // java/lang/invoke/LambdaMetafactory.altMetafactory:(Ljava/lang/invoke/MethodHandles$Lookup;Ljava/lang/String;Ljava/lang/invoke/MethodType;[Ljava/lang/Object;)Ljava/lang/invoke/CallSite;
  #212 = MethodHandle       6:#211        // REF_invokeStatic java/lang/invoke/LambdaMetafactory.altMetafactory:(Ljava/lang/invoke/MethodHandles$Lookup;Ljava/lang/String;Ljava/lang/invoke/MethodType;[Ljava/lang/Object;)Ljava/lang/invoke/CallSite;
  #213 = Utf8               apply
  #214 = Utf8               ()Lscala/Function0;
  #215 = NameAndType        #213:#214     // apply:()Lscala/Function0;
  #216 = InvokeDynamic      #0:#215       // #0:apply:()Lscala/Function0;
  #217 = String             #23           // FixtureAnyFlatSpecLike.scala
  #218 = Utf8               registerTest
  #219 = String             #218          // registerTest
  #220 = Utf8               scala/None$
  #221 = Class              #220          // scala/None$
  #222 = Utf8               MODULE$
  #223 = Utf8               Lscala/None$;
  #224 = NameAndType        #222:#223     // MODULE$:Lscala/None$;
  #225 = Fieldref           #221.#224     // scala/None$.MODULE$:Lscala/None$;
  #226 = Utf8               scala/Some
  #227 = Class              #226          // scala/Some
  #228 = Utf8               (Ljava/lang/Object;)V
  #229 = NameAndType        #194:#228     // "<init>":(Ljava/lang/Object;)V
  #230 = Methodref          #227.#229     // scala/Some."<init>":(Ljava/lang/Object;)V
  #231 = Utf8               (Ljava/lang/String;Ljava/lang/Object;Lscala/Function0;Ljava/lang/String;Ljava/lang/String;IILscala/Option;Lscala/Option;Lscala/Option;Lscala/Option;Lscala/collection/immutable/Seq;)Ljava/lang/String;
  #232 = NameAndType        #218:#231     // registerTest:(Ljava/lang/String;Ljava/lang/Object;Lscala/Function0;Ljava/lang/String;Ljava/lang/String;IILscala/Option;Lscala/Option;Lscala/Option;Lscala/Option;Lscala/collection/immutable/Seq;)Ljava/lang/String;
  #233 = Methodref          #138.#232     // org/scalatest/FixtureEngine.registerTest:(Ljava/lang/String;Ljava/lang/Object;Lscala/Function0;Ljava/lang/String;Ljava/lang/String;IILscala/Option;Lscala/Option;Lscala/Option;Lscala/Option;Lscala/collection/immutable/Seq;)Ljava/lang/String;
  #234 = Utf8               stackDepthAdjustment
  #235 = Utf8               I
  #236 = Utf8               Ljava/lang/String;
  #237 = Utf8               Lscala/collection/immutable/Seq;
  #238 = Utf8               Lscala/Function1;
  #239 = Utf8               Lorg/scalactic/source/Position;
  #240 = Utf8               registerTest$
  #241 = Utf8               (Lorg/scalatest/flatspec/FixtureAnyFlatSpecLike;Ljava/lang/String;Lscala/collection/immutable/Seq;Lscala/Function1;Lorg/scalactic/source/Position;)V
  #242 = NameAndType        #218:#186     // registerTest:(Ljava/lang/String;Lscala/collection/immutable/Seq;Lscala/Function1;Lorg/scalactic/source/Position;)V
  #243 = InterfaceMethodref #2.#242       // org/scalatest/flatspec/FixtureAnyFlatSpecLike.registerTest:(Ljava/lang/String;Lscala/collection/immutable/Seq;Lscala/Function1;Lorg/scalactic/source/Position;)V
  #244 = NameAndType        #185:#186     // registerTestImpl:(Ljava/lang/String;Lscala/collection/immutable/Seq;Lscala/Function1;Lorg/scalactic/source/Position;)V
  #245 = InterfaceMethodref #2.#244       // org/scalatest/flatspec/FixtureAnyFlatSpecLike.registerTestImpl:(Ljava/lang/String;Lscala/collection/immutable/Seq;Lscala/Function1;Lorg/scalactic/source/Position;)V
  #246 = Utf8               registerIgnoredTestImpl
  #247 = Utf8               $anonfun$registerIgnoredTestImpl$1
  #248 = NameAndType        #247:#126     // $anonfun$registerIgnoredTestImpl$1:()Ljava/lang/String;
  #249 = InterfaceMethodref #2.#248       // org/scalatest/flatspec/FixtureAnyFlatSpecLike.$anonfun$registerIgnoredTestImpl$1:()Ljava/lang/String;
  #250 = MethodHandle       6:#249        // REF_invokeStatic org/scalatest/flatspec/FixtureAnyFlatSpecLike.$anonfun$registerIgnoredTestImpl$1:()Ljava/lang/String;
  #251 = InvokeDynamic      #1:#215       // #1:apply:()Lscala/Function0;
  #252 = Utf8               registerIgnoredTest
  #253 = String             #252          // registerIgnoredTest
  #254 = Utf8               (Ljava/lang/String;Ljava/lang/Object;Lscala/Function0;Ljava/lang/String;Ljava/lang/String;IILscala/Option;Lscala/Option;Lscala/collection/immutable/Seq;)V
  #255 = NameAndType        #252:#254     // registerIgnoredTest:(Ljava/lang/String;Ljava/lang/Object;Lscala/Function0;Ljava/lang/String;Ljava/lang/String;IILscala/Option;Lscala/Option;Lscala/collection/immutable/Seq;)V
  #256 = Methodref          #138.#255     // org/scalatest/FixtureEngine.registerIgnoredTest:(Ljava/lang/String;Ljava/lang/Object;Lscala/Function0;Ljava/lang/String;Ljava/lang/String;IILscala/Option;Lscala/Option;Lscala/collection/immutable/Seq;)V
  #257 = Utf8               registerIgnoredTest$
  #258 = NameAndType        #252:#186     // registerIgnoredTest:(Ljava/lang/String;Lscala/collection/immutable/Seq;Lscala/Function1;Lorg/scalactic/source/Position;)V
  #259 = InterfaceMethodref #2.#258       // org/scalatest/flatspec/FixtureAnyFlatSpecLike.registerIgnoredTest:(Ljava/lang/String;Lscala/collection/immutable/Seq;Lscala/Function1;Lorg/scalactic/source/Position;)V
  #260 = NameAndType        #246:#186     // registerIgnoredTestImpl:(Ljava/lang/String;Lscala/collection/immutable/Seq;Lscala/Function1;Lorg/scalactic/source/Position;)V
  #261 = InterfaceMethodref #2.#260       // org/scalatest/flatspec/FixtureAnyFlatSpecLike.registerIgnoredTestImpl:(Ljava/lang/String;Lscala/collection/immutable/Seq;Lscala/Function1;Lorg/scalactic/source/Position;)V
  #262 = Utf8               org$scalatest$flatspec$FixtureAnyFlatSpecLike$$registerTestToRun$
  #263 = Utf8               (Lorg/scalatest/flatspec/FixtureAnyFlatSpecLike;Ljava/lang/String;Lscala/collection/immutable/List;Ljava/lang/String;Lscala/Function1;Lorg/scalactic/source/Position;)V
  #264 = Utf8               specText
  #265 = Utf8               methodName
  #266 = Utf8               org$scalatest$flatspec$FixtureAnyFlatSpecLike$$registerTestToRun
  #267 = Utf8               (Ljava/lang/String;Lscala/collection/immutable/List;Ljava/lang/String;Lscala/Function1;Lorg/scalactic/source/Position;)V
  #268 = NameAndType        #266:#267     // org$scalatest$flatspec$FixtureAnyFlatSpecLike$$registerTestToRun:(Ljava/lang/String;Lscala/collection/immutable/List;Ljava/lang/String;Lscala/Function1;Lorg/scalactic/source/Position;)V
  #269 = InterfaceMethodref #2.#268       // org/scalatest/flatspec/FixtureAnyFlatSpecLike.org$scalatest$flatspec$FixtureAnyFlatSpecLike$$registerTestToRun:(Ljava/lang/String;Lscala/collection/immutable/List;Ljava/lang/String;Lscala/Function1;Lorg/scalactic/source/Position;)V
  #270 = Utf8               Lscala/collection/immutable/List;
  #271 = Utf8               (Ljava/lang/String;Lscala/collection/immutable/List<Lorg/scalatest/Tag;>;Ljava/lang/String;Lscala/Function1<Ljava/lang/Object;Ljava/lang/Object;>;Lorg/scalactic/source/Position;)V
  #272 = Utf8               $anonfun$registerTestToRun$1
  #273 = Utf8               (Ljava/lang/String;)Ljava/lang/String;
  #274 = NameAndType        #272:#273     // $anonfun$registerTestToRun$1:(Ljava/lang/String;)Ljava/lang/String;
  #275 = InterfaceMethodref #2.#274       // org/scalatest/flatspec/FixtureAnyFlatSpecLike.$anonfun$registerTestToRun$1:(Ljava/lang/String;)Ljava/lang/String;
  #276 = MethodHandle       6:#275        // REF_invokeStatic org/scalatest/flatspec/FixtureAnyFlatSpecLike.$anonfun$registerTestToRun$1:(Ljava/lang/String;)Ljava/lang/String;
  #277 = Utf8               (Ljava/lang/String;)Lscala/Function0;
  #278 = NameAndType        #213:#277     // apply:(Ljava/lang/String;)Lscala/Function0;
  #279 = InvokeDynamic      #2:#278       // #2:apply:(Ljava/lang/String;)Lscala/Function0;
  #280 = NameAndType        #125:#126     // sourceFileName:()Ljava/lang/String;
  #281 = InterfaceMethodref #2.#280       // org/scalatest/flatspec/FixtureAnyFlatSpecLike.sourceFileName:()Ljava/lang/String;
  #282 = Utf8               stackDepth
  #283 = Utf8               org$scalatest$flatspec$FixtureAnyFlatSpecLike$$registerPendingTestToRun$
  #284 = Utf8               org$scalatest$flatspec$FixtureAnyFlatSpecLike$$registerPendingTestToRun
  #285 = NameAndType        #284:#267     // org$scalatest$flatspec$FixtureAnyFlatSpecLike$$registerPendingTestToRun:(Ljava/lang/String;Lscala/collection/immutable/List;Ljava/lang/String;Lscala/Function1;Lorg/scalactic/source/Position;)V
  #286 = InterfaceMethodref #2.#285       // org/scalatest/flatspec/FixtureAnyFlatSpecLike.org$scalatest$flatspec$FixtureAnyFlatSpecLike$$registerPendingTestToRun:(Ljava/lang/String;Lscala/collection/immutable/List;Ljava/lang/String;Lscala/Function1;Lorg/scalactic/source/Position;)V
  #287 = Utf8               (Ljava/lang/String;Lscala/collection/immutable/List<Lorg/scalatest/Tag;>;Ljava/lang/String;Lscala/Function1<Ljava/lang/Object;Lorg/scalatest/PendingStatement;>;Lorg/scalactic/source/Position;)V
  #288 = Utf8               $anonfun$registerPendingTestToRun$1
  #289 = NameAndType        #288:#273     // $anonfun$registerPendingTestToRun$1:(Ljava/lang/String;)Ljava/lang/String;
  #290 = InterfaceMethodref #2.#289       // org/scalatest/flatspec/FixtureAnyFlatSpecLike.$anonfun$registerPendingTestToRun$1:(Ljava/lang/String;)Ljava/lang/String;
  #291 = MethodHandle       6:#290        // REF_invokeStatic org/scalatest/flatspec/FixtureAnyFlatSpecLike.$anonfun$registerPendingTestToRun$1:(Ljava/lang/String;)Ljava/lang/String;
  #292 = InvokeDynamic      #3:#278       // #3:apply:(Ljava/lang/String;)Lscala/Function0;
  #293 = Utf8               behavior
  #294 = Utf8               ()Lorg/scalatest/flatspec/FixtureAnyFlatSpecLike$BehaviorWord;
  #295 = Utf8               it
  #296 = Utf8               ()Lorg/scalatest/flatspec/FixtureAnyFlatSpecLike$ItWord;
  #297 = Utf8               they
  #298 = Utf8               ()Lorg/scalatest/flatspec/FixtureAnyFlatSpecLike$TheyWord;
  #299 = Utf8               ignore
  #300 = Utf8               ()Lorg/scalatest/flatspec/FixtureAnyFlatSpecLike$IgnoreWord;
  #301 = Utf8               convertToInAndIgnoreMethods$
  #302 = Utf8               (Lorg/scalatest/flatspec/FixtureAnyFlatSpecLike;Lorg/scalatest/verbs/ResultOfStringPassedToVerb;)Lorg/scalatest/flatspec/FixtureAnyFlatSpecLike$InAndIgnoreMethods;
  #303 = Utf8               resultOfStringPassedToVerb
  #304 = Utf8               convertToInAndIgnoreMethods
  #305 = Utf8               (Lorg/scalatest/verbs/ResultOfStringPassedToVerb;)Lorg/scalatest/flatspec/FixtureAnyFlatSpecLike$InAndIgnoreMethods;
  #306 = NameAndType        #304:#305     // convertToInAndIgnoreMethods:(Lorg/scalatest/verbs/ResultOfStringPassedToVerb;)Lorg/scalatest/flatspec/FixtureAnyFlatSpecLike$InAndIgnoreMethods;
  #307 = InterfaceMethodref #2.#306       // org/scalatest/flatspec/FixtureAnyFlatSpecLike.convertToInAndIgnoreMethods:(Lorg/scalatest/verbs/ResultOfStringPassedToVerb;)Lorg/scalatest/flatspec/FixtureAnyFlatSpecLike$InAndIgnoreMethods;
  #308 = Utf8               Lorg/scalatest/verbs/ResultOfStringPassedToVerb;
  #309 = Utf8               (Lorg/scalatest/flatspec/FixtureAnyFlatSpecLike;Lorg/scalatest/verbs/ResultOfStringPassedToVerb;)V
  #310 = NameAndType        #194:#309     // "<init>":(Lorg/scalatest/flatspec/FixtureAnyFlatSpecLike;Lorg/scalatest/verbs/ResultOfStringPassedToVerb;)V
  #311 = Methodref          #74.#310      // org/scalatest/flatspec/FixtureAnyFlatSpecLike$InAndIgnoreMethods."<init>":(Lorg/scalatest/flatspec/FixtureAnyFlatSpecLike;Lorg/scalatest/verbs/ResultOfStringPassedToVerb;)V
  #312 = Utf8               convertToInAndIgnoreMethodsAfterTaggedAs$
  #313 = Utf8               (Lorg/scalatest/flatspec/FixtureAnyFlatSpecLike;Lorg/scalatest/verbs/ResultOfTaggedAsInvocation;)Lorg/scalatest/flatspec/FixtureAnyFlatSpecLike$InAndIgnoreMethodsAfterTaggedAs;
  #314 = Utf8               resultOfTaggedAsInvocation
  #315 = Utf8               convertToInAndIgnoreMethodsAfterTaggedAs
  #316 = Utf8               (Lorg/scalatest/verbs/ResultOfTaggedAsInvocation;)Lorg/scalatest/flatspec/FixtureAnyFlatSpecLike$InAndIgnoreMethodsAfterTaggedAs;
  #317 = NameAndType        #315:#316     // convertToInAndIgnoreMethodsAfterTaggedAs:(Lorg/scalatest/verbs/ResultOfTaggedAsInvocation;)Lorg/scalatest/flatspec/FixtureAnyFlatSpecLike$InAndIgnoreMethodsAfterTaggedAs;
  #318 = InterfaceMethodref #2.#317       // org/scalatest/flatspec/FixtureAnyFlatSpecLike.convertToInAndIgnoreMethodsAfterTaggedAs:(Lorg/scalatest/verbs/ResultOfTaggedAsInvocation;)Lorg/scalatest/flatspec/FixtureAnyFlatSpecLike$InAndIgnoreMethodsAfterTaggedAs;
  #319 = Utf8               Lorg/scalatest/verbs/ResultOfTaggedAsInvocation;
  #320 = Utf8               (Lorg/scalatest/flatspec/FixtureAnyFlatSpecLike;Lorg/scalatest/verbs/ResultOfTaggedAsInvocation;)V
  #321 = NameAndType        #194:#320     // "<init>":(Lorg/scalatest/flatspec/FixtureAnyFlatSpecLike;Lorg/scalatest/verbs/ResultOfTaggedAsInvocation;)V
  #322 = Methodref          #77.#321      // org/scalatest/flatspec/FixtureAnyFlatSpecLike$InAndIgnoreMethodsAfterTaggedAs."<init>":(Lorg/scalatest/flatspec/FixtureAnyFlatSpecLike;Lorg/scalatest/verbs/ResultOfTaggedAsInvocation;)V
  #323 = Utf8               shorthandTestRegistrationFunction
  #324 = Utf8               ()Lorg/scalatest/verbs/StringVerbStringInvocation;
  #325 = Utf8               shorthandSharedTestRegistrationFunction
  #326 = Utf8               ()Lorg/scalatest/verbs/StringVerbBehaveLikeInvocation;
  #327 = Utf8               org$scalatest$flatspec$FixtureAnyFlatSpecLike$$registerTestToIgnore$
  #328 = Utf8               org$scalatest$flatspec$FixtureAnyFlatSpecLike$$registerTestToIgnore
  #329 = NameAndType        #328:#267     // org$scalatest$flatspec$FixtureAnyFlatSpecLike$$registerTestToIgnore:(Ljava/lang/String;Lscala/collection/immutable/List;Ljava/lang/String;Lscala/Function1;Lorg/scalactic/source/Position;)V
  #330 = InterfaceMethodref #2.#329       // org/scalatest/flatspec/FixtureAnyFlatSpecLike.org$scalatest$flatspec$FixtureAnyFlatSpecLike$$registerTestToIgnore:(Ljava/lang/String;Lscala/collection/immutable/List;Ljava/lang/String;Lscala/Function1;Lorg/scalactic/source/Position;)V
  #331 = Utf8               $anonfun$registerTestToIgnore$1
  #332 = NameAndType        #331:#126     // $anonfun$registerTestToIgnore$1:()Ljava/lang/String;
  #333 = InterfaceMethodref #2.#332       // org/scalatest/flatspec/FixtureAnyFlatSpecLike.$anonfun$registerTestToIgnore$1:()Ljava/lang/String;
  #334 = MethodHandle       6:#333        // REF_invokeStatic org/scalatest/flatspec/FixtureAnyFlatSpecLike.$anonfun$registerTestToIgnore$1:()Ljava/lang/String;
  #335 = InvokeDynamic      #4:#215       // #4:apply:()Lscala/Function0;
  #336 = Utf8               org$scalatest$flatspec$FixtureAnyFlatSpecLike$$registerPendingTestToIgnore$
  #337 = Utf8               org$scalatest$flatspec$FixtureAnyFlatSpecLike$$registerPendingTestToIgnore
  #338 = NameAndType        #337:#267     // org$scalatest$flatspec$FixtureAnyFlatSpecLike$$registerPendingTestToIgnore:(Ljava/lang/String;Lscala/collection/immutable/List;Ljava/lang/String;Lscala/Function1;Lorg/scalactic/source/Position;)V
  #339 = InterfaceMethodref #2.#338       // org/scalatest/flatspec/FixtureAnyFlatSpecLike.org$scalatest$flatspec$FixtureAnyFlatSpecLike$$registerPendingTestToIgnore:(Ljava/lang/String;Lscala/collection/immutable/List;Ljava/lang/String;Lscala/Function1;Lorg/scalactic/source/Position;)V
  #340 = Utf8               $anonfun$registerPendingTestToIgnore$1
  #341 = NameAndType        #340:#126     // $anonfun$registerPendingTestToIgnore$1:()Ljava/lang/String;
  #342 = InterfaceMethodref #2.#341       // org/scalatest/flatspec/FixtureAnyFlatSpecLike.$anonfun$registerPendingTestToIgnore$1:()Ljava/lang/String;
  #343 = MethodHandle       6:#342        // REF_invokeStatic org/scalatest/flatspec/FixtureAnyFlatSpecLike.$anonfun$registerPendingTestToIgnore$1:()Ljava/lang/String;
  #344 = InvokeDynamic      #5:#215       // #5:apply:()Lscala/Function0;
  #345 = Utf8               tags$
  #346 = Utf8               (Lorg/scalatest/flatspec/FixtureAnyFlatSpecLike;)Lscala/collection/immutable/Map;
  #347 = Utf8               tags
  #348 = Utf8               ()Lscala/collection/immutable/Map;
  #349 = NameAndType        #347:#348     // tags:()Lscala/collection/immutable/Map;
  #350 = InterfaceMethodref #2.#349       // org/scalatest/flatspec/FixtureAnyFlatSpecLike.tags:()Lscala/collection/immutable/Map;
  #351 = Utf8               ()Lscala/collection/immutable/Map<Ljava/lang/String;Lscala/collection/immutable/Set<Ljava/lang/String;>;>;
  #352 = Utf8               org/scalatest/Suite$
  #353 = Class              #352          // org/scalatest/Suite$
  #354 = Utf8               Lorg/scalatest/Suite$;
  #355 = NameAndType        #222:#354     // MODULE$:Lorg/scalatest/Suite$;
  #356 = Fieldref           #353.#355     // org/scalatest/Suite$.MODULE$:Lorg/scalatest/Suite$;
  #357 = Utf8               atomic
  #358 = NameAndType        #357:#140     // atomic:()Ljava/util/concurrent/atomic/AtomicReference;
  #359 = Methodref          #138.#358     // org/scalatest/FixtureEngine.atomic:()Ljava/util/concurrent/atomic/AtomicReference;
  #360 = Utf8               tagsMap
  #361 = NameAndType        #360:#348     // tagsMap:()Lscala/collection/immutable/Map;
  #362 = Methodref          #45.#361      // org/scalatest/SuperEngine$Bundle.tagsMap:()Lscala/collection/immutable/Map;
  #363 = Utf8               autoTagClassAnnotations
  #364 = Utf8               (Lscala/collection/immutable/Map;Lorg/scalatest/Suite;)Lscala/collection/immutable/Map;
  #365 = NameAndType        #363:#364     // autoTagClassAnnotations:(Lscala/collection/immutable/Map;Lorg/scalatest/Suite;)Lscala/collection/immutable/Map;
  #366 = Methodref          #353.#365     // org/scalatest/Suite$.autoTagClassAnnotations:(Lscala/collection/immutable/Map;Lorg/scalatest/Suite;)Lscala/collection/immutable/Map;
  #367 = Utf8               runTest$
  #368 = Utf8               (Lorg/scalatest/flatspec/FixtureAnyFlatSpecLike;Ljava/lang/String;Lorg/scalatest/Args;)Lorg/scalatest/Status;
  #369 = Utf8               runTest
  #370 = Utf8               (Ljava/lang/String;Lorg/scalatest/Args;)Lorg/scalatest/Status;
  #371 = NameAndType        #369:#370     // runTest:(Ljava/lang/String;Lorg/scalatest/Args;)Lorg/scalatest/Status;
  #372 = InterfaceMethodref #2.#371       // org/scalatest/flatspec/FixtureAnyFlatSpecLike.runTest:(Ljava/lang/String;Lorg/scalatest/Args;)Lorg/scalatest/Status;
  #373 = Utf8               Lorg/scalatest/Args;
  #374 = Utf8               (Ljava/lang/Object;)Ljava/lang/Object;
  #375 = MethodType         #374          //  (Ljava/lang/Object;)Ljava/lang/Object;
  #376 = Utf8               $anonfun$runTest$1
  #377 = Utf8               (Lorg/scalatest/flatspec/FixtureAnyFlatSpecLike;Ljava/lang/String;Lorg/scalatest/Args;Lorg/scalatest/SuperEngine$TestLeaf;)Lorg/scalatest/Outcome;
  #378 = NameAndType        #376:#377     // $anonfun$runTest$1:(Lorg/scalatest/flatspec/FixtureAnyFlatSpecLike;Ljava/lang/String;Lorg/scalatest/Args;Lorg/scalatest/SuperEngine$TestLeaf;)Lorg/scalatest/Outcome;
  #379 = InterfaceMethodref #2.#378       // org/scalatest/flatspec/FixtureAnyFlatSpecLike.$anonfun$runTest$1:(Lorg/scalatest/flatspec/FixtureAnyFlatSpecLike;Ljava/lang/String;Lorg/scalatest/Args;Lorg/scalatest/SuperEngine$TestLeaf;)Lorg/scalatest/Outcome;
  #380 = MethodHandle       6:#379        // REF_invokeStatic org/scalatest/flatspec/FixtureAnyFlatSpecLike.$anonfun$runTest$1:(Lorg/scalatest/flatspec/FixtureAnyFlatSpecLike;Ljava/lang/String;Lorg/scalatest/Args;Lorg/scalatest/SuperEngine$TestLeaf;)Lorg/scalatest/Outcome;
  #381 = Utf8               (Lorg/scalatest/SuperEngine$TestLeaf;)Lorg/scalatest/Outcome;
  #382 = MethodType         #381          //  (Lorg/scalatest/SuperEngine$TestLeaf;)Lorg/scalatest/Outcome;
  #383 = Utf8               (Lorg/scalatest/flatspec/FixtureAnyFlatSpecLike;Ljava/lang/String;Lorg/scalatest/Args;)Lscala/Function1;
  #384 = NameAndType        #213:#383     // apply:(Lorg/scalatest/flatspec/FixtureAnyFlatSpecLike;Ljava/lang/String;Lorg/scalatest/Args;)Lscala/Function1;
  #385 = InvokeDynamic      #6:#384       // #6:apply:(Lorg/scalatest/flatspec/FixtureAnyFlatSpecLike;Ljava/lang/String;Lorg/scalatest/Args;)Lscala/Function1;
  #386 = Utf8               runTestImpl
  #387 = Utf8               (Lorg/scalatest/Suite;Ljava/lang/String;Lorg/scalatest/Args;ZLscala/Function1;)Lorg/scalatest/Status;
  #388 = NameAndType        #386:#387     // runTestImpl:(Lorg/scalatest/Suite;Ljava/lang/String;Lorg/scalatest/Args;ZLscala/Function1;)Lorg/scalatest/Status;
  #389 = Methodref          #138.#388     // org/scalatest/FixtureEngine.runTestImpl:(Lorg/scalatest/Suite;Ljava/lang/String;Lorg/scalatest/Args;ZLscala/Function1;)Lorg/scalatest/Status;
  #390 = Utf8               runTests$
  #391 = Utf8               (Lorg/scalatest/flatspec/FixtureAnyFlatSpecLike;Lscala/Option;Lorg/scalatest/Args;)Lorg/scalatest/Status;
  #392 = Utf8               runTests
  #393 = NameAndType        #392:#119     // runTests:(Lscala/Option;Lorg/scalatest/Args;)Lorg/scalatest/Status;
  #394 = InterfaceMethodref #2.#393       // org/scalatest/flatspec/FixtureAnyFlatSpecLike.runTests:(Lscala/Option;Lorg/scalatest/Args;)Lorg/scalatest/Status;
  #395 = Utf8               Lscala/Option;
  #396 = Utf8               (Lscala/Option<Ljava/lang/String;>;Lorg/scalatest/Args;)Lorg/scalatest/Status;
  #397 = Utf8               (Ljava/lang/Object;Ljava/lang/Object;)Ljava/lang/Object;
  #398 = MethodType         #397          //  (Ljava/lang/Object;Ljava/lang/Object;)Ljava/lang/Object;
  #399 = Utf8               $anonfun$runTests$1
  #400 = NameAndType        #399:#368     // $anonfun$runTests$1:(Lorg/scalatest/flatspec/FixtureAnyFlatSpecLike;Ljava/lang/String;Lorg/scalatest/Args;)Lorg/scalatest/Status;
  #401 = InterfaceMethodref #2.#400       // org/scalatest/flatspec/FixtureAnyFlatSpecLike.$anonfun$runTests$1:(Lorg/scalatest/flatspec/FixtureAnyFlatSpecLike;Ljava/lang/String;Lorg/scalatest/Args;)Lorg/scalatest/Status;
  #402 = MethodHandle       6:#401        // REF_invokeStatic org/scalatest/flatspec/FixtureAnyFlatSpecLike.$anonfun$runTests$1:(Lorg/scalatest/flatspec/FixtureAnyFlatSpecLike;Ljava/lang/String;Lorg/scalatest/Args;)Lorg/scalatest/Status;
  #403 = MethodType         #370          //  (Ljava/lang/String;Lorg/scalatest/Args;)Lorg/scalatest/Status;
  #404 = Utf8               (Lorg/scalatest/flatspec/FixtureAnyFlatSpecLike;)Lscala/Function2;
  #405 = NameAndType        #213:#404     // apply:(Lorg/scalatest/flatspec/FixtureAnyFlatSpecLike;)Lscala/Function2;
  #406 = InvokeDynamic      #7:#405       // #7:apply:(Lorg/scalatest/flatspec/FixtureAnyFlatSpecLike;)Lscala/Function2;
  #407 = Utf8               runTestsImpl
  #408 = Utf8               (Lorg/scalatest/Suite;Lscala/Option;Lorg/scalatest/Args;Lorg/scalatest/Informer;ZLscala/Function2;)Lorg/scalatest/Status;
  #409 = NameAndType        #407:#408     // runTestsImpl:(Lorg/scalatest/Suite;Lscala/Option;Lorg/scalatest/Args;Lorg/scalatest/Informer;ZLscala/Function2;)Lorg/scalatest/Status;
  #410 = Methodref          #138.#409     // org/scalatest/FixtureEngine.runTestsImpl:(Lorg/scalatest/Suite;Lscala/Option;Lorg/scalatest/Args;Lorg/scalatest/Informer;ZLscala/Function2;)Lorg/scalatest/Status;
  #411 = Utf8               testNames$
  #412 = Utf8               (Lorg/scalatest/flatspec/FixtureAnyFlatSpecLike;)Lscala/collection/immutable/Set;
  #413 = Utf8               testNames
  #414 = Utf8               ()Lscala/collection/immutable/Set;
  #415 = NameAndType        #413:#414     // testNames:()Lscala/collection/immutable/Set;
  #416 = InterfaceMethodref #2.#415       // org/scalatest/flatspec/FixtureAnyFlatSpecLike.testNames:()Lscala/collection/immutable/Set;
  #417 = Utf8               ()Lscala/collection/immutable/Set<Ljava/lang/String;>;
  #418 = Utf8               org/scalatest/InsertionOrderSet$
  #419 = Class              #418          // org/scalatest/InsertionOrderSet$
  #420 = Utf8               Lorg/scalatest/InsertionOrderSet$;
  #421 = NameAndType        #222:#420     // MODULE$:Lorg/scalatest/InsertionOrderSet$;
  #422 = Fieldref           #419.#421     // org/scalatest/InsertionOrderSet$.MODULE$:Lorg/scalatest/InsertionOrderSet$;
  #423 = Utf8               testNamesList
  #424 = Utf8               ()Lscala/collection/immutable/List;
  #425 = NameAndType        #423:#424     // testNamesList:()Lscala/collection/immutable/List;
  #426 = Methodref          #45.#425      // org/scalatest/SuperEngine$Bundle.testNamesList:()Lscala/collection/immutable/List;
  #427 = Utf8               (Lscala/collection/immutable/List;)Lscala/collection/immutable/Set;
  #428 = NameAndType        #213:#427     // apply:(Lscala/collection/immutable/List;)Lscala/collection/immutable/Set;
  #429 = Methodref          #419.#428     // org/scalatest/InsertionOrderSet$.apply:(Lscala/collection/immutable/List;)Lscala/collection/immutable/Set;
  #430 = Utf8               run$
  #431 = Utf8               run
  #432 = NameAndType        #431:#119     // run:(Lscala/Option;Lorg/scalatest/Args;)Lorg/scalatest/Status;
  #433 = InterfaceMethodref #2.#432       // org/scalatest/flatspec/FixtureAnyFlatSpecLike.run:(Lscala/Option;Lorg/scalatest/Args;)Lorg/scalatest/Status;
  #434 = Utf8               $anonfun$run$1
  #435 = NameAndType        #434:#391     // $anonfun$run$1:(Lorg/scalatest/flatspec/FixtureAnyFlatSpecLike;Lscala/Option;Lorg/scalatest/Args;)Lorg/scalatest/Status;
  #436 = InterfaceMethodref #2.#435       // org/scalatest/flatspec/FixtureAnyFlatSpecLike.$anonfun$run$1:(Lorg/scalatest/flatspec/FixtureAnyFlatSpecLike;Lscala/Option;Lorg/scalatest/Args;)Lorg/scalatest/Status;
  #437 = MethodHandle       6:#436        // REF_invokeStatic org/scalatest/flatspec/FixtureAnyFlatSpecLike.$anonfun$run$1:(Lorg/scalatest/flatspec/FixtureAnyFlatSpecLike;Lscala/Option;Lorg/scalatest/Args;)Lorg/scalatest/Status;
  #438 = MethodType         #119          //  (Lscala/Option;Lorg/scalatest/Args;)Lorg/scalatest/Status;
  #439 = InvokeDynamic      #8:#405       // #8:apply:(Lorg/scalatest/flatspec/FixtureAnyFlatSpecLike;)Lscala/Function2;
  #440 = Utf8               runImpl
  #441 = Utf8               (Lorg/scalatest/Suite;Lscala/Option;Lorg/scalatest/Args;Lscala/Function2;)Lorg/scalatest/Status;
  #442 = NameAndType        #440:#441     // runImpl:(Lorg/scalatest/Suite;Lscala/Option;Lorg/scalatest/Args;Lscala/Function2;)Lorg/scalatest/Status;
  #443 = Methodref          #138.#442     // org/scalatest/FixtureEngine.runImpl:(Lorg/scalatest/Suite;Lscala/Option;Lorg/scalatest/Args;Lscala/Function2;)Lorg/scalatest/Status;
  #444 = Utf8               behave
  #445 = Utf8               ()Lorg/scalatest/verbs/BehaveWord;
  #446 = Utf8               styleName
  #447 = Utf8               testDataFor$
  #448 = Utf8               (Lorg/scalatest/flatspec/FixtureAnyFlatSpecLike;Ljava/lang/String;Lorg/scalatest/ConfigMap;)Lorg/scalatest/TestData;
  #449 = Utf8               theConfigMap
  #450 = Utf8               testDataFor
  #451 = Utf8               (Ljava/lang/String;Lorg/scalatest/ConfigMap;)Lorg/scalatest/TestData;
  #452 = NameAndType        #450:#451     // testDataFor:(Ljava/lang/String;Lorg/scalatest/ConfigMap;)Lorg/scalatest/TestData;
  #453 = InterfaceMethodref #2.#452       // org/scalatest/flatspec/FixtureAnyFlatSpecLike.testDataFor:(Ljava/lang/String;Lorg/scalatest/ConfigMap;)Lorg/scalatest/TestData;
  #454 = Utf8               Lorg/scalatest/ConfigMap;
  #455 = Utf8               createTestDataFor
  #456 = Utf8               (Ljava/lang/String;Lorg/scalatest/ConfigMap;Lorg/scalatest/Suite;)Lorg/scalatest/TestData;
  #457 = NameAndType        #455:#456     // createTestDataFor:(Ljava/lang/String;Lorg/scalatest/ConfigMap;Lorg/scalatest/Suite;)Lorg/scalatest/TestData;
  #458 = Methodref          #138.#457     // org/scalatest/FixtureEngine.createTestDataFor:(Ljava/lang/String;Lorg/scalatest/ConfigMap;Lorg/scalatest/Suite;)Lorg/scalatest/TestData;
  #459 = Utf8               testDataFor$default$2$
  #460 = Utf8               (Lorg/scalatest/flatspec/FixtureAnyFlatSpecLike;)Lorg/scalatest/ConfigMap;
  #461 = Utf8               testDataFor$default$2
  #462 = Utf8               ()Lorg/scalatest/ConfigMap;
  #463 = NameAndType        #461:#462     // testDataFor$default$2:()Lorg/scalatest/ConfigMap;
  #464 = InterfaceMethodref #2.#463       // org/scalatest/flatspec/FixtureAnyFlatSpecLike.testDataFor$default$2:()Lorg/scalatest/ConfigMap;
  #465 = Utf8               org/scalatest/ConfigMap$
  #466 = Class              #465          // org/scalatest/ConfigMap$
  #467 = Utf8               Lorg/scalatest/ConfigMap$;
  #468 = NameAndType        #222:#467     // MODULE$:Lorg/scalatest/ConfigMap$;
  #469 = Fieldref           #466.#468     // org/scalatest/ConfigMap$.MODULE$:Lorg/scalatest/ConfigMap$;
  #470 = Utf8               empty
  #471 = NameAndType        #470:#462     // empty:()Lorg/scalatest/ConfigMap;
  #472 = Methodref          #466.#471     // org/scalatest/ConfigMap$.empty:()Lorg/scalatest/ConfigMap;
  #473 = Utf8               $anonfun$engine$1
  #474 = Utf8               org/scalatest/Resources$
  #475 = Class              #474          // org/scalatest/Resources$
  #476 = Utf8               Lorg/scalatest/Resources$;
  #477 = NameAndType        #222:#476     // MODULE$:Lorg/scalatest/Resources$;
  #478 = Fieldref           #475.#477     // org/scalatest/Resources$.MODULE$:Lorg/scalatest/Resources$;
  #479 = Utf8               concurrentFixtureFlatSpecMod
  #480 = NameAndType        #479:#126     // concurrentFixtureFlatSpecMod:()Ljava/lang/String;
  #481 = Methodref          #475.#480     // org/scalatest/Resources$.concurrentFixtureFlatSpecMod:()Ljava/lang/String;
  #482 = Utf8               testCannotBeNestedInsideAnotherTest
  #483 = NameAndType        #482:#126     // testCannotBeNestedInsideAnotherTest:()Ljava/lang/String;
  #484 = Methodref          #475.#483     // org/scalatest/Resources$.testCannotBeNestedInsideAnotherTest:()Ljava/lang/String;
  #485 = Utf8               testRegistrationClosedMessageFun$1
  #486 = Utf8               methodName$1
  #487 = Utf8               java/lang/String
  #488 = Class              #487          // java/lang/String
  #489 = Utf8               hashCode
  #490 = Utf8               ()I
  #491 = NameAndType        #489:#490     // hashCode:()I
  #492 = Methodref          #488.#491     // java/lang/String.hashCode:()I
  #493 = Utf8               in
  #494 = String             #493          // in
  #495 = Utf8               equals
  #496 = Utf8               (Ljava/lang/Object;)Z
  #497 = NameAndType        #495:#496     // equals:(Ljava/lang/Object;)Z
  #498 = Methodref          #488.#497     // java/lang/String.equals:(Ljava/lang/Object;)Z
  #499 = Utf8               inCannotAppearInsideAnotherInOrIs
  #500 = NameAndType        #499:#126     // inCannotAppearInsideAnotherInOrIs:()Ljava/lang/String;
  #501 = Methodref          #475.#500     // org/scalatest/Resources$.inCannotAppearInsideAnotherInOrIs:()Ljava/lang/String;
  #502 = Utf8               is
  #503 = String             #502          // is
  #504 = Utf8               isCannotAppearInsideAnotherInOrIs
  #505 = NameAndType        #504:#126     // isCannotAppearInsideAnotherInOrIs:()Ljava/lang/String;
  #506 = Methodref          #475.#505     // org/scalatest/Resources$.isCannotAppearInsideAnotherInOrIs:()Ljava/lang/String;
  #507 = Utf8               scala/MatchError
  #508 = Class              #507          // scala/MatchError
  #509 = Methodref          #508.#229     // scala/MatchError."<init>":(Ljava/lang/Object;)V
  #510 = NameAndType        #485:#273     // testRegistrationClosedMessageFun$1:(Ljava/lang/String;)Ljava/lang/String;
  #511 = InterfaceMethodref #2.#510       // org/scalatest/flatspec/FixtureAnyFlatSpecLike.testRegistrationClosedMessageFun$1:(Ljava/lang/String;)Ljava/lang/String;
  #512 = Utf8               testRegistrationClosedMessageFun$2
  #513 = Utf8               methodName$2
  #514 = NameAndType        #512:#273     // testRegistrationClosedMessageFun$2:(Ljava/lang/String;)Ljava/lang/String;
  #515 = InterfaceMethodref #2.#514       // org/scalatest/flatspec/FixtureAnyFlatSpecLike.testRegistrationClosedMessageFun$2:(Ljava/lang/String;)Ljava/lang/String;
  #516 = Utf8               ignoreCannotAppearInsideAnInOrAnIs
  #517 = NameAndType        #516:#126     // ignoreCannotAppearInsideAnInOrAnIs:()Ljava/lang/String;
  #518 = Methodref          #475.#517     // org/scalatest/Resources$.ignoreCannotAppearInsideAnInOrAnIs:()Ljava/lang/String;
  #519 = Utf8               invokeWithFixture$1
  #520 = Utf8               (Lorg/scalatest/SuperEngine$TestLeaf;Ljava/lang/String;Lorg/scalatest/Args;)Lorg/scalatest/Outcome;
  #521 = Utf8               theTest
  #522 = Utf8               testName$1
  #523 = Utf8               args$1
  #524 = NameAndType        #190:#146     // testFun:()Ljava/lang/Object;
  #525 = Methodref          #50.#524      // org/scalatest/SuperEngine$TestLeaf.testFun:()Ljava/lang/Object;
  #526 = Utf8               scala/Function1
  #527 = Class              #526          // scala/Function1
  #528 = Utf8               exceptionalTestFun
  #529 = Utf8               ()Lscala/Function1;
  #530 = NameAndType        #528:#529     // exceptionalTestFun:()Lscala/Function1;
  #531 = Methodref          #193.#530     // org/scalatest/fixture/Transformer.exceptionalTestFun:()Lscala/Function1;
  #532 = Utf8               org/scalatest/fixture/NoArgTestWrapper
  #533 = Class              #532          // org/scalatest/fixture/NoArgTestWrapper
  #534 = Utf8               test
  #535 = NameAndType        #534:#214     // test:()Lscala/Function0;
  #536 = Methodref          #533.#535     // org/scalatest/fixture/NoArgTestWrapper.test:()Lscala/Function0;
  #537 = Utf8               org/scalatest/Args
  #538 = Class              #537          // org/scalatest/Args
  #539 = Utf8               configMap
  #540 = NameAndType        #539:#462     // configMap:()Lorg/scalatest/ConfigMap;
  #541 = Methodref          #538.#540     // org/scalatest/Args.configMap:()Lorg/scalatest/ConfigMap;
  #542 = Utf8               (Lorg/scalatest/FixtureTestSuite;Ljava/lang/String;Lscala/Function0;Lorg/scalatest/ConfigMap;)V
  #543 = NameAndType        #194:#542     // "<init>":(Lorg/scalatest/FixtureTestSuite;Ljava/lang/String;Lscala/Function0;Lorg/scalatest/ConfigMap;)V
  #544 = Methodref          #36.#543      // org/scalatest/FixtureTestSuite$FixturelessTestFunAndConfigMap."<init>":(Lorg/scalatest/FixtureTestSuite;Ljava/lang/String;Lscala/Function0;Lorg/scalatest/ConfigMap;)V
  #545 = Utf8               withFixture
  #546 = Utf8               (Lorg/scalatest/TestSuite$NoArgTest;)Lorg/scalatest/Outcome;
  #547 = NameAndType        #545:#546     // withFixture:(Lorg/scalatest/TestSuite$NoArgTest;)Lorg/scalatest/Outcome;
  #548 = InterfaceMethodref #2.#547       // org/scalatest/flatspec/FixtureAnyFlatSpecLike.withFixture:(Lorg/scalatest/TestSuite$NoArgTest;)Lorg/scalatest/Outcome;
  #549 = Utf8               (Lorg/scalatest/FixtureTestSuite;Ljava/lang/String;Lscala/Function1;Lorg/scalatest/ConfigMap;)V
  #550 = NameAndType        #194:#549     // "<init>":(Lorg/scalatest/FixtureTestSuite;Ljava/lang/String;Lscala/Function1;Lorg/scalatest/ConfigMap;)V
  #551 = Methodref          #42.#550      // org/scalatest/FixtureTestSuite$TestFunAndConfigMap."<init>":(Lorg/scalatest/FixtureTestSuite;Ljava/lang/String;Lscala/Function1;Lorg/scalatest/ConfigMap;)V
  #552 = Utf8               (Lorg/scalatest/FixtureTestSuite$OneArgTest;)Lorg/scalatest/Outcome;
  #553 = NameAndType        #545:#552     // withFixture:(Lorg/scalatest/FixtureTestSuite$OneArgTest;)Lorg/scalatest/Outcome;
  #554 = InterfaceMethodref #2.#553       // org/scalatest/flatspec/FixtureAnyFlatSpecLike.withFixture:(Lorg/scalatest/FixtureTestSuite$OneArgTest;)Lorg/scalatest/Outcome;
  #555 = Utf8               Lorg/scalatest/SuperEngine$TestLeaf;
  #556 = Utf8               org/scalatest/Outcome
  #557 = Class              #556          // org/scalatest/Outcome
  #558 = NameAndType        #519:#520     // invokeWithFixture$1:(Lorg/scalatest/SuperEngine$TestLeaf;Ljava/lang/String;Lorg/scalatest/Args;)Lorg/scalatest/Outcome;
  #559 = InterfaceMethodref #2.#558       // org/scalatest/flatspec/FixtureAnyFlatSpecLike.invokeWithFixture$1:(Lorg/scalatest/SuperEngine$TestLeaf;Ljava/lang/String;Lorg/scalatest/Args;)Lorg/scalatest/Outcome;
  #560 = NameAndType        #118:#119     // org$scalatest$flatspec$FixtureAnyFlatSpecLike$$super$run:(Lscala/Option;Lorg/scalatest/Args;)Lorg/scalatest/Status;
  #561 = InterfaceMethodref #2.#560       // org/scalatest/flatspec/FixtureAnyFlatSpecLike.org$scalatest$flatspec$FixtureAnyFlatSpecLike$$super$run:(Lscala/Option;Lorg/scalatest/Args;)Lorg/scalatest/Status;
  #562 = Utf8               $init$
  #563 = Utf8               (Lorg/scalatest/flatspec/FixtureAnyFlatSpecLike;)V
  #564 = NameAndType        #473:#126     // $anonfun$engine$1:()Ljava/lang/String;
  #565 = InterfaceMethodref #2.#564       // org/scalatest/flatspec/FixtureAnyFlatSpecLike.$anonfun$engine$1:()Ljava/lang/String;
  #566 = MethodHandle       6:#565        // REF_invokeStatic org/scalatest/flatspec/FixtureAnyFlatSpecLike.$anonfun$engine$1:()Ljava/lang/String;
  #567 = InvokeDynamic      #9:#215       // #9:apply:()Lscala/Function0;
  #568 = Utf8               FixtureFlatSpec
  #569 = String             #568          // FixtureFlatSpec
  #570 = Utf8               (Lscala/Function0;Ljava/lang/String;)V
  #571 = NameAndType        #194:#570     // "<init>":(Lscala/Function0;Ljava/lang/String;)V
  #572 = Methodref          #138.#571     // org/scalatest/FixtureEngine."<init>":(Lscala/Function0;Ljava/lang/String;)V
  #573 = NameAndType        #97:#98       // org$scalatest$flatspec$FixtureAnyFlatSpecLike$_setter_$org$scalatest$flatspec$FixtureAnyFlatSpecLike$$engine_$eq:(Lorg/scalatest/FixtureEngine;)V
  #574 = InterfaceMethodref #2.#573       // org/scalatest/flatspec/FixtureAnyFlatSpecLike.org$scalatest$flatspec$FixtureAnyFlatSpecLike$_setter_$org$scalatest$flatspec$FixtureAnyFlatSpecLike$$engine_$eq:(Lorg/scalatest/FixtureEngine;)V
  #575 = NameAndType        #101:#102     // org$scalatest$flatspec$FixtureAnyFlatSpecLike$_setter_$sourceFileName_$eq:(Ljava/lang/String;)V
  #576 = InterfaceMethodref #2.#575       // org/scalatest/flatspec/FixtureAnyFlatSpecLike.org$scalatest$flatspec$FixtureAnyFlatSpecLike$_setter_$sourceFileName_$eq:(Ljava/lang/String;)V
  #577 = NameAndType        #194:#563     // "<init>":(Lorg/scalatest/flatspec/FixtureAnyFlatSpecLike;)V
  #578 = Methodref          #62.#577      // org/scalatest/flatspec/FixtureAnyFlatSpecLike$BehaviorWord."<init>":(Lorg/scalatest/flatspec/FixtureAnyFlatSpecLike;)V
  #579 = NameAndType        #103:#104     // org$scalatest$flatspec$FixtureAnyFlatSpecLike$_setter_$behavior_$eq:(Lorg/scalatest/flatspec/FixtureAnyFlatSpecLike$BehaviorWord;)V
  #580 = InterfaceMethodref #2.#579       // org/scalatest/flatspec/FixtureAnyFlatSpecLike.org$scalatest$flatspec$FixtureAnyFlatSpecLike$_setter_$behavior_$eq:(Lorg/scalatest/flatspec/FixtureAnyFlatSpecLike$BehaviorWord;)V
  #581 = Methodref          #86.#577      // org/scalatest/flatspec/FixtureAnyFlatSpecLike$ItWord."<init>":(Lorg/scalatest/flatspec/FixtureAnyFlatSpecLike;)V
  #582 = NameAndType        #105:#106     // org$scalatest$flatspec$FixtureAnyFlatSpecLike$_setter_$it_$eq:(Lorg/scalatest/flatspec/FixtureAnyFlatSpecLike$ItWord;)V
  #583 = InterfaceMethodref #2.#582       // org/scalatest/flatspec/FixtureAnyFlatSpecLike.org$scalatest$flatspec$FixtureAnyFlatSpecLike$_setter_$it_$eq:(Lorg/scalatest/flatspec/FixtureAnyFlatSpecLike$ItWord;)V
  #584 = Methodref          #95.#577      // org/scalatest/flatspec/FixtureAnyFlatSpecLike$TheyWord."<init>":(Lorg/scalatest/flatspec/FixtureAnyFlatSpecLike;)V
  #585 = NameAndType        #107:#108     // org$scalatest$flatspec$FixtureAnyFlatSpecLike$_setter_$they_$eq:(Lorg/scalatest/flatspec/FixtureAnyFlatSpecLike$TheyWord;)V
  #586 = InterfaceMethodref #2.#585       // org/scalatest/flatspec/FixtureAnyFlatSpecLike.org$scalatest$flatspec$FixtureAnyFlatSpecLike$_setter_$they_$eq:(Lorg/scalatest/flatspec/FixtureAnyFlatSpecLike$TheyWord;)V
  #587 = Methodref          #71.#577      // org/scalatest/flatspec/FixtureAnyFlatSpecLike$IgnoreWord."<init>":(Lorg/scalatest/flatspec/FixtureAnyFlatSpecLike;)V
  #588 = NameAndType        #109:#110     // org$scalatest$flatspec$FixtureAnyFlatSpecLike$_setter_$ignore_$eq:(Lorg/scalatest/flatspec/FixtureAnyFlatSpecLike$IgnoreWord;)V
  #589 = InterfaceMethodref #2.#588       // org/scalatest/flatspec/FixtureAnyFlatSpecLike.org$scalatest$flatspec$FixtureAnyFlatSpecLike$_setter_$ignore_$eq:(Lorg/scalatest/flatspec/FixtureAnyFlatSpecLike$IgnoreWord;)V
  #590 = Methodref          #58.#577      // org/scalatest/flatspec/FixtureAnyFlatSpecLike$$anon$1."<init>":(Lorg/scalatest/flatspec/FixtureAnyFlatSpecLike;)V
  #591 = NameAndType        #111:#112     // org$scalatest$flatspec$FixtureAnyFlatSpecLike$_setter_$shorthandTestRegistrationFunction_$eq:(Lorg/scalatest/verbs/StringVerbStringInvocation;)V
  #592 = InterfaceMethodref #2.#591       // org/scalatest/flatspec/FixtureAnyFlatSpecLike.org$scalatest$flatspec$FixtureAnyFlatSpecLike$_setter_$shorthandTestRegistrationFunction_$eq:(Lorg/scalatest/verbs/StringVerbStringInvocation;)V
  #593 = Methodref          #60.#577      // org/scalatest/flatspec/FixtureAnyFlatSpecLike$$anon$4."<init>":(Lorg/scalatest/flatspec/FixtureAnyFlatSpecLike;)V
  #594 = NameAndType        #113:#114     // org$scalatest$flatspec$FixtureAnyFlatSpecLike$_setter_$shorthandSharedTestRegistrationFunction_$eq:(Lorg/scalatest/verbs/StringVerbBehaveLikeInvocation;)V
  #595 = InterfaceMethodref #2.#594       // org/scalatest/flatspec/FixtureAnyFlatSpecLike.org$scalatest$flatspec$FixtureAnyFlatSpecLike$_setter_$shorthandSharedTestRegistrationFunction_$eq:(Lorg/scalatest/verbs/StringVerbBehaveLikeInvocation;)V
  #596 = Utf8               org/scalatest/verbs/BehaveWord
  #597 = Class              #596          // org/scalatest/verbs/BehaveWord
  #598 = Utf8               ()V
  #599 = NameAndType        #194:#598     // "<init>":()V
  #600 = Methodref          #597.#599     // org/scalatest/verbs/BehaveWord."<init>":()V
  #601 = NameAndType        #115:#116     // org$scalatest$flatspec$FixtureAnyFlatSpecLike$_setter_$behave_$eq:(Lorg/scalatest/verbs/BehaveWord;)V
  #602 = InterfaceMethodref #2.#601       // org/scalatest/flatspec/FixtureAnyFlatSpecLike.org$scalatest$flatspec$FixtureAnyFlatSpecLike$_setter_$behave_$eq:(Lorg/scalatest/verbs/BehaveWord;)V
  #603 = Utf8               org.scalatest.fixture.FlatSpec
  #604 = String             #603          // org.scalatest.fixture.FlatSpec
  #605 = NameAndType        #117:#102     // org$scalatest$flatspec$FixtureAnyFlatSpecLike$_setter_$styleName_$eq:(Ljava/lang/String;)V
  #606 = InterfaceMethodref #2.#605       // org/scalatest/flatspec/FixtureAnyFlatSpecLike.org$scalatest$flatspec$FixtureAnyFlatSpecLike$_setter_$styleName_$eq:(Ljava/lang/String;)V
  #607 = Utf8               $deserializeLambda$
  #608 = Utf8               (Ljava/lang/invoke/SerializedLambda;)Ljava/lang/Object;
  #609 = Utf8               scala/runtime/LambdaDeserialize
  #610 = Class              #609          // scala/runtime/LambdaDeserialize
  #611 = Utf8               bootstrap
  #612 = Utf8               (Ljava/lang/invoke/MethodHandles$Lookup;Ljava/lang/String;Ljava/lang/invoke/MethodType;[Ljava/lang/invoke/MethodHandle;)Ljava/lang/invoke/CallSite;
  #613 = NameAndType        #611:#612     // bootstrap:(Ljava/lang/invoke/MethodHandles$Lookup;Ljava/lang/String;Ljava/lang/invoke/MethodType;[Ljava/lang/invoke/MethodHandle;)Ljava/lang/invoke/CallSite;
  #614 = Methodref          #610.#613     // scala/runtime/LambdaDeserialize.bootstrap:(Ljava/lang/invoke/MethodHandles$Lookup;Ljava/lang/String;Ljava/lang/invoke/MethodType;[Ljava/lang/invoke/MethodHandle;)Ljava/lang/invoke/CallSite;
  #615 = MethodHandle       6:#614        // REF_invokeStatic scala/runtime/LambdaDeserialize.bootstrap:(Ljava/lang/invoke/MethodHandles$Lookup;Ljava/lang/String;Ljava/lang/invoke/MethodType;[Ljava/lang/invoke/MethodHandle;)Ljava/lang/invoke/CallSite;
  #616 = Utf8               lambdaDeserialize
  #617 = NameAndType        #616:#608     // lambdaDeserialize:(Ljava/lang/invoke/SerializedLambda;)Ljava/lang/Object;
  #618 = InvokeDynamic      #10:#617      // #10:lambdaDeserialize:(Ljava/lang/invoke/SerializedLambda;)Ljava/lang/Object;
  #619 = Utf8               Signature
  #620 = Utf8               MethodParameters
  #621 = Utf8               Code
  #622 = Utf8               LineNumberTable
  #623 = Utf8               LocalVariableTable
  #624 = Utf8               Deprecated
  #625 = Utf8               StackMapTable
  #626 = Utf8               InnerClasses
  #627 = Utf8               SourceFile
  #628 = Utf8               RuntimeVisibleAnnotations
  #629 = Utf8               BootstrapMethods
  #630 = Utf8               ScalaInlineInfo
  #631 = Utf8               ScalaSig
{
  public abstract void org$scalatest$flatspec$FixtureAnyFlatSpecLike$_setter_$org$scalatest$flatspec$FixtureAnyFlatSpecLike$$engine_$eq(org.scalatest.FixtureEngine<java.lang.Object>);
    descriptor: (Lorg/scalatest/FixtureEngine;)V
    flags: (0x0401) ACC_PUBLIC, ACC_ABSTRACT
    Signature: #99                          // (Lorg/scalatest/FixtureEngine<Ljava/lang/Object;>;)V
    MethodParameters:
      Name                           Flags
      x$1                            final

  public abstract void org$scalatest$flatspec$FixtureAnyFlatSpecLike$_setter_$sourceFileName_$eq(java.lang.String);
    descriptor: (Ljava/lang/String;)V
    flags: (0x0401) ACC_PUBLIC, ACC_ABSTRACT
    MethodParameters:
      Name                           Flags
      x$1                            final

  public abstract void org$scalatest$flatspec$FixtureAnyFlatSpecLike$_setter_$behavior_$eq(org.scalatest.flatspec.FixtureAnyFlatSpecLike$BehaviorWord);
    descriptor: (Lorg/scalatest/flatspec/FixtureAnyFlatSpecLike$BehaviorWord;)V
    flags: (0x0401) ACC_PUBLIC, ACC_ABSTRACT
    MethodParameters:
      Name                           Flags
      x$1                            final

  public abstract void org$scalatest$flatspec$FixtureAnyFlatSpecLike$_setter_$it_$eq(org.scalatest.flatspec.FixtureAnyFlatSpecLike$ItWord);
    descriptor: (Lorg/scalatest/flatspec/FixtureAnyFlatSpecLike$ItWord;)V
    flags: (0x0401) ACC_PUBLIC, ACC_ABSTRACT
    MethodParameters:
      Name                           Flags
      x$1                            final

  public abstract void org$scalatest$flatspec$FixtureAnyFlatSpecLike$_setter_$they_$eq(org.scalatest.flatspec.FixtureAnyFlatSpecLike$TheyWord);
    descriptor: (Lorg/scalatest/flatspec/FixtureAnyFlatSpecLike$TheyWord;)V
    flags: (0x0401) ACC_PUBLIC, ACC_ABSTRACT
    MethodParameters:
      Name                           Flags
      x$1                            final

  public abstract void org$scalatest$flatspec$FixtureAnyFlatSpecLike$_setter_$ignore_$eq(org.scalatest.flatspec.FixtureAnyFlatSpecLike$IgnoreWord);
    descriptor: (Lorg/scalatest/flatspec/FixtureAnyFlatSpecLike$IgnoreWord;)V
    flags: (0x0401) ACC_PUBLIC, ACC_ABSTRACT
    MethodParameters:
      Name                           Flags
      x$1                            final

  public abstract void org$scalatest$flatspec$FixtureAnyFlatSpecLike$_setter_$shorthandTestRegistrationFunction_$eq(org.scalatest.verbs.StringVerbStringInvocation);
    descriptor: (Lorg/scalatest/verbs/StringVerbStringInvocation;)V
    flags: (0x0401) ACC_PUBLIC, ACC_ABSTRACT
    MethodParameters:
      Name                           Flags
      x$1                            final

  public abstract void org$scalatest$flatspec$FixtureAnyFlatSpecLike$_setter_$shorthandSharedTestRegistrationFunction_$eq(org.scalatest.verbs.StringVerbBehaveLikeInvocation);
    descriptor: (Lorg/scalatest/verbs/StringVerbBehaveLikeInvocation;)V
    flags: (0x0401) ACC_PUBLIC, ACC_ABSTRACT
    MethodParameters:
      Name                           Flags
      x$1                            final

  public abstract void org$scalatest$flatspec$FixtureAnyFlatSpecLike$_setter_$behave_$eq(org.scalatest.verbs.BehaveWord);
    descriptor: (Lorg/scalatest/verbs/BehaveWord;)V
    flags: (0x0401) ACC_PUBLIC, ACC_ABSTRACT
    MethodParameters:
      Name                           Flags
      x$1                            final

  public abstract void org$scalatest$flatspec$FixtureAnyFlatSpecLike$_setter_$styleName_$eq(java.lang.String);
    descriptor: (Ljava/lang/String;)V
    flags: (0x0401) ACC_PUBLIC, ACC_ABSTRACT
    MethodParameters:
      Name                           Flags
      x$1                            final

  public abstract org.scalatest.Status org$scalatest$flatspec$FixtureAnyFlatSpecLike$$super$run(scala.Option, org.scalatest.Args);
    descriptor: (Lscala/Option;Lorg/scalatest/Args;)Lorg/scalatest/Status;
    flags: (0x1401) ACC_PUBLIC, ACC_ABSTRACT, ACC_SYNTHETIC
    MethodParameters:
      Name                           Flags
      testName                       final
      args                           final

  public abstract org.scalatest.FixtureEngine<java.lang.Object> org$scalatest$flatspec$FixtureAnyFlatSpecLike$$engine();
    descriptor: ()Lorg/scalatest/FixtureEngine;
    flags: (0x0401) ACC_PUBLIC, ACC_ABSTRACT
    Signature: #124                         // ()Lorg/scalatest/FixtureEngine<Ljava/lang/Object;>;

  public abstract java.lang.String sourceFileName();
    descriptor: ()Ljava/lang/String;
    flags: (0x0401) ACC_PUBLIC, ACC_ABSTRACT

  public static org.scalatest.Informer info$(org.scalatest.flatspec.FixtureAnyFlatSpecLike);
    descriptor: (Lorg/scalatest/flatspec/FixtureAnyFlatSpecLike;)Lorg/scalatest/Informer;
    flags: (0x1009) ACC_PUBLIC, ACC_STATIC, ACC_SYNTHETIC
    Code:
      stack=1, locals=1, args_size=1
         0: aload_0
         1: invokespecial #133                // InterfaceMethod info:()Lorg/scalatest/Informer;
         4: areturn
      LineNumberTable:
        line 65: 0
      LocalVariableTable:
        Start  Length  Slot  Name   Signature
            0       5     0 $this   Lorg/scalatest/flatspec/FixtureAnyFlatSpecLike;
    MethodParameters:
      Name                           Flags
      $this                          final synthetic

  public default org.scalatest.Informer info();
    descriptor: ()Lorg/scalatest/Informer;
    flags: (0x0001) ACC_PUBLIC
    Code:
      stack=1, locals=1, args_size=1
         0: aload_0
         1: invokeinterface #136,  1          // InterfaceMethod org$scalatest$flatspec$FixtureAnyFlatSpecLike$$engine:()Lorg/scalatest/FixtureEngine;
         6: invokevirtual #142                // Method org/scalatest/FixtureEngine.atomicInformer:()Ljava/util/concurrent/atomic/AtomicReference;
         9: invokevirtual #148                // Method java/util/concurrent/atomic/AtomicReference.get:()Ljava/lang/Object;
        12: checkcast     #150                // class org/scalatest/Informer
        15: areturn
      LineNumberTable:
        line 65: 0
      LocalVariableTable:
        Start  Length  Slot  Name   Signature
            0      16     0  this   Lorg/scalatest/flatspec/FixtureAnyFlatSpecLike;

  public static org.scalatest.Notifier note$(org.scalatest.flatspec.FixtureAnyFlatSpecLike);
    descriptor: (Lorg/scalatest/flatspec/FixtureAnyFlatSpecLike;)Lorg/scalatest/Notifier;
    flags: (0x1009) ACC_PUBLIC, ACC_STATIC, ACC_SYNTHETIC
    Code:
      stack=1, locals=1, args_size=1
         0: aload_0
         1: invokespecial #157                // InterfaceMethod note:()Lorg/scalatest/Notifier;
         4: areturn
      LineNumberTable:
        line 75: 0
      LocalVariableTable:
        Start  Length  Slot  Name   Signature
            0       5     0 $this   Lorg/scalatest/flatspec/FixtureAnyFlatSpecLike;
    MethodParameters:
      Name                           Flags
      $this                          final synthetic

  public default org.scalatest.Notifier note();
    descriptor: ()Lorg/scalatest/Notifier;
    flags: (0x0001) ACC_PUBLIC
    Code:
      stack=1, locals=1, args_size=1
         0: aload_0
         1: invokeinterface #136,  1          // InterfaceMethod org$scalatest$flatspec$FixtureAnyFlatSpecLike$$engine:()Lorg/scalatest/FixtureEngine;
         6: invokevirtual #160                // Method org/scalatest/FixtureEngine.atomicNotifier:()Ljava/util/concurrent/atomic/AtomicReference;
         9: invokevirtual #148                // Method java/util/concurrent/atomic/AtomicReference.get:()Ljava/lang/Object;
        12: checkcast     #162                // class org/scalatest/Notifier
        15: areturn
      LineNumberTable:
        line 75: 0
      LocalVariableTable:
        Start  Length  Slot  Name   Signature
            0      16     0  this   Lorg/scalatest/flatspec/FixtureAnyFlatSpecLike;

  public static org.scalatest.Alerter alert$(org.scalatest.flatspec.FixtureAnyFlatSpecLike);
    descriptor: (Lorg/scalatest/flatspec/FixtureAnyFlatSpecLike;)Lorg/scalatest/Alerter;
    flags: (0x1009) ACC_PUBLIC, ACC_STATIC, ACC_SYNTHETIC
    Code:
      stack=1, locals=1, args_size=1
         0: aload_0
         1: invokespecial #168                // InterfaceMethod alert:()Lorg/scalatest/Alerter;
         4: areturn
      LineNumberTable:
        line 85: 0
      LocalVariableTable:
        Start  Length  Slot  Name   Signature
            0       5     0 $this   Lorg/scalatest/flatspec/FixtureAnyFlatSpecLike;
    MethodParameters:
      Name                           Flags
      $this                          final synthetic

  public default org.scalatest.Alerter alert();
    descriptor: ()Lorg/scalatest/Alerter;
    flags: (0x0001) ACC_PUBLIC
    Code:
      stack=1, locals=1, args_size=1
         0: aload_0
         1: invokeinterface #136,  1          // InterfaceMethod org$scalatest$flatspec$FixtureAnyFlatSpecLike$$engine:()Lorg/scalatest/FixtureEngine;
         6: invokevirtual #171                // Method org/scalatest/FixtureEngine.atomicAlerter:()Ljava/util/concurrent/atomic/AtomicReference;
         9: invokevirtual #148                // Method java/util/concurrent/atomic/AtomicReference.get:()Ljava/lang/Object;
        12: checkcast     #173                // class org/scalatest/Alerter
        15: areturn
      LineNumberTable:
        line 85: 0
      LocalVariableTable:
        Start  Length  Slot  Name   Signature
            0      16     0  this   Lorg/scalatest/flatspec/FixtureAnyFlatSpecLike;

  public static org.scalatest.Documenter markup$(org.scalatest.flatspec.FixtureAnyFlatSpecLike);
    descriptor: (Lorg/scalatest/flatspec/FixtureAnyFlatSpecLike;)Lorg/scalatest/Documenter;
    flags: (0x1009) ACC_PUBLIC, ACC_STATIC, ACC_SYNTHETIC
    Code:
      stack=1, locals=1, args_size=1
         0: aload_0
         1: invokespecial #179                // InterfaceMethod markup:()Lorg/scalatest/Documenter;
         4: areturn
      LineNumberTable:
        line 96: 0
      LocalVariableTable:
        Start  Length  Slot  Name   Signature
            0       5     0 $this   Lorg/scalatest/flatspec/FixtureAnyFlatSpecLike;
    MethodParameters:
      Name                           Flags
      $this                          final synthetic

  public default org.scalatest.Documenter markup();
    descriptor: ()Lorg/scalatest/Documenter;
    flags: (0x0001) ACC_PUBLIC
    Code:
      stack=1, locals=1, args_size=1
         0: aload_0
         1: invokeinterface #136,  1          // InterfaceMethod org$scalatest$flatspec$FixtureAnyFlatSpecLike$$engine:()Lorg/scalatest/FixtureEngine;
         6: invokevirtual #182                // Method org/scalatest/FixtureEngine.atomicDocumenter:()Ljava/util/concurrent/atomic/AtomicReference;
         9: invokevirtual #148                // Method java/util/concurrent/atomic/AtomicReference.get:()Ljava/lang/Object;
        12: checkcast     #184                // class org/scalatest/Documenter
        15: areturn
      LineNumberTable:
        line 96: 0
      LocalVariableTable:
        Start  Length  Slot  Name   Signature
            0      16     0  this   Lorg/scalatest/flatspec/FixtureAnyFlatSpecLike;

  private void registerTestImpl(java.lang.String, scala.collection.immutable.Seq<org.scalatest.Tag>, scala.Function1<java.lang.Object, java.lang.Object>, org.scalactic.source.Position);
    descriptor: (Ljava/lang/String;Lscala/collection/immutable/Seq;Lscala/Function1;Lorg/scalactic/source/Position;)V
    flags: (0x0002) ACC_PRIVATE
    Code:
      stack=13, locals=6, args_size=5
         0: iconst_m1
         1: istore        5
         3: aload_0
         4: invokeinterface #136,  1          // InterfaceMethod org$scalatest$flatspec$FixtureAnyFlatSpecLike$$engine:()Lorg/scalatest/FixtureEngine;
         9: aload_1
        10: new           #193                // class org/scalatest/fixture/Transformer
        13: dup
        14: aload_3
        15: invokespecial #197                // Method org/scalatest/fixture/Transformer."<init>":(Lscala/Function1;)V
        18: invokedynamic #216,  0            // InvokeDynamic #0:apply:()Lscala/Function0;
        23: ldc           #217                // String FixtureAnyFlatSpecLike.scala
        25: ldc           #219                // String registerTest
        27: iconst_4
        28: iload         5
        30: getstatic     #225                // Field scala/None$.MODULE$:Lscala/None$;
        33: getstatic     #225                // Field scala/None$.MODULE$:Lscala/None$;
        36: new           #227                // class scala/Some
        39: dup
        40: aload         4
        42: invokespecial #230                // Method scala/Some."<init>":(Ljava/lang/Object;)V
        45: getstatic     #225                // Field scala/None$.MODULE$:Lscala/None$;
        48: aload_2
        49: invokevirtual #233                // Method org/scalatest/FixtureEngine.registerTest:(Ljava/lang/String;Ljava/lang/Object;Lscala/Function0;Ljava/lang/String;Ljava/lang/String;IILscala/Option;Lscala/Option;Lscala/Option;Lscala/Option;Lscala/collection/immutable/Seq;)Ljava/lang/String;
        52: pop
        53: return
      LineNumberTable:
        line 100: 0
        line 103: 3
      LocalVariableTable:
        Start  Length  Slot  Name   Signature
            3      50     5 stackDepthAdjustment   I
            0      54     0  this   Lorg/scalatest/flatspec/FixtureAnyFlatSpecLike;
            0      54     1 testText   Ljava/lang/String;
            0      54     2 testTags   Lscala/collection/immutable/Seq;
            0      54     3 testFun   Lscala/Function1;
            0      54     4   pos   Lorg/scalactic/source/Position;
    Signature: #187                         // (Ljava/lang/String;Lscala/collection/immutable/Seq<Lorg/scalatest/Tag;>;Lscala/Function1<Ljava/lang/Object;Ljava/lang/Object;>;Lorg/scalactic/source/Position;)V
    MethodParameters:
      Name                           Flags
      testText                       final
      testTags                       final
      testFun                        final
      pos                            final

  public static void registerTest$(org.scalatest.flatspec.FixtureAnyFlatSpecLike, java.lang.String, scala.collection.immutable.Seq, scala.Function1, org.scalactic.source.Position);
    descriptor: (Lorg/scalatest/flatspec/FixtureAnyFlatSpecLike;Ljava/lang/String;Lscala/collection/immutable/Seq;Lscala/Function1;Lorg/scalactic/source/Position;)V
    flags: (0x1009) ACC_PUBLIC, ACC_STATIC, ACC_SYNTHETIC
    Code:
      stack=5, locals=5, args_size=5
         0: aload_0
         1: aload_1
         2: aload_2
         3: aload_3
         4: aload         4
         6: invokespecial #243                // InterfaceMethod registerTest:(Ljava/lang/String;Lscala/collection/immutable/Seq;Lscala/Function1;Lorg/scalactic/source/Position;)V
         9: return
      LineNumberTable:
        line 107: 0
      LocalVariableTable:
        Start  Length  Slot  Name   Signature
            0      10     0 $this   Lorg/scalatest/flatspec/FixtureAnyFlatSpecLike;
            0      10     1 testText   Ljava/lang/String;
            0      10     2 testTags   Lscala/collection/immutable/Seq;
            0      10     3 testFun   Lscala/Function1;
            0      10     4   pos   Lorg/scalactic/source/Position;
    MethodParameters:
      Name                           Flags
      $this                          final synthetic
      testText                       final
      testTags                       final
      testFun                        final
      pos                            final

  public default void registerTest(java.lang.String, scala.collection.immutable.Seq<org.scalatest.Tag>, scala.Function1<java.lang.Object, java.lang.Object>, org.scalactic.source.Position);
    descriptor: (Ljava/lang/String;Lscala/collection/immutable/Seq;Lscala/Function1;Lorg/scalactic/source/Position;)V
    flags: (0x0001) ACC_PUBLIC
    Code:
      stack=5, locals=5, args_size=5
         0: aload_0
         1: aload_1
         2: aload_2
         3: aload_3
         4: aload         4
         6: invokespecial #245                // InterfaceMethod registerTestImpl:(Ljava/lang/String;Lscala/collection/immutable/Seq;Lscala/Function1;Lorg/scalactic/source/Position;)V
         9: return
      LineNumberTable:
        line 108: 0
      LocalVariableTable:
        Start  Length  Slot  Name   Signature
            0      10     0  this   Lorg/scalatest/flatspec/FixtureAnyFlatSpecLike;
            0      10     1 testText   Ljava/lang/String;
            0      10     2 testTags   Lscala/collection/immutable/Seq;
            0      10     3 testFun   Lscala/Function1;
            0      10     4   pos   Lorg/scalactic/source/Position;
    Signature: #187                         // (Ljava/lang/String;Lscala/collection/immutable/Seq<Lorg/scalatest/Tag;>;Lscala/Function1<Ljava/lang/Object;Ljava/lang/Object;>;Lorg/scalactic/source/Position;)V
    MethodParameters:
      Name                           Flags
      testText                       final
      testTags                       final
      testFun                        final
      pos                            final

  private void registerIgnoredTestImpl(java.lang.String, scala.collection.immutable.Seq<org.scalatest.Tag>, scala.Function1<java.lang.Object, java.lang.Object>, org.scalactic.source.Position);
    descriptor: (Ljava/lang/String;Lscala/collection/immutable/Seq;Lscala/Function1;Lorg/scalactic/source/Position;)V
    flags: (0x0002) ACC_PRIVATE
    Code:
      stack=12, locals=6, args_size=5
         0: bipush        -3
         2: istore        5
         4: aload_0
         5: invokeinterface #136,  1          // InterfaceMethod org$scalatest$flatspec$FixtureAnyFlatSpecLike$$engine:()Lorg/scalatest/FixtureEngine;
        10: aload_1
        11: new           #193                // class org/scalatest/fixture/Transformer
        14: dup
        15: aload_3
        16: invokespecial #197                // Method org/scalatest/fixture/Transformer."<init>":(Lscala/Function1;)V
        19: invokedynamic #251,  0            // InvokeDynamic #1:apply:()Lscala/Function0;
        24: ldc           #217                // String FixtureAnyFlatSpecLike.scala
        26: ldc           #253                // String registerIgnoredTest
        28: iconst_4
        29: iload         5
        31: getstatic     #225                // Field scala/None$.MODULE$:Lscala/None$;
        34: new           #227                // class scala/Some
        37: dup
        38: aload         4
        40: invokespecial #230                // Method scala/Some."<init>":(Ljava/lang/Object;)V
        43: aload_2
        44: invokevirtual #256                // Method org/scalatest/FixtureEngine.registerIgnoredTest:(Ljava/lang/String;Ljava/lang/Object;Lscala/Function0;Ljava/lang/String;Ljava/lang/String;IILscala/Option;Lscala/Option;Lscala/collection/immutable/Seq;)V
        47: return
      LineNumberTable:
        line 117: 0
        line 120: 4
      LocalVariableTable:
        Start  Length  Slot  Name   Signature
            4      43     5 stackDepthAdjustment   I
            0      48     0  this   Lorg/scalatest/flatspec/FixtureAnyFlatSpecLike;
            0      48     1 testText   Ljava/lang/String;
            0      48     2 testTags   Lscala/collection/immutable/Seq;
            0      48     3 testFun   Lscala/Function1;
            0      48     4   pos   Lorg/scalactic/source/Position;
    Signature: #187                         // (Ljava/lang/String;Lscala/collection/immutable/Seq<Lorg/scalatest/Tag;>;Lscala/Function1<Ljava/lang/Object;Ljava/lang/Object;>;Lorg/scalactic/source/Position;)V
    MethodParameters:
      Name                           Flags
      testText                       final
      testTags                       final
      testFun                        final
      pos                            final

  public static void registerIgnoredTest$(org.scalatest.flatspec.FixtureAnyFlatSpecLike, java.lang.String, scala.collection.immutable.Seq, scala.Function1, org.scalactic.source.Position);
    descriptor: (Lorg/scalatest/flatspec/FixtureAnyFlatSpecLike;Ljava/lang/String;Lscala/collection/immutable/Seq;Lscala/Function1;Lorg/scalactic/source/Position;)V
    flags: (0x1009) ACC_PUBLIC, ACC_STATIC, ACC_SYNTHETIC
    Code:
      stack=5, locals=5, args_size=5
         0: aload_0
         1: aload_1
         2: aload_2
         3: aload_3
         4: aload         4
         6: invokespecial #259                // InterfaceMethod registerIgnoredTest:(Ljava/lang/String;Lscala/collection/immutable/Seq;Lscala/Function1;Lorg/scalactic/source/Position;)V
         9: return
      LineNumberTable:
        line 124: 0
      LocalVariableTable:
        Start  Length  Slot  Name   Signature
            0      10     0 $this   Lorg/scalatest/flatspec/FixtureAnyFlatSpecLike;
            0      10     1 testText   Ljava/lang/String;
            0      10     2 testTags   Lscala/collection/immutable/Seq;
            0      10     3 testFun   Lscala/Function1;
            0      10     4   pos   Lorg/scalactic/source/Position;
    MethodParameters:
      Name                           Flags
      $this                          final synthetic
      testText                       final
      testTags                       final
      testFun                        final
      pos                            final

  public default void registerIgnoredTest(java.lang.String, scala.collection.immutable.Seq<org.scalatest.Tag>, scala.Function1<java.lang.Object, java.lang.Object>, org.scalactic.source.Position);
    descriptor: (Ljava/lang/String;Lscala/collection/immutable/Seq;Lscala/Function1;Lorg/scalactic/source/Position;)V
    flags: (0x0001) ACC_PUBLIC
    Code:
      stack=5, locals=5, args_size=5
         0: aload_0
         1: aload_1
         2: aload_2
         3: aload_3
         4: aload         4
         6: invokespecial #261                // InterfaceMethod registerIgnoredTestImpl:(Ljava/lang/String;Lscala/collection/immutable/Seq;Lscala/Function1;Lorg/scalactic/source/Position;)V
         9: return
      LineNumberTable:
        line 125: 0
      LocalVariableTable:
        Start  Length  Slot  Name   Signature
            0      10     0  this   Lorg/scalatest/flatspec/FixtureAnyFlatSpecLike;
            0      10     1 testText   Ljava/lang/String;
            0      10     2 testTags   Lscala/collection/immutable/Seq;
            0      10     3 testFun   Lscala/Function1;
            0      10     4   pos   Lorg/scalactic/source/Position;
    Signature: #187                         // (Ljava/lang/String;Lscala/collection/immutable/Seq<Lorg/scalatest/Tag;>;Lscala/Function1<Ljava/lang/Object;Ljava/lang/Object;>;Lorg/scalactic/source/Position;)V
    MethodParameters:
      Name                           Flags
      testText                       final
      testTags                       final
      testFun                        final
      pos                            final

  public static void org$scalatest$flatspec$FixtureAnyFlatSpecLike$$registerTestToRun$(org.scalatest.flatspec.FixtureAnyFlatSpecLike, java.lang.String, scala.collection.immutable.List, java.lang.String, scala.Function1, org.scalactic.source.Position);
    descriptor: (Lorg/scalatest/flatspec/FixtureAnyFlatSpecLike;Ljava/lang/String;Lscala/collection/immutable/List;Ljava/lang/String;Lscala/Function1;Lorg/scalactic/source/Position;)V
    flags: (0x1009) ACC_PUBLIC, ACC_STATIC, ACC_SYNTHETIC
    Code:
      stack=6, locals=6, args_size=6
         0: aload_0
         1: aload_1
         2: aload_2
         3: aload_3
         4: aload         4
         6: aload         5
         8: invokespecial #269                // InterfaceMethod org$scalatest$flatspec$FixtureAnyFlatSpecLike$$registerTestToRun:(Ljava/lang/String;Lscala/collection/immutable/List;Ljava/lang/String;Lscala/Function1;Lorg/scalactic/source/Position;)V
        11: return
      LineNumberTable:
        line 151: 0
      LocalVariableTable:
        Start  Length  Slot  Name   Signature
            0      12     0 $this   Lorg/scalatest/flatspec/FixtureAnyFlatSpecLike;
            0      12     1 specText   Ljava/lang/String;
            0      12     2 testTags   Lscala/collection/immutable/List;
            0      12     3 methodName   Ljava/lang/String;
            0      12     4 testFun   Lscala/Function1;
            0      12     5   pos   Lorg/scalactic/source/Position;
    MethodParameters:
      Name                           Flags
      $this                          final synthetic
      specText                       final
      testTags                       final
      methodName                     final
      testFun                        final
      pos                            final

  public default void org$scalatest$flatspec$FixtureAnyFlatSpecLike$$registerTestToRun(java.lang.String, scala.collection.immutable.List<org.scalatest.Tag>, java.lang.String, scala.Function1<java.lang.Object, java.lang.Object>, org.scalactic.source.Position);
    descriptor: (Ljava/lang/String;Lscala/collection/immutable/List;Ljava/lang/String;Lscala/Function1;Lorg/scalactic/source/Position;)V
    flags: (0x0001) ACC_PUBLIC
    Code:
      stack=13, locals=8, args_size=6
         0: iconst_4
         1: istore        6
         3: bipush        -3
         5: istore        7
         7: aload_0
         8: invokeinterface #136,  1          // InterfaceMethod org$scalatest$flatspec$FixtureAnyFlatSpecLike$$engine:()Lorg/scalatest/FixtureEngine;
        13: aload_1
        14: new           #193                // class org/scalatest/fixture/Transformer
        17: dup
        18: aload         4
        20: invokespecial #197                // Method org/scalatest/fixture/Transformer."<init>":(Lscala/Function1;)V
        23: aload_3
        24: invokedynamic #279,  0            // InvokeDynamic #2:apply:(Ljava/lang/String;)Lscala/Function0;
        29: aload_0
        30: invokeinterface #281,  1          // InterfaceMethod sourceFileName:()Ljava/lang/String;
        35: aload_3
        36: iload         6
        38: iload         7
        40: getstatic     #225                // Field scala/None$.MODULE$:Lscala/None$;
        43: getstatic     #225                // Field scala/None$.MODULE$:Lscala/None$;
        46: new           #227                // class scala/Some
        49: dup
        50: aload         5
        52: invokespecial #230                // Method scala/Some."<init>":(Ljava/lang/Object;)V
        55: getstatic     #225                // Field scala/None$.MODULE$:Lscala/None$;
        58: aload_2
        59: invokevirtual #233                // Method org/scalatest/FixtureEngine.registerTest:(Ljava/lang/String;Ljava/lang/Object;Lscala/Function0;Ljava/lang/String;Ljava/lang/String;IILscala/Option;Lscala/Option;Lscala/Option;Lscala/Option;Lscala/collection/immutable/Seq;)Ljava/lang/String;
        62: pop
        63: return
      LineNumberTable:
        line 154: 0
        line 155: 3
        line 166: 7
      LocalVariableTable:
        Start  Length  Slot  Name   Signature
            3      60     6 stackDepth   I
            7      56     7 stackDepthAdjustment   I
            0      64     0  this   Lorg/scalatest/flatspec/FixtureAnyFlatSpecLike;
            0      64     1 specText   Ljava/lang/String;
            0      64     2 testTags   Lscala/collection/immutable/List;
            0      64     3 methodName   Ljava/lang/String;
            0      64     4 testFun   Lscala/Function1;
            0      64     5   pos   Lorg/scalactic/source/Position;
    Signature: #271                         // (Ljava/lang/String;Lscala/collection/immutable/List<Lorg/scalatest/Tag;>;Ljava/lang/String;Lscala/Function1<Ljava/lang/Object;Ljava/lang/Object;>;Lorg/scalactic/source/Position;)V
    MethodParameters:
      Name                           Flags
      specText                       final
      testTags                       final
      methodName                     final
      testFun                        final
      pos                            final

  public static void org$scalatest$flatspec$FixtureAnyFlatSpecLike$$registerPendingTestToRun$(org.scalatest.flatspec.FixtureAnyFlatSpecLike, java.lang.String, scala.collection.immutable.List, java.lang.String, scala.Function1, org.scalactic.source.Position);
    descriptor: (Lorg/scalatest/flatspec/FixtureAnyFlatSpecLike;Ljava/lang/String;Lscala/collection/immutable/List;Ljava/lang/String;Lscala/Function1;Lorg/scalactic/source/Position;)V
    flags: (0x1009) ACC_PUBLIC, ACC_STATIC, ACC_SYNTHETIC
    Code:
      stack=6, locals=6, args_size=6
         0: aload_0
         1: aload_1
         2: aload_2
         3: aload_3
         4: aload         4
         6: aload         5
         8: invokespecial #286                // InterfaceMethod org$scalatest$flatspec$FixtureAnyFlatSpecLike$$registerPendingTestToRun:(Ljava/lang/String;Lscala/collection/immutable/List;Ljava/lang/String;Lscala/Function1;Lorg/scalactic/source/Position;)V
        11: return
      LineNumberTable:
        line 169: 0
      LocalVariableTable:
        Start  Length  Slot  Name   Signature
            0      12     0 $this   Lorg/scalatest/flatspec/FixtureAnyFlatSpecLike;
            0      12     1 specText   Ljava/lang/String;
            0      12     2 testTags   Lscala/collection/immutable/List;
            0      12     3 methodName   Ljava/lang/String;
            0      12     4 testFun   Lscala/Function1;
            0      12     5   pos   Lorg/scalactic/source/Position;
    MethodParameters:
      Name                           Flags
      $this                          final synthetic
      specText                       final
      testTags                       final
      methodName                     final
      testFun                        final
      pos                            final

  public default void org$scalatest$flatspec$FixtureAnyFlatSpecLike$$registerPendingTestToRun(java.lang.String, scala.collection.immutable.List<org.scalatest.Tag>, java.lang.String, scala.Function1<java.lang.Object, org.scalatest.PendingStatement>, org.scalactic.source.Position);
    descriptor: (Ljava/lang/String;Lscala/collection/immutable/List;Ljava/lang/String;Lscala/Function1;Lorg/scalactic/source/Position;)V
    flags: (0x0001) ACC_PUBLIC
    Code:
      stack=13, locals=6, args_size=6
         0: aload_0
         1: invokeinterface #136,  1          // InterfaceMethod org$scalatest$flatspec$FixtureAnyFlatSpecLike$$engine:()Lorg/scalatest/FixtureEngine;
         6: aload_1
         7: new           #193                // class org/scalatest/fixture/Transformer
        10: dup
        11: aload         4
        13: invokespecial #197                // Method org/scalatest/fixture/Transformer."<init>":(Lscala/Function1;)V
        16: aload_3
        17: invokedynamic #292,  0            // InvokeDynamic #3:apply:(Ljava/lang/String;)Lscala/Function0;
        22: aload_0
        23: invokeinterface #281,  1          // InterfaceMethod sourceFileName:()Ljava/lang/String;
        28: aload_3
        29: iconst_4
        30: bipush        -3
        32: getstatic     #225                // Field scala/None$.MODULE$:Lscala/None$;
        35: getstatic     #225                // Field scala/None$.MODULE$:Lscala/None$;
        38: new           #227                // class scala/Some
        41: dup
        42: aload         5
        44: invokespecial #230                // Method scala/Some."<init>":(Ljava/lang/Object;)V
        47: getstatic     #225                // Field scala/None$.MODULE$:Lscala/None$;
        50: aload_2
        51: invokevirtual #233                // Method org/scalatest/FixtureEngine.registerTest:(Ljava/lang/String;Ljava/lang/Object;Lscala/Function0;Ljava/lang/String;Ljava/lang/String;IILscala/Option;Lscala/Option;Lscala/Option;Lscala/Option;Lscala/collection/immutable/Seq;)Ljava/lang/String;
        54: pop
        55: return
      LineNumberTable:
        line 176: 0
      LocalVariableTable:
        Start  Length  Slot  Name   Signature
            0      56     0  this   Lorg/scalatest/flatspec/FixtureAnyFlatSpecLike;
            0      56     1 specText   Ljava/lang/String;
            0      56     2 testTags   Lscala/collection/immutable/List;
            0      56     3 methodName   Ljava/lang/String;
            0      56     4 testFun   Lscala/Function1;
            0      56     5   pos   Lorg/scalactic/source/Position;
    Signature: #287                         // (Ljava/lang/String;Lscala/collection/immutable/List<Lorg/scalatest/Tag;>;Ljava/lang/String;Lscala/Function1<Ljava/lang/Object;Lorg/scalatest/PendingStatement;>;Lorg/scalactic/source/Position;)V
    MethodParameters:
      Name                           Flags
      specText                       final
      testTags                       final
      methodName                     final
      testFun                        final
      pos                            final

  public abstract org.scalatest.flatspec.FixtureAnyFlatSpecLike$BehaviorWord behavior();
    descriptor: ()Lorg/scalatest/flatspec/FixtureAnyFlatSpecLike$BehaviorWord;
    flags: (0x0401) ACC_PUBLIC, ACC_ABSTRACT

  public abstract org.scalatest.flatspec.FixtureAnyFlatSpecLike$ItWord it();
    descriptor: ()Lorg/scalatest/flatspec/FixtureAnyFlatSpecLike$ItWord;
    flags: (0x0401) ACC_PUBLIC, ACC_ABSTRACT

  public abstract org.scalatest.flatspec.FixtureAnyFlatSpecLike$TheyWord they();
    descriptor: ()Lorg/scalatest/flatspec/FixtureAnyFlatSpecLike$TheyWord;
    flags: (0x0401) ACC_PUBLIC, ACC_ABSTRACT

  public abstract org.scalatest.flatspec.FixtureAnyFlatSpecLike$IgnoreWord ignore();
    descriptor: ()Lorg/scalatest/flatspec/FixtureAnyFlatSpecLike$IgnoreWord;
    flags: (0x0401) ACC_PUBLIC, ACC_ABSTRACT

  public static org.scalatest.flatspec.FixtureAnyFlatSpecLike$InAndIgnoreMethods convertToInAndIgnoreMethods$(org.scalatest.flatspec.FixtureAnyFlatSpecLike, org.scalatest.verbs.ResultOfStringPassedToVerb);
    descriptor: (Lorg/scalatest/flatspec/FixtureAnyFlatSpecLike;Lorg/scalatest/verbs/ResultOfStringPassedToVerb;)Lorg/scalatest/flatspec/FixtureAnyFlatSpecLike$InAndIgnoreMethods;
    flags: (0x1009) ACC_PUBLIC, ACC_STATIC, ACC_SYNTHETIC
    Code:
      stack=2, locals=2, args_size=2
         0: aload_0
         1: aload_1
         2: invokespecial #307                // InterfaceMethod convertToInAndIgnoreMethods:(Lorg/scalatest/verbs/ResultOfStringPassedToVerb;)Lorg/scalatest/flatspec/FixtureAnyFlatSpecLike$InAndIgnoreMethods;
         5: areturn
      LineNumberTable:
        line 2050: 0
      LocalVariableTable:
        Start  Length  Slot  Name   Signature
            0       6     0 $this   Lorg/scalatest/flatspec/FixtureAnyFlatSpecLike;
            0       6     1 resultOfStringPassedToVerb   Lorg/scalatest/verbs/ResultOfStringPassedToVerb;
    MethodParameters:
      Name                           Flags
      $this                          final synthetic
      resultOfStringPassedToVerb     final

  public default org.scalatest.flatspec.FixtureAnyFlatSpecLike$InAndIgnoreMethods convertToInAndIgnoreMethods(org.scalatest.verbs.ResultOfStringPassedToVerb);
    descriptor: (Lorg/scalatest/verbs/ResultOfStringPassedToVerb;)Lorg/scalatest/flatspec/FixtureAnyFlatSpecLike$InAndIgnoreMethods;
    flags: (0x0001) ACC_PUBLIC
    Code:
      stack=4, locals=2, args_size=2
         0: new           #74                 // class org/scalatest/flatspec/FixtureAnyFlatSpecLike$InAndIgnoreMethods
         3: dup
         4: aload_0
         5: aload_1
         6: invokespecial #311                // Method org/scalatest/flatspec/FixtureAnyFlatSpecLike$InAndIgnoreMethods."<init>":(Lorg/scalatest/flatspec/FixtureAnyFlatSpecLike;Lorg/scalatest/verbs/ResultOfStringPassedToVerb;)V
         9: areturn
      LineNumberTable:
        line 2051: 0
      LocalVariableTable:
        Start  Length  Slot  Name   Signature
            0      10     0  this   Lorg/scalatest/flatspec/FixtureAnyFlatSpecLike;
            0      10     1 resultOfStringPassedToVerb   Lorg/scalatest/verbs/ResultOfStringPassedToVerb;
    MethodParameters:
      Name                           Flags
      resultOfStringPassedToVerb     final

  public static org.scalatest.flatspec.FixtureAnyFlatSpecLike$InAndIgnoreMethodsAfterTaggedAs convertToInAndIgnoreMethodsAfterTaggedAs$(org.scalatest.flatspec.FixtureAnyFlatSpecLike, org.scalatest.verbs.ResultOfTaggedAsInvocation);
    descriptor: (Lorg/scalatest/flatspec/FixtureAnyFlatSpecLike;Lorg/scalatest/verbs/ResultOfTaggedAsInvocation;)Lorg/scalatest/flatspec/FixtureAnyFlatSpecLike$InAndIgnoreMethodsAfterTaggedAs;
    flags: (0x1009) ACC_PUBLIC, ACC_STATIC, ACC_SYNTHETIC
    Code:
      stack=2, locals=2, args_size=2
         0: aload_0
         1: aload_1
         2: invokespecial #318                // InterfaceMethod convertToInAndIgnoreMethodsAfterTaggedAs:(Lorg/scalatest/verbs/ResultOfTaggedAsInvocation;)Lorg/scalatest/flatspec/FixtureAnyFlatSpecLike$InAndIgnoreMethodsAfterTaggedAs;
         5: areturn
      LineNumberTable:
        line 2233: 0
      LocalVariableTable:
        Start  Length  Slot  Name   Signature
            0       6     0 $this   Lorg/scalatest/flatspec/FixtureAnyFlatSpecLike;
            0       6     1 resultOfTaggedAsInvocation   Lorg/scalatest/verbs/ResultOfTaggedAsInvocation;
    MethodParameters:
      Name                           Flags
      $this                          final synthetic
      resultOfTaggedAsInvocation     final

  public default org.scalatest.flatspec.FixtureAnyFlatSpecLike$InAndIgnoreMethodsAfterTaggedAs convertToInAndIgnoreMethodsAfterTaggedAs(org.scalatest.verbs.ResultOfTaggedAsInvocation);
    descriptor: (Lorg/scalatest/verbs/ResultOfTaggedAsInvocation;)Lorg/scalatest/flatspec/FixtureAnyFlatSpecLike$InAndIgnoreMethodsAfterTaggedAs;
    flags: (0x0001) ACC_PUBLIC
    Code:
      stack=4, locals=2, args_size=2
         0: new           #77                 // class org/scalatest/flatspec/FixtureAnyFlatSpecLike$InAndIgnoreMethodsAfterTaggedAs
         3: dup
         4: aload_0
         5: aload_1
         6: invokespecial #322                // Method org/scalatest/flatspec/FixtureAnyFlatSpecLike$InAndIgnoreMethodsAfterTaggedAs."<init>":(Lorg/scalatest/flatspec/FixtureAnyFlatSpecLike;Lorg/scalatest/verbs/ResultOfTaggedAsInvocation;)V
         9: areturn
      LineNumberTable:
        line 2234: 0
      LocalVariableTable:
        Start  Length  Slot  Name   Signature
            0      10     0  this   Lorg/scalatest/flatspec/FixtureAnyFlatSpecLike;
            0      10     1 resultOfTaggedAsInvocation   Lorg/scalatest/verbs/ResultOfTaggedAsInvocation;
    MethodParameters:
      Name                           Flags
      resultOfTaggedAsInvocation     final

  public abstract org.scalatest.verbs.StringVerbStringInvocation shorthandTestRegistrationFunction();
    descriptor: ()Lorg/scalatest/verbs/StringVerbStringInvocation;
    flags: (0x0401) ACC_PUBLIC, ACC_ABSTRACT

  public abstract org.scalatest.verbs.StringVerbBehaveLikeInvocation shorthandSharedTestRegistrationFunction();
    descriptor: ()Lorg/scalatest/verbs/StringVerbBehaveLikeInvocation;
    flags: (0x0401) ACC_PUBLIC, ACC_ABSTRACT

  public static void org$scalatest$flatspec$FixtureAnyFlatSpecLike$$registerTestToIgnore$(org.scalatest.flatspec.FixtureAnyFlatSpecLike, java.lang.String, scala.collection.immutable.List, java.lang.String, scala.Function1, org.scalactic.source.Position);
    descriptor: (Lorg/scalatest/flatspec/FixtureAnyFlatSpecLike;Ljava/lang/String;Lscala/collection/immutable/List;Ljava/lang/String;Lscala/Function1;Lorg/scalactic/source/Position;)V
    flags: (0x1009) ACC_PUBLIC, ACC_STATIC, ACC_SYNTHETIC
    Code:
      stack=6, locals=6, args_size=6
         0: aload_0
         1: aload_1
         2: aload_2
         3: aload_3
         4: aload         4
         6: aload         5
         8: invokespecial #330                // InterfaceMethod org$scalatest$flatspec$FixtureAnyFlatSpecLike$$registerTestToIgnore:(Ljava/lang/String;Lscala/collection/immutable/List;Ljava/lang/String;Lscala/Function1;Lorg/scalactic/source/Position;)V
        11: return
      LineNumberTable:
        line 2333: 0
      LocalVariableTable:
        Start  Length  Slot  Name   Signature
            0      12     0 $this   Lorg/scalatest/flatspec/FixtureAnyFlatSpecLike;
            0      12     1 specText   Ljava/lang/String;
            0      12     2 testTags   Lscala/collection/immutable/List;
            0      12     3 methodName   Ljava/lang/String;
            0      12     4 testFun   Lscala/Function1;
            0      12     5   pos   Lorg/scalactic/source/Position;
    MethodParameters:
      Name                           Flags
      $this                          final synthetic
      specText                       final
      testTags                       final
      methodName                     final
      testFun                        final
      pos                            final

  public default void org$scalatest$flatspec$FixtureAnyFlatSpecLike$$registerTestToIgnore(java.lang.String, scala.collection.immutable.List<org.scalatest.Tag>, java.lang.String, scala.Function1<java.lang.Object, java.lang.Object>, org.scalactic.source.Position);
    descriptor: (Ljava/lang/String;Lscala/collection/immutable/List;Ljava/lang/String;Lscala/Function1;Lorg/scalactic/source/Position;)V
    flags: (0x0001) ACC_PUBLIC
    Code:
      stack=12, locals=8, args_size=6
         0: iconst_4
         1: istore        6
         3: bipush        -4
         5: istore        7
         7: aload_0
         8: invokeinterface #136,  1          // InterfaceMethod org$scalatest$flatspec$FixtureAnyFlatSpecLike$$engine:()Lorg/scalatest/FixtureEngine;
        13: aload_1
        14: new           #193                // class org/scalatest/fixture/Transformer
        17: dup
        18: aload         4
        20: invokespecial #197                // Method org/scalatest/fixture/Transformer."<init>":(Lscala/Function1;)V
        23: invokedynamic #335,  0            // InvokeDynamic #4:apply:()Lscala/Function0;
        28: aload_0
        29: invokeinterface #281,  1          // InterfaceMethod sourceFileName:()Ljava/lang/String;
        34: aload_3
        35: iload         6
        37: iload         7
        39: getstatic     #225                // Field scala/None$.MODULE$:Lscala/None$;
        42: new           #227                // class scala/Some
        45: dup
        46: aload         5
        48: invokespecial #230                // Method scala/Some."<init>":(Ljava/lang/Object;)V
        51: aload_2
        52: invokevirtual #256                // Method org/scalatest/FixtureEngine.registerIgnoredTest:(Ljava/lang/String;Ljava/lang/Object;Lscala/Function0;Ljava/lang/String;Ljava/lang/String;IILscala/Option;Lscala/Option;Lscala/collection/immutable/Seq;)V
        55: return
      LineNumberTable:
        line 2335: 0
        line 2336: 3
        line 2340: 7
      LocalVariableTable:
        Start  Length  Slot  Name   Signature
            3      52     6 stackDepth   I
            7      48     7 stackDepthAdjustment   I
            0      56     0  this   Lorg/scalatest/flatspec/FixtureAnyFlatSpecLike;
            0      56     1 specText   Ljava/lang/String;
            0      56     2 testTags   Lscala/collection/immutable/List;
            0      56     3 methodName   Ljava/lang/String;
            0      56     4 testFun   Lscala/Function1;
            0      56     5   pos   Lorg/scalactic/source/Position;
    Signature: #271                         // (Ljava/lang/String;Lscala/collection/immutable/List<Lorg/scalatest/Tag;>;Ljava/lang/String;Lscala/Function1<Ljava/lang/Object;Ljava/lang/Object;>;Lorg/scalactic/source/Position;)V
    MethodParameters:
      Name                           Flags
      specText                       final
      testTags                       final
      methodName                     final
      testFun                        final
      pos                            final

  public static void org$scalatest$flatspec$FixtureAnyFlatSpecLike$$registerPendingTestToIgnore$(org.scalatest.flatspec.FixtureAnyFlatSpecLike, java.lang.String, scala.collection.immutable.List, java.lang.String, scala.Function1, org.scalactic.source.Position);
    descriptor: (Lorg/scalatest/flatspec/FixtureAnyFlatSpecLike;Ljava/lang/String;Lscala/collection/immutable/List;Ljava/lang/String;Lscala/Function1;Lorg/scalactic/source/Position;)V
    flags: (0x1009) ACC_PUBLIC, ACC_STATIC, ACC_SYNTHETIC
    Code:
      stack=6, locals=6, args_size=6
         0: aload_0
         1: aload_1
         2: aload_2
         3: aload_3
         4: aload         4
         6: aload         5
         8: invokespecial #339                // InterfaceMethod org$scalatest$flatspec$FixtureAnyFlatSpecLike$$registerPendingTestToIgnore:(Ljava/lang/String;Lscala/collection/immutable/List;Ljava/lang/String;Lscala/Function1;Lorg/scalactic/source/Position;)V
        11: return
      LineNumberTable:
        line 2343: 0
      LocalVariableTable:
        Start  Length  Slot  Name   Signature
            0      12     0 $this   Lorg/scalatest/flatspec/FixtureAnyFlatSpecLike;
            0      12     1 specText   Ljava/lang/String;
            0      12     2 testTags   Lscala/collection/immutable/List;
            0      12     3 methodName   Ljava/lang/String;
            0      12     4 testFun   Lscala/Function1;
            0      12     5   pos   Lorg/scalactic/source/Position;
    MethodParameters:
      Name                           Flags
      $this                          final synthetic
      specText                       final
      testTags                       final
      methodName                     final
      testFun                        final
      pos                            final

  public default void org$scalatest$flatspec$FixtureAnyFlatSpecLike$$registerPendingTestToIgnore(java.lang.String, scala.collection.immutable.List<org.scalatest.Tag>, java.lang.String, scala.Function1<java.lang.Object, org.scalatest.PendingStatement>, org.scalactic.source.Position);
    descriptor: (Ljava/lang/String;Lscala/collection/immutable/List;Ljava/lang/String;Lscala/Function1;Lorg/scalactic/source/Position;)V
    flags: (0x0001) ACC_PUBLIC
    Code:
      stack=12, locals=6, args_size=6
         0: aload_0
         1: invokeinterface #136,  1          // InterfaceMethod org$scalatest$flatspec$FixtureAnyFlatSpecLike$$engine:()Lorg/scalatest/FixtureEngine;
         6: aload_1
         7: new           #193                // class org/scalatest/fixture/Transformer
        10: dup
        11: aload         4
        13: invokespecial #197                // Method org/scalatest/fixture/Transformer."<init>":(Lscala/Function1;)V
        16: invokedynamic #344,  0            // InvokeDynamic #5:apply:()Lscala/Function0;
        21: aload_0
        22: invokeinterface #281,  1          // InterfaceMethod sourceFileName:()Ljava/lang/String;
        27: aload_3
        28: iconst_4
        29: bipush        -4
        31: getstatic     #225                // Field scala/None$.MODULE$:Lscala/None$;
        34: new           #227                // class scala/Some
        37: dup
        38: aload         5
        40: invokespecial #230                // Method scala/Some."<init>":(Ljava/lang/Object;)V
        43: aload_2
        44: invokevirtual #256                // Method org/scalatest/FixtureEngine.registerIgnoredTest:(Ljava/lang/String;Ljava/lang/Object;Lscala/Function0;Ljava/lang/String;Ljava/lang/String;IILscala/Option;Lscala/Option;Lscala/collection/immutable/Seq;)V
        47: return
      LineNumberTable:
        line 2344: 0
      LocalVariableTable:
        Start  Length  Slot  Name   Signature
            0      48     0  this   Lorg/scalatest/flatspec/FixtureAnyFlatSpecLike;
            0      48     1 specText   Ljava/lang/String;
            0      48     2 testTags   Lscala/collection/immutable/List;
            0      48     3 methodName   Ljava/lang/String;
            0      48     4 testFun   Lscala/Function1;
            0      48     5   pos   Lorg/scalactic/source/Position;
    Signature: #287                         // (Ljava/lang/String;Lscala/collection/immutable/List<Lorg/scalatest/Tag;>;Ljava/lang/String;Lscala/Function1<Ljava/lang/Object;Lorg/scalatest/PendingStatement;>;Lorg/scalactic/source/Position;)V
    MethodParameters:
      Name                           Flags
      specText                       final
      testTags                       final
      methodName                     final
      testFun                        final
      pos                            final

  public static scala.collection.immutable.Map tags$(org.scalatest.flatspec.FixtureAnyFlatSpecLike);
    descriptor: (Lorg/scalatest/flatspec/FixtureAnyFlatSpecLike;)Lscala/collection/immutable/Map;
    flags: (0x1009) ACC_PUBLIC, ACC_STATIC, ACC_SYNTHETIC
    Code:
      stack=1, locals=1, args_size=1
         0: aload_0
         1: invokespecial #350                // InterfaceMethod tags:()Lscala/collection/immutable/Map;
         4: areturn
      LineNumberTable:
        line 2361: 0
      LocalVariableTable:
        Start  Length  Slot  Name   Signature
            0       5     0 $this   Lorg/scalatest/flatspec/FixtureAnyFlatSpecLike;
    MethodParameters:
      Name                           Flags
      $this                          final synthetic

  public default scala.collection.immutable.Map<java.lang.String, scala.collection.immutable.Set<java.lang.String>> tags();
    descriptor: ()Lscala/collection/immutable/Map;
    flags: (0x0001) ACC_PUBLIC
    Code:
      stack=3, locals=1, args_size=1
         0: getstatic     #356                // Field org/scalatest/Suite$.MODULE$:Lorg/scalatest/Suite$;
         3: aload_0
         4: invokeinterface #136,  1          // InterfaceMethod org$scalatest$flatspec$FixtureAnyFlatSpecLike$$engine:()Lorg/scalatest/FixtureEngine;
         9: invokevirtual #359                // Method org/scalatest/FixtureEngine.atomic:()Ljava/util/concurrent/atomic/AtomicReference;
        12: invokevirtual #148                // Method java/util/concurrent/atomic/AtomicReference.get:()Ljava/lang/Object;
        15: checkcast     #45                 // class org/scalatest/SuperEngine$Bundle
        18: invokevirtual #362                // Method org/scalatest/SuperEngine$Bundle.tagsMap:()Lscala/collection/immutable/Map;
        21: aload_0
        22: invokevirtual #366                // Method org/scalatest/Suite$.autoTagClassAnnotations:(Lscala/collection/immutable/Map;Lorg/scalatest/Suite;)Lscala/collection/immutable/Map;
        25: areturn
      LineNumberTable:
        line 2361: 0
      LocalVariableTable:
        Start  Length  Slot  Name   Signature
            0      26     0  this   Lorg/scalatest/flatspec/FixtureAnyFlatSpecLike;
    Signature: #351                         // ()Lscala/collection/immutable/Map<Ljava/lang/String;Lscala/collection/immutable/Set<Ljava/lang/String;>;>;

  public static org.scalatest.Status runTest$(org.scalatest.flatspec.FixtureAnyFlatSpecLike, java.lang.String, org.scalatest.Args);
    descriptor: (Lorg/scalatest/flatspec/FixtureAnyFlatSpecLike;Ljava/lang/String;Lorg/scalatest/Args;)Lorg/scalatest/Status;
    flags: (0x1009) ACC_PUBLIC, ACC_STATIC, ACC_SYNTHETIC
    Code:
      stack=3, locals=3, args_size=3
         0: aload_0
         1: aload_1
         2: aload_2
         3: invokespecial #372                // InterfaceMethod runTest:(Ljava/lang/String;Lorg/scalatest/Args;)Lorg/scalatest/Status;
         6: areturn
      LineNumberTable:
        line 2374: 0
      LocalVariableTable:
        Start  Length  Slot  Name   Signature
            0       7     0 $this   Lorg/scalatest/flatspec/FixtureAnyFlatSpecLike;
            0       7     1 testName   Ljava/lang/String;
            0       7     2  args   Lorg/scalatest/Args;
    MethodParameters:
      Name                           Flags
      $this                          final synthetic
      testName                       final
      args                           final

  public default org.scalatest.Status runTest(java.lang.String, org.scalatest.Args);
    descriptor: (Ljava/lang/String;Lorg/scalatest/Args;)Lorg/scalatest/Status;
    flags: (0x0001) ACC_PUBLIC
    Code:
      stack=8, locals=3, args_size=3
         0: aload_0
         1: invokeinterface #136,  1          // InterfaceMethod org$scalatest$flatspec$FixtureAnyFlatSpecLike$$engine:()Lorg/scalatest/FixtureEngine;
         6: aload_0
         7: aload_1
         8: aload_2
         9: iconst_1
        10: aload_0
        11: aload_1
        12: aload_2
        13: invokedynamic #385,  0            // InvokeDynamic #6:apply:(Lorg/scalatest/flatspec/FixtureAnyFlatSpecLike;Ljava/lang/String;Lorg/scalatest/Args;)Lscala/Function1;
        18: invokevirtual #389                // Method org/scalatest/FixtureEngine.runTestImpl:(Lorg/scalatest/Suite;Ljava/lang/String;Lorg/scalatest/Args;ZLscala/Function1;)Lorg/scalatest/Status;
        21: areturn
      LineNumberTable:
        line 2393: 0
      LocalVariableTable:
        Start  Length  Slot  Name   Signature
            0      22     0  this   Lorg/scalatest/flatspec/FixtureAnyFlatSpecLike;
            0      22     1 testName   Ljava/lang/String;
            0      22     2  args   Lorg/scalatest/Args;
    MethodParameters:
      Name                           Flags
      testName                       final
      args                           final

  public static org.scalatest.Status runTests$(org.scalatest.flatspec.FixtureAnyFlatSpecLike, scala.Option, org.scalatest.Args);
    descriptor: (Lorg/scalatest/flatspec/FixtureAnyFlatSpecLike;Lscala/Option;Lorg/scalatest/Args;)Lorg/scalatest/Status;
    flags: (0x1009) ACC_PUBLIC, ACC_STATIC, ACC_SYNTHETIC
    Code:
      stack=3, locals=3, args_size=3
         0: aload_0
         1: aload_1
         2: aload_2
         3: invokespecial #394                // InterfaceMethod runTests:(Lscala/Option;Lorg/scalatest/Args;)Lorg/scalatest/Status;
         6: areturn
      LineNumberTable:
        line 2435: 0
      LocalVariableTable:
        Start  Length  Slot  Name   Signature
            0       7     0 $this   Lorg/scalatest/flatspec/FixtureAnyFlatSpecLike;
            0       7     1 testName   Lscala/Option;
            0       7     2  args   Lorg/scalatest/Args;
    MethodParameters:
      Name                           Flags
      $this                          final synthetic
      testName                       final
      args                           final

  public default org.scalatest.Status runTests(scala.Option<java.lang.String>, org.scalatest.Args);
    descriptor: (Lscala/Option;Lorg/scalatest/Args;)Lorg/scalatest/Status;
    flags: (0x0001) ACC_PUBLIC
    Code:
      stack=7, locals=3, args_size=3
         0: aload_0
         1: invokeinterface #136,  1          // InterfaceMethod org$scalatest$flatspec$FixtureAnyFlatSpecLike$$engine:()Lorg/scalatest/FixtureEngine;
         6: aload_0
         7: aload_1
         8: aload_2
         9: aload_0
        10: invokeinterface #133,  1          // InterfaceMethod info:()Lorg/scalatest/Informer;
        15: iconst_1
        16: aload_0
        17: invokedynamic #406,  0            // InvokeDynamic #7:apply:(Lorg/scalatest/flatspec/FixtureAnyFlatSpecLike;)Lscala/Function2;
        22: invokevirtual #410                // Method org/scalatest/FixtureEngine.runTestsImpl:(Lorg/scalatest/Suite;Lscala/Option;Lorg/scalatest/Args;Lorg/scalatest/Informer;ZLscala/Function2;)Lorg/scalatest/Status;
        25: areturn
      LineNumberTable:
        line 2436: 0
      LocalVariableTable:
        Start  Length  Slot  Name   Signature
            0      26     0  this   Lorg/scalatest/flatspec/FixtureAnyFlatSpecLike;
            0      26     1 testName   Lscala/Option;
            0      26     2  args   Lorg/scalatest/Args;
    Signature: #396                         // (Lscala/Option<Ljava/lang/String;>;Lorg/scalatest/Args;)Lorg/scalatest/Status;
    MethodParameters:
      Name                           Flags
      testName                       final
      args                           final

  public static scala.collection.immutable.Set testNames$(org.scalatest.flatspec.FixtureAnyFlatSpecLike);
    descriptor: (Lorg/scalatest/flatspec/FixtureAnyFlatSpecLike;)Lscala/collection/immutable/Set;
    flags: (0x1009) ACC_PUBLIC, ACC_STATIC, ACC_SYNTHETIC
    Code:
      stack=1, locals=1, args_size=1
         0: aload_0
         1: invokespecial #416                // InterfaceMethod testNames:()Lscala/collection/immutable/Set;
         4: areturn
      LineNumberTable:
        line 2452: 0
      LocalVariableTable:
        Start  Length  Slot  Name   Signature
            0       5     0 $this   Lorg/scalatest/flatspec/FixtureAnyFlatSpecLike;
    MethodParameters:
      Name                           Flags
      $this                          final synthetic

  public default scala.collection.immutable.Set<java.lang.String> testNames();
    descriptor: ()Lscala/collection/immutable/Set;
    flags: (0x0001) ACC_PUBLIC
    Code:
      stack=2, locals=1, args_size=1
         0: getstatic     #422                // Field org/scalatest/InsertionOrderSet$.MODULE$:Lorg/scalatest/InsertionOrderSet$;
         3: aload_0
         4: invokeinterface #136,  1          // InterfaceMethod org$scalatest$flatspec$FixtureAnyFlatSpecLike$$engine:()Lorg/scalatest/FixtureEngine;
         9: invokevirtual #359                // Method org/scalatest/FixtureEngine.atomic:()Ljava/util/concurrent/atomic/AtomicReference;
        12: invokevirtual #148                // Method java/util/concurrent/atomic/AtomicReference.get:()Ljava/lang/Object;
        15: checkcast     #45                 // class org/scalatest/SuperEngine$Bundle
        18: invokevirtual #426                // Method org/scalatest/SuperEngine$Bundle.testNamesList:()Lscala/collection/immutable/List;
        21: invokevirtual #429                // Method org/scalatest/InsertionOrderSet$.apply:(Lscala/collection/immutable/List;)Lscala/collection/immutable/Set;
        24: areturn
      LineNumberTable:
        line 2453: 0
      LocalVariableTable:
        Start  Length  Slot  Name   Signature
            0      25     0  this   Lorg/scalatest/flatspec/FixtureAnyFlatSpecLike;
    Signature: #417                         // ()Lscala/collection/immutable/Set<Ljava/lang/String;>;

  public static org.scalatest.Status run$(org.scalatest.flatspec.FixtureAnyFlatSpecLike, scala.Option, org.scalatest.Args);
    descriptor: (Lorg/scalatest/flatspec/FixtureAnyFlatSpecLike;Lscala/Option;Lorg/scalatest/Args;)Lorg/scalatest/Status;
    flags: (0x1009) ACC_PUBLIC, ACC_STATIC, ACC_SYNTHETIC
    Code:
      stack=3, locals=3, args_size=3
         0: aload_0
         1: aload_1
         2: aload_2
         3: invokespecial #433                // InterfaceMethod run:(Lscala/Option;Lorg/scalatest/Args;)Lorg/scalatest/Status;
         6: areturn
      LineNumberTable:
        line 2456: 0
      LocalVariableTable:
        Start  Length  Slot  Name   Signature
            0       7     0 $this   Lorg/scalatest/flatspec/FixtureAnyFlatSpecLike;
            0       7     1 testName   Lscala/Option;
            0       7     2  args   Lorg/scalatest/Args;
    MethodParameters:
      Name                           Flags
      $this                          final synthetic
      testName                       final
      args                           final

  public default org.scalatest.Status run(scala.Option<java.lang.String>, org.scalatest.Args);
    descriptor: (Lscala/Option;Lorg/scalatest/Args;)Lorg/scalatest/Status;
    flags: (0x0001) ACC_PUBLIC
    Code:
      stack=5, locals=3, args_size=3
         0: aload_0
         1: invokeinterface #136,  1          // InterfaceMethod org$scalatest$flatspec$FixtureAnyFlatSpecLike$$engine:()Lorg/scalatest/FixtureEngine;
         6: aload_0
         7: aload_1
         8: aload_2
         9: aload_0
        10: invokedynamic #439,  0            // InvokeDynamic #8:apply:(Lorg/scalatest/flatspec/FixtureAnyFlatSpecLike;)Lscala/Function2;
        15: invokevirtual #443                // Method org/scalatest/FixtureEngine.runImpl:(Lorg/scalatest/Suite;Lscala/Option;Lorg/scalatest/Args;Lscala/Function2;)Lorg/scalatest/Status;
        18: areturn
      LineNumberTable:
        line 2457: 0
      LocalVariableTable:
        Start  Length  Slot  Name   Signature
            0      19     0  this   Lorg/scalatest/flatspec/FixtureAnyFlatSpecLike;
            0      19     1 testName   Lscala/Option;
            0      19     2  args   Lorg/scalatest/Args;
    Signature: #396                         // (Lscala/Option<Ljava/lang/String;>;Lorg/scalatest/Args;)Lorg/scalatest/Status;
    MethodParameters:
      Name                           Flags
      testName                       final
      args                           final

  public abstract org.scalatest.verbs.BehaveWord behave();
    descriptor: ()Lorg/scalatest/verbs/BehaveWord;
    flags: (0x0401) ACC_PUBLIC, ACC_ABSTRACT

  public abstract java.lang.String styleName();
    descriptor: ()Ljava/lang/String;
    flags: (0x0401) ACC_PUBLIC, ACC_ABSTRACT
    Deprecated: true

  public static org.scalatest.TestData testDataFor$(org.scalatest.flatspec.FixtureAnyFlatSpecLike, java.lang.String, org.scalatest.ConfigMap);
    descriptor: (Lorg/scalatest/flatspec/FixtureAnyFlatSpecLike;Ljava/lang/String;Lorg/scalatest/ConfigMap;)Lorg/scalatest/TestData;
    flags: (0x1009) ACC_PUBLIC, ACC_STATIC, ACC_SYNTHETIC
    Code:
      stack=3, locals=3, args_size=3
         0: aload_0
         1: aload_1
         2: aload_2
         3: invokespecial #453                // InterfaceMethod testDataFor:(Ljava/lang/String;Lorg/scalatest/ConfigMap;)Lorg/scalatest/TestData;
         6: areturn
      LineNumberTable:
        line 2488: 0
      LocalVariableTable:
        Start  Length  Slot  Name   Signature
            0       7     0 $this   Lorg/scalatest/flatspec/FixtureAnyFlatSpecLike;
            0       7     1 testName   Ljava/lang/String;
            0       7     2 theConfigMap   Lorg/scalatest/ConfigMap;
    MethodParameters:
      Name                           Flags
      $this                          final synthetic
      testName                       final
      theConfigMap                   final

  public default org.scalatest.TestData testDataFor(java.lang.String, org.scalatest.ConfigMap);
    descriptor: (Ljava/lang/String;Lorg/scalatest/ConfigMap;)Lorg/scalatest/TestData;
    flags: (0x0001) ACC_PUBLIC
    Code:
      stack=4, locals=3, args_size=3
         0: aload_0
         1: invokeinterface #136,  1          // InterfaceMethod org$scalatest$flatspec$FixtureAnyFlatSpecLike$$engine:()Lorg/scalatest/FixtureEngine;
         6: aload_1
         7: aload_2
         8: aload_0
         9: invokevirtual #458                // Method org/scalatest/FixtureEngine.createTestDataFor:(Ljava/lang/String;Lorg/scalatest/ConfigMap;Lorg/scalatest/Suite;)Lorg/scalatest/TestData;
        12: areturn
      LineNumberTable:
        line 2488: 0
      LocalVariableTable:
        Start  Length  Slot  Name   Signature
            0      13     0  this   Lorg/scalatest/flatspec/FixtureAnyFlatSpecLike;
            0      13     1 testName   Ljava/lang/String;
            0      13     2 theConfigMap   Lorg/scalatest/ConfigMap;
    MethodParameters:
      Name                           Flags
      testName                       final
      theConfigMap                   final

  public static org.scalatest.ConfigMap testDataFor$default$2$(org.scalatest.flatspec.FixtureAnyFlatSpecLike);
    descriptor: (Lorg/scalatest/flatspec/FixtureAnyFlatSpecLike;)Lorg/scalatest/ConfigMap;
    flags: (0x1009) ACC_PUBLIC, ACC_STATIC, ACC_SYNTHETIC
    Code:
      stack=1, locals=1, args_size=1
         0: aload_0
         1: invokespecial #464                // InterfaceMethod testDataFor$default$2:()Lorg/scalatest/ConfigMap;
         4: areturn
      LineNumberTable:
        line 2488: 0
      LocalVariableTable:
        Start  Length  Slot  Name   Signature
            0       5     0 $this   Lorg/scalatest/flatspec/FixtureAnyFlatSpecLike;
    MethodParameters:
      Name                           Flags
      $this                          final synthetic

  public default org.scalatest.ConfigMap testDataFor$default$2();
    descriptor: ()Lorg/scalatest/ConfigMap;
    flags: (0x0001) ACC_PUBLIC
    Code:
      stack=1, locals=1, args_size=1
         0: getstatic     #469                // Field org/scalatest/ConfigMap$.MODULE$:Lorg/scalatest/ConfigMap$;
         3: invokevirtual #472                // Method org/scalatest/ConfigMap$.empty:()Lorg/scalatest/ConfigMap;
         6: areturn
      LineNumberTable:
        line 2488: 0
      LocalVariableTable:
        Start  Length  Slot  Name   Signature
            0       7     0  this   Lorg/scalatest/flatspec/FixtureAnyFlatSpecLike;

  public static java.lang.String $anonfun$engine$1();
    descriptor: ()Ljava/lang/String;
    flags: (0x1009) ACC_PUBLIC, ACC_STATIC, ACC_SYNTHETIC
    Code:
      stack=1, locals=0, args_size=0
         0: getstatic     #478                // Field org/scalatest/Resources$.MODULE$:Lorg/scalatest/Resources$;
         3: invokevirtual #481                // Method org/scalatest/Resources$.concurrentFixtureFlatSpecMod:()Ljava/lang/String;
         6: areturn
      LineNumberTable:
        line 50: 0

  public static java.lang.String $anonfun$registerTestImpl$1();
    descriptor: ()Ljava/lang/String;
    flags: (0x1009) ACC_PUBLIC, ACC_STATIC, ACC_SYNTHETIC
    Code:
      stack=1, locals=0, args_size=0
         0: getstatic     #478                // Field org/scalatest/Resources$.MODULE$:Lorg/scalatest/Resources$;
         3: invokevirtual #484                // Method org/scalatest/Resources$.testCannotBeNestedInsideAnotherTest:()Ljava/lang/String;
         6: areturn
      LineNumberTable:
        line 103: 0

  public static java.lang.String $anonfun$registerIgnoredTestImpl$1();
    descriptor: ()Ljava/lang/String;
    flags: (0x1009) ACC_PUBLIC, ACC_STATIC, ACC_SYNTHETIC
    Code:
      stack=1, locals=0, args_size=0
         0: getstatic     #478                // Field org/scalatest/Resources$.MODULE$:Lorg/scalatest/Resources$;
         3: invokevirtual #484                // Method org/scalatest/Resources$.testCannotBeNestedInsideAnotherTest:()Ljava/lang/String;
         6: areturn
      LineNumberTable:
        line 120: 0

  private static java.lang.String testRegistrationClosedMessageFun$1(java.lang.String);
    descriptor: (Ljava/lang/String;)Ljava/lang/String;
    flags: (0x000a) ACC_PRIVATE, ACC_STATIC
    Code:
      stack=3, locals=3, args_size=1
         0: aload_0
         1: astore_2
         2: aload_2
         3: ifnonnull     10
         6: iconst_0
         7: goto          14
        10: aload_2
        11: invokevirtual #492                // Method java/lang/String.hashCode:()I
        14: lookupswitch  { // 2
                    3365: 40
                    3370: 63
                 default: 86
            }
        40: ldc_w         #494                // String in
        43: aload_2
        44: invokevirtual #498                // Method java/lang/String.equals:(Ljava/lang/Object;)Z
        47: ifeq          60
        50: getstatic     #478                // Field org/scalatest/Resources$.MODULE$:Lorg/scalatest/Resources$;
        53: invokevirtual #501                // Method org/scalatest/Resources$.inCannotAppearInsideAnotherInOrIs:()Ljava/lang/String;
        56: astore_1
        57: goto          98
        60: goto          89
        63: ldc_w         #503                // String is
        66: aload_2
        67: invokevirtual #498                // Method java/lang/String.equals:(Ljava/lang/Object;)Z
        70: ifeq          83
        73: getstatic     #478                // Field org/scalatest/Resources$.MODULE$:Lorg/scalatest/Resources$;
        76: invokevirtual #506                // Method org/scalatest/Resources$.isCannotAppearInsideAnotherInOrIs:()Ljava/lang/String;
        79: astore_1
        80: goto          98
        83: goto          89
        86: goto          89
        89: new           #508                // class scala/MatchError
        92: dup
        93: aload_2
        94: invokespecial #509                // Method scala/MatchError."<init>":(Ljava/lang/Object;)V
        97: athrow
        98: aload_1
        99: areturn
      StackMapTable: number_of_entries = 9
        frame_type = 253 /* append */
          offset_delta = 10
          locals = [ top, class java/lang/String ]
        frame_type = 67 /* same_locals_1_stack_item */
          stack = [ int ]
        frame_type = 25 /* same */
        frame_type = 19 /* same */
        frame_type = 2 /* same */
        frame_type = 19 /* same */
        frame_type = 2 /* same */
        frame_type = 2 /* same */
        frame_type = 255 /* full_frame */
          offset_delta = 8
          locals = [ class java/lang/String, class java/lang/String, class java/lang/String ]
          stack = []
      LineNumberTable:
        line 162: 0
        line 163: 40
        line 162: 60
        line 164: 63
        line 162: 83
      LocalVariableTable:
        Start  Length  Slot  Name   Signature
            0     100     0 methodName$1   Ljava/lang/String;
    MethodParameters:
      Name                           Flags
      methodName$1                   final

  public static java.lang.String $anonfun$registerTestToRun$1(java.lang.String);
    descriptor: (Ljava/lang/String;)Ljava/lang/String;
    flags: (0x1009) ACC_PUBLIC, ACC_STATIC, ACC_SYNTHETIC
    Code:
      stack=1, locals=1, args_size=1
         0: aload_0
         1: invokestatic  #511                // InterfaceMethod testRegistrationClosedMessageFun$1:(Ljava/lang/String;)Ljava/lang/String;
         4: areturn
      LineNumberTable:
        line 166: 0
      LocalVariableTable:
        Start  Length  Slot  Name   Signature
            0       5     0 methodName$1   Ljava/lang/String;
    MethodParameters:
      Name                           Flags
      methodName$1                   final

  private static java.lang.String testRegistrationClosedMessageFun$2(java.lang.String);
    descriptor: (Ljava/lang/String;)Ljava/lang/String;
    flags: (0x000a) ACC_PRIVATE, ACC_STATIC
    Code:
      stack=3, locals=3, args_size=1
         0: aload_0
         1: astore_2
         2: aload_2
         3: ifnonnull     10
         6: iconst_0
         7: goto          14
        10: aload_2
        11: invokevirtual #492                // Method java/lang/String.hashCode:()I
        14: lookupswitch  { // 2
                    3365: 40
                    3370: 63
                 default: 86
            }
        40: ldc_w         #494                // String in
        43: aload_2
        44: invokevirtual #498                // Method java/lang/String.equals:(Ljava/lang/Object;)Z
        47: ifeq          60
        50: getstatic     #478                // Field org/scalatest/Resources$.MODULE$:Lorg/scalatest/Resources$;
        53: invokevirtual #501                // Method org/scalatest/Resources$.inCannotAppearInsideAnotherInOrIs:()Ljava/lang/String;
        56: astore_1
        57: goto          98
        60: goto          89
        63: ldc_w         #503                // String is
        66: aload_2
        67: invokevirtual #498                // Method java/lang/String.equals:(Ljava/lang/Object;)Z
        70: ifeq          83
        73: getstatic     #478                // Field org/scalatest/Resources$.MODULE$:Lorg/scalatest/Resources$;
        76: invokevirtual #506                // Method org/scalatest/Resources$.isCannotAppearInsideAnotherInOrIs:()Ljava/lang/String;
        79: astore_1
        80: goto          98
        83: goto          89
        86: goto          89
        89: new           #508                // class scala/MatchError
        92: dup
        93: aload_2
        94: invokespecial #509                // Method scala/MatchError."<init>":(Ljava/lang/Object;)V
        97: athrow
        98: aload_1
        99: areturn
      StackMapTable: number_of_entries = 9
        frame_type = 253 /* append */
          offset_delta = 10
          locals = [ top, class java/lang/String ]
        frame_type = 67 /* same_locals_1_stack_item */
          stack = [ int ]
        frame_type = 25 /* same */
        frame_type = 19 /* same */
        frame_type = 2 /* same */
        frame_type = 19 /* same */
        frame_type = 2 /* same */
        frame_type = 2 /* same */
        frame_type = 255 /* full_frame */
          offset_delta = 8
          locals = [ class java/lang/String, class java/lang/String, class java/lang/String ]
          stack = []
      LineNumberTable:
        line 172: 0
        line 173: 40
        line 172: 60
        line 174: 63
        line 172: 83
      LocalVariableTable:
        Start  Length  Slot  Name   Signature
            0     100     0 methodName$2   Ljava/lang/String;
    MethodParameters:
      Name                           Flags
      methodName$2                   final

  public static java.lang.String $anonfun$registerPendingTestToRun$1(java.lang.String);
    descriptor: (Ljava/lang/String;)Ljava/lang/String;
    flags: (0x1009) ACC_PUBLIC, ACC_STATIC, ACC_SYNTHETIC
    Code:
      stack=1, locals=1, args_size=1
         0: aload_0
         1: invokestatic  #515                // InterfaceMethod testRegistrationClosedMessageFun$2:(Ljava/lang/String;)Ljava/lang/String;
         4: areturn
      LineNumberTable:
        line 176: 0
      LocalVariableTable:
        Start  Length  Slot  Name   Signature
            0       5     0 methodName$2   Ljava/lang/String;
    MethodParameters:
      Name                           Flags
      methodName$2                   final

  public static java.lang.String $anonfun$registerTestToIgnore$1();
    descriptor: ()Ljava/lang/String;
    flags: (0x1009) ACC_PUBLIC, ACC_STATIC, ACC_SYNTHETIC
    Code:
      stack=1, locals=0, args_size=0
         0: getstatic     #478                // Field org/scalatest/Resources$.MODULE$:Lorg/scalatest/Resources$;
         3: invokevirtual #518                // Method org/scalatest/Resources$.ignoreCannotAppearInsideAnInOrAnIs:()Ljava/lang/String;
         6: areturn
      LineNumberTable:
        line 2340: 0

  public static java.lang.String $anonfun$registerPendingTestToIgnore$1();
    descriptor: ()Ljava/lang/String;
    flags: (0x1009) ACC_PUBLIC, ACC_STATIC, ACC_SYNTHETIC
    Code:
      stack=1, locals=0, args_size=0
         0: getstatic     #478                // Field org/scalatest/Resources$.MODULE$:Lorg/scalatest/Resources$;
         3: invokevirtual #518                // Method org/scalatest/Resources$.ignoreCannotAppearInsideAnInOrAnIs:()Ljava/lang/String;
         6: areturn
      LineNumberTable:
        line 2344: 0

  private org.scalatest.Outcome invokeWithFixture$1(org.scalatest.SuperEngine$TestLeaf, java.lang.String, org.scalatest.Args);
    descriptor: (Lorg/scalatest/SuperEngine$TestLeaf;Ljava/lang/String;Lorg/scalatest/Args;)Lorg/scalatest/Outcome;
    flags: (0x0002) ACC_PRIVATE
    Code:
      stack=7, locals=13, args_size=4
         0: aload_1
         1: invokevirtual #525                // Method org/scalatest/SuperEngine$TestLeaf.testFun:()Ljava/lang/Object;
         4: checkcast     #527                // class scala/Function1
         7: astore        7
         9: aload         7
        11: instanceof    #193                // class org/scalatest/fixture/Transformer
        14: ifeq          111
        17: aload         7
        19: checkcast     #193                // class org/scalatest/fixture/Transformer
        22: astore        8
        24: aload         8
        26: invokevirtual #531                // Method org/scalatest/fixture/Transformer.exceptionalTestFun:()Lscala/Function1;
        29: astore        9
        31: aload         9
        33: instanceof    #533                // class org/scalatest/fixture/NoArgTestWrapper
        36: ifeq          75
        39: aload         9
        41: checkcast     #533                // class org/scalatest/fixture/NoArgTestWrapper
        44: astore        10
        46: aload_0
        47: new           #36                 // class org/scalatest/FixtureTestSuite$FixturelessTestFunAndConfigMap
        50: dup
        51: aload_0
        52: aload_2
        53: aload         10
        55: invokevirtual #536                // Method org/scalatest/fixture/NoArgTestWrapper.test:()Lscala/Function0;
        58: aload_3
        59: invokevirtual #541                // Method org/scalatest/Args.configMap:()Lorg/scalatest/ConfigMap;
        62: invokespecial #544                // Method org/scalatest/FixtureTestSuite$FixturelessTestFunAndConfigMap."<init>":(Lorg/scalatest/FixtureTestSuite;Ljava/lang/String;Lscala/Function0;Lorg/scalatest/ConfigMap;)V
        65: invokeinterface #548,  2          // InterfaceMethod withFixture:(Lorg/scalatest/TestSuite$NoArgTest;)Lorg/scalatest/Outcome;
        70: astore        6
        72: goto          104
        75: goto          78
        78: aload_0
        79: new           #42                 // class org/scalatest/FixtureTestSuite$TestFunAndConfigMap
        82: dup
        83: aload_0
        84: aload_2
        85: aload         9
        87: aload_3
        88: invokevirtual #541                // Method org/scalatest/Args.configMap:()Lorg/scalatest/ConfigMap;
        91: invokespecial #551                // Method org/scalatest/FixtureTestSuite$TestFunAndConfigMap."<init>":(Lorg/scalatest/FixtureTestSuite;Ljava/lang/String;Lscala/Function1;Lorg/scalatest/ConfigMap;)V
        94: invokeinterface #554,  2          // InterfaceMethod withFixture:(Lorg/scalatest/FixtureTestSuite$OneArgTest;)Lorg/scalatest/Outcome;
        99: astore        6
       101: goto          104
       104: aload         6
       106: astore        4
       108: goto          198
       111: goto          114
       114: aload         7
       116: astore        11
       118: aload         11
       120: instanceof    #533                // class org/scalatest/fixture/NoArgTestWrapper
       123: ifeq          162
       126: aload         11
       128: checkcast     #533                // class org/scalatest/fixture/NoArgTestWrapper
       131: astore        12
       133: aload_0
       134: new           #36                 // class org/scalatest/FixtureTestSuite$FixturelessTestFunAndConfigMap
       137: dup
       138: aload_0
       139: aload_2
       140: aload         12
       142: invokevirtual #536                // Method org/scalatest/fixture/NoArgTestWrapper.test:()Lscala/Function0;
       145: aload_3
       146: invokevirtual #541                // Method org/scalatest/Args.configMap:()Lorg/scalatest/ConfigMap;
       149: invokespecial #544                // Method org/scalatest/FixtureTestSuite$FixturelessTestFunAndConfigMap."<init>":(Lorg/scalatest/FixtureTestSuite;Ljava/lang/String;Lscala/Function0;Lorg/scalatest/ConfigMap;)V
       152: invokeinterface #548,  2          // InterfaceMethod withFixture:(Lorg/scalatest/TestSuite$NoArgTest;)Lorg/scalatest/Outcome;
       157: astore        5
       159: goto          191
       162: goto          165
       165: aload_0
       166: new           #42                 // class org/scalatest/FixtureTestSuite$TestFunAndConfigMap
       169: dup
       170: aload_0
       171: aload_2
       172: aload         11
       174: aload_3
       175: invokevirtual #541                // Method org/scalatest/Args.configMap:()Lorg/scalatest/ConfigMap;
       178: invokespecial #551                // Method org/scalatest/FixtureTestSuite$TestFunAndConfigMap."<init>":(Lorg/scalatest/FixtureTestSuite;Ljava/lang/String;Lscala/Function1;Lorg/scalatest/ConfigMap;)V
       181: invokeinterface #554,  2          // InterfaceMethod withFixture:(Lorg/scalatest/FixtureTestSuite$OneArgTest;)Lorg/scalatest/Outcome;
       186: astore        5
       188: goto          191
       191: aload         5
       193: astore        4
       195: goto          198
       198: aload         4
       200: areturn
      StackMapTable: number_of_entries = 9
        frame_type = 255 /* full_frame */
          offset_delta = 75
          locals = [ class org/scalatest/flatspec/FixtureAnyFlatSpecLike, class org/scalatest/SuperEngine$TestLeaf, class java/lang/String, class org/scalatest/Args, top, top, top, class scala/Function1, class org/scalatest/fixture/Transformer, class scala/Function1 ]
          stack = []
        frame_type = 2 /* same */
        frame_type = 255 /* full_frame */
          offset_delta = 25
          locals = [ class org/scalatest/flatspec/FixtureAnyFlatSpecLike, class org/scalatest/SuperEngine$TestLeaf, class java/lang/String, class org/scalatest/Args, top, top, class org/scalatest/Outcome, class scala/Function1, class org/scalatest/fixture/Transformer, class scala/Function1 ]
          stack = []
        frame_type = 255 /* full_frame */
          offset_delta = 6
          locals = [ class org/scalatest/flatspec/FixtureAnyFlatSpecLike, class org/scalatest/SuperEngine$TestLeaf, class java/lang/String, class org/scalatest/Args, top, top, top, class scala/Function1 ]
          stack = []
        frame_type = 2 /* same */
        frame_type = 255 /* full_frame */
          offset_delta = 47
          locals = [ class org/scalatest/flatspec/FixtureAnyFlatSpecLike, class org/scalatest/SuperEngine$TestLeaf, class java/lang/String, class org/scalatest/Args, top, top, top, class scala/Function1, top, top, top, class scala/Function1 ]
          stack = []
        frame_type = 2 /* same */
        frame_type = 255 /* full_frame */
          offset_delta = 25
          locals = [ class org/scalatest/flatspec/FixtureAnyFlatSpecLike, class org/scalatest/SuperEngine$TestLeaf, class java/lang/String, class org/scalatest/Args, top, class org/scalatest/Outcome, top, class scala/Function1, top, top, top, class scala/Function1 ]
          stack = []
        frame_type = 255 /* full_frame */
          offset_delta = 6
          locals = [ class org/scalatest/flatspec/FixtureAnyFlatSpecLike, class org/scalatest/SuperEngine$TestLeaf, class java/lang/String, class org/scalatest/Args, class org/scalatest/Outcome, top, top, class scala/Function1 ]
          stack = []
      LineNumberTable:
        line 2377: 0
        line 2378: 9
        line 2379: 24
        line 2380: 31
        line 2381: 46
        line 2380: 75
        line 2382: 78
        line 2379: 104
        line 2378: 111
        line 2385: 114
        line 2386: 118
        line 2387: 133
        line 2386: 162
        line 2388: 165
        line 2385: 191
        line 2377: 198
      LocalVariableTable:
        Start  Length  Slot  Name   Signature
            0     201     0  this   Lorg/scalatest/flatspec/FixtureAnyFlatSpecLike;
            0     201     1 theTest   Lorg/scalatest/SuperEngine$TestLeaf;
            0     201     2 testName$1   Ljava/lang/String;
            0     201     3 args$1   Lorg/scalatest/Args;
    MethodParameters:
      Name                           Flags
      theTest                        final
      testName$1                     final
      args$1                         final

  public static org.scalatest.Outcome $anonfun$runTest$1(org.scalatest.flatspec.FixtureAnyFlatSpecLike, java.lang.String, org.scalatest.Args, org.scalatest.SuperEngine$TestLeaf);
    descriptor: (Lorg/scalatest/flatspec/FixtureAnyFlatSpecLike;Ljava/lang/String;Lorg/scalatest/Args;Lorg/scalatest/SuperEngine$TestLeaf;)Lorg/scalatest/Outcome;
    flags: (0x1009) ACC_PUBLIC, ACC_STATIC, ACC_SYNTHETIC
    Code:
      stack=4, locals=4, args_size=4
         0: aload_0
         1: aload_3
         2: aload_1
         3: aload_2
         4: invokespecial #559                // InterfaceMethod invokeWithFixture$1:(Lorg/scalatest/SuperEngine$TestLeaf;Ljava/lang/String;Lorg/scalatest/Args;)Lorg/scalatest/Outcome;
         7: areturn
      LineNumberTable:
        line 2393: 0
      LocalVariableTable:
        Start  Length  Slot  Name   Signature
            0       8     0 $this   Lorg/scalatest/flatspec/FixtureAnyFlatSpecLike;
            0       8     1 testName$1   Ljava/lang/String;
            0       8     2 args$1   Lorg/scalatest/Args;
            0       8     3 theTest   Lorg/scalatest/SuperEngine$TestLeaf;
    MethodParameters:
      Name                           Flags
      $this                          final synthetic
      testName$1                     final
      args$1                         final
      theTest                        final

  public static org.scalatest.Status $anonfun$runTests$1(org.scalatest.flatspec.FixtureAnyFlatSpecLike, java.lang.String, org.scalatest.Args);
    descriptor: (Lorg/scalatest/flatspec/FixtureAnyFlatSpecLike;Ljava/lang/String;Lorg/scalatest/Args;)Lorg/scalatest/Status;
    flags: (0x1009) ACC_PUBLIC, ACC_STATIC, ACC_SYNTHETIC
    Code:
      stack=3, locals=3, args_size=3
         0: aload_0
         1: aload_1
         2: aload_2
         3: invokeinterface #372,  3          // InterfaceMethod runTest:(Ljava/lang/String;Lorg/scalatest/Args;)Lorg/scalatest/Status;
         8: areturn
      LineNumberTable:
        line 2436: 0
      LocalVariableTable:
        Start  Length  Slot  Name   Signature
            0       9     0 $this   Lorg/scalatest/flatspec/FixtureAnyFlatSpecLike;
            0       9     1 testName   Ljava/lang/String;
            0       9     2  args   Lorg/scalatest/Args;
    MethodParameters:
      Name                           Flags
      $this                          final synthetic
      testName                       final
      args                           final

  public static org.scalatest.Status $anonfun$run$1(org.scalatest.flatspec.FixtureAnyFlatSpecLike, scala.Option, org.scalatest.Args);
    descriptor: (Lorg/scalatest/flatspec/FixtureAnyFlatSpecLike;Lscala/Option;Lorg/scalatest/Args;)Lorg/scalatest/Status;
    flags: (0x1009) ACC_PUBLIC, ACC_STATIC, ACC_SYNTHETIC
    Code:
      stack=3, locals=3, args_size=3
         0: aload_0
         1: aload_1
         2: aload_2
         3: invokeinterface #561,  3          // InterfaceMethod org$scalatest$flatspec$FixtureAnyFlatSpecLike$$super$run:(Lscala/Option;Lorg/scalatest/Args;)Lorg/scalatest/Status;
         8: areturn
      LineNumberTable:
        line 2457: 0
      LocalVariableTable:
        Start  Length  Slot  Name   Signature
            0       9     0 $this   Lorg/scalatest/flatspec/FixtureAnyFlatSpecLike;
            0       9     1 testName   Lscala/Option;
            0       9     2  args   Lorg/scalatest/Args;
    MethodParameters:
      Name                           Flags
      $this                          final synthetic
      testName                       final
      args                           final

  public static void $init$(org.scalatest.flatspec.FixtureAnyFlatSpecLike);
    descriptor: (Lorg/scalatest/flatspec/FixtureAnyFlatSpecLike;)V
    flags: (0x0009) ACC_PUBLIC, ACC_STATIC
    Code:
      stack=5, locals=1, args_size=1
         0: aload_0
         1: new           #138                // class org/scalatest/FixtureEngine
         4: dup
         5: invokedynamic #567,  0            // InvokeDynamic #9:apply:()Lscala/Function0;
        10: ldc_w         #569                // String FixtureFlatSpec
        13: invokespecial #572                // Method org/scalatest/FixtureEngine."<init>":(Lscala/Function0;Ljava/lang/String;)V
        16: invokeinterface #574,  2          // InterfaceMethod org$scalatest$flatspec$FixtureAnyFlatSpecLike$_setter_$org$scalatest$flatspec$FixtureAnyFlatSpecLike$$engine_$eq:(Lorg/scalatest/FixtureEngine;)V
        21: aload_0
        22: ldc           #217                // String FixtureAnyFlatSpecLike.scala
        24: invokeinterface #576,  2          // InterfaceMethod org$scalatest$flatspec$FixtureAnyFlatSpecLike$_setter_$sourceFileName_$eq:(Ljava/lang/String;)V
        29: aload_0
        30: new           #62                 // class org/scalatest/flatspec/FixtureAnyFlatSpecLike$BehaviorWord
        33: dup
        34: aload_0
        35: invokespecial #578                // Method org/scalatest/flatspec/FixtureAnyFlatSpecLike$BehaviorWord."<init>":(Lorg/scalatest/flatspec/FixtureAnyFlatSpecLike;)V
        38: invokeinterface #580,  2          // InterfaceMethod org$scalatest$flatspec$FixtureAnyFlatSpecLike$_setter_$behavior_$eq:(Lorg/scalatest/flatspec/FixtureAnyFlatSpecLike$BehaviorWord;)V
        43: aload_0
        44: new           #86                 // class org/scalatest/flatspec/FixtureAnyFlatSpecLike$ItWord
        47: dup
        48: aload_0
        49: invokespecial #581                // Method org/scalatest/flatspec/FixtureAnyFlatSpecLike$ItWord."<init>":(Lorg/scalatest/flatspec/FixtureAnyFlatSpecLike;)V
        52: invokeinterface #583,  2          // InterfaceMethod org$scalatest$flatspec$FixtureAnyFlatSpecLike$_setter_$it_$eq:(Lorg/scalatest/flatspec/FixtureAnyFlatSpecLike$ItWord;)V
        57: aload_0
        58: new           #95                 // class org/scalatest/flatspec/FixtureAnyFlatSpecLike$TheyWord
        61: dup
        62: aload_0
        63: invokespecial #584                // Method org/scalatest/flatspec/FixtureAnyFlatSpecLike$TheyWord."<init>":(Lorg/scalatest/flatspec/FixtureAnyFlatSpecLike;)V
        66: invokeinterface #586,  2          // InterfaceMethod org$scalatest$flatspec$FixtureAnyFlatSpecLike$_setter_$they_$eq:(Lorg/scalatest/flatspec/FixtureAnyFlatSpecLike$TheyWord;)V
        71: aload_0
        72: new           #71                 // class org/scalatest/flatspec/FixtureAnyFlatSpecLike$IgnoreWord
        75: dup
        76: aload_0
        77: invokespecial #587                // Method org/scalatest/flatspec/FixtureAnyFlatSpecLike$IgnoreWord."<init>":(Lorg/scalatest/flatspec/FixtureAnyFlatSpecLike;)V
        80: invokeinterface #589,  2          // InterfaceMethod org$scalatest$flatspec$FixtureAnyFlatSpecLike$_setter_$ignore_$eq:(Lorg/scalatest/flatspec/FixtureAnyFlatSpecLike$IgnoreWord;)V
        85: aload_0
        86: new           #58                 // class org/scalatest/flatspec/FixtureAnyFlatSpecLike$$anon$1
        89: dup
        90: aload_0
        91: invokespecial #590                // Method org/scalatest/flatspec/FixtureAnyFlatSpecLike$$anon$1."<init>":(Lorg/scalatest/flatspec/FixtureAnyFlatSpecLike;)V
        94: invokeinterface #592,  2          // InterfaceMethod org$scalatest$flatspec$FixtureAnyFlatSpecLike$_setter_$shorthandTestRegistrationFunction_$eq:(Lorg/scalatest/verbs/StringVerbStringInvocation;)V
        99: aload_0
       100: new           #60                 // class org/scalatest/flatspec/FixtureAnyFlatSpecLike$$anon$4
       103: dup
       104: aload_0
       105: invokespecial #593                // Method org/scalatest/flatspec/FixtureAnyFlatSpecLike$$anon$4."<init>":(Lorg/scalatest/flatspec/FixtureAnyFlatSpecLike;)V
       108: invokeinterface #595,  2          // InterfaceMethod org$scalatest$flatspec$FixtureAnyFlatSpecLike$_setter_$shorthandSharedTestRegistrationFunction_$eq:(Lorg/scalatest/verbs/StringVerbBehaveLikeInvocation;)V
       113: aload_0
       114: new           #597                // class org/scalatest/verbs/BehaveWord
       117: dup
       118: invokespecial #600                // Method org/scalatest/verbs/BehaveWord."<init>":()V
       121: invokeinterface #602,  2          // InterfaceMethod org$scalatest$flatspec$FixtureAnyFlatSpecLike$_setter_$behave_$eq:(Lorg/scalatest/verbs/BehaveWord;)V
       126: aload_0
       127: ldc_w         #604                // String org.scalatest.fixture.FlatSpec
       130: invokeinterface #606,  2          // InterfaceMethod org$scalatest$flatspec$FixtureAnyFlatSpecLike$_setter_$styleName_$eq:(Ljava/lang/String;)V
       135: return
      LineNumberTable:
        line 50: 0
        line 54: 21
        line 254: 29
        line 857: 43
        line 1458: 57
        line 1874: 71
        line 2258: 85
        line 2259: 86
        line 2306: 99
        line 2307: 100
        line 2477: 113
        line 2486: 126
        line 48: 135
      LocalVariableTable:
        Start  Length  Slot  Name   Signature
            0     136     0 $this   Lorg/scalatest/flatspec/FixtureAnyFlatSpecLike;
    MethodParameters:
      Name                           Flags
      $this                          final synthetic

  private static java.lang.Object $deserializeLambda$(java.lang.invoke.SerializedLambda);
    descriptor: (Ljava/lang/invoke/SerializedLambda;)Ljava/lang/Object;
    flags: (0x100a) ACC_PRIVATE, ACC_STATIC, ACC_SYNTHETIC
    Code:
      stack=1, locals=1, args_size=1
         0: aload_0
         1: invokedynamic #618,  0            // InvokeDynamic #10:lambdaDeserialize:(Ljava/lang/invoke/SerializedLambda;)Ljava/lang/Object;
         6: areturn
}
InnerClasses:
  public static final #34= #31 of #33;    // Lookup=class java/lang/invoke/MethodHandles$Lookup of class java/lang/invoke/MethodHandles
  public #37= #36 of #6;                  // FixturelessTestFunAndConfigMap=class org/scalatest/FixtureTestSuite$FixturelessTestFunAndConfigMap of class org/scalatest/FixtureTestSuite
  public #40= #39 of #6;                  // OneArgTest=class org/scalatest/FixtureTestSuite$OneArgTest of class org/scalatest/FixtureTestSuite
  public #43= #42 of #6;                  // TestFunAndConfigMap=class org/scalatest/FixtureTestSuite$TestFunAndConfigMap of class org/scalatest/FixtureTestSuite
  public #48= #45 of #47;                 // Bundle=class org/scalatest/SuperEngine$Bundle of class org/scalatest/SuperEngine
  public #51= #50 of #47;                 // TestLeaf=class org/scalatest/SuperEngine$TestLeaf of class org/scalatest/SuperEngine
  public #56= #53 of #55;                 // NoArgTest=class org/scalatest/TestSuite$NoArgTest of class org/scalatest/TestSuite
  public final #58;                       // class org/scalatest/flatspec/FixtureAnyFlatSpecLike$$anon$1
  public final #60;                       // class org/scalatest/flatspec/FixtureAnyFlatSpecLike$$anon$4
  public final #63= #62 of #2;            // BehaviorWord=class org/scalatest/flatspec/FixtureAnyFlatSpecLike$BehaviorWord of class org/scalatest/flatspec/FixtureAnyFlatSpecLike
  public final #66= #65 of #2;            // IgnoreVerbString=class org/scalatest/flatspec/FixtureAnyFlatSpecLike$IgnoreVerbString of class org/scalatest/flatspec/FixtureAnyFlatSpecLike
  public final #69= #68 of #2;            // IgnoreVerbStringTaggedAs=class org/scalatest/flatspec/FixtureAnyFlatSpecLike$IgnoreVerbStringTaggedAs of class org/scalatest/flatspec/FixtureAnyFlatSpecLike
  public final #72= #71 of #2;            // IgnoreWord=class org/scalatest/flatspec/FixtureAnyFlatSpecLike$IgnoreWord of class org/scalatest/flatspec/FixtureAnyFlatSpecLike
  public final #75= #74 of #2;            // InAndIgnoreMethods=class org/scalatest/flatspec/FixtureAnyFlatSpecLike$InAndIgnoreMethods of class org/scalatest/flatspec/FixtureAnyFlatSpecLike
  public final #78= #77 of #2;            // InAndIgnoreMethodsAfterTaggedAs=class org/scalatest/flatspec/FixtureAnyFlatSpecLike$InAndIgnoreMethodsAfterTaggedAs of class org/scalatest/flatspec/FixtureAnyFlatSpecLike
  public final #81= #80 of #2;            // ItVerbString=class org/scalatest/flatspec/FixtureAnyFlatSpecLike$ItVerbString of class org/scalatest/flatspec/FixtureAnyFlatSpecLike
  public final #84= #83 of #2;            // ItVerbStringTaggedAs=class org/scalatest/flatspec/FixtureAnyFlatSpecLike$ItVerbStringTaggedAs of class org/scalatest/flatspec/FixtureAnyFlatSpecLike
  public final #87= #86 of #2;            // ItWord=class org/scalatest/flatspec/FixtureAnyFlatSpecLike$ItWord of class org/scalatest/flatspec/FixtureAnyFlatSpecLike
  public final #90= #89 of #2;            // TheyVerbString=class org/scalatest/flatspec/FixtureAnyFlatSpecLike$TheyVerbString of class org/scalatest/flatspec/FixtureAnyFlatSpecLike
  public final #93= #92 of #2;            // TheyVerbStringTaggedAs=class org/scalatest/flatspec/FixtureAnyFlatSpecLike$TheyVerbStringTaggedAs of class org/scalatest/flatspec/FixtureAnyFlatSpecLike
  public final #96= #95 of #2;            // TheyWord=class org/scalatest/flatspec/FixtureAnyFlatSpecLike$TheyWord of class org/scalatest/flatspec/FixtureAnyFlatSpecLike
SourceFile: "FixtureAnyFlatSpecLike.scala"
RuntimeVisibleAnnotations:
  0: #24(#25=[s#26])
    org.scalatest.Finders(
      value=["org.scalatest.finders.FlatSpecFinder"]
    )
  1: #27(#28=s#29)
    scala.reflect.ScalaSignature(
      bytes="\u0006\u0005\u0019=aACA\u0010\u0003C\u0001\n1!\u0001\u00020!9\u00111\u0010\u0001\u0005\u0002\u0005u\u0004\"CAC\u0001\t\u0007IQBAD\u0011-\tY\n\u0001b\u0001\n\u0003\t)#!(\t\u000f\u0005=\u0006\u0001\"\u0005\u00022\"9\u0011\u0011\u0018\u0001\u0005\u0012\u0005m\u0006bBAb\u0001\u0011E\u0011Q\u0019\u0005\b\u0003\u001b\u0004A\u0011CAh\u0011\u001d\t9\u000e\u0001C\u0007\u00033DqA!\u000b\u0001\t\u000b\u0011Y\u0003C\u0004\u0003:\u0001!iAa\u000f\t\u000f\t\u001d\u0003\u0001\"\u0002\u0003J!9!q\u000b\u0001\u0005\n\te\u0003b\u0002B>\u0001\u0011%!Q\u0010\u0004\u0007\u0005#\u0003!Ba%\t\u000f\tUe\u0002\"\u0001\u0003\u0018\"9!1\u0014\b\u0005\u000e\tu\u0005b\u0002BS\u001d\u0011\u0005!q\u0015\u0005\n\u0005_\u0003!\u0019!C\t\u0005c3aAa-\u0001\u0015\tU\u0006B\u0003B\\\'\t\u0005\t\u0015!\u0003\u0003\u0006!Q!\u0011X\n\u0003\u0002\u0003\u0006IA!\u0002\t\u0015\tm6C!A!\u0002\u0013\u0011\t\u0007C\u0004\u0003\u0016N!\tA!0\t\u000f\t\u001d7\u0003\"\u0004\u0003J\"9!Q[\n\u0005\u0002\t]\u0007b\u0002Bk\'\u0011\u0005!q\u001c\u0005\b\u0005O\u001cB\u0011\u0001Bu\u0011\u001d\u00119p\u0005C\u0007\u0005sDqAa@\u0014\t\u0003\u0019\t\u0001C\u0004\u0003\u0000N!\ta!\u0003\u0007\r\rE\u0001ACB\n\u0011)\u00119l\bB\u0001B\u0003%!Q\u0001\u0005\u000b\u0005s{\"\u0011!Q\u0001\n\t\u0015\u0001b\u0002BK?\u0011\u00051Q\u0003\u0005\b\u0005\u000f|BQBB\u000f\u0011\u001d\u0011)n\bC\u0001\u0007GAqA!6 \t\u0003\u0019Y\u0003C\u0004\u0003h~!\taa\r\t\u000f\t]x\u0004\"\u0004\u0004<!9!q`\u0010\u0005\u0002\r\u0005\u0003b\u0002B\u0000?\u0011\u00051\u0011\n\u0005\b\u0007#zB\u0011AB*\r\u0019\u0019i\u0006\u0001\u0006\u0004`!9!QS\u0016\u0005\u0002\r\u0005\u0004bBB3W\u0011\u00051q\r\u0005\b\u0007[ZC\u0011AB8\u0011\u001d\u0019\u0019h\u000bC\u0001\u0007kBqa!\u001a,\t\u0003\u0019I\bC\u0004\u0004n-\"\ta!\"\t\u000f\rM4\u0006\"\u0001\u0004\n\"I1Q\u0012\u0001C\u0002\u0013E1q\u0012\u0004\u0007\u0007#\u0003!ba%\t\u0015\t]FG!A!\u0002\u0013\u0011)\u0001\u0003\u0006\u0003:R\u0012\t\u0011)A\u0005\u0005\u000bA!Ba/5\u0005\u0003\u0005\u000b\u0011\u0002B1\u0011\u001d\u0011)\n\u000eC\u0001\u0007+CqAa25\t\u001b\u0019y\nC\u0004\u0003VR\"\ta!*\t\u000f\tUG\u0007\"\u0001\u0004.\"9!q\u001d\u001b\u0005\u0002\rU\u0006b\u0002B|i\u001151Q\u0018\u0005\b\u0005\u007f$D\u0011ABb\u0011\u001d\u0011y\u0010\u000eC\u0001\u0007\u00174aaa5\u0001\u0015\rU\u0007B\u0003B\\\u0001\n\u0005\t\u0015!\u0003\u0003\u0006!Q!\u0011\u0018!\u0003\u0002\u0003\u0006IA!\u0002\t\u000f\tU\u0005\t\"\u0001\u0004X\"9!q\u0019!\u0005\u0002\r}\u0007b\u0002Bk\u0001\u0012\u00051Q\u001d\u0005\b\u0005+\u0004E\u0011ABw\u0011\u001d\u00119\u000f\u0011C\u0001\u0007kDqAa>A\t\u001b\u0019i\u0010C\u0004\u0003\u0000\u0002#\t\u0001b\u0001\t\u000f\t}\b\t\"\u0001\u0005\f!91\u0011\u000b!\u0005\u0002\u0011MaA\u0002C\r\u0001)!Y\u0002C\u0004\u0003\u00162#\t\u0001\"\b\t\u000f\r\u0015D\n\"\u0001\u0005\"!91Q\u000e\'\u0005\u0002\u0011\u0015\u0002bBB:\u0019\u0012\u0005A\u0011\u0006\u0005\b\u0007KbE\u0011\u0001C\u0017\u0011\u001d\u0019i\u0007\u0014C\u0001\tcAqaa\u001dM\t\u0003!)\u0004C\u0005\u0005:\u0001\u0011\r\u0011\"\u0005\u0005<\u00191AQ\b\u0001\u000b\t\u007fA!Ba.V\u0005\u0003\u0005\u000b\u0011\u0002B\u0003\u0011)\u0011I,\u0016B\u0001B\u0003%!Q\u0001\u0005\u000b\u0005w+&\u0011!Q\u0001\n\t\u0005\u0004b\u0002BK+\u0012\u0005A\u0011\t\u0005\b\u0005\u000f,FQ\u0002C&\u0011\u001d\u0011).\u0016C\u0001\t#BqA!6V\t\u0003!I\u0006C\u0004\u0003hV#\t\u0001\"\u0019\u0007\r\u0011%\u0004A\u0003C6\u0011)\u00119L\u0018B\u0001B\u0003%!Q\u0001\u0005\u000b\u0005ss&\u0011!Q\u0001\n\t\u0015\u0001b\u0002BK=\u0012\u0005AQ\u000e\u0005\b\u0005\u000ftFQ\u0002C;\u0011\u001d\u0011)N\u0018C\u0001\twBqA!6_\t\u0003!\u0019\tC\u0004\u0003hz#\t\u0001b#\t\u000f\rEc\f\"\u0001\u0005\u0014\u001a1A\u0011\u0014\u0001\u000b\t7CqA!&h\t\u0003!i\nC\u0004\u0004f\u001d$\t\u0001\")\t\u000f\r5t\r\"\u0001\u0005&\"911O4\u0005\u0002\u0011%\u0006\"\u0003B\u0000\u0001\t\u0007I\u0011\u0003CW\r\u0019!y\u000b\u0001\u0006\u00052\"QA1W7\u0003\u0002\u0003\u0006I\u0001\".\t\u000f\tUU\u000e\"\u0001\u0005<\"9!qY7\u0005\u000e\u0011\u0005\u0007b\u0002Bk[\u0012\u0005Aq\u0019\u0005\b\u0005olGQ\u0002Ch\u0011\u001d\u0011y0\u001cC\u0001\t+DqA!6n\t\u0003!i\u000eC\u0004\u0003\u00006$\t\u0001\":\t\u000f\u00115\b\u0001b\u0005\u0005p\u001a1A1\u001f\u0001\u000b\tkD!\u0002b>x\u0005\u0003\u0005\u000b\u0011\u0002C}\u0011\u001d\u0011)j\u001eC\u0001\t\u007fDqAa2x\t\u001b))\u0001C\u0004\u0003V^$\t!b\u0003\t\u000f\t]x\u000f\"\u0004\u0006\u0014!9!q`<\u0005\u0002\u0015e\u0001b\u0002Bko\u0012\u0005Q\u0011\u0005\u0005\b\u0005\u007f<H\u0011AC\u0015\u0011\u001d)\t\u0004\u0001C\n\u000bgA\u0011\"b\u000e\u0001\u0005\u0004%\u0019\"\"\u000f\t\u0013\u0015\u0005\u0003A1A\u0005\u0014\u0015\r\u0003bBC&\u0001\u0011%QQ\n\u0005\b\u000b3\u0002A\u0011BC.\u0011\u001d\u0011Y\f\u0001C!\u000bOBq!\"\u001e\u0001\t#*9\bC\u0004\u0006\u000e\u0002!\t&b$\t\u000f\u0015m\u0005\u0001\"\u0011\u0006\u001e\"9Qq\u0014\u0001\u0005B\u0015\u0005\u0006\"CCT\u0001\t\u0007I\u0011CCU\u0011%)Y\u000b\u0001b\u0001\n\u000b*i\u000bC\u0004\u0006D\u0002!\t%\"2\t\u0013\u0015e\u0007!%A\u0005\u0002\u0015m\u0007BDCy\u0001A\u0005\u0019\u0011!A\u0005\n\u0015MX\u0011 \u0002\u0017\r&DH/\u001e:f\u0003:Lh\t\\1u\'B,7\rT5lK*!\u00111EA\u0013\u0003!1G.\u0019;ta\u0016\u001c\'\u0002BA\u0014\u0003S\t\u0011b]2bY\u0006$Xm\u001d;\u000b\u0005\u0005-\u0012aA8sO\u000e\u00011#\u0006\u0001\u00022\u0005u\u0012QIA&\u0003/\ni&a\u0019\u0002j\u0005=\u0014Q\u000f\t\u0005\u0003g\tI$\u0004\u0002\u00026)\u0011\u0011qG\u0001\u0006g\u000e\fG.Y\u0005\u0005\u0003w\t)D\u0001\u0004B]f\u0014VM\u001a\t\u0005\u0003\u007f\t\t%\u0004\u0002\u0002&%!\u00111IA\u0013\u0005A1\u0015\u000e\u001f;ve\u0016$Vm\u001d;Tk&$X\r\u0005\u0003\u0002@\u0005\u001d\u0013\u0002BA%\u0003K\u0011qCR5yiV\u0014X\rV3tiJ+w-[:ue\u0006$\u0018n\u001c8\u0011\t\u00055\u00131K\u0007\u0003\u0003\u001fRA!!\u0015\u0002&\u0005)a/\u001a:cg&!\u0011QKA(\u0005)\u0019\u0006n\\;mIZ+\'O\u0019\t\u0005\u0003\u001b\nI&\u0003\u0003\u0002\\\u0005=#\u0001C\'vgR4VM\u001d2\u0011\t\u00055\u0013qL\u0005\u0005\u0003C\nyEA\u0004DC:4VM\u001d2\u0011\t\u0005}\u0012QM\u0005\u0005\u0003O\n)CA\u0005J]\u001a|\'/\\5oOB!\u0011qHA6\u0013\u0011\ti\'!\n\u0003\u00139{G/\u001b4zS:<\u0007\u0003BA \u0003cJA!a\u001d\u0002&\tA\u0011\t\\3si&tw\r\u0005\u0003\u0002@\u0005]\u0014\u0002BA=\u0003K\u00111\u0002R8dk6,g\u000e^5oO\u00061A%\u001b8ji\u0012\"\"!a \u0011\t\u0005M\u0012\u0011Q\u0005\u0005\u0003\u0007\u000b)D\u0001\u0003V]&$\u0018AB3oO&tW-\u0006\u0002\u0002\nB1\u0011qHAF\u0003\u001fKA!!$\u0002&\tia)\u001b=ukJ,WI\\4j]\u0016\u0004B!!%\u0002\u00146\t\u0001!\u0003\u0003\u0002\u0016\u0006]%\u0001\u0004$jqR,(/\u001a)be\u0006l\u0017\u0002BAM\u0003K\u0011ABR5yiV\u0014XmU;ji\u0016\fab]8ve\u000e,g)\u001b7f\u001d\u0006lW-\u0006\u0002\u0002 B!\u0011\u0011UAV\u001b\t\t\u0019K\u0003\u0003\u0002&\u0006\u001d\u0016\u0001\u00027b]\u001eT!!!+\u0002\t)\fg/Y\u0005\u0005\u0003[\u000b\u0019K\u0001\u0004TiJLgnZ\u0001\u0005S:4w.\u0006\u0002\u00024B!\u0011qHA[\u0013\u0011\t9,!\n\u0003\u0011%sgm\u001c:nKJ\fAA\\8uKV\u0011\u0011Q\u0018\t\u0005\u0003\u007f\ty,\u0003\u0003\u0002B\u0006\u0015\"\u0001\u0003(pi&4\u0017.\u001a:\u0002\u000b\u0005dWM\u001d;\u0016\u0005\u0005\u001d\u0007\u0003BA \u0003\u0013LA!a3\u0002&\t9\u0011\t\\3si\u0016\u0014\u0018AB7be.,\b/\u0006\u0002\u0002RB!\u0011qHAj\u0013\u0011\t).!\n\u0003\u0015\u0011{7-^7f]R,\'/\u0001\tsK\u001eL7\u000f^3s)\u0016\u001cH/S7qYR1\u00111\u001cB\u0001\u00053!b!a \u0002^\u00065\bbBAp\u0011\u0001\u0007\u0011\u0011]\u0001\bi\u0016\u001cHOR;o!!\t\u0019$a9\u0002\u0010\u0006\u001d\u0018\u0002BAs\u0003k\u0011\u0011BR;oGRLwN\\\u0019\u0011\t\u0005M\u0012\u0011^\u0005\u0005\u0003W\f)DA\u0002B]fDq!a<\t\u0001\u0004\t\t0A\u0002q_N\u0004B!a=\u0002~6\u0011\u0011Q\u001f\u0006\u0005\u0003o\fI0\u0001\u0004t_V\u00148-\u001a\u0006\u0005\u0003w\fI#A\u0005tG\u0006d\u0017m\u0019;jG&!\u0011q`A{\u0005!\u0001vn]5uS>t\u0007b\u0002B\u0002\u0011\u0001\u0007!QA\u0001\ti\u0016\u001cH\u000fV3yiB!!q\u0001B\u000b\u001d\u0011\u0011IA!\u0005\u0011\t\t-\u0011QG\u0007\u0003\u0005\u001bQAAa\u0004\u0002.\u00051AH]8pizJAAa\u0005\u00026\u00051\u0001K]3eK\u001aLA!!,\u0003\u0018)!!1CA\u001b\u0011\u001d\u0011Y\u0002\u0003a\u0001\u0005;\t\u0001\u0002^3tiR\u000bwm\u001d\t\u0007\u0003g\u0011yBa\t\n\t\t\u0005\u0012Q\u0007\u0002\u000byI,\u0007/Z1uK\u0012t\u0004\u0003BA \u0005KIAAa\n\u0002&\t\u0019A+Y4\u0002\u0019I,w-[:uKJ$Vm\u001d;\u0015\r\t5\"Q\u0007B\u001c)\u0011\u0011yCa\r\u0015\t\u0005}$\u0011\u0007\u0005\b\u0003_L\u00019AAy\u0011\u001d\ty.\u0003a\u0001\u0003CDqAa\u0001\n\u0001\u0004\u0011)\u0001C\u0004\u0003\u001c%\u0001\rA!\b\u0002/I,w-[:uKJLuM\\8sK\u0012$Vm\u001d;J[BdGC\u0002B\u001f\u0005\u0007\u0012)\u0005\u0006\u0004\u0002\u0000\t}\"\u0011\t\u0005\b\u0003?T\u0001\u0019AAq\u0011\u001d\tyO\u0003a\u0001\u0003cDqAa\u0001\u000b\u0001\u0004\u0011)\u0001C\u0004\u0003\u001c)\u0001\rA!\b\u0002\'I,w-[:uKJLuM\\8sK\u0012$Vm\u001d;\u0015\r\t-#1\u000bB+)\u0011\u0011iE!\u0015\u0015\t\u0005}$q\n\u0005\b\u0003_\\\u00019AAy\u0011\u001d\tyn\u0003a\u0001\u0003CDqAa\u0001\f\u0001\u0004\u0011)\u0001C\u0004\u0003\u001c-\u0001\rA!\b\u0002#I,w-[:uKJ$Vm\u001d;U_J+h\u000e\u0006\u0007\u0002\u0000\tm#q\fB:\u0005o\u0012I\bC\u0004\u0003^1\u0001\rA!\u0002\u0002\u0011M\u0004Xm\u0019+fqRDqAa\u0007\r\u0001\u0004\u0011\t\u0007\u0005\u0004\u0003d\t5$1\u0005\b\u0005\u0005K\u0012IG\u0004\u0003\u0003\f\t\u001d\u0014BAA\u001c\u0013\u0011\u0011Y\'!\u000e\u0002\u000fA\f7m[1hK&!!q\u000eB9\u0005\u0011a\u0015n\u001d;\u000b\t\t-\u0014Q\u0007\u0005\b\u0005kb\u0001\u0019\u0001B\u0003\u0003)iW\r\u001e5pI:\u000bW.\u001a\u0005\b\u0003?d\u0001\u0019AAq\u0011\u001d\ty\u000f\u0004a\u0001\u0003c\f\u0001D]3hSN$XM\u001d)f]\u0012Lgn\u001a+fgR$vNU;o)1\tyHa \u0003\u0002\n\r%Q\u0011BH\u0011\u001d\u0011i&\u0004a\u0001\u0005\u000bAqAa\u0007\u000e\u0001\u0004\u0011\t\u0007C\u0004\u0003v5\u0001\rA!\u0002\t\u000f\u0005}W\u00021\u0001\u0003\bBA\u00111GAr\u0003\u001f\u0013I\t\u0005\u0003\u0002@\t-\u0015\u0002\u0002BG\u0003K\u0011\u0001\u0003U3oI&twm\u0015;bi\u0016lWM\u001c;\t\u000f\u0005=X\u00021\u0001\u0002r\na!)\u001a5bm&|\'oV8sIN\u0019a\"!\r\u0002\rqJg.\u001b;?)\t\u0011I\nE\u0002\u0002\u0012:\taa\u001c4J[BdGCBA@\u0005?\u0013\u0019\u000bC\u0004\u0003\"B\u0001\rA!\u0002\u0002\u0017\u0011,7o\u0019:jaRLwN\u001c\u0005\b\u0003_\u0004\u0002\u0019AAy\u0003\tyg\r\u0006\u0003\u0003*\n5F\u0003BA@\u0005WCq!a<\u0012\u0001\b\t\t\u0010C\u0004\u0003\"F\u0001\rA!\u0002\u0002\u0011\t,\u0007.\u0019<j_J,\"A!\'\u0003)%#h+\u001a:c\'R\u0014\u0018N\\4UC\u001e<W\rZ!t\'\r\u0019\u0012\u0011G\u0001\u0005m\u0016\u0014(-\u0001\u0003oC6,\u0017\u0001\u0002;bON$\u0002Ba0\u0003B\n\r\'Q\u0019\t\u0004\u0003#\u001b\u0002b\u0002B\\/\u0001\u0007!Q\u0001\u0005\b\u0005s;\u0002\u0019\u0001B\u0003\u0011\u001d\u0011Yl\u0006a\u0001\u0005C\na!\u001b8J[BdGCBA@\u0005\u0017\u0014\u0019\u000eC\u0004\u0002`b\u0001\rA!4\u0011\r\u0005M\"qZAt\u0013\u0011\u0011\t.!\u000e\u0003\u0013\u0019+hn\u0019;j_:\u0004\u0004bBAx1\u0001\u0007\u0011\u0011_\u0001\u0003S:$BA!7\u0003^R!\u0011q\u0010Bn\u0011\u001d\ty/\u0007a\u0002\u0003cDq!a8\u001a\u0001\u0004\u0011i\r\u0006\u0003\u0003b\n\u0015H\u0003BA@\u0005GDq!a<\u001b\u0001\b\t\t\u0010C\u0004\u0002`j\u0001\r!!9\u0002\u0005%\u001cH\u0003\u0002Bv\u0005_$B!a \u0003n\"9\u0011q^\u000eA\u0004\u0005E\b\u0002CAp7\u0011\u0005\rA!=\u0011\r\u0005M\"1\u001fBE\u0013\u0011\u0011)0!\u000e\u0003\u0011q\u0012\u0017P\\1nKz\n!\"[4o_J,\u0017*\u001c9m)\u0019\tyHa?\u0003~\"9\u0011q\u001c\u000fA\u0002\t5\u0007bBAx9\u0001\u0007\u0011\u0011_\u0001\u0007S\u001etwN]3\u0015\t\r\r1q\u0001\u000b\u0005\u0003\u007f\u001a)\u0001C\u0004\u0002pv\u0001\u001d!!=\t\u000f\u0005}W\u00041\u0001\u0003NR!11BB\b)\u0011\tyh!\u0004\t\u000f\u0005=h\u0004q\u0001\u0002r\"9\u0011q\u001c\u0010A\u0002\u0005\u0005(\u0001D%u-\u0016\u0014(m\u0015;sS:<7cA\u0010\u00022Q11qCB\r\u00077\u00012!!% \u0011\u001d\u00119L\ta\u0001\u0005\u000bAqA!/#\u0001\u0004\u0011)\u0001\u0006\u0004\u0002\u0000\r}1\u0011\u0005\u0005\b\u0003?\u001c\u0003\u0019\u0001Bg\u0011\u001d\tyo\ta\u0001\u0003c$Ba!\n\u0004*Q!\u0011qPB\u0014\u0011\u001d\ty\u000f\na\u0002\u0003cDq!a8%\u0001\u0004\u0011i\r\u0006\u0003\u0004.\rEB\u0003BA@\u0007_Aq!a<&\u0001\b\t\t\u0010C\u0004\u0002`\u0016\u0002\r!!9\u0015\t\rU2\u0011\b\u000b\u0005\u0003\u007f\u001a9\u0004C\u0004\u0002p\u001a\u0002\u001d!!=\t\u0011\u0005}g\u0005\"a\u0001\u0005c$b!a \u0004>\r}\u0002bBApO\u0001\u0007!Q\u001a\u0005\b\u0003_<\u0003\u0019AAy)\u0011\u0019\u0019ea\u0012\u0015\t\u0005}4Q\t\u0005\b\u0003_D\u00039AAy\u0011\u001d\ty\u000e\u000ba\u0001\u0005\u001b$Baa\u0013\u0004PQ!\u0011qPB\'\u0011\u001d\ty/\u000ba\u0002\u0003cDq!a8*\u0001\u0004\t\t/\u0001\u0005uC\u001e<W\rZ!t)\u0019\u0011yl!\u0016\u0004Z!91q\u000b\u0016A\u0002\t\r\u0012\u0001\u00044jeN$H+Z:u)\u0006<\u0007bBB.U\u0001\u0007!QD\u0001\u000e_RDWM\u001d+fgR$\u0016mZ:\u0003\r%#xk\u001c:e\'\rY\u0013\u0011\u0007\u000b\u0003\u0007G\u00022!!%,\u0003\u0019\u0019\bn\\;mIR!1qCB5\u0011\u001d\u0019Y\'\fa\u0001\u0005\u000b\taa\u001d;sS:<\u0017\u0001B7vgR$Baa\u0006\u0004r!911\u000e\u0018A\u0002\t\u0015\u0011aA2b]R!1qCB<\u0011\u001d\u0019Yg\fa\u0001\u0005\u000b!Baa\u001f\u0004\u0002B!\u0011QJB?\u0013\u0011\u0019y(a\u0014\u0003\u0015\t+\u0007.\u0019<f/>\u0014H\rC\u0004\u0004\u0004B\u0002\raa\u001f\u0002\u0015\t,\u0007.\u0019<f/>\u0014H\r\u0006\u0003\u0004|\r\u001d\u0005bBBBc\u0001\u000711\u0010\u000b\u0005\u0007w\u001aY\tC\u0004\u0004\u0004J\u0002\raa\u001f\u0002\u0005%$XCAB2\u0005Y!\u0006.Z=WKJ\u00147\u000b\u001e:j]\u001e$\u0016mZ4fI\u0006\u001b8c\u0001\u001b\u00022QA1qSBM\u00077\u001bi\nE\u0002\u0002\u0012RBqAa.9\u0001\u0004\u0011)\u0001C\u0004\u0003:b\u0002\rA!\u0002\t\u000f\tm\u0006\b1\u0001\u0003bQ1\u0011qPBQ\u0007GCq!a8:\u0001\u0004\u0011i\rC\u0004\u0002pf\u0002\r!!=\u0015\t\r\u001d61\u0016\u000b\u0005\u0003\u007f\u001aI\u000bC\u0004\u0002pj\u0002\u001d!!=\t\u000f\u0005}\'\b1\u0001\u0003NR!1qVBZ)\u0011\tyh!-\t\u000f\u0005=8\bq\u0001\u0002r\"9\u0011q\\\u001eA\u0002\u0005\u0005H\u0003BB\\\u0007w#B!a \u0004:\"9\u0011q\u001e\u001fA\u0004\u0005E\b\u0002CApy\u0011\u0005\rA!=\u0015\r\u0005}4qXBa\u0011\u001d\ty.\u0010a\u0001\u0005\u001bDq!a<>\u0001\u0004\t\t\u0010\u0006\u0003\u0004F\u000e%G\u0003BA@\u0007\u000fDq!a<?\u0001\b\t\t\u0010C\u0004\u0002`z\u0002\rA!4\u0015\t\r57\u0011\u001b\u000b\u0005\u0003\u007f\u001ay\rC\u0004\u0002p~\u0002\u001d!!=\t\u000f\u0005}w\b1\u0001\u0002b\nqA\u000b[3z-\u0016\u0014(m\u0015;sS:<7c\u0001!\u00022Q11\u0011\\Bn\u0007;\u00042!!%A\u0011\u001d\u00119l\u0011a\u0001\u0005\u000bAqA!/D\u0001\u0004\u0011)\u0001\u0006\u0004\u0002\u0000\r\u000581\u001d\u0005\b\u0003?$\u0005\u0019\u0001Bg\u0011\u001d\ty\u000f\u0012a\u0001\u0003c$Baa:\u0004lR!\u0011qPBu\u0011\u001d\ty/\u0012a\u0002\u0003cDq!a8F\u0001\u0004\u0011i\r\u0006\u0003\u0004p\u000eMH\u0003BA@\u0007cDq!a<G\u0001\b\t\t\u0010C\u0004\u0002`\u001a\u0003\r!!9\u0015\t\r]81 \u000b\u0005\u0003\u007f\u001aI\u0010C\u0004\u0002p\u001e\u0003\u001d!!=\t\u0011\u0005}w\t\"a\u0001\u0005c$b!a \u0004\u0000\u0012\u0005\u0001bBAp\u0011\u0002\u0007!Q\u001a\u0005\b\u0003_D\u0005\u0019AAy)\u0011!)\u0001\"\u0003\u0015\t\u0005}Dq\u0001\u0005\b\u0003_L\u00059AAy\u0011\u001d\ty.\u0013a\u0001\u0005\u001b$B\u0001\"\u0004\u0005\u0012Q!\u0011q\u0010C\b\u0011\u001d\tyO\u0013a\u0002\u0003cDq!a8K\u0001\u0004\t\t\u000f\u0006\u0004\u0003@\u0012UAq\u0003\u0005\b\u0007/Z\u0005\u0019\u0001B\u0012\u0011\u001d\u0019Yf\u0013a\u0001\u0005;\u0011\u0001\u0002\u00165fs^{\'\u000fZ\n\u0004\u0019\u0006EBC\u0001C\u0010!\r\t\t\n\u0014\u000b\u0005\u0007/!\u0019\u0003C\u0004\u0004l9\u0003\rA!\u0002\u0015\t\r]Aq\u0005\u0005\b\u0007Wz\u0005\u0019\u0001B\u0003)\u0011\u00199\u0002b\u000b\t\u000f\r-\u0004\u000b1\u0001\u0003\u0006Q!11\u0010C\u0018\u0011\u001d\u0019\u0019)\u0015a\u0001\u0007w\"Baa\u001f\u00054!911\u0011*A\u0002\rmD\u0003BB>\toAqaa!T\u0001\u0004\u0019Y(\u0001\u0003uQ\u0016LXC\u0001C\u0010\u0005aIuM\\8sKZ+\'OY*ue&tw\rV1hO\u0016$\u0017i]\n\u0004+\u0006EB\u0003\u0003C\"\t\u000b\"9\u0005\"\u0013\u0011\u0007\u0005EU\u000bC\u0004\u00038f\u0003\rA!\u0002\t\u000f\te\u0016\f1\u0001\u0003\u0006!9!1X-A\u0002\t\u0005DCBA@\t\u001b\"y\u0005C\u0004\u0002`j\u0003\rA!4\t\u000f\u0005=(\f1\u0001\u0002rR!A1\u000bC,)\u0011\ty\b\"\u0016\t\u000f\u0005=8\fq\u0001\u0002r\"9\u0011q\\.A\u0002\t5G\u0003\u0002C.\t?\"B!a \u0005^!9\u0011q\u001e/A\u0004\u0005E\bbBAp9\u0002\u0007\u0011\u0011\u001d\u000b\u0005\tG\"9\u0007\u0006\u0003\u0002\u0000\u0011\u0015\u0004bBAx;\u0002\u000f\u0011\u0011\u001f\u0005\t\u0003?lF\u00111\u0001\u0003r\n\u0001\u0012j\u001a8pe\u00164VM\u001d2TiJLgnZ\n\u0004=\u0006EBC\u0002C8\tc\"\u0019\bE\u0002\u0002\u0012zCqAa.b\u0001\u0004\u0011)\u0001C\u0004\u0003:\u0006\u0004\rA!\u0002\u0015\r\u0005}Dq\u000fC=\u0011\u001d\tyN\u0019a\u0001\u0005\u001bDq!a<c\u0001\u0004\t\t\u0010\u0006\u0003\u0005~\u0011\u0005E\u0003BA@\t\u007fBq!a<d\u0001\b\t\t\u0010C\u0004\u0002`\u000e\u0004\rA!4\u0015\t\u0011\u0015E\u0011\u0012\u000b\u0005\u0003\u007f\"9\tC\u0004\u0002p\u0012\u0004\u001d!!=\t\u000f\u0005}G\r1\u0001\u0002bR!AQ\u0012CI)\u0011\ty\bb$\t\u000f\u0005=X\rq\u0001\u0002r\"A\u0011q\\3\u0005\u0002\u0004\u0011\t\u0010\u0006\u0004\u0005D\u0011UEq\u0013\u0005\b\u0007/2\u0007\u0019\u0001B\u0012\u0011\u001d\u0019YF\u001aa\u0001\u0005;\u0011!\"S4o_J,wk\u001c:e\'\r9\u0017\u0011\u0007\u000b\u0003\t?\u00032!!%h)\u0011!y\u0007b)\t\u000f\r-\u0014\u000e1\u0001\u0003\u0006Q!Aq\u000eCT\u0011\u001d\u0019YG\u001ba\u0001\u0005\u000b!B\u0001b\u001c\u0005,\"911N6A\u0002\t\u0015QC\u0001CP\u0005IIe.\u00118e\u0013\u001etwN]3NKRDw\u000eZ:\u0014\u00075\f\t$\u0001\u000esKN,H\u000e^(g\'R\u0014\u0018N\\4QCN\u001cX\r\u001a+p-\u0016\u0014(\r\u0005\u0003\u0002N\u0011]\u0016\u0002\u0002C]\u0003\u001f\u0012!DU3tk2$xJZ*ue&tw\rU1tg\u0016$Gk\u001c,fe\n$B\u0001\"0\u0005@B\u0019\u0011\u0011S7\t\u000f\u0011Mv\u000e1\u0001\u00056R1\u0011q\u0010Cb\t\u000bDq!a8q\u0001\u0004\u0011i\rC\u0004\u0002pB\u0004\r!!=\u0015\t\u0011%GQ\u001a\u000b\u0005\u0003\u007f\"Y\rC\u0004\u0002pF\u0004\u001d!!=\t\u000f\u0005}\u0017\u000f1\u0001\u0003NR1\u0011q\u0010Ci\t\'Dq!a8s\u0001\u0004\u0011i\rC\u0004\u0002pJ\u0004\r!!=\u0015\t\u0011]G1\u001c\u000b\u0005\u0003\u007f\"I\u000eC\u0004\u0002pN\u0004\u001d!!=\t\u000f\u0005}7\u000f1\u0001\u0003NR!Aq\u001cCr)\u0011\ty\b\"9\t\u000f\u0005=H\u000fq\u0001\u0002r\"9\u0011q\u001c;A\u0002\u0005\u0005H\u0003\u0002Ct\tW$B!a \u0005j\"9\u0011q^;A\u0004\u0005E\bbBApk\u0002\u0007\u0011\u0011]\u0001\u001cG>tg/\u001a:u)>Le.\u00118e\u0013\u001etwN]3NKRDw\u000eZ:\u0015\t\u0011uF\u0011\u001f\u0005\b\tg3\b\u0019\u0001C[\u0005}Ie.\u00118e\u0013\u001etwN]3NKRDw\u000eZ:BMR,\'\u000fV1hO\u0016$\u0017i]\n\u0004o\u0006E\u0012A\u0007:fgVdGo\u00144UC\u001e<W\rZ!t\u0013:4xnY1uS>t\u0007\u0003BA\'\twLA\u0001\"@\u0002P\tQ\"+Z:vYR|e\rV1hO\u0016$\u0017i]%om>\u001c\u0017\r^5p]R!Q\u0011AC\u0002!\r\t\tj\u001e\u0005\b\toL\b\u0019\u0001C})\u0019\ty(b\u0002\u0006\n!9\u0011q\u001c>A\u0002\t5\u0007bBAxu\u0002\u0007\u0011\u0011\u001f\u000b\u0005\u000b\u001b)\t\u0002\u0006\u0003\u0002\u0000\u0015=\u0001bBAxw\u0002\u000f\u0011\u0011\u001f\u0005\b\u0003?\\\b\u0019\u0001Bg)\u0019\ty(\"\u0006\u0006\u0018!9\u0011q\u001c?A\u0002\t5\u0007bBAxy\u0002\u0007\u0011\u0011\u001f\u000b\u0005\u000b7)y\u0002\u0006\u0003\u0002\u0000\u0015u\u0001bBAx{\u0002\u000f\u0011\u0011\u001f\u0005\b\u0003?l\b\u0019\u0001Bg)\u0011)\u0019#b\n\u0015\t\u0005}TQ\u0005\u0005\b\u0003_t\b9AAy\u0011\u001d\tyN a\u0001\u0003C$B!b\u000b\u00060Q!\u0011qPC\u0017\u0011\u001d\tyo a\u0002\u0003cDq!a8\u0000\u0001\u0004\t\t/\u0001\u0015d_:4XM\u001d;U_&s\u0017I\u001c3JO:|\'/Z\'fi\"|Gm]!gi\u0016\u0014H+Y4hK\u0012\f5\u000f\u0006\u0003\u0006\u0002\u0015U\u0002\u0002\u0003C|\u0003\u0003\u0001\r\u0001\"?\u0002CMDwN\u001d;iC:$G+Z:u%\u0016<\u0017n\u001d;sCRLwN\u001c$v]\u000e$\u0018n\u001c8\u0016\u0005\u0015m\u0002\u0003BA\'\u000b{IA!b\u0010\u0002P\tQ2\u000b\u001e:j]\u001e4VM\u001d2TiJLgnZ%om>\u001c\u0017\r^5p]\u000693\u000f[8si\"\fg\u000eZ*iCJ,G\rV3tiJ+w-[:ue\u0006$\u0018n\u001c8Gk:\u001cG/[8o+\t))\u0005\u0005\u0003\u0002N\u0015\u001d\u0013\u0002BC%\u0003\u001f\u0012ad\u0015;sS:<g+\u001a:c\u0005\u0016D\u0017M^3MS.,\u0017J\u001c<pG\u0006$\u0018n\u001c8\u0002)I,w-[:uKJ$Vm\u001d;U_&;gn\u001c:f)1\ty(b\u0014\u0006R\u0015MSQKC,\u0011!\u0011i&a\u0002A\u0002\t\u0015\u0001\u0002\u0003B\u000e\u0003\u000f\u0001\rA!\u0019\t\u0011\tU\u0014q\u0001a\u0001\u0005\u000bA\u0001\"a8\u0002\b\u0001\u0007\u0011\u0011\u001d\u0005\t\u0003_\f9\u00011\u0001\u0002r\u0006Y\"/Z4jgR,\'\u000fU3oI&tw\rV3tiR{\u0017j\u001a8pe\u0016$B\"a \u0006^\u0015}S\u0011MC2\u000bKB\u0001B!\u0018\u0002\n\u0001\u0007!Q\u0001\u0005\t\u00057\tI\u00011\u0001\u0003b!A!QOA\u0005\u0001\u0004\u0011)\u0001\u0003\u0005\u0002`\u0006%\u0001\u0019\u0001BD\u0011!\ty/!\u0003A\u0002\u0005EXCAC5!!\u00119!b\u001b\u0003\u0006\u0015=\u0014\u0002BC7\u0005/\u00111!T1q!\u0019\u00119!\"\u001d\u0003\u0006%!Q1\u000fB\f\u0005\r\u0019V\r^\u0001\beVtG+Z:u)\u0019)I(b \u0006\u0004B!\u0011qHC>\u0013\u0011)i(!\n\u0003\rM#\u0018\r^;t\u0011!)\t)!\u0004A\u0002\t\u0015\u0011\u0001\u0003;fgRt\u0015-\\3\t\u0011\u0015\u0015\u0015Q\u0002a\u0001\u000b\u000f\u000bA!\u0019:hgB!\u0011qHCE\u0013\u0011)Y)!\n\u0003\t\u0005\u0013xm]\u0001\teVtG+Z:ugR1Q\u0011PCI\u000b3C\u0001\"\"!\u0002\u0010\u0001\u0007Q1\u0013\t\u0007\u0003g))J!\u0002\n\t\u0015]\u0015Q\u0007\u0002\u0007\u001fB$\u0018n\u001c8\t\u0011\u0015\u0015\u0015q\u0002a\u0001\u000b\u000f\u000b\u0011\u0002^3ti:\u000bW.Z:\u0016\u0005\u0015=\u0014a\u0001:v]R1Q\u0011PCR\u000bKC\u0001\"\"!\u0002\u0014\u0001\u0007Q1\u0013\u0005\t\u000b\u000b\u000b\u0019\u00021\u0001\u0006\b\u00061!-\u001a5bm\u0016,\"aa\u001f\u0002\u0013M$\u0018\u0010\\3OC6,WC\u0001B\u0003Q1\t9\"\"-\u00068\u0016eVQXC`!\u0011\t\u0019$b-\n\t\u0015U\u0016Q\u0007\u0002\u000bI\u0016\u0004(/Z2bi\u0016$\u0017aB7fgN\fw-Z\u0011\u0003\u000bw\u000bA\u0010\u00165fAM$\u0018\u0010\\3OC6,\u0007\u0005\\5gK\u000eL8\r\\3![\u0016$\bn\u001c3!Q\u0006\u001c\bEY3f]\u0002\"W\r\u001d:fG\u0006$X\r\u001a\u0011b]\u0012\u0004s/\u001b7mA\t,\u0007E]3n_Z,G\rI5oA\u0005\u0004c-\u001e;ve\u0016\u0004c/\u001a:tS>t\u0007e\u001c4!\'\u000e\fG.\u0019+fgR\u0004s/\u001b;iA9|\u0007E]3qY\u0006\u001cW-\\3oi:\nQa]5oG\u0016\f#!\"1\u0002\u000bMr\u0013G\f\u0019\u0002\u0017Q,7\u000f\u001e#bi\u00064uN\u001d\u000b\u0007\u000b\u000f,i-b4\u0011\t\u0005}R\u0011Z\u0005\u0005\u000b\u0017\f)C\u0001\u0005UKN$H)\u0019;b\u0011!)\t)!\u0007A\u0002\t\u0015\u0001BCCi\u00033\u0001\n\u00111\u0001\u0006T\u0006aA\u000f[3D_:4\u0017nZ\'baB!\u0011qHCk\u0013\u0011)9.!\n\u0003\u0013\r{gNZ5h\u001b\u0006\u0004\u0018!\u0006;fgR$\u0015\r^1G_J$C-\u001a4bk2$HEM\u000b\u0003\u000b;TC!b5\u0006`.\u0012Q\u0011\u001d\t\u0005\u000bG,i/\u0004\u0002\u0006f*!Qq]Cu\u0003%)hn\u00195fG.,GM\u0003\u0003\u0006l\u0006U\u0012AC1o]>$\u0018\r^5p]&!Qq^Cs\u0005E)hn\u00195fG.,GMV1sS\u0006t7-Z\u0001\ngV\u0004XM\u001d\u0013sk:$b!\"\u001f\u0006v\u0016]\b\u0002CCA\u0003;\u0001\r!b%\t\u0011\u0015\u0015\u0015Q\u0004a\u0001\u000b\u000fKA!b(\u0006|&!QQ`A\u0013\u0005\u0015\u0019V/\u001b;fQ\u001d\u0001a\u0011\u0001D\u0004\r\u0013\u0001B!a\u0010\u0007\u0004%!aQAA\u0013\u0005\u001d1\u0015N\u001c3feN\fQA^1mk\u0016d#Ab\u0003\"\u0005\u00195\u0011\u0001J8sO:\u001a8-\u00197bi\u0016\u001cHO\f4j]\u0012,\'o\u001d\u0018GY\u0006$8\u000b]3d\r&tG-\u001a:"
    )
BootstrapMethods:
  0: #212 REF_invokeStatic java/lang/invoke/LambdaMetafactory.altMetafactory:(Ljava/lang/invoke/MethodHandles$Lookup;Ljava/lang/String;Ljava/lang/invoke/MethodType;[Ljava/lang/Object;)Ljava/lang/invoke/CallSite;
    Method arguments:
      #198 ()Ljava/lang/Object;
      #202 REF_invokeStatic org/scalatest/flatspec/FixtureAnyFlatSpecLike.$anonfun$registerTestImpl$1:()Ljava/lang/String;
      #203 ()Ljava/lang/String;
      #204 5
      #205 1
      #203 ()Ljava/lang/String;
  1: #212 REF_invokeStatic java/lang/invoke/LambdaMetafactory.altMetafactory:(Ljava/lang/invoke/MethodHandles$Lookup;Ljava/lang/String;Ljava/lang/invoke/MethodType;[Ljava/lang/Object;)Ljava/lang/invoke/CallSite;
    Method arguments:
      #198 ()Ljava/lang/Object;
      #250 REF_invokeStatic org/scalatest/flatspec/FixtureAnyFlatSpecLike.$anonfun$registerIgnoredTestImpl$1:()Ljava/lang/String;
      #203 ()Ljava/lang/String;
      #204 5
      #205 1
      #203 ()Ljava/lang/String;
  2: #212 REF_invokeStatic java/lang/invoke/LambdaMetafactory.altMetafactory:(Ljava/lang/invoke/MethodHandles$Lookup;Ljava/lang/String;Ljava/lang/invoke/MethodType;[Ljava/lang/Object;)Ljava/lang/invoke/CallSite;
    Method arguments:
      #198 ()Ljava/lang/Object;
      #276 REF_invokeStatic org/scalatest/flatspec/FixtureAnyFlatSpecLike.$anonfun$registerTestToRun$1:(Ljava/lang/String;)Ljava/lang/String;
      #203 ()Ljava/lang/String;
      #204 5
      #205 1
      #203 ()Ljava/lang/String;
  3: #212 REF_invokeStatic java/lang/invoke/LambdaMetafactory.altMetafactory:(Ljava/lang/invoke/MethodHandles$Lookup;Ljava/lang/String;Ljava/lang/invoke/MethodType;[Ljava/lang/Object;)Ljava/lang/invoke/CallSite;
    Method arguments:
      #198 ()Ljava/lang/Object;
      #291 REF_invokeStatic org/scalatest/flatspec/FixtureAnyFlatSpecLike.$anonfun$registerPendingTestToRun$1:(Ljava/lang/String;)Ljava/lang/String;
      #203 ()Ljava/lang/String;
      #204 5
      #205 1
      #203 ()Ljava/lang/String;
  4: #212 REF_invokeStatic java/lang/invoke/LambdaMetafactory.altMetafactory:(Ljava/lang/invoke/MethodHandles$Lookup;Ljava/lang/String;Ljava/lang/invoke/MethodType;[Ljava/lang/Object;)Ljava/lang/invoke/CallSite;
    Method arguments:
      #198 ()Ljava/lang/Object;
      #334 REF_invokeStatic org/scalatest/flatspec/FixtureAnyFlatSpecLike.$anonfun$registerTestToIgnore$1:()Ljava/lang/String;
      #203 ()Ljava/lang/String;
      #204 5
      #205 1
      #203 ()Ljava/lang/String;
  5: #212 REF_invokeStatic java/lang/invoke/LambdaMetafactory.altMetafactory:(Ljava/lang/invoke/MethodHandles$Lookup;Ljava/lang/String;Ljava/lang/invoke/MethodType;[Ljava/lang/Object;)Ljava/lang/invoke/CallSite;
    Method arguments:
      #198 ()Ljava/lang/Object;
      #343 REF_invokeStatic org/scalatest/flatspec/FixtureAnyFlatSpecLike.$anonfun$registerPendingTestToIgnore$1:()Ljava/lang/String;
      #203 ()Ljava/lang/String;
      #204 5
      #205 1
      #203 ()Ljava/lang/String;
  6: #212 REF_invokeStatic java/lang/invoke/LambdaMetafactory.altMetafactory:(Ljava/lang/invoke/MethodHandles$Lookup;Ljava/lang/String;Ljava/lang/invoke/MethodType;[Ljava/lang/Object;)Ljava/lang/invoke/CallSite;
    Method arguments:
      #375 (Ljava/lang/Object;)Ljava/lang/Object;
      #380 REF_invokeStatic org/scalatest/flatspec/FixtureAnyFlatSpecLike.$anonfun$runTest$1:(Lorg/scalatest/flatspec/FixtureAnyFlatSpecLike;Ljava/lang/String;Lorg/scalatest/Args;Lorg/scalatest/SuperEngine$TestLeaf;)Lorg/scalatest/Outcome;
      #382 (Lorg/scalatest/SuperEngine$TestLeaf;)Lorg/scalatest/Outcome;
      #204 5
      #205 1
      #382 (Lorg/scalatest/SuperEngine$TestLeaf;)Lorg/scalatest/Outcome;
  7: #212 REF_invokeStatic java/lang/invoke/LambdaMetafactory.altMetafactory:(Ljava/lang/invoke/MethodHandles$Lookup;Ljava/lang/String;Ljava/lang/invoke/MethodType;[Ljava/lang/Object;)Ljava/lang/invoke/CallSite;
    Method arguments:
      #398 (Ljava/lang/Object;Ljava/lang/Object;)Ljava/lang/Object;
      #402 REF_invokeStatic org/scalatest/flatspec/FixtureAnyFlatSpecLike.$anonfun$runTests$1:(Lorg/scalatest/flatspec/FixtureAnyFlatSpecLike;Ljava/lang/String;Lorg/scalatest/Args;)Lorg/scalatest/Status;
      #403 (Ljava/lang/String;Lorg/scalatest/Args;)Lorg/scalatest/Status;
      #204 5
      #205 1
      #403 (Ljava/lang/String;Lorg/scalatest/Args;)Lorg/scalatest/Status;
  8: #212 REF_invokeStatic java/lang/invoke/LambdaMetafactory.altMetafactory:(Ljava/lang/invoke/MethodHandles$Lookup;Ljava/lang/String;Ljava/lang/invoke/MethodType;[Ljava/lang/Object;)Ljava/lang/invoke/CallSite;
    Method arguments:
      #398 (Ljava/lang/Object;Ljava/lang/Object;)Ljava/lang/Object;
      #437 REF_invokeStatic org/scalatest/flatspec/FixtureAnyFlatSpecLike.$anonfun$run$1:(Lorg/scalatest/flatspec/FixtureAnyFlatSpecLike;Lscala/Option;Lorg/scalatest/Args;)Lorg/scalatest/Status;
      #438 (Lscala/Option;Lorg/scalatest/Args;)Lorg/scalatest/Status;
      #204 5
      #205 1
      #438 (Lscala/Option;Lorg/scalatest/Args;)Lorg/scalatest/Status;
  9: #212 REF_invokeStatic java/lang/invoke/LambdaMetafactory.altMetafactory:(Ljava/lang/invoke/MethodHandles$Lookup;Ljava/lang/String;Ljava/lang/invoke/MethodType;[Ljava/lang/Object;)Ljava/lang/invoke/CallSite;
    Method arguments:
      #198 ()Ljava/lang/Object;
      #566 REF_invokeStatic org/scalatest/flatspec/FixtureAnyFlatSpecLike.$anonfun$engine$1:()Ljava/lang/String;
      #203 ()Ljava/lang/String;
      #204 5
      #205 1
      #203 ()Ljava/lang/String;
  10: #615 REF_invokeStatic scala/runtime/LambdaDeserialize.bootstrap:(Ljava/lang/invoke/MethodHandles$Lookup;Ljava/lang/String;Ljava/lang/invoke/MethodType;[Ljava/lang/invoke/MethodHandle;)Ljava/lang/invoke/CallSite;
    Method arguments:
      #566 REF_invokeStatic org/scalatest/flatspec/FixtureAnyFlatSpecLike.$anonfun$engine$1:()Ljava/lang/String;
      #250 REF_invokeStatic org/scalatest/flatspec/FixtureAnyFlatSpecLike.$anonfun$registerIgnoredTestImpl$1:()Ljava/lang/String;
      #343 REF_invokeStatic org/scalatest/flatspec/FixtureAnyFlatSpecLike.$anonfun$registerPendingTestToIgnore$1:()Ljava/lang/String;
      #291 REF_invokeStatic org/scalatest/flatspec/FixtureAnyFlatSpecLike.$anonfun$registerPendingTestToRun$1:(Ljava/lang/String;)Ljava/lang/String;
      #202 REF_invokeStatic org/scalatest/flatspec/FixtureAnyFlatSpecLike.$anonfun$registerTestImpl$1:()Ljava/lang/String;
      #334 REF_invokeStatic org/scalatest/flatspec/FixtureAnyFlatSpecLike.$anonfun$registerTestToIgnore$1:()Ljava/lang/String;
      #276 REF_invokeStatic org/scalatest/flatspec/FixtureAnyFlatSpecLike.$anonfun$registerTestToRun$1:(Ljava/lang/String;)Ljava/lang/String;
      #437 REF_invokeStatic org/scalatest/flatspec/FixtureAnyFlatSpecLike.$anonfun$run$1:(Lorg/scalatest/flatspec/FixtureAnyFlatSpecLike;Lscala/Option;Lorg/scalatest/Args;)Lorg/scalatest/Status;
      #380 REF_invokeStatic org/scalatest/flatspec/FixtureAnyFlatSpecLike.$anonfun$runTest$1:(Lorg/scalatest/flatspec/FixtureAnyFlatSpecLike;Ljava/lang/String;Lorg/scalatest/Args;Lorg/scalatest/SuperEngine$TestLeaf;)Lorg/scalatest/Outcome;
      #402 REF_invokeStatic org/scalatest/flatspec/FixtureAnyFlatSpecLike.$anonfun$runTests$1:(Lorg/scalatest/flatspec/FixtureAnyFlatSpecLike;Ljava/lang/String;Lorg/scalatest/Args;)Lorg/scalatest/Status;
  ScalaInlineInfo: length = 0x17B (unknown attribute)
   01 00 00 4B 01 D9 00 7E 01 00 F7 00 7E 01 01 54
   00 7E 01 01 20 01 11 01 00 C7 00 7E 01 01 4B 00
   7E 01 01 10 01 11 01 01 B2 01 87 01 01 78 01 79
   01 01 8F 01 70 01 02 32 02 33 01 00 A5 00 A6 00
   00 A3 00 A4 01 01 BC 01 BD 00 01 25 01 26 00 01
   30 01 31 00 01 2D 01 2E 01 01 3B 01 3C 00 01 38
   01 39 01 01 2B 01 2C 00 00 82 00 83 00 00 7F 00
   80 01 02 07 02 08 01 01 27 01 28 00 00 B0 00 B1
   00 00 AE 00 AF 01 00 9A 00 9B 00 00 98 00 99 01
   00 7A 00 7B 00 01 51 01 0B 01 01 50 01 07 01 01
   1C 01 0B 01 01 1B 01 07 01 01 48 01 0B 01 01 47
   01 07 01 01 0A 01 0B 01 01 06 01 07 01 00 76 00
   77 01 00 73 00 74 00 00 67 00 68 00 00 6D 00 6E
   00 00 69 00 6A 00 00 61 00 62 00 00 71 00 72 00
   00 6F 00 70 00 00 65 00 66 00 00 75 00 66 00 00
   6B 00 6C 00 00 FC 00 BA 01 01 01 00 F1 01 00 F6
   00 BA 01 00 DA 00 BA 01 00 F0 00 F1 01 00 B9 00
   BA 01 01 AF 00 77 00 01 AE 01 87 01 01 71 01 72
   00 01 6F 01 70 01 01 88 00 77 00 01 86 01 87 01
   01 45 01 46 00 01 43 01 44 00 00 7D 00 7E 00 01
   BE 00 7E 00 01 5B 01 5C 00 01 59 01 5A 01 01 C2
   01 C3 00 01 BF 01 C0 01 01 CD 01 CE 00 01 CB 01
   CC 01 01 9D 01 9E 00 01 9B 01 9C 01 01 E5 01 11
   01 02 00 01 11 01 01 29 01 2A 00
  ScalaSig: length = 0x3 (unknown attribute)
   05 02 00
