Classfile /Users/mw/Projects/slang-braindump/.jar/jar8/assemble/slang-braindump/assemble/content/com/fasterxml/jackson/databind/deser/BeanDeserializerModifier.class
  Last modified May 29, 2022; size 7691 bytes
  SHA-256 checksum b789bcd408139b5ac48144f96b5227476c97a41cbe96c2ba8013408b30298b56
  Compiled from "BeanDeserializerModifier.java"
public abstract class com.fasterxml.jackson.databind.deser.BeanDeserializerModifier
  minor version: 0
  major version: 52
  flags: (0x0421) ACC_PUBLIC, ACC_SUPER, ACC_ABSTRACT
  this_class: #2                          // com/fasterxml/jackson/databind/deser/BeanDeserializerModifier
  super_class: #3                         // java/lang/Object
  interfaces: 0, fields: 0, methods: 12, attributes: 1
Constant pool:
   #1 = Methodref          #3.#68         // java/lang/Object."<init>":()V
   #2 = Class              #69            // com/fasterxml/jackson/databind/deser/BeanDeserializerModifier
   #3 = Class              #70            // java/lang/Object
   #4 = Utf8               <init>
   #5 = Utf8               ()V
   #6 = Utf8               Code
   #7 = Utf8               LineNumberTable
   #8 = Utf8               LocalVariableTable
   #9 = Utf8               this
  #10 = Utf8               Lcom/fasterxml/jackson/databind/deser/BeanDeserializerModifier;
  #11 = Utf8               updateProperties
  #12 = Utf8               (Lcom/fasterxml/jackson/databind/DeserializationConfig;Lcom/fasterxml/jackson/databind/BeanDescription;Ljava/util/List;)Ljava/util/List;
  #13 = Utf8               config
  #14 = Utf8               Lcom/fasterxml/jackson/databind/DeserializationConfig;
  #15 = Utf8               beanDesc
  #16 = Utf8               Lcom/fasterxml/jackson/databind/BeanDescription;
  #17 = Utf8               propDefs
  #18 = Utf8               Ljava/util/List;
  #19 = Utf8               LocalVariableTypeTable
  #20 = Utf8               Ljava/util/List<Lcom/fasterxml/jackson/databind/introspect/BeanPropertyDefinition;>;
  #21 = Utf8               Signature
  #22 = Utf8               (Lcom/fasterxml/jackson/databind/DeserializationConfig;Lcom/fasterxml/jackson/databind/BeanDescription;Ljava/util/List<Lcom/fasterxml/jackson/databind/introspect/BeanPropertyDefinition;>;)Ljava/util/List<Lcom/fasterxml/jackson/databind/introspect/BeanPropertyDefinition;>;
  #23 = Utf8               updateBuilder
  #24 = Utf8               (Lcom/fasterxml/jackson/databind/DeserializationConfig;Lcom/fasterxml/jackson/databind/BeanDescription;Lcom/fasterxml/jackson/databind/deser/BeanDeserializerBuilder;)Lcom/fasterxml/jackson/databind/deser/BeanDeserializerBuilder;
  #25 = Utf8               builder
  #26 = Utf8               Lcom/fasterxml/jackson/databind/deser/BeanDeserializerBuilder;
  #27 = Utf8               modifyDeserializer
  #28 = Utf8               (Lcom/fasterxml/jackson/databind/DeserializationConfig;Lcom/fasterxml/jackson/databind/BeanDescription;Lcom/fasterxml/jackson/databind/JsonDeserializer;)Lcom/fasterxml/jackson/databind/JsonDeserializer;
  #29 = Utf8               deserializer
  #30 = Utf8               Lcom/fasterxml/jackson/databind/JsonDeserializer;
  #31 = Utf8               Lcom/fasterxml/jackson/databind/JsonDeserializer<*>;
  #32 = Utf8               (Lcom/fasterxml/jackson/databind/DeserializationConfig;Lcom/fasterxml/jackson/databind/BeanDescription;Lcom/fasterxml/jackson/databind/JsonDeserializer<*>;)Lcom/fasterxml/jackson/databind/JsonDeserializer<*>;
  #33 = Utf8               modifyEnumDeserializer
  #34 = Utf8               (Lcom/fasterxml/jackson/databind/DeserializationConfig;Lcom/fasterxml/jackson/databind/JavaType;Lcom/fasterxml/jackson/databind/BeanDescription;Lcom/fasterxml/jackson/databind/JsonDeserializer;)Lcom/fasterxml/jackson/databind/JsonDeserializer;
  #35 = Utf8               type
  #36 = Utf8               Lcom/fasterxml/jackson/databind/JavaType;
  #37 = Utf8               (Lcom/fasterxml/jackson/databind/DeserializationConfig;Lcom/fasterxml/jackson/databind/JavaType;Lcom/fasterxml/jackson/databind/BeanDescription;Lcom/fasterxml/jackson/databind/JsonDeserializer<*>;)Lcom/fasterxml/jackson/databind/JsonDeserializer<*>;
  #38 = Utf8               modifyReferenceDeserializer
  #39 = Utf8               (Lcom/fasterxml/jackson/databind/DeserializationConfig;Lcom/fasterxml/jackson/databind/type/ReferenceType;Lcom/fasterxml/jackson/databind/BeanDescription;Lcom/fasterxml/jackson/databind/JsonDeserializer;)Lcom/fasterxml/jackson/databind/JsonDeserializer;
  #40 = Utf8               Lcom/fasterxml/jackson/databind/type/ReferenceType;
  #41 = Utf8               (Lcom/fasterxml/jackson/databind/DeserializationConfig;Lcom/fasterxml/jackson/databind/type/ReferenceType;Lcom/fasterxml/jackson/databind/BeanDescription;Lcom/fasterxml/jackson/databind/JsonDeserializer<*>;)Lcom/fasterxml/jackson/databind/JsonDeserializer<*>;
  #42 = Utf8               modifyArrayDeserializer
  #43 = Utf8               (Lcom/fasterxml/jackson/databind/DeserializationConfig;Lcom/fasterxml/jackson/databind/type/ArrayType;Lcom/fasterxml/jackson/databind/BeanDescription;Lcom/fasterxml/jackson/databind/JsonDeserializer;)Lcom/fasterxml/jackson/databind/JsonDeserializer;
  #44 = Utf8               valueType
  #45 = Utf8               Lcom/fasterxml/jackson/databind/type/ArrayType;
  #46 = Utf8               (Lcom/fasterxml/jackson/databind/DeserializationConfig;Lcom/fasterxml/jackson/databind/type/ArrayType;Lcom/fasterxml/jackson/databind/BeanDescription;Lcom/fasterxml/jackson/databind/JsonDeserializer<*>;)Lcom/fasterxml/jackson/databind/JsonDeserializer<*>;
  #47 = Utf8               modifyCollectionDeserializer
  #48 = Utf8               (Lcom/fasterxml/jackson/databind/DeserializationConfig;Lcom/fasterxml/jackson/databind/type/CollectionType;Lcom/fasterxml/jackson/databind/BeanDescription;Lcom/fasterxml/jackson/databind/JsonDeserializer;)Lcom/fasterxml/jackson/databind/JsonDeserializer;
  #49 = Utf8               Lcom/fasterxml/jackson/databind/type/CollectionType;
  #50 = Utf8               (Lcom/fasterxml/jackson/databind/DeserializationConfig;Lcom/fasterxml/jackson/databind/type/CollectionType;Lcom/fasterxml/jackson/databind/BeanDescription;Lcom/fasterxml/jackson/databind/JsonDeserializer<*>;)Lcom/fasterxml/jackson/databind/JsonDeserializer<*>;
  #51 = Utf8               modifyCollectionLikeDeserializer
  #52 = Utf8               (Lcom/fasterxml/jackson/databind/DeserializationConfig;Lcom/fasterxml/jackson/databind/type/CollectionLikeType;Lcom/fasterxml/jackson/databind/BeanDescription;Lcom/fasterxml/jackson/databind/JsonDeserializer;)Lcom/fasterxml/jackson/databind/JsonDeserializer;
  #53 = Utf8               Lcom/fasterxml/jackson/databind/type/CollectionLikeType;
  #54 = Utf8               (Lcom/fasterxml/jackson/databind/DeserializationConfig;Lcom/fasterxml/jackson/databind/type/CollectionLikeType;Lcom/fasterxml/jackson/databind/BeanDescription;Lcom/fasterxml/jackson/databind/JsonDeserializer<*>;)Lcom/fasterxml/jackson/databind/JsonDeserializer<*>;
  #55 = Utf8               modifyMapDeserializer
  #56 = Utf8               (Lcom/fasterxml/jackson/databind/DeserializationConfig;Lcom/fasterxml/jackson/databind/type/MapType;Lcom/fasterxml/jackson/databind/BeanDescription;Lcom/fasterxml/jackson/databind/JsonDeserializer;)Lcom/fasterxml/jackson/databind/JsonDeserializer;
  #57 = Utf8               Lcom/fasterxml/jackson/databind/type/MapType;
  #58 = Utf8               (Lcom/fasterxml/jackson/databind/DeserializationConfig;Lcom/fasterxml/jackson/databind/type/MapType;Lcom/fasterxml/jackson/databind/BeanDescription;Lcom/fasterxml/jackson/databind/JsonDeserializer<*>;)Lcom/fasterxml/jackson/databind/JsonDeserializer<*>;
  #59 = Utf8               modifyMapLikeDeserializer
  #60 = Utf8               (Lcom/fasterxml/jackson/databind/DeserializationConfig;Lcom/fasterxml/jackson/databind/type/MapLikeType;Lcom/fasterxml/jackson/databind/BeanDescription;Lcom/fasterxml/jackson/databind/JsonDeserializer;)Lcom/fasterxml/jackson/databind/JsonDeserializer;
  #61 = Utf8               Lcom/fasterxml/jackson/databind/type/MapLikeType;
  #62 = Utf8               (Lcom/fasterxml/jackson/databind/DeserializationConfig;Lcom/fasterxml/jackson/databind/type/MapLikeType;Lcom/fasterxml/jackson/databind/BeanDescription;Lcom/fasterxml/jackson/databind/JsonDeserializer<*>;)Lcom/fasterxml/jackson/databind/JsonDeserializer<*>;
  #63 = Utf8               modifyKeyDeserializer
  #64 = Utf8               (Lcom/fasterxml/jackson/databind/DeserializationConfig;Lcom/fasterxml/jackson/databind/JavaType;Lcom/fasterxml/jackson/databind/KeyDeserializer;)Lcom/fasterxml/jackson/databind/KeyDeserializer;
  #65 = Utf8               Lcom/fasterxml/jackson/databind/KeyDeserializer;
  #66 = Utf8               SourceFile
  #67 = Utf8               BeanDeserializerModifier.java
  #68 = NameAndType        #4:#5          // "<init>":()V
  #69 = Utf8               com/fasterxml/jackson/databind/deser/BeanDeserializerModifier
  #70 = Utf8               java/lang/Object
{
  public com.fasterxml.jackson.databind.deser.BeanDeserializerModifier();
    descriptor: ()V
    flags: (0x0001) ACC_PUBLIC
    Code:
      stack=1, locals=1, args_size=1
         0: aload_0
         1: invokespecial #1                  // Method java/lang/Object."<init>":()V
         4: return
      LineNumberTable:
        line 48: 0
      LocalVariableTable:
        Start  Length  Slot  Name   Signature
            0       5     0  this   Lcom/fasterxml/jackson/databind/deser/BeanDeserializerModifier;

  public java.util.List<com.fasterxml.jackson.databind.introspect.BeanPropertyDefinition> updateProperties(com.fasterxml.jackson.databind.DeserializationConfig, com.fasterxml.jackson.databind.BeanDescription, java.util.List<com.fasterxml.jackson.databind.introspect.BeanPropertyDefinition>);
    descriptor: (Lcom/fasterxml/jackson/databind/DeserializationConfig;Lcom/fasterxml/jackson/databind/BeanDescription;Ljava/util/List;)Ljava/util/List;
    flags: (0x0001) ACC_PUBLIC
    Code:
      stack=1, locals=4, args_size=4
         0: aload_3
         1: areturn
      LineNumberTable:
        line 62: 0
      LocalVariableTable:
        Start  Length  Slot  Name   Signature
            0       2     0  this   Lcom/fasterxml/jackson/databind/deser/BeanDeserializerModifier;
            0       2     1 config   Lcom/fasterxml/jackson/databind/DeserializationConfig;
            0       2     2 beanDesc   Lcom/fasterxml/jackson/databind/BeanDescription;
            0       2     3 propDefs   Ljava/util/List;
      LocalVariableTypeTable:
        Start  Length  Slot  Name   Signature
            0       2     3 propDefs   Ljava/util/List<Lcom/fasterxml/jackson/databind/introspect/BeanPropertyDefinition;>;
    Signature: #22                          // (Lcom/fasterxml/jackson/databind/DeserializationConfig;Lcom/fasterxml/jackson/databind/BeanDescription;Ljava/util/List<Lcom/fasterxml/jackson/databind/introspect/BeanPropertyDefinition;>;)Ljava/util/List<Lcom/fasterxml/jackson/databind/introspect/BeanPropertyDefinition;>;

  public com.fasterxml.jackson.databind.deser.BeanDeserializerBuilder updateBuilder(com.fasterxml.jackson.databind.DeserializationConfig, com.fasterxml.jackson.databind.BeanDescription, com.fasterxml.jackson.databind.deser.BeanDeserializerBuilder);
    descriptor: (Lcom/fasterxml/jackson/databind/DeserializationConfig;Lcom/fasterxml/jackson/databind/BeanDescription;Lcom/fasterxml/jackson/databind/deser/BeanDeserializerBuilder;)Lcom/fasterxml/jackson/databind/deser/BeanDeserializerBuilder;
    flags: (0x0001) ACC_PUBLIC
    Code:
      stack=1, locals=4, args_size=4
         0: aload_3
         1: areturn
      LineNumberTable:
        line 75: 0
      LocalVariableTable:
        Start  Length  Slot  Name   Signature
            0       2     0  this   Lcom/fasterxml/jackson/databind/deser/BeanDeserializerModifier;
            0       2     1 config   Lcom/fasterxml/jackson/databind/DeserializationConfig;
            0       2     2 beanDesc   Lcom/fasterxml/jackson/databind/BeanDescription;
            0       2     3 builder   Lcom/fasterxml/jackson/databind/deser/BeanDeserializerBuilder;

  public com.fasterxml.jackson.databind.JsonDeserializer<?> modifyDeserializer(com.fasterxml.jackson.databind.DeserializationConfig, com.fasterxml.jackson.databind.BeanDescription, com.fasterxml.jackson.databind.JsonDeserializer<?>);
    descriptor: (Lcom/fasterxml/jackson/databind/DeserializationConfig;Lcom/fasterxml/jackson/databind/BeanDescription;Lcom/fasterxml/jackson/databind/JsonDeserializer;)Lcom/fasterxml/jackson/databind/JsonDeserializer;
    flags: (0x0001) ACC_PUBLIC
    Code:
      stack=1, locals=4, args_size=4
         0: aload_3
         1: areturn
      LineNumberTable:
        line 92: 0
      LocalVariableTable:
        Start  Length  Slot  Name   Signature
            0       2     0  this   Lcom/fasterxml/jackson/databind/deser/BeanDeserializerModifier;
            0       2     1 config   Lcom/fasterxml/jackson/databind/DeserializationConfig;
            0       2     2 beanDesc   Lcom/fasterxml/jackson/databind/BeanDescription;
            0       2     3 deserializer   Lcom/fasterxml/jackson/databind/JsonDeserializer;
      LocalVariableTypeTable:
        Start  Length  Slot  Name   Signature
            0       2     3 deserializer   Lcom/fasterxml/jackson/databind/JsonDeserializer<*>;
    Signature: #32                          // (Lcom/fasterxml/jackson/databind/DeserializationConfig;Lcom/fasterxml/jackson/databind/BeanDescription;Lcom/fasterxml/jackson/databind/JsonDeserializer<*>;)Lcom/fasterxml/jackson/databind/JsonDeserializer<*>;

  public com.fasterxml.jackson.databind.JsonDeserializer<?> modifyEnumDeserializer(com.fasterxml.jackson.databind.DeserializationConfig, com.fasterxml.jackson.databind.JavaType, com.fasterxml.jackson.databind.BeanDescription, com.fasterxml.jackson.databind.JsonDeserializer<?>);
    descriptor: (Lcom/fasterxml/jackson/databind/DeserializationConfig;Lcom/fasterxml/jackson/databind/JavaType;Lcom/fasterxml/jackson/databind/BeanDescription;Lcom/fasterxml/jackson/databind/JsonDeserializer;)Lcom/fasterxml/jackson/databind/JsonDeserializer;
    flags: (0x0001) ACC_PUBLIC
    Code:
      stack=1, locals=5, args_size=5
         0: aload         4
         2: areturn
      LineNumberTable:
        line 109: 0
      LocalVariableTable:
        Start  Length  Slot  Name   Signature
            0       3     0  this   Lcom/fasterxml/jackson/databind/deser/BeanDeserializerModifier;
            0       3     1 config   Lcom/fasterxml/jackson/databind/DeserializationConfig;
            0       3     2  type   Lcom/fasterxml/jackson/databind/JavaType;
            0       3     3 beanDesc   Lcom/fasterxml/jackson/databind/BeanDescription;
            0       3     4 deserializer   Lcom/fasterxml/jackson/databind/JsonDeserializer;
      LocalVariableTypeTable:
        Start  Length  Slot  Name   Signature
            0       3     4 deserializer   Lcom/fasterxml/jackson/databind/JsonDeserializer<*>;
    Signature: #37                          // (Lcom/fasterxml/jackson/databind/DeserializationConfig;Lcom/fasterxml/jackson/databind/JavaType;Lcom/fasterxml/jackson/databind/BeanDescription;Lcom/fasterxml/jackson/databind/JsonDeserializer<*>;)Lcom/fasterxml/jackson/databind/JsonDeserializer<*>;

  public com.fasterxml.jackson.databind.JsonDeserializer<?> modifyReferenceDeserializer(com.fasterxml.jackson.databind.DeserializationConfig, com.fasterxml.jackson.databind.type.ReferenceType, com.fasterxml.jackson.databind.BeanDescription, com.fasterxml.jackson.databind.JsonDeserializer<?>);
    descriptor: (Lcom/fasterxml/jackson/databind/DeserializationConfig;Lcom/fasterxml/jackson/databind/type/ReferenceType;Lcom/fasterxml/jackson/databind/BeanDescription;Lcom/fasterxml/jackson/databind/JsonDeserializer;)Lcom/fasterxml/jackson/databind/JsonDeserializer;
    flags: (0x0001) ACC_PUBLIC
    Code:
      stack=1, locals=5, args_size=5
         0: aload         4
         2: areturn
      LineNumberTable:
        line 120: 0
      LocalVariableTable:
        Start  Length  Slot  Name   Signature
            0       3     0  this   Lcom/fasterxml/jackson/databind/deser/BeanDeserializerModifier;
            0       3     1 config   Lcom/fasterxml/jackson/databind/DeserializationConfig;
            0       3     2  type   Lcom/fasterxml/jackson/databind/type/ReferenceType;
            0       3     3 beanDesc   Lcom/fasterxml/jackson/databind/BeanDescription;
            0       3     4 deserializer   Lcom/fasterxml/jackson/databind/JsonDeserializer;
      LocalVariableTypeTable:
        Start  Length  Slot  Name   Signature
            0       3     4 deserializer   Lcom/fasterxml/jackson/databind/JsonDeserializer<*>;
    Signature: #41                          // (Lcom/fasterxml/jackson/databind/DeserializationConfig;Lcom/fasterxml/jackson/databind/type/ReferenceType;Lcom/fasterxml/jackson/databind/BeanDescription;Lcom/fasterxml/jackson/databind/JsonDeserializer<*>;)Lcom/fasterxml/jackson/databind/JsonDeserializer<*>;

  public com.fasterxml.jackson.databind.JsonDeserializer<?> modifyArrayDeserializer(com.fasterxml.jackson.databind.DeserializationConfig, com.fasterxml.jackson.databind.type.ArrayType, com.fasterxml.jackson.databind.BeanDescription, com.fasterxml.jackson.databind.JsonDeserializer<?>);
    descriptor: (Lcom/fasterxml/jackson/databind/DeserializationConfig;Lcom/fasterxml/jackson/databind/type/ArrayType;Lcom/fasterxml/jackson/databind/BeanDescription;Lcom/fasterxml/jackson/databind/JsonDeserializer;)Lcom/fasterxml/jackson/databind/JsonDeserializer;
    flags: (0x0001) ACC_PUBLIC
    Code:
      stack=1, locals=5, args_size=5
         0: aload         4
         2: areturn
      LineNumberTable:
        line 142: 0
      LocalVariableTable:
        Start  Length  Slot  Name   Signature
            0       3     0  this   Lcom/fasterxml/jackson/databind/deser/BeanDeserializerModifier;
            0       3     1 config   Lcom/fasterxml/jackson/databind/DeserializationConfig;
            0       3     2 valueType   Lcom/fasterxml/jackson/databind/type/ArrayType;
            0       3     3 beanDesc   Lcom/fasterxml/jackson/databind/BeanDescription;
            0       3     4 deserializer   Lcom/fasterxml/jackson/databind/JsonDeserializer;
      LocalVariableTypeTable:
        Start  Length  Slot  Name   Signature
            0       3     4 deserializer   Lcom/fasterxml/jackson/databind/JsonDeserializer<*>;
    Signature: #46                          // (Lcom/fasterxml/jackson/databind/DeserializationConfig;Lcom/fasterxml/jackson/databind/type/ArrayType;Lcom/fasterxml/jackson/databind/BeanDescription;Lcom/fasterxml/jackson/databind/JsonDeserializer<*>;)Lcom/fasterxml/jackson/databind/JsonDeserializer<*>;

  public com.fasterxml.jackson.databind.JsonDeserializer<?> modifyCollectionDeserializer(com.fasterxml.jackson.databind.DeserializationConfig, com.fasterxml.jackson.databind.type.CollectionType, com.fasterxml.jackson.databind.BeanDescription, com.fasterxml.jackson.databind.JsonDeserializer<?>);
    descriptor: (Lcom/fasterxml/jackson/databind/DeserializationConfig;Lcom/fasterxml/jackson/databind/type/CollectionType;Lcom/fasterxml/jackson/databind/BeanDescription;Lcom/fasterxml/jackson/databind/JsonDeserializer;)Lcom/fasterxml/jackson/databind/JsonDeserializer;
    flags: (0x0001) ACC_PUBLIC
    Code:
      stack=1, locals=5, args_size=5
         0: aload         4
         2: areturn
      LineNumberTable:
        line 153: 0
      LocalVariableTable:
        Start  Length  Slot  Name   Signature
            0       3     0  this   Lcom/fasterxml/jackson/databind/deser/BeanDeserializerModifier;
            0       3     1 config   Lcom/fasterxml/jackson/databind/DeserializationConfig;
            0       3     2  type   Lcom/fasterxml/jackson/databind/type/CollectionType;
            0       3     3 beanDesc   Lcom/fasterxml/jackson/databind/BeanDescription;
            0       3     4 deserializer   Lcom/fasterxml/jackson/databind/JsonDeserializer;
      LocalVariableTypeTable:
        Start  Length  Slot  Name   Signature
            0       3     4 deserializer   Lcom/fasterxml/jackson/databind/JsonDeserializer<*>;
    Signature: #50                          // (Lcom/fasterxml/jackson/databind/DeserializationConfig;Lcom/fasterxml/jackson/databind/type/CollectionType;Lcom/fasterxml/jackson/databind/BeanDescription;Lcom/fasterxml/jackson/databind/JsonDeserializer<*>;)Lcom/fasterxml/jackson/databind/JsonDeserializer<*>;

  public com.fasterxml.jackson.databind.JsonDeserializer<?> modifyCollectionLikeDeserializer(com.fasterxml.jackson.databind.DeserializationConfig, com.fasterxml.jackson.databind.type.CollectionLikeType, com.fasterxml.jackson.databind.BeanDescription, com.fasterxml.jackson.databind.JsonDeserializer<?>);
    descriptor: (Lcom/fasterxml/jackson/databind/DeserializationConfig;Lcom/fasterxml/jackson/databind/type/CollectionLikeType;Lcom/fasterxml/jackson/databind/BeanDescription;Lcom/fasterxml/jackson/databind/JsonDeserializer;)Lcom/fasterxml/jackson/databind/JsonDeserializer;
    flags: (0x0001) ACC_PUBLIC
    Code:
      stack=1, locals=5, args_size=5
         0: aload         4
         2: areturn
      LineNumberTable:
        line 164: 0
      LocalVariableTable:
        Start  Length  Slot  Name   Signature
            0       3     0  this   Lcom/fasterxml/jackson/databind/deser/BeanDeserializerModifier;
            0       3     1 config   Lcom/fasterxml/jackson/databind/DeserializationConfig;
            0       3     2  type   Lcom/fasterxml/jackson/databind/type/CollectionLikeType;
            0       3     3 beanDesc   Lcom/fasterxml/jackson/databind/BeanDescription;
            0       3     4 deserializer   Lcom/fasterxml/jackson/databind/JsonDeserializer;
      LocalVariableTypeTable:
        Start  Length  Slot  Name   Signature
            0       3     4 deserializer   Lcom/fasterxml/jackson/databind/JsonDeserializer<*>;
    Signature: #54                          // (Lcom/fasterxml/jackson/databind/DeserializationConfig;Lcom/fasterxml/jackson/databind/type/CollectionLikeType;Lcom/fasterxml/jackson/databind/BeanDescription;Lcom/fasterxml/jackson/databind/JsonDeserializer<*>;)Lcom/fasterxml/jackson/databind/JsonDeserializer<*>;

  public com.fasterxml.jackson.databind.JsonDeserializer<?> modifyMapDeserializer(com.fasterxml.jackson.databind.DeserializationConfig, com.fasterxml.jackson.databind.type.MapType, com.fasterxml.jackson.databind.BeanDescription, com.fasterxml.jackson.databind.JsonDeserializer<?>);
    descriptor: (Lcom/fasterxml/jackson/databind/DeserializationConfig;Lcom/fasterxml/jackson/databind/type/MapType;Lcom/fasterxml/jackson/databind/BeanDescription;Lcom/fasterxml/jackson/databind/JsonDeserializer;)Lcom/fasterxml/jackson/databind/JsonDeserializer;
    flags: (0x0001) ACC_PUBLIC
    Code:
      stack=1, locals=5, args_size=5
         0: aload         4
         2: areturn
      LineNumberTable:
        line 175: 0
      LocalVariableTable:
        Start  Length  Slot  Name   Signature
            0       3     0  this   Lcom/fasterxml/jackson/databind/deser/BeanDeserializerModifier;
            0       3     1 config   Lcom/fasterxml/jackson/databind/DeserializationConfig;
            0       3     2  type   Lcom/fasterxml/jackson/databind/type/MapType;
            0       3     3 beanDesc   Lcom/fasterxml/jackson/databind/BeanDescription;
            0       3     4 deserializer   Lcom/fasterxml/jackson/databind/JsonDeserializer;
      LocalVariableTypeTable:
        Start  Length  Slot  Name   Signature
            0       3     4 deserializer   Lcom/fasterxml/jackson/databind/JsonDeserializer<*>;
    Signature: #58                          // (Lcom/fasterxml/jackson/databind/DeserializationConfig;Lcom/fasterxml/jackson/databind/type/MapType;Lcom/fasterxml/jackson/databind/BeanDescription;Lcom/fasterxml/jackson/databind/JsonDeserializer<*>;)Lcom/fasterxml/jackson/databind/JsonDeserializer<*>;

  public com.fasterxml.jackson.databind.JsonDeserializer<?> modifyMapLikeDeserializer(com.fasterxml.jackson.databind.DeserializationConfig, com.fasterxml.jackson.databind.type.MapLikeType, com.fasterxml.jackson.databind.BeanDescription, com.fasterxml.jackson.databind.JsonDeserializer<?>);
    descriptor: (Lcom/fasterxml/jackson/databind/DeserializationConfig;Lcom/fasterxml/jackson/databind/type/MapLikeType;Lcom/fasterxml/jackson/databind/BeanDescription;Lcom/fasterxml/jackson/databind/JsonDeserializer;)Lcom/fasterxml/jackson/databind/JsonDeserializer;
    flags: (0x0001) ACC_PUBLIC
    Code:
      stack=1, locals=5, args_size=5
         0: aload         4
         2: areturn
      LineNumberTable:
        line 186: 0
      LocalVariableTable:
        Start  Length  Slot  Name   Signature
            0       3     0  this   Lcom/fasterxml/jackson/databind/deser/BeanDeserializerModifier;
            0       3     1 config   Lcom/fasterxml/jackson/databind/DeserializationConfig;
            0       3     2  type   Lcom/fasterxml/jackson/databind/type/MapLikeType;
            0       3     3 beanDesc   Lcom/fasterxml/jackson/databind/BeanDescription;
            0       3     4 deserializer   Lcom/fasterxml/jackson/databind/JsonDeserializer;
      LocalVariableTypeTable:
        Start  Length  Slot  Name   Signature
            0       3     4 deserializer   Lcom/fasterxml/jackson/databind/JsonDeserializer<*>;
    Signature: #62                          // (Lcom/fasterxml/jackson/databind/DeserializationConfig;Lcom/fasterxml/jackson/databind/type/MapLikeType;Lcom/fasterxml/jackson/databind/BeanDescription;Lcom/fasterxml/jackson/databind/JsonDeserializer<*>;)Lcom/fasterxml/jackson/databind/JsonDeserializer<*>;

  public com.fasterxml.jackson.databind.KeyDeserializer modifyKeyDeserializer(com.fasterxml.jackson.databind.DeserializationConfig, com.fasterxml.jackson.databind.JavaType, com.fasterxml.jackson.databind.KeyDeserializer);
    descriptor: (Lcom/fasterxml/jackson/databind/DeserializationConfig;Lcom/fasterxml/jackson/databind/JavaType;Lcom/fasterxml/jackson/databind/KeyDeserializer;)Lcom/fasterxml/jackson/databind/KeyDeserializer;
    flags: (0x0001) ACC_PUBLIC
    Code:
      stack=1, locals=4, args_size=4
         0: aload_3
         1: areturn
      LineNumberTable:
        line 200: 0
      LocalVariableTable:
        Start  Length  Slot  Name   Signature
            0       2     0  this   Lcom/fasterxml/jackson/databind/deser/BeanDeserializerModifier;
            0       2     1 config   Lcom/fasterxml/jackson/databind/DeserializationConfig;
            0       2     2  type   Lcom/fasterxml/jackson/databind/JavaType;
            0       2     3 deserializer   Lcom/fasterxml/jackson/databind/KeyDeserializer;
}
SourceFile: "BeanDeserializerModifier.java"
