Classfile /Users/mw/Projects/slang-braindump/.jar/jar8/assemble/slang-braindump/assemble/content/com/fasterxml/jackson/databind/deser/ValueInstantiators$Base.class
  Last modified May 29, 2022; size 1004 bytes
  SHA-256 checksum 07be409207218cfab176a809669707995728ea1eff07a55796ec6dd67becb92c
  Compiled from "ValueInstantiators.java"
public class com.fasterxml.jackson.databind.deser.ValueInstantiators$Base implements com.fasterxml.jackson.databind.deser.ValueInstantiators
  minor version: 0
  major version: 52
  flags: (0x0021) ACC_PUBLIC, ACC_SUPER
  this_class: #2                          // com/fasterxml/jackson/databind/deser/ValueInstantiators$Base
  super_class: #3                         // java/lang/Object
  interfaces: 1, fields: 0, methods: 2, attributes: 2
Constant pool:
   #1 = Methodref          #3.#24         // java/lang/Object."<init>":()V
   #2 = Class              #25            // com/fasterxml/jackson/databind/deser/ValueInstantiators$Base
   #3 = Class              #26            // java/lang/Object
   #4 = Class              #27            // com/fasterxml/jackson/databind/deser/ValueInstantiators
   #5 = Utf8               <init>
   #6 = Utf8               ()V
   #7 = Utf8               Code
   #8 = Utf8               LineNumberTable
   #9 = Utf8               LocalVariableTable
  #10 = Utf8               this
  #11 = Utf8               Base
  #12 = Utf8               InnerClasses
  #13 = Utf8               Lcom/fasterxml/jackson/databind/deser/ValueInstantiators$Base;
  #14 = Utf8               findValueInstantiator
  #15 = Utf8               (Lcom/fasterxml/jackson/databind/DeserializationConfig;Lcom/fasterxml/jackson/databind/BeanDescription;Lcom/fasterxml/jackson/databind/deser/ValueInstantiator;)Lcom/fasterxml/jackson/databind/deser/ValueInstantiator;
  #16 = Utf8               config
  #17 = Utf8               Lcom/fasterxml/jackson/databind/DeserializationConfig;
  #18 = Utf8               beanDesc
  #19 = Utf8               Lcom/fasterxml/jackson/databind/BeanDescription;
  #20 = Utf8               defaultInstantiator
  #21 = Utf8               Lcom/fasterxml/jackson/databind/deser/ValueInstantiator;
  #22 = Utf8               SourceFile
  #23 = Utf8               ValueInstantiators.java
  #24 = NameAndType        #5:#6          // "<init>":()V
  #25 = Utf8               com/fasterxml/jackson/databind/deser/ValueInstantiators$Base
  #26 = Utf8               java/lang/Object
  #27 = Utf8               com/fasterxml/jackson/databind/deser/ValueInstantiators
{
  public com.fasterxml.jackson.databind.deser.ValueInstantiators$Base();
    descriptor: ()V
    flags: (0x0001) ACC_PUBLIC
    Code:
      stack=1, locals=1, args_size=1
         0: aload_0
         1: invokespecial #1                  // Method java/lang/Object."<init>":()V
         4: return
      LineNumberTable:
        line 39: 0
      LocalVariableTable:
        Start  Length  Slot  Name   Signature
            0       5     0  this   Lcom/fasterxml/jackson/databind/deser/ValueInstantiators$Base;

  public com.fasterxml.jackson.databind.deser.ValueInstantiator findValueInstantiator(com.fasterxml.jackson.databind.DeserializationConfig, com.fasterxml.jackson.databind.BeanDescription, com.fasterxml.jackson.databind.deser.ValueInstantiator);
    descriptor: (Lcom/fasterxml/jackson/databind/DeserializationConfig;Lcom/fasterxml/jackson/databind/BeanDescription;Lcom/fasterxml/jackson/databind/deser/ValueInstantiator;)Lcom/fasterxml/jackson/databind/deser/ValueInstantiator;
    flags: (0x0001) ACC_PUBLIC
    Code:
      stack=1, locals=4, args_size=4
         0: aload_3
         1: areturn
      LineNumberTable:
        line 44: 0
      LocalVariableTable:
        Start  Length  Slot  Name   Signature
            0       2     0  this   Lcom/fasterxml/jackson/databind/deser/ValueInstantiators$Base;
            0       2     1 config   Lcom/fasterxml/jackson/databind/DeserializationConfig;
            0       2     2 beanDesc   Lcom/fasterxml/jackson/databind/BeanDescription;
            0       2     3 defaultInstantiator   Lcom/fasterxml/jackson/databind/deser/ValueInstantiator;
}
SourceFile: "ValueInstantiators.java"
InnerClasses:
  public static #11= #2 of #4;            // Base=class com/fasterxml/jackson/databind/deser/ValueInstantiators$Base of class com/fasterxml/jackson/databind/deser/ValueInstantiators
