Classfile /Users/mw/Projects/slang-braindump/.jar/jar11/assemble/slang-braindump/assemble/content/org/apache/commons/io/HexDump.class
  Last modified May 29, 2022; size 2742 bytes
  SHA-256 checksum 0ba47e709301ec561f6a99c4475a8b2761dbfccff19e5e739e315b7c7ffae50d
  Compiled from "HexDump.java"
public class org.apache.commons.io.HexDump
  minor version: 0
  major version: 52
  flags: (0x0021) ACC_PUBLIC, ACC_SUPER
  this_class: #29                         // org/apache/commons/io/HexDump
  super_class: #30                        // java/lang/Object
  interfaces: 0, fields: 3, methods: 5, attributes: 1
Constant pool:
    #1 = Methodref          #30.#73       // java/lang/Object."<init>":()V
    #2 = Class              #74           // java/lang/ArrayIndexOutOfBoundsException
    #3 = Class              #75           // java/lang/StringBuilder
    #4 = Methodref          #3.#73        // java/lang/StringBuilder."<init>":()V
    #5 = String             #76           // illegal index:
    #6 = Methodref          #3.#77        // java/lang/StringBuilder.append:(Ljava/lang/String;)Ljava/lang/StringBuilder;
    #7 = Methodref          #3.#78        // java/lang/StringBuilder.append:(I)Ljava/lang/StringBuilder;
    #8 = String             #79           //  into array of length
    #9 = Methodref          #3.#80        // java/lang/StringBuilder.toString:()Ljava/lang/String;
   #10 = Methodref          #2.#81        // java/lang/ArrayIndexOutOfBoundsException."<init>":(Ljava/lang/String;)V
   #11 = Class              #82           // java/lang/IllegalArgumentException
   #12 = String             #83           // cannot write to nullstream
   #13 = Methodref          #11.#81       // java/lang/IllegalArgumentException."<init>":(Ljava/lang/String;)V
   #14 = Methodref          #3.#84        // java/lang/StringBuilder."<init>":(I)V
   #15 = Methodref          #29.#85       // org/apache/commons/io/HexDump.dump:(Ljava/lang/StringBuilder;J)Ljava/lang/StringBuilder;
   #16 = Methodref          #3.#86        // java/lang/StringBuilder.append:(C)Ljava/lang/StringBuilder;
   #17 = Methodref          #29.#87       // org/apache/commons/io/HexDump.dump:(Ljava/lang/StringBuilder;B)Ljava/lang/StringBuilder;
   #18 = String             #88           //
   #19 = Fieldref           #29.#89       // org/apache/commons/io/HexDump.EOL:Ljava/lang/String;
   #20 = Methodref          #90.#91       // java/nio/charset/Charset.defaultCharset:()Ljava/nio/charset/Charset;
   #21 = Methodref          #92.#93       // java/lang/String.getBytes:(Ljava/nio/charset/Charset;)[B
   #22 = Methodref          #94.#95       // java/io/OutputStream.write:([B)V
   #23 = Methodref          #94.#96       // java/io/OutputStream.flush:()V
   #24 = Methodref          #3.#97        // java/lang/StringBuilder.setLength:(I)V
   #25 = Fieldref           #29.#98       // org/apache/commons/io/HexDump._hexcodes:[C
   #26 = Fieldref           #29.#99       // org/apache/commons/io/HexDump._shifts:[I
   #27 = String             #100          // line.separator
   #28 = Methodref          #101.#102     // java/lang/System.getProperty:(Ljava/lang/String;)Ljava/lang/String;
   #29 = Class              #103          // org/apache/commons/io/HexDump
   #30 = Class              #104          // java/lang/Object
   #31 = Utf8               EOL
   #32 = Utf8               Ljava/lang/String;
   #33 = Utf8               _hexcodes
   #34 = Utf8               [C
   #35 = Utf8               _shifts
   #36 = Utf8               [I
   #37 = Utf8               <init>
   #38 = Utf8               ()V
   #39 = Utf8               Code
   #40 = Utf8               LineNumberTable
   #41 = Utf8               LocalVariableTable
   #42 = Utf8               this
   #43 = Utf8               Lorg/apache/commons/io/HexDump;
   #44 = Utf8               dump
   #45 = Utf8               ([BJLjava/io/OutputStream;I)V
   #46 = Utf8               k
   #47 = Utf8               I
   #48 = Utf8               chars_read
   #49 = Utf8               j
   #50 = Utf8               data
   #51 = Utf8               [B
   #52 = Utf8               offset
   #53 = Utf8               J
   #54 = Utf8               stream
   #55 = Utf8               Ljava/io/OutputStream;
   #56 = Utf8               index
   #57 = Utf8               display_offset
   #58 = Utf8               buffer
   #59 = Utf8               Ljava/lang/StringBuilder;
   #60 = Utf8               StackMapTable
   #61 = Class              #75           // java/lang/StringBuilder
   #62 = Utf8               Exceptions
   #63 = Class              #105          // java/io/IOException
   #64 = Utf8               (Ljava/lang/StringBuilder;J)Ljava/lang/StringBuilder;
   #65 = Utf8               _lbuffer
   #66 = Utf8               value
   #67 = Utf8               (Ljava/lang/StringBuilder;B)Ljava/lang/StringBuilder;
   #68 = Utf8               _cbuffer
   #69 = Utf8               B
   #70 = Utf8               <clinit>
   #71 = Utf8               SourceFile
   #72 = Utf8               HexDump.java
   #73 = NameAndType        #37:#38       // "<init>":()V
   #74 = Utf8               java/lang/ArrayIndexOutOfBoundsException
   #75 = Utf8               java/lang/StringBuilder
   #76 = Utf8               illegal index:
   #77 = NameAndType        #106:#107     // append:(Ljava/lang/String;)Ljava/lang/StringBuilder;
   #78 = NameAndType        #106:#108     // append:(I)Ljava/lang/StringBuilder;
   #79 = Utf8                into array of length
   #80 = NameAndType        #109:#110     // toString:()Ljava/lang/String;
   #81 = NameAndType        #37:#111      // "<init>":(Ljava/lang/String;)V
   #82 = Utf8               java/lang/IllegalArgumentException
   #83 = Utf8               cannot write to nullstream
   #84 = NameAndType        #37:#112      // "<init>":(I)V
   #85 = NameAndType        #44:#64       // dump:(Ljava/lang/StringBuilder;J)Ljava/lang/StringBuilder;
   #86 = NameAndType        #106:#113     // append:(C)Ljava/lang/StringBuilder;
   #87 = NameAndType        #44:#67       // dump:(Ljava/lang/StringBuilder;B)Ljava/lang/StringBuilder;
   #88 = Utf8
   #89 = NameAndType        #31:#32       // EOL:Ljava/lang/String;
   #90 = Class              #114          // java/nio/charset/Charset
   #91 = NameAndType        #115:#116     // defaultCharset:()Ljava/nio/charset/Charset;
   #92 = Class              #117          // java/lang/String
   #93 = NameAndType        #118:#119     // getBytes:(Ljava/nio/charset/Charset;)[B
   #94 = Class              #120          // java/io/OutputStream
   #95 = NameAndType        #121:#122     // write:([B)V
   #96 = NameAndType        #123:#38      // flush:()V
   #97 = NameAndType        #124:#112     // setLength:(I)V
   #98 = NameAndType        #33:#34       // _hexcodes:[C
   #99 = NameAndType        #35:#36       // _shifts:[I
  #100 = Utf8               line.separator
  #101 = Class              #125          // java/lang/System
  #102 = NameAndType        #126:#127     // getProperty:(Ljava/lang/String;)Ljava/lang/String;
  #103 = Utf8               org/apache/commons/io/HexDump
  #104 = Utf8               java/lang/Object
  #105 = Utf8               java/io/IOException
  #106 = Utf8               append
  #107 = Utf8               (Ljava/lang/String;)Ljava/lang/StringBuilder;
  #108 = Utf8               (I)Ljava/lang/StringBuilder;
  #109 = Utf8               toString
  #110 = Utf8               ()Ljava/lang/String;
  #111 = Utf8               (Ljava/lang/String;)V
  #112 = Utf8               (I)V
  #113 = Utf8               (C)Ljava/lang/StringBuilder;
  #114 = Utf8               java/nio/charset/Charset
  #115 = Utf8               defaultCharset
  #116 = Utf8               ()Ljava/nio/charset/Charset;
  #117 = Utf8               java/lang/String
  #118 = Utf8               getBytes
  #119 = Utf8               (Ljava/nio/charset/Charset;)[B
  #120 = Utf8               java/io/OutputStream
  #121 = Utf8               write
  #122 = Utf8               ([B)V
  #123 = Utf8               flush
  #124 = Utf8               setLength
  #125 = Utf8               java/lang/System
  #126 = Utf8               getProperty
  #127 = Utf8               (Ljava/lang/String;)Ljava/lang/String;
{
  public static final java.lang.String EOL;
    descriptor: Ljava/lang/String;
    flags: (0x0019) ACC_PUBLIC, ACC_STATIC, ACC_FINAL

  private static final char[] _hexcodes;
    descriptor: [C
    flags: (0x001a) ACC_PRIVATE, ACC_STATIC, ACC_FINAL

  private static final int[] _shifts;
    descriptor: [I
    flags: (0x001a) ACC_PRIVATE, ACC_STATIC, ACC_FINAL

  public org.apache.commons.io.HexDump();
    descriptor: ()V
    flags: (0x0001) ACC_PUBLIC
    Code:
      stack=1, locals=1, args_size=1
         0: aload_0
         1: invokespecial #1                  // Method java/lang/Object."<init>":()V
         4: return
      LineNumberTable:
        line 38: 0
        line 39: 4
      LocalVariableTable:
        Start  Length  Slot  Name   Signature
            0       5     0  this   Lorg/apache/commons/io/HexDump;

  public static void dump(byte[], long, java.io.OutputStream, int) throws java.io.IOException, java.lang.ArrayIndexOutOfBoundsException, java.lang.IllegalArgumentException;
    descriptor: ([BJLjava/io/OutputStream;I)V
    flags: (0x0009) ACC_PUBLIC, ACC_STATIC
    Code:
      stack=4, locals=11, args_size=4
         0: iload         4
         2: iflt          12
         5: iload         4
         7: aload_0
         8: arraylength
         9: if_icmplt     50
        12: new           #2                  // class java/lang/ArrayIndexOutOfBoundsException
        15: dup
        16: new           #3                  // class java/lang/StringBuilder
        19: dup
        20: invokespecial #4                  // Method java/lang/StringBuilder."<init>":()V
        23: ldc           #5                  // String illegal index:
        25: invokevirtual #6                  // Method java/lang/StringBuilder.append:(Ljava/lang/String;)Ljava/lang/StringBuilder;
        28: iload         4
        30: invokevirtual #7                  // Method java/lang/StringBuilder.append:(I)Ljava/lang/StringBuilder;
        33: ldc           #8                  // String  into array of length
        35: invokevirtual #6                  // Method java/lang/StringBuilder.append:(Ljava/lang/String;)Ljava/lang/StringBuilder;
        38: aload_0
        39: arraylength
        40: invokevirtual #7                  // Method java/lang/StringBuilder.append:(I)Ljava/lang/StringBuilder;
        43: invokevirtual #9                  // Method java/lang/StringBuilder.toString:()Ljava/lang/String;
        46: invokespecial #10                 // Method java/lang/ArrayIndexOutOfBoundsException."<init>":(Ljava/lang/String;)V
        49: athrow
        50: aload_3
        51: ifnonnull     64
        54: new           #11                 // class java/lang/IllegalArgumentException
        57: dup
        58: ldc           #12                 // String cannot write to nullstream
        60: invokespecial #13                 // Method java/lang/IllegalArgumentException."<init>":(Ljava/lang/String;)V
        63: athrow
        64: lload_1
        65: iload         4
        67: i2l
        68: ladd
        69: lstore        5
        71: new           #3                  // class java/lang/StringBuilder
        74: dup
        75: bipush        74
        77: invokespecial #14                 // Method java/lang/StringBuilder."<init>":(I)V
        80: astore        7
        82: iload         4
        84: istore        8
        86: iload         8
        88: aload_0
        89: arraylength
        90: if_icmpge     292
        93: aload_0
        94: arraylength
        95: iload         8
        97: isub
        98: istore        9
       100: iload         9
       102: bipush        16
       104: if_icmple     111
       107: bipush        16
       109: istore        9
       111: aload         7
       113: lload         5
       115: invokestatic  #15                 // Method dump:(Ljava/lang/StringBuilder;J)Ljava/lang/StringBuilder;
       118: bipush        32
       120: invokevirtual #16                 // Method java/lang/StringBuilder.append:(C)Ljava/lang/StringBuilder;
       123: pop
       124: iconst_0
       125: istore        10
       127: iload         10
       129: bipush        16
       131: if_icmpge     179
       134: iload         10
       136: iload         9
       138: if_icmpge     157
       141: aload         7
       143: aload_0
       144: iload         10
       146: iload         8
       148: iadd
       149: baload
       150: invokestatic  #17                 // Method dump:(Ljava/lang/StringBuilder;B)Ljava/lang/StringBuilder;
       153: pop
       154: goto          165
       157: aload         7
       159: ldc           #18                 // String
       161: invokevirtual #6                  // Method java/lang/StringBuilder.append:(Ljava/lang/String;)Ljava/lang/StringBuilder;
       164: pop
       165: aload         7
       167: bipush        32
       169: invokevirtual #16                 // Method java/lang/StringBuilder.append:(C)Ljava/lang/StringBuilder;
       172: pop
       173: iinc          10, 1
       176: goto          127
       179: iconst_0
       180: istore        10
       182: iload         10
       184: iload         9
       186: if_icmpge     244
       189: aload_0
       190: iload         10
       192: iload         8
       194: iadd
       195: baload
       196: bipush        32
       198: if_icmplt     230
       201: aload_0
       202: iload         10
       204: iload         8
       206: iadd
       207: baload
       208: bipush        127
       210: if_icmpge     230
       213: aload         7
       215: aload_0
       216: iload         10
       218: iload         8
       220: iadd
       221: baload
       222: i2c
       223: invokevirtual #16                 // Method java/lang/StringBuilder.append:(C)Ljava/lang/StringBuilder;
       226: pop
       227: goto          238
       230: aload         7
       232: bipush        46
       234: invokevirtual #16                 // Method java/lang/StringBuilder.append:(C)Ljava/lang/StringBuilder;
       237: pop
       238: iinc          10, 1
       241: goto          182
       244: aload         7
       246: getstatic     #19                 // Field EOL:Ljava/lang/String;
       249: invokevirtual #6                  // Method java/lang/StringBuilder.append:(Ljava/lang/String;)Ljava/lang/StringBuilder;
       252: pop
       253: aload_3
       254: aload         7
       256: invokevirtual #9                  // Method java/lang/StringBuilder.toString:()Ljava/lang/String;
       259: invokestatic  #20                 // Method java/nio/charset/Charset.defaultCharset:()Ljava/nio/charset/Charset;
       262: invokevirtual #21                 // Method java/lang/String.getBytes:(Ljava/nio/charset/Charset;)[B
       265: invokevirtual #22                 // Method java/io/OutputStream.write:([B)V
       268: aload_3
       269: invokevirtual #23                 // Method java/io/OutputStream.flush:()V
       272: aload         7
       274: iconst_0
       275: invokevirtual #24                 // Method java/lang/StringBuilder.setLength:(I)V
       278: lload         5
       280: iload         9
       282: i2l
       283: ladd
       284: lstore        5
       286: iinc          8, 16
       289: goto          86
       292: return
      LineNumberTable:
        line 76: 0
        line 77: 12
        line 81: 50
        line 82: 54
        line 84: 64
        line 85: 71
        line 87: 82
        line 88: 93
        line 90: 100
        line 91: 107
        line 93: 111
        line 94: 124
        line 95: 134
        line 96: 141
        line 98: 157
        line 100: 165
        line 94: 173
        line 102: 179
        line 103: 189
        line 104: 213
        line 106: 230
        line 102: 238
        line 109: 244
        line 111: 253
        line 112: 268
        line 113: 272
        line 114: 278
        line 87: 286
        line 116: 292
      LocalVariableTable:
        Start  Length  Slot  Name   Signature
          127      52    10     k   I
          182      62    10     k   I
          100     186     9 chars_read   I
           86     206     8     j   I
            0     293     0  data   [B
            0     293     1 offset   J
            0     293     3 stream   Ljava/io/OutputStream;
            0     293     4 index   I
           71     222     5 display_offset   J
           82     211     7 buffer   Ljava/lang/StringBuilder;
      StackMapTable: number_of_entries = 14
        frame_type = 12 /* same */
        frame_type = 37 /* same */
        frame_type = 13 /* same */
        frame_type = 254 /* append */
          offset_delta = 21
          locals = [ long, class java/lang/StringBuilder, int ]
        frame_type = 252 /* append */
          offset_delta = 24
          locals = [ int ]
        frame_type = 252 /* append */
          offset_delta = 15
          locals = [ int ]
        frame_type = 29 /* same */
        frame_type = 7 /* same */
        frame_type = 250 /* chop */
          offset_delta = 13
        frame_type = 252 /* append */
          offset_delta = 2
          locals = [ int ]
        frame_type = 47 /* same */
        frame_type = 7 /* same */
        frame_type = 250 /* chop */
          offset_delta = 5
        frame_type = 249 /* chop */
          offset_delta = 47
    Exceptions:
      throws java.io.IOException, java.lang.ArrayIndexOutOfBoundsException, java.lang.IllegalArgumentException

  private static java.lang.StringBuilder dump(java.lang.StringBuilder, long);
    descriptor: (Ljava/lang/StringBuilder;J)Ljava/lang/StringBuilder;
    flags: (0x000a) ACC_PRIVATE, ACC_STATIC
    Code:
      stack=6, locals=4, args_size=2
         0: iconst_0
         1: istore_3
         2: iload_3
         3: bipush        8
         5: if_icmpge     34
         8: aload_0
         9: getstatic     #25                 // Field _hexcodes:[C
        12: lload_1
        13: getstatic     #26                 // Field _shifts:[I
        16: iload_3
        17: iaload
        18: lshr
        19: l2i
        20: bipush        15
        22: iand
        23: caload
        24: invokevirtual #16                 // Method java/lang/StringBuilder.append:(C)Ljava/lang/StringBuilder;
        27: pop
        28: iinc          3, 1
        31: goto          2
        34: aload_0
        35: areturn
      LineNumberTable:
        line 141: 0
        line 142: 8
        line 143: 24
        line 141: 28
        line 145: 34
      LocalVariableTable:
        Start  Length  Slot  Name   Signature
            2      32     3     j   I
            0      36     0 _lbuffer   Ljava/lang/StringBuilder;
            0      36     1 value   J
      StackMapTable: number_of_entries = 2
        frame_type = 252 /* append */
          offset_delta = 2
          locals = [ int ]
        frame_type = 250 /* chop */
          offset_delta = 31

  private static java.lang.StringBuilder dump(java.lang.StringBuilder, byte);
    descriptor: (Ljava/lang/StringBuilder;B)Ljava/lang/StringBuilder;
    flags: (0x000a) ACC_PRIVATE, ACC_STATIC
    Code:
      stack=6, locals=3, args_size=2
         0: iconst_0
         1: istore_2
         2: iload_2
         3: iconst_2
         4: if_icmpge     35
         7: aload_0
         8: getstatic     #25                 // Field _hexcodes:[C
        11: iload_1
        12: getstatic     #26                 // Field _shifts:[I
        15: iload_2
        16: bipush        6
        18: iadd
        19: iaload
        20: ishr
        21: bipush        15
        23: iand
        24: caload
        25: invokevirtual #16                 // Method java/lang/StringBuilder.append:(C)Ljava/lang/StringBuilder;
        28: pop
        29: iinc          2, 1
        32: goto          2
        35: aload_0
        36: areturn
      LineNumberTable:
        line 156: 0
        line 157: 7
        line 156: 29
        line 159: 35
      LocalVariableTable:
        Start  Length  Slot  Name   Signature
            2      33     2     j   I
            0      37     0 _cbuffer   Ljava/lang/StringBuilder;
            0      37     1 value   B
      StackMapTable: number_of_entries = 2
        frame_type = 252 /* append */
          offset_delta = 2
          locals = [ int ]
        frame_type = 250 /* chop */
          offset_delta = 32

  static {};
    descriptor: ()V
    flags: (0x0008) ACC_STATIC
    Code:
      stack=4, locals=0, args_size=0
         0: ldc           #27                 // String line.separator
         2: invokestatic  #28                 // Method java/lang/System.getProperty:(Ljava/lang/String;)Ljava/lang/String;
         5: putstatic     #19                 // Field EOL:Ljava/lang/String;
         8: bipush        16
        10: newarray       char
        12: dup
        13: iconst_0
        14: bipush        48
        16: castore
        17: dup
        18: iconst_1
        19: bipush        49
        21: castore
        22: dup
        23: iconst_2
        24: bipush        50
        26: castore
        27: dup
        28: iconst_3
        29: bipush        51
        31: castore
        32: dup
        33: iconst_4
        34: bipush        52
        36: castore
        37: dup
        38: iconst_5
        39: bipush        53
        41: castore
        42: dup
        43: bipush        6
        45: bipush        54
        47: castore
        48: dup
        49: bipush        7
        51: bipush        55
        53: castore
        54: dup
        55: bipush        8
        57: bipush        56
        59: castore
        60: dup
        61: bipush        9
        63: bipush        57
        65: castore
        66: dup
        67: bipush        10
        69: bipush        65
        71: castore
        72: dup
        73: bipush        11
        75: bipush        66
        77: castore
        78: dup
        79: bipush        12
        81: bipush        67
        83: castore
        84: dup
        85: bipush        13
        87: bipush        68
        89: castore
        90: dup
        91: bipush        14
        93: bipush        69
        95: castore
        96: dup
        97: bipush        15
        99: bipush        70
       101: castore
       102: putstatic     #25                 // Field _hexcodes:[C
       105: bipush        8
       107: newarray       int
       109: dup
       110: iconst_0
       111: bipush        28
       113: iastore
       114: dup
       115: iconst_1
       116: bipush        24
       118: iastore
       119: dup
       120: iconst_2
       121: bipush        20
       123: iastore
       124: dup
       125: iconst_3
       126: bipush        16
       128: iastore
       129: dup
       130: iconst_4
       131: bipush        12
       133: iastore
       134: dup
       135: iconst_5
       136: bipush        8
       138: iastore
       139: dup
       140: bipush        6
       142: iconst_4
       143: iastore
       144: dup
       145: bipush        7
       147: iconst_0
       148: iastore
       149: putstatic     #26                 // Field _shifts:[I
       152: return
      LineNumberTable:
        line 121: 0
        line 122: 2
        line 123: 8
        line 128: 105
}
SourceFile: "HexDump.java"
