Classfile /Users/mw/Projects/slang-braindump/.jar/jar8/assemble/slang-braindump/assemble/content/coursier/util/shaded/org/jsoup/parser/HtmlTreeBuilderState$9.class
  Last modified May 29, 2022; size 5212 bytes
  SHA-256 checksum 675518572dfe5e98624fe70330b6a1df7d7376143d20f335398f10300ee06c52
  Compiled from "HtmlTreeBuilderState.java"
final class coursier.util.shaded.org.jsoup.parser.HtmlTreeBuilderState$9 extends coursier.util.shaded.org.jsoup.parser.HtmlTreeBuilderState
  minor version: 0
  major version: 51
  flags: (0x4030) ACC_FINAL, ACC_SUPER, ACC_ENUM
  this_class: #2                          // coursier/util/shaded/org/jsoup/parser/HtmlTreeBuilderState$9
  super_class: #4                         // coursier/util/shaded/org/jsoup/parser/HtmlTreeBuilderState
  interfaces: 0, fields: 0, methods: 3, attributes: 3
Constant pool:
    #1 = Utf8               coursier/util/shaded/org/jsoup/parser/HtmlTreeBuilderState$9
    #2 = Class              #1            // coursier/util/shaded/org/jsoup/parser/HtmlTreeBuilderState$9
    #3 = Utf8               coursier/util/shaded/org/jsoup/parser/HtmlTreeBuilderState
    #4 = Class              #3            // coursier/util/shaded/org/jsoup/parser/HtmlTreeBuilderState
    #5 = Utf8               HtmlTreeBuilderState.java
    #6 = Utf8               coursier/util/shaded/org/jsoup/parser/HtmlTreeBuilderState$1
    #7 = Class              #6            // coursier/util/shaded/org/jsoup/parser/HtmlTreeBuilderState$1
    #8 = Utf8               coursier/util/shaded/org/jsoup/parser/Token$Comment
    #9 = Class              #8            // coursier/util/shaded/org/jsoup/parser/Token$Comment
   #10 = Utf8               coursier/util/shaded/org/jsoup/parser/Token
   #11 = Class              #10           // coursier/util/shaded/org/jsoup/parser/Token
   #12 = Utf8               Comment
   #13 = Utf8               coursier/util/shaded/org/jsoup/parser/Token$StartTag
   #14 = Class              #13           // coursier/util/shaded/org/jsoup/parser/Token$StartTag
   #15 = Utf8               StartTag
   #16 = Utf8               coursier/util/shaded/org/jsoup/parser/HtmlTreeBuilderState$Constants
   #17 = Class              #16           // coursier/util/shaded/org/jsoup/parser/HtmlTreeBuilderState$Constants
   #18 = Utf8               Constants
   #19 = Utf8               coursier/util/shaded/org/jsoup/parser/Token$EndTag
   #20 = Class              #19           // coursier/util/shaded/org/jsoup/parser/Token$EndTag
   #21 = Utf8               EndTag
   #22 = Utf8               <init>
   #23 = Utf8               (Ljava/lang/String;I)V
   #24 = Utf8               (Ljava/lang/String;ILcoursier/util/shaded/org/jsoup/parser/HtmlTreeBuilderState$1;)V
   #25 = NameAndType        #22:#24       // "<init>":(Ljava/lang/String;ILcoursier/util/shaded/org/jsoup/parser/HtmlTreeBuilderState$1;)V
   #26 = Methodref          #4.#25        // coursier/util/shaded/org/jsoup/parser/HtmlTreeBuilderState."<init>":(Ljava/lang/String;ILcoursier/util/shaded/org/jsoup/parser/HtmlTreeBuilderState$1;)V
   #27 = Utf8               this
   #28 = Utf8               Lcoursier/util/shaded/org/jsoup/parser/HtmlTreeBuilderState$9;
   #29 = Utf8               process
   #30 = Utf8               (Lcoursier/util/shaded/org/jsoup/parser/Token;Lcoursier/util/shaded/org/jsoup/parser/HtmlTreeBuilder;)Z
   #31 = Utf8               isCharacter
   #32 = Utf8               ()Z
   #33 = NameAndType        #31:#32       // isCharacter:()Z
   #34 = Methodref          #11.#33       // coursier/util/shaded/org/jsoup/parser/Token.isCharacter:()Z
   #35 = Utf8               coursier/util/shaded/org/jsoup/parser/HtmlTreeBuilder
   #36 = Class              #35           // coursier/util/shaded/org/jsoup/parser/HtmlTreeBuilder
   #37 = Utf8               newPendingTableCharacters
   #38 = Utf8               ()V
   #39 = NameAndType        #37:#38       // newPendingTableCharacters:()V
   #40 = Methodref          #36.#39       // coursier/util/shaded/org/jsoup/parser/HtmlTreeBuilder.newPendingTableCharacters:()V
   #41 = Utf8               markInsertionMode
   #42 = NameAndType        #41:#38       // markInsertionMode:()V
   #43 = Methodref          #36.#42       // coursier/util/shaded/org/jsoup/parser/HtmlTreeBuilder.markInsertionMode:()V
   #44 = Utf8               InTableText
   #45 = Utf8               Lcoursier/util/shaded/org/jsoup/parser/HtmlTreeBuilderState;
   #46 = NameAndType        #44:#45       // InTableText:Lcoursier/util/shaded/org/jsoup/parser/HtmlTreeBuilderState;
   #47 = Fieldref           #2.#46        // coursier/util/shaded/org/jsoup/parser/HtmlTreeBuilderState$9.InTableText:Lcoursier/util/shaded/org/jsoup/parser/HtmlTreeBuilderState;
   #48 = Utf8               transition
   #49 = Utf8               (Lcoursier/util/shaded/org/jsoup/parser/HtmlTreeBuilderState;)V
   #50 = NameAndType        #48:#49       // transition:(Lcoursier/util/shaded/org/jsoup/parser/HtmlTreeBuilderState;)V
   #51 = Methodref          #36.#50       // coursier/util/shaded/org/jsoup/parser/HtmlTreeBuilder.transition:(Lcoursier/util/shaded/org/jsoup/parser/HtmlTreeBuilderState;)V
   #52 = Utf8               (Lcoursier/util/shaded/org/jsoup/parser/Token;)Z
   #53 = NameAndType        #29:#52       // process:(Lcoursier/util/shaded/org/jsoup/parser/Token;)Z
   #54 = Methodref          #36.#53       // coursier/util/shaded/org/jsoup/parser/HtmlTreeBuilder.process:(Lcoursier/util/shaded/org/jsoup/parser/Token;)Z
   #55 = Utf8               isComment
   #56 = NameAndType        #55:#32       // isComment:()Z
   #57 = Methodref          #11.#56       // coursier/util/shaded/org/jsoup/parser/Token.isComment:()Z
   #58 = Utf8               asComment
   #59 = Utf8               ()Lcoursier/util/shaded/org/jsoup/parser/Token$Comment;
   #60 = NameAndType        #58:#59       // asComment:()Lcoursier/util/shaded/org/jsoup/parser/Token$Comment;
   #61 = Methodref          #11.#60       // coursier/util/shaded/org/jsoup/parser/Token.asComment:()Lcoursier/util/shaded/org/jsoup/parser/Token$Comment;
   #62 = Utf8               insert
   #63 = Utf8               (Lcoursier/util/shaded/org/jsoup/parser/Token$Comment;)V
   #64 = NameAndType        #62:#63       // insert:(Lcoursier/util/shaded/org/jsoup/parser/Token$Comment;)V
   #65 = Methodref          #36.#64       // coursier/util/shaded/org/jsoup/parser/HtmlTreeBuilder.insert:(Lcoursier/util/shaded/org/jsoup/parser/Token$Comment;)V
   #66 = Utf8               isDoctype
   #67 = NameAndType        #66:#32       // isDoctype:()Z
   #68 = Methodref          #11.#67       // coursier/util/shaded/org/jsoup/parser/Token.isDoctype:()Z
   #69 = Utf8               error
   #70 = NameAndType        #69:#49       // error:(Lcoursier/util/shaded/org/jsoup/parser/HtmlTreeBuilderState;)V
   #71 = Methodref          #36.#70       // coursier/util/shaded/org/jsoup/parser/HtmlTreeBuilder.error:(Lcoursier/util/shaded/org/jsoup/parser/HtmlTreeBuilderState;)V
   #72 = Utf8               isStartTag
   #73 = NameAndType        #72:#32       // isStartTag:()Z
   #74 = Methodref          #11.#73       // coursier/util/shaded/org/jsoup/parser/Token.isStartTag:()Z
   #75 = Utf8               asStartTag
   #76 = Utf8               ()Lcoursier/util/shaded/org/jsoup/parser/Token$StartTag;
   #77 = NameAndType        #75:#76       // asStartTag:()Lcoursier/util/shaded/org/jsoup/parser/Token$StartTag;
   #78 = Methodref          #11.#77       // coursier/util/shaded/org/jsoup/parser/Token.asStartTag:()Lcoursier/util/shaded/org/jsoup/parser/Token$StartTag;
   #79 = Utf8               normalName
   #80 = Utf8               ()Ljava/lang/String;
   #81 = NameAndType        #79:#80       // normalName:()Ljava/lang/String;
   #82 = Methodref          #14.#81       // coursier/util/shaded/org/jsoup/parser/Token$StartTag.normalName:()Ljava/lang/String;
   #83 = Utf8               caption
   #84 = String             #83           // caption
   #85 = Utf8               java/lang/String
   #86 = Class              #85           // java/lang/String
   #87 = Utf8               equals
   #88 = Utf8               (Ljava/lang/Object;)Z
   #89 = NameAndType        #87:#88       // equals:(Ljava/lang/Object;)Z
   #90 = Methodref          #86.#89       // java/lang/String.equals:(Ljava/lang/Object;)Z
   #91 = Utf8               clearStackToTableContext
   #92 = NameAndType        #91:#38       // clearStackToTableContext:()V
   #93 = Methodref          #36.#92       // coursier/util/shaded/org/jsoup/parser/HtmlTreeBuilder.clearStackToTableContext:()V
   #94 = Utf8               insertMarkerToFormattingElements
   #95 = NameAndType        #94:#38       // insertMarkerToFormattingElements:()V
   #96 = Methodref          #36.#95       // coursier/util/shaded/org/jsoup/parser/HtmlTreeBuilder.insertMarkerToFormattingElements:()V
   #97 = Utf8               (Lcoursier/util/shaded/org/jsoup/parser/Token$StartTag;)Lcoursier/util/shaded/org/jsoup/nodes/Element;
   #98 = NameAndType        #62:#97       // insert:(Lcoursier/util/shaded/org/jsoup/parser/Token$StartTag;)Lcoursier/util/shaded/org/jsoup/nodes/Element;
   #99 = Methodref          #36.#98       // coursier/util/shaded/org/jsoup/parser/HtmlTreeBuilder.insert:(Lcoursier/util/shaded/org/jsoup/parser/Token$StartTag;)Lcoursier/util/shaded/org/jsoup/nodes/Element;
  #100 = Utf8               InCaption
  #101 = NameAndType        #100:#45      // InCaption:Lcoursier/util/shaded/org/jsoup/parser/HtmlTreeBuilderState;
  #102 = Fieldref           #2.#101       // coursier/util/shaded/org/jsoup/parser/HtmlTreeBuilderState$9.InCaption:Lcoursier/util/shaded/org/jsoup/parser/HtmlTreeBuilderState;
  #103 = Utf8               colgroup
  #104 = String             #103          // colgroup
  #105 = Utf8               InColumnGroup
  #106 = NameAndType        #105:#45      // InColumnGroup:Lcoursier/util/shaded/org/jsoup/parser/HtmlTreeBuilderState;
  #107 = Fieldref           #2.#106       // coursier/util/shaded/org/jsoup/parser/HtmlTreeBuilderState$9.InColumnGroup:Lcoursier/util/shaded/org/jsoup/parser/HtmlTreeBuilderState;
  #108 = Utf8               col
  #109 = String             #108          // col
  #110 = Utf8               processStartTag
  #111 = Utf8               (Ljava/lang/String;)Z
  #112 = NameAndType        #110:#111     // processStartTag:(Ljava/lang/String;)Z
  #113 = Methodref          #36.#112      // coursier/util/shaded/org/jsoup/parser/HtmlTreeBuilder.processStartTag:(Ljava/lang/String;)Z
  #114 = Utf8               InTableToBody
  #115 = Utf8               [Ljava/lang/String;
  #116 = NameAndType        #114:#115     // InTableToBody:[Ljava/lang/String;
  #117 = Fieldref           #17.#116      // coursier/util/shaded/org/jsoup/parser/HtmlTreeBuilderState$Constants.InTableToBody:[Ljava/lang/String;
  #118 = Utf8               coursier/util/shaded/org/jsoup/internal/StringUtil
  #119 = Class              #118          // coursier/util/shaded/org/jsoup/internal/StringUtil
  #120 = Utf8               inSorted
  #121 = Utf8               (Ljava/lang/String;[Ljava/lang/String;)Z
  #122 = NameAndType        #120:#121     // inSorted:(Ljava/lang/String;[Ljava/lang/String;)Z
  #123 = Methodref          #119.#122     // coursier/util/shaded/org/jsoup/internal/StringUtil.inSorted:(Ljava/lang/String;[Ljava/lang/String;)Z
  #124 = Utf8               InTableBody
  #125 = NameAndType        #124:#45      // InTableBody:Lcoursier/util/shaded/org/jsoup/parser/HtmlTreeBuilderState;
  #126 = Fieldref           #2.#125       // coursier/util/shaded/org/jsoup/parser/HtmlTreeBuilderState$9.InTableBody:Lcoursier/util/shaded/org/jsoup/parser/HtmlTreeBuilderState;
  #127 = Utf8               InTableAddBody
  #128 = NameAndType        #127:#115     // InTableAddBody:[Ljava/lang/String;
  #129 = Fieldref           #17.#128      // coursier/util/shaded/org/jsoup/parser/HtmlTreeBuilderState$Constants.InTableAddBody:[Ljava/lang/String;
  #130 = Utf8               tbody
  #131 = String             #130          // tbody
  #132 = Utf8               table
  #133 = String             #132          // table
  #134 = Utf8               processEndTag
  #135 = NameAndType        #134:#111     // processEndTag:(Ljava/lang/String;)Z
  #136 = Methodref          #36.#135      // coursier/util/shaded/org/jsoup/parser/HtmlTreeBuilder.processEndTag:(Ljava/lang/String;)Z
  #137 = Utf8               InTableToHead
  #138 = NameAndType        #137:#115     // InTableToHead:[Ljava/lang/String;
  #139 = Fieldref           #17.#138      // coursier/util/shaded/org/jsoup/parser/HtmlTreeBuilderState$Constants.InTableToHead:[Ljava/lang/String;
  #140 = Utf8               InHead
  #141 = NameAndType        #140:#45      // InHead:Lcoursier/util/shaded/org/jsoup/parser/HtmlTreeBuilderState;
  #142 = Fieldref           #2.#141       // coursier/util/shaded/org/jsoup/parser/HtmlTreeBuilderState$9.InHead:Lcoursier/util/shaded/org/jsoup/parser/HtmlTreeBuilderState;
  #143 = Utf8               (Lcoursier/util/shaded/org/jsoup/parser/Token;Lcoursier/util/shaded/org/jsoup/parser/HtmlTreeBuilderState;)Z
  #144 = NameAndType        #29:#143      // process:(Lcoursier/util/shaded/org/jsoup/parser/Token;Lcoursier/util/shaded/org/jsoup/parser/HtmlTreeBuilderState;)Z
  #145 = Methodref          #36.#144      // coursier/util/shaded/org/jsoup/parser/HtmlTreeBuilder.process:(Lcoursier/util/shaded/org/jsoup/parser/Token;Lcoursier/util/shaded/org/jsoup/parser/HtmlTreeBuilderState;)Z
  #146 = Utf8               input
  #147 = String             #146          // input
  #148 = Utf8               attributes
  #149 = Utf8               Lcoursier/util/shaded/org/jsoup/nodes/Attributes;
  #150 = NameAndType        #148:#149     // attributes:Lcoursier/util/shaded/org/jsoup/nodes/Attributes;
  #151 = Fieldref           #14.#150      // coursier/util/shaded/org/jsoup/parser/Token$StartTag.attributes:Lcoursier/util/shaded/org/jsoup/nodes/Attributes;
  #152 = Utf8               type
  #153 = String             #152          // type
  #154 = Utf8               coursier/util/shaded/org/jsoup/nodes/Attributes
  #155 = Class              #154          // coursier/util/shaded/org/jsoup/nodes/Attributes
  #156 = Utf8               get
  #157 = Utf8               (Ljava/lang/String;)Ljava/lang/String;
  #158 = NameAndType        #156:#157     // get:(Ljava/lang/String;)Ljava/lang/String;
  #159 = Methodref          #155.#158     // coursier/util/shaded/org/jsoup/nodes/Attributes.get:(Ljava/lang/String;)Ljava/lang/String;
  #160 = Utf8               hidden
  #161 = String             #160          // hidden
  #162 = Utf8               equalsIgnoreCase
  #163 = NameAndType        #162:#111     // equalsIgnoreCase:(Ljava/lang/String;)Z
  #164 = Methodref          #86.#163      // java/lang/String.equalsIgnoreCase:(Ljava/lang/String;)Z
  #165 = Utf8               anythingElse
  #166 = NameAndType        #165:#30      // anythingElse:(Lcoursier/util/shaded/org/jsoup/parser/Token;Lcoursier/util/shaded/org/jsoup/parser/HtmlTreeBuilder;)Z
  #167 = Methodref          #2.#166       // coursier/util/shaded/org/jsoup/parser/HtmlTreeBuilderState$9.anythingElse:(Lcoursier/util/shaded/org/jsoup/parser/Token;Lcoursier/util/shaded/org/jsoup/parser/HtmlTreeBuilder;)Z
  #168 = Utf8               insertEmpty
  #169 = NameAndType        #168:#97      // insertEmpty:(Lcoursier/util/shaded/org/jsoup/parser/Token$StartTag;)Lcoursier/util/shaded/org/jsoup/nodes/Element;
  #170 = Methodref          #36.#169      // coursier/util/shaded/org/jsoup/parser/HtmlTreeBuilder.insertEmpty:(Lcoursier/util/shaded/org/jsoup/parser/Token$StartTag;)Lcoursier/util/shaded/org/jsoup/nodes/Element;
  #171 = Utf8               form
  #172 = String             #171          // form
  #173 = Utf8               getFormElement
  #174 = Utf8               ()Lcoursier/util/shaded/org/jsoup/nodes/FormElement;
  #175 = NameAndType        #173:#174     // getFormElement:()Lcoursier/util/shaded/org/jsoup/nodes/FormElement;
  #176 = Methodref          #36.#175      // coursier/util/shaded/org/jsoup/parser/HtmlTreeBuilder.getFormElement:()Lcoursier/util/shaded/org/jsoup/nodes/FormElement;
  #177 = Utf8               insertForm
  #178 = Utf8               (Lcoursier/util/shaded/org/jsoup/parser/Token$StartTag;Z)Lcoursier/util/shaded/org/jsoup/nodes/FormElement;
  #179 = NameAndType        #177:#178     // insertForm:(Lcoursier/util/shaded/org/jsoup/parser/Token$StartTag;Z)Lcoursier/util/shaded/org/jsoup/nodes/FormElement;
  #180 = Methodref          #36.#179      // coursier/util/shaded/org/jsoup/parser/HtmlTreeBuilder.insertForm:(Lcoursier/util/shaded/org/jsoup/parser/Token$StartTag;Z)Lcoursier/util/shaded/org/jsoup/nodes/FormElement;
  #181 = Utf8               isEndTag
  #182 = NameAndType        #181:#32      // isEndTag:()Z
  #183 = Methodref          #11.#182      // coursier/util/shaded/org/jsoup/parser/Token.isEndTag:()Z
  #184 = Utf8               asEndTag
  #185 = Utf8               ()Lcoursier/util/shaded/org/jsoup/parser/Token$EndTag;
  #186 = NameAndType        #184:#185     // asEndTag:()Lcoursier/util/shaded/org/jsoup/parser/Token$EndTag;
  #187 = Methodref          #11.#186      // coursier/util/shaded/org/jsoup/parser/Token.asEndTag:()Lcoursier/util/shaded/org/jsoup/parser/Token$EndTag;
  #188 = Methodref          #20.#81       // coursier/util/shaded/org/jsoup/parser/Token$EndTag.normalName:()Ljava/lang/String;
  #189 = Utf8               inTableScope
  #190 = NameAndType        #189:#111     // inTableScope:(Ljava/lang/String;)Z
  #191 = Methodref          #36.#190      // coursier/util/shaded/org/jsoup/parser/HtmlTreeBuilder.inTableScope:(Ljava/lang/String;)Z
  #192 = Utf8               popStackToClose
  #193 = Utf8               (Ljava/lang/String;)Lcoursier/util/shaded/org/jsoup/nodes/Element;
  #194 = NameAndType        #192:#193     // popStackToClose:(Ljava/lang/String;)Lcoursier/util/shaded/org/jsoup/nodes/Element;
  #195 = Methodref          #36.#194      // coursier/util/shaded/org/jsoup/parser/HtmlTreeBuilder.popStackToClose:(Ljava/lang/String;)Lcoursier/util/shaded/org/jsoup/nodes/Element;
  #196 = Utf8               resetInsertionMode
  #197 = NameAndType        #196:#38      // resetInsertionMode:()V
  #198 = Methodref          #36.#197      // coursier/util/shaded/org/jsoup/parser/HtmlTreeBuilder.resetInsertionMode:()V
  #199 = Utf8               InTableEndErr
  #200 = NameAndType        #199:#115     // InTableEndErr:[Ljava/lang/String;
  #201 = Fieldref           #17.#200      // coursier/util/shaded/org/jsoup/parser/HtmlTreeBuilderState$Constants.InTableEndErr:[Ljava/lang/String;
  #202 = Utf8               isEOF
  #203 = NameAndType        #202:#32      // isEOF:()Z
  #204 = Methodref          #11.#203      // coursier/util/shaded/org/jsoup/parser/Token.isEOF:()Z
  #205 = Utf8               currentElement
  #206 = Utf8               ()Lcoursier/util/shaded/org/jsoup/nodes/Element;
  #207 = NameAndType        #205:#206     // currentElement:()Lcoursier/util/shaded/org/jsoup/nodes/Element;
  #208 = Methodref          #36.#207      // coursier/util/shaded/org/jsoup/parser/HtmlTreeBuilder.currentElement:()Lcoursier/util/shaded/org/jsoup/nodes/Element;
  #209 = Utf8               coursier/util/shaded/org/jsoup/nodes/Element
  #210 = Class              #209          // coursier/util/shaded/org/jsoup/nodes/Element
  #211 = Methodref          #210.#81      // coursier/util/shaded/org/jsoup/nodes/Element.normalName:()Ljava/lang/String;
  #212 = Utf8               html
  #213 = String             #212          // html
  #214 = Utf8               processed
  #215 = Utf8               Z
  #216 = Utf8               startTag
  #217 = Utf8               Lcoursier/util/shaded/org/jsoup/parser/Token$StartTag;
  #218 = Utf8               name
  #219 = Utf8               Ljava/lang/String;
  #220 = Utf8               endTag
  #221 = Utf8               Lcoursier/util/shaded/org/jsoup/parser/Token$EndTag;
  #222 = Utf8               t
  #223 = Utf8               Lcoursier/util/shaded/org/jsoup/parser/Token;
  #224 = Utf8               tb
  #225 = Utf8               Lcoursier/util/shaded/org/jsoup/parser/HtmlTreeBuilder;
  #226 = Utf8               InTableFoster
  #227 = NameAndType        #226:#115     // InTableFoster:[Ljava/lang/String;
  #228 = Fieldref           #17.#227      // coursier/util/shaded/org/jsoup/parser/HtmlTreeBuilderState$Constants.InTableFoster:[Ljava/lang/String;
  #229 = Utf8               setFosterInserts
  #230 = Utf8               (Z)V
  #231 = NameAndType        #229:#230     // setFosterInserts:(Z)V
  #232 = Methodref          #36.#231      // coursier/util/shaded/org/jsoup/parser/HtmlTreeBuilder.setFosterInserts:(Z)V
  #233 = Utf8               InBody
  #234 = NameAndType        #233:#45      // InBody:Lcoursier/util/shaded/org/jsoup/parser/HtmlTreeBuilderState;
  #235 = Fieldref           #2.#234       // coursier/util/shaded/org/jsoup/parser/HtmlTreeBuilderState$9.InBody:Lcoursier/util/shaded/org/jsoup/parser/HtmlTreeBuilderState;
  #236 = Utf8               Code
  #237 = Utf8               LineNumberTable
  #238 = Utf8               LocalVariableTable
  #239 = Utf8               StackMapTable
  #240 = Utf8               InnerClasses
  #241 = Utf8               EnclosingMethod
  #242 = Utf8               SourceFile
{
  coursier.util.shaded.org.jsoup.parser.HtmlTreeBuilderState$9(java.lang.String, int);
    descriptor: (Ljava/lang/String;I)V
    flags: (0x0000)
    Code:
      stack=4, locals=3, args_size=3
         0: aload_0
         1: aload_1
         2: iload_2
         3: aconst_null
         4: invokespecial #26                 // Method coursier/util/shaded/org/jsoup/parser/HtmlTreeBuilderState."<init>":(Ljava/lang/String;ILcoursier/util/shaded/org/jsoup/parser/HtmlTreeBuilderState$1;)V
         7: return
      LineNumberTable:
        line 891: 0
      LocalVariableTable:
        Start  Length  Slot  Name   Signature
            0       8     0  this   Lcoursier/util/shaded/org/jsoup/parser/HtmlTreeBuilderState$9;

  boolean process(coursier.util.shaded.org.jsoup.parser.Token, coursier.util.shaded.org.jsoup.parser.HtmlTreeBuilder);
    descriptor: (Lcoursier/util/shaded/org/jsoup/parser/Token;Lcoursier/util/shaded/org/jsoup/parser/HtmlTreeBuilder;)Z
    flags: (0x0000)
    Code:
      stack=3, locals=6, args_size=3
         0: aload_1
         1: invokevirtual #34                 // Method coursier/util/shaded/org/jsoup/parser/Token.isCharacter:()Z
         4: ifeq          28
         7: aload_2
         8: invokevirtual #40                 // Method coursier/util/shaded/org/jsoup/parser/HtmlTreeBuilder.newPendingTableCharacters:()V
        11: aload_2
        12: invokevirtual #43                 // Method coursier/util/shaded/org/jsoup/parser/HtmlTreeBuilder.markInsertionMode:()V
        15: aload_2
        16: getstatic     #47                 // Field InTableText:Lcoursier/util/shaded/org/jsoup/parser/HtmlTreeBuilderState;
        19: invokevirtual #51                 // Method coursier/util/shaded/org/jsoup/parser/HtmlTreeBuilder.transition:(Lcoursier/util/shaded/org/jsoup/parser/HtmlTreeBuilderState;)V
        22: aload_2
        23: aload_1
        24: invokevirtual #54                 // Method coursier/util/shaded/org/jsoup/parser/HtmlTreeBuilder.process:(Lcoursier/util/shaded/org/jsoup/parser/Token;)Z
        27: ireturn
        28: aload_1
        29: invokevirtual #57                 // Method coursier/util/shaded/org/jsoup/parser/Token.isComment:()Z
        32: ifeq          45
        35: aload_2
        36: aload_1
        37: invokevirtual #61                 // Method coursier/util/shaded/org/jsoup/parser/Token.asComment:()Lcoursier/util/shaded/org/jsoup/parser/Token$Comment;
        40: invokevirtual #65                 // Method coursier/util/shaded/org/jsoup/parser/HtmlTreeBuilder.insert:(Lcoursier/util/shaded/org/jsoup/parser/Token$Comment;)V
        43: iconst_1
        44: ireturn
        45: aload_1
        46: invokevirtual #68                 // Method coursier/util/shaded/org/jsoup/parser/Token.isDoctype:()Z
        49: ifeq          59
        52: aload_2
        53: aload_0
        54: invokevirtual #71                 // Method coursier/util/shaded/org/jsoup/parser/HtmlTreeBuilder.error:(Lcoursier/util/shaded/org/jsoup/parser/HtmlTreeBuilderState;)V
        57: iconst_0
        58: ireturn
        59: aload_1
        60: invokevirtual #74                 // Method coursier/util/shaded/org/jsoup/parser/Token.isStartTag:()Z
        63: ifeq          362
        66: aload_1
        67: invokevirtual #78                 // Method coursier/util/shaded/org/jsoup/parser/Token.asStartTag:()Lcoursier/util/shaded/org/jsoup/parser/Token$StartTag;
        70: astore_3
        71: aload_3
        72: invokevirtual #82                 // Method coursier/util/shaded/org/jsoup/parser/Token$StartTag.normalName:()Ljava/lang/String;
        75: astore        4
        77: aload         4
        79: ldc           #84                 // String caption
        81: invokevirtual #90                 // Method java/lang/String.equals:(Ljava/lang/Object;)Z
        84: ifeq          111
        87: aload_2
        88: invokevirtual #93                 // Method coursier/util/shaded/org/jsoup/parser/HtmlTreeBuilder.clearStackToTableContext:()V
        91: aload_2
        92: invokevirtual #96                 // Method coursier/util/shaded/org/jsoup/parser/HtmlTreeBuilder.insertMarkerToFormattingElements:()V
        95: aload_2
        96: aload_3
        97: invokevirtual #99                 // Method coursier/util/shaded/org/jsoup/parser/HtmlTreeBuilder.insert:(Lcoursier/util/shaded/org/jsoup/parser/Token$StartTag;)Lcoursier/util/shaded/org/jsoup/nodes/Element;
       100: pop
       101: aload_2
       102: getstatic     #102                // Field InCaption:Lcoursier/util/shaded/org/jsoup/parser/HtmlTreeBuilderState;
       105: invokevirtual #51                 // Method coursier/util/shaded/org/jsoup/parser/HtmlTreeBuilder.transition:(Lcoursier/util/shaded/org/jsoup/parser/HtmlTreeBuilderState;)V
       108: goto          360
       111: aload         4
       113: ldc           #104                // String colgroup
       115: invokevirtual #90                 // Method java/lang/String.equals:(Ljava/lang/Object;)Z
       118: ifeq          141
       121: aload_2
       122: invokevirtual #93                 // Method coursier/util/shaded/org/jsoup/parser/HtmlTreeBuilder.clearStackToTableContext:()V
       125: aload_2
       126: aload_3
       127: invokevirtual #99                 // Method coursier/util/shaded/org/jsoup/parser/HtmlTreeBuilder.insert:(Lcoursier/util/shaded/org/jsoup/parser/Token$StartTag;)Lcoursier/util/shaded/org/jsoup/nodes/Element;
       130: pop
       131: aload_2
       132: getstatic     #107                // Field InColumnGroup:Lcoursier/util/shaded/org/jsoup/parser/HtmlTreeBuilderState;
       135: invokevirtual #51                 // Method coursier/util/shaded/org/jsoup/parser/HtmlTreeBuilder.transition:(Lcoursier/util/shaded/org/jsoup/parser/HtmlTreeBuilderState;)V
       138: goto          360
       141: aload         4
       143: ldc           #109                // String col
       145: invokevirtual #90                 // Method java/lang/String.equals:(Ljava/lang/Object;)Z
       148: ifeq          164
       151: aload_2
       152: ldc           #104                // String colgroup
       154: invokevirtual #113                // Method coursier/util/shaded/org/jsoup/parser/HtmlTreeBuilder.processStartTag:(Ljava/lang/String;)Z
       157: pop
       158: aload_2
       159: aload_1
       160: invokevirtual #54                 // Method coursier/util/shaded/org/jsoup/parser/HtmlTreeBuilder.process:(Lcoursier/util/shaded/org/jsoup/parser/Token;)Z
       163: ireturn
       164: aload         4
       166: getstatic     #117                // Field coursier/util/shaded/org/jsoup/parser/HtmlTreeBuilderState$Constants.InTableToBody:[Ljava/lang/String;
       169: invokestatic  #123                // Method coursier/util/shaded/org/jsoup/internal/StringUtil.inSorted:(Ljava/lang/String;[Ljava/lang/String;)Z
       172: ifeq          195
       175: aload_2
       176: invokevirtual #93                 // Method coursier/util/shaded/org/jsoup/parser/HtmlTreeBuilder.clearStackToTableContext:()V
       179: aload_2
       180: aload_3
       181: invokevirtual #99                 // Method coursier/util/shaded/org/jsoup/parser/HtmlTreeBuilder.insert:(Lcoursier/util/shaded/org/jsoup/parser/Token$StartTag;)Lcoursier/util/shaded/org/jsoup/nodes/Element;
       184: pop
       185: aload_2
       186: getstatic     #126                // Field InTableBody:Lcoursier/util/shaded/org/jsoup/parser/HtmlTreeBuilderState;
       189: invokevirtual #51                 // Method coursier/util/shaded/org/jsoup/parser/HtmlTreeBuilder.transition:(Lcoursier/util/shaded/org/jsoup/parser/HtmlTreeBuilderState;)V
       192: goto          360
       195: aload         4
       197: getstatic     #129                // Field coursier/util/shaded/org/jsoup/parser/HtmlTreeBuilderState$Constants.InTableAddBody:[Ljava/lang/String;
       200: invokestatic  #123                // Method coursier/util/shaded/org/jsoup/internal/StringUtil.inSorted:(Ljava/lang/String;[Ljava/lang/String;)Z
       203: ifeq          219
       206: aload_2
       207: ldc           #131                // String tbody
       209: invokevirtual #113                // Method coursier/util/shaded/org/jsoup/parser/HtmlTreeBuilder.processStartTag:(Ljava/lang/String;)Z
       212: pop
       213: aload_2
       214: aload_1
       215: invokevirtual #54                 // Method coursier/util/shaded/org/jsoup/parser/HtmlTreeBuilder.process:(Lcoursier/util/shaded/org/jsoup/parser/Token;)Z
       218: ireturn
       219: aload         4
       221: ldc           #133                // String table
       223: invokevirtual #90                 // Method java/lang/String.equals:(Ljava/lang/Object;)Z
       226: ifeq          256
       229: aload_2
       230: aload_0
       231: invokevirtual #71                 // Method coursier/util/shaded/org/jsoup/parser/HtmlTreeBuilder.error:(Lcoursier/util/shaded/org/jsoup/parser/HtmlTreeBuilderState;)V
       234: aload_2
       235: ldc           #133                // String table
       237: invokevirtual #136                // Method coursier/util/shaded/org/jsoup/parser/HtmlTreeBuilder.processEndTag:(Ljava/lang/String;)Z
       240: istore        5
       242: iload         5
       244: ifeq          253
       247: aload_2
       248: aload_1
       249: invokevirtual #54                 // Method coursier/util/shaded/org/jsoup/parser/HtmlTreeBuilder.process:(Lcoursier/util/shaded/org/jsoup/parser/Token;)Z
       252: ireturn
       253: goto          360
       256: aload         4
       258: getstatic     #139                // Field coursier/util/shaded/org/jsoup/parser/HtmlTreeBuilderState$Constants.InTableToHead:[Ljava/lang/String;
       261: invokestatic  #123                // Method coursier/util/shaded/org/jsoup/internal/StringUtil.inSorted:(Ljava/lang/String;[Ljava/lang/String;)Z
       264: ifeq          276
       267: aload_2
       268: aload_1
       269: getstatic     #142                // Field InHead:Lcoursier/util/shaded/org/jsoup/parser/HtmlTreeBuilderState;
       272: invokevirtual #145                // Method coursier/util/shaded/org/jsoup/parser/HtmlTreeBuilder.process:(Lcoursier/util/shaded/org/jsoup/parser/Token;Lcoursier/util/shaded/org/jsoup/parser/HtmlTreeBuilderState;)Z
       275: ireturn
       276: aload         4
       278: ldc           #147                // String input
       280: invokevirtual #90                 // Method java/lang/String.equals:(Ljava/lang/Object;)Z
       283: ifeq          319
       286: aload_3
       287: getfield      #151                // Field coursier/util/shaded/org/jsoup/parser/Token$StartTag.attributes:Lcoursier/util/shaded/org/jsoup/nodes/Attributes;
       290: ldc           #153                // String type
       292: invokevirtual #159                // Method coursier/util/shaded/org/jsoup/nodes/Attributes.get:(Ljava/lang/String;)Ljava/lang/String;
       295: ldc           #161                // String hidden
       297: invokevirtual #164                // Method java/lang/String.equalsIgnoreCase:(Ljava/lang/String;)Z
       300: ifne          310
       303: aload_0
       304: aload_1
       305: aload_2
       306: invokevirtual #167                // Method anythingElse:(Lcoursier/util/shaded/org/jsoup/parser/Token;Lcoursier/util/shaded/org/jsoup/parser/HtmlTreeBuilder;)Z
       309: ireturn
       310: aload_2
       311: aload_3
       312: invokevirtual #170                // Method coursier/util/shaded/org/jsoup/parser/HtmlTreeBuilder.insertEmpty:(Lcoursier/util/shaded/org/jsoup/parser/Token$StartTag;)Lcoursier/util/shaded/org/jsoup/nodes/Element;
       315: pop
       316: goto          360
       319: aload         4
       321: ldc           #172                // String form
       323: invokevirtual #90                 // Method java/lang/String.equals:(Ljava/lang/Object;)Z
       326: ifeq          353
       329: aload_2
       330: aload_0
       331: invokevirtual #71                 // Method coursier/util/shaded/org/jsoup/parser/HtmlTreeBuilder.error:(Lcoursier/util/shaded/org/jsoup/parser/HtmlTreeBuilderState;)V
       334: aload_2
       335: invokevirtual #176                // Method coursier/util/shaded/org/jsoup/parser/HtmlTreeBuilder.getFormElement:()Lcoursier/util/shaded/org/jsoup/nodes/FormElement;
       338: ifnull        343
       341: iconst_0
       342: ireturn
       343: aload_2
       344: aload_3
       345: iconst_0
       346: invokevirtual #180                // Method coursier/util/shaded/org/jsoup/parser/HtmlTreeBuilder.insertForm:(Lcoursier/util/shaded/org/jsoup/parser/Token$StartTag;Z)Lcoursier/util/shaded/org/jsoup/nodes/FormElement;
       349: pop
       350: goto          360
       353: aload_0
       354: aload_1
       355: aload_2
       356: invokevirtual #167                // Method anythingElse:(Lcoursier/util/shaded/org/jsoup/parser/Token;Lcoursier/util/shaded/org/jsoup/parser/HtmlTreeBuilder;)Z
       359: ireturn
       360: iconst_1
       361: ireturn
       362: aload_1
       363: invokevirtual #183                // Method coursier/util/shaded/org/jsoup/parser/Token.isEndTag:()Z
       366: ifeq          447
       369: aload_1
       370: invokevirtual #187                // Method coursier/util/shaded/org/jsoup/parser/Token.asEndTag:()Lcoursier/util/shaded/org/jsoup/parser/Token$EndTag;
       373: astore_3
       374: aload_3
       375: invokevirtual #188                // Method coursier/util/shaded/org/jsoup/parser/Token$EndTag.normalName:()Ljava/lang/String;
       378: astore        4
       380: aload         4
       382: ldc           #133                // String table
       384: invokevirtual #90                 // Method java/lang/String.equals:(Ljava/lang/Object;)Z
       387: ifeq          420
       390: aload_2
       391: aload         4
       393: invokevirtual #191                // Method coursier/util/shaded/org/jsoup/parser/HtmlTreeBuilder.inTableScope:(Ljava/lang/String;)Z
       396: ifne          406
       399: aload_2
       400: aload_0
       401: invokevirtual #71                 // Method coursier/util/shaded/org/jsoup/parser/HtmlTreeBuilder.error:(Lcoursier/util/shaded/org/jsoup/parser/HtmlTreeBuilderState;)V
       404: iconst_0
       405: ireturn
       406: aload_2
       407: ldc           #133                // String table
       409: invokevirtual #195                // Method coursier/util/shaded/org/jsoup/parser/HtmlTreeBuilder.popStackToClose:(Ljava/lang/String;)Lcoursier/util/shaded/org/jsoup/nodes/Element;
       412: pop
       413: aload_2
       414: invokevirtual #198                // Method coursier/util/shaded/org/jsoup/parser/HtmlTreeBuilder.resetInsertionMode:()V
       417: goto          445
       420: aload         4
       422: getstatic     #201                // Field coursier/util/shaded/org/jsoup/parser/HtmlTreeBuilderState$Constants.InTableEndErr:[Ljava/lang/String;
       425: invokestatic  #123                // Method coursier/util/shaded/org/jsoup/internal/StringUtil.inSorted:(Ljava/lang/String;[Ljava/lang/String;)Z
       428: ifeq          438
       431: aload_2
       432: aload_0
       433: invokevirtual #71                 // Method coursier/util/shaded/org/jsoup/parser/HtmlTreeBuilder.error:(Lcoursier/util/shaded/org/jsoup/parser/HtmlTreeBuilderState;)V
       436: iconst_0
       437: ireturn
       438: aload_0
       439: aload_1
       440: aload_2
       441: invokevirtual #167                // Method anythingElse:(Lcoursier/util/shaded/org/jsoup/parser/Token;Lcoursier/util/shaded/org/jsoup/parser/HtmlTreeBuilder;)Z
       444: ireturn
       445: iconst_1
       446: ireturn
       447: aload_1
       448: invokevirtual #204                // Method coursier/util/shaded/org/jsoup/parser/Token.isEOF:()Z
       451: ifeq          476
       454: aload_2
       455: invokevirtual #208                // Method coursier/util/shaded/org/jsoup/parser/HtmlTreeBuilder.currentElement:()Lcoursier/util/shaded/org/jsoup/nodes/Element;
       458: invokevirtual #211                // Method coursier/util/shaded/org/jsoup/nodes/Element.normalName:()Ljava/lang/String;
       461: ldc           #213                // String html
       463: invokevirtual #90                 // Method java/lang/String.equals:(Ljava/lang/Object;)Z
       466: ifeq          474
       469: aload_2
       470: aload_0
       471: invokevirtual #71                 // Method coursier/util/shaded/org/jsoup/parser/HtmlTreeBuilder.error:(Lcoursier/util/shaded/org/jsoup/parser/HtmlTreeBuilderState;)V
       474: iconst_1
       475: ireturn
       476: aload_0
       477: aload_1
       478: aload_2
       479: invokevirtual #167                // Method anythingElse:(Lcoursier/util/shaded/org/jsoup/parser/Token;Lcoursier/util/shaded/org/jsoup/parser/HtmlTreeBuilder;)Z
       482: ireturn
      StackMapTable: number_of_entries = 24
        frame_type = 28 /* same */
        frame_type = 16 /* same */
        frame_type = 13 /* same */
        frame_type = 253 /* append */
          offset_delta = 51
          locals = [ class coursier/util/shaded/org/jsoup/parser/Token$StartTag, class java/lang/String ]
        frame_type = 29 /* same */
        frame_type = 22 /* same */
        frame_type = 30 /* same */
        frame_type = 23 /* same */
        frame_type = 33 /* same */
        frame_type = 2 /* same */
        frame_type = 19 /* same */
        frame_type = 33 /* same */
        frame_type = 8 /* same */
        frame_type = 23 /* same */
        frame_type = 9 /* same */
        frame_type = 6 /* same */
        frame_type = 249 /* chop */
          offset_delta = 1
        frame_type = 253 /* append */
          offset_delta = 43
          locals = [ class coursier/util/shaded/org/jsoup/parser/Token$EndTag, class java/lang/String ]
        frame_type = 13 /* same */
        frame_type = 17 /* same */
        frame_type = 6 /* same */
        frame_type = 249 /* chop */
          offset_delta = 1
        frame_type = 26 /* same */
        frame_type = 1 /* same */
      LineNumberTable:
        line 893: 0
        line 894: 7
        line 895: 11
        line 896: 15
        line 897: 22
        line 898: 28
        line 899: 35
        line 900: 43
        line 901: 45
        line 902: 52
        line 903: 57
        line 904: 59
        line 905: 66
        line 906: 71
        line 907: 77
        line 908: 87
        line 909: 91
        line 910: 95
        line 911: 101
        line 912: 111
        line 913: 121
        line 914: 125
        line 915: 131
        line 916: 141
        line 917: 151
        line 918: 158
        line 919: 164
        line 920: 175
        line 921: 179
        line 922: 185
        line 923: 195
        line 924: 206
        line 925: 213
        line 926: 219
        line 927: 229
        line 928: 234
        line 929: 242
        line 930: 247
        line 931: 253
        line 932: 267
        line 933: 276
        line 934: 286
        line 935: 303
        line 937: 310
        line 939: 319
        line 940: 329
        line 941: 334
        line 942: 341
        line 944: 343
        line 947: 353
        line 949: 360
        line 950: 362
        line 951: 369
        line 952: 374
        line 954: 380
        line 955: 390
        line 956: 399
        line 957: 404
        line 959: 406
        line 961: 413
        line 962: 420
        line 963: 431
        line 964: 436
        line 966: 438
        line 968: 445
        line 969: 447
        line 970: 454
        line 971: 469
        line 972: 474
        line 974: 476
      LocalVariableTable:
        Start  Length  Slot  Name   Signature
          242      11     5 processed   Z
           71     291     3 startTag   Lcoursier/util/shaded/org/jsoup/parser/Token$StartTag;
           77     285     4  name   Ljava/lang/String;
          374      73     3 endTag   Lcoursier/util/shaded/org/jsoup/parser/Token$EndTag;
          380      67     4  name   Ljava/lang/String;
            0     483     0  this   Lcoursier/util/shaded/org/jsoup/parser/HtmlTreeBuilderState$9;
            0     483     1     t   Lcoursier/util/shaded/org/jsoup/parser/Token;
            0     483     2    tb   Lcoursier/util/shaded/org/jsoup/parser/HtmlTreeBuilder;

  boolean anythingElse(coursier.util.shaded.org.jsoup.parser.Token, coursier.util.shaded.org.jsoup.parser.HtmlTreeBuilder);
    descriptor: (Lcoursier/util/shaded/org/jsoup/parser/Token;Lcoursier/util/shaded/org/jsoup/parser/HtmlTreeBuilder;)Z
    flags: (0x0000)
    Code:
      stack=3, locals=4, args_size=3
         0: aload_2
         1: aload_0
         2: invokevirtual #71                 // Method coursier/util/shaded/org/jsoup/parser/HtmlTreeBuilder.error:(Lcoursier/util/shaded/org/jsoup/parser/HtmlTreeBuilderState;)V
         5: aload_2
         6: invokevirtual #208                // Method coursier/util/shaded/org/jsoup/parser/HtmlTreeBuilder.currentElement:()Lcoursier/util/shaded/org/jsoup/nodes/Element;
         9: invokevirtual #211                // Method coursier/util/shaded/org/jsoup/nodes/Element.normalName:()Ljava/lang/String;
        12: getstatic     #228                // Field coursier/util/shaded/org/jsoup/parser/HtmlTreeBuilderState$Constants.InTableFoster:[Ljava/lang/String;
        15: invokestatic  #123                // Method coursier/util/shaded/org/jsoup/internal/StringUtil.inSorted:(Ljava/lang/String;[Ljava/lang/String;)Z
        18: ifeq          43
        21: aload_2
        22: iconst_1
        23: invokevirtual #232                // Method coursier/util/shaded/org/jsoup/parser/HtmlTreeBuilder.setFosterInserts:(Z)V
        26: aload_2
        27: aload_1
        28: getstatic     #235                // Field InBody:Lcoursier/util/shaded/org/jsoup/parser/HtmlTreeBuilderState;
        31: invokevirtual #145                // Method coursier/util/shaded/org/jsoup/parser/HtmlTreeBuilder.process:(Lcoursier/util/shaded/org/jsoup/parser/Token;Lcoursier/util/shaded/org/jsoup/parser/HtmlTreeBuilderState;)Z
        34: istore_3
        35: aload_2
        36: iconst_0
        37: invokevirtual #232                // Method coursier/util/shaded/org/jsoup/parser/HtmlTreeBuilder.setFosterInserts:(Z)V
        40: goto          52
        43: aload_2
        44: aload_1
        45: getstatic     #235                // Field InBody:Lcoursier/util/shaded/org/jsoup/parser/HtmlTreeBuilderState;
        48: invokevirtual #145                // Method coursier/util/shaded/org/jsoup/parser/HtmlTreeBuilder.process:(Lcoursier/util/shaded/org/jsoup/parser/Token;Lcoursier/util/shaded/org/jsoup/parser/HtmlTreeBuilderState;)Z
        51: istore_3
        52: iload_3
        53: ireturn
      StackMapTable: number_of_entries = 2
        frame_type = 43 /* same */
        frame_type = 252 /* append */
          offset_delta = 8
          locals = [ int ]
      LineNumberTable:
        line 978: 0
        line 980: 5
        line 981: 21
        line 982: 26
        line 983: 35
        line 985: 43
        line 987: 52
      LocalVariableTable:
        Start  Length  Slot  Name   Signature
           35       8     3 processed   Z
            0      54     0  this   Lcoursier/util/shaded/org/jsoup/parser/HtmlTreeBuilderState$9;
            0      54     1     t   Lcoursier/util/shaded/org/jsoup/parser/Token;
            0      54     2    tb   Lcoursier/util/shaded/org/jsoup/parser/HtmlTreeBuilder;
           52       2     3 processed   Z
}
InnerClasses:
  final #7;                               // class coursier/util/shaded/org/jsoup/parser/HtmlTreeBuilderState$1
  final #2;                               // class coursier/util/shaded/org/jsoup/parser/HtmlTreeBuilderState$9
  static final #12= #9 of #11;            // Comment=class coursier/util/shaded/org/jsoup/parser/Token$Comment of class coursier/util/shaded/org/jsoup/parser/Token
  static final #15= #14 of #11;           // StartTag=class coursier/util/shaded/org/jsoup/parser/Token$StartTag of class coursier/util/shaded/org/jsoup/parser/Token
  static final #18= #17 of #4;            // Constants=class coursier/util/shaded/org/jsoup/parser/HtmlTreeBuilderState$Constants of class coursier/util/shaded/org/jsoup/parser/HtmlTreeBuilderState
  static final #21= #20 of #11;           // EndTag=class coursier/util/shaded/org/jsoup/parser/Token$EndTag of class coursier/util/shaded/org/jsoup/parser/Token
EnclosingMethod: #4.#0                  // coursier.util.shaded.org.jsoup.parser.HtmlTreeBuilderState
SourceFile: "HtmlTreeBuilderState.java"
