Classfile /Users/mw/Projects/slang-braindump/.jar/jar8/assemble/slang-braindump/assemble/content/coursier/util/shaded/org/jsoup/parser/ParseError.class
  Last modified May 29, 2022; size 1221 bytes
  SHA-256 checksum 4fc5792b7be4da1f0cec87abedd9f0e76f23b07f610c1b9a97e69ba11999b98e
  Compiled from "ParseError.java"
public class coursier.util.shaded.org.jsoup.parser.ParseError
  minor version: 0
  major version: 51
  flags: (0x0021) ACC_PUBLIC, ACC_SUPER
  this_class: #2                          // coursier/util/shaded/org/jsoup/parser/ParseError
  super_class: #4                         // java/lang/Object
  interfaces: 0, fields: 2, methods: 5, attributes: 1
Constant pool:
   #1 = Utf8               coursier/util/shaded/org/jsoup/parser/ParseError
   #2 = Class              #1             // coursier/util/shaded/org/jsoup/parser/ParseError
   #3 = Utf8               java/lang/Object
   #4 = Class              #3             // java/lang/Object
   #5 = Utf8               ParseError.java
   #6 = Utf8               pos
   #7 = Utf8               I
   #8 = Utf8               errorMsg
   #9 = Utf8               Ljava/lang/String;
  #10 = Utf8               <init>
  #11 = Utf8               (ILjava/lang/String;)V
  #12 = Utf8               ()V
  #13 = NameAndType        #10:#12        // "<init>":()V
  #14 = Methodref          #4.#13         // java/lang/Object."<init>":()V
  #15 = NameAndType        #6:#7          // pos:I
  #16 = Fieldref           #2.#15         // coursier/util/shaded/org/jsoup/parser/ParseError.pos:I
  #17 = NameAndType        #8:#9          // errorMsg:Ljava/lang/String;
  #18 = Fieldref           #2.#17         // coursier/util/shaded/org/jsoup/parser/ParseError.errorMsg:Ljava/lang/String;
  #19 = Utf8               this
  #20 = Utf8               Lcoursier/util/shaded/org/jsoup/parser/ParseError;
  #21 = Utf8               (ILjava/lang/String;[Ljava/lang/Object;)V
  #22 = Utf8               java/lang/String
  #23 = Class              #22            // java/lang/String
  #24 = Utf8               format
  #25 = Utf8               (Ljava/lang/String;[Ljava/lang/Object;)Ljava/lang/String;
  #26 = NameAndType        #24:#25        // format:(Ljava/lang/String;[Ljava/lang/Object;)Ljava/lang/String;
  #27 = Methodref          #23.#26        // java/lang/String.format:(Ljava/lang/String;[Ljava/lang/Object;)Ljava/lang/String;
  #28 = Utf8               errorFormat
  #29 = Utf8               args
  #30 = Utf8               [Ljava/lang/Object;
  #31 = Utf8               getErrorMessage
  #32 = Utf8               ()Ljava/lang/String;
  #33 = Utf8               getPosition
  #34 = Utf8               ()I
  #35 = Utf8               toString
  #36 = Utf8               java/lang/StringBuilder
  #37 = Class              #36            // java/lang/StringBuilder
  #38 = Methodref          #37.#13        // java/lang/StringBuilder."<init>":()V
  #39 = Utf8               append
  #40 = Utf8               (I)Ljava/lang/StringBuilder;
  #41 = NameAndType        #39:#40        // append:(I)Ljava/lang/StringBuilder;
  #42 = Methodref          #37.#41        // java/lang/StringBuilder.append:(I)Ljava/lang/StringBuilder;
  #43 = Utf8               :
  #44 = String             #43            // :
  #45 = Utf8               (Ljava/lang/String;)Ljava/lang/StringBuilder;
  #46 = NameAndType        #39:#45        // append:(Ljava/lang/String;)Ljava/lang/StringBuilder;
  #47 = Methodref          #37.#46        // java/lang/StringBuilder.append:(Ljava/lang/String;)Ljava/lang/StringBuilder;
  #48 = NameAndType        #35:#32        // toString:()Ljava/lang/String;
  #49 = Methodref          #37.#48        // java/lang/StringBuilder.toString:()Ljava/lang/String;
  #50 = Utf8               Code
  #51 = Utf8               LineNumberTable
  #52 = Utf8               LocalVariableTable
  #53 = Utf8               SourceFile
{
  private int pos;
    descriptor: I
    flags: (0x0002) ACC_PRIVATE

  private java.lang.String errorMsg;
    descriptor: Ljava/lang/String;
    flags: (0x0002) ACC_PRIVATE

  coursier.util.shaded.org.jsoup.parser.ParseError(int, java.lang.String);
    descriptor: (ILjava/lang/String;)V
    flags: (0x0000)
    Code:
      stack=2, locals=3, args_size=3
         0: aload_0
         1: invokespecial #14                 // Method java/lang/Object."<init>":()V
         4: aload_0
         5: iload_1
         6: putfield      #16                 // Field pos:I
         9: aload_0
        10: aload_2
        11: putfield      #18                 // Field errorMsg:Ljava/lang/String;
        14: return
      LineNumberTable:
        line 10: 0
        line 11: 4
        line 12: 9
        line 13: 14
      LocalVariableTable:
        Start  Length  Slot  Name   Signature
            0      15     0  this   Lcoursier/util/shaded/org/jsoup/parser/ParseError;
            0      15     1   pos   I
            0      15     2 errorMsg   Ljava/lang/String;

  coursier.util.shaded.org.jsoup.parser.ParseError(int, java.lang.String, java.lang.Object...);
    descriptor: (ILjava/lang/String;[Ljava/lang/Object;)V
    flags: (0x0080) ACC_VARARGS
    Code:
      stack=3, locals=4, args_size=4
         0: aload_0
         1: invokespecial #14                 // Method java/lang/Object."<init>":()V
         4: aload_0
         5: aload_2
         6: aload_3
         7: invokestatic  #27                 // Method java/lang/String.format:(Ljava/lang/String;[Ljava/lang/Object;)Ljava/lang/String;
        10: putfield      #18                 // Field errorMsg:Ljava/lang/String;
        13: aload_0
        14: iload_1
        15: putfield      #16                 // Field pos:I
        18: return
      LineNumberTable:
        line 15: 0
        line 16: 4
        line 17: 13
        line 18: 18
      LocalVariableTable:
        Start  Length  Slot  Name   Signature
            0      19     0  this   Lcoursier/util/shaded/org/jsoup/parser/ParseError;
            0      19     1   pos   I
            0      19     2 errorFormat   Ljava/lang/String;
            0      19     3  args   [Ljava/lang/Object;

  public java.lang.String getErrorMessage();
    descriptor: ()Ljava/lang/String;
    flags: (0x0001) ACC_PUBLIC
    Code:
      stack=1, locals=1, args_size=1
         0: aload_0
         1: getfield      #18                 // Field errorMsg:Ljava/lang/String;
         4: areturn
      LineNumberTable:
        line 25: 0
      LocalVariableTable:
        Start  Length  Slot  Name   Signature
            0       5     0  this   Lcoursier/util/shaded/org/jsoup/parser/ParseError;

  public int getPosition();
    descriptor: ()I
    flags: (0x0001) ACC_PUBLIC
    Code:
      stack=1, locals=1, args_size=1
         0: aload_0
         1: getfield      #16                 // Field pos:I
         4: ireturn
      LineNumberTable:
        line 33: 0
      LocalVariableTable:
        Start  Length  Slot  Name   Signature
            0       5     0  this   Lcoursier/util/shaded/org/jsoup/parser/ParseError;

  public java.lang.String toString();
    descriptor: ()Ljava/lang/String;
    flags: (0x0001) ACC_PUBLIC
    Code:
      stack=2, locals=1, args_size=1
         0: new           #37                 // class java/lang/StringBuilder
         3: dup
         4: invokespecial #38                 // Method java/lang/StringBuilder."<init>":()V
         7: aload_0
         8: getfield      #16                 // Field pos:I
        11: invokevirtual #42                 // Method java/lang/StringBuilder.append:(I)Ljava/lang/StringBuilder;
        14: ldc           #44                 // String :
        16: invokevirtual #47                 // Method java/lang/StringBuilder.append:(Ljava/lang/String;)Ljava/lang/StringBuilder;
        19: aload_0
        20: getfield      #18                 // Field errorMsg:Ljava/lang/String;
        23: invokevirtual #47                 // Method java/lang/StringBuilder.append:(Ljava/lang/String;)Ljava/lang/StringBuilder;
        26: invokevirtual #49                 // Method java/lang/StringBuilder.toString:()Ljava/lang/String;
        29: areturn
      LineNumberTable:
        line 38: 0
      LocalVariableTable:
        Start  Length  Slot  Name   Signature
            0      30     0  this   Lcoursier/util/shaded/org/jsoup/parser/ParseError;
}
SourceFile: "ParseError.java"
