Classfile /Users/mw/Projects/slang-braindump/.jar/jar8/assemble/slang-braindump/assemble/content/coursier/util/shaded/org/jsoup/parser/Token.class
  Last modified May 29, 2022; size 3224 bytes
  SHA-256 checksum 20d83c14d03edf8289b5fef73872a50075215e01c70e40fe39fd54e789e4d6a3
  Compiled from "Token.java"
abstract class coursier.util.shaded.org.jsoup.parser.Token
  minor version: 0
  major version: 51
  flags: (0x0420) ACC_SUPER, ACC_ABSTRACT
  this_class: #2                          // coursier/util/shaded/org/jsoup/parser/Token
  super_class: #4                         // java/lang/Object
  interfaces: 0, fields: 1, methods: 17, attributes: 2
Constant pool:
    #1 = Utf8               coursier/util/shaded/org/jsoup/parser/Token
    #2 = Class              #1            // coursier/util/shaded/org/jsoup/parser/Token
    #3 = Utf8               java/lang/Object
    #4 = Class              #3            // java/lang/Object
    #5 = Utf8               Token.java
    #6 = Utf8               coursier/util/shaded/org/jsoup/parser/Token$TokenType
    #7 = Class              #6            // coursier/util/shaded/org/jsoup/parser/Token$TokenType
    #8 = Utf8               TokenType
    #9 = Utf8               coursier/util/shaded/org/jsoup/parser/Token$Doctype
   #10 = Class              #9            // coursier/util/shaded/org/jsoup/parser/Token$Doctype
   #11 = Utf8               Doctype
   #12 = Utf8               coursier/util/shaded/org/jsoup/parser/Token$StartTag
   #13 = Class              #12           // coursier/util/shaded/org/jsoup/parser/Token$StartTag
   #14 = Utf8               StartTag
   #15 = Utf8               coursier/util/shaded/org/jsoup/parser/Token$EndTag
   #16 = Class              #15           // coursier/util/shaded/org/jsoup/parser/Token$EndTag
   #17 = Utf8               EndTag
   #18 = Utf8               coursier/util/shaded/org/jsoup/parser/Token$Comment
   #19 = Class              #18           // coursier/util/shaded/org/jsoup/parser/Token$Comment
   #20 = Utf8               Comment
   #21 = Utf8               coursier/util/shaded/org/jsoup/parser/Token$CData
   #22 = Class              #21           // coursier/util/shaded/org/jsoup/parser/Token$CData
   #23 = Utf8               CData
   #24 = Utf8               coursier/util/shaded/org/jsoup/parser/Token$Character
   #25 = Class              #24           // coursier/util/shaded/org/jsoup/parser/Token$Character
   #26 = Utf8               Character
   #27 = Utf8               coursier/util/shaded/org/jsoup/parser/Token$1
   #28 = Class              #27           // coursier/util/shaded/org/jsoup/parser/Token$1
   #29 = Utf8               coursier/util/shaded/org/jsoup/parser/Token$EOF
   #30 = Class              #29           // coursier/util/shaded/org/jsoup/parser/Token$EOF
   #31 = Utf8               EOF
   #32 = Utf8               coursier/util/shaded/org/jsoup/parser/Token$Tag
   #33 = Class              #32           // coursier/util/shaded/org/jsoup/parser/Token$Tag
   #34 = Utf8               Tag
   #35 = Utf8               type
   #36 = Utf8               Lcoursier/util/shaded/org/jsoup/parser/Token$TokenType;
   #37 = Utf8               <init>
   #38 = Utf8               ()V
   #39 = NameAndType        #37:#38       // "<init>":()V
   #40 = Methodref          #4.#39        // java/lang/Object."<init>":()V
   #41 = Utf8               this
   #42 = Utf8               Lcoursier/util/shaded/org/jsoup/parser/Token;
   #43 = Utf8               tokenType
   #44 = Utf8               ()Ljava/lang/String;
   #45 = Utf8               getClass
   #46 = Utf8               ()Ljava/lang/Class;
   #47 = NameAndType        #45:#46       // getClass:()Ljava/lang/Class;
   #48 = Methodref          #4.#47        // java/lang/Object.getClass:()Ljava/lang/Class;
   #49 = Utf8               java/lang/Class
   #50 = Class              #49           // java/lang/Class
   #51 = Utf8               getSimpleName
   #52 = NameAndType        #51:#44       // getSimpleName:()Ljava/lang/String;
   #53 = Methodref          #50.#52       // java/lang/Class.getSimpleName:()Ljava/lang/String;
   #54 = Utf8               reset
   #55 = Utf8               ()Lcoursier/util/shaded/org/jsoup/parser/Token;
   #56 = Utf8               (Ljava/lang/StringBuilder;)V
   #57 = Utf8               java/lang/StringBuilder
   #58 = Class              #57           // java/lang/StringBuilder
   #59 = Utf8               length
   #60 = Utf8               ()I
   #61 = NameAndType        #59:#60       // length:()I
   #62 = Methodref          #58.#61       // java/lang/StringBuilder.length:()I
   #63 = Utf8               delete
   #64 = Utf8               (II)Ljava/lang/StringBuilder;
   #65 = NameAndType        #63:#64       // delete:(II)Ljava/lang/StringBuilder;
   #66 = Methodref          #58.#65       // java/lang/StringBuilder.delete:(II)Ljava/lang/StringBuilder;
   #67 = Utf8               sb
   #68 = Utf8               Ljava/lang/StringBuilder;
   #69 = Utf8               isDoctype
   #70 = Utf8               ()Z
   #71 = NameAndType        #35:#36       // type:Lcoursier/util/shaded/org/jsoup/parser/Token$TokenType;
   #72 = Fieldref           #2.#71        // coursier/util/shaded/org/jsoup/parser/Token.type:Lcoursier/util/shaded/org/jsoup/parser/Token$TokenType;
   #73 = NameAndType        #11:#36       // Doctype:Lcoursier/util/shaded/org/jsoup/parser/Token$TokenType;
   #74 = Fieldref           #7.#73        // coursier/util/shaded/org/jsoup/parser/Token$TokenType.Doctype:Lcoursier/util/shaded/org/jsoup/parser/Token$TokenType;
   #75 = Utf8               asDoctype
   #76 = Utf8               ()Lcoursier/util/shaded/org/jsoup/parser/Token$Doctype;
   #77 = Utf8               isStartTag
   #78 = NameAndType        #14:#36       // StartTag:Lcoursier/util/shaded/org/jsoup/parser/Token$TokenType;
   #79 = Fieldref           #7.#78        // coursier/util/shaded/org/jsoup/parser/Token$TokenType.StartTag:Lcoursier/util/shaded/org/jsoup/parser/Token$TokenType;
   #80 = Utf8               asStartTag
   #81 = Utf8               ()Lcoursier/util/shaded/org/jsoup/parser/Token$StartTag;
   #82 = Utf8               isEndTag
   #83 = NameAndType        #17:#36       // EndTag:Lcoursier/util/shaded/org/jsoup/parser/Token$TokenType;
   #84 = Fieldref           #7.#83        // coursier/util/shaded/org/jsoup/parser/Token$TokenType.EndTag:Lcoursier/util/shaded/org/jsoup/parser/Token$TokenType;
   #85 = Utf8               asEndTag
   #86 = Utf8               ()Lcoursier/util/shaded/org/jsoup/parser/Token$EndTag;
   #87 = Utf8               isComment
   #88 = NameAndType        #20:#36       // Comment:Lcoursier/util/shaded/org/jsoup/parser/Token$TokenType;
   #89 = Fieldref           #7.#88        // coursier/util/shaded/org/jsoup/parser/Token$TokenType.Comment:Lcoursier/util/shaded/org/jsoup/parser/Token$TokenType;
   #90 = Utf8               asComment
   #91 = Utf8               ()Lcoursier/util/shaded/org/jsoup/parser/Token$Comment;
   #92 = Utf8               isCharacter
   #93 = NameAndType        #26:#36       // Character:Lcoursier/util/shaded/org/jsoup/parser/Token$TokenType;
   #94 = Fieldref           #7.#93        // coursier/util/shaded/org/jsoup/parser/Token$TokenType.Character:Lcoursier/util/shaded/org/jsoup/parser/Token$TokenType;
   #95 = Utf8               isCData
   #96 = Utf8               asCharacter
   #97 = Utf8               ()Lcoursier/util/shaded/org/jsoup/parser/Token$Character;
   #98 = Utf8               isEOF
   #99 = NameAndType        #31:#36       // EOF:Lcoursier/util/shaded/org/jsoup/parser/Token$TokenType;
  #100 = Fieldref           #7.#99        // coursier/util/shaded/org/jsoup/parser/Token$TokenType.EOF:Lcoursier/util/shaded/org/jsoup/parser/Token$TokenType;
  #101 = Utf8               (Lcoursier/util/shaded/org/jsoup/parser/Token$1;)V
  #102 = Methodref          #2.#39        // coursier/util/shaded/org/jsoup/parser/Token."<init>":()V
  #103 = Utf8               x0
  #104 = Utf8               Lcoursier/util/shaded/org/jsoup/parser/Token$1;
  #105 = Utf8               Code
  #106 = Utf8               LineNumberTable
  #107 = Utf8               LocalVariableTable
  #108 = Utf8               StackMapTable
  #109 = Utf8               InnerClasses
  #110 = Utf8               SourceFile
{
  coursier.util.shaded.org.jsoup.parser.Token$TokenType type;
    descriptor: Lcoursier/util/shaded/org/jsoup/parser/Token$TokenType;
    flags: (0x0000)

  private coursier.util.shaded.org.jsoup.parser.Token();
    descriptor: ()V
    flags: (0x0002) ACC_PRIVATE
    Code:
      stack=1, locals=1, args_size=1
         0: aload_0
         1: invokespecial #40                 // Method java/lang/Object."<init>":()V
         4: return
      LineNumberTable:
        line 14: 0
        line 15: 4
      LocalVariableTable:
        Start  Length  Slot  Name   Signature
            0       5     0  this   Lcoursier/util/shaded/org/jsoup/parser/Token;

  java.lang.String tokenType();
    descriptor: ()Ljava/lang/String;
    flags: (0x0000)
    Code:
      stack=1, locals=1, args_size=1
         0: aload_0
         1: invokevirtual #48                 // Method java/lang/Object.getClass:()Ljava/lang/Class;
         4: invokevirtual #53                 // Method java/lang/Class.getSimpleName:()Ljava/lang/String;
         7: areturn
      LineNumberTable:
        line 18: 0
      LocalVariableTable:
        Start  Length  Slot  Name   Signature
            0       8     0  this   Lcoursier/util/shaded/org/jsoup/parser/Token;

  abstract coursier.util.shaded.org.jsoup.parser.Token reset();
    descriptor: ()Lcoursier/util/shaded/org/jsoup/parser/Token;
    flags: (0x0400) ACC_ABSTRACT

  static void reset(java.lang.StringBuilder);
    descriptor: (Ljava/lang/StringBuilder;)V
    flags: (0x0008) ACC_STATIC
    Code:
      stack=3, locals=1, args_size=1
         0: aload_0
         1: ifnull        14
         4: aload_0
         5: iconst_0
         6: aload_0
         7: invokevirtual #62                 // Method java/lang/StringBuilder.length:()I
        10: invokevirtual #66                 // Method java/lang/StringBuilder.delete:(II)Ljava/lang/StringBuilder;
        13: pop
        14: return
      StackMapTable: number_of_entries = 1
        frame_type = 14 /* same */
      LineNumberTable:
        line 28: 0
        line 29: 4
        line 31: 14
      LocalVariableTable:
        Start  Length  Slot  Name   Signature
            0      15     0    sb   Ljava/lang/StringBuilder;

  final boolean isDoctype();
    descriptor: ()Z
    flags: (0x0010) ACC_FINAL
    Code:
      stack=2, locals=1, args_size=1
         0: aload_0
         1: getfield      #72                 // Field type:Lcoursier/util/shaded/org/jsoup/parser/Token$TokenType;
         4: getstatic     #74                 // Field coursier/util/shaded/org/jsoup/parser/Token$TokenType.Doctype:Lcoursier/util/shaded/org/jsoup/parser/Token$TokenType;
         7: if_acmpne     14
        10: iconst_1
        11: goto          15
        14: iconst_0
        15: ireturn
      StackMapTable: number_of_entries = 2
        frame_type = 14 /* same */
        frame_type = 64 /* same_locals_1_stack_item */
          stack = [ int ]
      LineNumberTable:
        line 365: 0
      LocalVariableTable:
        Start  Length  Slot  Name   Signature
            0      16     0  this   Lcoursier/util/shaded/org/jsoup/parser/Token;

  final coursier.util.shaded.org.jsoup.parser.Token$Doctype asDoctype();
    descriptor: ()Lcoursier/util/shaded/org/jsoup/parser/Token$Doctype;
    flags: (0x0010) ACC_FINAL
    Code:
      stack=1, locals=1, args_size=1
         0: aload_0
         1: checkcast     #10                 // class coursier/util/shaded/org/jsoup/parser/Token$Doctype
         4: areturn
      LineNumberTable:
        line 369: 0
      LocalVariableTable:
        Start  Length  Slot  Name   Signature
            0       5     0  this   Lcoursier/util/shaded/org/jsoup/parser/Token;

  final boolean isStartTag();
    descriptor: ()Z
    flags: (0x0010) ACC_FINAL
    Code:
      stack=2, locals=1, args_size=1
         0: aload_0
         1: getfield      #72                 // Field type:Lcoursier/util/shaded/org/jsoup/parser/Token$TokenType;
         4: getstatic     #79                 // Field coursier/util/shaded/org/jsoup/parser/Token$TokenType.StartTag:Lcoursier/util/shaded/org/jsoup/parser/Token$TokenType;
         7: if_acmpne     14
        10: iconst_1
        11: goto          15
        14: iconst_0
        15: ireturn
      StackMapTable: number_of_entries = 2
        frame_type = 14 /* same */
        frame_type = 64 /* same_locals_1_stack_item */
          stack = [ int ]
      LineNumberTable:
        line 373: 0
      LocalVariableTable:
        Start  Length  Slot  Name   Signature
            0      16     0  this   Lcoursier/util/shaded/org/jsoup/parser/Token;

  final coursier.util.shaded.org.jsoup.parser.Token$StartTag asStartTag();
    descriptor: ()Lcoursier/util/shaded/org/jsoup/parser/Token$StartTag;
    flags: (0x0010) ACC_FINAL
    Code:
      stack=1, locals=1, args_size=1
         0: aload_0
         1: checkcast     #13                 // class coursier/util/shaded/org/jsoup/parser/Token$StartTag
         4: areturn
      LineNumberTable:
        line 377: 0
      LocalVariableTable:
        Start  Length  Slot  Name   Signature
            0       5     0  this   Lcoursier/util/shaded/org/jsoup/parser/Token;

  final boolean isEndTag();
    descriptor: ()Z
    flags: (0x0010) ACC_FINAL
    Code:
      stack=2, locals=1, args_size=1
         0: aload_0
         1: getfield      #72                 // Field type:Lcoursier/util/shaded/org/jsoup/parser/Token$TokenType;
         4: getstatic     #84                 // Field coursier/util/shaded/org/jsoup/parser/Token$TokenType.EndTag:Lcoursier/util/shaded/org/jsoup/parser/Token$TokenType;
         7: if_acmpne     14
        10: iconst_1
        11: goto          15
        14: iconst_0
        15: ireturn
      StackMapTable: number_of_entries = 2
        frame_type = 14 /* same */
        frame_type = 64 /* same_locals_1_stack_item */
          stack = [ int ]
      LineNumberTable:
        line 381: 0
      LocalVariableTable:
        Start  Length  Slot  Name   Signature
            0      16     0  this   Lcoursier/util/shaded/org/jsoup/parser/Token;

  final coursier.util.shaded.org.jsoup.parser.Token$EndTag asEndTag();
    descriptor: ()Lcoursier/util/shaded/org/jsoup/parser/Token$EndTag;
    flags: (0x0010) ACC_FINAL
    Code:
      stack=1, locals=1, args_size=1
         0: aload_0
         1: checkcast     #16                 // class coursier/util/shaded/org/jsoup/parser/Token$EndTag
         4: areturn
      LineNumberTable:
        line 385: 0
      LocalVariableTable:
        Start  Length  Slot  Name   Signature
            0       5     0  this   Lcoursier/util/shaded/org/jsoup/parser/Token;

  final boolean isComment();
    descriptor: ()Z
    flags: (0x0010) ACC_FINAL
    Code:
      stack=2, locals=1, args_size=1
         0: aload_0
         1: getfield      #72                 // Field type:Lcoursier/util/shaded/org/jsoup/parser/Token$TokenType;
         4: getstatic     #89                 // Field coursier/util/shaded/org/jsoup/parser/Token$TokenType.Comment:Lcoursier/util/shaded/org/jsoup/parser/Token$TokenType;
         7: if_acmpne     14
        10: iconst_1
        11: goto          15
        14: iconst_0
        15: ireturn
      StackMapTable: number_of_entries = 2
        frame_type = 14 /* same */
        frame_type = 64 /* same_locals_1_stack_item */
          stack = [ int ]
      LineNumberTable:
        line 389: 0
      LocalVariableTable:
        Start  Length  Slot  Name   Signature
            0      16     0  this   Lcoursier/util/shaded/org/jsoup/parser/Token;

  final coursier.util.shaded.org.jsoup.parser.Token$Comment asComment();
    descriptor: ()Lcoursier/util/shaded/org/jsoup/parser/Token$Comment;
    flags: (0x0010) ACC_FINAL
    Code:
      stack=1, locals=1, args_size=1
         0: aload_0
         1: checkcast     #19                 // class coursier/util/shaded/org/jsoup/parser/Token$Comment
         4: areturn
      LineNumberTable:
        line 393: 0
      LocalVariableTable:
        Start  Length  Slot  Name   Signature
            0       5     0  this   Lcoursier/util/shaded/org/jsoup/parser/Token;

  final boolean isCharacter();
    descriptor: ()Z
    flags: (0x0010) ACC_FINAL
    Code:
      stack=2, locals=1, args_size=1
         0: aload_0
         1: getfield      #72                 // Field type:Lcoursier/util/shaded/org/jsoup/parser/Token$TokenType;
         4: getstatic     #94                 // Field coursier/util/shaded/org/jsoup/parser/Token$TokenType.Character:Lcoursier/util/shaded/org/jsoup/parser/Token$TokenType;
         7: if_acmpne     14
        10: iconst_1
        11: goto          15
        14: iconst_0
        15: ireturn
      StackMapTable: number_of_entries = 2
        frame_type = 14 /* same */
        frame_type = 64 /* same_locals_1_stack_item */
          stack = [ int ]
      LineNumberTable:
        line 397: 0
      LocalVariableTable:
        Start  Length  Slot  Name   Signature
            0      16     0  this   Lcoursier/util/shaded/org/jsoup/parser/Token;

  final boolean isCData();
    descriptor: ()Z
    flags: (0x0010) ACC_FINAL
    Code:
      stack=1, locals=1, args_size=1
         0: aload_0
         1: instanceof    #22                 // class coursier/util/shaded/org/jsoup/parser/Token$CData
         4: ireturn
      LineNumberTable:
        line 401: 0
      LocalVariableTable:
        Start  Length  Slot  Name   Signature
            0       5     0  this   Lcoursier/util/shaded/org/jsoup/parser/Token;

  final coursier.util.shaded.org.jsoup.parser.Token$Character asCharacter();
    descriptor: ()Lcoursier/util/shaded/org/jsoup/parser/Token$Character;
    flags: (0x0010) ACC_FINAL
    Code:
      stack=1, locals=1, args_size=1
         0: aload_0
         1: checkcast     #25                 // class coursier/util/shaded/org/jsoup/parser/Token$Character
         4: areturn
      LineNumberTable:
        line 405: 0
      LocalVariableTable:
        Start  Length  Slot  Name   Signature
            0       5     0  this   Lcoursier/util/shaded/org/jsoup/parser/Token;

  final boolean isEOF();
    descriptor: ()Z
    flags: (0x0010) ACC_FINAL
    Code:
      stack=2, locals=1, args_size=1
         0: aload_0
         1: getfield      #72                 // Field type:Lcoursier/util/shaded/org/jsoup/parser/Token$TokenType;
         4: getstatic     #100                // Field coursier/util/shaded/org/jsoup/parser/Token$TokenType.EOF:Lcoursier/util/shaded/org/jsoup/parser/Token$TokenType;
         7: if_acmpne     14
        10: iconst_1
        11: goto          15
        14: iconst_0
        15: ireturn
      StackMapTable: number_of_entries = 2
        frame_type = 14 /* same */
        frame_type = 64 /* same_locals_1_stack_item */
          stack = [ int ]
      LineNumberTable:
        line 409: 0
      LocalVariableTable:
        Start  Length  Slot  Name   Signature
            0      16     0  this   Lcoursier/util/shaded/org/jsoup/parser/Token;

  coursier.util.shaded.org.jsoup.parser.Token(coursier.util.shaded.org.jsoup.parser.Token$1);
    descriptor: (Lcoursier/util/shaded/org/jsoup/parser/Token$1;)V
    flags: (0x1000) ACC_SYNTHETIC
    Code:
      stack=1, locals=2, args_size=2
         0: aload_0
         1: invokespecial #102                // Method "<init>":()V
         4: return
      LineNumberTable:
        line 11: 0
      LocalVariableTable:
        Start  Length  Slot  Name   Signature
            0       5     0  this   Lcoursier/util/shaded/org/jsoup/parser/Token;
            0       5     1    x0   Lcoursier/util/shaded/org/jsoup/parser/Token$1;
}
InnerClasses:
  public static final #8= #7 of #2;       // TokenType=class coursier/util/shaded/org/jsoup/parser/Token$TokenType of class coursier/util/shaded/org/jsoup/parser/Token
  static final #11= #10 of #2;            // Doctype=class coursier/util/shaded/org/jsoup/parser/Token$Doctype of class coursier/util/shaded/org/jsoup/parser/Token
  static final #14= #13 of #2;            // StartTag=class coursier/util/shaded/org/jsoup/parser/Token$StartTag of class coursier/util/shaded/org/jsoup/parser/Token
  static final #17= #16 of #2;            // EndTag=class coursier/util/shaded/org/jsoup/parser/Token$EndTag of class coursier/util/shaded/org/jsoup/parser/Token
  static final #20= #19 of #2;            // Comment=class coursier/util/shaded/org/jsoup/parser/Token$Comment of class coursier/util/shaded/org/jsoup/parser/Token
  static final #23= #22 of #2;            // CData=class coursier/util/shaded/org/jsoup/parser/Token$CData of class coursier/util/shaded/org/jsoup/parser/Token
  static #26= #25 of #2;                  // Character=class coursier/util/shaded/org/jsoup/parser/Token$Character of class coursier/util/shaded/org/jsoup/parser/Token
  static #28;                             // class coursier/util/shaded/org/jsoup/parser/Token$1
  static final #31= #30 of #2;            // EOF=class coursier/util/shaded/org/jsoup/parser/Token$EOF of class coursier/util/shaded/org/jsoup/parser/Token
  static abstract #34= #33 of #2;         // Tag=class coursier/util/shaded/org/jsoup/parser/Token$Tag of class coursier/util/shaded/org/jsoup/parser/Token
SourceFile: "Token.java"
