Classfile /Users/mw/Projects/slang-braindump/.jar/jar8/assemble/slang-braindump/assemble/content/com/fasterxml/jackson/databind/introspect/AccessorNamingStrategy$Base.class
  Last modified May 29, 2022; size 1330 bytes
  SHA-256 checksum 66b1070742523761abcb1d35f021674f22f4557342e1e4154cf5a1354bec607e
  Compiled from "AccessorNamingStrategy.java"
public class com.fasterxml.jackson.databind.introspect.AccessorNamingStrategy$Base extends com.fasterxml.jackson.databind.introspect.AccessorNamingStrategy implements java.io.Serializable
  minor version: 0
  major version: 52
  flags: (0x0021) ACC_PUBLIC, ACC_SUPER
  this_class: #2                          // com/fasterxml/jackson/databind/introspect/AccessorNamingStrategy$Base
  super_class: #3                         // com/fasterxml/jackson/databind/introspect/AccessorNamingStrategy
  interfaces: 1, fields: 1, methods: 5, attributes: 2
Constant pool:
   #1 = Methodref          #3.#33         // com/fasterxml/jackson/databind/introspect/AccessorNamingStrategy."<init>":()V
   #2 = Class              #34            // com/fasterxml/jackson/databind/introspect/AccessorNamingStrategy$Base
   #3 = Class              #35            // com/fasterxml/jackson/databind/introspect/AccessorNamingStrategy
   #4 = Class              #36            // java/io/Serializable
   #5 = Utf8               serialVersionUID
   #6 = Utf8               J
   #7 = Utf8               ConstantValue
   #8 = Long               1l
  #10 = Utf8               <init>
  #11 = Utf8               ()V
  #12 = Utf8               Code
  #13 = Utf8               LineNumberTable
  #14 = Utf8               LocalVariableTable
  #15 = Utf8               this
  #16 = Utf8               Base
  #17 = Utf8               InnerClasses
  #18 = Utf8               Lcom/fasterxml/jackson/databind/introspect/AccessorNamingStrategy$Base;
  #19 = Utf8               findNameForIsGetter
  #20 = Utf8               (Lcom/fasterxml/jackson/databind/introspect/AnnotatedMethod;Ljava/lang/String;)Ljava/lang/String;
  #21 = Utf8               method
  #22 = Utf8               Lcom/fasterxml/jackson/databind/introspect/AnnotatedMethod;
  #23 = Utf8               name
  #24 = Utf8               Ljava/lang/String;
  #25 = Utf8               findNameForRegularGetter
  #26 = Utf8               findNameForMutator
  #27 = Utf8               modifyFieldName
  #28 = Utf8               (Lcom/fasterxml/jackson/databind/introspect/AnnotatedField;Ljava/lang/String;)Ljava/lang/String;
  #29 = Utf8               field
  #30 = Utf8               Lcom/fasterxml/jackson/databind/introspect/AnnotatedField;
  #31 = Utf8               SourceFile
  #32 = Utf8               AccessorNamingStrategy.java
  #33 = NameAndType        #10:#11        // "<init>":()V
  #34 = Utf8               com/fasterxml/jackson/databind/introspect/AccessorNamingStrategy$Base
  #35 = Utf8               com/fasterxml/jackson/databind/introspect/AccessorNamingStrategy
  #36 = Utf8               java/io/Serializable
{
  private static final long serialVersionUID;
    descriptor: J
    flags: (0x001a) ACC_PRIVATE, ACC_STATIC, ACC_FINAL
    ConstantValue: long 1l

  public com.fasterxml.jackson.databind.introspect.AccessorNamingStrategy$Base();
    descriptor: ()V
    flags: (0x0001) ACC_PUBLIC
    Code:
      stack=1, locals=1, args_size=1
         0: aload_0
         1: invokespecial #1                  // Method com/fasterxml/jackson/databind/introspect/AccessorNamingStrategy."<init>":()V
         4: return
      LineNumberTable:
        line 109: 0
      LocalVariableTable:
        Start  Length  Slot  Name   Signature
            0       5     0  this   Lcom/fasterxml/jackson/databind/introspect/AccessorNamingStrategy$Base;

  public java.lang.String findNameForIsGetter(com.fasterxml.jackson.databind.introspect.AnnotatedMethod, java.lang.String);
    descriptor: (Lcom/fasterxml/jackson/databind/introspect/AnnotatedMethod;Ljava/lang/String;)Ljava/lang/String;
    flags: (0x0001) ACC_PUBLIC
    Code:
      stack=1, locals=3, args_size=3
         0: aconst_null
         1: areturn
      LineNumberTable:
        line 117: 0
      LocalVariableTable:
        Start  Length  Slot  Name   Signature
            0       2     0  this   Lcom/fasterxml/jackson/databind/introspect/AccessorNamingStrategy$Base;
            0       2     1 method   Lcom/fasterxml/jackson/databind/introspect/AnnotatedMethod;
            0       2     2  name   Ljava/lang/String;

  public java.lang.String findNameForRegularGetter(com.fasterxml.jackson.databind.introspect.AnnotatedMethod, java.lang.String);
    descriptor: (Lcom/fasterxml/jackson/databind/introspect/AnnotatedMethod;Ljava/lang/String;)Ljava/lang/String;
    flags: (0x0001) ACC_PUBLIC
    Code:
      stack=1, locals=3, args_size=3
         0: aconst_null
         1: areturn
      LineNumberTable:
        line 122: 0
      LocalVariableTable:
        Start  Length  Slot  Name   Signature
            0       2     0  this   Lcom/fasterxml/jackson/databind/introspect/AccessorNamingStrategy$Base;
            0       2     1 method   Lcom/fasterxml/jackson/databind/introspect/AnnotatedMethod;
            0       2     2  name   Ljava/lang/String;

  public java.lang.String findNameForMutator(com.fasterxml.jackson.databind.introspect.AnnotatedMethod, java.lang.String);
    descriptor: (Lcom/fasterxml/jackson/databind/introspect/AnnotatedMethod;Ljava/lang/String;)Ljava/lang/String;
    flags: (0x0001) ACC_PUBLIC
    Code:
      stack=1, locals=3, args_size=3
         0: aconst_null
         1: areturn
      LineNumberTable:
        line 127: 0
      LocalVariableTable:
        Start  Length  Slot  Name   Signature
            0       2     0  this   Lcom/fasterxml/jackson/databind/introspect/AccessorNamingStrategy$Base;
            0       2     1 method   Lcom/fasterxml/jackson/databind/introspect/AnnotatedMethod;
            0       2     2  name   Ljava/lang/String;

  public java.lang.String modifyFieldName(com.fasterxml.jackson.databind.introspect.AnnotatedField, java.lang.String);
    descriptor: (Lcom/fasterxml/jackson/databind/introspect/AnnotatedField;Ljava/lang/String;)Ljava/lang/String;
    flags: (0x0001) ACC_PUBLIC
    Code:
      stack=1, locals=3, args_size=3
         0: aload_2
         1: areturn
      LineNumberTable:
        line 132: 0
      LocalVariableTable:
        Start  Length  Slot  Name   Signature
            0       2     0  this   Lcom/fasterxml/jackson/databind/introspect/AccessorNamingStrategy$Base;
            0       2     1 field   Lcom/fasterxml/jackson/databind/introspect/AnnotatedField;
            0       2     2  name   Ljava/lang/String;
}
SourceFile: "AccessorNamingStrategy.java"
InnerClasses:
  public static #16= #2 of #3;            // Base=class com/fasterxml/jackson/databind/introspect/AccessorNamingStrategy$Base of class com/fasterxml/jackson/databind/introspect/AccessorNamingStrategy
