Classfile /Users/mw/Projects/slang-braindump/.jar/jar8/assemble/slang-braindump/assemble/content/com/fasterxml/jackson/databind/introspect/MemberKey.class
  Last modified May 29, 2022; size 2595 bytes
  SHA-256 checksum 5dd8eb1ca9a745ba54aefa781c847cdeed5080c0460c582e52c53547e94d2a88
  Compiled from "MemberKey.java"
public final class com.fasterxml.jackson.databind.introspect.MemberKey
  minor version: 0
  major version: 52
  flags: (0x0031) ACC_PUBLIC, ACC_FINAL, ACC_SUPER
  this_class: #19                         // com/fasterxml/jackson/databind/introspect/MemberKey
  super_class: #22                        // java/lang/Object
  interfaces: 0, fields: 3, methods: 9, attributes: 1
Constant pool:
    #1 = Methodref          #77.#78       // java/lang/reflect/Method.getName:()Ljava/lang/String;
    #2 = Methodref          #77.#79       // java/lang/reflect/Method.getParameterTypes:()[Ljava/lang/Class;
    #3 = Methodref          #19.#80       // com/fasterxml/jackson/databind/introspect/MemberKey."<init>":(Ljava/lang/String;[Ljava/lang/Class;)V
    #4 = String             #81           //
    #5 = Methodref          #82.#79       // java/lang/reflect/Constructor.getParameterTypes:()[Ljava/lang/Class;
    #6 = Methodref          #22.#83       // java/lang/Object."<init>":()V
    #7 = Fieldref           #19.#84       // com/fasterxml/jackson/databind/introspect/MemberKey._name:Ljava/lang/String;
    #8 = Fieldref           #19.#85       // com/fasterxml/jackson/databind/introspect/MemberKey.NO_CLASSES:[Ljava/lang/Class;
    #9 = Fieldref           #19.#86       // com/fasterxml/jackson/databind/introspect/MemberKey._argTypes:[Ljava/lang/Class;
   #10 = Class              #87           // java/lang/StringBuilder
   #11 = Methodref          #10.#83       // java/lang/StringBuilder."<init>":()V
   #12 = Methodref          #10.#88       // java/lang/StringBuilder.append:(Ljava/lang/String;)Ljava/lang/StringBuilder;
   #13 = String             #89           // (
   #14 = Methodref          #10.#90       // java/lang/StringBuilder.append:(I)Ljava/lang/StringBuilder;
   #15 = String             #91           // -args)
   #16 = Methodref          #10.#92       // java/lang/StringBuilder.toString:()Ljava/lang/String;
   #17 = Methodref          #93.#94       // java/lang/String.hashCode:()I
   #18 = Methodref          #22.#95       // java/lang/Object.getClass:()Ljava/lang/Class;
   #19 = Class              #96           // com/fasterxml/jackson/databind/introspect/MemberKey
   #20 = Methodref          #93.#97       // java/lang/String.equals:(Ljava/lang/Object;)Z
   #21 = Class              #98           // java/lang/Class
   #22 = Class              #99           // java/lang/Object
   #23 = Utf8               NO_CLASSES
   #24 = Utf8               [Ljava/lang/Class;
   #25 = Utf8               Signature
   #26 = Utf8               [Ljava/lang/Class<*>;
   #27 = Utf8               _name
   #28 = Utf8               Ljava/lang/String;
   #29 = Utf8               _argTypes
   #30 = Utf8               <init>
   #31 = Utf8               (Ljava/lang/reflect/Method;)V
   #32 = Utf8               Code
   #33 = Utf8               LineNumberTable
   #34 = Utf8               LocalVariableTable
   #35 = Utf8               this
   #36 = Utf8               Lcom/fasterxml/jackson/databind/introspect/MemberKey;
   #37 = Utf8               m
   #38 = Utf8               Ljava/lang/reflect/Method;
   #39 = Utf8               (Ljava/lang/reflect/Constructor;)V
   #40 = Utf8               ctor
   #41 = Utf8               Ljava/lang/reflect/Constructor;
   #42 = Utf8               LocalVariableTypeTable
   #43 = Utf8               Ljava/lang/reflect/Constructor<*>;
   #44 = Utf8               (Ljava/lang/reflect/Constructor<*>;)V
   #45 = Utf8               (Ljava/lang/String;[Ljava/lang/Class;)V
   #46 = Utf8               name
   #47 = Utf8               argTypes
   #48 = Utf8               StackMapTable
   #49 = Class              #96           // com/fasterxml/jackson/databind/introspect/MemberKey
   #50 = Class              #100          // java/lang/String
   #51 = Class              #24           // "[Ljava/lang/Class;"
   #52 = Utf8               (Ljava/lang/String;[Ljava/lang/Class<*>;)V
   #53 = Utf8               getName
   #54 = Utf8               ()Ljava/lang/String;
   #55 = Utf8               argCount
   #56 = Utf8               ()I
   #57 = Utf8               toString
   #58 = Utf8               hashCode
   #59 = Utf8               equals
   #60 = Utf8               (Ljava/lang/Object;)Z
   #61 = Utf8               type1
   #62 = Utf8               Ljava/lang/Class;
   #63 = Utf8               type2
   #64 = Utf8               i
   #65 = Utf8               I
   #66 = Utf8               o
   #67 = Utf8               Ljava/lang/Object;
   #68 = Utf8               other
   #69 = Utf8               otherArgs
   #70 = Utf8               len
   #71 = Utf8               Ljava/lang/Class<*>;
   #72 = Class              #98           // java/lang/Class
   #73 = Utf8               <clinit>
   #74 = Utf8               ()V
   #75 = Utf8               SourceFile
   #76 = Utf8               MemberKey.java
   #77 = Class              #101          // java/lang/reflect/Method
   #78 = NameAndType        #53:#54       // getName:()Ljava/lang/String;
   #79 = NameAndType        #102:#103     // getParameterTypes:()[Ljava/lang/Class;
   #80 = NameAndType        #30:#45       // "<init>":(Ljava/lang/String;[Ljava/lang/Class;)V
   #81 = Utf8
   #82 = Class              #104          // java/lang/reflect/Constructor
   #83 = NameAndType        #30:#74       // "<init>":()V
   #84 = NameAndType        #27:#28       // _name:Ljava/lang/String;
   #85 = NameAndType        #23:#24       // NO_CLASSES:[Ljava/lang/Class;
   #86 = NameAndType        #29:#24       // _argTypes:[Ljava/lang/Class;
   #87 = Utf8               java/lang/StringBuilder
   #88 = NameAndType        #105:#106     // append:(Ljava/lang/String;)Ljava/lang/StringBuilder;
   #89 = Utf8               (
   #90 = NameAndType        #105:#107     // append:(I)Ljava/lang/StringBuilder;
   #91 = Utf8               -args)
   #92 = NameAndType        #57:#54       // toString:()Ljava/lang/String;
   #93 = Class              #100          // java/lang/String
   #94 = NameAndType        #58:#56       // hashCode:()I
   #95 = NameAndType        #108:#109     // getClass:()Ljava/lang/Class;
   #96 = Utf8               com/fasterxml/jackson/databind/introspect/MemberKey
   #97 = NameAndType        #59:#60       // equals:(Ljava/lang/Object;)Z
   #98 = Utf8               java/lang/Class
   #99 = Utf8               java/lang/Object
  #100 = Utf8               java/lang/String
  #101 = Utf8               java/lang/reflect/Method
  #102 = Utf8               getParameterTypes
  #103 = Utf8               ()[Ljava/lang/Class;
  #104 = Utf8               java/lang/reflect/Constructor
  #105 = Utf8               append
  #106 = Utf8               (Ljava/lang/String;)Ljava/lang/StringBuilder;
  #107 = Utf8               (I)Ljava/lang/StringBuilder;
  #108 = Utf8               getClass
  #109 = Utf8               ()Ljava/lang/Class;
{
  static final java.lang.Class<?>[] NO_CLASSES;
    descriptor: [Ljava/lang/Class;
    flags: (0x0018) ACC_STATIC, ACC_FINAL
    Signature: #26                          // [Ljava/lang/Class<*>;

  final java.lang.String _name;
    descriptor: Ljava/lang/String;
    flags: (0x0010) ACC_FINAL

  final java.lang.Class<?>[] _argTypes;
    descriptor: [Ljava/lang/Class;
    flags: (0x0010) ACC_FINAL
    Signature: #26                          // [Ljava/lang/Class<*>;

  public com.fasterxml.jackson.databind.introspect.MemberKey(java.lang.reflect.Method);
    descriptor: (Ljava/lang/reflect/Method;)V
    flags: (0x0001) ACC_PUBLIC
    Code:
      stack=3, locals=2, args_size=2
         0: aload_0
         1: aload_1
         2: invokevirtual #1                  // Method java/lang/reflect/Method.getName:()Ljava/lang/String;
         5: aload_1
         6: invokevirtual #2                  // Method java/lang/reflect/Method.getParameterTypes:()[Ljava/lang/Class;
         9: invokespecial #3                  // Method "<init>":(Ljava/lang/String;[Ljava/lang/Class;)V
        12: return
      LineNumberTable:
        line 20: 0
        line 21: 12
      LocalVariableTable:
        Start  Length  Slot  Name   Signature
            0      13     0  this   Lcom/fasterxml/jackson/databind/introspect/MemberKey;
            0      13     1     m   Ljava/lang/reflect/Method;

  public com.fasterxml.jackson.databind.introspect.MemberKey(java.lang.reflect.Constructor<?>);
    descriptor: (Ljava/lang/reflect/Constructor;)V
    flags: (0x0001) ACC_PUBLIC
    Code:
      stack=3, locals=2, args_size=2
         0: aload_0
         1: ldc           #4                  // String
         3: aload_1
         4: invokevirtual #5                  // Method java/lang/reflect/Constructor.getParameterTypes:()[Ljava/lang/Class;
         7: invokespecial #3                  // Method "<init>":(Ljava/lang/String;[Ljava/lang/Class;)V
        10: return
      LineNumberTable:
        line 25: 0
        line 26: 10
      LocalVariableTable:
        Start  Length  Slot  Name   Signature
            0      11     0  this   Lcom/fasterxml/jackson/databind/introspect/MemberKey;
            0      11     1  ctor   Ljava/lang/reflect/Constructor;
      LocalVariableTypeTable:
        Start  Length  Slot  Name   Signature
            0      11     1  ctor   Ljava/lang/reflect/Constructor<*>;
    Signature: #44                          // (Ljava/lang/reflect/Constructor<*>;)V

  public com.fasterxml.jackson.databind.introspect.MemberKey(java.lang.String, java.lang.Class<?>[]);
    descriptor: (Ljava/lang/String;[Ljava/lang/Class;)V
    flags: (0x0001) ACC_PUBLIC
    Code:
      stack=2, locals=3, args_size=3
         0: aload_0
         1: invokespecial #6                  // Method java/lang/Object."<init>":()V
         4: aload_0
         5: aload_1
         6: putfield      #7                  // Field _name:Ljava/lang/String;
         9: aload_0
        10: aload_2
        11: ifnonnull     20
        14: getstatic     #8                  // Field NO_CLASSES:[Ljava/lang/Class;
        17: goto          21
        20: aload_2
        21: putfield      #9                  // Field _argTypes:[Ljava/lang/Class;
        24: return
      LineNumberTable:
        line 29: 0
        line 30: 4
        line 31: 9
        line 32: 24
      LocalVariableTable:
        Start  Length  Slot  Name   Signature
            0      25     0  this   Lcom/fasterxml/jackson/databind/introspect/MemberKey;
            0      25     1  name   Ljava/lang/String;
            0      25     2 argTypes   [Ljava/lang/Class;
      LocalVariableTypeTable:
        Start  Length  Slot  Name   Signature
            0      25     2 argTypes   [Ljava/lang/Class<*>;
      StackMapTable: number_of_entries = 2
        frame_type = 255 /* full_frame */
          offset_delta = 20
          locals = [ class com/fasterxml/jackson/databind/introspect/MemberKey, class java/lang/String, class "[Ljava/lang/Class;" ]
          stack = [ class com/fasterxml/jackson/databind/introspect/MemberKey ]
        frame_type = 255 /* full_frame */
          offset_delta = 0
          locals = [ class com/fasterxml/jackson/databind/introspect/MemberKey, class java/lang/String, class "[Ljava/lang/Class;" ]
          stack = [ class com/fasterxml/jackson/databind/introspect/MemberKey, class "[Ljava/lang/Class;" ]
    Signature: #52                          // (Ljava/lang/String;[Ljava/lang/Class<*>;)V

  public java.lang.String getName();
    descriptor: ()Ljava/lang/String;
    flags: (0x0001) ACC_PUBLIC
    Code:
      stack=1, locals=1, args_size=1
         0: aload_0
         1: getfield      #7                  // Field _name:Ljava/lang/String;
         4: areturn
      LineNumberTable:
        line 35: 0
      LocalVariableTable:
        Start  Length  Slot  Name   Signature
            0       5     0  this   Lcom/fasterxml/jackson/databind/introspect/MemberKey;

  public int argCount();
    descriptor: ()I
    flags: (0x0001) ACC_PUBLIC
    Code:
      stack=1, locals=1, args_size=1
         0: aload_0
         1: getfield      #9                  // Field _argTypes:[Ljava/lang/Class;
         4: arraylength
         5: ireturn
      LineNumberTable:
        line 39: 0
      LocalVariableTable:
        Start  Length  Slot  Name   Signature
            0       6     0  this   Lcom/fasterxml/jackson/databind/introspect/MemberKey;

  public java.lang.String toString();
    descriptor: ()Ljava/lang/String;
    flags: (0x0001) ACC_PUBLIC
    Code:
      stack=2, locals=1, args_size=1
         0: new           #10                 // class java/lang/StringBuilder
         3: dup
         4: invokespecial #11                 // Method java/lang/StringBuilder."<init>":()V
         7: aload_0
         8: getfield      #7                  // Field _name:Ljava/lang/String;
        11: invokevirtual #12                 // Method java/lang/StringBuilder.append:(Ljava/lang/String;)Ljava/lang/StringBuilder;
        14: ldc           #13                 // String (
        16: invokevirtual #12                 // Method java/lang/StringBuilder.append:(Ljava/lang/String;)Ljava/lang/StringBuilder;
        19: aload_0
        20: getfield      #9                  // Field _argTypes:[Ljava/lang/Class;
        23: arraylength
        24: invokevirtual #14                 // Method java/lang/StringBuilder.append:(I)Ljava/lang/StringBuilder;
        27: ldc           #15                 // String -args)
        29: invokevirtual #12                 // Method java/lang/StringBuilder.append:(Ljava/lang/String;)Ljava/lang/StringBuilder;
        32: invokevirtual #16                 // Method java/lang/StringBuilder.toString:()Ljava/lang/String;
        35: areturn
      LineNumberTable:
        line 44: 0
      LocalVariableTable:
        Start  Length  Slot  Name   Signature
            0      36     0  this   Lcom/fasterxml/jackson/databind/introspect/MemberKey;

  public int hashCode();
    descriptor: ()I
    flags: (0x0001) ACC_PUBLIC
    Code:
      stack=2, locals=1, args_size=1
         0: aload_0
         1: getfield      #7                  // Field _name:Ljava/lang/String;
         4: invokevirtual #17                 // Method java/lang/String.hashCode:()I
         7: aload_0
         8: getfield      #9                  // Field _argTypes:[Ljava/lang/Class;
        11: arraylength
        12: iadd
        13: ireturn
      LineNumberTable:
        line 49: 0
      LocalVariableTable:
        Start  Length  Slot  Name   Signature
            0      14     0  this   Lcom/fasterxml/jackson/databind/introspect/MemberKey;

  public boolean equals(java.lang.Object);
    descriptor: (Ljava/lang/Object;)Z
    flags: (0x0001) ACC_PUBLIC
    Code:
      stack=2, locals=8, args_size=2
         0: aload_1
         1: aload_0
         2: if_acmpne     7
         5: iconst_1
         6: ireturn
         7: aload_1
         8: ifnonnull     13
        11: iconst_0
        12: ireturn
        13: aload_1
        14: invokevirtual #18                 // Method java/lang/Object.getClass:()Ljava/lang/Class;
        17: aload_0
        18: invokevirtual #18                 // Method java/lang/Object.getClass:()Ljava/lang/Class;
        21: if_acmpeq     26
        24: iconst_0
        25: ireturn
        26: aload_1
        27: checkcast     #19                 // class com/fasterxml/jackson/databind/introspect/MemberKey
        30: astore_2
        31: aload_0
        32: getfield      #7                  // Field _name:Ljava/lang/String;
        35: aload_2
        36: getfield      #7                  // Field _name:Ljava/lang/String;
        39: invokevirtual #20                 // Method java/lang/String.equals:(Ljava/lang/Object;)Z
        42: ifne          47
        45: iconst_0
        46: ireturn
        47: aload_2
        48: getfield      #9                  // Field _argTypes:[Ljava/lang/Class;
        51: astore_3
        52: aload_0
        53: getfield      #9                  // Field _argTypes:[Ljava/lang/Class;
        56: arraylength
        57: istore        4
        59: aload_3
        60: arraylength
        61: iload         4
        63: if_icmpeq     68
        66: iconst_0
        67: ireturn
        68: iconst_0
        69: istore        5
        71: iload         5
        73: iload         4
        75: if_icmpge     111
        78: aload_3
        79: iload         5
        81: aaload
        82: astore        6
        84: aload_0
        85: getfield      #9                  // Field _argTypes:[Ljava/lang/Class;
        88: iload         5
        90: aaload
        91: astore        7
        93: aload         6
        95: aload         7
        97: if_acmpne     103
       100: goto          105
       103: iconst_0
       104: ireturn
       105: iinc          5, 1
       108: goto          71
       111: iconst_1
       112: ireturn
      LineNumberTable:
        line 55: 0
        line 56: 7
        line 57: 13
        line 58: 24
        line 60: 26
        line 61: 31
        line 62: 45
        line 64: 47
        line 65: 52
        line 66: 59
        line 67: 66
        line 69: 68
        line 70: 78
        line 71: 84
        line 72: 93
        line 73: 100
        line 92: 103
        line 69: 105
        line 94: 111
      LocalVariableTable:
        Start  Length  Slot  Name   Signature
           84      21     6 type1   Ljava/lang/Class;
           93      12     7 type2   Ljava/lang/Class;
           71      40     5     i   I
            0     113     0  this   Lcom/fasterxml/jackson/databind/introspect/MemberKey;
            0     113     1     o   Ljava/lang/Object;
           31      82     2 other   Lcom/fasterxml/jackson/databind/introspect/MemberKey;
           52      61     3 otherArgs   [Ljava/lang/Class;
           59      54     4   len   I
      LocalVariableTypeTable:
        Start  Length  Slot  Name   Signature
           84      21     6 type1   Ljava/lang/Class<*>;
           93      12     7 type2   Ljava/lang/Class<*>;
           52      61     3 otherArgs   [Ljava/lang/Class<*>;
      StackMapTable: number_of_entries = 9
        frame_type = 7 /* same */
        frame_type = 5 /* same */
        frame_type = 12 /* same */
        frame_type = 252 /* append */
          offset_delta = 20
          locals = [ class com/fasterxml/jackson/databind/introspect/MemberKey ]
        frame_type = 253 /* append */
          offset_delta = 20
          locals = [ class "[Ljava/lang/Class;", int ]
        frame_type = 252 /* append */
          offset_delta = 2
          locals = [ int ]
        frame_type = 253 /* append */
          offset_delta = 31
          locals = [ class java/lang/Class, class java/lang/Class ]
        frame_type = 249 /* chop */
          offset_delta = 1
        frame_type = 250 /* chop */
          offset_delta = 5

  static {};
    descriptor: ()V
    flags: (0x0008) ACC_STATIC
    Code:
      stack=1, locals=0, args_size=0
         0: iconst_0
         1: anewarray     #21                 // class java/lang/Class
         4: putstatic     #8                  // Field NO_CLASSES:[Ljava/lang/Class;
         7: return
      LineNumberTable:
        line 13: 0
}
SourceFile: "MemberKey.java"
