Classfile /Users/mw/Projects/slang-braindump/.jar/jar11/assemble/slang-braindump/assemble/content/org/scalactic/AccumulationLowPriorityImplicits$$anon$2.class
  Last modified May 29, 2022; size 4295 bytes
  SHA-256 checksum b77fc2b026903af707b240ec9d1872252986a9250049fef5a1800819c8928b73
  Compiled from "Accumulation.scala"
public final class org.scalactic.AccumulationLowPriorityImplicits$$anon$2 extends java.lang.Object implements org.scalactic.Accumulation$Combinable<scala.runtime.Nothing$, E, TRAVONCE>
  minor version: 0
  major version: 52
  flags: (0x0031) ACC_PUBLIC, ACC_FINAL, ACC_SUPER
  this_class: #2                          // org/scalactic/AccumulationLowPriorityImplicits$$anon$2
  super_class: #5                         // java/lang/Object
  interfaces: 1, fields: 1, methods: 4, attributes: 7
Constant pool:
    #1 = Utf8               org/scalactic/AccumulationLowPriorityImplicits$$anon$2
    #2 = Class              #1            // org/scalactic/AccumulationLowPriorityImplicits$$anon$2
    #3 = Utf8               Ljava/lang/Object;Lorg/scalactic/Accumulation$Combinable<Lscala/runtime/Nothing$;TE;TTRAVONCE;>;
    #4 = Utf8               java/lang/Object
    #5 = Class              #4            // java/lang/Object
    #6 = Utf8               org/scalactic/Accumulation$Combinable
    #7 = Class              #6            // org/scalactic/Accumulation$Combinable
    #8 = Utf8               Accumulation.scala
    #9 = Utf8               org/scalactic/AccumulationLowPriorityImplicits
   #10 = Class              #9            // org/scalactic/AccumulationLowPriorityImplicits
   #11 = Utf8               convertGenTraversableOnceToCombinable3
   #12 = Utf8               (Lscala/collection/IterableOnce;)Lorg/scalactic/Accumulation$Combinable;
   #13 = NameAndType        #11:#12       // convertGenTraversableOnceToCombinable3:(Lscala/collection/IterableOnce;)Lorg/scalactic/Accumulation$Combinable;
   #14 = Utf8               java/lang/invoke/MethodHandles$Lookup
   #15 = Class              #14           // java/lang/invoke/MethodHandles$Lookup
   #16 = Utf8               java/lang/invoke/MethodHandles
   #17 = Class              #16           // java/lang/invoke/MethodHandles
   #18 = Utf8               Lookup
   #19 = Utf8               org/scalactic/Accumulation
   #20 = Class              #19           // org/scalactic/Accumulation
   #21 = Utf8               Combinable
   #22 = Utf8               xs$2
   #23 = Utf8               Lscala/collection/IterableOnce;
   #24 = Utf8               combined
   #25 = Utf8               ()Lorg/scalactic/Or;
   #26 = Utf8               ()Lorg/scalactic/Or<TTRAVONCE;Lorg/scalactic/Every<TE;>;>;
   #27 = Utf8               scala/collection/IterableOnceExtensionMethods$
   #28 = Class              #27           // scala/collection/IterableOnceExtensionMethods$
   #29 = Utf8               MODULE$
   #30 = Utf8               Lscala/collection/IterableOnceExtensionMethods$;
   #31 = NameAndType        #29:#30       // MODULE$:Lscala/collection/IterableOnceExtensionMethods$;
   #32 = Fieldref           #28.#31       // scala/collection/IterableOnceExtensionMethods$.MODULE$:Lscala/collection/IterableOnceExtensionMethods$;
   #33 = Utf8               scala/collection/IterableOnce$
   #34 = Class              #33           // scala/collection/IterableOnce$
   #35 = Utf8               Lscala/collection/IterableOnce$;
   #36 = NameAndType        #29:#35       // MODULE$:Lscala/collection/IterableOnce$;
   #37 = Fieldref           #34.#36       // scala/collection/IterableOnce$.MODULE$:Lscala/collection/IterableOnce$;
   #38 = NameAndType        #22:#23       // xs$2:Lscala/collection/IterableOnce;
   #39 = Fieldref           #2.#38        // org/scalactic/AccumulationLowPriorityImplicits$$anon$2.xs$2:Lscala/collection/IterableOnce;
   #40 = Utf8               iterableOnceExtensionMethods
   #41 = Utf8               (Lscala/collection/IterableOnce;)Lscala/collection/IterableOnce;
   #42 = NameAndType        #40:#41       // iterableOnceExtensionMethods:(Lscala/collection/IterableOnce;)Lscala/collection/IterableOnce;
   #43 = Methodref          #34.#42       // scala/collection/IterableOnce$.iterableOnceExtensionMethods:(Lscala/collection/IterableOnce;)Lscala/collection/IterableOnce;
   #44 = Utf8               isEmpty$extension
   #45 = Utf8               (Lscala/collection/IterableOnce;)Z
   #46 = NameAndType        #44:#45       // isEmpty$extension:(Lscala/collection/IterableOnce;)Z
   #47 = Methodref          #28.#46       // scala/collection/IterableOnceExtensionMethods$.isEmpty$extension:(Lscala/collection/IterableOnce;)Z
   #48 = Utf8               scala/package$
   #49 = Class              #48           // scala/package$
   #50 = Utf8               Lscala/package$;
   #51 = NameAndType        #29:#50       // MODULE$:Lscala/package$;
   #52 = Fieldref           #49.#51       // scala/package$.MODULE$:Lscala/package$;
   #53 = Utf8               Right
   #54 = Utf8               ()Lscala/util/Right$;
   #55 = NameAndType        #53:#54       // Right:()Lscala/util/Right$;
   #56 = Methodref          #49.#55       // scala/package$.Right:()Lscala/util/Right$;
   #57 = Utf8               Vector
   #58 = Utf8               ()Lscala/collection/immutable/Vector$;
   #59 = NameAndType        #57:#58       // Vector:()Lscala/collection/immutable/Vector$;
   #60 = Methodref          #49.#59       // scala/package$.Vector:()Lscala/collection/immutable/Vector$;
   #61 = Utf8               scala/collection/immutable/Vector$
   #62 = Class              #61           // scala/collection/immutable/Vector$
   #63 = Utf8               empty
   #64 = Utf8               ()Lscala/collection/immutable/Vector;
   #65 = NameAndType        #63:#64       // empty:()Lscala/collection/immutable/Vector;
   #66 = Methodref          #62.#65       // scala/collection/immutable/Vector$.empty:()Lscala/collection/immutable/Vector;
   #67 = Utf8               scala/util/Right$
   #68 = Class              #67           // scala/util/Right$
   #69 = Utf8               apply
   #70 = Utf8               (Ljava/lang/Object;)Lscala/util/Right;
   #71 = NameAndType        #69:#70       // apply:(Ljava/lang/Object;)Lscala/util/Right;
   #72 = Methodref          #68.#71       // scala/util/Right$.apply:(Ljava/lang/Object;)Lscala/util/Right;
   #73 = Utf8               toIterable$extension
   #74 = Utf8               (Lscala/collection/IterableOnce;)Lscala/collection/Iterable;
   #75 = NameAndType        #73:#74       // toIterable$extension:(Lscala/collection/IterableOnce;)Lscala/collection/Iterable;
   #76 = Methodref          #28.#75       // scala/collection/IterableOnceExtensionMethods$.toIterable$extension:(Lscala/collection/IterableOnce;)Lscala/collection/Iterable;
   #77 = Utf8               Left
   #78 = Utf8               ()Lscala/util/Left$;
   #79 = NameAndType        #77:#78       // Left:()Lscala/util/Left$;
   #80 = Methodref          #49.#79       // scala/package$.Left:()Lscala/util/Left$;
   #81 = Utf8               scala/collection/Iterable
   #82 = Class              #81           // scala/collection/Iterable
   #83 = Utf8               tail
   #84 = Utf8               ()Ljava/lang/Object;
   #85 = NameAndType        #83:#84       // tail:()Ljava/lang/Object;
   #86 = InterfaceMethodref #82.#85       // scala/collection/Iterable.tail:()Ljava/lang/Object;
   #87 = Utf8               scala/collection/IterableOnceOps
   #88 = Class              #87           // scala/collection/IterableOnceOps
   #89 = Utf8               head
   #90 = NameAndType        #89:#84       // head:()Ljava/lang/Object;
   #91 = InterfaceMethodref #82.#90       // scala/collection/Iterable.head:()Ljava/lang/Object;
   #92 = Utf8               org/scalactic/Bad
   #93 = Class              #92           // org/scalactic/Bad
   #94 = Utf8               b
   #95 = NameAndType        #94:#84       // b:()Ljava/lang/Object;
   #96 = Methodref          #93.#95       // org/scalactic/Bad.b:()Ljava/lang/Object;
   #97 = Utf8               (Ljava/lang/Object;Ljava/lang/Object;)Ljava/lang/Object;
   #98 = MethodType         #97           //  (Ljava/lang/Object;Ljava/lang/Object;)Ljava/lang/Object;
   #99 = Utf8               $anonfun$combined$3
  #100 = Utf8               (Lorg/scalactic/Every;Lorg/scalactic/Bad;)Lorg/scalactic/Every;
  #101 = NameAndType        #99:#100      // $anonfun$combined$3:(Lorg/scalactic/Every;Lorg/scalactic/Bad;)Lorg/scalactic/Every;
  #102 = Methodref          #2.#101       // org/scalactic/AccumulationLowPriorityImplicits$$anon$2.$anonfun$combined$3:(Lorg/scalactic/Every;Lorg/scalactic/Bad;)Lorg/scalactic/Every;
  #103 = MethodHandle       6:#102        // REF_invokeStatic org/scalactic/AccumulationLowPriorityImplicits$$anon$2.$anonfun$combined$3:(Lorg/scalactic/Every;Lorg/scalactic/Bad;)Lorg/scalactic/Every;
  #104 = MethodType         #100          //  (Lorg/scalactic/Every;Lorg/scalactic/Bad;)Lorg/scalactic/Every;
  #105 = Integer            5
  #106 = Integer            1
  #107 = Utf8               java/lang/invoke/LambdaMetafactory
  #108 = Class              #107          // java/lang/invoke/LambdaMetafactory
  #109 = Utf8               altMetafactory
  #110 = Utf8               (Ljava/lang/invoke/MethodHandles$Lookup;Ljava/lang/String;Ljava/lang/invoke/MethodType;[Ljava/lang/Object;)Ljava/lang/invoke/CallSite;
  #111 = NameAndType        #109:#110     // altMetafactory:(Ljava/lang/invoke/MethodHandles$Lookup;Ljava/lang/String;Ljava/lang/invoke/MethodType;[Ljava/lang/Object;)Ljava/lang/invoke/CallSite;
  #112 = Methodref          #108.#111     // java/lang/invoke/LambdaMetafactory.altMetafactory:(Ljava/lang/invoke/MethodHandles$Lookup;Ljava/lang/String;Ljava/lang/invoke/MethodType;[Ljava/lang/Object;)Ljava/lang/invoke/CallSite;
  #113 = MethodHandle       6:#112        // REF_invokeStatic java/lang/invoke/LambdaMetafactory.altMetafactory:(Ljava/lang/invoke/MethodHandles$Lookup;Ljava/lang/String;Ljava/lang/invoke/MethodType;[Ljava/lang/Object;)Ljava/lang/invoke/CallSite;
  #114 = Utf8               ()Lscala/Function2;
  #115 = NameAndType        #69:#114      // apply:()Lscala/Function2;
  #116 = InvokeDynamic      #0:#115       // #0:apply:()Lscala/Function2;
  #117 = Utf8               foldLeft
  #118 = Utf8               (Ljava/lang/Object;Lscala/Function2;)Ljava/lang/Object;
  #119 = NameAndType        #117:#118     // foldLeft:(Ljava/lang/Object;Lscala/Function2;)Ljava/lang/Object;
  #120 = InterfaceMethodref #88.#119      // scala/collection/IterableOnceOps.foldLeft:(Ljava/lang/Object;Lscala/Function2;)Ljava/lang/Object;
  #121 = Utf8               org/scalactic/Every
  #122 = Class              #121          // org/scalactic/Every
  #123 = Utf8               scala/util/Left$
  #124 = Class              #123          // scala/util/Left$
  #125 = Utf8               (Ljava/lang/Object;)Lscala/util/Left;
  #126 = NameAndType        #69:#125      // apply:(Ljava/lang/Object;)Lscala/util/Left;
  #127 = Methodref          #124.#126     // scala/util/Left$.apply:(Ljava/lang/Object;)Lscala/util/Left;
  #128 = Utf8               org/scalactic/Or$
  #129 = Class              #128          // org/scalactic/Or$
  #130 = Utf8               Lorg/scalactic/Or$;
  #131 = NameAndType        #29:#130      // MODULE$:Lorg/scalactic/Or$;
  #132 = Fieldref           #129.#131     // org/scalactic/Or$.MODULE$:Lorg/scalactic/Or$;
  #133 = Utf8               from
  #134 = Utf8               (Lscala/util/Either;)Lorg/scalactic/Or;
  #135 = NameAndType        #133:#134     // from:(Lscala/util/Either;)Lorg/scalactic/Or;
  #136 = Methodref          #129.#135     // org/scalactic/Or$.from:(Lscala/util/Either;)Lorg/scalactic/Or;
  #137 = Utf8               i
  #138 = Utf8               Lscala/collection/Iterable;
  #139 = Utf8               either
  #140 = Utf8               Lscala/util/Either;
  #141 = Utf8               this
  #142 = Utf8               Lorg/scalactic/AccumulationLowPriorityImplicits$$anon$2;
  #143 = Utf8               scala/util/Either
  #144 = Class              #143          // scala/util/Either
  #145 = Utf8               x0$1
  #146 = Utf8               x1$1
  #147 = Utf8               scala/Tuple2
  #148 = Class              #147          // scala/Tuple2
  #149 = Utf8               <init>
  #150 = Utf8               (Ljava/lang/Object;Ljava/lang/Object;)V
  #151 = NameAndType        #149:#150     // "<init>":(Ljava/lang/Object;Ljava/lang/Object;)V
  #152 = Methodref          #148.#151     // scala/Tuple2."<init>":(Ljava/lang/Object;Ljava/lang/Object;)V
  #153 = Utf8               _1
  #154 = NameAndType        #153:#84      // _1:()Ljava/lang/Object;
  #155 = Methodref          #148.#154     // scala/Tuple2._1:()Ljava/lang/Object;
  #156 = Utf8               _2
  #157 = NameAndType        #156:#84      // _2:()Ljava/lang/Object;
  #158 = Methodref          #148.#157     // scala/Tuple2._2:()Ljava/lang/Object;
  #159 = Utf8               $plus$plus
  #160 = Utf8               (Lorg/scalactic/Every;)Lorg/scalactic/Many;
  #161 = NameAndType        #159:#160     // $plus$plus:(Lorg/scalactic/Every;)Lorg/scalactic/Many;
  #162 = Methodref          #122.#161     // org/scalactic/Every.$plus$plus:(Lorg/scalactic/Every;)Lorg/scalactic/Many;
  #163 = Utf8               scala/MatchError
  #164 = Class              #163          // scala/MatchError
  #165 = Utf8               (Ljava/lang/Object;)V
  #166 = NameAndType        #149:#165     // "<init>":(Ljava/lang/Object;)V
  #167 = Methodref          #164.#166     // scala/MatchError."<init>":(Ljava/lang/Object;)V
  #168 = Utf8               res
  #169 = Utf8               Lorg/scalactic/Every;
  #170 = Utf8               ele
  #171 = Utf8               Lorg/scalactic/Bad;
  #172 = Utf8               org/scalactic/Many
  #173 = Class              #172          // org/scalactic/Many
  #174 = Utf8               (Lorg/scalactic/AccumulationLowPriorityImplicits;Lscala/collection/IterableOnce;)V
  #175 = Utf8               $outer
  #176 = Utf8               ()V
  #177 = NameAndType        #149:#176     // "<init>":()V
  #178 = Methodref          #5.#177       // java/lang/Object."<init>":()V
  #179 = Utf8               Lorg/scalactic/AccumulationLowPriorityImplicits;
  #180 = Utf8               $deserializeLambda$
  #181 = Utf8               (Ljava/lang/invoke/SerializedLambda;)Ljava/lang/Object;
  #182 = Utf8               scala/runtime/LambdaDeserialize
  #183 = Class              #182          // scala/runtime/LambdaDeserialize
  #184 = Utf8               bootstrap
  #185 = Utf8               (Ljava/lang/invoke/MethodHandles$Lookup;Ljava/lang/String;Ljava/lang/invoke/MethodType;[Ljava/lang/invoke/MethodHandle;)Ljava/lang/invoke/CallSite;
  #186 = NameAndType        #184:#185     // bootstrap:(Ljava/lang/invoke/MethodHandles$Lookup;Ljava/lang/String;Ljava/lang/invoke/MethodType;[Ljava/lang/invoke/MethodHandle;)Ljava/lang/invoke/CallSite;
  #187 = Methodref          #183.#186     // scala/runtime/LambdaDeserialize.bootstrap:(Ljava/lang/invoke/MethodHandles$Lookup;Ljava/lang/String;Ljava/lang/invoke/MethodType;[Ljava/lang/invoke/MethodHandle;)Ljava/lang/invoke/CallSite;
  #188 = MethodHandle       6:#187        // REF_invokeStatic scala/runtime/LambdaDeserialize.bootstrap:(Ljava/lang/invoke/MethodHandles$Lookup;Ljava/lang/String;Ljava/lang/invoke/MethodType;[Ljava/lang/invoke/MethodHandle;)Ljava/lang/invoke/CallSite;
  #189 = Utf8               lambdaDeserialize
  #190 = NameAndType        #189:#181     // lambdaDeserialize:(Ljava/lang/invoke/SerializedLambda;)Ljava/lang/Object;
  #191 = InvokeDynamic      #1:#190       // #1:lambdaDeserialize:(Ljava/lang/invoke/SerializedLambda;)Ljava/lang/Object;
  #192 = Utf8               Code
  #193 = Utf8               StackMapTable
  #194 = Utf8               LineNumberTable
  #195 = Utf8               LocalVariableTable
  #196 = Utf8               Signature
  #197 = Utf8               MethodParameters
  #198 = Utf8               InnerClasses
  #199 = Utf8               EnclosingMethod
  #200 = Utf8               SourceFile
  #201 = Utf8               BootstrapMethods
  #202 = Utf8               ScalaInlineInfo
  #203 = Utf8               Scala
{
  private final scala.collection.IterableOnce xs$2;
    descriptor: Lscala/collection/IterableOnce;
    flags: (0x0012) ACC_PRIVATE, ACC_FINAL

  public org.scalactic.Or<TRAVONCE, org.scalactic.Every<E>> combined();
    descriptor: ()Lorg/scalactic/Or;
    flags: (0x0001) ACC_PUBLIC
    Code:
      stack=4, locals=3, args_size=1
         0: getstatic     #32                 // Field scala/collection/IterableOnceExtensionMethods$.MODULE$:Lscala/collection/IterableOnceExtensionMethods$;
         3: getstatic     #37                 // Field scala/collection/IterableOnce$.MODULE$:Lscala/collection/IterableOnce$;
         6: aload_0
         7: getfield      #39                 // Field xs$2:Lscala/collection/IterableOnce;
        10: invokevirtual #43                 // Method scala/collection/IterableOnce$.iterableOnceExtensionMethods:(Lscala/collection/IterableOnce;)Lscala/collection/IterableOnce;
        13: invokevirtual #47                 // Method scala/collection/IterableOnceExtensionMethods$.isEmpty$extension:(Lscala/collection/IterableOnce;)Z
        16: ifeq          40
        19: getstatic     #52                 // Field scala/package$.MODULE$:Lscala/package$;
        22: invokevirtual #56                 // Method scala/package$.Right:()Lscala/util/Right$;
        25: getstatic     #52                 // Field scala/package$.MODULE$:Lscala/package$;
        28: invokevirtual #60                 // Method scala/package$.Vector:()Lscala/collection/immutable/Vector$;
        31: invokevirtual #66                 // Method scala/collection/immutable/Vector$.empty:()Lscala/collection/immutable/Vector;
        34: invokevirtual #72                 // Method scala/util/Right$.apply:(Ljava/lang/Object;)Lscala/util/Right;
        37: goto          100
        40: getstatic     #32                 // Field scala/collection/IterableOnceExtensionMethods$.MODULE$:Lscala/collection/IterableOnceExtensionMethods$;
        43: getstatic     #37                 // Field scala/collection/IterableOnce$.MODULE$:Lscala/collection/IterableOnce$;
        46: aload_0
        47: getfield      #39                 // Field xs$2:Lscala/collection/IterableOnce;
        50: invokevirtual #43                 // Method scala/collection/IterableOnce$.iterableOnceExtensionMethods:(Lscala/collection/IterableOnce;)Lscala/collection/IterableOnce;
        53: invokevirtual #76                 // Method scala/collection/IterableOnceExtensionMethods$.toIterable$extension:(Lscala/collection/IterableOnce;)Lscala/collection/Iterable;
        56: astore_2
        57: getstatic     #52                 // Field scala/package$.MODULE$:Lscala/package$;
        60: invokevirtual #80                 // Method scala/package$.Left:()Lscala/util/Left$;
        63: aload_2
        64: invokeinterface #86,  1           // InterfaceMethod scala/collection/Iterable.tail:()Ljava/lang/Object;
        69: checkcast     #88                 // class scala/collection/IterableOnceOps
        72: aload_2
        73: invokeinterface #91,  1           // InterfaceMethod scala/collection/Iterable.head:()Ljava/lang/Object;
        78: checkcast     #93                 // class org/scalactic/Bad
        81: invokevirtual #96                 // Method org/scalactic/Bad.b:()Ljava/lang/Object;
        84: invokedynamic #116,  0            // InvokeDynamic #0:apply:()Lscala/Function2;
        89: invokeinterface #120,  3          // InterfaceMethod scala/collection/IterableOnceOps.foldLeft:(Ljava/lang/Object;Lscala/Function2;)Ljava/lang/Object;
        94: checkcast     #122                // class org/scalactic/Every
        97: invokevirtual #127                // Method scala/util/Left$.apply:(Ljava/lang/Object;)Lscala/util/Left;
       100: astore_1
       101: getstatic     #132                // Field org/scalactic/Or$.MODULE$:Lorg/scalactic/Or$;
       104: aload_1
       105: invokevirtual #136                // Method org/scalactic/Or$.from:(Lscala/util/Either;)Lorg/scalactic/Or;
       108: areturn
      StackMapTable: number_of_entries = 2
        frame_type = 40 /* same */
        frame_type = 123 /* same_locals_1_stack_item */
          stack = [ class scala/util/Either ]
      LineNumberTable:
        line 67: 0
        line 68: 19
        line 70: 40
        line 71: 57
        line 72: 63
        line 78: 101
      LocalVariableTable:
        Start  Length  Slot  Name   Signature
           57      43     2     i   Lscala/collection/Iterable;
          101       7     1 either   Lscala/util/Either;
            0     109     0  this   Lorg/scalactic/AccumulationLowPriorityImplicits$$anon$2;
    Signature: #26                          // ()Lorg/scalactic/Or<TTRAVONCE;Lorg/scalactic/Every<TE;>;>;

  public static final org.scalactic.Every $anonfun$combined$3(org.scalactic.Every, org.scalactic.Bad);
    descriptor: (Lorg/scalactic/Every;Lorg/scalactic/Bad;)Lorg/scalactic/Every;
    flags: (0x1019) ACC_PUBLIC, ACC_STATIC, ACC_FINAL, ACC_SYNTHETIC
    Code:
      stack=4, locals=6, args_size=2
         0: new           #148                // class scala/Tuple2
         3: dup
         4: aload_0
         5: aload_1
         6: invokespecial #152                // Method scala/Tuple2."<init>":(Ljava/lang/Object;Ljava/lang/Object;)V
         9: astore_3
        10: aload_3
        11: ifnull        49
        14: aload_3
        15: invokevirtual #155                // Method scala/Tuple2._1:()Ljava/lang/Object;
        18: checkcast     #122                // class org/scalactic/Every
        21: astore        4
        23: aload_3
        24: invokevirtual #158                // Method scala/Tuple2._2:()Ljava/lang/Object;
        27: checkcast     #93                 // class org/scalactic/Bad
        30: astore        5
        32: aload         4
        34: aload         5
        36: invokevirtual #96                 // Method org/scalactic/Bad.b:()Ljava/lang/Object;
        39: checkcast     #122                // class org/scalactic/Every
        42: invokevirtual #162                // Method org/scalactic/Every.$plus$plus:(Lorg/scalactic/Every;)Lorg/scalactic/Many;
        45: astore_2
        46: goto          61
        49: goto          52
        52: new           #164                // class scala/MatchError
        55: dup
        56: aload_3
        57: invokespecial #167                // Method scala/MatchError."<init>":(Ljava/lang/Object;)V
        60: athrow
        61: aload_2
        62: areturn
      StackMapTable: number_of_entries = 3
        frame_type = 253 /* append */
          offset_delta = 49
          locals = [ top, class scala/Tuple2 ]
        frame_type = 2 /* same */
        frame_type = 255 /* full_frame */
          offset_delta = 8
          locals = [ class org/scalactic/Every, class org/scalactic/Bad, class org/scalactic/Many, class scala/Tuple2, class org/scalactic/Every, class org/scalactic/Bad ]
          stack = []
      LineNumberTable:
        line 72: 0
        line 73: 32
        line 72: 49
      LocalVariableTable:
        Start  Length  Slot  Name   Signature
           23      26     4   res   Lorg/scalactic/Every;
           32      17     5   ele   Lorg/scalactic/Bad;
            0      63     0  x0$1   Lorg/scalactic/Every;
            0      63     1  x1$1   Lorg/scalactic/Bad;
    MethodParameters:
      Name                           Flags
      x0$1                           final
      x1$1                           final

  public org.scalactic.AccumulationLowPriorityImplicits$$anon$2(org.scalactic.AccumulationLowPriorityImplicits, scala.collection.IterableOnce);
    descriptor: (Lorg/scalactic/AccumulationLowPriorityImplicits;Lscala/collection/IterableOnce;)V
    flags: (0x0001) ACC_PUBLIC
    Code:
      stack=2, locals=3, args_size=3
         0: aload_0
         1: aload_2
         2: putfield      #39                 // Field xs$2:Lscala/collection/IterableOnce;
         5: aload_0
         6: invokespecial #178                // Method java/lang/Object."<init>":()V
         9: return
      LineNumberTable:
        line 63: 0
        line 64: 5
      LocalVariableTable:
        Start  Length  Slot  Name   Signature
            0      10     0  this   Lorg/scalactic/AccumulationLowPriorityImplicits$$anon$2;
            0      10     1 $outer   Lorg/scalactic/AccumulationLowPriorityImplicits;
            0      10     2  xs$2   Lscala/collection/IterableOnce;
    MethodParameters:
      Name                           Flags
      $outer                         final synthetic
      xs$2                           final

  private static java.lang.Object $deserializeLambda$(java.lang.invoke.SerializedLambda);
    descriptor: (Ljava/lang/invoke/SerializedLambda;)Ljava/lang/Object;
    flags: (0x100a) ACC_PRIVATE, ACC_STATIC, ACC_SYNTHETIC
    Code:
      stack=1, locals=1, args_size=1
         0: aload_0
         1: invokedynamic #191,  0            // InvokeDynamic #1:lambdaDeserialize:(Ljava/lang/invoke/SerializedLambda;)Ljava/lang/Object;
         6: areturn
}
InnerClasses:
  public static final #18= #15 of #17;    // Lookup=class java/lang/invoke/MethodHandles$Lookup of class java/lang/invoke/MethodHandles
  public static #21= #7 of #20;           // Combinable=class org/scalactic/Accumulation$Combinable of class org/scalactic/Accumulation
  public final #2;                        // class org/scalactic/AccumulationLowPriorityImplicits$$anon$2
EnclosingMethod: #10.#13                // org.scalactic.AccumulationLowPriorityImplicits.convertGenTraversableOnceToCombinable3
Signature: #3                           // Ljava/lang/Object;Lorg/scalactic/Accumulation$Combinable<Lscala/runtime/Nothing$;TE;TTRAVONCE;>;
SourceFile: "Accumulation.scala"
BootstrapMethods:
  0: #113 REF_invokeStatic java/lang/invoke/LambdaMetafactory.altMetafactory:(Ljava/lang/invoke/MethodHandles$Lookup;Ljava/lang/String;Ljava/lang/invoke/MethodType;[Ljava/lang/Object;)Ljava/lang/invoke/CallSite;
    Method arguments:
      #98 (Ljava/lang/Object;Ljava/lang/Object;)Ljava/lang/Object;
      #103 REF_invokeStatic org/scalactic/AccumulationLowPriorityImplicits$$anon$2.$anonfun$combined$3:(Lorg/scalactic/Every;Lorg/scalactic/Bad;)Lorg/scalactic/Every;
      #104 (Lorg/scalactic/Every;Lorg/scalactic/Bad;)Lorg/scalactic/Every;
      #105 5
      #106 1
      #104 (Lorg/scalactic/Every;Lorg/scalactic/Bad;)Lorg/scalactic/Every;
  1: #188 REF_invokeStatic scala/runtime/LambdaDeserialize.bootstrap:(Ljava/lang/invoke/MethodHandles$Lookup;Ljava/lang/String;Ljava/lang/invoke/MethodType;[Ljava/lang/invoke/MethodHandle;)Ljava/lang/invoke/CallSite;
    Method arguments:
      #103 REF_invokeStatic org/scalactic/AccumulationLowPriorityImplicits$$anon$2.$anonfun$combined$3:(Lorg/scalactic/Every;Lorg/scalactic/Bad;)Lorg/scalactic/Every;
  ScalaInlineInfo: length = 0x13 (unknown attribute)
   01 01 00 03 00 63 00 64 01 00 95 00 AE 01 00 18
   00 19 01
  Scala: length = 0x0 (unknown attribute)

