Classfile /Users/mw/Projects/slang-braindump/.jar/jar11/assemble/slang-braindump/assemble/content/org/scalactic/AnyDiffer.class
  Last modified May 29, 2022; size 3770 bytes
  SHA-256 checksum fdfbf94071737559eae03b1fd3dcd74f194cb60683eb21747026c068d46c8871
  Compiled from "Differ.scala"
public class org.scalactic.AnyDiffer implements org.scalactic.Differ
  minor version: 0
  major version: 52
  flags: (0x0021) ACC_PUBLIC, ACC_SUPER
  this_class: #2                          // org/scalactic/AnyDiffer
  super_class: #4                         // java/lang/Object
  interfaces: 1, fields: 0, methods: 3, attributes: 4
Constant pool:
    #1 = Utf8               org/scalactic/AnyDiffer
    #2 = Class              #1            // org/scalactic/AnyDiffer
    #3 = Utf8               java/lang/Object
    #4 = Class              #3            // java/lang/Object
    #5 = Utf8               org/scalactic/Differ
    #6 = Class              #5            // org/scalactic/Differ
    #7 = Utf8               Differ.scala
    #8 = Utf8               Lscala/reflect/ScalaSignature;
    #9 = Utf8               bytes
   #10 = Utf8               \u0006\u0005\t3Qa\u0002\u0005\u0001\u00111AQa\u0006\u0001\u0005\u0002eAQa\u0007\u0001\u0005\u0002qAQ\u0001\f\u0001\u0005\u00025:aA\u0010\u0005\t\u0002!ydAB\u0004\t\u0011\u0003A\u0001\tC\u0003\u0018\u000b\u0011\u0005\u0011IA\u0005B]f$\u0015N\u001a4fe*\u0011\u0011BC\u0001\ng\u000e\fG.Y2uS\u000eT\u0011aC\u0001\u0004_J<7c\u0001\u0001\u000e\'A\u0011a\"E\u0007\u0002\u001f)\t\u0001#A\u0003tG\u0006d\u0017-\u0003\u0002\u0013\u001f\t1\u0011I\\=SK\u001a\u0004\"\u0001F\u000b\u000e\u0003!I!A\u0006\u0005\u0003\r\u0011KgMZ3s\u0003\u0019a\u0014N\\5u}\r\u0001A#\u0001\u000e\u0011\u0005Q\u0001\u0011A\u00033jM\u001a,\'/\u001a8dKR!Q\u0004I\u0013(!\t!b$\u0003\u0002 \u0011\tQ\u0001K]3uif\u0004\u0016-\u001b:\t\u000b\u0005\u0012\u0001\u0019\u0001\u0012\u0002\u0003\u0005\u0004\"AD\u0012\n\u0005\u0011z!aA!os\")aE\u0001a\u0001E\u0005\t!\rC\u0003)\u0005\u0001\u0007\u0011&\u0001\u0006qe\u0016$H/\u001b4jKJ\u0004\"\u0001\u0006\u0016\n\u0005-B!A\u0003)sKR$\u0018NZ5fe\u0006AA-\u001b4g\u00136\u0004H\u000eF\u0003\u001e]=\u0002\u0014\u0007C\u0003\"\u0007\u0001\u0007!\u0005C\u0003\'\u0007\u0001\u0007!\u0005C\u0003)\u0007\u0001\u0007\u0011\u0006C\u00033\u0007\u0001\u00071\'A\u0005qe>\u001cWm]:fIB\u0019Ag\u000f\u0012\u000f\u0005UJ\u0004C\u0001\u001c\u0010\u001b\u00059$B\u0001\u001d\u0019\u0003\u0019a$o\\8u}%\u0011!hD\u0001\u0007!J,G-\u001a4\n\u0005qj$aA*fi*\u0011!hD\u0001\n\u0003:LH)\u001b4gKJ\u0004\"\u0001F\u0003\u0014\u0005\u0015QB#A
   #11 = Utf8               difference
   #12 = Utf8               (Ljava/lang/Object;Ljava/lang/Object;Lorg/scalactic/Prettifier;)Lorg/scalactic/PrettyPair;
   #13 = Utf8               a
   #14 = Utf8               b
   #15 = Utf8               prettifier
   #16 = Utf8               scala/Predef$
   #17 = Class              #16           // scala/Predef$
   #18 = Utf8               MODULE$
   #19 = Utf8               Lscala/Predef$;
   #20 = NameAndType        #18:#19       // MODULE$:Lscala/Predef$;
   #21 = Fieldref           #17.#20       // scala/Predef$.MODULE$:Lscala/Predef$;
   #22 = Utf8               Set
   #23 = Utf8               ()Lscala/collection/immutable/Set$;
   #24 = NameAndType        #22:#23       // Set:()Lscala/collection/immutable/Set$;
   #25 = Methodref          #17.#24       // scala/Predef$.Set:()Lscala/collection/immutable/Set$;
   #26 = Utf8               scala/collection/immutable/Set$
   #27 = Class              #26           // scala/collection/immutable/Set$
   #28 = Utf8               empty
   #29 = Utf8               ()Lscala/collection/immutable/Set;
   #30 = NameAndType        #28:#29       // empty:()Lscala/collection/immutable/Set;
   #31 = Methodref          #27.#30       // scala/collection/immutable/Set$.empty:()Lscala/collection/immutable/Set;
   #32 = Utf8               diffImpl
   #33 = Utf8               (Ljava/lang/Object;Ljava/lang/Object;Lorg/scalactic/Prettifier;Lscala/collection/immutable/Set;)Lorg/scalactic/PrettyPair;
   #34 = NameAndType        #32:#33       // diffImpl:(Ljava/lang/Object;Ljava/lang/Object;Lorg/scalactic/Prettifier;Lscala/collection/immutable/Set;)Lorg/scalactic/PrettyPair;
   #35 = Methodref          #2.#34        // org/scalactic/AnyDiffer.diffImpl:(Ljava/lang/Object;Ljava/lang/Object;Lorg/scalactic/Prettifier;Lscala/collection/immutable/Set;)Lorg/scalactic/PrettyPair;
   #36 = Utf8               this
   #37 = Utf8               Lorg/scalactic/AnyDiffer;
   #38 = Utf8               Ljava/lang/Object;
   #39 = Utf8               Lorg/scalactic/Prettifier;
   #40 = Utf8               (Ljava/lang/Object;Ljava/lang/Object;Lorg/scalactic/Prettifier;Lscala/collection/immutable/Set<Ljava/lang/Object;>;)Lorg/scalactic/PrettyPair;
   #41 = Utf8               processed
   #42 = Utf8               scala/Tuple2
   #43 = Class              #42           // scala/Tuple2
   #44 = Utf8               <init>
   #45 = Utf8               (Ljava/lang/Object;Ljava/lang/Object;)V
   #46 = NameAndType        #44:#45       // "<init>":(Ljava/lang/Object;Ljava/lang/Object;)V
   #47 = Methodref          #43.#46       // scala/Tuple2."<init>":(Ljava/lang/Object;Ljava/lang/Object;)V
   #48 = Utf8               _1
   #49 = Utf8               ()Ljava/lang/Object;
   #50 = NameAndType        #48:#49       // _1:()Ljava/lang/Object;
   #51 = Methodref          #43.#50       // scala/Tuple2._1:()Ljava/lang/Object;
   #52 = Utf8               _2
   #53 = NameAndType        #52:#49       // _2:()Ljava/lang/Object;
   #54 = Methodref          #43.#53       // scala/Tuple2._2:()Ljava/lang/Object;
   #55 = Utf8               java/lang/String
   #56 = Class              #55           // java/lang/String
   #57 = Utf8               org/scalactic/StringDiffer$
   #58 = Class              #57           // org/scalactic/StringDiffer$
   #59 = Utf8               Lorg/scalactic/StringDiffer$;
   #60 = NameAndType        #18:#59       // MODULE$:Lorg/scalactic/StringDiffer$;
   #61 = Fieldref           #58.#60       // org/scalactic/StringDiffer$.MODULE$:Lorg/scalactic/StringDiffer$;
   #62 = NameAndType        #11:#12       // difference:(Ljava/lang/Object;Ljava/lang/Object;Lorg/scalactic/Prettifier;)Lorg/scalactic/PrettyPair;
   #63 = Methodref          #58.#62       // org/scalactic/StringDiffer$.difference:(Ljava/lang/Object;Ljava/lang/Object;Lorg/scalactic/Prettifier;)Lorg/scalactic/PrettyPair;
   #64 = Utf8               scala/collection/Map
   #65 = Class              #64           // scala/collection/Map
   #66 = Utf8               org/scalactic/GenMapDiffer$
   #67 = Class              #66           // org/scalactic/GenMapDiffer$
   #68 = Utf8               Lorg/scalactic/GenMapDiffer$;
   #69 = NameAndType        #18:#68       // MODULE$:Lorg/scalactic/GenMapDiffer$;
   #70 = Fieldref           #67.#69       // org/scalactic/GenMapDiffer$.MODULE$:Lorg/scalactic/GenMapDiffer$;
   #71 = Methodref          #67.#62       // org/scalactic/GenMapDiffer$.difference:(Ljava/lang/Object;Ljava/lang/Object;Lorg/scalactic/Prettifier;)Lorg/scalactic/PrettyPair;
   #72 = Utf8               scala/collection/Seq
   #73 = Class              #72           // scala/collection/Seq
   #74 = Utf8               org/scalactic/GenSeqDiffer$
   #75 = Class              #74           // org/scalactic/GenSeqDiffer$
   #76 = Utf8               Lorg/scalactic/GenSeqDiffer$;
   #77 = NameAndType        #18:#76       // MODULE$:Lorg/scalactic/GenSeqDiffer$;
   #78 = Fieldref           #75.#77       // org/scalactic/GenSeqDiffer$.MODULE$:Lorg/scalactic/GenSeqDiffer$;
   #79 = Methodref          #75.#62       // org/scalactic/GenSeqDiffer$.difference:(Ljava/lang/Object;Ljava/lang/Object;Lorg/scalactic/Prettifier;)Lorg/scalactic/PrettyPair;
   #80 = Utf8               scala/collection/Set
   #81 = Class              #80           // scala/collection/Set
   #82 = Utf8               org/scalactic/GenSetDiffer$
   #83 = Class              #82           // org/scalactic/GenSetDiffer$
   #84 = Utf8               Lorg/scalactic/GenSetDiffer$;
   #85 = NameAndType        #18:#84       // MODULE$:Lorg/scalactic/GenSetDiffer$;
   #86 = Fieldref           #83.#85       // org/scalactic/GenSetDiffer$.MODULE$:Lorg/scalactic/GenSetDiffer$;
   #87 = Methodref          #83.#62       // org/scalactic/GenSetDiffer$.difference:(Ljava/lang/Object;Ljava/lang/Object;Lorg/scalactic/Prettifier;)Lorg/scalactic/PrettyPair;
   #88 = Utf8               scala/Product
   #89 = Class              #88           // scala/Product
   #90 = Utf8               org/scalactic/ObjectDiffer$
   #91 = Class              #90           // org/scalactic/ObjectDiffer$
   #92 = Utf8               Lorg/scalactic/ObjectDiffer$;
   #93 = NameAndType        #18:#92       // MODULE$:Lorg/scalactic/ObjectDiffer$;
   #94 = Fieldref           #91.#93       // org/scalactic/ObjectDiffer$.MODULE$:Lorg/scalactic/ObjectDiffer$;
   #95 = Methodref          #91.#34       // org/scalactic/ObjectDiffer$.diffImpl:(Ljava/lang/Object;Ljava/lang/Object;Lorg/scalactic/Prettifier;Lscala/collection/immutable/Set;)Lorg/scalactic/PrettyPair;
   #96 = Utf8               org/scalactic/PrettyPair
   #97 = Class              #96           // org/scalactic/PrettyPair
   #98 = Utf8               org/scalactic/Prettifier
   #99 = Class              #98           // org/scalactic/Prettifier
  #100 = Utf8               apply
  #101 = Utf8               (Ljava/lang/Object;)Ljava/lang/String;
  #102 = NameAndType        #100:#101     // apply:(Ljava/lang/Object;)Ljava/lang/String;
  #103 = InterfaceMethodref #99.#102      // org/scalactic/Prettifier.apply:(Ljava/lang/Object;)Ljava/lang/String;
  #104 = Utf8               scala/None$
  #105 = Class              #104          // scala/None$
  #106 = Utf8               Lscala/None$;
  #107 = NameAndType        #18:#106      // MODULE$:Lscala/None$;
  #108 = Fieldref           #105.#107     // scala/None$.MODULE$:Lscala/None$;
  #109 = Utf8               (Ljava/lang/String;Ljava/lang/String;Lscala/Option;)V
  #110 = NameAndType        #44:#109      // "<init>":(Ljava/lang/String;Ljava/lang/String;Lscala/Option;)V
  #111 = Methodref          #97.#110      // org/scalactic/PrettyPair."<init>":(Ljava/lang/String;Ljava/lang/String;Lscala/Option;)V
  #112 = Utf8               s1
  #113 = Utf8               s2
  #114 = Utf8               Lscala/collection/immutable/Set;
  #115 = Utf8               scala/collection/immutable/Set
  #116 = Class              #115          // scala/collection/immutable/Set
  #117 = Utf8               ()V
  #118 = NameAndType        #44:#117      // "<init>":()V
  #119 = Methodref          #4.#118       // java/lang/Object."<init>":()V
  #120 = Utf8               Code
  #121 = Utf8               LineNumberTable
  #122 = Utf8               LocalVariableTable
  #123 = Utf8               MethodParameters
  #124 = Utf8               StackMapTable
  #125 = Utf8               Signature
  #126 = Utf8               SourceFile
  #127 = Utf8               RuntimeVisibleAnnotations
  #128 = Utf8               ScalaInlineInfo
  #129 = Utf8               ScalaSig
{
  public org.scalactic.PrettyPair difference(java.lang.Object, java.lang.Object, org.scalactic.Prettifier);
    descriptor: (Ljava/lang/Object;Ljava/lang/Object;Lorg/scalactic/Prettifier;)Lorg/scalactic/PrettyPair;
    flags: (0x0001) ACC_PUBLIC
    Code:
      stack=5, locals=4, args_size=4
         0: aload_0
         1: aload_1
         2: aload_2
         3: aload_3
         4: getstatic     #21                 // Field scala/Predef$.MODULE$:Lscala/Predef$;
         7: invokevirtual #25                 // Method scala/Predef$.Set:()Lscala/collection/immutable/Set$;
        10: invokevirtual #31                 // Method scala/collection/immutable/Set$.empty:()Lscala/collection/immutable/Set;
        13: invokevirtual #35                 // Method diffImpl:(Ljava/lang/Object;Ljava/lang/Object;Lorg/scalactic/Prettifier;Lscala/collection/immutable/Set;)Lorg/scalactic/PrettyPair;
        16: areturn
      LineNumberTable:
        line 291: 0
      LocalVariableTable:
        Start  Length  Slot  Name   Signature
            0      17     0  this   Lorg/scalactic/AnyDiffer;
            0      17     1     a   Ljava/lang/Object;
            0      17     2     b   Ljava/lang/Object;
            0      17     3 prettifier   Lorg/scalactic/Prettifier;
    MethodParameters:
      Name                           Flags
      a                              final
      b                              final
      prettifier                     final

  public org.scalactic.PrettyPair diffImpl(java.lang.Object, java.lang.Object, org.scalactic.Prettifier, scala.collection.immutable.Set<java.lang.Object>);
    descriptor: (Ljava/lang/Object;Ljava/lang/Object;Lorg/scalactic/Prettifier;Lscala/collection/immutable/Set;)Lorg/scalactic/PrettyPair;
    flags: (0x0001) ACC_PUBLIC
    Code:
      stack=5, locals=27, args_size=5
         0: new           #43                 // class scala/Tuple2
         3: dup
         4: aload_1
         5: aload_2
         6: invokespecial #47                 // Method scala/Tuple2."<init>":(Ljava/lang/Object;Ljava/lang/Object;)V
         9: astore        6
        11: aload         6
        13: ifnull        82
        16: aload         6
        18: invokevirtual #51                 // Method scala/Tuple2._1:()Ljava/lang/Object;
        21: astore        7
        23: aload         6
        25: invokevirtual #54                 // Method scala/Tuple2._2:()Ljava/lang/Object;
        28: astore        8
        30: aload         7
        32: instanceof    #56                 // class java/lang/String
        35: ifeq          79
        38: aload         7
        40: checkcast     #56                 // class java/lang/String
        43: astore        9
        45: aload         8
        47: instanceof    #56                 // class java/lang/String
        50: ifeq          76
        53: aload         8
        55: checkcast     #56                 // class java/lang/String
        58: astore        10
        60: getstatic     #61                 // Field org/scalactic/StringDiffer$.MODULE$:Lorg/scalactic/StringDiffer$;
        63: aload         9
        65: aload         10
        67: aload_3
        68: invokevirtual #63                 // Method org/scalactic/StringDiffer$.difference:(Ljava/lang/Object;Ljava/lang/Object;Lorg/scalactic/Prettifier;)Lorg/scalactic/PrettyPair;
        71: astore        5
        73: goto          412
        76: goto          85
        79: goto          85
        82: goto          85
        85: aload         6
        87: ifnull        156
        90: aload         6
        92: invokevirtual #51                 // Method scala/Tuple2._1:()Ljava/lang/Object;
        95: astore        11
        97: aload         6
        99: invokevirtual #54                 // Method scala/Tuple2._2:()Ljava/lang/Object;
       102: astore        12
       104: aload         11
       106: instanceof    #65                 // class scala/collection/Map
       109: ifeq          153
       112: aload         11
       114: checkcast     #65                 // class scala/collection/Map
       117: astore        13
       119: aload         12
       121: instanceof    #65                 // class scala/collection/Map
       124: ifeq          150
       127: aload         12
       129: checkcast     #65                 // class scala/collection/Map
       132: astore        14
       134: getstatic     #70                 // Field org/scalactic/GenMapDiffer$.MODULE$:Lorg/scalactic/GenMapDiffer$;
       137: aload         13
       139: aload         14
       141: aload_3
       142: invokevirtual #71                 // Method org/scalactic/GenMapDiffer$.difference:(Ljava/lang/Object;Ljava/lang/Object;Lorg/scalactic/Prettifier;)Lorg/scalactic/PrettyPair;
       145: astore        5
       147: goto          412
       150: goto          159
       153: goto          159
       156: goto          159
       159: aload         6
       161: ifnull        230
       164: aload         6
       166: invokevirtual #51                 // Method scala/Tuple2._1:()Ljava/lang/Object;
       169: astore        15
       171: aload         6
       173: invokevirtual #54                 // Method scala/Tuple2._2:()Ljava/lang/Object;
       176: astore        16
       178: aload         15
       180: instanceof    #73                 // class scala/collection/Seq
       183: ifeq          227
       186: aload         15
       188: checkcast     #73                 // class scala/collection/Seq
       191: astore        17
       193: aload         16
       195: instanceof    #73                 // class scala/collection/Seq
       198: ifeq          224
       201: aload         16
       203: checkcast     #73                 // class scala/collection/Seq
       206: astore        18
       208: getstatic     #78                 // Field org/scalactic/GenSeqDiffer$.MODULE$:Lorg/scalactic/GenSeqDiffer$;
       211: aload         17
       213: aload         18
       215: aload_3
       216: invokevirtual #79                 // Method org/scalactic/GenSeqDiffer$.difference:(Ljava/lang/Object;Ljava/lang/Object;Lorg/scalactic/Prettifier;)Lorg/scalactic/PrettyPair;
       219: astore        5
       221: goto          412
       224: goto          233
       227: goto          233
       230: goto          233
       233: aload         6
       235: ifnull        304
       238: aload         6
       240: invokevirtual #51                 // Method scala/Tuple2._1:()Ljava/lang/Object;
       243: astore        19
       245: aload         6
       247: invokevirtual #54                 // Method scala/Tuple2._2:()Ljava/lang/Object;
       250: astore        20
       252: aload         19
       254: instanceof    #81                 // class scala/collection/Set
       257: ifeq          301
       260: aload         19
       262: checkcast     #81                 // class scala/collection/Set
       265: astore        21
       267: aload         20
       269: instanceof    #81                 // class scala/collection/Set
       272: ifeq          298
       275: aload         20
       277: checkcast     #81                 // class scala/collection/Set
       280: astore        22
       282: getstatic     #86                 // Field org/scalactic/GenSetDiffer$.MODULE$:Lorg/scalactic/GenSetDiffer$;
       285: aload         21
       287: aload         22
       289: aload_3
       290: invokevirtual #87                 // Method org/scalactic/GenSetDiffer$.difference:(Ljava/lang/Object;Ljava/lang/Object;Lorg/scalactic/Prettifier;)Lorg/scalactic/PrettyPair;
       293: astore        5
       295: goto          412
       298: goto          307
       301: goto          307
       304: goto          307
       307: aload         6
       309: ifnull        380
       312: aload         6
       314: invokevirtual #51                 // Method scala/Tuple2._1:()Ljava/lang/Object;
       317: astore        23
       319: aload         6
       321: invokevirtual #54                 // Method scala/Tuple2._2:()Ljava/lang/Object;
       324: astore        24
       326: aload         23
       328: instanceof    #89                 // class scala/Product
       331: ifeq          377
       334: aload         23
       336: checkcast     #89                 // class scala/Product
       339: astore        25
       341: aload         24
       343: instanceof    #89                 // class scala/Product
       346: ifeq          374
       349: aload         24
       351: checkcast     #89                 // class scala/Product
       354: astore        26
       356: getstatic     #94                 // Field org/scalactic/ObjectDiffer$.MODULE$:Lorg/scalactic/ObjectDiffer$;
       359: aload         25
       361: aload         26
       363: aload_3
       364: aload         4
       366: invokevirtual #95                 // Method org/scalactic/ObjectDiffer$.diffImpl:(Ljava/lang/Object;Ljava/lang/Object;Lorg/scalactic/Prettifier;Lscala/collection/immutable/Set;)Lorg/scalactic/PrettyPair;
       369: astore        5
       371: goto          412
       374: goto          383
       377: goto          383
       380: goto          383
       383: new           #97                 // class org/scalactic/PrettyPair
       386: dup
       387: aload_3
       388: aload_1
       389: invokeinterface #103,  2          // InterfaceMethod org/scalactic/Prettifier.apply:(Ljava/lang/Object;)Ljava/lang/String;
       394: aload_3
       395: aload_2
       396: invokeinterface #103,  2          // InterfaceMethod org/scalactic/Prettifier.apply:(Ljava/lang/Object;)Ljava/lang/String;
       401: getstatic     #108                // Field scala/None$.MODULE$:Lscala/None$;
       404: invokespecial #111                // Method org/scalactic/PrettyPair."<init>":(Ljava/lang/String;Ljava/lang/String;Lscala/Option;)V
       407: astore        5
       409: goto          412
       412: aload         5
       414: areturn
      StackMapTable: number_of_entries = 21
        frame_type = 255 /* full_frame */
          offset_delta = 76
          locals = [ class org/scalactic/AnyDiffer, class java/lang/Object, class java/lang/Object, class org/scalactic/Prettifier, class scala/collection/immutable/Set, top, class scala/Tuple2, class java/lang/Object, class java/lang/Object, class java/lang/String ]
          stack = []
        frame_type = 250 /* chop */
          offset_delta = 2
        frame_type = 249 /* chop */
          offset_delta = 2
        frame_type = 2 /* same */
        frame_type = 255 /* full_frame */
          offset_delta = 64
          locals = [ class org/scalactic/AnyDiffer, class java/lang/Object, class java/lang/Object, class org/scalactic/Prettifier, class scala/collection/immutable/Set, top, class scala/Tuple2, top, top, top, top, class java/lang/Object, class java/lang/Object, class scala/collection/Map ]
          stack = []
        frame_type = 250 /* chop */
          offset_delta = 2
        frame_type = 255 /* full_frame */
          offset_delta = 2
          locals = [ class org/scalactic/AnyDiffer, class java/lang/Object, class java/lang/Object, class org/scalactic/Prettifier, class scala/collection/immutable/Set, top, class scala/Tuple2 ]
          stack = []
        frame_type = 2 /* same */
        frame_type = 255 /* full_frame */
          offset_delta = 64
          locals = [ class org/scalactic/AnyDiffer, class java/lang/Object, class java/lang/Object, class org/scalactic/Prettifier, class scala/collection/immutable/Set, top, class scala/Tuple2, top, top, top, top, top, top, top, top, class java/lang/Object, class java/lang/Object, class scala/collection/Seq ]
          stack = []
        frame_type = 250 /* chop */
          offset_delta = 2
        frame_type = 255 /* full_frame */
          offset_delta = 2
          locals = [ class org/scalactic/AnyDiffer, class java/lang/Object, class java/lang/Object, class org/scalactic/Prettifier, class scala/collection/immutable/Set, top, class scala/Tuple2 ]
          stack = []
        frame_type = 2 /* same */
        frame_type = 255 /* full_frame */
          offset_delta = 64
          locals = [ class org/scalactic/AnyDiffer, class java/lang/Object, class java/lang/Object, class org/scalactic/Prettifier, class scala/collection/immutable/Set, top, class scala/Tuple2, top, top, top, top, top, top, top, top, top, top, top, top, class java/lang/Object, class java/lang/Object, class scala/collection/Set ]
          stack = []
        frame_type = 250 /* chop */
          offset_delta = 2
        frame_type = 255 /* full_frame */
          offset_delta = 2
          locals = [ class org/scalactic/AnyDiffer, class java/lang/Object, class java/lang/Object, class org/scalactic/Prettifier, class scala/collection/immutable/Set, top, class scala/Tuple2 ]
          stack = []
        frame_type = 2 /* same */
        frame_type = 255 /* full_frame */
          offset_delta = 66
          locals = [ class org/scalactic/AnyDiffer, class java/lang/Object, class java/lang/Object, class org/scalactic/Prettifier, class scala/collection/immutable/Set, top, class scala/Tuple2, top, top, top, top, top, top, top, top, top, top, top, top, top, top, top, top, class java/lang/Object, class java/lang/Object, class scala/Product ]
          stack = []
        frame_type = 250 /* chop */
          offset_delta = 2
        frame_type = 255 /* full_frame */
          offset_delta = 2
          locals = [ class org/scalactic/AnyDiffer, class java/lang/Object, class java/lang/Object, class org/scalactic/Prettifier, class scala/collection/immutable/Set, top, class scala/Tuple2 ]
          stack = []
        frame_type = 2 /* same */
        frame_type = 255 /* full_frame */
          offset_delta = 28
          locals = [ class org/scalactic/AnyDiffer, class java/lang/Object, class java/lang/Object, class org/scalactic/Prettifier, class scala/collection/immutable/Set, class org/scalactic/PrettyPair, class scala/Tuple2 ]
          stack = []
      LineNumberTable:
        line 295: 0
        line 296: 11
        line 297: 85
        line 298: 159
        line 299: 233
        line 301: 307
        line 303: 383
        line 295: 412
      LocalVariableTable:
        Start  Length  Slot  Name   Signature
           23      59     7    s1   Ljava/lang/Object;
           30      52     8    s2   Ljava/lang/Object;
           97      59    11    s1   Ljava/lang/Object;
          104      52    12    s2   Ljava/lang/Object;
          171      59    15    s1   Ljava/lang/Object;
          178      52    16    s2   Ljava/lang/Object;
          245      59    19    s1   Ljava/lang/Object;
          252      52    20    s2   Ljava/lang/Object;
          319      61    23    s1   Ljava/lang/Object;
          326      54    24    s2   Ljava/lang/Object;
            0     415     0  this   Lorg/scalactic/AnyDiffer;
            0     415     1     a   Ljava/lang/Object;
            0     415     2     b   Ljava/lang/Object;
            0     415     3 prettifier   Lorg/scalactic/Prettifier;
            0     415     4 processed   Lscala/collection/immutable/Set;
    Signature: #40                          // (Ljava/lang/Object;Ljava/lang/Object;Lorg/scalactic/Prettifier;Lscala/collection/immutable/Set<Ljava/lang/Object;>;)Lorg/scalactic/PrettyPair;
    MethodParameters:
      Name                           Flags
      a                              final
      b                              final
      prettifier                     final
      processed                      final

  public org.scalactic.AnyDiffer();
    descriptor: ()V
    flags: (0x0001) ACC_PUBLIC
    Code:
      stack=1, locals=1, args_size=1
         0: aload_0
         1: invokespecial #119                // Method java/lang/Object."<init>":()V
         4: return
      LineNumberTable:
        line 289: 0
      LocalVariableTable:
        Start  Length  Slot  Name   Signature
            0       5     0  this   Lorg/scalactic/AnyDiffer;
}
SourceFile: "Differ.scala"
RuntimeVisibleAnnotations:
  0: #8(#9=s#10)
    scala.reflect.ScalaSignature(
      bytes="\u0006\u0005\t3Qa\u0002\u0005\u0001\u00111AQa\u0006\u0001\u0005\u0002eAQa\u0007\u0001\u0005\u0002qAQ\u0001\f\u0001\u0005\u00025:aA\u0010\u0005\t\u0002!ydAB\u0004\t\u0011\u0003A\u0001\tC\u0003\u0018\u000b\u0011\u0005\u0011IA\u0005B]f$\u0015N\u001a4fe*\u0011\u0011BC\u0001\ng\u000e\fG.Y2uS\u000eT\u0011aC\u0001\u0004_J<7c\u0001\u0001\u000e\'A\u0011a\"E\u0007\u0002\u001f)\t\u0001#A\u0003tG\u0006d\u0017-\u0003\u0002\u0013\u001f\t1\u0011I\\=SK\u001a\u0004\"\u0001F\u000b\u000e\u0003!I!A\u0006\u0005\u0003\r\u0011KgMZ3s\u0003\u0019a\u0014N\\5u}\r\u0001A#\u0001\u000e\u0011\u0005Q\u0001\u0011A\u00033jM\u001a,\'/\u001a8dKR!Q\u0004I\u0013(!\t!b$\u0003\u0002 \u0011\tQ\u0001K]3uif\u0004\u0016-\u001b:\t\u000b\u0005\u0012\u0001\u0019\u0001\u0012\u0002\u0003\u0005\u0004\"AD\u0012\n\u0005\u0011z!aA!os\")aE\u0001a\u0001E\u0005\t!\rC\u0003)\u0005\u0001\u0007\u0011&\u0001\u0006qe\u0016$H/\u001b4jKJ\u0004\"\u0001\u0006\u0016\n\u0005-B!A\u0003)sKR$\u0018NZ5fe\u0006AA-\u001b4g\u00136\u0004H\u000eF\u0003\u001e]=\u0002\u0014\u0007C\u0003\"\u0007\u0001\u0007!\u0005C\u0003\'\u0007\u0001\u0007!\u0005C\u0003)\u0007\u0001\u0007\u0011\u0006C\u00033\u0007\u0001\u00071\'A\u0005qe>\u001cWm]:fIB\u0019Ag\u000f\u0012\u000f\u0005UJ\u0004C\u0001\u001c\u0010\u001b\u00059$B\u0001\u001d\u0019\u0003\u0019a$o\\8u}%\u0011!hD\u0001\u0007!J,G-\u001a4\n\u0005qj$aA*fi*\u0011!hD\u0001\n\u0003:LH)\u001b4gKJ\u0004\"\u0001F\u0003\u0014\u0005\u0015QB#A "
    )
  ScalaInlineInfo: length = 0x13 (unknown attribute)
   01 00 00 03 00 2C 00 75 00 00 20 00 21 00 00 0B
   00 0C 00
  ScalaSig: length = 0x3 (unknown attribute)
   05 02 00
