Classfile /Users/mw/Projects/slang-braindump/.jar/jar11/assemble/slang-braindump/assemble/content/org/scalactic/ColCompatHelper$.class
  Last modified May 29, 2022; size 2471 bytes
  SHA-256 checksum f3f885ffe0d8d4c1b091ecec413f45d8284dca6412d4781829994ed38144321e
  Compiled from "ColCompatHelper.scala"
public final class org.scalactic.ColCompatHelper$
  minor version: 0
  major version: 52
  flags: (0x0031) ACC_PUBLIC, ACC_FINAL, ACC_SUPER
  this_class: #2                          // org/scalactic/ColCompatHelper$
  super_class: #4                         // java/lang/Object
  interfaces: 0, fields: 1, methods: 5, attributes: 3
Constant pool:
    #1 = Utf8               org/scalactic/ColCompatHelper$
    #2 = Class              #1            // org/scalactic/ColCompatHelper$
    #3 = Utf8               java/lang/Object
    #4 = Class              #3            // java/lang/Object
    #5 = Utf8               ColCompatHelper.scala
    #6 = Utf8               MODULE$
    #7 = Utf8               Lorg/scalactic/ColCompatHelper$;
    #8 = Utf8               <clinit>
    #9 = Utf8               ()V
   #10 = Utf8               <init>
   #11 = NameAndType        #10:#9        // "<init>":()V
   #12 = Methodref          #2.#11        // org/scalactic/ColCompatHelper$."<init>":()V
   #13 = NameAndType        #6:#7         // MODULE$:Lorg/scalactic/ColCompatHelper$;
   #14 = Fieldref           #2.#13        // org/scalactic/ColCompatHelper$.MODULE$:Lorg/scalactic/ColCompatHelper$;
   #15 = Utf8               aggregate
   #16 = Utf8               (Lscala/collection/Iterable;Lscala/Function0;Lscala/Function2;Lscala/Function2;)Ljava/lang/Object;
   #17 = Utf8               <A:Ljava/lang/Object;B:Ljava/lang/Object;>(Lscala/collection/Iterable<TA;>;Lscala/Function0<TB;>;Lscala/Function2<TB;TA;TB;>;Lscala/Function2<TB;TB;TB;>;)TB;
   #18 = Utf8               col
   #19 = Utf8               z
   #20 = Utf8               seqop
   #21 = Utf8               combop
   #22 = Utf8               scala/Function0
   #23 = Class              #22           // scala/Function0
   #24 = Utf8               apply
   #25 = Utf8               ()Ljava/lang/Object;
   #26 = NameAndType        #24:#25       // apply:()Ljava/lang/Object;
   #27 = InterfaceMethodref #23.#26       // scala/Function0.apply:()Ljava/lang/Object;
   #28 = Utf8               scala/collection/Iterable
   #29 = Class              #28           // scala/collection/Iterable
   #30 = Utf8               foldLeft
   #31 = Utf8               (Ljava/lang/Object;Lscala/Function2;)Ljava/lang/Object;
   #32 = NameAndType        #30:#31       // foldLeft:(Ljava/lang/Object;Lscala/Function2;)Ljava/lang/Object;
   #33 = InterfaceMethodref #29.#32       // scala/collection/Iterable.foldLeft:(Ljava/lang/Object;Lscala/Function2;)Ljava/lang/Object;
   #34 = Utf8               this
   #35 = Utf8               Lscala/collection/Iterable;
   #36 = Utf8               Lscala/Function0;
   #37 = Utf8               Lscala/Function2;
   #38 = Utf8               className
   #39 = Utf8               (Lscala/collection/Iterable;)Ljava/lang/String;
   #40 = Utf8               (Lscala/collection/Iterable<*>;)Ljava/lang/String;
   #41 = Utf8               toString
   #42 = Utf8               ()Ljava/lang/String;
   #43 = NameAndType        #41:#42       // toString:()Ljava/lang/String;
   #44 = InterfaceMethodref #29.#43       // scala/collection/Iterable.toString:()Ljava/lang/String;
   #45 = Utf8               (
   #46 = String             #45           // (
   #47 = Utf8               java/lang/String
   #48 = Class              #47           // java/lang/String
   #49 = Utf8               indexOf
   #50 = Utf8               (Ljava/lang/String;)I
   #51 = NameAndType        #49:#50       // indexOf:(Ljava/lang/String;)I
   #52 = Methodref          #48.#51       // java/lang/String.indexOf:(Ljava/lang/String;)I
   #53 = Utf8               scala/collection/StringOps$
   #54 = Class              #53           // scala/collection/StringOps$
   #55 = Utf8               Lscala/collection/StringOps$;
   #56 = NameAndType        #6:#55        // MODULE$:Lscala/collection/StringOps$;
   #57 = Fieldref           #54.#56       // scala/collection/StringOps$.MODULE$:Lscala/collection/StringOps$;
   #58 = Utf8               scala/Predef$
   #59 = Class              #58           // scala/Predef$
   #60 = Utf8               Lscala/Predef$;
   #61 = NameAndType        #6:#60        // MODULE$:Lscala/Predef$;
   #62 = Fieldref           #59.#61       // scala/Predef$.MODULE$:Lscala/Predef$;
   #63 = Utf8               augmentString
   #64 = Utf8               (Ljava/lang/String;)Ljava/lang/String;
   #65 = NameAndType        #63:#64       // augmentString:(Ljava/lang/String;)Ljava/lang/String;
   #66 = Methodref          #59.#65       // scala/Predef$.augmentString:(Ljava/lang/String;)Ljava/lang/String;
   #67 = Utf8               take$extension
   #68 = Utf8               (Ljava/lang/String;I)Ljava/lang/String;
   #69 = NameAndType        #67:#68       // take$extension:(Ljava/lang/String;I)Ljava/lang/String;
   #70 = Methodref          #54.#69       // scala/collection/StringOps$.take$extension:(Ljava/lang/String;I)Ljava/lang/String;
   #71 = Utf8               org/scalactic/NameUtil$
   #72 = Class              #71           // org/scalactic/NameUtil$
   #73 = Utf8               Lorg/scalactic/NameUtil$;
   #74 = NameAndType        #6:#73        // MODULE$:Lorg/scalactic/NameUtil$;
   #75 = Fieldref           #72.#74       // org/scalactic/NameUtil$.MODULE$:Lorg/scalactic/NameUtil$;
   #76 = Utf8               getSimpleNameOfAnObjectsClass
   #77 = Utf8               (Ljava/lang/Object;)Ljava/lang/String;
   #78 = NameAndType        #76:#77       // getSimpleNameOfAnObjectsClass:(Ljava/lang/Object;)Ljava/lang/String;
   #79 = Methodref          #72.#78       // org/scalactic/NameUtil$.getSimpleNameOfAnObjectsClass:(Ljava/lang/Object;)Ljava/lang/String;
   #80 = Utf8               colToString
   #81 = Utf8               Ljava/lang/String;
   #82 = Utf8               bracketIdx
   #83 = Utf8               I
   #84 = Utf8               newBuilder
   #85 = Utf8               (Lscala/collection/Factory;)Lscala/collection/mutable/Builder;
   #86 = Utf8               <A:Ljava/lang/Object;C:Ljava/lang/Object;>(Lscala/collection/Factory<TA;TC;>;)Lscala/collection/mutable/Builder<TA;TC;>;
   #87 = Utf8               f
   #88 = Utf8               scala/collection/Factory
   #89 = Class              #88           // scala/collection/Factory
   #90 = Utf8               ()Lscala/collection/mutable/Builder;
   #91 = NameAndType        #84:#90       // newBuilder:()Lscala/collection/mutable/Builder;
   #92 = InterfaceMethodref #89.#91       // scala/collection/Factory.newBuilder:()Lscala/collection/mutable/Builder;
   #93 = Utf8               Lscala/collection/Factory;
   #94 = Methodref          #4.#11        // java/lang/Object."<init>":()V
   #95 = Utf8               Code
   #96 = Utf8               LineNumberTable
   #97 = Utf8               LocalVariableTable
   #98 = Utf8               Signature
   #99 = Utf8               MethodParameters
  #100 = Utf8               StackMapTable
  #101 = Utf8               SourceFile
  #102 = Utf8               ScalaInlineInfo
  #103 = Utf8               Scala
{
  public static final org.scalactic.ColCompatHelper$ MODULE$;
    descriptor: Lorg/scalactic/ColCompatHelper$;
    flags: (0x0019) ACC_PUBLIC, ACC_STATIC, ACC_FINAL

  public static {};
    descriptor: ()V
    flags: (0x0009) ACC_PUBLIC, ACC_STATIC
    Code:
      stack=2, locals=0, args_size=0
         0: new           #2                  // class org/scalactic/ColCompatHelper$
         3: dup
         4: invokespecial #12                 // Method "<init>":()V
         7: putstatic     #14                 // Field MODULE$:Lorg/scalactic/ColCompatHelper$;
        10: return
      LineNumberTable:
        line 20: 0

  public <A extends java.lang.Object, B extends java.lang.Object> B aggregate(scala.collection.Iterable<A>, scala.Function0<B>, scala.Function2<B, A, B>, scala.Function2<B, B, B>);
    descriptor: (Lscala/collection/Iterable;Lscala/Function0;Lscala/Function2;Lscala/Function2;)Ljava/lang/Object;
    flags: (0x0001) ACC_PUBLIC
    Code:
      stack=3, locals=5, args_size=5
         0: aload_1
         1: aload_2
         2: invokeinterface #27,  1           // InterfaceMethod scala/Function0.apply:()Ljava/lang/Object;
         7: aload_3
         8: invokeinterface #33,  3           // InterfaceMethod scala/collection/Iterable.foldLeft:(Ljava/lang/Object;Lscala/Function2;)Ljava/lang/Object;
        13: areturn
      LineNumberTable:
        line 24: 0
      LocalVariableTable:
        Start  Length  Slot  Name   Signature
            0      14     0  this   Lorg/scalactic/ColCompatHelper$;
            0      14     1   col   Lscala/collection/Iterable;
            0      14     2     z   Lscala/Function0;
            0      14     3 seqop   Lscala/Function2;
            0      14     4 combop   Lscala/Function2;
    Signature: #17                          // <A:Ljava/lang/Object;B:Ljava/lang/Object;>(Lscala/collection/Iterable<TA;>;Lscala/Function0<TB;>;Lscala/Function2<TB;TA;TB;>;Lscala/Function2<TB;TB;TB;>;)TB;
    MethodParameters:
      Name                           Flags
      col                            final
      z                              final
      seqop                          final
      combop                         final

  public java.lang.String className(scala.collection.Iterable<?>);
    descriptor: (Lscala/collection/Iterable;)Ljava/lang/String;
    flags: (0x0001) ACC_PUBLIC
    Code:
      stack=3, locals=4, args_size=2
         0: aload_1
         1: invokeinterface #44,  1           // InterfaceMethod scala/collection/Iterable.toString:()Ljava/lang/String;
         6: astore_2
         7: aload_2
         8: ldc           #46                 // String (
        10: invokevirtual #52                 // Method java/lang/String.indexOf:(Ljava/lang/String;)I
        13: istore_3
        14: iload_3
        15: iconst_0
        16: if_icmplt     36
        19: getstatic     #57                 // Field scala/collection/StringOps$.MODULE$:Lscala/collection/StringOps$;
        22: getstatic     #62                 // Field scala/Predef$.MODULE$:Lscala/Predef$;
        25: aload_2
        26: invokevirtual #66                 // Method scala/Predef$.augmentString:(Ljava/lang/String;)Ljava/lang/String;
        29: iload_3
        30: invokevirtual #70                 // Method scala/collection/StringOps$.take$extension:(Ljava/lang/String;I)Ljava/lang/String;
        33: goto          43
        36: getstatic     #75                 // Field org/scalactic/NameUtil$.MODULE$:Lorg/scalactic/NameUtil$;
        39: aload_1
        40: invokevirtual #79                 // Method org/scalactic/NameUtil$.getSimpleNameOfAnObjectsClass:(Ljava/lang/Object;)Ljava/lang/String;
        43: areturn
      StackMapTable: number_of_entries = 2
        frame_type = 253 /* append */
          offset_delta = 36
          locals = [ class java/lang/String, int ]
        frame_type = 70 /* same_locals_1_stack_item */
          stack = [ class java/lang/String ]
      LineNumberTable:
        line 35: 0
        line 36: 7
        line 37: 14
        line 38: 22
        line 40: 36
      LocalVariableTable:
        Start  Length  Slot  Name   Signature
            7      36     2 colToString   Ljava/lang/String;
           14      29     3 bracketIdx   I
            0      44     0  this   Lorg/scalactic/ColCompatHelper$;
            0      44     1   col   Lscala/collection/Iterable;
    Signature: #40                          // (Lscala/collection/Iterable<*>;)Ljava/lang/String;
    MethodParameters:
      Name                           Flags
      col                            final

  public <A extends java.lang.Object, C extends java.lang.Object> scala.collection.mutable.Builder<A, C> newBuilder(scala.collection.Factory<A, C>);
    descriptor: (Lscala/collection/Factory;)Lscala/collection/mutable/Builder;
    flags: (0x0001) ACC_PUBLIC
    Code:
      stack=1, locals=2, args_size=2
         0: aload_1
         1: invokeinterface #92,  1           // InterfaceMethod scala/collection/Factory.newBuilder:()Lscala/collection/mutable/Builder;
         6: areturn
      LineNumberTable:
        line 43: 0
      LocalVariableTable:
        Start  Length  Slot  Name   Signature
            0       7     0  this   Lorg/scalactic/ColCompatHelper$;
            0       7     1     f   Lscala/collection/Factory;
    Signature: #86                          // <A:Ljava/lang/Object;C:Ljava/lang/Object;>(Lscala/collection/Factory<TA;TC;>;)Lscala/collection/mutable/Builder<TA;TC;>;
    MethodParameters:
      Name                           Flags
      f                              final

  private org.scalactic.ColCompatHelper$();
    descriptor: ()V
    flags: (0x0002) ACC_PRIVATE
    Code:
      stack=1, locals=1, args_size=1
         0: aload_0
         1: invokespecial #94                 // Method java/lang/Object."<init>":()V
         4: return
      LineNumberTable:
        line 48: 0
        line 20: 4
      LocalVariableTable:
        Start  Length  Slot  Name   Signature
            0       5     0  this   Lorg/scalactic/ColCompatHelper$;
}
SourceFile: "ColCompatHelper.scala"
  ScalaInlineInfo: length = 0x18 (unknown attribute)
   01 01 00 04 00 0A 00 09 01 00 0F 00 10 01 00 26
   00 27 01 00 54 00 55 01
  Scala: length = 0x0 (unknown attribute)

