Classfile /Users/mw/Projects/slang-braindump/.jar/jar11/assemble/slang-braindump/assemble/content/org/scalactic/ComposedNormalizingEquivalence$.class
  Last modified May 29, 2022; size 2195 bytes
  SHA-256 checksum 0e97952f493f6c348963adf59c39cc770e77ed248711060637a1e71e0dc5f2b1
  Compiled from "ComposedNormalizingEquivalence.scala"
public final class org.scalactic.ComposedNormalizingEquivalence$ implements java.io.Serializable
  minor version: 0
  major version: 52
  flags: (0x0031) ACC_PUBLIC, ACC_FINAL, ACC_SUPER
  this_class: #2                          // org/scalactic/ComposedNormalizingEquivalence$
  super_class: #4                         // java/lang/Object
  interfaces: 1, fields: 1, methods: 6, attributes: 3
Constant pool:
   #1 = Utf8               org/scalactic/ComposedNormalizingEquivalence$
   #2 = Class              #1             // org/scalactic/ComposedNormalizingEquivalence$
   #3 = Utf8               java/lang/Object
   #4 = Class              #3             // java/lang/Object
   #5 = Utf8               java/io/Serializable
   #6 = Class              #5             // java/io/Serializable
   #7 = Utf8               ComposedNormalizingEquivalence.scala
   #8 = Utf8               MODULE$
   #9 = Utf8               Lorg/scalactic/ComposedNormalizingEquivalence$;
  #10 = Utf8               <clinit>
  #11 = Utf8               ()V
  #12 = Utf8               <init>
  #13 = NameAndType        #12:#11        // "<init>":()V
  #14 = Methodref          #2.#13         // org/scalactic/ComposedNormalizingEquivalence$."<init>":()V
  #15 = NameAndType        #8:#9          // MODULE$:Lorg/scalactic/ComposedNormalizingEquivalence$;
  #16 = Fieldref           #2.#15         // org/scalactic/ComposedNormalizingEquivalence$.MODULE$:Lorg/scalactic/ComposedNormalizingEquivalence$;
  #17 = Utf8               toString
  #18 = Utf8               ()Ljava/lang/String;
  #19 = Utf8               ComposedNormalizingEquivalence
  #20 = String             #19            // ComposedNormalizingEquivalence
  #21 = Utf8               this
  #22 = Utf8               apply
  #23 = Utf8               (Lorg/scalactic/Equivalence;Lorg/scalactic/Normalization;)Lorg/scalactic/ComposedNormalizingEquivalence;
  #24 = Utf8               <A:Ljava/lang/Object;>(Lorg/scalactic/Equivalence<TA;>;Lorg/scalactic/Normalization<TA;>;)Lorg/scalactic/ComposedNormalizingEquivalence<TA;>;
  #25 = Utf8               afterNormalizationEquivalence
  #26 = Utf8               normalization
  #27 = Utf8               org/scalactic/ComposedNormalizingEquivalence
  #28 = Class              #27            // org/scalactic/ComposedNormalizingEquivalence
  #29 = Utf8               (Lorg/scalactic/Equivalence;Lorg/scalactic/Normalization;)V
  #30 = NameAndType        #12:#29        // "<init>":(Lorg/scalactic/Equivalence;Lorg/scalactic/Normalization;)V
  #31 = Methodref          #28.#30        // org/scalactic/ComposedNormalizingEquivalence."<init>":(Lorg/scalactic/Equivalence;Lorg/scalactic/Normalization;)V
  #32 = Utf8               Lorg/scalactic/Equivalence;
  #33 = Utf8               Lorg/scalactic/Normalization;
  #34 = Utf8               unapply
  #35 = Utf8               (Lorg/scalactic/ComposedNormalizingEquivalence;)Lscala/Option;
  #36 = Utf8               <A:Ljava/lang/Object;>(Lorg/scalactic/ComposedNormalizingEquivalence<TA;>;)Lscala/Option<Lscala/Tuple2<Lorg/scalactic/Equivalence<TA;>;Lorg/scalactic/Normalization<TA;>;>;>;
  #37 = Utf8               x$0
  #38 = Utf8               scala/None$
  #39 = Class              #38            // scala/None$
  #40 = Utf8               Lscala/None$;
  #41 = NameAndType        #8:#40         // MODULE$:Lscala/None$;
  #42 = Fieldref           #39.#41        // scala/None$.MODULE$:Lscala/None$;
  #43 = Utf8               scala/Some
  #44 = Class              #43            // scala/Some
  #45 = Utf8               scala/Tuple2
  #46 = Class              #45            // scala/Tuple2
  #47 = Utf8               ()Lorg/scalactic/Equivalence;
  #48 = NameAndType        #25:#47        // afterNormalizationEquivalence:()Lorg/scalactic/Equivalence;
  #49 = Methodref          #28.#48        // org/scalactic/ComposedNormalizingEquivalence.afterNormalizationEquivalence:()Lorg/scalactic/Equivalence;
  #50 = Utf8               ()Lorg/scalactic/Normalization;
  #51 = NameAndType        #26:#50        // normalization:()Lorg/scalactic/Normalization;
  #52 = Methodref          #28.#51        // org/scalactic/ComposedNormalizingEquivalence.normalization:()Lorg/scalactic/Normalization;
  #53 = Utf8               (Ljava/lang/Object;Ljava/lang/Object;)V
  #54 = NameAndType        #12:#53        // "<init>":(Ljava/lang/Object;Ljava/lang/Object;)V
  #55 = Methodref          #46.#54        // scala/Tuple2."<init>":(Ljava/lang/Object;Ljava/lang/Object;)V
  #56 = Utf8               (Ljava/lang/Object;)V
  #57 = NameAndType        #12:#56        // "<init>":(Ljava/lang/Object;)V
  #58 = Methodref          #44.#57        // scala/Some."<init>":(Ljava/lang/Object;)V
  #59 = Utf8               Lorg/scalactic/ComposedNormalizingEquivalence;
  #60 = Utf8               scala/Option
  #61 = Class              #60            // scala/Option
  #62 = Utf8               writeReplace
  #63 = Utf8               ()Ljava/lang/Object;
  #64 = Utf8               scala/runtime/ModuleSerializationProxy
  #65 = Class              #64            // scala/runtime/ModuleSerializationProxy
  #66 = Utf8               (Ljava/lang/Class;)V
  #67 = NameAndType        #12:#66        // "<init>":(Ljava/lang/Class;)V
  #68 = Methodref          #65.#67        // scala/runtime/ModuleSerializationProxy."<init>":(Ljava/lang/Class;)V
  #69 = Methodref          #4.#13         // java/lang/Object."<init>":()V
  #70 = Utf8               Code
  #71 = Utf8               LineNumberTable
  #72 = Utf8               LocalVariableTable
  #73 = Utf8               Signature
  #74 = Utf8               MethodParameters
  #75 = Utf8               StackMapTable
  #76 = Utf8               SourceFile
  #77 = Utf8               ScalaInlineInfo
  #78 = Utf8               Scala
{
  public static final org.scalactic.ComposedNormalizingEquivalence$ MODULE$;
    descriptor: Lorg/scalactic/ComposedNormalizingEquivalence$;
    flags: (0x0019) ACC_PUBLIC, ACC_STATIC, ACC_FINAL

  public static {};
    descriptor: ()V
    flags: (0x0009) ACC_PUBLIC, ACC_STATIC
    Code:
      stack=2, locals=0, args_size=0
         0: new           #2                  // class org/scalactic/ComposedNormalizingEquivalence$
         3: dup
         4: invokespecial #14                 // Method "<init>":()V
         7: putstatic     #16                 // Field MODULE$:Lorg/scalactic/ComposedNormalizingEquivalence$;
        10: return
      LineNumberTable:
        line 18: 0

  public final java.lang.String toString();
    descriptor: ()Ljava/lang/String;
    flags: (0x0011) ACC_PUBLIC, ACC_FINAL
    Code:
      stack=1, locals=1, args_size=1
         0: ldc           #20                 // String ComposedNormalizingEquivalence
         2: areturn
      LineNumberTable:
        line 18: 0
      LocalVariableTable:
        Start  Length  Slot  Name   Signature
            0       3     0  this   Lorg/scalactic/ComposedNormalizingEquivalence$;

  public <A extends java.lang.Object> org.scalactic.ComposedNormalizingEquivalence<A> apply(org.scalactic.Equivalence<A>, org.scalactic.Normalization<A>);
    descriptor: (Lorg/scalactic/Equivalence;Lorg/scalactic/Normalization;)Lorg/scalactic/ComposedNormalizingEquivalence;
    flags: (0x0001) ACC_PUBLIC
    Code:
      stack=4, locals=3, args_size=3
         0: new           #28                 // class org/scalactic/ComposedNormalizingEquivalence
         3: dup
         4: aload_1
         5: aload_2
         6: invokespecial #31                 // Method org/scalactic/ComposedNormalizingEquivalence."<init>":(Lorg/scalactic/Equivalence;Lorg/scalactic/Normalization;)V
         9: areturn
      LineNumberTable:
        line 18: 0
      LocalVariableTable:
        Start  Length  Slot  Name   Signature
            0      10     0  this   Lorg/scalactic/ComposedNormalizingEquivalence$;
            0      10     1 afterNormalizationEquivalence   Lorg/scalactic/Equivalence;
            0      10     2 normalization   Lorg/scalactic/Normalization;
    Signature: #24                          // <A:Ljava/lang/Object;>(Lorg/scalactic/Equivalence<TA;>;Lorg/scalactic/Normalization<TA;>;)Lorg/scalactic/ComposedNormalizingEquivalence<TA;>;
    MethodParameters:
      Name                           Flags
      afterNormalizationEquivalence  final
      normalization                  final

  public <A extends java.lang.Object> scala.Option<scala.Tuple2<org.scalactic.Equivalence<A>, org.scalactic.Normalization<A>>> unapply(org.scalactic.ComposedNormalizingEquivalence<A>);
    descriptor: (Lorg/scalactic/ComposedNormalizingEquivalence;)Lscala/Option;
    flags: (0x0001) ACC_PUBLIC
    Code:
      stack=6, locals=2, args_size=2
         0: aload_1
         1: ifnonnull     10
         4: getstatic     #42                 // Field scala/None$.MODULE$:Lscala/None$;
         7: goto          32
        10: new           #44                 // class scala/Some
        13: dup
        14: new           #46                 // class scala/Tuple2
        17: dup
        18: aload_1
        19: invokevirtual #49                 // Method org/scalactic/ComposedNormalizingEquivalence.afterNormalizationEquivalence:()Lorg/scalactic/Equivalence;
        22: aload_1
        23: invokevirtual #52                 // Method org/scalactic/ComposedNormalizingEquivalence.normalization:()Lorg/scalactic/Normalization;
        26: invokespecial #55                 // Method scala/Tuple2."<init>":(Ljava/lang/Object;Ljava/lang/Object;)V
        29: invokespecial #58                 // Method scala/Some."<init>":(Ljava/lang/Object;)V
        32: areturn
      StackMapTable: number_of_entries = 2
        frame_type = 10 /* same */
        frame_type = 85 /* same_locals_1_stack_item */
          stack = [ class scala/Option ]
      LineNumberTable:
        line 18: 0
      LocalVariableTable:
        Start  Length  Slot  Name   Signature
            0      33     0  this   Lorg/scalactic/ComposedNormalizingEquivalence$;
            0      33     1   x$0   Lorg/scalactic/ComposedNormalizingEquivalence;
    Signature: #36                          // <A:Ljava/lang/Object;>(Lorg/scalactic/ComposedNormalizingEquivalence<TA;>;)Lscala/Option<Lscala/Tuple2<Lorg/scalactic/Equivalence<TA;>;Lorg/scalactic/Normalization<TA;>;>;>;
    MethodParameters:
      Name                           Flags
      x$0                            final

  private java.lang.Object writeReplace();
    descriptor: ()Ljava/lang/Object;
    flags: (0x0002) ACC_PRIVATE
    Code:
      stack=3, locals=1, args_size=1
         0: new           #65                 // class scala/runtime/ModuleSerializationProxy
         3: dup
         4: ldc           #2                  // class org/scalactic/ComposedNormalizingEquivalence$
         6: invokespecial #68                 // Method scala/runtime/ModuleSerializationProxy."<init>":(Ljava/lang/Class;)V
         9: areturn
      LineNumberTable:
        line 18: 0
      LocalVariableTable:
        Start  Length  Slot  Name   Signature
            0      10     0  this   Lorg/scalactic/ComposedNormalizingEquivalence$;

  private org.scalactic.ComposedNormalizingEquivalence$();
    descriptor: ()V
    flags: (0x0002) ACC_PRIVATE
    Code:
      stack=1, locals=1, args_size=1
         0: aload_0
         1: invokespecial #69                 // Method java/lang/Object."<init>":()V
         4: return
      LineNumberTable:
        line 18: 0
      LocalVariableTable:
        Start  Length  Slot  Name   Signature
            0       5     0  this   Lorg/scalactic/ComposedNormalizingEquivalence$;
}
SourceFile: "ComposedNormalizingEquivalence.scala"
  ScalaInlineInfo: length = 0x1D (unknown attribute)
   01 01 00 05 00 0C 00 0B 01 00 16 00 17 01 00 11
   00 12 01 00 22 00 23 01 00 3E 00 3F 01
  Scala: length = 0x0 (unknown attribute)

