Classfile /Users/mw/Projects/slang-braindump/.jar/jar11/assemble/slang-braindump/assemble/content/org/scalactic/DefaultEquality$.class
  Last modified May 29, 2022; size 2560 bytes
  SHA-256 checksum 8b1d8ad067ebc018c240060e17a618d9dc9db0f68ad7736cdc3823a2f6ed4a47
  Compiled from "DefaultEquality.scala"
public final class org.scalactic.DefaultEquality$
  minor version: 0
  major version: 52
  flags: (0x0031) ACC_PUBLIC, ACC_FINAL, ACC_SUPER
  this_class: #2                          // org/scalactic/DefaultEquality$
  super_class: #4                         // java/lang/Object
  interfaces: 0, fields: 1, methods: 3, attributes: 3
Constant pool:
   #1 = Utf8               org/scalactic/DefaultEquality$
   #2 = Class              #1             // org/scalactic/DefaultEquality$
   #3 = Utf8               java/lang/Object
   #4 = Class              #3             // java/lang/Object
   #5 = Utf8               DefaultEquality.scala
   #6 = Utf8               MODULE$
   #7 = Utf8               Lorg/scalactic/DefaultEquality$;
   #8 = Utf8               <clinit>
   #9 = Utf8               ()V
  #10 = Utf8               <init>
  #11 = NameAndType        #10:#9         // "<init>":()V
  #12 = Methodref          #2.#11         // org/scalactic/DefaultEquality$."<init>":()V
  #13 = NameAndType        #6:#7          // MODULE$:Lorg/scalactic/DefaultEquality$;
  #14 = Fieldref           #2.#13         // org/scalactic/DefaultEquality$.MODULE$:Lorg/scalactic/DefaultEquality$;
  #15 = Utf8               areEqualComparingArraysStructurally
  #16 = Utf8               (Ljava/lang/Object;Ljava/lang/Object;)Z
  #17 = Utf8               left
  #18 = Utf8               right
  #19 = Utf8               scala/runtime/ScalaRunTime$
  #20 = Class              #19            // scala/runtime/ScalaRunTime$
  #21 = Utf8               Lscala/runtime/ScalaRunTime$;
  #22 = NameAndType        #6:#21         // MODULE$:Lscala/runtime/ScalaRunTime$;
  #23 = Fieldref           #20.#22        // scala/runtime/ScalaRunTime$.MODULE$:Lscala/runtime/ScalaRunTime$;
  #24 = Utf8               isArray
  #25 = Utf8               (Ljava/lang/Object;I)Z
  #26 = NameAndType        #24:#25        // isArray:(Ljava/lang/Object;I)Z
  #27 = Methodref          #20.#26        // scala/runtime/ScalaRunTime$.isArray:(Ljava/lang/Object;I)Z
  #28 = Utf8               org/scalactic/ArrayHelper$
  #29 = Class              #28            // org/scalactic/ArrayHelper$
  #30 = Utf8               Lorg/scalactic/ArrayHelper$;
  #31 = NameAndType        #6:#30         // MODULE$:Lorg/scalactic/ArrayHelper$;
  #32 = Fieldref           #29.#31        // org/scalactic/ArrayHelper$.MODULE$:Lorg/scalactic/ArrayHelper$;
  #33 = Utf8               deep
  #34 = Utf8               (Ljava/lang/Object;)Lscala/collection/IndexedSeq;
  #35 = NameAndType        #33:#34        // deep:(Ljava/lang/Object;)Lscala/collection/IndexedSeq;
  #36 = Methodref          #29.#35        // org/scalactic/ArrayHelper$.deep:(Ljava/lang/Object;)Lscala/collection/IndexedSeq;
  #37 = Utf8               equals
  #38 = Utf8               (Ljava/lang/Object;)Z
  #39 = NameAndType        #37:#38        // equals:(Ljava/lang/Object;)Z
  #40 = Methodref          #4.#39         // java/lang/Object.equals:(Ljava/lang/Object;)Z
  #41 = Utf8               org/scalactic/anyvals/NonEmptyArray
  #42 = Class              #41            // org/scalactic/anyvals/NonEmptyArray
  #43 = Utf8               toArray
  #44 = Utf8               ()Ljava/lang/Object;
  #45 = NameAndType        #43:#44        // toArray:()Ljava/lang/Object;
  #46 = Methodref          #42.#45        // org/scalactic/anyvals/NonEmptyArray.toArray:()Ljava/lang/Object;
  #47 = Utf8               scala/runtime/BoxesRunTime
  #48 = Class              #47            // scala/runtime/BoxesRunTime
  #49 = NameAndType        #37:#16        // equals:(Ljava/lang/Object;Ljava/lang/Object;)Z
  #50 = Methodref          #48.#49        // scala/runtime/BoxesRunTime.equals:(Ljava/lang/Object;Ljava/lang/Object;)Z
  #51 = Utf8               this
  #52 = Utf8               Ljava/lang/Object;
  #53 = Utf8               scala/collection/IndexedSeq
  #54 = Class              #53            // scala/collection/IndexedSeq
  #55 = Methodref          #4.#11         // java/lang/Object."<init>":()V
  #56 = Utf8               Code
  #57 = Utf8               LineNumberTable
  #58 = Utf8               StackMapTable
  #59 = Utf8               LocalVariableTable
  #60 = Utf8               MethodParameters
  #61 = Utf8               SourceFile
  #62 = Utf8               ScalaInlineInfo
  #63 = Utf8               Scala
{
  public static final org.scalactic.DefaultEquality$ MODULE$;
    descriptor: Lorg/scalactic/DefaultEquality$;
    flags: (0x0019) ACC_PUBLIC, ACC_STATIC, ACC_FINAL

  public static {};
    descriptor: ()V
    flags: (0x0009) ACC_PUBLIC, ACC_STATIC
    Code:
      stack=2, locals=0, args_size=0
         0: new           #2                  // class org/scalactic/DefaultEquality$
         3: dup
         4: invokespecial #12                 // Method "<init>":()V
         7: putstatic     #14                 // Field MODULE$:Lorg/scalactic/DefaultEquality$;
        10: return
      LineNumberTable:
        line 43: 0

  public boolean areEqualComparingArraysStructurally(java.lang.Object, java.lang.Object);
    descriptor: (Ljava/lang/Object;Ljava/lang/Object;)Z
    flags: (0x0001) ACC_PUBLIC
    Code:
      stack=3, locals=27, args_size=3
         0: aload_1
         1: astore        7
         3: getstatic     #23                 // Field scala/runtime/ScalaRunTime$.MODULE$:Lscala/runtime/ScalaRunTime$;
         6: aload         7
         8: iconst_1
         9: invokevirtual #27                 // Method scala/runtime/ScalaRunTime$.isArray:(Ljava/lang/Object;I)Z
        12: ifeq          217
        15: aload         7
        17: astore        8
        19: aload_2
        20: astore        9
        22: getstatic     #23                 // Field scala/runtime/ScalaRunTime$.MODULE$:Lscala/runtime/ScalaRunTime$;
        25: aload         9
        27: iconst_1
        28: invokevirtual #27                 // Method scala/runtime/ScalaRunTime$.isArray:(Ljava/lang/Object;I)Z
        31: ifeq          87
        34: aload         9
        36: astore        10
        38: getstatic     #32                 // Field org/scalactic/ArrayHelper$.MODULE$:Lorg/scalactic/ArrayHelper$;
        41: aload         8
        43: invokevirtual #36                 // Method org/scalactic/ArrayHelper$.deep:(Ljava/lang/Object;)Lscala/collection/IndexedSeq;
        46: getstatic     #32                 // Field org/scalactic/ArrayHelper$.MODULE$:Lorg/scalactic/ArrayHelper$;
        49: aload         10
        51: invokevirtual #36                 // Method org/scalactic/ArrayHelper$.deep:(Ljava/lang/Object;)Lscala/collection/IndexedSeq;
        54: astore        11
        56: dup
        57: ifnonnull     69
        60: pop
        61: aload         11
        63: ifnull        77
        66: goto          81
        69: aload         11
        71: invokevirtual #40                 // Method java/lang/Object.equals:(Ljava/lang/Object;)Z
        74: ifeq          81
        77: iconst_1
        78: goto          82
        81: iconst_0
        82: istore        6
        84: goto          211
        87: goto          90
        90: aload         9
        92: instanceof    #42                 // class org/scalactic/anyvals/NonEmptyArray
        95: ifeq          166
        98: aload         9
       100: ifnonnull     107
       103: aconst_null
       104: goto          115
       107: aload         9
       109: checkcast     #42                 // class org/scalactic/anyvals/NonEmptyArray
       112: invokevirtual #46                 // Method org/scalactic/anyvals/NonEmptyArray.toArray:()Ljava/lang/Object;
       115: astore        12
       117: getstatic     #32                 // Field org/scalactic/ArrayHelper$.MODULE$:Lorg/scalactic/ArrayHelper$;
       120: aload         8
       122: invokevirtual #36                 // Method org/scalactic/ArrayHelper$.deep:(Ljava/lang/Object;)Lscala/collection/IndexedSeq;
       125: getstatic     #32                 // Field org/scalactic/ArrayHelper$.MODULE$:Lorg/scalactic/ArrayHelper$;
       128: aload         12
       130: invokevirtual #36                 // Method org/scalactic/ArrayHelper$.deep:(Ljava/lang/Object;)Lscala/collection/IndexedSeq;
       133: astore        13
       135: dup
       136: ifnonnull     148
       139: pop
       140: aload         13
       142: ifnull        156
       145: goto          160
       148: aload         13
       150: invokevirtual #40                 // Method java/lang/Object.equals:(Ljava/lang/Object;)Z
       153: ifeq          160
       156: iconst_1
       157: goto          161
       160: iconst_0
       161: istore        6
       163: goto          211
       166: goto          169
       169: getstatic     #32                 // Field org/scalactic/ArrayHelper$.MODULE$:Lorg/scalactic/ArrayHelper$;
       172: aload         8
       174: invokevirtual #36                 // Method org/scalactic/ArrayHelper$.deep:(Ljava/lang/Object;)Lscala/collection/IndexedSeq;
       177: aload_2
       178: astore        14
       180: dup
       181: ifnonnull     193
       184: pop
       185: aload         14
       187: ifnull        201
       190: goto          205
       193: aload         14
       195: invokevirtual #40                 // Method java/lang/Object.equals:(Ljava/lang/Object;)Z
       198: ifeq          205
       201: iconst_1
       202: goto          206
       205: iconst_0
       206: istore        6
       208: goto          211
       211: iload         6
       213: istore_3
       214: goto          608
       217: goto          220
       220: aload         7
       222: instanceof    #42                 // class org/scalactic/anyvals/NonEmptyArray
       225: ifeq          445
       228: aload         7
       230: ifnonnull     237
       233: aconst_null
       234: goto          245
       237: aload         7
       239: checkcast     #42                 // class org/scalactic/anyvals/NonEmptyArray
       242: invokevirtual #46                 // Method org/scalactic/anyvals/NonEmptyArray.toArray:()Ljava/lang/Object;
       245: astore        15
       247: aload_2
       248: astore        16
       250: getstatic     #23                 // Field scala/runtime/ScalaRunTime$.MODULE$:Lscala/runtime/ScalaRunTime$;
       253: aload         16
       255: iconst_1
       256: invokevirtual #27                 // Method scala/runtime/ScalaRunTime$.isArray:(Ljava/lang/Object;I)Z
       259: ifeq          315
       262: aload         16
       264: astore        17
       266: getstatic     #32                 // Field org/scalactic/ArrayHelper$.MODULE$:Lorg/scalactic/ArrayHelper$;
       269: aload         15
       271: invokevirtual #36                 // Method org/scalactic/ArrayHelper$.deep:(Ljava/lang/Object;)Lscala/collection/IndexedSeq;
       274: getstatic     #32                 // Field org/scalactic/ArrayHelper$.MODULE$:Lorg/scalactic/ArrayHelper$;
       277: aload         17
       279: invokevirtual #36                 // Method org/scalactic/ArrayHelper$.deep:(Ljava/lang/Object;)Lscala/collection/IndexedSeq;
       282: astore        18
       284: dup
       285: ifnonnull     297
       288: pop
       289: aload         18
       291: ifnull        305
       294: goto          309
       297: aload         18
       299: invokevirtual #40                 // Method java/lang/Object.equals:(Ljava/lang/Object;)Z
       302: ifeq          309
       305: iconst_1
       306: goto          310
       309: iconst_0
       310: istore        5
       312: goto          439
       315: goto          318
       318: aload         16
       320: instanceof    #42                 // class org/scalactic/anyvals/NonEmptyArray
       323: ifeq          394
       326: aload         16
       328: ifnonnull     335
       331: aconst_null
       332: goto          343
       335: aload         16
       337: checkcast     #42                 // class org/scalactic/anyvals/NonEmptyArray
       340: invokevirtual #46                 // Method org/scalactic/anyvals/NonEmptyArray.toArray:()Ljava/lang/Object;
       343: astore        19
       345: getstatic     #32                 // Field org/scalactic/ArrayHelper$.MODULE$:Lorg/scalactic/ArrayHelper$;
       348: aload         15
       350: invokevirtual #36                 // Method org/scalactic/ArrayHelper$.deep:(Ljava/lang/Object;)Lscala/collection/IndexedSeq;
       353: getstatic     #32                 // Field org/scalactic/ArrayHelper$.MODULE$:Lorg/scalactic/ArrayHelper$;
       356: aload         19
       358: invokevirtual #36                 // Method org/scalactic/ArrayHelper$.deep:(Ljava/lang/Object;)Lscala/collection/IndexedSeq;
       361: astore        20
       363: dup
       364: ifnonnull     376
       367: pop
       368: aload         20
       370: ifnull        384
       373: goto          388
       376: aload         20
       378: invokevirtual #40                 // Method java/lang/Object.equals:(Ljava/lang/Object;)Z
       381: ifeq          388
       384: iconst_1
       385: goto          389
       388: iconst_0
       389: istore        5
       391: goto          439
       394: goto          397
       397: getstatic     #32                 // Field org/scalactic/ArrayHelper$.MODULE$:Lorg/scalactic/ArrayHelper$;
       400: aload         15
       402: invokevirtual #36                 // Method org/scalactic/ArrayHelper$.deep:(Ljava/lang/Object;)Lscala/collection/IndexedSeq;
       405: aload_2
       406: astore        21
       408: dup
       409: ifnonnull     421
       412: pop
       413: aload         21
       415: ifnull        429
       418: goto          433
       421: aload         21
       423: invokevirtual #40                 // Method java/lang/Object.equals:(Ljava/lang/Object;)Z
       426: ifeq          433
       429: iconst_1
       430: goto          434
       433: iconst_0
       434: istore        5
       436: goto          439
       439: iload         5
       441: istore_3
       442: goto          608
       445: goto          448
       448: aload_2
       449: astore        22
       451: getstatic     #23                 // Field scala/runtime/ScalaRunTime$.MODULE$:Lscala/runtime/ScalaRunTime$;
       454: aload         22
       456: iconst_1
       457: invokevirtual #27                 // Method scala/runtime/ScalaRunTime$.isArray:(Ljava/lang/Object;I)Z
       460: ifeq          509
       463: aload         22
       465: astore        23
       467: aload_1
       468: getstatic     #32                 // Field org/scalactic/ArrayHelper$.MODULE$:Lorg/scalactic/ArrayHelper$;
       471: aload         23
       473: invokevirtual #36                 // Method org/scalactic/ArrayHelper$.deep:(Ljava/lang/Object;)Lscala/collection/IndexedSeq;
       476: astore        24
       478: dup
       479: ifnonnull     491
       482: pop
       483: aload         24
       485: ifnull        499
       488: goto          503
       491: aload         24
       493: invokevirtual #40                 // Method java/lang/Object.equals:(Ljava/lang/Object;)Z
       496: ifeq          503
       499: iconst_1
       500: goto          504
       503: iconst_0
       504: istore        4
       506: goto          602
       509: goto          512
       512: aload         22
       514: instanceof    #42                 // class org/scalactic/anyvals/NonEmptyArray
       517: ifeq          581
       520: aload         22
       522: ifnonnull     529
       525: aconst_null
       526: goto          537
       529: aload         22
       531: checkcast     #42                 // class org/scalactic/anyvals/NonEmptyArray
       534: invokevirtual #46                 // Method org/scalactic/anyvals/NonEmptyArray.toArray:()Ljava/lang/Object;
       537: astore        25
       539: aload_1
       540: getstatic     #32                 // Field org/scalactic/ArrayHelper$.MODULE$:Lorg/scalactic/ArrayHelper$;
       543: aload         25
       545: invokevirtual #36                 // Method org/scalactic/ArrayHelper$.deep:(Ljava/lang/Object;)Lscala/collection/IndexedSeq;
       548: astore        26
       550: dup
       551: ifnonnull     563
       554: pop
       555: aload         26
       557: ifnull        571
       560: goto          575
       563: aload         26
       565: invokevirtual #40                 // Method java/lang/Object.equals:(Ljava/lang/Object;)Z
       568: ifeq          575
       571: iconst_1
       572: goto          576
       575: iconst_0
       576: istore        4
       578: goto          602
       581: goto          584
       584: aload_1
       585: aload_2
       586: invokestatic  #50                 // Method scala/runtime/BoxesRunTime.equals:(Ljava/lang/Object;Ljava/lang/Object;)Z
       589: ifeq          596
       592: iconst_1
       593: goto          597
       596: iconst_0
       597: istore        4
       599: goto          602
       602: iload         4
       604: istore_3
       605: goto          608
       608: iload_3
       609: ireturn
      StackMapTable: number_of_entries = 62
        frame_type = 255 /* full_frame */
          offset_delta = 69
          locals = [ class org/scalactic/DefaultEquality$, class java/lang/Object, class java/lang/Object, top, top, top, top, class java/lang/Object, class java/lang/Object, class java/lang/Object, class java/lang/Object, class scala/collection/IndexedSeq ]
          stack = [ class scala/collection/IndexedSeq ]
        frame_type = 7 /* same */
        frame_type = 3 /* same */
        frame_type = 64 /* same_locals_1_stack_item */
          stack = [ int ]
        frame_type = 249 /* chop */
          offset_delta = 4
        frame_type = 2 /* same */
        frame_type = 16 /* same */
        frame_type = 71 /* same_locals_1_stack_item */
          stack = [ class java/lang/Object ]
        frame_type = 255 /* full_frame */
          offset_delta = 32
          locals = [ class org/scalactic/DefaultEquality$, class java/lang/Object, class java/lang/Object, top, top, top, top, class java/lang/Object, class java/lang/Object, class java/lang/Object, top, top, class java/lang/Object, class scala/collection/IndexedSeq ]
          stack = [ class scala/collection/IndexedSeq ]
        frame_type = 7 /* same */
        frame_type = 3 /* same */
        frame_type = 64 /* same_locals_1_stack_item */
          stack = [ int ]
        frame_type = 255 /* full_frame */
          offset_delta = 4
          locals = [ class org/scalactic/DefaultEquality$, class java/lang/Object, class java/lang/Object, top, top, top, top, class java/lang/Object, class java/lang/Object, class java/lang/Object ]
          stack = []
        frame_type = 2 /* same */
        frame_type = 255 /* full_frame */
          offset_delta = 23
          locals = [ class org/scalactic/DefaultEquality$, class java/lang/Object, class java/lang/Object, top, top, top, top, class java/lang/Object, class java/lang/Object, class java/lang/Object, top, top, top, top, class java/lang/Object ]
          stack = [ class scala/collection/IndexedSeq ]
        frame_type = 7 /* same */
        frame_type = 3 /* same */
        frame_type = 64 /* same_locals_1_stack_item */
          stack = [ int ]
        frame_type = 255 /* full_frame */
          offset_delta = 4
          locals = [ class org/scalactic/DefaultEquality$, class java/lang/Object, class java/lang/Object, top, top, top, int, class java/lang/Object, class java/lang/Object, class java/lang/Object ]
          stack = []
        frame_type = 255 /* full_frame */
          offset_delta = 5
          locals = [ class org/scalactic/DefaultEquality$, class java/lang/Object, class java/lang/Object, top, top, top, top, class java/lang/Object ]
          stack = []
        frame_type = 2 /* same */
        frame_type = 16 /* same */
        frame_type = 71 /* same_locals_1_stack_item */
          stack = [ class java/lang/Object ]
        frame_type = 255 /* full_frame */
          offset_delta = 51
          locals = [ class org/scalactic/DefaultEquality$, class java/lang/Object, class java/lang/Object, top, top, top, top, class java/lang/Object, top, top, top, top, top, top, top, class java/lang/Object, class java/lang/Object, class java/lang/Object, class scala/collection/IndexedSeq ]
          stack = [ class scala/collection/IndexedSeq ]
        frame_type = 7 /* same */
        frame_type = 3 /* same */
        frame_type = 64 /* same_locals_1_stack_item */
          stack = [ int ]
        frame_type = 249 /* chop */
          offset_delta = 4
        frame_type = 2 /* same */
        frame_type = 16 /* same */
        frame_type = 71 /* same_locals_1_stack_item */
          stack = [ class java/lang/Object ]
        frame_type = 255 /* full_frame */
          offset_delta = 32
          locals = [ class org/scalactic/DefaultEquality$, class java/lang/Object, class java/lang/Object, top, top, top, top, class java/lang/Object, top, top, top, top, top, top, top, class java/lang/Object, class java/lang/Object, top, top, class java/lang/Object, class scala/collection/IndexedSeq ]
          stack = [ class scala/collection/IndexedSeq ]
        frame_type = 7 /* same */
        frame_type = 3 /* same */
        frame_type = 64 /* same_locals_1_stack_item */
          stack = [ int ]
        frame_type = 255 /* full_frame */
          offset_delta = 4
          locals = [ class org/scalactic/DefaultEquality$, class java/lang/Object, class java/lang/Object, top, top, top, top, class java/lang/Object, top, top, top, top, top, top, top, class java/lang/Object, class java/lang/Object ]
          stack = []
        frame_type = 2 /* same */
        frame_type = 255 /* full_frame */
          offset_delta = 23
          locals = [ class org/scalactic/DefaultEquality$, class java/lang/Object, class java/lang/Object, top, top, top, top, class java/lang/Object, top, top, top, top, top, top, top, class java/lang/Object, class java/lang/Object, top, top, top, top, class java/lang/Object ]
          stack = [ class scala/collection/IndexedSeq ]
        frame_type = 7 /* same */
        frame_type = 3 /* same */
        frame_type = 64 /* same_locals_1_stack_item */
          stack = [ int ]
        frame_type = 255 /* full_frame */
          offset_delta = 4
          locals = [ class org/scalactic/DefaultEquality$, class java/lang/Object, class java/lang/Object, top, top, int, top, class java/lang/Object, top, top, top, top, top, top, top, class java/lang/Object, class java/lang/Object ]
          stack = []
        frame_type = 255 /* full_frame */
          offset_delta = 5
          locals = [ class org/scalactic/DefaultEquality$, class java/lang/Object, class java/lang/Object, top, top, top, top, class java/lang/Object ]
          stack = []
        frame_type = 2 /* same */
        frame_type = 255 /* full_frame */
          offset_delta = 42
          locals = [ class org/scalactic/DefaultEquality$, class java/lang/Object, class java/lang/Object, top, top, top, top, class java/lang/Object, top, top, top, top, top, top, top, top, top, top, top, top, top, top, class java/lang/Object, class java/lang/Object, class scala/collection/IndexedSeq ]
          stack = [ class java/lang/Object ]
        frame_type = 7 /* same */
        frame_type = 3 /* same */
        frame_type = 64 /* same_locals_1_stack_item */
          stack = [ int ]
        frame_type = 249 /* chop */
          offset_delta = 4
        frame_type = 2 /* same */
        frame_type = 16 /* same */
        frame_type = 71 /* same_locals_1_stack_item */
          stack = [ class java/lang/Object ]
        frame_type = 255 /* full_frame */
          offset_delta = 25
          locals = [ class org/scalactic/DefaultEquality$, class java/lang/Object, class java/lang/Object, top, top, top, top, class java/lang/Object, top, top, top, top, top, top, top, top, top, top, top, top, top, top, class java/lang/Object, top, top, class java/lang/Object, class scala/collection/IndexedSeq ]
          stack = [ class java/lang/Object ]
        frame_type = 7 /* same */
        frame_type = 3 /* same */
        frame_type = 64 /* same_locals_1_stack_item */
          stack = [ int ]
        frame_type = 255 /* full_frame */
          offset_delta = 4
          locals = [ class org/scalactic/DefaultEquality$, class java/lang/Object, class java/lang/Object, top, top, top, top, class java/lang/Object, top, top, top, top, top, top, top, top, top, top, top, top, top, top, class java/lang/Object ]
          stack = []
        frame_type = 2 /* same */
        frame_type = 11 /* same */
        frame_type = 64 /* same_locals_1_stack_item */
          stack = [ int ]
        frame_type = 255 /* full_frame */
          offset_delta = 4
          locals = [ class org/scalactic/DefaultEquality$, class java/lang/Object, class java/lang/Object, top, int, top, top, class java/lang/Object, top, top, top, top, top, top, top, top, top, top, top, top, top, top, class java/lang/Object ]
          stack = []
        frame_type = 255 /* full_frame */
          offset_delta = 5
          locals = [ class org/scalactic/DefaultEquality$, class java/lang/Object, class java/lang/Object, int, top, top, top, class java/lang/Object ]
          stack = []
      LineNumberTable:
        line 52: 0
        line 53: 3
        line 54: 19
        line 55: 22
        line 56: 90
        line 57: 169
        line 54: 211
        line 53: 217
        line 59: 220
        line 60: 247
        line 61: 250
        line 62: 318
        line 63: 397
        line 60: 439
        line 59: 445
        line 67: 448
        line 68: 451
        line 69: 512
        line 70: 584
        line 67: 602
        line 52: 608
      LocalVariableTable:
        Start  Length  Slot  Name   Signature
            0     610     0  this   Lorg/scalactic/DefaultEquality$;
            0     610     1  left   Ljava/lang/Object;
            0     610     2 right   Ljava/lang/Object;
    MethodParameters:
      Name                           Flags
      left                           final
      right                          final

  private org.scalactic.DefaultEquality$();
    descriptor: ()V
    flags: (0x0002) ACC_PRIVATE
    Code:
      stack=1, locals=1, args_size=1
         0: aload_0
         1: invokespecial #55                 // Method java/lang/Object."<init>":()V
         4: return
      LineNumberTable:
        line 77: 0
        line 43: 4
      LocalVariableTable:
        Start  Length  Slot  Name   Signature
            0       5     0  this   Lorg/scalactic/DefaultEquality$;
}
SourceFile: "DefaultEquality.scala"
  ScalaInlineInfo: length = 0xE (unknown attribute)
   01 01 00 02 00 0A 00 09 01 00 0F 00 10 01
  Scala: length = 0x0 (unknown attribute)

