Classfile /Users/mw/Projects/slang-braindump/.jar/jar11/assemble/slang-braindump/assemble/content/org/scalactic/Equivalence.class
  Last modified May 29, 2022; size 1032 bytes
  SHA-256 checksum 58e5eae0ef239dd320523e9ac844c5504c08f8a8136b0b3fe88a383fa422cc03
  Compiled from "Equivalence.scala"
public interface org.scalactic.Equivalence<T extends java.lang.Object>
  minor version: 0
  major version: 52
  flags: (0x0601) ACC_PUBLIC, ACC_INTERFACE, ACC_ABSTRACT
  this_class: #2                          // org/scalactic/Equivalence
  super_class: #5                         // java/lang/Object
  interfaces: 0, fields: 0, methods: 2, attributes: 5
Constant pool:
   #1 = Utf8               org/scalactic/Equivalence
   #2 = Class              #1             // org/scalactic/Equivalence
   #3 = Utf8               <T:Ljava/lang/Object;>Ljava/lang/Object;
   #4 = Utf8               java/lang/Object
   #5 = Class              #4             // java/lang/Object
   #6 = Utf8               Equivalence.scala
   #7 = Utf8               Lscala/reflect/ScalaSignature;
   #8 = Utf8               bytes
   #9 = Utf8               \u0006\u0005Q2qAB\u0004\u0011\u0002G\u0005A\u0002C\u0003\u0015\u0001\u0019\u0005QcB\u0003)\u000f!\u0005\u0011FB\u0003\u0007\u000f!\u00051\u0006C\u0003-\u0007\u0011\u0005Q\u0006C\u0003/\u0007\u0011\rqFA\u0006FcVLg/\u00197f]\u000e,\'B\u0001\u0005\n\u0003%\u00198-\u00197bGRL7MC\u0001\u000b\u0003\ry\'oZ\u0002\u0001+\tiQd\u0005\u0002\u0001\u001dA\u0011qBE\u0007\u0002!)\t\u0011#A\u0003tG\u0006d\u0017-\u0003\u0002\u0014!\t1\u0011I\\=SK\u001a\fQ\"\u0019:f\u000bF,\u0018N^1mK:$Hc\u0001\f\u001aMA\u0011qbF\u0005\u00031A\u0011qAQ8pY\u0016\fg\u000eC\u0003\u001b\u0003\u0001\u00071$A\u0001b!\taR\u0004\u0004\u0001\u0005\u000by\u0001!\u0019A\u0010\u0003\u0003Q\u000b\"\u0001I\u0012\u0011\u0005=\t\u0013B\u0001\u0012\u0011\u0005\u001dqu\u000e\u001e5j]\u001e\u0004\"a\u0004\u0013\n\u0005\u0015\u0002\"aA!os\")q%\u0001a\u00017\u0005\t!-A\u0006FcVLg/\u00197f]\u000e,\u0007C\u0001\u0016\u0004\u001b\u000591CA\u0002\u000f\u0003\u0019a\u0014N\\5u}Q\t\u0011&A\u0004eK\u001a\fW\u000f\u001c;\u0016\u0005A\u001aT#A\u0019\u0011\u0007)\u0002!\u0007\u0005\u0002\u001dg\u0011)a$\u0002b\u0001?\u0001
  #10 = Utf8               default
  #11 = Utf8               ()Lorg/scalactic/Equivalence;
  #12 = Utf8               <T:Ljava/lang/Object;>()Lorg/scalactic/Equivalence<TT;>;
  #13 = Utf8               org/scalactic/Equivalence$
  #14 = Class              #13            // org/scalactic/Equivalence$
  #15 = Utf8               MODULE$
  #16 = Utf8               Lorg/scalactic/Equivalence$;
  #17 = NameAndType        #15:#16        // MODULE$:Lorg/scalactic/Equivalence$;
  #18 = Fieldref           #14.#17        // org/scalactic/Equivalence$.MODULE$:Lorg/scalactic/Equivalence$;
  #19 = NameAndType        #10:#11        // default:()Lorg/scalactic/Equivalence;
  #20 = Methodref          #14.#19        // org/scalactic/Equivalence$.default:()Lorg/scalactic/Equivalence;
  #21 = Utf8               areEquivalent
  #22 = Utf8               (Ljava/lang/Object;Ljava/lang/Object;)Z
  #23 = Utf8               (TT;TT;)Z
  #24 = Utf8               a
  #25 = Utf8               b
  #26 = Utf8               Code
  #27 = Utf8               Signature
  #28 = Utf8               MethodParameters
  #29 = Utf8               SourceFile
  #30 = Utf8               RuntimeVisibleAnnotations
  #31 = Utf8               ScalaInlineInfo
  #32 = Utf8               ScalaSig
{
  public static <T extends java.lang.Object> org.scalactic.Equivalence<T> default();
    descriptor: ()Lorg/scalactic/Equivalence;
    flags: (0x0009) ACC_PUBLIC, ACC_STATIC
    Code:
      stack=1, locals=0, args_size=0
         0: getstatic     #18                 // Field org/scalactic/Equivalence$.MODULE$:Lorg/scalactic/Equivalence$;
         3: invokevirtual #20                 // Method org/scalactic/Equivalence$.default:()Lorg/scalactic/Equivalence;
         6: areturn
    Signature: #12                          // <T:Ljava/lang/Object;>()Lorg/scalactic/Equivalence<TT;>;

  public abstract boolean areEquivalent(T, T);
    descriptor: (Ljava/lang/Object;Ljava/lang/Object;)Z
    flags: (0x0401) ACC_PUBLIC, ACC_ABSTRACT
    Signature: #23                          // (TT;TT;)Z
    MethodParameters:
      Name                           Flags
      a                              final
      b                              final
}
Signature: #3                           // <T:Ljava/lang/Object;>Ljava/lang/Object;
SourceFile: "Equivalence.scala"
RuntimeVisibleAnnotations:
  0: #7(#8=s#9)
    scala.reflect.ScalaSignature(
      bytes="\u0006\u0005Q2qAB\u0004\u0011\u0002G\u0005A\u0002C\u0003\u0015\u0001\u0019\u0005QcB\u0003)\u000f!\u0005\u0011FB\u0003\u0007\u000f!\u00051\u0006C\u0003-\u0007\u0011\u0005Q\u0006C\u0003/\u0007\u0011\rqFA\u0006FcVLg/\u00197f]\u000e,\'B\u0001\u0005\n\u0003%\u00198-\u00197bGRL7MC\u0001\u000b\u0003\ry\'oZ\u0002\u0001+\tiQd\u0005\u0002\u0001\u001dA\u0011qBE\u0007\u0002!)\t\u0011#A\u0003tG\u0006d\u0017-\u0003\u0002\u0014!\t1\u0011I\\=SK\u001a\fQ\"\u0019:f\u000bF,\u0018N^1mK:$Hc\u0001\f\u001aMA\u0011qbF\u0005\u00031A\u0011qAQ8pY\u0016\fg\u000eC\u0003\u001b\u0003\u0001\u00071$A\u0001b!\taR\u0004\u0004\u0001\u0005\u000by\u0001!\u0019A\u0010\u0003\u0003Q\u000b\"\u0001I\u0012\u0011\u0005=\t\u0013B\u0001\u0012\u0011\u0005\u001dqu\u000e\u001e5j]\u001e\u0004\"a\u0004\u0013\n\u0005\u0015\u0002\"aA!os\")q%\u0001a\u00017\u0005\t!-A\u0006FcVLg/\u00197f]\u000e,\u0007C\u0001\u0016\u0004\u001b\u000591CA\u0002\u000f\u0003\u0019a\u0014N\\5u}Q\t\u0011&A\u0004eK\u001a\fW\u000f\u001c;\u0016\u0005A\u001aT#A\u0019\u0011\u0007)\u0002!\u0007\u0005\u0002\u001dg\u0011)a$\u0002b\u0001?\u0001"
    )
  ScalaInlineInfo: length = 0x9 (unknown attribute)
   01 00 00 01 00 15 00 16 00
  ScalaSig: length = 0x3 (unknown attribute)
   05 02 00
