Classfile /Users/mw/Projects/slang-braindump/.jar/jar11/assemble/slang-braindump/assemble/content/org/scalactic/Every$.class
  Last modified May 29, 2022; size 3399 bytes
  SHA-256 checksum 43ca96c07434a7b4499e12ae0553b22288d56e20b07d18292a06563eb42b0d17
  Compiled from "Every.scala"
public final class org.scalactic.Every$ implements java.io.Serializable
  minor version: 0
  major version: 52
  flags: (0x0031) ACC_PUBLIC, ACC_FINAL, ACC_SUPER
  this_class: #2                          // org/scalactic/Every$
  super_class: #4                         // java/lang/Object
  interfaces: 1, fields: 1, methods: 8, attributes: 3
Constant pool:
    #1 = Utf8               org/scalactic/Every$
    #2 = Class              #1            // org/scalactic/Every$
    #3 = Utf8               java/lang/Object
    #4 = Class              #3            // java/lang/Object
    #5 = Utf8               java/io/Serializable
    #6 = Class              #5            // java/io/Serializable
    #7 = Utf8               Every.scala
    #8 = Utf8               MODULE$
    #9 = Utf8               Lorg/scalactic/Every$;
   #10 = Utf8               <clinit>
   #11 = Utf8               ()V
   #12 = Utf8               <init>
   #13 = NameAndType        #12:#11       // "<init>":()V
   #14 = Methodref          #2.#13        // org/scalactic/Every$."<init>":()V
   #15 = NameAndType        #8:#9         // MODULE$:Lorg/scalactic/Every$;
   #16 = Fieldref           #2.#15        // org/scalactic/Every$.MODULE$:Lorg/scalactic/Every$;
   #17 = Utf8               apply
   #18 = Utf8               (Ljava/lang/Object;Lscala/collection/immutable/Seq;)Lorg/scalactic/Every;
   #19 = Utf8               <T:Ljava/lang/Object;>(TT;Lscala/collection/immutable/Seq<TT;>;)Lorg/scalactic/Every<TT;>;
   #20 = Utf8               firstElement
   #21 = Utf8               otherElements
   #22 = Utf8               scala/collection/immutable/Seq
   #23 = Class              #22           // scala/collection/immutable/Seq
   #24 = Utf8               isEmpty
   #25 = Utf8               ()Z
   #26 = NameAndType        #24:#25       // isEmpty:()Z
   #27 = InterfaceMethodref #23.#26       // scala/collection/immutable/Seq.isEmpty:()Z
   #28 = Utf8               org/scalactic/One
   #29 = Class              #28           // org/scalactic/One
   #30 = Utf8               (Ljava/lang/Object;)V
   #31 = NameAndType        #12:#30       // "<init>":(Ljava/lang/Object;)V
   #32 = Methodref          #29.#31       // org/scalactic/One."<init>":(Ljava/lang/Object;)V
   #33 = Utf8               org/scalactic/Many
   #34 = Class              #33           // org/scalactic/Many
   #35 = Utf8               head
   #36 = Utf8               ()Ljava/lang/Object;
   #37 = NameAndType        #35:#36       // head:()Ljava/lang/Object;
   #38 = InterfaceMethodref #23.#37       // scala/collection/immutable/Seq.head:()Ljava/lang/Object;
   #39 = Utf8               tail
   #40 = NameAndType        #39:#36       // tail:()Ljava/lang/Object;
   #41 = InterfaceMethodref #23.#40       // scala/collection/immutable/Seq.tail:()Ljava/lang/Object;
   #42 = Utf8               (Ljava/lang/Object;Ljava/lang/Object;Lscala/collection/immutable/Seq;)V
   #43 = NameAndType        #12:#42       // "<init>":(Ljava/lang/Object;Ljava/lang/Object;Lscala/collection/immutable/Seq;)V
   #44 = Methodref          #34.#43       // org/scalactic/Many."<init>":(Ljava/lang/Object;Ljava/lang/Object;Lscala/collection/immutable/Seq;)V
   #45 = Utf8               this
   #46 = Utf8               Ljava/lang/Object;
   #47 = Utf8               Lscala/collection/immutable/Seq;
   #48 = Utf8               org/scalactic/Every
   #49 = Class              #48           // org/scalactic/Every
   #50 = Utf8               unapplySeq
   #51 = Utf8               (Lorg/scalactic/Every;)Lscala/Option;
   #52 = Utf8               <T:Ljava/lang/Object;>(Lorg/scalactic/Every<TT;>;)Lscala/Option<Lscala/collection/immutable/Seq<TT;>;>;
   #53 = Utf8               every
   #54 = Utf8               scala/Some
   #55 = Class              #54           // scala/Some
   #56 = Utf8               toVector
   #57 = Utf8               ()Lscala/collection/immutable/Vector;
   #58 = NameAndType        #56:#57       // toVector:()Lscala/collection/immutable/Vector;
   #59 = Methodref          #49.#58       // org/scalactic/Every.toVector:()Lscala/collection/immutable/Vector;
   #60 = Methodref          #55.#31       // scala/Some."<init>":(Ljava/lang/Object;)V
   #61 = Utf8               Lorg/scalactic/Every;
   #62 = Utf8               from
   #63 = Utf8               (Lscala/collection/Seq;)Lscala/Option;
   #64 = Utf8               <T:Ljava/lang/Object;>(Lscala/collection/Seq<TT;>;)Lscala/Option<Lorg/scalactic/Every<TT;>;>;
   #65 = Utf8               seq
   #66 = Utf8               scala/collection/Seq
   #67 = Class              #66           // scala/collection/Seq
   #68 = Utf8               headOption
   #69 = Utf8               ()Lscala/Option;
   #70 = NameAndType        #68:#69       // headOption:()Lscala/Option;
   #71 = InterfaceMethodref #67.#70       // scala/collection/Seq.headOption:()Lscala/Option;
   #72 = Utf8               scala/None$
   #73 = Class              #72           // scala/None$
   #74 = Utf8               Lscala/None$;
   #75 = NameAndType        #8:#74        // MODULE$:Lscala/None$;
   #76 = Fieldref           #73.#75       // scala/None$.MODULE$:Lscala/None$;
   #77 = Utf8               equals
   #78 = Utf8               (Ljava/lang/Object;)Z
   #79 = NameAndType        #77:#78       // equals:(Ljava/lang/Object;)Z
   #80 = Methodref          #4.#79        // java/lang/Object.equals:(Ljava/lang/Object;)Z
   #81 = Utf8               value
   #82 = NameAndType        #81:#36       // value:()Ljava/lang/Object;
   #83 = Methodref          #55.#82       // scala/Some.value:()Ljava/lang/Object;
   #84 = InterfaceMethodref #67.#40       // scala/collection/Seq.tail:()Ljava/lang/Object;
   #85 = Utf8               scala/collection/IterableOps
   #86 = Class              #85           // scala/collection/IterableOps
   #87 = InterfaceMethodref #86.#70       // scala/collection/IterableOps.headOption:()Lscala/Option;
   #88 = InterfaceMethodref #86.#40       // scala/collection/IterableOps.tail:()Ljava/lang/Object;
   #89 = Utf8               scala/collection/IterableOnceOps
   #90 = Class              #89           // scala/collection/IterableOnceOps
   #91 = InterfaceMethodref #90.#58       // scala/collection/IterableOnceOps.toVector:()Lscala/collection/immutable/Vector;
   #92 = Utf8               scala/MatchError
   #93 = Class              #92           // scala/MatchError
   #94 = Methodref          #93.#31       // scala/MatchError."<init>":(Ljava/lang/Object;)V
   #95 = Utf8               second
   #96 = Utf8               first
   #97 = Utf8               Lscala/collection/Seq;
   #98 = Utf8               scala/Option
   #99 = Class              #98           // scala/Option
  #100 = Utf8               everyToGenTraversableOnce
  #101 = Utf8               (Lorg/scalactic/Every;)Lscala/collection/immutable/IndexedSeq;
  #102 = Utf8               <E:Ljava/lang/Object;>(Lorg/scalactic/Every<TE;>;)Lscala/collection/immutable/IndexedSeq<TE;>;
  #103 = Utf8               org$scalactic$Every$$fromNonEmptyVector
  #104 = Utf8               (Lscala/collection/immutable/Vector;)Lorg/scalactic/Every;
  #105 = Utf8               <E:Ljava/lang/Object;>(Lscala/collection/immutable/Vector<TE;>;)Lorg/scalactic/Every<TE;>;
  #106 = Utf8               vec
  #107 = Utf8               scala/collection/immutable/Vector
  #108 = Class              #107          // scala/collection/immutable/Vector
  #109 = Methodref          #108.#37      // scala/collection/immutable/Vector.head:()Ljava/lang/Object;
  #110 = NameAndType        #39:#57       // tail:()Lscala/collection/immutable/Vector;
  #111 = Methodref          #108.#110     // scala/collection/immutable/Vector.tail:()Lscala/collection/immutable/Vector;
  #112 = NameAndType        #17:#18       // apply:(Ljava/lang/Object;Lscala/collection/immutable/Seq;)Lorg/scalactic/Every;
  #113 = Methodref          #2.#112       // org/scalactic/Every$.apply:(Ljava/lang/Object;Lscala/collection/immutable/Seq;)Lorg/scalactic/Every;
  #114 = Utf8               Lscala/collection/immutable/Vector;
  #115 = Utf8               writeReplace
  #116 = Utf8               scala/runtime/ModuleSerializationProxy
  #117 = Class              #116          // scala/runtime/ModuleSerializationProxy
  #118 = Utf8               (Ljava/lang/Class;)V
  #119 = NameAndType        #12:#118      // "<init>":(Ljava/lang/Class;)V
  #120 = Methodref          #117.#119     // scala/runtime/ModuleSerializationProxy."<init>":(Ljava/lang/Class;)V
  #121 = Methodref          #4.#13        // java/lang/Object."<init>":()V
  #122 = Utf8               Code
  #123 = Utf8               LineNumberTable
  #124 = Utf8               StackMapTable
  #125 = Utf8               LocalVariableTable
  #126 = Utf8               Signature
  #127 = Utf8               MethodParameters
  #128 = Utf8               SourceFile
  #129 = Utf8               ScalaInlineInfo
  #130 = Utf8               Scala
{
  public static final org.scalactic.Every$ MODULE$;
    descriptor: Lorg/scalactic/Every$;
    flags: (0x0019) ACC_PUBLIC, ACC_STATIC, ACC_FINAL

  public static {};
    descriptor: ()V
    flags: (0x0009) ACC_PUBLIC, ACC_STATIC
    Code:
      stack=2, locals=0, args_size=0
         0: new           #2                  // class org/scalactic/Every$
         3: dup
         4: invokespecial #14                 // Method "<init>":()V
         7: putstatic     #16                 // Field MODULE$:Lorg/scalactic/Every$;
        10: return
      LineNumberTable:
        line 1487: 0

  public <T extends java.lang.Object> org.scalactic.Every<T> apply(T, scala.collection.immutable.Seq<T>);
    descriptor: (Ljava/lang/Object;Lscala/collection/immutable/Seq;)Lorg/scalactic/Every;
    flags: (0x0001) ACC_PUBLIC
    Code:
      stack=5, locals=3, args_size=3
         0: aload_2
         1: invokeinterface #27,  1           // InterfaceMethod scala/collection/immutable/Seq.isEmpty:()Z
         6: ifeq          20
         9: new           #29                 // class org/scalactic/One
        12: dup
        13: aload_1
        14: invokespecial #32                 // Method org/scalactic/One."<init>":(Ljava/lang/Object;)V
        17: goto          43
        20: new           #34                 // class org/scalactic/Many
        23: dup
        24: aload_1
        25: aload_2
        26: invokeinterface #38,  1           // InterfaceMethod scala/collection/immutable/Seq.head:()Ljava/lang/Object;
        31: aload_2
        32: invokeinterface #41,  1           // InterfaceMethod scala/collection/immutable/Seq.tail:()Ljava/lang/Object;
        37: checkcast     #23                 // class scala/collection/immutable/Seq
        40: invokespecial #44                 // Method org/scalactic/Many."<init>":(Ljava/lang/Object;Ljava/lang/Object;Lscala/collection/immutable/Seq;)V
        43: areturn
      StackMapTable: number_of_entries = 2
        frame_type = 20 /* same */
        frame_type = 86 /* same_locals_1_stack_item */
          stack = [ class org/scalactic/Every ]
      LineNumberTable:
        line 1497: 0
      LocalVariableTable:
        Start  Length  Slot  Name   Signature
            0      44     0  this   Lorg/scalactic/Every$;
            0      44     1 firstElement   Ljava/lang/Object;
            0      44     2 otherElements   Lscala/collection/immutable/Seq;
    Signature: #19                          // <T:Ljava/lang/Object;>(TT;Lscala/collection/immutable/Seq<TT;>;)Lorg/scalactic/Every<TT;>;
    MethodParameters:
      Name                           Flags
      firstElement                   final
      otherElements                  final

  public <T extends java.lang.Object> scala.Option<scala.collection.immutable.Seq<T>> unapplySeq(org.scalactic.Every<T>);
    descriptor: (Lorg/scalactic/Every;)Lscala/Option;
    flags: (0x0001) ACC_PUBLIC
    Code:
      stack=3, locals=2, args_size=2
         0: new           #55                 // class scala/Some
         3: dup
         4: aload_1
         5: invokevirtual #59                 // Method org/scalactic/Every.toVector:()Lscala/collection/immutable/Vector;
         8: invokespecial #60                 // Method scala/Some."<init>":(Ljava/lang/Object;)V
        11: areturn
      LineNumberTable:
        line 1505: 0
      LocalVariableTable:
        Start  Length  Slot  Name   Signature
            0      12     0  this   Lorg/scalactic/Every$;
            0      12     1 every   Lorg/scalactic/Every;
    Signature: #52                          // <T:Ljava/lang/Object;>(Lorg/scalactic/Every<TT;>;)Lscala/Option<Lscala/collection/immutable/Seq<TT;>;>;
    MethodParameters:
      Name                           Flags
      every                          final

  public <T extends java.lang.Object> scala.Option<org.scalactic.Every<T>> from(scala.collection.Seq<T>);
    descriptor: (Lscala/collection/Seq;)Lscala/Option;
    flags: (0x0001) ACC_PUBLIC
    Code:
      stack=7, locals=10, args_size=2
         0: aload_1
         1: invokeinterface #71,  1           // InterfaceMethod scala/collection/Seq.headOption:()Lscala/Option;
         6: astore        4
         8: getstatic     #76                 // Field scala/None$.MODULE$:Lscala/None$;
        11: aload         4
        13: invokevirtual #80                 // Method java/lang/Object.equals:(Ljava/lang/Object;)Z
        16: ifeq          26
        19: getstatic     #76                 // Field scala/None$.MODULE$:Lscala/None$;
        22: astore_2
        23: goto          198
        26: goto          29
        29: aload         4
        31: instanceof    #55                 // class scala/Some
        34: ifeq          185
        37: aload         4
        39: checkcast     #55                 // class scala/Some
        42: astore        5
        44: aload         5
        46: invokevirtual #83                 // Method scala/Some.value:()Ljava/lang/Object;
        49: astore        6
        51: aload_1
        52: invokeinterface #84,  1           // InterfaceMethod scala/collection/Seq.tail:()Ljava/lang/Object;
        57: checkcast     #86                 // class scala/collection/IterableOps
        60: invokeinterface #87,  1           // InterfaceMethod scala/collection/IterableOps.headOption:()Lscala/Option;
        65: astore        7
        67: getstatic     #76                 // Field scala/None$.MODULE$:Lscala/None$;
        70: aload         7
        72: invokevirtual #80                 // Method java/lang/Object.equals:(Ljava/lang/Object;)Z
        75: ifeq          98
        78: new           #55                 // class scala/Some
        81: dup
        82: new           #29                 // class org/scalactic/One
        85: dup
        86: aload         6
        88: invokespecial #32                 // Method org/scalactic/One."<init>":(Ljava/lang/Object;)V
        91: invokespecial #60                 // Method scala/Some."<init>":(Ljava/lang/Object;)V
        94: astore_3
        95: goto          180
        98: goto          101
       101: aload         7
       103: instanceof    #55                 // class scala/Some
       106: ifeq          167
       109: aload         7
       111: checkcast     #55                 // class scala/Some
       114: astore        8
       116: aload         8
       118: invokevirtual #83                 // Method scala/Some.value:()Ljava/lang/Object;
       121: astore        9
       123: new           #55                 // class scala/Some
       126: dup
       127: new           #34                 // class org/scalactic/Many
       130: dup
       131: aload         6
       133: aload         9
       135: aload_1
       136: invokeinterface #84,  1           // InterfaceMethod scala/collection/Seq.tail:()Ljava/lang/Object;
       141: checkcast     #86                 // class scala/collection/IterableOps
       144: invokeinterface #88,  1           // InterfaceMethod scala/collection/IterableOps.tail:()Ljava/lang/Object;
       149: checkcast     #90                 // class scala/collection/IterableOnceOps
       152: invokeinterface #91,  1           // InterfaceMethod scala/collection/IterableOnceOps.toVector:()Lscala/collection/immutable/Vector;
       157: invokespecial #44                 // Method org/scalactic/Many."<init>":(Ljava/lang/Object;Ljava/lang/Object;Lscala/collection/immutable/Seq;)V
       160: invokespecial #60                 // Method scala/Some."<init>":(Ljava/lang/Object;)V
       163: astore_3
       164: goto          180
       167: goto          170
       170: new           #93                 // class scala/MatchError
       173: dup
       174: aload         7
       176: invokespecial #94                 // Method scala/MatchError."<init>":(Ljava/lang/Object;)V
       179: athrow
       180: aload_3
       181: astore_2
       182: goto          198
       185: goto          188
       188: new           #93                 // class scala/MatchError
       191: dup
       192: aload         4
       194: invokespecial #94                 // Method scala/MatchError."<init>":(Ljava/lang/Object;)V
       197: athrow
       198: aload_2
       199: areturn
      StackMapTable: number_of_entries = 10
        frame_type = 254 /* append */
          offset_delta = 26
          locals = [ top, top, class scala/Option ]
        frame_type = 2 /* same */
        frame_type = 254 /* append */
          offset_delta = 68
          locals = [ class scala/Some, class java/lang/Object, class scala/Option ]
        frame_type = 2 /* same */
        frame_type = 251 /* same_frame_extended */
          offset_delta = 65
        frame_type = 2 /* same */
        frame_type = 255 /* full_frame */
          offset_delta = 9
          locals = [ class org/scalactic/Every$, class scala/collection/Seq, top, class scala/Some, class scala/Option, class scala/Some, class java/lang/Object, class scala/Option ]
          stack = []
        frame_type = 255 /* full_frame */
          offset_delta = 4
          locals = [ class org/scalactic/Every$, class scala/collection/Seq, top, top, class scala/Option ]
          stack = []
        frame_type = 2 /* same */
        frame_type = 255 /* full_frame */
          offset_delta = 9
          locals = [ class org/scalactic/Every$, class scala/collection/Seq, class scala/Option, top, class scala/Option ]
          stack = []
      LineNumberTable:
        line 1520: 0
        line 1521: 8
        line 1522: 29
        line 1523: 51
        line 1524: 67
        line 1525: 101
        line 1523: 170
        line 1522: 185
        line 1520: 188
      LocalVariableTable:
        Start  Length  Slot  Name   Signature
          123      44     9 second   Ljava/lang/Object;
           51     134     6 first   Ljava/lang/Object;
            0     200     0  this   Lorg/scalactic/Every$;
            0     200     1   seq   Lscala/collection/Seq;
    Signature: #64                          // <T:Ljava/lang/Object;>(Lscala/collection/Seq<TT;>;)Lscala/Option<Lorg/scalactic/Every<TT;>;>;
    MethodParameters:
      Name                           Flags
      seq                            final

  public <E extends java.lang.Object> scala.collection.immutable.IndexedSeq<E> everyToGenTraversableOnce(org.scalactic.Every<E>);
    descriptor: (Lorg/scalactic/Every;)Lscala/collection/immutable/IndexedSeq;
    flags: (0x0001) ACC_PUBLIC
    Code:
      stack=1, locals=2, args_size=2
         0: aload_1
         1: invokevirtual #59                 // Method org/scalactic/Every.toVector:()Lscala/collection/immutable/Vector;
         4: areturn
      LineNumberTable:
        line 1548: 0
      LocalVariableTable:
        Start  Length  Slot  Name   Signature
            0       5     0  this   Lorg/scalactic/Every$;
            0       5     1 every   Lorg/scalactic/Every;
    Signature: #102                         // <E:Ljava/lang/Object;>(Lorg/scalactic/Every<TE;>;)Lscala/collection/immutable/IndexedSeq<TE;>;
    MethodParameters:
      Name                           Flags
      every                          final

  public <E extends java.lang.Object> org.scalactic.Every<E> org$scalactic$Every$$fromNonEmptyVector(scala.collection.immutable.Vector<E>);
    descriptor: (Lscala/collection/immutable/Vector;)Lorg/scalactic/Every;
    flags: (0x0001) ACC_PUBLIC
    Code:
      stack=3, locals=2, args_size=2
         0: aload_0
         1: aload_1
         2: invokevirtual #109                // Method scala/collection/immutable/Vector.head:()Ljava/lang/Object;
         5: aload_1
         6: invokevirtual #111                // Method scala/collection/immutable/Vector.tail:()Lscala/collection/immutable/Vector;
         9: invokevirtual #113                // Method apply:(Ljava/lang/Object;Lscala/collection/immutable/Seq;)Lorg/scalactic/Every;
        12: areturn
      LineNumberTable:
        line 1550: 0
      LocalVariableTable:
        Start  Length  Slot  Name   Signature
            0      13     0  this   Lorg/scalactic/Every$;
            0      13     1   vec   Lscala/collection/immutable/Vector;
    Signature: #105                         // <E:Ljava/lang/Object;>(Lscala/collection/immutable/Vector<TE;>;)Lorg/scalactic/Every<TE;>;
    MethodParameters:
      Name                           Flags
      vec                            final

  private java.lang.Object writeReplace();
    descriptor: ()Ljava/lang/Object;
    flags: (0x0002) ACC_PRIVATE
    Code:
      stack=3, locals=1, args_size=1
         0: new           #117                // class scala/runtime/ModuleSerializationProxy
         3: dup
         4: ldc           #2                  // class org/scalactic/Every$
         6: invokespecial #120                // Method scala/runtime/ModuleSerializationProxy."<init>":(Ljava/lang/Class;)V
         9: areturn
      LineNumberTable:
        line 1487: 0
      LocalVariableTable:
        Start  Length  Slot  Name   Signature
            0      10     0  this   Lorg/scalactic/Every$;

  private org.scalactic.Every$();
    descriptor: ()V
    flags: (0x0002) ACC_PRIVATE
    Code:
      stack=1, locals=1, args_size=1
         0: aload_0
         1: invokespecial #121                // Method java/lang/Object."<init>":()V
         4: return
      LineNumberTable:
        line 1563: 0
        line 1487: 4
      LocalVariableTable:
        Start  Length  Slot  Name   Signature
            0       5     0  this   Lorg/scalactic/Every$;
}
SourceFile: "Every.scala"
  ScalaInlineInfo: length = 0x27 (unknown attribute)
   01 01 00 07 00 0C 00 0B 01 00 11 00 12 01 00 64
   00 65 01 00 3E 00 3F 01 00 67 00 68 01 00 32 00
   33 01 00 73 00 24 01
  Scala: length = 0x0 (unknown attribute)

