Classfile /Users/mw/Projects/slang-braindump/.jar/jar11/assemble/slang-braindump/assemble/content/org/scalactic/Explicitly.class
  Last modified May 29, 2022; size 2889 bytes
  SHA-256 checksum af5b05548318f23d0f0799f73b8ea1fe6513a6f8b6f92aec711e72a53d38c32d
  Compiled from "Explicitly.scala"
public interface org.scalactic.Explicitly
  minor version: 0
  major version: 52
  flags: (0x0601) ACC_PUBLIC, ACC_INTERFACE, ACC_ABSTRACT
  this_class: #2                          // org/scalactic/Explicitly
  super_class: #4                         // java/lang/Object
  interfaces: 0, fields: 0, methods: 7, attributes: 5
Constant pool:
   #1 = Utf8               org/scalactic/Explicitly
   #2 = Class              #1             // org/scalactic/Explicitly
   #3 = Utf8               java/lang/Object
   #4 = Class              #3             // java/lang/Object
   #5 = Utf8               Explicitly.scala
   #6 = Utf8               Lscala/reflect/ScalaSignature;
   #7 = Utf8               bytes
   #8 = Utf8               \u0006\u0005\u0005}ca\u0002\u000f\u001e!\u0003\r\tA\t\u0005\u0006S\u0001!\tA\u000b\u0004\u0005]\u0001\u0001q\u0006C\u00031\u0005\u0011\u0005\u0011\u0007C\u00035\u0005\u0011\u0005Q\u0007C\u0004f\u0001\t\u0007I\u0011\u00014\u0007\t\u001d\u0004\u0001\u0001\u001b\u0005\u0006a\u0019!\t!\u001b\u0005\u0006i\u0019!\ta\u001b\u0005\n\u00033\u0001!\u0019!C\u0001\u000371A\u0001\u000f\u0001\u0001s!A!J\u0003B\u0001B\u0003%1\bC\u00031\u0015\u0011\u00051\nC\u0003O\u0015\u0011\u0005q\nC\u0003X\u0015\u0011\u0005\u0001L\u0002\u0003o\u0001\u0001y\u0007\u0002C<\u0010\u0005\u0003\u0005\u000b\u0011B9\t\u000bAzA\u0011\u0001=\t\u000bm|A\u0011\u0001?\t\u000b]{A\u0011A@\u0007\r\u0005u\u0001\u0001AA\u0010\u0011\u0019\u0001D\u0003\"\u0001\u0002\"!9\u0011Q\u0005\u000b\u0005\u0002\u0005\u001d\u0002bBA\u0013)\u0011\u0005\u0011Q\b\u0005\n\u0003#\u0002!\u0019!C\u0001\u0003\':q!!\u0016\u001e\u0011\u0003\t9F\u0002\u0004\u001d;!\u0005\u0011\u0011\f\u0005\u0007ai!\t!!\u0018\u0003\u0015\u0015C\b\u000f\\5dSRd\u0017P\u0003\u0002\u001f?\u0005I1oY1mC\u000e$\u0018n\u0019\u0006\u0002A\u0005\u0019qN]4\u0004\u0001M\u0011\u0001a\t\t\u0003I\u001dj\u0011!\n\u0006\u0002M\u0005)1oY1mC&\u0011\u0001&\n\u0002\u0007\u0003:L(+\u001a4\u0002\r\u0011Jg.\u001b;%)\u0005Y\u0003C\u0001\u0013-\u0013\tiSE\u0001\u0003V]&$(a\u0003#fG&$W\rZ,pe\u0012\u001c\"AA\u0012\u0002\rqJg.\u001b;?)\u0005\u0011\u0004CA\u001a\u0003\u001b\u0005\u0001\u0011A\u00012z+\t1$\r\u0006\u00028GB\u00191GC1\u0003#\u0011+7-\u001b3fI\nKX)];bY&$\u00180\u0006\u0002;\u0003N\u0019!bI\u001e\u0011\u0007qjt(D\u0001\u001e\u0013\tqTD\u0001\u0005FcV\fG.\u001b;z!\t\u0001\u0015\t\u0004\u0001\u0005\u000b\tS!\u0019A\"\u0003\u0003\u0005\u000b\"\u0001R$\u0011\u0005\u0011*\u0015B\u0001$&\u0005\u001dqu\u000e\u001e5j]\u001e\u0004\"\u0001\n%\n\u0005%+#aA!os\u0006AQ-];bY&$\u0018\u0010\u0006\u0002M\u001bB\u00191GC \t\u000b)c\u0001\u0019A\u001e\u0002\u0011\u0005\u0014X-R9vC2$2\u0001U*V!\t!\u0013+\u0003\u0002SK\t9!i\\8mK\u0006t\u0007\"\u0002+\u000e\u0001\u0004y\u0014!A1\t\u000bYk\u0001\u0019A$\u0002\u0003\t\f!\"\u00194uKJ\u0014U-\u001b8h)\tIF\fE\u0002=5~J!aW\u000f\u0003\'9{\'/\\1mSjLgnZ#rk\u0006d\u0017\u000e^=\t\u000bus\u0001\u0019\u00010\u0002\u0015Ut\u0017NZ8s[&$\u0018\u0010E\u0002=?~J!\u0001Y\u000f\u0003\u0015Us\u0017NZ8s[&$\u0018\u0010\u0005\u0002AE\u0012)!\t\u0002b\u0001\u0007\")!\n\u0002a\u0001IB\u0019A(P1\u0002\u000f\u0011,7-\u001b3fIV\t!G\u0001\bEKR,\'/\\5oK\u0012<vN\u001d3\u0014\u0005\u0019\u0019C#\u00016\u0011\u0005M2Qc\u00017\u0002\u0014Q\u0019Q.!\u0006\u0011\tMz\u0011\u0011\u0003\u0002\u0018\t\u0016$XM]7j]\u0016$\')_#rk&4\u0018\r\\3oG\u0016,\"\u0001];\u0014\u0007=\u0019\u0013\u000fE\u0002=eRL!a]\u000f\u0003\u0017\u0015\u000bX/\u001b<bY\u0016t7-\u001a\t\u0003\u0001V$QA^\bC\u0002\r\u0013\u0011\u0001V\u0001\fKF,\u0018N^1mK:\u001cW\r\u0006\u0002zuB\u00191g\u0004;\t\u000b]\f\u0002\u0019A9\u0002\u001b\u0005\u0014X-R9vSZ\fG.\u001a8u)\r\u0001VP \u0005\u0006)J\u0001\r\u0001\u001e\u0005\u0006-J\u0001\r\u0001\u001e\u000b\u0005\u0003\u0003\t9\u0001\u0005\u0003=\u0003\u0007!\u0018bAA\u0003;\t1bj\u001c:nC2L\'0\u001b8h\u000bF,\u0018N^1mK:\u001cW\rC\u0004\u0002\nM\u0001\r!a\u0003\u0002\u001b9|\'/\\1mSj\fG/[8o!\u0011a\u0014Q\u0002;\n\u0007\u0005=QDA\u0007O_Jl\u0017\r\\5{CRLwN\u001c\t\u0004\u0001\u0006MA!\u0002\"\t\u0005\u0004\u0019\u0005BB<\t\u0001\u0004\t9\u0002\u0005\u0003=e\u0006E\u0011A\u00033fi\u0016\u0014X.\u001b8fIV\t!N\u0001\u0007UQ\u0016\fe\r^3s/>\u0014Hm\u0005\u0002\u0015GQ\u0011\u00111\u0005\t\u0003gQ\tQAY3j]\u001e,B!!\u000b\u00022Q!\u00111FA\u001d)\u0011\ti#!\u000e\u0011\tqR\u0016q\u0006\t\u0004\u0001\u0006EBABA\u001a-\t\u00071IA\u0001O\u0011\u0019Qe\u0003q\u0001\u00028A!A(PA\u0018\u0011\u0019if\u00031\u0001\u0002<A!AhXA\u0018+\u0011\ty$a\u0012\u0015\t\u0005\u0005\u0013Q\n\u000b\u0005\u0003\u0007\nI\u0005E\u0003=\u0003\u0007\t)\u0005E\u0002A\u0003\u000f\"a!a\r\u0018\u0005\u0004\u0019\u0005BB<\u0018\u0001\b\tY\u0005\u0005\u0003=e\u0006\u0015\u0003bBA\u0005/\u0001\u0007\u0011q\n\t\u0006y\u00055\u0011QI\u0001\u0006C\u001a$XM]\u000b\u0003\u0003G\t!\"\u0012=qY&\u001c\u0017\u000e\u001e7z!\ta$d\u0005\u0003\u001bG\u0005m\u0003C\u0001\u001f\u0001)\t\t9\u0006
   #9 = Utf8               org/scalactic/Explicitly$DecidedByEquality
  #10 = Class              #9             // org/scalactic/Explicitly$DecidedByEquality
  #11 = Utf8               DecidedByEquality
  #12 = Utf8               org/scalactic/Explicitly$DecidedWord
  #13 = Class              #12            // org/scalactic/Explicitly$DecidedWord
  #14 = Utf8               DecidedWord
  #15 = Utf8               org/scalactic/Explicitly$DeterminedByEquivalence
  #16 = Class              #15            // org/scalactic/Explicitly$DeterminedByEquivalence
  #17 = Utf8               DeterminedByEquivalence
  #18 = Utf8               org/scalactic/Explicitly$DeterminedWord
  #19 = Class              #18            // org/scalactic/Explicitly$DeterminedWord
  #20 = Utf8               DeterminedWord
  #21 = Utf8               org/scalactic/Explicitly$TheAfterWord
  #22 = Class              #21            // org/scalactic/Explicitly$TheAfterWord
  #23 = Utf8               TheAfterWord
  #24 = Utf8               org$scalactic$Explicitly$_setter_$decided_$eq
  #25 = Utf8               (Lorg/scalactic/Explicitly$DecidedWord;)V
  #26 = Utf8               x$1
  #27 = Utf8               org$scalactic$Explicitly$_setter_$determined_$eq
  #28 = Utf8               (Lorg/scalactic/Explicitly$DeterminedWord;)V
  #29 = Utf8               org$scalactic$Explicitly$_setter_$after_$eq
  #30 = Utf8               (Lorg/scalactic/Explicitly$TheAfterWord;)V
  #31 = Utf8               decided
  #32 = Utf8               ()Lorg/scalactic/Explicitly$DecidedWord;
  #33 = Utf8               determined
  #34 = Utf8               ()Lorg/scalactic/Explicitly$DeterminedWord;
  #35 = Utf8               after
  #36 = Utf8               ()Lorg/scalactic/Explicitly$TheAfterWord;
  #37 = Utf8               $init$
  #38 = Utf8               (Lorg/scalactic/Explicitly;)V
  #39 = Utf8               $this
  #40 = Utf8               <init>
  #41 = NameAndType        #40:#38        // "<init>":(Lorg/scalactic/Explicitly;)V
  #42 = Methodref          #13.#41        // org/scalactic/Explicitly$DecidedWord."<init>":(Lorg/scalactic/Explicitly;)V
  #43 = NameAndType        #24:#25        // org$scalactic$Explicitly$_setter_$decided_$eq:(Lorg/scalactic/Explicitly$DecidedWord;)V
  #44 = InterfaceMethodref #2.#43         // org/scalactic/Explicitly.org$scalactic$Explicitly$_setter_$decided_$eq:(Lorg/scalactic/Explicitly$DecidedWord;)V
  #45 = Methodref          #19.#41        // org/scalactic/Explicitly$DeterminedWord."<init>":(Lorg/scalactic/Explicitly;)V
  #46 = NameAndType        #27:#28        // org$scalactic$Explicitly$_setter_$determined_$eq:(Lorg/scalactic/Explicitly$DeterminedWord;)V
  #47 = InterfaceMethodref #2.#46         // org/scalactic/Explicitly.org$scalactic$Explicitly$_setter_$determined_$eq:(Lorg/scalactic/Explicitly$DeterminedWord;)V
  #48 = Methodref          #22.#41        // org/scalactic/Explicitly$TheAfterWord."<init>":(Lorg/scalactic/Explicitly;)V
  #49 = NameAndType        #29:#30        // org$scalactic$Explicitly$_setter_$after_$eq:(Lorg/scalactic/Explicitly$TheAfterWord;)V
  #50 = InterfaceMethodref #2.#49         // org/scalactic/Explicitly.org$scalactic$Explicitly$_setter_$after_$eq:(Lorg/scalactic/Explicitly$TheAfterWord;)V
  #51 = Utf8               Lorg/scalactic/Explicitly;
  #52 = Utf8               MethodParameters
  #53 = Utf8               Code
  #54 = Utf8               LineNumberTable
  #55 = Utf8               LocalVariableTable
  #56 = Utf8               InnerClasses
  #57 = Utf8               SourceFile
  #58 = Utf8               RuntimeVisibleAnnotations
  #59 = Utf8               ScalaInlineInfo
  #60 = Utf8               ScalaSig
{
  public abstract void org$scalactic$Explicitly$_setter_$decided_$eq(org.scalactic.Explicitly$DecidedWord);
    descriptor: (Lorg/scalactic/Explicitly$DecidedWord;)V
    flags: (0x0401) ACC_PUBLIC, ACC_ABSTRACT
    MethodParameters:
      Name                           Flags
      x$1                            final

  public abstract void org$scalactic$Explicitly$_setter_$determined_$eq(org.scalactic.Explicitly$DeterminedWord);
    descriptor: (Lorg/scalactic/Explicitly$DeterminedWord;)V
    flags: (0x0401) ACC_PUBLIC, ACC_ABSTRACT
    MethodParameters:
      Name                           Flags
      x$1                            final

  public abstract void org$scalactic$Explicitly$_setter_$after_$eq(org.scalactic.Explicitly$TheAfterWord);
    descriptor: (Lorg/scalactic/Explicitly$TheAfterWord;)V
    flags: (0x0401) ACC_PUBLIC, ACC_ABSTRACT
    MethodParameters:
      Name                           Flags
      x$1                            final

  public abstract org.scalactic.Explicitly$DecidedWord decided();
    descriptor: ()Lorg/scalactic/Explicitly$DecidedWord;
    flags: (0x0401) ACC_PUBLIC, ACC_ABSTRACT

  public abstract org.scalactic.Explicitly$DeterminedWord determined();
    descriptor: ()Lorg/scalactic/Explicitly$DeterminedWord;
    flags: (0x0401) ACC_PUBLIC, ACC_ABSTRACT

  public abstract org.scalactic.Explicitly$TheAfterWord after();
    descriptor: ()Lorg/scalactic/Explicitly$TheAfterWord;
    flags: (0x0401) ACC_PUBLIC, ACC_ABSTRACT

  public static void $init$(org.scalactic.Explicitly);
    descriptor: (Lorg/scalactic/Explicitly;)V
    flags: (0x0009) ACC_PUBLIC, ACC_STATIC
    Code:
      stack=4, locals=1, args_size=1
         0: aload_0
         1: new           #13                 // class org/scalactic/Explicitly$DecidedWord
         4: dup
         5: aload_0
         6: invokespecial #42                 // Method org/scalactic/Explicitly$DecidedWord."<init>":(Lorg/scalactic/Explicitly;)V
         9: invokeinterface #44,  2           // InterfaceMethod org$scalactic$Explicitly$_setter_$decided_$eq:(Lorg/scalactic/Explicitly$DecidedWord;)V
        14: aload_0
        15: new           #19                 // class org/scalactic/Explicitly$DeterminedWord
        18: dup
        19: aload_0
        20: invokespecial #45                 // Method org/scalactic/Explicitly$DeterminedWord."<init>":(Lorg/scalactic/Explicitly;)V
        23: invokeinterface #47,  2           // InterfaceMethod org$scalactic$Explicitly$_setter_$determined_$eq:(Lorg/scalactic/Explicitly$DeterminedWord;)V
        28: aload_0
        29: new           #22                 // class org/scalactic/Explicitly$TheAfterWord
        32: dup
        33: aload_0
        34: invokespecial #48                 // Method org/scalactic/Explicitly$TheAfterWord."<init>":(Lorg/scalactic/Explicitly;)V
        37: invokeinterface #50,  2           // InterfaceMethod org$scalactic$Explicitly$_setter_$after_$eq:(Lorg/scalactic/Explicitly$TheAfterWord;)V
        42: return
      LineNumberTable:
        line 112: 0
        line 145: 14
        line 292: 28
        line 82: 42
      LocalVariableTable:
        Start  Length  Slot  Name   Signature
            0      43     0 $this   Lorg/scalactic/Explicitly;
    MethodParameters:
      Name                           Flags
      $this                          final synthetic
}
InnerClasses:
  public #11= #10 of #2;                  // DecidedByEquality=class org/scalactic/Explicitly$DecidedByEquality of class org/scalactic/Explicitly
  public #14= #13 of #2;                  // DecidedWord=class org/scalactic/Explicitly$DecidedWord of class org/scalactic/Explicitly
  public #17= #16 of #2;                  // DeterminedByEquivalence=class org/scalactic/Explicitly$DeterminedByEquivalence of class org/scalactic/Explicitly
  public #20= #19 of #2;                  // DeterminedWord=class org/scalactic/Explicitly$DeterminedWord of class org/scalactic/Explicitly
  public #23= #22 of #2;                  // TheAfterWord=class org/scalactic/Explicitly$TheAfterWord of class org/scalactic/Explicitly
SourceFile: "Explicitly.scala"
RuntimeVisibleAnnotations:
  0: #6(#7=s#8)
    scala.reflect.ScalaSignature(
      bytes="\u0006\u0005\u0005}ca\u0002\u000f\u001e!\u0003\r\tA\t\u0005\u0006S\u0001!\tA\u000b\u0004\u0005]\u0001\u0001q\u0006C\u00031\u0005\u0011\u0005\u0011\u0007C\u00035\u0005\u0011\u0005Q\u0007C\u0004f\u0001\t\u0007I\u0011\u00014\u0007\t\u001d\u0004\u0001\u0001\u001b\u0005\u0006a\u0019!\t!\u001b\u0005\u0006i\u0019!\ta\u001b\u0005\n\u00033\u0001!\u0019!C\u0001\u000371A\u0001\u000f\u0001\u0001s!A!J\u0003B\u0001B\u0003%1\bC\u00031\u0015\u0011\u00051\nC\u0003O\u0015\u0011\u0005q\nC\u0003X\u0015\u0011\u0005\u0001L\u0002\u0003o\u0001\u0001y\u0007\u0002C<\u0010\u0005\u0003\u0005\u000b\u0011B9\t\u000bAzA\u0011\u0001=\t\u000bm|A\u0011\u0001?\t\u000b]{A\u0011A@\u0007\r\u0005u\u0001\u0001AA\u0010\u0011\u0019\u0001D\u0003\"\u0001\u0002\"!9\u0011Q\u0005\u000b\u0005\u0002\u0005\u001d\u0002bBA\u0013)\u0011\u0005\u0011Q\b\u0005\n\u0003#\u0002!\u0019!C\u0001\u0003\':q!!\u0016\u001e\u0011\u0003\t9F\u0002\u0004\u001d;!\u0005\u0011\u0011\f\u0005\u0007ai!\t!!\u0018\u0003\u0015\u0015C\b\u000f\\5dSRd\u0017P\u0003\u0002\u001f?\u0005I1oY1mC\u000e$\u0018n\u0019\u0006\u0002A\u0005\u0019qN]4\u0004\u0001M\u0011\u0001a\t\t\u0003I\u001dj\u0011!\n\u0006\u0002M\u0005)1oY1mC&\u0011\u0001&\n\u0002\u0007\u0003:L(+\u001a4\u0002\r\u0011Jg.\u001b;%)\u0005Y\u0003C\u0001\u0013-\u0013\tiSE\u0001\u0003V]&$(a\u0003#fG&$W\rZ,pe\u0012\u001c\"AA\u0012\u0002\rqJg.\u001b;?)\u0005\u0011\u0004CA\u001a\u0003\u001b\u0005\u0001\u0011A\u00012z+\t1$\r\u0006\u00028GB\u00191GC1\u0003#\u0011+7-\u001b3fI\nKX)];bY&$\u00180\u0006\u0002;\u0003N\u0019!bI\u001e\u0011\u0007qjt(D\u0001\u001e\u0013\tqTD\u0001\u0005FcV\fG.\u001b;z!\t\u0001\u0015\t\u0004\u0001\u0005\u000b\tS!\u0019A\"\u0003\u0003\u0005\u000b\"\u0001R$\u0011\u0005\u0011*\u0015B\u0001$&\u0005\u001dqu\u000e\u001e5j]\u001e\u0004\"\u0001\n%\n\u0005%+#aA!os\u0006AQ-];bY&$\u0018\u0010\u0006\u0002M\u001bB\u00191GC \t\u000b)c\u0001\u0019A\u001e\u0002\u0011\u0005\u0014X-R9vC2$2\u0001U*V!\t!\u0013+\u0003\u0002SK\t9!i\\8mK\u0006t\u0007\"\u0002+\u000e\u0001\u0004y\u0014!A1\t\u000bYk\u0001\u0019A$\u0002\u0003\t\f!\"\u00194uKJ\u0014U-\u001b8h)\tIF\fE\u0002=5~J!aW\u000f\u0003\'9{\'/\\1mSjLgnZ#rk\u0006d\u0017\u000e^=\t\u000bus\u0001\u0019\u00010\u0002\u0015Ut\u0017NZ8s[&$\u0018\u0010E\u0002=?~J!\u0001Y\u000f\u0003\u0015Us\u0017NZ8s[&$\u0018\u0010\u0005\u0002AE\u0012)!\t\u0002b\u0001\u0007\")!\n\u0002a\u0001IB\u0019A(P1\u0002\u000f\u0011,7-\u001b3fIV\t!G\u0001\bEKR,\'/\\5oK\u0012<vN\u001d3\u0014\u0005\u0019\u0019C#\u00016\u0011\u0005M2Qc\u00017\u0002\u0014Q\u0019Q.!\u0006\u0011\tMz\u0011\u0011\u0003\u0002\u0018\t\u0016$XM]7j]\u0016$\')_#rk&4\u0018\r\\3oG\u0016,\"\u0001];\u0014\u0007=\u0019\u0013\u000fE\u0002=eRL!a]\u000f\u0003\u0017\u0015\u000bX/\u001b<bY\u0016t7-\u001a\t\u0003\u0001V$QA^\bC\u0002\r\u0013\u0011\u0001V\u0001\fKF,\u0018N^1mK:\u001cW\r\u0006\u0002zuB\u00191g\u0004;\t\u000b]\f\u0002\u0019A9\u0002\u001b\u0005\u0014X-R9vSZ\fG.\u001a8u)\r\u0001VP \u0005\u0006)J\u0001\r\u0001\u001e\u0005\u0006-J\u0001\r\u0001\u001e\u000b\u0005\u0003\u0003\t9\u0001\u0005\u0003=\u0003\u0007!\u0018bAA\u0003;\t1bj\u001c:nC2L\'0\u001b8h\u000bF,\u0018N^1mK:\u001cW\rC\u0004\u0002\nM\u0001\r!a\u0003\u0002\u001b9|\'/\\1mSj\fG/[8o!\u0011a\u0014Q\u0002;\n\u0007\u0005=QDA\u0007O_Jl\u0017\r\\5{CRLwN\u001c\t\u0004\u0001\u0006MA!\u0002\"\t\u0005\u0004\u0019\u0005BB<\t\u0001\u0004\t9\u0002\u0005\u0003=e\u0006E\u0011A\u00033fi\u0016\u0014X.\u001b8fIV\t!N\u0001\u0007UQ\u0016\fe\r^3s/>\u0014Hm\u0005\u0002\u0015GQ\u0011\u00111\u0005\t\u0003gQ\tQAY3j]\u001e,B!!\u000b\u00022Q!\u00111FA\u001d)\u0011\ti#!\u000e\u0011\tqR\u0016q\u0006\t\u0004\u0001\u0006EBABA\u001a-\t\u00071IA\u0001O\u0011\u0019Qe\u0003q\u0001\u00028A!A(PA\u0018\u0011\u0019if\u00031\u0001\u0002<A!AhXA\u0018+\u0011\ty$a\u0012\u0015\t\u0005\u0005\u0013Q\n\u000b\u0005\u0003\u0007\nI\u0005E\u0003=\u0003\u0007\t)\u0005E\u0002A\u0003\u000f\"a!a\r\u0018\u0005\u0004\u0019\u0005BB<\u0018\u0001\b\tY\u0005\u0005\u0003=e\u0006\u0015\u0003bBA\u0005/\u0001\u0007\u0011q\n\t\u0006y\u00055\u0011QI\u0001\u0006C\u001a$XM]\u000b\u0003\u0003G\t!\"\u0012=qY&\u001c\u0017\u000e\u001e7z!\ta$d\u0005\u0003\u001bG\u0005m\u0003C\u0001\u001f\u0001)\t\t9\u0006"
    )
  ScalaInlineInfo: length = 0x27 (unknown attribute)
   01 00 00 07 00 25 00 26 01 00 23 00 24 00 00 1F
   00 20 00 00 21 00 22 00 00 1D 00 1E 00 00 18 00
   19 00 00 1B 00 1C 00
  ScalaSig: length = 0x3 (unknown attribute)
   05 02 00
