Classfile /Users/mw/Projects/slang-braindump/.jar/jar11/assemble/slang-braindump/assemble/content/org/scalactic/Explicitly$.class
  Last modified May 29, 2022; size 1845 bytes
  SHA-256 checksum 968d237cf80bc68361970d4cefd69e0e12ad750dda2445479e8aade121f6e9ea
  Compiled from "Explicitly.scala"
public final class org.scalactic.Explicitly$ implements org.scalactic.Explicitly
  minor version: 0
  major version: 52
  flags: (0x0031) ACC_PUBLIC, ACC_FINAL, ACC_SUPER
  this_class: #2                          // org/scalactic/Explicitly$
  super_class: #4                         // java/lang/Object
  interfaces: 1, fields: 4, methods: 8, attributes: 4
Constant pool:
   #1 = Utf8               org/scalactic/Explicitly$
   #2 = Class              #1             // org/scalactic/Explicitly$
   #3 = Utf8               java/lang/Object
   #4 = Class              #3             // java/lang/Object
   #5 = Utf8               org/scalactic/Explicitly
   #6 = Class              #5             // org/scalactic/Explicitly
   #7 = Utf8               Explicitly.scala
   #8 = Utf8               org/scalactic/Explicitly$DecidedWord
   #9 = Class              #8             // org/scalactic/Explicitly$DecidedWord
  #10 = Utf8               DecidedWord
  #11 = Utf8               org/scalactic/Explicitly$DeterminedWord
  #12 = Class              #11            // org/scalactic/Explicitly$DeterminedWord
  #13 = Utf8               DeterminedWord
  #14 = Utf8               org/scalactic/Explicitly$TheAfterWord
  #15 = Class              #14            // org/scalactic/Explicitly$TheAfterWord
  #16 = Utf8               TheAfterWord
  #17 = Utf8               MODULE$
  #18 = Utf8               Lorg/scalactic/Explicitly$;
  #19 = Utf8               decided
  #20 = Utf8               Lorg/scalactic/Explicitly$DecidedWord;
  #21 = Utf8               determined
  #22 = Utf8               Lorg/scalactic/Explicitly$DeterminedWord;
  #23 = Utf8               after
  #24 = Utf8               Lorg/scalactic/Explicitly$TheAfterWord;
  #25 = Utf8               <clinit>
  #26 = Utf8               ()V
  #27 = Utf8               <init>
  #28 = NameAndType        #27:#26        // "<init>":()V
  #29 = Methodref          #2.#28         // org/scalactic/Explicitly$."<init>":()V
  #30 = NameAndType        #17:#18        // MODULE$:Lorg/scalactic/Explicitly$;
  #31 = Fieldref           #2.#30         // org/scalactic/Explicitly$.MODULE$:Lorg/scalactic/Explicitly$;
  #32 = Utf8               $init$
  #33 = Utf8               (Lorg/scalactic/Explicitly;)V
  #34 = NameAndType        #32:#33        // $init$:(Lorg/scalactic/Explicitly;)V
  #35 = InterfaceMethodref #6.#34         // org/scalactic/Explicitly.$init$:(Lorg/scalactic/Explicitly;)V
  #36 = Utf8               ()Lorg/scalactic/Explicitly$DecidedWord;
  #37 = NameAndType        #19:#20        // decided:Lorg/scalactic/Explicitly$DecidedWord;
  #38 = Fieldref           #2.#37         // org/scalactic/Explicitly$.decided:Lorg/scalactic/Explicitly$DecidedWord;
  #39 = Utf8               this
  #40 = Utf8               ()Lorg/scalactic/Explicitly$DeterminedWord;
  #41 = NameAndType        #21:#22        // determined:Lorg/scalactic/Explicitly$DeterminedWord;
  #42 = Fieldref           #2.#41         // org/scalactic/Explicitly$.determined:Lorg/scalactic/Explicitly$DeterminedWord;
  #43 = Utf8               ()Lorg/scalactic/Explicitly$TheAfterWord;
  #44 = NameAndType        #23:#24        // after:Lorg/scalactic/Explicitly$TheAfterWord;
  #45 = Fieldref           #2.#44         // org/scalactic/Explicitly$.after:Lorg/scalactic/Explicitly$TheAfterWord;
  #46 = Utf8               org$scalactic$Explicitly$_setter_$decided_$eq
  #47 = Utf8               (Lorg/scalactic/Explicitly$DecidedWord;)V
  #48 = Utf8               x$1
  #49 = Utf8               org$scalactic$Explicitly$_setter_$determined_$eq
  #50 = Utf8               (Lorg/scalactic/Explicitly$DeterminedWord;)V
  #51 = Utf8               org$scalactic$Explicitly$_setter_$after_$eq
  #52 = Utf8               (Lorg/scalactic/Explicitly$TheAfterWord;)V
  #53 = Methodref          #4.#28         // java/lang/Object."<init>":()V
  #54 = Utf8               Code
  #55 = Utf8               LineNumberTable
  #56 = Utf8               LocalVariableTable
  #57 = Utf8               MethodParameters
  #58 = Utf8               InnerClasses
  #59 = Utf8               SourceFile
  #60 = Utf8               ScalaInlineInfo
  #61 = Utf8               Scala
{
  public static final org.scalactic.Explicitly$ MODULE$;
    descriptor: Lorg/scalactic/Explicitly$;
    flags: (0x0019) ACC_PUBLIC, ACC_STATIC, ACC_FINAL

  private static org.scalactic.Explicitly$DecidedWord decided;
    descriptor: Lorg/scalactic/Explicitly$DecidedWord;
    flags: (0x000a) ACC_PRIVATE, ACC_STATIC

  private static org.scalactic.Explicitly$DeterminedWord determined;
    descriptor: Lorg/scalactic/Explicitly$DeterminedWord;
    flags: (0x000a) ACC_PRIVATE, ACC_STATIC

  private static org.scalactic.Explicitly$TheAfterWord after;
    descriptor: Lorg/scalactic/Explicitly$TheAfterWord;
    flags: (0x000a) ACC_PRIVATE, ACC_STATIC

  public static {};
    descriptor: ()V
    flags: (0x0009) ACC_PUBLIC, ACC_STATIC
    Code:
      stack=2, locals=0, args_size=0
         0: new           #2                  // class org/scalactic/Explicitly$
         3: dup
         4: invokespecial #29                 // Method "<init>":()V
         7: putstatic     #31                 // Field MODULE$:Lorg/scalactic/Explicitly$;
        10: getstatic     #31                 // Field MODULE$:Lorg/scalactic/Explicitly$;
        13: invokestatic  #35                 // InterfaceMethod org/scalactic/Explicitly.$init$:(Lorg/scalactic/Explicitly;)V
        16: return
      LineNumberTable:
        line 306: 0

  public org.scalactic.Explicitly$DecidedWord decided();
    descriptor: ()Lorg/scalactic/Explicitly$DecidedWord;
    flags: (0x0001) ACC_PUBLIC
    Code:
      stack=1, locals=1, args_size=1
         0: getstatic     #38                 // Field decided:Lorg/scalactic/Explicitly$DecidedWord;
         3: areturn
      LineNumberTable:
        line 306: 0
      LocalVariableTable:
        Start  Length  Slot  Name   Signature
            0       4     0  this   Lorg/scalactic/Explicitly$;

  public org.scalactic.Explicitly$DeterminedWord determined();
    descriptor: ()Lorg/scalactic/Explicitly$DeterminedWord;
    flags: (0x0001) ACC_PUBLIC
    Code:
      stack=1, locals=1, args_size=1
         0: getstatic     #42                 // Field determined:Lorg/scalactic/Explicitly$DeterminedWord;
         3: areturn
      LineNumberTable:
        line 306: 0
      LocalVariableTable:
        Start  Length  Slot  Name   Signature
            0       4     0  this   Lorg/scalactic/Explicitly$;

  public org.scalactic.Explicitly$TheAfterWord after();
    descriptor: ()Lorg/scalactic/Explicitly$TheAfterWord;
    flags: (0x0001) ACC_PUBLIC
    Code:
      stack=1, locals=1, args_size=1
         0: getstatic     #45                 // Field after:Lorg/scalactic/Explicitly$TheAfterWord;
         3: areturn
      LineNumberTable:
        line 306: 0
      LocalVariableTable:
        Start  Length  Slot  Name   Signature
            0       4     0  this   Lorg/scalactic/Explicitly$;

  public void org$scalactic$Explicitly$_setter_$decided_$eq(org.scalactic.Explicitly$DecidedWord);
    descriptor: (Lorg/scalactic/Explicitly$DecidedWord;)V
    flags: (0x0001) ACC_PUBLIC
    Code:
      stack=1, locals=2, args_size=2
         0: aload_1
         1: putstatic     #38                 // Field decided:Lorg/scalactic/Explicitly$DecidedWord;
         4: return
      LineNumberTable:
        line 306: 0
      LocalVariableTable:
        Start  Length  Slot  Name   Signature
            0       5     0  this   Lorg/scalactic/Explicitly$;
            0       5     1   x$1   Lorg/scalactic/Explicitly$DecidedWord;
    MethodParameters:
      Name                           Flags
      x$1                            final

  public void org$scalactic$Explicitly$_setter_$determined_$eq(org.scalactic.Explicitly$DeterminedWord);
    descriptor: (Lorg/scalactic/Explicitly$DeterminedWord;)V
    flags: (0x0001) ACC_PUBLIC
    Code:
      stack=1, locals=2, args_size=2
         0: aload_1
         1: putstatic     #42                 // Field determined:Lorg/scalactic/Explicitly$DeterminedWord;
         4: return
      LineNumberTable:
        line 306: 0
      LocalVariableTable:
        Start  Length  Slot  Name   Signature
            0       5     0  this   Lorg/scalactic/Explicitly$;
            0       5     1   x$1   Lorg/scalactic/Explicitly$DeterminedWord;
    MethodParameters:
      Name                           Flags
      x$1                            final

  public void org$scalactic$Explicitly$_setter_$after_$eq(org.scalactic.Explicitly$TheAfterWord);
    descriptor: (Lorg/scalactic/Explicitly$TheAfterWord;)V
    flags: (0x0001) ACC_PUBLIC
    Code:
      stack=1, locals=2, args_size=2
         0: aload_1
         1: putstatic     #45                 // Field after:Lorg/scalactic/Explicitly$TheAfterWord;
         4: return
      LineNumberTable:
        line 306: 0
      LocalVariableTable:
        Start  Length  Slot  Name   Signature
            0       5     0  this   Lorg/scalactic/Explicitly$;
            0       5     1   x$1   Lorg/scalactic/Explicitly$TheAfterWord;
    MethodParameters:
      Name                           Flags
      x$1                            final

  private org.scalactic.Explicitly$();
    descriptor: ()V
    flags: (0x0002) ACC_PRIVATE
    Code:
      stack=1, locals=1, args_size=1
         0: aload_0
         1: invokespecial #53                 // Method java/lang/Object."<init>":()V
         4: return
      LineNumberTable:
        line 306: 0
      LocalVariableTable:
        Start  Length  Slot  Name   Signature
            0       5     0  this   Lorg/scalactic/Explicitly$;
}
InnerClasses:
  public #10= #9 of #6;                   // DecidedWord=class org/scalactic/Explicitly$DecidedWord of class org/scalactic/Explicitly
  public #13= #12 of #6;                  // DeterminedWord=class org/scalactic/Explicitly$DeterminedWord of class org/scalactic/Explicitly
  public #16= #15 of #6;                  // TheAfterWord=class org/scalactic/Explicitly$TheAfterWord of class org/scalactic/Explicitly
SourceFile: "Explicitly.scala"
  ScalaInlineInfo: length = 0x27 (unknown attribute)
   01 01 00 07 00 1B 00 1A 01 00 17 00 2B 01 00 13
   00 24 01 00 15 00 28 01 00 33 00 34 01 00 2E 00
   2F 01 00 31 00 32 01
  Scala: length = 0x0 (unknown attribute)

