Classfile /Users/mw/Projects/slang-braindump/.jar/jar11/assemble/slang-braindump/assemble/content/org/scalactic/FutureSugar$Futureizer.class
  Last modified May 29, 2022; size 4171 bytes
  SHA-256 checksum 57cdd2fdddf2af533897a1bf3f77204e20ce08aeb019a694fde34063f369fc02
  Compiled from "FutureSugar.scala"
public class org.scalactic.FutureSugar$Futureizer<T extends java.lang.Object> extends java.lang.Object
  minor version: 0
  major version: 52
  flags: (0x0021) ACC_PUBLIC, ACC_SUPER
  this_class: #2                          // org/scalactic/FutureSugar$Futureizer
  super_class: #5                         // java/lang/Object
  interfaces: 0, fields: 2, methods: 5, attributes: 6
Constant pool:
    #1 = Utf8               org/scalactic/FutureSugar$Futureizer
    #2 = Class              #1            // org/scalactic/FutureSugar$Futureizer
    #3 = Utf8               <T:Ljava/lang/Object;>Ljava/lang/Object;
    #4 = Utf8               java/lang/Object
    #5 = Class              #4            // java/lang/Object
    #6 = Utf8               FutureSugar.scala
    #7 = Utf8               java/lang/invoke/MethodHandles$Lookup
    #8 = Class              #7            // java/lang/invoke/MethodHandles$Lookup
    #9 = Utf8               java/lang/invoke/MethodHandles
   #10 = Class              #9            // java/lang/invoke/MethodHandles
   #11 = Utf8               Lookup
   #12 = Utf8               org/scalactic/FutureSugar
   #13 = Class              #12           // org/scalactic/FutureSugar
   #14 = Utf8               Futureizer
   #15 = Utf8               theFuture
   #16 = Utf8               Lscala/concurrent/Future;
   #17 = Utf8               Lscala/concurrent/Future<TT;>;
   #18 = Utf8               $outer
   #19 = Utf8               Lorg/scalactic/FutureSugar;
   #20 = Utf8               validating
   #21 = Utf8               (Lscala/Function1;Lscala/collection/immutable/Seq;Lscala/concurrent/ExecutionContext;)Lscala/concurrent/Future;
   #22 = Utf8               (Lscala/Function1<TT;Lorg/scalactic/Validation<Ljava/lang/String;>;>;Lscala/collection/immutable/Seq<Lscala/Function1<TT;Lorg/scalactic/Validation<Ljava/lang/String;>;>;>;Lscala/concurrent/ExecutionContext;)Lscala/concurrent/Future<TT;>;
   #23 = Utf8               first
   #24 = Utf8               rest
   #25 = Utf8               executor
   #26 = NameAndType        #15:#16       // theFuture:Lscala/concurrent/Future;
   #27 = Fieldref           #2.#26        // org/scalactic/FutureSugar$Futureizer.theFuture:Lscala/concurrent/Future;
   #28 = Utf8               (Ljava/lang/Object;)Ljava/lang/Object;
   #29 = MethodType         #28           //  (Ljava/lang/Object;)Ljava/lang/Object;
   #30 = Utf8               $anonfun$validating$1
   #31 = Utf8               (Lorg/scalactic/FutureSugar$Futureizer;Lscala/Function1;Lscala/collection/immutable/Seq;Ljava/lang/Object;)Lscala/concurrent/Future;
   #32 = NameAndType        #30:#31       // $anonfun$validating$1:(Lorg/scalactic/FutureSugar$Futureizer;Lscala/Function1;Lscala/collection/immutable/Seq;Ljava/lang/Object;)Lscala/concurrent/Future;
   #33 = Methodref          #2.#32        // org/scalactic/FutureSugar$Futureizer.$anonfun$validating$1:(Lorg/scalactic/FutureSugar$Futureizer;Lscala/Function1;Lscala/collection/immutable/Seq;Ljava/lang/Object;)Lscala/concurrent/Future;
   #34 = MethodHandle       6:#33         // REF_invokeStatic org/scalactic/FutureSugar$Futureizer.$anonfun$validating$1:(Lorg/scalactic/FutureSugar$Futureizer;Lscala/Function1;Lscala/collection/immutable/Seq;Ljava/lang/Object;)Lscala/concurrent/Future;
   #35 = Utf8               (Ljava/lang/Object;)Lscala/concurrent/Future;
   #36 = MethodType         #35           //  (Ljava/lang/Object;)Lscala/concurrent/Future;
   #37 = Integer            5
   #38 = Integer            1
   #39 = Utf8               java/lang/invoke/LambdaMetafactory
   #40 = Class              #39           // java/lang/invoke/LambdaMetafactory
   #41 = Utf8               altMetafactory
   #42 = Utf8               (Ljava/lang/invoke/MethodHandles$Lookup;Ljava/lang/String;Ljava/lang/invoke/MethodType;[Ljava/lang/Object;)Ljava/lang/invoke/CallSite;
   #43 = NameAndType        #41:#42       // altMetafactory:(Ljava/lang/invoke/MethodHandles$Lookup;Ljava/lang/String;Ljava/lang/invoke/MethodType;[Ljava/lang/Object;)Ljava/lang/invoke/CallSite;
   #44 = Methodref          #40.#43       // java/lang/invoke/LambdaMetafactory.altMetafactory:(Ljava/lang/invoke/MethodHandles$Lookup;Ljava/lang/String;Ljava/lang/invoke/MethodType;[Ljava/lang/Object;)Ljava/lang/invoke/CallSite;
   #45 = MethodHandle       6:#44         // REF_invokeStatic java/lang/invoke/LambdaMetafactory.altMetafactory:(Ljava/lang/invoke/MethodHandles$Lookup;Ljava/lang/String;Ljava/lang/invoke/MethodType;[Ljava/lang/Object;)Ljava/lang/invoke/CallSite;
   #46 = Utf8               apply
   #47 = Utf8               (Lorg/scalactic/FutureSugar$Futureizer;Lscala/Function1;Lscala/collection/immutable/Seq;)Lscala/Function1;
   #48 = NameAndType        #46:#47       // apply:(Lorg/scalactic/FutureSugar$Futureizer;Lscala/Function1;Lscala/collection/immutable/Seq;)Lscala/Function1;
   #49 = InvokeDynamic      #0:#48        // #0:apply:(Lorg/scalactic/FutureSugar$Futureizer;Lscala/Function1;Lscala/collection/immutable/Seq;)Lscala/Function1;
   #50 = Utf8               scala/concurrent/Future
   #51 = Class              #50           // scala/concurrent/Future
   #52 = Utf8               flatMap
   #53 = Utf8               (Lscala/Function1;Lscala/concurrent/ExecutionContext;)Lscala/concurrent/Future;
   #54 = NameAndType        #52:#53       // flatMap:(Lscala/Function1;Lscala/concurrent/ExecutionContext;)Lscala/concurrent/Future;
   #55 = InterfaceMethodref #51.#54       // scala/concurrent/Future.flatMap:(Lscala/Function1;Lscala/concurrent/ExecutionContext;)Lscala/concurrent/Future;
   #56 = Utf8               this
   #57 = Utf8               Lorg/scalactic/FutureSugar$Futureizer;
   #58 = Utf8               Lscala/Function1;
   #59 = Utf8               Lscala/collection/immutable/Seq;
   #60 = Utf8               Lscala/concurrent/ExecutionContext;
   #61 = Utf8               org$scalactic$FutureSugar$Futureizer$$$outer
   #62 = Utf8               ()Lorg/scalactic/FutureSugar;
   #63 = NameAndType        #18:#19       // $outer:Lorg/scalactic/FutureSugar;
   #64 = Fieldref           #2.#63        // org/scalactic/FutureSugar$Futureizer.$outer:Lorg/scalactic/FutureSugar;
   #65 = Utf8               $this
   #66 = Utf8               first$1
   #67 = Utf8               rest$1
   #68 = Utf8               o
   #69 = Utf8               org/scalactic/TrySugar$
   #70 = Class              #69           // org/scalactic/TrySugar$
   #71 = Utf8               MODULE$
   #72 = Utf8               Lorg/scalactic/TrySugar$;
   #73 = NameAndType        #71:#72       // MODULE$:Lorg/scalactic/TrySugar$;
   #74 = Fieldref           #70.#73       // org/scalactic/TrySugar$.MODULE$:Lorg/scalactic/TrySugar$;
   #75 = Utf8               scala/collection/immutable/Seq
   #76 = Class              #75           // scala/collection/immutable/Seq
   #77 = Utf8               toList
   #78 = Utf8               ()Lscala/collection/immutable/List;
   #79 = NameAndType        #77:#78       // toList:()Lscala/collection/immutable/List;
   #80 = InterfaceMethodref #76.#79       // scala/collection/immutable/Seq.toList:()Lscala/collection/immutable/List;
   #81 = Utf8               scala/collection/immutable/List
   #82 = Class              #81           // scala/collection/immutable/List
   #83 = Utf8               $colon$colon
   #84 = Utf8               (Ljava/lang/Object;)Lscala/collection/immutable/List;
   #85 = NameAndType        #83:#84       // $colon$colon:(Ljava/lang/Object;)Lscala/collection/immutable/List;
   #86 = Methodref          #82.#85       // scala/collection/immutable/List.$colon$colon:(Ljava/lang/Object;)Lscala/collection/immutable/List;
   #87 = Utf8               passOrFirstFail
   #88 = Utf8               (Ljava/lang/Object;Lscala/collection/immutable/List;)Lorg/scalactic/Validation;
   #89 = NameAndType        #87:#88       // passOrFirstFail:(Ljava/lang/Object;Lscala/collection/immutable/List;)Lorg/scalactic/Validation;
   #90 = Methodref          #70.#89       // org/scalactic/TrySugar$.passOrFirstFail:(Ljava/lang/Object;Lscala/collection/immutable/List;)Lorg/scalactic/Validation;
   #91 = Utf8               org/scalactic/Pass$
   #92 = Class              #91           // org/scalactic/Pass$
   #93 = Utf8               Lorg/scalactic/Pass$;
   #94 = NameAndType        #71:#93       // MODULE$:Lorg/scalactic/Pass$;
   #95 = Fieldref           #92.#94       // org/scalactic/Pass$.MODULE$:Lorg/scalactic/Pass$;
   #96 = Utf8               equals
   #97 = Utf8               (Ljava/lang/Object;)Z
   #98 = NameAndType        #96:#97       // equals:(Ljava/lang/Object;)Z
   #99 = Methodref          #5.#98        // java/lang/Object.equals:(Ljava/lang/Object;)Z
  #100 = Utf8               org/scalactic/Fail
  #101 = Class              #100          // org/scalactic/Fail
  #102 = Utf8               error
  #103 = Utf8               ()Ljava/lang/Object;
  #104 = NameAndType        #102:#103     // error:()Ljava/lang/Object;
  #105 = Methodref          #101.#104     // org/scalactic/Fail.error:()Ljava/lang/Object;
  #106 = Utf8               java/lang/String
  #107 = Class              #106          // java/lang/String
  #108 = Utf8               scala/concurrent/Future$
  #109 = Class              #108          // scala/concurrent/Future$
  #110 = Utf8               Lscala/concurrent/Future$;
  #111 = NameAndType        #71:#110      // MODULE$:Lscala/concurrent/Future$;
  #112 = Fieldref           #109.#111     // scala/concurrent/Future$.MODULE$:Lscala/concurrent/Future$;
  #113 = Utf8               org/scalactic/exceptions/ValidationFailedException
  #114 = Class              #113          // org/scalactic/exceptions/ValidationFailedException
  #115 = Utf8               <init>
  #116 = Utf8               (Ljava/lang/String;)V
  #117 = NameAndType        #115:#116     // "<init>":(Ljava/lang/String;)V
  #118 = Methodref          #114.#117     // org/scalactic/exceptions/ValidationFailedException."<init>":(Ljava/lang/String;)V
  #119 = Utf8               failed
  #120 = Utf8               (Ljava/lang/Throwable;)Lscala/concurrent/Future;
  #121 = NameAndType        #119:#120     // failed:(Ljava/lang/Throwable;)Lscala/concurrent/Future;
  #122 = Methodref          #109.#121     // scala/concurrent/Future$.failed:(Ljava/lang/Throwable;)Lscala/concurrent/Future;
  #123 = Utf8               scala/MatchError
  #124 = Class              #123          // scala/MatchError
  #125 = Utf8               (Ljava/lang/Object;)V
  #126 = NameAndType        #115:#125     // "<init>":(Ljava/lang/Object;)V
  #127 = Methodref          #124.#126     // scala/MatchError."<init>":(Ljava/lang/Object;)V
  #128 = Utf8               errorMessage
  #129 = Utf8               Ljava/lang/String;
  #130 = Utf8               Ljava/lang/Object;
  #131 = Utf8               org/scalactic/Validation
  #132 = Class              #131          // org/scalactic/Validation
  #133 = Utf8               scala/Function1
  #134 = Class              #133          // scala/Function1
  #135 = Utf8               (Lorg/scalactic/FutureSugar;Lscala/concurrent/Future;)V
  #136 = Utf8               (Lscala/concurrent/Future<TT;>;)V
  #137 = Utf8               ()V
  #138 = NameAndType        #115:#137     // "<init>":()V
  #139 = Methodref          #5.#138       // java/lang/Object."<init>":()V
  #140 = Utf8               $deserializeLambda$
  #141 = Utf8               (Ljava/lang/invoke/SerializedLambda;)Ljava/lang/Object;
  #142 = Utf8               scala/runtime/LambdaDeserialize
  #143 = Class              #142          // scala/runtime/LambdaDeserialize
  #144 = Utf8               bootstrap
  #145 = Utf8               (Ljava/lang/invoke/MethodHandles$Lookup;Ljava/lang/String;Ljava/lang/invoke/MethodType;[Ljava/lang/invoke/MethodHandle;)Ljava/lang/invoke/CallSite;
  #146 = NameAndType        #144:#145     // bootstrap:(Ljava/lang/invoke/MethodHandles$Lookup;Ljava/lang/String;Ljava/lang/invoke/MethodType;[Ljava/lang/invoke/MethodHandle;)Ljava/lang/invoke/CallSite;
  #147 = Methodref          #143.#146     // scala/runtime/LambdaDeserialize.bootstrap:(Ljava/lang/invoke/MethodHandles$Lookup;Ljava/lang/String;Ljava/lang/invoke/MethodType;[Ljava/lang/invoke/MethodHandle;)Ljava/lang/invoke/CallSite;
  #148 = MethodHandle       6:#147        // REF_invokeStatic scala/runtime/LambdaDeserialize.bootstrap:(Ljava/lang/invoke/MethodHandles$Lookup;Ljava/lang/String;Ljava/lang/invoke/MethodType;[Ljava/lang/invoke/MethodHandle;)Ljava/lang/invoke/CallSite;
  #149 = Utf8               lambdaDeserialize
  #150 = NameAndType        #149:#141     // lambdaDeserialize:(Ljava/lang/invoke/SerializedLambda;)Ljava/lang/Object;
  #151 = InvokeDynamic      #1:#150       // #1:lambdaDeserialize:(Ljava/lang/invoke/SerializedLambda;)Ljava/lang/Object;
  #152 = Utf8               Signature
  #153 = Utf8               Code
  #154 = Utf8               LineNumberTable
  #155 = Utf8               LocalVariableTable
  #156 = Utf8               MethodParameters
  #157 = Utf8               StackMapTable
  #158 = Utf8               InnerClasses
  #159 = Utf8               SourceFile
  #160 = Utf8               BootstrapMethods
  #161 = Utf8               ScalaInlineInfo
  #162 = Utf8               Scala
{
  private final scala.concurrent.Future<T> theFuture;
    descriptor: Lscala/concurrent/Future;
    flags: (0x0012) ACC_PRIVATE, ACC_FINAL
    Signature: #17                          // Lscala/concurrent/Future<TT;>;

  public final org.scalactic.FutureSugar $outer;
    descriptor: Lorg/scalactic/FutureSugar;
    flags: (0x1011) ACC_PUBLIC, ACC_FINAL, ACC_SYNTHETIC

  public scala.concurrent.Future<T> validating(scala.Function1<T, org.scalactic.Validation<java.lang.String>>, scala.collection.immutable.Seq<scala.Function1<T, org.scalactic.Validation<java.lang.String>>>, scala.concurrent.ExecutionContext);
    descriptor: (Lscala/Function1;Lscala/collection/immutable/Seq;Lscala/concurrent/ExecutionContext;)Lscala/concurrent/Future;
    flags: (0x0001) ACC_PUBLIC
    Code:
      stack=4, locals=4, args_size=4
         0: aload_0
         1: getfield      #27                 // Field theFuture:Lscala/concurrent/Future;
         4: aload_0
         5: aload_1
         6: aload_2
         7: invokedynamic #49,  0             // InvokeDynamic #0:apply:(Lorg/scalactic/FutureSugar$Futureizer;Lscala/Function1;Lscala/collection/immutable/Seq;)Lscala/Function1;
        12: aload_3
        13: invokeinterface #55,  3           // InterfaceMethod scala/concurrent/Future.flatMap:(Lscala/Function1;Lscala/concurrent/ExecutionContext;)Lscala/concurrent/Future;
        18: areturn
      LineNumberTable:
        line 170: 0
      LocalVariableTable:
        Start  Length  Slot  Name   Signature
            0      19     0  this   Lorg/scalactic/FutureSugar$Futureizer;
            0      19     1 first   Lscala/Function1;
            0      19     2  rest   Lscala/collection/immutable/Seq;
            0      19     3 executor   Lscala/concurrent/ExecutionContext;
    Signature: #22                          // (Lscala/Function1<TT;Lorg/scalactic/Validation<Ljava/lang/String;>;>;Lscala/collection/immutable/Seq<Lscala/Function1<TT;Lorg/scalactic/Validation<Ljava/lang/String;>;>;>;Lscala/concurrent/ExecutionContext;)Lscala/concurrent/Future<TT;>;
    MethodParameters:
      Name                           Flags
      first                          final
      rest                           final
      executor                       final

  public org.scalactic.FutureSugar org$scalactic$FutureSugar$Futureizer$$$outer();
    descriptor: ()Lorg/scalactic/FutureSugar;
    flags: (0x1001) ACC_PUBLIC, ACC_SYNTHETIC
    Code:
      stack=1, locals=1, args_size=1
         0: aload_0
         1: getfield      #64                 // Field $outer:Lorg/scalactic/FutureSugar;
         4: areturn
      LineNumberTable:
        line 155: 0
      LocalVariableTable:
        Start  Length  Slot  Name   Signature
            0       5     0  this   Lorg/scalactic/FutureSugar$Futureizer;

  public static final scala.concurrent.Future $anonfun$validating$1(org.scalactic.FutureSugar$Futureizer, scala.Function1, scala.collection.immutable.Seq, java.lang.Object);
    descriptor: (Lorg/scalactic/FutureSugar$Futureizer;Lscala/Function1;Lscala/collection/immutable/Seq;Ljava/lang/Object;)Lscala/concurrent/Future;
    flags: (0x1019) ACC_PUBLIC, ACC_STATIC, ACC_FINAL, ACC_SYNTHETIC
    Code:
      stack=4, locals=9, args_size=4
         0: getstatic     #74                 // Field org/scalactic/TrySugar$.MODULE$:Lorg/scalactic/TrySugar$;
         3: aload_3
         4: aload_1
         5: astore        6
         7: aload_2
         8: invokeinterface #80,  1           // InterfaceMethod scala/collection/immutable/Seq.toList:()Lscala/collection/immutable/List;
        13: aload         6
        15: invokevirtual #86                 // Method scala/collection/immutable/List.$colon$colon:(Ljava/lang/Object;)Lscala/collection/immutable/List;
        18: invokevirtual #90                 // Method org/scalactic/TrySugar$.passOrFirstFail:(Ljava/lang/Object;Lscala/collection/immutable/List;)Lorg/scalactic/Validation;
        21: astore        5
        23: getstatic     #95                 // Field org/scalactic/Pass$.MODULE$:Lorg/scalactic/Pass$;
        26: aload         5
        28: invokevirtual #99                 // Method java/lang/Object.equals:(Ljava/lang/Object;)Z
        31: ifeq          43
        34: aload_0
        35: getfield      #27                 // Field theFuture:Lscala/concurrent/Future;
        38: astore        4
        40: goto          104
        43: goto          46
        46: aload         5
        48: instanceof    #101                // class org/scalactic/Fail
        51: ifeq          91
        54: aload         5
        56: checkcast     #101                // class org/scalactic/Fail
        59: astore        7
        61: aload         7
        63: invokevirtual #105                // Method org/scalactic/Fail.error:()Ljava/lang/Object;
        66: checkcast     #107                // class java/lang/String
        69: astore        8
        71: getstatic     #112                // Field scala/concurrent/Future$.MODULE$:Lscala/concurrent/Future$;
        74: new           #114                // class org/scalactic/exceptions/ValidationFailedException
        77: dup
        78: aload         8
        80: invokespecial #118                // Method org/scalactic/exceptions/ValidationFailedException."<init>":(Ljava/lang/String;)V
        83: invokevirtual #122                // Method scala/concurrent/Future$.failed:(Ljava/lang/Throwable;)Lscala/concurrent/Future;
        86: astore        4
        88: goto          104
        91: goto          94
        94: new           #124                // class scala/MatchError
        97: dup
        98: aload         5
       100: invokespecial #127                // Method scala/MatchError."<init>":(Ljava/lang/Object;)V
       103: athrow
       104: aload         4
       106: areturn
      StackMapTable: number_of_entries = 5
        frame_type = 254 /* append */
          offset_delta = 43
          locals = [ top, class org/scalactic/Validation, class scala/Function1 ]
        frame_type = 2 /* same */
        frame_type = 44 /* same */
        frame_type = 2 /* same */
        frame_type = 255 /* full_frame */
          offset_delta = 9
          locals = [ class org/scalactic/FutureSugar$Futureizer, class scala/Function1, class scala/collection/immutable/Seq, class java/lang/Object, class scala/concurrent/Future, class org/scalactic/Validation, class scala/Function1 ]
          stack = []
      LineNumberTable:
        line 171: 0
        line 172: 23
        line 173: 46
        line 171: 94
      LocalVariableTable:
        Start  Length  Slot  Name   Signature
           71      20     8 errorMessage   Ljava/lang/String;
            0     107     0 $this   Lorg/scalactic/FutureSugar$Futureizer;
            0     107     1 first$1   Lscala/Function1;
            0     107     2 rest$1   Lscala/collection/immutable/Seq;
            0     107     3     o   Ljava/lang/Object;
    MethodParameters:
      Name                           Flags
      $this                          final synthetic
      first$1                        final
      rest$1                         final
      o                              final

  public org.scalactic.FutureSugar$Futureizer(scala.concurrent.Future<T>);
    descriptor: (Lorg/scalactic/FutureSugar;Lscala/concurrent/Future;)V
    flags: (0x0001) ACC_PUBLIC
    Code:
      stack=2, locals=3, args_size=3
         0: aload_0
         1: aload_2
         2: putfield      #27                 // Field theFuture:Lscala/concurrent/Future;
         5: aload_1
         6: ifnonnull     11
         9: aconst_null
        10: athrow
        11: aload_0
        12: aload_1
        13: putfield      #64                 // Field $outer:Lorg/scalactic/FutureSugar;
        16: aload_0
        17: invokespecial #139                // Method java/lang/Object."<init>":()V
        20: return
      StackMapTable: number_of_entries = 1
        frame_type = 11 /* same */
      LineNumberTable:
        line 155: 0
        line 178: 16
        line 155: 20
      LocalVariableTable:
        Start  Length  Slot  Name   Signature
            0      21     0  this   Lorg/scalactic/FutureSugar$Futureizer;
            0      21     1 $outer   Lorg/scalactic/FutureSugar;
            0      21     2 theFuture   Lscala/concurrent/Future;
    Signature: #136                         // (Lscala/concurrent/Future<TT;>;)V
    MethodParameters:
      Name                           Flags
      $outer                         final synthetic
      theFuture                      final

  private static java.lang.Object $deserializeLambda$(java.lang.invoke.SerializedLambda);
    descriptor: (Ljava/lang/invoke/SerializedLambda;)Ljava/lang/Object;
    flags: (0x100a) ACC_PRIVATE, ACC_STATIC, ACC_SYNTHETIC
    Code:
      stack=1, locals=1, args_size=1
         0: aload_0
         1: invokedynamic #151,  0            // InvokeDynamic #1:lambdaDeserialize:(Ljava/lang/invoke/SerializedLambda;)Ljava/lang/Object;
         6: areturn
}
InnerClasses:
  public static final #11= #8 of #10;     // Lookup=class java/lang/invoke/MethodHandles$Lookup of class java/lang/invoke/MethodHandles
  public #14= #2 of #13;                  // Futureizer=class org/scalactic/FutureSugar$Futureizer of class org/scalactic/FutureSugar
Signature: #3                           // <T:Ljava/lang/Object;>Ljava/lang/Object;
SourceFile: "FutureSugar.scala"
BootstrapMethods:
  0: #45 REF_invokeStatic java/lang/invoke/LambdaMetafactory.altMetafactory:(Ljava/lang/invoke/MethodHandles$Lookup;Ljava/lang/String;Ljava/lang/invoke/MethodType;[Ljava/lang/Object;)Ljava/lang/invoke/CallSite;
    Method arguments:
      #29 (Ljava/lang/Object;)Ljava/lang/Object;
      #34 REF_invokeStatic org/scalactic/FutureSugar$Futureizer.$anonfun$validating$1:(Lorg/scalactic/FutureSugar$Futureizer;Lscala/Function1;Lscala/collection/immutable/Seq;Ljava/lang/Object;)Lscala/concurrent/Future;
      #36 (Ljava/lang/Object;)Lscala/concurrent/Future;
      #37 5
      #38 1
      #36 (Ljava/lang/Object;)Lscala/concurrent/Future;
  1: #148 REF_invokeStatic scala/runtime/LambdaDeserialize.bootstrap:(Ljava/lang/invoke/MethodHandles$Lookup;Ljava/lang/String;Ljava/lang/invoke/MethodType;[Ljava/lang/invoke/MethodHandle;)Ljava/lang/invoke/CallSite;
    Method arguments:
      #34 REF_invokeStatic org/scalactic/FutureSugar$Futureizer.$anonfun$validating$1:(Lorg/scalactic/FutureSugar$Futureizer;Lscala/Function1;Lscala/collection/immutable/Seq;Ljava/lang/Object;)Lscala/concurrent/Future;
  ScalaInlineInfo: length = 0x18 (unknown attribute)
   01 00 00 04 00 1E 00 1F 01 00 73 00 87 00 00 3D
   00 3E 00 00 14 00 15 00
  Scala: length = 0x0 (unknown attribute)

