Classfile /Users/mw/Projects/slang-braindump/.jar/jar11/assemble/slang-braindump/assemble/content/org/scalactic/Many.class
  Last modified May 29, 2022; size 7577 bytes
  SHA-256 checksum 5ded9bbb42bfdb59ca4e7faad7575b59d7b67ed95ce848aebb9cf4930be9fe81
  Compiled from "Every.scala"
public final class org.scalactic.Many<T extends java.lang.Object> extends org.scalactic.Every<T>
  minor version: 0
  major version: 52
  flags: (0x0031) ACC_PUBLIC, ACC_FINAL, ACC_SUPER
  this_class: #2                          // org/scalactic/Many
  super_class: #5                         // org/scalactic/Every
  interfaces: 0, fields: 3, methods: 19, attributes: 5
Constant pool:
    #1 = Utf8               org/scalactic/Many
    #2 = Class              #1            // org/scalactic/Many
    #3 = Utf8               <T:Ljava/lang/Object;>Lorg/scalactic/Every<TT;>;
    #4 = Utf8               org/scalactic/Every
    #5 = Class              #4            // org/scalactic/Every
    #6 = Utf8               Every.scala
    #7 = Utf8               Lscala/reflect/ScalaSignature;
    #8 = Utf8               bytes
    #9 = Utf8               \u0006\u0005\u0005]f\u0001B\u000f\u001f\u0005\u000eB\u0001B\u0012\u0001\u0003\u0016\u0004%\ta\u0012\u0005\t\u0011\u0002\u0011\t\u0012)A\u0005S!A\u0011\n\u0001BK\u0002\u0013\u0005q\t\u0003\u0005K\u0001\tE\t\u0015!\u0003*\u0011!Y\u0005A!f\u0001\n\u0003a\u0005\u0002\u0003)\u0001\u0005#\u0005\u000b\u0011B\'\t\u000bE\u0003A\u0011\u0001*\t\u000b]\u0003A\u0011\u0001-\t\u000be\u0003A\u0011\u0001.\t\u000be\u0003A\u0011\u00013\t\u000bQ\u0004A\u0011A;\t\u000bq\u0004A\u0011A?\t\u000f\u00055\u0001\u0001\"\u0011\u0002\u0010!I\u0011\u0011\u0003\u0001\u0002\u0002\u0013\u0005\u00131\u0003\u0005\n\u0003G\u0001\u0011\u0011!C\u0001\u0003KA\u0011\"!\f\u0001\u0003\u0003%\t!a\f\t\u0013\u0005U\u0002!!A\u0005B\u0005]\u0002\"CA!\u0001\u0005\u0005I\u0011AA\"\u0011%\ti\u0005AA\u0001\n\u0003\ny\u0005C\u0005\u0002T\u0001\t\t\u0011\"\u0011\u0002V!I\u0011q\u000b\u0001\u0002\u0002\u0013\u0005\u0013\u0011L\u0004\n\u0003;r\u0012\u0011!E\u0001\u0003?2\u0001\"\b\u0010\u0002\u0002#\u0005\u0011\u0011\r\u0005\u0007#^!\t!a\u001d\t\u0013\u00055q#!A\u0005F\u0005U\u0004\"CA</\u0005\u0005I\u0011QA=\u0011%\tYiFA\u0001\n\u0003\u000bi\tC\u0005\u0002.^\t\t\u0011\"\u0003\u00020\n!Q*\u00198z\u0015\ty\u0002%A\u0005tG\u0006d\u0017m\u0019;jG*\t\u0011%A\u0002pe\u001e\u001c\u0001!\u0006\u0002%WM!\u0001!J\u001c;!\r1s%K\u0007\u0002=%\u0011\u0001F\b\u0002\u0006\u000bZ,\'/\u001f\t\u0003U-b\u0001\u0001\u0002\u0004-\u0001\u0011\u0015\r!\f\u0002\u0002)F\u0011a\u0006\u000e\t\u0003_Ij\u0011\u0001\r\u0006\u0002c\u0005)1oY1mC&\u00111\u0007\r\u0002\b\u001d>$\b.\u001b8h!\tyS\'\u0003\u00027a\t\u0019\u0011I\\=\u0011\u0005=B\u0014BA\u001d1\u0005\u001d\u0001&o\u001c3vGR\u0004\"aO\"\u000f\u0005q\neBA\u001fA\u001b\u0005q$BA #\u0003\u0019a$o\\8u}%\t\u0011\'\u0003\u0002Ca\u00059\u0001/Y2lC\u001e,\u0017B\u0001#F\u00051\u0019VM]5bY&T\u0018M\u00197f\u0015\t\u0011\u0005\'\u0001\u0007gSJ\u001cH/\u00127f[\u0016tG/F\u0001*\u000351\u0017N]:u\u000b2,W.\u001a8uA\u0005i1/Z2p]\u0012,E.Z7f]R\fab]3d_:$W\t\\3nK:$\b%A\u0007pi\",\'/\u00127f[\u0016tGo]\u000b\u0002\u001bB\u0019qFT\u0015\n\u0005=\u0003$A\u0003\u001fsKB,\u0017\r^3e}\u0005qq\u000e\u001e5fe\u0016cW-\\3oiN\u0004\u0013A\u0002\u001fj]&$h\b\u0006\u0003T)V3\u0006c\u0001\u0014\u0001S!)ai\u0002a\u0001S!)\u0011j\u0002a\u0001S!)1j\u0002a\u0001\u001b\u00069\u0011m]#wKJLX#A\u0013\u0002\u0015\u0011\u0002H.^:%a2,8/\u0006\u0002\\=R\u0011A,\u0019\t\u0004M\u0001i\u0006C\u0001\u0016_\t\u0015y\u0016B1\u0001a\u0005\u0005)\u0016CA\u00155\u0011\u0015\u0011\u0017\u00021\u0001d\u0003\u0015yG\u000f[3s!\r1s%X\u000b\u0003K\"$\"AZ5\u0011\u0007\u0019:s\r\u0005\u0002+Q\u0012)qL\u0003b\u0001A\")!M\u0003a\u0001UB\u00191.]4\u000f\u00051|gB\u0001\u001fn\u0013\tq\u0007\'\u0001\u0006d_2dWm\u0019;j_:L!A\u00119\u000b\u00059\u0004\u0014B\u0001:t\u0005I9UM\u001c+sCZ,\'o]1cY\u0016|enY3\u000b\u0005\t\u0003\u0018a\u0003\u0013d_2|g\u000e\n9mkN,\"A^=\u0015\u0005]T\bc\u0001\u0014\u0001qB\u0011!&\u001f\u0003\u0006?.\u0011\r\u0001\u0019\u0005\u0006w.\u0001\r\u0001_\u0001\bK2,W.\u001a8u\u00031\u0019HO]5oOB\u0013XMZ5y+\u0005q\bcA@\u0002\b9!\u0011\u0011AA\u0002!\ti\u0004\'C\u0002\u0002\u0006A\na\u0001\u0015:fI\u00164\u0017\u0002BA\u0005\u0003\u0017\u0011aa\u0015;sS:<\'bAA\u0003a\u0005AAo\\*ue&tw\rF\u0001\u007f\u00035\u0001(o\u001c3vGR\u0004&/\u001a4jqV\u0011\u0011Q\u0003\t\u0005\u0003/\t\t#\u0004\u0002\u0002\u001a)!\u00111DA\u000f\u0003\u0011a\u0017M\\4\u000b\u0005\u0005}\u0011\u0001\u00026bm\u0006LA!!\u0003\u0002\u001a\u0005a\u0001O]8ek\u000e$\u0018I]5usV\u0011\u0011q\u0005\t\u0004_\u0005%\u0012bAA\u0016a\t\u0019\u0011J\u001c;\u0002\u001dA\u0014x\u000eZ;di\u0016cW-\\3oiR\u0019A\'!\r\t\u0013\u0005M\u0002#!AA\u0002\u0005\u001d\u0012a\u0001=%c\u0005y\u0001O]8ek\u000e$\u0018\n^3sCR|\'/\u0006\u0002\u0002:A)\u00111HA\u001fi5\t\u0001/C\u0002\u0002@A\u0014\u0001\"\u0013;fe\u0006$xN]\u0001\tG\u0006tW)];bYR!\u0011QIA&!\ry\u0013qI\u0005\u0004\u0003\u0013\u0002$a\u0002\"p_2,\u0017M\u001c\u0005\t\u0003g\u0011\u0012\u0011!a\u0001i\u0005\u0011\u0002O]8ek\u000e$X\t\\3nK:$h*Y7f)\u0011\t)\"!\u0015\t\u0013\u0005M2#!AA\u0002\u0005\u001d\u0012\u0001\u00035bg\"\u001cu\u000eZ3\u0015\u0005\u0005\u001d\u0012AB3rk\u0006d7\u000f\u0006\u0003\u0002F\u0005m\u0003\u0002CA\u001a+\u0005\u0005\t\u0019\u0001\u001b\u0002\t5\u000bg.\u001f\t\u0003M]\u0019RaFA2\u0003S\u00022aLA3\u0013\r\t9\u0007\r\u0002\u0007\u0003:L(+\u001a4\u0011\t\u0005-\u0014\u0011O\u0007\u0003\u0003[RA!a\u001c\u0002\u001e\u0005\u0011\u0011n\\\u0005\u0004\t\u00065DCAA0)\t\t)\"A\u0003baBd\u00170\u0006\u0003\u0002|\u0005\u0005E\u0003CA?\u0003\u0007\u000b))a\"\u0011\t\u0019\u0002\u0011q\u0010\t\u0004U\u0005\u0005E!\u0002\u0017\u001b\u0005\u0004i\u0003B\u0002$\u001b\u0001\u0004\ty\b\u0003\u0004J5\u0001\u0007\u0011q\u0010\u0005\u0007\u0017j\u0001\r!!#\u0011\t=r\u0015qP\u0001\u000bk:\f\u0007\u000f\u001d7z\'\u0016\fX\u0003BAH\u0003?#B!!%\u0002(B)q&a%\u0002\u0018&\u0019\u0011Q\u0013\u0019\u0003\r=\u0003H/[8o!%y\u0013\u0011TAO\u0003;\u000b\t+C\u0002\u0002\u001cB\u0012a\u0001V;qY\u0016\u001c\u0004c\u0001\u0016\u0002 \u0012)Af\u0007b\u0001[A)1(a)\u0002\u001e&\u0019\u0011QU#\u0003\u0007M+\u0017\u000fC\u0005\u0002*n\t\t\u00111\u0001\u0002,\u0006\u0019\u0001\u0010\n\u0019\u0011\t\u0019\u0002\u0011QT\u0001\roJLG/\u001a*fa2\f7-\u001a\u000b\u0003\u0003c\u0003B!a\u0006\u00024&!\u0011QWA\r\u0005\u0019y%M[3di\u0002
   #10 = Utf8               firstElement
   #11 = Utf8               Ljava/lang/Object;
   #12 = Utf8               TT;
   #13 = Utf8               secondElement
   #14 = Utf8               otherElements
   #15 = Utf8               Lscala/collection/immutable/Seq;
   #16 = Utf8               Lscala/collection/immutable/Seq<TT;>;
   #17 = Utf8               unapplySeq
   #18 = Utf8               (Lorg/scalactic/Many;)Lscala/Option;
   #19 = Utf8               <T:Ljava/lang/Object;>(Lorg/scalactic/Many<TT;>;)Lscala/Option<Lscala/Tuple3<TT;TT;Lscala/collection/immutable/Seq<TT;>;>;>;
   #20 = Utf8               x$0
   #21 = Utf8               org/scalactic/Many$
   #22 = Class              #21           // org/scalactic/Many$
   #23 = Utf8               MODULE$
   #24 = Utf8               Lorg/scalactic/Many$;
   #25 = NameAndType        #23:#24       // MODULE$:Lorg/scalactic/Many$;
   #26 = Fieldref           #22.#25       // org/scalactic/Many$.MODULE$:Lorg/scalactic/Many$;
   #27 = NameAndType        #17:#18       // unapplySeq:(Lorg/scalactic/Many;)Lscala/Option;
   #28 = Methodref          #22.#27       // org/scalactic/Many$.unapplySeq:(Lorg/scalactic/Many;)Lscala/Option;
   #29 = Utf8               Lorg/scalactic/Many;
   #30 = Utf8               ()Ljava/lang/Object;
   #31 = Utf8               ()TT;
   #32 = NameAndType        #10:#11       // firstElement:Ljava/lang/Object;
   #33 = Fieldref           #2.#32        // org/scalactic/Many.firstElement:Ljava/lang/Object;
   #34 = Utf8               this
   #35 = NameAndType        #13:#11       // secondElement:Ljava/lang/Object;
   #36 = Fieldref           #2.#35        // org/scalactic/Many.secondElement:Ljava/lang/Object;
   #37 = Utf8               ()Lscala/collection/immutable/Seq;
   #38 = Utf8               ()Lscala/collection/immutable/Seq<TT;>;
   #39 = NameAndType        #14:#15       // otherElements:Lscala/collection/immutable/Seq;
   #40 = Fieldref           #2.#39        // org/scalactic/Many.otherElements:Lscala/collection/immutable/Seq;
   #41 = Utf8               asEvery
   #42 = Utf8               ()Lorg/scalactic/Every;
   #43 = Utf8               ()Lorg/scalactic/Every<TT;>;
   #44 = Utf8               $plus$plus
   #45 = Utf8               (Lorg/scalactic/Every;)Lorg/scalactic/Many;
   #46 = Utf8               <U:Ljava/lang/Object;>(Lorg/scalactic/Every<TU;>;)Lorg/scalactic/Many<TU;>;
   #47 = Utf8               other
   #48 = NameAndType        #10:#30       // firstElement:()Ljava/lang/Object;
   #49 = Methodref          #2.#48        // org/scalactic/Many.firstElement:()Ljava/lang/Object;
   #50 = NameAndType        #13:#30       // secondElement:()Ljava/lang/Object;
   #51 = Methodref          #2.#50        // org/scalactic/Many.secondElement:()Ljava/lang/Object;
   #52 = NameAndType        #14:#37       // otherElements:()Lscala/collection/immutable/Seq;
   #53 = Methodref          #2.#52        // org/scalactic/Many.otherElements:()Lscala/collection/immutable/Seq;
   #54 = Utf8               scala/collection/immutable/Seq
   #55 = Class              #54           // scala/collection/immutable/Seq
   #56 = Utf8               toVector
   #57 = Utf8               ()Lscala/collection/immutable/Vector;
   #58 = NameAndType        #56:#57       // toVector:()Lscala/collection/immutable/Vector;
   #59 = InterfaceMethodref #55.#58       // scala/collection/immutable/Seq.toVector:()Lscala/collection/immutable/Vector;
   #60 = Methodref          #5.#58        // org/scalactic/Every.toVector:()Lscala/collection/immutable/Vector;
   #61 = Utf8               scala/collection/immutable/Vector
   #62 = Class              #61           // scala/collection/immutable/Vector
   #63 = Utf8               (Lscala/collection/IterableOnce;)Ljava/lang/Object;
   #64 = NameAndType        #44:#63       // $plus$plus:(Lscala/collection/IterableOnce;)Ljava/lang/Object;
   #65 = Methodref          #62.#64       // scala/collection/immutable/Vector.$plus$plus:(Lscala/collection/IterableOnce;)Ljava/lang/Object;
   #66 = Utf8               <init>
   #67 = Utf8               (Ljava/lang/Object;Ljava/lang/Object;Lscala/collection/immutable/Seq;)V
   #68 = NameAndType        #66:#67       // "<init>":(Ljava/lang/Object;Ljava/lang/Object;Lscala/collection/immutable/Seq;)V
   #69 = Methodref          #2.#68        // org/scalactic/Many."<init>":(Ljava/lang/Object;Ljava/lang/Object;Lscala/collection/immutable/Seq;)V
   #70 = Utf8               Lorg/scalactic/Every;
   #71 = Utf8               (Lscala/collection/IterableOnce;)Lorg/scalactic/Every;
   #72 = Utf8               <U:Ljava/lang/Object;>(Lscala/collection/IterableOnce<TU;>;)Lorg/scalactic/Every<TU;>;
   #73 = Utf8               scala/collection/IterableOnceExtensionMethods$
   #74 = Class              #73           // scala/collection/IterableOnceExtensionMethods$
   #75 = Utf8               Lscala/collection/IterableOnceExtensionMethods$;
   #76 = NameAndType        #23:#75       // MODULE$:Lscala/collection/IterableOnceExtensionMethods$;
   #77 = Fieldref           #74.#76       // scala/collection/IterableOnceExtensionMethods$.MODULE$:Lscala/collection/IterableOnceExtensionMethods$;
   #78 = Utf8               scala/collection/IterableOnce$
   #79 = Class              #78           // scala/collection/IterableOnce$
   #80 = Utf8               Lscala/collection/IterableOnce$;
   #81 = NameAndType        #23:#80       // MODULE$:Lscala/collection/IterableOnce$;
   #82 = Fieldref           #79.#81       // scala/collection/IterableOnce$.MODULE$:Lscala/collection/IterableOnce$;
   #83 = Utf8               iterableOnceExtensionMethods
   #84 = Utf8               (Lscala/collection/IterableOnce;)Lscala/collection/IterableOnce;
   #85 = NameAndType        #83:#84       // iterableOnceExtensionMethods:(Lscala/collection/IterableOnce;)Lscala/collection/IterableOnce;
   #86 = Methodref          #79.#85       // scala/collection/IterableOnce$.iterableOnceExtensionMethods:(Lscala/collection/IterableOnce;)Lscala/collection/IterableOnce;
   #87 = Utf8               isEmpty$extension
   #88 = Utf8               (Lscala/collection/IterableOnce;)Z
   #89 = NameAndType        #87:#88       // isEmpty$extension:(Lscala/collection/IterableOnce;)Z
   #90 = Methodref          #74.#89       // scala/collection/IterableOnceExtensionMethods$.isEmpty$extension:(Lscala/collection/IterableOnce;)Z
   #91 = Utf8               toVector$extension
   #92 = Utf8               (Lscala/collection/IterableOnce;)Lscala/collection/immutable/Vector;
   #93 = NameAndType        #91:#92       // toVector$extension:(Lscala/collection/IterableOnce;)Lscala/collection/immutable/Vector;
   #94 = Methodref          #74.#93       // scala/collection/IterableOnceExtensionMethods$.toVector$extension:(Lscala/collection/IterableOnce;)Lscala/collection/immutable/Vector;
   #95 = InterfaceMethodref #55.#64       // scala/collection/immutable/Seq.$plus$plus:(Lscala/collection/IterableOnce;)Ljava/lang/Object;
   #96 = Utf8               Lscala/collection/IterableOnce;
   #97 = Utf8               $colon$plus
   #98 = Utf8               (Ljava/lang/Object;)Lorg/scalactic/Many;
   #99 = Utf8               <U:Ljava/lang/Object;>(TU;)Lorg/scalactic/Many<TU;>;
  #100 = Utf8               element
  #101 = Utf8               (Ljava/lang/Object;)Ljava/lang/Object;
  #102 = NameAndType        #97:#101      // $colon$plus:(Ljava/lang/Object;)Ljava/lang/Object;
  #103 = InterfaceMethodref #55.#102      // scala/collection/immutable/Seq.$colon$plus:(Ljava/lang/Object;)Ljava/lang/Object;
  #104 = Utf8               stringPrefix
  #105 = Utf8               ()Ljava/lang/String;
  #106 = Utf8               Many
  #107 = String             #106          // Many
  #108 = Utf8               toString
  #109 = Utf8               java/lang/StringBuilder
  #110 = Class              #109          // java/lang/StringBuilder
  #111 = Integer            6
  #112 = Utf8               (I)V
  #113 = NameAndType        #66:#112      // "<init>":(I)V
  #114 = Methodref          #110.#113     // java/lang/StringBuilder."<init>":(I)V
  #115 = Utf8               Many(
  #116 = String             #115          // Many(
  #117 = Utf8               append
  #118 = Utf8               (Ljava/lang/String;)Ljava/lang/StringBuilder;
  #119 = NameAndType        #117:#118     // append:(Ljava/lang/String;)Ljava/lang/StringBuilder;
  #120 = Methodref          #110.#119     // java/lang/StringBuilder.append:(Ljava/lang/String;)Ljava/lang/StringBuilder;
  #121 = Methodref          #2.#58        // org/scalactic/Many.toVector:()Lscala/collection/immutable/Vector;
  #122 = Utf8               ,
  #123 = String             #122          // ,
  #124 = Utf8               mkString
  #125 = Utf8               (Ljava/lang/String;)Ljava/lang/String;
  #126 = NameAndType        #124:#125     // mkString:(Ljava/lang/String;)Ljava/lang/String;
  #127 = Methodref          #62.#126      // scala/collection/immutable/Vector.mkString:(Ljava/lang/String;)Ljava/lang/String;
  #128 = Utf8               )
  #129 = String             #128          // )
  #130 = NameAndType        #108:#105     // toString:()Ljava/lang/String;
  #131 = Methodref          #110.#130     // java/lang/StringBuilder.toString:()Ljava/lang/String;
  #132 = Utf8               productPrefix
  #133 = Utf8               productArity
  #134 = Utf8               ()I
  #135 = Utf8               productElement
  #136 = Utf8               (I)Ljava/lang/Object;
  #137 = Utf8               x$1
  #138 = Utf8               scala/runtime/Statics
  #139 = Class              #138          // scala/runtime/Statics
  #140 = Utf8               ioobe
  #141 = NameAndType        #140:#136     // ioobe:(I)Ljava/lang/Object;
  #142 = Methodref          #139.#141     // scala/runtime/Statics.ioobe:(I)Ljava/lang/Object;
  #143 = Utf8               I
  #144 = Utf8               java/lang/Object
  #145 = Class              #144          // java/lang/Object
  #146 = Utf8               productIterator
  #147 = Utf8               ()Lscala/collection/Iterator;
  #148 = Utf8               ()Lscala/collection/Iterator<Ljava/lang/Object;>;
  #149 = Utf8               scala/runtime/ScalaRunTime$
  #150 = Class              #149          // scala/runtime/ScalaRunTime$
  #151 = Utf8               Lscala/runtime/ScalaRunTime$;
  #152 = NameAndType        #23:#151      // MODULE$:Lscala/runtime/ScalaRunTime$;
  #153 = Fieldref           #150.#152     // scala/runtime/ScalaRunTime$.MODULE$:Lscala/runtime/ScalaRunTime$;
  #154 = Utf8               typedProductIterator
  #155 = Utf8               (Lscala/Product;)Lscala/collection/Iterator;
  #156 = NameAndType        #154:#155     // typedProductIterator:(Lscala/Product;)Lscala/collection/Iterator;
  #157 = Methodref          #150.#156     // scala/runtime/ScalaRunTime$.typedProductIterator:(Lscala/Product;)Lscala/collection/Iterator;
  #158 = Utf8               canEqual
  #159 = Utf8               (Ljava/lang/Object;)Z
  #160 = Utf8               productElementName
  #161 = Utf8               (I)Ljava/lang/String;
  #162 = String             #10           // firstElement
  #163 = String             #13           // secondElement
  #164 = String             #14           // otherElements
  #165 = Utf8               java/lang/String
  #166 = Class              #165          // java/lang/String
  #167 = Utf8               hashCode
  #168 = Utf8               _hashCode
  #169 = Utf8               (Lscala/Product;)I
  #170 = NameAndType        #168:#169     // _hashCode:(Lscala/Product;)I
  #171 = Methodref          #150.#170     // scala/runtime/ScalaRunTime$._hashCode:(Lscala/Product;)I
  #172 = Utf8               equals
  #173 = Utf8               scala/runtime/BoxesRunTime
  #174 = Class              #173          // scala/runtime/BoxesRunTime
  #175 = Utf8               (Ljava/lang/Object;Ljava/lang/Object;)Z
  #176 = NameAndType        #172:#175     // equals:(Ljava/lang/Object;Ljava/lang/Object;)Z
  #177 = Methodref          #174.#176     // scala/runtime/BoxesRunTime.equals:(Ljava/lang/Object;Ljava/lang/Object;)Z
  #178 = NameAndType        #172:#159     // equals:(Ljava/lang/Object;)Z
  #179 = Methodref          #145.#178     // java/lang/Object.equals:(Ljava/lang/Object;)Z
  #180 = Utf8               (TT;TT;Lscala/collection/immutable/Seq<TT;>;)V
  #181 = Utf8               scala/package$
  #182 = Class              #181          // scala/package$
  #183 = Utf8               Lscala/package$;
  #184 = NameAndType        #23:#183      // MODULE$:Lscala/package$;
  #185 = Fieldref           #182.#184     // scala/package$.MODULE$:Lscala/package$;
  #186 = Utf8               Vector
  #187 = Utf8               ()Lscala/collection/immutable/Vector$;
  #188 = NameAndType        #186:#187     // Vector:()Lscala/collection/immutable/Vector$;
  #189 = Methodref          #182.#188     // scala/package$.Vector:()Lscala/collection/immutable/Vector$;
  #190 = Utf8               scala/collection/immutable/Vector$
  #191 = Class              #190          // scala/collection/immutable/Vector$
  #192 = Utf8               apply
  #193 = Utf8               (Lscala/collection/immutable/Seq;)Ljava/lang/Object;
  #194 = NameAndType        #192:#193     // apply:(Lscala/collection/immutable/Seq;)Ljava/lang/Object;
  #195 = Methodref          #191.#194     // scala/collection/immutable/Vector$.apply:(Lscala/collection/immutable/Seq;)Ljava/lang/Object;
  #196 = Utf8               scala/collection/SeqOps
  #197 = Class              #196          // scala/collection/SeqOps
  #198 = Utf8               $plus$colon
  #199 = NameAndType        #198:#101     // $plus$colon:(Ljava/lang/Object;)Ljava/lang/Object;
  #200 = InterfaceMethodref #197.#199     // scala/collection/SeqOps.$plus$colon:(Ljava/lang/Object;)Ljava/lang/Object;
  #201 = Utf8               (Lscala/collection/immutable/Vector;)V
  #202 = NameAndType        #66:#201      // "<init>":(Lscala/collection/immutable/Vector;)V
  #203 = Methodref          #5.#202       // org/scalactic/Every."<init>":(Lscala/collection/immutable/Vector;)V
  #204 = Utf8               Signature
  #205 = Utf8               Code
  #206 = Utf8               LocalVariableTable
  #207 = Utf8               MethodParameters
  #208 = Utf8               LineNumberTable
  #209 = Utf8               StackMapTable
  #210 = Utf8               SourceFile
  #211 = Utf8               RuntimeVisibleAnnotations
  #212 = Utf8               ScalaInlineInfo
  #213 = Utf8               ScalaSig
{
  private final T firstElement;
    descriptor: Ljava/lang/Object;
    flags: (0x0012) ACC_PRIVATE, ACC_FINAL
    Signature: #12                          // TT;

  private final T secondElement;
    descriptor: Ljava/lang/Object;
    flags: (0x0012) ACC_PRIVATE, ACC_FINAL
    Signature: #12                          // TT;

  private final scala.collection.immutable.Seq<T> otherElements;
    descriptor: Lscala/collection/immutable/Seq;
    flags: (0x0012) ACC_PRIVATE, ACC_FINAL
    Signature: #16                          // Lscala/collection/immutable/Seq<TT;>;

  public static <T extends java.lang.Object> scala.Option<scala.Tuple3<T, T, scala.collection.immutable.Seq<T>>> unapplySeq(org.scalactic.Many<T>);
    descriptor: (Lorg/scalactic/Many;)Lscala/Option;
    flags: (0x0009) ACC_PUBLIC, ACC_STATIC
    Code:
      stack=2, locals=1, args_size=1
         0: getstatic     #26                 // Field org/scalactic/Many$.MODULE$:Lorg/scalactic/Many$;
         3: aload_0
         4: invokevirtual #28                 // Method org/scalactic/Many$.unapplySeq:(Lorg/scalactic/Many;)Lscala/Option;
         7: areturn
      LocalVariableTable:
        Start  Length  Slot  Name   Signature
            0       8     0   x$0   Lorg/scalactic/Many;
    Signature: #19                          // <T:Ljava/lang/Object;>(Lorg/scalactic/Many<TT;>;)Lscala/Option<Lscala/Tuple3<TT;TT;Lscala/collection/immutable/Seq<TT;>;>;>;
    MethodParameters:
      Name                           Flags
      x$0                            final

  public T firstElement();
    descriptor: ()Ljava/lang/Object;
    flags: (0x0001) ACC_PUBLIC
    Code:
      stack=1, locals=1, args_size=1
         0: aload_0
         1: getfield      #33                 // Field firstElement:Ljava/lang/Object;
         4: areturn
      LineNumberTable:
        line 1604: 0
      LocalVariableTable:
        Start  Length  Slot  Name   Signature
            0       5     0  this   Lorg/scalactic/Many;
    Signature: #31                          // ()TT;

  public T secondElement();
    descriptor: ()Ljava/lang/Object;
    flags: (0x0001) ACC_PUBLIC
    Code:
      stack=1, locals=1, args_size=1
         0: aload_0
         1: getfield      #36                 // Field secondElement:Ljava/lang/Object;
         4: areturn
      LineNumberTable:
        line 1604: 0
      LocalVariableTable:
        Start  Length  Slot  Name   Signature
            0       5     0  this   Lorg/scalactic/Many;
    Signature: #31                          // ()TT;

  public scala.collection.immutable.Seq<T> otherElements();
    descriptor: ()Lscala/collection/immutable/Seq;
    flags: (0x0001) ACC_PUBLIC
    Code:
      stack=1, locals=1, args_size=1
         0: aload_0
         1: getfield      #40                 // Field otherElements:Lscala/collection/immutable/Seq;
         4: areturn
      LineNumberTable:
        line 1604: 0
      LocalVariableTable:
        Start  Length  Slot  Name   Signature
            0       5     0  this   Lorg/scalactic/Many;
    Signature: #38                          // ()Lscala/collection/immutable/Seq<TT;>;

  public org.scalactic.Every<T> asEvery();
    descriptor: ()Lorg/scalactic/Every;
    flags: (0x0001) ACC_PUBLIC
    Code:
      stack=1, locals=1, args_size=1
         0: aload_0
         1: areturn
      LineNumberTable:
        line 1611: 0
      LocalVariableTable:
        Start  Length  Slot  Name   Signature
            0       2     0  this   Lorg/scalactic/Many;
    Signature: #43                          // ()Lorg/scalactic/Every<TT;>;

  public <U extends java.lang.Object> org.scalactic.Many<U> $plus$plus(org.scalactic.Every<U>);
    descriptor: (Lorg/scalactic/Every;)Lorg/scalactic/Many;
    flags: (0x0001) ACC_PUBLIC
    Code:
      stack=6, locals=2, args_size=2
         0: new           #2                  // class org/scalactic/Many
         3: dup
         4: aload_0
         5: invokevirtual #49                 // Method firstElement:()Ljava/lang/Object;
         8: aload_0
         9: invokevirtual #51                 // Method secondElement:()Ljava/lang/Object;
        12: aload_0
        13: invokevirtual #53                 // Method otherElements:()Lscala/collection/immutable/Seq;
        16: invokeinterface #59,  1           // InterfaceMethod scala/collection/immutable/Seq.toVector:()Lscala/collection/immutable/Vector;
        21: aload_1
        22: invokevirtual #60                 // Method org/scalactic/Every.toVector:()Lscala/collection/immutable/Vector;
        25: invokevirtual #65                 // Method scala/collection/immutable/Vector.$plus$plus:(Lscala/collection/IterableOnce;)Ljava/lang/Object;
        28: checkcast     #55                 // class scala/collection/immutable/Seq
        31: invokespecial #69                 // Method "<init>":(Ljava/lang/Object;Ljava/lang/Object;Lscala/collection/immutable/Seq;)V
        34: areturn
      LineNumberTable:
        line 1612: 0
      LocalVariableTable:
        Start  Length  Slot  Name   Signature
            0      35     0  this   Lorg/scalactic/Many;
            0      35     1 other   Lorg/scalactic/Every;
    Signature: #46                          // <U:Ljava/lang/Object;>(Lorg/scalactic/Every<TU;>;)Lorg/scalactic/Many<TU;>;
    MethodParameters:
      Name                           Flags
      other                          final

  public <U extends java.lang.Object> org.scalactic.Every<U> $plus$plus(scala.collection.IterableOnce<U>);
    descriptor: (Lscala/collection/IterableOnce;)Lorg/scalactic/Every;
    flags: (0x0001) ACC_PUBLIC
    Code:
      stack=8, locals=2, args_size=2
         0: getstatic     #77                 // Field scala/collection/IterableOnceExtensionMethods$.MODULE$:Lscala/collection/IterableOnceExtensionMethods$;
         3: getstatic     #82                 // Field scala/collection/IterableOnce$.MODULE$:Lscala/collection/IterableOnce$;
         6: aload_1
         7: invokevirtual #86                 // Method scala/collection/IterableOnce$.iterableOnceExtensionMethods:(Lscala/collection/IterableOnce;)Lscala/collection/IterableOnce;
        10: invokevirtual #90                 // Method scala/collection/IterableOnceExtensionMethods$.isEmpty$extension:(Lscala/collection/IterableOnce;)Z
        13: ifeq          20
        16: aload_0
        17: goto          60
        20: new           #2                  // class org/scalactic/Many
        23: dup
        24: aload_0
        25: invokevirtual #49                 // Method firstElement:()Ljava/lang/Object;
        28: aload_0
        29: invokevirtual #51                 // Method secondElement:()Ljava/lang/Object;
        32: aload_0
        33: invokevirtual #53                 // Method otherElements:()Lscala/collection/immutable/Seq;
        36: getstatic     #77                 // Field scala/collection/IterableOnceExtensionMethods$.MODULE$:Lscala/collection/IterableOnceExtensionMethods$;
        39: getstatic     #82                 // Field scala/collection/IterableOnce$.MODULE$:Lscala/collection/IterableOnce$;
        42: aload_1
        43: invokevirtual #86                 // Method scala/collection/IterableOnce$.iterableOnceExtensionMethods:(Lscala/collection/IterableOnce;)Lscala/collection/IterableOnce;
        46: invokevirtual #94                 // Method scala/collection/IterableOnceExtensionMethods$.toVector$extension:(Lscala/collection/IterableOnce;)Lscala/collection/immutable/Vector;
        49: invokeinterface #95,  2           // InterfaceMethod scala/collection/immutable/Seq.$plus$plus:(Lscala/collection/IterableOnce;)Ljava/lang/Object;
        54: checkcast     #55                 // class scala/collection/immutable/Seq
        57: invokespecial #69                 // Method "<init>":(Ljava/lang/Object;Ljava/lang/Object;Lscala/collection/immutable/Seq;)V
        60: areturn
      StackMapTable: number_of_entries = 2
        frame_type = 20 /* same */
        frame_type = 103 /* same_locals_1_stack_item */
          stack = [ class org/scalactic/Many ]
      LineNumberTable:
        line 1614: 0
      LocalVariableTable:
        Start  Length  Slot  Name   Signature
            0      61     0  this   Lorg/scalactic/Many;
            0      61     1 other   Lscala/collection/IterableOnce;
    Signature: #72                          // <U:Ljava/lang/Object;>(Lscala/collection/IterableOnce<TU;>;)Lorg/scalactic/Every<TU;>;
    MethodParameters:
      Name                           Flags
      other                          final

  public <U extends java.lang.Object> org.scalactic.Many<U> $colon$plus(U);
    descriptor: (Ljava/lang/Object;)Lorg/scalactic/Many;
    flags: (0x0001) ACC_PUBLIC
    Code:
      stack=6, locals=2, args_size=2
         0: new           #2                  // class org/scalactic/Many
         3: dup
         4: aload_0
         5: invokevirtual #49                 // Method firstElement:()Ljava/lang/Object;
         8: aload_0
         9: invokevirtual #51                 // Method secondElement:()Ljava/lang/Object;
        12: aload_0
        13: invokevirtual #53                 // Method otherElements:()Lscala/collection/immutable/Seq;
        16: aload_1
        17: invokeinterface #103,  2          // InterfaceMethod scala/collection/immutable/Seq.$colon$plus:(Ljava/lang/Object;)Ljava/lang/Object;
        22: checkcast     #55                 // class scala/collection/immutable/Seq
        25: invokespecial #69                 // Method "<init>":(Ljava/lang/Object;Ljava/lang/Object;Lscala/collection/immutable/Seq;)V
        28: areturn
      LineNumberTable:
        line 1615: 0
      LocalVariableTable:
        Start  Length  Slot  Name   Signature
            0      29     0  this   Lorg/scalactic/Many;
            0      29     1 element   Ljava/lang/Object;
    Signature: #99                          // <U:Ljava/lang/Object;>(TU;)Lorg/scalactic/Many<TU;>;
    MethodParameters:
      Name                           Flags
      element                        final

  public java.lang.String stringPrefix();
    descriptor: ()Ljava/lang/String;
    flags: (0x0001) ACC_PUBLIC
    Code:
      stack=1, locals=1, args_size=1
         0: ldc           #107                // String Many
         2: areturn
      LineNumberTable:
        line 1622: 0
      LocalVariableTable:
        Start  Length  Slot  Name   Signature
            0       3     0  this   Lorg/scalactic/Many;

  public java.lang.String toString();
    descriptor: ()Ljava/lang/String;
    flags: (0x0001) ACC_PUBLIC
    Code:
      stack=3, locals=1, args_size=1
         0: new           #110                // class java/lang/StringBuilder
         3: dup
         4: ldc           #111                // int 6
         6: invokespecial #114                // Method java/lang/StringBuilder."<init>":(I)V
         9: ldc           #116                // String Many(
        11: invokevirtual #120                // Method java/lang/StringBuilder.append:(Ljava/lang/String;)Ljava/lang/StringBuilder;
        14: aload_0
        15: invokevirtual #121                // Method toVector:()Lscala/collection/immutable/Vector;
        18: ldc           #123                // String ,
        20: invokevirtual #127                // Method scala/collection/immutable/Vector.mkString:(Ljava/lang/String;)Ljava/lang/String;
        23: invokevirtual #120                // Method java/lang/StringBuilder.append:(Ljava/lang/String;)Ljava/lang/StringBuilder;
        26: ldc           #129                // String )
        28: invokevirtual #120                // Method java/lang/StringBuilder.append:(Ljava/lang/String;)Ljava/lang/StringBuilder;
        31: invokevirtual #131                // Method java/lang/StringBuilder.toString:()Ljava/lang/String;
        34: areturn
      LineNumberTable:
        line 1630: 0
      LocalVariableTable:
        Start  Length  Slot  Name   Signature
            0      35     0  this   Lorg/scalactic/Many;

  public java.lang.String productPrefix();
    descriptor: ()Ljava/lang/String;
    flags: (0x0001) ACC_PUBLIC
    Code:
      stack=1, locals=1, args_size=1
         0: ldc           #107                // String Many
         2: areturn
      LineNumberTable:
        line 1604: 0
      LocalVariableTable:
        Start  Length  Slot  Name   Signature
            0       3     0  this   Lorg/scalactic/Many;

  public int productArity();
    descriptor: ()I
    flags: (0x0001) ACC_PUBLIC
    Code:
      stack=1, locals=1, args_size=1
         0: iconst_3
         1: ireturn
      LineNumberTable:
        line 1604: 0
      LocalVariableTable:
        Start  Length  Slot  Name   Signature
            0       2     0  this   Lorg/scalactic/Many;

  public java.lang.Object productElement(int);
    descriptor: (I)Ljava/lang/Object;
    flags: (0x0001) ACC_PUBLIC
    Code:
      stack=1, locals=3, args_size=2
         0: iload_1
         1: istore_2
         2: iload_2
         3: tableswitch   { // 0 to 2
                       0: 28
                       1: 35
                       2: 42
                 default: 49
            }
        28: aload_0
        29: invokevirtual #49                 // Method firstElement:()Ljava/lang/Object;
        32: goto          56
        35: aload_0
        36: invokevirtual #51                 // Method secondElement:()Ljava/lang/Object;
        39: goto          56
        42: aload_0
        43: invokevirtual #53                 // Method otherElements:()Lscala/collection/immutable/Seq;
        46: goto          56
        49: iload_1
        50: invokestatic  #142                // Method scala/runtime/Statics.ioobe:(I)Ljava/lang/Object;
        53: goto          56
        56: areturn
      StackMapTable: number_of_entries = 5
        frame_type = 252 /* append */
          offset_delta = 28
          locals = [ int ]
        frame_type = 6 /* same */
        frame_type = 6 /* same */
        frame_type = 6 /* same */
        frame_type = 70 /* same_locals_1_stack_item */
          stack = [ class java/lang/Object ]
      LineNumberTable:
        line 1604: 0
      LocalVariableTable:
        Start  Length  Slot  Name   Signature
            0      57     0  this   Lorg/scalactic/Many;
            0      57     1   x$1   I
    MethodParameters:
      Name                           Flags
      x$1                            final

  public scala.collection.Iterator<java.lang.Object> productIterator();
    descriptor: ()Lscala/collection/Iterator;
    flags: (0x0001) ACC_PUBLIC
    Code:
      stack=2, locals=1, args_size=1
         0: getstatic     #153                // Field scala/runtime/ScalaRunTime$.MODULE$:Lscala/runtime/ScalaRunTime$;
         3: aload_0
         4: invokevirtual #157                // Method scala/runtime/ScalaRunTime$.typedProductIterator:(Lscala/Product;)Lscala/collection/Iterator;
         7: areturn
      LineNumberTable:
        line 1604: 0
      LocalVariableTable:
        Start  Length  Slot  Name   Signature
            0       8     0  this   Lorg/scalactic/Many;
    Signature: #148                         // ()Lscala/collection/Iterator<Ljava/lang/Object;>;

  public boolean canEqual(java.lang.Object);
    descriptor: (Ljava/lang/Object;)Z
    flags: (0x0001) ACC_PUBLIC
    Code:
      stack=1, locals=2, args_size=2
         0: aload_1
         1: instanceof    #2                  // class org/scalactic/Many
         4: ireturn
      LineNumberTable:
        line 1604: 0
      LocalVariableTable:
        Start  Length  Slot  Name   Signature
            0       5     0  this   Lorg/scalactic/Many;
            0       5     1   x$1   Ljava/lang/Object;
    MethodParameters:
      Name                           Flags
      x$1                            final

  public java.lang.String productElementName(int);
    descriptor: (I)Ljava/lang/String;
    flags: (0x0001) ACC_PUBLIC
    Code:
      stack=1, locals=3, args_size=2
         0: iload_1
         1: istore_2
         2: iload_2
         3: tableswitch   { // 0 to 2
                       0: 28
                       1: 33
                       2: 38
                 default: 43
            }
        28: ldc           #162                // String firstElement
        30: goto          53
        33: ldc           #163                // String secondElement
        35: goto          53
        38: ldc           #164                // String otherElements
        40: goto          53
        43: iload_1
        44: invokestatic  #142                // Method scala/runtime/Statics.ioobe:(I)Ljava/lang/Object;
        47: checkcast     #166                // class java/lang/String
        50: goto          53
        53: areturn
      StackMapTable: number_of_entries = 5
        frame_type = 252 /* append */
          offset_delta = 28
          locals = [ int ]
        frame_type = 4 /* same */
        frame_type = 4 /* same */
        frame_type = 4 /* same */
        frame_type = 73 /* same_locals_1_stack_item */
          stack = [ class java/lang/String ]
      LineNumberTable:
        line 1604: 0
      LocalVariableTable:
        Start  Length  Slot  Name   Signature
            0      54     0  this   Lorg/scalactic/Many;
            0      54     1   x$1   I
    MethodParameters:
      Name                           Flags
      x$1                            final

  public int hashCode();
    descriptor: ()I
    flags: (0x0001) ACC_PUBLIC
    Code:
      stack=2, locals=1, args_size=1
         0: getstatic     #153                // Field scala/runtime/ScalaRunTime$.MODULE$:Lscala/runtime/ScalaRunTime$;
         3: aload_0
         4: invokevirtual #171                // Method scala/runtime/ScalaRunTime$._hashCode:(Lscala/Product;)I
         7: ireturn
      LineNumberTable:
        line 1604: 0
      LocalVariableTable:
        Start  Length  Slot  Name   Signature
            0       8     0  this   Lorg/scalactic/Many;

  public boolean equals(java.lang.Object);
    descriptor: (Ljava/lang/Object;)Z
    flags: (0x0001) ACC_PUBLIC
    Code:
      stack=2, locals=6, args_size=2
         0: aload_0
         1: aload_1
         2: if_acmpeq     107
         5: aload_1
         6: astore_3
         7: aload_3
         8: instanceof    #2                  // class org/scalactic/Many
        11: ifeq          19
        14: iconst_1
        15: istore_2
        16: goto          27
        19: goto          22
        22: iconst_0
        23: istore_2
        24: goto          27
        27: iload_2
        28: ifeq          111
        31: aload_1
        32: checkcast     #2                  // class org/scalactic/Many
        35: astore        4
        37: aload_0
        38: invokevirtual #49                 // Method firstElement:()Ljava/lang/Object;
        41: aload         4
        43: invokevirtual #49                 // Method firstElement:()Ljava/lang/Object;
        46: invokestatic  #177                // Method scala/runtime/BoxesRunTime.equals:(Ljava/lang/Object;Ljava/lang/Object;)Z
        49: ifeq          103
        52: aload_0
        53: invokevirtual #51                 // Method secondElement:()Ljava/lang/Object;
        56: aload         4
        58: invokevirtual #51                 // Method secondElement:()Ljava/lang/Object;
        61: invokestatic  #177                // Method scala/runtime/BoxesRunTime.equals:(Ljava/lang/Object;Ljava/lang/Object;)Z
        64: ifeq          103
        67: aload_0
        68: invokevirtual #53                 // Method otherElements:()Lscala/collection/immutable/Seq;
        71: aload         4
        73: invokevirtual #53                 // Method otherElements:()Lscala/collection/immutable/Seq;
        76: astore        5
        78: dup
        79: ifnonnull     91
        82: pop
        83: aload         5
        85: ifnull        99
        88: goto          103
        91: aload         5
        93: invokevirtual #179                // Method java/lang/Object.equals:(Ljava/lang/Object;)Z
        96: ifeq          103
        99: iconst_1
       100: goto          104
       103: iconst_0
       104: ifeq          111
       107: iconst_1
       108: goto          112
       111: iconst_0
       112: ireturn
      StackMapTable: number_of_entries = 10
        frame_type = 253 /* append */
          offset_delta = 19
          locals = [ top, class java/lang/Object ]
        frame_type = 2 /* same */
        frame_type = 255 /* full_frame */
          offset_delta = 4
          locals = [ class org/scalactic/Many, class java/lang/Object, int, class java/lang/Object ]
          stack = []
        frame_type = 255 /* full_frame */
          offset_delta = 63
          locals = [ class org/scalactic/Many, class java/lang/Object, int, class java/lang/Object, class org/scalactic/Many, class scala/collection/immutable/Seq ]
          stack = [ class scala/collection/immutable/Seq ]
        frame_type = 7 /* same */
        frame_type = 250 /* chop */
          offset_delta = 3
        frame_type = 64 /* same_locals_1_stack_item */
          stack = [ int ]
        frame_type = 248 /* chop */
          offset_delta = 2
        frame_type = 253 /* append */
          offset_delta = 3
          locals = [ int, class java/lang/Object ]
        frame_type = 255 /* full_frame */
          offset_delta = 0
          locals = [ class org/scalactic/Many, class java/lang/Object ]
          stack = [ int ]
      LineNumberTable:
        line 1604: 0
      LocalVariableTable:
        Start  Length  Slot  Name   Signature
            0     113     0  this   Lorg/scalactic/Many;
            0     113     1   x$1   Ljava/lang/Object;
    MethodParameters:
      Name                           Flags
      x$1                            final

  public org.scalactic.Many(T, T, scala.collection.immutable.Seq<T>);
    descriptor: (Ljava/lang/Object;Ljava/lang/Object;Lscala/collection/immutable/Seq;)V
    flags: (0x0001) ACC_PUBLIC
    Code:
      stack=3, locals=6, args_size=4
         0: aload_0
         1: aload_1
         2: putfield      #33                 // Field firstElement:Ljava/lang/Object;
         5: aload_0
         6: aload_2
         7: putfield      #36                 // Field secondElement:Ljava/lang/Object;
        10: aload_0
        11: aload_3
        12: putfield      #40                 // Field otherElements:Lscala/collection/immutable/Seq;
        15: aload_0
        16: aload_1
        17: astore        4
        19: aload_2
        20: astore        5
        22: getstatic     #185                // Field scala/package$.MODULE$:Lscala/package$;
        25: invokevirtual #189                // Method scala/package$.Vector:()Lscala/collection/immutable/Vector$;
        28: aload_3
        29: invokevirtual #195                // Method scala/collection/immutable/Vector$.apply:(Lscala/collection/immutable/Seq;)Ljava/lang/Object;
        32: checkcast     #197                // class scala/collection/SeqOps
        35: aload         5
        37: invokeinterface #200,  2          // InterfaceMethod scala/collection/SeqOps.$plus$colon:(Ljava/lang/Object;)Ljava/lang/Object;
        42: checkcast     #197                // class scala/collection/SeqOps
        45: aload         4
        47: invokeinterface #200,  2          // InterfaceMethod scala/collection/SeqOps.$plus$colon:(Ljava/lang/Object;)Ljava/lang/Object;
        52: checkcast     #62                 // class scala/collection/immutable/Vector
        55: invokespecial #203                // Method org/scalactic/Every."<init>":(Lscala/collection/immutable/Vector;)V
        58: return
      LineNumberTable:
        line 1604: 0
      LocalVariableTable:
        Start  Length  Slot  Name   Signature
            0      59     0  this   Lorg/scalactic/Many;
            0      59     1 firstElement   Ljava/lang/Object;
            0      59     2 secondElement   Ljava/lang/Object;
            0      59     3 otherElements   Lscala/collection/immutable/Seq;
    Signature: #180                         // (TT;TT;Lscala/collection/immutable/Seq<TT;>;)V
    MethodParameters:
      Name                           Flags
      firstElement                   final
      secondElement                  final
      otherElements                  final
}
Signature: #3                           // <T:Ljava/lang/Object;>Lorg/scalactic/Every<TT;>;
SourceFile: "Every.scala"
RuntimeVisibleAnnotations:
  0: #7(#8=s#9)
    scala.reflect.ScalaSignature(
      bytes="\u0006\u0005\u0005]f\u0001B\u000f\u001f\u0005\u000eB\u0001B\u0012\u0001\u0003\u0016\u0004%\ta\u0012\u0005\t\u0011\u0002\u0011\t\u0012)A\u0005S!A\u0011\n\u0001BK\u0002\u0013\u0005q\t\u0003\u0005K\u0001\tE\t\u0015!\u0003*\u0011!Y\u0005A!f\u0001\n\u0003a\u0005\u0002\u0003)\u0001\u0005#\u0005\u000b\u0011B\'\t\u000bE\u0003A\u0011\u0001*\t\u000b]\u0003A\u0011\u0001-\t\u000be\u0003A\u0011\u0001.\t\u000be\u0003A\u0011\u00013\t\u000bQ\u0004A\u0011A;\t\u000bq\u0004A\u0011A?\t\u000f\u00055\u0001\u0001\"\u0011\u0002\u0010!I\u0011\u0011\u0003\u0001\u0002\u0002\u0013\u0005\u00131\u0003\u0005\n\u0003G\u0001\u0011\u0011!C\u0001\u0003KA\u0011\"!\f\u0001\u0003\u0003%\t!a\f\t\u0013\u0005U\u0002!!A\u0005B\u0005]\u0002\"CA!\u0001\u0005\u0005I\u0011AA\"\u0011%\ti\u0005AA\u0001\n\u0003\ny\u0005C\u0005\u0002T\u0001\t\t\u0011\"\u0011\u0002V!I\u0011q\u000b\u0001\u0002\u0002\u0013\u0005\u0013\u0011L\u0004\n\u0003;r\u0012\u0011!E\u0001\u0003?2\u0001\"\b\u0010\u0002\u0002#\u0005\u0011\u0011\r\u0005\u0007#^!\t!a\u001d\t\u0013\u00055q#!A\u0005F\u0005U\u0004\"CA</\u0005\u0005I\u0011QA=\u0011%\tYiFA\u0001\n\u0003\u000bi\tC\u0005\u0002.^\t\t\u0011\"\u0003\u00020\n!Q*\u00198z\u0015\ty\u0002%A\u0005tG\u0006d\u0017m\u0019;jG*\t\u0011%A\u0002pe\u001e\u001c\u0001!\u0006\u0002%WM!\u0001!J\u001c;!\r1s%K\u0007\u0002=%\u0011\u0001F\b\u0002\u0006\u000bZ,\'/\u001f\t\u0003U-b\u0001\u0001\u0002\u0004-\u0001\u0011\u0015\r!\f\u0002\u0002)F\u0011a\u0006\u000e\t\u0003_Ij\u0011\u0001\r\u0006\u0002c\u0005)1oY1mC&\u00111\u0007\r\u0002\b\u001d>$\b.\u001b8h!\tyS\'\u0003\u00027a\t\u0019\u0011I\\=\u0011\u0005=B\u0014BA\u001d1\u0005\u001d\u0001&o\u001c3vGR\u0004\"aO\"\u000f\u0005q\neBA\u001fA\u001b\u0005q$BA #\u0003\u0019a$o\\8u}%\t\u0011\'\u0003\u0002Ca\u00059\u0001/Y2lC\u001e,\u0017B\u0001#F\u00051\u0019VM]5bY&T\u0018M\u00197f\u0015\t\u0011\u0005\'\u0001\u0007gSJ\u001cH/\u00127f[\u0016tG/F\u0001*\u000351\u0017N]:u\u000b2,W.\u001a8uA\u0005i1/Z2p]\u0012,E.Z7f]R\fab]3d_:$W\t\\3nK:$\b%A\u0007pi\",\'/\u00127f[\u0016tGo]\u000b\u0002\u001bB\u0019qFT\u0015\n\u0005=\u0003$A\u0003\u001fsKB,\u0017\r^3e}\u0005qq\u000e\u001e5fe\u0016cW-\\3oiN\u0004\u0013A\u0002\u001fj]&$h\b\u0006\u0003T)V3\u0006c\u0001\u0014\u0001S!)ai\u0002a\u0001S!)\u0011j\u0002a\u0001S!)1j\u0002a\u0001\u001b\u00069\u0011m]#wKJLX#A\u0013\u0002\u0015\u0011\u0002H.^:%a2,8/\u0006\u0002\\=R\u0011A,\u0019\t\u0004M\u0001i\u0006C\u0001\u0016_\t\u0015y\u0016B1\u0001a\u0005\u0005)\u0016CA\u00155\u0011\u0015\u0011\u0017\u00021\u0001d\u0003\u0015yG\u000f[3s!\r1s%X\u000b\u0003K\"$\"AZ5\u0011\u0007\u0019:s\r\u0005\u0002+Q\u0012)qL\u0003b\u0001A\")!M\u0003a\u0001UB\u00191.]4\u000f\u00051|gB\u0001\u001fn\u0013\tq\u0007\'\u0001\u0006d_2dWm\u0019;j_:L!A\u00119\u000b\u00059\u0004\u0014B\u0001:t\u0005I9UM\u001c+sCZ,\'o]1cY\u0016|enY3\u000b\u0005\t\u0003\u0018a\u0003\u0013d_2|g\u000e\n9mkN,\"A^=\u0015\u0005]T\bc\u0001\u0014\u0001qB\u0011!&\u001f\u0003\u0006?.\u0011\r\u0001\u0019\u0005\u0006w.\u0001\r\u0001_\u0001\bK2,W.\u001a8u\u00031\u0019HO]5oOB\u0013XMZ5y+\u0005q\bcA@\u0002\b9!\u0011\u0011AA\u0002!\ti\u0004\'C\u0002\u0002\u0006A\na\u0001\u0015:fI\u00164\u0017\u0002BA\u0005\u0003\u0017\u0011aa\u0015;sS:<\'bAA\u0003a\u0005AAo\\*ue&tw\rF\u0001\u007f\u00035\u0001(o\u001c3vGR\u0004&/\u001a4jqV\u0011\u0011Q\u0003\t\u0005\u0003/\t\t#\u0004\u0002\u0002\u001a)!\u00111DA\u000f\u0003\u0011a\u0017M\\4\u000b\u0005\u0005}\u0011\u0001\u00026bm\u0006LA!!\u0003\u0002\u001a\u0005a\u0001O]8ek\u000e$\u0018I]5usV\u0011\u0011q\u0005\t\u0004_\u0005%\u0012bAA\u0016a\t\u0019\u0011J\u001c;\u0002\u001dA\u0014x\u000eZ;di\u0016cW-\\3oiR\u0019A\'!\r\t\u0013\u0005M\u0002#!AA\u0002\u0005\u001d\u0012a\u0001=%c\u0005y\u0001O]8ek\u000e$\u0018\n^3sCR|\'/\u0006\u0002\u0002:A)\u00111HA\u001fi5\t\u0001/C\u0002\u0002@A\u0014\u0001\"\u0013;fe\u0006$xN]\u0001\tG\u0006tW)];bYR!\u0011QIA&!\ry\u0013qI\u0005\u0004\u0003\u0013\u0002$a\u0002\"p_2,\u0017M\u001c\u0005\t\u0003g\u0011\u0012\u0011!a\u0001i\u0005\u0011\u0002O]8ek\u000e$X\t\\3nK:$h*Y7f)\u0011\t)\"!\u0015\t\u0013\u0005M2#!AA\u0002\u0005\u001d\u0012\u0001\u00035bg\"\u001cu\u000eZ3\u0015\u0005\u0005\u001d\u0012AB3rk\u0006d7\u000f\u0006\u0003\u0002F\u0005m\u0003\u0002CA\u001a+\u0005\u0005\t\u0019\u0001\u001b\u0002\t5\u000bg.\u001f\t\u0003M]\u0019RaFA2\u0003S\u00022aLA3\u0013\r\t9\u0007\r\u0002\u0007\u0003:L(+\u001a4\u0011\t\u0005-\u0014\u0011O\u0007\u0003\u0003[RA!a\u001c\u0002\u001e\u0005\u0011\u0011n\\\u0005\u0004\t\u00065DCAA0)\t\t)\"A\u0003baBd\u00170\u0006\u0003\u0002|\u0005\u0005E\u0003CA?\u0003\u0007\u000b))a\"\u0011\t\u0019\u0002\u0011q\u0010\t\u0004U\u0005\u0005E!\u0002\u0017\u001b\u0005\u0004i\u0003B\u0002$\u001b\u0001\u0004\ty\b\u0003\u0004J5\u0001\u0007\u0011q\u0010\u0005\u0007\u0017j\u0001\r!!#\u0011\t=r\u0015qP\u0001\u000bk:\f\u0007\u000f\u001d7z\'\u0016\fX\u0003BAH\u0003?#B!!%\u0002(B)q&a%\u0002\u0018&\u0019\u0011Q\u0013\u0019\u0003\r=\u0003H/[8o!%y\u0013\u0011TAO\u0003;\u000b\t+C\u0002\u0002\u001cB\u0012a\u0001V;qY\u0016\u001c\u0004c\u0001\u0016\u0002 \u0012)Af\u0007b\u0001[A)1(a)\u0002\u001e&\u0019\u0011QU#\u0003\u0007M+\u0017\u000fC\u0005\u0002*n\t\t\u00111\u0001\u0002,\u0006\u0019\u0001\u0010\n\u0019\u0011\t\u0019\u0002\u0011QT\u0001\roJLG/\u001a*fa2\f7-\u001a\u000b\u0003\u0003c\u0003B!a\u0006\u00024&!\u0011QWA\r\u0005\u0019y%M[3di\u0002"
    )
  ScalaInlineInfo: length = 0x5E (unknown attribute)
   01 01 00 12 00 61 00 62 01 00 2C 00 2D 01 00 2C
   00 47 01 00 42 00 43 01 00 29 00 2A 01 00 9E 00
   9F 01 00 AC 00 9F 01 00 0A 00 1E 01 00 A7 00 86
   01 00 0E 00 25 01 00 85 00 86 01 00 87 00 88 01
   00 A0 00 A1 01 00 92 00 93 01 00 84 00 69 01 00
   0D 00 1E 01 00 68 00 69 01 00 6C 00 69 01
  ScalaSig: length = 0x3 (unknown attribute)
   05 02 00
