Classfile /Users/mw/Projects/slang-braindump/.jar/jar11/assemble/slang-braindump/assemble/content/org/scalactic/MapEqualityConstraints.class
  Last modified May 29, 2022; size 2425 bytes
  SHA-256 checksum e8c63544358a0d178dbf19ad255d0c547d433ad0e2864a027eefef186b83c1a7
  Compiled from "MapEqualityConstraints.scala"
public interface org.scalactic.MapEqualityConstraints
  minor version: 0
  major version: 52
  flags: (0x0601) ACC_PUBLIC, ACC_INTERFACE, ACC_ABSTRACT
  this_class: #2                          // org/scalactic/MapEqualityConstraints
  super_class: #4                         // java/lang/Object
  interfaces: 0, fields: 0, methods: 3, attributes: 5
Constant pool:
   #1 = Utf8               org/scalactic/MapEqualityConstraints
   #2 = Class              #1             // org/scalactic/MapEqualityConstraints
   #3 = Utf8               java/lang/Object
   #4 = Class              #3             // java/lang/Object
   #5 = Utf8               MapEqualityConstraints.scala
   #6 = Utf8               Lscala/reflect/ScalaSignature;
   #7 = Utf8               bytes
   #8 = Utf8               \u0006\u0005\u00154qAB\u0004\u0011\u0002\u0007\u0005A\u0002C\u0003\u0014\u0001\u0011\u0005A\u0003C\u0003\u0019\u0001\u0011\r\u0011dB\u0003`\u000f!\u0005\u0001MB\u0003\u0007\u000f!\u0005\u0011\rC\u0003d\t\u0011\u0005AM\u0001\fNCB,\u0015/^1mSRL8i\u001c8tiJ\f\u0017N\u001c;t\u0015\tA\u0011\"A\u0005tG\u0006d\u0017m\u0019;jG*\t!\"A\u0002pe\u001e\u001c\u0001a\u0005\u0002\u0001\u001bA\u0011a\"E\u0007\u0002\u001f)\t\u0001#A\u0003tG\u0006d\u0017-\u0003\u0002\u0013\u001f\t1\u0011I\\=SK\u001a\fa\u0001J5oSR$C#A\u000b\u0011\u000591\u0012BA\f\u0010\u0005\u0011)f.\u001b;\u0002+5\f\u0007/R9vC2LG/_\"p]N$(/Y5oiV9!DP!\"\u001fJ#E\u0003B\u000eU3r\u0003B\u0001H\u000f \u00076\tq!\u0003\u0002\u001f\u000f\tA1)\u00198FcV\fG\u000e\u0005\u0003!Cu\u0002E\u0002\u0001\u0003\u0006E\t\u0011\ra\t\u0002\u0003\u0007\u0006+2\u0001\n\u001b<#\t)\u0003\u0006\u0005\u0002\u000fM%\u0011qe\u0004\u0002\b\u001d>$\b.\u001b8h!\u0011I\u0003g\r\u001e\u000f\u0005)jcB\u0001\b,\u0013\tas\"\u0001\u0006d_2dWm\u0019;j_:L!AL\u0018\u0002\u000fA\f7m[1hK*\u0011AfD\u0005\u0003cI\u0012aaR3o\u001b\u0006\u0004(B\u0001\u00180!\t\u0001C\u0007B\u00036C\t\u0007aG\u0001\u0002lCF\u0011Qe\u000e\t\u0003\u001daJ!!O\b\u0003\u0007\u0005s\u0017\u0010\u0005\u0002!w\u0011)A(\tb\u0001m\t\u00111N\u0019\t\u0003Ay\"Qa\u0010\u0002C\u0002Y\u0012!aS!\u0011\u0005\u0001\nE!\u0002\"\u0003\u0005\u00041$A\u0001,B!\u0011\u0001CIT)\u0005\u000b\u0015\u0013!\u0019\u0001$\u0003\u0005\r\u0013UcA$K\u0019F\u0011Q\u0005\u0013\t\u0005SAJ5\n\u0005\u0002!\u0015\u0012)A\b\u0012b\u0001mA\u0011\u0001\u0005\u0014\u0003\u0006\u001b\u0012\u0013\rA\u000e\u0002\u0003m\n\u0004\"\u0001I(\u0005\u000bA\u0013!\u0019\u0001\u001c\u0003\u0005-\u0013\u0005C\u0001\u0011S\t\u0015\u0019&A1\u00017\u0005\t1&\tC\u0003V\u0005\u0001\u000fa+A\u0006fcV\fG.\u001b;z\u001f\u001a\f\u0005c\u0001\u000fX?%\u0011\u0001l\u0002\u0002\t\u000bF,\u0018\r\\5us\")!L\u0001a\u00027\u0006)QM^&fsB!A$H\u001fO\u0011\u0015i&\u0001q\u0001_\u0003\u001d)gOV1mk\u0016\u0004B\u0001H\u000fA#\u00061R*\u00199FcV\fG.\u001b;z\u0007>t7\u000f\u001e:bS:$8\u000f\u0005\u0002\u001d\tM\u0019A!\u00042\u0011\u0005q\u0001\u0011A\u0002\u001fj]&$h\bF\u0001a\u0001
   #9 = Utf8               org/scalactic/TripleEqualsSupport$EqualityConstraint
  #10 = Class              #9             // org/scalactic/TripleEqualsSupport$EqualityConstraint
  #11 = Utf8               org/scalactic/TripleEqualsSupport
  #12 = Class              #11            // org/scalactic/TripleEqualsSupport
  #13 = Utf8               EqualityConstraint
  #14 = Utf8               mapEqualityConstraint$
  #15 = Utf8               (Lorg/scalactic/MapEqualityConstraints;Lorg/scalactic/Equality;Lorg/scalactic/CanEqual;Lorg/scalactic/CanEqual;)Lorg/scalactic/CanEqual;
  #16 = Utf8               $this
  #17 = Utf8               equalityOfA
  #18 = Utf8               evKey
  #19 = Utf8               evValue
  #20 = Utf8               mapEqualityConstraint
  #21 = Utf8               (Lorg/scalactic/Equality;Lorg/scalactic/CanEqual;Lorg/scalactic/CanEqual;)Lorg/scalactic/CanEqual;
  #22 = NameAndType        #20:#21        // mapEqualityConstraint:(Lorg/scalactic/Equality;Lorg/scalactic/CanEqual;Lorg/scalactic/CanEqual;)Lorg/scalactic/CanEqual;
  #23 = InterfaceMethodref #2.#22         // org/scalactic/MapEqualityConstraints.mapEqualityConstraint:(Lorg/scalactic/Equality;Lorg/scalactic/CanEqual;Lorg/scalactic/CanEqual;)Lorg/scalactic/CanEqual;
  #24 = Utf8               Lorg/scalactic/MapEqualityConstraints;
  #25 = Utf8               Lorg/scalactic/Equality;
  #26 = Utf8               Lorg/scalactic/CanEqual;
  #27 = Utf8               <KA:Ljava/lang/Object;VA:Ljava/lang/Object;CA::Lscala/collection/Map<Ljava/lang/Object;Ljava/lang/Object;>;KB:Ljava/lang/Object;VB:Ljava/lang/Object;CB::Lscala/collection/Map<Ljava/lang/Object;Ljava/lang/Object;>;>(Lorg/scalactic/Equality<TCA;>;Lorg/scalactic/CanEqual<TKA;TKB;>;Lorg/scalactic/CanEqual<TVA;TVB;>;)Lorg/scalactic/CanEqual<TCA;TCB;>;
  #28 = Utf8               <init>
  #29 = Utf8               (Lorg/scalactic/Equality;)V
  #30 = NameAndType        #28:#29        // "<init>":(Lorg/scalactic/Equality;)V
  #31 = Methodref          #10.#30        // org/scalactic/TripleEqualsSupport$EqualityConstraint."<init>":(Lorg/scalactic/Equality;)V
  #32 = Utf8               this
  #33 = Utf8               $init$
  #34 = Utf8               (Lorg/scalactic/MapEqualityConstraints;)V
  #35 = Utf8               Code
  #36 = Utf8               LineNumberTable
  #37 = Utf8               LocalVariableTable
  #38 = Utf8               MethodParameters
  #39 = Utf8               Signature
  #40 = Utf8               InnerClasses
  #41 = Utf8               SourceFile
  #42 = Utf8               RuntimeVisibleAnnotations
  #43 = Utf8               ScalaInlineInfo
  #44 = Utf8               ScalaSig
{
  public static org.scalactic.CanEqual mapEqualityConstraint$(org.scalactic.MapEqualityConstraints, org.scalactic.Equality, org.scalactic.CanEqual, org.scalactic.CanEqual);
    descriptor: (Lorg/scalactic/MapEqualityConstraints;Lorg/scalactic/Equality;Lorg/scalactic/CanEqual;Lorg/scalactic/CanEqual;)Lorg/scalactic/CanEqual;
    flags: (0x1009) ACC_PUBLIC, ACC_STATIC, ACC_SYNTHETIC
    Code:
      stack=4, locals=4, args_size=4
         0: aload_0
         1: aload_1
         2: aload_2
         3: aload_3
         4: invokespecial #23                 // InterfaceMethod mapEqualityConstraint:(Lorg/scalactic/Equality;Lorg/scalactic/CanEqual;Lorg/scalactic/CanEqual;)Lorg/scalactic/CanEqual;
         7: areturn
      LineNumberTable:
        line 108: 0
      LocalVariableTable:
        Start  Length  Slot  Name   Signature
            0       8     0 $this   Lorg/scalactic/MapEqualityConstraints;
            0       8     1 equalityOfA   Lorg/scalactic/Equality;
            0       8     2 evKey   Lorg/scalactic/CanEqual;
            0       8     3 evValue   Lorg/scalactic/CanEqual;
    MethodParameters:
      Name                           Flags
      $this                          final synthetic
      equalityOfA                    final
      evKey                          final
      evValue                        final

  public default <KA extends java.lang.Object, VA extends java.lang.Object, CA extends scala.collection.Map<java.lang.Object, java.lang.Object>, KB extends java.lang.Object, VB extends java.lang.Object, CB extends scala.collection.Map<java.lang.Object, java.lang.Object>> org.scalactic.CanEqual<CA, CB> mapEqualityConstraint(org.scalactic.Equality<CA>, org.scalactic.CanEqual<KA, KB>, org.scalactic.CanEqual<VA, VB>);
    descriptor: (Lorg/scalactic/Equality;Lorg/scalactic/CanEqual;Lorg/scalactic/CanEqual;)Lorg/scalactic/CanEqual;
    flags: (0x0001) ACC_PUBLIC
    Code:
      stack=3, locals=4, args_size=4
         0: new           #10                 // class org/scalactic/TripleEqualsSupport$EqualityConstraint
         3: dup
         4: aload_1
         5: invokespecial #31                 // Method org/scalactic/TripleEqualsSupport$EqualityConstraint."<init>":(Lorg/scalactic/Equality;)V
         8: areturn
      LineNumberTable:
        line 108: 0
      LocalVariableTable:
        Start  Length  Slot  Name   Signature
            0       9     0  this   Lorg/scalactic/MapEqualityConstraints;
            0       9     1 equalityOfA   Lorg/scalactic/Equality;
            0       9     2 evKey   Lorg/scalactic/CanEqual;
            0       9     3 evValue   Lorg/scalactic/CanEqual;
    Signature: #27                          // <KA:Ljava/lang/Object;VA:Ljava/lang/Object;CA::Lscala/collection/Map<Ljava/lang/Object;Ljava/lang/Object;>;KB:Ljava/lang/Object;VB:Ljava/lang/Object;CB::Lscala/collection/Map<Ljava/lang/Object;Ljava/lang/Object;>;>(Lorg/scalactic/Equality<TCA;>;Lorg/scalactic/CanEqual<TKA;TKB;>;Lorg/scalactic/CanEqual<TVA;TVB;>;)Lorg/scalactic/CanEqual<TCA;TCB;>;
    MethodParameters:
      Name                           Flags
      equalityOfA                    final
      evKey                          final
      evValue                        final

  public static void $init$(org.scalactic.MapEqualityConstraints);
    descriptor: (Lorg/scalactic/MapEqualityConstraints;)V
    flags: (0x0009) ACC_PUBLIC, ACC_STATIC
    Code:
      stack=0, locals=1, args_size=1
         0: return
      LineNumberTable:
        line 100: 0
      LocalVariableTable:
        Start  Length  Slot  Name   Signature
            0       1     0 $this   Lorg/scalactic/MapEqualityConstraints;
    MethodParameters:
      Name                           Flags
      $this                          final synthetic
}
InnerClasses:
  public static final #13= #10 of #12;    // EqualityConstraint=class org/scalactic/TripleEqualsSupport$EqualityConstraint of class org/scalactic/TripleEqualsSupport
SourceFile: "MapEqualityConstraints.scala"
RuntimeVisibleAnnotations:
  0: #6(#7=s#8)
    scala.reflect.ScalaSignature(
      bytes="\u0006\u0005\u00154qAB\u0004\u0011\u0002\u0007\u0005A\u0002C\u0003\u0014\u0001\u0011\u0005A\u0003C\u0003\u0019\u0001\u0011\r\u0011dB\u0003`\u000f!\u0005\u0001MB\u0003\u0007\u000f!\u0005\u0011\rC\u0003d\t\u0011\u0005AM\u0001\fNCB,\u0015/^1mSRL8i\u001c8tiJ\f\u0017N\u001c;t\u0015\tA\u0011\"A\u0005tG\u0006d\u0017m\u0019;jG*\t!\"A\u0002pe\u001e\u001c\u0001a\u0005\u0002\u0001\u001bA\u0011a\"E\u0007\u0002\u001f)\t\u0001#A\u0003tG\u0006d\u0017-\u0003\u0002\u0013\u001f\t1\u0011I\\=SK\u001a\fa\u0001J5oSR$C#A\u000b\u0011\u000591\u0012BA\f\u0010\u0005\u0011)f.\u001b;\u0002+5\f\u0007/R9vC2LG/_\"p]N$(/Y5oiV9!DP!\"\u001fJ#E\u0003B\u000eU3r\u0003B\u0001H\u000f \u00076\tq!\u0003\u0002\u001f\u000f\tA1)\u00198FcV\fG\u000e\u0005\u0003!Cu\u0002E\u0002\u0001\u0003\u0006E\t\u0011\ra\t\u0002\u0003\u0007\u0006+2\u0001\n\u001b<#\t)\u0003\u0006\u0005\u0002\u000fM%\u0011qe\u0004\u0002\b\u001d>$\b.\u001b8h!\u0011I\u0003g\r\u001e\u000f\u0005)jcB\u0001\b,\u0013\tas\"\u0001\u0006d_2dWm\u0019;j_:L!AL\u0018\u0002\u000fA\f7m[1hK*\u0011AfD\u0005\u0003cI\u0012aaR3o\u001b\u0006\u0004(B\u0001\u00180!\t\u0001C\u0007B\u00036C\t\u0007aG\u0001\u0002lCF\u0011Qe\u000e\t\u0003\u001daJ!!O\b\u0003\u0007\u0005s\u0017\u0010\u0005\u0002!w\u0011)A(\tb\u0001m\t\u00111N\u0019\t\u0003Ay\"Qa\u0010\u0002C\u0002Y\u0012!aS!\u0011\u0005\u0001\nE!\u0002\"\u0003\u0005\u00041$A\u0001,B!\u0011\u0001CIT)\u0005\u000b\u0015\u0013!\u0019\u0001$\u0003\u0005\r\u0013UcA$K\u0019F\u0011Q\u0005\u0013\t\u0005SAJ5\n\u0005\u0002!\u0015\u0012)A\b\u0012b\u0001mA\u0011\u0001\u0005\u0014\u0003\u0006\u001b\u0012\u0013\rA\u000e\u0002\u0003m\n\u0004\"\u0001I(\u0005\u000bA\u0013!\u0019\u0001\u001c\u0003\u0005-\u0013\u0005C\u0001\u0011S\t\u0015\u0019&A1\u00017\u0005\t1&\tC\u0003V\u0005\u0001\u000fa+A\u0006fcV\fG.\u001b;z\u001f\u001a\f\u0005c\u0001\u000fX?%\u0011\u0001l\u0002\u0002\t\u000bF,\u0018\r\\5us\")!L\u0001a\u00027\u0006)QM^&fsB!A$H\u001fO\u0011\u0015i&\u0001q\u0001_\u0003\u001d)gOV1mk\u0016\u0004B\u0001H\u000fA#\u00061R*\u00199FcV\fG.\u001b;z\u0007>t7\u000f\u001e:bS:$8\u000f\u0005\u0002\u001d\tM\u0019A!\u00042\u0011\u0005q\u0001\u0011A\u0002\u001fj]&$h\bF\u0001a\u0001"
    )
  ScalaInlineInfo: length = 0x13 (unknown attribute)
   01 00 00 03 00 21 00 22 01 00 14 00 15 00 00 0E
   00 0F 01
  ScalaSig: length = 0x3 (unknown attribute)
   05 02 00
