Classfile /Users/mw/Projects/slang-braindump/.jar/jar11/assemble/slang-braindump/assemble/content/org/scalactic/NormMethods.class
  Last modified May 29, 2022; size 1847 bytes
  SHA-256 checksum 4d599db6e7f60770750ed322321cbf876c646e93985e094091699cb61f364aa5
  Compiled from "NormMethods.scala"
public interface org.scalactic.NormMethods
  minor version: 0
  major version: 52
  flags: (0x0601) ACC_PUBLIC, ACC_INTERFACE, ACC_ABSTRACT
  this_class: #2                          // org/scalactic/NormMethods
  super_class: #4                         // java/lang/Object
  interfaces: 0, fields: 0, methods: 3, attributes: 5
Constant pool:
   #1 = Utf8               org/scalactic/NormMethods
   #2 = Class              #1             // org/scalactic/NormMethods
   #3 = Utf8               java/lang/Object
   #4 = Class              #3             // java/lang/Object
   #5 = Utf8               NormMethods.scala
   #6 = Utf8               Lscala/reflect/ScalaSignature;
   #7 = Utf8               bytes
   #8 = Utf8               \u0006\u0005%3qa\u0003\u0007\u0011\u0002\u0007\u0005\u0011\u0003C\u0003\u0019\u0001\u0011\u0005\u0011D\u0002\u0003\u001e\u0001\tq\u0002\u0002\u0003\u0011\u0003\u0005\u0003\u0005\u000b\u0011B\u0011\t\u00111\u0012!\u0011!Q\u0001\f5BQ!\r\u0002\u0005\u0002IBQ\u0001\u000f\u0002\u0005\u0002eBQA\u000f\u0001\u0005\u0004m:Q\u0001\u0012\u0007\t\u0002\u00153Qa\u0003\u0007\t\u0002\u0019CQ!M\u0005\u0005\u0002!\u00131BT8s[6+G\u000f[8eg*\u0011QBD\u0001\ng\u000e\fG.Y2uS\u000eT\u0011aD\u0001\u0004_J<7\u0001A\n\u0003\u0001I\u0001\"a\u0005\f\u000e\u0003QQ\u0011!F\u0001\u0006g\u000e\fG.Y\u0005\u0003/Q\u0011a!\u00118z%\u00164\u0017A\u0002\u0013j]&$H\u0005F\u0001\u001b!\t\u00192$\u0003\u0002\u001d)\t!QK\\5u\u0005)quN]7bY&TXM]\u000b\u0003?\r\u001a\"A\u0001\n\u0002\u0003=\u0004\"AI\u0012\r\u0001\u0011)AE\u0001b\u0001K\t\tA+\u0005\u0002\'SA\u00111cJ\u0005\u0003QQ\u0011qAT8uQ&tw\r\u0005\u0002\u0014U%\u00111\u0006\u0006\u0002\u0004\u0003:L\u0018!\u00048pe6\fG.\u001b>bi&|g\u000eE\u0002/_\u0005j\u0011\u0001D\u0005\u0003a1\u0011QBT8s[\u0006d\u0017N_1uS>t\u0017A\u0002\u001fj]&$h\b\u0006\u00024oQ\u0011AG\u000e\t\u0004k\t\tS\"\u0001\u0001\t\u000b1*\u00019A\u0017\t\u000b\u0001*\u0001\u0019A\u0011\u0002\t9|\'/\\\u000b\u0002C\u0005\u00192m\u001c8wKJ$Hk\u001c(pe6\fG.\u001b>feV\u0011A\b\u0011\u000b\u0003{\r#\"AP!\u0011\u0007U\u0012q\b\u0005\u0002#\u0001\u0012)Ae\u0002b\u0001K!)Af\u0002a\u0002\u0005B\u0019afL \t\u000b\u0001:\u0001\u0019A \u0002\u00179{\'/\\\'fi\"|Gm\u001d\t\u0003]%\u00192!\u0003\nH!\tq\u0003\u0001F\u0001F\u0001
   #9 = Utf8               org/scalactic/NormMethods$Normalizer
  #10 = Class              #9             // org/scalactic/NormMethods$Normalizer
  #11 = Utf8               Normalizer
  #12 = Utf8               convertToNormalizer$
  #13 = Utf8               (Lorg/scalactic/NormMethods;Ljava/lang/Object;Lorg/scalactic/Normalization;)Lorg/scalactic/NormMethods$Normalizer;
  #14 = Utf8               $this
  #15 = Utf8               o
  #16 = Utf8               normalization
  #17 = Utf8               convertToNormalizer
  #18 = Utf8               (Ljava/lang/Object;Lorg/scalactic/Normalization;)Lorg/scalactic/NormMethods$Normalizer;
  #19 = NameAndType        #17:#18        // convertToNormalizer:(Ljava/lang/Object;Lorg/scalactic/Normalization;)Lorg/scalactic/NormMethods$Normalizer;
  #20 = InterfaceMethodref #2.#19         // org/scalactic/NormMethods.convertToNormalizer:(Ljava/lang/Object;Lorg/scalactic/Normalization;)Lorg/scalactic/NormMethods$Normalizer;
  #21 = Utf8               Lorg/scalactic/NormMethods;
  #22 = Utf8               Ljava/lang/Object;
  #23 = Utf8               Lorg/scalactic/Normalization;
  #24 = Utf8               <T:Ljava/lang/Object;>(TT;Lorg/scalactic/Normalization<TT;>;)Lorg/scalactic/NormMethods$Normalizer<TT;>;
  #25 = Utf8               <init>
  #26 = Utf8               (Lorg/scalactic/NormMethods;Ljava/lang/Object;Lorg/scalactic/Normalization;)V
  #27 = NameAndType        #25:#26        // "<init>":(Lorg/scalactic/NormMethods;Ljava/lang/Object;Lorg/scalactic/Normalization;)V
  #28 = Methodref          #10.#27        // org/scalactic/NormMethods$Normalizer."<init>":(Lorg/scalactic/NormMethods;Ljava/lang/Object;Lorg/scalactic/Normalization;)V
  #29 = Utf8               this
  #30 = Utf8               $init$
  #31 = Utf8               (Lorg/scalactic/NormMethods;)V
  #32 = Utf8               Code
  #33 = Utf8               LineNumberTable
  #34 = Utf8               LocalVariableTable
  #35 = Utf8               MethodParameters
  #36 = Utf8               Signature
  #37 = Utf8               InnerClasses
  #38 = Utf8               SourceFile
  #39 = Utf8               RuntimeVisibleAnnotations
  #40 = Utf8               ScalaInlineInfo
  #41 = Utf8               ScalaSig
{
  public static org.scalactic.NormMethods$Normalizer convertToNormalizer$(org.scalactic.NormMethods, java.lang.Object, org.scalactic.Normalization);
    descriptor: (Lorg/scalactic/NormMethods;Ljava/lang/Object;Lorg/scalactic/Normalization;)Lorg/scalactic/NormMethods$Normalizer;
    flags: (0x1009) ACC_PUBLIC, ACC_STATIC, ACC_SYNTHETIC
    Code:
      stack=3, locals=3, args_size=3
         0: aload_0
         1: aload_1
         2: aload_2
         3: invokespecial #20                 // InterfaceMethod convertToNormalizer:(Ljava/lang/Object;Lorg/scalactic/Normalization;)Lorg/scalactic/NormMethods$Normalizer;
         6: areturn
      LineNumberTable:
        line 75: 0
      LocalVariableTable:
        Start  Length  Slot  Name   Signature
            0       7     0 $this   Lorg/scalactic/NormMethods;
            0       7     1     o   Ljava/lang/Object;
            0       7     2 normalization   Lorg/scalactic/Normalization;
    MethodParameters:
      Name                           Flags
      $this                          final synthetic
      o                              final
      normalization                  final

  public default <T extends java.lang.Object> org.scalactic.NormMethods$Normalizer<T> convertToNormalizer(T, org.scalactic.Normalization<T>);
    descriptor: (Ljava/lang/Object;Lorg/scalactic/Normalization;)Lorg/scalactic/NormMethods$Normalizer;
    flags: (0x0001) ACC_PUBLIC
    Code:
      stack=5, locals=3, args_size=3
         0: new           #10                 // class org/scalactic/NormMethods$Normalizer
         3: dup
         4: aload_0
         5: aload_1
         6: aload_2
         7: invokespecial #28                 // Method org/scalactic/NormMethods$Normalizer."<init>":(Lorg/scalactic/NormMethods;Ljava/lang/Object;Lorg/scalactic/Normalization;)V
        10: areturn
      LineNumberTable:
        line 75: 0
      LocalVariableTable:
        Start  Length  Slot  Name   Signature
            0      11     0  this   Lorg/scalactic/NormMethods;
            0      11     1     o   Ljava/lang/Object;
            0      11     2 normalization   Lorg/scalactic/Normalization;
    Signature: #24                          // <T:Ljava/lang/Object;>(TT;Lorg/scalactic/Normalization<TT;>;)Lorg/scalactic/NormMethods$Normalizer<TT;>;
    MethodParameters:
      Name                           Flags
      o                              final
      normalization                  final

  public static void $init$(org.scalactic.NormMethods);
    descriptor: (Lorg/scalactic/NormMethods;)V
    flags: (0x0009) ACC_PUBLIC, ACC_STATIC
    Code:
      stack=0, locals=1, args_size=1
         0: return
      LineNumberTable:
        line 49: 0
      LocalVariableTable:
        Start  Length  Slot  Name   Signature
            0       1     0 $this   Lorg/scalactic/NormMethods;
    MethodParameters:
      Name                           Flags
      $this                          final synthetic
}
InnerClasses:
  public final #11= #10 of #2;            // Normalizer=class org/scalactic/NormMethods$Normalizer of class org/scalactic/NormMethods
SourceFile: "NormMethods.scala"
RuntimeVisibleAnnotations:
  0: #6(#7=s#8)
    scala.reflect.ScalaSignature(
      bytes="\u0006\u0005%3qa\u0003\u0007\u0011\u0002\u0007\u0005\u0011\u0003C\u0003\u0019\u0001\u0011\u0005\u0011D\u0002\u0003\u001e\u0001\tq\u0002\u0002\u0003\u0011\u0003\u0005\u0003\u0005\u000b\u0011B\u0011\t\u00111\u0012!\u0011!Q\u0001\f5BQ!\r\u0002\u0005\u0002IBQ\u0001\u000f\u0002\u0005\u0002eBQA\u000f\u0001\u0005\u0004m:Q\u0001\u0012\u0007\t\u0002\u00153Qa\u0003\u0007\t\u0002\u0019CQ!M\u0005\u0005\u0002!\u00131BT8s[6+G\u000f[8eg*\u0011QBD\u0001\ng\u000e\fG.Y2uS\u000eT\u0011aD\u0001\u0004_J<7\u0001A\n\u0003\u0001I\u0001\"a\u0005\f\u000e\u0003QQ\u0011!F\u0001\u0006g\u000e\fG.Y\u0005\u0003/Q\u0011a!\u00118z%\u00164\u0017A\u0002\u0013j]&$H\u0005F\u0001\u001b!\t\u00192$\u0003\u0002\u001d)\t!QK\\5u\u0005)quN]7bY&TXM]\u000b\u0003?\r\u001a\"A\u0001\n\u0002\u0003=\u0004\"AI\u0012\r\u0001\u0011)AE\u0001b\u0001K\t\tA+\u0005\u0002\'SA\u00111cJ\u0005\u0003QQ\u0011qAT8uQ&tw\r\u0005\u0002\u0014U%\u00111\u0006\u0006\u0002\u0004\u0003:L\u0018!\u00048pe6\fG.\u001b>bi&|g\u000eE\u0002/_\u0005j\u0011\u0001D\u0005\u0003a1\u0011QBT8s[\u0006d\u0017N_1uS>t\u0017A\u0002\u001fj]&$h\b\u0006\u00024oQ\u0011AG\u000e\t\u0004k\t\tS\"\u0001\u0001\t\u000b1*\u00019A\u0017\t\u000b\u0001*\u0001\u0019A\u0011\u0002\t9|\'/\\\u000b\u0002C\u0005\u00192m\u001c8wKJ$Hk\u001c(pe6\fG.\u001b>feV\u0011A\b\u0011\u000b\u0003{\r#\"AP!\u0011\u0007U\u0012q\b\u0005\u0002#\u0001\u0012)Ae\u0002b\u0001K!)Af\u0002a\u0002\u0005B\u0019afL \t\u000b\u0001:\u0001\u0019A \u0002\u00179{\'/\\\'fi\"|Gm\u001d\t\u0003]%\u00192!\u0003\nH!\tq\u0003\u0001F\u0001F\u0001"
    )
  ScalaInlineInfo: length = 0x13 (unknown attribute)
   01 00 00 03 00 1E 00 1F 01 00 11 00 12 00 00 0C
   00 0D 01
  ScalaSig: length = 0x3 (unknown attribute)
   05 02 00
