Classfile /Users/mw/Projects/slang-braindump/.jar/jar11/assemble/slang-braindump/assemble/content/org/scalactic/NormalizingEquality.class
  Last modified May 29, 2022; size 3440 bytes
  SHA-256 checksum 16e200b87524ccd92c61d2a5b788959405d8b74e4a710c3b4f70c9cf3fbc8425
  Compiled from "NormalizingEquality.scala"
public interface org.scalactic.NormalizingEquality<A extends java.lang.Object> extends org.scalactic.Equality<A>
  minor version: 0
  major version: 52
  flags: (0x0601) ACC_PUBLIC, ACC_INTERFACE, ACC_ABSTRACT
  this_class: #2                          // org/scalactic/NormalizingEquality
  super_class: #5                         // java/lang/Object
  interfaces: 1, fields: 0, methods: 12, attributes: 6
Constant pool:
   #1 = Utf8               org/scalactic/NormalizingEquality
   #2 = Class              #1             // org/scalactic/NormalizingEquality
   #3 = Utf8               <A:Ljava/lang/Object;>Ljava/lang/Object;Lorg/scalactic/Equality<TA;>;
   #4 = Utf8               java/lang/Object
   #5 = Class              #4             // java/lang/Object
   #6 = Utf8               org/scalactic/Equality
   #7 = Class              #6             // org/scalactic/Equality
   #8 = Utf8               NormalizingEquality.scala
   #9 = Utf8               Lscala/reflect/ScalaSignature;
  #10 = Utf8               bytes
  #11 = Utf8               \u0006\u0005%3q!\u0003\u0006\u0011\u0002\u0007\u0005q\u0002C\u0003\'\u0001\u0011\u0005q\u0005C\u0004,\u0001\t\u0007I\u0011\u0001\u0017\t\u000b5\u0002AQ\u0001\u0018\t\u000bY\u0002a\u0011A\u001c\t\u000be\u0002a\u0011\u0001\u001e\t\u000bq\u0002a\u0011A\u001f\t\u000b}\u0002AQ\u0001!\t\u000b\u001d\u0003AQ\u0001%\u0003\'9{\'/\\1mSjLgnZ#rk\u0006d\u0017\u000e^=\u000b\u0005-a\u0011!C:dC2\f7\r^5d\u0015\u0005i\u0011aA8sO\u000e\u0001QC\u0001\t\u001e\'\r\u0001\u0011c\u0006\t\u0003%Ui\u0011a\u0005\u0006\u0002)\u0005)1oY1mC&\u0011ac\u0005\u0002\u0007\u0003:L(+\u001a4\u0011\u0007aI2$D\u0001\u000b\u0013\tQ\"B\u0001\u0005FcV\fG.\u001b;z!\taR\u0004\u0004\u0001\u0005\u000by\u0001!\u0019A\u0010\u0003\u0003\u0005\u000b\"\u0001I\u0012\u0011\u0005I\t\u0013B\u0001\u0012\u0014\u0005\u001dqu\u000e\u001e5j]\u001e\u0004\"A\u0005\u0013\n\u0005\u0015\u001a\"aA!os\u00061A%\u001b8ji\u0012\"\u0012\u0001\u000b\t\u0003%%J!AK\n\u0003\tUs\u0017\u000e^\u0001\u001bC\u001a$XM\u001d(pe6\fG.\u001b>bi&|g.R9vC2LG/_\u000b\u0002/\u0005A\u0011M]3FcV\fG\u000eF\u00020eQ\u0002\"A\u0005\u0019\n\u0005E\u001a\"a\u0002\"p_2,\u0017M\u001c\u0005\u0006g\r\u0001\raG\u0001\u0002C\")Qg\u0001a\u0001G\u0005\t!-\u0001\u0006o_Jl\u0017\r\\5{K\u0012$\"a\u0007\u001d\t\u000bM\"\u0001\u0019A\u000e\u0002\'9|\'/\\1mSj,GmQ1o\u0011\u0006tG\r\\3\u0015\u0005=Z\u0004\"B\u001b\u0006\u0001\u0004\u0019\u0013\u0001\u00058pe6\fG.\u001b>fI>\u00138+Y7f)\t\u0019c\bC\u00036\r\u0001\u00071%A\u0002b]\u0012$\"!\u0011\"\u0011\u0007a\u00011\u0004C\u0003D\u000f\u0001\u0007A)A\u0003pi\",\'\u000fE\u0002\u0019\u000bnI!A\u0012\u0006\u0003\u0015Us\u0017NZ8s[&$\u00180\u0001\u0007u_Vs\u0017NZ8s[&$\u00180F\u0001E\u0001
  #12 = Utf8               org/scalactic/NormalizingEquality$$anon$1
  #13 = Class              #12            // org/scalactic/NormalizingEquality$$anon$1
  #14 = Utf8               org$scalactic$NormalizingEquality$_setter_$afterNormalizationEquality_$eq
  #15 = Utf8               (Lorg/scalactic/Equality;)V
  #16 = Utf8               (Lorg/scalactic/Equality<TA;>;)V
  #17 = Utf8               x$1
  #18 = Utf8               afterNormalizationEquality
  #19 = Utf8               ()Lorg/scalactic/Equality;
  #20 = Utf8               ()Lorg/scalactic/Equality<TA;>;
  #21 = Utf8               areEqual$
  #22 = Utf8               (Lorg/scalactic/NormalizingEquality;Ljava/lang/Object;Ljava/lang/Object;)Z
  #23 = Utf8               $this
  #24 = Utf8               a
  #25 = Utf8               b
  #26 = Utf8               areEqual
  #27 = Utf8               (Ljava/lang/Object;Ljava/lang/Object;)Z
  #28 = NameAndType        #26:#27        // areEqual:(Ljava/lang/Object;Ljava/lang/Object;)Z
  #29 = InterfaceMethodref #2.#28         // org/scalactic/NormalizingEquality.areEqual:(Ljava/lang/Object;Ljava/lang/Object;)Z
  #30 = Utf8               Lorg/scalactic/NormalizingEquality;
  #31 = Utf8               Ljava/lang/Object;
  #32 = Utf8               (TA;Ljava/lang/Object;)Z
  #33 = NameAndType        #18:#19        // afterNormalizationEquality:()Lorg/scalactic/Equality;
  #34 = InterfaceMethodref #2.#33         // org/scalactic/NormalizingEquality.afterNormalizationEquality:()Lorg/scalactic/Equality;
  #35 = Utf8               normalized
  #36 = Utf8               (Ljava/lang/Object;)Ljava/lang/Object;
  #37 = NameAndType        #35:#36        // normalized:(Ljava/lang/Object;)Ljava/lang/Object;
  #38 = InterfaceMethodref #2.#37         // org/scalactic/NormalizingEquality.normalized:(Ljava/lang/Object;)Ljava/lang/Object;
  #39 = Utf8               normalizedOrSame
  #40 = NameAndType        #39:#36        // normalizedOrSame:(Ljava/lang/Object;)Ljava/lang/Object;
  #41 = InterfaceMethodref #2.#40         // org/scalactic/NormalizingEquality.normalizedOrSame:(Ljava/lang/Object;)Ljava/lang/Object;
  #42 = InterfaceMethodref #7.#28         // org/scalactic/Equality.areEqual:(Ljava/lang/Object;Ljava/lang/Object;)Z
  #43 = Utf8               this
  #44 = Utf8               (TA;)TA;
  #45 = Utf8               normalizedCanHandle
  #46 = Utf8               (Ljava/lang/Object;)Z
  #47 = Utf8               and$
  #48 = Utf8               (Lorg/scalactic/NormalizingEquality;Lorg/scalactic/Uniformity;)Lorg/scalactic/NormalizingEquality;
  #49 = Utf8               other
  #50 = Utf8               and
  #51 = Utf8               (Lorg/scalactic/Uniformity;)Lorg/scalactic/NormalizingEquality;
  #52 = NameAndType        #50:#51        // and:(Lorg/scalactic/Uniformity;)Lorg/scalactic/NormalizingEquality;
  #53 = InterfaceMethodref #2.#52         // org/scalactic/NormalizingEquality.and:(Lorg/scalactic/Uniformity;)Lorg/scalactic/NormalizingEquality;
  #54 = Utf8               Lorg/scalactic/Uniformity;
  #55 = Utf8               (Lorg/scalactic/Uniformity<TA;>;)Lorg/scalactic/NormalizingEquality<TA;>;
  #56 = Utf8               org/scalactic/ComposedNormalizingEquality
  #57 = Class              #56            // org/scalactic/ComposedNormalizingEquality
  #58 = Utf8               toUniformity
  #59 = Utf8               ()Lorg/scalactic/Uniformity;
  #60 = NameAndType        #58:#59        // toUniformity:()Lorg/scalactic/Uniformity;
  #61 = InterfaceMethodref #2.#60         // org/scalactic/NormalizingEquality.toUniformity:()Lorg/scalactic/Uniformity;
  #62 = Utf8               org/scalactic/Uniformity
  #63 = Class              #62            // org/scalactic/Uniformity
  #64 = Utf8               (Lorg/scalactic/Uniformity;)Lorg/scalactic/Uniformity;
  #65 = NameAndType        #50:#64        // and:(Lorg/scalactic/Uniformity;)Lorg/scalactic/Uniformity;
  #66 = InterfaceMethodref #63.#65        // org/scalactic/Uniformity.and:(Lorg/scalactic/Uniformity;)Lorg/scalactic/Uniformity;
  #67 = Utf8               <init>
  #68 = Utf8               (Lorg/scalactic/Equality;Lorg/scalactic/Uniformity;)V
  #69 = NameAndType        #67:#68        // "<init>":(Lorg/scalactic/Equality;Lorg/scalactic/Uniformity;)V
  #70 = Methodref          #57.#69        // org/scalactic/ComposedNormalizingEquality."<init>":(Lorg/scalactic/Equality;Lorg/scalactic/Uniformity;)V
  #71 = Utf8               toUniformity$
  #72 = Utf8               (Lorg/scalactic/NormalizingEquality;)Lorg/scalactic/Uniformity;
  #73 = Utf8               ()Lorg/scalactic/Uniformity<TA;>;
  #74 = Utf8               (Lorg/scalactic/NormalizingEquality;)V
  #75 = NameAndType        #67:#74        // "<init>":(Lorg/scalactic/NormalizingEquality;)V
  #76 = Methodref          #13.#75        // org/scalactic/NormalizingEquality$$anon$1."<init>":(Lorg/scalactic/NormalizingEquality;)V
  #77 = Utf8               $init$
  #78 = Utf8               org/scalactic/Equality$
  #79 = Class              #78            // org/scalactic/Equality$
  #80 = Utf8               MODULE$
  #81 = Utf8               Lorg/scalactic/Equality$;
  #82 = NameAndType        #80:#81        // MODULE$:Lorg/scalactic/Equality$;
  #83 = Fieldref           #79.#82        // org/scalactic/Equality$.MODULE$:Lorg/scalactic/Equality$;
  #84 = Utf8               default
  #85 = NameAndType        #84:#19        // default:()Lorg/scalactic/Equality;
  #86 = Methodref          #79.#85        // org/scalactic/Equality$.default:()Lorg/scalactic/Equality;
  #87 = NameAndType        #14:#15        // org$scalactic$NormalizingEquality$_setter_$afterNormalizationEquality_$eq:(Lorg/scalactic/Equality;)V
  #88 = InterfaceMethodref #2.#87         // org/scalactic/NormalizingEquality.org$scalactic$NormalizingEquality$_setter_$afterNormalizationEquality_$eq:(Lorg/scalactic/Equality;)V
  #89 = Utf8               Signature
  #90 = Utf8               MethodParameters
  #91 = Utf8               Code
  #92 = Utf8               LineNumberTable
  #93 = Utf8               LocalVariableTable
  #94 = Utf8               InnerClasses
  #95 = Utf8               SourceFile
  #96 = Utf8               RuntimeVisibleAnnotations
  #97 = Utf8               ScalaInlineInfo
  #98 = Utf8               ScalaSig
{
  public abstract void org$scalactic$NormalizingEquality$_setter_$afterNormalizationEquality_$eq(org.scalactic.Equality<A>);
    descriptor: (Lorg/scalactic/Equality;)V
    flags: (0x0401) ACC_PUBLIC, ACC_ABSTRACT
    Signature: #16                          // (Lorg/scalactic/Equality<TA;>;)V
    MethodParameters:
      Name                           Flags
      x$1                            final

  public abstract org.scalactic.Equality<A> afterNormalizationEquality();
    descriptor: ()Lorg/scalactic/Equality;
    flags: (0x0401) ACC_PUBLIC, ACC_ABSTRACT
    Signature: #20                          // ()Lorg/scalactic/Equality<TA;>;

  public static boolean areEqual$(org.scalactic.NormalizingEquality, java.lang.Object, java.lang.Object);
    descriptor: (Lorg/scalactic/NormalizingEquality;Ljava/lang/Object;Ljava/lang/Object;)Z
    flags: (0x1009) ACC_PUBLIC, ACC_STATIC, ACC_SYNTHETIC
    Code:
      stack=3, locals=3, args_size=3
         0: aload_0
         1: aload_1
         2: aload_2
         3: invokespecial #29                 // InterfaceMethod areEqual:(Ljava/lang/Object;Ljava/lang/Object;)Z
         6: ireturn
      LineNumberTable:
        line 69: 0
      LocalVariableTable:
        Start  Length  Slot  Name   Signature
            0       7     0 $this   Lorg/scalactic/NormalizingEquality;
            0       7     1     a   Ljava/lang/Object;
            0       7     2     b   Ljava/lang/Object;
    MethodParameters:
      Name                           Flags
      $this                          final synthetic
      a                              final
      b                              final

  public default boolean areEqual(A, java.lang.Object);
    descriptor: (Ljava/lang/Object;Ljava/lang/Object;)Z
    flags: (0x0001) ACC_PUBLIC
    Code:
      stack=4, locals=3, args_size=3
         0: aload_0
         1: invokeinterface #34,  1           // InterfaceMethod afterNormalizationEquality:()Lorg/scalactic/Equality;
         6: aload_0
         7: aload_1
         8: invokeinterface #38,  2           // InterfaceMethod normalized:(Ljava/lang/Object;)Ljava/lang/Object;
        13: aload_0
        14: aload_2
        15: invokeinterface #41,  2           // InterfaceMethod normalizedOrSame:(Ljava/lang/Object;)Ljava/lang/Object;
        20: invokeinterface #42,  3           // InterfaceMethod org/scalactic/Equality.areEqual:(Ljava/lang/Object;Ljava/lang/Object;)Z
        25: ireturn
      LineNumberTable:
        line 70: 0
      LocalVariableTable:
        Start  Length  Slot  Name   Signature
            0      26     0  this   Lorg/scalactic/NormalizingEquality;
            0      26     1     a   Ljava/lang/Object;
            0      26     2     b   Ljava/lang/Object;
    Signature: #32                          // (TA;Ljava/lang/Object;)Z
    MethodParameters:
      Name                           Flags
      a                              final
      b                              final

  public abstract A normalized(A);
    descriptor: (Ljava/lang/Object;)Ljava/lang/Object;
    flags: (0x0401) ACC_PUBLIC, ACC_ABSTRACT
    Signature: #44                          // (TA;)TA;
    MethodParameters:
      Name                           Flags
      a                              final

  public abstract boolean normalizedCanHandle(java.lang.Object);
    descriptor: (Ljava/lang/Object;)Z
    flags: (0x0401) ACC_PUBLIC, ACC_ABSTRACT
    MethodParameters:
      Name                           Flags
      b                              final

  public abstract java.lang.Object normalizedOrSame(java.lang.Object);
    descriptor: (Ljava/lang/Object;)Ljava/lang/Object;
    flags: (0x0401) ACC_PUBLIC, ACC_ABSTRACT
    MethodParameters:
      Name                           Flags
      b                              final

  public static org.scalactic.NormalizingEquality and$(org.scalactic.NormalizingEquality, org.scalactic.Uniformity);
    descriptor: (Lorg/scalactic/NormalizingEquality;Lorg/scalactic/Uniformity;)Lorg/scalactic/NormalizingEquality;
    flags: (0x1009) ACC_PUBLIC, ACC_STATIC, ACC_SYNTHETIC
    Code:
      stack=2, locals=2, args_size=2
         0: aload_0
         1: aload_1
         2: invokespecial #53                 // InterfaceMethod and:(Lorg/scalactic/Uniformity;)Lorg/scalactic/NormalizingEquality;
         5: areturn
      LineNumberTable:
        line 145: 0
      LocalVariableTable:
        Start  Length  Slot  Name   Signature
            0       6     0 $this   Lorg/scalactic/NormalizingEquality;
            0       6     1 other   Lorg/scalactic/Uniformity;
    MethodParameters:
      Name                           Flags
      $this                          final synthetic
      other                          final

  public default org.scalactic.NormalizingEquality<A> and(org.scalactic.Uniformity<A>);
    descriptor: (Lorg/scalactic/Uniformity;)Lorg/scalactic/NormalizingEquality;
    flags: (0x0001) ACC_PUBLIC
    Code:
      stack=5, locals=2, args_size=2
         0: new           #57                 // class org/scalactic/ComposedNormalizingEquality
         3: dup
         4: aload_0
         5: invokeinterface #34,  1           // InterfaceMethod afterNormalizationEquality:()Lorg/scalactic/Equality;
        10: aload_0
        11: invokeinterface #61,  1           // InterfaceMethod toUniformity:()Lorg/scalactic/Uniformity;
        16: aload_1
        17: invokeinterface #66,  2           // InterfaceMethod org/scalactic/Uniformity.and:(Lorg/scalactic/Uniformity;)Lorg/scalactic/Uniformity;
        22: invokespecial #70                 // Method org/scalactic/ComposedNormalizingEquality."<init>":(Lorg/scalactic/Equality;Lorg/scalactic/Uniformity;)V
        25: areturn
      LineNumberTable:
        line 146: 0
      LocalVariableTable:
        Start  Length  Slot  Name   Signature
            0      26     0  this   Lorg/scalactic/NormalizingEquality;
            0      26     1 other   Lorg/scalactic/Uniformity;
    Signature: #55                          // (Lorg/scalactic/Uniformity<TA;>;)Lorg/scalactic/NormalizingEquality<TA;>;
    MethodParameters:
      Name                           Flags
      other                          final

  public static org.scalactic.Uniformity toUniformity$(org.scalactic.NormalizingEquality);
    descriptor: (Lorg/scalactic/NormalizingEquality;)Lorg/scalactic/Uniformity;
    flags: (0x1009) ACC_PUBLIC, ACC_STATIC, ACC_SYNTHETIC
    Code:
      stack=1, locals=1, args_size=1
         0: aload_0
         1: invokespecial #61                 // InterfaceMethod toUniformity:()Lorg/scalactic/Uniformity;
         4: areturn
      LineNumberTable:
        line 157: 0
      LocalVariableTable:
        Start  Length  Slot  Name   Signature
            0       5     0 $this   Lorg/scalactic/NormalizingEquality;
    MethodParameters:
      Name                           Flags
      $this                          final synthetic

  public default org.scalactic.Uniformity<A> toUniformity();
    descriptor: ()Lorg/scalactic/Uniformity;
    flags: (0x0001) ACC_PUBLIC
    Code:
      stack=3, locals=1, args_size=1
         0: new           #13                 // class org/scalactic/NormalizingEquality$$anon$1
         3: dup
         4: aload_0
         5: invokespecial #76                 // Method org/scalactic/NormalizingEquality$$anon$1."<init>":(Lorg/scalactic/NormalizingEquality;)V
         8: areturn
      LineNumberTable:
        line 158: 0
      LocalVariableTable:
        Start  Length  Slot  Name   Signature
            0       9     0  this   Lorg/scalactic/NormalizingEquality;
    Signature: #73                          // ()Lorg/scalactic/Uniformity<TA;>;

  public static void $init$(org.scalactic.NormalizingEquality);
    descriptor: (Lorg/scalactic/NormalizingEquality;)V
    flags: (0x0009) ACC_PUBLIC, ACC_STATIC
    Code:
      stack=2, locals=1, args_size=1
         0: aload_0
         1: getstatic     #83                 // Field org/scalactic/Equality$.MODULE$:Lorg/scalactic/Equality$;
         4: invokevirtual #86                 // Method org/scalactic/Equality$.default:()Lorg/scalactic/Equality;
         7: invokeinterface #88,  2           // InterfaceMethod org$scalactic$NormalizingEquality$_setter_$afterNormalizationEquality_$eq:(Lorg/scalactic/Equality;)V
        12: return
      LineNumberTable:
        line 57: 0
        line 45: 12
      LocalVariableTable:
        Start  Length  Slot  Name   Signature
            0      13     0 $this   Lorg/scalactic/NormalizingEquality;
    MethodParameters:
      Name                           Flags
      $this                          final synthetic
}
InnerClasses:
  public final #13;                       // class org/scalactic/NormalizingEquality$$anon$1
Signature: #3                           // <A:Ljava/lang/Object;>Ljava/lang/Object;Lorg/scalactic/Equality<TA;>;
SourceFile: "NormalizingEquality.scala"
RuntimeVisibleAnnotations:
  0: #9(#10=s#11)
    scala.reflect.ScalaSignature(
      bytes="\u0006\u0005%3q!\u0003\u0006\u0011\u0002\u0007\u0005q\u0002C\u0003\'\u0001\u0011\u0005q\u0005C\u0004,\u0001\t\u0007I\u0011\u0001\u0017\t\u000b5\u0002AQ\u0001\u0018\t\u000bY\u0002a\u0011A\u001c\t\u000be\u0002a\u0011\u0001\u001e\t\u000bq\u0002a\u0011A\u001f\t\u000b}\u0002AQ\u0001!\t\u000b\u001d\u0003AQ\u0001%\u0003\'9{\'/\\1mSjLgnZ#rk\u0006d\u0017\u000e^=\u000b\u0005-a\u0011!C:dC2\f7\r^5d\u0015\u0005i\u0011aA8sO\u000e\u0001QC\u0001\t\u001e\'\r\u0001\u0011c\u0006\t\u0003%Ui\u0011a\u0005\u0006\u0002)\u0005)1oY1mC&\u0011ac\u0005\u0002\u0007\u0003:L(+\u001a4\u0011\u0007aI2$D\u0001\u000b\u0013\tQ\"B\u0001\u0005FcV\fG.\u001b;z!\taR\u0004\u0004\u0001\u0005\u000by\u0001!\u0019A\u0010\u0003\u0003\u0005\u000b\"\u0001I\u0012\u0011\u0005I\t\u0013B\u0001\u0012\u0014\u0005\u001dqu\u000e\u001e5j]\u001e\u0004\"A\u0005\u0013\n\u0005\u0015\u001a\"aA!os\u00061A%\u001b8ji\u0012\"\u0012\u0001\u000b\t\u0003%%J!AK\n\u0003\tUs\u0017\u000e^\u0001\u001bC\u001a$XM\u001d(pe6\fG.\u001b>bi&|g.R9vC2LG/_\u000b\u0002/\u0005A\u0011M]3FcV\fG\u000eF\u00020eQ\u0002\"A\u0005\u0019\n\u0005E\u001a\"a\u0002\"p_2,\u0017M\u001c\u0005\u0006g\r\u0001\raG\u0001\u0002C\")Qg\u0001a\u0001G\u0005\t!-\u0001\u0006o_Jl\u0017\r\\5{K\u0012$\"a\u0007\u001d\t\u000bM\"\u0001\u0019A\u000e\u0002\'9|\'/\\1mSj,GmQ1o\u0011\u0006tG\r\\3\u0015\u0005=Z\u0004\"B\u001b\u0006\u0001\u0004\u0019\u0013\u0001\u00058pe6\fG.\u001b>fI>\u00138+Y7f)\t\u0019c\bC\u00036\r\u0001\u00071%A\u0002b]\u0012$\"!\u0011\"\u0011\u0007a\u00011\u0004C\u0003D\u000f\u0001\u0007A)A\u0003pi\",\'\u000fE\u0002\u0019\u000bnI!A\u0012\u0006\u0003\u0015Us\u0017NZ8s[&$\u00180\u0001\u0007u_Vs\u0017NZ8s[&$\u00180F\u0001E\u0001"
    )
  ScalaInlineInfo: length = 0x40 (unknown attribute)
   01 00 00 0C 00 4D 00 4A 01 00 12 00 13 00 00 32
   00 33 01 00 2F 00 30 01 00 1A 00 1B 01 00 15 00
   16 01 00 23 00 24 00 00 2D 00 2E 00 00 27 00 24
   00 00 0E 00 0F 00 00 3A 00 3B 01 00 47 00 48 01

  ScalaSig: length = 0x3 (unknown attribute)
   05 02 00
