Classfile /Users/mw/Projects/slang-braindump/.jar/jar11/assemble/slang-braindump/assemble/content/org/scalactic/NumericEqualityConstraints.class
  Last modified May 29, 2022; size 2066 bytes
  SHA-256 checksum 996ff49ea40f0147ab3ca0f8d8ffde675754cce85be1bd42d88661abb43ecbdc
  Compiled from "NumericEqualityConstraints.scala"
public interface org.scalactic.NumericEqualityConstraints
  minor version: 0
  major version: 52
  flags: (0x0601) ACC_PUBLIC, ACC_INTERFACE, ACC_ABSTRACT
  this_class: #2                          // org/scalactic/NumericEqualityConstraints
  super_class: #4                         // java/lang/Object
  interfaces: 0, fields: 0, methods: 3, attributes: 5
Constant pool:
   #1 = Utf8               org/scalactic/NumericEqualityConstraints
   #2 = Class              #1             // org/scalactic/NumericEqualityConstraints
   #3 = Utf8               java/lang/Object
   #4 = Class              #3             // java/lang/Object
   #5 = Utf8               NumericEqualityConstraints.scala
   #6 = Utf8               Lscala/reflect/ScalaSignature;
   #7 = Utf8               bytes
   #8 = Utf8               \u0006\u0005%3\u0001BB\u0004\u0011\u0002\u0007\u0005qa\u0003\u0005\u0006%\u0001!\t\u0001\u0006\u0005\u00061\u0001!\u0019!G\u0004\u0007\u0007\u001eA\ta\u0002#\u0007\r\u00199\u0001\u0012A\u0004F\u0011\u00159E\u0001\"\u0001I\u0005iqU/\\3sS\u000e,\u0015/^1mSRL8i\u001c8tiJ\f\u0017N\u001c;t\u0015\tA\u0011\"A\u0005tG\u0006d\u0017m\u0019;jG*\t!\"A\u0002pe\u001e\u001c\"\u0001\u0001\u0007\u0011\u00055\u0001R\"\u0001\b\u000b\u0003=\tQa]2bY\u0006L!!\u0005\b\u0003\r\u0005s\u0017PU3g\u0003\u0019!\u0013N\\5uI\r\u0001A#A\u000b\u0011\u000551\u0012BA\f\u000f\u0005\u0011)f.\u001b;\u000239,X.\u001a:jG\u0016\u000bX/\u00197jif\u001cuN\\:ue\u0006Lg\u000e^\u000b\u00045\u0005ZC\u0003B\u000e.e\u0001\u0003B\u0001H\u000f U5\tq!\u0003\u0002\u001f\u000f\tA1)\u00198FcV\fG\u000e\u0005\u0002!C1\u0001A!\u0002\u0012\u0003\u0005\u0004\u0019#!A!\u0012\u0005\u0011:\u0003CA\u0007&\u0013\t1cBA\u0004O_RD\u0017N\\4\u0011\u00055A\u0013BA\u0015\u000f\u0005\r\te.\u001f\t\u0003A-\"Q\u0001\f\u0002C\u0002\r\u0012\u0011A\u0011\u0005\u0006]\t\u0001\u001daL\u0001\fKF,\u0018\r\\5us>3\u0017\tE\u0002\u001da}I!!M\u0004\u0003\u0011\u0015\u000bX/\u00197jifDQa\r\u0002A\u0004Q\nAA\\;n\u0003B\u0019Q\'P\u0010\u000f\u0005YZdBA\u001c;\u001b\u0005A$BA\u001d\u0014\u0003\u0019a$o\\8u}%\tq\"\u0003\u0002=\u001d\u00059\u0001/Y2lC\u001e,\u0017B\u0001 @\u0005\u001dqU/\\3sS\u000eT!\u0001\u0010\b\t\u000b\u0005\u0013\u00019\u0001\"\u0002\t9,XN\u0011\t\u0004kuR\u0013A\u0007(v[\u0016\u0014\u0018nY#rk\u0006d\u0017\u000e^=D_:\u001cHO]1j]R\u001c\bC\u0001\u000f\u0005\'\r!AB\u0012\t\u00039\u0001\ta\u0001P5oSRtD#\u0001#
   #9 = Utf8               org/scalactic/TripleEqualsSupport$EqualityConstraint
  #10 = Class              #9             // org/scalactic/TripleEqualsSupport$EqualityConstraint
  #11 = Utf8               org/scalactic/TripleEqualsSupport
  #12 = Class              #11            // org/scalactic/TripleEqualsSupport
  #13 = Utf8               EqualityConstraint
  #14 = Utf8               numericEqualityConstraint$
  #15 = Utf8               (Lorg/scalactic/NumericEqualityConstraints;Lorg/scalactic/Equality;Lscala/math/Numeric;Lscala/math/Numeric;)Lorg/scalactic/CanEqual;
  #16 = Utf8               $this
  #17 = Utf8               equalityOfA
  #18 = Utf8               numA
  #19 = Utf8               numB
  #20 = Utf8               numericEqualityConstraint
  #21 = Utf8               (Lorg/scalactic/Equality;Lscala/math/Numeric;Lscala/math/Numeric;)Lorg/scalactic/CanEqual;
  #22 = NameAndType        #20:#21        // numericEqualityConstraint:(Lorg/scalactic/Equality;Lscala/math/Numeric;Lscala/math/Numeric;)Lorg/scalactic/CanEqual;
  #23 = InterfaceMethodref #2.#22         // org/scalactic/NumericEqualityConstraints.numericEqualityConstraint:(Lorg/scalactic/Equality;Lscala/math/Numeric;Lscala/math/Numeric;)Lorg/scalactic/CanEqual;
  #24 = Utf8               Lorg/scalactic/NumericEqualityConstraints;
  #25 = Utf8               Lorg/scalactic/Equality;
  #26 = Utf8               Lscala/math/Numeric;
  #27 = Utf8               <A:Ljava/lang/Object;B:Ljava/lang/Object;>(Lorg/scalactic/Equality<TA;>;Lscala/math/Numeric<TA;>;Lscala/math/Numeric<TB;>;)Lorg/scalactic/CanEqual<TA;TB;>;
  #28 = Utf8               <init>
  #29 = Utf8               (Lorg/scalactic/Equality;)V
  #30 = NameAndType        #28:#29        // "<init>":(Lorg/scalactic/Equality;)V
  #31 = Methodref          #10.#30        // org/scalactic/TripleEqualsSupport$EqualityConstraint."<init>":(Lorg/scalactic/Equality;)V
  #32 = Utf8               this
  #33 = Utf8               $init$
  #34 = Utf8               (Lorg/scalactic/NumericEqualityConstraints;)V
  #35 = Utf8               Code
  #36 = Utf8               LineNumberTable
  #37 = Utf8               LocalVariableTable
  #38 = Utf8               MethodParameters
  #39 = Utf8               Signature
  #40 = Utf8               InnerClasses
  #41 = Utf8               SourceFile
  #42 = Utf8               RuntimeVisibleAnnotations
  #43 = Utf8               ScalaInlineInfo
  #44 = Utf8               ScalaSig
{
  public static org.scalactic.CanEqual numericEqualityConstraint$(org.scalactic.NumericEqualityConstraints, org.scalactic.Equality, scala.math.Numeric, scala.math.Numeric);
    descriptor: (Lorg/scalactic/NumericEqualityConstraints;Lorg/scalactic/Equality;Lscala/math/Numeric;Lscala/math/Numeric;)Lorg/scalactic/CanEqual;
    flags: (0x1009) ACC_PUBLIC, ACC_STATIC, ACC_SYNTHETIC
    Code:
      stack=4, locals=4, args_size=4
         0: aload_0
         1: aload_1
         2: aload_2
         3: aload_3
         4: invokespecial #23                 // InterfaceMethod numericEqualityConstraint:(Lorg/scalactic/Equality;Lscala/math/Numeric;Lscala/math/Numeric;)Lorg/scalactic/CanEqual;
         7: areturn
      LineNumberTable:
        line 21: 0
      LocalVariableTable:
        Start  Length  Slot  Name   Signature
            0       8     0 $this   Lorg/scalactic/NumericEqualityConstraints;
            0       8     1 equalityOfA   Lorg/scalactic/Equality;
            0       8     2  numA   Lscala/math/Numeric;
            0       8     3  numB   Lscala/math/Numeric;
    MethodParameters:
      Name                           Flags
      $this                          final synthetic
      equalityOfA                    final
      numA                           final
      numB                           final

  public default <A extends java.lang.Object, B extends java.lang.Object> org.scalactic.CanEqual<A, B> numericEqualityConstraint(org.scalactic.Equality<A>, scala.math.Numeric<A>, scala.math.Numeric<B>);
    descriptor: (Lorg/scalactic/Equality;Lscala/math/Numeric;Lscala/math/Numeric;)Lorg/scalactic/CanEqual;
    flags: (0x0001) ACC_PUBLIC
    Code:
      stack=3, locals=4, args_size=4
         0: new           #10                 // class org/scalactic/TripleEqualsSupport$EqualityConstraint
         3: dup
         4: aload_1
         5: invokespecial #31                 // Method org/scalactic/TripleEqualsSupport$EqualityConstraint."<init>":(Lorg/scalactic/Equality;)V
         8: areturn
      LineNumberTable:
        line 21: 0
      LocalVariableTable:
        Start  Length  Slot  Name   Signature
            0       9     0  this   Lorg/scalactic/NumericEqualityConstraints;
            0       9     1 equalityOfA   Lorg/scalactic/Equality;
            0       9     2  numA   Lscala/math/Numeric;
            0       9     3  numB   Lscala/math/Numeric;
    Signature: #27                          // <A:Ljava/lang/Object;B:Ljava/lang/Object;>(Lorg/scalactic/Equality<TA;>;Lscala/math/Numeric<TA;>;Lscala/math/Numeric<TB;>;)Lorg/scalactic/CanEqual<TA;TB;>;
    MethodParameters:
      Name                           Flags
      equalityOfA                    final
      numA                           final
      numB                           final

  public static void $init$(org.scalactic.NumericEqualityConstraints);
    descriptor: (Lorg/scalactic/NumericEqualityConstraints;)V
    flags: (0x0009) ACC_PUBLIC, ACC_STATIC
    Code:
      stack=0, locals=1, args_size=1
         0: return
      LineNumberTable:
        line 20: 0
      LocalVariableTable:
        Start  Length  Slot  Name   Signature
            0       1     0 $this   Lorg/scalactic/NumericEqualityConstraints;
    MethodParameters:
      Name                           Flags
      $this                          final synthetic
}
InnerClasses:
  public static final #13= #10 of #12;    // EqualityConstraint=class org/scalactic/TripleEqualsSupport$EqualityConstraint of class org/scalactic/TripleEqualsSupport
SourceFile: "NumericEqualityConstraints.scala"
RuntimeVisibleAnnotations:
  0: #6(#7=s#8)
    scala.reflect.ScalaSignature(
      bytes="\u0006\u0005%3\u0001BB\u0004\u0011\u0002\u0007\u0005qa\u0003\u0005\u0006%\u0001!\t\u0001\u0006\u0005\u00061\u0001!\u0019!G\u0004\u0007\u0007\u001eA\ta\u0002#\u0007\r\u00199\u0001\u0012A\u0004F\u0011\u00159E\u0001\"\u0001I\u0005iqU/\\3sS\u000e,\u0015/^1mSRL8i\u001c8tiJ\f\u0017N\u001c;t\u0015\tA\u0011\"A\u0005tG\u0006d\u0017m\u0019;jG*\t!\"A\u0002pe\u001e\u001c\"\u0001\u0001\u0007\u0011\u00055\u0001R\"\u0001\b\u000b\u0003=\tQa]2bY\u0006L!!\u0005\b\u0003\r\u0005s\u0017PU3g\u0003\u0019!\u0013N\\5uI\r\u0001A#A\u000b\u0011\u000551\u0012BA\f\u000f\u0005\u0011)f.\u001b;\u000239,X.\u001a:jG\u0016\u000bX/\u00197jif\u001cuN\\:ue\u0006Lg\u000e^\u000b\u00045\u0005ZC\u0003B\u000e.e\u0001\u0003B\u0001H\u000f U5\tq!\u0003\u0002\u001f\u000f\tA1)\u00198FcV\fG\u000e\u0005\u0002!C1\u0001A!\u0002\u0012\u0003\u0005\u0004\u0019#!A!\u0012\u0005\u0011:\u0003CA\u0007&\u0013\t1cBA\u0004O_RD\u0017N\\4\u0011\u00055A\u0013BA\u0015\u000f\u0005\r\te.\u001f\t\u0003A-\"Q\u0001\f\u0002C\u0002\r\u0012\u0011A\u0011\u0005\u0006]\t\u0001\u001daL\u0001\fKF,\u0018\r\\5us>3\u0017\tE\u0002\u001da}I!!M\u0004\u0003\u0011\u0015\u000bX/\u00197jifDQa\r\u0002A\u0004Q\nAA\\;n\u0003B\u0019Q\'P\u0010\u000f\u0005YZdBA\u001c;\u001b\u0005A$BA\u001d\u0014\u0003\u0019a$o\\8u}%\tq\"\u0003\u0002=\u001d\u00059\u0001/Y2lC\u001e,\u0017B\u0001 @\u0005\u001dqU/\\3sS\u000eT!\u0001\u0010\b\t\u000b\u0005\u0013\u00019\u0001\"\u0002\t9,XN\u0011\t\u0004kuR\u0013A\u0007(v[\u0016\u0014\u0018nY#rk\u0006d\u0017\u000e^=D_:\u001cHO]1j]R\u001c\bC\u0001\u000f\u0005\'\r!AB\u0012\t\u00039\u0001\ta\u0001P5oSRtD#\u0001#"
    )
  ScalaInlineInfo: length = 0x13 (unknown attribute)
   01 00 00 03 00 21 00 22 01 00 14 00 15 00 00 0E
   00 0F 01
  ScalaSig: length = 0x3 (unknown attribute)
   05 02 00
