Classfile /Users/mw/Projects/slang-braindump/.jar/jar11/assemble/slang-braindump/assemble/content/org/scalactic/Or$.class
  Last modified May 29, 2022; size 2533 bytes
  SHA-256 checksum fdc413c73df60ce666fea21e2218cbbe80aca286bd2ba4104aa6cdf0c647b921
  Compiled from "Or.scala"
public final class org.scalactic.Or$ implements java.io.Serializable
  minor version: 0
  major version: 52
  flags: (0x0031) ACC_PUBLIC, ACC_FINAL, ACC_SUPER
  this_class: #2                          // org/scalactic/Or$
  super_class: #4                         // java/lang/Object
  interfaces: 1, fields: 1, methods: 6, attributes: 3
Constant pool:
    #1 = Utf8               org/scalactic/Or$
    #2 = Class              #1            // org/scalactic/Or$
    #3 = Utf8               java/lang/Object
    #4 = Class              #3            // java/lang/Object
    #5 = Utf8               java/io/Serializable
    #6 = Class              #5            // java/io/Serializable
    #7 = Utf8               Or.scala
    #8 = Utf8               MODULE$
    #9 = Utf8               Lorg/scalactic/Or$;
   #10 = Utf8               <clinit>
   #11 = Utf8               ()V
   #12 = Utf8               <init>
   #13 = NameAndType        #12:#11       // "<init>":()V
   #14 = Methodref          #2.#13        // org/scalactic/Or$."<init>":()V
   #15 = NameAndType        #8:#9         // MODULE$:Lorg/scalactic/Or$;
   #16 = Fieldref           #2.#15        // org/scalactic/Or$.MODULE$:Lorg/scalactic/Or$;
   #17 = Utf8               from
   #18 = Utf8               (Lscala/util/Try;)Lorg/scalactic/Or;
   #19 = Utf8               <G:Ljava/lang/Object;>(Lscala/util/Try<TG;>;)Lorg/scalactic/Or<TG;Ljava/lang/Throwable;>;
   #20 = Utf8               theTry
   #21 = Utf8               scala/util/Success
   #22 = Class              #21           // scala/util/Success
   #23 = Utf8               value
   #24 = Utf8               ()Ljava/lang/Object;
   #25 = NameAndType        #23:#24       // value:()Ljava/lang/Object;
   #26 = Methodref          #22.#25       // scala/util/Success.value:()Ljava/lang/Object;
   #27 = Utf8               org/scalactic/Good
   #28 = Class              #27           // org/scalactic/Good
   #29 = Utf8               (Ljava/lang/Object;)V
   #30 = NameAndType        #12:#29       // "<init>":(Ljava/lang/Object;)V
   #31 = Methodref          #28.#30       // org/scalactic/Good."<init>":(Ljava/lang/Object;)V
   #32 = Utf8               scala/util/Failure
   #33 = Class              #32           // scala/util/Failure
   #34 = Utf8               exception
   #35 = Utf8               ()Ljava/lang/Throwable;
   #36 = NameAndType        #34:#35       // exception:()Ljava/lang/Throwable;
   #37 = Methodref          #33.#36       // scala/util/Failure.exception:()Ljava/lang/Throwable;
   #38 = Utf8               org/scalactic/Bad
   #39 = Class              #38           // org/scalactic/Bad
   #40 = Methodref          #39.#30       // org/scalactic/Bad."<init>":(Ljava/lang/Object;)V
   #41 = Utf8               scala/MatchError
   #42 = Class              #41           // scala/MatchError
   #43 = Methodref          #42.#30       // scala/MatchError."<init>":(Ljava/lang/Object;)V
   #44 = Utf8               g
   #45 = Utf8               Ljava/lang/Object;
   #46 = Utf8               e
   #47 = Utf8               Ljava/lang/Throwable;
   #48 = Utf8               this
   #49 = Utf8               Lscala/util/Try;
   #50 = Utf8               scala/util/Try
   #51 = Class              #50           // scala/util/Try
   #52 = Utf8               org/scalactic/Or
   #53 = Class              #52           // org/scalactic/Or
   #54 = Utf8               (Lscala/util/Either;)Lorg/scalactic/Or;
   #55 = Utf8               <B:Ljava/lang/Object;G:Ljava/lang/Object;>(Lscala/util/Either<TB;TG;>;)Lorg/scalactic/Or<TG;TB;>;
   #56 = Utf8               either
   #57 = Utf8               scala/util/Right
   #58 = Class              #57           // scala/util/Right
   #59 = Methodref          #58.#25       // scala/util/Right.value:()Ljava/lang/Object;
   #60 = Utf8               scala/util/Left
   #61 = Class              #60           // scala/util/Left
   #62 = Methodref          #61.#25       // scala/util/Left.value:()Ljava/lang/Object;
   #63 = Utf8               b
   #64 = Utf8               Lscala/util/Either;
   #65 = Utf8               scala/util/Either
   #66 = Class              #65           // scala/util/Either
   #67 = Utf8               (Lscala/Option;Lscala/Function0;)Lorg/scalactic/Or;
   #68 = Utf8               <G:Ljava/lang/Object;B:Ljava/lang/Object;>(Lscala/Option<TG;>;Lscala/Function0<TB;>;)Lorg/scalactic/Or<TG;TB;>;
   #69 = Utf8               option
   #70 = Utf8               orElse
   #71 = Utf8               scala/Some
   #72 = Class              #71           // scala/Some
   #73 = Methodref          #72.#25       // scala/Some.value:()Ljava/lang/Object;
   #74 = Utf8               scala/None$
   #75 = Class              #74           // scala/None$
   #76 = Utf8               Lscala/None$;
   #77 = NameAndType        #8:#76        // MODULE$:Lscala/None$;
   #78 = Fieldref           #75.#77       // scala/None$.MODULE$:Lscala/None$;
   #79 = Utf8               equals
   #80 = Utf8               (Ljava/lang/Object;)Z
   #81 = NameAndType        #79:#80       // equals:(Ljava/lang/Object;)Z
   #82 = Methodref          #4.#81        // java/lang/Object.equals:(Ljava/lang/Object;)Z
   #83 = Utf8               scala/Function0
   #84 = Class              #83           // scala/Function0
   #85 = Utf8               apply
   #86 = NameAndType        #85:#24       // apply:()Ljava/lang/Object;
   #87 = InterfaceMethodref #84.#86       // scala/Function0.apply:()Ljava/lang/Object;
   #88 = Utf8               Lscala/Option;
   #89 = Utf8               Lscala/Function0;
   #90 = Utf8               scala/Option
   #91 = Class              #90           // scala/Option
   #92 = Utf8               writeReplace
   #93 = Utf8               scala/runtime/ModuleSerializationProxy
   #94 = Class              #93           // scala/runtime/ModuleSerializationProxy
   #95 = Utf8               (Ljava/lang/Class;)V
   #96 = NameAndType        #12:#95       // "<init>":(Ljava/lang/Class;)V
   #97 = Methodref          #94.#96       // scala/runtime/ModuleSerializationProxy."<init>":(Ljava/lang/Class;)V
   #98 = Methodref          #4.#13        // java/lang/Object."<init>":()V
   #99 = Utf8               Code
  #100 = Utf8               LineNumberTable
  #101 = Utf8               StackMapTable
  #102 = Utf8               LocalVariableTable
  #103 = Utf8               Signature
  #104 = Utf8               MethodParameters
  #105 = Utf8               SourceFile
  #106 = Utf8               ScalaInlineInfo
  #107 = Utf8               Scala
{
  public static final org.scalactic.Or$ MODULE$;
    descriptor: Lorg/scalactic/Or$;
    flags: (0x0019) ACC_PUBLIC, ACC_STATIC, ACC_FINAL

  public static {};
    descriptor: ()V
    flags: (0x0009) ACC_PUBLIC, ACC_STATIC
    Code:
      stack=2, locals=0, args_size=0
         0: new           #2                  // class org/scalactic/Or$
         3: dup
         4: invokespecial #14                 // Method "<init>":()V
         7: putstatic     #16                 // Field MODULE$:Lorg/scalactic/Or$;
        10: return
      LineNumberTable:
        line 860: 0

  public <G extends java.lang.Object> org.scalactic.Or<G, java.lang.Throwable> from(scala.util.Try<G>);
    descriptor: (Lscala/util/Try;)Lorg/scalactic/Or;
    flags: (0x0001) ACC_PUBLIC
    Code:
      stack=3, locals=8, args_size=2
         0: aload_1
         1: astore_3
         2: aload_3
         3: instanceof    #22                 // class scala/util/Success
         6: ifeq          35
         9: aload_3
        10: checkcast     #22                 // class scala/util/Success
        13: astore        4
        15: aload         4
        17: invokevirtual #26                 // Method scala/util/Success.value:()Ljava/lang/Object;
        20: astore        5
        22: new           #28                 // class org/scalactic/Good
        25: dup
        26: aload         5
        28: invokespecial #31                 // Method org/scalactic/Good."<init>":(Ljava/lang/Object;)V
        31: astore_2
        32: goto          83
        35: goto          38
        38: aload_3
        39: instanceof    #33                 // class scala/util/Failure
        42: ifeq          71
        45: aload_3
        46: checkcast     #33                 // class scala/util/Failure
        49: astore        6
        51: aload         6
        53: invokevirtual #37                 // Method scala/util/Failure.exception:()Ljava/lang/Throwable;
        56: astore        7
        58: new           #39                 // class org/scalactic/Bad
        61: dup
        62: aload         7
        64: invokespecial #40                 // Method org/scalactic/Bad."<init>":(Ljava/lang/Object;)V
        67: astore_2
        68: goto          83
        71: goto          74
        74: new           #42                 // class scala/MatchError
        77: dup
        78: aload_3
        79: invokespecial #43                 // Method scala/MatchError."<init>":(Ljava/lang/Object;)V
        82: athrow
        83: aload_2
        84: areturn
      StackMapTable: number_of_entries = 5
        frame_type = 253 /* append */
          offset_delta = 35
          locals = [ top, class scala/util/Try ]
        frame_type = 2 /* same */
        frame_type = 32 /* same */
        frame_type = 2 /* same */
        frame_type = 255 /* full_frame */
          offset_delta = 8
          locals = [ class org/scalactic/Or$, class scala/util/Try, class org/scalactic/Or, class scala/util/Try ]
          stack = []
      LineNumberTable:
        line 1054: 0
        line 1055: 2
        line 1056: 38
        line 1054: 74
      LocalVariableTable:
        Start  Length  Slot  Name   Signature
           22      13     5     g   Ljava/lang/Object;
           58      13     7     e   Ljava/lang/Throwable;
            0      85     0  this   Lorg/scalactic/Or$;
            0      85     1 theTry   Lscala/util/Try;
    Signature: #19                          // <G:Ljava/lang/Object;>(Lscala/util/Try<TG;>;)Lorg/scalactic/Or<TG;Ljava/lang/Throwable;>;
    MethodParameters:
      Name                           Flags
      theTry                         final

  public <B extends java.lang.Object, G extends java.lang.Object> org.scalactic.Or<G, B> from(scala.util.Either<B, G>);
    descriptor: (Lscala/util/Either;)Lorg/scalactic/Or;
    flags: (0x0001) ACC_PUBLIC
    Code:
      stack=3, locals=8, args_size=2
         0: aload_1
         1: astore_3
         2: aload_3
         3: instanceof    #58                 // class scala/util/Right
         6: ifeq          35
         9: aload_3
        10: checkcast     #58                 // class scala/util/Right
        13: astore        4
        15: aload         4
        17: invokevirtual #59                 // Method scala/util/Right.value:()Ljava/lang/Object;
        20: astore        5
        22: new           #28                 // class org/scalactic/Good
        25: dup
        26: aload         5
        28: invokespecial #31                 // Method org/scalactic/Good."<init>":(Ljava/lang/Object;)V
        31: astore_2
        32: goto          83
        35: goto          38
        38: aload_3
        39: instanceof    #61                 // class scala/util/Left
        42: ifeq          71
        45: aload_3
        46: checkcast     #61                 // class scala/util/Left
        49: astore        6
        51: aload         6
        53: invokevirtual #62                 // Method scala/util/Left.value:()Ljava/lang/Object;
        56: astore        7
        58: new           #39                 // class org/scalactic/Bad
        61: dup
        62: aload         7
        64: invokespecial #40                 // Method org/scalactic/Bad."<init>":(Ljava/lang/Object;)V
        67: astore_2
        68: goto          83
        71: goto          74
        74: new           #42                 // class scala/MatchError
        77: dup
        78: aload_3
        79: invokespecial #43                 // Method scala/MatchError."<init>":(Ljava/lang/Object;)V
        82: athrow
        83: aload_2
        84: areturn
      StackMapTable: number_of_entries = 5
        frame_type = 253 /* append */
          offset_delta = 35
          locals = [ top, class scala/util/Either ]
        frame_type = 2 /* same */
        frame_type = 32 /* same */
        frame_type = 2 /* same */
        frame_type = 255 /* full_frame */
          offset_delta = 8
          locals = [ class org/scalactic/Or$, class scala/util/Either, class org/scalactic/Or, class scala/util/Either ]
          stack = []
      LineNumberTable:
        line 1075: 0
        line 1076: 2
        line 1077: 38
        line 1075: 74
      LocalVariableTable:
        Start  Length  Slot  Name   Signature
           22      13     5     g   Ljava/lang/Object;
           58      13     7     b   Ljava/lang/Object;
            0      85     0  this   Lorg/scalactic/Or$;
            0      85     1 either   Lscala/util/Either;
    Signature: #55                          // <B:Ljava/lang/Object;G:Ljava/lang/Object;>(Lscala/util/Either<TB;TG;>;)Lorg/scalactic/Or<TG;TB;>;
    MethodParameters:
      Name                           Flags
      either                         final

  public <G extends java.lang.Object, B extends java.lang.Object> org.scalactic.Or<G, B> from(scala.Option<G>, scala.Function0<B>);
    descriptor: (Lscala/Option;Lscala/Function0;)Lorg/scalactic/Or;
    flags: (0x0001) ACC_PUBLIC
    Code:
      stack=3, locals=7, args_size=3
         0: aload_1
         1: astore        4
         3: aload         4
         5: instanceof    #72                 // class scala/Some
         8: ifeq          38
        11: aload         4
        13: checkcast     #72                 // class scala/Some
        16: astore        5
        18: aload         5
        20: invokevirtual #73                 // Method scala/Some.value:()Ljava/lang/Object;
        23: astore        6
        25: new           #28                 // class org/scalactic/Good
        28: dup
        29: aload         6
        31: invokespecial #31                 // Method org/scalactic/Good."<init>":(Ljava/lang/Object;)V
        34: astore_3
        35: goto          82
        38: goto          41
        41: getstatic     #78                 // Field scala/None$.MODULE$:Lscala/None$;
        44: aload         4
        46: invokevirtual #82                 // Method java/lang/Object.equals:(Ljava/lang/Object;)Z
        49: ifeq          69
        52: new           #39                 // class org/scalactic/Bad
        55: dup
        56: aload_2
        57: invokeinterface #87,  1           // InterfaceMethod scala/Function0.apply:()Ljava/lang/Object;
        62: invokespecial #40                 // Method org/scalactic/Bad."<init>":(Ljava/lang/Object;)V
        65: astore_3
        66: goto          82
        69: goto          72
        72: new           #42                 // class scala/MatchError
        75: dup
        76: aload         4
        78: invokespecial #43                 // Method scala/MatchError."<init>":(Ljava/lang/Object;)V
        81: athrow
        82: aload_3
        83: areturn
      StackMapTable: number_of_entries = 5
        frame_type = 253 /* append */
          offset_delta = 38
          locals = [ top, class scala/Option ]
        frame_type = 2 /* same */
        frame_type = 27 /* same */
        frame_type = 2 /* same */
        frame_type = 255 /* full_frame */
          offset_delta = 9
          locals = [ class org/scalactic/Or$, class scala/Option, class scala/Function0, class org/scalactic/Or, class scala/Option ]
          stack = []
      LineNumberTable:
        line 1089: 0
        line 1090: 3
        line 1091: 41
        line 1089: 72
      LocalVariableTable:
        Start  Length  Slot  Name   Signature
           25      13     6     g   Ljava/lang/Object;
            0      84     0  this   Lorg/scalactic/Or$;
            0      84     1 option   Lscala/Option;
            0      84     2 orElse   Lscala/Function0;
    Signature: #68                          // <G:Ljava/lang/Object;B:Ljava/lang/Object;>(Lscala/Option<TG;>;Lscala/Function0<TB;>;)Lorg/scalactic/Or<TG;TB;>;
    MethodParameters:
      Name                           Flags
      option                         final
      orElse                         final

  private java.lang.Object writeReplace();
    descriptor: ()Ljava/lang/Object;
    flags: (0x0002) ACC_PRIVATE
    Code:
      stack=3, locals=1, args_size=1
         0: new           #94                 // class scala/runtime/ModuleSerializationProxy
         3: dup
         4: ldc           #2                  // class org/scalactic/Or$
         6: invokespecial #97                 // Method scala/runtime/ModuleSerializationProxy."<init>":(Ljava/lang/Class;)V
         9: areturn
      LineNumberTable:
        line 860: 0
      LocalVariableTable:
        Start  Length  Slot  Name   Signature
            0      10     0  this   Lorg/scalactic/Or$;

  private org.scalactic.Or$();
    descriptor: ()V
    flags: (0x0002) ACC_PRIVATE
    Code:
      stack=1, locals=1, args_size=1
         0: aload_0
         1: invokespecial #98                 // Method java/lang/Object."<init>":()V
         4: return
      LineNumberTable:
        line 1105: 0
        line 860: 4
      LocalVariableTable:
        Start  Length  Slot  Name   Signature
            0       5     0  this   Lorg/scalactic/Or$;
}
SourceFile: "Or.scala"
  ScalaInlineInfo: length = 0x1D (unknown attribute)
   01 01 00 05 00 0C 00 0B 01 00 11 00 43 01 00 11
   00 36 01 00 11 00 12 01 00 5C 00 18 01
  Scala: length = 0x0 (unknown attribute)

