Classfile /Users/mw/Projects/slang-braindump/.jar/jar11/assemble/slang-braindump/assemble/content/org/scalactic/Or.class
  Last modified May 29, 2022; size 8534 bytes
  SHA-256 checksum 3c4f820ee76b109bdfb2e689553c16c782bb6204553837c8765a181a9c4f6094
  Compiled from "Or.scala"
public abstract class org.scalactic.Or<G extends java.lang.Object, B extends java.lang.Object> extends java.lang.Object implements scala.Product, java.io.Serializable
  minor version: 0
  major version: 52
  flags: (0x0421) ACC_PUBLIC, ACC_SUPER, ACC_ABSTRACT
  this_class: #2                          // org/scalactic/Or
  super_class: #5                         // java/lang/Object
  interfaces: 2, fields: 2, methods: 32, attributes: 6
Constant pool:
    #1 = Utf8               org/scalactic/Or
    #2 = Class              #1            // org/scalactic/Or
    #3 = Utf8               <G:Ljava/lang/Object;B:Ljava/lang/Object;>Ljava/lang/Object;Lscala/Product;Ljava/io/Serializable;
    #4 = Utf8               java/lang/Object
    #5 = Class              #4            // java/lang/Object
    #6 = Utf8               scala/Product
    #7 = Class              #6            // scala/Product
    #8 = Utf8               java/io/Serializable
    #9 = Class              #8            // java/io/Serializable
   #10 = Utf8               Or.scala
   #11 = Utf8               Lscala/reflect/ScalaSignature;
   #12 = Utf8               bytes
   #13 = Utf8               \u0006\u0005\t\u0015g!B\u0014)\u0003Ci\u0003\"\u0002#\u0001\t\u0003)\u0005b\u0002,\u0001\u0005\u0004%\ta\u0016\u0005\u00077\u0002\u0001\u000b\u0011\u0002-\t\u000fq\u0003!\u0019!C\u0001/\"1Q\f\u0001Q\u0001\naCQA\u0018\u0001\u0007\u0002}CQ\u0001\u0019\u0001\u0007\u0002\u0005DQ\u0001\u001c\u0001\u0007\u00025DQ!\u001e\u0001\u0007\u0002YDQA \u0001\u0007\u0002}Dq!!\u0005\u0001\r\u0003\t\u0019\u0002C\u0004\u0002 \u00011\t!!\t\t\u000f\u0005U\u0002A\"\u0001\u00028!9\u00111\n\u0001\u0005\u0002\u00055\u0003bBA/\u0001\u0019\u0005\u0011q\f\u0005\b\u0003O\u0002a\u0011AA5\u0011\u001d\ti\u0007\u0001D\u0001\u0003_Bq!!!\u0001\r\u0003\t\u0019\tC\u0004\u0002\u0018\u00021\t!!\'\t\u000f\u0005\u0005\u0006A\"\u0001\u0002$\"9\u0011Q\u0017\u0001\u0007\u0002\u0005]\u0006bBA`\u0001\u0019\u0005\u0011\u0011\u0019\u0005\b\u0003\u0017\u0004a\u0011AAg\u0011\u001d\tY\u000f\u0001D\u0001\u0003[Dq!!=\u0001\r\u0003\t\u0019\u0010C\u0004\u0003\u000e\u00011\tAa\u0004\t\u000f\t\u0005\u0002\u0001\"\u0001\u0003$\u001d9!Q\b\u0015\t\u0002\t}bAB\u0014)\u0011\u0003\u0011\t\u0005\u0003\u0004E;\u0011\u0005!\u0011\u000b\u0004\n+v\u0001\n1%\u0001)\u0005\'*QaS\u0010\u0001\u0005/2\u0011bS\u000f\u0011\u0002G\u0005\u0001Fa\u001a\u0006\u000bU\u000b\u0003Aa\u001b\t\u000f\t]T\u0004\"\u0001\u0003z!9!qO\u000f\u0005\u0002\t%\u0005b\u0002B<;\u0011\u0005!Q\u0014\u0005\n\u0005kk\u0012\u0011!C\u0005\u0005o\u0013!a\u0014:\u000b\u0005%R\u0013!C:dC2\f7\r^5d\u0015\u0005Y\u0013aA8sO\u000e\u0001Qc\u0001\u0018K)N!\u0001aL\u001b9!\t\u00014\'D\u00012\u0015\u0005\u0011\u0014!B:dC2\f\u0017B\u0001\u001b2\u0005\u0019\te.\u001f*fMB\u0011\u0001GN\u0005\u0003oE\u0012q\u0001\u0015:pIV\u001cG\u000f\u0005\u0002:\u0003:\u0011!h\u0010\b\u0003wyj\u0011\u0001\u0010\u0006\u0003{1\na\u0001\u0010:p_Rt\u0014\"\u0001\u001a\n\u0005\u0001\u000b\u0014a\u00029bG.\fw-Z\u0005\u0003\u0005\u000e\u0013AbU3sS\u0006d\u0017N_1cY\u0016T!\u0001Q\u0019\u0002\rqJg.\u001b;?)\u00051\u0005\u0003B$\u0001\u0011Nk\u0011\u0001\u000b\t\u0003\u0013*c\u0001\u0001\u0002\u0004L\u0001\u0011\u0015\r\u0001\u0014\u0002\u0002\u000fF\u0011Q\n\u0015\t\u0003a9K!aT\u0019\u0003\u000f9{G\u000f[5oOB\u0011\u0001\'U\u0005\u0003%F\u00121!\u00118z!\tIE\u000b\u0002\u0004V\u0001\u0011\u0015\r\u0001\u0014\u0002\u0002\u0005\u00061\u0011n]$p_\u0012,\u0012\u0001\u0017\t\u0003aeK!AW\u0019\u0003\u000f\t{w\u000e\\3b]\u00069\u0011n]$p_\u0012\u0004\u0013!B5t\u0005\u0006$\u0017AB5t\u0005\u0006$\u0007%A\u0002hKR,\u0012\u0001S\u0001\u0004[\u0006\u0004XC\u00012f)\t\u0019w\r\u0005\u0003H\u0001\u0011\u001c\u0006CA%f\t\u00151wA1\u0001M\u0005\u0005A\u0005\"\u00025\b\u0001\u0004I\u0017!\u00014\u0011\tAR\u0007\nZ\u0005\u0003WF\u0012\u0011BR;oGRLwN\\\u0019\u0002\r\t\fG-T1q+\tq\u0017\u000f\u0006\u0002pgB!q\t\u0001%q!\tI\u0015\u000fB\u0003s\u0011\t\u0007AJA\u0001D\u0011\u0015A\u0007\u00021\u0001u!\u0011\u0001$n\u00159\u0002\u000fI,7m\u001c<feV\u0011qO\u001f\u000b\u0003qr\u0004Ba\u0012\u0001z\'B\u0011\u0011J\u001f\u0003\u0006M&\u0011\ra_\t\u0003\u0011BCQ\u0001[\u0005A\u0002u\u0004B\u0001\r6Ts\u0006Y!/Z2pm\u0016\u0014x+\u001b;i+\u0019\t\t!a\u0002\u0002\fQ!\u00111AA\u0007!\u00199\u0005!!\u0002\u0002\nA\u0019\u0011*a\u0002\u0005\u000b\u0019T!\u0019A>\u0011\u0007%\u000bY\u0001B\u0003s\u0015\t\u0007A\n\u0003\u0004i\u0015\u0001\u0007\u0011q\u0002\t\u0006a)\u001c\u00161A\u0001\bM>\u0014X-Y2i)\u0011\t)\"a\u0007\u0011\u0007A\n9\"C\u0002\u0002\u001aE\u0012A!\u00168ji\"1\u0001n\u0003a\u0001\u0003;\u0001R\u0001\r6I\u0003+\tqA\u001a7bi6\u000b\u0007/\u0006\u0004\u0002$\u0005%\u0012Q\u0006\u000b\u0005\u0003K\t\t\u0004\u0005\u0004H\u0001\u0005\u001d\u00121\u0006\t\u0004\u0013\u0006%B!\u00024\r\u0005\u0004a\u0005cA%\u0002.\u00111!\u000f\u0004b\u0001\u0003_\t\"a\u0015)\t\r!d\u0001\u0019AA\u001a!\u0015\u0001$\u000eSA\u0013\u0003\u00191\u0017\u000e\u001c;feV!\u0011\u0011HA )\u0011\tY$!\u0011\u0011\u000b\u001d\u0003\u0001*!\u0010\u0011\u0007%\u000by\u0004\u0002\u0004s\u001b\t\u0007\u0011q\u0006\u0005\u0007Q6\u0001\r!a\u0011\u0011\u000bAR\u0007*!\u0012\u0011\u000b\u001d\u000b9%!\u0010\n\u0007\u0005%\u0003F\u0001\u0006WC2LG-\u0019;j_:\f!b^5uQ\u001aKG\u000e^3s+\u0011\ty%!\u0016\u0015\t\u0005E\u0013q\u000b\t\u0006\u000f\u0002A\u00151\u000b\t\u0004\u0013\u0006UCA\u0002:\u000f\u0005\u0004\ty\u0003\u0003\u0004i\u001d\u0001\u0007\u0011\u0011\f\t\u0006a)D\u00151\f\t\u0006\u000f\u0006\u001d\u00131K\u0001\u0007KbL7\u000f^:\u0015\u0007a\u000b\t\u0007C\u0004\u0002d=\u0001\r!!\u001a\u0002\u0003A\u0004B\u0001\r6I1\u00061am\u001c:bY2$2\u0001WA6\u0011\u0019A\u0007\u00031\u0001\u0002f\u0005Iq-\u001a;Pe\u0016c7/Z\u000b\u0005\u0003c\n)\b\u0006\u0003\u0002t\u0005]\u0004cA%\u0002v\u0011)a-\u0005b\u0001w\"A\u0011\u0011P\t\u0005\u0002\u0004\tY(A\u0004eK\u001a\fW\u000f\u001c;\u0011\u000bA\ni(a\u001d\n\u0007\u0005}\u0014G\u0001\u0005=Eft\u0017-\\3?\u0003\u0019y\'/\u00127tKV1\u0011QQAF\u0003\u001f#B!a\"\u0002\u0012B1q\tAAE\u0003\u001b\u00032!SAF\t\u00151\'C1\u0001|!\rI\u0015q\u0012\u0003\u0007eJ\u0011\r!a\f\t\u0011\u0005M%\u0003\"a\u0001\u0003+\u000b1\"\u00197uKJt\u0017\r^5wKB)\u0001\'! \u0002\b\u0006AAo\\(qi&|g.\u0006\u0002\u0002\u001cB!\u0001\'!(I\u0013\r\ty*\r\u0002\u0007\u001fB$\u0018n\u001c8\u0002\u000bQ|7+Z9\u0016\u0005\u0005\u0015\u0006#BAT\u0003cCUBAAU\u0015\u0011\tY+!,\u0002\u0013%lW.\u001e;bE2,\'bAAXc\u0005Q1m\u001c7mK\u000e$\u0018n\u001c8\n\t\u0005M\u0016\u0011\u0016\u0002\u000b\u0013:$W\r_3e\'\u0016\f\u0018\u0001\u0003;p\u000b&$\b.\u001a:\u0016\u0005\u0005e\u0006#B\u001d\u0002<NC\u0015bAA_\u0007\n1Q)\u001b;iKJ\fA\"Y2dk6,H.\u0019;j]\u001e,\"!a1\u0011\u000b\u001d\u0003\u0001*!2\u0011\t\u001d\u000b9mU\u0005\u0004\u0003\u0013D#aA(oK\u0006)Ao\u001c+ssR!\u0011qZAn!\u0015\t\t.a6I\u001b\t\t\u0019NC\u0002\u0002VF\nA!\u001e;jY&!\u0011\u0011\\Aj\u0005\r!&/\u001f\u0005\b\u0003;<\u00029AAp\u0003\t)g\u000f\u0005\u00041\u0003C\u001c\u0016Q]\u0005\u0004\u0003G\f$\u0001\u0005\u0013mKN\u001cHeY8m_:$C.Z:t!\rI\u0014q]\u0005\u0004\u0003S\u001c%!\u0003+ie><\u0018M\u00197f\u0003\u0011\u0019x/\u00199\u0016\u0005\u0005=\b\u0003B$\u0001\'\"\u000b\u0011\u0002\u001e:b]N4wN]7\u0016\r\u0005U\u00181`A\u0000)\u0019\t9P!\u0001\u0003\bA1q\tAA}\u0003{\u00042!SA~\t\u00151\u0017D1\u0001M!\rI\u0015q \u0003\u0006ef\u0011\r\u0001\u0014\u0005\b\u0005\u0007I\u0002\u0019\u0001B\u0003\u0003\t9g\rE\u00031U\"\u000b9\u0010C\u0004\u0003\ne\u0001\rAa\u0003\u0002\u0005\t4\u0007#\u0002\u0019k\'\u0006]\u0018\u0001\u00024pY\u0012,BA!\u0005\u0003\u0016Q1!1\u0003B\r\u0005;\u00012!\u0013B\u000b\t\u0019\u00119B\u0007b\u0001\u0019\n\ta\u000bC\u0004\u0003\u0004i\u0001\rAa\u0007\u0011\u000bAR\u0007Ja\u0005\t\u000f\t%!\u00041\u0001\u0003 A)\u0001G[*\u0003\u0014\u0005!\u0011m](s+\u00051\u0005fB\u000e\u0003(\t5\"q\u0006\t\u0004a\t%\u0012b\u0001B\u0016c\tQA-\u001a9sK\u000e\fG/\u001a3\u0002\u000f5,7o]1hK\u0006\u0012!\u0011G\u0001\u0002vRCW\rI1t\u001fJ\u0004\u0013n\u001d\u0011o_\u0002bwN\\4fe\u0002rW-\u001a3fI\u0002\u0012WmY1vg\u0016\u0004si\\8eQY\fG.^3*]=\u0014()\u00193\\)f\u0004X-\u0018\u0011b]\u0012\u0004si\\8e7RK\b/Z//_J\u0014\u0015\r\u001a\u0015wC2,X-\u000b\u0011o_^\u0004#/\u001a;ve:\u0004sJ\u001d\u0018!3>,\beY1oA\u0011,G.\u001a;fA%tgo\\2bi&|gn\u001d\u0011pM\u0002\n7o\u0014:!S:\u0004C\u000f[8tK\u0002\u001a\u0017m]3tY\u0001zG\u000f[3so&\u001cX\r\f\u0011qY\u0016\f7/\u001a\u0011vg\u0016\u0004\u0013\r\t;za\u0016\u0004\u0013M\u001c8pi\u0006$\u0018n\u001c8!i>\u0004s/\u001b3f]\u0002\"\b.\u001a\u0011usB,G\u0006\t7jW\u0016\u0004\u0003fR8pI\"\u001a\u0014F\u000f\u0011J]R\u0004sJ\u001d\u0011FeJ|\'/T3tg\u0006<W-\u000b\u0018*\u000b\u0001\u0011)D!\u000f\n\u0007\t]\u0002FA\u0002CC\u0012L1Aa\u000f)\u0005\u00119un\u001c3\u0002\u0005=\u0013\bCA$\u001e\'\u0011irFa\u0011\u0011\t\t\u0015#qJ\u0007\u0003\u0005\u000fRAA!\u0013\u0003L\u0005\u0011\u0011n\u001c\u0006\u0003\u0005\u001b\nAA[1wC&\u0019!Ia\u0012\u0015\u0005\t}R\u0003\u0002B+\u0005G\u001a\"aH\u0018\u0016\t\te#Q\f\t\u0007\u000f\u0002\u0011YF!\u0019\u0011\u0007%\u0013i\u0006\u0002\u0004\u0003`\u0001\u0012\r\u0001\u0014\u0002\u0005\u000f>{E\tE\u0002J\u0005G\"aA!\u001a \u0005\u0004a%a\u0001\"B\tV!!\u0011\u000eB9\'\t\ts&\u0006\u0003\u0003n\tU\u0004CB$\u0001\u0005_\u0012\u0019\bE\u0002J\u0005c\"aAa\u0018\"\u0005\u0004a\u0005cA%\u0003v\u00111!Q\r\u0012C\u00021\u000bAA\u001a:p[V!!1\u0010BA)\u0011\u0011iHa!\u0011\r\u001d\u0003!qPAs!\rI%\u0011\u0011\u0003\u0006\u0017\u000e\u0012\r\u0001\u0014\u0005\b\u0005\u000b\u001b\u0003\u0019\u0001BD\u0003\u0019!\b.\u001a+ssB1\u0011\u0011[Al\u0005\u007f*bAa#\u0003\u0016\nEE\u0003\u0002BG\u0005/\u0003ba\u0012\u0001\u0003\u0010\nM\u0005cA%\u0003\u0012\u0012)1\n\nb\u0001\u0019B\u0019\u0011J!&\u0005\u000bU##\u0019\u0001\'\t\u000f\teE\u00051\u0001\u0003\u001c\u00061Q-\u001b;iKJ\u0004r!OA^\u0005\'\u0013y)\u0006\u0004\u0003 \n\u0015&\u0011\u0016\u000b\u0007\u0005C\u0013YK!-\u0011\r\u001d\u0003!1\u0015BT!\rI%Q\u0015\u0003\u0006\u0017\u0016\u0012\r\u0001\u0014\t\u0004\u0013\n%F!B+&\u0005\u0004a\u0005b\u0002BWK\u0001\u0007!qV\u0001\u0007_B$\u0018n\u001c8\u0011\u000bA\niJa)\t\u0011\u0005\u0005U\u0005\"a\u0001\u0005g\u0003R\u0001MA?\u0005O\u000bAb\u001e:ji\u0016\u0014V\r\u001d7bG\u0016$\"A!/\u0011\t\tm&\u0011Y\u0007\u0003\u0005{SAAa0\u0003L\u0005!A.\u00198h\u0013\u0011\u0011\u0019M!0\u0003\r=\u0013\'.Z2u\u0001
   #14 = Utf8               org/scalactic/Or$B
   #15 = Class              #14           // org/scalactic/Or$B
   #16 = Utf8               B
   #17 = Utf8               org/scalactic/Or$G
   #18 = Class              #17           // org/scalactic/Or$G
   #19 = Utf8               G
   #20 = Utf8               isGood
   #21 = Utf8               Z
   #22 = Utf8               isBad
   #23 = Utf8               from
   #24 = Utf8               (Lscala/Option;Lscala/Function0;)Lorg/scalactic/Or;
   #25 = Utf8               <G:Ljava/lang/Object;B:Ljava/lang/Object;>(Lscala/Option<TG;>;Lscala/Function0<TB;>;)Lorg/scalactic/Or<TG;TB;>;
   #26 = Utf8               option
   #27 = Utf8               orElse
   #28 = Utf8               org/scalactic/Or$
   #29 = Class              #28           // org/scalactic/Or$
   #30 = Utf8               MODULE$
   #31 = Utf8               Lorg/scalactic/Or$;
   #32 = NameAndType        #30:#31       // MODULE$:Lorg/scalactic/Or$;
   #33 = Fieldref           #29.#32       // org/scalactic/Or$.MODULE$:Lorg/scalactic/Or$;
   #34 = NameAndType        #23:#24       // from:(Lscala/Option;Lscala/Function0;)Lorg/scalactic/Or;
   #35 = Methodref          #29.#34       // org/scalactic/Or$.from:(Lscala/Option;Lscala/Function0;)Lorg/scalactic/Or;
   #36 = Utf8               Lscala/Option;
   #37 = Utf8               Lscala/Function0;
   #38 = Utf8               (Lscala/util/Either;)Lorg/scalactic/Or;
   #39 = Utf8               <B:Ljava/lang/Object;G:Ljava/lang/Object;>(Lscala/util/Either<TB;TG;>;)Lorg/scalactic/Or<TG;TB;>;
   #40 = Utf8               either
   #41 = NameAndType        #23:#38       // from:(Lscala/util/Either;)Lorg/scalactic/Or;
   #42 = Methodref          #29.#41       // org/scalactic/Or$.from:(Lscala/util/Either;)Lorg/scalactic/Or;
   #43 = Utf8               Lscala/util/Either;
   #44 = Utf8               (Lscala/util/Try;)Lorg/scalactic/Or;
   #45 = Utf8               <G:Ljava/lang/Object;>(Lscala/util/Try<TG;>;)Lorg/scalactic/Or<TG;Ljava/lang/Throwable;>;
   #46 = Utf8               theTry
   #47 = NameAndType        #23:#44       // from:(Lscala/util/Try;)Lorg/scalactic/Or;
   #48 = Methodref          #29.#47       // org/scalactic/Or$.from:(Lscala/util/Try;)Lorg/scalactic/Or;
   #49 = Utf8               Lscala/util/Try;
   #50 = Utf8               productIterator
   #51 = Utf8               ()Lscala/collection/Iterator;
   #52 = Utf8               ()Lscala/collection/Iterator<Ljava/lang/Object;>;
   #53 = Utf8               productIterator$
   #54 = Utf8               (Lscala/Product;)Lscala/collection/Iterator;
   #55 = NameAndType        #53:#54       // productIterator$:(Lscala/Product;)Lscala/collection/Iterator;
   #56 = InterfaceMethodref #7.#55        // scala/Product.productIterator$:(Lscala/Product;)Lscala/collection/Iterator;
   #57 = Utf8               this
   #58 = Utf8               Lorg/scalactic/Or;
   #59 = Utf8               productPrefix
   #60 = Utf8               ()Ljava/lang/String;
   #61 = Utf8               productPrefix$
   #62 = Utf8               (Lscala/Product;)Ljava/lang/String;
   #63 = NameAndType        #61:#62       // productPrefix$:(Lscala/Product;)Ljava/lang/String;
   #64 = InterfaceMethodref #7.#63        // scala/Product.productPrefix$:(Lscala/Product;)Ljava/lang/String;
   #65 = Utf8               productElementName
   #66 = Utf8               (I)Ljava/lang/String;
   #67 = Utf8               n
   #68 = Utf8               productElementName$
   #69 = Utf8               (Lscala/Product;I)Ljava/lang/String;
   #70 = NameAndType        #68:#69       // productElementName$:(Lscala/Product;I)Ljava/lang/String;
   #71 = InterfaceMethodref #7.#70        // scala/Product.productElementName$:(Lscala/Product;I)Ljava/lang/String;
   #72 = Utf8               I
   #73 = Utf8               productElementNames
   #74 = Utf8               ()Lscala/collection/Iterator<Ljava/lang/String;>;
   #75 = Utf8               productElementNames$
   #76 = NameAndType        #75:#54       // productElementNames$:(Lscala/Product;)Lscala/collection/Iterator;
   #77 = InterfaceMethodref #7.#76        // scala/Product.productElementNames$:(Lscala/Product;)Lscala/collection/Iterator;
   #78 = Utf8               ()Z
   #79 = NameAndType        #20:#21       // isGood:Z
   #80 = Fieldref           #2.#79        // org/scalactic/Or.isGood:Z
   #81 = NameAndType        #22:#21       // isBad:Z
   #82 = Fieldref           #2.#81        // org/scalactic/Or.isBad:Z
   #83 = Utf8               get
   #84 = Utf8               ()Ljava/lang/Object;
   #85 = Utf8               ()TG;
   #86 = Utf8               map
   #87 = Utf8               (Lscala/Function1;)Lorg/scalactic/Or;
   #88 = Utf8               <H:Ljava/lang/Object;>(Lscala/Function1<TG;TH;>;)Lorg/scalactic/Or<TH;TB;>;
   #89 = Utf8               f
   #90 = Utf8               badMap
   #91 = Utf8               <C:Ljava/lang/Object;>(Lscala/Function1<TB;TC;>;)Lorg/scalactic/Or<TG;TC;>;
   #92 = Utf8               recover
   #93 = Utf8               <H:Ljava/lang/Object;>(Lscala/Function1<TB;TH;>;)Lorg/scalactic/Or<TH;TB;>;
   #94 = Utf8               recoverWith
   #95 = Utf8               <H:Ljava/lang/Object;C:Ljava/lang/Object;>(Lscala/Function1<TB;Lorg/scalactic/Or<TH;TC;>;>;)Lorg/scalactic/Or<TH;TC;>;
   #96 = Utf8               foreach
   #97 = Utf8               (Lscala/Function1;)V
   #98 = Utf8               (Lscala/Function1<TG;Lscala/runtime/BoxedUnit;>;)V
   #99 = Utf8               flatMap
  #100 = Utf8               <H:Ljava/lang/Object;C:Ljava/lang/Object;>(Lscala/Function1<TG;Lorg/scalactic/Or<TH;TC;>;>;)Lorg/scalactic/Or<TH;TC;>;
  #101 = Utf8               filter
  #102 = Utf8               <C:Ljava/lang/Object;>(Lscala/Function1<TG;Lorg/scalactic/Validation<TC;>;>;)Lorg/scalactic/Or<TG;TC;>;
  #103 = Utf8               withFilter
  #104 = NameAndType        #101:#87      // filter:(Lscala/Function1;)Lorg/scalactic/Or;
  #105 = Methodref          #2.#104       // org/scalactic/Or.filter:(Lscala/Function1;)Lorg/scalactic/Or;
  #106 = Utf8               Lscala/Function1;
  #107 = Utf8               exists
  #108 = Utf8               (Lscala/Function1;)Z
  #109 = Utf8               (Lscala/Function1<TG;Ljava/lang/Object;>;)Z
  #110 = Utf8               p
  #111 = Utf8               forall
  #112 = Utf8               getOrElse
  #113 = Utf8               (Lscala/Function0;)Ljava/lang/Object;
  #114 = Utf8               <H:Ljava/lang/Object;>(Lscala/Function0<TH;>;)TH;
  #115 = Utf8               default
  #116 = Utf8               (Lscala/Function0;)Lorg/scalactic/Or;
  #117 = Utf8               <H:Ljava/lang/Object;C:Ljava/lang/Object;>(Lscala/Function0<Lorg/scalactic/Or<TH;TC;>;>;)Lorg/scalactic/Or<TH;TC;>;
  #118 = Utf8               alternative
  #119 = Utf8               toOption
  #120 = Utf8               ()Lscala/Option;
  #121 = Utf8               ()Lscala/Option<TG;>;
  #122 = Utf8               toSeq
  #123 = Utf8               ()Lscala/collection/immutable/IndexedSeq;
  #124 = Utf8               ()Lscala/collection/immutable/IndexedSeq<TG;>;
  #125 = Utf8               toEither
  #126 = Utf8               ()Lscala/util/Either;
  #127 = Utf8               ()Lscala/util/Either<TB;TG;>;
  #128 = Utf8               accumulating
  #129 = Utf8               ()Lorg/scalactic/Or;
  #130 = Utf8               ()Lorg/scalactic/Or<TG;Lorg/scalactic/One<TB;>;>;
  #131 = Utf8               toTry
  #132 = Utf8               (Lscala/$less$colon$less;)Lscala/util/Try;
  #133 = Utf8               (Lscala/$less$colon$less<TB;Ljava/lang/Throwable;>;)Lscala/util/Try<TG;>;
  #134 = Utf8               ev
  #135 = Utf8               swap
  #136 = Utf8               ()Lorg/scalactic/Or<TB;TG;>;
  #137 = Utf8               transform
  #138 = Utf8               (Lscala/Function1;Lscala/Function1;)Lorg/scalactic/Or;
  #139 = Utf8               <H:Ljava/lang/Object;C:Ljava/lang/Object;>(Lscala/Function1<TG;Lorg/scalactic/Or<TH;TC;>;>;Lscala/Function1<TB;Lorg/scalactic/Or<TH;TC;>;>;)Lorg/scalactic/Or<TH;TC;>;
  #140 = Utf8               gf
  #141 = Utf8               bf
  #142 = Utf8               fold
  #143 = Utf8               (Lscala/Function1;Lscala/Function1;)Ljava/lang/Object;
  #144 = Utf8               <V:Ljava/lang/Object;>(Lscala/Function1<TG;TV;>;Lscala/Function1<TB;TV;>;)TV;
  #145 = Utf8               asOr
  #146 = Utf8               ()Lorg/scalactic/Or<TG;TB;>;
  #147 = Utf8               <init>
  #148 = Utf8               ()V
  #149 = NameAndType        #147:#148     // "<init>":()V
  #150 = Methodref          #5.#149       // java/lang/Object."<init>":()V
  #151 = Utf8               $init$
  #152 = Utf8               (Lscala/Product;)V
  #153 = NameAndType        #151:#152     // $init$:(Lscala/Product;)V
  #154 = InterfaceMethodref #7.#153       // scala/Product.$init$:(Lscala/Product;)V
  #155 = Utf8               Code
  #156 = Utf8               LocalVariableTable
  #157 = Utf8               Signature
  #158 = Utf8               MethodParameters
  #159 = Utf8               LineNumberTable
  #160 = Utf8               Deprecated
  #161 = Utf8               InnerClasses
  #162 = Utf8               SourceFile
  #163 = Utf8               RuntimeVisibleAnnotations
  #164 = Utf8               ScalaInlineInfo
  #165 = Utf8               ScalaSig
{
  private final boolean isGood;
    descriptor: Z
    flags: (0x0012) ACC_PRIVATE, ACC_FINAL

  private final boolean isBad;
    descriptor: Z
    flags: (0x0012) ACC_PRIVATE, ACC_FINAL

  public static <G extends java.lang.Object, B extends java.lang.Object> org.scalactic.Or<G, B> from(scala.Option<G>, scala.Function0<B>);
    descriptor: (Lscala/Option;Lscala/Function0;)Lorg/scalactic/Or;
    flags: (0x0009) ACC_PUBLIC, ACC_STATIC
    Code:
      stack=3, locals=2, args_size=2
         0: getstatic     #33                 // Field org/scalactic/Or$.MODULE$:Lorg/scalactic/Or$;
         3: aload_0
         4: aload_1
         5: invokevirtual #35                 // Method org/scalactic/Or$.from:(Lscala/Option;Lscala/Function0;)Lorg/scalactic/Or;
         8: areturn
      LocalVariableTable:
        Start  Length  Slot  Name   Signature
            0       9     0 option   Lscala/Option;
            0       9     1 orElse   Lscala/Function0;
    Signature: #25                          // <G:Ljava/lang/Object;B:Ljava/lang/Object;>(Lscala/Option<TG;>;Lscala/Function0<TB;>;)Lorg/scalactic/Or<TG;TB;>;
    MethodParameters:
      Name                           Flags
      option                         final
      orElse                         final

  public static <B extends java.lang.Object, G extends java.lang.Object> org.scalactic.Or<G, B> from(scala.util.Either<B, G>);
    descriptor: (Lscala/util/Either;)Lorg/scalactic/Or;
    flags: (0x0009) ACC_PUBLIC, ACC_STATIC
    Code:
      stack=2, locals=1, args_size=1
         0: getstatic     #33                 // Field org/scalactic/Or$.MODULE$:Lorg/scalactic/Or$;
         3: aload_0
         4: invokevirtual #42                 // Method org/scalactic/Or$.from:(Lscala/util/Either;)Lorg/scalactic/Or;
         7: areturn
      LocalVariableTable:
        Start  Length  Slot  Name   Signature
            0       8     0 either   Lscala/util/Either;
    Signature: #39                          // <B:Ljava/lang/Object;G:Ljava/lang/Object;>(Lscala/util/Either<TB;TG;>;)Lorg/scalactic/Or<TG;TB;>;
    MethodParameters:
      Name                           Flags
      either                         final

  public static <G extends java.lang.Object> org.scalactic.Or<G, java.lang.Throwable> from(scala.util.Try<G>);
    descriptor: (Lscala/util/Try;)Lorg/scalactic/Or;
    flags: (0x0009) ACC_PUBLIC, ACC_STATIC
    Code:
      stack=2, locals=1, args_size=1
         0: getstatic     #33                 // Field org/scalactic/Or$.MODULE$:Lorg/scalactic/Or$;
         3: aload_0
         4: invokevirtual #48                 // Method org/scalactic/Or$.from:(Lscala/util/Try;)Lorg/scalactic/Or;
         7: areturn
      LocalVariableTable:
        Start  Length  Slot  Name   Signature
            0       8     0 theTry   Lscala/util/Try;
    Signature: #45                          // <G:Ljava/lang/Object;>(Lscala/util/Try<TG;>;)Lorg/scalactic/Or<TG;Ljava/lang/Throwable;>;
    MethodParameters:
      Name                           Flags
      theTry                         final

  public scala.collection.Iterator<java.lang.Object> productIterator();
    descriptor: ()Lscala/collection/Iterator;
    flags: (0x0001) ACC_PUBLIC
    Code:
      stack=1, locals=1, args_size=1
         0: aload_0
         1: invokestatic  #56                 // InterfaceMethod scala/Product.productIterator$:(Lscala/Product;)Lscala/collection/Iterator;
         4: areturn
      LineNumberTable:
        line 581: 0
      LocalVariableTable:
        Start  Length  Slot  Name   Signature
            0       5     0  this   Lorg/scalactic/Or;
    Signature: #52                          // ()Lscala/collection/Iterator<Ljava/lang/Object;>;

  public java.lang.String productPrefix();
    descriptor: ()Ljava/lang/String;
    flags: (0x0001) ACC_PUBLIC
    Code:
      stack=1, locals=1, args_size=1
         0: aload_0
         1: invokestatic  #64                 // InterfaceMethod scala/Product.productPrefix$:(Lscala/Product;)Ljava/lang/String;
         4: areturn
      LineNumberTable:
        line 581: 0
      LocalVariableTable:
        Start  Length  Slot  Name   Signature
            0       5     0  this   Lorg/scalactic/Or;

  public java.lang.String productElementName(int);
    descriptor: (I)Ljava/lang/String;
    flags: (0x0001) ACC_PUBLIC
    Code:
      stack=2, locals=2, args_size=2
         0: aload_0
         1: iload_1
         2: invokestatic  #71                 // InterfaceMethod scala/Product.productElementName$:(Lscala/Product;I)Ljava/lang/String;
         5: areturn
      LineNumberTable:
        line 581: 0
      LocalVariableTable:
        Start  Length  Slot  Name   Signature
            0       6     0  this   Lorg/scalactic/Or;
            0       6     1     n   I
    MethodParameters:
      Name                           Flags
      n                              final

  public scala.collection.Iterator<java.lang.String> productElementNames();
    descriptor: ()Lscala/collection/Iterator;
    flags: (0x0001) ACC_PUBLIC
    Code:
      stack=1, locals=1, args_size=1
         0: aload_0
         1: invokestatic  #77                 // InterfaceMethod scala/Product.productElementNames$:(Lscala/Product;)Lscala/collection/Iterator;
         4: areturn
      LineNumberTable:
        line 581: 0
      LocalVariableTable:
        Start  Length  Slot  Name   Signature
            0       5     0  this   Lorg/scalactic/Or;
    Signature: #74                          // ()Lscala/collection/Iterator<Ljava/lang/String;>;

  public boolean isGood();
    descriptor: ()Z
    flags: (0x0001) ACC_PUBLIC
    Code:
      stack=1, locals=1, args_size=1
         0: aload_0
         1: getfield      #80                 // Field isGood:Z
         4: ireturn
      LineNumberTable:
        line 588: 0
      LocalVariableTable:
        Start  Length  Slot  Name   Signature
            0       5     0  this   Lorg/scalactic/Or;

  public boolean isBad();
    descriptor: ()Z
    flags: (0x0001) ACC_PUBLIC
    Code:
      stack=1, locals=1, args_size=1
         0: aload_0
         1: getfield      #82                 // Field isBad:Z
         4: ireturn
      LineNumberTable:
        line 595: 0
      LocalVariableTable:
        Start  Length  Slot  Name   Signature
            0       5     0  this   Lorg/scalactic/Or;

  public abstract G get();
    descriptor: ()Ljava/lang/Object;
    flags: (0x0401) ACC_PUBLIC, ACC_ABSTRACT
    Signature: #85                          // ()TG;

  public abstract <H extends java.lang.Object> org.scalactic.Or<H, B> map(scala.Function1<G, H>);
    descriptor: (Lscala/Function1;)Lorg/scalactic/Or;
    flags: (0x0401) ACC_PUBLIC, ACC_ABSTRACT
    Signature: #88                          // <H:Ljava/lang/Object;>(Lscala/Function1<TG;TH;>;)Lorg/scalactic/Or<TH;TB;>;
    MethodParameters:
      Name                           Flags
      f                              final

  public abstract <C extends java.lang.Object> org.scalactic.Or<G, C> badMap(scala.Function1<B, C>);
    descriptor: (Lscala/Function1;)Lorg/scalactic/Or;
    flags: (0x0401) ACC_PUBLIC, ACC_ABSTRACT
    Signature: #91                          // <C:Ljava/lang/Object;>(Lscala/Function1<TB;TC;>;)Lorg/scalactic/Or<TG;TC;>;
    MethodParameters:
      Name                           Flags
      f                              final

  public abstract <H extends java.lang.Object> org.scalactic.Or<H, B> recover(scala.Function1<B, H>);
    descriptor: (Lscala/Function1;)Lorg/scalactic/Or;
    flags: (0x0401) ACC_PUBLIC, ACC_ABSTRACT
    Signature: #93                          // <H:Ljava/lang/Object;>(Lscala/Function1<TB;TH;>;)Lorg/scalactic/Or<TH;TB;>;
    MethodParameters:
      Name                           Flags
      f                              final

  public abstract <H extends java.lang.Object, C extends java.lang.Object> org.scalactic.Or<H, C> recoverWith(scala.Function1<B, org.scalactic.Or<H, C>>);
    descriptor: (Lscala/Function1;)Lorg/scalactic/Or;
    flags: (0x0401) ACC_PUBLIC, ACC_ABSTRACT
    Signature: #95                          // <H:Ljava/lang/Object;C:Ljava/lang/Object;>(Lscala/Function1<TB;Lorg/scalactic/Or<TH;TC;>;>;)Lorg/scalactic/Or<TH;TC;>;
    MethodParameters:
      Name                           Flags
      f                              final

  public abstract void foreach(scala.Function1<G, scala.runtime.BoxedUnit>);
    descriptor: (Lscala/Function1;)V
    flags: (0x0401) ACC_PUBLIC, ACC_ABSTRACT
    Signature: #98                          // (Lscala/Function1<TG;Lscala/runtime/BoxedUnit;>;)V
    MethodParameters:
      Name                           Flags
      f                              final

  public abstract <H extends java.lang.Object, C extends java.lang.Object> org.scalactic.Or<H, C> flatMap(scala.Function1<G, org.scalactic.Or<H, C>>);
    descriptor: (Lscala/Function1;)Lorg/scalactic/Or;
    flags: (0x0401) ACC_PUBLIC, ACC_ABSTRACT
    Signature: #100                         // <H:Ljava/lang/Object;C:Ljava/lang/Object;>(Lscala/Function1<TG;Lorg/scalactic/Or<TH;TC;>;>;)Lorg/scalactic/Or<TH;TC;>;
    MethodParameters:
      Name                           Flags
      f                              final

  public abstract <C extends java.lang.Object> org.scalactic.Or<G, C> filter(scala.Function1<G, org.scalactic.Validation<C>>);
    descriptor: (Lscala/Function1;)Lorg/scalactic/Or;
    flags: (0x0401) ACC_PUBLIC, ACC_ABSTRACT
    Signature: #102                         // <C:Ljava/lang/Object;>(Lscala/Function1<TG;Lorg/scalactic/Validation<TC;>;>;)Lorg/scalactic/Or<TG;TC;>;
    MethodParameters:
      Name                           Flags
      f                              final

  public <C extends java.lang.Object> org.scalactic.Or<G, C> withFilter(scala.Function1<G, org.scalactic.Validation<C>>);
    descriptor: (Lscala/Function1;)Lorg/scalactic/Or;
    flags: (0x0001) ACC_PUBLIC
    Code:
      stack=2, locals=2, args_size=2
         0: aload_0
         1: aload_1
         2: invokevirtual #105                // Method filter:(Lscala/Function1;)Lorg/scalactic/Or;
         5: areturn
      LineNumberTable:
        line 681: 0
      LocalVariableTable:
        Start  Length  Slot  Name   Signature
            0       6     0  this   Lorg/scalactic/Or;
            0       6     1     f   Lscala/Function1;
    Signature: #102                         // <C:Ljava/lang/Object;>(Lscala/Function1<TG;Lorg/scalactic/Validation<TC;>;>;)Lorg/scalactic/Or<TG;TC;>;
    MethodParameters:
      Name                           Flags
      f                              final

  public abstract boolean exists(scala.Function1<G, java.lang.Object>);
    descriptor: (Lscala/Function1;)Z
    flags: (0x0401) ACC_PUBLIC, ACC_ABSTRACT
    Signature: #109                         // (Lscala/Function1<TG;Ljava/lang/Object;>;)Z
    MethodParameters:
      Name                           Flags
      p                              final

  public abstract boolean forall(scala.Function1<G, java.lang.Object>);
    descriptor: (Lscala/Function1;)Z
    flags: (0x0401) ACC_PUBLIC, ACC_ABSTRACT
    Signature: #109                         // (Lscala/Function1<TG;Ljava/lang/Object;>;)Z
    MethodParameters:
      Name                           Flags
      f                              final

  public abstract <H extends java.lang.Object> H getOrElse(scala.Function0<H>);
    descriptor: (Lscala/Function0;)Ljava/lang/Object;
    flags: (0x0401) ACC_PUBLIC, ACC_ABSTRACT
    Signature: #114                         // <H:Ljava/lang/Object;>(Lscala/Function0<TH;>;)TH;
    MethodParameters:
      Name                           Flags
      default                        final

  public abstract <H extends java.lang.Object, C extends java.lang.Object> org.scalactic.Or<H, C> orElse(scala.Function0<org.scalactic.Or<H, C>>);
    descriptor: (Lscala/Function0;)Lorg/scalactic/Or;
    flags: (0x0401) ACC_PUBLIC, ACC_ABSTRACT
    Signature: #117                         // <H:Ljava/lang/Object;C:Ljava/lang/Object;>(Lscala/Function0<Lorg/scalactic/Or<TH;TC;>;>;)Lorg/scalactic/Or<TH;TC;>;
    MethodParameters:
      Name                           Flags
      alternative                    final

  public abstract scala.Option<G> toOption();
    descriptor: ()Lscala/Option;
    flags: (0x0401) ACC_PUBLIC, ACC_ABSTRACT
    Signature: #121                         // ()Lscala/Option<TG;>;

  public abstract scala.collection.immutable.IndexedSeq<G> toSeq();
    descriptor: ()Lscala/collection/immutable/IndexedSeq;
    flags: (0x0401) ACC_PUBLIC, ACC_ABSTRACT
    Signature: #124                         // ()Lscala/collection/immutable/IndexedSeq<TG;>;

  public abstract scala.util.Either<B, G> toEither();
    descriptor: ()Lscala/util/Either;
    flags: (0x0401) ACC_PUBLIC, ACC_ABSTRACT
    Signature: #127                         // ()Lscala/util/Either<TB;TG;>;

  public abstract org.scalactic.Or<G, org.scalactic.One<B>> accumulating();
    descriptor: ()Lorg/scalactic/Or;
    flags: (0x0401) ACC_PUBLIC, ACC_ABSTRACT
    Signature: #130                         // ()Lorg/scalactic/Or<TG;Lorg/scalactic/One<TB;>;>;

  public abstract scala.util.Try<G> toTry(scala.$less$colon$less<B, java.lang.Throwable>);
    descriptor: (Lscala/$less$colon$less;)Lscala/util/Try;
    flags: (0x0401) ACC_PUBLIC, ACC_ABSTRACT
    Signature: #133                         // (Lscala/$less$colon$less<TB;Ljava/lang/Throwable;>;)Lscala/util/Try<TG;>;
    MethodParameters:
      Name                           Flags
      ev                             final

  public abstract org.scalactic.Or<B, G> swap();
    descriptor: ()Lorg/scalactic/Or;
    flags: (0x0401) ACC_PUBLIC, ACC_ABSTRACT
    Signature: #136                         // ()Lorg/scalactic/Or<TB;TG;>;

  public abstract <H extends java.lang.Object, C extends java.lang.Object> org.scalactic.Or<H, C> transform(scala.Function1<G, org.scalactic.Or<H, C>>, scala.Function1<B, org.scalactic.Or<H, C>>);
    descriptor: (Lscala/Function1;Lscala/Function1;)Lorg/scalactic/Or;
    flags: (0x0401) ACC_PUBLIC, ACC_ABSTRACT
    Signature: #139                         // <H:Ljava/lang/Object;C:Ljava/lang/Object;>(Lscala/Function1<TG;Lorg/scalactic/Or<TH;TC;>;>;Lscala/Function1<TB;Lorg/scalactic/Or<TH;TC;>;>;)Lorg/scalactic/Or<TH;TC;>;
    MethodParameters:
      Name                           Flags
      gf                             final
      bf                             final

  public abstract <V extends java.lang.Object> V fold(scala.Function1<G, V>, scala.Function1<B, V>);
    descriptor: (Lscala/Function1;Lscala/Function1;)Ljava/lang/Object;
    flags: (0x0401) ACC_PUBLIC, ACC_ABSTRACT
    Signature: #144                         // <V:Ljava/lang/Object;>(Lscala/Function1<TG;TV;>;Lscala/Function1<TB;TV;>;)TV;
    MethodParameters:
      Name                           Flags
      gf                             final
      bf                             final

  public org.scalactic.Or<G, B> asOr();
    descriptor: ()Lorg/scalactic/Or;
    flags: (0x0001) ACC_PUBLIC
    Code:
      stack=1, locals=1, args_size=1
         0: aload_0
         1: areturn
      LineNumberTable:
        line 854: 0
      LocalVariableTable:
        Start  Length  Slot  Name   Signature
            0       2     0  this   Lorg/scalactic/Or;
    Signature: #146                         // ()Lorg/scalactic/Or<TG;TB;>;
    Deprecated: true

  public org.scalactic.Or();
    descriptor: ()V
    flags: (0x0001) ACC_PUBLIC
    Code:
      stack=2, locals=1, args_size=1
         0: aload_0
         1: invokespecial #150                // Method java/lang/Object."<init>":()V
         4: aload_0
         5: invokestatic  #154                // InterfaceMethod scala/Product.$init$:(Lscala/Product;)V
         8: aload_0
         9: iconst_0
        10: putfield      #80                 // Field isGood:Z
        13: aload_0
        14: iconst_0
        15: putfield      #82                 // Field isBad:Z
        18: return
      LineNumberTable:
        line 581: 0
        line 588: 8
        line 595: 13
        line 581: 18
      LocalVariableTable:
        Start  Length  Slot  Name   Signature
            0      19     0  this   Lorg/scalactic/Or;
}
InnerClasses:
  public static #16= #15 of #2;           // B=class org/scalactic/Or$B of class org/scalactic/Or
  public static #19= #18 of #2;           // G=class org/scalactic/Or$G of class org/scalactic/Or
Signature: #3                           // <G:Ljava/lang/Object;B:Ljava/lang/Object;>Ljava/lang/Object;Lscala/Product;Ljava/io/Serializable;
SourceFile: "Or.scala"
RuntimeVisibleAnnotations:
  0: #11(#12=s#13)
    scala.reflect.ScalaSignature(
      bytes="\u0006\u0005\t\u0015g!B\u0014)\u0003Ci\u0003\"\u0002#\u0001\t\u0003)\u0005b\u0002,\u0001\u0005\u0004%\ta\u0016\u0005\u00077\u0002\u0001\u000b\u0011\u0002-\t\u000fq\u0003!\u0019!C\u0001/\"1Q\f\u0001Q\u0001\naCQA\u0018\u0001\u0007\u0002}CQ\u0001\u0019\u0001\u0007\u0002\u0005DQ\u0001\u001c\u0001\u0007\u00025DQ!\u001e\u0001\u0007\u0002YDQA \u0001\u0007\u0002}Dq!!\u0005\u0001\r\u0003\t\u0019\u0002C\u0004\u0002 \u00011\t!!\t\t\u000f\u0005U\u0002A\"\u0001\u00028!9\u00111\n\u0001\u0005\u0002\u00055\u0003bBA/\u0001\u0019\u0005\u0011q\f\u0005\b\u0003O\u0002a\u0011AA5\u0011\u001d\ti\u0007\u0001D\u0001\u0003_Bq!!!\u0001\r\u0003\t\u0019\tC\u0004\u0002\u0018\u00021\t!!\'\t\u000f\u0005\u0005\u0006A\"\u0001\u0002$\"9\u0011Q\u0017\u0001\u0007\u0002\u0005]\u0006bBA`\u0001\u0019\u0005\u0011\u0011\u0019\u0005\b\u0003\u0017\u0004a\u0011AAg\u0011\u001d\tY\u000f\u0001D\u0001\u0003[Dq!!=\u0001\r\u0003\t\u0019\u0010C\u0004\u0003\u000e\u00011\tAa\u0004\t\u000f\t\u0005\u0002\u0001\"\u0001\u0003$\u001d9!Q\b\u0015\t\u0002\t}bAB\u0014)\u0011\u0003\u0011\t\u0005\u0003\u0004E;\u0011\u0005!\u0011\u000b\u0004\n+v\u0001\n1%\u0001)\u0005\'*QaS\u0010\u0001\u0005/2\u0011bS\u000f\u0011\u0002G\u0005\u0001Fa\u001a\u0006\u000bU\u000b\u0003Aa\u001b\t\u000f\t]T\u0004\"\u0001\u0003z!9!qO\u000f\u0005\u0002\t%\u0005b\u0002B<;\u0011\u0005!Q\u0014\u0005\n\u0005kk\u0012\u0011!C\u0005\u0005o\u0013!a\u0014:\u000b\u0005%R\u0013!C:dC2\f7\r^5d\u0015\u0005Y\u0013aA8sO\u000e\u0001Qc\u0001\u0018K)N!\u0001aL\u001b9!\t\u00014\'D\u00012\u0015\u0005\u0011\u0014!B:dC2\f\u0017B\u0001\u001b2\u0005\u0019\te.\u001f*fMB\u0011\u0001GN\u0005\u0003oE\u0012q\u0001\u0015:pIV\u001cG\u000f\u0005\u0002:\u0003:\u0011!h\u0010\b\u0003wyj\u0011\u0001\u0010\u0006\u0003{1\na\u0001\u0010:p_Rt\u0014\"\u0001\u001a\n\u0005\u0001\u000b\u0014a\u00029bG.\fw-Z\u0005\u0003\u0005\u000e\u0013AbU3sS\u0006d\u0017N_1cY\u0016T!\u0001Q\u0019\u0002\rqJg.\u001b;?)\u00051\u0005\u0003B$\u0001\u0011Nk\u0011\u0001\u000b\t\u0003\u0013*c\u0001\u0001\u0002\u0004L\u0001\u0011\u0015\r\u0001\u0014\u0002\u0002\u000fF\u0011Q\n\u0015\t\u0003a9K!aT\u0019\u0003\u000f9{G\u000f[5oOB\u0011\u0001\'U\u0005\u0003%F\u00121!\u00118z!\tIE\u000b\u0002\u0004V\u0001\u0011\u0015\r\u0001\u0014\u0002\u0002\u0005\u00061\u0011n]$p_\u0012,\u0012\u0001\u0017\t\u0003aeK!AW\u0019\u0003\u000f\t{w\u000e\\3b]\u00069\u0011n]$p_\u0012\u0004\u0013!B5t\u0005\u0006$\u0017AB5t\u0005\u0006$\u0007%A\u0002hKR,\u0012\u0001S\u0001\u0004[\u0006\u0004XC\u00012f)\t\u0019w\r\u0005\u0003H\u0001\u0011\u001c\u0006CA%f\t\u00151wA1\u0001M\u0005\u0005A\u0005\"\u00025\b\u0001\u0004I\u0017!\u00014\u0011\tAR\u0007\nZ\u0005\u0003WF\u0012\u0011BR;oGRLwN\\\u0019\u0002\r\t\fG-T1q+\tq\u0017\u000f\u0006\u0002pgB!q\t\u0001%q!\tI\u0015\u000fB\u0003s\u0011\t\u0007AJA\u0001D\u0011\u0015A\u0007\u00021\u0001u!\u0011\u0001$n\u00159\u0002\u000fI,7m\u001c<feV\u0011qO\u001f\u000b\u0003qr\u0004Ba\u0012\u0001z\'B\u0011\u0011J\u001f\u0003\u0006M&\u0011\ra_\t\u0003\u0011BCQ\u0001[\u0005A\u0002u\u0004B\u0001\r6Ts\u0006Y!/Z2pm\u0016\u0014x+\u001b;i+\u0019\t\t!a\u0002\u0002\fQ!\u00111AA\u0007!\u00199\u0005!!\u0002\u0002\nA\u0019\u0011*a\u0002\u0005\u000b\u0019T!\u0019A>\u0011\u0007%\u000bY\u0001B\u0003s\u0015\t\u0007A\n\u0003\u0004i\u0015\u0001\u0007\u0011q\u0002\t\u0006a)\u001c\u00161A\u0001\bM>\u0014X-Y2i)\u0011\t)\"a\u0007\u0011\u0007A\n9\"C\u0002\u0002\u001aE\u0012A!\u00168ji\"1\u0001n\u0003a\u0001\u0003;\u0001R\u0001\r6I\u0003+\tqA\u001a7bi6\u000b\u0007/\u0006\u0004\u0002$\u0005%\u0012Q\u0006\u000b\u0005\u0003K\t\t\u0004\u0005\u0004H\u0001\u0005\u001d\u00121\u0006\t\u0004\u0013\u0006%B!\u00024\r\u0005\u0004a\u0005cA%\u0002.\u00111!\u000f\u0004b\u0001\u0003_\t\"a\u0015)\t\r!d\u0001\u0019AA\u001a!\u0015\u0001$\u000eSA\u0013\u0003\u00191\u0017\u000e\u001c;feV!\u0011\u0011HA )\u0011\tY$!\u0011\u0011\u000b\u001d\u0003\u0001*!\u0010\u0011\u0007%\u000by\u0004\u0002\u0004s\u001b\t\u0007\u0011q\u0006\u0005\u0007Q6\u0001\r!a\u0011\u0011\u000bAR\u0007*!\u0012\u0011\u000b\u001d\u000b9%!\u0010\n\u0007\u0005%\u0003F\u0001\u0006WC2LG-\u0019;j_:\f!b^5uQ\u001aKG\u000e^3s+\u0011\ty%!\u0016\u0015\t\u0005E\u0013q\u000b\t\u0006\u000f\u0002A\u00151\u000b\t\u0004\u0013\u0006UCA\u0002:\u000f\u0005\u0004\ty\u0003\u0003\u0004i\u001d\u0001\u0007\u0011\u0011\f\t\u0006a)D\u00151\f\t\u0006\u000f\u0006\u001d\u00131K\u0001\u0007KbL7\u000f^:\u0015\u0007a\u000b\t\u0007C\u0004\u0002d=\u0001\r!!\u001a\u0002\u0003A\u0004B\u0001\r6I1\u00061am\u001c:bY2$2\u0001WA6\u0011\u0019A\u0007\u00031\u0001\u0002f\u0005Iq-\u001a;Pe\u0016c7/Z\u000b\u0005\u0003c\n)\b\u0006\u0003\u0002t\u0005]\u0004cA%\u0002v\u0011)a-\u0005b\u0001w\"A\u0011\u0011P\t\u0005\u0002\u0004\tY(A\u0004eK\u001a\fW\u000f\u001c;\u0011\u000bA\ni(a\u001d\n\u0007\u0005}\u0014G\u0001\u0005=Eft\u0017-\\3?\u0003\u0019y\'/\u00127tKV1\u0011QQAF\u0003\u001f#B!a\"\u0002\u0012B1q\tAAE\u0003\u001b\u00032!SAF\t\u00151\'C1\u0001|!\rI\u0015q\u0012\u0003\u0007eJ\u0011\r!a\f\t\u0011\u0005M%\u0003\"a\u0001\u0003+\u000b1\"\u00197uKJt\u0017\r^5wKB)\u0001\'! \u0002\b\u0006AAo\\(qi&|g.\u0006\u0002\u0002\u001cB!\u0001\'!(I\u0013\r\ty*\r\u0002\u0007\u001fB$\u0018n\u001c8\u0002\u000bQ|7+Z9\u0016\u0005\u0005\u0015\u0006#BAT\u0003cCUBAAU\u0015\u0011\tY+!,\u0002\u0013%lW.\u001e;bE2,\'bAAXc\u0005Q1m\u001c7mK\u000e$\u0018n\u001c8\n\t\u0005M\u0016\u0011\u0016\u0002\u000b\u0013:$W\r_3e\'\u0016\f\u0018\u0001\u0003;p\u000b&$\b.\u001a:\u0016\u0005\u0005e\u0006#B\u001d\u0002<NC\u0015bAA_\u0007\n1Q)\u001b;iKJ\fA\"Y2dk6,H.\u0019;j]\u001e,\"!a1\u0011\u000b\u001d\u0003\u0001*!2\u0011\t\u001d\u000b9mU\u0005\u0004\u0003\u0013D#aA(oK\u0006)Ao\u001c+ssR!\u0011qZAn!\u0015\t\t.a6I\u001b\t\t\u0019NC\u0002\u0002VF\nA!\u001e;jY&!\u0011\u0011\\Aj\u0005\r!&/\u001f\u0005\b\u0003;<\u00029AAp\u0003\t)g\u000f\u0005\u00041\u0003C\u001c\u0016Q]\u0005\u0004\u0003G\f$\u0001\u0005\u0013mKN\u001cHeY8m_:$C.Z:t!\rI\u0014q]\u0005\u0004\u0003S\u001c%!\u0003+ie><\u0018M\u00197f\u0003\u0011\u0019x/\u00199\u0016\u0005\u0005=\b\u0003B$\u0001\'\"\u000b\u0011\u0002\u001e:b]N4wN]7\u0016\r\u0005U\u00181`A\u0000)\u0019\t9P!\u0001\u0003\bA1q\tAA}\u0003{\u00042!SA~\t\u00151\u0017D1\u0001M!\rI\u0015q \u0003\u0006ef\u0011\r\u0001\u0014\u0005\b\u0005\u0007I\u0002\u0019\u0001B\u0003\u0003\t9g\rE\u00031U\"\u000b9\u0010C\u0004\u0003\ne\u0001\rAa\u0003\u0002\u0005\t4\u0007#\u0002\u0019k\'\u0006]\u0018\u0001\u00024pY\u0012,BA!\u0005\u0003\u0016Q1!1\u0003B\r\u0005;\u00012!\u0013B\u000b\t\u0019\u00119B\u0007b\u0001\u0019\n\ta\u000bC\u0004\u0003\u0004i\u0001\rAa\u0007\u0011\u000bAR\u0007Ja\u0005\t\u000f\t%!\u00041\u0001\u0003 A)\u0001G[*\u0003\u0014\u0005!\u0011m](s+\u00051\u0005fB\u000e\u0003(\t5\"q\u0006\t\u0004a\t%\u0012b\u0001B\u0016c\tQA-\u001a9sK\u000e\fG/\u001a3\u0002\u000f5,7o]1hK\u0006\u0012!\u0011G\u0001\u0002vRCW\rI1t\u001fJ\u0004\u0013n\u001d\u0011o_\u0002bwN\\4fe\u0002rW-\u001a3fI\u0002\u0012WmY1vg\u0016\u0004si\\8eQY\fG.^3*]=\u0014()\u00193\\)f\u0004X-\u0018\u0011b]\u0012\u0004si\\8e7RK\b/Z//_J\u0014\u0015\r\u001a\u0015wC2,X-\u000b\u0011o_^\u0004#/\u001a;ve:\u0004sJ\u001d\u0018!3>,\beY1oA\u0011,G.\u001a;fA%tgo\\2bi&|gn\u001d\u0011pM\u0002\n7o\u0014:!S:\u0004C\u000f[8tK\u0002\u001a\u0017m]3tY\u0001zG\u000f[3so&\u001cX\r\f\u0011qY\u0016\f7/\u001a\u0011vg\u0016\u0004\u0013\r\t;za\u0016\u0004\u0013M\u001c8pi\u0006$\u0018n\u001c8!i>\u0004s/\u001b3f]\u0002\"\b.\u001a\u0011usB,G\u0006\t7jW\u0016\u0004\u0003fR8pI\"\u001a\u0014F\u000f\u0011J]R\u0004sJ\u001d\u0011FeJ|\'/T3tg\u0006<W-\u000b\u0018*\u000b\u0001\u0011)D!\u000f\n\u0007\t]\u0002FA\u0002CC\u0012L1Aa\u000f)\u0005\u00119un\u001c3\u0002\u0005=\u0013\bCA$\u001e\'\u0011irFa\u0011\u0011\t\t\u0015#qJ\u0007\u0003\u0005\u000fRAA!\u0013\u0003L\u0005\u0011\u0011n\u001c\u0006\u0003\u0005\u001b\nAA[1wC&\u0019!Ia\u0012\u0015\u0005\t}R\u0003\u0002B+\u0005G\u001a\"aH\u0018\u0016\t\te#Q\f\t\u0007\u000f\u0002\u0011YF!\u0019\u0011\u0007%\u0013i\u0006\u0002\u0004\u0003`\u0001\u0012\r\u0001\u0014\u0002\u0005\u000f>{E\tE\u0002J\u0005G\"aA!\u001a \u0005\u0004a%a\u0001\"B\tV!!\u0011\u000eB9\'\t\ts&\u0006\u0003\u0003n\tU\u0004CB$\u0001\u0005_\u0012\u0019\bE\u0002J\u0005c\"aAa\u0018\"\u0005\u0004a\u0005cA%\u0003v\u00111!Q\r\u0012C\u00021\u000bAA\u001a:p[V!!1\u0010BA)\u0011\u0011iHa!\u0011\r\u001d\u0003!qPAs!\rI%\u0011\u0011\u0003\u0006\u0017\u000e\u0012\r\u0001\u0014\u0005\b\u0005\u000b\u001b\u0003\u0019\u0001BD\u0003\u0019!\b.\u001a+ssB1\u0011\u0011[Al\u0005\u007f*bAa#\u0003\u0016\nEE\u0003\u0002BG\u0005/\u0003ba\u0012\u0001\u0003\u0010\nM\u0005cA%\u0003\u0012\u0012)1\n\nb\u0001\u0019B\u0019\u0011J!&\u0005\u000bU##\u0019\u0001\'\t\u000f\teE\u00051\u0001\u0003\u001c\u00061Q-\u001b;iKJ\u0004r!OA^\u0005\'\u0013y)\u0006\u0004\u0003 \n\u0015&\u0011\u0016\u000b\u0007\u0005C\u0013YK!-\u0011\r\u001d\u0003!1\u0015BT!\rI%Q\u0015\u0003\u0006\u0017\u0016\u0012\r\u0001\u0014\t\u0004\u0013\n%F!B+&\u0005\u0004a\u0005b\u0002BWK\u0001\u0007!qV\u0001\u0007_B$\u0018n\u001c8\u0011\u000bA\niJa)\t\u0011\u0005\u0005U\u0005\"a\u0001\u0005g\u0003R\u0001MA?\u0005O\u000bAb\u001e:ji\u0016\u0014V\r\u001d7bG\u0016$\"A!/\u0011\t\tm&\u0011Y\u0007\u0003\u0005{SAAa0\u0003L\u0005!A.\u00198h\u0013\u0011\u0011\u0019M!0\u0003\r=\u0013\'.Z2u\u0001"
    )
  ScalaInlineInfo: length = 0x95 (unknown attribute)
   01 00 00 1D 00 93 00 94 01 00 80 00 81 00 00 91
   00 81 00 00 5A 00 57 00 00 6B 00 6C 00 00 65 00
   57 00 00 63 00 57 00 00 8E 00 8F 00 00 6F 00 6C
   00 00 60 00 61 00 00 53 00 54 00 00 70 00 71 00
   00 16 00 4E 00 00 14 00 4E 00 00 56 00 57 00 00
   1B 00 74 00 00 41 00 42 00 00 49 00 33 01 00 32
   00 33 00 00 3B 00 3C 00 00 5C 00 57 00 00 5E 00
   57 00 00 87 00 81 00 00 7D 00 7E 00 00 77 00 78
   00 00 7A 00 7B 00 00 83 00 84 00 00 89 00 8A 00
   00 67 00 57 01
  ScalaSig: length = 0x3 (unknown attribute)
   05 02 00
