Classfile /Users/mw/Projects/slang-braindump/.jar/jar11/assemble/slang-braindump/assemble/content/org/scalactic/package.class
  Last modified May 29, 2022; size 1972 bytes
  SHA-256 checksum deae1eb2598044468c33c417c52f44e5baf6df84e0e4ab38e5fc7ce7a56438f2
  Compiled from "package.scala"
public final class org.scalactic.package
  minor version: 0
  major version: 52
  flags: (0x0031) ACC_PUBLIC, ACC_FINAL, ACC_SUPER
  this_class: #2                          // org/scalactic/package
  super_class: #4                         // java/lang/Object
  interfaces: 0, fields: 0, methods: 4, attributes: 3
Constant pool:
   #1 = Utf8               org/scalactic/package
   #2 = Class              #1             // org/scalactic/package
   #3 = Utf8               java/lang/Object
   #4 = Class              #3             // java/lang/Object
   #5 = Utf8               package.scala
   #6 = Utf8               Lscala/reflect/ScalaSignature;
   #7 = Utf8               bytes
   #8 = Utf8               \u0006\u0005]<Q\u0001D\u0007\t\u0002I1Q\u0001F\u0007\t\u0002UAQ\u0001H\u0001\u0005\u0002u)AAH\u0001\u0001?!)!&\u0001C\u0001W!9\u0001*\u0001b\u0001\n\u0003I\u0005B\u0002&\u0002A\u0003%q$\u0002\u0003L\u0003\u0001a\u0005b\u00021\u0002\u0005\u0004%\t!\u0019\u0005\u0007Y\u0006\u0001\u000b\u0011\u00022\t\u000f9\f!\u0019!C\u0001_\"1Q/\u0001Q\u0001\nA\fq\u0001]1dW\u0006<WM\u0003\u0002\u000f\u001f\u0005I1oY1mC\u000e$\u0018n\u0019\u0006\u0002!\u0005\u0019qN]4\u0004\u0001A\u00111#A\u0007\u0002\u001b\t9\u0001/Y2lC\u001e,7CA\u0001\u0017!\t9\"$D\u0001\u0019\u0015\u0005I\u0012!B:dC2\f\u0017BA\u000e\u0019\u0005\u0019\te.\u001f*fM\u00061A(\u001b8jiz\"\u0012A\u0005\u0002\r\u000bJ\u0014xN]\'fgN\fw-\u001a\t\u0003A\u001dr!!I\u0013\u0011\u0005\tBR\"A\u0012\u000b\u0005\u0011\n\u0012A\u0002\u001fs_>$h(\u0003\u0002\'1\u00051\u0001K]3eK\u001aL!\u0001K\u0015\u0003\rM#(/\u001b8h\u0015\t1\u0003$A\u0004biR,W\u000e\u001d;\u0016\u00051\u0012DCA\u0017D!\u0011\u0019b\u0006M\u001e\n\u0005=j!AA(s!\t\t$\u0007\u0004\u0001\u0005\u000bM\"!\u0019\u0001\u001b\u0003\u0003I\u000b\"!\u000e\u001d\u0011\u0005]1\u0014BA\u001c\u0019\u0005\u001dqu\u000e\u001e5j]\u001e\u0004\"aF\u001d\n\u0005iB\"aA!osB\u0011A\b\u0011\b\u0003{}r!A\t \n\u0003eI!\u0001\u0004\r\n\u0005\u0005\u0013%!\u0003+ie><\u0018M\u00197f\u0015\ta\u0001\u0004\u0003\u0004E\t\u0011\u0005\r!R\u0001\u0002MB\u0019qC\u0012\u0019\n\u0005\u001dC\"\u0001\u0003\u001fcs:\fW.\u001a \u0002!M\u001b\u0017\r\\1di&\u001cg+\u001a:tS>tW#A\u0010\u0002#M\u001b\u0017\r\\1di&\u001cg+\u001a:tS>t\u0007EA\u0003DQ\u0006Lg.\u0006\u0002N)B\u0019a*U*\u000e\u0003=S!\u0001U\u0007\u0002\u000f\u0005t\u0017P^1mg&\u0011!k\u0014\u0002\r\u001d>tW)\u001c9us2K7\u000f\u001e\t\u0003cQ#a!V\u0004\u0005\u0006\u0004!$!\u0001+)\r\u001d9&lW/_!\t9\u0002,\u0003\u0002Z1\tQA-\u001a9sK\u000e\fG/\u001a3\u0002\u000f5,7o]1hK\u0006\nA,AA\u0007\u0007\"\f\u0017N\u001c\u0011iCN\u0004#-Z3oA\u0011,\u0007O]3dCR,G\rI1oI\u0002:\u0018\u000e\u001c7!E\u0016\u0004#/Z7pm\u0016$\u0007%\u001b8!C\u00022W\u000f^;sK\u00022XM]:j_:\u0004sN\u001a\u0011TG\u0006d\u0017m\u0019;jG:\u0002\u0003\u000b\\3bg\u0016\u0004So]3!_J<gf]2bY\u0006\u001cG/[2/C:Lh/\u00197t]9{g.R7qifd\u0015n\u001d;!S:\u001cH/Z1e]\u0005)1/\u001b8dK\u0006\nq,A\u00034]Er\u0003\'A\u0003DQ\u0006Lg.F\u0001c\u001d\t\u0019\u0017N\u0004\u0002eQ:\u0011Qm\u001a\b\u0003E\u0019L\u0011\u0001E\u0005\u0003\u001d=I!\u0001U\u0007\n\u0005)|\u0015\u0001\u0004(p]\u0016k\u0007\u000f^=MSN$\bF\u0002\u0005X5nkf,\u0001\u0004DQ\u0006Lg\u000e\t\u0015\u0007\u0013]S6,\u00180\u0002\u0007\u0015sG-F\u0001q\u001d\t\u0019\u0017/\u0003\u0002o\u001f\"2!b\u0016.t;z\u000b\u0013\u0001^\u0001|\u000b:$\u0007\u0005[1tA\t,WM\u001c\u0011eKB\u0014XmY1uK\u0012\u0004\u0013M\u001c3!o&dG\u000e\t2fAI,Wn\u001c<fI\u0002Jg\u000eI1!MV$XO]3!m\u0016\u00148/[8oA=4\u0007eU2bY\u0006\u001cG/[2/AAcW-Y:fAU\u001cX\rI8sO:\u001a8-\u00197bGRL7ML1osZ\fGn\u001d\u0018F]\u0012\u0004\u0013N\\:uK\u0006$g&\u0001\u0003F]\u0012\u0004\u0003FB\u0006X5Nlf\f
   #9 = Utf8               End
  #10 = Utf8               ()Lorg/scalactic/anyvals/End$;
  #11 = Utf8               org/scalactic/package$
  #12 = Class              #11            // org/scalactic/package$
  #13 = Utf8               MODULE$
  #14 = Utf8               Lorg/scalactic/package$;
  #15 = NameAndType        #13:#14        // MODULE$:Lorg/scalactic/package$;
  #16 = Fieldref           #12.#15        // org/scalactic/package$.MODULE$:Lorg/scalactic/package$;
  #17 = NameAndType        #9:#10         // End:()Lorg/scalactic/anyvals/End$;
  #18 = Methodref          #12.#17        // org/scalactic/package$.End:()Lorg/scalactic/anyvals/End$;
  #19 = Utf8               Chain
  #20 = Utf8               ()Lorg/scalactic/anyvals/NonEmptyList$;
  #21 = NameAndType        #19:#20        // Chain:()Lorg/scalactic/anyvals/NonEmptyList$;
  #22 = Methodref          #12.#21        // org/scalactic/package$.Chain:()Lorg/scalactic/anyvals/NonEmptyList$;
  #23 = Utf8               ScalacticVersion
  #24 = Utf8               ()Ljava/lang/String;
  #25 = NameAndType        #23:#24        // ScalacticVersion:()Ljava/lang/String;
  #26 = Methodref          #12.#25        // org/scalactic/package$.ScalacticVersion:()Ljava/lang/String;
  #27 = Utf8               attempt
  #28 = Utf8               (Lscala/Function0;)Lorg/scalactic/Or;
  #29 = Utf8               <R:Ljava/lang/Object;>(Lscala/Function0<TR;>;)Lorg/scalactic/Or<TR;Ljava/lang/Throwable;>;
  #30 = Utf8               f
  #31 = NameAndType        #27:#28        // attempt:(Lscala/Function0;)Lorg/scalactic/Or;
  #32 = Methodref          #12.#31        // org/scalactic/package$.attempt:(Lscala/Function0;)Lorg/scalactic/Or;
  #33 = Utf8               Lscala/Function0;
  #34 = Utf8               Code
  #35 = Utf8               Deprecated
  #36 = Utf8               LocalVariableTable
  #37 = Utf8               Signature
  #38 = Utf8               MethodParameters
  #39 = Utf8               SourceFile
  #40 = Utf8               RuntimeVisibleAnnotations
  #41 = Utf8               ScalaSig
{
  public static org.scalactic.anyvals.End$ End();
    descriptor: ()Lorg/scalactic/anyvals/End$;
    flags: (0x0009) ACC_PUBLIC, ACC_STATIC
    Code:
      stack=1, locals=0, args_size=0
         0: getstatic     #16                 // Field org/scalactic/package$.MODULE$:Lorg/scalactic/package$;
         3: invokevirtual #18                 // Method org/scalactic/package$.End:()Lorg/scalactic/anyvals/End$;
         6: areturn
    Deprecated: true

  public static org.scalactic.anyvals.NonEmptyList$ Chain();
    descriptor: ()Lorg/scalactic/anyvals/NonEmptyList$;
    flags: (0x0009) ACC_PUBLIC, ACC_STATIC
    Code:
      stack=1, locals=0, args_size=0
         0: getstatic     #16                 // Field org/scalactic/package$.MODULE$:Lorg/scalactic/package$;
         3: invokevirtual #22                 // Method org/scalactic/package$.Chain:()Lorg/scalactic/anyvals/NonEmptyList$;
         6: areturn
    Deprecated: true

  public static java.lang.String ScalacticVersion();
    descriptor: ()Ljava/lang/String;
    flags: (0x0009) ACC_PUBLIC, ACC_STATIC
    Code:
      stack=1, locals=0, args_size=0
         0: getstatic     #16                 // Field org/scalactic/package$.MODULE$:Lorg/scalactic/package$;
         3: invokevirtual #26                 // Method org/scalactic/package$.ScalacticVersion:()Ljava/lang/String;
         6: areturn

  public static <R extends java.lang.Object> org.scalactic.Or<R, java.lang.Throwable> attempt(scala.Function0<R>);
    descriptor: (Lscala/Function0;)Lorg/scalactic/Or;
    flags: (0x0009) ACC_PUBLIC, ACC_STATIC
    Code:
      stack=2, locals=1, args_size=1
         0: getstatic     #16                 // Field org/scalactic/package$.MODULE$:Lorg/scalactic/package$;
         3: aload_0
         4: invokevirtual #32                 // Method org/scalactic/package$.attempt:(Lscala/Function0;)Lorg/scalactic/Or;
         7: areturn
      LocalVariableTable:
        Start  Length  Slot  Name   Signature
            0       8     0     f   Lscala/Function0;
    Signature: #29                          // <R:Ljava/lang/Object;>(Lscala/Function0<TR;>;)Lorg/scalactic/Or<TR;Ljava/lang/Throwable;>;
    MethodParameters:
      Name                           Flags
      f                              final
}
SourceFile: "package.scala"
RuntimeVisibleAnnotations:
  0: #6(#7=s#8)
    scala.reflect.ScalaSignature(
      bytes="\u0006\u0005]<Q\u0001D\u0007\t\u0002I1Q\u0001F\u0007\t\u0002UAQ\u0001H\u0001\u0005\u0002u)AAH\u0001\u0001?!)!&\u0001C\u0001W!9\u0001*\u0001b\u0001\n\u0003I\u0005B\u0002&\u0002A\u0003%q$\u0002\u0003L\u0003\u0001a\u0005b\u00021\u0002\u0005\u0004%\t!\u0019\u0005\u0007Y\u0006\u0001\u000b\u0011\u00022\t\u000f9\f!\u0019!C\u0001_\"1Q/\u0001Q\u0001\nA\fq\u0001]1dW\u0006<WM\u0003\u0002\u000f\u001f\u0005I1oY1mC\u000e$\u0018n\u0019\u0006\u0002!\u0005\u0019qN]4\u0004\u0001A\u00111#A\u0007\u0002\u001b\t9\u0001/Y2lC\u001e,7CA\u0001\u0017!\t9\"$D\u0001\u0019\u0015\u0005I\u0012!B:dC2\f\u0017BA\u000e\u0019\u0005\u0019\te.\u001f*fM\u00061A(\u001b8jiz\"\u0012A\u0005\u0002\r\u000bJ\u0014xN]\'fgN\fw-\u001a\t\u0003A\u001dr!!I\u0013\u0011\u0005\tBR\"A\u0012\u000b\u0005\u0011\n\u0012A\u0002\u001fs_>$h(\u0003\u0002\'1\u00051\u0001K]3eK\u001aL!\u0001K\u0015\u0003\rM#(/\u001b8h\u0015\t1\u0003$A\u0004biR,W\u000e\u001d;\u0016\u00051\u0012DCA\u0017D!\u0011\u0019b\u0006M\u001e\n\u0005=j!AA(s!\t\t$\u0007\u0004\u0001\u0005\u000bM\"!\u0019\u0001\u001b\u0003\u0003I\u000b\"!\u000e\u001d\u0011\u0005]1\u0014BA\u001c\u0019\u0005\u001dqu\u000e\u001e5j]\u001e\u0004\"aF\u001d\n\u0005iB\"aA!osB\u0011A\b\u0011\b\u0003{}r!A\t \n\u0003eI!\u0001\u0004\r\n\u0005\u0005\u0013%!\u0003+ie><\u0018M\u00197f\u0015\ta\u0001\u0004\u0003\u0004E\t\u0011\u0005\r!R\u0001\u0002MB\u0019qC\u0012\u0019\n\u0005\u001dC\"\u0001\u0003\u001fcs:\fW.\u001a \u0002!M\u001b\u0017\r\\1di&\u001cg+\u001a:tS>tW#A\u0010\u0002#M\u001b\u0017\r\\1di&\u001cg+\u001a:tS>t\u0007EA\u0003DQ\u0006Lg.\u0006\u0002N)B\u0019a*U*\u000e\u0003=S!\u0001U\u0007\u0002\u000f\u0005t\u0017P^1mg&\u0011!k\u0014\u0002\r\u001d>tW)\u001c9us2K7\u000f\u001e\t\u0003cQ#a!V\u0004\u0005\u0006\u0004!$!\u0001+)\r\u001d9&lW/_!\t9\u0002,\u0003\u0002Z1\tQA-\u001a9sK\u000e\fG/\u001a3\u0002\u000f5,7o]1hK\u0006\nA,AA\u0007\u0007\"\f\u0017N\u001c\u0011iCN\u0004#-Z3oA\u0011,\u0007O]3dCR,G\rI1oI\u0002:\u0018\u000e\u001c7!E\u0016\u0004#/Z7pm\u0016$\u0007%\u001b8!C\u00022W\u000f^;sK\u00022XM]:j_:\u0004sN\u001a\u0011TG\u0006d\u0017m\u0019;jG:\u0002\u0003\u000b\\3bg\u0016\u0004So]3!_J<gf]2bY\u0006\u001cG/[2/C:Lh/\u00197t]9{g.R7qifd\u0015n\u001d;!S:\u001cH/Z1e]\u0005)1/\u001b8dK\u0006\nq,A\u00034]Er\u0003\'A\u0003DQ\u0006Lg.F\u0001c\u001d\t\u0019\u0017N\u0004\u0002eQ:\u0011Qm\u001a\b\u0003E\u0019L\u0011\u0001E\u0005\u0003\u001d=I!\u0001U\u0007\n\u0005)|\u0015\u0001\u0004(p]\u0016k\u0007\u000f^=MSN$\bF\u0002\u0005X5nkf,\u0001\u0004DQ\u0006Lg\u000e\t\u0015\u0007\u0013]S6,\u00180\u0002\u0007\u0015sG-F\u0001q\u001d\t\u0019\u0017/\u0003\u0002o\u001f\"2!b\u0016.t;z\u000b\u0013\u0001^\u0001|\u000b:$\u0007\u0005[1tA\t,WM\u001c\u0011eKB\u0014XmY1uK\u0012\u0004\u0013M\u001c3!o&dG\u000e\t2fAI,Wn\u001c<fI\u0002Jg\u000eI1!MV$XO]3!m\u0016\u00148/[8oA=4\u0007eU2bY\u0006\u001cG/[2/AAcW-Y:fAU\u001cX\rI8sO:\u001a8-\u00197bGRL7ML1osZ\fGn\u001d\u0018F]\u0012\u0004\u0013N\\:uK\u0006$g&\u0001\u0003F]\u0012\u0004\u0003FB\u0006X5Nlf\f"
    )
  ScalaSig: length = 0x3 (unknown attribute)
   05 02 00
