Classfile /Users/mw/Projects/slang-braindump/.jar/jar11/assemble/slang-braindump/assemble/content/org/scalactic/RequirementsMacro$.class
  Last modified May 29, 2022; size 9045 bytes
  SHA-256 checksum 1beb12adc47b93d41cef2491e4f3230315dc832d9fd27e6dcc19677274b20beb
  Compiled from "Requirements.scala"
public final class org.scalactic.RequirementsMacro$
  minor version: 0
  major version: 52
  flags: (0x0031) ACC_PUBLIC, ACC_FINAL, ACC_SUPER
  this_class: #2                          // org/scalactic/RequirementsMacro$
  super_class: #4                         // java/lang/Object
  interfaces: 0, fields: 1, methods: 10, attributes: 5
Constant pool:
    #1 = Utf8               org/scalactic/RequirementsMacro$
    #2 = Class              #1            // org/scalactic/RequirementsMacro$
    #3 = Utf8               java/lang/Object
    #4 = Class              #3            // java/lang/Object
    #5 = Utf8               Requirements.scala
    #6 = Utf8               java/lang/invoke/MethodHandles$Lookup
    #7 = Class              #6            // java/lang/invoke/MethodHandles$Lookup
    #8 = Utf8               java/lang/invoke/MethodHandles
    #9 = Class              #8            // java/lang/invoke/MethodHandles
   #10 = Utf8               Lookup
   #11 = Utf8               scala/reflect/api/Exprs$Expr
   #12 = Class              #11           // scala/reflect/api/Exprs$Expr
   #13 = Utf8               scala/reflect/api/Exprs
   #14 = Class              #13           // scala/reflect/api/Exprs
   #15 = Utf8               Expr
   #16 = Utf8               scala/reflect/api/Names$NameApi
   #17 = Class              #16           // scala/reflect/api/Names$NameApi
   #18 = Utf8               scala/reflect/api/Names
   #19 = Class              #18           // scala/reflect/api/Names
   #20 = Utf8               NameApi
   #21 = Utf8               scala/reflect/api/Names$TermNameApi
   #22 = Class              #21           // scala/reflect/api/Names$TermNameApi
   #23 = Utf8               TermNameApi
   #24 = Utf8               scala/reflect/api/Printers$BooleanFlag
   #25 = Class              #24           // scala/reflect/api/Printers$BooleanFlag
   #26 = Utf8               scala/reflect/api/Printers
   #27 = Class              #26           // scala/reflect/api/Printers
   #28 = Utf8               BooleanFlag
   #29 = Utf8               scala/reflect/api/Trees$ApplyApi
   #30 = Class              #29           // scala/reflect/api/Trees$ApplyApi
   #31 = Utf8               scala/reflect/api/Trees
   #32 = Class              #31           // scala/reflect/api/Trees
   #33 = Utf8               ApplyApi
   #34 = Utf8               scala/reflect/api/Trees$ApplyExtractor
   #35 = Class              #34           // scala/reflect/api/Trees$ApplyExtractor
   #36 = Utf8               ApplyExtractor
   #37 = Utf8               scala/reflect/api/Trees$IdentApi
   #38 = Class              #37           // scala/reflect/api/Trees$IdentApi
   #39 = Utf8               IdentApi
   #40 = Utf8               scala/reflect/api/Trees$IdentExtractor
   #41 = Class              #40           // scala/reflect/api/Trees$IdentExtractor
   #42 = Utf8               IdentExtractor
   #43 = Utf8               scala/reflect/api/Trees$SelectApi
   #44 = Class              #43           // scala/reflect/api/Trees$SelectApi
   #45 = Utf8               SelectApi
   #46 = Utf8               scala/reflect/api/Trees$SelectExtractor
   #47 = Class              #46           // scala/reflect/api/Trees$SelectExtractor
   #48 = Utf8               SelectExtractor
   #49 = Utf8               scala/reflect/api/Trees$TreeApi
   #50 = Class              #49           // scala/reflect/api/Trees$TreeApi
   #51 = Utf8               TreeApi
   #52 = Utf8               scala/reflect/api/TypeTags$WeakTypeTag
   #53 = Class              #52           // scala/reflect/api/TypeTags$WeakTypeTag
   #54 = Utf8               scala/reflect/api/TypeTags
   #55 = Class              #54           // scala/reflect/api/TypeTags
   #56 = Utf8               WeakTypeTag
   #57 = Utf8               scala/reflect/api/TypeTags$WeakTypeTag$
   #58 = Class              #57           // scala/reflect/api/TypeTags$WeakTypeTag$
   #59 = Utf8               WeakTypeTag$
   #60 = Utf8               MODULE$
   #61 = Utf8               Lorg/scalactic/RequirementsMacro$;
   #62 = Utf8               <clinit>
   #63 = Utf8               ()V
   #64 = Utf8               <init>
   #65 = NameAndType        #64:#63       // "<init>":()V
   #66 = Methodref          #2.#65        // org/scalactic/RequirementsMacro$."<init>":()V
   #67 = NameAndType        #60:#61       // MODULE$:Lorg/scalactic/RequirementsMacro$;
   #68 = Fieldref           #2.#67        // org/scalactic/RequirementsMacro$.MODULE$:Lorg/scalactic/RequirementsMacro$;
   #69 = Utf8               require
   #70 = Utf8               (Lscala/reflect/macros/whitebox/Context;Lscala/reflect/api/Exprs$Expr;Lscala/reflect/api/Exprs$Expr;)Lscala/reflect/api/Exprs$Expr;
   #71 = Utf8               (Lscala/reflect/macros/whitebox/Context;Lscala/reflect/api/Exprs$Expr<Ljava/lang/Object;>;Lscala/reflect/api/Exprs$Expr<Lorg/scalactic/Prettifier;>;)Lscala/reflect/api/Exprs$Expr<Lscala/runtime/BoxedUnit;>;
   #72 = Utf8               context
   #73 = Utf8               condition
   #74 = Utf8               prettifier
   #75 = Utf8               org/scalactic/BooleanMacro
   #76 = Class              #75           // org/scalactic/BooleanMacro
   #77 = Utf8               (Lscala/reflect/macros/whitebox/Context;)V
   #78 = NameAndType        #64:#77       // "<init>":(Lscala/reflect/macros/whitebox/Context;)V
   #79 = Methodref          #76.#78       // org/scalactic/BooleanMacro."<init>":(Lscala/reflect/macros/whitebox/Context;)V
   #80 = Utf8               scala/reflect/macros/whitebox/Context
   #81 = Class              #80           // scala/reflect/macros/whitebox/Context
   #82 = Utf8               universe
   #83 = Utf8               ()Lscala/reflect/macros/Universe;
   #84 = NameAndType        #82:#83       // universe:()Lscala/reflect/macros/Universe;
   #85 = InterfaceMethodref #81.#84       // scala/reflect/macros/whitebox/Context.universe:()Lscala/reflect/macros/Universe;
   #86 = Utf8               scala/reflect/macros/Universe
   #87 = Class              #86           // scala/reflect/macros/Universe
   #88 = Utf8               Select
   #89 = Utf8               ()Lscala/reflect/api/Trees$SelectExtractor;
   #90 = NameAndType        #88:#89       // Select:()Lscala/reflect/api/Trees$SelectExtractor;
   #91 = Methodref          #87.#90       // scala/reflect/macros/Universe.Select:()Lscala/reflect/api/Trees$SelectExtractor;
   #92 = Utf8               Ident
   #93 = Utf8               ()Lscala/reflect/api/Trees$IdentExtractor;
   #94 = NameAndType        #92:#93       // Ident:()Lscala/reflect/api/Trees$IdentExtractor;
   #95 = Methodref          #87.#94       // scala/reflect/macros/Universe.Ident:()Lscala/reflect/api/Trees$IdentExtractor;
   #96 = Utf8               _root_
   #97 = String             #96           // _root_
   #98 = Utf8               newTermName
   #99 = Utf8               (Ljava/lang/String;)Lscala/reflect/api/Names$TermNameApi;
  #100 = NameAndType        #98:#99       // newTermName:(Ljava/lang/String;)Lscala/reflect/api/Names$TermNameApi;
  #101 = Methodref          #87.#100      // scala/reflect/macros/Universe.newTermName:(Ljava/lang/String;)Lscala/reflect/api/Names$TermNameApi;
  #102 = Utf8               apply
  #103 = Utf8               (Lscala/reflect/api/Names$NameApi;)Lscala/reflect/api/Trees$IdentApi;
  #104 = NameAndType        #102:#103     // apply:(Lscala/reflect/api/Names$NameApi;)Lscala/reflect/api/Trees$IdentApi;
  #105 = Methodref          #41.#104      // scala/reflect/api/Trees$IdentExtractor.apply:(Lscala/reflect/api/Names$NameApi;)Lscala/reflect/api/Trees$IdentApi;
  #106 = Utf8               org
  #107 = String             #106          // org
  #108 = Utf8               (Lscala/reflect/api/Trees$TreeApi;Lscala/reflect/api/Names$NameApi;)Lscala/reflect/api/Trees$SelectApi;
  #109 = NameAndType        #102:#108     // apply:(Lscala/reflect/api/Trees$TreeApi;Lscala/reflect/api/Names$NameApi;)Lscala/reflect/api/Trees$SelectApi;
  #110 = Methodref          #47.#109      // scala/reflect/api/Trees$SelectExtractor.apply:(Lscala/reflect/api/Trees$TreeApi;Lscala/reflect/api/Names$NameApi;)Lscala/reflect/api/Trees$SelectApi;
  #111 = Utf8               scalactic
  #112 = String             #111          // scalactic
  #113 = Utf8               Requirements
  #114 = String             #113          // Requirements
  #115 = Utf8               requirementsHelper
  #116 = String             #115          // requirementsHelper
  #117 = Utf8               macroRequire
  #118 = String             #117          // macroRequire
  #119 = Utf8
  #120 = String             #119          //
  #121 = Utf8               literal
  #122 = Utf8               (Ljava/lang/String;)Lscala/reflect/api/Exprs$Expr;
  #123 = NameAndType        #121:#122     // literal:(Ljava/lang/String;)Lscala/reflect/api/Exprs$Expr;
  #124 = InterfaceMethodref #81.#123      // scala/reflect/macros/whitebox/Context.literal:(Ljava/lang/String;)Lscala/reflect/api/Exprs$Expr;
  #125 = Utf8               genMacro
  #126 = Utf8               (Lscala/reflect/api/Trees$TreeApi;Lscala/reflect/api/Exprs$Expr;Ljava/lang/String;Lscala/reflect/api/Exprs$Expr;Lscala/reflect/api/Exprs$Expr;)Lscala/reflect/api/Exprs$Expr;
  #127 = NameAndType        #125:#126     // genMacro:(Lscala/reflect/api/Trees$TreeApi;Lscala/reflect/api/Exprs$Expr;Ljava/lang/String;Lscala/reflect/api/Exprs$Expr;Lscala/reflect/api/Exprs$Expr;)Lscala/reflect/api/Exprs$Expr;
  #128 = Methodref          #76.#127      // org/scalactic/BooleanMacro.genMacro:(Lscala/reflect/api/Trees$TreeApi;Lscala/reflect/api/Exprs$Expr;Ljava/lang/String;Lscala/reflect/api/Exprs$Expr;Lscala/reflect/api/Exprs$Expr;)Lscala/reflect/api/Exprs$Expr;
  #129 = Utf8               this
  #130 = Utf8               Lscala/reflect/macros/whitebox/Context;
  #131 = Utf8               Lscala/reflect/api/Exprs$Expr;
  #132 = Utf8               requireWithClue
  #133 = Utf8               (Lscala/reflect/macros/whitebox/Context;Lscala/reflect/api/Exprs$Expr;Lscala/reflect/api/Exprs$Expr;Lscala/reflect/api/Exprs$Expr;)Lscala/reflect/api/Exprs$Expr;
  #134 = Utf8               (Lscala/reflect/macros/whitebox/Context;Lscala/reflect/api/Exprs$Expr<Ljava/lang/Object;>;Lscala/reflect/api/Exprs$Expr<Ljava/lang/Object;>;Lscala/reflect/api/Exprs$Expr<Lorg/scalactic/Prettifier;>;)Lscala/reflect/api/Exprs$Expr<Lscala/runtime/BoxedUnit;>;
  #135 = Utf8               clue
  #136 = Utf8               requireState
  #137 = Utf8               macroRequireState
  #138 = String             #137          // macroRequireState
  #139 = Utf8               requireStateWithClue
  #140 = Utf8               requireNonNull
  #141 = Utf8               (Lscala/reflect/macros/whitebox/Context;Lscala/collection/immutable/Seq;Lscala/reflect/api/Exprs$Expr;Lscala/reflect/api/Exprs$Expr;)Lscala/reflect/api/Exprs$Expr;
  #142 = Utf8               (Lscala/reflect/macros/whitebox/Context;Lscala/collection/immutable/Seq<Lscala/reflect/api/Exprs$Expr<Ljava/lang/Object;>;>;Lscala/reflect/api/Exprs$Expr<*>;Lscala/reflect/api/Exprs$Expr<*>;)Lscala/reflect/api/Exprs$Expr<Lscala/runtime/BoxedUnit;>;
  #143 = Utf8               arguments
  #144 = Utf8               pos
  #145 = Utf8               Apply
  #146 = Utf8               ()Lscala/reflect/api/Trees$ApplyExtractor;
  #147 = NameAndType        #145:#146     // Apply:()Lscala/reflect/api/Trees$ApplyExtractor;
  #148 = Methodref          #87.#147      // scala/reflect/macros/Universe.Apply:()Lscala/reflect/api/Trees$ApplyExtractor;
  #149 = Utf8               Array
  #150 = String             #149          // Array
  #151 = Utf8               (Ljava/lang/String;)Lscala/reflect/api/Trees$IdentApi;
  #152 = NameAndType        #92:#151      // Ident:(Ljava/lang/String;)Lscala/reflect/api/Trees$IdentApi;
  #153 = Methodref          #87.#152      // scala/reflect/macros/Universe.Ident:(Ljava/lang/String;)Lscala/reflect/api/Trees$IdentApi;
  #154 = String             #102          // apply
  #155 = Utf8               scala/package$
  #156 = Class              #155          // scala/package$
  #157 = Utf8               Lscala/package$;
  #158 = NameAndType        #60:#157      // MODULE$:Lscala/package$;
  #159 = Fieldref           #156.#158     // scala/package$.MODULE$:Lscala/package$;
  #160 = Utf8               List
  #161 = Utf8               ()Lscala/collection/immutable/List$;
  #162 = NameAndType        #160:#161     // List:()Lscala/collection/immutable/List$;
  #163 = Methodref          #156.#162     // scala/package$.List:()Lscala/collection/immutable/List$;
  #164 = Utf8               (Ljava/lang/Object;)Ljava/lang/Object;
  #165 = MethodType         #164          //  (Ljava/lang/Object;)Ljava/lang/Object;
  #166 = Utf8               $anonfun$requireNonNull$1
  #167 = Utf8               (Lscala/reflect/macros/whitebox/Context;Lscala/reflect/api/Exprs$Expr;)Lscala/reflect/api/Trees$TreeApi;
  #168 = NameAndType        #166:#167     // $anonfun$requireNonNull$1:(Lscala/reflect/macros/whitebox/Context;Lscala/reflect/api/Exprs$Expr;)Lscala/reflect/api/Trees$TreeApi;
  #169 = Methodref          #2.#168       // org/scalactic/RequirementsMacro$.$anonfun$requireNonNull$1:(Lscala/reflect/macros/whitebox/Context;Lscala/reflect/api/Exprs$Expr;)Lscala/reflect/api/Trees$TreeApi;
  #170 = MethodHandle       6:#169        // REF_invokeStatic org/scalactic/RequirementsMacro$.$anonfun$requireNonNull$1:(Lscala/reflect/macros/whitebox/Context;Lscala/reflect/api/Exprs$Expr;)Lscala/reflect/api/Trees$TreeApi;
  #171 = Utf8               (Lscala/reflect/api/Exprs$Expr;)Lscala/reflect/api/Trees$TreeApi;
  #172 = MethodType         #171          //  (Lscala/reflect/api/Exprs$Expr;)Lscala/reflect/api/Trees$TreeApi;
  #173 = Integer            5
  #174 = Integer            1
  #175 = Utf8               java/lang/invoke/LambdaMetafactory
  #176 = Class              #175          // java/lang/invoke/LambdaMetafactory
  #177 = Utf8               altMetafactory
  #178 = Utf8               (Ljava/lang/invoke/MethodHandles$Lookup;Ljava/lang/String;Ljava/lang/invoke/MethodType;[Ljava/lang/Object;)Ljava/lang/invoke/CallSite;
  #179 = NameAndType        #177:#178     // altMetafactory:(Ljava/lang/invoke/MethodHandles$Lookup;Ljava/lang/String;Ljava/lang/invoke/MethodType;[Ljava/lang/Object;)Ljava/lang/invoke/CallSite;
  #180 = Methodref          #176.#179     // java/lang/invoke/LambdaMetafactory.altMetafactory:(Ljava/lang/invoke/MethodHandles$Lookup;Ljava/lang/String;Ljava/lang/invoke/MethodType;[Ljava/lang/Object;)Ljava/lang/invoke/CallSite;
  #181 = MethodHandle       6:#180        // REF_invokeStatic java/lang/invoke/LambdaMetafactory.altMetafactory:(Ljava/lang/invoke/MethodHandles$Lookup;Ljava/lang/String;Ljava/lang/invoke/MethodType;[Ljava/lang/Object;)Ljava/lang/invoke/CallSite;
  #182 = Utf8               (Lscala/reflect/macros/whitebox/Context;)Lscala/Function1;
  #183 = NameAndType        #102:#182     // apply:(Lscala/reflect/macros/whitebox/Context;)Lscala/Function1;
  #184 = InvokeDynamic      #0:#183       // #0:apply:(Lscala/reflect/macros/whitebox/Context;)Lscala/Function1;
  #185 = Utf8               scala/collection/immutable/Seq
  #186 = Class              #185          // scala/collection/immutable/Seq
  #187 = Utf8               map
  #188 = Utf8               (Lscala/Function1;)Ljava/lang/Object;
  #189 = NameAndType        #187:#188     // map:(Lscala/Function1;)Ljava/lang/Object;
  #190 = InterfaceMethodref #186.#189     // scala/collection/immutable/Seq.map:(Lscala/Function1;)Ljava/lang/Object;
  #191 = Utf8               scala/collection/immutable/List$
  #192 = Class              #191          // scala/collection/immutable/List$
  #193 = Utf8               (Lscala/collection/immutable/Seq;)Ljava/lang/Object;
  #194 = NameAndType        #102:#193     // apply:(Lscala/collection/immutable/Seq;)Ljava/lang/Object;
  #195 = Methodref          #192.#194     // scala/collection/immutable/List$.apply:(Lscala/collection/immutable/Seq;)Ljava/lang/Object;
  #196 = Utf8               scala/collection/immutable/List
  #197 = Class              #196          // scala/collection/immutable/List
  #198 = Utf8               (Lscala/reflect/api/Trees$TreeApi;Lscala/collection/immutable/List;)Lscala/reflect/api/Trees$ApplyApi;
  #199 = NameAndType        #102:#198     // apply:(Lscala/reflect/api/Trees$TreeApi;Lscala/collection/immutable/List;)Lscala/reflect/api/Trees$ApplyApi;
  #200 = Methodref          #35.#199      // scala/reflect/api/Trees$ApplyExtractor.apply:(Lscala/reflect/api/Trees$TreeApi;Lscala/collection/immutable/List;)Lscala/reflect/api/Trees$ApplyApi;
  #201 = Utf8               $anonfun$requireNonNull$2
  #202 = NameAndType        #201:#171     // $anonfun$requireNonNull$2:(Lscala/reflect/api/Exprs$Expr;)Lscala/reflect/api/Trees$TreeApi;
  #203 = Methodref          #2.#202       // org/scalactic/RequirementsMacro$.$anonfun$requireNonNull$2:(Lscala/reflect/api/Exprs$Expr;)Lscala/reflect/api/Trees$TreeApi;
  #204 = MethodHandle       6:#203        // REF_invokeStatic org/scalactic/RequirementsMacro$.$anonfun$requireNonNull$2:(Lscala/reflect/api/Exprs$Expr;)Lscala/reflect/api/Trees$TreeApi;
  #205 = Utf8               ()Lscala/Function1;
  #206 = NameAndType        #102:#205     // apply:()Lscala/Function1;
  #207 = InvokeDynamic      #1:#206       // #1:apply:()Lscala/Function1;
  #208 = Utf8               macroRequireNonNull
  #209 = String             #208          // macroRequireNonNull
  #210 = Utf8               scala/runtime/ScalaRunTime$
  #211 = Class              #210          // scala/runtime/ScalaRunTime$
  #212 = Utf8               Lscala/runtime/ScalaRunTime$;
  #213 = NameAndType        #60:#212      // MODULE$:Lscala/runtime/ScalaRunTime$;
  #214 = Fieldref           #211.#213     // scala/runtime/ScalaRunTime$.MODULE$:Lscala/runtime/ScalaRunTime$;
  #215 = Utf8               tree
  #216 = Utf8               ()Lscala/reflect/api/Trees$TreeApi;
  #217 = NameAndType        #215:#216     // tree:()Lscala/reflect/api/Trees$TreeApi;
  #218 = InterfaceMethodref #12.#217      // scala/reflect/api/Exprs$Expr.tree:()Lscala/reflect/api/Trees$TreeApi;
  #219 = Utf8               [Ljava/lang/Object;
  #220 = Class              #219          // "[Ljava/lang/Object;"
  #221 = Utf8               wrapRefArray
  #222 = Utf8               ([Ljava/lang/Object;)Lscala/collection/immutable/ArraySeq;
  #223 = NameAndType        #221:#222     // wrapRefArray:([Ljava/lang/Object;)Lscala/collection/immutable/ArraySeq;
  #224 = Methodref          #211.#223     // scala/runtime/ScalaRunTime$.wrapRefArray:([Ljava/lang/Object;)Lscala/collection/immutable/ArraySeq;
  #225 = Utf8               ()Lscala/reflect/api/TypeTags$WeakTypeTag$;
  #226 = NameAndType        #56:#225      // WeakTypeTag:()Lscala/reflect/api/TypeTags$WeakTypeTag$;
  #227 = Methodref          #87.#226      // scala/reflect/macros/Universe.WeakTypeTag:()Lscala/reflect/api/TypeTags$WeakTypeTag$;
  #228 = Utf8               Nothing
  #229 = Utf8               ()Lscala/reflect/api/TypeTags$WeakTypeTag;
  #230 = NameAndType        #228:#229     // Nothing:()Lscala/reflect/api/TypeTags$WeakTypeTag;
  #231 = Methodref          #58.#230      // scala/reflect/api/TypeTags$WeakTypeTag$.Nothing:()Lscala/reflect/api/TypeTags$WeakTypeTag;
  #232 = Utf8               (Lscala/reflect/api/Trees$TreeApi;Lscala/reflect/api/TypeTags$WeakTypeTag;)Lscala/reflect/api/Exprs$Expr;
  #233 = NameAndType        #15:#232      // Expr:(Lscala/reflect/api/Trees$TreeApi;Lscala/reflect/api/TypeTags$WeakTypeTag;)Lscala/reflect/api/Exprs$Expr;
  #234 = InterfaceMethodref #81.#233      // scala/reflect/macros/whitebox/Context.Expr:(Lscala/reflect/api/Trees$TreeApi;Lscala/reflect/api/TypeTags$WeakTypeTag;)Lscala/reflect/api/Exprs$Expr;
  #235 = Utf8               variablesNamesArray
  #236 = Utf8               Lscala/reflect/api/Trees$ApplyApi;
  #237 = Utf8               argumentsArray
  #238 = Utf8               Lscala/collection/immutable/Seq;
  #239 = Utf8               context$1
  #240 = Utf8               e
  #241 = Utf8               show$default$2
  #242 = Utf8               ()Lscala/reflect/api/Printers$BooleanFlag;
  #243 = NameAndType        #241:#242     // show$default$2:()Lscala/reflect/api/Printers$BooleanFlag;
  #244 = Methodref          #87.#243      // scala/reflect/macros/Universe.show$default$2:()Lscala/reflect/api/Printers$BooleanFlag;
  #245 = Utf8               show$default$3
  #246 = NameAndType        #245:#242     // show$default$3:()Lscala/reflect/api/Printers$BooleanFlag;
  #247 = Methodref          #87.#246      // scala/reflect/macros/Universe.show$default$3:()Lscala/reflect/api/Printers$BooleanFlag;
  #248 = Utf8               show$default$4
  #249 = NameAndType        #248:#242     // show$default$4:()Lscala/reflect/api/Printers$BooleanFlag;
  #250 = Methodref          #87.#249      // scala/reflect/macros/Universe.show$default$4:()Lscala/reflect/api/Printers$BooleanFlag;
  #251 = Utf8               show$default$5
  #252 = NameAndType        #251:#242     // show$default$5:()Lscala/reflect/api/Printers$BooleanFlag;
  #253 = Methodref          #87.#252      // scala/reflect/macros/Universe.show$default$5:()Lscala/reflect/api/Printers$BooleanFlag;
  #254 = Utf8               show$default$6
  #255 = NameAndType        #254:#242     // show$default$6:()Lscala/reflect/api/Printers$BooleanFlag;
  #256 = Methodref          #87.#255      // scala/reflect/macros/Universe.show$default$6:()Lscala/reflect/api/Printers$BooleanFlag;
  #257 = Utf8               show$default$7
  #258 = NameAndType        #257:#242     // show$default$7:()Lscala/reflect/api/Printers$BooleanFlag;
  #259 = Methodref          #87.#258      // scala/reflect/macros/Universe.show$default$7:()Lscala/reflect/api/Printers$BooleanFlag;
  #260 = Utf8               show
  #261 = Utf8               (Ljava/lang/Object;Lscala/reflect/api/Printers$BooleanFlag;Lscala/reflect/api/Printers$BooleanFlag;Lscala/reflect/api/Printers$BooleanFlag;Lscala/reflect/api/Printers$BooleanFlag;Lscala/reflect/api/Printers$BooleanFlag;Lscala/reflect/api/Printers$BooleanFlag;)Ljava/lang/String;
  #262 = NameAndType        #260:#261     // show:(Ljava/lang/Object;Lscala/reflect/api/Printers$BooleanFlag;Lscala/reflect/api/Printers$BooleanFlag;Lscala/reflect/api/Printers$BooleanFlag;Lscala/reflect/api/Printers$BooleanFlag;Lscala/reflect/api/Printers$BooleanFlag;Lscala/reflect/api/Printers$BooleanFlag;)Ljava/lang/String;
  #263 = Methodref          #87.#262      // scala/reflect/macros/Universe.show:(Ljava/lang/Object;Lscala/reflect/api/Printers$BooleanFlag;Lscala/reflect/api/Printers$BooleanFlag;Lscala/reflect/api/Printers$BooleanFlag;Lscala/reflect/api/Printers$BooleanFlag;Lscala/reflect/api/Printers$BooleanFlag;Lscala/reflect/api/Printers$BooleanFlag;)Ljava/lang/String;
  #264 = Methodref          #4.#65        // java/lang/Object."<init>":()V
  #265 = Utf8               $deserializeLambda$
  #266 = Utf8               (Ljava/lang/invoke/SerializedLambda;)Ljava/lang/Object;
  #267 = Utf8               scala/runtime/LambdaDeserialize
  #268 = Class              #267          // scala/runtime/LambdaDeserialize
  #269 = Utf8               bootstrap
  #270 = Utf8               (Ljava/lang/invoke/MethodHandles$Lookup;Ljava/lang/String;Ljava/lang/invoke/MethodType;[Ljava/lang/invoke/MethodHandle;)Ljava/lang/invoke/CallSite;
  #271 = NameAndType        #269:#270     // bootstrap:(Ljava/lang/invoke/MethodHandles$Lookup;Ljava/lang/String;Ljava/lang/invoke/MethodType;[Ljava/lang/invoke/MethodHandle;)Ljava/lang/invoke/CallSite;
  #272 = Methodref          #268.#271     // scala/runtime/LambdaDeserialize.bootstrap:(Ljava/lang/invoke/MethodHandles$Lookup;Ljava/lang/String;Ljava/lang/invoke/MethodType;[Ljava/lang/invoke/MethodHandle;)Ljava/lang/invoke/CallSite;
  #273 = MethodHandle       6:#272        // REF_invokeStatic scala/runtime/LambdaDeserialize.bootstrap:(Ljava/lang/invoke/MethodHandles$Lookup;Ljava/lang/String;Ljava/lang/invoke/MethodType;[Ljava/lang/invoke/MethodHandle;)Ljava/lang/invoke/CallSite;
  #274 = Utf8               lambdaDeserialize
  #275 = NameAndType        #274:#266     // lambdaDeserialize:(Ljava/lang/invoke/SerializedLambda;)Ljava/lang/Object;
  #276 = InvokeDynamic      #2:#275       // #2:lambdaDeserialize:(Ljava/lang/invoke/SerializedLambda;)Ljava/lang/Object;
  #277 = Utf8               Code
  #278 = Utf8               LineNumberTable
  #279 = Utf8               LocalVariableTable
  #280 = Utf8               Signature
  #281 = Utf8               MethodParameters
  #282 = Utf8               InnerClasses
  #283 = Utf8               SourceFile
  #284 = Utf8               BootstrapMethods
  #285 = Utf8               ScalaInlineInfo
  #286 = Utf8               Scala
{
  public static final org.scalactic.RequirementsMacro$ MODULE$;
    descriptor: Lorg/scalactic/RequirementsMacro$;
    flags: (0x0019) ACC_PUBLIC, ACC_STATIC, ACC_FINAL

  public static {};
    descriptor: ()V
    flags: (0x0009) ACC_PUBLIC, ACC_STATIC
    Code:
      stack=2, locals=0, args_size=0
         0: new           #2                  // class org/scalactic/RequirementsMacro$
         3: dup
         4: invokespecial #66                 // Method "<init>":()V
         7: putstatic     #68                 // Field MODULE$:Lorg/scalactic/RequirementsMacro$;
        10: return
      LineNumberTable:
        line 220: 0

  public scala.reflect.api.Exprs$Expr<scala.runtime.BoxedUnit> require(scala.reflect.macros.whitebox.Context, scala.reflect.api.Exprs$Expr<java.lang.Object>, scala.reflect.api.Exprs$Expr<org.scalactic.Prettifier>);
    descriptor: (Lscala/reflect/macros/whitebox/Context;Lscala/reflect/api/Exprs$Expr;Lscala/reflect/api/Exprs$Expr;)Lscala/reflect/api/Exprs$Expr;
    flags: (0x0001) ACC_PUBLIC
    Code:
      stack=8, locals=6, args_size=4
         0: aload_2
         1: astore        4
         3: aload_3
         4: astore        5
         6: new           #76                 // class org/scalactic/BooleanMacro
         9: dup
        10: aload_1
        11: invokespecial #79                 // Method org/scalactic/BooleanMacro."<init>":(Lscala/reflect/macros/whitebox/Context;)V
        14: aload_1
        15: invokeinterface #85,  1           // InterfaceMethod scala/reflect/macros/whitebox/Context.universe:()Lscala/reflect/macros/Universe;
        20: invokevirtual #91                 // Method scala/reflect/macros/Universe.Select:()Lscala/reflect/api/Trees$SelectExtractor;
        23: aload_1
        24: invokeinterface #85,  1           // InterfaceMethod scala/reflect/macros/whitebox/Context.universe:()Lscala/reflect/macros/Universe;
        29: invokevirtual #91                 // Method scala/reflect/macros/Universe.Select:()Lscala/reflect/api/Trees$SelectExtractor;
        32: aload_1
        33: invokeinterface #85,  1           // InterfaceMethod scala/reflect/macros/whitebox/Context.universe:()Lscala/reflect/macros/Universe;
        38: invokevirtual #91                 // Method scala/reflect/macros/Universe.Select:()Lscala/reflect/api/Trees$SelectExtractor;
        41: aload_1
        42: invokeinterface #85,  1           // InterfaceMethod scala/reflect/macros/whitebox/Context.universe:()Lscala/reflect/macros/Universe;
        47: invokevirtual #91                 // Method scala/reflect/macros/Universe.Select:()Lscala/reflect/api/Trees$SelectExtractor;
        50: aload_1
        51: invokeinterface #85,  1           // InterfaceMethod scala/reflect/macros/whitebox/Context.universe:()Lscala/reflect/macros/Universe;
        56: invokevirtual #95                 // Method scala/reflect/macros/Universe.Ident:()Lscala/reflect/api/Trees$IdentExtractor;
        59: aload_1
        60: invokeinterface #85,  1           // InterfaceMethod scala/reflect/macros/whitebox/Context.universe:()Lscala/reflect/macros/Universe;
        65: ldc           #97                 // String _root_
        67: invokevirtual #101                // Method scala/reflect/macros/Universe.newTermName:(Ljava/lang/String;)Lscala/reflect/api/Names$TermNameApi;
        70: checkcast     #17                 // class scala/reflect/api/Names$NameApi
        73: invokevirtual #105                // Method scala/reflect/api/Trees$IdentExtractor.apply:(Lscala/reflect/api/Names$NameApi;)Lscala/reflect/api/Trees$IdentApi;
        76: aload_1
        77: invokeinterface #85,  1           // InterfaceMethod scala/reflect/macros/whitebox/Context.universe:()Lscala/reflect/macros/Universe;
        82: ldc           #107                // String org
        84: invokevirtual #101                // Method scala/reflect/macros/Universe.newTermName:(Ljava/lang/String;)Lscala/reflect/api/Names$TermNameApi;
        87: checkcast     #17                 // class scala/reflect/api/Names$NameApi
        90: invokevirtual #110                // Method scala/reflect/api/Trees$SelectExtractor.apply:(Lscala/reflect/api/Trees$TreeApi;Lscala/reflect/api/Names$NameApi;)Lscala/reflect/api/Trees$SelectApi;
        93: aload_1
        94: invokeinterface #85,  1           // InterfaceMethod scala/reflect/macros/whitebox/Context.universe:()Lscala/reflect/macros/Universe;
        99: ldc           #112                // String scalactic
       101: invokevirtual #101                // Method scala/reflect/macros/Universe.newTermName:(Ljava/lang/String;)Lscala/reflect/api/Names$TermNameApi;
       104: checkcast     #17                 // class scala/reflect/api/Names$NameApi
       107: invokevirtual #110                // Method scala/reflect/api/Trees$SelectExtractor.apply:(Lscala/reflect/api/Trees$TreeApi;Lscala/reflect/api/Names$NameApi;)Lscala/reflect/api/Trees$SelectApi;
       110: aload_1
       111: invokeinterface #85,  1           // InterfaceMethod scala/reflect/macros/whitebox/Context.universe:()Lscala/reflect/macros/Universe;
       116: ldc           #114                // String Requirements
       118: invokevirtual #101                // Method scala/reflect/macros/Universe.newTermName:(Ljava/lang/String;)Lscala/reflect/api/Names$TermNameApi;
       121: checkcast     #17                 // class scala/reflect/api/Names$NameApi
       124: invokevirtual #110                // Method scala/reflect/api/Trees$SelectExtractor.apply:(Lscala/reflect/api/Trees$TreeApi;Lscala/reflect/api/Names$NameApi;)Lscala/reflect/api/Trees$SelectApi;
       127: aload_1
       128: invokeinterface #85,  1           // InterfaceMethod scala/reflect/macros/whitebox/Context.universe:()Lscala/reflect/macros/Universe;
       133: ldc           #116                // String requirementsHelper
       135: invokevirtual #101                // Method scala/reflect/macros/Universe.newTermName:(Ljava/lang/String;)Lscala/reflect/api/Names$TermNameApi;
       138: checkcast     #17                 // class scala/reflect/api/Names$NameApi
       141: invokevirtual #110                // Method scala/reflect/api/Trees$SelectExtractor.apply:(Lscala/reflect/api/Trees$TreeApi;Lscala/reflect/api/Names$NameApi;)Lscala/reflect/api/Trees$SelectApi;
       144: aload         4
       146: ldc           #118                // String macroRequire
       148: aload_1
       149: ldc           #120                // String
       151: invokeinterface #124,  2          // InterfaceMethod scala/reflect/macros/whitebox/Context.literal:(Ljava/lang/String;)Lscala/reflect/api/Exprs$Expr;
       156: aload         5
       158: invokevirtual #128                // Method org/scalactic/BooleanMacro.genMacro:(Lscala/reflect/api/Trees$TreeApi;Lscala/reflect/api/Exprs$Expr;Ljava/lang/String;Lscala/reflect/api/Exprs$Expr;Lscala/reflect/api/Exprs$Expr;)Lscala/reflect/api/Exprs$Expr;
       161: areturn
      LineNumberTable:
        line 229: 0
        line 231: 6
        line 232: 14
        line 233: 23
        line 234: 32
        line 235: 41
        line 236: 50
        line 237: 76
        line 239: 93
        line 241: 110
        line 243: 127
        line 245: 144
        line 246: 146
        line 247: 148
        line 248: 156
      LocalVariableTable:
        Start  Length  Slot  Name   Signature
            0     162     0  this   Lorg/scalactic/RequirementsMacro$;
            0     162     1 context   Lscala/reflect/macros/whitebox/Context;
            0     162     2 condition   Lscala/reflect/api/Exprs$Expr;
            0     162     3 prettifier   Lscala/reflect/api/Exprs$Expr;
    Signature: #71                          // (Lscala/reflect/macros/whitebox/Context;Lscala/reflect/api/Exprs$Expr<Ljava/lang/Object;>;Lscala/reflect/api/Exprs$Expr<Lorg/scalactic/Prettifier;>;)Lscala/reflect/api/Exprs$Expr<Lscala/runtime/BoxedUnit;>;
    MethodParameters:
      Name                           Flags
      context                        final
      condition                      final
      prettifier                     final

  public scala.reflect.api.Exprs$Expr<scala.runtime.BoxedUnit> requireWithClue(scala.reflect.macros.whitebox.Context, scala.reflect.api.Exprs$Expr<java.lang.Object>, scala.reflect.api.Exprs$Expr<java.lang.Object>, scala.reflect.api.Exprs$Expr<org.scalactic.Prettifier>);
    descriptor: (Lscala/reflect/macros/whitebox/Context;Lscala/reflect/api/Exprs$Expr;Lscala/reflect/api/Exprs$Expr;Lscala/reflect/api/Exprs$Expr;)Lscala/reflect/api/Exprs$Expr;
    flags: (0x0001) ACC_PUBLIC
    Code:
      stack=8, locals=8, args_size=5
         0: aload_2
         1: astore        5
         3: aload_3
         4: astore        6
         6: aload         4
         8: astore        7
        10: new           #76                 // class org/scalactic/BooleanMacro
        13: dup
        14: aload_1
        15: invokespecial #79                 // Method org/scalactic/BooleanMacro."<init>":(Lscala/reflect/macros/whitebox/Context;)V
        18: aload_1
        19: invokeinterface #85,  1           // InterfaceMethod scala/reflect/macros/whitebox/Context.universe:()Lscala/reflect/macros/Universe;
        24: invokevirtual #91                 // Method scala/reflect/macros/Universe.Select:()Lscala/reflect/api/Trees$SelectExtractor;
        27: aload_1
        28: invokeinterface #85,  1           // InterfaceMethod scala/reflect/macros/whitebox/Context.universe:()Lscala/reflect/macros/Universe;
        33: invokevirtual #91                 // Method scala/reflect/macros/Universe.Select:()Lscala/reflect/api/Trees$SelectExtractor;
        36: aload_1
        37: invokeinterface #85,  1           // InterfaceMethod scala/reflect/macros/whitebox/Context.universe:()Lscala/reflect/macros/Universe;
        42: invokevirtual #91                 // Method scala/reflect/macros/Universe.Select:()Lscala/reflect/api/Trees$SelectExtractor;
        45: aload_1
        46: invokeinterface #85,  1           // InterfaceMethod scala/reflect/macros/whitebox/Context.universe:()Lscala/reflect/macros/Universe;
        51: invokevirtual #91                 // Method scala/reflect/macros/Universe.Select:()Lscala/reflect/api/Trees$SelectExtractor;
        54: aload_1
        55: invokeinterface #85,  1           // InterfaceMethod scala/reflect/macros/whitebox/Context.universe:()Lscala/reflect/macros/Universe;
        60: invokevirtual #95                 // Method scala/reflect/macros/Universe.Ident:()Lscala/reflect/api/Trees$IdentExtractor;
        63: aload_1
        64: invokeinterface #85,  1           // InterfaceMethod scala/reflect/macros/whitebox/Context.universe:()Lscala/reflect/macros/Universe;
        69: ldc           #97                 // String _root_
        71: invokevirtual #101                // Method scala/reflect/macros/Universe.newTermName:(Ljava/lang/String;)Lscala/reflect/api/Names$TermNameApi;
        74: checkcast     #17                 // class scala/reflect/api/Names$NameApi
        77: invokevirtual #105                // Method scala/reflect/api/Trees$IdentExtractor.apply:(Lscala/reflect/api/Names$NameApi;)Lscala/reflect/api/Trees$IdentApi;
        80: aload_1
        81: invokeinterface #85,  1           // InterfaceMethod scala/reflect/macros/whitebox/Context.universe:()Lscala/reflect/macros/Universe;
        86: ldc           #107                // String org
        88: invokevirtual #101                // Method scala/reflect/macros/Universe.newTermName:(Ljava/lang/String;)Lscala/reflect/api/Names$TermNameApi;
        91: checkcast     #17                 // class scala/reflect/api/Names$NameApi
        94: invokevirtual #110                // Method scala/reflect/api/Trees$SelectExtractor.apply:(Lscala/reflect/api/Trees$TreeApi;Lscala/reflect/api/Names$NameApi;)Lscala/reflect/api/Trees$SelectApi;
        97: aload_1
        98: invokeinterface #85,  1           // InterfaceMethod scala/reflect/macros/whitebox/Context.universe:()Lscala/reflect/macros/Universe;
       103: ldc           #112                // String scalactic
       105: invokevirtual #101                // Method scala/reflect/macros/Universe.newTermName:(Ljava/lang/String;)Lscala/reflect/api/Names$TermNameApi;
       108: checkcast     #17                 // class scala/reflect/api/Names$NameApi
       111: invokevirtual #110                // Method scala/reflect/api/Trees$SelectExtractor.apply:(Lscala/reflect/api/Trees$TreeApi;Lscala/reflect/api/Names$NameApi;)Lscala/reflect/api/Trees$SelectApi;
       114: aload_1
       115: invokeinterface #85,  1           // InterfaceMethod scala/reflect/macros/whitebox/Context.universe:()Lscala/reflect/macros/Universe;
       120: ldc           #114                // String Requirements
       122: invokevirtual #101                // Method scala/reflect/macros/Universe.newTermName:(Ljava/lang/String;)Lscala/reflect/api/Names$TermNameApi;
       125: checkcast     #17                 // class scala/reflect/api/Names$NameApi
       128: invokevirtual #110                // Method scala/reflect/api/Trees$SelectExtractor.apply:(Lscala/reflect/api/Trees$TreeApi;Lscala/reflect/api/Names$NameApi;)Lscala/reflect/api/Trees$SelectApi;
       131: aload_1
       132: invokeinterface #85,  1           // InterfaceMethod scala/reflect/macros/whitebox/Context.universe:()Lscala/reflect/macros/Universe;
       137: ldc           #116                // String requirementsHelper
       139: invokevirtual #101                // Method scala/reflect/macros/Universe.newTermName:(Ljava/lang/String;)Lscala/reflect/api/Names$TermNameApi;
       142: checkcast     #17                 // class scala/reflect/api/Names$NameApi
       145: invokevirtual #110                // Method scala/reflect/api/Trees$SelectExtractor.apply:(Lscala/reflect/api/Trees$TreeApi;Lscala/reflect/api/Names$NameApi;)Lscala/reflect/api/Trees$SelectApi;
       148: aload         5
       150: ldc           #118                // String macroRequire
       152: aload         6
       154: aload         7
       156: invokevirtual #128                // Method org/scalactic/BooleanMacro.genMacro:(Lscala/reflect/api/Trees$TreeApi;Lscala/reflect/api/Exprs$Expr;Ljava/lang/String;Lscala/reflect/api/Exprs$Expr;Lscala/reflect/api/Exprs$Expr;)Lscala/reflect/api/Exprs$Expr;
       159: areturn
      LineNumberTable:
        line 259: 0
        line 261: 10
        line 262: 18
        line 263: 27
        line 264: 36
        line 265: 45
        line 266: 54
        line 267: 80
        line 269: 97
        line 271: 114
        line 273: 131
        line 275: 148
        line 276: 150
        line 277: 152
        line 278: 154
      LocalVariableTable:
        Start  Length  Slot  Name   Signature
            0     160     0  this   Lorg/scalactic/RequirementsMacro$;
            0     160     1 context   Lscala/reflect/macros/whitebox/Context;
            0     160     2 condition   Lscala/reflect/api/Exprs$Expr;
            0     160     3  clue   Lscala/reflect/api/Exprs$Expr;
            0     160     4 prettifier   Lscala/reflect/api/Exprs$Expr;
    Signature: #134                         // (Lscala/reflect/macros/whitebox/Context;Lscala/reflect/api/Exprs$Expr<Ljava/lang/Object;>;Lscala/reflect/api/Exprs$Expr<Ljava/lang/Object;>;Lscala/reflect/api/Exprs$Expr<Lorg/scalactic/Prettifier;>;)Lscala/reflect/api/Exprs$Expr<Lscala/runtime/BoxedUnit;>;
    MethodParameters:
      Name                           Flags
      context                        final
      condition                      final
      clue                           final
      prettifier                     final

  public scala.reflect.api.Exprs$Expr<scala.runtime.BoxedUnit> requireState(scala.reflect.macros.whitebox.Context, scala.reflect.api.Exprs$Expr<java.lang.Object>, scala.reflect.api.Exprs$Expr<org.scalactic.Prettifier>);
    descriptor: (Lscala/reflect/macros/whitebox/Context;Lscala/reflect/api/Exprs$Expr;Lscala/reflect/api/Exprs$Expr;)Lscala/reflect/api/Exprs$Expr;
    flags: (0x0001) ACC_PUBLIC
    Code:
      stack=8, locals=6, args_size=4
         0: aload_2
         1: astore        4
         3: aload_3
         4: astore        5
         6: new           #76                 // class org/scalactic/BooleanMacro
         9: dup
        10: aload_1
        11: invokespecial #79                 // Method org/scalactic/BooleanMacro."<init>":(Lscala/reflect/macros/whitebox/Context;)V
        14: aload_1
        15: invokeinterface #85,  1           // InterfaceMethod scala/reflect/macros/whitebox/Context.universe:()Lscala/reflect/macros/Universe;
        20: invokevirtual #91                 // Method scala/reflect/macros/Universe.Select:()Lscala/reflect/api/Trees$SelectExtractor;
        23: aload_1
        24: invokeinterface #85,  1           // InterfaceMethod scala/reflect/macros/whitebox/Context.universe:()Lscala/reflect/macros/Universe;
        29: invokevirtual #91                 // Method scala/reflect/macros/Universe.Select:()Lscala/reflect/api/Trees$SelectExtractor;
        32: aload_1
        33: invokeinterface #85,  1           // InterfaceMethod scala/reflect/macros/whitebox/Context.universe:()Lscala/reflect/macros/Universe;
        38: invokevirtual #91                 // Method scala/reflect/macros/Universe.Select:()Lscala/reflect/api/Trees$SelectExtractor;
        41: aload_1
        42: invokeinterface #85,  1           // InterfaceMethod scala/reflect/macros/whitebox/Context.universe:()Lscala/reflect/macros/Universe;
        47: invokevirtual #91                 // Method scala/reflect/macros/Universe.Select:()Lscala/reflect/api/Trees$SelectExtractor;
        50: aload_1
        51: invokeinterface #85,  1           // InterfaceMethod scala/reflect/macros/whitebox/Context.universe:()Lscala/reflect/macros/Universe;
        56: invokevirtual #95                 // Method scala/reflect/macros/Universe.Ident:()Lscala/reflect/api/Trees$IdentExtractor;
        59: aload_1
        60: invokeinterface #85,  1           // InterfaceMethod scala/reflect/macros/whitebox/Context.universe:()Lscala/reflect/macros/Universe;
        65: ldc           #97                 // String _root_
        67: invokevirtual #101                // Method scala/reflect/macros/Universe.newTermName:(Ljava/lang/String;)Lscala/reflect/api/Names$TermNameApi;
        70: checkcast     #17                 // class scala/reflect/api/Names$NameApi
        73: invokevirtual #105                // Method scala/reflect/api/Trees$IdentExtractor.apply:(Lscala/reflect/api/Names$NameApi;)Lscala/reflect/api/Trees$IdentApi;
        76: aload_1
        77: invokeinterface #85,  1           // InterfaceMethod scala/reflect/macros/whitebox/Context.universe:()Lscala/reflect/macros/Universe;
        82: ldc           #107                // String org
        84: invokevirtual #101                // Method scala/reflect/macros/Universe.newTermName:(Ljava/lang/String;)Lscala/reflect/api/Names$TermNameApi;
        87: checkcast     #17                 // class scala/reflect/api/Names$NameApi
        90: invokevirtual #110                // Method scala/reflect/api/Trees$SelectExtractor.apply:(Lscala/reflect/api/Trees$TreeApi;Lscala/reflect/api/Names$NameApi;)Lscala/reflect/api/Trees$SelectApi;
        93: aload_1
        94: invokeinterface #85,  1           // InterfaceMethod scala/reflect/macros/whitebox/Context.universe:()Lscala/reflect/macros/Universe;
        99: ldc           #112                // String scalactic
       101: invokevirtual #101                // Method scala/reflect/macros/Universe.newTermName:(Ljava/lang/String;)Lscala/reflect/api/Names$TermNameApi;
       104: checkcast     #17                 // class scala/reflect/api/Names$NameApi
       107: invokevirtual #110                // Method scala/reflect/api/Trees$SelectExtractor.apply:(Lscala/reflect/api/Trees$TreeApi;Lscala/reflect/api/Names$NameApi;)Lscala/reflect/api/Trees$SelectApi;
       110: aload_1
       111: invokeinterface #85,  1           // InterfaceMethod scala/reflect/macros/whitebox/Context.universe:()Lscala/reflect/macros/Universe;
       116: ldc           #114                // String Requirements
       118: invokevirtual #101                // Method scala/reflect/macros/Universe.newTermName:(Ljava/lang/String;)Lscala/reflect/api/Names$TermNameApi;
       121: checkcast     #17                 // class scala/reflect/api/Names$NameApi
       124: invokevirtual #110                // Method scala/reflect/api/Trees$SelectExtractor.apply:(Lscala/reflect/api/Trees$TreeApi;Lscala/reflect/api/Names$NameApi;)Lscala/reflect/api/Trees$SelectApi;
       127: aload_1
       128: invokeinterface #85,  1           // InterfaceMethod scala/reflect/macros/whitebox/Context.universe:()Lscala/reflect/macros/Universe;
       133: ldc           #116                // String requirementsHelper
       135: invokevirtual #101                // Method scala/reflect/macros/Universe.newTermName:(Ljava/lang/String;)Lscala/reflect/api/Names$TermNameApi;
       138: checkcast     #17                 // class scala/reflect/api/Names$NameApi
       141: invokevirtual #110                // Method scala/reflect/api/Trees$SelectExtractor.apply:(Lscala/reflect/api/Trees$TreeApi;Lscala/reflect/api/Names$NameApi;)Lscala/reflect/api/Trees$SelectApi;
       144: aload         4
       146: ldc           #138                // String macroRequireState
       148: aload_1
       149: ldc           #120                // String
       151: invokeinterface #124,  2          // InterfaceMethod scala/reflect/macros/whitebox/Context.literal:(Ljava/lang/String;)Lscala/reflect/api/Exprs$Expr;
       156: aload         5
       158: invokevirtual #128                // Method org/scalactic/BooleanMacro.genMacro:(Lscala/reflect/api/Trees$TreeApi;Lscala/reflect/api/Exprs$Expr;Ljava/lang/String;Lscala/reflect/api/Exprs$Expr;Lscala/reflect/api/Exprs$Expr;)Lscala/reflect/api/Exprs$Expr;
       161: areturn
      LineNumberTable:
        line 288: 0
        line 290: 6
        line 291: 14
        line 292: 23
        line 293: 32
        line 294: 41
        line 295: 50
        line 296: 76
        line 298: 93
        line 300: 110
        line 302: 127
        line 304: 144
        line 305: 146
        line 306: 148
        line 307: 156
      LocalVariableTable:
        Start  Length  Slot  Name   Signature
            0     162     0  this   Lorg/scalactic/RequirementsMacro$;
            0     162     1 context   Lscala/reflect/macros/whitebox/Context;
            0     162     2 condition   Lscala/reflect/api/Exprs$Expr;
            0     162     3 prettifier   Lscala/reflect/api/Exprs$Expr;
    Signature: #71                          // (Lscala/reflect/macros/whitebox/Context;Lscala/reflect/api/Exprs$Expr<Ljava/lang/Object;>;Lscala/reflect/api/Exprs$Expr<Lorg/scalactic/Prettifier;>;)Lscala/reflect/api/Exprs$Expr<Lscala/runtime/BoxedUnit;>;
    MethodParameters:
      Name                           Flags
      context                        final
      condition                      final
      prettifier                     final

  public scala.reflect.api.Exprs$Expr<scala.runtime.BoxedUnit> requireStateWithClue(scala.reflect.macros.whitebox.Context, scala.reflect.api.Exprs$Expr<java.lang.Object>, scala.reflect.api.Exprs$Expr<java.lang.Object>, scala.reflect.api.Exprs$Expr<org.scalactic.Prettifier>);
    descriptor: (Lscala/reflect/macros/whitebox/Context;Lscala/reflect/api/Exprs$Expr;Lscala/reflect/api/Exprs$Expr;Lscala/reflect/api/Exprs$Expr;)Lscala/reflect/api/Exprs$Expr;
    flags: (0x0001) ACC_PUBLIC
    Code:
      stack=8, locals=8, args_size=5
         0: aload_2
         1: astore        5
         3: aload_3
         4: astore        6
         6: aload         4
         8: astore        7
        10: new           #76                 // class org/scalactic/BooleanMacro
        13: dup
        14: aload_1
        15: invokespecial #79                 // Method org/scalactic/BooleanMacro."<init>":(Lscala/reflect/macros/whitebox/Context;)V
        18: aload_1
        19: invokeinterface #85,  1           // InterfaceMethod scala/reflect/macros/whitebox/Context.universe:()Lscala/reflect/macros/Universe;
        24: invokevirtual #91                 // Method scala/reflect/macros/Universe.Select:()Lscala/reflect/api/Trees$SelectExtractor;
        27: aload_1
        28: invokeinterface #85,  1           // InterfaceMethod scala/reflect/macros/whitebox/Context.universe:()Lscala/reflect/macros/Universe;
        33: invokevirtual #91                 // Method scala/reflect/macros/Universe.Select:()Lscala/reflect/api/Trees$SelectExtractor;
        36: aload_1
        37: invokeinterface #85,  1           // InterfaceMethod scala/reflect/macros/whitebox/Context.universe:()Lscala/reflect/macros/Universe;
        42: invokevirtual #91                 // Method scala/reflect/macros/Universe.Select:()Lscala/reflect/api/Trees$SelectExtractor;
        45: aload_1
        46: invokeinterface #85,  1           // InterfaceMethod scala/reflect/macros/whitebox/Context.universe:()Lscala/reflect/macros/Universe;
        51: invokevirtual #91                 // Method scala/reflect/macros/Universe.Select:()Lscala/reflect/api/Trees$SelectExtractor;
        54: aload_1
        55: invokeinterface #85,  1           // InterfaceMethod scala/reflect/macros/whitebox/Context.universe:()Lscala/reflect/macros/Universe;
        60: invokevirtual #95                 // Method scala/reflect/macros/Universe.Ident:()Lscala/reflect/api/Trees$IdentExtractor;
        63: aload_1
        64: invokeinterface #85,  1           // InterfaceMethod scala/reflect/macros/whitebox/Context.universe:()Lscala/reflect/macros/Universe;
        69: ldc           #97                 // String _root_
        71: invokevirtual #101                // Method scala/reflect/macros/Universe.newTermName:(Ljava/lang/String;)Lscala/reflect/api/Names$TermNameApi;
        74: checkcast     #17                 // class scala/reflect/api/Names$NameApi
        77: invokevirtual #105                // Method scala/reflect/api/Trees$IdentExtractor.apply:(Lscala/reflect/api/Names$NameApi;)Lscala/reflect/api/Trees$IdentApi;
        80: aload_1
        81: invokeinterface #85,  1           // InterfaceMethod scala/reflect/macros/whitebox/Context.universe:()Lscala/reflect/macros/Universe;
        86: ldc           #107                // String org
        88: invokevirtual #101                // Method scala/reflect/macros/Universe.newTermName:(Ljava/lang/String;)Lscala/reflect/api/Names$TermNameApi;
        91: checkcast     #17                 // class scala/reflect/api/Names$NameApi
        94: invokevirtual #110                // Method scala/reflect/api/Trees$SelectExtractor.apply:(Lscala/reflect/api/Trees$TreeApi;Lscala/reflect/api/Names$NameApi;)Lscala/reflect/api/Trees$SelectApi;
        97: aload_1
        98: invokeinterface #85,  1           // InterfaceMethod scala/reflect/macros/whitebox/Context.universe:()Lscala/reflect/macros/Universe;
       103: ldc           #112                // String scalactic
       105: invokevirtual #101                // Method scala/reflect/macros/Universe.newTermName:(Ljava/lang/String;)Lscala/reflect/api/Names$TermNameApi;
       108: checkcast     #17                 // class scala/reflect/api/Names$NameApi
       111: invokevirtual #110                // Method scala/reflect/api/Trees$SelectExtractor.apply:(Lscala/reflect/api/Trees$TreeApi;Lscala/reflect/api/Names$NameApi;)Lscala/reflect/api/Trees$SelectApi;
       114: aload_1
       115: invokeinterface #85,  1           // InterfaceMethod scala/reflect/macros/whitebox/Context.universe:()Lscala/reflect/macros/Universe;
       120: ldc           #114                // String Requirements
       122: invokevirtual #101                // Method scala/reflect/macros/Universe.newTermName:(Ljava/lang/String;)Lscala/reflect/api/Names$TermNameApi;
       125: checkcast     #17                 // class scala/reflect/api/Names$NameApi
       128: invokevirtual #110                // Method scala/reflect/api/Trees$SelectExtractor.apply:(Lscala/reflect/api/Trees$TreeApi;Lscala/reflect/api/Names$NameApi;)Lscala/reflect/api/Trees$SelectApi;
       131: aload_1
       132: invokeinterface #85,  1           // InterfaceMethod scala/reflect/macros/whitebox/Context.universe:()Lscala/reflect/macros/Universe;
       137: ldc           #116                // String requirementsHelper
       139: invokevirtual #101                // Method scala/reflect/macros/Universe.newTermName:(Ljava/lang/String;)Lscala/reflect/api/Names$TermNameApi;
       142: checkcast     #17                 // class scala/reflect/api/Names$NameApi
       145: invokevirtual #110                // Method scala/reflect/api/Trees$SelectExtractor.apply:(Lscala/reflect/api/Trees$TreeApi;Lscala/reflect/api/Names$NameApi;)Lscala/reflect/api/Trees$SelectApi;
       148: aload         5
       150: ldc           #138                // String macroRequireState
       152: aload         6
       154: aload         7
       156: invokevirtual #128                // Method org/scalactic/BooleanMacro.genMacro:(Lscala/reflect/api/Trees$TreeApi;Lscala/reflect/api/Exprs$Expr;Ljava/lang/String;Lscala/reflect/api/Exprs$Expr;Lscala/reflect/api/Exprs$Expr;)Lscala/reflect/api/Exprs$Expr;
       159: areturn
      LineNumberTable:
        line 318: 0
        line 320: 10
        line 321: 18
        line 322: 27
        line 323: 36
        line 324: 45
        line 325: 54
        line 326: 80
        line 328: 97
        line 330: 114
        line 332: 131
        line 334: 148
        line 335: 150
        line 336: 152
        line 337: 154
      LocalVariableTable:
        Start  Length  Slot  Name   Signature
            0     160     0  this   Lorg/scalactic/RequirementsMacro$;
            0     160     1 context   Lscala/reflect/macros/whitebox/Context;
            0     160     2 condition   Lscala/reflect/api/Exprs$Expr;
            0     160     3  clue   Lscala/reflect/api/Exprs$Expr;
            0     160     4 prettifier   Lscala/reflect/api/Exprs$Expr;
    Signature: #134                         // (Lscala/reflect/macros/whitebox/Context;Lscala/reflect/api/Exprs$Expr<Ljava/lang/Object;>;Lscala/reflect/api/Exprs$Expr<Ljava/lang/Object;>;Lscala/reflect/api/Exprs$Expr<Lorg/scalactic/Prettifier;>;)Lscala/reflect/api/Exprs$Expr<Lscala/runtime/BoxedUnit;>;
    MethodParameters:
      Name                           Flags
      context                        final
      condition                      final
      clue                           final
      prettifier                     final

  public scala.reflect.api.Exprs$Expr<scala.runtime.BoxedUnit> requireNonNull(scala.reflect.macros.whitebox.Context, scala.collection.immutable.Seq<scala.reflect.api.Exprs$Expr<java.lang.Object>>, scala.reflect.api.Exprs$Expr<?>, scala.reflect.api.Exprs$Expr<?>);
    descriptor: (Lscala/reflect/macros/whitebox/Context;Lscala/collection/immutable/Seq;Lscala/reflect/api/Exprs$Expr;Lscala/reflect/api/Exprs$Expr;)Lscala/reflect/api/Exprs$Expr;
    flags: (0x0001) ACC_PUBLIC
    Code:
      stack=10, locals=10, args_size=5
         0: aload_2
         1: astore        5
         3: aload_3
         4: astore        6
         6: aload         4
         8: astore        7
        10: aload_1
        11: invokeinterface #85,  1           // InterfaceMethod scala/reflect/macros/whitebox/Context.universe:()Lscala/reflect/macros/Universe;
        16: invokevirtual #148                // Method scala/reflect/macros/Universe.Apply:()Lscala/reflect/api/Trees$ApplyExtractor;
        19: aload_1
        20: invokeinterface #85,  1           // InterfaceMethod scala/reflect/macros/whitebox/Context.universe:()Lscala/reflect/macros/Universe;
        25: invokevirtual #91                 // Method scala/reflect/macros/Universe.Select:()Lscala/reflect/api/Trees$SelectExtractor;
        28: aload_1
        29: invokeinterface #85,  1           // InterfaceMethod scala/reflect/macros/whitebox/Context.universe:()Lscala/reflect/macros/Universe;
        34: ldc           #150                // String Array
        36: invokevirtual #153                // Method scala/reflect/macros/Universe.Ident:(Ljava/lang/String;)Lscala/reflect/api/Trees$IdentApi;
        39: aload_1
        40: invokeinterface #85,  1           // InterfaceMethod scala/reflect/macros/whitebox/Context.universe:()Lscala/reflect/macros/Universe;
        45: ldc           #154                // String apply
        47: invokevirtual #101                // Method scala/reflect/macros/Universe.newTermName:(Ljava/lang/String;)Lscala/reflect/api/Names$TermNameApi;
        50: checkcast     #17                 // class scala/reflect/api/Names$NameApi
        53: invokevirtual #110                // Method scala/reflect/api/Trees$SelectExtractor.apply:(Lscala/reflect/api/Trees$TreeApi;Lscala/reflect/api/Names$NameApi;)Lscala/reflect/api/Trees$SelectApi;
        56: getstatic     #159                // Field scala/package$.MODULE$:Lscala/package$;
        59: invokevirtual #163                // Method scala/package$.List:()Lscala/collection/immutable/List$;
        62: aload         5
        64: aload_1
        65: invokedynamic #184,  0            // InvokeDynamic #0:apply:(Lscala/reflect/macros/whitebox/Context;)Lscala/Function1;
        70: invokeinterface #190,  2          // InterfaceMethod scala/collection/immutable/Seq.map:(Lscala/Function1;)Ljava/lang/Object;
        75: checkcast     #186                // class scala/collection/immutable/Seq
        78: invokevirtual #195                // Method scala/collection/immutable/List$.apply:(Lscala/collection/immutable/Seq;)Ljava/lang/Object;
        81: checkcast     #197                // class scala/collection/immutable/List
        84: invokevirtual #200                // Method scala/reflect/api/Trees$ApplyExtractor.apply:(Lscala/reflect/api/Trees$TreeApi;Lscala/collection/immutable/List;)Lscala/reflect/api/Trees$ApplyApi;
        87: astore        8
        89: aload_1
        90: invokeinterface #85,  1           // InterfaceMethod scala/reflect/macros/whitebox/Context.universe:()Lscala/reflect/macros/Universe;
        95: invokevirtual #148                // Method scala/reflect/macros/Universe.Apply:()Lscala/reflect/api/Trees$ApplyExtractor;
        98: aload_1
        99: invokeinterface #85,  1           // InterfaceMethod scala/reflect/macros/whitebox/Context.universe:()Lscala/reflect/macros/Universe;
       104: invokevirtual #91                 // Method scala/reflect/macros/Universe.Select:()Lscala/reflect/api/Trees$SelectExtractor;
       107: aload_1
       108: invokeinterface #85,  1           // InterfaceMethod scala/reflect/macros/whitebox/Context.universe:()Lscala/reflect/macros/Universe;
       113: ldc           #150                // String Array
       115: invokevirtual #153                // Method scala/reflect/macros/Universe.Ident:(Ljava/lang/String;)Lscala/reflect/api/Trees$IdentApi;
       118: aload_1
       119: invokeinterface #85,  1           // InterfaceMethod scala/reflect/macros/whitebox/Context.universe:()Lscala/reflect/macros/Universe;
       124: ldc           #154                // String apply
       126: invokevirtual #101                // Method scala/reflect/macros/Universe.newTermName:(Ljava/lang/String;)Lscala/reflect/api/Names$TermNameApi;
       129: checkcast     #17                 // class scala/reflect/api/Names$NameApi
       132: invokevirtual #110                // Method scala/reflect/api/Trees$SelectExtractor.apply:(Lscala/reflect/api/Trees$TreeApi;Lscala/reflect/api/Names$NameApi;)Lscala/reflect/api/Trees$SelectApi;
       135: getstatic     #159                // Field scala/package$.MODULE$:Lscala/package$;
       138: invokevirtual #163                // Method scala/package$.List:()Lscala/collection/immutable/List$;
       141: aload         5
       143: invokedynamic #207,  0            // InvokeDynamic #1:apply:()Lscala/Function1;
       148: invokeinterface #190,  2          // InterfaceMethod scala/collection/immutable/Seq.map:(Lscala/Function1;)Ljava/lang/Object;
       153: checkcast     #186                // class scala/collection/immutable/Seq
       156: invokevirtual #195                // Method scala/collection/immutable/List$.apply:(Lscala/collection/immutable/Seq;)Ljava/lang/Object;
       159: checkcast     #197                // class scala/collection/immutable/List
       162: invokevirtual #200                // Method scala/reflect/api/Trees$ApplyExtractor.apply:(Lscala/reflect/api/Trees$TreeApi;Lscala/collection/immutable/List;)Lscala/reflect/api/Trees$ApplyApi;
       165: astore        9
       167: aload_1
       168: aload_1
       169: invokeinterface #85,  1           // InterfaceMethod scala/reflect/macros/whitebox/Context.universe:()Lscala/reflect/macros/Universe;
       174: invokevirtual #148                // Method scala/reflect/macros/Universe.Apply:()Lscala/reflect/api/Trees$ApplyExtractor;
       177: aload_1
       178: invokeinterface #85,  1           // InterfaceMethod scala/reflect/macros/whitebox/Context.universe:()Lscala/reflect/macros/Universe;
       183: invokevirtual #91                 // Method scala/reflect/macros/Universe.Select:()Lscala/reflect/api/Trees$SelectExtractor;
       186: aload_1
       187: invokeinterface #85,  1           // InterfaceMethod scala/reflect/macros/whitebox/Context.universe:()Lscala/reflect/macros/Universe;
       192: invokevirtual #91                 // Method scala/reflect/macros/Universe.Select:()Lscala/reflect/api/Trees$SelectExtractor;
       195: aload_1
       196: invokeinterface #85,  1           // InterfaceMethod scala/reflect/macros/whitebox/Context.universe:()Lscala/reflect/macros/Universe;
       201: invokevirtual #91                 // Method scala/reflect/macros/Universe.Select:()Lscala/reflect/api/Trees$SelectExtractor;
       204: aload_1
       205: invokeinterface #85,  1           // InterfaceMethod scala/reflect/macros/whitebox/Context.universe:()Lscala/reflect/macros/Universe;
       210: invokevirtual #91                 // Method scala/reflect/macros/Universe.Select:()Lscala/reflect/api/Trees$SelectExtractor;
       213: aload_1
       214: invokeinterface #85,  1           // InterfaceMethod scala/reflect/macros/whitebox/Context.universe:()Lscala/reflect/macros/Universe;
       219: invokevirtual #91                 // Method scala/reflect/macros/Universe.Select:()Lscala/reflect/api/Trees$SelectExtractor;
       222: aload_1
       223: invokeinterface #85,  1           // InterfaceMethod scala/reflect/macros/whitebox/Context.universe:()Lscala/reflect/macros/Universe;
       228: invokevirtual #95                 // Method scala/reflect/macros/Universe.Ident:()Lscala/reflect/api/Trees$IdentExtractor;
       231: aload_1
       232: invokeinterface #85,  1           // InterfaceMethod scala/reflect/macros/whitebox/Context.universe:()Lscala/reflect/macros/Universe;
       237: ldc           #97                 // String _root_
       239: invokevirtual #101                // Method scala/reflect/macros/Universe.newTermName:(Ljava/lang/String;)Lscala/reflect/api/Names$TermNameApi;
       242: checkcast     #17                 // class scala/reflect/api/Names$NameApi
       245: invokevirtual #105                // Method scala/reflect/api/Trees$IdentExtractor.apply:(Lscala/reflect/api/Names$NameApi;)Lscala/reflect/api/Trees$IdentApi;
       248: aload_1
       249: invokeinterface #85,  1           // InterfaceMethod scala/reflect/macros/whitebox/Context.universe:()Lscala/reflect/macros/Universe;
       254: ldc           #107                // String org
       256: invokevirtual #101                // Method scala/reflect/macros/Universe.newTermName:(Ljava/lang/String;)Lscala/reflect/api/Names$TermNameApi;
       259: checkcast     #17                 // class scala/reflect/api/Names$NameApi
       262: invokevirtual #110                // Method scala/reflect/api/Trees$SelectExtractor.apply:(Lscala/reflect/api/Trees$TreeApi;Lscala/reflect/api/Names$NameApi;)Lscala/reflect/api/Trees$SelectApi;
       265: aload_1
       266: invokeinterface #85,  1           // InterfaceMethod scala/reflect/macros/whitebox/Context.universe:()Lscala/reflect/macros/Universe;
       271: ldc           #112                // String scalactic
       273: invokevirtual #101                // Method scala/reflect/macros/Universe.newTermName:(Ljava/lang/String;)Lscala/reflect/api/Names$TermNameApi;
       276: checkcast     #17                 // class scala/reflect/api/Names$NameApi
       279: invokevirtual #110                // Method scala/reflect/api/Trees$SelectExtractor.apply:(Lscala/reflect/api/Trees$TreeApi;Lscala/reflect/api/Names$NameApi;)Lscala/reflect/api/Trees$SelectApi;
       282: aload_1
       283: invokeinterface #85,  1           // InterfaceMethod scala/reflect/macros/whitebox/Context.universe:()Lscala/reflect/macros/Universe;
       288: ldc           #114                // String Requirements
       290: invokevirtual #101                // Method scala/reflect/macros/Universe.newTermName:(Ljava/lang/String;)Lscala/reflect/api/Names$TermNameApi;
       293: checkcast     #17                 // class scala/reflect/api/Names$NameApi
       296: invokevirtual #110                // Method scala/reflect/api/Trees$SelectExtractor.apply:(Lscala/reflect/api/Trees$TreeApi;Lscala/reflect/api/Names$NameApi;)Lscala/reflect/api/Trees$SelectApi;
       299: aload_1
       300: invokeinterface #85,  1           // InterfaceMethod scala/reflect/macros/whitebox/Context.universe:()Lscala/reflect/macros/Universe;
       305: ldc           #116                // String requirementsHelper
       307: invokevirtual #101                // Method scala/reflect/macros/Universe.newTermName:(Ljava/lang/String;)Lscala/reflect/api/Names$TermNameApi;
       310: checkcast     #17                 // class scala/reflect/api/Names$NameApi
       313: invokevirtual #110                // Method scala/reflect/api/Trees$SelectExtractor.apply:(Lscala/reflect/api/Trees$TreeApi;Lscala/reflect/api/Names$NameApi;)Lscala/reflect/api/Trees$SelectApi;
       316: aload_1
       317: invokeinterface #85,  1           // InterfaceMethod scala/reflect/macros/whitebox/Context.universe:()Lscala/reflect/macros/Universe;
       322: ldc           #209                // String macroRequireNonNull
       324: invokevirtual #101                // Method scala/reflect/macros/Universe.newTermName:(Ljava/lang/String;)Lscala/reflect/api/Names$TermNameApi;
       327: checkcast     #17                 // class scala/reflect/api/Names$NameApi
       330: invokevirtual #110                // Method scala/reflect/api/Trees$SelectExtractor.apply:(Lscala/reflect/api/Trees$TreeApi;Lscala/reflect/api/Names$NameApi;)Lscala/reflect/api/Trees$SelectApi;
       333: getstatic     #159                // Field scala/package$.MODULE$:Lscala/package$;
       336: invokevirtual #163                // Method scala/package$.List:()Lscala/collection/immutable/List$;
       339: getstatic     #214                // Field scala/runtime/ScalaRunTime$.MODULE$:Lscala/runtime/ScalaRunTime$;
       342: iconst_4
       343: anewarray     #50                 // class scala/reflect/api/Trees$TreeApi
       346: dup
       347: iconst_0
       348: aload         8
       350: aastore
       351: dup
       352: iconst_1
       353: aload         9
       355: aastore
       356: dup
       357: iconst_2
       358: aload         6
       360: invokeinterface #218,  1          // InterfaceMethod scala/reflect/api/Exprs$Expr.tree:()Lscala/reflect/api/Trees$TreeApi;
       365: aastore
       366: dup
       367: iconst_3
       368: aload         7
       370: invokeinterface #218,  1          // InterfaceMethod scala/reflect/api/Exprs$Expr.tree:()Lscala/reflect/api/Trees$TreeApi;
       375: aastore
       376: checkcast     #220                // class "[Ljava/lang/Object;"
       379: invokevirtual #224                // Method scala/runtime/ScalaRunTime$.wrapRefArray:([Ljava/lang/Object;)Lscala/collection/immutable/ArraySeq;
       382: invokevirtual #195                // Method scala/collection/immutable/List$.apply:(Lscala/collection/immutable/Seq;)Ljava/lang/Object;
       385: checkcast     #197                // class scala/collection/immutable/List
       388: invokevirtual #200                // Method scala/reflect/api/Trees$ApplyExtractor.apply:(Lscala/reflect/api/Trees$TreeApi;Lscala/collection/immutable/List;)Lscala/reflect/api/Trees$ApplyApi;
       391: aload_1
       392: invokeinterface #85,  1           // InterfaceMethod scala/reflect/macros/whitebox/Context.universe:()Lscala/reflect/macros/Universe;
       397: invokevirtual #227                // Method scala/reflect/macros/Universe.WeakTypeTag:()Lscala/reflect/api/TypeTags$WeakTypeTag$;
       400: invokevirtual #231                // Method scala/reflect/api/TypeTags$WeakTypeTag$.Nothing:()Lscala/reflect/api/TypeTags$WeakTypeTag;
       403: invokeinterface #234,  3          // InterfaceMethod scala/reflect/macros/whitebox/Context.Expr:(Lscala/reflect/api/Trees$TreeApi;Lscala/reflect/api/TypeTags$WeakTypeTag;)Lscala/reflect/api/Exprs$Expr;
       408: areturn
      LineNumberTable:
        line 348: 0
        line 361: 10
        line 362: 19
        line 363: 28
        line 364: 39
        line 366: 56
        line 379: 89
        line 380: 98
        line 381: 107
        line 382: 118
        line 384: 135
        line 390: 167
        line 391: 168
        line 392: 177
        line 393: 186
        line 394: 195
        line 395: 204
        line 396: 213
        line 397: 222
        line 398: 248
        line 400: 265
        line 402: 282
        line 404: 299
        line 406: 316
        line 408: 333
        line 390: 391
      LocalVariableTable:
        Start  Length  Slot  Name   Signature
           89     319     8 variablesNamesArray   Lscala/reflect/api/Trees$ApplyApi;
          167     241     9 argumentsArray   Lscala/reflect/api/Trees$ApplyApi;
            0     409     0  this   Lorg/scalactic/RequirementsMacro$;
            0     409     1 context   Lscala/reflect/macros/whitebox/Context;
            0     409     2 arguments   Lscala/collection/immutable/Seq;
            0     409     3 prettifier   Lscala/reflect/api/Exprs$Expr;
            0     409     4   pos   Lscala/reflect/api/Exprs$Expr;
    Signature: #142                         // (Lscala/reflect/macros/whitebox/Context;Lscala/collection/immutable/Seq<Lscala/reflect/api/Exprs$Expr<Ljava/lang/Object;>;>;Lscala/reflect/api/Exprs$Expr<*>;Lscala/reflect/api/Exprs$Expr<*>;)Lscala/reflect/api/Exprs$Expr<Lscala/runtime/BoxedUnit;>;
    MethodParameters:
      Name                           Flags
      context                        final
      arguments                      final
      prettifier                     final
      pos                            final

  public static final scala.reflect.api.Trees$TreeApi $anonfun$requireNonNull$1(scala.reflect.macros.whitebox.Context, scala.reflect.api.Exprs$Expr);
    descriptor: (Lscala/reflect/macros/whitebox/Context;Lscala/reflect/api/Exprs$Expr;)Lscala/reflect/api/Trees$TreeApi;
    flags: (0x1019) ACC_PUBLIC, ACC_STATIC, ACC_FINAL, ACC_SYNTHETIC
    Code:
      stack=9, locals=2, args_size=2
         0: aload_0
         1: aload_0
         2: invokeinterface #85,  1           // InterfaceMethod scala/reflect/macros/whitebox/Context.universe:()Lscala/reflect/macros/Universe;
         7: aload_1
         8: invokeinterface #218,  1          // InterfaceMethod scala/reflect/api/Exprs$Expr.tree:()Lscala/reflect/api/Trees$TreeApi;
        13: aload_0
        14: invokeinterface #85,  1           // InterfaceMethod scala/reflect/macros/whitebox/Context.universe:()Lscala/reflect/macros/Universe;
        19: invokevirtual #244                // Method scala/reflect/macros/Universe.show$default$2:()Lscala/reflect/api/Printers$BooleanFlag;
        22: aload_0
        23: invokeinterface #85,  1           // InterfaceMethod scala/reflect/macros/whitebox/Context.universe:()Lscala/reflect/macros/Universe;
        28: invokevirtual #247                // Method scala/reflect/macros/Universe.show$default$3:()Lscala/reflect/api/Printers$BooleanFlag;
        31: aload_0
        32: invokeinterface #85,  1           // InterfaceMethod scala/reflect/macros/whitebox/Context.universe:()Lscala/reflect/macros/Universe;
        37: invokevirtual #250                // Method scala/reflect/macros/Universe.show$default$4:()Lscala/reflect/api/Printers$BooleanFlag;
        40: aload_0
        41: invokeinterface #85,  1           // InterfaceMethod scala/reflect/macros/whitebox/Context.universe:()Lscala/reflect/macros/Universe;
        46: invokevirtual #253                // Method scala/reflect/macros/Universe.show$default$5:()Lscala/reflect/api/Printers$BooleanFlag;
        49: aload_0
        50: invokeinterface #85,  1           // InterfaceMethod scala/reflect/macros/whitebox/Context.universe:()Lscala/reflect/macros/Universe;
        55: invokevirtual #256                // Method scala/reflect/macros/Universe.show$default$6:()Lscala/reflect/api/Printers$BooleanFlag;
        58: aload_0
        59: invokeinterface #85,  1           // InterfaceMethod scala/reflect/macros/whitebox/Context.universe:()Lscala/reflect/macros/Universe;
        64: invokevirtual #259                // Method scala/reflect/macros/Universe.show$default$7:()Lscala/reflect/api/Printers$BooleanFlag;
        67: invokevirtual #263                // Method scala/reflect/macros/Universe.show:(Ljava/lang/Object;Lscala/reflect/api/Printers$BooleanFlag;Lscala/reflect/api/Printers$BooleanFlag;Lscala/reflect/api/Printers$BooleanFlag;Lscala/reflect/api/Printers$BooleanFlag;Lscala/reflect/api/Printers$BooleanFlag;Lscala/reflect/api/Printers$BooleanFlag;)Ljava/lang/String;
        70: invokeinterface #124,  2          // InterfaceMethod scala/reflect/macros/whitebox/Context.literal:(Ljava/lang/String;)Lscala/reflect/api/Exprs$Expr;
        75: invokeinterface #218,  1          // InterfaceMethod scala/reflect/api/Exprs$Expr.tree:()Lscala/reflect/api/Trees$TreeApi;
        80: areturn
      LineNumberTable:
        line 366: 0
      LocalVariableTable:
        Start  Length  Slot  Name   Signature
            0      81     0 context$1   Lscala/reflect/macros/whitebox/Context;
            0      81     1     e   Lscala/reflect/api/Exprs$Expr;
    MethodParameters:
      Name                           Flags
      context$1                      final
      e                              final

  public static final scala.reflect.api.Trees$TreeApi $anonfun$requireNonNull$2(scala.reflect.api.Exprs$Expr);
    descriptor: (Lscala/reflect/api/Exprs$Expr;)Lscala/reflect/api/Trees$TreeApi;
    flags: (0x1019) ACC_PUBLIC, ACC_STATIC, ACC_FINAL, ACC_SYNTHETIC
    Code:
      stack=1, locals=1, args_size=1
         0: aload_0
         1: invokeinterface #218,  1          // InterfaceMethod scala/reflect/api/Exprs$Expr.tree:()Lscala/reflect/api/Trees$TreeApi;
         6: areturn
      LineNumberTable:
        line 384: 0
      LocalVariableTable:
        Start  Length  Slot  Name   Signature
            0       7     0     e   Lscala/reflect/api/Exprs$Expr;
    MethodParameters:
      Name                           Flags
      e                              final

  private org.scalactic.RequirementsMacro$();
    descriptor: ()V
    flags: (0x0002) ACC_PRIVATE
    Code:
      stack=1, locals=1, args_size=1
         0: aload_0
         1: invokespecial #264                // Method java/lang/Object."<init>":()V
         4: return
      LineNumberTable:
        line 441: 0
        line 220: 4
      LocalVariableTable:
        Start  Length  Slot  Name   Signature
            0       5     0  this   Lorg/scalactic/RequirementsMacro$;

  private static java.lang.Object $deserializeLambda$(java.lang.invoke.SerializedLambda);
    descriptor: (Ljava/lang/invoke/SerializedLambda;)Ljava/lang/Object;
    flags: (0x100a) ACC_PRIVATE, ACC_STATIC, ACC_SYNTHETIC
    Code:
      stack=1, locals=1, args_size=1
         0: aload_0
         1: invokedynamic #276,  0            // InvokeDynamic #2:lambdaDeserialize:(Ljava/lang/invoke/SerializedLambda;)Ljava/lang/Object;
         6: areturn
}
InnerClasses:
  public static final #10= #7 of #9;      // Lookup=class java/lang/invoke/MethodHandles$Lookup of class java/lang/invoke/MethodHandles
  public #15= #12 of #14;                 // Expr=class scala/reflect/api/Exprs$Expr of class scala/reflect/api/Exprs
  public abstract #20= #17 of #19;        // NameApi=class scala/reflect/api/Names$NameApi of class scala/reflect/api/Names
  public #23= #22 of #19;                 // TermNameApi=class scala/reflect/api/Names$TermNameApi of class scala/reflect/api/Names
  public #28= #25 of #27;                 // BooleanFlag=class scala/reflect/api/Printers$BooleanFlag of class scala/reflect/api/Printers
  public #33= #30 of #32;                 // ApplyApi=class scala/reflect/api/Trees$ApplyApi of class scala/reflect/api/Trees
  public abstract #36= #35 of #32;        // ApplyExtractor=class scala/reflect/api/Trees$ApplyExtractor of class scala/reflect/api/Trees
  public #39= #38 of #32;                 // IdentApi=class scala/reflect/api/Trees$IdentApi of class scala/reflect/api/Trees
  public abstract #42= #41 of #32;        // IdentExtractor=class scala/reflect/api/Trees$IdentExtractor of class scala/reflect/api/Trees
  public #45= #44 of #32;                 // SelectApi=class scala/reflect/api/Trees$SelectApi of class scala/reflect/api/Trees
  public abstract #48= #47 of #32;        // SelectExtractor=class scala/reflect/api/Trees$SelectExtractor of class scala/reflect/api/Trees
  public #51= #50 of #32;                 // TreeApi=class scala/reflect/api/Trees$TreeApi of class scala/reflect/api/Trees
  public #56= #53 of #55;                 // WeakTypeTag=class scala/reflect/api/TypeTags$WeakTypeTag of class scala/reflect/api/TypeTags
  public #59= #58 of #55;                 // WeakTypeTag$=class scala/reflect/api/TypeTags$WeakTypeTag$ of class scala/reflect/api/TypeTags
SourceFile: "Requirements.scala"
BootstrapMethods:
  0: #181 REF_invokeStatic java/lang/invoke/LambdaMetafactory.altMetafactory:(Ljava/lang/invoke/MethodHandles$Lookup;Ljava/lang/String;Ljava/lang/invoke/MethodType;[Ljava/lang/Object;)Ljava/lang/invoke/CallSite;
    Method arguments:
      #165 (Ljava/lang/Object;)Ljava/lang/Object;
      #170 REF_invokeStatic org/scalactic/RequirementsMacro$.$anonfun$requireNonNull$1:(Lscala/reflect/macros/whitebox/Context;Lscala/reflect/api/Exprs$Expr;)Lscala/reflect/api/Trees$TreeApi;
      #172 (Lscala/reflect/api/Exprs$Expr;)Lscala/reflect/api/Trees$TreeApi;
      #173 5
      #174 1
      #172 (Lscala/reflect/api/Exprs$Expr;)Lscala/reflect/api/Trees$TreeApi;
  1: #181 REF_invokeStatic java/lang/invoke/LambdaMetafactory.altMetafactory:(Ljava/lang/invoke/MethodHandles$Lookup;Ljava/lang/String;Ljava/lang/invoke/MethodType;[Ljava/lang/Object;)Ljava/lang/invoke/CallSite;
    Method arguments:
      #165 (Ljava/lang/Object;)Ljava/lang/Object;
      #204 REF_invokeStatic org/scalactic/RequirementsMacro$.$anonfun$requireNonNull$2:(Lscala/reflect/api/Exprs$Expr;)Lscala/reflect/api/Trees$TreeApi;
      #172 (Lscala/reflect/api/Exprs$Expr;)Lscala/reflect/api/Trees$TreeApi;
      #173 5
      #174 1
      #172 (Lscala/reflect/api/Exprs$Expr;)Lscala/reflect/api/Trees$TreeApi;
  2: #273 REF_invokeStatic scala/runtime/LambdaDeserialize.bootstrap:(Ljava/lang/invoke/MethodHandles$Lookup;Ljava/lang/String;Ljava/lang/invoke/MethodType;[Ljava/lang/invoke/MethodHandle;)Ljava/lang/invoke/CallSite;
    Method arguments:
      #170 REF_invokeStatic org/scalactic/RequirementsMacro$.$anonfun$requireNonNull$1:(Lscala/reflect/macros/whitebox/Context;Lscala/reflect/api/Exprs$Expr;)Lscala/reflect/api/Trees$TreeApi;
      #204 REF_invokeStatic org/scalactic/RequirementsMacro$.$anonfun$requireNonNull$2:(Lscala/reflect/api/Exprs$Expr;)Lscala/reflect/api/Trees$TreeApi;
  ScalaInlineInfo: length = 0x2C (unknown attribute)
   01 01 00 08 00 A6 00 A7 01 00 C9 00 AB 01 00 40
   00 3F 01 00 45 00 46 01 00 8C 00 8D 01 00 88 00
   46 01 00 8B 00 85 01 00 84 00 85 01
  Scala: length = 0x0 (unknown attribute)

