Classfile /Users/mw/Projects/slang-braindump/.jar/jar11/assemble/slang-braindump/assemble/content/org/scalactic/Resources.class
  Last modified May 29, 2022; size 26555 bytes
  SHA-256 checksum 9c1734f3822255767e84bfe6c104c6911be89e47c0aeb077a7fe03e468299635
  Compiled from "Resources.scala"
public final class org.scalactic.Resources
  minor version: 0
  major version: 52
  flags: (0x0031) ACC_PUBLIC, ACC_FINAL, ACC_SUPER
  this_class: #2                          // org/scalactic/Resources
  super_class: #4                         // java/lang/Object
  interfaces: 0, fields: 0, methods: 224, attributes: 3
Constant pool:
    #1 = Utf8               org/scalactic/Resources
    #2 = Class              #1            // org/scalactic/Resources
    #3 = Utf8               java/lang/Object
    #4 = Class              #3            // java/lang/Object
    #5 = Utf8               Resources.scala
    #6 = Utf8               Lscala/reflect/ScalaSignature;
    #7 = Utf8               bytes
    #8 = Utf8               \u0006\u0005\u0011\u0015xACAe\u0003\u0017D\t!a3\u0002T\u001aQ\u0011q[Af\u0011\u0003\tY-!7\t\u000f\u0005\u001d\u0018\u0001\"\u0001\u0002l\"Q\u0011Q^\u0001\t\u0006\u0004%\t!a<\t\u000f\t\u0005\u0011\u0001\"\u0003\u0003\u0004!9!qF\u0001\u0005\u0002\tE\u0002b\u0002B\u001d\u0003\u0011\u0005!1\b\u0005\b\u0005{\tA\u0011\u0001B\u001e\u0011\u001d\u0011y$\u0001C\u0001\u0005\u0003BqAa\u0012\u0002\t\u0003\u0011Y\u0004C\u0004\u0003J\u0005!\tAa\u0013\t\u000f\tM\u0013\u0001\"\u0001\u0003<!9!QK\u0001\u0005\u0002\t]\u0003b\u0002B/\u0003\u0011\u0005!1\b\u0005\b\u0005?\nA\u0011\u0001B1\u0011\u001d\u0011Y\'\u0001C\u0001\u0005wAqA!\u001c\u0002\t\u0003\u0011y\u0007C\u0004\u0003x\u0005!\tAa\u000f\t\u000f\te\u0014\u0001\"\u0001\u0003<!9!1P\u0001\u0005\u0002\tm\u0002b\u0002B?\u0003\u0011\u0005!1\b\u0005\b\u0005\u007f\nA\u0011\u0001B\u001e\u0011\u001d\u0011\t)\u0001C\u0001\u0005\u0007CqAa\"\u0002\t\u0003\u0011Y\u0004C\u0004\u0003\n\u0006!\tAa#\t\u000f\t=\u0015\u0001\"\u0001\u0003<!9!\u0011S\u0001\u0005\u0002\tm\u0002b\u0002BJ\u0003\u0011\u0005!1\b\u0005\b\u0005+\u000bA\u0011\u0001BL\u0011\u001d\u0011i*\u0001C\u0001\u0005wAqAa(\u0002\t\u0003\u0011\t\u000bC\u0004\u0003&\u0006!\tAa\u000f\t\u000f\t\u001d\u0016\u0001\"\u0001\u0003*\"9!QV\u0001\u0005\u0002\tm\u0002b\u0002BX\u0003\u0011\u0005!\u0011\u0017\u0005\b\u0005o\u000bA\u0011\u0001B\u001e\u0011\u001d\u0011I,\u0001C\u0001\u0005wCqA!1\u0002\t\u0003\u0011Y\u0004C\u0004\u0003D\u0006!\tA!2\t\u000f\t-\u0017\u0001\"\u0001\u0003<!9!QZ\u0001\u0005\u0002\t=\u0007b\u0002Bk\u0003\u0011\u0005!1\b\u0005\b\u0005/\fA\u0011\u0001Bm\u0011\u001d\u0011y.\u0001C\u0001\u0005wAqA!9\u0002\t\u0003\u0011\u0019\u000fC\u0004\u0003j\u0006!\tAa\u000f\t\u000f\t-\u0018\u0001\"\u0001\u0003n\"9!1_\u0001\u0005\u0002\tm\u0002b\u0002B{\u0003\u0011\u0005!q\u001f\u0005\b\u0005{\fA\u0011\u0001B\u001e\u0011\u001d\u0011y0\u0001C\u0001\u0007\u0003Aqaa\u0002\u0002\t\u0003\u0011Y\u0004C\u0004\u0004\n\u0005!\taa\u0003\t\u000f\rE\u0011\u0001\"\u0001\u0003<!911C\u0001\u0005\u0002\rU\u0001bBB\u000e\u0003\u0011\u0005!1\b\u0005\b\u0007;\tA\u0011AB\u0010\u0011\u001d\u0019)#\u0001C\u0001\u0005wAqaa\n\u0002\t\u0003\u0019I\u0003C\u0004\u00040\u0005!\tAa\u000f\t\u000f\rE\u0012\u0001\"\u0001\u00044!91\u0011H\u0001\u0005\u0002\tm\u0002bBB\u001e\u0003\u0011\u00051Q\b\u0005\b\u0007\u0007\nA\u0011\u0001B\u001e\u0011\u001d\u0019)%\u0001C\u0001\u0007\u000fBqa!\u0014\u0002\t\u0003\u0011Y\u0004C\u0004\u0004P\u0005!\ta!\u0015\t\u000f\r]\u0013\u0001\"\u0001\u0003<!91\u0011L\u0001\u0005\u0002\rm\u0003bBB1\u0003\u0011\u0005!1\b\u0005\b\u0007G\nA\u0011AB3\u0011\u001d\u0019I\'\u0001C\u0001\u0005wAqaa\u001b\u0002\t\u0003\u0019i\u0007C\u0004\u0004r\u0005!\tAa\u000f\t\u000f\rM\u0014\u0001\"\u0001\u0004v!911P\u0001\u0005\u0002\tm\u0002bBB?\u0003\u0011\u00051q\u0010\u0005\b\u0007\u000b\u000bA\u0011\u0001B\u001e\u0011\u001d\u00199)\u0001C\u0001\u0007\u0013Cqa!%\u0002\t\u0003\u0011Y\u0004C\u0004\u0004\u0014\u0006!\ta!&\t\u000f\rm\u0015\u0001\"\u0001\u0003<!91QT\u0001\u0005\u0002\r}\u0005bBBT\u0003\u0011\u0005!1\b\u0005\b\u0007S\u000bA\u0011ABV\u0011\u001d\u0019\t,\u0001C\u0001\u0005wAqaa-\u0002\t\u0003\u0019)\fC\u0004\u0004<\u0006!\tAa\u000f\t\u000f\ru\u0016\u0001\"\u0001\u0004@\"91QY\u0001\u0005\u0002\tm\u0002bBBd\u0003\u0011\u00051\u0011\u001a\u0005\b\u0007\u001f\fA\u0011\u0001B\u001e\u0011\u001d\u0019\t.\u0001C\u0001\u0005wAqaa5\u0002\t\u0003\u0011Y\u0004C\u0004\u0004V\u0006!\tAa\u000f\t\u000f\r]\u0017\u0001\"\u0001\u0003<!91\u0011\\\u0001\u0005\u0002\tm\u0002bBBn\u0003\u0011\u0005!1\b\u0005\b\u0007;\fA\u0011\u0001B\u001e\u0011\u001d\u0019y.\u0001C\u0001\u0005wAqa!9\u0002\t\u0003\u0011Y\u0004C\u0004\u0004d\u0006!\tAa\u000f\t\u000f\r\u0015\u0018\u0001\"\u0001\u0003<!91q]\u0001\u0005\u0002\tm\u0002bBBu\u0003\u0011\u0005!1\b\u0005\b\u0007W\fA\u0011\u0001B\u001e\u0011\u001d\u0019i/\u0001C\u0001\u0005wAqaa<\u0002\t\u0003\u0011Y\u0004C\u0004\u0004r\u0006!\tAa\u000f\t\u000f\rM\u0018\u0001\"\u0001\u0003<!91Q_\u0001\u0005\u0002\tm\u0002bBB|\u0003\u0011\u0005!1\b\u0005\b\u0007s\fA\u0011\u0001B\u001e\u0011\u001d\u0019Y0\u0001C\u0001\u0005wAqa!@\u0002\t\u0003\u0011Y\u0004C\u0004\u0004\u0000\u0006!\tAa\u000f\t\u000f\u0011\u0005\u0011\u0001\"\u0001\u0003<!9A1A\u0001\u0005\u0002\tm\u0002b\u0002C\u0003\u0003\u0011\u0005!1\b\u0005\b\t\u000f\tA\u0011\u0001B\u001e\u0011\u001d!I!\u0001C\u0001\u0005wAq\u0001b\u0003\u0002\t\u0003\u0011Y\u0004C\u0004\u0005\u000e\u0005!\tAa\u000f\t\u000f\u0011=\u0011\u0001\"\u0001\u0003<!9A\u0011C\u0001\u0005\u0002\tm\u0002b\u0002C\n\u0003\u0011\u0005!1\b\u0005\b\t+\tA\u0011\u0001B\u001e\u0011\u001d!9\"\u0001C\u0001\u0005wAq\u0001\"\u0007\u0002\t\u0003\u0011Y\u0004C\u0004\u0005\u001c\u0005!\tAa\u000f\t\u000f\u0011u\u0011\u0001\"\u0001\u0003<!9AqD\u0001\u0005\u0002\tm\u0002b\u0002C\u0011\u0003\u0011\u0005!1\b\u0005\b\tG\tA\u0011\u0001B\u001e\u0011\u001d!)#\u0001C\u0001\u0005wAq\u0001b\n\u0002\t\u0003\u0011Y\u0004C\u0004\u0005*\u0005!\tAa\u000f\t\u000f\u0011-\u0012\u0001\"\u0001\u0003<!9AQF\u0001\u0005\u0002\tm\u0002b\u0002C\u0018\u0003\u0011\u0005!1\b\u0005\b\tc\tA\u0011\u0001B\u001e\u0011\u001d!\u0019$\u0001C\u0001\u0005wAq\u0001\"\u000e\u0002\t\u0003\u0011Y\u0004C\u0004\u00058\u0005!\tAa\u000f\t\u000f\u0011e\u0012\u0001\"\u0001\u0003<!9A1H\u0001\u0005\u0002\tm\u0002b\u0002C\u001f\u0003\u0011\u0005!1\b\u0005\b\t\u007f\tA\u0011\u0001B\u001e\u0011\u001d!\t%\u0001C\u0001\u0005wAq\u0001b\u0011\u0002\t\u0003\u0011Y\u0004C\u0004\u0005F\u0005!\tAa\u000f\t\u000f\u0011\u001d\u0013\u0001\"\u0001\u0003<!9A\u0011J\u0001\u0005\u0002\tm\u0002b\u0002C&\u0003\u0011\u0005!1\b\u0005\b\t\u001b\nA\u0011\u0001B\u001e\u0011\u001d!y%\u0001C\u0001\u0005wAq\u0001\"\u0015\u0002\t\u0003\u0011Y\u0004C\u0004\u0005T\u0005!\tAa\u000f\t\u000f\u0011U\u0013\u0001\"\u0001\u0003<!9AqK\u0001\u0005\u0002\tm\u0002b\u0002C-\u0003\u0011\u0005!1\b\u0005\b\t7\nA\u0011\u0001B\u001e\u0011\u001d!i&\u0001C\u0001\u0005wAq\u0001b\u0018\u0002\t\u0003\u0011Y\u0004C\u0004\u0005b\u0005!\tAa\u000f\t\u000f\u0011\r\u0014\u0001\"\u0001\u0003<!9AQM\u0001\u0005\u0002\tm\u0002b\u0002C4\u0003\u0011\u0005!1\b\u0005\b\tS\nA\u0011\u0001B\u001e\u0011\u001d!Y\'\u0001C\u0001\u0005wAq\u0001\"\u001c\u0002\t\u0003\u0011Y\u0004C\u0004\u0005p\u0005!\tAa\u000f\t\u000f\u0011E\u0014\u0001\"\u0001\u0003<!9A1O\u0001\u0005\u0002\tm\u0002b\u0002C;\u0003\u0011\u0005!1\b\u0005\b\to\nA\u0011\u0001B\u001e\u0011\u001d!I(\u0001C\u0001\u0005wAq\u0001b\u001f\u0002\t\u0003\u0011Y\u0004C\u0004\u0005~\u0005!\tAa\u000f\t\u000f\u0011}\u0014\u0001\"\u0001\u0003<!9A\u0011Q\u0001\u0005\u0002\tm\u0002b\u0002CB\u0003\u0011\u0005!1\b\u0005\b\t\u000b\u000bA\u0011\u0001B\u001e\u0011\u001d!9)\u0001C\u0001\u0005wAq\u0001\"#\u0002\t\u0003\u0011Y\u0004C\u0004\u0005\f\u0006!\tAa\u000f\t\u000f\u00115\u0015\u0001\"\u0001\u0003<!9AqR\u0001\u0005\u0002\tm\u0002b\u0002CI\u0003\u0011\u0005!1\b\u0005\b\t\'\u000bA\u0011\u0001B\u001e\u0011\u001d!)*\u0001C\u0001\u0005wAq\u0001b&\u0002\t\u0003\u0011Y\u0004C\u0004\u0005\u001a\u0006!\tAa\u000f\t\u000f\u0011m\u0015\u0001\"\u0001\u0003<!9AQT\u0001\u0005\u0002\tm\u0002b\u0002CP\u0003\u0011\u0005!1\b\u0005\b\tC\u000bA\u0011\u0001B\u001e\u0011\u001d!\u0019+\u0001C\u0001\u0005wAq\u0001\"*\u0002\t\u0003\u0011Y\u0004C\u0004\u0005(\u0006!\tAa\u000f\t\u000f\u0011%\u0016\u0001\"\u0001\u0003<!9A1V\u0001\u0005\u0002\tm\u0002b\u0002CW\u0003\u0011\u0005!1\b\u0005\b\t_\u000bA\u0011\u0001B\u001e\u0011\u001d!\t,\u0001C\u0001\u0005wAq\u0001b-\u0002\t\u0003\u0011Y\u0004C\u0004\u00056\u0006!\tAa\u000f\t\u000f\u0011]\u0016\u0001\"\u0001\u0003<!9A\u0011X\u0001\u0005\u0002\tm\u0002b\u0002C^\u0003\u0011\u0005!1\b\u0005\b\t{\u000bA\u0011\u0001B\u001e\u0011\u001d!y,\u0001C\u0001\u0005wAq\u0001\"1\u0002\t\u0003\u0011Y\u0004C\u0004\u0005D\u0006!\tAa\u000f\t\u000f\u0011\u0015\u0017\u0001\"\u0001\u0003<!9AqY\u0001\u0005\u0002\tm\u0002b\u0002Ce\u0003\u0011\u0005!1\b\u0005\b\t\u0017\fA\u0011\u0001B\u001e\u0011\u001d!i-\u0001C\u0001\u0005wAq\u0001b4\u0002\t\u0003\u0011Y\u0004C\u0004\u0005R\u0006!\tAa\u000f\t\u000f\u0011M\u0017\u0001\"\u0001\u0003<!9AQ[\u0001\u0005\u0002\tm\u0002b\u0002Cl\u0003\u0011\u0005!1\b\u0005\b\t3\fA\u0011\u0001B\u001e\u0011\u001d!Y.\u0001C\u0001\u0005wAq\u0001\"8\u0002\t\u0003!y\u000eC\u0004\u0005d\u0006!\tAa\u000f\u0002\u0013I+7o\\;sG\u0016\u001c(\u0002BAg\u0003\u001f\f\u0011b]2bY\u0006\u001cG/[2\u000b\u0005\u0005E\u0017aA8sOB\u0019\u0011Q[\u0001\u000e\u0005\u0005-\'!\u0003*fg>,(oY3t\'\r\t\u00111\u001c\t\u0005\u0003;\f\u0019/\u0004\u0002\u0002`*\u0011\u0011\u0011]\u0001\u0006g\u000e\fG.Y\u0005\u0005\u0003K\fyN\u0001\u0004B]f\u0014VMZ\u0001\u0007y%t\u0017\u000e\u001e \u0004\u0001Q\u0011\u00111[\u0001\u000fe\u0016\u001cx.\u001e:dK\n+h\u000e\u001a7f+\t\t\t\u0010\u0005\u0003\u0002t\u0006uXBAA{\u0015\u0011\t90!?\u0002\tU$\u0018\u000e\u001c\u0006\u0003\u0003w\fAA[1wC&!\u0011q`A{\u00059\u0011Vm]8ve\u000e,\')\u001e8eY\u0016\f!\"\\1lKN#(/\u001b8h)\u0019\u0011)Aa\u0007\u0003 A!!q\u0001B\u000b\u001d\u0011\u0011IA!\u0005\u0011\t\t-\u0011q\\\u0007\u0003\u0005\u001bQAAa\u0004\u0002j\u00061AH]8pizJAAa\u0005\u0002`\u00061\u0001K]3eK\u001aLAAa\u0006\u0003\u001a\t11\u000b\u001e:j]\u001eTAAa\u0005\u0002`\"9!Q\u0004\u0003A\u0002\t\u0015\u0011\u0001\u0004:fg>,(oY3OC6,\u0007b\u0002B\u0011\t\u0001\u0007!1E\u0001\u0005CJ<7\u000f\u0005\u0004\u0002^\n\u0015\"\u0011F\u0005\u0005\u0005O\tyNA\u0003BeJ\f\u0017\u0010\u0005\u0003\u0002^\n-\u0012\u0002\u0002B\u0017\u0003?\u00141!\u00118z\u000311wN]7biN#(/\u001b8h)\u0019\u0011)Aa\r\u00038!9!QG\u0003A\u0002\t\u0015\u0011!\u0003:boN#(/\u001b8h\u0011\u001d\u0011\t#\u0002a\u0001\u0005G\t1BY5h!J|\'\r\\3ngV\u0011!QA\u0001\u000fe\u0006<()[4Qe>\u0014G.Z7t\u0003Y\u0011\u0017n\u001a)s_\ndW-\\:XSRDW*Z:tC\u001e,G\u0003\u0002B\u0003\u0005\u0007BqA!\u0012\t\u0001\u0004\u0011I#\u0001\u0004qCJ\fW\u000eM\u0001\u001ae\u0006<()[4Qe>\u0014G.Z7t/&$\b.T3tg\u0006<W-A\u0006eS\u0012tu\u000e^#rk\u0006dGC\u0002B\u0003\u0005\u001b\u0012y\u0005C\u0004\u0003F)\u0001\rA!\u000b\t\u000f\tE#\u00021\u0001\u0003*\u00051\u0001/\u0019:b[F\naB]1x\t&$gj\u001c;FcV\fG.A\u0004fcV\fG.\u001a3\u0015\r\t\u0015!\u0011\fB.\u0011\u001d\u0011)\u0005\u0004a\u0001\u0005SAqA!\u0015\r\u0001\u0004\u0011I#\u0001\u0006sC^,\u0015/^1mK\u0012\fab^1t!2,8o\u0014:NS:,8\u000f\u0006\u0005\u0003\u0006\t\r$Q\rB4\u0011\u001d\u0011)E\u0004a\u0001\u0005SAqA!\u0015\u000f\u0001\u0004\u0011I\u0003C\u0004\u0003j9\u0001\rA!\u000b\u0002\rA\f\'/Y73\u0003E\u0011\u0018m^,bgBcWo](s\u001b&tWo]\u0001\u0012o\u0006\u001chj\u001c;QYV\u001cxJ]\'j]V\u001cH\u0003\u0003B\u0003\u0005c\u0012\u0019H!\u001e\t\u000f\t\u0015\u0003\u00031\u0001\u0003*!9!\u0011\u000b\tA\u0002\t%\u0002b\u0002B5!\u0001\u0007!\u0011F\u0001\u0015e\u0006<x+Y:O_R\u0004F.^:Pe6Kg.^:\u0002%\u0015D\bO]3tg&|gnV1t\r\u0006d7/Z\u0001\u0016e\u0006<X\t\u001f9sKN\u001c\u0018n\u001c8XCN4\u0015\r\\:f\u0003E)\u0007\u0010\u001d:fgNLwN\\,bgR\u0013X/Z\u0001\u0015e\u0006<X\t\u001f9sKN\u001c\u0018n\u001c8XCN$&/^3\u0002\u000f]\f7OT;mYR!!Q\u0001BC\u0011\u001d\u0011)E\u0006a\u0001\u0005S\t!B]1x/\u0006\u001ch*\u001e7m\u0003!9XM]3Ok2dG\u0003\u0002B\u0003\u0005\u001bCqA!\u0012\u0019\u0001\u0004\u0011I#A\u0006sC^<VM]3Ok2d\u0017!B2p[6\f\u0017\u0001\u0003:bo\u000e{W.\\1\u0002\u0007\u0005tG\r\u0006\u0004\u0003\u0006\te%1\u0014\u0005\b\u0005\u000bb\u0002\u0019\u0001B\u0015\u0011\u001d\u0011\t\u0006\ba\u0001\u0005S\taA]1x\u0003:$\u0017aB<bgR\u0013X/\u001a\u000b\u0005\u0005\u000b\u0011\u0019\u000bC\u0004\u0003Fy\u0001\rA!\u000b\u0002\u0015I\fwoV1t)J,X-\u0001\u0005xCN4\u0015\r\\:f)\u0011\u0011)Aa+\t\u000f\t\u0015\u0003\u00051\u0001\u0003*\u0005Y!/Y<XCN4\u0015\r\\:f\u0003-9\u0018m\u001d\'fgN$\u0006.\u00198\u0015\r\t\u0015!1\u0017B[\u0011\u001d\u0011)E\ta\u0001\u0005SAqA!\u0015#\u0001\u0004\u0011I#\u0001\bsC^<\u0016m\u001d\'fgN$\u0006.\u00198\u0002\u001d]\f7OT8u\u0019\u0016\u001c8\u000f\u00165b]R1!Q\u0001B_\u0005\u007fCqA!\u0012%\u0001\u0004\u0011I\u0003C\u0004\u0003R\u0011\u0002\rA!\u000b\u0002#I\fwoV1t\u001d>$H*Z:t)\"\fg.\u0001\bxCN<%/Z1uKJ$\u0006.\u00198\u0015\r\t\u0015!q\u0019Be\u0011\u001d\u0011)E\na\u0001\u0005SAqA!\u0015\'\u0001\u0004\u0011I#A\tsC^<\u0016m]$sK\u0006$XM\u001d+iC:\f\u0011c^1t\u001d>$xI]3bi\u0016\u0014H\u000b[1o)\u0019\u0011)A!5\u0003T\"9!Q\t\u0015A\u0002\t%\u0002b\u0002B)Q\u0001\u0007!\u0011F\u0001\u0015e\u0006<x+Y:O_R<%/Z1uKJ$\u0006.\u00198\u0002)]\f7\u000fT3tgRC\u0017M\\(s\u000bF,\u0018\r\u001c+p)\u0019\u0011)Aa7\u0003^\"9!Q\t\u0016A\u0002\t%\u0002b\u0002B)U\u0001\u0007!\u0011F\u0001\u0018e\u0006<x+Y:MKN\u001cH\u000b[1o\u001fJ,\u0015/^1m)>\fqc^1t\u001d>$H*Z:t)\"\fgn\u0014:FcV\fG\u000eV8\u0015\r\t\u0015!Q\u001dBt\u0011\u001d\u0011)\u0005\fa\u0001\u0005SAqA!\u0015-\u0001\u0004\u0011I#\u0001\u000esC^<\u0016m\u001d(pi2+7o\u001d+iC:|%/R9vC2$v.A\fxCN<%/Z1uKJ$\u0006.\u00198Pe\u0016\u000bX/\u00197U_R1!Q\u0001Bx\u0005cDqA!\u0012/\u0001\u0004\u0011I\u0003C\u0004\u0003R9\u0002\rA!\u000b\u00025I\fwoV1t\u000fJ,\u0017\r^3s)\"\fgn\u0014:FcV\fG\u000eV8\u00025]\f7OT8u\u000fJ,\u0017\r^3s)\"\fgn\u0014:FcV\fG\u000eV8\u0015\r\t\u0015!\u0011 B~\u0011\u001d\u0011)\u0005\ra\u0001\u0005SAqA!\u00151\u0001\u0004\u0011I#A\u000fsC^<\u0016m\u001d(pi\u001e\u0013X-\u0019;feRC\u0017M\\(s\u000bF,\u0018\r\u001c+p\u0003=!\u0017\u000e\u001a(piN#\u0018M\u001d;XSRDGC\u0002B\u0003\u0007\u0007\u0019)\u0001C\u0004\u0003FI\u0002\rA!\u000b\t\u000f\tE#\u00071\u0001\u0003*\u0005\u0011\"/Y<ES\u0012tu\u000e^*uCJ$x+\u001b;i\u0003-\u0019H/\u0019:uK\u0012<\u0016\u000e\u001e5\u0015\r\t\u00151QBB\b\u0011\u001d\u0011)\u0005\u000ea\u0001\u0005SAqA!\u00155\u0001\u0004\u0011I#\u0001\bsC^\u001cF/\u0019:uK\u0012<\u0016\u000e\u001e5\u0002\u001b\u0011LGMT8u\u000b:$w+\u001b;i)\u0019\u0011)aa\u0006\u0004\u001a!9!Q\t\u001cA\u0002\t%\u0002b\u0002B)m\u0001\u0007!\u0011F\u0001\u0011e\u0006<H)\u001b3O_R,e\u000eZ,ji\"\f\u0011\"\u001a8eK\u0012<\u0016\u000e\u001e5\u0015\r\t\u00151\u0011EB\u0012\u0011\u001d\u0011)\u0005\u000fa\u0001\u0005SAqA!\u00159\u0001\u0004\u0011I#\u0001\u0007sC^,e\u000eZ3e/&$\b.A\u0007eS\u0012tu\u000e^\"p]R\f\u0017N\u001c\u000b\u0007\u0005\u000b\u0019Yc!\f\t\u000f\t\u0015#\b1\u0001\u0003*!9!\u0011\u000b\u001eA\u0002\t%\u0012\u0001\u0005:bo\u0012KGMT8u\u0007>tG/Y5o\u0003%\u0019wN\u001c;bS:,G\r\u0006\u0004\u0003\u0006\rU2q\u0007\u0005\b\u0005\u000bb\u0004\u0019\u0001B\u0015\u0011\u001d\u0011\t\u0006\u0010a\u0001\u0005S\tAB]1x\u0007>tG/Y5oK\u0012\f\u0001\u0003Z5e\u001d>$8i\u001c8uC&t7*Z=\u0015\r\t\u00151qHB!\u0011\u001d\u0011)E\u0010a\u0001\u0005SAqA!\u0015?\u0001\u0004\u0011I#A\nsC^$\u0015\u000e\u001a(pi\u000e{g\u000e^1j].+\u00170\u0001\u0007d_:$\u0018-\u001b8fI.+\u0017\u0010\u0006\u0004\u0003\u0006\r%31\n\u0005\b\u0005\u000b\u0002\u0005\u0019\u0001B\u0015\u0011\u001d\u0011\t\u0006\u0011a\u0001\u0005S\tqB]1x\u0007>tG/Y5oK\u0012\\U-_\u0001\u0015o\u0006\u001cH\u000b[3TC6,\u0017J\\:uC:\u001cW-Q:\u0015\r\t\u001511KB+\u0011\u001d\u0011)E\u0011a\u0001\u0005SAqA!\u0015C\u0001\u0004\u0011I#A\fsC^<\u0016m\u001d+iKN\u000bW.Z%ogR\fgnY3Bg\u00069r/Y:O_R$\u0006.Z*b[\u0016Len\u001d;b]\u000e,\u0017i\u001d\u000b\u0007\u0005\u000b\u0019ifa\u0018\t\u000f\t\u0015C\t1\u0001\u0003*!9!\u0011\u000b#A\u0002\t%\u0012A\u0007:bo^\u000b7OT8u)\",7+Y7f\u0013:\u001cH/\u00198dK\u0006\u001b\u0018aC<bg:{G/R7qif$BA!\u0002\u0004h!9!Q\t$A\u0002\t%\u0012A\u0004:bo^\u000b7OT8u\u000b6\u0004H/_\u0001\to\u0006\u001cX)\u001c9usR!!QAB8\u0011\u001d\u0011)\u0005\u0013a\u0001\u0005S\t1B]1x/\u0006\u001cX)\u001c9us\u0006\u0001r/Y:O_RLen\u001d;b]\u000e,wJ\u001a\u000b\u0007\u0005\u000b\u00199h!\u001f\t\u000f\t\u0015#\n1\u0001\u0003*!9!\u0011\u000b&A\u0002\t%\u0012a\u0005:bo^\u000b7OT8u\u0013:\u001cH/\u00198dK>3\u0017!D<bg&s7\u000f^1oG\u0016|e\r\u0006\u0004\u0003\u0006\r\u000551\u0011\u0005\b\u0005\u000bb\u0005\u0019\u0001B\u0015\u0011\u001d\u0011\t\u0006\u0014a\u0001\u0005S\t\u0001C]1x/\u0006\u001c\u0018J\\:uC:\u001cWm\u00144\u0002A!\fG\rT3oORD\u0017J\\:uK\u0006$wJZ#ya\u0016\u001cG/\u001a3MK:<G\u000f\u001b\u000b\t\u0005\u000b\u0019Yi!$\u0004\u0010\"9!Q\t(A\u0002\t%\u0002b\u0002B)\u001d\u0002\u0007!\u0011\u0006\u0005\b\u0005Sr\u0005\u0019\u0001B\u0015\u0003\r\u0012\u0018m\u001e%bI2+gn\u001a;i\u0013:\u001cH/Z1e\u001f\u001a,\u0005\u0010]3di\u0016$G*\u001a8hi\"\f\u0011\u0002[1e\u0019\u0016tw\r\u001e5\u0015\r\t\u00151qSBM\u0011\u001d\u0011)\u0005\u0015a\u0001\u0005SAqA!\u0015Q\u0001\u0004\u0011I#\u0001\u0007sC^D\u0015\r\u001a\'f]\u001e$\b.\u0001\u000fiC\u0012\u001c\u0016N_3J]N$X-\u00193PM\u0016C\b/Z2uK\u0012\u001c\u0016N_3\u0015\u0011\t\u00151\u0011UBR\u0007KCqA!\u0012S\u0001\u0004\u0011I\u0003C\u0004\u0003RI\u0003\rA!\u000b\t\u000f\t%$\u000b1\u0001\u0003*\u0005y\"/Y<IC\u0012\u001c\u0016N_3J]N$X-\u00193PM\u0016C\b/Z2uK\u0012\u001c\u0016N_3\u0002\u000f!\fGmU5{KR1!QABW\u0007_CqA!\u0012U\u0001\u0004\u0011I\u0003C\u0004\u0003RQ\u0003\rA!\u000b\u0002\u0015I\fw\u000fS1e\'&TX-\u0001\u0005d_6l\u0017MQ;u)\u0019\u0011)aa.\u0004:\"9!Q\t,A\u0002\t%\u0002b\u0002B)-\u0002\u0007!\u0011F\u0001\fe\u0006<8i\\7nC\n+H/\u0001\u0005d_6l\u0017-\u00118e)\u0019\u0011)a!1\u0004D\"9!Q\t-A\u0002\t%\u0002b\u0002B)1\u0002\u0007!\u0011F\u0001\fe\u0006<8i\\7nC\u0006sG-\u0001\twCJL\u0017M\u00197f/\u0006\u001ch+\u00197vKR1!QABf\u0007\u001bDqA!\u0012[\u0001\u0004\u0011I\u0003C\u0004\u0003Ri\u0003\rA!\u000b\u0002\'I\fwOV1sS\u0006\u0014G.Z,bgZ\u000bG.^3\u0002\u001d9|GOV1mS\u0012\u0004vn]%oi\u0006\t\"/Y<O_R4\u0016\r\\5e!>\u001c\u0018J\u001c;\u0002!9|G\u000fT5uKJ\fG\u000eU8t\u0013:$\u0018a\u0005:bo:{G\u000fT5uKJ\fG\u000eU8t\u0013:$\u0018a\u00048piZ\u000bG.\u001b3Q_NduN\\4\u0002%I\fwOT8u-\u0006d\u0017\u000e\u001a)pg2{gnZ\u0001\u0012]>$H*\u001b;fe\u0006d\u0007k\\:M_:<\u0017\u0001\u0006:bo:{G\u000fT5uKJ\fG\u000eU8t\u0019>tw-\u0001\to_R4\u0016\r\\5e!>\u001ch\t\\8bi\u0006\u0019\"/Y<O_R4\u0016\r\\5e!>\u001ch\t\\8bi\u0006\u0011bn\u001c;MSR,\'/\u00197Q_N4En\\1u\u0003U\u0011\u0018m\u001e(pi2KG/\u001a:bYB{7O\u00127pCR\f\u0011C\\8u-\u0006d\u0017\u000e\u001a)pg\u0012{WO\u00197f\u0003Q\u0011\u0018m\u001e(piZ\u000bG.\u001b3Q_N$u.\u001e2mK\u0006\u0019bn\u001c;MSR,\'/\u00197Q_N$u.\u001e2mK\u00061\"/Y<O_Rd\u0015\u000e^3sC2\u0004vn\u001d#pk\ndW-A\bo_R4\u0016\r\\5e!>\u001c(,\u00138u\u0003I\u0011\u0018m\u001e(piZ\u000bG.\u001b3Q_NT\u0016J\u001c;\u0002#9|G\u000fT5uKJ\fG\u000eU8t5&sG/\u0001\u000bsC^tu\u000e\u001e\'ji\u0016\u0014\u0018\r\u001c)pgjKe\u000e^\u0001\u0011]>$h+\u00197jIB{7O\u0017\'p]\u001e\f1C]1x\u001d>$h+\u00197jIB{7O\u0017\'p]\u001e\f!C\\8u\u0019&$XM]1m!>\u001c(\fT8oO\u0006)\"/Y<O_Rd\u0015\u000e^3sC2\u0004vn\u001d.M_:<\u0017!\u00058piZ\u000bG.\u001b3Q_NTf\t\\8bi\u0006!\"/Y<O_R4\u0016\r\\5e!>\u001c(L\u00127pCR\f1C\\8u\u0019&$XM]1m!>\u001c(L\u00127pCR\faC]1x\u001d>$H*\u001b;fe\u0006d\u0007k\\:[\r2|\u0017\r^\u0001\u0013]>$h+\u00197jIB{7O\u0017#pk\ndW-A\u000bsC^tu\u000e\u001e,bY&$\u0007k\\:[\t>,(\r\\3\u0002)9|G\u000fT5uKJ\fG\u000eU8t5\u0012{WO\u00197f\u0003]\u0011\u0018m\u001e(pi2KG/\u001a:bYB{7O\u0017#pk\ndW-A\u0016qY\u0016\f7/\u001a#fM&tWmU2bY\u0006\u001cG/[2GS2dg)\u001b7f!\u0006$\bN\\1nK\u0016sgOV1s\u00039\u0012\u0018m\u001e)mK\u0006\u001cX\rR3gS:,7kY1mC\u000e$\u0018n\u0019$jY24\u0015\u000e\\3QCRDg.Y7f\u000b:4h+\u0019:\u0002%9|GOV1mS\u0012tuN\u001c.fe>Le\u000e^\u0001\u0016e\u0006<hj\u001c;WC2LGMT8o5\u0016\u0014x.\u00138u\u0003Qqw\u000e\u001e\'ji\u0016\u0014\u0018\r\u001c(p]j+\'o\\%oi\u00069\"/Y<O_Rd\u0015\u000e^3sC2tuN\u001c.fe>Le\u000e^\u0001\u0014]>$h+\u00197jI:{gNW3s_2{gnZ\u0001\u0017e\u0006<hj\u001c;WC2LGMT8o5\u0016\u0014x\u000eT8oO\u0006)bn\u001c;MSR,\'/\u00197O_:TVM]8M_:<\u0017\u0001\u0007:bo:{G\u000fT5uKJ\fGNT8o5\u0016\u0014x\u000eT8oO\u0006!bn\u001c;WC2LGMT8o5\u0016\u0014xN\u00127pCR\fqC]1x\u001d>$h+\u00197jI:{gNW3s_\u001acw.\u0019;\u0002-9|G\u000fT5uKJ\fGNT8o5\u0016\u0014xN\u00127pCR\f\u0011D]1x\u001d>$H*\u001b;fe\u0006dgj\u001c8[KJ|g\t\\8bi\u0006)bn\u001c;WC2LGMT8o5\u0016\u0014x\u000eR8vE2,\u0017\u0001\u0007:bo:{GOV1mS\u0012tuN\u001c.fe>$u.\u001e2mK\u00069bn\u001c;MSR,\'/\u00197O_:TVM]8E_V\u0014G.Z\u0001\u001be\u0006<hj\u001c;MSR,\'/\u00197O_:TVM]8E_V\u0014G.Z\u0001\u000f]>$h+\u00197jI:+w-\u00138u\u0003E\u0011\u0018m\u001e(piZ\u000bG.\u001b3OK\u001eLe\u000e^\u0001\u0011]>$H*\u001b;fe\u0006dg*Z4J]R\f1C]1x\u001d>$H*\u001b;fe\u0006dg*Z4J]R\fqB\\8u-\u0006d\u0017\u000e\u001a(fO2{gnZ\u0001\u0013e\u0006<hj\u001c;WC2LGMT3h\u0019>tw-A\to_Rd\u0015\u000e^3sC2tUm\u001a\'p]\u001e\fAC]1x\u001d>$H*\u001b;fe\u0006dg*Z4M_:<\u0017\u0001\u00058piZ\u000bG.\u001b3OK\u001e4En\\1u\u0003M\u0011\u0018m\u001e(piZ\u000bG.\u001b3OK\u001e4En\\1u\u0003Iqw\u000e\u001e\'ji\u0016\u0014\u0018\r\u001c(fO\u001acw.\u0019;\u0002+I\fwOT8u\u0019&$XM]1m\u001d\u0016<g\t\\8bi\u0006\tbn\u001c;WC2LGMT3h\t>,(\r\\3\u0002)I\fwOT8u-\u0006d\u0017\u000e\u001a(fO\u0012{WO\u00197f\u0003Mqw\u000e\u001e\'ji\u0016\u0014\u0018\r\u001c(fO\u0012{WO\u00197f\u0003Y\u0011\u0018m\u001e(pi2KG/\u001a:bY:+w\rR8vE2,\u0017a\u00048piZ\u000bG.\u001b3OK\u001eT\u0016J\u001c;\u0002%I\fwOT8u-\u0006d\u0017\u000e\u001a(fOjKe\u000e^\u0001\u0012]>$H*\u001b;fe\u0006dg*Z4[\u0013:$\u0018\u0001\u0006:bo:{G\u000fT5uKJ\fGNT3h5&sG/\u0001\to_R4\u0016\r\\5e\u001d\u0016<\'\fT8oO\u0006\u0019\"/Y<O_R4\u0016\r\\5e\u001d\u0016<\'\fT8oO\u0006\u0011bn\u001c;MSR,\'/\u00197OK\u001eTFj\u001c8h\u0003U\u0011\u0018m\u001e(pi2KG/\u001a:bY:+wM\u0017\'p]\u001e\f\u0011C\\8u-\u0006d\u0017\u000e\u001a(fOj3En\\1u\u0003Q\u0011\u0018m\u001e(piZ\u000bG.\u001b3OK\u001eTf\t\\8bi\u0006\u0019bn\u001c;MSR,\'/\u00197OK\u001eTf\t\\8bi\u00061\"/Y<O_Rd\u0015\u000e^3sC2tUm\u001a.GY>\fG/\u0001\no_R4\u0016\r\\5e\u001d\u0016<\'\fR8vE2,\u0017!\u0006:bo:{GOV1mS\u0012tUm\u001a.E_V\u0014G.Z\u0001\u0015]>$H*\u001b;fe\u0006dg*Z4[\t>,(\r\\3\u0002/I\fwOT8u\u0019&$XM]1m\u001d\u0016<\'\fR8vE2,\u0017A\u00068piZ\u000bG.\u001b3Q_N4\u0015N\\5uK\u001acw.\u0019;\u00023I\fwOT8u-\u0006d\u0017\u000e\u001a)pg\u001aKg.\u001b;f\r2|\u0017\r^\u0001\u0019]>$H*\u001b;fe\u0006d\u0007k\\:GS:LG/\u001a$m_\u0006$\u0018a\u0007:bo:{G\u000fT5uKJ\fG\u000eU8t\r&t\u0017\u000e^3GY>\fG/A\fo_R4\u0016\r\\5e!>\u001ch)\u001b8ji\u0016$u.\u001e2mK\u0006Q\"/Y<O_R4\u0016\r\\5e!>\u001ch)\u001b8ji\u0016$u.\u001e2mK\u0006Ibn\u001c;MSR,\'/\u00197Q_N4\u0015N\\5uK\u0012{WO\u00197f\u0003q\u0011\u0018m\u001e(pi2KG/\u001a:bYB{7OR5oSR,Gi\\;cY\u0016\fqC\\8u-\u0006d\u0017\u000e\u001a)pgj3\u0015N\\5uK\u001acw.\u0019;\u00025I\fwOT8u-\u0006d\u0017\u000e\u001a)pgj3\u0015N\\5uK\u001acw.\u0019;\u000239|G\u000fT5uKJ\fG\u000eU8t5\u001aKg.\u001b;f\r2|\u0017\r^\u0001\u001de\u0006<hj\u001c;MSR,\'/\u00197Q_NTf)\u001b8ji\u00164En\\1u\u0003aqw\u000e\u001e,bY&$\u0007k\\:[\r&t\u0017\u000e^3E_V\u0014G.Z\u0001\u001ce\u0006<hj\u001c;WC2LG\rU8t5\u001aKg.\u001b;f\t>,(\r\\3\u000259|G\u000fT5uKJ\fG\u000eU8t5\u001aKg.\u001b;f\t>,(\r\\3\u0002;I\fwOT8u\u0019&$XM]1m!>\u001c(LR5oSR,Gi\\;cY\u0016\faC\\8u-\u0006d\u0017\u000e\u001a(fO\u001aKg.\u001b;f\r2|\u0017\r^\u0001\u001ae\u0006<hj\u001c;WC2LGMT3h\r&t\u0017\u000e^3GY>\fG/\u0001\ro_Rd\u0015\u000e^3sC2tUm\u001a$j]&$XM\u00127pCR\f1D]1x\u001d>$H*\u001b;fe\u0006dg*Z4GS:LG/\u001a$m_\u0006$\u0018a\u00068piZ\u000bG.\u001b3OK\u001e4\u0015N\\5uK\u0012{WO\u00197f\u0003i\u0011\u0018m\u001e(piZ\u000bG.\u001b3OK\u001e4\u0015N\\5uK\u0012{WO\u00197f\u0003eqw\u000e\u001e\'ji\u0016\u0014\u0018\r\u001c(fO\u001aKg.\u001b;f\t>,(\r\\3\u00029I\fwOT8u\u0019&$XM]1m\u001d\u0016<g)\u001b8ji\u0016$u.\u001e2mK\u00069bn\u001c;WC2LGMT3h5\u001aKg.\u001b;f\r2|\u0017\r^\u0001\u001be\u0006<hj\u001c;WC2LGMT3h5\u001aKg.\u001b;f\r2|\u0017\r^\u0001\u001a]>$H*\u001b;fe\u0006dg*Z4[\r&t\u0017\u000e^3GY>\fG/\u0001\u000fsC^tu\u000e\u001e\'ji\u0016\u0014\u0018\r\u001c(fOj3\u0015N\\5uK\u001acw.\u0019;\u000219|GOV1mS\u0012tUm\u001a.GS:LG/\u001a#pk\ndW-A\u000esC^tu\u000e\u001e,bY&$g*Z4[\r&t\u0017\u000e^3E_V\u0014G.Z\u0001\u001b]>$H*\u001b;fe\u0006dg*Z4[\r&t\u0017\u000e^3E_V\u0014G.Z\u0001\u001ee\u0006<hj\u001c;MSR,\'/\u00197OK\u001eTf)\u001b8ji\u0016$u.\u001e2mK\u0006Qbn\u001c;WC2LGMT8o5\u0016\u0014xNR5oSR,g\t\\8bi\u0006i\"/Y<O_R4\u0016\r\\5e\u001d>t\',\u001a:p\r&t\u0017\u000e^3GY>\fG/\u0001\u000fo_Rd\u0015\u000e^3sC2tuN\u001c.fe>4\u0015N\\5uK\u001acw.\u0019;\u0002?I\fwOT8u\u0019&$XM]1m\u001d>t\',\u001a:p\r&t\u0017\u000e^3GY>\fG/A\u000eo_R4\u0016\r\\5e\u001d>t\',\u001a:p\r&t\u0017\u000e^3E_V\u0014G.Z\u0001\u001fe\u0006<hj\u001c;WC2LGMT8o5\u0016\u0014xNR5oSR,Gi\\;cY\u0016\fQD\\8u\u0019&$XM]1m\u001d>t\',\u001a:p\r&t\u0017\u000e^3E_V\u0014G.Z\u0001!e\u0006<hj\u001c;MSR,\'/\u00197O_:TVM]8GS:LG/\u001a#pk\ndW-A\no_R4\u0016\r\\5e\r&t\u0017\u000e^3GY>\fG/\u0001\fsC^tu\u000e\u001e,bY&$g)\u001b8ji\u00164En\\1u\u0003Uqw\u000e\u001e\'ji\u0016\u0014\u0018\r\u001c$j]&$XM\u00127pCR\f\u0001D]1x\u001d>$H*\u001b;fe\u0006dg)\u001b8ji\u00164En\\1u\u0003Qqw\u000e\u001e,bY&$g)\u001b8ji\u0016$u.\u001e2mK\u00069\"/Y<O_R4\u0016\r\\5e\r&t\u0017\u000e^3E_V\u0014G.Z\u0001\u0017]>$H*\u001b;fe\u0006dg)\u001b8ji\u0016$u.\u001e2mK\u0006I\"/Y<O_Rd\u0015\u000e^3sC24\u0015N\\5uK\u0012{WO\u00197f\u0003Mqw\u000e\u001e,bY&$g*^7fe&\u001c7\t[1s\u0003Y\u0011\u0018m\u001e(piZ\u000bG.\u001b3Ok6,\'/[2DQ\u0006\u0014\u0018!\u00068pi2KG/\u001a:bY:+X.\u001a:jG\u000eC\u0017M]\u0001\u0019e\u0006<hj\u001c;MSR,\'/\u00197Ok6,\'/[2DQ\u0006\u0014\u0018aC5om\u0006d\u0017\u000eZ*ju\u0016$BA!\u0002\u0005b\"A!QIAc\u0001\u0004\u0011I#\u0001\bsC^LeN^1mS\u0012\u001c\u0016N_3
    #9 = Utf8               rawInvalidSize
   #10 = Utf8               ()Ljava/lang/String;
   #11 = Utf8               org/scalactic/Resources$
   #12 = Class              #11           // org/scalactic/Resources$
   #13 = Utf8               MODULE$
   #14 = Utf8               Lorg/scalactic/Resources$;
   #15 = NameAndType        #13:#14       // MODULE$:Lorg/scalactic/Resources$;
   #16 = Fieldref           #12.#15       // org/scalactic/Resources$.MODULE$:Lorg/scalactic/Resources$;
   #17 = NameAndType        #9:#10        // rawInvalidSize:()Ljava/lang/String;
   #18 = Methodref          #12.#17       // org/scalactic/Resources$.rawInvalidSize:()Ljava/lang/String;
   #19 = Utf8               invalidSize
   #20 = Utf8               (Ljava/lang/Object;)Ljava/lang/String;
   #21 = Utf8               param0
   #22 = NameAndType        #19:#20       // invalidSize:(Ljava/lang/Object;)Ljava/lang/String;
   #23 = Methodref          #12.#22       // org/scalactic/Resources$.invalidSize:(Ljava/lang/Object;)Ljava/lang/String;
   #24 = Utf8               Ljava/lang/Object;
   #25 = Utf8               rawNotLiteralNumericChar
   #26 = NameAndType        #25:#10       // rawNotLiteralNumericChar:()Ljava/lang/String;
   #27 = Methodref          #12.#26       // org/scalactic/Resources$.rawNotLiteralNumericChar:()Ljava/lang/String;
   #28 = Utf8               notLiteralNumericChar
   #29 = NameAndType        #28:#10       // notLiteralNumericChar:()Ljava/lang/String;
   #30 = Methodref          #12.#29       // org/scalactic/Resources$.notLiteralNumericChar:()Ljava/lang/String;
   #31 = Utf8               rawNotValidNumericChar
   #32 = NameAndType        #31:#10       // rawNotValidNumericChar:()Ljava/lang/String;
   #33 = Methodref          #12.#32       // org/scalactic/Resources$.rawNotValidNumericChar:()Ljava/lang/String;
   #34 = Utf8               notValidNumericChar
   #35 = NameAndType        #34:#10       // notValidNumericChar:()Ljava/lang/String;
   #36 = Methodref          #12.#35       // org/scalactic/Resources$.notValidNumericChar:()Ljava/lang/String;
   #37 = Utf8               rawNotLiteralFiniteDouble
   #38 = NameAndType        #37:#10       // rawNotLiteralFiniteDouble:()Ljava/lang/String;
   #39 = Methodref          #12.#38       // org/scalactic/Resources$.rawNotLiteralFiniteDouble:()Ljava/lang/String;
   #40 = Utf8               notLiteralFiniteDouble
   #41 = NameAndType        #40:#10       // notLiteralFiniteDouble:()Ljava/lang/String;
   #42 = Methodref          #12.#41       // org/scalactic/Resources$.notLiteralFiniteDouble:()Ljava/lang/String;
   #43 = Utf8               rawNotValidFiniteDouble
   #44 = NameAndType        #43:#10       // rawNotValidFiniteDouble:()Ljava/lang/String;
   #45 = Methodref          #12.#44       // org/scalactic/Resources$.rawNotValidFiniteDouble:()Ljava/lang/String;
   #46 = Utf8               notValidFiniteDouble
   #47 = NameAndType        #46:#10       // notValidFiniteDouble:()Ljava/lang/String;
   #48 = Methodref          #12.#47       // org/scalactic/Resources$.notValidFiniteDouble:()Ljava/lang/String;
   #49 = Utf8               rawNotLiteralFiniteFloat
   #50 = NameAndType        #49:#10       // rawNotLiteralFiniteFloat:()Ljava/lang/String;
   #51 = Methodref          #12.#50       // org/scalactic/Resources$.rawNotLiteralFiniteFloat:()Ljava/lang/String;
   #52 = Utf8               notLiteralFiniteFloat
   #53 = NameAndType        #52:#10       // notLiteralFiniteFloat:()Ljava/lang/String;
   #54 = Methodref          #12.#53       // org/scalactic/Resources$.notLiteralFiniteFloat:()Ljava/lang/String;
   #55 = Utf8               rawNotValidFiniteFloat
   #56 = NameAndType        #55:#10       // rawNotValidFiniteFloat:()Ljava/lang/String;
   #57 = Methodref          #12.#56       // org/scalactic/Resources$.rawNotValidFiniteFloat:()Ljava/lang/String;
   #58 = Utf8               notValidFiniteFloat
   #59 = NameAndType        #58:#10       // notValidFiniteFloat:()Ljava/lang/String;
   #60 = Methodref          #12.#59       // org/scalactic/Resources$.notValidFiniteFloat:()Ljava/lang/String;
   #61 = Utf8               rawNotLiteralNonZeroFiniteDouble
   #62 = NameAndType        #61:#10       // rawNotLiteralNonZeroFiniteDouble:()Ljava/lang/String;
   #63 = Methodref          #12.#62       // org/scalactic/Resources$.rawNotLiteralNonZeroFiniteDouble:()Ljava/lang/String;
   #64 = Utf8               notLiteralNonZeroFiniteDouble
   #65 = NameAndType        #64:#10       // notLiteralNonZeroFiniteDouble:()Ljava/lang/String;
   #66 = Methodref          #12.#65       // org/scalactic/Resources$.notLiteralNonZeroFiniteDouble:()Ljava/lang/String;
   #67 = Utf8               rawNotValidNonZeroFiniteDouble
   #68 = NameAndType        #67:#10       // rawNotValidNonZeroFiniteDouble:()Ljava/lang/String;
   #69 = Methodref          #12.#68       // org/scalactic/Resources$.rawNotValidNonZeroFiniteDouble:()Ljava/lang/String;
   #70 = Utf8               notValidNonZeroFiniteDouble
   #71 = NameAndType        #70:#10       // notValidNonZeroFiniteDouble:()Ljava/lang/String;
   #72 = Methodref          #12.#71       // org/scalactic/Resources$.notValidNonZeroFiniteDouble:()Ljava/lang/String;
   #73 = Utf8               rawNotLiteralNonZeroFiniteFloat
   #74 = NameAndType        #73:#10       // rawNotLiteralNonZeroFiniteFloat:()Ljava/lang/String;
   #75 = Methodref          #12.#74       // org/scalactic/Resources$.rawNotLiteralNonZeroFiniteFloat:()Ljava/lang/String;
   #76 = Utf8               notLiteralNonZeroFiniteFloat
   #77 = NameAndType        #76:#10       // notLiteralNonZeroFiniteFloat:()Ljava/lang/String;
   #78 = Methodref          #12.#77       // org/scalactic/Resources$.notLiteralNonZeroFiniteFloat:()Ljava/lang/String;
   #79 = Utf8               rawNotValidNonZeroFiniteFloat
   #80 = NameAndType        #79:#10       // rawNotValidNonZeroFiniteFloat:()Ljava/lang/String;
   #81 = Methodref          #12.#80       // org/scalactic/Resources$.rawNotValidNonZeroFiniteFloat:()Ljava/lang/String;
   #82 = Utf8               notValidNonZeroFiniteFloat
   #83 = NameAndType        #82:#10       // notValidNonZeroFiniteFloat:()Ljava/lang/String;
   #84 = Methodref          #12.#83       // org/scalactic/Resources$.notValidNonZeroFiniteFloat:()Ljava/lang/String;
   #85 = Utf8               rawNotLiteralNegZFiniteDouble
   #86 = NameAndType        #85:#10       // rawNotLiteralNegZFiniteDouble:()Ljava/lang/String;
   #87 = Methodref          #12.#86       // org/scalactic/Resources$.rawNotLiteralNegZFiniteDouble:()Ljava/lang/String;
   #88 = Utf8               notLiteralNegZFiniteDouble
   #89 = NameAndType        #88:#10       // notLiteralNegZFiniteDouble:()Ljava/lang/String;
   #90 = Methodref          #12.#89       // org/scalactic/Resources$.notLiteralNegZFiniteDouble:()Ljava/lang/String;
   #91 = Utf8               rawNotValidNegZFiniteDouble
   #92 = NameAndType        #91:#10       // rawNotValidNegZFiniteDouble:()Ljava/lang/String;
   #93 = Methodref          #12.#92       // org/scalactic/Resources$.rawNotValidNegZFiniteDouble:()Ljava/lang/String;
   #94 = Utf8               notValidNegZFiniteDouble
   #95 = NameAndType        #94:#10       // notValidNegZFiniteDouble:()Ljava/lang/String;
   #96 = Methodref          #12.#95       // org/scalactic/Resources$.notValidNegZFiniteDouble:()Ljava/lang/String;
   #97 = Utf8               rawNotLiteralNegZFiniteFloat
   #98 = NameAndType        #97:#10       // rawNotLiteralNegZFiniteFloat:()Ljava/lang/String;
   #99 = Methodref          #12.#98       // org/scalactic/Resources$.rawNotLiteralNegZFiniteFloat:()Ljava/lang/String;
  #100 = Utf8               notLiteralNegZFiniteFloat
  #101 = NameAndType        #100:#10      // notLiteralNegZFiniteFloat:()Ljava/lang/String;
  #102 = Methodref          #12.#101      // org/scalactic/Resources$.notLiteralNegZFiniteFloat:()Ljava/lang/String;
  #103 = Utf8               rawNotValidNegZFiniteFloat
  #104 = NameAndType        #103:#10      // rawNotValidNegZFiniteFloat:()Ljava/lang/String;
  #105 = Methodref          #12.#104      // org/scalactic/Resources$.rawNotValidNegZFiniteFloat:()Ljava/lang/String;
  #106 = Utf8               notValidNegZFiniteFloat
  #107 = NameAndType        #106:#10      // notValidNegZFiniteFloat:()Ljava/lang/String;
  #108 = Methodref          #12.#107      // org/scalactic/Resources$.notValidNegZFiniteFloat:()Ljava/lang/String;
  #109 = Utf8               rawNotLiteralNegFiniteDouble
  #110 = NameAndType        #109:#10      // rawNotLiteralNegFiniteDouble:()Ljava/lang/String;
  #111 = Methodref          #12.#110      // org/scalactic/Resources$.rawNotLiteralNegFiniteDouble:()Ljava/lang/String;
  #112 = Utf8               notLiteralNegFiniteDouble
  #113 = NameAndType        #112:#10      // notLiteralNegFiniteDouble:()Ljava/lang/String;
  #114 = Methodref          #12.#113      // org/scalactic/Resources$.notLiteralNegFiniteDouble:()Ljava/lang/String;
  #115 = Utf8               rawNotValidNegFiniteDouble
  #116 = NameAndType        #115:#10      // rawNotValidNegFiniteDouble:()Ljava/lang/String;
  #117 = Methodref          #12.#116      // org/scalactic/Resources$.rawNotValidNegFiniteDouble:()Ljava/lang/String;
  #118 = Utf8               notValidNegFiniteDouble
  #119 = NameAndType        #118:#10      // notValidNegFiniteDouble:()Ljava/lang/String;
  #120 = Methodref          #12.#119      // org/scalactic/Resources$.notValidNegFiniteDouble:()Ljava/lang/String;
  #121 = Utf8               rawNotLiteralNegFiniteFloat
  #122 = NameAndType        #121:#10      // rawNotLiteralNegFiniteFloat:()Ljava/lang/String;
  #123 = Methodref          #12.#122      // org/scalactic/Resources$.rawNotLiteralNegFiniteFloat:()Ljava/lang/String;
  #124 = Utf8               notLiteralNegFiniteFloat
  #125 = NameAndType        #124:#10      // notLiteralNegFiniteFloat:()Ljava/lang/String;
  #126 = Methodref          #12.#125      // org/scalactic/Resources$.notLiteralNegFiniteFloat:()Ljava/lang/String;
  #127 = Utf8               rawNotValidNegFiniteFloat
  #128 = NameAndType        #127:#10      // rawNotValidNegFiniteFloat:()Ljava/lang/String;
  #129 = Methodref          #12.#128      // org/scalactic/Resources$.rawNotValidNegFiniteFloat:()Ljava/lang/String;
  #130 = Utf8               notValidNegFiniteFloat
  #131 = NameAndType        #130:#10      // notValidNegFiniteFloat:()Ljava/lang/String;
  #132 = Methodref          #12.#131      // org/scalactic/Resources$.notValidNegFiniteFloat:()Ljava/lang/String;
  #133 = Utf8               rawNotLiteralPosZFiniteDouble
  #134 = NameAndType        #133:#10      // rawNotLiteralPosZFiniteDouble:()Ljava/lang/String;
  #135 = Methodref          #12.#134      // org/scalactic/Resources$.rawNotLiteralPosZFiniteDouble:()Ljava/lang/String;
  #136 = Utf8               notLiteralPosZFiniteDouble
  #137 = NameAndType        #136:#10      // notLiteralPosZFiniteDouble:()Ljava/lang/String;
  #138 = Methodref          #12.#137      // org/scalactic/Resources$.notLiteralPosZFiniteDouble:()Ljava/lang/String;
  #139 = Utf8               rawNotValidPosZFiniteDouble
  #140 = NameAndType        #139:#10      // rawNotValidPosZFiniteDouble:()Ljava/lang/String;
  #141 = Methodref          #12.#140      // org/scalactic/Resources$.rawNotValidPosZFiniteDouble:()Ljava/lang/String;
  #142 = Utf8               notValidPosZFiniteDouble
  #143 = NameAndType        #142:#10      // notValidPosZFiniteDouble:()Ljava/lang/String;
  #144 = Methodref          #12.#143      // org/scalactic/Resources$.notValidPosZFiniteDouble:()Ljava/lang/String;
  #145 = Utf8               rawNotLiteralPosZFiniteFloat
  #146 = NameAndType        #145:#10      // rawNotLiteralPosZFiniteFloat:()Ljava/lang/String;
  #147 = Methodref          #12.#146      // org/scalactic/Resources$.rawNotLiteralPosZFiniteFloat:()Ljava/lang/String;
  #148 = Utf8               notLiteralPosZFiniteFloat
  #149 = NameAndType        #148:#10      // notLiteralPosZFiniteFloat:()Ljava/lang/String;
  #150 = Methodref          #12.#149      // org/scalactic/Resources$.notLiteralPosZFiniteFloat:()Ljava/lang/String;
  #151 = Utf8               rawNotValidPosZFiniteFloat
  #152 = NameAndType        #151:#10      // rawNotValidPosZFiniteFloat:()Ljava/lang/String;
  #153 = Methodref          #12.#152      // org/scalactic/Resources$.rawNotValidPosZFiniteFloat:()Ljava/lang/String;
  #154 = Utf8               notValidPosZFiniteFloat
  #155 = NameAndType        #154:#10      // notValidPosZFiniteFloat:()Ljava/lang/String;
  #156 = Methodref          #12.#155      // org/scalactic/Resources$.notValidPosZFiniteFloat:()Ljava/lang/String;
  #157 = Utf8               rawNotLiteralPosFiniteDouble
  #158 = NameAndType        #157:#10      // rawNotLiteralPosFiniteDouble:()Ljava/lang/String;
  #159 = Methodref          #12.#158      // org/scalactic/Resources$.rawNotLiteralPosFiniteDouble:()Ljava/lang/String;
  #160 = Utf8               notLiteralPosFiniteDouble
  #161 = NameAndType        #160:#10      // notLiteralPosFiniteDouble:()Ljava/lang/String;
  #162 = Methodref          #12.#161      // org/scalactic/Resources$.notLiteralPosFiniteDouble:()Ljava/lang/String;
  #163 = Utf8               rawNotValidPosFiniteDouble
  #164 = NameAndType        #163:#10      // rawNotValidPosFiniteDouble:()Ljava/lang/String;
  #165 = Methodref          #12.#164      // org/scalactic/Resources$.rawNotValidPosFiniteDouble:()Ljava/lang/String;
  #166 = Utf8               notValidPosFiniteDouble
  #167 = NameAndType        #166:#10      // notValidPosFiniteDouble:()Ljava/lang/String;
  #168 = Methodref          #12.#167      // org/scalactic/Resources$.notValidPosFiniteDouble:()Ljava/lang/String;
  #169 = Utf8               rawNotLiteralPosFiniteFloat
  #170 = NameAndType        #169:#10      // rawNotLiteralPosFiniteFloat:()Ljava/lang/String;
  #171 = Methodref          #12.#170      // org/scalactic/Resources$.rawNotLiteralPosFiniteFloat:()Ljava/lang/String;
  #172 = Utf8               notLiteralPosFiniteFloat
  #173 = NameAndType        #172:#10      // notLiteralPosFiniteFloat:()Ljava/lang/String;
  #174 = Methodref          #12.#173      // org/scalactic/Resources$.notLiteralPosFiniteFloat:()Ljava/lang/String;
  #175 = Utf8               rawNotValidPosFiniteFloat
  #176 = NameAndType        #175:#10      // rawNotValidPosFiniteFloat:()Ljava/lang/String;
  #177 = Methodref          #12.#176      // org/scalactic/Resources$.rawNotValidPosFiniteFloat:()Ljava/lang/String;
  #178 = Utf8               notValidPosFiniteFloat
  #179 = NameAndType        #178:#10      // notValidPosFiniteFloat:()Ljava/lang/String;
  #180 = Methodref          #12.#179      // org/scalactic/Resources$.notValidPosFiniteFloat:()Ljava/lang/String;
  #181 = Utf8               rawNotLiteralNegZDouble
  #182 = NameAndType        #181:#10      // rawNotLiteralNegZDouble:()Ljava/lang/String;
  #183 = Methodref          #12.#182      // org/scalactic/Resources$.rawNotLiteralNegZDouble:()Ljava/lang/String;
  #184 = Utf8               notLiteralNegZDouble
  #185 = NameAndType        #184:#10      // notLiteralNegZDouble:()Ljava/lang/String;
  #186 = Methodref          #12.#185      // org/scalactic/Resources$.notLiteralNegZDouble:()Ljava/lang/String;
  #187 = Utf8               rawNotValidNegZDouble
  #188 = NameAndType        #187:#10      // rawNotValidNegZDouble:()Ljava/lang/String;
  #189 = Methodref          #12.#188      // org/scalactic/Resources$.rawNotValidNegZDouble:()Ljava/lang/String;
  #190 = Utf8               notValidNegZDouble
  #191 = NameAndType        #190:#10      // notValidNegZDouble:()Ljava/lang/String;
  #192 = Methodref          #12.#191      // org/scalactic/Resources$.notValidNegZDouble:()Ljava/lang/String;
  #193 = Utf8               rawNotLiteralNegZFloat
  #194 = NameAndType        #193:#10      // rawNotLiteralNegZFloat:()Ljava/lang/String;
  #195 = Methodref          #12.#194      // org/scalactic/Resources$.rawNotLiteralNegZFloat:()Ljava/lang/String;
  #196 = Utf8               notLiteralNegZFloat
  #197 = NameAndType        #196:#10      // notLiteralNegZFloat:()Ljava/lang/String;
  #198 = Methodref          #12.#197      // org/scalactic/Resources$.notLiteralNegZFloat:()Ljava/lang/String;
  #199 = Utf8               rawNotValidNegZFloat
  #200 = NameAndType        #199:#10      // rawNotValidNegZFloat:()Ljava/lang/String;
  #201 = Methodref          #12.#200      // org/scalactic/Resources$.rawNotValidNegZFloat:()Ljava/lang/String;
  #202 = Utf8               notValidNegZFloat
  #203 = NameAndType        #202:#10      // notValidNegZFloat:()Ljava/lang/String;
  #204 = Methodref          #12.#203      // org/scalactic/Resources$.notValidNegZFloat:()Ljava/lang/String;
  #205 = Utf8               rawNotLiteralNegZLong
  #206 = NameAndType        #205:#10      // rawNotLiteralNegZLong:()Ljava/lang/String;
  #207 = Methodref          #12.#206      // org/scalactic/Resources$.rawNotLiteralNegZLong:()Ljava/lang/String;
  #208 = Utf8               notLiteralNegZLong
  #209 = NameAndType        #208:#10      // notLiteralNegZLong:()Ljava/lang/String;
  #210 = Methodref          #12.#209      // org/scalactic/Resources$.notLiteralNegZLong:()Ljava/lang/String;
  #211 = Utf8               rawNotValidNegZLong
  #212 = NameAndType        #211:#10      // rawNotValidNegZLong:()Ljava/lang/String;
  #213 = Methodref          #12.#212      // org/scalactic/Resources$.rawNotValidNegZLong:()Ljava/lang/String;
  #214 = Utf8               notValidNegZLong
  #215 = NameAndType        #214:#10      // notValidNegZLong:()Ljava/lang/String;
  #216 = Methodref          #12.#215      // org/scalactic/Resources$.notValidNegZLong:()Ljava/lang/String;
  #217 = Utf8               rawNotLiteralNegZInt
  #218 = NameAndType        #217:#10      // rawNotLiteralNegZInt:()Ljava/lang/String;
  #219 = Methodref          #12.#218      // org/scalactic/Resources$.rawNotLiteralNegZInt:()Ljava/lang/String;
  #220 = Utf8               notLiteralNegZInt
  #221 = NameAndType        #220:#10      // notLiteralNegZInt:()Ljava/lang/String;
  #222 = Methodref          #12.#221      // org/scalactic/Resources$.notLiteralNegZInt:()Ljava/lang/String;
  #223 = Utf8               rawNotValidNegZInt
  #224 = NameAndType        #223:#10      // rawNotValidNegZInt:()Ljava/lang/String;
  #225 = Methodref          #12.#224      // org/scalactic/Resources$.rawNotValidNegZInt:()Ljava/lang/String;
  #226 = Utf8               notValidNegZInt
  #227 = NameAndType        #226:#10      // notValidNegZInt:()Ljava/lang/String;
  #228 = Methodref          #12.#227      // org/scalactic/Resources$.notValidNegZInt:()Ljava/lang/String;
  #229 = Utf8               rawNotLiteralNegDouble
  #230 = NameAndType        #229:#10      // rawNotLiteralNegDouble:()Ljava/lang/String;
  #231 = Methodref          #12.#230      // org/scalactic/Resources$.rawNotLiteralNegDouble:()Ljava/lang/String;
  #232 = Utf8               notLiteralNegDouble
  #233 = NameAndType        #232:#10      // notLiteralNegDouble:()Ljava/lang/String;
  #234 = Methodref          #12.#233      // org/scalactic/Resources$.notLiteralNegDouble:()Ljava/lang/String;
  #235 = Utf8               rawNotValidNegDouble
  #236 = NameAndType        #235:#10      // rawNotValidNegDouble:()Ljava/lang/String;
  #237 = Methodref          #12.#236      // org/scalactic/Resources$.rawNotValidNegDouble:()Ljava/lang/String;
  #238 = Utf8               notValidNegDouble
  #239 = NameAndType        #238:#10      // notValidNegDouble:()Ljava/lang/String;
  #240 = Methodref          #12.#239      // org/scalactic/Resources$.notValidNegDouble:()Ljava/lang/String;
  #241 = Utf8               rawNotLiteralNegFloat
  #242 = NameAndType        #241:#10      // rawNotLiteralNegFloat:()Ljava/lang/String;
  #243 = Methodref          #12.#242      // org/scalactic/Resources$.rawNotLiteralNegFloat:()Ljava/lang/String;
  #244 = Utf8               notLiteralNegFloat
  #245 = NameAndType        #244:#10      // notLiteralNegFloat:()Ljava/lang/String;
  #246 = Methodref          #12.#245      // org/scalactic/Resources$.notLiteralNegFloat:()Ljava/lang/String;
  #247 = Utf8               rawNotValidNegFloat
  #248 = NameAndType        #247:#10      // rawNotValidNegFloat:()Ljava/lang/String;
  #249 = Methodref          #12.#248      // org/scalactic/Resources$.rawNotValidNegFloat:()Ljava/lang/String;
  #250 = Utf8               notValidNegFloat
  #251 = NameAndType        #250:#10      // notValidNegFloat:()Ljava/lang/String;
  #252 = Methodref          #12.#251      // org/scalactic/Resources$.notValidNegFloat:()Ljava/lang/String;
  #253 = Utf8               rawNotLiteralNegLong
  #254 = NameAndType        #253:#10      // rawNotLiteralNegLong:()Ljava/lang/String;
  #255 = Methodref          #12.#254      // org/scalactic/Resources$.rawNotLiteralNegLong:()Ljava/lang/String;
  #256 = Utf8               notLiteralNegLong
  #257 = NameAndType        #256:#10      // notLiteralNegLong:()Ljava/lang/String;
  #258 = Methodref          #12.#257      // org/scalactic/Resources$.notLiteralNegLong:()Ljava/lang/String;
  #259 = Utf8               rawNotValidNegLong
  #260 = NameAndType        #259:#10      // rawNotValidNegLong:()Ljava/lang/String;
  #261 = Methodref          #12.#260      // org/scalactic/Resources$.rawNotValidNegLong:()Ljava/lang/String;
  #262 = Utf8               notValidNegLong
  #263 = NameAndType        #262:#10      // notValidNegLong:()Ljava/lang/String;
  #264 = Methodref          #12.#263      // org/scalactic/Resources$.notValidNegLong:()Ljava/lang/String;
  #265 = Utf8               rawNotLiteralNegInt
  #266 = NameAndType        #265:#10      // rawNotLiteralNegInt:()Ljava/lang/String;
  #267 = Methodref          #12.#266      // org/scalactic/Resources$.rawNotLiteralNegInt:()Ljava/lang/String;
  #268 = Utf8               notLiteralNegInt
  #269 = NameAndType        #268:#10      // notLiteralNegInt:()Ljava/lang/String;
  #270 = Methodref          #12.#269      // org/scalactic/Resources$.notLiteralNegInt:()Ljava/lang/String;
  #271 = Utf8               rawNotValidNegInt
  #272 = NameAndType        #271:#10      // rawNotValidNegInt:()Ljava/lang/String;
  #273 = Methodref          #12.#272      // org/scalactic/Resources$.rawNotValidNegInt:()Ljava/lang/String;
  #274 = Utf8               notValidNegInt
  #275 = NameAndType        #274:#10      // notValidNegInt:()Ljava/lang/String;
  #276 = Methodref          #12.#275      // org/scalactic/Resources$.notValidNegInt:()Ljava/lang/String;
  #277 = Utf8               rawNotLiteralNonZeroDouble
  #278 = NameAndType        #277:#10      // rawNotLiteralNonZeroDouble:()Ljava/lang/String;
  #279 = Methodref          #12.#278      // org/scalactic/Resources$.rawNotLiteralNonZeroDouble:()Ljava/lang/String;
  #280 = Utf8               notLiteralNonZeroDouble
  #281 = NameAndType        #280:#10      // notLiteralNonZeroDouble:()Ljava/lang/String;
  #282 = Methodref          #12.#281      // org/scalactic/Resources$.notLiteralNonZeroDouble:()Ljava/lang/String;
  #283 = Utf8               rawNotValidNonZeroDouble
  #284 = NameAndType        #283:#10      // rawNotValidNonZeroDouble:()Ljava/lang/String;
  #285 = Methodref          #12.#284      // org/scalactic/Resources$.rawNotValidNonZeroDouble:()Ljava/lang/String;
  #286 = Utf8               notValidNonZeroDouble
  #287 = NameAndType        #286:#10      // notValidNonZeroDouble:()Ljava/lang/String;
  #288 = Methodref          #12.#287      // org/scalactic/Resources$.notValidNonZeroDouble:()Ljava/lang/String;
  #289 = Utf8               rawNotLiteralNonZeroFloat
  #290 = NameAndType        #289:#10      // rawNotLiteralNonZeroFloat:()Ljava/lang/String;
  #291 = Methodref          #12.#290      // org/scalactic/Resources$.rawNotLiteralNonZeroFloat:()Ljava/lang/String;
  #292 = Utf8               notLiteralNonZeroFloat
  #293 = NameAndType        #292:#10      // notLiteralNonZeroFloat:()Ljava/lang/String;
  #294 = Methodref          #12.#293      // org/scalactic/Resources$.notLiteralNonZeroFloat:()Ljava/lang/String;
  #295 = Utf8               rawNotValidNonZeroFloat
  #296 = NameAndType        #295:#10      // rawNotValidNonZeroFloat:()Ljava/lang/String;
  #297 = Methodref          #12.#296      // org/scalactic/Resources$.rawNotValidNonZeroFloat:()Ljava/lang/String;
  #298 = Utf8               notValidNonZeroFloat
  #299 = NameAndType        #298:#10      // notValidNonZeroFloat:()Ljava/lang/String;
  #300 = Methodref          #12.#299      // org/scalactic/Resources$.notValidNonZeroFloat:()Ljava/lang/String;
  #301 = Utf8               rawNotLiteralNonZeroLong
  #302 = NameAndType        #301:#10      // rawNotLiteralNonZeroLong:()Ljava/lang/String;
  #303 = Methodref          #12.#302      // org/scalactic/Resources$.rawNotLiteralNonZeroLong:()Ljava/lang/String;
  #304 = Utf8               notLiteralNonZeroLong
  #305 = NameAndType        #304:#10      // notLiteralNonZeroLong:()Ljava/lang/String;
  #306 = Methodref          #12.#305      // org/scalactic/Resources$.notLiteralNonZeroLong:()Ljava/lang/String;
  #307 = Utf8               rawNotValidNonZeroLong
  #308 = NameAndType        #307:#10      // rawNotValidNonZeroLong:()Ljava/lang/String;
  #309 = Methodref          #12.#308      // org/scalactic/Resources$.rawNotValidNonZeroLong:()Ljava/lang/String;
  #310 = Utf8               notValidNonZeroLong
  #311 = NameAndType        #310:#10      // notValidNonZeroLong:()Ljava/lang/String;
  #312 = Methodref          #12.#311      // org/scalactic/Resources$.notValidNonZeroLong:()Ljava/lang/String;
  #313 = Utf8               rawNotLiteralNonZeroInt
  #314 = NameAndType        #313:#10      // rawNotLiteralNonZeroInt:()Ljava/lang/String;
  #315 = Methodref          #12.#314      // org/scalactic/Resources$.rawNotLiteralNonZeroInt:()Ljava/lang/String;
  #316 = Utf8               notLiteralNonZeroInt
  #317 = NameAndType        #316:#10      // notLiteralNonZeroInt:()Ljava/lang/String;
  #318 = Methodref          #12.#317      // org/scalactic/Resources$.notLiteralNonZeroInt:()Ljava/lang/String;
  #319 = Utf8               rawNotValidNonZeroInt
  #320 = NameAndType        #319:#10      // rawNotValidNonZeroInt:()Ljava/lang/String;
  #321 = Methodref          #12.#320      // org/scalactic/Resources$.rawNotValidNonZeroInt:()Ljava/lang/String;
  #322 = Utf8               notValidNonZeroInt
  #323 = NameAndType        #322:#10      // notValidNonZeroInt:()Ljava/lang/String;
  #324 = Methodref          #12.#323      // org/scalactic/Resources$.notValidNonZeroInt:()Ljava/lang/String;
  #325 = Utf8               rawPleaseDefineScalacticFillFilePathnameEnvVar
  #326 = NameAndType        #325:#10      // rawPleaseDefineScalacticFillFilePathnameEnvVar:()Ljava/lang/String;
  #327 = Methodref          #12.#326      // org/scalactic/Resources$.rawPleaseDefineScalacticFillFilePathnameEnvVar:()Ljava/lang/String;
  #328 = Utf8               pleaseDefineScalacticFillFilePathnameEnvVar
  #329 = NameAndType        #328:#10      // pleaseDefineScalacticFillFilePathnameEnvVar:()Ljava/lang/String;
  #330 = Methodref          #12.#329      // org/scalactic/Resources$.pleaseDefineScalacticFillFilePathnameEnvVar:()Ljava/lang/String;
  #331 = Utf8               rawNotLiteralPosZDouble
  #332 = NameAndType        #331:#10      // rawNotLiteralPosZDouble:()Ljava/lang/String;
  #333 = Methodref          #12.#332      // org/scalactic/Resources$.rawNotLiteralPosZDouble:()Ljava/lang/String;
  #334 = Utf8               notLiteralPosZDouble
  #335 = NameAndType        #334:#10      // notLiteralPosZDouble:()Ljava/lang/String;
  #336 = Methodref          #12.#335      // org/scalactic/Resources$.notLiteralPosZDouble:()Ljava/lang/String;
  #337 = Utf8               rawNotValidPosZDouble
  #338 = NameAndType        #337:#10      // rawNotValidPosZDouble:()Ljava/lang/String;
  #339 = Methodref          #12.#338      // org/scalactic/Resources$.rawNotValidPosZDouble:()Ljava/lang/String;
  #340 = Utf8               notValidPosZDouble
  #341 = NameAndType        #340:#10      // notValidPosZDouble:()Ljava/lang/String;
  #342 = Methodref          #12.#341      // org/scalactic/Resources$.notValidPosZDouble:()Ljava/lang/String;
  #343 = Utf8               rawNotLiteralPosZFloat
  #344 = NameAndType        #343:#10      // rawNotLiteralPosZFloat:()Ljava/lang/String;
  #345 = Methodref          #12.#344      // org/scalactic/Resources$.rawNotLiteralPosZFloat:()Ljava/lang/String;
  #346 = Utf8               notLiteralPosZFloat
  #347 = NameAndType        #346:#10      // notLiteralPosZFloat:()Ljava/lang/String;
  #348 = Methodref          #12.#347      // org/scalactic/Resources$.notLiteralPosZFloat:()Ljava/lang/String;
  #349 = Utf8               rawNotValidPosZFloat
  #350 = NameAndType        #349:#10      // rawNotValidPosZFloat:()Ljava/lang/String;
  #351 = Methodref          #12.#350      // org/scalactic/Resources$.rawNotValidPosZFloat:()Ljava/lang/String;
  #352 = Utf8               notValidPosZFloat
  #353 = NameAndType        #352:#10      // notValidPosZFloat:()Ljava/lang/String;
  #354 = Methodref          #12.#353      // org/scalactic/Resources$.notValidPosZFloat:()Ljava/lang/String;
  #355 = Utf8               rawNotLiteralPosZLong
  #356 = NameAndType        #355:#10      // rawNotLiteralPosZLong:()Ljava/lang/String;
  #357 = Methodref          #12.#356      // org/scalactic/Resources$.rawNotLiteralPosZLong:()Ljava/lang/String;
  #358 = Utf8               notLiteralPosZLong
  #359 = NameAndType        #358:#10      // notLiteralPosZLong:()Ljava/lang/String;
  #360 = Methodref          #12.#359      // org/scalactic/Resources$.notLiteralPosZLong:()Ljava/lang/String;
  #361 = Utf8               rawNotValidPosZLong
  #362 = NameAndType        #361:#10      // rawNotValidPosZLong:()Ljava/lang/String;
  #363 = Methodref          #12.#362      // org/scalactic/Resources$.rawNotValidPosZLong:()Ljava/lang/String;
  #364 = Utf8               notValidPosZLong
  #365 = NameAndType        #364:#10      // notValidPosZLong:()Ljava/lang/String;
  #366 = Methodref          #12.#365      // org/scalactic/Resources$.notValidPosZLong:()Ljava/lang/String;
  #367 = Utf8               rawNotLiteralPosZInt
  #368 = NameAndType        #367:#10      // rawNotLiteralPosZInt:()Ljava/lang/String;
  #369 = Methodref          #12.#368      // org/scalactic/Resources$.rawNotLiteralPosZInt:()Ljava/lang/String;
  #370 = Utf8               notLiteralPosZInt
  #371 = NameAndType        #370:#10      // notLiteralPosZInt:()Ljava/lang/String;
  #372 = Methodref          #12.#371      // org/scalactic/Resources$.notLiteralPosZInt:()Ljava/lang/String;
  #373 = Utf8               rawNotValidPosZInt
  #374 = NameAndType        #373:#10      // rawNotValidPosZInt:()Ljava/lang/String;
  #375 = Methodref          #12.#374      // org/scalactic/Resources$.rawNotValidPosZInt:()Ljava/lang/String;
  #376 = Utf8               notValidPosZInt
  #377 = NameAndType        #376:#10      // notValidPosZInt:()Ljava/lang/String;
  #378 = Methodref          #12.#377      // org/scalactic/Resources$.notValidPosZInt:()Ljava/lang/String;
  #379 = Utf8               rawNotLiteralPosDouble
  #380 = NameAndType        #379:#10      // rawNotLiteralPosDouble:()Ljava/lang/String;
  #381 = Methodref          #12.#380      // org/scalactic/Resources$.rawNotLiteralPosDouble:()Ljava/lang/String;
  #382 = Utf8               notLiteralPosDouble
  #383 = NameAndType        #382:#10      // notLiteralPosDouble:()Ljava/lang/String;
  #384 = Methodref          #12.#383      // org/scalactic/Resources$.notLiteralPosDouble:()Ljava/lang/String;
  #385 = Utf8               rawNotValidPosDouble
  #386 = NameAndType        #385:#10      // rawNotValidPosDouble:()Ljava/lang/String;
  #387 = Methodref          #12.#386      // org/scalactic/Resources$.rawNotValidPosDouble:()Ljava/lang/String;
  #388 = Utf8               notValidPosDouble
  #389 = NameAndType        #388:#10      // notValidPosDouble:()Ljava/lang/String;
  #390 = Methodref          #12.#389      // org/scalactic/Resources$.notValidPosDouble:()Ljava/lang/String;
  #391 = Utf8               rawNotLiteralPosFloat
  #392 = NameAndType        #391:#10      // rawNotLiteralPosFloat:()Ljava/lang/String;
  #393 = Methodref          #12.#392      // org/scalactic/Resources$.rawNotLiteralPosFloat:()Ljava/lang/String;
  #394 = Utf8               notLiteralPosFloat
  #395 = NameAndType        #394:#10      // notLiteralPosFloat:()Ljava/lang/String;
  #396 = Methodref          #12.#395      // org/scalactic/Resources$.notLiteralPosFloat:()Ljava/lang/String;
  #397 = Utf8               rawNotValidPosFloat
  #398 = NameAndType        #397:#10      // rawNotValidPosFloat:()Ljava/lang/String;
  #399 = Methodref          #12.#398      // org/scalactic/Resources$.rawNotValidPosFloat:()Ljava/lang/String;
  #400 = Utf8               notValidPosFloat
  #401 = NameAndType        #400:#10      // notValidPosFloat:()Ljava/lang/String;
  #402 = Methodref          #12.#401      // org/scalactic/Resources$.notValidPosFloat:()Ljava/lang/String;
  #403 = Utf8               rawNotLiteralPosLong
  #404 = NameAndType        #403:#10      // rawNotLiteralPosLong:()Ljava/lang/String;
  #405 = Methodref          #12.#404      // org/scalactic/Resources$.rawNotLiteralPosLong:()Ljava/lang/String;
  #406 = Utf8               notLiteralPosLong
  #407 = NameAndType        #406:#10      // notLiteralPosLong:()Ljava/lang/String;
  #408 = Methodref          #12.#407      // org/scalactic/Resources$.notLiteralPosLong:()Ljava/lang/String;
  #409 = Utf8               rawNotValidPosLong
  #410 = NameAndType        #409:#10      // rawNotValidPosLong:()Ljava/lang/String;
  #411 = Methodref          #12.#410      // org/scalactic/Resources$.rawNotValidPosLong:()Ljava/lang/String;
  #412 = Utf8               notValidPosLong
  #413 = NameAndType        #412:#10      // notValidPosLong:()Ljava/lang/String;
  #414 = Methodref          #12.#413      // org/scalactic/Resources$.notValidPosLong:()Ljava/lang/String;
  #415 = Utf8               rawNotLiteralPosInt
  #416 = NameAndType        #415:#10      // rawNotLiteralPosInt:()Ljava/lang/String;
  #417 = Methodref          #12.#416      // org/scalactic/Resources$.rawNotLiteralPosInt:()Ljava/lang/String;
  #418 = Utf8               notLiteralPosInt
  #419 = NameAndType        #418:#10      // notLiteralPosInt:()Ljava/lang/String;
  #420 = Methodref          #12.#419      // org/scalactic/Resources$.notLiteralPosInt:()Ljava/lang/String;
  #421 = Utf8               rawNotValidPosInt
  #422 = NameAndType        #421:#10      // rawNotValidPosInt:()Ljava/lang/String;
  #423 = Methodref          #12.#422      // org/scalactic/Resources$.rawNotValidPosInt:()Ljava/lang/String;
  #424 = Utf8               notValidPosInt
  #425 = NameAndType        #424:#10      // notValidPosInt:()Ljava/lang/String;
  #426 = Methodref          #12.#425      // org/scalactic/Resources$.notValidPosInt:()Ljava/lang/String;
  #427 = Utf8               rawVariableWasValue
  #428 = NameAndType        #427:#10      // rawVariableWasValue:()Ljava/lang/String;
  #429 = Methodref          #12.#428      // org/scalactic/Resources$.rawVariableWasValue:()Ljava/lang/String;
  #430 = Utf8               variableWasValue
  #431 = Utf8               (Ljava/lang/Object;Ljava/lang/Object;)Ljava/lang/String;
  #432 = Utf8               param1
  #433 = NameAndType        #430:#431     // variableWasValue:(Ljava/lang/Object;Ljava/lang/Object;)Ljava/lang/String;
  #434 = Methodref          #12.#433      // org/scalactic/Resources$.variableWasValue:(Ljava/lang/Object;Ljava/lang/Object;)Ljava/lang/String;
  #435 = Utf8               rawCommaAnd
  #436 = NameAndType        #435:#10      // rawCommaAnd:()Ljava/lang/String;
  #437 = Methodref          #12.#436      // org/scalactic/Resources$.rawCommaAnd:()Ljava/lang/String;
  #438 = Utf8               commaAnd
  #439 = NameAndType        #438:#431     // commaAnd:(Ljava/lang/Object;Ljava/lang/Object;)Ljava/lang/String;
  #440 = Methodref          #12.#439      // org/scalactic/Resources$.commaAnd:(Ljava/lang/Object;Ljava/lang/Object;)Ljava/lang/String;
  #441 = Utf8               rawCommaBut
  #442 = NameAndType        #441:#10      // rawCommaBut:()Ljava/lang/String;
  #443 = Methodref          #12.#442      // org/scalactic/Resources$.rawCommaBut:()Ljava/lang/String;
  #444 = Utf8               commaBut
  #445 = NameAndType        #444:#431     // commaBut:(Ljava/lang/Object;Ljava/lang/Object;)Ljava/lang/String;
  #446 = Methodref          #12.#445      // org/scalactic/Resources$.commaBut:(Ljava/lang/Object;Ljava/lang/Object;)Ljava/lang/String;
  #447 = Utf8               rawHadSize
  #448 = NameAndType        #447:#10      // rawHadSize:()Ljava/lang/String;
  #449 = Methodref          #12.#448      // org/scalactic/Resources$.rawHadSize:()Ljava/lang/String;
  #450 = Utf8               hadSize
  #451 = NameAndType        #450:#431     // hadSize:(Ljava/lang/Object;Ljava/lang/Object;)Ljava/lang/String;
  #452 = Methodref          #12.#451      // org/scalactic/Resources$.hadSize:(Ljava/lang/Object;Ljava/lang/Object;)Ljava/lang/String;
  #453 = Utf8               rawHadSizeInsteadOfExpectedSize
  #454 = NameAndType        #453:#10      // rawHadSizeInsteadOfExpectedSize:()Ljava/lang/String;
  #455 = Methodref          #12.#454      // org/scalactic/Resources$.rawHadSizeInsteadOfExpectedSize:()Ljava/lang/String;
  #456 = Utf8               hadSizeInsteadOfExpectedSize
  #457 = Utf8               (Ljava/lang/Object;Ljava/lang/Object;Ljava/lang/Object;)Ljava/lang/String;
  #458 = Utf8               param2
  #459 = NameAndType        #456:#457     // hadSizeInsteadOfExpectedSize:(Ljava/lang/Object;Ljava/lang/Object;Ljava/lang/Object;)Ljava/lang/String;
  #460 = Methodref          #12.#459      // org/scalactic/Resources$.hadSizeInsteadOfExpectedSize:(Ljava/lang/Object;Ljava/lang/Object;Ljava/lang/Object;)Ljava/lang/String;
  #461 = Utf8               rawHadLength
  #462 = NameAndType        #461:#10      // rawHadLength:()Ljava/lang/String;
  #463 = Methodref          #12.#462      // org/scalactic/Resources$.rawHadLength:()Ljava/lang/String;
  #464 = Utf8               hadLength
  #465 = NameAndType        #464:#431     // hadLength:(Ljava/lang/Object;Ljava/lang/Object;)Ljava/lang/String;
  #466 = Methodref          #12.#465      // org/scalactic/Resources$.hadLength:(Ljava/lang/Object;Ljava/lang/Object;)Ljava/lang/String;
  #467 = Utf8               rawHadLengthInsteadOfExpectedLength
  #468 = NameAndType        #467:#10      // rawHadLengthInsteadOfExpectedLength:()Ljava/lang/String;
  #469 = Methodref          #12.#468      // org/scalactic/Resources$.rawHadLengthInsteadOfExpectedLength:()Ljava/lang/String;
  #470 = Utf8               hadLengthInsteadOfExpectedLength
  #471 = NameAndType        #470:#457     // hadLengthInsteadOfExpectedLength:(Ljava/lang/Object;Ljava/lang/Object;Ljava/lang/Object;)Ljava/lang/String;
  #472 = Methodref          #12.#471      // org/scalactic/Resources$.hadLengthInsteadOfExpectedLength:(Ljava/lang/Object;Ljava/lang/Object;Ljava/lang/Object;)Ljava/lang/String;
  #473 = Utf8               rawWasInstanceOf
  #474 = NameAndType        #473:#10      // rawWasInstanceOf:()Ljava/lang/String;
  #475 = Methodref          #12.#474      // org/scalactic/Resources$.rawWasInstanceOf:()Ljava/lang/String;
  #476 = Utf8               wasInstanceOf
  #477 = NameAndType        #476:#431     // wasInstanceOf:(Ljava/lang/Object;Ljava/lang/Object;)Ljava/lang/String;
  #478 = Methodref          #12.#477      // org/scalactic/Resources$.wasInstanceOf:(Ljava/lang/Object;Ljava/lang/Object;)Ljava/lang/String;
  #479 = Utf8               rawWasNotInstanceOf
  #480 = NameAndType        #479:#10      // rawWasNotInstanceOf:()Ljava/lang/String;
  #481 = Methodref          #12.#480      // org/scalactic/Resources$.rawWasNotInstanceOf:()Ljava/lang/String;
  #482 = Utf8               wasNotInstanceOf
  #483 = NameAndType        #482:#431     // wasNotInstanceOf:(Ljava/lang/Object;Ljava/lang/Object;)Ljava/lang/String;
  #484 = Methodref          #12.#483      // org/scalactic/Resources$.wasNotInstanceOf:(Ljava/lang/Object;Ljava/lang/Object;)Ljava/lang/String;
  #485 = Utf8               rawWasEmpty
  #486 = NameAndType        #485:#10      // rawWasEmpty:()Ljava/lang/String;
  #487 = Methodref          #12.#486      // org/scalactic/Resources$.rawWasEmpty:()Ljava/lang/String;
  #488 = Utf8               wasEmpty
  #489 = NameAndType        #488:#20      // wasEmpty:(Ljava/lang/Object;)Ljava/lang/String;
  #490 = Methodref          #12.#489      // org/scalactic/Resources$.wasEmpty:(Ljava/lang/Object;)Ljava/lang/String;
  #491 = Utf8               rawWasNotEmpty
  #492 = NameAndType        #491:#10      // rawWasNotEmpty:()Ljava/lang/String;
  #493 = Methodref          #12.#492      // org/scalactic/Resources$.rawWasNotEmpty:()Ljava/lang/String;
  #494 = Utf8               wasNotEmpty
  #495 = NameAndType        #494:#20      // wasNotEmpty:(Ljava/lang/Object;)Ljava/lang/String;
  #496 = Methodref          #12.#495      // org/scalactic/Resources$.wasNotEmpty:(Ljava/lang/Object;)Ljava/lang/String;
  #497 = Utf8               rawWasNotTheSameInstanceAs
  #498 = NameAndType        #497:#10      // rawWasNotTheSameInstanceAs:()Ljava/lang/String;
  #499 = Methodref          #12.#498      // org/scalactic/Resources$.rawWasNotTheSameInstanceAs:()Ljava/lang/String;
  #500 = Utf8               wasNotTheSameInstanceAs
  #501 = NameAndType        #500:#431     // wasNotTheSameInstanceAs:(Ljava/lang/Object;Ljava/lang/Object;)Ljava/lang/String;
  #502 = Methodref          #12.#501      // org/scalactic/Resources$.wasNotTheSameInstanceAs:(Ljava/lang/Object;Ljava/lang/Object;)Ljava/lang/String;
  #503 = Utf8               rawWasTheSameInstanceAs
  #504 = NameAndType        #503:#10      // rawWasTheSameInstanceAs:()Ljava/lang/String;
  #505 = Methodref          #12.#504      // org/scalactic/Resources$.rawWasTheSameInstanceAs:()Ljava/lang/String;
  #506 = Utf8               wasTheSameInstanceAs
  #507 = NameAndType        #506:#431     // wasTheSameInstanceAs:(Ljava/lang/Object;Ljava/lang/Object;)Ljava/lang/String;
  #508 = Methodref          #12.#507      // org/scalactic/Resources$.wasTheSameInstanceAs:(Ljava/lang/Object;Ljava/lang/Object;)Ljava/lang/String;
  #509 = Utf8               rawContainedKey
  #510 = NameAndType        #509:#10      // rawContainedKey:()Ljava/lang/String;
  #511 = Methodref          #12.#510      // org/scalactic/Resources$.rawContainedKey:()Ljava/lang/String;
  #512 = Utf8               containedKey
  #513 = NameAndType        #512:#431     // containedKey:(Ljava/lang/Object;Ljava/lang/Object;)Ljava/lang/String;
  #514 = Methodref          #12.#513      // org/scalactic/Resources$.containedKey:(Ljava/lang/Object;Ljava/lang/Object;)Ljava/lang/String;
  #515 = Utf8               rawDidNotContainKey
  #516 = NameAndType        #515:#10      // rawDidNotContainKey:()Ljava/lang/String;
  #517 = Methodref          #12.#516      // org/scalactic/Resources$.rawDidNotContainKey:()Ljava/lang/String;
  #518 = Utf8               didNotContainKey
  #519 = NameAndType        #518:#431     // didNotContainKey:(Ljava/lang/Object;Ljava/lang/Object;)Ljava/lang/String;
  #520 = Methodref          #12.#519      // org/scalactic/Resources$.didNotContainKey:(Ljava/lang/Object;Ljava/lang/Object;)Ljava/lang/String;
  #521 = Utf8               rawContained
  #522 = NameAndType        #521:#10      // rawContained:()Ljava/lang/String;
  #523 = Methodref          #12.#522      // org/scalactic/Resources$.rawContained:()Ljava/lang/String;
  #524 = Utf8               contained
  #525 = NameAndType        #524:#431     // contained:(Ljava/lang/Object;Ljava/lang/Object;)Ljava/lang/String;
  #526 = Methodref          #12.#525      // org/scalactic/Resources$.contained:(Ljava/lang/Object;Ljava/lang/Object;)Ljava/lang/String;
  #527 = Utf8               rawDidNotContain
  #528 = NameAndType        #527:#10      // rawDidNotContain:()Ljava/lang/String;
  #529 = Methodref          #12.#528      // org/scalactic/Resources$.rawDidNotContain:()Ljava/lang/String;
  #530 = Utf8               didNotContain
  #531 = NameAndType        #530:#431     // didNotContain:(Ljava/lang/Object;Ljava/lang/Object;)Ljava/lang/String;
  #532 = Methodref          #12.#531      // org/scalactic/Resources$.didNotContain:(Ljava/lang/Object;Ljava/lang/Object;)Ljava/lang/String;
  #533 = Utf8               rawEndedWith
  #534 = NameAndType        #533:#10      // rawEndedWith:()Ljava/lang/String;
  #535 = Methodref          #12.#534      // org/scalactic/Resources$.rawEndedWith:()Ljava/lang/String;
  #536 = Utf8               endedWith
  #537 = NameAndType        #536:#431     // endedWith:(Ljava/lang/Object;Ljava/lang/Object;)Ljava/lang/String;
  #538 = Methodref          #12.#537      // org/scalactic/Resources$.endedWith:(Ljava/lang/Object;Ljava/lang/Object;)Ljava/lang/String;
  #539 = Utf8               rawDidNotEndWith
  #540 = NameAndType        #539:#10      // rawDidNotEndWith:()Ljava/lang/String;
  #541 = Methodref          #12.#540      // org/scalactic/Resources$.rawDidNotEndWith:()Ljava/lang/String;
  #542 = Utf8               didNotEndWith
  #543 = NameAndType        #542:#431     // didNotEndWith:(Ljava/lang/Object;Ljava/lang/Object;)Ljava/lang/String;
  #544 = Methodref          #12.#543      // org/scalactic/Resources$.didNotEndWith:(Ljava/lang/Object;Ljava/lang/Object;)Ljava/lang/String;
  #545 = Utf8               rawStartedWith
  #546 = NameAndType        #545:#10      // rawStartedWith:()Ljava/lang/String;
  #547 = Methodref          #12.#546      // org/scalactic/Resources$.rawStartedWith:()Ljava/lang/String;
  #548 = Utf8               startedWith
  #549 = NameAndType        #548:#431     // startedWith:(Ljava/lang/Object;Ljava/lang/Object;)Ljava/lang/String;
  #550 = Methodref          #12.#549      // org/scalactic/Resources$.startedWith:(Ljava/lang/Object;Ljava/lang/Object;)Ljava/lang/String;
  #551 = Utf8               rawDidNotStartWith
  #552 = NameAndType        #551:#10      // rawDidNotStartWith:()Ljava/lang/String;
  #553 = Methodref          #12.#552      // org/scalactic/Resources$.rawDidNotStartWith:()Ljava/lang/String;
  #554 = Utf8               didNotStartWith
  #555 = NameAndType        #554:#431     // didNotStartWith:(Ljava/lang/Object;Ljava/lang/Object;)Ljava/lang/String;
  #556 = Methodref          #12.#555      // org/scalactic/Resources$.didNotStartWith:(Ljava/lang/Object;Ljava/lang/Object;)Ljava/lang/String;
  #557 = Utf8               rawWasNotGreaterThanOrEqualTo
  #558 = NameAndType        #557:#10      // rawWasNotGreaterThanOrEqualTo:()Ljava/lang/String;
  #559 = Methodref          #12.#558      // org/scalactic/Resources$.rawWasNotGreaterThanOrEqualTo:()Ljava/lang/String;
  #560 = Utf8               wasNotGreaterThanOrEqualTo
  #561 = NameAndType        #560:#431     // wasNotGreaterThanOrEqualTo:(Ljava/lang/Object;Ljava/lang/Object;)Ljava/lang/String;
  #562 = Methodref          #12.#561      // org/scalactic/Resources$.wasNotGreaterThanOrEqualTo:(Ljava/lang/Object;Ljava/lang/Object;)Ljava/lang/String;
  #563 = Utf8               rawWasGreaterThanOrEqualTo
  #564 = NameAndType        #563:#10      // rawWasGreaterThanOrEqualTo:()Ljava/lang/String;
  #565 = Methodref          #12.#564      // org/scalactic/Resources$.rawWasGreaterThanOrEqualTo:()Ljava/lang/String;
  #566 = Utf8               wasGreaterThanOrEqualTo
  #567 = NameAndType        #566:#431     // wasGreaterThanOrEqualTo:(Ljava/lang/Object;Ljava/lang/Object;)Ljava/lang/String;
  #568 = Methodref          #12.#567      // org/scalactic/Resources$.wasGreaterThanOrEqualTo:(Ljava/lang/Object;Ljava/lang/Object;)Ljava/lang/String;
  #569 = Utf8               rawWasNotLessThanOrEqualTo
  #570 = NameAndType        #569:#10      // rawWasNotLessThanOrEqualTo:()Ljava/lang/String;
  #571 = Methodref          #12.#570      // org/scalactic/Resources$.rawWasNotLessThanOrEqualTo:()Ljava/lang/String;
  #572 = Utf8               wasNotLessThanOrEqualTo
  #573 = NameAndType        #572:#431     // wasNotLessThanOrEqualTo:(Ljava/lang/Object;Ljava/lang/Object;)Ljava/lang/String;
  #574 = Methodref          #12.#573      // org/scalactic/Resources$.wasNotLessThanOrEqualTo:(Ljava/lang/Object;Ljava/lang/Object;)Ljava/lang/String;
  #575 = Utf8               rawWasLessThanOrEqualTo
  #576 = NameAndType        #575:#10      // rawWasLessThanOrEqualTo:()Ljava/lang/String;
  #577 = Methodref          #12.#576      // org/scalactic/Resources$.rawWasLessThanOrEqualTo:()Ljava/lang/String;
  #578 = Utf8               wasLessThanOrEqualTo
  #579 = NameAndType        #578:#431     // wasLessThanOrEqualTo:(Ljava/lang/Object;Ljava/lang/Object;)Ljava/lang/String;
  #580 = Methodref          #12.#579      // org/scalactic/Resources$.wasLessThanOrEqualTo:(Ljava/lang/Object;Ljava/lang/Object;)Ljava/lang/String;
  #581 = Utf8               rawWasNotGreaterThan
  #582 = NameAndType        #581:#10      // rawWasNotGreaterThan:()Ljava/lang/String;
  #583 = Methodref          #12.#582      // org/scalactic/Resources$.rawWasNotGreaterThan:()Ljava/lang/String;
  #584 = Utf8               wasNotGreaterThan
  #585 = NameAndType        #584:#431     // wasNotGreaterThan:(Ljava/lang/Object;Ljava/lang/Object;)Ljava/lang/String;
  #586 = Methodref          #12.#585      // org/scalactic/Resources$.wasNotGreaterThan:(Ljava/lang/Object;Ljava/lang/Object;)Ljava/lang/String;
  #587 = Utf8               rawWasGreaterThan
  #588 = NameAndType        #587:#10      // rawWasGreaterThan:()Ljava/lang/String;
  #589 = Methodref          #12.#588      // org/scalactic/Resources$.rawWasGreaterThan:()Ljava/lang/String;
  #590 = Utf8               wasGreaterThan
  #591 = NameAndType        #590:#431     // wasGreaterThan:(Ljava/lang/Object;Ljava/lang/Object;)Ljava/lang/String;
  #592 = Methodref          #12.#591      // org/scalactic/Resources$.wasGreaterThan:(Ljava/lang/Object;Ljava/lang/Object;)Ljava/lang/String;
  #593 = Utf8               rawWasNotLessThan
  #594 = NameAndType        #593:#10      // rawWasNotLessThan:()Ljava/lang/String;
  #595 = Methodref          #12.#594      // org/scalactic/Resources$.rawWasNotLessThan:()Ljava/lang/String;
  #596 = Utf8               wasNotLessThan
  #597 = NameAndType        #596:#431     // wasNotLessThan:(Ljava/lang/Object;Ljava/lang/Object;)Ljava/lang/String;
  #598 = Methodref          #12.#597      // org/scalactic/Resources$.wasNotLessThan:(Ljava/lang/Object;Ljava/lang/Object;)Ljava/lang/String;
  #599 = Utf8               rawWasLessThan
  #600 = NameAndType        #599:#10      // rawWasLessThan:()Ljava/lang/String;
  #601 = Methodref          #12.#600      // org/scalactic/Resources$.rawWasLessThan:()Ljava/lang/String;
  #602 = Utf8               wasLessThan
  #603 = NameAndType        #602:#431     // wasLessThan:(Ljava/lang/Object;Ljava/lang/Object;)Ljava/lang/String;
  #604 = Methodref          #12.#603      // org/scalactic/Resources$.wasLessThan:(Ljava/lang/Object;Ljava/lang/Object;)Ljava/lang/String;
  #605 = Utf8               rawWasFalse
  #606 = NameAndType        #605:#10      // rawWasFalse:()Ljava/lang/String;
  #607 = Methodref          #12.#606      // org/scalactic/Resources$.rawWasFalse:()Ljava/lang/String;
  #608 = Utf8               wasFalse
  #609 = NameAndType        #608:#20      // wasFalse:(Ljava/lang/Object;)Ljava/lang/String;
  #610 = Methodref          #12.#609      // org/scalactic/Resources$.wasFalse:(Ljava/lang/Object;)Ljava/lang/String;
  #611 = Utf8               rawWasTrue
  #612 = NameAndType        #611:#10      // rawWasTrue:()Ljava/lang/String;
  #613 = Methodref          #12.#612      // org/scalactic/Resources$.rawWasTrue:()Ljava/lang/String;
  #614 = Utf8               wasTrue
  #615 = NameAndType        #614:#20      // wasTrue:(Ljava/lang/Object;)Ljava/lang/String;
  #616 = Methodref          #12.#615      // org/scalactic/Resources$.wasTrue:(Ljava/lang/Object;)Ljava/lang/String;
  #617 = Utf8               rawAnd
  #618 = NameAndType        #617:#10      // rawAnd:()Ljava/lang/String;
  #619 = Methodref          #12.#618      // org/scalactic/Resources$.rawAnd:()Ljava/lang/String;
  #620 = Utf8               and
  #621 = NameAndType        #620:#431     // and:(Ljava/lang/Object;Ljava/lang/Object;)Ljava/lang/String;
  #622 = Methodref          #12.#621      // org/scalactic/Resources$.and:(Ljava/lang/Object;Ljava/lang/Object;)Ljava/lang/String;
  #623 = Utf8               rawComma
  #624 = NameAndType        #623:#10      // rawComma:()Ljava/lang/String;
  #625 = Methodref          #12.#624      // org/scalactic/Resources$.rawComma:()Ljava/lang/String;
  #626 = Utf8               comma
  #627 = NameAndType        #626:#10      // comma:()Ljava/lang/String;
  #628 = Methodref          #12.#627      // org/scalactic/Resources$.comma:()Ljava/lang/String;
  #629 = Utf8               rawWereNull
  #630 = NameAndType        #629:#10      // rawWereNull:()Ljava/lang/String;
  #631 = Methodref          #12.#630      // org/scalactic/Resources$.rawWereNull:()Ljava/lang/String;
  #632 = Utf8               wereNull
  #633 = NameAndType        #632:#20      // wereNull:(Ljava/lang/Object;)Ljava/lang/String;
  #634 = Methodref          #12.#633      // org/scalactic/Resources$.wereNull:(Ljava/lang/Object;)Ljava/lang/String;
  #635 = Utf8               rawWasNull
  #636 = NameAndType        #635:#10      // rawWasNull:()Ljava/lang/String;
  #637 = Methodref          #12.#636      // org/scalactic/Resources$.rawWasNull:()Ljava/lang/String;
  #638 = Utf8               wasNull
  #639 = NameAndType        #638:#20      // wasNull:(Ljava/lang/Object;)Ljava/lang/String;
  #640 = Methodref          #12.#639      // org/scalactic/Resources$.wasNull:(Ljava/lang/Object;)Ljava/lang/String;
  #641 = Utf8               rawExpressionWasTrue
  #642 = NameAndType        #641:#10      // rawExpressionWasTrue:()Ljava/lang/String;
  #643 = Methodref          #12.#642      // org/scalactic/Resources$.rawExpressionWasTrue:()Ljava/lang/String;
  #644 = Utf8               expressionWasTrue
  #645 = NameAndType        #644:#10      // expressionWasTrue:()Ljava/lang/String;
  #646 = Methodref          #12.#645      // org/scalactic/Resources$.expressionWasTrue:()Ljava/lang/String;
  #647 = Utf8               rawExpressionWasFalse
  #648 = NameAndType        #647:#10      // rawExpressionWasFalse:()Ljava/lang/String;
  #649 = Methodref          #12.#648      // org/scalactic/Resources$.rawExpressionWasFalse:()Ljava/lang/String;
  #650 = Utf8               expressionWasFalse
  #651 = NameAndType        #650:#10      // expressionWasFalse:()Ljava/lang/String;
  #652 = Methodref          #12.#651      // org/scalactic/Resources$.expressionWasFalse:()Ljava/lang/String;
  #653 = Utf8               rawWasNotPlusOrMinus
  #654 = NameAndType        #653:#10      // rawWasNotPlusOrMinus:()Ljava/lang/String;
  #655 = Methodref          #12.#654      // org/scalactic/Resources$.rawWasNotPlusOrMinus:()Ljava/lang/String;
  #656 = Utf8               wasNotPlusOrMinus
  #657 = NameAndType        #656:#457     // wasNotPlusOrMinus:(Ljava/lang/Object;Ljava/lang/Object;Ljava/lang/Object;)Ljava/lang/String;
  #658 = Methodref          #12.#657      // org/scalactic/Resources$.wasNotPlusOrMinus:(Ljava/lang/Object;Ljava/lang/Object;Ljava/lang/Object;)Ljava/lang/String;
  #659 = Utf8               rawWasPlusOrMinus
  #660 = NameAndType        #659:#10      // rawWasPlusOrMinus:()Ljava/lang/String;
  #661 = Methodref          #12.#660      // org/scalactic/Resources$.rawWasPlusOrMinus:()Ljava/lang/String;
  #662 = Utf8               wasPlusOrMinus
  #663 = NameAndType        #662:#457     // wasPlusOrMinus:(Ljava/lang/Object;Ljava/lang/Object;Ljava/lang/Object;)Ljava/lang/String;
  #664 = Methodref          #12.#663      // org/scalactic/Resources$.wasPlusOrMinus:(Ljava/lang/Object;Ljava/lang/Object;Ljava/lang/Object;)Ljava/lang/String;
  #665 = Utf8               rawEqualed
  #666 = NameAndType        #665:#10      // rawEqualed:()Ljava/lang/String;
  #667 = Methodref          #12.#666      // org/scalactic/Resources$.rawEqualed:()Ljava/lang/String;
  #668 = Utf8               equaled
  #669 = NameAndType        #668:#431     // equaled:(Ljava/lang/Object;Ljava/lang/Object;)Ljava/lang/String;
  #670 = Methodref          #12.#669      // org/scalactic/Resources$.equaled:(Ljava/lang/Object;Ljava/lang/Object;)Ljava/lang/String;
  #671 = Utf8               rawDidNotEqual
  #672 = NameAndType        #671:#10      // rawDidNotEqual:()Ljava/lang/String;
  #673 = Methodref          #12.#672      // org/scalactic/Resources$.rawDidNotEqual:()Ljava/lang/String;
  #674 = Utf8               didNotEqual
  #675 = NameAndType        #674:#431     // didNotEqual:(Ljava/lang/Object;Ljava/lang/Object;)Ljava/lang/String;
  #676 = Methodref          #12.#675      // org/scalactic/Resources$.didNotEqual:(Ljava/lang/Object;Ljava/lang/Object;)Ljava/lang/String;
  #677 = Utf8               rawBigProblemsWithMessage
  #678 = NameAndType        #677:#10      // rawBigProblemsWithMessage:()Ljava/lang/String;
  #679 = Methodref          #12.#678      // org/scalactic/Resources$.rawBigProblemsWithMessage:()Ljava/lang/String;
  #680 = Utf8               bigProblemsWithMessage
  #681 = NameAndType        #680:#20      // bigProblemsWithMessage:(Ljava/lang/Object;)Ljava/lang/String;
  #682 = Methodref          #12.#681      // org/scalactic/Resources$.bigProblemsWithMessage:(Ljava/lang/Object;)Ljava/lang/String;
  #683 = Utf8               rawBigProblems
  #684 = NameAndType        #683:#10      // rawBigProblems:()Ljava/lang/String;
  #685 = Methodref          #12.#684      // org/scalactic/Resources$.rawBigProblems:()Ljava/lang/String;
  #686 = Utf8               bigProblems
  #687 = NameAndType        #686:#10      // bigProblems:()Ljava/lang/String;
  #688 = Methodref          #12.#687      // org/scalactic/Resources$.bigProblems:()Ljava/lang/String;
  #689 = Utf8               formatString
  #690 = Utf8               (Ljava/lang/String;[Ljava/lang/Object;)Ljava/lang/String;
  #691 = Utf8               rawString
  #692 = Utf8               args
  #693 = NameAndType        #689:#690     // formatString:(Ljava/lang/String;[Ljava/lang/Object;)Ljava/lang/String;
  #694 = Methodref          #12.#693      // org/scalactic/Resources$.formatString:(Ljava/lang/String;[Ljava/lang/Object;)Ljava/lang/String;
  #695 = Utf8               Ljava/lang/String;
  #696 = Utf8               [Ljava/lang/Object;
  #697 = Utf8               resourceBundle
  #698 = Utf8               ()Ljava/util/ResourceBundle;
  #699 = NameAndType        #697:#698     // resourceBundle:()Ljava/util/ResourceBundle;
  #700 = Methodref          #12.#699      // org/scalactic/Resources$.resourceBundle:()Ljava/util/ResourceBundle;
  #701 = Utf8               Code
  #702 = Utf8               LocalVariableTable
  #703 = Utf8               MethodParameters
  #704 = Utf8               SourceFile
  #705 = Utf8               RuntimeVisibleAnnotations
  #706 = Utf8               ScalaSig
{
  public static java.lang.String rawInvalidSize();
    descriptor: ()Ljava/lang/String;
    flags: (0x0009) ACC_PUBLIC, ACC_STATIC
    Code:
      stack=1, locals=0, args_size=0
         0: getstatic     #16                 // Field org/scalactic/Resources$.MODULE$:Lorg/scalactic/Resources$;
         3: invokevirtual #18                 // Method org/scalactic/Resources$.rawInvalidSize:()Ljava/lang/String;
         6: areturn

  public static java.lang.String invalidSize(java.lang.Object);
    descriptor: (Ljava/lang/Object;)Ljava/lang/String;
    flags: (0x0009) ACC_PUBLIC, ACC_STATIC
    Code:
      stack=2, locals=1, args_size=1
         0: getstatic     #16                 // Field org/scalactic/Resources$.MODULE$:Lorg/scalactic/Resources$;
         3: aload_0
         4: invokevirtual #23                 // Method org/scalactic/Resources$.invalidSize:(Ljava/lang/Object;)Ljava/lang/String;
         7: areturn
      LocalVariableTable:
        Start  Length  Slot  Name   Signature
            0       8     0 param0   Ljava/lang/Object;
    MethodParameters:
      Name                           Flags
      param0                         final

  public static java.lang.String rawNotLiteralNumericChar();
    descriptor: ()Ljava/lang/String;
    flags: (0x0009) ACC_PUBLIC, ACC_STATIC
    Code:
      stack=1, locals=0, args_size=0
         0: getstatic     #16                 // Field org/scalactic/Resources$.MODULE$:Lorg/scalactic/Resources$;
         3: invokevirtual #27                 // Method org/scalactic/Resources$.rawNotLiteralNumericChar:()Ljava/lang/String;
         6: areturn

  public static java.lang.String notLiteralNumericChar();
    descriptor: ()Ljava/lang/String;
    flags: (0x0009) ACC_PUBLIC, ACC_STATIC
    Code:
      stack=1, locals=0, args_size=0
         0: getstatic     #16                 // Field org/scalactic/Resources$.MODULE$:Lorg/scalactic/Resources$;
         3: invokevirtual #30                 // Method org/scalactic/Resources$.notLiteralNumericChar:()Ljava/lang/String;
         6: areturn

  public static java.lang.String rawNotValidNumericChar();
    descriptor: ()Ljava/lang/String;
    flags: (0x0009) ACC_PUBLIC, ACC_STATIC
    Code:
      stack=1, locals=0, args_size=0
         0: getstatic     #16                 // Field org/scalactic/Resources$.MODULE$:Lorg/scalactic/Resources$;
         3: invokevirtual #33                 // Method org/scalactic/Resources$.rawNotValidNumericChar:()Ljava/lang/String;
         6: areturn

  public static java.lang.String notValidNumericChar();
    descriptor: ()Ljava/lang/String;
    flags: (0x0009) ACC_PUBLIC, ACC_STATIC
    Code:
      stack=1, locals=0, args_size=0
         0: getstatic     #16                 // Field org/scalactic/Resources$.MODULE$:Lorg/scalactic/Resources$;
         3: invokevirtual #36                 // Method org/scalactic/Resources$.notValidNumericChar:()Ljava/lang/String;
         6: areturn

  public static java.lang.String rawNotLiteralFiniteDouble();
    descriptor: ()Ljava/lang/String;
    flags: (0x0009) ACC_PUBLIC, ACC_STATIC
    Code:
      stack=1, locals=0, args_size=0
         0: getstatic     #16                 // Field org/scalactic/Resources$.MODULE$:Lorg/scalactic/Resources$;
         3: invokevirtual #39                 // Method org/scalactic/Resources$.rawNotLiteralFiniteDouble:()Ljava/lang/String;
         6: areturn

  public static java.lang.String notLiteralFiniteDouble();
    descriptor: ()Ljava/lang/String;
    flags: (0x0009) ACC_PUBLIC, ACC_STATIC
    Code:
      stack=1, locals=0, args_size=0
         0: getstatic     #16                 // Field org/scalactic/Resources$.MODULE$:Lorg/scalactic/Resources$;
         3: invokevirtual #42                 // Method org/scalactic/Resources$.notLiteralFiniteDouble:()Ljava/lang/String;
         6: areturn

  public static java.lang.String rawNotValidFiniteDouble();
    descriptor: ()Ljava/lang/String;
    flags: (0x0009) ACC_PUBLIC, ACC_STATIC
    Code:
      stack=1, locals=0, args_size=0
         0: getstatic     #16                 // Field org/scalactic/Resources$.MODULE$:Lorg/scalactic/Resources$;
         3: invokevirtual #45                 // Method org/scalactic/Resources$.rawNotValidFiniteDouble:()Ljava/lang/String;
         6: areturn

  public static java.lang.String notValidFiniteDouble();
    descriptor: ()Ljava/lang/String;
    flags: (0x0009) ACC_PUBLIC, ACC_STATIC
    Code:
      stack=1, locals=0, args_size=0
         0: getstatic     #16                 // Field org/scalactic/Resources$.MODULE$:Lorg/scalactic/Resources$;
         3: invokevirtual #48                 // Method org/scalactic/Resources$.notValidFiniteDouble:()Ljava/lang/String;
         6: areturn

  public static java.lang.String rawNotLiteralFiniteFloat();
    descriptor: ()Ljava/lang/String;
    flags: (0x0009) ACC_PUBLIC, ACC_STATIC
    Code:
      stack=1, locals=0, args_size=0
         0: getstatic     #16                 // Field org/scalactic/Resources$.MODULE$:Lorg/scalactic/Resources$;
         3: invokevirtual #51                 // Method org/scalactic/Resources$.rawNotLiteralFiniteFloat:()Ljava/lang/String;
         6: areturn

  public static java.lang.String notLiteralFiniteFloat();
    descriptor: ()Ljava/lang/String;
    flags: (0x0009) ACC_PUBLIC, ACC_STATIC
    Code:
      stack=1, locals=0, args_size=0
         0: getstatic     #16                 // Field org/scalactic/Resources$.MODULE$:Lorg/scalactic/Resources$;
         3: invokevirtual #54                 // Method org/scalactic/Resources$.notLiteralFiniteFloat:()Ljava/lang/String;
         6: areturn

  public static java.lang.String rawNotValidFiniteFloat();
    descriptor: ()Ljava/lang/String;
    flags: (0x0009) ACC_PUBLIC, ACC_STATIC
    Code:
      stack=1, locals=0, args_size=0
         0: getstatic     #16                 // Field org/scalactic/Resources$.MODULE$:Lorg/scalactic/Resources$;
         3: invokevirtual #57                 // Method org/scalactic/Resources$.rawNotValidFiniteFloat:()Ljava/lang/String;
         6: areturn

  public static java.lang.String notValidFiniteFloat();
    descriptor: ()Ljava/lang/String;
    flags: (0x0009) ACC_PUBLIC, ACC_STATIC
    Code:
      stack=1, locals=0, args_size=0
         0: getstatic     #16                 // Field org/scalactic/Resources$.MODULE$:Lorg/scalactic/Resources$;
         3: invokevirtual #60                 // Method org/scalactic/Resources$.notValidFiniteFloat:()Ljava/lang/String;
         6: areturn

  public static java.lang.String rawNotLiteralNonZeroFiniteDouble();
    descriptor: ()Ljava/lang/String;
    flags: (0x0009) ACC_PUBLIC, ACC_STATIC
    Code:
      stack=1, locals=0, args_size=0
         0: getstatic     #16                 // Field org/scalactic/Resources$.MODULE$:Lorg/scalactic/Resources$;
         3: invokevirtual #63                 // Method org/scalactic/Resources$.rawNotLiteralNonZeroFiniteDouble:()Ljava/lang/String;
         6: areturn

  public static java.lang.String notLiteralNonZeroFiniteDouble();
    descriptor: ()Ljava/lang/String;
    flags: (0x0009) ACC_PUBLIC, ACC_STATIC
    Code:
      stack=1, locals=0, args_size=0
         0: getstatic     #16                 // Field org/scalactic/Resources$.MODULE$:Lorg/scalactic/Resources$;
         3: invokevirtual #66                 // Method org/scalactic/Resources$.notLiteralNonZeroFiniteDouble:()Ljava/lang/String;
         6: areturn

  public static java.lang.String rawNotValidNonZeroFiniteDouble();
    descriptor: ()Ljava/lang/String;
    flags: (0x0009) ACC_PUBLIC, ACC_STATIC
    Code:
      stack=1, locals=0, args_size=0
         0: getstatic     #16                 // Field org/scalactic/Resources$.MODULE$:Lorg/scalactic/Resources$;
         3: invokevirtual #69                 // Method org/scalactic/Resources$.rawNotValidNonZeroFiniteDouble:()Ljava/lang/String;
         6: areturn

  public static java.lang.String notValidNonZeroFiniteDouble();
    descriptor: ()Ljava/lang/String;
    flags: (0x0009) ACC_PUBLIC, ACC_STATIC
    Code:
      stack=1, locals=0, args_size=0
         0: getstatic     #16                 // Field org/scalactic/Resources$.MODULE$:Lorg/scalactic/Resources$;
         3: invokevirtual #72                 // Method org/scalactic/Resources$.notValidNonZeroFiniteDouble:()Ljava/lang/String;
         6: areturn

  public static java.lang.String rawNotLiteralNonZeroFiniteFloat();
    descriptor: ()Ljava/lang/String;
    flags: (0x0009) ACC_PUBLIC, ACC_STATIC
    Code:
      stack=1, locals=0, args_size=0
         0: getstatic     #16                 // Field org/scalactic/Resources$.MODULE$:Lorg/scalactic/Resources$;
         3: invokevirtual #75                 // Method org/scalactic/Resources$.rawNotLiteralNonZeroFiniteFloat:()Ljava/lang/String;
         6: areturn

  public static java.lang.String notLiteralNonZeroFiniteFloat();
    descriptor: ()Ljava/lang/String;
    flags: (0x0009) ACC_PUBLIC, ACC_STATIC
    Code:
      stack=1, locals=0, args_size=0
         0: getstatic     #16                 // Field org/scalactic/Resources$.MODULE$:Lorg/scalactic/Resources$;
         3: invokevirtual #78                 // Method org/scalactic/Resources$.notLiteralNonZeroFiniteFloat:()Ljava/lang/String;
         6: areturn

  public static java.lang.String rawNotValidNonZeroFiniteFloat();
    descriptor: ()Ljava/lang/String;
    flags: (0x0009) ACC_PUBLIC, ACC_STATIC
    Code:
      stack=1, locals=0, args_size=0
         0: getstatic     #16                 // Field org/scalactic/Resources$.MODULE$:Lorg/scalactic/Resources$;
         3: invokevirtual #81                 // Method org/scalactic/Resources$.rawNotValidNonZeroFiniteFloat:()Ljava/lang/String;
         6: areturn

  public static java.lang.String notValidNonZeroFiniteFloat();
    descriptor: ()Ljava/lang/String;
    flags: (0x0009) ACC_PUBLIC, ACC_STATIC
    Code:
      stack=1, locals=0, args_size=0
         0: getstatic     #16                 // Field org/scalactic/Resources$.MODULE$:Lorg/scalactic/Resources$;
         3: invokevirtual #84                 // Method org/scalactic/Resources$.notValidNonZeroFiniteFloat:()Ljava/lang/String;
         6: areturn

  public static java.lang.String rawNotLiteralNegZFiniteDouble();
    descriptor: ()Ljava/lang/String;
    flags: (0x0009) ACC_PUBLIC, ACC_STATIC
    Code:
      stack=1, locals=0, args_size=0
         0: getstatic     #16                 // Field org/scalactic/Resources$.MODULE$:Lorg/scalactic/Resources$;
         3: invokevirtual #87                 // Method org/scalactic/Resources$.rawNotLiteralNegZFiniteDouble:()Ljava/lang/String;
         6: areturn

  public static java.lang.String notLiteralNegZFiniteDouble();
    descriptor: ()Ljava/lang/String;
    flags: (0x0009) ACC_PUBLIC, ACC_STATIC
    Code:
      stack=1, locals=0, args_size=0
         0: getstatic     #16                 // Field org/scalactic/Resources$.MODULE$:Lorg/scalactic/Resources$;
         3: invokevirtual #90                 // Method org/scalactic/Resources$.notLiteralNegZFiniteDouble:()Ljava/lang/String;
         6: areturn

  public static java.lang.String rawNotValidNegZFiniteDouble();
    descriptor: ()Ljava/lang/String;
    flags: (0x0009) ACC_PUBLIC, ACC_STATIC
    Code:
      stack=1, locals=0, args_size=0
         0: getstatic     #16                 // Field org/scalactic/Resources$.MODULE$:Lorg/scalactic/Resources$;
         3: invokevirtual #93                 // Method org/scalactic/Resources$.rawNotValidNegZFiniteDouble:()Ljava/lang/String;
         6: areturn

  public static java.lang.String notValidNegZFiniteDouble();
    descriptor: ()Ljava/lang/String;
    flags: (0x0009) ACC_PUBLIC, ACC_STATIC
    Code:
      stack=1, locals=0, args_size=0
         0: getstatic     #16                 // Field org/scalactic/Resources$.MODULE$:Lorg/scalactic/Resources$;
         3: invokevirtual #96                 // Method org/scalactic/Resources$.notValidNegZFiniteDouble:()Ljava/lang/String;
         6: areturn

  public static java.lang.String rawNotLiteralNegZFiniteFloat();
    descriptor: ()Ljava/lang/String;
    flags: (0x0009) ACC_PUBLIC, ACC_STATIC
    Code:
      stack=1, locals=0, args_size=0
         0: getstatic     #16                 // Field org/scalactic/Resources$.MODULE$:Lorg/scalactic/Resources$;
         3: invokevirtual #99                 // Method org/scalactic/Resources$.rawNotLiteralNegZFiniteFloat:()Ljava/lang/String;
         6: areturn

  public static java.lang.String notLiteralNegZFiniteFloat();
    descriptor: ()Ljava/lang/String;
    flags: (0x0009) ACC_PUBLIC, ACC_STATIC
    Code:
      stack=1, locals=0, args_size=0
         0: getstatic     #16                 // Field org/scalactic/Resources$.MODULE$:Lorg/scalactic/Resources$;
         3: invokevirtual #102                // Method org/scalactic/Resources$.notLiteralNegZFiniteFloat:()Ljava/lang/String;
         6: areturn

  public static java.lang.String rawNotValidNegZFiniteFloat();
    descriptor: ()Ljava/lang/String;
    flags: (0x0009) ACC_PUBLIC, ACC_STATIC
    Code:
      stack=1, locals=0, args_size=0
         0: getstatic     #16                 // Field org/scalactic/Resources$.MODULE$:Lorg/scalactic/Resources$;
         3: invokevirtual #105                // Method org/scalactic/Resources$.rawNotValidNegZFiniteFloat:()Ljava/lang/String;
         6: areturn

  public static java.lang.String notValidNegZFiniteFloat();
    descriptor: ()Ljava/lang/String;
    flags: (0x0009) ACC_PUBLIC, ACC_STATIC
    Code:
      stack=1, locals=0, args_size=0
         0: getstatic     #16                 // Field org/scalactic/Resources$.MODULE$:Lorg/scalactic/Resources$;
         3: invokevirtual #108                // Method org/scalactic/Resources$.notValidNegZFiniteFloat:()Ljava/lang/String;
         6: areturn

  public static java.lang.String rawNotLiteralNegFiniteDouble();
    descriptor: ()Ljava/lang/String;
    flags: (0x0009) ACC_PUBLIC, ACC_STATIC
    Code:
      stack=1, locals=0, args_size=0
         0: getstatic     #16                 // Field org/scalactic/Resources$.MODULE$:Lorg/scalactic/Resources$;
         3: invokevirtual #111                // Method org/scalactic/Resources$.rawNotLiteralNegFiniteDouble:()Ljava/lang/String;
         6: areturn

  public static java.lang.String notLiteralNegFiniteDouble();
    descriptor: ()Ljava/lang/String;
    flags: (0x0009) ACC_PUBLIC, ACC_STATIC
    Code:
      stack=1, locals=0, args_size=0
         0: getstatic     #16                 // Field org/scalactic/Resources$.MODULE$:Lorg/scalactic/Resources$;
         3: invokevirtual #114                // Method org/scalactic/Resources$.notLiteralNegFiniteDouble:()Ljava/lang/String;
         6: areturn

  public static java.lang.String rawNotValidNegFiniteDouble();
    descriptor: ()Ljava/lang/String;
    flags: (0x0009) ACC_PUBLIC, ACC_STATIC
    Code:
      stack=1, locals=0, args_size=0
         0: getstatic     #16                 // Field org/scalactic/Resources$.MODULE$:Lorg/scalactic/Resources$;
         3: invokevirtual #117                // Method org/scalactic/Resources$.rawNotValidNegFiniteDouble:()Ljava/lang/String;
         6: areturn

  public static java.lang.String notValidNegFiniteDouble();
    descriptor: ()Ljava/lang/String;
    flags: (0x0009) ACC_PUBLIC, ACC_STATIC
    Code:
      stack=1, locals=0, args_size=0
         0: getstatic     #16                 // Field org/scalactic/Resources$.MODULE$:Lorg/scalactic/Resources$;
         3: invokevirtual #120                // Method org/scalactic/Resources$.notValidNegFiniteDouble:()Ljava/lang/String;
         6: areturn

  public static java.lang.String rawNotLiteralNegFiniteFloat();
    descriptor: ()Ljava/lang/String;
    flags: (0x0009) ACC_PUBLIC, ACC_STATIC
    Code:
      stack=1, locals=0, args_size=0
         0: getstatic     #16                 // Field org/scalactic/Resources$.MODULE$:Lorg/scalactic/Resources$;
         3: invokevirtual #123                // Method org/scalactic/Resources$.rawNotLiteralNegFiniteFloat:()Ljava/lang/String;
         6: areturn

  public static java.lang.String notLiteralNegFiniteFloat();
    descriptor: ()Ljava/lang/String;
    flags: (0x0009) ACC_PUBLIC, ACC_STATIC
    Code:
      stack=1, locals=0, args_size=0
         0: getstatic     #16                 // Field org/scalactic/Resources$.MODULE$:Lorg/scalactic/Resources$;
         3: invokevirtual #126                // Method org/scalactic/Resources$.notLiteralNegFiniteFloat:()Ljava/lang/String;
         6: areturn

  public static java.lang.String rawNotValidNegFiniteFloat();
    descriptor: ()Ljava/lang/String;
    flags: (0x0009) ACC_PUBLIC, ACC_STATIC
    Code:
      stack=1, locals=0, args_size=0
         0: getstatic     #16                 // Field org/scalactic/Resources$.MODULE$:Lorg/scalactic/Resources$;
         3: invokevirtual #129                // Method org/scalactic/Resources$.rawNotValidNegFiniteFloat:()Ljava/lang/String;
         6: areturn

  public static java.lang.String notValidNegFiniteFloat();
    descriptor: ()Ljava/lang/String;
    flags: (0x0009) ACC_PUBLIC, ACC_STATIC
    Code:
      stack=1, locals=0, args_size=0
         0: getstatic     #16                 // Field org/scalactic/Resources$.MODULE$:Lorg/scalactic/Resources$;
         3: invokevirtual #132                // Method org/scalactic/Resources$.notValidNegFiniteFloat:()Ljava/lang/String;
         6: areturn

  public static java.lang.String rawNotLiteralPosZFiniteDouble();
    descriptor: ()Ljava/lang/String;
    flags: (0x0009) ACC_PUBLIC, ACC_STATIC
    Code:
      stack=1, locals=0, args_size=0
         0: getstatic     #16                 // Field org/scalactic/Resources$.MODULE$:Lorg/scalactic/Resources$;
         3: invokevirtual #135                // Method org/scalactic/Resources$.rawNotLiteralPosZFiniteDouble:()Ljava/lang/String;
         6: areturn

  public static java.lang.String notLiteralPosZFiniteDouble();
    descriptor: ()Ljava/lang/String;
    flags: (0x0009) ACC_PUBLIC, ACC_STATIC
    Code:
      stack=1, locals=0, args_size=0
         0: getstatic     #16                 // Field org/scalactic/Resources$.MODULE$:Lorg/scalactic/Resources$;
         3: invokevirtual #138                // Method org/scalactic/Resources$.notLiteralPosZFiniteDouble:()Ljava/lang/String;
         6: areturn

  public static java.lang.String rawNotValidPosZFiniteDouble();
    descriptor: ()Ljava/lang/String;
    flags: (0x0009) ACC_PUBLIC, ACC_STATIC
    Code:
      stack=1, locals=0, args_size=0
         0: getstatic     #16                 // Field org/scalactic/Resources$.MODULE$:Lorg/scalactic/Resources$;
         3: invokevirtual #141                // Method org/scalactic/Resources$.rawNotValidPosZFiniteDouble:()Ljava/lang/String;
         6: areturn

  public static java.lang.String notValidPosZFiniteDouble();
    descriptor: ()Ljava/lang/String;
    flags: (0x0009) ACC_PUBLIC, ACC_STATIC
    Code:
      stack=1, locals=0, args_size=0
         0: getstatic     #16                 // Field org/scalactic/Resources$.MODULE$:Lorg/scalactic/Resources$;
         3: invokevirtual #144                // Method org/scalactic/Resources$.notValidPosZFiniteDouble:()Ljava/lang/String;
         6: areturn

  public static java.lang.String rawNotLiteralPosZFiniteFloat();
    descriptor: ()Ljava/lang/String;
    flags: (0x0009) ACC_PUBLIC, ACC_STATIC
    Code:
      stack=1, locals=0, args_size=0
         0: getstatic     #16                 // Field org/scalactic/Resources$.MODULE$:Lorg/scalactic/Resources$;
         3: invokevirtual #147                // Method org/scalactic/Resources$.rawNotLiteralPosZFiniteFloat:()Ljava/lang/String;
         6: areturn

  public static java.lang.String notLiteralPosZFiniteFloat();
    descriptor: ()Ljava/lang/String;
    flags: (0x0009) ACC_PUBLIC, ACC_STATIC
    Code:
      stack=1, locals=0, args_size=0
         0: getstatic     #16                 // Field org/scalactic/Resources$.MODULE$:Lorg/scalactic/Resources$;
         3: invokevirtual #150                // Method org/scalactic/Resources$.notLiteralPosZFiniteFloat:()Ljava/lang/String;
         6: areturn

  public static java.lang.String rawNotValidPosZFiniteFloat();
    descriptor: ()Ljava/lang/String;
    flags: (0x0009) ACC_PUBLIC, ACC_STATIC
    Code:
      stack=1, locals=0, args_size=0
         0: getstatic     #16                 // Field org/scalactic/Resources$.MODULE$:Lorg/scalactic/Resources$;
         3: invokevirtual #153                // Method org/scalactic/Resources$.rawNotValidPosZFiniteFloat:()Ljava/lang/String;
         6: areturn

  public static java.lang.String notValidPosZFiniteFloat();
    descriptor: ()Ljava/lang/String;
    flags: (0x0009) ACC_PUBLIC, ACC_STATIC
    Code:
      stack=1, locals=0, args_size=0
         0: getstatic     #16                 // Field org/scalactic/Resources$.MODULE$:Lorg/scalactic/Resources$;
         3: invokevirtual #156                // Method org/scalactic/Resources$.notValidPosZFiniteFloat:()Ljava/lang/String;
         6: areturn

  public static java.lang.String rawNotLiteralPosFiniteDouble();
    descriptor: ()Ljava/lang/String;
    flags: (0x0009) ACC_PUBLIC, ACC_STATIC
    Code:
      stack=1, locals=0, args_size=0
         0: getstatic     #16                 // Field org/scalactic/Resources$.MODULE$:Lorg/scalactic/Resources$;
         3: invokevirtual #159                // Method org/scalactic/Resources$.rawNotLiteralPosFiniteDouble:()Ljava/lang/String;
         6: areturn

  public static java.lang.String notLiteralPosFiniteDouble();
    descriptor: ()Ljava/lang/String;
    flags: (0x0009) ACC_PUBLIC, ACC_STATIC
    Code:
      stack=1, locals=0, args_size=0
         0: getstatic     #16                 // Field org/scalactic/Resources$.MODULE$:Lorg/scalactic/Resources$;
         3: invokevirtual #162                // Method org/scalactic/Resources$.notLiteralPosFiniteDouble:()Ljava/lang/String;
         6: areturn

  public static java.lang.String rawNotValidPosFiniteDouble();
    descriptor: ()Ljava/lang/String;
    flags: (0x0009) ACC_PUBLIC, ACC_STATIC
    Code:
      stack=1, locals=0, args_size=0
         0: getstatic     #16                 // Field org/scalactic/Resources$.MODULE$:Lorg/scalactic/Resources$;
         3: invokevirtual #165                // Method org/scalactic/Resources$.rawNotValidPosFiniteDouble:()Ljava/lang/String;
         6: areturn

  public static java.lang.String notValidPosFiniteDouble();
    descriptor: ()Ljava/lang/String;
    flags: (0x0009) ACC_PUBLIC, ACC_STATIC
    Code:
      stack=1, locals=0, args_size=0
         0: getstatic     #16                 // Field org/scalactic/Resources$.MODULE$:Lorg/scalactic/Resources$;
         3: invokevirtual #168                // Method org/scalactic/Resources$.notValidPosFiniteDouble:()Ljava/lang/String;
         6: areturn

  public static java.lang.String rawNotLiteralPosFiniteFloat();
    descriptor: ()Ljava/lang/String;
    flags: (0x0009) ACC_PUBLIC, ACC_STATIC
    Code:
      stack=1, locals=0, args_size=0
         0: getstatic     #16                 // Field org/scalactic/Resources$.MODULE$:Lorg/scalactic/Resources$;
         3: invokevirtual #171                // Method org/scalactic/Resources$.rawNotLiteralPosFiniteFloat:()Ljava/lang/String;
         6: areturn

  public static java.lang.String notLiteralPosFiniteFloat();
    descriptor: ()Ljava/lang/String;
    flags: (0x0009) ACC_PUBLIC, ACC_STATIC
    Code:
      stack=1, locals=0, args_size=0
         0: getstatic     #16                 // Field org/scalactic/Resources$.MODULE$:Lorg/scalactic/Resources$;
         3: invokevirtual #174                // Method org/scalactic/Resources$.notLiteralPosFiniteFloat:()Ljava/lang/String;
         6: areturn

  public static java.lang.String rawNotValidPosFiniteFloat();
    descriptor: ()Ljava/lang/String;
    flags: (0x0009) ACC_PUBLIC, ACC_STATIC
    Code:
      stack=1, locals=0, args_size=0
         0: getstatic     #16                 // Field org/scalactic/Resources$.MODULE$:Lorg/scalactic/Resources$;
         3: invokevirtual #177                // Method org/scalactic/Resources$.rawNotValidPosFiniteFloat:()Ljava/lang/String;
         6: areturn

  public static java.lang.String notValidPosFiniteFloat();
    descriptor: ()Ljava/lang/String;
    flags: (0x0009) ACC_PUBLIC, ACC_STATIC
    Code:
      stack=1, locals=0, args_size=0
         0: getstatic     #16                 // Field org/scalactic/Resources$.MODULE$:Lorg/scalactic/Resources$;
         3: invokevirtual #180                // Method org/scalactic/Resources$.notValidPosFiniteFloat:()Ljava/lang/String;
         6: areturn

  public static java.lang.String rawNotLiteralNegZDouble();
    descriptor: ()Ljava/lang/String;
    flags: (0x0009) ACC_PUBLIC, ACC_STATIC
    Code:
      stack=1, locals=0, args_size=0
         0: getstatic     #16                 // Field org/scalactic/Resources$.MODULE$:Lorg/scalactic/Resources$;
         3: invokevirtual #183                // Method org/scalactic/Resources$.rawNotLiteralNegZDouble:()Ljava/lang/String;
         6: areturn

  public static java.lang.String notLiteralNegZDouble();
    descriptor: ()Ljava/lang/String;
    flags: (0x0009) ACC_PUBLIC, ACC_STATIC
    Code:
      stack=1, locals=0, args_size=0
         0: getstatic     #16                 // Field org/scalactic/Resources$.MODULE$:Lorg/scalactic/Resources$;
         3: invokevirtual #186                // Method org/scalactic/Resources$.notLiteralNegZDouble:()Ljava/lang/String;
         6: areturn

  public static java.lang.String rawNotValidNegZDouble();
    descriptor: ()Ljava/lang/String;
    flags: (0x0009) ACC_PUBLIC, ACC_STATIC
    Code:
      stack=1, locals=0, args_size=0
         0: getstatic     #16                 // Field org/scalactic/Resources$.MODULE$:Lorg/scalactic/Resources$;
         3: invokevirtual #189                // Method org/scalactic/Resources$.rawNotValidNegZDouble:()Ljava/lang/String;
         6: areturn

  public static java.lang.String notValidNegZDouble();
    descriptor: ()Ljava/lang/String;
    flags: (0x0009) ACC_PUBLIC, ACC_STATIC
    Code:
      stack=1, locals=0, args_size=0
         0: getstatic     #16                 // Field org/scalactic/Resources$.MODULE$:Lorg/scalactic/Resources$;
         3: invokevirtual #192                // Method org/scalactic/Resources$.notValidNegZDouble:()Ljava/lang/String;
         6: areturn

  public static java.lang.String rawNotLiteralNegZFloat();
    descriptor: ()Ljava/lang/String;
    flags: (0x0009) ACC_PUBLIC, ACC_STATIC
    Code:
      stack=1, locals=0, args_size=0
         0: getstatic     #16                 // Field org/scalactic/Resources$.MODULE$:Lorg/scalactic/Resources$;
         3: invokevirtual #195                // Method org/scalactic/Resources$.rawNotLiteralNegZFloat:()Ljava/lang/String;
         6: areturn

  public static java.lang.String notLiteralNegZFloat();
    descriptor: ()Ljava/lang/String;
    flags: (0x0009) ACC_PUBLIC, ACC_STATIC
    Code:
      stack=1, locals=0, args_size=0
         0: getstatic     #16                 // Field org/scalactic/Resources$.MODULE$:Lorg/scalactic/Resources$;
         3: invokevirtual #198                // Method org/scalactic/Resources$.notLiteralNegZFloat:()Ljava/lang/String;
         6: areturn

  public static java.lang.String rawNotValidNegZFloat();
    descriptor: ()Ljava/lang/String;
    flags: (0x0009) ACC_PUBLIC, ACC_STATIC
    Code:
      stack=1, locals=0, args_size=0
         0: getstatic     #16                 // Field org/scalactic/Resources$.MODULE$:Lorg/scalactic/Resources$;
         3: invokevirtual #201                // Method org/scalactic/Resources$.rawNotValidNegZFloat:()Ljava/lang/String;
         6: areturn

  public static java.lang.String notValidNegZFloat();
    descriptor: ()Ljava/lang/String;
    flags: (0x0009) ACC_PUBLIC, ACC_STATIC
    Code:
      stack=1, locals=0, args_size=0
         0: getstatic     #16                 // Field org/scalactic/Resources$.MODULE$:Lorg/scalactic/Resources$;
         3: invokevirtual #204                // Method org/scalactic/Resources$.notValidNegZFloat:()Ljava/lang/String;
         6: areturn

  public static java.lang.String rawNotLiteralNegZLong();
    descriptor: ()Ljava/lang/String;
    flags: (0x0009) ACC_PUBLIC, ACC_STATIC
    Code:
      stack=1, locals=0, args_size=0
         0: getstatic     #16                 // Field org/scalactic/Resources$.MODULE$:Lorg/scalactic/Resources$;
         3: invokevirtual #207                // Method org/scalactic/Resources$.rawNotLiteralNegZLong:()Ljava/lang/String;
         6: areturn

  public static java.lang.String notLiteralNegZLong();
    descriptor: ()Ljava/lang/String;
    flags: (0x0009) ACC_PUBLIC, ACC_STATIC
    Code:
      stack=1, locals=0, args_size=0
         0: getstatic     #16                 // Field org/scalactic/Resources$.MODULE$:Lorg/scalactic/Resources$;
         3: invokevirtual #210                // Method org/scalactic/Resources$.notLiteralNegZLong:()Ljava/lang/String;
         6: areturn

  public static java.lang.String rawNotValidNegZLong();
    descriptor: ()Ljava/lang/String;
    flags: (0x0009) ACC_PUBLIC, ACC_STATIC
    Code:
      stack=1, locals=0, args_size=0
         0: getstatic     #16                 // Field org/scalactic/Resources$.MODULE$:Lorg/scalactic/Resources$;
         3: invokevirtual #213                // Method org/scalactic/Resources$.rawNotValidNegZLong:()Ljava/lang/String;
         6: areturn

  public static java.lang.String notValidNegZLong();
    descriptor: ()Ljava/lang/String;
    flags: (0x0009) ACC_PUBLIC, ACC_STATIC
    Code:
      stack=1, locals=0, args_size=0
         0: getstatic     #16                 // Field org/scalactic/Resources$.MODULE$:Lorg/scalactic/Resources$;
         3: invokevirtual #216                // Method org/scalactic/Resources$.notValidNegZLong:()Ljava/lang/String;
         6: areturn

  public static java.lang.String rawNotLiteralNegZInt();
    descriptor: ()Ljava/lang/String;
    flags: (0x0009) ACC_PUBLIC, ACC_STATIC
    Code:
      stack=1, locals=0, args_size=0
         0: getstatic     #16                 // Field org/scalactic/Resources$.MODULE$:Lorg/scalactic/Resources$;
         3: invokevirtual #219                // Method org/scalactic/Resources$.rawNotLiteralNegZInt:()Ljava/lang/String;
         6: areturn

  public static java.lang.String notLiteralNegZInt();
    descriptor: ()Ljava/lang/String;
    flags: (0x0009) ACC_PUBLIC, ACC_STATIC
    Code:
      stack=1, locals=0, args_size=0
         0: getstatic     #16                 // Field org/scalactic/Resources$.MODULE$:Lorg/scalactic/Resources$;
         3: invokevirtual #222                // Method org/scalactic/Resources$.notLiteralNegZInt:()Ljava/lang/String;
         6: areturn

  public static java.lang.String rawNotValidNegZInt();
    descriptor: ()Ljava/lang/String;
    flags: (0x0009) ACC_PUBLIC, ACC_STATIC
    Code:
      stack=1, locals=0, args_size=0
         0: getstatic     #16                 // Field org/scalactic/Resources$.MODULE$:Lorg/scalactic/Resources$;
         3: invokevirtual #225                // Method org/scalactic/Resources$.rawNotValidNegZInt:()Ljava/lang/String;
         6: areturn

  public static java.lang.String notValidNegZInt();
    descriptor: ()Ljava/lang/String;
    flags: (0x0009) ACC_PUBLIC, ACC_STATIC
    Code:
      stack=1, locals=0, args_size=0
         0: getstatic     #16                 // Field org/scalactic/Resources$.MODULE$:Lorg/scalactic/Resources$;
         3: invokevirtual #228                // Method org/scalactic/Resources$.notValidNegZInt:()Ljava/lang/String;
         6: areturn

  public static java.lang.String rawNotLiteralNegDouble();
    descriptor: ()Ljava/lang/String;
    flags: (0x0009) ACC_PUBLIC, ACC_STATIC
    Code:
      stack=1, locals=0, args_size=0
         0: getstatic     #16                 // Field org/scalactic/Resources$.MODULE$:Lorg/scalactic/Resources$;
         3: invokevirtual #231                // Method org/scalactic/Resources$.rawNotLiteralNegDouble:()Ljava/lang/String;
         6: areturn

  public static java.lang.String notLiteralNegDouble();
    descriptor: ()Ljava/lang/String;
    flags: (0x0009) ACC_PUBLIC, ACC_STATIC
    Code:
      stack=1, locals=0, args_size=0
         0: getstatic     #16                 // Field org/scalactic/Resources$.MODULE$:Lorg/scalactic/Resources$;
         3: invokevirtual #234                // Method org/scalactic/Resources$.notLiteralNegDouble:()Ljava/lang/String;
         6: areturn

  public static java.lang.String rawNotValidNegDouble();
    descriptor: ()Ljava/lang/String;
    flags: (0x0009) ACC_PUBLIC, ACC_STATIC
    Code:
      stack=1, locals=0, args_size=0
         0: getstatic     #16                 // Field org/scalactic/Resources$.MODULE$:Lorg/scalactic/Resources$;
         3: invokevirtual #237                // Method org/scalactic/Resources$.rawNotValidNegDouble:()Ljava/lang/String;
         6: areturn

  public static java.lang.String notValidNegDouble();
    descriptor: ()Ljava/lang/String;
    flags: (0x0009) ACC_PUBLIC, ACC_STATIC
    Code:
      stack=1, locals=0, args_size=0
         0: getstatic     #16                 // Field org/scalactic/Resources$.MODULE$:Lorg/scalactic/Resources$;
         3: invokevirtual #240                // Method org/scalactic/Resources$.notValidNegDouble:()Ljava/lang/String;
         6: areturn

  public static java.lang.String rawNotLiteralNegFloat();
    descriptor: ()Ljava/lang/String;
    flags: (0x0009) ACC_PUBLIC, ACC_STATIC
    Code:
      stack=1, locals=0, args_size=0
         0: getstatic     #16                 // Field org/scalactic/Resources$.MODULE$:Lorg/scalactic/Resources$;
         3: invokevirtual #243                // Method org/scalactic/Resources$.rawNotLiteralNegFloat:()Ljava/lang/String;
         6: areturn

  public static java.lang.String notLiteralNegFloat();
    descriptor: ()Ljava/lang/String;
    flags: (0x0009) ACC_PUBLIC, ACC_STATIC
    Code:
      stack=1, locals=0, args_size=0
         0: getstatic     #16                 // Field org/scalactic/Resources$.MODULE$:Lorg/scalactic/Resources$;
         3: invokevirtual #246                // Method org/scalactic/Resources$.notLiteralNegFloat:()Ljava/lang/String;
         6: areturn

  public static java.lang.String rawNotValidNegFloat();
    descriptor: ()Ljava/lang/String;
    flags: (0x0009) ACC_PUBLIC, ACC_STATIC
    Code:
      stack=1, locals=0, args_size=0
         0: getstatic     #16                 // Field org/scalactic/Resources$.MODULE$:Lorg/scalactic/Resources$;
         3: invokevirtual #249                // Method org/scalactic/Resources$.rawNotValidNegFloat:()Ljava/lang/String;
         6: areturn

  public static java.lang.String notValidNegFloat();
    descriptor: ()Ljava/lang/String;
    flags: (0x0009) ACC_PUBLIC, ACC_STATIC
    Code:
      stack=1, locals=0, args_size=0
         0: getstatic     #16                 // Field org/scalactic/Resources$.MODULE$:Lorg/scalactic/Resources$;
         3: invokevirtual #252                // Method org/scalactic/Resources$.notValidNegFloat:()Ljava/lang/String;
         6: areturn

  public static java.lang.String rawNotLiteralNegLong();
    descriptor: ()Ljava/lang/String;
    flags: (0x0009) ACC_PUBLIC, ACC_STATIC
    Code:
      stack=1, locals=0, args_size=0
         0: getstatic     #16                 // Field org/scalactic/Resources$.MODULE$:Lorg/scalactic/Resources$;
         3: invokevirtual #255                // Method org/scalactic/Resources$.rawNotLiteralNegLong:()Ljava/lang/String;
         6: areturn

  public static java.lang.String notLiteralNegLong();
    descriptor: ()Ljava/lang/String;
    flags: (0x0009) ACC_PUBLIC, ACC_STATIC
    Code:
      stack=1, locals=0, args_size=0
         0: getstatic     #16                 // Field org/scalactic/Resources$.MODULE$:Lorg/scalactic/Resources$;
         3: invokevirtual #258                // Method org/scalactic/Resources$.notLiteralNegLong:()Ljava/lang/String;
         6: areturn

  public static java.lang.String rawNotValidNegLong();
    descriptor: ()Ljava/lang/String;
    flags: (0x0009) ACC_PUBLIC, ACC_STATIC
    Code:
      stack=1, locals=0, args_size=0
         0: getstatic     #16                 // Field org/scalactic/Resources$.MODULE$:Lorg/scalactic/Resources$;
         3: invokevirtual #261                // Method org/scalactic/Resources$.rawNotValidNegLong:()Ljava/lang/String;
         6: areturn

  public static java.lang.String notValidNegLong();
    descriptor: ()Ljava/lang/String;
    flags: (0x0009) ACC_PUBLIC, ACC_STATIC
    Code:
      stack=1, locals=0, args_size=0
         0: getstatic     #16                 // Field org/scalactic/Resources$.MODULE$:Lorg/scalactic/Resources$;
         3: invokevirtual #264                // Method org/scalactic/Resources$.notValidNegLong:()Ljava/lang/String;
         6: areturn

  public static java.lang.String rawNotLiteralNegInt();
    descriptor: ()Ljava/lang/String;
    flags: (0x0009) ACC_PUBLIC, ACC_STATIC
    Code:
      stack=1, locals=0, args_size=0
         0: getstatic     #16                 // Field org/scalactic/Resources$.MODULE$:Lorg/scalactic/Resources$;
         3: invokevirtual #267                // Method org/scalactic/Resources$.rawNotLiteralNegInt:()Ljava/lang/String;
         6: areturn

  public static java.lang.String notLiteralNegInt();
    descriptor: ()Ljava/lang/String;
    flags: (0x0009) ACC_PUBLIC, ACC_STATIC
    Code:
      stack=1, locals=0, args_size=0
         0: getstatic     #16                 // Field org/scalactic/Resources$.MODULE$:Lorg/scalactic/Resources$;
         3: invokevirtual #270                // Method org/scalactic/Resources$.notLiteralNegInt:()Ljava/lang/String;
         6: areturn

  public static java.lang.String rawNotValidNegInt();
    descriptor: ()Ljava/lang/String;
    flags: (0x0009) ACC_PUBLIC, ACC_STATIC
    Code:
      stack=1, locals=0, args_size=0
         0: getstatic     #16                 // Field org/scalactic/Resources$.MODULE$:Lorg/scalactic/Resources$;
         3: invokevirtual #273                // Method org/scalactic/Resources$.rawNotValidNegInt:()Ljava/lang/String;
         6: areturn

  public static java.lang.String notValidNegInt();
    descriptor: ()Ljava/lang/String;
    flags: (0x0009) ACC_PUBLIC, ACC_STATIC
    Code:
      stack=1, locals=0, args_size=0
         0: getstatic     #16                 // Field org/scalactic/Resources$.MODULE$:Lorg/scalactic/Resources$;
         3: invokevirtual #276                // Method org/scalactic/Resources$.notValidNegInt:()Ljava/lang/String;
         6: areturn

  public static java.lang.String rawNotLiteralNonZeroDouble();
    descriptor: ()Ljava/lang/String;
    flags: (0x0009) ACC_PUBLIC, ACC_STATIC
    Code:
      stack=1, locals=0, args_size=0
         0: getstatic     #16                 // Field org/scalactic/Resources$.MODULE$:Lorg/scalactic/Resources$;
         3: invokevirtual #279                // Method org/scalactic/Resources$.rawNotLiteralNonZeroDouble:()Ljava/lang/String;
         6: areturn

  public static java.lang.String notLiteralNonZeroDouble();
    descriptor: ()Ljava/lang/String;
    flags: (0x0009) ACC_PUBLIC, ACC_STATIC
    Code:
      stack=1, locals=0, args_size=0
         0: getstatic     #16                 // Field org/scalactic/Resources$.MODULE$:Lorg/scalactic/Resources$;
         3: invokevirtual #282                // Method org/scalactic/Resources$.notLiteralNonZeroDouble:()Ljava/lang/String;
         6: areturn

  public static java.lang.String rawNotValidNonZeroDouble();
    descriptor: ()Ljava/lang/String;
    flags: (0x0009) ACC_PUBLIC, ACC_STATIC
    Code:
      stack=1, locals=0, args_size=0
         0: getstatic     #16                 // Field org/scalactic/Resources$.MODULE$:Lorg/scalactic/Resources$;
         3: invokevirtual #285                // Method org/scalactic/Resources$.rawNotValidNonZeroDouble:()Ljava/lang/String;
         6: areturn

  public static java.lang.String notValidNonZeroDouble();
    descriptor: ()Ljava/lang/String;
    flags: (0x0009) ACC_PUBLIC, ACC_STATIC
    Code:
      stack=1, locals=0, args_size=0
         0: getstatic     #16                 // Field org/scalactic/Resources$.MODULE$:Lorg/scalactic/Resources$;
         3: invokevirtual #288                // Method org/scalactic/Resources$.notValidNonZeroDouble:()Ljava/lang/String;
         6: areturn

  public static java.lang.String rawNotLiteralNonZeroFloat();
    descriptor: ()Ljava/lang/String;
    flags: (0x0009) ACC_PUBLIC, ACC_STATIC
    Code:
      stack=1, locals=0, args_size=0
         0: getstatic     #16                 // Field org/scalactic/Resources$.MODULE$:Lorg/scalactic/Resources$;
         3: invokevirtual #291                // Method org/scalactic/Resources$.rawNotLiteralNonZeroFloat:()Ljava/lang/String;
         6: areturn

  public static java.lang.String notLiteralNonZeroFloat();
    descriptor: ()Ljava/lang/String;
    flags: (0x0009) ACC_PUBLIC, ACC_STATIC
    Code:
      stack=1, locals=0, args_size=0
         0: getstatic     #16                 // Field org/scalactic/Resources$.MODULE$:Lorg/scalactic/Resources$;
         3: invokevirtual #294                // Method org/scalactic/Resources$.notLiteralNonZeroFloat:()Ljava/lang/String;
         6: areturn

  public static java.lang.String rawNotValidNonZeroFloat();
    descriptor: ()Ljava/lang/String;
    flags: (0x0009) ACC_PUBLIC, ACC_STATIC
    Code:
      stack=1, locals=0, args_size=0
         0: getstatic     #16                 // Field org/scalactic/Resources$.MODULE$:Lorg/scalactic/Resources$;
         3: invokevirtual #297                // Method org/scalactic/Resources$.rawNotValidNonZeroFloat:()Ljava/lang/String;
         6: areturn

  public static java.lang.String notValidNonZeroFloat();
    descriptor: ()Ljava/lang/String;
    flags: (0x0009) ACC_PUBLIC, ACC_STATIC
    Code:
      stack=1, locals=0, args_size=0
         0: getstatic     #16                 // Field org/scalactic/Resources$.MODULE$:Lorg/scalactic/Resources$;
         3: invokevirtual #300                // Method org/scalactic/Resources$.notValidNonZeroFloat:()Ljava/lang/String;
         6: areturn

  public static java.lang.String rawNotLiteralNonZeroLong();
    descriptor: ()Ljava/lang/String;
    flags: (0x0009) ACC_PUBLIC, ACC_STATIC
    Code:
      stack=1, locals=0, args_size=0
         0: getstatic     #16                 // Field org/scalactic/Resources$.MODULE$:Lorg/scalactic/Resources$;
         3: invokevirtual #303                // Method org/scalactic/Resources$.rawNotLiteralNonZeroLong:()Ljava/lang/String;
         6: areturn

  public static java.lang.String notLiteralNonZeroLong();
    descriptor: ()Ljava/lang/String;
    flags: (0x0009) ACC_PUBLIC, ACC_STATIC
    Code:
      stack=1, locals=0, args_size=0
         0: getstatic     #16                 // Field org/scalactic/Resources$.MODULE$:Lorg/scalactic/Resources$;
         3: invokevirtual #306                // Method org/scalactic/Resources$.notLiteralNonZeroLong:()Ljava/lang/String;
         6: areturn

  public static java.lang.String rawNotValidNonZeroLong();
    descriptor: ()Ljava/lang/String;
    flags: (0x0009) ACC_PUBLIC, ACC_STATIC
    Code:
      stack=1, locals=0, args_size=0
         0: getstatic     #16                 // Field org/scalactic/Resources$.MODULE$:Lorg/scalactic/Resources$;
         3: invokevirtual #309                // Method org/scalactic/Resources$.rawNotValidNonZeroLong:()Ljava/lang/String;
         6: areturn

  public static java.lang.String notValidNonZeroLong();
    descriptor: ()Ljava/lang/String;
    flags: (0x0009) ACC_PUBLIC, ACC_STATIC
    Code:
      stack=1, locals=0, args_size=0
         0: getstatic     #16                 // Field org/scalactic/Resources$.MODULE$:Lorg/scalactic/Resources$;
         3: invokevirtual #312                // Method org/scalactic/Resources$.notValidNonZeroLong:()Ljava/lang/String;
         6: areturn

  public static java.lang.String rawNotLiteralNonZeroInt();
    descriptor: ()Ljava/lang/String;
    flags: (0x0009) ACC_PUBLIC, ACC_STATIC
    Code:
      stack=1, locals=0, args_size=0
         0: getstatic     #16                 // Field org/scalactic/Resources$.MODULE$:Lorg/scalactic/Resources$;
         3: invokevirtual #315                // Method org/scalactic/Resources$.rawNotLiteralNonZeroInt:()Ljava/lang/String;
         6: areturn

  public static java.lang.String notLiteralNonZeroInt();
    descriptor: ()Ljava/lang/String;
    flags: (0x0009) ACC_PUBLIC, ACC_STATIC
    Code:
      stack=1, locals=0, args_size=0
         0: getstatic     #16                 // Field org/scalactic/Resources$.MODULE$:Lorg/scalactic/Resources$;
         3: invokevirtual #318                // Method org/scalactic/Resources$.notLiteralNonZeroInt:()Ljava/lang/String;
         6: areturn

  public static java.lang.String rawNotValidNonZeroInt();
    descriptor: ()Ljava/lang/String;
    flags: (0x0009) ACC_PUBLIC, ACC_STATIC
    Code:
      stack=1, locals=0, args_size=0
         0: getstatic     #16                 // Field org/scalactic/Resources$.MODULE$:Lorg/scalactic/Resources$;
         3: invokevirtual #321                // Method org/scalactic/Resources$.rawNotValidNonZeroInt:()Ljava/lang/String;
         6: areturn

  public static java.lang.String notValidNonZeroInt();
    descriptor: ()Ljava/lang/String;
    flags: (0x0009) ACC_PUBLIC, ACC_STATIC
    Code:
      stack=1, locals=0, args_size=0
         0: getstatic     #16                 // Field org/scalactic/Resources$.MODULE$:Lorg/scalactic/Resources$;
         3: invokevirtual #324                // Method org/scalactic/Resources$.notValidNonZeroInt:()Ljava/lang/String;
         6: areturn

  public static java.lang.String rawPleaseDefineScalacticFillFilePathnameEnvVar();
    descriptor: ()Ljava/lang/String;
    flags: (0x0009) ACC_PUBLIC, ACC_STATIC
    Code:
      stack=1, locals=0, args_size=0
         0: getstatic     #16                 // Field org/scalactic/Resources$.MODULE$:Lorg/scalactic/Resources$;
         3: invokevirtual #327                // Method org/scalactic/Resources$.rawPleaseDefineScalacticFillFilePathnameEnvVar:()Ljava/lang/String;
         6: areturn

  public static java.lang.String pleaseDefineScalacticFillFilePathnameEnvVar();
    descriptor: ()Ljava/lang/String;
    flags: (0x0009) ACC_PUBLIC, ACC_STATIC
    Code:
      stack=1, locals=0, args_size=0
         0: getstatic     #16                 // Field org/scalactic/Resources$.MODULE$:Lorg/scalactic/Resources$;
         3: invokevirtual #330                // Method org/scalactic/Resources$.pleaseDefineScalacticFillFilePathnameEnvVar:()Ljava/lang/String;
         6: areturn

  public static java.lang.String rawNotLiteralPosZDouble();
    descriptor: ()Ljava/lang/String;
    flags: (0x0009) ACC_PUBLIC, ACC_STATIC
    Code:
      stack=1, locals=0, args_size=0
         0: getstatic     #16                 // Field org/scalactic/Resources$.MODULE$:Lorg/scalactic/Resources$;
         3: invokevirtual #333                // Method org/scalactic/Resources$.rawNotLiteralPosZDouble:()Ljava/lang/String;
         6: areturn

  public static java.lang.String notLiteralPosZDouble();
    descriptor: ()Ljava/lang/String;
    flags: (0x0009) ACC_PUBLIC, ACC_STATIC
    Code:
      stack=1, locals=0, args_size=0
         0: getstatic     #16                 // Field org/scalactic/Resources$.MODULE$:Lorg/scalactic/Resources$;
         3: invokevirtual #336                // Method org/scalactic/Resources$.notLiteralPosZDouble:()Ljava/lang/String;
         6: areturn

  public static java.lang.String rawNotValidPosZDouble();
    descriptor: ()Ljava/lang/String;
    flags: (0x0009) ACC_PUBLIC, ACC_STATIC
    Code:
      stack=1, locals=0, args_size=0
         0: getstatic     #16                 // Field org/scalactic/Resources$.MODULE$:Lorg/scalactic/Resources$;
         3: invokevirtual #339                // Method org/scalactic/Resources$.rawNotValidPosZDouble:()Ljava/lang/String;
         6: areturn

  public static java.lang.String notValidPosZDouble();
    descriptor: ()Ljava/lang/String;
    flags: (0x0009) ACC_PUBLIC, ACC_STATIC
    Code:
      stack=1, locals=0, args_size=0
         0: getstatic     #16                 // Field org/scalactic/Resources$.MODULE$:Lorg/scalactic/Resources$;
         3: invokevirtual #342                // Method org/scalactic/Resources$.notValidPosZDouble:()Ljava/lang/String;
         6: areturn

  public static java.lang.String rawNotLiteralPosZFloat();
    descriptor: ()Ljava/lang/String;
    flags: (0x0009) ACC_PUBLIC, ACC_STATIC
    Code:
      stack=1, locals=0, args_size=0
         0: getstatic     #16                 // Field org/scalactic/Resources$.MODULE$:Lorg/scalactic/Resources$;
         3: invokevirtual #345                // Method org/scalactic/Resources$.rawNotLiteralPosZFloat:()Ljava/lang/String;
         6: areturn

  public static java.lang.String notLiteralPosZFloat();
    descriptor: ()Ljava/lang/String;
    flags: (0x0009) ACC_PUBLIC, ACC_STATIC
    Code:
      stack=1, locals=0, args_size=0
         0: getstatic     #16                 // Field org/scalactic/Resources$.MODULE$:Lorg/scalactic/Resources$;
         3: invokevirtual #348                // Method org/scalactic/Resources$.notLiteralPosZFloat:()Ljava/lang/String;
         6: areturn

  public static java.lang.String rawNotValidPosZFloat();
    descriptor: ()Ljava/lang/String;
    flags: (0x0009) ACC_PUBLIC, ACC_STATIC
    Code:
      stack=1, locals=0, args_size=0
         0: getstatic     #16                 // Field org/scalactic/Resources$.MODULE$:Lorg/scalactic/Resources$;
         3: invokevirtual #351                // Method org/scalactic/Resources$.rawNotValidPosZFloat:()Ljava/lang/String;
         6: areturn

  public static java.lang.String notValidPosZFloat();
    descriptor: ()Ljava/lang/String;
    flags: (0x0009) ACC_PUBLIC, ACC_STATIC
    Code:
      stack=1, locals=0, args_size=0
         0: getstatic     #16                 // Field org/scalactic/Resources$.MODULE$:Lorg/scalactic/Resources$;
         3: invokevirtual #354                // Method org/scalactic/Resources$.notValidPosZFloat:()Ljava/lang/String;
         6: areturn

  public static java.lang.String rawNotLiteralPosZLong();
    descriptor: ()Ljava/lang/String;
    flags: (0x0009) ACC_PUBLIC, ACC_STATIC
    Code:
      stack=1, locals=0, args_size=0
         0: getstatic     #16                 // Field org/scalactic/Resources$.MODULE$:Lorg/scalactic/Resources$;
         3: invokevirtual #357                // Method org/scalactic/Resources$.rawNotLiteralPosZLong:()Ljava/lang/String;
         6: areturn

  public static java.lang.String notLiteralPosZLong();
    descriptor: ()Ljava/lang/String;
    flags: (0x0009) ACC_PUBLIC, ACC_STATIC
    Code:
      stack=1, locals=0, args_size=0
         0: getstatic     #16                 // Field org/scalactic/Resources$.MODULE$:Lorg/scalactic/Resources$;
         3: invokevirtual #360                // Method org/scalactic/Resources$.notLiteralPosZLong:()Ljava/lang/String;
         6: areturn

  public static java.lang.String rawNotValidPosZLong();
    descriptor: ()Ljava/lang/String;
    flags: (0x0009) ACC_PUBLIC, ACC_STATIC
    Code:
      stack=1, locals=0, args_size=0
         0: getstatic     #16                 // Field org/scalactic/Resources$.MODULE$:Lorg/scalactic/Resources$;
         3: invokevirtual #363                // Method org/scalactic/Resources$.rawNotValidPosZLong:()Ljava/lang/String;
         6: areturn

  public static java.lang.String notValidPosZLong();
    descriptor: ()Ljava/lang/String;
    flags: (0x0009) ACC_PUBLIC, ACC_STATIC
    Code:
      stack=1, locals=0, args_size=0
         0: getstatic     #16                 // Field org/scalactic/Resources$.MODULE$:Lorg/scalactic/Resources$;
         3: invokevirtual #366                // Method org/scalactic/Resources$.notValidPosZLong:()Ljava/lang/String;
         6: areturn

  public static java.lang.String rawNotLiteralPosZInt();
    descriptor: ()Ljava/lang/String;
    flags: (0x0009) ACC_PUBLIC, ACC_STATIC
    Code:
      stack=1, locals=0, args_size=0
         0: getstatic     #16                 // Field org/scalactic/Resources$.MODULE$:Lorg/scalactic/Resources$;
         3: invokevirtual #369                // Method org/scalactic/Resources$.rawNotLiteralPosZInt:()Ljava/lang/String;
         6: areturn

  public static java.lang.String notLiteralPosZInt();
    descriptor: ()Ljava/lang/String;
    flags: (0x0009) ACC_PUBLIC, ACC_STATIC
    Code:
      stack=1, locals=0, args_size=0
         0: getstatic     #16                 // Field org/scalactic/Resources$.MODULE$:Lorg/scalactic/Resources$;
         3: invokevirtual #372                // Method org/scalactic/Resources$.notLiteralPosZInt:()Ljava/lang/String;
         6: areturn

  public static java.lang.String rawNotValidPosZInt();
    descriptor: ()Ljava/lang/String;
    flags: (0x0009) ACC_PUBLIC, ACC_STATIC
    Code:
      stack=1, locals=0, args_size=0
         0: getstatic     #16                 // Field org/scalactic/Resources$.MODULE$:Lorg/scalactic/Resources$;
         3: invokevirtual #375                // Method org/scalactic/Resources$.rawNotValidPosZInt:()Ljava/lang/String;
         6: areturn

  public static java.lang.String notValidPosZInt();
    descriptor: ()Ljava/lang/String;
    flags: (0x0009) ACC_PUBLIC, ACC_STATIC
    Code:
      stack=1, locals=0, args_size=0
         0: getstatic     #16                 // Field org/scalactic/Resources$.MODULE$:Lorg/scalactic/Resources$;
         3: invokevirtual #378                // Method org/scalactic/Resources$.notValidPosZInt:()Ljava/lang/String;
         6: areturn

  public static java.lang.String rawNotLiteralPosDouble();
    descriptor: ()Ljava/lang/String;
    flags: (0x0009) ACC_PUBLIC, ACC_STATIC
    Code:
      stack=1, locals=0, args_size=0
         0: getstatic     #16                 // Field org/scalactic/Resources$.MODULE$:Lorg/scalactic/Resources$;
         3: invokevirtual #381                // Method org/scalactic/Resources$.rawNotLiteralPosDouble:()Ljava/lang/String;
         6: areturn

  public static java.lang.String notLiteralPosDouble();
    descriptor: ()Ljava/lang/String;
    flags: (0x0009) ACC_PUBLIC, ACC_STATIC
    Code:
      stack=1, locals=0, args_size=0
         0: getstatic     #16                 // Field org/scalactic/Resources$.MODULE$:Lorg/scalactic/Resources$;
         3: invokevirtual #384                // Method org/scalactic/Resources$.notLiteralPosDouble:()Ljava/lang/String;
         6: areturn

  public static java.lang.String rawNotValidPosDouble();
    descriptor: ()Ljava/lang/String;
    flags: (0x0009) ACC_PUBLIC, ACC_STATIC
    Code:
      stack=1, locals=0, args_size=0
         0: getstatic     #16                 // Field org/scalactic/Resources$.MODULE$:Lorg/scalactic/Resources$;
         3: invokevirtual #387                // Method org/scalactic/Resources$.rawNotValidPosDouble:()Ljava/lang/String;
         6: areturn

  public static java.lang.String notValidPosDouble();
    descriptor: ()Ljava/lang/String;
    flags: (0x0009) ACC_PUBLIC, ACC_STATIC
    Code:
      stack=1, locals=0, args_size=0
         0: getstatic     #16                 // Field org/scalactic/Resources$.MODULE$:Lorg/scalactic/Resources$;
         3: invokevirtual #390                // Method org/scalactic/Resources$.notValidPosDouble:()Ljava/lang/String;
         6: areturn

  public static java.lang.String rawNotLiteralPosFloat();
    descriptor: ()Ljava/lang/String;
    flags: (0x0009) ACC_PUBLIC, ACC_STATIC
    Code:
      stack=1, locals=0, args_size=0
         0: getstatic     #16                 // Field org/scalactic/Resources$.MODULE$:Lorg/scalactic/Resources$;
         3: invokevirtual #393                // Method org/scalactic/Resources$.rawNotLiteralPosFloat:()Ljava/lang/String;
         6: areturn

  public static java.lang.String notLiteralPosFloat();
    descriptor: ()Ljava/lang/String;
    flags: (0x0009) ACC_PUBLIC, ACC_STATIC
    Code:
      stack=1, locals=0, args_size=0
         0: getstatic     #16                 // Field org/scalactic/Resources$.MODULE$:Lorg/scalactic/Resources$;
         3: invokevirtual #396                // Method org/scalactic/Resources$.notLiteralPosFloat:()Ljava/lang/String;
         6: areturn

  public static java.lang.String rawNotValidPosFloat();
    descriptor: ()Ljava/lang/String;
    flags: (0x0009) ACC_PUBLIC, ACC_STATIC
    Code:
      stack=1, locals=0, args_size=0
         0: getstatic     #16                 // Field org/scalactic/Resources$.MODULE$:Lorg/scalactic/Resources$;
         3: invokevirtual #399                // Method org/scalactic/Resources$.rawNotValidPosFloat:()Ljava/lang/String;
         6: areturn

  public static java.lang.String notValidPosFloat();
    descriptor: ()Ljava/lang/String;
    flags: (0x0009) ACC_PUBLIC, ACC_STATIC
    Code:
      stack=1, locals=0, args_size=0
         0: getstatic     #16                 // Field org/scalactic/Resources$.MODULE$:Lorg/scalactic/Resources$;
         3: invokevirtual #402                // Method org/scalactic/Resources$.notValidPosFloat:()Ljava/lang/String;
         6: areturn

  public static java.lang.String rawNotLiteralPosLong();
    descriptor: ()Ljava/lang/String;
    flags: (0x0009) ACC_PUBLIC, ACC_STATIC
    Code:
      stack=1, locals=0, args_size=0
         0: getstatic     #16                 // Field org/scalactic/Resources$.MODULE$:Lorg/scalactic/Resources$;
         3: invokevirtual #405                // Method org/scalactic/Resources$.rawNotLiteralPosLong:()Ljava/lang/String;
         6: areturn

  public static java.lang.String notLiteralPosLong();
    descriptor: ()Ljava/lang/String;
    flags: (0x0009) ACC_PUBLIC, ACC_STATIC
    Code:
      stack=1, locals=0, args_size=0
         0: getstatic     #16                 // Field org/scalactic/Resources$.MODULE$:Lorg/scalactic/Resources$;
         3: invokevirtual #408                // Method org/scalactic/Resources$.notLiteralPosLong:()Ljava/lang/String;
         6: areturn

  public static java.lang.String rawNotValidPosLong();
    descriptor: ()Ljava/lang/String;
    flags: (0x0009) ACC_PUBLIC, ACC_STATIC
    Code:
      stack=1, locals=0, args_size=0
         0: getstatic     #16                 // Field org/scalactic/Resources$.MODULE$:Lorg/scalactic/Resources$;
         3: invokevirtual #411                // Method org/scalactic/Resources$.rawNotValidPosLong:()Ljava/lang/String;
         6: areturn

  public static java.lang.String notValidPosLong();
    descriptor: ()Ljava/lang/String;
    flags: (0x0009) ACC_PUBLIC, ACC_STATIC
    Code:
      stack=1, locals=0, args_size=0
         0: getstatic     #16                 // Field org/scalactic/Resources$.MODULE$:Lorg/scalactic/Resources$;
         3: invokevirtual #414                // Method org/scalactic/Resources$.notValidPosLong:()Ljava/lang/String;
         6: areturn

  public static java.lang.String rawNotLiteralPosInt();
    descriptor: ()Ljava/lang/String;
    flags: (0x0009) ACC_PUBLIC, ACC_STATIC
    Code:
      stack=1, locals=0, args_size=0
         0: getstatic     #16                 // Field org/scalactic/Resources$.MODULE$:Lorg/scalactic/Resources$;
         3: invokevirtual #417                // Method org/scalactic/Resources$.rawNotLiteralPosInt:()Ljava/lang/String;
         6: areturn

  public static java.lang.String notLiteralPosInt();
    descriptor: ()Ljava/lang/String;
    flags: (0x0009) ACC_PUBLIC, ACC_STATIC
    Code:
      stack=1, locals=0, args_size=0
         0: getstatic     #16                 // Field org/scalactic/Resources$.MODULE$:Lorg/scalactic/Resources$;
         3: invokevirtual #420                // Method org/scalactic/Resources$.notLiteralPosInt:()Ljava/lang/String;
         6: areturn

  public static java.lang.String rawNotValidPosInt();
    descriptor: ()Ljava/lang/String;
    flags: (0x0009) ACC_PUBLIC, ACC_STATIC
    Code:
      stack=1, locals=0, args_size=0
         0: getstatic     #16                 // Field org/scalactic/Resources$.MODULE$:Lorg/scalactic/Resources$;
         3: invokevirtual #423                // Method org/scalactic/Resources$.rawNotValidPosInt:()Ljava/lang/String;
         6: areturn

  public static java.lang.String notValidPosInt();
    descriptor: ()Ljava/lang/String;
    flags: (0x0009) ACC_PUBLIC, ACC_STATIC
    Code:
      stack=1, locals=0, args_size=0
         0: getstatic     #16                 // Field org/scalactic/Resources$.MODULE$:Lorg/scalactic/Resources$;
         3: invokevirtual #426                // Method org/scalactic/Resources$.notValidPosInt:()Ljava/lang/String;
         6: areturn

  public static java.lang.String rawVariableWasValue();
    descriptor: ()Ljava/lang/String;
    flags: (0x0009) ACC_PUBLIC, ACC_STATIC
    Code:
      stack=1, locals=0, args_size=0
         0: getstatic     #16                 // Field org/scalactic/Resources$.MODULE$:Lorg/scalactic/Resources$;
         3: invokevirtual #429                // Method org/scalactic/Resources$.rawVariableWasValue:()Ljava/lang/String;
         6: areturn

  public static java.lang.String variableWasValue(java.lang.Object, java.lang.Object);
    descriptor: (Ljava/lang/Object;Ljava/lang/Object;)Ljava/lang/String;
    flags: (0x0009) ACC_PUBLIC, ACC_STATIC
    Code:
      stack=3, locals=2, args_size=2
         0: getstatic     #16                 // Field org/scalactic/Resources$.MODULE$:Lorg/scalactic/Resources$;
         3: aload_0
         4: aload_1
         5: invokevirtual #434                // Method org/scalactic/Resources$.variableWasValue:(Ljava/lang/Object;Ljava/lang/Object;)Ljava/lang/String;
         8: areturn
      LocalVariableTable:
        Start  Length  Slot  Name   Signature
            0       9     0 param0   Ljava/lang/Object;
            0       9     1 param1   Ljava/lang/Object;
    MethodParameters:
      Name                           Flags
      param0                         final
      param1                         final

  public static java.lang.String rawCommaAnd();
    descriptor: ()Ljava/lang/String;
    flags: (0x0009) ACC_PUBLIC, ACC_STATIC
    Code:
      stack=1, locals=0, args_size=0
         0: getstatic     #16                 // Field org/scalactic/Resources$.MODULE$:Lorg/scalactic/Resources$;
         3: invokevirtual #437                // Method org/scalactic/Resources$.rawCommaAnd:()Ljava/lang/String;
         6: areturn

  public static java.lang.String commaAnd(java.lang.Object, java.lang.Object);
    descriptor: (Ljava/lang/Object;Ljava/lang/Object;)Ljava/lang/String;
    flags: (0x0009) ACC_PUBLIC, ACC_STATIC
    Code:
      stack=3, locals=2, args_size=2
         0: getstatic     #16                 // Field org/scalactic/Resources$.MODULE$:Lorg/scalactic/Resources$;
         3: aload_0
         4: aload_1
         5: invokevirtual #440                // Method org/scalactic/Resources$.commaAnd:(Ljava/lang/Object;Ljava/lang/Object;)Ljava/lang/String;
         8: areturn
      LocalVariableTable:
        Start  Length  Slot  Name   Signature
            0       9     0 param0   Ljava/lang/Object;
            0       9     1 param1   Ljava/lang/Object;
    MethodParameters:
      Name                           Flags
      param0                         final
      param1                         final

  public static java.lang.String rawCommaBut();
    descriptor: ()Ljava/lang/String;
    flags: (0x0009) ACC_PUBLIC, ACC_STATIC
    Code:
      stack=1, locals=0, args_size=0
         0: getstatic     #16                 // Field org/scalactic/Resources$.MODULE$:Lorg/scalactic/Resources$;
         3: invokevirtual #443                // Method org/scalactic/Resources$.rawCommaBut:()Ljava/lang/String;
         6: areturn

  public static java.lang.String commaBut(java.lang.Object, java.lang.Object);
    descriptor: (Ljava/lang/Object;Ljava/lang/Object;)Ljava/lang/String;
    flags: (0x0009) ACC_PUBLIC, ACC_STATIC
    Code:
      stack=3, locals=2, args_size=2
         0: getstatic     #16                 // Field org/scalactic/Resources$.MODULE$:Lorg/scalactic/Resources$;
         3: aload_0
         4: aload_1
         5: invokevirtual #446                // Method org/scalactic/Resources$.commaBut:(Ljava/lang/Object;Ljava/lang/Object;)Ljava/lang/String;
         8: areturn
      LocalVariableTable:
        Start  Length  Slot  Name   Signature
            0       9     0 param0   Ljava/lang/Object;
            0       9     1 param1   Ljava/lang/Object;
    MethodParameters:
      Name                           Flags
      param0                         final
      param1                         final

  public static java.lang.String rawHadSize();
    descriptor: ()Ljava/lang/String;
    flags: (0x0009) ACC_PUBLIC, ACC_STATIC
    Code:
      stack=1, locals=0, args_size=0
         0: getstatic     #16                 // Field org/scalactic/Resources$.MODULE$:Lorg/scalactic/Resources$;
         3: invokevirtual #449                // Method org/scalactic/Resources$.rawHadSize:()Ljava/lang/String;
         6: areturn

  public static java.lang.String hadSize(java.lang.Object, java.lang.Object);
    descriptor: (Ljava/lang/Object;Ljava/lang/Object;)Ljava/lang/String;
    flags: (0x0009) ACC_PUBLIC, ACC_STATIC
    Code:
      stack=3, locals=2, args_size=2
         0: getstatic     #16                 // Field org/scalactic/Resources$.MODULE$:Lorg/scalactic/Resources$;
         3: aload_0
         4: aload_1
         5: invokevirtual #452                // Method org/scalactic/Resources$.hadSize:(Ljava/lang/Object;Ljava/lang/Object;)Ljava/lang/String;
         8: areturn
      LocalVariableTable:
        Start  Length  Slot  Name   Signature
            0       9     0 param0   Ljava/lang/Object;
            0       9     1 param1   Ljava/lang/Object;
    MethodParameters:
      Name                           Flags
      param0                         final
      param1                         final

  public static java.lang.String rawHadSizeInsteadOfExpectedSize();
    descriptor: ()Ljava/lang/String;
    flags: (0x0009) ACC_PUBLIC, ACC_STATIC
    Code:
      stack=1, locals=0, args_size=0
         0: getstatic     #16                 // Field org/scalactic/Resources$.MODULE$:Lorg/scalactic/Resources$;
         3: invokevirtual #455                // Method org/scalactic/Resources$.rawHadSizeInsteadOfExpectedSize:()Ljava/lang/String;
         6: areturn

  public static java.lang.String hadSizeInsteadOfExpectedSize(java.lang.Object, java.lang.Object, java.lang.Object);
    descriptor: (Ljava/lang/Object;Ljava/lang/Object;Ljava/lang/Object;)Ljava/lang/String;
    flags: (0x0009) ACC_PUBLIC, ACC_STATIC
    Code:
      stack=4, locals=3, args_size=3
         0: getstatic     #16                 // Field org/scalactic/Resources$.MODULE$:Lorg/scalactic/Resources$;
         3: aload_0
         4: aload_1
         5: aload_2
         6: invokevirtual #460                // Method org/scalactic/Resources$.hadSizeInsteadOfExpectedSize:(Ljava/lang/Object;Ljava/lang/Object;Ljava/lang/Object;)Ljava/lang/String;
         9: areturn
      LocalVariableTable:
        Start  Length  Slot  Name   Signature
            0      10     0 param0   Ljava/lang/Object;
            0      10     1 param1   Ljava/lang/Object;
            0      10     2 param2   Ljava/lang/Object;
    MethodParameters:
      Name                           Flags
      param0                         final
      param1                         final
      param2                         final

  public static java.lang.String rawHadLength();
    descriptor: ()Ljava/lang/String;
    flags: (0x0009) ACC_PUBLIC, ACC_STATIC
    Code:
      stack=1, locals=0, args_size=0
         0: getstatic     #16                 // Field org/scalactic/Resources$.MODULE$:Lorg/scalactic/Resources$;
         3: invokevirtual #463                // Method org/scalactic/Resources$.rawHadLength:()Ljava/lang/String;
         6: areturn

  public static java.lang.String hadLength(java.lang.Object, java.lang.Object);
    descriptor: (Ljava/lang/Object;Ljava/lang/Object;)Ljava/lang/String;
    flags: (0x0009) ACC_PUBLIC, ACC_STATIC
    Code:
      stack=3, locals=2, args_size=2
         0: getstatic     #16                 // Field org/scalactic/Resources$.MODULE$:Lorg/scalactic/Resources$;
         3: aload_0
         4: aload_1
         5: invokevirtual #466                // Method org/scalactic/Resources$.hadLength:(Ljava/lang/Object;Ljava/lang/Object;)Ljava/lang/String;
         8: areturn
      LocalVariableTable:
        Start  Length  Slot  Name   Signature
            0       9     0 param0   Ljava/lang/Object;
            0       9     1 param1   Ljava/lang/Object;
    MethodParameters:
      Name                           Flags
      param0                         final
      param1                         final

  public static java.lang.String rawHadLengthInsteadOfExpectedLength();
    descriptor: ()Ljava/lang/String;
    flags: (0x0009) ACC_PUBLIC, ACC_STATIC
    Code:
      stack=1, locals=0, args_size=0
         0: getstatic     #16                 // Field org/scalactic/Resources$.MODULE$:Lorg/scalactic/Resources$;
         3: invokevirtual #469                // Method org/scalactic/Resources$.rawHadLengthInsteadOfExpectedLength:()Ljava/lang/String;
         6: areturn

  public static java.lang.String hadLengthInsteadOfExpectedLength(java.lang.Object, java.lang.Object, java.lang.Object);
    descriptor: (Ljava/lang/Object;Ljava/lang/Object;Ljava/lang/Object;)Ljava/lang/String;
    flags: (0x0009) ACC_PUBLIC, ACC_STATIC
    Code:
      stack=4, locals=3, args_size=3
         0: getstatic     #16                 // Field org/scalactic/Resources$.MODULE$:Lorg/scalactic/Resources$;
         3: aload_0
         4: aload_1
         5: aload_2
         6: invokevirtual #472                // Method org/scalactic/Resources$.hadLengthInsteadOfExpectedLength:(Ljava/lang/Object;Ljava/lang/Object;Ljava/lang/Object;)Ljava/lang/String;
         9: areturn
      LocalVariableTable:
        Start  Length  Slot  Name   Signature
            0      10     0 param0   Ljava/lang/Object;
            0      10     1 param1   Ljava/lang/Object;
            0      10     2 param2   Ljava/lang/Object;
    MethodParameters:
      Name                           Flags
      param0                         final
      param1                         final
      param2                         final

  public static java.lang.String rawWasInstanceOf();
    descriptor: ()Ljava/lang/String;
    flags: (0x0009) ACC_PUBLIC, ACC_STATIC
    Code:
      stack=1, locals=0, args_size=0
         0: getstatic     #16                 // Field org/scalactic/Resources$.MODULE$:Lorg/scalactic/Resources$;
         3: invokevirtual #475                // Method org/scalactic/Resources$.rawWasInstanceOf:()Ljava/lang/String;
         6: areturn

  public static java.lang.String wasInstanceOf(java.lang.Object, java.lang.Object);
    descriptor: (Ljava/lang/Object;Ljava/lang/Object;)Ljava/lang/String;
    flags: (0x0009) ACC_PUBLIC, ACC_STATIC
    Code:
      stack=3, locals=2, args_size=2
         0: getstatic     #16                 // Field org/scalactic/Resources$.MODULE$:Lorg/scalactic/Resources$;
         3: aload_0
         4: aload_1
         5: invokevirtual #478                // Method org/scalactic/Resources$.wasInstanceOf:(Ljava/lang/Object;Ljava/lang/Object;)Ljava/lang/String;
         8: areturn
      LocalVariableTable:
        Start  Length  Slot  Name   Signature
            0       9     0 param0   Ljava/lang/Object;
            0       9     1 param1   Ljava/lang/Object;
    MethodParameters:
      Name                           Flags
      param0                         final
      param1                         final

  public static java.lang.String rawWasNotInstanceOf();
    descriptor: ()Ljava/lang/String;
    flags: (0x0009) ACC_PUBLIC, ACC_STATIC
    Code:
      stack=1, locals=0, args_size=0
         0: getstatic     #16                 // Field org/scalactic/Resources$.MODULE$:Lorg/scalactic/Resources$;
         3: invokevirtual #481                // Method org/scalactic/Resources$.rawWasNotInstanceOf:()Ljava/lang/String;
         6: areturn

  public static java.lang.String wasNotInstanceOf(java.lang.Object, java.lang.Object);
    descriptor: (Ljava/lang/Object;Ljava/lang/Object;)Ljava/lang/String;
    flags: (0x0009) ACC_PUBLIC, ACC_STATIC
    Code:
      stack=3, locals=2, args_size=2
         0: getstatic     #16                 // Field org/scalactic/Resources$.MODULE$:Lorg/scalactic/Resources$;
         3: aload_0
         4: aload_1
         5: invokevirtual #484                // Method org/scalactic/Resources$.wasNotInstanceOf:(Ljava/lang/Object;Ljava/lang/Object;)Ljava/lang/String;
         8: areturn
      LocalVariableTable:
        Start  Length  Slot  Name   Signature
            0       9     0 param0   Ljava/lang/Object;
            0       9     1 param1   Ljava/lang/Object;
    MethodParameters:
      Name                           Flags
      param0                         final
      param1                         final

  public static java.lang.String rawWasEmpty();
    descriptor: ()Ljava/lang/String;
    flags: (0x0009) ACC_PUBLIC, ACC_STATIC
    Code:
      stack=1, locals=0, args_size=0
         0: getstatic     #16                 // Field org/scalactic/Resources$.MODULE$:Lorg/scalactic/Resources$;
         3: invokevirtual #487                // Method org/scalactic/Resources$.rawWasEmpty:()Ljava/lang/String;
         6: areturn

  public static java.lang.String wasEmpty(java.lang.Object);
    descriptor: (Ljava/lang/Object;)Ljava/lang/String;
    flags: (0x0009) ACC_PUBLIC, ACC_STATIC
    Code:
      stack=2, locals=1, args_size=1
         0: getstatic     #16                 // Field org/scalactic/Resources$.MODULE$:Lorg/scalactic/Resources$;
         3: aload_0
         4: invokevirtual #490                // Method org/scalactic/Resources$.wasEmpty:(Ljava/lang/Object;)Ljava/lang/String;
         7: areturn
      LocalVariableTable:
        Start  Length  Slot  Name   Signature
            0       8     0 param0   Ljava/lang/Object;
    MethodParameters:
      Name                           Flags
      param0                         final

  public static java.lang.String rawWasNotEmpty();
    descriptor: ()Ljava/lang/String;
    flags: (0x0009) ACC_PUBLIC, ACC_STATIC
    Code:
      stack=1, locals=0, args_size=0
         0: getstatic     #16                 // Field org/scalactic/Resources$.MODULE$:Lorg/scalactic/Resources$;
         3: invokevirtual #493                // Method org/scalactic/Resources$.rawWasNotEmpty:()Ljava/lang/String;
         6: areturn

  public static java.lang.String wasNotEmpty(java.lang.Object);
    descriptor: (Ljava/lang/Object;)Ljava/lang/String;
    flags: (0x0009) ACC_PUBLIC, ACC_STATIC
    Code:
      stack=2, locals=1, args_size=1
         0: getstatic     #16                 // Field org/scalactic/Resources$.MODULE$:Lorg/scalactic/Resources$;
         3: aload_0
         4: invokevirtual #496                // Method org/scalactic/Resources$.wasNotEmpty:(Ljava/lang/Object;)Ljava/lang/String;
         7: areturn
      LocalVariableTable:
        Start  Length  Slot  Name   Signature
            0       8     0 param0   Ljava/lang/Object;
    MethodParameters:
      Name                           Flags
      param0                         final

  public static java.lang.String rawWasNotTheSameInstanceAs();
    descriptor: ()Ljava/lang/String;
    flags: (0x0009) ACC_PUBLIC, ACC_STATIC
    Code:
      stack=1, locals=0, args_size=0
         0: getstatic     #16                 // Field org/scalactic/Resources$.MODULE$:Lorg/scalactic/Resources$;
         3: invokevirtual #499                // Method org/scalactic/Resources$.rawWasNotTheSameInstanceAs:()Ljava/lang/String;
         6: areturn

  public static java.lang.String wasNotTheSameInstanceAs(java.lang.Object, java.lang.Object);
    descriptor: (Ljava/lang/Object;Ljava/lang/Object;)Ljava/lang/String;
    flags: (0x0009) ACC_PUBLIC, ACC_STATIC
    Code:
      stack=3, locals=2, args_size=2
         0: getstatic     #16                 // Field org/scalactic/Resources$.MODULE$:Lorg/scalactic/Resources$;
         3: aload_0
         4: aload_1
         5: invokevirtual #502                // Method org/scalactic/Resources$.wasNotTheSameInstanceAs:(Ljava/lang/Object;Ljava/lang/Object;)Ljava/lang/String;
         8: areturn
      LocalVariableTable:
        Start  Length  Slot  Name   Signature
            0       9     0 param0   Ljava/lang/Object;
            0       9     1 param1   Ljava/lang/Object;
    MethodParameters:
      Name                           Flags
      param0                         final
      param1                         final

  public static java.lang.String rawWasTheSameInstanceAs();
    descriptor: ()Ljava/lang/String;
    flags: (0x0009) ACC_PUBLIC, ACC_STATIC
    Code:
      stack=1, locals=0, args_size=0
         0: getstatic     #16                 // Field org/scalactic/Resources$.MODULE$:Lorg/scalactic/Resources$;
         3: invokevirtual #505                // Method org/scalactic/Resources$.rawWasTheSameInstanceAs:()Ljava/lang/String;
         6: areturn

  public static java.lang.String wasTheSameInstanceAs(java.lang.Object, java.lang.Object);
    descriptor: (Ljava/lang/Object;Ljava/lang/Object;)Ljava/lang/String;
    flags: (0x0009) ACC_PUBLIC, ACC_STATIC
    Code:
      stack=3, locals=2, args_size=2
         0: getstatic     #16                 // Field org/scalactic/Resources$.MODULE$:Lorg/scalactic/Resources$;
         3: aload_0
         4: aload_1
         5: invokevirtual #508                // Method org/scalactic/Resources$.wasTheSameInstanceAs:(Ljava/lang/Object;Ljava/lang/Object;)Ljava/lang/String;
         8: areturn
      LocalVariableTable:
        Start  Length  Slot  Name   Signature
            0       9     0 param0   Ljava/lang/Object;
            0       9     1 param1   Ljava/lang/Object;
    MethodParameters:
      Name                           Flags
      param0                         final
      param1                         final

  public static java.lang.String rawContainedKey();
    descriptor: ()Ljava/lang/String;
    flags: (0x0009) ACC_PUBLIC, ACC_STATIC
    Code:
      stack=1, locals=0, args_size=0
         0: getstatic     #16                 // Field org/scalactic/Resources$.MODULE$:Lorg/scalactic/Resources$;
         3: invokevirtual #511                // Method org/scalactic/Resources$.rawContainedKey:()Ljava/lang/String;
         6: areturn

  public static java.lang.String containedKey(java.lang.Object, java.lang.Object);
    descriptor: (Ljava/lang/Object;Ljava/lang/Object;)Ljava/lang/String;
    flags: (0x0009) ACC_PUBLIC, ACC_STATIC
    Code:
      stack=3, locals=2, args_size=2
         0: getstatic     #16                 // Field org/scalactic/Resources$.MODULE$:Lorg/scalactic/Resources$;
         3: aload_0
         4: aload_1
         5: invokevirtual #514                // Method org/scalactic/Resources$.containedKey:(Ljava/lang/Object;Ljava/lang/Object;)Ljava/lang/String;
         8: areturn
      LocalVariableTable:
        Start  Length  Slot  Name   Signature
            0       9     0 param0   Ljava/lang/Object;
            0       9     1 param1   Ljava/lang/Object;
    MethodParameters:
      Name                           Flags
      param0                         final
      param1                         final

  public static java.lang.String rawDidNotContainKey();
    descriptor: ()Ljava/lang/String;
    flags: (0x0009) ACC_PUBLIC, ACC_STATIC
    Code:
      stack=1, locals=0, args_size=0
         0: getstatic     #16                 // Field org/scalactic/Resources$.MODULE$:Lorg/scalactic/Resources$;
         3: invokevirtual #517                // Method org/scalactic/Resources$.rawDidNotContainKey:()Ljava/lang/String;
         6: areturn

  public static java.lang.String didNotContainKey(java.lang.Object, java.lang.Object);
    descriptor: (Ljava/lang/Object;Ljava/lang/Object;)Ljava/lang/String;
    flags: (0x0009) ACC_PUBLIC, ACC_STATIC
    Code:
      stack=3, locals=2, args_size=2
         0: getstatic     #16                 // Field org/scalactic/Resources$.MODULE$:Lorg/scalactic/Resources$;
         3: aload_0
         4: aload_1
         5: invokevirtual #520                // Method org/scalactic/Resources$.didNotContainKey:(Ljava/lang/Object;Ljava/lang/Object;)Ljava/lang/String;
         8: areturn
      LocalVariableTable:
        Start  Length  Slot  Name   Signature
            0       9     0 param0   Ljava/lang/Object;
            0       9     1 param1   Ljava/lang/Object;
    MethodParameters:
      Name                           Flags
      param0                         final
      param1                         final

  public static java.lang.String rawContained();
    descriptor: ()Ljava/lang/String;
    flags: (0x0009) ACC_PUBLIC, ACC_STATIC
    Code:
      stack=1, locals=0, args_size=0
         0: getstatic     #16                 // Field org/scalactic/Resources$.MODULE$:Lorg/scalactic/Resources$;
         3: invokevirtual #523                // Method org/scalactic/Resources$.rawContained:()Ljava/lang/String;
         6: areturn

  public static java.lang.String contained(java.lang.Object, java.lang.Object);
    descriptor: (Ljava/lang/Object;Ljava/lang/Object;)Ljava/lang/String;
    flags: (0x0009) ACC_PUBLIC, ACC_STATIC
    Code:
      stack=3, locals=2, args_size=2
         0: getstatic     #16                 // Field org/scalactic/Resources$.MODULE$:Lorg/scalactic/Resources$;
         3: aload_0
         4: aload_1
         5: invokevirtual #526                // Method org/scalactic/Resources$.contained:(Ljava/lang/Object;Ljava/lang/Object;)Ljava/lang/String;
         8: areturn
      LocalVariableTable:
        Start  Length  Slot  Name   Signature
            0       9     0 param0   Ljava/lang/Object;
            0       9     1 param1   Ljava/lang/Object;
    MethodParameters:
      Name                           Flags
      param0                         final
      param1                         final

  public static java.lang.String rawDidNotContain();
    descriptor: ()Ljava/lang/String;
    flags: (0x0009) ACC_PUBLIC, ACC_STATIC
    Code:
      stack=1, locals=0, args_size=0
         0: getstatic     #16                 // Field org/scalactic/Resources$.MODULE$:Lorg/scalactic/Resources$;
         3: invokevirtual #529                // Method org/scalactic/Resources$.rawDidNotContain:()Ljava/lang/String;
         6: areturn

  public static java.lang.String didNotContain(java.lang.Object, java.lang.Object);
    descriptor: (Ljava/lang/Object;Ljava/lang/Object;)Ljava/lang/String;
    flags: (0x0009) ACC_PUBLIC, ACC_STATIC
    Code:
      stack=3, locals=2, args_size=2
         0: getstatic     #16                 // Field org/scalactic/Resources$.MODULE$:Lorg/scalactic/Resources$;
         3: aload_0
         4: aload_1
         5: invokevirtual #532                // Method org/scalactic/Resources$.didNotContain:(Ljava/lang/Object;Ljava/lang/Object;)Ljava/lang/String;
         8: areturn
      LocalVariableTable:
        Start  Length  Slot  Name   Signature
            0       9     0 param0   Ljava/lang/Object;
            0       9     1 param1   Ljava/lang/Object;
    MethodParameters:
      Name                           Flags
      param0                         final
      param1                         final

  public static java.lang.String rawEndedWith();
    descriptor: ()Ljava/lang/String;
    flags: (0x0009) ACC_PUBLIC, ACC_STATIC
    Code:
      stack=1, locals=0, args_size=0
         0: getstatic     #16                 // Field org/scalactic/Resources$.MODULE$:Lorg/scalactic/Resources$;
         3: invokevirtual #535                // Method org/scalactic/Resources$.rawEndedWith:()Ljava/lang/String;
         6: areturn

  public static java.lang.String endedWith(java.lang.Object, java.lang.Object);
    descriptor: (Ljava/lang/Object;Ljava/lang/Object;)Ljava/lang/String;
    flags: (0x0009) ACC_PUBLIC, ACC_STATIC
    Code:
      stack=3, locals=2, args_size=2
         0: getstatic     #16                 // Field org/scalactic/Resources$.MODULE$:Lorg/scalactic/Resources$;
         3: aload_0
         4: aload_1
         5: invokevirtual #538                // Method org/scalactic/Resources$.endedWith:(Ljava/lang/Object;Ljava/lang/Object;)Ljava/lang/String;
         8: areturn
      LocalVariableTable:
        Start  Length  Slot  Name   Signature
            0       9     0 param0   Ljava/lang/Object;
            0       9     1 param1   Ljava/lang/Object;
    MethodParameters:
      Name                           Flags
      param0                         final
      param1                         final

  public static java.lang.String rawDidNotEndWith();
    descriptor: ()Ljava/lang/String;
    flags: (0x0009) ACC_PUBLIC, ACC_STATIC
    Code:
      stack=1, locals=0, args_size=0
         0: getstatic     #16                 // Field org/scalactic/Resources$.MODULE$:Lorg/scalactic/Resources$;
         3: invokevirtual #541                // Method org/scalactic/Resources$.rawDidNotEndWith:()Ljava/lang/String;
         6: areturn

  public static java.lang.String didNotEndWith(java.lang.Object, java.lang.Object);
    descriptor: (Ljava/lang/Object;Ljava/lang/Object;)Ljava/lang/String;
    flags: (0x0009) ACC_PUBLIC, ACC_STATIC
    Code:
      stack=3, locals=2, args_size=2
         0: getstatic     #16                 // Field org/scalactic/Resources$.MODULE$:Lorg/scalactic/Resources$;
         3: aload_0
         4: aload_1
         5: invokevirtual #544                // Method org/scalactic/Resources$.didNotEndWith:(Ljava/lang/Object;Ljava/lang/Object;)Ljava/lang/String;
         8: areturn
      LocalVariableTable:
        Start  Length  Slot  Name   Signature
            0       9     0 param0   Ljava/lang/Object;
            0       9     1 param1   Ljava/lang/Object;
    MethodParameters:
      Name                           Flags
      param0                         final
      param1                         final

  public static java.lang.String rawStartedWith();
    descriptor: ()Ljava/lang/String;
    flags: (0x0009) ACC_PUBLIC, ACC_STATIC
    Code:
      stack=1, locals=0, args_size=0
         0: getstatic     #16                 // Field org/scalactic/Resources$.MODULE$:Lorg/scalactic/Resources$;
         3: invokevirtual #547                // Method org/scalactic/Resources$.rawStartedWith:()Ljava/lang/String;
         6: areturn

  public static java.lang.String startedWith(java.lang.Object, java.lang.Object);
    descriptor: (Ljava/lang/Object;Ljava/lang/Object;)Ljava/lang/String;
    flags: (0x0009) ACC_PUBLIC, ACC_STATIC
    Code:
      stack=3, locals=2, args_size=2
         0: getstatic     #16                 // Field org/scalactic/Resources$.MODULE$:Lorg/scalactic/Resources$;
         3: aload_0
         4: aload_1
         5: invokevirtual #550                // Method org/scalactic/Resources$.startedWith:(Ljava/lang/Object;Ljava/lang/Object;)Ljava/lang/String;
         8: areturn
      LocalVariableTable:
        Start  Length  Slot  Name   Signature
            0       9     0 param0   Ljava/lang/Object;
            0       9     1 param1   Ljava/lang/Object;
    MethodParameters:
      Name                           Flags
      param0                         final
      param1                         final

  public static java.lang.String rawDidNotStartWith();
    descriptor: ()Ljava/lang/String;
    flags: (0x0009) ACC_PUBLIC, ACC_STATIC
    Code:
      stack=1, locals=0, args_size=0
         0: getstatic     #16                 // Field org/scalactic/Resources$.MODULE$:Lorg/scalactic/Resources$;
         3: invokevirtual #553                // Method org/scalactic/Resources$.rawDidNotStartWith:()Ljava/lang/String;
         6: areturn

  public static java.lang.String didNotStartWith(java.lang.Object, java.lang.Object);
    descriptor: (Ljava/lang/Object;Ljava/lang/Object;)Ljava/lang/String;
    flags: (0x0009) ACC_PUBLIC, ACC_STATIC
    Code:
      stack=3, locals=2, args_size=2
         0: getstatic     #16                 // Field org/scalactic/Resources$.MODULE$:Lorg/scalactic/Resources$;
         3: aload_0
         4: aload_1
         5: invokevirtual #556                // Method org/scalactic/Resources$.didNotStartWith:(Ljava/lang/Object;Ljava/lang/Object;)Ljava/lang/String;
         8: areturn
      LocalVariableTable:
        Start  Length  Slot  Name   Signature
            0       9     0 param0   Ljava/lang/Object;
            0       9     1 param1   Ljava/lang/Object;
    MethodParameters:
      Name                           Flags
      param0                         final
      param1                         final

  public static java.lang.String rawWasNotGreaterThanOrEqualTo();
    descriptor: ()Ljava/lang/String;
    flags: (0x0009) ACC_PUBLIC, ACC_STATIC
    Code:
      stack=1, locals=0, args_size=0
         0: getstatic     #16                 // Field org/scalactic/Resources$.MODULE$:Lorg/scalactic/Resources$;
         3: invokevirtual #559                // Method org/scalactic/Resources$.rawWasNotGreaterThanOrEqualTo:()Ljava/lang/String;
         6: areturn

  public static java.lang.String wasNotGreaterThanOrEqualTo(java.lang.Object, java.lang.Object);
    descriptor: (Ljava/lang/Object;Ljava/lang/Object;)Ljava/lang/String;
    flags: (0x0009) ACC_PUBLIC, ACC_STATIC
    Code:
      stack=3, locals=2, args_size=2
         0: getstatic     #16                 // Field org/scalactic/Resources$.MODULE$:Lorg/scalactic/Resources$;
         3: aload_0
         4: aload_1
         5: invokevirtual #562                // Method org/scalactic/Resources$.wasNotGreaterThanOrEqualTo:(Ljava/lang/Object;Ljava/lang/Object;)Ljava/lang/String;
         8: areturn
      LocalVariableTable:
        Start  Length  Slot  Name   Signature
            0       9     0 param0   Ljava/lang/Object;
            0       9     1 param1   Ljava/lang/Object;
    MethodParameters:
      Name                           Flags
      param0                         final
      param1                         final

  public static java.lang.String rawWasGreaterThanOrEqualTo();
    descriptor: ()Ljava/lang/String;
    flags: (0x0009) ACC_PUBLIC, ACC_STATIC
    Code:
      stack=1, locals=0, args_size=0
         0: getstatic     #16                 // Field org/scalactic/Resources$.MODULE$:Lorg/scalactic/Resources$;
         3: invokevirtual #565                // Method org/scalactic/Resources$.rawWasGreaterThanOrEqualTo:()Ljava/lang/String;
         6: areturn

  public static java.lang.String wasGreaterThanOrEqualTo(java.lang.Object, java.lang.Object);
    descriptor: (Ljava/lang/Object;Ljava/lang/Object;)Ljava/lang/String;
    flags: (0x0009) ACC_PUBLIC, ACC_STATIC
    Code:
      stack=3, locals=2, args_size=2
         0: getstatic     #16                 // Field org/scalactic/Resources$.MODULE$:Lorg/scalactic/Resources$;
         3: aload_0
         4: aload_1
         5: invokevirtual #568                // Method org/scalactic/Resources$.wasGreaterThanOrEqualTo:(Ljava/lang/Object;Ljava/lang/Object;)Ljava/lang/String;
         8: areturn
      LocalVariableTable:
        Start  Length  Slot  Name   Signature
            0       9     0 param0   Ljava/lang/Object;
            0       9     1 param1   Ljava/lang/Object;
    MethodParameters:
      Name                           Flags
      param0                         final
      param1                         final

  public static java.lang.String rawWasNotLessThanOrEqualTo();
    descriptor: ()Ljava/lang/String;
    flags: (0x0009) ACC_PUBLIC, ACC_STATIC
    Code:
      stack=1, locals=0, args_size=0
         0: getstatic     #16                 // Field org/scalactic/Resources$.MODULE$:Lorg/scalactic/Resources$;
         3: invokevirtual #571                // Method org/scalactic/Resources$.rawWasNotLessThanOrEqualTo:()Ljava/lang/String;
         6: areturn

  public static java.lang.String wasNotLessThanOrEqualTo(java.lang.Object, java.lang.Object);
    descriptor: (Ljava/lang/Object;Ljava/lang/Object;)Ljava/lang/String;
    flags: (0x0009) ACC_PUBLIC, ACC_STATIC
    Code:
      stack=3, locals=2, args_size=2
         0: getstatic     #16                 // Field org/scalactic/Resources$.MODULE$:Lorg/scalactic/Resources$;
         3: aload_0
         4: aload_1
         5: invokevirtual #574                // Method org/scalactic/Resources$.wasNotLessThanOrEqualTo:(Ljava/lang/Object;Ljava/lang/Object;)Ljava/lang/String;
         8: areturn
      LocalVariableTable:
        Start  Length  Slot  Name   Signature
            0       9     0 param0   Ljava/lang/Object;
            0       9     1 param1   Ljava/lang/Object;
    MethodParameters:
      Name                           Flags
      param0                         final
      param1                         final

  public static java.lang.String rawWasLessThanOrEqualTo();
    descriptor: ()Ljava/lang/String;
    flags: (0x0009) ACC_PUBLIC, ACC_STATIC
    Code:
      stack=1, locals=0, args_size=0
         0: getstatic     #16                 // Field org/scalactic/Resources$.MODULE$:Lorg/scalactic/Resources$;
         3: invokevirtual #577                // Method org/scalactic/Resources$.rawWasLessThanOrEqualTo:()Ljava/lang/String;
         6: areturn

  public static java.lang.String wasLessThanOrEqualTo(java.lang.Object, java.lang.Object);
    descriptor: (Ljava/lang/Object;Ljava/lang/Object;)Ljava/lang/String;
    flags: (0x0009) ACC_PUBLIC, ACC_STATIC
    Code:
      stack=3, locals=2, args_size=2
         0: getstatic     #16                 // Field org/scalactic/Resources$.MODULE$:Lorg/scalactic/Resources$;
         3: aload_0
         4: aload_1
         5: invokevirtual #580                // Method org/scalactic/Resources$.wasLessThanOrEqualTo:(Ljava/lang/Object;Ljava/lang/Object;)Ljava/lang/String;
         8: areturn
      LocalVariableTable:
        Start  Length  Slot  Name   Signature
            0       9     0 param0   Ljava/lang/Object;
            0       9     1 param1   Ljava/lang/Object;
    MethodParameters:
      Name                           Flags
      param0                         final
      param1                         final

  public static java.lang.String rawWasNotGreaterThan();
    descriptor: ()Ljava/lang/String;
    flags: (0x0009) ACC_PUBLIC, ACC_STATIC
    Code:
      stack=1, locals=0, args_size=0
         0: getstatic     #16                 // Field org/scalactic/Resources$.MODULE$:Lorg/scalactic/Resources$;
         3: invokevirtual #583                // Method org/scalactic/Resources$.rawWasNotGreaterThan:()Ljava/lang/String;
         6: areturn

  public static java.lang.String wasNotGreaterThan(java.lang.Object, java.lang.Object);
    descriptor: (Ljava/lang/Object;Ljava/lang/Object;)Ljava/lang/String;
    flags: (0x0009) ACC_PUBLIC, ACC_STATIC
    Code:
      stack=3, locals=2, args_size=2
         0: getstatic     #16                 // Field org/scalactic/Resources$.MODULE$:Lorg/scalactic/Resources$;
         3: aload_0
         4: aload_1
         5: invokevirtual #586                // Method org/scalactic/Resources$.wasNotGreaterThan:(Ljava/lang/Object;Ljava/lang/Object;)Ljava/lang/String;
         8: areturn
      LocalVariableTable:
        Start  Length  Slot  Name   Signature
            0       9     0 param0   Ljava/lang/Object;
            0       9     1 param1   Ljava/lang/Object;
    MethodParameters:
      Name                           Flags
      param0                         final
      param1                         final

  public static java.lang.String rawWasGreaterThan();
    descriptor: ()Ljava/lang/String;
    flags: (0x0009) ACC_PUBLIC, ACC_STATIC
    Code:
      stack=1, locals=0, args_size=0
         0: getstatic     #16                 // Field org/scalactic/Resources$.MODULE$:Lorg/scalactic/Resources$;
         3: invokevirtual #589                // Method org/scalactic/Resources$.rawWasGreaterThan:()Ljava/lang/String;
         6: areturn

  public static java.lang.String wasGreaterThan(java.lang.Object, java.lang.Object);
    descriptor: (Ljava/lang/Object;Ljava/lang/Object;)Ljava/lang/String;
    flags: (0x0009) ACC_PUBLIC, ACC_STATIC
    Code:
      stack=3, locals=2, args_size=2
         0: getstatic     #16                 // Field org/scalactic/Resources$.MODULE$:Lorg/scalactic/Resources$;
         3: aload_0
         4: aload_1
         5: invokevirtual #592                // Method org/scalactic/Resources$.wasGreaterThan:(Ljava/lang/Object;Ljava/lang/Object;)Ljava/lang/String;
         8: areturn
      LocalVariableTable:
        Start  Length  Slot  Name   Signature
            0       9     0 param0   Ljava/lang/Object;
            0       9     1 param1   Ljava/lang/Object;
    MethodParameters:
      Name                           Flags
      param0                         final
      param1                         final

  public static java.lang.String rawWasNotLessThan();
    descriptor: ()Ljava/lang/String;
    flags: (0x0009) ACC_PUBLIC, ACC_STATIC
    Code:
      stack=1, locals=0, args_size=0
         0: getstatic     #16                 // Field org/scalactic/Resources$.MODULE$:Lorg/scalactic/Resources$;
         3: invokevirtual #595                // Method org/scalactic/Resources$.rawWasNotLessThan:()Ljava/lang/String;
         6: areturn

  public static java.lang.String wasNotLessThan(java.lang.Object, java.lang.Object);
    descriptor: (Ljava/lang/Object;Ljava/lang/Object;)Ljava/lang/String;
    flags: (0x0009) ACC_PUBLIC, ACC_STATIC
    Code:
      stack=3, locals=2, args_size=2
         0: getstatic     #16                 // Field org/scalactic/Resources$.MODULE$:Lorg/scalactic/Resources$;
         3: aload_0
         4: aload_1
         5: invokevirtual #598                // Method org/scalactic/Resources$.wasNotLessThan:(Ljava/lang/Object;Ljava/lang/Object;)Ljava/lang/String;
         8: areturn
      LocalVariableTable:
        Start  Length  Slot  Name   Signature
            0       9     0 param0   Ljava/lang/Object;
            0       9     1 param1   Ljava/lang/Object;
    MethodParameters:
      Name                           Flags
      param0                         final
      param1                         final

  public static java.lang.String rawWasLessThan();
    descriptor: ()Ljava/lang/String;
    flags: (0x0009) ACC_PUBLIC, ACC_STATIC
    Code:
      stack=1, locals=0, args_size=0
         0: getstatic     #16                 // Field org/scalactic/Resources$.MODULE$:Lorg/scalactic/Resources$;
         3: invokevirtual #601                // Method org/scalactic/Resources$.rawWasLessThan:()Ljava/lang/String;
         6: areturn

  public static java.lang.String wasLessThan(java.lang.Object, java.lang.Object);
    descriptor: (Ljava/lang/Object;Ljava/lang/Object;)Ljava/lang/String;
    flags: (0x0009) ACC_PUBLIC, ACC_STATIC
    Code:
      stack=3, locals=2, args_size=2
         0: getstatic     #16                 // Field org/scalactic/Resources$.MODULE$:Lorg/scalactic/Resources$;
         3: aload_0
         4: aload_1
         5: invokevirtual #604                // Method org/scalactic/Resources$.wasLessThan:(Ljava/lang/Object;Ljava/lang/Object;)Ljava/lang/String;
         8: areturn
      LocalVariableTable:
        Start  Length  Slot  Name   Signature
            0       9     0 param0   Ljava/lang/Object;
            0       9     1 param1   Ljava/lang/Object;
    MethodParameters:
      Name                           Flags
      param0                         final
      param1                         final

  public static java.lang.String rawWasFalse();
    descriptor: ()Ljava/lang/String;
    flags: (0x0009) ACC_PUBLIC, ACC_STATIC
    Code:
      stack=1, locals=0, args_size=0
         0: getstatic     #16                 // Field org/scalactic/Resources$.MODULE$:Lorg/scalactic/Resources$;
         3: invokevirtual #607                // Method org/scalactic/Resources$.rawWasFalse:()Ljava/lang/String;
         6: areturn

  public static java.lang.String wasFalse(java.lang.Object);
    descriptor: (Ljava/lang/Object;)Ljava/lang/String;
    flags: (0x0009) ACC_PUBLIC, ACC_STATIC
    Code:
      stack=2, locals=1, args_size=1
         0: getstatic     #16                 // Field org/scalactic/Resources$.MODULE$:Lorg/scalactic/Resources$;
         3: aload_0
         4: invokevirtual #610                // Method org/scalactic/Resources$.wasFalse:(Ljava/lang/Object;)Ljava/lang/String;
         7: areturn
      LocalVariableTable:
        Start  Length  Slot  Name   Signature
            0       8     0 param0   Ljava/lang/Object;
    MethodParameters:
      Name                           Flags
      param0                         final

  public static java.lang.String rawWasTrue();
    descriptor: ()Ljava/lang/String;
    flags: (0x0009) ACC_PUBLIC, ACC_STATIC
    Code:
      stack=1, locals=0, args_size=0
         0: getstatic     #16                 // Field org/scalactic/Resources$.MODULE$:Lorg/scalactic/Resources$;
         3: invokevirtual #613                // Method org/scalactic/Resources$.rawWasTrue:()Ljava/lang/String;
         6: areturn

  public static java.lang.String wasTrue(java.lang.Object);
    descriptor: (Ljava/lang/Object;)Ljava/lang/String;
    flags: (0x0009) ACC_PUBLIC, ACC_STATIC
    Code:
      stack=2, locals=1, args_size=1
         0: getstatic     #16                 // Field org/scalactic/Resources$.MODULE$:Lorg/scalactic/Resources$;
         3: aload_0
         4: invokevirtual #616                // Method org/scalactic/Resources$.wasTrue:(Ljava/lang/Object;)Ljava/lang/String;
         7: areturn
      LocalVariableTable:
        Start  Length  Slot  Name   Signature
            0       8     0 param0   Ljava/lang/Object;
    MethodParameters:
      Name                           Flags
      param0                         final

  public static java.lang.String rawAnd();
    descriptor: ()Ljava/lang/String;
    flags: (0x0009) ACC_PUBLIC, ACC_STATIC
    Code:
      stack=1, locals=0, args_size=0
         0: getstatic     #16                 // Field org/scalactic/Resources$.MODULE$:Lorg/scalactic/Resources$;
         3: invokevirtual #619                // Method org/scalactic/Resources$.rawAnd:()Ljava/lang/String;
         6: areturn

  public static java.lang.String and(java.lang.Object, java.lang.Object);
    descriptor: (Ljava/lang/Object;Ljava/lang/Object;)Ljava/lang/String;
    flags: (0x0009) ACC_PUBLIC, ACC_STATIC
    Code:
      stack=3, locals=2, args_size=2
         0: getstatic     #16                 // Field org/scalactic/Resources$.MODULE$:Lorg/scalactic/Resources$;
         3: aload_0
         4: aload_1
         5: invokevirtual #622                // Method org/scalactic/Resources$.and:(Ljava/lang/Object;Ljava/lang/Object;)Ljava/lang/String;
         8: areturn
      LocalVariableTable:
        Start  Length  Slot  Name   Signature
            0       9     0 param0   Ljava/lang/Object;
            0       9     1 param1   Ljava/lang/Object;
    MethodParameters:
      Name                           Flags
      param0                         final
      param1                         final

  public static java.lang.String rawComma();
    descriptor: ()Ljava/lang/String;
    flags: (0x0009) ACC_PUBLIC, ACC_STATIC
    Code:
      stack=1, locals=0, args_size=0
         0: getstatic     #16                 // Field org/scalactic/Resources$.MODULE$:Lorg/scalactic/Resources$;
         3: invokevirtual #625                // Method org/scalactic/Resources$.rawComma:()Ljava/lang/String;
         6: areturn

  public static java.lang.String comma();
    descriptor: ()Ljava/lang/String;
    flags: (0x0009) ACC_PUBLIC, ACC_STATIC
    Code:
      stack=1, locals=0, args_size=0
         0: getstatic     #16                 // Field org/scalactic/Resources$.MODULE$:Lorg/scalactic/Resources$;
         3: invokevirtual #628                // Method org/scalactic/Resources$.comma:()Ljava/lang/String;
         6: areturn

  public static java.lang.String rawWereNull();
    descriptor: ()Ljava/lang/String;
    flags: (0x0009) ACC_PUBLIC, ACC_STATIC
    Code:
      stack=1, locals=0, args_size=0
         0: getstatic     #16                 // Field org/scalactic/Resources$.MODULE$:Lorg/scalactic/Resources$;
         3: invokevirtual #631                // Method org/scalactic/Resources$.rawWereNull:()Ljava/lang/String;
         6: areturn

  public static java.lang.String wereNull(java.lang.Object);
    descriptor: (Ljava/lang/Object;)Ljava/lang/String;
    flags: (0x0009) ACC_PUBLIC, ACC_STATIC
    Code:
      stack=2, locals=1, args_size=1
         0: getstatic     #16                 // Field org/scalactic/Resources$.MODULE$:Lorg/scalactic/Resources$;
         3: aload_0
         4: invokevirtual #634                // Method org/scalactic/Resources$.wereNull:(Ljava/lang/Object;)Ljava/lang/String;
         7: areturn
      LocalVariableTable:
        Start  Length  Slot  Name   Signature
            0       8     0 param0   Ljava/lang/Object;
    MethodParameters:
      Name                           Flags
      param0                         final

  public static java.lang.String rawWasNull();
    descriptor: ()Ljava/lang/String;
    flags: (0x0009) ACC_PUBLIC, ACC_STATIC
    Code:
      stack=1, locals=0, args_size=0
         0: getstatic     #16                 // Field org/scalactic/Resources$.MODULE$:Lorg/scalactic/Resources$;
         3: invokevirtual #637                // Method org/scalactic/Resources$.rawWasNull:()Ljava/lang/String;
         6: areturn

  public static java.lang.String wasNull(java.lang.Object);
    descriptor: (Ljava/lang/Object;)Ljava/lang/String;
    flags: (0x0009) ACC_PUBLIC, ACC_STATIC
    Code:
      stack=2, locals=1, args_size=1
         0: getstatic     #16                 // Field org/scalactic/Resources$.MODULE$:Lorg/scalactic/Resources$;
         3: aload_0
         4: invokevirtual #640                // Method org/scalactic/Resources$.wasNull:(Ljava/lang/Object;)Ljava/lang/String;
         7: areturn
      LocalVariableTable:
        Start  Length  Slot  Name   Signature
            0       8     0 param0   Ljava/lang/Object;
    MethodParameters:
      Name                           Flags
      param0                         final

  public static java.lang.String rawExpressionWasTrue();
    descriptor: ()Ljava/lang/String;
    flags: (0x0009) ACC_PUBLIC, ACC_STATIC
    Code:
      stack=1, locals=0, args_size=0
         0: getstatic     #16                 // Field org/scalactic/Resources$.MODULE$:Lorg/scalactic/Resources$;
         3: invokevirtual #643                // Method org/scalactic/Resources$.rawExpressionWasTrue:()Ljava/lang/String;
         6: areturn

  public static java.lang.String expressionWasTrue();
    descriptor: ()Ljava/lang/String;
    flags: (0x0009) ACC_PUBLIC, ACC_STATIC
    Code:
      stack=1, locals=0, args_size=0
         0: getstatic     #16                 // Field org/scalactic/Resources$.MODULE$:Lorg/scalactic/Resources$;
         3: invokevirtual #646                // Method org/scalactic/Resources$.expressionWasTrue:()Ljava/lang/String;
         6: areturn

  public static java.lang.String rawExpressionWasFalse();
    descriptor: ()Ljava/lang/String;
    flags: (0x0009) ACC_PUBLIC, ACC_STATIC
    Code:
      stack=1, locals=0, args_size=0
         0: getstatic     #16                 // Field org/scalactic/Resources$.MODULE$:Lorg/scalactic/Resources$;
         3: invokevirtual #649                // Method org/scalactic/Resources$.rawExpressionWasFalse:()Ljava/lang/String;
         6: areturn

  public static java.lang.String expressionWasFalse();
    descriptor: ()Ljava/lang/String;
    flags: (0x0009) ACC_PUBLIC, ACC_STATIC
    Code:
      stack=1, locals=0, args_size=0
         0: getstatic     #16                 // Field org/scalactic/Resources$.MODULE$:Lorg/scalactic/Resources$;
         3: invokevirtual #652                // Method org/scalactic/Resources$.expressionWasFalse:()Ljava/lang/String;
         6: areturn

  public static java.lang.String rawWasNotPlusOrMinus();
    descriptor: ()Ljava/lang/String;
    flags: (0x0009) ACC_PUBLIC, ACC_STATIC
    Code:
      stack=1, locals=0, args_size=0
         0: getstatic     #16                 // Field org/scalactic/Resources$.MODULE$:Lorg/scalactic/Resources$;
         3: invokevirtual #655                // Method org/scalactic/Resources$.rawWasNotPlusOrMinus:()Ljava/lang/String;
         6: areturn

  public static java.lang.String wasNotPlusOrMinus(java.lang.Object, java.lang.Object, java.lang.Object);
    descriptor: (Ljava/lang/Object;Ljava/lang/Object;Ljava/lang/Object;)Ljava/lang/String;
    flags: (0x0009) ACC_PUBLIC, ACC_STATIC
    Code:
      stack=4, locals=3, args_size=3
         0: getstatic     #16                 // Field org/scalactic/Resources$.MODULE$:Lorg/scalactic/Resources$;
         3: aload_0
         4: aload_1
         5: aload_2
         6: invokevirtual #658                // Method org/scalactic/Resources$.wasNotPlusOrMinus:(Ljava/lang/Object;Ljava/lang/Object;Ljava/lang/Object;)Ljava/lang/String;
         9: areturn
      LocalVariableTable:
        Start  Length  Slot  Name   Signature
            0      10     0 param0   Ljava/lang/Object;
            0      10     1 param1   Ljava/lang/Object;
            0      10     2 param2   Ljava/lang/Object;
    MethodParameters:
      Name                           Flags
      param0                         final
      param1                         final
      param2                         final

  public static java.lang.String rawWasPlusOrMinus();
    descriptor: ()Ljava/lang/String;
    flags: (0x0009) ACC_PUBLIC, ACC_STATIC
    Code:
      stack=1, locals=0, args_size=0
         0: getstatic     #16                 // Field org/scalactic/Resources$.MODULE$:Lorg/scalactic/Resources$;
         3: invokevirtual #661                // Method org/scalactic/Resources$.rawWasPlusOrMinus:()Ljava/lang/String;
         6: areturn

  public static java.lang.String wasPlusOrMinus(java.lang.Object, java.lang.Object, java.lang.Object);
    descriptor: (Ljava/lang/Object;Ljava/lang/Object;Ljava/lang/Object;)Ljava/lang/String;
    flags: (0x0009) ACC_PUBLIC, ACC_STATIC
    Code:
      stack=4, locals=3, args_size=3
         0: getstatic     #16                 // Field org/scalactic/Resources$.MODULE$:Lorg/scalactic/Resources$;
         3: aload_0
         4: aload_1
         5: aload_2
         6: invokevirtual #664                // Method org/scalactic/Resources$.wasPlusOrMinus:(Ljava/lang/Object;Ljava/lang/Object;Ljava/lang/Object;)Ljava/lang/String;
         9: areturn
      LocalVariableTable:
        Start  Length  Slot  Name   Signature
            0      10     0 param0   Ljava/lang/Object;
            0      10     1 param1   Ljava/lang/Object;
            0      10     2 param2   Ljava/lang/Object;
    MethodParameters:
      Name                           Flags
      param0                         final
      param1                         final
      param2                         final

  public static java.lang.String rawEqualed();
    descriptor: ()Ljava/lang/String;
    flags: (0x0009) ACC_PUBLIC, ACC_STATIC
    Code:
      stack=1, locals=0, args_size=0
         0: getstatic     #16                 // Field org/scalactic/Resources$.MODULE$:Lorg/scalactic/Resources$;
         3: invokevirtual #667                // Method org/scalactic/Resources$.rawEqualed:()Ljava/lang/String;
         6: areturn

  public static java.lang.String equaled(java.lang.Object, java.lang.Object);
    descriptor: (Ljava/lang/Object;Ljava/lang/Object;)Ljava/lang/String;
    flags: (0x0009) ACC_PUBLIC, ACC_STATIC
    Code:
      stack=3, locals=2, args_size=2
         0: getstatic     #16                 // Field org/scalactic/Resources$.MODULE$:Lorg/scalactic/Resources$;
         3: aload_0
         4: aload_1
         5: invokevirtual #670                // Method org/scalactic/Resources$.equaled:(Ljava/lang/Object;Ljava/lang/Object;)Ljava/lang/String;
         8: areturn
      LocalVariableTable:
        Start  Length  Slot  Name   Signature
            0       9     0 param0   Ljava/lang/Object;
            0       9     1 param1   Ljava/lang/Object;
    MethodParameters:
      Name                           Flags
      param0                         final
      param1                         final

  public static java.lang.String rawDidNotEqual();
    descriptor: ()Ljava/lang/String;
    flags: (0x0009) ACC_PUBLIC, ACC_STATIC
    Code:
      stack=1, locals=0, args_size=0
         0: getstatic     #16                 // Field org/scalactic/Resources$.MODULE$:Lorg/scalactic/Resources$;
         3: invokevirtual #673                // Method org/scalactic/Resources$.rawDidNotEqual:()Ljava/lang/String;
         6: areturn

  public static java.lang.String didNotEqual(java.lang.Object, java.lang.Object);
    descriptor: (Ljava/lang/Object;Ljava/lang/Object;)Ljava/lang/String;
    flags: (0x0009) ACC_PUBLIC, ACC_STATIC
    Code:
      stack=3, locals=2, args_size=2
         0: getstatic     #16                 // Field org/scalactic/Resources$.MODULE$:Lorg/scalactic/Resources$;
         3: aload_0
         4: aload_1
         5: invokevirtual #676                // Method org/scalactic/Resources$.didNotEqual:(Ljava/lang/Object;Ljava/lang/Object;)Ljava/lang/String;
         8: areturn
      LocalVariableTable:
        Start  Length  Slot  Name   Signature
            0       9     0 param0   Ljava/lang/Object;
            0       9     1 param1   Ljava/lang/Object;
    MethodParameters:
      Name                           Flags
      param0                         final
      param1                         final

  public static java.lang.String rawBigProblemsWithMessage();
    descriptor: ()Ljava/lang/String;
    flags: (0x0009) ACC_PUBLIC, ACC_STATIC
    Code:
      stack=1, locals=0, args_size=0
         0: getstatic     #16                 // Field org/scalactic/Resources$.MODULE$:Lorg/scalactic/Resources$;
         3: invokevirtual #679                // Method org/scalactic/Resources$.rawBigProblemsWithMessage:()Ljava/lang/String;
         6: areturn

  public static java.lang.String bigProblemsWithMessage(java.lang.Object);
    descriptor: (Ljava/lang/Object;)Ljava/lang/String;
    flags: (0x0009) ACC_PUBLIC, ACC_STATIC
    Code:
      stack=2, locals=1, args_size=1
         0: getstatic     #16                 // Field org/scalactic/Resources$.MODULE$:Lorg/scalactic/Resources$;
         3: aload_0
         4: invokevirtual #682                // Method org/scalactic/Resources$.bigProblemsWithMessage:(Ljava/lang/Object;)Ljava/lang/String;
         7: areturn
      LocalVariableTable:
        Start  Length  Slot  Name   Signature
            0       8     0 param0   Ljava/lang/Object;
    MethodParameters:
      Name                           Flags
      param0                         final

  public static java.lang.String rawBigProblems();
    descriptor: ()Ljava/lang/String;
    flags: (0x0009) ACC_PUBLIC, ACC_STATIC
    Code:
      stack=1, locals=0, args_size=0
         0: getstatic     #16                 // Field org/scalactic/Resources$.MODULE$:Lorg/scalactic/Resources$;
         3: invokevirtual #685                // Method org/scalactic/Resources$.rawBigProblems:()Ljava/lang/String;
         6: areturn

  public static java.lang.String bigProblems();
    descriptor: ()Ljava/lang/String;
    flags: (0x0009) ACC_PUBLIC, ACC_STATIC
    Code:
      stack=1, locals=0, args_size=0
         0: getstatic     #16                 // Field org/scalactic/Resources$.MODULE$:Lorg/scalactic/Resources$;
         3: invokevirtual #688                // Method org/scalactic/Resources$.bigProblems:()Ljava/lang/String;
         6: areturn

  public static java.lang.String formatString(java.lang.String, java.lang.Object[]);
    descriptor: (Ljava/lang/String;[Ljava/lang/Object;)Ljava/lang/String;
    flags: (0x0009) ACC_PUBLIC, ACC_STATIC
    Code:
      stack=3, locals=2, args_size=2
         0: getstatic     #16                 // Field org/scalactic/Resources$.MODULE$:Lorg/scalactic/Resources$;
         3: aload_0
         4: aload_1
         5: invokevirtual #694                // Method org/scalactic/Resources$.formatString:(Ljava/lang/String;[Ljava/lang/Object;)Ljava/lang/String;
         8: areturn
      LocalVariableTable:
        Start  Length  Slot  Name   Signature
            0       9     0 rawString   Ljava/lang/String;
            0       9     1  args   [Ljava/lang/Object;
    MethodParameters:
      Name                           Flags
      rawString                      final
      args                           final

  public static java.util.ResourceBundle resourceBundle();
    descriptor: ()Ljava/util/ResourceBundle;
    flags: (0x0009) ACC_PUBLIC, ACC_STATIC
    Code:
      stack=1, locals=0, args_size=0
         0: getstatic     #16                 // Field org/scalactic/Resources$.MODULE$:Lorg/scalactic/Resources$;
         3: invokevirtual #700                // Method org/scalactic/Resources$.resourceBundle:()Ljava/util/ResourceBundle;
         6: areturn
}
SourceFile: "Resources.scala"
RuntimeVisibleAnnotations:
  0: #6(#7=s#8)
    scala.reflect.ScalaSignature(
      bytes="\u0006\u0005\u0011\u0015xACAe\u0003\u0017D\t!a3\u0002T\u001aQ\u0011q[Af\u0011\u0003\tY-!7\t\u000f\u0005\u001d\u0018\u0001\"\u0001\u0002l\"Q\u0011Q^\u0001\t\u0006\u0004%\t!a<\t\u000f\t\u0005\u0011\u0001\"\u0003\u0003\u0004!9!qF\u0001\u0005\u0002\tE\u0002b\u0002B\u001d\u0003\u0011\u0005!1\b\u0005\b\u0005{\tA\u0011\u0001B\u001e\u0011\u001d\u0011y$\u0001C\u0001\u0005\u0003BqAa\u0012\u0002\t\u0003\u0011Y\u0004C\u0004\u0003J\u0005!\tAa\u0013\t\u000f\tM\u0013\u0001\"\u0001\u0003<!9!QK\u0001\u0005\u0002\t]\u0003b\u0002B/\u0003\u0011\u0005!1\b\u0005\b\u0005?\nA\u0011\u0001B1\u0011\u001d\u0011Y\'\u0001C\u0001\u0005wAqA!\u001c\u0002\t\u0003\u0011y\u0007C\u0004\u0003x\u0005!\tAa\u000f\t\u000f\te\u0014\u0001\"\u0001\u0003<!9!1P\u0001\u0005\u0002\tm\u0002b\u0002B?\u0003\u0011\u0005!1\b\u0005\b\u0005\u007f\nA\u0011\u0001B\u001e\u0011\u001d\u0011\t)\u0001C\u0001\u0005\u0007CqAa\"\u0002\t\u0003\u0011Y\u0004C\u0004\u0003\n\u0006!\tAa#\t\u000f\t=\u0015\u0001\"\u0001\u0003<!9!\u0011S\u0001\u0005\u0002\tm\u0002b\u0002BJ\u0003\u0011\u0005!1\b\u0005\b\u0005+\u000bA\u0011\u0001BL\u0011\u001d\u0011i*\u0001C\u0001\u0005wAqAa(\u0002\t\u0003\u0011\t\u000bC\u0004\u0003&\u0006!\tAa\u000f\t\u000f\t\u001d\u0016\u0001\"\u0001\u0003*\"9!QV\u0001\u0005\u0002\tm\u0002b\u0002BX\u0003\u0011\u0005!\u0011\u0017\u0005\b\u0005o\u000bA\u0011\u0001B\u001e\u0011\u001d\u0011I,\u0001C\u0001\u0005wCqA!1\u0002\t\u0003\u0011Y\u0004C\u0004\u0003D\u0006!\tA!2\t\u000f\t-\u0017\u0001\"\u0001\u0003<!9!QZ\u0001\u0005\u0002\t=\u0007b\u0002Bk\u0003\u0011\u0005!1\b\u0005\b\u0005/\fA\u0011\u0001Bm\u0011\u001d\u0011y.\u0001C\u0001\u0005wAqA!9\u0002\t\u0003\u0011\u0019\u000fC\u0004\u0003j\u0006!\tAa\u000f\t\u000f\t-\u0018\u0001\"\u0001\u0003n\"9!1_\u0001\u0005\u0002\tm\u0002b\u0002B{\u0003\u0011\u0005!q\u001f\u0005\b\u0005{\fA\u0011\u0001B\u001e\u0011\u001d\u0011y0\u0001C\u0001\u0007\u0003Aqaa\u0002\u0002\t\u0003\u0011Y\u0004C\u0004\u0004\n\u0005!\taa\u0003\t\u000f\rE\u0011\u0001\"\u0001\u0003<!911C\u0001\u0005\u0002\rU\u0001bBB\u000e\u0003\u0011\u0005!1\b\u0005\b\u0007;\tA\u0011AB\u0010\u0011\u001d\u0019)#\u0001C\u0001\u0005wAqaa\n\u0002\t\u0003\u0019I\u0003C\u0004\u00040\u0005!\tAa\u000f\t\u000f\rE\u0012\u0001\"\u0001\u00044!91\u0011H\u0001\u0005\u0002\tm\u0002bBB\u001e\u0003\u0011\u00051Q\b\u0005\b\u0007\u0007\nA\u0011\u0001B\u001e\u0011\u001d\u0019)%\u0001C\u0001\u0007\u000fBqa!\u0014\u0002\t\u0003\u0011Y\u0004C\u0004\u0004P\u0005!\ta!\u0015\t\u000f\r]\u0013\u0001\"\u0001\u0003<!91\u0011L\u0001\u0005\u0002\rm\u0003bBB1\u0003\u0011\u0005!1\b\u0005\b\u0007G\nA\u0011AB3\u0011\u001d\u0019I\'\u0001C\u0001\u0005wAqaa\u001b\u0002\t\u0003\u0019i\u0007C\u0004\u0004r\u0005!\tAa\u000f\t\u000f\rM\u0014\u0001\"\u0001\u0004v!911P\u0001\u0005\u0002\tm\u0002bBB?\u0003\u0011\u00051q\u0010\u0005\b\u0007\u000b\u000bA\u0011\u0001B\u001e\u0011\u001d\u00199)\u0001C\u0001\u0007\u0013Cqa!%\u0002\t\u0003\u0011Y\u0004C\u0004\u0004\u0014\u0006!\ta!&\t\u000f\rm\u0015\u0001\"\u0001\u0003<!91QT\u0001\u0005\u0002\r}\u0005bBBT\u0003\u0011\u0005!1\b\u0005\b\u0007S\u000bA\u0011ABV\u0011\u001d\u0019\t,\u0001C\u0001\u0005wAqaa-\u0002\t\u0003\u0019)\fC\u0004\u0004<\u0006!\tAa\u000f\t\u000f\ru\u0016\u0001\"\u0001\u0004@\"91QY\u0001\u0005\u0002\tm\u0002bBBd\u0003\u0011\u00051\u0011\u001a\u0005\b\u0007\u001f\fA\u0011\u0001B\u001e\u0011\u001d\u0019\t.\u0001C\u0001\u0005wAqaa5\u0002\t\u0003\u0011Y\u0004C\u0004\u0004V\u0006!\tAa\u000f\t\u000f\r]\u0017\u0001\"\u0001\u0003<!91\u0011\\\u0001\u0005\u0002\tm\u0002bBBn\u0003\u0011\u0005!1\b\u0005\b\u0007;\fA\u0011\u0001B\u001e\u0011\u001d\u0019y.\u0001C\u0001\u0005wAqa!9\u0002\t\u0003\u0011Y\u0004C\u0004\u0004d\u0006!\tAa\u000f\t\u000f\r\u0015\u0018\u0001\"\u0001\u0003<!91q]\u0001\u0005\u0002\tm\u0002bBBu\u0003\u0011\u0005!1\b\u0005\b\u0007W\fA\u0011\u0001B\u001e\u0011\u001d\u0019i/\u0001C\u0001\u0005wAqaa<\u0002\t\u0003\u0011Y\u0004C\u0004\u0004r\u0006!\tAa\u000f\t\u000f\rM\u0018\u0001\"\u0001\u0003<!91Q_\u0001\u0005\u0002\tm\u0002bBB|\u0003\u0011\u0005!1\b\u0005\b\u0007s\fA\u0011\u0001B\u001e\u0011\u001d\u0019Y0\u0001C\u0001\u0005wAqa!@\u0002\t\u0003\u0011Y\u0004C\u0004\u0004\u0000\u0006!\tAa\u000f\t\u000f\u0011\u0005\u0011\u0001\"\u0001\u0003<!9A1A\u0001\u0005\u0002\tm\u0002b\u0002C\u0003\u0003\u0011\u0005!1\b\u0005\b\t\u000f\tA\u0011\u0001B\u001e\u0011\u001d!I!\u0001C\u0001\u0005wAq\u0001b\u0003\u0002\t\u0003\u0011Y\u0004C\u0004\u0005\u000e\u0005!\tAa\u000f\t\u000f\u0011=\u0011\u0001\"\u0001\u0003<!9A\u0011C\u0001\u0005\u0002\tm\u0002b\u0002C\n\u0003\u0011\u0005!1\b\u0005\b\t+\tA\u0011\u0001B\u001e\u0011\u001d!9\"\u0001C\u0001\u0005wAq\u0001\"\u0007\u0002\t\u0003\u0011Y\u0004C\u0004\u0005\u001c\u0005!\tAa\u000f\t\u000f\u0011u\u0011\u0001\"\u0001\u0003<!9AqD\u0001\u0005\u0002\tm\u0002b\u0002C\u0011\u0003\u0011\u0005!1\b\u0005\b\tG\tA\u0011\u0001B\u001e\u0011\u001d!)#\u0001C\u0001\u0005wAq\u0001b\n\u0002\t\u0003\u0011Y\u0004C\u0004\u0005*\u0005!\tAa\u000f\t\u000f\u0011-\u0012\u0001\"\u0001\u0003<!9AQF\u0001\u0005\u0002\tm\u0002b\u0002C\u0018\u0003\u0011\u0005!1\b\u0005\b\tc\tA\u0011\u0001B\u001e\u0011\u001d!\u0019$\u0001C\u0001\u0005wAq\u0001\"\u000e\u0002\t\u0003\u0011Y\u0004C\u0004\u00058\u0005!\tAa\u000f\t\u000f\u0011e\u0012\u0001\"\u0001\u0003<!9A1H\u0001\u0005\u0002\tm\u0002b\u0002C\u001f\u0003\u0011\u0005!1\b\u0005\b\t\u007f\tA\u0011\u0001B\u001e\u0011\u001d!\t%\u0001C\u0001\u0005wAq\u0001b\u0011\u0002\t\u0003\u0011Y\u0004C\u0004\u0005F\u0005!\tAa\u000f\t\u000f\u0011\u001d\u0013\u0001\"\u0001\u0003<!9A\u0011J\u0001\u0005\u0002\tm\u0002b\u0002C&\u0003\u0011\u0005!1\b\u0005\b\t\u001b\nA\u0011\u0001B\u001e\u0011\u001d!y%\u0001C\u0001\u0005wAq\u0001\"\u0015\u0002\t\u0003\u0011Y\u0004C\u0004\u0005T\u0005!\tAa\u000f\t\u000f\u0011U\u0013\u0001\"\u0001\u0003<!9AqK\u0001\u0005\u0002\tm\u0002b\u0002C-\u0003\u0011\u0005!1\b\u0005\b\t7\nA\u0011\u0001B\u001e\u0011\u001d!i&\u0001C\u0001\u0005wAq\u0001b\u0018\u0002\t\u0003\u0011Y\u0004C\u0004\u0005b\u0005!\tAa\u000f\t\u000f\u0011\r\u0014\u0001\"\u0001\u0003<!9AQM\u0001\u0005\u0002\tm\u0002b\u0002C4\u0003\u0011\u0005!1\b\u0005\b\tS\nA\u0011\u0001B\u001e\u0011\u001d!Y\'\u0001C\u0001\u0005wAq\u0001\"\u001c\u0002\t\u0003\u0011Y\u0004C\u0004\u0005p\u0005!\tAa\u000f\t\u000f\u0011E\u0014\u0001\"\u0001\u0003<!9A1O\u0001\u0005\u0002\tm\u0002b\u0002C;\u0003\u0011\u0005!1\b\u0005\b\to\nA\u0011\u0001B\u001e\u0011\u001d!I(\u0001C\u0001\u0005wAq\u0001b\u001f\u0002\t\u0003\u0011Y\u0004C\u0004\u0005~\u0005!\tAa\u000f\t\u000f\u0011}\u0014\u0001\"\u0001\u0003<!9A\u0011Q\u0001\u0005\u0002\tm\u0002b\u0002CB\u0003\u0011\u0005!1\b\u0005\b\t\u000b\u000bA\u0011\u0001B\u001e\u0011\u001d!9)\u0001C\u0001\u0005wAq\u0001\"#\u0002\t\u0003\u0011Y\u0004C\u0004\u0005\f\u0006!\tAa\u000f\t\u000f\u00115\u0015\u0001\"\u0001\u0003<!9AqR\u0001\u0005\u0002\tm\u0002b\u0002CI\u0003\u0011\u0005!1\b\u0005\b\t\'\u000bA\u0011\u0001B\u001e\u0011\u001d!)*\u0001C\u0001\u0005wAq\u0001b&\u0002\t\u0003\u0011Y\u0004C\u0004\u0005\u001a\u0006!\tAa\u000f\t\u000f\u0011m\u0015\u0001\"\u0001\u0003<!9AQT\u0001\u0005\u0002\tm\u0002b\u0002CP\u0003\u0011\u0005!1\b\u0005\b\tC\u000bA\u0011\u0001B\u001e\u0011\u001d!\u0019+\u0001C\u0001\u0005wAq\u0001\"*\u0002\t\u0003\u0011Y\u0004C\u0004\u0005(\u0006!\tAa\u000f\t\u000f\u0011%\u0016\u0001\"\u0001\u0003<!9A1V\u0001\u0005\u0002\tm\u0002b\u0002CW\u0003\u0011\u0005!1\b\u0005\b\t_\u000bA\u0011\u0001B\u001e\u0011\u001d!\t,\u0001C\u0001\u0005wAq\u0001b-\u0002\t\u0003\u0011Y\u0004C\u0004\u00056\u0006!\tAa\u000f\t\u000f\u0011]\u0016\u0001\"\u0001\u0003<!9A\u0011X\u0001\u0005\u0002\tm\u0002b\u0002C^\u0003\u0011\u0005!1\b\u0005\b\t{\u000bA\u0011\u0001B\u001e\u0011\u001d!y,\u0001C\u0001\u0005wAq\u0001\"1\u0002\t\u0003\u0011Y\u0004C\u0004\u0005D\u0006!\tAa\u000f\t\u000f\u0011\u0015\u0017\u0001\"\u0001\u0003<!9AqY\u0001\u0005\u0002\tm\u0002b\u0002Ce\u0003\u0011\u0005!1\b\u0005\b\t\u0017\fA\u0011\u0001B\u001e\u0011\u001d!i-\u0001C\u0001\u0005wAq\u0001b4\u0002\t\u0003\u0011Y\u0004C\u0004\u0005R\u0006!\tAa\u000f\t\u000f\u0011M\u0017\u0001\"\u0001\u0003<!9AQ[\u0001\u0005\u0002\tm\u0002b\u0002Cl\u0003\u0011\u0005!1\b\u0005\b\t3\fA\u0011\u0001B\u001e\u0011\u001d!Y.\u0001C\u0001\u0005wAq\u0001\"8\u0002\t\u0003!y\u000eC\u0004\u0005d\u0006!\tAa\u000f\u0002\u0013I+7o\\;sG\u0016\u001c(\u0002BAg\u0003\u001f\f\u0011b]2bY\u0006\u001cG/[2\u000b\u0005\u0005E\u0017aA8sOB\u0019\u0011Q[\u0001\u000e\u0005\u0005-\'!\u0003*fg>,(oY3t\'\r\t\u00111\u001c\t\u0005\u0003;\f\u0019/\u0004\u0002\u0002`*\u0011\u0011\u0011]\u0001\u0006g\u000e\fG.Y\u0005\u0005\u0003K\fyN\u0001\u0004B]f\u0014VMZ\u0001\u0007y%t\u0017\u000e\u001e \u0004\u0001Q\u0011\u00111[\u0001\u000fe\u0016\u001cx.\u001e:dK\n+h\u000e\u001a7f+\t\t\t\u0010\u0005\u0003\u0002t\u0006uXBAA{\u0015\u0011\t90!?\u0002\tU$\u0018\u000e\u001c\u0006\u0003\u0003w\fAA[1wC&!\u0011q`A{\u00059\u0011Vm]8ve\u000e,\')\u001e8eY\u0016\f!\"\\1lKN#(/\u001b8h)\u0019\u0011)Aa\u0007\u0003 A!!q\u0001B\u000b\u001d\u0011\u0011IA!\u0005\u0011\t\t-\u0011q\\\u0007\u0003\u0005\u001bQAAa\u0004\u0002j\u00061AH]8pizJAAa\u0005\u0002`\u00061\u0001K]3eK\u001aLAAa\u0006\u0003\u001a\t11\u000b\u001e:j]\u001eTAAa\u0005\u0002`\"9!Q\u0004\u0003A\u0002\t\u0015\u0011\u0001\u0004:fg>,(oY3OC6,\u0007b\u0002B\u0011\t\u0001\u0007!1E\u0001\u0005CJ<7\u000f\u0005\u0004\u0002^\n\u0015\"\u0011F\u0005\u0005\u0005O\tyNA\u0003BeJ\f\u0017\u0010\u0005\u0003\u0002^\n-\u0012\u0002\u0002B\u0017\u0003?\u00141!\u00118z\u000311wN]7biN#(/\u001b8h)\u0019\u0011)Aa\r\u00038!9!QG\u0003A\u0002\t\u0015\u0011!\u0003:boN#(/\u001b8h\u0011\u001d\u0011\t#\u0002a\u0001\u0005G\t1BY5h!J|\'\r\\3ngV\u0011!QA\u0001\u000fe\u0006<()[4Qe>\u0014G.Z7t\u0003Y\u0011\u0017n\u001a)s_\ndW-\\:XSRDW*Z:tC\u001e,G\u0003\u0002B\u0003\u0005\u0007BqA!\u0012\t\u0001\u0004\u0011I#\u0001\u0004qCJ\fW\u000eM\u0001\u001ae\u0006<()[4Qe>\u0014G.Z7t/&$\b.T3tg\u0006<W-A\u0006eS\u0012tu\u000e^#rk\u0006dGC\u0002B\u0003\u0005\u001b\u0012y\u0005C\u0004\u0003F)\u0001\rA!\u000b\t\u000f\tE#\u00021\u0001\u0003*\u00051\u0001/\u0019:b[F\naB]1x\t&$gj\u001c;FcV\fG.A\u0004fcV\fG.\u001a3\u0015\r\t\u0015!\u0011\fB.\u0011\u001d\u0011)\u0005\u0004a\u0001\u0005SAqA!\u0015\r\u0001\u0004\u0011I#\u0001\u0006sC^,\u0015/^1mK\u0012\fab^1t!2,8o\u0014:NS:,8\u000f\u0006\u0005\u0003\u0006\t\r$Q\rB4\u0011\u001d\u0011)E\u0004a\u0001\u0005SAqA!\u0015\u000f\u0001\u0004\u0011I\u0003C\u0004\u0003j9\u0001\rA!\u000b\u0002\rA\f\'/Y73\u0003E\u0011\u0018m^,bgBcWo](s\u001b&tWo]\u0001\u0012o\u0006\u001chj\u001c;QYV\u001cxJ]\'j]V\u001cH\u0003\u0003B\u0003\u0005c\u0012\u0019H!\u001e\t\u000f\t\u0015\u0003\u00031\u0001\u0003*!9!\u0011\u000b\tA\u0002\t%\u0002b\u0002B5!\u0001\u0007!\u0011F\u0001\u0015e\u0006<x+Y:O_R\u0004F.^:Pe6Kg.^:\u0002%\u0015D\bO]3tg&|gnV1t\r\u0006d7/Z\u0001\u0016e\u0006<X\t\u001f9sKN\u001c\u0018n\u001c8XCN4\u0015\r\\:f\u0003E)\u0007\u0010\u001d:fgNLwN\\,bgR\u0013X/Z\u0001\u0015e\u0006<X\t\u001f9sKN\u001c\u0018n\u001c8XCN$&/^3\u0002\u000f]\f7OT;mYR!!Q\u0001BC\u0011\u001d\u0011)E\u0006a\u0001\u0005S\t!B]1x/\u0006\u001ch*\u001e7m\u0003!9XM]3Ok2dG\u0003\u0002B\u0003\u0005\u001bCqA!\u0012\u0019\u0001\u0004\u0011I#A\u0006sC^<VM]3Ok2d\u0017!B2p[6\f\u0017\u0001\u0003:bo\u000e{W.\\1\u0002\u0007\u0005tG\r\u0006\u0004\u0003\u0006\te%1\u0014\u0005\b\u0005\u000bb\u0002\u0019\u0001B\u0015\u0011\u001d\u0011\t\u0006\ba\u0001\u0005S\taA]1x\u0003:$\u0017aB<bgR\u0013X/\u001a\u000b\u0005\u0005\u000b\u0011\u0019\u000bC\u0004\u0003Fy\u0001\rA!\u000b\u0002\u0015I\fwoV1t)J,X-\u0001\u0005xCN4\u0015\r\\:f)\u0011\u0011)Aa+\t\u000f\t\u0015\u0003\u00051\u0001\u0003*\u0005Y!/Y<XCN4\u0015\r\\:f\u0003-9\u0018m\u001d\'fgN$\u0006.\u00198\u0015\r\t\u0015!1\u0017B[\u0011\u001d\u0011)E\ta\u0001\u0005SAqA!\u0015#\u0001\u0004\u0011I#\u0001\bsC^<\u0016m\u001d\'fgN$\u0006.\u00198\u0002\u001d]\f7OT8u\u0019\u0016\u001c8\u000f\u00165b]R1!Q\u0001B_\u0005\u007fCqA!\u0012%\u0001\u0004\u0011I\u0003C\u0004\u0003R\u0011\u0002\rA!\u000b\u0002#I\fwoV1t\u001d>$H*Z:t)\"\fg.\u0001\bxCN<%/Z1uKJ$\u0006.\u00198\u0015\r\t\u0015!q\u0019Be\u0011\u001d\u0011)E\na\u0001\u0005SAqA!\u0015\'\u0001\u0004\u0011I#A\tsC^<\u0016m]$sK\u0006$XM\u001d+iC:\f\u0011c^1t\u001d>$xI]3bi\u0016\u0014H\u000b[1o)\u0019\u0011)A!5\u0003T\"9!Q\t\u0015A\u0002\t%\u0002b\u0002B)Q\u0001\u0007!\u0011F\u0001\u0015e\u0006<x+Y:O_R<%/Z1uKJ$\u0006.\u00198\u0002)]\f7\u000fT3tgRC\u0017M\\(s\u000bF,\u0018\r\u001c+p)\u0019\u0011)Aa7\u0003^\"9!Q\t\u0016A\u0002\t%\u0002b\u0002B)U\u0001\u0007!\u0011F\u0001\u0018e\u0006<x+Y:MKN\u001cH\u000b[1o\u001fJ,\u0015/^1m)>\fqc^1t\u001d>$H*Z:t)\"\fgn\u0014:FcV\fG\u000eV8\u0015\r\t\u0015!Q\u001dBt\u0011\u001d\u0011)\u0005\fa\u0001\u0005SAqA!\u0015-\u0001\u0004\u0011I#\u0001\u000esC^<\u0016m\u001d(pi2+7o\u001d+iC:|%/R9vC2$v.A\fxCN<%/Z1uKJ$\u0006.\u00198Pe\u0016\u000bX/\u00197U_R1!Q\u0001Bx\u0005cDqA!\u0012/\u0001\u0004\u0011I\u0003C\u0004\u0003R9\u0002\rA!\u000b\u00025I\fwoV1t\u000fJ,\u0017\r^3s)\"\fgn\u0014:FcV\fG\u000eV8\u00025]\f7OT8u\u000fJ,\u0017\r^3s)\"\fgn\u0014:FcV\fG\u000eV8\u0015\r\t\u0015!\u0011 B~\u0011\u001d\u0011)\u0005\ra\u0001\u0005SAqA!\u00151\u0001\u0004\u0011I#A\u000fsC^<\u0016m\u001d(pi\u001e\u0013X-\u0019;feRC\u0017M\\(s\u000bF,\u0018\r\u001c+p\u0003=!\u0017\u000e\u001a(piN#\u0018M\u001d;XSRDGC\u0002B\u0003\u0007\u0007\u0019)\u0001C\u0004\u0003FI\u0002\rA!\u000b\t\u000f\tE#\u00071\u0001\u0003*\u0005\u0011\"/Y<ES\u0012tu\u000e^*uCJ$x+\u001b;i\u0003-\u0019H/\u0019:uK\u0012<\u0016\u000e\u001e5\u0015\r\t\u00151QBB\b\u0011\u001d\u0011)\u0005\u000ea\u0001\u0005SAqA!\u00155\u0001\u0004\u0011I#\u0001\bsC^\u001cF/\u0019:uK\u0012<\u0016\u000e\u001e5\u0002\u001b\u0011LGMT8u\u000b:$w+\u001b;i)\u0019\u0011)aa\u0006\u0004\u001a!9!Q\t\u001cA\u0002\t%\u0002b\u0002B)m\u0001\u0007!\u0011F\u0001\u0011e\u0006<H)\u001b3O_R,e\u000eZ,ji\"\f\u0011\"\u001a8eK\u0012<\u0016\u000e\u001e5\u0015\r\t\u00151\u0011EB\u0012\u0011\u001d\u0011)\u0005\u000fa\u0001\u0005SAqA!\u00159\u0001\u0004\u0011I#\u0001\u0007sC^,e\u000eZ3e/&$\b.A\u0007eS\u0012tu\u000e^\"p]R\f\u0017N\u001c\u000b\u0007\u0005\u000b\u0019Yc!\f\t\u000f\t\u0015#\b1\u0001\u0003*!9!\u0011\u000b\u001eA\u0002\t%\u0012\u0001\u0005:bo\u0012KGMT8u\u0007>tG/Y5o\u0003%\u0019wN\u001c;bS:,G\r\u0006\u0004\u0003\u0006\rU2q\u0007\u0005\b\u0005\u000bb\u0004\u0019\u0001B\u0015\u0011\u001d\u0011\t\u0006\u0010a\u0001\u0005S\tAB]1x\u0007>tG/Y5oK\u0012\f\u0001\u0003Z5e\u001d>$8i\u001c8uC&t7*Z=\u0015\r\t\u00151qHB!\u0011\u001d\u0011)E\u0010a\u0001\u0005SAqA!\u0015?\u0001\u0004\u0011I#A\nsC^$\u0015\u000e\u001a(pi\u000e{g\u000e^1j].+\u00170\u0001\u0007d_:$\u0018-\u001b8fI.+\u0017\u0010\u0006\u0004\u0003\u0006\r%31\n\u0005\b\u0005\u000b\u0002\u0005\u0019\u0001B\u0015\u0011\u001d\u0011\t\u0006\u0011a\u0001\u0005S\tqB]1x\u0007>tG/Y5oK\u0012\\U-_\u0001\u0015o\u0006\u001cH\u000b[3TC6,\u0017J\\:uC:\u001cW-Q:\u0015\r\t\u001511KB+\u0011\u001d\u0011)E\u0011a\u0001\u0005SAqA!\u0015C\u0001\u0004\u0011I#A\fsC^<\u0016m\u001d+iKN\u000bW.Z%ogR\fgnY3Bg\u00069r/Y:O_R$\u0006.Z*b[\u0016Len\u001d;b]\u000e,\u0017i\u001d\u000b\u0007\u0005\u000b\u0019ifa\u0018\t\u000f\t\u0015C\t1\u0001\u0003*!9!\u0011\u000b#A\u0002\t%\u0012A\u0007:bo^\u000b7OT8u)\",7+Y7f\u0013:\u001cH/\u00198dK\u0006\u001b\u0018aC<bg:{G/R7qif$BA!\u0002\u0004h!9!Q\t$A\u0002\t%\u0012A\u0004:bo^\u000b7OT8u\u000b6\u0004H/_\u0001\to\u0006\u001cX)\u001c9usR!!QAB8\u0011\u001d\u0011)\u0005\u0013a\u0001\u0005S\t1B]1x/\u0006\u001cX)\u001c9us\u0006\u0001r/Y:O_RLen\u001d;b]\u000e,wJ\u001a\u000b\u0007\u0005\u000b\u00199h!\u001f\t\u000f\t\u0015#\n1\u0001\u0003*!9!\u0011\u000b&A\u0002\t%\u0012a\u0005:bo^\u000b7OT8u\u0013:\u001cH/\u00198dK>3\u0017!D<bg&s7\u000f^1oG\u0016|e\r\u0006\u0004\u0003\u0006\r\u000551\u0011\u0005\b\u0005\u000bb\u0005\u0019\u0001B\u0015\u0011\u001d\u0011\t\u0006\u0014a\u0001\u0005S\t\u0001C]1x/\u0006\u001c\u0018J\\:uC:\u001cWm\u00144\u0002A!\fG\rT3oORD\u0017J\\:uK\u0006$wJZ#ya\u0016\u001cG/\u001a3MK:<G\u000f\u001b\u000b\t\u0005\u000b\u0019Yi!$\u0004\u0010\"9!Q\t(A\u0002\t%\u0002b\u0002B)\u001d\u0002\u0007!\u0011\u0006\u0005\b\u0005Sr\u0005\u0019\u0001B\u0015\u0003\r\u0012\u0018m\u001e%bI2+gn\u001a;i\u0013:\u001cH/Z1e\u001f\u001a,\u0005\u0010]3di\u0016$G*\u001a8hi\"\f\u0011\u0002[1e\u0019\u0016tw\r\u001e5\u0015\r\t\u00151qSBM\u0011\u001d\u0011)\u0005\u0015a\u0001\u0005SAqA!\u0015Q\u0001\u0004\u0011I#\u0001\u0007sC^D\u0015\r\u001a\'f]\u001e$\b.\u0001\u000fiC\u0012\u001c\u0016N_3J]N$X-\u00193PM\u0016C\b/Z2uK\u0012\u001c\u0016N_3\u0015\u0011\t\u00151\u0011UBR\u0007KCqA!\u0012S\u0001\u0004\u0011I\u0003C\u0004\u0003RI\u0003\rA!\u000b\t\u000f\t%$\u000b1\u0001\u0003*\u0005y\"/Y<IC\u0012\u001c\u0016N_3J]N$X-\u00193PM\u0016C\b/Z2uK\u0012\u001c\u0016N_3\u0002\u000f!\fGmU5{KR1!QABW\u0007_CqA!\u0012U\u0001\u0004\u0011I\u0003C\u0004\u0003RQ\u0003\rA!\u000b\u0002\u0015I\fw\u000fS1e\'&TX-\u0001\u0005d_6l\u0017MQ;u)\u0019\u0011)aa.\u0004:\"9!Q\t,A\u0002\t%\u0002b\u0002B)-\u0002\u0007!\u0011F\u0001\fe\u0006<8i\\7nC\n+H/\u0001\u0005d_6l\u0017-\u00118e)\u0019\u0011)a!1\u0004D\"9!Q\t-A\u0002\t%\u0002b\u0002B)1\u0002\u0007!\u0011F\u0001\fe\u0006<8i\\7nC\u0006sG-\u0001\twCJL\u0017M\u00197f/\u0006\u001ch+\u00197vKR1!QABf\u0007\u001bDqA!\u0012[\u0001\u0004\u0011I\u0003C\u0004\u0003Ri\u0003\rA!\u000b\u0002\'I\fwOV1sS\u0006\u0014G.Z,bgZ\u000bG.^3\u0002\u001d9|GOV1mS\u0012\u0004vn]%oi\u0006\t\"/Y<O_R4\u0016\r\\5e!>\u001c\u0018J\u001c;\u0002!9|G\u000fT5uKJ\fG\u000eU8t\u0013:$\u0018a\u0005:bo:{G\u000fT5uKJ\fG\u000eU8t\u0013:$\u0018a\u00048piZ\u000bG.\u001b3Q_NduN\\4\u0002%I\fwOT8u-\u0006d\u0017\u000e\u001a)pg2{gnZ\u0001\u0012]>$H*\u001b;fe\u0006d\u0007k\\:M_:<\u0017\u0001\u0006:bo:{G\u000fT5uKJ\fG\u000eU8t\u0019>tw-\u0001\to_R4\u0016\r\\5e!>\u001ch\t\\8bi\u0006\u0019\"/Y<O_R4\u0016\r\\5e!>\u001ch\t\\8bi\u0006\u0011bn\u001c;MSR,\'/\u00197Q_N4En\\1u\u0003U\u0011\u0018m\u001e(pi2KG/\u001a:bYB{7O\u00127pCR\f\u0011C\\8u-\u0006d\u0017\u000e\u001a)pg\u0012{WO\u00197f\u0003Q\u0011\u0018m\u001e(piZ\u000bG.\u001b3Q_N$u.\u001e2mK\u0006\u0019bn\u001c;MSR,\'/\u00197Q_N$u.\u001e2mK\u00061\"/Y<O_Rd\u0015\u000e^3sC2\u0004vn\u001d#pk\ndW-A\bo_R4\u0016\r\\5e!>\u001c(,\u00138u\u0003I\u0011\u0018m\u001e(piZ\u000bG.\u001b3Q_NT\u0016J\u001c;\u0002#9|G\u000fT5uKJ\fG\u000eU8t5&sG/\u0001\u000bsC^tu\u000e\u001e\'ji\u0016\u0014\u0018\r\u001c)pgjKe\u000e^\u0001\u0011]>$h+\u00197jIB{7O\u0017\'p]\u001e\f1C]1x\u001d>$h+\u00197jIB{7O\u0017\'p]\u001e\f!C\\8u\u0019&$XM]1m!>\u001c(\fT8oO\u0006)\"/Y<O_Rd\u0015\u000e^3sC2\u0004vn\u001d.M_:<\u0017!\u00058piZ\u000bG.\u001b3Q_NTf\t\\8bi\u0006!\"/Y<O_R4\u0016\r\\5e!>\u001c(L\u00127pCR\f1C\\8u\u0019&$XM]1m!>\u001c(L\u00127pCR\faC]1x\u001d>$H*\u001b;fe\u0006d\u0007k\\:[\r2|\u0017\r^\u0001\u0013]>$h+\u00197jIB{7O\u0017#pk\ndW-A\u000bsC^tu\u000e\u001e,bY&$\u0007k\\:[\t>,(\r\\3\u0002)9|G\u000fT5uKJ\fG\u000eU8t5\u0012{WO\u00197f\u0003]\u0011\u0018m\u001e(pi2KG/\u001a:bYB{7O\u0017#pk\ndW-A\u0016qY\u0016\f7/\u001a#fM&tWmU2bY\u0006\u001cG/[2GS2dg)\u001b7f!\u0006$\bN\\1nK\u0016sgOV1s\u00039\u0012\u0018m\u001e)mK\u0006\u001cX\rR3gS:,7kY1mC\u000e$\u0018n\u0019$jY24\u0015\u000e\\3QCRDg.Y7f\u000b:4h+\u0019:\u0002%9|GOV1mS\u0012tuN\u001c.fe>Le\u000e^\u0001\u0016e\u0006<hj\u001c;WC2LGMT8o5\u0016\u0014x.\u00138u\u0003Qqw\u000e\u001e\'ji\u0016\u0014\u0018\r\u001c(p]j+\'o\\%oi\u00069\"/Y<O_Rd\u0015\u000e^3sC2tuN\u001c.fe>Le\u000e^\u0001\u0014]>$h+\u00197jI:{gNW3s_2{gnZ\u0001\u0017e\u0006<hj\u001c;WC2LGMT8o5\u0016\u0014x\u000eT8oO\u0006)bn\u001c;MSR,\'/\u00197O_:TVM]8M_:<\u0017\u0001\u0007:bo:{G\u000fT5uKJ\fGNT8o5\u0016\u0014x\u000eT8oO\u0006!bn\u001c;WC2LGMT8o5\u0016\u0014xN\u00127pCR\fqC]1x\u001d>$h+\u00197jI:{gNW3s_\u001acw.\u0019;\u0002-9|G\u000fT5uKJ\fGNT8o5\u0016\u0014xN\u00127pCR\f\u0011D]1x\u001d>$H*\u001b;fe\u0006dgj\u001c8[KJ|g\t\\8bi\u0006)bn\u001c;WC2LGMT8o5\u0016\u0014x\u000eR8vE2,\u0017\u0001\u0007:bo:{GOV1mS\u0012tuN\u001c.fe>$u.\u001e2mK\u00069bn\u001c;MSR,\'/\u00197O_:TVM]8E_V\u0014G.Z\u0001\u001be\u0006<hj\u001c;MSR,\'/\u00197O_:TVM]8E_V\u0014G.Z\u0001\u000f]>$h+\u00197jI:+w-\u00138u\u0003E\u0011\u0018m\u001e(piZ\u000bG.\u001b3OK\u001eLe\u000e^\u0001\u0011]>$H*\u001b;fe\u0006dg*Z4J]R\f1C]1x\u001d>$H*\u001b;fe\u0006dg*Z4J]R\fqB\\8u-\u0006d\u0017\u000e\u001a(fO2{gnZ\u0001\u0013e\u0006<hj\u001c;WC2LGMT3h\u0019>tw-A\to_Rd\u0015\u000e^3sC2tUm\u001a\'p]\u001e\fAC]1x\u001d>$H*\u001b;fe\u0006dg*Z4M_:<\u0017\u0001\u00058piZ\u000bG.\u001b3OK\u001e4En\\1u\u0003M\u0011\u0018m\u001e(piZ\u000bG.\u001b3OK\u001e4En\\1u\u0003Iqw\u000e\u001e\'ji\u0016\u0014\u0018\r\u001c(fO\u001acw.\u0019;\u0002+I\fwOT8u\u0019&$XM]1m\u001d\u0016<g\t\\8bi\u0006\tbn\u001c;WC2LGMT3h\t>,(\r\\3\u0002)I\fwOT8u-\u0006d\u0017\u000e\u001a(fO\u0012{WO\u00197f\u0003Mqw\u000e\u001e\'ji\u0016\u0014\u0018\r\u001c(fO\u0012{WO\u00197f\u0003Y\u0011\u0018m\u001e(pi2KG/\u001a:bY:+w\rR8vE2,\u0017a\u00048piZ\u000bG.\u001b3OK\u001eT\u0016J\u001c;\u0002%I\fwOT8u-\u0006d\u0017\u000e\u001a(fOjKe\u000e^\u0001\u0012]>$H*\u001b;fe\u0006dg*Z4[\u0013:$\u0018\u0001\u0006:bo:{G\u000fT5uKJ\fGNT3h5&sG/\u0001\to_R4\u0016\r\\5e\u001d\u0016<\'\fT8oO\u0006\u0019\"/Y<O_R4\u0016\r\\5e\u001d\u0016<\'\fT8oO\u0006\u0011bn\u001c;MSR,\'/\u00197OK\u001eTFj\u001c8h\u0003U\u0011\u0018m\u001e(pi2KG/\u001a:bY:+wM\u0017\'p]\u001e\f\u0011C\\8u-\u0006d\u0017\u000e\u001a(fOj3En\\1u\u0003Q\u0011\u0018m\u001e(piZ\u000bG.\u001b3OK\u001eTf\t\\8bi\u0006\u0019bn\u001c;MSR,\'/\u00197OK\u001eTf\t\\8bi\u00061\"/Y<O_Rd\u0015\u000e^3sC2tUm\u001a.GY>\fG/\u0001\no_R4\u0016\r\\5e\u001d\u0016<\'\fR8vE2,\u0017!\u0006:bo:{GOV1mS\u0012tUm\u001a.E_V\u0014G.Z\u0001\u0015]>$H*\u001b;fe\u0006dg*Z4[\t>,(\r\\3\u0002/I\fwOT8u\u0019&$XM]1m\u001d\u0016<\'\fR8vE2,\u0017A\u00068piZ\u000bG.\u001b3Q_N4\u0015N\\5uK\u001acw.\u0019;\u00023I\fwOT8u-\u0006d\u0017\u000e\u001a)pg\u001aKg.\u001b;f\r2|\u0017\r^\u0001\u0019]>$H*\u001b;fe\u0006d\u0007k\\:GS:LG/\u001a$m_\u0006$\u0018a\u0007:bo:{G\u000fT5uKJ\fG\u000eU8t\r&t\u0017\u000e^3GY>\fG/A\fo_R4\u0016\r\\5e!>\u001ch)\u001b8ji\u0016$u.\u001e2mK\u0006Q\"/Y<O_R4\u0016\r\\5e!>\u001ch)\u001b8ji\u0016$u.\u001e2mK\u0006Ibn\u001c;MSR,\'/\u00197Q_N4\u0015N\\5uK\u0012{WO\u00197f\u0003q\u0011\u0018m\u001e(pi2KG/\u001a:bYB{7OR5oSR,Gi\\;cY\u0016\fqC\\8u-\u0006d\u0017\u000e\u001a)pgj3\u0015N\\5uK\u001acw.\u0019;\u00025I\fwOT8u-\u0006d\u0017\u000e\u001a)pgj3\u0015N\\5uK\u001acw.\u0019;\u000239|G\u000fT5uKJ\fG\u000eU8t5\u001aKg.\u001b;f\r2|\u0017\r^\u0001\u001de\u0006<hj\u001c;MSR,\'/\u00197Q_NTf)\u001b8ji\u00164En\\1u\u0003aqw\u000e\u001e,bY&$\u0007k\\:[\r&t\u0017\u000e^3E_V\u0014G.Z\u0001\u001ce\u0006<hj\u001c;WC2LG\rU8t5\u001aKg.\u001b;f\t>,(\r\\3\u000259|G\u000fT5uKJ\fG\u000eU8t5\u001aKg.\u001b;f\t>,(\r\\3\u0002;I\fwOT8u\u0019&$XM]1m!>\u001c(LR5oSR,Gi\\;cY\u0016\faC\\8u-\u0006d\u0017\u000e\u001a(fO\u001aKg.\u001b;f\r2|\u0017\r^\u0001\u001ae\u0006<hj\u001c;WC2LGMT3h\r&t\u0017\u000e^3GY>\fG/\u0001\ro_Rd\u0015\u000e^3sC2tUm\u001a$j]&$XM\u00127pCR\f1D]1x\u001d>$H*\u001b;fe\u0006dg*Z4GS:LG/\u001a$m_\u0006$\u0018a\u00068piZ\u000bG.\u001b3OK\u001e4\u0015N\\5uK\u0012{WO\u00197f\u0003i\u0011\u0018m\u001e(piZ\u000bG.\u001b3OK\u001e4\u0015N\\5uK\u0012{WO\u00197f\u0003eqw\u000e\u001e\'ji\u0016\u0014\u0018\r\u001c(fO\u001aKg.\u001b;f\t>,(\r\\3\u00029I\fwOT8u\u0019&$XM]1m\u001d\u0016<g)\u001b8ji\u0016$u.\u001e2mK\u00069bn\u001c;WC2LGMT3h5\u001aKg.\u001b;f\r2|\u0017\r^\u0001\u001be\u0006<hj\u001c;WC2LGMT3h5\u001aKg.\u001b;f\r2|\u0017\r^\u0001\u001a]>$H*\u001b;fe\u0006dg*Z4[\r&t\u0017\u000e^3GY>\fG/\u0001\u000fsC^tu\u000e\u001e\'ji\u0016\u0014\u0018\r\u001c(fOj3\u0015N\\5uK\u001acw.\u0019;\u000219|GOV1mS\u0012tUm\u001a.GS:LG/\u001a#pk\ndW-A\u000esC^tu\u000e\u001e,bY&$g*Z4[\r&t\u0017\u000e^3E_V\u0014G.Z\u0001\u001b]>$H*\u001b;fe\u0006dg*Z4[\r&t\u0017\u000e^3E_V\u0014G.Z\u0001\u001ee\u0006<hj\u001c;MSR,\'/\u00197OK\u001eTf)\u001b8ji\u0016$u.\u001e2mK\u0006Qbn\u001c;WC2LGMT8o5\u0016\u0014xNR5oSR,g\t\\8bi\u0006i\"/Y<O_R4\u0016\r\\5e\u001d>t\',\u001a:p\r&t\u0017\u000e^3GY>\fG/\u0001\u000fo_Rd\u0015\u000e^3sC2tuN\u001c.fe>4\u0015N\\5uK\u001acw.\u0019;\u0002?I\fwOT8u\u0019&$XM]1m\u001d>t\',\u001a:p\r&t\u0017\u000e^3GY>\fG/A\u000eo_R4\u0016\r\\5e\u001d>t\',\u001a:p\r&t\u0017\u000e^3E_V\u0014G.Z\u0001\u001fe\u0006<hj\u001c;WC2LGMT8o5\u0016\u0014xNR5oSR,Gi\\;cY\u0016\fQD\\8u\u0019&$XM]1m\u001d>t\',\u001a:p\r&t\u0017\u000e^3E_V\u0014G.Z\u0001!e\u0006<hj\u001c;MSR,\'/\u00197O_:TVM]8GS:LG/\u001a#pk\ndW-A\no_R4\u0016\r\\5e\r&t\u0017\u000e^3GY>\fG/\u0001\fsC^tu\u000e\u001e,bY&$g)\u001b8ji\u00164En\\1u\u0003Uqw\u000e\u001e\'ji\u0016\u0014\u0018\r\u001c$j]&$XM\u00127pCR\f\u0001D]1x\u001d>$H*\u001b;fe\u0006dg)\u001b8ji\u00164En\\1u\u0003Qqw\u000e\u001e,bY&$g)\u001b8ji\u0016$u.\u001e2mK\u00069\"/Y<O_R4\u0016\r\\5e\r&t\u0017\u000e^3E_V\u0014G.Z\u0001\u0017]>$H*\u001b;fe\u0006dg)\u001b8ji\u0016$u.\u001e2mK\u0006I\"/Y<O_Rd\u0015\u000e^3sC24\u0015N\\5uK\u0012{WO\u00197f\u0003Mqw\u000e\u001e,bY&$g*^7fe&\u001c7\t[1s\u0003Y\u0011\u0018m\u001e(piZ\u000bG.\u001b3Ok6,\'/[2DQ\u0006\u0014\u0018!\u00068pi2KG/\u001a:bY:+X.\u001a:jG\u000eC\u0017M]\u0001\u0019e\u0006<hj\u001c;MSR,\'/\u00197Ok6,\'/[2DQ\u0006\u0014\u0018aC5om\u0006d\u0017\u000eZ*ju\u0016$BA!\u0002\u0005b\"A!QIAc\u0001\u0004\u0011I#\u0001\bsC^LeN^1mS\u0012\u001c\u0016N_3"
    )
  ScalaSig: length = 0x3 (unknown attribute)
   05 02 00
