Classfile /Users/mw/Projects/slang-braindump/.jar/jar11/assemble/slang-braindump/assemble/content/org/scalactic/StringNormalizations$$anon$1.class
  Last modified May 29, 2022; size 3517 bytes
  SHA-256 checksum 63211e3afb3670b35f29670a8c605e93208f3f019122d762c51974ce1eabf4fa
  Compiled from "StringNormalizations.scala"
public final class org.scalactic.StringNormalizations$$anon$1 implements org.scalactic.AbstractStringUniformity
  minor version: 0
  major version: 52
  flags: (0x0031) ACC_PUBLIC, ACC_FINAL, ACC_SUPER
  this_class: #2                          // org/scalactic/StringNormalizations$$anon$1
  super_class: #4                         // java/lang/Object
  interfaces: 1, fields: 0, methods: 10, attributes: 5
Constant pool:
    #1 = Utf8               org/scalactic/StringNormalizations$$anon$1
    #2 = Class              #1            // org/scalactic/StringNormalizations$$anon$1
    #3 = Utf8               java/lang/Object
    #4 = Class              #3            // java/lang/Object
    #5 = Utf8               org/scalactic/AbstractStringUniformity
    #6 = Class              #5            // org/scalactic/AbstractStringUniformity
    #7 = Utf8               StringNormalizations.scala
    #8 = Utf8               org/scalactic/StringNormalizations
    #9 = Class              #8            // org/scalactic/StringNormalizations
   #10 = Utf8               normalizedCanHandle
   #11 = Utf8               (Ljava/lang/Object;)Z
   #12 = Utf8               b
   #13 = Utf8               normalizedCanHandle$
   #14 = Utf8               (Lorg/scalactic/AbstractStringUniformity;Ljava/lang/Object;)Z
   #15 = NameAndType        #13:#14       // normalizedCanHandle$:(Lorg/scalactic/AbstractStringUniformity;Ljava/lang/Object;)Z
   #16 = InterfaceMethodref #6.#15        // org/scalactic/AbstractStringUniformity.normalizedCanHandle$:(Lorg/scalactic/AbstractStringUniformity;Ljava/lang/Object;)Z
   #17 = Utf8               this
   #18 = Utf8               Lorg/scalactic/StringNormalizations$$anon$1;
   #19 = Utf8               Ljava/lang/Object;
   #20 = Utf8               normalizedOrSame
   #21 = Utf8               (Ljava/lang/Object;)Ljava/lang/Object;
   #22 = Utf8               normalizedOrSame$
   #23 = Utf8               (Lorg/scalactic/AbstractStringUniformity;Ljava/lang/Object;)Ljava/lang/Object;
   #24 = NameAndType        #22:#23       // normalizedOrSame$:(Lorg/scalactic/AbstractStringUniformity;Ljava/lang/Object;)Ljava/lang/Object;
   #25 = InterfaceMethodref #6.#24        // org/scalactic/AbstractStringUniformity.normalizedOrSame$:(Lorg/scalactic/AbstractStringUniformity;Ljava/lang/Object;)Ljava/lang/Object;
   #26 = Utf8               and
   #27 = Utf8               (Lorg/scalactic/Uniformity;)Lorg/scalactic/Uniformity;
   #28 = Utf8               (Lorg/scalactic/Uniformity<Ljava/lang/String;>;)Lorg/scalactic/Uniformity<Ljava/lang/String;>;
   #29 = Utf8               other
   #30 = Utf8               org/scalactic/Uniformity
   #31 = Class              #30           // org/scalactic/Uniformity
   #32 = Utf8               and$
   #33 = Utf8               (Lorg/scalactic/Uniformity;Lorg/scalactic/Uniformity;)Lorg/scalactic/Uniformity;
   #34 = NameAndType        #32:#33       // and$:(Lorg/scalactic/Uniformity;Lorg/scalactic/Uniformity;)Lorg/scalactic/Uniformity;
   #35 = InterfaceMethodref #31.#34       // org/scalactic/Uniformity.and$:(Lorg/scalactic/Uniformity;Lorg/scalactic/Uniformity;)Lorg/scalactic/Uniformity;
   #36 = Utf8               Lorg/scalactic/Uniformity;
   #37 = Utf8               toEquality
   #38 = Utf8               (Lorg/scalactic/Equality;)Lorg/scalactic/NormalizingEquality;
   #39 = Utf8               (Lorg/scalactic/Equality<Ljava/lang/String;>;)Lorg/scalactic/NormalizingEquality<Ljava/lang/String;>;
   #40 = Utf8               equality
   #41 = Utf8               toEquality$
   #42 = Utf8               (Lorg/scalactic/Uniformity;Lorg/scalactic/Equality;)Lorg/scalactic/NormalizingEquality;
   #43 = NameAndType        #41:#42       // toEquality$:(Lorg/scalactic/Uniformity;Lorg/scalactic/Equality;)Lorg/scalactic/NormalizingEquality;
   #44 = InterfaceMethodref #31.#43       // org/scalactic/Uniformity.toEquality$:(Lorg/scalactic/Uniformity;Lorg/scalactic/Equality;)Lorg/scalactic/NormalizingEquality;
   #45 = Utf8               Lorg/scalactic/Equality;
   #46 = Utf8               (Lorg/scalactic/Normalization;)Lorg/scalactic/Normalization;
   #47 = Utf8               (Lorg/scalactic/Normalization<Ljava/lang/String;>;)Lorg/scalactic/Normalization<Ljava/lang/String;>;
   #48 = Utf8               org/scalactic/Normalization
   #49 = Class              #48           // org/scalactic/Normalization
   #50 = Utf8               (Lorg/scalactic/Normalization;Lorg/scalactic/Normalization;)Lorg/scalactic/Normalization;
   #51 = NameAndType        #32:#50       // and$:(Lorg/scalactic/Normalization;Lorg/scalactic/Normalization;)Lorg/scalactic/Normalization;
   #52 = InterfaceMethodref #49.#51       // org/scalactic/Normalization.and$:(Lorg/scalactic/Normalization;Lorg/scalactic/Normalization;)Lorg/scalactic/Normalization;
   #53 = Utf8               Lorg/scalactic/Normalization;
   #54 = Utf8               toEquivalence
   #55 = Utf8               (Lorg/scalactic/Equivalence;)Lorg/scalactic/NormalizingEquivalence;
   #56 = Utf8               (Lorg/scalactic/Equivalence<Ljava/lang/String;>;)Lorg/scalactic/NormalizingEquivalence<Ljava/lang/String;>;
   #57 = Utf8               equivalence
   #58 = Utf8               toEquivalence$
   #59 = Utf8               (Lorg/scalactic/Normalization;Lorg/scalactic/Equivalence;)Lorg/scalactic/NormalizingEquivalence;
   #60 = NameAndType        #58:#59       // toEquivalence$:(Lorg/scalactic/Normalization;Lorg/scalactic/Equivalence;)Lorg/scalactic/NormalizingEquivalence;
   #61 = InterfaceMethodref #49.#60       // org/scalactic/Normalization.toEquivalence$:(Lorg/scalactic/Normalization;Lorg/scalactic/Equivalence;)Lorg/scalactic/NormalizingEquivalence;
   #62 = Utf8               Lorg/scalactic/Equivalence;
   #63 = Utf8               normalized
   #64 = Utf8               (Ljava/lang/String;)Ljava/lang/String;
   #65 = Utf8               s
   #66 = Utf8               java/lang/String
   #67 = Class              #66           // java/lang/String
   #68 = Utf8               toLowerCase
   #69 = Utf8               ()Ljava/lang/String;
   #70 = NameAndType        #68:#69       // toLowerCase:()Ljava/lang/String;
   #71 = Methodref          #67.#70       // java/lang/String.toLowerCase:()Ljava/lang/String;
   #72 = Utf8               Ljava/lang/String;
   #73 = Utf8               toString
   #74 = Utf8               lowerCased
   #75 = String             #74           // lowerCased
   #76 = Utf8               a
   #77 = NameAndType        #63:#64       // normalized:(Ljava/lang/String;)Ljava/lang/String;
   #78 = Methodref          #2.#77        // org/scalactic/StringNormalizations$$anon$1.normalized:(Ljava/lang/String;)Ljava/lang/String;
   #79 = Utf8               <init>
   #80 = Utf8               (Lorg/scalactic/StringNormalizations;)V
   #81 = Utf8               $outer
   #82 = Utf8               ()V
   #83 = NameAndType        #79:#82       // "<init>":()V
   #84 = Methodref          #4.#83        // java/lang/Object."<init>":()V
   #85 = Utf8               $init$
   #86 = Utf8               (Lorg/scalactic/Normalization;)V
   #87 = NameAndType        #85:#86       // $init$:(Lorg/scalactic/Normalization;)V
   #88 = InterfaceMethodref #49.#87       // org/scalactic/Normalization.$init$:(Lorg/scalactic/Normalization;)V
   #89 = Utf8               (Lorg/scalactic/Uniformity;)V
   #90 = NameAndType        #85:#89       // $init$:(Lorg/scalactic/Uniformity;)V
   #91 = InterfaceMethodref #31.#90       // org/scalactic/Uniformity.$init$:(Lorg/scalactic/Uniformity;)V
   #92 = Utf8               (Lorg/scalactic/AbstractStringUniformity;)V
   #93 = NameAndType        #85:#92       // $init$:(Lorg/scalactic/AbstractStringUniformity;)V
   #94 = InterfaceMethodref #6.#93        // org/scalactic/AbstractStringUniformity.$init$:(Lorg/scalactic/AbstractStringUniformity;)V
   #95 = Utf8               Lorg/scalactic/StringNormalizations;
   #96 = Utf8               Code
   #97 = Utf8               LineNumberTable
   #98 = Utf8               LocalVariableTable
   #99 = Utf8               MethodParameters
  #100 = Utf8               Signature
  #101 = Utf8               InnerClasses
  #102 = Utf8               EnclosingMethod
  #103 = Utf8               SourceFile
  #104 = Utf8               ScalaInlineInfo
  #105 = Utf8               Scala
{
  public final boolean normalizedCanHandle(java.lang.Object);
    descriptor: (Ljava/lang/Object;)Z
    flags: (0x0011) ACC_PUBLIC, ACC_FINAL
    Code:
      stack=2, locals=2, args_size=2
         0: aload_0
         1: aload_1
         2: invokestatic  #16                 // InterfaceMethod org/scalactic/AbstractStringUniformity.normalizedCanHandle$:(Lorg/scalactic/AbstractStringUniformity;Ljava/lang/Object;)Z
         5: ireturn
      LineNumberTable:
        line 33: 0
      LocalVariableTable:
        Start  Length  Slot  Name   Signature
            0       6     0  this   Lorg/scalactic/StringNormalizations$$anon$1;
            0       6     1     b   Ljava/lang/Object;
    MethodParameters:
      Name                           Flags
      b                              final

  public final java.lang.Object normalizedOrSame(java.lang.Object);
    descriptor: (Ljava/lang/Object;)Ljava/lang/Object;
    flags: (0x0011) ACC_PUBLIC, ACC_FINAL
    Code:
      stack=2, locals=2, args_size=2
         0: aload_0
         1: aload_1
         2: invokestatic  #25                 // InterfaceMethod org/scalactic/AbstractStringUniformity.normalizedOrSame$:(Lorg/scalactic/AbstractStringUniformity;Ljava/lang/Object;)Ljava/lang/Object;
         5: areturn
      LineNumberTable:
        line 33: 0
      LocalVariableTable:
        Start  Length  Slot  Name   Signature
            0       6     0  this   Lorg/scalactic/StringNormalizations$$anon$1;
            0       6     1     b   Ljava/lang/Object;
    MethodParameters:
      Name                           Flags
      b                              final

  public final org.scalactic.Uniformity<java.lang.String> and(org.scalactic.Uniformity<java.lang.String>);
    descriptor: (Lorg/scalactic/Uniformity;)Lorg/scalactic/Uniformity;
    flags: (0x0011) ACC_PUBLIC, ACC_FINAL
    Code:
      stack=2, locals=2, args_size=2
         0: aload_0
         1: aload_1
         2: invokestatic  #35                 // InterfaceMethod org/scalactic/Uniformity.and$:(Lorg/scalactic/Uniformity;Lorg/scalactic/Uniformity;)Lorg/scalactic/Uniformity;
         5: areturn
      LineNumberTable:
        line 33: 0
      LocalVariableTable:
        Start  Length  Slot  Name   Signature
            0       6     0  this   Lorg/scalactic/StringNormalizations$$anon$1;
            0       6     1 other   Lorg/scalactic/Uniformity;
    Signature: #28                          // (Lorg/scalactic/Uniformity<Ljava/lang/String;>;)Lorg/scalactic/Uniformity<Ljava/lang/String;>;
    MethodParameters:
      Name                           Flags
      other                          final

  public final org.scalactic.NormalizingEquality<java.lang.String> toEquality(org.scalactic.Equality<java.lang.String>);
    descriptor: (Lorg/scalactic/Equality;)Lorg/scalactic/NormalizingEquality;
    flags: (0x0011) ACC_PUBLIC, ACC_FINAL
    Code:
      stack=2, locals=2, args_size=2
         0: aload_0
         1: aload_1
         2: invokestatic  #44                 // InterfaceMethod org/scalactic/Uniformity.toEquality$:(Lorg/scalactic/Uniformity;Lorg/scalactic/Equality;)Lorg/scalactic/NormalizingEquality;
         5: areturn
      LineNumberTable:
        line 33: 0
      LocalVariableTable:
        Start  Length  Slot  Name   Signature
            0       6     0  this   Lorg/scalactic/StringNormalizations$$anon$1;
            0       6     1 equality   Lorg/scalactic/Equality;
    Signature: #39                          // (Lorg/scalactic/Equality<Ljava/lang/String;>;)Lorg/scalactic/NormalizingEquality<Ljava/lang/String;>;
    MethodParameters:
      Name                           Flags
      equality                       final

  public final org.scalactic.Normalization<java.lang.String> and(org.scalactic.Normalization<java.lang.String>);
    descriptor: (Lorg/scalactic/Normalization;)Lorg/scalactic/Normalization;
    flags: (0x0011) ACC_PUBLIC, ACC_FINAL
    Code:
      stack=2, locals=2, args_size=2
         0: aload_0
         1: aload_1
         2: invokestatic  #52                 // InterfaceMethod org/scalactic/Normalization.and$:(Lorg/scalactic/Normalization;Lorg/scalactic/Normalization;)Lorg/scalactic/Normalization;
         5: areturn
      LineNumberTable:
        line 33: 0
      LocalVariableTable:
        Start  Length  Slot  Name   Signature
            0       6     0  this   Lorg/scalactic/StringNormalizations$$anon$1;
            0       6     1 other   Lorg/scalactic/Normalization;
    Signature: #47                          // (Lorg/scalactic/Normalization<Ljava/lang/String;>;)Lorg/scalactic/Normalization<Ljava/lang/String;>;
    MethodParameters:
      Name                           Flags
      other                          final

  public final org.scalactic.NormalizingEquivalence<java.lang.String> toEquivalence(org.scalactic.Equivalence<java.lang.String>);
    descriptor: (Lorg/scalactic/Equivalence;)Lorg/scalactic/NormalizingEquivalence;
    flags: (0x0011) ACC_PUBLIC, ACC_FINAL
    Code:
      stack=2, locals=2, args_size=2
         0: aload_0
         1: aload_1
         2: invokestatic  #61                 // InterfaceMethod org/scalactic/Normalization.toEquivalence$:(Lorg/scalactic/Normalization;Lorg/scalactic/Equivalence;)Lorg/scalactic/NormalizingEquivalence;
         5: areturn
      LineNumberTable:
        line 33: 0
      LocalVariableTable:
        Start  Length  Slot  Name   Signature
            0       6     0  this   Lorg/scalactic/StringNormalizations$$anon$1;
            0       6     1 equivalence   Lorg/scalactic/Equivalence;
    Signature: #56                          // (Lorg/scalactic/Equivalence<Ljava/lang/String;>;)Lorg/scalactic/NormalizingEquivalence<Ljava/lang/String;>;
    MethodParameters:
      Name                           Flags
      equivalence                    final

  public java.lang.String normalized(java.lang.String);
    descriptor: (Ljava/lang/String;)Ljava/lang/String;
    flags: (0x0001) ACC_PUBLIC
    Code:
      stack=1, locals=2, args_size=2
         0: aload_1
         1: invokevirtual #71                 // Method java/lang/String.toLowerCase:()Ljava/lang/String;
         4: areturn
      LineNumberTable:
        line 40: 0
      LocalVariableTable:
        Start  Length  Slot  Name   Signature
            0       5     0  this   Lorg/scalactic/StringNormalizations$$anon$1;
            0       5     1     s   Ljava/lang/String;
    MethodParameters:
      Name                           Flags
      s                              final

  public java.lang.String toString();
    descriptor: ()Ljava/lang/String;
    flags: (0x0001) ACC_PUBLIC
    Code:
      stack=1, locals=1, args_size=1
         0: ldc           #75                 // String lowerCased
         2: areturn
      LineNumberTable:
        line 42: 0
      LocalVariableTable:
        Start  Length  Slot  Name   Signature
            0       3     0  this   Lorg/scalactic/StringNormalizations$$anon$1;

  public java.lang.Object normalized(java.lang.Object);
    descriptor: (Ljava/lang/Object;)Ljava/lang/Object;
    flags: (0x1041) ACC_PUBLIC, ACC_BRIDGE, ACC_SYNTHETIC
    Code:
      stack=2, locals=2, args_size=2
         0: aload_0
         1: aload_1
         2: checkcast     #67                 // class java/lang/String
         5: invokevirtual #78                 // Method normalized:(Ljava/lang/String;)Ljava/lang/String;
         8: areturn
      LineNumberTable:
        line 33: 0
      LocalVariableTable:
        Start  Length  Slot  Name   Signature
            0       9     0  this   Lorg/scalactic/StringNormalizations$$anon$1;
            0       9     1     a   Ljava/lang/Object;
    MethodParameters:
      Name                           Flags
      a                              final

  public org.scalactic.StringNormalizations$$anon$1(org.scalactic.StringNormalizations);
    descriptor: (Lorg/scalactic/StringNormalizations;)V
    flags: (0x0001) ACC_PUBLIC
    Code:
      stack=1, locals=2, args_size=2
         0: aload_0
         1: invokespecial #84                 // Method java/lang/Object."<init>":()V
         4: aload_0
         5: invokestatic  #88                 // InterfaceMethod org/scalactic/Normalization.$init$:(Lorg/scalactic/Normalization;)V
         8: aload_0
         9: invokestatic  #91                 // InterfaceMethod org/scalactic/Uniformity.$init$:(Lorg/scalactic/Uniformity;)V
        12: aload_0
        13: invokestatic  #94                 // InterfaceMethod org/scalactic/AbstractStringUniformity.$init$:(Lorg/scalactic/AbstractStringUniformity;)V
        16: return
      LineNumberTable:
        line 33: 0
      LocalVariableTable:
        Start  Length  Slot  Name   Signature
            0      17     0  this   Lorg/scalactic/StringNormalizations$$anon$1;
            0      17     1 $outer   Lorg/scalactic/StringNormalizations;
    MethodParameters:
      Name                           Flags
      $outer                         final synthetic
}
InnerClasses:
  public final #2;                        // class org/scalactic/StringNormalizations$$anon$1
EnclosingMethod: #9.#0                  // org.scalactic.StringNormalizations
SourceFile: "StringNormalizations.scala"
  ScalaInlineInfo: length = 0x36 (unknown attribute)
   01 01 00 0A 00 4F 00 50 01 00 1A 00 2E 01 00 1A
   00 1B 01 00 3F 00 15 01 00 3F 00 40 01 00 0A 00
   0B 01 00 14 00 15 01 00 25 00 26 01 00 36 00 37
   01 00 49 00 45 01
  Scala: length = 0x0 (unknown attribute)

