Classfile /Users/mw/Projects/slang-braindump/.jar/jar11/assemble/slang-braindump/assemble/content/org/scalactic/StringDiffer$.class
  Last modified May 29, 2022; size 978 bytes
  SHA-256 checksum e88acbb46dafb6f1d98929cc711adb045664cf0e1c5b15ba3259c89ccf404b86
  Compiled from "Differ.scala"
public final class org.scalactic.StringDiffer$ implements org.scalactic.StringDiffer
  minor version: 0
  major version: 52
  flags: (0x0031) ACC_PUBLIC, ACC_FINAL, ACC_SUPER
  this_class: #2                          // org/scalactic/StringDiffer$
  super_class: #4                         // java/lang/Object
  interfaces: 1, fields: 1, methods: 3, attributes: 3
Constant pool:
   #1 = Utf8               org/scalactic/StringDiffer$
   #2 = Class              #1             // org/scalactic/StringDiffer$
   #3 = Utf8               java/lang/Object
   #4 = Class              #3             // java/lang/Object
   #5 = Utf8               org/scalactic/StringDiffer
   #6 = Class              #5             // org/scalactic/StringDiffer
   #7 = Utf8               Differ.scala
   #8 = Utf8               MODULE$
   #9 = Utf8               Lorg/scalactic/StringDiffer$;
  #10 = Utf8               <clinit>
  #11 = Utf8               ()V
  #12 = Utf8               <init>
  #13 = NameAndType        #12:#11        // "<init>":()V
  #14 = Methodref          #2.#13         // org/scalactic/StringDiffer$."<init>":()V
  #15 = NameAndType        #8:#9          // MODULE$:Lorg/scalactic/StringDiffer$;
  #16 = Fieldref           #2.#15         // org/scalactic/StringDiffer$.MODULE$:Lorg/scalactic/StringDiffer$;
  #17 = Utf8               $init$
  #18 = Utf8               (Lorg/scalactic/StringDiffer;)V
  #19 = NameAndType        #17:#18        // $init$:(Lorg/scalactic/StringDiffer;)V
  #20 = InterfaceMethodref #6.#19         // org/scalactic/StringDiffer.$init$:(Lorg/scalactic/StringDiffer;)V
  #21 = Utf8               difference
  #22 = Utf8               (Ljava/lang/Object;Ljava/lang/Object;Lorg/scalactic/Prettifier;)Lorg/scalactic/PrettyPair;
  #23 = Utf8               a
  #24 = Utf8               b
  #25 = Utf8               prettifier
  #26 = Utf8               difference$
  #27 = Utf8               (Lorg/scalactic/StringDiffer;Ljava/lang/Object;Ljava/lang/Object;Lorg/scalactic/Prettifier;)Lorg/scalactic/PrettyPair;
  #28 = NameAndType        #26:#27        // difference$:(Lorg/scalactic/StringDiffer;Ljava/lang/Object;Ljava/lang/Object;Lorg/scalactic/Prettifier;)Lorg/scalactic/PrettyPair;
  #29 = InterfaceMethodref #6.#28         // org/scalactic/StringDiffer.difference$:(Lorg/scalactic/StringDiffer;Ljava/lang/Object;Ljava/lang/Object;Lorg/scalactic/Prettifier;)Lorg/scalactic/PrettyPair;
  #30 = Utf8               this
  #31 = Utf8               Ljava/lang/Object;
  #32 = Utf8               Lorg/scalactic/Prettifier;
  #33 = Methodref          #4.#13         // java/lang/Object."<init>":()V
  #34 = Utf8               Code
  #35 = Utf8               LineNumberTable
  #36 = Utf8               LocalVariableTable
  #37 = Utf8               MethodParameters
  #38 = Utf8               SourceFile
  #39 = Utf8               ScalaInlineInfo
  #40 = Utf8               Scala
{
  public static final org.scalactic.StringDiffer$ MODULE$;
    descriptor: Lorg/scalactic/StringDiffer$;
    flags: (0x0019) ACC_PUBLIC, ACC_STATIC, ACC_FINAL

  public static {};
    descriptor: ()V
    flags: (0x0009) ACC_PUBLIC, ACC_STATIC
    Code:
      stack=2, locals=0, args_size=0
         0: new           #2                  // class org/scalactic/StringDiffer$
         3: dup
         4: invokespecial #14                 // Method "<init>":()V
         7: putstatic     #16                 // Field MODULE$:Lorg/scalactic/StringDiffer$;
        10: getstatic     #16                 // Field MODULE$:Lorg/scalactic/StringDiffer$;
        13: invokestatic  #20                 // InterfaceMethod org/scalactic/StringDiffer.$init$:(Lorg/scalactic/StringDiffer;)V
        16: return
      LineNumberTable:
        line 114: 0

  public org.scalactic.PrettyPair difference(java.lang.Object, java.lang.Object, org.scalactic.Prettifier);
    descriptor: (Ljava/lang/Object;Ljava/lang/Object;Lorg/scalactic/Prettifier;)Lorg/scalactic/PrettyPair;
    flags: (0x0001) ACC_PUBLIC
    Code:
      stack=4, locals=4, args_size=4
         0: aload_0
         1: aload_1
         2: aload_2
         3: aload_3
         4: invokestatic  #29                 // InterfaceMethod org/scalactic/StringDiffer.difference$:(Lorg/scalactic/StringDiffer;Ljava/lang/Object;Ljava/lang/Object;Lorg/scalactic/Prettifier;)Lorg/scalactic/PrettyPair;
         7: areturn
      LineNumberTable:
        line 114: 0
      LocalVariableTable:
        Start  Length  Slot  Name   Signature
            0       8     0  this   Lorg/scalactic/StringDiffer$;
            0       8     1     a   Ljava/lang/Object;
            0       8     2     b   Ljava/lang/Object;
            0       8     3 prettifier   Lorg/scalactic/Prettifier;
    MethodParameters:
      Name                           Flags
      a                              final
      b                              final
      prettifier                     final

  private org.scalactic.StringDiffer$();
    descriptor: ()V
    flags: (0x0002) ACC_PRIVATE
    Code:
      stack=1, locals=1, args_size=1
         0: aload_0
         1: invokespecial #33                 // Method java/lang/Object."<init>":()V
         4: return
      LineNumberTable:
        line 114: 0
      LocalVariableTable:
        Start  Length  Slot  Name   Signature
            0       5     0  this   Lorg/scalactic/StringDiffer$;
}
SourceFile: "Differ.scala"
  ScalaInlineInfo: length = 0xE (unknown attribute)
   01 01 00 02 00 0C 00 0B 01 00 15 00 16 01
  Scala: length = 0x0 (unknown attribute)

