Classfile /Users/mw/Projects/slang-braindump/.jar/jar11/assemble/slang-braindump/assemble/content/org/scalactic/TripleEqualsSupport$BToAEquivalenceConstraint.class
  Last modified May 29, 2022; size 1340 bytes
  SHA-256 checksum d25c34e43df1011afb3d114104caf598a46f838ebd9b12735bda6d7cb6431aef
  Compiled from "TripleEqualsSupport.scala"
public final class org.scalactic.TripleEqualsSupport$BToAEquivalenceConstraint<A extends java.lang.Object, B extends java.lang.Object> extends org.scalactic.CanEqual<A, B>
  minor version: 0
  major version: 52
  flags: (0x0031) ACC_PUBLIC, ACC_FINAL, ACC_SUPER
  this_class: #2                          // org/scalactic/TripleEqualsSupport$BToAEquivalenceConstraint
  super_class: #5                         // org/scalactic/CanEqual
  interfaces: 0, fields: 2, methods: 2, attributes: 5
Constant pool:
   #1 = Utf8               org/scalactic/TripleEqualsSupport$BToAEquivalenceConstraint
   #2 = Class              #1             // org/scalactic/TripleEqualsSupport$BToAEquivalenceConstraint
   #3 = Utf8               <A:Ljava/lang/Object;B:Ljava/lang/Object;>Lorg/scalactic/CanEqual<TA;TB;>;
   #4 = Utf8               org/scalactic/CanEqual
   #5 = Class              #4             // org/scalactic/CanEqual
   #6 = Utf8               TripleEqualsSupport.scala
   #7 = Utf8               org/scalactic/TripleEqualsSupport
   #8 = Class              #7             // org/scalactic/TripleEqualsSupport
   #9 = Utf8               BToAEquivalenceConstraint
  #10 = Utf8               equivalenceOfA
  #11 = Utf8               Lorg/scalactic/Equivalence;
  #12 = Utf8               Lorg/scalactic/Equivalence<TA;>;
  #13 = Utf8               cnv
  #14 = Utf8               Lscala/Function1;
  #15 = Utf8               Lscala/Function1<TB;TA;>;
  #16 = Utf8               areEqual
  #17 = Utf8               (Ljava/lang/Object;Ljava/lang/Object;)Z
  #18 = Utf8               (TA;TB;)Z
  #19 = Utf8               a
  #20 = Utf8               b
  #21 = NameAndType        #10:#11        // equivalenceOfA:Lorg/scalactic/Equivalence;
  #22 = Fieldref           #2.#21         // org/scalactic/TripleEqualsSupport$BToAEquivalenceConstraint.equivalenceOfA:Lorg/scalactic/Equivalence;
  #23 = NameAndType        #13:#14        // cnv:Lscala/Function1;
  #24 = Fieldref           #2.#23         // org/scalactic/TripleEqualsSupport$BToAEquivalenceConstraint.cnv:Lscala/Function1;
  #25 = Utf8               scala/Function1
  #26 = Class              #25            // scala/Function1
  #27 = Utf8               apply
  #28 = Utf8               (Ljava/lang/Object;)Ljava/lang/Object;
  #29 = NameAndType        #27:#28        // apply:(Ljava/lang/Object;)Ljava/lang/Object;
  #30 = InterfaceMethodref #26.#29        // scala/Function1.apply:(Ljava/lang/Object;)Ljava/lang/Object;
  #31 = Utf8               org/scalactic/Equivalence
  #32 = Class              #31            // org/scalactic/Equivalence
  #33 = Utf8               areEquivalent
  #34 = NameAndType        #33:#17        // areEquivalent:(Ljava/lang/Object;Ljava/lang/Object;)Z
  #35 = InterfaceMethodref #32.#34        // org/scalactic/Equivalence.areEquivalent:(Ljava/lang/Object;Ljava/lang/Object;)Z
  #36 = Utf8               this
  #37 = Utf8               Lorg/scalactic/TripleEqualsSupport$BToAEquivalenceConstraint;
  #38 = Utf8               Ljava/lang/Object;
  #39 = Utf8               <init>
  #40 = Utf8               (Lorg/scalactic/Equivalence;Lscala/Function1;)V
  #41 = Utf8               (Lorg/scalactic/Equivalence<TA;>;Lscala/Function1<TB;TA;>;)V
  #42 = Utf8               ()V
  #43 = NameAndType        #39:#42        // "<init>":()V
  #44 = Methodref          #5.#43         // org/scalactic/CanEqual."<init>":()V
  #45 = Utf8               Signature
  #46 = Utf8               Code
  #47 = Utf8               LineNumberTable
  #48 = Utf8               LocalVariableTable
  #49 = Utf8               MethodParameters
  #50 = Utf8               InnerClasses
  #51 = Utf8               SourceFile
  #52 = Utf8               ScalaInlineInfo
  #53 = Utf8               Scala
{
  private final org.scalactic.Equivalence<A> equivalenceOfA;
    descriptor: Lorg/scalactic/Equivalence;
    flags: (0x0012) ACC_PRIVATE, ACC_FINAL
    Signature: #12                          // Lorg/scalactic/Equivalence<TA;>;

  private final scala.Function1<B, A> cnv;
    descriptor: Lscala/Function1;
    flags: (0x0012) ACC_PRIVATE, ACC_FINAL
    Signature: #15                          // Lscala/Function1<TB;TA;>;

  public boolean areEqual(A, B);
    descriptor: (Ljava/lang/Object;Ljava/lang/Object;)Z
    flags: (0x0001) ACC_PUBLIC
    Code:
      stack=4, locals=3, args_size=3
         0: aload_0
         1: getfield      #22                 // Field equivalenceOfA:Lorg/scalactic/Equivalence;
         4: aload_1
         5: aload_0
         6: getfield      #24                 // Field cnv:Lscala/Function1;
         9: aload_2
        10: invokeinterface #30,  2           // InterfaceMethod scala/Function1.apply:(Ljava/lang/Object;)Ljava/lang/Object;
        15: invokeinterface #35,  3           // InterfaceMethod org/scalactic/Equivalence.areEquivalent:(Ljava/lang/Object;Ljava/lang/Object;)Z
        20: ireturn
      LineNumberTable:
        line 653: 0
      LocalVariableTable:
        Start  Length  Slot  Name   Signature
            0      21     0  this   Lorg/scalactic/TripleEqualsSupport$BToAEquivalenceConstraint;
            0      21     1     a   Ljava/lang/Object;
            0      21     2     b   Ljava/lang/Object;
    Signature: #18                          // (TA;TB;)Z
    MethodParameters:
      Name                           Flags
      a                              final
      b                              final

  public org.scalactic.TripleEqualsSupport$BToAEquivalenceConstraint(org.scalactic.Equivalence<A>, scala.Function1<B, A>);
    descriptor: (Lorg/scalactic/Equivalence;Lscala/Function1;)V
    flags: (0x0001) ACC_PUBLIC
    Code:
      stack=2, locals=3, args_size=3
         0: aload_0
         1: aload_1
         2: putfield      #22                 // Field equivalenceOfA:Lorg/scalactic/Equivalence;
         5: aload_0
         6: aload_2
         7: putfield      #24                 // Field cnv:Lscala/Function1;
        10: aload_0
        11: invokespecial #44                 // Method org/scalactic/CanEqual."<init>":()V
        14: return
      LineNumberTable:
        line 639: 0
      LocalVariableTable:
        Start  Length  Slot  Name   Signature
            0      15     0  this   Lorg/scalactic/TripleEqualsSupport$BToAEquivalenceConstraint;
            0      15     1 equivalenceOfA   Lorg/scalactic/Equivalence;
            0      15     2   cnv   Lscala/Function1;
    Signature: #41                          // (Lorg/scalactic/Equivalence<TA;>;Lscala/Function1<TB;TA;>;)V
    MethodParameters:
      Name                           Flags
      equivalenceOfA                 final
      cnv                            final
}
InnerClasses:
  public static final #9= #2 of #8;       // BToAEquivalenceConstraint=class org/scalactic/TripleEqualsSupport$BToAEquivalenceConstraint of class org/scalactic/TripleEqualsSupport
Signature: #3                           // <A:Ljava/lang/Object;B:Ljava/lang/Object;>Lorg/scalactic/CanEqual<TA;TB;>;
SourceFile: "TripleEqualsSupport.scala"
  ScalaInlineInfo: length = 0xE (unknown attribute)
   01 01 00 02 00 27 00 28 01 00 10 00 11 01
  Scala: length = 0x0 (unknown attribute)

