Classfile /Users/mw/Projects/slang-braindump/.jar/jar11/assemble/slang-braindump/assemble/content/coursier/util/shaded/org/jsoup/select/Evaluator$AttributeWithValueMatching.class
  Last modified May 29, 2022; size 1632 bytes
  SHA-256 checksum 22242a971915b0ba97cf219709c44cd5a90c03808889c5db3ad08259f3b534e4
  Compiled from "Evaluator.java"
public final class coursier.util.shaded.org.jsoup.select.Evaluator$AttributeWithValueMatching extends coursier.util.shaded.org.jsoup.select.Evaluator
  minor version: 0
  major version: 51
  flags: (0x0031) ACC_PUBLIC, ACC_FINAL, ACC_SUPER
  this_class: #2                          // coursier/util/shaded/org/jsoup/select/Evaluator$AttributeWithValueMatching
  super_class: #4                         // coursier/util/shaded/org/jsoup/select/Evaluator
  interfaces: 0, fields: 2, methods: 3, attributes: 2
Constant pool:
   #1 = Utf8               coursier/util/shaded/org/jsoup/select/Evaluator$AttributeWithValueMatching
   #2 = Class              #1             // coursier/util/shaded/org/jsoup/select/Evaluator$AttributeWithValueMatching
   #3 = Utf8               coursier/util/shaded/org/jsoup/select/Evaluator
   #4 = Class              #3             // coursier/util/shaded/org/jsoup/select/Evaluator
   #5 = Utf8               Evaluator.java
   #6 = Utf8               AttributeWithValueMatching
   #7 = Utf8               key
   #8 = Utf8               Ljava/lang/String;
   #9 = Utf8               pattern
  #10 = Utf8               Ljava/util/regex/Pattern;
  #11 = Utf8               <init>
  #12 = Utf8               (Ljava/lang/String;Ljava/util/regex/Pattern;)V
  #13 = Utf8               ()V
  #14 = NameAndType        #11:#13        // "<init>":()V
  #15 = Methodref          #4.#14         // coursier/util/shaded/org/jsoup/select/Evaluator."<init>":()V
  #16 = Utf8               coursier/util/shaded/org/jsoup/internal/Normalizer
  #17 = Class              #16            // coursier/util/shaded/org/jsoup/internal/Normalizer
  #18 = Utf8               normalize
  #19 = Utf8               (Ljava/lang/String;)Ljava/lang/String;
  #20 = NameAndType        #18:#19        // normalize:(Ljava/lang/String;)Ljava/lang/String;
  #21 = Methodref          #17.#20        // coursier/util/shaded/org/jsoup/internal/Normalizer.normalize:(Ljava/lang/String;)Ljava/lang/String;
  #22 = NameAndType        #7:#8          // key:Ljava/lang/String;
  #23 = Fieldref           #2.#22         // coursier/util/shaded/org/jsoup/select/Evaluator$AttributeWithValueMatching.key:Ljava/lang/String;
  #24 = NameAndType        #9:#10         // pattern:Ljava/util/regex/Pattern;
  #25 = Fieldref           #2.#24         // coursier/util/shaded/org/jsoup/select/Evaluator$AttributeWithValueMatching.pattern:Ljava/util/regex/Pattern;
  #26 = Utf8               this
  #27 = Utf8               Lcoursier/util/shaded/org/jsoup/select/Evaluator$AttributeWithValueMatching;
  #28 = Utf8               matches
  #29 = Utf8               (Lcoursier/util/shaded/org/jsoup/nodes/Element;Lcoursier/util/shaded/org/jsoup/nodes/Element;)Z
  #30 = Utf8               coursier/util/shaded/org/jsoup/nodes/Element
  #31 = Class              #30            // coursier/util/shaded/org/jsoup/nodes/Element
  #32 = Utf8               hasAttr
  #33 = Utf8               (Ljava/lang/String;)Z
  #34 = NameAndType        #32:#33        // hasAttr:(Ljava/lang/String;)Z
  #35 = Methodref          #31.#34        // coursier/util/shaded/org/jsoup/nodes/Element.hasAttr:(Ljava/lang/String;)Z
  #36 = Utf8               attr
  #37 = NameAndType        #36:#19        // attr:(Ljava/lang/String;)Ljava/lang/String;
  #38 = Methodref          #31.#37        // coursier/util/shaded/org/jsoup/nodes/Element.attr:(Ljava/lang/String;)Ljava/lang/String;
  #39 = Utf8               java/util/regex/Pattern
  #40 = Class              #39            // java/util/regex/Pattern
  #41 = Utf8               matcher
  #42 = Utf8               (Ljava/lang/CharSequence;)Ljava/util/regex/Matcher;
  #43 = NameAndType        #41:#42        // matcher:(Ljava/lang/CharSequence;)Ljava/util/regex/Matcher;
  #44 = Methodref          #40.#43        // java/util/regex/Pattern.matcher:(Ljava/lang/CharSequence;)Ljava/util/regex/Matcher;
  #45 = Utf8               java/util/regex/Matcher
  #46 = Class              #45            // java/util/regex/Matcher
  #47 = Utf8               find
  #48 = Utf8               ()Z
  #49 = NameAndType        #47:#48        // find:()Z
  #50 = Methodref          #46.#49        // java/util/regex/Matcher.find:()Z
  #51 = Utf8               root
  #52 = Utf8               Lcoursier/util/shaded/org/jsoup/nodes/Element;
  #53 = Utf8               element
  #54 = Utf8               toString
  #55 = Utf8               ()Ljava/lang/String;
  #56 = Utf8               [%s~=%s]
  #57 = String             #56            // [%s~=%s]
  #58 = Utf8               java/lang/Object
  #59 = Class              #58            // java/lang/Object
  #60 = NameAndType        #54:#55        // toString:()Ljava/lang/String;
  #61 = Methodref          #40.#60        // java/util/regex/Pattern.toString:()Ljava/lang/String;
  #62 = Utf8               java/lang/String
  #63 = Class              #62            // java/lang/String
  #64 = Utf8               format
  #65 = Utf8               (Ljava/lang/String;[Ljava/lang/Object;)Ljava/lang/String;
  #66 = NameAndType        #64:#65        // format:(Ljava/lang/String;[Ljava/lang/Object;)Ljava/lang/String;
  #67 = Methodref          #63.#66        // java/lang/String.format:(Ljava/lang/String;[Ljava/lang/Object;)Ljava/lang/String;
  #68 = Utf8               Code
  #69 = Utf8               LineNumberTable
  #70 = Utf8               LocalVariableTable
  #71 = Utf8               StackMapTable
  #72 = Utf8               InnerClasses
  #73 = Utf8               SourceFile
{
  java.lang.String key;
    descriptor: Ljava/lang/String;
    flags: (0x0000)

  java.util.regex.Pattern pattern;
    descriptor: Ljava/util/regex/Pattern;
    flags: (0x0000)

  public coursier.util.shaded.org.jsoup.select.Evaluator$AttributeWithValueMatching(java.lang.String, java.util.regex.Pattern);
    descriptor: (Ljava/lang/String;Ljava/util/regex/Pattern;)V
    flags: (0x0001) ACC_PUBLIC
    Code:
      stack=2, locals=3, args_size=3
         0: aload_0
         1: invokespecial #15                 // Method coursier/util/shaded/org/jsoup/select/Evaluator."<init>":()V
         4: aload_0
         5: aload_1
         6: invokestatic  #21                 // Method coursier/util/shaded/org/jsoup/internal/Normalizer.normalize:(Ljava/lang/String;)Ljava/lang/String;
         9: putfield      #23                 // Field key:Ljava/lang/String;
        12: aload_0
        13: aload_2
        14: putfield      #25                 // Field pattern:Ljava/util/regex/Pattern;
        17: return
      LineNumberTable:
        line 282: 0
        line 283: 4
        line 284: 12
        line 285: 17
      LocalVariableTable:
        Start  Length  Slot  Name   Signature
            0      18     0  this   Lcoursier/util/shaded/org/jsoup/select/Evaluator$AttributeWithValueMatching;
            0      18     1   key   Ljava/lang/String;
            0      18     2 pattern   Ljava/util/regex/Pattern;

  public boolean matches(coursier.util.shaded.org.jsoup.nodes.Element, coursier.util.shaded.org.jsoup.nodes.Element);
    descriptor: (Lcoursier/util/shaded/org/jsoup/nodes/Element;Lcoursier/util/shaded/org/jsoup/nodes/Element;)Z
    flags: (0x0001) ACC_PUBLIC
    Code:
      stack=3, locals=3, args_size=3
         0: aload_2
         1: aload_0
         2: getfield      #23                 // Field key:Ljava/lang/String;
         5: invokevirtual #35                 // Method coursier/util/shaded/org/jsoup/nodes/Element.hasAttr:(Ljava/lang/String;)Z
         8: ifeq          36
        11: aload_0
        12: getfield      #25                 // Field pattern:Ljava/util/regex/Pattern;
        15: aload_2
        16: aload_0
        17: getfield      #23                 // Field key:Ljava/lang/String;
        20: invokevirtual #38                 // Method coursier/util/shaded/org/jsoup/nodes/Element.attr:(Ljava/lang/String;)Ljava/lang/String;
        23: invokevirtual #44                 // Method java/util/regex/Pattern.matcher:(Ljava/lang/CharSequence;)Ljava/util/regex/Matcher;
        26: invokevirtual #50                 // Method java/util/regex/Matcher.find:()Z
        29: ifeq          36
        32: iconst_1
        33: goto          37
        36: iconst_0
        37: ireturn
      StackMapTable: number_of_entries = 2
        frame_type = 36 /* same */
        frame_type = 64 /* same_locals_1_stack_item */
          stack = [ int ]
      LineNumberTable:
        line 289: 0
      LocalVariableTable:
        Start  Length  Slot  Name   Signature
            0      38     0  this   Lcoursier/util/shaded/org/jsoup/select/Evaluator$AttributeWithValueMatching;
            0      38     1  root   Lcoursier/util/shaded/org/jsoup/nodes/Element;
            0      38     2 element   Lcoursier/util/shaded/org/jsoup/nodes/Element;

  public java.lang.String toString();
    descriptor: ()Ljava/lang/String;
    flags: (0x0001) ACC_PUBLIC
    Code:
      stack=5, locals=1, args_size=1
         0: ldc           #57                 // String [%s~=%s]
         2: iconst_2
         3: anewarray     #59                 // class java/lang/Object
         6: dup
         7: iconst_0
         8: aload_0
         9: getfield      #23                 // Field key:Ljava/lang/String;
        12: aastore
        13: dup
        14: iconst_1
        15: aload_0
        16: getfield      #25                 // Field pattern:Ljava/util/regex/Pattern;
        19: invokevirtual #61                 // Method java/util/regex/Pattern.toString:()Ljava/lang/String;
        22: aastore
        23: invokestatic  #67                 // Method java/lang/String.format:(Ljava/lang/String;[Ljava/lang/Object;)Ljava/lang/String;
        26: areturn
      LineNumberTable:
        line 294: 0
      LocalVariableTable:
        Start  Length  Slot  Name   Signature
            0      27     0  this   Lcoursier/util/shaded/org/jsoup/select/Evaluator$AttributeWithValueMatching;
}
InnerClasses:
  public static final #6= #2 of #4;       // AttributeWithValueMatching=class coursier/util/shaded/org/jsoup/select/Evaluator$AttributeWithValueMatching of class coursier/util/shaded/org/jsoup/select/Evaluator
SourceFile: "Evaluator.java"
