Classfile /Users/mw/Projects/slang-braindump/.jar/jar11/assemble/slang-braindump/assemble/content/coursier/util/shaded/org/jsoup/select/Evaluator$IsOnlyOfType.class
  Last modified May 29, 2022; size 1664 bytes
  SHA-256 checksum 69465c3906ab97312a93b217284ba28ade0c5ddd69e907b543ba32747f7cac78
  Compiled from "Evaluator.java"
public final class coursier.util.shaded.org.jsoup.select.Evaluator$IsOnlyOfType extends coursier.util.shaded.org.jsoup.select.Evaluator
  minor version: 0
  major version: 51
  flags: (0x0031) ACC_PUBLIC, ACC_FINAL, ACC_SUPER
  this_class: #2                          // coursier/util/shaded/org/jsoup/select/Evaluator$IsOnlyOfType
  super_class: #4                         // coursier/util/shaded/org/jsoup/select/Evaluator
  interfaces: 0, fields: 0, methods: 3, attributes: 2
Constant pool:
   #1 = Utf8               coursier/util/shaded/org/jsoup/select/Evaluator$IsOnlyOfType
   #2 = Class              #1             // coursier/util/shaded/org/jsoup/select/Evaluator$IsOnlyOfType
   #3 = Utf8               coursier/util/shaded/org/jsoup/select/Evaluator
   #4 = Class              #3             // coursier/util/shaded/org/jsoup/select/Evaluator
   #5 = Utf8               Evaluator.java
   #6 = Utf8               IsOnlyOfType
   #7 = Utf8               <init>
   #8 = Utf8               ()V
   #9 = NameAndType        #7:#8          // "<init>":()V
  #10 = Methodref          #4.#9          // coursier/util/shaded/org/jsoup/select/Evaluator."<init>":()V
  #11 = Utf8               this
  #12 = Utf8               Lcoursier/util/shaded/org/jsoup/select/Evaluator$IsOnlyOfType;
  #13 = Utf8               matches
  #14 = Utf8               (Lcoursier/util/shaded/org/jsoup/nodes/Element;Lcoursier/util/shaded/org/jsoup/nodes/Element;)Z
  #15 = Utf8               coursier/util/shaded/org/jsoup/nodes/Element
  #16 = Class              #15            // coursier/util/shaded/org/jsoup/nodes/Element
  #17 = Utf8               parent
  #18 = Utf8               ()Lcoursier/util/shaded/org/jsoup/nodes/Element;
  #19 = NameAndType        #17:#18        // parent:()Lcoursier/util/shaded/org/jsoup/nodes/Element;
  #20 = Methodref          #16.#19        // coursier/util/shaded/org/jsoup/nodes/Element.parent:()Lcoursier/util/shaded/org/jsoup/nodes/Element;
  #21 = Utf8               coursier/util/shaded/org/jsoup/nodes/Document
  #22 = Class              #21            // coursier/util/shaded/org/jsoup/nodes/Document
  #23 = Utf8               children
  #24 = Utf8               ()Lcoursier/util/shaded/org/jsoup/select/Elements;
  #25 = NameAndType        #23:#24        // children:()Lcoursier/util/shaded/org/jsoup/select/Elements;
  #26 = Methodref          #16.#25        // coursier/util/shaded/org/jsoup/nodes/Element.children:()Lcoursier/util/shaded/org/jsoup/select/Elements;
  #27 = Utf8               coursier/util/shaded/org/jsoup/select/Elements
  #28 = Class              #27            // coursier/util/shaded/org/jsoup/select/Elements
  #29 = Utf8               iterator
  #30 = Utf8               ()Ljava/util/Iterator;
  #31 = NameAndType        #29:#30        // iterator:()Ljava/util/Iterator;
  #32 = Methodref          #28.#31        // coursier/util/shaded/org/jsoup/select/Elements.iterator:()Ljava/util/Iterator;
  #33 = Utf8               java/util/Iterator
  #34 = Class              #33            // java/util/Iterator
  #35 = Utf8               hasNext
  #36 = Utf8               ()Z
  #37 = NameAndType        #35:#36        // hasNext:()Z
  #38 = InterfaceMethodref #34.#37        // java/util/Iterator.hasNext:()Z
  #39 = Utf8               next
  #40 = Utf8               ()Ljava/lang/Object;
  #41 = NameAndType        #39:#40        // next:()Ljava/lang/Object;
  #42 = InterfaceMethodref #34.#41        // java/util/Iterator.next:()Ljava/lang/Object;
  #43 = Utf8               tag
  #44 = Utf8               ()Lcoursier/util/shaded/org/jsoup/parser/Tag;
  #45 = NameAndType        #43:#44        // tag:()Lcoursier/util/shaded/org/jsoup/parser/Tag;
  #46 = Methodref          #16.#45        // coursier/util/shaded/org/jsoup/nodes/Element.tag:()Lcoursier/util/shaded/org/jsoup/parser/Tag;
  #47 = Utf8               coursier/util/shaded/org/jsoup/parser/Tag
  #48 = Class              #47            // coursier/util/shaded/org/jsoup/parser/Tag
  #49 = Utf8               equals
  #50 = Utf8               (Ljava/lang/Object;)Z
  #51 = NameAndType        #49:#50        // equals:(Ljava/lang/Object;)Z
  #52 = Methodref          #48.#51        // coursier/util/shaded/org/jsoup/parser/Tag.equals:(Ljava/lang/Object;)Z
  #53 = Utf8               el
  #54 = Utf8               Lcoursier/util/shaded/org/jsoup/nodes/Element;
  #55 = Utf8               root
  #56 = Utf8               element
  #57 = Utf8               p
  #58 = Utf8               pos
  #59 = Utf8               I
  #60 = Utf8               family
  #61 = Utf8               Lcoursier/util/shaded/org/jsoup/select/Elements;
  #62 = Utf8               toString
  #63 = Utf8               ()Ljava/lang/String;
  #64 = Utf8               :only-of-type
  #65 = String             #64            // :only-of-type
  #66 = Utf8               Code
  #67 = Utf8               LineNumberTable
  #68 = Utf8               LocalVariableTable
  #69 = Utf8               StackMapTable
  #70 = Utf8               InnerClasses
  #71 = Utf8               SourceFile
{
  public coursier.util.shaded.org.jsoup.select.Evaluator$IsOnlyOfType();
    descriptor: ()V
    flags: (0x0001) ACC_PUBLIC
    Code:
      stack=1, locals=1, args_size=1
         0: aload_0
         1: invokespecial #10                 // Method coursier/util/shaded/org/jsoup/select/Evaluator."<init>":()V
         4: return
      LineNumberTable:
        line 608: 0
      LocalVariableTable:
        Start  Length  Slot  Name   Signature
            0       5     0  this   Lcoursier/util/shaded/org/jsoup/select/Evaluator$IsOnlyOfType;

  public boolean matches(coursier.util.shaded.org.jsoup.nodes.Element, coursier.util.shaded.org.jsoup.nodes.Element);
    descriptor: (Lcoursier/util/shaded/org/jsoup/nodes/Element;Lcoursier/util/shaded/org/jsoup/nodes/Element;)Z
    flags: (0x0001) ACC_PUBLIC
    Code:
      stack=2, locals=8, args_size=3
         0: aload_2
         1: invokevirtual #20                 // Method coursier/util/shaded/org/jsoup/nodes/Element.parent:()Lcoursier/util/shaded/org/jsoup/nodes/Element;
         4: astore_3
         5: aload_3
         6: ifnull        16
         9: aload_3
        10: instanceof    #22                 // class coursier/util/shaded/org/jsoup/nodes/Document
        13: ifeq          18
        16: iconst_0
        17: ireturn
        18: iconst_0
        19: istore        4
        21: aload_3
        22: invokevirtual #26                 // Method coursier/util/shaded/org/jsoup/nodes/Element.children:()Lcoursier/util/shaded/org/jsoup/select/Elements;
        25: astore        5
        27: aload         5
        29: invokevirtual #32                 // Method coursier/util/shaded/org/jsoup/select/Elements.iterator:()Ljava/util/Iterator;
        32: astore        6
        34: aload         6
        36: invokeinterface #38,  1           // InterfaceMethod java/util/Iterator.hasNext:()Z
        41: ifeq          77
        44: aload         6
        46: invokeinterface #42,  1           // InterfaceMethod java/util/Iterator.next:()Ljava/lang/Object;
        51: checkcast     #16                 // class coursier/util/shaded/org/jsoup/nodes/Element
        54: astore        7
        56: aload         7
        58: invokevirtual #46                 // Method coursier/util/shaded/org/jsoup/nodes/Element.tag:()Lcoursier/util/shaded/org/jsoup/parser/Tag;
        61: aload_2
        62: invokevirtual #46                 // Method coursier/util/shaded/org/jsoup/nodes/Element.tag:()Lcoursier/util/shaded/org/jsoup/parser/Tag;
        65: invokevirtual #52                 // Method coursier/util/shaded/org/jsoup/parser/Tag.equals:(Ljava/lang/Object;)Z
        68: ifeq          74
        71: iinc          4, 1
        74: goto          34
        77: iload         4
        79: iconst_1
        80: if_icmpne     87
        83: iconst_1
        84: goto          88
        87: iconst_0
        88: ireturn
      StackMapTable: number_of_entries = 7
        frame_type = 252 /* append */
          offset_delta = 16
          locals = [ class coursier/util/shaded/org/jsoup/nodes/Element ]
        frame_type = 1 /* same */
        frame_type = 254 /* append */
          offset_delta = 15
          locals = [ int, class coursier/util/shaded/org/jsoup/select/Elements, class java/util/Iterator ]
        frame_type = 39 /* same */
        frame_type = 250 /* chop */
          offset_delta = 2
        frame_type = 9 /* same */
        frame_type = 64 /* same_locals_1_stack_item */
          stack = [ int ]
      LineNumberTable:
        line 611: 0
        line 612: 5
        line 614: 18
        line 615: 21
        line 616: 27
        line 617: 56
        line 618: 74
        line 619: 77
      LocalVariableTable:
        Start  Length  Slot  Name   Signature
           56      18     7    el   Lcoursier/util/shaded/org/jsoup/nodes/Element;
            0      89     0  this   Lcoursier/util/shaded/org/jsoup/select/Evaluator$IsOnlyOfType;
            0      89     1  root   Lcoursier/util/shaded/org/jsoup/nodes/Element;
            0      89     2 element   Lcoursier/util/shaded/org/jsoup/nodes/Element;
            5      84     3     p   Lcoursier/util/shaded/org/jsoup/nodes/Element;
           21      68     4   pos   I
           27      62     5 family   Lcoursier/util/shaded/org/jsoup/select/Elements;

  public java.lang.String toString();
    descriptor: ()Ljava/lang/String;
    flags: (0x0001) ACC_PUBLIC
    Code:
      stack=1, locals=1, args_size=1
         0: ldc           #65                 // String :only-of-type
         2: areturn
      LineNumberTable:
        line 623: 0
      LocalVariableTable:
        Start  Length  Slot  Name   Signature
            0       3     0  this   Lcoursier/util/shaded/org/jsoup/select/Evaluator$IsOnlyOfType;
}
InnerClasses:
  public static final #6= #2 of #4;       // IsOnlyOfType=class coursier/util/shaded/org/jsoup/select/Evaluator$IsOnlyOfType of class coursier/util/shaded/org/jsoup/select/Evaluator
SourceFile: "Evaluator.java"
