Classfile /Users/mw/Projects/slang-braindump/.jar/jar11/assemble/slang-braindump/assemble/content/coursier/util/shaded/org/jsoup/select/Evaluator$AttributeStarting.class
  Last modified May 29, 2022; size 2075 bytes
  SHA-256 checksum 717a5d759b6bfa173ab1b9d112c75cb9cc3ad0877f1b26be3b6cc13b84b78cf3
  Compiled from "Evaluator.java"
public final class coursier.util.shaded.org.jsoup.select.Evaluator$AttributeStarting extends coursier.util.shaded.org.jsoup.select.Evaluator
  minor version: 0
  major version: 51
  flags: (0x0031) ACC_PUBLIC, ACC_FINAL, ACC_SUPER
  this_class: #2                          // coursier/util/shaded/org/jsoup/select/Evaluator$AttributeStarting
  super_class: #4                         // coursier/util/shaded/org/jsoup/select/Evaluator
  interfaces: 0, fields: 1, methods: 3, attributes: 2
Constant pool:
   #1 = Utf8               coursier/util/shaded/org/jsoup/select/Evaluator$AttributeStarting
   #2 = Class              #1             // coursier/util/shaded/org/jsoup/select/Evaluator$AttributeStarting
   #3 = Utf8               coursier/util/shaded/org/jsoup/select/Evaluator
   #4 = Class              #3             // coursier/util/shaded/org/jsoup/select/Evaluator
   #5 = Utf8               Evaluator.java
   #6 = Utf8               AttributeStarting
   #7 = Utf8               keyPrefix
   #8 = Utf8               Ljava/lang/String;
   #9 = Utf8               <init>
  #10 = Utf8               (Ljava/lang/String;)V
  #11 = Utf8               ()V
  #12 = NameAndType        #9:#11         // "<init>":()V
  #13 = Methodref          #4.#12         // coursier/util/shaded/org/jsoup/select/Evaluator."<init>":()V
  #14 = Utf8               coursier/util/shaded/org/jsoup/helper/Validate
  #15 = Class              #14            // coursier/util/shaded/org/jsoup/helper/Validate
  #16 = Utf8               notEmpty
  #17 = NameAndType        #16:#10        // notEmpty:(Ljava/lang/String;)V
  #18 = Methodref          #15.#17        // coursier/util/shaded/org/jsoup/helper/Validate.notEmpty:(Ljava/lang/String;)V
  #19 = Utf8               coursier/util/shaded/org/jsoup/internal/Normalizer
  #20 = Class              #19            // coursier/util/shaded/org/jsoup/internal/Normalizer
  #21 = Utf8               lowerCase
  #22 = Utf8               (Ljava/lang/String;)Ljava/lang/String;
  #23 = NameAndType        #21:#22        // lowerCase:(Ljava/lang/String;)Ljava/lang/String;
  #24 = Methodref          #20.#23        // coursier/util/shaded/org/jsoup/internal/Normalizer.lowerCase:(Ljava/lang/String;)Ljava/lang/String;
  #25 = NameAndType        #7:#8          // keyPrefix:Ljava/lang/String;
  #26 = Fieldref           #2.#25         // coursier/util/shaded/org/jsoup/select/Evaluator$AttributeStarting.keyPrefix:Ljava/lang/String;
  #27 = Utf8               this
  #28 = Utf8               Lcoursier/util/shaded/org/jsoup/select/Evaluator$AttributeStarting;
  #29 = Utf8               matches
  #30 = Utf8               (Lcoursier/util/shaded/org/jsoup/nodes/Element;Lcoursier/util/shaded/org/jsoup/nodes/Element;)Z
  #31 = Utf8               coursier/util/shaded/org/jsoup/nodes/Element
  #32 = Class              #31            // coursier/util/shaded/org/jsoup/nodes/Element
  #33 = Utf8               attributes
  #34 = Utf8               ()Lcoursier/util/shaded/org/jsoup/nodes/Attributes;
  #35 = NameAndType        #33:#34        // attributes:()Lcoursier/util/shaded/org/jsoup/nodes/Attributes;
  #36 = Methodref          #32.#35        // coursier/util/shaded/org/jsoup/nodes/Element.attributes:()Lcoursier/util/shaded/org/jsoup/nodes/Attributes;
  #37 = Utf8               coursier/util/shaded/org/jsoup/nodes/Attributes
  #38 = Class              #37            // coursier/util/shaded/org/jsoup/nodes/Attributes
  #39 = Utf8               asList
  #40 = Utf8               ()Ljava/util/List;
  #41 = NameAndType        #39:#40        // asList:()Ljava/util/List;
  #42 = Methodref          #38.#41        // coursier/util/shaded/org/jsoup/nodes/Attributes.asList:()Ljava/util/List;
  #43 = Utf8               java/util/List
  #44 = Class              #43            // java/util/List
  #45 = Utf8               iterator
  #46 = Utf8               ()Ljava/util/Iterator;
  #47 = NameAndType        #45:#46        // iterator:()Ljava/util/Iterator;
  #48 = InterfaceMethodref #44.#47        // java/util/List.iterator:()Ljava/util/Iterator;
  #49 = Utf8               java/util/Iterator
  #50 = Class              #49            // java/util/Iterator
  #51 = Utf8               hasNext
  #52 = Utf8               ()Z
  #53 = NameAndType        #51:#52        // hasNext:()Z
  #54 = InterfaceMethodref #50.#53        // java/util/Iterator.hasNext:()Z
  #55 = Utf8               next
  #56 = Utf8               ()Ljava/lang/Object;
  #57 = NameAndType        #55:#56        // next:()Ljava/lang/Object;
  #58 = InterfaceMethodref #50.#57        // java/util/Iterator.next:()Ljava/lang/Object;
  #59 = Utf8               coursier/util/shaded/org/jsoup/nodes/Attribute
  #60 = Class              #59            // coursier/util/shaded/org/jsoup/nodes/Attribute
  #61 = Utf8               getKey
  #62 = Utf8               ()Ljava/lang/String;
  #63 = NameAndType        #61:#62        // getKey:()Ljava/lang/String;
  #64 = Methodref          #60.#63        // coursier/util/shaded/org/jsoup/nodes/Attribute.getKey:()Ljava/lang/String;
  #65 = Utf8               java/lang/String
  #66 = Class              #65            // java/lang/String
  #67 = Utf8               startsWith
  #68 = Utf8               (Ljava/lang/String;)Z
  #69 = NameAndType        #67:#68        // startsWith:(Ljava/lang/String;)Z
  #70 = Methodref          #66.#69        // java/lang/String.startsWith:(Ljava/lang/String;)Z
  #71 = Utf8               attribute
  #72 = Utf8               Lcoursier/util/shaded/org/jsoup/nodes/Attribute;
  #73 = Utf8               root
  #74 = Utf8               Lcoursier/util/shaded/org/jsoup/nodes/Element;
  #75 = Utf8               element
  #76 = Utf8               values
  #77 = Utf8               Ljava/util/List<Lcoursier/util/shaded/org/jsoup/nodes/Attribute;>;
  #78 = Utf8               Ljava/util/List;
  #79 = Utf8               toString
  #80 = Utf8               [^%s]
  #81 = String             #80            // [^%s]
  #82 = Utf8               java/lang/Object
  #83 = Class              #82            // java/lang/Object
  #84 = Utf8               format
  #85 = Utf8               (Ljava/lang/String;[Ljava/lang/Object;)Ljava/lang/String;
  #86 = NameAndType        #84:#85        // format:(Ljava/lang/String;[Ljava/lang/Object;)Ljava/lang/String;
  #87 = Methodref          #66.#86        // java/lang/String.format:(Ljava/lang/String;[Ljava/lang/Object;)Ljava/lang/String;
  #88 = Utf8               Code
  #89 = Utf8               LineNumberTable
  #90 = Utf8               LocalVariableTable
  #91 = Utf8               StackMapTable
  #92 = Utf8               LocalVariableTypeTable
  #93 = Utf8               InnerClasses
  #94 = Utf8               SourceFile
{
  private java.lang.String keyPrefix;
    descriptor: Ljava/lang/String;
    flags: (0x0002) ACC_PRIVATE

  public coursier.util.shaded.org.jsoup.select.Evaluator$AttributeStarting(java.lang.String);
    descriptor: (Ljava/lang/String;)V
    flags: (0x0001) ACC_PUBLIC
    Code:
      stack=2, locals=2, args_size=2
         0: aload_0
         1: invokespecial #13                 // Method coursier/util/shaded/org/jsoup/select/Evaluator."<init>":()V
         4: aload_1
         5: invokestatic  #18                 // Method coursier/util/shaded/org/jsoup/helper/Validate.notEmpty:(Ljava/lang/String;)V
         8: aload_0
         9: aload_1
        10: invokestatic  #24                 // Method coursier/util/shaded/org/jsoup/internal/Normalizer.lowerCase:(Ljava/lang/String;)Ljava/lang/String;
        13: putfield      #26                 // Field keyPrefix:Ljava/lang/String;
        16: return
      LineNumberTable:
        line 153: 0
        line 154: 4
        line 155: 8
        line 156: 16
      LocalVariableTable:
        Start  Length  Slot  Name   Signature
            0      17     0  this   Lcoursier/util/shaded/org/jsoup/select/Evaluator$AttributeStarting;
            0      17     1 keyPrefix   Ljava/lang/String;

  public boolean matches(coursier.util.shaded.org.jsoup.nodes.Element, coursier.util.shaded.org.jsoup.nodes.Element);
    descriptor: (Lcoursier/util/shaded/org/jsoup/nodes/Element;Lcoursier/util/shaded/org/jsoup/nodes/Element;)Z
    flags: (0x0001) ACC_PUBLIC
    Code:
      stack=2, locals=6, args_size=3
         0: aload_2
         1: invokevirtual #36                 // Method coursier/util/shaded/org/jsoup/nodes/Element.attributes:()Lcoursier/util/shaded/org/jsoup/nodes/Attributes;
         4: invokevirtual #42                 // Method coursier/util/shaded/org/jsoup/nodes/Attributes.asList:()Ljava/util/List;
         7: astore_3
         8: aload_3
         9: invokeinterface #48,  1           // InterfaceMethod java/util/List.iterator:()Ljava/util/Iterator;
        14: astore        4
        16: aload         4
        18: invokeinterface #54,  1           // InterfaceMethod java/util/Iterator.hasNext:()Z
        23: ifeq          61
        26: aload         4
        28: invokeinterface #58,  1           // InterfaceMethod java/util/Iterator.next:()Ljava/lang/Object;
        33: checkcast     #60                 // class coursier/util/shaded/org/jsoup/nodes/Attribute
        36: astore        5
        38: aload         5
        40: invokevirtual #64                 // Method coursier/util/shaded/org/jsoup/nodes/Attribute.getKey:()Ljava/lang/String;
        43: invokestatic  #24                 // Method coursier/util/shaded/org/jsoup/internal/Normalizer.lowerCase:(Ljava/lang/String;)Ljava/lang/String;
        46: aload_0
        47: getfield      #26                 // Field keyPrefix:Ljava/lang/String;
        50: invokevirtual #70                 // Method java/lang/String.startsWith:(Ljava/lang/String;)Z
        53: ifeq          58
        56: iconst_1
        57: ireturn
        58: goto          16
        61: iconst_0
        62: ireturn
      StackMapTable: number_of_entries = 3
        frame_type = 253 /* append */
          offset_delta = 16
          locals = [ class java/util/List, class java/util/Iterator ]
        frame_type = 41 /* same */
        frame_type = 250 /* chop */
          offset_delta = 2
      LineNumberTable:
        line 160: 0
        line 161: 8
        line 162: 38
        line 163: 56
        line 164: 58
        line 165: 61
      LocalVariableTable:
        Start  Length  Slot  Name   Signature
           38      20     5 attribute   Lcoursier/util/shaded/org/jsoup/nodes/Attribute;
            0      63     0  this   Lcoursier/util/shaded/org/jsoup/select/Evaluator$AttributeStarting;
            0      63     1  root   Lcoursier/util/shaded/org/jsoup/nodes/Element;
            0      63     2 element   Lcoursier/util/shaded/org/jsoup/nodes/Element;
            8      55     3 values   Ljava/util/List;
      LocalVariableTypeTable:
        Start  Length  Slot  Name   Signature
            8      55     3 values   Ljava/util/List<Lcoursier/util/shaded/org/jsoup/nodes/Attribute;>;

  public java.lang.String toString();
    descriptor: ()Ljava/lang/String;
    flags: (0x0001) ACC_PUBLIC
    Code:
      stack=5, locals=1, args_size=1
         0: ldc           #81                 // String [^%s]
         2: iconst_1
         3: anewarray     #83                 // class java/lang/Object
         6: dup
         7: iconst_0
         8: aload_0
         9: getfield      #26                 // Field keyPrefix:Ljava/lang/String;
        12: aastore
        13: invokestatic  #87                 // Method java/lang/String.format:(Ljava/lang/String;[Ljava/lang/Object;)Ljava/lang/String;
        16: areturn
      LineNumberTable:
        line 170: 0
      LocalVariableTable:
        Start  Length  Slot  Name   Signature
            0      17     0  this   Lcoursier/util/shaded/org/jsoup/select/Evaluator$AttributeStarting;
}
InnerClasses:
  public static final #6= #2 of #4;       // AttributeStarting=class coursier/util/shaded/org/jsoup/select/Evaluator$AttributeStarting of class coursier/util/shaded/org/jsoup/select/Evaluator
SourceFile: "Evaluator.java"
