Classfile /Users/mw/Projects/slang-braindump/.jar/jar11/assemble/slang-braindump/assemble/content/coursier/util/shaded/org/jsoup/select/QueryParser.class
  Last modified May 29, 2022; size 15710 bytes
  SHA-256 checksum b8c752976fa60ab3065122e76cdd34eed29c9df28be1b2a1729a2faf6b0310b0
  Compiled from "QueryParser.java"
public class coursier.util.shaded.org.jsoup.select.QueryParser
  minor version: 0
  major version: 51
  flags: (0x0021) ACC_PUBLIC, ACC_SUPER
  this_class: #2                          // coursier/util/shaded/org/jsoup/select/QueryParser
  super_class: #4                         // java/lang/Object
  interfaces: 0, fields: 7, methods: 22, attributes: 2
Constant pool:
    #1 = Utf8               coursier/util/shaded/org/jsoup/select/QueryParser
    #2 = Class              #1            // coursier/util/shaded/org/jsoup/select/QueryParser
    #3 = Utf8               java/lang/Object
    #4 = Class              #3            // java/lang/Object
    #5 = Utf8               QueryParser.java
    #6 = Utf8               coursier/util/shaded/org/jsoup/select/Selector$SelectorParseException
    #7 = Class              #6            // coursier/util/shaded/org/jsoup/select/Selector$SelectorParseException
    #8 = Utf8               coursier/util/shaded/org/jsoup/select/Selector
    #9 = Class              #8            // coursier/util/shaded/org/jsoup/select/Selector
   #10 = Utf8               SelectorParseException
   #11 = Utf8               coursier/util/shaded/org/jsoup/select/StructuralEvaluator$Root
   #12 = Class              #11           // coursier/util/shaded/org/jsoup/select/StructuralEvaluator$Root
   #13 = Utf8               coursier/util/shaded/org/jsoup/select/StructuralEvaluator
   #14 = Class              #13           // coursier/util/shaded/org/jsoup/select/StructuralEvaluator
   #15 = Utf8               Root
   #16 = Utf8               coursier/util/shaded/org/jsoup/select/CombiningEvaluator$And
   #17 = Class              #16           // coursier/util/shaded/org/jsoup/select/CombiningEvaluator$And
   #18 = Utf8               coursier/util/shaded/org/jsoup/select/CombiningEvaluator
   #19 = Class              #18           // coursier/util/shaded/org/jsoup/select/CombiningEvaluator
   #20 = Utf8               And
   #21 = Utf8               coursier/util/shaded/org/jsoup/select/CombiningEvaluator$Or
   #22 = Class              #21           // coursier/util/shaded/org/jsoup/select/CombiningEvaluator$Or
   #23 = Utf8               Or
   #24 = Utf8               coursier/util/shaded/org/jsoup/select/StructuralEvaluator$ImmediateParent
   #25 = Class              #24           // coursier/util/shaded/org/jsoup/select/StructuralEvaluator$ImmediateParent
   #26 = Utf8               ImmediateParent
   #27 = Utf8               coursier/util/shaded/org/jsoup/select/StructuralEvaluator$Parent
   #28 = Class              #27           // coursier/util/shaded/org/jsoup/select/StructuralEvaluator$Parent
   #29 = Utf8               Parent
   #30 = Utf8               coursier/util/shaded/org/jsoup/select/StructuralEvaluator$ImmediatePreviousSibling
   #31 = Class              #30           // coursier/util/shaded/org/jsoup/select/StructuralEvaluator$ImmediatePreviousSibling
   #32 = Utf8               ImmediatePreviousSibling
   #33 = Utf8               coursier/util/shaded/org/jsoup/select/StructuralEvaluator$PreviousSibling
   #34 = Class              #33           // coursier/util/shaded/org/jsoup/select/StructuralEvaluator$PreviousSibling
   #35 = Utf8               PreviousSibling
   #36 = Utf8               coursier/util/shaded/org/jsoup/select/Evaluator$IsFirstChild
   #37 = Class              #36           // coursier/util/shaded/org/jsoup/select/Evaluator$IsFirstChild
   #38 = Utf8               coursier/util/shaded/org/jsoup/select/Evaluator
   #39 = Class              #38           // coursier/util/shaded/org/jsoup/select/Evaluator
   #40 = Utf8               IsFirstChild
   #41 = Utf8               coursier/util/shaded/org/jsoup/select/Evaluator$IsLastChild
   #42 = Class              #41           // coursier/util/shaded/org/jsoup/select/Evaluator$IsLastChild
   #43 = Utf8               IsLastChild
   #44 = Utf8               coursier/util/shaded/org/jsoup/select/Evaluator$IsFirstOfType
   #45 = Class              #44           // coursier/util/shaded/org/jsoup/select/Evaluator$IsFirstOfType
   #46 = Utf8               IsFirstOfType
   #47 = Utf8               coursier/util/shaded/org/jsoup/select/Evaluator$IsLastOfType
   #48 = Class              #47           // coursier/util/shaded/org/jsoup/select/Evaluator$IsLastOfType
   #49 = Utf8               IsLastOfType
   #50 = Utf8               coursier/util/shaded/org/jsoup/select/Evaluator$IsOnlyChild
   #51 = Class              #50           // coursier/util/shaded/org/jsoup/select/Evaluator$IsOnlyChild
   #52 = Utf8               IsOnlyChild
   #53 = Utf8               coursier/util/shaded/org/jsoup/select/Evaluator$IsOnlyOfType
   #54 = Class              #53           // coursier/util/shaded/org/jsoup/select/Evaluator$IsOnlyOfType
   #55 = Utf8               IsOnlyOfType
   #56 = Utf8               coursier/util/shaded/org/jsoup/select/Evaluator$IsEmpty
   #57 = Class              #56           // coursier/util/shaded/org/jsoup/select/Evaluator$IsEmpty
   #58 = Utf8               IsEmpty
   #59 = Utf8               coursier/util/shaded/org/jsoup/select/Evaluator$IsRoot
   #60 = Class              #59           // coursier/util/shaded/org/jsoup/select/Evaluator$IsRoot
   #61 = Utf8               IsRoot
   #62 = Utf8               coursier/util/shaded/org/jsoup/select/Evaluator$MatchText
   #63 = Class              #62           // coursier/util/shaded/org/jsoup/select/Evaluator$MatchText
   #64 = Utf8               MatchText
   #65 = Utf8               coursier/util/shaded/org/jsoup/select/Evaluator$Id
   #66 = Class              #65           // coursier/util/shaded/org/jsoup/select/Evaluator$Id
   #67 = Utf8               Id
   #68 = Utf8               coursier/util/shaded/org/jsoup/select/Evaluator$Class
   #69 = Class              #68           // coursier/util/shaded/org/jsoup/select/Evaluator$Class
   #70 = Utf8               Class
   #71 = Utf8               coursier/util/shaded/org/jsoup/select/Evaluator$Tag
   #72 = Class              #71           // coursier/util/shaded/org/jsoup/select/Evaluator$Tag
   #73 = Utf8               Tag
   #74 = Utf8               coursier/util/shaded/org/jsoup/select/Evaluator$TagEndsWith
   #75 = Class              #74           // coursier/util/shaded/org/jsoup/select/Evaluator$TagEndsWith
   #76 = Utf8               TagEndsWith
   #77 = Utf8               coursier/util/shaded/org/jsoup/select/Evaluator$AttributeStarting
   #78 = Class              #77           // coursier/util/shaded/org/jsoup/select/Evaluator$AttributeStarting
   #79 = Utf8               AttributeStarting
   #80 = Utf8               coursier/util/shaded/org/jsoup/select/Evaluator$Attribute
   #81 = Class              #80           // coursier/util/shaded/org/jsoup/select/Evaluator$Attribute
   #82 = Utf8               Attribute
   #83 = Utf8               coursier/util/shaded/org/jsoup/select/Evaluator$AttributeWithValue
   #84 = Class              #83           // coursier/util/shaded/org/jsoup/select/Evaluator$AttributeWithValue
   #85 = Utf8               AttributeWithValue
   #86 = Utf8               coursier/util/shaded/org/jsoup/select/Evaluator$AttributeWithValueNot
   #87 = Class              #86           // coursier/util/shaded/org/jsoup/select/Evaluator$AttributeWithValueNot
   #88 = Utf8               AttributeWithValueNot
   #89 = Utf8               coursier/util/shaded/org/jsoup/select/Evaluator$AttributeWithValueStarting
   #90 = Class              #89           // coursier/util/shaded/org/jsoup/select/Evaluator$AttributeWithValueStarting
   #91 = Utf8               AttributeWithValueStarting
   #92 = Utf8               coursier/util/shaded/org/jsoup/select/Evaluator$AttributeWithValueEnding
   #93 = Class              #92           // coursier/util/shaded/org/jsoup/select/Evaluator$AttributeWithValueEnding
   #94 = Utf8               AttributeWithValueEnding
   #95 = Utf8               coursier/util/shaded/org/jsoup/select/Evaluator$AttributeWithValueContaining
   #96 = Class              #95           // coursier/util/shaded/org/jsoup/select/Evaluator$AttributeWithValueContaining
   #97 = Utf8               AttributeWithValueContaining
   #98 = Utf8               coursier/util/shaded/org/jsoup/select/Evaluator$AttributeWithValueMatching
   #99 = Class              #98           // coursier/util/shaded/org/jsoup/select/Evaluator$AttributeWithValueMatching
  #100 = Utf8               AttributeWithValueMatching
  #101 = Utf8               coursier/util/shaded/org/jsoup/select/Evaluator$AllElements
  #102 = Class              #101          // coursier/util/shaded/org/jsoup/select/Evaluator$AllElements
  #103 = Utf8               AllElements
  #104 = Utf8               coursier/util/shaded/org/jsoup/select/Evaluator$IndexLessThan
  #105 = Class              #104          // coursier/util/shaded/org/jsoup/select/Evaluator$IndexLessThan
  #106 = Utf8               IndexLessThan
  #107 = Utf8               coursier/util/shaded/org/jsoup/select/Evaluator$IndexGreaterThan
  #108 = Class              #107          // coursier/util/shaded/org/jsoup/select/Evaluator$IndexGreaterThan
  #109 = Utf8               IndexGreaterThan
  #110 = Utf8               coursier/util/shaded/org/jsoup/select/Evaluator$IndexEquals
  #111 = Class              #110          // coursier/util/shaded/org/jsoup/select/Evaluator$IndexEquals
  #112 = Utf8               IndexEquals
  #113 = Utf8               coursier/util/shaded/org/jsoup/select/Evaluator$IsNthLastOfType
  #114 = Class              #113          // coursier/util/shaded/org/jsoup/select/Evaluator$IsNthLastOfType
  #115 = Utf8               IsNthLastOfType
  #116 = Utf8               coursier/util/shaded/org/jsoup/select/Evaluator$IsNthOfType
  #117 = Class              #116          // coursier/util/shaded/org/jsoup/select/Evaluator$IsNthOfType
  #118 = Utf8               IsNthOfType
  #119 = Utf8               coursier/util/shaded/org/jsoup/select/Evaluator$IsNthLastChild
  #120 = Class              #119          // coursier/util/shaded/org/jsoup/select/Evaluator$IsNthLastChild
  #121 = Utf8               IsNthLastChild
  #122 = Utf8               coursier/util/shaded/org/jsoup/select/Evaluator$IsNthChild
  #123 = Class              #122          // coursier/util/shaded/org/jsoup/select/Evaluator$IsNthChild
  #124 = Utf8               IsNthChild
  #125 = Utf8               coursier/util/shaded/org/jsoup/select/StructuralEvaluator$Has
  #126 = Class              #125          // coursier/util/shaded/org/jsoup/select/StructuralEvaluator$Has
  #127 = Utf8               Has
  #128 = Utf8               coursier/util/shaded/org/jsoup/select/Evaluator$ContainsOwnText
  #129 = Class              #128          // coursier/util/shaded/org/jsoup/select/Evaluator$ContainsOwnText
  #130 = Utf8               ContainsOwnText
  #131 = Utf8               coursier/util/shaded/org/jsoup/select/Evaluator$ContainsText
  #132 = Class              #131          // coursier/util/shaded/org/jsoup/select/Evaluator$ContainsText
  #133 = Utf8               ContainsText
  #134 = Utf8               coursier/util/shaded/org/jsoup/select/Evaluator$ContainsData
  #135 = Class              #134          // coursier/util/shaded/org/jsoup/select/Evaluator$ContainsData
  #136 = Utf8               ContainsData
  #137 = Utf8               coursier/util/shaded/org/jsoup/select/Evaluator$MatchesOwn
  #138 = Class              #137          // coursier/util/shaded/org/jsoup/select/Evaluator$MatchesOwn
  #139 = Utf8               MatchesOwn
  #140 = Utf8               coursier/util/shaded/org/jsoup/select/Evaluator$Matches
  #141 = Class              #140          // coursier/util/shaded/org/jsoup/select/Evaluator$Matches
  #142 = Utf8               Matches
  #143 = Utf8               coursier/util/shaded/org/jsoup/select/StructuralEvaluator$Not
  #144 = Class              #143          // coursier/util/shaded/org/jsoup/select/StructuralEvaluator$Not
  #145 = Utf8               Not
  #146 = Utf8               combinators
  #147 = Utf8               [Ljava/lang/String;
  #148 = Utf8               AttributeEvals
  #149 = Utf8               tq
  #150 = Utf8               Lcoursier/util/shaded/org/jsoup/parser/TokenQueue;
  #151 = Utf8               query
  #152 = Utf8               Ljava/lang/String;
  #153 = Utf8               evals
  #154 = Utf8               Ljava/util/List;
  #155 = Utf8               Ljava/util/List<Lcoursier/util/shaded/org/jsoup/select/Evaluator;>;
  #156 = Utf8               NTH_AB
  #157 = Utf8               Ljava/util/regex/Pattern;
  #158 = Utf8               NTH_B
  #159 = Utf8               <init>
  #160 = Utf8               (Ljava/lang/String;)V
  #161 = Utf8               ()V
  #162 = NameAndType        #159:#161     // "<init>":()V
  #163 = Methodref          #4.#162       // java/lang/Object."<init>":()V
  #164 = Utf8               java/util/ArrayList
  #165 = Class              #164          // java/util/ArrayList
  #166 = Methodref          #165.#162     // java/util/ArrayList."<init>":()V
  #167 = NameAndType        #153:#154     // evals:Ljava/util/List;
  #168 = Fieldref           #2.#167       // coursier/util/shaded/org/jsoup/select/QueryParser.evals:Ljava/util/List;
  #169 = Utf8               coursier/util/shaded/org/jsoup/helper/Validate
  #170 = Class              #169          // coursier/util/shaded/org/jsoup/helper/Validate
  #171 = Utf8               notEmpty
  #172 = NameAndType        #171:#160     // notEmpty:(Ljava/lang/String;)V
  #173 = Methodref          #170.#172     // coursier/util/shaded/org/jsoup/helper/Validate.notEmpty:(Ljava/lang/String;)V
  #174 = Utf8               java/lang/String
  #175 = Class              #174          // java/lang/String
  #176 = Utf8               trim
  #177 = Utf8               ()Ljava/lang/String;
  #178 = NameAndType        #176:#177     // trim:()Ljava/lang/String;
  #179 = Methodref          #175.#178     // java/lang/String.trim:()Ljava/lang/String;
  #180 = NameAndType        #151:#152     // query:Ljava/lang/String;
  #181 = Fieldref           #2.#180       // coursier/util/shaded/org/jsoup/select/QueryParser.query:Ljava/lang/String;
  #182 = Utf8               coursier/util/shaded/org/jsoup/parser/TokenQueue
  #183 = Class              #182          // coursier/util/shaded/org/jsoup/parser/TokenQueue
  #184 = NameAndType        #159:#160     // "<init>":(Ljava/lang/String;)V
  #185 = Methodref          #183.#184     // coursier/util/shaded/org/jsoup/parser/TokenQueue."<init>":(Ljava/lang/String;)V
  #186 = NameAndType        #149:#150     // tq:Lcoursier/util/shaded/org/jsoup/parser/TokenQueue;
  #187 = Fieldref           #2.#186       // coursier/util/shaded/org/jsoup/select/QueryParser.tq:Lcoursier/util/shaded/org/jsoup/parser/TokenQueue;
  #188 = Utf8               this
  #189 = Utf8               Lcoursier/util/shaded/org/jsoup/select/QueryParser;
  #190 = Utf8               parse
  #191 = Utf8               (Ljava/lang/String;)Lcoursier/util/shaded/org/jsoup/select/Evaluator;
  #192 = Utf8               java/lang/IllegalArgumentException
  #193 = Class              #192          // java/lang/IllegalArgumentException
  #194 = Methodref          #2.#184       // coursier/util/shaded/org/jsoup/select/QueryParser."<init>":(Ljava/lang/String;)V
  #195 = Utf8               ()Lcoursier/util/shaded/org/jsoup/select/Evaluator;
  #196 = NameAndType        #190:#195     // parse:()Lcoursier/util/shaded/org/jsoup/select/Evaluator;
  #197 = Methodref          #2.#196       // coursier/util/shaded/org/jsoup/select/QueryParser.parse:()Lcoursier/util/shaded/org/jsoup/select/Evaluator;
  #198 = Utf8               getMessage
  #199 = NameAndType        #198:#177     // getMessage:()Ljava/lang/String;
  #200 = Methodref          #193.#199     // java/lang/IllegalArgumentException.getMessage:()Ljava/lang/String;
  #201 = Utf8               (Ljava/lang/String;[Ljava/lang/Object;)V
  #202 = NameAndType        #159:#201     // "<init>":(Ljava/lang/String;[Ljava/lang/Object;)V
  #203 = Methodref          #7.#202       // coursier/util/shaded/org/jsoup/select/Selector$SelectorParseException."<init>":(Ljava/lang/String;[Ljava/lang/Object;)V
  #204 = Utf8               p
  #205 = Utf8               e
  #206 = Utf8               Ljava/lang/IllegalArgumentException;
  #207 = Utf8               consumeWhitespace
  #208 = Utf8               ()Z
  #209 = NameAndType        #207:#208     // consumeWhitespace:()Z
  #210 = Methodref          #183.#209     // coursier/util/shaded/org/jsoup/parser/TokenQueue.consumeWhitespace:()Z
  #211 = NameAndType        #146:#147     // combinators:[Ljava/lang/String;
  #212 = Fieldref           #2.#211       // coursier/util/shaded/org/jsoup/select/QueryParser.combinators:[Ljava/lang/String;
  #213 = Utf8               matchesAny
  #214 = Utf8               ([Ljava/lang/String;)Z
  #215 = NameAndType        #213:#214     // matchesAny:([Ljava/lang/String;)Z
  #216 = Methodref          #183.#215     // coursier/util/shaded/org/jsoup/parser/TokenQueue.matchesAny:([Ljava/lang/String;)Z
  #217 = Methodref          #12.#162      // coursier/util/shaded/org/jsoup/select/StructuralEvaluator$Root."<init>":()V
  #218 = Utf8               java/util/List
  #219 = Class              #218          // java/util/List
  #220 = Utf8               add
  #221 = Utf8               (Ljava/lang/Object;)Z
  #222 = NameAndType        #220:#221     // add:(Ljava/lang/Object;)Z
  #223 = InterfaceMethodref #219.#222     // java/util/List.add:(Ljava/lang/Object;)Z
  #224 = Utf8               consume
  #225 = Utf8               ()C
  #226 = NameAndType        #224:#225     // consume:()C
  #227 = Methodref          #183.#226     // coursier/util/shaded/org/jsoup/parser/TokenQueue.consume:()C
  #228 = Utf8               combinator
  #229 = Utf8               (C)V
  #230 = NameAndType        #228:#229     // combinator:(C)V
  #231 = Methodref          #2.#230       // coursier/util/shaded/org/jsoup/select/QueryParser.combinator:(C)V
  #232 = Utf8               findElements
  #233 = NameAndType        #232:#161     // findElements:()V
  #234 = Methodref          #2.#233       // coursier/util/shaded/org/jsoup/select/QueryParser.findElements:()V
  #235 = Utf8               isEmpty
  #236 = NameAndType        #235:#208     // isEmpty:()Z
  #237 = Methodref          #183.#236     // coursier/util/shaded/org/jsoup/parser/TokenQueue.isEmpty:()Z
  #238 = Utf8               size
  #239 = Utf8               ()I
  #240 = NameAndType        #238:#239     // size:()I
  #241 = InterfaceMethodref #219.#240     // java/util/List.size:()I
  #242 = Utf8               get
  #243 = Utf8               (I)Ljava/lang/Object;
  #244 = NameAndType        #242:#243     // get:(I)Ljava/lang/Object;
  #245 = InterfaceMethodref #219.#244     // java/util/List.get:(I)Ljava/lang/Object;
  #246 = Utf8               (Ljava/util/Collection;)V
  #247 = NameAndType        #159:#246     // "<init>":(Ljava/util/Collection;)V
  #248 = Methodref          #17.#247      // coursier/util/shaded/org/jsoup/select/CombiningEvaluator$And."<init>":(Ljava/util/Collection;)V
  #249 = Utf8               seenWhite
  #250 = Utf8               Z
  #251 = Utf8               consumeSubQuery
  #252 = NameAndType        #251:#177     // consumeSubQuery:()Ljava/lang/String;
  #253 = Methodref          #2.#252       // coursier/util/shaded/org/jsoup/select/QueryParser.consumeSubQuery:()Ljava/lang/String;
  #254 = NameAndType        #190:#191     // parse:(Ljava/lang/String;)Lcoursier/util/shaded/org/jsoup/select/Evaluator;
  #255 = Methodref          #2.#254       // coursier/util/shaded/org/jsoup/select/QueryParser.parse:(Ljava/lang/String;)Lcoursier/util/shaded/org/jsoup/select/Evaluator;
  #256 = Utf8               rightMostEvaluator
  #257 = NameAndType        #256:#195     // rightMostEvaluator:()Lcoursier/util/shaded/org/jsoup/select/Evaluator;
  #258 = Methodref          #22.#257      // coursier/util/shaded/org/jsoup/select/CombiningEvaluator$Or.rightMostEvaluator:()Lcoursier/util/shaded/org/jsoup/select/Evaluator;
  #259 = Utf8               clear
  #260 = NameAndType        #259:#161     // clear:()V
  #261 = InterfaceMethodref #219.#260     // java/util/List.clear:()V
  #262 = Utf8               (Lcoursier/util/shaded/org/jsoup/select/Evaluator;)V
  #263 = NameAndType        #159:#262     // "<init>":(Lcoursier/util/shaded/org/jsoup/select/Evaluator;)V
  #264 = Methodref          #25.#263      // coursier/util/shaded/org/jsoup/select/StructuralEvaluator$ImmediateParent."<init>":(Lcoursier/util/shaded/org/jsoup/select/Evaluator;)V
  #265 = Utf8               ([Lcoursier/util/shaded/org/jsoup/select/Evaluator;)V
  #266 = NameAndType        #159:#265     // "<init>":([Lcoursier/util/shaded/org/jsoup/select/Evaluator;)V
  #267 = Methodref          #17.#266      // coursier/util/shaded/org/jsoup/select/CombiningEvaluator$And."<init>":([Lcoursier/util/shaded/org/jsoup/select/Evaluator;)V
  #268 = Methodref          #28.#263      // coursier/util/shaded/org/jsoup/select/StructuralEvaluator$Parent."<init>":(Lcoursier/util/shaded/org/jsoup/select/Evaluator;)V
  #269 = Methodref          #31.#263      // coursier/util/shaded/org/jsoup/select/StructuralEvaluator$ImmediatePreviousSibling."<init>":(Lcoursier/util/shaded/org/jsoup/select/Evaluator;)V
  #270 = Methodref          #34.#263      // coursier/util/shaded/org/jsoup/select/StructuralEvaluator$PreviousSibling."<init>":(Lcoursier/util/shaded/org/jsoup/select/Evaluator;)V
  #271 = NameAndType        #220:#262     // add:(Lcoursier/util/shaded/org/jsoup/select/Evaluator;)V
  #272 = Methodref          #22.#271      // coursier/util/shaded/org/jsoup/select/CombiningEvaluator$Or.add:(Lcoursier/util/shaded/org/jsoup/select/Evaluator;)V
  #273 = Methodref          #22.#162      // coursier/util/shaded/org/jsoup/select/CombiningEvaluator$Or."<init>":()V
  #274 = Utf8               java/lang/StringBuilder
  #275 = Class              #274          // java/lang/StringBuilder
  #276 = Methodref          #275.#162     // java/lang/StringBuilder."<init>":()V
  #277 = Utf8               Unknown combinator:
  #278 = String             #277          // Unknown combinator:
  #279 = Utf8               append
  #280 = Utf8               (Ljava/lang/String;)Ljava/lang/StringBuilder;
  #281 = NameAndType        #279:#280     // append:(Ljava/lang/String;)Ljava/lang/StringBuilder;
  #282 = Methodref          #275.#281     // java/lang/StringBuilder.append:(Ljava/lang/String;)Ljava/lang/StringBuilder;
  #283 = Utf8               (C)Ljava/lang/StringBuilder;
  #284 = NameAndType        #279:#283     // append:(C)Ljava/lang/StringBuilder;
  #285 = Methodref          #275.#284     // java/lang/StringBuilder.append:(C)Ljava/lang/StringBuilder;
  #286 = Utf8               toString
  #287 = NameAndType        #286:#177     // toString:()Ljava/lang/String;
  #288 = Methodref          #275.#287     // java/lang/StringBuilder.toString:()Ljava/lang/String;
  #289 = Utf8               replaceRightMostEvaluator
  #290 = NameAndType        #289:#262     // replaceRightMostEvaluator:(Lcoursier/util/shaded/org/jsoup/select/Evaluator;)V
  #291 = Methodref          #22.#290      // coursier/util/shaded/org/jsoup/select/CombiningEvaluator$Or.replaceRightMostEvaluator:(Lcoursier/util/shaded/org/jsoup/select/Evaluator;)V
  #292 = Utf8               rootEval
  #293 = Utf8               Lcoursier/util/shaded/org/jsoup/select/Evaluator;
  #294 = Utf8               currentEval
  #295 = Utf8               or
  #296 = Utf8               Lcoursier/util/shaded/org/jsoup/select/CombiningEvaluator$Or;
  #297 = Utf8               C
  #298 = Utf8               subQuery
  #299 = Utf8               newEval
  #300 = Utf8               replaceRightMost
  #301 = Utf8               coursier/util/shaded/org/jsoup/internal/StringUtil
  #302 = Class              #301          // coursier/util/shaded/org/jsoup/internal/StringUtil
  #303 = Utf8               borrowBuilder
  #304 = Utf8               ()Ljava/lang/StringBuilder;
  #305 = NameAndType        #303:#304     // borrowBuilder:()Ljava/lang/StringBuilder;
  #306 = Methodref          #302.#305     // coursier/util/shaded/org/jsoup/internal/StringUtil.borrowBuilder:()Ljava/lang/StringBuilder;
  #307 = Utf8               (
  #308 = String             #307          // (
  #309 = Utf8               matches
  #310 = Utf8               (Ljava/lang/String;)Z
  #311 = NameAndType        #309:#310     // matches:(Ljava/lang/String;)Z
  #312 = Methodref          #183.#311     // coursier/util/shaded/org/jsoup/parser/TokenQueue.matches:(Ljava/lang/String;)Z
  #313 = Utf8               chompBalanced
  #314 = Utf8               (CC)Ljava/lang/String;
  #315 = NameAndType        #313:#314     // chompBalanced:(CC)Ljava/lang/String;
  #316 = Methodref          #183.#315     // coursier/util/shaded/org/jsoup/parser/TokenQueue.chompBalanced:(CC)Ljava/lang/String;
  #317 = Utf8               )
  #318 = String             #317          // )
  #319 = Utf8               [
  #320 = String             #319          // [
  #321 = Utf8               ]
  #322 = String             #321          // ]
  #323 = Utf8               releaseBuilder
  #324 = Utf8               (Ljava/lang/StringBuilder;)Ljava/lang/String;
  #325 = NameAndType        #323:#324     // releaseBuilder:(Ljava/lang/StringBuilder;)Ljava/lang/String;
  #326 = Methodref          #302.#325     // coursier/util/shaded/org/jsoup/internal/StringUtil.releaseBuilder:(Ljava/lang/StringBuilder;)Ljava/lang/String;
  #327 = Utf8               sq
  #328 = Utf8               Ljava/lang/StringBuilder;
  #329 = Utf8               #
  #330 = String             #329          // #
  #331 = Utf8               matchChomp
  #332 = NameAndType        #331:#310     // matchChomp:(Ljava/lang/String;)Z
  #333 = Methodref          #183.#332     // coursier/util/shaded/org/jsoup/parser/TokenQueue.matchChomp:(Ljava/lang/String;)Z
  #334 = Utf8               byId
  #335 = NameAndType        #334:#161     // byId:()V
  #336 = Methodref          #2.#335       // coursier/util/shaded/org/jsoup/select/QueryParser.byId:()V
  #337 = Utf8               .
  #338 = String             #337          // .
  #339 = Utf8               byClass
  #340 = NameAndType        #339:#161     // byClass:()V
  #341 = Methodref          #2.#340       // coursier/util/shaded/org/jsoup/select/QueryParser.byClass:()V
  #342 = Utf8               matchesWord
  #343 = NameAndType        #342:#208     // matchesWord:()Z
  #344 = Methodref          #183.#343     // coursier/util/shaded/org/jsoup/parser/TokenQueue.matchesWord:()Z
  #345 = Utf8               *|
  #346 = String             #345          // *|
  #347 = Utf8               byTag
  #348 = NameAndType        #347:#161     // byTag:()V
  #349 = Methodref          #2.#348       // coursier/util/shaded/org/jsoup/select/QueryParser.byTag:()V
  #350 = Utf8               byAttribute
  #351 = NameAndType        #350:#161     // byAttribute:()V
  #352 = Methodref          #2.#351       // coursier/util/shaded/org/jsoup/select/QueryParser.byAttribute:()V
  #353 = Utf8               *
  #354 = String             #353          // *
  #355 = Utf8               allElements
  #356 = NameAndType        #355:#161     // allElements:()V
  #357 = Methodref          #2.#356       // coursier/util/shaded/org/jsoup/select/QueryParser.allElements:()V
  #358 = Utf8               :lt(
  #359 = String             #358          // :lt(
  #360 = Utf8               indexLessThan
  #361 = NameAndType        #360:#161     // indexLessThan:()V
  #362 = Methodref          #2.#361       // coursier/util/shaded/org/jsoup/select/QueryParser.indexLessThan:()V
  #363 = Utf8               :gt(
  #364 = String             #363          // :gt(
  #365 = Utf8               indexGreaterThan
  #366 = NameAndType        #365:#161     // indexGreaterThan:()V
  #367 = Methodref          #2.#366       // coursier/util/shaded/org/jsoup/select/QueryParser.indexGreaterThan:()V
  #368 = Utf8               :eq(
  #369 = String             #368          // :eq(
  #370 = Utf8               indexEquals
  #371 = NameAndType        #370:#161     // indexEquals:()V
  #372 = Methodref          #2.#371       // coursier/util/shaded/org/jsoup/select/QueryParser.indexEquals:()V
  #373 = Utf8               :has(
  #374 = String             #373          // :has(
  #375 = Utf8               has
  #376 = NameAndType        #375:#161     // has:()V
  #377 = Methodref          #2.#376       // coursier/util/shaded/org/jsoup/select/QueryParser.has:()V
  #378 = Utf8               :contains(
  #379 = String             #378          // :contains(
  #380 = Utf8               contains
  #381 = Utf8               (Z)V
  #382 = NameAndType        #380:#381     // contains:(Z)V
  #383 = Methodref          #2.#382       // coursier/util/shaded/org/jsoup/select/QueryParser.contains:(Z)V
  #384 = Utf8               :containsOwn(
  #385 = String             #384          // :containsOwn(
  #386 = Utf8               :containsData(
  #387 = String             #386          // :containsData(
  #388 = Utf8               containsData
  #389 = NameAndType        #388:#161     // containsData:()V
  #390 = Methodref          #2.#389       // coursier/util/shaded/org/jsoup/select/QueryParser.containsData:()V
  #391 = Utf8               :matches(
  #392 = String             #391          // :matches(
  #393 = NameAndType        #309:#381     // matches:(Z)V
  #394 = Methodref          #2.#393       // coursier/util/shaded/org/jsoup/select/QueryParser.matches:(Z)V
  #395 = Utf8               :matchesOwn(
  #396 = String             #395          // :matchesOwn(
  #397 = Utf8               :not(
  #398 = String             #397          // :not(
  #399 = Utf8               not
  #400 = NameAndType        #399:#161     // not:()V
  #401 = Methodref          #2.#400       // coursier/util/shaded/org/jsoup/select/QueryParser.not:()V
  #402 = Utf8               :nth-child(
  #403 = String             #402          // :nth-child(
  #404 = Utf8               cssNthChild
  #405 = Utf8               (ZZ)V
  #406 = NameAndType        #404:#405     // cssNthChild:(ZZ)V
  #407 = Methodref          #2.#406       // coursier/util/shaded/org/jsoup/select/QueryParser.cssNthChild:(ZZ)V
  #408 = Utf8               :nth-last-child(
  #409 = String             #408          // :nth-last-child(
  #410 = Utf8               :nth-of-type(
  #411 = String             #410          // :nth-of-type(
  #412 = Utf8               :nth-last-of-type(
  #413 = String             #412          // :nth-last-of-type(
  #414 = Utf8               :first-child
  #415 = String             #414          // :first-child
  #416 = Methodref          #37.#162      // coursier/util/shaded/org/jsoup/select/Evaluator$IsFirstChild."<init>":()V
  #417 = Utf8               :last-child
  #418 = String             #417          // :last-child
  #419 = Methodref          #42.#162      // coursier/util/shaded/org/jsoup/select/Evaluator$IsLastChild."<init>":()V
  #420 = Utf8               :first-of-type
  #421 = String             #420          // :first-of-type
  #422 = Methodref          #45.#162      // coursier/util/shaded/org/jsoup/select/Evaluator$IsFirstOfType."<init>":()V
  #423 = Utf8               :last-of-type
  #424 = String             #423          // :last-of-type
  #425 = Methodref          #48.#162      // coursier/util/shaded/org/jsoup/select/Evaluator$IsLastOfType."<init>":()V
  #426 = Utf8               :only-child
  #427 = String             #426          // :only-child
  #428 = Methodref          #51.#162      // coursier/util/shaded/org/jsoup/select/Evaluator$IsOnlyChild."<init>":()V
  #429 = Utf8               :only-of-type
  #430 = String             #429          // :only-of-type
  #431 = Methodref          #54.#162      // coursier/util/shaded/org/jsoup/select/Evaluator$IsOnlyOfType."<init>":()V
  #432 = Utf8               :empty
  #433 = String             #432          // :empty
  #434 = Methodref          #57.#162      // coursier/util/shaded/org/jsoup/select/Evaluator$IsEmpty."<init>":()V
  #435 = Utf8               :root
  #436 = String             #435          // :root
  #437 = Methodref          #60.#162      // coursier/util/shaded/org/jsoup/select/Evaluator$IsRoot."<init>":()V
  #438 = Utf8               :matchText
  #439 = String             #438          // :matchText
  #440 = Methodref          #63.#162      // coursier/util/shaded/org/jsoup/select/Evaluator$MatchText."<init>":()V
  #441 = Utf8               Could not parse query \'%s\': unexpected token at \'%s\'
  #442 = String             #441          // Could not parse query \'%s\': unexpected token at \'%s\'
  #443 = Utf8               remainder
  #444 = NameAndType        #443:#177     // remainder:()Ljava/lang/String;
  #445 = Methodref          #183.#444     // coursier/util/shaded/org/jsoup/parser/TokenQueue.remainder:()Ljava/lang/String;
  #446 = Utf8               consumeCssIdentifier
  #447 = NameAndType        #446:#177     // consumeCssIdentifier:()Ljava/lang/String;
  #448 = Methodref          #183.#447     // coursier/util/shaded/org/jsoup/parser/TokenQueue.consumeCssIdentifier:()Ljava/lang/String;
  #449 = Methodref          #66.#184      // coursier/util/shaded/org/jsoup/select/Evaluator$Id."<init>":(Ljava/lang/String;)V
  #450 = Utf8               id
  #451 = Methodref          #69.#184      // coursier/util/shaded/org/jsoup/select/Evaluator$Class."<init>":(Ljava/lang/String;)V
  #452 = Utf8               className
  #453 = Utf8               consumeElementSelector
  #454 = NameAndType        #453:#177     // consumeElementSelector:()Ljava/lang/String;
  #455 = Methodref          #183.#454     // coursier/util/shaded/org/jsoup/parser/TokenQueue.consumeElementSelector:()Ljava/lang/String;
  #456 = Utf8               coursier/util/shaded/org/jsoup/internal/Normalizer
  #457 = Class              #456          // coursier/util/shaded/org/jsoup/internal/Normalizer
  #458 = Utf8               normalize
  #459 = Utf8               (Ljava/lang/String;)Ljava/lang/String;
  #460 = NameAndType        #458:#459     // normalize:(Ljava/lang/String;)Ljava/lang/String;
  #461 = Methodref          #457.#460     // coursier/util/shaded/org/jsoup/internal/Normalizer.normalize:(Ljava/lang/String;)Ljava/lang/String;
  #462 = Utf8               startsWith
  #463 = NameAndType        #462:#310     // startsWith:(Ljava/lang/String;)Z
  #464 = Methodref          #175.#463     // java/lang/String.startsWith:(Ljava/lang/String;)Z
  #465 = Methodref          #72.#184      // coursier/util/shaded/org/jsoup/select/Evaluator$Tag."<init>":(Ljava/lang/String;)V
  #466 = Utf8               :
  #467 = String             #466          // :
  #468 = Utf8               replace
  #469 = Utf8               (Ljava/lang/CharSequence;Ljava/lang/CharSequence;)Ljava/lang/String;
  #470 = NameAndType        #468:#469     // replace:(Ljava/lang/CharSequence;Ljava/lang/CharSequence;)Ljava/lang/String;
  #471 = Methodref          #175.#470     // java/lang/String.replace:(Ljava/lang/CharSequence;Ljava/lang/CharSequence;)Ljava/lang/String;
  #472 = Methodref          #75.#184      // coursier/util/shaded/org/jsoup/select/Evaluator$TagEndsWith."<init>":(Ljava/lang/String;)V
  #473 = Methodref          #22.#266      // coursier/util/shaded/org/jsoup/select/CombiningEvaluator$Or."<init>":([Lcoursier/util/shaded/org/jsoup/select/Evaluator;)V
  #474 = Utf8               |
  #475 = String             #474          // |
  #476 = Utf8               (Ljava/lang/CharSequence;)Z
  #477 = NameAndType        #380:#476     // contains:(Ljava/lang/CharSequence;)Z
  #478 = Methodref          #175.#477     // java/lang/String.contains:(Ljava/lang/CharSequence;)Z
  #479 = Utf8               tagName
  #480 = NameAndType        #148:#147     // AttributeEvals:[Ljava/lang/String;
  #481 = Fieldref           #2.#480       // coursier/util/shaded/org/jsoup/select/QueryParser.AttributeEvals:[Ljava/lang/String;
  #482 = Utf8               consumeToAny
  #483 = Utf8               ([Ljava/lang/String;)Ljava/lang/String;
  #484 = NameAndType        #482:#483     // consumeToAny:([Ljava/lang/String;)Ljava/lang/String;
  #485 = Methodref          #183.#484     // coursier/util/shaded/org/jsoup/parser/TokenQueue.consumeToAny:([Ljava/lang/String;)Ljava/lang/String;
  #486 = Utf8               ^
  #487 = String             #486          // ^
  #488 = Utf8               substring
  #489 = Utf8               (I)Ljava/lang/String;
  #490 = NameAndType        #488:#489     // substring:(I)Ljava/lang/String;
  #491 = Methodref          #175.#490     // java/lang/String.substring:(I)Ljava/lang/String;
  #492 = Methodref          #78.#184      // coursier/util/shaded/org/jsoup/select/Evaluator$AttributeStarting."<init>":(Ljava/lang/String;)V
  #493 = Methodref          #81.#184      // coursier/util/shaded/org/jsoup/select/Evaluator$Attribute."<init>":(Ljava/lang/String;)V
  #494 = Utf8               =
  #495 = String             #494          // =
  #496 = Utf8               (Ljava/lang/String;Ljava/lang/String;)V
  #497 = NameAndType        #159:#496     // "<init>":(Ljava/lang/String;Ljava/lang/String;)V
  #498 = Methodref          #84.#497      // coursier/util/shaded/org/jsoup/select/Evaluator$AttributeWithValue."<init>":(Ljava/lang/String;Ljava/lang/String;)V
  #499 = Utf8               !=
  #500 = String             #499          // !=
  #501 = Methodref          #87.#497      // coursier/util/shaded/org/jsoup/select/Evaluator$AttributeWithValueNot."<init>":(Ljava/lang/String;Ljava/lang/String;)V
  #502 = Utf8               ^=
  #503 = String             #502          // ^=
  #504 = Methodref          #90.#497      // coursier/util/shaded/org/jsoup/select/Evaluator$AttributeWithValueStarting."<init>":(Ljava/lang/String;Ljava/lang/String;)V
  #505 = Utf8               $=
  #506 = String             #505          // $=
  #507 = Methodref          #93.#497      // coursier/util/shaded/org/jsoup/select/Evaluator$AttributeWithValueEnding."<init>":(Ljava/lang/String;Ljava/lang/String;)V
  #508 = Utf8               *=
  #509 = String             #508          // *=
  #510 = Methodref          #96.#497      // coursier/util/shaded/org/jsoup/select/Evaluator$AttributeWithValueContaining."<init>":(Ljava/lang/String;Ljava/lang/String;)V
  #511 = Utf8               ~=
  #512 = String             #511          // ~=
  #513 = Utf8               java/util/regex/Pattern
  #514 = Class              #513          // java/util/regex/Pattern
  #515 = Utf8               compile
  #516 = Utf8               (Ljava/lang/String;)Ljava/util/regex/Pattern;
  #517 = NameAndType        #515:#516     // compile:(Ljava/lang/String;)Ljava/util/regex/Pattern;
  #518 = Methodref          #514.#517     // java/util/regex/Pattern.compile:(Ljava/lang/String;)Ljava/util/regex/Pattern;
  #519 = Utf8               (Ljava/lang/String;Ljava/util/regex/Pattern;)V
  #520 = NameAndType        #159:#519     // "<init>":(Ljava/lang/String;Ljava/util/regex/Pattern;)V
  #521 = Methodref          #99.#520      // coursier/util/shaded/org/jsoup/select/Evaluator$AttributeWithValueMatching."<init>":(Ljava/lang/String;Ljava/util/regex/Pattern;)V
  #522 = Utf8               Could not parse attribute query \'%s\': unexpected token at \'%s\'
  #523 = String             #522          // Could not parse attribute query \'%s\': unexpected token at \'%s\'
  #524 = Utf8               cq
  #525 = Utf8               key
  #526 = Methodref          #102.#162     // coursier/util/shaded/org/jsoup/select/Evaluator$AllElements."<init>":()V
  #527 = Utf8               consumeIndex
  #528 = NameAndType        #527:#239     // consumeIndex:()I
  #529 = Methodref          #2.#528       // coursier/util/shaded/org/jsoup/select/QueryParser.consumeIndex:()I
  #530 = Utf8               (I)V
  #531 = NameAndType        #159:#530     // "<init>":(I)V
  #532 = Methodref          #105.#531     // coursier/util/shaded/org/jsoup/select/Evaluator$IndexLessThan."<init>":(I)V
  #533 = Methodref          #108.#531     // coursier/util/shaded/org/jsoup/select/Evaluator$IndexGreaterThan."<init>":(I)V
  #534 = Methodref          #111.#531     // coursier/util/shaded/org/jsoup/select/Evaluator$IndexEquals."<init>":(I)V
  #535 = Utf8               chompTo
  #536 = NameAndType        #535:#459     // chompTo:(Ljava/lang/String;)Ljava/lang/String;
  #537 = Methodref          #183.#536     // coursier/util/shaded/org/jsoup/parser/TokenQueue.chompTo:(Ljava/lang/String;)Ljava/lang/String;
  #538 = NameAndType        #156:#157     // NTH_AB:Ljava/util/regex/Pattern;
  #539 = Fieldref           #2.#538       // coursier/util/shaded/org/jsoup/select/QueryParser.NTH_AB:Ljava/util/regex/Pattern;
  #540 = Utf8               matcher
  #541 = Utf8               (Ljava/lang/CharSequence;)Ljava/util/regex/Matcher;
  #542 = NameAndType        #540:#541     // matcher:(Ljava/lang/CharSequence;)Ljava/util/regex/Matcher;
  #543 = Methodref          #514.#542     // java/util/regex/Pattern.matcher:(Ljava/lang/CharSequence;)Ljava/util/regex/Matcher;
  #544 = NameAndType        #158:#157     // NTH_B:Ljava/util/regex/Pattern;
  #545 = Fieldref           #2.#544       // coursier/util/shaded/org/jsoup/select/QueryParser.NTH_B:Ljava/util/regex/Pattern;
  #546 = Utf8               odd
  #547 = String             #546          // odd
  #548 = Utf8               equals
  #549 = NameAndType        #548:#221     // equals:(Ljava/lang/Object;)Z
  #550 = Methodref          #175.#549     // java/lang/String.equals:(Ljava/lang/Object;)Z
  #551 = Utf8               java/util/regex/Matcher
  #552 = Class              #551          // java/util/regex/Matcher
  #553 = Utf8               even
  #554 = String             #553          // even
  #555 = NameAndType        #309:#208     // matches:()Z
  #556 = Methodref          #552.#555     // java/util/regex/Matcher.matches:()Z
  #557 = Utf8               group
  #558 = NameAndType        #557:#489     // group:(I)Ljava/lang/String;
  #559 = Methodref          #552.#558     // java/util/regex/Matcher.group:(I)Ljava/lang/String;
  #560 = Utf8               ^\\+
  #561 = String             #560          // ^\\+
  #562 = Utf8
  #563 = String             #562          //
  #564 = Utf8               replaceFirst
  #565 = Utf8               (Ljava/lang/String;Ljava/lang/String;)Ljava/lang/String;
  #566 = NameAndType        #564:#565     // replaceFirst:(Ljava/lang/String;Ljava/lang/String;)Ljava/lang/String;
  #567 = Methodref          #175.#566     // java/lang/String.replaceFirst:(Ljava/lang/String;Ljava/lang/String;)Ljava/lang/String;
  #568 = Utf8               java/lang/Integer
  #569 = Class              #568          // java/lang/Integer
  #570 = Utf8               parseInt
  #571 = Utf8               (Ljava/lang/String;)I
  #572 = NameAndType        #570:#571     // parseInt:(Ljava/lang/String;)I
  #573 = Methodref          #569.#572     // java/lang/Integer.parseInt:(Ljava/lang/String;)I
  #574 = NameAndType        #557:#177     // group:()Ljava/lang/String;
  #575 = Methodref          #552.#574     // java/util/regex/Matcher.group:()Ljava/lang/String;
  #576 = Utf8               Could not parse nth-index \'%s\': unexpected format
  #577 = String             #576          // Could not parse nth-index \'%s\': unexpected format
  #578 = Utf8               (II)V
  #579 = NameAndType        #159:#578     // "<init>":(II)V
  #580 = Methodref          #114.#579     // coursier/util/shaded/org/jsoup/select/Evaluator$IsNthLastOfType."<init>":(II)V
  #581 = Methodref          #117.#579     // coursier/util/shaded/org/jsoup/select/Evaluator$IsNthOfType."<init>":(II)V
  #582 = Methodref          #120.#579     // coursier/util/shaded/org/jsoup/select/Evaluator$IsNthLastChild."<init>":(II)V
  #583 = Methodref          #123.#579     // coursier/util/shaded/org/jsoup/select/Evaluator$IsNthChild."<init>":(II)V
  #584 = Utf8               a
  #585 = Utf8               I
  #586 = Utf8               b
  #587 = Utf8               backwards
  #588 = Utf8               ofType
  #589 = Utf8               argS
  #590 = Utf8               mAB
  #591 = Utf8               Ljava/util/regex/Matcher;
  #592 = Utf8               mB
  #593 = Utf8               isNumeric
  #594 = NameAndType        #593:#310     // isNumeric:(Ljava/lang/String;)Z
  #595 = Methodref          #302.#594     // coursier/util/shaded/org/jsoup/internal/StringUtil.isNumeric:(Ljava/lang/String;)Z
  #596 = Utf8               Index must be numeric
  #597 = String             #596          // Index must be numeric
  #598 = Utf8               isTrue
  #599 = Utf8               (ZLjava/lang/String;)V
  #600 = NameAndType        #598:#599     // isTrue:(ZLjava/lang/String;)V
  #601 = Methodref          #170.#600     // coursier/util/shaded/org/jsoup/helper/Validate.isTrue:(ZLjava/lang/String;)V
  #602 = Utf8               indexS
  #603 = Utf8               :has
  #604 = String             #603          // :has
  #605 = NameAndType        #224:#160     // consume:(Ljava/lang/String;)V
  #606 = Methodref          #183.#605     // coursier/util/shaded/org/jsoup/parser/TokenQueue.consume:(Ljava/lang/String;)V
  #607 = Utf8               :has(el) subselect must not be empty
  #608 = String             #607          // :has(el) subselect must not be empty
  #609 = NameAndType        #171:#496     // notEmpty:(Ljava/lang/String;Ljava/lang/String;)V
  #610 = Methodref          #170.#609     // coursier/util/shaded/org/jsoup/helper/Validate.notEmpty:(Ljava/lang/String;Ljava/lang/String;)V
  #611 = Methodref          #126.#263     // coursier/util/shaded/org/jsoup/select/StructuralEvaluator$Has."<init>":(Lcoursier/util/shaded/org/jsoup/select/Evaluator;)V
  #612 = Utf8               :containsOwn
  #613 = String             #612          // :containsOwn
  #614 = Utf8               :contains
  #615 = String             #614          // :contains
  #616 = Utf8               unescape
  #617 = NameAndType        #616:#459     // unescape:(Ljava/lang/String;)Ljava/lang/String;
  #618 = Methodref          #183.#617     // coursier/util/shaded/org/jsoup/parser/TokenQueue.unescape:(Ljava/lang/String;)Ljava/lang/String;
  #619 = Utf8               :contains(text) query must not be empty
  #620 = String             #619          // :contains(text) query must not be empty
  #621 = Methodref          #129.#184     // coursier/util/shaded/org/jsoup/select/Evaluator$ContainsOwnText."<init>":(Ljava/lang/String;)V
  #622 = Methodref          #132.#184     // coursier/util/shaded/org/jsoup/select/Evaluator$ContainsText."<init>":(Ljava/lang/String;)V
  #623 = Utf8               own
  #624 = Utf8               searchText
  #625 = Utf8               :containsData
  #626 = String             #625          // :containsData
  #627 = Utf8               :containsData(text) query must not be empty
  #628 = String             #627          // :containsData(text) query must not be empty
  #629 = Methodref          #135.#184     // coursier/util/shaded/org/jsoup/select/Evaluator$ContainsData."<init>":(Ljava/lang/String;)V
  #630 = Utf8               :matchesOwn
  #631 = String             #630          // :matchesOwn
  #632 = Utf8               :matches
  #633 = String             #632          // :matches
  #634 = Utf8               :matches(regex) query must not be empty
  #635 = String             #634          // :matches(regex) query must not be empty
  #636 = Utf8               (Ljava/util/regex/Pattern;)V
  #637 = NameAndType        #159:#636     // "<init>":(Ljava/util/regex/Pattern;)V
  #638 = Methodref          #138.#637     // coursier/util/shaded/org/jsoup/select/Evaluator$MatchesOwn."<init>":(Ljava/util/regex/Pattern;)V
  #639 = Methodref          #141.#637     // coursier/util/shaded/org/jsoup/select/Evaluator$Matches."<init>":(Ljava/util/regex/Pattern;)V
  #640 = Utf8               regex
  #641 = Utf8               :not
  #642 = String             #641          // :not
  #643 = Utf8               :not(selector) subselect must not be empty
  #644 = String             #643          // :not(selector) subselect must not be empty
  #645 = Methodref          #144.#263     // coursier/util/shaded/org/jsoup/select/StructuralEvaluator$Not."<init>":(Lcoursier/util/shaded/org/jsoup/select/Evaluator;)V
  #646 = Utf8               <clinit>
  #647 = Utf8               ,
  #648 = String             #647          // ,
  #649 = Utf8               >
  #650 = String             #649          // >
  #651 = Utf8               +
  #652 = String             #651          // +
  #653 = Utf8               ~
  #654 = String             #653          // ~
  #655 = Utf8
  #656 = String             #655          //
  #657 = Utf8               (([+-])?(\\d+)?)n(\\s*([+-])?\\s*\\d+)?
  #658 = String             #657          // (([+-])?(\\d+)?)n(\\s*([+-])?\\s*\\d+)?
  #659 = Utf8               (Ljava/lang/String;I)Ljava/util/regex/Pattern;
  #660 = NameAndType        #515:#659     // compile:(Ljava/lang/String;I)Ljava/util/regex/Pattern;
  #661 = Methodref          #514.#660     // java/util/regex/Pattern.compile:(Ljava/lang/String;I)Ljava/util/regex/Pattern;
  #662 = Utf8               ([+-])?(\\d+)
  #663 = String             #662          // ([+-])?(\\d+)
  #664 = Utf8               Signature
  #665 = Utf8               Code
  #666 = Utf8               LineNumberTable
  #667 = Utf8               LocalVariableTable
  #668 = Utf8               StackMapTable
  #669 = Utf8               InnerClasses
  #670 = Utf8               SourceFile
{
  private static final java.lang.String[] combinators;
    descriptor: [Ljava/lang/String;
    flags: (0x001a) ACC_PRIVATE, ACC_STATIC, ACC_FINAL

  private static final java.lang.String[] AttributeEvals;
    descriptor: [Ljava/lang/String;
    flags: (0x001a) ACC_PRIVATE, ACC_STATIC, ACC_FINAL

  private coursier.util.shaded.org.jsoup.parser.TokenQueue tq;
    descriptor: Lcoursier/util/shaded/org/jsoup/parser/TokenQueue;
    flags: (0x0002) ACC_PRIVATE

  private java.lang.String query;
    descriptor: Ljava/lang/String;
    flags: (0x0002) ACC_PRIVATE

  private java.util.List<coursier.util.shaded.org.jsoup.select.Evaluator> evals;
    descriptor: Ljava/util/List;
    flags: (0x0002) ACC_PRIVATE
    Signature: #155                         // Ljava/util/List<Lcoursier/util/shaded/org/jsoup/select/Evaluator;>;

  private static final java.util.regex.Pattern NTH_AB;
    descriptor: Ljava/util/regex/Pattern;
    flags: (0x001a) ACC_PRIVATE, ACC_STATIC, ACC_FINAL

  private static final java.util.regex.Pattern NTH_B;
    descriptor: Ljava/util/regex/Pattern;
    flags: (0x001a) ACC_PRIVATE, ACC_STATIC, ACC_FINAL

  private coursier.util.shaded.org.jsoup.select.QueryParser(java.lang.String);
    descriptor: (Ljava/lang/String;)V
    flags: (0x0002) ACC_PRIVATE
    Code:
      stack=4, locals=2, args_size=2
         0: aload_0
         1: invokespecial #163                // Method java/lang/Object."<init>":()V
         4: aload_0
         5: new           #165                // class java/util/ArrayList
         8: dup
         9: invokespecial #166                // Method java/util/ArrayList."<init>":()V
        12: putfield      #168                // Field evals:Ljava/util/List;
        15: aload_1
        16: invokestatic  #173                // Method coursier/util/shaded/org/jsoup/helper/Validate.notEmpty:(Ljava/lang/String;)V
        19: aload_1
        20: invokevirtual #179                // Method java/lang/String.trim:()Ljava/lang/String;
        23: astore_1
        24: aload_0
        25: aload_1
        26: putfield      #181                // Field query:Ljava/lang/String;
        29: aload_0
        30: new           #183                // class coursier/util/shaded/org/jsoup/parser/TokenQueue
        33: dup
        34: aload_1
        35: invokespecial #185                // Method coursier/util/shaded/org/jsoup/parser/TokenQueue."<init>":(Ljava/lang/String;)V
        38: putfield      #187                // Field tq:Lcoursier/util/shaded/org/jsoup/parser/TokenQueue;
        41: return
      LineNumberTable:
        line 29: 0
        line 23: 4
        line 30: 15
        line 31: 19
        line 32: 24
        line 33: 29
        line 34: 41
      LocalVariableTable:
        Start  Length  Slot  Name   Signature
            0      42     0  this   Lcoursier/util/shaded/org/jsoup/select/QueryParser;
            0      42     1 query   Ljava/lang/String;

  public static coursier.util.shaded.org.jsoup.select.Evaluator parse(java.lang.String);
    descriptor: (Ljava/lang/String;)Lcoursier/util/shaded/org/jsoup/select/Evaluator;
    flags: (0x0009) ACC_PUBLIC, ACC_STATIC
    Code:
      stack=4, locals=2, args_size=1
         0: new           #2                  // class coursier/util/shaded/org/jsoup/select/QueryParser
         3: dup
         4: aload_0
         5: invokespecial #194                // Method "<init>":(Ljava/lang/String;)V
         8: astore_1
         9: aload_1
        10: invokevirtual #197                // Method parse:()Lcoursier/util/shaded/org/jsoup/select/Evaluator;
        13: areturn
        14: astore_1
        15: new           #7                  // class coursier/util/shaded/org/jsoup/select/Selector$SelectorParseException
        18: dup
        19: aload_1
        20: invokevirtual #200                // Method java/lang/IllegalArgumentException.getMessage:()Ljava/lang/String;
        23: iconst_0
        24: anewarray     #4                  // class java/lang/Object
        27: invokespecial #203                // Method coursier/util/shaded/org/jsoup/select/Selector$SelectorParseException."<init>":(Ljava/lang/String;[Ljava/lang/Object;)V
        30: athrow
      Exception table:
         from    to  target type
             0    13    14   Class java/lang/IllegalArgumentException
      StackMapTable: number_of_entries = 1
        frame_type = 78 /* same_locals_1_stack_item */
          stack = [ class java/lang/IllegalArgumentException ]
      LineNumberTable:
        line 44: 0
        line 45: 9
        line 46: 14
        line 47: 15
      LocalVariableTable:
        Start  Length  Slot  Name   Signature
            9       5     1     p   Lcoursier/util/shaded/org/jsoup/select/QueryParser;
           15      16     1     e   Ljava/lang/IllegalArgumentException;
            0      31     0 query   Ljava/lang/String;

  coursier.util.shaded.org.jsoup.select.Evaluator parse();
    descriptor: ()Lcoursier/util/shaded/org/jsoup/select/Evaluator;
    flags: (0x0000)
    Code:
      stack=3, locals=2, args_size=1
         0: aload_0
         1: getfield      #187                // Field tq:Lcoursier/util/shaded/org/jsoup/parser/TokenQueue;
         4: invokevirtual #210                // Method coursier/util/shaded/org/jsoup/parser/TokenQueue.consumeWhitespace:()Z
         7: pop
         8: aload_0
         9: getfield      #187                // Field tq:Lcoursier/util/shaded/org/jsoup/parser/TokenQueue;
        12: getstatic     #212                // Field combinators:[Ljava/lang/String;
        15: invokevirtual #216                // Method coursier/util/shaded/org/jsoup/parser/TokenQueue.matchesAny:([Ljava/lang/String;)Z
        18: ifeq          52
        21: aload_0
        22: getfield      #168                // Field evals:Ljava/util/List;
        25: new           #12                 // class coursier/util/shaded/org/jsoup/select/StructuralEvaluator$Root
        28: dup
        29: invokespecial #217                // Method coursier/util/shaded/org/jsoup/select/StructuralEvaluator$Root."<init>":()V
        32: invokeinterface #223,  2          // InterfaceMethod java/util/List.add:(Ljava/lang/Object;)Z
        37: pop
        38: aload_0
        39: aload_0
        40: getfield      #187                // Field tq:Lcoursier/util/shaded/org/jsoup/parser/TokenQueue;
        43: invokevirtual #227                // Method coursier/util/shaded/org/jsoup/parser/TokenQueue.consume:()C
        46: invokespecial #231                // Method combinator:(C)V
        49: goto          56
        52: aload_0
        53: invokespecial #234                // Method findElements:()V
        56: aload_0
        57: getfield      #187                // Field tq:Lcoursier/util/shaded/org/jsoup/parser/TokenQueue;
        60: invokevirtual #237                // Method coursier/util/shaded/org/jsoup/parser/TokenQueue.isEmpty:()Z
        63: ifne          121
        66: aload_0
        67: getfield      #187                // Field tq:Lcoursier/util/shaded/org/jsoup/parser/TokenQueue;
        70: invokevirtual #210                // Method coursier/util/shaded/org/jsoup/parser/TokenQueue.consumeWhitespace:()Z
        73: istore_1
        74: aload_0
        75: getfield      #187                // Field tq:Lcoursier/util/shaded/org/jsoup/parser/TokenQueue;
        78: getstatic     #212                // Field combinators:[Ljava/lang/String;
        81: invokevirtual #216                // Method coursier/util/shaded/org/jsoup/parser/TokenQueue.matchesAny:([Ljava/lang/String;)Z
        84: ifeq          101
        87: aload_0
        88: aload_0
        89: getfield      #187                // Field tq:Lcoursier/util/shaded/org/jsoup/parser/TokenQueue;
        92: invokevirtual #227                // Method coursier/util/shaded/org/jsoup/parser/TokenQueue.consume:()C
        95: invokespecial #231                // Method combinator:(C)V
        98: goto          118
       101: iload_1
       102: ifeq          114
       105: aload_0
       106: bipush        32
       108: invokespecial #231                // Method combinator:(C)V
       111: goto          118
       114: aload_0
       115: invokespecial #234                // Method findElements:()V
       118: goto          56
       121: aload_0
       122: getfield      #168                // Field evals:Ljava/util/List;
       125: invokeinterface #241,  1          // InterfaceMethod java/util/List.size:()I
       130: iconst_1
       131: if_icmpne     148
       134: aload_0
       135: getfield      #168                // Field evals:Ljava/util/List;
       138: iconst_0
       139: invokeinterface #245,  2          // InterfaceMethod java/util/List.get:(I)Ljava/lang/Object;
       144: checkcast     #39                 // class coursier/util/shaded/org/jsoup/select/Evaluator
       147: areturn
       148: new           #17                 // class coursier/util/shaded/org/jsoup/select/CombiningEvaluator$And
       151: dup
       152: aload_0
       153: getfield      #168                // Field evals:Ljava/util/List;
       156: invokespecial #248                // Method coursier/util/shaded/org/jsoup/select/CombiningEvaluator$And."<init>":(Ljava/util/Collection;)V
       159: areturn
      StackMapTable: number_of_entries = 7
        frame_type = 52 /* same */
        frame_type = 3 /* same */
        frame_type = 252 /* append */
          offset_delta = 44
          locals = [ int ]
        frame_type = 12 /* same */
        frame_type = 250 /* chop */
          offset_delta = 3
        frame_type = 2 /* same */
        frame_type = 26 /* same */
      LineNumberTable:
        line 56: 0
        line 58: 8
        line 59: 21
        line 60: 38
        line 62: 52
        line 65: 56
        line 67: 66
        line 69: 74
        line 70: 87
        line 71: 101
        line 72: 105
        line 74: 114
        line 76: 118
        line 78: 121
        line 79: 134
        line 81: 148
      LocalVariableTable:
        Start  Length  Slot  Name   Signature
           74      44     1 seenWhite   Z
            0     160     0  this   Lcoursier/util/shaded/org/jsoup/select/QueryParser;

  private void combinator(char);
    descriptor: (C)V
    flags: (0x0002) ACC_PRIVATE
    Code:
      stack=8, locals=8, args_size=2
         0: aload_0
         1: getfield      #187                // Field tq:Lcoursier/util/shaded/org/jsoup/parser/TokenQueue;
         4: invokevirtual #210                // Method coursier/util/shaded/org/jsoup/parser/TokenQueue.consumeWhitespace:()Z
         7: pop
         8: aload_0
         9: invokespecial #253                // Method consumeSubQuery:()Ljava/lang/String;
        12: astore_2
        13: aload_2
        14: invokestatic  #255                // Method parse:(Ljava/lang/String;)Lcoursier/util/shaded/org/jsoup/select/Evaluator;
        17: astore        5
        19: iconst_0
        20: istore        6
        22: aload_0
        23: getfield      #168                // Field evals:Ljava/util/List;
        26: invokeinterface #241,  1          // InterfaceMethod java/util/List.size:()I
        31: iconst_1
        32: if_icmpne     81
        35: aload_0
        36: getfield      #168                // Field evals:Ljava/util/List;
        39: iconst_0
        40: invokeinterface #245,  2          // InterfaceMethod java/util/List.get:(I)Ljava/lang/Object;
        45: checkcast     #39                 // class coursier/util/shaded/org/jsoup/select/Evaluator
        48: dup
        49: astore        4
        51: astore_3
        52: aload_3
        53: instanceof    #22                 // class coursier/util/shaded/org/jsoup/select/CombiningEvaluator$Or
        56: ifeq          96
        59: iload_1
        60: bipush        44
        62: if_icmpeq     96
        65: aload         4
        67: checkcast     #22                 // class coursier/util/shaded/org/jsoup/select/CombiningEvaluator$Or
        70: invokevirtual #258                // Method coursier/util/shaded/org/jsoup/select/CombiningEvaluator$Or.rightMostEvaluator:()Lcoursier/util/shaded/org/jsoup/select/Evaluator;
        73: astore        4
        75: iconst_1
        76: istore        6
        78: goto          96
        81: new           #17                 // class coursier/util/shaded/org/jsoup/select/CombiningEvaluator$And
        84: dup
        85: aload_0
        86: getfield      #168                // Field evals:Ljava/util/List;
        89: invokespecial #248                // Method coursier/util/shaded/org/jsoup/select/CombiningEvaluator$And."<init>":(Ljava/util/Collection;)V
        92: dup
        93: astore        4
        95: astore_3
        96: aload_0
        97: getfield      #168                // Field evals:Ljava/util/List;
       100: invokeinterface #261,  1          // InterfaceMethod java/util/List.clear:()V
       105: iload_1
       106: bipush        62
       108: if_icmpne     144
       111: new           #17                 // class coursier/util/shaded/org/jsoup/select/CombiningEvaluator$And
       114: dup
       115: iconst_2
       116: anewarray     #39                 // class coursier/util/shaded/org/jsoup/select/Evaluator
       119: dup
       120: iconst_0
       121: aload         5
       123: aastore
       124: dup
       125: iconst_1
       126: new           #25                 // class coursier/util/shaded/org/jsoup/select/StructuralEvaluator$ImmediateParent
       129: dup
       130: aload         4
       132: invokespecial #264                // Method coursier/util/shaded/org/jsoup/select/StructuralEvaluator$ImmediateParent."<init>":(Lcoursier/util/shaded/org/jsoup/select/Evaluator;)V
       135: aastore
       136: invokespecial #267                // Method coursier/util/shaded/org/jsoup/select/CombiningEvaluator$And."<init>":([Lcoursier/util/shaded/org/jsoup/select/Evaluator;)V
       139: astore        4
       141: goto          354
       144: iload_1
       145: bipush        32
       147: if_icmpne     183
       150: new           #17                 // class coursier/util/shaded/org/jsoup/select/CombiningEvaluator$And
       153: dup
       154: iconst_2
       155: anewarray     #39                 // class coursier/util/shaded/org/jsoup/select/Evaluator
       158: dup
       159: iconst_0
       160: aload         5
       162: aastore
       163: dup
       164: iconst_1
       165: new           #28                 // class coursier/util/shaded/org/jsoup/select/StructuralEvaluator$Parent
       168: dup
       169: aload         4
       171: invokespecial #268                // Method coursier/util/shaded/org/jsoup/select/StructuralEvaluator$Parent."<init>":(Lcoursier/util/shaded/org/jsoup/select/Evaluator;)V
       174: aastore
       175: invokespecial #267                // Method coursier/util/shaded/org/jsoup/select/CombiningEvaluator$And."<init>":([Lcoursier/util/shaded/org/jsoup/select/Evaluator;)V
       178: astore        4
       180: goto          354
       183: iload_1
       184: bipush        43
       186: if_icmpne     222
       189: new           #17                 // class coursier/util/shaded/org/jsoup/select/CombiningEvaluator$And
       192: dup
       193: iconst_2
       194: anewarray     #39                 // class coursier/util/shaded/org/jsoup/select/Evaluator
       197: dup
       198: iconst_0
       199: aload         5
       201: aastore
       202: dup
       203: iconst_1
       204: new           #31                 // class coursier/util/shaded/org/jsoup/select/StructuralEvaluator$ImmediatePreviousSibling
       207: dup
       208: aload         4
       210: invokespecial #269                // Method coursier/util/shaded/org/jsoup/select/StructuralEvaluator$ImmediatePreviousSibling."<init>":(Lcoursier/util/shaded/org/jsoup/select/Evaluator;)V
       213: aastore
       214: invokespecial #267                // Method coursier/util/shaded/org/jsoup/select/CombiningEvaluator$And."<init>":([Lcoursier/util/shaded/org/jsoup/select/Evaluator;)V
       217: astore        4
       219: goto          354
       222: iload_1
       223: bipush        126
       225: if_icmpne     261
       228: new           #17                 // class coursier/util/shaded/org/jsoup/select/CombiningEvaluator$And
       231: dup
       232: iconst_2
       233: anewarray     #39                 // class coursier/util/shaded/org/jsoup/select/Evaluator
       236: dup
       237: iconst_0
       238: aload         5
       240: aastore
       241: dup
       242: iconst_1
       243: new           #34                 // class coursier/util/shaded/org/jsoup/select/StructuralEvaluator$PreviousSibling
       246: dup
       247: aload         4
       249: invokespecial #270                // Method coursier/util/shaded/org/jsoup/select/StructuralEvaluator$PreviousSibling."<init>":(Lcoursier/util/shaded/org/jsoup/select/Evaluator;)V
       252: aastore
       253: invokespecial #267                // Method coursier/util/shaded/org/jsoup/select/CombiningEvaluator$And."<init>":([Lcoursier/util/shaded/org/jsoup/select/Evaluator;)V
       256: astore        4
       258: goto          354
       261: iload_1
       262: bipush        44
       264: if_icmpne     322
       267: aload         4
       269: instanceof    #22                 // class coursier/util/shaded/org/jsoup/select/CombiningEvaluator$Or
       272: ifeq          292
       275: aload         4
       277: checkcast     #22                 // class coursier/util/shaded/org/jsoup/select/CombiningEvaluator$Or
       280: astore        7
       282: aload         7
       284: aload         5
       286: invokevirtual #272                // Method coursier/util/shaded/org/jsoup/select/CombiningEvaluator$Or.add:(Lcoursier/util/shaded/org/jsoup/select/Evaluator;)V
       289: goto          315
       292: new           #22                 // class coursier/util/shaded/org/jsoup/select/CombiningEvaluator$Or
       295: dup
       296: invokespecial #273                // Method coursier/util/shaded/org/jsoup/select/CombiningEvaluator$Or."<init>":()V
       299: astore        7
       301: aload         7
       303: aload         4
       305: invokevirtual #272                // Method coursier/util/shaded/org/jsoup/select/CombiningEvaluator$Or.add:(Lcoursier/util/shaded/org/jsoup/select/Evaluator;)V
       308: aload         7
       310: aload         5
       312: invokevirtual #272                // Method coursier/util/shaded/org/jsoup/select/CombiningEvaluator$Or.add:(Lcoursier/util/shaded/org/jsoup/select/Evaluator;)V
       315: aload         7
       317: astore        4
       319: goto          354
       322: new           #7                  // class coursier/util/shaded/org/jsoup/select/Selector$SelectorParseException
       325: dup
       326: new           #275                // class java/lang/StringBuilder
       329: dup
       330: invokespecial #276                // Method java/lang/StringBuilder."<init>":()V
       333: ldc_w         #278                // String Unknown combinator:
       336: invokevirtual #282                // Method java/lang/StringBuilder.append:(Ljava/lang/String;)Ljava/lang/StringBuilder;
       339: iload_1
       340: invokevirtual #285                // Method java/lang/StringBuilder.append:(C)Ljava/lang/StringBuilder;
       343: invokevirtual #288                // Method java/lang/StringBuilder.toString:()Ljava/lang/String;
       346: iconst_0
       347: anewarray     #4                  // class java/lang/Object
       350: invokespecial #203                // Method coursier/util/shaded/org/jsoup/select/Selector$SelectorParseException."<init>":(Ljava/lang/String;[Ljava/lang/Object;)V
       353: athrow
       354: iload         6
       356: ifeq          371
       359: aload_3
       360: checkcast     #22                 // class coursier/util/shaded/org/jsoup/select/CombiningEvaluator$Or
       363: aload         4
       365: invokevirtual #291                // Method coursier/util/shaded/org/jsoup/select/CombiningEvaluator$Or.replaceRightMostEvaluator:(Lcoursier/util/shaded/org/jsoup/select/Evaluator;)V
       368: goto          374
       371: aload         4
       373: astore_3
       374: aload_0
       375: getfield      #168                // Field evals:Ljava/util/List;
       378: aload_3
       379: invokeinterface #223,  2          // InterfaceMethod java/util/List.add:(Ljava/lang/Object;)Z
       384: pop
       385: return
      StackMapTable: number_of_entries = 12
        frame_type = 255 /* full_frame */
          offset_delta = 81
          locals = [ class coursier/util/shaded/org/jsoup/select/QueryParser, int, class java/lang/String, top, top, class coursier/util/shaded/org/jsoup/select/Evaluator, int ]
          stack = []
        frame_type = 255 /* full_frame */
          offset_delta = 14
          locals = [ class coursier/util/shaded/org/jsoup/select/QueryParser, int, class java/lang/String, class coursier/util/shaded/org/jsoup/select/Evaluator, class coursier/util/shaded/org/jsoup/select/Evaluator, class coursier/util/shaded/org/jsoup/select/Evaluator, int ]
          stack = []
        frame_type = 47 /* same */
        frame_type = 38 /* same */
        frame_type = 38 /* same */
        frame_type = 38 /* same */
        frame_type = 30 /* same */
        frame_type = 252 /* append */
          offset_delta = 22
          locals = [ class coursier/util/shaded/org/jsoup/select/CombiningEvaluator$Or ]
        frame_type = 250 /* chop */
          offset_delta = 6
        frame_type = 31 /* same */
        frame_type = 16 /* same */
        frame_type = 2 /* same */
      LineNumberTable:
        line 85: 0
        line 86: 8
        line 90: 13
        line 91: 19
        line 93: 22
        line 94: 35
        line 96: 52
        line 97: 65
        line 98: 75
        line 102: 81
        line 104: 96
        line 107: 105
        line 108: 111
        line 109: 144
        line 110: 150
        line 111: 183
        line 112: 189
        line 113: 222
        line 114: 228
        line 115: 261
        line 117: 267
        line 118: 275
        line 119: 282
        line 121: 292
        line 122: 301
        line 123: 308
        line 125: 315
        line 126: 319
        line 128: 322
        line 130: 354
        line 131: 359
        line 132: 371
        line 133: 374
        line 134: 385
      LocalVariableTable:
        Start  Length  Slot  Name   Signature
           52      29     3 rootEval   Lcoursier/util/shaded/org/jsoup/select/Evaluator;
           51      30     4 currentEval   Lcoursier/util/shaded/org/jsoup/select/Evaluator;
          282      10     7    or   Lcoursier/util/shaded/org/jsoup/select/CombiningEvaluator$Or;
          301      18     7    or   Lcoursier/util/shaded/org/jsoup/select/CombiningEvaluator$Or;
            0     386     0  this   Lcoursier/util/shaded/org/jsoup/select/QueryParser;
            0     386     1 combinator   C
           13     373     2 subQuery   Ljava/lang/String;
           96     290     3 rootEval   Lcoursier/util/shaded/org/jsoup/select/Evaluator;
           95     291     4 currentEval   Lcoursier/util/shaded/org/jsoup/select/Evaluator;
           19     367     5 newEval   Lcoursier/util/shaded/org/jsoup/select/Evaluator;
           22     364     6 replaceRightMost   Z

  private java.lang.String consumeSubQuery();
    descriptor: ()Ljava/lang/String;
    flags: (0x0002) ACC_PRIVATE
    Code:
      stack=4, locals=2, args_size=1
         0: invokestatic  #306                // Method coursier/util/shaded/org/jsoup/internal/StringUtil.borrowBuilder:()Ljava/lang/StringBuilder;
         3: astore_1
         4: aload_0
         5: getfield      #187                // Field tq:Lcoursier/util/shaded/org/jsoup/parser/TokenQueue;
         8: invokevirtual #237                // Method coursier/util/shaded/org/jsoup/parser/TokenQueue.isEmpty:()Z
        11: ifne          133
        14: aload_0
        15: getfield      #187                // Field tq:Lcoursier/util/shaded/org/jsoup/parser/TokenQueue;
        18: ldc_w         #308                // String (
        21: invokevirtual #312                // Method coursier/util/shaded/org/jsoup/parser/TokenQueue.matches:(Ljava/lang/String;)Z
        24: ifeq          58
        27: aload_1
        28: ldc_w         #308                // String (
        31: invokevirtual #282                // Method java/lang/StringBuilder.append:(Ljava/lang/String;)Ljava/lang/StringBuilder;
        34: aload_0
        35: getfield      #187                // Field tq:Lcoursier/util/shaded/org/jsoup/parser/TokenQueue;
        38: bipush        40
        40: bipush        41
        42: invokevirtual #316                // Method coursier/util/shaded/org/jsoup/parser/TokenQueue.chompBalanced:(CC)Ljava/lang/String;
        45: invokevirtual #282                // Method java/lang/StringBuilder.append:(Ljava/lang/String;)Ljava/lang/StringBuilder;
        48: ldc_w         #318                // String )
        51: invokevirtual #282                // Method java/lang/StringBuilder.append:(Ljava/lang/String;)Ljava/lang/StringBuilder;
        54: pop
        55: goto          4
        58: aload_0
        59: getfield      #187                // Field tq:Lcoursier/util/shaded/org/jsoup/parser/TokenQueue;
        62: ldc_w         #320                // String [
        65: invokevirtual #312                // Method coursier/util/shaded/org/jsoup/parser/TokenQueue.matches:(Ljava/lang/String;)Z
        68: ifeq          102
        71: aload_1
        72: ldc_w         #320                // String [
        75: invokevirtual #282                // Method java/lang/StringBuilder.append:(Ljava/lang/String;)Ljava/lang/StringBuilder;
        78: aload_0
        79: getfield      #187                // Field tq:Lcoursier/util/shaded/org/jsoup/parser/TokenQueue;
        82: bipush        91
        84: bipush        93
        86: invokevirtual #316                // Method coursier/util/shaded/org/jsoup/parser/TokenQueue.chompBalanced:(CC)Ljava/lang/String;
        89: invokevirtual #282                // Method java/lang/StringBuilder.append:(Ljava/lang/String;)Ljava/lang/StringBuilder;
        92: ldc_w         #322                // String ]
        95: invokevirtual #282                // Method java/lang/StringBuilder.append:(Ljava/lang/String;)Ljava/lang/StringBuilder;
        98: pop
        99: goto          4
       102: aload_0
       103: getfield      #187                // Field tq:Lcoursier/util/shaded/org/jsoup/parser/TokenQueue;
       106: getstatic     #212                // Field combinators:[Ljava/lang/String;
       109: invokevirtual #216                // Method coursier/util/shaded/org/jsoup/parser/TokenQueue.matchesAny:([Ljava/lang/String;)Z
       112: ifeq          118
       115: goto          133
       118: aload_1
       119: aload_0
       120: getfield      #187                // Field tq:Lcoursier/util/shaded/org/jsoup/parser/TokenQueue;
       123: invokevirtual #227                // Method coursier/util/shaded/org/jsoup/parser/TokenQueue.consume:()C
       126: invokevirtual #285                // Method java/lang/StringBuilder.append:(C)Ljava/lang/StringBuilder;
       129: pop
       130: goto          4
       133: aload_1
       134: invokestatic  #326                // Method coursier/util/shaded/org/jsoup/internal/StringUtil.releaseBuilder:(Ljava/lang/StringBuilder;)Ljava/lang/String;
       137: areturn
      StackMapTable: number_of_entries = 5
        frame_type = 252 /* append */
          offset_delta = 4
          locals = [ class java/lang/StringBuilder ]
        frame_type = 53 /* same */
        frame_type = 43 /* same */
        frame_type = 15 /* same */
        frame_type = 14 /* same */
      LineNumberTable:
        line 137: 0
        line 138: 4
        line 139: 14
        line 140: 27
        line 141: 58
        line 142: 71
        line 143: 102
        line 144: 115
        line 146: 118
        line 148: 133
      LocalVariableTable:
        Start  Length  Slot  Name   Signature
            0     138     0  this   Lcoursier/util/shaded/org/jsoup/select/QueryParser;
            4     134     1    sq   Ljava/lang/StringBuilder;

  private void findElements();
    descriptor: ()V
    flags: (0x0002) ACC_PRIVATE
    Code:
      stack=7, locals=1, args_size=1
         0: aload_0
         1: getfield      #187                // Field tq:Lcoursier/util/shaded/org/jsoup/parser/TokenQueue;
         4: ldc_w         #330                // String #
         7: invokevirtual #333                // Method coursier/util/shaded/org/jsoup/parser/TokenQueue.matchChomp:(Ljava/lang/String;)Z
        10: ifeq          20
        13: aload_0
        14: invokespecial #336                // Method byId:()V
        17: goto          731
        20: aload_0
        21: getfield      #187                // Field tq:Lcoursier/util/shaded/org/jsoup/parser/TokenQueue;
        24: ldc_w         #338                // String .
        27: invokevirtual #333                // Method coursier/util/shaded/org/jsoup/parser/TokenQueue.matchChomp:(Ljava/lang/String;)Z
        30: ifeq          40
        33: aload_0
        34: invokespecial #341                // Method byClass:()V
        37: goto          731
        40: aload_0
        41: getfield      #187                // Field tq:Lcoursier/util/shaded/org/jsoup/parser/TokenQueue;
        44: invokevirtual #344                // Method coursier/util/shaded/org/jsoup/parser/TokenQueue.matchesWord:()Z
        47: ifne          63
        50: aload_0
        51: getfield      #187                // Field tq:Lcoursier/util/shaded/org/jsoup/parser/TokenQueue;
        54: ldc_w         #346                // String *|
        57: invokevirtual #312                // Method coursier/util/shaded/org/jsoup/parser/TokenQueue.matches:(Ljava/lang/String;)Z
        60: ifeq          70
        63: aload_0
        64: invokespecial #349                // Method byTag:()V
        67: goto          731
        70: aload_0
        71: getfield      #187                // Field tq:Lcoursier/util/shaded/org/jsoup/parser/TokenQueue;
        74: ldc_w         #320                // String [
        77: invokevirtual #312                // Method coursier/util/shaded/org/jsoup/parser/TokenQueue.matches:(Ljava/lang/String;)Z
        80: ifeq          90
        83: aload_0
        84: invokespecial #352                // Method byAttribute:()V
        87: goto          731
        90: aload_0
        91: getfield      #187                // Field tq:Lcoursier/util/shaded/org/jsoup/parser/TokenQueue;
        94: ldc_w         #354                // String *
        97: invokevirtual #333                // Method coursier/util/shaded/org/jsoup/parser/TokenQueue.matchChomp:(Ljava/lang/String;)Z
       100: ifeq          110
       103: aload_0
       104: invokespecial #357                // Method allElements:()V
       107: goto          731
       110: aload_0
       111: getfield      #187                // Field tq:Lcoursier/util/shaded/org/jsoup/parser/TokenQueue;
       114: ldc_w         #359                // String :lt(
       117: invokevirtual #333                // Method coursier/util/shaded/org/jsoup/parser/TokenQueue.matchChomp:(Ljava/lang/String;)Z
       120: ifeq          130
       123: aload_0
       124: invokespecial #362                // Method indexLessThan:()V
       127: goto          731
       130: aload_0
       131: getfield      #187                // Field tq:Lcoursier/util/shaded/org/jsoup/parser/TokenQueue;
       134: ldc_w         #364                // String :gt(
       137: invokevirtual #333                // Method coursier/util/shaded/org/jsoup/parser/TokenQueue.matchChomp:(Ljava/lang/String;)Z
       140: ifeq          150
       143: aload_0
       144: invokespecial #367                // Method indexGreaterThan:()V
       147: goto          731
       150: aload_0
       151: getfield      #187                // Field tq:Lcoursier/util/shaded/org/jsoup/parser/TokenQueue;
       154: ldc_w         #369                // String :eq(
       157: invokevirtual #333                // Method coursier/util/shaded/org/jsoup/parser/TokenQueue.matchChomp:(Ljava/lang/String;)Z
       160: ifeq          170
       163: aload_0
       164: invokespecial #372                // Method indexEquals:()V
       167: goto          731
       170: aload_0
       171: getfield      #187                // Field tq:Lcoursier/util/shaded/org/jsoup/parser/TokenQueue;
       174: ldc_w         #374                // String :has(
       177: invokevirtual #312                // Method coursier/util/shaded/org/jsoup/parser/TokenQueue.matches:(Ljava/lang/String;)Z
       180: ifeq          190
       183: aload_0
       184: invokespecial #377                // Method has:()V
       187: goto          731
       190: aload_0
       191: getfield      #187                // Field tq:Lcoursier/util/shaded/org/jsoup/parser/TokenQueue;
       194: ldc_w         #379                // String :contains(
       197: invokevirtual #312                // Method coursier/util/shaded/org/jsoup/parser/TokenQueue.matches:(Ljava/lang/String;)Z
       200: ifeq          211
       203: aload_0
       204: iconst_0
       205: invokespecial #383                // Method contains:(Z)V
       208: goto          731
       211: aload_0
       212: getfield      #187                // Field tq:Lcoursier/util/shaded/org/jsoup/parser/TokenQueue;
       215: ldc_w         #385                // String :containsOwn(
       218: invokevirtual #312                // Method coursier/util/shaded/org/jsoup/parser/TokenQueue.matches:(Ljava/lang/String;)Z
       221: ifeq          232
       224: aload_0
       225: iconst_1
       226: invokespecial #383                // Method contains:(Z)V
       229: goto          731
       232: aload_0
       233: getfield      #187                // Field tq:Lcoursier/util/shaded/org/jsoup/parser/TokenQueue;
       236: ldc_w         #387                // String :containsData(
       239: invokevirtual #312                // Method coursier/util/shaded/org/jsoup/parser/TokenQueue.matches:(Ljava/lang/String;)Z
       242: ifeq          252
       245: aload_0
       246: invokespecial #390                // Method containsData:()V
       249: goto          731
       252: aload_0
       253: getfield      #187                // Field tq:Lcoursier/util/shaded/org/jsoup/parser/TokenQueue;
       256: ldc_w         #392                // String :matches(
       259: invokevirtual #312                // Method coursier/util/shaded/org/jsoup/parser/TokenQueue.matches:(Ljava/lang/String;)Z
       262: ifeq          273
       265: aload_0
       266: iconst_0
       267: invokespecial #394                // Method matches:(Z)V
       270: goto          731
       273: aload_0
       274: getfield      #187                // Field tq:Lcoursier/util/shaded/org/jsoup/parser/TokenQueue;
       277: ldc_w         #396                // String :matchesOwn(
       280: invokevirtual #312                // Method coursier/util/shaded/org/jsoup/parser/TokenQueue.matches:(Ljava/lang/String;)Z
       283: ifeq          294
       286: aload_0
       287: iconst_1
       288: invokespecial #394                // Method matches:(Z)V
       291: goto          731
       294: aload_0
       295: getfield      #187                // Field tq:Lcoursier/util/shaded/org/jsoup/parser/TokenQueue;
       298: ldc_w         #398                // String :not(
       301: invokevirtual #312                // Method coursier/util/shaded/org/jsoup/parser/TokenQueue.matches:(Ljava/lang/String;)Z
       304: ifeq          314
       307: aload_0
       308: invokespecial #401                // Method not:()V
       311: goto          731
       314: aload_0
       315: getfield      #187                // Field tq:Lcoursier/util/shaded/org/jsoup/parser/TokenQueue;
       318: ldc_w         #403                // String :nth-child(
       321: invokevirtual #333                // Method coursier/util/shaded/org/jsoup/parser/TokenQueue.matchChomp:(Ljava/lang/String;)Z
       324: ifeq          336
       327: aload_0
       328: iconst_0
       329: iconst_0
       330: invokespecial #407                // Method cssNthChild:(ZZ)V
       333: goto          731
       336: aload_0
       337: getfield      #187                // Field tq:Lcoursier/util/shaded/org/jsoup/parser/TokenQueue;
       340: ldc_w         #409                // String :nth-last-child(
       343: invokevirtual #333                // Method coursier/util/shaded/org/jsoup/parser/TokenQueue.matchChomp:(Ljava/lang/String;)Z
       346: ifeq          358
       349: aload_0
       350: iconst_1
       351: iconst_0
       352: invokespecial #407                // Method cssNthChild:(ZZ)V
       355: goto          731
       358: aload_0
       359: getfield      #187                // Field tq:Lcoursier/util/shaded/org/jsoup/parser/TokenQueue;
       362: ldc_w         #411                // String :nth-of-type(
       365: invokevirtual #333                // Method coursier/util/shaded/org/jsoup/parser/TokenQueue.matchChomp:(Ljava/lang/String;)Z
       368: ifeq          380
       371: aload_0
       372: iconst_0
       373: iconst_1
       374: invokespecial #407                // Method cssNthChild:(ZZ)V
       377: goto          731
       380: aload_0
       381: getfield      #187                // Field tq:Lcoursier/util/shaded/org/jsoup/parser/TokenQueue;
       384: ldc_w         #413                // String :nth-last-of-type(
       387: invokevirtual #333                // Method coursier/util/shaded/org/jsoup/parser/TokenQueue.matchChomp:(Ljava/lang/String;)Z
       390: ifeq          402
       393: aload_0
       394: iconst_1
       395: iconst_1
       396: invokespecial #407                // Method cssNthChild:(ZZ)V
       399: goto          731
       402: aload_0
       403: getfield      #187                // Field tq:Lcoursier/util/shaded/org/jsoup/parser/TokenQueue;
       406: ldc_w         #415                // String :first-child
       409: invokevirtual #333                // Method coursier/util/shaded/org/jsoup/parser/TokenQueue.matchChomp:(Ljava/lang/String;)Z
       412: ifeq          435
       415: aload_0
       416: getfield      #168                // Field evals:Ljava/util/List;
       419: new           #37                 // class coursier/util/shaded/org/jsoup/select/Evaluator$IsFirstChild
       422: dup
       423: invokespecial #416                // Method coursier/util/shaded/org/jsoup/select/Evaluator$IsFirstChild."<init>":()V
       426: invokeinterface #223,  2          // InterfaceMethod java/util/List.add:(Ljava/lang/Object;)Z
       431: pop
       432: goto          731
       435: aload_0
       436: getfield      #187                // Field tq:Lcoursier/util/shaded/org/jsoup/parser/TokenQueue;
       439: ldc_w         #418                // String :last-child
       442: invokevirtual #333                // Method coursier/util/shaded/org/jsoup/parser/TokenQueue.matchChomp:(Ljava/lang/String;)Z
       445: ifeq          468
       448: aload_0
       449: getfield      #168                // Field evals:Ljava/util/List;
       452: new           #42                 // class coursier/util/shaded/org/jsoup/select/Evaluator$IsLastChild
       455: dup
       456: invokespecial #419                // Method coursier/util/shaded/org/jsoup/select/Evaluator$IsLastChild."<init>":()V
       459: invokeinterface #223,  2          // InterfaceMethod java/util/List.add:(Ljava/lang/Object;)Z
       464: pop
       465: goto          731
       468: aload_0
       469: getfield      #187                // Field tq:Lcoursier/util/shaded/org/jsoup/parser/TokenQueue;
       472: ldc_w         #421                // String :first-of-type
       475: invokevirtual #333                // Method coursier/util/shaded/org/jsoup/parser/TokenQueue.matchChomp:(Ljava/lang/String;)Z
       478: ifeq          501
       481: aload_0
       482: getfield      #168                // Field evals:Ljava/util/List;
       485: new           #45                 // class coursier/util/shaded/org/jsoup/select/Evaluator$IsFirstOfType
       488: dup
       489: invokespecial #422                // Method coursier/util/shaded/org/jsoup/select/Evaluator$IsFirstOfType."<init>":()V
       492: invokeinterface #223,  2          // InterfaceMethod java/util/List.add:(Ljava/lang/Object;)Z
       497: pop
       498: goto          731
       501: aload_0
       502: getfield      #187                // Field tq:Lcoursier/util/shaded/org/jsoup/parser/TokenQueue;
       505: ldc_w         #424                // String :last-of-type
       508: invokevirtual #333                // Method coursier/util/shaded/org/jsoup/parser/TokenQueue.matchChomp:(Ljava/lang/String;)Z
       511: ifeq          534
       514: aload_0
       515: getfield      #168                // Field evals:Ljava/util/List;
       518: new           #48                 // class coursier/util/shaded/org/jsoup/select/Evaluator$IsLastOfType
       521: dup
       522: invokespecial #425                // Method coursier/util/shaded/org/jsoup/select/Evaluator$IsLastOfType."<init>":()V
       525: invokeinterface #223,  2          // InterfaceMethod java/util/List.add:(Ljava/lang/Object;)Z
       530: pop
       531: goto          731
       534: aload_0
       535: getfield      #187                // Field tq:Lcoursier/util/shaded/org/jsoup/parser/TokenQueue;
       538: ldc_w         #427                // String :only-child
       541: invokevirtual #333                // Method coursier/util/shaded/org/jsoup/parser/TokenQueue.matchChomp:(Ljava/lang/String;)Z
       544: ifeq          567
       547: aload_0
       548: getfield      #168                // Field evals:Ljava/util/List;
       551: new           #51                 // class coursier/util/shaded/org/jsoup/select/Evaluator$IsOnlyChild
       554: dup
       555: invokespecial #428                // Method coursier/util/shaded/org/jsoup/select/Evaluator$IsOnlyChild."<init>":()V
       558: invokeinterface #223,  2          // InterfaceMethod java/util/List.add:(Ljava/lang/Object;)Z
       563: pop
       564: goto          731
       567: aload_0
       568: getfield      #187                // Field tq:Lcoursier/util/shaded/org/jsoup/parser/TokenQueue;
       571: ldc_w         #430                // String :only-of-type
       574: invokevirtual #333                // Method coursier/util/shaded/org/jsoup/parser/TokenQueue.matchChomp:(Ljava/lang/String;)Z
       577: ifeq          600
       580: aload_0
       581: getfield      #168                // Field evals:Ljava/util/List;
       584: new           #54                 // class coursier/util/shaded/org/jsoup/select/Evaluator$IsOnlyOfType
       587: dup
       588: invokespecial #431                // Method coursier/util/shaded/org/jsoup/select/Evaluator$IsOnlyOfType."<init>":()V
       591: invokeinterface #223,  2          // InterfaceMethod java/util/List.add:(Ljava/lang/Object;)Z
       596: pop
       597: goto          731
       600: aload_0
       601: getfield      #187                // Field tq:Lcoursier/util/shaded/org/jsoup/parser/TokenQueue;
       604: ldc_w         #433                // String :empty
       607: invokevirtual #333                // Method coursier/util/shaded/org/jsoup/parser/TokenQueue.matchChomp:(Ljava/lang/String;)Z
       610: ifeq          633
       613: aload_0
       614: getfield      #168                // Field evals:Ljava/util/List;
       617: new           #57                 // class coursier/util/shaded/org/jsoup/select/Evaluator$IsEmpty
       620: dup
       621: invokespecial #434                // Method coursier/util/shaded/org/jsoup/select/Evaluator$IsEmpty."<init>":()V
       624: invokeinterface #223,  2          // InterfaceMethod java/util/List.add:(Ljava/lang/Object;)Z
       629: pop
       630: goto          731
       633: aload_0
       634: getfield      #187                // Field tq:Lcoursier/util/shaded/org/jsoup/parser/TokenQueue;
       637: ldc_w         #436                // String :root
       640: invokevirtual #333                // Method coursier/util/shaded/org/jsoup/parser/TokenQueue.matchChomp:(Ljava/lang/String;)Z
       643: ifeq          666
       646: aload_0
       647: getfield      #168                // Field evals:Ljava/util/List;
       650: new           #60                 // class coursier/util/shaded/org/jsoup/select/Evaluator$IsRoot
       653: dup
       654: invokespecial #437                // Method coursier/util/shaded/org/jsoup/select/Evaluator$IsRoot."<init>":()V
       657: invokeinterface #223,  2          // InterfaceMethod java/util/List.add:(Ljava/lang/Object;)Z
       662: pop
       663: goto          731
       666: aload_0
       667: getfield      #187                // Field tq:Lcoursier/util/shaded/org/jsoup/parser/TokenQueue;
       670: ldc_w         #439                // String :matchText
       673: invokevirtual #333                // Method coursier/util/shaded/org/jsoup/parser/TokenQueue.matchChomp:(Ljava/lang/String;)Z
       676: ifeq          699
       679: aload_0
       680: getfield      #168                // Field evals:Ljava/util/List;
       683: new           #63                 // class coursier/util/shaded/org/jsoup/select/Evaluator$MatchText
       686: dup
       687: invokespecial #440                // Method coursier/util/shaded/org/jsoup/select/Evaluator$MatchText."<init>":()V
       690: invokeinterface #223,  2          // InterfaceMethod java/util/List.add:(Ljava/lang/Object;)Z
       695: pop
       696: goto          731
       699: new           #7                  // class coursier/util/shaded/org/jsoup/select/Selector$SelectorParseException
       702: dup
       703: ldc_w         #442                // String Could not parse query \'%s\': unexpected token at \'%s\'
       706: iconst_2
       707: anewarray     #4                  // class java/lang/Object
       710: dup
       711: iconst_0
       712: aload_0
       713: getfield      #181                // Field query:Ljava/lang/String;
       716: aastore
       717: dup
       718: iconst_1
       719: aload_0
       720: getfield      #187                // Field tq:Lcoursier/util/shaded/org/jsoup/parser/TokenQueue;
       723: invokevirtual #445                // Method coursier/util/shaded/org/jsoup/parser/TokenQueue.remainder:()Ljava/lang/String;
       726: aastore
       727: invokespecial #203                // Method coursier/util/shaded/org/jsoup/select/Selector$SelectorParseException."<init>":(Ljava/lang/String;[Ljava/lang/Object;)V
       730: athrow
       731: return
      StackMapTable: number_of_entries = 30
        frame_type = 20 /* same */
        frame_type = 19 /* same */
        frame_type = 22 /* same */
        frame_type = 6 /* same */
        frame_type = 19 /* same */
        frame_type = 19 /* same */
        frame_type = 19 /* same */
        frame_type = 19 /* same */
        frame_type = 19 /* same */
        frame_type = 19 /* same */
        frame_type = 20 /* same */
        frame_type = 20 /* same */
        frame_type = 19 /* same */
        frame_type = 20 /* same */
        frame_type = 20 /* same */
        frame_type = 19 /* same */
        frame_type = 21 /* same */
        frame_type = 21 /* same */
        frame_type = 21 /* same */
        frame_type = 21 /* same */
        frame_type = 32 /* same */
        frame_type = 32 /* same */
        frame_type = 32 /* same */
        frame_type = 32 /* same */
        frame_type = 32 /* same */
        frame_type = 32 /* same */
        frame_type = 32 /* same */
        frame_type = 32 /* same */
        frame_type = 32 /* same */
        frame_type = 31 /* same */
      LineNumberTable:
        line 152: 0
        line 153: 13
        line 154: 20
        line 155: 33
        line 156: 40
        line 157: 63
        line 158: 70
        line 159: 83
        line 160: 90
        line 161: 103
        line 162: 110
        line 163: 123
        line 164: 130
        line 165: 143
        line 166: 150
        line 167: 163
        line 168: 170
        line 169: 183
        line 170: 190
        line 171: 203
        line 172: 211
        line 173: 224
        line 174: 232
        line 175: 245
        line 176: 252
        line 177: 265
        line 178: 273
        line 179: 286
        line 180: 294
        line 181: 307
        line 182: 314
        line 183: 327
        line 184: 336
        line 185: 349
        line 186: 358
        line 187: 371
        line 188: 380
        line 189: 393
        line 190: 402
        line 191: 415
        line 192: 435
        line 193: 448
        line 194: 468
        line 195: 481
        line 196: 501
        line 197: 514
        line 198: 534
        line 199: 547
        line 200: 567
        line 201: 580
        line 202: 600
        line 203: 613
        line 204: 633
        line 205: 646
        line 206: 666
        line 207: 679
        line 209: 699
        line 211: 731
      LocalVariableTable:
        Start  Length  Slot  Name   Signature
            0     732     0  this   Lcoursier/util/shaded/org/jsoup/select/QueryParser;

  private void byId();
    descriptor: ()V
    flags: (0x0002) ACC_PRIVATE
    Code:
      stack=4, locals=2, args_size=1
         0: aload_0
         1: getfield      #187                // Field tq:Lcoursier/util/shaded/org/jsoup/parser/TokenQueue;
         4: invokevirtual #448                // Method coursier/util/shaded/org/jsoup/parser/TokenQueue.consumeCssIdentifier:()Ljava/lang/String;
         7: astore_1
         8: aload_1
         9: invokestatic  #173                // Method coursier/util/shaded/org/jsoup/helper/Validate.notEmpty:(Ljava/lang/String;)V
        12: aload_0
        13: getfield      #168                // Field evals:Ljava/util/List;
        16: new           #66                 // class coursier/util/shaded/org/jsoup/select/Evaluator$Id
        19: dup
        20: aload_1
        21: invokespecial #449                // Method coursier/util/shaded/org/jsoup/select/Evaluator$Id."<init>":(Ljava/lang/String;)V
        24: invokeinterface #223,  2          // InterfaceMethod java/util/List.add:(Ljava/lang/Object;)Z
        29: pop
        30: return
      LineNumberTable:
        line 214: 0
        line 215: 8
        line 216: 12
        line 217: 30
      LocalVariableTable:
        Start  Length  Slot  Name   Signature
            0      31     0  this   Lcoursier/util/shaded/org/jsoup/select/QueryParser;
            8      23     1    id   Ljava/lang/String;

  private void byClass();
    descriptor: ()V
    flags: (0x0002) ACC_PRIVATE
    Code:
      stack=4, locals=2, args_size=1
         0: aload_0
         1: getfield      #187                // Field tq:Lcoursier/util/shaded/org/jsoup/parser/TokenQueue;
         4: invokevirtual #448                // Method coursier/util/shaded/org/jsoup/parser/TokenQueue.consumeCssIdentifier:()Ljava/lang/String;
         7: astore_1
         8: aload_1
         9: invokestatic  #173                // Method coursier/util/shaded/org/jsoup/helper/Validate.notEmpty:(Ljava/lang/String;)V
        12: aload_0
        13: getfield      #168                // Field evals:Ljava/util/List;
        16: new           #69                 // class coursier/util/shaded/org/jsoup/select/Evaluator$Class
        19: dup
        20: aload_1
        21: invokevirtual #179                // Method java/lang/String.trim:()Ljava/lang/String;
        24: invokespecial #451                // Method coursier/util/shaded/org/jsoup/select/Evaluator$Class."<init>":(Ljava/lang/String;)V
        27: invokeinterface #223,  2          // InterfaceMethod java/util/List.add:(Ljava/lang/Object;)Z
        32: pop
        33: return
      LineNumberTable:
        line 220: 0
        line 221: 8
        line 222: 12
        line 223: 33
      LocalVariableTable:
        Start  Length  Slot  Name   Signature
            0      34     0  this   Lcoursier/util/shaded/org/jsoup/select/QueryParser;
            8      26     1 className   Ljava/lang/String;

  private void byTag();
    descriptor: ()V
    flags: (0x0002) ACC_PRIVATE
    Code:
      stack=11, locals=2, args_size=1
         0: aload_0
         1: getfield      #187                // Field tq:Lcoursier/util/shaded/org/jsoup/parser/TokenQueue;
         4: invokevirtual #455                // Method coursier/util/shaded/org/jsoup/parser/TokenQueue.consumeElementSelector:()Ljava/lang/String;
         7: invokestatic  #461                // Method coursier/util/shaded/org/jsoup/internal/Normalizer.normalize:(Ljava/lang/String;)Ljava/lang/String;
        10: astore_1
        11: aload_1
        12: invokestatic  #173                // Method coursier/util/shaded/org/jsoup/helper/Validate.notEmpty:(Ljava/lang/String;)V
        15: aload_1
        16: ldc_w         #346                // String *|
        19: invokevirtual #464                // Method java/lang/String.startsWith:(Ljava/lang/String;)Z
        22: ifeq          80
        25: aload_0
        26: getfield      #168                // Field evals:Ljava/util/List;
        29: new           #22                 // class coursier/util/shaded/org/jsoup/select/CombiningEvaluator$Or
        32: dup
        33: iconst_2
        34: anewarray     #39                 // class coursier/util/shaded/org/jsoup/select/Evaluator
        37: dup
        38: iconst_0
        39: new           #72                 // class coursier/util/shaded/org/jsoup/select/Evaluator$Tag
        42: dup
        43: aload_1
        44: invokespecial #465                // Method coursier/util/shaded/org/jsoup/select/Evaluator$Tag."<init>":(Ljava/lang/String;)V
        47: aastore
        48: dup
        49: iconst_1
        50: new           #75                 // class coursier/util/shaded/org/jsoup/select/Evaluator$TagEndsWith
        53: dup
        54: aload_1
        55: ldc_w         #346                // String *|
        58: ldc_w         #467                // String :
        61: invokevirtual #471                // Method java/lang/String.replace:(Ljava/lang/CharSequence;Ljava/lang/CharSequence;)Ljava/lang/String;
        64: invokespecial #472                // Method coursier/util/shaded/org/jsoup/select/Evaluator$TagEndsWith."<init>":(Ljava/lang/String;)V
        67: aastore
        68: invokespecial #473                // Method coursier/util/shaded/org/jsoup/select/CombiningEvaluator$Or."<init>":([Lcoursier/util/shaded/org/jsoup/select/Evaluator;)V
        71: invokeinterface #223,  2          // InterfaceMethod java/util/List.add:(Ljava/lang/Object;)Z
        76: pop
        77: goto          119
        80: aload_1
        81: ldc_w         #475                // String |
        84: invokevirtual #478                // Method java/lang/String.contains:(Ljava/lang/CharSequence;)Z
        87: ifeq          101
        90: aload_1
        91: ldc_w         #475                // String |
        94: ldc_w         #467                // String :
        97: invokevirtual #471                // Method java/lang/String.replace:(Ljava/lang/CharSequence;Ljava/lang/CharSequence;)Ljava/lang/String;
       100: astore_1
       101: aload_0
       102: getfield      #168                // Field evals:Ljava/util/List;
       105: new           #72                 // class coursier/util/shaded/org/jsoup/select/Evaluator$Tag
       108: dup
       109: aload_1
       110: invokespecial #465                // Method coursier/util/shaded/org/jsoup/select/Evaluator$Tag."<init>":(Ljava/lang/String;)V
       113: invokeinterface #223,  2          // InterfaceMethod java/util/List.add:(Ljava/lang/Object;)Z
       118: pop
       119: return
      StackMapTable: number_of_entries = 3
        frame_type = 252 /* append */
          offset_delta = 80
          locals = [ class java/lang/String ]
        frame_type = 20 /* same */
        frame_type = 17 /* same */
      LineNumberTable:
        line 229: 0
        line 230: 11
        line 233: 15
        line 234: 25
        line 237: 80
        line 238: 90
        line 240: 101
        line 242: 119
      LocalVariableTable:
        Start  Length  Slot  Name   Signature
            0     120     0  this   Lcoursier/util/shaded/org/jsoup/select/QueryParser;
           11     109     1 tagName   Ljava/lang/String;

  private void byAttribute();
    descriptor: ()V
    flags: (0x0002) ACC_PRIVATE
    Code:
      stack=7, locals=3, args_size=1
         0: new           #183                // class coursier/util/shaded/org/jsoup/parser/TokenQueue
         3: dup
         4: aload_0
         5: getfield      #187                // Field tq:Lcoursier/util/shaded/org/jsoup/parser/TokenQueue;
         8: bipush        91
        10: bipush        93
        12: invokevirtual #316                // Method coursier/util/shaded/org/jsoup/parser/TokenQueue.chompBalanced:(CC)Ljava/lang/String;
        15: invokespecial #185                // Method coursier/util/shaded/org/jsoup/parser/TokenQueue."<init>":(Ljava/lang/String;)V
        18: astore_1
        19: aload_1
        20: getstatic     #481                // Field AttributeEvals:[Ljava/lang/String;
        23: invokevirtual #485                // Method coursier/util/shaded/org/jsoup/parser/TokenQueue.consumeToAny:([Ljava/lang/String;)Ljava/lang/String;
        26: astore_2
        27: aload_2
        28: invokestatic  #173                // Method coursier/util/shaded/org/jsoup/helper/Validate.notEmpty:(Ljava/lang/String;)V
        31: aload_1
        32: invokevirtual #210                // Method coursier/util/shaded/org/jsoup/parser/TokenQueue.consumeWhitespace:()Z
        35: pop
        36: aload_1
        37: invokevirtual #237                // Method coursier/util/shaded/org/jsoup/parser/TokenQueue.isEmpty:()Z
        40: ifeq          99
        43: aload_2
        44: ldc_w         #487                // String ^
        47: invokevirtual #464                // Method java/lang/String.startsWith:(Ljava/lang/String;)Z
        50: ifeq          78
        53: aload_0
        54: getfield      #168                // Field evals:Ljava/util/List;
        57: new           #78                 // class coursier/util/shaded/org/jsoup/select/Evaluator$AttributeStarting
        60: dup
        61: aload_2
        62: iconst_1
        63: invokevirtual #491                // Method java/lang/String.substring:(I)Ljava/lang/String;
        66: invokespecial #492                // Method coursier/util/shaded/org/jsoup/select/Evaluator$AttributeStarting."<init>":(Ljava/lang/String;)V
        69: invokeinterface #223,  2          // InterfaceMethod java/util/List.add:(Ljava/lang/Object;)Z
        74: pop
        75: goto          341
        78: aload_0
        79: getfield      #168                // Field evals:Ljava/util/List;
        82: new           #81                 // class coursier/util/shaded/org/jsoup/select/Evaluator$Attribute
        85: dup
        86: aload_2
        87: invokespecial #493                // Method coursier/util/shaded/org/jsoup/select/Evaluator$Attribute."<init>":(Ljava/lang/String;)V
        90: invokeinterface #223,  2          // InterfaceMethod java/util/List.add:(Ljava/lang/Object;)Z
        95: pop
        96: goto          341
        99: aload_1
       100: ldc_w         #495                // String =
       103: invokevirtual #333                // Method coursier/util/shaded/org/jsoup/parser/TokenQueue.matchChomp:(Ljava/lang/String;)Z
       106: ifeq          134
       109: aload_0
       110: getfield      #168                // Field evals:Ljava/util/List;
       113: new           #84                 // class coursier/util/shaded/org/jsoup/select/Evaluator$AttributeWithValue
       116: dup
       117: aload_2
       118: aload_1
       119: invokevirtual #445                // Method coursier/util/shaded/org/jsoup/parser/TokenQueue.remainder:()Ljava/lang/String;
       122: invokespecial #498                // Method coursier/util/shaded/org/jsoup/select/Evaluator$AttributeWithValue."<init>":(Ljava/lang/String;Ljava/lang/String;)V
       125: invokeinterface #223,  2          // InterfaceMethod java/util/List.add:(Ljava/lang/Object;)Z
       130: pop
       131: goto          341
       134: aload_1
       135: ldc_w         #500                // String !=
       138: invokevirtual #333                // Method coursier/util/shaded/org/jsoup/parser/TokenQueue.matchChomp:(Ljava/lang/String;)Z
       141: ifeq          169
       144: aload_0
       145: getfield      #168                // Field evals:Ljava/util/List;
       148: new           #87                 // class coursier/util/shaded/org/jsoup/select/Evaluator$AttributeWithValueNot
       151: dup
       152: aload_2
       153: aload_1
       154: invokevirtual #445                // Method coursier/util/shaded/org/jsoup/parser/TokenQueue.remainder:()Ljava/lang/String;
       157: invokespecial #501                // Method coursier/util/shaded/org/jsoup/select/Evaluator$AttributeWithValueNot."<init>":(Ljava/lang/String;Ljava/lang/String;)V
       160: invokeinterface #223,  2          // InterfaceMethod java/util/List.add:(Ljava/lang/Object;)Z
       165: pop
       166: goto          341
       169: aload_1
       170: ldc_w         #503                // String ^=
       173: invokevirtual #333                // Method coursier/util/shaded/org/jsoup/parser/TokenQueue.matchChomp:(Ljava/lang/String;)Z
       176: ifeq          204
       179: aload_0
       180: getfield      #168                // Field evals:Ljava/util/List;
       183: new           #90                 // class coursier/util/shaded/org/jsoup/select/Evaluator$AttributeWithValueStarting
       186: dup
       187: aload_2
       188: aload_1
       189: invokevirtual #445                // Method coursier/util/shaded/org/jsoup/parser/TokenQueue.remainder:()Ljava/lang/String;
       192: invokespecial #504                // Method coursier/util/shaded/org/jsoup/select/Evaluator$AttributeWithValueStarting."<init>":(Ljava/lang/String;Ljava/lang/String;)V
       195: invokeinterface #223,  2          // InterfaceMethod java/util/List.add:(Ljava/lang/Object;)Z
       200: pop
       201: goto          341
       204: aload_1
       205: ldc_w         #506                // String $=
       208: invokevirtual #333                // Method coursier/util/shaded/org/jsoup/parser/TokenQueue.matchChomp:(Ljava/lang/String;)Z
       211: ifeq          239
       214: aload_0
       215: getfield      #168                // Field evals:Ljava/util/List;
       218: new           #93                 // class coursier/util/shaded/org/jsoup/select/Evaluator$AttributeWithValueEnding
       221: dup
       222: aload_2
       223: aload_1
       224: invokevirtual #445                // Method coursier/util/shaded/org/jsoup/parser/TokenQueue.remainder:()Ljava/lang/String;
       227: invokespecial #507                // Method coursier/util/shaded/org/jsoup/select/Evaluator$AttributeWithValueEnding."<init>":(Ljava/lang/String;Ljava/lang/String;)V
       230: invokeinterface #223,  2          // InterfaceMethod java/util/List.add:(Ljava/lang/Object;)Z
       235: pop
       236: goto          341
       239: aload_1
       240: ldc_w         #509                // String *=
       243: invokevirtual #333                // Method coursier/util/shaded/org/jsoup/parser/TokenQueue.matchChomp:(Ljava/lang/String;)Z
       246: ifeq          274
       249: aload_0
       250: getfield      #168                // Field evals:Ljava/util/List;
       253: new           #96                 // class coursier/util/shaded/org/jsoup/select/Evaluator$AttributeWithValueContaining
       256: dup
       257: aload_2
       258: aload_1
       259: invokevirtual #445                // Method coursier/util/shaded/org/jsoup/parser/TokenQueue.remainder:()Ljava/lang/String;
       262: invokespecial #510                // Method coursier/util/shaded/org/jsoup/select/Evaluator$AttributeWithValueContaining."<init>":(Ljava/lang/String;Ljava/lang/String;)V
       265: invokeinterface #223,  2          // InterfaceMethod java/util/List.add:(Ljava/lang/Object;)Z
       270: pop
       271: goto          341
       274: aload_1
       275: ldc_w         #512                // String ~=
       278: invokevirtual #333                // Method coursier/util/shaded/org/jsoup/parser/TokenQueue.matchChomp:(Ljava/lang/String;)Z
       281: ifeq          312
       284: aload_0
       285: getfield      #168                // Field evals:Ljava/util/List;
       288: new           #99                 // class coursier/util/shaded/org/jsoup/select/Evaluator$AttributeWithValueMatching
       291: dup
       292: aload_2
       293: aload_1
       294: invokevirtual #445                // Method coursier/util/shaded/org/jsoup/parser/TokenQueue.remainder:()Ljava/lang/String;
       297: invokestatic  #518                // Method java/util/regex/Pattern.compile:(Ljava/lang/String;)Ljava/util/regex/Pattern;
       300: invokespecial #521                // Method coursier/util/shaded/org/jsoup/select/Evaluator$AttributeWithValueMatching."<init>":(Ljava/lang/String;Ljava/util/regex/Pattern;)V
       303: invokeinterface #223,  2          // InterfaceMethod java/util/List.add:(Ljava/lang/Object;)Z
       308: pop
       309: goto          341
       312: new           #7                  // class coursier/util/shaded/org/jsoup/select/Selector$SelectorParseException
       315: dup
       316: ldc_w         #523                // String Could not parse attribute query \'%s\': unexpected token at \'%s\'
       319: iconst_2
       320: anewarray     #4                  // class java/lang/Object
       323: dup
       324: iconst_0
       325: aload_0
       326: getfield      #181                // Field query:Ljava/lang/String;
       329: aastore
       330: dup
       331: iconst_1
       332: aload_1
       333: invokevirtual #445                // Method coursier/util/shaded/org/jsoup/parser/TokenQueue.remainder:()Ljava/lang/String;
       336: aastore
       337: invokespecial #203                // Method coursier/util/shaded/org/jsoup/select/Selector$SelectorParseException."<init>":(Ljava/lang/String;[Ljava/lang/Object;)V
       340: athrow
       341: return
      StackMapTable: number_of_entries = 9
        frame_type = 253 /* append */
          offset_delta = 78
          locals = [ class coursier/util/shaded/org/jsoup/parser/TokenQueue, class java/lang/String ]
        frame_type = 20 /* same */
        frame_type = 34 /* same */
        frame_type = 34 /* same */
        frame_type = 34 /* same */
        frame_type = 34 /* same */
        frame_type = 34 /* same */
        frame_type = 37 /* same */
        frame_type = 28 /* same */
      LineNumberTable:
        line 245: 0
        line 246: 19
        line 247: 27
        line 248: 31
        line 250: 36
        line 251: 43
        line 252: 53
        line 254: 78
        line 256: 99
        line 257: 109
        line 259: 134
        line 260: 144
        line 262: 169
        line 263: 179
        line 265: 204
        line 266: 214
        line 268: 239
        line 269: 249
        line 271: 274
        line 272: 284
        line 274: 312
        line 276: 341
      LocalVariableTable:
        Start  Length  Slot  Name   Signature
            0     342     0  this   Lcoursier/util/shaded/org/jsoup/select/QueryParser;
           19     323     1    cq   Lcoursier/util/shaded/org/jsoup/parser/TokenQueue;
           27     315     2   key   Ljava/lang/String;

  private void allElements();
    descriptor: ()V
    flags: (0x0002) ACC_PRIVATE
    Code:
      stack=3, locals=1, args_size=1
         0: aload_0
         1: getfield      #168                // Field evals:Ljava/util/List;
         4: new           #102                // class coursier/util/shaded/org/jsoup/select/Evaluator$AllElements
         7: dup
         8: invokespecial #526                // Method coursier/util/shaded/org/jsoup/select/Evaluator$AllElements."<init>":()V
        11: invokeinterface #223,  2          // InterfaceMethod java/util/List.add:(Ljava/lang/Object;)Z
        16: pop
        17: return
      LineNumberTable:
        line 279: 0
        line 280: 17
      LocalVariableTable:
        Start  Length  Slot  Name   Signature
            0      18     0  this   Lcoursier/util/shaded/org/jsoup/select/QueryParser;

  private void indexLessThan();
    descriptor: ()V
    flags: (0x0002) ACC_PRIVATE
    Code:
      stack=4, locals=1, args_size=1
         0: aload_0
         1: getfield      #168                // Field evals:Ljava/util/List;
         4: new           #105                // class coursier/util/shaded/org/jsoup/select/Evaluator$IndexLessThan
         7: dup
         8: aload_0
         9: invokespecial #529                // Method consumeIndex:()I
        12: invokespecial #532                // Method coursier/util/shaded/org/jsoup/select/Evaluator$IndexLessThan."<init>":(I)V
        15: invokeinterface #223,  2          // InterfaceMethod java/util/List.add:(Ljava/lang/Object;)Z
        20: pop
        21: return
      LineNumberTable:
        line 284: 0
        line 285: 21
      LocalVariableTable:
        Start  Length  Slot  Name   Signature
            0      22     0  this   Lcoursier/util/shaded/org/jsoup/select/QueryParser;

  private void indexGreaterThan();
    descriptor: ()V
    flags: (0x0002) ACC_PRIVATE
    Code:
      stack=4, locals=1, args_size=1
         0: aload_0
         1: getfield      #168                // Field evals:Ljava/util/List;
         4: new           #108                // class coursier/util/shaded/org/jsoup/select/Evaluator$IndexGreaterThan
         7: dup
         8: aload_0
         9: invokespecial #529                // Method consumeIndex:()I
        12: invokespecial #533                // Method coursier/util/shaded/org/jsoup/select/Evaluator$IndexGreaterThan."<init>":(I)V
        15: invokeinterface #223,  2          // InterfaceMethod java/util/List.add:(Ljava/lang/Object;)Z
        20: pop
        21: return
      LineNumberTable:
        line 288: 0
        line 289: 21
      LocalVariableTable:
        Start  Length  Slot  Name   Signature
            0      22     0  this   Lcoursier/util/shaded/org/jsoup/select/QueryParser;

  private void indexEquals();
    descriptor: ()V
    flags: (0x0002) ACC_PRIVATE
    Code:
      stack=4, locals=1, args_size=1
         0: aload_0
         1: getfield      #168                // Field evals:Ljava/util/List;
         4: new           #111                // class coursier/util/shaded/org/jsoup/select/Evaluator$IndexEquals
         7: dup
         8: aload_0
         9: invokespecial #529                // Method consumeIndex:()I
        12: invokespecial #534                // Method coursier/util/shaded/org/jsoup/select/Evaluator$IndexEquals."<init>":(I)V
        15: invokeinterface #223,  2          // InterfaceMethod java/util/List.add:(Ljava/lang/Object;)Z
        20: pop
        21: return
      LineNumberTable:
        line 292: 0
        line 293: 21
      LocalVariableTable:
        Start  Length  Slot  Name   Signature
            0      22     0  this   Lcoursier/util/shaded/org/jsoup/select/QueryParser;

  private void cssNthChild(boolean, boolean);
    descriptor: (ZZ)V
    flags: (0x0002) ACC_PRIVATE
    Code:
      stack=7, locals=8, args_size=3
         0: aload_0
         1: getfield      #187                // Field tq:Lcoursier/util/shaded/org/jsoup/parser/TokenQueue;
         4: ldc_w         #318                // String )
         7: invokevirtual #537                // Method coursier/util/shaded/org/jsoup/parser/TokenQueue.chompTo:(Ljava/lang/String;)Ljava/lang/String;
        10: invokestatic  #461                // Method coursier/util/shaded/org/jsoup/internal/Normalizer.normalize:(Ljava/lang/String;)Ljava/lang/String;
        13: astore_3
        14: getstatic     #539                // Field NTH_AB:Ljava/util/regex/Pattern;
        17: aload_3
        18: invokevirtual #543                // Method java/util/regex/Pattern.matcher:(Ljava/lang/CharSequence;)Ljava/util/regex/Matcher;
        21: astore        4
        23: getstatic     #545                // Field NTH_B:Ljava/util/regex/Pattern;
        26: aload_3
        27: invokevirtual #543                // Method java/util/regex/Pattern.matcher:(Ljava/lang/CharSequence;)Ljava/util/regex/Matcher;
        30: astore        5
        32: ldc_w         #547                // String odd
        35: aload_3
        36: invokevirtual #550                // Method java/lang/String.equals:(Ljava/lang/Object;)Z
        39: ifeq          51
        42: iconst_2
        43: istore        6
        45: iconst_1
        46: istore        7
        48: goto          199
        51: ldc_w         #554                // String even
        54: aload_3
        55: invokevirtual #550                // Method java/lang/String.equals:(Ljava/lang/Object;)Z
        58: ifeq          70
        61: iconst_2
        62: istore        6
        64: iconst_0
        65: istore        7
        67: goto          199
        70: aload         4
        72: invokevirtual #556                // Method java/util/regex/Matcher.matches:()Z
        75: ifeq          147
        78: aload         4
        80: iconst_3
        81: invokevirtual #559                // Method java/util/regex/Matcher.group:(I)Ljava/lang/String;
        84: ifnull        108
        87: aload         4
        89: iconst_1
        90: invokevirtual #559                // Method java/util/regex/Matcher.group:(I)Ljava/lang/String;
        93: ldc_w         #561                // String ^\\+
        96: ldc_w         #563                // String
        99: invokevirtual #567                // Method java/lang/String.replaceFirst:(Ljava/lang/String;Ljava/lang/String;)Ljava/lang/String;
       102: invokestatic  #573                // Method java/lang/Integer.parseInt:(Ljava/lang/String;)I
       105: goto          109
       108: iconst_1
       109: istore        6
       111: aload         4
       113: iconst_4
       114: invokevirtual #559                // Method java/util/regex/Matcher.group:(I)Ljava/lang/String;
       117: ifnull        141
       120: aload         4
       122: iconst_4
       123: invokevirtual #559                // Method java/util/regex/Matcher.group:(I)Ljava/lang/String;
       126: ldc_w         #561                // String ^\\+
       129: ldc_w         #563                // String
       132: invokevirtual #567                // Method java/lang/String.replaceFirst:(Ljava/lang/String;Ljava/lang/String;)Ljava/lang/String;
       135: invokestatic  #573                // Method java/lang/Integer.parseInt:(Ljava/lang/String;)I
       138: goto          142
       141: iconst_0
       142: istore        7
       144: goto          199
       147: aload         5
       149: invokevirtual #556                // Method java/util/regex/Matcher.matches:()Z
       152: ifeq          180
       155: iconst_0
       156: istore        6
       158: aload         5
       160: invokevirtual #575                // Method java/util/regex/Matcher.group:()Ljava/lang/String;
       163: ldc_w         #561                // String ^\\+
       166: ldc_w         #563                // String
       169: invokevirtual #567                // Method java/lang/String.replaceFirst:(Ljava/lang/String;Ljava/lang/String;)Ljava/lang/String;
       172: invokestatic  #573                // Method java/lang/Integer.parseInt:(Ljava/lang/String;)I
       175: istore        7
       177: goto          199
       180: new           #7                  // class coursier/util/shaded/org/jsoup/select/Selector$SelectorParseException
       183: dup
       184: ldc_w         #577                // String Could not parse nth-index \'%s\': unexpected format
       187: iconst_1
       188: anewarray     #4                  // class java/lang/Object
       191: dup
       192: iconst_0
       193: aload_3
       194: aastore
       195: invokespecial #203                // Method coursier/util/shaded/org/jsoup/select/Selector$SelectorParseException."<init>":(Ljava/lang/String;[Ljava/lang/Object;)V
       198: athrow
       199: iload_2
       200: ifeq          255
       203: iload_1
       204: ifeq          231
       207: aload_0
       208: getfield      #168                // Field evals:Ljava/util/List;
       211: new           #114                // class coursier/util/shaded/org/jsoup/select/Evaluator$IsNthLastOfType
       214: dup
       215: iload         6
       217: iload         7
       219: invokespecial #580                // Method coursier/util/shaded/org/jsoup/select/Evaluator$IsNthLastOfType."<init>":(II)V
       222: invokeinterface #223,  2          // InterfaceMethod java/util/List.add:(Ljava/lang/Object;)Z
       227: pop
       228: goto          304
       231: aload_0
       232: getfield      #168                // Field evals:Ljava/util/List;
       235: new           #117                // class coursier/util/shaded/org/jsoup/select/Evaluator$IsNthOfType
       238: dup
       239: iload         6
       241: iload         7
       243: invokespecial #581                // Method coursier/util/shaded/org/jsoup/select/Evaluator$IsNthOfType."<init>":(II)V
       246: invokeinterface #223,  2          // InterfaceMethod java/util/List.add:(Ljava/lang/Object;)Z
       251: pop
       252: goto          304
       255: iload_1
       256: ifeq          283
       259: aload_0
       260: getfield      #168                // Field evals:Ljava/util/List;
       263: new           #120                // class coursier/util/shaded/org/jsoup/select/Evaluator$IsNthLastChild
       266: dup
       267: iload         6
       269: iload         7
       271: invokespecial #582                // Method coursier/util/shaded/org/jsoup/select/Evaluator$IsNthLastChild."<init>":(II)V
       274: invokeinterface #223,  2          // InterfaceMethod java/util/List.add:(Ljava/lang/Object;)Z
       279: pop
       280: goto          304
       283: aload_0
       284: getfield      #168                // Field evals:Ljava/util/List;
       287: new           #123                // class coursier/util/shaded/org/jsoup/select/Evaluator$IsNthChild
       290: dup
       291: iload         6
       293: iload         7
       295: invokespecial #583                // Method coursier/util/shaded/org/jsoup/select/Evaluator$IsNthChild."<init>":(II)V
       298: invokeinterface #223,  2          // InterfaceMethod java/util/List.add:(Ljava/lang/Object;)Z
       303: pop
       304: return
      StackMapTable: number_of_entries = 13
        frame_type = 254 /* append */
          offset_delta = 51
          locals = [ class java/lang/String, class java/util/regex/Matcher, class java/util/regex/Matcher ]
        frame_type = 18 /* same */
        frame_type = 37 /* same */
        frame_type = 64 /* same_locals_1_stack_item */
          stack = [ int ]
        frame_type = 252 /* append */
          offset_delta = 31
          locals = [ int ]
        frame_type = 64 /* same_locals_1_stack_item */
          stack = [ int ]
        frame_type = 250 /* chop */
          offset_delta = 4
        frame_type = 32 /* same */
        frame_type = 253 /* append */
          offset_delta = 18
          locals = [ int, int ]
        frame_type = 31 /* same */
        frame_type = 23 /* same */
        frame_type = 27 /* same */
        frame_type = 20 /* same */
      LineNumberTable:
        line 300: 0
        line 301: 14
        line 302: 23
        line 304: 32
        line 305: 42
        line 306: 45
        line 307: 51
        line 308: 61
        line 309: 64
        line 310: 70
        line 311: 78
        line 312: 111
        line 313: 147
        line 314: 155
        line 315: 158
        line 317: 180
        line 319: 199
        line 320: 203
        line 321: 207
        line 323: 231
        line 325: 255
        line 326: 259
        line 328: 283
        line 330: 304
      LocalVariableTable:
        Start  Length  Slot  Name   Signature
           45       6     6     a   I
           48       3     7     b   I
           64       6     6     a   I
           67       3     7     b   I
          111      36     6     a   I
          144       3     7     b   I
          158      22     6     a   I
          177       3     7     b   I
            0     305     0  this   Lcoursier/util/shaded/org/jsoup/select/QueryParser;
            0     305     1 backwards   Z
            0     305     2 ofType   Z
           14     291     3  argS   Ljava/lang/String;
           23     282     4   mAB   Ljava/util/regex/Matcher;
           32     273     5    mB   Ljava/util/regex/Matcher;
          199     106     6     a   I
          199     106     7     b   I

  private int consumeIndex();
    descriptor: ()I
    flags: (0x0002) ACC_PRIVATE
    Code:
      stack=2, locals=2, args_size=1
         0: aload_0
         1: getfield      #187                // Field tq:Lcoursier/util/shaded/org/jsoup/parser/TokenQueue;
         4: ldc_w         #318                // String )
         7: invokevirtual #537                // Method coursier/util/shaded/org/jsoup/parser/TokenQueue.chompTo:(Ljava/lang/String;)Ljava/lang/String;
        10: invokevirtual #179                // Method java/lang/String.trim:()Ljava/lang/String;
        13: astore_1
        14: aload_1
        15: invokestatic  #595                // Method coursier/util/shaded/org/jsoup/internal/StringUtil.isNumeric:(Ljava/lang/String;)Z
        18: ldc_w         #597                // String Index must be numeric
        21: invokestatic  #601                // Method coursier/util/shaded/org/jsoup/helper/Validate.isTrue:(ZLjava/lang/String;)V
        24: aload_1
        25: invokestatic  #573                // Method java/lang/Integer.parseInt:(Ljava/lang/String;)I
        28: ireturn
      LineNumberTable:
        line 333: 0
        line 334: 14
        line 335: 24
      LocalVariableTable:
        Start  Length  Slot  Name   Signature
            0      29     0  this   Lcoursier/util/shaded/org/jsoup/select/QueryParser;
           14      15     1 indexS   Ljava/lang/String;

  private void has();
    descriptor: ()V
    flags: (0x0002) ACC_PRIVATE
    Code:
      stack=4, locals=2, args_size=1
         0: aload_0
         1: getfield      #187                // Field tq:Lcoursier/util/shaded/org/jsoup/parser/TokenQueue;
         4: ldc_w         #604                // String :has
         7: invokevirtual #606                // Method coursier/util/shaded/org/jsoup/parser/TokenQueue.consume:(Ljava/lang/String;)V
        10: aload_0
        11: getfield      #187                // Field tq:Lcoursier/util/shaded/org/jsoup/parser/TokenQueue;
        14: bipush        40
        16: bipush        41
        18: invokevirtual #316                // Method coursier/util/shaded/org/jsoup/parser/TokenQueue.chompBalanced:(CC)Ljava/lang/String;
        21: astore_1
        22: aload_1
        23: ldc_w         #608                // String :has(el) subselect must not be empty
        26: invokestatic  #610                // Method coursier/util/shaded/org/jsoup/helper/Validate.notEmpty:(Ljava/lang/String;Ljava/lang/String;)V
        29: aload_0
        30: getfield      #168                // Field evals:Ljava/util/List;
        33: new           #126                // class coursier/util/shaded/org/jsoup/select/StructuralEvaluator$Has
        36: dup
        37: aload_1
        38: invokestatic  #255                // Method parse:(Ljava/lang/String;)Lcoursier/util/shaded/org/jsoup/select/Evaluator;
        41: invokespecial #611                // Method coursier/util/shaded/org/jsoup/select/StructuralEvaluator$Has."<init>":(Lcoursier/util/shaded/org/jsoup/select/Evaluator;)V
        44: invokeinterface #223,  2          // InterfaceMethod java/util/List.add:(Ljava/lang/Object;)Z
        49: pop
        50: return
      LineNumberTable:
        line 340: 0
        line 341: 10
        line 342: 22
        line 343: 29
        line 344: 50
      LocalVariableTable:
        Start  Length  Slot  Name   Signature
            0      51     0  this   Lcoursier/util/shaded/org/jsoup/select/QueryParser;
           22      29     1 subQuery   Ljava/lang/String;

  private void contains(boolean);
    descriptor: (Z)V
    flags: (0x0002) ACC_PRIVATE
    Code:
      stack=4, locals=3, args_size=2
         0: aload_0
         1: getfield      #187                // Field tq:Lcoursier/util/shaded/org/jsoup/parser/TokenQueue;
         4: iload_1
         5: ifeq          14
         8: ldc_w         #613                // String :containsOwn
        11: goto          17
        14: ldc_w         #615                // String :contains
        17: invokevirtual #606                // Method coursier/util/shaded/org/jsoup/parser/TokenQueue.consume:(Ljava/lang/String;)V
        20: aload_0
        21: getfield      #187                // Field tq:Lcoursier/util/shaded/org/jsoup/parser/TokenQueue;
        24: bipush        40
        26: bipush        41
        28: invokevirtual #316                // Method coursier/util/shaded/org/jsoup/parser/TokenQueue.chompBalanced:(CC)Ljava/lang/String;
        31: invokestatic  #618                // Method coursier/util/shaded/org/jsoup/parser/TokenQueue.unescape:(Ljava/lang/String;)Ljava/lang/String;
        34: astore_2
        35: aload_2
        36: ldc_w         #620                // String :contains(text) query must not be empty
        39: invokestatic  #610                // Method coursier/util/shaded/org/jsoup/helper/Validate.notEmpty:(Ljava/lang/String;Ljava/lang/String;)V
        42: iload_1
        43: ifeq          67
        46: aload_0
        47: getfield      #168                // Field evals:Ljava/util/List;
        50: new           #129                // class coursier/util/shaded/org/jsoup/select/Evaluator$ContainsOwnText
        53: dup
        54: aload_2
        55: invokespecial #621                // Method coursier/util/shaded/org/jsoup/select/Evaluator$ContainsOwnText."<init>":(Ljava/lang/String;)V
        58: invokeinterface #223,  2          // InterfaceMethod java/util/List.add:(Ljava/lang/Object;)Z
        63: pop
        64: goto          85
        67: aload_0
        68: getfield      #168                // Field evals:Ljava/util/List;
        71: new           #132                // class coursier/util/shaded/org/jsoup/select/Evaluator$ContainsText
        74: dup
        75: aload_2
        76: invokespecial #622                // Method coursier/util/shaded/org/jsoup/select/Evaluator$ContainsText."<init>":(Ljava/lang/String;)V
        79: invokeinterface #223,  2          // InterfaceMethod java/util/List.add:(Ljava/lang/Object;)Z
        84: pop
        85: return
      StackMapTable: number_of_entries = 4
        frame_type = 78 /* same_locals_1_stack_item */
          stack = [ class coursier/util/shaded/org/jsoup/parser/TokenQueue ]
        frame_type = 255 /* full_frame */
          offset_delta = 2
          locals = [ class coursier/util/shaded/org/jsoup/select/QueryParser, int ]
          stack = [ class coursier/util/shaded/org/jsoup/parser/TokenQueue, class java/lang/String ]
        frame_type = 252 /* append */
          offset_delta = 49
          locals = [ class java/lang/String ]
        frame_type = 17 /* same */
      LineNumberTable:
        line 348: 0
        line 349: 20
        line 350: 35
        line 351: 42
        line 352: 46
        line 354: 67
        line 355: 85
      LocalVariableTable:
        Start  Length  Slot  Name   Signature
            0      86     0  this   Lcoursier/util/shaded/org/jsoup/select/QueryParser;
            0      86     1   own   Z
           35      51     2 searchText   Ljava/lang/String;

  private void containsData();
    descriptor: ()V
    flags: (0x0002) ACC_PRIVATE
    Code:
      stack=4, locals=2, args_size=1
         0: aload_0
         1: getfield      #187                // Field tq:Lcoursier/util/shaded/org/jsoup/parser/TokenQueue;
         4: ldc_w         #626                // String :containsData
         7: invokevirtual #606                // Method coursier/util/shaded/org/jsoup/parser/TokenQueue.consume:(Ljava/lang/String;)V
        10: aload_0
        11: getfield      #187                // Field tq:Lcoursier/util/shaded/org/jsoup/parser/TokenQueue;
        14: bipush        40
        16: bipush        41
        18: invokevirtual #316                // Method coursier/util/shaded/org/jsoup/parser/TokenQueue.chompBalanced:(CC)Ljava/lang/String;
        21: invokestatic  #618                // Method coursier/util/shaded/org/jsoup/parser/TokenQueue.unescape:(Ljava/lang/String;)Ljava/lang/String;
        24: astore_1
        25: aload_1
        26: ldc_w         #628                // String :containsData(text) query must not be empty
        29: invokestatic  #610                // Method coursier/util/shaded/org/jsoup/helper/Validate.notEmpty:(Ljava/lang/String;Ljava/lang/String;)V
        32: aload_0
        33: getfield      #168                // Field evals:Ljava/util/List;
        36: new           #135                // class coursier/util/shaded/org/jsoup/select/Evaluator$ContainsData
        39: dup
        40: aload_1
        41: invokespecial #629                // Method coursier/util/shaded/org/jsoup/select/Evaluator$ContainsData."<init>":(Ljava/lang/String;)V
        44: invokeinterface #223,  2          // InterfaceMethod java/util/List.add:(Ljava/lang/Object;)Z
        49: pop
        50: return
      LineNumberTable:
        line 359: 0
        line 360: 10
        line 361: 25
        line 362: 32
        line 363: 50
      LocalVariableTable:
        Start  Length  Slot  Name   Signature
            0      51     0  this   Lcoursier/util/shaded/org/jsoup/select/QueryParser;
           25      26     1 searchText   Ljava/lang/String;

  private void matches(boolean);
    descriptor: (Z)V
    flags: (0x0002) ACC_PRIVATE
    Code:
      stack=4, locals=3, args_size=2
         0: aload_0
         1: getfield      #187                // Field tq:Lcoursier/util/shaded/org/jsoup/parser/TokenQueue;
         4: iload_1
         5: ifeq          14
         8: ldc_w         #631                // String :matchesOwn
        11: goto          17
        14: ldc_w         #633                // String :matches
        17: invokevirtual #606                // Method coursier/util/shaded/org/jsoup/parser/TokenQueue.consume:(Ljava/lang/String;)V
        20: aload_0
        21: getfield      #187                // Field tq:Lcoursier/util/shaded/org/jsoup/parser/TokenQueue;
        24: bipush        40
        26: bipush        41
        28: invokevirtual #316                // Method coursier/util/shaded/org/jsoup/parser/TokenQueue.chompBalanced:(CC)Ljava/lang/String;
        31: astore_2
        32: aload_2
        33: ldc_w         #635                // String :matches(regex) query must not be empty
        36: invokestatic  #610                // Method coursier/util/shaded/org/jsoup/helper/Validate.notEmpty:(Ljava/lang/String;Ljava/lang/String;)V
        39: iload_1
        40: ifeq          67
        43: aload_0
        44: getfield      #168                // Field evals:Ljava/util/List;
        47: new           #138                // class coursier/util/shaded/org/jsoup/select/Evaluator$MatchesOwn
        50: dup
        51: aload_2
        52: invokestatic  #518                // Method java/util/regex/Pattern.compile:(Ljava/lang/String;)Ljava/util/regex/Pattern;
        55: invokespecial #638                // Method coursier/util/shaded/org/jsoup/select/Evaluator$MatchesOwn."<init>":(Ljava/util/regex/Pattern;)V
        58: invokeinterface #223,  2          // InterfaceMethod java/util/List.add:(Ljava/lang/Object;)Z
        63: pop
        64: goto          88
        67: aload_0
        68: getfield      #168                // Field evals:Ljava/util/List;
        71: new           #141                // class coursier/util/shaded/org/jsoup/select/Evaluator$Matches
        74: dup
        75: aload_2
        76: invokestatic  #518                // Method java/util/regex/Pattern.compile:(Ljava/lang/String;)Ljava/util/regex/Pattern;
        79: invokespecial #639                // Method coursier/util/shaded/org/jsoup/select/Evaluator$Matches."<init>":(Ljava/util/regex/Pattern;)V
        82: invokeinterface #223,  2          // InterfaceMethod java/util/List.add:(Ljava/lang/Object;)Z
        87: pop
        88: return
      StackMapTable: number_of_entries = 4
        frame_type = 78 /* same_locals_1_stack_item */
          stack = [ class coursier/util/shaded/org/jsoup/parser/TokenQueue ]
        frame_type = 255 /* full_frame */
          offset_delta = 2
          locals = [ class coursier/util/shaded/org/jsoup/select/QueryParser, int ]
          stack = [ class coursier/util/shaded/org/jsoup/parser/TokenQueue, class java/lang/String ]
        frame_type = 252 /* append */
          offset_delta = 49
          locals = [ class java/lang/String ]
        frame_type = 20 /* same */
      LineNumberTable:
        line 367: 0
        line 368: 20
        line 369: 32
        line 371: 39
        line 372: 43
        line 374: 67
        line 375: 88
      LocalVariableTable:
        Start  Length  Slot  Name   Signature
            0      89     0  this   Lcoursier/util/shaded/org/jsoup/select/QueryParser;
            0      89     1   own   Z
           32      57     2 regex   Ljava/lang/String;

  private void not();
    descriptor: ()V
    flags: (0x0002) ACC_PRIVATE
    Code:
      stack=4, locals=2, args_size=1
         0: aload_0
         1: getfield      #187                // Field tq:Lcoursier/util/shaded/org/jsoup/parser/TokenQueue;
         4: ldc_w         #642                // String :not
         7: invokevirtual #606                // Method coursier/util/shaded/org/jsoup/parser/TokenQueue.consume:(Ljava/lang/String;)V
        10: aload_0
        11: getfield      #187                // Field tq:Lcoursier/util/shaded/org/jsoup/parser/TokenQueue;
        14: bipush        40
        16: bipush        41
        18: invokevirtual #316                // Method coursier/util/shaded/org/jsoup/parser/TokenQueue.chompBalanced:(CC)Ljava/lang/String;
        21: astore_1
        22: aload_1
        23: ldc_w         #644                // String :not(selector) subselect must not be empty
        26: invokestatic  #610                // Method coursier/util/shaded/org/jsoup/helper/Validate.notEmpty:(Ljava/lang/String;Ljava/lang/String;)V
        29: aload_0
        30: getfield      #168                // Field evals:Ljava/util/List;
        33: new           #144                // class coursier/util/shaded/org/jsoup/select/StructuralEvaluator$Not
        36: dup
        37: aload_1
        38: invokestatic  #255                // Method parse:(Ljava/lang/String;)Lcoursier/util/shaded/org/jsoup/select/Evaluator;
        41: invokespecial #645                // Method coursier/util/shaded/org/jsoup/select/StructuralEvaluator$Not."<init>":(Lcoursier/util/shaded/org/jsoup/select/Evaluator;)V
        44: invokeinterface #223,  2          // InterfaceMethod java/util/List.add:(Ljava/lang/Object;)Z
        49: pop
        50: return
      LineNumberTable:
        line 379: 0
        line 380: 10
        line 381: 22
        line 383: 29
        line 384: 50
      LocalVariableTable:
        Start  Length  Slot  Name   Signature
            0      51     0  this   Lcoursier/util/shaded/org/jsoup/select/QueryParser;
           22      29     1 subQuery   Ljava/lang/String;

  static {};
    descriptor: ()V
    flags: (0x0008) ACC_STATIC
    Code:
      stack=4, locals=0, args_size=0
         0: iconst_5
         1: anewarray     #175                // class java/lang/String
         4: dup
         5: iconst_0
         6: ldc_w         #648                // String ,
         9: aastore
        10: dup
        11: iconst_1
        12: ldc_w         #650                // String >
        15: aastore
        16: dup
        17: iconst_2
        18: ldc_w         #652                // String +
        21: aastore
        22: dup
        23: iconst_3
        24: ldc_w         #654                // String ~
        27: aastore
        28: dup
        29: iconst_4
        30: ldc_w         #656                // String
        33: aastore
        34: putstatic     #212                // Field combinators:[Ljava/lang/String;
        37: bipush        6
        39: anewarray     #175                // class java/lang/String
        42: dup
        43: iconst_0
        44: ldc_w         #495                // String =
        47: aastore
        48: dup
        49: iconst_1
        50: ldc_w         #500                // String !=
        53: aastore
        54: dup
        55: iconst_2
        56: ldc_w         #503                // String ^=
        59: aastore
        60: dup
        61: iconst_3
        62: ldc_w         #506                // String $=
        65: aastore
        66: dup
        67: iconst_4
        68: ldc_w         #509                // String *=
        71: aastore
        72: dup
        73: iconst_5
        74: ldc_w         #512                // String ~=
        77: aastore
        78: putstatic     #481                // Field AttributeEvals:[Ljava/lang/String;
        81: ldc_w         #658                // String (([+-])?(\\d+)?)n(\\s*([+-])?\\s*\\d+)?
        84: iconst_2
        85: invokestatic  #661                // Method java/util/regex/Pattern.compile:(Ljava/lang/String;I)Ljava/util/regex/Pattern;
        88: putstatic     #539                // Field NTH_AB:Ljava/util/regex/Pattern;
        91: ldc_w         #663                // String ([+-])?(\\d+)
        94: invokestatic  #518                // Method java/util/regex/Pattern.compile:(Ljava/lang/String;)Ljava/util/regex/Pattern;
        97: putstatic     #545                // Field NTH_B:Ljava/util/regex/Pattern;
       100: return
      LineNumberTable:
        line 18: 0
        line 19: 37
        line 296: 81
        line 297: 91
}
InnerClasses:
  public static #10= #7 of #9;            // SelectorParseException=class coursier/util/shaded/org/jsoup/select/Selector$SelectorParseException of class coursier/util/shaded/org/jsoup/select/Selector
  static #15= #12 of #14;                 // Root=class coursier/util/shaded/org/jsoup/select/StructuralEvaluator$Root of class coursier/util/shaded/org/jsoup/select/StructuralEvaluator
  static final #20= #17 of #19;           // And=class coursier/util/shaded/org/jsoup/select/CombiningEvaluator$And of class coursier/util/shaded/org/jsoup/select/CombiningEvaluator
  static final #23= #22 of #19;           // Or=class coursier/util/shaded/org/jsoup/select/CombiningEvaluator$Or of class coursier/util/shaded/org/jsoup/select/CombiningEvaluator
  static #26= #25 of #14;                 // ImmediateParent=class coursier/util/shaded/org/jsoup/select/StructuralEvaluator$ImmediateParent of class coursier/util/shaded/org/jsoup/select/StructuralEvaluator
  static #29= #28 of #14;                 // Parent=class coursier/util/shaded/org/jsoup/select/StructuralEvaluator$Parent of class coursier/util/shaded/org/jsoup/select/StructuralEvaluator
  static #32= #31 of #14;                 // ImmediatePreviousSibling=class coursier/util/shaded/org/jsoup/select/StructuralEvaluator$ImmediatePreviousSibling of class coursier/util/shaded/org/jsoup/select/StructuralEvaluator
  static #35= #34 of #14;                 // PreviousSibling=class coursier/util/shaded/org/jsoup/select/StructuralEvaluator$PreviousSibling of class coursier/util/shaded/org/jsoup/select/StructuralEvaluator
  public static final #40= #37 of #39;    // IsFirstChild=class coursier/util/shaded/org/jsoup/select/Evaluator$IsFirstChild of class coursier/util/shaded/org/jsoup/select/Evaluator
  public static final #43= #42 of #39;    // IsLastChild=class coursier/util/shaded/org/jsoup/select/Evaluator$IsLastChild of class coursier/util/shaded/org/jsoup/select/Evaluator
  public static final #46= #45 of #39;    // IsFirstOfType=class coursier/util/shaded/org/jsoup/select/Evaluator$IsFirstOfType of class coursier/util/shaded/org/jsoup/select/Evaluator
  public static final #49= #48 of #39;    // IsLastOfType=class coursier/util/shaded/org/jsoup/select/Evaluator$IsLastOfType of class coursier/util/shaded/org/jsoup/select/Evaluator
  public static final #52= #51 of #39;    // IsOnlyChild=class coursier/util/shaded/org/jsoup/select/Evaluator$IsOnlyChild of class coursier/util/shaded/org/jsoup/select/Evaluator
  public static final #55= #54 of #39;    // IsOnlyOfType=class coursier/util/shaded/org/jsoup/select/Evaluator$IsOnlyOfType of class coursier/util/shaded/org/jsoup/select/Evaluator
  public static final #58= #57 of #39;    // IsEmpty=class coursier/util/shaded/org/jsoup/select/Evaluator$IsEmpty of class coursier/util/shaded/org/jsoup/select/Evaluator
  public static final #61= #60 of #39;    // IsRoot=class coursier/util/shaded/org/jsoup/select/Evaluator$IsRoot of class coursier/util/shaded/org/jsoup/select/Evaluator
  public static final #64= #63 of #39;    // MatchText=class coursier/util/shaded/org/jsoup/select/Evaluator$MatchText of class coursier/util/shaded/org/jsoup/select/Evaluator
  public static final #67= #66 of #39;    // Id=class coursier/util/shaded/org/jsoup/select/Evaluator$Id of class coursier/util/shaded/org/jsoup/select/Evaluator
  public static final #70= #69 of #39;    // Class=class coursier/util/shaded/org/jsoup/select/Evaluator$Class of class coursier/util/shaded/org/jsoup/select/Evaluator
  public static final #73= #72 of #39;    // Tag=class coursier/util/shaded/org/jsoup/select/Evaluator$Tag of class coursier/util/shaded/org/jsoup/select/Evaluator
  public static final #76= #75 of #39;    // TagEndsWith=class coursier/util/shaded/org/jsoup/select/Evaluator$TagEndsWith of class coursier/util/shaded/org/jsoup/select/Evaluator
  public static final #79= #78 of #39;    // AttributeStarting=class coursier/util/shaded/org/jsoup/select/Evaluator$AttributeStarting of class coursier/util/shaded/org/jsoup/select/Evaluator
  public static final #82= #81 of #39;    // Attribute=class coursier/util/shaded/org/jsoup/select/Evaluator$Attribute of class coursier/util/shaded/org/jsoup/select/Evaluator
  public static final #85= #84 of #39;    // AttributeWithValue=class coursier/util/shaded/org/jsoup/select/Evaluator$AttributeWithValue of class coursier/util/shaded/org/jsoup/select/Evaluator
  public static final #88= #87 of #39;    // AttributeWithValueNot=class coursier/util/shaded/org/jsoup/select/Evaluator$AttributeWithValueNot of class coursier/util/shaded/org/jsoup/select/Evaluator
  public static final #91= #90 of #39;    // AttributeWithValueStarting=class coursier/util/shaded/org/jsoup/select/Evaluator$AttributeWithValueStarting of class coursier/util/shaded/org/jsoup/select/Evaluator
  public static final #94= #93 of #39;    // AttributeWithValueEnding=class coursier/util/shaded/org/jsoup/select/Evaluator$AttributeWithValueEnding of class coursier/util/shaded/org/jsoup/select/Evaluator
  public static final #97= #96 of #39;    // AttributeWithValueContaining=class coursier/util/shaded/org/jsoup/select/Evaluator$AttributeWithValueContaining of class coursier/util/shaded/org/jsoup/select/Evaluator
  public static final #100= #99 of #39;   // AttributeWithValueMatching=class coursier/util/shaded/org/jsoup/select/Evaluator$AttributeWithValueMatching of class coursier/util/shaded/org/jsoup/select/Evaluator
  public static final #103= #102 of #39;  // AllElements=class coursier/util/shaded/org/jsoup/select/Evaluator$AllElements of class coursier/util/shaded/org/jsoup/select/Evaluator
  public static final #106= #105 of #39;  // IndexLessThan=class coursier/util/shaded/org/jsoup/select/Evaluator$IndexLessThan of class coursier/util/shaded/org/jsoup/select/Evaluator
  public static final #109= #108 of #39;  // IndexGreaterThan=class coursier/util/shaded/org/jsoup/select/Evaluator$IndexGreaterThan of class coursier/util/shaded/org/jsoup/select/Evaluator
  public static final #112= #111 of #39;  // IndexEquals=class coursier/util/shaded/org/jsoup/select/Evaluator$IndexEquals of class coursier/util/shaded/org/jsoup/select/Evaluator
  public static #115= #114 of #39;        // IsNthLastOfType=class coursier/util/shaded/org/jsoup/select/Evaluator$IsNthLastOfType of class coursier/util/shaded/org/jsoup/select/Evaluator
  public static #118= #117 of #39;        // IsNthOfType=class coursier/util/shaded/org/jsoup/select/Evaluator$IsNthOfType of class coursier/util/shaded/org/jsoup/select/Evaluator
  public static final #121= #120 of #39;  // IsNthLastChild=class coursier/util/shaded/org/jsoup/select/Evaluator$IsNthLastChild of class coursier/util/shaded/org/jsoup/select/Evaluator
  public static final #124= #123 of #39;  // IsNthChild=class coursier/util/shaded/org/jsoup/select/Evaluator$IsNthChild of class coursier/util/shaded/org/jsoup/select/Evaluator
  static #127= #126 of #14;               // Has=class coursier/util/shaded/org/jsoup/select/StructuralEvaluator$Has of class coursier/util/shaded/org/jsoup/select/StructuralEvaluator
  public static final #130= #129 of #39;  // ContainsOwnText=class coursier/util/shaded/org/jsoup/select/Evaluator$ContainsOwnText of class coursier/util/shaded/org/jsoup/select/Evaluator
  public static final #133= #132 of #39;  // ContainsText=class coursier/util/shaded/org/jsoup/select/Evaluator$ContainsText of class coursier/util/shaded/org/jsoup/select/Evaluator
  public static final #136= #135 of #39;  // ContainsData=class coursier/util/shaded/org/jsoup/select/Evaluator$ContainsData of class coursier/util/shaded/org/jsoup/select/Evaluator
  public static final #139= #138 of #39;  // MatchesOwn=class coursier/util/shaded/org/jsoup/select/Evaluator$MatchesOwn of class coursier/util/shaded/org/jsoup/select/Evaluator
  public static final #142= #141 of #39;  // Matches=class coursier/util/shaded/org/jsoup/select/Evaluator$Matches of class coursier/util/shaded/org/jsoup/select/Evaluator
  static #145= #144 of #14;               // Not=class coursier/util/shaded/org/jsoup/select/StructuralEvaluator$Not of class coursier/util/shaded/org/jsoup/select/StructuralEvaluator
SourceFile: "QueryParser.java"
