Classfile /Users/mw/Projects/slang-braindump/.jar/jar11/assemble/slang-braindump/assemble/content/coursier/util/shaded/org/jsoup/select/Selector.class
  Last modified May 29, 2022; size 4378 bytes
  SHA-256 checksum a837290d5c4ed7865cb20fd4943fe7c20f9816f66afb2a040a45b450d8ba3d3c
  Compiled from "Selector.java"
public class coursier.util.shaded.org.jsoup.select.Selector
  minor version: 0
  major version: 51
  flags: (0x0021) ACC_PUBLIC, ACC_SUPER
  this_class: #2                          // coursier/util/shaded/org/jsoup/select/Selector
  super_class: #4                         // java/lang/Object
  interfaces: 0, fields: 0, methods: 6, attributes: 2
Constant pool:
    #1 = Utf8               coursier/util/shaded/org/jsoup/select/Selector
    #2 = Class              #1            // coursier/util/shaded/org/jsoup/select/Selector
    #3 = Utf8               java/lang/Object
    #4 = Class              #3            // java/lang/Object
    #5 = Utf8               Selector.java
    #6 = Utf8               coursier/util/shaded/org/jsoup/select/Selector$SelectorParseException
    #7 = Class              #6            // coursier/util/shaded/org/jsoup/select/Selector$SelectorParseException
    #8 = Utf8               SelectorParseException
    #9 = Utf8               <init>
   #10 = Utf8               ()V
   #11 = NameAndType        #9:#10        // "<init>":()V
   #12 = Methodref          #4.#11        // java/lang/Object."<init>":()V
   #13 = Utf8               this
   #14 = Utf8               Lcoursier/util/shaded/org/jsoup/select/Selector;
   #15 = Utf8               select
   #16 = Utf8               (Ljava/lang/String;Lcoursier/util/shaded/org/jsoup/nodes/Element;)Lcoursier/util/shaded/org/jsoup/select/Elements;
   #17 = Utf8               coursier/util/shaded/org/jsoup/helper/Validate
   #18 = Class              #17           // coursier/util/shaded/org/jsoup/helper/Validate
   #19 = Utf8               notEmpty
   #20 = Utf8               (Ljava/lang/String;)V
   #21 = NameAndType        #19:#20       // notEmpty:(Ljava/lang/String;)V
   #22 = Methodref          #18.#21       // coursier/util/shaded/org/jsoup/helper/Validate.notEmpty:(Ljava/lang/String;)V
   #23 = Utf8               coursier/util/shaded/org/jsoup/select/QueryParser
   #24 = Class              #23           // coursier/util/shaded/org/jsoup/select/QueryParser
   #25 = Utf8               parse
   #26 = Utf8               (Ljava/lang/String;)Lcoursier/util/shaded/org/jsoup/select/Evaluator;
   #27 = NameAndType        #25:#26       // parse:(Ljava/lang/String;)Lcoursier/util/shaded/org/jsoup/select/Evaluator;
   #28 = Methodref          #24.#27       // coursier/util/shaded/org/jsoup/select/QueryParser.parse:(Ljava/lang/String;)Lcoursier/util/shaded/org/jsoup/select/Evaluator;
   #29 = Utf8               (Lcoursier/util/shaded/org/jsoup/select/Evaluator;Lcoursier/util/shaded/org/jsoup/nodes/Element;)Lcoursier/util/shaded/org/jsoup/select/Elements;
   #30 = NameAndType        #15:#29       // select:(Lcoursier/util/shaded/org/jsoup/select/Evaluator;Lcoursier/util/shaded/org/jsoup/nodes/Element;)Lcoursier/util/shaded/org/jsoup/select/Elements;
   #31 = Methodref          #2.#30        // coursier/util/shaded/org/jsoup/select/Selector.select:(Lcoursier/util/shaded/org/jsoup/select/Evaluator;Lcoursier/util/shaded/org/jsoup/nodes/Element;)Lcoursier/util/shaded/org/jsoup/select/Elements;
   #32 = Utf8               query
   #33 = Utf8               Ljava/lang/String;
   #34 = Utf8               root
   #35 = Utf8               Lcoursier/util/shaded/org/jsoup/nodes/Element;
   #36 = Utf8               notNull
   #37 = Utf8               (Ljava/lang/Object;)V
   #38 = NameAndType        #36:#37       // notNull:(Ljava/lang/Object;)V
   #39 = Methodref          #18.#38       // coursier/util/shaded/org/jsoup/helper/Validate.notNull:(Ljava/lang/Object;)V
   #40 = Utf8               coursier/util/shaded/org/jsoup/select/Collector
   #41 = Class              #40           // coursier/util/shaded/org/jsoup/select/Collector
   #42 = Utf8               collect
   #43 = NameAndType        #42:#29       // collect:(Lcoursier/util/shaded/org/jsoup/select/Evaluator;Lcoursier/util/shaded/org/jsoup/nodes/Element;)Lcoursier/util/shaded/org/jsoup/select/Elements;
   #44 = Methodref          #41.#43       // coursier/util/shaded/org/jsoup/select/Collector.collect:(Lcoursier/util/shaded/org/jsoup/select/Evaluator;Lcoursier/util/shaded/org/jsoup/nodes/Element;)Lcoursier/util/shaded/org/jsoup/select/Elements;
   #45 = Utf8               evaluator
   #46 = Utf8               Lcoursier/util/shaded/org/jsoup/select/Evaluator;
   #47 = Utf8               (Ljava/lang/String;Ljava/lang/Iterable;)Lcoursier/util/shaded/org/jsoup/select/Elements;
   #48 = Utf8               (Ljava/lang/String;Ljava/lang/Iterable<Lcoursier/util/shaded/org/jsoup/nodes/Element;>;)Lcoursier/util/shaded/org/jsoup/select/Elements;
   #49 = Utf8               java/util/ArrayList
   #50 = Class              #49           // java/util/ArrayList
   #51 = Methodref          #50.#11       // java/util/ArrayList."<init>":()V
   #52 = Utf8               java/util/IdentityHashMap
   #53 = Class              #52           // java/util/IdentityHashMap
   #54 = Methodref          #53.#11       // java/util/IdentityHashMap."<init>":()V
   #55 = Utf8               java/lang/Iterable
   #56 = Class              #55           // java/lang/Iterable
   #57 = Utf8               iterator
   #58 = Utf8               ()Ljava/util/Iterator;
   #59 = NameAndType        #57:#58       // iterator:()Ljava/util/Iterator;
   #60 = InterfaceMethodref #56.#59       // java/lang/Iterable.iterator:()Ljava/util/Iterator;
   #61 = Utf8               java/lang/String
   #62 = Class              #61           // java/lang/String
   #63 = Utf8               coursier/util/shaded/org/jsoup/select/Evaluator
   #64 = Class              #63           // coursier/util/shaded/org/jsoup/select/Evaluator
   #65 = Utf8               java/util/Iterator
   #66 = Class              #65           // java/util/Iterator
   #67 = Utf8               hasNext
   #68 = Utf8               ()Z
   #69 = NameAndType        #67:#68       // hasNext:()Z
   #70 = InterfaceMethodref #66.#69       // java/util/Iterator.hasNext:()Z
   #71 = Utf8               next
   #72 = Utf8               ()Ljava/lang/Object;
   #73 = NameAndType        #71:#72       // next:()Ljava/lang/Object;
   #74 = InterfaceMethodref #66.#73       // java/util/Iterator.next:()Ljava/lang/Object;
   #75 = Utf8               coursier/util/shaded/org/jsoup/nodes/Element
   #76 = Class              #75           // coursier/util/shaded/org/jsoup/nodes/Element
   #77 = Utf8               coursier/util/shaded/org/jsoup/select/Elements
   #78 = Class              #77           // coursier/util/shaded/org/jsoup/select/Elements
   #79 = Methodref          #78.#59       // coursier/util/shaded/org/jsoup/select/Elements.iterator:()Ljava/util/Iterator;
   #80 = Utf8               containsKey
   #81 = Utf8               (Ljava/lang/Object;)Z
   #82 = NameAndType        #80:#81       // containsKey:(Ljava/lang/Object;)Z
   #83 = Methodref          #53.#82       // java/util/IdentityHashMap.containsKey:(Ljava/lang/Object;)Z
   #84 = Utf8               add
   #85 = NameAndType        #84:#81       // add:(Ljava/lang/Object;)Z
   #86 = Methodref          #50.#85       // java/util/ArrayList.add:(Ljava/lang/Object;)Z
   #87 = Utf8               java/lang/Boolean
   #88 = Class              #87           // java/lang/Boolean
   #89 = Utf8               TRUE
   #90 = Utf8               Ljava/lang/Boolean;
   #91 = NameAndType        #89:#90       // TRUE:Ljava/lang/Boolean;
   #92 = Fieldref           #88.#91       // java/lang/Boolean.TRUE:Ljava/lang/Boolean;
   #93 = Utf8               put
   #94 = Utf8               (Ljava/lang/Object;Ljava/lang/Object;)Ljava/lang/Object;
   #95 = NameAndType        #93:#94       // put:(Ljava/lang/Object;Ljava/lang/Object;)Ljava/lang/Object;
   #96 = Methodref          #53.#95       // java/util/IdentityHashMap.put:(Ljava/lang/Object;Ljava/lang/Object;)Ljava/lang/Object;
   #97 = Utf8               (Ljava/util/List;)V
   #98 = NameAndType        #9:#97        // "<init>":(Ljava/util/List;)V
   #99 = Methodref          #78.#98       // coursier/util/shaded/org/jsoup/select/Elements."<init>":(Ljava/util/List;)V
  #100 = Utf8               el
  #101 = Utf8               found
  #102 = Utf8               Lcoursier/util/shaded/org/jsoup/select/Elements;
  #103 = Utf8               roots
  #104 = Utf8               Ljava/lang/Iterable<Lcoursier/util/shaded/org/jsoup/nodes/Element;>;
  #105 = Utf8               Ljava/lang/Iterable;
  #106 = Utf8               elements
  #107 = Utf8               Ljava/util/ArrayList<Lcoursier/util/shaded/org/jsoup/nodes/Element;>;
  #108 = Utf8               Ljava/util/ArrayList;
  #109 = Utf8               seenElements
  #110 = Utf8               Ljava/util/IdentityHashMap<Lcoursier/util/shaded/org/jsoup/nodes/Element;Ljava/lang/Boolean;>;
  #111 = Utf8               Ljava/util/IdentityHashMap;
  #112 = Utf8               filterOut
  #113 = Utf8               (Ljava/util/Collection;Ljava/util/Collection;)Lcoursier/util/shaded/org/jsoup/select/Elements;
  #114 = Utf8               (Ljava/util/Collection<Lcoursier/util/shaded/org/jsoup/nodes/Element;>;Ljava/util/Collection<Lcoursier/util/shaded/org/jsoup/nodes/Element;>;)Lcoursier/util/shaded/org/jsoup/select/Elements;
  #115 = Methodref          #78.#11       // coursier/util/shaded/org/jsoup/select/Elements."<init>":()V
  #116 = Utf8               java/util/Collection
  #117 = Class              #116          // java/util/Collection
  #118 = InterfaceMethodref #117.#59      // java/util/Collection.iterator:()Ljava/util/Iterator;
  #119 = Utf8               equals
  #120 = NameAndType        #119:#81      // equals:(Ljava/lang/Object;)Z
  #121 = Methodref          #76.#120      // coursier/util/shaded/org/jsoup/nodes/Element.equals:(Ljava/lang/Object;)Z
  #122 = Methodref          #78.#85       // coursier/util/shaded/org/jsoup/select/Elements.add:(Ljava/lang/Object;)Z
  #123 = Utf8               out
  #124 = Utf8               Z
  #125 = Utf8               Ljava/util/Collection<Lcoursier/util/shaded/org/jsoup/nodes/Element;>;
  #126 = Utf8               Ljava/util/Collection;
  #127 = Utf8               outs
  #128 = Utf8               output
  #129 = Utf8               selectFirst
  #130 = Utf8               (Ljava/lang/String;Lcoursier/util/shaded/org/jsoup/nodes/Element;)Lcoursier/util/shaded/org/jsoup/nodes/Element;
  #131 = Utf8               findFirst
  #132 = Utf8               (Lcoursier/util/shaded/org/jsoup/select/Evaluator;Lcoursier/util/shaded/org/jsoup/nodes/Element;)Lcoursier/util/shaded/org/jsoup/nodes/Element;
  #133 = NameAndType        #131:#132     // findFirst:(Lcoursier/util/shaded/org/jsoup/select/Evaluator;Lcoursier/util/shaded/org/jsoup/nodes/Element;)Lcoursier/util/shaded/org/jsoup/nodes/Element;
  #134 = Methodref          #41.#133      // coursier/util/shaded/org/jsoup/select/Collector.findFirst:(Lcoursier/util/shaded/org/jsoup/select/Evaluator;Lcoursier/util/shaded/org/jsoup/nodes/Element;)Lcoursier/util/shaded/org/jsoup/nodes/Element;
  #135 = Utf8               cssQuery
  #136 = Utf8               Code
  #137 = Utf8               LineNumberTable
  #138 = Utf8               LocalVariableTable
  #139 = Utf8               StackMapTable
  #140 = Utf8               LocalVariableTypeTable
  #141 = Utf8               Signature
  #142 = Utf8               InnerClasses
  #143 = Utf8               SourceFile
{
  private coursier.util.shaded.org.jsoup.select.Selector();
    descriptor: ()V
    flags: (0x0002) ACC_PRIVATE
    Code:
      stack=1, locals=1, args_size=1
         0: aload_0
         1: invokespecial #12                 // Method java/lang/Object."<init>":()V
         4: return
      LineNumberTable:
        line 80: 0
      LocalVariableTable:
        Start  Length  Slot  Name   Signature
            0       5     0  this   Lcoursier/util/shaded/org/jsoup/select/Selector;

  public static coursier.util.shaded.org.jsoup.select.Elements select(java.lang.String, coursier.util.shaded.org.jsoup.nodes.Element);
    descriptor: (Ljava/lang/String;Lcoursier/util/shaded/org/jsoup/nodes/Element;)Lcoursier/util/shaded/org/jsoup/select/Elements;
    flags: (0x0009) ACC_PUBLIC, ACC_STATIC
    Code:
      stack=2, locals=2, args_size=2
         0: aload_0
         1: invokestatic  #22                 // Method coursier/util/shaded/org/jsoup/helper/Validate.notEmpty:(Ljava/lang/String;)V
         4: aload_0
         5: invokestatic  #28                 // Method coursier/util/shaded/org/jsoup/select/QueryParser.parse:(Ljava/lang/String;)Lcoursier/util/shaded/org/jsoup/select/Evaluator;
         8: aload_1
         9: invokestatic  #31                 // Method select:(Lcoursier/util/shaded/org/jsoup/select/Evaluator;Lcoursier/util/shaded/org/jsoup/nodes/Element;)Lcoursier/util/shaded/org/jsoup/select/Elements;
        12: areturn
      LineNumberTable:
        line 91: 0
        line 92: 4
      LocalVariableTable:
        Start  Length  Slot  Name   Signature
            0      13     0 query   Ljava/lang/String;
            0      13     1  root   Lcoursier/util/shaded/org/jsoup/nodes/Element;

  public static coursier.util.shaded.org.jsoup.select.Elements select(coursier.util.shaded.org.jsoup.select.Evaluator, coursier.util.shaded.org.jsoup.nodes.Element);
    descriptor: (Lcoursier/util/shaded/org/jsoup/select/Evaluator;Lcoursier/util/shaded/org/jsoup/nodes/Element;)Lcoursier/util/shaded/org/jsoup/select/Elements;
    flags: (0x0009) ACC_PUBLIC, ACC_STATIC
    Code:
      stack=2, locals=2, args_size=2
         0: aload_0
         1: invokestatic  #39                 // Method coursier/util/shaded/org/jsoup/helper/Validate.notNull:(Ljava/lang/Object;)V
         4: aload_1
         5: invokestatic  #39                 // Method coursier/util/shaded/org/jsoup/helper/Validate.notNull:(Ljava/lang/Object;)V
         8: aload_0
         9: aload_1
        10: invokestatic  #44                 // Method coursier/util/shaded/org/jsoup/select/Collector.collect:(Lcoursier/util/shaded/org/jsoup/select/Evaluator;Lcoursier/util/shaded/org/jsoup/nodes/Element;)Lcoursier/util/shaded/org/jsoup/select/Elements;
        13: areturn
      LineNumberTable:
        line 103: 0
        line 104: 4
        line 105: 8
      LocalVariableTable:
        Start  Length  Slot  Name   Signature
            0      14     0 evaluator   Lcoursier/util/shaded/org/jsoup/select/Evaluator;
            0      14     1  root   Lcoursier/util/shaded/org/jsoup/nodes/Element;

  public static coursier.util.shaded.org.jsoup.select.Elements select(java.lang.String, java.lang.Iterable<coursier.util.shaded.org.jsoup.nodes.Element>);
    descriptor: (Ljava/lang/String;Ljava/lang/Iterable;)Lcoursier/util/shaded/org/jsoup/select/Elements;
    flags: (0x0009) ACC_PUBLIC, ACC_STATIC
    Code:
      stack=3, locals=10, args_size=2
         0: aload_0
         1: invokestatic  #22                 // Method coursier/util/shaded/org/jsoup/helper/Validate.notEmpty:(Ljava/lang/String;)V
         4: aload_1
         5: invokestatic  #39                 // Method coursier/util/shaded/org/jsoup/helper/Validate.notNull:(Ljava/lang/Object;)V
         8: aload_0
         9: invokestatic  #28                 // Method coursier/util/shaded/org/jsoup/select/QueryParser.parse:(Ljava/lang/String;)Lcoursier/util/shaded/org/jsoup/select/Evaluator;
        12: astore_2
        13: new           #50                 // class java/util/ArrayList
        16: dup
        17: invokespecial #51                 // Method java/util/ArrayList."<init>":()V
        20: astore_3
        21: new           #53                 // class java/util/IdentityHashMap
        24: dup
        25: invokespecial #54                 // Method java/util/IdentityHashMap."<init>":()V
        28: astore        4
        30: aload_1
        31: invokeinterface #60,  1           // InterfaceMethod java/lang/Iterable.iterator:()Ljava/util/Iterator;
        36: astore        5
        38: aload         5
        40: invokeinterface #70,  1           // InterfaceMethod java/util/Iterator.hasNext:()Z
        45: ifeq          131
        48: aload         5
        50: invokeinterface #74,  1           // InterfaceMethod java/util/Iterator.next:()Ljava/lang/Object;
        55: checkcast     #76                 // class coursier/util/shaded/org/jsoup/nodes/Element
        58: astore        6
        60: aload_2
        61: aload         6
        63: invokestatic  #31                 // Method select:(Lcoursier/util/shaded/org/jsoup/select/Evaluator;Lcoursier/util/shaded/org/jsoup/nodes/Element;)Lcoursier/util/shaded/org/jsoup/select/Elements;
        66: astore        7
        68: aload         7
        70: invokevirtual #79                 // Method coursier/util/shaded/org/jsoup/select/Elements.iterator:()Ljava/util/Iterator;
        73: astore        8
        75: aload         8
        77: invokeinterface #70,  1           // InterfaceMethod java/util/Iterator.hasNext:()Z
        82: ifeq          128
        85: aload         8
        87: invokeinterface #74,  1           // InterfaceMethod java/util/Iterator.next:()Ljava/lang/Object;
        92: checkcast     #76                 // class coursier/util/shaded/org/jsoup/nodes/Element
        95: astore        9
        97: aload         4
        99: aload         9
       101: invokevirtual #83                 // Method java/util/IdentityHashMap.containsKey:(Ljava/lang/Object;)Z
       104: ifne          125
       107: aload_3
       108: aload         9
       110: invokevirtual #86                 // Method java/util/ArrayList.add:(Ljava/lang/Object;)Z
       113: pop
       114: aload         4
       116: aload         9
       118: getstatic     #92                 // Field java/lang/Boolean.TRUE:Ljava/lang/Boolean;
       121: invokevirtual #96                 // Method java/util/IdentityHashMap.put:(Ljava/lang/Object;Ljava/lang/Object;)Ljava/lang/Object;
       124: pop
       125: goto          75
       128: goto          38
       131: new           #78                 // class coursier/util/shaded/org/jsoup/select/Elements
       134: dup
       135: aload_3
       136: invokespecial #99                 // Method coursier/util/shaded/org/jsoup/select/Elements."<init>":(Ljava/util/List;)V
       139: areturn
      StackMapTable: number_of_entries = 5
        frame_type = 255 /* full_frame */
          offset_delta = 38
          locals = [ class java/lang/String, class java/lang/Iterable, class coursier/util/shaded/org/jsoup/select/Evaluator, class java/util/ArrayList, class java/util/IdentityHashMap, class java/util/Iterator ]
          stack = []
        frame_type = 254 /* append */
          offset_delta = 36
          locals = [ class coursier/util/shaded/org/jsoup/nodes/Element, class coursier/util/shaded/org/jsoup/select/Elements, class java/util/Iterator ]
        frame_type = 49 /* same */
        frame_type = 248 /* chop */
          offset_delta = 2
        frame_type = 250 /* chop */
          offset_delta = 2
      LineNumberTable:
        line 116: 0
        line 117: 4
        line 118: 8
        line 119: 13
        line 120: 21
        line 123: 30
        line 124: 60
        line 125: 68
        line 126: 97
        line 127: 107
        line 128: 114
        line 130: 125
        line 131: 128
        line 132: 131
      LocalVariableTable:
        Start  Length  Slot  Name   Signature
           97      28     9    el   Lcoursier/util/shaded/org/jsoup/nodes/Element;
           68      60     7 found   Lcoursier/util/shaded/org/jsoup/select/Elements;
           60      68     6  root   Lcoursier/util/shaded/org/jsoup/nodes/Element;
            0     140     0 query   Ljava/lang/String;
            0     140     1 roots   Ljava/lang/Iterable;
           13     127     2 evaluator   Lcoursier/util/shaded/org/jsoup/select/Evaluator;
           21     119     3 elements   Ljava/util/ArrayList;
           30     110     4 seenElements   Ljava/util/IdentityHashMap;
      LocalVariableTypeTable:
        Start  Length  Slot  Name   Signature
            0     140     1 roots   Ljava/lang/Iterable<Lcoursier/util/shaded/org/jsoup/nodes/Element;>;
           21     119     3 elements   Ljava/util/ArrayList<Lcoursier/util/shaded/org/jsoup/nodes/Element;>;
           30     110     4 seenElements   Ljava/util/IdentityHashMap<Lcoursier/util/shaded/org/jsoup/nodes/Element;Ljava/lang/Boolean;>;
    Signature: #48                          // (Ljava/lang/String;Ljava/lang/Iterable<Lcoursier/util/shaded/org/jsoup/nodes/Element;>;)Lcoursier/util/shaded/org/jsoup/select/Elements;

  static coursier.util.shaded.org.jsoup.select.Elements filterOut(java.util.Collection<coursier.util.shaded.org.jsoup.nodes.Element>, java.util.Collection<coursier.util.shaded.org.jsoup.nodes.Element>);
    descriptor: (Ljava/util/Collection;Ljava/util/Collection;)Lcoursier/util/shaded/org/jsoup/select/Elements;
    flags: (0x0008) ACC_STATIC
    Code:
      stack=2, locals=8, args_size=2
         0: new           #78                 // class coursier/util/shaded/org/jsoup/select/Elements
         3: dup
         4: invokespecial #115                // Method coursier/util/shaded/org/jsoup/select/Elements."<init>":()V
         7: astore_2
         8: aload_0
         9: invokeinterface #118,  1          // InterfaceMethod java/util/Collection.iterator:()Ljava/util/Iterator;
        14: astore_3
        15: aload_3
        16: invokeinterface #70,  1           // InterfaceMethod java/util/Iterator.hasNext:()Z
        21: ifeq          102
        24: aload_3
        25: invokeinterface #74,  1           // InterfaceMethod java/util/Iterator.next:()Ljava/lang/Object;
        30: checkcast     #76                 // class coursier/util/shaded/org/jsoup/nodes/Element
        33: astore        4
        35: iconst_0
        36: istore        5
        38: aload_1
        39: invokeinterface #118,  1          // InterfaceMethod java/util/Collection.iterator:()Ljava/util/Iterator;
        44: astore        6
        46: aload         6
        48: invokeinterface #70,  1           // InterfaceMethod java/util/Iterator.hasNext:()Z
        53: ifeq          87
        56: aload         6
        58: invokeinterface #74,  1           // InterfaceMethod java/util/Iterator.next:()Ljava/lang/Object;
        63: checkcast     #76                 // class coursier/util/shaded/org/jsoup/nodes/Element
        66: astore        7
        68: aload         4
        70: aload         7
        72: invokevirtual #121                // Method coursier/util/shaded/org/jsoup/nodes/Element.equals:(Ljava/lang/Object;)Z
        75: ifeq          84
        78: iconst_1
        79: istore        5
        81: goto          87
        84: goto          46
        87: iload         5
        89: ifne          99
        92: aload_2
        93: aload         4
        95: invokevirtual #122                // Method coursier/util/shaded/org/jsoup/select/Elements.add:(Ljava/lang/Object;)Z
        98: pop
        99: goto          15
       102: aload_2
       103: areturn
      StackMapTable: number_of_entries = 6
        frame_type = 253 /* append */
          offset_delta = 15
          locals = [ class coursier/util/shaded/org/jsoup/select/Elements, class java/util/Iterator ]
        frame_type = 254 /* append */
          offset_delta = 30
          locals = [ class coursier/util/shaded/org/jsoup/nodes/Element, int, class java/util/Iterator ]
        frame_type = 37 /* same */
        frame_type = 250 /* chop */
          offset_delta = 2
        frame_type = 249 /* chop */
          offset_delta = 11
        frame_type = 250 /* chop */
          offset_delta = 2
      LineNumberTable:
        line 137: 0
        line 138: 8
        line 139: 35
        line 140: 38
        line 141: 68
        line 142: 78
        line 143: 81
        line 145: 84
        line 146: 87
        line 147: 92
        line 148: 99
        line 149: 102
      LocalVariableTable:
        Start  Length  Slot  Name   Signature
           68      16     7   out   Lcoursier/util/shaded/org/jsoup/nodes/Element;
           38      61     5 found   Z
           35      64     4    el   Lcoursier/util/shaded/org/jsoup/nodes/Element;
            0     104     0 elements   Ljava/util/Collection;
            0     104     1  outs   Ljava/util/Collection;
            8      96     2 output   Lcoursier/util/shaded/org/jsoup/select/Elements;
      LocalVariableTypeTable:
        Start  Length  Slot  Name   Signature
            0     104     0 elements   Ljava/util/Collection<Lcoursier/util/shaded/org/jsoup/nodes/Element;>;
            0     104     1  outs   Ljava/util/Collection<Lcoursier/util/shaded/org/jsoup/nodes/Element;>;
    Signature: #114                         // (Ljava/util/Collection<Lcoursier/util/shaded/org/jsoup/nodes/Element;>;Ljava/util/Collection<Lcoursier/util/shaded/org/jsoup/nodes/Element;>;)Lcoursier/util/shaded/org/jsoup/select/Elements;

  public static coursier.util.shaded.org.jsoup.nodes.Element selectFirst(java.lang.String, coursier.util.shaded.org.jsoup.nodes.Element);
    descriptor: (Ljava/lang/String;Lcoursier/util/shaded/org/jsoup/nodes/Element;)Lcoursier/util/shaded/org/jsoup/nodes/Element;
    flags: (0x0009) ACC_PUBLIC, ACC_STATIC
    Code:
      stack=2, locals=2, args_size=2
         0: aload_0
         1: invokestatic  #22                 // Method coursier/util/shaded/org/jsoup/helper/Validate.notEmpty:(Ljava/lang/String;)V
         4: aload_0
         5: invokestatic  #28                 // Method coursier/util/shaded/org/jsoup/select/QueryParser.parse:(Ljava/lang/String;)Lcoursier/util/shaded/org/jsoup/select/Evaluator;
         8: aload_1
         9: invokestatic  #134                // Method coursier/util/shaded/org/jsoup/select/Collector.findFirst:(Lcoursier/util/shaded/org/jsoup/select/Evaluator;Lcoursier/util/shaded/org/jsoup/nodes/Element;)Lcoursier/util/shaded/org/jsoup/nodes/Element;
        12: areturn
      LineNumberTable:
        line 159: 0
        line 160: 4
      LocalVariableTable:
        Start  Length  Slot  Name   Signature
            0      13     0 cssQuery   Ljava/lang/String;
            0      13     1  root   Lcoursier/util/shaded/org/jsoup/nodes/Element;
}
InnerClasses:
  public static #8= #7 of #2;             // SelectorParseException=class coursier/util/shaded/org/jsoup/select/Selector$SelectorParseException of class coursier/util/shaded/org/jsoup/select/Selector
SourceFile: "Selector.java"
