Classfile /Users/mw/Projects/slang-braindump/.jar/jar11/assemble/slang-braindump/assemble/content/coursier/util/shaded/org/jsoup/select/StructuralEvaluator.class
  Last modified May 29, 2022; size 1149 bytes
  SHA-256 checksum 544434c44d1494d75197beffd645dd831e817ce74bbcb44f7bb4401edf9c2b9f
  Compiled from "StructuralEvaluator.java"
abstract class coursier.util.shaded.org.jsoup.select.StructuralEvaluator extends coursier.util.shaded.org.jsoup.select.Evaluator
  minor version: 0
  major version: 51
  flags: (0x0420) ACC_SUPER, ACC_ABSTRACT
  this_class: #2                          // coursier/util/shaded/org/jsoup/select/StructuralEvaluator
  super_class: #4                         // coursier/util/shaded/org/jsoup/select/Evaluator
  interfaces: 0, fields: 1, methods: 1, attributes: 2
Constant pool:
   #1 = Utf8               coursier/util/shaded/org/jsoup/select/StructuralEvaluator
   #2 = Class              #1             // coursier/util/shaded/org/jsoup/select/StructuralEvaluator
   #3 = Utf8               coursier/util/shaded/org/jsoup/select/Evaluator
   #4 = Class              #3             // coursier/util/shaded/org/jsoup/select/Evaluator
   #5 = Utf8               StructuralEvaluator.java
   #6 = Utf8               coursier/util/shaded/org/jsoup/select/StructuralEvaluator$ImmediatePreviousSibling
   #7 = Class              #6             // coursier/util/shaded/org/jsoup/select/StructuralEvaluator$ImmediatePreviousSibling
   #8 = Utf8               ImmediatePreviousSibling
   #9 = Utf8               coursier/util/shaded/org/jsoup/select/StructuralEvaluator$PreviousSibling
  #10 = Class              #9             // coursier/util/shaded/org/jsoup/select/StructuralEvaluator$PreviousSibling
  #11 = Utf8               PreviousSibling
  #12 = Utf8               coursier/util/shaded/org/jsoup/select/StructuralEvaluator$ImmediateParent
  #13 = Class              #12            // coursier/util/shaded/org/jsoup/select/StructuralEvaluator$ImmediateParent
  #14 = Utf8               ImmediateParent
  #15 = Utf8               coursier/util/shaded/org/jsoup/select/StructuralEvaluator$Parent
  #16 = Class              #15            // coursier/util/shaded/org/jsoup/select/StructuralEvaluator$Parent
  #17 = Utf8               Parent
  #18 = Utf8               coursier/util/shaded/org/jsoup/select/StructuralEvaluator$Not
  #19 = Class              #18            // coursier/util/shaded/org/jsoup/select/StructuralEvaluator$Not
  #20 = Utf8               Not
  #21 = Utf8               coursier/util/shaded/org/jsoup/select/StructuralEvaluator$Has
  #22 = Class              #21            // coursier/util/shaded/org/jsoup/select/StructuralEvaluator$Has
  #23 = Utf8               Has
  #24 = Utf8               coursier/util/shaded/org/jsoup/select/StructuralEvaluator$Root
  #25 = Class              #24            // coursier/util/shaded/org/jsoup/select/StructuralEvaluator$Root
  #26 = Utf8               Root
  #27 = Utf8               evaluator
  #28 = Utf8               Lcoursier/util/shaded/org/jsoup/select/Evaluator;
  #29 = Utf8               <init>
  #30 = Utf8               ()V
  #31 = NameAndType        #29:#30        // "<init>":()V
  #32 = Methodref          #4.#31         // coursier/util/shaded/org/jsoup/select/Evaluator."<init>":()V
  #33 = Utf8               this
  #34 = Utf8               Lcoursier/util/shaded/org/jsoup/select/StructuralEvaluator;
  #35 = Utf8               Code
  #36 = Utf8               LineNumberTable
  #37 = Utf8               LocalVariableTable
  #38 = Utf8               InnerClasses
  #39 = Utf8               SourceFile
{
  coursier.util.shaded.org.jsoup.select.Evaluator evaluator;
    descriptor: Lcoursier/util/shaded/org/jsoup/select/Evaluator;
    flags: (0x0000)

  coursier.util.shaded.org.jsoup.select.StructuralEvaluator();
    descriptor: ()V
    flags: (0x0000)
    Code:
      stack=1, locals=1, args_size=1
         0: aload_0
         1: invokespecial #32                 // Method coursier/util/shaded/org/jsoup/select/Evaluator."<init>":()V
         4: return
      LineNumberTable:
        line 8: 0
      LocalVariableTable:
        Start  Length  Slot  Name   Signature
            0       5     0  this   Lcoursier/util/shaded/org/jsoup/select/StructuralEvaluator;
}
InnerClasses:
  static #8= #7 of #2;                    // ImmediatePreviousSibling=class coursier/util/shaded/org/jsoup/select/StructuralEvaluator$ImmediatePreviousSibling of class coursier/util/shaded/org/jsoup/select/StructuralEvaluator
  static #11= #10 of #2;                  // PreviousSibling=class coursier/util/shaded/org/jsoup/select/StructuralEvaluator$PreviousSibling of class coursier/util/shaded/org/jsoup/select/StructuralEvaluator
  static #14= #13 of #2;                  // ImmediateParent=class coursier/util/shaded/org/jsoup/select/StructuralEvaluator$ImmediateParent of class coursier/util/shaded/org/jsoup/select/StructuralEvaluator
  static #17= #16 of #2;                  // Parent=class coursier/util/shaded/org/jsoup/select/StructuralEvaluator$Parent of class coursier/util/shaded/org/jsoup/select/StructuralEvaluator
  static #20= #19 of #2;                  // Not=class coursier/util/shaded/org/jsoup/select/StructuralEvaluator$Not of class coursier/util/shaded/org/jsoup/select/StructuralEvaluator
  static #23= #22 of #2;                  // Has=class coursier/util/shaded/org/jsoup/select/StructuralEvaluator$Has of class coursier/util/shaded/org/jsoup/select/StructuralEvaluator
  static #26= #25 of #2;                  // Root=class coursier/util/shaded/org/jsoup/select/StructuralEvaluator$Root of class coursier/util/shaded/org/jsoup/select/StructuralEvaluator
SourceFile: "StructuralEvaluator.java"
