Classfile /Users/mw/Projects/slang-braindump/.jar/jar11/assemble/slang-braindump/assemble/content/org/scalatest/matchers/dsl/BeWord.class
  Last modified May 29, 2022; size 16062 bytes
  SHA-256 checksum c2119ebf764ecc52a74d650a3cde49ddba35fc38d9ac2c35e304a9c5b63cf9fa
  Compiled from "BeWord.scala"
public final class org.scalatest.matchers.dsl.BeWord
  minor version: 0
  major version: 52
  flags: (0x0031) ACC_PUBLIC, ACC_FINAL, ACC_SUPER
  this_class: #2                          // org/scalatest/matchers/dsl/BeWord
  super_class: #4                         // java/lang/Object
  interfaces: 0, fields: 0, methods: 29, attributes: 5
Constant pool:
    #1 = Utf8               org/scalatest/matchers/dsl/BeWord
    #2 = Class              #1            // org/scalatest/matchers/dsl/BeWord
    #3 = Utf8               java/lang/Object
    #4 = Class              #3            // java/lang/Object
    #5 = Utf8               BeWord.scala
    #6 = Utf8               Lscala/reflect/ScalaSignature;
    #7 = Utf8               bytes
    #8 = Utf8               \u0006\u0005\rEh\u0001\u0002\u0011\"\u0005)BQ!\r\u0001\u0005\u0002IBQ!\u000e\u0001\u0005\u0002YBQ\u0001\u0017\u0001\u0005\u0002eCQa\u0019\u0001\u0005\u0002\u0011DQA\u001c\u0001\u0005\u0002=DQ!\u001f\u0001\u0005\u0002iDq!a\b\u0001\t\u0003\t\t\u0003C\u0004\u0002 \u0001!\t!!\u0010\t\u000f\u0005}\u0001\u0001\"\u0001\u0002V!9\u0011\u0011\u000e\u0001\u0005\u0002\u0005-\u0004bBA5\u0001\u0011\u0005\u0011Q\u000f\u0005\b\u0003S\u0002A\u0011AAB\u0011\u001d\t9\n\u0001C\u0001\u00033Cq!a0\u0001\t\u0003\t\t\rC\u0004\u0002\u0018\u0002!\t!!2\t\u000f\u0005]\u0005\u0001\"\u0001\u0002R\"9\u0011q\u0013\u0001\u0005\u0002\u0005u\u0007bBAL\u0001\u0011\u0005\u0011q\u001d\u0005\b\u0003/\u0003A\u0011AA}\u0011\u001d\t9\n\u0001C\u0001\u0005\u000fAq!a&\u0001\t\u0003\u0011Y\u0001C\u0004\u0003(\u0001!\tA!\u000b\t\u000f\t-\u0003\u0001\"\u0001\u0003N!9\u0011q\u0013\u0001\u0005\u0002\t\u0015\u0004\u0002CAL\u0001\t%\tA!#\t\u0011\u0005]\u0005A!C\u0001\u0007wAq!a&\u0001\t\u0003\u0019i\tC\u0004\u0002\u0018\u0002!\ta!)\t\u000f\u0005]\u0005\u0001\"\u0001\u00046\"9\u0011q\u0013\u0001\u0005\u0002\r%\u0007bBBo\u0001\u0011\u00053q\u001c\u0002\u0007\u0005\u0016<vN\u001d3\u000b\u0005\t\u001a\u0013a\u00013tY*\u0011A%J\u0001\t[\u0006$8\r[3sg*\u0011aeJ\u0001\ng\u000e\fG.\u0019;fgRT\u0011\u0001K\u0001\u0004_J<7\u0001A\n\u0003\u0001-\u0002\"\u0001L\u0018\u000e\u00035R\u0011AL\u0001\u0006g\u000e\fG.Y\u0005\u0003a5\u0012a!\u00118z%\u00164\u0017A\u0002\u001fj]&$h\bF\u00014!\t!\u0004!D\u0001\"\u0003\u0015!C.Z:t+\t9t\b\u0006\u00029-R\u0011\u0011\b\u0013\t\u0004umjT\"A\u0012\n\u0005q\u001a#aB\'bi\u000eDWM\u001d\t\u0003}}b\u0001\u0001B\u0003A\u0005\t\u0007\u0011IA\u0001U#\t\u0011U\t\u0005\u0002-\u0007&\u0011A)\f\u0002\b\u001d>$\b.\u001b8h!\tac)\u0003\u0002H[\t\u0019\u0011I\\=\t\u000f%\u0013\u0011\u0011!a\u0002\u0015\u0006QQM^5eK:\u001cW\rJ\u0019\u0011\u0007-\u001bVH\u0004\u0002M#:\u0011Q\nU\u0007\u0002\u001d*\u0011q*K\u0001\u0007yI|w\u000e\u001e \n\u00039J!AU\u0017\u0002\u000fA\f7m[1hK&\u0011A+\u0016\u0002\t\u001fJ$WM]5oO*\u0011!+\f\u0005\u0006/\n\u0001\r!P\u0001\u0006e&<\u0007\u000e^\u0001\tI\u001d\u0014X-\u0019;feV\u0011!L\u0018\u000b\u00037\n$\"\u0001X0\u0011\u0007iZT\f\u0005\u0002?=\u0012)\u0001i\u0001b\u0001\u0003\"9\u0001mAA\u0001\u0002\b\t\u0017AC3wS\u0012,gnY3%eA\u00191jU/\t\u000b]\u001b\u0001\u0019A/\u0002\u0011\u0011bWm]:%KF,\"!Z5\u0015\u0005\u0019lGCA4k!\rQ4\b\u001b\t\u0003}%$Q\u0001\u0011\u0003C\u0002\u0005Cqa\u001b\u0003\u0002\u0002\u0003\u000fA.\u0001\u0006fm&$WM\\2fIM\u00022aS*i\u0011\u00159F\u00011\u0001i\u0003-!sM]3bi\u0016\u0014H%Z9\u0016\u0005A$HCA9y)\t\u0011X\u000fE\u0002;wM\u0004\"A\u0010;\u0005\u000b\u0001+!\u0019A!\t\u000fY,\u0011\u0011!a\u0002o\u0006QQM^5eK:\u001cW\r\n\u001b\u0011\u0007-\u001b6\u000fC\u0003X\u000b\u0001\u00071/A\u0005%KF$S-\u001d\u0013fcR\u001910a\u0004\u0015\u0005ql\bc\u0001\u001e<\u000b\")aP\u0002a\u0002\u007f\u0006\u0019\u0001o\\:\u0011\t\u0005\u0005\u00111B\u0007\u0003\u0003\u0007QA!!\u0002\u0002\b\u000511o\\;sG\u0016T1!!\u0003(\u0003%\u00198-\u00197bGRL7-\u0003\u0003\u0002\u000e\u0005\r!\u0001\u0003)pg&$\u0018n\u001c8\t\u000b]3\u0001\u0019A#)\u000f\u0019\t\u0019\"!\u0007\u0002\u001cA\u0019A&!\u0006\n\u0007\u0005]QF\u0001\u0006eKB\u0014XmY1uK\u0012\fq!\\3tg\u0006<W-\t\u0002\u0002\u001e\u0005\t9\u0002\u00165fA\u0011,\u0007O]3dCRLwN\u001c\u0011qKJLw\u000e\u001a\u0011g_J\u0004C\u000f[3!E\u0016\u0004S(P\u001f!gftG/\u0019=!Q\u0006\u001c\b%\u001a=qSJ,GM\f\u0011QY\u0016\f7/\u001a\u0011vg\u0016\u00043\u000f[8vY\u0012\u0004S-];bY2\u00023\u000f[8vY\u0012\u0004S(P\u001f-AMDw.\u001e7e\u000bF,\u0018\r\u001c\u0017!g\"|W\u000f\u001c3!E\u0016d\u0003e\u001c:!g\"|W\u000f\u001c3CK\u0002Jgn\u001d;fC\u0012t\u0013!A1\u0015\t\u0005\r\u0012Q\u0007\u000b\u0007\u0003K\t9#a\r\u0011\u0007iZ4\u0006C\u0004\u0002*\u001d\u0001\u001d!a\u000b\u0002\u0015A\u0014X\r\u001e;jM&,\'\u000f\u0005\u0003\u0002.\u0005=RBAA\u0004\u0013\u0011\t\t$a\u0002\u0003\u0015A\u0013X\r\u001e;jM&,\'\u000fC\u0003\u007f\u000f\u0001\u000fq\u0010\u0003\u0004X\u000f\u0001\u0007\u0011q\u0007\t\u0004Y\u0005e\u0012bAA\u001e[\t11+_7c_2,B!a\u0010\u0002FQ!\u0011\u0011IA&!\u0011Q4(a\u0011\u0011\u0007y\n)\u0005B\u0004\u0002H!\u0011\r!!\u0013\u0003\u0003M\u000b\"AQ\u0016\t\u000f\u00055\u0003\u00021\u0001\u0002P\u0005\t\"-\u001a)s_B,\'\u000f^=NCR\u001c\u0007.\u001a:\u0011\u000bi\n\t&a\u0011\n\u0007\u0005M3EA\tCKB\u0013x\u000e]3sifl\u0015\r^2iKJ,B!a\u0016\u0002^Q!\u0011\u0011LA0!\u0011Q4(a\u0017\u0011\u0007y\ni\u0006\u0002\u0004\u0002H%\u0011\r!\u0011\u0005\b\u0003CJ\u0001\u0019AA2\u0003!\tW*\u0019;dQ\u0016\u0014\b#\u0002\u001e\u0002f\u0005m\u0013bAA4G\tA\u0011)T1uG\",\'/\u0001\u0002b]R!\u0011QNA:)\u0019\t)#a\u001c\u0002r!9\u0011\u0011\u0006\u0006A\u0004\u0005-\u0002\"\u0002@\u000b\u0001\by\bBB,\u000b\u0001\u0004\t9$\u0006\u0003\u0002x\u0005uD\u0003BA=\u0003\u007f\u0002BAO\u001e\u0002|A\u0019a(! \u0005\u000f\u0005\u001d3B1\u0001\u0002J!9\u0011QJ\u0006A\u0002\u0005\u0005\u0005#\u0002\u001e\u0002R\u0005mT\u0003BAC\u0003\u0017#B!a\"\u0002\u000eB!!hOAE!\rq\u00141\u0012\u0003\u0007\u0003\u000fb!\u0019A!\t\u000f\u0005=E\u00021\u0001\u0002\u0012\u0006I\u0011M\\\'bi\u000eDWM\u001d\t\u0006u\u0005M\u0015\u0011R\u0005\u0004\u0003+\u001b#!C!o\u001b\u0006$8\r[3s\u0003\u0015\t\u0007\u000f\u001d7z+\u0011\tY*!)\u0015\t\u0005u\u0015Q\u0015\t\u0005um\ny\nE\u0002?\u0003C#a!a)\u000e\u0005\u0004\t%!A+\t\u000f\u0005\u001dV\u00021\u0001\u0002*\u000611\u000f\u001d:fC\u0012\u0004b!a+\u0002:\u0006}e\u0002BAW\u0003ksA!a,\u00024:\u0019Q*!-\n\u0003!J1!!\u0003(\u0013\u0011\t9,a\u0002\u0002\'Q\u0013\u0018\u000e\u001d7f\u000bF,\u0018\r\\:TkB\u0004xN\u001d;\n\t\u0005m\u0016Q\u0018\u0002\u0007\'B\u0014X-\u00193\u000b\t\u0005]\u0016qA\u0001\u0012i\",7+Y7f\u0013:\u001cH/\u00198dK\u0006\u001bH\u0003BA\u0013\u0003\u0007DQa\u0016\bA\u0002-\"B!a2\u0002PB!!hOAe!\ra\u00131Z\u0005\u0004\u0003\u001bl#a\u0002\"p_2,\u0017M\u001c\u0005\u0007/>\u0001\r!!3\u0015\t\u0005\u0015\u00121\u001b\u0005\b\u0003+\u0004\u0002\u0019AAl\u0003\u0005y\u0007c\u0001\u0017\u0002Z&\u0019\u00111\\\u0017\u0003\t9+H\u000e\u001c\u000b\u0005\u0003?\f)\u000f\u0006\u0004\u0002&\u0005\u0005\u00181\u001d\u0005\b\u0003S\t\u00029AA\u0016\u0011\u0015q\u0018\u0003q\u0001\u0000\u0011\u00199\u0016\u00031\u0001\u00028U!\u0011\u0011^Ax)\u0011\tY/!=\u0011\tiZ\u0014Q\u001e\t\u0004}\u0005=H!\u0002!\u0013\u0005\u0004\t\u0005BB,\u0013\u0001\u0004\t\u0019\u0010E\u0003;\u0003k\fi/C\u0002\u0002x\u000e\u0012\u0011BQ3NCR\u001c\u0007.\u001a:\u0016\t\u0005m(\u0011\u0001\u000b\u0005\u0003{\u0014\u0019\u0001\u0005\u0003;w\u0005}\bc\u0001 \u0003\u0002\u0011)\u0001i\u0005b\u0001\u0003\"9\u0011QJ\nA\u0002\t\u0015\u0001#\u0002\u001e\u0002R\u0005}Hc\u0001?\u0003\n!)q\u000b\u0006a\u0001\u000bR!!Q\u0002B\u0010!\u0019!$qB#\u0003\u0014%\u0019!\u0011C\u0011\u0003\u001f5\u000bGo\u00195fe\u001a\u000b7\r^8ssF\u0002BA!\u0006\u0003\u001c5\u0011!q\u0003\u0006\u0004\u00053)\u0013\u0001C3oC\ndWM]:\n\t\tu!q\u0003\u0002\t\'>\u0014H/\u00192mK\"1q+\u0006a\u0001\u0005C\u00012\u0001\u000eB\u0012\u0013\r\u0011)#\t\u0002\u000b\'>\u0014H/\u001a3X_J$\u0017!\u00033fM&tW\rZ!u+\u0019\u0011YCa\u0010\u00032Q!!Q\u0006B%!\u0011Q4Ha\f\u0011\u0007y\u0012\t\u0004B\u0004\u0002$Z\u0011\rAa\r\u0012\u0007\t\u0013)\u0004\r\u0003\u00038\t\u0015\u0003c\u0002\u0017\u0003:\tu\"1I\u0005\u0004\u0005wi#a\u0004)beRL\u0017\r\u001c$v]\u000e$\u0018n\u001c8\u0011\u0007y\u0012y\u0004\u0002\u0004\u0003BY\u0011\r!\u0011\u0002\u0002\u0003B\u0019aH!\u0012\u0005\u0017\t\u001d#\u0011GA\u0001\u0002\u0003\u0015\t!\u0011\u0002\u0004?\u0012\n\u0004BB,\u0017\u0001\u0004\u0011i$\u0001\u0005uQJ|wO\u001c\"z)\u0011\u0011yE!\u0016\u0011\u0007Q\u0012\t&C\u0002\u0003T\u0005\u0012!CU3tk2$xJ\u001a\"f)\"\u0014xn\u001e8Cs\"A!qK\f\u0005\u0002\u0004\u0011I&\u0001\u0003d_\u0012,\u0007#\u0002\u0017\u0003\\\t}\u0013b\u0001B/[\tAAHY=oC6,g\bE\u0002-\u0005CJ1Aa\u0019.\u0005\u0011)f.\u001b;\u0016\r\t\u001d$q\u000fB7)\u0011\u0011IGa \u0011\tiZ$1\u000e\t\u0004}\t5DaBAR1\t\u0007!qN\t\u0004\u0005\nE\u0004\u0007\u0002B:\u0005w\u0002r\u0001\fB\u001d\u0005k\u0012I\bE\u0002?\u0005o\"aA!\u0011\u0019\u0005\u0004\t\u0005c\u0001 \u0003|\u0011Y!Q\u0010B7\u0003\u0003\u0005\tQ!\u0001B\u0005\ryFE\r\u0005\b\u0005\u0003C\u0002\u0019\u0001BB\u0003E\u0011Xm];mi>3G)\u001a4j]\u0016$\u0017\t\u001e\t\u0006i\t\u0015%QO\u0005\u0004\u0005\u000f\u000b#!\u0005*fgVdGo\u00144EK\u001aLg.\u001a3BiR\u0019APa#\t\u000f\t5\u0015\u00041\u0001\u0003\u0010\u0006)\u0011\rV=qKB\"!\u0011\u0013BM!\u0015!$1\u0013BL\u0013\r\u0011)*\t\u0002\u0018%\u0016\u001cX\u000f\u001c;PM\u0006#\u0016\u0010]3J]Z|7-\u0019;j_:\u00042A\u0010BM\t-\u0011YJa#\u0002\u0002\u0003\u0005)\u0011A!\u0003\u0007}#3\u0007K\u0003\u001a\u0005?\u0013\u0019\f\u0005\u0003\u0003\"\n=VB\u0001BR\u0015\u0011\u0011)Ka*\u0002\u0011%tG/\u001a:oC2TAA!+\u0003,\u00061Q.Y2s_NT1A!,.\u0003\u001d\u0011XM\u001a7fGRLAA!-\u0003$\nIQ.Y2s_&k\u0007\u000f\\\u0019\u0012?\tU&q\u0017B^\u0005\u001b\u0014iN!;\u0003|\u000e51\u0002A\u0019\u0007I\tU\u0016F!/\u0002\u000b5\f7M]82\u000fY\u0011)L!0\u0003FF*QEa0\u0003B>\u0011!\u0011Y\u0011\u0003\u0005\u0007\f1\"\\1de>,enZ5oKF*QEa2\u0003J>\u0011!\u0011Z\u0011\u0003\u0005\u0017\fQE^\u001c/a\u0001B\u0013.\u001c9mK6,g\u000e^3eA%t\u0007eU2bY\u0006\u0004#GL\u00192]AjS\nO\u00152\u000fY\u0011)La4\u0003XF*QE!5\u0003T>\u0011!1[\u0011\u0003\u0005+\f\u0001\"[:Ck:$G.Z\u0019\u0006K\te\'1\\\b\u0003\u00057L\u0012\u0001A\u0019\b-\tU&q\u001cBtc\u0015)#\u0011\u001dBr\u001f\t\u0011\u0019/\t\u0002\u0003f\u0006Q\u0011n\u001d\"mC\u000e\\\'m\u001c=2\u000b\u0015\u0012INa72\u000fY\u0011)La;\u0003tF*QE!<\u0003p>\u0011!q^\u0011\u0003\u0005c\f\u0011b\u00197bgNt\u0015-\\32\u000b\u0015\u0012)Pa>\u0010\u0005\t]\u0018E\u0001B}\u0003!z\'o\u001a\u0018tG\u0006d\u0017\r^3ti:j\u0017\r^2iKJ\u001ch\u0006V=qK6\u000bGo\u00195fe6\u000b7M]8%c\u001d1\"Q\u0017B\u007f\u0007\u000b\tT!\nB\u0000\u0007\u0003y!a!\u0001\"\u0005\r\r\u0011AC7fi\"|GMT1nKF*Qea\u0002\u0004\n=\u00111\u0011B\u0011\u0003\u0007\u0017\t\u0001#\u0019+za\u0016l\u0015\r^2iKJLU\u000e\u001d72\u000fY\u0011)la\u0004\u0004\u0018E*Qe!\u0005\u0004\u0014=\u001111C\u0011\u0003\u0007+\t\u0011b]5h]\u0006$XO]32\u0013}\u0011)l!\u0007\u0004(\rE\u0012g\u0002\u0013\u00036\u000em1QD\u0005\u0005\u0007;\u0019y\"\u0001\u0003MSN$(\u0002BB\u0011\u0007G\t\u0011\"[7nkR\f\'\r\\3\u000b\u0007\r\u0015R&\u0001\u0006d_2dWm\u0019;j_:\fta\bB[\u0007S\u0019Y#M\u0004%\u0005k\u001bYb!\b2\u000b\u0015\u001aica\f\u0010\u0005\r=R$A\u00002\u000f}\u0011)la\r\u00046E:AE!.\u0004\u001c\ru\u0011\'B\u0013\u00048\rerBAB\u001d;\u0005qPc\u0001?\u0004>!91q\b\u000eA\u0002\r\u0005\u0013AB1o)f\u0004X\r\r\u0003\u0004D\r-\u0003#\u0002\u001b\u0004F\r%\u0013bAB$C\tA\"+Z:vYR|e-\u00118UsB,\u0017J\u001c<pG\u0006$\u0018n\u001c8\u0011\u0007y\u001aY\u0005B\u0006\u0004N\ru\u0012\u0011!A\u0001\u0006\u0003\t%aA0%i!*!Da(\u0004RE\nrD!.\u0004T\rU31LB1\u0007O\u001aig!\u001f2\r\u0011\u0012),\u000bB]c\u001d1\"QWB,\u00073\nT!\nB`\u0005\u0003\fT!\nBd\u0005\u0013\ftA\u0006B[\u0007;\u001ay&M\u0003&\u0005#\u0014\u0019.M\u0003&\u00053\u0014Y.M\u0004\u0017\u0005k\u001b\u0019g!\u001a2\u000b\u0015\u0012\tOa92\u000b\u0015\u0012INa72\u000fY\u0011)l!\u001b\u0004lE*QE!<\u0003pF*QE!>\u0003xF:aC!.\u0004p\rE\u0014\'B\u0013\u0003\u0000\u000e\u0005\u0011\'B\u0013\u0004t\rUtBAB;C\t\u00199(A\tb]RK\b/Z\'bi\u000eDWM]%na2\ftA\u0006B[\u0007w\u001ai(M\u0003&\u0007#\u0019\u0019\"M\u0005 \u0005k\u001byh!!\u0004\bF:AE!.\u0004\u001c\ru\u0011gB\u0010\u00036\u000e\r5QQ\u0019\bI\tU61DB\u000fc\u0015)3QFB\u0018c\u001dy\"QWBE\u0007\u0017\u000bt\u0001\nB[\u00077\u0019i\"M\u0003&\u0007o\u0019I\u0004\u0006\u0003\u0004\u0010\u000e]\u0005C\u0002\u001b\u0003\u0010\u0015\u001b\t\n\u0005\u0003\u0003\u0016\rM\u0015\u0002BBK\u0005/\u00111BU3bI\u0006\u0014\u0017\u000e\\5us\"91\u0011T\u000eA\u0002\rm\u0015\u0001\u0003:fC\u0012\f\'\r\\3\u0011\u0007Q\u001ai*C\u0002\u0004 \u0006\u0012ABU3bI\u0006\u0014G.Z,pe\u0012$Baa)\u0004,B1AGa\u0004F\u0007K\u0003BA!\u0006\u0004(&!1\u0011\u0016B\f\u0005-9&/\u001b;bE&d\u0017\u000e^=\t\u000f\r5F\u00041\u0001\u00040\u0006AqO]5uC\ndW\rE\u00025\u0007cK1aa-\"\u000519&/\u001b;bE2,wk\u001c:e)\u0011\u00199la0\u0011\rQ\u0012y!RB]!\u0011\u0011)ba/\n\t\ru&q\u0003\u0002\n\u000b6\u0004H/\u001b8fgNDqa!1\u001e\u0001\u0004\u0019\u0019-A\u0003f[B$\u0018\u0010E\u00025\u0007\u000bL1aa2\"\u0005%)U\u000e\u001d;z/>\u0014H\r\u0006\u0003\u0004L\u000eM\u0007C\u0002\u001b\u0003\u0010\u0015\u001bi\r\u0005\u0003\u0003\u0016\r=\u0017\u0002BBi\u0005/\u0011!\u0002R3gS:LG/[8o\u0011\u001d\u0019)N\ba\u0001\u0007/\fq\u0001Z3gS:,G\rE\u00025\u00073L1aa7\"\u0005-!UMZ5oK\u0012<vN\u001d3\u0002\u0011Q|7\u000b\u001e:j]\u001e$\"a!9\u0011\t\r\r81\u001e\b\u0005\u0007K\u001c9\u000f\u0005\u0002N[%\u00191\u0011^\u0017\u0002\rA\u0013X\rZ3g\u0013\u0011\u0019ioa<\u0003\rM#(/\u001b8h\u0015\r\u0019I/\f
    #9 = Utf8               org/scalactic/TripleEqualsSupport$Spread
   #10 = Class              #9            // org/scalactic/TripleEqualsSupport$Spread
   #11 = Utf8               org/scalactic/TripleEqualsSupport
   #12 = Class              #11           // org/scalactic/TripleEqualsSupport
   #13 = Utf8               Spread
   #14 = Utf8               org/scalatest/matchers/dsl/BeWord$$anon$1
   #15 = Class              #14           // org/scalatest/matchers/dsl/BeWord$$anon$1
   #16 = Utf8               org/scalatest/matchers/dsl/BeWord$$anon$10
   #17 = Class              #16           // org/scalatest/matchers/dsl/BeWord$$anon$10
   #18 = Utf8               org/scalatest/matchers/dsl/BeWord$$anon$11
   #19 = Class              #18           // org/scalatest/matchers/dsl/BeWord$$anon$11
   #20 = Utf8               org/scalatest/matchers/dsl/BeWord$$anon$12
   #21 = Class              #20           // org/scalatest/matchers/dsl/BeWord$$anon$12
   #22 = Utf8               org/scalatest/matchers/dsl/BeWord$$anon$13
   #23 = Class              #22           // org/scalatest/matchers/dsl/BeWord$$anon$13
   #24 = Utf8               org/scalatest/matchers/dsl/BeWord$$anon$14
   #25 = Class              #24           // org/scalatest/matchers/dsl/BeWord$$anon$14
   #26 = Utf8               org/scalatest/matchers/dsl/BeWord$$anon$15
   #27 = Class              #26           // org/scalatest/matchers/dsl/BeWord$$anon$15
   #28 = Utf8               org/scalatest/matchers/dsl/BeWord$$anon$16
   #29 = Class              #28           // org/scalatest/matchers/dsl/BeWord$$anon$16
   #30 = Utf8               org/scalatest/matchers/dsl/BeWord$$anon$17
   #31 = Class              #30           // org/scalatest/matchers/dsl/BeWord$$anon$17
   #32 = Utf8               org/scalatest/matchers/dsl/BeWord$$anon$18
   #33 = Class              #32           // org/scalatest/matchers/dsl/BeWord$$anon$18
   #34 = Utf8               org/scalatest/matchers/dsl/BeWord$$anon$19
   #35 = Class              #34           // org/scalatest/matchers/dsl/BeWord$$anon$19
   #36 = Utf8               org/scalatest/matchers/dsl/BeWord$$anon$2
   #37 = Class              #36           // org/scalatest/matchers/dsl/BeWord$$anon$2
   #38 = Utf8               org/scalatest/matchers/dsl/BeWord$$anon$21
   #39 = Class              #38           // org/scalatest/matchers/dsl/BeWord$$anon$21
   #40 = Utf8               org/scalatest/matchers/dsl/BeWord$$anon$22
   #41 = Class              #40           // org/scalatest/matchers/dsl/BeWord$$anon$22
   #42 = Utf8               org/scalatest/matchers/dsl/BeWord$$anon$23
   #43 = Class              #42           // org/scalatest/matchers/dsl/BeWord$$anon$23
   #44 = Utf8               org/scalatest/matchers/dsl/BeWord$$anon$25
   #45 = Class              #44           // org/scalatest/matchers/dsl/BeWord$$anon$25
   #46 = Utf8               org/scalatest/matchers/dsl/BeWord$$anon$27
   #47 = Class              #46           // org/scalatest/matchers/dsl/BeWord$$anon$27
   #48 = Utf8               org/scalatest/matchers/dsl/BeWord$$anon$29
   #49 = Class              #48           // org/scalatest/matchers/dsl/BeWord$$anon$29
   #50 = Utf8               org/scalatest/matchers/dsl/BeWord$$anon$3
   #51 = Class              #50           // org/scalatest/matchers/dsl/BeWord$$anon$3
   #52 = Utf8               org/scalatest/matchers/dsl/BeWord$$anon$4
   #53 = Class              #52           // org/scalatest/matchers/dsl/BeWord$$anon$4
   #54 = Utf8               org/scalatest/matchers/dsl/BeWord$$anon$5
   #55 = Class              #54           // org/scalatest/matchers/dsl/BeWord$$anon$5
   #56 = Utf8               org/scalatest/matchers/dsl/BeWord$$anon$6
   #57 = Class              #56           // org/scalatest/matchers/dsl/BeWord$$anon$6
   #58 = Utf8               org/scalatest/matchers/dsl/BeWord$$anon$7
   #59 = Class              #58           // org/scalatest/matchers/dsl/BeWord$$anon$7
   #60 = Utf8               org/scalatest/matchers/dsl/BeWord$$anon$8
   #61 = Class              #60           // org/scalatest/matchers/dsl/BeWord$$anon$8
   #62 = Utf8               org/scalatest/matchers/dsl/BeWord$$anon$9
   #63 = Class              #62           // org/scalatest/matchers/dsl/BeWord$$anon$9
   #64 = Utf8               $less
   #65 = Utf8               (Ljava/lang/Object;Lscala/math/Ordering;)Lorg/scalatest/matchers/Matcher;
   #66 = Utf8               <T:Ljava/lang/Object;>(TT;Lscala/math/Ordering<TT;>;)Lorg/scalatest/matchers/Matcher<TT;>;
   #67 = Utf8               right
   #68 = Utf8               evidence$1
   #69 = Utf8               <init>
   #70 = Utf8               (Lorg/scalatest/matchers/dsl/BeWord;Lscala/math/Ordering;Ljava/lang/Object;)V
   #71 = NameAndType        #69:#70       // "<init>":(Lorg/scalatest/matchers/dsl/BeWord;Lscala/math/Ordering;Ljava/lang/Object;)V
   #72 = Methodref          #15.#71       // org/scalatest/matchers/dsl/BeWord$$anon$1."<init>":(Lorg/scalatest/matchers/dsl/BeWord;Lscala/math/Ordering;Ljava/lang/Object;)V
   #73 = Utf8               this
   #74 = Utf8               Lorg/scalatest/matchers/dsl/BeWord;
   #75 = Utf8               Ljava/lang/Object;
   #76 = Utf8               Lscala/math/Ordering;
   #77 = Utf8               $greater
   #78 = Utf8               evidence$2
   #79 = Methodref          #37.#71       // org/scalatest/matchers/dsl/BeWord$$anon$2."<init>":(Lorg/scalatest/matchers/dsl/BeWord;Lscala/math/Ordering;Ljava/lang/Object;)V
   #80 = Utf8               $less$eq
   #81 = Utf8               evidence$3
   #82 = Methodref          #51.#71       // org/scalatest/matchers/dsl/BeWord$$anon$3."<init>":(Lorg/scalatest/matchers/dsl/BeWord;Lscala/math/Ordering;Ljava/lang/Object;)V
   #83 = Utf8               $greater$eq
   #84 = Utf8               evidence$4
   #85 = Methodref          #53.#71       // org/scalatest/matchers/dsl/BeWord$$anon$4."<init>":(Lorg/scalatest/matchers/dsl/BeWord;Lscala/math/Ordering;Ljava/lang/Object;)V
   #86 = Utf8               $eq$eq$eq
   #87 = Utf8               (Ljava/lang/Object;Lorg/scalactic/source/Position;)Lorg/scalatest/matchers/Matcher;
   #88 = Utf8               (Ljava/lang/Object;Lorg/scalactic/source/Position;)Lorg/scalatest/matchers/Matcher<Ljava/lang/Object;>;
   #89 = Utf8               pos
   #90 = Utf8               org/scalatest/exceptions/NotAllowedException
   #91 = Class              #90           // org/scalatest/exceptions/NotAllowedException
   #92 = Utf8               org/scalatest/FailureMessages$
   #93 = Class              #92           // org/scalatest/FailureMessages$
   #94 = Utf8               MODULE$
   #95 = Utf8               Lorg/scalatest/FailureMessages$;
   #96 = NameAndType        #94:#95       // MODULE$:Lorg/scalatest/FailureMessages$;
   #97 = Fieldref           #93.#96       // org/scalatest/FailureMessages$.MODULE$:Lorg/scalatest/FailureMessages$;
   #98 = Utf8               beTripleEqualsNotAllowed
   #99 = Utf8               ()Ljava/lang/String;
  #100 = NameAndType        #98:#99       // beTripleEqualsNotAllowed:()Ljava/lang/String;
  #101 = Methodref          #93.#100      // org/scalatest/FailureMessages$.beTripleEqualsNotAllowed:()Ljava/lang/String;
  #102 = Utf8               (Ljava/lang/String;Lorg/scalactic/source/Position;)V
  #103 = NameAndType        #69:#102      // "<init>":(Ljava/lang/String;Lorg/scalactic/source/Position;)V
  #104 = Methodref          #91.#103      // org/scalatest/exceptions/NotAllowedException."<init>":(Ljava/lang/String;Lorg/scalactic/source/Position;)V
  #105 = Utf8               Lorg/scalactic/source/Position;
  #106 = Utf8               a
  #107 = Utf8               (Lscala/Symbol;Lorg/scalactic/Prettifier;Lorg/scalactic/source/Position;)Lorg/scalatest/matchers/Matcher;
  #108 = Utf8               (Lscala/Symbol;Lorg/scalactic/Prettifier;Lorg/scalactic/source/Position;)Lorg/scalatest/matchers/Matcher<Ljava/lang/Object;>;
  #109 = Utf8               prettifier
  #110 = Utf8               (Lorg/scalatest/matchers/dsl/BeWord;Lscala/Symbol;Lorg/scalactic/Prettifier;Lorg/scalactic/source/Position;)V
  #111 = NameAndType        #69:#110      // "<init>":(Lorg/scalatest/matchers/dsl/BeWord;Lscala/Symbol;Lorg/scalactic/Prettifier;Lorg/scalactic/source/Position;)V
  #112 = Methodref          #55.#111      // org/scalatest/matchers/dsl/BeWord$$anon$5."<init>":(Lorg/scalatest/matchers/dsl/BeWord;Lscala/Symbol;Lorg/scalactic/Prettifier;Lorg/scalactic/source/Position;)V
  #113 = Utf8               Lscala/Symbol;
  #114 = Utf8               Lorg/scalactic/Prettifier;
  #115 = Utf8               (Lorg/scalatest/matchers/BePropertyMatcher;)Lorg/scalatest/matchers/Matcher;
  #116 = Utf8               <S:Ljava/lang/Object;>(Lorg/scalatest/matchers/BePropertyMatcher<TS;>;)Lorg/scalatest/matchers/Matcher<TS;>;
  #117 = Utf8               bePropertyMatcher
  #118 = Utf8               (Lorg/scalatest/matchers/dsl/BeWord;Lorg/scalatest/matchers/BePropertyMatcher;)V
  #119 = NameAndType        #69:#118      // "<init>":(Lorg/scalatest/matchers/dsl/BeWord;Lorg/scalatest/matchers/BePropertyMatcher;)V
  #120 = Methodref          #57.#119      // org/scalatest/matchers/dsl/BeWord$$anon$6."<init>":(Lorg/scalatest/matchers/dsl/BeWord;Lorg/scalatest/matchers/BePropertyMatcher;)V
  #121 = Utf8               Lorg/scalatest/matchers/BePropertyMatcher;
  #122 = Utf8               (Lorg/scalatest/matchers/AMatcher;)Lorg/scalatest/matchers/Matcher;
  #123 = Utf8               <S:Ljava/lang/Object;>(Lorg/scalatest/matchers/AMatcher<TS;>;)Lorg/scalatest/matchers/Matcher<TS;>;
  #124 = Utf8               aMatcher
  #125 = Utf8               (Lorg/scalatest/matchers/dsl/BeWord;Lorg/scalatest/matchers/AMatcher;)V
  #126 = NameAndType        #69:#125      // "<init>":(Lorg/scalatest/matchers/dsl/BeWord;Lorg/scalatest/matchers/AMatcher;)V
  #127 = Methodref          #59.#126      // org/scalatest/matchers/dsl/BeWord$$anon$7."<init>":(Lorg/scalatest/matchers/dsl/BeWord;Lorg/scalatest/matchers/AMatcher;)V
  #128 = Utf8               Lorg/scalatest/matchers/AMatcher;
  #129 = Utf8               an
  #130 = Methodref          #61.#111      // org/scalatest/matchers/dsl/BeWord$$anon$8."<init>":(Lorg/scalatest/matchers/dsl/BeWord;Lscala/Symbol;Lorg/scalactic/Prettifier;Lorg/scalactic/source/Position;)V
  #131 = Methodref          #63.#119      // org/scalatest/matchers/dsl/BeWord$$anon$9."<init>":(Lorg/scalatest/matchers/dsl/BeWord;Lorg/scalatest/matchers/BePropertyMatcher;)V
  #132 = Utf8               (Lorg/scalatest/matchers/AnMatcher;)Lorg/scalatest/matchers/Matcher;
  #133 = Utf8               <S:Ljava/lang/Object;>(Lorg/scalatest/matchers/AnMatcher<TS;>;)Lorg/scalatest/matchers/Matcher<TS;>;
  #134 = Utf8               anMatcher
  #135 = Utf8               (Lorg/scalatest/matchers/dsl/BeWord;Lorg/scalatest/matchers/AnMatcher;)V
  #136 = NameAndType        #69:#135      // "<init>":(Lorg/scalatest/matchers/dsl/BeWord;Lorg/scalatest/matchers/AnMatcher;)V
  #137 = Methodref          #17.#136      // org/scalatest/matchers/dsl/BeWord$$anon$10."<init>":(Lorg/scalatest/matchers/dsl/BeWord;Lorg/scalatest/matchers/AnMatcher;)V
  #138 = Utf8               Lorg/scalatest/matchers/AnMatcher;
  #139 = Utf8               apply
  #140 = Utf8               (Lorg/scalactic/TripleEqualsSupport$Spread;)Lorg/scalatest/matchers/Matcher;
  #141 = Utf8               <U:Ljava/lang/Object;>(Lorg/scalactic/TripleEqualsSupport$Spread<TU;>;)Lorg/scalatest/matchers/Matcher<TU;>;
  #142 = Utf8               spread
  #143 = Utf8               (Lorg/scalatest/matchers/dsl/BeWord;Lorg/scalactic/TripleEqualsSupport$Spread;)V
  #144 = NameAndType        #69:#143      // "<init>":(Lorg/scalatest/matchers/dsl/BeWord;Lorg/scalactic/TripleEqualsSupport$Spread;)V
  #145 = Methodref          #19.#144      // org/scalatest/matchers/dsl/BeWord$$anon$11."<init>":(Lorg/scalatest/matchers/dsl/BeWord;Lorg/scalactic/TripleEqualsSupport$Spread;)V
  #146 = Utf8               Lorg/scalactic/TripleEqualsSupport$Spread;
  #147 = Utf8               theSameInstanceAs
  #148 = Utf8               (Ljava/lang/Object;)Lorg/scalatest/matchers/Matcher;
  #149 = Utf8               (Ljava/lang/Object;)Lorg/scalatest/matchers/Matcher<Ljava/lang/Object;>;
  #150 = Utf8               (Lorg/scalatest/matchers/dsl/BeWord;Ljava/lang/Object;)V
  #151 = NameAndType        #69:#150      // "<init>":(Lorg/scalatest/matchers/dsl/BeWord;Ljava/lang/Object;)V
  #152 = Methodref          #21.#151      // org/scalatest/matchers/dsl/BeWord$$anon$12."<init>":(Lorg/scalatest/matchers/dsl/BeWord;Ljava/lang/Object;)V
  #153 = Utf8               (Z)Lorg/scalatest/matchers/Matcher;
  #154 = Utf8               (Z)Lorg/scalatest/matchers/Matcher<Ljava/lang/Object;>;
  #155 = Utf8               (Lorg/scalatest/matchers/dsl/BeWord;Z)V
  #156 = NameAndType        #69:#155      // "<init>":(Lorg/scalatest/matchers/dsl/BeWord;Z)V
  #157 = Methodref          #23.#156      // org/scalatest/matchers/dsl/BeWord$$anon$13."<init>":(Lorg/scalatest/matchers/dsl/BeWord;Z)V
  #158 = Utf8               Z
  #159 = Utf8               (Lscala/runtime/Null$;)Lorg/scalatest/matchers/Matcher;
  #160 = Utf8               (Lscala/runtime/Null$;)Lorg/scalatest/matchers/Matcher<Ljava/lang/Object;>;
  #161 = Utf8               o
  #162 = Utf8               (Lorg/scalatest/matchers/dsl/BeWord;)V
  #163 = NameAndType        #69:#162      // "<init>":(Lorg/scalatest/matchers/dsl/BeWord;)V
  #164 = Methodref          #25.#163      // org/scalatest/matchers/dsl/BeWord$$anon$14."<init>":(Lorg/scalatest/matchers/dsl/BeWord;)V
  #165 = Utf8               Lscala/runtime/Null$;
  #166 = Methodref          #27.#111      // org/scalatest/matchers/dsl/BeWord$$anon$15."<init>":(Lorg/scalatest/matchers/dsl/BeWord;Lscala/Symbol;Lorg/scalactic/Prettifier;Lorg/scalactic/source/Position;)V
  #167 = Utf8               (Lorg/scalatest/matchers/BeMatcher;)Lorg/scalatest/matchers/Matcher;
  #168 = Utf8               <T:Ljava/lang/Object;>(Lorg/scalatest/matchers/BeMatcher<TT;>;)Lorg/scalatest/matchers/Matcher<TT;>;
  #169 = Utf8               (Lorg/scalatest/matchers/dsl/BeWord;Lorg/scalatest/matchers/BeMatcher;)V
  #170 = NameAndType        #69:#169      // "<init>":(Lorg/scalatest/matchers/dsl/BeWord;Lorg/scalatest/matchers/BeMatcher;)V
  #171 = Methodref          #29.#170      // org/scalatest/matchers/dsl/BeWord$$anon$16."<init>":(Lorg/scalatest/matchers/dsl/BeWord;Lorg/scalatest/matchers/BeMatcher;)V
  #172 = Utf8               Lorg/scalatest/matchers/BeMatcher;
  #173 = Utf8               <T:Ljava/lang/Object;>(Lorg/scalatest/matchers/BePropertyMatcher<TT;>;)Lorg/scalatest/matchers/Matcher<TT;>;
  #174 = Methodref          #31.#119      // org/scalatest/matchers/dsl/BeWord$$anon$17."<init>":(Lorg/scalatest/matchers/dsl/BeWord;Lorg/scalatest/matchers/BePropertyMatcher;)V
  #175 = Methodref          #33.#151      // org/scalatest/matchers/dsl/BeWord$$anon$18."<init>":(Lorg/scalatest/matchers/dsl/BeWord;Ljava/lang/Object;)V
  #176 = Utf8               (Lorg/scalatest/matchers/dsl/SortedWord;)Lorg/scalatest/matchers/dsl/MatcherFactory1;
  #177 = Utf8               (Lorg/scalatest/matchers/dsl/SortedWord;)Lorg/scalatest/matchers/dsl/MatcherFactory1<Ljava/lang/Object;Lorg/scalatest/enablers/Sortable;>;
  #178 = Methodref          #35.#163      // org/scalatest/matchers/dsl/BeWord$$anon$19."<init>":(Lorg/scalatest/matchers/dsl/BeWord;)V
  #179 = Utf8               Lorg/scalatest/matchers/dsl/SortedWord;
  #180 = Utf8               definedAt
  #181 = Utf8               <A:Ljava/lang/Object;U::Lscala/PartialFunction<TA;*>;>(TA;)Lorg/scalatest/matchers/Matcher<TU;>;
  #182 = Methodref          #39.#151      // org/scalatest/matchers/dsl/BeWord$$anon$21."<init>":(Lorg/scalatest/matchers/dsl/BeWord;Ljava/lang/Object;)V
  #183 = Utf8               thrownBy
  #184 = Utf8               (Lscala/Function0;)Lorg/scalatest/matchers/dsl/ResultOfBeThrownBy;
  #185 = Utf8               (Lscala/Function0<Lscala/runtime/BoxedUnit;>;)Lorg/scalatest/matchers/dsl/ResultOfBeThrownBy;
  #186 = Utf8               code
  #187 = Utf8               org/scalatest/matchers/dsl/ResultOfBeThrownBy
  #188 = Class              #187          // org/scalatest/matchers/dsl/ResultOfBeThrownBy
  #189 = Utf8               scala/package$
  #190 = Class              #189          // scala/package$
  #191 = Utf8               Lscala/package$;
  #192 = NameAndType        #94:#191      // MODULE$:Lscala/package$;
  #193 = Fieldref           #190.#192     // scala/package$.MODULE$:Lscala/package$;
  #194 = Utf8               Vector
  #195 = Utf8               ()Lscala/collection/immutable/Vector$;
  #196 = NameAndType        #194:#195     // Vector:()Lscala/collection/immutable/Vector$;
  #197 = Methodref          #190.#196     // scala/package$.Vector:()Lscala/collection/immutable/Vector$;
  #198 = Utf8               scala/runtime/ScalaRunTime$
  #199 = Class              #198          // scala/runtime/ScalaRunTime$
  #200 = Utf8               Lscala/runtime/ScalaRunTime$;
  #201 = NameAndType        #94:#200      // MODULE$:Lscala/runtime/ScalaRunTime$;
  #202 = Fieldref           #199.#201     // scala/runtime/ScalaRunTime$.MODULE$:Lscala/runtime/ScalaRunTime$;
  #203 = Utf8               scala/Function0
  #204 = Class              #203          // scala/Function0
  #205 = Utf8               [Ljava/lang/Object;
  #206 = Class              #205          // "[Ljava/lang/Object;"
  #207 = Utf8               wrapRefArray
  #208 = Utf8               ([Ljava/lang/Object;)Lscala/collection/immutable/ArraySeq;
  #209 = NameAndType        #207:#208     // wrapRefArray:([Ljava/lang/Object;)Lscala/collection/immutable/ArraySeq;
  #210 = Methodref          #199.#209     // scala/runtime/ScalaRunTime$.wrapRefArray:([Ljava/lang/Object;)Lscala/collection/immutable/ArraySeq;
  #211 = Utf8               scala/collection/immutable/Vector$
  #212 = Class              #211          // scala/collection/immutable/Vector$
  #213 = Utf8               (Lscala/collection/immutable/Seq;)Ljava/lang/Object;
  #214 = NameAndType        #139:#213     // apply:(Lscala/collection/immutable/Seq;)Ljava/lang/Object;
  #215 = Methodref          #212.#214     // scala/collection/immutable/Vector$.apply:(Lscala/collection/immutable/Seq;)Ljava/lang/Object;
  #216 = Utf8               scala/collection/immutable/IndexedSeq
  #217 = Class              #216          // scala/collection/immutable/IndexedSeq
  #218 = Utf8               (Lscala/collection/immutable/IndexedSeq;)V
  #219 = NameAndType        #69:#218      // "<init>":(Lscala/collection/immutable/IndexedSeq;)V
  #220 = Methodref          #188.#219     // org/scalatest/matchers/dsl/ResultOfBeThrownBy."<init>":(Lscala/collection/immutable/IndexedSeq;)V
  #221 = Utf8               Lscala/Function0;
  #222 = Utf8               (Lorg/scalatest/matchers/dsl/ResultOfDefinedAt;)Lorg/scalatest/matchers/Matcher;
  #223 = Utf8               <A:Ljava/lang/Object;U::Lscala/PartialFunction<TA;*>;>(Lorg/scalatest/matchers/dsl/ResultOfDefinedAt<TA;>;)Lorg/scalatest/matchers/Matcher<TU;>;
  #224 = Utf8               resultOfDefinedAt
  #225 = Utf8               (Lorg/scalatest/matchers/dsl/BeWord;Lorg/scalatest/matchers/dsl/ResultOfDefinedAt;)V
  #226 = NameAndType        #69:#225      // "<init>":(Lorg/scalatest/matchers/dsl/BeWord;Lorg/scalatest/matchers/dsl/ResultOfDefinedAt;)V
  #227 = Methodref          #41.#226      // org/scalatest/matchers/dsl/BeWord$$anon$22."<init>":(Lorg/scalatest/matchers/dsl/BeWord;Lorg/scalatest/matchers/dsl/ResultOfDefinedAt;)V
  #228 = Utf8               Lorg/scalatest/matchers/dsl/ResultOfDefinedAt;
  #229 = Utf8               (Lorg/scalatest/matchers/dsl/ReadableWord;)Lorg/scalatest/matchers/dsl/MatcherFactory1;
  #230 = Utf8               (Lorg/scalatest/matchers/dsl/ReadableWord;)Lorg/scalatest/matchers/dsl/MatcherFactory1<Ljava/lang/Object;Lorg/scalatest/enablers/Readability;>;
  #231 = Utf8               readable
  #232 = Utf8               (Lorg/scalatest/matchers/dsl/BeWord;Lorg/scalatest/matchers/dsl/ReadableWord;)V
  #233 = NameAndType        #69:#232      // "<init>":(Lorg/scalatest/matchers/dsl/BeWord;Lorg/scalatest/matchers/dsl/ReadableWord;)V
  #234 = Methodref          #43.#233      // org/scalatest/matchers/dsl/BeWord$$anon$23."<init>":(Lorg/scalatest/matchers/dsl/BeWord;Lorg/scalatest/matchers/dsl/ReadableWord;)V
  #235 = Utf8               Lorg/scalatest/matchers/dsl/ReadableWord;
  #236 = Utf8               (Lorg/scalatest/matchers/dsl/WritableWord;)Lorg/scalatest/matchers/dsl/MatcherFactory1;
  #237 = Utf8               (Lorg/scalatest/matchers/dsl/WritableWord;)Lorg/scalatest/matchers/dsl/MatcherFactory1<Ljava/lang/Object;Lorg/scalatest/enablers/Writability;>;
  #238 = Utf8               writable
  #239 = Methodref          #45.#163      // org/scalatest/matchers/dsl/BeWord$$anon$25."<init>":(Lorg/scalatest/matchers/dsl/BeWord;)V
  #240 = Utf8               Lorg/scalatest/matchers/dsl/WritableWord;
  #241 = Utf8               (Lorg/scalatest/matchers/dsl/EmptyWord;)Lorg/scalatest/matchers/dsl/MatcherFactory1;
  #242 = Utf8               (Lorg/scalatest/matchers/dsl/EmptyWord;)Lorg/scalatest/matchers/dsl/MatcherFactory1<Ljava/lang/Object;Lorg/scalatest/enablers/Emptiness;>;
  #243 = Utf8               empty
  #244 = Methodref          #47.#163      // org/scalatest/matchers/dsl/BeWord$$anon$27."<init>":(Lorg/scalatest/matchers/dsl/BeWord;)V
  #245 = Utf8               Lorg/scalatest/matchers/dsl/EmptyWord;
  #246 = Utf8               (Lorg/scalatest/matchers/dsl/DefinedWord;)Lorg/scalatest/matchers/dsl/MatcherFactory1;
  #247 = Utf8               (Lorg/scalatest/matchers/dsl/DefinedWord;)Lorg/scalatest/matchers/dsl/MatcherFactory1<Ljava/lang/Object;Lorg/scalatest/enablers/Definition;>;
  #248 = Utf8               defined
  #249 = Methodref          #49.#163      // org/scalatest/matchers/dsl/BeWord$$anon$29."<init>":(Lorg/scalatest/matchers/dsl/BeWord;)V
  #250 = Utf8               Lorg/scalatest/matchers/dsl/DefinedWord;
  #251 = Utf8               toString
  #252 = Utf8               be
  #253 = String             #252          // be
  #254 = Utf8               ()V
  #255 = NameAndType        #69:#254      // "<init>":()V
  #256 = Methodref          #4.#255       // java/lang/Object."<init>":()V
  #257 = Utf8               Code
  #258 = Utf8               LineNumberTable
  #259 = Utf8               LocalVariableTable
  #260 = Utf8               Signature
  #261 = Utf8               MethodParameters
  #262 = Utf8               Deprecated
  #263 = Utf8               InnerClasses
  #264 = Utf8               SourceFile
  #265 = Utf8               RuntimeVisibleAnnotations
  #266 = Utf8               ScalaInlineInfo
  #267 = Utf8               (Lorg/scalatest/matchers/dsl/ResultOfATypeInvocation;)Lorg/scalatest/matchers/Matcher;
  #268 = Utf8               (Lorg/scalatest/matchers/dsl/ResultOfAnTypeInvocation;)Lorg/scalatest/matchers/Matcher;
  #269 = Utf8               ScalaSig
{
  public <T extends java.lang.Object> org.scalatest.matchers.Matcher<T> $less(T, scala.math.Ordering<T>);
    descriptor: (Ljava/lang/Object;Lscala/math/Ordering;)Lorg/scalatest/matchers/Matcher;
    flags: (0x0001) ACC_PUBLIC
    Code:
      stack=5, locals=3, args_size=3
         0: new           #15                 // class org/scalatest/matchers/dsl/BeWord$$anon$1
         3: dup
         4: aconst_null
         5: aload_2
         6: aload_1
         7: invokespecial #72                 // Method org/scalatest/matchers/dsl/BeWord$$anon$1."<init>":(Lorg/scalatest/matchers/dsl/BeWord;Lscala/math/Ordering;Ljava/lang/Object;)V
        10: areturn
      LineNumberTable:
        line 94: 0
      LocalVariableTable:
        Start  Length  Slot  Name   Signature
            0      11     0  this   Lorg/scalatest/matchers/dsl/BeWord;
            0      11     1 right   Ljava/lang/Object;
            0      11     2 evidence$1   Lscala/math/Ordering;
    Signature: #66                          // <T:Ljava/lang/Object;>(TT;Lscala/math/Ordering<TT;>;)Lorg/scalatest/matchers/Matcher<TT;>;
    MethodParameters:
      Name                           Flags
      right                          final
      evidence$1                     final

  public <T extends java.lang.Object> org.scalatest.matchers.Matcher<T> $greater(T, scala.math.Ordering<T>);
    descriptor: (Ljava/lang/Object;Lscala/math/Ordering;)Lorg/scalatest/matchers/Matcher;
    flags: (0x0001) ACC_PUBLIC
    Code:
      stack=5, locals=3, args_size=3
         0: new           #37                 // class org/scalatest/matchers/dsl/BeWord$$anon$2
         3: dup
         4: aconst_null
         5: aload_2
         6: aload_1
         7: invokespecial #79                 // Method org/scalatest/matchers/dsl/BeWord$$anon$2."<init>":(Lorg/scalatest/matchers/dsl/BeWord;Lscala/math/Ordering;Ljava/lang/Object;)V
        10: areturn
      LineNumberTable:
        line 133: 0
      LocalVariableTable:
        Start  Length  Slot  Name   Signature
            0      11     0  this   Lorg/scalatest/matchers/dsl/BeWord;
            0      11     1 right   Ljava/lang/Object;
            0      11     2 evidence$2   Lscala/math/Ordering;
    Signature: #66                          // <T:Ljava/lang/Object;>(TT;Lscala/math/Ordering<TT;>;)Lorg/scalatest/matchers/Matcher<TT;>;
    MethodParameters:
      Name                           Flags
      right                          final
      evidence$2                     final

  public <T extends java.lang.Object> org.scalatest.matchers.Matcher<T> $less$eq(T, scala.math.Ordering<T>);
    descriptor: (Ljava/lang/Object;Lscala/math/Ordering;)Lorg/scalatest/matchers/Matcher;
    flags: (0x0001) ACC_PUBLIC
    Code:
      stack=5, locals=3, args_size=3
         0: new           #51                 // class org/scalatest/matchers/dsl/BeWord$$anon$3
         3: dup
         4: aconst_null
         5: aload_2
         6: aload_1
         7: invokespecial #82                 // Method org/scalatest/matchers/dsl/BeWord$$anon$3."<init>":(Lorg/scalatest/matchers/dsl/BeWord;Lscala/math/Ordering;Ljava/lang/Object;)V
        10: areturn
      LineNumberTable:
        line 172: 0
      LocalVariableTable:
        Start  Length  Slot  Name   Signature
            0      11     0  this   Lorg/scalatest/matchers/dsl/BeWord;
            0      11     1 right   Ljava/lang/Object;
            0      11     2 evidence$3   Lscala/math/Ordering;
    Signature: #66                          // <T:Ljava/lang/Object;>(TT;Lscala/math/Ordering<TT;>;)Lorg/scalatest/matchers/Matcher<TT;>;
    MethodParameters:
      Name                           Flags
      right                          final
      evidence$3                     final

  public <T extends java.lang.Object> org.scalatest.matchers.Matcher<T> $greater$eq(T, scala.math.Ordering<T>);
    descriptor: (Ljava/lang/Object;Lscala/math/Ordering;)Lorg/scalatest/matchers/Matcher;
    flags: (0x0001) ACC_PUBLIC
    Code:
      stack=5, locals=3, args_size=3
         0: new           #53                 // class org/scalatest/matchers/dsl/BeWord$$anon$4
         3: dup
         4: aconst_null
         5: aload_2
         6: aload_1
         7: invokespecial #85                 // Method org/scalatest/matchers/dsl/BeWord$$anon$4."<init>":(Lorg/scalatest/matchers/dsl/BeWord;Lscala/math/Ordering;Ljava/lang/Object;)V
        10: areturn
      LineNumberTable:
        line 211: 0
      LocalVariableTable:
        Start  Length  Slot  Name   Signature
            0      11     0  this   Lorg/scalatest/matchers/dsl/BeWord;
            0      11     1 right   Ljava/lang/Object;
            0      11     2 evidence$4   Lscala/math/Ordering;
    Signature: #66                          // <T:Ljava/lang/Object;>(TT;Lscala/math/Ordering<TT;>;)Lorg/scalatest/matchers/Matcher<TT;>;
    MethodParameters:
      Name                           Flags
      right                          final
      evidence$4                     final

  public org.scalatest.matchers.Matcher<java.lang.Object> $eq$eq$eq(java.lang.Object, org.scalactic.source.Position);
    descriptor: (Ljava/lang/Object;Lorg/scalactic/source/Position;)Lorg/scalatest/matchers/Matcher;
    flags: (0x0001) ACC_PUBLIC
    Code:
      stack=4, locals=3, args_size=3
         0: new           #91                 // class org/scalatest/exceptions/NotAllowedException
         3: dup
         4: getstatic     #97                 // Field org/scalatest/FailureMessages$.MODULE$:Lorg/scalatest/FailureMessages$;
         7: invokevirtual #101                // Method org/scalatest/FailureMessages$.beTripleEqualsNotAllowed:()Ljava/lang/String;
        10: aload_2
        11: invokespecial #104                // Method org/scalatest/exceptions/NotAllowedException."<init>":(Ljava/lang/String;Lorg/scalactic/source/Position;)V
        14: athrow
      LineNumberTable:
        line 238: 0
      LocalVariableTable:
        Start  Length  Slot  Name   Signature
            0      15     0  this   Lorg/scalatest/matchers/dsl/BeWord;
            0      15     1 right   Ljava/lang/Object;
            0      15     2   pos   Lorg/scalactic/source/Position;
    Signature: #88                          // (Ljava/lang/Object;Lorg/scalactic/source/Position;)Lorg/scalatest/matchers/Matcher<Ljava/lang/Object;>;
    Deprecated: true
    MethodParameters:
      Name                           Flags
      right                          final
      pos                            final

  public org.scalatest.matchers.Matcher<java.lang.Object> a(scala.Symbol, org.scalactic.Prettifier, org.scalactic.source.Position);
    descriptor: (Lscala/Symbol;Lorg/scalactic/Prettifier;Lorg/scalactic/source/Position;)Lorg/scalatest/matchers/Matcher;
    flags: (0x0001) ACC_PUBLIC
    Code:
      stack=6, locals=4, args_size=4
         0: new           #55                 // class org/scalatest/matchers/dsl/BeWord$$anon$5
         3: dup
         4: aconst_null
         5: aload_1
         6: aload_2
         7: aload_3
         8: invokespecial #112                // Method org/scalatest/matchers/dsl/BeWord$$anon$5."<init>":(Lorg/scalatest/matchers/dsl/BeWord;Lscala/Symbol;Lorg/scalactic/Prettifier;Lorg/scalactic/source/Position;)V
        11: areturn
      LineNumberTable:
        line 251: 0
      LocalVariableTable:
        Start  Length  Slot  Name   Signature
            0      12     0  this   Lorg/scalatest/matchers/dsl/BeWord;
            0      12     1 right   Lscala/Symbol;
            0      12     2 prettifier   Lorg/scalactic/Prettifier;
            0      12     3   pos   Lorg/scalactic/source/Position;
    Signature: #108                         // (Lscala/Symbol;Lorg/scalactic/Prettifier;Lorg/scalactic/source/Position;)Lorg/scalatest/matchers/Matcher<Ljava/lang/Object;>;
    MethodParameters:
      Name                           Flags
      right                          final
      prettifier                     final
      pos                            final

  public <S extends java.lang.Object> org.scalatest.matchers.Matcher<S> a(org.scalatest.matchers.BePropertyMatcher<S>);
    descriptor: (Lorg/scalatest/matchers/BePropertyMatcher;)Lorg/scalatest/matchers/Matcher;
    flags: (0x0001) ACC_PUBLIC
    Code:
      stack=4, locals=2, args_size=2
         0: new           #57                 // class org/scalatest/matchers/dsl/BeWord$$anon$6
         3: dup
         4: aconst_null
         5: aload_1
         6: invokespecial #120                // Method org/scalatest/matchers/dsl/BeWord$$anon$6."<init>":(Lorg/scalatest/matchers/dsl/BeWord;Lorg/scalatest/matchers/BePropertyMatcher;)V
         9: areturn
      LineNumberTable:
        line 267: 0
      LocalVariableTable:
        Start  Length  Slot  Name   Signature
            0      10     0  this   Lorg/scalatest/matchers/dsl/BeWord;
            0      10     1 bePropertyMatcher   Lorg/scalatest/matchers/BePropertyMatcher;
    Signature: #116                         // <S:Ljava/lang/Object;>(Lorg/scalatest/matchers/BePropertyMatcher<TS;>;)Lorg/scalatest/matchers/Matcher<TS;>;
    MethodParameters:
      Name                           Flags
      bePropertyMatcher              final

  public <S extends java.lang.Object> org.scalatest.matchers.Matcher<S> a(org.scalatest.matchers.AMatcher<S>);
    descriptor: (Lorg/scalatest/matchers/AMatcher;)Lorg/scalatest/matchers/Matcher;
    flags: (0x0001) ACC_PUBLIC
    Code:
      stack=4, locals=2, args_size=2
         0: new           #59                 // class org/scalatest/matchers/dsl/BeWord$$anon$7
         3: dup
         4: aconst_null
         5: aload_1
         6: invokespecial #127                // Method org/scalatest/matchers/dsl/BeWord$$anon$7."<init>":(Lorg/scalatest/matchers/dsl/BeWord;Lorg/scalatest/matchers/AMatcher;)V
         9: areturn
      LineNumberTable:
        line 289: 0
      LocalVariableTable:
        Start  Length  Slot  Name   Signature
            0      10     0  this   Lorg/scalatest/matchers/dsl/BeWord;
            0      10     1 aMatcher   Lorg/scalatest/matchers/AMatcher;
    Signature: #123                         // <S:Ljava/lang/Object;>(Lorg/scalatest/matchers/AMatcher<TS;>;)Lorg/scalatest/matchers/Matcher<TS;>;
    MethodParameters:
      Name                           Flags
      aMatcher                       final

  public org.scalatest.matchers.Matcher<java.lang.Object> an(scala.Symbol, org.scalactic.Prettifier, org.scalactic.source.Position);
    descriptor: (Lscala/Symbol;Lorg/scalactic/Prettifier;Lorg/scalactic/source/Position;)Lorg/scalatest/matchers/Matcher;
    flags: (0x0001) ACC_PUBLIC
    Code:
      stack=6, locals=4, args_size=4
         0: new           #61                 // class org/scalatest/matchers/dsl/BeWord$$anon$8
         3: dup
         4: aconst_null
         5: aload_1
         6: aload_2
         7: aload_3
         8: invokespecial #130                // Method org/scalatest/matchers/dsl/BeWord$$anon$8."<init>":(Lorg/scalatest/matchers/dsl/BeWord;Lscala/Symbol;Lorg/scalactic/Prettifier;Lorg/scalactic/source/Position;)V
        11: areturn
      LineNumberTable:
        line 304: 0
      LocalVariableTable:
        Start  Length  Slot  Name   Signature
            0      12     0  this   Lorg/scalatest/matchers/dsl/BeWord;
            0      12     1 right   Lscala/Symbol;
            0      12     2 prettifier   Lorg/scalactic/Prettifier;
            0      12     3   pos   Lorg/scalactic/source/Position;
    Signature: #108                         // (Lscala/Symbol;Lorg/scalactic/Prettifier;Lorg/scalactic/source/Position;)Lorg/scalatest/matchers/Matcher<Ljava/lang/Object;>;
    MethodParameters:
      Name                           Flags
      right                          final
      prettifier                     final
      pos                            final

  public <S extends java.lang.Object> org.scalatest.matchers.Matcher<S> an(org.scalatest.matchers.BePropertyMatcher<S>);
    descriptor: (Lorg/scalatest/matchers/BePropertyMatcher;)Lorg/scalatest/matchers/Matcher;
    flags: (0x0001) ACC_PUBLIC
    Code:
      stack=4, locals=2, args_size=2
         0: new           #63                 // class org/scalatest/matchers/dsl/BeWord$$anon$9
         3: dup
         4: aconst_null
         5: aload_1
         6: invokespecial #131                // Method org/scalatest/matchers/dsl/BeWord$$anon$9."<init>":(Lorg/scalatest/matchers/dsl/BeWord;Lorg/scalatest/matchers/BePropertyMatcher;)V
         9: areturn
      LineNumberTable:
        line 320: 0
      LocalVariableTable:
        Start  Length  Slot  Name   Signature
            0      10     0  this   Lorg/scalatest/matchers/dsl/BeWord;
            0      10     1 bePropertyMatcher   Lorg/scalatest/matchers/BePropertyMatcher;
    Signature: #116                         // <S:Ljava/lang/Object;>(Lorg/scalatest/matchers/BePropertyMatcher<TS;>;)Lorg/scalatest/matchers/Matcher<TS;>;
    MethodParameters:
      Name                           Flags
      bePropertyMatcher              final

  public <S extends java.lang.Object> org.scalatest.matchers.Matcher<S> an(org.scalatest.matchers.AnMatcher<S>);
    descriptor: (Lorg/scalatest/matchers/AnMatcher;)Lorg/scalatest/matchers/Matcher;
    flags: (0x0001) ACC_PUBLIC
    Code:
      stack=4, locals=2, args_size=2
         0: new           #17                 // class org/scalatest/matchers/dsl/BeWord$$anon$10
         3: dup
         4: aconst_null
         5: aload_1
         6: invokespecial #137                // Method org/scalatest/matchers/dsl/BeWord$$anon$10."<init>":(Lorg/scalatest/matchers/dsl/BeWord;Lorg/scalatest/matchers/AnMatcher;)V
         9: areturn
      LineNumberTable:
        line 342: 0
      LocalVariableTable:
        Start  Length  Slot  Name   Signature
            0      10     0  this   Lorg/scalatest/matchers/dsl/BeWord;
            0      10     1 anMatcher   Lorg/scalatest/matchers/AnMatcher;
    Signature: #133                         // <S:Ljava/lang/Object;>(Lorg/scalatest/matchers/AnMatcher<TS;>;)Lorg/scalatest/matchers/Matcher<TS;>;
    MethodParameters:
      Name                           Flags
      anMatcher                      final

  public <U extends java.lang.Object> org.scalatest.matchers.Matcher<U> apply(org.scalactic.TripleEqualsSupport$Spread<U>);
    descriptor: (Lorg/scalactic/TripleEqualsSupport$Spread;)Lorg/scalatest/matchers/Matcher;
    flags: (0x0001) ACC_PUBLIC
    Code:
      stack=4, locals=2, args_size=2
         0: new           #19                 // class org/scalatest/matchers/dsl/BeWord$$anon$11
         3: dup
         4: aconst_null
         5: aload_1
         6: invokespecial #145                // Method org/scalatest/matchers/dsl/BeWord$$anon$11."<init>":(Lorg/scalatest/matchers/dsl/BeWord;Lorg/scalactic/TripleEqualsSupport$Spread;)V
         9: areturn
      LineNumberTable:
        line 356: 0
      LocalVariableTable:
        Start  Length  Slot  Name   Signature
            0      10     0  this   Lorg/scalatest/matchers/dsl/BeWord;
            0      10     1 spread   Lorg/scalactic/TripleEqualsSupport$Spread;
    Signature: #141                         // <U:Ljava/lang/Object;>(Lorg/scalactic/TripleEqualsSupport$Spread<TU;>;)Lorg/scalatest/matchers/Matcher<TU;>;
    MethodParameters:
      Name                           Flags
      spread                         final

  public org.scalatest.matchers.Matcher<java.lang.Object> theSameInstanceAs(java.lang.Object);
    descriptor: (Ljava/lang/Object;)Lorg/scalatest/matchers/Matcher;
    flags: (0x0001) ACC_PUBLIC
    Code:
      stack=4, locals=2, args_size=2
         0: new           #21                 // class org/scalatest/matchers/dsl/BeWord$$anon$12
         3: dup
         4: aconst_null
         5: aload_1
         6: invokespecial #152                // Method org/scalatest/matchers/dsl/BeWord$$anon$12."<init>":(Lorg/scalatest/matchers/dsl/BeWord;Ljava/lang/Object;)V
         9: areturn
      LineNumberTable:
        line 377: 0
      LocalVariableTable:
        Start  Length  Slot  Name   Signature
            0      10     0  this   Lorg/scalatest/matchers/dsl/BeWord;
            0      10     1 right   Ljava/lang/Object;
    Signature: #149                         // (Ljava/lang/Object;)Lorg/scalatest/matchers/Matcher<Ljava/lang/Object;>;
    MethodParameters:
      Name                           Flags
      right                          final

  public org.scalatest.matchers.Matcher<java.lang.Object> apply(boolean);
    descriptor: (Z)Lorg/scalatest/matchers/Matcher;
    flags: (0x0001) ACC_PUBLIC
    Code:
      stack=4, locals=2, args_size=2
         0: new           #23                 // class org/scalatest/matchers/dsl/BeWord$$anon$13
         3: dup
         4: aconst_null
         5: iload_1
         6: invokespecial #157                // Method org/scalatest/matchers/dsl/BeWord$$anon$13."<init>":(Lorg/scalatest/matchers/dsl/BeWord;Z)V
         9: areturn
      LineNumberTable:
        line 397: 0
      LocalVariableTable:
        Start  Length  Slot  Name   Signature
            0      10     0  this   Lorg/scalatest/matchers/dsl/BeWord;
            0      10     1 right   Z
    Signature: #154                         // (Z)Lorg/scalatest/matchers/Matcher<Ljava/lang/Object;>;
    MethodParameters:
      Name                           Flags
      right                          final

  public org.scalatest.matchers.Matcher<java.lang.Object> apply(scala.runtime.Null$);
    descriptor: (Lscala/runtime/Null$;)Lorg/scalatest/matchers/Matcher;
    flags: (0x0001) ACC_PUBLIC
    Code:
      stack=3, locals=2, args_size=2
         0: new           #25                 // class org/scalatest/matchers/dsl/BeWord$$anon$14
         3: dup
         4: aconst_null
         5: invokespecial #164                // Method org/scalatest/matchers/dsl/BeWord$$anon$14."<init>":(Lorg/scalatest/matchers/dsl/BeWord;)V
         8: areturn
      LineNumberTable:
        line 417: 0
      LocalVariableTable:
        Start  Length  Slot  Name   Signature
            0       9     0  this   Lorg/scalatest/matchers/dsl/BeWord;
            0       9     1     o   Lscala/runtime/Null$;
    Signature: #160                         // (Lscala/runtime/Null$;)Lorg/scalatest/matchers/Matcher<Ljava/lang/Object;>;
    MethodParameters:
      Name                           Flags
      o                              final

  public org.scalatest.matchers.Matcher<java.lang.Object> apply(scala.Symbol, org.scalactic.Prettifier, org.scalactic.source.Position);
    descriptor: (Lscala/Symbol;Lorg/scalactic/Prettifier;Lorg/scalactic/source/Position;)Lorg/scalatest/matchers/Matcher;
    flags: (0x0001) ACC_PUBLIC
    Code:
      stack=6, locals=4, args_size=4
         0: new           #27                 // class org/scalatest/matchers/dsl/BeWord$$anon$15
         3: dup
         4: aconst_null
         5: aload_1
         6: aload_2
         7: aload_3
         8: invokespecial #166                // Method org/scalatest/matchers/dsl/BeWord$$anon$15."<init>":(Lorg/scalatest/matchers/dsl/BeWord;Lscala/Symbol;Lorg/scalactic/Prettifier;Lorg/scalactic/source/Position;)V
        11: areturn
      LineNumberTable:
        line 462: 0
      LocalVariableTable:
        Start  Length  Slot  Name   Signature
            0      12     0  this   Lorg/scalatest/matchers/dsl/BeWord;
            0      12     1 right   Lscala/Symbol;
            0      12     2 prettifier   Lorg/scalactic/Prettifier;
            0      12     3   pos   Lorg/scalactic/source/Position;
    Signature: #108                         // (Lscala/Symbol;Lorg/scalactic/Prettifier;Lorg/scalactic/source/Position;)Lorg/scalatest/matchers/Matcher<Ljava/lang/Object;>;
    MethodParameters:
      Name                           Flags
      right                          final
      prettifier                     final
      pos                            final

  public <T extends java.lang.Object> org.scalatest.matchers.Matcher<T> apply(org.scalatest.matchers.BeMatcher<T>);
    descriptor: (Lorg/scalatest/matchers/BeMatcher;)Lorg/scalatest/matchers/Matcher;
    flags: (0x0001) ACC_PUBLIC
    Code:
      stack=4, locals=2, args_size=2
         0: new           #29                 // class org/scalatest/matchers/dsl/BeWord$$anon$16
         3: dup
         4: aconst_null
         5: aload_1
         6: invokespecial #171                // Method org/scalatest/matchers/dsl/BeWord$$anon$16."<init>":(Lorg/scalatest/matchers/dsl/BeWord;Lorg/scalatest/matchers/BeMatcher;)V
         9: areturn
      LineNumberTable:
        line 478: 0
      LocalVariableTable:
        Start  Length  Slot  Name   Signature
            0      10     0  this   Lorg/scalatest/matchers/dsl/BeWord;
            0      10     1 right   Lorg/scalatest/matchers/BeMatcher;
    Signature: #168                         // <T:Ljava/lang/Object;>(Lorg/scalatest/matchers/BeMatcher<TT;>;)Lorg/scalatest/matchers/Matcher<TT;>;
    MethodParameters:
      Name                           Flags
      right                          final

  public <T extends java.lang.Object> org.scalatest.matchers.Matcher<T> apply(org.scalatest.matchers.BePropertyMatcher<T>);
    descriptor: (Lorg/scalatest/matchers/BePropertyMatcher;)Lorg/scalatest/matchers/Matcher;
    flags: (0x0001) ACC_PUBLIC
    Code:
      stack=4, locals=2, args_size=2
         0: new           #31                 // class org/scalatest/matchers/dsl/BeWord$$anon$17
         3: dup
         4: aconst_null
         5: aload_1
         6: invokespecial #174                // Method org/scalatest/matchers/dsl/BeWord$$anon$17."<init>":(Lorg/scalatest/matchers/dsl/BeWord;Lorg/scalatest/matchers/BePropertyMatcher;)V
         9: areturn
      LineNumberTable:
        line 492: 0
      LocalVariableTable:
        Start  Length  Slot  Name   Signature
            0      10     0  this   Lorg/scalatest/matchers/dsl/BeWord;
            0      10     1 bePropertyMatcher   Lorg/scalatest/matchers/BePropertyMatcher;
    Signature: #173                         // <T:Ljava/lang/Object;>(Lorg/scalatest/matchers/BePropertyMatcher<TT;>;)Lorg/scalatest/matchers/Matcher<TT;>;
    MethodParameters:
      Name                           Flags
      bePropertyMatcher              final

  public org.scalatest.matchers.Matcher<java.lang.Object> apply(java.lang.Object);
    descriptor: (Ljava/lang/Object;)Lorg/scalatest/matchers/Matcher;
    flags: (0x0001) ACC_PUBLIC
    Code:
      stack=4, locals=2, args_size=2
         0: new           #33                 // class org/scalatest/matchers/dsl/BeWord$$anon$18
         3: dup
         4: aconst_null
         5: aload_1
         6: invokespecial #175                // Method org/scalatest/matchers/dsl/BeWord$$anon$18."<init>":(Lorg/scalatest/matchers/dsl/BeWord;Ljava/lang/Object;)V
         9: areturn
      LineNumberTable:
        line 522: 0
      LocalVariableTable:
        Start  Length  Slot  Name   Signature
            0      10     0  this   Lorg/scalatest/matchers/dsl/BeWord;
            0      10     1 right   Ljava/lang/Object;
    Signature: #149                         // (Ljava/lang/Object;)Lorg/scalatest/matchers/Matcher<Ljava/lang/Object;>;
    MethodParameters:
      Name                           Flags
      right                          final

  public org.scalatest.matchers.dsl.MatcherFactory1<java.lang.Object, org.scalatest.enablers.Sortable> apply(org.scalatest.matchers.dsl.SortedWord);
    descriptor: (Lorg/scalatest/matchers/dsl/SortedWord;)Lorg/scalatest/matchers/dsl/MatcherFactory1;
    flags: (0x0001) ACC_PUBLIC
    Code:
      stack=3, locals=2, args_size=2
         0: new           #35                 // class org/scalatest/matchers/dsl/BeWord$$anon$19
         3: dup
         4: aconst_null
         5: invokespecial #178                // Method org/scalatest/matchers/dsl/BeWord$$anon$19."<init>":(Lorg/scalatest/matchers/dsl/BeWord;)V
         8: areturn
      LineNumberTable:
        line 544: 0
      LocalVariableTable:
        Start  Length  Slot  Name   Signature
            0       9     0  this   Lorg/scalatest/matchers/dsl/BeWord;
            0       9     1 right   Lorg/scalatest/matchers/dsl/SortedWord;
    Signature: #177                         // (Lorg/scalatest/matchers/dsl/SortedWord;)Lorg/scalatest/matchers/dsl/MatcherFactory1<Ljava/lang/Object;Lorg/scalatest/enablers/Sortable;>;
    MethodParameters:
      Name                           Flags
      right                          final

  public <A extends java.lang.Object, U extends scala.PartialFunction<A, ?>> org.scalatest.matchers.Matcher<U> definedAt(A);
    descriptor: (Ljava/lang/Object;)Lorg/scalatest/matchers/Matcher;
    flags: (0x0001) ACC_PUBLIC
    Code:
      stack=4, locals=2, args_size=2
         0: new           #39                 // class org/scalatest/matchers/dsl/BeWord$$anon$21
         3: dup
         4: aconst_null
         5: aload_1
         6: invokespecial #182                // Method org/scalatest/matchers/dsl/BeWord$$anon$21."<init>":(Lorg/scalatest/matchers/dsl/BeWord;Ljava/lang/Object;)V
         9: areturn
      LineNumberTable:
        line 570: 0
      LocalVariableTable:
        Start  Length  Slot  Name   Signature
            0      10     0  this   Lorg/scalatest/matchers/dsl/BeWord;
            0      10     1 right   Ljava/lang/Object;
    Signature: #181                         // <A:Ljava/lang/Object;U::Lscala/PartialFunction<TA;*>;>(TA;)Lorg/scalatest/matchers/Matcher<TU;>;
    MethodParameters:
      Name                           Flags
      right                          final

  public org.scalatest.matchers.dsl.ResultOfBeThrownBy thrownBy(scala.Function0<scala.runtime.BoxedUnit>);
    descriptor: (Lscala/Function0;)Lorg/scalatest/matchers/dsl/ResultOfBeThrownBy;
    flags: (0x0001) ACC_PUBLIC
    Code:
      stack=8, locals=2, args_size=2
         0: new           #188                // class org/scalatest/matchers/dsl/ResultOfBeThrownBy
         3: dup
         4: getstatic     #193                // Field scala/package$.MODULE$:Lscala/package$;
         7: invokevirtual #197                // Method scala/package$.Vector:()Lscala/collection/immutable/Vector$;
        10: getstatic     #202                // Field scala/runtime/ScalaRunTime$.MODULE$:Lscala/runtime/ScalaRunTime$;
        13: iconst_1
        14: anewarray     #204                // class scala/Function0
        17: dup
        18: iconst_0
        19: aload_1
        20: aastore
        21: checkcast     #206                // class "[Ljava/lang/Object;"
        24: invokevirtual #210                // Method scala/runtime/ScalaRunTime$.wrapRefArray:([Ljava/lang/Object;)Lscala/collection/immutable/ArraySeq;
        27: invokevirtual #215                // Method scala/collection/immutable/Vector$.apply:(Lscala/collection/immutable/Seq;)Ljava/lang/Object;
        30: checkcast     #217                // class scala/collection/immutable/IndexedSeq
        33: invokespecial #220                // Method org/scalatest/matchers/dsl/ResultOfBeThrownBy."<init>":(Lscala/collection/immutable/IndexedSeq;)V
        36: areturn
      LineNumberTable:
        line 589: 0
      LocalVariableTable:
        Start  Length  Slot  Name   Signature
            0      37     0  this   Lorg/scalatest/matchers/dsl/BeWord;
            0      37     1  code   Lscala/Function0;
    Signature: #185                         // (Lscala/Function0<Lscala/runtime/BoxedUnit;>;)Lorg/scalatest/matchers/dsl/ResultOfBeThrownBy;
    MethodParameters:
      Name                           Flags
      code                           final

  public <A extends java.lang.Object, U extends scala.PartialFunction<A, ?>> org.scalatest.matchers.Matcher<U> apply(org.scalatest.matchers.dsl.ResultOfDefinedAt<A>);
    descriptor: (Lorg/scalatest/matchers/dsl/ResultOfDefinedAt;)Lorg/scalatest/matchers/Matcher;
    flags: (0x0001) ACC_PUBLIC
    Code:
      stack=4, locals=2, args_size=2
         0: new           #41                 // class org/scalatest/matchers/dsl/BeWord$$anon$22
         3: dup
         4: aconst_null
         5: aload_1
         6: invokespecial #227                // Method org/scalatest/matchers/dsl/BeWord$$anon$22."<init>":(Lorg/scalatest/matchers/dsl/BeWord;Lorg/scalatest/matchers/dsl/ResultOfDefinedAt;)V
         9: areturn
      LineNumberTable:
        line 600: 0
      LocalVariableTable:
        Start  Length  Slot  Name   Signature
            0      10     0  this   Lorg/scalatest/matchers/dsl/BeWord;
            0      10     1 resultOfDefinedAt   Lorg/scalatest/matchers/dsl/ResultOfDefinedAt;
    Signature: #223                         // <A:Ljava/lang/Object;U::Lscala/PartialFunction<TA;*>;>(Lorg/scalatest/matchers/dsl/ResultOfDefinedAt<TA;>;)Lorg/scalatest/matchers/Matcher<TU;>;
    MethodParameters:
      Name                           Flags
      resultOfDefinedAt              final

  public org.scalatest.matchers.dsl.MatcherFactory1<java.lang.Object, org.scalatest.enablers.Readability> apply(org.scalatest.matchers.dsl.ReadableWord);
    descriptor: (Lorg/scalatest/matchers/dsl/ReadableWord;)Lorg/scalatest/matchers/dsl/MatcherFactory1;
    flags: (0x0001) ACC_PUBLIC
    Code:
      stack=4, locals=2, args_size=2
         0: new           #43                 // class org/scalatest/matchers/dsl/BeWord$$anon$23
         3: dup
         4: aconst_null
         5: aload_1
         6: invokespecial #234                // Method org/scalatest/matchers/dsl/BeWord$$anon$23."<init>":(Lorg/scalatest/matchers/dsl/BeWord;Lorg/scalatest/matchers/dsl/ReadableWord;)V
         9: areturn
      LineNumberTable:
        line 642: 0
      LocalVariableTable:
        Start  Length  Slot  Name   Signature
            0      10     0  this   Lorg/scalatest/matchers/dsl/BeWord;
            0      10     1 readable   Lorg/scalatest/matchers/dsl/ReadableWord;
    Signature: #230                         // (Lorg/scalatest/matchers/dsl/ReadableWord;)Lorg/scalatest/matchers/dsl/MatcherFactory1<Ljava/lang/Object;Lorg/scalatest/enablers/Readability;>;
    MethodParameters:
      Name                           Flags
      readable                       final

  public org.scalatest.matchers.dsl.MatcherFactory1<java.lang.Object, org.scalatest.enablers.Writability> apply(org.scalatest.matchers.dsl.WritableWord);
    descriptor: (Lorg/scalatest/matchers/dsl/WritableWord;)Lorg/scalatest/matchers/dsl/MatcherFactory1;
    flags: (0x0001) ACC_PUBLIC
    Code:
      stack=3, locals=2, args_size=2
         0: new           #45                 // class org/scalatest/matchers/dsl/BeWord$$anon$25
         3: dup
         4: aconst_null
         5: invokespecial #239                // Method org/scalatest/matchers/dsl/BeWord$$anon$25."<init>":(Lorg/scalatest/matchers/dsl/BeWord;)V
         8: areturn
      LineNumberTable:
        line 668: 0
      LocalVariableTable:
        Start  Length  Slot  Name   Signature
            0       9     0  this   Lorg/scalatest/matchers/dsl/BeWord;
            0       9     1 writable   Lorg/scalatest/matchers/dsl/WritableWord;
    Signature: #237                         // (Lorg/scalatest/matchers/dsl/WritableWord;)Lorg/scalatest/matchers/dsl/MatcherFactory1<Ljava/lang/Object;Lorg/scalatest/enablers/Writability;>;
    MethodParameters:
      Name                           Flags
      writable                       final

  public org.scalatest.matchers.dsl.MatcherFactory1<java.lang.Object, org.scalatest.enablers.Emptiness> apply(org.scalatest.matchers.dsl.EmptyWord);
    descriptor: (Lorg/scalatest/matchers/dsl/EmptyWord;)Lorg/scalatest/matchers/dsl/MatcherFactory1;
    flags: (0x0001) ACC_PUBLIC
    Code:
      stack=3, locals=2, args_size=2
         0: new           #47                 // class org/scalatest/matchers/dsl/BeWord$$anon$27
         3: dup
         4: aconst_null
         5: invokespecial #244                // Method org/scalatest/matchers/dsl/BeWord$$anon$27."<init>":(Lorg/scalatest/matchers/dsl/BeWord;)V
         8: areturn
      LineNumberTable:
        line 694: 0
      LocalVariableTable:
        Start  Length  Slot  Name   Signature
            0       9     0  this   Lorg/scalatest/matchers/dsl/BeWord;
            0       9     1 empty   Lorg/scalatest/matchers/dsl/EmptyWord;
    Signature: #242                         // (Lorg/scalatest/matchers/dsl/EmptyWord;)Lorg/scalatest/matchers/dsl/MatcherFactory1<Ljava/lang/Object;Lorg/scalatest/enablers/Emptiness;>;
    MethodParameters:
      Name                           Flags
      empty                          final

  public org.scalatest.matchers.dsl.MatcherFactory1<java.lang.Object, org.scalatest.enablers.Definition> apply(org.scalatest.matchers.dsl.DefinedWord);
    descriptor: (Lorg/scalatest/matchers/dsl/DefinedWord;)Lorg/scalatest/matchers/dsl/MatcherFactory1;
    flags: (0x0001) ACC_PUBLIC
    Code:
      stack=3, locals=2, args_size=2
         0: new           #49                 // class org/scalatest/matchers/dsl/BeWord$$anon$29
         3: dup
         4: aconst_null
         5: invokespecial #249                // Method org/scalatest/matchers/dsl/BeWord$$anon$29."<init>":(Lorg/scalatest/matchers/dsl/BeWord;)V
         8: areturn
      LineNumberTable:
        line 720: 0
      LocalVariableTable:
        Start  Length  Slot  Name   Signature
            0       9     0  this   Lorg/scalatest/matchers/dsl/BeWord;
            0       9     1 defined   Lorg/scalatest/matchers/dsl/DefinedWord;
    Signature: #247                         // (Lorg/scalatest/matchers/dsl/DefinedWord;)Lorg/scalatest/matchers/dsl/MatcherFactory1<Ljava/lang/Object;Lorg/scalatest/enablers/Definition;>;
    MethodParameters:
      Name                           Flags
      defined                        final

  public java.lang.String toString();
    descriptor: ()Ljava/lang/String;
    flags: (0x0001) ACC_PUBLIC
    Code:
      stack=1, locals=1, args_size=1
         0: ldc           #253                // String be
         2: areturn
      LineNumberTable:
        line 740: 0
      LocalVariableTable:
        Start  Length  Slot  Name   Signature
            0       3     0  this   Lorg/scalatest/matchers/dsl/BeWord;

  public org.scalatest.matchers.dsl.BeWord();
    descriptor: ()V
    flags: (0x0001) ACC_PUBLIC
    Code:
      stack=1, locals=1, args_size=1
         0: aload_0
         1: invokespecial #256                // Method java/lang/Object."<init>":()V
         4: return
      LineNumberTable:
        line 741: 0
        line 65: 4
      LocalVariableTable:
        Start  Length  Slot  Name   Signature
            0       5     0  this   Lorg/scalatest/matchers/dsl/BeWord;
}
InnerClasses:
  public static final #13= #10 of #12;    // Spread=class org/scalactic/TripleEqualsSupport$Spread of class org/scalactic/TripleEqualsSupport
  public final #15;                       // class org/scalatest/matchers/dsl/BeWord$$anon$1
  public final #17;                       // class org/scalatest/matchers/dsl/BeWord$$anon$10
  public final #19;                       // class org/scalatest/matchers/dsl/BeWord$$anon$11
  public final #21;                       // class org/scalatest/matchers/dsl/BeWord$$anon$12
  public final #23;                       // class org/scalatest/matchers/dsl/BeWord$$anon$13
  public final #25;                       // class org/scalatest/matchers/dsl/BeWord$$anon$14
  public final #27;                       // class org/scalatest/matchers/dsl/BeWord$$anon$15
  public final #29;                       // class org/scalatest/matchers/dsl/BeWord$$anon$16
  public final #31;                       // class org/scalatest/matchers/dsl/BeWord$$anon$17
  public final #33;                       // class org/scalatest/matchers/dsl/BeWord$$anon$18
  public final #35;                       // class org/scalatest/matchers/dsl/BeWord$$anon$19
  public final #37;                       // class org/scalatest/matchers/dsl/BeWord$$anon$2
  public final #39;                       // class org/scalatest/matchers/dsl/BeWord$$anon$21
  public final #41;                       // class org/scalatest/matchers/dsl/BeWord$$anon$22
  public final #43;                       // class org/scalatest/matchers/dsl/BeWord$$anon$23
  public final #45;                       // class org/scalatest/matchers/dsl/BeWord$$anon$25
  public final #47;                       // class org/scalatest/matchers/dsl/BeWord$$anon$27
  public final #49;                       // class org/scalatest/matchers/dsl/BeWord$$anon$29
  public final #51;                       // class org/scalatest/matchers/dsl/BeWord$$anon$3
  public final #53;                       // class org/scalatest/matchers/dsl/BeWord$$anon$4
  public final #55;                       // class org/scalatest/matchers/dsl/BeWord$$anon$5
  public final #57;                       // class org/scalatest/matchers/dsl/BeWord$$anon$6
  public final #59;                       // class org/scalatest/matchers/dsl/BeWord$$anon$7
  public final #61;                       // class org/scalatest/matchers/dsl/BeWord$$anon$8
  public final #63;                       // class org/scalatest/matchers/dsl/BeWord$$anon$9
SourceFile: "BeWord.scala"
RuntimeVisibleAnnotations:
  0: #6(#7=s#8)
    scala.reflect.ScalaSignature(
      bytes="\u0006\u0005\rEh\u0001\u0002\u0011\"\u0005)BQ!\r\u0001\u0005\u0002IBQ!\u000e\u0001\u0005\u0002YBQ\u0001\u0017\u0001\u0005\u0002eCQa\u0019\u0001\u0005\u0002\u0011DQA\u001c\u0001\u0005\u0002=DQ!\u001f\u0001\u0005\u0002iDq!a\b\u0001\t\u0003\t\t\u0003C\u0004\u0002 \u0001!\t!!\u0010\t\u000f\u0005}\u0001\u0001\"\u0001\u0002V!9\u0011\u0011\u000e\u0001\u0005\u0002\u0005-\u0004bBA5\u0001\u0011\u0005\u0011Q\u000f\u0005\b\u0003S\u0002A\u0011AAB\u0011\u001d\t9\n\u0001C\u0001\u00033Cq!a0\u0001\t\u0003\t\t\rC\u0004\u0002\u0018\u0002!\t!!2\t\u000f\u0005]\u0005\u0001\"\u0001\u0002R\"9\u0011q\u0013\u0001\u0005\u0002\u0005u\u0007bBAL\u0001\u0011\u0005\u0011q\u001d\u0005\b\u0003/\u0003A\u0011AA}\u0011\u001d\t9\n\u0001C\u0001\u0005\u000fAq!a&\u0001\t\u0003\u0011Y\u0001C\u0004\u0003(\u0001!\tA!\u000b\t\u000f\t-\u0003\u0001\"\u0001\u0003N!9\u0011q\u0013\u0001\u0005\u0002\t\u0015\u0004\u0002CAL\u0001\t%\tA!#\t\u0011\u0005]\u0005A!C\u0001\u0007wAq!a&\u0001\t\u0003\u0019i\tC\u0004\u0002\u0018\u0002!\ta!)\t\u000f\u0005]\u0005\u0001\"\u0001\u00046\"9\u0011q\u0013\u0001\u0005\u0002\r%\u0007bBBo\u0001\u0011\u00053q\u001c\u0002\u0007\u0005\u0016<vN\u001d3\u000b\u0005\t\u001a\u0013a\u00013tY*\u0011A%J\u0001\t[\u0006$8\r[3sg*\u0011aeJ\u0001\ng\u000e\fG.\u0019;fgRT\u0011\u0001K\u0001\u0004_J<7\u0001A\n\u0003\u0001-\u0002\"\u0001L\u0018\u000e\u00035R\u0011AL\u0001\u0006g\u000e\fG.Y\u0005\u0003a5\u0012a!\u00118z%\u00164\u0017A\u0002\u001fj]&$h\bF\u00014!\t!\u0004!D\u0001\"\u0003\u0015!C.Z:t+\t9t\b\u0006\u00029-R\u0011\u0011\b\u0013\t\u0004umjT\"A\u0012\n\u0005q\u001a#aB\'bi\u000eDWM\u001d\t\u0003}}b\u0001\u0001B\u0003A\u0005\t\u0007\u0011IA\u0001U#\t\u0011U\t\u0005\u0002-\u0007&\u0011A)\f\u0002\b\u001d>$\b.\u001b8h!\tac)\u0003\u0002H[\t\u0019\u0011I\\=\t\u000f%\u0013\u0011\u0011!a\u0002\u0015\u0006QQM^5eK:\u001cW\rJ\u0019\u0011\u0007-\u001bVH\u0004\u0002M#:\u0011Q\nU\u0007\u0002\u001d*\u0011q*K\u0001\u0007yI|w\u000e\u001e \n\u00039J!AU\u0017\u0002\u000fA\f7m[1hK&\u0011A+\u0016\u0002\t\u001fJ$WM]5oO*\u0011!+\f\u0005\u0006/\n\u0001\r!P\u0001\u0006e&<\u0007\u000e^\u0001\tI\u001d\u0014X-\u0019;feV\u0011!L\u0018\u000b\u00037\n$\"\u0001X0\u0011\u0007iZT\f\u0005\u0002?=\u0012)\u0001i\u0001b\u0001\u0003\"9\u0001mAA\u0001\u0002\b\t\u0017AC3wS\u0012,gnY3%eA\u00191jU/\t\u000b]\u001b\u0001\u0019A/\u0002\u0011\u0011bWm]:%KF,\"!Z5\u0015\u0005\u0019lGCA4k!\rQ4\b\u001b\t\u0003}%$Q\u0001\u0011\u0003C\u0002\u0005Cqa\u001b\u0003\u0002\u0002\u0003\u000fA.\u0001\u0006fm&$WM\\2fIM\u00022aS*i\u0011\u00159F\u00011\u0001i\u0003-!sM]3bi\u0016\u0014H%Z9\u0016\u0005A$HCA9y)\t\u0011X\u000fE\u0002;wM\u0004\"A\u0010;\u0005\u000b\u0001+!\u0019A!\t\u000fY,\u0011\u0011!a\u0002o\u0006QQM^5eK:\u001cW\r\n\u001b\u0011\u0007-\u001b6\u000fC\u0003X\u000b\u0001\u00071/A\u0005%KF$S-\u001d\u0013fcR\u001910a\u0004\u0015\u0005ql\bc\u0001\u001e<\u000b\")aP\u0002a\u0002\u007f\u0006\u0019\u0001o\\:\u0011\t\u0005\u0005\u00111B\u0007\u0003\u0003\u0007QA!!\u0002\u0002\b\u000511o\\;sG\u0016T1!!\u0003(\u0003%\u00198-\u00197bGRL7-\u0003\u0003\u0002\u000e\u0005\r!\u0001\u0003)pg&$\u0018n\u001c8\t\u000b]3\u0001\u0019A#)\u000f\u0019\t\u0019\"!\u0007\u0002\u001cA\u0019A&!\u0006\n\u0007\u0005]QF\u0001\u0006eKB\u0014XmY1uK\u0012\fq!\\3tg\u0006<W-\t\u0002\u0002\u001e\u0005\t9\u0002\u00165fA\u0011,\u0007O]3dCRLwN\u001c\u0011qKJLw\u000e\u001a\u0011g_J\u0004C\u000f[3!E\u0016\u0004S(P\u001f!gftG/\u0019=!Q\u0006\u001c\b%\u001a=qSJ,GM\f\u0011QY\u0016\f7/\u001a\u0011vg\u0016\u00043\u000f[8vY\u0012\u0004S-];bY2\u00023\u000f[8vY\u0012\u0004S(P\u001f-AMDw.\u001e7e\u000bF,\u0018\r\u001c\u0017!g\"|W\u000f\u001c3!E\u0016d\u0003e\u001c:!g\"|W\u000f\u001c3CK\u0002Jgn\u001d;fC\u0012t\u0013!A1\u0015\t\u0005\r\u0012Q\u0007\u000b\u0007\u0003K\t9#a\r\u0011\u0007iZ4\u0006C\u0004\u0002*\u001d\u0001\u001d!a\u000b\u0002\u0015A\u0014X\r\u001e;jM&,\'\u000f\u0005\u0003\u0002.\u0005=RBAA\u0004\u0013\u0011\t\t$a\u0002\u0003\u0015A\u0013X\r\u001e;jM&,\'\u000fC\u0003\u007f\u000f\u0001\u000fq\u0010\u0003\u0004X\u000f\u0001\u0007\u0011q\u0007\t\u0004Y\u0005e\u0012bAA\u001e[\t11+_7c_2,B!a\u0010\u0002FQ!\u0011\u0011IA&!\u0011Q4(a\u0011\u0011\u0007y\n)\u0005B\u0004\u0002H!\u0011\r!!\u0013\u0003\u0003M\u000b\"AQ\u0016\t\u000f\u00055\u0003\u00021\u0001\u0002P\u0005\t\"-\u001a)s_B,\'\u000f^=NCR\u001c\u0007.\u001a:\u0011\u000bi\n\t&a\u0011\n\u0007\u0005M3EA\tCKB\u0013x\u000e]3sifl\u0015\r^2iKJ,B!a\u0016\u0002^Q!\u0011\u0011LA0!\u0011Q4(a\u0017\u0011\u0007y\ni\u0006\u0002\u0004\u0002H%\u0011\r!\u0011\u0005\b\u0003CJ\u0001\u0019AA2\u0003!\tW*\u0019;dQ\u0016\u0014\b#\u0002\u001e\u0002f\u0005m\u0013bAA4G\tA\u0011)T1uG\",\'/\u0001\u0002b]R!\u0011QNA:)\u0019\t)#a\u001c\u0002r!9\u0011\u0011\u0006\u0006A\u0004\u0005-\u0002\"\u0002@\u000b\u0001\by\bBB,\u000b\u0001\u0004\t9$\u0006\u0003\u0002x\u0005uD\u0003BA=\u0003\u007f\u0002BAO\u001e\u0002|A\u0019a(! \u0005\u000f\u0005\u001d3B1\u0001\u0002J!9\u0011QJ\u0006A\u0002\u0005\u0005\u0005#\u0002\u001e\u0002R\u0005mT\u0003BAC\u0003\u0017#B!a\"\u0002\u000eB!!hOAE!\rq\u00141\u0012\u0003\u0007\u0003\u000fb!\u0019A!\t\u000f\u0005=E\u00021\u0001\u0002\u0012\u0006I\u0011M\\\'bi\u000eDWM\u001d\t\u0006u\u0005M\u0015\u0011R\u0005\u0004\u0003+\u001b#!C!o\u001b\u0006$8\r[3s\u0003\u0015\t\u0007\u000f\u001d7z+\u0011\tY*!)\u0015\t\u0005u\u0015Q\u0015\t\u0005um\ny\nE\u0002?\u0003C#a!a)\u000e\u0005\u0004\t%!A+\t\u000f\u0005\u001dV\u00021\u0001\u0002*\u000611\u000f\u001d:fC\u0012\u0004b!a+\u0002:\u0006}e\u0002BAW\u0003ksA!a,\u00024:\u0019Q*!-\n\u0003!J1!!\u0003(\u0013\u0011\t9,a\u0002\u0002\'Q\u0013\u0018\u000e\u001d7f\u000bF,\u0018\r\\:TkB\u0004xN\u001d;\n\t\u0005m\u0016Q\u0018\u0002\u0007\'B\u0014X-\u00193\u000b\t\u0005]\u0016qA\u0001\u0012i\",7+Y7f\u0013:\u001cH/\u00198dK\u0006\u001bH\u0003BA\u0013\u0003\u0007DQa\u0016\bA\u0002-\"B!a2\u0002PB!!hOAe!\ra\u00131Z\u0005\u0004\u0003\u001bl#a\u0002\"p_2,\u0017M\u001c\u0005\u0007/>\u0001\r!!3\u0015\t\u0005\u0015\u00121\u001b\u0005\b\u0003+\u0004\u0002\u0019AAl\u0003\u0005y\u0007c\u0001\u0017\u0002Z&\u0019\u00111\\\u0017\u0003\t9+H\u000e\u001c\u000b\u0005\u0003?\f)\u000f\u0006\u0004\u0002&\u0005\u0005\u00181\u001d\u0005\b\u0003S\t\u00029AA\u0016\u0011\u0015q\u0018\u0003q\u0001\u0000\u0011\u00199\u0016\u00031\u0001\u00028U!\u0011\u0011^Ax)\u0011\tY/!=\u0011\tiZ\u0014Q\u001e\t\u0004}\u0005=H!\u0002!\u0013\u0005\u0004\t\u0005BB,\u0013\u0001\u0004\t\u0019\u0010E\u0003;\u0003k\fi/C\u0002\u0002x\u000e\u0012\u0011BQ3NCR\u001c\u0007.\u001a:\u0016\t\u0005m(\u0011\u0001\u000b\u0005\u0003{\u0014\u0019\u0001\u0005\u0003;w\u0005}\bc\u0001 \u0003\u0002\u0011)\u0001i\u0005b\u0001\u0003\"9\u0011QJ\nA\u0002\t\u0015\u0001#\u0002\u001e\u0002R\u0005}Hc\u0001?\u0003\n!)q\u000b\u0006a\u0001\u000bR!!Q\u0002B\u0010!\u0019!$qB#\u0003\u0014%\u0019!\u0011C\u0011\u0003\u001f5\u000bGo\u00195fe\u001a\u000b7\r^8ssF\u0002BA!\u0006\u0003\u001c5\u0011!q\u0003\u0006\u0004\u00053)\u0013\u0001C3oC\ndWM]:\n\t\tu!q\u0003\u0002\t\'>\u0014H/\u00192mK\"1q+\u0006a\u0001\u0005C\u00012\u0001\u000eB\u0012\u0013\r\u0011)#\t\u0002\u000b\'>\u0014H/\u001a3X_J$\u0017!\u00033fM&tW\rZ!u+\u0019\u0011YCa\u0010\u00032Q!!Q\u0006B%!\u0011Q4Ha\f\u0011\u0007y\u0012\t\u0004B\u0004\u0002$Z\u0011\rAa\r\u0012\u0007\t\u0013)\u0004\r\u0003\u00038\t\u0015\u0003c\u0002\u0017\u0003:\tu\"1I\u0005\u0004\u0005wi#a\u0004)beRL\u0017\r\u001c$v]\u000e$\u0018n\u001c8\u0011\u0007y\u0012y\u0004\u0002\u0004\u0003BY\u0011\r!\u0011\u0002\u0002\u0003B\u0019aH!\u0012\u0005\u0017\t\u001d#\u0011GA\u0001\u0002\u0003\u0015\t!\u0011\u0002\u0004?\u0012\n\u0004BB,\u0017\u0001\u0004\u0011i$\u0001\u0005uQJ|wO\u001c\"z)\u0011\u0011yE!\u0016\u0011\u0007Q\u0012\t&C\u0002\u0003T\u0005\u0012!CU3tk2$xJ\u001a\"f)\"\u0014xn\u001e8Cs\"A!qK\f\u0005\u0002\u0004\u0011I&\u0001\u0003d_\u0012,\u0007#\u0002\u0017\u0003\\\t}\u0013b\u0001B/[\tAAHY=oC6,g\bE\u0002-\u0005CJ1Aa\u0019.\u0005\u0011)f.\u001b;\u0016\r\t\u001d$q\u000fB7)\u0011\u0011IGa \u0011\tiZ$1\u000e\t\u0004}\t5DaBAR1\t\u0007!qN\t\u0004\u0005\nE\u0004\u0007\u0002B:\u0005w\u0002r\u0001\fB\u001d\u0005k\u0012I\bE\u0002?\u0005o\"aA!\u0011\u0019\u0005\u0004\t\u0005c\u0001 \u0003|\u0011Y!Q\u0010B7\u0003\u0003\u0005\tQ!\u0001B\u0005\ryFE\r\u0005\b\u0005\u0003C\u0002\u0019\u0001BB\u0003E\u0011Xm];mi>3G)\u001a4j]\u0016$\u0017\t\u001e\t\u0006i\t\u0015%QO\u0005\u0004\u0005\u000f\u000b#!\u0005*fgVdGo\u00144EK\u001aLg.\u001a3BiR\u0019APa#\t\u000f\t5\u0015\u00041\u0001\u0003\u0010\u0006)\u0011\rV=qKB\"!\u0011\u0013BM!\u0015!$1\u0013BL\u0013\r\u0011)*\t\u0002\u0018%\u0016\u001cX\u000f\u001c;PM\u0006#\u0016\u0010]3J]Z|7-\u0019;j_:\u00042A\u0010BM\t-\u0011YJa#\u0002\u0002\u0003\u0005)\u0011A!\u0003\u0007}#3\u0007K\u0003\u001a\u0005?\u0013\u0019\f\u0005\u0003\u0003\"\n=VB\u0001BR\u0015\u0011\u0011)Ka*\u0002\u0011%tG/\u001a:oC2TAA!+\u0003,\u00061Q.Y2s_NT1A!,.\u0003\u001d\u0011XM\u001a7fGRLAA!-\u0003$\nIQ.Y2s_&k\u0007\u000f\\\u0019\u0012?\tU&q\u0017B^\u0005\u001b\u0014iN!;\u0003|\u000e51\u0002A\u0019\u0007I\tU\u0016F!/\u0002\u000b5\f7M]82\u000fY\u0011)L!0\u0003FF*QEa0\u0003B>\u0011!\u0011Y\u0011\u0003\u0005\u0007\f1\"\\1de>,enZ5oKF*QEa2\u0003J>\u0011!\u0011Z\u0011\u0003\u0005\u0017\fQE^\u001c/a\u0001B\u0013.\u001c9mK6,g\u000e^3eA%t\u0007eU2bY\u0006\u0004#GL\u00192]AjS\nO\u00152\u000fY\u0011)La4\u0003XF*QE!5\u0003T>\u0011!1[\u0011\u0003\u0005+\f\u0001\"[:Ck:$G.Z\u0019\u0006K\te\'1\\\b\u0003\u00057L\u0012\u0001A\u0019\b-\tU&q\u001cBtc\u0015)#\u0011\u001dBr\u001f\t\u0011\u0019/\t\u0002\u0003f\u0006Q\u0011n\u001d\"mC\u000e\\\'m\u001c=2\u000b\u0015\u0012INa72\u000fY\u0011)La;\u0003tF*QE!<\u0003p>\u0011!q^\u0011\u0003\u0005c\f\u0011b\u00197bgNt\u0015-\\32\u000b\u0015\u0012)Pa>\u0010\u0005\t]\u0018E\u0001B}\u0003!z\'o\u001a\u0018tG\u0006d\u0017\r^3ti:j\u0017\r^2iKJ\u001ch\u0006V=qK6\u000bGo\u00195fe6\u000b7M]8%c\u001d1\"Q\u0017B\u007f\u0007\u000b\tT!\nB\u0000\u0007\u0003y!a!\u0001\"\u0005\r\r\u0011AC7fi\"|GMT1nKF*Qea\u0002\u0004\n=\u00111\u0011B\u0011\u0003\u0007\u0017\t\u0001#\u0019+za\u0016l\u0015\r^2iKJLU\u000e\u001d72\u000fY\u0011)la\u0004\u0004\u0018E*Qe!\u0005\u0004\u0014=\u001111C\u0011\u0003\u0007+\t\u0011b]5h]\u0006$XO]32\u0013}\u0011)l!\u0007\u0004(\rE\u0012g\u0002\u0013\u00036\u000em1QD\u0005\u0005\u0007;\u0019y\"\u0001\u0003MSN$(\u0002BB\u0011\u0007G\t\u0011\"[7nkR\f\'\r\\3\u000b\u0007\r\u0015R&\u0001\u0006d_2dWm\u0019;j_:\fta\bB[\u0007S\u0019Y#M\u0004%\u0005k\u001bYb!\b2\u000b\u0015\u001aica\f\u0010\u0005\r=R$A\u00002\u000f}\u0011)la\r\u00046E:AE!.\u0004\u001c\ru\u0011\'B\u0013\u00048\rerBAB\u001d;\u0005qPc\u0001?\u0004>!91q\b\u000eA\u0002\r\u0005\u0013AB1o)f\u0004X\r\r\u0003\u0004D\r-\u0003#\u0002\u001b\u0004F\r%\u0013bAB$C\tA\"+Z:vYR|e-\u00118UsB,\u0017J\u001c<pG\u0006$\u0018n\u001c8\u0011\u0007y\u001aY\u0005B\u0006\u0004N\ru\u0012\u0011!A\u0001\u0006\u0003\t%aA0%i!*!Da(\u0004RE\nrD!.\u0004T\rU31LB1\u0007O\u001aig!\u001f2\r\u0011\u0012),\u000bB]c\u001d1\"QWB,\u00073\nT!\nB`\u0005\u0003\fT!\nBd\u0005\u0013\ftA\u0006B[\u0007;\u001ay&M\u0003&\u0005#\u0014\u0019.M\u0003&\u00053\u0014Y.M\u0004\u0017\u0005k\u001b\u0019g!\u001a2\u000b\u0015\u0012\tOa92\u000b\u0015\u0012INa72\u000fY\u0011)l!\u001b\u0004lE*QE!<\u0003pF*QE!>\u0003xF:aC!.\u0004p\rE\u0014\'B\u0013\u0003\u0000\u000e\u0005\u0011\'B\u0013\u0004t\rUtBAB;C\t\u00199(A\tb]RK\b/Z\'bi\u000eDWM]%na2\ftA\u0006B[\u0007w\u001ai(M\u0003&\u0007#\u0019\u0019\"M\u0005 \u0005k\u001byh!!\u0004\bF:AE!.\u0004\u001c\ru\u0011gB\u0010\u00036\u000e\r5QQ\u0019\bI\tU61DB\u000fc\u0015)3QFB\u0018c\u001dy\"QWBE\u0007\u0017\u000bt\u0001\nB[\u00077\u0019i\"M\u0003&\u0007o\u0019I\u0004\u0006\u0003\u0004\u0010\u000e]\u0005C\u0002\u001b\u0003\u0010\u0015\u001b\t\n\u0005\u0003\u0003\u0016\rM\u0015\u0002BBK\u0005/\u00111BU3bI\u0006\u0014\u0017\u000e\\5us\"91\u0011T\u000eA\u0002\rm\u0015\u0001\u0003:fC\u0012\f\'\r\\3\u0011\u0007Q\u001ai*C\u0002\u0004 \u0006\u0012ABU3bI\u0006\u0014G.Z,pe\u0012$Baa)\u0004,B1AGa\u0004F\u0007K\u0003BA!\u0006\u0004(&!1\u0011\u0016B\f\u0005-9&/\u001b;bE&d\u0017\u000e^=\t\u000f\r5F\u00041\u0001\u00040\u0006AqO]5uC\ndW\rE\u00025\u0007cK1aa-\"\u000519&/\u001b;bE2,wk\u001c:e)\u0011\u00199la0\u0011\rQ\u0012y!RB]!\u0011\u0011)ba/\n\t\ru&q\u0003\u0002\n\u000b6\u0004H/\u001b8fgNDqa!1\u001e\u0001\u0004\u0019\u0019-A\u0003f[B$\u0018\u0010E\u00025\u0007\u000bL1aa2\"\u0005%)U\u000e\u001d;z/>\u0014H\r\u0006\u0003\u0004L\u000eM\u0007C\u0002\u001b\u0003\u0010\u0015\u001bi\r\u0005\u0003\u0003\u0016\r=\u0017\u0002BBi\u0005/\u0011!\u0002R3gS:LG/[8o\u0011\u001d\u0019)N\ba\u0001\u0007/\fq\u0001Z3gS:,G\rE\u00025\u00073L1aa7\"\u0005-!UMZ5oK\u0012<vN\u001d3\u0002\u0011Q|7\u000b\u001e:j]\u001e$\"a!9\u0011\t\r\r81\u001e\b\u0005\u0007K\u001c9\u000f\u0005\u0002N[%\u00191\u0011^\u0017\u0002\rA\u0013X\rZ3g\u0013\u0011\u0019ioa<\u0003\rM#(/\u001b8h\u0015\r\u0019I/\f"
    )
  ScalaInlineInfo: length = 0x9F (unknown attribute)
   01 01 00 1F 00 56 00 57 01 00 4D 00 41 01 00 53
   00 41 01 00 40 00 41 01 00 50 00 41 01 00 45 00
   FE 01 00 6A 00 7A 01 00 6A 00 73 01 00 6A 00 6B
   01 00 81 00 84 01 00 81 00 73 01 00 81 00 6B 01
   00 8B 00 94 01 00 8B 00 8C 01 00 8B 00 A7 01 00
   8B 00 73 01 00 8B 00 F6 01 00 8B 00 F1 01 00 8B
   00 E5 01 00 8B 01 0B 01 00 8B 01 0C 01 00 8B 00
   DE 01 00 8B 00 B0 01 00 8B 00 EC 01 00 8B 00 6B
   01 00 8B 00 9F 01 00 8B 00 99 01 00 B4 00 94 01
   00 93 00 94 01 00 B7 00 B8 01 00 FB 00 63 01
  ScalaSig: length = 0x3 (unknown attribute)
   05 02 00
