Classfile /Users/mw/Projects/slang-braindump/.jar/jar11/assemble/slang-braindump/assemble/content/org/scalatest/matchers/dsl/ContainWord$$anon$1.class
  Last modified May 29, 2022; size 1686 bytes
  SHA-256 checksum b7033d3a0f8e2fee6eb9f77fa0cac6857f3fb833a57410afe2f7207b32de1de0
  Compiled from "ContainWord.scala"
public final class org.scalatest.matchers.dsl.ContainWord$$anon$1 extends org.scalatest.matchers.dsl.MatcherFactory1<java.lang.Object, org.scalatest.enablers.Containing>
  minor version: 0
  major version: 52
  flags: (0x0031) ACC_PUBLIC, ACC_FINAL, ACC_SUPER
  this_class: #2                          // org/scalatest/matchers/dsl/ContainWord$$anon$1
  super_class: #5                         // org/scalatest/matchers/dsl/MatcherFactory1
  interfaces: 0, fields: 0, methods: 4, attributes: 6
Constant pool:
   #1 = Utf8               org/scalatest/matchers/dsl/ContainWord$$anon$1
   #2 = Class              #1             // org/scalatest/matchers/dsl/ContainWord$$anon$1
   #3 = Utf8               Lorg/scalatest/matchers/dsl/MatcherFactory1<Ljava/lang/Object;Lorg/scalatest/enablers/Containing;>;
   #4 = Utf8               org/scalatest/matchers/dsl/MatcherFactory1
   #5 = Class              #4             // org/scalatest/matchers/dsl/MatcherFactory1
   #6 = Utf8               ContainWord.scala
   #7 = Utf8               org/scalatest/matchers/dsl/ContainWord
   #8 = Class              #7             // org/scalatest/matchers/dsl/ContainWord
   #9 = Utf8               apply
  #10 = Utf8               (Lscala/runtime/Null$;)Lorg/scalatest/matchers/dsl/MatcherFactory1;
  #11 = NameAndType        #9:#10         // apply:(Lscala/runtime/Null$;)Lorg/scalatest/matchers/dsl/MatcherFactory1;
  #12 = Utf8               org/scalatest/matchers/dsl/ContainWord$$anon$1$$anon$2
  #13 = Class              #12            // org/scalatest/matchers/dsl/ContainWord$$anon$1$$anon$2
  #14 = Utf8               matcher
  #15 = Utf8               (Lorg/scalatest/enablers/Containing;)Lorg/scalatest/matchers/Matcher;
  #16 = Utf8               <U:Ljava/lang/Object;>(Lorg/scalatest/enablers/Containing<TU;>;)Lorg/scalatest/matchers/Matcher<TU;>;
  #17 = Utf8               evidence$1
  #18 = Utf8               <init>
  #19 = Utf8               (Lorg/scalatest/matchers/dsl/ContainWord$$anon$1;Lorg/scalatest/enablers/Containing;)V
  #20 = NameAndType        #18:#19        // "<init>":(Lorg/scalatest/matchers/dsl/ContainWord$$anon$1;Lorg/scalatest/enablers/Containing;)V
  #21 = Methodref          #13.#20        // org/scalatest/matchers/dsl/ContainWord$$anon$1$$anon$2."<init>":(Lorg/scalatest/matchers/dsl/ContainWord$$anon$1;Lorg/scalatest/enablers/Containing;)V
  #22 = Utf8               this
  #23 = Utf8               Lorg/scalatest/matchers/dsl/ContainWord$$anon$1;
  #24 = Utf8               Lorg/scalatest/enablers/Containing;
  #25 = Utf8               toString
  #26 = Utf8               ()Ljava/lang/String;
  #27 = Utf8               contain (null)
  #28 = String             #27            // contain (null)
  #29 = Utf8               (Ljava/lang/Object;)Lorg/scalatest/matchers/Matcher;
  #30 = Utf8               org/scalatest/enablers/Containing
  #31 = Class              #30            // org/scalatest/enablers/Containing
  #32 = NameAndType        #14:#15        // matcher:(Lorg/scalatest/enablers/Containing;)Lorg/scalatest/matchers/Matcher;
  #33 = Methodref          #2.#32         // org/scalatest/matchers/dsl/ContainWord$$anon$1.matcher:(Lorg/scalatest/enablers/Containing;)Lorg/scalatest/matchers/Matcher;
  #34 = Utf8               Ljava/lang/Object;
  #35 = Utf8               (Lorg/scalatest/matchers/dsl/ContainWord;)V
  #36 = Utf8               $outer
  #37 = Utf8               ()V
  #38 = NameAndType        #18:#37        // "<init>":()V
  #39 = Methodref          #5.#38         // org/scalatest/matchers/dsl/MatcherFactory1."<init>":()V
  #40 = Utf8               Lorg/scalatest/matchers/dsl/ContainWord;
  #41 = Utf8               Code
  #42 = Utf8               LineNumberTable
  #43 = Utf8               LocalVariableTable
  #44 = Utf8               Signature
  #45 = Utf8               MethodParameters
  #46 = Utf8               InnerClasses
  #47 = Utf8               EnclosingMethod
  #48 = Utf8               SourceFile
  #49 = Utf8               ScalaInlineInfo
  #50 = Utf8               Scala
{
  public <U extends java.lang.Object> org.scalatest.matchers.Matcher<U> matcher(org.scalatest.enablers.Containing<U>);
    descriptor: (Lorg/scalatest/enablers/Containing;)Lorg/scalatest/matchers/Matcher;
    flags: (0x0001) ACC_PUBLIC
    Code:
      stack=4, locals=2, args_size=2
         0: new           #13                 // class org/scalatest/matchers/dsl/ContainWord$$anon$1$$anon$2
         3: dup
         4: aconst_null
         5: aload_1
         6: invokespecial #21                 // Method org/scalatest/matchers/dsl/ContainWord$$anon$1$$anon$2."<init>":(Lorg/scalatest/matchers/dsl/ContainWord$$anon$1;Lorg/scalatest/enablers/Containing;)V
         9: areturn
      LineNumberTable:
        line 51: 0
      LocalVariableTable:
        Start  Length  Slot  Name   Signature
            0      10     0  this   Lorg/scalatest/matchers/dsl/ContainWord$$anon$1;
            0      10     1 evidence$1   Lorg/scalatest/enablers/Containing;
    Signature: #16                          // <U:Ljava/lang/Object;>(Lorg/scalatest/enablers/Containing<TU;>;)Lorg/scalatest/matchers/Matcher<TU;>;
    MethodParameters:
      Name                           Flags
      evidence$1                     final

  public java.lang.String toString();
    descriptor: ()Ljava/lang/String;
    flags: (0x0001) ACC_PUBLIC
    Code:
      stack=1, locals=1, args_size=1
         0: ldc           #28                 // String contain (null)
         2: areturn
      LineNumberTable:
        line 63: 0
      LocalVariableTable:
        Start  Length  Slot  Name   Signature
            0       3     0  this   Lorg/scalatest/matchers/dsl/ContainWord$$anon$1;

  public org.scalatest.matchers.Matcher matcher(java.lang.Object);
    descriptor: (Ljava/lang/Object;)Lorg/scalatest/matchers/Matcher;
    flags: (0x1041) ACC_PUBLIC, ACC_BRIDGE, ACC_SYNTHETIC
    Code:
      stack=2, locals=2, args_size=2
         0: aload_0
         1: aload_1
         2: checkcast     #31                 // class org/scalatest/enablers/Containing
         5: invokevirtual #33                 // Method matcher:(Lorg/scalatest/enablers/Containing;)Lorg/scalatest/matchers/Matcher;
         8: areturn
      LineNumberTable:
        line 49: 0
      LocalVariableTable:
        Start  Length  Slot  Name   Signature
            0       9     0  this   Lorg/scalatest/matchers/dsl/ContainWord$$anon$1;
            0       9     1 evidence$1   Ljava/lang/Object;
    MethodParameters:
      Name                           Flags
      evidence$1                     final

  public org.scalatest.matchers.dsl.ContainWord$$anon$1(org.scalatest.matchers.dsl.ContainWord);
    descriptor: (Lorg/scalatest/matchers/dsl/ContainWord;)V
    flags: (0x0001) ACC_PUBLIC
    Code:
      stack=1, locals=2, args_size=2
         0: aload_0
         1: invokespecial #39                 // Method org/scalatest/matchers/dsl/MatcherFactory1."<init>":()V
         4: return
      LineNumberTable:
        line 49: 0
      LocalVariableTable:
        Start  Length  Slot  Name   Signature
            0       5     0  this   Lorg/scalatest/matchers/dsl/ContainWord$$anon$1;
            0       5     1 $outer   Lorg/scalatest/matchers/dsl/ContainWord;
    MethodParameters:
      Name                           Flags
      $outer                         final synthetic
}
InnerClasses:
  public final #2;                        // class org/scalatest/matchers/dsl/ContainWord$$anon$1
  public final #13;                       // class org/scalatest/matchers/dsl/ContainWord$$anon$1$$anon$2
EnclosingMethod: #8.#11                 // org.scalatest.matchers.dsl.ContainWord.apply
Signature: #3                           // Lorg/scalatest/matchers/dsl/MatcherFactory1<Ljava/lang/Object;Lorg/scalatest/enablers/Containing;>;
SourceFile: "ContainWord.scala"
  ScalaInlineInfo: length = 0x18 (unknown attribute)
   01 01 00 04 00 12 00 23 01 00 0E 00 1D 01 00 0E
   00 0F 01 00 19 00 1A 01
  Scala: length = 0x0 (unknown attribute)

