Classfile /Users/mw/Projects/slang-braindump/.jar/jar11/assemble/slang-braindump/assemble/content/org/scalatest/matchers/dsl/HaveWord$$anon$7.class
  Last modified May 29, 2022; size 24622 bytes
  SHA-256 checksum d44946d38399a0fac82a8f5d6ce3b26a72ff0bdacf4a339e535e85f95a886e16
  Compiled from "HaveWord.scala"
public final class org.scalatest.matchers.dsl.HaveWord$$anon$7 extends java.lang.Object implements org.scalatest.matchers.Matcher<T>
  minor version: 0
  major version: 52
  flags: (0x0031) ACC_PUBLIC, ACC_FINAL, ACC_SUPER
  this_class: #2                          // org/scalatest/matchers/dsl/HaveWord$$anon$7
  super_class: #5                         // java/lang/Object
  interfaces: 1, fields: 2, methods: 61, attributes: 7
Constant pool:
    #1 = Utf8               org/scalatest/matchers/dsl/HaveWord$$anon$7
    #2 = Class              #1            // org/scalatest/matchers/dsl/HaveWord$$anon$7
    #3 = Utf8               Ljava/lang/Object;Lorg/scalatest/matchers/Matcher<TT;>;
    #4 = Utf8               java/lang/Object
    #5 = Class              #4            // java/lang/Object
    #6 = Utf8               org/scalatest/matchers/Matcher
    #7 = Class              #6            // org/scalatest/matchers/Matcher
    #8 = Utf8               HaveWord.scala
    #9 = Utf8               org/scalatest/matchers/dsl/HaveWord
   #10 = Class              #9            // org/scalatest/matchers/dsl/HaveWord
   #11 = Utf8               apply
   #12 = Utf8               (Lorg/scalatest/matchers/HavePropertyMatcher;Lscala/collection/immutable/Seq;)Lorg/scalatest/matchers/Matcher;
   #13 = NameAndType        #11:#12       // apply:(Lorg/scalatest/matchers/HavePropertyMatcher;Lscala/collection/immutable/Seq;)Lorg/scalatest/matchers/Matcher;
   #14 = Utf8               java/lang/invoke/MethodHandles$Lookup
   #15 = Class              #14           // java/lang/invoke/MethodHandles$Lookup
   #16 = Utf8               java/lang/invoke/MethodHandles
   #17 = Class              #16           // java/lang/invoke/MethodHandles
   #18 = Utf8               Lookup
   #19 = Utf8               org/scalatest/matchers/Matcher$AndBeWord
   #20 = Class              #19           // org/scalatest/matchers/Matcher$AndBeWord
   #21 = Utf8               AndBeWord
   #22 = Utf8               org/scalatest/matchers/Matcher$AndContainWord
   #23 = Class              #22           // org/scalatest/matchers/Matcher$AndContainWord
   #24 = Utf8               AndContainWord
   #25 = Utf8               org/scalatest/matchers/Matcher$AndEndWithWord
   #26 = Class              #25           // org/scalatest/matchers/Matcher$AndEndWithWord
   #27 = Utf8               AndEndWithWord
   #28 = Utf8               org/scalatest/matchers/Matcher$AndFullyMatchWord
   #29 = Class              #28           // org/scalatest/matchers/Matcher$AndFullyMatchWord
   #30 = Utf8               AndFullyMatchWord
   #31 = Utf8               org/scalatest/matchers/Matcher$AndHaveWord
   #32 = Class              #31           // org/scalatest/matchers/Matcher$AndHaveWord
   #33 = Utf8               AndHaveWord
   #34 = Utf8               org/scalatest/matchers/Matcher$AndIncludeWord
   #35 = Class              #34           // org/scalatest/matchers/Matcher$AndIncludeWord
   #36 = Utf8               AndIncludeWord
   #37 = Utf8               org/scalatest/matchers/Matcher$AndNotWord
   #38 = Class              #37           // org/scalatest/matchers/Matcher$AndNotWord
   #39 = Utf8               AndNotWord
   #40 = Utf8               org/scalatest/matchers/Matcher$AndStartWithWord
   #41 = Class              #40           // org/scalatest/matchers/Matcher$AndStartWithWord
   #42 = Utf8               AndStartWithWord
   #43 = Utf8               org/scalatest/matchers/Matcher$OrBeWord
   #44 = Class              #43           // org/scalatest/matchers/Matcher$OrBeWord
   #45 = Utf8               OrBeWord
   #46 = Utf8               org/scalatest/matchers/Matcher$OrContainWord
   #47 = Class              #46           // org/scalatest/matchers/Matcher$OrContainWord
   #48 = Utf8               OrContainWord
   #49 = Utf8               org/scalatest/matchers/Matcher$OrEndWithWord
   #50 = Class              #49           // org/scalatest/matchers/Matcher$OrEndWithWord
   #51 = Utf8               OrEndWithWord
   #52 = Utf8               org/scalatest/matchers/Matcher$OrFullyMatchWord
   #53 = Class              #52           // org/scalatest/matchers/Matcher$OrFullyMatchWord
   #54 = Utf8               OrFullyMatchWord
   #55 = Utf8               org/scalatest/matchers/Matcher$OrHaveWord
   #56 = Class              #55           // org/scalatest/matchers/Matcher$OrHaveWord
   #57 = Utf8               OrHaveWord
   #58 = Utf8               org/scalatest/matchers/Matcher$OrIncludeWord
   #59 = Class              #58           // org/scalatest/matchers/Matcher$OrIncludeWord
   #60 = Utf8               OrIncludeWord
   #61 = Utf8               org/scalatest/matchers/Matcher$OrNotWord
   #62 = Class              #61           // org/scalatest/matchers/Matcher$OrNotWord
   #63 = Utf8               OrNotWord
   #64 = Utf8               org/scalatest/matchers/Matcher$OrStartWithWord
   #65 = Class              #64           // org/scalatest/matchers/Matcher$OrStartWithWord
   #66 = Utf8               OrStartWithWord
   #67 = Utf8               firstPropertyMatcher$1
   #68 = Utf8               Lorg/scalatest/matchers/HavePropertyMatcher;
   #69 = Utf8               propertyMatchers$1
   #70 = Utf8               Lscala/collection/immutable/Seq;
   #71 = Utf8               compose
   #72 = Utf8               (Lscala/Function1;)Lorg/scalatest/matchers/Matcher;
   #73 = Utf8               <U:Ljava/lang/Object;>(Lscala/Function1<TU;TT;>;)Lorg/scalatest/matchers/Matcher<TU;>;
   #74 = Utf8               g
   #75 = Utf8               compose$
   #76 = Utf8               (Lorg/scalatest/matchers/Matcher;Lscala/Function1;)Lorg/scalatest/matchers/Matcher;
   #77 = NameAndType        #75:#76       // compose$:(Lorg/scalatest/matchers/Matcher;Lscala/Function1;)Lorg/scalatest/matchers/Matcher;
   #78 = InterfaceMethodref #7.#77        // org/scalatest/matchers/Matcher.compose$:(Lorg/scalatest/matchers/Matcher;Lscala/Function1;)Lorg/scalatest/matchers/Matcher;
   #79 = Utf8               this
   #80 = Utf8               Lorg/scalatest/matchers/dsl/HaveWord$$anon$7;
   #81 = Utf8               Lscala/Function1;
   #82 = Utf8               and
   #83 = Utf8               (Lorg/scalatest/matchers/Matcher;)Lorg/scalatest/matchers/Matcher;
   #84 = Utf8               <U:TT;>(Lorg/scalatest/matchers/Matcher<TU;>;)Lorg/scalatest/matchers/Matcher<TU;>;
   #85 = Utf8               rightMatcher
   #86 = Utf8               and$
   #87 = Utf8               (Lorg/scalatest/matchers/Matcher;Lorg/scalatest/matchers/Matcher;)Lorg/scalatest/matchers/Matcher;
   #88 = NameAndType        #86:#87       // and$:(Lorg/scalatest/matchers/Matcher;Lorg/scalatest/matchers/Matcher;)Lorg/scalatest/matchers/Matcher;
   #89 = InterfaceMethodref #7.#88        // org/scalatest/matchers/Matcher.and$:(Lorg/scalatest/matchers/Matcher;Lorg/scalatest/matchers/Matcher;)Lorg/scalatest/matchers/Matcher;
   #90 = Utf8               Lorg/scalatest/matchers/Matcher;
   #91 = Utf8               (Lorg/scalatest/matchers/dsl/MatcherFactory1;)Lorg/scalatest/matchers/dsl/MatcherFactory1;
   #92 = Utf8               <U:Ljava/lang/Object;TC1:Ljava/lang/Object;>(Lorg/scalatest/matchers/dsl/MatcherFactory1<TU;TTC1;>;)Lorg/scalatest/matchers/dsl/MatcherFactory1<TT;TTC1;>;
   #93 = Utf8               rightMatcherFactory1
   #94 = Utf8               (Lorg/scalatest/matchers/Matcher;Lorg/scalatest/matchers/dsl/MatcherFactory1;)Lorg/scalatest/matchers/dsl/MatcherFactory1;
   #95 = NameAndType        #86:#94       // and$:(Lorg/scalatest/matchers/Matcher;Lorg/scalatest/matchers/dsl/MatcherFactory1;)Lorg/scalatest/matchers/dsl/MatcherFactory1;
   #96 = InterfaceMethodref #7.#95        // org/scalatest/matchers/Matcher.and$:(Lorg/scalatest/matchers/Matcher;Lorg/scalatest/matchers/dsl/MatcherFactory1;)Lorg/scalatest/matchers/dsl/MatcherFactory1;
   #97 = Utf8               Lorg/scalatest/matchers/dsl/MatcherFactory1;
   #98 = Utf8               or
   #99 = Utf8               or$
  #100 = NameAndType        #99:#87       // or$:(Lorg/scalatest/matchers/Matcher;Lorg/scalatest/matchers/Matcher;)Lorg/scalatest/matchers/Matcher;
  #101 = InterfaceMethodref #7.#100       // org/scalatest/matchers/Matcher.or$:(Lorg/scalatest/matchers/Matcher;Lorg/scalatest/matchers/Matcher;)Lorg/scalatest/matchers/Matcher;
  #102 = NameAndType        #99:#94       // or$:(Lorg/scalatest/matchers/Matcher;Lorg/scalatest/matchers/dsl/MatcherFactory1;)Lorg/scalatest/matchers/dsl/MatcherFactory1;
  #103 = InterfaceMethodref #7.#102       // org/scalatest/matchers/Matcher.or$:(Lorg/scalatest/matchers/Matcher;Lorg/scalatest/matchers/dsl/MatcherFactory1;)Lorg/scalatest/matchers/dsl/MatcherFactory1;
  #104 = Utf8               (Lorg/scalatest/matchers/dsl/HaveWord;)Lorg/scalatest/matchers/Matcher$AndHaveWord;
  #105 = Utf8               (Lorg/scalatest/matchers/dsl/HaveWord;)Lorg/scalatest/matchers/Matcher<TT;>.AndHaveWord;
  #106 = Utf8               haveWord
  #107 = Utf8               (Lorg/scalatest/matchers/Matcher;Lorg/scalatest/matchers/dsl/HaveWord;)Lorg/scalatest/matchers/Matcher$AndHaveWord;
  #108 = NameAndType        #86:#107      // and$:(Lorg/scalatest/matchers/Matcher;Lorg/scalatest/matchers/dsl/HaveWord;)Lorg/scalatest/matchers/Matcher$AndHaveWord;
  #109 = InterfaceMethodref #7.#108       // org/scalatest/matchers/Matcher.and$:(Lorg/scalatest/matchers/Matcher;Lorg/scalatest/matchers/dsl/HaveWord;)Lorg/scalatest/matchers/Matcher$AndHaveWord;
  #110 = Utf8               Lorg/scalatest/matchers/dsl/HaveWord;
  #111 = Utf8               (Lorg/scalatest/matchers/dsl/ContainWord;Lorg/scalactic/Prettifier;Lorg/scalactic/source/Position;)Lorg/scalatest/matchers/Matcher$AndContainWord;
  #112 = Utf8               (Lorg/scalatest/matchers/dsl/ContainWord;Lorg/scalactic/Prettifier;Lorg/scalactic/source/Position;)Lorg/scalatest/matchers/Matcher<TT;>.AndContainWord;
  #113 = Utf8               containWord
  #114 = Utf8               prettifier
  #115 = Utf8               pos
  #116 = Utf8               (Lorg/scalatest/matchers/Matcher;Lorg/scalatest/matchers/dsl/ContainWord;Lorg/scalactic/Prettifier;Lorg/scalactic/source/Position;)Lorg/scalatest/matchers/Matcher$AndContainWord;
  #117 = NameAndType        #86:#116      // and$:(Lorg/scalatest/matchers/Matcher;Lorg/scalatest/matchers/dsl/ContainWord;Lorg/scalactic/Prettifier;Lorg/scalactic/source/Position;)Lorg/scalatest/matchers/Matcher$AndContainWord;
  #118 = InterfaceMethodref #7.#117       // org/scalatest/matchers/Matcher.and$:(Lorg/scalatest/matchers/Matcher;Lorg/scalatest/matchers/dsl/ContainWord;Lorg/scalactic/Prettifier;Lorg/scalactic/source/Position;)Lorg/scalatest/matchers/Matcher$AndContainWord;
  #119 = Utf8               Lorg/scalatest/matchers/dsl/ContainWord;
  #120 = Utf8               Lorg/scalactic/Prettifier;
  #121 = Utf8               Lorg/scalactic/source/Position;
  #122 = Utf8               (Lorg/scalatest/matchers/dsl/BeWord;)Lorg/scalatest/matchers/Matcher$AndBeWord;
  #123 = Utf8               (Lorg/scalatest/matchers/dsl/BeWord;)Lorg/scalatest/matchers/Matcher<TT;>.AndBeWord;
  #124 = Utf8               beWord
  #125 = Utf8               (Lorg/scalatest/matchers/Matcher;Lorg/scalatest/matchers/dsl/BeWord;)Lorg/scalatest/matchers/Matcher$AndBeWord;
  #126 = NameAndType        #86:#125      // and$:(Lorg/scalatest/matchers/Matcher;Lorg/scalatest/matchers/dsl/BeWord;)Lorg/scalatest/matchers/Matcher$AndBeWord;
  #127 = InterfaceMethodref #7.#126       // org/scalatest/matchers/Matcher.and$:(Lorg/scalatest/matchers/Matcher;Lorg/scalatest/matchers/dsl/BeWord;)Lorg/scalatest/matchers/Matcher$AndBeWord;
  #128 = Utf8               Lorg/scalatest/matchers/dsl/BeWord;
  #129 = Utf8               (Lorg/scalatest/matchers/dsl/FullyMatchWord;)Lorg/scalatest/matchers/Matcher$AndFullyMatchWord;
  #130 = Utf8               (Lorg/scalatest/matchers/dsl/FullyMatchWord;)Lorg/scalatest/matchers/Matcher<TT;>.AndFullyMatchWord;
  #131 = Utf8               fullyMatchWord
  #132 = Utf8               (Lorg/scalatest/matchers/Matcher;Lorg/scalatest/matchers/dsl/FullyMatchWord;)Lorg/scalatest/matchers/Matcher$AndFullyMatchWord;
  #133 = NameAndType        #86:#132      // and$:(Lorg/scalatest/matchers/Matcher;Lorg/scalatest/matchers/dsl/FullyMatchWord;)Lorg/scalatest/matchers/Matcher$AndFullyMatchWord;
  #134 = InterfaceMethodref #7.#133       // org/scalatest/matchers/Matcher.and$:(Lorg/scalatest/matchers/Matcher;Lorg/scalatest/matchers/dsl/FullyMatchWord;)Lorg/scalatest/matchers/Matcher$AndFullyMatchWord;
  #135 = Utf8               Lorg/scalatest/matchers/dsl/FullyMatchWord;
  #136 = Utf8               (Lorg/scalatest/matchers/dsl/IncludeWord;)Lorg/scalatest/matchers/Matcher$AndIncludeWord;
  #137 = Utf8               (Lorg/scalatest/matchers/dsl/IncludeWord;)Lorg/scalatest/matchers/Matcher<TT;>.AndIncludeWord;
  #138 = Utf8               includeWord
  #139 = Utf8               (Lorg/scalatest/matchers/Matcher;Lorg/scalatest/matchers/dsl/IncludeWord;)Lorg/scalatest/matchers/Matcher$AndIncludeWord;
  #140 = NameAndType        #86:#139      // and$:(Lorg/scalatest/matchers/Matcher;Lorg/scalatest/matchers/dsl/IncludeWord;)Lorg/scalatest/matchers/Matcher$AndIncludeWord;
  #141 = InterfaceMethodref #7.#140       // org/scalatest/matchers/Matcher.and$:(Lorg/scalatest/matchers/Matcher;Lorg/scalatest/matchers/dsl/IncludeWord;)Lorg/scalatest/matchers/Matcher$AndIncludeWord;
  #142 = Utf8               Lorg/scalatest/matchers/dsl/IncludeWord;
  #143 = Utf8               (Lorg/scalatest/matchers/dsl/StartWithWord;)Lorg/scalatest/matchers/Matcher$AndStartWithWord;
  #144 = Utf8               (Lorg/scalatest/matchers/dsl/StartWithWord;)Lorg/scalatest/matchers/Matcher<TT;>.AndStartWithWord;
  #145 = Utf8               startWithWord
  #146 = Utf8               (Lorg/scalatest/matchers/Matcher;Lorg/scalatest/matchers/dsl/StartWithWord;)Lorg/scalatest/matchers/Matcher$AndStartWithWord;
  #147 = NameAndType        #86:#146      // and$:(Lorg/scalatest/matchers/Matcher;Lorg/scalatest/matchers/dsl/StartWithWord;)Lorg/scalatest/matchers/Matcher$AndStartWithWord;
  #148 = InterfaceMethodref #7.#147       // org/scalatest/matchers/Matcher.and$:(Lorg/scalatest/matchers/Matcher;Lorg/scalatest/matchers/dsl/StartWithWord;)Lorg/scalatest/matchers/Matcher$AndStartWithWord;
  #149 = Utf8               Lorg/scalatest/matchers/dsl/StartWithWord;
  #150 = Utf8               (Lorg/scalatest/matchers/dsl/EndWithWord;)Lorg/scalatest/matchers/Matcher$AndEndWithWord;
  #151 = Utf8               (Lorg/scalatest/matchers/dsl/EndWithWord;)Lorg/scalatest/matchers/Matcher<TT;>.AndEndWithWord;
  #152 = Utf8               endWithWord
  #153 = Utf8               (Lorg/scalatest/matchers/Matcher;Lorg/scalatest/matchers/dsl/EndWithWord;)Lorg/scalatest/matchers/Matcher$AndEndWithWord;
  #154 = NameAndType        #86:#153      // and$:(Lorg/scalatest/matchers/Matcher;Lorg/scalatest/matchers/dsl/EndWithWord;)Lorg/scalatest/matchers/Matcher$AndEndWithWord;
  #155 = InterfaceMethodref #7.#154       // org/scalatest/matchers/Matcher.and$:(Lorg/scalatest/matchers/Matcher;Lorg/scalatest/matchers/dsl/EndWithWord;)Lorg/scalatest/matchers/Matcher$AndEndWithWord;
  #156 = Utf8               Lorg/scalatest/matchers/dsl/EndWithWord;
  #157 = Utf8               (Lorg/scalatest/matchers/dsl/NotWord;)Lorg/scalatest/matchers/Matcher$AndNotWord;
  #158 = Utf8               (Lorg/scalatest/matchers/dsl/NotWord;)Lorg/scalatest/matchers/Matcher<TT;>.AndNotWord;
  #159 = Utf8               notWord
  #160 = Utf8               (Lorg/scalatest/matchers/Matcher;Lorg/scalatest/matchers/dsl/NotWord;)Lorg/scalatest/matchers/Matcher$AndNotWord;
  #161 = NameAndType        #86:#160      // and$:(Lorg/scalatest/matchers/Matcher;Lorg/scalatest/matchers/dsl/NotWord;)Lorg/scalatest/matchers/Matcher$AndNotWord;
  #162 = InterfaceMethodref #7.#161       // org/scalatest/matchers/Matcher.and$:(Lorg/scalatest/matchers/Matcher;Lorg/scalatest/matchers/dsl/NotWord;)Lorg/scalatest/matchers/Matcher$AndNotWord;
  #163 = Utf8               Lorg/scalatest/matchers/dsl/NotWord;
  #164 = Utf8               (Lorg/scalatest/matchers/dsl/ExistWord;)Lorg/scalatest/matchers/dsl/MatcherFactory1;
  #165 = Utf8               (Lorg/scalatest/matchers/dsl/ExistWord;)Lorg/scalatest/matchers/dsl/MatcherFactory1<TT;Lorg/scalatest/enablers/Existence;>;
  #166 = Utf8               existWord
  #167 = Utf8               (Lorg/scalatest/matchers/Matcher;Lorg/scalatest/matchers/dsl/ExistWord;)Lorg/scalatest/matchers/dsl/MatcherFactory1;
  #168 = NameAndType        #86:#167      // and$:(Lorg/scalatest/matchers/Matcher;Lorg/scalatest/matchers/dsl/ExistWord;)Lorg/scalatest/matchers/dsl/MatcherFactory1;
  #169 = InterfaceMethodref #7.#168       // org/scalatest/matchers/Matcher.and$:(Lorg/scalatest/matchers/Matcher;Lorg/scalatest/matchers/dsl/ExistWord;)Lorg/scalatest/matchers/dsl/MatcherFactory1;
  #170 = Utf8               Lorg/scalatest/matchers/dsl/ExistWord;
  #171 = Utf8               (Lorg/scalatest/matchers/dsl/ResultOfNotExist;)Lorg/scalatest/matchers/dsl/MatcherFactory1;
  #172 = Utf8               (Lorg/scalatest/matchers/dsl/ResultOfNotExist;)Lorg/scalatest/matchers/dsl/MatcherFactory1<TT;Lorg/scalatest/enablers/Existence;>;
  #173 = Utf8               notExist
  #174 = Utf8               (Lorg/scalatest/matchers/Matcher;Lorg/scalatest/matchers/dsl/ResultOfNotExist;)Lorg/scalatest/matchers/dsl/MatcherFactory1;
  #175 = NameAndType        #86:#174      // and$:(Lorg/scalatest/matchers/Matcher;Lorg/scalatest/matchers/dsl/ResultOfNotExist;)Lorg/scalatest/matchers/dsl/MatcherFactory1;
  #176 = InterfaceMethodref #7.#175       // org/scalatest/matchers/Matcher.and$:(Lorg/scalatest/matchers/Matcher;Lorg/scalatest/matchers/dsl/ResultOfNotExist;)Lorg/scalatest/matchers/dsl/MatcherFactory1;
  #177 = Utf8               Lorg/scalatest/matchers/dsl/ResultOfNotExist;
  #178 = Utf8               (Lorg/scalatest/matchers/dsl/HaveWord;)Lorg/scalatest/matchers/Matcher$OrHaveWord;
  #179 = Utf8               (Lorg/scalatest/matchers/dsl/HaveWord;)Lorg/scalatest/matchers/Matcher<TT;>.OrHaveWord;
  #180 = Utf8               (Lorg/scalatest/matchers/Matcher;Lorg/scalatest/matchers/dsl/HaveWord;)Lorg/scalatest/matchers/Matcher$OrHaveWord;
  #181 = NameAndType        #99:#180      // or$:(Lorg/scalatest/matchers/Matcher;Lorg/scalatest/matchers/dsl/HaveWord;)Lorg/scalatest/matchers/Matcher$OrHaveWord;
  #182 = InterfaceMethodref #7.#181       // org/scalatest/matchers/Matcher.or$:(Lorg/scalatest/matchers/Matcher;Lorg/scalatest/matchers/dsl/HaveWord;)Lorg/scalatest/matchers/Matcher$OrHaveWord;
  #183 = Utf8               (Lorg/scalatest/matchers/dsl/ContainWord;Lorg/scalactic/Prettifier;Lorg/scalactic/source/Position;)Lorg/scalatest/matchers/Matcher$OrContainWord;
  #184 = Utf8               (Lorg/scalatest/matchers/dsl/ContainWord;Lorg/scalactic/Prettifier;Lorg/scalactic/source/Position;)Lorg/scalatest/matchers/Matcher<TT;>.OrContainWord;
  #185 = Utf8               (Lorg/scalatest/matchers/Matcher;Lorg/scalatest/matchers/dsl/ContainWord;Lorg/scalactic/Prettifier;Lorg/scalactic/source/Position;)Lorg/scalatest/matchers/Matcher$OrContainWord;
  #186 = NameAndType        #99:#185      // or$:(Lorg/scalatest/matchers/Matcher;Lorg/scalatest/matchers/dsl/ContainWord;Lorg/scalactic/Prettifier;Lorg/scalactic/source/Position;)Lorg/scalatest/matchers/Matcher$OrContainWord;
  #187 = InterfaceMethodref #7.#186       // org/scalatest/matchers/Matcher.or$:(Lorg/scalatest/matchers/Matcher;Lorg/scalatest/matchers/dsl/ContainWord;Lorg/scalactic/Prettifier;Lorg/scalactic/source/Position;)Lorg/scalatest/matchers/Matcher$OrContainWord;
  #188 = Utf8               (Lorg/scalatest/matchers/dsl/BeWord;)Lorg/scalatest/matchers/Matcher$OrBeWord;
  #189 = Utf8               (Lorg/scalatest/matchers/dsl/BeWord;)Lorg/scalatest/matchers/Matcher<TT;>.OrBeWord;
  #190 = Utf8               (Lorg/scalatest/matchers/Matcher;Lorg/scalatest/matchers/dsl/BeWord;)Lorg/scalatest/matchers/Matcher$OrBeWord;
  #191 = NameAndType        #99:#190      // or$:(Lorg/scalatest/matchers/Matcher;Lorg/scalatest/matchers/dsl/BeWord;)Lorg/scalatest/matchers/Matcher$OrBeWord;
  #192 = InterfaceMethodref #7.#191       // org/scalatest/matchers/Matcher.or$:(Lorg/scalatest/matchers/Matcher;Lorg/scalatest/matchers/dsl/BeWord;)Lorg/scalatest/matchers/Matcher$OrBeWord;
  #193 = Utf8               (Lorg/scalatest/matchers/dsl/FullyMatchWord;)Lorg/scalatest/matchers/Matcher$OrFullyMatchWord;
  #194 = Utf8               (Lorg/scalatest/matchers/dsl/FullyMatchWord;)Lorg/scalatest/matchers/Matcher<TT;>.OrFullyMatchWord;
  #195 = Utf8               (Lorg/scalatest/matchers/Matcher;Lorg/scalatest/matchers/dsl/FullyMatchWord;)Lorg/scalatest/matchers/Matcher$OrFullyMatchWord;
  #196 = NameAndType        #99:#195      // or$:(Lorg/scalatest/matchers/Matcher;Lorg/scalatest/matchers/dsl/FullyMatchWord;)Lorg/scalatest/matchers/Matcher$OrFullyMatchWord;
  #197 = InterfaceMethodref #7.#196       // org/scalatest/matchers/Matcher.or$:(Lorg/scalatest/matchers/Matcher;Lorg/scalatest/matchers/dsl/FullyMatchWord;)Lorg/scalatest/matchers/Matcher$OrFullyMatchWord;
  #198 = Utf8               (Lorg/scalatest/matchers/dsl/IncludeWord;)Lorg/scalatest/matchers/Matcher$OrIncludeWord;
  #199 = Utf8               (Lorg/scalatest/matchers/dsl/IncludeWord;)Lorg/scalatest/matchers/Matcher<TT;>.OrIncludeWord;
  #200 = Utf8               (Lorg/scalatest/matchers/Matcher;Lorg/scalatest/matchers/dsl/IncludeWord;)Lorg/scalatest/matchers/Matcher$OrIncludeWord;
  #201 = NameAndType        #99:#200      // or$:(Lorg/scalatest/matchers/Matcher;Lorg/scalatest/matchers/dsl/IncludeWord;)Lorg/scalatest/matchers/Matcher$OrIncludeWord;
  #202 = InterfaceMethodref #7.#201       // org/scalatest/matchers/Matcher.or$:(Lorg/scalatest/matchers/Matcher;Lorg/scalatest/matchers/dsl/IncludeWord;)Lorg/scalatest/matchers/Matcher$OrIncludeWord;
  #203 = Utf8               (Lorg/scalatest/matchers/dsl/StartWithWord;)Lorg/scalatest/matchers/Matcher$OrStartWithWord;
  #204 = Utf8               (Lorg/scalatest/matchers/dsl/StartWithWord;)Lorg/scalatest/matchers/Matcher<TT;>.OrStartWithWord;
  #205 = Utf8               (Lorg/scalatest/matchers/Matcher;Lorg/scalatest/matchers/dsl/StartWithWord;)Lorg/scalatest/matchers/Matcher$OrStartWithWord;
  #206 = NameAndType        #99:#205      // or$:(Lorg/scalatest/matchers/Matcher;Lorg/scalatest/matchers/dsl/StartWithWord;)Lorg/scalatest/matchers/Matcher$OrStartWithWord;
  #207 = InterfaceMethodref #7.#206       // org/scalatest/matchers/Matcher.or$:(Lorg/scalatest/matchers/Matcher;Lorg/scalatest/matchers/dsl/StartWithWord;)Lorg/scalatest/matchers/Matcher$OrStartWithWord;
  #208 = Utf8               (Lorg/scalatest/matchers/dsl/EndWithWord;)Lorg/scalatest/matchers/Matcher$OrEndWithWord;
  #209 = Utf8               (Lorg/scalatest/matchers/dsl/EndWithWord;)Lorg/scalatest/matchers/Matcher<TT;>.OrEndWithWord;
  #210 = Utf8               (Lorg/scalatest/matchers/Matcher;Lorg/scalatest/matchers/dsl/EndWithWord;)Lorg/scalatest/matchers/Matcher$OrEndWithWord;
  #211 = NameAndType        #99:#210      // or$:(Lorg/scalatest/matchers/Matcher;Lorg/scalatest/matchers/dsl/EndWithWord;)Lorg/scalatest/matchers/Matcher$OrEndWithWord;
  #212 = InterfaceMethodref #7.#211       // org/scalatest/matchers/Matcher.or$:(Lorg/scalatest/matchers/Matcher;Lorg/scalatest/matchers/dsl/EndWithWord;)Lorg/scalatest/matchers/Matcher$OrEndWithWord;
  #213 = Utf8               (Lorg/scalatest/matchers/dsl/NotWord;)Lorg/scalatest/matchers/Matcher$OrNotWord;
  #214 = Utf8               (Lorg/scalatest/matchers/dsl/NotWord;)Lorg/scalatest/matchers/Matcher<TT;>.OrNotWord;
  #215 = Utf8               (Lorg/scalatest/matchers/Matcher;Lorg/scalatest/matchers/dsl/NotWord;)Lorg/scalatest/matchers/Matcher$OrNotWord;
  #216 = NameAndType        #99:#215      // or$:(Lorg/scalatest/matchers/Matcher;Lorg/scalatest/matchers/dsl/NotWord;)Lorg/scalatest/matchers/Matcher$OrNotWord;
  #217 = InterfaceMethodref #7.#216       // org/scalatest/matchers/Matcher.or$:(Lorg/scalatest/matchers/Matcher;Lorg/scalatest/matchers/dsl/NotWord;)Lorg/scalatest/matchers/Matcher$OrNotWord;
  #218 = NameAndType        #99:#167      // or$:(Lorg/scalatest/matchers/Matcher;Lorg/scalatest/matchers/dsl/ExistWord;)Lorg/scalatest/matchers/dsl/MatcherFactory1;
  #219 = InterfaceMethodref #7.#218       // org/scalatest/matchers/Matcher.or$:(Lorg/scalatest/matchers/Matcher;Lorg/scalatest/matchers/dsl/ExistWord;)Lorg/scalatest/matchers/dsl/MatcherFactory1;
  #220 = NameAndType        #99:#174      // or$:(Lorg/scalatest/matchers/Matcher;Lorg/scalatest/matchers/dsl/ResultOfNotExist;)Lorg/scalatest/matchers/dsl/MatcherFactory1;
  #221 = InterfaceMethodref #7.#220       // org/scalatest/matchers/Matcher.or$:(Lorg/scalatest/matchers/Matcher;Lorg/scalatest/matchers/dsl/ResultOfNotExist;)Lorg/scalatest/matchers/dsl/MatcherFactory1;
  #222 = Utf8               mapResult
  #223 = Utf8               (Lscala/Function1<Lorg/scalatest/matchers/MatchResult;Lorg/scalatest/matchers/MatchResult;>;)Lorg/scalatest/matchers/Matcher<TT;>;
  #224 = Utf8               prettify
  #225 = Utf8               mapResult$
  #226 = NameAndType        #225:#76      // mapResult$:(Lorg/scalatest/matchers/Matcher;Lscala/Function1;)Lorg/scalatest/matchers/Matcher;
  #227 = InterfaceMethodref #7.#226       // org/scalatest/matchers/Matcher.mapResult$:(Lorg/scalatest/matchers/Matcher;Lscala/Function1;)Lorg/scalatest/matchers/Matcher;
  #228 = Utf8               mapArgs
  #229 = Utf8               (Lscala/Function1<Ljava/lang/Object;Ljava/lang/String;>;)Lorg/scalatest/matchers/Matcher<TT;>;
  #230 = Utf8               mapArgs$
  #231 = NameAndType        #230:#76      // mapArgs$:(Lorg/scalatest/matchers/Matcher;Lscala/Function1;)Lorg/scalatest/matchers/Matcher;
  #232 = InterfaceMethodref #7.#231       // org/scalatest/matchers/Matcher.mapArgs$:(Lorg/scalatest/matchers/Matcher;Lscala/Function1;)Lorg/scalatest/matchers/Matcher;
  #233 = Utf8               apply$mcZD$sp
  #234 = Utf8               (D)Z
  #235 = Utf8               v1
  #236 = Utf8               scala/Function1
  #237 = Class              #236          // scala/Function1
  #238 = Utf8               apply$mcZD$sp$
  #239 = Utf8               (Lscala/Function1;D)Z
  #240 = NameAndType        #238:#239     // apply$mcZD$sp$:(Lscala/Function1;D)Z
  #241 = InterfaceMethodref #237.#240     // scala/Function1.apply$mcZD$sp$:(Lscala/Function1;D)Z
  #242 = Utf8               D
  #243 = Utf8               apply$mcDD$sp
  #244 = Utf8               (D)D
  #245 = Utf8               apply$mcDD$sp$
  #246 = Utf8               (Lscala/Function1;D)D
  #247 = NameAndType        #245:#246     // apply$mcDD$sp$:(Lscala/Function1;D)D
  #248 = InterfaceMethodref #237.#247     // scala/Function1.apply$mcDD$sp$:(Lscala/Function1;D)D
  #249 = Utf8               apply$mcFD$sp
  #250 = Utf8               (D)F
  #251 = Utf8               apply$mcFD$sp$
  #252 = Utf8               (Lscala/Function1;D)F
  #253 = NameAndType        #251:#252     // apply$mcFD$sp$:(Lscala/Function1;D)F
  #254 = InterfaceMethodref #237.#253     // scala/Function1.apply$mcFD$sp$:(Lscala/Function1;D)F
  #255 = Utf8               apply$mcID$sp
  #256 = Utf8               (D)I
  #257 = Utf8               apply$mcID$sp$
  #258 = Utf8               (Lscala/Function1;D)I
  #259 = NameAndType        #257:#258     // apply$mcID$sp$:(Lscala/Function1;D)I
  #260 = InterfaceMethodref #237.#259     // scala/Function1.apply$mcID$sp$:(Lscala/Function1;D)I
  #261 = Utf8               apply$mcJD$sp
  #262 = Utf8               (D)J
  #263 = Utf8               apply$mcJD$sp$
  #264 = Utf8               (Lscala/Function1;D)J
  #265 = NameAndType        #263:#264     // apply$mcJD$sp$:(Lscala/Function1;D)J
  #266 = InterfaceMethodref #237.#265     // scala/Function1.apply$mcJD$sp$:(Lscala/Function1;D)J
  #267 = Utf8               apply$mcVD$sp
  #268 = Utf8               (D)V
  #269 = Utf8               apply$mcVD$sp$
  #270 = Utf8               (Lscala/Function1;D)V
  #271 = NameAndType        #269:#270     // apply$mcVD$sp$:(Lscala/Function1;D)V
  #272 = InterfaceMethodref #237.#271     // scala/Function1.apply$mcVD$sp$:(Lscala/Function1;D)V
  #273 = Utf8               apply$mcZF$sp
  #274 = Utf8               (F)Z
  #275 = Utf8               apply$mcZF$sp$
  #276 = Utf8               (Lscala/Function1;F)Z
  #277 = NameAndType        #275:#276     // apply$mcZF$sp$:(Lscala/Function1;F)Z
  #278 = InterfaceMethodref #237.#277     // scala/Function1.apply$mcZF$sp$:(Lscala/Function1;F)Z
  #279 = Utf8               F
  #280 = Utf8               apply$mcDF$sp
  #281 = Utf8               (F)D
  #282 = Utf8               apply$mcDF$sp$
  #283 = Utf8               (Lscala/Function1;F)D
  #284 = NameAndType        #282:#283     // apply$mcDF$sp$:(Lscala/Function1;F)D
  #285 = InterfaceMethodref #237.#284     // scala/Function1.apply$mcDF$sp$:(Lscala/Function1;F)D
  #286 = Utf8               apply$mcFF$sp
  #287 = Utf8               (F)F
  #288 = Utf8               apply$mcFF$sp$
  #289 = Utf8               (Lscala/Function1;F)F
  #290 = NameAndType        #288:#289     // apply$mcFF$sp$:(Lscala/Function1;F)F
  #291 = InterfaceMethodref #237.#290     // scala/Function1.apply$mcFF$sp$:(Lscala/Function1;F)F
  #292 = Utf8               apply$mcIF$sp
  #293 = Utf8               (F)I
  #294 = Utf8               apply$mcIF$sp$
  #295 = Utf8               (Lscala/Function1;F)I
  #296 = NameAndType        #294:#295     // apply$mcIF$sp$:(Lscala/Function1;F)I
  #297 = InterfaceMethodref #237.#296     // scala/Function1.apply$mcIF$sp$:(Lscala/Function1;F)I
  #298 = Utf8               apply$mcJF$sp
  #299 = Utf8               (F)J
  #300 = Utf8               apply$mcJF$sp$
  #301 = Utf8               (Lscala/Function1;F)J
  #302 = NameAndType        #300:#301     // apply$mcJF$sp$:(Lscala/Function1;F)J
  #303 = InterfaceMethodref #237.#302     // scala/Function1.apply$mcJF$sp$:(Lscala/Function1;F)J
  #304 = Utf8               apply$mcVF$sp
  #305 = Utf8               (F)V
  #306 = Utf8               apply$mcVF$sp$
  #307 = Utf8               (Lscala/Function1;F)V
  #308 = NameAndType        #306:#307     // apply$mcVF$sp$:(Lscala/Function1;F)V
  #309 = InterfaceMethodref #237.#308     // scala/Function1.apply$mcVF$sp$:(Lscala/Function1;F)V
  #310 = Utf8               apply$mcZI$sp
  #311 = Utf8               (I)Z
  #312 = Utf8               apply$mcZI$sp$
  #313 = Utf8               (Lscala/Function1;I)Z
  #314 = NameAndType        #312:#313     // apply$mcZI$sp$:(Lscala/Function1;I)Z
  #315 = InterfaceMethodref #237.#314     // scala/Function1.apply$mcZI$sp$:(Lscala/Function1;I)Z
  #316 = Utf8               I
  #317 = Utf8               apply$mcDI$sp
  #318 = Utf8               (I)D
  #319 = Utf8               apply$mcDI$sp$
  #320 = Utf8               (Lscala/Function1;I)D
  #321 = NameAndType        #319:#320     // apply$mcDI$sp$:(Lscala/Function1;I)D
  #322 = InterfaceMethodref #237.#321     // scala/Function1.apply$mcDI$sp$:(Lscala/Function1;I)D
  #323 = Utf8               apply$mcFI$sp
  #324 = Utf8               (I)F
  #325 = Utf8               apply$mcFI$sp$
  #326 = Utf8               (Lscala/Function1;I)F
  #327 = NameAndType        #325:#326     // apply$mcFI$sp$:(Lscala/Function1;I)F
  #328 = InterfaceMethodref #237.#327     // scala/Function1.apply$mcFI$sp$:(Lscala/Function1;I)F
  #329 = Utf8               apply$mcII$sp
  #330 = Utf8               (I)I
  #331 = Utf8               apply$mcII$sp$
  #332 = Utf8               (Lscala/Function1;I)I
  #333 = NameAndType        #331:#332     // apply$mcII$sp$:(Lscala/Function1;I)I
  #334 = InterfaceMethodref #237.#333     // scala/Function1.apply$mcII$sp$:(Lscala/Function1;I)I
  #335 = Utf8               apply$mcJI$sp
  #336 = Utf8               (I)J
  #337 = Utf8               apply$mcJI$sp$
  #338 = Utf8               (Lscala/Function1;I)J
  #339 = NameAndType        #337:#338     // apply$mcJI$sp$:(Lscala/Function1;I)J
  #340 = InterfaceMethodref #237.#339     // scala/Function1.apply$mcJI$sp$:(Lscala/Function1;I)J
  #341 = Utf8               apply$mcVI$sp
  #342 = Utf8               (I)V
  #343 = Utf8               apply$mcVI$sp$
  #344 = Utf8               (Lscala/Function1;I)V
  #345 = NameAndType        #343:#344     // apply$mcVI$sp$:(Lscala/Function1;I)V
  #346 = InterfaceMethodref #237.#345     // scala/Function1.apply$mcVI$sp$:(Lscala/Function1;I)V
  #347 = Utf8               apply$mcZJ$sp
  #348 = Utf8               (J)Z
  #349 = Utf8               apply$mcZJ$sp$
  #350 = Utf8               (Lscala/Function1;J)Z
  #351 = NameAndType        #349:#350     // apply$mcZJ$sp$:(Lscala/Function1;J)Z
  #352 = InterfaceMethodref #237.#351     // scala/Function1.apply$mcZJ$sp$:(Lscala/Function1;J)Z
  #353 = Utf8               J
  #354 = Utf8               apply$mcDJ$sp
  #355 = Utf8               (J)D
  #356 = Utf8               apply$mcDJ$sp$
  #357 = Utf8               (Lscala/Function1;J)D
  #358 = NameAndType        #356:#357     // apply$mcDJ$sp$:(Lscala/Function1;J)D
  #359 = InterfaceMethodref #237.#358     // scala/Function1.apply$mcDJ$sp$:(Lscala/Function1;J)D
  #360 = Utf8               apply$mcFJ$sp
  #361 = Utf8               (J)F
  #362 = Utf8               apply$mcFJ$sp$
  #363 = Utf8               (Lscala/Function1;J)F
  #364 = NameAndType        #362:#363     // apply$mcFJ$sp$:(Lscala/Function1;J)F
  #365 = InterfaceMethodref #237.#364     // scala/Function1.apply$mcFJ$sp$:(Lscala/Function1;J)F
  #366 = Utf8               apply$mcIJ$sp
  #367 = Utf8               (J)I
  #368 = Utf8               apply$mcIJ$sp$
  #369 = Utf8               (Lscala/Function1;J)I
  #370 = NameAndType        #368:#369     // apply$mcIJ$sp$:(Lscala/Function1;J)I
  #371 = InterfaceMethodref #237.#370     // scala/Function1.apply$mcIJ$sp$:(Lscala/Function1;J)I
  #372 = Utf8               apply$mcJJ$sp
  #373 = Utf8               (J)J
  #374 = Utf8               apply$mcJJ$sp$
  #375 = Utf8               (Lscala/Function1;J)J
  #376 = NameAndType        #374:#375     // apply$mcJJ$sp$:(Lscala/Function1;J)J
  #377 = InterfaceMethodref #237.#376     // scala/Function1.apply$mcJJ$sp$:(Lscala/Function1;J)J
  #378 = Utf8               apply$mcVJ$sp
  #379 = Utf8               (J)V
  #380 = Utf8               apply$mcVJ$sp$
  #381 = Utf8               (Lscala/Function1;J)V
  #382 = NameAndType        #380:#381     // apply$mcVJ$sp$:(Lscala/Function1;J)V
  #383 = InterfaceMethodref #237.#382     // scala/Function1.apply$mcVJ$sp$:(Lscala/Function1;J)V
  #384 = Utf8               andThen
  #385 = Utf8               (Lscala/Function1;)Lscala/Function1;
  #386 = Utf8               <A:Ljava/lang/Object;>(Lscala/Function1<Lorg/scalatest/matchers/MatchResult;TA;>;)Lscala/Function1<TT;TA;>;
  #387 = Utf8               andThen$
  #388 = Utf8               (Lscala/Function1;Lscala/Function1;)Lscala/Function1;
  #389 = NameAndType        #387:#388     // andThen$:(Lscala/Function1;Lscala/Function1;)Lscala/Function1;
  #390 = InterfaceMethodref #237.#389     // scala/Function1.andThen$:(Lscala/Function1;Lscala/Function1;)Lscala/Function1;
  #391 = Utf8               (Ljava/lang/Object;)Lorg/scalatest/matchers/MatchResult;
  #392 = Utf8               (TT;)Lorg/scalatest/matchers/MatchResult;
  #393 = Utf8               left
  #394 = NameAndType        #67:#68       // firstPropertyMatcher$1:Lorg/scalatest/matchers/HavePropertyMatcher;
  #395 = Fieldref           #2.#394       // org/scalatest/matchers/dsl/HaveWord$$anon$7.firstPropertyMatcher$1:Lorg/scalatest/matchers/HavePropertyMatcher;
  #396 = NameAndType        #69:#70       // propertyMatchers$1:Lscala/collection/immutable/Seq;
  #397 = Fieldref           #2.#396       // org/scalatest/matchers/dsl/HaveWord$$anon$7.propertyMatchers$1:Lscala/collection/immutable/Seq;
  #398 = Utf8               scala/collection/immutable/Seq
  #399 = Class              #398          // scala/collection/immutable/Seq
  #400 = Utf8               toList
  #401 = Utf8               ()Lscala/collection/immutable/List;
  #402 = NameAndType        #400:#401     // toList:()Lscala/collection/immutable/List;
  #403 = InterfaceMethodref #399.#402     // scala/collection/immutable/Seq.toList:()Lscala/collection/immutable/List;
  #404 = Utf8               scala/collection/immutable/List
  #405 = Class              #404          // scala/collection/immutable/List
  #406 = Utf8               $colon$colon
  #407 = Utf8               (Ljava/lang/Object;)Lscala/collection/immutable/List;
  #408 = NameAndType        #406:#407     // $colon$colon:(Ljava/lang/Object;)Lscala/collection/immutable/List;
  #409 = Methodref          #405.#408     // scala/collection/immutable/List.$colon$colon:(Ljava/lang/Object;)Lscala/collection/immutable/List;
  #410 = Utf8               (Ljava/lang/Object;)Ljava/lang/Object;
  #411 = MethodType         #410          //  (Ljava/lang/Object;)Ljava/lang/Object;
  #412 = Utf8               $anonfun$apply$1
  #413 = Utf8               (Ljava/lang/Object;Lorg/scalatest/matchers/HavePropertyMatcher;)Lorg/scalatest/matchers/HavePropertyMatchResult;
  #414 = NameAndType        #412:#413     // $anonfun$apply$1:(Ljava/lang/Object;Lorg/scalatest/matchers/HavePropertyMatcher;)Lorg/scalatest/matchers/HavePropertyMatchResult;
  #415 = Methodref          #2.#414       // org/scalatest/matchers/dsl/HaveWord$$anon$7.$anonfun$apply$1:(Ljava/lang/Object;Lorg/scalatest/matchers/HavePropertyMatcher;)Lorg/scalatest/matchers/HavePropertyMatchResult;
  #416 = MethodHandle       6:#415        // REF_invokeStatic org/scalatest/matchers/dsl/HaveWord$$anon$7.$anonfun$apply$1:(Ljava/lang/Object;Lorg/scalatest/matchers/HavePropertyMatcher;)Lorg/scalatest/matchers/HavePropertyMatchResult;
  #417 = Utf8               (Lorg/scalatest/matchers/HavePropertyMatcher;)Lorg/scalatest/matchers/HavePropertyMatchResult;
  #418 = MethodType         #417          //  (Lorg/scalatest/matchers/HavePropertyMatcher;)Lorg/scalatest/matchers/HavePropertyMatchResult;
  #419 = Integer            5
  #420 = Integer            1
  #421 = Utf8               java/lang/invoke/LambdaMetafactory
  #422 = Class              #421          // java/lang/invoke/LambdaMetafactory
  #423 = Utf8               altMetafactory
  #424 = Utf8               (Ljava/lang/invoke/MethodHandles$Lookup;Ljava/lang/String;Ljava/lang/invoke/MethodType;[Ljava/lang/Object;)Ljava/lang/invoke/CallSite;
  #425 = NameAndType        #423:#424     // altMetafactory:(Ljava/lang/invoke/MethodHandles$Lookup;Ljava/lang/String;Ljava/lang/invoke/MethodType;[Ljava/lang/Object;)Ljava/lang/invoke/CallSite;
  #426 = Methodref          #422.#425     // java/lang/invoke/LambdaMetafactory.altMetafactory:(Ljava/lang/invoke/MethodHandles$Lookup;Ljava/lang/String;Ljava/lang/invoke/MethodType;[Ljava/lang/Object;)Ljava/lang/invoke/CallSite;
  #427 = MethodHandle       6:#426        // REF_invokeStatic java/lang/invoke/LambdaMetafactory.altMetafactory:(Ljava/lang/invoke/MethodHandles$Lookup;Ljava/lang/String;Ljava/lang/invoke/MethodType;[Ljava/lang/Object;)Ljava/lang/invoke/CallSite;
  #428 = Utf8               (Ljava/lang/Object;)Lscala/Function1;
  #429 = NameAndType        #11:#428      // apply:(Ljava/lang/Object;)Lscala/Function1;
  #430 = InvokeDynamic      #0:#429       // #0:apply:(Ljava/lang/Object;)Lscala/Function1;
  #431 = Utf8               map
  #432 = Utf8               (Lscala/Function1;)Lscala/collection/immutable/List;
  #433 = NameAndType        #431:#432     // map:(Lscala/Function1;)Lscala/collection/immutable/List;
  #434 = Methodref          #405.#433     // scala/collection/immutable/List.map:(Lscala/Function1;)Lscala/collection/immutable/List;
  #435 = Utf8               $anonfun$apply$2$adapted
  #436 = Utf8               (Lorg/scalatest/matchers/HavePropertyMatchResult;)Ljava/lang/Object;
  #437 = NameAndType        #435:#436     // $anonfun$apply$2$adapted:(Lorg/scalatest/matchers/HavePropertyMatchResult;)Ljava/lang/Object;
  #438 = Methodref          #2.#437       // org/scalatest/matchers/dsl/HaveWord$$anon$7.$anonfun$apply$2$adapted:(Lorg/scalatest/matchers/HavePropertyMatchResult;)Ljava/lang/Object;
  #439 = MethodHandle       6:#438        // REF_invokeStatic org/scalatest/matchers/dsl/HaveWord$$anon$7.$anonfun$apply$2$adapted:(Lorg/scalatest/matchers/HavePropertyMatchResult;)Ljava/lang/Object;
  #440 = MethodType         #436          //  (Lorg/scalatest/matchers/HavePropertyMatchResult;)Ljava/lang/Object;
  #441 = Utf8               ()Lscala/Function1;
  #442 = NameAndType        #11:#441      // apply:()Lscala/Function1;
  #443 = InvokeDynamic      #1:#442       // #1:apply:()Lscala/Function1;
  #444 = Utf8               find
  #445 = Utf8               (Lscala/Function1;)Lscala/Option;
  #446 = NameAndType        #444:#445     // find:(Lscala/Function1;)Lscala/Option;
  #447 = Methodref          #405.#446     // scala/collection/immutable/List.find:(Lscala/Function1;)Lscala/Option;
  #448 = Utf8               isEmpty
  #449 = Utf8               ()Z
  #450 = NameAndType        #448:#449     // isEmpty:()Z
  #451 = InterfaceMethodref #399.#450     // scala/collection/immutable/Seq.isEmpty:()Z
  #452 = Utf8               scala/Some
  #453 = Class              #452          // scala/Some
  #454 = Utf8               value
  #455 = Utf8               ()Ljava/lang/Object;
  #456 = NameAndType        #454:#455     // value:()Ljava/lang/Object;
  #457 = Methodref          #453.#456     // scala/Some.value:()Ljava/lang/Object;
  #458 = Utf8               org/scalatest/matchers/HavePropertyMatchResult
  #459 = Class              #458          // org/scalatest/matchers/HavePropertyMatchResult
  #460 = Utf8               scala/Tuple2
  #461 = Class              #460          // scala/Tuple2
  #462 = Utf8               org/scalatest/Resources$
  #463 = Class              #462          // org/scalatest/Resources$
  #464 = Utf8               MODULE$
  #465 = Utf8               Lorg/scalatest/Resources$;
  #466 = NameAndType        #464:#465     // MODULE$:Lorg/scalatest/Resources$;
  #467 = Fieldref           #463.#466     // org/scalatest/Resources$.MODULE$:Lorg/scalatest/Resources$;
  #468 = Utf8               rawPropertyDidNotHaveExpectedValue
  #469 = Utf8               ()Ljava/lang/String;
  #470 = NameAndType        #468:#469     // rawPropertyDidNotHaveExpectedValue:()Ljava/lang/String;
  #471 = Methodref          #463.#470     // org/scalatest/Resources$.rawPropertyDidNotHaveExpectedValue:()Ljava/lang/String;
  #472 = Utf8               scala/package$
  #473 = Class              #472          // scala/package$
  #474 = Utf8               Lscala/package$;
  #475 = NameAndType        #464:#474     // MODULE$:Lscala/package$;
  #476 = Fieldref           #473.#475     // scala/package$.MODULE$:Lscala/package$;
  #477 = Utf8               Vector
  #478 = Utf8               ()Lscala/collection/immutable/Vector$;
  #479 = NameAndType        #477:#478     // Vector:()Lscala/collection/immutable/Vector$;
  #480 = Methodref          #473.#479     // scala/package$.Vector:()Lscala/collection/immutable/Vector$;
  #481 = Utf8               scala/runtime/ScalaRunTime$
  #482 = Class              #481          // scala/runtime/ScalaRunTime$
  #483 = Utf8               Lscala/runtime/ScalaRunTime$;
  #484 = NameAndType        #464:#483     // MODULE$:Lscala/runtime/ScalaRunTime$;
  #485 = Fieldref           #482.#484     // scala/runtime/ScalaRunTime$.MODULE$:Lscala/runtime/ScalaRunTime$;
  #486 = Utf8               org/scalatest/UnquotedString$
  #487 = Class              #486          // org/scalatest/UnquotedString$
  #488 = Utf8               Lorg/scalatest/UnquotedString$;
  #489 = NameAndType        #464:#488     // MODULE$:Lorg/scalatest/UnquotedString$;
  #490 = Fieldref           #487.#489     // org/scalatest/UnquotedString$.MODULE$:Lorg/scalatest/UnquotedString$;
  #491 = Utf8               propertyName
  #492 = NameAndType        #491:#469     // propertyName:()Ljava/lang/String;
  #493 = Methodref          #459.#492     // org/scalatest/matchers/HavePropertyMatchResult.propertyName:()Ljava/lang/String;
  #494 = Utf8               (Ljava/lang/String;)Lorg/scalatest/UnquotedString;
  #495 = NameAndType        #11:#494      // apply:(Ljava/lang/String;)Lorg/scalatest/UnquotedString;
  #496 = Methodref          #487.#495     // org/scalatest/UnquotedString$.apply:(Ljava/lang/String;)Lorg/scalatest/UnquotedString;
  #497 = Utf8               expectedValue
  #498 = NameAndType        #497:#455     // expectedValue:()Ljava/lang/Object;
  #499 = Methodref          #459.#498     // org/scalatest/matchers/HavePropertyMatchResult.expectedValue:()Ljava/lang/Object;
  #500 = Utf8               actualValue
  #501 = NameAndType        #500:#455     // actualValue:()Ljava/lang/Object;
  #502 = Methodref          #459.#501     // org/scalatest/matchers/HavePropertyMatchResult.actualValue:()Ljava/lang/Object;
  #503 = Utf8               genericWrapArray
  #504 = Utf8               (Ljava/lang/Object;)Lscala/collection/immutable/ArraySeq;
  #505 = NameAndType        #503:#504     // genericWrapArray:(Ljava/lang/Object;)Lscala/collection/immutable/ArraySeq;
  #506 = Methodref          #482.#505     // scala/runtime/ScalaRunTime$.genericWrapArray:(Ljava/lang/Object;)Lscala/collection/immutable/ArraySeq;
  #507 = Utf8               scala/collection/immutable/Vector$
  #508 = Class              #507          // scala/collection/immutable/Vector$
  #509 = Utf8               (Lscala/collection/immutable/Seq;)Ljava/lang/Object;
  #510 = NameAndType        #11:#509      // apply:(Lscala/collection/immutable/Seq;)Ljava/lang/Object;
  #511 = Methodref          #508.#510     // scala/collection/immutable/Vector$.apply:(Lscala/collection/immutable/Seq;)Ljava/lang/Object;
  #512 = Utf8               <init>
  #513 = Utf8               (Ljava/lang/Object;Ljava/lang/Object;)V
  #514 = NameAndType        #512:#513     // "<init>":(Ljava/lang/Object;Ljava/lang/Object;)V
  #515 = Methodref          #461.#514     // scala/Tuple2."<init>":(Ljava/lang/Object;Ljava/lang/Object;)V
  #516 = Utf8               _1
  #517 = NameAndType        #516:#455     // _1:()Ljava/lang/Object;
  #518 = Methodref          #461.#517     // scala/Tuple2._1:()Ljava/lang/Object;
  #519 = Utf8               java/lang/String
  #520 = Class              #519          // java/lang/String
  #521 = Utf8               _2
  #522 = NameAndType        #521:#455     // _2:()Ljava/lang/Object;
  #523 = Methodref          #461.#522     // scala/Tuple2._2:()Ljava/lang/Object;
  #524 = Utf8               scala/collection/immutable/Vector
  #525 = Class              #524          // scala/collection/immutable/Vector
  #526 = Utf8               scala/MatchError
  #527 = Class              #526          // scala/MatchError
  #528 = Utf8               (Ljava/lang/Object;)V
  #529 = NameAndType        #512:#528     // "<init>":(Ljava/lang/Object;)V
  #530 = Methodref          #527.#529     // scala/MatchError."<init>":(Ljava/lang/Object;)V
  #531 = Utf8               rawMidSentencePropertyDidNotHaveExpectedValue
  #532 = NameAndType        #531:#469     // rawMidSentencePropertyDidNotHaveExpectedValue:()Ljava/lang/String;
  #533 = Methodref          #463.#532     // org/scalatest/Resources$.rawMidSentencePropertyDidNotHaveExpectedValue:()Ljava/lang/String;
  #534 = Utf8               org/scalatest/matchers/MatchResult$
  #535 = Class              #534          // org/scalatest/matchers/MatchResult$
  #536 = Utf8               Lorg/scalatest/matchers/MatchResult$;
  #537 = NameAndType        #464:#536     // MODULE$:Lorg/scalatest/matchers/MatchResult$;
  #538 = Fieldref           #535.#537     // org/scalatest/matchers/MatchResult$.MODULE$:Lorg/scalatest/matchers/MatchResult$;
  #539 = Utf8               (ZLjava/lang/String;Ljava/lang/String;Ljava/lang/String;Ljava/lang/String;Lscala/collection/immutable/IndexedSeq;Lscala/collection/immutable/IndexedSeq;)Lorg/scalatest/matchers/MatchResult;
  #540 = NameAndType        #11:#539      // apply:(ZLjava/lang/String;Ljava/lang/String;Ljava/lang/String;Ljava/lang/String;Lscala/collection/immutable/IndexedSeq;Lscala/collection/immutable/IndexedSeq;)Lorg/scalatest/matchers/MatchResult;
  #541 = Methodref          #535.#540     // org/scalatest/matchers/MatchResult$.apply:(ZLjava/lang/String;Ljava/lang/String;Ljava/lang/String;Ljava/lang/String;Lscala/collection/immutable/IndexedSeq;Lscala/collection/immutable/IndexedSeq;)Lorg/scalatest/matchers/MatchResult;
  #542 = Utf8               scala/None$
  #543 = Class              #542          // scala/None$
  #544 = Utf8               Lscala/None$;
  #545 = NameAndType        #464:#544     // MODULE$:Lscala/None$;
  #546 = Fieldref           #543.#545     // scala/None$.MODULE$:Lscala/None$;
  #547 = Utf8               equals
  #548 = Utf8               (Ljava/lang/Object;)Z
  #549 = NameAndType        #547:#548     // equals:(Ljava/lang/Object;)Z
  #550 = Methodref          #5.#549       // java/lang/Object.equals:(Ljava/lang/Object;)Z
  #551 = Utf8               head
  #552 = NameAndType        #551:#455     // head:()Ljava/lang/Object;
  #553 = Methodref          #405.#552     // scala/collection/immutable/List.head:()Ljava/lang/Object;
  #554 = Utf8               rawPropertyHadExpectedValue
  #555 = NameAndType        #554:#469     // rawPropertyHadExpectedValue:()Ljava/lang/String;
  #556 = Methodref          #463.#555     // org/scalatest/Resources$.rawPropertyHadExpectedValue:()Ljava/lang/String;
  #557 = Utf8               rawAllPropertiesHadExpectedValues
  #558 = NameAndType        #557:#469     // rawAllPropertiesHadExpectedValues:()Ljava/lang/String;
  #559 = Methodref          #463.#558     // org/scalatest/Resources$.rawAllPropertiesHadExpectedValues:()Ljava/lang/String;
  #560 = Utf8               rawMidSentencePropertyHadExpectedValue
  #561 = NameAndType        #560:#469     // rawMidSentencePropertyHadExpectedValue:()Ljava/lang/String;
  #562 = Methodref          #463.#561     // org/scalatest/Resources$.rawMidSentencePropertyHadExpectedValue:()Ljava/lang/String;
  #563 = Utf8               rawMidSentenceAllPropertiesHadExpectedValues
  #564 = NameAndType        #563:#469     // rawMidSentenceAllPropertiesHadExpectedValues:()Ljava/lang/String;
  #565 = Methodref          #463.#564     // org/scalatest/Resources$.rawMidSentenceAllPropertiesHadExpectedValues:()Ljava/lang/String;
  #566 = Utf8               rawFailureMessage
  #567 = Utf8               Ljava/lang/String;
  #568 = Utf8               failureMessageArgs
  #569 = Utf8               Lscala/collection/immutable/Vector;
  #570 = Utf8               rawMidSentenceFailureMessage
  #571 = Utf8               midSentenceFailureMessageArgs
  #572 = Utf8               failedVerification
  #573 = Utf8               Lorg/scalatest/matchers/HavePropertyMatchResult;
  #574 = Utf8               firstFailure
  #575 = Utf8               firstPropertyResult
  #576 = Utf8               rawMidSentenceFailureMessageArgs
  #577 = Utf8               results
  #578 = Utf8               Lscala/collection/immutable/List;
  #579 = Utf8               firstFailureOption
  #580 = Utf8               Lscala/Option;
  #581 = Utf8               justOneProperty
  #582 = Utf8               Z
  #583 = Utf8               Ljava/lang/Object;
  #584 = Utf8               org/scalatest/matchers/HavePropertyMatcher
  #585 = Class              #584          // org/scalatest/matchers/HavePropertyMatcher
  #586 = Utf8               scala/Option
  #587 = Class              #586          // scala/Option
  #588 = Utf8               org/scalatest/matchers/MatchResult
  #589 = Class              #588          // org/scalatest/matchers/MatchResult
  #590 = Utf8               toString
  #591 = Utf8               java/lang/StringBuilder
  #592 = Class              #591          // java/lang/StringBuilder
  #593 = Integer            7
  #594 = NameAndType        #512:#342     // "<init>":(I)V
  #595 = Methodref          #592.#594     // java/lang/StringBuilder."<init>":(I)V
  #596 = Utf8               have (
  #597 = String             #596          // have (
  #598 = Utf8               append
  #599 = Utf8               (Ljava/lang/String;)Ljava/lang/StringBuilder;
  #600 = NameAndType        #598:#599     // append:(Ljava/lang/String;)Ljava/lang/StringBuilder;
  #601 = Methodref          #592.#600     // java/lang/StringBuilder.append:(Ljava/lang/String;)Ljava/lang/StringBuilder;
  #602 = Utf8               org/scalactic/Prettifier$
  #603 = Class              #602          // org/scalactic/Prettifier$
  #604 = Utf8               Lorg/scalactic/Prettifier$;
  #605 = NameAndType        #464:#604     // MODULE$:Lorg/scalactic/Prettifier$;
  #606 = Fieldref           #603.#605     // org/scalactic/Prettifier$.MODULE$:Lorg/scalactic/Prettifier$;
  #607 = Utf8               default
  #608 = Utf8               ()Lorg/scalactic/Prettifier;
  #609 = NameAndType        #607:#608     // default:()Lorg/scalactic/Prettifier;
  #610 = Methodref          #603.#609     // org/scalactic/Prettifier$.default:()Lorg/scalactic/Prettifier;
  #611 = Utf8               org/scalactic/Prettifier
  #612 = Class              #611          // org/scalactic/Prettifier
  #613 = Utf8               (Ljava/lang/Object;)Ljava/lang/String;
  #614 = NameAndType        #11:#613      // apply:(Ljava/lang/Object;)Ljava/lang/String;
  #615 = InterfaceMethodref #612.#614     // org/scalactic/Prettifier.apply:(Ljava/lang/Object;)Ljava/lang/String;
  #616 = Utf8               )
  #617 = String             #616          // )
  #618 = NameAndType        #590:#469     // toString:()Ljava/lang/String;
  #619 = Methodref          #592.#618     // java/lang/StringBuilder.toString:()Ljava/lang/String;
  #620 = NameAndType        #71:#72       // compose:(Lscala/Function1;)Lorg/scalatest/matchers/Matcher;
  #621 = Methodref          #2.#620       // org/scalatest/matchers/dsl/HaveWord$$anon$7.compose:(Lscala/Function1;)Lorg/scalatest/matchers/Matcher;
  #622 = NameAndType        #11:#391      // apply:(Ljava/lang/Object;)Lorg/scalatest/matchers/MatchResult;
  #623 = Methodref          #2.#622       // org/scalatest/matchers/dsl/HaveWord$$anon$7.apply:(Ljava/lang/Object;)Lorg/scalatest/matchers/MatchResult;
  #624 = Utf8               left$1
  #625 = Utf8               propertyVerifier
  #626 = Utf8               (Ljava/lang/Object;)Lorg/scalatest/matchers/HavePropertyMatchResult;
  #627 = NameAndType        #11:#626      // apply:(Ljava/lang/Object;)Lorg/scalatest/matchers/HavePropertyMatchResult;
  #628 = InterfaceMethodref #585.#627     // org/scalatest/matchers/HavePropertyMatcher.apply:(Ljava/lang/Object;)Lorg/scalatest/matchers/HavePropertyMatchResult;
  #629 = Utf8               $anonfun$apply$2
  #630 = Utf8               (Lorg/scalatest/matchers/HavePropertyMatchResult;)Z
  #631 = Utf8               pv
  #632 = Utf8               matches
  #633 = NameAndType        #632:#449     // matches:()Z
  #634 = Methodref          #459.#633     // org/scalatest/matchers/HavePropertyMatchResult.matches:()Z
  #635 = Utf8               (Lorg/scalatest/matchers/dsl/HaveWord;Lorg/scalatest/matchers/HavePropertyMatcher;Lscala/collection/immutable/Seq;)V
  #636 = Utf8               $outer
  #637 = Utf8               ()V
  #638 = NameAndType        #512:#637     // "<init>":()V
  #639 = Methodref          #5.#638       // java/lang/Object."<init>":()V
  #640 = Utf8               $init$
  #641 = Utf8               (Lscala/Function1;)V
  #642 = NameAndType        #640:#641     // $init$:(Lscala/Function1;)V
  #643 = InterfaceMethodref #237.#642     // scala/Function1.$init$:(Lscala/Function1;)V
  #644 = Utf8               (Lorg/scalatest/matchers/Matcher;)V
  #645 = NameAndType        #640:#644     // $init$:(Lorg/scalatest/matchers/Matcher;)V
  #646 = InterfaceMethodref #7.#645       // org/scalatest/matchers/Matcher.$init$:(Lorg/scalatest/matchers/Matcher;)V
  #647 = NameAndType        #629:#630     // $anonfun$apply$2:(Lorg/scalatest/matchers/HavePropertyMatchResult;)Z
  #648 = Methodref          #2.#647       // org/scalatest/matchers/dsl/HaveWord$$anon$7.$anonfun$apply$2:(Lorg/scalatest/matchers/HavePropertyMatchResult;)Z
  #649 = Utf8               scala/runtime/BoxesRunTime
  #650 = Class              #649          // scala/runtime/BoxesRunTime
  #651 = Utf8               boxToBoolean
  #652 = Utf8               (Z)Ljava/lang/Boolean;
  #653 = NameAndType        #651:#652     // boxToBoolean:(Z)Ljava/lang/Boolean;
  #654 = Methodref          #650.#653     // scala/runtime/BoxesRunTime.boxToBoolean:(Z)Ljava/lang/Boolean;
  #655 = Utf8               $deserializeLambda$
  #656 = Utf8               (Ljava/lang/invoke/SerializedLambda;)Ljava/lang/Object;
  #657 = Utf8               scala/runtime/LambdaDeserialize
  #658 = Class              #657          // scala/runtime/LambdaDeserialize
  #659 = Utf8               bootstrap
  #660 = Utf8               (Ljava/lang/invoke/MethodHandles$Lookup;Ljava/lang/String;Ljava/lang/invoke/MethodType;[Ljava/lang/invoke/MethodHandle;)Ljava/lang/invoke/CallSite;
  #661 = NameAndType        #659:#660     // bootstrap:(Ljava/lang/invoke/MethodHandles$Lookup;Ljava/lang/String;Ljava/lang/invoke/MethodType;[Ljava/lang/invoke/MethodHandle;)Ljava/lang/invoke/CallSite;
  #662 = Methodref          #658.#661     // scala/runtime/LambdaDeserialize.bootstrap:(Ljava/lang/invoke/MethodHandles$Lookup;Ljava/lang/String;Ljava/lang/invoke/MethodType;[Ljava/lang/invoke/MethodHandle;)Ljava/lang/invoke/CallSite;
  #663 = MethodHandle       6:#662        // REF_invokeStatic scala/runtime/LambdaDeserialize.bootstrap:(Ljava/lang/invoke/MethodHandles$Lookup;Ljava/lang/String;Ljava/lang/invoke/MethodType;[Ljava/lang/invoke/MethodHandle;)Ljava/lang/invoke/CallSite;
  #664 = Utf8               lambdaDeserialize
  #665 = NameAndType        #664:#656     // lambdaDeserialize:(Ljava/lang/invoke/SerializedLambda;)Ljava/lang/Object;
  #666 = InvokeDynamic      #2:#665       // #2:lambdaDeserialize:(Ljava/lang/invoke/SerializedLambda;)Ljava/lang/Object;
  #667 = Utf8               Code
  #668 = Utf8               LineNumberTable
  #669 = Utf8               LocalVariableTable
  #670 = Utf8               Signature
  #671 = Utf8               MethodParameters
  #672 = Utf8               StackMapTable
  #673 = Utf8               InnerClasses
  #674 = Utf8               EnclosingMethod
  #675 = Utf8               SourceFile
  #676 = Utf8               BootstrapMethods
  #677 = Utf8               ScalaInlineInfo
  #678 = Utf8               Scala
{
  private final org.scalatest.matchers.HavePropertyMatcher firstPropertyMatcher$1;
    descriptor: Lorg/scalatest/matchers/HavePropertyMatcher;
    flags: (0x0012) ACC_PRIVATE, ACC_FINAL

  private final scala.collection.immutable.Seq propertyMatchers$1;
    descriptor: Lscala/collection/immutable/Seq;
    flags: (0x0012) ACC_PRIVATE, ACC_FINAL

  public <U extends java.lang.Object> org.scalatest.matchers.Matcher<U> compose(scala.Function1<U, T>);
    descriptor: (Lscala/Function1;)Lorg/scalatest/matchers/Matcher;
    flags: (0x0001) ACC_PUBLIC
    Code:
      stack=2, locals=2, args_size=2
         0: aload_0
         1: aload_1
         2: invokestatic  #78                 // InterfaceMethod org/scalatest/matchers/Matcher.compose$:(Lorg/scalatest/matchers/Matcher;Lscala/Function1;)Lorg/scalatest/matchers/Matcher;
         5: areturn
      LineNumberTable:
        line 150: 0
      LocalVariableTable:
        Start  Length  Slot  Name   Signature
            0       6     0  this   Lorg/scalatest/matchers/dsl/HaveWord$$anon$7;
            0       6     1     g   Lscala/Function1;
    Signature: #73                          // <U:Ljava/lang/Object;>(Lscala/Function1<TU;TT;>;)Lorg/scalatest/matchers/Matcher<TU;>;
    MethodParameters:
      Name                           Flags
      g                              final

  public <U extends T> org.scalatest.matchers.Matcher<U> and(org.scalatest.matchers.Matcher<U>);
    descriptor: (Lorg/scalatest/matchers/Matcher;)Lorg/scalatest/matchers/Matcher;
    flags: (0x0001) ACC_PUBLIC
    Code:
      stack=2, locals=2, args_size=2
         0: aload_0
         1: aload_1
         2: invokestatic  #89                 // InterfaceMethod org/scalatest/matchers/Matcher.and$:(Lorg/scalatest/matchers/Matcher;Lorg/scalatest/matchers/Matcher;)Lorg/scalatest/matchers/Matcher;
         5: areturn
      LineNumberTable:
        line 150: 0
      LocalVariableTable:
        Start  Length  Slot  Name   Signature
            0       6     0  this   Lorg/scalatest/matchers/dsl/HaveWord$$anon$7;
            0       6     1 rightMatcher   Lorg/scalatest/matchers/Matcher;
    Signature: #84                          // <U:TT;>(Lorg/scalatest/matchers/Matcher<TU;>;)Lorg/scalatest/matchers/Matcher<TU;>;
    MethodParameters:
      Name                           Flags
      rightMatcher                   final

  public <U extends java.lang.Object, TC1 extends java.lang.Object> org.scalatest.matchers.dsl.MatcherFactory1<T, TC1> and(org.scalatest.matchers.dsl.MatcherFactory1<U, TC1>);
    descriptor: (Lorg/scalatest/matchers/dsl/MatcherFactory1;)Lorg/scalatest/matchers/dsl/MatcherFactory1;
    flags: (0x0001) ACC_PUBLIC
    Code:
      stack=2, locals=2, args_size=2
         0: aload_0
         1: aload_1
         2: invokestatic  #96                 // InterfaceMethod org/scalatest/matchers/Matcher.and$:(Lorg/scalatest/matchers/Matcher;Lorg/scalatest/matchers/dsl/MatcherFactory1;)Lorg/scalatest/matchers/dsl/MatcherFactory1;
         5: areturn
      LineNumberTable:
        line 150: 0
      LocalVariableTable:
        Start  Length  Slot  Name   Signature
            0       6     0  this   Lorg/scalatest/matchers/dsl/HaveWord$$anon$7;
            0       6     1 rightMatcherFactory1   Lorg/scalatest/matchers/dsl/MatcherFactory1;
    Signature: #92                          // <U:Ljava/lang/Object;TC1:Ljava/lang/Object;>(Lorg/scalatest/matchers/dsl/MatcherFactory1<TU;TTC1;>;)Lorg/scalatest/matchers/dsl/MatcherFactory1<TT;TTC1;>;
    MethodParameters:
      Name                           Flags
      rightMatcherFactory1           final

  public <U extends T> org.scalatest.matchers.Matcher<U> or(org.scalatest.matchers.Matcher<U>);
    descriptor: (Lorg/scalatest/matchers/Matcher;)Lorg/scalatest/matchers/Matcher;
    flags: (0x0001) ACC_PUBLIC
    Code:
      stack=2, locals=2, args_size=2
         0: aload_0
         1: aload_1
         2: invokestatic  #101                // InterfaceMethod org/scalatest/matchers/Matcher.or$:(Lorg/scalatest/matchers/Matcher;Lorg/scalatest/matchers/Matcher;)Lorg/scalatest/matchers/Matcher;
         5: areturn
      LineNumberTable:
        line 150: 0
      LocalVariableTable:
        Start  Length  Slot  Name   Signature
            0       6     0  this   Lorg/scalatest/matchers/dsl/HaveWord$$anon$7;
            0       6     1 rightMatcher   Lorg/scalatest/matchers/Matcher;
    Signature: #84                          // <U:TT;>(Lorg/scalatest/matchers/Matcher<TU;>;)Lorg/scalatest/matchers/Matcher<TU;>;
    MethodParameters:
      Name                           Flags
      rightMatcher                   final

  public <U extends java.lang.Object, TC1 extends java.lang.Object> org.scalatest.matchers.dsl.MatcherFactory1<T, TC1> or(org.scalatest.matchers.dsl.MatcherFactory1<U, TC1>);
    descriptor: (Lorg/scalatest/matchers/dsl/MatcherFactory1;)Lorg/scalatest/matchers/dsl/MatcherFactory1;
    flags: (0x0001) ACC_PUBLIC
    Code:
      stack=2, locals=2, args_size=2
         0: aload_0
         1: aload_1
         2: invokestatic  #103                // InterfaceMethod org/scalatest/matchers/Matcher.or$:(Lorg/scalatest/matchers/Matcher;Lorg/scalatest/matchers/dsl/MatcherFactory1;)Lorg/scalatest/matchers/dsl/MatcherFactory1;
         5: areturn
      LineNumberTable:
        line 150: 0
      LocalVariableTable:
        Start  Length  Slot  Name   Signature
            0       6     0  this   Lorg/scalatest/matchers/dsl/HaveWord$$anon$7;
            0       6     1 rightMatcherFactory1   Lorg/scalatest/matchers/dsl/MatcherFactory1;
    Signature: #92                          // <U:Ljava/lang/Object;TC1:Ljava/lang/Object;>(Lorg/scalatest/matchers/dsl/MatcherFactory1<TU;TTC1;>;)Lorg/scalatest/matchers/dsl/MatcherFactory1<TT;TTC1;>;
    MethodParameters:
      Name                           Flags
      rightMatcherFactory1           final

  public org.scalatest.matchers.Matcher<T>.AndHaveWord and(org.scalatest.matchers.dsl.HaveWord);
    descriptor: (Lorg/scalatest/matchers/dsl/HaveWord;)Lorg/scalatest/matchers/Matcher$AndHaveWord;
    flags: (0x0001) ACC_PUBLIC
    Code:
      stack=2, locals=2, args_size=2
         0: aload_0
         1: aload_1
         2: invokestatic  #109                // InterfaceMethod org/scalatest/matchers/Matcher.and$:(Lorg/scalatest/matchers/Matcher;Lorg/scalatest/matchers/dsl/HaveWord;)Lorg/scalatest/matchers/Matcher$AndHaveWord;
         5: areturn
      LineNumberTable:
        line 150: 0
      LocalVariableTable:
        Start  Length  Slot  Name   Signature
            0       6     0  this   Lorg/scalatest/matchers/dsl/HaveWord$$anon$7;
            0       6     1 haveWord   Lorg/scalatest/matchers/dsl/HaveWord;
    Signature: #105                         // (Lorg/scalatest/matchers/dsl/HaveWord;)Lorg/scalatest/matchers/Matcher<TT;>.AndHaveWord;
    MethodParameters:
      Name                           Flags
      haveWord                       final

  public org.scalatest.matchers.Matcher<T>.AndContainWord and(org.scalatest.matchers.dsl.ContainWord, org.scalactic.Prettifier, org.scalactic.source.Position);
    descriptor: (Lorg/scalatest/matchers/dsl/ContainWord;Lorg/scalactic/Prettifier;Lorg/scalactic/source/Position;)Lorg/scalatest/matchers/Matcher$AndContainWord;
    flags: (0x0001) ACC_PUBLIC
    Code:
      stack=4, locals=4, args_size=4
         0: aload_0
         1: aload_1
         2: aload_2
         3: aload_3
         4: invokestatic  #118                // InterfaceMethod org/scalatest/matchers/Matcher.and$:(Lorg/scalatest/matchers/Matcher;Lorg/scalatest/matchers/dsl/ContainWord;Lorg/scalactic/Prettifier;Lorg/scalactic/source/Position;)Lorg/scalatest/matchers/Matcher$AndContainWord;
         7: areturn
      LineNumberTable:
        line 150: 0
      LocalVariableTable:
        Start  Length  Slot  Name   Signature
            0       8     0  this   Lorg/scalatest/matchers/dsl/HaveWord$$anon$7;
            0       8     1 containWord   Lorg/scalatest/matchers/dsl/ContainWord;
            0       8     2 prettifier   Lorg/scalactic/Prettifier;
            0       8     3   pos   Lorg/scalactic/source/Position;
    Signature: #112                         // (Lorg/scalatest/matchers/dsl/ContainWord;Lorg/scalactic/Prettifier;Lorg/scalactic/source/Position;)Lorg/scalatest/matchers/Matcher<TT;>.AndContainWord;
    MethodParameters:
      Name                           Flags
      containWord                    final
      prettifier                     final
      pos                            final

  public org.scalatest.matchers.Matcher<T>.AndBeWord and(org.scalatest.matchers.dsl.BeWord);
    descriptor: (Lorg/scalatest/matchers/dsl/BeWord;)Lorg/scalatest/matchers/Matcher$AndBeWord;
    flags: (0x0001) ACC_PUBLIC
    Code:
      stack=2, locals=2, args_size=2
         0: aload_0
         1: aload_1
         2: invokestatic  #127                // InterfaceMethod org/scalatest/matchers/Matcher.and$:(Lorg/scalatest/matchers/Matcher;Lorg/scalatest/matchers/dsl/BeWord;)Lorg/scalatest/matchers/Matcher$AndBeWord;
         5: areturn
      LineNumberTable:
        line 150: 0
      LocalVariableTable:
        Start  Length  Slot  Name   Signature
            0       6     0  this   Lorg/scalatest/matchers/dsl/HaveWord$$anon$7;
            0       6     1 beWord   Lorg/scalatest/matchers/dsl/BeWord;
    Signature: #123                         // (Lorg/scalatest/matchers/dsl/BeWord;)Lorg/scalatest/matchers/Matcher<TT;>.AndBeWord;
    MethodParameters:
      Name                           Flags
      beWord                         final

  public org.scalatest.matchers.Matcher<T>.AndFullyMatchWord and(org.scalatest.matchers.dsl.FullyMatchWord);
    descriptor: (Lorg/scalatest/matchers/dsl/FullyMatchWord;)Lorg/scalatest/matchers/Matcher$AndFullyMatchWord;
    flags: (0x0001) ACC_PUBLIC
    Code:
      stack=2, locals=2, args_size=2
         0: aload_0
         1: aload_1
         2: invokestatic  #134                // InterfaceMethod org/scalatest/matchers/Matcher.and$:(Lorg/scalatest/matchers/Matcher;Lorg/scalatest/matchers/dsl/FullyMatchWord;)Lorg/scalatest/matchers/Matcher$AndFullyMatchWord;
         5: areturn
      LineNumberTable:
        line 150: 0
      LocalVariableTable:
        Start  Length  Slot  Name   Signature
            0       6     0  this   Lorg/scalatest/matchers/dsl/HaveWord$$anon$7;
            0       6     1 fullyMatchWord   Lorg/scalatest/matchers/dsl/FullyMatchWord;
    Signature: #130                         // (Lorg/scalatest/matchers/dsl/FullyMatchWord;)Lorg/scalatest/matchers/Matcher<TT;>.AndFullyMatchWord;
    MethodParameters:
      Name                           Flags
      fullyMatchWord                 final

  public org.scalatest.matchers.Matcher<T>.AndIncludeWord and(org.scalatest.matchers.dsl.IncludeWord);
    descriptor: (Lorg/scalatest/matchers/dsl/IncludeWord;)Lorg/scalatest/matchers/Matcher$AndIncludeWord;
    flags: (0x0001) ACC_PUBLIC
    Code:
      stack=2, locals=2, args_size=2
         0: aload_0
         1: aload_1
         2: invokestatic  #141                // InterfaceMethod org/scalatest/matchers/Matcher.and$:(Lorg/scalatest/matchers/Matcher;Lorg/scalatest/matchers/dsl/IncludeWord;)Lorg/scalatest/matchers/Matcher$AndIncludeWord;
         5: areturn
      LineNumberTable:
        line 150: 0
      LocalVariableTable:
        Start  Length  Slot  Name   Signature
            0       6     0  this   Lorg/scalatest/matchers/dsl/HaveWord$$anon$7;
            0       6     1 includeWord   Lorg/scalatest/matchers/dsl/IncludeWord;
    Signature: #137                         // (Lorg/scalatest/matchers/dsl/IncludeWord;)Lorg/scalatest/matchers/Matcher<TT;>.AndIncludeWord;
    MethodParameters:
      Name                           Flags
      includeWord                    final

  public org.scalatest.matchers.Matcher<T>.AndStartWithWord and(org.scalatest.matchers.dsl.StartWithWord);
    descriptor: (Lorg/scalatest/matchers/dsl/StartWithWord;)Lorg/scalatest/matchers/Matcher$AndStartWithWord;
    flags: (0x0001) ACC_PUBLIC
    Code:
      stack=2, locals=2, args_size=2
         0: aload_0
         1: aload_1
         2: invokestatic  #148                // InterfaceMethod org/scalatest/matchers/Matcher.and$:(Lorg/scalatest/matchers/Matcher;Lorg/scalatest/matchers/dsl/StartWithWord;)Lorg/scalatest/matchers/Matcher$AndStartWithWord;
         5: areturn
      LineNumberTable:
        line 150: 0
      LocalVariableTable:
        Start  Length  Slot  Name   Signature
            0       6     0  this   Lorg/scalatest/matchers/dsl/HaveWord$$anon$7;
            0       6     1 startWithWord   Lorg/scalatest/matchers/dsl/StartWithWord;
    Signature: #144                         // (Lorg/scalatest/matchers/dsl/StartWithWord;)Lorg/scalatest/matchers/Matcher<TT;>.AndStartWithWord;
    MethodParameters:
      Name                           Flags
      startWithWord                  final

  public org.scalatest.matchers.Matcher<T>.AndEndWithWord and(org.scalatest.matchers.dsl.EndWithWord);
    descriptor: (Lorg/scalatest/matchers/dsl/EndWithWord;)Lorg/scalatest/matchers/Matcher$AndEndWithWord;
    flags: (0x0001) ACC_PUBLIC
    Code:
      stack=2, locals=2, args_size=2
         0: aload_0
         1: aload_1
         2: invokestatic  #155                // InterfaceMethod org/scalatest/matchers/Matcher.and$:(Lorg/scalatest/matchers/Matcher;Lorg/scalatest/matchers/dsl/EndWithWord;)Lorg/scalatest/matchers/Matcher$AndEndWithWord;
         5: areturn
      LineNumberTable:
        line 150: 0
      LocalVariableTable:
        Start  Length  Slot  Name   Signature
            0       6     0  this   Lorg/scalatest/matchers/dsl/HaveWord$$anon$7;
            0       6     1 endWithWord   Lorg/scalatest/matchers/dsl/EndWithWord;
    Signature: #151                         // (Lorg/scalatest/matchers/dsl/EndWithWord;)Lorg/scalatest/matchers/Matcher<TT;>.AndEndWithWord;
    MethodParameters:
      Name                           Flags
      endWithWord                    final

  public org.scalatest.matchers.Matcher<T>.AndNotWord and(org.scalatest.matchers.dsl.NotWord);
    descriptor: (Lorg/scalatest/matchers/dsl/NotWord;)Lorg/scalatest/matchers/Matcher$AndNotWord;
    flags: (0x0001) ACC_PUBLIC
    Code:
      stack=2, locals=2, args_size=2
         0: aload_0
         1: aload_1
         2: invokestatic  #162                // InterfaceMethod org/scalatest/matchers/Matcher.and$:(Lorg/scalatest/matchers/Matcher;Lorg/scalatest/matchers/dsl/NotWord;)Lorg/scalatest/matchers/Matcher$AndNotWord;
         5: areturn
      LineNumberTable:
        line 150: 0
      LocalVariableTable:
        Start  Length  Slot  Name   Signature
            0       6     0  this   Lorg/scalatest/matchers/dsl/HaveWord$$anon$7;
            0       6     1 notWord   Lorg/scalatest/matchers/dsl/NotWord;
    Signature: #158                         // (Lorg/scalatest/matchers/dsl/NotWord;)Lorg/scalatest/matchers/Matcher<TT;>.AndNotWord;
    MethodParameters:
      Name                           Flags
      notWord                        final

  public org.scalatest.matchers.dsl.MatcherFactory1<T, org.scalatest.enablers.Existence> and(org.scalatest.matchers.dsl.ExistWord);
    descriptor: (Lorg/scalatest/matchers/dsl/ExistWord;)Lorg/scalatest/matchers/dsl/MatcherFactory1;
    flags: (0x0001) ACC_PUBLIC
    Code:
      stack=2, locals=2, args_size=2
         0: aload_0
         1: aload_1
         2: invokestatic  #169                // InterfaceMethod org/scalatest/matchers/Matcher.and$:(Lorg/scalatest/matchers/Matcher;Lorg/scalatest/matchers/dsl/ExistWord;)Lorg/scalatest/matchers/dsl/MatcherFactory1;
         5: areturn
      LineNumberTable:
        line 150: 0
      LocalVariableTable:
        Start  Length  Slot  Name   Signature
            0       6     0  this   Lorg/scalatest/matchers/dsl/HaveWord$$anon$7;
            0       6     1 existWord   Lorg/scalatest/matchers/dsl/ExistWord;
    Signature: #165                         // (Lorg/scalatest/matchers/dsl/ExistWord;)Lorg/scalatest/matchers/dsl/MatcherFactory1<TT;Lorg/scalatest/enablers/Existence;>;
    MethodParameters:
      Name                           Flags
      existWord                      final

  public org.scalatest.matchers.dsl.MatcherFactory1<T, org.scalatest.enablers.Existence> and(org.scalatest.matchers.dsl.ResultOfNotExist);
    descriptor: (Lorg/scalatest/matchers/dsl/ResultOfNotExist;)Lorg/scalatest/matchers/dsl/MatcherFactory1;
    flags: (0x0001) ACC_PUBLIC
    Code:
      stack=2, locals=2, args_size=2
         0: aload_0
         1: aload_1
         2: invokestatic  #176                // InterfaceMethod org/scalatest/matchers/Matcher.and$:(Lorg/scalatest/matchers/Matcher;Lorg/scalatest/matchers/dsl/ResultOfNotExist;)Lorg/scalatest/matchers/dsl/MatcherFactory1;
         5: areturn
      LineNumberTable:
        line 150: 0
      LocalVariableTable:
        Start  Length  Slot  Name   Signature
            0       6     0  this   Lorg/scalatest/matchers/dsl/HaveWord$$anon$7;
            0       6     1 notExist   Lorg/scalatest/matchers/dsl/ResultOfNotExist;
    Signature: #172                         // (Lorg/scalatest/matchers/dsl/ResultOfNotExist;)Lorg/scalatest/matchers/dsl/MatcherFactory1<TT;Lorg/scalatest/enablers/Existence;>;
    MethodParameters:
      Name                           Flags
      notExist                       final

  public org.scalatest.matchers.Matcher<T>.OrHaveWord or(org.scalatest.matchers.dsl.HaveWord);
    descriptor: (Lorg/scalatest/matchers/dsl/HaveWord;)Lorg/scalatest/matchers/Matcher$OrHaveWord;
    flags: (0x0001) ACC_PUBLIC
    Code:
      stack=2, locals=2, args_size=2
         0: aload_0
         1: aload_1
         2: invokestatic  #182                // InterfaceMethod org/scalatest/matchers/Matcher.or$:(Lorg/scalatest/matchers/Matcher;Lorg/scalatest/matchers/dsl/HaveWord;)Lorg/scalatest/matchers/Matcher$OrHaveWord;
         5: areturn
      LineNumberTable:
        line 150: 0
      LocalVariableTable:
        Start  Length  Slot  Name   Signature
            0       6     0  this   Lorg/scalatest/matchers/dsl/HaveWord$$anon$7;
            0       6     1 haveWord   Lorg/scalatest/matchers/dsl/HaveWord;
    Signature: #179                         // (Lorg/scalatest/matchers/dsl/HaveWord;)Lorg/scalatest/matchers/Matcher<TT;>.OrHaveWord;
    MethodParameters:
      Name                           Flags
      haveWord                       final

  public org.scalatest.matchers.Matcher<T>.OrContainWord or(org.scalatest.matchers.dsl.ContainWord, org.scalactic.Prettifier, org.scalactic.source.Position);
    descriptor: (Lorg/scalatest/matchers/dsl/ContainWord;Lorg/scalactic/Prettifier;Lorg/scalactic/source/Position;)Lorg/scalatest/matchers/Matcher$OrContainWord;
    flags: (0x0001) ACC_PUBLIC
    Code:
      stack=4, locals=4, args_size=4
         0: aload_0
         1: aload_1
         2: aload_2
         3: aload_3
         4: invokestatic  #187                // InterfaceMethod org/scalatest/matchers/Matcher.or$:(Lorg/scalatest/matchers/Matcher;Lorg/scalatest/matchers/dsl/ContainWord;Lorg/scalactic/Prettifier;Lorg/scalactic/source/Position;)Lorg/scalatest/matchers/Matcher$OrContainWord;
         7: areturn
      LineNumberTable:
        line 150: 0
      LocalVariableTable:
        Start  Length  Slot  Name   Signature
            0       8     0  this   Lorg/scalatest/matchers/dsl/HaveWord$$anon$7;
            0       8     1 containWord   Lorg/scalatest/matchers/dsl/ContainWord;
            0       8     2 prettifier   Lorg/scalactic/Prettifier;
            0       8     3   pos   Lorg/scalactic/source/Position;
    Signature: #184                         // (Lorg/scalatest/matchers/dsl/ContainWord;Lorg/scalactic/Prettifier;Lorg/scalactic/source/Position;)Lorg/scalatest/matchers/Matcher<TT;>.OrContainWord;
    MethodParameters:
      Name                           Flags
      containWord                    final
      prettifier                     final
      pos                            final

  public org.scalatest.matchers.Matcher<T>.OrBeWord or(org.scalatest.matchers.dsl.BeWord);
    descriptor: (Lorg/scalatest/matchers/dsl/BeWord;)Lorg/scalatest/matchers/Matcher$OrBeWord;
    flags: (0x0001) ACC_PUBLIC
    Code:
      stack=2, locals=2, args_size=2
         0: aload_0
         1: aload_1
         2: invokestatic  #192                // InterfaceMethod org/scalatest/matchers/Matcher.or$:(Lorg/scalatest/matchers/Matcher;Lorg/scalatest/matchers/dsl/BeWord;)Lorg/scalatest/matchers/Matcher$OrBeWord;
         5: areturn
      LineNumberTable:
        line 150: 0
      LocalVariableTable:
        Start  Length  Slot  Name   Signature
            0       6     0  this   Lorg/scalatest/matchers/dsl/HaveWord$$anon$7;
            0       6     1 beWord   Lorg/scalatest/matchers/dsl/BeWord;
    Signature: #189                         // (Lorg/scalatest/matchers/dsl/BeWord;)Lorg/scalatest/matchers/Matcher<TT;>.OrBeWord;
    MethodParameters:
      Name                           Flags
      beWord                         final

  public org.scalatest.matchers.Matcher<T>.OrFullyMatchWord or(org.scalatest.matchers.dsl.FullyMatchWord);
    descriptor: (Lorg/scalatest/matchers/dsl/FullyMatchWord;)Lorg/scalatest/matchers/Matcher$OrFullyMatchWord;
    flags: (0x0001) ACC_PUBLIC
    Code:
      stack=2, locals=2, args_size=2
         0: aload_0
         1: aload_1
         2: invokestatic  #197                // InterfaceMethod org/scalatest/matchers/Matcher.or$:(Lorg/scalatest/matchers/Matcher;Lorg/scalatest/matchers/dsl/FullyMatchWord;)Lorg/scalatest/matchers/Matcher$OrFullyMatchWord;
         5: areturn
      LineNumberTable:
        line 150: 0
      LocalVariableTable:
        Start  Length  Slot  Name   Signature
            0       6     0  this   Lorg/scalatest/matchers/dsl/HaveWord$$anon$7;
            0       6     1 fullyMatchWord   Lorg/scalatest/matchers/dsl/FullyMatchWord;
    Signature: #194                         // (Lorg/scalatest/matchers/dsl/FullyMatchWord;)Lorg/scalatest/matchers/Matcher<TT;>.OrFullyMatchWord;
    MethodParameters:
      Name                           Flags
      fullyMatchWord                 final

  public org.scalatest.matchers.Matcher<T>.OrIncludeWord or(org.scalatest.matchers.dsl.IncludeWord);
    descriptor: (Lorg/scalatest/matchers/dsl/IncludeWord;)Lorg/scalatest/matchers/Matcher$OrIncludeWord;
    flags: (0x0001) ACC_PUBLIC
    Code:
      stack=2, locals=2, args_size=2
         0: aload_0
         1: aload_1
         2: invokestatic  #202                // InterfaceMethod org/scalatest/matchers/Matcher.or$:(Lorg/scalatest/matchers/Matcher;Lorg/scalatest/matchers/dsl/IncludeWord;)Lorg/scalatest/matchers/Matcher$OrIncludeWord;
         5: areturn
      LineNumberTable:
        line 150: 0
      LocalVariableTable:
        Start  Length  Slot  Name   Signature
            0       6     0  this   Lorg/scalatest/matchers/dsl/HaveWord$$anon$7;
            0       6     1 includeWord   Lorg/scalatest/matchers/dsl/IncludeWord;
    Signature: #199                         // (Lorg/scalatest/matchers/dsl/IncludeWord;)Lorg/scalatest/matchers/Matcher<TT;>.OrIncludeWord;
    MethodParameters:
      Name                           Flags
      includeWord                    final

  public org.scalatest.matchers.Matcher<T>.OrStartWithWord or(org.scalatest.matchers.dsl.StartWithWord);
    descriptor: (Lorg/scalatest/matchers/dsl/StartWithWord;)Lorg/scalatest/matchers/Matcher$OrStartWithWord;
    flags: (0x0001) ACC_PUBLIC
    Code:
      stack=2, locals=2, args_size=2
         0: aload_0
         1: aload_1
         2: invokestatic  #207                // InterfaceMethod org/scalatest/matchers/Matcher.or$:(Lorg/scalatest/matchers/Matcher;Lorg/scalatest/matchers/dsl/StartWithWord;)Lorg/scalatest/matchers/Matcher$OrStartWithWord;
         5: areturn
      LineNumberTable:
        line 150: 0
      LocalVariableTable:
        Start  Length  Slot  Name   Signature
            0       6     0  this   Lorg/scalatest/matchers/dsl/HaveWord$$anon$7;
            0       6     1 startWithWord   Lorg/scalatest/matchers/dsl/StartWithWord;
    Signature: #204                         // (Lorg/scalatest/matchers/dsl/StartWithWord;)Lorg/scalatest/matchers/Matcher<TT;>.OrStartWithWord;
    MethodParameters:
      Name                           Flags
      startWithWord                  final

  public org.scalatest.matchers.Matcher<T>.OrEndWithWord or(org.scalatest.matchers.dsl.EndWithWord);
    descriptor: (Lorg/scalatest/matchers/dsl/EndWithWord;)Lorg/scalatest/matchers/Matcher$OrEndWithWord;
    flags: (0x0001) ACC_PUBLIC
    Code:
      stack=2, locals=2, args_size=2
         0: aload_0
         1: aload_1
         2: invokestatic  #212                // InterfaceMethod org/scalatest/matchers/Matcher.or$:(Lorg/scalatest/matchers/Matcher;Lorg/scalatest/matchers/dsl/EndWithWord;)Lorg/scalatest/matchers/Matcher$OrEndWithWord;
         5: areturn
      LineNumberTable:
        line 150: 0
      LocalVariableTable:
        Start  Length  Slot  Name   Signature
            0       6     0  this   Lorg/scalatest/matchers/dsl/HaveWord$$anon$7;
            0       6     1 endWithWord   Lorg/scalatest/matchers/dsl/EndWithWord;
    Signature: #209                         // (Lorg/scalatest/matchers/dsl/EndWithWord;)Lorg/scalatest/matchers/Matcher<TT;>.OrEndWithWord;
    MethodParameters:
      Name                           Flags
      endWithWord                    final

  public org.scalatest.matchers.Matcher<T>.OrNotWord or(org.scalatest.matchers.dsl.NotWord);
    descriptor: (Lorg/scalatest/matchers/dsl/NotWord;)Lorg/scalatest/matchers/Matcher$OrNotWord;
    flags: (0x0001) ACC_PUBLIC
    Code:
      stack=2, locals=2, args_size=2
         0: aload_0
         1: aload_1
         2: invokestatic  #217                // InterfaceMethod org/scalatest/matchers/Matcher.or$:(Lorg/scalatest/matchers/Matcher;Lorg/scalatest/matchers/dsl/NotWord;)Lorg/scalatest/matchers/Matcher$OrNotWord;
         5: areturn
      LineNumberTable:
        line 150: 0
      LocalVariableTable:
        Start  Length  Slot  Name   Signature
            0       6     0  this   Lorg/scalatest/matchers/dsl/HaveWord$$anon$7;
            0       6     1 notWord   Lorg/scalatest/matchers/dsl/NotWord;
    Signature: #214                         // (Lorg/scalatest/matchers/dsl/NotWord;)Lorg/scalatest/matchers/Matcher<TT;>.OrNotWord;
    MethodParameters:
      Name                           Flags
      notWord                        final

  public org.scalatest.matchers.dsl.MatcherFactory1<T, org.scalatest.enablers.Existence> or(org.scalatest.matchers.dsl.ExistWord);
    descriptor: (Lorg/scalatest/matchers/dsl/ExistWord;)Lorg/scalatest/matchers/dsl/MatcherFactory1;
    flags: (0x0001) ACC_PUBLIC
    Code:
      stack=2, locals=2, args_size=2
         0: aload_0
         1: aload_1
         2: invokestatic  #219                // InterfaceMethod org/scalatest/matchers/Matcher.or$:(Lorg/scalatest/matchers/Matcher;Lorg/scalatest/matchers/dsl/ExistWord;)Lorg/scalatest/matchers/dsl/MatcherFactory1;
         5: areturn
      LineNumberTable:
        line 150: 0
      LocalVariableTable:
        Start  Length  Slot  Name   Signature
            0       6     0  this   Lorg/scalatest/matchers/dsl/HaveWord$$anon$7;
            0       6     1 existWord   Lorg/scalatest/matchers/dsl/ExistWord;
    Signature: #165                         // (Lorg/scalatest/matchers/dsl/ExistWord;)Lorg/scalatest/matchers/dsl/MatcherFactory1<TT;Lorg/scalatest/enablers/Existence;>;
    MethodParameters:
      Name                           Flags
      existWord                      final

  public org.scalatest.matchers.dsl.MatcherFactory1<T, org.scalatest.enablers.Existence> or(org.scalatest.matchers.dsl.ResultOfNotExist);
    descriptor: (Lorg/scalatest/matchers/dsl/ResultOfNotExist;)Lorg/scalatest/matchers/dsl/MatcherFactory1;
    flags: (0x0001) ACC_PUBLIC
    Code:
      stack=2, locals=2, args_size=2
         0: aload_0
         1: aload_1
         2: invokestatic  #221                // InterfaceMethod org/scalatest/matchers/Matcher.or$:(Lorg/scalatest/matchers/Matcher;Lorg/scalatest/matchers/dsl/ResultOfNotExist;)Lorg/scalatest/matchers/dsl/MatcherFactory1;
         5: areturn
      LineNumberTable:
        line 150: 0
      LocalVariableTable:
        Start  Length  Slot  Name   Signature
            0       6     0  this   Lorg/scalatest/matchers/dsl/HaveWord$$anon$7;
            0       6     1 notExist   Lorg/scalatest/matchers/dsl/ResultOfNotExist;
    Signature: #172                         // (Lorg/scalatest/matchers/dsl/ResultOfNotExist;)Lorg/scalatest/matchers/dsl/MatcherFactory1<TT;Lorg/scalatest/enablers/Existence;>;
    MethodParameters:
      Name                           Flags
      notExist                       final

  public org.scalatest.matchers.Matcher<T> mapResult(scala.Function1<org.scalatest.matchers.MatchResult, org.scalatest.matchers.MatchResult>);
    descriptor: (Lscala/Function1;)Lorg/scalatest/matchers/Matcher;
    flags: (0x0001) ACC_PUBLIC
    Code:
      stack=2, locals=2, args_size=2
         0: aload_0
         1: aload_1
         2: invokestatic  #227                // InterfaceMethod org/scalatest/matchers/Matcher.mapResult$:(Lorg/scalatest/matchers/Matcher;Lscala/Function1;)Lorg/scalatest/matchers/Matcher;
         5: areturn
      LineNumberTable:
        line 150: 0
      LocalVariableTable:
        Start  Length  Slot  Name   Signature
            0       6     0  this   Lorg/scalatest/matchers/dsl/HaveWord$$anon$7;
            0       6     1 prettify   Lscala/Function1;
    Signature: #223                         // (Lscala/Function1<Lorg/scalatest/matchers/MatchResult;Lorg/scalatest/matchers/MatchResult;>;)Lorg/scalatest/matchers/Matcher<TT;>;
    MethodParameters:
      Name                           Flags
      prettify                       final

  public org.scalatest.matchers.Matcher<T> mapArgs(scala.Function1<java.lang.Object, java.lang.String>);
    descriptor: (Lscala/Function1;)Lorg/scalatest/matchers/Matcher;
    flags: (0x0001) ACC_PUBLIC
    Code:
      stack=2, locals=2, args_size=2
         0: aload_0
         1: aload_1
         2: invokestatic  #232                // InterfaceMethod org/scalatest/matchers/Matcher.mapArgs$:(Lorg/scalatest/matchers/Matcher;Lscala/Function1;)Lorg/scalatest/matchers/Matcher;
         5: areturn
      LineNumberTable:
        line 150: 0
      LocalVariableTable:
        Start  Length  Slot  Name   Signature
            0       6     0  this   Lorg/scalatest/matchers/dsl/HaveWord$$anon$7;
            0       6     1 prettify   Lscala/Function1;
    Signature: #229                         // (Lscala/Function1<Ljava/lang/Object;Ljava/lang/String;>;)Lorg/scalatest/matchers/Matcher<TT;>;
    MethodParameters:
      Name                           Flags
      prettify                       final

  public boolean apply$mcZD$sp(double);
    descriptor: (D)Z
    flags: (0x0001) ACC_PUBLIC
    Code:
      stack=3, locals=3, args_size=2
         0: aload_0
         1: dload_1
         2: invokestatic  #241                // InterfaceMethod scala/Function1.apply$mcZD$sp$:(Lscala/Function1;D)Z
         5: ireturn
      LineNumberTable:
        line 150: 0
      LocalVariableTable:
        Start  Length  Slot  Name   Signature
            0       6     0  this   Lorg/scalatest/matchers/dsl/HaveWord$$anon$7;
            0       6     1    v1   D
    MethodParameters:
      Name                           Flags
      v1                             final

  public double apply$mcDD$sp(double);
    descriptor: (D)D
    flags: (0x0001) ACC_PUBLIC
    Code:
      stack=3, locals=3, args_size=2
         0: aload_0
         1: dload_1
         2: invokestatic  #248                // InterfaceMethod scala/Function1.apply$mcDD$sp$:(Lscala/Function1;D)D
         5: dreturn
      LineNumberTable:
        line 150: 0
      LocalVariableTable:
        Start  Length  Slot  Name   Signature
            0       6     0  this   Lorg/scalatest/matchers/dsl/HaveWord$$anon$7;
            0       6     1    v1   D
    MethodParameters:
      Name                           Flags
      v1                             final

  public float apply$mcFD$sp(double);
    descriptor: (D)F
    flags: (0x0001) ACC_PUBLIC
    Code:
      stack=3, locals=3, args_size=2
         0: aload_0
         1: dload_1
         2: invokestatic  #254                // InterfaceMethod scala/Function1.apply$mcFD$sp$:(Lscala/Function1;D)F
         5: freturn
      LineNumberTable:
        line 150: 0
      LocalVariableTable:
        Start  Length  Slot  Name   Signature
            0       6     0  this   Lorg/scalatest/matchers/dsl/HaveWord$$anon$7;
            0       6     1    v1   D
    MethodParameters:
      Name                           Flags
      v1                             final

  public int apply$mcID$sp(double);
    descriptor: (D)I
    flags: (0x0001) ACC_PUBLIC
    Code:
      stack=3, locals=3, args_size=2
         0: aload_0
         1: dload_1
         2: invokestatic  #260                // InterfaceMethod scala/Function1.apply$mcID$sp$:(Lscala/Function1;D)I
         5: ireturn
      LineNumberTable:
        line 150: 0
      LocalVariableTable:
        Start  Length  Slot  Name   Signature
            0       6     0  this   Lorg/scalatest/matchers/dsl/HaveWord$$anon$7;
            0       6     1    v1   D
    MethodParameters:
      Name                           Flags
      v1                             final

  public long apply$mcJD$sp(double);
    descriptor: (D)J
    flags: (0x0001) ACC_PUBLIC
    Code:
      stack=3, locals=3, args_size=2
         0: aload_0
         1: dload_1
         2: invokestatic  #266                // InterfaceMethod scala/Function1.apply$mcJD$sp$:(Lscala/Function1;D)J
         5: lreturn
      LineNumberTable:
        line 150: 0
      LocalVariableTable:
        Start  Length  Slot  Name   Signature
            0       6     0  this   Lorg/scalatest/matchers/dsl/HaveWord$$anon$7;
            0       6     1    v1   D
    MethodParameters:
      Name                           Flags
      v1                             final

  public void apply$mcVD$sp(double);
    descriptor: (D)V
    flags: (0x0001) ACC_PUBLIC
    Code:
      stack=3, locals=3, args_size=2
         0: aload_0
         1: dload_1
         2: invokestatic  #272                // InterfaceMethod scala/Function1.apply$mcVD$sp$:(Lscala/Function1;D)V
         5: return
      LineNumberTable:
        line 150: 0
      LocalVariableTable:
        Start  Length  Slot  Name   Signature
            0       6     0  this   Lorg/scalatest/matchers/dsl/HaveWord$$anon$7;
            0       6     1    v1   D
    MethodParameters:
      Name                           Flags
      v1                             final

  public boolean apply$mcZF$sp(float);
    descriptor: (F)Z
    flags: (0x0001) ACC_PUBLIC
    Code:
      stack=2, locals=2, args_size=2
         0: aload_0
         1: fload_1
         2: invokestatic  #278                // InterfaceMethod scala/Function1.apply$mcZF$sp$:(Lscala/Function1;F)Z
         5: ireturn
      LineNumberTable:
        line 150: 0
      LocalVariableTable:
        Start  Length  Slot  Name   Signature
            0       6     0  this   Lorg/scalatest/matchers/dsl/HaveWord$$anon$7;
            0       6     1    v1   F
    MethodParameters:
      Name                           Flags
      v1                             final

  public double apply$mcDF$sp(float);
    descriptor: (F)D
    flags: (0x0001) ACC_PUBLIC
    Code:
      stack=2, locals=2, args_size=2
         0: aload_0
         1: fload_1
         2: invokestatic  #285                // InterfaceMethod scala/Function1.apply$mcDF$sp$:(Lscala/Function1;F)D
         5: dreturn
      LineNumberTable:
        line 150: 0
      LocalVariableTable:
        Start  Length  Slot  Name   Signature
            0       6     0  this   Lorg/scalatest/matchers/dsl/HaveWord$$anon$7;
            0       6     1    v1   F
    MethodParameters:
      Name                           Flags
      v1                             final

  public float apply$mcFF$sp(float);
    descriptor: (F)F
    flags: (0x0001) ACC_PUBLIC
    Code:
      stack=2, locals=2, args_size=2
         0: aload_0
         1: fload_1
         2: invokestatic  #291                // InterfaceMethod scala/Function1.apply$mcFF$sp$:(Lscala/Function1;F)F
         5: freturn
      LineNumberTable:
        line 150: 0
      LocalVariableTable:
        Start  Length  Slot  Name   Signature
            0       6     0  this   Lorg/scalatest/matchers/dsl/HaveWord$$anon$7;
            0       6     1    v1   F
    MethodParameters:
      Name                           Flags
      v1                             final

  public int apply$mcIF$sp(float);
    descriptor: (F)I
    flags: (0x0001) ACC_PUBLIC
    Code:
      stack=2, locals=2, args_size=2
         0: aload_0
         1: fload_1
         2: invokestatic  #297                // InterfaceMethod scala/Function1.apply$mcIF$sp$:(Lscala/Function1;F)I
         5: ireturn
      LineNumberTable:
        line 150: 0
      LocalVariableTable:
        Start  Length  Slot  Name   Signature
            0       6     0  this   Lorg/scalatest/matchers/dsl/HaveWord$$anon$7;
            0       6     1    v1   F
    MethodParameters:
      Name                           Flags
      v1                             final

  public long apply$mcJF$sp(float);
    descriptor: (F)J
    flags: (0x0001) ACC_PUBLIC
    Code:
      stack=2, locals=2, args_size=2
         0: aload_0
         1: fload_1
         2: invokestatic  #303                // InterfaceMethod scala/Function1.apply$mcJF$sp$:(Lscala/Function1;F)J
         5: lreturn
      LineNumberTable:
        line 150: 0
      LocalVariableTable:
        Start  Length  Slot  Name   Signature
            0       6     0  this   Lorg/scalatest/matchers/dsl/HaveWord$$anon$7;
            0       6     1    v1   F
    MethodParameters:
      Name                           Flags
      v1                             final

  public void apply$mcVF$sp(float);
    descriptor: (F)V
    flags: (0x0001) ACC_PUBLIC
    Code:
      stack=2, locals=2, args_size=2
         0: aload_0
         1: fload_1
         2: invokestatic  #309                // InterfaceMethod scala/Function1.apply$mcVF$sp$:(Lscala/Function1;F)V
         5: return
      LineNumberTable:
        line 150: 0
      LocalVariableTable:
        Start  Length  Slot  Name   Signature
            0       6     0  this   Lorg/scalatest/matchers/dsl/HaveWord$$anon$7;
            0       6     1    v1   F
    MethodParameters:
      Name                           Flags
      v1                             final

  public boolean apply$mcZI$sp(int);
    descriptor: (I)Z
    flags: (0x0001) ACC_PUBLIC
    Code:
      stack=2, locals=2, args_size=2
         0: aload_0
         1: iload_1
         2: invokestatic  #315                // InterfaceMethod scala/Function1.apply$mcZI$sp$:(Lscala/Function1;I)Z
         5: ireturn
      LineNumberTable:
        line 150: 0
      LocalVariableTable:
        Start  Length  Slot  Name   Signature
            0       6     0  this   Lorg/scalatest/matchers/dsl/HaveWord$$anon$7;
            0       6     1    v1   I
    MethodParameters:
      Name                           Flags
      v1                             final

  public double apply$mcDI$sp(int);
    descriptor: (I)D
    flags: (0x0001) ACC_PUBLIC
    Code:
      stack=2, locals=2, args_size=2
         0: aload_0
         1: iload_1
         2: invokestatic  #322                // InterfaceMethod scala/Function1.apply$mcDI$sp$:(Lscala/Function1;I)D
         5: dreturn
      LineNumberTable:
        line 150: 0
      LocalVariableTable:
        Start  Length  Slot  Name   Signature
            0       6     0  this   Lorg/scalatest/matchers/dsl/HaveWord$$anon$7;
            0       6     1    v1   I
    MethodParameters:
      Name                           Flags
      v1                             final

  public float apply$mcFI$sp(int);
    descriptor: (I)F
    flags: (0x0001) ACC_PUBLIC
    Code:
      stack=2, locals=2, args_size=2
         0: aload_0
         1: iload_1
         2: invokestatic  #328                // InterfaceMethod scala/Function1.apply$mcFI$sp$:(Lscala/Function1;I)F
         5: freturn
      LineNumberTable:
        line 150: 0
      LocalVariableTable:
        Start  Length  Slot  Name   Signature
            0       6     0  this   Lorg/scalatest/matchers/dsl/HaveWord$$anon$7;
            0       6     1    v1   I
    MethodParameters:
      Name                           Flags
      v1                             final

  public int apply$mcII$sp(int);
    descriptor: (I)I
    flags: (0x0001) ACC_PUBLIC
    Code:
      stack=2, locals=2, args_size=2
         0: aload_0
         1: iload_1
         2: invokestatic  #334                // InterfaceMethod scala/Function1.apply$mcII$sp$:(Lscala/Function1;I)I
         5: ireturn
      LineNumberTable:
        line 150: 0
      LocalVariableTable:
        Start  Length  Slot  Name   Signature
            0       6     0  this   Lorg/scalatest/matchers/dsl/HaveWord$$anon$7;
            0       6     1    v1   I
    MethodParameters:
      Name                           Flags
      v1                             final

  public long apply$mcJI$sp(int);
    descriptor: (I)J
    flags: (0x0001) ACC_PUBLIC
    Code:
      stack=2, locals=2, args_size=2
         0: aload_0
         1: iload_1
         2: invokestatic  #340                // InterfaceMethod scala/Function1.apply$mcJI$sp$:(Lscala/Function1;I)J
         5: lreturn
      LineNumberTable:
        line 150: 0
      LocalVariableTable:
        Start  Length  Slot  Name   Signature
            0       6     0  this   Lorg/scalatest/matchers/dsl/HaveWord$$anon$7;
            0       6     1    v1   I
    MethodParameters:
      Name                           Flags
      v1                             final

  public void apply$mcVI$sp(int);
    descriptor: (I)V
    flags: (0x0001) ACC_PUBLIC
    Code:
      stack=2, locals=2, args_size=2
         0: aload_0
         1: iload_1
         2: invokestatic  #346                // InterfaceMethod scala/Function1.apply$mcVI$sp$:(Lscala/Function1;I)V
         5: return
      LineNumberTable:
        line 150: 0
      LocalVariableTable:
        Start  Length  Slot  Name   Signature
            0       6     0  this   Lorg/scalatest/matchers/dsl/HaveWord$$anon$7;
            0       6     1    v1   I
    MethodParameters:
      Name                           Flags
      v1                             final

  public boolean apply$mcZJ$sp(long);
    descriptor: (J)Z
    flags: (0x0001) ACC_PUBLIC
    Code:
      stack=3, locals=3, args_size=2
         0: aload_0
         1: lload_1
         2: invokestatic  #352                // InterfaceMethod scala/Function1.apply$mcZJ$sp$:(Lscala/Function1;J)Z
         5: ireturn
      LineNumberTable:
        line 150: 0
      LocalVariableTable:
        Start  Length  Slot  Name   Signature
            0       6     0  this   Lorg/scalatest/matchers/dsl/HaveWord$$anon$7;
            0       6     1    v1   J
    MethodParameters:
      Name                           Flags
      v1                             final

  public double apply$mcDJ$sp(long);
    descriptor: (J)D
    flags: (0x0001) ACC_PUBLIC
    Code:
      stack=3, locals=3, args_size=2
         0: aload_0
         1: lload_1
         2: invokestatic  #359                // InterfaceMethod scala/Function1.apply$mcDJ$sp$:(Lscala/Function1;J)D
         5: dreturn
      LineNumberTable:
        line 150: 0
      LocalVariableTable:
        Start  Length  Slot  Name   Signature
            0       6     0  this   Lorg/scalatest/matchers/dsl/HaveWord$$anon$7;
            0       6     1    v1   J
    MethodParameters:
      Name                           Flags
      v1                             final

  public float apply$mcFJ$sp(long);
    descriptor: (J)F
    flags: (0x0001) ACC_PUBLIC
    Code:
      stack=3, locals=3, args_size=2
         0: aload_0
         1: lload_1
         2: invokestatic  #365                // InterfaceMethod scala/Function1.apply$mcFJ$sp$:(Lscala/Function1;J)F
         5: freturn
      LineNumberTable:
        line 150: 0
      LocalVariableTable:
        Start  Length  Slot  Name   Signature
            0       6     0  this   Lorg/scalatest/matchers/dsl/HaveWord$$anon$7;
            0       6     1    v1   J
    MethodParameters:
      Name                           Flags
      v1                             final

  public int apply$mcIJ$sp(long);
    descriptor: (J)I
    flags: (0x0001) ACC_PUBLIC
    Code:
      stack=3, locals=3, args_size=2
         0: aload_0
         1: lload_1
         2: invokestatic  #371                // InterfaceMethod scala/Function1.apply$mcIJ$sp$:(Lscala/Function1;J)I
         5: ireturn
      LineNumberTable:
        line 150: 0
      LocalVariableTable:
        Start  Length  Slot  Name   Signature
            0       6     0  this   Lorg/scalatest/matchers/dsl/HaveWord$$anon$7;
            0       6     1    v1   J
    MethodParameters:
      Name                           Flags
      v1                             final

  public long apply$mcJJ$sp(long);
    descriptor: (J)J
    flags: (0x0001) ACC_PUBLIC
    Code:
      stack=3, locals=3, args_size=2
         0: aload_0
         1: lload_1
         2: invokestatic  #377                // InterfaceMethod scala/Function1.apply$mcJJ$sp$:(Lscala/Function1;J)J
         5: lreturn
      LineNumberTable:
        line 150: 0
      LocalVariableTable:
        Start  Length  Slot  Name   Signature
            0       6     0  this   Lorg/scalatest/matchers/dsl/HaveWord$$anon$7;
            0       6     1    v1   J
    MethodParameters:
      Name                           Flags
      v1                             final

  public void apply$mcVJ$sp(long);
    descriptor: (J)V
    flags: (0x0001) ACC_PUBLIC
    Code:
      stack=3, locals=3, args_size=2
         0: aload_0
         1: lload_1
         2: invokestatic  #383                // InterfaceMethod scala/Function1.apply$mcVJ$sp$:(Lscala/Function1;J)V
         5: return
      LineNumberTable:
        line 150: 0
      LocalVariableTable:
        Start  Length  Slot  Name   Signature
            0       6     0  this   Lorg/scalatest/matchers/dsl/HaveWord$$anon$7;
            0       6     1    v1   J
    MethodParameters:
      Name                           Flags
      v1                             final

  public <A extends java.lang.Object> scala.Function1<T, A> andThen(scala.Function1<org.scalatest.matchers.MatchResult, A>);
    descriptor: (Lscala/Function1;)Lscala/Function1;
    flags: (0x0001) ACC_PUBLIC
    Code:
      stack=2, locals=2, args_size=2
         0: aload_0
         1: aload_1
         2: invokestatic  #390                // InterfaceMethod scala/Function1.andThen$:(Lscala/Function1;Lscala/Function1;)Lscala/Function1;
         5: areturn
      LineNumberTable:
        line 150: 0
      LocalVariableTable:
        Start  Length  Slot  Name   Signature
            0       6     0  this   Lorg/scalatest/matchers/dsl/HaveWord$$anon$7;
            0       6     1     g   Lscala/Function1;
    Signature: #386                         // <A:Ljava/lang/Object;>(Lscala/Function1<Lorg/scalatest/matchers/MatchResult;TA;>;)Lscala/Function1<TT;TA;>;
    MethodParameters:
      Name                           Flags
      g                              final

  public org.scalatest.matchers.MatchResult apply(T);
    descriptor: (Ljava/lang/Object;)Lorg/scalatest/matchers/MatchResult;
    flags: (0x0001) ACC_PUBLIC
    Code:
      stack=10, locals=41, args_size=2
         0: aload_0
         1: getfield      #395                // Field firstPropertyMatcher$1:Lorg/scalatest/matchers/HavePropertyMatcher;
         4: astore        8
         6: aload_0
         7: getfield      #397                // Field propertyMatchers$1:Lscala/collection/immutable/Seq;
        10: invokeinterface #403,  1          // InterfaceMethod scala/collection/immutable/Seq.toList:()Lscala/collection/immutable/List;
        15: aload         8
        17: invokevirtual #409                // Method scala/collection/immutable/List.$colon$colon:(Ljava/lang/Object;)Lscala/collection/immutable/List;
        20: aload_1
        21: invokedynamic #430,  0            // InvokeDynamic #0:apply:(Ljava/lang/Object;)Lscala/Function1;
        26: invokevirtual #434                // Method scala/collection/immutable/List.map:(Lscala/Function1;)Lscala/collection/immutable/List;
        29: astore        7
        31: aload         7
        33: invokedynamic #443,  0            // InvokeDynamic #1:apply:()Lscala/Function1;
        38: invokevirtual #447                // Method scala/collection/immutable/List.find:(Lscala/Function1;)Lscala/Option;
        41: astore        9
        43: aload_0
        44: getfield      #397                // Field propertyMatchers$1:Lscala/collection/immutable/Seq;
        47: invokeinterface #451,  1          // InterfaceMethod scala/collection/immutable/Seq.isEmpty:()Z
        52: istore        10
        54: aload         9
        56: astore        11
        58: aload         11
        60: instanceof    #453                // class scala/Some
        63: ifeq          402
        66: aload         11
        68: checkcast     #453                // class scala/Some
        71: astore        12
        73: aload         12
        75: invokevirtual #457                // Method scala/Some.value:()Ljava/lang/Object;
        78: checkcast     #459                // class org/scalatest/matchers/HavePropertyMatchResult
        81: astore        13
        83: aload         13
        85: astore        14
        87: new           #461                // class scala/Tuple2
        90: dup
        91: getstatic     #467                // Field org/scalatest/Resources$.MODULE$:Lorg/scalatest/Resources$;
        94: invokevirtual #471                // Method org/scalatest/Resources$.rawPropertyDidNotHaveExpectedValue:()Ljava/lang/String;
        97: getstatic     #476                // Field scala/package$.MODULE$:Lscala/package$;
       100: invokevirtual #480                // Method scala/package$.Vector:()Lscala/collection/immutable/Vector$;
       103: getstatic     #485                // Field scala/runtime/ScalaRunTime$.MODULE$:Lscala/runtime/ScalaRunTime$;
       106: iconst_4
       107: anewarray     #5                  // class java/lang/Object
       110: dup
       111: iconst_0
       112: getstatic     #490                // Field org/scalatest/UnquotedString$.MODULE$:Lorg/scalatest/UnquotedString$;
       115: aload         14
       117: invokevirtual #493                // Method org/scalatest/matchers/HavePropertyMatchResult.propertyName:()Ljava/lang/String;
       120: invokevirtual #496                // Method org/scalatest/UnquotedString$.apply:(Ljava/lang/String;)Lorg/scalatest/UnquotedString;
       123: aastore
       124: dup
       125: iconst_1
       126: aload         14
       128: invokevirtual #499                // Method org/scalatest/matchers/HavePropertyMatchResult.expectedValue:()Ljava/lang/Object;
       131: aastore
       132: dup
       133: iconst_2
       134: aload         14
       136: invokevirtual #502                // Method org/scalatest/matchers/HavePropertyMatchResult.actualValue:()Ljava/lang/Object;
       139: aastore
       140: dup
       141: iconst_3
       142: aload_1
       143: aastore
       144: invokevirtual #506                // Method scala/runtime/ScalaRunTime$.genericWrapArray:(Ljava/lang/Object;)Lscala/collection/immutable/ArraySeq;
       147: invokevirtual #511                // Method scala/collection/immutable/Vector$.apply:(Lscala/collection/immutable/Seq;)Ljava/lang/Object;
       150: invokespecial #515                // Method scala/Tuple2."<init>":(Ljava/lang/Object;Ljava/lang/Object;)V
       153: astore        16
       155: aload         16
       157: ifnull        196
       160: aload         16
       162: invokevirtual #518                // Method scala/Tuple2._1:()Ljava/lang/Object;
       165: checkcast     #520                // class java/lang/String
       168: astore        17
       170: aload         16
       172: invokevirtual #523                // Method scala/Tuple2._2:()Ljava/lang/Object;
       175: checkcast     #525                // class scala/collection/immutable/Vector
       178: astore        18
       180: new           #461                // class scala/Tuple2
       183: dup
       184: aload         17
       186: aload         18
       188: invokespecial #515                // Method scala/Tuple2."<init>":(Ljava/lang/Object;Ljava/lang/Object;)V
       191: astore        6
       193: goto          209
       196: goto          199
       199: new           #527                // class scala/MatchError
       202: dup
       203: aload         16
       205: invokespecial #530                // Method scala/MatchError."<init>":(Ljava/lang/Object;)V
       208: athrow
       209: aload         6
       211: astore        15
       213: aload         15
       215: invokevirtual #518                // Method scala/Tuple2._1:()Ljava/lang/Object;
       218: checkcast     #520                // class java/lang/String
       221: astore        19
       223: aload         15
       225: invokevirtual #523                // Method scala/Tuple2._2:()Ljava/lang/Object;
       228: checkcast     #525                // class scala/collection/immutable/Vector
       231: astore        20
       233: new           #461                // class scala/Tuple2
       236: dup
       237: getstatic     #467                // Field org/scalatest/Resources$.MODULE$:Lorg/scalatest/Resources$;
       240: invokevirtual #533                // Method org/scalatest/Resources$.rawMidSentencePropertyDidNotHaveExpectedValue:()Ljava/lang/String;
       243: getstatic     #476                // Field scala/package$.MODULE$:Lscala/package$;
       246: invokevirtual #480                // Method scala/package$.Vector:()Lscala/collection/immutable/Vector$;
       249: getstatic     #485                // Field scala/runtime/ScalaRunTime$.MODULE$:Lscala/runtime/ScalaRunTime$;
       252: iconst_4
       253: anewarray     #5                  // class java/lang/Object
       256: dup
       257: iconst_0
       258: getstatic     #490                // Field org/scalatest/UnquotedString$.MODULE$:Lorg/scalatest/UnquotedString$;
       261: aload         14
       263: invokevirtual #493                // Method org/scalatest/matchers/HavePropertyMatchResult.propertyName:()Ljava/lang/String;
       266: invokevirtual #496                // Method org/scalatest/UnquotedString$.apply:(Ljava/lang/String;)Lorg/scalatest/UnquotedString;
       269: aastore
       270: dup
       271: iconst_1
       272: aload         14
       274: invokevirtual #499                // Method org/scalatest/matchers/HavePropertyMatchResult.expectedValue:()Ljava/lang/Object;
       277: aastore
       278: dup
       279: iconst_2
       280: aload         14
       282: invokevirtual #502                // Method org/scalatest/matchers/HavePropertyMatchResult.actualValue:()Ljava/lang/Object;
       285: aastore
       286: dup
       287: iconst_3
       288: aload_1
       289: aastore
       290: invokevirtual #506                // Method scala/runtime/ScalaRunTime$.genericWrapArray:(Ljava/lang/Object;)Lscala/collection/immutable/ArraySeq;
       293: invokevirtual #511                // Method scala/collection/immutable/Vector$.apply:(Lscala/collection/immutable/Seq;)Ljava/lang/Object;
       296: invokespecial #515                // Method scala/Tuple2."<init>":(Ljava/lang/Object;Ljava/lang/Object;)V
       299: astore        22
       301: aload         22
       303: ifnull        342
       306: aload         22
       308: invokevirtual #518                // Method scala/Tuple2._1:()Ljava/lang/Object;
       311: checkcast     #520                // class java/lang/String
       314: astore        23
       316: aload         22
       318: invokevirtual #523                // Method scala/Tuple2._2:()Ljava/lang/Object;
       321: checkcast     #525                // class scala/collection/immutable/Vector
       324: astore        24
       326: new           #461                // class scala/Tuple2
       329: dup
       330: aload         23
       332: aload         24
       334: invokespecial #515                // Method scala/Tuple2."<init>":(Ljava/lang/Object;Ljava/lang/Object;)V
       337: astore        5
       339: goto          355
       342: goto          345
       345: new           #527                // class scala/MatchError
       348: dup
       349: aload         22
       351: invokespecial #530                // Method scala/MatchError."<init>":(Ljava/lang/Object;)V
       354: athrow
       355: aload         5
       357: astore        21
       359: aload         21
       361: invokevirtual #518                // Method scala/Tuple2._1:()Ljava/lang/Object;
       364: checkcast     #520                // class java/lang/String
       367: astore        25
       369: aload         21
       371: invokevirtual #523                // Method scala/Tuple2._2:()Ljava/lang/Object;
       374: checkcast     #525                // class scala/collection/immutable/Vector
       377: astore        26
       379: getstatic     #538                // Field org/scalatest/matchers/MatchResult$.MODULE$:Lorg/scalatest/matchers/MatchResult$;
       382: iconst_0
       383: aload         19
       385: aload         19
       387: aload         25
       389: aload         25
       391: aload         20
       393: aload         26
       395: invokevirtual #541                // Method org/scalatest/matchers/MatchResult$.apply:(ZLjava/lang/String;Ljava/lang/String;Ljava/lang/String;Ljava/lang/String;Lscala/collection/immutable/IndexedSeq;Lscala/collection/immutable/IndexedSeq;)Lorg/scalatest/matchers/MatchResult;
       398: astore_2
       399: goto          834
       402: goto          405
       405: getstatic     #546                // Field scala/None$.MODULE$:Lscala/None$;
       408: aload         11
       410: invokevirtual #550                // Method java/lang/Object.equals:(Ljava/lang/Object;)Z
       413: ifeq          821
       416: iload         10
       418: ifeq          492
       421: aload         7
       423: invokevirtual #553                // Method scala/collection/immutable/List.head:()Ljava/lang/Object;
       426: checkcast     #459                // class org/scalatest/matchers/HavePropertyMatchResult
       429: astore        29
       431: new           #461                // class scala/Tuple2
       434: dup
       435: getstatic     #467                // Field org/scalatest/Resources$.MODULE$:Lorg/scalatest/Resources$;
       438: invokevirtual #556                // Method org/scalatest/Resources$.rawPropertyHadExpectedValue:()Ljava/lang/String;
       441: getstatic     #476                // Field scala/package$.MODULE$:Lscala/package$;
       444: invokevirtual #480                // Method scala/package$.Vector:()Lscala/collection/immutable/Vector$;
       447: getstatic     #485                // Field scala/runtime/ScalaRunTime$.MODULE$:Lscala/runtime/ScalaRunTime$;
       450: iconst_3
       451: anewarray     #5                  // class java/lang/Object
       454: dup
       455: iconst_0
       456: getstatic     #490                // Field org/scalatest/UnquotedString$.MODULE$:Lorg/scalatest/UnquotedString$;
       459: aload         29
       461: invokevirtual #493                // Method org/scalatest/matchers/HavePropertyMatchResult.propertyName:()Ljava/lang/String;
       464: invokevirtual #496                // Method org/scalatest/UnquotedString$.apply:(Ljava/lang/String;)Lorg/scalatest/UnquotedString;
       467: aastore
       468: dup
       469: iconst_1
       470: aload         29
       472: invokevirtual #499                // Method org/scalatest/matchers/HavePropertyMatchResult.expectedValue:()Ljava/lang/Object;
       475: aastore
       476: dup
       477: iconst_2
       478: aload_1
       479: aastore
       480: invokevirtual #506                // Method scala/runtime/ScalaRunTime$.genericWrapArray:(Ljava/lang/Object;)Lscala/collection/immutable/ArraySeq;
       483: invokevirtual #511                // Method scala/collection/immutable/Vector$.apply:(Lscala/collection/immutable/Seq;)Ljava/lang/Object;
       486: invokespecial #515                // Method scala/Tuple2."<init>":(Ljava/lang/Object;Ljava/lang/Object;)V
       489: goto          528
       492: new           #461                // class scala/Tuple2
       495: dup
       496: getstatic     #467                // Field org/scalatest/Resources$.MODULE$:Lorg/scalatest/Resources$;
       499: invokevirtual #559                // Method org/scalatest/Resources$.rawAllPropertiesHadExpectedValues:()Ljava/lang/String;
       502: getstatic     #476                // Field scala/package$.MODULE$:Lscala/package$;
       505: invokevirtual #480                // Method scala/package$.Vector:()Lscala/collection/immutable/Vector$;
       508: getstatic     #485                // Field scala/runtime/ScalaRunTime$.MODULE$:Lscala/runtime/ScalaRunTime$;
       511: iconst_1
       512: anewarray     #5                  // class java/lang/Object
       515: dup
       516: iconst_0
       517: aload_1
       518: aastore
       519: invokevirtual #506                // Method scala/runtime/ScalaRunTime$.genericWrapArray:(Ljava/lang/Object;)Lscala/collection/immutable/ArraySeq;
       522: invokevirtual #511                // Method scala/collection/immutable/Vector$.apply:(Lscala/collection/immutable/Seq;)Ljava/lang/Object;
       525: invokespecial #515                // Method scala/Tuple2."<init>":(Ljava/lang/Object;Ljava/lang/Object;)V
       528: astore        28
       530: aload         28
       532: ifnull        571
       535: aload         28
       537: invokevirtual #518                // Method scala/Tuple2._1:()Ljava/lang/Object;
       540: checkcast     #520                // class java/lang/String
       543: astore        30
       545: aload         28
       547: invokevirtual #523                // Method scala/Tuple2._2:()Ljava/lang/Object;
       550: checkcast     #525                // class scala/collection/immutable/Vector
       553: astore        31
       555: new           #461                // class scala/Tuple2
       558: dup
       559: aload         30
       561: aload         31
       563: invokespecial #515                // Method scala/Tuple2."<init>":(Ljava/lang/Object;Ljava/lang/Object;)V
       566: astore        4
       568: goto          584
       571: goto          574
       574: new           #527                // class scala/MatchError
       577: dup
       578: aload         28
       580: invokespecial #530                // Method scala/MatchError."<init>":(Ljava/lang/Object;)V
       583: athrow
       584: aload         4
       586: astore        27
       588: aload         27
       590: invokevirtual #518                // Method scala/Tuple2._1:()Ljava/lang/Object;
       593: checkcast     #520                // class java/lang/String
       596: astore        32
       598: aload         27
       600: invokevirtual #523                // Method scala/Tuple2._2:()Ljava/lang/Object;
       603: checkcast     #525                // class scala/collection/immutable/Vector
       606: astore        33
       608: iload         10
       610: ifeq          684
       613: aload         7
       615: invokevirtual #553                // Method scala/collection/immutable/List.head:()Ljava/lang/Object;
       618: checkcast     #459                // class org/scalatest/matchers/HavePropertyMatchResult
       621: astore        36
       623: new           #461                // class scala/Tuple2
       626: dup
       627: getstatic     #467                // Field org/scalatest/Resources$.MODULE$:Lorg/scalatest/Resources$;
       630: invokevirtual #562                // Method org/scalatest/Resources$.rawMidSentencePropertyHadExpectedValue:()Ljava/lang/String;
       633: getstatic     #476                // Field scala/package$.MODULE$:Lscala/package$;
       636: invokevirtual #480                // Method scala/package$.Vector:()Lscala/collection/immutable/Vector$;
       639: getstatic     #485                // Field scala/runtime/ScalaRunTime$.MODULE$:Lscala/runtime/ScalaRunTime$;
       642: iconst_3
       643: anewarray     #5                  // class java/lang/Object
       646: dup
       647: iconst_0
       648: getstatic     #490                // Field org/scalatest/UnquotedString$.MODULE$:Lorg/scalatest/UnquotedString$;
       651: aload         36
       653: invokevirtual #493                // Method org/scalatest/matchers/HavePropertyMatchResult.propertyName:()Ljava/lang/String;
       656: invokevirtual #496                // Method org/scalatest/UnquotedString$.apply:(Ljava/lang/String;)Lorg/scalatest/UnquotedString;
       659: aastore
       660: dup
       661: iconst_1
       662: aload         36
       664: invokevirtual #499                // Method org/scalatest/matchers/HavePropertyMatchResult.expectedValue:()Ljava/lang/Object;
       667: aastore
       668: dup
       669: iconst_2
       670: aload_1
       671: aastore
       672: invokevirtual #506                // Method scala/runtime/ScalaRunTime$.genericWrapArray:(Ljava/lang/Object;)Lscala/collection/immutable/ArraySeq;
       675: invokevirtual #511                // Method scala/collection/immutable/Vector$.apply:(Lscala/collection/immutable/Seq;)Ljava/lang/Object;
       678: invokespecial #515                // Method scala/Tuple2."<init>":(Ljava/lang/Object;Ljava/lang/Object;)V
       681: goto          720
       684: new           #461                // class scala/Tuple2
       687: dup
       688: getstatic     #467                // Field org/scalatest/Resources$.MODULE$:Lorg/scalatest/Resources$;
       691: invokevirtual #565                // Method org/scalatest/Resources$.rawMidSentenceAllPropertiesHadExpectedValues:()Ljava/lang/String;
       694: getstatic     #476                // Field scala/package$.MODULE$:Lscala/package$;
       697: invokevirtual #480                // Method scala/package$.Vector:()Lscala/collection/immutable/Vector$;
       700: getstatic     #485                // Field scala/runtime/ScalaRunTime$.MODULE$:Lscala/runtime/ScalaRunTime$;
       703: iconst_1
       704: anewarray     #5                  // class java/lang/Object
       707: dup
       708: iconst_0
       709: aload_1
       710: aastore
       711: invokevirtual #506                // Method scala/runtime/ScalaRunTime$.genericWrapArray:(Ljava/lang/Object;)Lscala/collection/immutable/ArraySeq;
       714: invokevirtual #511                // Method scala/collection/immutable/Vector$.apply:(Lscala/collection/immutable/Seq;)Ljava/lang/Object;
       717: invokespecial #515                // Method scala/Tuple2."<init>":(Ljava/lang/Object;Ljava/lang/Object;)V
       720: astore        35
       722: aload         35
       724: ifnull        762
       727: aload         35
       729: invokevirtual #518                // Method scala/Tuple2._1:()Ljava/lang/Object;
       732: checkcast     #520                // class java/lang/String
       735: astore        37
       737: aload         35
       739: invokevirtual #523                // Method scala/Tuple2._2:()Ljava/lang/Object;
       742: checkcast     #525                // class scala/collection/immutable/Vector
       745: astore        38
       747: new           #461                // class scala/Tuple2
       750: dup
       751: aload         37
       753: aload         38
       755: invokespecial #515                // Method scala/Tuple2."<init>":(Ljava/lang/Object;Ljava/lang/Object;)V
       758: astore_3
       759: goto          775
       762: goto          765
       765: new           #527                // class scala/MatchError
       768: dup
       769: aload         35
       771: invokespecial #530                // Method scala/MatchError."<init>":(Ljava/lang/Object;)V
       774: athrow
       775: aload_3
       776: astore        34
       778: aload         34
       780: invokevirtual #518                // Method scala/Tuple2._1:()Ljava/lang/Object;
       783: checkcast     #520                // class java/lang/String
       786: astore        39
       788: aload         34
       790: invokevirtual #523                // Method scala/Tuple2._2:()Ljava/lang/Object;
       793: checkcast     #525                // class scala/collection/immutable/Vector
       796: astore        40
       798: getstatic     #538                // Field org/scalatest/matchers/MatchResult$.MODULE$:Lorg/scalatest/matchers/MatchResult$;
       801: iconst_1
       802: aload         32
       804: aload         32
       806: aload         39
       808: aload         39
       810: aload         33
       812: aload         40
       814: invokevirtual #541                // Method org/scalatest/matchers/MatchResult$.apply:(ZLjava/lang/String;Ljava/lang/String;Ljava/lang/String;Ljava/lang/String;Lscala/collection/immutable/IndexedSeq;Lscala/collection/immutable/IndexedSeq;)Lorg/scalatest/matchers/MatchResult;
       817: astore_2
       818: goto          834
       821: goto          824
       824: new           #527                // class scala/MatchError
       827: dup
       828: aload         11
       830: invokespecial #530                // Method scala/MatchError."<init>":(Ljava/lang/Object;)V
       833: athrow
       834: aload_2
       835: areturn
      StackMapTable: number_of_entries = 21
        frame_type = 255 /* full_frame */
          offset_delta = 196
          locals = [ class org/scalatest/matchers/dsl/HaveWord$$anon$7, class java/lang/Object, top, top, top, top, top, class scala/collection/immutable/List, class org/scalatest/matchers/HavePropertyMatcher, class scala/Option, int, class scala/Option, class scala/Some, class org/scalatest/matchers/HavePropertyMatchResult, class org/scalatest/matchers/HavePropertyMatchResult, top, class scala/Tuple2 ]
          stack = []
        frame_type = 2 /* same */
        frame_type = 255 /* full_frame */
          offset_delta = 9
          locals = [ class org/scalatest/matchers/dsl/HaveWord$$anon$7, class java/lang/Object, top, top, top, top, class scala/Tuple2, class scala/collection/immutable/List, class org/scalatest/matchers/HavePropertyMatcher, class scala/Option, int, class scala/Option, class scala/Some, class org/scalatest/matchers/HavePropertyMatchResult, class org/scalatest/matchers/HavePropertyMatchResult, top, class scala/Tuple2, class java/lang/String, class scala/collection/immutable/Vector ]
          stack = []
        frame_type = 255 /* full_frame */
          offset_delta = 132
          locals = [ class org/scalatest/matchers/dsl/HaveWord$$anon$7, class java/lang/Object, top, top, top, top, class scala/Tuple2, class scala/collection/immutable/List, class org/scalatest/matchers/HavePropertyMatcher, class scala/Option, int, class scala/Option, class scala/Some, class org/scalatest/matchers/HavePropertyMatchResult, class org/scalatest/matchers/HavePropertyMatchResult, class scala/Tuple2, class scala/Tuple2, class java/lang/String, class scala/collection/immutable/Vector, class java/lang/String, class scala/collection/immutable/Vector, top, class scala/Tuple2 ]
          stack = []
        frame_type = 2 /* same */
        frame_type = 255 /* full_frame */
          offset_delta = 9
          locals = [ class org/scalatest/matchers/dsl/HaveWord$$anon$7, class java/lang/Object, top, top, top, class scala/Tuple2, class scala/Tuple2, class scala/collection/immutable/List, class org/scalatest/matchers/HavePropertyMatcher, class scala/Option, int, class scala/Option, class scala/Some, class org/scalatest/matchers/HavePropertyMatchResult, class org/scalatest/matchers/HavePropertyMatchResult, class scala/Tuple2, class scala/Tuple2, class java/lang/String, class scala/collection/immutable/Vector, class java/lang/String, class scala/collection/immutable/Vector, top, class scala/Tuple2, class java/lang/String, class scala/collection/immutable/Vector ]
          stack = []
        frame_type = 255 /* full_frame */
          offset_delta = 46
          locals = [ class org/scalatest/matchers/dsl/HaveWord$$anon$7, class java/lang/Object, top, top, top, top, top, class scala/collection/immutable/List, class org/scalatest/matchers/HavePropertyMatcher, class scala/Option, int, class scala/Option ]
          stack = []
        frame_type = 2 /* same */
        frame_type = 251 /* same_frame_extended */
          offset_delta = 86
        frame_type = 99 /* same_locals_1_stack_item */
          stack = [ class scala/Tuple2 ]
        frame_type = 255 /* full_frame */
          offset_delta = 42
          locals = [ class org/scalatest/matchers/dsl/HaveWord$$anon$7, class java/lang/Object, top, top, top, top, top, class scala/collection/immutable/List, class org/scalatest/matchers/HavePropertyMatcher, class scala/Option, int, class scala/Option, top, top, top, top, top, top, top, top, top, top, top, top, top, top, top, top, class scala/Tuple2 ]
          stack = []
        frame_type = 2 /* same */
        frame_type = 255 /* full_frame */
          offset_delta = 9
          locals = [ class org/scalatest/matchers/dsl/HaveWord$$anon$7, class java/lang/Object, top, top, class scala/Tuple2, top, top, class scala/collection/immutable/List, class org/scalatest/matchers/HavePropertyMatcher, class scala/Option, int, class scala/Option, top, top, top, top, top, top, top, top, top, top, top, top, top, top, top, top, class scala/Tuple2, top, class java/lang/String, class scala/collection/immutable/Vector ]
          stack = []
        frame_type = 255 /* full_frame */
          offset_delta = 99
          locals = [ class org/scalatest/matchers/dsl/HaveWord$$anon$7, class java/lang/Object, top, top, class scala/Tuple2, top, top, class scala/collection/immutable/List, class org/scalatest/matchers/HavePropertyMatcher, class scala/Option, int, class scala/Option, top, top, top, top, top, top, top, top, top, top, top, top, top, top, top, class scala/Tuple2, class scala/Tuple2, top, class java/lang/String, class scala/collection/immutable/Vector, class java/lang/String, class scala/collection/immutable/Vector ]
          stack = []
        frame_type = 99 /* same_locals_1_stack_item */
          stack = [ class scala/Tuple2 ]
        frame_type = 253 /* append */
          offset_delta = 41
          locals = [ top, class scala/Tuple2 ]
        frame_type = 2 /* same */
        frame_type = 255 /* full_frame */
          offset_delta = 9
          locals = [ class org/scalatest/matchers/dsl/HaveWord$$anon$7, class java/lang/Object, top, class scala/Tuple2, class scala/Tuple2, top, top, class scala/collection/immutable/List, class org/scalatest/matchers/HavePropertyMatcher, class scala/Option, int, class scala/Option, top, top, top, top, top, top, top, top, top, top, top, top, top, top, top, class scala/Tuple2, class scala/Tuple2, top, class java/lang/String, class scala/collection/immutable/Vector, class java/lang/String, class scala/collection/immutable/Vector, top, class scala/Tuple2, top, class java/lang/String, class scala/collection/immutable/Vector ]
          stack = []
        frame_type = 255 /* full_frame */
          offset_delta = 45
          locals = [ class org/scalatest/matchers/dsl/HaveWord$$anon$7, class java/lang/Object, top, top, top, top, top, class scala/collection/immutable/List, class org/scalatest/matchers/HavePropertyMatcher, class scala/Option, int, class scala/Option ]
          stack = []
        frame_type = 2 /* same */
        frame_type = 255 /* full_frame */
          offset_delta = 9
          locals = [ class org/scalatest/matchers/dsl/HaveWord$$anon$7, class java/lang/Object, class org/scalatest/matchers/MatchResult, top, top, top, top, class scala/collection/immutable/List, class org/scalatest/matchers/HavePropertyMatcher, class scala/Option, int, class scala/Option ]
          stack = []
      LineNumberTable:
        line 155: 0
        line 158: 31
        line 160: 43
        line 162: 54
        line 164: 58
        line 166: 83
        line 168: 87
        line 169: 91
        line 170: 97
        line 171: 112
        line 172: 126
        line 173: 134
        line 174: 142
        line 167: 155
        line 168: 199
        line 167: 213
        line 178: 233
        line 179: 237
        line 180: 243
        line 181: 258
        line 182: 272
        line 183: 280
        line 184: 288
        line 177: 301
        line 178: 345
        line 177: 359
        line 188: 379
        line 164: 402
        line 190: 405
        line 193: 416
        line 194: 421
        line 195: 431
        line 196: 435
        line 197: 441
        line 198: 456
        line 199: 470
        line 200: 478
        line 204: 492
        line 192: 530
        line 193: 574
        line 192: 588
        line 207: 608
        line 208: 613
        line 209: 623
        line 210: 627
        line 211: 633
        line 212: 648
        line 213: 662
        line 214: 670
        line 218: 684
        line 206: 722
        line 207: 765
        line 206: 778
        line 220: 798
        line 190: 821
        line 162: 824
      LocalVariableTable:
        Start  Length  Slot  Name   Signature
          170      26    17 rawFailureMessage   Ljava/lang/String;
          180      16    18 failureMessageArgs   Lscala/collection/immutable/Vector;
          316      26    23 rawMidSentenceFailureMessage   Ljava/lang/String;
          326      16    24 midSentenceFailureMessageArgs   Lscala/collection/immutable/Vector;
           87     311    14 failedVerification   Lorg/scalatest/matchers/HavePropertyMatchResult;
          223     175    19 rawFailureMessage   Ljava/lang/String;
          233     165    20 failureMessageArgs   Lscala/collection/immutable/Vector;
          369      29    25 rawMidSentenceFailureMessage   Ljava/lang/String;
          379      19    26 midSentenceFailureMessageArgs   Lscala/collection/immutable/Vector;
           83     319    13 firstFailure   Lorg/scalatest/matchers/HavePropertyMatchResult;
          431      58    29 firstPropertyResult   Lorg/scalatest/matchers/HavePropertyMatchResult;
          545      26    30 rawFailureMessage   Ljava/lang/String;
          555      16    31 failureMessageArgs   Lscala/collection/immutable/Vector;
          623      58    36 firstPropertyResult   Lorg/scalatest/matchers/HavePropertyMatchResult;
          737      25    37 rawMidSentenceFailureMessage   Ljava/lang/String;
          747      15    38 rawMidSentenceFailureMessageArgs   Lscala/collection/immutable/Vector;
          598     219    32 rawFailureMessage   Ljava/lang/String;
          608     209    33 failureMessageArgs   Lscala/collection/immutable/Vector;
          788      29    39 rawMidSentenceFailureMessage   Ljava/lang/String;
          798      19    40 rawMidSentenceFailureMessageArgs   Lscala/collection/immutable/Vector;
           31     804     7 results   Lscala/collection/immutable/List;
           43     792     9 firstFailureOption   Lscala/Option;
           54     781    10 justOneProperty   Z
            0     836     0  this   Lorg/scalatest/matchers/dsl/HaveWord$$anon$7;
            0     836     1  left   Ljava/lang/Object;
    Signature: #392                         // (TT;)Lorg/scalatest/matchers/MatchResult;
    MethodParameters:
      Name                           Flags
      left                           final

  public java.lang.String toString();
    descriptor: ()Ljava/lang/String;
    flags: (0x0001) ACC_PUBLIC
    Code:
      stack=3, locals=1, args_size=1
         0: new           #592                // class java/lang/StringBuilder
         3: dup
         4: ldc_w         #593                // int 7
         7: invokespecial #595                // Method java/lang/StringBuilder."<init>":(I)V
        10: ldc_w         #597                // String have (
        13: invokevirtual #601                // Method java/lang/StringBuilder.append:(Ljava/lang/String;)Ljava/lang/StringBuilder;
        16: getstatic     #606                // Field org/scalactic/Prettifier$.MODULE$:Lorg/scalactic/Prettifier$;
        19: invokevirtual #610                // Method org/scalactic/Prettifier$.default:()Lorg/scalactic/Prettifier;
        22: aload_0
        23: getfield      #395                // Field firstPropertyMatcher$1:Lorg/scalatest/matchers/HavePropertyMatcher;
        26: invokeinterface #615,  2          // InterfaceMethod org/scalactic/Prettifier.apply:(Ljava/lang/Object;)Ljava/lang/String;
        31: invokevirtual #601                // Method java/lang/StringBuilder.append:(Ljava/lang/String;)Ljava/lang/StringBuilder;
        34: ldc_w         #617                // String )
        37: invokevirtual #601                // Method java/lang/StringBuilder.append:(Ljava/lang/String;)Ljava/lang/StringBuilder;
        40: invokevirtual #619                // Method java/lang/StringBuilder.toString:()Ljava/lang/String;
        43: areturn
      LineNumberTable:
        line 224: 0
      LocalVariableTable:
        Start  Length  Slot  Name   Signature
            0      44     0  this   Lorg/scalatest/matchers/dsl/HaveWord$$anon$7;

  public scala.Function1 compose(scala.Function1);
    descriptor: (Lscala/Function1;)Lscala/Function1;
    flags: (0x1041) ACC_PUBLIC, ACC_BRIDGE, ACC_SYNTHETIC
    Code:
      stack=2, locals=2, args_size=2
         0: aload_0
         1: aload_1
         2: invokevirtual #621                // Method compose:(Lscala/Function1;)Lorg/scalatest/matchers/Matcher;
         5: areturn
      LineNumberTable:
        line 150: 0
      LocalVariableTable:
        Start  Length  Slot  Name   Signature
            0       6     0  this   Lorg/scalatest/matchers/dsl/HaveWord$$anon$7;
            0       6     1     g   Lscala/Function1;
    MethodParameters:
      Name                           Flags
      g                              final

  public java.lang.Object apply(java.lang.Object);
    descriptor: (Ljava/lang/Object;)Ljava/lang/Object;
    flags: (0x1041) ACC_PUBLIC, ACC_BRIDGE, ACC_SYNTHETIC
    Code:
      stack=2, locals=2, args_size=2
         0: aload_0
         1: aload_1
         2: invokevirtual #623                // Method apply:(Ljava/lang/Object;)Lorg/scalatest/matchers/MatchResult;
         5: areturn
      LineNumberTable:
        line 150: 0
      LocalVariableTable:
        Start  Length  Slot  Name   Signature
            0       6     0  this   Lorg/scalatest/matchers/dsl/HaveWord$$anon$7;
            0       6     1    v1   Ljava/lang/Object;
    MethodParameters:
      Name                           Flags
      v1                             final

  public static final org.scalatest.matchers.HavePropertyMatchResult $anonfun$apply$1(java.lang.Object, org.scalatest.matchers.HavePropertyMatcher);
    descriptor: (Ljava/lang/Object;Lorg/scalatest/matchers/HavePropertyMatcher;)Lorg/scalatest/matchers/HavePropertyMatchResult;
    flags: (0x1019) ACC_PUBLIC, ACC_STATIC, ACC_FINAL, ACC_SYNTHETIC
    Code:
      stack=2, locals=2, args_size=2
         0: aload_1
         1: aload_0
         2: invokeinterface #628,  2          // InterfaceMethod org/scalatest/matchers/HavePropertyMatcher.apply:(Ljava/lang/Object;)Lorg/scalatest/matchers/HavePropertyMatchResult;
         7: areturn
      LineNumberTable:
        line 156: 0
      LocalVariableTable:
        Start  Length  Slot  Name   Signature
            0       8     0 left$1   Ljava/lang/Object;
            0       8     1 propertyVerifier   Lorg/scalatest/matchers/HavePropertyMatcher;
    MethodParameters:
      Name                           Flags
      left$1                         final
      propertyVerifier               final

  public static final boolean $anonfun$apply$2(org.scalatest.matchers.HavePropertyMatchResult);
    descriptor: (Lorg/scalatest/matchers/HavePropertyMatchResult;)Z
    flags: (0x1019) ACC_PUBLIC, ACC_STATIC, ACC_FINAL, ACC_SYNTHETIC
    Code:
      stack=1, locals=1, args_size=1
         0: aload_0
         1: invokevirtual #634                // Method org/scalatest/matchers/HavePropertyMatchResult.matches:()Z
         4: ifne          11
         7: iconst_1
         8: goto          12
        11: iconst_0
        12: ireturn
      StackMapTable: number_of_entries = 2
        frame_type = 11 /* same */
        frame_type = 64 /* same_locals_1_stack_item */
          stack = [ int ]
      LineNumberTable:
        line 158: 0
      LocalVariableTable:
        Start  Length  Slot  Name   Signature
            0      13     0    pv   Lorg/scalatest/matchers/HavePropertyMatchResult;
    MethodParameters:
      Name                           Flags
      pv                             final

  public org.scalatest.matchers.dsl.HaveWord$$anon$7(org.scalatest.matchers.dsl.HaveWord, org.scalatest.matchers.HavePropertyMatcher, scala.collection.immutable.Seq);
    descriptor: (Lorg/scalatest/matchers/dsl/HaveWord;Lorg/scalatest/matchers/HavePropertyMatcher;Lscala/collection/immutable/Seq;)V
    flags: (0x0001) ACC_PUBLIC
    Code:
      stack=2, locals=4, args_size=4
         0: aload_0
         1: aload_2
         2: putfield      #395                // Field firstPropertyMatcher$1:Lorg/scalatest/matchers/HavePropertyMatcher;
         5: aload_0
         6: aload_3
         7: putfield      #397                // Field propertyMatchers$1:Lscala/collection/immutable/Seq;
        10: aload_0
        11: invokespecial #639                // Method java/lang/Object."<init>":()V
        14: aload_0
        15: invokestatic  #643                // InterfaceMethod scala/Function1.$init$:(Lscala/Function1;)V
        18: aload_0
        19: invokestatic  #646                // InterfaceMethod org/scalatest/matchers/Matcher.$init$:(Lorg/scalatest/matchers/Matcher;)V
        22: return
      LineNumberTable:
        line 148: 0
        line 150: 10
      LocalVariableTable:
        Start  Length  Slot  Name   Signature
            0      23     0  this   Lorg/scalatest/matchers/dsl/HaveWord$$anon$7;
            0      23     1 $outer   Lorg/scalatest/matchers/dsl/HaveWord;
            0      23     2 firstPropertyMatcher$1   Lorg/scalatest/matchers/HavePropertyMatcher;
            0      23     3 propertyMatchers$1   Lscala/collection/immutable/Seq;
    MethodParameters:
      Name                           Flags
      $outer                         final synthetic
      firstPropertyMatcher$1         final
      propertyMatchers$1             final

  public static final java.lang.Object $anonfun$apply$2$adapted(org.scalatest.matchers.HavePropertyMatchResult);
    descriptor: (Lorg/scalatest/matchers/HavePropertyMatchResult;)Ljava/lang/Object;
    flags: (0x1019) ACC_PUBLIC, ACC_STATIC, ACC_FINAL, ACC_SYNTHETIC
    Code:
      stack=1, locals=1, args_size=1
         0: aload_0
         1: invokestatic  #648                // Method $anonfun$apply$2:(Lorg/scalatest/matchers/HavePropertyMatchResult;)Z
         4: invokestatic  #654                // Method scala/runtime/BoxesRunTime.boxToBoolean:(Z)Ljava/lang/Boolean;
         7: areturn
      LineNumberTable:
        line 158: 0
      LocalVariableTable:
        Start  Length  Slot  Name   Signature
            0       8     0    pv   Lorg/scalatest/matchers/HavePropertyMatchResult;
    MethodParameters:
      Name                           Flags
      pv                             final

  private static java.lang.Object $deserializeLambda$(java.lang.invoke.SerializedLambda);
    descriptor: (Ljava/lang/invoke/SerializedLambda;)Ljava/lang/Object;
    flags: (0x100a) ACC_PRIVATE, ACC_STATIC, ACC_SYNTHETIC
    Code:
      stack=1, locals=1, args_size=1
         0: aload_0
         1: invokedynamic #666,  0            // InvokeDynamic #2:lambdaDeserialize:(Ljava/lang/invoke/SerializedLambda;)Ljava/lang/Object;
         6: areturn
}
InnerClasses:
  public static final #18= #15 of #17;    // Lookup=class java/lang/invoke/MethodHandles$Lookup of class java/lang/invoke/MethodHandles
  public final #21= #20 of #7;            // AndBeWord=class org/scalatest/matchers/Matcher$AndBeWord of class org/scalatest/matchers/Matcher
  public final #24= #23 of #7;            // AndContainWord=class org/scalatest/matchers/Matcher$AndContainWord of class org/scalatest/matchers/Matcher
  public final #27= #26 of #7;            // AndEndWithWord=class org/scalatest/matchers/Matcher$AndEndWithWord of class org/scalatest/matchers/Matcher
  public final #30= #29 of #7;            // AndFullyMatchWord=class org/scalatest/matchers/Matcher$AndFullyMatchWord of class org/scalatest/matchers/Matcher
  public final #33= #32 of #7;            // AndHaveWord=class org/scalatest/matchers/Matcher$AndHaveWord of class org/scalatest/matchers/Matcher
  public final #36= #35 of #7;            // AndIncludeWord=class org/scalatest/matchers/Matcher$AndIncludeWord of class org/scalatest/matchers/Matcher
  public final #39= #38 of #7;            // AndNotWord=class org/scalatest/matchers/Matcher$AndNotWord of class org/scalatest/matchers/Matcher
  public final #42= #41 of #7;            // AndStartWithWord=class org/scalatest/matchers/Matcher$AndStartWithWord of class org/scalatest/matchers/Matcher
  public final #45= #44 of #7;            // OrBeWord=class org/scalatest/matchers/Matcher$OrBeWord of class org/scalatest/matchers/Matcher
  public final #48= #47 of #7;            // OrContainWord=class org/scalatest/matchers/Matcher$OrContainWord of class org/scalatest/matchers/Matcher
  public final #51= #50 of #7;            // OrEndWithWord=class org/scalatest/matchers/Matcher$OrEndWithWord of class org/scalatest/matchers/Matcher
  public final #54= #53 of #7;            // OrFullyMatchWord=class org/scalatest/matchers/Matcher$OrFullyMatchWord of class org/scalatest/matchers/Matcher
  public final #57= #56 of #7;            // OrHaveWord=class org/scalatest/matchers/Matcher$OrHaveWord of class org/scalatest/matchers/Matcher
  public final #60= #59 of #7;            // OrIncludeWord=class org/scalatest/matchers/Matcher$OrIncludeWord of class org/scalatest/matchers/Matcher
  public final #63= #62 of #7;            // OrNotWord=class org/scalatest/matchers/Matcher$OrNotWord of class org/scalatest/matchers/Matcher
  public final #66= #65 of #7;            // OrStartWithWord=class org/scalatest/matchers/Matcher$OrStartWithWord of class org/scalatest/matchers/Matcher
  public final #2;                        // class org/scalatest/matchers/dsl/HaveWord$$anon$7
EnclosingMethod: #10.#13                // org.scalatest.matchers.dsl.HaveWord.apply
Signature: #3                           // Ljava/lang/Object;Lorg/scalatest/matchers/Matcher<TT;>;
SourceFile: "HaveWord.scala"
BootstrapMethods:
  0: #427 REF_invokeStatic java/lang/invoke/LambdaMetafactory.altMetafactory:(Ljava/lang/invoke/MethodHandles$Lookup;Ljava/lang/String;Ljava/lang/invoke/MethodType;[Ljava/lang/Object;)Ljava/lang/invoke/CallSite;
    Method arguments:
      #411 (Ljava/lang/Object;)Ljava/lang/Object;
      #416 REF_invokeStatic org/scalatest/matchers/dsl/HaveWord$$anon$7.$anonfun$apply$1:(Ljava/lang/Object;Lorg/scalatest/matchers/HavePropertyMatcher;)Lorg/scalatest/matchers/HavePropertyMatchResult;
      #418 (Lorg/scalatest/matchers/HavePropertyMatcher;)Lorg/scalatest/matchers/HavePropertyMatchResult;
      #419 5
      #420 1
      #418 (Lorg/scalatest/matchers/HavePropertyMatcher;)Lorg/scalatest/matchers/HavePropertyMatchResult;
  1: #427 REF_invokeStatic java/lang/invoke/LambdaMetafactory.altMetafactory:(Ljava/lang/invoke/MethodHandles$Lookup;Ljava/lang/String;Ljava/lang/invoke/MethodType;[Ljava/lang/Object;)Ljava/lang/invoke/CallSite;
    Method arguments:
      #411 (Ljava/lang/Object;)Ljava/lang/Object;
      #439 REF_invokeStatic org/scalatest/matchers/dsl/HaveWord$$anon$7.$anonfun$apply$2$adapted:(Lorg/scalatest/matchers/HavePropertyMatchResult;)Ljava/lang/Object;
      #440 (Lorg/scalatest/matchers/HavePropertyMatchResult;)Ljava/lang/Object;
      #419 5
      #420 1
      #440 (Lorg/scalatest/matchers/HavePropertyMatchResult;)Ljava/lang/Object;
  2: #663 REF_invokeStatic scala/runtime/LambdaDeserialize.bootstrap:(Ljava/lang/invoke/MethodHandles$Lookup;Ljava/lang/String;Ljava/lang/invoke/MethodType;[Ljava/lang/invoke/MethodHandle;)Ljava/lang/invoke/CallSite;
    Method arguments:
      #416 REF_invokeStatic org/scalatest/matchers/dsl/HaveWord$$anon$7.$anonfun$apply$1:(Ljava/lang/Object;Lorg/scalatest/matchers/HavePropertyMatcher;)Lorg/scalatest/matchers/HavePropertyMatchResult;
      #439 REF_invokeStatic org/scalatest/matchers/dsl/HaveWord$$anon$7.$anonfun$apply$2$adapted:(Lorg/scalatest/matchers/HavePropertyMatchResult;)Ljava/lang/Object;
  ScalaInlineInfo: length = 0x130 (unknown attribute)
   01 01 00 3C 01 9C 01 9D 01 02 75 02 76 01 01 B3
   01 B4 01 02 00 02 7B 01 00 52 00 53 01 00 52 00
   7A 01 00 52 00 6F 01 00 52 00 96 01 00 52 00 A4
   01 00 52 00 81 01 00 52 00 68 01 00 52 00 88 01
   00 52 00 5B 01 00 52 00 9D 01 00 52 00 AB 01 00
   52 00 8F 01 01 80 01 81 01 00 0B 01 9A 01 00 0B
   01 87 01 00 F3 00 F4 01 01 18 01 19 01 01 3D 01
   3E 01 01 62 01 63 01 00 F9 00 FA 01 01 1E 01 1F
   01 01 43 01 44 01 01 68 01 69 01 00 FF 01 00 01
   01 24 01 25 01 01 49 01 4A 01 01 6E 01 6F 01 01
   05 01 06 01 01 2A 01 2B 01 01 4F 01 50 01 01 74
   01 75 01 01 0B 01 0C 01 01 30 01 31 01 01 55 01
   56 01 01 7A 01 7B 01 00 E9 00 EA 01 01 11 01 12
   01 01 36 01 37 01 01 5B 01 5C 01 00 47 00 48 01
   00 47 01 81 01 00 E4 00 48 01 00 DE 00 48 01 00
   62 00 53 01 00 62 00 BC 01 00 62 00 B7 01 00 62
   00 D0 01 00 62 00 A4 01 00 62 00 C1 01 00 62 00
   B2 01 00 62 00 C6 01 00 62 00 5B 01 00 62 00 D5
   01 00 62 00 AB 01 00 62 00 CB 01 02 4E 01 D5 01

  Scala: length = 0x0 (unknown attribute)

