Classfile /Users/mw/Projects/slang-braindump/.jar/jar11/assemble/slang-braindump/assemble/content/org/scalatest/matchers/dsl/MatchPatternWord.class
  Last modified May 29, 2022; size 1668 bytes
  SHA-256 checksum a5f9d11783402aae63e528f01ad8eb662940fec11f84209aa20309fe7f2492b7
  Compiled from "MatchPatternWord.scala"
public final class org.scalatest.matchers.dsl.MatchPatternWord
  minor version: 0
  major version: 52
  flags: (0x0031) ACC_PUBLIC, ACC_FINAL, ACC_SUPER
  this_class: #2                          // org/scalatest/matchers/dsl/MatchPatternWord
  super_class: #4                         // java/lang/Object
  interfaces: 0, fields: 0, methods: 2, attributes: 4
Constant pool:
   #1 = Utf8               org/scalatest/matchers/dsl/MatchPatternWord
   #2 = Class              #1             // org/scalatest/matchers/dsl/MatchPatternWord
   #3 = Utf8               java/lang/Object
   #4 = Class              #3             // java/lang/Object
   #5 = Utf8               MatchPatternWord.scala
   #6 = Utf8               Lscala/reflect/ScalaSignature;
   #7 = Utf8               bytes
   #8 = Utf8               \u0006\u0005\u0005ea\u0001\u0002\u0003\u0006\u00059AQ!\u0006\u0001\u0005\u0002YAa!\u0007\u0001\u0003\n\u0003Q\u0002BB@\u0001\t\u0003\n\tA\u0001\tNCR\u001c\u0007\u000eU1ui\u0016\u0014hnV8sI*\u0011aaB\u0001\u0004INd\'B\u0001\u0005\n\u0003!i\u0017\r^2iKJ\u001c(B\u0001\u0006\f\u0003%\u00198-\u00197bi\u0016\u001cHOC\u0001\r\u0003\ry\'oZ\u0002\u0001\'\t\u0001q\u0002\u0005\u0002\u0011\'5\t\u0011CC\u0001\u0013\u0003\u0015\u00198-\u00197b\u0013\t!\u0012C\u0001\u0004B]f\u0014VMZ\u0001\u0007y%t\u0017\u000e\u001e \u0015\u0003]\u0001\"\u0001\u0007\u0001\u000e\u0003\u0015\tQ!\u00199qYf$\"a\u0007\u0012\u0011\u0007qir$D\u0001\b\u0013\tqrAA\u0004NCR\u001c\u0007.\u001a:\u0011\u0005A\u0001\u0013BA\u0011\u0012\u0005\r\te.\u001f\u0005\u0006G\t\u0001\r\u0001J\u0001\u0006e&<\u0007\u000e\u001e\u0019\u0003K)\u0002B\u0001\u0005\u0014 Q%\u0011q%\u0005\u0002\u0010!\u0006\u0014H/[1m\rVt7\r^5p]B\u0011\u0011F\u000b\u0007\u0001\t%Y#%!A\u0001\u0002\u000b\u0005AFA\u0002`IE\n\"!L\u0010\u0011\u0005Aq\u0013BA\u0018\u0012\u0005\u001dqu\u000e\u001e5j]\u001eD3AA\u0019<!\t\u0011\u0014(D\u00014\u0015\t!T\'\u0001\u0005j]R,\'O\\1m\u0015\t1t\'\u0001\u0004nC\u000e\u0014xn\u001d\u0006\u0003qE\tqA]3gY\u0016\u001cG/\u0003\u0002;g\tIQ.Y2s_&k\u0007\u000f\\\u0019\n?qjt\b\u0013)W?\"\\\u0001!\r\u0003%y5q\u0014!B7bGJ|\u0017\u0007\u0002\f=\u0001\u0012\u000b4!J!C\u001f\u0005\u0011\u0015%A\"\u0002\u00175\f7M]8F]\u001eLg.Z\u0019\u0004K\u00153u\"\u0001$\"\u0003\u001d\u000bQE^\u001c/a\u0001B\u0013.\u001c9mK6,g\u000e^3eA%t\u0007eU2bY\u0006\u0004#GL\u00192]AjS\nO\u00152\tYa\u0014*T\u0019\u0004K)[u\"A&\"\u00031\u000b\u0001\"[:Ck:$G.Z\u0019\u0004K9{u\"A(\u001a\u0003\u0001\tDA\u0006\u001fR+F\u001aQEU*\u0010\u0003M\u000b\u0013\u0001V\u0001\u000bSN\u0014E.Y2lE>D\u0018gA\u0013O\u001fF\"a\u0003P,\\c\r)\u0003,W\b\u00023\u0006\n!,A\u0005dY\u0006\u001c8OT1nKF\u001aQ\u0005X/\u0010\u0003u\u000b\u0013AX\u0001*_J<gf]2bY\u0006$Xm\u001d;/[\u0006$8\r[3sg:j\u0015\r^2i!\u0006$H/\u001a:o\u001b\u0006\u001c\'o\u001c\u00132\tYa\u0004\rZ\u0019\u0004K\u0005\u0014w\"\u00012\"\u0003\r\f!\"\\3uQ>$g*Y7fc\r)SMZ\b\u0002M\u0006\nq-A\nnCR\u001c\u0007\u000eU1ui\u0016\u0014h.T1uG\",\'/\r\u0003\u0017y%l\u0017gA\u0013kW>\t1.I\u0001m\u0003%\u0019\u0018n\u001a8biV\u0014X-M\u0003 y9,(0\r\u0003%y=\u0004\u0018B\u00019r\u0003\u0011a\u0015n\u001d;\u000b\u0005I\u001c\u0018!C5n[V$\u0018M\u00197f\u0015\t!\u0018#\u0001\u0006d_2dWm\u0019;j_:\fDa\b\u001fwoF\"A\u0005P8qc\r)\u00030_\b\u0002sv\tq@\r\u0003 ymd\u0018\u0007\u0002\u0013=_B\f4!J?\u007f\u001f\u0005qX$\u0001\u0000\u0002\u0011Q|7\u000b\u001e:j]\u001e$\"!a\u0001\u0011\t\u0005\u0015\u00111\u0003\b\u0005\u0003\u000f\ty\u0001E\u0002\u0002\nEi!!a\u0003\u000b\u0007\u00055Q\"\u0001\u0004=e>|GOP\u0005\u0004\u0003#\t\u0012A\u0002)sK\u0012,g-\u0003\u0003\u0002\u0016\u0005]!AB*ue&twMC\u0002\u0002\u0012E\u0001
   #9 = Utf8               toString
  #10 = Utf8               ()Ljava/lang/String;
  #11 = Utf8               matchPattern
  #12 = String             #11            // matchPattern
  #13 = Utf8               this
  #14 = Utf8               Lorg/scalatest/matchers/dsl/MatchPatternWord;
  #15 = Utf8               <init>
  #16 = Utf8               ()V
  #17 = NameAndType        #15:#16        // "<init>":()V
  #18 = Methodref          #4.#17         // java/lang/Object."<init>":()V
  #19 = Utf8               Code
  #20 = Utf8               LineNumberTable
  #21 = Utf8               LocalVariableTable
  #22 = Utf8               SourceFile
  #23 = Utf8               RuntimeVisibleAnnotations
  #24 = Utf8               ScalaInlineInfo
  #25 = Utf8               apply
  #26 = Utf8               (Lscala/PartialFunction;)Lorg/scalatest/matchers/Matcher;
  #27 = Utf8               ScalaSig
{
  public java.lang.String toString();
    descriptor: ()Ljava/lang/String;
    flags: (0x0001) ACC_PUBLIC
    Code:
      stack=1, locals=1, args_size=1
         0: ldc           #12                 // String matchPattern
         2: areturn
      LineNumberTable:
        line 45: 0
      LocalVariableTable:
        Start  Length  Slot  Name   Signature
            0       3     0  this   Lorg/scalatest/matchers/dsl/MatchPatternWord;

  public org.scalatest.matchers.dsl.MatchPatternWord();
    descriptor: ()V
    flags: (0x0001) ACC_PUBLIC
    Code:
      stack=1, locals=1, args_size=1
         0: aload_0
         1: invokespecial #18                 // Method java/lang/Object."<init>":()V
         4: return
      LineNumberTable:
        line 46: 0
        line 28: 4
      LocalVariableTable:
        Start  Length  Slot  Name   Signature
            0       5     0  this   Lorg/scalatest/matchers/dsl/MatchPatternWord;
}
SourceFile: "MatchPatternWord.scala"
RuntimeVisibleAnnotations:
  0: #6(#7=s#8)
    scala.reflect.ScalaSignature(
      bytes="\u0006\u0005\u0005ea\u0001\u0002\u0003\u0006\u00059AQ!\u0006\u0001\u0005\u0002YAa!\u0007\u0001\u0003\n\u0003Q\u0002BB@\u0001\t\u0003\n\tA\u0001\tNCR\u001c\u0007\u000eU1ui\u0016\u0014hnV8sI*\u0011aaB\u0001\u0004INd\'B\u0001\u0005\n\u0003!i\u0017\r^2iKJ\u001c(B\u0001\u0006\f\u0003%\u00198-\u00197bi\u0016\u001cHOC\u0001\r\u0003\ry\'oZ\u0002\u0001\'\t\u0001q\u0002\u0005\u0002\u0011\'5\t\u0011CC\u0001\u0013\u0003\u0015\u00198-\u00197b\u0013\t!\u0012C\u0001\u0004B]f\u0014VMZ\u0001\u0007y%t\u0017\u000e\u001e \u0015\u0003]\u0001\"\u0001\u0007\u0001\u000e\u0003\u0015\tQ!\u00199qYf$\"a\u0007\u0012\u0011\u0007qir$D\u0001\b\u0013\tqrAA\u0004NCR\u001c\u0007.\u001a:\u0011\u0005A\u0001\u0013BA\u0011\u0012\u0005\r\te.\u001f\u0005\u0006G\t\u0001\r\u0001J\u0001\u0006e&<\u0007\u000e\u001e\u0019\u0003K)\u0002B\u0001\u0005\u0014 Q%\u0011q%\u0005\u0002\u0010!\u0006\u0014H/[1m\rVt7\r^5p]B\u0011\u0011F\u000b\u0007\u0001\t%Y#%!A\u0001\u0002\u000b\u0005AFA\u0002`IE\n\"!L\u0010\u0011\u0005Aq\u0013BA\u0018\u0012\u0005\u001dqu\u000e\u001e5j]\u001eD3AA\u0019<!\t\u0011\u0014(D\u00014\u0015\t!T\'\u0001\u0005j]R,\'O\\1m\u0015\t1t\'\u0001\u0004nC\u000e\u0014xn\u001d\u0006\u0003qE\tqA]3gY\u0016\u001cG/\u0003\u0002;g\tIQ.Y2s_&k\u0007\u000f\\\u0019\n?qjt\b\u0013)W?\"\\\u0001!\r\u0003%y5q\u0014!B7bGJ|\u0017\u0007\u0002\f=\u0001\u0012\u000b4!J!C\u001f\u0005\u0011\u0015%A\"\u0002\u00175\f7M]8F]\u001eLg.Z\u0019\u0004K\u00153u\"\u0001$\"\u0003\u001d\u000bQE^\u001c/a\u0001B\u0013.\u001c9mK6,g\u000e^3eA%t\u0007eU2bY\u0006\u0004#GL\u00192]AjS\nO\u00152\tYa\u0014*T\u0019\u0004K)[u\"A&\"\u00031\u000b\u0001\"[:Ck:$G.Z\u0019\u0004K9{u\"A(\u001a\u0003\u0001\tDA\u0006\u001fR+F\u001aQEU*\u0010\u0003M\u000b\u0013\u0001V\u0001\u000bSN\u0014E.Y2lE>D\u0018gA\u0013O\u001fF\"a\u0003P,\\c\r)\u0003,W\b\u00023\u0006\n!,A\u0005dY\u0006\u001c8OT1nKF\u001aQ\u0005X/\u0010\u0003u\u000b\u0013AX\u0001*_J<gf]2bY\u0006$Xm\u001d;/[\u0006$8\r[3sg:j\u0015\r^2i!\u0006$H/\u001a:o\u001b\u0006\u001c\'o\u001c\u00132\tYa\u0004\rZ\u0019\u0004K\u0005\u0014w\"\u00012\"\u0003\r\f!\"\\3uQ>$g*Y7fc\r)SMZ\b\u0002M\u0006\nq-A\nnCR\u001c\u0007\u000eU1ui\u0016\u0014h.T1uG\",\'/\r\u0003\u0017y%l\u0017gA\u0013kW>\t1.I\u0001m\u0003%\u0019\u0018n\u001a8biV\u0014X-M\u0003 y9,(0\r\u0003%y=\u0004\u0018B\u00019r\u0003\u0011a\u0015n\u001d;\u000b\u0005I\u001c\u0018!C5n[V$\u0018M\u00197f\u0015\t!\u0018#\u0001\u0006d_2dWm\u0019;j_:\fDa\b\u001fwoF\"A\u0005P8qc\r)\u00030_\b\u0002sv\tq@\r\u0003 ymd\u0018\u0007\u0002\u0013=_B\f4!J?\u007f\u001f\u0005qX$\u0001\u0000\u0002\u0011Q|7\u000b\u001e:j]\u001e$\"!a\u0001\u0011\t\u0005\u0015\u00111\u0003\b\u0005\u0003\u000f\ty\u0001E\u0002\u0002\nEi!!a\u0003\u000b\u0007\u00055Q\"\u0001\u0004=e>|GOP\u0005\u0004\u0003#\t\u0012A\u0002)sK\u0012,g-\u0003\u0003\u0002\u0016\u0005]!AB*ue&twMC\u0002\u0002\u0012E\u0001"
    )
  ScalaInlineInfo: length = 0x13 (unknown attribute)
   01 01 00 03 00 0F 00 10 01 00 19 00 1A 01 00 09
   00 0A 01
  ScalaSig: length = 0x3 (unknown attribute)
   05 02 00
