Classfile /Users/mw/Projects/slang-braindump/.jar/jar11/assemble/slang-braindump/assemble/content/org/scalatest/matchers/dsl/MatcherFactory5$OrNotWord.class
  Last modified May 29, 2022; size 29769 bytes
  SHA-256 checksum 8e3f33f12945c1d06e2eec8f1f2ba42a34aff00ee7e922f0f07f0b1216ea40d5
  Compiled from "MatcherFactory5.scala"
public final class org.scalatest.matchers.dsl.MatcherFactory5$OrNotWord
  minor version: 0
  major version: 52
  flags: (0x0031) ACC_PUBLIC, ACC_FINAL, ACC_SUPER
  this_class: #2                          // org/scalatest/matchers/dsl/MatcherFactory5$OrNotWord
  super_class: #4                         // java/lang/Object
  interfaces: 0, fields: 3, methods: 56, attributes: 4
Constant pool:
    #1 = Utf8               org/scalatest/matchers/dsl/MatcherFactory5$OrNotWord
    #2 = Class              #1            // org/scalatest/matchers/dsl/MatcherFactory5$OrNotWord
    #3 = Utf8               java/lang/Object
    #4 = Class              #3            // java/lang/Object
    #5 = Utf8               MatcherFactory5.scala
    #6 = Utf8               org/scalactic/TripleEqualsSupport$Spread
    #7 = Class              #6            // org/scalactic/TripleEqualsSupport$Spread
    #8 = Utf8               org/scalactic/TripleEqualsSupport
    #9 = Class              #8            // org/scalactic/TripleEqualsSupport
   #10 = Utf8               Spread
   #11 = Utf8               org/scalactic/TripleEqualsSupport$TripleEqualsInvocation
   #12 = Class              #11           // org/scalactic/TripleEqualsSupport$TripleEqualsInvocation
   #13 = Utf8               TripleEqualsInvocation
   #14 = Utf8               org/scalatest/matchers/dsl/MatcherFactory5
   #15 = Class              #14           // org/scalatest/matchers/dsl/MatcherFactory5
   #16 = Utf8               OrNotWord
   #17 = Utf8               org/scalatest/matchers/dsl/MatcherFactory5$OrNotWord$$anon$26
   #18 = Class              #17           // org/scalatest/matchers/dsl/MatcherFactory5$OrNotWord$$anon$26
   #19 = Utf8               pos
   #20 = Utf8               Lorg/scalactic/source/Position;
   #21 = Utf8               owner
   #22 = Utf8               Lorg/scalatest/matchers/dsl/MatcherFactory5;
   #23 = Utf8               Lorg/scalatest/matchers/dsl/MatcherFactory5<TSC;TTC1;TTC2;TTC3;TTC4;TTC5;>;
   #24 = Utf8               $outer
   #25 = Utf8               ()Lorg/scalatest/matchers/dsl/MatcherFactory5;
   #26 = Utf8               ()Lorg/scalatest/matchers/dsl/MatcherFactory5<TSC;TTC1;TTC2;TTC3;TTC4;TTC5;>;
   #27 = NameAndType        #21:#22       // owner:Lorg/scalatest/matchers/dsl/MatcherFactory5;
   #28 = Fieldref           #2.#27        // org/scalatest/matchers/dsl/MatcherFactory5$OrNotWord.owner:Lorg/scalatest/matchers/dsl/MatcherFactory5;
   #29 = Utf8               this
   #30 = Utf8               Lorg/scalatest/matchers/dsl/MatcherFactory5$OrNotWord;
   #31 = Utf8               equal
   #32 = Utf8               (Ljava/lang/Object;)Lorg/scalatest/matchers/dsl/MatcherFactory6;
   #33 = Utf8               (Ljava/lang/Object;)Lorg/scalatest/matchers/dsl/MatcherFactory6<TSC;TTC1;TTC2;TTC3;TTC4;TTC5;Lorg/scalactic/Equality;>;
   #34 = Utf8               any
   #35 = NameAndType        #24:#22       // $outer:Lorg/scalatest/matchers/dsl/MatcherFactory5;
   #36 = Fieldref           #2.#35        // org/scalatest/matchers/dsl/MatcherFactory5$OrNotWord.$outer:Lorg/scalatest/matchers/dsl/MatcherFactory5;
   #37 = Utf8               org/scalatest/matchers/dsl/MatcherWords$
   #38 = Class              #37           // org/scalatest/matchers/dsl/MatcherWords$
   #39 = Utf8               MODULE$
   #40 = Utf8               Lorg/scalatest/matchers/dsl/MatcherWords$;
   #41 = NameAndType        #39:#40       // MODULE$:Lorg/scalatest/matchers/dsl/MatcherWords$;
   #42 = Fieldref           #38.#41       // org/scalatest/matchers/dsl/MatcherWords$.MODULE$:Lorg/scalatest/matchers/dsl/MatcherWords$;
   #43 = Utf8               not
   #44 = Utf8               ()Lorg/scalatest/matchers/dsl/NotWord;
   #45 = NameAndType        #43:#44       // not:()Lorg/scalatest/matchers/dsl/NotWord;
   #46 = Methodref          #38.#45       // org/scalatest/matchers/dsl/MatcherWords$.not:()Lorg/scalatest/matchers/dsl/NotWord;
   #47 = Utf8               (Ljava/lang/Object;)Lorg/scalatest/matchers/dsl/MatcherFactory1;
   #48 = NameAndType        #31:#47       // equal:(Ljava/lang/Object;)Lorg/scalatest/matchers/dsl/MatcherFactory1;
   #49 = Methodref          #38.#48       // org/scalatest/matchers/dsl/MatcherWords$.equal:(Ljava/lang/Object;)Lorg/scalatest/matchers/dsl/MatcherFactory1;
   #50 = Utf8               org/scalatest/matchers/dsl/NotWord
   #51 = Class              #50           // org/scalatest/matchers/dsl/NotWord
   #52 = Utf8               apply
   #53 = Utf8               (Lorg/scalatest/matchers/dsl/MatcherFactory1;)Lorg/scalatest/matchers/dsl/MatcherFactory1;
   #54 = NameAndType        #52:#53       // apply:(Lorg/scalatest/matchers/dsl/MatcherFactory1;)Lorg/scalatest/matchers/dsl/MatcherFactory1;
   #55 = Methodref          #51.#54       // org/scalatest/matchers/dsl/NotWord.apply:(Lorg/scalatest/matchers/dsl/MatcherFactory1;)Lorg/scalatest/matchers/dsl/MatcherFactory1;
   #56 = Utf8               or
   #57 = Utf8               (Lorg/scalatest/matchers/dsl/MatcherFactory1;)Lorg/scalatest/matchers/dsl/MatcherFactory6;
   #58 = NameAndType        #56:#57       // or:(Lorg/scalatest/matchers/dsl/MatcherFactory1;)Lorg/scalatest/matchers/dsl/MatcherFactory6;
   #59 = Methodref          #15.#58       // org/scalatest/matchers/dsl/MatcherFactory5.or:(Lorg/scalatest/matchers/dsl/MatcherFactory1;)Lorg/scalatest/matchers/dsl/MatcherFactory6;
   #60 = Utf8               Ljava/lang/Object;
   #61 = Utf8               (Lorg/scalactic/TripleEqualsSupport$Spread;)Lorg/scalatest/matchers/dsl/MatcherFactory5;
   #62 = Utf8               <U:Ljava/lang/Object;>(Lorg/scalactic/TripleEqualsSupport$Spread<TU;>;)Lorg/scalatest/matchers/dsl/MatcherFactory5<TSC;TTC1;TTC2;TTC3;TTC4;TTC5;>;
   #63 = Utf8               spread
   #64 = Utf8               (Lorg/scalactic/TripleEqualsSupport$Spread;)Lorg/scalatest/matchers/Matcher;
   #65 = NameAndType        #31:#64       // equal:(Lorg/scalactic/TripleEqualsSupport$Spread;)Lorg/scalatest/matchers/Matcher;
   #66 = Methodref          #51.#65       // org/scalatest/matchers/dsl/NotWord.equal:(Lorg/scalactic/TripleEqualsSupport$Spread;)Lorg/scalatest/matchers/Matcher;
   #67 = Utf8               (Lorg/scalatest/matchers/Matcher;)Lorg/scalatest/matchers/dsl/MatcherFactory5;
   #68 = NameAndType        #56:#67       // or:(Lorg/scalatest/matchers/Matcher;)Lorg/scalatest/matchers/dsl/MatcherFactory5;
   #69 = Methodref          #15.#68       // org/scalatest/matchers/dsl/MatcherFactory5.or:(Lorg/scalatest/matchers/Matcher;)Lorg/scalatest/matchers/dsl/MatcherFactory5;
   #70 = Utf8               Lorg/scalactic/TripleEqualsSupport$Spread;
   #71 = Utf8               (Lscala/runtime/Null$;)Lorg/scalatest/matchers/dsl/MatcherFactory5;
   #72 = Utf8               (Lscala/runtime/Null$;)Lorg/scalatest/matchers/dsl/MatcherFactory5<TSC;TTC1;TTC2;TTC3;TTC4;TTC5;>;
   #73 = Utf8               o
   #74 = Utf8               <init>
   #75 = Utf8               (Lorg/scalatest/matchers/dsl/MatcherFactory5$OrNotWord;)V
   #76 = NameAndType        #74:#75       // "<init>":(Lorg/scalatest/matchers/dsl/MatcherFactory5$OrNotWord;)V
   #77 = Methodref          #18.#76       // org/scalatest/matchers/dsl/MatcherFactory5$OrNotWord$$anon$26."<init>":(Lorg/scalatest/matchers/dsl/MatcherFactory5$OrNotWord;)V
   #78 = Utf8               Lscala/runtime/Null$;
   #79 = Utf8               be
   #80 = Utf8               (Ljava/lang/Object;)Lorg/scalatest/matchers/dsl/MatcherFactory5;
   #81 = Utf8               (Ljava/lang/Object;)Lorg/scalatest/matchers/dsl/MatcherFactory5<TSC;TTC1;TTC2;TTC3;TTC4;TTC5;>;
   #82 = Utf8               ()Lorg/scalatest/matchers/dsl/BeWord;
   #83 = NameAndType        #79:#82       // be:()Lorg/scalatest/matchers/dsl/BeWord;
   #84 = Methodref          #38.#83       // org/scalatest/matchers/dsl/MatcherWords$.be:()Lorg/scalatest/matchers/dsl/BeWord;
   #85 = Utf8               org/scalatest/matchers/dsl/BeWord
   #86 = Class              #85           // org/scalatest/matchers/dsl/BeWord
   #87 = Utf8               (Ljava/lang/Object;)Lorg/scalatest/matchers/Matcher;
   #88 = NameAndType        #52:#87       // apply:(Ljava/lang/Object;)Lorg/scalatest/matchers/Matcher;
   #89 = Methodref          #86.#88       // org/scalatest/matchers/dsl/BeWord.apply:(Ljava/lang/Object;)Lorg/scalatest/matchers/Matcher;
   #90 = Utf8               (Lorg/scalatest/matchers/Matcher;)Lorg/scalatest/matchers/Matcher;
   #91 = NameAndType        #52:#90       // apply:(Lorg/scalatest/matchers/Matcher;)Lorg/scalatest/matchers/Matcher;
   #92 = Methodref          #51.#91       // org/scalatest/matchers/dsl/NotWord.apply:(Lorg/scalatest/matchers/Matcher;)Lorg/scalatest/matchers/Matcher;
   #93 = Utf8               have
   #94 = Utf8               (Lorg/scalatest/matchers/dsl/ResultOfLengthWordApplication;)Lorg/scalatest/matchers/dsl/MatcherFactory6;
   #95 = Utf8               (Lorg/scalatest/matchers/dsl/ResultOfLengthWordApplication;)Lorg/scalatest/matchers/dsl/MatcherFactory6<TSC;TTC1;TTC2;TTC3;TTC4;TTC5;Lorg/scalatest/enablers/Length;>;
   #96 = Utf8               resultOfLengthWordApplication
   #97 = Utf8               ()Lorg/scalatest/matchers/dsl/HaveWord;
   #98 = NameAndType        #93:#97       // have:()Lorg/scalatest/matchers/dsl/HaveWord;
   #99 = Methodref          #38.#98       // org/scalatest/matchers/dsl/MatcherWords$.have:()Lorg/scalatest/matchers/dsl/HaveWord;
  #100 = Utf8               org/scalatest/matchers/dsl/ResultOfLengthWordApplication
  #101 = Class              #100          // org/scalatest/matchers/dsl/ResultOfLengthWordApplication
  #102 = Utf8               expectedLength
  #103 = Utf8               ()J
  #104 = NameAndType        #102:#103     // expectedLength:()J
  #105 = Methodref          #101.#104     // org/scalatest/matchers/dsl/ResultOfLengthWordApplication.expectedLength:()J
  #106 = Utf8               org/scalatest/matchers/dsl/HaveWord
  #107 = Class              #106          // org/scalatest/matchers/dsl/HaveWord
  #108 = Utf8               length
  #109 = Utf8               (J)Lorg/scalatest/matchers/dsl/MatcherFactory1;
  #110 = NameAndType        #108:#109     // length:(J)Lorg/scalatest/matchers/dsl/MatcherFactory1;
  #111 = Methodref          #107.#110     // org/scalatest/matchers/dsl/HaveWord.length:(J)Lorg/scalatest/matchers/dsl/MatcherFactory1;
  #112 = Utf8               Lorg/scalatest/matchers/dsl/ResultOfLengthWordApplication;
  #113 = Utf8               (Lorg/scalatest/matchers/dsl/ResultOfSizeWordApplication;)Lorg/scalatest/matchers/dsl/MatcherFactory6;
  #114 = Utf8               (Lorg/scalatest/matchers/dsl/ResultOfSizeWordApplication;)Lorg/scalatest/matchers/dsl/MatcherFactory6<TSC;TTC1;TTC2;TTC3;TTC4;TTC5;Lorg/scalatest/enablers/Size;>;
  #115 = Utf8               resultOfSizeWordApplication
  #116 = Utf8               org/scalatest/matchers/dsl/ResultOfSizeWordApplication
  #117 = Class              #116          // org/scalatest/matchers/dsl/ResultOfSizeWordApplication
  #118 = Utf8               expectedSize
  #119 = NameAndType        #118:#103     // expectedSize:()J
  #120 = Methodref          #117.#119     // org/scalatest/matchers/dsl/ResultOfSizeWordApplication.expectedSize:()J
  #121 = Utf8               size
  #122 = NameAndType        #121:#109     // size:(J)Lorg/scalatest/matchers/dsl/MatcherFactory1;
  #123 = Methodref          #107.#122     // org/scalatest/matchers/dsl/HaveWord.size:(J)Lorg/scalatest/matchers/dsl/MatcherFactory1;
  #124 = Utf8               Lorg/scalatest/matchers/dsl/ResultOfSizeWordApplication;
  #125 = Utf8               (Lorg/scalatest/matchers/dsl/ResultOfMessageWordApplication;)Lorg/scalatest/matchers/dsl/MatcherFactory6;
  #126 = Utf8               (Lorg/scalatest/matchers/dsl/ResultOfMessageWordApplication;)Lorg/scalatest/matchers/dsl/MatcherFactory6<TSC;TTC1;TTC2;TTC3;TTC4;TTC5;Lorg/scalatest/enablers/Messaging;>;
  #127 = Utf8               resultOfMessageWordApplication
  #128 = Utf8               org/scalatest/matchers/dsl/ResultOfMessageWordApplication
  #129 = Class              #128          // org/scalatest/matchers/dsl/ResultOfMessageWordApplication
  #130 = Utf8               expectedMessage
  #131 = Utf8               ()Ljava/lang/String;
  #132 = NameAndType        #130:#131     // expectedMessage:()Ljava/lang/String;
  #133 = Methodref          #129.#132     // org/scalatest/matchers/dsl/ResultOfMessageWordApplication.expectedMessage:()Ljava/lang/String;
  #134 = Utf8               message
  #135 = Utf8               (Ljava/lang/String;)Lorg/scalatest/matchers/dsl/MatcherFactory1;
  #136 = NameAndType        #134:#135     // message:(Ljava/lang/String;)Lorg/scalatest/matchers/dsl/MatcherFactory1;
  #137 = Methodref          #107.#136     // org/scalatest/matchers/dsl/HaveWord.message:(Ljava/lang/String;)Lorg/scalatest/matchers/dsl/MatcherFactory1;
  #138 = Utf8               Lorg/scalatest/matchers/dsl/ResultOfMessageWordApplication;
  #139 = Utf8               (Lorg/scalatest/matchers/HavePropertyMatcher;Lscala/collection/immutable/Seq;)Lorg/scalatest/matchers/dsl/MatcherFactory5;
  #140 = Utf8               <U:Ljava/lang/Object;>(Lorg/scalatest/matchers/HavePropertyMatcher<TU;*>;Lscala/collection/immutable/Seq<Lorg/scalatest/matchers/HavePropertyMatcher<TU;*>;>;)Lorg/scalatest/matchers/dsl/MatcherFactory5<TSC;TTC1;TTC2;TTC3;TTC4;TTC5;>;
  #141 = Utf8               firstPropertyMatcher
  #142 = Utf8               propertyMatchers
  #143 = Utf8               (Lorg/scalatest/matchers/HavePropertyMatcher;Lscala/collection/immutable/Seq;)Lorg/scalatest/matchers/Matcher;
  #144 = NameAndType        #52:#143      // apply:(Lorg/scalatest/matchers/HavePropertyMatcher;Lscala/collection/immutable/Seq;)Lorg/scalatest/matchers/Matcher;
  #145 = Methodref          #107.#144     // org/scalatest/matchers/dsl/HaveWord.apply:(Lorg/scalatest/matchers/HavePropertyMatcher;Lscala/collection/immutable/Seq;)Lorg/scalatest/matchers/Matcher;
  #146 = Utf8               Lorg/scalatest/matchers/HavePropertyMatcher;
  #147 = Utf8               Lscala/collection/immutable/Seq;
  #148 = Utf8               (Lscala/runtime/Null$;)Lorg/scalatest/matchers/dsl/MatcherFactory5<Ljava/lang/Object;TTC1;TTC2;TTC3;TTC4;TTC5;>;
  #149 = Utf8               (Lscala/runtime/Null$;)Lorg/scalatest/matchers/Matcher;
  #150 = NameAndType        #79:#149      // be:(Lscala/runtime/Null$;)Lorg/scalatest/matchers/Matcher;
  #151 = Methodref          #51.#150      // org/scalatest/matchers/dsl/NotWord.be:(Lscala/runtime/Null$;)Lorg/scalatest/matchers/Matcher;
  #152 = Utf8               (Lorg/scalatest/matchers/dsl/ResultOfLessThanComparison;)Lorg/scalatest/matchers/dsl/MatcherFactory5;
  #153 = Utf8               <U:Ljava/lang/Object;>(Lorg/scalatest/matchers/dsl/ResultOfLessThanComparison<TU;>;)Lorg/scalatest/matchers/dsl/MatcherFactory5<TSC;TTC1;TTC2;TTC3;TTC4;TTC5;>;
  #154 = Utf8               resultOfLessThanComparison
  #155 = Utf8               (Lorg/scalatest/matchers/dsl/ResultOfLessThanComparison;)Lorg/scalatest/matchers/Matcher;
  #156 = NameAndType        #79:#155      // be:(Lorg/scalatest/matchers/dsl/ResultOfLessThanComparison;)Lorg/scalatest/matchers/Matcher;
  #157 = Methodref          #51.#156      // org/scalatest/matchers/dsl/NotWord.be:(Lorg/scalatest/matchers/dsl/ResultOfLessThanComparison;)Lorg/scalatest/matchers/Matcher;
  #158 = Utf8               Lorg/scalatest/matchers/dsl/ResultOfLessThanComparison;
  #159 = Utf8               (Lorg/scalatest/matchers/dsl/ResultOfGreaterThanComparison;)Lorg/scalatest/matchers/dsl/MatcherFactory5;
  #160 = Utf8               <U:Ljava/lang/Object;>(Lorg/scalatest/matchers/dsl/ResultOfGreaterThanComparison<TU;>;)Lorg/scalatest/matchers/dsl/MatcherFactory5<TSC;TTC1;TTC2;TTC3;TTC4;TTC5;>;
  #161 = Utf8               resultOfGreaterThanComparison
  #162 = Utf8               (Lorg/scalatest/matchers/dsl/ResultOfGreaterThanComparison;)Lorg/scalatest/matchers/Matcher;
  #163 = NameAndType        #79:#162      // be:(Lorg/scalatest/matchers/dsl/ResultOfGreaterThanComparison;)Lorg/scalatest/matchers/Matcher;
  #164 = Methodref          #51.#163      // org/scalatest/matchers/dsl/NotWord.be:(Lorg/scalatest/matchers/dsl/ResultOfGreaterThanComparison;)Lorg/scalatest/matchers/Matcher;
  #165 = Utf8               Lorg/scalatest/matchers/dsl/ResultOfGreaterThanComparison;
  #166 = Utf8               (Lorg/scalatest/matchers/dsl/ResultOfLessThanOrEqualToComparison;)Lorg/scalatest/matchers/dsl/MatcherFactory5;
  #167 = Utf8               <U:Ljava/lang/Object;>(Lorg/scalatest/matchers/dsl/ResultOfLessThanOrEqualToComparison<TU;>;)Lorg/scalatest/matchers/dsl/MatcherFactory5<TSC;TTC1;TTC2;TTC3;TTC4;TTC5;>;
  #168 = Utf8               resultOfLessThanOrEqualToComparison
  #169 = Utf8               (Lorg/scalatest/matchers/dsl/ResultOfLessThanOrEqualToComparison;)Lorg/scalatest/matchers/Matcher;
  #170 = NameAndType        #79:#169      // be:(Lorg/scalatest/matchers/dsl/ResultOfLessThanOrEqualToComparison;)Lorg/scalatest/matchers/Matcher;
  #171 = Methodref          #51.#170      // org/scalatest/matchers/dsl/NotWord.be:(Lorg/scalatest/matchers/dsl/ResultOfLessThanOrEqualToComparison;)Lorg/scalatest/matchers/Matcher;
  #172 = Utf8               Lorg/scalatest/matchers/dsl/ResultOfLessThanOrEqualToComparison;
  #173 = Utf8               (Lorg/scalatest/matchers/dsl/ResultOfGreaterThanOrEqualToComparison;)Lorg/scalatest/matchers/dsl/MatcherFactory5;
  #174 = Utf8               <U:Ljava/lang/Object;>(Lorg/scalatest/matchers/dsl/ResultOfGreaterThanOrEqualToComparison<TU;>;)Lorg/scalatest/matchers/dsl/MatcherFactory5<TSC;TTC1;TTC2;TTC3;TTC4;TTC5;>;
  #175 = Utf8               resultOfGreaterThanOrEqualToComparison
  #176 = Utf8               (Lorg/scalatest/matchers/dsl/ResultOfGreaterThanOrEqualToComparison;)Lorg/scalatest/matchers/Matcher;
  #177 = NameAndType        #79:#176      // be:(Lorg/scalatest/matchers/dsl/ResultOfGreaterThanOrEqualToComparison;)Lorg/scalatest/matchers/Matcher;
  #178 = Methodref          #51.#177      // org/scalatest/matchers/dsl/NotWord.be:(Lorg/scalatest/matchers/dsl/ResultOfGreaterThanOrEqualToComparison;)Lorg/scalatest/matchers/Matcher;
  #179 = Utf8               Lorg/scalatest/matchers/dsl/ResultOfGreaterThanOrEqualToComparison;
  #180 = Utf8               (Lorg/scalactic/TripleEqualsSupport$TripleEqualsInvocation;)Lorg/scalatest/matchers/dsl/MatcherFactory5;
  #181 = Utf8               (Lorg/scalactic/TripleEqualsSupport$TripleEqualsInvocation<*>;)Lorg/scalatest/matchers/dsl/MatcherFactory5<TSC;TTC1;TTC2;TTC3;TTC4;TTC5;>;
  #182 = Utf8               tripleEqualsInvocation
  #183 = NameAndType        #19:#20       // pos:Lorg/scalactic/source/Position;
  #184 = Fieldref           #2.#183       // org/scalatest/matchers/dsl/MatcherFactory5$OrNotWord.pos:Lorg/scalactic/source/Position;
  #185 = Utf8               (Lorg/scalactic/TripleEqualsSupport$TripleEqualsInvocation;Lorg/scalactic/source/Position;)Lorg/scalatest/matchers/Matcher;
  #186 = NameAndType        #79:#185      // be:(Lorg/scalactic/TripleEqualsSupport$TripleEqualsInvocation;Lorg/scalactic/source/Position;)Lorg/scalatest/matchers/Matcher;
  #187 = Methodref          #51.#186      // org/scalatest/matchers/dsl/NotWord.be:(Lorg/scalactic/TripleEqualsSupport$TripleEqualsInvocation;Lorg/scalactic/source/Position;)Lorg/scalatest/matchers/Matcher;
  #188 = Utf8               Lorg/scalactic/TripleEqualsSupport$TripleEqualsInvocation;
  #189 = Utf8               (Lorg/scalatest/matchers/BeMatcher;)Lorg/scalatest/matchers/dsl/MatcherFactory5;
  #190 = Utf8               <U:Ljava/lang/Object;>(Lorg/scalatest/matchers/BeMatcher<TU;>;)Lorg/scalatest/matchers/dsl/MatcherFactory5<TSC;TTC1;TTC2;TTC3;TTC4;TTC5;>;
  #191 = Utf8               beMatcher
  #192 = Utf8               (Lorg/scalatest/matchers/BeMatcher;)Lorg/scalatest/matchers/Matcher;
  #193 = NameAndType        #79:#192      // be:(Lorg/scalatest/matchers/BeMatcher;)Lorg/scalatest/matchers/Matcher;
  #194 = Methodref          #51.#193      // org/scalatest/matchers/dsl/NotWord.be:(Lorg/scalatest/matchers/BeMatcher;)Lorg/scalatest/matchers/Matcher;
  #195 = Utf8               Lorg/scalatest/matchers/BeMatcher;
  #196 = Utf8               (Lorg/scalatest/matchers/BePropertyMatcher;)Lorg/scalatest/matchers/dsl/MatcherFactory5;
  #197 = Utf8               <U:Ljava/lang/Object;>(Lorg/scalatest/matchers/BePropertyMatcher<TU;>;)Lorg/scalatest/matchers/dsl/MatcherFactory5<Ljava/lang/Object;TTC1;TTC2;TTC3;TTC4;TTC5;>;
  #198 = Utf8               bePropertyMatcher
  #199 = Utf8               (Lorg/scalatest/matchers/BePropertyMatcher;)Lorg/scalatest/matchers/Matcher;
  #200 = NameAndType        #79:#199      // be:(Lorg/scalatest/matchers/BePropertyMatcher;)Lorg/scalatest/matchers/Matcher;
  #201 = Methodref          #51.#200      // org/scalatest/matchers/dsl/NotWord.be:(Lorg/scalatest/matchers/BePropertyMatcher;)Lorg/scalatest/matchers/Matcher;
  #202 = Utf8               Lorg/scalatest/matchers/BePropertyMatcher;
  #203 = Utf8               (Lorg/scalatest/matchers/dsl/ResultOfAWordToAMatcherApplication;)Lorg/scalatest/matchers/dsl/MatcherFactory5;
  #204 = Utf8               <U:Ljava/lang/Object;>(Lorg/scalatest/matchers/dsl/ResultOfAWordToAMatcherApplication<TU;>;)Lorg/scalatest/matchers/dsl/MatcherFactory5<TSC;TTC1;TTC2;TTC3;TTC4;TTC5;>;
  #205 = Utf8               resultOfAWordApplication
  #206 = Utf8               (Lorg/scalatest/matchers/dsl/ResultOfAWordToAMatcherApplication;)Lorg/scalatest/matchers/Matcher;
  #207 = NameAndType        #79:#206      // be:(Lorg/scalatest/matchers/dsl/ResultOfAWordToAMatcherApplication;)Lorg/scalatest/matchers/Matcher;
  #208 = Methodref          #51.#207      // org/scalatest/matchers/dsl/NotWord.be:(Lorg/scalatest/matchers/dsl/ResultOfAWordToAMatcherApplication;)Lorg/scalatest/matchers/Matcher;
  #209 = Utf8               Lorg/scalatest/matchers/dsl/ResultOfAWordToAMatcherApplication;
  #210 = Utf8               (Lorg/scalatest/matchers/dsl/ResultOfAWordToBePropertyMatcherApplication;)Lorg/scalatest/matchers/dsl/MatcherFactory5;
  #211 = Utf8               <U:Ljava/lang/Object;>(Lorg/scalatest/matchers/dsl/ResultOfAWordToBePropertyMatcherApplication<TU;>;)Lorg/scalatest/matchers/dsl/MatcherFactory5<TSC;TTC1;TTC2;TTC3;TTC4;TTC5;>;
  #212 = Utf8               (Lorg/scalatest/matchers/dsl/ResultOfAWordToBePropertyMatcherApplication;)Lorg/scalatest/matchers/Matcher;
  #213 = NameAndType        #79:#212      // be:(Lorg/scalatest/matchers/dsl/ResultOfAWordToBePropertyMatcherApplication;)Lorg/scalatest/matchers/Matcher;
  #214 = Methodref          #51.#213      // org/scalatest/matchers/dsl/NotWord.be:(Lorg/scalatest/matchers/dsl/ResultOfAWordToBePropertyMatcherApplication;)Lorg/scalatest/matchers/Matcher;
  #215 = Utf8               Lorg/scalatest/matchers/dsl/ResultOfAWordToBePropertyMatcherApplication;
  #216 = Utf8               (Lorg/scalatest/matchers/dsl/ResultOfAnWordToBePropertyMatcherApplication;)Lorg/scalatest/matchers/dsl/MatcherFactory5;
  #217 = Utf8               <U:Ljava/lang/Object;>(Lorg/scalatest/matchers/dsl/ResultOfAnWordToBePropertyMatcherApplication<TU;>;)Lorg/scalatest/matchers/dsl/MatcherFactory5<TSC;TTC1;TTC2;TTC3;TTC4;TTC5;>;
  #218 = Utf8               resultOfAnWordApplication
  #219 = Utf8               (Lorg/scalatest/matchers/dsl/ResultOfAnWordToBePropertyMatcherApplication;)Lorg/scalatest/matchers/Matcher;
  #220 = NameAndType        #79:#219      // be:(Lorg/scalatest/matchers/dsl/ResultOfAnWordToBePropertyMatcherApplication;)Lorg/scalatest/matchers/Matcher;
  #221 = Methodref          #51.#220      // org/scalatest/matchers/dsl/NotWord.be:(Lorg/scalatest/matchers/dsl/ResultOfAnWordToBePropertyMatcherApplication;)Lorg/scalatest/matchers/Matcher;
  #222 = Utf8               Lorg/scalatest/matchers/dsl/ResultOfAnWordToBePropertyMatcherApplication;
  #223 = Utf8               (Lorg/scalatest/matchers/dsl/ResultOfAnWordToAnMatcherApplication;)Lorg/scalatest/matchers/dsl/MatcherFactory5;
  #224 = Utf8               <U:Ljava/lang/Object;>(Lorg/scalatest/matchers/dsl/ResultOfAnWordToAnMatcherApplication<TU;>;)Lorg/scalatest/matchers/dsl/MatcherFactory5<TSC;TTC1;TTC2;TTC3;TTC4;TTC5;>;
  #225 = Utf8               (Lorg/scalatest/matchers/dsl/ResultOfAnWordToAnMatcherApplication;)Lorg/scalatest/matchers/Matcher;
  #226 = NameAndType        #79:#225      // be:(Lorg/scalatest/matchers/dsl/ResultOfAnWordToAnMatcherApplication;)Lorg/scalatest/matchers/Matcher;
  #227 = Methodref          #51.#226      // org/scalatest/matchers/dsl/NotWord.be:(Lorg/scalatest/matchers/dsl/ResultOfAnWordToAnMatcherApplication;)Lorg/scalatest/matchers/Matcher;
  #228 = Utf8               Lorg/scalatest/matchers/dsl/ResultOfAnWordToAnMatcherApplication;
  #229 = Utf8               (Lorg/scalatest/matchers/dsl/ResultOfTheSameInstanceAsApplication;)Lorg/scalatest/matchers/dsl/MatcherFactory5;
  #230 = Utf8               (Lorg/scalatest/matchers/dsl/ResultOfTheSameInstanceAsApplication;)Lorg/scalatest/matchers/dsl/MatcherFactory5<Ljava/lang/Object;TTC1;TTC2;TTC3;TTC4;TTC5;>;
  #231 = Utf8               resultOfTheSameInstanceAsApplication
  #232 = Utf8               (Lorg/scalatest/matchers/dsl/ResultOfTheSameInstanceAsApplication;)Lorg/scalatest/matchers/Matcher;
  #233 = NameAndType        #79:#232      // be:(Lorg/scalatest/matchers/dsl/ResultOfTheSameInstanceAsApplication;)Lorg/scalatest/matchers/Matcher;
  #234 = Methodref          #51.#233      // org/scalatest/matchers/dsl/NotWord.be:(Lorg/scalatest/matchers/dsl/ResultOfTheSameInstanceAsApplication;)Lorg/scalatest/matchers/Matcher;
  #235 = Utf8               Lorg/scalatest/matchers/dsl/ResultOfTheSameInstanceAsApplication;
  #236 = NameAndType        #79:#64       // be:(Lorg/scalactic/TripleEqualsSupport$Spread;)Lorg/scalatest/matchers/Matcher;
  #237 = Methodref          #51.#236      // org/scalatest/matchers/dsl/NotWord.be:(Lorg/scalactic/TripleEqualsSupport$Spread;)Lorg/scalatest/matchers/Matcher;
  #238 = Utf8               (Lorg/scalatest/matchers/dsl/ResultOfDefinedAt;)Lorg/scalatest/matchers/dsl/MatcherFactory5;
  #239 = Utf8               <A:Ljava/lang/Object;U::Lscala/PartialFunction<TA;*>;>(Lorg/scalatest/matchers/dsl/ResultOfDefinedAt<TA;>;)Lorg/scalatest/matchers/dsl/MatcherFactory5<TSC;TTC1;TTC2;TTC3;TTC4;TTC5;>;
  #240 = Utf8               resultOfDefinedAt
  #241 = Utf8               (Lorg/scalatest/matchers/dsl/ResultOfDefinedAt;)Lorg/scalatest/matchers/Matcher;
  #242 = NameAndType        #79:#241      // be:(Lorg/scalatest/matchers/dsl/ResultOfDefinedAt;)Lorg/scalatest/matchers/Matcher;
  #243 = Methodref          #51.#242      // org/scalatest/matchers/dsl/NotWord.be:(Lorg/scalatest/matchers/dsl/ResultOfDefinedAt;)Lorg/scalatest/matchers/Matcher;
  #244 = Utf8               Lorg/scalatest/matchers/dsl/ResultOfDefinedAt;
  #245 = Utf8               (Lorg/scalatest/matchers/dsl/SortedWord;)Lorg/scalatest/matchers/dsl/MatcherFactory6;
  #246 = Utf8               (Lorg/scalatest/matchers/dsl/SortedWord;)Lorg/scalatest/matchers/dsl/MatcherFactory6<TSC;TTC1;TTC2;TTC3;TTC4;TTC5;*>;
  #247 = Utf8               sortedWord
  #248 = Utf8               (Lorg/scalatest/matchers/dsl/SortedWord;)Lorg/scalatest/matchers/dsl/MatcherFactory1;
  #249 = NameAndType        #79:#248      // be:(Lorg/scalatest/matchers/dsl/SortedWord;)Lorg/scalatest/matchers/dsl/MatcherFactory1;
  #250 = Methodref          #51.#249      // org/scalatest/matchers/dsl/NotWord.be:(Lorg/scalatest/matchers/dsl/SortedWord;)Lorg/scalatest/matchers/dsl/MatcherFactory1;
  #251 = Utf8               Lorg/scalatest/matchers/dsl/SortedWord;
  #252 = Utf8               (Lorg/scalatest/matchers/dsl/ReadableWord;)Lorg/scalatest/matchers/dsl/MatcherFactory6;
  #253 = Utf8               (Lorg/scalatest/matchers/dsl/ReadableWord;)Lorg/scalatest/matchers/dsl/MatcherFactory6<TSC;TTC1;TTC2;TTC3;TTC4;TTC5;*>;
  #254 = Utf8               readableWord
  #255 = Utf8               (Lorg/scalatest/matchers/dsl/ReadableWord;)Lorg/scalatest/matchers/dsl/MatcherFactory1;
  #256 = NameAndType        #79:#255      // be:(Lorg/scalatest/matchers/dsl/ReadableWord;)Lorg/scalatest/matchers/dsl/MatcherFactory1;
  #257 = Methodref          #51.#256      // org/scalatest/matchers/dsl/NotWord.be:(Lorg/scalatest/matchers/dsl/ReadableWord;)Lorg/scalatest/matchers/dsl/MatcherFactory1;
  #258 = Utf8               Lorg/scalatest/matchers/dsl/ReadableWord;
  #259 = Utf8               (Lorg/scalatest/matchers/dsl/WritableWord;)Lorg/scalatest/matchers/dsl/MatcherFactory6;
  #260 = Utf8               (Lorg/scalatest/matchers/dsl/WritableWord;)Lorg/scalatest/matchers/dsl/MatcherFactory6<TSC;TTC1;TTC2;TTC3;TTC4;TTC5;*>;
  #261 = Utf8               writableWord
  #262 = Utf8               (Lorg/scalatest/matchers/dsl/WritableWord;)Lorg/scalatest/matchers/dsl/MatcherFactory1;
  #263 = NameAndType        #79:#262      // be:(Lorg/scalatest/matchers/dsl/WritableWord;)Lorg/scalatest/matchers/dsl/MatcherFactory1;
  #264 = Methodref          #51.#263      // org/scalatest/matchers/dsl/NotWord.be:(Lorg/scalatest/matchers/dsl/WritableWord;)Lorg/scalatest/matchers/dsl/MatcherFactory1;
  #265 = Utf8               Lorg/scalatest/matchers/dsl/WritableWord;
  #266 = Utf8               (Lorg/scalatest/matchers/dsl/EmptyWord;)Lorg/scalatest/matchers/dsl/MatcherFactory6;
  #267 = Utf8               (Lorg/scalatest/matchers/dsl/EmptyWord;)Lorg/scalatest/matchers/dsl/MatcherFactory6<TSC;TTC1;TTC2;TTC3;TTC4;TTC5;*>;
  #268 = Utf8               emptyWord
  #269 = Utf8               (Lorg/scalatest/matchers/dsl/EmptyWord;)Lorg/scalatest/matchers/dsl/MatcherFactory1;
  #270 = NameAndType        #79:#269      // be:(Lorg/scalatest/matchers/dsl/EmptyWord;)Lorg/scalatest/matchers/dsl/MatcherFactory1;
  #271 = Methodref          #51.#270      // org/scalatest/matchers/dsl/NotWord.be:(Lorg/scalatest/matchers/dsl/EmptyWord;)Lorg/scalatest/matchers/dsl/MatcherFactory1;
  #272 = Utf8               Lorg/scalatest/matchers/dsl/EmptyWord;
  #273 = Utf8               (Lorg/scalatest/matchers/dsl/DefinedWord;)Lorg/scalatest/matchers/dsl/MatcherFactory6;
  #274 = Utf8               (Lorg/scalatest/matchers/dsl/DefinedWord;)Lorg/scalatest/matchers/dsl/MatcherFactory6<TSC;TTC1;TTC2;TTC3;TTC4;TTC5;*>;
  #275 = Utf8               definedWord
  #276 = Utf8               (Lorg/scalatest/matchers/dsl/DefinedWord;)Lorg/scalatest/matchers/dsl/MatcherFactory1;
  #277 = NameAndType        #79:#276      // be:(Lorg/scalatest/matchers/dsl/DefinedWord;)Lorg/scalatest/matchers/dsl/MatcherFactory1;
  #278 = Methodref          #51.#277      // org/scalatest/matchers/dsl/NotWord.be:(Lorg/scalatest/matchers/dsl/DefinedWord;)Lorg/scalatest/matchers/dsl/MatcherFactory1;
  #279 = Utf8               Lorg/scalatest/matchers/dsl/DefinedWord;
  #280 = Utf8               fullyMatch
  #281 = Utf8               (Lorg/scalatest/matchers/dsl/ResultOfRegexWordApplication;)Lorg/scalatest/matchers/dsl/MatcherFactory5;
  #282 = Utf8               (Lorg/scalatest/matchers/dsl/ResultOfRegexWordApplication;)Lorg/scalatest/matchers/dsl/MatcherFactory5<Ljava/lang/String;TTC1;TTC2;TTC3;TTC4;TTC5;>;
  #283 = Utf8               resultOfRegexWordApplication
  #284 = Utf8               (Lorg/scalatest/matchers/dsl/ResultOfRegexWordApplication;)Lorg/scalatest/matchers/Matcher;
  #285 = NameAndType        #280:#284     // fullyMatch:(Lorg/scalatest/matchers/dsl/ResultOfRegexWordApplication;)Lorg/scalatest/matchers/Matcher;
  #286 = Methodref          #51.#285      // org/scalatest/matchers/dsl/NotWord.fullyMatch:(Lorg/scalatest/matchers/dsl/ResultOfRegexWordApplication;)Lorg/scalatest/matchers/Matcher;
  #287 = Utf8               Lorg/scalatest/matchers/dsl/ResultOfRegexWordApplication;
  #288 = Utf8               include
  #289 = NameAndType        #288:#284     // include:(Lorg/scalatest/matchers/dsl/ResultOfRegexWordApplication;)Lorg/scalatest/matchers/Matcher;
  #290 = Methodref          #51.#289      // org/scalatest/matchers/dsl/NotWord.include:(Lorg/scalatest/matchers/dsl/ResultOfRegexWordApplication;)Lorg/scalatest/matchers/Matcher;
  #291 = Utf8               (Ljava/lang/String;)Lorg/scalatest/matchers/dsl/MatcherFactory5;
  #292 = Utf8               (Ljava/lang/String;)Lorg/scalatest/matchers/dsl/MatcherFactory5<Ljava/lang/String;TTC1;TTC2;TTC3;TTC4;TTC5;>;
  #293 = Utf8               expectedSubstring
  #294 = Utf8               (Ljava/lang/String;)Lorg/scalatest/matchers/Matcher;
  #295 = NameAndType        #288:#294     // include:(Ljava/lang/String;)Lorg/scalatest/matchers/Matcher;
  #296 = Methodref          #51.#295      // org/scalatest/matchers/dsl/NotWord.include:(Ljava/lang/String;)Lorg/scalatest/matchers/Matcher;
  #297 = Utf8               Ljava/lang/String;
  #298 = Utf8               startWith
  #299 = NameAndType        #298:#284     // startWith:(Lorg/scalatest/matchers/dsl/ResultOfRegexWordApplication;)Lorg/scalatest/matchers/Matcher;
  #300 = Methodref          #51.#299      // org/scalatest/matchers/dsl/NotWord.startWith:(Lorg/scalatest/matchers/dsl/ResultOfRegexWordApplication;)Lorg/scalatest/matchers/Matcher;
  #301 = NameAndType        #298:#294     // startWith:(Ljava/lang/String;)Lorg/scalatest/matchers/Matcher;
  #302 = Methodref          #51.#301      // org/scalatest/matchers/dsl/NotWord.startWith:(Ljava/lang/String;)Lorg/scalatest/matchers/Matcher;
  #303 = Utf8               endWith
  #304 = NameAndType        #303:#284     // endWith:(Lorg/scalatest/matchers/dsl/ResultOfRegexWordApplication;)Lorg/scalatest/matchers/Matcher;
  #305 = Methodref          #51.#304      // org/scalatest/matchers/dsl/NotWord.endWith:(Lorg/scalatest/matchers/dsl/ResultOfRegexWordApplication;)Lorg/scalatest/matchers/Matcher;
  #306 = NameAndType        #303:#294     // endWith:(Ljava/lang/String;)Lorg/scalatest/matchers/Matcher;
  #307 = Methodref          #51.#306      // org/scalatest/matchers/dsl/NotWord.endWith:(Ljava/lang/String;)Lorg/scalatest/matchers/Matcher;
  #308 = Utf8               contain
  #309 = Utf8               <U:Ljava/lang/Object;>(TU;)Lorg/scalatest/matchers/dsl/MatcherFactory6<TSC;TTC1;TTC2;TTC3;TTC4;TTC5;Lorg/scalatest/enablers/Containing;>;
  #310 = Utf8               expectedElement
  #311 = NameAndType        #308:#47      // contain:(Ljava/lang/Object;)Lorg/scalatest/matchers/dsl/MatcherFactory1;
  #312 = Methodref          #51.#311      // org/scalatest/matchers/dsl/NotWord.contain:(Ljava/lang/Object;)Lorg/scalatest/matchers/dsl/MatcherFactory1;
  #313 = Utf8               (Lorg/scalatest/matchers/dsl/ResultOfKeyWordApplication;)Lorg/scalatest/matchers/dsl/MatcherFactory6;
  #314 = Utf8               (Lorg/scalatest/matchers/dsl/ResultOfKeyWordApplication;)Lorg/scalatest/matchers/dsl/MatcherFactory6<TSC;TTC1;TTC2;TTC3;TTC4;TTC5;Lorg/scalatest/enablers/KeyMapping;>;
  #315 = Utf8               resultOfKeyWordApplication
  #316 = Utf8               (Lorg/scalatest/matchers/dsl/ResultOfKeyWordApplication;)Lorg/scalatest/matchers/dsl/MatcherFactory1;
  #317 = NameAndType        #308:#316     // contain:(Lorg/scalatest/matchers/dsl/ResultOfKeyWordApplication;)Lorg/scalatest/matchers/dsl/MatcherFactory1;
  #318 = Methodref          #51.#317      // org/scalatest/matchers/dsl/NotWord.contain:(Lorg/scalatest/matchers/dsl/ResultOfKeyWordApplication;)Lorg/scalatest/matchers/dsl/MatcherFactory1;
  #319 = Utf8               Lorg/scalatest/matchers/dsl/ResultOfKeyWordApplication;
  #320 = Utf8               (Lorg/scalatest/matchers/dsl/ResultOfValueWordApplication;)Lorg/scalatest/matchers/dsl/MatcherFactory6;
  #321 = Utf8               (Lorg/scalatest/matchers/dsl/ResultOfValueWordApplication;)Lorg/scalatest/matchers/dsl/MatcherFactory6<TSC;TTC1;TTC2;TTC3;TTC4;TTC5;Lorg/scalatest/enablers/ValueMapping;>;
  #322 = Utf8               resultOfValueWordApplication
  #323 = Utf8               (Lorg/scalatest/matchers/dsl/ResultOfValueWordApplication;)Lorg/scalatest/matchers/dsl/MatcherFactory1;
  #324 = NameAndType        #308:#323     // contain:(Lorg/scalatest/matchers/dsl/ResultOfValueWordApplication;)Lorg/scalatest/matchers/dsl/MatcherFactory1;
  #325 = Methodref          #51.#324      // org/scalatest/matchers/dsl/NotWord.contain:(Lorg/scalatest/matchers/dsl/ResultOfValueWordApplication;)Lorg/scalatest/matchers/dsl/MatcherFactory1;
  #326 = Utf8               Lorg/scalatest/matchers/dsl/ResultOfValueWordApplication;
  #327 = Utf8               (Lorg/scalatest/matchers/dsl/ResultOfOneOfApplication;)Lorg/scalatest/matchers/dsl/MatcherFactory6;
  #328 = Utf8               (Lorg/scalatest/matchers/dsl/ResultOfOneOfApplication;)Lorg/scalatest/matchers/dsl/MatcherFactory6<TSC;TTC1;TTC2;TTC3;TTC4;TTC5;Lorg/scalatest/enablers/Containing;>;
  #329 = Utf8               right
  #330 = Utf8               org/scalactic/Prettifier$
  #331 = Class              #330          // org/scalactic/Prettifier$
  #332 = Utf8               Lorg/scalactic/Prettifier$;
  #333 = NameAndType        #39:#332      // MODULE$:Lorg/scalactic/Prettifier$;
  #334 = Fieldref           #331.#333     // org/scalactic/Prettifier$.MODULE$:Lorg/scalactic/Prettifier$;
  #335 = Utf8               default
  #336 = Utf8               ()Lorg/scalactic/Prettifier;
  #337 = NameAndType        #335:#336     // default:()Lorg/scalactic/Prettifier;
  #338 = Methodref          #331.#337     // org/scalactic/Prettifier$.default:()Lorg/scalactic/Prettifier;
  #339 = Utf8               (Lorg/scalatest/matchers/dsl/ResultOfOneOfApplication;Lorg/scalactic/Prettifier;)Lorg/scalatest/matchers/dsl/MatcherFactory1;
  #340 = NameAndType        #308:#339     // contain:(Lorg/scalatest/matchers/dsl/ResultOfOneOfApplication;Lorg/scalactic/Prettifier;)Lorg/scalatest/matchers/dsl/MatcherFactory1;
  #341 = Methodref          #51.#340      // org/scalatest/matchers/dsl/NotWord.contain:(Lorg/scalatest/matchers/dsl/ResultOfOneOfApplication;Lorg/scalactic/Prettifier;)Lorg/scalatest/matchers/dsl/MatcherFactory1;
  #342 = Utf8               Lorg/scalatest/matchers/dsl/ResultOfOneOfApplication;
  #343 = Utf8               (Lorg/scalatest/matchers/dsl/ResultOfOneElementOfApplication;)Lorg/scalatest/matchers/dsl/MatcherFactory6;
  #344 = Utf8               (Lorg/scalatest/matchers/dsl/ResultOfOneElementOfApplication;)Lorg/scalatest/matchers/dsl/MatcherFactory6<TSC;TTC1;TTC2;TTC3;TTC4;TTC5;Lorg/scalatest/enablers/Containing;>;
  #345 = Utf8               (Lorg/scalatest/matchers/dsl/ResultOfOneElementOfApplication;)Lorg/scalatest/matchers/dsl/MatcherFactory1;
  #346 = NameAndType        #308:#345     // contain:(Lorg/scalatest/matchers/dsl/ResultOfOneElementOfApplication;)Lorg/scalatest/matchers/dsl/MatcherFactory1;
  #347 = Methodref          #51.#346      // org/scalatest/matchers/dsl/NotWord.contain:(Lorg/scalatest/matchers/dsl/ResultOfOneElementOfApplication;)Lorg/scalatest/matchers/dsl/MatcherFactory1;
  #348 = Utf8               Lorg/scalatest/matchers/dsl/ResultOfOneElementOfApplication;
  #349 = Utf8               (Lorg/scalatest/matchers/dsl/ResultOfAtLeastOneOfApplication;)Lorg/scalatest/matchers/dsl/MatcherFactory6;
  #350 = Utf8               (Lorg/scalatest/matchers/dsl/ResultOfAtLeastOneOfApplication;)Lorg/scalatest/matchers/dsl/MatcherFactory6<TSC;TTC1;TTC2;TTC3;TTC4;TTC5;Lorg/scalatest/enablers/Aggregating;>;
  #351 = Utf8               (Lorg/scalatest/matchers/dsl/ResultOfAtLeastOneOfApplication;Lorg/scalactic/Prettifier;)Lorg/scalatest/matchers/dsl/MatcherFactory1;
  #352 = NameAndType        #308:#351     // contain:(Lorg/scalatest/matchers/dsl/ResultOfAtLeastOneOfApplication;Lorg/scalactic/Prettifier;)Lorg/scalatest/matchers/dsl/MatcherFactory1;
  #353 = Methodref          #51.#352      // org/scalatest/matchers/dsl/NotWord.contain:(Lorg/scalatest/matchers/dsl/ResultOfAtLeastOneOfApplication;Lorg/scalactic/Prettifier;)Lorg/scalatest/matchers/dsl/MatcherFactory1;
  #354 = Utf8               Lorg/scalatest/matchers/dsl/ResultOfAtLeastOneOfApplication;
  #355 = Utf8               (Lorg/scalatest/matchers/dsl/ResultOfAtLeastOneElementOfApplication;)Lorg/scalatest/matchers/dsl/MatcherFactory6;
  #356 = Utf8               (Lorg/scalatest/matchers/dsl/ResultOfAtLeastOneElementOfApplication;)Lorg/scalatest/matchers/dsl/MatcherFactory6<TSC;TTC1;TTC2;TTC3;TTC4;TTC5;Lorg/scalatest/enablers/Aggregating;>;
  #357 = Utf8               (Lorg/scalatest/matchers/dsl/ResultOfAtLeastOneElementOfApplication;)Lorg/scalatest/matchers/dsl/MatcherFactory1;
  #358 = NameAndType        #308:#357     // contain:(Lorg/scalatest/matchers/dsl/ResultOfAtLeastOneElementOfApplication;)Lorg/scalatest/matchers/dsl/MatcherFactory1;
  #359 = Methodref          #51.#358      // org/scalatest/matchers/dsl/NotWord.contain:(Lorg/scalatest/matchers/dsl/ResultOfAtLeastOneElementOfApplication;)Lorg/scalatest/matchers/dsl/MatcherFactory1;
  #360 = Utf8               Lorg/scalatest/matchers/dsl/ResultOfAtLeastOneElementOfApplication;
  #361 = Utf8               (Lorg/scalatest/matchers/dsl/ResultOfNoneOfApplication;)Lorg/scalatest/matchers/dsl/MatcherFactory6;
  #362 = Utf8               (Lorg/scalatest/matchers/dsl/ResultOfNoneOfApplication;)Lorg/scalatest/matchers/dsl/MatcherFactory6<TSC;TTC1;TTC2;TTC3;TTC4;TTC5;Lorg/scalatest/enablers/Containing;>;
  #363 = Utf8               (Lorg/scalatest/matchers/dsl/ResultOfNoneOfApplication;Lorg/scalactic/Prettifier;)Lorg/scalatest/matchers/dsl/MatcherFactory1;
  #364 = NameAndType        #308:#363     // contain:(Lorg/scalatest/matchers/dsl/ResultOfNoneOfApplication;Lorg/scalactic/Prettifier;)Lorg/scalatest/matchers/dsl/MatcherFactory1;
  #365 = Methodref          #51.#364      // org/scalatest/matchers/dsl/NotWord.contain:(Lorg/scalatest/matchers/dsl/ResultOfNoneOfApplication;Lorg/scalactic/Prettifier;)Lorg/scalatest/matchers/dsl/MatcherFactory1;
  #366 = Utf8               Lorg/scalatest/matchers/dsl/ResultOfNoneOfApplication;
  #367 = Utf8               (Lorg/scalatest/matchers/dsl/ResultOfNoElementsOfApplication;)Lorg/scalatest/matchers/dsl/MatcherFactory6;
  #368 = Utf8               (Lorg/scalatest/matchers/dsl/ResultOfNoElementsOfApplication;)Lorg/scalatest/matchers/dsl/MatcherFactory6<TSC;TTC1;TTC2;TTC3;TTC4;TTC5;Lorg/scalatest/enablers/Containing;>;
  #369 = Utf8               (Lorg/scalatest/matchers/dsl/ResultOfNoElementsOfApplication;)Lorg/scalatest/matchers/dsl/MatcherFactory1;
  #370 = NameAndType        #308:#369     // contain:(Lorg/scalatest/matchers/dsl/ResultOfNoElementsOfApplication;)Lorg/scalatest/matchers/dsl/MatcherFactory1;
  #371 = Methodref          #51.#370      // org/scalatest/matchers/dsl/NotWord.contain:(Lorg/scalatest/matchers/dsl/ResultOfNoElementsOfApplication;)Lorg/scalatest/matchers/dsl/MatcherFactory1;
  #372 = Utf8               Lorg/scalatest/matchers/dsl/ResultOfNoElementsOfApplication;
  #373 = Utf8               (Lorg/scalatest/matchers/dsl/ResultOfTheSameElementsAsApplication;)Lorg/scalatest/matchers/dsl/MatcherFactory6;
  #374 = Utf8               (Lorg/scalatest/matchers/dsl/ResultOfTheSameElementsAsApplication;)Lorg/scalatest/matchers/dsl/MatcherFactory6<TSC;TTC1;TTC2;TTC3;TTC4;TTC5;Lorg/scalatest/enablers/Aggregating;>;
  #375 = Utf8               (Lorg/scalatest/matchers/dsl/ResultOfTheSameElementsAsApplication;)Lorg/scalatest/matchers/dsl/MatcherFactory1;
  #376 = NameAndType        #308:#375     // contain:(Lorg/scalatest/matchers/dsl/ResultOfTheSameElementsAsApplication;)Lorg/scalatest/matchers/dsl/MatcherFactory1;
  #377 = Methodref          #51.#376      // org/scalatest/matchers/dsl/NotWord.contain:(Lorg/scalatest/matchers/dsl/ResultOfTheSameElementsAsApplication;)Lorg/scalatest/matchers/dsl/MatcherFactory1;
  #378 = Utf8               Lorg/scalatest/matchers/dsl/ResultOfTheSameElementsAsApplication;
  #379 = Utf8               (Lorg/scalatest/matchers/dsl/ResultOfTheSameElementsInOrderAsApplication;)Lorg/scalatest/matchers/dsl/MatcherFactory6;
  #380 = Utf8               (Lorg/scalatest/matchers/dsl/ResultOfTheSameElementsInOrderAsApplication;)Lorg/scalatest/matchers/dsl/MatcherFactory6<TSC;TTC1;TTC2;TTC3;TTC4;TTC5;Lorg/scalatest/enablers/Sequencing;>;
  #381 = Utf8               (Lorg/scalatest/matchers/dsl/ResultOfTheSameElementsInOrderAsApplication;)Lorg/scalatest/matchers/dsl/MatcherFactory1;
  #382 = NameAndType        #308:#381     // contain:(Lorg/scalatest/matchers/dsl/ResultOfTheSameElementsInOrderAsApplication;)Lorg/scalatest/matchers/dsl/MatcherFactory1;
  #383 = Methodref          #51.#382      // org/scalatest/matchers/dsl/NotWord.contain:(Lorg/scalatest/matchers/dsl/ResultOfTheSameElementsInOrderAsApplication;)Lorg/scalatest/matchers/dsl/MatcherFactory1;
  #384 = Utf8               Lorg/scalatest/matchers/dsl/ResultOfTheSameElementsInOrderAsApplication;
  #385 = Utf8               (Lorg/scalatest/matchers/dsl/ResultOfOnlyApplication;)Lorg/scalatest/matchers/dsl/MatcherFactory6;
  #386 = Utf8               (Lorg/scalatest/matchers/dsl/ResultOfOnlyApplication;)Lorg/scalatest/matchers/dsl/MatcherFactory6<TSC;TTC1;TTC2;TTC3;TTC4;TTC5;Lorg/scalatest/enablers/Aggregating;>;
  #387 = Utf8               (Lorg/scalatest/matchers/dsl/ResultOfOnlyApplication;Lorg/scalactic/Prettifier;)Lorg/scalatest/matchers/dsl/MatcherFactory1;
  #388 = NameAndType        #308:#387     // contain:(Lorg/scalatest/matchers/dsl/ResultOfOnlyApplication;Lorg/scalactic/Prettifier;)Lorg/scalatest/matchers/dsl/MatcherFactory1;
  #389 = Methodref          #51.#388      // org/scalatest/matchers/dsl/NotWord.contain:(Lorg/scalatest/matchers/dsl/ResultOfOnlyApplication;Lorg/scalactic/Prettifier;)Lorg/scalatest/matchers/dsl/MatcherFactory1;
  #390 = Utf8               Lorg/scalatest/matchers/dsl/ResultOfOnlyApplication;
  #391 = Utf8               (Lorg/scalatest/matchers/dsl/ResultOfInOrderOnlyApplication;)Lorg/scalatest/matchers/dsl/MatcherFactory6;
  #392 = Utf8               (Lorg/scalatest/matchers/dsl/ResultOfInOrderOnlyApplication;)Lorg/scalatest/matchers/dsl/MatcherFactory6<TSC;TTC1;TTC2;TTC3;TTC4;TTC5;Lorg/scalatest/enablers/Sequencing;>;
  #393 = Utf8               (Lorg/scalatest/matchers/dsl/ResultOfInOrderOnlyApplication;Lorg/scalactic/Prettifier;)Lorg/scalatest/matchers/dsl/MatcherFactory1;
  #394 = NameAndType        #308:#393     // contain:(Lorg/scalatest/matchers/dsl/ResultOfInOrderOnlyApplication;Lorg/scalactic/Prettifier;)Lorg/scalatest/matchers/dsl/MatcherFactory1;
  #395 = Methodref          #51.#394      // org/scalatest/matchers/dsl/NotWord.contain:(Lorg/scalatest/matchers/dsl/ResultOfInOrderOnlyApplication;Lorg/scalactic/Prettifier;)Lorg/scalatest/matchers/dsl/MatcherFactory1;
  #396 = Utf8               Lorg/scalatest/matchers/dsl/ResultOfInOrderOnlyApplication;
  #397 = Utf8               (Lorg/scalatest/matchers/dsl/ResultOfAllOfApplication;)Lorg/scalatest/matchers/dsl/MatcherFactory6;
  #398 = Utf8               (Lorg/scalatest/matchers/dsl/ResultOfAllOfApplication;)Lorg/scalatest/matchers/dsl/MatcherFactory6<TSC;TTC1;TTC2;TTC3;TTC4;TTC5;Lorg/scalatest/enablers/Aggregating;>;
  #399 = Utf8               (Lorg/scalatest/matchers/dsl/ResultOfAllOfApplication;Lorg/scalactic/Prettifier;)Lorg/scalatest/matchers/dsl/MatcherFactory1;
  #400 = NameAndType        #308:#399     // contain:(Lorg/scalatest/matchers/dsl/ResultOfAllOfApplication;Lorg/scalactic/Prettifier;)Lorg/scalatest/matchers/dsl/MatcherFactory1;
  #401 = Methodref          #51.#400      // org/scalatest/matchers/dsl/NotWord.contain:(Lorg/scalatest/matchers/dsl/ResultOfAllOfApplication;Lorg/scalactic/Prettifier;)Lorg/scalatest/matchers/dsl/MatcherFactory1;
  #402 = Utf8               Lorg/scalatest/matchers/dsl/ResultOfAllOfApplication;
  #403 = Utf8               (Lorg/scalatest/matchers/dsl/ResultOfAllElementsOfApplication;)Lorg/scalatest/matchers/dsl/MatcherFactory6;
  #404 = Utf8               (Lorg/scalatest/matchers/dsl/ResultOfAllElementsOfApplication;)Lorg/scalatest/matchers/dsl/MatcherFactory6<TSC;TTC1;TTC2;TTC3;TTC4;TTC5;Lorg/scalatest/enablers/Aggregating;>;
  #405 = Utf8               (Lorg/scalatest/matchers/dsl/ResultOfAllElementsOfApplication;)Lorg/scalatest/matchers/dsl/MatcherFactory1;
  #406 = NameAndType        #308:#405     // contain:(Lorg/scalatest/matchers/dsl/ResultOfAllElementsOfApplication;)Lorg/scalatest/matchers/dsl/MatcherFactory1;
  #407 = Methodref          #51.#406      // org/scalatest/matchers/dsl/NotWord.contain:(Lorg/scalatest/matchers/dsl/ResultOfAllElementsOfApplication;)Lorg/scalatest/matchers/dsl/MatcherFactory1;
  #408 = Utf8               Lorg/scalatest/matchers/dsl/ResultOfAllElementsOfApplication;
  #409 = Utf8               (Lorg/scalatest/matchers/dsl/ResultOfInOrderApplication;)Lorg/scalatest/matchers/dsl/MatcherFactory6;
  #410 = Utf8               (Lorg/scalatest/matchers/dsl/ResultOfInOrderApplication;)Lorg/scalatest/matchers/dsl/MatcherFactory6<TSC;TTC1;TTC2;TTC3;TTC4;TTC5;Lorg/scalatest/enablers/Sequencing;>;
  #411 = Utf8               (Lorg/scalatest/matchers/dsl/ResultOfInOrderApplication;Lorg/scalactic/Prettifier;)Lorg/scalatest/matchers/dsl/MatcherFactory1;
  #412 = NameAndType        #308:#411     // contain:(Lorg/scalatest/matchers/dsl/ResultOfInOrderApplication;Lorg/scalactic/Prettifier;)Lorg/scalatest/matchers/dsl/MatcherFactory1;
  #413 = Methodref          #51.#412      // org/scalatest/matchers/dsl/NotWord.contain:(Lorg/scalatest/matchers/dsl/ResultOfInOrderApplication;Lorg/scalactic/Prettifier;)Lorg/scalatest/matchers/dsl/MatcherFactory1;
  #414 = Utf8               Lorg/scalatest/matchers/dsl/ResultOfInOrderApplication;
  #415 = Utf8               (Lorg/scalatest/matchers/dsl/ResultOfInOrderElementsOfApplication;)Lorg/scalatest/matchers/dsl/MatcherFactory6;
  #416 = Utf8               (Lorg/scalatest/matchers/dsl/ResultOfInOrderElementsOfApplication;)Lorg/scalatest/matchers/dsl/MatcherFactory6<TSC;TTC1;TTC2;TTC3;TTC4;TTC5;Lorg/scalatest/enablers/Sequencing;>;
  #417 = Utf8               (Lorg/scalatest/matchers/dsl/ResultOfInOrderElementsOfApplication;)Lorg/scalatest/matchers/dsl/MatcherFactory1;
  #418 = NameAndType        #308:#417     // contain:(Lorg/scalatest/matchers/dsl/ResultOfInOrderElementsOfApplication;)Lorg/scalatest/matchers/dsl/MatcherFactory1;
  #419 = Methodref          #51.#418      // org/scalatest/matchers/dsl/NotWord.contain:(Lorg/scalatest/matchers/dsl/ResultOfInOrderElementsOfApplication;)Lorg/scalatest/matchers/dsl/MatcherFactory1;
  #420 = Utf8               Lorg/scalatest/matchers/dsl/ResultOfInOrderElementsOfApplication;
  #421 = Utf8               (Lorg/scalatest/matchers/dsl/ResultOfAtMostOneOfApplication;)Lorg/scalatest/matchers/dsl/MatcherFactory6;
  #422 = Utf8               (Lorg/scalatest/matchers/dsl/ResultOfAtMostOneOfApplication;)Lorg/scalatest/matchers/dsl/MatcherFactory6<TSC;TTC1;TTC2;TTC3;TTC4;TTC5;Lorg/scalatest/enablers/Aggregating;>;
  #423 = Utf8               (Lorg/scalatest/matchers/dsl/ResultOfAtMostOneOfApplication;Lorg/scalactic/Prettifier;)Lorg/scalatest/matchers/dsl/MatcherFactory1;
  #424 = NameAndType        #308:#423     // contain:(Lorg/scalatest/matchers/dsl/ResultOfAtMostOneOfApplication;Lorg/scalactic/Prettifier;)Lorg/scalatest/matchers/dsl/MatcherFactory1;
  #425 = Methodref          #51.#424      // org/scalatest/matchers/dsl/NotWord.contain:(Lorg/scalatest/matchers/dsl/ResultOfAtMostOneOfApplication;Lorg/scalactic/Prettifier;)Lorg/scalatest/matchers/dsl/MatcherFactory1;
  #426 = Utf8               Lorg/scalatest/matchers/dsl/ResultOfAtMostOneOfApplication;
  #427 = Utf8               (Lorg/scalatest/matchers/dsl/ResultOfAtMostOneElementOfApplication;)Lorg/scalatest/matchers/dsl/MatcherFactory6;
  #428 = Utf8               (Lorg/scalatest/matchers/dsl/ResultOfAtMostOneElementOfApplication;)Lorg/scalatest/matchers/dsl/MatcherFactory6<TSC;TTC1;TTC2;TTC3;TTC4;TTC5;Lorg/scalatest/enablers/Aggregating;>;
  #429 = Utf8               (Lorg/scalatest/matchers/dsl/ResultOfAtMostOneElementOfApplication;)Lorg/scalatest/matchers/dsl/MatcherFactory1;
  #430 = NameAndType        #308:#429     // contain:(Lorg/scalatest/matchers/dsl/ResultOfAtMostOneElementOfApplication;)Lorg/scalatest/matchers/dsl/MatcherFactory1;
  #431 = Methodref          #51.#430      // org/scalatest/matchers/dsl/NotWord.contain:(Lorg/scalatest/matchers/dsl/ResultOfAtMostOneElementOfApplication;)Lorg/scalatest/matchers/dsl/MatcherFactory1;
  #432 = Utf8               Lorg/scalatest/matchers/dsl/ResultOfAtMostOneElementOfApplication;
  #433 = Utf8               (Lorg/scalatest/matchers/dsl/MatcherFactory5;Lorg/scalactic/Prettifier;Lorg/scalactic/source/Position;)V
  #434 = Utf8               prettifier
  #435 = Utf8               ()V
  #436 = NameAndType        #74:#435      // "<init>":()V
  #437 = Methodref          #4.#436       // java/lang/Object."<init>":()V
  #438 = Utf8               Lorg/scalactic/Prettifier;
  #439 = Utf8               Signature
  #440 = Utf8               Code
  #441 = Utf8               LineNumberTable
  #442 = Utf8               LocalVariableTable
  #443 = Utf8               MethodParameters
  #444 = Utf8               StackMapTable
  #445 = Utf8               InnerClasses
  #446 = Utf8               SourceFile
  #447 = Utf8               ScalaInlineInfo
  #448 = Utf8               (Lorg/scalatest/matchers/dsl/ResultOfATypeInvocation;)Lorg/scalatest/matchers/dsl/MatcherFactory5;
  #449 = Utf8               (Lorg/scalatest/matchers/dsl/ResultOfAnTypeInvocation;)Lorg/scalatest/matchers/dsl/MatcherFactory5;
  #450 = Utf8               matchPattern
  #451 = Utf8               (Lscala/PartialFunction;)Lorg/scalatest/matchers/Matcher;
  #452 = Utf8               Scala
{
  private final org.scalactic.source.Position pos;
    descriptor: Lorg/scalactic/source/Position;
    flags: (0x0012) ACC_PRIVATE, ACC_FINAL

  private final org.scalatest.matchers.dsl.MatcherFactory5<SC, TC1, TC2, TC3, TC4, TC5> owner;
    descriptor: Lorg/scalatest/matchers/dsl/MatcherFactory5;
    flags: (0x0012) ACC_PRIVATE, ACC_FINAL
    Signature: #23                          // Lorg/scalatest/matchers/dsl/MatcherFactory5<TSC;TTC1;TTC2;TTC3;TTC4;TTC5;>;

  private final org.scalatest.matchers.dsl.MatcherFactory5 $outer;
    descriptor: Lorg/scalatest/matchers/dsl/MatcherFactory5;
    flags: (0x1012) ACC_PRIVATE, ACC_FINAL, ACC_SYNTHETIC

  public org.scalatest.matchers.dsl.MatcherFactory5<SC, TC1, TC2, TC3, TC4, TC5> owner();
    descriptor: ()Lorg/scalatest/matchers/dsl/MatcherFactory5;
    flags: (0x0001) ACC_PUBLIC
    Code:
      stack=1, locals=1, args_size=1
         0: aload_0
         1: getfield      #28                 // Field owner:Lorg/scalatest/matchers/dsl/MatcherFactory5;
         4: areturn
      LineNumberTable:
        line 2182: 0
      LocalVariableTable:
        Start  Length  Slot  Name   Signature
            0       5     0  this   Lorg/scalatest/matchers/dsl/MatcherFactory5$OrNotWord;
    Signature: #26                          // ()Lorg/scalatest/matchers/dsl/MatcherFactory5<TSC;TTC1;TTC2;TTC3;TTC4;TTC5;>;

  public org.scalatest.matchers.dsl.MatcherFactory6<SC, TC1, TC2, TC3, TC4, TC5, org.scalactic.Equality> equal(java.lang.Object);
    descriptor: (Ljava/lang/Object;)Lorg/scalatest/matchers/dsl/MatcherFactory6;
    flags: (0x0001) ACC_PUBLIC
    Code:
      stack=4, locals=2, args_size=2
         0: aload_0
         1: getfield      #36                 // Field $outer:Lorg/scalatest/matchers/dsl/MatcherFactory5;
         4: getstatic     #42                 // Field org/scalatest/matchers/dsl/MatcherWords$.MODULE$:Lorg/scalatest/matchers/dsl/MatcherWords$;
         7: invokevirtual #46                 // Method org/scalatest/matchers/dsl/MatcherWords$.not:()Lorg/scalatest/matchers/dsl/NotWord;
        10: getstatic     #42                 // Field org/scalatest/matchers/dsl/MatcherWords$.MODULE$:Lorg/scalatest/matchers/dsl/MatcherWords$;
        13: aload_1
        14: invokevirtual #49                 // Method org/scalatest/matchers/dsl/MatcherWords$.equal:(Ljava/lang/Object;)Lorg/scalatest/matchers/dsl/MatcherFactory1;
        17: invokevirtual #55                 // Method org/scalatest/matchers/dsl/NotWord.apply:(Lorg/scalatest/matchers/dsl/MatcherFactory1;)Lorg/scalatest/matchers/dsl/MatcherFactory1;
        20: invokevirtual #59                 // Method org/scalatest/matchers/dsl/MatcherFactory5.or:(Lorg/scalatest/matchers/dsl/MatcherFactory1;)Lorg/scalatest/matchers/dsl/MatcherFactory6;
        23: areturn
      LineNumberTable:
        line 2193: 0
      LocalVariableTable:
        Start  Length  Slot  Name   Signature
            0      24     0  this   Lorg/scalatest/matchers/dsl/MatcherFactory5$OrNotWord;
            0      24     1   any   Ljava/lang/Object;
    Signature: #33                          // (Ljava/lang/Object;)Lorg/scalatest/matchers/dsl/MatcherFactory6<TSC;TTC1;TTC2;TTC3;TTC4;TTC5;Lorg/scalactic/Equality;>;
    MethodParameters:
      Name                           Flags
      any                            final

  public <U extends java.lang.Object> org.scalatest.matchers.dsl.MatcherFactory5<SC, TC1, TC2, TC3, TC4, TC5> equal(org.scalactic.TripleEqualsSupport$Spread<U>);
    descriptor: (Lorg/scalactic/TripleEqualsSupport$Spread;)Lorg/scalatest/matchers/dsl/MatcherFactory5;
    flags: (0x0001) ACC_PUBLIC
    Code:
      stack=3, locals=2, args_size=2
         0: aload_0
         1: getfield      #36                 // Field $outer:Lorg/scalatest/matchers/dsl/MatcherFactory5;
         4: getstatic     #42                 // Field org/scalatest/matchers/dsl/MatcherWords$.MODULE$:Lorg/scalatest/matchers/dsl/MatcherWords$;
         7: invokevirtual #46                 // Method org/scalatest/matchers/dsl/MatcherWords$.not:()Lorg/scalatest/matchers/dsl/NotWord;
        10: aload_1
        11: invokevirtual #66                 // Method org/scalatest/matchers/dsl/NotWord.equal:(Lorg/scalactic/TripleEqualsSupport$Spread;)Lorg/scalatest/matchers/Matcher;
        14: invokevirtual #69                 // Method org/scalatest/matchers/dsl/MatcherFactory5.or:(Lorg/scalatest/matchers/Matcher;)Lorg/scalatest/matchers/dsl/MatcherFactory5;
        17: areturn
      LineNumberTable:
        line 2203: 0
      LocalVariableTable:
        Start  Length  Slot  Name   Signature
            0      18     0  this   Lorg/scalatest/matchers/dsl/MatcherFactory5$OrNotWord;
            0      18     1 spread   Lorg/scalactic/TripleEqualsSupport$Spread;
    Signature: #62                          // <U:Ljava/lang/Object;>(Lorg/scalactic/TripleEqualsSupport$Spread<TU;>;)Lorg/scalatest/matchers/dsl/MatcherFactory5<TSC;TTC1;TTC2;TTC3;TTC4;TTC5;>;
    MethodParameters:
      Name                           Flags
      spread                         final

  public org.scalatest.matchers.dsl.MatcherFactory5<SC, TC1, TC2, TC3, TC4, TC5> equal(scala.runtime.Null$);
    descriptor: (Lscala/runtime/Null$;)Lorg/scalatest/matchers/dsl/MatcherFactory5;
    flags: (0x0001) ACC_PUBLIC
    Code:
      stack=4, locals=2, args_size=2
         0: aload_0
         1: getfield      #36                 // Field $outer:Lorg/scalatest/matchers/dsl/MatcherFactory5;
         4: new           #18                 // class org/scalatest/matchers/dsl/MatcherFactory5$OrNotWord$$anon$26
         7: dup
         8: aconst_null
         9: invokespecial #77                 // Method org/scalatest/matchers/dsl/MatcherFactory5$OrNotWord$$anon$26."<init>":(Lorg/scalatest/matchers/dsl/MatcherFactory5$OrNotWord;)V
        12: invokevirtual #69                 // Method org/scalatest/matchers/dsl/MatcherFactory5.or:(Lorg/scalatest/matchers/Matcher;)Lorg/scalatest/matchers/dsl/MatcherFactory5;
        15: areturn
      LineNumberTable:
        line 2214: 0
        line 2215: 4
      LocalVariableTable:
        Start  Length  Slot  Name   Signature
            0      16     0  this   Lorg/scalatest/matchers/dsl/MatcherFactory5$OrNotWord;
            0      16     1     o   Lscala/runtime/Null$;
    Signature: #72                          // (Lscala/runtime/Null$;)Lorg/scalatest/matchers/dsl/MatcherFactory5<TSC;TTC1;TTC2;TTC3;TTC4;TTC5;>;
    MethodParameters:
      Name                           Flags
      o                              final

  public org.scalatest.matchers.dsl.MatcherFactory5<SC, TC1, TC2, TC3, TC4, TC5> be(java.lang.Object);
    descriptor: (Ljava/lang/Object;)Lorg/scalatest/matchers/dsl/MatcherFactory5;
    flags: (0x0001) ACC_PUBLIC
    Code:
      stack=4, locals=2, args_size=2
         0: aload_0
         1: getfield      #36                 // Field $outer:Lorg/scalatest/matchers/dsl/MatcherFactory5;
         4: getstatic     #42                 // Field org/scalatest/matchers/dsl/MatcherWords$.MODULE$:Lorg/scalatest/matchers/dsl/MatcherWords$;
         7: invokevirtual #46                 // Method org/scalatest/matchers/dsl/MatcherWords$.not:()Lorg/scalatest/matchers/dsl/NotWord;
        10: getstatic     #42                 // Field org/scalatest/matchers/dsl/MatcherWords$.MODULE$:Lorg/scalatest/matchers/dsl/MatcherWords$;
        13: invokevirtual #84                 // Method org/scalatest/matchers/dsl/MatcherWords$.be:()Lorg/scalatest/matchers/dsl/BeWord;
        16: aload_1
        17: invokevirtual #89                 // Method org/scalatest/matchers/dsl/BeWord.apply:(Ljava/lang/Object;)Lorg/scalatest/matchers/Matcher;
        20: invokevirtual #92                 // Method org/scalatest/matchers/dsl/NotWord.apply:(Lorg/scalatest/matchers/Matcher;)Lorg/scalatest/matchers/Matcher;
        23: invokevirtual #69                 // Method org/scalatest/matchers/dsl/MatcherFactory5.or:(Lorg/scalatest/matchers/Matcher;)Lorg/scalatest/matchers/dsl/MatcherFactory5;
        26: areturn
      LineNumberTable:
        line 2241: 0
      LocalVariableTable:
        Start  Length  Slot  Name   Signature
            0      27     0  this   Lorg/scalatest/matchers/dsl/MatcherFactory5$OrNotWord;
            0      27     1   any   Ljava/lang/Object;
    Signature: #81                          // (Ljava/lang/Object;)Lorg/scalatest/matchers/dsl/MatcherFactory5<TSC;TTC1;TTC2;TTC3;TTC4;TTC5;>;
    MethodParameters:
      Name                           Flags
      any                            final

  public org.scalatest.matchers.dsl.MatcherFactory6<SC, TC1, TC2, TC3, TC4, TC5, org.scalatest.enablers.Length> have(org.scalatest.matchers.dsl.ResultOfLengthWordApplication);
    descriptor: (Lorg/scalatest/matchers/dsl/ResultOfLengthWordApplication;)Lorg/scalatest/matchers/dsl/MatcherFactory6;
    flags: (0x0001) ACC_PUBLIC
    Code:
      stack=5, locals=2, args_size=2
         0: aload_0
         1: getfield      #36                 // Field $outer:Lorg/scalatest/matchers/dsl/MatcherFactory5;
         4: getstatic     #42                 // Field org/scalatest/matchers/dsl/MatcherWords$.MODULE$:Lorg/scalatest/matchers/dsl/MatcherWords$;
         7: invokevirtual #46                 // Method org/scalatest/matchers/dsl/MatcherWords$.not:()Lorg/scalatest/matchers/dsl/NotWord;
        10: getstatic     #42                 // Field org/scalatest/matchers/dsl/MatcherWords$.MODULE$:Lorg/scalatest/matchers/dsl/MatcherWords$;
        13: invokevirtual #99                 // Method org/scalatest/matchers/dsl/MatcherWords$.have:()Lorg/scalatest/matchers/dsl/HaveWord;
        16: aload_1
        17: invokevirtual #105                // Method org/scalatest/matchers/dsl/ResultOfLengthWordApplication.expectedLength:()J
        20: invokevirtual #111                // Method org/scalatest/matchers/dsl/HaveWord.length:(J)Lorg/scalatest/matchers/dsl/MatcherFactory1;
        23: invokevirtual #55                 // Method org/scalatest/matchers/dsl/NotWord.apply:(Lorg/scalatest/matchers/dsl/MatcherFactory1;)Lorg/scalatest/matchers/dsl/MatcherFactory1;
        26: invokevirtual #59                 // Method org/scalatest/matchers/dsl/MatcherFactory5.or:(Lorg/scalatest/matchers/dsl/MatcherFactory1;)Lorg/scalatest/matchers/dsl/MatcherFactory6;
        29: areturn
      LineNumberTable:
        line 2252: 0
      LocalVariableTable:
        Start  Length  Slot  Name   Signature
            0      30     0  this   Lorg/scalatest/matchers/dsl/MatcherFactory5$OrNotWord;
            0      30     1 resultOfLengthWordApplication   Lorg/scalatest/matchers/dsl/ResultOfLengthWordApplication;
    Signature: #95                          // (Lorg/scalatest/matchers/dsl/ResultOfLengthWordApplication;)Lorg/scalatest/matchers/dsl/MatcherFactory6<TSC;TTC1;TTC2;TTC3;TTC4;TTC5;Lorg/scalatest/enablers/Length;>;
    MethodParameters:
      Name                           Flags
      resultOfLengthWordApplication  final

  public org.scalatest.matchers.dsl.MatcherFactory6<SC, TC1, TC2, TC3, TC4, TC5, org.scalatest.enablers.Size> have(org.scalatest.matchers.dsl.ResultOfSizeWordApplication);
    descriptor: (Lorg/scalatest/matchers/dsl/ResultOfSizeWordApplication;)Lorg/scalatest/matchers/dsl/MatcherFactory6;
    flags: (0x0001) ACC_PUBLIC
    Code:
      stack=5, locals=2, args_size=2
         0: aload_0
         1: getfield      #36                 // Field $outer:Lorg/scalatest/matchers/dsl/MatcherFactory5;
         4: getstatic     #42                 // Field org/scalatest/matchers/dsl/MatcherWords$.MODULE$:Lorg/scalatest/matchers/dsl/MatcherWords$;
         7: invokevirtual #46                 // Method org/scalatest/matchers/dsl/MatcherWords$.not:()Lorg/scalatest/matchers/dsl/NotWord;
        10: getstatic     #42                 // Field org/scalatest/matchers/dsl/MatcherWords$.MODULE$:Lorg/scalatest/matchers/dsl/MatcherWords$;
        13: invokevirtual #99                 // Method org/scalatest/matchers/dsl/MatcherWords$.have:()Lorg/scalatest/matchers/dsl/HaveWord;
        16: aload_1
        17: invokevirtual #120                // Method org/scalatest/matchers/dsl/ResultOfSizeWordApplication.expectedSize:()J
        20: invokevirtual #123                // Method org/scalatest/matchers/dsl/HaveWord.size:(J)Lorg/scalatest/matchers/dsl/MatcherFactory1;
        23: invokevirtual #55                 // Method org/scalatest/matchers/dsl/NotWord.apply:(Lorg/scalatest/matchers/dsl/MatcherFactory1;)Lorg/scalatest/matchers/dsl/MatcherFactory1;
        26: invokevirtual #59                 // Method org/scalatest/matchers/dsl/MatcherFactory5.or:(Lorg/scalatest/matchers/dsl/MatcherFactory1;)Lorg/scalatest/matchers/dsl/MatcherFactory6;
        29: areturn
      LineNumberTable:
        line 2263: 0
      LocalVariableTable:
        Start  Length  Slot  Name   Signature
            0      30     0  this   Lorg/scalatest/matchers/dsl/MatcherFactory5$OrNotWord;
            0      30     1 resultOfSizeWordApplication   Lorg/scalatest/matchers/dsl/ResultOfSizeWordApplication;
    Signature: #114                         // (Lorg/scalatest/matchers/dsl/ResultOfSizeWordApplication;)Lorg/scalatest/matchers/dsl/MatcherFactory6<TSC;TTC1;TTC2;TTC3;TTC4;TTC5;Lorg/scalatest/enablers/Size;>;
    MethodParameters:
      Name                           Flags
      resultOfSizeWordApplication    final

  public org.scalatest.matchers.dsl.MatcherFactory6<SC, TC1, TC2, TC3, TC4, TC5, org.scalatest.enablers.Messaging> have(org.scalatest.matchers.dsl.ResultOfMessageWordApplication);
    descriptor: (Lorg/scalatest/matchers/dsl/ResultOfMessageWordApplication;)Lorg/scalatest/matchers/dsl/MatcherFactory6;
    flags: (0x0001) ACC_PUBLIC
    Code:
      stack=4, locals=2, args_size=2
         0: aload_0
         1: getfield      #36                 // Field $outer:Lorg/scalatest/matchers/dsl/MatcherFactory5;
         4: getstatic     #42                 // Field org/scalatest/matchers/dsl/MatcherWords$.MODULE$:Lorg/scalatest/matchers/dsl/MatcherWords$;
         7: invokevirtual #46                 // Method org/scalatest/matchers/dsl/MatcherWords$.not:()Lorg/scalatest/matchers/dsl/NotWord;
        10: getstatic     #42                 // Field org/scalatest/matchers/dsl/MatcherWords$.MODULE$:Lorg/scalatest/matchers/dsl/MatcherWords$;
        13: invokevirtual #99                 // Method org/scalatest/matchers/dsl/MatcherWords$.have:()Lorg/scalatest/matchers/dsl/HaveWord;
        16: aload_1
        17: invokevirtual #133                // Method org/scalatest/matchers/dsl/ResultOfMessageWordApplication.expectedMessage:()Ljava/lang/String;
        20: invokevirtual #137                // Method org/scalatest/matchers/dsl/HaveWord.message:(Ljava/lang/String;)Lorg/scalatest/matchers/dsl/MatcherFactory1;
        23: invokevirtual #55                 // Method org/scalatest/matchers/dsl/NotWord.apply:(Lorg/scalatest/matchers/dsl/MatcherFactory1;)Lorg/scalatest/matchers/dsl/MatcherFactory1;
        26: invokevirtual #59                 // Method org/scalatest/matchers/dsl/MatcherFactory5.or:(Lorg/scalatest/matchers/dsl/MatcherFactory1;)Lorg/scalatest/matchers/dsl/MatcherFactory6;
        29: areturn
      LineNumberTable:
        line 2274: 0
      LocalVariableTable:
        Start  Length  Slot  Name   Signature
            0      30     0  this   Lorg/scalatest/matchers/dsl/MatcherFactory5$OrNotWord;
            0      30     1 resultOfMessageWordApplication   Lorg/scalatest/matchers/dsl/ResultOfMessageWordApplication;
    Signature: #126                         // (Lorg/scalatest/matchers/dsl/ResultOfMessageWordApplication;)Lorg/scalatest/matchers/dsl/MatcherFactory6<TSC;TTC1;TTC2;TTC3;TTC4;TTC5;Lorg/scalatest/enablers/Messaging;>;
    MethodParameters:
      Name                           Flags
      resultOfMessageWordApplication final

  public <U extends java.lang.Object> org.scalatest.matchers.dsl.MatcherFactory5<SC, TC1, TC2, TC3, TC4, TC5> have(org.scalatest.matchers.HavePropertyMatcher<U, ?>, scala.collection.immutable.Seq<org.scalatest.matchers.HavePropertyMatcher<U, ?>>);
    descriptor: (Lorg/scalatest/matchers/HavePropertyMatcher;Lscala/collection/immutable/Seq;)Lorg/scalatest/matchers/dsl/MatcherFactory5;
    flags: (0x0001) ACC_PUBLIC
    Code:
      stack=5, locals=3, args_size=3
         0: aload_0
         1: getfield      #36                 // Field $outer:Lorg/scalatest/matchers/dsl/MatcherFactory5;
         4: getstatic     #42                 // Field org/scalatest/matchers/dsl/MatcherWords$.MODULE$:Lorg/scalatest/matchers/dsl/MatcherWords$;
         7: invokevirtual #46                 // Method org/scalatest/matchers/dsl/MatcherWords$.not:()Lorg/scalatest/matchers/dsl/NotWord;
        10: getstatic     #42                 // Field org/scalatest/matchers/dsl/MatcherWords$.MODULE$:Lorg/scalatest/matchers/dsl/MatcherWords$;
        13: invokevirtual #99                 // Method org/scalatest/matchers/dsl/MatcherWords$.have:()Lorg/scalatest/matchers/dsl/HaveWord;
        16: aload_1
        17: aload_2
        18: invokevirtual #145                // Method org/scalatest/matchers/dsl/HaveWord.apply:(Lorg/scalatest/matchers/HavePropertyMatcher;Lscala/collection/immutable/Seq;)Lorg/scalatest/matchers/Matcher;
        21: invokevirtual #92                 // Method org/scalatest/matchers/dsl/NotWord.apply:(Lorg/scalatest/matchers/Matcher;)Lorg/scalatest/matchers/Matcher;
        24: invokevirtual #69                 // Method org/scalatest/matchers/dsl/MatcherFactory5.or:(Lorg/scalatest/matchers/Matcher;)Lorg/scalatest/matchers/dsl/MatcherFactory5;
        27: areturn
      LineNumberTable:
        line 2285: 0
      LocalVariableTable:
        Start  Length  Slot  Name   Signature
            0      28     0  this   Lorg/scalatest/matchers/dsl/MatcherFactory5$OrNotWord;
            0      28     1 firstPropertyMatcher   Lorg/scalatest/matchers/HavePropertyMatcher;
            0      28     2 propertyMatchers   Lscala/collection/immutable/Seq;
    Signature: #140                         // <U:Ljava/lang/Object;>(Lorg/scalatest/matchers/HavePropertyMatcher<TU;*>;Lscala/collection/immutable/Seq<Lorg/scalatest/matchers/HavePropertyMatcher<TU;*>;>;)Lorg/scalatest/matchers/dsl/MatcherFactory5<TSC;TTC1;TTC2;TTC3;TTC4;TTC5;>;
    MethodParameters:
      Name                           Flags
      firstPropertyMatcher           final
      propertyMatchers               final

  public org.scalatest.matchers.dsl.MatcherFactory5<java.lang.Object, TC1, TC2, TC3, TC4, TC5> be(scala.runtime.Null$);
    descriptor: (Lscala/runtime/Null$;)Lorg/scalatest/matchers/dsl/MatcherFactory5;
    flags: (0x0001) ACC_PUBLIC
    Code:
      stack=3, locals=2, args_size=2
         0: aload_0
         1: getfield      #36                 // Field $outer:Lorg/scalatest/matchers/dsl/MatcherFactory5;
         4: getstatic     #42                 // Field org/scalatest/matchers/dsl/MatcherWords$.MODULE$:Lorg/scalatest/matchers/dsl/MatcherWords$;
         7: invokevirtual #46                 // Method org/scalatest/matchers/dsl/MatcherWords$.not:()Lorg/scalatest/matchers/dsl/NotWord;
        10: aload_1
        11: invokevirtual #151                // Method org/scalatest/matchers/dsl/NotWord.be:(Lscala/runtime/Null$;)Lorg/scalatest/matchers/Matcher;
        14: invokevirtual #69                 // Method org/scalatest/matchers/dsl/MatcherFactory5.or:(Lorg/scalatest/matchers/Matcher;)Lorg/scalatest/matchers/dsl/MatcherFactory5;
        17: areturn
      LineNumberTable:
        line 2295: 0
      LocalVariableTable:
        Start  Length  Slot  Name   Signature
            0      18     0  this   Lorg/scalatest/matchers/dsl/MatcherFactory5$OrNotWord;
            0      18     1     o   Lscala/runtime/Null$;
    Signature: #148                         // (Lscala/runtime/Null$;)Lorg/scalatest/matchers/dsl/MatcherFactory5<Ljava/lang/Object;TTC1;TTC2;TTC3;TTC4;TTC5;>;
    MethodParameters:
      Name                           Flags
      o                              final

  public <U extends java.lang.Object> org.scalatest.matchers.dsl.MatcherFactory5<SC, TC1, TC2, TC3, TC4, TC5> be(org.scalatest.matchers.dsl.ResultOfLessThanComparison<U>);
    descriptor: (Lorg/scalatest/matchers/dsl/ResultOfLessThanComparison;)Lorg/scalatest/matchers/dsl/MatcherFactory5;
    flags: (0x0001) ACC_PUBLIC
    Code:
      stack=3, locals=2, args_size=2
         0: aload_0
         1: getfield      #36                 // Field $outer:Lorg/scalatest/matchers/dsl/MatcherFactory5;
         4: getstatic     #42                 // Field org/scalatest/matchers/dsl/MatcherWords$.MODULE$:Lorg/scalatest/matchers/dsl/MatcherWords$;
         7: invokevirtual #46                 // Method org/scalatest/matchers/dsl/MatcherWords$.not:()Lorg/scalatest/matchers/dsl/NotWord;
        10: aload_1
        11: invokevirtual #157                // Method org/scalatest/matchers/dsl/NotWord.be:(Lorg/scalatest/matchers/dsl/ResultOfLessThanComparison;)Lorg/scalatest/matchers/Matcher;
        14: invokevirtual #69                 // Method org/scalatest/matchers/dsl/MatcherFactory5.or:(Lorg/scalatest/matchers/Matcher;)Lorg/scalatest/matchers/dsl/MatcherFactory5;
        17: areturn
      LineNumberTable:
        line 2306: 0
      LocalVariableTable:
        Start  Length  Slot  Name   Signature
            0      18     0  this   Lorg/scalatest/matchers/dsl/MatcherFactory5$OrNotWord;
            0      18     1 resultOfLessThanComparison   Lorg/scalatest/matchers/dsl/ResultOfLessThanComparison;
    Signature: #153                         // <U:Ljava/lang/Object;>(Lorg/scalatest/matchers/dsl/ResultOfLessThanComparison<TU;>;)Lorg/scalatest/matchers/dsl/MatcherFactory5<TSC;TTC1;TTC2;TTC3;TTC4;TTC5;>;
    MethodParameters:
      Name                           Flags
      resultOfLessThanComparison     final

  public <U extends java.lang.Object> org.scalatest.matchers.dsl.MatcherFactory5<SC, TC1, TC2, TC3, TC4, TC5> be(org.scalatest.matchers.dsl.ResultOfGreaterThanComparison<U>);
    descriptor: (Lorg/scalatest/matchers/dsl/ResultOfGreaterThanComparison;)Lorg/scalatest/matchers/dsl/MatcherFactory5;
    flags: (0x0001) ACC_PUBLIC
    Code:
      stack=3, locals=2, args_size=2
         0: aload_0
         1: getfield      #36                 // Field $outer:Lorg/scalatest/matchers/dsl/MatcherFactory5;
         4: getstatic     #42                 // Field org/scalatest/matchers/dsl/MatcherWords$.MODULE$:Lorg/scalatest/matchers/dsl/MatcherWords$;
         7: invokevirtual #46                 // Method org/scalatest/matchers/dsl/MatcherWords$.not:()Lorg/scalatest/matchers/dsl/NotWord;
        10: aload_1
        11: invokevirtual #164                // Method org/scalatest/matchers/dsl/NotWord.be:(Lorg/scalatest/matchers/dsl/ResultOfGreaterThanComparison;)Lorg/scalatest/matchers/Matcher;
        14: invokevirtual #69                 // Method org/scalatest/matchers/dsl/MatcherFactory5.or:(Lorg/scalatest/matchers/Matcher;)Lorg/scalatest/matchers/dsl/MatcherFactory5;
        17: areturn
      LineNumberTable:
        line 2317: 0
      LocalVariableTable:
        Start  Length  Slot  Name   Signature
            0      18     0  this   Lorg/scalatest/matchers/dsl/MatcherFactory5$OrNotWord;
            0      18     1 resultOfGreaterThanComparison   Lorg/scalatest/matchers/dsl/ResultOfGreaterThanComparison;
    Signature: #160                         // <U:Ljava/lang/Object;>(Lorg/scalatest/matchers/dsl/ResultOfGreaterThanComparison<TU;>;)Lorg/scalatest/matchers/dsl/MatcherFactory5<TSC;TTC1;TTC2;TTC3;TTC4;TTC5;>;
    MethodParameters:
      Name                           Flags
      resultOfGreaterThanComparison  final

  public <U extends java.lang.Object> org.scalatest.matchers.dsl.MatcherFactory5<SC, TC1, TC2, TC3, TC4, TC5> be(org.scalatest.matchers.dsl.ResultOfLessThanOrEqualToComparison<U>);
    descriptor: (Lorg/scalatest/matchers/dsl/ResultOfLessThanOrEqualToComparison;)Lorg/scalatest/matchers/dsl/MatcherFactory5;
    flags: (0x0001) ACC_PUBLIC
    Code:
      stack=3, locals=2, args_size=2
         0: aload_0
         1: getfield      #36                 // Field $outer:Lorg/scalatest/matchers/dsl/MatcherFactory5;
         4: getstatic     #42                 // Field org/scalatest/matchers/dsl/MatcherWords$.MODULE$:Lorg/scalatest/matchers/dsl/MatcherWords$;
         7: invokevirtual #46                 // Method org/scalatest/matchers/dsl/MatcherWords$.not:()Lorg/scalatest/matchers/dsl/NotWord;
        10: aload_1
        11: invokevirtual #171                // Method org/scalatest/matchers/dsl/NotWord.be:(Lorg/scalatest/matchers/dsl/ResultOfLessThanOrEqualToComparison;)Lorg/scalatest/matchers/Matcher;
        14: invokevirtual #69                 // Method org/scalatest/matchers/dsl/MatcherFactory5.or:(Lorg/scalatest/matchers/Matcher;)Lorg/scalatest/matchers/dsl/MatcherFactory5;
        17: areturn
      LineNumberTable:
        line 2328: 0
      LocalVariableTable:
        Start  Length  Slot  Name   Signature
            0      18     0  this   Lorg/scalatest/matchers/dsl/MatcherFactory5$OrNotWord;
            0      18     1 resultOfLessThanOrEqualToComparison   Lorg/scalatest/matchers/dsl/ResultOfLessThanOrEqualToComparison;
    Signature: #167                         // <U:Ljava/lang/Object;>(Lorg/scalatest/matchers/dsl/ResultOfLessThanOrEqualToComparison<TU;>;)Lorg/scalatest/matchers/dsl/MatcherFactory5<TSC;TTC1;TTC2;TTC3;TTC4;TTC5;>;
    MethodParameters:
      Name                           Flags
      resultOfLessThanOrEqualToComparisonfinal

  public <U extends java.lang.Object> org.scalatest.matchers.dsl.MatcherFactory5<SC, TC1, TC2, TC3, TC4, TC5> be(org.scalatest.matchers.dsl.ResultOfGreaterThanOrEqualToComparison<U>);
    descriptor: (Lorg/scalatest/matchers/dsl/ResultOfGreaterThanOrEqualToComparison;)Lorg/scalatest/matchers/dsl/MatcherFactory5;
    flags: (0x0001) ACC_PUBLIC
    Code:
      stack=3, locals=2, args_size=2
         0: aload_0
         1: getfield      #36                 // Field $outer:Lorg/scalatest/matchers/dsl/MatcherFactory5;
         4: getstatic     #42                 // Field org/scalatest/matchers/dsl/MatcherWords$.MODULE$:Lorg/scalatest/matchers/dsl/MatcherWords$;
         7: invokevirtual #46                 // Method org/scalatest/matchers/dsl/MatcherWords$.not:()Lorg/scalatest/matchers/dsl/NotWord;
        10: aload_1
        11: invokevirtual #178                // Method org/scalatest/matchers/dsl/NotWord.be:(Lorg/scalatest/matchers/dsl/ResultOfGreaterThanOrEqualToComparison;)Lorg/scalatest/matchers/Matcher;
        14: invokevirtual #69                 // Method org/scalatest/matchers/dsl/MatcherFactory5.or:(Lorg/scalatest/matchers/Matcher;)Lorg/scalatest/matchers/dsl/MatcherFactory5;
        17: areturn
      LineNumberTable:
        line 2339: 0
      LocalVariableTable:
        Start  Length  Slot  Name   Signature
            0      18     0  this   Lorg/scalatest/matchers/dsl/MatcherFactory5$OrNotWord;
            0      18     1 resultOfGreaterThanOrEqualToComparison   Lorg/scalatest/matchers/dsl/ResultOfGreaterThanOrEqualToComparison;
    Signature: #174                         // <U:Ljava/lang/Object;>(Lorg/scalatest/matchers/dsl/ResultOfGreaterThanOrEqualToComparison<TU;>;)Lorg/scalatest/matchers/dsl/MatcherFactory5<TSC;TTC1;TTC2;TTC3;TTC4;TTC5;>;
    MethodParameters:
      Name                           Flags
      resultOfGreaterThanOrEqualToComparisonfinal

  public org.scalatest.matchers.dsl.MatcherFactory5<SC, TC1, TC2, TC3, TC4, TC5> be(org.scalactic.TripleEqualsSupport$TripleEqualsInvocation<?>);
    descriptor: (Lorg/scalactic/TripleEqualsSupport$TripleEqualsInvocation;)Lorg/scalatest/matchers/dsl/MatcherFactory5;
    flags: (0x0001) ACC_PUBLIC
    Code:
      stack=4, locals=2, args_size=2
         0: aload_0
         1: getfield      #36                 // Field $outer:Lorg/scalatest/matchers/dsl/MatcherFactory5;
         4: getstatic     #42                 // Field org/scalatest/matchers/dsl/MatcherWords$.MODULE$:Lorg/scalatest/matchers/dsl/MatcherWords$;
         7: invokevirtual #46                 // Method org/scalatest/matchers/dsl/MatcherWords$.not:()Lorg/scalatest/matchers/dsl/NotWord;
        10: aload_1
        11: aload_0
        12: getfield      #184                // Field pos:Lorg/scalactic/source/Position;
        15: invokevirtual #187                // Method org/scalatest/matchers/dsl/NotWord.be:(Lorg/scalactic/TripleEqualsSupport$TripleEqualsInvocation;Lorg/scalactic/source/Position;)Lorg/scalatest/matchers/Matcher;
        18: invokevirtual #69                 // Method org/scalatest/matchers/dsl/MatcherFactory5.or:(Lorg/scalatest/matchers/Matcher;)Lorg/scalatest/matchers/dsl/MatcherFactory5;
        21: areturn
      LineNumberTable:
        line 2354: 0
      LocalVariableTable:
        Start  Length  Slot  Name   Signature
            0      22     0  this   Lorg/scalatest/matchers/dsl/MatcherFactory5$OrNotWord;
            0      22     1 tripleEqualsInvocation   Lorg/scalactic/TripleEqualsSupport$TripleEqualsInvocation;
    Signature: #181                         // (Lorg/scalactic/TripleEqualsSupport$TripleEqualsInvocation<*>;)Lorg/scalatest/matchers/dsl/MatcherFactory5<TSC;TTC1;TTC2;TTC3;TTC4;TTC5;>;
    MethodParameters:
      Name                           Flags
      tripleEqualsInvocation         final

  public <U extends java.lang.Object> org.scalatest.matchers.dsl.MatcherFactory5<SC, TC1, TC2, TC3, TC4, TC5> be(org.scalatest.matchers.BeMatcher<U>);
    descriptor: (Lorg/scalatest/matchers/BeMatcher;)Lorg/scalatest/matchers/dsl/MatcherFactory5;
    flags: (0x0001) ACC_PUBLIC
    Code:
      stack=3, locals=2, args_size=2
         0: aload_0
         1: getfield      #36                 // Field $outer:Lorg/scalatest/matchers/dsl/MatcherFactory5;
         4: getstatic     #42                 // Field org/scalatest/matchers/dsl/MatcherWords$.MODULE$:Lorg/scalatest/matchers/dsl/MatcherWords$;
         7: invokevirtual #46                 // Method org/scalatest/matchers/dsl/MatcherWords$.not:()Lorg/scalatest/matchers/dsl/NotWord;
        10: aload_1
        11: invokevirtual #194                // Method org/scalatest/matchers/dsl/NotWord.be:(Lorg/scalatest/matchers/BeMatcher;)Lorg/scalatest/matchers/Matcher;
        14: invokevirtual #69                 // Method org/scalatest/matchers/dsl/MatcherFactory5.or:(Lorg/scalatest/matchers/Matcher;)Lorg/scalatest/matchers/dsl/MatcherFactory5;
        17: areturn
      LineNumberTable:
        line 2376: 0
      LocalVariableTable:
        Start  Length  Slot  Name   Signature
            0      18     0  this   Lorg/scalatest/matchers/dsl/MatcherFactory5$OrNotWord;
            0      18     1 beMatcher   Lorg/scalatest/matchers/BeMatcher;
    Signature: #190                         // <U:Ljava/lang/Object;>(Lorg/scalatest/matchers/BeMatcher<TU;>;)Lorg/scalatest/matchers/dsl/MatcherFactory5<TSC;TTC1;TTC2;TTC3;TTC4;TTC5;>;
    MethodParameters:
      Name                           Flags
      beMatcher                      final

  public <U extends java.lang.Object> org.scalatest.matchers.dsl.MatcherFactory5<java.lang.Object, TC1, TC2, TC3, TC4, TC5> be(org.scalatest.matchers.BePropertyMatcher<U>);
    descriptor: (Lorg/scalatest/matchers/BePropertyMatcher;)Lorg/scalatest/matchers/dsl/MatcherFactory5;
    flags: (0x0001) ACC_PUBLIC
    Code:
      stack=3, locals=2, args_size=2
         0: aload_0
         1: getfield      #36                 // Field $outer:Lorg/scalatest/matchers/dsl/MatcherFactory5;
         4: getstatic     #42                 // Field org/scalatest/matchers/dsl/MatcherWords$.MODULE$:Lorg/scalatest/matchers/dsl/MatcherWords$;
         7: invokevirtual #46                 // Method org/scalatest/matchers/dsl/MatcherWords$.not:()Lorg/scalatest/matchers/dsl/NotWord;
        10: aload_1
        11: invokevirtual #201                // Method org/scalatest/matchers/dsl/NotWord.be:(Lorg/scalatest/matchers/BePropertyMatcher;)Lorg/scalatest/matchers/Matcher;
        14: invokevirtual #69                 // Method org/scalatest/matchers/dsl/MatcherFactory5.or:(Lorg/scalatest/matchers/Matcher;)Lorg/scalatest/matchers/dsl/MatcherFactory5;
        17: areturn
      LineNumberTable:
        line 2386: 0
      LocalVariableTable:
        Start  Length  Slot  Name   Signature
            0      18     0  this   Lorg/scalatest/matchers/dsl/MatcherFactory5$OrNotWord;
            0      18     1 bePropertyMatcher   Lorg/scalatest/matchers/BePropertyMatcher;
    Signature: #197                         // <U:Ljava/lang/Object;>(Lorg/scalatest/matchers/BePropertyMatcher<TU;>;)Lorg/scalatest/matchers/dsl/MatcherFactory5<Ljava/lang/Object;TTC1;TTC2;TTC3;TTC4;TTC5;>;
    MethodParameters:
      Name                           Flags
      bePropertyMatcher              final

  public <U extends java.lang.Object> org.scalatest.matchers.dsl.MatcherFactory5<SC, TC1, TC2, TC3, TC4, TC5> be(org.scalatest.matchers.dsl.ResultOfAWordToAMatcherApplication<U>);
    descriptor: (Lorg/scalatest/matchers/dsl/ResultOfAWordToAMatcherApplication;)Lorg/scalatest/matchers/dsl/MatcherFactory5;
    flags: (0x0001) ACC_PUBLIC
    Code:
      stack=3, locals=2, args_size=2
         0: aload_0
         1: getfield      #36                 // Field $outer:Lorg/scalatest/matchers/dsl/MatcherFactory5;
         4: getstatic     #42                 // Field org/scalatest/matchers/dsl/MatcherWords$.MODULE$:Lorg/scalatest/matchers/dsl/MatcherWords$;
         7: invokevirtual #46                 // Method org/scalatest/matchers/dsl/MatcherWords$.not:()Lorg/scalatest/matchers/dsl/NotWord;
        10: aload_1
        11: invokevirtual #208                // Method org/scalatest/matchers/dsl/NotWord.be:(Lorg/scalatest/matchers/dsl/ResultOfAWordToAMatcherApplication;)Lorg/scalatest/matchers/Matcher;
        14: invokevirtual #69                 // Method org/scalatest/matchers/dsl/MatcherFactory5.or:(Lorg/scalatest/matchers/Matcher;)Lorg/scalatest/matchers/dsl/MatcherFactory5;
        17: areturn
      LineNumberTable:
        line 2408: 0
      LocalVariableTable:
        Start  Length  Slot  Name   Signature
            0      18     0  this   Lorg/scalatest/matchers/dsl/MatcherFactory5$OrNotWord;
            0      18     1 resultOfAWordApplication   Lorg/scalatest/matchers/dsl/ResultOfAWordToAMatcherApplication;
    Signature: #204                         // <U:Ljava/lang/Object;>(Lorg/scalatest/matchers/dsl/ResultOfAWordToAMatcherApplication<TU;>;)Lorg/scalatest/matchers/dsl/MatcherFactory5<TSC;TTC1;TTC2;TTC3;TTC4;TTC5;>;
    MethodParameters:
      Name                           Flags
      resultOfAWordApplication       final

  public <U extends java.lang.Object> org.scalatest.matchers.dsl.MatcherFactory5<SC, TC1, TC2, TC3, TC4, TC5> be(org.scalatest.matchers.dsl.ResultOfAWordToBePropertyMatcherApplication<U>);
    descriptor: (Lorg/scalatest/matchers/dsl/ResultOfAWordToBePropertyMatcherApplication;)Lorg/scalatest/matchers/dsl/MatcherFactory5;
    flags: (0x0001) ACC_PUBLIC
    Code:
      stack=3, locals=2, args_size=2
         0: aload_0
         1: getfield      #36                 // Field $outer:Lorg/scalatest/matchers/dsl/MatcherFactory5;
         4: getstatic     #42                 // Field org/scalatest/matchers/dsl/MatcherWords$.MODULE$:Lorg/scalatest/matchers/dsl/MatcherWords$;
         7: invokevirtual #46                 // Method org/scalatest/matchers/dsl/MatcherWords$.not:()Lorg/scalatest/matchers/dsl/NotWord;
        10: aload_1
        11: invokevirtual #214                // Method org/scalatest/matchers/dsl/NotWord.be:(Lorg/scalatest/matchers/dsl/ResultOfAWordToBePropertyMatcherApplication;)Lorg/scalatest/matchers/Matcher;
        14: invokevirtual #69                 // Method org/scalatest/matchers/dsl/MatcherFactory5.or:(Lorg/scalatest/matchers/Matcher;)Lorg/scalatest/matchers/dsl/MatcherFactory5;
        17: areturn
      LineNumberTable:
        line 2418: 0
      LocalVariableTable:
        Start  Length  Slot  Name   Signature
            0      18     0  this   Lorg/scalatest/matchers/dsl/MatcherFactory5$OrNotWord;
            0      18     1 resultOfAWordApplication   Lorg/scalatest/matchers/dsl/ResultOfAWordToBePropertyMatcherApplication;
    Signature: #211                         // <U:Ljava/lang/Object;>(Lorg/scalatest/matchers/dsl/ResultOfAWordToBePropertyMatcherApplication<TU;>;)Lorg/scalatest/matchers/dsl/MatcherFactory5<TSC;TTC1;TTC2;TTC3;TTC4;TTC5;>;
    MethodParameters:
      Name                           Flags
      resultOfAWordApplication       final

  public <U extends java.lang.Object> org.scalatest.matchers.dsl.MatcherFactory5<SC, TC1, TC2, TC3, TC4, TC5> be(org.scalatest.matchers.dsl.ResultOfAnWordToBePropertyMatcherApplication<U>);
    descriptor: (Lorg/scalatest/matchers/dsl/ResultOfAnWordToBePropertyMatcherApplication;)Lorg/scalatest/matchers/dsl/MatcherFactory5;
    flags: (0x0001) ACC_PUBLIC
    Code:
      stack=3, locals=2, args_size=2
         0: aload_0
         1: getfield      #36                 // Field $outer:Lorg/scalatest/matchers/dsl/MatcherFactory5;
         4: getstatic     #42                 // Field org/scalatest/matchers/dsl/MatcherWords$.MODULE$:Lorg/scalatest/matchers/dsl/MatcherWords$;
         7: invokevirtual #46                 // Method org/scalatest/matchers/dsl/MatcherWords$.not:()Lorg/scalatest/matchers/dsl/NotWord;
        10: aload_1
        11: invokevirtual #221                // Method org/scalatest/matchers/dsl/NotWord.be:(Lorg/scalatest/matchers/dsl/ResultOfAnWordToBePropertyMatcherApplication;)Lorg/scalatest/matchers/Matcher;
        14: invokevirtual #69                 // Method org/scalatest/matchers/dsl/MatcherFactory5.or:(Lorg/scalatest/matchers/Matcher;)Lorg/scalatest/matchers/dsl/MatcherFactory5;
        17: areturn
      LineNumberTable:
        line 2440: 0
      LocalVariableTable:
        Start  Length  Slot  Name   Signature
            0      18     0  this   Lorg/scalatest/matchers/dsl/MatcherFactory5$OrNotWord;
            0      18     1 resultOfAnWordApplication   Lorg/scalatest/matchers/dsl/ResultOfAnWordToBePropertyMatcherApplication;
    Signature: #217                         // <U:Ljava/lang/Object;>(Lorg/scalatest/matchers/dsl/ResultOfAnWordToBePropertyMatcherApplication<TU;>;)Lorg/scalatest/matchers/dsl/MatcherFactory5<TSC;TTC1;TTC2;TTC3;TTC4;TTC5;>;
    MethodParameters:
      Name                           Flags
      resultOfAnWordApplication      final

  public <U extends java.lang.Object> org.scalatest.matchers.dsl.MatcherFactory5<SC, TC1, TC2, TC3, TC4, TC5> be(org.scalatest.matchers.dsl.ResultOfAnWordToAnMatcherApplication<U>);
    descriptor: (Lorg/scalatest/matchers/dsl/ResultOfAnWordToAnMatcherApplication;)Lorg/scalatest/matchers/dsl/MatcherFactory5;
    flags: (0x0001) ACC_PUBLIC
    Code:
      stack=3, locals=2, args_size=2
         0: aload_0
         1: getfield      #36                 // Field $outer:Lorg/scalatest/matchers/dsl/MatcherFactory5;
         4: getstatic     #42                 // Field org/scalatest/matchers/dsl/MatcherWords$.MODULE$:Lorg/scalatest/matchers/dsl/MatcherWords$;
         7: invokevirtual #46                 // Method org/scalatest/matchers/dsl/MatcherWords$.not:()Lorg/scalatest/matchers/dsl/NotWord;
        10: aload_1
        11: invokevirtual #227                // Method org/scalatest/matchers/dsl/NotWord.be:(Lorg/scalatest/matchers/dsl/ResultOfAnWordToAnMatcherApplication;)Lorg/scalatest/matchers/Matcher;
        14: invokevirtual #69                 // Method org/scalatest/matchers/dsl/MatcherFactory5.or:(Lorg/scalatest/matchers/Matcher;)Lorg/scalatest/matchers/dsl/MatcherFactory5;
        17: areturn
      LineNumberTable:
        line 2450: 0
      LocalVariableTable:
        Start  Length  Slot  Name   Signature
            0      18     0  this   Lorg/scalatest/matchers/dsl/MatcherFactory5$OrNotWord;
            0      18     1 resultOfAnWordApplication   Lorg/scalatest/matchers/dsl/ResultOfAnWordToAnMatcherApplication;
    Signature: #224                         // <U:Ljava/lang/Object;>(Lorg/scalatest/matchers/dsl/ResultOfAnWordToAnMatcherApplication<TU;>;)Lorg/scalatest/matchers/dsl/MatcherFactory5<TSC;TTC1;TTC2;TTC3;TTC4;TTC5;>;
    MethodParameters:
      Name                           Flags
      resultOfAnWordApplication      final

  public org.scalatest.matchers.dsl.MatcherFactory5<java.lang.Object, TC1, TC2, TC3, TC4, TC5> be(org.scalatest.matchers.dsl.ResultOfTheSameInstanceAsApplication);
    descriptor: (Lorg/scalatest/matchers/dsl/ResultOfTheSameInstanceAsApplication;)Lorg/scalatest/matchers/dsl/MatcherFactory5;
    flags: (0x0001) ACC_PUBLIC
    Code:
      stack=3, locals=2, args_size=2
         0: aload_0
         1: getfield      #36                 // Field $outer:Lorg/scalatest/matchers/dsl/MatcherFactory5;
         4: getstatic     #42                 // Field org/scalatest/matchers/dsl/MatcherWords$.MODULE$:Lorg/scalatest/matchers/dsl/MatcherWords$;
         7: invokevirtual #46                 // Method org/scalatest/matchers/dsl/MatcherWords$.not:()Lorg/scalatest/matchers/dsl/NotWord;
        10: aload_1
        11: invokevirtual #234                // Method org/scalatest/matchers/dsl/NotWord.be:(Lorg/scalatest/matchers/dsl/ResultOfTheSameInstanceAsApplication;)Lorg/scalatest/matchers/Matcher;
        14: invokevirtual #69                 // Method org/scalatest/matchers/dsl/MatcherFactory5.or:(Lorg/scalatest/matchers/Matcher;)Lorg/scalatest/matchers/dsl/MatcherFactory5;
        17: areturn
      LineNumberTable:
        line 2482: 0
      LocalVariableTable:
        Start  Length  Slot  Name   Signature
            0      18     0  this   Lorg/scalatest/matchers/dsl/MatcherFactory5$OrNotWord;
            0      18     1 resultOfTheSameInstanceAsApplication   Lorg/scalatest/matchers/dsl/ResultOfTheSameInstanceAsApplication;
    Signature: #230                         // (Lorg/scalatest/matchers/dsl/ResultOfTheSameInstanceAsApplication;)Lorg/scalatest/matchers/dsl/MatcherFactory5<Ljava/lang/Object;TTC1;TTC2;TTC3;TTC4;TTC5;>;
    MethodParameters:
      Name                           Flags
      resultOfTheSameInstanceAsApplicationfinal

  public <U extends java.lang.Object> org.scalatest.matchers.dsl.MatcherFactory5<SC, TC1, TC2, TC3, TC4, TC5> be(org.scalactic.TripleEqualsSupport$Spread<U>);
    descriptor: (Lorg/scalactic/TripleEqualsSupport$Spread;)Lorg/scalatest/matchers/dsl/MatcherFactory5;
    flags: (0x0001) ACC_PUBLIC
    Code:
      stack=3, locals=2, args_size=2
         0: aload_0
         1: getfield      #36                 // Field $outer:Lorg/scalatest/matchers/dsl/MatcherFactory5;
         4: getstatic     #42                 // Field org/scalatest/matchers/dsl/MatcherWords$.MODULE$:Lorg/scalatest/matchers/dsl/MatcherWords$;
         7: invokevirtual #46                 // Method org/scalatest/matchers/dsl/MatcherWords$.not:()Lorg/scalatest/matchers/dsl/NotWord;
        10: aload_1
        11: invokevirtual #237                // Method org/scalatest/matchers/dsl/NotWord.be:(Lorg/scalactic/TripleEqualsSupport$Spread;)Lorg/scalatest/matchers/Matcher;
        14: invokevirtual #69                 // Method org/scalatest/matchers/dsl/MatcherFactory5.or:(Lorg/scalatest/matchers/Matcher;)Lorg/scalatest/matchers/dsl/MatcherFactory5;
        17: areturn
      LineNumberTable:
        line 2492: 0
      LocalVariableTable:
        Start  Length  Slot  Name   Signature
            0      18     0  this   Lorg/scalatest/matchers/dsl/MatcherFactory5$OrNotWord;
            0      18     1 spread   Lorg/scalactic/TripleEqualsSupport$Spread;
    Signature: #62                          // <U:Ljava/lang/Object;>(Lorg/scalactic/TripleEqualsSupport$Spread<TU;>;)Lorg/scalatest/matchers/dsl/MatcherFactory5<TSC;TTC1;TTC2;TTC3;TTC4;TTC5;>;
    MethodParameters:
      Name                           Flags
      spread                         final

  public <A extends java.lang.Object, U extends scala.PartialFunction<A, ?>> org.scalatest.matchers.dsl.MatcherFactory5<SC, TC1, TC2, TC3, TC4, TC5> be(org.scalatest.matchers.dsl.ResultOfDefinedAt<A>);
    descriptor: (Lorg/scalatest/matchers/dsl/ResultOfDefinedAt;)Lorg/scalatest/matchers/dsl/MatcherFactory5;
    flags: (0x0001) ACC_PUBLIC
    Code:
      stack=3, locals=2, args_size=2
         0: aload_0
         1: getfield      #36                 // Field $outer:Lorg/scalatest/matchers/dsl/MatcherFactory5;
         4: getstatic     #42                 // Field org/scalatest/matchers/dsl/MatcherWords$.MODULE$:Lorg/scalatest/matchers/dsl/MatcherWords$;
         7: invokevirtual #46                 // Method org/scalatest/matchers/dsl/MatcherWords$.not:()Lorg/scalatest/matchers/dsl/NotWord;
        10: aload_1
        11: invokevirtual #243                // Method org/scalatest/matchers/dsl/NotWord.be:(Lorg/scalatest/matchers/dsl/ResultOfDefinedAt;)Lorg/scalatest/matchers/Matcher;
        14: invokevirtual #69                 // Method org/scalatest/matchers/dsl/MatcherFactory5.or:(Lorg/scalatest/matchers/Matcher;)Lorg/scalatest/matchers/dsl/MatcherFactory5;
        17: areturn
      LineNumberTable:
        line 2503: 0
      LocalVariableTable:
        Start  Length  Slot  Name   Signature
            0      18     0  this   Lorg/scalatest/matchers/dsl/MatcherFactory5$OrNotWord;
            0      18     1 resultOfDefinedAt   Lorg/scalatest/matchers/dsl/ResultOfDefinedAt;
    Signature: #239                         // <A:Ljava/lang/Object;U::Lscala/PartialFunction<TA;*>;>(Lorg/scalatest/matchers/dsl/ResultOfDefinedAt<TA;>;)Lorg/scalatest/matchers/dsl/MatcherFactory5<TSC;TTC1;TTC2;TTC3;TTC4;TTC5;>;
    MethodParameters:
      Name                           Flags
      resultOfDefinedAt              final

  public org.scalatest.matchers.dsl.MatcherFactory6<SC, TC1, TC2, TC3, TC4, TC5, ?> be(org.scalatest.matchers.dsl.SortedWord);
    descriptor: (Lorg/scalatest/matchers/dsl/SortedWord;)Lorg/scalatest/matchers/dsl/MatcherFactory6;
    flags: (0x0001) ACC_PUBLIC
    Code:
      stack=3, locals=2, args_size=2
         0: aload_0
         1: getfield      #36                 // Field $outer:Lorg/scalatest/matchers/dsl/MatcherFactory5;
         4: getstatic     #42                 // Field org/scalatest/matchers/dsl/MatcherWords$.MODULE$:Lorg/scalatest/matchers/dsl/MatcherWords$;
         7: invokevirtual #46                 // Method org/scalatest/matchers/dsl/MatcherWords$.not:()Lorg/scalatest/matchers/dsl/NotWord;
        10: aload_1
        11: invokevirtual #250                // Method org/scalatest/matchers/dsl/NotWord.be:(Lorg/scalatest/matchers/dsl/SortedWord;)Lorg/scalatest/matchers/dsl/MatcherFactory1;
        14: invokevirtual #59                 // Method org/scalatest/matchers/dsl/MatcherFactory5.or:(Lorg/scalatest/matchers/dsl/MatcherFactory1;)Lorg/scalatest/matchers/dsl/MatcherFactory6;
        17: areturn
      LineNumberTable:
        line 2514: 0
      LocalVariableTable:
        Start  Length  Slot  Name   Signature
            0      18     0  this   Lorg/scalatest/matchers/dsl/MatcherFactory5$OrNotWord;
            0      18     1 sortedWord   Lorg/scalatest/matchers/dsl/SortedWord;
    Signature: #246                         // (Lorg/scalatest/matchers/dsl/SortedWord;)Lorg/scalatest/matchers/dsl/MatcherFactory6<TSC;TTC1;TTC2;TTC3;TTC4;TTC5;*>;
    MethodParameters:
      Name                           Flags
      sortedWord                     final

  public org.scalatest.matchers.dsl.MatcherFactory6<SC, TC1, TC2, TC3, TC4, TC5, ?> be(org.scalatest.matchers.dsl.ReadableWord);
    descriptor: (Lorg/scalatest/matchers/dsl/ReadableWord;)Lorg/scalatest/matchers/dsl/MatcherFactory6;
    flags: (0x0001) ACC_PUBLIC
    Code:
      stack=3, locals=2, args_size=2
         0: aload_0
         1: getfield      #36                 // Field $outer:Lorg/scalatest/matchers/dsl/MatcherFactory5;
         4: getstatic     #42                 // Field org/scalatest/matchers/dsl/MatcherWords$.MODULE$:Lorg/scalatest/matchers/dsl/MatcherWords$;
         7: invokevirtual #46                 // Method org/scalatest/matchers/dsl/MatcherWords$.not:()Lorg/scalatest/matchers/dsl/NotWord;
        10: aload_1
        11: invokevirtual #257                // Method org/scalatest/matchers/dsl/NotWord.be:(Lorg/scalatest/matchers/dsl/ReadableWord;)Lorg/scalatest/matchers/dsl/MatcherFactory1;
        14: invokevirtual #59                 // Method org/scalatest/matchers/dsl/MatcherFactory5.or:(Lorg/scalatest/matchers/dsl/MatcherFactory1;)Lorg/scalatest/matchers/dsl/MatcherFactory6;
        17: areturn
      LineNumberTable:
        line 2525: 0
      LocalVariableTable:
        Start  Length  Slot  Name   Signature
            0      18     0  this   Lorg/scalatest/matchers/dsl/MatcherFactory5$OrNotWord;
            0      18     1 readableWord   Lorg/scalatest/matchers/dsl/ReadableWord;
    Signature: #253                         // (Lorg/scalatest/matchers/dsl/ReadableWord;)Lorg/scalatest/matchers/dsl/MatcherFactory6<TSC;TTC1;TTC2;TTC3;TTC4;TTC5;*>;
    MethodParameters:
      Name                           Flags
      readableWord                   final

  public org.scalatest.matchers.dsl.MatcherFactory6<SC, TC1, TC2, TC3, TC4, TC5, ?> be(org.scalatest.matchers.dsl.WritableWord);
    descriptor: (Lorg/scalatest/matchers/dsl/WritableWord;)Lorg/scalatest/matchers/dsl/MatcherFactory6;
    flags: (0x0001) ACC_PUBLIC
    Code:
      stack=3, locals=2, args_size=2
         0: aload_0
         1: getfield      #36                 // Field $outer:Lorg/scalatest/matchers/dsl/MatcherFactory5;
         4: getstatic     #42                 // Field org/scalatest/matchers/dsl/MatcherWords$.MODULE$:Lorg/scalatest/matchers/dsl/MatcherWords$;
         7: invokevirtual #46                 // Method org/scalatest/matchers/dsl/MatcherWords$.not:()Lorg/scalatest/matchers/dsl/NotWord;
        10: aload_1
        11: invokevirtual #264                // Method org/scalatest/matchers/dsl/NotWord.be:(Lorg/scalatest/matchers/dsl/WritableWord;)Lorg/scalatest/matchers/dsl/MatcherFactory1;
        14: invokevirtual #59                 // Method org/scalatest/matchers/dsl/MatcherFactory5.or:(Lorg/scalatest/matchers/dsl/MatcherFactory1;)Lorg/scalatest/matchers/dsl/MatcherFactory6;
        17: areturn
      LineNumberTable:
        line 2536: 0
      LocalVariableTable:
        Start  Length  Slot  Name   Signature
            0      18     0  this   Lorg/scalatest/matchers/dsl/MatcherFactory5$OrNotWord;
            0      18     1 writableWord   Lorg/scalatest/matchers/dsl/WritableWord;
    Signature: #260                         // (Lorg/scalatest/matchers/dsl/WritableWord;)Lorg/scalatest/matchers/dsl/MatcherFactory6<TSC;TTC1;TTC2;TTC3;TTC4;TTC5;*>;
    MethodParameters:
      Name                           Flags
      writableWord                   final

  public org.scalatest.matchers.dsl.MatcherFactory6<SC, TC1, TC2, TC3, TC4, TC5, ?> be(org.scalatest.matchers.dsl.EmptyWord);
    descriptor: (Lorg/scalatest/matchers/dsl/EmptyWord;)Lorg/scalatest/matchers/dsl/MatcherFactory6;
    flags: (0x0001) ACC_PUBLIC
    Code:
      stack=3, locals=2, args_size=2
         0: aload_0
         1: getfield      #36                 // Field $outer:Lorg/scalatest/matchers/dsl/MatcherFactory5;
         4: getstatic     #42                 // Field org/scalatest/matchers/dsl/MatcherWords$.MODULE$:Lorg/scalatest/matchers/dsl/MatcherWords$;
         7: invokevirtual #46                 // Method org/scalatest/matchers/dsl/MatcherWords$.not:()Lorg/scalatest/matchers/dsl/NotWord;
        10: aload_1
        11: invokevirtual #271                // Method org/scalatest/matchers/dsl/NotWord.be:(Lorg/scalatest/matchers/dsl/EmptyWord;)Lorg/scalatest/matchers/dsl/MatcherFactory1;
        14: invokevirtual #59                 // Method org/scalatest/matchers/dsl/MatcherFactory5.or:(Lorg/scalatest/matchers/dsl/MatcherFactory1;)Lorg/scalatest/matchers/dsl/MatcherFactory6;
        17: areturn
      LineNumberTable:
        line 2547: 0
      LocalVariableTable:
        Start  Length  Slot  Name   Signature
            0      18     0  this   Lorg/scalatest/matchers/dsl/MatcherFactory5$OrNotWord;
            0      18     1 emptyWord   Lorg/scalatest/matchers/dsl/EmptyWord;
    Signature: #267                         // (Lorg/scalatest/matchers/dsl/EmptyWord;)Lorg/scalatest/matchers/dsl/MatcherFactory6<TSC;TTC1;TTC2;TTC3;TTC4;TTC5;*>;
    MethodParameters:
      Name                           Flags
      emptyWord                      final

  public org.scalatest.matchers.dsl.MatcherFactory6<SC, TC1, TC2, TC3, TC4, TC5, ?> be(org.scalatest.matchers.dsl.DefinedWord);
    descriptor: (Lorg/scalatest/matchers/dsl/DefinedWord;)Lorg/scalatest/matchers/dsl/MatcherFactory6;
    flags: (0x0001) ACC_PUBLIC
    Code:
      stack=3, locals=2, args_size=2
         0: aload_0
         1: getfield      #36                 // Field $outer:Lorg/scalatest/matchers/dsl/MatcherFactory5;
         4: getstatic     #42                 // Field org/scalatest/matchers/dsl/MatcherWords$.MODULE$:Lorg/scalatest/matchers/dsl/MatcherWords$;
         7: invokevirtual #46                 // Method org/scalatest/matchers/dsl/MatcherWords$.not:()Lorg/scalatest/matchers/dsl/NotWord;
        10: aload_1
        11: invokevirtual #278                // Method org/scalatest/matchers/dsl/NotWord.be:(Lorg/scalatest/matchers/dsl/DefinedWord;)Lorg/scalatest/matchers/dsl/MatcherFactory1;
        14: invokevirtual #59                 // Method org/scalatest/matchers/dsl/MatcherFactory5.or:(Lorg/scalatest/matchers/dsl/MatcherFactory1;)Lorg/scalatest/matchers/dsl/MatcherFactory6;
        17: areturn
      LineNumberTable:
        line 2558: 0
      LocalVariableTable:
        Start  Length  Slot  Name   Signature
            0      18     0  this   Lorg/scalatest/matchers/dsl/MatcherFactory5$OrNotWord;
            0      18     1 definedWord   Lorg/scalatest/matchers/dsl/DefinedWord;
    Signature: #274                         // (Lorg/scalatest/matchers/dsl/DefinedWord;)Lorg/scalatest/matchers/dsl/MatcherFactory6<TSC;TTC1;TTC2;TTC3;TTC4;TTC5;*>;
    MethodParameters:
      Name                           Flags
      definedWord                    final

  public org.scalatest.matchers.dsl.MatcherFactory5<java.lang.String, TC1, TC2, TC3, TC4, TC5> fullyMatch(org.scalatest.matchers.dsl.ResultOfRegexWordApplication);
    descriptor: (Lorg/scalatest/matchers/dsl/ResultOfRegexWordApplication;)Lorg/scalatest/matchers/dsl/MatcherFactory5;
    flags: (0x0001) ACC_PUBLIC
    Code:
      stack=3, locals=2, args_size=2
         0: aload_0
         1: getfield      #36                 // Field $outer:Lorg/scalatest/matchers/dsl/MatcherFactory5;
         4: getstatic     #42                 // Field org/scalatest/matchers/dsl/MatcherWords$.MODULE$:Lorg/scalatest/matchers/dsl/MatcherWords$;
         7: invokevirtual #46                 // Method org/scalatest/matchers/dsl/MatcherWords$.not:()Lorg/scalatest/matchers/dsl/NotWord;
        10: aload_1
        11: invokevirtual #286                // Method org/scalatest/matchers/dsl/NotWord.fullyMatch:(Lorg/scalatest/matchers/dsl/ResultOfRegexWordApplication;)Lorg/scalatest/matchers/Matcher;
        14: invokevirtual #69                 // Method org/scalatest/matchers/dsl/MatcherFactory5.or:(Lorg/scalatest/matchers/Matcher;)Lorg/scalatest/matchers/dsl/MatcherFactory5;
        17: areturn
      LineNumberTable:
        line 2569: 0
      LocalVariableTable:
        Start  Length  Slot  Name   Signature
            0      18     0  this   Lorg/scalatest/matchers/dsl/MatcherFactory5$OrNotWord;
            0      18     1 resultOfRegexWordApplication   Lorg/scalatest/matchers/dsl/ResultOfRegexWordApplication;
    Signature: #282                         // (Lorg/scalatest/matchers/dsl/ResultOfRegexWordApplication;)Lorg/scalatest/matchers/dsl/MatcherFactory5<Ljava/lang/String;TTC1;TTC2;TTC3;TTC4;TTC5;>;
    MethodParameters:
      Name                           Flags
      resultOfRegexWordApplication   final

  public org.scalatest.matchers.dsl.MatcherFactory5<java.lang.String, TC1, TC2, TC3, TC4, TC5> include(org.scalatest.matchers.dsl.ResultOfRegexWordApplication);
    descriptor: (Lorg/scalatest/matchers/dsl/ResultOfRegexWordApplication;)Lorg/scalatest/matchers/dsl/MatcherFactory5;
    flags: (0x0001) ACC_PUBLIC
    Code:
      stack=3, locals=2, args_size=2
         0: aload_0
         1: getfield      #36                 // Field $outer:Lorg/scalatest/matchers/dsl/MatcherFactory5;
         4: getstatic     #42                 // Field org/scalatest/matchers/dsl/MatcherWords$.MODULE$:Lorg/scalatest/matchers/dsl/MatcherWords$;
         7: invokevirtual #46                 // Method org/scalatest/matchers/dsl/MatcherWords$.not:()Lorg/scalatest/matchers/dsl/NotWord;
        10: aload_1
        11: invokevirtual #290                // Method org/scalatest/matchers/dsl/NotWord.include:(Lorg/scalatest/matchers/dsl/ResultOfRegexWordApplication;)Lorg/scalatest/matchers/Matcher;
        14: invokevirtual #69                 // Method org/scalatest/matchers/dsl/MatcherFactory5.or:(Lorg/scalatest/matchers/Matcher;)Lorg/scalatest/matchers/dsl/MatcherFactory5;
        17: areturn
      LineNumberTable:
        line 2580: 0
      LocalVariableTable:
        Start  Length  Slot  Name   Signature
            0      18     0  this   Lorg/scalatest/matchers/dsl/MatcherFactory5$OrNotWord;
            0      18     1 resultOfRegexWordApplication   Lorg/scalatest/matchers/dsl/ResultOfRegexWordApplication;
    Signature: #282                         // (Lorg/scalatest/matchers/dsl/ResultOfRegexWordApplication;)Lorg/scalatest/matchers/dsl/MatcherFactory5<Ljava/lang/String;TTC1;TTC2;TTC3;TTC4;TTC5;>;
    MethodParameters:
      Name                           Flags
      resultOfRegexWordApplication   final

  public org.scalatest.matchers.dsl.MatcherFactory5<java.lang.String, TC1, TC2, TC3, TC4, TC5> include(java.lang.String);
    descriptor: (Ljava/lang/String;)Lorg/scalatest/matchers/dsl/MatcherFactory5;
    flags: (0x0001) ACC_PUBLIC
    Code:
      stack=3, locals=2, args_size=2
         0: aload_0
         1: getfield      #36                 // Field $outer:Lorg/scalatest/matchers/dsl/MatcherFactory5;
         4: getstatic     #42                 // Field org/scalatest/matchers/dsl/MatcherWords$.MODULE$:Lorg/scalatest/matchers/dsl/MatcherWords$;
         7: invokevirtual #46                 // Method org/scalatest/matchers/dsl/MatcherWords$.not:()Lorg/scalatest/matchers/dsl/NotWord;
        10: aload_1
        11: invokevirtual #296                // Method org/scalatest/matchers/dsl/NotWord.include:(Ljava/lang/String;)Lorg/scalatest/matchers/Matcher;
        14: invokevirtual #69                 // Method org/scalatest/matchers/dsl/MatcherFactory5.or:(Lorg/scalatest/matchers/Matcher;)Lorg/scalatest/matchers/dsl/MatcherFactory5;
        17: areturn
      LineNumberTable:
        line 2591: 0
      LocalVariableTable:
        Start  Length  Slot  Name   Signature
            0      18     0  this   Lorg/scalatest/matchers/dsl/MatcherFactory5$OrNotWord;
            0      18     1 expectedSubstring   Ljava/lang/String;
    Signature: #292                         // (Ljava/lang/String;)Lorg/scalatest/matchers/dsl/MatcherFactory5<Ljava/lang/String;TTC1;TTC2;TTC3;TTC4;TTC5;>;
    MethodParameters:
      Name                           Flags
      expectedSubstring              final

  public org.scalatest.matchers.dsl.MatcherFactory5<java.lang.String, TC1, TC2, TC3, TC4, TC5> startWith(org.scalatest.matchers.dsl.ResultOfRegexWordApplication);
    descriptor: (Lorg/scalatest/matchers/dsl/ResultOfRegexWordApplication;)Lorg/scalatest/matchers/dsl/MatcherFactory5;
    flags: (0x0001) ACC_PUBLIC
    Code:
      stack=3, locals=2, args_size=2
         0: aload_0
         1: getfield      #36                 // Field $outer:Lorg/scalatest/matchers/dsl/MatcherFactory5;
         4: getstatic     #42                 // Field org/scalatest/matchers/dsl/MatcherWords$.MODULE$:Lorg/scalatest/matchers/dsl/MatcherWords$;
         7: invokevirtual #46                 // Method org/scalatest/matchers/dsl/MatcherWords$.not:()Lorg/scalatest/matchers/dsl/NotWord;
        10: aload_1
        11: invokevirtual #300                // Method org/scalatest/matchers/dsl/NotWord.startWith:(Lorg/scalatest/matchers/dsl/ResultOfRegexWordApplication;)Lorg/scalatest/matchers/Matcher;
        14: invokevirtual #69                 // Method org/scalatest/matchers/dsl/MatcherFactory5.or:(Lorg/scalatest/matchers/Matcher;)Lorg/scalatest/matchers/dsl/MatcherFactory5;
        17: areturn
      LineNumberTable:
        line 2602: 0
      LocalVariableTable:
        Start  Length  Slot  Name   Signature
            0      18     0  this   Lorg/scalatest/matchers/dsl/MatcherFactory5$OrNotWord;
            0      18     1 resultOfRegexWordApplication   Lorg/scalatest/matchers/dsl/ResultOfRegexWordApplication;
    Signature: #282                         // (Lorg/scalatest/matchers/dsl/ResultOfRegexWordApplication;)Lorg/scalatest/matchers/dsl/MatcherFactory5<Ljava/lang/String;TTC1;TTC2;TTC3;TTC4;TTC5;>;
    MethodParameters:
      Name                           Flags
      resultOfRegexWordApplication   final

  public org.scalatest.matchers.dsl.MatcherFactory5<java.lang.String, TC1, TC2, TC3, TC4, TC5> startWith(java.lang.String);
    descriptor: (Ljava/lang/String;)Lorg/scalatest/matchers/dsl/MatcherFactory5;
    flags: (0x0001) ACC_PUBLIC
    Code:
      stack=3, locals=2, args_size=2
         0: aload_0
         1: getfield      #36                 // Field $outer:Lorg/scalatest/matchers/dsl/MatcherFactory5;
         4: getstatic     #42                 // Field org/scalatest/matchers/dsl/MatcherWords$.MODULE$:Lorg/scalatest/matchers/dsl/MatcherWords$;
         7: invokevirtual #46                 // Method org/scalatest/matchers/dsl/MatcherWords$.not:()Lorg/scalatest/matchers/dsl/NotWord;
        10: aload_1
        11: invokevirtual #302                // Method org/scalatest/matchers/dsl/NotWord.startWith:(Ljava/lang/String;)Lorg/scalatest/matchers/Matcher;
        14: invokevirtual #69                 // Method org/scalatest/matchers/dsl/MatcherFactory5.or:(Lorg/scalatest/matchers/Matcher;)Lorg/scalatest/matchers/dsl/MatcherFactory5;
        17: areturn
      LineNumberTable:
        line 2613: 0
      LocalVariableTable:
        Start  Length  Slot  Name   Signature
            0      18     0  this   Lorg/scalatest/matchers/dsl/MatcherFactory5$OrNotWord;
            0      18     1 expectedSubstring   Ljava/lang/String;
    Signature: #292                         // (Ljava/lang/String;)Lorg/scalatest/matchers/dsl/MatcherFactory5<Ljava/lang/String;TTC1;TTC2;TTC3;TTC4;TTC5;>;
    MethodParameters:
      Name                           Flags
      expectedSubstring              final

  public org.scalatest.matchers.dsl.MatcherFactory5<java.lang.String, TC1, TC2, TC3, TC4, TC5> endWith(org.scalatest.matchers.dsl.ResultOfRegexWordApplication);
    descriptor: (Lorg/scalatest/matchers/dsl/ResultOfRegexWordApplication;)Lorg/scalatest/matchers/dsl/MatcherFactory5;
    flags: (0x0001) ACC_PUBLIC
    Code:
      stack=3, locals=2, args_size=2
         0: aload_0
         1: getfield      #36                 // Field $outer:Lorg/scalatest/matchers/dsl/MatcherFactory5;
         4: getstatic     #42                 // Field org/scalatest/matchers/dsl/MatcherWords$.MODULE$:Lorg/scalatest/matchers/dsl/MatcherWords$;
         7: invokevirtual #46                 // Method org/scalatest/matchers/dsl/MatcherWords$.not:()Lorg/scalatest/matchers/dsl/NotWord;
        10: aload_1
        11: invokevirtual #305                // Method org/scalatest/matchers/dsl/NotWord.endWith:(Lorg/scalatest/matchers/dsl/ResultOfRegexWordApplication;)Lorg/scalatest/matchers/Matcher;
        14: invokevirtual #69                 // Method org/scalatest/matchers/dsl/MatcherFactory5.or:(Lorg/scalatest/matchers/Matcher;)Lorg/scalatest/matchers/dsl/MatcherFactory5;
        17: areturn
      LineNumberTable:
        line 2624: 0
      LocalVariableTable:
        Start  Length  Slot  Name   Signature
            0      18     0  this   Lorg/scalatest/matchers/dsl/MatcherFactory5$OrNotWord;
            0      18     1 resultOfRegexWordApplication   Lorg/scalatest/matchers/dsl/ResultOfRegexWordApplication;
    Signature: #282                         // (Lorg/scalatest/matchers/dsl/ResultOfRegexWordApplication;)Lorg/scalatest/matchers/dsl/MatcherFactory5<Ljava/lang/String;TTC1;TTC2;TTC3;TTC4;TTC5;>;
    MethodParameters:
      Name                           Flags
      resultOfRegexWordApplication   final

  public org.scalatest.matchers.dsl.MatcherFactory5<java.lang.String, TC1, TC2, TC3, TC4, TC5> endWith(java.lang.String);
    descriptor: (Ljava/lang/String;)Lorg/scalatest/matchers/dsl/MatcherFactory5;
    flags: (0x0001) ACC_PUBLIC
    Code:
      stack=3, locals=2, args_size=2
         0: aload_0
         1: getfield      #36                 // Field $outer:Lorg/scalatest/matchers/dsl/MatcherFactory5;
         4: getstatic     #42                 // Field org/scalatest/matchers/dsl/MatcherWords$.MODULE$:Lorg/scalatest/matchers/dsl/MatcherWords$;
         7: invokevirtual #46                 // Method org/scalatest/matchers/dsl/MatcherWords$.not:()Lorg/scalatest/matchers/dsl/NotWord;
        10: aload_1
        11: invokevirtual #307                // Method org/scalatest/matchers/dsl/NotWord.endWith:(Ljava/lang/String;)Lorg/scalatest/matchers/Matcher;
        14: invokevirtual #69                 // Method org/scalatest/matchers/dsl/MatcherFactory5.or:(Lorg/scalatest/matchers/Matcher;)Lorg/scalatest/matchers/dsl/MatcherFactory5;
        17: areturn
      LineNumberTable:
        line 2635: 0
      LocalVariableTable:
        Start  Length  Slot  Name   Signature
            0      18     0  this   Lorg/scalatest/matchers/dsl/MatcherFactory5$OrNotWord;
            0      18     1 expectedSubstring   Ljava/lang/String;
    Signature: #292                         // (Ljava/lang/String;)Lorg/scalatest/matchers/dsl/MatcherFactory5<Ljava/lang/String;TTC1;TTC2;TTC3;TTC4;TTC5;>;
    MethodParameters:
      Name                           Flags
      expectedSubstring              final

  public <U extends java.lang.Object> org.scalatest.matchers.dsl.MatcherFactory6<SC, TC1, TC2, TC3, TC4, TC5, org.scalatest.enablers.Containing> contain(U);
    descriptor: (Ljava/lang/Object;)Lorg/scalatest/matchers/dsl/MatcherFactory6;
    flags: (0x0001) ACC_PUBLIC
    Code:
      stack=3, locals=2, args_size=2
         0: aload_0
         1: getfield      #36                 // Field $outer:Lorg/scalatest/matchers/dsl/MatcherFactory5;
         4: getstatic     #42                 // Field org/scalatest/matchers/dsl/MatcherWords$.MODULE$:Lorg/scalatest/matchers/dsl/MatcherWords$;
         7: invokevirtual #46                 // Method org/scalatest/matchers/dsl/MatcherWords$.not:()Lorg/scalatest/matchers/dsl/NotWord;
        10: aload_1
        11: invokevirtual #312                // Method org/scalatest/matchers/dsl/NotWord.contain:(Ljava/lang/Object;)Lorg/scalatest/matchers/dsl/MatcherFactory1;
        14: invokevirtual #59                 // Method org/scalatest/matchers/dsl/MatcherFactory5.or:(Lorg/scalatest/matchers/dsl/MatcherFactory1;)Lorg/scalatest/matchers/dsl/MatcherFactory6;
        17: areturn
      LineNumberTable:
        line 2646: 0
      LocalVariableTable:
        Start  Length  Slot  Name   Signature
            0      18     0  this   Lorg/scalatest/matchers/dsl/MatcherFactory5$OrNotWord;
            0      18     1 expectedElement   Ljava/lang/Object;
    Signature: #309                         // <U:Ljava/lang/Object;>(TU;)Lorg/scalatest/matchers/dsl/MatcherFactory6<TSC;TTC1;TTC2;TTC3;TTC4;TTC5;Lorg/scalatest/enablers/Containing;>;
    MethodParameters:
      Name                           Flags
      expectedElement                final

  public org.scalatest.matchers.dsl.MatcherFactory6<SC, TC1, TC2, TC3, TC4, TC5, org.scalatest.enablers.KeyMapping> contain(org.scalatest.matchers.dsl.ResultOfKeyWordApplication);
    descriptor: (Lorg/scalatest/matchers/dsl/ResultOfKeyWordApplication;)Lorg/scalatest/matchers/dsl/MatcherFactory6;
    flags: (0x0001) ACC_PUBLIC
    Code:
      stack=3, locals=2, args_size=2
         0: aload_0
         1: getfield      #36                 // Field $outer:Lorg/scalatest/matchers/dsl/MatcherFactory5;
         4: getstatic     #42                 // Field org/scalatest/matchers/dsl/MatcherWords$.MODULE$:Lorg/scalatest/matchers/dsl/MatcherWords$;
         7: invokevirtual #46                 // Method org/scalatest/matchers/dsl/MatcherWords$.not:()Lorg/scalatest/matchers/dsl/NotWord;
        10: aload_1
        11: invokevirtual #318                // Method org/scalatest/matchers/dsl/NotWord.contain:(Lorg/scalatest/matchers/dsl/ResultOfKeyWordApplication;)Lorg/scalatest/matchers/dsl/MatcherFactory1;
        14: invokevirtual #59                 // Method org/scalatest/matchers/dsl/MatcherFactory5.or:(Lorg/scalatest/matchers/dsl/MatcherFactory1;)Lorg/scalatest/matchers/dsl/MatcherFactory6;
        17: areturn
      LineNumberTable:
        line 2657: 0
      LocalVariableTable:
        Start  Length  Slot  Name   Signature
            0      18     0  this   Lorg/scalatest/matchers/dsl/MatcherFactory5$OrNotWord;
            0      18     1 resultOfKeyWordApplication   Lorg/scalatest/matchers/dsl/ResultOfKeyWordApplication;
    Signature: #314                         // (Lorg/scalatest/matchers/dsl/ResultOfKeyWordApplication;)Lorg/scalatest/matchers/dsl/MatcherFactory6<TSC;TTC1;TTC2;TTC3;TTC4;TTC5;Lorg/scalatest/enablers/KeyMapping;>;
    MethodParameters:
      Name                           Flags
      resultOfKeyWordApplication     final

  public org.scalatest.matchers.dsl.MatcherFactory6<SC, TC1, TC2, TC3, TC4, TC5, org.scalatest.enablers.ValueMapping> contain(org.scalatest.matchers.dsl.ResultOfValueWordApplication);
    descriptor: (Lorg/scalatest/matchers/dsl/ResultOfValueWordApplication;)Lorg/scalatest/matchers/dsl/MatcherFactory6;
    flags: (0x0001) ACC_PUBLIC
    Code:
      stack=3, locals=2, args_size=2
         0: aload_0
         1: getfield      #36                 // Field $outer:Lorg/scalatest/matchers/dsl/MatcherFactory5;
         4: getstatic     #42                 // Field org/scalatest/matchers/dsl/MatcherWords$.MODULE$:Lorg/scalatest/matchers/dsl/MatcherWords$;
         7: invokevirtual #46                 // Method org/scalatest/matchers/dsl/MatcherWords$.not:()Lorg/scalatest/matchers/dsl/NotWord;
        10: aload_1
        11: invokevirtual #325                // Method org/scalatest/matchers/dsl/NotWord.contain:(Lorg/scalatest/matchers/dsl/ResultOfValueWordApplication;)Lorg/scalatest/matchers/dsl/MatcherFactory1;
        14: invokevirtual #59                 // Method org/scalatest/matchers/dsl/MatcherFactory5.or:(Lorg/scalatest/matchers/dsl/MatcherFactory1;)Lorg/scalatest/matchers/dsl/MatcherFactory6;
        17: areturn
      LineNumberTable:
        line 2668: 0
      LocalVariableTable:
        Start  Length  Slot  Name   Signature
            0      18     0  this   Lorg/scalatest/matchers/dsl/MatcherFactory5$OrNotWord;
            0      18     1 resultOfValueWordApplication   Lorg/scalatest/matchers/dsl/ResultOfValueWordApplication;
    Signature: #321                         // (Lorg/scalatest/matchers/dsl/ResultOfValueWordApplication;)Lorg/scalatest/matchers/dsl/MatcherFactory6<TSC;TTC1;TTC2;TTC3;TTC4;TTC5;Lorg/scalatest/enablers/ValueMapping;>;
    MethodParameters:
      Name                           Flags
      resultOfValueWordApplication   final

  public org.scalatest.matchers.dsl.MatcherFactory6<SC, TC1, TC2, TC3, TC4, TC5, org.scalatest.enablers.Containing> contain(org.scalatest.matchers.dsl.ResultOfOneOfApplication);
    descriptor: (Lorg/scalatest/matchers/dsl/ResultOfOneOfApplication;)Lorg/scalatest/matchers/dsl/MatcherFactory6;
    flags: (0x0001) ACC_PUBLIC
    Code:
      stack=4, locals=2, args_size=2
         0: aload_0
         1: getfield      #36                 // Field $outer:Lorg/scalatest/matchers/dsl/MatcherFactory5;
         4: getstatic     #42                 // Field org/scalatest/matchers/dsl/MatcherWords$.MODULE$:Lorg/scalatest/matchers/dsl/MatcherWords$;
         7: invokevirtual #46                 // Method org/scalatest/matchers/dsl/MatcherWords$.not:()Lorg/scalatest/matchers/dsl/NotWord;
        10: aload_1
        11: getstatic     #334                // Field org/scalactic/Prettifier$.MODULE$:Lorg/scalactic/Prettifier$;
        14: invokevirtual #338                // Method org/scalactic/Prettifier$.default:()Lorg/scalactic/Prettifier;
        17: invokevirtual #341                // Method org/scalatest/matchers/dsl/NotWord.contain:(Lorg/scalatest/matchers/dsl/ResultOfOneOfApplication;Lorg/scalactic/Prettifier;)Lorg/scalatest/matchers/dsl/MatcherFactory1;
        20: invokevirtual #59                 // Method org/scalatest/matchers/dsl/MatcherFactory5.or:(Lorg/scalatest/matchers/dsl/MatcherFactory1;)Lorg/scalatest/matchers/dsl/MatcherFactory6;
        23: areturn
      LineNumberTable:
        line 2679: 0
      LocalVariableTable:
        Start  Length  Slot  Name   Signature
            0      24     0  this   Lorg/scalatest/matchers/dsl/MatcherFactory5$OrNotWord;
            0      24     1 right   Lorg/scalatest/matchers/dsl/ResultOfOneOfApplication;
    Signature: #328                         // (Lorg/scalatest/matchers/dsl/ResultOfOneOfApplication;)Lorg/scalatest/matchers/dsl/MatcherFactory6<TSC;TTC1;TTC2;TTC3;TTC4;TTC5;Lorg/scalatest/enablers/Containing;>;
    MethodParameters:
      Name                           Flags
      right                          final

  public org.scalatest.matchers.dsl.MatcherFactory6<SC, TC1, TC2, TC3, TC4, TC5, org.scalatest.enablers.Containing> contain(org.scalatest.matchers.dsl.ResultOfOneElementOfApplication);
    descriptor: (Lorg/scalatest/matchers/dsl/ResultOfOneElementOfApplication;)Lorg/scalatest/matchers/dsl/MatcherFactory6;
    flags: (0x0001) ACC_PUBLIC
    Code:
      stack=3, locals=2, args_size=2
         0: aload_0
         1: getfield      #36                 // Field $outer:Lorg/scalatest/matchers/dsl/MatcherFactory5;
         4: getstatic     #42                 // Field org/scalatest/matchers/dsl/MatcherWords$.MODULE$:Lorg/scalatest/matchers/dsl/MatcherWords$;
         7: invokevirtual #46                 // Method org/scalatest/matchers/dsl/MatcherWords$.not:()Lorg/scalatest/matchers/dsl/NotWord;
        10: aload_1
        11: invokevirtual #347                // Method org/scalatest/matchers/dsl/NotWord.contain:(Lorg/scalatest/matchers/dsl/ResultOfOneElementOfApplication;)Lorg/scalatest/matchers/dsl/MatcherFactory1;
        14: invokevirtual #59                 // Method org/scalatest/matchers/dsl/MatcherFactory5.or:(Lorg/scalatest/matchers/dsl/MatcherFactory1;)Lorg/scalatest/matchers/dsl/MatcherFactory6;
        17: areturn
      LineNumberTable:
        line 2690: 0
      LocalVariableTable:
        Start  Length  Slot  Name   Signature
            0      18     0  this   Lorg/scalatest/matchers/dsl/MatcherFactory5$OrNotWord;
            0      18     1 right   Lorg/scalatest/matchers/dsl/ResultOfOneElementOfApplication;
    Signature: #344                         // (Lorg/scalatest/matchers/dsl/ResultOfOneElementOfApplication;)Lorg/scalatest/matchers/dsl/MatcherFactory6<TSC;TTC1;TTC2;TTC3;TTC4;TTC5;Lorg/scalatest/enablers/Containing;>;
    MethodParameters:
      Name                           Flags
      right                          final

  public org.scalatest.matchers.dsl.MatcherFactory6<SC, TC1, TC2, TC3, TC4, TC5, org.scalatest.enablers.Aggregating> contain(org.scalatest.matchers.dsl.ResultOfAtLeastOneOfApplication);
    descriptor: (Lorg/scalatest/matchers/dsl/ResultOfAtLeastOneOfApplication;)Lorg/scalatest/matchers/dsl/MatcherFactory6;
    flags: (0x0001) ACC_PUBLIC
    Code:
      stack=4, locals=2, args_size=2
         0: aload_0
         1: getfield      #36                 // Field $outer:Lorg/scalatest/matchers/dsl/MatcherFactory5;
         4: getstatic     #42                 // Field org/scalatest/matchers/dsl/MatcherWords$.MODULE$:Lorg/scalatest/matchers/dsl/MatcherWords$;
         7: invokevirtual #46                 // Method org/scalatest/matchers/dsl/MatcherWords$.not:()Lorg/scalatest/matchers/dsl/NotWord;
        10: aload_1
        11: getstatic     #334                // Field org/scalactic/Prettifier$.MODULE$:Lorg/scalactic/Prettifier$;
        14: invokevirtual #338                // Method org/scalactic/Prettifier$.default:()Lorg/scalactic/Prettifier;
        17: invokevirtual #353                // Method org/scalatest/matchers/dsl/NotWord.contain:(Lorg/scalatest/matchers/dsl/ResultOfAtLeastOneOfApplication;Lorg/scalactic/Prettifier;)Lorg/scalatest/matchers/dsl/MatcherFactory1;
        20: invokevirtual #59                 // Method org/scalatest/matchers/dsl/MatcherFactory5.or:(Lorg/scalatest/matchers/dsl/MatcherFactory1;)Lorg/scalatest/matchers/dsl/MatcherFactory6;
        23: areturn
      LineNumberTable:
        line 2701: 0
      LocalVariableTable:
        Start  Length  Slot  Name   Signature
            0      24     0  this   Lorg/scalatest/matchers/dsl/MatcherFactory5$OrNotWord;
            0      24     1 right   Lorg/scalatest/matchers/dsl/ResultOfAtLeastOneOfApplication;
    Signature: #350                         // (Lorg/scalatest/matchers/dsl/ResultOfAtLeastOneOfApplication;)Lorg/scalatest/matchers/dsl/MatcherFactory6<TSC;TTC1;TTC2;TTC3;TTC4;TTC5;Lorg/scalatest/enablers/Aggregating;>;
    MethodParameters:
      Name                           Flags
      right                          final

  public org.scalatest.matchers.dsl.MatcherFactory6<SC, TC1, TC2, TC3, TC4, TC5, org.scalatest.enablers.Aggregating> contain(org.scalatest.matchers.dsl.ResultOfAtLeastOneElementOfApplication);
    descriptor: (Lorg/scalatest/matchers/dsl/ResultOfAtLeastOneElementOfApplication;)Lorg/scalatest/matchers/dsl/MatcherFactory6;
    flags: (0x0001) ACC_PUBLIC
    Code:
      stack=3, locals=2, args_size=2
         0: aload_0
         1: getfield      #36                 // Field $outer:Lorg/scalatest/matchers/dsl/MatcherFactory5;
         4: getstatic     #42                 // Field org/scalatest/matchers/dsl/MatcherWords$.MODULE$:Lorg/scalatest/matchers/dsl/MatcherWords$;
         7: invokevirtual #46                 // Method org/scalatest/matchers/dsl/MatcherWords$.not:()Lorg/scalatest/matchers/dsl/NotWord;
        10: aload_1
        11: invokevirtual #359                // Method org/scalatest/matchers/dsl/NotWord.contain:(Lorg/scalatest/matchers/dsl/ResultOfAtLeastOneElementOfApplication;)Lorg/scalatest/matchers/dsl/MatcherFactory1;
        14: invokevirtual #59                 // Method org/scalatest/matchers/dsl/MatcherFactory5.or:(Lorg/scalatest/matchers/dsl/MatcherFactory1;)Lorg/scalatest/matchers/dsl/MatcherFactory6;
        17: areturn
      LineNumberTable:
        line 2712: 0
      LocalVariableTable:
        Start  Length  Slot  Name   Signature
            0      18     0  this   Lorg/scalatest/matchers/dsl/MatcherFactory5$OrNotWord;
            0      18     1 right   Lorg/scalatest/matchers/dsl/ResultOfAtLeastOneElementOfApplication;
    Signature: #356                         // (Lorg/scalatest/matchers/dsl/ResultOfAtLeastOneElementOfApplication;)Lorg/scalatest/matchers/dsl/MatcherFactory6<TSC;TTC1;TTC2;TTC3;TTC4;TTC5;Lorg/scalatest/enablers/Aggregating;>;
    MethodParameters:
      Name                           Flags
      right                          final

  public org.scalatest.matchers.dsl.MatcherFactory6<SC, TC1, TC2, TC3, TC4, TC5, org.scalatest.enablers.Containing> contain(org.scalatest.matchers.dsl.ResultOfNoneOfApplication);
    descriptor: (Lorg/scalatest/matchers/dsl/ResultOfNoneOfApplication;)Lorg/scalatest/matchers/dsl/MatcherFactory6;
    flags: (0x0001) ACC_PUBLIC
    Code:
      stack=4, locals=2, args_size=2
         0: aload_0
         1: getfield      #36                 // Field $outer:Lorg/scalatest/matchers/dsl/MatcherFactory5;
         4: getstatic     #42                 // Field org/scalatest/matchers/dsl/MatcherWords$.MODULE$:Lorg/scalatest/matchers/dsl/MatcherWords$;
         7: invokevirtual #46                 // Method org/scalatest/matchers/dsl/MatcherWords$.not:()Lorg/scalatest/matchers/dsl/NotWord;
        10: aload_1
        11: getstatic     #334                // Field org/scalactic/Prettifier$.MODULE$:Lorg/scalactic/Prettifier$;
        14: invokevirtual #338                // Method org/scalactic/Prettifier$.default:()Lorg/scalactic/Prettifier;
        17: invokevirtual #365                // Method org/scalatest/matchers/dsl/NotWord.contain:(Lorg/scalatest/matchers/dsl/ResultOfNoneOfApplication;Lorg/scalactic/Prettifier;)Lorg/scalatest/matchers/dsl/MatcherFactory1;
        20: invokevirtual #59                 // Method org/scalatest/matchers/dsl/MatcherFactory5.or:(Lorg/scalatest/matchers/dsl/MatcherFactory1;)Lorg/scalatest/matchers/dsl/MatcherFactory6;
        23: areturn
      LineNumberTable:
        line 2723: 0
      LocalVariableTable:
        Start  Length  Slot  Name   Signature
            0      24     0  this   Lorg/scalatest/matchers/dsl/MatcherFactory5$OrNotWord;
            0      24     1 right   Lorg/scalatest/matchers/dsl/ResultOfNoneOfApplication;
    Signature: #362                         // (Lorg/scalatest/matchers/dsl/ResultOfNoneOfApplication;)Lorg/scalatest/matchers/dsl/MatcherFactory6<TSC;TTC1;TTC2;TTC3;TTC4;TTC5;Lorg/scalatest/enablers/Containing;>;
    MethodParameters:
      Name                           Flags
      right                          final

  public org.scalatest.matchers.dsl.MatcherFactory6<SC, TC1, TC2, TC3, TC4, TC5, org.scalatest.enablers.Containing> contain(org.scalatest.matchers.dsl.ResultOfNoElementsOfApplication);
    descriptor: (Lorg/scalatest/matchers/dsl/ResultOfNoElementsOfApplication;)Lorg/scalatest/matchers/dsl/MatcherFactory6;
    flags: (0x0001) ACC_PUBLIC
    Code:
      stack=3, locals=2, args_size=2
         0: aload_0
         1: getfield      #36                 // Field $outer:Lorg/scalatest/matchers/dsl/MatcherFactory5;
         4: getstatic     #42                 // Field org/scalatest/matchers/dsl/MatcherWords$.MODULE$:Lorg/scalatest/matchers/dsl/MatcherWords$;
         7: invokevirtual #46                 // Method org/scalatest/matchers/dsl/MatcherWords$.not:()Lorg/scalatest/matchers/dsl/NotWord;
        10: aload_1
        11: invokevirtual #371                // Method org/scalatest/matchers/dsl/NotWord.contain:(Lorg/scalatest/matchers/dsl/ResultOfNoElementsOfApplication;)Lorg/scalatest/matchers/dsl/MatcherFactory1;
        14: invokevirtual #59                 // Method org/scalatest/matchers/dsl/MatcherFactory5.or:(Lorg/scalatest/matchers/dsl/MatcherFactory1;)Lorg/scalatest/matchers/dsl/MatcherFactory6;
        17: areturn
      LineNumberTable:
        line 2734: 0
      LocalVariableTable:
        Start  Length  Slot  Name   Signature
            0      18     0  this   Lorg/scalatest/matchers/dsl/MatcherFactory5$OrNotWord;
            0      18     1 right   Lorg/scalatest/matchers/dsl/ResultOfNoElementsOfApplication;
    Signature: #368                         // (Lorg/scalatest/matchers/dsl/ResultOfNoElementsOfApplication;)Lorg/scalatest/matchers/dsl/MatcherFactory6<TSC;TTC1;TTC2;TTC3;TTC4;TTC5;Lorg/scalatest/enablers/Containing;>;
    MethodParameters:
      Name                           Flags
      right                          final

  public org.scalatest.matchers.dsl.MatcherFactory6<SC, TC1, TC2, TC3, TC4, TC5, org.scalatest.enablers.Aggregating> contain(org.scalatest.matchers.dsl.ResultOfTheSameElementsAsApplication);
    descriptor: (Lorg/scalatest/matchers/dsl/ResultOfTheSameElementsAsApplication;)Lorg/scalatest/matchers/dsl/MatcherFactory6;
    flags: (0x0001) ACC_PUBLIC
    Code:
      stack=3, locals=2, args_size=2
         0: aload_0
         1: getfield      #36                 // Field $outer:Lorg/scalatest/matchers/dsl/MatcherFactory5;
         4: getstatic     #42                 // Field org/scalatest/matchers/dsl/MatcherWords$.MODULE$:Lorg/scalatest/matchers/dsl/MatcherWords$;
         7: invokevirtual #46                 // Method org/scalatest/matchers/dsl/MatcherWords$.not:()Lorg/scalatest/matchers/dsl/NotWord;
        10: aload_1
        11: invokevirtual #377                // Method org/scalatest/matchers/dsl/NotWord.contain:(Lorg/scalatest/matchers/dsl/ResultOfTheSameElementsAsApplication;)Lorg/scalatest/matchers/dsl/MatcherFactory1;
        14: invokevirtual #59                 // Method org/scalatest/matchers/dsl/MatcherFactory5.or:(Lorg/scalatest/matchers/dsl/MatcherFactory1;)Lorg/scalatest/matchers/dsl/MatcherFactory6;
        17: areturn
      LineNumberTable:
        line 2745: 0
      LocalVariableTable:
        Start  Length  Slot  Name   Signature
            0      18     0  this   Lorg/scalatest/matchers/dsl/MatcherFactory5$OrNotWord;
            0      18     1 right   Lorg/scalatest/matchers/dsl/ResultOfTheSameElementsAsApplication;
    Signature: #374                         // (Lorg/scalatest/matchers/dsl/ResultOfTheSameElementsAsApplication;)Lorg/scalatest/matchers/dsl/MatcherFactory6<TSC;TTC1;TTC2;TTC3;TTC4;TTC5;Lorg/scalatest/enablers/Aggregating;>;
    MethodParameters:
      Name                           Flags
      right                          final

  public org.scalatest.matchers.dsl.MatcherFactory6<SC, TC1, TC2, TC3, TC4, TC5, org.scalatest.enablers.Sequencing> contain(org.scalatest.matchers.dsl.ResultOfTheSameElementsInOrderAsApplication);
    descriptor: (Lorg/scalatest/matchers/dsl/ResultOfTheSameElementsInOrderAsApplication;)Lorg/scalatest/matchers/dsl/MatcherFactory6;
    flags: (0x0001) ACC_PUBLIC
    Code:
      stack=3, locals=2, args_size=2
         0: aload_0
         1: getfield      #36                 // Field $outer:Lorg/scalatest/matchers/dsl/MatcherFactory5;
         4: getstatic     #42                 // Field org/scalatest/matchers/dsl/MatcherWords$.MODULE$:Lorg/scalatest/matchers/dsl/MatcherWords$;
         7: invokevirtual #46                 // Method org/scalatest/matchers/dsl/MatcherWords$.not:()Lorg/scalatest/matchers/dsl/NotWord;
        10: aload_1
        11: invokevirtual #383                // Method org/scalatest/matchers/dsl/NotWord.contain:(Lorg/scalatest/matchers/dsl/ResultOfTheSameElementsInOrderAsApplication;)Lorg/scalatest/matchers/dsl/MatcherFactory1;
        14: invokevirtual #59                 // Method org/scalatest/matchers/dsl/MatcherFactory5.or:(Lorg/scalatest/matchers/dsl/MatcherFactory1;)Lorg/scalatest/matchers/dsl/MatcherFactory6;
        17: areturn
      LineNumberTable:
        line 2756: 0
      LocalVariableTable:
        Start  Length  Slot  Name   Signature
            0      18     0  this   Lorg/scalatest/matchers/dsl/MatcherFactory5$OrNotWord;
            0      18     1 right   Lorg/scalatest/matchers/dsl/ResultOfTheSameElementsInOrderAsApplication;
    Signature: #380                         // (Lorg/scalatest/matchers/dsl/ResultOfTheSameElementsInOrderAsApplication;)Lorg/scalatest/matchers/dsl/MatcherFactory6<TSC;TTC1;TTC2;TTC3;TTC4;TTC5;Lorg/scalatest/enablers/Sequencing;>;
    MethodParameters:
      Name                           Flags
      right                          final

  public org.scalatest.matchers.dsl.MatcherFactory6<SC, TC1, TC2, TC3, TC4, TC5, org.scalatest.enablers.Aggregating> contain(org.scalatest.matchers.dsl.ResultOfOnlyApplication);
    descriptor: (Lorg/scalatest/matchers/dsl/ResultOfOnlyApplication;)Lorg/scalatest/matchers/dsl/MatcherFactory6;
    flags: (0x0001) ACC_PUBLIC
    Code:
      stack=4, locals=2, args_size=2
         0: aload_0
         1: getfield      #36                 // Field $outer:Lorg/scalatest/matchers/dsl/MatcherFactory5;
         4: getstatic     #42                 // Field org/scalatest/matchers/dsl/MatcherWords$.MODULE$:Lorg/scalatest/matchers/dsl/MatcherWords$;
         7: invokevirtual #46                 // Method org/scalatest/matchers/dsl/MatcherWords$.not:()Lorg/scalatest/matchers/dsl/NotWord;
        10: aload_1
        11: getstatic     #334                // Field org/scalactic/Prettifier$.MODULE$:Lorg/scalactic/Prettifier$;
        14: invokevirtual #338                // Method org/scalactic/Prettifier$.default:()Lorg/scalactic/Prettifier;
        17: invokevirtual #389                // Method org/scalatest/matchers/dsl/NotWord.contain:(Lorg/scalatest/matchers/dsl/ResultOfOnlyApplication;Lorg/scalactic/Prettifier;)Lorg/scalatest/matchers/dsl/MatcherFactory1;
        20: invokevirtual #59                 // Method org/scalatest/matchers/dsl/MatcherFactory5.or:(Lorg/scalatest/matchers/dsl/MatcherFactory1;)Lorg/scalatest/matchers/dsl/MatcherFactory6;
        23: areturn
      LineNumberTable:
        line 2767: 0
      LocalVariableTable:
        Start  Length  Slot  Name   Signature
            0      24     0  this   Lorg/scalatest/matchers/dsl/MatcherFactory5$OrNotWord;
            0      24     1 right   Lorg/scalatest/matchers/dsl/ResultOfOnlyApplication;
    Signature: #386                         // (Lorg/scalatest/matchers/dsl/ResultOfOnlyApplication;)Lorg/scalatest/matchers/dsl/MatcherFactory6<TSC;TTC1;TTC2;TTC3;TTC4;TTC5;Lorg/scalatest/enablers/Aggregating;>;
    MethodParameters:
      Name                           Flags
      right                          final

  public org.scalatest.matchers.dsl.MatcherFactory6<SC, TC1, TC2, TC3, TC4, TC5, org.scalatest.enablers.Sequencing> contain(org.scalatest.matchers.dsl.ResultOfInOrderOnlyApplication);
    descriptor: (Lorg/scalatest/matchers/dsl/ResultOfInOrderOnlyApplication;)Lorg/scalatest/matchers/dsl/MatcherFactory6;
    flags: (0x0001) ACC_PUBLIC
    Code:
      stack=4, locals=2, args_size=2
         0: aload_0
         1: getfield      #36                 // Field $outer:Lorg/scalatest/matchers/dsl/MatcherFactory5;
         4: getstatic     #42                 // Field org/scalatest/matchers/dsl/MatcherWords$.MODULE$:Lorg/scalatest/matchers/dsl/MatcherWords$;
         7: invokevirtual #46                 // Method org/scalatest/matchers/dsl/MatcherWords$.not:()Lorg/scalatest/matchers/dsl/NotWord;
        10: aload_1
        11: getstatic     #334                // Field org/scalactic/Prettifier$.MODULE$:Lorg/scalactic/Prettifier$;
        14: invokevirtual #338                // Method org/scalactic/Prettifier$.default:()Lorg/scalactic/Prettifier;
        17: invokevirtual #395                // Method org/scalatest/matchers/dsl/NotWord.contain:(Lorg/scalatest/matchers/dsl/ResultOfInOrderOnlyApplication;Lorg/scalactic/Prettifier;)Lorg/scalatest/matchers/dsl/MatcherFactory1;
        20: invokevirtual #59                 // Method org/scalatest/matchers/dsl/MatcherFactory5.or:(Lorg/scalatest/matchers/dsl/MatcherFactory1;)Lorg/scalatest/matchers/dsl/MatcherFactory6;
        23: areturn
      LineNumberTable:
        line 2778: 0
      LocalVariableTable:
        Start  Length  Slot  Name   Signature
            0      24     0  this   Lorg/scalatest/matchers/dsl/MatcherFactory5$OrNotWord;
            0      24     1 right   Lorg/scalatest/matchers/dsl/ResultOfInOrderOnlyApplication;
    Signature: #392                         // (Lorg/scalatest/matchers/dsl/ResultOfInOrderOnlyApplication;)Lorg/scalatest/matchers/dsl/MatcherFactory6<TSC;TTC1;TTC2;TTC3;TTC4;TTC5;Lorg/scalatest/enablers/Sequencing;>;
    MethodParameters:
      Name                           Flags
      right                          final

  public org.scalatest.matchers.dsl.MatcherFactory6<SC, TC1, TC2, TC3, TC4, TC5, org.scalatest.enablers.Aggregating> contain(org.scalatest.matchers.dsl.ResultOfAllOfApplication);
    descriptor: (Lorg/scalatest/matchers/dsl/ResultOfAllOfApplication;)Lorg/scalatest/matchers/dsl/MatcherFactory6;
    flags: (0x0001) ACC_PUBLIC
    Code:
      stack=4, locals=2, args_size=2
         0: aload_0
         1: getfield      #36                 // Field $outer:Lorg/scalatest/matchers/dsl/MatcherFactory5;
         4: getstatic     #42                 // Field org/scalatest/matchers/dsl/MatcherWords$.MODULE$:Lorg/scalatest/matchers/dsl/MatcherWords$;
         7: invokevirtual #46                 // Method org/scalatest/matchers/dsl/MatcherWords$.not:()Lorg/scalatest/matchers/dsl/NotWord;
        10: aload_1
        11: getstatic     #334                // Field org/scalactic/Prettifier$.MODULE$:Lorg/scalactic/Prettifier$;
        14: invokevirtual #338                // Method org/scalactic/Prettifier$.default:()Lorg/scalactic/Prettifier;
        17: invokevirtual #401                // Method org/scalatest/matchers/dsl/NotWord.contain:(Lorg/scalatest/matchers/dsl/ResultOfAllOfApplication;Lorg/scalactic/Prettifier;)Lorg/scalatest/matchers/dsl/MatcherFactory1;
        20: invokevirtual #59                 // Method org/scalatest/matchers/dsl/MatcherFactory5.or:(Lorg/scalatest/matchers/dsl/MatcherFactory1;)Lorg/scalatest/matchers/dsl/MatcherFactory6;
        23: areturn
      LineNumberTable:
        line 2789: 0
      LocalVariableTable:
        Start  Length  Slot  Name   Signature
            0      24     0  this   Lorg/scalatest/matchers/dsl/MatcherFactory5$OrNotWord;
            0      24     1 right   Lorg/scalatest/matchers/dsl/ResultOfAllOfApplication;
    Signature: #398                         // (Lorg/scalatest/matchers/dsl/ResultOfAllOfApplication;)Lorg/scalatest/matchers/dsl/MatcherFactory6<TSC;TTC1;TTC2;TTC3;TTC4;TTC5;Lorg/scalatest/enablers/Aggregating;>;
    MethodParameters:
      Name                           Flags
      right                          final

  public org.scalatest.matchers.dsl.MatcherFactory6<SC, TC1, TC2, TC3, TC4, TC5, org.scalatest.enablers.Aggregating> contain(org.scalatest.matchers.dsl.ResultOfAllElementsOfApplication);
    descriptor: (Lorg/scalatest/matchers/dsl/ResultOfAllElementsOfApplication;)Lorg/scalatest/matchers/dsl/MatcherFactory6;
    flags: (0x0001) ACC_PUBLIC
    Code:
      stack=3, locals=2, args_size=2
         0: aload_0
         1: getfield      #36                 // Field $outer:Lorg/scalatest/matchers/dsl/MatcherFactory5;
         4: getstatic     #42                 // Field org/scalatest/matchers/dsl/MatcherWords$.MODULE$:Lorg/scalatest/matchers/dsl/MatcherWords$;
         7: invokevirtual #46                 // Method org/scalatest/matchers/dsl/MatcherWords$.not:()Lorg/scalatest/matchers/dsl/NotWord;
        10: aload_1
        11: invokevirtual #407                // Method org/scalatest/matchers/dsl/NotWord.contain:(Lorg/scalatest/matchers/dsl/ResultOfAllElementsOfApplication;)Lorg/scalatest/matchers/dsl/MatcherFactory1;
        14: invokevirtual #59                 // Method org/scalatest/matchers/dsl/MatcherFactory5.or:(Lorg/scalatest/matchers/dsl/MatcherFactory1;)Lorg/scalatest/matchers/dsl/MatcherFactory6;
        17: areturn
      LineNumberTable:
        line 2800: 0
      LocalVariableTable:
        Start  Length  Slot  Name   Signature
            0      18     0  this   Lorg/scalatest/matchers/dsl/MatcherFactory5$OrNotWord;
            0      18     1 right   Lorg/scalatest/matchers/dsl/ResultOfAllElementsOfApplication;
    Signature: #404                         // (Lorg/scalatest/matchers/dsl/ResultOfAllElementsOfApplication;)Lorg/scalatest/matchers/dsl/MatcherFactory6<TSC;TTC1;TTC2;TTC3;TTC4;TTC5;Lorg/scalatest/enablers/Aggregating;>;
    MethodParameters:
      Name                           Flags
      right                          final

  public org.scalatest.matchers.dsl.MatcherFactory6<SC, TC1, TC2, TC3, TC4, TC5, org.scalatest.enablers.Sequencing> contain(org.scalatest.matchers.dsl.ResultOfInOrderApplication);
    descriptor: (Lorg/scalatest/matchers/dsl/ResultOfInOrderApplication;)Lorg/scalatest/matchers/dsl/MatcherFactory6;
    flags: (0x0001) ACC_PUBLIC
    Code:
      stack=4, locals=2, args_size=2
         0: aload_0
         1: getfield      #36                 // Field $outer:Lorg/scalatest/matchers/dsl/MatcherFactory5;
         4: getstatic     #42                 // Field org/scalatest/matchers/dsl/MatcherWords$.MODULE$:Lorg/scalatest/matchers/dsl/MatcherWords$;
         7: invokevirtual #46                 // Method org/scalatest/matchers/dsl/MatcherWords$.not:()Lorg/scalatest/matchers/dsl/NotWord;
        10: aload_1
        11: getstatic     #334                // Field org/scalactic/Prettifier$.MODULE$:Lorg/scalactic/Prettifier$;
        14: invokevirtual #338                // Method org/scalactic/Prettifier$.default:()Lorg/scalactic/Prettifier;
        17: invokevirtual #413                // Method org/scalatest/matchers/dsl/NotWord.contain:(Lorg/scalatest/matchers/dsl/ResultOfInOrderApplication;Lorg/scalactic/Prettifier;)Lorg/scalatest/matchers/dsl/MatcherFactory1;
        20: invokevirtual #59                 // Method org/scalatest/matchers/dsl/MatcherFactory5.or:(Lorg/scalatest/matchers/dsl/MatcherFactory1;)Lorg/scalatest/matchers/dsl/MatcherFactory6;
        23: areturn
      LineNumberTable:
        line 2811: 0
      LocalVariableTable:
        Start  Length  Slot  Name   Signature
            0      24     0  this   Lorg/scalatest/matchers/dsl/MatcherFactory5$OrNotWord;
            0      24     1 right   Lorg/scalatest/matchers/dsl/ResultOfInOrderApplication;
    Signature: #410                         // (Lorg/scalatest/matchers/dsl/ResultOfInOrderApplication;)Lorg/scalatest/matchers/dsl/MatcherFactory6<TSC;TTC1;TTC2;TTC3;TTC4;TTC5;Lorg/scalatest/enablers/Sequencing;>;
    MethodParameters:
      Name                           Flags
      right                          final

  public org.scalatest.matchers.dsl.MatcherFactory6<SC, TC1, TC2, TC3, TC4, TC5, org.scalatest.enablers.Sequencing> contain(org.scalatest.matchers.dsl.ResultOfInOrderElementsOfApplication);
    descriptor: (Lorg/scalatest/matchers/dsl/ResultOfInOrderElementsOfApplication;)Lorg/scalatest/matchers/dsl/MatcherFactory6;
    flags: (0x0001) ACC_PUBLIC
    Code:
      stack=3, locals=2, args_size=2
         0: aload_0
         1: getfield      #36                 // Field $outer:Lorg/scalatest/matchers/dsl/MatcherFactory5;
         4: getstatic     #42                 // Field org/scalatest/matchers/dsl/MatcherWords$.MODULE$:Lorg/scalatest/matchers/dsl/MatcherWords$;
         7: invokevirtual #46                 // Method org/scalatest/matchers/dsl/MatcherWords$.not:()Lorg/scalatest/matchers/dsl/NotWord;
        10: aload_1
        11: invokevirtual #419                // Method org/scalatest/matchers/dsl/NotWord.contain:(Lorg/scalatest/matchers/dsl/ResultOfInOrderElementsOfApplication;)Lorg/scalatest/matchers/dsl/MatcherFactory1;
        14: invokevirtual #59                 // Method org/scalatest/matchers/dsl/MatcherFactory5.or:(Lorg/scalatest/matchers/dsl/MatcherFactory1;)Lorg/scalatest/matchers/dsl/MatcherFactory6;
        17: areturn
      LineNumberTable:
        line 2822: 0
      LocalVariableTable:
        Start  Length  Slot  Name   Signature
            0      18     0  this   Lorg/scalatest/matchers/dsl/MatcherFactory5$OrNotWord;
            0      18     1 right   Lorg/scalatest/matchers/dsl/ResultOfInOrderElementsOfApplication;
    Signature: #416                         // (Lorg/scalatest/matchers/dsl/ResultOfInOrderElementsOfApplication;)Lorg/scalatest/matchers/dsl/MatcherFactory6<TSC;TTC1;TTC2;TTC3;TTC4;TTC5;Lorg/scalatest/enablers/Sequencing;>;
    MethodParameters:
      Name                           Flags
      right                          final

  public org.scalatest.matchers.dsl.MatcherFactory6<SC, TC1, TC2, TC3, TC4, TC5, org.scalatest.enablers.Aggregating> contain(org.scalatest.matchers.dsl.ResultOfAtMostOneOfApplication);
    descriptor: (Lorg/scalatest/matchers/dsl/ResultOfAtMostOneOfApplication;)Lorg/scalatest/matchers/dsl/MatcherFactory6;
    flags: (0x0001) ACC_PUBLIC
    Code:
      stack=4, locals=2, args_size=2
         0: aload_0
         1: getfield      #36                 // Field $outer:Lorg/scalatest/matchers/dsl/MatcherFactory5;
         4: getstatic     #42                 // Field org/scalatest/matchers/dsl/MatcherWords$.MODULE$:Lorg/scalatest/matchers/dsl/MatcherWords$;
         7: invokevirtual #46                 // Method org/scalatest/matchers/dsl/MatcherWords$.not:()Lorg/scalatest/matchers/dsl/NotWord;
        10: aload_1
        11: getstatic     #334                // Field org/scalactic/Prettifier$.MODULE$:Lorg/scalactic/Prettifier$;
        14: invokevirtual #338                // Method org/scalactic/Prettifier$.default:()Lorg/scalactic/Prettifier;
        17: invokevirtual #425                // Method org/scalatest/matchers/dsl/NotWord.contain:(Lorg/scalatest/matchers/dsl/ResultOfAtMostOneOfApplication;Lorg/scalactic/Prettifier;)Lorg/scalatest/matchers/dsl/MatcherFactory1;
        20: invokevirtual #59                 // Method org/scalatest/matchers/dsl/MatcherFactory5.or:(Lorg/scalatest/matchers/dsl/MatcherFactory1;)Lorg/scalatest/matchers/dsl/MatcherFactory6;
        23: areturn
      LineNumberTable:
        line 2833: 0
      LocalVariableTable:
        Start  Length  Slot  Name   Signature
            0      24     0  this   Lorg/scalatest/matchers/dsl/MatcherFactory5$OrNotWord;
            0      24     1 right   Lorg/scalatest/matchers/dsl/ResultOfAtMostOneOfApplication;
    Signature: #422                         // (Lorg/scalatest/matchers/dsl/ResultOfAtMostOneOfApplication;)Lorg/scalatest/matchers/dsl/MatcherFactory6<TSC;TTC1;TTC2;TTC3;TTC4;TTC5;Lorg/scalatest/enablers/Aggregating;>;
    MethodParameters:
      Name                           Flags
      right                          final

  public org.scalatest.matchers.dsl.MatcherFactory6<SC, TC1, TC2, TC3, TC4, TC5, org.scalatest.enablers.Aggregating> contain(org.scalatest.matchers.dsl.ResultOfAtMostOneElementOfApplication);
    descriptor: (Lorg/scalatest/matchers/dsl/ResultOfAtMostOneElementOfApplication;)Lorg/scalatest/matchers/dsl/MatcherFactory6;
    flags: (0x0001) ACC_PUBLIC
    Code:
      stack=3, locals=2, args_size=2
         0: aload_0
         1: getfield      #36                 // Field $outer:Lorg/scalatest/matchers/dsl/MatcherFactory5;
         4: getstatic     #42                 // Field org/scalatest/matchers/dsl/MatcherWords$.MODULE$:Lorg/scalatest/matchers/dsl/MatcherWords$;
         7: invokevirtual #46                 // Method org/scalatest/matchers/dsl/MatcherWords$.not:()Lorg/scalatest/matchers/dsl/NotWord;
        10: aload_1
        11: invokevirtual #431                // Method org/scalatest/matchers/dsl/NotWord.contain:(Lorg/scalatest/matchers/dsl/ResultOfAtMostOneElementOfApplication;)Lorg/scalatest/matchers/dsl/MatcherFactory1;
        14: invokevirtual #59                 // Method org/scalatest/matchers/dsl/MatcherFactory5.or:(Lorg/scalatest/matchers/dsl/MatcherFactory1;)Lorg/scalatest/matchers/dsl/MatcherFactory6;
        17: areturn
      LineNumberTable:
        line 2844: 0
      LocalVariableTable:
        Start  Length  Slot  Name   Signature
            0      18     0  this   Lorg/scalatest/matchers/dsl/MatcherFactory5$OrNotWord;
            0      18     1 right   Lorg/scalatest/matchers/dsl/ResultOfAtMostOneElementOfApplication;
    Signature: #428                         // (Lorg/scalatest/matchers/dsl/ResultOfAtMostOneElementOfApplication;)Lorg/scalatest/matchers/dsl/MatcherFactory6<TSC;TTC1;TTC2;TTC3;TTC4;TTC5;Lorg/scalatest/enablers/Aggregating;>;
    MethodParameters:
      Name                           Flags
      right                          final

  public org.scalatest.matchers.dsl.MatcherFactory5$OrNotWord(org.scalatest.matchers.dsl.MatcherFactory5, org.scalactic.Prettifier, org.scalactic.source.Position);
    descriptor: (Lorg/scalatest/matchers/dsl/MatcherFactory5;Lorg/scalactic/Prettifier;Lorg/scalactic/source/Position;)V
    flags: (0x0001) ACC_PUBLIC
    Code:
      stack=2, locals=4, args_size=4
         0: aload_0
         1: aload_3
         2: putfield      #184                // Field pos:Lorg/scalactic/source/Position;
         5: aload_1
         6: ifnonnull     11
         9: aconst_null
        10: athrow
        11: aload_0
        12: aload_1
        13: putfield      #36                 // Field $outer:Lorg/scalatest/matchers/dsl/MatcherFactory5;
        16: aload_0
        17: invokespecial #437                // Method java/lang/Object."<init>":()V
        20: aload_0
        21: aload_1
        22: putfield      #28                 // Field owner:Lorg/scalatest/matchers/dsl/MatcherFactory5;
        25: return
      StackMapTable: number_of_entries = 1
        frame_type = 11 /* same */
      LineNumberTable:
        line 2177: 0
        line 2865: 16
        line 2182: 20
        line 2177: 25
      LocalVariableTable:
        Start  Length  Slot  Name   Signature
            0      26     0  this   Lorg/scalatest/matchers/dsl/MatcherFactory5$OrNotWord;
            0      26     1 $outer   Lorg/scalatest/matchers/dsl/MatcherFactory5;
            0      26     2 prettifier   Lorg/scalactic/Prettifier;
            0      26     3   pos   Lorg/scalactic/source/Position;
    MethodParameters:
      Name                           Flags
      $outer                         final synthetic
      prettifier                     final
      pos                            final
}
InnerClasses:
  public static final #10= #7 of #9;      // Spread=class org/scalactic/TripleEqualsSupport$Spread of class org/scalactic/TripleEqualsSupport
  public static final #13= #12 of #9;     // TripleEqualsInvocation=class org/scalactic/TripleEqualsSupport$TripleEqualsInvocation of class org/scalactic/TripleEqualsSupport
  public final #16= #2 of #15;            // OrNotWord=class org/scalatest/matchers/dsl/MatcherFactory5$OrNotWord of class org/scalatest/matchers/dsl/MatcherFactory5
  public final #18;                       // class org/scalatest/matchers/dsl/MatcherFactory5$OrNotWord$$anon$26
SourceFile: "MatcherFactory5.scala"
  ScalaInlineInfo: length = 0x12B (unknown attribute)
   01 01 00 3B 00 4A 01 B1 01 00 4F 00 50 01 00 4F
   00 3D 01 00 4F 00 B4 01 00 4F 00 BD 01 00 4F 00
   C4 01 00 4F 01 11 01 00 4F 01 0A 01 00 4F 00 FC
   01 00 4F 01 C0 01 00 4F 00 CB 01 00 4F 00 D2 01
   00 4F 01 C1 01 00 4F 00 DF 01 00 4F 00 D8 01 00
   4F 00 EE 01 00 4F 00 9F 01 00 4F 00 AD 01 00 4F
   00 98 01 00 4F 00 A6 01 00 4F 00 E5 01 00 4F 00
   F5 01 00 4F 01 03 01 00 4F 00 47 01 01 34 00 20
   01 01 34 01 93 01 01 34 01 8D 01 01 34 01 63 01
   01 34 01 5D 01 01 34 01 AB 01 01 34 01 A5 01 01
   34 01 99 01 01 34 01 9F 01 01 34 01 87 01 01 34
   01 39 01 01 34 01 6F 01 01 34 01 69 01 01 34 01
   57 01 01 34 01 47 01 01 34 01 81 01 01 34 01 75
   01 01 34 01 7B 01 01 34 01 40 01 01 2F 01 23 01
   01 2F 01 19 01 00 1F 00 20 01 00 1F 00 3D 01 00
   1F 00 47 01 01 18 01 19 01 00 5D 00 8B 01 00 5D
   00 5E 01 00 5D 00 7D 01 00 5D 00 71 01 01 20 01
   23 01 01 20 01 19 01 01 C2 01 C3 01 00 15 00 19
   01 01 2A 01 23 01 01 2A 01 19 01
  Scala: length = 0x0 (unknown attribute)

