Classfile /Users/mw/Projects/slang-braindump/.jar/jar11/assemble/slang-braindump/assemble/content/org/scalatest/matchers/dsl/MatcherFactory8$AndHaveWord.class
  Last modified May 29, 2022; size 2117 bytes
  SHA-256 checksum 30b25d3b5dee6f14dcfae5f218c7ef5f366c0a8d42d8793982109e642f4662e0
  Compiled from "MatcherFactory8.scala"
public final class org.scalatest.matchers.dsl.MatcherFactory8$AndHaveWord
  minor version: 0
  major version: 52
  flags: (0x0031) ACC_PUBLIC, ACC_FINAL, ACC_SUPER
  this_class: #2                          // org/scalatest/matchers/dsl/MatcherFactory8$AndHaveWord
  super_class: #4                         // java/lang/Object
  interfaces: 0, fields: 1, methods: 4, attributes: 4
Constant pool:
   #1 = Utf8               org/scalatest/matchers/dsl/MatcherFactory8$AndHaveWord
   #2 = Class              #1             // org/scalatest/matchers/dsl/MatcherFactory8$AndHaveWord
   #3 = Utf8               java/lang/Object
   #4 = Class              #3             // java/lang/Object
   #5 = Utf8               MatcherFactory8.scala
   #6 = Utf8               org/scalatest/matchers/dsl/MatcherFactory8
   #7 = Class              #6             // org/scalatest/matchers/dsl/MatcherFactory8
   #8 = Utf8               AndHaveWord
   #9 = Utf8               $outer
  #10 = Utf8               Lorg/scalatest/matchers/dsl/MatcherFactory8;
  #11 = Utf8               length
  #12 = Utf8               (J)Lorg/scalatest/matchers/dsl/MatcherFactory9;
  #13 = Utf8               (J)Lorg/scalatest/matchers/dsl/MatcherFactory9<TSC;TTC1;TTC2;TTC3;TTC4;TTC5;TTC6;TTC7;TTC8;Lorg/scalatest/enablers/Length;>;
  #14 = Utf8               expectedLength
  #15 = NameAndType        #9:#10         // $outer:Lorg/scalatest/matchers/dsl/MatcherFactory8;
  #16 = Fieldref           #2.#15         // org/scalatest/matchers/dsl/MatcherFactory8$AndHaveWord.$outer:Lorg/scalatest/matchers/dsl/MatcherFactory8;
  #17 = Utf8               org/scalatest/matchers/dsl/MatcherWords$
  #18 = Class              #17            // org/scalatest/matchers/dsl/MatcherWords$
  #19 = Utf8               MODULE$
  #20 = Utf8               Lorg/scalatest/matchers/dsl/MatcherWords$;
  #21 = NameAndType        #19:#20        // MODULE$:Lorg/scalatest/matchers/dsl/MatcherWords$;
  #22 = Fieldref           #18.#21        // org/scalatest/matchers/dsl/MatcherWords$.MODULE$:Lorg/scalatest/matchers/dsl/MatcherWords$;
  #23 = Utf8               have
  #24 = Utf8               ()Lorg/scalatest/matchers/dsl/HaveWord;
  #25 = NameAndType        #23:#24        // have:()Lorg/scalatest/matchers/dsl/HaveWord;
  #26 = Methodref          #18.#25        // org/scalatest/matchers/dsl/MatcherWords$.have:()Lorg/scalatest/matchers/dsl/HaveWord;
  #27 = Utf8               org/scalatest/matchers/dsl/HaveWord
  #28 = Class              #27            // org/scalatest/matchers/dsl/HaveWord
  #29 = Utf8               (J)Lorg/scalatest/matchers/dsl/MatcherFactory1;
  #30 = NameAndType        #11:#29        // length:(J)Lorg/scalatest/matchers/dsl/MatcherFactory1;
  #31 = Methodref          #28.#30        // org/scalatest/matchers/dsl/HaveWord.length:(J)Lorg/scalatest/matchers/dsl/MatcherFactory1;
  #32 = Utf8               and
  #33 = Utf8               (Lorg/scalatest/matchers/dsl/MatcherFactory1;)Lorg/scalatest/matchers/dsl/MatcherFactory9;
  #34 = NameAndType        #32:#33        // and:(Lorg/scalatest/matchers/dsl/MatcherFactory1;)Lorg/scalatest/matchers/dsl/MatcherFactory9;
  #35 = Methodref          #7.#34         // org/scalatest/matchers/dsl/MatcherFactory8.and:(Lorg/scalatest/matchers/dsl/MatcherFactory1;)Lorg/scalatest/matchers/dsl/MatcherFactory9;
  #36 = Utf8               this
  #37 = Utf8               Lorg/scalatest/matchers/dsl/MatcherFactory8$AndHaveWord;
  #38 = Utf8               J
  #39 = Utf8               size
  #40 = Utf8               (J)Lorg/scalatest/matchers/dsl/MatcherFactory9<TSC;TTC1;TTC2;TTC3;TTC4;TTC5;TTC6;TTC7;TTC8;Lorg/scalatest/enablers/Size;>;
  #41 = Utf8               expectedSize
  #42 = NameAndType        #39:#29        // size:(J)Lorg/scalatest/matchers/dsl/MatcherFactory1;
  #43 = Methodref          #28.#42        // org/scalatest/matchers/dsl/HaveWord.size:(J)Lorg/scalatest/matchers/dsl/MatcherFactory1;
  #44 = Utf8               message
  #45 = Utf8               (Ljava/lang/String;)Lorg/scalatest/matchers/dsl/MatcherFactory9;
  #46 = Utf8               (Ljava/lang/String;)Lorg/scalatest/matchers/dsl/MatcherFactory9<TSC;TTC1;TTC2;TTC3;TTC4;TTC5;TTC6;TTC7;TTC8;Lorg/scalatest/enablers/Messaging;>;
  #47 = Utf8               expectedMessage
  #48 = Utf8               (Ljava/lang/String;)Lorg/scalatest/matchers/dsl/MatcherFactory1;
  #49 = NameAndType        #44:#48        // message:(Ljava/lang/String;)Lorg/scalatest/matchers/dsl/MatcherFactory1;
  #50 = Methodref          #28.#49        // org/scalatest/matchers/dsl/HaveWord.message:(Ljava/lang/String;)Lorg/scalatest/matchers/dsl/MatcherFactory1;
  #51 = Utf8               Ljava/lang/String;
  #52 = Utf8               <init>
  #53 = Utf8               (Lorg/scalatest/matchers/dsl/MatcherFactory8;)V
  #54 = Utf8               ()V
  #55 = NameAndType        #52:#54        // "<init>":()V
  #56 = Methodref          #4.#55         // java/lang/Object."<init>":()V
  #57 = Utf8               Code
  #58 = Utf8               LineNumberTable
  #59 = Utf8               LocalVariableTable
  #60 = Utf8               Signature
  #61 = Utf8               MethodParameters
  #62 = Utf8               StackMapTable
  #63 = Utf8               InnerClasses
  #64 = Utf8               SourceFile
  #65 = Utf8               ScalaInlineInfo
  #66 = Utf8               Scala
{
  private final org.scalatest.matchers.dsl.MatcherFactory8 $outer;
    descriptor: Lorg/scalatest/matchers/dsl/MatcherFactory8;
    flags: (0x1012) ACC_PRIVATE, ACC_FINAL, ACC_SYNTHETIC

  public org.scalatest.matchers.dsl.MatcherFactory9<SC, TC1, TC2, TC3, TC4, TC5, TC6, TC7, TC8, org.scalatest.enablers.Length> length(long);
    descriptor: (J)Lorg/scalatest/matchers/dsl/MatcherFactory9;
    flags: (0x0001) ACC_PUBLIC
    Code:
      stack=4, locals=3, args_size=2
         0: aload_0
         1: getfield      #16                 // Field $outer:Lorg/scalatest/matchers/dsl/MatcherFactory8;
         4: getstatic     #22                 // Field org/scalatest/matchers/dsl/MatcherWords$.MODULE$:Lorg/scalatest/matchers/dsl/MatcherWords$;
         7: invokevirtual #26                 // Method org/scalatest/matchers/dsl/MatcherWords$.have:()Lorg/scalatest/matchers/dsl/HaveWord;
        10: lload_1
        11: invokevirtual #31                 // Method org/scalatest/matchers/dsl/HaveWord.length:(J)Lorg/scalatest/matchers/dsl/MatcherFactory1;
        14: invokevirtual #35                 // Method org/scalatest/matchers/dsl/MatcherFactory8.and:(Lorg/scalatest/matchers/dsl/MatcherFactory1;)Lorg/scalatest/matchers/dsl/MatcherFactory9;
        17: areturn
      LineNumberTable:
        line 220: 0
      LocalVariableTable:
        Start  Length  Slot  Name   Signature
            0      18     0  this   Lorg/scalatest/matchers/dsl/MatcherFactory8$AndHaveWord;
            0      18     1 expectedLength   J
    Signature: #13                          // (J)Lorg/scalatest/matchers/dsl/MatcherFactory9<TSC;TTC1;TTC2;TTC3;TTC4;TTC5;TTC6;TTC7;TTC8;Lorg/scalatest/enablers/Length;>;
    MethodParameters:
      Name                           Flags
      expectedLength                 final

  public org.scalatest.matchers.dsl.MatcherFactory9<SC, TC1, TC2, TC3, TC4, TC5, TC6, TC7, TC8, org.scalatest.enablers.Size> size(long);
    descriptor: (J)Lorg/scalatest/matchers/dsl/MatcherFactory9;
    flags: (0x0001) ACC_PUBLIC
    Code:
      stack=4, locals=3, args_size=2
         0: aload_0
         1: getfield      #16                 // Field $outer:Lorg/scalatest/matchers/dsl/MatcherFactory8;
         4: getstatic     #22                 // Field org/scalatest/matchers/dsl/MatcherWords$.MODULE$:Lorg/scalatest/matchers/dsl/MatcherWords$;
         7: invokevirtual #26                 // Method org/scalatest/matchers/dsl/MatcherWords$.have:()Lorg/scalatest/matchers/dsl/HaveWord;
        10: lload_1
        11: invokevirtual #43                 // Method org/scalatest/matchers/dsl/HaveWord.size:(J)Lorg/scalatest/matchers/dsl/MatcherFactory1;
        14: invokevirtual #35                 // Method org/scalatest/matchers/dsl/MatcherFactory8.and:(Lorg/scalatest/matchers/dsl/MatcherFactory1;)Lorg/scalatest/matchers/dsl/MatcherFactory9;
        17: areturn
      LineNumberTable:
        line 232: 0
      LocalVariableTable:
        Start  Length  Slot  Name   Signature
            0      18     0  this   Lorg/scalatest/matchers/dsl/MatcherFactory8$AndHaveWord;
            0      18     1 expectedSize   J
    Signature: #40                          // (J)Lorg/scalatest/matchers/dsl/MatcherFactory9<TSC;TTC1;TTC2;TTC3;TTC4;TTC5;TTC6;TTC7;TTC8;Lorg/scalatest/enablers/Size;>;
    MethodParameters:
      Name                           Flags
      expectedSize                   final

  public org.scalatest.matchers.dsl.MatcherFactory9<SC, TC1, TC2, TC3, TC4, TC5, TC6, TC7, TC8, org.scalatest.enablers.Messaging> message(java.lang.String);
    descriptor: (Ljava/lang/String;)Lorg/scalatest/matchers/dsl/MatcherFactory9;
    flags: (0x0001) ACC_PUBLIC
    Code:
      stack=3, locals=2, args_size=2
         0: aload_0
         1: getfield      #16                 // Field $outer:Lorg/scalatest/matchers/dsl/MatcherFactory8;
         4: getstatic     #22                 // Field org/scalatest/matchers/dsl/MatcherWords$.MODULE$:Lorg/scalatest/matchers/dsl/MatcherWords$;
         7: invokevirtual #26                 // Method org/scalatest/matchers/dsl/MatcherWords$.have:()Lorg/scalatest/matchers/dsl/HaveWord;
        10: aload_1
        11: invokevirtual #50                 // Method org/scalatest/matchers/dsl/HaveWord.message:(Ljava/lang/String;)Lorg/scalatest/matchers/dsl/MatcherFactory1;
        14: invokevirtual #35                 // Method org/scalatest/matchers/dsl/MatcherFactory8.and:(Lorg/scalatest/matchers/dsl/MatcherFactory1;)Lorg/scalatest/matchers/dsl/MatcherFactory9;
        17: areturn
      LineNumberTable:
        line 242: 0
      LocalVariableTable:
        Start  Length  Slot  Name   Signature
            0      18     0  this   Lorg/scalatest/matchers/dsl/MatcherFactory8$AndHaveWord;
            0      18     1 expectedMessage   Ljava/lang/String;
    Signature: #46                          // (Ljava/lang/String;)Lorg/scalatest/matchers/dsl/MatcherFactory9<TSC;TTC1;TTC2;TTC3;TTC4;TTC5;TTC6;TTC7;TTC8;Lorg/scalatest/enablers/Messaging;>;
    MethodParameters:
      Name                           Flags
      expectedMessage                final

  public org.scalatest.matchers.dsl.MatcherFactory8$AndHaveWord(org.scalatest.matchers.dsl.MatcherFactory8);
    descriptor: (Lorg/scalatest/matchers/dsl/MatcherFactory8;)V
    flags: (0x0001) ACC_PUBLIC
    Code:
      stack=2, locals=2, args_size=2
         0: aload_1
         1: ifnonnull     6
         4: aconst_null
         5: athrow
         6: aload_0
         7: aload_1
         8: putfield      #16                 // Field $outer:Lorg/scalatest/matchers/dsl/MatcherFactory8;
        11: aload_0
        12: invokespecial #56                 // Method java/lang/Object."<init>":()V
        15: return
      StackMapTable: number_of_entries = 1
        frame_type = 6 /* same */
      LineNumberTable:
        line 210: 0
        line 253: 11
        line 210: 15
      LocalVariableTable:
        Start  Length  Slot  Name   Signature
            0      16     0  this   Lorg/scalatest/matchers/dsl/MatcherFactory8$AndHaveWord;
            0      16     1 $outer   Lorg/scalatest/matchers/dsl/MatcherFactory8;
    MethodParameters:
      Name                           Flags
      $outer                         final synthetic
}
InnerClasses:
  public final #8= #2 of #7;              // AndHaveWord=class org/scalatest/matchers/dsl/MatcherFactory8$AndHaveWord of class org/scalatest/matchers/dsl/MatcherFactory8
SourceFile: "MatcherFactory8.scala"
  ScalaInlineInfo: length = 0x18 (unknown attribute)
   01 01 00 04 00 34 00 35 01 00 0B 00 0C 01 00 2C
   00 2D 01 00 27 00 0C 01
  Scala: length = 0x0 (unknown attribute)

