Classfile /Users/mw/Projects/slang-braindump/.jar/jar11/assemble/slang-braindump/assemble/content/org/scalatest/matchers/dsl/PleaseUseNoExceptionShouldSyntaxInstead.class
  Last modified May 29, 2022; size 718 bytes
  SHA-256 checksum 99d4d63fa30c19b496a5411fb79ece7cb17e38d917dfeacb6158e01b95127143
  Compiled from "PleaseUseNoExceptionShouldSyntaxInstead.scala"
public final class org.scalatest.matchers.dsl.PleaseUseNoExceptionShouldSyntaxInstead
  minor version: 0
  major version: 52
  flags: (0x0031) ACC_PUBLIC, ACC_FINAL, ACC_SUPER
  this_class: #2                          // org/scalatest/matchers/dsl/PleaseUseNoExceptionShouldSyntaxInstead
  super_class: #4                         // java/lang/Object
  interfaces: 0, fields: 0, methods: 1, attributes: 4
Constant pool:
   #1 = Utf8               org/scalatest/matchers/dsl/PleaseUseNoExceptionShouldSyntaxInstead
   #2 = Class              #1             // org/scalatest/matchers/dsl/PleaseUseNoExceptionShouldSyntaxInstead
   #3 = Utf8               java/lang/Object
   #4 = Class              #3             // java/lang/Object
   #5 = Utf8               PleaseUseNoExceptionShouldSyntaxInstead.scala
   #6 = Utf8               Lscala/reflect/ScalaSignature;
   #7 = Utf8               bytes
   #8 = Utf8               \u0006\u0005]1AAA\u0002\u0003\u0019!)1\u0003\u0001C\u0001)\t9\u0003\u000b\\3bg\u0016,6/\u001a(p\u000bb\u001cW\r\u001d;j_:\u001c\u0006n\\;mINKh\u000e^1y\u0013:\u001cH/Z1e\u0015\t!Q!A\u0002eg2T!AB\u0004\u0002\u00115\fGo\u00195feNT!\u0001C\u0005\u0002\u0013M\u001c\u0017\r\\1uKN$(\"\u0001\u0006\u0002\u0007=\u0014xm\u0001\u0001\u0014\u0005\u0001i\u0001C\u0001\b\u0012\u001b\u0005y!\"\u0001\t\u0002\u000bM\u001c\u0017\r\\1\n\u0005Iy!AB!osJ+g-\u0001\u0004=S:LGO\u0010\u000b\u0002+A\u0011a\u0003A\u0007\u0002\u0007\u0001
   #9 = Utf8               <init>
  #10 = Utf8               ()V
  #11 = NameAndType        #9:#10         // "<init>":()V
  #12 = Methodref          #4.#11         // java/lang/Object."<init>":()V
  #13 = Utf8               this
  #14 = Utf8               Lorg/scalatest/matchers/dsl/PleaseUseNoExceptionShouldSyntaxInstead;
  #15 = Utf8               Code
  #16 = Utf8               LineNumberTable
  #17 = Utf8               LocalVariableTable
  #18 = Utf8               SourceFile
  #19 = Utf8               RuntimeVisibleAnnotations
  #20 = Utf8               ScalaInlineInfo
  #21 = Utf8               ScalaSig
{
  public org.scalatest.matchers.dsl.PleaseUseNoExceptionShouldSyntaxInstead();
    descriptor: ()V
    flags: (0x0001) ACC_PUBLIC
    Code:
      stack=1, locals=1, args_size=1
         0: aload_0
         1: invokespecial #12                 // Method java/lang/Object."<init>":()V
         4: return
      LineNumberTable:
        line 18: 0
      LocalVariableTable:
        Start  Length  Slot  Name   Signature
            0       5     0  this   Lorg/scalatest/matchers/dsl/PleaseUseNoExceptionShouldSyntaxInstead;
}
SourceFile: "PleaseUseNoExceptionShouldSyntaxInstead.scala"
RuntimeVisibleAnnotations:
  0: #6(#7=s#8)
    scala.reflect.ScalaSignature(
      bytes="\u0006\u0005]1AAA\u0002\u0003\u0019!)1\u0003\u0001C\u0001)\t9\u0003\u000b\\3bg\u0016,6/\u001a(p\u000bb\u001cW\r\u001d;j_:\u001c\u0006n\\;mINKh\u000e^1y\u0013:\u001cH/Z1e\u0015\t!Q!A\u0002eg2T!AB\u0004\u0002\u00115\fGo\u00195feNT!\u0001C\u0005\u0002\u0013M\u001c\u0017\r\\1uKN$(\"\u0001\u0006\u0002\u0007=\u0014xm\u0001\u0001\u0014\u0005\u0001i\u0001C\u0001\b\u0012\u001b\u0005y!\"\u0001\t\u0002\u000bM\u001c\u0017\r\\1\n\u0005Iy!AB!osJ+g-\u0001\u0004=S:LGO\u0010\u000b\u0002+A\u0011a\u0003A\u0007\u0002\u0007\u0001"
    )
  ScalaInlineInfo: length = 0x9 (unknown attribute)
   01 01 00 01 00 09 00 0A 01
  ScalaSig: length = 0x3 (unknown attribute)
   05 02 00
