Classfile /Users/mw/Projects/slang-braindump/.jar/jar11/assemble/slang-braindump/assemble/content/org/scalatest/matchers/dsl/ResultOfLengthWordApplication.class
  Last modified May 29, 2022; size 2666 bytes
  SHA-256 checksum a236a809ce95b0ca969d62724b71e60452f9cbe94f56fd818876116d321671ad
  Compiled from "ResultOfLengthWordApplication.scala"
public final class org.scalatest.matchers.dsl.ResultOfLengthWordApplication
  minor version: 0
  major version: 52
  flags: (0x0031) ACC_PUBLIC, ACC_FINAL, ACC_SUPER
  this_class: #2                          // org/scalatest/matchers/dsl/ResultOfLengthWordApplication
  super_class: #4                         // java/lang/Object
  interfaces: 0, fields: 1, methods: 4, attributes: 5
Constant pool:
   #1 = Utf8               org/scalatest/matchers/dsl/ResultOfLengthWordApplication
   #2 = Class              #1             // org/scalatest/matchers/dsl/ResultOfLengthWordApplication
   #3 = Utf8               java/lang/Object
   #4 = Class              #3             // java/lang/Object
   #5 = Utf8               ResultOfLengthWordApplication.scala
   #6 = Utf8               Lscala/reflect/ScalaSignature;
   #7 = Utf8               bytes
   #8 = Utf8               \u0006\u0005=3AAB\u0004\u0003!!Aq\u0003\u0001BC\u0002\u0013\u0005\u0001\u0004\u0003\u0005\u001d\u0001\t\u0005\t\u0015!\u0003\u001a\u0011\u0015i\u0002\u0001\"\u0001\u001f\u0011\u0015\u0011\u0003\u0001\"\u0001$\u0011\u0015\u0011\u0005\u0001\"\u0011D\u0005u\u0011Vm];mi>3G*\u001a8hi\"<vN\u001d3BaBd\u0017nY1uS>t\'B\u0001\u0005\n\u0003\r!7\u000f\u001c\u0006\u0003\u0015-\t\u0001\"\\1uG\",\'o\u001d\u0006\u0003\u00195\t\u0011b]2bY\u0006$Xm\u001d;\u000b\u00039\t1a\u001c:h\u0007\u0001\u0019\"\u0001A\t\u0011\u0005I)R\"A\n\u000b\u0003Q\tQa]2bY\u0006L!AF\n\u0003\r\u0005s\u0017PU3g\u00039)\u0007\u0010]3di\u0016$G*\u001a8hi\",\u0012!\u0007\t\u0003%iI!aG\n\u0003\t1{gnZ\u0001\u0010Kb\u0004Xm\u0019;fI2+gn\u001a;iA\u00051A(\u001b8jiz\"\"aH\u0011\u0011\u0005\u0001\u0002Q\"A\u0004\t\u000b]\u0019\u0001\u0019A\r\u0002\u000b\u0005\u0004\b\u000f\\=\u0016\u0005\u0011bCCA\u0013>)\t1S\u0007\u0005\u0003(Q)JR\"A\u0005\n\u0005%J!a\u0005%bm\u0016\u0004&o\u001c9feRLX*\u0019;dQ\u0016\u0014\bCA\u0016-\u0019\u0001!Q!\f\u0003C\u00029\u0012\u0011\u0001V\t\u0003_I\u0002\"A\u0005\u0019\n\u0005E\u001a\"a\u0002(pi\"Lgn\u001a\t\u0003%MJ!\u0001N\n\u0003\u0007\u0005s\u0017\u0010C\u00047\t\u0005\u0005\t9A\u001c\u0002\u0015\u00154\u0018\u000eZ3oG\u0016$\u0013\u0007E\u00029w)j\u0011!\u000f\u0006\u0003u-\t\u0001\"\u001a8bE2,\'o]\u0005\u0003ye\u0012a\u0001T3oORD\u0007\"\u0002 \u0005\u0001\u0004y\u0014\u0001\u0007:fgVdGo\u00144PMRK\b/Z%om>\u001c\u0017\r^5p]B\u0019\u0001\u0005\u0011\u0016\n\u0005\u0005;!\u0001\u0007*fgVdGo\u00144PMRK\b/Z%om>\u001c\u0017\r^5p]\u0006AAo\\*ue&tw\rF\u0001E!\t)EJ\u0004\u0002G\u0015B\u0011qiE\u0007\u0002\u0011*\u0011\u0011jD\u0001\u0007yI|w\u000e\u001e \n\u0005-\u001b\u0012A\u0002)sK\u0012,g-\u0003\u0002N\u001d\n11\u000b\u001e:j]\u001eT!aS\n
   #9 = Utf8               org/scalatest/matchers/dsl/ResultOfLengthWordApplication$$anon$1
  #10 = Class              #9             // org/scalatest/matchers/dsl/ResultOfLengthWordApplication$$anon$1
  #11 = Utf8               expectedLength
  #12 = Utf8               J
  #13 = Utf8               ()J
  #14 = NameAndType        #11:#12        // expectedLength:J
  #15 = Fieldref           #2.#14         // org/scalatest/matchers/dsl/ResultOfLengthWordApplication.expectedLength:J
  #16 = Utf8               this
  #17 = Utf8               Lorg/scalatest/matchers/dsl/ResultOfLengthWordApplication;
  #18 = Utf8               apply
  #19 = Utf8               (Lorg/scalatest/matchers/dsl/ResultOfOfTypeInvocation;Lorg/scalatest/enablers/Length;)Lorg/scalatest/matchers/HavePropertyMatcher;
  #20 = Utf8               <T:Ljava/lang/Object;>(Lorg/scalatest/matchers/dsl/ResultOfOfTypeInvocation<TT;>;Lorg/scalatest/enablers/Length<TT;>;)Lorg/scalatest/matchers/HavePropertyMatcher<TT;Ljava/lang/Object;>;
  #21 = Utf8               resultOfOfTypeInvocation
  #22 = Utf8               evidence$1
  #23 = Utf8               <init>
  #24 = Utf8               (Lorg/scalatest/matchers/dsl/ResultOfLengthWordApplication;Lorg/scalatest/enablers/Length;)V
  #25 = NameAndType        #23:#24        // "<init>":(Lorg/scalatest/matchers/dsl/ResultOfLengthWordApplication;Lorg/scalatest/enablers/Length;)V
  #26 = Methodref          #10.#25        // org/scalatest/matchers/dsl/ResultOfLengthWordApplication$$anon$1."<init>":(Lorg/scalatest/matchers/dsl/ResultOfLengthWordApplication;Lorg/scalatest/enablers/Length;)V
  #27 = Utf8               Lorg/scalatest/matchers/dsl/ResultOfOfTypeInvocation;
  #28 = Utf8               Lorg/scalatest/enablers/Length;
  #29 = Utf8               toString
  #30 = Utf8               ()Ljava/lang/String;
  #31 = Utf8               java/lang/StringBuilder
  #32 = Class              #31            // java/lang/StringBuilder
  #33 = Integer            9
  #34 = Utf8               (I)V
  #35 = NameAndType        #23:#34        // "<init>":(I)V
  #36 = Methodref          #32.#35        // java/lang/StringBuilder."<init>":(I)V
  #37 = Utf8               length (
  #38 = String             #37            // length (
  #39 = Utf8               append
  #40 = Utf8               (Ljava/lang/String;)Ljava/lang/StringBuilder;
  #41 = NameAndType        #39:#40        // append:(Ljava/lang/String;)Ljava/lang/StringBuilder;
  #42 = Methodref          #32.#41        // java/lang/StringBuilder.append:(Ljava/lang/String;)Ljava/lang/StringBuilder;
  #43 = Utf8               org/scalactic/Prettifier$
  #44 = Class              #43            // org/scalactic/Prettifier$
  #45 = Utf8               MODULE$
  #46 = Utf8               Lorg/scalactic/Prettifier$;
  #47 = NameAndType        #45:#46        // MODULE$:Lorg/scalactic/Prettifier$;
  #48 = Fieldref           #44.#47        // org/scalactic/Prettifier$.MODULE$:Lorg/scalactic/Prettifier$;
  #49 = Utf8               default
  #50 = Utf8               ()Lorg/scalactic/Prettifier;
  #51 = NameAndType        #49:#50        // default:()Lorg/scalactic/Prettifier;
  #52 = Methodref          #44.#51        // org/scalactic/Prettifier$.default:()Lorg/scalactic/Prettifier;
  #53 = NameAndType        #11:#13        // expectedLength:()J
  #54 = Methodref          #2.#53         // org/scalatest/matchers/dsl/ResultOfLengthWordApplication.expectedLength:()J
  #55 = Utf8               scala/runtime/BoxesRunTime
  #56 = Class              #55            // scala/runtime/BoxesRunTime
  #57 = Utf8               boxToLong
  #58 = Utf8               (J)Ljava/lang/Long;
  #59 = NameAndType        #57:#58        // boxToLong:(J)Ljava/lang/Long;
  #60 = Methodref          #56.#59        // scala/runtime/BoxesRunTime.boxToLong:(J)Ljava/lang/Long;
  #61 = Utf8               org/scalactic/Prettifier
  #62 = Class              #61            // org/scalactic/Prettifier
  #63 = Utf8               (Ljava/lang/Object;)Ljava/lang/String;
  #64 = NameAndType        #18:#63        // apply:(Ljava/lang/Object;)Ljava/lang/String;
  #65 = InterfaceMethodref #62.#64        // org/scalactic/Prettifier.apply:(Ljava/lang/Object;)Ljava/lang/String;
  #66 = Utf8               )
  #67 = String             #66            // )
  #68 = NameAndType        #29:#30        // toString:()Ljava/lang/String;
  #69 = Methodref          #32.#68        // java/lang/StringBuilder.toString:()Ljava/lang/String;
  #70 = Utf8               (J)V
  #71 = Utf8               ()V
  #72 = NameAndType        #23:#71        // "<init>":()V
  #73 = Methodref          #4.#72         // java/lang/Object."<init>":()V
  #74 = Utf8               Code
  #75 = Utf8               LineNumberTable
  #76 = Utf8               LocalVariableTable
  #77 = Utf8               Signature
  #78 = Utf8               MethodParameters
  #79 = Utf8               InnerClasses
  #80 = Utf8               SourceFile
  #81 = Utf8               RuntimeVisibleAnnotations
  #82 = Utf8               ScalaInlineInfo
  #83 = Utf8               ScalaSig
{
  private final long expectedLength;
    descriptor: J
    flags: (0x0012) ACC_PRIVATE, ACC_FINAL

  public long expectedLength();
    descriptor: ()J
    flags: (0x0001) ACC_PUBLIC
    Code:
      stack=2, locals=1, args_size=1
         0: aload_0
         1: getfield      #15                 // Field expectedLength:J
         4: lreturn
      LineNumberTable:
        line 29: 0
      LocalVariableTable:
        Start  Length  Slot  Name   Signature
            0       5     0  this   Lorg/scalatest/matchers/dsl/ResultOfLengthWordApplication;

  public <T extends java.lang.Object> org.scalatest.matchers.HavePropertyMatcher<T, java.lang.Object> apply(org.scalatest.matchers.dsl.ResultOfOfTypeInvocation<T>, org.scalatest.enablers.Length<T>);
    descriptor: (Lorg/scalatest/matchers/dsl/ResultOfOfTypeInvocation;Lorg/scalatest/enablers/Length;)Lorg/scalatest/matchers/HavePropertyMatcher;
    flags: (0x0001) ACC_PUBLIC
    Code:
      stack=4, locals=3, args_size=3
         0: new           #10                 // class org/scalatest/matchers/dsl/ResultOfLengthWordApplication$$anon$1
         3: dup
         4: aload_0
         5: aload_2
         6: invokespecial #26                 // Method org/scalatest/matchers/dsl/ResultOfLengthWordApplication$$anon$1."<init>":(Lorg/scalatest/matchers/dsl/ResultOfLengthWordApplication;Lorg/scalatest/enablers/Length;)V
         9: areturn
      LineNumberTable:
        line 33: 0
      LocalVariableTable:
        Start  Length  Slot  Name   Signature
            0      10     0  this   Lorg/scalatest/matchers/dsl/ResultOfLengthWordApplication;
            0      10     1 resultOfOfTypeInvocation   Lorg/scalatest/matchers/dsl/ResultOfOfTypeInvocation;
            0      10     2 evidence$1   Lorg/scalatest/enablers/Length;
    Signature: #20                          // <T:Ljava/lang/Object;>(Lorg/scalatest/matchers/dsl/ResultOfOfTypeInvocation<TT;>;Lorg/scalatest/enablers/Length<TT;>;)Lorg/scalatest/matchers/HavePropertyMatcher<TT;Ljava/lang/Object;>;
    MethodParameters:
      Name                           Flags
      resultOfOfTypeInvocation       final
      evidence$1                     final

  public java.lang.String toString();
    descriptor: ()Ljava/lang/String;
    flags: (0x0001) ACC_PUBLIC
    Code:
      stack=4, locals=1, args_size=1
         0: new           #32                 // class java/lang/StringBuilder
         3: dup
         4: ldc           #33                 // int 9
         6: invokespecial #36                 // Method java/lang/StringBuilder."<init>":(I)V
         9: ldc           #38                 // String length (
        11: invokevirtual #42                 // Method java/lang/StringBuilder.append:(Ljava/lang/String;)Ljava/lang/StringBuilder;
        14: getstatic     #48                 // Field org/scalactic/Prettifier$.MODULE$:Lorg/scalactic/Prettifier$;
        17: invokevirtual #52                 // Method org/scalactic/Prettifier$.default:()Lorg/scalactic/Prettifier;
        20: aload_0
        21: invokevirtual #54                 // Method expectedLength:()J
        24: invokestatic  #60                 // Method scala/runtime/BoxesRunTime.boxToLong:(J)Ljava/lang/Long;
        27: invokeinterface #65,  2           // InterfaceMethod org/scalactic/Prettifier.apply:(Ljava/lang/Object;)Ljava/lang/String;
        32: invokevirtual #42                 // Method java/lang/StringBuilder.append:(Ljava/lang/String;)Ljava/lang/StringBuilder;
        35: ldc           #67                 // String )
        37: invokevirtual #42                 // Method java/lang/StringBuilder.append:(Ljava/lang/String;)Ljava/lang/StringBuilder;
        40: invokevirtual #69                 // Method java/lang/StringBuilder.toString:()Ljava/lang/String;
        43: areturn
      LineNumberTable:
        line 50: 0
      LocalVariableTable:
        Start  Length  Slot  Name   Signature
            0      44     0  this   Lorg/scalatest/matchers/dsl/ResultOfLengthWordApplication;

  public org.scalatest.matchers.dsl.ResultOfLengthWordApplication(long);
    descriptor: (J)V
    flags: (0x0001) ACC_PUBLIC
    Code:
      stack=3, locals=3, args_size=2
         0: aload_0
         1: lload_1
         2: putfield      #15                 // Field expectedLength:J
         5: aload_0
         6: invokespecial #73                 // Method java/lang/Object."<init>":()V
         9: return
      LineNumberTable:
        line 29: 0
        line 51: 5
        line 29: 9
      LocalVariableTable:
        Start  Length  Slot  Name   Signature
            0      10     0  this   Lorg/scalatest/matchers/dsl/ResultOfLengthWordApplication;
            0      10     1 expectedLength   J
    MethodParameters:
      Name                           Flags
      expectedLength                 final
}
InnerClasses:
  public final #10;                       // class org/scalatest/matchers/dsl/ResultOfLengthWordApplication$$anon$1
SourceFile: "ResultOfLengthWordApplication.scala"
RuntimeVisibleAnnotations:
  0: #6(#7=s#8)
    scala.reflect.ScalaSignature(
      bytes="\u0006\u0005=3AAB\u0004\u0003!!Aq\u0003\u0001BC\u0002\u0013\u0005\u0001\u0004\u0003\u0005\u001d\u0001\t\u0005\t\u0015!\u0003\u001a\u0011\u0015i\u0002\u0001\"\u0001\u001f\u0011\u0015\u0011\u0003\u0001\"\u0001$\u0011\u0015\u0011\u0005\u0001\"\u0011D\u0005u\u0011Vm];mi>3G*\u001a8hi\"<vN\u001d3BaBd\u0017nY1uS>t\'B\u0001\u0005\n\u0003\r!7\u000f\u001c\u0006\u0003\u0015-\t\u0001\"\\1uG\",\'o\u001d\u0006\u0003\u00195\t\u0011b]2bY\u0006$Xm\u001d;\u000b\u00039\t1a\u001c:h\u0007\u0001\u0019\"\u0001A\t\u0011\u0005I)R\"A\n\u000b\u0003Q\tQa]2bY\u0006L!AF\n\u0003\r\u0005s\u0017PU3g\u00039)\u0007\u0010]3di\u0016$G*\u001a8hi\",\u0012!\u0007\t\u0003%iI!aG\n\u0003\t1{gnZ\u0001\u0010Kb\u0004Xm\u0019;fI2+gn\u001a;iA\u00051A(\u001b8jiz\"\"aH\u0011\u0011\u0005\u0001\u0002Q\"A\u0004\t\u000b]\u0019\u0001\u0019A\r\u0002\u000b\u0005\u0004\b\u000f\\=\u0016\u0005\u0011bCCA\u0013>)\t1S\u0007\u0005\u0003(Q)JR\"A\u0005\n\u0005%J!a\u0005%bm\u0016\u0004&o\u001c9feRLX*\u0019;dQ\u0016\u0014\bCA\u0016-\u0019\u0001!Q!\f\u0003C\u00029\u0012\u0011\u0001V\t\u0003_I\u0002\"A\u0005\u0019\n\u0005E\u001a\"a\u0002(pi\"Lgn\u001a\t\u0003%MJ!\u0001N\n\u0003\u0007\u0005s\u0017\u0010C\u00047\t\u0005\u0005\t9A\u001c\u0002\u0015\u00154\u0018\u000eZ3oG\u0016$\u0013\u0007E\u00029w)j\u0011!\u000f\u0006\u0003u-\t\u0001\"\u001a8bE2,\'o]\u0005\u0003ye\u0012a\u0001T3oORD\u0007\"\u0002 \u0005\u0001\u0004y\u0014\u0001\u0007:fgVdGo\u00144PMRK\b/Z%om>\u001c\u0017\r^5p]B\u0019\u0001\u0005\u0011\u0016\n\u0005\u0005;!\u0001\u0007*fgVdGo\u00144PMRK\b/Z%om>\u001c\u0017\r^5p]\u0006AAo\\*ue&tw\rF\u0001E!\t)EJ\u0004\u0002G\u0015B\u0011qiE\u0007\u0002\u0011*\u0011\u0011jD\u0001\u0007yI|w\u000e\u001e \n\u0005-\u001b\u0012A\u0002)sK\u0012,g-\u0003\u0002N\u001d\n11\u000b\u001e:j]\u001eT!aS\n"
    )
  ScalaInlineInfo: length = 0x18 (unknown attribute)
   01 01 00 04 00 17 00 46 01 00 12 00 13 01 00 0B
   00 0D 01 00 1D 00 1E 01
  ScalaSig: length = 0x3 (unknown attribute)
   05 02 00
