Classfile /Users/mw/Projects/slang-braindump/.jar/jar11/assemble/slang-braindump/assemble/content/org/scalatest/matchers/dsl/ResultOfThrownByApplication.class
  Last modified May 29, 2022; size 1333 bytes
  SHA-256 checksum 8fdba5e4938ddb0a3faf523ef0870f3a5870b3723acb76d58a73e18d6b2e34ca
  Compiled from "ResultOfThrownByApplication.scala"
public final class org.scalatest.matchers.dsl.ResultOfThrownByApplication
  minor version: 0
  major version: 52
  flags: (0x0031) ACC_PUBLIC, ACC_FINAL, ACC_SUPER
  this_class: #2                          // org/scalatest/matchers/dsl/ResultOfThrownByApplication
  super_class: #4                         // java/lang/Object
  interfaces: 0, fields: 1, methods: 3, attributes: 4
Constant pool:
   #1 = Utf8               org/scalatest/matchers/dsl/ResultOfThrownByApplication
   #2 = Class              #1             // org/scalatest/matchers/dsl/ResultOfThrownByApplication
   #3 = Utf8               java/lang/Object
   #4 = Class              #3             // java/lang/Object
   #5 = Utf8               ResultOfThrownByApplication.scala
   #6 = Utf8               Lscala/reflect/ScalaSignature;
   #7 = Utf8               bytes
   #8 = Utf8               \u0006\u0005E2A!\u0002\u0004\u0003\u001f!Aa\u0003\u0001B\u0001J\u0003%q\u0003C\u0003\u001e\u0001\u0011\u0005a\u0004C\u0003#\u0001\u0011\u00051\u0005C\u0003%\u0001\u0011\u0005SEA\u000eSKN,H\u000e^(g)\"\u0014xn\u001e8Cs\u0006\u0003\b\u000f\\5dCRLwN\u001c\u0006\u0003\u000f!\t1\u0001Z:m\u0015\tI!\"\u0001\u0005nCR\u001c\u0007.\u001a:t\u0015\tYA\"A\u0005tG\u0006d\u0017\r^3ti*\tQ\"A\u0002pe\u001e\u001c\u0001a\u0005\u0002\u0001!A\u0011\u0011\u0003F\u0007\u0002%)\t1#A\u0003tG\u0006d\u0017-\u0003\u0002\u0016%\t1\u0011I\\=SK\u001a\f1AZ;o!\r\t\u0002DG\u0005\u00033I\u0011\u0001\u0002\u00102z]\u0006lWM\u0010\t\u0003#mI!\u0001\b\n\u0003\tUs\u0017\u000e^\u0001\u0007y%t\u0017\u000e\u001e \u0015\u0005}\t\u0003C\u0001\u0011\u0001\u001b\u00051\u0001B\u0002\f\u0003\t\u0003\u0007q#A\u0004fq\u0016\u001cW\u000f^3\u0015\u0003i\t\u0001\u0002^8TiJLgn\u001a\u000b\u0002MA\u0011qE\f\b\u0003Q1\u0002\"!\u000b\n\u000e\u0003)R!a\u000b\b\u0002\rq\u0012xn\u001c;?\u0013\ti##\u0001\u0004Qe\u0016$WMZ\u0005\u0003_A\u0012aa\u0015;sS:<\'BA\u0017\u0013\u0001
   #9 = Utf8               fun
  #10 = Utf8               Lscala/Function0;
  #11 = Utf8               Lscala/Function0<Lscala/runtime/BoxedUnit;>;
  #12 = Utf8               execute
  #13 = Utf8               ()V
  #14 = NameAndType        #9:#10         // fun:Lscala/Function0;
  #15 = Fieldref           #2.#14         // org/scalatest/matchers/dsl/ResultOfThrownByApplication.fun:Lscala/Function0;
  #16 = Utf8               scala/Function0
  #17 = Class              #16            // scala/Function0
  #18 = Utf8               apply$mcV$sp
  #19 = NameAndType        #18:#13        // apply$mcV$sp:()V
  #20 = InterfaceMethodref #17.#19        // scala/Function0.apply$mcV$sp:()V
  #21 = Utf8               this
  #22 = Utf8               Lorg/scalatest/matchers/dsl/ResultOfThrownByApplication;
  #23 = Utf8               toString
  #24 = Utf8               ()Ljava/lang/String;
  #25 = Utf8               thrownBy { ... }
  #26 = String             #25            // thrownBy { ... }
  #27 = Utf8               <init>
  #28 = Utf8               (Lscala/Function0;)V
  #29 = Utf8               (Lscala/Function0<Lscala/runtime/BoxedUnit;>;)V
  #30 = NameAndType        #27:#13        // "<init>":()V
  #31 = Methodref          #4.#30         // java/lang/Object."<init>":()V
  #32 = Utf8               Signature
  #33 = Utf8               Code
  #34 = Utf8               LineNumberTable
  #35 = Utf8               LocalVariableTable
  #36 = Utf8               MethodParameters
  #37 = Utf8               SourceFile
  #38 = Utf8               RuntimeVisibleAnnotations
  #39 = Utf8               ScalaInlineInfo
  #40 = Utf8               ScalaSig
{
  private final scala.Function0<scala.runtime.BoxedUnit> fun;
    descriptor: Lscala/Function0;
    flags: (0x0012) ACC_PRIVATE, ACC_FINAL
    Signature: #11                          // Lscala/Function0<Lscala/runtime/BoxedUnit;>;

  public void execute();
    descriptor: ()V
    flags: (0x0001) ACC_PUBLIC
    Code:
      stack=1, locals=1, args_size=1
         0: aload_0
         1: getfield      #15                 // Field fun:Lscala/Function0;
         4: invokeinterface #20,  1           // InterfaceMethod scala/Function0.apply$mcV$sp:()V
         9: return
      LineNumberTable:
        line 30: 0
      LocalVariableTable:
        Start  Length  Slot  Name   Signature
            0      10     0  this   Lorg/scalatest/matchers/dsl/ResultOfThrownByApplication;

  public java.lang.String toString();
    descriptor: ()Ljava/lang/String;
    flags: (0x0001) ACC_PUBLIC
    Code:
      stack=1, locals=1, args_size=1
         0: ldc           #26                 // String thrownBy { ... }
         2: areturn
      LineNumberTable:
        line 32: 0
      LocalVariableTable:
        Start  Length  Slot  Name   Signature
            0       3     0  this   Lorg/scalatest/matchers/dsl/ResultOfThrownByApplication;

  public org.scalatest.matchers.dsl.ResultOfThrownByApplication(scala.Function0<scala.runtime.BoxedUnit>);
    descriptor: (Lscala/Function0;)V
    flags: (0x0001) ACC_PUBLIC
    Code:
      stack=2, locals=2, args_size=2
         0: aload_0
         1: aload_1
         2: putfield      #15                 // Field fun:Lscala/Function0;
         5: aload_0
         6: invokespecial #31                 // Method java/lang/Object."<init>":()V
         9: return
      LineNumberTable:
        line 25: 0
        line 33: 5
        line 25: 9
      LocalVariableTable:
        Start  Length  Slot  Name   Signature
            0      10     0  this   Lorg/scalatest/matchers/dsl/ResultOfThrownByApplication;
            0      10     1   fun   Lscala/Function0;
    Signature: #29                          // (Lscala/Function0<Lscala/runtime/BoxedUnit;>;)V
    MethodParameters:
      Name                           Flags
      fun                            final
}
SourceFile: "ResultOfThrownByApplication.scala"
RuntimeVisibleAnnotations:
  0: #6(#7=s#8)
    scala.reflect.ScalaSignature(
      bytes="\u0006\u0005E2A!\u0002\u0004\u0003\u001f!Aa\u0003\u0001B\u0001J\u0003%q\u0003C\u0003\u001e\u0001\u0011\u0005a\u0004C\u0003#\u0001\u0011\u00051\u0005C\u0003%\u0001\u0011\u0005SEA\u000eSKN,H\u000e^(g)\"\u0014xn\u001e8Cs\u0006\u0003\b\u000f\\5dCRLwN\u001c\u0006\u0003\u000f!\t1\u0001Z:m\u0015\tI!\"\u0001\u0005nCR\u001c\u0007.\u001a:t\u0015\tYA\"A\u0005tG\u0006d\u0017\r^3ti*\tQ\"A\u0002pe\u001e\u001c\u0001a\u0005\u0002\u0001!A\u0011\u0011\u0003F\u0007\u0002%)\t1#A\u0003tG\u0006d\u0017-\u0003\u0002\u0016%\t1\u0011I\\=SK\u001a\f1AZ;o!\r\t\u0002DG\u0005\u00033I\u0011\u0001\u0002\u00102z]\u0006lWM\u0010\t\u0003#mI!\u0001\b\n\u0003\tUs\u0017\u000e^\u0001\u0007y%t\u0017\u000e\u001e \u0015\u0005}\t\u0003C\u0001\u0011\u0001\u001b\u00051\u0001B\u0002\f\u0003\t\u0003\u0007q#A\u0004fq\u0016\u001cW\u000f^3\u0015\u0003i\t\u0001\u0002^8TiJLgn\u001a\u000b\u0002MA\u0011qE\f\b\u0003Q1\u0002\"!\u000b\n\u000e\u0003)R!a\u000b\b\u0002\rq\u0012xn\u001c;?\u0013\ti##\u0001\u0004Qe\u0016$WMZ\u0005\u0003_A\u0012aa\u0015;sS:<\'BA\u0017\u0013\u0001"
    )
  ScalaInlineInfo: length = 0x13 (unknown attribute)
   01 01 00 03 00 1B 00 1C 01 00 0C 00 0D 01 00 17
   00 18 01
  ScalaSig: length = 0x3 (unknown attribute)
   05 02 00
