Classfile /Users/mw/Projects/slang-braindump/.jar/jar11/assemble/slang-braindump/assemble/content/org/scalatest/matchers/dsl/ResultOfMessageWordApplication.class
  Last modified May 29, 2022; size 2625 bytes
  SHA-256 checksum 61ac1975682eaf8fa0c431a18e070072e08cc32175cbf64fb9f19c58a74da6b1
  Compiled from "ResultOfMessageWordApplication.scala"
public final class org.scalatest.matchers.dsl.ResultOfMessageWordApplication
  minor version: 0
  major version: 52
  flags: (0x0031) ACC_PUBLIC, ACC_FINAL, ACC_SUPER
  this_class: #2                          // org/scalatest/matchers/dsl/ResultOfMessageWordApplication
  super_class: #4                         // java/lang/Object
  interfaces: 0, fields: 1, methods: 4, attributes: 5
Constant pool:
   #1 = Utf8               org/scalatest/matchers/dsl/ResultOfMessageWordApplication
   #2 = Class              #1             // org/scalatest/matchers/dsl/ResultOfMessageWordApplication
   #3 = Utf8               java/lang/Object
   #4 = Class              #3             // java/lang/Object
   #5 = Utf8               ResultOfMessageWordApplication.scala
   #6 = Utf8               Lscala/reflect/ScalaSignature;
   #7 = Utf8               bytes
   #8 = Utf8               \u0006\u000513AAB\u0004\u0003!!Aq\u0003\u0001BC\u0002\u0013\u0005\u0001\u0004\u0003\u0005%\u0001\t\u0005\t\u0015!\u0003\u001a\u0011\u0015)\u0003\u0001\"\u0001\'\u0011\u0015Q\u0003\u0001\"\u0001,\u0011\u0015Q\u0005\u0001\"\u0011L\u0005y\u0011Vm];mi>3W*Z:tC\u001e,wk\u001c:e\u0003B\u0004H.[2bi&|gN\u0003\u0002\t\u0013\u0005\u0019Am\u001d7\u000b\u0005)Y\u0011\u0001C7bi\u000eDWM]:\u000b\u00051i\u0011!C:dC2\fG/Z:u\u0015\u0005q\u0011aA8sO\u000e\u00011C\u0001\u0001\u0012!\t\u0011R#D\u0001\u0014\u0015\u0005!\u0012!B:dC2\f\u0017B\u0001\f\u0014\u0005\u0019\te.\u001f*fM\u0006yQ\r\u001f9fGR,G-T3tg\u0006<W-F\u0001\u001a!\tQ\u0012E\u0004\u0002\u001c?A\u0011AdE\u0007\u0002;)\u0011adD\u0001\u0007yI|w\u000e\u001e \n\u0005\u0001\u001a\u0012A\u0002)sK\u0012,g-\u0003\u0002#G\t11\u000b\u001e:j]\u001eT!\u0001I\n\u0002!\u0015D\b/Z2uK\u0012lUm]:bO\u0016\u0004\u0013A\u0002\u001fj]&$h\b\u0006\u0002(SA\u0011\u0001\u0006A\u0007\u0002\u000f!)qc\u0001a\u00013\u0005)\u0011\r\u001d9msV\u0011A\u0006\u000e\u000b\u0003[\u0015#\"AL\u001f\u0011\t=\u0002$\'G\u0007\u0002\u0013%\u0011\u0011\'\u0003\u0002\u0014\u0011\u00064X\r\u0015:pa\u0016\u0014H/_\'bi\u000eDWM\u001d\t\u0003gQb\u0001\u0001B\u00036\t\t\u0007aGA\u0001U#\t9$\b\u0005\u0002\u0013q%\u0011\u0011h\u0005\u0002\b\u001d>$\b.\u001b8h!\t\u00112(\u0003\u0002=\'\t\u0019\u0011I\\=\t\u000fy\"\u0011\u0011!a\u0002\u007f\u0005QQM^5eK:\u001cW\rJ\u0019\u0011\u0007\u0001\u001b%\'D\u0001B\u0015\t\u00115\"\u0001\u0005f]\u0006\u0014G.\u001a:t\u0013\t!\u0015IA\u0005NKN\u001c\u0018mZ5oO\")a\t\u0002a\u0001\u000f\u0006A\"/Z:vYR|em\u00144UsB,\u0017J\u001c<pG\u0006$\u0018n\u001c8\u0011\u0007!B%\'\u0003\u0002J\u000f\tA\"+Z:vYR|em\u00144UsB,\u0017J\u001c<pG\u0006$\u0018n\u001c8\u0002\u0011Q|7\u000b\u001e:j]\u001e$\u0012!\u0007
   #9 = Utf8               org/scalatest/matchers/dsl/ResultOfMessageWordApplication$$anon$1
  #10 = Class              #9             // org/scalatest/matchers/dsl/ResultOfMessageWordApplication$$anon$1
  #11 = Utf8               expectedMessage
  #12 = Utf8               Ljava/lang/String;
  #13 = Utf8               ()Ljava/lang/String;
  #14 = NameAndType        #11:#12        // expectedMessage:Ljava/lang/String;
  #15 = Fieldref           #2.#14         // org/scalatest/matchers/dsl/ResultOfMessageWordApplication.expectedMessage:Ljava/lang/String;
  #16 = Utf8               this
  #17 = Utf8               Lorg/scalatest/matchers/dsl/ResultOfMessageWordApplication;
  #18 = Utf8               apply
  #19 = Utf8               (Lorg/scalatest/matchers/dsl/ResultOfOfTypeInvocation;Lorg/scalatest/enablers/Messaging;)Lorg/scalatest/matchers/HavePropertyMatcher;
  #20 = Utf8               <T:Ljava/lang/Object;>(Lorg/scalatest/matchers/dsl/ResultOfOfTypeInvocation<TT;>;Lorg/scalatest/enablers/Messaging<TT;>;)Lorg/scalatest/matchers/HavePropertyMatcher<TT;Ljava/lang/String;>;
  #21 = Utf8               resultOfOfTypeInvocation
  #22 = Utf8               evidence$1
  #23 = Utf8               <init>
  #24 = Utf8               (Lorg/scalatest/matchers/dsl/ResultOfMessageWordApplication;Lorg/scalatest/enablers/Messaging;)V
  #25 = NameAndType        #23:#24        // "<init>":(Lorg/scalatest/matchers/dsl/ResultOfMessageWordApplication;Lorg/scalatest/enablers/Messaging;)V
  #26 = Methodref          #10.#25        // org/scalatest/matchers/dsl/ResultOfMessageWordApplication$$anon$1."<init>":(Lorg/scalatest/matchers/dsl/ResultOfMessageWordApplication;Lorg/scalatest/enablers/Messaging;)V
  #27 = Utf8               Lorg/scalatest/matchers/dsl/ResultOfOfTypeInvocation;
  #28 = Utf8               Lorg/scalatest/enablers/Messaging;
  #29 = Utf8               toString
  #30 = Utf8               java/lang/StringBuilder
  #31 = Class              #30            // java/lang/StringBuilder
  #32 = Integer            10
  #33 = Utf8               (I)V
  #34 = NameAndType        #23:#33        // "<init>":(I)V
  #35 = Methodref          #31.#34        // java/lang/StringBuilder."<init>":(I)V
  #36 = Utf8               message (
  #37 = String             #36            // message (
  #38 = Utf8               append
  #39 = Utf8               (Ljava/lang/String;)Ljava/lang/StringBuilder;
  #40 = NameAndType        #38:#39        // append:(Ljava/lang/String;)Ljava/lang/StringBuilder;
  #41 = Methodref          #31.#40        // java/lang/StringBuilder.append:(Ljava/lang/String;)Ljava/lang/StringBuilder;
  #42 = Utf8               org/scalactic/Prettifier$
  #43 = Class              #42            // org/scalactic/Prettifier$
  #44 = Utf8               MODULE$
  #45 = Utf8               Lorg/scalactic/Prettifier$;
  #46 = NameAndType        #44:#45        // MODULE$:Lorg/scalactic/Prettifier$;
  #47 = Fieldref           #43.#46        // org/scalactic/Prettifier$.MODULE$:Lorg/scalactic/Prettifier$;
  #48 = Utf8               default
  #49 = Utf8               ()Lorg/scalactic/Prettifier;
  #50 = NameAndType        #48:#49        // default:()Lorg/scalactic/Prettifier;
  #51 = Methodref          #43.#50        // org/scalactic/Prettifier$.default:()Lorg/scalactic/Prettifier;
  #52 = NameAndType        #11:#13        // expectedMessage:()Ljava/lang/String;
  #53 = Methodref          #2.#52         // org/scalatest/matchers/dsl/ResultOfMessageWordApplication.expectedMessage:()Ljava/lang/String;
  #54 = Utf8               org/scalactic/Prettifier
  #55 = Class              #54            // org/scalactic/Prettifier
  #56 = Utf8               (Ljava/lang/Object;)Ljava/lang/String;
  #57 = NameAndType        #18:#56        // apply:(Ljava/lang/Object;)Ljava/lang/String;
  #58 = InterfaceMethodref #55.#57        // org/scalactic/Prettifier.apply:(Ljava/lang/Object;)Ljava/lang/String;
  #59 = Utf8               )
  #60 = String             #59            // )
  #61 = NameAndType        #29:#13        // toString:()Ljava/lang/String;
  #62 = Methodref          #31.#61        // java/lang/StringBuilder.toString:()Ljava/lang/String;
  #63 = Utf8               (Ljava/lang/String;)V
  #64 = Utf8               ()V
  #65 = NameAndType        #23:#64        // "<init>":()V
  #66 = Methodref          #4.#65         // java/lang/Object."<init>":()V
  #67 = Utf8               Code
  #68 = Utf8               LineNumberTable
  #69 = Utf8               LocalVariableTable
  #70 = Utf8               Signature
  #71 = Utf8               MethodParameters
  #72 = Utf8               InnerClasses
  #73 = Utf8               SourceFile
  #74 = Utf8               RuntimeVisibleAnnotations
  #75 = Utf8               ScalaInlineInfo
  #76 = Utf8               ScalaSig
{
  private final java.lang.String expectedMessage;
    descriptor: Ljava/lang/String;
    flags: (0x0012) ACC_PRIVATE, ACC_FINAL

  public java.lang.String expectedMessage();
    descriptor: ()Ljava/lang/String;
    flags: (0x0001) ACC_PUBLIC
    Code:
      stack=1, locals=1, args_size=1
         0: aload_0
         1: getfield      #15                 // Field expectedMessage:Ljava/lang/String;
         4: areturn
      LineNumberTable:
        line 30: 0
      LocalVariableTable:
        Start  Length  Slot  Name   Signature
            0       5     0  this   Lorg/scalatest/matchers/dsl/ResultOfMessageWordApplication;

  public <T extends java.lang.Object> org.scalatest.matchers.HavePropertyMatcher<T, java.lang.String> apply(org.scalatest.matchers.dsl.ResultOfOfTypeInvocation<T>, org.scalatest.enablers.Messaging<T>);
    descriptor: (Lorg/scalatest/matchers/dsl/ResultOfOfTypeInvocation;Lorg/scalatest/enablers/Messaging;)Lorg/scalatest/matchers/HavePropertyMatcher;
    flags: (0x0001) ACC_PUBLIC
    Code:
      stack=4, locals=3, args_size=3
         0: new           #10                 // class org/scalatest/matchers/dsl/ResultOfMessageWordApplication$$anon$1
         3: dup
         4: aload_0
         5: aload_2
         6: invokespecial #26                 // Method org/scalatest/matchers/dsl/ResultOfMessageWordApplication$$anon$1."<init>":(Lorg/scalatest/matchers/dsl/ResultOfMessageWordApplication;Lorg/scalatest/enablers/Messaging;)V
         9: areturn
      LineNumberTable:
        line 34: 0
      LocalVariableTable:
        Start  Length  Slot  Name   Signature
            0      10     0  this   Lorg/scalatest/matchers/dsl/ResultOfMessageWordApplication;
            0      10     1 resultOfOfTypeInvocation   Lorg/scalatest/matchers/dsl/ResultOfOfTypeInvocation;
            0      10     2 evidence$1   Lorg/scalatest/enablers/Messaging;
    Signature: #20                          // <T:Ljava/lang/Object;>(Lorg/scalatest/matchers/dsl/ResultOfOfTypeInvocation<TT;>;Lorg/scalatest/enablers/Messaging<TT;>;)Lorg/scalatest/matchers/HavePropertyMatcher<TT;Ljava/lang/String;>;
    MethodParameters:
      Name                           Flags
      resultOfOfTypeInvocation       final
      evidence$1                     final

  public java.lang.String toString();
    descriptor: ()Ljava/lang/String;
    flags: (0x0001) ACC_PUBLIC
    Code:
      stack=3, locals=1, args_size=1
         0: new           #31                 // class java/lang/StringBuilder
         3: dup
         4: ldc           #32                 // int 10
         6: invokespecial #35                 // Method java/lang/StringBuilder."<init>":(I)V
         9: ldc           #37                 // String message (
        11: invokevirtual #41                 // Method java/lang/StringBuilder.append:(Ljava/lang/String;)Ljava/lang/StringBuilder;
        14: getstatic     #47                 // Field org/scalactic/Prettifier$.MODULE$:Lorg/scalactic/Prettifier$;
        17: invokevirtual #51                 // Method org/scalactic/Prettifier$.default:()Lorg/scalactic/Prettifier;
        20: aload_0
        21: invokevirtual #53                 // Method expectedMessage:()Ljava/lang/String;
        24: invokeinterface #58,  2           // InterfaceMethod org/scalactic/Prettifier.apply:(Ljava/lang/Object;)Ljava/lang/String;
        29: invokevirtual #41                 // Method java/lang/StringBuilder.append:(Ljava/lang/String;)Ljava/lang/StringBuilder;
        32: ldc           #60                 // String )
        34: invokevirtual #41                 // Method java/lang/StringBuilder.append:(Ljava/lang/String;)Ljava/lang/StringBuilder;
        37: invokevirtual #62                 // Method java/lang/StringBuilder.toString:()Ljava/lang/String;
        40: areturn
      LineNumberTable:
        line 51: 0
      LocalVariableTable:
        Start  Length  Slot  Name   Signature
            0      41     0  this   Lorg/scalatest/matchers/dsl/ResultOfMessageWordApplication;

  public org.scalatest.matchers.dsl.ResultOfMessageWordApplication(java.lang.String);
    descriptor: (Ljava/lang/String;)V
    flags: (0x0001) ACC_PUBLIC
    Code:
      stack=2, locals=2, args_size=2
         0: aload_0
         1: aload_1
         2: putfield      #15                 // Field expectedMessage:Ljava/lang/String;
         5: aload_0
         6: invokespecial #66                 // Method java/lang/Object."<init>":()V
         9: return
      LineNumberTable:
        line 30: 0
        line 52: 5
        line 30: 9
      LocalVariableTable:
        Start  Length  Slot  Name   Signature
            0      10     0  this   Lorg/scalatest/matchers/dsl/ResultOfMessageWordApplication;
            0      10     1 expectedMessage   Ljava/lang/String;
    MethodParameters:
      Name                           Flags
      expectedMessage                final
}
InnerClasses:
  public final #10;                       // class org/scalatest/matchers/dsl/ResultOfMessageWordApplication$$anon$1
SourceFile: "ResultOfMessageWordApplication.scala"
RuntimeVisibleAnnotations:
  0: #6(#7=s#8)
    scala.reflect.ScalaSignature(
      bytes="\u0006\u000513AAB\u0004\u0003!!Aq\u0003\u0001BC\u0002\u0013\u0005\u0001\u0004\u0003\u0005%\u0001\t\u0005\t\u0015!\u0003\u001a\u0011\u0015)\u0003\u0001\"\u0001\'\u0011\u0015Q\u0003\u0001\"\u0001,\u0011\u0015Q\u0005\u0001\"\u0011L\u0005y\u0011Vm];mi>3W*Z:tC\u001e,wk\u001c:e\u0003B\u0004H.[2bi&|gN\u0003\u0002\t\u0013\u0005\u0019Am\u001d7\u000b\u0005)Y\u0011\u0001C7bi\u000eDWM]:\u000b\u00051i\u0011!C:dC2\fG/Z:u\u0015\u0005q\u0011aA8sO\u000e\u00011C\u0001\u0001\u0012!\t\u0011R#D\u0001\u0014\u0015\u0005!\u0012!B:dC2\f\u0017B\u0001\f\u0014\u0005\u0019\te.\u001f*fM\u0006yQ\r\u001f9fGR,G-T3tg\u0006<W-F\u0001\u001a!\tQ\u0012E\u0004\u0002\u001c?A\u0011AdE\u0007\u0002;)\u0011adD\u0001\u0007yI|w\u000e\u001e \n\u0005\u0001\u001a\u0012A\u0002)sK\u0012,g-\u0003\u0002#G\t11\u000b\u001e:j]\u001eT!\u0001I\n\u0002!\u0015D\b/Z2uK\u0012lUm]:bO\u0016\u0004\u0013A\u0002\u001fj]&$h\b\u0006\u0002(SA\u0011\u0001\u0006A\u0007\u0002\u000f!)qc\u0001a\u00013\u0005)\u0011\r\u001d9msV\u0011A\u0006\u000e\u000b\u0003[\u0015#\"AL\u001f\u0011\t=\u0002$\'G\u0007\u0002\u0013%\u0011\u0011\'\u0003\u0002\u0014\u0011\u00064X\r\u0015:pa\u0016\u0014H/_\'bi\u000eDWM\u001d\t\u0003gQb\u0001\u0001B\u00036\t\t\u0007aGA\u0001U#\t9$\b\u0005\u0002\u0013q%\u0011\u0011h\u0005\u0002\b\u001d>$\b.\u001b8h!\t\u00112(\u0003\u0002=\'\t\u0019\u0011I\\=\t\u000fy\"\u0011\u0011!a\u0002\u007f\u0005QQM^5eK:\u001cW\rJ\u0019\u0011\u0007\u0001\u001b%\'D\u0001B\u0015\t\u00115\"\u0001\u0005f]\u0006\u0014G.\u001a:t\u0013\t!\u0015IA\u0005NKN\u001c\u0018mZ5oO\")a\t\u0002a\u0001\u000f\u0006A\"/Z:vYR|em\u00144UsB,\u0017J\u001c<pG\u0006$\u0018n\u001c8\u0011\u0007!B%\'\u0003\u0002J\u000f\tA\"+Z:vYR|em\u00144UsB,\u0017J\u001c<pG\u0006$\u0018n\u001c8\u0002\u0011Q|7\u000b\u001e:j]\u001e$\u0012!\u0007"
    )
  ScalaInlineInfo: length = 0x18 (unknown attribute)
   01 01 00 04 00 17 00 3F 01 00 12 00 13 01 00 0B
   00 0D 01 00 1D 00 0D 01
  ScalaSig: length = 0x3 (unknown attribute)
   05 02 00
