Classfile /Users/mw/Projects/slang-braindump/.jar/jar8/assemble/slang-braindump/assemble/content/scala/concurrent/java8/FuturesConvertersImpl$CF$$anon$1.class
  Last modified May 29, 2022; size 2368 bytes
  SHA-256 checksum ccae668fa0cd0a5c1595fd344bc9cf20595c97142d45167ddc6ba17a816f9b3d
  Compiled from "FutureConvertersImpl.scala"
public final class scala.concurrent.java8.FuturesConvertersImpl$CF$$anon$1 extends java.lang.Object implements java.util.function.BiConsumer<T, java.lang.Throwable>
  minor version: 0
  major version: 52
  flags: (0x0031) ACC_PUBLIC, ACC_FINAL, ACC_SUPER
  this_class: #2                          // scala/concurrent/java8/FuturesConvertersImpl$CF$$anon$1
  super_class: #5                         // java/lang/Object
  interfaces: 1, fields: 2, methods: 4, attributes: 6
Constant pool:
   #1 = Utf8               scala/concurrent/java8/FuturesConvertersImpl$CF$$anon$1
   #2 = Class              #1             // scala/concurrent/java8/FuturesConvertersImpl$CF$$anon$1
   #3 = Utf8               Ljava/lang/Object;Ljava/util/function/BiConsumer<TT;Ljava/lang/Throwable;>;
   #4 = Utf8               java/lang/Object
   #5 = Class              #4             // java/lang/Object
   #6 = Utf8               java/util/function/BiConsumer
   #7 = Class              #6             // java/util/function/BiConsumer
   #8 = Utf8               FutureConvertersImpl.scala
   #9 = Utf8               scala/concurrent/java8/FuturesConvertersImpl$CF
  #10 = Class              #9             // scala/concurrent/java8/FuturesConvertersImpl$CF
  #11 = Utf8               exceptionally
  #12 = Utf8               (Ljava/util/function/Function;)Ljava/util/concurrent/CompletableFuture;
  #13 = NameAndType        #11:#12        // exceptionally:(Ljava/util/function/Function;)Ljava/util/concurrent/CompletableFuture;
  #14 = Utf8               scala/concurrent/java8/FuturesConvertersImpl
  #15 = Class              #14            // scala/concurrent/java8/FuturesConvertersImpl
  #16 = Utf8               CF
  #17 = Utf8               cf$1
  #18 = Utf8               Ljava/util/concurrent/CompletableFuture;
  #19 = Utf8               fn$1
  #20 = Utf8               Ljava/util/function/Function;
  #21 = Utf8               andThen
  #22 = Utf8               (Ljava/util/function/BiConsumer;)Ljava/util/function/BiConsumer;
  #23 = Utf8               (Ljava/util/function/BiConsumer<-TT;-Ljava/lang/Throwable;>;)Ljava/util/function/BiConsumer<TT;Ljava/lang/Throwable;>;
  #24 = Utf8               x$1
  #25 = NameAndType        #21:#22        // andThen:(Ljava/util/function/BiConsumer;)Ljava/util/function/BiConsumer;
  #26 = InterfaceMethodref #7.#25         // java/util/function/BiConsumer.andThen:(Ljava/util/function/BiConsumer;)Ljava/util/function/BiConsumer;
  #27 = Utf8               this
  #28 = Utf8               Lscala/concurrent/java8/FuturesConvertersImpl$CF$$anon$1;
  #29 = Utf8               Ljava/util/function/BiConsumer;
  #30 = Utf8               accept
  #31 = Utf8               (Ljava/lang/Object;Ljava/lang/Throwable;)V
  #32 = Utf8               (TT;Ljava/lang/Throwable;)V
  #33 = Utf8               t
  #34 = Utf8               e
  #35 = Utf8               java/lang/Throwable
  #36 = Class              #35            // java/lang/Throwable
  #37 = NameAndType        #17:#18        // cf$1:Ljava/util/concurrent/CompletableFuture;
  #38 = Fieldref           #2.#37         // scala/concurrent/java8/FuturesConvertersImpl$CF$$anon$1.cf$1:Ljava/util/concurrent/CompletableFuture;
  #39 = Utf8               java/util/concurrent/CompletableFuture
  #40 = Class              #39            // java/util/concurrent/CompletableFuture
  #41 = Utf8               complete
  #42 = Utf8               (Ljava/lang/Object;)Z
  #43 = NameAndType        #41:#42        // complete:(Ljava/lang/Object;)Z
  #44 = Methodref          #40.#43        // java/util/concurrent/CompletableFuture.complete:(Ljava/lang/Object;)Z
  #45 = NameAndType        #19:#20        // fn$1:Ljava/util/function/Function;
  #46 = Fieldref           #2.#45         // scala/concurrent/java8/FuturesConvertersImpl$CF$$anon$1.fn$1:Ljava/util/function/Function;
  #47 = Utf8               java/util/function/Function
  #48 = Class              #47            // java/util/function/Function
  #49 = Utf8               apply
  #50 = Utf8               (Ljava/lang/Object;)Ljava/lang/Object;
  #51 = NameAndType        #49:#50        // apply:(Ljava/lang/Object;)Ljava/lang/Object;
  #52 = InterfaceMethodref #48.#51        // java/util/function/Function.apply:(Ljava/lang/Object;)Ljava/lang/Object;
  #53 = Utf8               completeExceptionally
  #54 = Utf8               (Ljava/lang/Throwable;)Z
  #55 = NameAndType        #53:#54        // completeExceptionally:(Ljava/lang/Throwable;)Z
  #56 = Methodref          #40.#55        // java/util/concurrent/CompletableFuture.completeExceptionally:(Ljava/lang/Throwable;)Z
  #57 = Utf8               thr
  #58 = Utf8               Ljava/lang/Throwable;
  #59 = Utf8               n
  #60 = Utf8               Ljava/lang/Object;
  #61 = Utf8               (Ljava/lang/Object;Ljava/lang/Object;)V
  #62 = Utf8               x$2
  #63 = NameAndType        #30:#31        // accept:(Ljava/lang/Object;Ljava/lang/Throwable;)V
  #64 = Methodref          #2.#63         // scala/concurrent/java8/FuturesConvertersImpl$CF$$anon$1.accept:(Ljava/lang/Object;Ljava/lang/Throwable;)V
  #65 = Utf8               <init>
  #66 = Utf8               (Lscala/concurrent/java8/FuturesConvertersImpl$CF;Ljava/util/concurrent/CompletableFuture;Ljava/util/function/Function;)V
  #67 = Utf8               $outer
  #68 = Utf8               ()V
  #69 = NameAndType        #65:#68        // "<init>":()V
  #70 = Methodref          #5.#69         // java/lang/Object."<init>":()V
  #71 = Utf8               Lscala/concurrent/java8/FuturesConvertersImpl$CF;
  #72 = Utf8               Code
  #73 = Utf8               LineNumberTable
  #74 = Utf8               LocalVariableTable
  #75 = Utf8               Signature
  #76 = Utf8               MethodParameters
  #77 = Utf8               StackMapTable
  #78 = Utf8               InnerClasses
  #79 = Utf8               EnclosingMethod
  #80 = Utf8               SourceFile
  #81 = Utf8               ScalaInlineInfo
  #82 = Utf8               Scala
{
  private final java.util.concurrent.CompletableFuture cf$1;
    descriptor: Ljava/util/concurrent/CompletableFuture;
    flags: (0x0012) ACC_PRIVATE, ACC_FINAL

  private final java.util.function.Function fn$1;
    descriptor: Ljava/util/function/Function;
    flags: (0x0012) ACC_PRIVATE, ACC_FINAL

  public java.util.function.BiConsumer<T, java.lang.Throwable> andThen(java.util.function.BiConsumer<? super T, ? super java.lang.Throwable>);
    descriptor: (Ljava/util/function/BiConsumer;)Ljava/util/function/BiConsumer;
    flags: (0x0001) ACC_PUBLIC
    Code:
      stack=2, locals=2, args_size=2
         0: aload_0
         1: aload_1
         2: invokespecial #26                 // InterfaceMethod java/util/function/BiConsumer.andThen:(Ljava/util/function/BiConsumer;)Ljava/util/function/BiConsumer;
         5: areturn
      LineNumberTable:
        line 61: 0
      LocalVariableTable:
        Start  Length  Slot  Name   Signature
            0       6     0  this   Lscala/concurrent/java8/FuturesConvertersImpl$CF$$anon$1;
            0       6     1   x$1   Ljava/util/function/BiConsumer;
    Signature: #23                          // (Ljava/util/function/BiConsumer<-TT;-Ljava/lang/Throwable;>;)Ljava/util/function/BiConsumer<TT;Ljava/lang/Throwable;>;
    MethodParameters:
      Name                           Flags
      x$1                            final

  public void accept(T, java.lang.Throwable);
    descriptor: (Ljava/lang/Object;Ljava/lang/Throwable;)V
    flags: (0x0001) ACC_PUBLIC
    Code:
      stack=2, locals=5, args_size=3
         0: aload_2
         1: ifnonnull     16
         4: aload_0
         5: getfield      #38                 // Field cf$1:Ljava/util/concurrent/CompletableFuture;
         8: aload_1
         9: invokevirtual #44                 // Method java/util/concurrent/CompletableFuture.complete:(Ljava/lang/Object;)Z
        12: pop
        13: goto          63
        16: aload_0
        17: getfield      #46                 // Field fn$1:Ljava/util/function/Function;
        20: aload_2
        21: invokeinterface #52,  2           // InterfaceMethod java/util/function/Function.apply:(Ljava/lang/Object;)Ljava/lang/Object;
        26: goto          45
        29: astore        4
        31: aload_0
        32: getfield      #38                 // Field cf$1:Ljava/util/concurrent/CompletableFuture;
        35: aload         4
        37: invokevirtual #56                 // Method java/util/concurrent/CompletableFuture.completeExceptionally:(Ljava/lang/Throwable;)Z
        40: pop
        41: aload_0
        42: goto          45
        45: astore_3
        46: aload_3
        47: aload_0
        48: if_acmpeq     63
        51: aload_0
        52: getfield      #38                 // Field cf$1:Ljava/util/concurrent/CompletableFuture;
        55: aload_3
        56: invokevirtual #44                 // Method java/util/concurrent/CompletableFuture.complete:(Ljava/lang/Object;)Z
        59: pop
        60: goto          63
        63: return
      Exception table:
         from    to  target type
            16    26    29   Class java/lang/Throwable
      StackMapTable: number_of_entries = 4
        frame_type = 16 /* same */
        frame_type = 76 /* same_locals_1_stack_item */
          stack = [ class java/lang/Throwable ]
        frame_type = 79 /* same_locals_1_stack_item */
          stack = [ class java/lang/Object ]
        frame_type = 17 /* same */
      LineNumberTable:
        line 63: 0
        line 67: 16
        line 69: 31
        line 71: 46
      LocalVariableTable:
        Start  Length  Slot  Name   Signature
           29      13     4   thr   Ljava/lang/Throwable;
           46      17     3     n   Ljava/lang/Object;
            0      64     0  this   Lscala/concurrent/java8/FuturesConvertersImpl$CF$$anon$1;
            0      64     1     t   Ljava/lang/Object;
            0      64     2     e   Ljava/lang/Throwable;
    Signature: #32                          // (TT;Ljava/lang/Throwable;)V
    MethodParameters:
      Name                           Flags
      t                              final
      e                              final

  public void accept(java.lang.Object, java.lang.Object);
    descriptor: (Ljava/lang/Object;Ljava/lang/Object;)V
    flags: (0x1041) ACC_PUBLIC, ACC_BRIDGE, ACC_SYNTHETIC
    Code:
      stack=3, locals=3, args_size=3
         0: aload_0
         1: aload_1
         2: aload_2
         3: checkcast     #36                 // class java/lang/Throwable
         6: invokevirtual #64                 // Method accept:(Ljava/lang/Object;Ljava/lang/Throwable;)V
         9: return
      LineNumberTable:
        line 61: 0
      LocalVariableTable:
        Start  Length  Slot  Name   Signature
            0      10     0  this   Lscala/concurrent/java8/FuturesConvertersImpl$CF$$anon$1;
            0      10     1   x$1   Ljava/lang/Object;
            0      10     2   x$2   Ljava/lang/Object;
    MethodParameters:
      Name                           Flags
      x$1                            final
      x$2                            final

  public scala.concurrent.java8.FuturesConvertersImpl$CF$$anon$1(scala.concurrent.java8.FuturesConvertersImpl$CF, java.util.concurrent.CompletableFuture, java.util.function.Function);
    descriptor: (Lscala/concurrent/java8/FuturesConvertersImpl$CF;Ljava/util/concurrent/CompletableFuture;Ljava/util/function/Function;)V
    flags: (0x0001) ACC_PUBLIC
    Code:
      stack=2, locals=4, args_size=4
         0: aload_0
         1: aload_2
         2: putfield      #38                 // Field cf$1:Ljava/util/concurrent/CompletableFuture;
         5: aload_0
         6: aload_3
         7: putfield      #46                 // Field fn$1:Ljava/util/function/Function;
        10: aload_0
        11: invokespecial #70                 // Method java/lang/Object."<init>":()V
        14: return
      LineNumberTable:
        line 60: 0
        line 59: 5
        line 61: 10
      LocalVariableTable:
        Start  Length  Slot  Name   Signature
            0      15     0  this   Lscala/concurrent/java8/FuturesConvertersImpl$CF$$anon$1;
            0      15     1 $outer   Lscala/concurrent/java8/FuturesConvertersImpl$CF;
            0      15     2  cf$1   Ljava/util/concurrent/CompletableFuture;
            0      15     3  fn$1   Ljava/util/function/Function;
    MethodParameters:
      Name                           Flags
      $outer                         final synthetic
      cf$1                           final
      fn$1                           final
}
InnerClasses:
  public static #16= #10 of #15;          // CF=class scala/concurrent/java8/FuturesConvertersImpl$CF of class scala/concurrent/java8/FuturesConvertersImpl
  public final #2;                        // class scala/concurrent/java8/FuturesConvertersImpl$CF$$anon$1
EnclosingMethod: #10.#13                // scala.concurrent.java8.FuturesConvertersImpl$CF.exceptionally
Signature: #3                           // Ljava/lang/Object;Ljava/util/function/BiConsumer<TT;Ljava/lang/Throwable;>;
SourceFile: "FutureConvertersImpl.scala"
  ScalaInlineInfo: length = 0x18 (unknown attribute)
   01 01 00 04 00 41 00 42 01 00 1E 00 3D 01 00 1E
   00 1F 01 00 15 00 16 01
  Scala: length = 0x0 (unknown attribute)

