Classfile /Users/mw/Projects/slang-braindump/.jar/jar11/assemble/slang-braindump/assemble/content/coursier/util/shaded/org/jsoup/helper/DataUtil$BomCharset.class
  Last modified May 29, 2022; size 890 bytes
  SHA-256 checksum e9b30b2a2860566dee533504d15d5575680422ac467f049a6ae5bf61fc085a03
  Compiled from "DataUtil.java"
class coursier.util.shaded.org.jsoup.helper.DataUtil$BomCharset
  minor version: 0
  major version: 51
  flags: (0x0020) ACC_SUPER
  this_class: #2                          // coursier/util/shaded/org/jsoup/helper/DataUtil$BomCharset
  super_class: #4                         // java/lang/Object
  interfaces: 0, fields: 2, methods: 3, attributes: 2
Constant pool:
   #1 = Utf8               coursier/util/shaded/org/jsoup/helper/DataUtil$BomCharset
   #2 = Class              #1             // coursier/util/shaded/org/jsoup/helper/DataUtil$BomCharset
   #3 = Utf8               java/lang/Object
   #4 = Class              #3             // java/lang/Object
   #5 = Utf8               DataUtil.java
   #6 = Utf8               coursier/util/shaded/org/jsoup/helper/DataUtil
   #7 = Class              #6             // coursier/util/shaded/org/jsoup/helper/DataUtil
   #8 = Utf8               BomCharset
   #9 = Utf8               charset
  #10 = Utf8               Ljava/lang/String;
  #11 = Utf8               offset
  #12 = Utf8               Z
  #13 = Utf8               <init>
  #14 = Utf8               (Ljava/lang/String;Z)V
  #15 = Utf8               ()V
  #16 = NameAndType        #13:#15        // "<init>":()V
  #17 = Methodref          #4.#16         // java/lang/Object."<init>":()V
  #18 = NameAndType        #9:#10         // charset:Ljava/lang/String;
  #19 = Fieldref           #2.#18         // coursier/util/shaded/org/jsoup/helper/DataUtil$BomCharset.charset:Ljava/lang/String;
  #20 = NameAndType        #11:#12        // offset:Z
  #21 = Fieldref           #2.#20         // coursier/util/shaded/org/jsoup/helper/DataUtil$BomCharset.offset:Z
  #22 = Utf8               this
  #23 = Utf8               Lcoursier/util/shaded/org/jsoup/helper/DataUtil$BomCharset;
  #24 = Utf8               access$000
  #25 = Utf8               (Lcoursier/util/shaded/org/jsoup/helper/DataUtil$BomCharset;)Ljava/lang/String;
  #26 = Utf8               x0
  #27 = Utf8               access$100
  #28 = Utf8               (Lcoursier/util/shaded/org/jsoup/helper/DataUtil$BomCharset;)Z
  #29 = Utf8               Code
  #30 = Utf8               LineNumberTable
  #31 = Utf8               LocalVariableTable
  #32 = Utf8               InnerClasses
  #33 = Utf8               SourceFile
{
  private final java.lang.String charset;
    descriptor: Ljava/lang/String;
    flags: (0x0012) ACC_PRIVATE, ACC_FINAL

  private final boolean offset;
    descriptor: Z
    flags: (0x0012) ACC_PRIVATE, ACC_FINAL

  public coursier.util.shaded.org.jsoup.helper.DataUtil$BomCharset(java.lang.String, boolean);
    descriptor: (Ljava/lang/String;Z)V
    flags: (0x0001) ACC_PUBLIC
    Code:
      stack=2, locals=3, args_size=3
         0: aload_0
         1: invokespecial #17                 // Method java/lang/Object."<init>":()V
         4: aload_0
         5: aload_1
         6: putfield      #19                 // Field charset:Ljava/lang/String;
         9: aload_0
        10: iload_2
        11: putfield      #21                 // Field offset:Z
        14: return
      LineNumberTable:
        line 276: 0
        line 277: 4
        line 278: 9
        line 279: 14
      LocalVariableTable:
        Start  Length  Slot  Name   Signature
            0      15     0  this   Lcoursier/util/shaded/org/jsoup/helper/DataUtil$BomCharset;
            0      15     1 charset   Ljava/lang/String;
            0      15     2 offset   Z

  static java.lang.String access$000(coursier.util.shaded.org.jsoup.helper.DataUtil$BomCharset);
    descriptor: (Lcoursier/util/shaded/org/jsoup/helper/DataUtil$BomCharset;)Ljava/lang/String;
    flags: (0x1008) ACC_STATIC, ACC_SYNTHETIC
    Code:
      stack=1, locals=1, args_size=1
         0: aload_0
         1: getfield      #19                 // Field charset:Ljava/lang/String;
         4: areturn
      LineNumberTable:
        line 272: 0
      LocalVariableTable:
        Start  Length  Slot  Name   Signature
            0       5     0    x0   Lcoursier/util/shaded/org/jsoup/helper/DataUtil$BomCharset;

  static boolean access$100(coursier.util.shaded.org.jsoup.helper.DataUtil$BomCharset);
    descriptor: (Lcoursier/util/shaded/org/jsoup/helper/DataUtil$BomCharset;)Z
    flags: (0x1008) ACC_STATIC, ACC_SYNTHETIC
    Code:
      stack=1, locals=1, args_size=1
         0: aload_0
         1: getfield      #21                 // Field offset:Z
         4: ireturn
      LineNumberTable:
        line 272: 0
      LocalVariableTable:
        Start  Length  Slot  Name   Signature
            0       5     0    x0   Lcoursier/util/shaded/org/jsoup/helper/DataUtil$BomCharset;
}
InnerClasses:
  private static #8= #2 of #7;            // BomCharset=class coursier/util/shaded/org/jsoup/helper/DataUtil$BomCharset of class coursier/util/shaded/org/jsoup/helper/DataUtil
SourceFile: "DataUtil.java"
