Classfile /Users/mw/Projects/slang-braindump/.jar/jar11/assemble/slang-braindump/assemble/content/coursier/util/shaded/org/jsoup/helper/HttpConnection$Base.class
  Last modified May 29, 2022; size 8600 bytes
  SHA-256 checksum b4b5722c792731506280db6b9c0a60b3ed107533c69d543d611f6c1634cc4e1f
  Compiled from "HttpConnection.java"
abstract class coursier.util.shaded.org.jsoup.helper.HttpConnection$Base<T extends coursier.util.shaded.org.jsoup.Connection$Base> extends java.lang.Object implements coursier.util.shaded.org.jsoup.Connection$Base<T>
  minor version: 0
  major version: 51
  flags: (0x0420) ACC_SUPER, ACC_ABSTRACT
  this_class: #2                          // coursier/util/shaded/org/jsoup/helper/HttpConnection$Base
  super_class: #5                         // java/lang/Object
  interfaces: 1, fields: 4, methods: 24, attributes: 3
Constant pool:
    #1 = Utf8               coursier/util/shaded/org/jsoup/helper/HttpConnection$Base
    #2 = Class              #1            // coursier/util/shaded/org/jsoup/helper/HttpConnection$Base
    #3 = Utf8               <T::Lcoursier/util/shaded/org/jsoup/Connection$Base;>Ljava/lang/Object;Lcoursier/util/shaded/org/jsoup/Connection$Base<TT;>;
    #4 = Utf8               java/lang/Object
    #5 = Class              #4            // java/lang/Object
    #6 = Utf8               coursier/util/shaded/org/jsoup/Connection$Base
    #7 = Class              #6            // coursier/util/shaded/org/jsoup/Connection$Base
    #8 = Utf8               HttpConnection.java
    #9 = Utf8               coursier/util/shaded/org/jsoup/helper/HttpConnection
   #10 = Class              #9            // coursier/util/shaded/org/jsoup/helper/HttpConnection
   #11 = Utf8               Base
   #12 = Utf8               coursier/util/shaded/org/jsoup/Connection$Method
   #13 = Class              #12           // coursier/util/shaded/org/jsoup/Connection$Method
   #14 = Utf8               coursier/util/shaded/org/jsoup/Connection
   #15 = Class              #14           // coursier/util/shaded/org/jsoup/Connection
   #16 = Utf8               Method
   #17 = Utf8               java/util/Map$Entry
   #18 = Class              #17           // java/util/Map$Entry
   #19 = Utf8               java/util/Map
   #20 = Class              #19           // java/util/Map
   #21 = Utf8               Entry
   #22 = Utf8               coursier/util/shaded/org/jsoup/helper/HttpConnection$1
   #23 = Class              #22           // coursier/util/shaded/org/jsoup/helper/HttpConnection$1
   #24 = Utf8               url
   #25 = Utf8               Ljava/net/URL;
   #26 = Utf8               method
   #27 = Utf8               Lcoursier/util/shaded/org/jsoup/Connection$Method;
   #28 = Utf8               headers
   #29 = Utf8               Ljava/util/Map;
   #30 = Utf8               Ljava/util/Map<Ljava/lang/String;Ljava/util/List<Ljava/lang/String;>;>;
   #31 = Utf8               cookies
   #32 = Utf8               Ljava/util/Map<Ljava/lang/String;Ljava/lang/String;>;
   #33 = Utf8               <init>
   #34 = Utf8               ()V
   #35 = NameAndType        #33:#34       // "<init>":()V
   #36 = Methodref          #5.#35        // java/lang/Object."<init>":()V
   #37 = Utf8               java/util/LinkedHashMap
   #38 = Class              #37           // java/util/LinkedHashMap
   #39 = Methodref          #38.#35       // java/util/LinkedHashMap."<init>":()V
   #40 = NameAndType        #28:#29       // headers:Ljava/util/Map;
   #41 = Fieldref           #2.#40        // coursier/util/shaded/org/jsoup/helper/HttpConnection$Base.headers:Ljava/util/Map;
   #42 = NameAndType        #31:#29       // cookies:Ljava/util/Map;
   #43 = Fieldref           #2.#42        // coursier/util/shaded/org/jsoup/helper/HttpConnection$Base.cookies:Ljava/util/Map;
   #44 = Utf8               this
   #45 = Utf8               Lcoursier/util/shaded/org/jsoup/helper/HttpConnection$Base<TT;>;
   #46 = Utf8               Lcoursier/util/shaded/org/jsoup/helper/HttpConnection$Base;
   #47 = Utf8               ()Ljava/net/URL;
   #48 = NameAndType        #24:#25       // url:Ljava/net/URL;
   #49 = Fieldref           #2.#48        // coursier/util/shaded/org/jsoup/helper/HttpConnection$Base.url:Ljava/net/URL;
   #50 = Utf8               (Ljava/net/URL;)Lcoursier/util/shaded/org/jsoup/Connection$Base;
   #51 = Utf8               (Ljava/net/URL;)TT;
   #52 = Utf8               URL must not be null
   #53 = String             #52           // URL must not be null
   #54 = Utf8               coursier/util/shaded/org/jsoup/helper/Validate
   #55 = Class              #54           // coursier/util/shaded/org/jsoup/helper/Validate
   #56 = Utf8               notNull
   #57 = Utf8               (Ljava/lang/Object;Ljava/lang/String;)V
   #58 = NameAndType        #56:#57       // notNull:(Ljava/lang/Object;Ljava/lang/String;)V
   #59 = Methodref          #55.#58       // coursier/util/shaded/org/jsoup/helper/Validate.notNull:(Ljava/lang/Object;Ljava/lang/String;)V
   #60 = Utf8               ()Lcoursier/util/shaded/org/jsoup/Connection$Method;
   #61 = NameAndType        #26:#27       // method:Lcoursier/util/shaded/org/jsoup/Connection$Method;
   #62 = Fieldref           #2.#61        // coursier/util/shaded/org/jsoup/helper/HttpConnection$Base.method:Lcoursier/util/shaded/org/jsoup/Connection$Method;
   #63 = Utf8               (Lcoursier/util/shaded/org/jsoup/Connection$Method;)Lcoursier/util/shaded/org/jsoup/Connection$Base;
   #64 = Utf8               (Lcoursier/util/shaded/org/jsoup/Connection$Method;)TT;
   #65 = Utf8               Method must not be null
   #66 = String             #65           // Method must not be null
   #67 = Utf8               header
   #68 = Utf8               (Ljava/lang/String;)Ljava/lang/String;
   #69 = Utf8               Header name must not be null
   #70 = String             #69           // Header name must not be null
   #71 = Utf8               getHeadersCaseInsensitive
   #72 = Utf8               (Ljava/lang/String;)Ljava/util/List;
   #73 = NameAndType        #71:#72       // getHeadersCaseInsensitive:(Ljava/lang/String;)Ljava/util/List;
   #74 = Methodref          #2.#73        // coursier/util/shaded/org/jsoup/helper/HttpConnection$Base.getHeadersCaseInsensitive:(Ljava/lang/String;)Ljava/util/List;
   #75 = Utf8               java/util/List
   #76 = Class              #75           // java/util/List
   #77 = Utf8               size
   #78 = Utf8               ()I
   #79 = NameAndType        #77:#78       // size:()I
   #80 = InterfaceMethodref #76.#79       // java/util/List.size:()I
   #81 = Utf8               ,
   #82 = String             #81           // ,
   #83 = Utf8               coursier/util/shaded/org/jsoup/internal/StringUtil
   #84 = Class              #83           // coursier/util/shaded/org/jsoup/internal/StringUtil
   #85 = Utf8               join
   #86 = Utf8               (Ljava/util/Collection;Ljava/lang/String;)Ljava/lang/String;
   #87 = NameAndType        #85:#86       // join:(Ljava/util/Collection;Ljava/lang/String;)Ljava/lang/String;
   #88 = Methodref          #84.#87       // coursier/util/shaded/org/jsoup/internal/StringUtil.join:(Ljava/util/Collection;Ljava/lang/String;)Ljava/lang/String;
   #89 = Utf8               name
   #90 = Utf8               Ljava/lang/String;
   #91 = Utf8               vals
   #92 = Utf8               Ljava/util/List<Ljava/lang/String;>;
   #93 = Utf8               Ljava/util/List;
   #94 = Utf8               addHeader
   #95 = Utf8               (Ljava/lang/String;Ljava/lang/String;)Lcoursier/util/shaded/org/jsoup/Connection$Base;
   #96 = Utf8               (Ljava/lang/String;Ljava/lang/String;)TT;
   #97 = Utf8               notEmpty
   #98 = Utf8               (Ljava/lang/String;)V
   #99 = NameAndType        #97:#98       // notEmpty:(Ljava/lang/String;)V
  #100 = Methodref          #55.#99       // coursier/util/shaded/org/jsoup/helper/Validate.notEmpty:(Ljava/lang/String;)V
  #101 = Utf8
  #102 = String             #101          //
  #103 = Utf8               java/lang/String
  #104 = Class              #103          // java/lang/String
  #105 = NameAndType        #28:#72       // headers:(Ljava/lang/String;)Ljava/util/List;
  #106 = Methodref          #2.#105       // coursier/util/shaded/org/jsoup/helper/HttpConnection$Base.headers:(Ljava/lang/String;)Ljava/util/List;
  #107 = Utf8               isEmpty
  #108 = Utf8               ()Z
  #109 = NameAndType        #107:#108     // isEmpty:()Z
  #110 = InterfaceMethodref #76.#109      // java/util/List.isEmpty:()Z
  #111 = Utf8               java/util/ArrayList
  #112 = Class              #111          // java/util/ArrayList
  #113 = Methodref          #112.#35      // java/util/ArrayList."<init>":()V
  #114 = Utf8               put
  #115 = Utf8               (Ljava/lang/Object;Ljava/lang/Object;)Ljava/lang/Object;
  #116 = NameAndType        #114:#115     // put:(Ljava/lang/Object;Ljava/lang/Object;)Ljava/lang/Object;
  #117 = InterfaceMethodref #20.#116      // java/util/Map.put:(Ljava/lang/Object;Ljava/lang/Object;)Ljava/lang/Object;
  #118 = Utf8               fixHeaderEncoding
  #119 = NameAndType        #118:#68      // fixHeaderEncoding:(Ljava/lang/String;)Ljava/lang/String;
  #120 = Methodref          #2.#119       // coursier/util/shaded/org/jsoup/helper/HttpConnection$Base.fixHeaderEncoding:(Ljava/lang/String;)Ljava/lang/String;
  #121 = Utf8               add
  #122 = Utf8               (Ljava/lang/Object;)Z
  #123 = NameAndType        #121:#122     // add:(Ljava/lang/Object;)Z
  #124 = InterfaceMethodref #76.#123      // java/util/List.add:(Ljava/lang/Object;)Z
  #125 = Utf8               value
  #126 = Utf8               values
  #127 = Utf8               (Ljava/lang/String;)Ljava/util/List<Ljava/lang/String;>;
  #128 = Utf8               java/io/UnsupportedEncodingException
  #129 = Class              #128          // java/io/UnsupportedEncodingException
  #130 = Utf8               ISO-8859-1
  #131 = String             #130          // ISO-8859-1
  #132 = Utf8               getBytes
  #133 = Utf8               (Ljava/lang/String;)[B
  #134 = NameAndType        #132:#133     // getBytes:(Ljava/lang/String;)[B
  #135 = Methodref          #104.#134     // java/lang/String.getBytes:(Ljava/lang/String;)[B
  #136 = Utf8               looksLikeUtf8
  #137 = Utf8               ([B)Z
  #138 = NameAndType        #136:#137     // looksLikeUtf8:([B)Z
  #139 = Methodref          #2.#138       // coursier/util/shaded/org/jsoup/helper/HttpConnection$Base.looksLikeUtf8:([B)Z
  #140 = Utf8               [B
  #141 = Class              #140          // "[B"
  #142 = Utf8               UTF-8
  #143 = String             #142          // UTF-8
  #144 = Utf8               ([BLjava/lang/String;)V
  #145 = NameAndType        #33:#144      // "<init>":([BLjava/lang/String;)V
  #146 = Methodref          #104.#145     // java/lang/String."<init>":([BLjava/lang/String;)V
  #147 = Utf8               bytes
  #148 = Utf8               e
  #149 = Utf8               Ljava/io/UnsupportedEncodingException;
  #150 = Utf8               val
  #151 = Utf8               end
  #152 = Utf8               I
  #153 = Utf8               o
  #154 = Utf8               j
  #155 = Utf8               input
  #156 = Utf8               i
  #157 = Utf8               Header name must not be empty
  #158 = String             #157          // Header name must not be empty
  #159 = Utf8               (Ljava/lang/String;Ljava/lang/String;)V
  #160 = NameAndType        #97:#159      // notEmpty:(Ljava/lang/String;Ljava/lang/String;)V
  #161 = Methodref          #55.#160      // coursier/util/shaded/org/jsoup/helper/Validate.notEmpty:(Ljava/lang/String;Ljava/lang/String;)V
  #162 = Utf8               removeHeader
  #163 = Utf8               (Ljava/lang/String;)Lcoursier/util/shaded/org/jsoup/Connection$Base;
  #164 = NameAndType        #162:#163     // removeHeader:(Ljava/lang/String;)Lcoursier/util/shaded/org/jsoup/Connection$Base;
  #165 = Methodref          #2.#164       // coursier/util/shaded/org/jsoup/helper/HttpConnection$Base.removeHeader:(Ljava/lang/String;)Lcoursier/util/shaded/org/jsoup/Connection$Base;
  #166 = NameAndType        #94:#95       // addHeader:(Ljava/lang/String;Ljava/lang/String;)Lcoursier/util/shaded/org/jsoup/Connection$Base;
  #167 = Methodref          #2.#166       // coursier/util/shaded/org/jsoup/helper/HttpConnection$Base.addHeader:(Ljava/lang/String;Ljava/lang/String;)Lcoursier/util/shaded/org/jsoup/Connection$Base;
  #168 = Utf8               hasHeader
  #169 = Utf8               (Ljava/lang/String;)Z
  #170 = Utf8               hasHeaderWithValue
  #171 = Utf8               (Ljava/lang/String;Ljava/lang/String;)Z
  #172 = Utf8               iterator
  #173 = Utf8               ()Ljava/util/Iterator;
  #174 = NameAndType        #172:#173     // iterator:()Ljava/util/Iterator;
  #175 = InterfaceMethodref #76.#174      // java/util/List.iterator:()Ljava/util/Iterator;
  #176 = Utf8               java/util/Iterator
  #177 = Class              #176          // java/util/Iterator
  #178 = Utf8               hasNext
  #179 = NameAndType        #178:#108     // hasNext:()Z
  #180 = InterfaceMethodref #177.#179     // java/util/Iterator.hasNext:()Z
  #181 = Utf8               next
  #182 = Utf8               ()Ljava/lang/Object;
  #183 = NameAndType        #181:#182     // next:()Ljava/lang/Object;
  #184 = InterfaceMethodref #177.#183     // java/util/Iterator.next:()Ljava/lang/Object;
  #185 = Utf8               equalsIgnoreCase
  #186 = NameAndType        #185:#169     // equalsIgnoreCase:(Ljava/lang/String;)Z
  #187 = Methodref          #104.#186     // java/lang/String.equalsIgnoreCase:(Ljava/lang/String;)Z
  #188 = Utf8               candidate
  #189 = Utf8               (Ljava/lang/String;)TT;
  #190 = Utf8               scanHeaders
  #191 = Utf8               (Ljava/lang/String;)Ljava/util/Map$Entry;
  #192 = NameAndType        #190:#191     // scanHeaders:(Ljava/lang/String;)Ljava/util/Map$Entry;
  #193 = Methodref          #2.#192       // coursier/util/shaded/org/jsoup/helper/HttpConnection$Base.scanHeaders:(Ljava/lang/String;)Ljava/util/Map$Entry;
  #194 = Utf8               getKey
  #195 = NameAndType        #194:#182     // getKey:()Ljava/lang/Object;
  #196 = InterfaceMethodref #18.#195      // java/util/Map$Entry.getKey:()Ljava/lang/Object;
  #197 = Utf8               remove
  #198 = Utf8               (Ljava/lang/Object;)Ljava/lang/Object;
  #199 = NameAndType        #197:#198     // remove:(Ljava/lang/Object;)Ljava/lang/Object;
  #200 = InterfaceMethodref #20.#199      // java/util/Map.remove:(Ljava/lang/Object;)Ljava/lang/Object;
  #201 = Utf8               entry
  #202 = Utf8               Ljava/util/Map$Entry<Ljava/lang/String;Ljava/util/List<Ljava/lang/String;>;>;
  #203 = Utf8               Ljava/util/Map$Entry;
  #204 = Utf8               ()Ljava/util/Map;
  #205 = Utf8               ()Ljava/util/Map<Ljava/lang/String;Ljava/lang/String;>;
  #206 = InterfaceMethodref #20.#79       // java/util/Map.size:()I
  #207 = Utf8               (I)V
  #208 = NameAndType        #33:#207      // "<init>":(I)V
  #209 = Methodref          #38.#208      // java/util/LinkedHashMap."<init>":(I)V
  #210 = Utf8               entrySet
  #211 = Utf8               ()Ljava/util/Set;
  #212 = NameAndType        #210:#211     // entrySet:()Ljava/util/Set;
  #213 = InterfaceMethodref #20.#212      // java/util/Map.entrySet:()Ljava/util/Set;
  #214 = Utf8               java/util/Set
  #215 = Class              #214          // java/util/Set
  #216 = InterfaceMethodref #215.#174     // java/util/Set.iterator:()Ljava/util/Iterator;
  #217 = Utf8               getValue
  #218 = NameAndType        #217:#182     // getValue:()Ljava/lang/Object;
  #219 = InterfaceMethodref #18.#218      // java/util/Map$Entry.getValue:()Ljava/lang/Object;
  #220 = Utf8               get
  #221 = Utf8               (I)Ljava/lang/Object;
  #222 = NameAndType        #220:#221     // get:(I)Ljava/lang/Object;
  #223 = InterfaceMethodref #76.#222      // java/util/List.get:(I)Ljava/lang/Object;
  #224 = Methodref          #38.#116      // java/util/LinkedHashMap.put:(Ljava/lang/Object;Ljava/lang/Object;)Ljava/lang/Object;
  #225 = Utf8               map
  #226 = Utf8               Ljava/util/LinkedHashMap<Ljava/lang/String;Ljava/lang/String;>;
  #227 = Utf8               Ljava/util/LinkedHashMap;
  #228 = Utf8               multiHeaders
  #229 = Utf8               ()Ljava/util/Map<Ljava/lang/String;Ljava/util/List<Ljava/lang/String;>;>;
  #230 = Utf8               (Ljava/lang/Object;)V
  #231 = NameAndType        #56:#230      // notNull:(Ljava/lang/Object;)V
  #232 = Methodref          #55.#231      // coursier/util/shaded/org/jsoup/helper/Validate.notNull:(Ljava/lang/Object;)V
  #233 = Utf8               java/util/Collections
  #234 = Class              #233          // java/util/Collections
  #235 = Utf8               emptyList
  #236 = Utf8               ()Ljava/util/List;
  #237 = NameAndType        #235:#236     // emptyList:()Ljava/util/List;
  #238 = Methodref          #234.#237     // java/util/Collections.emptyList:()Ljava/util/List;
  #239 = Utf8               (Ljava/lang/String;)Ljava/util/Map$Entry<Ljava/lang/String;Ljava/util/List<Ljava/lang/String;>;>;
  #240 = Utf8               coursier/util/shaded/org/jsoup/internal/Normalizer
  #241 = Class              #240          // coursier/util/shaded/org/jsoup/internal/Normalizer
  #242 = Utf8               lowerCase
  #243 = NameAndType        #242:#68      // lowerCase:(Ljava/lang/String;)Ljava/lang/String;
  #244 = Methodref          #241.#243     // coursier/util/shaded/org/jsoup/internal/Normalizer.lowerCase:(Ljava/lang/String;)Ljava/lang/String;
  #245 = Utf8               equals
  #246 = NameAndType        #245:#122     // equals:(Ljava/lang/Object;)Z
  #247 = Methodref          #104.#246     // java/lang/String.equals:(Ljava/lang/Object;)Z
  #248 = Utf8               lc
  #249 = Utf8               cookie
  #250 = Utf8               Cookie name must not be empty
  #251 = String             #250          // Cookie name must not be empty
  #252 = NameAndType        #220:#198     // get:(Ljava/lang/Object;)Ljava/lang/Object;
  #253 = InterfaceMethodref #20.#252      // java/util/Map.get:(Ljava/lang/Object;)Ljava/lang/Object;
  #254 = Utf8               Cookie value must not be null
  #255 = String             #254          // Cookie value must not be null
  #256 = Utf8               hasCookie
  #257 = Utf8               containsKey
  #258 = NameAndType        #257:#122     // containsKey:(Ljava/lang/Object;)Z
  #259 = InterfaceMethodref #20.#258      // java/util/Map.containsKey:(Ljava/lang/Object;)Z
  #260 = Utf8               removeCookie
  #261 = Utf8               (Lcoursier/util/shaded/org/jsoup/helper/HttpConnection$1;)V
  #262 = Methodref          #2.#35        // coursier/util/shaded/org/jsoup/helper/HttpConnection$Base."<init>":()V
  #263 = Utf8               x0
  #264 = Utf8               Lcoursier/util/shaded/org/jsoup/helper/HttpConnection$1;
  #265 = Utf8               Signature
  #266 = Utf8               Code
  #267 = Utf8               LineNumberTable
  #268 = Utf8               LocalVariableTable
  #269 = Utf8               LocalVariableTypeTable
  #270 = Utf8               StackMapTable
  #271 = Utf8               InnerClasses
  #272 = Utf8               SourceFile
{
  java.net.URL url;
    descriptor: Ljava/net/URL;
    flags: (0x0000)

  coursier.util.shaded.org.jsoup.Connection$Method method;
    descriptor: Lcoursier/util/shaded/org/jsoup/Connection$Method;
    flags: (0x0000)

  java.util.Map<java.lang.String, java.util.List<java.lang.String>> headers;
    descriptor: Ljava/util/Map;
    flags: (0x0000)
    Signature: #30                          // Ljava/util/Map<Ljava/lang/String;Ljava/util/List<Ljava/lang/String;>;>;

  java.util.Map<java.lang.String, java.lang.String> cookies;
    descriptor: Ljava/util/Map;
    flags: (0x0000)
    Signature: #32                          // Ljava/util/Map<Ljava/lang/String;Ljava/lang/String;>;

  private coursier.util.shaded.org.jsoup.helper.HttpConnection$Base();
    descriptor: ()V
    flags: (0x0002) ACC_PRIVATE
    Code:
      stack=3, locals=1, args_size=1
         0: aload_0
         1: invokespecial #36                 // Method java/lang/Object."<init>":()V
         4: aload_0
         5: new           #38                 // class java/util/LinkedHashMap
         8: dup
         9: invokespecial #39                 // Method java/util/LinkedHashMap."<init>":()V
        12: putfield      #41                 // Field headers:Ljava/util/Map;
        15: aload_0
        16: new           #38                 // class java/util/LinkedHashMap
        19: dup
        20: invokespecial #39                 // Method java/util/LinkedHashMap."<init>":()V
        23: putfield      #43                 // Field cookies:Ljava/util/Map;
        26: return
      LineNumberTable:
        line 331: 0
        line 332: 4
        line 333: 15
        line 334: 26
      LocalVariableTable:
        Start  Length  Slot  Name   Signature
            0      27     0  this   Lcoursier/util/shaded/org/jsoup/helper/HttpConnection$Base;
      LocalVariableTypeTable:
        Start  Length  Slot  Name   Signature
            0      27     0  this   Lcoursier/util/shaded/org/jsoup/helper/HttpConnection$Base<TT;>;

  public java.net.URL url();
    descriptor: ()Ljava/net/URL;
    flags: (0x0001) ACC_PUBLIC
    Code:
      stack=1, locals=1, args_size=1
         0: aload_0
         1: getfield      #49                 // Field url:Ljava/net/URL;
         4: areturn
      LineNumberTable:
        line 337: 0
      LocalVariableTable:
        Start  Length  Slot  Name   Signature
            0       5     0  this   Lcoursier/util/shaded/org/jsoup/helper/HttpConnection$Base;
      LocalVariableTypeTable:
        Start  Length  Slot  Name   Signature
            0       5     0  this   Lcoursier/util/shaded/org/jsoup/helper/HttpConnection$Base<TT;>;

  public T url(java.net.URL);
    descriptor: (Ljava/net/URL;)Lcoursier/util/shaded/org/jsoup/Connection$Base;
    flags: (0x0001) ACC_PUBLIC
    Code:
      stack=2, locals=2, args_size=2
         0: aload_1
         1: ldc           #53                 // String URL must not be null
         3: invokestatic  #59                 // Method coursier/util/shaded/org/jsoup/helper/Validate.notNull:(Ljava/lang/Object;Ljava/lang/String;)V
         6: aload_0
         7: aload_1
         8: putfield      #49                 // Field url:Ljava/net/URL;
        11: aload_0
        12: areturn
      LineNumberTable:
        line 341: 0
        line 342: 6
        line 343: 11
      LocalVariableTable:
        Start  Length  Slot  Name   Signature
            0      13     0  this   Lcoursier/util/shaded/org/jsoup/helper/HttpConnection$Base;
            0      13     1   url   Ljava/net/URL;
      LocalVariableTypeTable:
        Start  Length  Slot  Name   Signature
            0      13     0  this   Lcoursier/util/shaded/org/jsoup/helper/HttpConnection$Base<TT;>;
    Signature: #51                          // (Ljava/net/URL;)TT;

  public coursier.util.shaded.org.jsoup.Connection$Method method();
    descriptor: ()Lcoursier/util/shaded/org/jsoup/Connection$Method;
    flags: (0x0001) ACC_PUBLIC
    Code:
      stack=1, locals=1, args_size=1
         0: aload_0
         1: getfield      #62                 // Field method:Lcoursier/util/shaded/org/jsoup/Connection$Method;
         4: areturn
      LineNumberTable:
        line 347: 0
      LocalVariableTable:
        Start  Length  Slot  Name   Signature
            0       5     0  this   Lcoursier/util/shaded/org/jsoup/helper/HttpConnection$Base;
      LocalVariableTypeTable:
        Start  Length  Slot  Name   Signature
            0       5     0  this   Lcoursier/util/shaded/org/jsoup/helper/HttpConnection$Base<TT;>;

  public T method(coursier.util.shaded.org.jsoup.Connection$Method);
    descriptor: (Lcoursier/util/shaded/org/jsoup/Connection$Method;)Lcoursier/util/shaded/org/jsoup/Connection$Base;
    flags: (0x0001) ACC_PUBLIC
    Code:
      stack=2, locals=2, args_size=2
         0: aload_1
         1: ldc           #66                 // String Method must not be null
         3: invokestatic  #59                 // Method coursier/util/shaded/org/jsoup/helper/Validate.notNull:(Ljava/lang/Object;Ljava/lang/String;)V
         6: aload_0
         7: aload_1
         8: putfield      #62                 // Field method:Lcoursier/util/shaded/org/jsoup/Connection$Method;
        11: aload_0
        12: areturn
      LineNumberTable:
        line 351: 0
        line 352: 6
        line 353: 11
      LocalVariableTable:
        Start  Length  Slot  Name   Signature
            0      13     0  this   Lcoursier/util/shaded/org/jsoup/helper/HttpConnection$Base;
            0      13     1 method   Lcoursier/util/shaded/org/jsoup/Connection$Method;
      LocalVariableTypeTable:
        Start  Length  Slot  Name   Signature
            0      13     0  this   Lcoursier/util/shaded/org/jsoup/helper/HttpConnection$Base<TT;>;
    Signature: #64                          // (Lcoursier/util/shaded/org/jsoup/Connection$Method;)TT;

  public java.lang.String header(java.lang.String);
    descriptor: (Ljava/lang/String;)Ljava/lang/String;
    flags: (0x0001) ACC_PUBLIC
    Code:
      stack=2, locals=3, args_size=2
         0: aload_1
         1: ldc           #70                 // String Header name must not be null
         3: invokestatic  #59                 // Method coursier/util/shaded/org/jsoup/helper/Validate.notNull:(Ljava/lang/Object;Ljava/lang/String;)V
         6: aload_0
         7: aload_1
         8: invokespecial #74                 // Method getHeadersCaseInsensitive:(Ljava/lang/String;)Ljava/util/List;
        11: astore_2
        12: aload_2
        13: invokeinterface #80,  1           // InterfaceMethod java/util/List.size:()I
        18: ifle          28
        21: aload_2
        22: ldc           #82                 // String ,
        24: invokestatic  #88                 // Method coursier/util/shaded/org/jsoup/internal/StringUtil.join:(Ljava/util/Collection;Ljava/lang/String;)Ljava/lang/String;
        27: areturn
        28: aconst_null
        29: areturn
      StackMapTable: number_of_entries = 1
        frame_type = 252 /* append */
          offset_delta = 28
          locals = [ class java/util/List ]
      LineNumberTable:
        line 357: 0
        line 358: 6
        line 359: 12
        line 361: 21
        line 364: 28
      LocalVariableTable:
        Start  Length  Slot  Name   Signature
            0      30     0  this   Lcoursier/util/shaded/org/jsoup/helper/HttpConnection$Base;
            0      30     1  name   Ljava/lang/String;
           12      18     2  vals   Ljava/util/List;
      LocalVariableTypeTable:
        Start  Length  Slot  Name   Signature
            0      30     0  this   Lcoursier/util/shaded/org/jsoup/helper/HttpConnection$Base<TT;>;
           12      18     2  vals   Ljava/util/List<Ljava/lang/String;>;

  public T addHeader(java.lang.String, java.lang.String);
    descriptor: (Ljava/lang/String;Ljava/lang/String;)Lcoursier/util/shaded/org/jsoup/Connection$Base;
    flags: (0x0001) ACC_PUBLIC
    Code:
      stack=3, locals=4, args_size=3
         0: aload_1
         1: invokestatic  #100                // Method coursier/util/shaded/org/jsoup/helper/Validate.notEmpty:(Ljava/lang/String;)V
         4: aload_2
         5: ifnonnull     13
         8: ldc           #102                // String
        10: goto          14
        13: aload_2
        14: astore_2
        15: aload_0
        16: aload_1
        17: invokevirtual #106                // Method headers:(Ljava/lang/String;)Ljava/util/List;
        20: astore_3
        21: aload_3
        22: invokeinterface #110,  1          // InterfaceMethod java/util/List.isEmpty:()Z
        27: ifeq          50
        30: new           #112                // class java/util/ArrayList
        33: dup
        34: invokespecial #113                // Method java/util/ArrayList."<init>":()V
        37: astore_3
        38: aload_0
        39: getfield      #41                 // Field headers:Ljava/util/Map;
        42: aload_1
        43: aload_3
        44: invokeinterface #117,  3          // InterfaceMethod java/util/Map.put:(Ljava/lang/Object;Ljava/lang/Object;)Ljava/lang/Object;
        49: pop
        50: aload_3
        51: aload_2
        52: invokestatic  #120                // Method fixHeaderEncoding:(Ljava/lang/String;)Ljava/lang/String;
        55: invokeinterface #124,  2          // InterfaceMethod java/util/List.add:(Ljava/lang/Object;)Z
        60: pop
        61: aload_0
        62: areturn
      StackMapTable: number_of_entries = 3
        frame_type = 13 /* same */
        frame_type = 64 /* same_locals_1_stack_item */
          stack = [ class java/lang/String ]
        frame_type = 252 /* append */
          offset_delta = 35
          locals = [ class java/util/List ]
      LineNumberTable:
        line 369: 0
        line 370: 4
        line 372: 15
        line 373: 21
        line 374: 30
        line 375: 38
        line 377: 50
        line 379: 61
      LocalVariableTable:
        Start  Length  Slot  Name   Signature
            0      63     0  this   Lcoursier/util/shaded/org/jsoup/helper/HttpConnection$Base;
            0      63     1  name   Ljava/lang/String;
            0      63     2 value   Ljava/lang/String;
           21      42     3 values   Ljava/util/List;
      LocalVariableTypeTable:
        Start  Length  Slot  Name   Signature
            0      63     0  this   Lcoursier/util/shaded/org/jsoup/helper/HttpConnection$Base<TT;>;
           21      42     3 values   Ljava/util/List<Ljava/lang/String;>;
    Signature: #96                          // (Ljava/lang/String;Ljava/lang/String;)TT;

  public java.util.List<java.lang.String> headers(java.lang.String);
    descriptor: (Ljava/lang/String;)Ljava/util/List;
    flags: (0x0001) ACC_PUBLIC
    Code:
      stack=2, locals=2, args_size=2
         0: aload_1
         1: invokestatic  #100                // Method coursier/util/shaded/org/jsoup/helper/Validate.notEmpty:(Ljava/lang/String;)V
         4: aload_0
         5: aload_1
         6: invokespecial #74                 // Method getHeadersCaseInsensitive:(Ljava/lang/String;)Ljava/util/List;
         9: areturn
      LineNumberTable:
        line 384: 0
        line 385: 4
      LocalVariableTable:
        Start  Length  Slot  Name   Signature
            0      10     0  this   Lcoursier/util/shaded/org/jsoup/helper/HttpConnection$Base;
            0      10     1  name   Ljava/lang/String;
      LocalVariableTypeTable:
        Start  Length  Slot  Name   Signature
            0      10     0  this   Lcoursier/util/shaded/org/jsoup/helper/HttpConnection$Base<TT;>;
    Signature: #127                         // (Ljava/lang/String;)Ljava/util/List<Ljava/lang/String;>;

  private static java.lang.String fixHeaderEncoding(java.lang.String);
    descriptor: (Ljava/lang/String;)Ljava/lang/String;
    flags: (0x000a) ACC_PRIVATE, ACC_STATIC
    Code:
      stack=4, locals=2, args_size=1
         0: aload_0
         1: ldc           #131                // String ISO-8859-1
         3: invokevirtual #135                // Method java/lang/String.getBytes:(Ljava/lang/String;)[B
         6: astore_1
         7: aload_1
         8: invokestatic  #139                // Method looksLikeUtf8:([B)Z
        11: ifne          16
        14: aload_0
        15: areturn
        16: new           #104                // class java/lang/String
        19: dup
        20: aload_1
        21: ldc           #143                // String UTF-8
        23: invokespecial #146                // Method java/lang/String."<init>":([BLjava/lang/String;)V
        26: areturn
        27: astore_1
        28: aload_0
        29: areturn
      Exception table:
         from    to  target type
             0    15    27   Class java/io/UnsupportedEncodingException
            16    26    27   Class java/io/UnsupportedEncodingException
      StackMapTable: number_of_entries = 2
        frame_type = 252 /* append */
          offset_delta = 16
          locals = [ class "[B" ]
        frame_type = 255 /* full_frame */
          offset_delta = 10
          locals = [ class java/lang/String ]
          stack = [ class java/io/UnsupportedEncodingException ]
      LineNumberTable:
        line 390: 0
        line 391: 7
        line 392: 14
        line 393: 16
        line 394: 27
        line 396: 28
      LocalVariableTable:
        Start  Length  Slot  Name   Signature
            7      20     1 bytes   [B
           28       2     1     e   Ljava/io/UnsupportedEncodingException;
            0      30     0   val   Ljava/lang/String;

  private static boolean looksLikeUtf8(byte[]);
    descriptor: ([B)Z
    flags: (0x000a) ACC_PRIVATE, ACC_STATIC
    Code:
      stack=3, locals=5, args_size=1
         0: iconst_0
         1: istore_1
         2: aload_0
         3: arraylength
         4: iconst_3
         5: if_icmplt     63
         8: aload_0
         9: iconst_0
        10: baload
        11: sipush        255
        14: iand
        15: sipush        239
        18: if_icmpne     63
        21: aload_0
        22: iconst_1
        23: baload
        24: sipush        255
        27: iand
        28: sipush        187
        31: if_icmpne     38
        34: iconst_1
        35: goto          39
        38: iconst_0
        39: aload_0
        40: iconst_2
        41: baload
        42: sipush        255
        45: iand
        46: sipush        191
        49: if_icmpne     56
        52: iconst_1
        53: goto          57
        56: iconst_0
        57: iand
        58: ifeq          63
        61: iconst_3
        62: istore_1
        63: aload_0
        64: arraylength
        65: istore_3
        66: iload_1
        67: iload_3
        68: if_icmpge     188
        71: aload_0
        72: iload_1
        73: baload
        74: istore        4
        76: iload         4
        78: sipush        128
        81: iand
        82: ifne          88
        85: goto          182
        88: iload         4
        90: sipush        224
        93: iand
        94: sipush        192
        97: if_icmpne     107
       100: iload_1
       101: iconst_1
       102: iadd
       103: istore_2
       104: goto          147
       107: iload         4
       109: sipush        240
       112: iand
       113: sipush        224
       116: if_icmpne     126
       119: iload_1
       120: iconst_2
       121: iadd
       122: istore_2
       123: goto          147
       126: iload         4
       128: sipush        248
       131: iand
       132: sipush        240
       135: if_icmpne     145
       138: iload_1
       139: iconst_3
       140: iadd
       141: istore_2
       142: goto          147
       145: iconst_0
       146: ireturn
       147: iload_2
       148: aload_0
       149: arraylength
       150: if_icmplt     155
       153: iconst_0
       154: ireturn
       155: iload_1
       156: iload_2
       157: if_icmpge     182
       160: iinc          1, 1
       163: aload_0
       164: iload_1
       165: baload
       166: istore        4
       168: iload         4
       170: sipush        192
       173: iand
       174: sipush        128
       177: if_icmpeq     155
       180: iconst_0
       181: ireturn
       182: iinc          1, 1
       185: goto          66
       188: iconst_1
       189: ireturn
      StackMapTable: number_of_entries = 14
        frame_type = 252 /* append */
          offset_delta = 38
          locals = [ int ]
        frame_type = 64 /* same_locals_1_stack_item */
          stack = [ int ]
        frame_type = 80 /* same_locals_1_stack_item */
          stack = [ int ]
        frame_type = 255 /* full_frame */
          offset_delta = 0
          locals = [ class "[B", int ]
          stack = [ int, int ]
        frame_type = 5 /* same */
        frame_type = 253 /* append */
          offset_delta = 2
          locals = [ top, int ]
        frame_type = 252 /* append */
          offset_delta = 21
          locals = [ int ]
        frame_type = 18 /* same */
        frame_type = 18 /* same */
        frame_type = 18 /* same */
        frame_type = 255 /* full_frame */
          offset_delta = 1
          locals = [ class "[B", int, int, int, int ]
          stack = []
        frame_type = 7 /* same */
        frame_type = 255 /* full_frame */
          offset_delta = 26
          locals = [ class "[B", int, top, int ]
          stack = []
        frame_type = 249 /* chop */
          offset_delta = 5
      LineNumberTable:
        line 401: 0
        line 403: 2
        line 405: 61
        line 409: 63
        line 410: 71
        line 411: 76
        line 412: 85
        line 416: 88
        line 417: 100
        line 418: 107
        line 419: 119
        line 420: 126
        line 421: 138
        line 423: 145
        line 426: 147
        line 427: 153
        line 429: 155
        line 430: 160
        line 431: 163
        line 432: 168
        line 433: 180
        line 409: 182
        line 437: 188
      LocalVariableTable:
        Start  Length  Slot  Name   Signature
          104       3     2   end   I
          123       3     2   end   I
          142       3     2   end   I
           76     106     4     o   I
          147      35     2   end   I
           66     122     3     j   I
            0     190     0 input   [B
            2     188     1     i   I

  public T header(java.lang.String, java.lang.String);
    descriptor: (Ljava/lang/String;Ljava/lang/String;)Lcoursier/util/shaded/org/jsoup/Connection$Base;
    flags: (0x0001) ACC_PUBLIC
    Code:
      stack=3, locals=3, args_size=3
         0: aload_1
         1: ldc           #158                // String Header name must not be empty
         3: invokestatic  #161                // Method coursier/util/shaded/org/jsoup/helper/Validate.notEmpty:(Ljava/lang/String;Ljava/lang/String;)V
         6: aload_0
         7: aload_1
         8: invokevirtual #165                // Method removeHeader:(Ljava/lang/String;)Lcoursier/util/shaded/org/jsoup/Connection$Base;
        11: pop
        12: aload_0
        13: aload_1
        14: aload_2
        15: invokevirtual #167                // Method addHeader:(Ljava/lang/String;Ljava/lang/String;)Lcoursier/util/shaded/org/jsoup/Connection$Base;
        18: pop
        19: aload_0
        20: areturn
      LineNumberTable:
        line 441: 0
        line 442: 6
        line 443: 12
        line 444: 19
      LocalVariableTable:
        Start  Length  Slot  Name   Signature
            0      21     0  this   Lcoursier/util/shaded/org/jsoup/helper/HttpConnection$Base;
            0      21     1  name   Ljava/lang/String;
            0      21     2 value   Ljava/lang/String;
      LocalVariableTypeTable:
        Start  Length  Slot  Name   Signature
            0      21     0  this   Lcoursier/util/shaded/org/jsoup/helper/HttpConnection$Base<TT;>;
    Signature: #96                          // (Ljava/lang/String;Ljava/lang/String;)TT;

  public boolean hasHeader(java.lang.String);
    descriptor: (Ljava/lang/String;)Z
    flags: (0x0001) ACC_PUBLIC
    Code:
      stack=2, locals=2, args_size=2
         0: aload_1
         1: ldc           #158                // String Header name must not be empty
         3: invokestatic  #161                // Method coursier/util/shaded/org/jsoup/helper/Validate.notEmpty:(Ljava/lang/String;Ljava/lang/String;)V
         6: aload_0
         7: aload_1
         8: invokespecial #74                 // Method getHeadersCaseInsensitive:(Ljava/lang/String;)Ljava/util/List;
        11: invokeinterface #110,  1          // InterfaceMethod java/util/List.isEmpty:()Z
        16: ifne          23
        19: iconst_1
        20: goto          24
        23: iconst_0
        24: ireturn
      StackMapTable: number_of_entries = 2
        frame_type = 23 /* same */
        frame_type = 64 /* same_locals_1_stack_item */
          stack = [ int ]
      LineNumberTable:
        line 448: 0
        line 449: 6
      LocalVariableTable:
        Start  Length  Slot  Name   Signature
            0      25     0  this   Lcoursier/util/shaded/org/jsoup/helper/HttpConnection$Base;
            0      25     1  name   Ljava/lang/String;
      LocalVariableTypeTable:
        Start  Length  Slot  Name   Signature
            0      25     0  this   Lcoursier/util/shaded/org/jsoup/helper/HttpConnection$Base<TT;>;

  public boolean hasHeaderWithValue(java.lang.String, java.lang.String);
    descriptor: (Ljava/lang/String;Ljava/lang/String;)Z
    flags: (0x0001) ACC_PUBLIC
    Code:
      stack=2, locals=6, args_size=3
         0: aload_1
         1: invokestatic  #100                // Method coursier/util/shaded/org/jsoup/helper/Validate.notEmpty:(Ljava/lang/String;)V
         4: aload_2
         5: invokestatic  #100                // Method coursier/util/shaded/org/jsoup/helper/Validate.notEmpty:(Ljava/lang/String;)V
         8: aload_0
         9: aload_1
        10: invokevirtual #106                // Method headers:(Ljava/lang/String;)Ljava/util/List;
        13: astore_3
        14: aload_3
        15: invokeinterface #175,  1          // InterfaceMethod java/util/List.iterator:()Ljava/util/Iterator;
        20: astore        4
        22: aload         4
        24: invokeinterface #180,  1          // InterfaceMethod java/util/Iterator.hasNext:()Z
        29: ifeq          58
        32: aload         4
        34: invokeinterface #184,  1          // InterfaceMethod java/util/Iterator.next:()Ljava/lang/Object;
        39: checkcast     #104                // class java/lang/String
        42: astore        5
        44: aload_2
        45: aload         5
        47: invokevirtual #187                // Method java/lang/String.equalsIgnoreCase:(Ljava/lang/String;)Z
        50: ifeq          55
        53: iconst_1
        54: ireturn
        55: goto          22
        58: iconst_0
        59: ireturn
      StackMapTable: number_of_entries = 3
        frame_type = 253 /* append */
          offset_delta = 22
          locals = [ class java/util/List, class java/util/Iterator ]
        frame_type = 32 /* same */
        frame_type = 250 /* chop */
          offset_delta = 2
      LineNumberTable:
        line 456: 0
        line 457: 4
        line 458: 8
        line 459: 14
        line 460: 44
        line 461: 53
        line 462: 55
        line 463: 58
      LocalVariableTable:
        Start  Length  Slot  Name   Signature
           44      11     5 candidate   Ljava/lang/String;
            0      60     0  this   Lcoursier/util/shaded/org/jsoup/helper/HttpConnection$Base;
            0      60     1  name   Ljava/lang/String;
            0      60     2 value   Ljava/lang/String;
           14      46     3 values   Ljava/util/List;
      LocalVariableTypeTable:
        Start  Length  Slot  Name   Signature
            0      60     0  this   Lcoursier/util/shaded/org/jsoup/helper/HttpConnection$Base<TT;>;
           14      46     3 values   Ljava/util/List<Ljava/lang/String;>;

  public T removeHeader(java.lang.String);
    descriptor: (Ljava/lang/String;)Lcoursier/util/shaded/org/jsoup/Connection$Base;
    flags: (0x0001) ACC_PUBLIC
    Code:
      stack=2, locals=3, args_size=2
         0: aload_1
         1: ldc           #158                // String Header name must not be empty
         3: invokestatic  #161                // Method coursier/util/shaded/org/jsoup/helper/Validate.notEmpty:(Ljava/lang/String;Ljava/lang/String;)V
         6: aload_0
         7: aload_1
         8: invokespecial #193                // Method scanHeaders:(Ljava/lang/String;)Ljava/util/Map$Entry;
        11: astore_2
        12: aload_2
        13: ifnull        32
        16: aload_0
        17: getfield      #41                 // Field headers:Ljava/util/Map;
        20: aload_2
        21: invokeinterface #196,  1          // InterfaceMethod java/util/Map$Entry.getKey:()Ljava/lang/Object;
        26: invokeinterface #200,  2          // InterfaceMethod java/util/Map.remove:(Ljava/lang/Object;)Ljava/lang/Object;
        31: pop
        32: aload_0
        33: areturn
      StackMapTable: number_of_entries = 1
        frame_type = 252 /* append */
          offset_delta = 32
          locals = [ class java/util/Map$Entry ]
      LineNumberTable:
        line 467: 0
        line 468: 6
        line 469: 12
        line 470: 16
        line 471: 32
      LocalVariableTable:
        Start  Length  Slot  Name   Signature
            0      34     0  this   Lcoursier/util/shaded/org/jsoup/helper/HttpConnection$Base;
            0      34     1  name   Ljava/lang/String;
           12      22     2 entry   Ljava/util/Map$Entry;
      LocalVariableTypeTable:
        Start  Length  Slot  Name   Signature
            0      34     0  this   Lcoursier/util/shaded/org/jsoup/helper/HttpConnection$Base<TT;>;
           12      22     2 entry   Ljava/util/Map$Entry<Ljava/lang/String;Ljava/util/List<Ljava/lang/String;>;>;
    Signature: #189                         // (Ljava/lang/String;)TT;

  public java.util.Map<java.lang.String, java.lang.String> headers();
    descriptor: ()Ljava/util/Map;
    flags: (0x0001) ACC_PUBLIC
    Code:
      stack=4, locals=6, args_size=1
         0: new           #38                 // class java/util/LinkedHashMap
         3: dup
         4: aload_0
         5: getfield      #41                 // Field headers:Ljava/util/Map;
         8: invokeinterface #206,  1          // InterfaceMethod java/util/Map.size:()I
        13: invokespecial #209                // Method java/util/LinkedHashMap."<init>":(I)V
        16: astore_1
        17: aload_0
        18: getfield      #41                 // Field headers:Ljava/util/Map;
        21: invokeinterface #213,  1          // InterfaceMethod java/util/Map.entrySet:()Ljava/util/Set;
        26: invokeinterface #216,  1          // InterfaceMethod java/util/Set.iterator:()Ljava/util/Iterator;
        31: astore_2
        32: aload_2
        33: invokeinterface #180,  1          // InterfaceMethod java/util/Iterator.hasNext:()Z
        38: ifeq          101
        41: aload_2
        42: invokeinterface #184,  1          // InterfaceMethod java/util/Iterator.next:()Ljava/lang/Object;
        47: checkcast     #18                 // class java/util/Map$Entry
        50: astore_3
        51: aload_3
        52: invokeinterface #196,  1          // InterfaceMethod java/util/Map$Entry.getKey:()Ljava/lang/Object;
        57: checkcast     #104                // class java/lang/String
        60: astore        4
        62: aload_3
        63: invokeinterface #219,  1          // InterfaceMethod java/util/Map$Entry.getValue:()Ljava/lang/Object;
        68: checkcast     #76                 // class java/util/List
        71: astore        5
        73: aload         5
        75: invokeinterface #80,  1           // InterfaceMethod java/util/List.size:()I
        80: ifle          98
        83: aload_1
        84: aload         4
        86: aload         5
        88: iconst_0
        89: invokeinterface #223,  2          // InterfaceMethod java/util/List.get:(I)Ljava/lang/Object;
        94: invokevirtual #224                // Method java/util/LinkedHashMap.put:(Ljava/lang/Object;Ljava/lang/Object;)Ljava/lang/Object;
        97: pop
        98: goto          32
       101: aload_1
       102: areturn
      StackMapTable: number_of_entries = 3
        frame_type = 253 /* append */
          offset_delta = 32
          locals = [ class java/util/LinkedHashMap, class java/util/Iterator ]
        frame_type = 251 /* same_frame_extended */
          offset_delta = 65
        frame_type = 250 /* chop */
          offset_delta = 2
      LineNumberTable:
        line 475: 0
        line 476: 17
        line 477: 51
        line 478: 62
        line 479: 73
        line 480: 83
        line 481: 98
        line 482: 101
      LocalVariableTable:
        Start  Length  Slot  Name   Signature
           62      36     4 header   Ljava/lang/String;
           73      25     5 values   Ljava/util/List;
           51      47     3 entry   Ljava/util/Map$Entry;
            0     103     0  this   Lcoursier/util/shaded/org/jsoup/helper/HttpConnection$Base;
           17      86     1   map   Ljava/util/LinkedHashMap;
      LocalVariableTypeTable:
        Start  Length  Slot  Name   Signature
           73      25     5 values   Ljava/util/List<Ljava/lang/String;>;
           51      47     3 entry   Ljava/util/Map$Entry<Ljava/lang/String;Ljava/util/List<Ljava/lang/String;>;>;
            0     103     0  this   Lcoursier/util/shaded/org/jsoup/helper/HttpConnection$Base<TT;>;
           17      86     1   map   Ljava/util/LinkedHashMap<Ljava/lang/String;Ljava/lang/String;>;
    Signature: #205                         // ()Ljava/util/Map<Ljava/lang/String;Ljava/lang/String;>;

  public java.util.Map<java.lang.String, java.util.List<java.lang.String>> multiHeaders();
    descriptor: ()Ljava/util/Map;
    flags: (0x0001) ACC_PUBLIC
    Code:
      stack=1, locals=1, args_size=1
         0: aload_0
         1: getfield      #41                 // Field headers:Ljava/util/Map;
         4: areturn
      LineNumberTable:
        line 487: 0
      LocalVariableTable:
        Start  Length  Slot  Name   Signature
            0       5     0  this   Lcoursier/util/shaded/org/jsoup/helper/HttpConnection$Base;
      LocalVariableTypeTable:
        Start  Length  Slot  Name   Signature
            0       5     0  this   Lcoursier/util/shaded/org/jsoup/helper/HttpConnection$Base<TT;>;
    Signature: #229                         // ()Ljava/util/Map<Ljava/lang/String;Ljava/util/List<Ljava/lang/String;>;>;

  private java.util.List<java.lang.String> getHeadersCaseInsensitive(java.lang.String);
    descriptor: (Ljava/lang/String;)Ljava/util/List;
    flags: (0x0002) ACC_PRIVATE
    Code:
      stack=2, locals=4, args_size=2
         0: aload_1
         1: invokestatic  #232                // Method coursier/util/shaded/org/jsoup/helper/Validate.notNull:(Ljava/lang/Object;)V
         4: aload_0
         5: getfield      #41                 // Field headers:Ljava/util/Map;
         8: invokeinterface #213,  1          // InterfaceMethod java/util/Map.entrySet:()Ljava/util/Set;
        13: invokeinterface #216,  1          // InterfaceMethod java/util/Set.iterator:()Ljava/util/Iterator;
        18: astore_2
        19: aload_2
        20: invokeinterface #180,  1          // InterfaceMethod java/util/Iterator.hasNext:()Z
        25: ifeq          67
        28: aload_2
        29: invokeinterface #184,  1          // InterfaceMethod java/util/Iterator.next:()Ljava/lang/Object;
        34: checkcast     #18                 // class java/util/Map$Entry
        37: astore_3
        38: aload_1
        39: aload_3
        40: invokeinterface #196,  1          // InterfaceMethod java/util/Map$Entry.getKey:()Ljava/lang/Object;
        45: checkcast     #104                // class java/lang/String
        48: invokevirtual #187                // Method java/lang/String.equalsIgnoreCase:(Ljava/lang/String;)Z
        51: ifeq          64
        54: aload_3
        55: invokeinterface #219,  1          // InterfaceMethod java/util/Map$Entry.getValue:()Ljava/lang/Object;
        60: checkcast     #76                 // class java/util/List
        63: areturn
        64: goto          19
        67: invokestatic  #238                // Method java/util/Collections.emptyList:()Ljava/util/List;
        70: areturn
      StackMapTable: number_of_entries = 3
        frame_type = 252 /* append */
          offset_delta = 19
          locals = [ class java/util/Iterator ]
        frame_type = 44 /* same */
        frame_type = 250 /* chop */
          offset_delta = 2
      LineNumberTable:
        line 491: 0
        line 493: 4
        line 494: 38
        line 495: 54
        line 496: 64
        line 498: 67
      LocalVariableTable:
        Start  Length  Slot  Name   Signature
           38      26     3 entry   Ljava/util/Map$Entry;
            0      71     0  this   Lcoursier/util/shaded/org/jsoup/helper/HttpConnection$Base;
            0      71     1  name   Ljava/lang/String;
      LocalVariableTypeTable:
        Start  Length  Slot  Name   Signature
           38      26     3 entry   Ljava/util/Map$Entry<Ljava/lang/String;Ljava/util/List<Ljava/lang/String;>;>;
            0      71     0  this   Lcoursier/util/shaded/org/jsoup/helper/HttpConnection$Base<TT;>;
    Signature: #127                         // (Ljava/lang/String;)Ljava/util/List<Ljava/lang/String;>;

  private java.util.Map$Entry<java.lang.String, java.util.List<java.lang.String>> scanHeaders(java.lang.String);
    descriptor: (Ljava/lang/String;)Ljava/util/Map$Entry;
    flags: (0x0002) ACC_PRIVATE
    Code:
      stack=2, locals=5, args_size=2
         0: aload_1
         1: invokestatic  #244                // Method coursier/util/shaded/org/jsoup/internal/Normalizer.lowerCase:(Ljava/lang/String;)Ljava/lang/String;
         4: astore_2
         5: aload_0
         6: getfield      #41                 // Field headers:Ljava/util/Map;
         9: invokeinterface #213,  1          // InterfaceMethod java/util/Map.entrySet:()Ljava/util/Set;
        14: invokeinterface #216,  1          // InterfaceMethod java/util/Set.iterator:()Ljava/util/Iterator;
        19: astore_3
        20: aload_3
        21: invokeinterface #180,  1          // InterfaceMethod java/util/Iterator.hasNext:()Z
        26: ifeq          66
        29: aload_3
        30: invokeinterface #184,  1          // InterfaceMethod java/util/Iterator.next:()Ljava/lang/Object;
        35: checkcast     #18                 // class java/util/Map$Entry
        38: astore        4
        40: aload         4
        42: invokeinterface #196,  1          // InterfaceMethod java/util/Map$Entry.getKey:()Ljava/lang/Object;
        47: checkcast     #104                // class java/lang/String
        50: invokestatic  #244                // Method coursier/util/shaded/org/jsoup/internal/Normalizer.lowerCase:(Ljava/lang/String;)Ljava/lang/String;
        53: aload_2
        54: invokevirtual #247                // Method java/lang/String.equals:(Ljava/lang/Object;)Z
        57: ifeq          63
        60: aload         4
        62: areturn
        63: goto          20
        66: aconst_null
        67: areturn
      StackMapTable: number_of_entries = 3
        frame_type = 253 /* append */
          offset_delta = 20
          locals = [ class java/lang/String, class java/util/Iterator ]
        frame_type = 42 /* same */
        frame_type = 250 /* chop */
          offset_delta = 2
      LineNumberTable:
        line 502: 0
        line 503: 5
        line 504: 40
        line 505: 60
        line 506: 63
        line 507: 66
      LocalVariableTable:
        Start  Length  Slot  Name   Signature
           40      23     4 entry   Ljava/util/Map$Entry;
            0      68     0  this   Lcoursier/util/shaded/org/jsoup/helper/HttpConnection$Base;
            0      68     1  name   Ljava/lang/String;
            5      63     2    lc   Ljava/lang/String;
      LocalVariableTypeTable:
        Start  Length  Slot  Name   Signature
           40      23     4 entry   Ljava/util/Map$Entry<Ljava/lang/String;Ljava/util/List<Ljava/lang/String;>;>;
            0      68     0  this   Lcoursier/util/shaded/org/jsoup/helper/HttpConnection$Base<TT;>;
    Signature: #239                         // (Ljava/lang/String;)Ljava/util/Map$Entry<Ljava/lang/String;Ljava/util/List<Ljava/lang/String;>;>;

  public java.lang.String cookie(java.lang.String);
    descriptor: (Ljava/lang/String;)Ljava/lang/String;
    flags: (0x0001) ACC_PUBLIC
    Code:
      stack=2, locals=2, args_size=2
         0: aload_1
         1: ldc           #251                // String Cookie name must not be empty
         3: invokestatic  #161                // Method coursier/util/shaded/org/jsoup/helper/Validate.notEmpty:(Ljava/lang/String;Ljava/lang/String;)V
         6: aload_0
         7: getfield      #43                 // Field cookies:Ljava/util/Map;
        10: aload_1
        11: invokeinterface #253,  2          // InterfaceMethod java/util/Map.get:(Ljava/lang/Object;)Ljava/lang/Object;
        16: checkcast     #104                // class java/lang/String
        19: areturn
      LineNumberTable:
        line 511: 0
        line 512: 6
      LocalVariableTable:
        Start  Length  Slot  Name   Signature
            0      20     0  this   Lcoursier/util/shaded/org/jsoup/helper/HttpConnection$Base;
            0      20     1  name   Ljava/lang/String;
      LocalVariableTypeTable:
        Start  Length  Slot  Name   Signature
            0      20     0  this   Lcoursier/util/shaded/org/jsoup/helper/HttpConnection$Base<TT;>;

  public T cookie(java.lang.String, java.lang.String);
    descriptor: (Ljava/lang/String;Ljava/lang/String;)Lcoursier/util/shaded/org/jsoup/Connection$Base;
    flags: (0x0001) ACC_PUBLIC
    Code:
      stack=3, locals=3, args_size=3
         0: aload_1
         1: ldc           #251                // String Cookie name must not be empty
         3: invokestatic  #161                // Method coursier/util/shaded/org/jsoup/helper/Validate.notEmpty:(Ljava/lang/String;Ljava/lang/String;)V
         6: aload_2
         7: ldc           #255                // String Cookie value must not be null
         9: invokestatic  #59                 // Method coursier/util/shaded/org/jsoup/helper/Validate.notNull:(Ljava/lang/Object;Ljava/lang/String;)V
        12: aload_0
        13: getfield      #43                 // Field cookies:Ljava/util/Map;
        16: aload_1
        17: aload_2
        18: invokeinterface #117,  3          // InterfaceMethod java/util/Map.put:(Ljava/lang/Object;Ljava/lang/Object;)Ljava/lang/Object;
        23: pop
        24: aload_0
        25: areturn
      LineNumberTable:
        line 516: 0
        line 517: 6
        line 518: 12
        line 519: 24
      LocalVariableTable:
        Start  Length  Slot  Name   Signature
            0      26     0  this   Lcoursier/util/shaded/org/jsoup/helper/HttpConnection$Base;
            0      26     1  name   Ljava/lang/String;
            0      26     2 value   Ljava/lang/String;
      LocalVariableTypeTable:
        Start  Length  Slot  Name   Signature
            0      26     0  this   Lcoursier/util/shaded/org/jsoup/helper/HttpConnection$Base<TT;>;
    Signature: #96                          // (Ljava/lang/String;Ljava/lang/String;)TT;

  public boolean hasCookie(java.lang.String);
    descriptor: (Ljava/lang/String;)Z
    flags: (0x0001) ACC_PUBLIC
    Code:
      stack=2, locals=2, args_size=2
         0: aload_1
         1: ldc           #251                // String Cookie name must not be empty
         3: invokestatic  #161                // Method coursier/util/shaded/org/jsoup/helper/Validate.notEmpty:(Ljava/lang/String;Ljava/lang/String;)V
         6: aload_0
         7: getfield      #43                 // Field cookies:Ljava/util/Map;
        10: aload_1
        11: invokeinterface #259,  2          // InterfaceMethod java/util/Map.containsKey:(Ljava/lang/Object;)Z
        16: ireturn
      LineNumberTable:
        line 523: 0
        line 524: 6
      LocalVariableTable:
        Start  Length  Slot  Name   Signature
            0      17     0  this   Lcoursier/util/shaded/org/jsoup/helper/HttpConnection$Base;
            0      17     1  name   Ljava/lang/String;
      LocalVariableTypeTable:
        Start  Length  Slot  Name   Signature
            0      17     0  this   Lcoursier/util/shaded/org/jsoup/helper/HttpConnection$Base<TT;>;

  public T removeCookie(java.lang.String);
    descriptor: (Ljava/lang/String;)Lcoursier/util/shaded/org/jsoup/Connection$Base;
    flags: (0x0001) ACC_PUBLIC
    Code:
      stack=2, locals=2, args_size=2
         0: aload_1
         1: ldc           #251                // String Cookie name must not be empty
         3: invokestatic  #161                // Method coursier/util/shaded/org/jsoup/helper/Validate.notEmpty:(Ljava/lang/String;Ljava/lang/String;)V
         6: aload_0
         7: getfield      #43                 // Field cookies:Ljava/util/Map;
        10: aload_1
        11: invokeinterface #200,  2          // InterfaceMethod java/util/Map.remove:(Ljava/lang/Object;)Ljava/lang/Object;
        16: pop
        17: aload_0
        18: areturn
      LineNumberTable:
        line 528: 0
        line 529: 6
        line 530: 17
      LocalVariableTable:
        Start  Length  Slot  Name   Signature
            0      19     0  this   Lcoursier/util/shaded/org/jsoup/helper/HttpConnection$Base;
            0      19     1  name   Ljava/lang/String;
      LocalVariableTypeTable:
        Start  Length  Slot  Name   Signature
            0      19     0  this   Lcoursier/util/shaded/org/jsoup/helper/HttpConnection$Base<TT;>;
    Signature: #189                         // (Ljava/lang/String;)TT;

  public java.util.Map<java.lang.String, java.lang.String> cookies();
    descriptor: ()Ljava/util/Map;
    flags: (0x0001) ACC_PUBLIC
    Code:
      stack=1, locals=1, args_size=1
         0: aload_0
         1: getfield      #43                 // Field cookies:Ljava/util/Map;
         4: areturn
      LineNumberTable:
        line 534: 0
      LocalVariableTable:
        Start  Length  Slot  Name   Signature
            0       5     0  this   Lcoursier/util/shaded/org/jsoup/helper/HttpConnection$Base;
      LocalVariableTypeTable:
        Start  Length  Slot  Name   Signature
            0       5     0  this   Lcoursier/util/shaded/org/jsoup/helper/HttpConnection$Base<TT;>;
    Signature: #205                         // ()Ljava/util/Map<Ljava/lang/String;Ljava/lang/String;>;

  coursier.util.shaded.org.jsoup.helper.HttpConnection$Base(coursier.util.shaded.org.jsoup.helper.HttpConnection$1);
    descriptor: (Lcoursier/util/shaded/org/jsoup/helper/HttpConnection$1;)V
    flags: (0x1000) ACC_SYNTHETIC
    Code:
      stack=1, locals=2, args_size=2
         0: aload_0
         1: invokespecial #262                // Method "<init>":()V
         4: return
      LineNumberTable:
        line 325: 0
      LocalVariableTable:
        Start  Length  Slot  Name   Signature
            0       5     0  this   Lcoursier/util/shaded/org/jsoup/helper/HttpConnection$Base;
            0       5     1    x0   Lcoursier/util/shaded/org/jsoup/helper/HttpConnection$1;
      LocalVariableTypeTable:
        Start  Length  Slot  Name   Signature
            0       5     0  this   Lcoursier/util/shaded/org/jsoup/helper/HttpConnection$Base<TT;>;
}
InnerClasses:
  private static abstract #11= #2 of #10; // Base=class coursier/util/shaded/org/jsoup/helper/HttpConnection$Base of class coursier/util/shaded/org/jsoup/helper/HttpConnection
  public static final #16= #13 of #15;    // Method=class coursier/util/shaded/org/jsoup/Connection$Method of class coursier/util/shaded/org/jsoup/Connection
  public static #11= #7 of #15;           // Base=class coursier/util/shaded/org/jsoup/Connection$Base of class coursier/util/shaded/org/jsoup/Connection
  public static #21= #18 of #20;          // Entry=class java/util/Map$Entry of class java/util/Map
  static #23;                             // class coursier/util/shaded/org/jsoup/helper/HttpConnection$1
Signature: #3                           // <T::Lcoursier/util/shaded/org/jsoup/Connection$Base;>Ljava/lang/Object;Lcoursier/util/shaded/org/jsoup/Connection$Base<TT;>;
SourceFile: "HttpConnection.java"
