Classfile /Users/mw/Projects/slang-braindump/.jar/jar8/assemble/slang-braindump/assemble/content/org/apache/commons/lang3/text/translate/AggregateTranslator.class
  Last modified May 29, 2022; size 1293 bytes
  SHA-256 checksum b6149e3e7ab3bbb4d0adb035bf90edb7aad8506aa58bc0b2d9db628e6ba989c9
  Compiled from "AggregateTranslator.java"
public class org.apache.commons.lang3.text.translate.AggregateTranslator extends org.apache.commons.lang3.text.translate.CharSequenceTranslator
  minor version: 0
  major version: 52
  flags: (0x0021) ACC_PUBLIC, ACC_SUPER
  this_class: #6                          // org/apache/commons/lang3/text/translate/AggregateTranslator
  super_class: #7                         // org/apache/commons/lang3/text/translate/CharSequenceTranslator
  interfaces: 0, fields: 1, methods: 2, attributes: 3
Constant pool:
   #1 = Methodref          #7.#36         // org/apache/commons/lang3/text/translate/CharSequenceTranslator."<init>":()V
   #2 = Methodref          #37.#38        // org/apache/commons/lang3/ArrayUtils.clone:([Ljava/lang/Object;)[Ljava/lang/Object;
   #3 = Class              #9             // "[Lorg/apache/commons/lang3/text/translate/CharSequenceTranslator;"
   #4 = Fieldref           #6.#39         // org/apache/commons/lang3/text/translate/AggregateTranslator.translators:[Lorg/apache/commons/lang3/text/translate/CharSequenceTranslator;
   #5 = Methodref          #7.#40         // org/apache/commons/lang3/text/translate/CharSequenceTranslator.translate:(Ljava/lang/CharSequence;ILjava/io/Writer;)I
   #6 = Class              #41            // org/apache/commons/lang3/text/translate/AggregateTranslator
   #7 = Class              #42            // org/apache/commons/lang3/text/translate/CharSequenceTranslator
   #8 = Utf8               translators
   #9 = Utf8               [Lorg/apache/commons/lang3/text/translate/CharSequenceTranslator;
  #10 = Utf8               <init>
  #11 = Utf8               ([Lorg/apache/commons/lang3/text/translate/CharSequenceTranslator;)V
  #12 = Utf8               Code
  #13 = Utf8               LineNumberTable
  #14 = Utf8               LocalVariableTable
  #15 = Utf8               this
  #16 = Utf8               Lorg/apache/commons/lang3/text/translate/AggregateTranslator;
  #17 = Utf8               translate
  #18 = Utf8               (Ljava/lang/CharSequence;ILjava/io/Writer;)I
  #19 = Utf8               consumed
  #20 = Utf8               I
  #21 = Utf8               translator
  #22 = Utf8               Lorg/apache/commons/lang3/text/translate/CharSequenceTranslator;
  #23 = Utf8               input
  #24 = Utf8               Ljava/lang/CharSequence;
  #25 = Utf8               index
  #26 = Utf8               out
  #27 = Utf8               Ljava/io/Writer;
  #28 = Utf8               StackMapTable
  #29 = Utf8               Exceptions
  #30 = Class              #43            // java/io/IOException
  #31 = Utf8               SourceFile
  #32 = Utf8               AggregateTranslator.java
  #33 = Utf8               Deprecated
  #34 = Utf8               RuntimeVisibleAnnotations
  #35 = Utf8               Ljava/lang/Deprecated;
  #36 = NameAndType        #10:#44        // "<init>":()V
  #37 = Class              #45            // org/apache/commons/lang3/ArrayUtils
  #38 = NameAndType        #46:#47        // clone:([Ljava/lang/Object;)[Ljava/lang/Object;
  #39 = NameAndType        #8:#9          // translators:[Lorg/apache/commons/lang3/text/translate/CharSequenceTranslator;
  #40 = NameAndType        #17:#18        // translate:(Ljava/lang/CharSequence;ILjava/io/Writer;)I
  #41 = Utf8               org/apache/commons/lang3/text/translate/AggregateTranslator
  #42 = Utf8               org/apache/commons/lang3/text/translate/CharSequenceTranslator
  #43 = Utf8               java/io/IOException
  #44 = Utf8               ()V
  #45 = Utf8               org/apache/commons/lang3/ArrayUtils
  #46 = Utf8               clone
  #47 = Utf8               ([Ljava/lang/Object;)[Ljava/lang/Object;
{
  private final org.apache.commons.lang3.text.translate.CharSequenceTranslator[] translators;
    descriptor: [Lorg/apache/commons/lang3/text/translate/CharSequenceTranslator;
    flags: (0x0012) ACC_PRIVATE, ACC_FINAL

  public org.apache.commons.lang3.text.translate.AggregateTranslator(org.apache.commons.lang3.text.translate.CharSequenceTranslator...);
    descriptor: ([Lorg/apache/commons/lang3/text/translate/CharSequenceTranslator;)V
    flags: (0x0081) ACC_PUBLIC, ACC_VARARGS
    Code:
      stack=2, locals=2, args_size=2
         0: aload_0
         1: invokespecial #1                  // Method org/apache/commons/lang3/text/translate/CharSequenceTranslator."<init>":()V
         4: aload_0
         5: aload_1
         6: invokestatic  #2                  // Method org/apache/commons/lang3/ArrayUtils.clone:([Ljava/lang/Object;)[Ljava/lang/Object;
         9: checkcast     #3                  // class "[Lorg/apache/commons/lang3/text/translate/CharSequenceTranslator;"
        12: putfield      #4                  // Field translators:[Lorg/apache/commons/lang3/text/translate/CharSequenceTranslator;
        15: return
      LineNumberTable:
        line 43: 0
        line 44: 4
        line 45: 15
      LocalVariableTable:
        Start  Length  Slot  Name   Signature
            0      16     0  this   Lorg/apache/commons/lang3/text/translate/AggregateTranslator;
            0      16     1 translators   [Lorg/apache/commons/lang3/text/translate/CharSequenceTranslator;

  public int translate(java.lang.CharSequence, int, java.io.Writer) throws java.io.IOException;
    descriptor: (Ljava/lang/CharSequence;ILjava/io/Writer;)I
    flags: (0x0001) ACC_PUBLIC
    Code:
      stack=4, locals=9, args_size=4
         0: aload_0
         1: getfield      #4                  // Field translators:[Lorg/apache/commons/lang3/text/translate/CharSequenceTranslator;
         4: astore        4
         6: aload         4
         8: arraylength
         9: istore        5
        11: iconst_0
        12: istore        6
        14: iload         6
        16: iload         5
        18: if_icmpge     52
        21: aload         4
        23: iload         6
        25: aaload
        26: astore        7
        28: aload         7
        30: aload_1
        31: iload_2
        32: aload_3
        33: invokevirtual #5                  // Method org/apache/commons/lang3/text/translate/CharSequenceTranslator.translate:(Ljava/lang/CharSequence;ILjava/io/Writer;)I
        36: istore        8
        38: iload         8
        40: ifeq          46
        43: iload         8
        45: ireturn
        46: iinc          6, 1
        49: goto          14
        52: iconst_0
        53: ireturn
      LineNumberTable:
        line 54: 0
        line 55: 28
        line 56: 38
        line 57: 43
        line 54: 46
        line 60: 52
      LocalVariableTable:
        Start  Length  Slot  Name   Signature
           38       8     8 consumed   I
           28      18     7 translator   Lorg/apache/commons/lang3/text/translate/CharSequenceTranslator;
            0      54     0  this   Lorg/apache/commons/lang3/text/translate/AggregateTranslator;
            0      54     1 input   Ljava/lang/CharSequence;
            0      54     2 index   I
            0      54     3   out   Ljava/io/Writer;
      StackMapTable: number_of_entries = 3
        frame_type = 254 /* append */
          offset_delta = 14
          locals = [ class "[Lorg/apache/commons/lang3/text/translate/CharSequenceTranslator;", int, int ]
        frame_type = 31 /* same */
        frame_type = 248 /* chop */
          offset_delta = 5
    Exceptions:
      throws java.io.IOException
}
SourceFile: "AggregateTranslator.java"
Deprecated: true
RuntimeVisibleAnnotations:
  0: #35()
    java.lang.Deprecated
