Classfile /Users/mw/Projects/slang-braindump/.jar/jar8/assemble/slang-braindump/assemble/content/org/apache/commons/lang3/text/translate/EntityArrays.class
  Last modified May 29, 2022; size 12249 bytes
  SHA-256 checksum 10724f6deeca88cde9a9b5b3c6dfe6cef4496126cc4bfb220b3b32a1f0ed8b91
  Compiled from "EntityArrays.java"
public class org.apache.commons.lang3.text.translate.EntityArrays
  minor version: 0
  major version: 52
  flags: (0x0021) ACC_PUBLIC, ACC_SUPER
  this_class: #542                        // org/apache/commons/lang3/text/translate/EntityArrays
  super_class: #543                       // java/lang/Object
  interfaces: 0, fields: 10, methods: 13, attributes: 3
Constant pool:
     #1 = Methodref          #543.#576    // java/lang/Object."<init>":()V
     #2 = Fieldref           #542.#577    // org/apache/commons/lang3/text/translate/EntityArrays.ISO8859_1_ESCAPE:[[Ljava/lang/String;
     #3 = Methodref          #578.#579    // "[[Ljava/lang/String;".clone:()Ljava/lang/Object;
     #4 = Class              #545         // "[[Ljava/lang/String;"
     #5 = Fieldref           #542.#580    // org/apache/commons/lang3/text/translate/EntityArrays.ISO8859_1_UNESCAPE:[[Ljava/lang/String;
     #6 = Methodref          #581.#579    // "[[Ljava/lang/String;".clone:()Ljava/lang/Object;
     #7 = Fieldref           #542.#582    // org/apache/commons/lang3/text/translate/EntityArrays.HTML40_EXTENDED_ESCAPE:[[Ljava/lang/String;
     #8 = Methodref          #583.#579    // "[[Ljava/lang/String;".clone:()Ljava/lang/Object;
     #9 = Fieldref           #542.#584    // org/apache/commons/lang3/text/translate/EntityArrays.HTML40_EXTENDED_UNESCAPE:[[Ljava/lang/String;
    #10 = Methodref          #585.#579    // "[[Ljava/lang/String;".clone:()Ljava/lang/Object;
    #11 = Fieldref           #542.#586    // org/apache/commons/lang3/text/translate/EntityArrays.BASIC_ESCAPE:[[Ljava/lang/String;
    #12 = Methodref          #587.#579    // "[[Ljava/lang/String;".clone:()Ljava/lang/Object;
    #13 = Fieldref           #542.#588    // org/apache/commons/lang3/text/translate/EntityArrays.BASIC_UNESCAPE:[[Ljava/lang/String;
    #14 = Methodref          #589.#579    // "[[Ljava/lang/String;".clone:()Ljava/lang/Object;
    #15 = Fieldref           #542.#590    // org/apache/commons/lang3/text/translate/EntityArrays.APOS_ESCAPE:[[Ljava/lang/String;
    #16 = Methodref          #591.#579    // "[[Ljava/lang/String;".clone:()Ljava/lang/Object;
    #17 = Fieldref           #542.#592    // org/apache/commons/lang3/text/translate/EntityArrays.APOS_UNESCAPE:[[Ljava/lang/String;
    #18 = Methodref          #593.#579    // "[[Ljava/lang/String;".clone:()Ljava/lang/Object;
    #19 = Fieldref           #542.#594    // org/apache/commons/lang3/text/translate/EntityArrays.JAVA_CTRL_CHARS_ESCAPE:[[Ljava/lang/String;
    #20 = Methodref          #595.#579    // "[[Ljava/lang/String;".clone:()Ljava/lang/Object;
    #21 = Fieldref           #542.#596    // org/apache/commons/lang3/text/translate/EntityArrays.JAVA_CTRL_CHARS_UNESCAPE:[[Ljava/lang/String;
    #22 = Methodref          #597.#579    // "[[Ljava/lang/String;".clone:()Ljava/lang/Object;
    #23 = Class              #598         // "[Ljava/lang/String;"
    #24 = Class              #599         // java/lang/String
    #25 = String             #600         //  
    #26 = String             #601         // &nbsp;
    #27 = String             #602         // ¡
    #28 = String             #603         // &iexcl;
    #29 = String             #604         // ¢
    #30 = String             #605         // &cent;
    #31 = String             #606         // £
    #32 = String             #607         // &pound;
    #33 = String             #608         // ¤
    #34 = String             #609         // &curren;
    #35 = String             #610         // ¥
    #36 = String             #611         // &yen;
    #37 = String             #612         // ¦
    #38 = String             #613         // &brvbar;
    #39 = String             #614         // §
    #40 = String             #615         // &sect;
    #41 = String             #616         // ¨
    #42 = String             #617         // &uml;
    #43 = String             #618         // ©
    #44 = String             #619         // &copy;
    #45 = String             #620         // ª
    #46 = String             #621         // &ordf;
    #47 = String             #622         // «
    #48 = String             #623         // &laquo;
    #49 = String             #624         // ¬
    #50 = String             #625         // &not;
    #51 = String             #626         // ­
    #52 = String             #627         // &shy;
    #53 = String             #628         // ®
    #54 = String             #629         // &reg;
    #55 = String             #630         // ¯
    #56 = String             #631         // &macr;
    #57 = String             #632         // °
    #58 = String             #633         // &deg;
    #59 = String             #634         // ±
    #60 = String             #635         // &plusmn;
    #61 = String             #636         // ²
    #62 = String             #637         // &sup2;
    #63 = String             #638         // ³
    #64 = String             #639         // &sup3;
    #65 = String             #640         // ´
    #66 = String             #641         // &acute;
    #67 = String             #642         // µ
    #68 = String             #643         // &micro;
    #69 = String             #644         // ¶
    #70 = String             #645         // &para;
    #71 = String             #646         // ·
    #72 = String             #647         // &middot;
    #73 = String             #648         // ¸
    #74 = String             #649         // &cedil;
    #75 = String             #650         // ¹
    #76 = String             #651         // &sup1;
    #77 = String             #652         // º
    #78 = String             #653         // &ordm;
    #79 = String             #654         // »
    #80 = String             #655         // &raquo;
    #81 = String             #656         // ¼
    #82 = String             #657         // &frac14;
    #83 = String             #658         // ½
    #84 = String             #659         // &frac12;
    #85 = String             #660         // ¾
    #86 = String             #661         // &frac34;
    #87 = String             #662         // ¿
    #88 = String             #663         // &iquest;
    #89 = String             #664         // À
    #90 = String             #665         // &Agrave;
    #91 = String             #666         // Á
    #92 = String             #667         // &Aacute;
    #93 = String             #668         // Â
    #94 = String             #669         // &Acirc;
    #95 = String             #670         // Ã
    #96 = String             #671         // &Atilde;
    #97 = String             #672         // Ä
    #98 = String             #673         // &Auml;
    #99 = String             #674         // Å
   #100 = String             #675         // &Aring;
   #101 = String             #676         // Æ
   #102 = String             #677         // &AElig;
   #103 = String             #678         // Ç
   #104 = String             #679         // &Ccedil;
   #105 = String             #680         // È
   #106 = String             #681         // &Egrave;
   #107 = String             #682         // É
   #108 = String             #683         // &Eacute;
   #109 = String             #684         // Ê
   #110 = String             #685         // &Ecirc;
   #111 = String             #686         // Ë
   #112 = String             #687         // &Euml;
   #113 = String             #688         // Ì
   #114 = String             #689         // &Igrave;
   #115 = String             #690         // Í
   #116 = String             #691         // &Iacute;
   #117 = String             #692         // Î
   #118 = String             #693         // &Icirc;
   #119 = String             #694         // Ï
   #120 = String             #695         // &Iuml;
   #121 = String             #696         // Ð
   #122 = String             #697         // &ETH;
   #123 = String             #698         // Ñ
   #124 = String             #699         // &Ntilde;
   #125 = String             #700         // Ò
   #126 = String             #701         // &Ograve;
   #127 = String             #702         // Ó
   #128 = String             #703         // &Oacute;
   #129 = String             #704         // Ô
   #130 = String             #705         // &Ocirc;
   #131 = String             #706         // Õ
   #132 = String             #707         // &Otilde;
   #133 = String             #708         // Ö
   #134 = String             #709         // &Ouml;
   #135 = String             #710         // ×
   #136 = String             #711         // &times;
   #137 = String             #712         // Ø
   #138 = String             #713         // &Oslash;
   #139 = String             #714         // Ù
   #140 = String             #715         // &Ugrave;
   #141 = String             #716         // Ú
   #142 = String             #717         // &Uacute;
   #143 = String             #718         // Û
   #144 = String             #719         // &Ucirc;
   #145 = String             #720         // Ü
   #146 = String             #721         // &Uuml;
   #147 = String             #722         // Ý
   #148 = String             #723         // &Yacute;
   #149 = String             #724         // Þ
   #150 = String             #725         // &THORN;
   #151 = String             #726         // ß
   #152 = String             #727         // &szlig;
   #153 = String             #728         // à
   #154 = String             #729         // &agrave;
   #155 = String             #730         // á
   #156 = String             #731         // &aacute;
   #157 = String             #732         // â
   #158 = String             #733         // &acirc;
   #159 = String             #734         // ã
   #160 = String             #735         // &atilde;
   #161 = String             #736         // ä
   #162 = String             #737         // &auml;
   #163 = String             #738         // å
   #164 = String             #739         // &aring;
   #165 = String             #740         // æ
   #166 = String             #741         // &aelig;
   #167 = String             #742         // ç
   #168 = String             #743         // &ccedil;
   #169 = String             #744         // è
   #170 = String             #745         // &egrave;
   #171 = String             #746         // é
   #172 = String             #747         // &eacute;
   #173 = String             #748         // ê
   #174 = String             #749         // &ecirc;
   #175 = String             #750         // ë
   #176 = String             #751         // &euml;
   #177 = String             #752         // ì
   #178 = String             #753         // &igrave;
   #179 = String             #754         // í
   #180 = String             #755         // &iacute;
   #181 = String             #756         // î
   #182 = String             #757         // &icirc;
   #183 = String             #758         // ï
   #184 = String             #759         // &iuml;
   #185 = String             #760         // ð
   #186 = String             #761         // &eth;
   #187 = String             #762         // ñ
   #188 = String             #763         // &ntilde;
   #189 = String             #764         // ò
   #190 = String             #765         // &ograve;
   #191 = String             #766         // ó
   #192 = String             #767         // &oacute;
   #193 = String             #768         // ô
   #194 = String             #769         // &ocirc;
   #195 = String             #770         // õ
   #196 = String             #771         // &otilde;
   #197 = String             #772         // ö
   #198 = String             #773         // &ouml;
   #199 = String             #774         // ÷
   #200 = String             #775         // &divide;
   #201 = String             #776         // ø
   #202 = String             #777         // &oslash;
   #203 = String             #778         // ù
   #204 = String             #779         // &ugrave;
   #205 = String             #780         // ú
   #206 = String             #781         // &uacute;
   #207 = String             #782         // û
   #208 = String             #783         // &ucirc;
   #209 = String             #784         // ü
   #210 = String             #785         // &uuml;
   #211 = String             #786         // ý
   #212 = String             #787         // &yacute;
   #213 = String             #788         // þ
   #214 = String             #789         // &thorn;
   #215 = String             #790         // ÿ
   #216 = String             #791         // &yuml;
   #217 = Methodref          #542.#792    // org/apache/commons/lang3/text/translate/EntityArrays.invert:([[Ljava/lang/String;)[[Ljava/lang/String;
   #218 = String             #793         // ƒ
   #219 = String             #794         // &fnof;
   #220 = String             #795         // Α
   #221 = String             #796         // &Alpha;
   #222 = String             #797         // Β
   #223 = String             #798         // &Beta;
   #224 = String             #799         // Γ
   #225 = String             #800         // &Gamma;
   #226 = String             #801         // Δ
   #227 = String             #802         // &Delta;
   #228 = String             #803         // Ε
   #229 = String             #804         // &Epsilon;
   #230 = String             #805         // Ζ
   #231 = String             #806         // &Zeta;
   #232 = String             #807         // Η
   #233 = String             #808         // &Eta;
   #234 = String             #809         // Θ
   #235 = String             #810         // &Theta;
   #236 = String             #811         // Ι
   #237 = String             #812         // &Iota;
   #238 = String             #813         // Κ
   #239 = String             #814         // &Kappa;
   #240 = String             #815         // Λ
   #241 = String             #816         // &Lambda;
   #242 = String             #817         // Μ
   #243 = String             #818         // &Mu;
   #244 = String             #819         // Ν
   #245 = String             #820         // &Nu;
   #246 = String             #821         // Ξ
   #247 = String             #822         // &Xi;
   #248 = String             #823         // Ο
   #249 = String             #824         // &Omicron;
   #250 = String             #825         // Π
   #251 = String             #826         // &Pi;
   #252 = String             #827         // Ρ
   #253 = String             #828         // &Rho;
   #254 = String             #829         // Σ
   #255 = String             #830         // &Sigma;
   #256 = String             #831         // Τ
   #257 = String             #832         // &Tau;
   #258 = String             #833         // Υ
   #259 = String             #834         // &Upsilon;
   #260 = String             #835         // Φ
   #261 = String             #836         // &Phi;
   #262 = String             #837         // Χ
   #263 = String             #838         // &Chi;
   #264 = String             #839         // Ψ
   #265 = String             #840         // &Psi;
   #266 = String             #841         // Ω
   #267 = String             #842         // &Omega;
   #268 = String             #843         // α
   #269 = String             #844         // &alpha;
   #270 = String             #845         // β
   #271 = String             #846         // &beta;
   #272 = String             #847         // γ
   #273 = String             #848         // &gamma;
   #274 = String             #849         // δ
   #275 = String             #850         // &delta;
   #276 = String             #851         // ε
   #277 = String             #852         // &epsilon;
   #278 = String             #853         // ζ
   #279 = String             #854         // &zeta;
   #280 = String             #855         // η
   #281 = String             #856         // &eta;
   #282 = String             #857         // θ
   #283 = String             #858         // &theta;
   #284 = String             #859         // ι
   #285 = String             #860         // &iota;
   #286 = String             #861         // κ
   #287 = String             #862         // &kappa;
   #288 = String             #863         // λ
   #289 = String             #864         // &lambda;
   #290 = String             #865         // μ
   #291 = String             #866         // &mu;
   #292 = String             #867         // ν
   #293 = String             #868         // &nu;
   #294 = String             #869         // ξ
   #295 = String             #870         // &xi;
   #296 = String             #871         // ο
   #297 = String             #872         // &omicron;
   #298 = String             #873         // π
   #299 = String             #874         // &pi;
   #300 = String             #875         // ρ
   #301 = String             #876         // &rho;
   #302 = String             #877         // ς
   #303 = String             #878         // &sigmaf;
   #304 = String             #879         // σ
   #305 = String             #880         // &sigma;
   #306 = String             #881         // τ
   #307 = String             #882         // &tau;
   #308 = String             #883         // υ
   #309 = String             #884         // &upsilon;
   #310 = String             #885         // φ
   #311 = String             #886         // &phi;
   #312 = String             #887         // χ
   #313 = String             #888         // &chi;
   #314 = String             #889         // ψ
   #315 = String             #890         // &psi;
   #316 = String             #891         // ω
   #317 = String             #892         // &omega;
   #318 = String             #893         // ϑ
   #319 = String             #894         // &thetasym;
   #320 = String             #895         // ϒ
   #321 = String             #896         // &upsih;
   #322 = String             #897         // ϖ
   #323 = String             #898         // &piv;
   #324 = String             #899         // •
   #325 = String             #900         // &bull;
   #326 = String             #901         // …
   #327 = String             #902         // &hellip;
   #328 = String             #903         // ′
   #329 = String             #904         // &prime;
   #330 = String             #905         // ″
   #331 = String             #906         // &Prime;
   #332 = String             #907         // ‾
   #333 = String             #908         // &oline;
   #334 = String             #909         // ⁄
   #335 = String             #910         // &frasl;
   #336 = String             #911         // ℘
   #337 = String             #912         // &weierp;
   #338 = String             #913         // ℑ
   #339 = String             #914         // &image;
   #340 = String             #915         // ℜ
   #341 = String             #916         // &real;
   #342 = String             #917         // ™
   #343 = String             #918         // &trade;
   #344 = String             #919         // ℵ
   #345 = String             #920         // &alefsym;
   #346 = String             #921         // ←
   #347 = String             #922         // &larr;
   #348 = String             #923         // ↑
   #349 = String             #924         // &uarr;
   #350 = String             #925         // →
   #351 = String             #926         // &rarr;
   #352 = String             #927         // ↓
   #353 = String             #928         // &darr;
   #354 = String             #929         // ↔
   #355 = String             #930         // &harr;
   #356 = String             #931         // ↵
   #357 = String             #932         // &crarr;
   #358 = String             #933         // ⇐
   #359 = String             #934         // &lArr;
   #360 = String             #935         // ⇑
   #361 = String             #936         // &uArr;
   #362 = String             #937         // ⇒
   #363 = String             #938         // &rArr;
   #364 = String             #939         // ⇓
   #365 = String             #940         // &dArr;
   #366 = String             #941         // ⇔
   #367 = String             #942         // &hArr;
   #368 = String             #943         // ∀
   #369 = String             #944         // &forall;
   #370 = String             #945         // ∂
   #371 = String             #946         // &part;
   #372 = String             #947         // ∃
   #373 = String             #948         // &exist;
   #374 = String             #949         // ∅
   #375 = String             #950         // &empty;
   #376 = String             #951         // ∇
   #377 = String             #952         // &nabla;
   #378 = String             #953         // ∈
   #379 = String             #954         // &isin;
   #380 = String             #955         // ∉
   #381 = String             #956         // &notin;
   #382 = String             #957         // ∋
   #383 = String             #958         // &ni;
   #384 = String             #959         // ∏
   #385 = String             #960         // &prod;
   #386 = String             #961         // ∑
   #387 = String             #962         // &sum;
   #388 = String             #963         // −
   #389 = String             #964         // &minus;
   #390 = String             #965         // ∗
   #391 = String             #966         // &lowast;
   #392 = String             #967         // √
   #393 = String             #968         // &radic;
   #394 = String             #969         // ∝
   #395 = String             #970         // &prop;
   #396 = String             #971         // ∞
   #397 = String             #972         // &infin;
   #398 = String             #973         // ∠
   #399 = String             #974         // &ang;
   #400 = String             #975         // ∧
   #401 = String             #976         // &and;
   #402 = String             #977         // ∨
   #403 = String             #978         // &or;
   #404 = String             #979         // ∩
   #405 = String             #980         // &cap;
   #406 = String             #981         // ∪
   #407 = String             #982         // &cup;
   #408 = String             #983         // ∫
   #409 = String             #984         // &int;
   #410 = String             #985         // ∴
   #411 = String             #986         // &there4;
   #412 = String             #987         // ∼
   #413 = String             #988         // &sim;
   #414 = String             #989         // ≅
   #415 = String             #990         // &cong;
   #416 = String             #991         // ≈
   #417 = String             #992         // &asymp;
   #418 = String             #993         // ≠
   #419 = String             #994         // &ne;
   #420 = String             #995         // ≡
   #421 = String             #996         // &equiv;
   #422 = String             #997         // ≤
   #423 = String             #998         // &le;
   #424 = String             #999         // ≥
   #425 = String             #1000        // &ge;
   #426 = String             #1001        // ⊂
   #427 = String             #1002        // &sub;
   #428 = String             #1003        // ⊃
   #429 = String             #1004        // &sup;
   #430 = String             #1005        // ⊄
   #431 = String             #1006        // &nsub;
   #432 = String             #1007        // ⊆
   #433 = String             #1008        // &sube;
   #434 = String             #1009        // ⊇
   #435 = String             #1010        // &supe;
   #436 = String             #1011        // ⊕
   #437 = String             #1012        // &oplus;
   #438 = String             #1013        // ⊗
   #439 = String             #1014        // &otimes;
   #440 = String             #1015        // ⊥
   #441 = String             #1016        // &perp;
   #442 = String             #1017        // ⋅
   #443 = String             #1018        // &sdot;
   #444 = String             #1019        // ⌈
   #445 = String             #1020        // &lceil;
   #446 = String             #1021        // ⌉
   #447 = String             #1022        // &rceil;
   #448 = String             #1023        // ⌊
   #449 = String             #1024        // &lfloor;
   #450 = String             #1025        // ⌋
   #451 = String             #1026        // &rfloor;
   #452 = String             #1027        // 〈
   #453 = String             #1028        // &lang;
   #454 = String             #1029        // 〉
   #455 = String             #1030        // &rang;
   #456 = String             #1031        // ◊
   #457 = String             #1032        // &loz;
   #458 = String             #1033        // ♠
   #459 = String             #1034        // &spades;
   #460 = String             #1035        // ♣
   #461 = String             #1036        // &clubs;
   #462 = String             #1037        // ♥
   #463 = String             #1038        // &hearts;
   #464 = String             #1039        // ♦
   #465 = String             #1040        // &diams;
   #466 = String             #1041        // Œ
   #467 = String             #1042        // &OElig;
   #468 = String             #1043        // œ
   #469 = String             #1044        // &oelig;
   #470 = String             #1045        // Š
   #471 = String             #1046        // &Scaron;
   #472 = String             #1047        // š
   #473 = String             #1048        // &scaron;
   #474 = String             #1049        // Ÿ
   #475 = String             #1050        // &Yuml;
   #476 = String             #1051        // ˆ
   #477 = String             #1052        // &circ;
   #478 = String             #1053        // ˜
   #479 = String             #1054        // &tilde;
   #480 = String             #1055        //  
   #481 = String             #1056        // &ensp;
   #482 = String             #1057        //  
   #483 = String             #1058        // &emsp;
   #484 = String             #1059        //  
   #485 = String             #1060        // &thinsp;
   #486 = String             #1061        // ‌
   #487 = String             #1062        // &zwnj;
   #488 = String             #1063        // ‍
   #489 = String             #1064        // &zwj;
   #490 = String             #1065        // ‎
   #491 = String             #1066        // &lrm;
   #492 = String             #1067        // ‏
   #493 = String             #1068        // &rlm;
   #494 = String             #1069        // –
   #495 = String             #1070        // &ndash;
   #496 = String             #1071        // —
   #497 = String             #1072        // &mdash;
   #498 = String             #1073        // ‘
   #499 = String             #1074        // &lsquo;
   #500 = String             #1075        // ’
   #501 = String             #1076        // &rsquo;
   #502 = String             #1077        // ‚
   #503 = String             #1078        // &sbquo;
   #504 = String             #1079        // “
   #505 = String             #1080        // &ldquo;
   #506 = String             #1081        // ”
   #507 = String             #1082        // &rdquo;
   #508 = String             #1083        // „
   #509 = String             #1084        // &bdquo;
   #510 = String             #1085        // †
   #511 = String             #1086        // &dagger;
   #512 = String             #1087        // ‡
   #513 = String             #1088        // &Dagger;
   #514 = String             #1089        // ‰
   #515 = String             #1090        // &permil;
   #516 = String             #1091        // ‹
   #517 = String             #1092        // &lsaquo;
   #518 = String             #1093        // ›
   #519 = String             #1094        // &rsaquo;
   #520 = String             #1095        // €
   #521 = String             #1096        // &euro;
   #522 = String             #1097        // \"
   #523 = String             #1098        // &quot;
   #524 = String             #1099        // &
   #525 = String             #1100        // &amp;
   #526 = String             #1101        // <
   #527 = String             #1102        // &lt;
   #528 = String             #1103        // >
   #529 = String             #1104        // &gt;
   #530 = String             #1105        // \'
   #531 = String             #1106        // &apos;
   #532 = String             #1107        // \b
   #533 = String             #1108        // \\b
   #534 = String             #1109        // \n
   #535 = String             #1110        // \\n
   #536 = String             #1111        // \t
   #537 = String             #1112        // \\t
   #538 = String             #1113        // \f
   #539 = String             #1114        // \\f
   #540 = String             #1115        // \r
   #541 = String             #1116        // \\r
   #542 = Class              #1117        // org/apache/commons/lang3/text/translate/EntityArrays
   #543 = Class              #1118        // java/lang/Object
   #544 = Utf8               ISO8859_1_ESCAPE
   #545 = Utf8               [[Ljava/lang/String;
   #546 = Utf8               ISO8859_1_UNESCAPE
   #547 = Utf8               HTML40_EXTENDED_ESCAPE
   #548 = Utf8               HTML40_EXTENDED_UNESCAPE
   #549 = Utf8               BASIC_ESCAPE
   #550 = Utf8               BASIC_UNESCAPE
   #551 = Utf8               APOS_ESCAPE
   #552 = Utf8               APOS_UNESCAPE
   #553 = Utf8               JAVA_CTRL_CHARS_ESCAPE
   #554 = Utf8               JAVA_CTRL_CHARS_UNESCAPE
   #555 = Utf8               <init>
   #556 = Utf8               ()V
   #557 = Utf8               Code
   #558 = Utf8               LineNumberTable
   #559 = Utf8               LocalVariableTable
   #560 = Utf8               this
   #561 = Utf8               Lorg/apache/commons/lang3/text/translate/EntityArrays;
   #562 = Utf8               ()[[Ljava/lang/String;
   #563 = Utf8               invert
   #564 = Utf8               ([[Ljava/lang/String;)[[Ljava/lang/String;
   #565 = Utf8               i
   #566 = Utf8               I
   #567 = Utf8               array
   #568 = Utf8               newarray
   #569 = Utf8               StackMapTable
   #570 = Utf8               <clinit>
   #571 = Utf8               SourceFile
   #572 = Utf8               EntityArrays.java
   #573 = Utf8               Deprecated
   #574 = Utf8               RuntimeVisibleAnnotations
   #575 = Utf8               Ljava/lang/Deprecated;
   #576 = NameAndType        #555:#556    // "<init>":()V
   #577 = NameAndType        #544:#545    // ISO8859_1_ESCAPE:[[Ljava/lang/String;
   #578 = Class              #545         // "[[Ljava/lang/String;"
   #579 = NameAndType        #1119:#1120  // clone:()Ljava/lang/Object;
   #580 = NameAndType        #546:#545    // ISO8859_1_UNESCAPE:[[Ljava/lang/String;
   #581 = Class              #545         // "[[Ljava/lang/String;"
   #582 = NameAndType        #547:#545    // HTML40_EXTENDED_ESCAPE:[[Ljava/lang/String;
   #583 = Class              #545         // "[[Ljava/lang/String;"
   #584 = NameAndType        #548:#545    // HTML40_EXTENDED_UNESCAPE:[[Ljava/lang/String;
   #585 = Class              #545         // "[[Ljava/lang/String;"
   #586 = NameAndType        #549:#545    // BASIC_ESCAPE:[[Ljava/lang/String;
   #587 = Class              #545         // "[[Ljava/lang/String;"
   #588 = NameAndType        #550:#545    // BASIC_UNESCAPE:[[Ljava/lang/String;
   #589 = Class              #545         // "[[Ljava/lang/String;"
   #590 = NameAndType        #551:#545    // APOS_ESCAPE:[[Ljava/lang/String;
   #591 = Class              #545         // "[[Ljava/lang/String;"
   #592 = NameAndType        #552:#545    // APOS_UNESCAPE:[[Ljava/lang/String;
   #593 = Class              #545         // "[[Ljava/lang/String;"
   #594 = NameAndType        #553:#545    // JAVA_CTRL_CHARS_ESCAPE:[[Ljava/lang/String;
   #595 = Class              #545         // "[[Ljava/lang/String;"
   #596 = NameAndType        #554:#545    // JAVA_CTRL_CHARS_UNESCAPE:[[Ljava/lang/String;
   #597 = Class              #545         // "[[Ljava/lang/String;"
   #598 = Utf8               [Ljava/lang/String;
   #599 = Utf8               java/lang/String
   #600 = Utf8                
   #601 = Utf8               &nbsp;
   #602 = Utf8               ¡
   #603 = Utf8               &iexcl;
   #604 = Utf8               ¢
   #605 = Utf8               &cent;
   #606 = Utf8               £
   #607 = Utf8               &pound;
   #608 = Utf8               ¤
   #609 = Utf8               &curren;
   #610 = Utf8               ¥
   #611 = Utf8               &yen;
   #612 = Utf8               ¦
   #613 = Utf8               &brvbar;
   #614 = Utf8               §
   #615 = Utf8               &sect;
   #616 = Utf8               ¨
   #617 = Utf8               &uml;
   #618 = Utf8               ©
   #619 = Utf8               &copy;
   #620 = Utf8               ª
   #621 = Utf8               &ordf;
   #622 = Utf8               «
   #623 = Utf8               &laquo;
   #624 = Utf8               ¬
   #625 = Utf8               &not;
   #626 = Utf8               ­
   #627 = Utf8               &shy;
   #628 = Utf8               ®
   #629 = Utf8               &reg;
   #630 = Utf8               ¯
   #631 = Utf8               &macr;
   #632 = Utf8               °
   #633 = Utf8               &deg;
   #634 = Utf8               ±
   #635 = Utf8               &plusmn;
   #636 = Utf8               ²
   #637 = Utf8               &sup2;
   #638 = Utf8               ³
   #639 = Utf8               &sup3;
   #640 = Utf8               ´
   #641 = Utf8               &acute;
   #642 = Utf8               µ
   #643 = Utf8               &micro;
   #644 = Utf8               ¶
   #645 = Utf8               &para;
   #646 = Utf8               ·
   #647 = Utf8               &middot;
   #648 = Utf8               ¸
   #649 = Utf8               &cedil;
   #650 = Utf8               ¹
   #651 = Utf8               &sup1;
   #652 = Utf8               º
   #653 = Utf8               &ordm;
   #654 = Utf8               »
   #655 = Utf8               &raquo;
   #656 = Utf8               ¼
   #657 = Utf8               &frac14;
   #658 = Utf8               ½
   #659 = Utf8               &frac12;
   #660 = Utf8               ¾
   #661 = Utf8               &frac34;
   #662 = Utf8               ¿
   #663 = Utf8               &iquest;
   #664 = Utf8               À
   #665 = Utf8               &Agrave;
   #666 = Utf8               Á
   #667 = Utf8               &Aacute;
   #668 = Utf8               Â
   #669 = Utf8               &Acirc;
   #670 = Utf8               Ã
   #671 = Utf8               &Atilde;
   #672 = Utf8               Ä
   #673 = Utf8               &Auml;
   #674 = Utf8               Å
   #675 = Utf8               &Aring;
   #676 = Utf8               Æ
   #677 = Utf8               &AElig;
   #678 = Utf8               Ç
   #679 = Utf8               &Ccedil;
   #680 = Utf8               È
   #681 = Utf8               &Egrave;
   #682 = Utf8               É
   #683 = Utf8               &Eacute;
   #684 = Utf8               Ê
   #685 = Utf8               &Ecirc;
   #686 = Utf8               Ë
   #687 = Utf8               &Euml;
   #688 = Utf8               Ì
   #689 = Utf8               &Igrave;
   #690 = Utf8               Í
   #691 = Utf8               &Iacute;
   #692 = Utf8               Î
   #693 = Utf8               &Icirc;
   #694 = Utf8               Ï
   #695 = Utf8               &Iuml;
   #696 = Utf8               Ð
   #697 = Utf8               &ETH;
   #698 = Utf8               Ñ
   #699 = Utf8               &Ntilde;
   #700 = Utf8               Ò
   #701 = Utf8               &Ograve;
   #702 = Utf8               Ó
   #703 = Utf8               &Oacute;
   #704 = Utf8               Ô
   #705 = Utf8               &Ocirc;
   #706 = Utf8               Õ
   #707 = Utf8               &Otilde;
   #708 = Utf8               Ö
   #709 = Utf8               &Ouml;
   #710 = Utf8               ×
   #711 = Utf8               &times;
   #712 = Utf8               Ø
   #713 = Utf8               &Oslash;
   #714 = Utf8               Ù
   #715 = Utf8               &Ugrave;
   #716 = Utf8               Ú
   #717 = Utf8               &Uacute;
   #718 = Utf8               Û
   #719 = Utf8               &Ucirc;
   #720 = Utf8               Ü
   #721 = Utf8               &Uuml;
   #722 = Utf8               Ý
   #723 = Utf8               &Yacute;
   #724 = Utf8               Þ
   #725 = Utf8               &THORN;
   #726 = Utf8               ß
   #727 = Utf8               &szlig;
   #728 = Utf8               à
   #729 = Utf8               &agrave;
   #730 = Utf8               á
   #731 = Utf8               &aacute;
   #732 = Utf8               â
   #733 = Utf8               &acirc;
   #734 = Utf8               ã
   #735 = Utf8               &atilde;
   #736 = Utf8               ä
   #737 = Utf8               &auml;
   #738 = Utf8               å
   #739 = Utf8               &aring;
   #740 = Utf8               æ
   #741 = Utf8               &aelig;
   #742 = Utf8               ç
   #743 = Utf8               &ccedil;
   #744 = Utf8               è
   #745 = Utf8               &egrave;
   #746 = Utf8               é
   #747 = Utf8               &eacute;
   #748 = Utf8               ê
   #749 = Utf8               &ecirc;
   #750 = Utf8               ë
   #751 = Utf8               &euml;
   #752 = Utf8               ì
   #753 = Utf8               &igrave;
   #754 = Utf8               í
   #755 = Utf8               &iacute;
   #756 = Utf8               î
   #757 = Utf8               &icirc;
   #758 = Utf8               ï
   #759 = Utf8               &iuml;
   #760 = Utf8               ð
   #761 = Utf8               &eth;
   #762 = Utf8               ñ
   #763 = Utf8               &ntilde;
   #764 = Utf8               ò
   #765 = Utf8               &ograve;
   #766 = Utf8               ó
   #767 = Utf8               &oacute;
   #768 = Utf8               ô
   #769 = Utf8               &ocirc;
   #770 = Utf8               õ
   #771 = Utf8               &otilde;
   #772 = Utf8               ö
   #773 = Utf8               &ouml;
   #774 = Utf8               ÷
   #775 = Utf8               &divide;
   #776 = Utf8               ø
   #777 = Utf8               &oslash;
   #778 = Utf8               ù
   #779 = Utf8               &ugrave;
   #780 = Utf8               ú
   #781 = Utf8               &uacute;
   #782 = Utf8               û
   #783 = Utf8               &ucirc;
   #784 = Utf8               ü
   #785 = Utf8               &uuml;
   #786 = Utf8               ý
   #787 = Utf8               &yacute;
   #788 = Utf8               þ
   #789 = Utf8               &thorn;
   #790 = Utf8               ÿ
   #791 = Utf8               &yuml;
   #792 = NameAndType        #563:#564    // invert:([[Ljava/lang/String;)[[Ljava/lang/String;
   #793 = Utf8               ƒ
   #794 = Utf8               &fnof;
   #795 = Utf8               Α
   #796 = Utf8               &Alpha;
   #797 = Utf8               Β
   #798 = Utf8               &Beta;
   #799 = Utf8               Γ
   #800 = Utf8               &Gamma;
   #801 = Utf8               Δ
   #802 = Utf8               &Delta;
   #803 = Utf8               Ε
   #804 = Utf8               &Epsilon;
   #805 = Utf8               Ζ
   #806 = Utf8               &Zeta;
   #807 = Utf8               Η
   #808 = Utf8               &Eta;
   #809 = Utf8               Θ
   #810 = Utf8               &Theta;
   #811 = Utf8               Ι
   #812 = Utf8               &Iota;
   #813 = Utf8               Κ
   #814 = Utf8               &Kappa;
   #815 = Utf8               Λ
   #816 = Utf8               &Lambda;
   #817 = Utf8               Μ
   #818 = Utf8               &Mu;
   #819 = Utf8               Ν
   #820 = Utf8               &Nu;
   #821 = Utf8               Ξ
   #822 = Utf8               &Xi;
   #823 = Utf8               Ο
   #824 = Utf8               &Omicron;
   #825 = Utf8               Π
   #826 = Utf8               &Pi;
   #827 = Utf8               Ρ
   #828 = Utf8               &Rho;
   #829 = Utf8               Σ
   #830 = Utf8               &Sigma;
   #831 = Utf8               Τ
   #832 = Utf8               &Tau;
   #833 = Utf8               Υ
   #834 = Utf8               &Upsilon;
   #835 = Utf8               Φ
   #836 = Utf8               &Phi;
   #837 = Utf8               Χ
   #838 = Utf8               &Chi;
   #839 = Utf8               Ψ
   #840 = Utf8               &Psi;
   #841 = Utf8               Ω
   #842 = Utf8               &Omega;
   #843 = Utf8               α
   #844 = Utf8               &alpha;
   #845 = Utf8               β
   #846 = Utf8               &beta;
   #847 = Utf8               γ
   #848 = Utf8               &gamma;
   #849 = Utf8               δ
   #850 = Utf8               &delta;
   #851 = Utf8               ε
   #852 = Utf8               &epsilon;
   #853 = Utf8               ζ
   #854 = Utf8               &zeta;
   #855 = Utf8               η
   #856 = Utf8               &eta;
   #857 = Utf8               θ
   #858 = Utf8               &theta;
   #859 = Utf8               ι
   #860 = Utf8               &iota;
   #861 = Utf8               κ
   #862 = Utf8               &kappa;
   #863 = Utf8               λ
   #864 = Utf8               &lambda;
   #865 = Utf8               μ
   #866 = Utf8               &mu;
   #867 = Utf8               ν
   #868 = Utf8               &nu;
   #869 = Utf8               ξ
   #870 = Utf8               &xi;
   #871 = Utf8               ο
   #872 = Utf8               &omicron;
   #873 = Utf8               π
   #874 = Utf8               &pi;
   #875 = Utf8               ρ
   #876 = Utf8               &rho;
   #877 = Utf8               ς
   #878 = Utf8               &sigmaf;
   #879 = Utf8               σ
   #880 = Utf8               &sigma;
   #881 = Utf8               τ
   #882 = Utf8               &tau;
   #883 = Utf8               υ
   #884 = Utf8               &upsilon;
   #885 = Utf8               φ
   #886 = Utf8               &phi;
   #887 = Utf8               χ
   #888 = Utf8               &chi;
   #889 = Utf8               ψ
   #890 = Utf8               &psi;
   #891 = Utf8               ω
   #892 = Utf8               &omega;
   #893 = Utf8               ϑ
   #894 = Utf8               &thetasym;
   #895 = Utf8               ϒ
   #896 = Utf8               &upsih;
   #897 = Utf8               ϖ
   #898 = Utf8               &piv;
   #899 = Utf8               •
   #900 = Utf8               &bull;
   #901 = Utf8               …
   #902 = Utf8               &hellip;
   #903 = Utf8               ′
   #904 = Utf8               &prime;
   #905 = Utf8               ″
   #906 = Utf8               &Prime;
   #907 = Utf8               ‾
   #908 = Utf8               &oline;
   #909 = Utf8               ⁄
   #910 = Utf8               &frasl;
   #911 = Utf8               ℘
   #912 = Utf8               &weierp;
   #913 = Utf8               ℑ
   #914 = Utf8               &image;
   #915 = Utf8               ℜ
   #916 = Utf8               &real;
   #917 = Utf8               ™
   #918 = Utf8               &trade;
   #919 = Utf8               ℵ
   #920 = Utf8               &alefsym;
   #921 = Utf8               ←
   #922 = Utf8               &larr;
   #923 = Utf8               ↑
   #924 = Utf8               &uarr;
   #925 = Utf8               →
   #926 = Utf8               &rarr;
   #927 = Utf8               ↓
   #928 = Utf8               &darr;
   #929 = Utf8               ↔
   #930 = Utf8               &harr;
   #931 = Utf8               ↵
   #932 = Utf8               &crarr;
   #933 = Utf8               ⇐
   #934 = Utf8               &lArr;
   #935 = Utf8               ⇑
   #936 = Utf8               &uArr;
   #937 = Utf8               ⇒
   #938 = Utf8               &rArr;
   #939 = Utf8               ⇓
   #940 = Utf8               &dArr;
   #941 = Utf8               ⇔
   #942 = Utf8               &hArr;
   #943 = Utf8               ∀
   #944 = Utf8               &forall;
   #945 = Utf8               ∂
   #946 = Utf8               &part;
   #947 = Utf8               ∃
   #948 = Utf8               &exist;
   #949 = Utf8               ∅
   #950 = Utf8               &empty;
   #951 = Utf8               ∇
   #952 = Utf8               &nabla;
   #953 = Utf8               ∈
   #954 = Utf8               &isin;
   #955 = Utf8               ∉
   #956 = Utf8               &notin;
   #957 = Utf8               ∋
   #958 = Utf8               &ni;
   #959 = Utf8               ∏
   #960 = Utf8               &prod;
   #961 = Utf8               ∑
   #962 = Utf8               &sum;
   #963 = Utf8               −
   #964 = Utf8               &minus;
   #965 = Utf8               ∗
   #966 = Utf8               &lowast;
   #967 = Utf8               √
   #968 = Utf8               &radic;
   #969 = Utf8               ∝
   #970 = Utf8               &prop;
   #971 = Utf8               ∞
   #972 = Utf8               &infin;
   #973 = Utf8               ∠
   #974 = Utf8               &ang;
   #975 = Utf8               ∧
   #976 = Utf8               &and;
   #977 = Utf8               ∨
   #978 = Utf8               &or;
   #979 = Utf8               ∩
   #980 = Utf8               &cap;
   #981 = Utf8               ∪
   #982 = Utf8               &cup;
   #983 = Utf8               ∫
   #984 = Utf8               &int;
   #985 = Utf8               ∴
   #986 = Utf8               &there4;
   #987 = Utf8               ∼
   #988 = Utf8               &sim;
   #989 = Utf8               ≅
   #990 = Utf8               &cong;
   #991 = Utf8               ≈
   #992 = Utf8               &asymp;
   #993 = Utf8               ≠
   #994 = Utf8               &ne;
   #995 = Utf8               ≡
   #996 = Utf8               &equiv;
   #997 = Utf8               ≤
   #998 = Utf8               &le;
   #999 = Utf8               ≥
  #1000 = Utf8               &ge;
  #1001 = Utf8               ⊂
  #1002 = Utf8               &sub;
  #1003 = Utf8               ⊃
  #1004 = Utf8               &sup;
  #1005 = Utf8               ⊄
  #1006 = Utf8               &nsub;
  #1007 = Utf8               ⊆
  #1008 = Utf8               &sube;
  #1009 = Utf8               ⊇
  #1010 = Utf8               &supe;
  #1011 = Utf8               ⊕
  #1012 = Utf8               &oplus;
  #1013 = Utf8               ⊗
  #1014 = Utf8               &otimes;
  #1015 = Utf8               ⊥
  #1016 = Utf8               &perp;
  #1017 = Utf8               ⋅
  #1018 = Utf8               &sdot;
  #1019 = Utf8               ⌈
  #1020 = Utf8               &lceil;
  #1021 = Utf8               ⌉
  #1022 = Utf8               &rceil;
  #1023 = Utf8               ⌊
  #1024 = Utf8               &lfloor;
  #1025 = Utf8               ⌋
  #1026 = Utf8               &rfloor;
  #1027 = Utf8               〈
  #1028 = Utf8               &lang;
  #1029 = Utf8               〉
  #1030 = Utf8               &rang;
  #1031 = Utf8               ◊
  #1032 = Utf8               &loz;
  #1033 = Utf8               ♠
  #1034 = Utf8               &spades;
  #1035 = Utf8               ♣
  #1036 = Utf8               &clubs;
  #1037 = Utf8               ♥
  #1038 = Utf8               &hearts;
  #1039 = Utf8               ♦
  #1040 = Utf8               &diams;
  #1041 = Utf8               Œ
  #1042 = Utf8               &OElig;
  #1043 = Utf8               œ
  #1044 = Utf8               &oelig;
  #1045 = Utf8               Š
  #1046 = Utf8               &Scaron;
  #1047 = Utf8               š
  #1048 = Utf8               &scaron;
  #1049 = Utf8               Ÿ
  #1050 = Utf8               &Yuml;
  #1051 = Utf8               ˆ
  #1052 = Utf8               &circ;
  #1053 = Utf8               ˜
  #1054 = Utf8               &tilde;
  #1055 = Utf8                
  #1056 = Utf8               &ensp;
  #1057 = Utf8                
  #1058 = Utf8               &emsp;
  #1059 = Utf8                
  #1060 = Utf8               &thinsp;
  #1061 = Utf8               ‌
  #1062 = Utf8               &zwnj;
  #1063 = Utf8               ‍
  #1064 = Utf8               &zwj;
  #1065 = Utf8               ‎
  #1066 = Utf8               &lrm;
  #1067 = Utf8               ‏
  #1068 = Utf8               &rlm;
  #1069 = Utf8               –
  #1070 = Utf8               &ndash;
  #1071 = Utf8               —
  #1072 = Utf8               &mdash;
  #1073 = Utf8               ‘
  #1074 = Utf8               &lsquo;
  #1075 = Utf8               ’
  #1076 = Utf8               &rsquo;
  #1077 = Utf8               ‚
  #1078 = Utf8               &sbquo;
  #1079 = Utf8               “
  #1080 = Utf8               &ldquo;
  #1081 = Utf8               ”
  #1082 = Utf8               &rdquo;
  #1083 = Utf8               „
  #1084 = Utf8               &bdquo;
  #1085 = Utf8               †
  #1086 = Utf8               &dagger;
  #1087 = Utf8               ‡
  #1088 = Utf8               &Dagger;
  #1089 = Utf8               ‰
  #1090 = Utf8               &permil;
  #1091 = Utf8               ‹
  #1092 = Utf8               &lsaquo;
  #1093 = Utf8               ›
  #1094 = Utf8               &rsaquo;
  #1095 = Utf8               €
  #1096 = Utf8               &euro;
  #1097 = Utf8               \"
  #1098 = Utf8               &quot;
  #1099 = Utf8               &
  #1100 = Utf8               &amp;
  #1101 = Utf8               <
  #1102 = Utf8               &lt;
  #1103 = Utf8               >
  #1104 = Utf8               &gt;
  #1105 = Utf8               \'
  #1106 = Utf8               &apos;
  #1107 = Utf8               \b
  #1108 = Utf8               \\b
  #1109 = Utf8               \n
  #1110 = Utf8               \\n
  #1111 = Utf8               \t
  #1112 = Utf8               \\t
  #1113 = Utf8               \f
  #1114 = Utf8               \\f
  #1115 = Utf8               \r
  #1116 = Utf8               \\r
  #1117 = Utf8               org/apache/commons/lang3/text/translate/EntityArrays
  #1118 = Utf8               java/lang/Object
  #1119 = Utf8               clone
  #1120 = Utf8               ()Ljava/lang/Object;
{
  private static final java.lang.String[][] ISO8859_1_ESCAPE;
    descriptor: [[Ljava/lang/String;
    flags: (0x001a) ACC_PRIVATE, ACC_STATIC, ACC_FINAL

  private static final java.lang.String[][] ISO8859_1_UNESCAPE;
    descriptor: [[Ljava/lang/String;
    flags: (0x001a) ACC_PRIVATE, ACC_STATIC, ACC_FINAL

  private static final java.lang.String[][] HTML40_EXTENDED_ESCAPE;
    descriptor: [[Ljava/lang/String;
    flags: (0x001a) ACC_PRIVATE, ACC_STATIC, ACC_FINAL

  private static final java.lang.String[][] HTML40_EXTENDED_UNESCAPE;
    descriptor: [[Ljava/lang/String;
    flags: (0x001a) ACC_PRIVATE, ACC_STATIC, ACC_FINAL

  private static final java.lang.String[][] BASIC_ESCAPE;
    descriptor: [[Ljava/lang/String;
    flags: (0x001a) ACC_PRIVATE, ACC_STATIC, ACC_FINAL

  private static final java.lang.String[][] BASIC_UNESCAPE;
    descriptor: [[Ljava/lang/String;
    flags: (0x001a) ACC_PRIVATE, ACC_STATIC, ACC_FINAL

  private static final java.lang.String[][] APOS_ESCAPE;
    descriptor: [[Ljava/lang/String;
    flags: (0x001a) ACC_PRIVATE, ACC_STATIC, ACC_FINAL

  private static final java.lang.String[][] APOS_UNESCAPE;
    descriptor: [[Ljava/lang/String;
    flags: (0x001a) ACC_PRIVATE, ACC_STATIC, ACC_FINAL

  private static final java.lang.String[][] JAVA_CTRL_CHARS_ESCAPE;
    descriptor: [[Ljava/lang/String;
    flags: (0x001a) ACC_PRIVATE, ACC_STATIC, ACC_FINAL

  private static final java.lang.String[][] JAVA_CTRL_CHARS_UNESCAPE;
    descriptor: [[Ljava/lang/String;
    flags: (0x001a) ACC_PRIVATE, ACC_STATIC, ACC_FINAL

  public org.apache.commons.lang3.text.translate.EntityArrays();
    descriptor: ()V
    flags: (0x0001) ACC_PUBLIC
    Code:
      stack=1, locals=1, args_size=1
         0: aload_0
         1: invokespecial #1                  // Method java/lang/Object."<init>":()V
         4: return
      LineNumberTable:
        line 30: 0
      LocalVariableTable:
        Start  Length  Slot  Name   Signature
            0       5     0  this   Lorg/apache/commons/lang3/text/translate/EntityArrays;

  public static java.lang.String[][] ISO8859_1_ESCAPE();
    descriptor: ()[[Ljava/lang/String;
    flags: (0x0009) ACC_PUBLIC, ACC_STATIC
    Code:
      stack=1, locals=0, args_size=0
         0: getstatic     #2                  // Field ISO8859_1_ESCAPE:[[Ljava/lang/String;
         3: invokevirtual #3                  // Method "[[Ljava/lang/String;".clone:()Ljava/lang/Object;
         6: checkcast     #4                  // class "[[Ljava/lang/String;"
         9: areturn
      LineNumberTable:
        line 38: 0

  public static java.lang.String[][] ISO8859_1_UNESCAPE();
    descriptor: ()[[Ljava/lang/String;
    flags: (0x0009) ACC_PUBLIC, ACC_STATIC
    Code:
      stack=1, locals=0, args_size=0
         0: getstatic     #5                  // Field ISO8859_1_UNESCAPE:[[Ljava/lang/String;
         3: invokevirtual #6                  // Method "[[Ljava/lang/String;".clone:()Ljava/lang/Object;
         6: checkcast     #4                  // class "[[Ljava/lang/String;"
         9: areturn
      LineNumberTable:
        line 145: 0

  public static java.lang.String[][] HTML40_EXTENDED_ESCAPE();
    descriptor: ()[[Ljava/lang/String;
    flags: (0x0009) ACC_PUBLIC, ACC_STATIC
    Code:
      stack=1, locals=0, args_size=0
         0: getstatic     #7                  // Field HTML40_EXTENDED_ESCAPE:[[Ljava/lang/String;
         3: invokevirtual #8                  // Method "[[Ljava/lang/String;".clone:()Ljava/lang/Object;
         6: checkcast     #4                  // class "[[Ljava/lang/String;"
         9: areturn
      LineNumberTable:
        line 157: 0

  public static java.lang.String[][] HTML40_EXTENDED_UNESCAPE();
    descriptor: ()[[Ljava/lang/String;
    flags: (0x0009) ACC_PUBLIC, ACC_STATIC
    Code:
      stack=1, locals=0, args_size=0
         0: getstatic     #9                  // Field HTML40_EXTENDED_UNESCAPE:[[Ljava/lang/String;
         3: invokevirtual #10                 // Method "[[Ljava/lang/String;".clone:()Ljava/lang/Object;
         6: checkcast     #4                  // class "[[Ljava/lang/String;"
         9: areturn
      LineNumberTable:
        line 362: 0

  public static java.lang.String[][] BASIC_ESCAPE();
    descriptor: ()[[Ljava/lang/String;
    flags: (0x0009) ACC_PUBLIC, ACC_STATIC
    Code:
      stack=1, locals=0, args_size=0
         0: getstatic     #11                 // Field BASIC_ESCAPE:[[Ljava/lang/String;
         3: invokevirtual #12                 // Method "[[Ljava/lang/String;".clone:()Ljava/lang/Object;
         6: checkcast     #4                  // class "[[Ljava/lang/String;"
         9: areturn
      LineNumberTable:
        line 374: 0

  public static java.lang.String[][] BASIC_UNESCAPE();
    descriptor: ()[[Ljava/lang/String;
    flags: (0x0009) ACC_PUBLIC, ACC_STATIC
    Code:
      stack=1, locals=0, args_size=0
         0: getstatic     #13                 // Field BASIC_UNESCAPE:[[Ljava/lang/String;
         3: invokevirtual #14                 // Method "[[Ljava/lang/String;".clone:()Ljava/lang/Object;
         6: checkcast     #4                  // class "[[Ljava/lang/String;"
         9: areturn
      LineNumberTable:
        line 389: 0

  public static java.lang.String[][] APOS_ESCAPE();
    descriptor: ()[[Ljava/lang/String;
    flags: (0x0009) ACC_PUBLIC, ACC_STATIC
    Code:
      stack=1, locals=0, args_size=0
         0: getstatic     #15                 // Field APOS_ESCAPE:[[Ljava/lang/String;
         3: invokevirtual #16                 // Method "[[Ljava/lang/String;".clone:()Ljava/lang/Object;
         6: checkcast     #4                  // class "[[Ljava/lang/String;"
         9: areturn
      LineNumberTable:
        line 399: 0

  public static java.lang.String[][] APOS_UNESCAPE();
    descriptor: ()[[Ljava/lang/String;
    flags: (0x0009) ACC_PUBLIC, ACC_STATIC
    Code:
      stack=1, locals=0, args_size=0
         0: getstatic     #17                 // Field APOS_UNESCAPE:[[Ljava/lang/String;
         3: invokevirtual #18                 // Method "[[Ljava/lang/String;".clone:()Ljava/lang/Object;
         6: checkcast     #4                  // class "[[Ljava/lang/String;"
         9: areturn
      LineNumberTable:
        line 411: 0

  public static java.lang.String[][] JAVA_CTRL_CHARS_ESCAPE();
    descriptor: ()[[Ljava/lang/String;
    flags: (0x0009) ACC_PUBLIC, ACC_STATIC
    Code:
      stack=1, locals=0, args_size=0
         0: getstatic     #19                 // Field JAVA_CTRL_CHARS_ESCAPE:[[Ljava/lang/String;
         3: invokevirtual #20                 // Method "[[Ljava/lang/String;".clone:()Ljava/lang/Object;
         6: checkcast     #4                  // class "[[Ljava/lang/String;"
         9: areturn
      LineNumberTable:
        line 423: 0

  public static java.lang.String[][] JAVA_CTRL_CHARS_UNESCAPE();
    descriptor: ()[[Ljava/lang/String;
    flags: (0x0009) ACC_PUBLIC, ACC_STATIC
    Code:
      stack=1, locals=0, args_size=0
         0: getstatic     #21                 // Field JAVA_CTRL_CHARS_UNESCAPE:[[Ljava/lang/String;
         3: invokevirtual #22                 // Method "[[Ljava/lang/String;".clone:()Ljava/lang/Object;
         6: checkcast     #4                  // class "[[Ljava/lang/String;"
         9: areturn
      LineNumberTable:
        line 439: 0

  public static java.lang.String[][] invert(java.lang.String[][]);
    descriptor: ([[Ljava/lang/String;)[[Ljava/lang/String;
    flags: (0x0009) ACC_PUBLIC, ACC_STATIC
    Code:
      stack=4, locals=3, args_size=1
         0: aload_0
         1: arraylength
         2: iconst_2
         3: multianewarray #4,  2             // class "[[Ljava/lang/String;"
         7: astore_1
         8: iconst_0
         9: istore_2
        10: iload_2
        11: aload_0
        12: arraylength
        13: if_icmpge     42
        16: aload_1
        17: iload_2
        18: aaload
        19: iconst_0
        20: aload_0
        21: iload_2
        22: aaload
        23: iconst_1
        24: aaload
        25: aastore
        26: aload_1
        27: iload_2
        28: aaload
        29: iconst_1
        30: aload_0
        31: iload_2
        32: aaload
        33: iconst_0
        34: aaload
        35: aastore
        36: iinc          2, 1
        39: goto          10
        42: aload_1
        43: areturn
      LineNumberTable:
        line 450: 0
        line 451: 8
        line 452: 16
        line 453: 26
        line 451: 36
        line 455: 42
      LocalVariableTable:
        Start  Length  Slot  Name   Signature
           10      32     2     i   I
            0      44     0 array   [[Ljava/lang/String;
            8      36     1 newarray   [[Ljava/lang/String;
      StackMapTable: number_of_entries = 2
        frame_type = 253 /* append */
          offset_delta = 10
          locals = [ class "[[Ljava/lang/String;", int ]
        frame_type = 250 /* chop */
          offset_delta = 31

  static {};
    descriptor: ()V
    flags: (0x0008) ACC_STATIC
    Code:
      stack=7, locals=0, args_size=0
         0: bipush        96
         2: anewarray     #23                 // class "[Ljava/lang/String;"
         5: dup
         6: iconst_0
         7: iconst_2
         8: anewarray     #24                 // class java/lang/String
        11: dup
        12: iconst_0
        13: ldc           #25                 // String  
        15: aastore
        16: dup
        17: iconst_1
        18: ldc           #26                 // String &nbsp;
        20: aastore
        21: aastore
        22: dup
        23: iconst_1
        24: iconst_2
        25: anewarray     #24                 // class java/lang/String
        28: dup
        29: iconst_0
        30: ldc           #27                 // String ¡
        32: aastore
        33: dup
        34: iconst_1
        35: ldc           #28                 // String &iexcl;
        37: aastore
        38: aastore
        39: dup
        40: iconst_2
        41: iconst_2
        42: anewarray     #24                 // class java/lang/String
        45: dup
        46: iconst_0
        47: ldc           #29                 // String ¢
        49: aastore
        50: dup
        51: iconst_1
        52: ldc           #30                 // String &cent;
        54: aastore
        55: aastore
        56: dup
        57: iconst_3
        58: iconst_2
        59: anewarray     #24                 // class java/lang/String
        62: dup
        63: iconst_0
        64: ldc           #31                 // String £
        66: aastore
        67: dup
        68: iconst_1
        69: ldc           #32                 // String &pound;
        71: aastore
        72: aastore
        73: dup
        74: iconst_4
        75: iconst_2
        76: anewarray     #24                 // class java/lang/String
        79: dup
        80: iconst_0
        81: ldc           #33                 // String ¤
        83: aastore
        84: dup
        85: iconst_1
        86: ldc           #34                 // String &curren;
        88: aastore
        89: aastore
        90: dup
        91: iconst_5
        92: iconst_2
        93: anewarray     #24                 // class java/lang/String
        96: dup
        97: iconst_0
        98: ldc           #35                 // String ¥
       100: aastore
       101: dup
       102: iconst_1
       103: ldc           #36                 // String &yen;
       105: aastore
       106: aastore
       107: dup
       108: bipush        6
       110: iconst_2
       111: anewarray     #24                 // class java/lang/String
       114: dup
       115: iconst_0
       116: ldc           #37                 // String ¦
       118: aastore
       119: dup
       120: iconst_1
       121: ldc           #38                 // String &brvbar;
       123: aastore
       124: aastore
       125: dup
       126: bipush        7
       128: iconst_2
       129: anewarray     #24                 // class java/lang/String
       132: dup
       133: iconst_0
       134: ldc           #39                 // String §
       136: aastore
       137: dup
       138: iconst_1
       139: ldc           #40                 // String &sect;
       141: aastore
       142: aastore
       143: dup
       144: bipush        8
       146: iconst_2
       147: anewarray     #24                 // class java/lang/String
       150: dup
       151: iconst_0
       152: ldc           #41                 // String ¨
       154: aastore
       155: dup
       156: iconst_1
       157: ldc           #42                 // String &uml;
       159: aastore
       160: aastore
       161: dup
       162: bipush        9
       164: iconst_2
       165: anewarray     #24                 // class java/lang/String
       168: dup
       169: iconst_0
       170: ldc           #43                 // String ©
       172: aastore
       173: dup
       174: iconst_1
       175: ldc           #44                 // String &copy;
       177: aastore
       178: aastore
       179: dup
       180: bipush        10
       182: iconst_2
       183: anewarray     #24                 // class java/lang/String
       186: dup
       187: iconst_0
       188: ldc           #45                 // String ª
       190: aastore
       191: dup
       192: iconst_1
       193: ldc           #46                 // String &ordf;
       195: aastore
       196: aastore
       197: dup
       198: bipush        11
       200: iconst_2
       201: anewarray     #24                 // class java/lang/String
       204: dup
       205: iconst_0
       206: ldc           #47                 // String «
       208: aastore
       209: dup
       210: iconst_1
       211: ldc           #48                 // String &laquo;
       213: aastore
       214: aastore
       215: dup
       216: bipush        12
       218: iconst_2
       219: anewarray     #24                 // class java/lang/String
       222: dup
       223: iconst_0
       224: ldc           #49                 // String ¬
       226: aastore
       227: dup
       228: iconst_1
       229: ldc           #50                 // String &not;
       231: aastore
       232: aastore
       233: dup
       234: bipush        13
       236: iconst_2
       237: anewarray     #24                 // class java/lang/String
       240: dup
       241: iconst_0
       242: ldc           #51                 // String ­
       244: aastore
       245: dup
       246: iconst_1
       247: ldc           #52                 // String &shy;
       249: aastore
       250: aastore
       251: dup
       252: bipush        14
       254: iconst_2
       255: anewarray     #24                 // class java/lang/String
       258: dup
       259: iconst_0
       260: ldc           #53                 // String ®
       262: aastore
       263: dup
       264: iconst_1
       265: ldc           #54                 // String &reg;
       267: aastore
       268: aastore
       269: dup
       270: bipush        15
       272: iconst_2
       273: anewarray     #24                 // class java/lang/String
       276: dup
       277: iconst_0
       278: ldc           #55                 // String ¯
       280: aastore
       281: dup
       282: iconst_1
       283: ldc           #56                 // String &macr;
       285: aastore
       286: aastore
       287: dup
       288: bipush        16
       290: iconst_2
       291: anewarray     #24                 // class java/lang/String
       294: dup
       295: iconst_0
       296: ldc           #57                 // String °
       298: aastore
       299: dup
       300: iconst_1
       301: ldc           #58                 // String &deg;
       303: aastore
       304: aastore
       305: dup
       306: bipush        17
       308: iconst_2
       309: anewarray     #24                 // class java/lang/String
       312: dup
       313: iconst_0
       314: ldc           #59                 // String ±
       316: aastore
       317: dup
       318: iconst_1
       319: ldc           #60                 // String &plusmn;
       321: aastore
       322: aastore
       323: dup
       324: bipush        18
       326: iconst_2
       327: anewarray     #24                 // class java/lang/String
       330: dup
       331: iconst_0
       332: ldc           #61                 // String ²
       334: aastore
       335: dup
       336: iconst_1
       337: ldc           #62                 // String &sup2;
       339: aastore
       340: aastore
       341: dup
       342: bipush        19
       344: iconst_2
       345: anewarray     #24                 // class java/lang/String
       348: dup
       349: iconst_0
       350: ldc           #63                 // String ³
       352: aastore
       353: dup
       354: iconst_1
       355: ldc           #64                 // String &sup3;
       357: aastore
       358: aastore
       359: dup
       360: bipush        20
       362: iconst_2
       363: anewarray     #24                 // class java/lang/String
       366: dup
       367: iconst_0
       368: ldc           #65                 // String ´
       370: aastore
       371: dup
       372: iconst_1
       373: ldc           #66                 // String &acute;
       375: aastore
       376: aastore
       377: dup
       378: bipush        21
       380: iconst_2
       381: anewarray     #24                 // class java/lang/String
       384: dup
       385: iconst_0
       386: ldc           #67                 // String µ
       388: aastore
       389: dup
       390: iconst_1
       391: ldc           #68                 // String &micro;
       393: aastore
       394: aastore
       395: dup
       396: bipush        22
       398: iconst_2
       399: anewarray     #24                 // class java/lang/String
       402: dup
       403: iconst_0
       404: ldc           #69                 // String ¶
       406: aastore
       407: dup
       408: iconst_1
       409: ldc           #70                 // String &para;
       411: aastore
       412: aastore
       413: dup
       414: bipush        23
       416: iconst_2
       417: anewarray     #24                 // class java/lang/String
       420: dup
       421: iconst_0
       422: ldc           #71                 // String ·
       424: aastore
       425: dup
       426: iconst_1
       427: ldc           #72                 // String &middot;
       429: aastore
       430: aastore
       431: dup
       432: bipush        24
       434: iconst_2
       435: anewarray     #24                 // class java/lang/String
       438: dup
       439: iconst_0
       440: ldc           #73                 // String ¸
       442: aastore
       443: dup
       444: iconst_1
       445: ldc           #74                 // String &cedil;
       447: aastore
       448: aastore
       449: dup
       450: bipush        25
       452: iconst_2
       453: anewarray     #24                 // class java/lang/String
       456: dup
       457: iconst_0
       458: ldc           #75                 // String ¹
       460: aastore
       461: dup
       462: iconst_1
       463: ldc           #76                 // String &sup1;
       465: aastore
       466: aastore
       467: dup
       468: bipush        26
       470: iconst_2
       471: anewarray     #24                 // class java/lang/String
       474: dup
       475: iconst_0
       476: ldc           #77                 // String º
       478: aastore
       479: dup
       480: iconst_1
       481: ldc           #78                 // String &ordm;
       483: aastore
       484: aastore
       485: dup
       486: bipush        27
       488: iconst_2
       489: anewarray     #24                 // class java/lang/String
       492: dup
       493: iconst_0
       494: ldc           #79                 // String »
       496: aastore
       497: dup
       498: iconst_1
       499: ldc           #80                 // String &raquo;
       501: aastore
       502: aastore
       503: dup
       504: bipush        28
       506: iconst_2
       507: anewarray     #24                 // class java/lang/String
       510: dup
       511: iconst_0
       512: ldc           #81                 // String ¼
       514: aastore
       515: dup
       516: iconst_1
       517: ldc           #82                 // String &frac14;
       519: aastore
       520: aastore
       521: dup
       522: bipush        29
       524: iconst_2
       525: anewarray     #24                 // class java/lang/String
       528: dup
       529: iconst_0
       530: ldc           #83                 // String ½
       532: aastore
       533: dup
       534: iconst_1
       535: ldc           #84                 // String &frac12;
       537: aastore
       538: aastore
       539: dup
       540: bipush        30
       542: iconst_2
       543: anewarray     #24                 // class java/lang/String
       546: dup
       547: iconst_0
       548: ldc           #85                 // String ¾
       550: aastore
       551: dup
       552: iconst_1
       553: ldc           #86                 // String &frac34;
       555: aastore
       556: aastore
       557: dup
       558: bipush        31
       560: iconst_2
       561: anewarray     #24                 // class java/lang/String
       564: dup
       565: iconst_0
       566: ldc           #87                 // String ¿
       568: aastore
       569: dup
       570: iconst_1
       571: ldc           #88                 // String &iquest;
       573: aastore
       574: aastore
       575: dup
       576: bipush        32
       578: iconst_2
       579: anewarray     #24                 // class java/lang/String
       582: dup
       583: iconst_0
       584: ldc           #89                 // String À
       586: aastore
       587: dup
       588: iconst_1
       589: ldc           #90                 // String &Agrave;
       591: aastore
       592: aastore
       593: dup
       594: bipush        33
       596: iconst_2
       597: anewarray     #24                 // class java/lang/String
       600: dup
       601: iconst_0
       602: ldc           #91                 // String Á
       604: aastore
       605: dup
       606: iconst_1
       607: ldc           #92                 // String &Aacute;
       609: aastore
       610: aastore
       611: dup
       612: bipush        34
       614: iconst_2
       615: anewarray     #24                 // class java/lang/String
       618: dup
       619: iconst_0
       620: ldc           #93                 // String Â
       622: aastore
       623: dup
       624: iconst_1
       625: ldc           #94                 // String &Acirc;
       627: aastore
       628: aastore
       629: dup
       630: bipush        35
       632: iconst_2
       633: anewarray     #24                 // class java/lang/String
       636: dup
       637: iconst_0
       638: ldc           #95                 // String Ã
       640: aastore
       641: dup
       642: iconst_1
       643: ldc           #96                 // String &Atilde;
       645: aastore
       646: aastore
       647: dup
       648: bipush        36
       650: iconst_2
       651: anewarray     #24                 // class java/lang/String
       654: dup
       655: iconst_0
       656: ldc           #97                 // String Ä
       658: aastore
       659: dup
       660: iconst_1
       661: ldc           #98                 // String &Auml;
       663: aastore
       664: aastore
       665: dup
       666: bipush        37
       668: iconst_2
       669: anewarray     #24                 // class java/lang/String
       672: dup
       673: iconst_0
       674: ldc           #99                 // String Å
       676: aastore
       677: dup
       678: iconst_1
       679: ldc           #100                // String &Aring;
       681: aastore
       682: aastore
       683: dup
       684: bipush        38
       686: iconst_2
       687: anewarray     #24                 // class java/lang/String
       690: dup
       691: iconst_0
       692: ldc           #101                // String Æ
       694: aastore
       695: dup
       696: iconst_1
       697: ldc           #102                // String &AElig;
       699: aastore
       700: aastore
       701: dup
       702: bipush        39
       704: iconst_2
       705: anewarray     #24                 // class java/lang/String
       708: dup
       709: iconst_0
       710: ldc           #103                // String Ç
       712: aastore
       713: dup
       714: iconst_1
       715: ldc           #104                // String &Ccedil;
       717: aastore
       718: aastore
       719: dup
       720: bipush        40
       722: iconst_2
       723: anewarray     #24                 // class java/lang/String
       726: dup
       727: iconst_0
       728: ldc           #105                // String È
       730: aastore
       731: dup
       732: iconst_1
       733: ldc           #106                // String &Egrave;
       735: aastore
       736: aastore
       737: dup
       738: bipush        41
       740: iconst_2
       741: anewarray     #24                 // class java/lang/String
       744: dup
       745: iconst_0
       746: ldc           #107                // String É
       748: aastore
       749: dup
       750: iconst_1
       751: ldc           #108                // String &Eacute;
       753: aastore
       754: aastore
       755: dup
       756: bipush        42
       758: iconst_2
       759: anewarray     #24                 // class java/lang/String
       762: dup
       763: iconst_0
       764: ldc           #109                // String Ê
       766: aastore
       767: dup
       768: iconst_1
       769: ldc           #110                // String &Ecirc;
       771: aastore
       772: aastore
       773: dup
       774: bipush        43
       776: iconst_2
       777: anewarray     #24                 // class java/lang/String
       780: dup
       781: iconst_0
       782: ldc           #111                // String Ë
       784: aastore
       785: dup
       786: iconst_1
       787: ldc           #112                // String &Euml;
       789: aastore
       790: aastore
       791: dup
       792: bipush        44
       794: iconst_2
       795: anewarray     #24                 // class java/lang/String
       798: dup
       799: iconst_0
       800: ldc           #113                // String Ì
       802: aastore
       803: dup
       804: iconst_1
       805: ldc           #114                // String &Igrave;
       807: aastore
       808: aastore
       809: dup
       810: bipush        45
       812: iconst_2
       813: anewarray     #24                 // class java/lang/String
       816: dup
       817: iconst_0
       818: ldc           #115                // String Í
       820: aastore
       821: dup
       822: iconst_1
       823: ldc           #116                // String &Iacute;
       825: aastore
       826: aastore
       827: dup
       828: bipush        46
       830: iconst_2
       831: anewarray     #24                 // class java/lang/String
       834: dup
       835: iconst_0
       836: ldc           #117                // String Î
       838: aastore
       839: dup
       840: iconst_1
       841: ldc           #118                // String &Icirc;
       843: aastore
       844: aastore
       845: dup
       846: bipush        47
       848: iconst_2
       849: anewarray     #24                 // class java/lang/String
       852: dup
       853: iconst_0
       854: ldc           #119                // String Ï
       856: aastore
       857: dup
       858: iconst_1
       859: ldc           #120                // String &Iuml;
       861: aastore
       862: aastore
       863: dup
       864: bipush        48
       866: iconst_2
       867: anewarray     #24                 // class java/lang/String
       870: dup
       871: iconst_0
       872: ldc           #121                // String Ð
       874: aastore
       875: dup
       876: iconst_1
       877: ldc           #122                // String &ETH;
       879: aastore
       880: aastore
       881: dup
       882: bipush        49
       884: iconst_2
       885: anewarray     #24                 // class java/lang/String
       888: dup
       889: iconst_0
       890: ldc           #123                // String Ñ
       892: aastore
       893: dup
       894: iconst_1
       895: ldc           #124                // String &Ntilde;
       897: aastore
       898: aastore
       899: dup
       900: bipush        50
       902: iconst_2
       903: anewarray     #24                 // class java/lang/String
       906: dup
       907: iconst_0
       908: ldc           #125                // String Ò
       910: aastore
       911: dup
       912: iconst_1
       913: ldc           #126                // String &Ograve;
       915: aastore
       916: aastore
       917: dup
       918: bipush        51
       920: iconst_2
       921: anewarray     #24                 // class java/lang/String
       924: dup
       925: iconst_0
       926: ldc           #127                // String Ó
       928: aastore
       929: dup
       930: iconst_1
       931: ldc           #128                // String &Oacute;
       933: aastore
       934: aastore
       935: dup
       936: bipush        52
       938: iconst_2
       939: anewarray     #24                 // class java/lang/String
       942: dup
       943: iconst_0
       944: ldc           #129                // String Ô
       946: aastore
       947: dup
       948: iconst_1
       949: ldc           #130                // String &Ocirc;
       951: aastore
       952: aastore
       953: dup
       954: bipush        53
       956: iconst_2
       957: anewarray     #24                 // class java/lang/String
       960: dup
       961: iconst_0
       962: ldc           #131                // String Õ
       964: aastore
       965: dup
       966: iconst_1
       967: ldc           #132                // String &Otilde;
       969: aastore
       970: aastore
       971: dup
       972: bipush        54
       974: iconst_2
       975: anewarray     #24                 // class java/lang/String
       978: dup
       979: iconst_0
       980: ldc           #133                // String Ö
       982: aastore
       983: dup
       984: iconst_1
       985: ldc           #134                // String &Ouml;
       987: aastore
       988: aastore
       989: dup
       990: bipush        55
       992: iconst_2
       993: anewarray     #24                 // class java/lang/String
       996: dup
       997: iconst_0
       998: ldc           #135                // String ×
      1000: aastore
      1001: dup
      1002: iconst_1
      1003: ldc           #136                // String &times;
      1005: aastore
      1006: aastore
      1007: dup
      1008: bipush        56
      1010: iconst_2
      1011: anewarray     #24                 // class java/lang/String
      1014: dup
      1015: iconst_0
      1016: ldc           #137                // String Ø
      1018: aastore
      1019: dup
      1020: iconst_1
      1021: ldc           #138                // String &Oslash;
      1023: aastore
      1024: aastore
      1025: dup
      1026: bipush        57
      1028: iconst_2
      1029: anewarray     #24                 // class java/lang/String
      1032: dup
      1033: iconst_0
      1034: ldc           #139                // String Ù
      1036: aastore
      1037: dup
      1038: iconst_1
      1039: ldc           #140                // String &Ugrave;
      1041: aastore
      1042: aastore
      1043: dup
      1044: bipush        58
      1046: iconst_2
      1047: anewarray     #24                 // class java/lang/String
      1050: dup
      1051: iconst_0
      1052: ldc           #141                // String Ú
      1054: aastore
      1055: dup
      1056: iconst_1
      1057: ldc           #142                // String &Uacute;
      1059: aastore
      1060: aastore
      1061: dup
      1062: bipush        59
      1064: iconst_2
      1065: anewarray     #24                 // class java/lang/String
      1068: dup
      1069: iconst_0
      1070: ldc           #143                // String Û
      1072: aastore
      1073: dup
      1074: iconst_1
      1075: ldc           #144                // String &Ucirc;
      1077: aastore
      1078: aastore
      1079: dup
      1080: bipush        60
      1082: iconst_2
      1083: anewarray     #24                 // class java/lang/String
      1086: dup
      1087: iconst_0
      1088: ldc           #145                // String Ü
      1090: aastore
      1091: dup
      1092: iconst_1
      1093: ldc           #146                // String &Uuml;
      1095: aastore
      1096: aastore
      1097: dup
      1098: bipush        61
      1100: iconst_2
      1101: anewarray     #24                 // class java/lang/String
      1104: dup
      1105: iconst_0
      1106: ldc           #147                // String Ý
      1108: aastore
      1109: dup
      1110: iconst_1
      1111: ldc           #148                // String &Yacute;
      1113: aastore
      1114: aastore
      1115: dup
      1116: bipush        62
      1118: iconst_2
      1119: anewarray     #24                 // class java/lang/String
      1122: dup
      1123: iconst_0
      1124: ldc           #149                // String Þ
      1126: aastore
      1127: dup
      1128: iconst_1
      1129: ldc           #150                // String &THORN;
      1131: aastore
      1132: aastore
      1133: dup
      1134: bipush        63
      1136: iconst_2
      1137: anewarray     #24                 // class java/lang/String
      1140: dup
      1141: iconst_0
      1142: ldc           #151                // String ß
      1144: aastore
      1145: dup
      1146: iconst_1
      1147: ldc           #152                // String &szlig;
      1149: aastore
      1150: aastore
      1151: dup
      1152: bipush        64
      1154: iconst_2
      1155: anewarray     #24                 // class java/lang/String
      1158: dup
      1159: iconst_0
      1160: ldc           #153                // String à
      1162: aastore
      1163: dup
      1164: iconst_1
      1165: ldc           #154                // String &agrave;
      1167: aastore
      1168: aastore
      1169: dup
      1170: bipush        65
      1172: iconst_2
      1173: anewarray     #24                 // class java/lang/String
      1176: dup
      1177: iconst_0
      1178: ldc           #155                // String á
      1180: aastore
      1181: dup
      1182: iconst_1
      1183: ldc           #156                // String &aacute;
      1185: aastore
      1186: aastore
      1187: dup
      1188: bipush        66
      1190: iconst_2
      1191: anewarray     #24                 // class java/lang/String
      1194: dup
      1195: iconst_0
      1196: ldc           #157                // String â
      1198: aastore
      1199: dup
      1200: iconst_1
      1201: ldc           #158                // String &acirc;
      1203: aastore
      1204: aastore
      1205: dup
      1206: bipush        67
      1208: iconst_2
      1209: anewarray     #24                 // class java/lang/String
      1212: dup
      1213: iconst_0
      1214: ldc           #159                // String ã
      1216: aastore
      1217: dup
      1218: iconst_1
      1219: ldc           #160                // String &atilde;
      1221: aastore
      1222: aastore
      1223: dup
      1224: bipush        68
      1226: iconst_2
      1227: anewarray     #24                 // class java/lang/String
      1230: dup
      1231: iconst_0
      1232: ldc           #161                // String ä
      1234: aastore
      1235: dup
      1236: iconst_1
      1237: ldc           #162                // String &auml;
      1239: aastore
      1240: aastore
      1241: dup
      1242: bipush        69
      1244: iconst_2
      1245: anewarray     #24                 // class java/lang/String
      1248: dup
      1249: iconst_0
      1250: ldc           #163                // String å
      1252: aastore
      1253: dup
      1254: iconst_1
      1255: ldc           #164                // String &aring;
      1257: aastore
      1258: aastore
      1259: dup
      1260: bipush        70
      1262: iconst_2
      1263: anewarray     #24                 // class java/lang/String
      1266: dup
      1267: iconst_0
      1268: ldc           #165                // String æ
      1270: aastore
      1271: dup
      1272: iconst_1
      1273: ldc           #166                // String &aelig;
      1275: aastore
      1276: aastore
      1277: dup
      1278: bipush        71
      1280: iconst_2
      1281: anewarray     #24                 // class java/lang/String
      1284: dup
      1285: iconst_0
      1286: ldc           #167                // String ç
      1288: aastore
      1289: dup
      1290: iconst_1
      1291: ldc           #168                // String &ccedil;
      1293: aastore
      1294: aastore
      1295: dup
      1296: bipush        72
      1298: iconst_2
      1299: anewarray     #24                 // class java/lang/String
      1302: dup
      1303: iconst_0
      1304: ldc           #169                // String è
      1306: aastore
      1307: dup
      1308: iconst_1
      1309: ldc           #170                // String &egrave;
      1311: aastore
      1312: aastore
      1313: dup
      1314: bipush        73
      1316: iconst_2
      1317: anewarray     #24                 // class java/lang/String
      1320: dup
      1321: iconst_0
      1322: ldc           #171                // String é
      1324: aastore
      1325: dup
      1326: iconst_1
      1327: ldc           #172                // String &eacute;
      1329: aastore
      1330: aastore
      1331: dup
      1332: bipush        74
      1334: iconst_2
      1335: anewarray     #24                 // class java/lang/String
      1338: dup
      1339: iconst_0
      1340: ldc           #173                // String ê
      1342: aastore
      1343: dup
      1344: iconst_1
      1345: ldc           #174                // String &ecirc;
      1347: aastore
      1348: aastore
      1349: dup
      1350: bipush        75
      1352: iconst_2
      1353: anewarray     #24                 // class java/lang/String
      1356: dup
      1357: iconst_0
      1358: ldc           #175                // String ë
      1360: aastore
      1361: dup
      1362: iconst_1
      1363: ldc           #176                // String &euml;
      1365: aastore
      1366: aastore
      1367: dup
      1368: bipush        76
      1370: iconst_2
      1371: anewarray     #24                 // class java/lang/String
      1374: dup
      1375: iconst_0
      1376: ldc           #177                // String ì
      1378: aastore
      1379: dup
      1380: iconst_1
      1381: ldc           #178                // String &igrave;
      1383: aastore
      1384: aastore
      1385: dup
      1386: bipush        77
      1388: iconst_2
      1389: anewarray     #24                 // class java/lang/String
      1392: dup
      1393: iconst_0
      1394: ldc           #179                // String í
      1396: aastore
      1397: dup
      1398: iconst_1
      1399: ldc           #180                // String &iacute;
      1401: aastore
      1402: aastore
      1403: dup
      1404: bipush        78
      1406: iconst_2
      1407: anewarray     #24                 // class java/lang/String
      1410: dup
      1411: iconst_0
      1412: ldc           #181                // String î
      1414: aastore
      1415: dup
      1416: iconst_1
      1417: ldc           #182                // String &icirc;
      1419: aastore
      1420: aastore
      1421: dup
      1422: bipush        79
      1424: iconst_2
      1425: anewarray     #24                 // class java/lang/String
      1428: dup
      1429: iconst_0
      1430: ldc           #183                // String ï
      1432: aastore
      1433: dup
      1434: iconst_1
      1435: ldc           #184                // String &iuml;
      1437: aastore
      1438: aastore
      1439: dup
      1440: bipush        80
      1442: iconst_2
      1443: anewarray     #24                 // class java/lang/String
      1446: dup
      1447: iconst_0
      1448: ldc           #185                // String ð
      1450: aastore
      1451: dup
      1452: iconst_1
      1453: ldc           #186                // String &eth;
      1455: aastore
      1456: aastore
      1457: dup
      1458: bipush        81
      1460: iconst_2
      1461: anewarray     #24                 // class java/lang/String
      1464: dup
      1465: iconst_0
      1466: ldc           #187                // String ñ
      1468: aastore
      1469: dup
      1470: iconst_1
      1471: ldc           #188                // String &ntilde;
      1473: aastore
      1474: aastore
      1475: dup
      1476: bipush        82
      1478: iconst_2
      1479: anewarray     #24                 // class java/lang/String
      1482: dup
      1483: iconst_0
      1484: ldc           #189                // String ò
      1486: aastore
      1487: dup
      1488: iconst_1
      1489: ldc           #190                // String &ograve;
      1491: aastore
      1492: aastore
      1493: dup
      1494: bipush        83
      1496: iconst_2
      1497: anewarray     #24                 // class java/lang/String
      1500: dup
      1501: iconst_0
      1502: ldc           #191                // String ó
      1504: aastore
      1505: dup
      1506: iconst_1
      1507: ldc           #192                // String &oacute;
      1509: aastore
      1510: aastore
      1511: dup
      1512: bipush        84
      1514: iconst_2
      1515: anewarray     #24                 // class java/lang/String
      1518: dup
      1519: iconst_0
      1520: ldc           #193                // String ô
      1522: aastore
      1523: dup
      1524: iconst_1
      1525: ldc           #194                // String &ocirc;
      1527: aastore
      1528: aastore
      1529: dup
      1530: bipush        85
      1532: iconst_2
      1533: anewarray     #24                 // class java/lang/String
      1536: dup
      1537: iconst_0
      1538: ldc           #195                // String õ
      1540: aastore
      1541: dup
      1542: iconst_1
      1543: ldc           #196                // String &otilde;
      1545: aastore
      1546: aastore
      1547: dup
      1548: bipush        86
      1550: iconst_2
      1551: anewarray     #24                 // class java/lang/String
      1554: dup
      1555: iconst_0
      1556: ldc           #197                // String ö
      1558: aastore
      1559: dup
      1560: iconst_1
      1561: ldc           #198                // String &ouml;
      1563: aastore
      1564: aastore
      1565: dup
      1566: bipush        87
      1568: iconst_2
      1569: anewarray     #24                 // class java/lang/String
      1572: dup
      1573: iconst_0
      1574: ldc           #199                // String ÷
      1576: aastore
      1577: dup
      1578: iconst_1
      1579: ldc           #200                // String &divide;
      1581: aastore
      1582: aastore
      1583: dup
      1584: bipush        88
      1586: iconst_2
      1587: anewarray     #24                 // class java/lang/String
      1590: dup
      1591: iconst_0
      1592: ldc           #201                // String ø
      1594: aastore
      1595: dup
      1596: iconst_1
      1597: ldc           #202                // String &oslash;
      1599: aastore
      1600: aastore
      1601: dup
      1602: bipush        89
      1604: iconst_2
      1605: anewarray     #24                 // class java/lang/String
      1608: dup
      1609: iconst_0
      1610: ldc           #203                // String ù
      1612: aastore
      1613: dup
      1614: iconst_1
      1615: ldc           #204                // String &ugrave;
      1617: aastore
      1618: aastore
      1619: dup
      1620: bipush        90
      1622: iconst_2
      1623: anewarray     #24                 // class java/lang/String
      1626: dup
      1627: iconst_0
      1628: ldc           #205                // String ú
      1630: aastore
      1631: dup
      1632: iconst_1
      1633: ldc           #206                // String &uacute;
      1635: aastore
      1636: aastore
      1637: dup
      1638: bipush        91
      1640: iconst_2
      1641: anewarray     #24                 // class java/lang/String
      1644: dup
      1645: iconst_0
      1646: ldc           #207                // String û
      1648: aastore
      1649: dup
      1650: iconst_1
      1651: ldc           #208                // String &ucirc;
      1653: aastore
      1654: aastore
      1655: dup
      1656: bipush        92
      1658: iconst_2
      1659: anewarray     #24                 // class java/lang/String
      1662: dup
      1663: iconst_0
      1664: ldc           #209                // String ü
      1666: aastore
      1667: dup
      1668: iconst_1
      1669: ldc           #210                // String &uuml;
      1671: aastore
      1672: aastore
      1673: dup
      1674: bipush        93
      1676: iconst_2
      1677: anewarray     #24                 // class java/lang/String
      1680: dup
      1681: iconst_0
      1682: ldc           #211                // String ý
      1684: aastore
      1685: dup
      1686: iconst_1
      1687: ldc           #212                // String &yacute;
      1689: aastore
      1690: aastore
      1691: dup
      1692: bipush        94
      1694: iconst_2
      1695: anewarray     #24                 // class java/lang/String
      1698: dup
      1699: iconst_0
      1700: ldc           #213                // String þ
      1702: aastore
      1703: dup
      1704: iconst_1
      1705: ldc           #214                // String &thorn;
      1707: aastore
      1708: aastore
      1709: dup
      1710: bipush        95
      1712: iconst_2
      1713: anewarray     #24                 // class java/lang/String
      1716: dup
      1717: iconst_0
      1718: ldc           #215                // String ÿ
      1720: aastore
      1721: dup
      1722: iconst_1
      1723: ldc           #216                // String &yuml;
      1725: aastore
      1726: aastore
      1727: putstatic     #2                  // Field ISO8859_1_ESCAPE:[[Ljava/lang/String;
      1730: getstatic     #2                  // Field ISO8859_1_ESCAPE:[[Ljava/lang/String;
      1733: invokestatic  #217                // Method invert:([[Ljava/lang/String;)[[Ljava/lang/String;
      1736: putstatic     #5                  // Field ISO8859_1_UNESCAPE:[[Ljava/lang/String;
      1739: sipush        152
      1742: anewarray     #23                 // class "[Ljava/lang/String;"
      1745: dup
      1746: iconst_0
      1747: iconst_2
      1748: anewarray     #24                 // class java/lang/String
      1751: dup
      1752: iconst_0
      1753: ldc           #218                // String ƒ
      1755: aastore
      1756: dup
      1757: iconst_1
      1758: ldc           #219                // String &fnof;
      1760: aastore
      1761: aastore
      1762: dup
      1763: iconst_1
      1764: iconst_2
      1765: anewarray     #24                 // class java/lang/String
      1768: dup
      1769: iconst_0
      1770: ldc           #220                // String Α
      1772: aastore
      1773: dup
      1774: iconst_1
      1775: ldc           #221                // String &Alpha;
      1777: aastore
      1778: aastore
      1779: dup
      1780: iconst_2
      1781: iconst_2
      1782: anewarray     #24                 // class java/lang/String
      1785: dup
      1786: iconst_0
      1787: ldc           #222                // String Β
      1789: aastore
      1790: dup
      1791: iconst_1
      1792: ldc           #223                // String &Beta;
      1794: aastore
      1795: aastore
      1796: dup
      1797: iconst_3
      1798: iconst_2
      1799: anewarray     #24                 // class java/lang/String
      1802: dup
      1803: iconst_0
      1804: ldc           #224                // String Γ
      1806: aastore
      1807: dup
      1808: iconst_1
      1809: ldc           #225                // String &Gamma;
      1811: aastore
      1812: aastore
      1813: dup
      1814: iconst_4
      1815: iconst_2
      1816: anewarray     #24                 // class java/lang/String
      1819: dup
      1820: iconst_0
      1821: ldc           #226                // String Δ
      1823: aastore
      1824: dup
      1825: iconst_1
      1826: ldc           #227                // String &Delta;
      1828: aastore
      1829: aastore
      1830: dup
      1831: iconst_5
      1832: iconst_2
      1833: anewarray     #24                 // class java/lang/String
      1836: dup
      1837: iconst_0
      1838: ldc           #228                // String Ε
      1840: aastore
      1841: dup
      1842: iconst_1
      1843: ldc           #229                // String &Epsilon;
      1845: aastore
      1846: aastore
      1847: dup
      1848: bipush        6
      1850: iconst_2
      1851: anewarray     #24                 // class java/lang/String
      1854: dup
      1855: iconst_0
      1856: ldc           #230                // String Ζ
      1858: aastore
      1859: dup
      1860: iconst_1
      1861: ldc           #231                // String &Zeta;
      1863: aastore
      1864: aastore
      1865: dup
      1866: bipush        7
      1868: iconst_2
      1869: anewarray     #24                 // class java/lang/String
      1872: dup
      1873: iconst_0
      1874: ldc           #232                // String Η
      1876: aastore
      1877: dup
      1878: iconst_1
      1879: ldc           #233                // String &Eta;
      1881: aastore
      1882: aastore
      1883: dup
      1884: bipush        8
      1886: iconst_2
      1887: anewarray     #24                 // class java/lang/String
      1890: dup
      1891: iconst_0
      1892: ldc           #234                // String Θ
      1894: aastore
      1895: dup
      1896: iconst_1
      1897: ldc           #235                // String &Theta;
      1899: aastore
      1900: aastore
      1901: dup
      1902: bipush        9
      1904: iconst_2
      1905: anewarray     #24                 // class java/lang/String
      1908: dup
      1909: iconst_0
      1910: ldc           #236                // String Ι
      1912: aastore
      1913: dup
      1914: iconst_1
      1915: ldc           #237                // String &Iota;
      1917: aastore
      1918: aastore
      1919: dup
      1920: bipush        10
      1922: iconst_2
      1923: anewarray     #24                 // class java/lang/String
      1926: dup
      1927: iconst_0
      1928: ldc           #238                // String Κ
      1930: aastore
      1931: dup
      1932: iconst_1
      1933: ldc           #239                // String &Kappa;
      1935: aastore
      1936: aastore
      1937: dup
      1938: bipush        11
      1940: iconst_2
      1941: anewarray     #24                 // class java/lang/String
      1944: dup
      1945: iconst_0
      1946: ldc           #240                // String Λ
      1948: aastore
      1949: dup
      1950: iconst_1
      1951: ldc           #241                // String &Lambda;
      1953: aastore
      1954: aastore
      1955: dup
      1956: bipush        12
      1958: iconst_2
      1959: anewarray     #24                 // class java/lang/String
      1962: dup
      1963: iconst_0
      1964: ldc           #242                // String Μ
      1966: aastore
      1967: dup
      1968: iconst_1
      1969: ldc           #243                // String &Mu;
      1971: aastore
      1972: aastore
      1973: dup
      1974: bipush        13
      1976: iconst_2
      1977: anewarray     #24                 // class java/lang/String
      1980: dup
      1981: iconst_0
      1982: ldc           #244                // String Ν
      1984: aastore
      1985: dup
      1986: iconst_1
      1987: ldc           #245                // String &Nu;
      1989: aastore
      1990: aastore
      1991: dup
      1992: bipush        14
      1994: iconst_2
      1995: anewarray     #24                 // class java/lang/String
      1998: dup
      1999: iconst_0
      2000: ldc           #246                // String Ξ
      2002: aastore
      2003: dup
      2004: iconst_1
      2005: ldc           #247                // String &Xi;
      2007: aastore
      2008: aastore
      2009: dup
      2010: bipush        15
      2012: iconst_2
      2013: anewarray     #24                 // class java/lang/String
      2016: dup
      2017: iconst_0
      2018: ldc           #248                // String Ο
      2020: aastore
      2021: dup
      2022: iconst_1
      2023: ldc           #249                // String &Omicron;
      2025: aastore
      2026: aastore
      2027: dup
      2028: bipush        16
      2030: iconst_2
      2031: anewarray     #24                 // class java/lang/String
      2034: dup
      2035: iconst_0
      2036: ldc           #250                // String Π
      2038: aastore
      2039: dup
      2040: iconst_1
      2041: ldc           #251                // String &Pi;
      2043: aastore
      2044: aastore
      2045: dup
      2046: bipush        17
      2048: iconst_2
      2049: anewarray     #24                 // class java/lang/String
      2052: dup
      2053: iconst_0
      2054: ldc           #252                // String Ρ
      2056: aastore
      2057: dup
      2058: iconst_1
      2059: ldc           #253                // String &Rho;
      2061: aastore
      2062: aastore
      2063: dup
      2064: bipush        18
      2066: iconst_2
      2067: anewarray     #24                 // class java/lang/String
      2070: dup
      2071: iconst_0
      2072: ldc           #254                // String Σ
      2074: aastore
      2075: dup
      2076: iconst_1
      2077: ldc           #255                // String &Sigma;
      2079: aastore
      2080: aastore
      2081: dup
      2082: bipush        19
      2084: iconst_2
      2085: anewarray     #24                 // class java/lang/String
      2088: dup
      2089: iconst_0
      2090: ldc_w         #256                // String Τ
      2093: aastore
      2094: dup
      2095: iconst_1
      2096: ldc_w         #257                // String &Tau;
      2099: aastore
      2100: aastore
      2101: dup
      2102: bipush        20
      2104: iconst_2
      2105: anewarray     #24                 // class java/lang/String
      2108: dup
      2109: iconst_0
      2110: ldc_w         #258                // String Υ
      2113: aastore
      2114: dup
      2115: iconst_1
      2116: ldc_w         #259                // String &Upsilon;
      2119: aastore
      2120: aastore
      2121: dup
      2122: bipush        21
      2124: iconst_2
      2125: anewarray     #24                 // class java/lang/String
      2128: dup
      2129: iconst_0
      2130: ldc_w         #260                // String Φ
      2133: aastore
      2134: dup
      2135: iconst_1
      2136: ldc_w         #261                // String &Phi;
      2139: aastore
      2140: aastore
      2141: dup
      2142: bipush        22
      2144: iconst_2
      2145: anewarray     #24                 // class java/lang/String
      2148: dup
      2149: iconst_0
      2150: ldc_w         #262                // String Χ
      2153: aastore
      2154: dup
      2155: iconst_1
      2156: ldc_w         #263                // String &Chi;
      2159: aastore
      2160: aastore
      2161: dup
      2162: bipush        23
      2164: iconst_2
      2165: anewarray     #24                 // class java/lang/String
      2168: dup
      2169: iconst_0
      2170: ldc_w         #264                // String Ψ
      2173: aastore
      2174: dup
      2175: iconst_1
      2176: ldc_w         #265                // String &Psi;
      2179: aastore
      2180: aastore
      2181: dup
      2182: bipush        24
      2184: iconst_2
      2185: anewarray     #24                 // class java/lang/String
      2188: dup
      2189: iconst_0
      2190: ldc_w         #266                // String Ω
      2193: aastore
      2194: dup
      2195: iconst_1
      2196: ldc_w         #267                // String &Omega;
      2199: aastore
      2200: aastore
      2201: dup
      2202: bipush        25
      2204: iconst_2
      2205: anewarray     #24                 // class java/lang/String
      2208: dup
      2209: iconst_0
      2210: ldc_w         #268                // String α
      2213: aastore
      2214: dup
      2215: iconst_1
      2216: ldc_w         #269                // String &alpha;
      2219: aastore
      2220: aastore
      2221: dup
      2222: bipush        26
      2224: iconst_2
      2225: anewarray     #24                 // class java/lang/String
      2228: dup
      2229: iconst_0
      2230: ldc_w         #270                // String β
      2233: aastore
      2234: dup
      2235: iconst_1
      2236: ldc_w         #271                // String &beta;
      2239: aastore
      2240: aastore
      2241: dup
      2242: bipush        27
      2244: iconst_2
      2245: anewarray     #24                 // class java/lang/String
      2248: dup
      2249: iconst_0
      2250: ldc_w         #272                // String γ
      2253: aastore
      2254: dup
      2255: iconst_1
      2256: ldc_w         #273                // String &gamma;
      2259: aastore
      2260: aastore
      2261: dup
      2262: bipush        28
      2264: iconst_2
      2265: anewarray     #24                 // class java/lang/String
      2268: dup
      2269: iconst_0
      2270: ldc_w         #274                // String δ
      2273: aastore
      2274: dup
      2275: iconst_1
      2276: ldc_w         #275                // String &delta;
      2279: aastore
      2280: aastore
      2281: dup
      2282: bipush        29
      2284: iconst_2
      2285: anewarray     #24                 // class java/lang/String
      2288: dup
      2289: iconst_0
      2290: ldc_w         #276                // String ε
      2293: aastore
      2294: dup
      2295: iconst_1
      2296: ldc_w         #277                // String &epsilon;
      2299: aastore
      2300: aastore
      2301: dup
      2302: bipush        30
      2304: iconst_2
      2305: anewarray     #24                 // class java/lang/String
      2308: dup
      2309: iconst_0
      2310: ldc_w         #278                // String ζ
      2313: aastore
      2314: dup
      2315: iconst_1
      2316: ldc_w         #279                // String &zeta;
      2319: aastore
      2320: aastore
      2321: dup
      2322: bipush        31
      2324: iconst_2
      2325: anewarray     #24                 // class java/lang/String
      2328: dup
      2329: iconst_0
      2330: ldc_w         #280                // String η
      2333: aastore
      2334: dup
      2335: iconst_1
      2336: ldc_w         #281                // String &eta;
      2339: aastore
      2340: aastore
      2341: dup
      2342: bipush        32
      2344: iconst_2
      2345: anewarray     #24                 // class java/lang/String
      2348: dup
      2349: iconst_0
      2350: ldc_w         #282                // String θ
      2353: aastore
      2354: dup
      2355: iconst_1
      2356: ldc_w         #283                // String &theta;
      2359: aastore
      2360: aastore
      2361: dup
      2362: bipush        33
      2364: iconst_2
      2365: anewarray     #24                 // class java/lang/String
      2368: dup
      2369: iconst_0
      2370: ldc_w         #284                // String ι
      2373: aastore
      2374: dup
      2375: iconst_1
      2376: ldc_w         #285                // String &iota;
      2379: aastore
      2380: aastore
      2381: dup
      2382: bipush        34
      2384: iconst_2
      2385: anewarray     #24                 // class java/lang/String
      2388: dup
      2389: iconst_0
      2390: ldc_w         #286                // String κ
      2393: aastore
      2394: dup
      2395: iconst_1
      2396: ldc_w         #287                // String &kappa;
      2399: aastore
      2400: aastore
      2401: dup
      2402: bipush        35
      2404: iconst_2
      2405: anewarray     #24                 // class java/lang/String
      2408: dup
      2409: iconst_0
      2410: ldc_w         #288                // String λ
      2413: aastore
      2414: dup
      2415: iconst_1
      2416: ldc_w         #289                // String &lambda;
      2419: aastore
      2420: aastore
      2421: dup
      2422: bipush        36
      2424: iconst_2
      2425: anewarray     #24                 // class java/lang/String
      2428: dup
      2429: iconst_0
      2430: ldc_w         #290                // String μ
      2433: aastore
      2434: dup
      2435: iconst_1
      2436: ldc_w         #291                // String &mu;
      2439: aastore
      2440: aastore
      2441: dup
      2442: bipush        37
      2444: iconst_2
      2445: anewarray     #24                 // class java/lang/String
      2448: dup
      2449: iconst_0
      2450: ldc_w         #292                // String ν
      2453: aastore
      2454: dup
      2455: iconst_1
      2456: ldc_w         #293                // String &nu;
      2459: aastore
      2460: aastore
      2461: dup
      2462: bipush        38
      2464: iconst_2
      2465: anewarray     #24                 // class java/lang/String
      2468: dup
      2469: iconst_0
      2470: ldc_w         #294                // String ξ
      2473: aastore
      2474: dup
      2475: iconst_1
      2476: ldc_w         #295                // String &xi;
      2479: aastore
      2480: aastore
      2481: dup
      2482: bipush        39
      2484: iconst_2
      2485: anewarray     #24                 // class java/lang/String
      2488: dup
      2489: iconst_0
      2490: ldc_w         #296                // String ο
      2493: aastore
      2494: dup
      2495: iconst_1
      2496: ldc_w         #297                // String &omicron;
      2499: aastore
      2500: aastore
      2501: dup
      2502: bipush        40
      2504: iconst_2
      2505: anewarray     #24                 // class java/lang/String
      2508: dup
      2509: iconst_0
      2510: ldc_w         #298                // String π
      2513: aastore
      2514: dup
      2515: iconst_1
      2516: ldc_w         #299                // String &pi;
      2519: aastore
      2520: aastore
      2521: dup
      2522: bipush        41
      2524: iconst_2
      2525: anewarray     #24                 // class java/lang/String
      2528: dup
      2529: iconst_0
      2530: ldc_w         #300                // String ρ
      2533: aastore
      2534: dup
      2535: iconst_1
      2536: ldc_w         #301                // String &rho;
      2539: aastore
      2540: aastore
      2541: dup
      2542: bipush        42
      2544: iconst_2
      2545: anewarray     #24                 // class java/lang/String
      2548: dup
      2549: iconst_0
      2550: ldc_w         #302                // String ς
      2553: aastore
      2554: dup
      2555: iconst_1
      2556: ldc_w         #303                // String &sigmaf;
      2559: aastore
      2560: aastore
      2561: dup
      2562: bipush        43
      2564: iconst_2
      2565: anewarray     #24                 // class java/lang/String
      2568: dup
      2569: iconst_0
      2570: ldc_w         #304                // String σ
      2573: aastore
      2574: dup
      2575: iconst_1
      2576: ldc_w         #305                // String &sigma;
      2579: aastore
      2580: aastore
      2581: dup
      2582: bipush        44
      2584: iconst_2
      2585: anewarray     #24                 // class java/lang/String
      2588: dup
      2589: iconst_0
      2590: ldc_w         #306                // String τ
      2593: aastore
      2594: dup
      2595: iconst_1
      2596: ldc_w         #307                // String &tau;
      2599: aastore
      2600: aastore
      2601: dup
      2602: bipush        45
      2604: iconst_2
      2605: anewarray     #24                 // class java/lang/String
      2608: dup
      2609: iconst_0
      2610: ldc_w         #308                // String υ
      2613: aastore
      2614: dup
      2615: iconst_1
      2616: ldc_w         #309                // String &upsilon;
      2619: aastore
      2620: aastore
      2621: dup
      2622: bipush        46
      2624: iconst_2
      2625: anewarray     #24                 // class java/lang/String
      2628: dup
      2629: iconst_0
      2630: ldc_w         #310                // String φ
      2633: aastore
      2634: dup
      2635: iconst_1
      2636: ldc_w         #311                // String &phi;
      2639: aastore
      2640: aastore
      2641: dup
      2642: bipush        47
      2644: iconst_2
      2645: anewarray     #24                 // class java/lang/String
      2648: dup
      2649: iconst_0
      2650: ldc_w         #312                // String χ
      2653: aastore
      2654: dup
      2655: iconst_1
      2656: ldc_w         #313                // String &chi;
      2659: aastore
      2660: aastore
      2661: dup
      2662: bipush        48
      2664: iconst_2
      2665: anewarray     #24                 // class java/lang/String
      2668: dup
      2669: iconst_0
      2670: ldc_w         #314                // String ψ
      2673: aastore
      2674: dup
      2675: iconst_1
      2676: ldc_w         #315                // String &psi;
      2679: aastore
      2680: aastore
      2681: dup
      2682: bipush        49
      2684: iconst_2
      2685: anewarray     #24                 // class java/lang/String
      2688: dup
      2689: iconst_0
      2690: ldc_w         #316                // String ω
      2693: aastore
      2694: dup
      2695: iconst_1
      2696: ldc_w         #317                // String &omega;
      2699: aastore
      2700: aastore
      2701: dup
      2702: bipush        50
      2704: iconst_2
      2705: anewarray     #24                 // class java/lang/String
      2708: dup
      2709: iconst_0
      2710: ldc_w         #318                // String ϑ
      2713: aastore
      2714: dup
      2715: iconst_1
      2716: ldc_w         #319                // String &thetasym;
      2719: aastore
      2720: aastore
      2721: dup
      2722: bipush        51
      2724: iconst_2
      2725: anewarray     #24                 // class java/lang/String
      2728: dup
      2729: iconst_0
      2730: ldc_w         #320                // String ϒ
      2733: aastore
      2734: dup
      2735: iconst_1
      2736: ldc_w         #321                // String &upsih;
      2739: aastore
      2740: aastore
      2741: dup
      2742: bipush        52
      2744: iconst_2
      2745: anewarray     #24                 // class java/lang/String
      2748: dup
      2749: iconst_0
      2750: ldc_w         #322                // String ϖ
      2753: aastore
      2754: dup
      2755: iconst_1
      2756: ldc_w         #323                // String &piv;
      2759: aastore
      2760: aastore
      2761: dup
      2762: bipush        53
      2764: iconst_2
      2765: anewarray     #24                 // class java/lang/String
      2768: dup
      2769: iconst_0
      2770: ldc_w         #324                // String •
      2773: aastore
      2774: dup
      2775: iconst_1
      2776: ldc_w         #325                // String &bull;
      2779: aastore
      2780: aastore
      2781: dup
      2782: bipush        54
      2784: iconst_2
      2785: anewarray     #24                 // class java/lang/String
      2788: dup
      2789: iconst_0
      2790: ldc_w         #326                // String …
      2793: aastore
      2794: dup
      2795: iconst_1
      2796: ldc_w         #327                // String &hellip;
      2799: aastore
      2800: aastore
      2801: dup
      2802: bipush        55
      2804: iconst_2
      2805: anewarray     #24                 // class java/lang/String
      2808: dup
      2809: iconst_0
      2810: ldc_w         #328                // String ′
      2813: aastore
      2814: dup
      2815: iconst_1
      2816: ldc_w         #329                // String &prime;
      2819: aastore
      2820: aastore
      2821: dup
      2822: bipush        56
      2824: iconst_2
      2825: anewarray     #24                 // class java/lang/String
      2828: dup
      2829: iconst_0
      2830: ldc_w         #330                // String ″
      2833: aastore
      2834: dup
      2835: iconst_1
      2836: ldc_w         #331                // String &Prime;
      2839: aastore
      2840: aastore
      2841: dup
      2842: bipush        57
      2844: iconst_2
      2845: anewarray     #24                 // class java/lang/String
      2848: dup
      2849: iconst_0
      2850: ldc_w         #332                // String ‾
      2853: aastore
      2854: dup
      2855: iconst_1
      2856: ldc_w         #333                // String &oline;
      2859: aastore
      2860: aastore
      2861: dup
      2862: bipush        58
      2864: iconst_2
      2865: anewarray     #24                 // class java/lang/String
      2868: dup
      2869: iconst_0
      2870: ldc_w         #334                // String ⁄
      2873: aastore
      2874: dup
      2875: iconst_1
      2876: ldc_w         #335                // String &frasl;
      2879: aastore
      2880: aastore
      2881: dup
      2882: bipush        59
      2884: iconst_2
      2885: anewarray     #24                 // class java/lang/String
      2888: dup
      2889: iconst_0
      2890: ldc_w         #336                // String ℘
      2893: aastore
      2894: dup
      2895: iconst_1
      2896: ldc_w         #337                // String &weierp;
      2899: aastore
      2900: aastore
      2901: dup
      2902: bipush        60
      2904: iconst_2
      2905: anewarray     #24                 // class java/lang/String
      2908: dup
      2909: iconst_0
      2910: ldc_w         #338                // String ℑ
      2913: aastore
      2914: dup
      2915: iconst_1
      2916: ldc_w         #339                // String &image;
      2919: aastore
      2920: aastore
      2921: dup
      2922: bipush        61
      2924: iconst_2
      2925: anewarray     #24                 // class java/lang/String
      2928: dup
      2929: iconst_0
      2930: ldc_w         #340                // String ℜ
      2933: aastore
      2934: dup
      2935: iconst_1
      2936: ldc_w         #341                // String &real;
      2939: aastore
      2940: aastore
      2941: dup
      2942: bipush        62
      2944: iconst_2
      2945: anewarray     #24                 // class java/lang/String
      2948: dup
      2949: iconst_0
      2950: ldc_w         #342                // String ™
      2953: aastore
      2954: dup
      2955: iconst_1
      2956: ldc_w         #343                // String &trade;
      2959: aastore
      2960: aastore
      2961: dup
      2962: bipush        63
      2964: iconst_2
      2965: anewarray     #24                 // class java/lang/String
      2968: dup
      2969: iconst_0
      2970: ldc_w         #344                // String ℵ
      2973: aastore
      2974: dup
      2975: iconst_1
      2976: ldc_w         #345                // String &alefsym;
      2979: aastore
      2980: aastore
      2981: dup
      2982: bipush        64
      2984: iconst_2
      2985: anewarray     #24                 // class java/lang/String
      2988: dup
      2989: iconst_0
      2990: ldc_w         #346                // String ←
      2993: aastore
      2994: dup
      2995: iconst_1
      2996: ldc_w         #347                // String &larr;
      2999: aastore
      3000: aastore
      3001: dup
      3002: bipush        65
      3004: iconst_2
      3005: anewarray     #24                 // class java/lang/String
      3008: dup
      3009: iconst_0
      3010: ldc_w         #348                // String ↑
      3013: aastore
      3014: dup
      3015: iconst_1
      3016: ldc_w         #349                // String &uarr;
      3019: aastore
      3020: aastore
      3021: dup
      3022: bipush        66
      3024: iconst_2
      3025: anewarray     #24                 // class java/lang/String
      3028: dup
      3029: iconst_0
      3030: ldc_w         #350                // String →
      3033: aastore
      3034: dup
      3035: iconst_1
      3036: ldc_w         #351                // String &rarr;
      3039: aastore
      3040: aastore
      3041: dup
      3042: bipush        67
      3044: iconst_2
      3045: anewarray     #24                 // class java/lang/String
      3048: dup
      3049: iconst_0
      3050: ldc_w         #352                // String ↓
      3053: aastore
      3054: dup
      3055: iconst_1
      3056: ldc_w         #353                // String &darr;
      3059: aastore
      3060: aastore
      3061: dup
      3062: bipush        68
      3064: iconst_2
      3065: anewarray     #24                 // class java/lang/String
      3068: dup
      3069: iconst_0
      3070: ldc_w         #354                // String ↔
      3073: aastore
      3074: dup
      3075: iconst_1
      3076: ldc_w         #355                // String &harr;
      3079: aastore
      3080: aastore
      3081: dup
      3082: bipush        69
      3084: iconst_2
      3085: anewarray     #24                 // class java/lang/String
      3088: dup
      3089: iconst_0
      3090: ldc_w         #356                // String ↵
      3093: aastore
      3094: dup
      3095: iconst_1
      3096: ldc_w         #357                // String &crarr;
      3099: aastore
      3100: aastore
      3101: dup
      3102: bipush        70
      3104: iconst_2
      3105: anewarray     #24                 // class java/lang/String
      3108: dup
      3109: iconst_0
      3110: ldc_w         #358                // String ⇐
      3113: aastore
      3114: dup
      3115: iconst_1
      3116: ldc_w         #359                // String &lArr;
      3119: aastore
      3120: aastore
      3121: dup
      3122: bipush        71
      3124: iconst_2
      3125: anewarray     #24                 // class java/lang/String
      3128: dup
      3129: iconst_0
      3130: ldc_w         #360                // String ⇑
      3133: aastore
      3134: dup
      3135: iconst_1
      3136: ldc_w         #361                // String &uArr;
      3139: aastore
      3140: aastore
      3141: dup
      3142: bipush        72
      3144: iconst_2
      3145: anewarray     #24                 // class java/lang/String
      3148: dup
      3149: iconst_0
      3150: ldc_w         #362                // String ⇒
      3153: aastore
      3154: dup
      3155: iconst_1
      3156: ldc_w         #363                // String &rArr;
      3159: aastore
      3160: aastore
      3161: dup
      3162: bipush        73
      3164: iconst_2
      3165: anewarray     #24                 // class java/lang/String
      3168: dup
      3169: iconst_0
      3170: ldc_w         #364                // String ⇓
      3173: aastore
      3174: dup
      3175: iconst_1
      3176: ldc_w         #365                // String &dArr;
      3179: aastore
      3180: aastore
      3181: dup
      3182: bipush        74
      3184: iconst_2
      3185: anewarray     #24                 // class java/lang/String
      3188: dup
      3189: iconst_0
      3190: ldc_w         #366                // String ⇔
      3193: aastore
      3194: dup
      3195: iconst_1
      3196: ldc_w         #367                // String &hArr;
      3199: aastore
      3200: aastore
      3201: dup
      3202: bipush        75
      3204: iconst_2
      3205: anewarray     #24                 // class java/lang/String
      3208: dup
      3209: iconst_0
      3210: ldc_w         #368                // String ∀
      3213: aastore
      3214: dup
      3215: iconst_1
      3216: ldc_w         #369                // String &forall;
      3219: aastore
      3220: aastore
      3221: dup
      3222: bipush        76
      3224: iconst_2
      3225: anewarray     #24                 // class java/lang/String
      3228: dup
      3229: iconst_0
      3230: ldc_w         #370                // String ∂
      3233: aastore
      3234: dup
      3235: iconst_1
      3236: ldc_w         #371                // String &part;
      3239: aastore
      3240: aastore
      3241: dup
      3242: bipush        77
      3244: iconst_2
      3245: anewarray     #24                 // class java/lang/String
      3248: dup
      3249: iconst_0
      3250: ldc_w         #372                // String ∃
      3253: aastore
      3254: dup
      3255: iconst_1
      3256: ldc_w         #373                // String &exist;
      3259: aastore
      3260: aastore
      3261: dup
      3262: bipush        78
      3264: iconst_2
      3265: anewarray     #24                 // class java/lang/String
      3268: dup
      3269: iconst_0
      3270: ldc_w         #374                // String ∅
      3273: aastore
      3274: dup
      3275: iconst_1
      3276: ldc_w         #375                // String &empty;
      3279: aastore
      3280: aastore
      3281: dup
      3282: bipush        79
      3284: iconst_2
      3285: anewarray     #24                 // class java/lang/String
      3288: dup
      3289: iconst_0
      3290: ldc_w         #376                // String ∇
      3293: aastore
      3294: dup
      3295: iconst_1
      3296: ldc_w         #377                // String &nabla;
      3299: aastore
      3300: aastore
      3301: dup
      3302: bipush        80
      3304: iconst_2
      3305: anewarray     #24                 // class java/lang/String
      3308: dup
      3309: iconst_0
      3310: ldc_w         #378                // String ∈
      3313: aastore
      3314: dup
      3315: iconst_1
      3316: ldc_w         #379                // String &isin;
      3319: aastore
      3320: aastore
      3321: dup
      3322: bipush        81
      3324: iconst_2
      3325: anewarray     #24                 // class java/lang/String
      3328: dup
      3329: iconst_0
      3330: ldc_w         #380                // String ∉
      3333: aastore
      3334: dup
      3335: iconst_1
      3336: ldc_w         #381                // String &notin;
      3339: aastore
      3340: aastore
      3341: dup
      3342: bipush        82
      3344: iconst_2
      3345: anewarray     #24                 // class java/lang/String
      3348: dup
      3349: iconst_0
      3350: ldc_w         #382                // String ∋
      3353: aastore
      3354: dup
      3355: iconst_1
      3356: ldc_w         #383                // String &ni;
      3359: aastore
      3360: aastore
      3361: dup
      3362: bipush        83
      3364: iconst_2
      3365: anewarray     #24                 // class java/lang/String
      3368: dup
      3369: iconst_0
      3370: ldc_w         #384                // String ∏
      3373: aastore
      3374: dup
      3375: iconst_1
      3376: ldc_w         #385                // String &prod;
      3379: aastore
      3380: aastore
      3381: dup
      3382: bipush        84
      3384: iconst_2
      3385: anewarray     #24                 // class java/lang/String
      3388: dup
      3389: iconst_0
      3390: ldc_w         #386                // String ∑
      3393: aastore
      3394: dup
      3395: iconst_1
      3396: ldc_w         #387                // String &sum;
      3399: aastore
      3400: aastore
      3401: dup
      3402: bipush        85
      3404: iconst_2
      3405: anewarray     #24                 // class java/lang/String
      3408: dup
      3409: iconst_0
      3410: ldc_w         #388                // String −
      3413: aastore
      3414: dup
      3415: iconst_1
      3416: ldc_w         #389                // String &minus;
      3419: aastore
      3420: aastore
      3421: dup
      3422: bipush        86
      3424: iconst_2
      3425: anewarray     #24                 // class java/lang/String
      3428: dup
      3429: iconst_0
      3430: ldc_w         #390                // String ∗
      3433: aastore
      3434: dup
      3435: iconst_1
      3436: ldc_w         #391                // String &lowast;
      3439: aastore
      3440: aastore
      3441: dup
      3442: bipush        87
      3444: iconst_2
      3445: anewarray     #24                 // class java/lang/String
      3448: dup
      3449: iconst_0
      3450: ldc_w         #392                // String √
      3453: aastore
      3454: dup
      3455: iconst_1
      3456: ldc_w         #393                // String &radic;
      3459: aastore
      3460: aastore
      3461: dup
      3462: bipush        88
      3464: iconst_2
      3465: anewarray     #24                 // class java/lang/String
      3468: dup
      3469: iconst_0
      3470: ldc_w         #394                // String ∝
      3473: aastore
      3474: dup
      3475: iconst_1
      3476: ldc_w         #395                // String &prop;
      3479: aastore
      3480: aastore
      3481: dup
      3482: bipush        89
      3484: iconst_2
      3485: anewarray     #24                 // class java/lang/String
      3488: dup
      3489: iconst_0
      3490: ldc_w         #396                // String ∞
      3493: aastore
      3494: dup
      3495: iconst_1
      3496: ldc_w         #397                // String &infin;
      3499: aastore
      3500: aastore
      3501: dup
      3502: bipush        90
      3504: iconst_2
      3505: anewarray     #24                 // class java/lang/String
      3508: dup
      3509: iconst_0
      3510: ldc_w         #398                // String ∠
      3513: aastore
      3514: dup
      3515: iconst_1
      3516: ldc_w         #399                // String &ang;
      3519: aastore
      3520: aastore
      3521: dup
      3522: bipush        91
      3524: iconst_2
      3525: anewarray     #24                 // class java/lang/String
      3528: dup
      3529: iconst_0
      3530: ldc_w         #400                // String ∧
      3533: aastore
      3534: dup
      3535: iconst_1
      3536: ldc_w         #401                // String &and;
      3539: aastore
      3540: aastore
      3541: dup
      3542: bipush        92
      3544: iconst_2
      3545: anewarray     #24                 // class java/lang/String
      3548: dup
      3549: iconst_0
      3550: ldc_w         #402                // String ∨
      3553: aastore
      3554: dup
      3555: iconst_1
      3556: ldc_w         #403                // String &or;
      3559: aastore
      3560: aastore
      3561: dup
      3562: bipush        93
      3564: iconst_2
      3565: anewarray     #24                 // class java/lang/String
      3568: dup
      3569: iconst_0
      3570: ldc_w         #404                // String ∩
      3573: aastore
      3574: dup
      3575: iconst_1
      3576: ldc_w         #405                // String &cap;
      3579: aastore
      3580: aastore
      3581: dup
      3582: bipush        94
      3584: iconst_2
      3585: anewarray     #24                 // class java/lang/String
      3588: dup
      3589: iconst_0
      3590: ldc_w         #406                // String ∪
      3593: aastore
      3594: dup
      3595: iconst_1
      3596: ldc_w         #407                // String &cup;
      3599: aastore
      3600: aastore
      3601: dup
      3602: bipush        95
      3604: iconst_2
      3605: anewarray     #24                 // class java/lang/String
      3608: dup
      3609: iconst_0
      3610: ldc_w         #408                // String ∫
      3613: aastore
      3614: dup
      3615: iconst_1
      3616: ldc_w         #409                // String &int;
      3619: aastore
      3620: aastore
      3621: dup
      3622: bipush        96
      3624: iconst_2
      3625: anewarray     #24                 // class java/lang/String
      3628: dup
      3629: iconst_0
      3630: ldc_w         #410                // String ∴
      3633: aastore
      3634: dup
      3635: iconst_1
      3636: ldc_w         #411                // String &there4;
      3639: aastore
      3640: aastore
      3641: dup
      3642: bipush        97
      3644: iconst_2
      3645: anewarray     #24                 // class java/lang/String
      3648: dup
      3649: iconst_0
      3650: ldc_w         #412                // String ∼
      3653: aastore
      3654: dup
      3655: iconst_1
      3656: ldc_w         #413                // String &sim;
      3659: aastore
      3660: aastore
      3661: dup
      3662: bipush        98
      3664: iconst_2
      3665: anewarray     #24                 // class java/lang/String
      3668: dup
      3669: iconst_0
      3670: ldc_w         #414                // String ≅
      3673: aastore
      3674: dup
      3675: iconst_1
      3676: ldc_w         #415                // String &cong;
      3679: aastore
      3680: aastore
      3681: dup
      3682: bipush        99
      3684: iconst_2
      3685: anewarray     #24                 // class java/lang/String
      3688: dup
      3689: iconst_0
      3690: ldc_w         #416                // String ≈
      3693: aastore
      3694: dup
      3695: iconst_1
      3696: ldc_w         #417                // String &asymp;
      3699: aastore
      3700: aastore
      3701: dup
      3702: bipush        100
      3704: iconst_2
      3705: anewarray     #24                 // class java/lang/String
      3708: dup
      3709: iconst_0
      3710: ldc_w         #418                // String ≠
      3713: aastore
      3714: dup
      3715: iconst_1
      3716: ldc_w         #419                // String &ne;
      3719: aastore
      3720: aastore
      3721: dup
      3722: bipush        101
      3724: iconst_2
      3725: anewarray     #24                 // class java/lang/String
      3728: dup
      3729: iconst_0
      3730: ldc_w         #420                // String ≡
      3733: aastore
      3734: dup
      3735: iconst_1
      3736: ldc_w         #421                // String &equiv;
      3739: aastore
      3740: aastore
      3741: dup
      3742: bipush        102
      3744: iconst_2
      3745: anewarray     #24                 // class java/lang/String
      3748: dup
      3749: iconst_0
      3750: ldc_w         #422                // String ≤
      3753: aastore
      3754: dup
      3755: iconst_1
      3756: ldc_w         #423                // String &le;
      3759: aastore
      3760: aastore
      3761: dup
      3762: bipush        103
      3764: iconst_2
      3765: anewarray     #24                 // class java/lang/String
      3768: dup
      3769: iconst_0
      3770: ldc_w         #424                // String ≥
      3773: aastore
      3774: dup
      3775: iconst_1
      3776: ldc_w         #425                // String &ge;
      3779: aastore
      3780: aastore
      3781: dup
      3782: bipush        104
      3784: iconst_2
      3785: anewarray     #24                 // class java/lang/String
      3788: dup
      3789: iconst_0
      3790: ldc_w         #426                // String ⊂
      3793: aastore
      3794: dup
      3795: iconst_1
      3796: ldc_w         #427                // String &sub;
      3799: aastore
      3800: aastore
      3801: dup
      3802: bipush        105
      3804: iconst_2
      3805: anewarray     #24                 // class java/lang/String
      3808: dup
      3809: iconst_0
      3810: ldc_w         #428                // String ⊃
      3813: aastore
      3814: dup
      3815: iconst_1
      3816: ldc_w         #429                // String &sup;
      3819: aastore
      3820: aastore
      3821: dup
      3822: bipush        106
      3824: iconst_2
      3825: anewarray     #24                 // class java/lang/String
      3828: dup
      3829: iconst_0
      3830: ldc_w         #430                // String ⊄
      3833: aastore
      3834: dup
      3835: iconst_1
      3836: ldc_w         #431                // String &nsub;
      3839: aastore
      3840: aastore
      3841: dup
      3842: bipush        107
      3844: iconst_2
      3845: anewarray     #24                 // class java/lang/String
      3848: dup
      3849: iconst_0
      3850: ldc_w         #432                // String ⊆
      3853: aastore
      3854: dup
      3855: iconst_1
      3856: ldc_w         #433                // String &sube;
      3859: aastore
      3860: aastore
      3861: dup
      3862: bipush        108
      3864: iconst_2
      3865: anewarray     #24                 // class java/lang/String
      3868: dup
      3869: iconst_0
      3870: ldc_w         #434                // String ⊇
      3873: aastore
      3874: dup
      3875: iconst_1
      3876: ldc_w         #435                // String &supe;
      3879: aastore
      3880: aastore
      3881: dup
      3882: bipush        109
      3884: iconst_2
      3885: anewarray     #24                 // class java/lang/String
      3888: dup
      3889: iconst_0
      3890: ldc_w         #436                // String ⊕
      3893: aastore
      3894: dup
      3895: iconst_1
      3896: ldc_w         #437                // String &oplus;
      3899: aastore
      3900: aastore
      3901: dup
      3902: bipush        110
      3904: iconst_2
      3905: anewarray     #24                 // class java/lang/String
      3908: dup
      3909: iconst_0
      3910: ldc_w         #438                // String ⊗
      3913: aastore
      3914: dup
      3915: iconst_1
      3916: ldc_w         #439                // String &otimes;
      3919: aastore
      3920: aastore
      3921: dup
      3922: bipush        111
      3924: iconst_2
      3925: anewarray     #24                 // class java/lang/String
      3928: dup
      3929: iconst_0
      3930: ldc_w         #440                // String ⊥
      3933: aastore
      3934: dup
      3935: iconst_1
      3936: ldc_w         #441                // String &perp;
      3939: aastore
      3940: aastore
      3941: dup
      3942: bipush        112
      3944: iconst_2
      3945: anewarray     #24                 // class java/lang/String
      3948: dup
      3949: iconst_0
      3950: ldc_w         #442                // String ⋅
      3953: aastore
      3954: dup
      3955: iconst_1
      3956: ldc_w         #443                // String &sdot;
      3959: aastore
      3960: aastore
      3961: dup
      3962: bipush        113
      3964: iconst_2
      3965: anewarray     #24                 // class java/lang/String
      3968: dup
      3969: iconst_0
      3970: ldc_w         #444                // String ⌈
      3973: aastore
      3974: dup
      3975: iconst_1
      3976: ldc_w         #445                // String &lceil;
      3979: aastore
      3980: aastore
      3981: dup
      3982: bipush        114
      3984: iconst_2
      3985: anewarray     #24                 // class java/lang/String
      3988: dup
      3989: iconst_0
      3990: ldc_w         #446                // String ⌉
      3993: aastore
      3994: dup
      3995: iconst_1
      3996: ldc_w         #447                // String &rceil;
      3999: aastore
      4000: aastore
      4001: dup
      4002: bipush        115
      4004: iconst_2
      4005: anewarray     #24                 // class java/lang/String
      4008: dup
      4009: iconst_0
      4010: ldc_w         #448                // String ⌊
      4013: aastore
      4014: dup
      4015: iconst_1
      4016: ldc_w         #449                // String &lfloor;
      4019: aastore
      4020: aastore
      4021: dup
      4022: bipush        116
      4024: iconst_2
      4025: anewarray     #24                 // class java/lang/String
      4028: dup
      4029: iconst_0
      4030: ldc_w         #450                // String ⌋
      4033: aastore
      4034: dup
      4035: iconst_1
      4036: ldc_w         #451                // String &rfloor;
      4039: aastore
      4040: aastore
      4041: dup
      4042: bipush        117
      4044: iconst_2
      4045: anewarray     #24                 // class java/lang/String
      4048: dup
      4049: iconst_0
      4050: ldc_w         #452                // String 〈
      4053: aastore
      4054: dup
      4055: iconst_1
      4056: ldc_w         #453                // String &lang;
      4059: aastore
      4060: aastore
      4061: dup
      4062: bipush        118
      4064: iconst_2
      4065: anewarray     #24                 // class java/lang/String
      4068: dup
      4069: iconst_0
      4070: ldc_w         #454                // String 〉
      4073: aastore
      4074: dup
      4075: iconst_1
      4076: ldc_w         #455                // String &rang;
      4079: aastore
      4080: aastore
      4081: dup
      4082: bipush        119
      4084: iconst_2
      4085: anewarray     #24                 // class java/lang/String
      4088: dup
      4089: iconst_0
      4090: ldc_w         #456                // String ◊
      4093: aastore
      4094: dup
      4095: iconst_1
      4096: ldc_w         #457                // String &loz;
      4099: aastore
      4100: aastore
      4101: dup
      4102: bipush        120
      4104: iconst_2
      4105: anewarray     #24                 // class java/lang/String
      4108: dup
      4109: iconst_0
      4110: ldc_w         #458                // String ♠
      4113: aastore
      4114: dup
      4115: iconst_1
      4116: ldc_w         #459                // String &spades;
      4119: aastore
      4120: aastore
      4121: dup
      4122: bipush        121
      4124: iconst_2
      4125: anewarray     #24                 // class java/lang/String
      4128: dup
      4129: iconst_0
      4130: ldc_w         #460                // String ♣
      4133: aastore
      4134: dup
      4135: iconst_1
      4136: ldc_w         #461                // String &clubs;
      4139: aastore
      4140: aastore
      4141: dup
      4142: bipush        122
      4144: iconst_2
      4145: anewarray     #24                 // class java/lang/String
      4148: dup
      4149: iconst_0
      4150: ldc_w         #462                // String ♥
      4153: aastore
      4154: dup
      4155: iconst_1
      4156: ldc_w         #463                // String &hearts;
      4159: aastore
      4160: aastore
      4161: dup
      4162: bipush        123
      4164: iconst_2
      4165: anewarray     #24                 // class java/lang/String
      4168: dup
      4169: iconst_0
      4170: ldc_w         #464                // String ♦
      4173: aastore
      4174: dup
      4175: iconst_1
      4176: ldc_w         #465                // String &diams;
      4179: aastore
      4180: aastore
      4181: dup
      4182: bipush        124
      4184: iconst_2
      4185: anewarray     #24                 // class java/lang/String
      4188: dup
      4189: iconst_0
      4190: ldc_w         #466                // String Œ
      4193: aastore
      4194: dup
      4195: iconst_1
      4196: ldc_w         #467                // String &OElig;
      4199: aastore
      4200: aastore
      4201: dup
      4202: bipush        125
      4204: iconst_2
      4205: anewarray     #24                 // class java/lang/String
      4208: dup
      4209: iconst_0
      4210: ldc_w         #468                // String œ
      4213: aastore
      4214: dup
      4215: iconst_1
      4216: ldc_w         #469                // String &oelig;
      4219: aastore
      4220: aastore
      4221: dup
      4222: bipush        126
      4224: iconst_2
      4225: anewarray     #24                 // class java/lang/String
      4228: dup
      4229: iconst_0
      4230: ldc_w         #470                // String Š
      4233: aastore
      4234: dup
      4235: iconst_1
      4236: ldc_w         #471                // String &Scaron;
      4239: aastore
      4240: aastore
      4241: dup
      4242: bipush        127
      4244: iconst_2
      4245: anewarray     #24                 // class java/lang/String
      4248: dup
      4249: iconst_0
      4250: ldc_w         #472                // String š
      4253: aastore
      4254: dup
      4255: iconst_1
      4256: ldc_w         #473                // String &scaron;
      4259: aastore
      4260: aastore
      4261: dup
      4262: sipush        128
      4265: iconst_2
      4266: anewarray     #24                 // class java/lang/String
      4269: dup
      4270: iconst_0
      4271: ldc_w         #474                // String Ÿ
      4274: aastore
      4275: dup
      4276: iconst_1
      4277: ldc_w         #475                // String &Yuml;
      4280: aastore
      4281: aastore
      4282: dup
      4283: sipush        129
      4286: iconst_2
      4287: anewarray     #24                 // class java/lang/String
      4290: dup
      4291: iconst_0
      4292: ldc_w         #476                // String ˆ
      4295: aastore
      4296: dup
      4297: iconst_1
      4298: ldc_w         #477                // String &circ;
      4301: aastore
      4302: aastore
      4303: dup
      4304: sipush        130
      4307: iconst_2
      4308: anewarray     #24                 // class java/lang/String
      4311: dup
      4312: iconst_0
      4313: ldc_w         #478                // String ˜
      4316: aastore
      4317: dup
      4318: iconst_1
      4319: ldc_w         #479                // String &tilde;
      4322: aastore
      4323: aastore
      4324: dup
      4325: sipush        131
      4328: iconst_2
      4329: anewarray     #24                 // class java/lang/String
      4332: dup
      4333: iconst_0
      4334: ldc_w         #480                // String  
      4337: aastore
      4338: dup
      4339: iconst_1
      4340: ldc_w         #481                // String &ensp;
      4343: aastore
      4344: aastore
      4345: dup
      4346: sipush        132
      4349: iconst_2
      4350: anewarray     #24                 // class java/lang/String
      4353: dup
      4354: iconst_0
      4355: ldc_w         #482                // String  
      4358: aastore
      4359: dup
      4360: iconst_1
      4361: ldc_w         #483                // String &emsp;
      4364: aastore
      4365: aastore
      4366: dup
      4367: sipush        133
      4370: iconst_2
      4371: anewarray     #24                 // class java/lang/String
      4374: dup
      4375: iconst_0
      4376: ldc_w         #484                // String  
      4379: aastore
      4380: dup
      4381: iconst_1
      4382: ldc_w         #485                // String &thinsp;
      4385: aastore
      4386: aastore
      4387: dup
      4388: sipush        134
      4391: iconst_2
      4392: anewarray     #24                 // class java/lang/String
      4395: dup
      4396: iconst_0
      4397: ldc_w         #486                // String ‌
      4400: aastore
      4401: dup
      4402: iconst_1
      4403: ldc_w         #487                // String &zwnj;
      4406: aastore
      4407: aastore
      4408: dup
      4409: sipush        135
      4412: iconst_2
      4413: anewarray     #24                 // class java/lang/String
      4416: dup
      4417: iconst_0
      4418: ldc_w         #488                // String ‍
      4421: aastore
      4422: dup
      4423: iconst_1
      4424: ldc_w         #489                // String &zwj;
      4427: aastore
      4428: aastore
      4429: dup
      4430: sipush        136
      4433: iconst_2
      4434: anewarray     #24                 // class java/lang/String
      4437: dup
      4438: iconst_0
      4439: ldc_w         #490                // String ‎
      4442: aastore
      4443: dup
      4444: iconst_1
      4445: ldc_w         #491                // String &lrm;
      4448: aastore
      4449: aastore
      4450: dup
      4451: sipush        137
      4454: iconst_2
      4455: anewarray     #24                 // class java/lang/String
      4458: dup
      4459: iconst_0
      4460: ldc_w         #492                // String ‏
      4463: aastore
      4464: dup
      4465: iconst_1
      4466: ldc_w         #493                // String &rlm;
      4469: aastore
      4470: aastore
      4471: dup
      4472: sipush        138
      4475: iconst_2
      4476: anewarray     #24                 // class java/lang/String
      4479: dup
      4480: iconst_0
      4481: ldc_w         #494                // String –
      4484: aastore
      4485: dup
      4486: iconst_1
      4487: ldc_w         #495                // String &ndash;
      4490: aastore
      4491: aastore
      4492: dup
      4493: sipush        139
      4496: iconst_2
      4497: anewarray     #24                 // class java/lang/String
      4500: dup
      4501: iconst_0
      4502: ldc_w         #496                // String —
      4505: aastore
      4506: dup
      4507: iconst_1
      4508: ldc_w         #497                // String &mdash;
      4511: aastore
      4512: aastore
      4513: dup
      4514: sipush        140
      4517: iconst_2
      4518: anewarray     #24                 // class java/lang/String
      4521: dup
      4522: iconst_0
      4523: ldc_w         #498                // String ‘
      4526: aastore
      4527: dup
      4528: iconst_1
      4529: ldc_w         #499                // String &lsquo;
      4532: aastore
      4533: aastore
      4534: dup
      4535: sipush        141
      4538: iconst_2
      4539: anewarray     #24                 // class java/lang/String
      4542: dup
      4543: iconst_0
      4544: ldc_w         #500                // String ’
      4547: aastore
      4548: dup
      4549: iconst_1
      4550: ldc_w         #501                // String &rsquo;
      4553: aastore
      4554: aastore
      4555: dup
      4556: sipush        142
      4559: iconst_2
      4560: anewarray     #24                 // class java/lang/String
      4563: dup
      4564: iconst_0
      4565: ldc_w         #502                // String ‚
      4568: aastore
      4569: dup
      4570: iconst_1
      4571: ldc_w         #503                // String &sbquo;
      4574: aastore
      4575: aastore
      4576: dup
      4577: sipush        143
      4580: iconst_2
      4581: anewarray     #24                 // class java/lang/String
      4584: dup
      4585: iconst_0
      4586: ldc_w         #504                // String “
      4589: aastore
      4590: dup
      4591: iconst_1
      4592: ldc_w         #505                // String &ldquo;
      4595: aastore
      4596: aastore
      4597: dup
      4598: sipush        144
      4601: iconst_2
      4602: anewarray     #24                 // class java/lang/String
      4605: dup
      4606: iconst_0
      4607: ldc_w         #506                // String ”
      4610: aastore
      4611: dup
      4612: iconst_1
      4613: ldc_w         #507                // String &rdquo;
      4616: aastore
      4617: aastore
      4618: dup
      4619: sipush        145
      4622: iconst_2
      4623: anewarray     #24                 // class java/lang/String
      4626: dup
      4627: iconst_0
      4628: ldc_w         #508                // String „
      4631: aastore
      4632: dup
      4633: iconst_1
      4634: ldc_w         #509                // String &bdquo;
      4637: aastore
      4638: aastore
      4639: dup
      4640: sipush        146
      4643: iconst_2
      4644: anewarray     #24                 // class java/lang/String
      4647: dup
      4648: iconst_0
      4649: ldc_w         #510                // String †
      4652: aastore
      4653: dup
      4654: iconst_1
      4655: ldc_w         #511                // String &dagger;
      4658: aastore
      4659: aastore
      4660: dup
      4661: sipush        147
      4664: iconst_2
      4665: anewarray     #24                 // class java/lang/String
      4668: dup
      4669: iconst_0
      4670: ldc_w         #512                // String ‡
      4673: aastore
      4674: dup
      4675: iconst_1
      4676: ldc_w         #513                // String &Dagger;
      4679: aastore
      4680: aastore
      4681: dup
      4682: sipush        148
      4685: iconst_2
      4686: anewarray     #24                 // class java/lang/String
      4689: dup
      4690: iconst_0
      4691: ldc_w         #514                // String ‰
      4694: aastore
      4695: dup
      4696: iconst_1
      4697: ldc_w         #515                // String &permil;
      4700: aastore
      4701: aastore
      4702: dup
      4703: sipush        149
      4706: iconst_2
      4707: anewarray     #24                 // class java/lang/String
      4710: dup
      4711: iconst_0
      4712: ldc_w         #516                // String ‹
      4715: aastore
      4716: dup
      4717: iconst_1
      4718: ldc_w         #517                // String &lsaquo;
      4721: aastore
      4722: aastore
      4723: dup
      4724: sipush        150
      4727: iconst_2
      4728: anewarray     #24                 // class java/lang/String
      4731: dup
      4732: iconst_0
      4733: ldc_w         #518                // String ›
      4736: aastore
      4737: dup
      4738: iconst_1
      4739: ldc_w         #519                // String &rsaquo;
      4742: aastore
      4743: aastore
      4744: dup
      4745: sipush        151
      4748: iconst_2
      4749: anewarray     #24                 // class java/lang/String
      4752: dup
      4753: iconst_0
      4754: ldc_w         #520                // String €
      4757: aastore
      4758: dup
      4759: iconst_1
      4760: ldc_w         #521                // String &euro;
      4763: aastore
      4764: aastore
      4765: putstatic     #7                  // Field HTML40_EXTENDED_ESCAPE:[[Ljava/lang/String;
      4768: getstatic     #7                  // Field HTML40_EXTENDED_ESCAPE:[[Ljava/lang/String;
      4771: invokestatic  #217                // Method invert:([[Ljava/lang/String;)[[Ljava/lang/String;
      4774: putstatic     #9                  // Field HTML40_EXTENDED_UNESCAPE:[[Ljava/lang/String;
      4777: iconst_4
      4778: anewarray     #23                 // class "[Ljava/lang/String;"
      4781: dup
      4782: iconst_0
      4783: iconst_2
      4784: anewarray     #24                 // class java/lang/String
      4787: dup
      4788: iconst_0
      4789: ldc_w         #522                // String \"
      4792: aastore
      4793: dup
      4794: iconst_1
      4795: ldc_w         #523                // String &quot;
      4798: aastore
      4799: aastore
      4800: dup
      4801: iconst_1
      4802: iconst_2
      4803: anewarray     #24                 // class java/lang/String
      4806: dup
      4807: iconst_0
      4808: ldc_w         #524                // String &
      4811: aastore
      4812: dup
      4813: iconst_1
      4814: ldc_w         #525                // String &amp;
      4817: aastore
      4818: aastore
      4819: dup
      4820: iconst_2
      4821: iconst_2
      4822: anewarray     #24                 // class java/lang/String
      4825: dup
      4826: iconst_0
      4827: ldc_w         #526                // String <
      4830: aastore
      4831: dup
      4832: iconst_1
      4833: ldc_w         #527                // String &lt;
      4836: aastore
      4837: aastore
      4838: dup
      4839: iconst_3
      4840: iconst_2
      4841: anewarray     #24                 // class java/lang/String
      4844: dup
      4845: iconst_0
      4846: ldc_w         #528                // String >
      4849: aastore
      4850: dup
      4851: iconst_1
      4852: ldc_w         #529                // String &gt;
      4855: aastore
      4856: aastore
      4857: putstatic     #11                 // Field BASIC_ESCAPE:[[Ljava/lang/String;
      4860: getstatic     #11                 // Field BASIC_ESCAPE:[[Ljava/lang/String;
      4863: invokestatic  #217                // Method invert:([[Ljava/lang/String;)[[Ljava/lang/String;
      4866: putstatic     #13                 // Field BASIC_UNESCAPE:[[Ljava/lang/String;
      4869: iconst_1
      4870: anewarray     #23                 // class "[Ljava/lang/String;"
      4873: dup
      4874: iconst_0
      4875: iconst_2
      4876: anewarray     #24                 // class java/lang/String
      4879: dup
      4880: iconst_0
      4881: ldc_w         #530                // String \'
      4884: aastore
      4885: dup
      4886: iconst_1
      4887: ldc_w         #531                // String &apos;
      4890: aastore
      4891: aastore
      4892: putstatic     #15                 // Field APOS_ESCAPE:[[Ljava/lang/String;
      4895: getstatic     #15                 // Field APOS_ESCAPE:[[Ljava/lang/String;
      4898: invokestatic  #217                // Method invert:([[Ljava/lang/String;)[[Ljava/lang/String;
      4901: putstatic     #17                 // Field APOS_UNESCAPE:[[Ljava/lang/String;
      4904: iconst_5
      4905: anewarray     #23                 // class "[Ljava/lang/String;"
      4908: dup
      4909: iconst_0
      4910: iconst_2
      4911: anewarray     #24                 // class java/lang/String
      4914: dup
      4915: iconst_0
      4916: ldc_w         #532                // String \b
      4919: aastore
      4920: dup
      4921: iconst_1
      4922: ldc_w         #533                // String \\b
      4925: aastore
      4926: aastore
      4927: dup
      4928: iconst_1
      4929: iconst_2
      4930: anewarray     #24                 // class java/lang/String
      4933: dup
      4934: iconst_0
      4935: ldc_w         #534                // String \n
      4938: aastore
      4939: dup
      4940: iconst_1
      4941: ldc_w         #535                // String \\n
      4944: aastore
      4945: aastore
      4946: dup
      4947: iconst_2
      4948: iconst_2
      4949: anewarray     #24                 // class java/lang/String
      4952: dup
      4953: iconst_0
      4954: ldc_w         #536                // String \t
      4957: aastore
      4958: dup
      4959: iconst_1
      4960: ldc_w         #537                // String \\t
      4963: aastore
      4964: aastore
      4965: dup
      4966: iconst_3
      4967: iconst_2
      4968: anewarray     #24                 // class java/lang/String
      4971: dup
      4972: iconst_0
      4973: ldc_w         #538                // String \f
      4976: aastore
      4977: dup
      4978: iconst_1
      4979: ldc_w         #539                // String \\f
      4982: aastore
      4983: aastore
      4984: dup
      4985: iconst_4
      4986: iconst_2
      4987: anewarray     #24                 // class java/lang/String
      4990: dup
      4991: iconst_0
      4992: ldc_w         #540                // String \r
      4995: aastore
      4996: dup
      4997: iconst_1
      4998: ldc_w         #541                // String \\r
      5001: aastore
      5002: aastore
      5003: putstatic     #19                 // Field JAVA_CTRL_CHARS_ESCAPE:[[Ljava/lang/String;
      5006: getstatic     #19                 // Field JAVA_CTRL_CHARS_ESCAPE:[[Ljava/lang/String;
      5009: invokestatic  #217                // Method invert:([[Ljava/lang/String;)[[Ljava/lang/String;
      5012: putstatic     #21                 // Field JAVA_CTRL_CHARS_UNESCAPE:[[Ljava/lang/String;
      5015: return
      LineNumberTable:
        line 41: 0
        line 148: 1730
        line 160: 1739
        line 365: 4768
        line 377: 4777
        line 392: 4860
        line 402: 4869
        line 414: 4895
        line 426: 4904
        line 442: 5006
}
SourceFile: "EntityArrays.java"
Deprecated: true
RuntimeVisibleAnnotations:
  0: #575()
    java.lang.Deprecated
