Classfile /Users/mw/Projects/slang-braindump/.jar/jar8/assemble/slang-braindump/assemble/content/org/apache/commons/lang3/text/translate/LookupTranslator.class
  Last modified May 29, 2022; size 2385 bytes
  SHA-256 checksum 5f41905def56af63214e421fffa44ae7667e4f0d9f5294ce4867b9fc54e665f6
  Compiled from "LookupTranslator.java"
public class org.apache.commons.lang3.text.translate.LookupTranslator extends org.apache.commons.lang3.text.translate.CharSequenceTranslator
  minor version: 0
  major version: 52
  flags: (0x0021) ACC_PUBLIC, ACC_SUPER
  this_class: #23                         // org/apache/commons/lang3/text/translate/LookupTranslator
  super_class: #24                        // org/apache/commons/lang3/text/translate/CharSequenceTranslator
  interfaces: 0, fields: 4, methods: 2, attributes: 3
Constant pool:
    #1 = Methodref          #24.#71       // org/apache/commons/lang3/text/translate/CharSequenceTranslator."<init>":()V
    #2 = Class              #72           // java/util/HashMap
    #3 = Methodref          #2.#71        // java/util/HashMap."<init>":()V
    #4 = Fieldref           #23.#73       // org/apache/commons/lang3/text/translate/LookupTranslator.lookupMap:Ljava/util/HashMap;
    #5 = Class              #74           // java/util/HashSet
    #6 = Methodref          #5.#71        // java/util/HashSet."<init>":()V
    #7 = Fieldref           #23.#75       // org/apache/commons/lang3/text/translate/LookupTranslator.prefixSet:Ljava/util/HashSet;
    #8 = Class              #76           // java/lang/Integer
    #9 = Integer            2147483647
   #10 = InterfaceMethodref #77.#78       // java/lang/CharSequence.toString:()Ljava/lang/String;
   #11 = Methodref          #2.#79        // java/util/HashMap.put:(Ljava/lang/Object;Ljava/lang/Object;)Ljava/lang/Object;
   #12 = InterfaceMethodref #77.#80       // java/lang/CharSequence.charAt:(I)C
   #13 = Methodref          #81.#82       // java/lang/Character.valueOf:(C)Ljava/lang/Character;
   #14 = Methodref          #5.#83        // java/util/HashSet.add:(Ljava/lang/Object;)Z
   #15 = InterfaceMethodref #77.#84       // java/lang/CharSequence.length:()I
   #16 = Fieldref           #23.#85       // org/apache/commons/lang3/text/translate/LookupTranslator.shortest:I
   #17 = Fieldref           #23.#86       // org/apache/commons/lang3/text/translate/LookupTranslator.longest:I
   #18 = Methodref          #5.#87        // java/util/HashSet.contains:(Ljava/lang/Object;)Z
   #19 = InterfaceMethodref #77.#88       // java/lang/CharSequence.subSequence:(II)Ljava/lang/CharSequence;
   #20 = Methodref          #2.#89        // java/util/HashMap.get:(Ljava/lang/Object;)Ljava/lang/Object;
   #21 = Class              #90           // java/lang/String
   #22 = Methodref          #91.#92       // java/io/Writer.write:(Ljava/lang/String;)V
   #23 = Class              #93           // org/apache/commons/lang3/text/translate/LookupTranslator
   #24 = Class              #94           // org/apache/commons/lang3/text/translate/CharSequenceTranslator
   #25 = Utf8               lookupMap
   #26 = Utf8               Ljava/util/HashMap;
   #27 = Utf8               Signature
   #28 = Utf8               Ljava/util/HashMap<Ljava/lang/String;Ljava/lang/String;>;
   #29 = Utf8               prefixSet
   #30 = Utf8               Ljava/util/HashSet;
   #31 = Utf8               Ljava/util/HashSet<Ljava/lang/Character;>;
   #32 = Utf8               shortest
   #33 = Utf8               I
   #34 = Utf8               longest
   #35 = Utf8               <init>
   #36 = Utf8               ([[Ljava/lang/CharSequence;)V
   #37 = Utf8               Code
   #38 = Utf8               LineNumberTable
   #39 = Utf8               LocalVariableTable
   #40 = Utf8               sz
   #41 = Utf8               seq
   #42 = Utf8               [Ljava/lang/CharSequence;
   #43 = Utf8               this
   #44 = Utf8               Lorg/apache/commons/lang3/text/translate/LookupTranslator;
   #45 = Utf8               lookup
   #46 = Utf8               [[Ljava/lang/CharSequence;
   #47 = Utf8               _shortest
   #48 = Utf8               _longest
   #49 = Utf8               StackMapTable
   #50 = Class              #46           // "[[Ljava/lang/CharSequence;"
   #51 = Class              #42           // "[Ljava/lang/CharSequence;"
   #52 = Utf8               translate
   #53 = Utf8               (Ljava/lang/CharSequence;ILjava/io/Writer;)I
   #54 = Utf8               subSeq
   #55 = Utf8               Ljava/lang/CharSequence;
   #56 = Utf8               result
   #57 = Utf8               Ljava/lang/String;
   #58 = Utf8               i
   #59 = Utf8               max
   #60 = Utf8               input
   #61 = Utf8               index
   #62 = Utf8               out
   #63 = Utf8               Ljava/io/Writer;
   #64 = Utf8               Exceptions
   #65 = Class              #95           // java/io/IOException
   #66 = Utf8               SourceFile
   #67 = Utf8               LookupTranslator.java
   #68 = Utf8               Deprecated
   #69 = Utf8               RuntimeVisibleAnnotations
   #70 = Utf8               Ljava/lang/Deprecated;
   #71 = NameAndType        #35:#96       // "<init>":()V
   #72 = Utf8               java/util/HashMap
   #73 = NameAndType        #25:#26       // lookupMap:Ljava/util/HashMap;
   #74 = Utf8               java/util/HashSet
   #75 = NameAndType        #29:#30       // prefixSet:Ljava/util/HashSet;
   #76 = Utf8               java/lang/Integer
   #77 = Class              #97           // java/lang/CharSequence
   #78 = NameAndType        #98:#99       // toString:()Ljava/lang/String;
   #79 = NameAndType        #100:#101     // put:(Ljava/lang/Object;Ljava/lang/Object;)Ljava/lang/Object;
   #80 = NameAndType        #102:#103     // charAt:(I)C
   #81 = Class              #104          // java/lang/Character
   #82 = NameAndType        #105:#106     // valueOf:(C)Ljava/lang/Character;
   #83 = NameAndType        #107:#108     // add:(Ljava/lang/Object;)Z
   #84 = NameAndType        #109:#110     // length:()I
   #85 = NameAndType        #32:#33       // shortest:I
   #86 = NameAndType        #34:#33       // longest:I
   #87 = NameAndType        #111:#108     // contains:(Ljava/lang/Object;)Z
   #88 = NameAndType        #112:#113     // subSequence:(II)Ljava/lang/CharSequence;
   #89 = NameAndType        #114:#115     // get:(Ljava/lang/Object;)Ljava/lang/Object;
   #90 = Utf8               java/lang/String
   #91 = Class              #116          // java/io/Writer
   #92 = NameAndType        #117:#118     // write:(Ljava/lang/String;)V
   #93 = Utf8               org/apache/commons/lang3/text/translate/LookupTranslator
   #94 = Utf8               org/apache/commons/lang3/text/translate/CharSequenceTranslator
   #95 = Utf8               java/io/IOException
   #96 = Utf8               ()V
   #97 = Utf8               java/lang/CharSequence
   #98 = Utf8               toString
   #99 = Utf8               ()Ljava/lang/String;
  #100 = Utf8               put
  #101 = Utf8               (Ljava/lang/Object;Ljava/lang/Object;)Ljava/lang/Object;
  #102 = Utf8               charAt
  #103 = Utf8               (I)C
  #104 = Utf8               java/lang/Character
  #105 = Utf8               valueOf
  #106 = Utf8               (C)Ljava/lang/Character;
  #107 = Utf8               add
  #108 = Utf8               (Ljava/lang/Object;)Z
  #109 = Utf8               length
  #110 = Utf8               ()I
  #111 = Utf8               contains
  #112 = Utf8               subSequence
  #113 = Utf8               (II)Ljava/lang/CharSequence;
  #114 = Utf8               get
  #115 = Utf8               (Ljava/lang/Object;)Ljava/lang/Object;
  #116 = Utf8               java/io/Writer
  #117 = Utf8               write
  #118 = Utf8               (Ljava/lang/String;)V
{
  private final java.util.HashMap<java.lang.String, java.lang.String> lookupMap;
    descriptor: Ljava/util/HashMap;
    flags: (0x0012) ACC_PRIVATE, ACC_FINAL
    Signature: #28                          // Ljava/util/HashMap<Ljava/lang/String;Ljava/lang/String;>;

  private final java.util.HashSet<java.lang.Character> prefixSet;
    descriptor: Ljava/util/HashSet;
    flags: (0x0012) ACC_PRIVATE, ACC_FINAL
    Signature: #31                          // Ljava/util/HashSet<Ljava/lang/Character;>;

  private final int shortest;
    descriptor: I
    flags: (0x0012) ACC_PRIVATE, ACC_FINAL

  private final int longest;
    descriptor: I
    flags: (0x0012) ACC_PRIVATE, ACC_FINAL

  public org.apache.commons.lang3.text.translate.LookupTranslator(java.lang.CharSequence[]...);
    descriptor: ([[Ljava/lang/CharSequence;)V
    flags: (0x0081) ACC_PUBLIC, ACC_VARARGS
    Code:
      stack=4, locals=9, args_size=2
         0: aload_0
         1: invokespecial #1                  // Method org/apache/commons/lang3/text/translate/CharSequenceTranslator."<init>":()V
         4: aload_0
         5: new           #2                  // class java/util/HashMap
         8: dup
         9: invokespecial #3                  // Method java/util/HashMap."<init>":()V
        12: putfield      #4                  // Field lookupMap:Ljava/util/HashMap;
        15: aload_0
        16: new           #5                  // class java/util/HashSet
        19: dup
        20: invokespecial #6                  // Method java/util/HashSet."<init>":()V
        23: putfield      #7                  // Field prefixSet:Ljava/util/HashSet;
        26: ldc           #9                  // int 2147483647
        28: istore_2
        29: iconst_0
        30: istore_3
        31: aload_1
        32: ifnull        142
        35: aload_1
        36: astore        4
        38: aload         4
        40: arraylength
        41: istore        5
        43: iconst_0
        44: istore        6
        46: iload         6
        48: iload         5
        50: if_icmpge     142
        53: aload         4
        55: iload         6
        57: aaload
        58: astore        7
        60: aload_0
        61: getfield      #4                  // Field lookupMap:Ljava/util/HashMap;
        64: aload         7
        66: iconst_0
        67: aaload
        68: invokeinterface #10,  1           // InterfaceMethod java/lang/CharSequence.toString:()Ljava/lang/String;
        73: aload         7
        75: iconst_1
        76: aaload
        77: invokeinterface #10,  1           // InterfaceMethod java/lang/CharSequence.toString:()Ljava/lang/String;
        82: invokevirtual #11                 // Method java/util/HashMap.put:(Ljava/lang/Object;Ljava/lang/Object;)Ljava/lang/Object;
        85: pop
        86: aload_0
        87: getfield      #7                  // Field prefixSet:Ljava/util/HashSet;
        90: aload         7
        92: iconst_0
        93: aaload
        94: iconst_0
        95: invokeinterface #12,  2           // InterfaceMethod java/lang/CharSequence.charAt:(I)C
       100: invokestatic  #13                 // Method java/lang/Character.valueOf:(C)Ljava/lang/Character;
       103: invokevirtual #14                 // Method java/util/HashSet.add:(Ljava/lang/Object;)Z
       106: pop
       107: aload         7
       109: iconst_0
       110: aaload
       111: invokeinterface #15,  1           // InterfaceMethod java/lang/CharSequence.length:()I
       116: istore        8
       118: iload         8
       120: iload_2
       121: if_icmpge     127
       124: iload         8
       126: istore_2
       127: iload         8
       129: iload_3
       130: if_icmple     136
       133: iload         8
       135: istore_3
       136: iinc          6, 1
       139: goto          46
       142: aload_0
       143: iload_2
       144: putfield      #16                 // Field shortest:I
       147: aload_0
       148: iload_3
       149: putfield      #17                 // Field longest:I
       152: return
      LineNumberTable:
        line 49: 0
        line 50: 4
        line 51: 15
        line 52: 26
        line 53: 29
        line 54: 31
        line 55: 35
        line 56: 60
        line 57: 86
        line 58: 107
        line 59: 118
        line 60: 124
        line 62: 127
        line 63: 133
        line 55: 136
        line 67: 142
        line 68: 147
        line 69: 152
      LocalVariableTable:
        Start  Length  Slot  Name   Signature
          118      18     8    sz   I
           60      76     7   seq   [Ljava/lang/CharSequence;
            0     153     0  this   Lorg/apache/commons/lang3/text/translate/LookupTranslator;
            0     153     1 lookup   [[Ljava/lang/CharSequence;
           29     124     2 _shortest   I
           31     122     3 _longest   I
      StackMapTable: number_of_entries = 4
        frame_type = 255 /* full_frame */
          offset_delta = 46
          locals = [ class org/apache/commons/lang3/text/translate/LookupTranslator, class "[[Ljava/lang/CharSequence;", int, int, class "[[Ljava/lang/CharSequence;", int, int ]
          stack = []
        frame_type = 253 /* append */
          offset_delta = 80
          locals = [ class "[Ljava/lang/CharSequence;", int ]
        frame_type = 249 /* chop */
          offset_delta = 8
        frame_type = 248 /* chop */
          offset_delta = 5

  public int translate(java.lang.CharSequence, int, java.io.Writer) throws java.io.IOException;
    descriptor: (Ljava/lang/CharSequence;ILjava/io/Writer;)I
    flags: (0x0001) ACC_PUBLIC
    Code:
      stack=4, locals=8, args_size=4
         0: aload_0
         1: getfield      #7                  // Field prefixSet:Ljava/util/HashSet;
         4: aload_1
         5: iload_2
         6: invokeinterface #12,  2           // InterfaceMethod java/lang/CharSequence.charAt:(I)C
        11: invokestatic  #13                 // Method java/lang/Character.valueOf:(C)Ljava/lang/Character;
        14: invokevirtual #18                 // Method java/util/HashSet.contains:(Ljava/lang/Object;)Z
        17: ifeq          116
        20: aload_0
        21: getfield      #17                 // Field longest:I
        24: istore        4
        26: iload_2
        27: aload_0
        28: getfield      #17                 // Field longest:I
        31: iadd
        32: aload_1
        33: invokeinterface #15,  1           // InterfaceMethod java/lang/CharSequence.length:()I
        38: if_icmple     51
        41: aload_1
        42: invokeinterface #15,  1           // InterfaceMethod java/lang/CharSequence.length:()I
        47: iload_2
        48: isub
        49: istore        4
        51: iload         4
        53: istore        5
        55: iload         5
        57: aload_0
        58: getfield      #16                 // Field shortest:I
        61: if_icmplt     116
        64: aload_1
        65: iload_2
        66: iload_2
        67: iload         5
        69: iadd
        70: invokeinterface #19,  3           // InterfaceMethod java/lang/CharSequence.subSequence:(II)Ljava/lang/CharSequence;
        75: astore        6
        77: aload_0
        78: getfield      #4                  // Field lookupMap:Ljava/util/HashMap;
        81: aload         6
        83: invokeinterface #10,  1           // InterfaceMethod java/lang/CharSequence.toString:()Ljava/lang/String;
        88: invokevirtual #20                 // Method java/util/HashMap.get:(Ljava/lang/Object;)Ljava/lang/Object;
        91: checkcast     #21                 // class java/lang/String
        94: astore        7
        96: aload         7
        98: ifnull        110
       101: aload_3
       102: aload         7
       104: invokevirtual #22                 // Method java/io/Writer.write:(Ljava/lang/String;)V
       107: iload         5
       109: ireturn
       110: iinc          5, -1
       113: goto          55
       116: iconst_0
       117: ireturn
      LineNumberTable:
        line 77: 0
        line 78: 20
        line 79: 26
        line 80: 41
        line 83: 51
        line 84: 64
        line 85: 77
        line 87: 96
        line 88: 101
        line 89: 107
        line 83: 110
        line 93: 116
      LocalVariableTable:
        Start  Length  Slot  Name   Signature
           77      33     6 subSeq   Ljava/lang/CharSequence;
           96      14     7 result   Ljava/lang/String;
           55      61     5     i   I
           26      90     4   max   I
            0     118     0  this   Lorg/apache/commons/lang3/text/translate/LookupTranslator;
            0     118     1 input   Ljava/lang/CharSequence;
            0     118     2 index   I
            0     118     3   out   Ljava/io/Writer;
      StackMapTable: number_of_entries = 4
        frame_type = 252 /* append */
          offset_delta = 51
          locals = [ int ]
        frame_type = 252 /* append */
          offset_delta = 3
          locals = [ int ]
        frame_type = 54 /* same */
        frame_type = 249 /* chop */
          offset_delta = 5
    Exceptions:
      throws java.io.IOException
}
SourceFile: "LookupTranslator.java"
Deprecated: true
RuntimeVisibleAnnotations:
  0: #70()
    java.lang.Deprecated
