Classfile /Users/mw/Projects/slang-braindump/.jar/jar11/assemble/slang-braindump/assemble/content/com/fasterxml/jackson/databind/jsonschema/JsonSchema.class
  Last modified May 29, 2022; size 1785 bytes
  SHA-256 checksum e20e08778cf94d7ae5b8b2933d99e2c1f623d469633b6288fe33b182aa12cd84
  Compiled from "JsonSchema.java"
public class com.fasterxml.jackson.databind.jsonschema.JsonSchema
  minor version: 0
  major version: 52
  flags: (0x0021) ACC_PUBLIC, ACC_SUPER
  this_class: #5                          // com/fasterxml/jackson/databind/jsonschema/JsonSchema
  super_class: #12                        // java/lang/Object
  interfaces: 0, fields: 1, methods: 6, attributes: 3
Constant pool:
   #1 = Methodref          #12.#45        // java/lang/Object."<init>":()V
   #2 = Fieldref           #5.#46         // com/fasterxml/jackson/databind/jsonschema/JsonSchema.schema:Lcom/fasterxml/jackson/databind/node/ObjectNode;
   #3 = Methodref          #47.#48        // com/fasterxml/jackson/databind/node/ObjectNode.toString:()Ljava/lang/String;
   #4 = Methodref          #47.#49        // com/fasterxml/jackson/databind/node/ObjectNode.hashCode:()I
   #5 = Class              #50            // com/fasterxml/jackson/databind/jsonschema/JsonSchema
   #6 = Methodref          #47.#51        // com/fasterxml/jackson/databind/node/ObjectNode.equals:(Ljava/lang/Object;)Z
   #7 = Fieldref           #52.#53        // com/fasterxml/jackson/databind/node/JsonNodeFactory.instance:Lcom/fasterxml/jackson/databind/node/JsonNodeFactory;
   #8 = Methodref          #52.#54        // com/fasterxml/jackson/databind/node/JsonNodeFactory.objectNode:()Lcom/fasterxml/jackson/databind/node/ObjectNode;
   #9 = String             #55            // type
  #10 = String             #56            // any
  #11 = Methodref          #47.#57        // com/fasterxml/jackson/databind/node/ObjectNode.put:(Ljava/lang/String;Ljava/lang/String;)Lcom/fasterxml/jackson/databind/node/ObjectNode;
  #12 = Class              #58            // java/lang/Object
  #13 = Utf8               schema
  #14 = Utf8               Lcom/fasterxml/jackson/databind/node/ObjectNode;
  #15 = Utf8               <init>
  #16 = Utf8               (Lcom/fasterxml/jackson/databind/node/ObjectNode;)V
  #17 = Utf8               Code
  #18 = Utf8               LineNumberTable
  #19 = Utf8               LocalVariableTable
  #20 = Utf8               this
  #21 = Utf8               Lcom/fasterxml/jackson/databind/jsonschema/JsonSchema;
  #22 = Utf8               RuntimeVisibleAnnotations
  #23 = Utf8               Lcom/fasterxml/jackson/annotation/JsonCreator;
  #24 = Utf8               getSchemaNode
  #25 = Utf8               ()Lcom/fasterxml/jackson/databind/node/ObjectNode;
  #26 = Utf8               Lcom/fasterxml/jackson/annotation/JsonValue;
  #27 = Utf8               toString
  #28 = Utf8               ()Ljava/lang/String;
  #29 = Utf8               hashCode
  #30 = Utf8               ()I
  #31 = Utf8               equals
  #32 = Utf8               (Ljava/lang/Object;)Z
  #33 = Utf8               o
  #34 = Utf8               Ljava/lang/Object;
  #35 = Utf8               other
  #36 = Utf8               StackMapTable
  #37 = Class              #50            // com/fasterxml/jackson/databind/jsonschema/JsonSchema
  #38 = Utf8               getDefaultSchemaNode
  #39 = Utf8               ()Lcom/fasterxml/jackson/databind/JsonNode;
  #40 = Utf8               objectNode
  #41 = Utf8               SourceFile
  #42 = Utf8               JsonSchema.java
  #43 = Utf8               Deprecated
  #44 = Utf8               Ljava/lang/Deprecated;
  #45 = NameAndType        #15:#59        // "<init>":()V
  #46 = NameAndType        #13:#14        // schema:Lcom/fasterxml/jackson/databind/node/ObjectNode;
  #47 = Class              #60            // com/fasterxml/jackson/databind/node/ObjectNode
  #48 = NameAndType        #27:#28        // toString:()Ljava/lang/String;
  #49 = NameAndType        #29:#30        // hashCode:()I
  #50 = Utf8               com/fasterxml/jackson/databind/jsonschema/JsonSchema
  #51 = NameAndType        #31:#32        // equals:(Ljava/lang/Object;)Z
  #52 = Class              #61            // com/fasterxml/jackson/databind/node/JsonNodeFactory
  #53 = NameAndType        #62:#63        // instance:Lcom/fasterxml/jackson/databind/node/JsonNodeFactory;
  #54 = NameAndType        #40:#25        // objectNode:()Lcom/fasterxml/jackson/databind/node/ObjectNode;
  #55 = Utf8               type
  #56 = Utf8               any
  #57 = NameAndType        #64:#65        // put:(Ljava/lang/String;Ljava/lang/String;)Lcom/fasterxml/jackson/databind/node/ObjectNode;
  #58 = Utf8               java/lang/Object
  #59 = Utf8               ()V
  #60 = Utf8               com/fasterxml/jackson/databind/node/ObjectNode
  #61 = Utf8               com/fasterxml/jackson/databind/node/JsonNodeFactory
  #62 = Utf8               instance
  #63 = Utf8               Lcom/fasterxml/jackson/databind/node/JsonNodeFactory;
  #64 = Utf8               put
  #65 = Utf8               (Ljava/lang/String;Ljava/lang/String;)Lcom/fasterxml/jackson/databind/node/ObjectNode;
{
  private final com.fasterxml.jackson.databind.node.ObjectNode schema;
    descriptor: Lcom/fasterxml/jackson/databind/node/ObjectNode;
    flags: (0x0012) ACC_PRIVATE, ACC_FINAL

  public com.fasterxml.jackson.databind.jsonschema.JsonSchema(com.fasterxml.jackson.databind.node.ObjectNode);
    descriptor: (Lcom/fasterxml/jackson/databind/node/ObjectNode;)V
    flags: (0x0001) ACC_PUBLIC
    Code:
      stack=2, locals=2, args_size=2
         0: aload_0
         1: invokespecial #1                  // Method java/lang/Object."<init>":()V
         4: aload_0
         5: aload_1
         6: putfield      #2                  // Field schema:Lcom/fasterxml/jackson/databind/node/ObjectNode;
         9: return
      LineNumberTable:
        line 37: 0
        line 38: 4
        line 39: 9
      LocalVariableTable:
        Start  Length  Slot  Name   Signature
            0      10     0  this   Lcom/fasterxml/jackson/databind/jsonschema/JsonSchema;
            0      10     1 schema   Lcom/fasterxml/jackson/databind/node/ObjectNode;
    RuntimeVisibleAnnotations:
      0: #23()
        com.fasterxml.jackson.annotation.JsonCreator

  public com.fasterxml.jackson.databind.node.ObjectNode getSchemaNode();
    descriptor: ()Lcom/fasterxml/jackson/databind/node/ObjectNode;
    flags: (0x0001) ACC_PUBLIC
    Code:
      stack=1, locals=1, args_size=1
         0: aload_0
         1: getfield      #2                  // Field schema:Lcom/fasterxml/jackson/databind/node/ObjectNode;
         4: areturn
      LineNumberTable:
        line 53: 0
      LocalVariableTable:
        Start  Length  Slot  Name   Signature
            0       5     0  this   Lcom/fasterxml/jackson/databind/jsonschema/JsonSchema;
    RuntimeVisibleAnnotations:
      0: #26()
        com.fasterxml.jackson.annotation.JsonValue

  public java.lang.String toString();
    descriptor: ()Ljava/lang/String;
    flags: (0x0001) ACC_PUBLIC
    Code:
      stack=1, locals=1, args_size=1
         0: aload_0
         1: getfield      #2                  // Field schema:Lcom/fasterxml/jackson/databind/node/ObjectNode;
         4: invokevirtual #3                  // Method com/fasterxml/jackson/databind/node/ObjectNode.toString:()Ljava/lang/String;
         7: areturn
      LineNumberTable:
        line 59: 0
      LocalVariableTable:
        Start  Length  Slot  Name   Signature
            0       8     0  this   Lcom/fasterxml/jackson/databind/jsonschema/JsonSchema;

  public int hashCode();
    descriptor: ()I
    flags: (0x0001) ACC_PUBLIC
    Code:
      stack=1, locals=1, args_size=1
         0: aload_0
         1: getfield      #2                  // Field schema:Lcom/fasterxml/jackson/databind/node/ObjectNode;
         4: invokevirtual #4                  // Method com/fasterxml/jackson/databind/node/ObjectNode.hashCode:()I
         7: ireturn
      LineNumberTable:
        line 65: 0
      LocalVariableTable:
        Start  Length  Slot  Name   Signature
            0       8     0  this   Lcom/fasterxml/jackson/databind/jsonschema/JsonSchema;

  public boolean equals(java.lang.Object);
    descriptor: (Ljava/lang/Object;)Z
    flags: (0x0001) ACC_PUBLIC
    Code:
      stack=2, locals=3, args_size=2
         0: aload_1
         1: aload_0
         2: if_acmpne     7
         5: iconst_1
         6: ireturn
         7: aload_1
         8: ifnonnull     13
        11: iconst_0
        12: ireturn
        13: aload_1
        14: instanceof    #5                  // class com/fasterxml/jackson/databind/jsonschema/JsonSchema
        17: ifne          22
        20: iconst_0
        21: ireturn
        22: aload_1
        23: checkcast     #5                  // class com/fasterxml/jackson/databind/jsonschema/JsonSchema
        26: astore_2
        27: aload_0
        28: getfield      #2                  // Field schema:Lcom/fasterxml/jackson/databind/node/ObjectNode;
        31: ifnonnull     47
        34: aload_2
        35: getfield      #2                  // Field schema:Lcom/fasterxml/jackson/databind/node/ObjectNode;
        38: ifnonnull     45
        41: iconst_1
        42: goto          46
        45: iconst_0
        46: ireturn
        47: aload_0
        48: getfield      #2                  // Field schema:Lcom/fasterxml/jackson/databind/node/ObjectNode;
        51: aload_2
        52: getfield      #2                  // Field schema:Lcom/fasterxml/jackson/databind/node/ObjectNode;
        55: invokevirtual #6                  // Method com/fasterxml/jackson/databind/node/ObjectNode.equals:(Ljava/lang/Object;)Z
        58: ireturn
      LineNumberTable:
        line 71: 0
        line 72: 7
        line 73: 13
        line 75: 22
        line 76: 27
        line 77: 34
        line 79: 47
      LocalVariableTable:
        Start  Length  Slot  Name   Signature
            0      59     0  this   Lcom/fasterxml/jackson/databind/jsonschema/JsonSchema;
            0      59     1     o   Ljava/lang/Object;
           27      32     2 other   Lcom/fasterxml/jackson/databind/jsonschema/JsonSchema;
      StackMapTable: number_of_entries = 6
        frame_type = 7 /* same */
        frame_type = 5 /* same */
        frame_type = 8 /* same */
        frame_type = 252 /* append */
          offset_delta = 22
          locals = [ class com/fasterxml/jackson/databind/jsonschema/JsonSchema ]
        frame_type = 64 /* same_locals_1_stack_item */
          stack = [ int ]
        frame_type = 0 /* same */

  public static com.fasterxml.jackson.databind.JsonNode getDefaultSchemaNode();
    descriptor: ()Lcom/fasterxml/jackson/databind/JsonNode;
    flags: (0x0009) ACC_PUBLIC, ACC_STATIC
    Code:
      stack=3, locals=1, args_size=0
         0: getstatic     #7                  // Field com/fasterxml/jackson/databind/node/JsonNodeFactory.instance:Lcom/fasterxml/jackson/databind/node/JsonNodeFactory;
         3: invokevirtual #8                  // Method com/fasterxml/jackson/databind/node/JsonNodeFactory.objectNode:()Lcom/fasterxml/jackson/databind/node/ObjectNode;
         6: astore_0
         7: aload_0
         8: ldc           #9                  // String type
        10: ldc           #10                 // String any
        12: invokevirtual #11                 // Method com/fasterxml/jackson/databind/node/ObjectNode.put:(Ljava/lang/String;Ljava/lang/String;)Lcom/fasterxml/jackson/databind/node/ObjectNode;
        15: pop
        16: aload_0
        17: areturn
      LineNumberTable:
        line 89: 0
        line 90: 7
        line 93: 16
      LocalVariableTable:
        Start  Length  Slot  Name   Signature
            7      11     0 objectNode   Lcom/fasterxml/jackson/databind/node/ObjectNode;
}
SourceFile: "JsonSchema.java"
Deprecated: true
RuntimeVisibleAnnotations:
  0: #44()
    java.lang.Deprecated
