Classfile /Users/mw/Projects/slang-braindump/.jar/jar8/assemble/slang-braindump/assemble/content/org/scalatest/freespec/FixtureAsyncFreeSpecLike.class
  Last modified May 29, 2022; size 21404 bytes
  SHA-256 checksum de989a07fabff4f22d2842aa5cca804f6c55683a83984d2bece359ca1243d3ba
  Compiled from "FixtureAsyncFreeSpecLike.scala"
public interface org.scalatest.freespec.FixtureAsyncFreeSpecLike extends org.scalatest.FixtureAsyncTestSuite,org.scalatest.FixtureAsyncTestRegistration,org.scalatest.Informing,org.scalatest.Notifying,org.scalatest.Alerting,org.scalatest.Documenting
  minor version: 0
  major version: 52
  flags: (0x0601) ACC_PUBLIC, ACC_INTERFACE, ACC_ABSTRACT
  this_class: #2                          // org/scalatest/freespec/FixtureAsyncFreeSpecLike
  super_class: #4                         // java/lang/Object
  interfaces: 6, fields: 0, methods: 57, attributes: 6
Constant pool:
    #1 = Utf8               org/scalatest/freespec/FixtureAsyncFreeSpecLike
    #2 = Class              #1            // org/scalatest/freespec/FixtureAsyncFreeSpecLike
    #3 = Utf8               java/lang/Object
    #4 = Class              #3            // java/lang/Object
    #5 = Utf8               org/scalatest/FixtureAsyncTestSuite
    #6 = Class              #5            // org/scalatest/FixtureAsyncTestSuite
    #7 = Utf8               org/scalatest/FixtureAsyncTestRegistration
    #8 = Class              #7            // org/scalatest/FixtureAsyncTestRegistration
    #9 = Utf8               org/scalatest/Informing
   #10 = Class              #9            // org/scalatest/Informing
   #11 = Utf8               org/scalatest/Notifying
   #12 = Class              #11           // org/scalatest/Notifying
   #13 = Utf8               org/scalatest/Alerting
   #14 = Class              #13           // org/scalatest/Alerting
   #15 = Utf8               org/scalatest/Documenting
   #16 = Class              #15           // org/scalatest/Documenting
   #17 = Utf8               FixtureAsyncFreeSpecLike.scala
   #18 = Utf8               Lorg/scalatest/Finders;
   #19 = Utf8               value
   #20 = Utf8               org.scalatest.finders.FreeSpecFinder
   #21 = Utf8               Lscala/reflect/ScalaSignature;
   #22 = Utf8               bytes
   #23 = Utf8               \u0006\u0005\r\u0015aaB\u00181!\u0003\r\ta\u000e\u0005\u0006#\u0002!\tA\u0015\u0005\b-\u0002\u0011\r\u0011\"\u0004X\u0011\u0015\t\u0007\u0001\"\u0005c\u0011\u00151\u0007\u0001\"\u0005h\u0011\u0015Y\u0007\u0001\"\u0005m\u0011\u0015\u0001\b\u0001\"\u0005r\u0011\u0015)\b\u0001\"\u0004w\u0011\u001d\t\t\u0006\u0001C\u0003\u0003\'Bq!!\u0019\u0001\t\u001b\t\u0019\u0007C\u0004\u0002p\u0001!)!!\u001d\t\u000f\u0005}\u0004\u0001\"\u0003\u0002\u0002\"9\u00111\u0015\u0001\u0005\n\u0005\u0015\u0006bBA]\u0001\u0011%\u00111\u0018\u0005\b\u0003\u000f\u0004A\u0011BAe\r\u0019\t)\u000e\u0001\u0006\u0002X\"Q\u0011QQ\b\u0003\u0002\u0003\u0006I!a\u000b\t\u0015\u0005ewB!A!\u0002\u0013\tI\t\u0003\u0006\u0002\u0016=\u0011\t\u0011)A\u0005\u0003/Aq!a7\u0010\t\u0003\ti\u000eC\u0004\u0002h>!\t!!;\t\u000f\u0005\u001dx\u0002\"\u0001\u0002n\"9\u0011q_\b\u0005\u0002\u0005e\bb\u0002B\u0002\u001f\u0011\u0005!Q\u0001\u0005\b\u0005\u0007yA\u0011\u0001B\u0005\r\u0019\u0011i\u0001\u0001\u0006\u0003\u0010!Q!\u0011C\r\u0003\u0002\u0003\u0006I!a\u000b\t\u0015\u0005U\u0011D!A!\u0002\u0013\t9\u0002C\u0004\u0002\\f!\tAa\u0005\t\u000f\tm\u0011\u0004\"\u0001\u0003\u001e!9\u0011q]\r\u0005\u0002\t\u0015\u0002bBAt3\u0011\u0005!\u0011\u0006\u0005\b\u0003oLB\u0011\u0001B\u0017\u0011\u001d\u0011\u0019!\u0007C\u0001\u0005cAqAa\u0001\u001a\t\u0003\u0011)\u0004C\u0004\u0003:e!\tAa\u000f\t\u000f\t\u0015\u0003\u0001b\u0005\u0003H!9\u0011\u0011\u001c\u0001\u0005B\tE\u0003b\u0002B0\u0001\u0011E#\u0011\r\u0005\b\u0005o\u0002A\u0011\u000bB=\u0011\u001d\u0011)\t\u0001C!\u0005\u000fCqA!#\u0001\t\u0003\u0012Y\tC\u0005\u0003\u0012\u0002\u0011\r\u0011\"\u0005\u0003\u0014\"I!\u0011\u0015\u0001C\u0002\u0013\u0015#1\u0015\u0005\b\u0005s\u0003A\u0011\tB^\u0011%\u0011y\rAI\u0001\n\u0003\u0011\t\u000e\u0003\b\u0003h\u0002\u0001\n1!A\u0001\n\u0013\u0011IOa<\u00031\u0019K\u0007\u0010^;sK\u0006\u001b\u0018P\\2Ge\u0016,7\u000b]3d\u0019&\\WM\u0003\u00022e\u0005AaM]3fgB,7M\u0003\u00024i\u0005I1oY1mCR,7\u000f\u001e\u0006\u0002k\u0005\u0019qN]4\u0004\u0001MA\u0001\u0001\u000f C\u000b\"[e\n\u0005\u0002:y5\t!HC\u0001<\u0003\u0015\u00198-\u00197b\u0013\ti$H\u0001\u0004B]f\u0014VM\u001a\t\u0003\u007f\u0001k\u0011AM\u0005\u0003\u0003J\u0012QCR5yiV\u0014X-Q:z]\u000e$Vm\u001d;Tk&$X\r\u0005\u0002@\u0007&\u0011AI\r\u0002\u001d\r&DH/\u001e:f\u0003NLhn\u0019+fgR\u0014VmZ5tiJ\fG/[8o!\tyd)\u0003\u0002He\tI\u0011J\u001c4pe6Lgn\u001a\t\u0003\u007f%K!A\u0013\u001a\u0003\u00139{G/\u001b4zS:<\u0007CA M\u0013\ti%G\u0001\u0005BY\u0016\u0014H/\u001b8h!\tyt*\u0003\u0002Qe\tYAi\\2v[\u0016tG/\u001b8h\u0003\u0019!\u0013N\\5uIQ\t1\u000b\u0005\u0002:)&\u0011QK\u000f\u0002\u0005+:LG/\u0001\u0004f]\u001eLg.Z\u000b\u00021B\u0019q(W.\n\u0005i\u0013$AE!ts:\u001cg)\u001b=ukJ,WI\\4j]\u0016\u0004\"\u0001X/\u000e\u0003\u0001I!AX0\u0003\u0019\u0019K\u0007\u0010^;sKB\u000b\'/Y7\n\u0005\u0001\u0014$\u0001\u0004$jqR,(/Z*vSR,\u0017\u0001B5oM>,\u0012a\u0019\t\u0003\u007f\u0011L!!\u001a\u001a\u0003\u0011%sgm\u001c:nKJ\fAA\\8uKV\t\u0001\u000e\u0005\u0002@S&\u0011!N\r\u0002\t\u001d>$\u0018NZ5fe\u0006)\u0011\r\\3siV\tQ\u000e\u0005\u0002@]&\u0011qN\r\u0002\b\u00032,\'\u000f^3s\u0003\u0019i\u0017M]6vaV\t!\u000f\u0005\u0002@g&\u0011AO\r\u0002\u000b\t>\u001cW/\\3oi\u0016\u0014\u0018!\u0006:fO&\u001cH/\u001a:Bgft7\rV3ti&k\u0007\u000f\u001c\u000b\u0006o\u0006\u001d\u0012\u0011\t\u000b\u0005\'b\f\u0019\u0002C\u0003z\u000f\u0001\u0007!0A\u0004uKN$h)\u001e8\u0011\teZ8,`\u0005\u0003yj\u0012\u0011BR;oGRLwN\\\u0019\u0011\u000by\f\u0019!a\u0002\u000e\u0003}T1!!\u0001;\u0003)\u0019wN\\2veJ,g\u000e^\u0005\u0004\u0003\u000by(A\u0002$viV\u0014X\r\u0005\u0003\u0002\n\u0005=QBAA\u0006\u0015\r\tiAM\u0001\u000bG>l\u0007/\u0019;jE2,\u0017\u0002BA\t\u0003\u0017\u0011\u0011\"Q:tKJ$\u0018n\u001c8\t\u000f\u0005Uq\u00011\u0001\u0002\u0018\u0005\u0019\u0001o\\:\u0011\t\u0005e\u00111E\u0007\u0003\u00037QA!!\b\u0002 \u000511o\\;sG\u0016T1!!\t5\u0003%\u00198-\u00197bGRL7-\u0003\u0003\u0002&\u0005m!\u0001\u0003)pg&$\u0018n\u001c8\t\u000f\u0005%r\u00011\u0001\u0002,\u0005AA/Z:u)\u0016DH\u000f\u0005\u0003\u0002.\u0005mb\u0002BA\u0018\u0003o\u00012!!\r;\u001b\t\t\u0019DC\u0002\u00026Y\na\u0001\u0010:p_Rt\u0014bAA\u001du\u00051\u0001K]3eK\u001aLA!!\u0010\u0002@\t11\u000b\u001e:j]\u001eT1!!\u000f;\u0011\u001d\t\u0019e\u0002a\u0001\u0003\u000b\n\u0001\u0002^3tiR\u000bwm\u001d\t\u0006s\u0005\u001d\u00131J\u0005\u0004\u0003\u0013R$A\u0003\u001fsKB,\u0017\r^3e}A\u0019q(!\u0014\n\u0007\u0005=#GA\u0002UC\u001e\f\u0011C]3hSN$XM]!ts:\u001cG+Z:u)\u0019\t)&!\u0018\u0002`Q!\u0011qKA.)\r\u0019\u0016\u0011\f\u0005\b\u0003+A\u00019AA\f\u0011\u0015I\b\u00021\u0001{\u0011\u001d\tI\u0003\u0003a\u0001\u0003WAq!a\u0011\t\u0001\u0004\t)%\u0001\u000fsK\u001eL7\u000f^3s\u0013\u001etwN]3e\u0003NLhn\u0019+fgRLU\u000e\u001d7\u0015\r\u0005\u0015\u00141NA7)\u0015\u0019\u0016qMA5\u0011\u0015I\u0018\u00021\u0001{\u0011\u001d\t)\"\u0003a\u0001\u0003/Aq!!\u000b\n\u0001\u0004\tY\u0003C\u0004\u0002D%\u0001\r!!\u0012\u00021I,w-[:uKJLuM\\8sK\u0012\f5/\u001f8d)\u0016\u001cH\u000f\u0006\u0004\u0002t\u0005m\u0014Q\u0010\u000b\u0005\u0003k\nI\bF\u0002T\u0003oBq!!\u0006\u000b\u0001\b\t9\u0002C\u0003z\u0015\u0001\u0007!\u0010C\u0004\u0002*)\u0001\r!a\u000b\t\u000f\u0005\r#\u00021\u0001\u0002F\u00051\"/Z4jgR,\'/Q:z]\u000e$Vm\u001d;U_J+h\u000eF\u0006T\u0003\u0007\u000b9)a\'\u0002 \u0006\u0005\u0006bBAC\u0017\u0001\u0007\u00111F\u0001\tgB,7\rV3yi\"9\u00111I\u0006A\u0002\u0005%\u0005CBAF\u0003+\u000bYE\u0004\u0003\u0002\u000e\u0006Ee\u0002BA\u0019\u0003\u001fK\u0011aO\u0005\u0004\u0003\'S\u0014a\u00029bG.\fw-Z\u0005\u0005\u0003/\u000bIJ\u0001\u0003MSN$(bAAJu!9\u0011QT\u0006A\u0002\u0005-\u0012AC7fi\"|GMT1nK\")\u0011p\u0003a\u0001u\"9\u0011QC\u0006A\u0002\u0005]\u0011\u0001\u0007:fO&\u001cH/\u001a:QK:$\u0017N\\4UKN$Hk\u001c*v]RY1+a*\u0002*\u0006-\u0016QVA\\\u0011\u001d\t)\t\u0004a\u0001\u0003WAq!a\u0011\r\u0001\u0004\tI\tC\u0004\u0002\u001e2\u0001\r!a\u000b\t\red\u0001\u0019AAX!\u0015I4pWAY!\ry\u00141W\u0005\u0004\u0003k\u0013$\u0001\u0005)f]\u0012LgnZ*uCR,W.\u001a8u\u0011\u001d\t)\u0002\u0004a\u0001\u0003/\t\u0011D]3hSN$XM]!ts:\u001cG+Z:u)>LuM\\8sKRY1+!0\u0002@\u0006\u0005\u00171YAc\u0011\u001d\t))\u0004a\u0001\u0003WAq!a\u0011\u000e\u0001\u0004\tI\tC\u0004\u0002\u001e6\u0001\r!a\u000b\t\u000bel\u0001\u0019\u0001>\t\u000f\u0005UQ\u00021\u0001\u0002\u0018\u0005Y\"/Z4jgR,\'\u000fU3oI&tw\rV3tiR{\u0017j\u001a8pe\u0016$2bUAf\u0003\u001b\fy-!5\u0002T\"9\u0011Q\u0011\bA\u0002\u0005-\u0002bBA\"\u001d\u0001\u0007\u0011\u0011\u0012\u0005\b\u0003;s\u0001\u0019AA\u0016\u0011\u0019Ih\u00021\u0001\u00020\"9\u0011Q\u0003\bA\u0002\u0005]!A\t*fgVdGo\u00144UC\u001e<W\rZ!t\u0013:4xnY1uS>twJ\\*ue&twm\u0005\u0002\u0010q\u0005!A/Y4t\u0003\u0019a\u0014N\\5u}QA\u0011q\\Aq\u0003G\f)\u000f\u0005\u0002]\u001f!9\u0011QQ\nA\u0002\u0005-\u0002bBAm\'\u0001\u0007\u0011\u0011\u0012\u0005\b\u0003+\u0019\u0002\u0019AA\f\u0003\tIg\u000eF\u0002T\u0003WDQ!\u001f\u000bA\u0002i$2aUAx\u0011\u0019IX\u00031\u0001\u0002rB!\u0011(a=~\u0013\r\t)P\u000f\u0002\n\rVt7\r^5p]B\n!![:\u0015\u0007M\u000bY\u0010C\u0004z-\u0011\u0005\r!!@\u0011\u000be\ny0!-\n\u0007\t\u0005!H\u0001\u0005=Eft\u0017-\\3?\u0003\u0019IwM\\8sKR\u00191Ka\u0002\t\u000be<\u0002\u0019\u0001>\u0015\u0007M\u0013Y\u0001\u0003\u0004z1\u0001\u0007\u0011\u0011\u001f\u0002\u0016\rJ,Wm\u00159fGN#(/\u001b8h/J\f\u0007\u000f]3s\'\tI\u0002(\u0001\u0004tiJLgn\u001a\u000b\u0007\u0005+\u00119B!\u0007\u0011\u0005qK\u0002b\u0002B\t9\u0001\u0007\u00111\u0006\u0005\b\u0003+a\u0002\u0019AA\f\u0003\u0019!S.\u001b8vgR\u00191Ka\b\t\u0011\t\u0005R\u0004\"a\u0001\u0005G\t1AZ;o!\u0011I\u0014q`*\u0015\u0007M\u00139\u0003C\u0003z=\u0001\u0007!\u0010F\u0002T\u0005WAa!_\u0010A\u0002\u0005EHcA*\u00030!9\u0011\u0010\tCA\u0002\u0005uHcA*\u00034!)\u00110\ta\u0001uR\u00191Ka\u000e\t\re\u0014\u0003\u0019AAy\u0003!!\u0018mZ4fI\u0006\u001bHCBAp\u0005{\u0011\t\u0005C\u0004\u0003@\r\u0002\r!a\u0013\u0002\u0019\u0019L\'o\u001d;UKN$H+Y4\t\u000f\t\r3\u00051\u0001\u0002F\u0005iq\u000e\u001e5feR+7\u000f\u001e+bON\fadY8om\u0016\u0014H\u000fV8Ge\u0016,7\u000b]3d\'R\u0014\u0018N\\4Xe\u0006\u0004\b/\u001a:\u0015\t\t%#Q\n\u000b\u0005\u0005+\u0011Y\u0005C\u0004\u0002\u0016\u0011\u0002\u001d!a\u0006\t\u000f\t=C\u00051\u0001\u0002,\u0005\t1/\u0006\u0002\u0003TAA\u0011Q\u0006B+\u0003W\u0011I&\u0003\u0003\u0003X\u0005}\"aA\'baB1\u0011Q\u0006B.\u0003WIAA!\u0018\u0002@\t\u00191+\u001a;\u0002\u000fI,h\u000eV3tiR1!1\rB5\u0005[\u00022a\u0010B3\u0013\r\u00119G\r\u0002\u0007\'R\fG/^:\t\u000f\t-d\u00051\u0001\u0002,\u0005AA/Z:u\u001d\u0006lW\rC\u0004\u0003p\u0019\u0002\rA!\u001d\u0002\t\u0005\u0014xm\u001d\t\u0004\u007f\tM\u0014b\u0001B;e\t!\u0011I]4t\u0003!\u0011XO\u001c+fgR\u001cHC\u0002B2\u0005w\u0012\u0019\tC\u0004\u0003l\u001d\u0002\rA! \u0011\u000be\u0012y(a\u000b\n\u0007\t\u0005%H\u0001\u0004PaRLwN\u001c\u0005\b\u0005_:\u0003\u0019\u0001B9\u0003%!Xm\u001d;OC6,7/\u0006\u0002\u0003Z\u0005\u0019!/\u001e8\u0015\r\t\r$Q\u0012BH\u0011\u001d\u0011Y\'\u000ba\u0001\u0005{BqAa\u001c*\u0001\u0004\u0011\t(\u0001\u0004cK\"\fg/Z\u000b\u0003\u0005+\u0003BAa&\u0003\u001e6\u0011!\u0011\u0014\u0006\u0004\u00057\u0013\u0014!\u0002<fe\n\u001c\u0018\u0002\u0002BP\u00053\u0013!BQ3iCZ,wk\u001c:e\u0003%\u0019H/\u001f7f\u001d\u0006lW-\u0006\u0002\u0002,!Z1Fa*\u0003.\n=&1\u0017B[!\rI$\u0011V\u0005\u0004\u0005WS$A\u00033faJ,7-\u0019;fI\u00069Q.Z:tC\u001e,\u0017E\u0001BY\u0003q$\u0006.\u001a\u0011tifdWMT1nK\u0002b\u0017NZ3ds\u000edW\rI7fi\"|G\r\t5bg\u0002\u0012W-\u001a8!I\u0016\u0004(/Z2bi\u0016$\u0007%\u00198eA]LG\u000e\u001c\u0011cK\u0002\u0012X-\\8wK\u0012\u0004\u0013N\u001c\u0011bA\u0019,H/\u001e:fAY,\'o]5p]\u0002zg\rI*dC2\fG+Z:uA]LG\u000f\u001b\u0011o_\u0002\u0012X\r\u001d7bG\u0016lWM\u001c;/\u0003\u0015\u0019\u0018N\\2fC\t\u00119,A\u00034]Er\u0003\'A\u0006uKN$H)\u0019;b\r>\u0014HC\u0002B_\u0005\u0007\u0014)\rE\u0002@\u0005\u007fK1A!13\u0005!!Vm\u001d;ECR\f\u0007b\u0002B6Y\u0001\u0007\u00111\u0006\u0005\n\u0005\u000fd\u0003\u0013!a\u0001\u0005\u0013\fA\u0002\u001e5f\u0007>tg-[4NCB\u00042a\u0010Bf\u0013\r\u0011iM\r\u0002\n\u0007>tg-[4NCB\fQ\u0003^3ti\u0012\u000bG/\u0019$pe\u0012\"WMZ1vYR$#\'\u0006\u0002\u0003T*\"!\u0011\u001aBkW\t\u00119\u000e\u0005\u0003\u0003Z\n\rXB\u0001Bn\u0015\u0011\u0011iNa8\u0002\u0013Ut7\r[3dW\u0016$\'b\u0001Bqu\u0005Q\u0011M\u001c8pi\u0006$\u0018n\u001c8\n\t\t\u0015(1\u001c\u0002\u0012k:\u001c\u0007.Z2lK\u00124\u0016M]5b]\u000e,\u0017!C:va\u0016\u0014HE];o)\u0019\u0011\u0019Ga;\u0003n\"9!1\u000e\u0018A\u0002\tu\u0004b\u0002B8]\u0001\u0007!\u0011O\u0005\u0005\u0005\u0013\u0013\t0C\u0002\u0003tJ\u0012QaU;ji\u0016Ds\u0001\u0001B|\u0005{\u0014y\u0010E\u0002@\u0005sL1Aa?3\u0005\u001d1\u0015N\u001c3feN\fQA^1mk\u0016d#a!\u0001\"\u0005\r\r\u0011\u0001J8sO:\u001a8-\u00197bi\u0016\u001cHO\f4j]\u0012,\'o\u001d\u0018Ge\u0016,7\u000b]3d\r&tG-\u001a:
   #24 = Utf8               java/lang/invoke/MethodHandles$Lookup
   #25 = Class              #24           // java/lang/invoke/MethodHandles$Lookup
   #26 = Utf8               java/lang/invoke/MethodHandles
   #27 = Class              #26           // java/lang/invoke/MethodHandles
   #28 = Utf8               Lookup
   #29 = Utf8               org/scalatest/AsyncSuperEngine$Bundle
   #30 = Class              #29           // org/scalatest/AsyncSuperEngine$Bundle
   #31 = Utf8               org/scalatest/AsyncSuperEngine
   #32 = Class              #31           // org/scalatest/AsyncSuperEngine
   #33 = Utf8               Bundle
   #34 = Utf8               org/scalatest/AsyncSuperEngine$TestLeaf
   #35 = Class              #34           // org/scalatest/AsyncSuperEngine$TestLeaf
   #36 = Utf8               TestLeaf
   #37 = Utf8               org/scalatest/FixtureAsyncTestSuite$OneArgAsyncTest
   #38 = Class              #37           // org/scalatest/FixtureAsyncTestSuite$OneArgAsyncTest
   #39 = Utf8               OneArgAsyncTest
   #40 = Utf8               org/scalatest/freespec/FixtureAsyncFreeSpecLike$$anon$1
   #41 = Class              #40           // org/scalatest/freespec/FixtureAsyncFreeSpecLike$$anon$1
   #42 = Utf8               org/scalatest/freespec/FixtureAsyncFreeSpecLike$FreeSpecStringWrapper
   #43 = Class              #42           // org/scalatest/freespec/FixtureAsyncFreeSpecLike$FreeSpecStringWrapper
   #44 = Utf8               FreeSpecStringWrapper
   #45 = Utf8               org/scalatest/freespec/FixtureAsyncFreeSpecLike$ResultOfTaggedAsInvocationOnString
   #46 = Class              #45           // org/scalatest/freespec/FixtureAsyncFreeSpecLike$ResultOfTaggedAsInvocationOnString
   #47 = Utf8               ResultOfTaggedAsInvocationOnString
   #48 = Utf8               org$scalatest$freespec$FixtureAsyncFreeSpecLike$_setter_$org$scalatest$freespec$FixtureAsyncFreeSpecLike$$engine_$eq
   #49 = Utf8               (Lorg/scalatest/AsyncFixtureEngine;)V
   #50 = Utf8               (Lorg/scalatest/AsyncFixtureEngine<Ljava/lang/Object;>;)V
   #51 = Utf8               x$1
   #52 = Utf8               org$scalatest$freespec$FixtureAsyncFreeSpecLike$_setter_$behave_$eq
   #53 = Utf8               (Lorg/scalatest/verbs/BehaveWord;)V
   #54 = Utf8               org$scalatest$freespec$FixtureAsyncFreeSpecLike$_setter_$styleName_$eq
   #55 = Utf8               (Ljava/lang/String;)V
   #56 = Utf8               org$scalatest$freespec$FixtureAsyncFreeSpecLike$$super$run
   #57 = Utf8               (Lscala/Option;Lorg/scalatest/Args;)Lorg/scalatest/Status;
   #58 = Utf8               testName
   #59 = Utf8               args
   #60 = Utf8               org$scalatest$freespec$FixtureAsyncFreeSpecLike$$engine
   #61 = Utf8               ()Lorg/scalatest/AsyncFixtureEngine;
   #62 = Utf8               ()Lorg/scalatest/AsyncFixtureEngine<Ljava/lang/Object;>;
   #63 = Utf8               info$
   #64 = Utf8               (Lorg/scalatest/freespec/FixtureAsyncFreeSpecLike;)Lorg/scalatest/Informer;
   #65 = Utf8               $this
   #66 = Utf8               info
   #67 = Utf8               ()Lorg/scalatest/Informer;
   #68 = NameAndType        #66:#67       // info:()Lorg/scalatest/Informer;
   #69 = InterfaceMethodref #2.#68        // org/scalatest/freespec/FixtureAsyncFreeSpecLike.info:()Lorg/scalatest/Informer;
   #70 = Utf8               Lorg/scalatest/freespec/FixtureAsyncFreeSpecLike;
   #71 = NameAndType        #60:#61       // org$scalatest$freespec$FixtureAsyncFreeSpecLike$$engine:()Lorg/scalatest/AsyncFixtureEngine;
   #72 = InterfaceMethodref #2.#71        // org/scalatest/freespec/FixtureAsyncFreeSpecLike.org$scalatest$freespec$FixtureAsyncFreeSpecLike$$engine:()Lorg/scalatest/AsyncFixtureEngine;
   #73 = Utf8               org/scalatest/AsyncFixtureEngine
   #74 = Class              #73           // org/scalatest/AsyncFixtureEngine
   #75 = Utf8               atomicInformer
   #76 = Utf8               ()Ljava/util/concurrent/atomic/AtomicReference;
   #77 = NameAndType        #75:#76       // atomicInformer:()Ljava/util/concurrent/atomic/AtomicReference;
   #78 = Methodref          #74.#77       // org/scalatest/AsyncFixtureEngine.atomicInformer:()Ljava/util/concurrent/atomic/AtomicReference;
   #79 = Utf8               java/util/concurrent/atomic/AtomicReference
   #80 = Class              #79           // java/util/concurrent/atomic/AtomicReference
   #81 = Utf8               get
   #82 = Utf8               ()Ljava/lang/Object;
   #83 = NameAndType        #81:#82       // get:()Ljava/lang/Object;
   #84 = Methodref          #80.#83       // java/util/concurrent/atomic/AtomicReference.get:()Ljava/lang/Object;
   #85 = Utf8               org/scalatest/Informer
   #86 = Class              #85           // org/scalatest/Informer
   #87 = Utf8               this
   #88 = Utf8               note$
   #89 = Utf8               (Lorg/scalatest/freespec/FixtureAsyncFreeSpecLike;)Lorg/scalatest/Notifier;
   #90 = Utf8               note
   #91 = Utf8               ()Lorg/scalatest/Notifier;
   #92 = NameAndType        #90:#91       // note:()Lorg/scalatest/Notifier;
   #93 = InterfaceMethodref #2.#92        // org/scalatest/freespec/FixtureAsyncFreeSpecLike.note:()Lorg/scalatest/Notifier;
   #94 = Utf8               atomicNotifier
   #95 = NameAndType        #94:#76       // atomicNotifier:()Ljava/util/concurrent/atomic/AtomicReference;
   #96 = Methodref          #74.#95       // org/scalatest/AsyncFixtureEngine.atomicNotifier:()Ljava/util/concurrent/atomic/AtomicReference;
   #97 = Utf8               org/scalatest/Notifier
   #98 = Class              #97           // org/scalatest/Notifier
   #99 = Utf8               alert$
  #100 = Utf8               (Lorg/scalatest/freespec/FixtureAsyncFreeSpecLike;)Lorg/scalatest/Alerter;
  #101 = Utf8               alert
  #102 = Utf8               ()Lorg/scalatest/Alerter;
  #103 = NameAndType        #101:#102     // alert:()Lorg/scalatest/Alerter;
  #104 = InterfaceMethodref #2.#103       // org/scalatest/freespec/FixtureAsyncFreeSpecLike.alert:()Lorg/scalatest/Alerter;
  #105 = Utf8               atomicAlerter
  #106 = NameAndType        #105:#76      // atomicAlerter:()Ljava/util/concurrent/atomic/AtomicReference;
  #107 = Methodref          #74.#106      // org/scalatest/AsyncFixtureEngine.atomicAlerter:()Ljava/util/concurrent/atomic/AtomicReference;
  #108 = Utf8               org/scalatest/Alerter
  #109 = Class              #108          // org/scalatest/Alerter
  #110 = Utf8               markup$
  #111 = Utf8               (Lorg/scalatest/freespec/FixtureAsyncFreeSpecLike;)Lorg/scalatest/Documenter;
  #112 = Utf8               markup
  #113 = Utf8               ()Lorg/scalatest/Documenter;
  #114 = NameAndType        #112:#113     // markup:()Lorg/scalatest/Documenter;
  #115 = InterfaceMethodref #2.#114       // org/scalatest/freespec/FixtureAsyncFreeSpecLike.markup:()Lorg/scalatest/Documenter;
  #116 = Utf8               atomicDocumenter
  #117 = NameAndType        #116:#76      // atomicDocumenter:()Ljava/util/concurrent/atomic/AtomicReference;
  #118 = Methodref          #74.#117      // org/scalatest/AsyncFixtureEngine.atomicDocumenter:()Ljava/util/concurrent/atomic/AtomicReference;
  #119 = Utf8               org/scalatest/Documenter
  #120 = Class              #119          // org/scalatest/Documenter
  #121 = Utf8               registerAsyncTestImpl
  #122 = Utf8               (Ljava/lang/String;Lscala/collection/immutable/Seq;Lscala/Function1;Lorg/scalactic/source/Position;)V
  #123 = Utf8               (Ljava/lang/String;Lscala/collection/immutable/Seq<Lorg/scalatest/Tag;>;Lscala/Function1<Ljava/lang/Object;Lscala/concurrent/Future<Lorg/scalatest/compatible/Assertion;>;>;Lorg/scalactic/source/Position;)V
  #124 = Utf8               testText
  #125 = Utf8               testTags
  #126 = Utf8               testFun
  #127 = Utf8               pos
  #128 = Utf8               transformToOutcome
  #129 = Utf8               (Lscala/Function1;)Lscala/Function1;
  #130 = NameAndType        #128:#129     // transformToOutcome:(Lscala/Function1;)Lscala/Function1;
  #131 = InterfaceMethodref #2.#130       // org/scalatest/freespec/FixtureAsyncFreeSpecLike.transformToOutcome:(Lscala/Function1;)Lscala/Function1;
  #132 = MethodType         #82           //  ()Ljava/lang/Object;
  #133 = Utf8               $anonfun$registerAsyncTestImpl$1
  #134 = Utf8               ()Ljava/lang/String;
  #135 = NameAndType        #133:#134     // $anonfun$registerAsyncTestImpl$1:()Ljava/lang/String;
  #136 = InterfaceMethodref #2.#135       // org/scalatest/freespec/FixtureAsyncFreeSpecLike.$anonfun$registerAsyncTestImpl$1:()Ljava/lang/String;
  #137 = MethodHandle       6:#136        // REF_invokeStatic org/scalatest/freespec/FixtureAsyncFreeSpecLike.$anonfun$registerAsyncTestImpl$1:()Ljava/lang/String;
  #138 = MethodType         #134          //  ()Ljava/lang/String;
  #139 = Integer            5
  #140 = Integer            1
  #141 = Utf8               java/lang/invoke/LambdaMetafactory
  #142 = Class              #141          // java/lang/invoke/LambdaMetafactory
  #143 = Utf8               altMetafactory
  #144 = Utf8               (Ljava/lang/invoke/MethodHandles$Lookup;Ljava/lang/String;Ljava/lang/invoke/MethodType;[Ljava/lang/Object;)Ljava/lang/invoke/CallSite;
  #145 = NameAndType        #143:#144     // altMetafactory:(Ljava/lang/invoke/MethodHandles$Lookup;Ljava/lang/String;Ljava/lang/invoke/MethodType;[Ljava/lang/Object;)Ljava/lang/invoke/CallSite;
  #146 = Methodref          #142.#145     // java/lang/invoke/LambdaMetafactory.altMetafactory:(Ljava/lang/invoke/MethodHandles$Lookup;Ljava/lang/String;Ljava/lang/invoke/MethodType;[Ljava/lang/Object;)Ljava/lang/invoke/CallSite;
  #147 = MethodHandle       6:#146        // REF_invokeStatic java/lang/invoke/LambdaMetafactory.altMetafactory:(Ljava/lang/invoke/MethodHandles$Lookup;Ljava/lang/String;Ljava/lang/invoke/MethodType;[Ljava/lang/Object;)Ljava/lang/invoke/CallSite;
  #148 = Utf8               apply
  #149 = Utf8               ()Lscala/Function0;
  #150 = NameAndType        #148:#149     // apply:()Lscala/Function0;
  #151 = InvokeDynamic      #0:#150       // #0:apply:()Lscala/Function0;
  #152 = Utf8               scala/None$
  #153 = Class              #152          // scala/None$
  #154 = Utf8               MODULE$
  #155 = Utf8               Lscala/None$;
  #156 = NameAndType        #154:#155     // MODULE$:Lscala/None$;
  #157 = Fieldref           #153.#156     // scala/None$.MODULE$:Lscala/None$;
  #158 = Utf8               registerAsyncTest
  #159 = Utf8               (Ljava/lang/String;Ljava/lang/Object;Lscala/Function0;Lscala/Option;Lscala/Option;Lorg/scalactic/source/Position;Lscala/collection/immutable/Seq;)Ljava/lang/String;
  #160 = NameAndType        #158:#159     // registerAsyncTest:(Ljava/lang/String;Ljava/lang/Object;Lscala/Function0;Lscala/Option;Lscala/Option;Lorg/scalactic/source/Position;Lscala/collection/immutable/Seq;)Ljava/lang/String;
  #161 = Methodref          #74.#160      // org/scalatest/AsyncFixtureEngine.registerAsyncTest:(Ljava/lang/String;Ljava/lang/Object;Lscala/Function0;Lscala/Option;Lscala/Option;Lorg/scalactic/source/Position;Lscala/collection/immutable/Seq;)Ljava/lang/String;
  #162 = Utf8               Ljava/lang/String;
  #163 = Utf8               Lscala/collection/immutable/Seq;
  #164 = Utf8               Lscala/Function1;
  #165 = Utf8               Lorg/scalactic/source/Position;
  #166 = Utf8               registerAsyncTest$
  #167 = Utf8               (Lorg/scalatest/freespec/FixtureAsyncFreeSpecLike;Ljava/lang/String;Lscala/collection/immutable/Seq;Lscala/Function1;Lorg/scalactic/source/Position;)V
  #168 = NameAndType        #158:#122     // registerAsyncTest:(Ljava/lang/String;Lscala/collection/immutable/Seq;Lscala/Function1;Lorg/scalactic/source/Position;)V
  #169 = InterfaceMethodref #2.#168       // org/scalatest/freespec/FixtureAsyncFreeSpecLike.registerAsyncTest:(Ljava/lang/String;Lscala/collection/immutable/Seq;Lscala/Function1;Lorg/scalactic/source/Position;)V
  #170 = NameAndType        #121:#122     // registerAsyncTestImpl:(Ljava/lang/String;Lscala/collection/immutable/Seq;Lscala/Function1;Lorg/scalactic/source/Position;)V
  #171 = InterfaceMethodref #2.#170       // org/scalatest/freespec/FixtureAsyncFreeSpecLike.registerAsyncTestImpl:(Ljava/lang/String;Lscala/collection/immutable/Seq;Lscala/Function1;Lorg/scalactic/source/Position;)V
  #172 = Utf8               registerIgnoredAsyncTestImpl
  #173 = Utf8               $anonfun$registerIgnoredAsyncTestImpl$1
  #174 = NameAndType        #173:#134     // $anonfun$registerIgnoredAsyncTestImpl$1:()Ljava/lang/String;
  #175 = InterfaceMethodref #2.#174       // org/scalatest/freespec/FixtureAsyncFreeSpecLike.$anonfun$registerIgnoredAsyncTestImpl$1:()Ljava/lang/String;
  #176 = MethodHandle       6:#175        // REF_invokeStatic org/scalatest/freespec/FixtureAsyncFreeSpecLike.$anonfun$registerIgnoredAsyncTestImpl$1:()Ljava/lang/String;
  #177 = InvokeDynamic      #1:#150       // #1:apply:()Lscala/Function0;
  #178 = Utf8               registerIgnoredAsyncTest
  #179 = Utf8               (Ljava/lang/String;Ljava/lang/Object;Lscala/Function0;Lscala/Option;Lorg/scalactic/source/Position;Lscala/collection/immutable/Seq;)V
  #180 = NameAndType        #178:#179     // registerIgnoredAsyncTest:(Ljava/lang/String;Ljava/lang/Object;Lscala/Function0;Lscala/Option;Lorg/scalactic/source/Position;Lscala/collection/immutable/Seq;)V
  #181 = Methodref          #74.#180      // org/scalatest/AsyncFixtureEngine.registerIgnoredAsyncTest:(Ljava/lang/String;Ljava/lang/Object;Lscala/Function0;Lscala/Option;Lorg/scalactic/source/Position;Lscala/collection/immutable/Seq;)V
  #182 = Utf8               registerIgnoredAsyncTest$
  #183 = NameAndType        #178:#122     // registerIgnoredAsyncTest:(Ljava/lang/String;Lscala/collection/immutable/Seq;Lscala/Function1;Lorg/scalactic/source/Position;)V
  #184 = InterfaceMethodref #2.#183       // org/scalatest/freespec/FixtureAsyncFreeSpecLike.registerIgnoredAsyncTest:(Ljava/lang/String;Lscala/collection/immutable/Seq;Lscala/Function1;Lorg/scalactic/source/Position;)V
  #185 = NameAndType        #172:#122     // registerIgnoredAsyncTestImpl:(Ljava/lang/String;Lscala/collection/immutable/Seq;Lscala/Function1;Lorg/scalactic/source/Position;)V
  #186 = InterfaceMethodref #2.#185       // org/scalatest/freespec/FixtureAsyncFreeSpecLike.registerIgnoredAsyncTestImpl:(Ljava/lang/String;Lscala/collection/immutable/Seq;Lscala/Function1;Lorg/scalactic/source/Position;)V
  #187 = Utf8               org$scalatest$freespec$FixtureAsyncFreeSpecLike$$registerAsyncTestToRun$
  #188 = Utf8               (Lorg/scalatest/freespec/FixtureAsyncFreeSpecLike;Ljava/lang/String;Lscala/collection/immutable/List;Ljava/lang/String;Lscala/Function1;Lorg/scalactic/source/Position;)V
  #189 = Utf8               specText
  #190 = Utf8               methodName
  #191 = Utf8               org$scalatest$freespec$FixtureAsyncFreeSpecLike$$registerAsyncTestToRun
  #192 = Utf8               (Ljava/lang/String;Lscala/collection/immutable/List;Ljava/lang/String;Lscala/Function1;Lorg/scalactic/source/Position;)V
  #193 = NameAndType        #191:#192     // org$scalatest$freespec$FixtureAsyncFreeSpecLike$$registerAsyncTestToRun:(Ljava/lang/String;Lscala/collection/immutable/List;Ljava/lang/String;Lscala/Function1;Lorg/scalactic/source/Position;)V
  #194 = InterfaceMethodref #2.#193       // org/scalatest/freespec/FixtureAsyncFreeSpecLike.org$scalatest$freespec$FixtureAsyncFreeSpecLike$$registerAsyncTestToRun:(Ljava/lang/String;Lscala/collection/immutable/List;Ljava/lang/String;Lscala/Function1;Lorg/scalactic/source/Position;)V
  #195 = Utf8               Lscala/collection/immutable/List;
  #196 = Utf8               (Ljava/lang/String;Lscala/collection/immutable/List<Lorg/scalatest/Tag;>;Ljava/lang/String;Lscala/Function1<Ljava/lang/Object;Lscala/concurrent/Future<Lorg/scalatest/compatible/Assertion;>;>;Lorg/scalactic/source/Position;)V
  #197 = Utf8               $anonfun$registerAsyncTestToRun$1
  #198 = NameAndType        #197:#134     // $anonfun$registerAsyncTestToRun$1:()Ljava/lang/String;
  #199 = InterfaceMethodref #2.#198       // org/scalatest/freespec/FixtureAsyncFreeSpecLike.$anonfun$registerAsyncTestToRun$1:()Ljava/lang/String;
  #200 = MethodHandle       6:#199        // REF_invokeStatic org/scalatest/freespec/FixtureAsyncFreeSpecLike.$anonfun$registerAsyncTestToRun$1:()Ljava/lang/String;
  #201 = InvokeDynamic      #2:#150       // #2:apply:()Lscala/Function0;
  #202 = Utf8               org$scalatest$freespec$FixtureAsyncFreeSpecLike$$registerPendingTestToRun$
  #203 = Utf8               org$scalatest$freespec$FixtureAsyncFreeSpecLike$$registerPendingTestToRun
  #204 = NameAndType        #203:#192     // org$scalatest$freespec$FixtureAsyncFreeSpecLike$$registerPendingTestToRun:(Ljava/lang/String;Lscala/collection/immutable/List;Ljava/lang/String;Lscala/Function1;Lorg/scalactic/source/Position;)V
  #205 = InterfaceMethodref #2.#204       // org/scalatest/freespec/FixtureAsyncFreeSpecLike.org$scalatest$freespec$FixtureAsyncFreeSpecLike$$registerPendingTestToRun:(Ljava/lang/String;Lscala/collection/immutable/List;Ljava/lang/String;Lscala/Function1;Lorg/scalactic/source/Position;)V
  #206 = Utf8               (Ljava/lang/String;Lscala/collection/immutable/List<Lorg/scalatest/Tag;>;Ljava/lang/String;Lscala/Function1<Ljava/lang/Object;Lorg/scalatest/PendingStatement;>;Lorg/scalactic/source/Position;)V
  #207 = Utf8               org/scalatest/fixture/AsyncPendingTransformer
  #208 = Class              #207          // org/scalatest/fixture/AsyncPendingTransformer
  #209 = Utf8               executionContext
  #210 = Utf8               ()Lscala/concurrent/ExecutionContext;
  #211 = NameAndType        #209:#210     // executionContext:()Lscala/concurrent/ExecutionContext;
  #212 = InterfaceMethodref #2.#211       // org/scalatest/freespec/FixtureAsyncFreeSpecLike.executionContext:()Lscala/concurrent/ExecutionContext;
  #213 = Utf8               <init>
  #214 = Utf8               (Lscala/Function1;Lscala/concurrent/ExecutionContext;)V
  #215 = NameAndType        #213:#214     // "<init>":(Lscala/Function1;Lscala/concurrent/ExecutionContext;)V
  #216 = Methodref          #208.#215     // org/scalatest/fixture/AsyncPendingTransformer."<init>":(Lscala/Function1;Lscala/concurrent/ExecutionContext;)V
  #217 = Utf8               $anonfun$registerPendingTestToRun$1
  #218 = NameAndType        #217:#134     // $anonfun$registerPendingTestToRun$1:()Ljava/lang/String;
  #219 = InterfaceMethodref #2.#218       // org/scalatest/freespec/FixtureAsyncFreeSpecLike.$anonfun$registerPendingTestToRun$1:()Ljava/lang/String;
  #220 = MethodHandle       6:#219        // REF_invokeStatic org/scalatest/freespec/FixtureAsyncFreeSpecLike.$anonfun$registerPendingTestToRun$1:()Ljava/lang/String;
  #221 = InvokeDynamic      #3:#150       // #3:apply:()Lscala/Function0;
  #222 = Utf8               org$scalatest$freespec$FixtureAsyncFreeSpecLike$$registerAsyncTestToIgnore$
  #223 = Utf8               org$scalatest$freespec$FixtureAsyncFreeSpecLike$$registerAsyncTestToIgnore
  #224 = NameAndType        #223:#192     // org$scalatest$freespec$FixtureAsyncFreeSpecLike$$registerAsyncTestToIgnore:(Ljava/lang/String;Lscala/collection/immutable/List;Ljava/lang/String;Lscala/Function1;Lorg/scalactic/source/Position;)V
  #225 = InterfaceMethodref #2.#224       // org/scalatest/freespec/FixtureAsyncFreeSpecLike.org$scalatest$freespec$FixtureAsyncFreeSpecLike$$registerAsyncTestToIgnore:(Ljava/lang/String;Lscala/collection/immutable/List;Ljava/lang/String;Lscala/Function1;Lorg/scalactic/source/Position;)V
  #226 = Utf8               $anonfun$registerAsyncTestToIgnore$1
  #227 = NameAndType        #226:#134     // $anonfun$registerAsyncTestToIgnore$1:()Ljava/lang/String;
  #228 = InterfaceMethodref #2.#227       // org/scalatest/freespec/FixtureAsyncFreeSpecLike.$anonfun$registerAsyncTestToIgnore$1:()Ljava/lang/String;
  #229 = MethodHandle       6:#228        // REF_invokeStatic org/scalatest/freespec/FixtureAsyncFreeSpecLike.$anonfun$registerAsyncTestToIgnore$1:()Ljava/lang/String;
  #230 = InvokeDynamic      #4:#150       // #4:apply:()Lscala/Function0;
  #231 = Utf8               registerPendingTestToIgnore
  #232 = Utf8               $anonfun$registerPendingTestToIgnore$1
  #233 = NameAndType        #232:#134     // $anonfun$registerPendingTestToIgnore$1:()Ljava/lang/String;
  #234 = InterfaceMethodref #2.#233       // org/scalatest/freespec/FixtureAsyncFreeSpecLike.$anonfun$registerPendingTestToIgnore$1:()Ljava/lang/String;
  #235 = MethodHandle       6:#234        // REF_invokeStatic org/scalatest/freespec/FixtureAsyncFreeSpecLike.$anonfun$registerPendingTestToIgnore$1:()Ljava/lang/String;
  #236 = InvokeDynamic      #5:#150       // #5:apply:()Lscala/Function0;
  #237 = Utf8               convertToFreeSpecStringWrapper$
  #238 = Utf8               (Lorg/scalatest/freespec/FixtureAsyncFreeSpecLike;Ljava/lang/String;Lorg/scalactic/source/Position;)Lorg/scalatest/freespec/FixtureAsyncFreeSpecLike$FreeSpecStringWrapper;
  #239 = Utf8               s
  #240 = Utf8               convertToFreeSpecStringWrapper
  #241 = Utf8               (Ljava/lang/String;Lorg/scalactic/source/Position;)Lorg/scalatest/freespec/FixtureAsyncFreeSpecLike$FreeSpecStringWrapper;
  #242 = NameAndType        #240:#241     // convertToFreeSpecStringWrapper:(Ljava/lang/String;Lorg/scalactic/source/Position;)Lorg/scalatest/freespec/FixtureAsyncFreeSpecLike$FreeSpecStringWrapper;
  #243 = InterfaceMethodref #2.#242       // org/scalatest/freespec/FixtureAsyncFreeSpecLike.convertToFreeSpecStringWrapper:(Ljava/lang/String;Lorg/scalactic/source/Position;)Lorg/scalatest/freespec/FixtureAsyncFreeSpecLike$FreeSpecStringWrapper;
  #244 = Utf8               (Lorg/scalatest/freespec/FixtureAsyncFreeSpecLike;Ljava/lang/String;Lorg/scalactic/source/Position;)V
  #245 = NameAndType        #213:#244     // "<init>":(Lorg/scalatest/freespec/FixtureAsyncFreeSpecLike;Ljava/lang/String;Lorg/scalactic/source/Position;)V
  #246 = Methodref          #43.#245      // org/scalatest/freespec/FixtureAsyncFreeSpecLike$FreeSpecStringWrapper."<init>":(Lorg/scalatest/freespec/FixtureAsyncFreeSpecLike;Ljava/lang/String;Lorg/scalactic/source/Position;)V
  #247 = Utf8               tags$
  #248 = Utf8               (Lorg/scalatest/freespec/FixtureAsyncFreeSpecLike;)Lscala/collection/immutable/Map;
  #249 = Utf8               tags
  #250 = Utf8               ()Lscala/collection/immutable/Map;
  #251 = NameAndType        #249:#250     // tags:()Lscala/collection/immutable/Map;
  #252 = InterfaceMethodref #2.#251       // org/scalatest/freespec/FixtureAsyncFreeSpecLike.tags:()Lscala/collection/immutable/Map;
  #253 = Utf8               ()Lscala/collection/immutable/Map<Ljava/lang/String;Lscala/collection/immutable/Set<Ljava/lang/String;>;>;
  #254 = Utf8               org/scalatest/Suite$
  #255 = Class              #254          // org/scalatest/Suite$
  #256 = Utf8               Lorg/scalatest/Suite$;
  #257 = NameAndType        #154:#256     // MODULE$:Lorg/scalatest/Suite$;
  #258 = Fieldref           #255.#257     // org/scalatest/Suite$.MODULE$:Lorg/scalatest/Suite$;
  #259 = Utf8               atomic
  #260 = NameAndType        #259:#76      // atomic:()Ljava/util/concurrent/atomic/AtomicReference;
  #261 = Methodref          #74.#260      // org/scalatest/AsyncFixtureEngine.atomic:()Ljava/util/concurrent/atomic/AtomicReference;
  #262 = Utf8               tagsMap
  #263 = NameAndType        #262:#250     // tagsMap:()Lscala/collection/immutable/Map;
  #264 = Methodref          #30.#263      // org/scalatest/AsyncSuperEngine$Bundle.tagsMap:()Lscala/collection/immutable/Map;
  #265 = Utf8               autoTagClassAnnotations
  #266 = Utf8               (Lscala/collection/immutable/Map;Lorg/scalatest/Suite;)Lscala/collection/immutable/Map;
  #267 = NameAndType        #265:#266     // autoTagClassAnnotations:(Lscala/collection/immutable/Map;Lorg/scalatest/Suite;)Lscala/collection/immutable/Map;
  #268 = Methodref          #255.#267     // org/scalatest/Suite$.autoTagClassAnnotations:(Lscala/collection/immutable/Map;Lorg/scalatest/Suite;)Lscala/collection/immutable/Map;
  #269 = Utf8               runTest$
  #270 = Utf8               (Lorg/scalatest/freespec/FixtureAsyncFreeSpecLike;Ljava/lang/String;Lorg/scalatest/Args;)Lorg/scalatest/Status;
  #271 = Utf8               runTest
  #272 = Utf8               (Ljava/lang/String;Lorg/scalatest/Args;)Lorg/scalatest/Status;
  #273 = NameAndType        #271:#272     // runTest:(Ljava/lang/String;Lorg/scalatest/Args;)Lorg/scalatest/Status;
  #274 = InterfaceMethodref #2.#273       // org/scalatest/freespec/FixtureAsyncFreeSpecLike.runTest:(Ljava/lang/String;Lorg/scalatest/Args;)Lorg/scalatest/Status;
  #275 = Utf8               Lorg/scalatest/Args;
  #276 = Utf8               parallelAsyncTestExecution
  #277 = Utf8               ()Z
  #278 = NameAndType        #276:#277     // parallelAsyncTestExecution:()Z
  #279 = InterfaceMethodref #2.#278       // org/scalatest/freespec/FixtureAsyncFreeSpecLike.parallelAsyncTestExecution:()Z
  #280 = Utf8               (Ljava/lang/Object;Ljava/lang/Object;)Ljava/lang/Object;
  #281 = MethodType         #280          //  (Ljava/lang/Object;Ljava/lang/Object;)Ljava/lang/Object;
  #282 = Utf8               $anonfun$runTest$1
  #283 = Utf8               (Lorg/scalatest/freespec/FixtureAsyncFreeSpecLike;Lorg/scalatest/Args;Ljava/lang/String;Lorg/scalatest/AsyncSuperEngine$TestLeaf;Lscala/Function1;)Lorg/scalatest/AsyncOutcome;
  #284 = NameAndType        #282:#283     // $anonfun$runTest$1:(Lorg/scalatest/freespec/FixtureAsyncFreeSpecLike;Lorg/scalatest/Args;Ljava/lang/String;Lorg/scalatest/AsyncSuperEngine$TestLeaf;Lscala/Function1;)Lorg/scalatest/AsyncOutcome;
  #285 = InterfaceMethodref #2.#284       // org/scalatest/freespec/FixtureAsyncFreeSpecLike.$anonfun$runTest$1:(Lorg/scalatest/freespec/FixtureAsyncFreeSpecLike;Lorg/scalatest/Args;Ljava/lang/String;Lorg/scalatest/AsyncSuperEngine$TestLeaf;Lscala/Function1;)Lorg/scalatest/AsyncOutcome;
  #286 = MethodHandle       6:#285        // REF_invokeStatic org/scalatest/freespec/FixtureAsyncFreeSpecLike.$anonfun$runTest$1:(Lorg/scalatest/freespec/FixtureAsyncFreeSpecLike;Lorg/scalatest/Args;Ljava/lang/String;Lorg/scalatest/AsyncSuperEngine$TestLeaf;Lscala/Function1;)Lorg/scalatest/AsyncOutcome;
  #287 = Utf8               (Lorg/scalatest/AsyncSuperEngine$TestLeaf;Lscala/Function1;)Lorg/scalatest/AsyncOutcome;
  #288 = MethodType         #287          //  (Lorg/scalatest/AsyncSuperEngine$TestLeaf;Lscala/Function1;)Lorg/scalatest/AsyncOutcome;
  #289 = Utf8               (Lorg/scalatest/freespec/FixtureAsyncFreeSpecLike;Lorg/scalatest/Args;Ljava/lang/String;)Lscala/Function2;
  #290 = NameAndType        #148:#289     // apply:(Lorg/scalatest/freespec/FixtureAsyncFreeSpecLike;Lorg/scalatest/Args;Ljava/lang/String;)Lscala/Function2;
  #291 = InvokeDynamic      #6:#290       // #6:apply:(Lorg/scalatest/freespec/FixtureAsyncFreeSpecLike;Lorg/scalatest/Args;Ljava/lang/String;)Lscala/Function2;
  #292 = Utf8               runTestImpl
  #293 = Utf8               (Lorg/scalatest/Suite;Ljava/lang/String;Lorg/scalatest/Args;ZZLscala/Function2;Lscala/concurrent/ExecutionContext;)Lorg/scalatest/Status;
  #294 = NameAndType        #292:#293     // runTestImpl:(Lorg/scalatest/Suite;Ljava/lang/String;Lorg/scalatest/Args;ZZLscala/Function2;Lscala/concurrent/ExecutionContext;)Lorg/scalatest/Status;
  #295 = Methodref          #74.#294      // org/scalatest/AsyncFixtureEngine.runTestImpl:(Lorg/scalatest/Suite;Ljava/lang/String;Lorg/scalatest/Args;ZZLscala/Function2;Lscala/concurrent/ExecutionContext;)Lorg/scalatest/Status;
  #296 = Utf8               runTests$
  #297 = Utf8               (Lorg/scalatest/freespec/FixtureAsyncFreeSpecLike;Lscala/Option;Lorg/scalatest/Args;)Lorg/scalatest/Status;
  #298 = Utf8               runTests
  #299 = NameAndType        #298:#57      // runTests:(Lscala/Option;Lorg/scalatest/Args;)Lorg/scalatest/Status;
  #300 = InterfaceMethodref #2.#299       // org/scalatest/freespec/FixtureAsyncFreeSpecLike.runTests:(Lscala/Option;Lorg/scalatest/Args;)Lorg/scalatest/Status;
  #301 = Utf8               Lscala/Option;
  #302 = Utf8               (Lscala/Option<Ljava/lang/String;>;Lorg/scalatest/Args;)Lorg/scalatest/Status;
  #303 = Utf8               $anonfun$runTests$1
  #304 = NameAndType        #303:#270     // $anonfun$runTests$1:(Lorg/scalatest/freespec/FixtureAsyncFreeSpecLike;Ljava/lang/String;Lorg/scalatest/Args;)Lorg/scalatest/Status;
  #305 = InterfaceMethodref #2.#304       // org/scalatest/freespec/FixtureAsyncFreeSpecLike.$anonfun$runTests$1:(Lorg/scalatest/freespec/FixtureAsyncFreeSpecLike;Ljava/lang/String;Lorg/scalatest/Args;)Lorg/scalatest/Status;
  #306 = MethodHandle       6:#305        // REF_invokeStatic org/scalatest/freespec/FixtureAsyncFreeSpecLike.$anonfun$runTests$1:(Lorg/scalatest/freespec/FixtureAsyncFreeSpecLike;Ljava/lang/String;Lorg/scalatest/Args;)Lorg/scalatest/Status;
  #307 = MethodType         #272          //  (Ljava/lang/String;Lorg/scalatest/Args;)Lorg/scalatest/Status;
  #308 = Utf8               (Lorg/scalatest/freespec/FixtureAsyncFreeSpecLike;)Lscala/Function2;
  #309 = NameAndType        #148:#308     // apply:(Lorg/scalatest/freespec/FixtureAsyncFreeSpecLike;)Lscala/Function2;
  #310 = InvokeDynamic      #7:#309       // #7:apply:(Lorg/scalatest/freespec/FixtureAsyncFreeSpecLike;)Lscala/Function2;
  #311 = Utf8               runTestsImpl
  #312 = Utf8               (Lorg/scalatest/Suite;Lscala/Option;Lorg/scalatest/Args;ZZLscala/Function2;)Lorg/scalatest/Status;
  #313 = NameAndType        #311:#312     // runTestsImpl:(Lorg/scalatest/Suite;Lscala/Option;Lorg/scalatest/Args;ZZLscala/Function2;)Lorg/scalatest/Status;
  #314 = Methodref          #74.#313      // org/scalatest/AsyncFixtureEngine.runTestsImpl:(Lorg/scalatest/Suite;Lscala/Option;Lorg/scalatest/Args;ZZLscala/Function2;)Lorg/scalatest/Status;
  #315 = Utf8               testNames$
  #316 = Utf8               (Lorg/scalatest/freespec/FixtureAsyncFreeSpecLike;)Lscala/collection/immutable/Set;
  #317 = Utf8               testNames
  #318 = Utf8               ()Lscala/collection/immutable/Set;
  #319 = NameAndType        #317:#318     // testNames:()Lscala/collection/immutable/Set;
  #320 = InterfaceMethodref #2.#319       // org/scalatest/freespec/FixtureAsyncFreeSpecLike.testNames:()Lscala/collection/immutable/Set;
  #321 = Utf8               ()Lscala/collection/immutable/Set<Ljava/lang/String;>;
  #322 = Utf8               org/scalatest/InsertionOrderSet$
  #323 = Class              #322          // org/scalatest/InsertionOrderSet$
  #324 = Utf8               Lorg/scalatest/InsertionOrderSet$;
  #325 = NameAndType        #154:#324     // MODULE$:Lorg/scalatest/InsertionOrderSet$;
  #326 = Fieldref           #323.#325     // org/scalatest/InsertionOrderSet$.MODULE$:Lorg/scalatest/InsertionOrderSet$;
  #327 = Utf8               testNamesList
  #328 = Utf8               ()Lscala/collection/immutable/List;
  #329 = NameAndType        #327:#328     // testNamesList:()Lscala/collection/immutable/List;
  #330 = Methodref          #30.#329      // org/scalatest/AsyncSuperEngine$Bundle.testNamesList:()Lscala/collection/immutable/List;
  #331 = Utf8               (Lscala/collection/immutable/List;)Lscala/collection/immutable/Set;
  #332 = NameAndType        #148:#331     // apply:(Lscala/collection/immutable/List;)Lscala/collection/immutable/Set;
  #333 = Methodref          #323.#332     // org/scalatest/InsertionOrderSet$.apply:(Lscala/collection/immutable/List;)Lscala/collection/immutable/Set;
  #334 = Utf8               run$
  #335 = Utf8               run
  #336 = NameAndType        #335:#57      // run:(Lscala/Option;Lorg/scalatest/Args;)Lorg/scalatest/Status;
  #337 = InterfaceMethodref #2.#336       // org/scalatest/freespec/FixtureAsyncFreeSpecLike.run:(Lscala/Option;Lorg/scalatest/Args;)Lorg/scalatest/Status;
  #338 = Utf8               $anonfun$run$1
  #339 = NameAndType        #338:#297     // $anonfun$run$1:(Lorg/scalatest/freespec/FixtureAsyncFreeSpecLike;Lscala/Option;Lorg/scalatest/Args;)Lorg/scalatest/Status;
  #340 = InterfaceMethodref #2.#339       // org/scalatest/freespec/FixtureAsyncFreeSpecLike.$anonfun$run$1:(Lorg/scalatest/freespec/FixtureAsyncFreeSpecLike;Lscala/Option;Lorg/scalatest/Args;)Lorg/scalatest/Status;
  #341 = MethodHandle       6:#340        // REF_invokeStatic org/scalatest/freespec/FixtureAsyncFreeSpecLike.$anonfun$run$1:(Lorg/scalatest/freespec/FixtureAsyncFreeSpecLike;Lscala/Option;Lorg/scalatest/Args;)Lorg/scalatest/Status;
  #342 = MethodType         #57           //  (Lscala/Option;Lorg/scalatest/Args;)Lorg/scalatest/Status;
  #343 = InvokeDynamic      #8:#309       // #8:apply:(Lorg/scalatest/freespec/FixtureAsyncFreeSpecLike;)Lscala/Function2;
  #344 = Utf8               runImpl
  #345 = Utf8               (Lorg/scalatest/Suite;Lscala/Option;Lorg/scalatest/Args;ZLscala/Function2;)Lorg/scalatest/Status;
  #346 = NameAndType        #344:#345     // runImpl:(Lorg/scalatest/Suite;Lscala/Option;Lorg/scalatest/Args;ZLscala/Function2;)Lorg/scalatest/Status;
  #347 = Methodref          #74.#346      // org/scalatest/AsyncFixtureEngine.runImpl:(Lorg/scalatest/Suite;Lscala/Option;Lorg/scalatest/Args;ZLscala/Function2;)Lorg/scalatest/Status;
  #348 = Utf8               behave
  #349 = Utf8               ()Lorg/scalatest/verbs/BehaveWord;
  #350 = Utf8               styleName
  #351 = Utf8               testDataFor$
  #352 = Utf8               (Lorg/scalatest/freespec/FixtureAsyncFreeSpecLike;Ljava/lang/String;Lorg/scalatest/ConfigMap;)Lorg/scalatest/TestData;
  #353 = Utf8               theConfigMap
  #354 = Utf8               testDataFor
  #355 = Utf8               (Ljava/lang/String;Lorg/scalatest/ConfigMap;)Lorg/scalatest/TestData;
  #356 = NameAndType        #354:#355     // testDataFor:(Ljava/lang/String;Lorg/scalatest/ConfigMap;)Lorg/scalatest/TestData;
  #357 = InterfaceMethodref #2.#356       // org/scalatest/freespec/FixtureAsyncFreeSpecLike.testDataFor:(Ljava/lang/String;Lorg/scalatest/ConfigMap;)Lorg/scalatest/TestData;
  #358 = Utf8               Lorg/scalatest/ConfigMap;
  #359 = Utf8               createTestDataFor
  #360 = Utf8               (Ljava/lang/String;Lorg/scalatest/ConfigMap;Lorg/scalatest/Suite;)Lorg/scalatest/TestData;
  #361 = NameAndType        #359:#360     // createTestDataFor:(Ljava/lang/String;Lorg/scalatest/ConfigMap;Lorg/scalatest/Suite;)Lorg/scalatest/TestData;
  #362 = Methodref          #74.#361      // org/scalatest/AsyncFixtureEngine.createTestDataFor:(Ljava/lang/String;Lorg/scalatest/ConfigMap;Lorg/scalatest/Suite;)Lorg/scalatest/TestData;
  #363 = Utf8               testDataFor$default$2$
  #364 = Utf8               (Lorg/scalatest/freespec/FixtureAsyncFreeSpecLike;)Lorg/scalatest/ConfigMap;
  #365 = Utf8               testDataFor$default$2
  #366 = Utf8               ()Lorg/scalatest/ConfigMap;
  #367 = NameAndType        #365:#366     // testDataFor$default$2:()Lorg/scalatest/ConfigMap;
  #368 = InterfaceMethodref #2.#367       // org/scalatest/freespec/FixtureAsyncFreeSpecLike.testDataFor$default$2:()Lorg/scalatest/ConfigMap;
  #369 = Utf8               org/scalatest/ConfigMap$
  #370 = Class              #369          // org/scalatest/ConfigMap$
  #371 = Utf8               Lorg/scalatest/ConfigMap$;
  #372 = NameAndType        #154:#371     // MODULE$:Lorg/scalatest/ConfigMap$;
  #373 = Fieldref           #370.#372     // org/scalatest/ConfigMap$.MODULE$:Lorg/scalatest/ConfigMap$;
  #374 = Utf8               empty
  #375 = NameAndType        #374:#366     // empty:()Lorg/scalatest/ConfigMap;
  #376 = Methodref          #370.#375     // org/scalatest/ConfigMap$.empty:()Lorg/scalatest/ConfigMap;
  #377 = Utf8               $anonfun$engine$1
  #378 = Utf8               org/scalatest/Resources$
  #379 = Class              #378          // org/scalatest/Resources$
  #380 = Utf8               Lorg/scalatest/Resources$;
  #381 = NameAndType        #154:#380     // MODULE$:Lorg/scalatest/Resources$;
  #382 = Fieldref           #379.#381     // org/scalatest/Resources$.MODULE$:Lorg/scalatest/Resources$;
  #383 = Utf8               concurrentFixtureFreeSpecMod
  #384 = NameAndType        #383:#134     // concurrentFixtureFreeSpecMod:()Ljava/lang/String;
  #385 = Methodref          #379.#384     // org/scalatest/Resources$.concurrentFixtureFreeSpecMod:()Ljava/lang/String;
  #386 = Utf8               testCannotBeNestedInsideAnotherTest
  #387 = NameAndType        #386:#134     // testCannotBeNestedInsideAnotherTest:()Ljava/lang/String;
  #388 = Methodref          #379.#387     // org/scalatest/Resources$.testCannotBeNestedInsideAnotherTest:()Ljava/lang/String;
  #389 = Utf8               inCannotAppearInsideAnotherIn
  #390 = NameAndType        #389:#134     // inCannotAppearInsideAnotherIn:()Ljava/lang/String;
  #391 = Methodref          #379.#390     // org/scalatest/Resources$.inCannotAppearInsideAnotherIn:()Ljava/lang/String;
  #392 = Utf8               ignoreCannotAppearInsideAnIn
  #393 = NameAndType        #392:#134     // ignoreCannotAppearInsideAnIn:()Ljava/lang/String;
  #394 = Methodref          #379.#393     // org/scalatest/Resources$.ignoreCannotAppearInsideAnIn:()Ljava/lang/String;
  #395 = Utf8               invokeWithAsyncFixture$1
  #396 = Utf8               (Lorg/scalatest/AsyncSuperEngine$TestLeaf;Lscala/Function1;Lorg/scalatest/Args;Ljava/lang/String;)Lorg/scalatest/AsyncOutcome;
  #397 = Utf8               theTest
  #398 = Utf8               onCompleteFun
  #399 = Utf8               args$1
  #400 = Utf8               testName$1
  #401 = Utf8               org/scalatest/Args
  #402 = Class              #401          // org/scalatest/Args
  #403 = Utf8               configMap
  #404 = NameAndType        #403:#366     // configMap:()Lorg/scalatest/ConfigMap;
  #405 = Methodref          #402.#404     // org/scalatest/Args.configMap:()Lorg/scalatest/ConfigMap;
  #406 = Utf8               org/scalatest/FutureAsyncOutcome
  #407 = Class              #406          // org/scalatest/FutureAsyncOutcome
  #408 = Utf8               (Lorg/scalatest/freespec/FixtureAsyncFreeSpecLike;Lorg/scalatest/TestData;Lorg/scalatest/AsyncSuperEngine$TestLeaf;)V
  #409 = NameAndType        #213:#408     // "<init>":(Lorg/scalatest/freespec/FixtureAsyncFreeSpecLike;Lorg/scalatest/TestData;Lorg/scalatest/AsyncSuperEngine$TestLeaf;)V
  #410 = Methodref          #41.#409      // org/scalatest/freespec/FixtureAsyncFreeSpecLike$$anon$1."<init>":(Lorg/scalatest/freespec/FixtureAsyncFreeSpecLike;Lorg/scalatest/TestData;Lorg/scalatest/AsyncSuperEngine$TestLeaf;)V
  #411 = Utf8               withFixture
  #412 = Utf8               (Lorg/scalatest/FixtureAsyncTestSuite$OneArgAsyncTest;)Lorg/scalatest/FutureOutcome;
  #413 = NameAndType        #411:#412     // withFixture:(Lorg/scalatest/FixtureAsyncTestSuite$OneArgAsyncTest;)Lorg/scalatest/FutureOutcome;
  #414 = InterfaceMethodref #2.#413       // org/scalatest/freespec/FixtureAsyncFreeSpecLike.withFixture:(Lorg/scalatest/FixtureAsyncTestSuite$OneArgAsyncTest;)Lorg/scalatest/FutureOutcome;
  #415 = Utf8               org/scalatest/FutureOutcome
  #416 = Class              #415          // org/scalatest/FutureOutcome
  #417 = Utf8               underlying
  #418 = Utf8               ()Lscala/concurrent/Future;
  #419 = NameAndType        #417:#418     // underlying:()Lscala/concurrent/Future;
  #420 = Methodref          #416.#419     // org/scalatest/FutureOutcome.underlying:()Lscala/concurrent/Future;
  #421 = Utf8               (Lscala/concurrent/Future;Lscala/Function1;Lscala/concurrent/ExecutionContext;)V
  #422 = NameAndType        #213:#421     // "<init>":(Lscala/concurrent/Future;Lscala/Function1;Lscala/concurrent/ExecutionContext;)V
  #423 = Methodref          #407.#422     // org/scalatest/FutureAsyncOutcome."<init>":(Lscala/concurrent/Future;Lscala/Function1;Lscala/concurrent/ExecutionContext;)V
  #424 = Utf8               testData
  #425 = Utf8               Lorg/scalatest/TestData;
  #426 = Utf8               Lorg/scalatest/AsyncSuperEngine$TestLeaf;
  #427 = NameAndType        #395:#396     // invokeWithAsyncFixture$1:(Lorg/scalatest/AsyncSuperEngine$TestLeaf;Lscala/Function1;Lorg/scalatest/Args;Ljava/lang/String;)Lorg/scalatest/AsyncOutcome;
  #428 = InterfaceMethodref #2.#427       // org/scalatest/freespec/FixtureAsyncFreeSpecLike.invokeWithAsyncFixture$1:(Lorg/scalatest/AsyncSuperEngine$TestLeaf;Lscala/Function1;Lorg/scalatest/Args;Ljava/lang/String;)Lorg/scalatest/AsyncOutcome;
  #429 = NameAndType        #56:#57       // org$scalatest$freespec$FixtureAsyncFreeSpecLike$$super$run:(Lscala/Option;Lorg/scalatest/Args;)Lorg/scalatest/Status;
  #430 = InterfaceMethodref #2.#429       // org/scalatest/freespec/FixtureAsyncFreeSpecLike.org$scalatest$freespec$FixtureAsyncFreeSpecLike$$super$run:(Lscala/Option;Lorg/scalatest/Args;)Lorg/scalatest/Status;
  #431 = Utf8               $init$
  #432 = Utf8               (Lorg/scalatest/freespec/FixtureAsyncFreeSpecLike;)V
  #433 = NameAndType        #377:#134     // $anonfun$engine$1:()Ljava/lang/String;
  #434 = InterfaceMethodref #2.#433       // org/scalatest/freespec/FixtureAsyncFreeSpecLike.$anonfun$engine$1:()Ljava/lang/String;
  #435 = MethodHandle       6:#434        // REF_invokeStatic org/scalatest/freespec/FixtureAsyncFreeSpecLike.$anonfun$engine$1:()Ljava/lang/String;
  #436 = InvokeDynamic      #9:#150       // #9:apply:()Lscala/Function0;
  #437 = Utf8               FixtureFreeSpec
  #438 = String             #437          // FixtureFreeSpec
  #439 = Utf8               (Lscala/Function0;Ljava/lang/String;)V
  #440 = NameAndType        #213:#439     // "<init>":(Lscala/Function0;Ljava/lang/String;)V
  #441 = Methodref          #74.#440      // org/scalatest/AsyncFixtureEngine."<init>":(Lscala/Function0;Ljava/lang/String;)V
  #442 = NameAndType        #48:#49       // org$scalatest$freespec$FixtureAsyncFreeSpecLike$_setter_$org$scalatest$freespec$FixtureAsyncFreeSpecLike$$engine_$eq:(Lorg/scalatest/AsyncFixtureEngine;)V
  #443 = InterfaceMethodref #2.#442       // org/scalatest/freespec/FixtureAsyncFreeSpecLike.org$scalatest$freespec$FixtureAsyncFreeSpecLike$_setter_$org$scalatest$freespec$FixtureAsyncFreeSpecLike$$engine_$eq:(Lorg/scalatest/AsyncFixtureEngine;)V
  #444 = Utf8               org/scalatest/verbs/BehaveWord
  #445 = Class              #444          // org/scalatest/verbs/BehaveWord
  #446 = Utf8               ()V
  #447 = NameAndType        #213:#446     // "<init>":()V
  #448 = Methodref          #445.#447     // org/scalatest/verbs/BehaveWord."<init>":()V
  #449 = NameAndType        #52:#53       // org$scalatest$freespec$FixtureAsyncFreeSpecLike$_setter_$behave_$eq:(Lorg/scalatest/verbs/BehaveWord;)V
  #450 = InterfaceMethodref #2.#449       // org/scalatest/freespec/FixtureAsyncFreeSpecLike.org$scalatest$freespec$FixtureAsyncFreeSpecLike$_setter_$behave_$eq:(Lorg/scalatest/verbs/BehaveWord;)V
  #451 = Utf8               org.scalatest.fixture.FreeSpec
  #452 = String             #451          // org.scalatest.fixture.FreeSpec
  #453 = NameAndType        #54:#55       // org$scalatest$freespec$FixtureAsyncFreeSpecLike$_setter_$styleName_$eq:(Ljava/lang/String;)V
  #454 = InterfaceMethodref #2.#453       // org/scalatest/freespec/FixtureAsyncFreeSpecLike.org$scalatest$freespec$FixtureAsyncFreeSpecLike$_setter_$styleName_$eq:(Ljava/lang/String;)V
  #455 = Utf8               $deserializeLambda$
  #456 = Utf8               (Ljava/lang/invoke/SerializedLambda;)Ljava/lang/Object;
  #457 = Utf8               scala/runtime/LambdaDeserialize
  #458 = Class              #457          // scala/runtime/LambdaDeserialize
  #459 = Utf8               bootstrap
  #460 = Utf8               (Ljava/lang/invoke/MethodHandles$Lookup;Ljava/lang/String;Ljava/lang/invoke/MethodType;[Ljava/lang/invoke/MethodHandle;)Ljava/lang/invoke/CallSite;
  #461 = NameAndType        #459:#460     // bootstrap:(Ljava/lang/invoke/MethodHandles$Lookup;Ljava/lang/String;Ljava/lang/invoke/MethodType;[Ljava/lang/invoke/MethodHandle;)Ljava/lang/invoke/CallSite;
  #462 = Methodref          #458.#461     // scala/runtime/LambdaDeserialize.bootstrap:(Ljava/lang/invoke/MethodHandles$Lookup;Ljava/lang/String;Ljava/lang/invoke/MethodType;[Ljava/lang/invoke/MethodHandle;)Ljava/lang/invoke/CallSite;
  #463 = MethodHandle       6:#462        // REF_invokeStatic scala/runtime/LambdaDeserialize.bootstrap:(Ljava/lang/invoke/MethodHandles$Lookup;Ljava/lang/String;Ljava/lang/invoke/MethodType;[Ljava/lang/invoke/MethodHandle;)Ljava/lang/invoke/CallSite;
  #464 = Utf8               lambdaDeserialize
  #465 = NameAndType        #464:#456     // lambdaDeserialize:(Ljava/lang/invoke/SerializedLambda;)Ljava/lang/Object;
  #466 = InvokeDynamic      #10:#465      // #10:lambdaDeserialize:(Ljava/lang/invoke/SerializedLambda;)Ljava/lang/Object;
  #467 = Utf8               Signature
  #468 = Utf8               MethodParameters
  #469 = Utf8               Code
  #470 = Utf8               LineNumberTable
  #471 = Utf8               LocalVariableTable
  #472 = Utf8               Deprecated
  #473 = Utf8               InnerClasses
  #474 = Utf8               SourceFile
  #475 = Utf8               RuntimeVisibleAnnotations
  #476 = Utf8               BootstrapMethods
  #477 = Utf8               ScalaInlineInfo
  #478 = Utf8               ScalaSig
{
  public abstract void org$scalatest$freespec$FixtureAsyncFreeSpecLike$_setter_$org$scalatest$freespec$FixtureAsyncFreeSpecLike$$engine_$eq(org.scalatest.AsyncFixtureEngine<java.lang.Object>);
    descriptor: (Lorg/scalatest/AsyncFixtureEngine;)V
    flags: (0x0401) ACC_PUBLIC, ACC_ABSTRACT
    Signature: #50                          // (Lorg/scalatest/AsyncFixtureEngine<Ljava/lang/Object;>;)V
    MethodParameters:
      Name                           Flags
      x$1                            final

  public abstract void org$scalatest$freespec$FixtureAsyncFreeSpecLike$_setter_$behave_$eq(org.scalatest.verbs.BehaveWord);
    descriptor: (Lorg/scalatest/verbs/BehaveWord;)V
    flags: (0x0401) ACC_PUBLIC, ACC_ABSTRACT
    MethodParameters:
      Name                           Flags
      x$1                            final

  public abstract void org$scalatest$freespec$FixtureAsyncFreeSpecLike$_setter_$styleName_$eq(java.lang.String);
    descriptor: (Ljava/lang/String;)V
    flags: (0x0401) ACC_PUBLIC, ACC_ABSTRACT
    MethodParameters:
      Name                           Flags
      x$1                            final

  public abstract org.scalatest.Status org$scalatest$freespec$FixtureAsyncFreeSpecLike$$super$run(scala.Option, org.scalatest.Args);
    descriptor: (Lscala/Option;Lorg/scalatest/Args;)Lorg/scalatest/Status;
    flags: (0x1401) ACC_PUBLIC, ACC_ABSTRACT, ACC_SYNTHETIC
    MethodParameters:
      Name                           Flags
      testName                       final
      args                           final

  public abstract org.scalatest.AsyncFixtureEngine<java.lang.Object> org$scalatest$freespec$FixtureAsyncFreeSpecLike$$engine();
    descriptor: ()Lorg/scalatest/AsyncFixtureEngine;
    flags: (0x0401) ACC_PUBLIC, ACC_ABSTRACT
    Signature: #62                          // ()Lorg/scalatest/AsyncFixtureEngine<Ljava/lang/Object;>;

  public static org.scalatest.Informer info$(org.scalatest.freespec.FixtureAsyncFreeSpecLike);
    descriptor: (Lorg/scalatest/freespec/FixtureAsyncFreeSpecLike;)Lorg/scalatest/Informer;
    flags: (0x1009) ACC_PUBLIC, ACC_STATIC, ACC_SYNTHETIC
    Code:
      stack=1, locals=1, args_size=1
         0: aload_0
         1: invokespecial #69                 // InterfaceMethod info:()Lorg/scalatest/Informer;
         4: areturn
      LineNumberTable:
        line 66: 0
      LocalVariableTable:
        Start  Length  Slot  Name   Signature
            0       5     0 $this   Lorg/scalatest/freespec/FixtureAsyncFreeSpecLike;
    MethodParameters:
      Name                           Flags
      $this                          final synthetic

  public default org.scalatest.Informer info();
    descriptor: ()Lorg/scalatest/Informer;
    flags: (0x0001) ACC_PUBLIC
    Code:
      stack=1, locals=1, args_size=1
         0: aload_0
         1: invokeinterface #72,  1           // InterfaceMethod org$scalatest$freespec$FixtureAsyncFreeSpecLike$$engine:()Lorg/scalatest/AsyncFixtureEngine;
         6: invokevirtual #78                 // Method org/scalatest/AsyncFixtureEngine.atomicInformer:()Ljava/util/concurrent/atomic/AtomicReference;
         9: invokevirtual #84                 // Method java/util/concurrent/atomic/AtomicReference.get:()Ljava/lang/Object;
        12: checkcast     #86                 // class org/scalatest/Informer
        15: areturn
      LineNumberTable:
        line 66: 0
      LocalVariableTable:
        Start  Length  Slot  Name   Signature
            0      16     0  this   Lorg/scalatest/freespec/FixtureAsyncFreeSpecLike;

  public static org.scalatest.Notifier note$(org.scalatest.freespec.FixtureAsyncFreeSpecLike);
    descriptor: (Lorg/scalatest/freespec/FixtureAsyncFreeSpecLike;)Lorg/scalatest/Notifier;
    flags: (0x1009) ACC_PUBLIC, ACC_STATIC, ACC_SYNTHETIC
    Code:
      stack=1, locals=1, args_size=1
         0: aload_0
         1: invokespecial #93                 // InterfaceMethod note:()Lorg/scalatest/Notifier;
         4: areturn
      LineNumberTable:
        line 76: 0
      LocalVariableTable:
        Start  Length  Slot  Name   Signature
            0       5     0 $this   Lorg/scalatest/freespec/FixtureAsyncFreeSpecLike;
    MethodParameters:
      Name                           Flags
      $this                          final synthetic

  public default org.scalatest.Notifier note();
    descriptor: ()Lorg/scalatest/Notifier;
    flags: (0x0001) ACC_PUBLIC
    Code:
      stack=1, locals=1, args_size=1
         0: aload_0
         1: invokeinterface #72,  1           // InterfaceMethod org$scalatest$freespec$FixtureAsyncFreeSpecLike$$engine:()Lorg/scalatest/AsyncFixtureEngine;
         6: invokevirtual #96                 // Method org/scalatest/AsyncFixtureEngine.atomicNotifier:()Ljava/util/concurrent/atomic/AtomicReference;
         9: invokevirtual #84                 // Method java/util/concurrent/atomic/AtomicReference.get:()Ljava/lang/Object;
        12: checkcast     #98                 // class org/scalatest/Notifier
        15: areturn
      LineNumberTable:
        line 76: 0
      LocalVariableTable:
        Start  Length  Slot  Name   Signature
            0      16     0  this   Lorg/scalatest/freespec/FixtureAsyncFreeSpecLike;

  public static org.scalatest.Alerter alert$(org.scalatest.freespec.FixtureAsyncFreeSpecLike);
    descriptor: (Lorg/scalatest/freespec/FixtureAsyncFreeSpecLike;)Lorg/scalatest/Alerter;
    flags: (0x1009) ACC_PUBLIC, ACC_STATIC, ACC_SYNTHETIC
    Code:
      stack=1, locals=1, args_size=1
         0: aload_0
         1: invokespecial #104                // InterfaceMethod alert:()Lorg/scalatest/Alerter;
         4: areturn
      LineNumberTable:
        line 86: 0
      LocalVariableTable:
        Start  Length  Slot  Name   Signature
            0       5     0 $this   Lorg/scalatest/freespec/FixtureAsyncFreeSpecLike;
    MethodParameters:
      Name                           Flags
      $this                          final synthetic

  public default org.scalatest.Alerter alert();
    descriptor: ()Lorg/scalatest/Alerter;
    flags: (0x0001) ACC_PUBLIC
    Code:
      stack=1, locals=1, args_size=1
         0: aload_0
         1: invokeinterface #72,  1           // InterfaceMethod org$scalatest$freespec$FixtureAsyncFreeSpecLike$$engine:()Lorg/scalatest/AsyncFixtureEngine;
         6: invokevirtual #107                // Method org/scalatest/AsyncFixtureEngine.atomicAlerter:()Ljava/util/concurrent/atomic/AtomicReference;
         9: invokevirtual #84                 // Method java/util/concurrent/atomic/AtomicReference.get:()Ljava/lang/Object;
        12: checkcast     #109                // class org/scalatest/Alerter
        15: areturn
      LineNumberTable:
        line 86: 0
      LocalVariableTable:
        Start  Length  Slot  Name   Signature
            0      16     0  this   Lorg/scalatest/freespec/FixtureAsyncFreeSpecLike;

  public static org.scalatest.Documenter markup$(org.scalatest.freespec.FixtureAsyncFreeSpecLike);
    descriptor: (Lorg/scalatest/freespec/FixtureAsyncFreeSpecLike;)Lorg/scalatest/Documenter;
    flags: (0x1009) ACC_PUBLIC, ACC_STATIC, ACC_SYNTHETIC
    Code:
      stack=1, locals=1, args_size=1
         0: aload_0
         1: invokespecial #115                // InterfaceMethod markup:()Lorg/scalatest/Documenter;
         4: areturn
      LineNumberTable:
        line 97: 0
      LocalVariableTable:
        Start  Length  Slot  Name   Signature
            0       5     0 $this   Lorg/scalatest/freespec/FixtureAsyncFreeSpecLike;
    MethodParameters:
      Name                           Flags
      $this                          final synthetic

  public default org.scalatest.Documenter markup();
    descriptor: ()Lorg/scalatest/Documenter;
    flags: (0x0001) ACC_PUBLIC
    Code:
      stack=1, locals=1, args_size=1
         0: aload_0
         1: invokeinterface #72,  1           // InterfaceMethod org$scalatest$freespec$FixtureAsyncFreeSpecLike$$engine:()Lorg/scalatest/AsyncFixtureEngine;
         6: invokevirtual #118                // Method org/scalatest/AsyncFixtureEngine.atomicDocumenter:()Ljava/util/concurrent/atomic/AtomicReference;
         9: invokevirtual #84                 // Method java/util/concurrent/atomic/AtomicReference.get:()Ljava/lang/Object;
        12: checkcast     #120                // class org/scalatest/Documenter
        15: areturn
      LineNumberTable:
        line 97: 0
      LocalVariableTable:
        Start  Length  Slot  Name   Signature
            0      16     0  this   Lorg/scalatest/freespec/FixtureAsyncFreeSpecLike;

  private void registerAsyncTestImpl(java.lang.String, scala.collection.immutable.Seq<org.scalatest.Tag>, scala.Function1<java.lang.Object, scala.concurrent.Future<org.scalatest.compatible.Assertion>>, org.scalactic.source.Position);
    descriptor: (Ljava/lang/String;Lscala/collection/immutable/Seq;Lscala/Function1;Lorg/scalactic/source/Position;)V
    flags: (0x0002) ACC_PRIVATE
    Code:
      stack=8, locals=5, args_size=5
         0: aload_0
         1: invokeinterface #72,  1           // InterfaceMethod org$scalatest$freespec$FixtureAsyncFreeSpecLike$$engine:()Lorg/scalatest/AsyncFixtureEngine;
         6: aload_1
         7: aload_0
         8: aload_3
         9: invokeinterface #131,  2          // InterfaceMethod transformToOutcome:(Lscala/Function1;)Lscala/Function1;
        14: invokedynamic #151,  0            // InvokeDynamic #0:apply:()Lscala/Function0;
        19: getstatic     #157                // Field scala/None$.MODULE$:Lscala/None$;
        22: getstatic     #157                // Field scala/None$.MODULE$:Lscala/None$;
        25: aload         4
        27: aload_2
        28: invokevirtual #161                // Method org/scalatest/AsyncFixtureEngine.registerAsyncTest:(Ljava/lang/String;Ljava/lang/Object;Lscala/Function0;Lscala/Option;Lscala/Option;Lorg/scalactic/source/Position;Lscala/collection/immutable/Seq;)Ljava/lang/String;
        31: pop
        32: return
      LineNumberTable:
        line 100: 0
      LocalVariableTable:
        Start  Length  Slot  Name   Signature
            0      33     0  this   Lorg/scalatest/freespec/FixtureAsyncFreeSpecLike;
            0      33     1 testText   Ljava/lang/String;
            0      33     2 testTags   Lscala/collection/immutable/Seq;
            0      33     3 testFun   Lscala/Function1;
            0      33     4   pos   Lorg/scalactic/source/Position;
    Signature: #123                         // (Ljava/lang/String;Lscala/collection/immutable/Seq<Lorg/scalatest/Tag;>;Lscala/Function1<Ljava/lang/Object;Lscala/concurrent/Future<Lorg/scalatest/compatible/Assertion;>;>;Lorg/scalactic/source/Position;)V
    MethodParameters:
      Name                           Flags
      testText                       final
      testTags                       final
      testFun                        final
      pos                            final

  public static void registerAsyncTest$(org.scalatest.freespec.FixtureAsyncFreeSpecLike, java.lang.String, scala.collection.immutable.Seq, scala.Function1, org.scalactic.source.Position);
    descriptor: (Lorg/scalatest/freespec/FixtureAsyncFreeSpecLike;Ljava/lang/String;Lscala/collection/immutable/Seq;Lscala/Function1;Lorg/scalactic/source/Position;)V
    flags: (0x1009) ACC_PUBLIC, ACC_STATIC, ACC_SYNTHETIC
    Code:
      stack=5, locals=5, args_size=5
         0: aload_0
         1: aload_1
         2: aload_2
         3: aload_3
         4: aload         4
         6: invokespecial #169                // InterfaceMethod registerAsyncTest:(Ljava/lang/String;Lscala/collection/immutable/Seq;Lscala/Function1;Lorg/scalactic/source/Position;)V
         9: return
      LineNumberTable:
        line 104: 0
      LocalVariableTable:
        Start  Length  Slot  Name   Signature
            0      10     0 $this   Lorg/scalatest/freespec/FixtureAsyncFreeSpecLike;
            0      10     1 testText   Ljava/lang/String;
            0      10     2 testTags   Lscala/collection/immutable/Seq;
            0      10     3 testFun   Lscala/Function1;
            0      10     4   pos   Lorg/scalactic/source/Position;
    MethodParameters:
      Name                           Flags
      $this                          final synthetic
      testText                       final
      testTags                       final
      testFun                        final
      pos                            final

  public default void registerAsyncTest(java.lang.String, scala.collection.immutable.Seq<org.scalatest.Tag>, scala.Function1<java.lang.Object, scala.concurrent.Future<org.scalatest.compatible.Assertion>>, org.scalactic.source.Position);
    descriptor: (Ljava/lang/String;Lscala/collection/immutable/Seq;Lscala/Function1;Lorg/scalactic/source/Position;)V
    flags: (0x0001) ACC_PUBLIC
    Code:
      stack=5, locals=5, args_size=5
         0: aload_0
         1: aload_1
         2: aload_2
         3: aload_3
         4: aload         4
         6: invokespecial #171                // InterfaceMethod registerAsyncTestImpl:(Ljava/lang/String;Lscala/collection/immutable/Seq;Lscala/Function1;Lorg/scalactic/source/Position;)V
         9: return
      LineNumberTable:
        line 105: 0
      LocalVariableTable:
        Start  Length  Slot  Name   Signature
            0      10     0  this   Lorg/scalatest/freespec/FixtureAsyncFreeSpecLike;
            0      10     1 testText   Ljava/lang/String;
            0      10     2 testTags   Lscala/collection/immutable/Seq;
            0      10     3 testFun   Lscala/Function1;
            0      10     4   pos   Lorg/scalactic/source/Position;
    Signature: #123                         // (Ljava/lang/String;Lscala/collection/immutable/Seq<Lorg/scalatest/Tag;>;Lscala/Function1<Ljava/lang/Object;Lscala/concurrent/Future<Lorg/scalatest/compatible/Assertion;>;>;Lorg/scalactic/source/Position;)V
    MethodParameters:
      Name                           Flags
      testText                       final
      testTags                       final
      testFun                        final
      pos                            final

  private void registerIgnoredAsyncTestImpl(java.lang.String, scala.collection.immutable.Seq<org.scalatest.Tag>, scala.Function1<java.lang.Object, scala.concurrent.Future<org.scalatest.compatible.Assertion>>, org.scalactic.source.Position);
    descriptor: (Ljava/lang/String;Lscala/collection/immutable/Seq;Lscala/Function1;Lorg/scalactic/source/Position;)V
    flags: (0x0002) ACC_PRIVATE
    Code:
      stack=7, locals=5, args_size=5
         0: aload_0
         1: invokeinterface #72,  1           // InterfaceMethod org$scalatest$freespec$FixtureAsyncFreeSpecLike$$engine:()Lorg/scalatest/AsyncFixtureEngine;
         6: aload_1
         7: aload_0
         8: aload_3
         9: invokeinterface #131,  2          // InterfaceMethod transformToOutcome:(Lscala/Function1;)Lscala/Function1;
        14: invokedynamic #177,  0            // InvokeDynamic #1:apply:()Lscala/Function0;
        19: getstatic     #157                // Field scala/None$.MODULE$:Lscala/None$;
        22: aload         4
        24: aload_2
        25: invokevirtual #181                // Method org/scalatest/AsyncFixtureEngine.registerIgnoredAsyncTest:(Ljava/lang/String;Ljava/lang/Object;Lscala/Function0;Lscala/Option;Lorg/scalactic/source/Position;Lscala/collection/immutable/Seq;)V
        28: return
      LineNumberTable:
        line 113: 0
      LocalVariableTable:
        Start  Length  Slot  Name   Signature
            0      29     0  this   Lorg/scalatest/freespec/FixtureAsyncFreeSpecLike;
            0      29     1 testText   Ljava/lang/String;
            0      29     2 testTags   Lscala/collection/immutable/Seq;
            0      29     3 testFun   Lscala/Function1;
            0      29     4   pos   Lorg/scalactic/source/Position;
    Signature: #123                         // (Ljava/lang/String;Lscala/collection/immutable/Seq<Lorg/scalatest/Tag;>;Lscala/Function1<Ljava/lang/Object;Lscala/concurrent/Future<Lorg/scalatest/compatible/Assertion;>;>;Lorg/scalactic/source/Position;)V
    MethodParameters:
      Name                           Flags
      testText                       final
      testTags                       final
      testFun                        final
      pos                            final

  public static void registerIgnoredAsyncTest$(org.scalatest.freespec.FixtureAsyncFreeSpecLike, java.lang.String, scala.collection.immutable.Seq, scala.Function1, org.scalactic.source.Position);
    descriptor: (Lorg/scalatest/freespec/FixtureAsyncFreeSpecLike;Ljava/lang/String;Lscala/collection/immutable/Seq;Lscala/Function1;Lorg/scalactic/source/Position;)V
    flags: (0x1009) ACC_PUBLIC, ACC_STATIC, ACC_SYNTHETIC
    Code:
      stack=5, locals=5, args_size=5
         0: aload_0
         1: aload_1
         2: aload_2
         3: aload_3
         4: aload         4
         6: invokespecial #184                // InterfaceMethod registerIgnoredAsyncTest:(Ljava/lang/String;Lscala/collection/immutable/Seq;Lscala/Function1;Lorg/scalactic/source/Position;)V
         9: return
      LineNumberTable:
        line 117: 0
      LocalVariableTable:
        Start  Length  Slot  Name   Signature
            0      10     0 $this   Lorg/scalatest/freespec/FixtureAsyncFreeSpecLike;
            0      10     1 testText   Ljava/lang/String;
            0      10     2 testTags   Lscala/collection/immutable/Seq;
            0      10     3 testFun   Lscala/Function1;
            0      10     4   pos   Lorg/scalactic/source/Position;
    MethodParameters:
      Name                           Flags
      $this                          final synthetic
      testText                       final
      testTags                       final
      testFun                        final
      pos                            final

  public default void registerIgnoredAsyncTest(java.lang.String, scala.collection.immutable.Seq<org.scalatest.Tag>, scala.Function1<java.lang.Object, scala.concurrent.Future<org.scalatest.compatible.Assertion>>, org.scalactic.source.Position);
    descriptor: (Ljava/lang/String;Lscala/collection/immutable/Seq;Lscala/Function1;Lorg/scalactic/source/Position;)V
    flags: (0x0001) ACC_PUBLIC
    Code:
      stack=5, locals=5, args_size=5
         0: aload_0
         1: aload_1
         2: aload_2
         3: aload_3
         4: aload         4
         6: invokespecial #186                // InterfaceMethod registerIgnoredAsyncTestImpl:(Ljava/lang/String;Lscala/collection/immutable/Seq;Lscala/Function1;Lorg/scalactic/source/Position;)V
         9: return
      LineNumberTable:
        line 118: 0
      LocalVariableTable:
        Start  Length  Slot  Name   Signature
            0      10     0  this   Lorg/scalatest/freespec/FixtureAsyncFreeSpecLike;
            0      10     1 testText   Ljava/lang/String;
            0      10     2 testTags   Lscala/collection/immutable/Seq;
            0      10     3 testFun   Lscala/Function1;
            0      10     4   pos   Lorg/scalactic/source/Position;
    Signature: #123                         // (Ljava/lang/String;Lscala/collection/immutable/Seq<Lorg/scalatest/Tag;>;Lscala/Function1<Ljava/lang/Object;Lscala/concurrent/Future<Lorg/scalatest/compatible/Assertion;>;>;Lorg/scalactic/source/Position;)V
    MethodParameters:
      Name                           Flags
      testText                       final
      testTags                       final
      testFun                        final
      pos                            final

  public static void org$scalatest$freespec$FixtureAsyncFreeSpecLike$$registerAsyncTestToRun$(org.scalatest.freespec.FixtureAsyncFreeSpecLike, java.lang.String, scala.collection.immutable.List, java.lang.String, scala.Function1, org.scalactic.source.Position);
    descriptor: (Lorg/scalatest/freespec/FixtureAsyncFreeSpecLike;Ljava/lang/String;Lscala/collection/immutable/List;Ljava/lang/String;Lscala/Function1;Lorg/scalactic/source/Position;)V
    flags: (0x1009) ACC_PUBLIC, ACC_STATIC, ACC_SYNTHETIC
    Code:
      stack=6, locals=6, args_size=6
         0: aload_0
         1: aload_1
         2: aload_2
         3: aload_3
         4: aload         4
         6: aload         5
         8: invokespecial #194                // InterfaceMethod org$scalatest$freespec$FixtureAsyncFreeSpecLike$$registerAsyncTestToRun:(Ljava/lang/String;Lscala/collection/immutable/List;Ljava/lang/String;Lscala/Function1;Lorg/scalactic/source/Position;)V
        11: return
      LineNumberTable:
        line 144: 0
      LocalVariableTable:
        Start  Length  Slot  Name   Signature
            0      12     0 $this   Lorg/scalatest/freespec/FixtureAsyncFreeSpecLike;
            0      12     1 specText   Ljava/lang/String;
            0      12     2 testTags   Lscala/collection/immutable/List;
            0      12     3 methodName   Ljava/lang/String;
            0      12     4 testFun   Lscala/Function1;
            0      12     5   pos   Lorg/scalactic/source/Position;
    MethodParameters:
      Name                           Flags
      $this                          final synthetic
      specText                       final
      testTags                       final
      methodName                     final
      testFun                        final
      pos                            final

  public default void org$scalatest$freespec$FixtureAsyncFreeSpecLike$$registerAsyncTestToRun(java.lang.String, scala.collection.immutable.List<org.scalatest.Tag>, java.lang.String, scala.Function1<java.lang.Object, scala.concurrent.Future<org.scalatest.compatible.Assertion>>, org.scalactic.source.Position);
    descriptor: (Ljava/lang/String;Lscala/collection/immutable/List;Ljava/lang/String;Lscala/Function1;Lorg/scalactic/source/Position;)V
    flags: (0x0001) ACC_PUBLIC
    Code:
      stack=8, locals=6, args_size=6
         0: aload_0
         1: invokeinterface #72,  1           // InterfaceMethod org$scalatest$freespec$FixtureAsyncFreeSpecLike$$engine:()Lorg/scalatest/AsyncFixtureEngine;
         6: aload_1
         7: aload_0
         8: aload         4
        10: invokeinterface #131,  2          // InterfaceMethod transformToOutcome:(Lscala/Function1;)Lscala/Function1;
        15: invokedynamic #201,  0            // InvokeDynamic #2:apply:()Lscala/Function0;
        20: getstatic     #157                // Field scala/None$.MODULE$:Lscala/None$;
        23: getstatic     #157                // Field scala/None$.MODULE$:Lscala/None$;
        26: aload         5
        28: aload_2
        29: invokevirtual #161                // Method org/scalatest/AsyncFixtureEngine.registerAsyncTest:(Ljava/lang/String;Ljava/lang/Object;Lscala/Function0;Lscala/Option;Lscala/Option;Lorg/scalactic/source/Position;Lscala/collection/immutable/Seq;)Ljava/lang/String;
        32: pop
        33: return
      LineNumberTable:
        line 145: 0
      LocalVariableTable:
        Start  Length  Slot  Name   Signature
            0      34     0  this   Lorg/scalatest/freespec/FixtureAsyncFreeSpecLike;
            0      34     1 specText   Ljava/lang/String;
            0      34     2 testTags   Lscala/collection/immutable/List;
            0      34     3 methodName   Ljava/lang/String;
            0      34     4 testFun   Lscala/Function1;
            0      34     5   pos   Lorg/scalactic/source/Position;
    Signature: #196                         // (Ljava/lang/String;Lscala/collection/immutable/List<Lorg/scalatest/Tag;>;Ljava/lang/String;Lscala/Function1<Ljava/lang/Object;Lscala/concurrent/Future<Lorg/scalatest/compatible/Assertion;>;>;Lorg/scalactic/source/Position;)V
    MethodParameters:
      Name                           Flags
      specText                       final
      testTags                       final
      methodName                     final
      testFun                        final
      pos                            final

  public static void org$scalatest$freespec$FixtureAsyncFreeSpecLike$$registerPendingTestToRun$(org.scalatest.freespec.FixtureAsyncFreeSpecLike, java.lang.String, scala.collection.immutable.List, java.lang.String, scala.Function1, org.scalactic.source.Position);
    descriptor: (Lorg/scalatest/freespec/FixtureAsyncFreeSpecLike;Ljava/lang/String;Lscala/collection/immutable/List;Ljava/lang/String;Lscala/Function1;Lorg/scalactic/source/Position;)V
    flags: (0x1009) ACC_PUBLIC, ACC_STATIC, ACC_SYNTHETIC
    Code:
      stack=6, locals=6, args_size=6
         0: aload_0
         1: aload_1
         2: aload_2
         3: aload_3
         4: aload         4
         6: aload         5
         8: invokespecial #205                // InterfaceMethod org$scalatest$freespec$FixtureAsyncFreeSpecLike$$registerPendingTestToRun:(Ljava/lang/String;Lscala/collection/immutable/List;Ljava/lang/String;Lscala/Function1;Lorg/scalactic/source/Position;)V
        11: return
      LineNumberTable:
        line 148: 0
      LocalVariableTable:
        Start  Length  Slot  Name   Signature
            0      12     0 $this   Lorg/scalatest/freespec/FixtureAsyncFreeSpecLike;
            0      12     1 specText   Ljava/lang/String;
            0      12     2 testTags   Lscala/collection/immutable/List;
            0      12     3 methodName   Ljava/lang/String;
            0      12     4 testFun   Lscala/Function1;
            0      12     5   pos   Lorg/scalactic/source/Position;
    MethodParameters:
      Name                           Flags
      $this                          final synthetic
      specText                       final
      testTags                       final
      methodName                     final
      testFun                        final
      pos                            final

  public default void org$scalatest$freespec$FixtureAsyncFreeSpecLike$$registerPendingTestToRun(java.lang.String, scala.collection.immutable.List<org.scalatest.Tag>, java.lang.String, scala.Function1<java.lang.Object, org.scalatest.PendingStatement>, org.scalactic.source.Position);
    descriptor: (Ljava/lang/String;Lscala/collection/immutable/List;Ljava/lang/String;Lscala/Function1;Lorg/scalactic/source/Position;)V
    flags: (0x0001) ACC_PUBLIC
    Code:
      stack=8, locals=6, args_size=6
         0: aload_0
         1: invokeinterface #72,  1           // InterfaceMethod org$scalatest$freespec$FixtureAsyncFreeSpecLike$$engine:()Lorg/scalatest/AsyncFixtureEngine;
         6: aload_1
         7: new           #208                // class org/scalatest/fixture/AsyncPendingTransformer
        10: dup
        11: aload         4
        13: aload_0
        14: invokeinterface #212,  1          // InterfaceMethod executionContext:()Lscala/concurrent/ExecutionContext;
        19: invokespecial #216                // Method org/scalatest/fixture/AsyncPendingTransformer."<init>":(Lscala/Function1;Lscala/concurrent/ExecutionContext;)V
        22: invokedynamic #221,  0            // InvokeDynamic #3:apply:()Lscala/Function0;
        27: getstatic     #157                // Field scala/None$.MODULE$:Lscala/None$;
        30: getstatic     #157                // Field scala/None$.MODULE$:Lscala/None$;
        33: aload         5
        35: aload_2
        36: invokevirtual #161                // Method org/scalatest/AsyncFixtureEngine.registerAsyncTest:(Ljava/lang/String;Ljava/lang/Object;Lscala/Function0;Lscala/Option;Lscala/Option;Lorg/scalactic/source/Position;Lscala/collection/immutable/Seq;)Ljava/lang/String;
        39: pop
        40: return
      LineNumberTable:
        line 149: 0
      LocalVariableTable:
        Start  Length  Slot  Name   Signature
            0      41     0  this   Lorg/scalatest/freespec/FixtureAsyncFreeSpecLike;
            0      41     1 specText   Ljava/lang/String;
            0      41     2 testTags   Lscala/collection/immutable/List;
            0      41     3 methodName   Ljava/lang/String;
            0      41     4 testFun   Lscala/Function1;
            0      41     5   pos   Lorg/scalactic/source/Position;
    Signature: #206                         // (Ljava/lang/String;Lscala/collection/immutable/List<Lorg/scalatest/Tag;>;Ljava/lang/String;Lscala/Function1<Ljava/lang/Object;Lorg/scalatest/PendingStatement;>;Lorg/scalactic/source/Position;)V
    MethodParameters:
      Name                           Flags
      specText                       final
      testTags                       final
      methodName                     final
      testFun                        final
      pos                            final

  public static void org$scalatest$freespec$FixtureAsyncFreeSpecLike$$registerAsyncTestToIgnore$(org.scalatest.freespec.FixtureAsyncFreeSpecLike, java.lang.String, scala.collection.immutable.List, java.lang.String, scala.Function1, org.scalactic.source.Position);
    descriptor: (Lorg/scalatest/freespec/FixtureAsyncFreeSpecLike;Ljava/lang/String;Lscala/collection/immutable/List;Ljava/lang/String;Lscala/Function1;Lorg/scalactic/source/Position;)V
    flags: (0x1009) ACC_PUBLIC, ACC_STATIC, ACC_SYNTHETIC
    Code:
      stack=6, locals=6, args_size=6
         0: aload_0
         1: aload_1
         2: aload_2
         3: aload_3
         4: aload         4
         6: aload         5
         8: invokespecial #225                // InterfaceMethod org$scalatest$freespec$FixtureAsyncFreeSpecLike$$registerAsyncTestToIgnore:(Ljava/lang/String;Lscala/collection/immutable/List;Ljava/lang/String;Lscala/Function1;Lorg/scalactic/source/Position;)V
        11: return
      LineNumberTable:
        line 171: 0
      LocalVariableTable:
        Start  Length  Slot  Name   Signature
            0      12     0 $this   Lorg/scalatest/freespec/FixtureAsyncFreeSpecLike;
            0      12     1 specText   Ljava/lang/String;
            0      12     2 testTags   Lscala/collection/immutable/List;
            0      12     3 methodName   Ljava/lang/String;
            0      12     4 testFun   Lscala/Function1;
            0      12     5   pos   Lorg/scalactic/source/Position;
    MethodParameters:
      Name                           Flags
      $this                          final synthetic
      specText                       final
      testTags                       final
      methodName                     final
      testFun                        final
      pos                            final

  public default void org$scalatest$freespec$FixtureAsyncFreeSpecLike$$registerAsyncTestToIgnore(java.lang.String, scala.collection.immutable.List<org.scalatest.Tag>, java.lang.String, scala.Function1<java.lang.Object, scala.concurrent.Future<org.scalatest.compatible.Assertion>>, org.scalactic.source.Position);
    descriptor: (Ljava/lang/String;Lscala/collection/immutable/List;Ljava/lang/String;Lscala/Function1;Lorg/scalactic/source/Position;)V
    flags: (0x0001) ACC_PUBLIC
    Code:
      stack=7, locals=6, args_size=6
         0: aload_0
         1: invokeinterface #72,  1           // InterfaceMethod org$scalatest$freespec$FixtureAsyncFreeSpecLike$$engine:()Lorg/scalatest/AsyncFixtureEngine;
         6: aload_1
         7: aload_0
         8: aload         4
        10: invokeinterface #131,  2          // InterfaceMethod transformToOutcome:(Lscala/Function1;)Lscala/Function1;
        15: invokedynamic #230,  0            // InvokeDynamic #4:apply:()Lscala/Function0;
        20: getstatic     #157                // Field scala/None$.MODULE$:Lscala/None$;
        23: aload         5
        25: aload_2
        26: invokevirtual #181                // Method org/scalatest/AsyncFixtureEngine.registerIgnoredAsyncTest:(Ljava/lang/String;Ljava/lang/Object;Lscala/Function0;Lscala/Option;Lorg/scalactic/source/Position;Lscala/collection/immutable/Seq;)V
        29: return
      LineNumberTable:
        line 172: 0
      LocalVariableTable:
        Start  Length  Slot  Name   Signature
            0      30     0  this   Lorg/scalatest/freespec/FixtureAsyncFreeSpecLike;
            0      30     1 specText   Ljava/lang/String;
            0      30     2 testTags   Lscala/collection/immutable/List;
            0      30     3 methodName   Ljava/lang/String;
            0      30     4 testFun   Lscala/Function1;
            0      30     5   pos   Lorg/scalactic/source/Position;
    Signature: #196                         // (Ljava/lang/String;Lscala/collection/immutable/List<Lorg/scalatest/Tag;>;Ljava/lang/String;Lscala/Function1<Ljava/lang/Object;Lscala/concurrent/Future<Lorg/scalatest/compatible/Assertion;>;>;Lorg/scalactic/source/Position;)V
    MethodParameters:
      Name                           Flags
      specText                       final
      testTags                       final
      methodName                     final
      testFun                        final
      pos                            final

  private void registerPendingTestToIgnore(java.lang.String, scala.collection.immutable.List<org.scalatest.Tag>, java.lang.String, scala.Function1<java.lang.Object, org.scalatest.PendingStatement>, org.scalactic.source.Position);
    descriptor: (Ljava/lang/String;Lscala/collection/immutable/List;Ljava/lang/String;Lscala/Function1;Lorg/scalactic/source/Position;)V
    flags: (0x0002) ACC_PRIVATE
    Code:
      stack=7, locals=6, args_size=6
         0: aload_0
         1: invokeinterface #72,  1           // InterfaceMethod org$scalatest$freespec$FixtureAsyncFreeSpecLike$$engine:()Lorg/scalatest/AsyncFixtureEngine;
         6: aload_1
         7: new           #208                // class org/scalatest/fixture/AsyncPendingTransformer
        10: dup
        11: aload         4
        13: aload_0
        14: invokeinterface #212,  1          // InterfaceMethod executionContext:()Lscala/concurrent/ExecutionContext;
        19: invokespecial #216                // Method org/scalatest/fixture/AsyncPendingTransformer."<init>":(Lscala/Function1;Lscala/concurrent/ExecutionContext;)V
        22: invokedynamic #236,  0            // InvokeDynamic #5:apply:()Lscala/Function0;
        27: getstatic     #157                // Field scala/None$.MODULE$:Lscala/None$;
        30: aload         5
        32: aload_2
        33: invokevirtual #181                // Method org/scalatest/AsyncFixtureEngine.registerIgnoredAsyncTest:(Ljava/lang/String;Ljava/lang/Object;Lscala/Function0;Lscala/Option;Lorg/scalactic/source/Position;Lscala/collection/immutable/Seq;)V
        36: return
      LineNumberTable:
        line 176: 0
      LocalVariableTable:
        Start  Length  Slot  Name   Signature
            0      37     0  this   Lorg/scalatest/freespec/FixtureAsyncFreeSpecLike;
            0      37     1 specText   Ljava/lang/String;
            0      37     2 testTags   Lscala/collection/immutable/List;
            0      37     3 methodName   Ljava/lang/String;
            0      37     4 testFun   Lscala/Function1;
            0      37     5   pos   Lorg/scalactic/source/Position;
    Signature: #206                         // (Ljava/lang/String;Lscala/collection/immutable/List<Lorg/scalatest/Tag;>;Ljava/lang/String;Lscala/Function1<Ljava/lang/Object;Lorg/scalatest/PendingStatement;>;Lorg/scalactic/source/Position;)V
    MethodParameters:
      Name                           Flags
      specText                       final
      testTags                       final
      methodName                     final
      testFun                        final
      pos                            final

  public static org.scalatest.freespec.FixtureAsyncFreeSpecLike$FreeSpecStringWrapper convertToFreeSpecStringWrapper$(org.scalatest.freespec.FixtureAsyncFreeSpecLike, java.lang.String, org.scalactic.source.Position);
    descriptor: (Lorg/scalatest/freespec/FixtureAsyncFreeSpecLike;Ljava/lang/String;Lorg/scalactic/source/Position;)Lorg/scalatest/freespec/FixtureAsyncFreeSpecLike$FreeSpecStringWrapper;
    flags: (0x1009) ACC_PUBLIC, ACC_STATIC, ACC_SYNTHETIC
    Code:
      stack=3, locals=3, args_size=3
         0: aload_0
         1: aload_1
         2: aload_2
         3: invokespecial #243                // InterfaceMethod convertToFreeSpecStringWrapper:(Ljava/lang/String;Lorg/scalactic/source/Position;)Lorg/scalatest/freespec/FixtureAsyncFreeSpecLike$FreeSpecStringWrapper;
         6: areturn
      LineNumberTable:
        line 494: 0
      LocalVariableTable:
        Start  Length  Slot  Name   Signature
            0       7     0 $this   Lorg/scalatest/freespec/FixtureAsyncFreeSpecLike;
            0       7     1     s   Ljava/lang/String;
            0       7     2   pos   Lorg/scalactic/source/Position;
    MethodParameters:
      Name                           Flags
      $this                          final synthetic
      s                              final
      pos                            final

  public default org.scalatest.freespec.FixtureAsyncFreeSpecLike$FreeSpecStringWrapper convertToFreeSpecStringWrapper(java.lang.String, org.scalactic.source.Position);
    descriptor: (Ljava/lang/String;Lorg/scalactic/source/Position;)Lorg/scalatest/freespec/FixtureAsyncFreeSpecLike$FreeSpecStringWrapper;
    flags: (0x0001) ACC_PUBLIC
    Code:
      stack=5, locals=3, args_size=3
         0: new           #43                 // class org/scalatest/freespec/FixtureAsyncFreeSpecLike$FreeSpecStringWrapper
         3: dup
         4: aload_0
         5: aload_1
         6: aload_2
         7: invokespecial #246                // Method org/scalatest/freespec/FixtureAsyncFreeSpecLike$FreeSpecStringWrapper."<init>":(Lorg/scalatest/freespec/FixtureAsyncFreeSpecLike;Ljava/lang/String;Lorg/scalactic/source/Position;)V
        10: areturn
      LineNumberTable:
        line 494: 0
      LocalVariableTable:
        Start  Length  Slot  Name   Signature
            0      11     0  this   Lorg/scalatest/freespec/FixtureAsyncFreeSpecLike;
            0      11     1     s   Ljava/lang/String;
            0      11     2   pos   Lorg/scalactic/source/Position;
    MethodParameters:
      Name                           Flags
      s                              final
      pos                            final

  public static scala.collection.immutable.Map tags$(org.scalatest.freespec.FixtureAsyncFreeSpecLike);
    descriptor: (Lorg/scalatest/freespec/FixtureAsyncFreeSpecLike;)Lscala/collection/immutable/Map;
    flags: (0x1009) ACC_PUBLIC, ACC_STATIC, ACC_SYNTHETIC
    Code:
      stack=1, locals=1, args_size=1
         0: aload_0
         1: invokespecial #252                // InterfaceMethod tags:()Lscala/collection/immutable/Map;
         4: areturn
      LineNumberTable:
        line 514: 0
      LocalVariableTable:
        Start  Length  Slot  Name   Signature
            0       5     0 $this   Lorg/scalatest/freespec/FixtureAsyncFreeSpecLike;
    MethodParameters:
      Name                           Flags
      $this                          final synthetic

  public default scala.collection.immutable.Map<java.lang.String, scala.collection.immutable.Set<java.lang.String>> tags();
    descriptor: ()Lscala/collection/immutable/Map;
    flags: (0x0001) ACC_PUBLIC
    Code:
      stack=3, locals=1, args_size=1
         0: getstatic     #258                // Field org/scalatest/Suite$.MODULE$:Lorg/scalatest/Suite$;
         3: aload_0
         4: invokeinterface #72,  1           // InterfaceMethod org$scalatest$freespec$FixtureAsyncFreeSpecLike$$engine:()Lorg/scalatest/AsyncFixtureEngine;
         9: invokevirtual #261                // Method org/scalatest/AsyncFixtureEngine.atomic:()Ljava/util/concurrent/atomic/AtomicReference;
        12: invokevirtual #84                 // Method java/util/concurrent/atomic/AtomicReference.get:()Ljava/lang/Object;
        15: checkcast     #30                 // class org/scalatest/AsyncSuperEngine$Bundle
        18: invokevirtual #264                // Method org/scalatest/AsyncSuperEngine$Bundle.tagsMap:()Lscala/collection/immutable/Map;
        21: aload_0
        22: invokevirtual #268                // Method org/scalatest/Suite$.autoTagClassAnnotations:(Lscala/collection/immutable/Map;Lorg/scalatest/Suite;)Lscala/collection/immutable/Map;
        25: areturn
      LineNumberTable:
        line 514: 0
      LocalVariableTable:
        Start  Length  Slot  Name   Signature
            0      26     0  this   Lorg/scalatest/freespec/FixtureAsyncFreeSpecLike;
    Signature: #253                         // ()Lscala/collection/immutable/Map<Ljava/lang/String;Lscala/collection/immutable/Set<Ljava/lang/String;>;>;

  public static org.scalatest.Status runTest$(org.scalatest.freespec.FixtureAsyncFreeSpecLike, java.lang.String, org.scalatest.Args);
    descriptor: (Lorg/scalatest/freespec/FixtureAsyncFreeSpecLike;Ljava/lang/String;Lorg/scalatest/Args;)Lorg/scalatest/Status;
    flags: (0x1009) ACC_PUBLIC, ACC_STATIC, ACC_SYNTHETIC
    Code:
      stack=3, locals=3, args_size=3
         0: aload_0
         1: aload_1
         2: aload_2
         3: invokespecial #274                // InterfaceMethod runTest:(Ljava/lang/String;Lorg/scalatest/Args;)Lorg/scalatest/Status;
         6: areturn
      LineNumberTable:
        line 527: 0
      LocalVariableTable:
        Start  Length  Slot  Name   Signature
            0       7     0 $this   Lorg/scalatest/freespec/FixtureAsyncFreeSpecLike;
            0       7     1 testName   Ljava/lang/String;
            0       7     2  args   Lorg/scalatest/Args;
    MethodParameters:
      Name                           Flags
      $this                          final synthetic
      testName                       final
      args                           final

  public default org.scalatest.Status runTest(java.lang.String, org.scalatest.Args);
    descriptor: (Ljava/lang/String;Lorg/scalatest/Args;)Lorg/scalatest/Status;
    flags: (0x0001) ACC_PUBLIC
    Code:
      stack=9, locals=3, args_size=3
         0: aload_0
         1: invokeinterface #72,  1           // InterfaceMethod org$scalatest$freespec$FixtureAsyncFreeSpecLike$$engine:()Lorg/scalatest/AsyncFixtureEngine;
         6: aload_0
         7: aload_1
         8: aload_2
         9: iconst_1
        10: aload_0
        11: invokeinterface #279,  1          // InterfaceMethod parallelAsyncTestExecution:()Z
        16: aload_0
        17: aload_2
        18: aload_1
        19: invokedynamic #291,  0            // InvokeDynamic #6:apply:(Lorg/scalatest/freespec/FixtureAsyncFreeSpecLike;Lorg/scalatest/Args;Ljava/lang/String;)Lscala/Function2;
        24: aload_0
        25: invokeinterface #212,  1          // InterfaceMethod executionContext:()Lscala/concurrent/ExecutionContext;
        30: invokevirtual #295                // Method org/scalatest/AsyncFixtureEngine.runTestImpl:(Lorg/scalatest/Suite;Ljava/lang/String;Lorg/scalatest/Args;ZZLscala/Function2;Lscala/concurrent/ExecutionContext;)Lorg/scalatest/Status;
        33: areturn
      LineNumberTable:
        line 550: 0
      LocalVariableTable:
        Start  Length  Slot  Name   Signature
            0      34     0  this   Lorg/scalatest/freespec/FixtureAsyncFreeSpecLike;
            0      34     1 testName   Ljava/lang/String;
            0      34     2  args   Lorg/scalatest/Args;
    MethodParameters:
      Name                           Flags
      testName                       final
      args                           final

  public static org.scalatest.Status runTests$(org.scalatest.freespec.FixtureAsyncFreeSpecLike, scala.Option, org.scalatest.Args);
    descriptor: (Lorg/scalatest/freespec/FixtureAsyncFreeSpecLike;Lscala/Option;Lorg/scalatest/Args;)Lorg/scalatest/Status;
    flags: (0x1009) ACC_PUBLIC, ACC_STATIC, ACC_SYNTHETIC
    Code:
      stack=3, locals=3, args_size=3
         0: aload_0
         1: aload_1
         2: aload_2
         3: invokespecial #300                // InterfaceMethod runTests:(Lscala/Option;Lorg/scalatest/Args;)Lorg/scalatest/Status;
         6: areturn
      LineNumberTable:
        line 592: 0
      LocalVariableTable:
        Start  Length  Slot  Name   Signature
            0       7     0 $this   Lorg/scalatest/freespec/FixtureAsyncFreeSpecLike;
            0       7     1 testName   Lscala/Option;
            0       7     2  args   Lorg/scalatest/Args;
    MethodParameters:
      Name                           Flags
      $this                          final synthetic
      testName                       final
      args                           final

  public default org.scalatest.Status runTests(scala.Option<java.lang.String>, org.scalatest.Args);
    descriptor: (Lscala/Option;Lorg/scalatest/Args;)Lorg/scalatest/Status;
    flags: (0x0001) ACC_PUBLIC
    Code:
      stack=7, locals=3, args_size=3
         0: aload_0
         1: invokeinterface #72,  1           // InterfaceMethod org$scalatest$freespec$FixtureAsyncFreeSpecLike$$engine:()Lorg/scalatest/AsyncFixtureEngine;
         6: aload_0
         7: aload_1
         8: aload_2
         9: iconst_1
        10: aload_0
        11: invokeinterface #279,  1          // InterfaceMethod parallelAsyncTestExecution:()Z
        16: aload_0
        17: invokedynamic #310,  0            // InvokeDynamic #7:apply:(Lorg/scalatest/freespec/FixtureAsyncFreeSpecLike;)Lscala/Function2;
        22: invokevirtual #314                // Method org/scalatest/AsyncFixtureEngine.runTestsImpl:(Lorg/scalatest/Suite;Lscala/Option;Lorg/scalatest/Args;ZZLscala/Function2;)Lorg/scalatest/Status;
        25: areturn
      LineNumberTable:
        line 593: 0
      LocalVariableTable:
        Start  Length  Slot  Name   Signature
            0      26     0  this   Lorg/scalatest/freespec/FixtureAsyncFreeSpecLike;
            0      26     1 testName   Lscala/Option;
            0      26     2  args   Lorg/scalatest/Args;
    Signature: #302                         // (Lscala/Option<Ljava/lang/String;>;Lorg/scalatest/Args;)Lorg/scalatest/Status;
    MethodParameters:
      Name                           Flags
      testName                       final
      args                           final

  public static scala.collection.immutable.Set testNames$(org.scalatest.freespec.FixtureAsyncFreeSpecLike);
    descriptor: (Lorg/scalatest/freespec/FixtureAsyncFreeSpecLike;)Lscala/collection/immutable/Set;
    flags: (0x1009) ACC_PUBLIC, ACC_STATIC, ACC_SYNTHETIC
    Code:
      stack=1, locals=1, args_size=1
         0: aload_0
         1: invokespecial #320                // InterfaceMethod testNames:()Lscala/collection/immutable/Set;
         4: areturn
      LineNumberTable:
        line 609: 0
      LocalVariableTable:
        Start  Length  Slot  Name   Signature
            0       5     0 $this   Lorg/scalatest/freespec/FixtureAsyncFreeSpecLike;
    MethodParameters:
      Name                           Flags
      $this                          final synthetic

  public default scala.collection.immutable.Set<java.lang.String> testNames();
    descriptor: ()Lscala/collection/immutable/Set;
    flags: (0x0001) ACC_PUBLIC
    Code:
      stack=2, locals=1, args_size=1
         0: getstatic     #326                // Field org/scalatest/InsertionOrderSet$.MODULE$:Lorg/scalatest/InsertionOrderSet$;
         3: aload_0
         4: invokeinterface #72,  1           // InterfaceMethod org$scalatest$freespec$FixtureAsyncFreeSpecLike$$engine:()Lorg/scalatest/AsyncFixtureEngine;
         9: invokevirtual #261                // Method org/scalatest/AsyncFixtureEngine.atomic:()Ljava/util/concurrent/atomic/AtomicReference;
        12: invokevirtual #84                 // Method java/util/concurrent/atomic/AtomicReference.get:()Ljava/lang/Object;
        15: checkcast     #30                 // class org/scalatest/AsyncSuperEngine$Bundle
        18: invokevirtual #330                // Method org/scalatest/AsyncSuperEngine$Bundle.testNamesList:()Lscala/collection/immutable/List;
        21: invokevirtual #333                // Method org/scalatest/InsertionOrderSet$.apply:(Lscala/collection/immutable/List;)Lscala/collection/immutable/Set;
        24: areturn
      LineNumberTable:
        line 610: 0
      LocalVariableTable:
        Start  Length  Slot  Name   Signature
            0      25     0  this   Lorg/scalatest/freespec/FixtureAsyncFreeSpecLike;
    Signature: #321                         // ()Lscala/collection/immutable/Set<Ljava/lang/String;>;

  public static org.scalatest.Status run$(org.scalatest.freespec.FixtureAsyncFreeSpecLike, scala.Option, org.scalatest.Args);
    descriptor: (Lorg/scalatest/freespec/FixtureAsyncFreeSpecLike;Lscala/Option;Lorg/scalatest/Args;)Lorg/scalatest/Status;
    flags: (0x1009) ACC_PUBLIC, ACC_STATIC, ACC_SYNTHETIC
    Code:
      stack=3, locals=3, args_size=3
         0: aload_0
         1: aload_1
         2: aload_2
         3: invokespecial #337                // InterfaceMethod run:(Lscala/Option;Lorg/scalatest/Args;)Lorg/scalatest/Status;
         6: areturn
      LineNumberTable:
        line 613: 0
      LocalVariableTable:
        Start  Length  Slot  Name   Signature
            0       7     0 $this   Lorg/scalatest/freespec/FixtureAsyncFreeSpecLike;
            0       7     1 testName   Lscala/Option;
            0       7     2  args   Lorg/scalatest/Args;
    MethodParameters:
      Name                           Flags
      $this                          final synthetic
      testName                       final
      args                           final

  public default org.scalatest.Status run(scala.Option<java.lang.String>, org.scalatest.Args);
    descriptor: (Lscala/Option;Lorg/scalatest/Args;)Lorg/scalatest/Status;
    flags: (0x0001) ACC_PUBLIC
    Code:
      stack=6, locals=3, args_size=3
         0: aload_0
         1: invokeinterface #72,  1           // InterfaceMethod org$scalatest$freespec$FixtureAsyncFreeSpecLike$$engine:()Lorg/scalatest/AsyncFixtureEngine;
         6: aload_0
         7: aload_1
         8: aload_2
         9: aload_0
        10: invokeinterface #279,  1          // InterfaceMethod parallelAsyncTestExecution:()Z
        15: aload_0
        16: invokedynamic #343,  0            // InvokeDynamic #8:apply:(Lorg/scalatest/freespec/FixtureAsyncFreeSpecLike;)Lscala/Function2;
        21: invokevirtual #347                // Method org/scalatest/AsyncFixtureEngine.runImpl:(Lorg/scalatest/Suite;Lscala/Option;Lorg/scalatest/Args;ZLscala/Function2;)Lorg/scalatest/Status;
        24: areturn
      LineNumberTable:
        line 614: 0
      LocalVariableTable:
        Start  Length  Slot  Name   Signature
            0      25     0  this   Lorg/scalatest/freespec/FixtureAsyncFreeSpecLike;
            0      25     1 testName   Lscala/Option;
            0      25     2  args   Lorg/scalatest/Args;
    Signature: #302                         // (Lscala/Option<Ljava/lang/String;>;Lorg/scalatest/Args;)Lorg/scalatest/Status;
    MethodParameters:
      Name                           Flags
      testName                       final
      args                           final

  public abstract org.scalatest.verbs.BehaveWord behave();
    descriptor: ()Lorg/scalatest/verbs/BehaveWord;
    flags: (0x0401) ACC_PUBLIC, ACC_ABSTRACT

  public abstract java.lang.String styleName();
    descriptor: ()Ljava/lang/String;
    flags: (0x0401) ACC_PUBLIC, ACC_ABSTRACT
    Deprecated: true

  public static org.scalatest.TestData testDataFor$(org.scalatest.freespec.FixtureAsyncFreeSpecLike, java.lang.String, org.scalatest.ConfigMap);
    descriptor: (Lorg/scalatest/freespec/FixtureAsyncFreeSpecLike;Ljava/lang/String;Lorg/scalatest/ConfigMap;)Lorg/scalatest/TestData;
    flags: (0x1009) ACC_PUBLIC, ACC_STATIC, ACC_SYNTHETIC
    Code:
      stack=3, locals=3, args_size=3
         0: aload_0
         1: aload_1
         2: aload_2
         3: invokespecial #357                // InterfaceMethod testDataFor:(Ljava/lang/String;Lorg/scalatest/ConfigMap;)Lorg/scalatest/TestData;
         6: areturn
      LineNumberTable:
        line 645: 0
      LocalVariableTable:
        Start  Length  Slot  Name   Signature
            0       7     0 $this   Lorg/scalatest/freespec/FixtureAsyncFreeSpecLike;
            0       7     1 testName   Ljava/lang/String;
            0       7     2 theConfigMap   Lorg/scalatest/ConfigMap;
    MethodParameters:
      Name                           Flags
      $this                          final synthetic
      testName                       final
      theConfigMap                   final

  public default org.scalatest.TestData testDataFor(java.lang.String, org.scalatest.ConfigMap);
    descriptor: (Ljava/lang/String;Lorg/scalatest/ConfigMap;)Lorg/scalatest/TestData;
    flags: (0x0001) ACC_PUBLIC
    Code:
      stack=4, locals=3, args_size=3
         0: aload_0
         1: invokeinterface #72,  1           // InterfaceMethod org$scalatest$freespec$FixtureAsyncFreeSpecLike$$engine:()Lorg/scalatest/AsyncFixtureEngine;
         6: aload_1
         7: aload_2
         8: aload_0
         9: invokevirtual #362                // Method org/scalatest/AsyncFixtureEngine.createTestDataFor:(Ljava/lang/String;Lorg/scalatest/ConfigMap;Lorg/scalatest/Suite;)Lorg/scalatest/TestData;
        12: areturn
      LineNumberTable:
        line 645: 0
      LocalVariableTable:
        Start  Length  Slot  Name   Signature
            0      13     0  this   Lorg/scalatest/freespec/FixtureAsyncFreeSpecLike;
            0      13     1 testName   Ljava/lang/String;
            0      13     2 theConfigMap   Lorg/scalatest/ConfigMap;
    MethodParameters:
      Name                           Flags
      testName                       final
      theConfigMap                   final

  public static org.scalatest.ConfigMap testDataFor$default$2$(org.scalatest.freespec.FixtureAsyncFreeSpecLike);
    descriptor: (Lorg/scalatest/freespec/FixtureAsyncFreeSpecLike;)Lorg/scalatest/ConfigMap;
    flags: (0x1009) ACC_PUBLIC, ACC_STATIC, ACC_SYNTHETIC
    Code:
      stack=1, locals=1, args_size=1
         0: aload_0
         1: invokespecial #368                // InterfaceMethod testDataFor$default$2:()Lorg/scalatest/ConfigMap;
         4: areturn
      LineNumberTable:
        line 645: 0
      LocalVariableTable:
        Start  Length  Slot  Name   Signature
            0       5     0 $this   Lorg/scalatest/freespec/FixtureAsyncFreeSpecLike;
    MethodParameters:
      Name                           Flags
      $this                          final synthetic

  public default org.scalatest.ConfigMap testDataFor$default$2();
    descriptor: ()Lorg/scalatest/ConfigMap;
    flags: (0x0001) ACC_PUBLIC
    Code:
      stack=1, locals=1, args_size=1
         0: getstatic     #373                // Field org/scalatest/ConfigMap$.MODULE$:Lorg/scalatest/ConfigMap$;
         3: invokevirtual #376                // Method org/scalatest/ConfigMap$.empty:()Lorg/scalatest/ConfigMap;
         6: areturn
      LineNumberTable:
        line 645: 0
      LocalVariableTable:
        Start  Length  Slot  Name   Signature
            0       7     0  this   Lorg/scalatest/freespec/FixtureAsyncFreeSpecLike;

  public static java.lang.String $anonfun$engine$1();
    descriptor: ()Ljava/lang/String;
    flags: (0x1009) ACC_PUBLIC, ACC_STATIC, ACC_SYNTHETIC
    Code:
      stack=1, locals=0, args_size=0
         0: getstatic     #382                // Field org/scalatest/Resources$.MODULE$:Lorg/scalatest/Resources$;
         3: invokevirtual #385                // Method org/scalatest/Resources$.concurrentFixtureFreeSpecMod:()Ljava/lang/String;
         6: areturn
      LineNumberTable:
        line 53: 0

  public static java.lang.String $anonfun$registerAsyncTestImpl$1();
    descriptor: ()Ljava/lang/String;
    flags: (0x1009) ACC_PUBLIC, ACC_STATIC, ACC_SYNTHETIC
    Code:
      stack=1, locals=0, args_size=0
         0: getstatic     #382                // Field org/scalatest/Resources$.MODULE$:Lorg/scalatest/Resources$;
         3: invokevirtual #388                // Method org/scalatest/Resources$.testCannotBeNestedInsideAnotherTest:()Ljava/lang/String;
         6: areturn
      LineNumberTable:
        line 100: 0

  public static java.lang.String $anonfun$registerIgnoredAsyncTestImpl$1();
    descriptor: ()Ljava/lang/String;
    flags: (0x1009) ACC_PUBLIC, ACC_STATIC, ACC_SYNTHETIC
    Code:
      stack=1, locals=0, args_size=0
         0: getstatic     #382                // Field org/scalatest/Resources$.MODULE$:Lorg/scalatest/Resources$;
         3: invokevirtual #388                // Method org/scalatest/Resources$.testCannotBeNestedInsideAnotherTest:()Ljava/lang/String;
         6: areturn
      LineNumberTable:
        line 113: 0

  public static java.lang.String $anonfun$registerAsyncTestToRun$1();
    descriptor: ()Ljava/lang/String;
    flags: (0x1009) ACC_PUBLIC, ACC_STATIC, ACC_SYNTHETIC
    Code:
      stack=1, locals=0, args_size=0
         0: getstatic     #382                // Field org/scalatest/Resources$.MODULE$:Lorg/scalatest/Resources$;
         3: invokevirtual #391                // Method org/scalatest/Resources$.inCannotAppearInsideAnotherIn:()Ljava/lang/String;
         6: areturn
      LineNumberTable:
        line 145: 0

  public static java.lang.String $anonfun$registerPendingTestToRun$1();
    descriptor: ()Ljava/lang/String;
    flags: (0x1009) ACC_PUBLIC, ACC_STATIC, ACC_SYNTHETIC
    Code:
      stack=1, locals=0, args_size=0
         0: getstatic     #382                // Field org/scalatest/Resources$.MODULE$:Lorg/scalatest/Resources$;
         3: invokevirtual #391                // Method org/scalatest/Resources$.inCannotAppearInsideAnotherIn:()Ljava/lang/String;
         6: areturn
      LineNumberTable:
        line 149: 0

  public static java.lang.String $anonfun$registerAsyncTestToIgnore$1();
    descriptor: ()Ljava/lang/String;
    flags: (0x1009) ACC_PUBLIC, ACC_STATIC, ACC_SYNTHETIC
    Code:
      stack=1, locals=0, args_size=0
         0: getstatic     #382                // Field org/scalatest/Resources$.MODULE$:Lorg/scalatest/Resources$;
         3: invokevirtual #394                // Method org/scalatest/Resources$.ignoreCannotAppearInsideAnIn:()Ljava/lang/String;
         6: areturn
      LineNumberTable:
        line 172: 0

  public static java.lang.String $anonfun$registerPendingTestToIgnore$1();
    descriptor: ()Ljava/lang/String;
    flags: (0x1009) ACC_PUBLIC, ACC_STATIC, ACC_SYNTHETIC
    Code:
      stack=1, locals=0, args_size=0
         0: getstatic     #382                // Field org/scalatest/Resources$.MODULE$:Lorg/scalatest/Resources$;
         3: invokevirtual #394                // Method org/scalatest/Resources$.ignoreCannotAppearInsideAnIn:()Ljava/lang/String;
         6: areturn
      LineNumberTable:
        line 176: 0

  private org.scalatest.AsyncOutcome invokeWithAsyncFixture$1(org.scalatest.AsyncSuperEngine$TestLeaf, scala.Function1, org.scalatest.Args, java.lang.String);
    descriptor: (Lorg/scalatest/AsyncSuperEngine$TestLeaf;Lscala/Function1;Lorg/scalatest/Args;Ljava/lang/String;)Lorg/scalatest/AsyncOutcome;
    flags: (0x0002) ACC_PRIVATE
    Code:
      stack=8, locals=7, args_size=5
         0: aload_3
         1: invokevirtual #405                // Method org/scalatest/Args.configMap:()Lorg/scalatest/ConfigMap;
         4: astore        5
         6: aload_0
         7: aload         4
         9: aload         5
        11: invokeinterface #357,  3          // InterfaceMethod testDataFor:(Ljava/lang/String;Lorg/scalatest/ConfigMap;)Lorg/scalatest/TestData;
        16: astore        6
        18: new           #407                // class org/scalatest/FutureAsyncOutcome
        21: dup
        22: aload_0
        23: new           #41                 // class org/scalatest/freespec/FixtureAsyncFreeSpecLike$$anon$1
        26: dup
        27: aload_0
        28: aload         6
        30: aload_1
        31: invokespecial #410                // Method org/scalatest/freespec/FixtureAsyncFreeSpecLike$$anon$1."<init>":(Lorg/scalatest/freespec/FixtureAsyncFreeSpecLike;Lorg/scalatest/TestData;Lorg/scalatest/AsyncSuperEngine$TestLeaf;)V
        34: invokeinterface #414,  2          // InterfaceMethod withFixture:(Lorg/scalatest/FixtureAsyncTestSuite$OneArgAsyncTest;)Lorg/scalatest/FutureOutcome;
        39: invokevirtual #420                // Method org/scalatest/FutureOutcome.underlying:()Lscala/concurrent/Future;
        42: aload_2
        43: aload_0
        44: invokeinterface #212,  1          // InterfaceMethod executionContext:()Lscala/concurrent/ExecutionContext;
        49: invokespecial #423                // Method org/scalatest/FutureAsyncOutcome."<init>":(Lscala/concurrent/Future;Lscala/Function1;Lscala/concurrent/ExecutionContext;)V
        52: areturn
      LineNumberTable:
        line 529: 0
        line 530: 6
        line 531: 18
        line 532: 22
        line 533: 23
        line 546: 42
        line 531: 43
      LocalVariableTable:
        Start  Length  Slot  Name   Signature
            6      46     5 theConfigMap   Lorg/scalatest/ConfigMap;
           18      34     6 testData   Lorg/scalatest/TestData;
            0      53     0  this   Lorg/scalatest/freespec/FixtureAsyncFreeSpecLike;
            0      53     1 theTest   Lorg/scalatest/AsyncSuperEngine$TestLeaf;
            0      53     2 onCompleteFun   Lscala/Function1;
            0      53     3 args$1   Lorg/scalatest/Args;
            0      53     4 testName$1   Ljava/lang/String;
    MethodParameters:
      Name                           Flags
      theTest                        final
      onCompleteFun                  final
      args$1                         final
      testName$1                     final

  public static org.scalatest.AsyncOutcome $anonfun$runTest$1(org.scalatest.freespec.FixtureAsyncFreeSpecLike, org.scalatest.Args, java.lang.String, org.scalatest.AsyncSuperEngine$TestLeaf, scala.Function1);
    descriptor: (Lorg/scalatest/freespec/FixtureAsyncFreeSpecLike;Lorg/scalatest/Args;Ljava/lang/String;Lorg/scalatest/AsyncSuperEngine$TestLeaf;Lscala/Function1;)Lorg/scalatest/AsyncOutcome;
    flags: (0x1009) ACC_PUBLIC, ACC_STATIC, ACC_SYNTHETIC
    Code:
      stack=5, locals=5, args_size=5
         0: aload_0
         1: aload_3
         2: aload         4
         4: aload_1
         5: aload_2
         6: invokespecial #428                // InterfaceMethod invokeWithAsyncFixture$1:(Lorg/scalatest/AsyncSuperEngine$TestLeaf;Lscala/Function1;Lorg/scalatest/Args;Ljava/lang/String;)Lorg/scalatest/AsyncOutcome;
         9: areturn
      LineNumberTable:
        line 550: 0
      LocalVariableTable:
        Start  Length  Slot  Name   Signature
            0      10     0 $this   Lorg/scalatest/freespec/FixtureAsyncFreeSpecLike;
            0      10     1 args$1   Lorg/scalatest/Args;
            0      10     2 testName$1   Ljava/lang/String;
            0      10     3 theTest   Lorg/scalatest/AsyncSuperEngine$TestLeaf;
            0      10     4 onCompleteFun   Lscala/Function1;
    MethodParameters:
      Name                           Flags
      $this                          final synthetic
      args$1                         final
      testName$1                     final
      theTest                        final
      onCompleteFun                  final

  public static org.scalatest.Status $anonfun$runTests$1(org.scalatest.freespec.FixtureAsyncFreeSpecLike, java.lang.String, org.scalatest.Args);
    descriptor: (Lorg/scalatest/freespec/FixtureAsyncFreeSpecLike;Ljava/lang/String;Lorg/scalatest/Args;)Lorg/scalatest/Status;
    flags: (0x1009) ACC_PUBLIC, ACC_STATIC, ACC_SYNTHETIC
    Code:
      stack=3, locals=3, args_size=3
         0: aload_0
         1: aload_1
         2: aload_2
         3: invokeinterface #274,  3          // InterfaceMethod runTest:(Ljava/lang/String;Lorg/scalatest/Args;)Lorg/scalatest/Status;
         8: areturn
      LineNumberTable:
        line 593: 0
      LocalVariableTable:
        Start  Length  Slot  Name   Signature
            0       9     0 $this   Lorg/scalatest/freespec/FixtureAsyncFreeSpecLike;
            0       9     1 testName   Ljava/lang/String;
            0       9     2  args   Lorg/scalatest/Args;
    MethodParameters:
      Name                           Flags
      $this                          final synthetic
      testName                       final
      args                           final

  public static org.scalatest.Status $anonfun$run$1(org.scalatest.freespec.FixtureAsyncFreeSpecLike, scala.Option, org.scalatest.Args);
    descriptor: (Lorg/scalatest/freespec/FixtureAsyncFreeSpecLike;Lscala/Option;Lorg/scalatest/Args;)Lorg/scalatest/Status;
    flags: (0x1009) ACC_PUBLIC, ACC_STATIC, ACC_SYNTHETIC
    Code:
      stack=3, locals=3, args_size=3
         0: aload_0
         1: aload_1
         2: aload_2
         3: invokeinterface #430,  3          // InterfaceMethod org$scalatest$freespec$FixtureAsyncFreeSpecLike$$super$run:(Lscala/Option;Lorg/scalatest/Args;)Lorg/scalatest/Status;
         8: areturn
      LineNumberTable:
        line 614: 0
      LocalVariableTable:
        Start  Length  Slot  Name   Signature
            0       9     0 $this   Lorg/scalatest/freespec/FixtureAsyncFreeSpecLike;
            0       9     1 testName   Lscala/Option;
            0       9     2  args   Lorg/scalatest/Args;
    MethodParameters:
      Name                           Flags
      $this                          final synthetic
      testName                       final
      args                           final

  public static void $init$(org.scalatest.freespec.FixtureAsyncFreeSpecLike);
    descriptor: (Lorg/scalatest/freespec/FixtureAsyncFreeSpecLike;)V
    flags: (0x0009) ACC_PUBLIC, ACC_STATIC
    Code:
      stack=5, locals=1, args_size=1
         0: aload_0
         1: new           #74                 // class org/scalatest/AsyncFixtureEngine
         4: dup
         5: invokedynamic #436,  0            // InvokeDynamic #9:apply:()Lscala/Function0;
        10: ldc_w         #438                // String FixtureFreeSpec
        13: invokespecial #441                // Method org/scalatest/AsyncFixtureEngine."<init>":(Lscala/Function0;Ljava/lang/String;)V
        16: invokeinterface #443,  2          // InterfaceMethod org$scalatest$freespec$FixtureAsyncFreeSpecLike$_setter_$org$scalatest$freespec$FixtureAsyncFreeSpecLike$$engine_$eq:(Lorg/scalatest/AsyncFixtureEngine;)V
        21: aload_0
        22: new           #445                // class org/scalatest/verbs/BehaveWord
        25: dup
        26: invokespecial #448                // Method org/scalatest/verbs/BehaveWord."<init>":()V
        29: invokeinterface #450,  2          // InterfaceMethod org$scalatest$freespec$FixtureAsyncFreeSpecLike$_setter_$behave_$eq:(Lorg/scalatest/verbs/BehaveWord;)V
        34: aload_0
        35: ldc_w         #452                // String org.scalatest.fixture.FreeSpec
        38: invokeinterface #454,  2          // InterfaceMethod org$scalatest$freespec$FixtureAsyncFreeSpecLike$_setter_$styleName_$eq:(Ljava/lang/String;)V
        43: return
      LineNumberTable:
        line 53: 0
        line 634: 21
        line 643: 34
        line 51: 43
      LocalVariableTable:
        Start  Length  Slot  Name   Signature
            0      44     0 $this   Lorg/scalatest/freespec/FixtureAsyncFreeSpecLike;
    MethodParameters:
      Name                           Flags
      $this                          final synthetic

  private static java.lang.Object $deserializeLambda$(java.lang.invoke.SerializedLambda);
    descriptor: (Ljava/lang/invoke/SerializedLambda;)Ljava/lang/Object;
    flags: (0x100a) ACC_PRIVATE, ACC_STATIC, ACC_SYNTHETIC
    Code:
      stack=1, locals=1, args_size=1
         0: aload_0
         1: invokedynamic #466,  0            // InvokeDynamic #10:lambdaDeserialize:(Ljava/lang/invoke/SerializedLambda;)Ljava/lang/Object;
         6: areturn
}
InnerClasses:
  public static final #28= #25 of #27;    // Lookup=class java/lang/invoke/MethodHandles$Lookup of class java/lang/invoke/MethodHandles
  public #33= #30 of #32;                 // Bundle=class org/scalatest/AsyncSuperEngine$Bundle of class org/scalatest/AsyncSuperEngine
  public #36= #35 of #32;                 // TestLeaf=class org/scalatest/AsyncSuperEngine$TestLeaf of class org/scalatest/AsyncSuperEngine
  public #39= #38 of #6;                  // OneArgAsyncTest=class org/scalatest/FixtureAsyncTestSuite$OneArgAsyncTest of class org/scalatest/FixtureAsyncTestSuite
  public final #41;                       // class org/scalatest/freespec/FixtureAsyncFreeSpecLike$$anon$1
  public final #44= #43 of #2;            // FreeSpecStringWrapper=class org/scalatest/freespec/FixtureAsyncFreeSpecLike$FreeSpecStringWrapper of class org/scalatest/freespec/FixtureAsyncFreeSpecLike
  public final #47= #46 of #2;            // ResultOfTaggedAsInvocationOnString=class org/scalatest/freespec/FixtureAsyncFreeSpecLike$ResultOfTaggedAsInvocationOnString of class org/scalatest/freespec/FixtureAsyncFreeSpecLike
SourceFile: "FixtureAsyncFreeSpecLike.scala"
RuntimeVisibleAnnotations:
  0: #18(#19=[s#20])
    org.scalatest.Finders(
      value=["org.scalatest.finders.FreeSpecFinder"]
    )
  1: #21(#22=s#23)
    scala.reflect.ScalaSignature(
      bytes="\u0006\u0005\r\u0015aaB\u00181!\u0003\r\ta\u000e\u0005\u0006#\u0002!\tA\u0015\u0005\b-\u0002\u0011\r\u0011\"\u0004X\u0011\u0015\t\u0007\u0001\"\u0005c\u0011\u00151\u0007\u0001\"\u0005h\u0011\u0015Y\u0007\u0001\"\u0005m\u0011\u0015\u0001\b\u0001\"\u0005r\u0011\u0015)\b\u0001\"\u0004w\u0011\u001d\t\t\u0006\u0001C\u0003\u0003\'Bq!!\u0019\u0001\t\u001b\t\u0019\u0007C\u0004\u0002p\u0001!)!!\u001d\t\u000f\u0005}\u0004\u0001\"\u0003\u0002\u0002\"9\u00111\u0015\u0001\u0005\n\u0005\u0015\u0006bBA]\u0001\u0011%\u00111\u0018\u0005\b\u0003\u000f\u0004A\u0011BAe\r\u0019\t)\u000e\u0001\u0006\u0002X\"Q\u0011QQ\b\u0003\u0002\u0003\u0006I!a\u000b\t\u0015\u0005ewB!A!\u0002\u0013\tI\t\u0003\u0006\u0002\u0016=\u0011\t\u0011)A\u0005\u0003/Aq!a7\u0010\t\u0003\ti\u000eC\u0004\u0002h>!\t!!;\t\u000f\u0005\u001dx\u0002\"\u0001\u0002n\"9\u0011q_\b\u0005\u0002\u0005e\bb\u0002B\u0002\u001f\u0011\u0005!Q\u0001\u0005\b\u0005\u0007yA\u0011\u0001B\u0005\r\u0019\u0011i\u0001\u0001\u0006\u0003\u0010!Q!\u0011C\r\u0003\u0002\u0003\u0006I!a\u000b\t\u0015\u0005U\u0011D!A!\u0002\u0013\t9\u0002C\u0004\u0002\\f!\tAa\u0005\t\u000f\tm\u0011\u0004\"\u0001\u0003\u001e!9\u0011q]\r\u0005\u0002\t\u0015\u0002bBAt3\u0011\u0005!\u0011\u0006\u0005\b\u0003oLB\u0011\u0001B\u0017\u0011\u001d\u0011\u0019!\u0007C\u0001\u0005cAqAa\u0001\u001a\t\u0003\u0011)\u0004C\u0004\u0003:e!\tAa\u000f\t\u000f\t\u0015\u0003\u0001b\u0005\u0003H!9\u0011\u0011\u001c\u0001\u0005B\tE\u0003b\u0002B0\u0001\u0011E#\u0011\r\u0005\b\u0005o\u0002A\u0011\u000bB=\u0011\u001d\u0011)\t\u0001C!\u0005\u000fCqA!#\u0001\t\u0003\u0012Y\tC\u0005\u0003\u0012\u0002\u0011\r\u0011\"\u0005\u0003\u0014\"I!\u0011\u0015\u0001C\u0002\u0013\u0015#1\u0015\u0005\b\u0005s\u0003A\u0011\tB^\u0011%\u0011y\rAI\u0001\n\u0003\u0011\t\u000e\u0003\b\u0003h\u0002\u0001\n1!A\u0001\n\u0013\u0011IOa<\u00031\u0019K\u0007\u0010^;sK\u0006\u001b\u0018P\\2Ge\u0016,7\u000b]3d\u0019&\\WM\u0003\u00022e\u0005AaM]3fgB,7M\u0003\u00024i\u0005I1oY1mCR,7\u000f\u001e\u0006\u0002k\u0005\u0019qN]4\u0004\u0001MA\u0001\u0001\u000f C\u000b\"[e\n\u0005\u0002:y5\t!HC\u0001<\u0003\u0015\u00198-\u00197b\u0013\ti$H\u0001\u0004B]f\u0014VM\u001a\t\u0003\u007f\u0001k\u0011AM\u0005\u0003\u0003J\u0012QCR5yiV\u0014X-Q:z]\u000e$Vm\u001d;Tk&$X\r\u0005\u0002@\u0007&\u0011AI\r\u0002\u001d\r&DH/\u001e:f\u0003NLhn\u0019+fgR\u0014VmZ5tiJ\fG/[8o!\tyd)\u0003\u0002He\tI\u0011J\u001c4pe6Lgn\u001a\t\u0003\u007f%K!A\u0013\u001a\u0003\u00139{G/\u001b4zS:<\u0007CA M\u0013\ti%G\u0001\u0005BY\u0016\u0014H/\u001b8h!\tyt*\u0003\u0002Qe\tYAi\\2v[\u0016tG/\u001b8h\u0003\u0019!\u0013N\\5uIQ\t1\u000b\u0005\u0002:)&\u0011QK\u000f\u0002\u0005+:LG/\u0001\u0004f]\u001eLg.Z\u000b\u00021B\u0019q(W.\n\u0005i\u0013$AE!ts:\u001cg)\u001b=ukJ,WI\\4j]\u0016\u0004\"\u0001X/\u000e\u0003\u0001I!AX0\u0003\u0019\u0019K\u0007\u0010^;sKB\u000b\'/Y7\n\u0005\u0001\u0014$\u0001\u0004$jqR,(/Z*vSR,\u0017\u0001B5oM>,\u0012a\u0019\t\u0003\u007f\u0011L!!\u001a\u001a\u0003\u0011%sgm\u001c:nKJ\fAA\\8uKV\t\u0001\u000e\u0005\u0002@S&\u0011!N\r\u0002\t\u001d>$\u0018NZ5fe\u0006)\u0011\r\\3siV\tQ\u000e\u0005\u0002@]&\u0011qN\r\u0002\b\u00032,\'\u000f^3s\u0003\u0019i\u0017M]6vaV\t!\u000f\u0005\u0002@g&\u0011AO\r\u0002\u000b\t>\u001cW/\\3oi\u0016\u0014\u0018!\u0006:fO&\u001cH/\u001a:Bgft7\rV3ti&k\u0007\u000f\u001c\u000b\u0006o\u0006\u001d\u0012\u0011\t\u000b\u0005\'b\f\u0019\u0002C\u0003z\u000f\u0001\u0007!0A\u0004uKN$h)\u001e8\u0011\teZ8,`\u0005\u0003yj\u0012\u0011BR;oGRLwN\\\u0019\u0011\u000by\f\u0019!a\u0002\u000e\u0003}T1!!\u0001;\u0003)\u0019wN\\2veJ,g\u000e^\u0005\u0004\u0003\u000by(A\u0002$viV\u0014X\r\u0005\u0003\u0002\n\u0005=QBAA\u0006\u0015\r\tiAM\u0001\u000bG>l\u0007/\u0019;jE2,\u0017\u0002BA\t\u0003\u0017\u0011\u0011\"Q:tKJ$\u0018n\u001c8\t\u000f\u0005Uq\u00011\u0001\u0002\u0018\u0005\u0019\u0001o\\:\u0011\t\u0005e\u00111E\u0007\u0003\u00037QA!!\b\u0002 \u000511o\\;sG\u0016T1!!\t5\u0003%\u00198-\u00197bGRL7-\u0003\u0003\u0002&\u0005m!\u0001\u0003)pg&$\u0018n\u001c8\t\u000f\u0005%r\u00011\u0001\u0002,\u0005AA/Z:u)\u0016DH\u000f\u0005\u0003\u0002.\u0005mb\u0002BA\u0018\u0003o\u00012!!\r;\u001b\t\t\u0019DC\u0002\u00026Y\na\u0001\u0010:p_Rt\u0014bAA\u001du\u00051\u0001K]3eK\u001aLA!!\u0010\u0002@\t11\u000b\u001e:j]\u001eT1!!\u000f;\u0011\u001d\t\u0019e\u0002a\u0001\u0003\u000b\n\u0001\u0002^3tiR\u000bwm\u001d\t\u0006s\u0005\u001d\u00131J\u0005\u0004\u0003\u0013R$A\u0003\u001fsKB,\u0017\r^3e}A\u0019q(!\u0014\n\u0007\u0005=#GA\u0002UC\u001e\f\u0011C]3hSN$XM]!ts:\u001cG+Z:u)\u0019\t)&!\u0018\u0002`Q!\u0011qKA.)\r\u0019\u0016\u0011\f\u0005\b\u0003+A\u00019AA\f\u0011\u0015I\b\u00021\u0001{\u0011\u001d\tI\u0003\u0003a\u0001\u0003WAq!a\u0011\t\u0001\u0004\t)%\u0001\u000fsK\u001eL7\u000f^3s\u0013\u001etwN]3e\u0003NLhn\u0019+fgRLU\u000e\u001d7\u0015\r\u0005\u0015\u00141NA7)\u0015\u0019\u0016qMA5\u0011\u0015I\u0018\u00021\u0001{\u0011\u001d\t)\"\u0003a\u0001\u0003/Aq!!\u000b\n\u0001\u0004\tY\u0003C\u0004\u0002D%\u0001\r!!\u0012\u00021I,w-[:uKJLuM\\8sK\u0012\f5/\u001f8d)\u0016\u001cH\u000f\u0006\u0004\u0002t\u0005m\u0014Q\u0010\u000b\u0005\u0003k\nI\bF\u0002T\u0003oBq!!\u0006\u000b\u0001\b\t9\u0002C\u0003z\u0015\u0001\u0007!\u0010C\u0004\u0002*)\u0001\r!a\u000b\t\u000f\u0005\r#\u00021\u0001\u0002F\u00051\"/Z4jgR,\'/Q:z]\u000e$Vm\u001d;U_J+h\u000eF\u0006T\u0003\u0007\u000b9)a\'\u0002 \u0006\u0005\u0006bBAC\u0017\u0001\u0007\u00111F\u0001\tgB,7\rV3yi\"9\u00111I\u0006A\u0002\u0005%\u0005CBAF\u0003+\u000bYE\u0004\u0003\u0002\u000e\u0006Ee\u0002BA\u0019\u0003\u001fK\u0011aO\u0005\u0004\u0003\'S\u0014a\u00029bG.\fw-Z\u0005\u0005\u0003/\u000bIJ\u0001\u0003MSN$(bAAJu!9\u0011QT\u0006A\u0002\u0005-\u0012AC7fi\"|GMT1nK\")\u0011p\u0003a\u0001u\"9\u0011QC\u0006A\u0002\u0005]\u0011\u0001\u0007:fO&\u001cH/\u001a:QK:$\u0017N\\4UKN$Hk\u001c*v]RY1+a*\u0002*\u0006-\u0016QVA\\\u0011\u001d\t)\t\u0004a\u0001\u0003WAq!a\u0011\r\u0001\u0004\tI\tC\u0004\u0002\u001e2\u0001\r!a\u000b\t\red\u0001\u0019AAX!\u0015I4pWAY!\ry\u00141W\u0005\u0004\u0003k\u0013$\u0001\u0005)f]\u0012LgnZ*uCR,W.\u001a8u\u0011\u001d\t)\u0002\u0004a\u0001\u0003/\t\u0011D]3hSN$XM]!ts:\u001cG+Z:u)>LuM\\8sKRY1+!0\u0002@\u0006\u0005\u00171YAc\u0011\u001d\t))\u0004a\u0001\u0003WAq!a\u0011\u000e\u0001\u0004\tI\tC\u0004\u0002\u001e6\u0001\r!a\u000b\t\u000bel\u0001\u0019\u0001>\t\u000f\u0005UQ\u00021\u0001\u0002\u0018\u0005Y\"/Z4jgR,\'\u000fU3oI&tw\rV3tiR{\u0017j\u001a8pe\u0016$2bUAf\u0003\u001b\fy-!5\u0002T\"9\u0011Q\u0011\bA\u0002\u0005-\u0002bBA\"\u001d\u0001\u0007\u0011\u0011\u0012\u0005\b\u0003;s\u0001\u0019AA\u0016\u0011\u0019Ih\u00021\u0001\u00020\"9\u0011Q\u0003\bA\u0002\u0005]!A\t*fgVdGo\u00144UC\u001e<W\rZ!t\u0013:4xnY1uS>twJ\\*ue&twm\u0005\u0002\u0010q\u0005!A/Y4t\u0003\u0019a\u0014N\\5u}QA\u0011q\\Aq\u0003G\f)\u000f\u0005\u0002]\u001f!9\u0011QQ\nA\u0002\u0005-\u0002bBAm\'\u0001\u0007\u0011\u0011\u0012\u0005\b\u0003+\u0019\u0002\u0019AA\f\u0003\tIg\u000eF\u0002T\u0003WDQ!\u001f\u000bA\u0002i$2aUAx\u0011\u0019IX\u00031\u0001\u0002rB!\u0011(a=~\u0013\r\t)P\u000f\u0002\n\rVt7\r^5p]B\n!![:\u0015\u0007M\u000bY\u0010C\u0004z-\u0011\u0005\r!!@\u0011\u000be\ny0!-\n\u0007\t\u0005!H\u0001\u0005=Eft\u0017-\\3?\u0003\u0019IwM\\8sKR\u00191Ka\u0002\t\u000be<\u0002\u0019\u0001>\u0015\u0007M\u0013Y\u0001\u0003\u0004z1\u0001\u0007\u0011\u0011\u001f\u0002\u0016\rJ,Wm\u00159fGN#(/\u001b8h/J\f\u0007\u000f]3s\'\tI\u0002(\u0001\u0004tiJLgn\u001a\u000b\u0007\u0005+\u00119B!\u0007\u0011\u0005qK\u0002b\u0002B\t9\u0001\u0007\u00111\u0006\u0005\b\u0003+a\u0002\u0019AA\f\u0003\u0019!S.\u001b8vgR\u00191Ka\b\t\u0011\t\u0005R\u0004\"a\u0001\u0005G\t1AZ;o!\u0011I\u0014q`*\u0015\u0007M\u00139\u0003C\u0003z=\u0001\u0007!\u0010F\u0002T\u0005WAa!_\u0010A\u0002\u0005EHcA*\u00030!9\u0011\u0010\tCA\u0002\u0005uHcA*\u00034!)\u00110\ta\u0001uR\u00191Ka\u000e\t\re\u0014\u0003\u0019AAy\u0003!!\u0018mZ4fI\u0006\u001bHCBAp\u0005{\u0011\t\u0005C\u0004\u0003@\r\u0002\r!a\u0013\u0002\u0019\u0019L\'o\u001d;UKN$H+Y4\t\u000f\t\r3\u00051\u0001\u0002F\u0005iq\u000e\u001e5feR+7\u000f\u001e+bON\fadY8om\u0016\u0014H\u000fV8Ge\u0016,7\u000b]3d\'R\u0014\u0018N\\4Xe\u0006\u0004\b/\u001a:\u0015\t\t%#Q\n\u000b\u0005\u0005+\u0011Y\u0005C\u0004\u0002\u0016\u0011\u0002\u001d!a\u0006\t\u000f\t=C\u00051\u0001\u0002,\u0005\t1/\u0006\u0002\u0003TAA\u0011Q\u0006B+\u0003W\u0011I&\u0003\u0003\u0003X\u0005}\"aA\'baB1\u0011Q\u0006B.\u0003WIAA!\u0018\u0002@\t\u00191+\u001a;\u0002\u000fI,h\u000eV3tiR1!1\rB5\u0005[\u00022a\u0010B3\u0013\r\u00119G\r\u0002\u0007\'R\fG/^:\t\u000f\t-d\u00051\u0001\u0002,\u0005AA/Z:u\u001d\u0006lW\rC\u0004\u0003p\u0019\u0002\rA!\u001d\u0002\t\u0005\u0014xm\u001d\t\u0004\u007f\tM\u0014b\u0001B;e\t!\u0011I]4t\u0003!\u0011XO\u001c+fgR\u001cHC\u0002B2\u0005w\u0012\u0019\tC\u0004\u0003l\u001d\u0002\rA! \u0011\u000be\u0012y(a\u000b\n\u0007\t\u0005%H\u0001\u0004PaRLwN\u001c\u0005\b\u0005_:\u0003\u0019\u0001B9\u0003%!Xm\u001d;OC6,7/\u0006\u0002\u0003Z\u0005\u0019!/\u001e8\u0015\r\t\r$Q\u0012BH\u0011\u001d\u0011Y\'\u000ba\u0001\u0005{BqAa\u001c*\u0001\u0004\u0011\t(\u0001\u0004cK\"\fg/Z\u000b\u0003\u0005+\u0003BAa&\u0003\u001e6\u0011!\u0011\u0014\u0006\u0004\u00057\u0013\u0014!\u0002<fe\n\u001c\u0018\u0002\u0002BP\u00053\u0013!BQ3iCZ,wk\u001c:e\u0003%\u0019H/\u001f7f\u001d\u0006lW-\u0006\u0002\u0002,!Z1Fa*\u0003.\n=&1\u0017B[!\rI$\u0011V\u0005\u0004\u0005WS$A\u00033faJ,7-\u0019;fI\u00069Q.Z:tC\u001e,\u0017E\u0001BY\u0003q$\u0006.\u001a\u0011tifdWMT1nK\u0002b\u0017NZ3ds\u000edW\rI7fi\"|G\r\t5bg\u0002\u0012W-\u001a8!I\u0016\u0004(/Z2bi\u0016$\u0007%\u00198eA]LG\u000e\u001c\u0011cK\u0002\u0012X-\\8wK\u0012\u0004\u0013N\u001c\u0011bA\u0019,H/\u001e:fAY,\'o]5p]\u0002zg\rI*dC2\fG+Z:uA]LG\u000f\u001b\u0011o_\u0002\u0012X\r\u001d7bG\u0016lWM\u001c;/\u0003\u0015\u0019\u0018N\\2fC\t\u00119,A\u00034]Er\u0003\'A\u0006uKN$H)\u0019;b\r>\u0014HC\u0002B_\u0005\u0007\u0014)\rE\u0002@\u0005\u007fK1A!13\u0005!!Vm\u001d;ECR\f\u0007b\u0002B6Y\u0001\u0007\u00111\u0006\u0005\n\u0005\u000fd\u0003\u0013!a\u0001\u0005\u0013\fA\u0002\u001e5f\u0007>tg-[4NCB\u00042a\u0010Bf\u0013\r\u0011iM\r\u0002\n\u0007>tg-[4NCB\fQ\u0003^3ti\u0012\u000bG/\u0019$pe\u0012\"WMZ1vYR$#\'\u0006\u0002\u0003T*\"!\u0011\u001aBkW\t\u00119\u000e\u0005\u0003\u0003Z\n\rXB\u0001Bn\u0015\u0011\u0011iNa8\u0002\u0013Ut7\r[3dW\u0016$\'b\u0001Bqu\u0005Q\u0011M\u001c8pi\u0006$\u0018n\u001c8\n\t\t\u0015(1\u001c\u0002\u0012k:\u001c\u0007.Z2lK\u00124\u0016M]5b]\u000e,\u0017!C:va\u0016\u0014HE];o)\u0019\u0011\u0019Ga;\u0003n\"9!1\u000e\u0018A\u0002\tu\u0004b\u0002B8]\u0001\u0007!\u0011O\u0005\u0005\u0005\u0013\u0013\t0C\u0002\u0003tJ\u0012QaU;ji\u0016Ds\u0001\u0001B|\u0005{\u0014y\u0010E\u0002@\u0005sL1Aa?3\u0005\u001d1\u0015N\u001c3feN\fQA^1mk\u0016d#a!\u0001\"\u0005\r\r\u0011\u0001J8sO:\u001a8-\u00197bi\u0016\u001cHO\f4j]\u0012,\'o\u001d\u0018Ge\u0016,7\u000b]3d\r&tG-\u001a:"
    )
BootstrapMethods:
  0: #147 REF_invokeStatic java/lang/invoke/LambdaMetafactory.altMetafactory:(Ljava/lang/invoke/MethodHandles$Lookup;Ljava/lang/String;Ljava/lang/invoke/MethodType;[Ljava/lang/Object;)Ljava/lang/invoke/CallSite;
    Method arguments:
      #132 ()Ljava/lang/Object;
      #137 REF_invokeStatic org/scalatest/freespec/FixtureAsyncFreeSpecLike.$anonfun$registerAsyncTestImpl$1:()Ljava/lang/String;
      #138 ()Ljava/lang/String;
      #139 5
      #140 1
      #138 ()Ljava/lang/String;
  1: #147 REF_invokeStatic java/lang/invoke/LambdaMetafactory.altMetafactory:(Ljava/lang/invoke/MethodHandles$Lookup;Ljava/lang/String;Ljava/lang/invoke/MethodType;[Ljava/lang/Object;)Ljava/lang/invoke/CallSite;
    Method arguments:
      #132 ()Ljava/lang/Object;
      #176 REF_invokeStatic org/scalatest/freespec/FixtureAsyncFreeSpecLike.$anonfun$registerIgnoredAsyncTestImpl$1:()Ljava/lang/String;
      #138 ()Ljava/lang/String;
      #139 5
      #140 1
      #138 ()Ljava/lang/String;
  2: #147 REF_invokeStatic java/lang/invoke/LambdaMetafactory.altMetafactory:(Ljava/lang/invoke/MethodHandles$Lookup;Ljava/lang/String;Ljava/lang/invoke/MethodType;[Ljava/lang/Object;)Ljava/lang/invoke/CallSite;
    Method arguments:
      #132 ()Ljava/lang/Object;
      #200 REF_invokeStatic org/scalatest/freespec/FixtureAsyncFreeSpecLike.$anonfun$registerAsyncTestToRun$1:()Ljava/lang/String;
      #138 ()Ljava/lang/String;
      #139 5
      #140 1
      #138 ()Ljava/lang/String;
  3: #147 REF_invokeStatic java/lang/invoke/LambdaMetafactory.altMetafactory:(Ljava/lang/invoke/MethodHandles$Lookup;Ljava/lang/String;Ljava/lang/invoke/MethodType;[Ljava/lang/Object;)Ljava/lang/invoke/CallSite;
    Method arguments:
      #132 ()Ljava/lang/Object;
      #220 REF_invokeStatic org/scalatest/freespec/FixtureAsyncFreeSpecLike.$anonfun$registerPendingTestToRun$1:()Ljava/lang/String;
      #138 ()Ljava/lang/String;
      #139 5
      #140 1
      #138 ()Ljava/lang/String;
  4: #147 REF_invokeStatic java/lang/invoke/LambdaMetafactory.altMetafactory:(Ljava/lang/invoke/MethodHandles$Lookup;Ljava/lang/String;Ljava/lang/invoke/MethodType;[Ljava/lang/Object;)Ljava/lang/invoke/CallSite;
    Method arguments:
      #132 ()Ljava/lang/Object;
      #229 REF_invokeStatic org/scalatest/freespec/FixtureAsyncFreeSpecLike.$anonfun$registerAsyncTestToIgnore$1:()Ljava/lang/String;
      #138 ()Ljava/lang/String;
      #139 5
      #140 1
      #138 ()Ljava/lang/String;
  5: #147 REF_invokeStatic java/lang/invoke/LambdaMetafactory.altMetafactory:(Ljava/lang/invoke/MethodHandles$Lookup;Ljava/lang/String;Ljava/lang/invoke/MethodType;[Ljava/lang/Object;)Ljava/lang/invoke/CallSite;
    Method arguments:
      #132 ()Ljava/lang/Object;
      #235 REF_invokeStatic org/scalatest/freespec/FixtureAsyncFreeSpecLike.$anonfun$registerPendingTestToIgnore$1:()Ljava/lang/String;
      #138 ()Ljava/lang/String;
      #139 5
      #140 1
      #138 ()Ljava/lang/String;
  6: #147 REF_invokeStatic java/lang/invoke/LambdaMetafactory.altMetafactory:(Ljava/lang/invoke/MethodHandles$Lookup;Ljava/lang/String;Ljava/lang/invoke/MethodType;[Ljava/lang/Object;)Ljava/lang/invoke/CallSite;
    Method arguments:
      #281 (Ljava/lang/Object;Ljava/lang/Object;)Ljava/lang/Object;
      #286 REF_invokeStatic org/scalatest/freespec/FixtureAsyncFreeSpecLike.$anonfun$runTest$1:(Lorg/scalatest/freespec/FixtureAsyncFreeSpecLike;Lorg/scalatest/Args;Ljava/lang/String;Lorg/scalatest/AsyncSuperEngine$TestLeaf;Lscala/Function1;)Lorg/scalatest/AsyncOutcome;
      #288 (Lorg/scalatest/AsyncSuperEngine$TestLeaf;Lscala/Function1;)Lorg/scalatest/AsyncOutcome;
      #139 5
      #140 1
      #288 (Lorg/scalatest/AsyncSuperEngine$TestLeaf;Lscala/Function1;)Lorg/scalatest/AsyncOutcome;
  7: #147 REF_invokeStatic java/lang/invoke/LambdaMetafactory.altMetafactory:(Ljava/lang/invoke/MethodHandles$Lookup;Ljava/lang/String;Ljava/lang/invoke/MethodType;[Ljava/lang/Object;)Ljava/lang/invoke/CallSite;
    Method arguments:
      #281 (Ljava/lang/Object;Ljava/lang/Object;)Ljava/lang/Object;
      #306 REF_invokeStatic org/scalatest/freespec/FixtureAsyncFreeSpecLike.$anonfun$runTests$1:(Lorg/scalatest/freespec/FixtureAsyncFreeSpecLike;Ljava/lang/String;Lorg/scalatest/Args;)Lorg/scalatest/Status;
      #307 (Ljava/lang/String;Lorg/scalatest/Args;)Lorg/scalatest/Status;
      #139 5
      #140 1
      #307 (Ljava/lang/String;Lorg/scalatest/Args;)Lorg/scalatest/Status;
  8: #147 REF_invokeStatic java/lang/invoke/LambdaMetafactory.altMetafactory:(Ljava/lang/invoke/MethodHandles$Lookup;Ljava/lang/String;Ljava/lang/invoke/MethodType;[Ljava/lang/Object;)Ljava/lang/invoke/CallSite;
    Method arguments:
      #281 (Ljava/lang/Object;Ljava/lang/Object;)Ljava/lang/Object;
      #341 REF_invokeStatic org/scalatest/freespec/FixtureAsyncFreeSpecLike.$anonfun$run$1:(Lorg/scalatest/freespec/FixtureAsyncFreeSpecLike;Lscala/Option;Lorg/scalatest/Args;)Lorg/scalatest/Status;
      #342 (Lscala/Option;Lorg/scalatest/Args;)Lorg/scalatest/Status;
      #139 5
      #140 1
      #342 (Lscala/Option;Lorg/scalatest/Args;)Lorg/scalatest/Status;
  9: #147 REF_invokeStatic java/lang/invoke/LambdaMetafactory.altMetafactory:(Ljava/lang/invoke/MethodHandles$Lookup;Ljava/lang/String;Ljava/lang/invoke/MethodType;[Ljava/lang/Object;)Ljava/lang/invoke/CallSite;
    Method arguments:
      #132 ()Ljava/lang/Object;
      #435 REF_invokeStatic org/scalatest/freespec/FixtureAsyncFreeSpecLike.$anonfun$engine$1:()Ljava/lang/String;
      #138 ()Ljava/lang/String;
      #139 5
      #140 1
      #138 ()Ljava/lang/String;
  10: #463 REF_invokeStatic scala/runtime/LambdaDeserialize.bootstrap:(Ljava/lang/invoke/MethodHandles$Lookup;Ljava/lang/String;Ljava/lang/invoke/MethodType;[Ljava/lang/invoke/MethodHandle;)Ljava/lang/invoke/CallSite;
    Method arguments:
      #435 REF_invokeStatic org/scalatest/freespec/FixtureAsyncFreeSpecLike.$anonfun$engine$1:()Ljava/lang/String;
      #137 REF_invokeStatic org/scalatest/freespec/FixtureAsyncFreeSpecLike.$anonfun$registerAsyncTestImpl$1:()Ljava/lang/String;
      #229 REF_invokeStatic org/scalatest/freespec/FixtureAsyncFreeSpecLike.$anonfun$registerAsyncTestToIgnore$1:()Ljava/lang/String;
      #200 REF_invokeStatic org/scalatest/freespec/FixtureAsyncFreeSpecLike.$anonfun$registerAsyncTestToRun$1:()Ljava/lang/String;
      #176 REF_invokeStatic org/scalatest/freespec/FixtureAsyncFreeSpecLike.$anonfun$registerIgnoredAsyncTestImpl$1:()Ljava/lang/String;
      #235 REF_invokeStatic org/scalatest/freespec/FixtureAsyncFreeSpecLike.$anonfun$registerPendingTestToIgnore$1:()Ljava/lang/String;
      #220 REF_invokeStatic org/scalatest/freespec/FixtureAsyncFreeSpecLike.$anonfun$registerPendingTestToRun$1:()Ljava/lang/String;
      #341 REF_invokeStatic org/scalatest/freespec/FixtureAsyncFreeSpecLike.$anonfun$run$1:(Lorg/scalatest/freespec/FixtureAsyncFreeSpecLike;Lscala/Option;Lorg/scalatest/Args;)Lorg/scalatest/Status;
      #286 REF_invokeStatic org/scalatest/freespec/FixtureAsyncFreeSpecLike.$anonfun$runTest$1:(Lorg/scalatest/freespec/FixtureAsyncFreeSpecLike;Lorg/scalatest/Args;Ljava/lang/String;Lorg/scalatest/AsyncSuperEngine$TestLeaf;Lscala/Function1;)Lorg/scalatest/AsyncOutcome;
      #306 REF_invokeStatic org/scalatest/freespec/FixtureAsyncFreeSpecLike.$anonfun$runTests$1:(Lorg/scalatest/freespec/FixtureAsyncFreeSpecLike;Ljava/lang/String;Lorg/scalatest/Args;)Lorg/scalatest/Status;
  ScalaInlineInfo: length = 0x11C (unknown attribute)
   01 00 00 38 01 79 00 86 01 00 85 00 86 01 00 E2
   00 86 01 00 C5 00 86 01 00 AD 00 86 01 00 E8 00
   86 01 00 D9 00 86 01 01 52 01 29 01 01 1A 01 1B
   01 01 2F 01 0E 01 01 AF 01 B0 01 00 65 00 66 00
   00 63 00 64 01 01 5C 01 5D 00 00 F0 00 F1 00 00
   ED 00 EE 01 00 42 00 43 00 00 3F 00 40 01 01 8B
   01 8C 01 00 70 00 71 00 00 6E 00 6F 01 00 5A 00
   5B 00 00 58 00 59 01 00 3C 00 3D 00 00 DF 00 C0
   01 00 DE 00 BC 01 00 BF 00 C0 01 00 BB 00 BC 01
   00 CB 00 C0 01 00 CA 00 BC 01 00 38 00 39 01 00
   34 00 35 00 00 30 00 31 00 00 36 00 37 00 00 9E
   00 7A 01 00 A6 00 A7 01 00 79 00 7A 01 00 B2 00
   7A 01 00 B6 00 A7 01 00 AC 00 7A 01 00 E7 00 C0
   01 01 4F 00 39 00 01 4E 01 29 01 01 0F 01 10 00
   01 0D 01 0E 01 01 2A 00 39 00 01 28 01 29 01 01
   5E 00 86 00 00 F9 00 FA 00 00 F7 00 F8 01 01 62
   01 63 00 01 5F 01 60 01 01 6D 01 6E 00 01 6B 01
   6C 01 01 3D 01 3E 00 01 3B 01 3C 01
  ScalaSig: length = 0x3 (unknown attribute)
   05 02 00
