Classfile /Users/mw/Projects/slang-braindump/.jar/jar8/assemble/slang-braindump/assemble/content/org/scalatest/freespec/PathAnyFreeSpecLike.class
  Last modified May 29, 2022; size 17554 bytes
  SHA-256 checksum b3a7bd5c3ec2b47851b718435999329244e349a87dbb960686a36d5e508730b8
  Compiled from "PathAnyFreeSpecLike.scala"
public interface org.scalatest.freespec.PathAnyFreeSpecLike extends org.scalatest.Suite,org.scalatest.OneInstancePerTest,org.scalatest.Informing,org.scalatest.Notifying,org.scalatest.Alerting,org.scalatest.Documenting
  minor version: 0
  major version: 52
  flags: (0x0601) ACC_PUBLIC, ACC_INTERFACE, ACC_ABSTRACT
  this_class: #2                          // org/scalatest/freespec/PathAnyFreeSpecLike
  super_class: #4                         // java/lang/Object
  interfaces: 6, fields: 0, methods: 50, attributes: 6
Constant pool:
    #1 = Utf8               org/scalatest/freespec/PathAnyFreeSpecLike
    #2 = Class              #1            // org/scalatest/freespec/PathAnyFreeSpecLike
    #3 = Utf8               java/lang/Object
    #4 = Class              #3            // java/lang/Object
    #5 = Utf8               org/scalatest/Suite
    #6 = Class              #5            // org/scalatest/Suite
    #7 = Utf8               org/scalatest/OneInstancePerTest
    #8 = Class              #7            // org/scalatest/OneInstancePerTest
    #9 = Utf8               org/scalatest/Informing
   #10 = Class              #9            // org/scalatest/Informing
   #11 = Utf8               org/scalatest/Notifying
   #12 = Class              #11           // org/scalatest/Notifying
   #13 = Utf8               org/scalatest/Alerting
   #14 = Class              #13           // org/scalatest/Alerting
   #15 = Utf8               org/scalatest/Documenting
   #16 = Class              #15           // org/scalatest/Documenting
   #17 = Utf8               PathAnyFreeSpecLike.scala
   #18 = Utf8               Lorg/scalatest/Finders;
   #19 = Utf8               value
   #20 = Utf8               org.scalatest.finders.FreeSpecFinder
   #21 = Utf8               Lscala/reflect/ScalaSignature;
   #22 = Utf8               bytes
   #23 = Utf8               \u0006\u0005\t]eaB\u0015+!\u0003\r\t!\r\u0005\u0006\u0017\u0002!\t\u0001\u0014\u0005\b!\u0002\u0011\r\u0011\"\u0004R\u0011\u0015)\u0006\u0001\"\u0011W\u0011\u0015I\u0006\u0001\"\u0005[\u0011\u0015q\u0006\u0001\"\u0005`\u0011\u0015\u0019\u0007\u0001\"\u0005e\u0011\u0015A\u0007\u0001\"\u0005j\u0011\u0015i\u0007\u0001\"\u0003o\u0011\u001d\t9\u0004\u0001C\u0005\u0003s1a!!\u0012\u0001\u0015\u0005\u001d\u0003\u0002\u00039\u000b\u0005\u0003\u0005\u000b\u0011B9\t\u0013\u0005%#B!A!\u0002\u0013q\bBCA\u0013\u0015\t\u0005\t\u0015!\u0003\u0002(!9\u00111\n\u0006\u0005\u0002\u00055\u0003bBA-\u0015\u0011\u0005\u00111\f\u0005\b\u0003KRA\u0011AA4\u0011\u001d\t\u0019H\u0003C\u0001\u0003k2a!!\u001f\u0001\u0015\u0005m\u0004\"CA?%\t\u0005\t\u0015!\u0003r\u0011)\t)C\u0005B\u0001B\u0003%\u0011q\u0005\u0005\b\u0003\u0017\u0012B\u0011AA@\u0011\u001d\t9I\u0005C\u0001\u0003\u0013Cq!!\u0017\u0013\t\u0003\ty\tC\u0004\u0002tI!\t!!&\t\u000f\u0005\u0015$\u0003\"\u0001\u0002\u001a\"9\u0011Q\u0014\n\u0005\u0002\u0005}\u0005bBAX\u0001\u0011M\u0011\u0011\u0017\u0005\n\u0003w\u0003!\u0019!C\t\u0003{Cq!a3\u0001\t\u000b\ni\rC\u0004\u0002V\u0002!)%a6\t\u000f\u0005%\b\u0001\"\u0016\u0002l\"9\u0011\u0011\n\u0001\u0005F\t\u0005\u0001b\u0002B\u0005\u0001\u0011\u0015#1\u0002\u0005\b\u0005/\u0001AQ\u000bB\r\u0011\u001d\u0011y\u0002\u0001C+\u0005CAqA!\n\u0001\t\u000b\u00129\u0003C\u0005\u0003:\u0001\u0011\r\u0011\"\u0012\u0003<!9!\u0011\u000b\u0001\u0005B\tM\u0003\"\u0003B4\u0001E\u0005I\u0011\u0001B5\u00119\u0011y\b\u0001I\u0001\u0004\u0003\u0005I\u0011\u0002BA\u0005\u000b\u00131\u0003U1uQ\u0006s\u0017P\u0012:fKN\u0003Xm\u0019\'jW\u0016T!a\u000b\u0017\u0002\u0011\u0019\u0014X-Z:qK\u000eT!!\f\u0018\u0002\u0013M\u001c\u0017\r\\1uKN$(\"A\u0018\u0002\u0007=\u0014xm\u0001\u0001\u0014\u0011\u0001\u0011\u0004\bP C\u000b\"\u0003\"a\r\u001c\u000e\u0003QR\u0011!N\u0001\u0006g\u000e\fG.Y\u0005\u0003oQ\u0012a!\u00118z%\u00164\u0007CA\u001d;\u001b\u0005a\u0013BA\u001e-\u0005\u0015\u0019V/\u001b;f!\tIT(\u0003\u0002?Y\t\u0011rJ\\3J]N$\u0018M\\2f!\u0016\u0014H+Z:u!\tI\u0004)\u0003\u0002BY\tI\u0011J\u001c4pe6Lgn\u001a\t\u0003s\rK!\u0001\u0012\u0017\u0003\u00139{G/\u001b4zS:<\u0007CA\u001dG\u0013\t9EF\u0001\u0005BY\u0016\u0014H/\u001b8h!\tI\u0014*\u0003\u0002KY\tYAi\\2v[\u0016tG/\u001b8h\u0003\u0019!\u0013N\\5uIQ\tQ\n\u0005\u00024\u001d&\u0011q\n\u000e\u0002\u0005+:LG/\u0001\u0004f]\u001eLg.Z\u000b\u0002%B\u0011\u0011hU\u0005\u0003)2\u0012!\u0002U1uQ\u0016sw-\u001b8f\u0003-qWm^%ogR\fgnY3\u0016\u0003]\u0003\"\u0001\u0017\u0001\u000e\u0003)\nA!\u001b8g_V\t1\f\u0005\u0002:9&\u0011Q\f\f\u0002\t\u0013:4wN]7fe\u0006!an\u001c;f+\u0005\u0001\u0007CA\u001db\u0013\t\u0011GF\u0001\u0005O_RLg-[3s\u0003\u0015\tG.\u001a:u+\u0005)\u0007CA\u001dg\u0013\t9GFA\u0004BY\u0016\u0014H/\u001a:\u0002\r5\f\'o[;q+\u0005Q\u0007CA\u001dl\u0013\taGF\u0001\u0006E_\u000e,X.\u001a8uKJ\f\u0011C]3hSN$XM\u001d+fgR$vNU;o)%iu\u000e`A\u000b\u00033\t\u0019\u0003C\u0003q\u0011\u0001\u0007\u0011/\u0001\u0005ta\u0016\u001cG+\u001a=u!\t\u0011\u0018P\u0004\u0002toB\u0011A\u000fN\u0007\u0002k*\u0011a\u000fM\u0001\u0007yI|w\u000e\u001e \n\u0005a$\u0014A\u0002)sK\u0012,g-\u0003\u0002{w\n11\u000b\u001e:j]\u001eT!\u0001\u001f\u001b\t\u000buD\u0001\u0019\u0001@\u0002\u0011Q,7\u000f\u001e+bON\u0004Ra`A\u0005\u0003\u001fqA!!\u0001\u0002\u00069\u0019A/a\u0001\n\u0003UJ1!a\u00025\u0003\u001d\u0001\u0018mY6bO\u0016LA!a\u0003\u0002\u000e\t!A*[:u\u0015\r\t9\u0001\u000e\t\u0004s\u0005E\u0011bAA\nY\t\u0019A+Y4\t\r\u0005]\u0001\u00021\u0001r\u0003)iW\r\u001e5pI:\u000bW.\u001a\u0005\b\u00037A\u0001\u0019AA\u000f\u0003\u001d!Xm\u001d;Gk:\u0004BaMA\u0010\u001b&\u0019\u0011\u0011\u0005\u001b\u0003\u0013\u0019+hn\u0019;j_:\u0004\u0004bBA\u0013\u0011\u0001\u0007\u0011qE\u0001\u0004a>\u001c\b\u0003BA\u0015\u0003gi!!a\u000b\u000b\t\u00055\u0012qF\u0001\u0007g>,(oY3\u000b\u0007\u0005Eb&A\u0005tG\u0006d\u0017m\u0019;jG&!\u0011QGA\u0016\u0005!\u0001vn]5uS>t\u0017\u0001\u0006:fO&\u001cH/\u001a:UKN$Hk\\%h]>\u0014X\rF\u0006N\u0003w\ti$a\u0010\u0002B\u0005\r\u0003\"\u00029\n\u0001\u0004\t\b\"B?\n\u0001\u0004q\bBBA\f\u0013\u0001\u0007\u0011\u000fC\u0004\u0002\u001c%\u0001\r!!\b\t\u000f\u0005\u0015\u0012\u00021\u0001\u0002(\t\u0011#+Z:vYR|e\rV1hO\u0016$\u0017i]%om>\u001c\u0017\r^5p]>s7\u000b\u001e:j]\u001e\u001c\"A\u0003\u001a\u0002\tQ\fwm]\u0001\u0007y%t\u0017\u000e\u001e \u0015\u0011\u0005=\u00131KA+\u0003/\u00022!!\u0015\u000b\u001b\u0005\u0001\u0001\"\u00029\u000f\u0001\u0004\t\bBBA%\u001d\u0001\u0007a\u0010C\u0004\u0002&9\u0001\r!a\n\u0002\u0005%tGcA\'\u0002^!A\u00111D\b\u0005\u0002\u0004\ty\u0006\u0005\u00034\u0003Cj\u0015bAA2i\tAAHY=oC6,g(\u0001\u0002jgR\u0019Q*!\u001b\t\u0011\u0005m\u0001\u0003\"a\u0001\u0003W\u0002RaMA1\u0003[\u00022!OA8\u0013\r\t\t\b\f\u0002\u0011!\u0016tG-\u001b8h\'R\fG/Z7f]R\fa![4o_J,GcA\'\u0002x!A\u00111D\t\u0005\u0002\u0004\tyFA\u000bGe\u0016,7\u000b]3d\'R\u0014\u0018N\\4Xe\u0006\u0004\b/\u001a:\u0014\u0005I\u0011\u0014AB:ue&tw\r\u0006\u0004\u0002\u0002\u0006\r\u0015Q\u0011\t\u0004\u0003#\u0012\u0002BBA?+\u0001\u0007\u0011\u000fC\u0004\u0002&U\u0001\r!a\n\u0002\r\u0011j\u0017N\\;t)\ri\u00151\u0012\u0005\t\u0003\u001b3B\u00111\u0001\u0002`\u0005\u0019a-\u001e8\u0015\u00075\u000b\t\n\u0003\u0005\u0002\u0014^!\t\u0019AA0\u0003\u00051GcA\'\u0002\u0018\"A\u00111\u0013\r\u0005\u0002\u0004\ty\u0006F\u0002N\u00037C\u0001\"a%\u001a\t\u0003\u0007\u00111N\u0001\ti\u0006<w-\u001a3BgR1\u0011qJAQ\u0003KCq!a)\u001b\u0001\u0004\ty!\u0001\u0007gSJ\u001cH\u000fV3tiR\u000bw\rC\u0004\u0002(j\u0001\r!!+\u0002\u001b=$\b.\u001a:UKN$H+Y4t!\u0015\u0019\u00141VA\b\u0013\r\ti\u000b\u000e\u0002\u000byI,\u0007/Z1uK\u0012t\u0014AH2p]Z,\'\u000f\u001e+p\rJ,Wm\u00159fGN#(/\u001b8h/J\f\u0007\u000f]3s)\u0011\t\u0019,a.\u0015\t\u0005\u0005\u0015Q\u0017\u0005\b\u0003KY\u00029AA\u0014\u0011\u0019\tIl\u0007a\u0001c\u0006\t1/\u0001\u0004cK\"\fg/Z\u000b\u0003\u0003\u007f\u0003B!!1\u0002H6\u0011\u00111\u0019\u0006\u0004\u0003\u000bd\u0013!\u0002<fe\n\u001c\u0018\u0002BAe\u0003\u0007\u0014!BQ3iCZ,wk\u001c:e\u0003%!Xm\u001d;OC6,7/\u0006\u0002\u0002PB!!/!5r\u0013\r\t\u0019n\u001f\u0002\u0004\'\u0016$\u0018!E3ya\u0016\u001cG/\u001a3UKN$8i\\;oiR!\u0011\u0011\\Ap!\r\u0019\u00141\\\u0005\u0004\u0003;$$aA%oi\"9\u0011\u0011\u001d\u0010A\u0002\u0005\r\u0018A\u00024jYR,\'\u000fE\u0002:\u0003KL1!a:-\u0005\u00191\u0015\u000e\u001c;fe\u00069!/\u001e8UKN$HCBAw\u0003g\f9\u0010E\u0002:\u0003_L1!!=-\u0005\u0019\u0019F/\u0019;vg\"1\u0011Q_\u0010A\u0002E\f\u0001\u0002^3ti:\u000bW.\u001a\u0005\b\u0003s|\u0002\u0019AA~\u0003\u0011\t\'oZ:\u0011\u0007e\ni0C\u0002\u0002\u00002\u0012A!\u0011:hgV\u0011!1\u0001\t\u0007e\n\u0015\u0011/a4\n\u0007\t\u001d1PA\u0002NCB\f1A];o)\u0019\tiO!\u0004\u0003\u0016!9\u0011Q_\u0011A\u0002\t=\u0001\u0003B\u001a\u0003\u0012EL1Aa\u00055\u0005\u0019y\u0005\u000f^5p]\"9\u0011\u0011`\u0011A\u0002\u0005m\u0018\u0001\u0003:v]R+7\u000f^:\u0015\r\u00055(1\u0004B\u000f\u0011\u001d\t)P\ta\u0001\u0005\u001fAq!!?#\u0001\u0004\tY0A\bsk:tUm\u001d;fIN+\u0018\u000e^3t)\u0011\tiOa\t\t\u000f\u0005e8\u00051\u0001\u0002|\u0006aa.Z:uK\u0012\u001cV/\u001b;fgV\u0011!\u0011\u0006\t\u0006\u0005W\u0011)\u0004O\u0007\u0003\u0005[QAAa\f\u00032\u0005I\u0011.\\7vi\u0006\u0014G.\u001a\u0006\u0004\u0005g!\u0014AC2pY2,7\r^5p]&!!q\u0007B\u0017\u0005)Ie\u000eZ3yK\u0012\u001cV-]\u0001\ngRLH.\u001a(b[\u0016,\u0012!\u001d\u0015\fK\t}\"Q\tB$\u0005\u0017\u0012i\u0005E\u00024\u0005\u0003J1Aa\u00115\u0005)!W\r\u001d:fG\u0006$X\rZ\u0001\b[\u0016\u001c8/Y4fC\t\u0011I%\u0001?UQ\u0016\u00043\u000f^=mK:\u000bW.\u001a\u0011mS\u001a,7-_2mK\u0002jW\r\u001e5pI\u0002B\u0017m\u001d\u0011cK\u0016t\u0007\u0005Z3qe\u0016\u001c\u0017\r^3eA\u0005tG\rI<jY2\u0004#-\u001a\u0011sK6|g/\u001a3!S:\u0004\u0013\r\t4viV\u0014X\r\t<feNLwN\u001c\u0011pM\u0002\u001a6-\u00197b)\u0016\u001cH\u000fI<ji\"\u0004cn\u001c\u0011sKBd\u0017mY3nK:$h&A\u0003tS:\u001cW-\t\u0002\u0003P\u0005)1GL\u0019/a\u0005YA/Z:u\t\u0006$\u0018MR8s)\u0019\u0011)Fa\u0017\u0003^A\u0019\u0011Ha\u0016\n\u0007\teCF\u0001\u0005UKN$H)\u0019;b\u0011\u0019\t)P\na\u0001c\"I!q\f\u0014\u0011\u0002\u0003\u0007!\u0011M\u0001\ri\",7i\u001c8gS\u001el\u0015\r\u001d\t\u0004s\t\r\u0014b\u0001B3Y\tI1i\u001c8gS\u001el\u0015\r]\u0001\u0016i\u0016\u001cH\u000fR1uC\u001a{\'\u000f\n3fM\u0006,H\u000e\u001e\u00133+\t\u0011YG\u000b\u0003\u0003b\t54F\u0001B8!\u0011\u0011\tHa\u001f\u000e\u0005\tM$\u0002\u0002B;\u0005o\n\u0011\"\u001e8dQ\u0016\u001c7.\u001a3\u000b\u0007\teD\'\u0001\u0006b]:|G/\u0019;j_:LAA! \u0003t\t\tRO\\2iK\u000e\\W\r\u001a,be&\fgnY3\u0002/M,\b/\u001a:%Kb\u0004Xm\u0019;fIR+7\u000f^\"pk:$H\u0003BAm\u0005\u0007Cq!!9)\u0001\u0004\t\u0019/C\u0002\u0002VjBs\u0001\u0001BE\u0005\u001f\u0013\t\nE\u0002:\u0005\u0017K1A!$-\u0005\u001d1\u0015N\u001c3feN\fQA^1mk\u0016d#Aa%\"\u0005\tU\u0015\u0001J8sO:\u001a8-\u00197bi\u0016\u001cHO\f4j]\u0012,\'o\u001d\u0018Ge\u0016,7\u000b]3d\r&tG-\u001a:
   #24 = Utf8               java/lang/invoke/MethodHandles$Lookup
   #25 = Class              #24           // java/lang/invoke/MethodHandles$Lookup
   #26 = Utf8               java/lang/invoke/MethodHandles
   #27 = Class              #26           // java/lang/invoke/MethodHandles
   #28 = Utf8               Lookup
   #29 = Utf8               org/scalatest/SuperEngine$Bundle
   #30 = Class              #29           // org/scalatest/SuperEngine$Bundle
   #31 = Utf8               org/scalatest/SuperEngine
   #32 = Class              #31           // org/scalatest/SuperEngine
   #33 = Utf8               Bundle
   #34 = Utf8               org/scalatest/SuperEngine$TestLeaf
   #35 = Class              #34           // org/scalatest/SuperEngine$TestLeaf
   #36 = Utf8               TestLeaf
   #37 = Utf8               org/scalatest/freespec/PathAnyFreeSpecLike$FreeSpecStringWrapper
   #38 = Class              #37           // org/scalatest/freespec/PathAnyFreeSpecLike$FreeSpecStringWrapper
   #39 = Utf8               FreeSpecStringWrapper
   #40 = Utf8               org/scalatest/freespec/PathAnyFreeSpecLike$ResultOfTaggedAsInvocationOnString
   #41 = Class              #40           // org/scalatest/freespec/PathAnyFreeSpecLike$ResultOfTaggedAsInvocationOnString
   #42 = Utf8               ResultOfTaggedAsInvocationOnString
   #43 = Utf8               org$scalatest$freespec$PathAnyFreeSpecLike$_setter_$org$scalatest$freespec$PathAnyFreeSpecLike$$engine_$eq
   #44 = Utf8               (Lorg/scalatest/PathEngine;)V
   #45 = Utf8               x$1
   #46 = Utf8               org$scalatest$freespec$PathAnyFreeSpecLike$_setter_$behave_$eq
   #47 = Utf8               (Lorg/scalatest/verbs/BehaveWord;)V
   #48 = Utf8               org$scalatest$freespec$PathAnyFreeSpecLike$_setter_$styleName_$eq
   #49 = Utf8               (Ljava/lang/String;)V
   #50 = Utf8               org$scalatest$freespec$PathAnyFreeSpecLike$$super$expectedTestCount
   #51 = Utf8               (Lorg/scalatest/Filter;)I
   #52 = Utf8               filter
   #53 = Utf8               org$scalatest$freespec$PathAnyFreeSpecLike$$engine
   #54 = Utf8               ()Lorg/scalatest/PathEngine;
   #55 = Utf8               newInstance$
   #56 = Utf8               (Lorg/scalatest/freespec/PathAnyFreeSpecLike;)Lorg/scalatest/freespec/PathAnyFreeSpecLike;
   #57 = Utf8               $this
   #58 = Utf8               newInstance
   #59 = Utf8               ()Lorg/scalatest/freespec/PathAnyFreeSpecLike;
   #60 = NameAndType        #58:#59       // newInstance:()Lorg/scalatest/freespec/PathAnyFreeSpecLike;
   #61 = InterfaceMethodref #2.#60        // org/scalatest/freespec/PathAnyFreeSpecLike.newInstance:()Lorg/scalatest/freespec/PathAnyFreeSpecLike;
   #62 = Utf8               Lorg/scalatest/freespec/PathAnyFreeSpecLike;
   #63 = Utf8               getClass
   #64 = Utf8               ()Ljava/lang/Class;
   #65 = NameAndType        #63:#64       // getClass:()Ljava/lang/Class;
   #66 = Methodref          #4.#65        // java/lang/Object.getClass:()Ljava/lang/Class;
   #67 = Utf8               java/lang/Class
   #68 = Class              #67           // java/lang/Class
   #69 = Utf8               ()Ljava/lang/Object;
   #70 = NameAndType        #58:#69       // newInstance:()Ljava/lang/Object;
   #71 = Methodref          #68.#70       // java/lang/Class.newInstance:()Ljava/lang/Object;
   #72 = Utf8               this
   #73 = Utf8               info$
   #74 = Utf8               (Lorg/scalatest/freespec/PathAnyFreeSpecLike;)Lorg/scalatest/Informer;
   #75 = Utf8               info
   #76 = Utf8               ()Lorg/scalatest/Informer;
   #77 = NameAndType        #75:#76       // info:()Lorg/scalatest/Informer;
   #78 = InterfaceMethodref #2.#77        // org/scalatest/freespec/PathAnyFreeSpecLike.info:()Lorg/scalatest/Informer;
   #79 = NameAndType        #53:#54       // org$scalatest$freespec$PathAnyFreeSpecLike$$engine:()Lorg/scalatest/PathEngine;
   #80 = InterfaceMethodref #2.#79        // org/scalatest/freespec/PathAnyFreeSpecLike.org$scalatest$freespec$PathAnyFreeSpecLike$$engine:()Lorg/scalatest/PathEngine;
   #81 = Utf8               org/scalatest/PathEngine
   #82 = Class              #81           // org/scalatest/PathEngine
   #83 = Utf8               atomicInformer
   #84 = Utf8               ()Ljava/util/concurrent/atomic/AtomicReference;
   #85 = NameAndType        #83:#84       // atomicInformer:()Ljava/util/concurrent/atomic/AtomicReference;
   #86 = Methodref          #82.#85       // org/scalatest/PathEngine.atomicInformer:()Ljava/util/concurrent/atomic/AtomicReference;
   #87 = Utf8               java/util/concurrent/atomic/AtomicReference
   #88 = Class              #87           // java/util/concurrent/atomic/AtomicReference
   #89 = Utf8               get
   #90 = NameAndType        #89:#69       // get:()Ljava/lang/Object;
   #91 = Methodref          #88.#90       // java/util/concurrent/atomic/AtomicReference.get:()Ljava/lang/Object;
   #92 = Utf8               org/scalatest/Informer
   #93 = Class              #92           // org/scalatest/Informer
   #94 = Utf8               note$
   #95 = Utf8               (Lorg/scalatest/freespec/PathAnyFreeSpecLike;)Lorg/scalatest/Notifier;
   #96 = Utf8               note
   #97 = Utf8               ()Lorg/scalatest/Notifier;
   #98 = NameAndType        #96:#97       // note:()Lorg/scalatest/Notifier;
   #99 = InterfaceMethodref #2.#98        // org/scalatest/freespec/PathAnyFreeSpecLike.note:()Lorg/scalatest/Notifier;
  #100 = Utf8               atomicNotifier
  #101 = NameAndType        #100:#84      // atomicNotifier:()Ljava/util/concurrent/atomic/AtomicReference;
  #102 = Methodref          #82.#101      // org/scalatest/PathEngine.atomicNotifier:()Ljava/util/concurrent/atomic/AtomicReference;
  #103 = Utf8               org/scalatest/Notifier
  #104 = Class              #103          // org/scalatest/Notifier
  #105 = Utf8               alert$
  #106 = Utf8               (Lorg/scalatest/freespec/PathAnyFreeSpecLike;)Lorg/scalatest/Alerter;
  #107 = Utf8               alert
  #108 = Utf8               ()Lorg/scalatest/Alerter;
  #109 = NameAndType        #107:#108     // alert:()Lorg/scalatest/Alerter;
  #110 = InterfaceMethodref #2.#109       // org/scalatest/freespec/PathAnyFreeSpecLike.alert:()Lorg/scalatest/Alerter;
  #111 = Utf8               atomicAlerter
  #112 = NameAndType        #111:#84      // atomicAlerter:()Ljava/util/concurrent/atomic/AtomicReference;
  #113 = Methodref          #82.#112      // org/scalatest/PathEngine.atomicAlerter:()Ljava/util/concurrent/atomic/AtomicReference;
  #114 = Utf8               org/scalatest/Alerter
  #115 = Class              #114          // org/scalatest/Alerter
  #116 = Utf8               markup$
  #117 = Utf8               (Lorg/scalatest/freespec/PathAnyFreeSpecLike;)Lorg/scalatest/Documenter;
  #118 = Utf8               markup
  #119 = Utf8               ()Lorg/scalatest/Documenter;
  #120 = NameAndType        #118:#119     // markup:()Lorg/scalatest/Documenter;
  #121 = InterfaceMethodref #2.#120       // org/scalatest/freespec/PathAnyFreeSpecLike.markup:()Lorg/scalatest/Documenter;
  #122 = Utf8               atomicDocumenter
  #123 = NameAndType        #122:#84      // atomicDocumenter:()Ljava/util/concurrent/atomic/AtomicReference;
  #124 = Methodref          #82.#123      // org/scalatest/PathEngine.atomicDocumenter:()Ljava/util/concurrent/atomic/AtomicReference;
  #125 = Utf8               org/scalatest/Documenter
  #126 = Class              #125          // org/scalatest/Documenter
  #127 = Utf8               org$scalatest$freespec$PathAnyFreeSpecLike$$registerTestToRun$
  #128 = Utf8               (Lorg/scalatest/freespec/PathAnyFreeSpecLike;Ljava/lang/String;Lscala/collection/immutable/List;Ljava/lang/String;Lscala/Function0;Lorg/scalactic/source/Position;)V
  #129 = Utf8               specText
  #130 = Utf8               testTags
  #131 = Utf8               methodName
  #132 = Utf8               testFun
  #133 = Utf8               pos
  #134 = Utf8               org$scalatest$freespec$PathAnyFreeSpecLike$$registerTestToRun
  #135 = Utf8               (Ljava/lang/String;Lscala/collection/immutable/List;Ljava/lang/String;Lscala/Function0;Lorg/scalactic/source/Position;)V
  #136 = NameAndType        #134:#135     // org$scalatest$freespec$PathAnyFreeSpecLike$$registerTestToRun:(Ljava/lang/String;Lscala/collection/immutable/List;Ljava/lang/String;Lscala/Function0;Lorg/scalactic/source/Position;)V
  #137 = InterfaceMethodref #2.#136       // org/scalatest/freespec/PathAnyFreeSpecLike.org$scalatest$freespec$PathAnyFreeSpecLike$$registerTestToRun:(Ljava/lang/String;Lscala/collection/immutable/List;Ljava/lang/String;Lscala/Function0;Lorg/scalactic/source/Position;)V
  #138 = Utf8               Ljava/lang/String;
  #139 = Utf8               Lscala/collection/immutable/List;
  #140 = Utf8               Lscala/Function0;
  #141 = Utf8               Lorg/scalactic/source/Position;
  #142 = Utf8               (Ljava/lang/String;Lscala/collection/immutable/List<Lorg/scalatest/Tag;>;Ljava/lang/String;Lscala/Function0<Lscala/runtime/BoxedUnit;>;Lorg/scalactic/source/Position;)V
  #143 = Utf8               org/scalatest/Transformer
  #144 = Class              #143          // org/scalatest/Transformer
  #145 = Utf8               <init>
  #146 = Utf8               (Lscala/Function0;)V
  #147 = NameAndType        #145:#146     // "<init>":(Lscala/Function0;)V
  #148 = Methodref          #144.#147     // org/scalatest/Transformer."<init>":(Lscala/Function0;)V
  #149 = MethodType         #69           //  ()Ljava/lang/Object;
  #150 = Utf8               $anonfun$registerTestToRun$1
  #151 = Utf8               ()Ljava/lang/String;
  #152 = NameAndType        #150:#151     // $anonfun$registerTestToRun$1:()Ljava/lang/String;
  #153 = InterfaceMethodref #2.#152       // org/scalatest/freespec/PathAnyFreeSpecLike.$anonfun$registerTestToRun$1:()Ljava/lang/String;
  #154 = MethodHandle       6:#153        // REF_invokeStatic org/scalatest/freespec/PathAnyFreeSpecLike.$anonfun$registerTestToRun$1:()Ljava/lang/String;
  #155 = MethodType         #151          //  ()Ljava/lang/String;
  #156 = Integer            5
  #157 = Integer            1
  #158 = Utf8               java/lang/invoke/LambdaMetafactory
  #159 = Class              #158          // java/lang/invoke/LambdaMetafactory
  #160 = Utf8               altMetafactory
  #161 = Utf8               (Ljava/lang/invoke/MethodHandles$Lookup;Ljava/lang/String;Ljava/lang/invoke/MethodType;[Ljava/lang/Object;)Ljava/lang/invoke/CallSite;
  #162 = NameAndType        #160:#161     // altMetafactory:(Ljava/lang/invoke/MethodHandles$Lookup;Ljava/lang/String;Ljava/lang/invoke/MethodType;[Ljava/lang/Object;)Ljava/lang/invoke/CallSite;
  #163 = Methodref          #159.#162     // java/lang/invoke/LambdaMetafactory.altMetafactory:(Ljava/lang/invoke/MethodHandles$Lookup;Ljava/lang/String;Ljava/lang/invoke/MethodType;[Ljava/lang/Object;)Ljava/lang/invoke/CallSite;
  #164 = MethodHandle       6:#163        // REF_invokeStatic java/lang/invoke/LambdaMetafactory.altMetafactory:(Ljava/lang/invoke/MethodHandles$Lookup;Ljava/lang/String;Ljava/lang/invoke/MethodType;[Ljava/lang/Object;)Ljava/lang/invoke/CallSite;
  #165 = Utf8               apply
  #166 = Utf8               ()Lscala/Function0;
  #167 = NameAndType        #165:#166     // apply:()Lscala/Function0;
  #168 = InvokeDynamic      #0:#167       // #0:apply:()Lscala/Function0;
  #169 = Utf8               FreeSpecLike.scala
  #170 = String             #169          // FreeSpecLike.scala
  #171 = Utf8               scala/None$
  #172 = Class              #171          // scala/None$
  #173 = Utf8               MODULE$
  #174 = Utf8               Lscala/None$;
  #175 = NameAndType        #173:#174     // MODULE$:Lscala/None$;
  #176 = Fieldref           #172.#175     // scala/None$.MODULE$:Lscala/None$;
  #177 = Utf8               scala/Some
  #178 = Class              #177          // scala/Some
  #179 = Utf8               (Ljava/lang/Object;)V
  #180 = NameAndType        #145:#179     // "<init>":(Ljava/lang/Object;)V
  #181 = Methodref          #178.#180     // scala/Some."<init>":(Ljava/lang/Object;)V
  #182 = Utf8               handleTest
  #183 = Utf8               (Lorg/scalatest/Suite;Ljava/lang/String;Lscala/Function0;Lscala/Function0;Ljava/lang/String;Ljava/lang/String;IILscala/Option;Lscala/Option;Lscala/collection/immutable/Seq;)V
  #184 = NameAndType        #182:#183     // handleTest:(Lorg/scalatest/Suite;Ljava/lang/String;Lscala/Function0;Lscala/Function0;Ljava/lang/String;Ljava/lang/String;IILscala/Option;Lscala/Option;Lscala/collection/immutable/Seq;)V
  #185 = Methodref          #82.#184      // org/scalatest/PathEngine.handleTest:(Lorg/scalatest/Suite;Ljava/lang/String;Lscala/Function0;Lscala/Function0;Ljava/lang/String;Ljava/lang/String;IILscala/Option;Lscala/Option;Lscala/collection/immutable/Seq;)V
  #186 = Utf8               stackDepth
  #187 = Utf8               I
  #188 = Utf8               stackDepthAdjustment
  #189 = Utf8               org$scalatest$freespec$PathAnyFreeSpecLike$$registerTestToIgnore$
  #190 = Utf8               org$scalatest$freespec$PathAnyFreeSpecLike$$registerTestToIgnore
  #191 = NameAndType        #190:#135     // org$scalatest$freespec$PathAnyFreeSpecLike$$registerTestToIgnore:(Ljava/lang/String;Lscala/collection/immutable/List;Ljava/lang/String;Lscala/Function0;Lorg/scalactic/source/Position;)V
  #192 = InterfaceMethodref #2.#191       // org/scalatest/freespec/PathAnyFreeSpecLike.org$scalatest$freespec$PathAnyFreeSpecLike$$registerTestToIgnore:(Ljava/lang/String;Lscala/collection/immutable/List;Ljava/lang/String;Lscala/Function0;Lorg/scalactic/source/Position;)V
  #193 = Utf8               $anonfun$registerTestToIgnore$1
  #194 = NameAndType        #193:#151     // $anonfun$registerTestToIgnore$1:()Ljava/lang/String;
  #195 = InterfaceMethodref #2.#194       // org/scalatest/freespec/PathAnyFreeSpecLike.$anonfun$registerTestToIgnore$1:()Ljava/lang/String;
  #196 = MethodHandle       6:#195        // REF_invokeStatic org/scalatest/freespec/PathAnyFreeSpecLike.$anonfun$registerTestToIgnore$1:()Ljava/lang/String;
  #197 = InvokeDynamic      #1:#167       // #1:apply:()Lscala/Function0;
  #198 = Utf8               handleIgnoredTest
  #199 = Utf8               (Ljava/lang/String;Lscala/Function0;Lscala/Function0;Ljava/lang/String;Ljava/lang/String;IILscala/Option;Lscala/Option;Lscala/collection/immutable/Seq;)V
  #200 = NameAndType        #198:#199     // handleIgnoredTest:(Ljava/lang/String;Lscala/Function0;Lscala/Function0;Ljava/lang/String;Ljava/lang/String;IILscala/Option;Lscala/Option;Lscala/collection/immutable/Seq;)V
  #201 = Methodref          #82.#200      // org/scalatest/PathEngine.handleIgnoredTest:(Ljava/lang/String;Lscala/Function0;Lscala/Function0;Ljava/lang/String;Ljava/lang/String;IILscala/Option;Lscala/Option;Lscala/collection/immutable/Seq;)V
  #202 = Utf8               convertToFreeSpecStringWrapper$
  #203 = Utf8               (Lorg/scalatest/freespec/PathAnyFreeSpecLike;Ljava/lang/String;Lorg/scalactic/source/Position;)Lorg/scalatest/freespec/PathAnyFreeSpecLike$FreeSpecStringWrapper;
  #204 = Utf8               s
  #205 = Utf8               convertToFreeSpecStringWrapper
  #206 = Utf8               (Ljava/lang/String;Lorg/scalactic/source/Position;)Lorg/scalatest/freespec/PathAnyFreeSpecLike$FreeSpecStringWrapper;
  #207 = NameAndType        #205:#206     // convertToFreeSpecStringWrapper:(Ljava/lang/String;Lorg/scalactic/source/Position;)Lorg/scalatest/freespec/PathAnyFreeSpecLike$FreeSpecStringWrapper;
  #208 = InterfaceMethodref #2.#207       // org/scalatest/freespec/PathAnyFreeSpecLike.convertToFreeSpecStringWrapper:(Ljava/lang/String;Lorg/scalactic/source/Position;)Lorg/scalatest/freespec/PathAnyFreeSpecLike$FreeSpecStringWrapper;
  #209 = Utf8               (Lorg/scalatest/freespec/PathAnyFreeSpecLike;Ljava/lang/String;Lorg/scalactic/source/Position;)V
  #210 = NameAndType        #145:#209     // "<init>":(Lorg/scalatest/freespec/PathAnyFreeSpecLike;Ljava/lang/String;Lorg/scalactic/source/Position;)V
  #211 = Methodref          #38.#210      // org/scalatest/freespec/PathAnyFreeSpecLike$FreeSpecStringWrapper."<init>":(Lorg/scalatest/freespec/PathAnyFreeSpecLike;Ljava/lang/String;Lorg/scalactic/source/Position;)V
  #212 = Utf8               behave
  #213 = Utf8               ()Lorg/scalatest/verbs/BehaveWord;
  #214 = Utf8               testNames$
  #215 = Utf8               (Lorg/scalatest/freespec/PathAnyFreeSpecLike;)Lscala/collection/immutable/Set;
  #216 = Utf8               testNames
  #217 = Utf8               ()Lscala/collection/immutable/Set;
  #218 = NameAndType        #216:#217     // testNames:()Lscala/collection/immutable/Set;
  #219 = InterfaceMethodref #2.#218       // org/scalatest/freespec/PathAnyFreeSpecLike.testNames:()Lscala/collection/immutable/Set;
  #220 = Utf8               ()Lscala/collection/immutable/Set<Ljava/lang/String;>;
  #221 = Utf8               ensureTestResultsRegistered
  #222 = Utf8               (Lorg/scalatest/Suite;)V
  #223 = NameAndType        #221:#222     // ensureTestResultsRegistered:(Lorg/scalatest/Suite;)V
  #224 = Methodref          #82.#223      // org/scalatest/PathEngine.ensureTestResultsRegistered:(Lorg/scalatest/Suite;)V
  #225 = Utf8               org/scalatest/InsertionOrderSet$
  #226 = Class              #225          // org/scalatest/InsertionOrderSet$
  #227 = Utf8               Lorg/scalatest/InsertionOrderSet$;
  #228 = NameAndType        #173:#227     // MODULE$:Lorg/scalatest/InsertionOrderSet$;
  #229 = Fieldref           #226.#228     // org/scalatest/InsertionOrderSet$.MODULE$:Lorg/scalatest/InsertionOrderSet$;
  #230 = Utf8               atomic
  #231 = NameAndType        #230:#84      // atomic:()Ljava/util/concurrent/atomic/AtomicReference;
  #232 = Methodref          #82.#231      // org/scalatest/PathEngine.atomic:()Ljava/util/concurrent/atomic/AtomicReference;
  #233 = Utf8               testNamesList
  #234 = Utf8               ()Lscala/collection/immutable/List;
  #235 = NameAndType        #233:#234     // testNamesList:()Lscala/collection/immutable/List;
  #236 = Methodref          #30.#235      // org/scalatest/SuperEngine$Bundle.testNamesList:()Lscala/collection/immutable/List;
  #237 = Utf8               (Lscala/collection/immutable/List;)Lscala/collection/immutable/Set;
  #238 = NameAndType        #165:#237     // apply:(Lscala/collection/immutable/List;)Lscala/collection/immutable/Set;
  #239 = Methodref          #226.#238     // org/scalatest/InsertionOrderSet$.apply:(Lscala/collection/immutable/List;)Lscala/collection/immutable/Set;
  #240 = Utf8               expectedTestCount$
  #241 = Utf8               (Lorg/scalatest/freespec/PathAnyFreeSpecLike;Lorg/scalatest/Filter;)I
  #242 = Utf8               expectedTestCount
  #243 = NameAndType        #242:#51      // expectedTestCount:(Lorg/scalatest/Filter;)I
  #244 = InterfaceMethodref #2.#243       // org/scalatest/freespec/PathAnyFreeSpecLike.expectedTestCount:(Lorg/scalatest/Filter;)I
  #245 = Utf8               Lorg/scalatest/Filter;
  #246 = NameAndType        #50:#51       // org$scalatest$freespec$PathAnyFreeSpecLike$$super$expectedTestCount:(Lorg/scalatest/Filter;)I
  #247 = InterfaceMethodref #2.#246       // org/scalatest/freespec/PathAnyFreeSpecLike.org$scalatest$freespec$PathAnyFreeSpecLike$$super$expectedTestCount:(Lorg/scalatest/Filter;)I
  #248 = Utf8               runTest$
  #249 = Utf8               (Lorg/scalatest/freespec/PathAnyFreeSpecLike;Ljava/lang/String;Lorg/scalatest/Args;)Lorg/scalatest/Status;
  #250 = Utf8               testName
  #251 = Utf8               args
  #252 = Utf8               runTest
  #253 = Utf8               (Ljava/lang/String;Lorg/scalatest/Args;)Lorg/scalatest/Status;
  #254 = NameAndType        #252:#253     // runTest:(Ljava/lang/String;Lorg/scalatest/Args;)Lorg/scalatest/Status;
  #255 = InterfaceMethodref #2.#254       // org/scalatest/freespec/PathAnyFreeSpecLike.runTest:(Ljava/lang/String;Lorg/scalatest/Args;)Lorg/scalatest/Status;
  #256 = Utf8               Lorg/scalatest/Args;
  #257 = Utf8               (Ljava/lang/Object;)Ljava/lang/Object;
  #258 = MethodType         #257          //  (Ljava/lang/Object;)Ljava/lang/Object;
  #259 = Utf8               $anonfun$runTest$1
  #260 = Utf8               (Lorg/scalatest/SuperEngine$TestLeaf;)Lorg/scalatest/Outcome;
  #261 = NameAndType        #259:#260     // $anonfun$runTest$1:(Lorg/scalatest/SuperEngine$TestLeaf;)Lorg/scalatest/Outcome;
  #262 = InterfaceMethodref #2.#261       // org/scalatest/freespec/PathAnyFreeSpecLike.$anonfun$runTest$1:(Lorg/scalatest/SuperEngine$TestLeaf;)Lorg/scalatest/Outcome;
  #263 = MethodHandle       6:#262        // REF_invokeStatic org/scalatest/freespec/PathAnyFreeSpecLike.$anonfun$runTest$1:(Lorg/scalatest/SuperEngine$TestLeaf;)Lorg/scalatest/Outcome;
  #264 = MethodType         #260          //  (Lorg/scalatest/SuperEngine$TestLeaf;)Lorg/scalatest/Outcome;
  #265 = Utf8               ()Lscala/Function1;
  #266 = NameAndType        #165:#265     // apply:()Lscala/Function1;
  #267 = InvokeDynamic      #2:#266       // #2:apply:()Lscala/Function1;
  #268 = Utf8               runTestImpl
  #269 = Utf8               (Lorg/scalatest/Suite;Ljava/lang/String;Lorg/scalatest/Args;ZLscala/Function1;)Lorg/scalatest/Status;
  #270 = NameAndType        #268:#269     // runTestImpl:(Lorg/scalatest/Suite;Ljava/lang/String;Lorg/scalatest/Args;ZLscala/Function1;)Lorg/scalatest/Status;
  #271 = Methodref          #82.#270      // org/scalatest/PathEngine.runTestImpl:(Lorg/scalatest/Suite;Ljava/lang/String;Lorg/scalatest/Args;ZLscala/Function1;)Lorg/scalatest/Status;
  #272 = Utf8               tags$
  #273 = Utf8               (Lorg/scalatest/freespec/PathAnyFreeSpecLike;)Lscala/collection/immutable/Map;
  #274 = Utf8               tags
  #275 = Utf8               ()Lscala/collection/immutable/Map;
  #276 = NameAndType        #274:#275     // tags:()Lscala/collection/immutable/Map;
  #277 = InterfaceMethodref #2.#276       // org/scalatest/freespec/PathAnyFreeSpecLike.tags:()Lscala/collection/immutable/Map;
  #278 = Utf8               ()Lscala/collection/immutable/Map<Ljava/lang/String;Lscala/collection/immutable/Set<Ljava/lang/String;>;>;
  #279 = Utf8               org/scalatest/Suite$
  #280 = Class              #279          // org/scalatest/Suite$
  #281 = Utf8               Lorg/scalatest/Suite$;
  #282 = NameAndType        #173:#281     // MODULE$:Lorg/scalatest/Suite$;
  #283 = Fieldref           #280.#282     // org/scalatest/Suite$.MODULE$:Lorg/scalatest/Suite$;
  #284 = Utf8               tagsMap
  #285 = NameAndType        #284:#275     // tagsMap:()Lscala/collection/immutable/Map;
  #286 = Methodref          #30.#285      // org/scalatest/SuperEngine$Bundle.tagsMap:()Lscala/collection/immutable/Map;
  #287 = Utf8               autoTagClassAnnotations
  #288 = Utf8               (Lscala/collection/immutable/Map;Lorg/scalatest/Suite;)Lscala/collection/immutable/Map;
  #289 = NameAndType        #287:#288     // autoTagClassAnnotations:(Lscala/collection/immutable/Map;Lorg/scalatest/Suite;)Lscala/collection/immutable/Map;
  #290 = Methodref          #280.#289     // org/scalatest/Suite$.autoTagClassAnnotations:(Lscala/collection/immutable/Map;Lorg/scalatest/Suite;)Lscala/collection/immutable/Map;
  #291 = Utf8               run$
  #292 = Utf8               (Lorg/scalatest/freespec/PathAnyFreeSpecLike;Lscala/Option;Lorg/scalatest/Args;)Lorg/scalatest/Status;
  #293 = Utf8               run
  #294 = Utf8               (Lscala/Option;Lorg/scalatest/Args;)Lorg/scalatest/Status;
  #295 = NameAndType        #293:#294     // run:(Lscala/Option;Lorg/scalatest/Args;)Lorg/scalatest/Status;
  #296 = InterfaceMethodref #2.#295       // org/scalatest/freespec/PathAnyFreeSpecLike.run:(Lscala/Option;Lorg/scalatest/Args;)Lorg/scalatest/Status;
  #297 = Utf8               Lscala/Option;
  #298 = Utf8               (Lscala/Option<Ljava/lang/String;>;Lorg/scalatest/Args;)Lorg/scalatest/Status;
  #299 = Utf8               (Ljava/lang/Object;Ljava/lang/Object;)Ljava/lang/Object;
  #300 = MethodType         #299          //  (Ljava/lang/Object;Ljava/lang/Object;)Ljava/lang/Object;
  #301 = Utf8               $anonfun$run$1
  #302 = NameAndType        #301:#249     // $anonfun$run$1:(Lorg/scalatest/freespec/PathAnyFreeSpecLike;Ljava/lang/String;Lorg/scalatest/Args;)Lorg/scalatest/Status;
  #303 = InterfaceMethodref #2.#302       // org/scalatest/freespec/PathAnyFreeSpecLike.$anonfun$run$1:(Lorg/scalatest/freespec/PathAnyFreeSpecLike;Ljava/lang/String;Lorg/scalatest/Args;)Lorg/scalatest/Status;
  #304 = MethodHandle       6:#303        // REF_invokeStatic org/scalatest/freespec/PathAnyFreeSpecLike.$anonfun$run$1:(Lorg/scalatest/freespec/PathAnyFreeSpecLike;Ljava/lang/String;Lorg/scalatest/Args;)Lorg/scalatest/Status;
  #305 = MethodType         #253          //  (Ljava/lang/String;Lorg/scalatest/Args;)Lorg/scalatest/Status;
  #306 = Utf8               (Lorg/scalatest/freespec/PathAnyFreeSpecLike;)Lscala/Function2;
  #307 = NameAndType        #165:#306     // apply:(Lorg/scalatest/freespec/PathAnyFreeSpecLike;)Lscala/Function2;
  #308 = InvokeDynamic      #3:#307       // #3:apply:(Lorg/scalatest/freespec/PathAnyFreeSpecLike;)Lscala/Function2;
  #309 = Utf8               runPathTestsImpl
  #310 = Utf8               (Lorg/scalatest/Suite;Lscala/Option;Lorg/scalatest/Args;Lorg/scalatest/Informer;ZLscala/Function2;)Lorg/scalatest/Status;
  #311 = NameAndType        #309:#310     // runPathTestsImpl:(Lorg/scalatest/Suite;Lscala/Option;Lorg/scalatest/Args;Lorg/scalatest/Informer;ZLscala/Function2;)Lorg/scalatest/Status;
  #312 = Methodref          #82.#311      // org/scalatest/PathEngine.runPathTestsImpl:(Lorg/scalatest/Suite;Lscala/Option;Lorg/scalatest/Args;Lorg/scalatest/Informer;ZLscala/Function2;)Lorg/scalatest/Status;
  #313 = Utf8               runTests$
  #314 = Utf8               runTests
  #315 = NameAndType        #314:#294     // runTests:(Lscala/Option;Lorg/scalatest/Args;)Lorg/scalatest/Status;
  #316 = InterfaceMethodref #2.#315       // org/scalatest/freespec/PathAnyFreeSpecLike.runTests:(Lscala/Option;Lorg/scalatest/Args;)Lorg/scalatest/Status;
  #317 = Utf8               java/lang/UnsupportedOperationException
  #318 = Class              #317          // java/lang/UnsupportedOperationException
  #319 = Utf8               ()V
  #320 = NameAndType        #145:#319     // "<init>":()V
  #321 = Methodref          #318.#320     // java/lang/UnsupportedOperationException."<init>":()V
  #322 = Utf8               runNestedSuites$
  #323 = Utf8               (Lorg/scalatest/freespec/PathAnyFreeSpecLike;Lorg/scalatest/Args;)Lorg/scalatest/Status;
  #324 = Utf8               runNestedSuites
  #325 = Utf8               (Lorg/scalatest/Args;)Lorg/scalatest/Status;
  #326 = NameAndType        #324:#325     // runNestedSuites:(Lorg/scalatest/Args;)Lorg/scalatest/Status;
  #327 = InterfaceMethodref #2.#326       // org/scalatest/freespec/PathAnyFreeSpecLike.runNestedSuites:(Lorg/scalatest/Args;)Lorg/scalatest/Status;
  #328 = Utf8               org/scalatest/SucceededStatus$
  #329 = Class              #328          // org/scalatest/SucceededStatus$
  #330 = Utf8               Lorg/scalatest/SucceededStatus$;
  #331 = NameAndType        #173:#330     // MODULE$:Lorg/scalatest/SucceededStatus$;
  #332 = Fieldref           #329.#331     // org/scalatest/SucceededStatus$.MODULE$:Lorg/scalatest/SucceededStatus$;
  #333 = Utf8               nestedSuites$
  #334 = Utf8               (Lorg/scalatest/freespec/PathAnyFreeSpecLike;)Lscala/collection/immutable/IndexedSeq;
  #335 = Utf8               nestedSuites
  #336 = Utf8               ()Lscala/collection/immutable/IndexedSeq;
  #337 = NameAndType        #335:#336     // nestedSuites:()Lscala/collection/immutable/IndexedSeq;
  #338 = InterfaceMethodref #2.#337       // org/scalatest/freespec/PathAnyFreeSpecLike.nestedSuites:()Lscala/collection/immutable/IndexedSeq;
  #339 = Utf8               ()Lscala/collection/immutable/IndexedSeq<Lorg/scalatest/Suite;>;
  #340 = Utf8               scala/package$
  #341 = Class              #340          // scala/package$
  #342 = Utf8               Lscala/package$;
  #343 = NameAndType        #173:#342     // MODULE$:Lscala/package$;
  #344 = Fieldref           #341.#343     // scala/package$.MODULE$:Lscala/package$;
  #345 = Utf8               Vector
  #346 = Utf8               ()Lscala/collection/immutable/Vector$;
  #347 = NameAndType        #345:#346     // Vector:()Lscala/collection/immutable/Vector$;
  #348 = Methodref          #341.#347     // scala/package$.Vector:()Lscala/collection/immutable/Vector$;
  #349 = Utf8               scala/collection/immutable/Vector$
  #350 = Class              #349          // scala/collection/immutable/Vector$
  #351 = Utf8               empty
  #352 = Utf8               ()Lscala/collection/immutable/Vector;
  #353 = NameAndType        #351:#352     // empty:()Lscala/collection/immutable/Vector;
  #354 = Methodref          #350.#353     // scala/collection/immutable/Vector$.empty:()Lscala/collection/immutable/Vector;
  #355 = Utf8               styleName
  #356 = Utf8               testDataFor$
  #357 = Utf8               (Lorg/scalatest/freespec/PathAnyFreeSpecLike;Ljava/lang/String;Lorg/scalatest/ConfigMap;)Lorg/scalatest/TestData;
  #358 = Utf8               theConfigMap
  #359 = Utf8               testDataFor
  #360 = Utf8               (Ljava/lang/String;Lorg/scalatest/ConfigMap;)Lorg/scalatest/TestData;
  #361 = NameAndType        #359:#360     // testDataFor:(Ljava/lang/String;Lorg/scalatest/ConfigMap;)Lorg/scalatest/TestData;
  #362 = InterfaceMethodref #2.#361       // org/scalatest/freespec/PathAnyFreeSpecLike.testDataFor:(Ljava/lang/String;Lorg/scalatest/ConfigMap;)Lorg/scalatest/TestData;
  #363 = Utf8               Lorg/scalatest/ConfigMap;
  #364 = Utf8               createTestDataFor
  #365 = Utf8               (Ljava/lang/String;Lorg/scalatest/ConfigMap;Lorg/scalatest/Suite;)Lorg/scalatest/TestData;
  #366 = NameAndType        #364:#365     // createTestDataFor:(Ljava/lang/String;Lorg/scalatest/ConfigMap;Lorg/scalatest/Suite;)Lorg/scalatest/TestData;
  #367 = Methodref          #82.#366      // org/scalatest/PathEngine.createTestDataFor:(Ljava/lang/String;Lorg/scalatest/ConfigMap;Lorg/scalatest/Suite;)Lorg/scalatest/TestData;
  #368 = Utf8               testDataFor$default$2$
  #369 = Utf8               (Lorg/scalatest/freespec/PathAnyFreeSpecLike;)Lorg/scalatest/ConfigMap;
  #370 = Utf8               testDataFor$default$2
  #371 = Utf8               ()Lorg/scalatest/ConfigMap;
  #372 = NameAndType        #370:#371     // testDataFor$default$2:()Lorg/scalatest/ConfigMap;
  #373 = InterfaceMethodref #2.#372       // org/scalatest/freespec/PathAnyFreeSpecLike.testDataFor$default$2:()Lorg/scalatest/ConfigMap;
  #374 = Utf8               org/scalatest/ConfigMap$
  #375 = Class              #374          // org/scalatest/ConfigMap$
  #376 = Utf8               Lorg/scalatest/ConfigMap$;
  #377 = NameAndType        #173:#376     // MODULE$:Lorg/scalatest/ConfigMap$;
  #378 = Fieldref           #375.#377     // org/scalatest/ConfigMap$.MODULE$:Lorg/scalatest/ConfigMap$;
  #379 = NameAndType        #351:#371     // empty:()Lorg/scalatest/ConfigMap;
  #380 = Methodref          #375.#379     // org/scalatest/ConfigMap$.empty:()Lorg/scalatest/ConfigMap;
  #381 = Utf8               org/scalatest/Resources$
  #382 = Class              #381          // org/scalatest/Resources$
  #383 = Utf8               Lorg/scalatest/Resources$;
  #384 = NameAndType        #173:#383     // MODULE$:Lorg/scalatest/Resources$;
  #385 = Fieldref           #382.#384     // org/scalatest/Resources$.MODULE$:Lorg/scalatest/Resources$;
  #386 = Utf8               itCannotAppearInsideAnotherIt
  #387 = NameAndType        #386:#151     // itCannotAppearInsideAnotherIt:()Ljava/lang/String;
  #388 = Methodref          #382.#387     // org/scalatest/Resources$.itCannotAppearInsideAnotherIt:()Ljava/lang/String;
  #389 = Utf8               ignoreCannotAppearInsideAnIt
  #390 = NameAndType        #389:#151     // ignoreCannotAppearInsideAnIt:()Ljava/lang/String;
  #391 = Methodref          #382.#390     // org/scalatest/Resources$.ignoreCannotAppearInsideAnIt:()Ljava/lang/String;
  #392 = Utf8               dontInvokeWithFixture$1
  #393 = Utf8               theTest
  #394 = NameAndType        #132:#69      // testFun:()Ljava/lang/Object;
  #395 = Methodref          #35.#394      // org/scalatest/SuperEngine$TestLeaf.testFun:()Ljava/lang/Object;
  #396 = Utf8               scala/Function0
  #397 = Class              #396          // scala/Function0
  #398 = NameAndType        #165:#69      // apply:()Ljava/lang/Object;
  #399 = InterfaceMethodref #397.#398     // scala/Function0.apply:()Ljava/lang/Object;
  #400 = Utf8               org/scalatest/Outcome
  #401 = Class              #400          // org/scalatest/Outcome
  #402 = Utf8               Lorg/scalatest/SuperEngine$TestLeaf;
  #403 = NameAndType        #392:#260     // dontInvokeWithFixture$1:(Lorg/scalatest/SuperEngine$TestLeaf;)Lorg/scalatest/Outcome;
  #404 = InterfaceMethodref #2.#403       // org/scalatest/freespec/PathAnyFreeSpecLike.dontInvokeWithFixture$1:(Lorg/scalatest/SuperEngine$TestLeaf;)Lorg/scalatest/Outcome;
  #405 = Utf8               $init$
  #406 = Utf8               (Lorg/scalatest/freespec/PathAnyFreeSpecLike;)V
  #407 = Utf8               org/scalatest/PathEngine$
  #408 = Class              #407          // org/scalatest/PathEngine$
  #409 = Utf8               Lorg/scalatest/PathEngine$;
  #410 = NameAndType        #173:#409     // MODULE$:Lorg/scalatest/PathEngine$;
  #411 = Fieldref           #408.#410     // org/scalatest/PathEngine$.MODULE$:Lorg/scalatest/PathEngine$;
  #412 = Utf8               getEngine
  #413 = NameAndType        #412:#54      // getEngine:()Lorg/scalatest/PathEngine;
  #414 = Methodref          #408.#413     // org/scalatest/PathEngine$.getEngine:()Lorg/scalatest/PathEngine;
  #415 = NameAndType        #43:#44       // org$scalatest$freespec$PathAnyFreeSpecLike$_setter_$org$scalatest$freespec$PathAnyFreeSpecLike$$engine_$eq:(Lorg/scalatest/PathEngine;)V
  #416 = InterfaceMethodref #2.#415       // org/scalatest/freespec/PathAnyFreeSpecLike.org$scalatest$freespec$PathAnyFreeSpecLike$_setter_$org$scalatest$freespec$PathAnyFreeSpecLike$$engine_$eq:(Lorg/scalatest/PathEngine;)V
  #417 = Utf8               org/scalatest/verbs/BehaveWord
  #418 = Class              #417          // org/scalatest/verbs/BehaveWord
  #419 = Methodref          #418.#320     // org/scalatest/verbs/BehaveWord."<init>":()V
  #420 = NameAndType        #46:#47       // org$scalatest$freespec$PathAnyFreeSpecLike$_setter_$behave_$eq:(Lorg/scalatest/verbs/BehaveWord;)V
  #421 = InterfaceMethodref #2.#420       // org/scalatest/freespec/PathAnyFreeSpecLike.org$scalatest$freespec$PathAnyFreeSpecLike$_setter_$behave_$eq:(Lorg/scalatest/verbs/BehaveWord;)V
  #422 = Utf8               org.scalatest.path.FreeSpec
  #423 = String             #422          // org.scalatest.path.FreeSpec
  #424 = NameAndType        #48:#49       // org$scalatest$freespec$PathAnyFreeSpecLike$_setter_$styleName_$eq:(Ljava/lang/String;)V
  #425 = InterfaceMethodref #2.#424       // org/scalatest/freespec/PathAnyFreeSpecLike.org$scalatest$freespec$PathAnyFreeSpecLike$_setter_$styleName_$eq:(Ljava/lang/String;)V
  #426 = Utf8               $deserializeLambda$
  #427 = Utf8               (Ljava/lang/invoke/SerializedLambda;)Ljava/lang/Object;
  #428 = Utf8               scala/runtime/LambdaDeserialize
  #429 = Class              #428          // scala/runtime/LambdaDeserialize
  #430 = Utf8               bootstrap
  #431 = Utf8               (Ljava/lang/invoke/MethodHandles$Lookup;Ljava/lang/String;Ljava/lang/invoke/MethodType;[Ljava/lang/invoke/MethodHandle;)Ljava/lang/invoke/CallSite;
  #432 = NameAndType        #430:#431     // bootstrap:(Ljava/lang/invoke/MethodHandles$Lookup;Ljava/lang/String;Ljava/lang/invoke/MethodType;[Ljava/lang/invoke/MethodHandle;)Ljava/lang/invoke/CallSite;
  #433 = Methodref          #429.#432     // scala/runtime/LambdaDeserialize.bootstrap:(Ljava/lang/invoke/MethodHandles$Lookup;Ljava/lang/String;Ljava/lang/invoke/MethodType;[Ljava/lang/invoke/MethodHandle;)Ljava/lang/invoke/CallSite;
  #434 = MethodHandle       6:#433        // REF_invokeStatic scala/runtime/LambdaDeserialize.bootstrap:(Ljava/lang/invoke/MethodHandles$Lookup;Ljava/lang/String;Ljava/lang/invoke/MethodType;[Ljava/lang/invoke/MethodHandle;)Ljava/lang/invoke/CallSite;
  #435 = Utf8               lambdaDeserialize
  #436 = NameAndType        #435:#427     // lambdaDeserialize:(Ljava/lang/invoke/SerializedLambda;)Ljava/lang/Object;
  #437 = InvokeDynamic      #4:#436       // #4:lambdaDeserialize:(Ljava/lang/invoke/SerializedLambda;)Ljava/lang/Object;
  #438 = Utf8               MethodParameters
  #439 = Utf8               Code
  #440 = Utf8               LineNumberTable
  #441 = Utf8               LocalVariableTable
  #442 = Utf8               Signature
  #443 = Utf8               Deprecated
  #444 = Utf8               InnerClasses
  #445 = Utf8               SourceFile
  #446 = Utf8               RuntimeVisibleAnnotations
  #447 = Utf8               BootstrapMethods
  #448 = Utf8               ScalaInlineInfo
  #449 = Utf8               ScalaSig
{
  public abstract void org$scalatest$freespec$PathAnyFreeSpecLike$_setter_$org$scalatest$freespec$PathAnyFreeSpecLike$$engine_$eq(org.scalatest.PathEngine);
    descriptor: (Lorg/scalatest/PathEngine;)V
    flags: (0x0401) ACC_PUBLIC, ACC_ABSTRACT
    MethodParameters:
      Name                           Flags
      x$1                            final

  public abstract void org$scalatest$freespec$PathAnyFreeSpecLike$_setter_$behave_$eq(org.scalatest.verbs.BehaveWord);
    descriptor: (Lorg/scalatest/verbs/BehaveWord;)V
    flags: (0x0401) ACC_PUBLIC, ACC_ABSTRACT
    MethodParameters:
      Name                           Flags
      x$1                            final

  public abstract void org$scalatest$freespec$PathAnyFreeSpecLike$_setter_$styleName_$eq(java.lang.String);
    descriptor: (Ljava/lang/String;)V
    flags: (0x0401) ACC_PUBLIC, ACC_ABSTRACT
    MethodParameters:
      Name                           Flags
      x$1                            final

  public abstract int org$scalatest$freespec$PathAnyFreeSpecLike$$super$expectedTestCount(org.scalatest.Filter);
    descriptor: (Lorg/scalatest/Filter;)I
    flags: (0x1401) ACC_PUBLIC, ACC_ABSTRACT, ACC_SYNTHETIC
    MethodParameters:
      Name                           Flags
      filter                         final

  public abstract org.scalatest.PathEngine org$scalatest$freespec$PathAnyFreeSpecLike$$engine();
    descriptor: ()Lorg/scalatest/PathEngine;
    flags: (0x0401) ACC_PUBLIC, ACC_ABSTRACT

  public static org.scalatest.freespec.PathAnyFreeSpecLike newInstance$(org.scalatest.freespec.PathAnyFreeSpecLike);
    descriptor: (Lorg/scalatest/freespec/PathAnyFreeSpecLike;)Lorg/scalatest/freespec/PathAnyFreeSpecLike;
    flags: (0x1009) ACC_PUBLIC, ACC_STATIC, ACC_SYNTHETIC
    Code:
      stack=1, locals=1, args_size=1
         0: aload_0
         1: invokespecial #61                 // InterfaceMethod newInstance:()Lorg/scalatest/freespec/PathAnyFreeSpecLike;
         4: areturn
      LineNumberTable:
        line 56: 0
      LocalVariableTable:
        Start  Length  Slot  Name   Signature
            0       5     0 $this   Lorg/scalatest/freespec/PathAnyFreeSpecLike;
    MethodParameters:
      Name                           Flags
      $this                          final synthetic

  public default org.scalatest.freespec.PathAnyFreeSpecLike newInstance();
    descriptor: ()Lorg/scalatest/freespec/PathAnyFreeSpecLike;
    flags: (0x0001) ACC_PUBLIC
    Code:
      stack=1, locals=1, args_size=1
         0: aload_0
         1: invokevirtual #66                 // Method java/lang/Object.getClass:()Ljava/lang/Class;
         4: invokevirtual #71                 // Method java/lang/Class.newInstance:()Ljava/lang/Object;
         7: checkcast     #2                  // class org/scalatest/freespec/PathAnyFreeSpecLike
        10: areturn
      LineNumberTable:
        line 56: 0
      LocalVariableTable:
        Start  Length  Slot  Name   Signature
            0      11     0  this   Lorg/scalatest/freespec/PathAnyFreeSpecLike;

  public static org.scalatest.Informer info$(org.scalatest.freespec.PathAnyFreeSpecLike);
    descriptor: (Lorg/scalatest/freespec/PathAnyFreeSpecLike;)Lorg/scalatest/Informer;
    flags: (0x1009) ACC_PUBLIC, ACC_STATIC, ACC_SYNTHETIC
    Code:
      stack=1, locals=1, args_size=1
         0: aload_0
         1: invokespecial #78                 // InterfaceMethod info:()Lorg/scalatest/Informer;
         4: areturn
      LineNumberTable:
        line 69: 0
      LocalVariableTable:
        Start  Length  Slot  Name   Signature
            0       5     0 $this   Lorg/scalatest/freespec/PathAnyFreeSpecLike;
    MethodParameters:
      Name                           Flags
      $this                          final synthetic

  public default org.scalatest.Informer info();
    descriptor: ()Lorg/scalatest/Informer;
    flags: (0x0001) ACC_PUBLIC
    Code:
      stack=1, locals=1, args_size=1
         0: aload_0
         1: invokeinterface #80,  1           // InterfaceMethod org$scalatest$freespec$PathAnyFreeSpecLike$$engine:()Lorg/scalatest/PathEngine;
         6: invokevirtual #86                 // Method org/scalatest/PathEngine.atomicInformer:()Ljava/util/concurrent/atomic/AtomicReference;
         9: invokevirtual #91                 // Method java/util/concurrent/atomic/AtomicReference.get:()Ljava/lang/Object;
        12: checkcast     #93                 // class org/scalatest/Informer
        15: areturn
      LineNumberTable:
        line 69: 0
      LocalVariableTable:
        Start  Length  Slot  Name   Signature
            0      16     0  this   Lorg/scalatest/freespec/PathAnyFreeSpecLike;

  public static org.scalatest.Notifier note$(org.scalatest.freespec.PathAnyFreeSpecLike);
    descriptor: (Lorg/scalatest/freespec/PathAnyFreeSpecLike;)Lorg/scalatest/Notifier;
    flags: (0x1009) ACC_PUBLIC, ACC_STATIC, ACC_SYNTHETIC
    Code:
      stack=1, locals=1, args_size=1
         0: aload_0
         1: invokespecial #99                 // InterfaceMethod note:()Lorg/scalatest/Notifier;
         4: areturn
      LineNumberTable:
        line 79: 0
      LocalVariableTable:
        Start  Length  Slot  Name   Signature
            0       5     0 $this   Lorg/scalatest/freespec/PathAnyFreeSpecLike;
    MethodParameters:
      Name                           Flags
      $this                          final synthetic

  public default org.scalatest.Notifier note();
    descriptor: ()Lorg/scalatest/Notifier;
    flags: (0x0001) ACC_PUBLIC
    Code:
      stack=1, locals=1, args_size=1
         0: aload_0
         1: invokeinterface #80,  1           // InterfaceMethod org$scalatest$freespec$PathAnyFreeSpecLike$$engine:()Lorg/scalatest/PathEngine;
         6: invokevirtual #102                // Method org/scalatest/PathEngine.atomicNotifier:()Ljava/util/concurrent/atomic/AtomicReference;
         9: invokevirtual #91                 // Method java/util/concurrent/atomic/AtomicReference.get:()Ljava/lang/Object;
        12: checkcast     #104                // class org/scalatest/Notifier
        15: areturn
      LineNumberTable:
        line 79: 0
      LocalVariableTable:
        Start  Length  Slot  Name   Signature
            0      16     0  this   Lorg/scalatest/freespec/PathAnyFreeSpecLike;

  public static org.scalatest.Alerter alert$(org.scalatest.freespec.PathAnyFreeSpecLike);
    descriptor: (Lorg/scalatest/freespec/PathAnyFreeSpecLike;)Lorg/scalatest/Alerter;
    flags: (0x1009) ACC_PUBLIC, ACC_STATIC, ACC_SYNTHETIC
    Code:
      stack=1, locals=1, args_size=1
         0: aload_0
         1: invokespecial #110                // InterfaceMethod alert:()Lorg/scalatest/Alerter;
         4: areturn
      LineNumberTable:
        line 89: 0
      LocalVariableTable:
        Start  Length  Slot  Name   Signature
            0       5     0 $this   Lorg/scalatest/freespec/PathAnyFreeSpecLike;
    MethodParameters:
      Name                           Flags
      $this                          final synthetic

  public default org.scalatest.Alerter alert();
    descriptor: ()Lorg/scalatest/Alerter;
    flags: (0x0001) ACC_PUBLIC
    Code:
      stack=1, locals=1, args_size=1
         0: aload_0
         1: invokeinterface #80,  1           // InterfaceMethod org$scalatest$freespec$PathAnyFreeSpecLike$$engine:()Lorg/scalatest/PathEngine;
         6: invokevirtual #113                // Method org/scalatest/PathEngine.atomicAlerter:()Ljava/util/concurrent/atomic/AtomicReference;
         9: invokevirtual #91                 // Method java/util/concurrent/atomic/AtomicReference.get:()Ljava/lang/Object;
        12: checkcast     #115                // class org/scalatest/Alerter
        15: areturn
      LineNumberTable:
        line 89: 0
      LocalVariableTable:
        Start  Length  Slot  Name   Signature
            0      16     0  this   Lorg/scalatest/freespec/PathAnyFreeSpecLike;

  public static org.scalatest.Documenter markup$(org.scalatest.freespec.PathAnyFreeSpecLike);
    descriptor: (Lorg/scalatest/freespec/PathAnyFreeSpecLike;)Lorg/scalatest/Documenter;
    flags: (0x1009) ACC_PUBLIC, ACC_STATIC, ACC_SYNTHETIC
    Code:
      stack=1, locals=1, args_size=1
         0: aload_0
         1: invokespecial #121                // InterfaceMethod markup:()Lorg/scalatest/Documenter;
         4: areturn
      LineNumberTable:
        line 100: 0
      LocalVariableTable:
        Start  Length  Slot  Name   Signature
            0       5     0 $this   Lorg/scalatest/freespec/PathAnyFreeSpecLike;
    MethodParameters:
      Name                           Flags
      $this                          final synthetic

  public default org.scalatest.Documenter markup();
    descriptor: ()Lorg/scalatest/Documenter;
    flags: (0x0001) ACC_PUBLIC
    Code:
      stack=1, locals=1, args_size=1
         0: aload_0
         1: invokeinterface #80,  1           // InterfaceMethod org$scalatest$freespec$PathAnyFreeSpecLike$$engine:()Lorg/scalatest/PathEngine;
         6: invokevirtual #124                // Method org/scalatest/PathEngine.atomicDocumenter:()Ljava/util/concurrent/atomic/AtomicReference;
         9: invokevirtual #91                 // Method java/util/concurrent/atomic/AtomicReference.get:()Ljava/lang/Object;
        12: checkcast     #126                // class org/scalatest/Documenter
        15: areturn
      LineNumberTable:
        line 100: 0
      LocalVariableTable:
        Start  Length  Slot  Name   Signature
            0      16     0  this   Lorg/scalatest/freespec/PathAnyFreeSpecLike;

  public static void org$scalatest$freespec$PathAnyFreeSpecLike$$registerTestToRun$(org.scalatest.freespec.PathAnyFreeSpecLike, java.lang.String, scala.collection.immutable.List, java.lang.String, scala.Function0, org.scalactic.source.Position);
    descriptor: (Lorg/scalatest/freespec/PathAnyFreeSpecLike;Ljava/lang/String;Lscala/collection/immutable/List;Ljava/lang/String;Lscala/Function0;Lorg/scalactic/source/Position;)V
    flags: (0x1009) ACC_PUBLIC, ACC_STATIC, ACC_SYNTHETIC
    Code:
      stack=6, locals=6, args_size=6
         0: aload_0
         1: aload_1
         2: aload_2
         3: aload_3
         4: aload         4
         6: aload         5
         8: invokespecial #137                // InterfaceMethod org$scalatest$freespec$PathAnyFreeSpecLike$$registerTestToRun:(Ljava/lang/String;Lscala/collection/immutable/List;Ljava/lang/String;Lscala/Function0;Lorg/scalactic/source/Position;)V
        11: return
      LineNumberTable:
        line 121: 0
      LocalVariableTable:
        Start  Length  Slot  Name   Signature
            0      12     0 $this   Lorg/scalatest/freespec/PathAnyFreeSpecLike;
            0      12     1 specText   Ljava/lang/String;
            0      12     2 testTags   Lscala/collection/immutable/List;
            0      12     3 methodName   Ljava/lang/String;
            0      12     4 testFun   Lscala/Function0;
            0      12     5   pos   Lorg/scalactic/source/Position;
    MethodParameters:
      Name                           Flags
      $this                          final synthetic
      specText                       final
      testTags                       final
      methodName                     final
      testFun                        final
      pos                            final

  public default void org$scalatest$freespec$PathAnyFreeSpecLike$$registerTestToRun(java.lang.String, scala.collection.immutable.List<org.scalatest.Tag>, java.lang.String, scala.Function0<scala.runtime.BoxedUnit>, org.scalactic.source.Position);
    descriptor: (Ljava/lang/String;Lscala/collection/immutable/List;Ljava/lang/String;Lscala/Function0;Lorg/scalactic/source/Position;)V
    flags: (0x0001) ACC_PUBLIC
    Code:
      stack=13, locals=8, args_size=6
         0: iconst_4
         1: istore        6
         3: bipush        -3
         5: istore        7
         7: aload_0
         8: invokeinterface #80,  1           // InterfaceMethod org$scalatest$freespec$PathAnyFreeSpecLike$$engine:()Lorg/scalatest/PathEngine;
        13: aload_0
        14: aload_1
        15: new           #144                // class org/scalatest/Transformer
        18: dup
        19: aload         4
        21: invokespecial #148                // Method org/scalatest/Transformer."<init>":(Lscala/Function0;)V
        24: invokedynamic #168,  0            // InvokeDynamic #0:apply:()Lscala/Function0;
        29: ldc           #170                // String FreeSpecLike.scala
        31: aload_3
        32: iload         6
        34: iload         7
        36: getstatic     #176                // Field scala/None$.MODULE$:Lscala/None$;
        39: new           #178                // class scala/Some
        42: dup
        43: aload         5
        45: invokespecial #181                // Method scala/Some."<init>":(Ljava/lang/Object;)V
        48: aload_2
        49: invokevirtual #185                // Method org/scalatest/PathEngine.handleTest:(Lorg/scalatest/Suite;Ljava/lang/String;Lscala/Function0;Lscala/Function0;Ljava/lang/String;Ljava/lang/String;IILscala/Option;Lscala/Option;Lscala/collection/immutable/Seq;)V
        52: return
      LineNumberTable:
        line 123: 0
        line 124: 3
        line 128: 7
      LocalVariableTable:
        Start  Length  Slot  Name   Signature
            3      49     6 stackDepth   I
            7      45     7 stackDepthAdjustment   I
            0      53     0  this   Lorg/scalatest/freespec/PathAnyFreeSpecLike;
            0      53     1 specText   Ljava/lang/String;
            0      53     2 testTags   Lscala/collection/immutable/List;
            0      53     3 methodName   Ljava/lang/String;
            0      53     4 testFun   Lscala/Function0;
            0      53     5   pos   Lorg/scalactic/source/Position;
    Signature: #142                         // (Ljava/lang/String;Lscala/collection/immutable/List<Lorg/scalatest/Tag;>;Ljava/lang/String;Lscala/Function0<Lscala/runtime/BoxedUnit;>;Lorg/scalactic/source/Position;)V
    MethodParameters:
      Name                           Flags
      specText                       final
      testTags                       final
      methodName                     final
      testFun                        final
      pos                            final

  public static void org$scalatest$freespec$PathAnyFreeSpecLike$$registerTestToIgnore$(org.scalatest.freespec.PathAnyFreeSpecLike, java.lang.String, scala.collection.immutable.List, java.lang.String, scala.Function0, org.scalactic.source.Position);
    descriptor: (Lorg/scalatest/freespec/PathAnyFreeSpecLike;Ljava/lang/String;Lscala/collection/immutable/List;Ljava/lang/String;Lscala/Function0;Lorg/scalactic/source/Position;)V
    flags: (0x1009) ACC_PUBLIC, ACC_STATIC, ACC_SYNTHETIC
    Code:
      stack=6, locals=6, args_size=6
         0: aload_0
         1: aload_1
         2: aload_2
         3: aload_3
         4: aload         4
         6: aload         5
         8: invokespecial #192                // InterfaceMethod org$scalatest$freespec$PathAnyFreeSpecLike$$registerTestToIgnore:(Ljava/lang/String;Lscala/collection/immutable/List;Ljava/lang/String;Lscala/Function0;Lorg/scalactic/source/Position;)V
        11: return
      LineNumberTable:
        line 150: 0
      LocalVariableTable:
        Start  Length  Slot  Name   Signature
            0      12     0 $this   Lorg/scalatest/freespec/PathAnyFreeSpecLike;
            0      12     1 specText   Ljava/lang/String;
            0      12     2 testTags   Lscala/collection/immutable/List;
            0      12     3 methodName   Ljava/lang/String;
            0      12     4 testFun   Lscala/Function0;
            0      12     5   pos   Lorg/scalactic/source/Position;
    MethodParameters:
      Name                           Flags
      $this                          final synthetic
      specText                       final
      testTags                       final
      methodName                     final
      testFun                        final
      pos                            final

  public default void org$scalatest$freespec$PathAnyFreeSpecLike$$registerTestToIgnore(java.lang.String, scala.collection.immutable.List<org.scalatest.Tag>, java.lang.String, scala.Function0<scala.runtime.BoxedUnit>, org.scalactic.source.Position);
    descriptor: (Ljava/lang/String;Lscala/collection/immutable/List;Ljava/lang/String;Lscala/Function0;Lorg/scalactic/source/Position;)V
    flags: (0x0001) ACC_PUBLIC
    Code:
      stack=12, locals=8, args_size=6
         0: iconst_4
         1: istore        6
         3: bipush        -3
         5: istore        7
         7: aload_0
         8: invokeinterface #80,  1           // InterfaceMethod org$scalatest$freespec$PathAnyFreeSpecLike$$engine:()Lorg/scalatest/PathEngine;
        13: aload_1
        14: new           #144                // class org/scalatest/Transformer
        17: dup
        18: aload         4
        20: invokespecial #148                // Method org/scalatest/Transformer."<init>":(Lscala/Function0;)V
        23: invokedynamic #197,  0            // InvokeDynamic #1:apply:()Lscala/Function0;
        28: ldc           #170                // String FreeSpecLike.scala
        30: aload_3
        31: iload         6
        33: iload         7
        35: getstatic     #176                // Field scala/None$.MODULE$:Lscala/None$;
        38: new           #178                // class scala/Some
        41: dup
        42: aload         5
        44: invokespecial #181                // Method scala/Some."<init>":(Ljava/lang/Object;)V
        47: aload_2
        48: invokevirtual #201                // Method org/scalatest/PathEngine.handleIgnoredTest:(Ljava/lang/String;Lscala/Function0;Lscala/Function0;Ljava/lang/String;Ljava/lang/String;IILscala/Option;Lscala/Option;Lscala/collection/immutable/Seq;)V
        51: return
      LineNumberTable:
        line 152: 0
        line 153: 3
        line 157: 7
      LocalVariableTable:
        Start  Length  Slot  Name   Signature
            3      48     6 stackDepth   I
            7      44     7 stackDepthAdjustment   I
            0      52     0  this   Lorg/scalatest/freespec/PathAnyFreeSpecLike;
            0      52     1 specText   Ljava/lang/String;
            0      52     2 testTags   Lscala/collection/immutable/List;
            0      52     3 methodName   Ljava/lang/String;
            0      52     4 testFun   Lscala/Function0;
            0      52     5   pos   Lorg/scalactic/source/Position;
    Signature: #142                         // (Ljava/lang/String;Lscala/collection/immutable/List<Lorg/scalatest/Tag;>;Ljava/lang/String;Lscala/Function0<Lscala/runtime/BoxedUnit;>;Lorg/scalactic/source/Position;)V
    MethodParameters:
      Name                           Flags
      specText                       final
      testTags                       final
      methodName                     final
      testFun                        final
      pos                            final

  public static org.scalatest.freespec.PathAnyFreeSpecLike$FreeSpecStringWrapper convertToFreeSpecStringWrapper$(org.scalatest.freespec.PathAnyFreeSpecLike, java.lang.String, org.scalactic.source.Position);
    descriptor: (Lorg/scalatest/freespec/PathAnyFreeSpecLike;Ljava/lang/String;Lorg/scalactic/source/Position;)Lorg/scalatest/freespec/PathAnyFreeSpecLike$FreeSpecStringWrapper;
    flags: (0x1009) ACC_PUBLIC, ACC_STATIC, ACC_SYNTHETIC
    Code:
      stack=3, locals=3, args_size=3
         0: aload_0
         1: aload_1
         2: aload_2
         3: invokespecial #208                // InterfaceMethod convertToFreeSpecStringWrapper:(Ljava/lang/String;Lorg/scalactic/source/Position;)Lorg/scalatest/freespec/PathAnyFreeSpecLike$FreeSpecStringWrapper;
         6: areturn
      LineNumberTable:
        line 393: 0
      LocalVariableTable:
        Start  Length  Slot  Name   Signature
            0       7     0 $this   Lorg/scalatest/freespec/PathAnyFreeSpecLike;
            0       7     1     s   Ljava/lang/String;
            0       7     2   pos   Lorg/scalactic/source/Position;
    MethodParameters:
      Name                           Flags
      $this                          final synthetic
      s                              final
      pos                            final

  public default org.scalatest.freespec.PathAnyFreeSpecLike$FreeSpecStringWrapper convertToFreeSpecStringWrapper(java.lang.String, org.scalactic.source.Position);
    descriptor: (Ljava/lang/String;Lorg/scalactic/source/Position;)Lorg/scalatest/freespec/PathAnyFreeSpecLike$FreeSpecStringWrapper;
    flags: (0x0001) ACC_PUBLIC
    Code:
      stack=5, locals=3, args_size=3
         0: new           #38                 // class org/scalatest/freespec/PathAnyFreeSpecLike$FreeSpecStringWrapper
         3: dup
         4: aload_0
         5: aload_1
         6: aload_2
         7: invokespecial #211                // Method org/scalatest/freespec/PathAnyFreeSpecLike$FreeSpecStringWrapper."<init>":(Lorg/scalatest/freespec/PathAnyFreeSpecLike;Ljava/lang/String;Lorg/scalactic/source/Position;)V
        10: areturn
      LineNumberTable:
        line 393: 0
      LocalVariableTable:
        Start  Length  Slot  Name   Signature
            0      11     0  this   Lorg/scalatest/freespec/PathAnyFreeSpecLike;
            0      11     1     s   Ljava/lang/String;
            0      11     2   pos   Lorg/scalactic/source/Position;
    MethodParameters:
      Name                           Flags
      s                              final
      pos                            final

  public abstract org.scalatest.verbs.BehaveWord behave();
    descriptor: ()Lorg/scalatest/verbs/BehaveWord;
    flags: (0x0401) ACC_PUBLIC, ACC_ABSTRACT

  public static scala.collection.immutable.Set testNames$(org.scalatest.freespec.PathAnyFreeSpecLike);
    descriptor: (Lorg/scalatest/freespec/PathAnyFreeSpecLike;)Lscala/collection/immutable/Set;
    flags: (0x1009) ACC_PUBLIC, ACC_STATIC, ACC_SYNTHETIC
    Code:
      stack=1, locals=1, args_size=1
         0: aload_0
         1: invokespecial #219                // InterfaceMethod testNames:()Lscala/collection/immutable/Set;
         4: areturn
      LineNumberTable:
        line 466: 0
      LocalVariableTable:
        Start  Length  Slot  Name   Signature
            0       5     0 $this   Lorg/scalatest/freespec/PathAnyFreeSpecLike;
    MethodParameters:
      Name                           Flags
      $this                          final synthetic

  public default scala.collection.immutable.Set<java.lang.String> testNames();
    descriptor: ()Lscala/collection/immutable/Set;
    flags: (0x0001) ACC_PUBLIC
    Code:
      stack=2, locals=1, args_size=1
         0: aload_0
         1: invokeinterface #80,  1           // InterfaceMethod org$scalatest$freespec$PathAnyFreeSpecLike$$engine:()Lorg/scalatest/PathEngine;
         6: aload_0
         7: invokevirtual #224                // Method org/scalatest/PathEngine.ensureTestResultsRegistered:(Lorg/scalatest/Suite;)V
        10: getstatic     #229                // Field org/scalatest/InsertionOrderSet$.MODULE$:Lorg/scalatest/InsertionOrderSet$;
        13: aload_0
        14: invokeinterface #80,  1           // InterfaceMethod org$scalatest$freespec$PathAnyFreeSpecLike$$engine:()Lorg/scalatest/PathEngine;
        19: invokevirtual #232                // Method org/scalatest/PathEngine.atomic:()Ljava/util/concurrent/atomic/AtomicReference;
        22: invokevirtual #91                 // Method java/util/concurrent/atomic/AtomicReference.get:()Ljava/lang/Object;
        25: checkcast     #30                 // class org/scalatest/SuperEngine$Bundle
        28: invokevirtual #236                // Method org/scalatest/SuperEngine$Bundle.testNamesList:()Lscala/collection/immutable/List;
        31: invokevirtual #239                // Method org/scalatest/InsertionOrderSet$.apply:(Lscala/collection/immutable/List;)Lscala/collection/immutable/Set;
        34: areturn
      LineNumberTable:
        line 467: 0
        line 468: 10
      LocalVariableTable:
        Start  Length  Slot  Name   Signature
            0      35     0  this   Lorg/scalatest/freespec/PathAnyFreeSpecLike;
    Signature: #220                         // ()Lscala/collection/immutable/Set<Ljava/lang/String;>;

  public static int expectedTestCount$(org.scalatest.freespec.PathAnyFreeSpecLike, org.scalatest.Filter);
    descriptor: (Lorg/scalatest/freespec/PathAnyFreeSpecLike;Lorg/scalatest/Filter;)I
    flags: (0x1009) ACC_PUBLIC, ACC_STATIC, ACC_SYNTHETIC
    Code:
      stack=2, locals=2, args_size=2
         0: aload_0
         1: aload_1
         2: invokespecial #244                // InterfaceMethod expectedTestCount:(Lorg/scalatest/Filter;)I
         5: ireturn
      LineNumberTable:
        line 493: 0
      LocalVariableTable:
        Start  Length  Slot  Name   Signature
            0       6     0 $this   Lorg/scalatest/freespec/PathAnyFreeSpecLike;
            0       6     1 filter   Lorg/scalatest/Filter;
    MethodParameters:
      Name                           Flags
      $this                          final synthetic
      filter                         final

  public default int expectedTestCount(org.scalatest.Filter);
    descriptor: (Lorg/scalatest/Filter;)I
    flags: (0x0001) ACC_PUBLIC
    Code:
      stack=2, locals=2, args_size=2
         0: aload_0
         1: invokeinterface #80,  1           // InterfaceMethod org$scalatest$freespec$PathAnyFreeSpecLike$$engine:()Lorg/scalatest/PathEngine;
         6: aload_0
         7: invokevirtual #224                // Method org/scalatest/PathEngine.ensureTestResultsRegistered:(Lorg/scalatest/Suite;)V
        10: aload_0
        11: aload_1
        12: invokeinterface #247,  2          // InterfaceMethod org$scalatest$freespec$PathAnyFreeSpecLike$$super$expectedTestCount:(Lorg/scalatest/Filter;)I
        17: ireturn
      LineNumberTable:
        line 494: 0
        line 495: 10
      LocalVariableTable:
        Start  Length  Slot  Name   Signature
            0      18     0  this   Lorg/scalatest/freespec/PathAnyFreeSpecLike;
            0      18     1 filter   Lorg/scalatest/Filter;
    MethodParameters:
      Name                           Flags
      filter                         final

  public static org.scalatest.Status runTest$(org.scalatest.freespec.PathAnyFreeSpecLike, java.lang.String, org.scalatest.Args);
    descriptor: (Lorg/scalatest/freespec/PathAnyFreeSpecLike;Ljava/lang/String;Lorg/scalatest/Args;)Lorg/scalatest/Status;
    flags: (0x1009) ACC_PUBLIC, ACC_STATIC, ACC_SYNTHETIC
    Code:
      stack=3, locals=3, args_size=3
         0: aload_0
         1: aload_1
         2: aload_2
         3: invokespecial #255                // InterfaceMethod runTest:(Ljava/lang/String;Lorg/scalatest/Args;)Lorg/scalatest/Status;
         6: areturn
      LineNumberTable:
        line 524: 0
      LocalVariableTable:
        Start  Length  Slot  Name   Signature
            0       7     0 $this   Lorg/scalatest/freespec/PathAnyFreeSpecLike;
            0       7     1 testName   Ljava/lang/String;
            0       7     2  args   Lorg/scalatest/Args;
    MethodParameters:
      Name                           Flags
      $this                          final synthetic
      testName                       final
      args                           final

  public default org.scalatest.Status runTest(java.lang.String, org.scalatest.Args);
    descriptor: (Ljava/lang/String;Lorg/scalatest/Args;)Lorg/scalatest/Status;
    flags: (0x0001) ACC_PUBLIC
    Code:
      stack=6, locals=3, args_size=3
         0: aload_0
         1: invokeinterface #80,  1           // InterfaceMethod org$scalatest$freespec$PathAnyFreeSpecLike$$engine:()Lorg/scalatest/PathEngine;
         6: aload_0
         7: invokevirtual #224                // Method org/scalatest/PathEngine.ensureTestResultsRegistered:(Lorg/scalatest/Suite;)V
        10: aload_0
        11: invokeinterface #80,  1           // InterfaceMethod org$scalatest$freespec$PathAnyFreeSpecLike$$engine:()Lorg/scalatest/PathEngine;
        16: aload_0
        17: aload_1
        18: aload_2
        19: iconst_1
        20: invokedynamic #267,  0            // InvokeDynamic #2:apply:()Lscala/Function1;
        25: invokevirtual #271                // Method org/scalatest/PathEngine.runTestImpl:(Lorg/scalatest/Suite;Ljava/lang/String;Lorg/scalatest/Args;ZLscala/Function1;)Lorg/scalatest/Status;
        28: areturn
      LineNumberTable:
        line 526: 0
        line 532: 10
      LocalVariableTable:
        Start  Length  Slot  Name   Signature
            0      29     0  this   Lorg/scalatest/freespec/PathAnyFreeSpecLike;
            0      29     1 testName   Ljava/lang/String;
            0      29     2  args   Lorg/scalatest/Args;
    MethodParameters:
      Name                           Flags
      testName                       final
      args                           final

  public static scala.collection.immutable.Map tags$(org.scalatest.freespec.PathAnyFreeSpecLike);
    descriptor: (Lorg/scalatest/freespec/PathAnyFreeSpecLike;)Lscala/collection/immutable/Map;
    flags: (0x1009) ACC_PUBLIC, ACC_STATIC, ACC_SYNTHETIC
    Code:
      stack=1, locals=1, args_size=1
         0: aload_0
         1: invokespecial #277                // InterfaceMethod tags:()Lscala/collection/immutable/Map;
         4: areturn
      LineNumberTable:
        line 561: 0
      LocalVariableTable:
        Start  Length  Slot  Name   Signature
            0       5     0 $this   Lorg/scalatest/freespec/PathAnyFreeSpecLike;
    MethodParameters:
      Name                           Flags
      $this                          final synthetic

  public default scala.collection.immutable.Map<java.lang.String, scala.collection.immutable.Set<java.lang.String>> tags();
    descriptor: ()Lscala/collection/immutable/Map;
    flags: (0x0001) ACC_PUBLIC
    Code:
      stack=3, locals=1, args_size=1
         0: aload_0
         1: invokeinterface #80,  1           // InterfaceMethod org$scalatest$freespec$PathAnyFreeSpecLike$$engine:()Lorg/scalatest/PathEngine;
         6: aload_0
         7: invokevirtual #224                // Method org/scalatest/PathEngine.ensureTestResultsRegistered:(Lorg/scalatest/Suite;)V
        10: getstatic     #283                // Field org/scalatest/Suite$.MODULE$:Lorg/scalatest/Suite$;
        13: aload_0
        14: invokeinterface #80,  1           // InterfaceMethod org$scalatest$freespec$PathAnyFreeSpecLike$$engine:()Lorg/scalatest/PathEngine;
        19: invokevirtual #232                // Method org/scalatest/PathEngine.atomic:()Ljava/util/concurrent/atomic/AtomicReference;
        22: invokevirtual #91                 // Method java/util/concurrent/atomic/AtomicReference.get:()Ljava/lang/Object;
        25: checkcast     #30                 // class org/scalatest/SuperEngine$Bundle
        28: invokevirtual #286                // Method org/scalatest/SuperEngine$Bundle.tagsMap:()Lscala/collection/immutable/Map;
        31: aload_0
        32: invokevirtual #290                // Method org/scalatest/Suite$.autoTagClassAnnotations:(Lscala/collection/immutable/Map;Lorg/scalatest/Suite;)Lscala/collection/immutable/Map;
        35: areturn
      LineNumberTable:
        line 562: 0
        line 563: 10
      LocalVariableTable:
        Start  Length  Slot  Name   Signature
            0      36     0  this   Lorg/scalatest/freespec/PathAnyFreeSpecLike;
    Signature: #278                         // ()Lscala/collection/immutable/Map<Ljava/lang/String;Lscala/collection/immutable/Set<Ljava/lang/String;>;>;

  public static org.scalatest.Status run$(org.scalatest.freespec.PathAnyFreeSpecLike, scala.Option, org.scalatest.Args);
    descriptor: (Lorg/scalatest/freespec/PathAnyFreeSpecLike;Lscala/Option;Lorg/scalatest/Args;)Lorg/scalatest/Status;
    flags: (0x1009) ACC_PUBLIC, ACC_STATIC, ACC_SYNTHETIC
    Code:
      stack=3, locals=3, args_size=3
         0: aload_0
         1: aload_1
         2: aload_2
         3: invokespecial #296                // InterfaceMethod run:(Lscala/Option;Lorg/scalatest/Args;)Lorg/scalatest/Status;
         6: areturn
      LineNumberTable:
        line 596: 0
      LocalVariableTable:
        Start  Length  Slot  Name   Signature
            0       7     0 $this   Lorg/scalatest/freespec/PathAnyFreeSpecLike;
            0       7     1 testName   Lscala/Option;
            0       7     2  args   Lorg/scalatest/Args;
    MethodParameters:
      Name                           Flags
      $this                          final synthetic
      testName                       final
      args                           final

  public default org.scalatest.Status run(scala.Option<java.lang.String>, org.scalatest.Args);
    descriptor: (Lscala/Option;Lorg/scalatest/Args;)Lorg/scalatest/Status;
    flags: (0x0001) ACC_PUBLIC
    Code:
      stack=7, locals=3, args_size=3
         0: aload_0
         1: invokeinterface #80,  1           // InterfaceMethod org$scalatest$freespec$PathAnyFreeSpecLike$$engine:()Lorg/scalatest/PathEngine;
         6: aload_0
         7: invokevirtual #224                // Method org/scalatest/PathEngine.ensureTestResultsRegistered:(Lorg/scalatest/Suite;)V
        10: aload_0
        11: invokeinterface #80,  1           // InterfaceMethod org$scalatest$freespec$PathAnyFreeSpecLike$$engine:()Lorg/scalatest/PathEngine;
        16: aload_0
        17: aload_1
        18: aload_2
        19: aload_0
        20: invokeinterface #78,  1           // InterfaceMethod info:()Lorg/scalatest/Informer;
        25: iconst_1
        26: aload_0
        27: invokedynamic #308,  0            // InvokeDynamic #3:apply:(Lorg/scalatest/freespec/PathAnyFreeSpecLike;)Lscala/Function2;
        32: invokevirtual #312                // Method org/scalatest/PathEngine.runPathTestsImpl:(Lorg/scalatest/Suite;Lscala/Option;Lorg/scalatest/Args;Lorg/scalatest/Informer;ZLscala/Function2;)Lorg/scalatest/Status;
        35: areturn
      LineNumberTable:
        line 599: 0
        line 600: 10
      LocalVariableTable:
        Start  Length  Slot  Name   Signature
            0      36     0  this   Lorg/scalatest/freespec/PathAnyFreeSpecLike;
            0      36     1 testName   Lscala/Option;
            0      36     2  args   Lorg/scalatest/Args;
    Signature: #298                         // (Lscala/Option<Ljava/lang/String;>;Lorg/scalatest/Args;)Lorg/scalatest/Status;
    MethodParameters:
      Name                           Flags
      testName                       final
      args                           final

  public static org.scalatest.Status runTests$(org.scalatest.freespec.PathAnyFreeSpecLike, scala.Option, org.scalatest.Args);
    descriptor: (Lorg/scalatest/freespec/PathAnyFreeSpecLike;Lscala/Option;Lorg/scalatest/Args;)Lorg/scalatest/Status;
    flags: (0x1009) ACC_PUBLIC, ACC_STATIC, ACC_SYNTHETIC
    Code:
      stack=3, locals=3, args_size=3
         0: aload_0
         1: aload_1
         2: aload_2
         3: invokespecial #316                // InterfaceMethod runTests:(Lscala/Option;Lorg/scalatest/Args;)Lorg/scalatest/Status;
         6: areturn
      LineNumberTable:
        line 612: 0
      LocalVariableTable:
        Start  Length  Slot  Name   Signature
            0       7     0 $this   Lorg/scalatest/freespec/PathAnyFreeSpecLike;
            0       7     1 testName   Lscala/Option;
            0       7     2  args   Lorg/scalatest/Args;
    MethodParameters:
      Name                           Flags
      $this                          final synthetic
      testName                       final
      args                           final

  public default org.scalatest.Status runTests(scala.Option<java.lang.String>, org.scalatest.Args);
    descriptor: (Lscala/Option;Lorg/scalatest/Args;)Lorg/scalatest/Status;
    flags: (0x0001) ACC_PUBLIC
    Code:
      stack=2, locals=3, args_size=3
         0: new           #318                // class java/lang/UnsupportedOperationException
         3: dup
         4: invokespecial #321                // Method java/lang/UnsupportedOperationException."<init>":()V
         7: athrow
      LineNumberTable:
        line 613: 0
      LocalVariableTable:
        Start  Length  Slot  Name   Signature
            0       8     0  this   Lorg/scalatest/freespec/PathAnyFreeSpecLike;
            0       8     1 testName   Lscala/Option;
            0       8     2  args   Lorg/scalatest/Args;
    Signature: #298                         // (Lscala/Option<Ljava/lang/String;>;Lorg/scalatest/Args;)Lorg/scalatest/Status;
    MethodParameters:
      Name                           Flags
      testName                       final
      args                           final

  public static org.scalatest.Status runNestedSuites$(org.scalatest.freespec.PathAnyFreeSpecLike, org.scalatest.Args);
    descriptor: (Lorg/scalatest/freespec/PathAnyFreeSpecLike;Lorg/scalatest/Args;)Lorg/scalatest/Status;
    flags: (0x1009) ACC_PUBLIC, ACC_STATIC, ACC_SYNTHETIC
    Code:
      stack=2, locals=2, args_size=2
         0: aload_0
         1: aload_1
         2: invokespecial #327                // InterfaceMethod runNestedSuites:(Lorg/scalatest/Args;)Lorg/scalatest/Status;
         5: areturn
      LineNumberTable:
        line 637: 0
      LocalVariableTable:
        Start  Length  Slot  Name   Signature
            0       6     0 $this   Lorg/scalatest/freespec/PathAnyFreeSpecLike;
            0       6     1  args   Lorg/scalatest/Args;
    MethodParameters:
      Name                           Flags
      $this                          final synthetic
      args                           final

  public default org.scalatest.Status runNestedSuites(org.scalatest.Args);
    descriptor: (Lorg/scalatest/Args;)Lorg/scalatest/Status;
    flags: (0x0001) ACC_PUBLIC
    Code:
      stack=1, locals=2, args_size=2
         0: getstatic     #332                // Field org/scalatest/SucceededStatus$.MODULE$:Lorg/scalatest/SucceededStatus$;
         3: areturn
      LineNumberTable:
        line 637: 0
      LocalVariableTable:
        Start  Length  Slot  Name   Signature
            0       4     0  this   Lorg/scalatest/freespec/PathAnyFreeSpecLike;
            0       4     1  args   Lorg/scalatest/Args;
    MethodParameters:
      Name                           Flags
      args                           final

  public static scala.collection.immutable.IndexedSeq nestedSuites$(org.scalatest.freespec.PathAnyFreeSpecLike);
    descriptor: (Lorg/scalatest/freespec/PathAnyFreeSpecLike;)Lscala/collection/immutable/IndexedSeq;
    flags: (0x1009) ACC_PUBLIC, ACC_STATIC, ACC_SYNTHETIC
    Code:
      stack=1, locals=1, args_size=1
         0: aload_0
         1: invokespecial #338                // InterfaceMethod nestedSuites:()Lscala/collection/immutable/IndexedSeq;
         4: areturn
      LineNumberTable:
        line 660: 0
      LocalVariableTable:
        Start  Length  Slot  Name   Signature
            0       5     0 $this   Lorg/scalatest/freespec/PathAnyFreeSpecLike;
    MethodParameters:
      Name                           Flags
      $this                          final synthetic

  public default scala.collection.immutable.IndexedSeq<org.scalatest.Suite> nestedSuites();
    descriptor: ()Lscala/collection/immutable/IndexedSeq;
    flags: (0x0001) ACC_PUBLIC
    Code:
      stack=1, locals=1, args_size=1
         0: getstatic     #344                // Field scala/package$.MODULE$:Lscala/package$;
         3: invokevirtual #348                // Method scala/package$.Vector:()Lscala/collection/immutable/Vector$;
         6: invokevirtual #354                // Method scala/collection/immutable/Vector$.empty:()Lscala/collection/immutable/Vector;
         9: areturn
      LineNumberTable:
        line 660: 0
      LocalVariableTable:
        Start  Length  Slot  Name   Signature
            0      10     0  this   Lorg/scalatest/freespec/PathAnyFreeSpecLike;
    Signature: #339                         // ()Lscala/collection/immutable/IndexedSeq<Lorg/scalatest/Suite;>;

  public abstract java.lang.String styleName();
    descriptor: ()Ljava/lang/String;
    flags: (0x0401) ACC_PUBLIC, ACC_ABSTRACT
    Deprecated: true

  public static org.scalatest.TestData testDataFor$(org.scalatest.freespec.PathAnyFreeSpecLike, java.lang.String, org.scalatest.ConfigMap);
    descriptor: (Lorg/scalatest/freespec/PathAnyFreeSpecLike;Ljava/lang/String;Lorg/scalatest/ConfigMap;)Lorg/scalatest/TestData;
    flags: (0x1009) ACC_PUBLIC, ACC_STATIC, ACC_SYNTHETIC
    Code:
      stack=3, locals=3, args_size=3
         0: aload_0
         1: aload_1
         2: aload_2
         3: invokespecial #362                // InterfaceMethod testDataFor:(Ljava/lang/String;Lorg/scalatest/ConfigMap;)Lorg/scalatest/TestData;
         6: areturn
      LineNumberTable:
        line 671: 0
      LocalVariableTable:
        Start  Length  Slot  Name   Signature
            0       7     0 $this   Lorg/scalatest/freespec/PathAnyFreeSpecLike;
            0       7     1 testName   Ljava/lang/String;
            0       7     2 theConfigMap   Lorg/scalatest/ConfigMap;
    MethodParameters:
      Name                           Flags
      $this                          final synthetic
      testName                       final
      theConfigMap                   final

  public default org.scalatest.TestData testDataFor(java.lang.String, org.scalatest.ConfigMap);
    descriptor: (Ljava/lang/String;Lorg/scalatest/ConfigMap;)Lorg/scalatest/TestData;
    flags: (0x0001) ACC_PUBLIC
    Code:
      stack=4, locals=3, args_size=3
         0: aload_0
         1: invokeinterface #80,  1           // InterfaceMethod org$scalatest$freespec$PathAnyFreeSpecLike$$engine:()Lorg/scalatest/PathEngine;
         6: aload_0
         7: invokevirtual #224                // Method org/scalatest/PathEngine.ensureTestResultsRegistered:(Lorg/scalatest/Suite;)V
        10: aload_0
        11: invokeinterface #80,  1           // InterfaceMethod org$scalatest$freespec$PathAnyFreeSpecLike$$engine:()Lorg/scalatest/PathEngine;
        16: aload_1
        17: aload_2
        18: aload_0
        19: invokevirtual #367                // Method org/scalatest/PathEngine.createTestDataFor:(Ljava/lang/String;Lorg/scalatest/ConfigMap;Lorg/scalatest/Suite;)Lorg/scalatest/TestData;
        22: areturn
      LineNumberTable:
        line 672: 0
        line 673: 10
      LocalVariableTable:
        Start  Length  Slot  Name   Signature
            0      23     0  this   Lorg/scalatest/freespec/PathAnyFreeSpecLike;
            0      23     1 testName   Ljava/lang/String;
            0      23     2 theConfigMap   Lorg/scalatest/ConfigMap;
    MethodParameters:
      Name                           Flags
      testName                       final
      theConfigMap                   final

  public static org.scalatest.ConfigMap testDataFor$default$2$(org.scalatest.freespec.PathAnyFreeSpecLike);
    descriptor: (Lorg/scalatest/freespec/PathAnyFreeSpecLike;)Lorg/scalatest/ConfigMap;
    flags: (0x1009) ACC_PUBLIC, ACC_STATIC, ACC_SYNTHETIC
    Code:
      stack=1, locals=1, args_size=1
         0: aload_0
         1: invokespecial #373                // InterfaceMethod testDataFor$default$2:()Lorg/scalatest/ConfigMap;
         4: areturn
      LineNumberTable:
        line 671: 0
      LocalVariableTable:
        Start  Length  Slot  Name   Signature
            0       5     0 $this   Lorg/scalatest/freespec/PathAnyFreeSpecLike;
    MethodParameters:
      Name                           Flags
      $this                          final synthetic

  public default org.scalatest.ConfigMap testDataFor$default$2();
    descriptor: ()Lorg/scalatest/ConfigMap;
    flags: (0x0001) ACC_PUBLIC
    Code:
      stack=1, locals=1, args_size=1
         0: getstatic     #378                // Field org/scalatest/ConfigMap$.MODULE$:Lorg/scalatest/ConfigMap$;
         3: invokevirtual #380                // Method org/scalatest/ConfigMap$.empty:()Lorg/scalatest/ConfigMap;
         6: areturn
      LineNumberTable:
        line 671: 0
      LocalVariableTable:
        Start  Length  Slot  Name   Signature
            0       7     0  this   Lorg/scalatest/freespec/PathAnyFreeSpecLike;

  public static java.lang.String $anonfun$registerTestToRun$1();
    descriptor: ()Ljava/lang/String;
    flags: (0x1009) ACC_PUBLIC, ACC_STATIC, ACC_SYNTHETIC
    Code:
      stack=1, locals=0, args_size=0
         0: getstatic     #385                // Field org/scalatest/Resources$.MODULE$:Lorg/scalatest/Resources$;
         3: invokevirtual #388                // Method org/scalatest/Resources$.itCannotAppearInsideAnotherIt:()Ljava/lang/String;
         6: areturn
      LineNumberTable:
        line 128: 0

  public static java.lang.String $anonfun$registerTestToIgnore$1();
    descriptor: ()Ljava/lang/String;
    flags: (0x1009) ACC_PUBLIC, ACC_STATIC, ACC_SYNTHETIC
    Code:
      stack=1, locals=0, args_size=0
         0: getstatic     #385                // Field org/scalatest/Resources$.MODULE$:Lorg/scalatest/Resources$;
         3: invokevirtual #391                // Method org/scalatest/Resources$.ignoreCannotAppearInsideAnIt:()Ljava/lang/String;
         6: areturn
      LineNumberTable:
        line 157: 0

  private static org.scalatest.Outcome dontInvokeWithFixture$1(org.scalatest.SuperEngine$TestLeaf);
    descriptor: (Lorg/scalatest/SuperEngine$TestLeaf;)Lorg/scalatest/Outcome;
    flags: (0x000a) ACC_PRIVATE, ACC_STATIC
    Code:
      stack=1, locals=1, args_size=1
         0: aload_0
         1: invokevirtual #395                // Method org/scalatest/SuperEngine$TestLeaf.testFun:()Ljava/lang/Object;
         4: checkcast     #397                // class scala/Function0
         7: invokeinterface #399,  1          // InterfaceMethod scala/Function0.apply:()Ljava/lang/Object;
        12: checkcast     #401                // class org/scalatest/Outcome
        15: areturn
      LineNumberTable:
        line 529: 0
      LocalVariableTable:
        Start  Length  Slot  Name   Signature
            0      16     0 theTest   Lorg/scalatest/SuperEngine$TestLeaf;
    MethodParameters:
      Name                           Flags
      theTest                        final

  public static org.scalatest.Outcome $anonfun$runTest$1(org.scalatest.SuperEngine$TestLeaf);
    descriptor: (Lorg/scalatest/SuperEngine$TestLeaf;)Lorg/scalatest/Outcome;
    flags: (0x1009) ACC_PUBLIC, ACC_STATIC, ACC_SYNTHETIC
    Code:
      stack=1, locals=1, args_size=1
         0: aload_0
         1: invokestatic  #404                // InterfaceMethod dontInvokeWithFixture$1:(Lorg/scalatest/SuperEngine$TestLeaf;)Lorg/scalatest/Outcome;
         4: areturn
      LineNumberTable:
        line 532: 0
      LocalVariableTable:
        Start  Length  Slot  Name   Signature
            0       5     0 theTest   Lorg/scalatest/SuperEngine$TestLeaf;
    MethodParameters:
      Name                           Flags
      theTest                        final

  public static org.scalatest.Status $anonfun$run$1(org.scalatest.freespec.PathAnyFreeSpecLike, java.lang.String, org.scalatest.Args);
    descriptor: (Lorg/scalatest/freespec/PathAnyFreeSpecLike;Ljava/lang/String;Lorg/scalatest/Args;)Lorg/scalatest/Status;
    flags: (0x1009) ACC_PUBLIC, ACC_STATIC, ACC_SYNTHETIC
    Code:
      stack=3, locals=3, args_size=3
         0: aload_0
         1: aload_1
         2: aload_2
         3: invokeinterface #255,  3          // InterfaceMethod runTest:(Ljava/lang/String;Lorg/scalatest/Args;)Lorg/scalatest/Status;
         8: areturn
      LineNumberTable:
        line 600: 0
      LocalVariableTable:
        Start  Length  Slot  Name   Signature
            0       9     0 $this   Lorg/scalatest/freespec/PathAnyFreeSpecLike;
            0       9     1 testName   Ljava/lang/String;
            0       9     2  args   Lorg/scalatest/Args;
    MethodParameters:
      Name                           Flags
      $this                          final synthetic
      testName                       final
      args                           final

  public static void $init$(org.scalatest.freespec.PathAnyFreeSpecLike);
    descriptor: (Lorg/scalatest/freespec/PathAnyFreeSpecLike;)V
    flags: (0x0009) ACC_PUBLIC, ACC_STATIC
    Code:
      stack=3, locals=1, args_size=1
         0: aload_0
         1: getstatic     #411                // Field org/scalatest/PathEngine$.MODULE$:Lorg/scalatest/PathEngine$;
         4: invokevirtual #414                // Method org/scalatest/PathEngine$.getEngine:()Lorg/scalatest/PathEngine;
         7: invokeinterface #416,  2          // InterfaceMethod org$scalatest$freespec$PathAnyFreeSpecLike$_setter_$org$scalatest$freespec$PathAnyFreeSpecLike$$engine_$eq:(Lorg/scalatest/PathEngine;)V
        12: aload_0
        13: new           #418                // class org/scalatest/verbs/BehaveWord
        16: dup
        17: invokespecial #419                // Method org/scalatest/verbs/BehaveWord."<init>":()V
        20: invokeinterface #421,  2          // InterfaceMethod org$scalatest$freespec$PathAnyFreeSpecLike$_setter_$behave_$eq:(Lorg/scalatest/verbs/BehaveWord;)V
        25: aload_0
        26: ldc_w         #423                // String org.scalatest.path.FreeSpec
        29: invokeinterface #425,  2          // InterfaceMethod org$scalatest$freespec$PathAnyFreeSpecLike$_setter_$styleName_$eq:(Ljava/lang/String;)V
        34: return
      LineNumberTable:
        line 52: 0
        line 417: 12
        line 669: 25
        line 50: 34
      LocalVariableTable:
        Start  Length  Slot  Name   Signature
            0      35     0 $this   Lorg/scalatest/freespec/PathAnyFreeSpecLike;
    MethodParameters:
      Name                           Flags
      $this                          final synthetic

  private static java.lang.Object $deserializeLambda$(java.lang.invoke.SerializedLambda);
    descriptor: (Ljava/lang/invoke/SerializedLambda;)Ljava/lang/Object;
    flags: (0x100a) ACC_PRIVATE, ACC_STATIC, ACC_SYNTHETIC
    Code:
      stack=1, locals=1, args_size=1
         0: aload_0
         1: invokedynamic #437,  0            // InvokeDynamic #4:lambdaDeserialize:(Ljava/lang/invoke/SerializedLambda;)Ljava/lang/Object;
         6: areturn
}
InnerClasses:
  public static final #28= #25 of #27;    // Lookup=class java/lang/invoke/MethodHandles$Lookup of class java/lang/invoke/MethodHandles
  public #33= #30 of #32;                 // Bundle=class org/scalatest/SuperEngine$Bundle of class org/scalatest/SuperEngine
  public #36= #35 of #32;                 // TestLeaf=class org/scalatest/SuperEngine$TestLeaf of class org/scalatest/SuperEngine
  public final #39= #38 of #2;            // FreeSpecStringWrapper=class org/scalatest/freespec/PathAnyFreeSpecLike$FreeSpecStringWrapper of class org/scalatest/freespec/PathAnyFreeSpecLike
  public final #42= #41 of #2;            // ResultOfTaggedAsInvocationOnString=class org/scalatest/freespec/PathAnyFreeSpecLike$ResultOfTaggedAsInvocationOnString of class org/scalatest/freespec/PathAnyFreeSpecLike
SourceFile: "PathAnyFreeSpecLike.scala"
RuntimeVisibleAnnotations:
  0: #18(#19=[s#20])
    org.scalatest.Finders(
      value=["org.scalatest.finders.FreeSpecFinder"]
    )
  1: #21(#22=s#23)
    scala.reflect.ScalaSignature(
      bytes="\u0006\u0005\t]eaB\u0015+!\u0003\r\t!\r\u0005\u0006\u0017\u0002!\t\u0001\u0014\u0005\b!\u0002\u0011\r\u0011\"\u0004R\u0011\u0015)\u0006\u0001\"\u0011W\u0011\u0015I\u0006\u0001\"\u0005[\u0011\u0015q\u0006\u0001\"\u0005`\u0011\u0015\u0019\u0007\u0001\"\u0005e\u0011\u0015A\u0007\u0001\"\u0005j\u0011\u0015i\u0007\u0001\"\u0003o\u0011\u001d\t9\u0004\u0001C\u0005\u0003s1a!!\u0012\u0001\u0015\u0005\u001d\u0003\u0002\u00039\u000b\u0005\u0003\u0005\u000b\u0011B9\t\u0013\u0005%#B!A!\u0002\u0013q\bBCA\u0013\u0015\t\u0005\t\u0015!\u0003\u0002(!9\u00111\n\u0006\u0005\u0002\u00055\u0003bBA-\u0015\u0011\u0005\u00111\f\u0005\b\u0003KRA\u0011AA4\u0011\u001d\t\u0019H\u0003C\u0001\u0003k2a!!\u001f\u0001\u0015\u0005m\u0004\"CA?%\t\u0005\t\u0015!\u0003r\u0011)\t)C\u0005B\u0001B\u0003%\u0011q\u0005\u0005\b\u0003\u0017\u0012B\u0011AA@\u0011\u001d\t9I\u0005C\u0001\u0003\u0013Cq!!\u0017\u0013\t\u0003\ty\tC\u0004\u0002tI!\t!!&\t\u000f\u0005\u0015$\u0003\"\u0001\u0002\u001a\"9\u0011Q\u0014\n\u0005\u0002\u0005}\u0005bBAX\u0001\u0011M\u0011\u0011\u0017\u0005\n\u0003w\u0003!\u0019!C\t\u0003{Cq!a3\u0001\t\u000b\ni\rC\u0004\u0002V\u0002!)%a6\t\u000f\u0005%\b\u0001\"\u0016\u0002l\"9\u0011\u0011\n\u0001\u0005F\t\u0005\u0001b\u0002B\u0005\u0001\u0011\u0015#1\u0002\u0005\b\u0005/\u0001AQ\u000bB\r\u0011\u001d\u0011y\u0002\u0001C+\u0005CAqA!\n\u0001\t\u000b\u00129\u0003C\u0005\u0003:\u0001\u0011\r\u0011\"\u0012\u0003<!9!\u0011\u000b\u0001\u0005B\tM\u0003\"\u0003B4\u0001E\u0005I\u0011\u0001B5\u00119\u0011y\b\u0001I\u0001\u0004\u0003\u0005I\u0011\u0002BA\u0005\u000b\u00131\u0003U1uQ\u0006s\u0017P\u0012:fKN\u0003Xm\u0019\'jW\u0016T!a\u000b\u0017\u0002\u0011\u0019\u0014X-Z:qK\u000eT!!\f\u0018\u0002\u0013M\u001c\u0017\r\\1uKN$(\"A\u0018\u0002\u0007=\u0014xm\u0001\u0001\u0014\u0011\u0001\u0011\u0004\bP C\u000b\"\u0003\"a\r\u001c\u000e\u0003QR\u0011!N\u0001\u0006g\u000e\fG.Y\u0005\u0003oQ\u0012a!\u00118z%\u00164\u0007CA\u001d;\u001b\u0005a\u0013BA\u001e-\u0005\u0015\u0019V/\u001b;f!\tIT(\u0003\u0002?Y\t\u0011rJ\\3J]N$\u0018M\\2f!\u0016\u0014H+Z:u!\tI\u0004)\u0003\u0002BY\tI\u0011J\u001c4pe6Lgn\u001a\t\u0003s\rK!\u0001\u0012\u0017\u0003\u00139{G/\u001b4zS:<\u0007CA\u001dG\u0013\t9EF\u0001\u0005BY\u0016\u0014H/\u001b8h!\tI\u0014*\u0003\u0002KY\tYAi\\2v[\u0016tG/\u001b8h\u0003\u0019!\u0013N\\5uIQ\tQ\n\u0005\u00024\u001d&\u0011q\n\u000e\u0002\u0005+:LG/\u0001\u0004f]\u001eLg.Z\u000b\u0002%B\u0011\u0011hU\u0005\u0003)2\u0012!\u0002U1uQ\u0016sw-\u001b8f\u0003-qWm^%ogR\fgnY3\u0016\u0003]\u0003\"\u0001\u0017\u0001\u000e\u0003)\nA!\u001b8g_V\t1\f\u0005\u0002:9&\u0011Q\f\f\u0002\t\u0013:4wN]7fe\u0006!an\u001c;f+\u0005\u0001\u0007CA\u001db\u0013\t\u0011GF\u0001\u0005O_RLg-[3s\u0003\u0015\tG.\u001a:u+\u0005)\u0007CA\u001dg\u0013\t9GFA\u0004BY\u0016\u0014H/\u001a:\u0002\r5\f\'o[;q+\u0005Q\u0007CA\u001dl\u0013\taGF\u0001\u0006E_\u000e,X.\u001a8uKJ\f\u0011C]3hSN$XM\u001d+fgR$vNU;o)%iu\u000e`A\u000b\u00033\t\u0019\u0003C\u0003q\u0011\u0001\u0007\u0011/\u0001\u0005ta\u0016\u001cG+\u001a=u!\t\u0011\u0018P\u0004\u0002toB\u0011A\u000fN\u0007\u0002k*\u0011a\u000fM\u0001\u0007yI|w\u000e\u001e \n\u0005a$\u0014A\u0002)sK\u0012,g-\u0003\u0002{w\n11\u000b\u001e:j]\u001eT!\u0001\u001f\u001b\t\u000buD\u0001\u0019\u0001@\u0002\u0011Q,7\u000f\u001e+bON\u0004Ra`A\u0005\u0003\u001fqA!!\u0001\u0002\u00069\u0019A/a\u0001\n\u0003UJ1!a\u00025\u0003\u001d\u0001\u0018mY6bO\u0016LA!a\u0003\u0002\u000e\t!A*[:u\u0015\r\t9\u0001\u000e\t\u0004s\u0005E\u0011bAA\nY\t\u0019A+Y4\t\r\u0005]\u0001\u00021\u0001r\u0003)iW\r\u001e5pI:\u000bW.\u001a\u0005\b\u00037A\u0001\u0019AA\u000f\u0003\u001d!Xm\u001d;Gk:\u0004BaMA\u0010\u001b&\u0019\u0011\u0011\u0005\u001b\u0003\u0013\u0019+hn\u0019;j_:\u0004\u0004bBA\u0013\u0011\u0001\u0007\u0011qE\u0001\u0004a>\u001c\b\u0003BA\u0015\u0003gi!!a\u000b\u000b\t\u00055\u0012qF\u0001\u0007g>,(oY3\u000b\u0007\u0005Eb&A\u0005tG\u0006d\u0017m\u0019;jG&!\u0011QGA\u0016\u0005!\u0001vn]5uS>t\u0017\u0001\u0006:fO&\u001cH/\u001a:UKN$Hk\\%h]>\u0014X\rF\u0006N\u0003w\ti$a\u0010\u0002B\u0005\r\u0003\"\u00029\n\u0001\u0004\t\b\"B?\n\u0001\u0004q\bBBA\f\u0013\u0001\u0007\u0011\u000fC\u0004\u0002\u001c%\u0001\r!!\b\t\u000f\u0005\u0015\u0012\u00021\u0001\u0002(\t\u0011#+Z:vYR|e\rV1hO\u0016$\u0017i]%om>\u001c\u0017\r^5p]>s7\u000b\u001e:j]\u001e\u001c\"A\u0003\u001a\u0002\tQ\fwm]\u0001\u0007y%t\u0017\u000e\u001e \u0015\u0011\u0005=\u00131KA+\u0003/\u00022!!\u0015\u000b\u001b\u0005\u0001\u0001\"\u00029\u000f\u0001\u0004\t\bBBA%\u001d\u0001\u0007a\u0010C\u0004\u0002&9\u0001\r!a\n\u0002\u0005%tGcA\'\u0002^!A\u00111D\b\u0005\u0002\u0004\ty\u0006\u0005\u00034\u0003Cj\u0015bAA2i\tAAHY=oC6,g(\u0001\u0002jgR\u0019Q*!\u001b\t\u0011\u0005m\u0001\u0003\"a\u0001\u0003W\u0002RaMA1\u0003[\u00022!OA8\u0013\r\t\t\b\f\u0002\u0011!\u0016tG-\u001b8h\'R\fG/Z7f]R\fa![4o_J,GcA\'\u0002x!A\u00111D\t\u0005\u0002\u0004\tyFA\u000bGe\u0016,7\u000b]3d\'R\u0014\u0018N\\4Xe\u0006\u0004\b/\u001a:\u0014\u0005I\u0011\u0014AB:ue&tw\r\u0006\u0004\u0002\u0002\u0006\r\u0015Q\u0011\t\u0004\u0003#\u0012\u0002BBA?+\u0001\u0007\u0011\u000fC\u0004\u0002&U\u0001\r!a\n\u0002\r\u0011j\u0017N\\;t)\ri\u00151\u0012\u0005\t\u0003\u001b3B\u00111\u0001\u0002`\u0005\u0019a-\u001e8\u0015\u00075\u000b\t\n\u0003\u0005\u0002\u0014^!\t\u0019AA0\u0003\u00051GcA\'\u0002\u0018\"A\u00111\u0013\r\u0005\u0002\u0004\ty\u0006F\u0002N\u00037C\u0001\"a%\u001a\t\u0003\u0007\u00111N\u0001\ti\u0006<w-\u001a3BgR1\u0011qJAQ\u0003KCq!a)\u001b\u0001\u0004\ty!\u0001\u0007gSJ\u001cH\u000fV3tiR\u000bw\rC\u0004\u0002(j\u0001\r!!+\u0002\u001b=$\b.\u001a:UKN$H+Y4t!\u0015\u0019\u00141VA\b\u0013\r\ti\u000b\u000e\u0002\u000byI,\u0007/Z1uK\u0012t\u0014AH2p]Z,\'\u000f\u001e+p\rJ,Wm\u00159fGN#(/\u001b8h/J\f\u0007\u000f]3s)\u0011\t\u0019,a.\u0015\t\u0005\u0005\u0015Q\u0017\u0005\b\u0003KY\u00029AA\u0014\u0011\u0019\tIl\u0007a\u0001c\u0006\t1/\u0001\u0004cK\"\fg/Z\u000b\u0003\u0003\u007f\u0003B!!1\u0002H6\u0011\u00111\u0019\u0006\u0004\u0003\u000bd\u0013!\u0002<fe\n\u001c\u0018\u0002BAe\u0003\u0007\u0014!BQ3iCZ,wk\u001c:e\u0003%!Xm\u001d;OC6,7/\u0006\u0002\u0002PB!!/!5r\u0013\r\t\u0019n\u001f\u0002\u0004\'\u0016$\u0018!E3ya\u0016\u001cG/\u001a3UKN$8i\\;oiR!\u0011\u0011\\Ap!\r\u0019\u00141\\\u0005\u0004\u0003;$$aA%oi\"9\u0011\u0011\u001d\u0010A\u0002\u0005\r\u0018A\u00024jYR,\'\u000fE\u0002:\u0003KL1!a:-\u0005\u00191\u0015\u000e\u001c;fe\u00069!/\u001e8UKN$HCBAw\u0003g\f9\u0010E\u0002:\u0003_L1!!=-\u0005\u0019\u0019F/\u0019;vg\"1\u0011Q_\u0010A\u0002E\f\u0001\u0002^3ti:\u000bW.\u001a\u0005\b\u0003s|\u0002\u0019AA~\u0003\u0011\t\'oZ:\u0011\u0007e\ni0C\u0002\u0002\u00002\u0012A!\u0011:hgV\u0011!1\u0001\t\u0007e\n\u0015\u0011/a4\n\u0007\t\u001d1PA\u0002NCB\f1A];o)\u0019\tiO!\u0004\u0003\u0016!9\u0011Q_\u0011A\u0002\t=\u0001\u0003B\u001a\u0003\u0012EL1Aa\u00055\u0005\u0019y\u0005\u000f^5p]\"9\u0011\u0011`\u0011A\u0002\u0005m\u0018\u0001\u0003:v]R+7\u000f^:\u0015\r\u00055(1\u0004B\u000f\u0011\u001d\t)P\ta\u0001\u0005\u001fAq!!?#\u0001\u0004\tY0A\bsk:tUm\u001d;fIN+\u0018\u000e^3t)\u0011\tiOa\t\t\u000f\u0005e8\u00051\u0001\u0002|\u0006aa.Z:uK\u0012\u001cV/\u001b;fgV\u0011!\u0011\u0006\t\u0006\u0005W\u0011)\u0004O\u0007\u0003\u0005[QAAa\f\u00032\u0005I\u0011.\\7vi\u0006\u0014G.\u001a\u0006\u0004\u0005g!\u0014AC2pY2,7\r^5p]&!!q\u0007B\u0017\u0005)Ie\u000eZ3yK\u0012\u001cV-]\u0001\ngRLH.\u001a(b[\u0016,\u0012!\u001d\u0015\fK\t}\"Q\tB$\u0005\u0017\u0012i\u0005E\u00024\u0005\u0003J1Aa\u00115\u0005)!W\r\u001d:fG\u0006$X\rZ\u0001\b[\u0016\u001c8/Y4fC\t\u0011I%\u0001?UQ\u0016\u00043\u000f^=mK:\u000bW.\u001a\u0011mS\u001a,7-_2mK\u0002jW\r\u001e5pI\u0002B\u0017m\u001d\u0011cK\u0016t\u0007\u0005Z3qe\u0016\u001c\u0017\r^3eA\u0005tG\rI<jY2\u0004#-\u001a\u0011sK6|g/\u001a3!S:\u0004\u0013\r\t4viV\u0014X\r\t<feNLwN\u001c\u0011pM\u0002\u001a6-\u00197b)\u0016\u001cH\u000fI<ji\"\u0004cn\u001c\u0011sKBd\u0017mY3nK:$h&A\u0003tS:\u001cW-\t\u0002\u0003P\u0005)1GL\u0019/a\u0005YA/Z:u\t\u0006$\u0018MR8s)\u0019\u0011)Fa\u0017\u0003^A\u0019\u0011Ha\u0016\n\u0007\teCF\u0001\u0005UKN$H)\u0019;b\u0011\u0019\t)P\na\u0001c\"I!q\f\u0014\u0011\u0002\u0003\u0007!\u0011M\u0001\ri\",7i\u001c8gS\u001el\u0015\r\u001d\t\u0004s\t\r\u0014b\u0001B3Y\tI1i\u001c8gS\u001el\u0015\r]\u0001\u0016i\u0016\u001cH\u000fR1uC\u001a{\'\u000f\n3fM\u0006,H\u000e\u001e\u00133+\t\u0011YG\u000b\u0003\u0003b\t54F\u0001B8!\u0011\u0011\tHa\u001f\u000e\u0005\tM$\u0002\u0002B;\u0005o\n\u0011\"\u001e8dQ\u0016\u001c7.\u001a3\u000b\u0007\teD\'\u0001\u0006b]:|G/\u0019;j_:LAA! \u0003t\t\tRO\\2iK\u000e\\W\r\u001a,be&\fgnY3\u0002/M,\b/\u001a:%Kb\u0004Xm\u0019;fIR+7\u000f^\"pk:$H\u0003BAm\u0005\u0007Cq!!9)\u0001\u0004\t\u0019/C\u0002\u0002VjBs\u0001\u0001BE\u0005\u001f\u0013\t\nE\u0002:\u0005\u0017K1A!$-\u0005\u001d1\u0015N\u001c3feN\fQA^1mk\u0016d#Aa%\"\u0005\tU\u0015\u0001J8sO:\u001a8-\u00197bi\u0016\u001cHO\f4j]\u0012,\'o\u001d\u0018Ge\u0016,7\u000b]3d\r&tG-\u001a:"
    )
BootstrapMethods:
  0: #164 REF_invokeStatic java/lang/invoke/LambdaMetafactory.altMetafactory:(Ljava/lang/invoke/MethodHandles$Lookup;Ljava/lang/String;Ljava/lang/invoke/MethodType;[Ljava/lang/Object;)Ljava/lang/invoke/CallSite;
    Method arguments:
      #149 ()Ljava/lang/Object;
      #154 REF_invokeStatic org/scalatest/freespec/PathAnyFreeSpecLike.$anonfun$registerTestToRun$1:()Ljava/lang/String;
      #155 ()Ljava/lang/String;
      #156 5
      #157 1
      #155 ()Ljava/lang/String;
  1: #164 REF_invokeStatic java/lang/invoke/LambdaMetafactory.altMetafactory:(Ljava/lang/invoke/MethodHandles$Lookup;Ljava/lang/String;Ljava/lang/invoke/MethodType;[Ljava/lang/Object;)Ljava/lang/invoke/CallSite;
    Method arguments:
      #149 ()Ljava/lang/Object;
      #196 REF_invokeStatic org/scalatest/freespec/PathAnyFreeSpecLike.$anonfun$registerTestToIgnore$1:()Ljava/lang/String;
      #155 ()Ljava/lang/String;
      #156 5
      #157 1
      #155 ()Ljava/lang/String;
  2: #164 REF_invokeStatic java/lang/invoke/LambdaMetafactory.altMetafactory:(Ljava/lang/invoke/MethodHandles$Lookup;Ljava/lang/String;Ljava/lang/invoke/MethodType;[Ljava/lang/Object;)Ljava/lang/invoke/CallSite;
    Method arguments:
      #258 (Ljava/lang/Object;)Ljava/lang/Object;
      #263 REF_invokeStatic org/scalatest/freespec/PathAnyFreeSpecLike.$anonfun$runTest$1:(Lorg/scalatest/SuperEngine$TestLeaf;)Lorg/scalatest/Outcome;
      #264 (Lorg/scalatest/SuperEngine$TestLeaf;)Lorg/scalatest/Outcome;
      #156 5
      #157 1
      #264 (Lorg/scalatest/SuperEngine$TestLeaf;)Lorg/scalatest/Outcome;
  3: #164 REF_invokeStatic java/lang/invoke/LambdaMetafactory.altMetafactory:(Ljava/lang/invoke/MethodHandles$Lookup;Ljava/lang/String;Ljava/lang/invoke/MethodType;[Ljava/lang/Object;)Ljava/lang/invoke/CallSite;
    Method arguments:
      #300 (Ljava/lang/Object;Ljava/lang/Object;)Ljava/lang/Object;
      #304 REF_invokeStatic org/scalatest/freespec/PathAnyFreeSpecLike.$anonfun$run$1:(Lorg/scalatest/freespec/PathAnyFreeSpecLike;Ljava/lang/String;Lorg/scalatest/Args;)Lorg/scalatest/Status;
      #305 (Ljava/lang/String;Lorg/scalatest/Args;)Lorg/scalatest/Status;
      #156 5
      #157 1
      #305 (Ljava/lang/String;Lorg/scalatest/Args;)Lorg/scalatest/Status;
  4: #434 REF_invokeStatic scala/runtime/LambdaDeserialize.bootstrap:(Ljava/lang/invoke/MethodHandles$Lookup;Ljava/lang/String;Ljava/lang/invoke/MethodType;[Ljava/lang/invoke/MethodHandle;)Ljava/lang/invoke/CallSite;
    Method arguments:
      #196 REF_invokeStatic org/scalatest/freespec/PathAnyFreeSpecLike.$anonfun$registerTestToIgnore$1:()Ljava/lang/String;
      #154 REF_invokeStatic org/scalatest/freespec/PathAnyFreeSpecLike.$anonfun$registerTestToRun$1:()Ljava/lang/String;
      #304 REF_invokeStatic org/scalatest/freespec/PathAnyFreeSpecLike.$anonfun$run$1:(Lorg/scalatest/freespec/PathAnyFreeSpecLike;Ljava/lang/String;Lorg/scalatest/Args;)Lorg/scalatest/Status;
      #263 REF_invokeStatic org/scalatest/freespec/PathAnyFreeSpecLike.$anonfun$runTest$1:(Lorg/scalatest/SuperEngine$TestLeaf;)Lorg/scalatest/Outcome;
  ScalaInlineInfo: length = 0xF9 (unknown attribute)
   01 00 00 31 00 C1 00 97 01 00 96 00 97 01 01 2D
   00 F9 01 01 03 01 04 01 01 95 01 96 01 00 6B 00
   6C 00 00 69 00 6A 01 00 D4 00 D5 00 00 CD 00 CE
   00 00 CA 00 CB 01 01 88 01 04 01 00 F2 00 33 01
   00 F0 00 F1 01 00 4B 00 4C 00 00 49 00 4A 01 00
   76 00 77 00 00 74 00 75 01 01 4F 01 50 01 01 4D
   01 4E 01 00 3A 00 3B 00 00 37 00 38 01 00 60 00
   61 00 00 5E 00 5F 01 00 35 00 36 00 00 BE 00 87
   01 00 BD 00 80 01 00 86 00 87 01 00 7F 00 80 01
   00 32 00 33 01 00 2E 00 2F 00 00 2B 00 2C 00 00
   30 00 31 00 01 25 01 26 01 01 23 01 24 01 01 44
   01 45 01 01 42 01 43 01 00 FC 00 FD 01 00 F8 00
   F9 01 01 3A 01 26 01 01 39 01 24 01 01 63 00 97
   00 01 12 01 13 01 01 10 01 11 01 01 67 01 68 00
   01 64 01 65 01 01 72 01 73 00 01 70 01 71 01 00
   D8 00 D9 01 00 D6 00 D7 01
  ScalaSig: length = 0x3 (unknown attribute)
   05 02 00
