Classfile /Users/mw/Projects/slang-braindump/.jar/jar8/assemble/slang-braindump/assemble/content/com/fasterxml/jackson/core/format/DataFormatMatcher.class
  Last modified May 29, 2022; size 2881 bytes
  SHA-256 checksum 9d0c2eb796dabfbfbbca342010f325f9031966ed58f30c76b0c1508073c551c7
  Compiled from "DataFormatMatcher.java"
public class com.fasterxml.jackson.core.format.DataFormatMatcher
  minor version: 0
  major version: 50
  flags: (0x0021) ACC_PUBLIC, ACC_SUPER
  this_class: #25                         // com/fasterxml/jackson/core/format/DataFormatMatcher
  super_class: #10                        // java/lang/Object
  interfaces: 0, fields: 6, methods: 7, attributes: 1
Constant pool:
    #1 = Methodref          #10.#73       // java/lang/Object."<init>":()V
    #2 = Fieldref           #25.#74       // com/fasterxml/jackson/core/format/DataFormatMatcher._originalStream:Ljava/io/InputStream;
    #3 = Fieldref           #25.#75       // com/fasterxml/jackson/core/format/DataFormatMatcher._bufferedData:[B
    #4 = Fieldref           #25.#76       // com/fasterxml/jackson/core/format/DataFormatMatcher._bufferedStart:I
    #5 = Fieldref           #25.#77       // com/fasterxml/jackson/core/format/DataFormatMatcher._bufferedLength:I
    #6 = Fieldref           #25.#78       // com/fasterxml/jackson/core/format/DataFormatMatcher._match:Lcom/fasterxml/jackson/core/JsonFactory;
    #7 = Fieldref           #25.#79       // com/fasterxml/jackson/core/format/DataFormatMatcher._matchStrength:Lcom/fasterxml/jackson/core/format/MatchStrength;
    #8 = Class              #80           // java/lang/IllegalArgumentException
    #9 = String             #81           // Illegal start/length (%d/%d) wrt input array of %d bytes
   #10 = Class              #82           // java/lang/Object
   #11 = Methodref          #83.#84       // java/lang/Integer.valueOf:(I)Ljava/lang/Integer;
   #12 = Methodref          #85.#86       // java/lang/String.format:(Ljava/lang/String;[Ljava/lang/Object;)Ljava/lang/String;
   #13 = Methodref          #8.#87        // java/lang/IllegalArgumentException."<init>":(Ljava/lang/String;)V
   #14 = Fieldref           #88.#89       // com/fasterxml/jackson/core/format/MatchStrength.INCONCLUSIVE:Lcom/fasterxml/jackson/core/format/MatchStrength;
   #15 = Methodref          #25.#90       // com/fasterxml/jackson/core/format/DataFormatMatcher.hasMatch:()Z
   #16 = Methodref          #25.#91       // com/fasterxml/jackson/core/format/DataFormatMatcher.getMatch:()Lcom/fasterxml/jackson/core/JsonFactory;
   #17 = Methodref          #92.#93       // com/fasterxml/jackson/core/JsonFactory.getFormatName:()Ljava/lang/String;
   #18 = Methodref          #92.#94       // com/fasterxml/jackson/core/JsonFactory.createParser:([BII)Lcom/fasterxml/jackson/core/JsonParser;
   #19 = Methodref          #25.#95       // com/fasterxml/jackson/core/format/DataFormatMatcher.getDataStream:()Ljava/io/InputStream;
   #20 = Methodref          #92.#96       // com/fasterxml/jackson/core/JsonFactory.createParser:(Ljava/io/InputStream;)Lcom/fasterxml/jackson/core/JsonParser;
   #21 = Class              #97           // java/io/ByteArrayInputStream
   #22 = Methodref          #21.#98       // java/io/ByteArrayInputStream."<init>":([BII)V
   #23 = Class              #99           // com/fasterxml/jackson/core/io/MergedStream
   #24 = Methodref          #23.#100      // com/fasterxml/jackson/core/io/MergedStream."<init>":(Lcom/fasterxml/jackson/core/io/IOContext;Ljava/io/InputStream;[BII)V
   #25 = Class              #101          // com/fasterxml/jackson/core/format/DataFormatMatcher
   #26 = Utf8               _originalStream
   #27 = Utf8               Ljava/io/InputStream;
   #28 = Utf8               _bufferedData
   #29 = Utf8               [B
   #30 = Utf8               _bufferedStart
   #31 = Utf8               I
   #32 = Utf8               _bufferedLength
   #33 = Utf8               _match
   #34 = Utf8               Lcom/fasterxml/jackson/core/JsonFactory;
   #35 = Utf8               _matchStrength
   #36 = Utf8               Lcom/fasterxml/jackson/core/format/MatchStrength;
   #37 = Utf8               <init>
   #38 = Utf8               (Ljava/io/InputStream;[BIILcom/fasterxml/jackson/core/JsonFactory;Lcom/fasterxml/jackson/core/format/MatchStrength;)V
   #39 = Utf8               Code
   #40 = Utf8               LineNumberTable
   #41 = Utf8               LocalVariableTable
   #42 = Utf8               this
   #43 = Utf8               Lcom/fasterxml/jackson/core/format/DataFormatMatcher;
   #44 = Utf8               in
   #45 = Utf8               buffered
   #46 = Utf8               bufferedStart
   #47 = Utf8               bufferedLength
   #48 = Utf8               match
   #49 = Utf8               strength
   #50 = Utf8               StackMapTable
   #51 = Class              #101          // com/fasterxml/jackson/core/format/DataFormatMatcher
   #52 = Class              #102          // java/io/InputStream
   #53 = Class              #29           // "[B"
   #54 = Class              #103          // com/fasterxml/jackson/core/JsonFactory
   #55 = Class              #104          // com/fasterxml/jackson/core/format/MatchStrength
   #56 = Utf8               hasMatch
   #57 = Utf8               ()Z
   #58 = Utf8               getMatchStrength
   #59 = Utf8               ()Lcom/fasterxml/jackson/core/format/MatchStrength;
   #60 = Utf8               getMatch
   #61 = Utf8               ()Lcom/fasterxml/jackson/core/JsonFactory;
   #62 = Utf8               getMatchedFormatName
   #63 = Utf8               ()Ljava/lang/String;
   #64 = Class              #105          // java/lang/String
   #65 = Utf8               createParserWithMatch
   #66 = Utf8               ()Lcom/fasterxml/jackson/core/JsonParser;
   #67 = Utf8               Exceptions
   #68 = Class              #106          // java/io/IOException
   #69 = Utf8               getDataStream
   #70 = Utf8               ()Ljava/io/InputStream;
   #71 = Utf8               SourceFile
   #72 = Utf8               DataFormatMatcher.java
   #73 = NameAndType        #37:#107      // "<init>":()V
   #74 = NameAndType        #26:#27       // _originalStream:Ljava/io/InputStream;
   #75 = NameAndType        #28:#29       // _bufferedData:[B
   #76 = NameAndType        #30:#31       // _bufferedStart:I
   #77 = NameAndType        #32:#31       // _bufferedLength:I
   #78 = NameAndType        #33:#34       // _match:Lcom/fasterxml/jackson/core/JsonFactory;
   #79 = NameAndType        #35:#36       // _matchStrength:Lcom/fasterxml/jackson/core/format/MatchStrength;
   #80 = Utf8               java/lang/IllegalArgumentException
   #81 = Utf8               Illegal start/length (%d/%d) wrt input array of %d bytes
   #82 = Utf8               java/lang/Object
   #83 = Class              #108          // java/lang/Integer
   #84 = NameAndType        #109:#110     // valueOf:(I)Ljava/lang/Integer;
   #85 = Class              #105          // java/lang/String
   #86 = NameAndType        #111:#112     // format:(Ljava/lang/String;[Ljava/lang/Object;)Ljava/lang/String;
   #87 = NameAndType        #37:#113      // "<init>":(Ljava/lang/String;)V
   #88 = Class              #104          // com/fasterxml/jackson/core/format/MatchStrength
   #89 = NameAndType        #114:#36      // INCONCLUSIVE:Lcom/fasterxml/jackson/core/format/MatchStrength;
   #90 = NameAndType        #56:#57       // hasMatch:()Z
   #91 = NameAndType        #60:#61       // getMatch:()Lcom/fasterxml/jackson/core/JsonFactory;
   #92 = Class              #103          // com/fasterxml/jackson/core/JsonFactory
   #93 = NameAndType        #115:#63      // getFormatName:()Ljava/lang/String;
   #94 = NameAndType        #116:#117     // createParser:([BII)Lcom/fasterxml/jackson/core/JsonParser;
   #95 = NameAndType        #69:#70       // getDataStream:()Ljava/io/InputStream;
   #96 = NameAndType        #116:#118     // createParser:(Ljava/io/InputStream;)Lcom/fasterxml/jackson/core/JsonParser;
   #97 = Utf8               java/io/ByteArrayInputStream
   #98 = NameAndType        #37:#119      // "<init>":([BII)V
   #99 = Utf8               com/fasterxml/jackson/core/io/MergedStream
  #100 = NameAndType        #37:#120      // "<init>":(Lcom/fasterxml/jackson/core/io/IOContext;Ljava/io/InputStream;[BII)V
  #101 = Utf8               com/fasterxml/jackson/core/format/DataFormatMatcher
  #102 = Utf8               java/io/InputStream
  #103 = Utf8               com/fasterxml/jackson/core/JsonFactory
  #104 = Utf8               com/fasterxml/jackson/core/format/MatchStrength
  #105 = Utf8               java/lang/String
  #106 = Utf8               java/io/IOException
  #107 = Utf8               ()V
  #108 = Utf8               java/lang/Integer
  #109 = Utf8               valueOf
  #110 = Utf8               (I)Ljava/lang/Integer;
  #111 = Utf8               format
  #112 = Utf8               (Ljava/lang/String;[Ljava/lang/Object;)Ljava/lang/String;
  #113 = Utf8               (Ljava/lang/String;)V
  #114 = Utf8               INCONCLUSIVE
  #115 = Utf8               getFormatName
  #116 = Utf8               createParser
  #117 = Utf8               ([BII)Lcom/fasterxml/jackson/core/JsonParser;
  #118 = Utf8               (Ljava/io/InputStream;)Lcom/fasterxml/jackson/core/JsonParser;
  #119 = Utf8               ([BII)V
  #120 = Utf8               (Lcom/fasterxml/jackson/core/io/IOContext;Ljava/io/InputStream;[BII)V
{
  protected final java.io.InputStream _originalStream;
    descriptor: Ljava/io/InputStream;
    flags: (0x0014) ACC_PROTECTED, ACC_FINAL

  protected final byte[] _bufferedData;
    descriptor: [B
    flags: (0x0014) ACC_PROTECTED, ACC_FINAL

  protected final int _bufferedStart;
    descriptor: I
    flags: (0x0014) ACC_PROTECTED, ACC_FINAL

  protected final int _bufferedLength;
    descriptor: I
    flags: (0x0014) ACC_PROTECTED, ACC_FINAL

  protected final com.fasterxml.jackson.core.JsonFactory _match;
    descriptor: Lcom/fasterxml/jackson/core/JsonFactory;
    flags: (0x0014) ACC_PROTECTED, ACC_FINAL

  protected final com.fasterxml.jackson.core.format.MatchStrength _matchStrength;
    descriptor: Lcom/fasterxml/jackson/core/format/MatchStrength;
    flags: (0x0014) ACC_PROTECTED, ACC_FINAL

  protected com.fasterxml.jackson.core.format.DataFormatMatcher(java.io.InputStream, byte[], int, int, com.fasterxml.jackson.core.JsonFactory, com.fasterxml.jackson.core.format.MatchStrength);
    descriptor: (Ljava/io/InputStream;[BIILcom/fasterxml/jackson/core/JsonFactory;Lcom/fasterxml/jackson/core/format/MatchStrength;)V
    flags: (0x0004) ACC_PROTECTED
    Code:
      stack=7, locals=7, args_size=7
         0: aload_0
         1: invokespecial #1                  // Method java/lang/Object."<init>":()V
         4: aload_0
         5: aload_1
         6: putfield      #2                  // Field _originalStream:Ljava/io/InputStream;
         9: aload_0
        10: aload_2
        11: putfield      #3                  // Field _bufferedData:[B
        14: aload_0
        15: iload_3
        16: putfield      #4                  // Field _bufferedStart:I
        19: aload_0
        20: iload         4
        22: putfield      #5                  // Field _bufferedLength:I
        25: aload_0
        26: aload         5
        28: putfield      #6                  // Field _match:Lcom/fasterxml/jackson/core/JsonFactory;
        31: aload_0
        32: aload         6
        34: putfield      #7                  // Field _matchStrength:Lcom/fasterxml/jackson/core/format/MatchStrength;
        37: iload_3
        38: iload         4
        40: ior
        41: iflt          53
        44: iload_3
        45: iload         4
        47: iadd
        48: aload_2
        49: arraylength
        50: if_icmple     93
        53: new           #8                  // class java/lang/IllegalArgumentException
        56: dup
        57: ldc           #9                  // String Illegal start/length (%d/%d) wrt input array of %d bytes
        59: iconst_3
        60: anewarray     #10                 // class java/lang/Object
        63: dup
        64: iconst_0
        65: iload_3
        66: invokestatic  #11                 // Method java/lang/Integer.valueOf:(I)Ljava/lang/Integer;
        69: aastore
        70: dup
        71: iconst_1
        72: iload         4
        74: invokestatic  #11                 // Method java/lang/Integer.valueOf:(I)Ljava/lang/Integer;
        77: aastore
        78: dup
        79: iconst_2
        80: aload_2
        81: arraylength
        82: invokestatic  #11                 // Method java/lang/Integer.valueOf:(I)Ljava/lang/Integer;
        85: aastore
        86: invokestatic  #12                 // Method java/lang/String.format:(Ljava/lang/String;[Ljava/lang/Object;)Ljava/lang/String;
        89: invokespecial #13                 // Method java/lang/IllegalArgumentException."<init>":(Ljava/lang/String;)V
        92: athrow
        93: return
      LineNumberTable:
        line 45: 0
        line 46: 4
        line 47: 9
        line 48: 14
        line 49: 19
        line 50: 25
        line 51: 31
        line 54: 37
        line 56: 53
        line 57: 66
        line 56: 86
        line 59: 93
      LocalVariableTable:
        Start  Length  Slot  Name   Signature
            0      94     0  this   Lcom/fasterxml/jackson/core/format/DataFormatMatcher;
            0      94     1    in   Ljava/io/InputStream;
            0      94     2 buffered   [B
            0      94     3 bufferedStart   I
            0      94     4 bufferedLength   I
            0      94     5 match   Lcom/fasterxml/jackson/core/JsonFactory;
            0      94     6 strength   Lcom/fasterxml/jackson/core/format/MatchStrength;
      StackMapTable: number_of_entries = 2
        frame_type = 255 /* full_frame */
          offset_delta = 53
          locals = [ class com/fasterxml/jackson/core/format/DataFormatMatcher, class java/io/InputStream, class "[B", int, int, class com/fasterxml/jackson/core/JsonFactory, class com/fasterxml/jackson/core/format/MatchStrength ]
          stack = []
        frame_type = 39 /* same */

  public boolean hasMatch();
    descriptor: ()Z
    flags: (0x0001) ACC_PUBLIC
    Code:
      stack=1, locals=1, args_size=1
         0: aload_0
         1: getfield      #6                  // Field _match:Lcom/fasterxml/jackson/core/JsonFactory;
         4: ifnull        11
         7: iconst_1
         8: goto          12
        11: iconst_0
        12: ireturn
      LineNumberTable:
        line 73: 0
      LocalVariableTable:
        Start  Length  Slot  Name   Signature
            0      13     0  this   Lcom/fasterxml/jackson/core/format/DataFormatMatcher;
      StackMapTable: number_of_entries = 2
        frame_type = 11 /* same */
        frame_type = 64 /* same_locals_1_stack_item */
          stack = [ int ]

  public com.fasterxml.jackson.core.format.MatchStrength getMatchStrength();
    descriptor: ()Lcom/fasterxml/jackson/core/format/MatchStrength;
    flags: (0x0001) ACC_PUBLIC
    Code:
      stack=1, locals=1, args_size=1
         0: aload_0
         1: getfield      #7                  // Field _matchStrength:Lcom/fasterxml/jackson/core/format/MatchStrength;
         4: ifnonnull     13
         7: getstatic     #14                 // Field com/fasterxml/jackson/core/format/MatchStrength.INCONCLUSIVE:Lcom/fasterxml/jackson/core/format/MatchStrength;
        10: goto          17
        13: aload_0
        14: getfield      #7                  // Field _matchStrength:Lcom/fasterxml/jackson/core/format/MatchStrength;
        17: areturn
      LineNumberTable:
        line 82: 0
      LocalVariableTable:
        Start  Length  Slot  Name   Signature
            0      18     0  this   Lcom/fasterxml/jackson/core/format/DataFormatMatcher;
      StackMapTable: number_of_entries = 2
        frame_type = 13 /* same */
        frame_type = 67 /* same_locals_1_stack_item */
          stack = [ class com/fasterxml/jackson/core/format/MatchStrength ]

  public com.fasterxml.jackson.core.JsonFactory getMatch();
    descriptor: ()Lcom/fasterxml/jackson/core/JsonFactory;
    flags: (0x0001) ACC_PUBLIC
    Code:
      stack=1, locals=1, args_size=1
         0: aload_0
         1: getfield      #6                  // Field _match:Lcom/fasterxml/jackson/core/JsonFactory;
         4: areturn
      LineNumberTable:
        line 90: 0
      LocalVariableTable:
        Start  Length  Slot  Name   Signature
            0       5     0  this   Lcom/fasterxml/jackson/core/format/DataFormatMatcher;

  public java.lang.String getMatchedFormatName();
    descriptor: ()Ljava/lang/String;
    flags: (0x0001) ACC_PUBLIC
    Code:
      stack=1, locals=1, args_size=1
         0: aload_0
         1: invokevirtual #15                 // Method hasMatch:()Z
         4: ifeq          17
         7: aload_0
         8: invokevirtual #16                 // Method getMatch:()Lcom/fasterxml/jackson/core/JsonFactory;
        11: invokevirtual #17                 // Method com/fasterxml/jackson/core/JsonFactory.getFormatName:()Ljava/lang/String;
        14: goto          18
        17: aconst_null
        18: areturn
      LineNumberTable:
        line 102: 0
      LocalVariableTable:
        Start  Length  Slot  Name   Signature
            0      19     0  this   Lcom/fasterxml/jackson/core/format/DataFormatMatcher;
      StackMapTable: number_of_entries = 2
        frame_type = 17 /* same */
        frame_type = 64 /* same_locals_1_stack_item */
          stack = [ class java/lang/String ]

  public com.fasterxml.jackson.core.JsonParser createParserWithMatch() throws java.io.IOException;
    descriptor: ()Lcom/fasterxml/jackson/core/JsonParser;
    flags: (0x0001) ACC_PUBLIC
    Code:
      stack=4, locals=1, args_size=1
         0: aload_0
         1: getfield      #6                  // Field _match:Lcom/fasterxml/jackson/core/JsonFactory;
         4: ifnonnull     9
         7: aconst_null
         8: areturn
         9: aload_0
        10: getfield      #2                  // Field _originalStream:Ljava/io/InputStream;
        13: ifnonnull     36
        16: aload_0
        17: getfield      #6                  // Field _match:Lcom/fasterxml/jackson/core/JsonFactory;
        20: aload_0
        21: getfield      #3                  // Field _bufferedData:[B
        24: aload_0
        25: getfield      #4                  // Field _bufferedStart:I
        28: aload_0
        29: getfield      #5                  // Field _bufferedLength:I
        32: invokevirtual #18                 // Method com/fasterxml/jackson/core/JsonFactory.createParser:([BII)Lcom/fasterxml/jackson/core/JsonParser;
        35: areturn
        36: aload_0
        37: getfield      #6                  // Field _match:Lcom/fasterxml/jackson/core/JsonFactory;
        40: aload_0
        41: invokevirtual #19                 // Method getDataStream:()Ljava/io/InputStream;
        44: invokevirtual #20                 // Method com/fasterxml/jackson/core/JsonFactory.createParser:(Ljava/io/InputStream;)Lcom/fasterxml/jackson/core/JsonParser;
        47: areturn
      LineNumberTable:
        line 115: 0
        line 116: 7
        line 118: 9
        line 119: 16
        line 121: 36
      LocalVariableTable:
        Start  Length  Slot  Name   Signature
            0      48     0  this   Lcom/fasterxml/jackson/core/format/DataFormatMatcher;
      StackMapTable: number_of_entries = 2
        frame_type = 9 /* same */
        frame_type = 26 /* same */
    Exceptions:
      throws java.io.IOException

  public java.io.InputStream getDataStream();
    descriptor: ()Ljava/io/InputStream;
    flags: (0x0001) ACC_PUBLIC
    Code:
      stack=7, locals=1, args_size=1
         0: aload_0
         1: getfield      #2                  // Field _originalStream:Ljava/io/InputStream;
         4: ifnonnull     27
         7: new           #21                 // class java/io/ByteArrayInputStream
        10: dup
        11: aload_0
        12: getfield      #3                  // Field _bufferedData:[B
        15: aload_0
        16: getfield      #4                  // Field _bufferedStart:I
        19: aload_0
        20: getfield      #5                  // Field _bufferedLength:I
        23: invokespecial #22                 // Method java/io/ByteArrayInputStream."<init>":([BII)V
        26: areturn
        27: new           #23                 // class com/fasterxml/jackson/core/io/MergedStream
        30: dup
        31: aconst_null
        32: aload_0
        33: getfield      #2                  // Field _originalStream:Ljava/io/InputStream;
        36: aload_0
        37: getfield      #3                  // Field _bufferedData:[B
        40: aload_0
        41: getfield      #4                  // Field _bufferedStart:I
        44: aload_0
        45: getfield      #5                  // Field _bufferedLength:I
        48: invokespecial #24                 // Method com/fasterxml/jackson/core/io/MergedStream."<init>":(Lcom/fasterxml/jackson/core/io/IOContext;Ljava/io/InputStream;[BII)V
        51: areturn
      LineNumberTable:
        line 134: 0
        line 135: 7
        line 137: 27
      LocalVariableTable:
        Start  Length  Slot  Name   Signature
            0      52     0  this   Lcom/fasterxml/jackson/core/format/DataFormatMatcher;
      StackMapTable: number_of_entries = 1
        frame_type = 27 /* same */
}
SourceFile: "DataFormatMatcher.java"
