Classfile /Users/mw/Projects/slang-braindump/.jar/jar8/assemble/slang-braindump/assemble/content/com/fasterxml/jackson/core/format/DataFormatDetector.class
  Last modified May 29, 2022; size 4580 bytes
  SHA-256 checksum 34f65e2dae15483d12cc3334fc0498a47ef10992f8daea9b7adcd3e259129294
  Compiled from "DataFormatDetector.java"
public class com.fasterxml.jackson.core.format.DataFormatDetector
  minor version: 0
  major version: 50
  flags: (0x0021) ACC_PUBLIC, ACC_SUPER
  this_class: #3                          // com/fasterxml/jackson/core/format/DataFormatDetector
  super_class: #30                        // java/lang/Object
  interfaces: 0, fields: 5, methods: 11, attributes: 2
Constant pool:
    #1 = Fieldref           #101.#102     // com/fasterxml/jackson/core/format/MatchStrength.SOLID_MATCH:Lcom/fasterxml/jackson/core/format/MatchStrength;
    #2 = Fieldref           #101.#103     // com/fasterxml/jackson/core/format/MatchStrength.WEAK_MATCH:Lcom/fasterxml/jackson/core/format/MatchStrength;
    #3 = Class              #104          // com/fasterxml/jackson/core/format/DataFormatDetector
    #4 = Methodref          #3.#105       // com/fasterxml/jackson/core/format/DataFormatDetector."<init>":([Lcom/fasterxml/jackson/core/JsonFactory;Lcom/fasterxml/jackson/core/format/MatchStrength;Lcom/fasterxml/jackson/core/format/MatchStrength;I)V
    #5 = Class              #106          // com/fasterxml/jackson/core/JsonFactory
    #6 = InterfaceMethodref #107.#108     // java/util/Collection.toArray:([Ljava/lang/Object;)[Ljava/lang/Object;
    #7 = Class              #36           // "[Lcom/fasterxml/jackson/core/JsonFactory;"
    #8 = Methodref          #3.#109       // com/fasterxml/jackson/core/format/DataFormatDetector."<init>":([Lcom/fasterxml/jackson/core/JsonFactory;)V
    #9 = Methodref          #30.#110      // java/lang/Object."<init>":()V
   #10 = Fieldref           #3.#111       // com/fasterxml/jackson/core/format/DataFormatDetector._detectors:[Lcom/fasterxml/jackson/core/JsonFactory;
   #11 = Fieldref           #3.#112       // com/fasterxml/jackson/core/format/DataFormatDetector._optimalMatch:Lcom/fasterxml/jackson/core/format/MatchStrength;
   #12 = Fieldref           #3.#113       // com/fasterxml/jackson/core/format/DataFormatDetector._minimalMatch:Lcom/fasterxml/jackson/core/format/MatchStrength;
   #13 = Fieldref           #3.#114       // com/fasterxml/jackson/core/format/DataFormatDetector._maxInputLookahead:I
   #14 = Class              #116          // com/fasterxml/jackson/core/format/InputAccessor$Std
   #15 = Methodref          #14.#117      // com/fasterxml/jackson/core/format/InputAccessor$Std."<init>":(Ljava/io/InputStream;[B)V
   #16 = Methodref          #3.#118       // com/fasterxml/jackson/core/format/DataFormatDetector._findFormat:(Lcom/fasterxml/jackson/core/format/InputAccessor$Std;)Lcom/fasterxml/jackson/core/format/DataFormatMatcher;
   #17 = Methodref          #14.#119      // com/fasterxml/jackson/core/format/InputAccessor$Std."<init>":([B)V
   #18 = Methodref          #14.#120      // com/fasterxml/jackson/core/format/InputAccessor$Std."<init>":([BII)V
   #19 = Class              #121          // java/lang/StringBuilder
   #20 = Methodref          #19.#110      // java/lang/StringBuilder."<init>":()V
   #21 = Methodref          #19.#122      // java/lang/StringBuilder.append:(C)Ljava/lang/StringBuilder;
   #22 = Methodref          #5.#123       // com/fasterxml/jackson/core/JsonFactory.getFormatName:()Ljava/lang/String;
   #23 = Methodref          #19.#124      // java/lang/StringBuilder.append:(Ljava/lang/String;)Ljava/lang/StringBuilder;
   #24 = String             #125          // ,
   #25 = Methodref          #19.#126      // java/lang/StringBuilder.toString:()Ljava/lang/String;
   #26 = Methodref          #14.#127      // com/fasterxml/jackson/core/format/InputAccessor$Std.reset:()V
   #27 = Methodref          #5.#128       // com/fasterxml/jackson/core/JsonFactory.hasFormat:(Lcom/fasterxml/jackson/core/format/InputAccessor;)Lcom/fasterxml/jackson/core/format/MatchStrength;
   #28 = Methodref          #101.#129     // com/fasterxml/jackson/core/format/MatchStrength.ordinal:()I
   #29 = Methodref          #14.#130      // com/fasterxml/jackson/core/format/InputAccessor$Std.createMatcher:(Lcom/fasterxml/jackson/core/JsonFactory;Lcom/fasterxml/jackson/core/format/MatchStrength;)Lcom/fasterxml/jackson/core/format/DataFormatMatcher;
   #30 = Class              #131          // java/lang/Object
   #31 = Utf8               DEFAULT_MAX_INPUT_LOOKAHEAD
   #32 = Utf8               I
   #33 = Utf8               ConstantValue
   #34 = Integer            64
   #35 = Utf8               _detectors
   #36 = Utf8               [Lcom/fasterxml/jackson/core/JsonFactory;
   #37 = Utf8               _optimalMatch
   #38 = Utf8               Lcom/fasterxml/jackson/core/format/MatchStrength;
   #39 = Utf8               _minimalMatch
   #40 = Utf8               _maxInputLookahead
   #41 = Utf8               <init>
   #42 = Utf8               ([Lcom/fasterxml/jackson/core/JsonFactory;)V
   #43 = Utf8               Code
   #44 = Utf8               LineNumberTable
   #45 = Utf8               LocalVariableTable
   #46 = Utf8               this
   #47 = Utf8               Lcom/fasterxml/jackson/core/format/DataFormatDetector;
   #48 = Utf8               detectors
   #49 = Utf8               (Ljava/util/Collection;)V
   #50 = Utf8               Ljava/util/Collection;
   #51 = Utf8               LocalVariableTypeTable
   #52 = Utf8               Ljava/util/Collection<Lcom/fasterxml/jackson/core/JsonFactory;>;
   #53 = Utf8               Signature
   #54 = Utf8               (Ljava/util/Collection<Lcom/fasterxml/jackson/core/JsonFactory;>;)V
   #55 = Utf8               ([Lcom/fasterxml/jackson/core/JsonFactory;Lcom/fasterxml/jackson/core/format/MatchStrength;Lcom/fasterxml/jackson/core/format/MatchStrength;I)V
   #56 = Utf8               optMatch
   #57 = Utf8               minMatch
   #58 = Utf8               maxInputLookahead
   #59 = Utf8               withOptimalMatch
   #60 = Utf8               (Lcom/fasterxml/jackson/core/format/MatchStrength;)Lcom/fasterxml/jackson/core/format/DataFormatDetector;
   #61 = Utf8               StackMapTable
   #62 = Utf8               withMinimalMatch
   #63 = Utf8               withMaxInputLookahead
   #64 = Utf8               (I)Lcom/fasterxml/jackson/core/format/DataFormatDetector;
   #65 = Utf8               lookaheadBytes
   #66 = Utf8               findFormat
   #67 = Utf8               (Ljava/io/InputStream;)Lcom/fasterxml/jackson/core/format/DataFormatMatcher;
   #68 = Utf8               in
   #69 = Utf8               Ljava/io/InputStream;
   #70 = Utf8               Exceptions
   #71 = Class              #132          // java/io/IOException
   #72 = Utf8               ([B)Lcom/fasterxml/jackson/core/format/DataFormatMatcher;
   #73 = Utf8               fullInputData
   #74 = Utf8               [B
   #75 = Utf8               ([BII)Lcom/fasterxml/jackson/core/format/DataFormatMatcher;
   #76 = Utf8               offset
   #77 = Utf8               len
   #78 = Utf8               toString
   #79 = Utf8               ()Ljava/lang/String;
   #80 = Utf8               i
   #81 = Utf8               sb
   #82 = Utf8               Ljava/lang/StringBuilder;
   #83 = Class              #121          // java/lang/StringBuilder
   #84 = Utf8               _findFormat
   #85 = Utf8               Std
   #86 = Utf8               InnerClasses
   #87 = Utf8               (Lcom/fasterxml/jackson/core/format/InputAccessor$Std;)Lcom/fasterxml/jackson/core/format/DataFormatMatcher;
   #88 = Utf8               strength
   #89 = Utf8               f
   #90 = Utf8               Lcom/fasterxml/jackson/core/JsonFactory;
   #91 = Utf8               acc
   #92 = Utf8               Lcom/fasterxml/jackson/core/format/InputAccessor$Std;
   #93 = Utf8               bestMatch
   #94 = Utf8               bestMatchStrength
   #95 = Class              #104          // com/fasterxml/jackson/core/format/DataFormatDetector
   #96 = Class              #116          // com/fasterxml/jackson/core/format/InputAccessor$Std
   #97 = Class              #106          // com/fasterxml/jackson/core/JsonFactory
   #98 = Class              #133          // com/fasterxml/jackson/core/format/MatchStrength
   #99 = Utf8               SourceFile
  #100 = Utf8               DataFormatDetector.java
  #101 = Class              #133          // com/fasterxml/jackson/core/format/MatchStrength
  #102 = NameAndType        #134:#38      // SOLID_MATCH:Lcom/fasterxml/jackson/core/format/MatchStrength;
  #103 = NameAndType        #135:#38      // WEAK_MATCH:Lcom/fasterxml/jackson/core/format/MatchStrength;
  #104 = Utf8               com/fasterxml/jackson/core/format/DataFormatDetector
  #105 = NameAndType        #41:#55       // "<init>":([Lcom/fasterxml/jackson/core/JsonFactory;Lcom/fasterxml/jackson/core/format/MatchStrength;Lcom/fasterxml/jackson/core/format/MatchStrength;I)V
  #106 = Utf8               com/fasterxml/jackson/core/JsonFactory
  #107 = Class              #136          // java/util/Collection
  #108 = NameAndType        #137:#138     // toArray:([Ljava/lang/Object;)[Ljava/lang/Object;
  #109 = NameAndType        #41:#42       // "<init>":([Lcom/fasterxml/jackson/core/JsonFactory;)V
  #110 = NameAndType        #41:#139      // "<init>":()V
  #111 = NameAndType        #35:#36       // _detectors:[Lcom/fasterxml/jackson/core/JsonFactory;
  #112 = NameAndType        #37:#38       // _optimalMatch:Lcom/fasterxml/jackson/core/format/MatchStrength;
  #113 = NameAndType        #39:#38       // _minimalMatch:Lcom/fasterxml/jackson/core/format/MatchStrength;
  #114 = NameAndType        #40:#32       // _maxInputLookahead:I
  #115 = Class              #140          // com/fasterxml/jackson/core/format/InputAccessor
  #116 = Utf8               com/fasterxml/jackson/core/format/InputAccessor$Std
  #117 = NameAndType        #41:#141      // "<init>":(Ljava/io/InputStream;[B)V
  #118 = NameAndType        #84:#87       // _findFormat:(Lcom/fasterxml/jackson/core/format/InputAccessor$Std;)Lcom/fasterxml/jackson/core/format/DataFormatMatcher;
  #119 = NameAndType        #41:#142      // "<init>":([B)V
  #120 = NameAndType        #41:#143      // "<init>":([BII)V
  #121 = Utf8               java/lang/StringBuilder
  #122 = NameAndType        #144:#145     // append:(C)Ljava/lang/StringBuilder;
  #123 = NameAndType        #146:#79      // getFormatName:()Ljava/lang/String;
  #124 = NameAndType        #144:#147     // append:(Ljava/lang/String;)Ljava/lang/StringBuilder;
  #125 = Utf8               ,
  #126 = NameAndType        #78:#79       // toString:()Ljava/lang/String;
  #127 = NameAndType        #148:#139     // reset:()V
  #128 = NameAndType        #149:#150     // hasFormat:(Lcom/fasterxml/jackson/core/format/InputAccessor;)Lcom/fasterxml/jackson/core/format/MatchStrength;
  #129 = NameAndType        #151:#152     // ordinal:()I
  #130 = NameAndType        #153:#154     // createMatcher:(Lcom/fasterxml/jackson/core/JsonFactory;Lcom/fasterxml/jackson/core/format/MatchStrength;)Lcom/fasterxml/jackson/core/format/DataFormatMatcher;
  #131 = Utf8               java/lang/Object
  #132 = Utf8               java/io/IOException
  #133 = Utf8               com/fasterxml/jackson/core/format/MatchStrength
  #134 = Utf8               SOLID_MATCH
  #135 = Utf8               WEAK_MATCH
  #136 = Utf8               java/util/Collection
  #137 = Utf8               toArray
  #138 = Utf8               ([Ljava/lang/Object;)[Ljava/lang/Object;
  #139 = Utf8               ()V
  #140 = Utf8               com/fasterxml/jackson/core/format/InputAccessor
  #141 = Utf8               (Ljava/io/InputStream;[B)V
  #142 = Utf8               ([B)V
  #143 = Utf8               ([BII)V
  #144 = Utf8               append
  #145 = Utf8               (C)Ljava/lang/StringBuilder;
  #146 = Utf8               getFormatName
  #147 = Utf8               (Ljava/lang/String;)Ljava/lang/StringBuilder;
  #148 = Utf8               reset
  #149 = Utf8               hasFormat
  #150 = Utf8               (Lcom/fasterxml/jackson/core/format/InputAccessor;)Lcom/fasterxml/jackson/core/format/MatchStrength;
  #151 = Utf8               ordinal
  #152 = Utf8               ()I
  #153 = Utf8               createMatcher
  #154 = Utf8               (Lcom/fasterxml/jackson/core/JsonFactory;Lcom/fasterxml/jackson/core/format/MatchStrength;)Lcom/fasterxml/jackson/core/format/DataFormatMatcher;
{
  public static final int DEFAULT_MAX_INPUT_LOOKAHEAD;
    descriptor: I
    flags: (0x0019) ACC_PUBLIC, ACC_STATIC, ACC_FINAL
    ConstantValue: int 64

  protected final com.fasterxml.jackson.core.JsonFactory[] _detectors;
    descriptor: [Lcom/fasterxml/jackson/core/JsonFactory;
    flags: (0x0014) ACC_PROTECTED, ACC_FINAL

  protected final com.fasterxml.jackson.core.format.MatchStrength _optimalMatch;
    descriptor: Lcom/fasterxml/jackson/core/format/MatchStrength;
    flags: (0x0014) ACC_PROTECTED, ACC_FINAL

  protected final com.fasterxml.jackson.core.format.MatchStrength _minimalMatch;
    descriptor: Lcom/fasterxml/jackson/core/format/MatchStrength;
    flags: (0x0014) ACC_PROTECTED, ACC_FINAL

  protected final int _maxInputLookahead;
    descriptor: I
    flags: (0x0014) ACC_PROTECTED, ACC_FINAL

  public com.fasterxml.jackson.core.format.DataFormatDetector(com.fasterxml.jackson.core.JsonFactory...);
    descriptor: ([Lcom/fasterxml/jackson/core/JsonFactory;)V
    flags: (0x0081) ACC_PUBLIC, ACC_VARARGS
    Code:
      stack=5, locals=2, args_size=2
         0: aload_0
         1: aload_1
         2: getstatic     #1                  // Field com/fasterxml/jackson/core/format/MatchStrength.SOLID_MATCH:Lcom/fasterxml/jackson/core/format/MatchStrength;
         5: getstatic     #2                  // Field com/fasterxml/jackson/core/format/MatchStrength.WEAK_MATCH:Lcom/fasterxml/jackson/core/format/MatchStrength;
         8: bipush        64
        10: invokespecial #4                  // Method "<init>":([Lcom/fasterxml/jackson/core/JsonFactory;Lcom/fasterxml/jackson/core/format/MatchStrength;Lcom/fasterxml/jackson/core/format/MatchStrength;I)V
        13: return
      LineNumberTable:
        line 58: 0
        line 60: 13
      LocalVariableTable:
        Start  Length  Slot  Name   Signature
            0      14     0  this   Lcom/fasterxml/jackson/core/format/DataFormatDetector;
            0      14     1 detectors   [Lcom/fasterxml/jackson/core/JsonFactory;

  public com.fasterxml.jackson.core.format.DataFormatDetector(java.util.Collection<com.fasterxml.jackson.core.JsonFactory>);
    descriptor: (Ljava/util/Collection;)V
    flags: (0x0001) ACC_PUBLIC
    Code:
      stack=3, locals=2, args_size=2
         0: aload_0
         1: aload_1
         2: iconst_0
         3: anewarray     #5                  // class com/fasterxml/jackson/core/JsonFactory
         6: invokeinterface #6,  2            // InterfaceMethod java/util/Collection.toArray:([Ljava/lang/Object;)[Ljava/lang/Object;
        11: checkcast     #7                  // class "[Lcom/fasterxml/jackson/core/JsonFactory;"
        14: invokespecial #8                  // Method "<init>":([Lcom/fasterxml/jackson/core/JsonFactory;)V
        17: return
      LineNumberTable:
        line 63: 0
        line 64: 17
      LocalVariableTable:
        Start  Length  Slot  Name   Signature
            0      18     0  this   Lcom/fasterxml/jackson/core/format/DataFormatDetector;
            0      18     1 detectors   Ljava/util/Collection;
      LocalVariableTypeTable:
        Start  Length  Slot  Name   Signature
            0      18     1 detectors   Ljava/util/Collection<Lcom/fasterxml/jackson/core/JsonFactory;>;
    Signature: #54                          // (Ljava/util/Collection<Lcom/fasterxml/jackson/core/JsonFactory;>;)V

  private com.fasterxml.jackson.core.format.DataFormatDetector(com.fasterxml.jackson.core.JsonFactory[], com.fasterxml.jackson.core.format.MatchStrength, com.fasterxml.jackson.core.format.MatchStrength, int);
    descriptor: ([Lcom/fasterxml/jackson/core/JsonFactory;Lcom/fasterxml/jackson/core/format/MatchStrength;Lcom/fasterxml/jackson/core/format/MatchStrength;I)V
    flags: (0x0002) ACC_PRIVATE
    Code:
      stack=2, locals=5, args_size=5
         0: aload_0
         1: invokespecial #9                  // Method java/lang/Object."<init>":()V
         4: aload_0
         5: aload_1
         6: putfield      #10                 // Field _detectors:[Lcom/fasterxml/jackson/core/JsonFactory;
         9: aload_0
        10: aload_2
        11: putfield      #11                 // Field _optimalMatch:Lcom/fasterxml/jackson/core/format/MatchStrength;
        14: aload_0
        15: aload_3
        16: putfield      #12                 // Field _minimalMatch:Lcom/fasterxml/jackson/core/format/MatchStrength;
        19: aload_0
        20: iload         4
        22: putfield      #13                 // Field _maxInputLookahead:I
        25: return
      LineNumberTable:
        line 67: 0
        line 68: 4
        line 69: 9
        line 70: 14
        line 71: 19
        line 72: 25
      LocalVariableTable:
        Start  Length  Slot  Name   Signature
            0      26     0  this   Lcom/fasterxml/jackson/core/format/DataFormatDetector;
            0      26     1 detectors   [Lcom/fasterxml/jackson/core/JsonFactory;
            0      26     2 optMatch   Lcom/fasterxml/jackson/core/format/MatchStrength;
            0      26     3 minMatch   Lcom/fasterxml/jackson/core/format/MatchStrength;
            0      26     4 maxInputLookahead   I

  public com.fasterxml.jackson.core.format.DataFormatDetector withOptimalMatch(com.fasterxml.jackson.core.format.MatchStrength);
    descriptor: (Lcom/fasterxml/jackson/core/format/MatchStrength;)Lcom/fasterxml/jackson/core/format/DataFormatDetector;
    flags: (0x0001) ACC_PUBLIC
    Code:
      stack=6, locals=2, args_size=2
         0: aload_1
         1: aload_0
         2: getfield      #11                 // Field _optimalMatch:Lcom/fasterxml/jackson/core/format/MatchStrength;
         5: if_acmpne     10
         8: aload_0
         9: areturn
        10: new           #3                  // class com/fasterxml/jackson/core/format/DataFormatDetector
        13: dup
        14: aload_0
        15: getfield      #10                 // Field _detectors:[Lcom/fasterxml/jackson/core/JsonFactory;
        18: aload_1
        19: aload_0
        20: getfield      #12                 // Field _minimalMatch:Lcom/fasterxml/jackson/core/format/MatchStrength;
        23: aload_0
        24: getfield      #13                 // Field _maxInputLookahead:I
        27: invokespecial #4                  // Method "<init>":([Lcom/fasterxml/jackson/core/JsonFactory;Lcom/fasterxml/jackson/core/format/MatchStrength;Lcom/fasterxml/jackson/core/format/MatchStrength;I)V
        30: areturn
      LineNumberTable:
        line 84: 0
        line 85: 8
        line 87: 10
      LocalVariableTable:
        Start  Length  Slot  Name   Signature
            0      31     0  this   Lcom/fasterxml/jackson/core/format/DataFormatDetector;
            0      31     1 optMatch   Lcom/fasterxml/jackson/core/format/MatchStrength;
      StackMapTable: number_of_entries = 1
        frame_type = 10 /* same */

  public com.fasterxml.jackson.core.format.DataFormatDetector withMinimalMatch(com.fasterxml.jackson.core.format.MatchStrength);
    descriptor: (Lcom/fasterxml/jackson/core/format/MatchStrength;)Lcom/fasterxml/jackson/core/format/DataFormatDetector;
    flags: (0x0001) ACC_PUBLIC
    Code:
      stack=6, locals=2, args_size=2
         0: aload_1
         1: aload_0
         2: getfield      #12                 // Field _minimalMatch:Lcom/fasterxml/jackson/core/format/MatchStrength;
         5: if_acmpne     10
         8: aload_0
         9: areturn
        10: new           #3                  // class com/fasterxml/jackson/core/format/DataFormatDetector
        13: dup
        14: aload_0
        15: getfield      #10                 // Field _detectors:[Lcom/fasterxml/jackson/core/JsonFactory;
        18: aload_0
        19: getfield      #11                 // Field _optimalMatch:Lcom/fasterxml/jackson/core/format/MatchStrength;
        22: aload_1
        23: aload_0
        24: getfield      #13                 // Field _maxInputLookahead:I
        27: invokespecial #4                  // Method "<init>":([Lcom/fasterxml/jackson/core/JsonFactory;Lcom/fasterxml/jackson/core/format/MatchStrength;Lcom/fasterxml/jackson/core/format/MatchStrength;I)V
        30: areturn
      LineNumberTable:
        line 99: 0
        line 100: 8
        line 102: 10
      LocalVariableTable:
        Start  Length  Slot  Name   Signature
            0      31     0  this   Lcom/fasterxml/jackson/core/format/DataFormatDetector;
            0      31     1 minMatch   Lcom/fasterxml/jackson/core/format/MatchStrength;
      StackMapTable: number_of_entries = 1
        frame_type = 10 /* same */

  public com.fasterxml.jackson.core.format.DataFormatDetector withMaxInputLookahead(int);
    descriptor: (I)Lcom/fasterxml/jackson/core/format/DataFormatDetector;
    flags: (0x0001) ACC_PUBLIC
    Code:
      stack=6, locals=2, args_size=2
         0: iload_1
         1: aload_0
         2: getfield      #13                 // Field _maxInputLookahead:I
         5: if_icmpne     10
         8: aload_0
         9: areturn
        10: new           #3                  // class com/fasterxml/jackson/core/format/DataFormatDetector
        13: dup
        14: aload_0
        15: getfield      #10                 // Field _detectors:[Lcom/fasterxml/jackson/core/JsonFactory;
        18: aload_0
        19: getfield      #11                 // Field _optimalMatch:Lcom/fasterxml/jackson/core/format/MatchStrength;
        22: aload_0
        23: getfield      #12                 // Field _minimalMatch:Lcom/fasterxml/jackson/core/format/MatchStrength;
        26: iload_1
        27: invokespecial #4                  // Method "<init>":([Lcom/fasterxml/jackson/core/JsonFactory;Lcom/fasterxml/jackson/core/format/MatchStrength;Lcom/fasterxml/jackson/core/format/MatchStrength;I)V
        30: areturn
      LineNumberTable:
        line 114: 0
        line 115: 8
        line 117: 10
      LocalVariableTable:
        Start  Length  Slot  Name   Signature
            0      31     0  this   Lcom/fasterxml/jackson/core/format/DataFormatDetector;
            0      31     1 lookaheadBytes   I
      StackMapTable: number_of_entries = 1
        frame_type = 10 /* same */

  public com.fasterxml.jackson.core.format.DataFormatMatcher findFormat(java.io.InputStream) throws java.io.IOException;
    descriptor: (Ljava/io/InputStream;)Lcom/fasterxml/jackson/core/format/DataFormatMatcher;
    flags: (0x0001) ACC_PUBLIC
    Code:
      stack=5, locals=2, args_size=2
         0: aload_0
         1: new           #14                 // class com/fasterxml/jackson/core/format/InputAccessor$Std
         4: dup
         5: aload_1
         6: aload_0
         7: getfield      #13                 // Field _maxInputLookahead:I
        10: newarray       byte
        12: invokespecial #15                 // Method com/fasterxml/jackson/core/format/InputAccessor$Std."<init>":(Ljava/io/InputStream;[B)V
        15: invokespecial #16                 // Method _findFormat:(Lcom/fasterxml/jackson/core/format/InputAccessor$Std;)Lcom/fasterxml/jackson/core/format/DataFormatMatcher;
        18: areturn
      LineNumberTable:
        line 139: 0
      LocalVariableTable:
        Start  Length  Slot  Name   Signature
            0      19     0  this   Lcom/fasterxml/jackson/core/format/DataFormatDetector;
            0      19     1    in   Ljava/io/InputStream;
    Exceptions:
      throws java.io.IOException

  public com.fasterxml.jackson.core.format.DataFormatMatcher findFormat(byte[]) throws java.io.IOException;
    descriptor: ([B)Lcom/fasterxml/jackson/core/format/DataFormatMatcher;
    flags: (0x0001) ACC_PUBLIC
    Code:
      stack=4, locals=2, args_size=2
         0: aload_0
         1: new           #14                 // class com/fasterxml/jackson/core/format/InputAccessor$Std
         4: dup
         5: aload_1
         6: invokespecial #17                 // Method com/fasterxml/jackson/core/format/InputAccessor$Std."<init>":([B)V
         9: invokespecial #16                 // Method _findFormat:(Lcom/fasterxml/jackson/core/format/InputAccessor$Std;)Lcom/fasterxml/jackson/core/format/DataFormatMatcher;
        12: areturn
      LineNumberTable:
        line 154: 0
      LocalVariableTable:
        Start  Length  Slot  Name   Signature
            0      13     0  this   Lcom/fasterxml/jackson/core/format/DataFormatDetector;
            0      13     1 fullInputData   [B
    Exceptions:
      throws java.io.IOException

  public com.fasterxml.jackson.core.format.DataFormatMatcher findFormat(byte[], int, int) throws java.io.IOException;
    descriptor: ([BII)Lcom/fasterxml/jackson/core/format/DataFormatMatcher;
    flags: (0x0001) ACC_PUBLIC
    Code:
      stack=6, locals=4, args_size=4
         0: aload_0
         1: new           #14                 // class com/fasterxml/jackson/core/format/InputAccessor$Std
         4: dup
         5: aload_1
         6: iload_2
         7: iload_3
         8: invokespecial #18                 // Method com/fasterxml/jackson/core/format/InputAccessor$Std."<init>":([BII)V
        11: invokespecial #16                 // Method _findFormat:(Lcom/fasterxml/jackson/core/format/InputAccessor$Std;)Lcom/fasterxml/jackson/core/format/DataFormatMatcher;
        14: areturn
      LineNumberTable:
        line 173: 0
      LocalVariableTable:
        Start  Length  Slot  Name   Signature
            0      15     0  this   Lcom/fasterxml/jackson/core/format/DataFormatDetector;
            0      15     1 fullInputData   [B
            0      15     2 offset   I
            0      15     3   len   I
    Exceptions:
      throws java.io.IOException

  public java.lang.String toString();
    descriptor: ()Ljava/lang/String;
    flags: (0x0001) ACC_PUBLIC
    Code:
      stack=3, locals=4, args_size=1
         0: new           #19                 // class java/lang/StringBuilder
         3: dup
         4: invokespecial #20                 // Method java/lang/StringBuilder."<init>":()V
         7: astore_1
         8: aload_1
         9: bipush        91
        11: invokevirtual #21                 // Method java/lang/StringBuilder.append:(C)Ljava/lang/StringBuilder;
        14: pop
        15: aload_0
        16: getfield      #10                 // Field _detectors:[Lcom/fasterxml/jackson/core/JsonFactory;
        19: arraylength
        20: istore_2
        21: iload_2
        22: ifle          73
        25: aload_1
        26: aload_0
        27: getfield      #10                 // Field _detectors:[Lcom/fasterxml/jackson/core/JsonFactory;
        30: iconst_0
        31: aaload
        32: invokevirtual #22                 // Method com/fasterxml/jackson/core/JsonFactory.getFormatName:()Ljava/lang/String;
        35: invokevirtual #23                 // Method java/lang/StringBuilder.append:(Ljava/lang/String;)Ljava/lang/StringBuilder;
        38: pop
        39: iconst_1
        40: istore_3
        41: iload_3
        42: iload_2
        43: if_icmpge     73
        46: aload_1
        47: ldc           #24                 // String ,
        49: invokevirtual #23                 // Method java/lang/StringBuilder.append:(Ljava/lang/String;)Ljava/lang/StringBuilder;
        52: pop
        53: aload_1
        54: aload_0
        55: getfield      #10                 // Field _detectors:[Lcom/fasterxml/jackson/core/JsonFactory;
        58: iload_3
        59: aaload
        60: invokevirtual #22                 // Method com/fasterxml/jackson/core/JsonFactory.getFormatName:()Ljava/lang/String;
        63: invokevirtual #23                 // Method java/lang/StringBuilder.append:(Ljava/lang/String;)Ljava/lang/StringBuilder;
        66: pop
        67: iinc          3, 1
        70: goto          41
        73: aload_1
        74: bipush        93
        76: invokevirtual #21                 // Method java/lang/StringBuilder.append:(C)Ljava/lang/StringBuilder;
        79: pop
        80: aload_1
        81: invokevirtual #25                 // Method java/lang/StringBuilder.toString:()Ljava/lang/String;
        84: areturn
      LineNumberTable:
        line 183: 0
        line 184: 8
        line 185: 15
        line 186: 21
        line 187: 25
        line 188: 39
        line 189: 46
        line 190: 53
        line 188: 67
        line 193: 73
        line 194: 80
      LocalVariableTable:
        Start  Length  Slot  Name   Signature
           41      32     3     i   I
            0      85     0  this   Lcom/fasterxml/jackson/core/format/DataFormatDetector;
            8      77     1    sb   Ljava/lang/StringBuilder;
           21      64     2   len   I
      StackMapTable: number_of_entries = 2
        frame_type = 254 /* append */
          offset_delta = 41
          locals = [ class java/lang/StringBuilder, int, int ]
        frame_type = 250 /* chop */
          offset_delta = 31

  private com.fasterxml.jackson.core.format.DataFormatMatcher _findFormat(com.fasterxml.jackson.core.format.InputAccessor$Std) throws java.io.IOException;
    descriptor: (Lcom/fasterxml/jackson/core/format/InputAccessor$Std;)Lcom/fasterxml/jackson/core/format/DataFormatMatcher;
    flags: (0x0002) ACC_PRIVATE
    Code:
      stack=3, locals=9, args_size=2
         0: aconst_null
         1: astore_2
         2: aconst_null
         3: astore_3
         4: aload_0
         5: getfield      #10                 // Field _detectors:[Lcom/fasterxml/jackson/core/JsonFactory;
         8: astore        4
        10: aload         4
        12: arraylength
        13: istore        5
        15: iconst_0
        16: istore        6
        18: iload         6
        20: iload         5
        22: if_icmpge     116
        25: aload         4
        27: iload         6
        29: aaload
        30: astore        7
        32: aload_1
        33: invokevirtual #26                 // Method com/fasterxml/jackson/core/format/InputAccessor$Std.reset:()V
        36: aload         7
        38: aload_1
        39: invokevirtual #27                 // Method com/fasterxml/jackson/core/JsonFactory.hasFormat:(Lcom/fasterxml/jackson/core/format/InputAccessor;)Lcom/fasterxml/jackson/core/format/MatchStrength;
        42: astore        8
        44: aload         8
        46: ifnull        110
        49: aload         8
        51: invokevirtual #28                 // Method com/fasterxml/jackson/core/format/MatchStrength.ordinal:()I
        54: aload_0
        55: getfield      #12                 // Field _minimalMatch:Lcom/fasterxml/jackson/core/format/MatchStrength;
        58: invokevirtual #28                 // Method com/fasterxml/jackson/core/format/MatchStrength.ordinal:()I
        61: if_icmpge     67
        64: goto          110
        67: aload_2
        68: ifnull        86
        71: aload_3
        72: invokevirtual #28                 // Method com/fasterxml/jackson/core/format/MatchStrength.ordinal:()I
        75: aload         8
        77: invokevirtual #28                 // Method com/fasterxml/jackson/core/format/MatchStrength.ordinal:()I
        80: if_icmplt     86
        83: goto          110
        86: aload         7
        88: astore_2
        89: aload         8
        91: astore_3
        92: aload         8
        94: invokevirtual #28                 // Method com/fasterxml/jackson/core/format/MatchStrength.ordinal:()I
        97: aload_0
        98: getfield      #11                 // Field _optimalMatch:Lcom/fasterxml/jackson/core/format/MatchStrength;
       101: invokevirtual #28                 // Method com/fasterxml/jackson/core/format/MatchStrength.ordinal:()I
       104: if_icmplt     110
       107: goto          116
       110: iinc          6, 1
       113: goto          18
       116: aload_1
       117: aload_2
       118: aload_3
       119: invokevirtual #29                 // Method com/fasterxml/jackson/core/format/InputAccessor$Std.createMatcher:(Lcom/fasterxml/jackson/core/JsonFactory;Lcom/fasterxml/jackson/core/format/MatchStrength;)Lcom/fasterxml/jackson/core/format/DataFormatMatcher;
       122: areturn
      LineNumberTable:
        line 204: 0
        line 205: 2
        line 206: 4
        line 207: 32
        line 208: 36
        line 210: 44
        line 211: 64
        line 214: 67
        line 215: 71
        line 216: 83
        line 220: 86
        line 221: 89
        line 222: 92
        line 223: 107
        line 206: 110
        line 226: 116
      LocalVariableTable:
        Start  Length  Slot  Name   Signature
           44      66     8 strength   Lcom/fasterxml/jackson/core/format/MatchStrength;
           32      78     7     f   Lcom/fasterxml/jackson/core/JsonFactory;
            0     123     0  this   Lcom/fasterxml/jackson/core/format/DataFormatDetector;
            0     123     1   acc   Lcom/fasterxml/jackson/core/format/InputAccessor$Std;
            2     121     2 bestMatch   Lcom/fasterxml/jackson/core/JsonFactory;
            4     119     3 bestMatchStrength   Lcom/fasterxml/jackson/core/format/MatchStrength;
      StackMapTable: number_of_entries = 5
        frame_type = 255 /* full_frame */
          offset_delta = 18
          locals = [ class com/fasterxml/jackson/core/format/DataFormatDetector, class com/fasterxml/jackson/core/format/InputAccessor$Std, class com/fasterxml/jackson/core/JsonFactory, class com/fasterxml/jackson/core/format/MatchStrength, class "[Lcom/fasterxml/jackson/core/JsonFactory;", int, int ]
          stack = []
        frame_type = 253 /* append */
          offset_delta = 48
          locals = [ class com/fasterxml/jackson/core/JsonFactory, class com/fasterxml/jackson/core/format/MatchStrength ]
        frame_type = 18 /* same */
        frame_type = 249 /* chop */
          offset_delta = 23
        frame_type = 248 /* chop */
          offset_delta = 5
    Exceptions:
      throws java.io.IOException
}
SourceFile: "DataFormatDetector.java"
InnerClasses:
  public static #85= #14 of #115;         // Std=class com/fasterxml/jackson/core/format/InputAccessor$Std of class com/fasterxml/jackson/core/format/InputAccessor
