Classfile /Users/mw/Projects/slang-braindump/.jar/jar8/assemble/slang-braindump/assemble/content/shapeless/ops/coproduct$LiftAll$Curried.class
  Last modified May 29, 2022; size 1024 bytes
  SHA-256 checksum f4d24959fa5105096b2f753dfeeb3f76cef3d0fd53b0bb74be966627caec7d9a
  Compiled from "coproduct.scala"
public class shapeless.ops.coproduct$LiftAll$Curried<F extends java.lang.Object> extends java.lang.Object
  minor version: 0
  major version: 52
  flags: (0x0021) ACC_PUBLIC, ACC_SUPER
  this_class: #2                          // shapeless/ops/coproduct$LiftAll$Curried
  super_class: #5                         // java/lang/Object
  interfaces: 0, fields: 0, methods: 2, attributes: 5
Constant pool:
   #1 = Utf8               shapeless/ops/coproduct$LiftAll$Curried
   #2 = Class              #1             // shapeless/ops/coproduct$LiftAll$Curried
   #3 = Utf8               <F:Ljava/lang/Object;>Ljava/lang/Object;
   #4 = Utf8               java/lang/Object
   #5 = Class              #4             // java/lang/Object
   #6 = Utf8               coproduct.scala
   #7 = Utf8               shapeless/ops/coproduct$LiftAll
   #8 = Class              #7             // shapeless/ops/coproduct$LiftAll
   #9 = Utf8               shapeless/ops/coproduct
  #10 = Class              #9             // shapeless/ops/coproduct
  #11 = Utf8               LiftAll
  #12 = Utf8               shapeless/ops/coproduct$LiftAll$
  #13 = Class              #12            // shapeless/ops/coproduct$LiftAll$
  #14 = Utf8               LiftAll$
  #15 = Utf8               Curried
  #16 = Utf8               apply
  #17 = Utf8               (Lshapeless/Coproduct;Lshapeless/ops/coproduct$LiftAll;)Lshapeless/ops/coproduct$LiftAll;
  #18 = Utf8               <In::Lshapeless/Coproduct;>(TIn;Lshapeless/ops/coproduct$LiftAll<TF;TIn;>;)Lshapeless/ops/coproduct$LiftAll<TF;TIn;>;
  #19 = Utf8               in
  #20 = Utf8               ev
  #21 = Utf8               this
  #22 = Utf8               Lshapeless/ops/coproduct$LiftAll$Curried;
  #23 = Utf8               Lshapeless/Coproduct;
  #24 = Utf8               Lshapeless/ops/coproduct$LiftAll;
  #25 = Utf8               <init>
  #26 = Utf8               ()V
  #27 = NameAndType        #25:#26        // "<init>":()V
  #28 = Methodref          #5.#27         // java/lang/Object."<init>":()V
  #29 = Utf8               Code
  #30 = Utf8               LineNumberTable
  #31 = Utf8               LocalVariableTable
  #32 = Utf8               Signature
  #33 = Utf8               MethodParameters
  #34 = Utf8               InnerClasses
  #35 = Utf8               SourceFile
  #36 = Utf8               ScalaInlineInfo
  #37 = Utf8               Scala
{
  public <In extends shapeless.Coproduct> shapeless.ops.coproduct$LiftAll<F, In> apply(In, shapeless.ops.coproduct$LiftAll<F, In>);
    descriptor: (Lshapeless/Coproduct;Lshapeless/ops/coproduct$LiftAll;)Lshapeless/ops/coproduct$LiftAll;
    flags: (0x0001) ACC_PUBLIC
    Code:
      stack=1, locals=3, args_size=3
         0: aload_2
         1: areturn
      LineNumberTable:
        line 1265: 0
      LocalVariableTable:
        Start  Length  Slot  Name   Signature
            0       2     0  this   Lshapeless/ops/coproduct$LiftAll$Curried;
            0       2     1    in   Lshapeless/Coproduct;
            0       2     2    ev   Lshapeless/ops/coproduct$LiftAll;
    Signature: #18                          // <In::Lshapeless/Coproduct;>(TIn;Lshapeless/ops/coproduct$LiftAll<TF;TIn;>;)Lshapeless/ops/coproduct$LiftAll<TF;TIn;>;
    MethodParameters:
      Name                           Flags
      in                             final
      ev                             final

  public shapeless.ops.coproduct$LiftAll$Curried();
    descriptor: ()V
    flags: (0x0001) ACC_PUBLIC
    Code:
      stack=1, locals=1, args_size=1
         0: aload_0
         1: invokespecial #28                 // Method java/lang/Object."<init>":()V
         4: return
      LineNumberTable:
        line 1267: 0
        line 1265: 4
      LocalVariableTable:
        Start  Length  Slot  Name   Signature
            0       5     0  this   Lshapeless/ops/coproduct$LiftAll$Curried;
}
InnerClasses:
  public static #11= #8 of #10;           // LiftAll=class shapeless/ops/coproduct$LiftAll of class shapeless/ops/coproduct
  public static #14= #13 of #10;          // LiftAll$=class shapeless/ops/coproduct$LiftAll$ of class shapeless/ops/coproduct
  public static #15= #2 of #13;           // Curried=class shapeless/ops/coproduct$LiftAll$Curried of class shapeless/ops/coproduct$LiftAll$
Signature: #3                           // <F:Ljava/lang/Object;>Ljava/lang/Object;
SourceFile: "coproduct.scala"
  ScalaInlineInfo: length = 0xE (unknown attribute)
   01 00 00 02 00 19 00 1A 00 00 10 00 11 00
  Scala: length = 0x0 (unknown attribute)

