Classfile /Users/mw/Projects/slang-braindump/.jar/jar8/assemble/slang-braindump/assemble/content/shapeless/ops/coproduct$Length$$anon$35.class
  Last modified May 29, 2022; size 1195 bytes
  SHA-256 checksum 7358390a355c09e3b2c8dad1d7dcc054f6c16a99e242b6b82db77492781a3467
  Compiled from "coproduct.scala"
public final class shapeless.ops.coproduct$Length$$anon$35 extends java.lang.Object implements shapeless.ops.coproduct$Length<shapeless.$colon$plus$colon<H, T>>
  minor version: 0
  major version: 52
  flags: (0x0031) ACC_PUBLIC, ACC_FINAL, ACC_SUPER
  this_class: #2                          // shapeless/ops/coproduct$Length$$anon$35
  super_class: #5                         // java/lang/Object
  interfaces: 1, fields: 1, methods: 3, attributes: 6
Constant pool:
   #1 = Utf8               shapeless/ops/coproduct$Length$$anon$35
   #2 = Class              #1             // shapeless/ops/coproduct$Length$$anon$35
   #3 = Utf8               Ljava/lang/Object;Lshapeless/ops/coproduct$Length<Lshapeless/$colon$plus$colon<TH;TT;>;>;
   #4 = Utf8               java/lang/Object
   #5 = Class              #4             // java/lang/Object
   #6 = Utf8               shapeless/ops/coproduct$Length
   #7 = Class              #6             // shapeless/ops/coproduct$Length
   #8 = Utf8               coproduct.scala
   #9 = Utf8               shapeless/ops/coproduct$Length$
  #10 = Class              #9             // shapeless/ops/coproduct$Length$
  #11 = Utf8               coproductLength
  #12 = Utf8               (Lshapeless/ops/coproduct$Length;Lshapeless/Witness;)Lshapeless/ops/coproduct$Length;
  #13 = NameAndType        #11:#12        // coproductLength:(Lshapeless/ops/coproduct$Length;Lshapeless/Witness;)Lshapeless/ops/coproduct$Length;
  #14 = Utf8               shapeless/ops/coproduct
  #15 = Class              #14            // shapeless/ops/coproduct
  #16 = Utf8               Length
  #17 = Utf8               Length$
  #18 = Utf8               sn$1
  #19 = Utf8               Lshapeless/Witness;
  #20 = Utf8               apply
  #21 = Utf8               ()Lshapeless/Succ;
  #22 = Utf8               ()Lshapeless/Succ<TN;>;
  #23 = NameAndType        #18:#19        // sn$1:Lshapeless/Witness;
  #24 = Fieldref           #2.#23         // shapeless/ops/coproduct$Length$$anon$35.sn$1:Lshapeless/Witness;
  #25 = Utf8               shapeless/Witness
  #26 = Class              #25            // shapeless/Witness
  #27 = Utf8               value
  #28 = Utf8               ()Ljava/lang/Object;
  #29 = NameAndType        #27:#28        // value:()Ljava/lang/Object;
  #30 = InterfaceMethodref #26.#29        // shapeless/Witness.value:()Ljava/lang/Object;
  #31 = Utf8               shapeless/Succ
  #32 = Class              #31            // shapeless/Succ
  #33 = Utf8               this
  #34 = Utf8               Lshapeless/ops/coproduct$Length$$anon$35;
  #35 = NameAndType        #20:#21        // apply:()Lshapeless/Succ;
  #36 = Methodref          #2.#35         // shapeless/ops/coproduct$Length$$anon$35.apply:()Lshapeless/Succ;
  #37 = Utf8               <init>
  #38 = Utf8               (Lshapeless/Witness;)V
  #39 = Utf8               ()V
  #40 = NameAndType        #37:#39        // "<init>":()V
  #41 = Methodref          #5.#40         // java/lang/Object."<init>":()V
  #42 = Utf8               Code
  #43 = Utf8               LineNumberTable
  #44 = Utf8               LocalVariableTable
  #45 = Utf8               Signature
  #46 = Utf8               MethodParameters
  #47 = Utf8               InnerClasses
  #48 = Utf8               EnclosingMethod
  #49 = Utf8               SourceFile
  #50 = Utf8               ScalaInlineInfo
  #51 = Utf8               Scala
{
  private final shapeless.Witness sn$1;
    descriptor: Lshapeless/Witness;
    flags: (0x0012) ACC_PRIVATE, ACC_FINAL

  public shapeless.Succ<N> apply();
    descriptor: ()Lshapeless/Succ;
    flags: (0x0001) ACC_PUBLIC
    Code:
      stack=1, locals=1, args_size=1
         0: aload_0
         1: getfield      #24                 // Field sn$1:Lshapeless/Witness;
         4: invokeinterface #30,  1           // InterfaceMethod shapeless/Witness.value:()Ljava/lang/Object;
         9: checkcast     #32                 // class shapeless/Succ
        12: areturn
      LineNumberTable:
        line 562: 0
      LocalVariableTable:
        Start  Length  Slot  Name   Signature
            0      13     0  this   Lshapeless/ops/coproduct$Length$$anon$35;
    Signature: #22                          // ()Lshapeless/Succ<TN;>;

  public java.lang.Object apply();
    descriptor: ()Ljava/lang/Object;
    flags: (0x1041) ACC_PUBLIC, ACC_BRIDGE, ACC_SYNTHETIC
    Code:
      stack=1, locals=1, args_size=1
         0: aload_0
         1: invokevirtual #36                 // Method apply:()Lshapeless/Succ;
         4: areturn
      LineNumberTable:
        line 559: 0
      LocalVariableTable:
        Start  Length  Slot  Name   Signature
            0       5     0  this   Lshapeless/ops/coproduct$Length$$anon$35;

  public shapeless.ops.coproduct$Length$$anon$35(shapeless.Witness);
    descriptor: (Lshapeless/Witness;)V
    flags: (0x0001) ACC_PUBLIC
    Code:
      stack=2, locals=2, args_size=2
         0: aload_0
         1: aload_1
         2: putfield      #24                 // Field sn$1:Lshapeless/Witness;
         5: aload_0
         6: invokespecial #41                 // Method java/lang/Object."<init>":()V
         9: return
      LineNumberTable:
        line 559: 0
      LocalVariableTable:
        Start  Length  Slot  Name   Signature
            0      10     0  this   Lshapeless/ops/coproduct$Length$$anon$35;
            0      10     1  sn$1   Lshapeless/Witness;
    MethodParameters:
      Name                           Flags
      sn$1                           final
}
InnerClasses:
  public static #16= #7 of #15;           // Length=class shapeless/ops/coproduct$Length of class shapeless/ops/coproduct
  public static #17= #10 of #15;          // Length$=class shapeless/ops/coproduct$Length$ of class shapeless/ops/coproduct
  public final #2;                        // class shapeless/ops/coproduct$Length$$anon$35
EnclosingMethod: #10.#13                // shapeless.ops.coproduct$Length$.coproductLength
Signature: #3                           // Ljava/lang/Object;Lshapeless/ops/coproduct$Length<Lshapeless/$colon$plus$colon<TH;TT;>;>;
SourceFile: "coproduct.scala"
  ScalaInlineInfo: length = 0x13 (unknown attribute)
   01 01 00 03 00 25 00 26 01 00 14 00 1C 01 00 14
   00 15 01
  Scala: length = 0x0 (unknown attribute)

