Classfile /Users/mw/Projects/slang-braindump/.jar/jar8/assemble/slang-braindump/assemble/content/shapeless/ops/coproduct$$anon$71.class
  Last modified May 29, 2022; size 5496 bytes
  SHA-256 checksum fa13f97fc086bf8a4b0fd59e55e33c6ed7a3ae0c883ecc2f7de00bf9fc8224c3
  Compiled from "coproduct.scala"
public final class shapeless.ops.coproduct$$anon$71 extends java.lang.Object implements scala.math.PartialOrdering<shapeless.$colon$plus$colon<H, T>>
  minor version: 0
  major version: 52
  flags: (0x0031) ACC_PUBLIC, ACC_FINAL, ACC_SUPER
  this_class: #2                          // shapeless/ops/coproduct$$anon$71
  super_class: #5                         // java/lang/Object
  interfaces: 1, fields: 2, methods: 13, attributes: 7
Constant pool:
    #1 = Utf8               shapeless/ops/coproduct$$anon$71
    #2 = Class              #1            // shapeless/ops/coproduct$$anon$71
    #3 = Utf8               Ljava/lang/Object;Lscala/math/PartialOrdering<Lshapeless/$colon$plus$colon<TH;TT;>;>;
    #4 = Utf8               java/lang/Object
    #5 = Class              #4            // java/lang/Object
    #6 = Utf8               scala/math/PartialOrdering
    #7 = Class              #6            // scala/math/PartialOrdering
    #8 = Utf8               coproduct.scala
    #9 = Utf8               shapeless/ops/coproduct$
   #10 = Class              #9            // shapeless/ops/coproduct$
   #11 = Utf8               coproductPartialOrdering
   #12 = Utf8               (Lscala/math/Ordering;Lscala/math/PartialOrdering;)Lscala/math/PartialOrdering;
   #13 = NameAndType        #11:#12       // coproductPartialOrdering:(Lscala/math/Ordering;Lscala/math/PartialOrdering;)Lscala/math/PartialOrdering;
   #14 = Utf8               java/lang/invoke/MethodHandles$Lookup
   #15 = Class              #14           // java/lang/invoke/MethodHandles$Lookup
   #16 = Utf8               java/lang/invoke/MethodHandles
   #17 = Class              #16           // java/lang/invoke/MethodHandles
   #18 = Utf8               Lookup
   #19 = Utf8               ordering$1
   #20 = Utf8               Lscala/math/Ordering;
   #21 = Utf8               partialOrdering$1
   #22 = Utf8               Lscala/math/PartialOrdering;
   #23 = Utf8               gteq
   #24 = Utf8               (Ljava/lang/Object;Ljava/lang/Object;)Z
   #25 = Utf8               x
   #26 = Utf8               y
   #27 = Utf8               gteq$
   #28 = Utf8               (Lscala/math/PartialOrdering;Ljava/lang/Object;Ljava/lang/Object;)Z
   #29 = NameAndType        #27:#28       // gteq$:(Lscala/math/PartialOrdering;Ljava/lang/Object;Ljava/lang/Object;)Z
   #30 = InterfaceMethodref #7.#29        // scala/math/PartialOrdering.gteq$:(Lscala/math/PartialOrdering;Ljava/lang/Object;Ljava/lang/Object;)Z
   #31 = Utf8               this
   #32 = Utf8               Lshapeless/ops/coproduct$$anon$71;
   #33 = Utf8               Ljava/lang/Object;
   #34 = Utf8               lt
   #35 = Utf8               lt$
   #36 = NameAndType        #35:#28       // lt$:(Lscala/math/PartialOrdering;Ljava/lang/Object;Ljava/lang/Object;)Z
   #37 = InterfaceMethodref #7.#36        // scala/math/PartialOrdering.lt$:(Lscala/math/PartialOrdering;Ljava/lang/Object;Ljava/lang/Object;)Z
   #38 = Utf8               gt
   #39 = Utf8               gt$
   #40 = NameAndType        #39:#28       // gt$:(Lscala/math/PartialOrdering;Ljava/lang/Object;Ljava/lang/Object;)Z
   #41 = InterfaceMethodref #7.#40        // scala/math/PartialOrdering.gt$:(Lscala/math/PartialOrdering;Ljava/lang/Object;Ljava/lang/Object;)Z
   #42 = Utf8               equiv
   #43 = Utf8               equiv$
   #44 = NameAndType        #43:#28       // equiv$:(Lscala/math/PartialOrdering;Ljava/lang/Object;Ljava/lang/Object;)Z
   #45 = InterfaceMethodref #7.#44        // scala/math/PartialOrdering.equiv$:(Lscala/math/PartialOrdering;Ljava/lang/Object;Ljava/lang/Object;)Z
   #46 = Utf8               reverse
   #47 = Utf8               ()Lscala/math/PartialOrdering;
   #48 = Utf8               ()Lscala/math/PartialOrdering<Lshapeless/$colon$plus$colon<TH;TT;>;>;
   #49 = Utf8               reverse$
   #50 = Utf8               (Lscala/math/PartialOrdering;)Lscala/math/PartialOrdering;
   #51 = NameAndType        #49:#50       // reverse$:(Lscala/math/PartialOrdering;)Lscala/math/PartialOrdering;
   #52 = InterfaceMethodref #7.#51        // scala/math/PartialOrdering.reverse$:(Lscala/math/PartialOrdering;)Lscala/math/PartialOrdering;
   #53 = Utf8               lteq
   #54 = Utf8               (Lshapeless/$colon$plus$colon;Lshapeless/$colon$plus$colon;)Z
   #55 = Utf8               (Lshapeless/$colon$plus$colon<TH;TT;>;Lshapeless/$colon$plus$colon<TH;TT;>;)Z
   #56 = Utf8               scala/Tuple2
   #57 = Class              #56           // scala/Tuple2
   #58 = Utf8               <init>
   #59 = Utf8               (Ljava/lang/Object;Ljava/lang/Object;)V
   #60 = NameAndType        #58:#59       // "<init>":(Ljava/lang/Object;Ljava/lang/Object;)V
   #61 = Methodref          #57.#60       // scala/Tuple2."<init>":(Ljava/lang/Object;Ljava/lang/Object;)V
   #62 = Utf8               _1
   #63 = Utf8               ()Ljava/lang/Object;
   #64 = NameAndType        #62:#63       // _1:()Ljava/lang/Object;
   #65 = Methodref          #57.#64       // scala/Tuple2._1:()Ljava/lang/Object;
   #66 = Utf8               shapeless/$colon$plus$colon
   #67 = Class              #66           // shapeless/$colon$plus$colon
   #68 = Utf8               _2
   #69 = NameAndType        #68:#63       // _2:()Ljava/lang/Object;
   #70 = Methodref          #57.#69       // scala/Tuple2._2:()Ljava/lang/Object;
   #71 = Utf8               shapeless/Inl
   #72 = Class              #71           // shapeless/Inl
   #73 = Utf8               head
   #74 = NameAndType        #73:#63       // head:()Ljava/lang/Object;
   #75 = Methodref          #72.#74       // shapeless/Inl.head:()Ljava/lang/Object;
   #76 = NameAndType        #19:#20       // ordering$1:Lscala/math/Ordering;
   #77 = Fieldref           #2.#76        // shapeless/ops/coproduct$$anon$71.ordering$1:Lscala/math/Ordering;
   #78 = Utf8               scala/math/Ordering
   #79 = Class              #78           // scala/math/Ordering
   #80 = Utf8               compare
   #81 = Utf8               (Ljava/lang/Object;Ljava/lang/Object;)I
   #82 = NameAndType        #80:#81       // compare:(Ljava/lang/Object;Ljava/lang/Object;)I
   #83 = InterfaceMethodref #79.#82       // scala/math/Ordering.compare:(Ljava/lang/Object;Ljava/lang/Object;)I
   #84 = Utf8               shapeless/Inr
   #85 = Class              #84           // shapeless/Inr
   #86 = Utf8               tail
   #87 = Utf8               ()Lshapeless/Coproduct;
   #88 = NameAndType        #86:#87       // tail:()Lshapeless/Coproduct;
   #89 = Methodref          #85.#88       // shapeless/Inr.tail:()Lshapeless/Coproduct;
   #90 = NameAndType        #21:#22       // partialOrdering$1:Lscala/math/PartialOrdering;
   #91 = Fieldref           #2.#90        // shapeless/ops/coproduct$$anon$71.partialOrdering$1:Lscala/math/PartialOrdering;
   #92 = Utf8               tryCompare
   #93 = Utf8               (Ljava/lang/Object;Ljava/lang/Object;)Lscala/Option;
   #94 = NameAndType        #92:#93       // tryCompare:(Ljava/lang/Object;Ljava/lang/Object;)Lscala/Option;
   #95 = InterfaceMethodref #7.#94        // scala/math/PartialOrdering.tryCompare:(Ljava/lang/Object;Ljava/lang/Object;)Lscala/Option;
   #96 = Utf8               ()Z
   #97 = MethodType         #96           //  ()Z
   #98 = Utf8               $anonfun$lteq$1
   #99 = NameAndType        #98:#96       // $anonfun$lteq$1:()Z
  #100 = Methodref          #2.#99        // shapeless/ops/coproduct$$anon$71.$anonfun$lteq$1:()Z
  #101 = MethodHandle       6:#100        // REF_invokeStatic shapeless/ops/coproduct$$anon$71.$anonfun$lteq$1:()Z
  #102 = Integer            1
  #103 = Utf8               java/lang/invoke/LambdaMetafactory
  #104 = Class              #103          // java/lang/invoke/LambdaMetafactory
  #105 = Utf8               altMetafactory
  #106 = Utf8               (Ljava/lang/invoke/MethodHandles$Lookup;Ljava/lang/String;Ljava/lang/invoke/MethodType;[Ljava/lang/Object;)Ljava/lang/invoke/CallSite;
  #107 = NameAndType        #105:#106     // altMetafactory:(Ljava/lang/invoke/MethodHandles$Lookup;Ljava/lang/String;Ljava/lang/invoke/MethodType;[Ljava/lang/Object;)Ljava/lang/invoke/CallSite;
  #108 = Methodref          #104.#107     // java/lang/invoke/LambdaMetafactory.altMetafactory:(Ljava/lang/invoke/MethodHandles$Lookup;Ljava/lang/String;Ljava/lang/invoke/MethodType;[Ljava/lang/Object;)Ljava/lang/invoke/CallSite;
  #109 = MethodHandle       6:#108        // REF_invokeStatic java/lang/invoke/LambdaMetafactory.altMetafactory:(Ljava/lang/invoke/MethodHandles$Lookup;Ljava/lang/String;Ljava/lang/invoke/MethodType;[Ljava/lang/Object;)Ljava/lang/invoke/CallSite;
  #110 = Utf8               apply$mcZ$sp
  #111 = Utf8               ()Lscala/runtime/java8/JFunction0$mcZ$sp;
  #112 = NameAndType        #110:#111     // apply$mcZ$sp:()Lscala/runtime/java8/JFunction0$mcZ$sp;
  #113 = InvokeDynamic      #0:#112       // #0:apply$mcZ$sp:()Lscala/runtime/java8/JFunction0$mcZ$sp;
  #114 = Utf8               (I)Z
  #115 = MethodType         #114          //  (I)Z
  #116 = Utf8               $anonfun$lteq$2
  #117 = NameAndType        #116:#114     // $anonfun$lteq$2:(I)Z
  #118 = Methodref          #2.#117       // shapeless/ops/coproduct$$anon$71.$anonfun$lteq$2:(I)Z
  #119 = MethodHandle       6:#118        // REF_invokeStatic shapeless/ops/coproduct$$anon$71.$anonfun$lteq$2:(I)Z
  #120 = Utf8               apply$mcZI$sp
  #121 = Utf8               ()Lscala/runtime/java8/JFunction1$mcZI$sp;
  #122 = NameAndType        #120:#121     // apply$mcZI$sp:()Lscala/runtime/java8/JFunction1$mcZI$sp;
  #123 = InvokeDynamic      #1:#122       // #1:apply$mcZI$sp:()Lscala/runtime/java8/JFunction1$mcZI$sp;
  #124 = Utf8               scala/Option
  #125 = Class              #124          // scala/Option
  #126 = Utf8               fold
  #127 = Utf8               (Lscala/Function0;Lscala/Function1;)Ljava/lang/Object;
  #128 = NameAndType        #126:#127     // fold:(Lscala/Function0;Lscala/Function1;)Ljava/lang/Object;
  #129 = Methodref          #125.#128     // scala/Option.fold:(Lscala/Function0;Lscala/Function1;)Ljava/lang/Object;
  #130 = Utf8               scala/runtime/BoxesRunTime
  #131 = Class              #130          // scala/runtime/BoxesRunTime
  #132 = Utf8               unboxToBoolean
  #133 = Utf8               (Ljava/lang/Object;)Z
  #134 = NameAndType        #132:#133     // unboxToBoolean:(Ljava/lang/Object;)Z
  #135 = Methodref          #131.#134     // scala/runtime/BoxesRunTime.unboxToBoolean:(Ljava/lang/Object;)Z
  #136 = Utf8               yh
  #137 = Utf8               xh
  #138 = Utf8               yt
  #139 = Utf8               Lshapeless/Coproduct;
  #140 = Utf8               xt
  #141 = Utf8               Lshapeless/$colon$plus$colon;
  #142 = Utf8               shapeless/Coproduct
  #143 = Class              #142          // shapeless/Coproduct
  #144 = Utf8               (Lshapeless/$colon$plus$colon;Lshapeless/$colon$plus$colon;)Lscala/Option;
  #145 = Utf8               (Lshapeless/$colon$plus$colon<TH;TT;>;Lshapeless/$colon$plus$colon<TH;TT;>;)Lscala/Option<Ljava/lang/Object;>;
  #146 = Utf8               scala/Some
  #147 = Class              #146          // scala/Some
  #148 = Utf8               boxToInteger
  #149 = Utf8               (I)Ljava/lang/Integer;
  #150 = NameAndType        #148:#149     // boxToInteger:(I)Ljava/lang/Integer;
  #151 = Methodref          #131.#150     // scala/runtime/BoxesRunTime.boxToInteger:(I)Ljava/lang/Integer;
  #152 = Utf8               (Ljava/lang/Object;)V
  #153 = NameAndType        #58:#152      // "<init>":(Ljava/lang/Object;)V
  #154 = Methodref          #147.#153     // scala/Some."<init>":(Ljava/lang/Object;)V
  #155 = Utf8               scala/None$
  #156 = Class              #155          // scala/None$
  #157 = Utf8               MODULE$
  #158 = Utf8               Lscala/None$;
  #159 = NameAndType        #157:#158     // MODULE$:Lscala/None$;
  #160 = Fieldref           #156.#159     // scala/None$.MODULE$:Lscala/None$;
  #161 = NameAndType        #92:#144      // tryCompare:(Lshapeless/$colon$plus$colon;Lshapeless/$colon$plus$colon;)Lscala/Option;
  #162 = Methodref          #2.#161       // shapeless/ops/coproduct$$anon$71.tryCompare:(Lshapeless/$colon$plus$colon;Lshapeless/$colon$plus$colon;)Lscala/Option;
  #163 = NameAndType        #53:#54       // lteq:(Lshapeless/$colon$plus$colon;Lshapeless/$colon$plus$colon;)Z
  #164 = Methodref          #2.#163       // shapeless/ops/coproduct$$anon$71.lteq:(Lshapeless/$colon$plus$colon;Lshapeless/$colon$plus$colon;)Z
  #165 = Utf8               x$2
  #166 = Utf8               I
  #167 = Utf8               (Lscala/math/Ordering;Lscala/math/PartialOrdering;)V
  #168 = Utf8               ()V
  #169 = NameAndType        #58:#168      // "<init>":()V
  #170 = Methodref          #5.#169       // java/lang/Object."<init>":()V
  #171 = Utf8               $init$
  #172 = Utf8               (Lscala/math/PartialOrdering;)V
  #173 = NameAndType        #171:#172     // $init$:(Lscala/math/PartialOrdering;)V
  #174 = InterfaceMethodref #7.#173       // scala/math/PartialOrdering.$init$:(Lscala/math/PartialOrdering;)V
  #175 = Utf8               $deserializeLambda$
  #176 = Utf8               (Ljava/lang/invoke/SerializedLambda;)Ljava/lang/Object;
  #177 = Utf8               scala/runtime/LambdaDeserialize
  #178 = Class              #177          // scala/runtime/LambdaDeserialize
  #179 = Utf8               bootstrap
  #180 = Utf8               (Ljava/lang/invoke/MethodHandles$Lookup;Ljava/lang/String;Ljava/lang/invoke/MethodType;[Ljava/lang/invoke/MethodHandle;)Ljava/lang/invoke/CallSite;
  #181 = NameAndType        #179:#180     // bootstrap:(Ljava/lang/invoke/MethodHandles$Lookup;Ljava/lang/String;Ljava/lang/invoke/MethodType;[Ljava/lang/invoke/MethodHandle;)Ljava/lang/invoke/CallSite;
  #182 = Methodref          #178.#181     // scala/runtime/LambdaDeserialize.bootstrap:(Ljava/lang/invoke/MethodHandles$Lookup;Ljava/lang/String;Ljava/lang/invoke/MethodType;[Ljava/lang/invoke/MethodHandle;)Ljava/lang/invoke/CallSite;
  #183 = MethodHandle       6:#182        // REF_invokeStatic scala/runtime/LambdaDeserialize.bootstrap:(Ljava/lang/invoke/MethodHandles$Lookup;Ljava/lang/String;Ljava/lang/invoke/MethodType;[Ljava/lang/invoke/MethodHandle;)Ljava/lang/invoke/CallSite;
  #184 = Utf8               lambdaDeserialize
  #185 = NameAndType        #184:#176     // lambdaDeserialize:(Ljava/lang/invoke/SerializedLambda;)Ljava/lang/Object;
  #186 = InvokeDynamic      #2:#185       // #2:lambdaDeserialize:(Ljava/lang/invoke/SerializedLambda;)Ljava/lang/Object;
  #187 = Utf8               Code
  #188 = Utf8               LineNumberTable
  #189 = Utf8               LocalVariableTable
  #190 = Utf8               MethodParameters
  #191 = Utf8               Signature
  #192 = Utf8               StackMapTable
  #193 = Utf8               InnerClasses
  #194 = Utf8               EnclosingMethod
  #195 = Utf8               SourceFile
  #196 = Utf8               BootstrapMethods
  #197 = Utf8               ScalaInlineInfo
  #198 = Utf8               Scala
{
  private final scala.math.Ordering ordering$1;
    descriptor: Lscala/math/Ordering;
    flags: (0x0012) ACC_PRIVATE, ACC_FINAL

  private final scala.math.PartialOrdering partialOrdering$1;
    descriptor: Lscala/math/PartialOrdering;
    flags: (0x0012) ACC_PRIVATE, ACC_FINAL

  public boolean gteq(java.lang.Object, java.lang.Object);
    descriptor: (Ljava/lang/Object;Ljava/lang/Object;)Z
    flags: (0x0001) ACC_PUBLIC
    Code:
      stack=3, locals=3, args_size=3
         0: aload_0
         1: aload_1
         2: aload_2
         3: invokestatic  #30                 // InterfaceMethod scala/math/PartialOrdering.gteq$:(Lscala/math/PartialOrdering;Ljava/lang/Object;Ljava/lang/Object;)Z
         6: ireturn
      LineNumberTable:
        line 1135: 0
      LocalVariableTable:
        Start  Length  Slot  Name   Signature
            0       7     0  this   Lshapeless/ops/coproduct$$anon$71;
            0       7     1     x   Ljava/lang/Object;
            0       7     2     y   Ljava/lang/Object;
    MethodParameters:
      Name                           Flags
      x                              final
      y                              final

  public boolean lt(java.lang.Object, java.lang.Object);
    descriptor: (Ljava/lang/Object;Ljava/lang/Object;)Z
    flags: (0x0001) ACC_PUBLIC
    Code:
      stack=3, locals=3, args_size=3
         0: aload_0
         1: aload_1
         2: aload_2
         3: invokestatic  #37                 // InterfaceMethod scala/math/PartialOrdering.lt$:(Lscala/math/PartialOrdering;Ljava/lang/Object;Ljava/lang/Object;)Z
         6: ireturn
      LineNumberTable:
        line 1135: 0
      LocalVariableTable:
        Start  Length  Slot  Name   Signature
            0       7     0  this   Lshapeless/ops/coproduct$$anon$71;
            0       7     1     x   Ljava/lang/Object;
            0       7     2     y   Ljava/lang/Object;
    MethodParameters:
      Name                           Flags
      x                              final
      y                              final

  public boolean gt(java.lang.Object, java.lang.Object);
    descriptor: (Ljava/lang/Object;Ljava/lang/Object;)Z
    flags: (0x0001) ACC_PUBLIC
    Code:
      stack=3, locals=3, args_size=3
         0: aload_0
         1: aload_1
         2: aload_2
         3: invokestatic  #41                 // InterfaceMethod scala/math/PartialOrdering.gt$:(Lscala/math/PartialOrdering;Ljava/lang/Object;Ljava/lang/Object;)Z
         6: ireturn
      LineNumberTable:
        line 1135: 0
      LocalVariableTable:
        Start  Length  Slot  Name   Signature
            0       7     0  this   Lshapeless/ops/coproduct$$anon$71;
            0       7     1     x   Ljava/lang/Object;
            0       7     2     y   Ljava/lang/Object;
    MethodParameters:
      Name                           Flags
      x                              final
      y                              final

  public boolean equiv(java.lang.Object, java.lang.Object);
    descriptor: (Ljava/lang/Object;Ljava/lang/Object;)Z
    flags: (0x0001) ACC_PUBLIC
    Code:
      stack=3, locals=3, args_size=3
         0: aload_0
         1: aload_1
         2: aload_2
         3: invokestatic  #45                 // InterfaceMethod scala/math/PartialOrdering.equiv$:(Lscala/math/PartialOrdering;Ljava/lang/Object;Ljava/lang/Object;)Z
         6: ireturn
      LineNumberTable:
        line 1135: 0
      LocalVariableTable:
        Start  Length  Slot  Name   Signature
            0       7     0  this   Lshapeless/ops/coproduct$$anon$71;
            0       7     1     x   Ljava/lang/Object;
            0       7     2     y   Ljava/lang/Object;
    MethodParameters:
      Name                           Flags
      x                              final
      y                              final

  public scala.math.PartialOrdering<shapeless.$colon$plus$colon<H, T>> reverse();
    descriptor: ()Lscala/math/PartialOrdering;
    flags: (0x0001) ACC_PUBLIC
    Code:
      stack=1, locals=1, args_size=1
         0: aload_0
         1: invokestatic  #52                 // InterfaceMethod scala/math/PartialOrdering.reverse$:(Lscala/math/PartialOrdering;)Lscala/math/PartialOrdering;
         4: areturn
      LineNumberTable:
        line 1135: 0
      LocalVariableTable:
        Start  Length  Slot  Name   Signature
            0       5     0  this   Lshapeless/ops/coproduct$$anon$71;
    Signature: #48                          // ()Lscala/math/PartialOrdering<Lshapeless/$colon$plus$colon<TH;TT;>;>;

  public boolean lteq(shapeless.$colon$plus$colon<H, T>, shapeless.$colon$plus$colon<H, T>);
    descriptor: (Lshapeless/$colon$plus$colon;Lshapeless/$colon$plus$colon;)Z
    flags: (0x0001) ACC_PUBLIC
    Code:
      stack=4, locals=17, args_size=3
         0: new           #57                 // class scala/Tuple2
         3: dup
         4: aload_1
         5: aload_2
         6: invokespecial #61                 // Method scala/Tuple2."<init>":(Ljava/lang/Object;Ljava/lang/Object;)V
         9: astore        4
        11: aload         4
        13: ifnull        112
        16: aload         4
        18: invokevirtual #65                 // Method scala/Tuple2._1:()Ljava/lang/Object;
        21: checkcast     #67                 // class shapeless/$colon$plus$colon
        24: astore        5
        26: aload         4
        28: invokevirtual #70                 // Method scala/Tuple2._2:()Ljava/lang/Object;
        31: checkcast     #67                 // class shapeless/$colon$plus$colon
        34: astore        6
        36: aload         5
        38: instanceof    #72                 // class shapeless/Inl
        41: ifeq          109
        44: aload         5
        46: checkcast     #72                 // class shapeless/Inl
        49: astore        7
        51: aload         7
        53: invokevirtual #75                 // Method shapeless/Inl.head:()Ljava/lang/Object;
        56: astore        8
        58: aload         6
        60: instanceof    #72                 // class shapeless/Inl
        63: ifeq          106
        66: aload         6
        68: checkcast     #72                 // class shapeless/Inl
        71: astore        9
        73: aload         9
        75: invokevirtual #75                 // Method shapeless/Inl.head:()Ljava/lang/Object;
        78: astore        10
        80: aload_0
        81: getfield      #77                 // Field ordering$1:Lscala/math/Ordering;
        84: aload         8
        86: aload         10
        88: invokeinterface #83,  3           // InterfaceMethod scala/math/Ordering.compare:(Ljava/lang/Object;Ljava/lang/Object;)I
        93: iconst_0
        94: if_icmpgt     101
        97: iconst_1
        98: goto          102
       101: iconst_0
       102: istore_3
       103: goto          231
       106: goto          115
       109: goto          115
       112: goto          115
       115: aload         4
       117: ifnull        223
       120: aload         4
       122: invokevirtual #65                 // Method scala/Tuple2._1:()Ljava/lang/Object;
       125: checkcast     #67                 // class shapeless/$colon$plus$colon
       128: astore        11
       130: aload         4
       132: invokevirtual #70                 // Method scala/Tuple2._2:()Ljava/lang/Object;
       135: checkcast     #67                 // class shapeless/$colon$plus$colon
       138: astore        12
       140: aload         11
       142: instanceof    #85                 // class shapeless/Inr
       145: ifeq          220
       148: aload         11
       150: checkcast     #85                 // class shapeless/Inr
       153: astore        13
       155: aload         13
       157: invokevirtual #89                 // Method shapeless/Inr.tail:()Lshapeless/Coproduct;
       160: astore        14
       162: aload         12
       164: instanceof    #85                 // class shapeless/Inr
       167: ifeq          217
       170: aload         12
       172: checkcast     #85                 // class shapeless/Inr
       175: astore        15
       177: aload         15
       179: invokevirtual #89                 // Method shapeless/Inr.tail:()Lshapeless/Coproduct;
       182: astore        16
       184: aload_0
       185: getfield      #91                 // Field partialOrdering$1:Lscala/math/PartialOrdering;
       188: aload         14
       190: aload         16
       192: invokeinterface #95,  3           // InterfaceMethod scala/math/PartialOrdering.tryCompare:(Ljava/lang/Object;Ljava/lang/Object;)Lscala/Option;
       197: invokedynamic #113,  0            // InvokeDynamic #0:apply$mcZ$sp:()Lscala/runtime/java8/JFunction0$mcZ$sp;
       202: invokedynamic #123,  0            // InvokeDynamic #1:apply$mcZI$sp:()Lscala/runtime/java8/JFunction1$mcZI$sp;
       207: invokevirtual #129                // Method scala/Option.fold:(Lscala/Function0;Lscala/Function1;)Ljava/lang/Object;
       210: invokestatic  #135                // Method scala/runtime/BoxesRunTime.unboxToBoolean:(Ljava/lang/Object;)Z
       213: istore_3
       214: goto          231
       217: goto          226
       220: goto          226
       223: goto          226
       226: iconst_0
       227: istore_3
       228: goto          231
       231: iload_3
       232: ireturn
      StackMapTable: number_of_entries = 11
        frame_type = 255 /* full_frame */
          offset_delta = 101
          locals = [ class shapeless/ops/coproduct$$anon$71, class shapeless/$colon$plus$colon, class shapeless/$colon$plus$colon, top, class scala/Tuple2, class shapeless/$colon$plus$colon, class shapeless/$colon$plus$colon, class shapeless/Inl, class java/lang/Object, class shapeless/Inl, class java/lang/Object ]
          stack = []
        frame_type = 64 /* same_locals_1_stack_item */
          stack = [ int ]
        frame_type = 249 /* chop */
          offset_delta = 3
        frame_type = 249 /* chop */
          offset_delta = 2
        frame_type = 249 /* chop */
          offset_delta = 2
        frame_type = 2 /* same */
        frame_type = 255 /* full_frame */
          offset_delta = 101
          locals = [ class shapeless/ops/coproduct$$anon$71, class shapeless/$colon$plus$colon, class shapeless/$colon$plus$colon, top, class scala/Tuple2, top, top, top, top, top, top, class shapeless/$colon$plus$colon, class shapeless/$colon$plus$colon, class shapeless/Inr, class shapeless/Coproduct ]
          stack = []
        frame_type = 249 /* chop */
          offset_delta = 2
        frame_type = 255 /* full_frame */
          offset_delta = 2
          locals = [ class shapeless/ops/coproduct$$anon$71, class shapeless/$colon$plus$colon, class shapeless/$colon$plus$colon, top, class scala/Tuple2 ]
          stack = []
        frame_type = 2 /* same */
        frame_type = 255 /* full_frame */
          offset_delta = 4
          locals = [ class shapeless/ops/coproduct$$anon$71, class shapeless/$colon$plus$colon, class shapeless/$colon$plus$colon, int, class scala/Tuple2 ]
          stack = []
      LineNumberTable:
        line 1136: 0
        line 1137: 11
        line 1138: 115
        line 1139: 226
        line 1136: 231
      LocalVariableTable:
        Start  Length  Slot  Name   Signature
           78      28    10    yh   Ljava/lang/Object;
           56      53     8    xh   Ljava/lang/Object;
          182      35    16    yt   Lshapeless/Coproduct;
          160      60    14    xt   Lshapeless/Coproduct;
            0     233     0  this   Lshapeless/ops/coproduct$$anon$71;
            0     233     1     x   Lshapeless/$colon$plus$colon;
            0     233     2     y   Lshapeless/$colon$plus$colon;
    Signature: #55                          // (Lshapeless/$colon$plus$colon<TH;TT;>;Lshapeless/$colon$plus$colon<TH;TT;>;)Z
    MethodParameters:
      Name                           Flags
      x                              final
      y                              final

  public scala.Option<java.lang.Object> tryCompare(shapeless.$colon$plus$colon<H, T>, shapeless.$colon$plus$colon<H, T>);
    descriptor: (Lshapeless/$colon$plus$colon;Lshapeless/$colon$plus$colon;)Lscala/Option;
    flags: (0x0001) ACC_PUBLIC
    Code:
      stack=5, locals=17, args_size=3
         0: new           #57                 // class scala/Tuple2
         3: dup
         4: aload_1
         5: aload_2
         6: invokespecial #61                 // Method scala/Tuple2."<init>":(Ljava/lang/Object;Ljava/lang/Object;)V
         9: astore        4
        11: aload         4
        13: ifnull        113
        16: aload         4
        18: invokevirtual #65                 // Method scala/Tuple2._1:()Ljava/lang/Object;
        21: checkcast     #67                 // class shapeless/$colon$plus$colon
        24: astore        5
        26: aload         4
        28: invokevirtual #70                 // Method scala/Tuple2._2:()Ljava/lang/Object;
        31: checkcast     #67                 // class shapeless/$colon$plus$colon
        34: astore        6
        36: aload         5
        38: instanceof    #72                 // class shapeless/Inl
        41: ifeq          110
        44: aload         5
        46: checkcast     #72                 // class shapeless/Inl
        49: astore        7
        51: aload         7
        53: invokevirtual #75                 // Method shapeless/Inl.head:()Ljava/lang/Object;
        56: astore        8
        58: aload         6
        60: instanceof    #72                 // class shapeless/Inl
        63: ifeq          107
        66: aload         6
        68: checkcast     #72                 // class shapeless/Inl
        71: astore        9
        73: aload         9
        75: invokevirtual #75                 // Method shapeless/Inl.head:()Ljava/lang/Object;
        78: astore        10
        80: new           #147                // class scala/Some
        83: dup
        84: aload_0
        85: getfield      #77                 // Field ordering$1:Lscala/math/Ordering;
        88: aload         8
        90: aload         10
        92: invokeinterface #83,  3           // InterfaceMethod scala/math/Ordering.compare:(Ljava/lang/Object;Ljava/lang/Object;)I
        97: invokestatic  #151                // Method scala/runtime/BoxesRunTime.boxToInteger:(I)Ljava/lang/Integer;
       100: invokespecial #154                // Method scala/Some."<init>":(Ljava/lang/Object;)V
       103: astore_3
       104: goto          218
       107: goto          116
       110: goto          116
       113: goto          116
       116: aload         4
       118: ifnull        208
       121: aload         4
       123: invokevirtual #65                 // Method scala/Tuple2._1:()Ljava/lang/Object;
       126: checkcast     #67                 // class shapeless/$colon$plus$colon
       129: astore        11
       131: aload         4
       133: invokevirtual #70                 // Method scala/Tuple2._2:()Ljava/lang/Object;
       136: checkcast     #67                 // class shapeless/$colon$plus$colon
       139: astore        12
       141: aload         11
       143: instanceof    #85                 // class shapeless/Inr
       146: ifeq          205
       149: aload         11
       151: checkcast     #85                 // class shapeless/Inr
       154: astore        13
       156: aload         13
       158: invokevirtual #89                 // Method shapeless/Inr.tail:()Lshapeless/Coproduct;
       161: astore        14
       163: aload         12
       165: instanceof    #85                 // class shapeless/Inr
       168: ifeq          202
       171: aload         12
       173: checkcast     #85                 // class shapeless/Inr
       176: astore        15
       178: aload         15
       180: invokevirtual #89                 // Method shapeless/Inr.tail:()Lshapeless/Coproduct;
       183: astore        16
       185: aload_0
       186: getfield      #91                 // Field partialOrdering$1:Lscala/math/PartialOrdering;
       189: aload         14
       191: aload         16
       193: invokeinterface #95,  3           // InterfaceMethod scala/math/PartialOrdering.tryCompare:(Ljava/lang/Object;Ljava/lang/Object;)Lscala/Option;
       198: astore_3
       199: goto          218
       202: goto          211
       205: goto          211
       208: goto          211
       211: getstatic     #160                // Field scala/None$.MODULE$:Lscala/None$;
       214: astore_3
       215: goto          218
       218: aload_3
       219: areturn
      StackMapTable: number_of_entries = 9
        frame_type = 255 /* full_frame */
          offset_delta = 107
          locals = [ class shapeless/ops/coproduct$$anon$71, class shapeless/$colon$plus$colon, class shapeless/$colon$plus$colon, top, class scala/Tuple2, class shapeless/$colon$plus$colon, class shapeless/$colon$plus$colon, class shapeless/Inl, class java/lang/Object ]
          stack = []
        frame_type = 249 /* chop */
          offset_delta = 2
        frame_type = 249 /* chop */
          offset_delta = 2
        frame_type = 2 /* same */
        frame_type = 255 /* full_frame */
          offset_delta = 85
          locals = [ class shapeless/ops/coproduct$$anon$71, class shapeless/$colon$plus$colon, class shapeless/$colon$plus$colon, top, class scala/Tuple2, top, top, top, top, top, top, class shapeless/$colon$plus$colon, class shapeless/$colon$plus$colon, class shapeless/Inr, class shapeless/Coproduct ]
          stack = []
        frame_type = 249 /* chop */
          offset_delta = 2
        frame_type = 255 /* full_frame */
          offset_delta = 2
          locals = [ class shapeless/ops/coproduct$$anon$71, class shapeless/$colon$plus$colon, class shapeless/$colon$plus$colon, top, class scala/Tuple2 ]
          stack = []
        frame_type = 2 /* same */
        frame_type = 255 /* full_frame */
          offset_delta = 6
          locals = [ class shapeless/ops/coproduct$$anon$71, class shapeless/$colon$plus$colon, class shapeless/$colon$plus$colon, class scala/Option, class scala/Tuple2 ]
          stack = []
      LineNumberTable:
        line 1142: 0
        line 1143: 11
        line 1144: 116
        line 1145: 211
        line 1142: 218
      LocalVariableTable:
        Start  Length  Slot  Name   Signature
           78      29    10    yh   Ljava/lang/Object;
           56      54     8    xh   Ljava/lang/Object;
          183      19    16    yt   Lshapeless/Coproduct;
          161      44    14    xt   Lshapeless/Coproduct;
            0     220     0  this   Lshapeless/ops/coproduct$$anon$71;
            0     220     1     x   Lshapeless/$colon$plus$colon;
            0     220     2     y   Lshapeless/$colon$plus$colon;
    Signature: #145                         // (Lshapeless/$colon$plus$colon<TH;TT;>;Lshapeless/$colon$plus$colon<TH;TT;>;)Lscala/Option<Ljava/lang/Object;>;
    MethodParameters:
      Name                           Flags
      x                              final
      y                              final

  public scala.Option tryCompare(java.lang.Object, java.lang.Object);
    descriptor: (Ljava/lang/Object;Ljava/lang/Object;)Lscala/Option;
    flags: (0x1041) ACC_PUBLIC, ACC_BRIDGE, ACC_SYNTHETIC
    Code:
      stack=3, locals=3, args_size=3
         0: aload_0
         1: aload_1
         2: checkcast     #67                 // class shapeless/$colon$plus$colon
         5: aload_2
         6: checkcast     #67                 // class shapeless/$colon$plus$colon
         9: invokevirtual #162                // Method tryCompare:(Lshapeless/$colon$plus$colon;Lshapeless/$colon$plus$colon;)Lscala/Option;
        12: areturn
      LineNumberTable:
        line 1135: 0
      LocalVariableTable:
        Start  Length  Slot  Name   Signature
            0      13     0  this   Lshapeless/ops/coproduct$$anon$71;
            0      13     1     x   Ljava/lang/Object;
            0      13     2     y   Ljava/lang/Object;
    MethodParameters:
      Name                           Flags
      x                              final
      y                              final

  public boolean lteq(java.lang.Object, java.lang.Object);
    descriptor: (Ljava/lang/Object;Ljava/lang/Object;)Z
    flags: (0x1041) ACC_PUBLIC, ACC_BRIDGE, ACC_SYNTHETIC
    Code:
      stack=3, locals=3, args_size=3
         0: aload_0
         1: aload_1
         2: checkcast     #67                 // class shapeless/$colon$plus$colon
         5: aload_2
         6: checkcast     #67                 // class shapeless/$colon$plus$colon
         9: invokevirtual #164                // Method lteq:(Lshapeless/$colon$plus$colon;Lshapeless/$colon$plus$colon;)Z
        12: ireturn
      LineNumberTable:
        line 1135: 0
      LocalVariableTable:
        Start  Length  Slot  Name   Signature
            0      13     0  this   Lshapeless/ops/coproduct$$anon$71;
            0      13     1     x   Ljava/lang/Object;
            0      13     2     y   Ljava/lang/Object;
    MethodParameters:
      Name                           Flags
      x                              final
      y                              final

  public static final boolean $anonfun$lteq$1();
    descriptor: ()Z
    flags: (0x1019) ACC_PUBLIC, ACC_STATIC, ACC_FINAL, ACC_SYNTHETIC
    Code:
      stack=1, locals=0, args_size=0
         0: iconst_0
         1: ireturn
      LineNumberTable:
        line 1138: 0

  public static final boolean $anonfun$lteq$2(int);
    descriptor: (I)Z
    flags: (0x1019) ACC_PUBLIC, ACC_STATIC, ACC_FINAL, ACC_SYNTHETIC
    Code:
      stack=2, locals=1, args_size=1
         0: iload_0
         1: iconst_0
         2: if_icmpgt     9
         5: iconst_1
         6: goto          10
         9: iconst_0
        10: ireturn
      StackMapTable: number_of_entries = 2
        frame_type = 9 /* same */
        frame_type = 64 /* same_locals_1_stack_item */
          stack = [ int ]
      LineNumberTable:
        line 1138: 0
      LocalVariableTable:
        Start  Length  Slot  Name   Signature
            0      11     0   x$2   I
    MethodParameters:
      Name                           Flags
      x$2                            final

  public shapeless.ops.coproduct$$anon$71(scala.math.Ordering, scala.math.PartialOrdering);
    descriptor: (Lscala/math/Ordering;Lscala/math/PartialOrdering;)V
    flags: (0x0001) ACC_PUBLIC
    Code:
      stack=2, locals=3, args_size=3
         0: aload_0
         1: aload_1
         2: putfield      #77                 // Field ordering$1:Lscala/math/Ordering;
         5: aload_0
         6: aload_2
         7: putfield      #91                 // Field partialOrdering$1:Lscala/math/PartialOrdering;
        10: aload_0
        11: invokespecial #170                // Method java/lang/Object."<init>":()V
        14: aload_0
        15: invokestatic  #174                // InterfaceMethod scala/math/PartialOrdering.$init$:(Lscala/math/PartialOrdering;)V
        18: return
      LineNumberTable:
        line 1134: 0
        line 1135: 10
      LocalVariableTable:
        Start  Length  Slot  Name   Signature
            0      19     0  this   Lshapeless/ops/coproduct$$anon$71;
            0      19     1 ordering$1   Lscala/math/Ordering;
            0      19     2 partialOrdering$1   Lscala/math/PartialOrdering;
    MethodParameters:
      Name                           Flags
      ordering$1                     final
      partialOrdering$1              final

  private static java.lang.Object $deserializeLambda$(java.lang.invoke.SerializedLambda);
    descriptor: (Ljava/lang/invoke/SerializedLambda;)Ljava/lang/Object;
    flags: (0x100a) ACC_PRIVATE, ACC_STATIC, ACC_SYNTHETIC
    Code:
      stack=1, locals=1, args_size=1
         0: aload_0
         1: invokedynamic #186,  0            // InvokeDynamic #2:lambdaDeserialize:(Ljava/lang/invoke/SerializedLambda;)Ljava/lang/Object;
         6: areturn
}
InnerClasses:
  public static final #18= #15 of #17;    // Lookup=class java/lang/invoke/MethodHandles$Lookup of class java/lang/invoke/MethodHandles
  public final #2;                        // class shapeless/ops/coproduct$$anon$71
EnclosingMethod: #10.#13                // shapeless.ops.coproduct$.coproductPartialOrdering
Signature: #3                           // Ljava/lang/Object;Lscala/math/PartialOrdering<Lshapeless/$colon$plus$colon<TH;TT;>;>;
SourceFile: "coproduct.scala"
BootstrapMethods:
  0: #109 REF_invokeStatic java/lang/invoke/LambdaMetafactory.altMetafactory:(Ljava/lang/invoke/MethodHandles$Lookup;Ljava/lang/String;Ljava/lang/invoke/MethodType;[Ljava/lang/Object;)Ljava/lang/invoke/CallSite;
    Method arguments:
      #97 ()Z
      #101 REF_invokeStatic shapeless/ops/coproduct$$anon$71.$anonfun$lteq$1:()Z
      #97 ()Z
      #102 1
  1: #109 REF_invokeStatic java/lang/invoke/LambdaMetafactory.altMetafactory:(Ljava/lang/invoke/MethodHandles$Lookup;Ljava/lang/String;Ljava/lang/invoke/MethodType;[Ljava/lang/Object;)Ljava/lang/invoke/CallSite;
    Method arguments:
      #115 (I)Z
      #119 REF_invokeStatic shapeless/ops/coproduct$$anon$71.$anonfun$lteq$2:(I)Z
      #115 (I)Z
      #102 1
  2: #183 REF_invokeStatic scala/runtime/LambdaDeserialize.bootstrap:(Ljava/lang/invoke/MethodHandles$Lookup;Ljava/lang/String;Ljava/lang/invoke/MethodType;[Ljava/lang/invoke/MethodHandle;)Ljava/lang/invoke/CallSite;
    Method arguments:
      #101 REF_invokeStatic shapeless/ops/coproduct$$anon$71.$anonfun$lteq$1:()Z
      #119 REF_invokeStatic shapeless/ops/coproduct$$anon$71.$anonfun$lteq$2:(I)Z
  ScalaInlineInfo: length = 0x40 (unknown attribute)
   01 01 00 0C 00 62 00 60 01 00 74 00 72 01 00 3A
   00 A7 01 00 2A 00 18 01 00 26 00 18 01 00 17 00
   18 01 00 22 00 18 01 00 35 00 18 01 00 35 00 36
   01 00 2E 00 2F 01 00 5C 00 5D 01 00 5C 00 90 01

  Scala: length = 0x0 (unknown attribute)

