Classfile /Users/mw/Projects/slang-braindump/.jar/jar8/assemble/slang-braindump/assemble/content/shapeless/ops/coproduct$FlatMap$.class
  Last modified May 29, 2022; size 2443 bytes
  SHA-256 checksum 817d9ce1766d09703f856821d6f82a8112f394fb6f34fa0ba7bbc83c23503a36
  Compiled from "coproduct.scala"
public class shapeless.ops.coproduct$FlatMap$ implements java.io.Serializable
  minor version: 0
  major version: 52
  flags: (0x0021) ACC_PUBLIC, ACC_SUPER
  this_class: #2                          // shapeless/ops/coproduct$FlatMap$
  super_class: #4                         // java/lang/Object
  interfaces: 1, fields: 1, methods: 6, attributes: 4
Constant pool:
   #1 = Utf8               shapeless/ops/coproduct$FlatMap$
   #2 = Class              #1             // shapeless/ops/coproduct$FlatMap$
   #3 = Utf8               java/lang/Object
   #4 = Class              #3             // java/lang/Object
   #5 = Utf8               java/io/Serializable
   #6 = Class              #5             // java/io/Serializable
   #7 = Utf8               coproduct.scala
   #8 = Utf8               shapeless/PolyDefns$Case
   #9 = Class              #8             // shapeless/PolyDefns$Case
  #10 = Utf8               shapeless/PolyDefns
  #11 = Class              #10            // shapeless/PolyDefns
  #12 = Utf8               Case
  #13 = Utf8               shapeless/ops/coproduct$ExtendBy
  #14 = Class              #13            // shapeless/ops/coproduct$ExtendBy
  #15 = Utf8               shapeless/ops/coproduct
  #16 = Class              #15            // shapeless/ops/coproduct
  #17 = Utf8               ExtendBy
  #18 = Utf8               shapeless/ops/coproduct$FlatMap
  #19 = Class              #18            // shapeless/ops/coproduct$FlatMap
  #20 = Utf8               FlatMap
  #21 = Utf8               FlatMap$
  #22 = Utf8               shapeless/ops/coproduct$FlatMap$$anon$16
  #23 = Class              #22            // shapeless/ops/coproduct$FlatMap$$anon$16
  #24 = Utf8               shapeless/ops/coproduct$FlatMap$$anon$17
  #25 = Class              #24            // shapeless/ops/coproduct$FlatMap$$anon$17
  #26 = Utf8               MODULE$
  #27 = Utf8               Lshapeless/ops/coproduct$FlatMap$;
  #28 = Utf8               <clinit>
  #29 = Utf8               ()V
  #30 = Utf8               <init>
  #31 = NameAndType        #30:#29        // "<init>":()V
  #32 = Methodref          #2.#31         // shapeless/ops/coproduct$FlatMap$."<init>":()V
  #33 = NameAndType        #26:#27        // MODULE$:Lshapeless/ops/coproduct$FlatMap$;
  #34 = Fieldref           #2.#33         // shapeless/ops/coproduct$FlatMap$.MODULE$:Lshapeless/ops/coproduct$FlatMap$;
  #35 = Utf8               apply
  #36 = Utf8               (Lshapeless/ops/coproduct$FlatMap;)Lshapeless/ops/coproduct$FlatMap;
  #37 = Utf8               <C::Lshapeless/Coproduct;F::Lshapeless/Poly;>(Lshapeless/ops/coproduct$FlatMap<TC;TF;>;)Lshapeless/ops/coproduct$FlatMap<TC;TF;>;
  #38 = Utf8               folder
  #39 = Utf8               this
  #40 = Utf8               Lshapeless/ops/coproduct$FlatMap;
  #41 = Utf8               cnilFlatMap
  #42 = Utf8               ()Lshapeless/ops/coproduct$FlatMap;
  #43 = Utf8               <F::Lshapeless/Poly;>()Lshapeless/ops/coproduct$FlatMap<Lshapeless/CNil;TF;>;
  #44 = Methodref          #23.#31        // shapeless/ops/coproduct$FlatMap$$anon$16."<init>":()V
  #45 = Utf8               cpFlatMap
  #46 = Utf8               (Lshapeless/PolyDefns$Case;Lshapeless/ops/coproduct$FlatMap;Lshapeless/ops/coproduct$ExtendBy;)Lshapeless/ops/coproduct$FlatMap;
  #47 = Utf8               <H:Ljava/lang/Object;T::Lshapeless/Coproduct;F::Lshapeless/Poly;OutH::Lshapeless/Coproduct;OutT::Lshapeless/Coproduct;>(Lshapeless/PolyDefns$Case<TF;Lshapeless/$colon$colon<TH;Lshapeless/HNil;>;>;Lshapeless/ops/coproduct$FlatMap<TT;TF;>;Lshapeless/ops/coproduct$ExtendBy<TOutH;TOutT;>;)Lshapeless/ops/coproduct$FlatMap<Lshapeless/$colon$plus$colon<TH;TT;>;TF;>;
  #48 = Utf8               fh
  #49 = Utf8               ft
  #50 = Utf8               extendBy
  #51 = Utf8               (Lshapeless/ops/coproduct$ExtendBy;Lshapeless/PolyDefns$Case;Lshapeless/ops/coproduct$FlatMap;)V
  #52 = NameAndType        #30:#51        // "<init>":(Lshapeless/ops/coproduct$ExtendBy;Lshapeless/PolyDefns$Case;Lshapeless/ops/coproduct$FlatMap;)V
  #53 = Methodref          #25.#52        // shapeless/ops/coproduct$FlatMap$$anon$17."<init>":(Lshapeless/ops/coproduct$ExtendBy;Lshapeless/PolyDefns$Case;Lshapeless/ops/coproduct$FlatMap;)V
  #54 = Utf8               Lshapeless/PolyDefns$Case;
  #55 = Utf8               Lshapeless/ops/coproduct$ExtendBy;
  #56 = Utf8               writeReplace
  #57 = Utf8               ()Ljava/lang/Object;
  #58 = Utf8               scala/runtime/ModuleSerializationProxy
  #59 = Class              #58            // scala/runtime/ModuleSerializationProxy
  #60 = Utf8               (Ljava/lang/Class;)V
  #61 = NameAndType        #30:#60        // "<init>":(Ljava/lang/Class;)V
  #62 = Methodref          #59.#61        // scala/runtime/ModuleSerializationProxy."<init>":(Ljava/lang/Class;)V
  #63 = Methodref          #4.#31         // java/lang/Object."<init>":()V
  #64 = Utf8               Code
  #65 = Utf8               LineNumberTable
  #66 = Utf8               LocalVariableTable
  #67 = Utf8               Signature
  #68 = Utf8               MethodParameters
  #69 = Utf8               InnerClasses
  #70 = Utf8               SourceFile
  #71 = Utf8               ScalaInlineInfo
  #72 = Utf8               Scala
{
  public static final shapeless.ops.coproduct$FlatMap$ MODULE$;
    descriptor: Lshapeless/ops/coproduct$FlatMap$;
    flags: (0x0019) ACC_PUBLIC, ACC_STATIC, ACC_FINAL

  public static {};
    descriptor: ()V
    flags: (0x0009) ACC_PUBLIC, ACC_STATIC
    Code:
      stack=2, locals=0, args_size=0
         0: new           #2                  // class shapeless/ops/coproduct$FlatMap$
         3: dup
         4: invokespecial #32                 // Method "<init>":()V
         7: putstatic     #34                 // Field MODULE$:Lshapeless/ops/coproduct$FlatMap$;
        10: return
      LineNumberTable:
        line 285: 0

  public <C extends shapeless.Coproduct, F extends shapeless.Poly> shapeless.ops.coproduct$FlatMap<C, F> apply(shapeless.ops.coproduct$FlatMap<C, F>);
    descriptor: (Lshapeless/ops/coproduct$FlatMap;)Lshapeless/ops/coproduct$FlatMap;
    flags: (0x0001) ACC_PUBLIC
    Code:
      stack=1, locals=2, args_size=2
         0: aload_1
         1: areturn
      LineNumberTable:
        line 286: 0
      LocalVariableTable:
        Start  Length  Slot  Name   Signature
            0       2     0  this   Lshapeless/ops/coproduct$FlatMap$;
            0       2     1 folder   Lshapeless/ops/coproduct$FlatMap;
    Signature: #37                          // <C::Lshapeless/Coproduct;F::Lshapeless/Poly;>(Lshapeless/ops/coproduct$FlatMap<TC;TF;>;)Lshapeless/ops/coproduct$FlatMap<TC;TF;>;
    MethodParameters:
      Name                           Flags
      folder                         final

  public <F extends shapeless.Poly> shapeless.ops.coproduct$FlatMap<shapeless.CNil, F> cnilFlatMap();
    descriptor: ()Lshapeless/ops/coproduct$FlatMap;
    flags: (0x0001) ACC_PUBLIC
    Code:
      stack=2, locals=1, args_size=1
         0: new           #23                 // class shapeless/ops/coproduct$FlatMap$$anon$16
         3: dup
         4: invokespecial #44                 // Method shapeless/ops/coproduct$FlatMap$$anon$16."<init>":()V
         7: areturn
      LineNumberTable:
        line 290: 0
      LocalVariableTable:
        Start  Length  Slot  Name   Signature
            0       8     0  this   Lshapeless/ops/coproduct$FlatMap$;
    Signature: #43                          // <F::Lshapeless/Poly;>()Lshapeless/ops/coproduct$FlatMap<Lshapeless/CNil;TF;>;

  public <H extends java.lang.Object, T extends shapeless.Coproduct, F extends shapeless.Poly, OutH extends shapeless.Coproduct, OutT extends shapeless.Coproduct> shapeless.ops.coproduct$FlatMap<shapeless.$colon$plus$colon<H, T>, F> cpFlatMap(shapeless.PolyDefns$Case<F, shapeless.$colon$colon<H, shapeless.HNil>>, shapeless.ops.coproduct$FlatMap<T, F>, shapeless.ops.coproduct$ExtendBy<OutH, OutT>);
    descriptor: (Lshapeless/PolyDefns$Case;Lshapeless/ops/coproduct$FlatMap;Lshapeless/ops/coproduct$ExtendBy;)Lshapeless/ops/coproduct$FlatMap;
    flags: (0x0001) ACC_PUBLIC
    Code:
      stack=5, locals=4, args_size=4
         0: new           #25                 // class shapeless/ops/coproduct$FlatMap$$anon$17
         3: dup
         4: aload_3
         5: aload_1
         6: aload_2
         7: invokespecial #53                 // Method shapeless/ops/coproduct$FlatMap$$anon$17."<init>":(Lshapeless/ops/coproduct$ExtendBy;Lshapeless/PolyDefns$Case;Lshapeless/ops/coproduct$FlatMap;)V
        10: areturn
      LineNumberTable:
        line 301: 0
      LocalVariableTable:
        Start  Length  Slot  Name   Signature
            0      11     0  this   Lshapeless/ops/coproduct$FlatMap$;
            0      11     1    fh   Lshapeless/PolyDefns$Case;
            0      11     2    ft   Lshapeless/ops/coproduct$FlatMap;
            0      11     3 extendBy   Lshapeless/ops/coproduct$ExtendBy;
    Signature: #47                          // <H:Ljava/lang/Object;T::Lshapeless/Coproduct;F::Lshapeless/Poly;OutH::Lshapeless/Coproduct;OutT::Lshapeless/Coproduct;>(Lshapeless/PolyDefns$Case<TF;Lshapeless/$colon$colon<TH;Lshapeless/HNil;>;>;Lshapeless/ops/coproduct$FlatMap<TT;TF;>;Lshapeless/ops/coproduct$ExtendBy<TOutH;TOutT;>;)Lshapeless/ops/coproduct$FlatMap<Lshapeless/$colon$plus$colon<TH;TT;>;TF;>;
    MethodParameters:
      Name                           Flags
      fh                             final
      ft                             final
      extendBy                       final

  private java.lang.Object writeReplace();
    descriptor: ()Ljava/lang/Object;
    flags: (0x0002) ACC_PRIVATE
    Code:
      stack=3, locals=1, args_size=1
         0: new           #59                 // class scala/runtime/ModuleSerializationProxy
         3: dup
         4: ldc           #2                  // class shapeless/ops/coproduct$FlatMap$
         6: invokespecial #62                 // Method scala/runtime/ModuleSerializationProxy."<init>":(Ljava/lang/Class;)V
         9: areturn
      LineNumberTable:
        line 285: 0
      LocalVariableTable:
        Start  Length  Slot  Name   Signature
            0      10     0  this   Lshapeless/ops/coproduct$FlatMap$;

  public shapeless.ops.coproduct$FlatMap$();
    descriptor: ()V
    flags: (0x0001) ACC_PUBLIC
    Code:
      stack=1, locals=1, args_size=1
         0: aload_0
         1: invokespecial #63                 // Method java/lang/Object."<init>":()V
         4: return
      LineNumberTable:
        line 312: 0
        line 285: 4
      LocalVariableTable:
        Start  Length  Slot  Name   Signature
            0       5     0  this   Lshapeless/ops/coproduct$FlatMap$;
}
InnerClasses:
  public static abstract #12= #9 of #11;  // Case=class shapeless/PolyDefns$Case of class shapeless/PolyDefns
  public static #17= #14 of #16;          // ExtendBy=class shapeless/ops/coproduct$ExtendBy of class shapeless/ops/coproduct
  public static #20= #19 of #16;          // FlatMap=class shapeless/ops/coproduct$FlatMap of class shapeless/ops/coproduct
  public static #21= #2 of #16;           // FlatMap$=class shapeless/ops/coproduct$FlatMap$ of class shapeless/ops/coproduct
  public final #23;                       // class shapeless/ops/coproduct$FlatMap$$anon$16
  public final #25;                       // class shapeless/ops/coproduct$FlatMap$$anon$17
SourceFile: "coproduct.scala"
  ScalaInlineInfo: length = 0x1D (unknown attribute)
   01 01 00 05 00 1E 00 1D 01 00 23 00 24 01 00 29
   00 2A 01 00 2D 00 2E 01 00 38 00 39 01
  Scala: length = 0x0 (unknown attribute)

