Classfile /Users/mw/Projects/slang-braindump/.jar/jar8/assemble/slang-braindump/assemble/content/shapeless/ops/coproduct$ZipWithIndex$Impl$.class
  Last modified May 29, 2022; size 2441 bytes
  SHA-256 checksum de849ba5c2b6110ab274e7e75a57fd42fc01fda4284898c6fce749ada6417c3b
  Compiled from "coproduct.scala"
public class shapeless.ops.coproduct$ZipWithIndex$Impl$ implements java.io.Serializable
  minor version: 0
  major version: 52
  flags: (0x0021) ACC_PUBLIC, ACC_SUPER
  this_class: #2                          // shapeless/ops/coproduct$ZipWithIndex$Impl$
  super_class: #4                         // java/lang/Object
  interfaces: 1, fields: 1, methods: 6, attributes: 4
Constant pool:
   #1 = Utf8               shapeless/ops/coproduct$ZipWithIndex$Impl$
   #2 = Class              #1             // shapeless/ops/coproduct$ZipWithIndex$Impl$
   #3 = Utf8               java/lang/Object
   #4 = Class              #3             // java/lang/Object
   #5 = Utf8               java/io/Serializable
   #6 = Class              #5             // java/io/Serializable
   #7 = Utf8               coproduct.scala
   #8 = Utf8               shapeless/ops/coproduct$ZipWithIndex$
   #9 = Class              #8             // shapeless/ops/coproduct$ZipWithIndex$
  #10 = Utf8               shapeless/ops/coproduct
  #11 = Class              #10            // shapeless/ops/coproduct
  #12 = Utf8               ZipWithIndex$
  #13 = Utf8               shapeless/ops/coproduct$ZipWithIndex$Impl
  #14 = Class              #13            // shapeless/ops/coproduct$ZipWithIndex$Impl
  #15 = Utf8               Impl
  #16 = Utf8               Impl$
  #17 = Utf8               shapeless/ops/coproduct$ZipWithIndex$Impl$$anon$30
  #18 = Class              #17            // shapeless/ops/coproduct$ZipWithIndex$Impl$$anon$30
  #19 = Utf8               shapeless/ops/coproduct$ZipWithIndex$Impl$$anon$31
  #20 = Class              #19            // shapeless/ops/coproduct$ZipWithIndex$Impl$$anon$31
  #21 = Utf8               MODULE$
  #22 = Utf8               Lshapeless/ops/coproduct$ZipWithIndex$Impl$;
  #23 = Utf8               <clinit>
  #24 = Utf8               ()V
  #25 = Utf8               <init>
  #26 = NameAndType        #25:#24        // "<init>":()V
  #27 = Methodref          #2.#26         // shapeless/ops/coproduct$ZipWithIndex$Impl$."<init>":()V
  #28 = NameAndType        #21:#22        // MODULE$:Lshapeless/ops/coproduct$ZipWithIndex$Impl$;
  #29 = Fieldref           #2.#28         // shapeless/ops/coproduct$ZipWithIndex$Impl$.MODULE$:Lshapeless/ops/coproduct$ZipWithIndex$Impl$;
  #30 = Utf8               apply
  #31 = Utf8               (Lshapeless/ops/coproduct$ZipWithIndex$Impl;)Lshapeless/ops/coproduct$ZipWithIndex$Impl;
  #32 = Utf8               <C::Lshapeless/Coproduct;N::Lshapeless/Nat;>(Lshapeless/ops/coproduct$ZipWithIndex$Impl<TC;TN;>;)Lshapeless/ops/coproduct$ZipWithIndex$Impl<TC;TN;>;
  #33 = Utf8               impl
  #34 = Utf8               this
  #35 = Utf8               Lshapeless/ops/coproduct$ZipWithIndex$Impl;
  #36 = Utf8               singleZipWithIndexImpl
  #37 = Utf8               (Lshapeless/Witness;)Lshapeless/ops/coproduct$ZipWithIndex$Impl;
  #38 = Utf8               <CH:Ljava/lang/Object;N::Lshapeless/Nat;>(Lshapeless/Witness;)Lshapeless/ops/coproduct$ZipWithIndex$Impl<Lshapeless/$colon$plus$colon<TCH;Lshapeless/CNil;>;TN;>;
  #39 = Utf8               w
  #40 = Utf8               (Lshapeless/Witness;)V
  #41 = NameAndType        #25:#40        // "<init>":(Lshapeless/Witness;)V
  #42 = Methodref          #18.#41        // shapeless/ops/coproduct$ZipWithIndex$Impl$$anon$30."<init>":(Lshapeless/Witness;)V
  #43 = Utf8               Lshapeless/Witness;
  #44 = Utf8               cpZipWithIndexImpl
  #45 = Utf8               (Lshapeless/ops/coproduct$ZipWithIndex$Impl;Lshapeless/Witness;)Lshapeless/ops/coproduct$ZipWithIndex$Impl;
  #46 = Utf8               <CH:Ljava/lang/Object;CT::Lshapeless/Coproduct;N::Lshapeless/Nat;OutC::Lshapeless/Coproduct;>(Lshapeless/ops/coproduct$ZipWithIndex$Impl<TCT;Lshapeless/Succ<TN;>;>;Lshapeless/Witness;)Lshapeless/ops/coproduct$ZipWithIndex$Impl<Lshapeless/$colon$plus$colon<TCH;TCT;>;TN;>;
  #47 = Utf8               (Lshapeless/Witness;Lshapeless/ops/coproduct$ZipWithIndex$Impl;)V
  #48 = NameAndType        #25:#47        // "<init>":(Lshapeless/Witness;Lshapeless/ops/coproduct$ZipWithIndex$Impl;)V
  #49 = Methodref          #20.#48        // shapeless/ops/coproduct$ZipWithIndex$Impl$$anon$31."<init>":(Lshapeless/Witness;Lshapeless/ops/coproduct$ZipWithIndex$Impl;)V
  #50 = Utf8               writeReplace
  #51 = Utf8               ()Ljava/lang/Object;
  #52 = Utf8               scala/runtime/ModuleSerializationProxy
  #53 = Class              #52            // scala/runtime/ModuleSerializationProxy
  #54 = Utf8               (Ljava/lang/Class;)V
  #55 = NameAndType        #25:#54        // "<init>":(Ljava/lang/Class;)V
  #56 = Methodref          #53.#55        // scala/runtime/ModuleSerializationProxy."<init>":(Ljava/lang/Class;)V
  #57 = Methodref          #4.#26         // java/lang/Object."<init>":()V
  #58 = Utf8               Code
  #59 = Utf8               LineNumberTable
  #60 = Utf8               LocalVariableTable
  #61 = Utf8               Signature
  #62 = Utf8               MethodParameters
  #63 = Utf8               InnerClasses
  #64 = Utf8               SourceFile
  #65 = Utf8               ScalaInlineInfo
  #66 = Utf8               Scala
{
  public static final shapeless.ops.coproduct$ZipWithIndex$Impl$ MODULE$;
    descriptor: Lshapeless/ops/coproduct$ZipWithIndex$Impl$;
    flags: (0x0019) ACC_PUBLIC, ACC_STATIC, ACC_FINAL

  public static {};
    descriptor: ()V
    flags: (0x0009) ACC_PUBLIC, ACC_STATIC
    Code:
      stack=2, locals=0, args_size=0
         0: new           #2                  // class shapeless/ops/coproduct$ZipWithIndex$Impl$
         3: dup
         4: invokespecial #27                 // Method "<init>":()V
         7: putstatic     #29                 // Field MODULE$:Lshapeless/ops/coproduct$ZipWithIndex$Impl$;
        10: return
      LineNumberTable:
        line 483: 0

  public <C extends shapeless.Coproduct, N extends shapeless.Nat> shapeless.ops.coproduct$ZipWithIndex$Impl<C, N> apply(shapeless.ops.coproduct$ZipWithIndex$Impl<C, N>);
    descriptor: (Lshapeless/ops/coproduct$ZipWithIndex$Impl;)Lshapeless/ops/coproduct$ZipWithIndex$Impl;
    flags: (0x0001) ACC_PUBLIC
    Code:
      stack=1, locals=2, args_size=2
         0: aload_1
         1: areturn
      LineNumberTable:
        line 484: 0
      LocalVariableTable:
        Start  Length  Slot  Name   Signature
            0       2     0  this   Lshapeless/ops/coproduct$ZipWithIndex$Impl$;
            0       2     1  impl   Lshapeless/ops/coproduct$ZipWithIndex$Impl;
    Signature: #32                          // <C::Lshapeless/Coproduct;N::Lshapeless/Nat;>(Lshapeless/ops/coproduct$ZipWithIndex$Impl<TC;TN;>;)Lshapeless/ops/coproduct$ZipWithIndex$Impl<TC;TN;>;
    MethodParameters:
      Name                           Flags
      impl                           final

  public <CH extends java.lang.Object, N extends shapeless.Nat> shapeless.ops.coproduct$ZipWithIndex$Impl<shapeless.$colon$plus$colon<CH, shapeless.CNil>, N> singleZipWithIndexImpl(shapeless.Witness);
    descriptor: (Lshapeless/Witness;)Lshapeless/ops/coproduct$ZipWithIndex$Impl;
    flags: (0x0001) ACC_PUBLIC
    Code:
      stack=3, locals=2, args_size=2
         0: new           #18                 // class shapeless/ops/coproduct$ZipWithIndex$Impl$$anon$30
         3: dup
         4: aload_1
         5: invokespecial #42                 // Method shapeless/ops/coproduct$ZipWithIndex$Impl$$anon$30."<init>":(Lshapeless/Witness;)V
         8: areturn
      LineNumberTable:
        line 489: 0
      LocalVariableTable:
        Start  Length  Slot  Name   Signature
            0       9     0  this   Lshapeless/ops/coproduct$ZipWithIndex$Impl$;
            0       9     1     w   Lshapeless/Witness;
    Signature: #38                          // <CH:Ljava/lang/Object;N::Lshapeless/Nat;>(Lshapeless/Witness;)Lshapeless/ops/coproduct$ZipWithIndex$Impl<Lshapeless/$colon$plus$colon<TCH;Lshapeless/CNil;>;TN;>;
    MethodParameters:
      Name                           Flags
      w                              final

  public <CH extends java.lang.Object, CT extends shapeless.Coproduct, N extends shapeless.Nat, OutC extends shapeless.Coproduct> shapeless.ops.coproduct$ZipWithIndex$Impl<shapeless.$colon$plus$colon<CH, CT>, N> cpZipWithIndexImpl(shapeless.ops.coproduct$ZipWithIndex$Impl<CT, shapeless.Succ<N>>, shapeless.Witness);
    descriptor: (Lshapeless/ops/coproduct$ZipWithIndex$Impl;Lshapeless/Witness;)Lshapeless/ops/coproduct$ZipWithIndex$Impl;
    flags: (0x0001) ACC_PUBLIC
    Code:
      stack=4, locals=3, args_size=3
         0: new           #20                 // class shapeless/ops/coproduct$ZipWithIndex$Impl$$anon$31
         3: dup
         4: aload_2
         5: aload_1
         6: invokespecial #49                 // Method shapeless/ops/coproduct$ZipWithIndex$Impl$$anon$31."<init>":(Lshapeless/Witness;Lshapeless/ops/coproduct$ZipWithIndex$Impl;)V
         9: areturn
      LineNumberTable:
        line 500: 0
      LocalVariableTable:
        Start  Length  Slot  Name   Signature
            0      10     0  this   Lshapeless/ops/coproduct$ZipWithIndex$Impl$;
            0      10     1  impl   Lshapeless/ops/coproduct$ZipWithIndex$Impl;
            0      10     2     w   Lshapeless/Witness;
    Signature: #46                          // <CH:Ljava/lang/Object;CT::Lshapeless/Coproduct;N::Lshapeless/Nat;OutC::Lshapeless/Coproduct;>(Lshapeless/ops/coproduct$ZipWithIndex$Impl<TCT;Lshapeless/Succ<TN;>;>;Lshapeless/Witness;)Lshapeless/ops/coproduct$ZipWithIndex$Impl<Lshapeless/$colon$plus$colon<TCH;TCT;>;TN;>;
    MethodParameters:
      Name                           Flags
      impl                           final
      w                              final

  private java.lang.Object writeReplace();
    descriptor: ()Ljava/lang/Object;
    flags: (0x0002) ACC_PRIVATE
    Code:
      stack=3, locals=1, args_size=1
         0: new           #53                 // class scala/runtime/ModuleSerializationProxy
         3: dup
         4: ldc           #2                  // class shapeless/ops/coproduct$ZipWithIndex$Impl$
         6: invokespecial #56                 // Method scala/runtime/ModuleSerializationProxy."<init>":(Ljava/lang/Class;)V
         9: areturn
      LineNumberTable:
        line 483: 0
      LocalVariableTable:
        Start  Length  Slot  Name   Signature
            0      10     0  this   Lshapeless/ops/coproduct$ZipWithIndex$Impl$;

  public shapeless.ops.coproduct$ZipWithIndex$Impl$();
    descriptor: ()V
    flags: (0x0001) ACC_PUBLIC
    Code:
      stack=1, locals=1, args_size=1
         0: aload_0
         1: invokespecial #57                 // Method java/lang/Object."<init>":()V
         4: return
      LineNumberTable:
        line 510: 0
        line 483: 4
      LocalVariableTable:
        Start  Length  Slot  Name   Signature
            0       5     0  this   Lshapeless/ops/coproduct$ZipWithIndex$Impl$;
}
InnerClasses:
  public static #12= #9 of #11;           // ZipWithIndex$=class shapeless/ops/coproduct$ZipWithIndex$ of class shapeless/ops/coproduct
  public static #15= #14 of #9;           // Impl=class shapeless/ops/coproduct$ZipWithIndex$Impl of class shapeless/ops/coproduct$ZipWithIndex$
  public static #16= #2 of #9;            // Impl$=class shapeless/ops/coproduct$ZipWithIndex$Impl$ of class shapeless/ops/coproduct$ZipWithIndex$
  public final #18;                       // class shapeless/ops/coproduct$ZipWithIndex$Impl$$anon$30
  public final #20;                       // class shapeless/ops/coproduct$ZipWithIndex$Impl$$anon$31
SourceFile: "coproduct.scala"
  ScalaInlineInfo: length = 0x1D (unknown attribute)
   01 01 00 05 00 19 00 18 01 00 1E 00 1F 01 00 2C
   00 2D 01 00 24 00 25 01 00 32 00 33 01
  Scala: length = 0x0 (unknown attribute)

