Classfile /Users/mw/Projects/slang-braindump/.jar/jar8/assemble/slang-braindump/assemble/content/shapeless/ops/coproduct$ExtendBy$$anon$38.class
  Last modified May 29, 2022; size 1641 bytes
  SHA-256 checksum c4ff03709c779d55e1e6dc58368144d82ddd0e22509a8aaaec48c1e10f3c4767
  Compiled from "coproduct.scala"
public final class shapeless.ops.coproduct$ExtendBy$$anon$38 extends java.lang.Object implements shapeless.ops.coproduct$ExtendBy<L, R>
  minor version: 0
  major version: 52
  flags: (0x0031) ACC_PUBLIC, ACC_FINAL, ACC_SUPER
  this_class: #2                          // shapeless/ops/coproduct$ExtendBy$$anon$38
  super_class: #5                         // java/lang/Object
  interfaces: 1, fields: 2, methods: 3, attributes: 6
Constant pool:
   #1 = Utf8               shapeless/ops/coproduct$ExtendBy$$anon$38
   #2 = Class              #1             // shapeless/ops/coproduct$ExtendBy$$anon$38
   #3 = Utf8               Ljava/lang/Object;Lshapeless/ops/coproduct$ExtendBy<TL;TR;>;
   #4 = Utf8               java/lang/Object
   #5 = Class              #4             // java/lang/Object
   #6 = Utf8               shapeless/ops/coproduct$ExtendBy
   #7 = Class              #6             // shapeless/ops/coproduct$ExtendBy
   #8 = Utf8               coproduct.scala
   #9 = Utf8               shapeless/ops/coproduct$ExtendBy$
  #10 = Class              #9             // shapeless/ops/coproduct$ExtendBy$
  #11 = Utf8               extendBy
  #12 = Utf8               (Lshapeless/ops/coproduct$ExtendLeftBy;Lshapeless/ops/coproduct$ExtendRightBy;)Lshapeless/ops/coproduct$ExtendBy;
  #13 = NameAndType        #11:#12        // extendBy:(Lshapeless/ops/coproduct$ExtendLeftBy;Lshapeless/ops/coproduct$ExtendRightBy;)Lshapeless/ops/coproduct$ExtendBy;
  #14 = Utf8               shapeless/ops/coproduct
  #15 = Class              #14            // shapeless/ops/coproduct
  #16 = Utf8               ExtendBy
  #17 = Utf8               ExtendBy$
  #18 = Utf8               shapeless/ops/coproduct$ExtendLeftBy
  #19 = Class              #18            // shapeless/ops/coproduct$ExtendLeftBy
  #20 = Utf8               ExtendLeftBy
  #21 = Utf8               shapeless/ops/coproduct$ExtendRightBy
  #22 = Class              #21            // shapeless/ops/coproduct$ExtendRightBy
  #23 = Utf8               ExtendRightBy
  #24 = Utf8               extendRightBy$1
  #25 = Utf8               Lshapeless/ops/coproduct$ExtendRightBy;
  #26 = Utf8               extendLeftBy$1
  #27 = Utf8               Lshapeless/ops/coproduct$ExtendLeftBy;
  #28 = Utf8               right
  #29 = Utf8               (Lshapeless/Coproduct;)Lshapeless/Coproduct;
  #30 = Utf8               (TL;)TOut0;
  #31 = Utf8               l
  #32 = NameAndType        #24:#25        // extendRightBy$1:Lshapeless/ops/coproduct$ExtendRightBy;
  #33 = Fieldref           #2.#32         // shapeless/ops/coproduct$ExtendBy$$anon$38.extendRightBy$1:Lshapeless/ops/coproduct$ExtendRightBy;
  #34 = Utf8               apply
  #35 = Utf8               (Ljava/lang/Object;)Ljava/lang/Object;
  #36 = NameAndType        #34:#35        // apply:(Ljava/lang/Object;)Ljava/lang/Object;
  #37 = InterfaceMethodref #22.#36        // shapeless/ops/coproduct$ExtendRightBy.apply:(Ljava/lang/Object;)Ljava/lang/Object;
  #38 = Utf8               shapeless/Coproduct
  #39 = Class              #38            // shapeless/Coproduct
  #40 = Utf8               this
  #41 = Utf8               Lshapeless/ops/coproduct$ExtendBy$$anon$38;
  #42 = Utf8               Lshapeless/Coproduct;
  #43 = Utf8               left
  #44 = Utf8               (TR;)TOut0;
  #45 = Utf8               r
  #46 = NameAndType        #26:#27        // extendLeftBy$1:Lshapeless/ops/coproduct$ExtendLeftBy;
  #47 = Fieldref           #2.#46         // shapeless/ops/coproduct$ExtendBy$$anon$38.extendLeftBy$1:Lshapeless/ops/coproduct$ExtendLeftBy;
  #48 = InterfaceMethodref #19.#36        // shapeless/ops/coproduct$ExtendLeftBy.apply:(Ljava/lang/Object;)Ljava/lang/Object;
  #49 = Utf8               <init>
  #50 = Utf8               (Lshapeless/ops/coproduct$ExtendRightBy;Lshapeless/ops/coproduct$ExtendLeftBy;)V
  #51 = Utf8               ()V
  #52 = NameAndType        #49:#51        // "<init>":()V
  #53 = Methodref          #5.#52         // java/lang/Object."<init>":()V
  #54 = Utf8               Code
  #55 = Utf8               LineNumberTable
  #56 = Utf8               LocalVariableTable
  #57 = Utf8               Signature
  #58 = Utf8               MethodParameters
  #59 = Utf8               InnerClasses
  #60 = Utf8               EnclosingMethod
  #61 = Utf8               SourceFile
  #62 = Utf8               ScalaInlineInfo
  #63 = Utf8               Scala
{
  private final shapeless.ops.coproduct$ExtendRightBy extendRightBy$1;
    descriptor: Lshapeless/ops/coproduct$ExtendRightBy;
    flags: (0x0012) ACC_PRIVATE, ACC_FINAL

  private final shapeless.ops.coproduct$ExtendLeftBy extendLeftBy$1;
    descriptor: Lshapeless/ops/coproduct$ExtendLeftBy;
    flags: (0x0012) ACC_PRIVATE, ACC_FINAL

  public Out0 right(L);
    descriptor: (Lshapeless/Coproduct;)Lshapeless/Coproduct;
    flags: (0x0001) ACC_PUBLIC
    Code:
      stack=2, locals=2, args_size=2
         0: aload_0
         1: getfield      #33                 // Field extendRightBy$1:Lshapeless/ops/coproduct$ExtendRightBy;
         4: aload_1
         5: invokeinterface #37,  2           // InterfaceMethod shapeless/ops/coproduct$ExtendRightBy.apply:(Ljava/lang/Object;)Ljava/lang/Object;
        10: checkcast     #39                 // class shapeless/Coproduct
        13: areturn
      LineNumberTable:
        line 620: 0
      LocalVariableTable:
        Start  Length  Slot  Name   Signature
            0      14     0  this   Lshapeless/ops/coproduct$ExtendBy$$anon$38;
            0      14     1     l   Lshapeless/Coproduct;
    Signature: #30                          // (TL;)TOut0;
    MethodParameters:
      Name                           Flags
      l                              final

  public Out0 left(R);
    descriptor: (Lshapeless/Coproduct;)Lshapeless/Coproduct;
    flags: (0x0001) ACC_PUBLIC
    Code:
      stack=2, locals=2, args_size=2
         0: aload_0
         1: getfield      #47                 // Field extendLeftBy$1:Lshapeless/ops/coproduct$ExtendLeftBy;
         4: aload_1
         5: invokeinterface #48,  2           // InterfaceMethod shapeless/ops/coproduct$ExtendLeftBy.apply:(Ljava/lang/Object;)Ljava/lang/Object;
        10: checkcast     #39                 // class shapeless/Coproduct
        13: areturn
      LineNumberTable:
        line 621: 0
      LocalVariableTable:
        Start  Length  Slot  Name   Signature
            0      14     0  this   Lshapeless/ops/coproduct$ExtendBy$$anon$38;
            0      14     1     r   Lshapeless/Coproduct;
    Signature: #44                          // (TR;)TOut0;
    MethodParameters:
      Name                           Flags
      r                              final

  public shapeless.ops.coproduct$ExtendBy$$anon$38(shapeless.ops.coproduct$ExtendRightBy, shapeless.ops.coproduct$ExtendLeftBy);
    descriptor: (Lshapeless/ops/coproduct$ExtendRightBy;Lshapeless/ops/coproduct$ExtendLeftBy;)V
    flags: (0x0001) ACC_PUBLIC
    Code:
      stack=2, locals=3, args_size=3
         0: aload_0
         1: aload_1
         2: putfield      #33                 // Field extendRightBy$1:Lshapeless/ops/coproduct$ExtendRightBy;
         5: aload_0
         6: aload_2
         7: putfield      #47                 // Field extendLeftBy$1:Lshapeless/ops/coproduct$ExtendLeftBy;
        10: aload_0
        11: invokespecial #53                 // Method java/lang/Object."<init>":()V
        14: return
      LineNumberTable:
        line 616: 0
        line 617: 10
      LocalVariableTable:
        Start  Length  Slot  Name   Signature
            0      15     0  this   Lshapeless/ops/coproduct$ExtendBy$$anon$38;
            0      15     1 extendRightBy$1   Lshapeless/ops/coproduct$ExtendRightBy;
            0      15     2 extendLeftBy$1   Lshapeless/ops/coproduct$ExtendLeftBy;
    MethodParameters:
      Name                           Flags
      extendRightBy$1                final
      extendLeftBy$1                 final
}
InnerClasses:
  public static #16= #7 of #15;           // ExtendBy=class shapeless/ops/coproduct$ExtendBy of class shapeless/ops/coproduct
  public static #17= #10 of #15;          // ExtendBy$=class shapeless/ops/coproduct$ExtendBy$ of class shapeless/ops/coproduct
  public final #2;                        // class shapeless/ops/coproduct$ExtendBy$$anon$38
  public static #20= #19 of #15;          // ExtendLeftBy=class shapeless/ops/coproduct$ExtendLeftBy of class shapeless/ops/coproduct
  public static #23= #22 of #15;          // ExtendRightBy=class shapeless/ops/coproduct$ExtendRightBy of class shapeless/ops/coproduct
EnclosingMethod: #10.#13                // shapeless.ops.coproduct$ExtendBy$.extendBy
Signature: #3                           // Ljava/lang/Object;Lshapeless/ops/coproduct$ExtendBy<TL;TR;>;
SourceFile: "coproduct.scala"
  ScalaInlineInfo: length = 0x13 (unknown attribute)
   01 01 00 03 00 31 00 32 01 00 2B 00 1D 01 00 1C
   00 1D 01
  Scala: length = 0x0 (unknown attribute)

