Classfile /Users/mw/Projects/slang-braindump/.jar/jar8/assemble/slang-braindump/assemble/content/shapeless/ops/coproduct$RuntimeInjectLowPrio.class
  Last modified May 29, 2022; size 1620 bytes
  SHA-256 checksum c515fcd12b860c3869087e5c712831bfd67e76c808d5d87b28f2e510ceb176e3
  Compiled from "coproduct.scala"
public interface shapeless.ops.coproduct$RuntimeInjectLowPrio
  minor version: 0
  major version: 52
  flags: (0x0601) ACC_PUBLIC, ACC_INTERFACE, ACC_ABSTRACT
  this_class: #2                          // shapeless/ops/coproduct$RuntimeInjectLowPrio
  super_class: #4                         // java/lang/Object
  interfaces: 0, fields: 0, methods: 3, attributes: 4
Constant pool:
   #1 = Utf8               shapeless/ops/coproduct$RuntimeInjectLowPrio
   #2 = Class              #1             // shapeless/ops/coproduct$RuntimeInjectLowPrio
   #3 = Utf8               java/lang/Object
   #4 = Class              #3             // java/lang/Object
   #5 = Utf8               coproduct.scala
   #6 = Utf8               shapeless/ops/coproduct$RuntimeInject
   #7 = Class              #6             // shapeless/ops/coproduct$RuntimeInject
   #8 = Utf8               shapeless/ops/coproduct
   #9 = Class              #8             // shapeless/ops/coproduct
  #10 = Utf8               RuntimeInject
  #11 = Utf8               RuntimeInjectLowPrio
  #12 = Utf8               shapeless/ops/coproduct$RuntimeInjectLowPrio$$anon$85
  #13 = Class              #12            // shapeless/ops/coproduct$RuntimeInjectLowPrio$$anon$85
  #14 = Utf8               inductiveCaseRuntimeInject$
  #15 = Utf8               (Lshapeless/ops/coproduct$RuntimeInjectLowPrio;Lshapeless/ops/coproduct$RuntimeInject;Lshapeless/Typeable;)Lshapeless/ops/coproduct$RuntimeInject;
  #16 = Utf8               $this
  #17 = Utf8               next
  #18 = Utf8               castH
  #19 = Utf8               inductiveCaseRuntimeInject
  #20 = Utf8               (Lshapeless/ops/coproduct$RuntimeInject;Lshapeless/Typeable;)Lshapeless/ops/coproduct$RuntimeInject;
  #21 = NameAndType        #19:#20        // inductiveCaseRuntimeInject:(Lshapeless/ops/coproduct$RuntimeInject;Lshapeless/Typeable;)Lshapeless/ops/coproduct$RuntimeInject;
  #22 = InterfaceMethodref #2.#21         // shapeless/ops/coproduct$RuntimeInjectLowPrio.inductiveCaseRuntimeInject:(Lshapeless/ops/coproduct$RuntimeInject;Lshapeless/Typeable;)Lshapeless/ops/coproduct$RuntimeInject;
  #23 = Utf8               Lshapeless/ops/coproduct$RuntimeInjectLowPrio;
  #24 = Utf8               Lshapeless/ops/coproduct$RuntimeInject;
  #25 = Utf8               Lshapeless/Typeable;
  #26 = Utf8               <H:Ljava/lang/Object;T::Lshapeless/Coproduct;>(Lshapeless/ops/coproduct$RuntimeInject<TT;>;Lshapeless/Typeable<TH;>;)Lshapeless/ops/coproduct$RuntimeInject<Lshapeless/$colon$plus$colon<TH;TT;>;>;
  #27 = Utf8               <init>
  #28 = Utf8               (Lshapeless/ops/coproduct$RuntimeInjectLowPrio;Lshapeless/Typeable;Lshapeless/ops/coproduct$RuntimeInject;)V
  #29 = NameAndType        #27:#28        // "<init>":(Lshapeless/ops/coproduct$RuntimeInjectLowPrio;Lshapeless/Typeable;Lshapeless/ops/coproduct$RuntimeInject;)V
  #30 = Methodref          #13.#29        // shapeless/ops/coproduct$RuntimeInjectLowPrio$$anon$85."<init>":(Lshapeless/ops/coproduct$RuntimeInjectLowPrio;Lshapeless/Typeable;Lshapeless/ops/coproduct$RuntimeInject;)V
  #31 = Utf8               this
  #32 = Utf8               $init$
  #33 = Utf8               (Lshapeless/ops/coproduct$RuntimeInjectLowPrio;)V
  #34 = Utf8               Code
  #35 = Utf8               LineNumberTable
  #36 = Utf8               LocalVariableTable
  #37 = Utf8               MethodParameters
  #38 = Utf8               Signature
  #39 = Utf8               InnerClasses
  #40 = Utf8               SourceFile
  #41 = Utf8               ScalaInlineInfo
  #42 = Utf8               Scala
{
  public static shapeless.ops.coproduct$RuntimeInject inductiveCaseRuntimeInject$(shapeless.ops.coproduct$RuntimeInjectLowPrio, shapeless.ops.coproduct$RuntimeInject, shapeless.Typeable);
    descriptor: (Lshapeless/ops/coproduct$RuntimeInjectLowPrio;Lshapeless/ops/coproduct$RuntimeInject;Lshapeless/Typeable;)Lshapeless/ops/coproduct$RuntimeInject;
    flags: (0x1009) ACC_PUBLIC, ACC_STATIC, ACC_SYNTHETIC
    Code:
      stack=3, locals=3, args_size=3
         0: aload_0
         1: aload_1
         2: aload_2
         3: invokespecial #22                 // InterfaceMethod inductiveCaseRuntimeInject:(Lshapeless/ops/coproduct$RuntimeInject;Lshapeless/Typeable;)Lshapeless/ops/coproduct$RuntimeInject;
         6: areturn
      LineNumberTable:
        line 1366: 0
      LocalVariableTable:
        Start  Length  Slot  Name   Signature
            0       7     0 $this   Lshapeless/ops/coproduct$RuntimeInjectLowPrio;
            0       7     1  next   Lshapeless/ops/coproduct$RuntimeInject;
            0       7     2 castH   Lshapeless/Typeable;
    MethodParameters:
      Name                           Flags
      $this                          final synthetic
      next                           final
      castH                          final

  public default <H extends java.lang.Object, T extends shapeless.Coproduct> shapeless.ops.coproduct$RuntimeInject<shapeless.$colon$plus$colon<H, T>> inductiveCaseRuntimeInject(shapeless.ops.coproduct$RuntimeInject<T>, shapeless.Typeable<H>);
    descriptor: (Lshapeless/ops/coproduct$RuntimeInject;Lshapeless/Typeable;)Lshapeless/ops/coproduct$RuntimeInject;
    flags: (0x0001) ACC_PUBLIC
    Code:
      stack=5, locals=3, args_size=3
         0: new           #13                 // class shapeless/ops/coproduct$RuntimeInjectLowPrio$$anon$85
         3: dup
         4: aconst_null
         5: aload_2
         6: aload_1
         7: invokespecial #30                 // Method shapeless/ops/coproduct$RuntimeInjectLowPrio$$anon$85."<init>":(Lshapeless/ops/coproduct$RuntimeInjectLowPrio;Lshapeless/Typeable;Lshapeless/ops/coproduct$RuntimeInject;)V
        10: areturn
      LineNumberTable:
        line 1369: 0
      LocalVariableTable:
        Start  Length  Slot  Name   Signature
            0      11     0  this   Lshapeless/ops/coproduct$RuntimeInjectLowPrio;
            0      11     1  next   Lshapeless/ops/coproduct$RuntimeInject;
            0      11     2 castH   Lshapeless/Typeable;
    Signature: #26                          // <H:Ljava/lang/Object;T::Lshapeless/Coproduct;>(Lshapeless/ops/coproduct$RuntimeInject<TT;>;Lshapeless/Typeable<TH;>;)Lshapeless/ops/coproduct$RuntimeInject<Lshapeless/$colon$plus$colon<TH;TT;>;>;
    MethodParameters:
      Name                           Flags
      next                           final
      castH                          final

  public static void $init$(shapeless.ops.coproduct$RuntimeInjectLowPrio);
    descriptor: (Lshapeless/ops/coproduct$RuntimeInjectLowPrio;)V
    flags: (0x0009) ACC_PUBLIC, ACC_STATIC
    Code:
      stack=0, locals=1, args_size=1
         0: return
      LineNumberTable:
        line 1365: 0
      LocalVariableTable:
        Start  Length  Slot  Name   Signature
            0       1     0 $this   Lshapeless/ops/coproduct$RuntimeInjectLowPrio;
    MethodParameters:
      Name                           Flags
      $this                          final synthetic
}
InnerClasses:
  public static #10= #7 of #9;            // RuntimeInject=class shapeless/ops/coproduct$RuntimeInject of class shapeless/ops/coproduct
  public static #11= #2 of #9;            // RuntimeInjectLowPrio=class shapeless/ops/coproduct$RuntimeInjectLowPrio of class shapeless/ops/coproduct
  public final #13;                       // class shapeless/ops/coproduct$RuntimeInjectLowPrio$$anon$85
SourceFile: "coproduct.scala"
  ScalaInlineInfo: length = 0x13 (unknown attribute)
   01 00 00 03 00 20 00 21 01 00 0E 00 0F 01 00 13
   00 14 00
  Scala: length = 0x0 (unknown attribute)

