Classfile /Users/mw/Projects/slang-braindump/.jar/jar8/assemble/slang-braindump/assemble/content/shapeless/ops/coproduct$LowPriorityRotateLeft$$anon$48.class
  Last modified May 29, 2022; size 1936 bytes
  SHA-256 checksum 19561333dc0bccaf6d46db9b03d386fbf6de3f81a9b77793c3dbd55c97351e6e
  Compiled from "coproduct.scala"
public final class shapeless.ops.coproduct$LowPriorityRotateLeft$$anon$48 extends java.lang.Object implements shapeless.ops.coproduct$RotateLeft<C, N>
  minor version: 0
  major version: 52
  flags: (0x0031) ACC_PUBLIC, ACC_FINAL, ACC_SUPER
  this_class: #2                          // shapeless/ops/coproduct$LowPriorityRotateLeft$$anon$48
  super_class: #5                         // java/lang/Object
  interfaces: 1, fields: 2, methods: 3, attributes: 6
Constant pool:
   #1 = Utf8               shapeless/ops/coproduct$LowPriorityRotateLeft$$anon$48
   #2 = Class              #1             // shapeless/ops/coproduct$LowPriorityRotateLeft$$anon$48
   #3 = Utf8               Ljava/lang/Object;Lshapeless/ops/coproduct$RotateLeft<TC;TN;>;
   #4 = Utf8               java/lang/Object
   #5 = Class              #4             // java/lang/Object
   #6 = Utf8               shapeless/ops/coproduct$RotateLeft
   #7 = Class              #6             // shapeless/ops/coproduct$RotateLeft
   #8 = Utf8               coproduct.scala
   #9 = Utf8               shapeless/ops/coproduct$LowPriorityRotateLeft
  #10 = Class              #9             // shapeless/ops/coproduct$LowPriorityRotateLeft
  #11 = Utf8               coproductRotateLeft
  #12 = Utf8               (Lshapeless/ops/coproduct$Length;Lshapeless/ops/nat$Mod;Lshapeless/ops/coproduct$Split;Lshapeless/ops/coproduct$Prepend;)Lshapeless/ops/coproduct$RotateLeft;
  #13 = NameAndType        #11:#12        // coproductRotateLeft:(Lshapeless/ops/coproduct$Length;Lshapeless/ops/nat$Mod;Lshapeless/ops/coproduct$Split;Lshapeless/ops/coproduct$Prepend;)Lshapeless/ops/coproduct$RotateLeft;
  #14 = Utf8               shapeless/ops/coproduct
  #15 = Class              #14            // shapeless/ops/coproduct
  #16 = Utf8               LowPriorityRotateLeft
  #17 = Utf8               shapeless/ops/coproduct$Prepend
  #18 = Class              #17            // shapeless/ops/coproduct$Prepend
  #19 = Utf8               Prepend
  #20 = Utf8               RotateLeft
  #21 = Utf8               shapeless/ops/coproduct$Split
  #22 = Class              #21            // shapeless/ops/coproduct$Split
  #23 = Utf8               Split
  #24 = Utf8               split$1
  #25 = Utf8               Lshapeless/ops/coproduct$Split;
  #26 = Utf8               prepend$1
  #27 = Utf8               Lshapeless/ops/coproduct$Prepend;
  #28 = Utf8               apply
  #29 = Utf8               (Lshapeless/Coproduct;)Lshapeless/Coproduct;
  #30 = Utf8               (TC;)Lshapeless/Coproduct;
  #31 = Utf8               c
  #32 = NameAndType        #24:#25        // split$1:Lshapeless/ops/coproduct$Split;
  #33 = Fieldref           #2.#32         // shapeless/ops/coproduct$LowPriorityRotateLeft$$anon$48.split$1:Lshapeless/ops/coproduct$Split;
  #34 = Utf8               (Ljava/lang/Object;)Ljava/lang/Object;
  #35 = NameAndType        #28:#34        // apply:(Ljava/lang/Object;)Ljava/lang/Object;
  #36 = InterfaceMethodref #22.#35        // shapeless/ops/coproduct$Split.apply:(Ljava/lang/Object;)Ljava/lang/Object;
  #37 = Utf8               scala/util/Either
  #38 = Class              #37            // scala/util/Either
  #39 = NameAndType        #26:#27        // prepend$1:Lshapeless/ops/coproduct$Prepend;
  #40 = Fieldref           #2.#39         // shapeless/ops/coproduct$LowPriorityRotateLeft$$anon$48.prepend$1:Lshapeless/ops/coproduct$Prepend;
  #41 = Utf8               swap
  #42 = Utf8               ()Lscala/util/Either;
  #43 = NameAndType        #41:#42        // swap:()Lscala/util/Either;
  #44 = Methodref          #38.#43        // scala/util/Either.swap:()Lscala/util/Either;
  #45 = InterfaceMethodref #18.#35        // shapeless/ops/coproduct$Prepend.apply:(Ljava/lang/Object;)Ljava/lang/Object;
  #46 = Utf8               shapeless/Coproduct
  #47 = Class              #46            // shapeless/Coproduct
  #48 = Utf8               e
  #49 = Utf8               Lscala/util/Either;
  #50 = Utf8               this
  #51 = Utf8               Lshapeless/ops/coproduct$LowPriorityRotateLeft$$anon$48;
  #52 = Utf8               Lshapeless/Coproduct;
  #53 = Utf8               t
  #54 = NameAndType        #28:#29        // apply:(Lshapeless/Coproduct;)Lshapeless/Coproduct;
  #55 = Methodref          #2.#54         // shapeless/ops/coproduct$LowPriorityRotateLeft$$anon$48.apply:(Lshapeless/Coproduct;)Lshapeless/Coproduct;
  #56 = Utf8               Ljava/lang/Object;
  #57 = Utf8               <init>
  #58 = Utf8               (Lshapeless/ops/coproduct$LowPriorityRotateLeft;Lshapeless/ops/coproduct$Split;Lshapeless/ops/coproduct$Prepend;)V
  #59 = Utf8               $outer
  #60 = Utf8               ()V
  #61 = NameAndType        #57:#60        // "<init>":()V
  #62 = Methodref          #5.#61         // java/lang/Object."<init>":()V
  #63 = Utf8               Lshapeless/ops/coproduct$LowPriorityRotateLeft;
  #64 = Utf8               Code
  #65 = Utf8               LineNumberTable
  #66 = Utf8               LocalVariableTable
  #67 = Utf8               Signature
  #68 = Utf8               MethodParameters
  #69 = Utf8               InnerClasses
  #70 = Utf8               EnclosingMethod
  #71 = Utf8               SourceFile
  #72 = Utf8               ScalaInlineInfo
  #73 = Utf8               Scala
{
  private final shapeless.ops.coproduct$Split split$1;
    descriptor: Lshapeless/ops/coproduct$Split;
    flags: (0x0012) ACC_PRIVATE, ACC_FINAL

  private final shapeless.ops.coproduct$Prepend prepend$1;
    descriptor: Lshapeless/ops/coproduct$Prepend;
    flags: (0x0012) ACC_PRIVATE, ACC_FINAL

  public shapeless.Coproduct apply(C);
    descriptor: (Lshapeless/Coproduct;)Lshapeless/Coproduct;
    flags: (0x0001) ACC_PUBLIC
    Code:
      stack=2, locals=3, args_size=2
         0: aload_0
         1: getfield      #33                 // Field split$1:Lshapeless/ops/coproduct$Split;
         4: aload_1
         5: invokeinterface #36,  2           // InterfaceMethod shapeless/ops/coproduct$Split.apply:(Ljava/lang/Object;)Ljava/lang/Object;
        10: checkcast     #38                 // class scala/util/Either
        13: astore_2
        14: aload_0
        15: getfield      #40                 // Field prepend$1:Lshapeless/ops/coproduct$Prepend;
        18: aload_2
        19: invokevirtual #44                 // Method scala/util/Either.swap:()Lscala/util/Either;
        22: invokeinterface #45,  2           // InterfaceMethod shapeless/ops/coproduct$Prepend.apply:(Ljava/lang/Object;)Ljava/lang/Object;
        27: checkcast     #47                 // class shapeless/Coproduct
        30: areturn
      LineNumberTable:
        line 755: 0
        line 757: 14
      LocalVariableTable:
        Start  Length  Slot  Name   Signature
           13      17     2     e   Lscala/util/Either;
            0      31     0  this   Lshapeless/ops/coproduct$LowPriorityRotateLeft$$anon$48;
            0      31     1     c   Lshapeless/Coproduct;
    Signature: #30                          // (TC;)Lshapeless/Coproduct;
    MethodParameters:
      Name                           Flags
      c                              final

  public java.lang.Object apply(java.lang.Object);
    descriptor: (Ljava/lang/Object;)Ljava/lang/Object;
    flags: (0x1041) ACC_PUBLIC, ACC_BRIDGE, ACC_SYNTHETIC
    Code:
      stack=2, locals=2, args_size=2
         0: aload_0
         1: aload_1
         2: checkcast     #47                 // class shapeless/Coproduct
         5: invokevirtual #55                 // Method apply:(Lshapeless/Coproduct;)Lshapeless/Coproduct;
         8: areturn
      LineNumberTable:
        line 751: 0
      LocalVariableTable:
        Start  Length  Slot  Name   Signature
            0       9     0  this   Lshapeless/ops/coproduct$LowPriorityRotateLeft$$anon$48;
            0       9     1     t   Ljava/lang/Object;
    MethodParameters:
      Name                           Flags
      t                              final

  public shapeless.ops.coproduct$LowPriorityRotateLeft$$anon$48(shapeless.ops.coproduct$LowPriorityRotateLeft, shapeless.ops.coproduct$Split, shapeless.ops.coproduct$Prepend);
    descriptor: (Lshapeless/ops/coproduct$LowPriorityRotateLeft;Lshapeless/ops/coproduct$Split;Lshapeless/ops/coproduct$Prepend;)V
    flags: (0x0001) ACC_PUBLIC
    Code:
      stack=2, locals=4, args_size=4
         0: aload_0
         1: aload_2
         2: putfield      #33                 // Field split$1:Lshapeless/ops/coproduct$Split;
         5: aload_0
         6: aload_3
         7: putfield      #40                 // Field prepend$1:Lshapeless/ops/coproduct$Prepend;
        10: aload_0
        11: invokespecial #62                 // Method java/lang/Object."<init>":()V
        14: return
      LineNumberTable:
        line 749: 0
        line 750: 5
        line 751: 10
      LocalVariableTable:
        Start  Length  Slot  Name   Signature
            0      15     0  this   Lshapeless/ops/coproduct$LowPriorityRotateLeft$$anon$48;
            0      15     1 $outer   Lshapeless/ops/coproduct$LowPriorityRotateLeft;
            0      15     2 split$1   Lshapeless/ops/coproduct$Split;
            0      15     3 prepend$1   Lshapeless/ops/coproduct$Prepend;
    MethodParameters:
      Name                           Flags
      $outer                         final synthetic
      split$1                        final
      prepend$1                      final
}
InnerClasses:
  public static #16= #10 of #15;          // LowPriorityRotateLeft=class shapeless/ops/coproduct$LowPriorityRotateLeft of class shapeless/ops/coproduct
  public final #2;                        // class shapeless/ops/coproduct$LowPriorityRotateLeft$$anon$48
  public static #19= #18 of #15;          // Prepend=class shapeless/ops/coproduct$Prepend of class shapeless/ops/coproduct
  public static #20= #7 of #15;           // RotateLeft=class shapeless/ops/coproduct$RotateLeft of class shapeless/ops/coproduct
  public static #23= #22 of #15;          // Split=class shapeless/ops/coproduct$Split of class shapeless/ops/coproduct
EnclosingMethod: #10.#13                // shapeless.ops.coproduct$LowPriorityRotateLeft.coproductRotateLeft
Signature: #3                           // Ljava/lang/Object;Lshapeless/ops/coproduct$RotateLeft<TC;TN;>;
SourceFile: "coproduct.scala"
  ScalaInlineInfo: length = 0x13 (unknown attribute)
   01 01 00 03 00 39 00 3A 01 00 1C 00 22 01 00 1C
   00 1D 01
  Scala: length = 0x0 (unknown attribute)

