Classfile /Users/mw/Projects/slang-braindump/.jar/jar8/assemble/slang-braindump/assemble/content/shapeless/ops/coproduct$Folder$.class
  Last modified May 29, 2022; size 2296 bytes
  SHA-256 checksum acc9d66a14faa38ea5078add35d630d6dc79e0a945b850ddca185285266f4a05
  Compiled from "coproduct.scala"
public class shapeless.ops.coproduct$Folder$ implements java.io.Serializable
  minor version: 0
  major version: 52
  flags: (0x0021) ACC_PUBLIC, ACC_SUPER
  this_class: #2                          // shapeless/ops/coproduct$Folder$
  super_class: #4                         // java/lang/Object
  interfaces: 1, fields: 1, methods: 6, attributes: 4
Constant pool:
   #1 = Utf8               shapeless/ops/coproduct$Folder$
   #2 = Class              #1             // shapeless/ops/coproduct$Folder$
   #3 = Utf8               java/lang/Object
   #4 = Class              #3             // java/lang/Object
   #5 = Utf8               java/io/Serializable
   #6 = Class              #5             // java/io/Serializable
   #7 = Utf8               coproduct.scala
   #8 = Utf8               shapeless/ops/coproduct$Folder
   #9 = Class              #8             // shapeless/ops/coproduct$Folder
  #10 = Utf8               shapeless/ops/coproduct
  #11 = Class              #10            // shapeless/ops/coproduct
  #12 = Utf8               Folder
  #13 = Utf8               Folder$
  #14 = Utf8               shapeless/ops/coproduct$Folder$$anon$22
  #15 = Class              #14            // shapeless/ops/coproduct$Folder$$anon$22
  #16 = Utf8               shapeless/ops/coproduct$Mapper
  #17 = Class              #16            // shapeless/ops/coproduct$Mapper
  #18 = Utf8               Mapper
  #19 = Utf8               shapeless/ops/coproduct$Unifier
  #20 = Class              #19            // shapeless/ops/coproduct$Unifier
  #21 = Utf8               Unifier
  #22 = Utf8               MODULE$
  #23 = Utf8               Lshapeless/ops/coproduct$Folder$;
  #24 = Utf8               <clinit>
  #25 = Utf8               ()V
  #26 = Utf8               <init>
  #27 = NameAndType        #26:#25        // "<init>":()V
  #28 = Methodref          #2.#27         // shapeless/ops/coproduct$Folder$."<init>":()V
  #29 = NameAndType        #22:#23        // MODULE$:Lshapeless/ops/coproduct$Folder$;
  #30 = Fieldref           #2.#29         // shapeless/ops/coproduct$Folder$.MODULE$:Lshapeless/ops/coproduct$Folder$;
  #31 = Utf8               apply
  #32 = Utf8               (Lshapeless/ops/coproduct$Folder;)Lshapeless/ops/coproduct$Folder;
  #33 = Utf8               <F::Lshapeless/Poly;C::Lshapeless/Coproduct;>(Lshapeless/ops/coproduct$Folder<TF;TC;>;)Lshapeless/ops/coproduct$Folder<TF;TC;>;
  #34 = Utf8               folder
  #35 = Utf8               this
  #36 = Utf8               Lshapeless/ops/coproduct$Folder;
  #37 = Utf8               (Lshapeless/Poly;Lshapeless/ops/coproduct$Folder;)Lshapeless/ops/coproduct$Folder;
  #38 = Utf8               <C::Lshapeless/Coproduct;>(Lshapeless/Poly;Lshapeless/ops/coproduct$Folder<+Lshapeless/Poly;TC;>;)Lshapeless/ops/coproduct$Folder<Lshapeless/Poly;TC;>;
  #39 = Utf8               f
  #40 = Utf8               Lshapeless/Poly;
  #41 = Utf8               mkFolder
  #42 = Utf8               (Lshapeless/ops/coproduct$Mapper;Lshapeless/ops/coproduct$Unifier;)Lshapeless/ops/coproduct$Folder;
  #43 = Utf8               <F::Lshapeless/Poly;C::Lshapeless/Coproduct;M::Lshapeless/Coproduct;Out0:Ljava/lang/Object;>(Lshapeless/ops/coproduct$Mapper<TF;TC;>;Lshapeless/ops/coproduct$Unifier<TM;>;)Lshapeless/ops/coproduct$Folder<TF;TC;>;
  #44 = Utf8               mapper
  #45 = Utf8               unifier
  #46 = Utf8               (Lshapeless/ops/coproduct$Unifier;Lshapeless/ops/coproduct$Mapper;)V
  #47 = NameAndType        #26:#46        // "<init>":(Lshapeless/ops/coproduct$Unifier;Lshapeless/ops/coproduct$Mapper;)V
  #48 = Methodref          #15.#47        // shapeless/ops/coproduct$Folder$$anon$22."<init>":(Lshapeless/ops/coproduct$Unifier;Lshapeless/ops/coproduct$Mapper;)V
  #49 = Utf8               Lshapeless/ops/coproduct$Mapper;
  #50 = Utf8               Lshapeless/ops/coproduct$Unifier;
  #51 = Utf8               writeReplace
  #52 = Utf8               ()Ljava/lang/Object;
  #53 = Utf8               scala/runtime/ModuleSerializationProxy
  #54 = Class              #53            // scala/runtime/ModuleSerializationProxy
  #55 = Utf8               (Ljava/lang/Class;)V
  #56 = NameAndType        #26:#55        // "<init>":(Ljava/lang/Class;)V
  #57 = Methodref          #54.#56        // scala/runtime/ModuleSerializationProxy."<init>":(Ljava/lang/Class;)V
  #58 = Methodref          #4.#27         // java/lang/Object."<init>":()V
  #59 = Utf8               Code
  #60 = Utf8               LineNumberTable
  #61 = Utf8               LocalVariableTable
  #62 = Utf8               Signature
  #63 = Utf8               MethodParameters
  #64 = Utf8               InnerClasses
  #65 = Utf8               SourceFile
  #66 = Utf8               ScalaInlineInfo
  #67 = Utf8               Scala
{
  public static final shapeless.ops.coproduct$Folder$ MODULE$;
    descriptor: Lshapeless/ops/coproduct$Folder$;
    flags: (0x0019) ACC_PUBLIC, ACC_STATIC, ACC_FINAL

  public static {};
    descriptor: ()V
    flags: (0x0009) ACC_PUBLIC, ACC_STATIC
    Code:
      stack=2, locals=0, args_size=0
         0: new           #2                  // class shapeless/ops/coproduct$Folder$
         3: dup
         4: invokespecial #28                 // Method "<init>":()V
         7: putstatic     #30                 // Field MODULE$:Lshapeless/ops/coproduct$Folder$;
        10: return
      LineNumberTable:
        line 364: 0

  public <F extends shapeless.Poly, C extends shapeless.Coproduct> shapeless.ops.coproduct$Folder<F, C> apply(shapeless.ops.coproduct$Folder<F, C>);
    descriptor: (Lshapeless/ops/coproduct$Folder;)Lshapeless/ops/coproduct$Folder;
    flags: (0x0001) ACC_PUBLIC
    Code:
      stack=1, locals=2, args_size=2
         0: aload_1
         1: areturn
      LineNumberTable:
        line 365: 0
      LocalVariableTable:
        Start  Length  Slot  Name   Signature
            0       2     0  this   Lshapeless/ops/coproduct$Folder$;
            0       2     1 folder   Lshapeless/ops/coproduct$Folder;
    Signature: #33                          // <F::Lshapeless/Poly;C::Lshapeless/Coproduct;>(Lshapeless/ops/coproduct$Folder<TF;TC;>;)Lshapeless/ops/coproduct$Folder<TF;TC;>;
    MethodParameters:
      Name                           Flags
      folder                         final

  public <C extends shapeless.Coproduct> shapeless.ops.coproduct$Folder<shapeless.Poly, C> apply(shapeless.Poly, shapeless.ops.coproduct$Folder<? extends shapeless.Poly, C>);
    descriptor: (Lshapeless/Poly;Lshapeless/ops/coproduct$Folder;)Lshapeless/ops/coproduct$Folder;
    flags: (0x0001) ACC_PUBLIC
    Code:
      stack=1, locals=4, args_size=3
         0: aload_2
         1: astore_3
         2: aload_3
         3: areturn
      LineNumberTable:
        line 366: 0
      LocalVariableTable:
        Start  Length  Slot  Name   Signature
            0       4     0  this   Lshapeless/ops/coproduct$Folder$;
            0       4     1     f   Lshapeless/Poly;
            0       4     2 folder   Lshapeless/ops/coproduct$Folder;
    Signature: #38                          // <C::Lshapeless/Coproduct;>(Lshapeless/Poly;Lshapeless/ops/coproduct$Folder<+Lshapeless/Poly;TC;>;)Lshapeless/ops/coproduct$Folder<Lshapeless/Poly;TC;>;
    MethodParameters:
      Name                           Flags
      f                              final
      folder                         final

  public <F extends shapeless.Poly, C extends shapeless.Coproduct, M extends shapeless.Coproduct, Out0 extends java.lang.Object> shapeless.ops.coproduct$Folder<F, C> mkFolder(shapeless.ops.coproduct$Mapper<F, C>, shapeless.ops.coproduct$Unifier<M>);
    descriptor: (Lshapeless/ops/coproduct$Mapper;Lshapeless/ops/coproduct$Unifier;)Lshapeless/ops/coproduct$Folder;
    flags: (0x0001) ACC_PUBLIC
    Code:
      stack=4, locals=3, args_size=3
         0: new           #15                 // class shapeless/ops/coproduct$Folder$$anon$22
         3: dup
         4: aload_2
         5: aload_1
         6: invokespecial #48                 // Method shapeless/ops/coproduct$Folder$$anon$22."<init>":(Lshapeless/ops/coproduct$Unifier;Lshapeless/ops/coproduct$Mapper;)V
         9: areturn
      LineNumberTable:
        line 372: 0
      LocalVariableTable:
        Start  Length  Slot  Name   Signature
            0      10     0  this   Lshapeless/ops/coproduct$Folder$;
            0      10     1 mapper   Lshapeless/ops/coproduct$Mapper;
            0      10     2 unifier   Lshapeless/ops/coproduct$Unifier;
    Signature: #43                          // <F::Lshapeless/Poly;C::Lshapeless/Coproduct;M::Lshapeless/Coproduct;Out0:Ljava/lang/Object;>(Lshapeless/ops/coproduct$Mapper<TF;TC;>;Lshapeless/ops/coproduct$Unifier<TM;>;)Lshapeless/ops/coproduct$Folder<TF;TC;>;
    MethodParameters:
      Name                           Flags
      mapper                         final
      unifier                        final

  private java.lang.Object writeReplace();
    descriptor: ()Ljava/lang/Object;
    flags: (0x0002) ACC_PRIVATE
    Code:
      stack=3, locals=1, args_size=1
         0: new           #54                 // class scala/runtime/ModuleSerializationProxy
         3: dup
         4: ldc           #2                  // class shapeless/ops/coproduct$Folder$
         6: invokespecial #57                 // Method scala/runtime/ModuleSerializationProxy."<init>":(Ljava/lang/Class;)V
         9: areturn
      LineNumberTable:
        line 364: 0
      LocalVariableTable:
        Start  Length  Slot  Name   Signature
            0      10     0  this   Lshapeless/ops/coproduct$Folder$;

  public shapeless.ops.coproduct$Folder$();
    descriptor: ()V
    flags: (0x0001) ACC_PUBLIC
    Code:
      stack=1, locals=1, args_size=1
         0: aload_0
         1: invokespecial #58                 // Method java/lang/Object."<init>":()V
         4: return
      LineNumberTable:
        line 378: 0
        line 364: 4
      LocalVariableTable:
        Start  Length  Slot  Name   Signature
            0       5     0  this   Lshapeless/ops/coproduct$Folder$;
}
InnerClasses:
  public static #12= #9 of #11;           // Folder=class shapeless/ops/coproduct$Folder of class shapeless/ops/coproduct
  public static #13= #2 of #11;           // Folder$=class shapeless/ops/coproduct$Folder$ of class shapeless/ops/coproduct
  public final #15;                       // class shapeless/ops/coproduct$Folder$$anon$22
  public static #18= #17 of #11;          // Mapper=class shapeless/ops/coproduct$Mapper of class shapeless/ops/coproduct
  public static #21= #20 of #11;          // Unifier=class shapeless/ops/coproduct$Unifier of class shapeless/ops/coproduct
SourceFile: "coproduct.scala"
  ScalaInlineInfo: length = 0x1D (unknown attribute)
   01 01 00 05 00 1A 00 19 01 00 1F 00 25 01 00 1F
   00 20 01 00 29 00 2A 01 00 33 00 34 01
  Scala: length = 0x0 (unknown attribute)

